{
  "type": "Feature",
  "properties": {
    "iso:country":"GB",
    "sg:address":"Glendronach, Forgue",
    "sg:city":"Huntly",
    "sg:classifiers":[
        {
            "category":"Distillery",
            "subcategory":"None",
            "type":"Food & Drink"
        }
    ],
    "sg:postcode":"AB54 6DB",
    "sg:province":"Aberdeenshire",
    "wof:name":"Glendronach Distillery Co. Ltd.",
    "wof:placetype":"venue"
},
  "geometry": {"coordinates":[-2.651031,57.493866],"type":"Point"}
}