{
  "type": "Feature",
  "properties": {
    "addr:full":"130 Hilton Lane, Prestwich Manchester Greater Manchester M25 9QX",
    "addr:housenumber":"130",
    "addr:postcode":"m25 9qx",
    "addr:street":"Hilton Lane",
    "iso:country":"GB",
    "sg:address":"130 Hilton Lane, Prestwich",
    "sg:city":"Manchester",
    "sg:classifiers":[
        {
            "category":"Farming",
            "subcategory":"Nursery",
            "type":"Manufacturing & Wholesale Goods"
        },
        {
            "category":"Education",
            "subcategory":"Preschool",
            "type":"Public Place"
        }
    ],
    "sg:phone":"+44 161 773 4703",
    "sg:postcode":"M25 9QX",
    "sg:province":"Greater Manchester",
    "sg:tags":[
        "school",
        "creche"
    ],
    "wof:name":"Rookwood Private Nursery School",
    "wof:placetype":"venue"
},
  "geometry": {"coordinates":[-2.2792770863,53.5213279724],"type":"Point"}
}