{
  "type": "Feature",
  "properties": {
    "addr:full":"48 Hanbury Road Bargoed Caerphilly CF81 8QW",
    "addr:housenumber":"48",
    "addr:postcode":"cf81 8qw",
    "addr:street":"Hanbury Road",
    "iso:country":"GB",
    "sg:address":"48 Hanbury Road",
    "sg:city":"Bargoed",
    "sg:classifiers":[
        {
            "category":"Professional",
            "subcategory":"Lawyer & Legal Services",
            "type":"Services"
        }
    ],
    "sg:phone":"+44 1443 838368",
    "sg:postcode":"CF81 8QW",
    "sg:province":"Caerphilly",
    "sg:tags":[
        "solicitor"
    ],
    "wof:name":"Charles Crookes & Jones",
    "wof:placetype":"venue"
},
  "geometry": {"coordinates":[-3.2292129993,51.6894264221],"type":"Point"}
}