{
  "type": "Feature",
  "properties": {
    "addr:full":"138 Christchurch Road Ringwood Dorset BH24 3AP",
    "addr:housenumber":"138",
    "addr:postcode":"bh24 3ap",
    "addr:street":"Christchurch Road",
    "iso:country":"GB",
    "sg:address":"138 Christchurch Road",
    "sg:city":"Ringwood",
    "sg:classifiers":[
        {
            "category":"Brewery",
            "type":"Food & Drink"
        }
    ],
    "sg:phone":"+44 1425 471177",
    "sg:postcode":"BH24 3AP",
    "sg:province":"Dorset",
    "sg:tags":[
        "brewer"
    ],
    "wof:name":"Ringwood Brewery Ltd.",
    "wof:placetype":"venue"
},
  "geometry": {"coordinates":[-1.7867,50.840546],"type":"Point"}
}