{
  "type": "Feature",
  "properties": {
    "addr:full":"6 Baird Close, Stephenson Washington Tyne and Wear NE37 3HL",
    "addr:housenumber":"6",
    "addr:postcode":"ne37 3hl",
    "addr:street":"Baird Close",
    "iso:country":"GB",
    "sg:address":"6 Baird Close, Stephenson",
    "sg:city":"Washington",
    "sg:classifiers":[
        {
            "category":"Communications",
            "type":"Services"
        }
    ],
    "sg:phone":"+44 191 417 7266",
    "sg:postcode":"NE37 3HL",
    "sg:province":"Tyne and Wear",
    "sg:tags":[
        "audio-visual"
    ],
    "wof:name":"Hi-Tech Video & Design Ltd.",
    "wof:placetype":"venue"
},
  "geometry": {"coordinates":[-1.5133140087,54.9215011597],"type":"Point"}
}