{
  "type": "Feature",
  "properties": {
    "addr:full":"6 Edburton Gardens Shoreham By Sea West Sussex BN43 5GR",
    "addr:housenumber":"6",
    "addr:postcode":"bn43 5gr",
    "addr:street":"Edburton Gardens",
    "iso:country":"GB",
    "sg:address":"6 Edburton Gardens",
    "sg:city":"Shoreham By Sea",
    "sg:classifiers":[
        {
            "category":"Banks & Credit Unions",
            "subcategory":"Bank",
            "type":"Services"
        }
    ],
    "sg:phone":"+44 1273 455800",
    "sg:postcode":"BN43 5GR",
    "sg:province":"West Sussex",
    "sg:tags":[
        "stocktaking",
        "inventory"
    ],
    "wof:name":"Ashley Denman & Co",
    "wof:placetype":"venue"
},
  "geometry": {"coordinates":[-0.2718870044,50.8437194824],"type":"Point"}
}