{
  "type": "Feature",
  "properties": {
    "addr:full":"Unit 1 Saxon Way Birmingham West Midlands B37 5AY",
    "addr:housenumber":"unit 1",
    "addr:postcode":"b37 5ay",
    "addr:street":"Saxon Way",
    "iso:country":"GB",
    "sg:address":"Unit 1 Saxon Way",
    "sg:city":"Birmingham",
    "sg:classifiers":[
        {
            "category":"Professional",
            "subcategory":"Art Services",
            "type":"Services"
        }
    ],
    "sg:phone":"+44 121 770 5201",
    "sg:postcode":"B37 5AY",
    "sg:province":"West Midlands",
    "sg:tags":[
        "framing"
    ],
    "wof:name":"Pictures & Frames Of Birmingham",
    "wof:placetype":"venue"
},
  "geometry": {"coordinates":[-1.7555650473,52.4834518433],"type":"Point"}
}