{
  "type": "Feature",
  "properties": {
    "addr:full":"33 Lockharton Avenue Edinburgh City of Edinburgh EH14 1AY",
    "addr:housenumber":"33",
    "addr:postcode":"eh14 1ay",
    "addr:street":"Lockharton Avenue Edinburgh",
    "iso:country":"GB",
    "sg:address":"33 Lockharton Avenue",
    "sg:city":"Edinburgh",
    "sg:classifiers":[
        {
            "category":"Wholesale",
            "subcategory":"Computers",
            "type":"Manufacturing & Wholesale Goods"
        },
        {
            "category":"Professional",
            "subcategory":"Computer Services",
            "type":"Services"
        }
    ],
    "sg:phone":"+44 131 443 1872",
    "sg:postcode":"EH14 1AY",
    "sg:province":"City of Edinburgh",
    "sg:tags":[
        "supplier",
        "consultant",
        "consumables"
    ],
    "wof:name":"Know Edge Ltd",
    "wof:placetype":"venue"
},
  "geometry": {"coordinates":[-3.232958,55.925121],"type":"Point"}
}