{
  "type": "Feature",
  "properties": {
    "addr:full":"34 Mortain Drive Berkhamsted Bedfordshire HP4 1JZ",
    "addr:housenumber":"34",
    "addr:postcode":"hp4 1jz",
    "addr:street":"Mortain Drive",
    "iso:country":"GB",
    "sg:address":"34 Mortain Drive",
    "sg:city":"Berkhamsted",
    "sg:classifiers":[
        {
            "category":"Building & Trades",
            "subcategory":"Landscaping Services",
            "type":"Services"
        }
    ],
    "sg:phone":"+44 1442 875222",
    "sg:postcode":"HP4 1JZ",
    "sg:province":"Bedfordshire",
    "sg:tags":[
        "gardening"
    ],
    "wof:name":"P & L Gardening Enterprises",
    "wof:placetype":"venue"
},
  "geometry": {"coordinates":[-0.582249,51.770535],"type":"Point"}
}