{
  "type": "Feature",
  "properties": {
    "iso:country":"GB",
    "sg:address":"1 Hurworth Street",
    "sg:city":"Bishop Auckland",
    "sg:classifiers":[
        {
            "category":"Personal",
            "subcategory":"Beauty Salon",
            "type":"Services"
        }
    ],
    "sg:phone":"+44 1388 603336",
    "sg:postcode":"DL14 6HJ",
    "sg:province":"Durham",
    "sg:tags":[
        "unisex",
        "hairdresser"
    ],
    "wof:name":"Christie-Ann",
    "wof:placetype":"venue"
},
  "geometry": {"coordinates":[-1.67673,54.653687],"type":"Point"}
}