{
  "type": "Feature",
  "properties": {
    "iso:country":"GB",
    "sg:address":"Wayside Farm, Watford Road",
    "sg:city":"King's Langley",
    "sg:classifiers":[
        {
            "category":"Farming",
            "subcategory":"Dairy Farm",
            "type":"Manufacturing & Wholesale Goods"
        },
        {
            "category":"Farming",
            "subcategory":"Livestock Farm",
            "type":"Manufacturing & Wholesale Goods"
        }
    ],
    "sg:postcode":"WD4 8EA",
    "sg:province":"Hertfordshire",
    "sg:tags":[
        "others"
    ],
    "wof:name":"Charles W D Wray",
    "wof:placetype":"venue"
},
  "geometry": {"coordinates":[-0.44729,51.70829],"type":"Point"}
}