{
  "type": "Feature",
  "properties": {
    "addr:full":"Edgwarebury Lane Edgware Greater London HA8 8QS",
    "addr:postcode":"ha8 8qs",
    "addr:street":"Edgwarebury Lane",
    "iso:country":"GB",
    "sg:address":"Edgwarebury Lane",
    "sg:city":"Edgware",
    "sg:classifiers":[
        {
            "category":"Shopping",
            "subcategory":"Pets & Pet Supplies",
            "type":"Retail Goods"
        }
    ],
    "sg:phone":"+44 20 8958 2932",
    "sg:postcode":"HA8 8QS",
    "sg:province":"Greater London",
    "sg:tags":[
        "food"
    ],
    "wof:name":"Bury Farm",
    "wof:placetype":"venue"
},
  "geometry": {"coordinates":[-0.2802700102,51.6312026978],"type":"Point"}
}