{
  "type": "Feature",
  "properties": {
    "addr:full":"10 Forge Lane, Mill Grn, Aldridge Walsall Staffordshire WS9 0LY",
    "addr:housenumber":"10",
    "addr:postcode":"ws9 0ly",
    "addr:street":"Forge Lane Mill Grn",
    "iso:country":"GB",
    "sg:address":"10 Forge Lane, Mill Grn, Aldridge",
    "sg:city":"Walsall",
    "sg:classifiers":[
        {
            "category":"Building & Trades",
            "subcategory":"Construction",
            "type":"Services"
        }
    ],
    "sg:postcode":"WS9 0LY",
    "sg:province":"Staffordshire",
    "sg:tags":[
        "decorator",
        "painter"
    ],
    "wof:name":"David R Ross Decorating",
    "wof:placetype":"venue"
},
  "geometry": {"coordinates":[-1.8861269951,52.6070976257],"type":"Point"}
}