{
  "type": "Feature",
  "properties": {
    "addr:full":"Coach And Travel (the) Centre, Scotland Road Carnforth Cumbria LA5 9RQ",
    "addr:postcode":"la5 9rq",
    "addr:street":"The Centre Scotland Road",
    "iso:country":"GB",
    "sg:address":"Coach And Travel (the) Centre, Scotland Road",
    "sg:city":"Carnforth",
    "sg:classifiers":[
        {
            "category":"Bus Charters",
            "type":"Transportation"
        }
    ],
    "sg:phone":"+44 1524 720033",
    "sg:postcode":"LA5 9RQ",
    "sg:province":"Cumbria",
    "sg:tags":[
        "hire",
        "coach"
    ],
    "wof:name":"Hadwins (Tours) Ltd.",
    "wof:placetype":"venue"
},
  "geometry": {"coordinates":[-2.768059,54.128479],"type":"Point"}
}