{
  "type": "Feature",
  "properties": {
    "addr:full":"55 Wyggeston Street Burton-on-trent Derbyshire DE13 0SD",
    "addr:housenumber":"55",
    "addr:postcode":"de13 0sd",
    "addr:street":"Wyggeston Street",
    "iso:country":"GB",
    "sg:address":"55 Wyggeston Street",
    "sg:city":"Burton-on-trent",
    "sg:classifiers":[
        {
            "category":"Freight",
            "type":"Transportation"
        }
    ],
    "sg:phone":"+44 1283 564754",
    "sg:postcode":"DE13 0SD",
    "sg:province":"Derbyshire",
    "sg:tags":[
        "haulage",
        "road"
    ],
    "wof:name":"A J Allen Haulage",
    "wof:placetype":"venue"
},
  "geometry": {"coordinates":[-1.6427890062,52.8188400269],"type":"Point"}
}