{
  "type": "Feature",
  "properties": {
    "iso:country":"GB",
    "sg:address":"3 Regal Arcade, Broad Lane",
    "sg:city":"Huddersfield",
    "sg:classifiers":[
        {
            "category":"Personal",
            "subcategory":"Beauty Salon",
            "type":"Services"
        }
    ],
    "sg:postcode":"HD5 9DJ",
    "sg:province":"West Yorkshire",
    "sg:tags":[
        "unisex",
        "hairdresser"
    ],
    "wof:name":"Scrunches Hair Studio & Trichologist",
    "wof:placetype":"venue"
},
  "geometry": {"coordinates":[-1.76186,53.64518],"type":"Point"}
}