{
  "type": "Feature",
  "properties": {
    "addr:full":"Second Floor Hill Stores, Huddersfield Road Oldham Lancashire OL4 2RD",
    "addr:housenumber":"second floor",
    "addr:postcode":"ol4 2rd",
    "addr:street":"Hill;Huddersfield Road",
    "iso:country":"GB",
    "sg:address":"Second Floor Hill Stores, Huddersfield Road",
    "sg:city":"Oldham",
    "sg:classifiers":[
        {
            "category":"Recreation",
            "type":"Entertainment"
        }
    ],
    "sg:phone":"+44 161 624 0881",
    "sg:postcode":"OL4 2RD",
    "sg:province":"Lancashire",
    "sg:tags":[
        "snooker",
        "billiards",
        "pool"
    ],
    "wof:name":"Hillbillies",
    "wof:placetype":"venue"
},
  "geometry": {"coordinates":[-2.0746700764,53.5497055054],"type":"Point"}
}