{
  "type": "Feature",
  "properties": {
    "iso:country":"GB",
    "sg:address":"123 Yarmouth Road, Ellingham",
    "sg:city":"Bungay",
    "sg:classifiers":[
        {
            "category":"Shopping",
            "subcategory":"Florist",
            "type":"Retail Goods"
        }
    ],
    "sg:phone":"+44 1508 518205",
    "sg:postcode":"NR35 2PG",
    "sg:province":"Norfolk",
    "wof:name":"F W Bale & Son",
    "wof:placetype":"venue"
},
  "geometry": {"coordinates":[1.457301,52.46917],"type":"Point"}
}