{
  "type": "Feature",
  "properties": {
    "iso:country":"GB",
    "sg:address":"Commercial Street, Pengam",
    "sg:city":"Blackwood",
    "sg:classifiers":[
        {
            "category":"Social Services",
            "subcategory":"Retirement Home",
            "type":"Services"
        }
    ],
    "sg:postcode":"NP12 3TX",
    "sg:province":"Caerphilly",
    "sg:tags":[
        "residential",
        "care"
    ],
    "wof:name":"Pencelli Residential Home",
    "wof:placetype":"venue"
},
  "geometry": {"coordinates":[-3.223494,51.664314],"type":"Point"}
}