{
  "type": "Feature",
  "properties": {
    "iso:country":"GB",
    "sg:address":"The Old Vicarage, Church Street",
    "sg:city":"Taunton",
    "sg:classifiers":[
        {
            "category":"Building & Trades",
            "subcategory":"Construction",
            "type":"Services"
        }
    ],
    "sg:postcode":"TA4 3AT",
    "sg:province":"Devon",
    "sg:tags":[
        "builder"
    ],
    "wof:name":"H W Back & Son (Builders) Ltd.",
    "wof:placetype":"venue"
},
  "geometry": {"coordinates":[-3.187644,51.061039],"type":"Point"}
}