{
  "type": "Feature",
  "properties": {
    "iso:country":"GB",
    "sg:address":"Unit C Boarshaw Ind Est",
    "sg:city":"Manchester",
    "sg:classifiers":[
        {
            "category":"Building & Trades",
            "subcategory":"Plumbing",
            "type":"Services"
        }
    ],
    "sg:phone":"+44 161 654 0866",
    "sg:postcode":"M24 2HG",
    "sg:province":"Greater Manchester",
    "sg:tags":[
        "merchant",
        "plumbers'"
    ],
    "wof:name":"Ideal Plumbing Supplies",
    "wof:placetype":"venue"
},
  "geometry": {"coordinates":[-2.1856,53.547798],"type":"Point"}
}