{
  "type": "Feature",
  "properties": {
    "iso:country":"GB",
    "sg:address":"Unit 3 Blackburn Road West",
    "sg:city":"Bolton",
    "sg:classifiers":[
        {
            "category":"Retail",
            "subcategory":"Emissions Testing",
            "type":"Services"
        },
        {
            "category":"Professional",
            "subcategory":"Testing Lab",
            "type":"Services"
        },
        {
            "category":"Retail",
            "subcategory":"Auto Repair",
            "type":"Services"
        }
    ],
    "sg:phone":"+44 1204 532542",
    "sg:postcode":"BL1 8NB",
    "sg:province":"Lancashire",
    "sg:tags":[
        "modification",
        "garage",
        "mot"
    ],
    "wof:name":"B R West M O T Centre",
    "wof:placetype":"venue"
},
  "geometry": {"coordinates":[-2.433344,53.60125],"type":"Point"}
}