{
  "type": "Feature",
  "properties": {
    "iso:country":"GB",
    "sg:address":"139a Western Road",
    "sg:city":"Brighton",
    "sg:classifiers":[
        {
            "category":"Shopping",
            "subcategory":"News",
            "type":"Retail Goods"
        }
    ],
    "sg:phone":"+44 1273 326375",
    "sg:postcode":"BN1 2LA",
    "sg:province":"East Sussex",
    "sg:tags":[
        "newsagent"
    ],
    "wof:name":"Brian Arthur Clifford",
    "wof:placetype":"venue"
},
  "geometry": {"coordinates":[-0.151297,50.824795],"type":"Point"}
}