{
  "type": "Feature",
  "properties": {
    "iso:country":"GB",
    "sg:address":"Garside Farm, Dig Gate Lane, Milnrow",
    "sg:city":"Rochdale",
    "sg:classifiers":[
        {
            "category":"Farming",
            "subcategory":"Livestock Farm",
            "type":"Manufacturing & Wholesale Goods"
        }
    ],
    "sg:phone":"+44 1706 845194",
    "sg:postcode":"OL16 4NS",
    "sg:province":"Lancashire",
    "sg:tags":[
        "others"
    ],
    "wof:name":"R Taylor",
    "wof:placetype":"venue"
},
  "geometry": {"coordinates":[-2.11989,53.597099],"type":"Point"}
}