{
  "type": "Feature",
  "properties": {
    "iso:country":"GB",
    "sg:address":"20 Kiln Ground, Leverstock Gn",
    "sg:city":"Hemel Hempstead",
    "sg:classifiers":[
        {
            "category":"Home & Garden",
            "subcategory":"Carpets & Floor Coverings",
            "type":"Retail Goods"
        }
    ],
    "sg:postcode":"HP3 8EZ",
    "sg:province":"Hertfordshire",
    "sg:tags":[
        "carpets",
        "rug",
        "matting"
    ],
    "wof:name":"Bovingdon Carpets",
    "wof:placetype":"venue"
},
  "geometry": {"coordinates":[-0.445044,51.744637],"type":"Point"}
}