{
  "type": "Feature",
  "properties": {
    "iso:country":"GB",
    "sg:address":"57 Antrobus St",
    "sg:city":"Congleton",
    "sg:classifiers":[
        {
            "category":"Recreation",
            "subcategory":"Dog Park",
            "type":"Entertainment"
        }
    ],
    "sg:phone":"+44 1260 277558",
    "sg:postcode":"CW12 1HE",
    "sg:province":"Cheshire",
    "wof:name":"Bow Wows",
    "wof:placetype":"venue"
},
  "geometry": {"coordinates":[-2.2162699699,53.1647186279],"type":"Point"}
}