{
  "type": "Feature",
  "properties": {
    "addr:full":"Albert Road Methodist Church & Community Centre, Albert Rd Penarth The Vale of Glamorgan CF64 1BY",
    "addr:postcode":"cf64 1by",
    "addr:street":"Albert;Albert Rd;Vale",
    "iso:country":"GB",
    "sg:address":"Albert Road Methodist Church & Community Centre, Albert Rd",
    "sg:city":"Penarth",
    "sg:classifiers":[
        {
            "category":"Professional",
            "subcategory":"Lawyer & Legal Services",
            "type":"Services"
        }
    ],
    "sg:phone":"+44 29 2070 9358",
    "sg:postcode":"CF64 1BY",
    "sg:province":"The Vale of Glamorgan",
    "sg:tags":[
        "advice",
        "counselling"
    ],
    "wof:name":"South Wales Counselling",
    "wof:placetype":"venue"
},
  "geometry": {"coordinates":[-3.17277,51.43985],"type":"Point"}
}