{
  "type": "Feature",
  "properties": {
    "addr:full":"Prospect Works, Allerton Road, Allerton Bradford West Yorkshire BD15 7AF",
    "addr:postcode":"bd15 7af",
    "addr:street":"Allerton Road",
    "iso:country":"GB",
    "sg:address":"Prospect Works, Allerton Road, Allerton",
    "sg:city":"Bradford",
    "sg:classifiers":[
        {
            "category":"Building & Trades",
            "subcategory":"Cleaning & Sanitation",
            "type":"Services"
        },
        {
            "category":"Manufacturing",
            "subcategory":"Retail Goods",
            "type":"Manufacturing & Wholesale Goods"
        }
    ],
    "sg:phone":"+44 1274 495709",
    "sg:postcode":"BD15 7AF",
    "sg:province":"West Yorkshire",
    "sg:tags":[
        "hygiene",
        "manufacturer",
        "brush",
        "cleansing"
    ],
    "sg:website":"http://www.widdops.com",
    "wof:name":"Widdop de Courcy Ltd.",
    "wof:placetype":"venue"
},
  "geometry": {"coordinates":[-1.8131099939,53.8032608032],"type":"Point"}
}