{
  "type": "Feature",
  "properties": {
    "iso:country":"GB",
    "sg:address":"Chishill Rd, Heydon",
    "sg:city":"Royston",
    "sg:classifiers":[
        {
            "category":"Organizations",
            "subcategory":"Non-profit Organization",
            "type":"Services"
        }
    ],
    "sg:phone":"+44 1763 838329",
    "sg:postcode":"SG8 8PN",
    "sg:province":"Bedfordshire",
    "sg:tags":[
        "organisation",
        "animal",
        "welfare"
    ],
    "wof:name":"Wood Green Animal Shelters",
    "wof:placetype":"venue"
},
  "geometry": {"coordinates":[0.086620003,52.0398025513],"type":"Point"}
}