{
  "type": "Feature",
  "properties": {
    "addr:full":"Lyon House, Red Lion Street London Greater London WC1R 4GB",
    "addr:postcode":"wc1r 4gb",
    "addr:street":"Red Lion Street",
    "iso:country":"GB",
    "sg:address":"Lyon House, Red Lion Street",
    "sg:city":"London",
    "sg:classifiers":[
        {
            "category":"Professional",
            "subcategory":"Accounting & Tax Preparation",
            "type":"Services"
        }
    ],
    "sg:phone":"+44 20 7841 4000",
    "sg:postcode":"WC1R 4GB",
    "sg:province":"Greater London",
    "sg:tags":[
        "accountant"
    ],
    "wof:name":"Saffery Champness International Ltd.",
    "wof:placetype":"venue"
},
  "geometry": {"coordinates":[-0.11774,51.518749],"type":"Point"}
}