{
  "type": "Feature",
  "properties": {
    "iso:country":"GB",
    "sg:address":"6 Northgate Street",
    "sg:city":"Ipswich",
    "sg:classifiers":[
        {
            "category":"Shopping",
            "subcategory":"Department Store",
            "type":"Retail Goods"
        }
    ],
    "sg:postcode":"IP1 3BZ",
    "sg:province":"Suffolk",
    "wof:name":"Brian Page",
    "wof:placetype":"venue"
},
  "geometry": {"coordinates":[1.156559,52.057915],"type":"Point"}
}