{
  "type": "Feature",
  "properties": {
    "iso:country":"GB",
    "sg:address":"2 Clark House, Haxby Shop Centre, The Village",
    "sg:city":"York",
    "sg:classifiers":[
        {
            "category":"Manufacturing",
            "subcategory":"Tools & Machinery",
            "type":"Manufacturing & Wholesale Goods"
        }
    ],
    "sg:phone":"+44 1653 697055",
    "sg:postcode":"YO32 3HU",
    "sg:province":"North Yorkshire",
    "sg:tags":[
        "society",
        "friendly"
    ],
    "wof:name":"Whisker Seekings & Wardle",
    "wof:placetype":"venue"
},
  "geometry": {"coordinates":[-1.074009,54.015755],"type":"Point"}
}