{
  "type": "Feature",
  "properties": {
    "addr:full":"4a North Gate Newark Nottinghamshire NG24 1EZ",
    "addr:housenumber":"4a",
    "addr:postcode":"ng24 1ez",
    "addr:street":"North Gate",
    "iso:country":"GB",
    "sg:address":"4a North Gate",
    "sg:city":"Newark",
    "sg:classifiers":[
        {
            "category":"Shopping",
            "subcategory":"Antiques",
            "type":"Retail Goods"
        }
    ],
    "sg:postcode":"NG24 1EZ",
    "sg:province":"Nottinghamshire",
    "wof:name":"D & V Antiques",
    "wof:placetype":"venue"
},
  "geometry": {"coordinates":[-0.808253,53.079563],"type":"Point"}
}