{
  "type": "Feature",
  "properties": {
    "iso:country":"GB",
    "sg:address":"57 Ivy Road",
    "sg:city":"Macclesfield",
    "sg:classifiers":[
        {
            "category":"Building & Trades",
            "subcategory":"Construction",
            "type":"Services"
        }
    ],
    "sg:postcode":"SK11 8QN",
    "sg:province":"Cheshire",
    "sg:tags":[
        "builder"
    ],
    "wof:name":"Simon Mear",
    "wof:placetype":"venue"
},
  "geometry": {"coordinates":[-2.1497468948,53.2568969727],"type":"Point"}
}