{
  "type": "Feature",
  "properties": {
    "iso:country":"GB",
    "sg:address":"8 Gro Road",
    "sg:city":"London",
    "sg:classifiers":[
        {
            "category":"Cafe",
            "type":"Food & Drink"
        }
    ],
    "sg:phone":"+44 20 8983 9723",
    "sg:postcode":"E3 5AX",
    "sg:province":"Greater London",
    "sg:tags":[
        "tea",
        "room"
    ],
    "wof:name":"G Tekle-Mariam",
    "wof:placetype":"venue"
},
  "geometry": {"coordinates":[-0.0348449983,51.5255889893],"type":"Point"}
}