{
  "type": "Feature",
  "properties": {
    "iso:country":"GB",
    "sg:address":"Unit 6 7a Piazza Centre, Sussex St",
    "sg:city":"Rhyl",
    "sg:classifiers":[
        {
            "category":"Shopping",
            "subcategory":"Department Store",
            "type":"Retail Goods"
        }
    ],
    "sg:postcode":"LL18 1SE",
    "sg:province":"Conwy",
    "wof:name":"Hughes,Alan,",
    "wof:placetype":"venue"
},
  "geometry": {"coordinates":[-3.472384,53.311581],"type":"Point"}
}