{
  "type": "Feature",
  "properties": {
    "iso:country":"GB",
    "sg:address":"15 Commercial Rd",
    "sg:city":"Swindon",
    "sg:classifiers":[
        {
            "category":"Real Estate",
            "subcategory":"Real Estate Agent",
            "type":"Services"
        }
    ],
    "sg:phone":"+44 1793 610061",
    "sg:postcode":"SN1 5NF",
    "sg:province":"Wiltshire",
    "wof:name":"Darlows",
    "wof:placetype":"venue"
},
  "geometry": {"coordinates":[-1.783184,51.558464],"type":"Point"}
}