{
  "type": "Feature",
  "properties": {
    "addr:full":"Battersea Business Centre, 103 Lavender Hill London Greater London SW11 5QL",
    "addr:housenumber":"103",
    "addr:postcode":"sw11 5ql",
    "addr:street":"Battersea;Lavender Hill",
    "iso:country":"GB",
    "sg:address":"Battersea Business Centre, 103 Lavender Hill",
    "sg:city":"London",
    "sg:classifiers":[
        {
            "category":"Professional",
            "type":"Services"
        }
    ],
    "sg:phone":"+44 20 7801 0694",
    "sg:postcode":"SW11 5QL",
    "sg:province":"Greater London",
    "sg:tags":[
        "caterer"
    ],
    "wof:name":"Above the Salt",
    "wof:placetype":"venue"
},
  "geometry": {"coordinates":[-0.1562100053,51.4654006958],"type":"Point"}
}