{
  "type": "Feature",
  "properties": {
    "addr:full":"2 Cromwell Road Hertford Hertfordshire SG13 7DP",
    "addr:housenumber":"2",
    "addr:postcode":"sg13 7dp",
    "addr:street":"Cromwell Road",
    "iso:country":"GB",
    "sg:address":"2 Cromwell Road",
    "sg:city":"Hertford",
    "sg:classifiers":[
        {
            "category":"Retail",
            "subcategory":"Event Space",
            "type":"Services"
        }
    ],
    "sg:phone":"+44 1992 589671",
    "sg:postcode":"SG13 7DP",
    "sg:province":"Hertfordshire",
    "sg:tags":[
        "pipeline"
    ],
    "wof:name":"Fleet Heating & Pipework Engineering Service",
    "wof:placetype":"venue"
},
  "geometry": {"coordinates":[-0.0594200008,51.8010063171],"type":"Point"}
}