{
  "type": "Feature",
  "properties": {
    "iso:country":"GB",
    "sg:address":"11 Eastgate",
    "sg:city":"Bourne",
    "sg:classifiers":[
        {
            "category":"Food & Beverages",
            "subcategory":"Meat & Fish",
            "type":"Retail Goods"
        }
    ],
    "sg:phone":"+44 1778 423489",
    "sg:postcode":"PE10 9LB",
    "sg:province":"Lincolnshire",
    "sg:tags":[
        "butcher"
    ],
    "wof:name":"N L Sandall & Sons",
    "wof:placetype":"venue"
},
  "geometry": {"coordinates":[-0.3681249917,52.7657928467],"type":"Point"}
}