{
  "type": "Feature",
  "properties": {
    "iso:country":"GB",
    "sg:address":"16 Lawrence Ave",
    "sg:city":"Chesterfield",
    "sg:classifiers":[
        {
            "category":"Building & Trades",
            "subcategory":"Construction",
            "type":"Services"
        }
    ],
    "sg:postcode":"S42 5TS",
    "sg:province":"Derbyshire",
    "sg:tags":[
        "builder"
    ],
    "wof:name":"J M Building Services",
    "wof:placetype":"venue"
},
  "geometry": {"coordinates":[-1.3610420227,53.1906814575],"type":"Point"}
}