{
  "type": "Feature",
  "properties": {
    "iso:country":"GB",
    "sg:address":"Addingford Mills, Addingford Lane, Horbury",
    "sg:city":"Wakefield",
    "sg:classifiers":[
        {
            "category":"Home & Garden",
            "subcategory":"Building Materials",
            "type":"Retail Goods"
        }
    ],
    "sg:phone":"+44 1924 272077",
    "sg:postcode":"WF4 5BL",
    "sg:province":"West Yorkshire",
    "sg:tags":[
        "plaster",
        "ware"
    ],
    "wof:name":"Victoria Mouldings",
    "wof:placetype":"venue"
},
  "geometry": {"coordinates":[-1.548139,53.65789],"type":"Point"}
}