{
  "type": "Feature",
  "properties": {
    "iso:country":"GB",
    "sg:address":"Phoenix Ho, 828 Edenfield Rd",
    "sg:city":"Rochdale",
    "sg:classifiers":[
        {
            "category":"Shopping",
            "subcategory":"Computers & Home Electronics",
            "type":"Retail Goods"
        }
    ],
    "sg:phone":"+44 1706 759771",
    "sg:postcode":"OL12 7RB",
    "sg:province":"Lancashire",
    "sg:tags":[
        "equipment",
        "video",
        "cctv"
    ],
    "wof:name":"Phoenix Integrated Security Systems Ltd",
    "wof:placetype":"venue"
},
  "geometry": {"coordinates":[-2.162766,53.619007],"type":"Point"}
}