{
  "type": "Feature",
  "properties": {
    "iso:country":"GB",
    "sg:address":"3 Mary Street",
    "sg:city":"Lancaster",
    "sg:classifiers":[
        {
            "category":"Taxi",
            "type":"Transportation"
        }
    ],
    "sg:phone":"+44 1524 847847",
    "sg:postcode":"LA1 1UW",
    "sg:province":"Lancashire",
    "sg:tags":[
        "mini",
        "cab"
    ],
    "wof:name":"848848 Ltd.",
    "wof:placetype":"venue"
},
  "geometry": {"coordinates":[-2.7989668846,54.0482826233],"type":"Point"}
}