{
  "type": "Feature",
  "properties": {
    "addr:full":"10b Harding Way, St Ives Huntingdon Cambridgeshire PE27 3WR",
    "addr:housenumber":"10b",
    "addr:postcode":"pe27 3wr",
    "addr:street":"Harding Way",
    "iso:country":"GB",
    "sg:address":"10b Harding Way, St Ives",
    "sg:city":"Huntingdon",
    "sg:classifiers":[
        {
            "category":"Organizations",
            "subcategory":"Non-profit Organization",
            "type":"Services"
        }
    ],
    "sg:phone":"+44 1480 309600",
    "sg:postcode":"PE27 3WR",
    "sg:province":"Cambridgeshire",
    "sg:tags":[
        "organisation",
        "voluntary",
        "charity"
    ],
    "wof:name":"Scope",
    "wof:placetype":"venue"
},
  "geometry": {"coordinates":[-0.0644249991,52.3340606689],"type":"Point"}
}