{
  "type": "Feature",
  "properties": {
    "iso:country":"GB",
    "sg:address":"Rumfields Road",
    "sg:city":"Broadstairs",
    "sg:classifiers":[
        {
            "category":"Social Services",
            "subcategory":"Retirement Home",
            "type":"Services"
        }
    ],
    "sg:phone":"+44 1843 867858",
    "sg:postcode":"CT10 2PW",
    "sg:province":"Kent",
    "sg:tags":[
        "residential",
        "care"
    ],
    "wof:name":"Appleton Lodge",
    "wof:placetype":"venue"
},
  "geometry": {"coordinates":[1.409134,51.360378],"type":"Point"}
}