{
  "type": "Feature",
  "properties": {
    "iso:country":"GB",
    "sg:address":"1 Brackley Square",
    "sg:city":"Oldham",
    "sg:classifiers":[
        {
            "category":"Food & Beverages",
            "subcategory":"Meat & Fish",
            "type":"Retail Goods"
        }
    ],
    "sg:phone":"+44 161 628 5906",
    "sg:postcode":"OL1 3RS",
    "sg:province":"Lancashire",
    "sg:tags":[
        "chip"
    ],
    "wof:name":"P T Chippy",
    "wof:placetype":"venue"
},
  "geometry": {"coordinates":[-2.1051120758,53.5461463928],"type":"Point"}
}