{
  "type": "Feature",
  "properties": {
    "addr:full":"St Barts Road Sandwich Kent CT13 0AS",
    "addr:postcode":"ct13 0as",
    "addr:street":"St Barts Road Sandwich",
    "iso:country":"GB",
    "sg:address":"St Barts Road",
    "sg:city":"Sandwich",
    "sg:classifiers":[
        {
            "category":"Education",
            "subcategory":"School",
            "type":"Public Place"
        }
    ],
    "sg:phone":"+44 1304 612227",
    "sg:postcode":"CT13 0AS",
    "sg:province":"Kent",
    "sg:tags":[
        "local",
        "authority"
    ],
    "wof:name":"Sandwich County Junior School",
    "wof:placetype":"venue"
},
  "geometry": {"coordinates":[1.3320080042,51.2703514099],"type":"Point"}
}