{
  "type": "Feature",
  "properties": {
    "addr:full":"Teyland House, 31a London Road, Markes Tey Colchester Essex CO6 1DZ",
    "addr:housenumber":"31a",
    "addr:postcode":"co6 1dz",
    "addr:street":"London Road;Tey Colchester",
    "iso:country":"GB",
    "sg:address":"Teyland House, 31a London Road, Markes Tey",
    "sg:city":"Colchester",
    "sg:classifiers":[
        {
            "category":"Retail",
            "subcategory":"Repair Shop",
            "type":"Services"
        },
        {
            "category":"Professional",
            "subcategory":"Business Services",
            "type":"Services"
        }
    ],
    "sg:phone":"+44 1206 212092",
    "sg:postcode":"CO6 1DZ",
    "sg:province":"Essex",
    "sg:tags":[
        "sale",
        "agent",
        "export",
        "machinery",
        "agricultural",
        "import"
    ],
    "wof:name":"B S G Supplies Ltd",
    "wof:placetype":"venue"
},
  "geometry": {"coordinates":[0.805113,51.880939],"type":"Point"}
}