{
  "type": "Feature",
  "properties": {
    "iso:country":"GB",
    "sg:address":"31 Talbot Rd",
    "sg:city":"Maidstone",
    "sg:classifiers":[
        {
            "category":"Freight",
            "type":"Transportation"
        }
    ],
    "sg:postcode":"ME16 0HB",
    "sg:province":"Kent",
    "sg:tags":[
        "haulage",
        "road"
    ],
    "wof:name":"Mid Kent Freight",
    "wof:placetype":"venue"
},
  "geometry": {"coordinates":[0.496018,51.284191],"type":"Point"}
}