{
  "type": "Feature",
  "properties": {
    "iso:country":"GB",
    "sg:address":"102 High Street",
    "sg:city":"Peterborough",
    "sg:classifiers":[
        {
            "category":"Home & Garden",
            "subcategory":"Garden Supply",
            "type":"Retail Goods"
        },
        {
            "category":"Shopping",
            "subcategory":"Pets & Pet Supplies",
            "type":"Retail Goods"
        }
    ],
    "sg:phone":"+44 1733 703285",
    "sg:postcode":"PE2 8DR",
    "sg:province":"Cambridgeshire",
    "sg:tags":[
        "supplier",
        "pond",
        "nursery",
        "aquarium",
        "centre"
    ],
    "wof:name":"Fletton Garden & Pond Centre",
    "wof:placetype":"venue"
},
  "geometry": {"coordinates":[-0.239081,52.557838],"type":"Point"}
}