{
  "type": "Feature",
  "properties": {
    "iso:country":"GB",
    "sg:address":"36 Mayfield Avenue, Parkstone",
    "sg:city":"Poole",
    "sg:classifiers":[
        {
            "category":"Building & Trades",
            "subcategory":"Landscaping Services",
            "type":"Services"
        }
    ],
    "sg:phone":"+44 1202 740795",
    "sg:postcode":"BH14 9NY",
    "sg:province":"Dorset",
    "sg:tags":[
        "landscape",
        "contractor"
    ],
    "wof:name":"Mayfield Landscape Contractors",
    "wof:placetype":"venue"
},
  "geometry": {"coordinates":[-1.926822,50.720112],"type":"Point"}
}