{
  "type": "Feature",
  "properties": {
    "addr:full":"Lower Denbigh Road St Asaph Conwy LL17 0EL",
    "addr:postcode":"ll17 0el",
    "addr:street":"Lower Denbigh Road St",
    "iso:country":"GB",
    "sg:address":"Lower Denbigh Road",
    "sg:city":"St Asaph",
    "sg:classifiers":[
        {
            "category":"Professional",
            "subcategory":"Engineering",
            "type":"Services"
        }
    ],
    "sg:phone":"+44 1745 583752",
    "sg:postcode":"LL17 0EL",
    "sg:province":"Conwy",
    "sg:tags":[
        "civil",
        "engineer"
    ],
    "wof:name":"K M Construction (North Wales) Ltd.",
    "wof:placetype":"venue"
},
  "geometry": {"coordinates":[-3.448719,53.256153],"type":"Point"}
}