{
  "type": "Feature",
  "properties": {
    "addr:full":"378 High Street Berkhamsted Bedfordshire HP4 1HU",
    "addr:housenumber":"378",
    "addr:postcode":"hp4 1hu",
    "addr:street":"High Street",
    "iso:country":"GB",
    "sg:address":"378 High Street",
    "sg:city":"Berkhamsted",
    "sg:classifiers":[
        {
            "category":"Food & Beverages",
            "subcategory":"Bakery",
            "type":"Retail Goods"
        }
    ],
    "sg:postcode":"HP4 1HU",
    "sg:province":"Bedfordshire",
    "sg:tags":[
        "baker"
    ],
    "wof:name":"The Old Bakery",
    "wof:placetype":"venue"
},
  "geometry": {"coordinates":[-0.5722,51.763069],"type":"Point"}
}