{
  "type": "Feature",
  "properties": {
    "addr:full":"Star Brewery Studios, Castle Ditch Lane Lewes East Sussex BN7 1YJ",
    "addr:postcode":"bn7 1yj",
    "addr:street":"Castle Ditch Lane",
    "iso:country":"GB",
    "sg:address":"Star Brewery Studios, Castle Ditch Lane",
    "sg:city":"Lewes",
    "sg:classifiers":[
        {
            "category":"Organizations",
            "subcategory":"Professional Association",
            "type":"Services"
        }
    ],
    "sg:postcode":"BN7 1YJ",
    "sg:province":"East Sussex",
    "sg:tags":[
        "editorial"
    ],
    "wof:name":"John Lloyd",
    "wof:placetype":"venue"
},
  "geometry": {"coordinates":[0.01062,50.873203],"type":"Point"}
}