{
  "type": "Feature",
  "properties": {
    "addr:full":"Church Road, Hucking Maidstone Kent ME17 1QT",
    "addr:postcode":"me17 1qt",
    "addr:street":"Church Road",
    "iso:country":"GB",
    "sg:address":"Church Road, Hucking",
    "sg:city":"Maidstone",
    "sg:classifiers":[
        {
            "category":"Bars & Pubs",
            "type":"Food & Drink"
        },
        {
            "category":"Community Center",
            "subcategory":"Social",
            "type":"Public Place"
        }
    ],
    "sg:phone":"+44 1622 880830",
    "sg:postcode":"ME17 1QT",
    "sg:province":"Kent",
    "sg:tags":[
        "pubs",
        "house",
        "inn",
        "activity"
    ],
    "wof:name":"Hook & Hatchet Inn",
    "wof:placetype":"venue"
},
  "geometry": {"coordinates":[0.6435040236,51.2944068909],"type":"Point"}
}