{
  "type": "Feature",
  "properties": {
    "addr:full":"5 Milland Mews Hailsham East Sussex BN27 1TZ",
    "addr:housenumber":"5",
    "addr:postcode":"bn27 1tz",
    "addr:street":"Milland Mews",
    "iso:country":"GB",
    "sg:address":"5 Milland Mews",
    "sg:city":"Hailsham",
    "sg:classifiers":[
        {
            "category":"Health Services",
            "subcategory":"Health Practitioner",
            "type":"Services"
        }
    ],
    "sg:postcode":"BN27 1TZ",
    "sg:province":"East Sussex",
    "sg:tags":[
        "psychotherapist"
    ],
    "wof:name":"Cheryl Menelaus",
    "wof:placetype":"venue"
},
  "geometry": {"coordinates":[0.258555,50.87009],"type":"Point"}
}