{
  "type": "Feature",
  "properties": {
    "addr:full":"162 Lord Street Southport Lancashire PR9 0QA",
    "addr:housenumber":"162",
    "addr:postcode":"pr9 0qa",
    "addr:street":"Lord Street",
    "iso:country":"GB",
    "sg:address":"162 Lord Street",
    "sg:city":"Southport",
    "sg:classifiers":[
        {
            "category":"Professional",
            "subcategory":"Lawyer & Legal Services",
            "type":"Services"
        }
    ],
    "sg:phone":"+44 1704 546919",
    "sg:postcode":"PR9 0QA",
    "sg:province":"Lancashire",
    "sg:tags":[
        "solicitor"
    ],
    "sg:website":"http://www.fletcherssolicitors.co.uk",
    "wof:name":"Fletchers Solicitors",
    "wof:placetype":"venue"
},
  "geometry": {"coordinates":[-3.00122,53.650532],"type":"Point"}
}