{
  "type": "Feature",
  "properties": {
    "addr:full":"6 Alston Rd Barnet Hertfordshire EN5 4ET",
    "addr:housenumber":"6",
    "addr:postcode":"en5 4et",
    "addr:street":"Alston Rd",
    "iso:country":"GB",
    "sg:address":"6 Alston Rd",
    "sg:city":"Barnet",
    "sg:classifiers":[
        {
            "category":"Cafe",
            "type":"Food & Drink"
        }
    ],
    "sg:phone":"+44 20 8364 8484",
    "sg:postcode":"EN5 4ET",
    "sg:province":"Hertfordshire",
    "sg:tags":[
        "tea",
        "room"
    ],
    "wof:name":"Charlies Cafe",
    "wof:placetype":"venue"
},
  "geometry": {"coordinates":[-0.207854,51.655952],"type":"Point"}
}