{
  "type": "Feature",
  "properties": {
    "iso:country":"GB",
    "sg:address":"Viking Indstl Pk",
    "sg:city":"Jarrow",
    "sg:classifiers":[
        {
            "category":"Retail",
            "subcategory":"Auto Repair",
            "type":"Services"
        }
    ],
    "sg:postcode":"NE32 3DT",
    "sg:province":"Tyne and Wear",
    "sg:tags":[
        "electrician"
    ],
    "wof:name":"I G Auto Electrics",
    "wof:placetype":"venue"
},
  "geometry": {"coordinates":[-1.50237,54.984692],"type":"Point"}
}