{
  "type": "Feature",
  "properties": {
    "addr:full":"70 Bangor Rd, Leith Edinburgh City of Edinburgh EH6 5JU",
    "addr:housenumber":"70",
    "addr:postcode":"eh6 5ju",
    "addr:street":"Bangor Rd",
    "iso:country":"GB",
    "sg:address":"70 Bangor Rd, Leith",
    "sg:city":"Edinburgh",
    "sg:classifiers":[
        {
            "category":"Bus Charters",
            "type":"Transportation"
        }
    ],
    "sg:phone":"+44 131 554 7209",
    "sg:postcode":"EH6 5JU",
    "sg:province":"City of Edinburgh",
    "sg:tags":[
        "hire",
        "coach"
    ],
    "wof:name":"Leith Coaches",
    "wof:placetype":"venue"
},
  "geometry": {"coordinates":[-3.179784,55.971432],"type":"Point"}
}