{
  "type": "Feature",
  "properties": {
    "iso:country":"GB",
    "sg:address":"3 Station Road, Keynsham",
    "sg:city":"Bristol",
    "sg:classifiers":[
        {
            "category":"Personal",
            "subcategory":"Beauty Salon",
            "type":"Services"
        }
    ],
    "sg:phone":"+44 117 987 3121",
    "sg:postcode":"BS31 2BH",
    "sg:province":"City of Bristol",
    "sg:tags":[
        "unisex",
        "hairdresser"
    ],
    "wof:name":"F L R Unisex Hair Studio",
    "wof:placetype":"venue"
},
  "geometry": {"coordinates":[-2.4993190765,51.4176521301],"type":"Point"}
}