{
  "type": "Feature",
  "properties": {
    "addr:full":"Unit 1, Castle Acres Industrial Park, Castle Road Sittingbourne Kent ME10 3RZ",
    "addr:housenumber":"unit 1",
    "addr:postcode":"me10 3rz",
    "addr:street":"Castle Acres Industrial Park Castle Road",
    "iso:country":"GB",
    "sg:address":"Unit 1, Castle Acres Industrial Park, Castle Road",
    "sg:city":"Sittingbourne",
    "sg:classifiers":[
        {
            "category":"Manufacturing",
            "subcategory":"Petroleum Products",
            "type":"Manufacturing & Wholesale Goods"
        }
    ],
    "sg:postcode":"ME10 3RZ",
    "sg:province":"Kent",
    "sg:tags":[
        "double",
        "glazing"
    ],
    "wof:name":"A 1 Conservatories",
    "wof:placetype":"venue"
},
  "geometry": {"coordinates":[0.7379099727,51.3408203125],"type":"Point"}
}