{
  "type": "Feature",
  "properties": {
    "addr:full":"Defford Mill, Earls Croome Worcester Gloucestershire WR8 9DF",
    "addr:postcode":"wr8 9df",
    "addr:street":"Defford;Earls",
    "iso:country":"GB",
    "sg:address":"Defford Mill, Earls Croome",
    "sg:city":"Worcester",
    "sg:classifiers":[
        {
            "category":"Utilities",
            "subcategory":"Fuel Oil & Lpg",
            "type":"Services"
        }
    ],
    "sg:phone":"+44 1386 750938",
    "sg:postcode":"WR8 9DF",
    "sg:province":"Gloucestershire",
    "sg:tags":[
        "distributor"
    ],
    "wof:name":"Midland Shires Farmers Ltd",
    "wof:placetype":"venue"
},
  "geometry": {"coordinates":[-2.117219,52.0867],"type":"Point"}
}