{
  "type": "Feature",
  "properties": {
    "addr:full":"95 Eversley Rd Swansea Swansea SA2 9DE",
    "addr:housenumber":"95",
    "addr:postcode":"sa2 9de",
    "addr:street":"Eversley Rd",
    "iso:country":"GB",
    "sg:address":"95 Eversley Rd",
    "sg:city":"Swansea",
    "sg:classifiers":[
        {
            "category":"Shopping",
            "subcategory":"Pharmacy",
            "type":"Retail Goods"
        }
    ],
    "sg:phone":"+44 1792 203063",
    "sg:postcode":"SA2 9DE",
    "sg:province":"Swansea",
    "sg:tags":[
        "pharmacist",
        "chemist"
    ],
    "wof:name":"Moss Chemists",
    "wof:placetype":"venue"
},
  "geometry": {"coordinates":[-3.9856059551,51.6182022095],"type":"Point"}
}