{
  "type": "Feature",
  "properties": {
    "addr:full":"29 Main Street, Kirkinner Newton Stewart Dumfries and Galloway DG8 9AN",
    "addr:housenumber":"29",
    "addr:postcode":"dg8 9an",
    "addr:street":"Main Street;Stewart",
    "iso:country":"GB",
    "sg:address":"29 Main Street, Kirkinner",
    "sg:city":"Newton Stewart",
    "sg:classifiers":[
        {
            "category":"Government",
            "subcategory":"Post Office",
            "type":"Public Place"
        }
    ],
    "sg:phone":"+44 1988 840221",
    "sg:postcode":"DG8 9AN",
    "sg:province":"Dumfries and Galloway",
    "wof:name":"Kirkinner Post Office",
    "wof:placetype":"venue"
},
  "geometry": {"coordinates":[-4.4577679634,54.832736969],"type":"Point"}
}