{
  "type": "Feature",
  "properties": {
    "addr:full":"Commercial Road Lowestoft Suffolk NR32 2TD",
    "addr:postcode":"nr32 2td",
    "addr:street":"Commercial Road",
    "iso:country":"GB",
    "sg:address":"Commercial Road",
    "sg:city":"Lowestoft",
    "sg:classifiers":[
        {
            "category":"Autos & Motor Vehicles",
            "subcategory":"Auto Supplies",
            "type":"Retail Goods"
        }
    ],
    "sg:phone":"+44 1502 500600",
    "sg:postcode":"NR32 2TD",
    "sg:province":"Suffolk",
    "sg:tags":[
        "component"
    ],
    "wof:name":"Motofacts",
    "wof:placetype":"venue"
},
  "geometry": {"coordinates":[1.7443100214,52.4739265442],"type":"Point"}
}