{
  "type": "Feature",
  "properties": {
    "addr:full":"Po Box 17, 2 Belgarve Crescent Scarborough North Yorkshire YO11 1UD",
    "addr:housenumber":"po box 17 2",
    "addr:postcode":"yo11 1ud",
    "addr:street":"Belgarve Crescent",
    "iso:country":"GB",
    "sg:address":"Po Box 17, 2 Belgarve Crescent",
    "sg:city":"Scarborough",
    "sg:classifiers":[
        {
            "category":"Professional",
            "type":"Services"
        }
    ],
    "sg:postcode":"YO11 1UD",
    "sg:province":"North Yorkshire",
    "sg:tags":[
        "repair",
        "tech",
        "maintenance"
    ],
    "wof:name":"Kule Ltd",
    "wof:placetype":"venue"
},
  "geometry": {"coordinates":[-0.3995099962,54.2835006714],"type":"Point"}
}