{
  "type": "Feature",
  "properties": {
    "addr:full":"212 Saltwell Road Gateshead Tyne and Wear NE8 4TP",
    "addr:housenumber":"212",
    "addr:postcode":"ne8 4tp",
    "addr:street":"Saltwell Road",
    "iso:country":"GB",
    "sg:address":"212 Saltwell Road",
    "sg:city":"Gateshead",
    "sg:classifiers":[
        {
            "category":"Food & Beverages",
            "subcategory":"Liquor & Beverages",
            "type":"Retail Goods"
        }
    ],
    "sg:phone":"+44 191 477 2870",
    "sg:postcode":"NE8 4TP",
    "sg:province":"Tyne and Wear",
    "sg:tags":[
        "beer",
        "wine",
        "spirit",
        "wines"
    ],
    "wof:name":"SHEILA KNOX",
    "wof:placetype":"venue"
},
  "geometry": {"coordinates":[-1.6140819788,54.9478607178],"type":"Point"}
}