{
  "type": "Feature",
  "properties": {
    "addr:full":"89-91 Oldham Road Rochdale Lancashire OL16 5QR",
    "addr:housenumber":"89-91",
    "addr:postcode":"ol16 5qr",
    "addr:street":"Oldham Road",
    "iso:country":"GB",
    "sg:address":"89-91 Oldham Road",
    "sg:city":"Rochdale",
    "sg:classifiers":[
        {
            "category":"Organizations",
            "subcategory":"Membership Organization",
            "type":"Services"
        }
    ],
    "sg:phone":"+44 1706 750135",
    "sg:postcode":"OL16 5QR",
    "sg:province":"Lancashire",
    "sg:tags":[
        "club"
    ],
    "wof:name":"Rochdale Labour Club",
    "wof:placetype":"venue"
},
  "geometry": {"coordinates":[-2.150868,53.612511],"type":"Point"}
}