{
  "type": "Feature",
  "properties": {
    "addr:full":"Lower Wincombe Farm, Donhead St Mary Shaftesbury Dorset SP7 9DB",
    "addr:housenumber":"donhead",
    "addr:postcode":"sp7 9db",
    "addr:street":"Lower Wincombe",
    "iso:country":"GB",
    "sg:address":"Lower Wincombe Farm, Donhead St Mary",
    "sg:city":"Shaftesbury",
    "sg:classifiers":[
        {
            "category":"Farming",
            "subcategory":"Dairy Farm",
            "type":"Manufacturing & Wholesale Goods"
        }
    ],
    "sg:postcode":"SP7 9DB",
    "sg:province":"Dorset",
    "wof:name":"Whitford W J & M A",
    "wof:placetype":"venue"
},
  "geometry": {"coordinates":[-2.1871240139,51.0057640076],"type":"Point"}
}