{
  "type": "Feature",
  "properties": {
    "addr:full":"2 New Hill, Conisbrough Doncaster South Yorkshire DN12 3HA",
    "addr:housenumber":"2",
    "addr:postcode":"dn12 3ha",
    "addr:street":"New Hill",
    "iso:country":"GB",
    "sg:address":"2 New Hill, Conisbrough",
    "sg:city":"Doncaster",
    "sg:classifiers":[
        {
            "category":"Personal",
            "subcategory":"Beauty Salon",
            "type":"Services"
        }
    ],
    "sg:phone":"+44 1709 858101",
    "sg:postcode":"DN12 3HA",
    "sg:province":"South Yorkshire",
    "sg:tags":[
        "unisex",
        "hairdresser"
    ],
    "wof:name":"Diva",
    "wof:placetype":"venue"
},
  "geometry": {"coordinates":[-1.2267689705,53.4807167053],"type":"Point"}
}