{
  "type": "Feature",
  "properties": {
    "addr:full":"Lilac Tree Cottage, The Green, Ewhurst Cranleigh Surrey GU6 7RT",
    "addr:postcode":"gu6 7rt",
    "addr:street":"Lilac;The Green",
    "iso:country":"GB",
    "sg:address":"Lilac Tree Cottage, The Green, Ewhurst",
    "sg:city":"Cranleigh",
    "sg:classifiers":[
        {
            "category":"Building & Trades",
            "subcategory":"Plumbing",
            "type":"Services"
        }
    ],
    "sg:phone":"+44 1483 277592",
    "sg:postcode":"GU6 7RT",
    "sg:province":"Surrey",
    "sg:tags":[
        "repair",
        "heating",
        "servicing",
        "boiler"
    ],
    "wof:name":"C J B Plumbing & Heating Ltd",
    "wof:placetype":"venue"
},
  "geometry": {"coordinates":[-0.482998997,51.1415405273],"type":"Point"}
}