{
  "type": "Feature",
  "properties": {
    "addr:full":"Fiveways Bull Clacton-on-sea Essex CO15 4EN",
    "addr:postcode":"co15 4en",
    "addr:street":"Clacton-On-Sea",
    "iso:country":"GB",
    "sg:address":"Fiveways Bull",
    "sg:city":"Clacton-on-sea",
    "sg:classifiers":[
        {
            "category":"Food & Beverages",
            "subcategory":"Supermarket",
            "type":"Retail Goods"
        },
        {
            "category":"Food & Beverages",
            "subcategory":"Fruits & Vegetables",
            "type":"Retail Goods"
        }
    ],
    "sg:phone":"+44 1255 432971",
    "sg:postcode":"CO15 4EN",
    "sg:province":"Essex",
    "sg:tags":[
        "greengrocer"
    ],
    "wof:name":"Colchester & East Essex Co-Operative Society",
    "wof:placetype":"venue"
},
  "geometry": {"coordinates":[1.1532700062,51.8018264771],"type":"Point"}
}