{
  "type": "Feature",
  "properties": {
    "addr:full":"The Hall, Trinity Close Wanstead Greater London E11 4RP",
    "addr:postcode":"e11 4rp",
    "addr:street":"Trinity Close",
    "iso:country":"GB",
    "sg:address":"The Hall, Trinity Close",
    "sg:city":"Wanstead",
    "sg:classifiers":[
        {
            "category":"Personal",
            "type":"Services"
        },
        {
            "category":"Professional",
            "subcategory":"Lawyer & Legal Services",
            "type":"Services"
        }
    ],
    "sg:phone":"+44 20 8558 6399",
    "sg:postcode":"E11 4RP",
    "sg:province":"Greater London",
    "sg:tags":[
        "advice",
        "counselling"
    ],
    "wof:name":"Indian Muslim Federation UK",
    "wof:placetype":"venue"
},
  "geometry": {"coordinates":[0.00914,51.562618],"type":"Point"}
}