{
  "type": "Feature",
  "properties": {
    "iso:country":"GB",
    "sg:address":"Alderney Avenue",
    "sg:city":"Hounslow",
    "sg:classifiers":[
        {
            "category":"Shopping",
            "subcategory":"Computers & Home Electronics",
            "type":"Retail Goods"
        },
        {
            "category":"Wholesale",
            "subcategory":"Computers",
            "type":"Manufacturing & Wholesale Goods"
        }
    ],
    "sg:postcode":"TW5 0QL",
    "sg:province":"Greater London",
    "sg:tags":[
        "supplier",
        "consumables"
    ],
    "wof:name":"SISTEMA TECHNOLOGIES",
    "wof:placetype":"venue"
},
  "geometry": {"coordinates":[-0.363907,51.481461],"type":"Point"}
}