{
  "type": "Feature",
  "properties": {
    "addr:full":"Mill Lane, Fazeley Tamworth Staffordshire B78 3QD",
    "addr:postcode":"b78 3qd",
    "addr:street":"Mill Lane",
    "iso:country":"GB",
    "sg:address":"Mill Lane, Fazeley",
    "sg:city":"Tamworth",
    "sg:classifiers":[
        {
            "category":"Manufacturing",
            "subcategory":"Tools & Machinery",
            "type":"Manufacturing & Wholesale Goods"
        }
    ],
    "sg:phone":"+44 1827 286399",
    "sg:postcode":"B78 3QD",
    "sg:province":"Staffordshire",
    "sg:tags":[
        "design",
        "maker"
    ],
    "wof:name":"H & S Engineering",
    "wof:placetype":"venue"
},
  "geometry": {"coordinates":[-1.701779,52.615002],"type":"Point"}
}