{
  "type": "Feature",
  "properties": {
    "addr:full":"West Mead Trading Estate, Cut Maple, Sible Hedingham Halstead Essex CO9 1UP",
    "addr:postcode":"co9 1up",
    "addr:street":"West Mead Trading Estate Cut",
    "iso:country":"GB",
    "sg:address":"West Mead Trading Estate, Cut Maple, Sible Hedingham",
    "sg:city":"Halstead",
    "sg:classifiers":[
        {
            "category":"Building & Trades",
            "subcategory":"Cleaning & Sanitation",
            "type":"Services"
        }
    ],
    "sg:phone":"+44 1440 710429",
    "sg:postcode":"CO9 1UP",
    "sg:province":"Essex",
    "sg:tags":[
        "sanitary",
        "hygiene"
    ],
    "wof:name":"Western Healthcare Services Ltd",
    "wof:placetype":"venue"
},
  "geometry": {"coordinates":[0.6331340075,51.9396781921],"type":"Point"}
}