{
  "type": "Feature",
  "properties": {
    "iso:country":"GB",
    "sg:address":"101 High St",
    "sg:city":"Evesham",
    "sg:classifiers":[
        {
            "category":"Professional",
            "subcategory":"Employment Agencies",
            "type":"Services"
        }
    ],
    "sg:postcode":"WR11 4DN",
    "sg:province":"Gloucestershire",
    "sg:tags":[
        "consultant"
    ],
    "wof:name":"H B Associates (Evesham) Ltd",
    "wof:placetype":"venue"
},
  "geometry": {"coordinates":[-1.946765,52.095966],"type":"Point"}
}