{
  "type": "Feature",
  "properties": {
    "addr:full":"Apollo House 56 New Bond Street London Greater London W1S 1RG",
    "addr:housenumber":"56",
    "addr:postcode":"w1s 1rg",
    "addr:street":"Apollo;New Bond Street",
    "iso:country":"GB",
    "sg:address":"Apollo House 56 New Bond Street",
    "sg:city":"London",
    "sg:classifiers":[
        {
            "category":"Organizations",
            "subcategory":"Membership Organization",
            "type":"Services"
        }
    ],
    "sg:postcode":"W1S 1RG",
    "sg:province":"Greater London",
    "sg:tags":[
        "club"
    ],
    "wof:name":"Association of Commercial Lawyers Intern",
    "wof:placetype":"venue"
},
  "geometry": {"coordinates":[-0.144621,51.512691],"type":"Point"}
}