{
  "type": "Feature",
  "properties": {
    "addr:full":"Green Trees, Holywell St Ives Cambridgeshire PE27 4TQ",
    "addr:postcode":"pe27 4tq",
    "addr:street":"Holywell",
    "iso:country":"GB",
    "sg:address":"Green Trees, Holywell",
    "sg:city":"St Ives",
    "sg:classifiers":[
        {
            "category":"Bus Charters",
            "type":"Transportation"
        }
    ],
    "sg:postcode":"PE27 4TQ",
    "sg:province":"Cambridgeshire",
    "sg:tags":[
        "hire",
        "coach"
    ],
    "wof:name":"F E & A M Kiddle",
    "wof:placetype":"venue"
},
  "geometry": {"coordinates":[-0.03641,52.318802],"type":"Point"}
}