{
  "type": "Feature",
  "properties": {
    "addr:full":"125 High Street Cinderford Gloucestershire GL14 2TB",
    "addr:housenumber":"125",
    "addr:postcode":"gl14 2tb",
    "addr:street":"High Street",
    "iso:country":"GB",
    "sg:address":"125 High Street",
    "sg:city":"Cinderford",
    "sg:classifiers":[
        {
            "category":"Autos & Motor Vehicles",
            "subcategory":"Motorcycle Sales",
            "type":"Retail Goods"
        }
    ],
    "sg:phone":"+44 1594 822202",
    "sg:postcode":"GL14 2TB",
    "sg:province":"Gloucestershire",
    "wof:name":"Haines & Co. (Motor Cycles) Ltd.",
    "wof:placetype":"venue"
},
  "geometry": {"coordinates":[-2.5017199516,51.8283615112],"type":"Point"}
}