{
  "type": "Feature",
  "properties": {
    "iso:country":"GB",
    "sg:address":"60 Ferry Road, Irlam",
    "sg:city":"Manchester",
    "sg:classifiers":[
        {
            "category":"Professional",
            "subcategory":"Detective & Security Services",
            "type":"Services"
        }
    ],
    "sg:postcode":"M44 6DN",
    "sg:province":"Greater Manchester",
    "sg:tags":[
        "alarm",
        "burglar",
        "system"
    ],
    "wof:name":"Securit",
    "wof:placetype":"venue"
},
  "geometry": {"coordinates":[-2.415472,53.448193],"type":"Point"}
}