{
  "type": "Feature",
  "properties": {
    "iso:country":"GB",
    "sg:address":"189 Freeman Street",
    "sg:city":"Grimsby",
    "sg:classifiers":[
        {
            "category":"Food & Beverages",
            "subcategory":"Specialty",
            "type":"Retail Goods"
        }
    ],
    "sg:phone":"+44 1472 241130",
    "sg:postcode":"DN32 7AS",
    "sg:province":"Lincolnshire",
    "sg:tags":[
        "retailer",
        "product",
        "health"
    ],
    "wof:name":"Oriental Spices",
    "wof:placetype":"venue"
},
  "geometry": {"coordinates":[-0.074045,53.569115],"type":"Point"}
}