{
  "type": "Feature",
  "properties": {
    "addr:full":"19 Team Valley Business Centre, Team Valley Trading Estate, Earlsway Gateshead Tyne and Wear NE11 0RQ",
    "addr:housenumber":"19;business",
    "addr:postcode":"wear ne11 0rq",
    "addr:street":"Team",
    "iso:country":"GB",
    "sg:address":"19 Team Valley Business Centre, Team Valley Trading Estate, Earlsway",
    "sg:city":"Gateshead",
    "sg:classifiers":[
        {
            "category":"Sports & Exercise",
            "subcategory":"Golf",
            "type":"Entertainment"
        }
    ],
    "sg:phone":"+44 191 491 1138",
    "sg:postcode":"NE11 0RQ",
    "sg:province":"Tyne and Wear",
    "sg:tags":[
        "equipment"
    ],
    "wof:name":"Hymax Products (U K) Ltd.",
    "wof:placetype":"venue"
},
  "geometry": {"coordinates":[-1.6203989983,54.9331130981],"type":"Point"}
}