{
  "type": "Feature",
  "properties": {
    "iso:country":"GB",
    "sg:address":"Church Farm, Chelwood",
    "sg:city":"Bristol",
    "sg:classifiers":[
        {
            "category":"Farming",
            "subcategory":"Livestock Farm",
            "type":"Manufacturing & Wholesale Goods"
        }
    ],
    "sg:phone":"+44 1761 490444",
    "sg:postcode":"BS39 4NW",
    "sg:province":"Somerset",
    "sg:tags":[
        "others"
    ],
    "wof:name":"Robert Maxwell",
    "wof:placetype":"venue"
},
  "geometry": {"coordinates":[-2.526966,51.355518],"type":"Point"}
}