{
  "type": "Feature",
  "properties": {
    "iso:country":"GB",
    "sg:address":"7-9 Bridge St",
    "sg:city":"Colchester",
    "sg:classifiers":[
        {
            "category":"Professional",
            "subcategory":"Accounting & Tax Preparation",
            "type":"Services"
        }
    ],
    "sg:phone":"+44 1376 562115",
    "sg:postcode":"CO6 1NP",
    "sg:province":"Essex",
    "sg:tags":[
        "accountant"
    ],
    "wof:name":"Paul Da Costa & Co",
    "wof:placetype":"venue"
},
  "geometry": {"coordinates":[0.6855720282,51.8704605103],"type":"Point"}
}