{
  "type": "Feature",
  "properties": {
    "addr:full":"Weedon Road Aylesbury Buckinghamshire HP19 9PG",
    "addr:postcode":"hp19 9pg",
    "addr:street":"Weedon Road",
    "iso:country":"GB",
    "sg:address":"Weedon Road",
    "sg:city":"Aylesbury",
    "sg:classifiers":[
        {
            "category":"Education",
            "subcategory":"School",
            "type":"Public Place"
        }
    ],
    "sg:phone":"+44 1296 428551",
    "sg:postcode":"HP19 9PG",
    "sg:province":"Buckinghamshire",
    "sg:tags":[
        "local",
        "authority"
    ],
    "wof:name":"Quarrendon Upper School",
    "wof:placetype":"venue"
},
  "geometry": {"coordinates":[-0.8183270097,51.8270568848],"type":"Point"}
}