{
  "type": "Feature",
  "properties": {
    "addr:full":"3 Barretts Green Rd Willesden Greater London NW10 7AE",
    "addr:housenumber":"3",
    "addr:postcode":"nw10 7ae",
    "addr:street":"Barretts Green Rd",
    "iso:country":"GB",
    "sg:address":"3 Barretts Green Rd",
    "sg:city":"Willesden",
    "sg:classifiers":[
        {
            "category":"Communications",
            "subcategory":"Film & Video Production",
            "type":"Services"
        }
    ],
    "sg:phone":"+44 20 8964 1232",
    "sg:postcode":"NW10 7AE",
    "sg:province":"Greater London",
    "sg:tags":[
        "tv",
        "studio"
    ],
    "wof:name":"Cirro Lite",
    "wof:placetype":"venue"
},
  "geometry": {"coordinates":[-0.262969,51.533951],"type":"Point"}
}