{
  "type": "Feature",
  "properties": {
    "addr:full":"17 Vicarage Place Walsall West Midlands WS1 3NA",
    "addr:housenumber":"17",
    "addr:postcode":"ws1 3na",
    "addr:street":"Vicarage Place Walsall",
    "iso:country":"GB",
    "sg:address":"17 Vicarage Place",
    "sg:city":"Walsall",
    "sg:classifiers":[
        {
            "category":"Manufacturing",
            "subcategory":"Petroleum Products",
            "type":"Manufacturing & Wholesale Goods"
        }
    ],
    "sg:phone":"+44 1922 638600",
    "sg:postcode":"WS1 3NA",
    "sg:province":"West Midlands",
    "sg:tags":[
        "double",
        "glazing"
    ],
    "wof:name":"A & S Windows",
    "wof:placetype":"venue"
},
  "geometry": {"coordinates":[-1.982283,52.580894],"type":"Point"}
}