{
  "type": "Feature",
  "properties": {
    "iso:country":"GB",
    "sg:address":"5 Queen St",
    "sg:city":"Lincoln",
    "sg:classifiers":[
        {
            "category":"Shopping",
            "subcategory":"Pets & Pet Supplies",
            "type":"Retail Goods"
        }
    ],
    "sg:phone":"+44 1526 860341",
    "sg:postcode":"LN4 4AX",
    "sg:province":"Lincolnshire",
    "wof:name":"Pets Pantry",
    "wof:placetype":"venue"
},
  "geometry": {"coordinates":[-0.276335,53.079052],"type":"Point"}
}