{
  "type": "Feature",
  "properties": {
    "iso:country":"GB",
    "sg:address":"113 Southwark Street",
    "sg:city":"London",
    "sg:classifiers":[
        {
            "category":"Professional",
            "subcategory":"Employment Agencies",
            "type":"Services"
        }
    ],
    "sg:phone":"+44 20 7463 0100",
    "sg:postcode":"SE1 0JF",
    "sg:province":"Greater London",
    "sg:tags":[
        "consultant"
    ],
    "wof:name":"T & T Travel",
    "wof:placetype":"venue"
},
  "geometry": {"coordinates":[-0.102664,51.506313],"type":"Point"}
}