{
  "type": "Feature",
  "properties": {
    "iso:country":"GB",
    "sg:address":"22 The Leys, Denton",
    "sg:city":"Northampton",
    "sg:classifiers":[
        {
            "category":"Building & Trades",
            "subcategory":"Pest Control",
            "type":"Services"
        }
    ],
    "sg:phone":"+44 1604 890150",
    "sg:postcode":"NN7 1DH",
    "sg:province":"Buckinghamshire",
    "sg:tags":[
        "vermin"
    ],
    "wof:name":"Rely-On Services",
    "wof:placetype":"venue"
},
  "geometry": {"coordinates":[-0.776134,52.215359],"type":"Point"}
}