{
  "type": "Feature",
  "properties": {
    "iso:country":"GB",
    "sg:address":"198a Leigh Road",
    "sg:city":"Leigh-on-sea",
    "sg:classifiers":[
        {
            "category":"Food & Beverages",
            "subcategory":"Supermarket",
            "type":"Retail Goods"
        }
    ],
    "sg:postcode":"SS9 1BS",
    "sg:province":"Essex",
    "wof:name":"Sanders Stores",
    "wof:placetype":"venue"
},
  "geometry": {"coordinates":[0.664738,51.543026],"type":"Point"}
}