{
  "type": "Feature",
  "properties": {
    "addr:full":"143 Ford Road, Upton Wirral Merseyside CH49 0XB",
    "addr:housenumber":"143",
    "addr:postcode":"ch49 0xb",
    "addr:street":"Ford Road",
    "iso:country":"GB",
    "sg:address":"143 Ford Road, Upton",
    "sg:city":"Wirral",
    "sg:classifiers":[
        {
            "category":"Shopping",
            "subcategory":"Florist",
            "type":"Retail Goods"
        }
    ],
    "sg:phone":"+44 151 677 3651",
    "sg:postcode":"CH49 0XB",
    "sg:province":"Merseyside",
    "wof:name":"Neilflowers",
    "wof:placetype":"venue"
},
  "geometry": {"coordinates":[-3.095546,53.384407],"type":"Point"}
}