{
  "type": "Feature",
  "properties": {
    "addr:full":"Parkside House, 36 Alexandra Avenue Luton Bedfordshire LU3 1HG",
    "addr:housenumber":"36",
    "addr:postcode":"lu3 1hg",
    "addr:street":"Alexandra Avenue",
    "iso:country":"GB",
    "sg:address":"Parkside House, 36 Alexandra Avenue",
    "sg:city":"Luton",
    "sg:classifiers":[
        {
            "category":"Professional",
            "subcategory":"Art Services",
            "type":"Services"
        }
    ],
    "sg:postcode":"LU3 1HG",
    "sg:province":"Bedfordshire",
    "sg:tags":[
        "photographer"
    ],
    "wof:name":"Terry Thorn Photography",
    "wof:placetype":"venue"
},
  "geometry": {"coordinates":[-0.423299998,51.8914108276],"type":"Point"}
}