{
  "type": "Feature",
  "properties": {
    "iso:country":"GB",
    "sg:address":"45 Chiltern Ct, 188 Baker St",
    "sg:city":"London",
    "sg:classifiers":[
        {
            "category":"Organizations",
            "subcategory":"Membership Organization",
            "type":"Services"
        }
    ],
    "sg:postcode":"NW1 5SP",
    "sg:province":"Greater London",
    "sg:tags":[
        "club"
    ],
    "wof:name":"Midmar Management Ltd",
    "wof:placetype":"venue"
},
  "geometry": {"coordinates":[-0.15752,51.523029],"type":"Point"}
}