{
  "type": "Feature",
  "properties": {
    "addr:full":"38a Nelson Street Market Harborough Leicestershire LE16 9AY",
    "addr:housenumber":"38a",
    "addr:postcode":"le16 9ay",
    "addr:street":"Nelson Street",
    "iso:country":"GB",
    "sg:address":"38a Nelson Street",
    "sg:city":"Market Harborough",
    "sg:classifiers":[
        {
            "category":"Professional",
            "subcategory":"Engineering",
            "type":"Services"
        },
        {
            "category":"Building & Trades",
            "subcategory":"Electrical",
            "type":"Services"
        }
    ],
    "sg:postcode":"LE16 9AY",
    "sg:province":"Leicestershire",
    "sg:tags":[
        "engineer",
        "electrician",
        "contractor"
    ],
    "wof:name":"Wards Electrical",
    "wof:placetype":"venue"
},
  "geometry": {"coordinates":[-0.927603,52.478035],"type":"Point"}
}