{
  "type": "Feature",
  "properties": {
    "addr:full":"6 South End Road Rainham Essex RM13 7XH",
    "addr:housenumber":"6",
    "addr:postcode":"rm13 7xh",
    "addr:street":"South End Road",
    "iso:country":"GB",
    "sg:address":"6 South End Road",
    "sg:city":"Rainham",
    "sg:classifiers":[
        {
            "category":"Personal",
            "subcategory":"Beauty Salon",
            "type":"Services"
        }
    ],
    "sg:phone":"+44 1708 554946",
    "sg:postcode":"RM13 7XH",
    "sg:province":"Essex",
    "sg:tags":[
        "unisex",
        "hairdresser"
    ],
    "wof:name":"Darnell's",
    "wof:placetype":"venue"
},
  "geometry": {"coordinates":[0.1902160048,51.5291290283],"type":"Point"}
}