{
  "type": "Feature",
  "properties": {
    "addr:full":"9 Slug Road Stonehaven Aberdeenshire AB39 2EX",
    "addr:housenumber":"9",
    "addr:postcode":"ab39 2ex",
    "addr:street":"Slug Road",
    "iso:country":"GB",
    "sg:address":"9 Slug Road",
    "sg:city":"Stonehaven",
    "sg:classifiers":[
        {
            "category":"Shopping",
            "subcategory":"Clothing, Apparel, & Fashions",
            "type":"Retail Goods"
        }
    ],
    "sg:postcode":"AB39 2EX",
    "sg:province":"Aberdeenshire",
    "sg:tags":[
        "t-shirt"
    ],
    "wof:name":"Kaleidoscope",
    "wof:placetype":"venue"
},
  "geometry": {"coordinates":[-2.21284,56.964256],"type":"Point"}
}