{
  "type": "Feature",
  "properties": {
    "addr:full":"121 London Rd Sittingbourne Kent ME9 9QJ",
    "addr:housenumber":"121",
    "addr:postcode":"me9 9qj",
    "addr:street":"London Rd",
    "iso:country":"GB",
    "sg:address":"121 London Rd",
    "sg:city":"Sittingbourne",
    "sg:classifiers":[
        {
            "category":"Health Services",
            "subcategory":"Dentist",
            "type":"Services"
        }
    ],
    "sg:phone":"+44 1795 521535",
    "sg:postcode":"ME9 9QJ",
    "sg:province":"Kent",
    "wof:name":"A S Lupin & Associates",
    "wof:placetype":"venue"
},
  "geometry": {"coordinates":[0.798926,51.328148],"type":"Point"}
}