{
  "type": "Feature",
  "properties": {
    "iso:country":"GB",
    "sg:address":"748-750 Romford Road",
    "sg:city":"London",
    "sg:classifiers":[
        {
            "category":"Shopping",
            "subcategory":"Used Merchandise",
            "type":"Retail Goods"
        }
    ],
    "sg:phone":"+44 20 8553 1222",
    "sg:postcode":"E12 6BU",
    "sg:province":"Greater London",
    "sg:tags":[
        "furniture"
    ],
    "wof:name":"Discount Beds Direct",
    "wof:placetype":"venue"
},
  "geometry": {"coordinates":[0.054118,51.55286],"type":"Point"}
}