{
  "type": "Feature",
  "properties": {
    "iso:country":"GB",
    "sg:address":"12 Lock View",
    "sg:city":"Bingley",
    "sg:classifiers":[
        {
            "category":"Professional",
            "subcategory":"Art Services",
            "type":"Services"
        }
    ],
    "sg:postcode":"BD16 2RW",
    "sg:province":"West Yorkshire",
    "sg:tags":[
        "photographer"
    ],
    "wof:name":"Young,Kevin,",
    "wof:placetype":"venue"
},
  "geometry": {"coordinates":[-1.841916,53.85334],"type":"Point"}
}