{
  "type": "Feature",
  "properties": {
    "iso:country":"GB",
    "sg:address":"103 Sea Road",
    "sg:city":"Sunderland",
    "sg:classifiers":[
        {
            "category":"Retail",
            "subcategory":"Storage",
            "type":"Services"
        }
    ],
    "sg:phone":"+44 191 548 0815",
    "sg:postcode":"SR6 9BN",
    "sg:province":"Tyne and Wear",
    "sg:tags":[
        "household",
        "removal"
    ],
    "wof:name":"Greenwells Wool Store",
    "wof:placetype":"venue"
},
  "geometry": {"coordinates":[-1.3771109581,54.9302597046],"type":"Point"}
}