{
  "type": "Feature",
  "properties": {
    "addr:full":"2 Beechfield Road Smethwick West Midlands B67 6BP",
    "addr:housenumber":"2",
    "addr:postcode":"b67 6bp",
    "addr:street":"Beechfield Road",
    "iso:country":"GB",
    "sg:address":"2 Beechfield Road",
    "sg:city":"Smethwick",
    "sg:classifiers":[
        {
            "category":"Retail",
            "subcategory":"Auto Repair",
            "type":"Services"
        }
    ],
    "sg:phone":"+44 121 558 7527",
    "sg:postcode":"B67 6BP",
    "sg:province":"West Midlands",
    "sg:tags":[
        "modification",
        "garage"
    ],
    "wof:name":"Hari Motors",
    "wof:placetype":"venue"
},
  "geometry": {"coordinates":[-1.9758690596,52.4891319275],"type":"Point"}
}