{
  "type": "Feature",
  "properties": {
    "iso:country":"GB",
    "sg:address":"46 Pennine Way",
    "sg:city":"Penrith",
    "sg:classifiers":[
        {
            "category":"Building & Trades",
            "subcategory":"Plumbing",
            "type":"Services"
        }
    ],
    "sg:phone":"+44 1768 865019",
    "sg:postcode":"CA11 8EB",
    "sg:province":"Cumbria",
    "sg:tags":[
        "heating"
    ],
    "wof:name":"Ian Clarke",
    "wof:placetype":"venue"
},
  "geometry": {"coordinates":[-2.742564,54.666348],"type":"Point"}
}