{
  "type": "Feature",
  "properties": {
    "addr:full":"121 Leigh Road Leigh-on-sea Essex SS9 1JH",
    "addr:housenumber":"121",
    "addr:postcode":"ss9 1jh",
    "addr:street":"Leigh Road",
    "iso:country":"GB",
    "sg:address":"121 Leigh Road",
    "sg:city":"Leigh-on-sea",
    "sg:classifiers":[
        {
            "category":"Food & Beverages",
            "subcategory":"Bakery",
            "type":"Retail Goods"
        }
    ],
    "sg:phone":"+44 1702 75274",
    "sg:postcode":"SS9 1JH",
    "sg:province":"Essex",
    "sg:tags":[
        "baker"
    ],
    "wof:name":"Carlton Bakery",
    "wof:placetype":"venue"
},
  "geometry": {"coordinates":[0.6666070223,51.5435600281],"type":"Point"}
}