{
  "type": "Feature",
  "properties": {
    "addr:full":"Bank House Farm, Croxton Whitchurch Cheshire SY13 3BT",
    "addr:postcode":"sy13 3bt",
    "addr:street":"Whitchurch",
    "iso:country":"GB",
    "sg:address":"Bank House Farm, Croxton",
    "sg:city":"Whitchurch",
    "sg:classifiers":[
        {
            "category":"Transit Center",
            "subcategory":"Passenger",
            "type":"Transportation"
        }
    ],
    "sg:postcode":"SY13 3BT",
    "sg:province":"Cheshire",
    "sg:tags":[
        "boarding",
        "kennel",
        "catteries"
    ],
    "wof:name":"D G Cooper",
    "wof:placetype":"venue"
},
  "geometry": {"coordinates":[-2.7373290062,52.9511299133],"type":"Point"}
}