{
  "type": "Feature",
  "properties": {
    "iso:country":"GB",
    "sg:address":"1 Mulfords Hill",
    "sg:city":"Tadley",
    "sg:classifiers":[
        {
            "category":"Building & Trades",
            "subcategory":"Construction",
            "type":"Services"
        }
    ],
    "sg:phone":"+44 118 981 5414",
    "sg:postcode":"RG26 3LQ",
    "sg:province":"Berkshire",
    "sg:tags":[
        "builder"
    ],
    "wof:name":"K Jordan",
    "wof:placetype":"venue"
},
  "geometry": {"coordinates":[-1.138169,51.350632],"type":"Point"}
}