{
  "type": "Feature",
  "properties": {
    "addr:full":"237 Eversholt St Camden Greater London NW1 1BE",
    "addr:housenumber":"237",
    "addr:postcode":"nw1 1be",
    "addr:street":"Eversholt St",
    "iso:country":"GB",
    "sg:address":"237 Eversholt St",
    "sg:city":"Camden",
    "sg:classifiers":[
        {
            "category":"Shopping",
            "subcategory":"Crafts & Fabrics",
            "type":"Retail Goods"
        }
    ],
    "sg:phone":"+44 20 7387 3901",
    "sg:postcode":"NW1 1BE",
    "sg:province":"Greater London",
    "sg:tags":[
        "machine",
        "sewing",
        "knitting"
    ],
    "wof:name":"Hygrade Sewing Machines & Co",
    "wof:placetype":"venue"
},
  "geometry": {"coordinates":[-0.137713,51.533501],"type":"Point"}
}