{
  "type": "Feature",
  "properties": {
    "addr:full":"6 Shurville Close, Earls Barton Northampton Northamptonshire NN6 0JB",
    "addr:housenumber":"6;barton",
    "addr:postcode":"nn6 0jb",
    "addr:street":"Shurville Close Earls",
    "iso:country":"GB",
    "sg:address":"6 Shurville Close, Earls Barton",
    "sg:city":"Northampton",
    "sg:classifiers":[
        {
            "category":"Shopping",
            "subcategory":"Bicycles & Sporting Goods",
            "type":"Retail Goods"
        },
        {
            "category":"Farming",
            "subcategory":"Fish & Marine Products",
            "type":"Manufacturing & Wholesale Goods"
        }
    ],
    "sg:phone":"+44 1604 812238",
    "sg:postcode":"NN6 0JB",
    "sg:province":"Northamptonshire",
    "sg:tags":[
        "equipment",
        "supply"
    ],
    "wof:name":"Marine Chart Services",
    "wof:placetype":"venue"
},
  "geometry": {"coordinates":[-0.746728003,52.2625083923],"type":"Point"}
}