{
  "type": "Feature",
  "properties": {
    "iso:country":"GB",
    "sg:address":"Wholesale, 3 Bridle La",
    "sg:city":"Ripley",
    "sg:classifiers":[
        {
            "category":"Recreation",
            "subcategory":"Fishing",
            "type":"Entertainment"
        }
    ],
    "sg:phone":"+44 1773 512035",
    "sg:postcode":"DE5 3RQ",
    "sg:province":"Derbyshire",
    "sg:tags":[
        "angling"
    ],
    "wof:name":"Shorelink",
    "wof:placetype":"venue"
},
  "geometry": {"coordinates":[-1.407668,53.050701],"type":"Point"}
}