{
  "type": "Feature",
  "properties": {
    "iso:country":"GB",
    "sg:address":"22 Bells Road",
    "sg:city":"Stornoway",
    "sg:classifiers":[
        {
            "category":"Retail",
            "subcategory":"Auto Repair",
            "type":"Services"
        }
    ],
    "sg:phone":"+44 1851 701166",
    "sg:postcode":"HS1 2RA",
    "sg:province":"Eilean Siar",
    "sg:tags":[
        "body",
        "car",
        "repairer"
    ],
    "sg:website":"http://www.hebridean-brewery.co.uk",
    "wof:name":"Hebridean Coachworks",
    "wof:placetype":"venue"
},
  "geometry": {"coordinates":[-6.379959,58.206497],"type":"Point"}
}