{
  "type": "Feature",
  "properties": {
    "iso:country":"GB",
    "sg:address":"15 Regent Road",
    "sg:city":"Lowestoft",
    "sg:classifiers":[
        {
            "category":"Real Estate",
            "subcategory":"Surveying",
            "type":"Services"
        }
    ],
    "sg:phone":"+44 1502 530505",
    "sg:postcode":"NR32 1PA",
    "sg:province":"Suffolk",
    "sg:tags":[
        "surveyor",
        "valuer"
    ],
    "wof:name":"O A Chapman & Son",
    "wof:placetype":"venue"
},
  "geometry": {"coordinates":[1.752472,52.477966],"type":"Point"}
}