{
  "type": "Feature",
  "properties": {
    "addr:full":"19 Andrew Court, Clyde Street Clydebank East Dunbartonshire G81 1DF",
    "addr:housenumber":"19",
    "addr:postcode":"g81 1df",
    "addr:street":"Andrew Court Clyde Street",
    "iso:country":"GB",
    "sg:address":"19 Andrew Court, Clyde Street",
    "sg:city":"Clydebank",
    "sg:classifiers":[
        {
            "category":"Retail",
            "subcategory":"Auto Repair",
            "type":"Services"
        }
    ],
    "sg:phone":"+44 141 951 4200",
    "sg:postcode":"G81 1DF",
    "sg:province":"East Dunbartonshire",
    "sg:tags":[
        "modification",
        "garage"
    ],
    "wof:name":"Clydebank Taxi Repairs",
    "wof:placetype":"venue"
},
  "geometry": {"coordinates":[-4.393659,55.89835],"type":"Point"}
}