{
  "type": "Feature",
  "properties": {
    "iso:country":"GB",
    "sg:address":"Stratford Rd",
    "sg:city":"Bromsgrove",
    "sg:classifiers":[
        {
            "category":"Education",
            "subcategory":"Library",
            "type":"Public Place"
        }
    ],
    "sg:phone":"+44 1905 765025",
    "sg:postcode":"B60 1AP",
    "sg:province":"Worcestershire",
    "sg:tags":[
        "book"
    ],
    "wof:name":"Bromsgrove Library",
    "wof:placetype":"venue"
},
  "geometry": {"coordinates":[-2.054274,52.335381],"type":"Point"}
}