{
  "type": "Feature",
  "properties": {
    "addr:full":"Parc Celynin Carmarthen Carmarthenshire SA33 6BS",
    "addr:postcode":"sa33 6bs",
    "iso:country":"GB",
    "sg:address":"Parc Celynin",
    "sg:city":"Carmarthen",
    "sg:classifiers":[
        {
            "category":"Building & Trades",
            "subcategory":"Construction",
            "type":"Services"
        }
    ],
    "sg:phone":"+44 1267 253383",
    "sg:postcode":"SA33 6BS",
    "sg:province":"Carmarthenshire",
    "sg:tags":[
        "builder"
    ],
    "wof:name":"H A Rees",
    "wof:placetype":"venue"
},
  "geometry": {"coordinates":[-4.305277,51.936069],"type":"Point"}
}