{
  "type": "Feature",
  "properties": {
    "addr:full":"27 Clockhouse Place Putney Greater London SW15 2EL",
    "addr:housenumber":"27",
    "addr:postcode":"sw15 2el",
    "addr:street":"Clockhouse Place",
    "iso:country":"GB",
    "sg:address":"27 Clockhouse Place",
    "sg:city":"Putney",
    "sg:classifiers":[
        {
            "category":"Professional",
            "subcategory":"Lawyer & Legal Services",
            "type":"Services"
        }
    ],
    "sg:phone":"+44 20 8789 0551",
    "sg:postcode":"SW15 2EL",
    "sg:province":"Greater London",
    "wof:name":"Legal Advice Service",
    "wof:placetype":"venue"
},
  "geometry": {"coordinates":[-0.2156240046,51.4636535645],"type":"Point"}
}