{
  "type": "Feature",
  "properties": {
    "addr:full":"255 Tame Road, Witton Birmingham West Midlands B6 7HL",
    "addr:housenumber":"255",
    "addr:postcode":"7hl",
    "addr:street":"Tame Road",
    "iso:country":"GB",
    "sg:address":"255 Tame Road, Witton",
    "sg:city":"Birmingham",
    "sg:classifiers":[
        {
            "category":"Fast Food",
            "type":"Food & Drink"
        },
        {
            "category":"Wholesale",
            "subcategory":"Metals & Minerals",
            "type":"Manufacturing & Wholesale Goods"
        }
    ],
    "sg:phone":"+44 121 322 2141",
    "sg:postcode":"B6 7HL",
    "sg:province":"West Midlands",
    "sg:tags":[
        "aluminium",
        "away",
        "outlet",
        "stockholder",
        "meal",
        "take"
    ],
    "wof:name":"Friardown Ltd",
    "wof:placetype":"venue"
},
  "geometry": {"coordinates":[-1.8757339716,52.5086898804],"type":"Point"}
}