{
  "type": "Feature",
  "properties": {
    "addr:full":"1st Floor, 166 Cheetham Hill Road Manchester Greater Manchester M8 8LQ",
    "addr:housenumber":"166",
    "addr:postcode":"m8 8lq",
    "addr:street":"Cheetham Hill Road",
    "iso:country":"GB",
    "sg:address":"1st Floor, 166 Cheetham Hill Road",
    "sg:city":"Manchester",
    "sg:classifiers":[
        {
            "category":"Shopping",
            "subcategory":"Beauty & Cosmetics",
            "type":"Retail Goods"
        }
    ],
    "sg:phone":"+44 161 839 5136",
    "sg:postcode":"M8 8LQ",
    "sg:province":"Greater Manchester",
    "wof:name":"Scents & Sensuality Ltd.",
    "wof:placetype":"venue"
},
  "geometry": {"coordinates":[-2.238809,53.494656],"type":"Point"}
}