{
  "type": "Feature",
  "properties": {
    "iso:country":"GB",
    "sg:address":"Main Road, Bicknacre",
    "sg:city":"Chelmsford",
    "sg:classifiers":[
        {
            "category":"Real Estate",
            "subcategory":"Real Estate Agent",
            "type":"Services"
        }
    ],
    "sg:phone":"+44 1245 227775",
    "sg:postcode":"CM3 4HA",
    "sg:province":"Essex",
    "wof:name":"Premier Homes",
    "wof:placetype":"venue"
},
  "geometry": {"coordinates":[0.585767,51.694653],"type":"Point"}
}