{
  "type": "Feature",
  "properties": {
    "iso:country":"GB",
    "sg:address":"49 Watergate Street",
    "sg:city":"Chester",
    "sg:classifiers":[
        {
            "category":"Cafe",
            "type":"Food & Drink"
        }
    ],
    "sg:phone":"+44 1244 323003",
    "sg:postcode":"CH1 2LB",
    "sg:province":"Cheshire",
    "sg:tags":[
        "tea",
        "snack",
        "bar",
        "room"
    ],
    "wof:name":"The Kalldra Tea Room",
    "wof:placetype":"venue"
},
  "geometry": {"coordinates":[-2.8935658932,53.1898422241],"type":"Point"}
}