{
  "type": "Feature",
  "properties": {
    "addr:full":"34 Cavendish Road, Trimley Felixstowe Suffolk IP11 0RR",
    "addr:housenumber":"34",
    "addr:postcode":"ip11 0rr",
    "addr:street":"Cavendish Road",
    "iso:country":"GB",
    "sg:address":"34 Cavendish Road, Trimley",
    "sg:city":"Felixstowe",
    "sg:classifiers":[
        {
            "category":"Building & Trades",
            "subcategory":"Construction",
            "type":"Services"
        }
    ],
    "sg:postcode":"IP11 0RR",
    "sg:province":"Suffolk",
    "sg:tags":[
        "decorator",
        "painter"
    ],
    "wof:name":"East Coast Painting",
    "wof:placetype":"venue"
},
  "geometry": {"coordinates":[1.310066,51.991535],"type":"Point"}
}