{
  "type": "Feature",
  "properties": {
    "addr:full":"60 Cowbridge Road East, Canton Cardiff Cardiff CF11 9DU",
    "addr:housenumber":"60",
    "addr:postcode":"cf11 9du",
    "addr:street":"Cowbridge Road East",
    "iso:country":"GB",
    "sg:address":"60 Cowbridge Road East, Canton",
    "sg:city":"Cardiff",
    "sg:classifiers":[
        {
            "category":"Professional",
            "subcategory":"Engineering",
            "type":"Services"
        }
    ],
    "sg:postcode":"CF11 9DU",
    "sg:province":"Cardiff",
    "sg:tags":[
        "contractor",
        "electrical",
        "engineer"
    ],
    "wof:name":"Electrical Excellence Contractors (E E C)",
    "wof:placetype":"venue"
},
  "geometry": {"coordinates":[-3.195199,51.481464],"type":"Point"}
}