{
  "type": "Feature",
  "properties": {
    "addr:full":"Tamasin, Hicks La Camberley Hampshire GU17 0DG",
    "addr:postcode":"gu17 0dg",
    "iso:country":"GB",
    "sg:address":"Tamasin, Hicks La",
    "sg:city":"Camberley",
    "sg:classifiers":[
        {
            "category":"Building & Trades",
            "subcategory":"Landscaping Services",
            "type":"Services"
        }
    ],
    "sg:phone":"+44 1252 861200",
    "sg:postcode":"GU17 0DG",
    "sg:province":"Hampshire",
    "sg:tags":[
        "forestry",
        "tree"
    ],
    "wof:name":"Squirrels Tree Services",
    "wof:placetype":"venue"
},
  "geometry": {"coordinates":[-0.79587,51.336281],"type":"Point"}
}