{
  "type": "Feature",
  "properties": {
    "iso:country":"GB",
    "sg:address":"Riseholme Cottage, Seven Hills Road",
    "sg:city":"Cobham",
    "sg:classifiers":[
        {
            "category":"Professional",
            "subcategory":"Accounting & Tax Preparation",
            "type":"Services"
        }
    ],
    "sg:phone":"+44 1932 863219",
    "sg:postcode":"KT11 1ES",
    "sg:province":"Surrey",
    "sg:tags":[
        "accountant",
        "activity"
    ],
    "wof:name":"Roy Bird Associates Ltd.",
    "wof:placetype":"venue"
},
  "geometry": {"coordinates":[-0.434679,51.334129],"type":"Point"}
}