{
  "type": "Feature",
  "properties": {
    "addr:full":"47 Acklam Road London Greater London W10 5YU",
    "addr:housenumber":"47",
    "addr:postcode":"w10 5yu",
    "addr:street":"Acklam Road",
    "iso:country":"GB",
    "sg:address":"47 Acklam Road",
    "sg:city":"London",
    "sg:classifiers":[
        {
            "category":"Farming",
            "subcategory":"Nursery",
            "type":"Manufacturing & Wholesale Goods"
        },
        {
            "category":"Government",
            "subcategory":"Office",
            "type":"Public Place"
        }
    ],
    "sg:phone":"+44 20 8968 5622",
    "sg:postcode":"W10 5YU",
    "sg:province":"Greater London",
    "sg:tags":[
        "local",
        "creche"
    ],
    "wof:name":"Ainsworth Nursery School",
    "wof:placetype":"venue"
},
  "geometry": {"coordinates":[-0.20623,51.519772],"type":"Point"}
}