{
  "type": "Feature",
  "properties": {
    "iso:country":"GB",
    "sg:address":"Drummond Road",
    "sg:city":"Bromsgrove",
    "sg:classifiers":[
        {
            "category":"Education",
            "subcategory":"School",
            "type":"Public Place"
        }
    ],
    "sg:phone":"+44 1527 876026",
    "sg:postcode":"B60 2ET",
    "sg:province":"Worcestershire",
    "sg:tags":[
        "local",
        "authority"
    ],
    "wof:name":"Aston Fields Middle School",
    "wof:placetype":"venue"
},
  "geometry": {"coordinates":[-2.046034,52.327179],"type":"Point"}
}