{
  "type": "Feature",
  "properties": {
    "addr:full":"7a Court Road Uxbridge Greater London UB10 8TF",
    "addr:housenumber":"7a",
    "addr:postcode":"ub10 8tf",
    "addr:street":"Court Road",
    "iso:country":"GB",
    "sg:address":"7a Court Road",
    "sg:city":"Uxbridge",
    "sg:classifiers":[
        {
            "category":"Arts & Performance",
            "subcategory":"Music",
            "type":"Entertainment"
        }
    ],
    "sg:phone":"+44 1895 677481",
    "sg:postcode":"UB10 8TF",
    "sg:province":"Greater London",
    "sg:tags":[
        "mobile",
        "disco"
    ],
    "wof:name":"Sound Music",
    "wof:placetype":"venue"
},
  "geometry": {"coordinates":[-0.4474110007,51.5591773987],"type":"Point"}
}