{
  "type": "Feature",
  "properties": {
    "iso:country":"GB",
    "sg:address":"13 Ravine Rd",
    "sg:city":"Poole",
    "sg:classifiers":[
        {
            "category":"Wholesale",
            "subcategory":"Photographic Equipment",
            "type":"Manufacturing & Wholesale Goods"
        }
    ],
    "sg:phone":"+44 1202 709771",
    "sg:postcode":"BH13 7HS",
    "sg:province":"Dorset",
    "sg:tags":[
        "w'sale"
    ],
    "wof:name":"Photovend UK Ltd",
    "wof:placetype":"venue"
},
  "geometry": {"coordinates":[-1.920451,50.705151],"type":"Point"}
}