{
  "type": "Feature",
  "properties": {
    "iso:country":"GB",
    "sg:address":"149 New Road, Booker",
    "sg:city":"High Wycombe",
    "sg:classifiers":[
        {
            "category":"Organizations",
            "subcategory":"Community Association",
            "type":"Services"
        }
    ],
    "sg:postcode":"HP12 4RH",
    "sg:province":"Buckinghamshire",
    "sg:tags":[
        "relation",
        "public"
    ],
    "wof:name":"Palmer & Rose Partnership",
    "wof:placetype":"venue"
},
  "geometry": {"coordinates":[-0.783731997,51.61951828],"type":"Point"}
}