{
  "type": "Feature",
  "properties": {
    "addr:full":"174 Heaton Road Newcastle-upon-tyne Tyne and Wear NE6 5HP",
    "addr:housenumber":"174",
    "addr:postcode":"ne6 5hp",
    "addr:street":"Heaton Road",
    "iso:country":"GB",
    "sg:address":"174 Heaton Road",
    "sg:city":"Newcastle-upon-tyne",
    "sg:classifiers":[
        {
            "category":"Shopping",
            "subcategory":"News",
            "type":"Retail Goods"
        }
    ],
    "sg:phone":"+44 191 240 0606",
    "sg:postcode":"NE6 5HP",
    "sg:province":"Tyne and Wear",
    "sg:tags":[
        "newsagent"
    ],
    "wof:name":"Westcott Newsagency",
    "wof:placetype":"venue"
},
  "geometry": {"coordinates":[-1.581692,54.984455],"type":"Point"}
}