{
  "type": "Feature",
  "properties": {
    "addr:full":"18 The Harlequin Watford Hertfordshire WD17 2TH",
    "addr:housenumber":"18",
    "addr:postcode":"wd17 2th",
    "addr:street":"The Harlequin",
    "iso:country":"GB",
    "sg:address":"18 The Harlequin",
    "sg:city":"Watford",
    "sg:classifiers":[
        {
            "category":"Shopping",
            "subcategory":"Clothing, Apparel, & Fashions",
            "type":"Retail Goods"
        }
    ],
    "sg:phone":"+44 1923 247233",
    "sg:postcode":"WD17 2TH",
    "sg:province":"Hertfordshire",
    "sg:tags":[
        "ladieswear"
    ],
    "wof:name":"Dorothy Perkins",
    "wof:placetype":"venue"
},
  "geometry": {"coordinates":[-0.3936969936,51.6544036865],"type":"Point"}
}