{
  "type": "Feature",
  "properties": {
    "addr:full":"26 Seymour St West End Greater London W1H 5WD",
    "addr:housenumber":"26",
    "addr:postcode":"w1h 5wd",
    "addr:street":"Seymour St",
    "iso:country":"GB",
    "sg:address":"26 Seymour St",
    "sg:city":"West End",
    "sg:classifiers":[
        {
            "category":"Professional",
            "subcategory":"Detective & Security Services",
            "type":"Services"
        }
    ],
    "sg:phone":"+44 20 7224 8424",
    "sg:postcode":"W1H 5WD",
    "sg:province":"Greater London",
    "wof:name":"Gordon Wilson Associates",
    "wof:placetype":"venue"
},
  "geometry": {"coordinates":[-0.161111,51.515202],"type":"Point"}
}