{
  "type": "Feature",
  "properties": {
    "addr:full":"140 Coniscliffe Rd Darlington Durham DL3 7RT",
    "addr:housenumber":"140",
    "addr:postcode":"dl3 7rt",
    "addr:street":"Coniscliffe Rd",
    "iso:country":"GB",
    "sg:address":"140 Coniscliffe Rd",
    "sg:city":"Darlington",
    "sg:classifiers":[
        {
            "category":"Professional",
            "subcategory":"Business Services",
            "type":"Services"
        }
    ],
    "sg:postcode":"DL3 7RT",
    "sg:province":"Durham",
    "sg:tags":[
        "holding"
    ],
    "wof:name":"Star Wood (Holdings) Ltd",
    "wof:placetype":"venue"
},
  "geometry": {"coordinates":[-1.5664600134,54.5205764771],"type":"Point"}
}