{
  "type": "Feature",
  "properties": {
    "addr:full":"Chesterfield Road, Calow Chesterfield Derbyshire S44 5UN",
    "addr:postcode":"s44 5un",
    "addr:street":"Chesterfield Road",
    "iso:country":"GB",
    "sg:address":"Chesterfield Road, Calow",
    "sg:city":"Chesterfield",
    "sg:classifiers":[
        {
            "category":"Wholesale",
            "subcategory":"Meat",
            "type":"Manufacturing & Wholesale Goods"
        }
    ],
    "sg:postcode":"S44 5UN",
    "sg:province":"Derbyshire",
    "sg:tags":[
        "-"
    ],
    "wof:name":"R B Elliott & Son",
    "wof:placetype":"venue"
},
  "geometry": {"coordinates":[-1.3587440252,53.2332344055],"type":"Point"}
}