{
  "type": "Feature",
  "properties": {
    "iso:country":"GB",
    "sg:address":"390 Godstone Rd",
    "sg:city":"Kenley",
    "sg:classifiers":[
        {
            "category":"Building & Trades",
            "subcategory":"Plumbing",
            "type":"Services"
        }
    ],
    "sg:postcode":"CR8 5BH",
    "sg:province":"Surrey",
    "sg:tags":[
        "heating"
    ],
    "wof:name":"G.K. Plumbing & Heating",
    "wof:placetype":"venue"
},
  "geometry": {"coordinates":[-0.084825,51.317478],"type":"Point"}
}