{
  "type": "Feature",
  "properties": {
    "iso:country":"GB",
    "sg:address":"21 Avenue Nozay, Broughton",
    "sg:city":"Brigg",
    "sg:classifiers":[
        {
            "category":"Building & Trades",
            "subcategory":"Construction",
            "type":"Services"
        }
    ],
    "sg:postcode":"DN20 0TR",
    "sg:province":"Lincolnshire",
    "sg:tags":[
        "builder"
    ],
    "wof:name":"Granthams Removals",
    "wof:placetype":"venue"
},
  "geometry": {"coordinates":[-0.549236,53.565613],"type":"Point"}
}