{
  "type": "Feature",
  "properties": {
    "iso:country":"GB",
    "sg:address":"Bolton Crescent",
    "sg:city":"London",
    "sg:classifiers":[
        {
            "category":"Social Services",
            "type":"Services"
        }
    ],
    "sg:phone":"+44 20 7735 1819",
    "sg:postcode":"SE5 0SE",
    "sg:province":"Greater London",
    "sg:tags":[
        "need",
        "disability",
        "special"
    ],
    "wof:name":"Lambeth Council (Mayor & Burgessess of)",
    "wof:placetype":"venue"
},
  "geometry": {"coordinates":[-0.10791,51.480412],"type":"Point"}
}