{
  "type": "Feature",
  "properties": {
    "addr:full":"Hartfield, Thorne Barton Barn, Chesham Road Chesham Buckinghamshire HP5 3PQ",
    "addr:postcode":"hp5 3pq",
    "addr:street":"Chesham Road",
    "iso:country":"GB",
    "sg:address":"Hartfield, Thorne Barton Barn, Chesham Road",
    "sg:city":"Chesham",
    "sg:classifiers":[
        {
            "category":"Mining & Drilling",
            "type":"Manufacturing & Wholesale Goods"
        }
    ],
    "sg:phone":"+44 1494 792000",
    "sg:postcode":"HP5 3PQ",
    "sg:province":"Buckinghamshire",
    "sg:tags":[
        "contractor"
    ],
    "wof:name":"H D Services Ltd.",
    "wof:placetype":"venue"
},
  "geometry": {"coordinates":[-0.609333,51.710537],"type":"Point"}
}