{
  "type": "Feature",
  "properties": {
    "addr:full":"Park View, Appleford Dr Abingdon Oxfordshire OX14 2BX",
    "addr:postcode":"ox14 2bx",
    "addr:street":"Park;Appleford Dr",
    "iso:country":"GB",
    "sg:address":"Park View, Appleford Dr",
    "sg:city":"Abingdon",
    "sg:classifiers":[
        {
            "category":"Building & Trades",
            "subcategory":"Construction",
            "type":"Services"
        }
    ],
    "sg:postcode":"OX14 2BX",
    "sg:province":"Oxfordshire",
    "sg:tags":[
        "builder"
    ],
    "wof:name":"Litt,Stephen P,",
    "wof:placetype":"venue"
},
  "geometry": {"coordinates":[-1.2710549831,51.6864929199],"type":"Point"}
}