{
  "type": "Feature",
  "properties": {
    "iso:country":"GB",
    "sg:address":"Gwastad Hall, Llay Road, Cefn-y-bedd",
    "sg:city":"Wrexham",
    "sg:classifiers":[
        {
            "category":"Farming",
            "subcategory":"Nursery",
            "type":"Manufacturing & Wholesale Goods"
        }
    ],
    "sg:phone":"+44 1978 761819",
    "sg:postcode":"LL12 9UH",
    "sg:province":"Wrexham",
    "sg:tags":[
        "creche"
    ],
    "wof:name":"A B C Private Nursery",
    "wof:placetype":"venue"
},
  "geometry": {"coordinates":[-3.031069,53.097919],"type":"Point"}
}