{
  "type": "Feature",
  "properties": {
    "addr:full":"3 Beech Crescent, Darrington Pontefract North Yorkshire WF8 3AD",
    "addr:housenumber":"3",
    "addr:postcode":"wf8 3ad",
    "addr:street":"Beech Crescent",
    "iso:country":"GB",
    "sg:address":"3 Beech Crescent, Darrington",
    "sg:city":"Pontefract",
    "sg:classifiers":[
        {
            "category":"Home & Garden",
            "subcategory":"Home Furnishings",
            "type":"Retail Goods"
        }
    ],
    "sg:phone":"+44 1977 790677",
    "sg:postcode":"WF8 3AD",
    "sg:province":"North Yorkshire",
    "sg:tags":[
        "furnishers",
        "planner",
        "kitchen"
    ],
    "wof:name":"K Harris",
    "wof:placetype":"venue"
},
  "geometry": {"coordinates":[-1.274155,53.67662],"type":"Point"}
}