{
  "type": "Feature",
  "properties": {
    "addr:full":"Old Ice Factory, Rolle Street Barnstaple Devon EX31 1JP",
    "addr:postcode":"ex31 1jp",
    "addr:street":"Rolle Street",
    "iso:country":"GB",
    "sg:address":"Old Ice Factory, Rolle Street",
    "sg:city":"Barnstaple",
    "sg:classifiers":[
        {
            "category":"Manufacturing",
            "subcategory":"Glass & Minerals",
            "type":"Manufacturing & Wholesale Goods"
        }
    ],
    "sg:phone":"+44 1271 374722",
    "sg:postcode":"EX31 1JP",
    "sg:province":"Devon",
    "sg:tags":[
        "fibre",
        "moulding"
    ],
    "wof:name":"Neptune Glassfibre Mouldings",
    "wof:placetype":"venue"
},
  "geometry": {"coordinates":[-4.06482,51.083969],"type":"Point"}
}