{
  "type": "Feature",
  "properties": {
    "iso:country":"GB",
    "sg:address":"144 St Michaels Hill",
    "sg:city":"Bristol",
    "sg:classifiers":[
        {
            "category":"Personal",
            "subcategory":"Beauty Salon",
            "type":"Services"
        }
    ],
    "sg:phone":"+44 117 925 0094",
    "sg:postcode":"BS2 8DA",
    "sg:province":"City of Bristol",
    "sg:tags":[
        "unisex",
        "hairdresser"
    ],
    "wof:name":"Ralph's Barber Shop",
    "wof:placetype":"venue"
},
  "geometry": {"coordinates":[-2.6018249989,51.4610176086],"type":"Point"}
}