{
  "type": "Feature",
  "properties": {
    "addr:full":"1 Agar Street Bradford West Yorkshire BD8 9QL",
    "addr:housenumber":"1",
    "addr:postcode":"bd8 9ql",
    "addr:street":"Agar Street",
    "iso:country":"GB",
    "sg:address":"1 Agar Street",
    "sg:city":"Bradford",
    "sg:classifiers":[
        {
            "category":"Recreation",
            "subcategory":"Dog Park",
            "type":"Entertainment"
        },
        {
            "category":"Retail",
            "subcategory":"Animal Services",
            "type":"Services"
        }
    ],
    "sg:phone":"+44 1274 543231",
    "sg:postcode":"BD8 9QL",
    "sg:province":"West Yorkshire",
    "sg:tags":[
        "grooming",
        "clipping"
    ],
    "wof:name":"Brush Puppies",
    "wof:placetype":"venue"
},
  "geometry": {"coordinates":[-1.7889120579,53.7995834351],"type":"Point"}
}