{
  "type": "Feature",
  "properties": {
    "addr:full":"96 Edgbaston Road Birmingham West Midlands B12 9QA",
    "addr:housenumber":"96",
    "addr:postcode":"b12 9qa",
    "addr:street":"Edgbaston Road",
    "iso:country":"GB",
    "sg:address":"96 Edgbaston Road",
    "sg:city":"Birmingham",
    "sg:classifiers":[
        {
            "category":"Travel",
            "subcategory":"Hostel",
            "type":"Entertainment"
        }
    ],
    "sg:phone":"+44 121 440 2657",
    "sg:postcode":"B12 9QA",
    "sg:province":"West Midlands",
    "wof:name":"Elliott House Probation Hostel",
    "wof:placetype":"venue"
},
  "geometry": {"coordinates":[-1.89775002,52.4543418884],"type":"Point"}
}