{
  "type": "Feature",
  "properties": {
    "addr:full":"Woodfield Road Harrogate North Yorkshire HG1 4HZ",
    "addr:postcode":"hg1 4hz",
    "addr:street":"Woodfield Road",
    "iso:country":"GB",
    "sg:address":"Woodfield Road",
    "sg:city":"Harrogate",
    "sg:classifiers":[
        {
            "category":"Education",
            "subcategory":"School",
            "type":"Public Place"
        },
        {
            "category":"Government",
            "subcategory":"Office",
            "type":"Public Place"
        }
    ],
    "sg:phone":"+44 1423 566494",
    "sg:postcode":"HG1 4HZ",
    "sg:province":"North Yorkshire",
    "sg:tags":[
        "local",
        "authority"
    ],
    "wof:name":"Woodfield County Primary School",
    "wof:placetype":"venue"
},
  "geometry": {"coordinates":[-1.5232640505,54.0130310059],"type":"Point"}
}