{
  "type": "Feature",
  "properties": {
    "addr:full":"28 Temple Street Aylesbury Buckinghamshire HP20 2RQ",
    "addr:housenumber":"28",
    "addr:postcode":"hp20 2rq",
    "addr:street":"Temple Street",
    "iso:country":"GB",
    "sg:address":"28 Temple Street",
    "sg:city":"Aylesbury",
    "sg:classifiers":[
        {
            "category":"Real Estate",
            "subcategory":"Real Estate Agent",
            "type":"Services"
        }
    ],
    "sg:phone":"+44 1296 336227",
    "sg:postcode":"HP20 2RQ",
    "sg:province":"Buckinghamshire",
    "wof:name":"Wilkinsons",
    "wof:placetype":"venue"
},
  "geometry": {"coordinates":[-0.814369,51.816521],"type":"Point"}
}