{
  "type": "Feature",
  "properties": {
    "addr:full":"Weavers Yard, Approach Road, Manselton Swansea Swansea SA5 8NL",
    "addr:postcode":"sa5 8nl",
    "addr:street":"Weavers Yard Approach Road Manselton",
    "iso:country":"GB",
    "sg:address":"Weavers Yard, Approach Road, Manselton",
    "sg:city":"Swansea",
    "sg:classifiers":[
        {
            "category":"Building & Trades",
            "subcategory":"Cleaning & Sanitation",
            "type":"Services"
        }
    ],
    "sg:phone":"+44 1792 652419",
    "sg:postcode":"SA5 8NL",
    "sg:province":"Swansea",
    "sg:tags":[
        "commercial"
    ],
    "wof:name":"A S E Power Cleaning",
    "wof:placetype":"venue"
},
  "geometry": {"coordinates":[-3.951390028,51.6360397339],"type":"Point"}
}