{
  "type": "Feature",
  "properties": {
    "addr:full":"Aspen, Stone House Rd, Halstead Sevenoaks Kent TN14 7HN",
    "addr:postcode":"tn14 7hn",
    "addr:street":"Aspen Stone House Rd",
    "iso:country":"GB",
    "sg:address":"Aspen, Stone House Rd, Halstead",
    "sg:city":"Sevenoaks",
    "sg:classifiers":[
        {
            "category":"Professional",
            "subcategory":"Engineering",
            "type":"Services"
        }
    ],
    "sg:phone":"+44 1689 862385",
    "sg:postcode":"TN14 7HN",
    "sg:province":"Kent",
    "sg:tags":[
        "contractor",
        "electrical",
        "engineer"
    ],
    "wof:name":"J A Installations",
    "wof:placetype":"venue"
},
  "geometry": {"coordinates":[0.133681,51.328606],"type":"Point"}
}