{
  "type": "Feature",
  "properties": {
    "addr:full":"61 Lowlands Avenue Sutton Coldfield Staffordshire B74 3QW",
    "addr:housenumber":"61",
    "addr:postcode":"b74 3qw",
    "addr:street":"Lowlands Avenue",
    "iso:country":"GB",
    "sg:address":"61 Lowlands Avenue",
    "sg:city":"Sutton Coldfield",
    "sg:classifiers":[
        {
            "category":"Retail",
            "subcategory":"Driving School",
            "type":"Services"
        }
    ],
    "sg:phone":"+44 121 353 0805",
    "sg:postcode":"B74 3QW",
    "sg:province":"Staffordshire",
    "wof:name":"Kings Ways School Of Motoring",
    "wof:placetype":"venue"
},
  "geometry": {"coordinates":[-1.893335,52.578087],"type":"Point"}
}