{
  "type": "Feature",
  "properties": {
    "iso:country":"GB",
    "sg:address":"19 Greenfields, Whetstone",
    "sg:city":"Leicester",
    "sg:classifiers":[
        {
            "category":"Personal",
            "subcategory":"Tanning Parlor",
            "type":"Services"
        }
    ],
    "sg:phone":"+44 116 286 4296",
    "sg:postcode":"LE8 6NY",
    "sg:province":"Leicestershire",
    "sg:tags":[
        "sunbeds"
    ],
    "wof:name":"Dial-A-Tan",
    "wof:placetype":"venue"
},
  "geometry": {"coordinates":[-1.1819159985,52.5711593628],"type":"Point"}
}