{
  "type": "Feature",
  "properties": {
    "iso:country":"GB",
    "sg:address":"2 Westfield, Clevedon Rd",
    "sg:city":"Bristol",
    "sg:classifiers":[
        {
            "category":"Building & Trades",
            "subcategory":"Construction",
            "type":"Services"
        }
    ],
    "sg:phone":"+44 1275 849152",
    "sg:postcode":"BS20 8PR",
    "sg:province":"Somerset",
    "sg:tags":[
        "decorator",
        "painter"
    ],
    "wof:name":"R A Gordon",
    "wof:placetype":"venue"
},
  "geometry": {"coordinates":[-2.79574,51.46497],"type":"Point"}
}