{
  "type": "Feature",
  "properties": {
    "iso:country":"GB",
    "sg:address":"10 New Walk, Kingfisher Shopping Centre",
    "sg:city":"Redditch",
    "sg:classifiers":[
        {
            "category":"Travel",
            "subcategory":"Travel Agent",
            "type":"Entertainment"
        }
    ],
    "sg:phone":"+44 1527 64249",
    "sg:postcode":"B97 4YP",
    "sg:province":"Warwickshire",
    "wof:name":"Midland Co-Op Travel",
    "wof:placetype":"venue"
},
  "geometry": {"coordinates":[-1.941267,52.30727],"type":"Point"}
}