{
  "type": "Feature",
  "properties": {
    "addr:full":"Coney Island, Foreshore Road Scarborough North Yorkshire YO11 1PB",
    "addr:postcode":"yo11 1pb",
    "addr:street":"Foreshore Road",
    "iso:country":"GB",
    "sg:address":"Coney Island, Foreshore Road",
    "sg:city":"Scarborough",
    "sg:classifiers":[
        {
            "category":"Community Center",
            "type":"Public Place"
        }
    ],
    "sg:phone":"+44 1723 365765",
    "sg:postcode":"YO11 1PB",
    "sg:province":"North Yorkshire",
    "sg:tags":[
        "recreation",
        "leisure",
        "centre"
    ],
    "wof:name":"Lord Corrigan Promotions Ltd.",
    "wof:placetype":"venue"
},
  "geometry": {"coordinates":[-0.3943099976,54.2834510803],"type":"Point"}
}