{
  "type": "Feature",
  "properties": {
    "iso:country":"GB",
    "sg:address":"2 Station Road",
    "sg:city":"Solihull",
    "sg:classifiers":[
        {
            "category":"Communications",
            "type":"Services"
        }
    ],
    "sg:phone":"+44 121 454 4141",
    "sg:postcode":"B91 3SB",
    "sg:province":"West Midlands",
    "sg:tags":[
        "broadcasting"
    ],
    "wof:name":"Gold Stone Television Ltd.",
    "wof:placetype":"venue"
},
  "geometry": {"coordinates":[-1.7795549631,52.4140548706],"type":"Point"}
}