{
  "type": "Feature",
  "properties": {
    "iso:country":"GB",
    "sg:address":"Dungewood Farm, Dungewood Lane, Shorwell",
    "sg:city":"Newport",
    "sg:classifiers":[
        {
            "category":"Farming",
            "subcategory":"Farm",
            "type":"Manufacturing & Wholesale Goods"
        }
    ],
    "sg:phone":"+44 1983 551226",
    "sg:postcode":"PO30 3LJ",
    "sg:province":"Isle of Wight",
    "sg:tags":[
        "mixed",
        "crop"
    ],
    "wof:name":"D L Morris",
    "wof:placetype":"venue"
},
  "geometry": {"coordinates":[-1.3547190428,50.6440582275],"type":"Point"}
}