{
  "type": "Feature",
  "properties": {
    "iso:country":"GB",
    "sg:address":"31 Upper Street",
    "sg:city":"London",
    "sg:classifiers":[
        {
            "category":"Food & Beverages",
            "subcategory":"Specialty",
            "type":"Retail Goods"
        }
    ],
    "sg:phone":"+44 20 7359 9117",
    "sg:postcode":"N1 0PN",
    "sg:province":"Greater London",
    "sg:tags":[
        "product",
        "health"
    ],
    "wof:name":"Holland & Barrett",
    "wof:placetype":"venue"
},
  "geometry": {"coordinates":[-0.10518,51.534424],"type":"Point"}
}