{
  "type": "Feature",
  "properties": {
    "addr:full":"Warren Road, Brean Burnham-on-sea Somerset TA8 2RP",
    "addr:postcode":"ta8 2rp",
    "addr:street":"Warren Road",
    "iso:country":"GB",
    "sg:address":"Warren Road, Brean",
    "sg:city":"Burnham-on-sea",
    "sg:classifiers":[
        {
            "category":"Bars & Pubs",
            "type":"Food & Drink"
        }
    ],
    "sg:phone":"+44 1278 751336",
    "sg:postcode":"TA8 2RP",
    "sg:province":"Somerset",
    "sg:tags":[
        "pubs",
        "inn"
    ],
    "wof:name":"The Beachcomber",
    "wof:placetype":"venue"
},
  "geometry": {"coordinates":[-3.0106320381,51.2938652039],"type":"Point"}
}