{
  "type": "Feature",
  "properties": {
    "iso:country":"GB",
    "sg:address":"57 Alma Road, Newhall",
    "sg:city":"Swadlincote",
    "sg:classifiers":[
        {
            "category":"Personal",
            "subcategory":"Beauty Salon",
            "type":"Services"
        },
        {
            "category":"Personal",
            "subcategory":"Barber",
            "type":"Services"
        }
    ],
    "sg:phone":"+44 1283 216645",
    "sg:postcode":"DE11 0SD",
    "sg:province":"Derbyshire",
    "sg:tags":[
        "unisex",
        "hairdresser"
    ],
    "wof:name":"The Warehouse Hair Salon",
    "wof:placetype":"venue"
},
  "geometry": {"coordinates":[-1.5758579969,52.7817955017],"type":"Point"}
}