{
  "type": "Feature",
  "properties": {
    "addr:full":"2 High Cross Road Newport Caerphilly NP10 9SJ",
    "addr:housenumber":"2",
    "addr:postcode":"np10 9sj",
    "addr:street":"High Cross Road",
    "iso:country":"GB",
    "sg:address":"2 High Cross Road",
    "sg:city":"Newport",
    "sg:classifiers":[
        {
            "category":"Shopping",
            "subcategory":"Department Store",
            "type":"Retail Goods"
        },
        {
            "category":"Government",
            "subcategory":"Post Office",
            "type":"Public Place"
        }
    ],
    "sg:postcode":"NP10 9SJ",
    "sg:province":"Caerphilly",
    "wof:name":"High Cross Road Post Office",
    "wof:placetype":"venue"
},
  "geometry": {"coordinates":[-3.040074,51.581539],"type":"Point"}
}