{
  "type": "Feature",
  "properties": {
    "addr:full":"108 Aldebury Road Maidenhead Berkshire SL6 7HE",
    "addr:housenumber":"108",
    "addr:postcode":"sl6 7he",
    "addr:street":"Aldebury Road",
    "iso:country":"GB",
    "sg:address":"108 Aldebury Road",
    "sg:city":"Maidenhead",
    "sg:classifiers":[
        {
            "category":"Shopping",
            "subcategory":"Musical Instruments",
            "type":"Retail Goods"
        }
    ],
    "sg:phone":"+44 1628 637294",
    "sg:postcode":"SL6 7HE",
    "sg:province":"Berkshire",
    "sg:tags":[
        "piano",
        "tuning",
        "maintenance"
    ],
    "wof:name":"John Loveridge",
    "wof:placetype":"venue"
},
  "geometry": {"coordinates":[-0.7239739895,51.5375022888],"type":"Point"}
}