{
  "type": "Feature",
  "properties": {
    "iso:country":"GB",
    "sg:address":"Furnace Mill Farm",
    "sg:city":"Crook",
    "sg:classifiers":[
        {
            "category":"Farming",
            "subcategory":"Dairy Farm",
            "type":"Manufacturing & Wholesale Goods"
        }
    ],
    "sg:postcode":"DL15 0RJ",
    "sg:province":"Durham",
    "wof:name":"N Basey & Son",
    "wof:placetype":"venue"
},
  "geometry": {"coordinates":[-1.748794,54.714363],"type":"Point"}
}