{
  "type": "Feature",
  "properties": {
    "addr:full":"Dundyvan Road Coatbridge North Lanarkshire ML5 1DN",
    "addr:postcode":"ml5 1dn",
    "addr:street":"Dundyvan Road",
    "iso:country":"GB",
    "sg:address":"Dundyvan Road",
    "sg:city":"Coatbridge",
    "sg:classifiers":[
        {
            "category":"Government",
            "subcategory":"Office",
            "type":"Public Place"
        }
    ],
    "sg:phone":"+44 1236 710069",
    "sg:postcode":"ML5 1DN",
    "sg:province":"North Lanarkshire",
    "sg:tags":[
        "local"
    ],
    "wof:name":"Charlotte Toal Centre",
    "wof:placetype":"venue"
},
  "geometry": {"coordinates":[-4.0364041328,55.8595809937],"type":"Point"}
}