{
  "type": "Feature",
  "properties": {
    "addr:full":"St Davids Close Pontypool Monmouthshire NP4 8BA",
    "addr:postcode":"pontypool;np4 8ba",
    "addr:street":"St Davids Close",
    "iso:country":"GB",
    "sg:address":"St Davids Close",
    "sg:city":"Pontypool",
    "sg:classifiers":[
        {
            "category":"Organizations",
            "subcategory":"Non-profit Organization",
            "type":"Services"
        }
    ],
    "sg:phone":"+44 1495 750457",
    "sg:postcode":"NP4 8BA",
    "sg:province":"Monmouthshire",
    "sg:tags":[
        "organisation",
        "voluntary",
        "charity"
    ],
    "wof:name":"Sense Cymru",
    "wof:placetype":"venue"
},
  "geometry": {"coordinates":[-3.0366148949,51.7051048279],"type":"Point"}
}