{
  "type": "Feature",
  "properties": {
    "addr:full":"Unit 2, Fenlake Industrial Estate, Fenlake Road Bedford Bedfordshire MK42 0BH",
    "addr:housenumber":"unit 2",
    "addr:postcode":"mk42 0bh",
    "addr:street":"Fenlake Industrial Estate Fenlake Road",
    "iso:country":"GB",
    "sg:address":"Unit 2, Fenlake Industrial Estate, Fenlake Road",
    "sg:city":"Bedford",
    "sg:classifiers":[
        {
            "category":"Home & Garden",
            "subcategory":"Home Furnishings",
            "type":"Retail Goods"
        }
    ],
    "sg:phone":"+44 1234 355540",
    "sg:postcode":"MK42 0BH",
    "sg:province":"Bedfordshire",
    "sg:tags":[
        "furnishers",
        "planner",
        "kitchen"
    ],
    "wof:name":"Q P Interiors",
    "wof:placetype":"venue"
},
  "geometry": {"coordinates":[-0.458504,52.12896],"type":"Point"}
}