{
  "type": "Feature",
  "properties": {
    "addr:full":"Selkirk Close Wimborne Dorset BH21 1TW",
    "addr:postcode":"bh21 1tw",
    "addr:street":"Selkirk Close",
    "iso:country":"GB",
    "sg:address":"Selkirk Close",
    "sg:city":"Wimborne",
    "sg:classifiers":[
        {
            "category":"Social Services",
            "subcategory":"Adult Care",
            "type":"Services"
        },
        {
            "category":"Social Services",
            "subcategory":"Retirement Home",
            "type":"Services"
        }
    ],
    "sg:phone":"+44 1202 888883",
    "sg:postcode":"BH21 1TW",
    "sg:province":"Dorset",
    "sg:tags":[
        "housing",
        "sheltered",
        "accommodation"
    ],
    "wof:name":"Selkirk Close Sheltered Housing",
    "wof:placetype":"venue"
},
  "geometry": {"coordinates":[-1.9672379494,50.7826080322],"type":"Point"}
}