{
  "type": "Feature",
  "properties": {
    "addr:full":"2 Kidmore Rd, Caversham Reading Berkshire RG4 7LU",
    "addr:housenumber":"2",
    "addr:postcode":"rg4 7lu",
    "addr:street":"Kidmore Rd",
    "iso:country":"GB",
    "sg:address":"2 Kidmore Rd, Caversham",
    "sg:city":"Reading",
    "sg:classifiers":[
        {
            "category":"Social Services",
            "subcategory":"Retirement Home",
            "type":"Services"
        }
    ],
    "sg:phone":"+44 118 947 6882",
    "sg:postcode":"RG4 7LU",
    "sg:province":"Berkshire",
    "sg:tags":[
        "residential",
        "care"
    ],
    "wof:name":"Goldendale Retirement Home",
    "wof:placetype":"venue"
},
  "geometry": {"coordinates":[-0.979379,51.471733],"type":"Point"}
}