{
  "type": "Feature",
  "properties": {
    "iso:country":"GB",
    "sg:address":"73 Ferry Rd",
    "sg:city":"Edinburgh",
    "sg:classifiers":[
        {
            "category":"Organizations",
            "subcategory":"Non-profit Organization",
            "type":"Services"
        }
    ],
    "sg:postcode":"EH6 4AQ",
    "sg:province":"City of Edinburgh",
    "sg:tags":[
        "organisation",
        "voluntary",
        "charity"
    ],
    "wof:name":"Ymca Edinburgh",
    "wof:placetype":"venue"
},
  "geometry": {"coordinates":[-3.1821060181,55.9747924805],"type":"Point"}
}