{
  "type": "Feature",
  "properties": {
    "addr:full":"479 Holloway Road London Greater London N7 6LH",
    "addr:housenumber":"479",
    "addr:postcode":"n7 6lh",
    "addr:street":"Holloway Road",
    "iso:country":"GB",
    "sg:address":"479 Holloway Road",
    "sg:city":"London",
    "sg:classifiers":[
        {
            "category":"Real Estate",
            "subcategory":"Developer",
            "type":"Services"
        }
    ],
    "sg:phone":"+44 20 7272 2255",
    "sg:postcode":"N7 6LH",
    "sg:province":"Greater London",
    "sg:tags":[
        "property"
    ],
    "wof:name":"Dealmore Ltd.",
    "wof:placetype":"venue"
},
  "geometry": {"coordinates":[-0.1238439977,51.5606689453],"type":"Point"}
}