{
  "type": "Feature",
  "properties": {
    "addr:full":"Stratford Road Bromsgrove Worcestershire B60 1LD",
    "addr:postcode":"b60 1ld",
    "addr:street":"Stratford Road",
    "iso:country":"GB",
    "sg:address":"Stratford Road",
    "sg:city":"Bromsgrove",
    "sg:classifiers":[
        {
            "category":"Sports & Exercise",
            "subcategory":"Golf",
            "type":"Entertainment"
        }
    ],
    "sg:phone":"+44 1527 575886",
    "sg:postcode":"B60 1LD",
    "sg:province":"Worcestershire",
    "sg:tags":[
        "club",
        "course"
    ],
    "wof:name":"The Bromsgrove Golf Centre Ltd.",
    "wof:placetype":"venue"
},
  "geometry": {"coordinates":[-2.0542740822,52.3353805542],"type":"Point"}
}