{
  "type": "Feature",
  "properties": {
    "addr:full":"Western Road Cheltenham Gloucestershire GL50 3RN",
    "addr:postcode":"gl50 3rn",
    "addr:street":"Western Road",
    "iso:country":"GB",
    "sg:address":"Western Road",
    "sg:city":"Cheltenham",
    "sg:classifiers":[
        {
            "category":"Travel",
            "subcategory":"Hotels & Motels",
            "type":"Entertainment"
        }
    ],
    "sg:postcode":"GL50 3RN",
    "sg:province":"Gloucestershire",
    "wof:name":"Stretton Lodge",
    "wof:placetype":"venue"
},
  "geometry": {"coordinates":[-2.088367939,51.9003639221],"type":"Point"}
}