{
  "type": "Feature",
  "properties": {
    "iso:country":"GB",
    "sg:address":"19 Wadham Street",
    "sg:city":"Weston-super-mare",
    "sg:classifiers":[
        {
            "category":"Bars & Pubs",
            "type":"Food & Drink"
        }
    ],
    "sg:phone":"+44 1934 642620",
    "sg:postcode":"BS23 1JZ",
    "sg:province":"Somerset",
    "sg:tags":[
        "pubs",
        "inn"
    ],
    "wof:name":"The Old Stable Steakhouse Restaurants",
    "wof:placetype":"venue"
},
  "geometry": {"coordinates":[-2.9804089069,51.3507881165],"type":"Point"}
}