{
  "type": "Feature",
  "properties": {
    "iso:country":"GB",
    "sg:address":"39 Yeovil Road",
    "sg:city":"Farnborough",
    "sg:classifiers":[
        {
            "category":"Building & Trades",
            "subcategory":"Plumbing",
            "type":"Services"
        }
    ],
    "sg:postcode":"GU14 6LB",
    "sg:province":"Hampshire",
    "sg:tags":[
        "heating"
    ],
    "wof:name":"Silvester Plumbing Services",
    "wof:placetype":"venue"
},
  "geometry": {"coordinates":[-0.739632,51.27932],"type":"Point"}
}