{
  "type": "Feature",
  "properties": {
    "addr:full":"1 Froghall Lane Warrington Cheshire WA2 7JJ",
    "addr:housenumber":"1",
    "addr:postcode":"wa2 7jj",
    "addr:street":"Froghall Lane",
    "iso:country":"GB",
    "sg:address":"1 Froghall Lane",
    "sg:city":"Warrington",
    "sg:classifiers":[
        {
            "category":"Communications",
            "subcategory":"News Services",
            "type":"Services"
        }
    ],
    "sg:postcode":"WA2 7JJ",
    "sg:province":"Cheshire",
    "sg:tags":[
        "photo",
        "agency"
    ],
    "wof:name":"Orbit News Service",
    "wof:placetype":"venue"
},
  "geometry": {"coordinates":[-2.5981769562,53.3929405212],"type":"Point"}
}