{
  "type": "Feature",
  "properties": {
    "iso:country":"GB",
    "sg:address":"Houghton Enterprise Centre, Lake St",
    "sg:city":"Houghton-le-spring",
    "sg:classifiers":[
        {
            "category":"Manufacturing",
            "subcategory":"Electronics",
            "type":"Manufacturing & Wholesale Goods"
        }
    ],
    "sg:postcode":"DH5 8BJ",
    "sg:province":"Durham",
    "sg:tags":[
        "control",
        "component",
        "-",
        "electronic"
    ],
    "wof:name":"Optolink Ltd",
    "wof:placetype":"venue"
},
  "geometry": {"coordinates":[-1.46656,54.84325],"type":"Point"}
}