{
  "type": "Feature",
  "properties": {
    "addr:full":"84-86 Westgate Wakefield West Yorkshire WF1 1JZ",
    "addr:housenumber":"84-86",
    "addr:postcode":"wf1 1jz",
    "addr:street":"Westgate Wakefield West",
    "iso:country":"GB",
    "sg:address":"84-86 Westgate",
    "sg:city":"Wakefield",
    "sg:classifiers":[
        {
            "category":"Bars & Pubs",
            "subcategory":"Nightclub",
            "type":"Food & Drink"
        }
    ],
    "sg:phone":"+44 1924 382569",
    "sg:postcode":"WF1 1JZ",
    "sg:province":"West Yorkshire",
    "sg:tags":[
        "club",
        "night"
    ],
    "wof:name":"Brook Leisure Ltd.",
    "wof:placetype":"venue"
},
  "geometry": {"coordinates":[-1.5018190145,53.6822166443],"type":"Point"}
}