{
  "type": "Feature",
  "properties": {
    "iso:country":"GB",
    "sg:address":"Clayton Wood Close",
    "sg:city":"Leeds",
    "sg:classifiers":[
        {
            "category":"Home & Garden",
            "subcategory":"Carpets & Floor Coverings",
            "type":"Retail Goods"
        }
    ],
    "sg:phone":"+44 20 7249 5141",
    "sg:postcode":"LS16 6QE",
    "sg:province":"West Yorkshire",
    "sg:tags":[
        "trimming",
        "trimmer"
    ],
    "wof:name":"Butonia (London) Ltd.",
    "wof:placetype":"venue"
},
  "geometry": {"coordinates":[-1.6090140343,53.8418502808],"type":"Point"}
}