{
  "type": "Feature",
  "properties": {
    "addr:full":"West End Lane, Horsforth Leeds West Yorkshire LS18 5JP",
    "addr:postcode":"ls18 5jp",
    "addr:street":"West End Lane",
    "iso:country":"GB",
    "sg:address":"West End Lane, Horsforth",
    "sg:city":"Leeds",
    "sg:classifiers":[
        {
            "category":"Education",
            "subcategory":"School",
            "type":"Public Place"
        }
    ],
    "sg:phone":"+44 113 258 2819",
    "sg:postcode":"LS18 5JP",
    "sg:province":"West Yorkshire",
    "sg:tags":[
        "local",
        "authority"
    ],
    "wof:name":"West End Primary School",
    "wof:placetype":"venue"
},
  "geometry": {"coordinates":[-1.6535849571,53.8475036621],"type":"Point"}
}