{
  "type": "Feature",
  "properties": {
    "iso:country":"GB",
    "sg:address":"8 St Swithins Street",
    "sg:city":"Worcester",
    "sg:classifiers":[
        {
            "category":"Shopping",
            "subcategory":"Florist",
            "type":"Retail Goods"
        }
    ],
    "sg:phone":"+44 1905 26226",
    "sg:postcode":"WR1 2PY",
    "sg:province":"Worcestershire",
    "wof:name":"Blooms Florist",
    "wof:placetype":"venue"
},
  "geometry": {"coordinates":[-2.220234,52.192642],"type":"Point"}
}