{
  "type": "Feature",
  "properties": {
    "iso:country":"GB",
    "sg:address":"15 Lynton Gardens",
    "sg:city":"Harrogate",
    "sg:classifiers":[
        {
            "category":"Professional",
            "subcategory":"Management & Consulting",
            "type":"Services"
        }
    ],
    "sg:phone":"+44 1423 549454",
    "sg:postcode":"HG1 4TE",
    "sg:province":"North Yorkshire",
    "sg:tags":[
        "project"
    ],
    "wof:name":"P P S Project Planning Services",
    "wof:placetype":"venue"
},
  "geometry": {"coordinates":[-1.5168659687,53.9967536926],"type":"Point"}
}