{
  "type": "Feature",
  "properties": {
    "addr:full":"The Croft, Lichfield St Burton On Trent Derbyshire DE14 3RH",
    "addr:postcode":"trent derbyshire de14 3rh",
    "addr:street":"Lichfield St",
    "iso:country":"GB",
    "sg:address":"The Croft, Lichfield St",
    "sg:city":"Burton On Trent",
    "sg:classifiers":[
        {
            "category":"Arena",
            "subcategory":"Sports Club",
            "type":"Entertainment"
        }
    ],
    "sg:phone":"+44 1283 564510",
    "sg:postcode":"DE14 3RH",
    "sg:province":"Derbyshire",
    "wof:name":"Burton Rugby Union Football Club",
    "wof:placetype":"venue"
},
  "geometry": {"coordinates":[-1.631654,52.800179],"type":"Point"}
}