{
  "type": "Feature",
  "properties": {
    "iso:country":"GB",
    "sg:address":"West End Garage",
    "sg:city":"Pwllheli",
    "sg:classifiers":[
        {
            "category":"Bus Charters",
            "type":"Transportation"
        }
    ],
    "sg:phone":"+44 1758 612719",
    "sg:postcode":"LL53 5PH",
    "sg:province":"Gwynedd",
    "sg:tags":[
        "hire",
        "coach"
    ],
    "wof:name":"Caelloi Motors",
    "wof:placetype":"venue"
},
  "geometry": {"coordinates":[-4.414314,52.889847],"type":"Point"}
}