{
  "type": "Feature",
  "properties": {
    "addr:full":"29 Hael Lane, Southgate Swansea Swansea SA3 2AP",
    "addr:housenumber":"29",
    "addr:postcode":"sa3 2ap",
    "addr:street":"Hael Lane",
    "iso:country":"GB",
    "sg:address":"29 Hael Lane, Southgate",
    "sg:city":"Swansea",
    "sg:classifiers":[
        {
            "category":"Home & Garden",
            "subcategory":"Hardware",
            "type":"Retail Goods"
        }
    ],
    "sg:phone":"+44 1792 232821",
    "sg:postcode":"SA3 2AP",
    "sg:province":"Swansea",
    "sg:tags":[
        "lawnmowers",
        "machinery"
    ],
    "wof:name":"South Gower",
    "wof:placetype":"venue"
},
  "geometry": {"coordinates":[-4.079882,51.569195],"type":"Point"}
}