{
  "type": "Feature",
  "properties": {
    "iso:country":"GB",
    "sg:address":"38-39 Bridge Street, Howden-le-wear",
    "sg:city":"Crook",
    "sg:classifiers":[
        {
            "category":"Food & Beverages",
            "subcategory":"Meat & Fish",
            "type":"Retail Goods"
        }
    ],
    "sg:postcode":"DL15 8EX",
    "sg:province":"Durham",
    "sg:tags":[
        "chip"
    ],
    "wof:name":"Howden Fisheries",
    "wof:placetype":"venue"
},
  "geometry": {"coordinates":[-1.749135,54.69487],"type":"Point"}
}