{
  "type": "Feature",
  "properties": {
    "iso:country":"GB",
    "sg:address":"32 Groathill Road North",
    "sg:city":"Edinburgh",
    "sg:classifiers":[
        {
            "category":"Manufacturing",
            "subcategory":"Apparel",
            "type":"Manufacturing & Wholesale Goods"
        }
    ],
    "sg:phone":"+44 131 343 3742",
    "sg:postcode":"EH4 2SL",
    "sg:province":"City of Edinburgh",
    "sg:tags":[
        "garment",
        "designer"
    ],
    "wof:name":"Chris Clyne",
    "wof:placetype":"venue"
},
  "geometry": {"coordinates":[-3.2430980206,55.9611663818],"type":"Point"}
}