{
  "type": "Feature",
  "properties": {
    "addr:full":"The Abbey, Preston Rd Yeovil Somerset BA20 2EN",
    "addr:postcode":"ba20 2en",
    "addr:street":"Preston Rd",
    "iso:country":"GB",
    "sg:address":"The Abbey, Preston Rd",
    "sg:city":"Yeovil",
    "sg:classifiers":[
        {
            "category":"Wholesale",
            "subcategory":"Machinery & Supplies",
            "type":"Manufacturing & Wholesale Goods"
        }
    ],
    "sg:phone":"+44 1935 479395",
    "sg:postcode":"BA20 2EN",
    "sg:province":"Somerset",
    "sg:tags":[
        "pump"
    ],
    "wof:name":"Sparrow & Newman Water Services",
    "wof:placetype":"venue"
},
  "geometry": {"coordinates":[-2.6609299183,50.9436683655],"type":"Point"}
}