{
  "type": "Feature",
  "properties": {
    "iso:country":"GB",
    "sg:address":"361 High Street",
    "sg:city":"Lincoln",
    "sg:classifiers":[
        {
            "category":"Wholesale",
            "subcategory":"Construction Materials",
            "type":"Manufacturing & Wholesale Goods"
        },
        {
            "category":"Manufacturing",
            "subcategory":"Building Materials",
            "type":"Manufacturing & Wholesale Goods"
        }
    ],
    "sg:phone":"+44 1522 532779",
    "sg:postcode":"LN5 7RL",
    "sg:province":"Lincolnshire",
    "sg:tags":[
        "tile",
        "mnfrs",
        "wholesaler",
        "supplier"
    ],
    "wof:name":"Ceramic Tile Centres Ltd",
    "wof:placetype":"venue"
},
  "geometry": {"coordinates":[-0.542974,53.22438],"type":"Point"}
}