{
  "type": "Feature",
  "properties": {
    "addr:full":"106 Coleridge St Hove East Sussex BN3 5AA",
    "addr:housenumber":"106",
    "addr:postcode":"bn3 5aa",
    "addr:street":"Coleridge St",
    "iso:country":"GB",
    "sg:address":"106 Coleridge St",
    "sg:city":"Hove",
    "sg:classifiers":[
        {
            "category":"Building & Trades",
            "subcategory":"Construction",
            "type":"Services"
        }
    ],
    "sg:phone":"+44 1273 674159",
    "sg:postcode":"BN3 5AA",
    "sg:province":"East Sussex",
    "sg:tags":[
        "joinery"
    ],
    "wof:name":"Anthony Meadows",
    "wof:placetype":"venue"
},
  "geometry": {"coordinates":[-0.1826879978,50.8351898193],"type":"Point"}
}