{
  "type": "Feature",
  "properties": {
    "addr:full":"Locksheath District Centre Southampton Hampshire SO31 6DX",
    "addr:postcode":"hampshire so31 6dx",
    "iso:country":"GB",
    "sg:address":"Locksheath District Centre",
    "sg:city":"Southampton",
    "sg:classifiers":[
        {
            "category":"Shopping",
            "subcategory":"Pharmacy",
            "type":"Retail Goods"
        }
    ],
    "sg:postcode":"SO31 6DX",
    "sg:province":"Hampshire",
    "sg:tags":[
        "pharmacist",
        "chemist"
    ],
    "wof:name":"H J Everett",
    "wof:placetype":"venue"
},
  "geometry": {"coordinates":[-1.268304,50.855381],"type":"Point"}
}