{
  "type": "Feature",
  "properties": {
    "iso:country":"GB",
    "sg:address":"Aislaby Grange",
    "sg:city":"Stockton On Tees",
    "sg:classifiers":[
        {
            "category":"Military Area",
            "subcategory":"Air Force Base",
            "type":"Public Place"
        }
    ],
    "sg:phone":"+44 7973 934234",
    "sg:postcode":"TS16 0QP",
    "sg:province":"Durham",
    "sg:tags":[
        "taxi",
        "hire",
        "private"
    ],
    "wof:name":"G G Taxis Of Yarm",
    "wof:placetype":"venue"
},
  "geometry": {"coordinates":[-1.3554940224,54.513343811],"type":"Point"}
}