{
  "type": "Feature",
  "properties": {
    "addr:full":"Wasps Studio, 15 East Campbell Street Glasgow Glasgow City G1 5DT",
    "addr:housenumber":"15",
    "addr:postcode":"g1 5dt",
    "addr:street":"East Campbell Street",
    "iso:country":"GB",
    "sg:address":"Wasps Studio, 15 East Campbell Street",
    "sg:city":"Glasgow",
    "sg:classifiers":[
        {
            "category":"Professional",
            "subcategory":"Art Services",
            "type":"Services"
        }
    ],
    "sg:phone":"+44 141 552 1222",
    "sg:postcode":"G1 5DT",
    "sg:province":"Glasgow City",
    "sg:tags":[
        "consultant",
        "design"
    ],
    "wof:name":"The Hub Design Consultancy",
    "wof:placetype":"venue"
},
  "geometry": {"coordinates":[-4.23684,55.85598],"type":"Point"}
}