{
  "type": "Feature",
  "properties": {
    "iso:country":"GB",
    "sg:address":"High Threaber Farm, Westhouse",
    "sg:city":"Carnforth",
    "sg:classifiers":[
        {
            "category":"Farming",
            "subcategory":"Livestock Farm",
            "type":"Manufacturing & Wholesale Goods"
        }
    ],
    "sg:phone":"+44 15242 41334",
    "sg:postcode":"LA6 3NX",
    "sg:province":"Cumbria",
    "sg:tags":[
        "others"
    ],
    "wof:name":"J & A Lawson & Son Farmers",
    "wof:placetype":"venue"
},
  "geometry": {"coordinates":[-2.504864,54.161461],"type":"Point"}
}