{
  "type": "Feature",
  "properties": {
    "iso:country":"GB",
    "sg:address":"16 Masin Rd, Cowdray Centre",
    "sg:city":"Colchester",
    "sg:classifiers":[
        {
            "category":"Professional",
            "subcategory":"Business Services",
            "type":"Services"
        }
    ],
    "sg:phone":"+44 1375 855950",
    "sg:postcode":"CO1 1BX",
    "sg:province":"Essex",
    "sg:tags":[
        "broker",
        "commodity"
    ],
    "wof:name":"Hecht Heyworth & Alcan Ltd",
    "wof:placetype":"venue"
},
  "geometry": {"coordinates":[0.9022200108,51.8988189697],"type":"Point"}
}