{
  "type": "Feature",
  "properties": {
    "iso:country":"GB",
    "sg:address":"17 Nevanthon Rd",
    "sg:city":"Leicester",
    "sg:classifiers":[
        {
            "category":"Manufacturing",
            "subcategory":"Textiles",
            "type":"Manufacturing & Wholesale Goods"
        }
    ],
    "sg:phone":"+44 116 247 1565",
    "sg:postcode":"LE3 6DR",
    "sg:province":"Leicestershire",
    "sg:tags":[
        "made-up"
    ],
    "wof:name":"Bedrock",
    "wof:placetype":"venue"
},
  "geometry": {"coordinates":[-1.162833,52.634975],"type":"Point"}
}