{
  "type": "Feature",
  "properties": {
    "addr:full":"Southwick Library, Southdown Road, Southwick Brighton West Sussex BN42 4FT",
    "addr:postcode":"bn42 4ft",
    "addr:street":"Southdown Road",
    "iso:country":"GB",
    "sg:address":"Southwick Library, Southdown Road, Southwick",
    "sg:city":"Brighton",
    "sg:classifiers":[
        {
            "category":"Education",
            "subcategory":"Library",
            "type":"Public Place"
        },
        {
            "category":"Government",
            "subcategory":"Office",
            "type":"Public Place"
        }
    ],
    "sg:phone":"+44 1273 592150",
    "sg:postcode":"BN42 4FT",
    "sg:province":"West Sussex",
    "sg:tags":[
        "book",
        "local"
    ],
    "wof:name":"Southwick Library",
    "wof:placetype":"venue"
},
  "geometry": {"coordinates":[-0.23742,50.836205],"type":"Point"}
}