{
  "type": "Feature",
  "properties": {
    "addr:full":"Unit 1, Chevron Business Park Southampton Hampshire SO45 2QL",
    "addr:housenumber":"unit 1",
    "addr:postcode":"so45 2ql",
    "addr:street":"Business Park",
    "iso:country":"GB",
    "sg:address":"Unit 1, Chevron Business Park",
    "sg:city":"Southampton",
    "sg:classifiers":[
        {
            "category":"Wholesale",
            "subcategory":"Office Equipment",
            "type":"Manufacturing & Wholesale Goods"
        }
    ],
    "sg:phone":"+44 23 8024 5777",
    "sg:postcode":"SO45 2QL",
    "sg:province":"Hampshire",
    "sg:tags":[
        "partition",
        "cubicle"
    ],
    "wof:name":"Mayflower Interiors & Storage Ltd.",
    "wof:placetype":"venue"
},
  "geometry": {"coordinates":[-1.3943400383,50.8396682739],"type":"Point"}
}