{
  "type": "Feature",
  "properties": {
    "addr:full":"22 White Rock Hastings East Sussex TN34 1JY",
    "addr:housenumber":"22",
    "addr:postcode":"tn34 1jy",
    "addr:street":"White Rock Hastings",
    "iso:country":"GB",
    "sg:address":"22 White Rock",
    "sg:city":"Hastings",
    "sg:classifiers":[
        {
            "category":"Organizations",
            "subcategory":"Non-profit Organization",
            "type":"Services"
        }
    ],
    "sg:phone":"+44 1424 439042",
    "sg:postcode":"TN34 1JY",
    "sg:province":"East Sussex",
    "sg:tags":[
        "organisation",
        "voluntary",
        "charity"
    ],
    "wof:name":"Scope Charity Shops",
    "wof:placetype":"venue"
},
  "geometry": {"coordinates":[0.5738229752,50.8539009094],"type":"Point"}
}