{
  "type": "Feature",
  "properties": {
    "addr:full":"Arch 42, Williamson Street Manchester Greater Manchester M4 4DZ",
    "addr:housenumber":"42",
    "addr:postcode":"m4 4dz",
    "addr:street":"Arch;Williamson Street",
    "iso:country":"GB",
    "sg:address":"Arch 42, Williamson Street",
    "sg:city":"Manchester",
    "sg:classifiers":[
        {
            "category":"Retail",
            "subcategory":"Auto Repair",
            "type":"Services"
        }
    ],
    "sg:postcode":"M4 4DZ",
    "sg:province":"Greater Manchester",
    "sg:tags":[
        "modification",
        "garage"
    ],
    "wof:name":"Archway Motors",
    "wof:placetype":"venue"
},
  "geometry": {"coordinates":[-2.2342998981,53.4893493652],"type":"Point"}
}