{
  "type": "Feature",
  "properties": {
    "addr:full":"60 Martingale Place, Downs Barn Milton Keynes Buckinghamshire MK14 7QN",
    "addr:housenumber":"60",
    "addr:postcode":"mk14 7qn",
    "addr:street":"Martingale Place Downs",
    "iso:country":"GB",
    "sg:address":"60 Martingale Place, Downs Barn",
    "sg:city":"Milton Keynes",
    "sg:classifiers":[
        {
            "category":"Building & Trades",
            "subcategory":"Construction",
            "type":"Services"
        }
    ],
    "sg:phone":"+44 1908 670440",
    "sg:postcode":"MK14 7QN",
    "sg:province":"Buckinghamshire",
    "sg:tags":[
        "decorator",
        "painter"
    ],
    "wof:name":"Decorite",
    "wof:placetype":"venue"
},
  "geometry": {"coordinates":[-0.7503780127,52.0541801453],"type":"Point"}
}