{
  "type": "Feature",
  "properties": {
    "addr:full":"10 Meadow Close Cheltenham Gloucestershire GL51 0TZ",
    "addr:housenumber":"10",
    "addr:postcode":"gl51 0tz",
    "addr:street":"Meadow Close",
    "iso:country":"GB",
    "sg:address":"10 Meadow Close",
    "sg:city":"Cheltenham",
    "sg:classifiers":[
        {
            "category":"Retail",
            "subcategory":"Driving School",
            "type":"Services"
        }
    ],
    "sg:phone":"+44 1242 528619",
    "sg:postcode":"GL51 0TZ",
    "sg:province":"Gloucestershire",
    "wof:name":"APOLLO DRIVING SCHOOL",
    "wof:placetype":"venue"
},
  "geometry": {"coordinates":[-2.1299359798,51.89818573],"type":"Point"}
}