{
  "type": "Feature",
  "properties": {
    "addr:full":"116 Walton Street Oxford Oxfordshire OX2 6AJ",
    "addr:housenumber":"116",
    "addr:postcode":"ox2 6aj",
    "addr:street":"Walton Street",
    "iso:country":"GB",
    "sg:address":"116 Walton Street",
    "sg:city":"Oxford",
    "sg:classifiers":[
        {
            "category":"Shopping",
            "subcategory":"Pharmacy",
            "type":"Retail Goods"
        }
    ],
    "sg:phone":"+44 1865 557219",
    "sg:postcode":"OX2 6AJ",
    "sg:province":"Oxfordshire",
    "sg:tags":[
        "pharmacist",
        "chemist"
    ],
    "wof:name":"Lloyds Chemist",
    "wof:placetype":"venue"
},
  "geometry": {"coordinates":[-1.2663099766,51.7604179382],"type":"Point"}
}