{
  "type": "Feature",
  "properties": {
    "addr:full":"197 Parrock Street Gravesend Kent DA12 1EW",
    "addr:housenumber":"197",
    "addr:postcode":"da12 1ew",
    "addr:street":"Parrock Street",
    "iso:country":"GB",
    "sg:address":"197 Parrock Street",
    "sg:city":"Gravesend",
    "sg:classifiers":[
        {
            "category":"Real Estate",
            "subcategory":"Real Estate Operator",
            "type":"Services"
        }
    ],
    "sg:postcode":"DA12 1EW",
    "sg:province":"Kent",
    "sg:tags":[
        "letting",
        "agent"
    ],
    "wof:name":"Sealeys",
    "wof:placetype":"venue"
},
  "geometry": {"coordinates":[0.3707709908,51.4416275024],"type":"Point"}
}