{
  "type": "Feature",
  "properties": {
    "iso:country":"GB",
    "sg:address":"Queslett Park Golf Centre, Booths Lane",
    "sg:city":"Birmingham",
    "sg:classifiers":[
        {
            "category":"Sports & Exercise",
            "subcategory":"Golf",
            "type":"Entertainment"
        }
    ],
    "sg:phone":"+44 121 366 7000",
    "sg:postcode":"B42 2RG",
    "sg:province":"West Midlands",
    "sg:tags":[
        "equipment",
        "range",
        "driving"
    ],
    "wof:name":"American Golf Discount Centre",
    "wof:placetype":"venue"
},
  "geometry": {"coordinates":[-1.91513,52.546322],"type":"Point"}
}