{
  "type": "Feature",
  "properties": {
    "iso:country":"GB",
    "sg:address":"Enviromental Centre, 98 Holmesdale Street, Grangetown",
    "sg:city":"Cardiff",
    "sg:classifiers":[
        {
            "category":"Manufacturing",
            "subcategory":"Buildings",
            "type":"Manufacturing & Wholesale Goods"
        },
        {
            "category":"Home & Garden",
            "subcategory":"Household Appliances",
            "type":"Retail Goods"
        }
    ],
    "sg:phone":"+44 29 2023 7654",
    "sg:postcode":"CF11 7BU",
    "sg:province":"Cardiff",
    "sg:tags":[
        "equipment",
        "system",
        "air conditioning"
    ],
    "wof:name":"S W Heating Equipment Ltd",
    "wof:placetype":"venue"
},
  "geometry": {"coordinates":[-3.1813890934,51.4676399231],"type":"Point"}
}