{
  "type": "Feature",
  "properties": {
    "iso:country":"GB",
    "sg:address":"131 Southampton Way",
    "sg:city":"London",
    "sg:classifiers":[
        {
            "category":"Travel",
            "subcategory":"Travel Agent",
            "type":"Entertainment"
        }
    ],
    "sg:postcode":"SE5 7EW",
    "sg:province":"Greater London",
    "wof:name":"Sevenseas Travel Ltd.",
    "wof:placetype":"venue"
},
  "geometry": {"coordinates":[-0.084842,51.478355],"type":"Point"}
}