{
  "type": "Feature",
  "properties": {
    "iso:country":"GB",
    "sg:address":"167 Radcliffe Road",
    "sg:city":"Bury",
    "sg:classifiers":[
        {
            "category":"Shopping",
            "subcategory":"News",
            "type":"Retail Goods"
        }
    ],
    "sg:postcode":"BL9 9LN",
    "sg:province":"Lancashire",
    "sg:tags":[
        "newsagent"
    ],
    "wof:name":"N M Thomson",
    "wof:placetype":"venue"
},
  "geometry": {"coordinates":[-2.3062639236,53.5792617798],"type":"Point"}
}