{
  "type": "Feature",
  "properties": {
    "addr:full":"Grn Gables Tewkesbury Gloucestershire GL20 6EX",
    "addr:postcode":"gl20 6ex",
    "addr:street":"Grn",
    "iso:country":"GB",
    "sg:address":"Grn Gables",
    "sg:city":"Tewkesbury",
    "sg:classifiers":[
        {
            "category":"Building & Trades",
            "subcategory":"Construction",
            "type":"Services"
        }
    ],
    "sg:postcode":"GL20 6EX",
    "sg:province":"Gloucestershire",
    "sg:tags":[
        "builder"
    ],
    "wof:name":"Frank Bird (Builders) Ltd.",
    "wof:placetype":"venue"
},
  "geometry": {"coordinates":[-2.1494629383,51.9929580688],"type":"Point"}
}