{
  "type": "Feature",
  "properties": {
    "iso:country":"GB",
    "sg:address":"Stations Yard",
    "sg:city":"Thurso",
    "sg:classifiers":[
        {
            "category":"Building & Trades",
            "subcategory":"Plumbing",
            "type":"Services"
        }
    ],
    "sg:phone":"+44 1847 894048",
    "sg:postcode":"KW14 7DH",
    "sg:province":"Highland",
    "sg:tags":[
        "central",
        "heating"
    ],
    "wof:name":"Thurso Building Supplies",
    "wof:placetype":"venue"
},
  "geometry": {"coordinates":[-3.525867,58.596565],"type":"Point"}
}