{
  "type": "Feature",
  "properties": {
    "iso:country":"GB",
    "sg:address":"4 Duffins Orchard, Ottershaw",
    "sg:city":"Chertsey",
    "sg:classifiers":[
        {
            "category":"Manufacturing",
            "subcategory":"Tools & Machinery",
            "type":"Manufacturing & Wholesale Goods"
        },
        {
            "category":"Insurance",
            "subcategory":"Insurance Agent",
            "type":"Services"
        }
    ],
    "sg:phone":"+44 1932 873479",
    "sg:postcode":"KT16 0LP",
    "sg:province":"Surrey",
    "sg:tags":[
        "society",
        "friendly"
    ],
    "wof:name":"Anthony Dunn & Co Ltd",
    "wof:placetype":"venue"
},
  "geometry": {"coordinates":[-0.533302,51.357952],"type":"Point"}
}