{
  "type": "Feature",
  "properties": {
    "addr:full":"The Hollies, Newport Rd Stafford Staffordshire ST16 1BY",
    "addr:postcode":"st16 1by",
    "addr:street":"Newport Rd",
    "iso:country":"GB",
    "sg:address":"The Hollies, Newport Rd",
    "sg:city":"Stafford",
    "sg:classifiers":[
        {
            "category":"Professional",
            "subcategory":"Computer Services",
            "type":"Services"
        }
    ],
    "sg:phone":"+44 1785 248131",
    "sg:postcode":"ST16 1BY",
    "sg:province":"Staffordshire",
    "sg:tags":[
        "system",
        "software"
    ],
    "wof:name":"Marconi Software Ltd",
    "wof:placetype":"venue"
},
  "geometry": {"coordinates":[-2.121768,52.803959],"type":"Point"}
}