{
  "type": "Feature",
  "properties": {
    "iso:country":"GB",
    "sg:address":"The Vine, 5 Dartford Road",
    "sg:city":"Sevenoaks",
    "sg:classifiers":[
        {
            "category":"Autos & Motor Vehicles",
            "subcategory":"Automobile Sales",
            "type":"Retail Goods"
        }
    ],
    "sg:phone":"+44 1732 743529",
    "sg:postcode":"TN13 3SX",
    "sg:province":"Kent",
    "sg:tags":[
        "commercial"
    ],
    "wof:name":"H M G Holdings Ltd.",
    "wof:placetype":"venue"
},
  "geometry": {"coordinates":[0.192955,51.276508],"type":"Point"}
}