{
  "type": "Feature",
  "properties": {
    "iso:country":"GB",
    "sg:address":"14 High St",
    "sg:city":"Penge",
    "sg:classifiers":[
        {
            "category":"Food & Beverages",
            "subcategory":"Supermarket",
            "type":"Retail Goods"
        }
    ],
    "sg:phone":"+44 181 659 6955",
    "sg:postcode":"SE20 7HG",
    "sg:province":"Greater London",
    "wof:name":"Costcutters Food Hall",
    "wof:placetype":"venue"
},
  "geometry": {"coordinates":[-0.058566,51.417522],"type":"Point"}
}