{
  "type": "Feature",
  "properties": {
    "iso:country":"GB",
    "sg:address":"St Martin's Walk",
    "sg:city":"Leicester",
    "sg:classifiers":[
        {
            "category":"Shopping",
            "subcategory":"Gifts & Souvenirs",
            "type":"Retail Goods"
        }
    ],
    "sg:phone":"+44 116 251 9022",
    "sg:postcode":"LE1 5DG",
    "sg:province":"Leicestershire",
    "sg:tags":[
        "shop"
    ],
    "wof:name":"The Ark",
    "wof:placetype":"venue"
},
  "geometry": {"coordinates":[-1.206411,52.623173],"type":"Point"}
}