{
  "type": "Feature",
  "properties": {
    "addr:full":"9 Aigan Court, York Street, Dufftown Keith Moray AB55 4AJ",
    "addr:housenumber":"9",
    "addr:postcode":"ab55 4aj",
    "addr:street":"Aigan Court;Street",
    "iso:country":"GB",
    "sg:address":"9 Aigan Court, York Street, Dufftown",
    "sg:city":"Keith",
    "sg:classifiers":[
        {
            "category":"Organizations",
            "subcategory":"Community Association",
            "type":"Services"
        }
    ],
    "sg:phone":"+44 1340 820900",
    "sg:postcode":"AB55 4AJ",
    "sg:province":"Moray",
    "sg:tags":[
        "co-operatives",
        "society",
        "housing",
        "trust"
    ],
    "wof:name":"Hanover Scotland Housing Association Ltd",
    "wof:placetype":"venue"
},
  "geometry": {"coordinates":[-3.1265668869,57.4448738098],"type":"Point"}
}