{
  "type": "Feature",
  "properties": {
    "iso:country":"GB",
    "sg:address":"Penamser Road",
    "sg:city":"Porthmadog",
    "sg:classifiers":[
        {
            "category":"Shopping",
            "subcategory":"Bicycles & Sporting Goods",
            "type":"Retail Goods"
        }
    ],
    "sg:phone":"+44 1766 512241",
    "sg:postcode":"LL49 9NY",
    "sg:province":"Gwynedd",
    "sg:tags":[
        "equipment",
        "camping"
    ],
    "wof:name":"Outdoor World",
    "wof:placetype":"venue"
},
  "geometry": {"coordinates":[-4.154389,52.933552],"type":"Point"}
}