{
  "type": "Feature",
  "properties": {
    "addr:full":"Durham Lane Industrial Park Stockton On Tees Durham TS16 0PN",
    "addr:postcode":"ts16 0pn",
    "addr:street":"Durham Lane Industrial Park",
    "iso:country":"GB",
    "sg:address":"Durham Lane Industrial Park",
    "sg:city":"Stockton On Tees",
    "sg:classifiers":[
        {
            "category":"Home & Garden",
            "subcategory":"Hardware",
            "type":"Retail Goods"
        }
    ],
    "sg:phone":"+44 1642 791666",
    "sg:postcode":"TS16 0PN",
    "sg:province":"Durham",
    "sg:tags":[
        "heat",
        "mech",
        "exchanger"
    ],
    "wof:name":"Jenkins Heat Exchanges",
    "wof:placetype":"venue"
},
  "geometry": {"coordinates":[-1.3599339724,54.5210418701],"type":"Point"}
}