{
  "type": "Feature",
  "properties": {
    "iso:country":"GB",
    "sg:address":"70 Ormonde Street",
    "sg:city":"Sunderland",
    "sg:classifiers":[
        {
            "category":"Government",
            "subcategory":"Post Office",
            "type":"Public Place"
        }
    ],
    "sg:phone":"+44 191 528 2607",
    "sg:postcode":"SR4 7PW",
    "sg:province":"Tyne and Wear",
    "wof:name":"Barnes Park Sub Post Office",
    "wof:placetype":"venue"
},
  "geometry": {"coordinates":[-1.4082109928,54.8981513977],"type":"Point"}
}