{
  "type": "Feature",
  "properties": {
    "addr:full":"Sparrow Farm Drive Feltham Greater London TW14 0DG",
    "addr:postcode":"tw14 0dg",
    "addr:street":"Farm Drive",
    "iso:country":"GB",
    "sg:address":"Sparrow Farm Drive",
    "sg:city":"Feltham",
    "sg:classifiers":[
        {
            "category":"Education",
            "subcategory":"School",
            "type":"Public Place"
        }
    ],
    "sg:phone":"+44 20 8890 7194",
    "sg:postcode":"TW14 0DG",
    "sg:province":"Greater London",
    "sg:tags":[
        "local",
        "authority"
    ],
    "wof:name":"Sparrow Farm Junior School",
    "wof:placetype":"venue"
},
  "geometry": {"coordinates":[-0.3941940069,51.453754425],"type":"Point"}
}