{
  "type": "Feature",
  "properties": {
    "iso:country":"GB",
    "sg:address":"14 Westhill Rd",
    "sg:city":"Coventry",
    "sg:classifiers":[
        {
            "category":"Place Of Worship",
            "type":"Public Place"
        }
    ],
    "sg:phone":"+44 24 7659 1618",
    "sg:postcode":"CV6 2AA",
    "sg:province":"Warwickshire",
    "wof:name":"Christ The King R C Church",
    "wof:placetype":"venue"
},
  "geometry": {"coordinates":[-1.53507,52.422089],"type":"Point"}
}