{
  "type": "Feature",
  "properties": {
    "addr:full":"Dolphin House, North Street Guildford Surrey GU1 4AA",
    "addr:postcode":"gu1 4aa",
    "addr:street":"North Street",
    "iso:country":"GB",
    "sg:address":"Dolphin House, North Street",
    "sg:city":"Guildford",
    "sg:classifiers":[
        {
            "category":"Bars & Pubs",
            "subcategory":"Nightclub",
            "type":"Food & Drink"
        }
    ],
    "sg:phone":"+44 1483 531446",
    "sg:postcode":"GU1 4AA",
    "sg:province":"Surrey",
    "sg:tags":[
        "club",
        "night"
    ],
    "wof:name":"C R's",
    "wof:placetype":"venue"
},
  "geometry": {"coordinates":[-0.572969,51.236774],"type":"Point"}
}