{
  "type": "Feature",
  "properties": {
    "iso:country":"GB",
    "sg:address":"22 Tenby Street",
    "sg:city":"Birmingham",
    "sg:classifiers":[
        {
            "category":"Shopping",
            "subcategory":"Jewelry",
            "type":"Retail Goods"
        },
        {
            "category":"Manufacturing",
            "subcategory":"Jewelry",
            "type":"Manufacturing & Wholesale Goods"
        }
    ],
    "sg:phone":"+44 121 236 1627",
    "sg:postcode":"B1 3EE",
    "sg:province":"West Midlands",
    "sg:tags":[
        "manufacture",
        "repair",
        "jewellery",
        "gold",
        "silversmith"
    ],
    "wof:name":"M T HENRICK LTD",
    "wof:placetype":"venue"
},
  "geometry": {"coordinates":[-1.9142090082,52.4860801697],"type":"Point"}
}