{
  "type": "Feature",
  "properties": {
    "addr:full":"The Old Smithy, Spital Street Malton North Yorkshire YO17 7JW",
    "addr:postcode":"yo17 7jw",
    "addr:street":"Spital Street",
    "iso:country":"GB",
    "sg:address":"The Old Smithy, Spital Street",
    "sg:city":"Malton",
    "sg:classifiers":[
        {
            "category":"Manufacturing",
            "subcategory":"Wood Products",
            "type":"Manufacturing & Wholesale Goods"
        }
    ],
    "sg:postcode":"YO17 7JW",
    "sg:province":"North Yorkshire",
    "sg:tags":[
        "woodturning"
    ],
    "wof:name":"Wood 'N' Things",
    "wof:placetype":"venue"
},
  "geometry": {"coordinates":[-0.800224,54.137825],"type":"Point"}
}