{
  "type": "Feature",
  "properties": {
    "iso:country":"GB",
    "sg:address":"Meadows Farm, Haughmond, Uffington",
    "sg:city":"Shrewsbury",
    "sg:classifiers":[
        {
            "category":"Farming",
            "subcategory":"Dairy Farm",
            "type":"Manufacturing & Wholesale Goods"
        }
    ],
    "sg:phone":"+44 1743 709252",
    "sg:postcode":"SY4 4RW",
    "sg:province":"Shropshire",
    "wof:name":"John Barry Griffiths",
    "wof:placetype":"venue"
},
  "geometry": {"coordinates":[-2.699204,52.721344],"type":"Point"}
}