{
  "type": "Feature",
  "properties": {
    "iso:country":"GB",
    "sg:address":"1 Horton Grange Rd",
    "sg:city":"Bradford",
    "sg:classifiers":[
        {
            "category":"Health Services",
            "subcategory":"Doctor",
            "type":"Services"
        }
    ],
    "sg:phone":"+44 1274 502102",
    "sg:postcode":"BD7 3AH",
    "sg:province":"West Yorkshire",
    "sg:tags":[
        "practitioners"
    ],
    "wof:name":"Khan, I A",
    "wof:placetype":"venue"
},
  "geometry": {"coordinates":[-1.775489,53.78701],"type":"Point"}
}