{
  "type": "Feature",
  "properties": {
    "addr:full":"High Mulberry, Ingleton Darlington Durham DL2 3HZ",
    "addr:postcode":"dl2 3hz",
    "addr:street":"High Mulberry",
    "iso:country":"GB",
    "sg:address":"High Mulberry, Ingleton",
    "sg:city":"Darlington",
    "sg:classifiers":[
        {
            "category":"Home & Garden",
            "subcategory":"Garden Supply",
            "type":"Retail Goods"
        },
        {
            "category":"Farming",
            "subcategory":"Farm",
            "type":"Manufacturing & Wholesale Goods"
        }
    ],
    "sg:phone":"+44 1833 660228",
    "sg:postcode":"DL2 3HZ",
    "sg:province":"Durham",
    "sg:tags":[
        "mixed",
        "bulb",
        "crop",
        "grower"
    ],
    "wof:name":"R W Raper & Son",
    "wof:placetype":"venue"
},
  "geometry": {"coordinates":[-1.733269,54.579815],"type":"Point"}
}