{
  "type": "Feature",
  "properties": {
    "iso:country":"GB",
    "sg:address":"225 Three Bridges Road",
    "sg:city":"Crawley",
    "sg:classifiers":[
        {
            "category":"Building & Trades",
            "subcategory":"Construction",
            "type":"Services"
        }
    ],
    "sg:postcode":"RH10 1LG",
    "sg:province":"Surrey",
    "sg:tags":[
        "decorator",
        "painter"
    ],
    "wof:name":"Moss Decor Ltd",
    "wof:placetype":"venue"
},
  "geometry": {"coordinates":[-0.164478004,51.1177368164],"type":"Point"}
}