{
  "type": "Feature",
  "properties": {
    "addr:full":"Hoylemill Road, Kinsley Pontefract West Yorkshire WF9 5JB",
    "addr:postcode":"wf9 5jb",
    "addr:street":"Hoylemill Road;Pontefract West",
    "iso:country":"GB",
    "sg:address":"Hoylemill Road, Kinsley",
    "sg:city":"Pontefract",
    "sg:classifiers":[
        {
            "category":"Retail",
            "subcategory":"Storage",
            "type":"Services"
        }
    ],
    "sg:phone":"+44 800 783 0609",
    "sg:postcode":"WF9 5JB",
    "sg:province":"West Yorkshire",
    "sg:tags":[
        "household",
        "removal"
    ],
    "wof:name":"Bennetts Removals Ltd.",
    "wof:placetype":"venue"
},
  "geometry": {"coordinates":[-1.3677790165,53.624710083],"type":"Point"}
}