{
  "type": "Feature",
  "properties": {
    "addr:full":"Wheyrigg Farm, Wheyrigg Wigton Cumbria CA7 0DH",
    "addr:postcode":"ca7 0dh",
    "addr:street":"Wheyrigg",
    "iso:country":"GB",
    "sg:address":"Wheyrigg Farm, Wheyrigg",
    "sg:city":"Wigton",
    "sg:classifiers":[
        {
            "category":"Farming",
            "subcategory":"Farm",
            "type":"Manufacturing & Wholesale Goods"
        }
    ],
    "sg:phone":"+44 16973 61200",
    "sg:postcode":"CA7 0DH",
    "sg:province":"Cumbria",
    "sg:tags":[
        "mixed",
        "crop"
    ],
    "wof:name":"J & D Wilson & Sons",
    "wof:placetype":"venue"
},
  "geometry": {"coordinates":[-3.2504389286,54.8278656006],"type":"Point"}
}