{
  "type": "Feature",
  "properties": {
    "addr:full":"Silver Birches, 17 The Stonebow Northallerton North Yorkshire DL6 3SR",
    "addr:housenumber":"17",
    "addr:postcode":"dl6 3sr",
    "addr:street":"The Stonebow",
    "iso:country":"GB",
    "sg:address":"Silver Birches, 17 The Stonebow",
    "sg:city":"Northallerton",
    "sg:classifiers":[
        {
            "category":"Professional",
            "subcategory":"Management & Consulting",
            "type":"Services"
        }
    ],
    "sg:postcode":"DL6 3SR",
    "sg:province":"North Yorkshire",
    "sg:tags":[
        "consultant",
        "business"
    ],
    "wof:name":"Business Services Associates Ltd.",
    "wof:placetype":"venue"
},
  "geometry": {"coordinates":[-1.320769,54.371731],"type":"Point"}
}