{
  "type": "Feature",
  "properties": {
    "iso:country":"GB",
    "sg:address":"Carleton Rd",
    "sg:city":"Skipton",
    "sg:classifiers":[
        {
            "category":"Social Services",
            "subcategory":"Retirement Home",
            "type":"Services"
        }
    ],
    "sg:phone":"+44 1756 792881",
    "sg:postcode":"BD23 2BE",
    "sg:province":"Lancashire",
    "sg:tags":[
        "residential",
        "care"
    ],
    "wof:name":"Ashfield House Residential Care",
    "wof:placetype":"venue"
},
  "geometry": {"coordinates":[-2.0208449364,53.9553565979],"type":"Point"}
}