{
  "type": "Feature",
  "properties": {
    "addr:full":"Manor Farm, Broughton Malton North Yorkshire YO17 6QJ",
    "addr:postcode":"yo17 6qj",
    "addr:street":"Manor;Broughton",
    "iso:country":"GB",
    "sg:address":"Manor Farm, Broughton",
    "sg:city":"Malton",
    "sg:classifiers":[
        {
            "category":"Farming",
            "subcategory":"Livestock Farm",
            "type":"Manufacturing & Wholesale Goods"
        }
    ],
    "sg:postcode":"YO17 6QJ",
    "sg:province":"North Yorkshire",
    "sg:tags":[
        "others"
    ],
    "wof:name":"C T Lund & Son",
    "wof:placetype":"venue"
},
  "geometry": {"coordinates":[-0.8258110285,54.1475028992],"type":"Point"}
}