{
  "type": "Feature",
  "properties": {
    "addr:full":"21 Craven Park Rd Willesden Greater London NW10 8SE",
    "addr:housenumber":"21",
    "addr:postcode":"nw10 8se",
    "addr:street":"Craven Park Rd",
    "iso:country":"GB",
    "sg:address":"21 Craven Park Rd",
    "sg:city":"Willesden",
    "sg:classifiers":[
        {
            "category":"Travel",
            "subcategory":"Travel Agent",
            "type":"Entertainment"
        }
    ],
    "sg:phone":"+44 20 8838 3221",
    "sg:postcode":"NW10 8SE",
    "sg:province":"Greater London",
    "wof:name":"R M Travels",
    "wof:placetype":"venue"
},
  "geometry": {"coordinates":[-0.2563689947,51.5411224365],"type":"Point"}
}