{
  "type": "Feature",
  "properties": {
    "addr:full":"953-959 Garratt Lane London Greater London SW17 0LW",
    "addr:housenumber":"953-959",
    "addr:postcode":"sw17 0lw",
    "addr:street":"Garratt Lane",
    "iso:country":"GB",
    "sg:address":"953-959 Garratt Lane",
    "sg:city":"London",
    "sg:classifiers":[
        {
            "category":"Food & Beverages",
            "subcategory":"Supermarket",
            "type":"Retail Goods"
        }
    ],
    "sg:phone":"+44 20 8767 7810",
    "sg:postcode":"SW17 0LW",
    "sg:province":"Greater London",
    "wof:name":"Rateneed Ltd.",
    "wof:placetype":"venue"
},
  "geometry": {"coordinates":[-0.174201,51.430302],"type":"Point"}
}