{
  "type": "Feature",
  "properties": {
    "addr:full":"Pillinger House, 4 Wells Place, Merstram Redhill Surrey RH1 3DR",
    "addr:housenumber":"4",
    "addr:postcode":"rh1 3dr",
    "addr:street":"Wells Place Merstram Redhill",
    "iso:country":"GB",
    "sg:address":"Pillinger House, 4 Wells Place, Merstram",
    "sg:city":"Redhill",
    "sg:classifiers":[
        {
            "category":"Home & Garden",
            "subcategory":"Hardware",
            "type":"Retail Goods"
        }
    ],
    "sg:phone":"+44 1737 732345",
    "sg:postcode":"RH1 3DR",
    "sg:province":"Surrey",
    "sg:tags":[
        "heat",
        "mech",
        "exchanger"
    ],
    "wof:name":"Daikin Airconditioning Uk East Ltd.",
    "wof:placetype":"venue"
},
  "geometry": {"coordinates":[-0.155547,51.257244],"type":"Point"}
}