{
  "type": "Feature",
  "properties": {
    "iso:country":"GB",
    "sg:address":"149 Mossley Road",
    "sg:city":"Ashton-under-lyne",
    "sg:classifiers":[
        {
            "category":"Shopping",
            "subcategory":"Florist",
            "type":"Retail Goods"
        }
    ],
    "sg:phone":"+44 161 330 1955",
    "sg:postcode":"OL6 6NE",
    "sg:province":"Greater Manchester",
    "wof:name":"The Flower Vase",
    "wof:placetype":"venue"
},
  "geometry": {"coordinates":[-2.077348,53.49324],"type":"Point"}
}