{
  "type": "Feature",
  "properties": {
    "addr:full":"35 Upper Barr Oxford Oxfordshire OX4 3UX",
    "addr:housenumber":"35",
    "addr:postcode":"ox4 3ux",
    "addr:street":"Upper Barr",
    "iso:country":"GB",
    "sg:address":"35 Upper Barr",
    "sg:city":"Oxford",
    "sg:classifiers":[
        {
            "category":"Home & Garden",
            "subcategory":"Hardware",
            "type":"Retail Goods"
        }
    ],
    "sg:phone":"+44 1865 716305",
    "sg:postcode":"OX4 3UX",
    "sg:province":"Oxfordshire",
    "sg:tags":[
        "retailer",
        "lighting"
    ],
    "wof:name":"The Lighting Clearance Centres",
    "wof:placetype":"venue"
},
  "geometry": {"coordinates":[-1.215386,51.731785],"type":"Point"}
}