{
  "type": "Feature",
  "properties": {
    "iso:country":"GB",
    "sg:address":"391b Roman Road, Bow",
    "sg:city":"London",
    "sg:classifiers":[
        {
            "category":"Building & Trades",
            "subcategory":"Construction",
            "type":"Services"
        }
    ],
    "sg:phone":"+44 20 8981 4090",
    "sg:postcode":"E3 5QS",
    "sg:province":"Greater London",
    "sg:tags":[
        "decorator",
        "painter"
    ],
    "wof:name":"T Gunning Decorators",
    "wof:placetype":"venue"
},
  "geometry": {"coordinates":[-0.037583,51.531475],"type":"Point"}
}