{
  "type": "Feature",
  "properties": {
    "iso:country":"GB",
    "sg:address":"9 Wells Road",
    "sg:city":"Ilkley",
    "sg:classifiers":[
        {
            "category":"Restaurant",
            "type":"Food & Drink"
        }
    ],
    "sg:phone":"+44 1943 607104",
    "sg:postcode":"LS29 9JB",
    "sg:province":"North Yorkshire",
    "sg:tags":[
        "indian"
    ],
    "wof:name":"Sabera Restaurant",
    "wof:placetype":"venue"
},
  "geometry": {"coordinates":[-1.823767,53.923779],"type":"Point"}
}