{
  "type": "Feature",
  "properties": {
    "addr:full":"Avenue Buildings, High St Tarporley Cheshire CW6 0AZ",
    "addr:postcode":"cw6 0az",
    "addr:street":"Avenue;High St",
    "iso:country":"GB",
    "sg:address":"Avenue Buildings, High St",
    "sg:city":"Tarporley",
    "sg:classifiers":[
        {
            "category":"Professional",
            "subcategory":"Lawyer & Legal Services",
            "type":"Services"
        }
    ],
    "sg:phone":"+44 1829 733338",
    "sg:postcode":"CW6 0AZ",
    "sg:province":"Cheshire",
    "sg:tags":[
        "solicitor"
    ],
    "wof:name":"Hulme & Co",
    "wof:placetype":"venue"
},
  "geometry": {"coordinates":[-2.666009,53.155899],"type":"Point"}
}