{
  "type": "Feature",
  "properties": {
    "addr:full":"20 Hockley Street Birmingham West Midlands B18 6BL",
    "addr:housenumber":"20",
    "addr:postcode":"b18 6bl",
    "addr:street":"Hockley Street",
    "iso:country":"GB",
    "sg:address":"20 Hockley Street",
    "sg:city":"Birmingham",
    "sg:classifiers":[
        {
            "category":"Manufacturing",
            "subcategory":"Jewelry",
            "type":"Manufacturing & Wholesale Goods"
        }
    ],
    "sg:phone":"+44 121 515 1686",
    "sg:postcode":"B18 6BL",
    "sg:province":"West Midlands",
    "sg:tags":[
        "repair",
        "jewellery"
    ],
    "wof:name":"Pyzers",
    "wof:placetype":"venue"
},
  "geometry": {"coordinates":[-1.9118560553,52.4894332886],"type":"Point"}
}