{
  "type": "Feature",
  "properties": {
    "iso:country":"GB",
    "sg:address":"Unit 13-14, Roman Way Industrial Estate, Roman Way",
    "sg:city":"London",
    "sg:classifiers":[
        {
            "category":"Professional",
            "subcategory":"Printing & Photocopies",
            "type":"Services"
        }
    ],
    "sg:phone":"+44 20 7607 8555",
    "sg:postcode":"N7 8XH",
    "sg:province":"Greater London",
    "sg:tags":[
        "printer"
    ],
    "wof:name":"Witdata Ltd.",
    "wof:placetype":"venue"
},
  "geometry": {"coordinates":[-0.114517,51.545479],"type":"Point"}
}