{
  "type": "Feature",
  "properties": {
    "iso:country":"GB",
    "sg:address":"49 Highstock Lane, Gedney Hill",
    "sg:city":"Spalding",
    "sg:classifiers":[
        {
            "category":"Bars & Pubs",
            "type":"Food & Drink"
        },
        {
            "category":"Community Center",
            "subcategory":"Social",
            "type":"Public Place"
        }
    ],
    "sg:phone":"+44 1406 330275",
    "sg:postcode":"PE12 0QQ",
    "sg:province":"Cambridgeshire",
    "sg:tags":[
        "pubs",
        "house",
        "inn",
        "activity"
    ],
    "wof:name":"The Dukes Head",
    "wof:placetype":"venue"
},
  "geometry": {"coordinates":[-0.019216,52.680798],"type":"Point"}
}