{
  "type": "Feature",
  "properties": {
    "addr:full":"144-146 Barlow Moor Road Manchester Greater Manchester M20 2UT",
    "addr:housenumber":"144-146",
    "addr:postcode":"m20 2ut",
    "addr:street":"Barlow Moor Road",
    "iso:country":"GB",
    "sg:address":"144-146 Barlow Moor Road",
    "sg:city":"Manchester",
    "sg:classifiers":[
        {
            "category":"Real Estate",
            "subcategory":"Real Estate Agent",
            "type":"Services"
        }
    ],
    "sg:phone":"+44 161 448 2000",
    "sg:postcode":"M20 2UT",
    "sg:province":"Greater Manchester",
    "wof:name":"S A Properties & Management",
    "wof:placetype":"venue"
},
  "geometry": {"coordinates":[-2.24773,53.422832],"type":"Point"}
}