{
  "type": "Feature",
  "properties": {
    "addr:full":"8-9 Market Lane Edgware Greater London HA8 0LP",
    "addr:housenumber":"8-9",
    "addr:postcode":"ha8 0lp",
    "addr:street":"Market Lane",
    "iso:country":"GB",
    "sg:address":"8-9 Market Lane",
    "sg:city":"Edgware",
    "sg:classifiers":[
        {
            "category":"Real Estate",
            "subcategory":"Real Estate Agent",
            "type":"Services"
        }
    ],
    "sg:phone":"+44 20 8951 4116",
    "sg:postcode":"HA8 0LP",
    "sg:province":"Greater London",
    "wof:name":"Compact Estates Ltd.",
    "wof:placetype":"venue"
},
  "geometry": {"coordinates":[-0.2666530013,51.6007194519],"type":"Point"}
}