{
  "type": "Feature",
  "properties": {
    "addr:full":"Tansy Farm, Hickstead La, Twineham Haywards Heath East Sussex RH17 5NT",
    "addr:postcode":"rh17 5nt",
    "addr:street":"Hickstead",
    "iso:country":"GB",
    "sg:address":"Tansy Farm, Hickstead La, Twineham",
    "sg:city":"Haywards Heath",
    "sg:classifiers":[
        {
            "category":"Farming",
            "subcategory":"Livestock Farm",
            "type":"Manufacturing & Wholesale Goods"
        }
    ],
    "sg:phone":"+44 1444 881104",
    "sg:postcode":"RH17 5NT",
    "sg:province":"East Sussex",
    "sg:tags":[
        "others"
    ],
    "wof:name":"Atfield,B W,",
    "wof:placetype":"venue"
},
  "geometry": {"coordinates":[-0.2026579976,50.9675064087],"type":"Point"}
}