{
  "type": "Feature",
  "properties": {
    "iso:country":"GB",
    "sg:address":"Endway House, The Endway",
    "sg:city":"Benfleet",
    "sg:classifiers":[
        {
            "category":"Building & Trades",
            "subcategory":"Construction",
            "type":"Services"
        }
    ],
    "sg:phone":"+44 1702 712195",
    "sg:postcode":"SS7 2AN",
    "sg:province":"Essex",
    "sg:tags":[
        "bricklaying"
    ],
    "wof:name":"P R Short Brickwork Ltd.",
    "wof:placetype":"venue"
},
  "geometry": {"coordinates":[0.60938,51.552185],"type":"Point"}
}