{
  "type": "Feature",
  "properties": {
    "addr:full":"81 Manor Park, Maids Moreton Buckingham Buckinghamshire MK18 1QZ",
    "addr:housenumber":"81",
    "addr:postcode":"mk18 1qz",
    "addr:street":"Manor Park",
    "iso:country":"GB",
    "sg:address":"81 Manor Park, Maids Moreton",
    "sg:city":"Buckingham",
    "sg:classifiers":[
        {
            "category":"Professional",
            "subcategory":"Management & Consulting",
            "type":"Services"
        }
    ],
    "sg:phone":"+44 1280 822218",
    "sg:postcode":"MK18 1QZ",
    "sg:province":"Buckinghamshire",
    "sg:tags":[
        "consultant",
        "business"
    ],
    "wof:name":"Batforce Business Services",
    "wof:placetype":"venue"
},
  "geometry": {"coordinates":[-0.972758,52.013504],"type":"Point"}
}