{
  "type": "Feature",
  "properties": {
    "iso:country":"GB",
    "sg:address":"Rosebery Court, Water Lane",
    "sg:city":"Leighton Buzzard",
    "sg:classifiers":[
        {
            "category":"Social Services",
            "subcategory":"Retirement Home",
            "type":"Services"
        }
    ],
    "sg:phone":"+44 1525 851267",
    "sg:postcode":"LU7 1DL",
    "sg:province":"Bedfordshire",
    "sg:tags":[
        "rest"
    ],
    "wof:name":"Rosebury Court",
    "wof:placetype":"venue"
},
  "geometry": {"coordinates":[-0.665943,51.917072],"type":"Point"}
}