{
  "type": "Feature",
  "properties": {
    "iso:country":"GB",
    "sg:address":"212 New London Road",
    "sg:city":"Chelmsford",
    "sg:classifiers":[
        {
            "category":"Health Services",
            "subcategory":"Hospice",
            "type":"Services"
        }
    ],
    "sg:phone":"+44 1245 358130",
    "sg:postcode":"CM2 9AE",
    "sg:province":"Essex",
    "wof:name":"Farleigh Hospice",
    "wof:placetype":"venue"
},
  "geometry": {"coordinates":[0.461212,51.723129],"type":"Point"}
}