{
  "type": "Feature",
  "properties": {
    "addr:full":"The Orchards, Dalton Lane, Halsham Hull East Riding of Yorkshire HU12 0DG",
    "addr:housenumber":"orchards",
    "addr:postcode":"hu12 0dg",
    "addr:street":"Dalton Lane",
    "iso:country":"GB",
    "sg:address":"The Orchards, Dalton Lane, Halsham",
    "sg:city":"Hull",
    "sg:classifiers":[
        {
            "category":"Real Estate",
            "subcategory":"Architect",
            "type":"Services"
        }
    ],
    "sg:phone":"+44 1964 670777",
    "sg:postcode":"HU12 0DG",
    "sg:province":"East Riding of Yorkshire",
    "wof:name":"Hansford Hornsby Architects",
    "wof:placetype":"venue"
},
  "geometry": {"coordinates":[-0.031205,53.684456],"type":"Point"}
}