{
  "type": "Feature",
  "properties": {
    "iso:country":"GB",
    "sg:address":"103 Cockney Hill, Tilehurst",
    "sg:city":"Reading",
    "sg:classifiers":[
        {
            "category":"Professional",
            "subcategory":"Accounting & Tax Preparation",
            "type":"Services"
        }
    ],
    "sg:postcode":"RG30 4EY",
    "sg:province":"Berkshire",
    "sg:tags":[
        "accountant"
    ],
    "wof:name":"Campbell Parker",
    "wof:placetype":"venue"
},
  "geometry": {"coordinates":[-1.018176,51.448147],"type":"Point"}
}