{
  "type": "Feature",
  "properties": {
    "addr:full":"Union Street Rothesay Argyll and Bute PA20 0HD",
    "addr:postcode":"pa20 0hd",
    "addr:street":"Union Street",
    "iso:country":"GB",
    "sg:address":"Union Street",
    "sg:city":"Rothesay",
    "sg:classifiers":[
        {
            "category":"Retail",
            "subcategory":"Auto Repair",
            "type":"Services"
        }
    ],
    "sg:phone":"+44 1700 505269",
    "sg:postcode":"PA20 0HD",
    "sg:province":"Argyll and Bute",
    "sg:tags":[
        "modification",
        "garage"
    ],
    "wof:name":"S B Cars",
    "wof:placetype":"venue"
},
  "geometry": {"coordinates":[-5.0695209503,55.8588943481],"type":"Point"}
}