{
  "type": "Feature",
  "properties": {
    "addr:full":"1 Common Lane, Culcheth Warrington Cheshire WA3 4EH",
    "addr:housenumber":"1",
    "addr:postcode":"wa3 4eh",
    "addr:street":"Common Lane",
    "iso:country":"GB",
    "sg:address":"1 Common Lane, Culcheth",
    "sg:city":"Warrington",
    "sg:classifiers":[
        {
            "category":"Professional",
            "subcategory":"Accounting & Tax Preparation",
            "type":"Services"
        }
    ],
    "sg:phone":"+44 1925 766688",
    "sg:postcode":"WA3 4EH",
    "sg:province":"Cheshire",
    "sg:tags":[
        "accountant"
    ],
    "wof:name":"The Self Employed Taxation Co.",
    "wof:placetype":"venue"
},
  "geometry": {"coordinates":[-2.519878,53.452141],"type":"Point"}
}