{
  "type": "Feature",
  "properties": {
    "addr:full":"Unit A, Rear Of 137-165 Hook Road Surbiton Surrey KT6 5AR",
    "addr:housenumber":"unit a;137-165",
    "addr:postcode":"kt6 5ar",
    "addr:street":"Hook Road",
    "iso:country":"GB",
    "sg:address":"Unit A, Rear Of 137-165 Hook Road",
    "sg:city":"Surbiton",
    "sg:classifiers":[
        {
            "category":"Building & Trades",
            "subcategory":"Construction",
            "type":"Services"
        }
    ],
    "sg:postcode":"KT6 5AR",
    "sg:province":"Surrey",
    "sg:tags":[
        "restoration",
        "refurbishment"
    ],
    "wof:name":"Bronze Restorations",
    "wof:placetype":"venue"
},
  "geometry": {"coordinates":[-0.306949,51.392059],"type":"Point"}
}