{
  "type": "Feature",
  "properties": {
    "iso:country":"GB",
    "sg:address":"Fern Lea, Mill Lane",
    "sg:city":"Kingsbridge",
    "sg:classifiers":[
        {
            "category":"Home & Garden",
            "subcategory":"Kitchen Supply",
            "type":"Retail Goods"
        }
    ],
    "sg:phone":"+44 1548 531372",
    "sg:postcode":"TQ7 2NZ",
    "sg:province":"Devon",
    "sg:tags":[
        "glassware",
        "china"
    ],
    "wof:name":"China Matching Service",
    "wof:placetype":"venue"
},
  "geometry": {"coordinates":[-3.777618885,50.2831039429],"type":"Point"}
}