{
  "type": "Feature",
  "properties": {
    "iso:country":"GB",
    "sg:address":"24a Hope Street",
    "sg:city":"Crook",
    "sg:classifiers":[
        {
            "category":"Building & Trades",
            "subcategory":"Electrical",
            "type":"Services"
        }
    ],
    "sg:postcode":"DL15 9HS",
    "sg:province":"Durham",
    "sg:tags":[
        "consultant",
        "lighting"
    ],
    "wof:name":"Vortex Lighting",
    "wof:placetype":"venue"
},
  "geometry": {"coordinates":[-1.7472749949,54.7161636353],"type":"Point"}
}