{
  "type": "Feature",
  "properties": {
    "addr:full":"71 Cumbernauld Road Glasgow Glasgow City G31 2SN",
    "addr:housenumber":"71",
    "addr:postcode":"g31 2sn",
    "addr:street":"Cumbernauld Road",
    "iso:country":"GB",
    "sg:address":"71 Cumbernauld Road",
    "sg:city":"Glasgow",
    "sg:classifiers":[
        {
            "category":"Autos & Motor Vehicles",
            "subcategory":"Fuel & Gas Station",
            "type":"Retail Goods"
        },
        {
            "category":"Wholesale",
            "subcategory":"Machinery & Supplies",
            "type":"Manufacturing & Wholesale Goods"
        }
    ],
    "sg:phone":"+44 141 554 3454",
    "sg:postcode":"G31 2SN",
    "sg:province":"Glasgow City",
    "sg:tags":[
        "pump",
        "sale",
        "servicing"
    ],
    "wof:name":"Ferrier Pumps Ltd",
    "wof:placetype":"venue"
},
  "geometry": {"coordinates":[-4.211518,55.860821],"type":"Point"}
}