{
  "type": "Feature",
  "properties": {
    "addr:full":"80 Annan Road Dumfries Dumfries and Galloway DG1 3EQ",
    "addr:housenumber":"80",
    "addr:postcode":"dg1 3eq",
    "addr:street":"Annan Road",
    "iso:country":"GB",
    "sg:address":"80 Annan Road",
    "sg:city":"Dumfries",
    "sg:classifiers":[
        {
            "category":"Shopping",
            "subcategory":"News",
            "type":"Retail Goods"
        }
    ],
    "sg:postcode":"DG1 3EQ",
    "sg:province":"Dumfries and Galloway",
    "sg:tags":[
        "newsagent"
    ],
    "wof:name":"Fresh N' Tastey",
    "wof:placetype":"venue"
},
  "geometry": {"coordinates":[-3.5952150822,55.0702857971],"type":"Point"}
}