{
  "type": "Feature",
  "properties": {
    "addr:full":"25 Brighton Rd South Croydon Surrey CR2 6EA",
    "addr:housenumber":"25",
    "addr:postcode":"cr2 6ea",
    "addr:street":"Brighton Rd",
    "iso:country":"GB",
    "sg:address":"25 Brighton Rd",
    "sg:city":"South Croydon",
    "sg:classifiers":[
        {
            "category":"Professional",
            "subcategory":"Accounting & Tax Preparation",
            "type":"Services"
        }
    ],
    "sg:postcode":"CR2 6EA",
    "sg:province":"Surrey",
    "sg:tags":[
        "accountant"
    ],
    "wof:name":"Pestell,John,",
    "wof:placetype":"venue"
},
  "geometry": {"coordinates":[-0.098003,51.361382],"type":"Point"}
}