{
  "type": "Feature",
  "properties": {
    "iso:country":"GB",
    "sg:address":"Grovebeck Grange, North Drove, Quadring Fen",
    "sg:city":"Spalding",
    "sg:classifiers":[
        {
            "category":"Recreation",
            "type":"Entertainment"
        }
    ],
    "sg:postcode":"PE11 4QS",
    "sg:province":"Lincolnshire",
    "sg:tags":[
        "outdoor",
        "pursuit"
    ],
    "wof:name":"Laser Like A Shot",
    "wof:placetype":"venue"
},
  "geometry": {"coordinates":[-0.180444,52.881104],"type":"Point"}
}