{
  "type": "Feature",
  "properties": {
    "iso:country":"GB",
    "sg:address":"141 Quarry Street",
    "sg:city":"Hamilton",
    "sg:classifiers":[
        {
            "category":"Shopping",
            "subcategory":"Thrift Store",
            "type":"Retail Goods"
        }
    ],
    "sg:phone":"+44 1698 282153",
    "sg:postcode":"ML3 7DR",
    "sg:province":"South Lanarkshire",
    "sg:tags":[
        "shop",
        "charity"
    ],
    "wof:name":"St Andrews Hospice Shop",
    "wof:placetype":"venue"
},
  "geometry": {"coordinates":[-4.037239,55.7733],"type":"Point"}
}