{
  "type": "Feature",
  "properties": {
    "addr:full":"8 Lanier Rd Lewisham Greater London SE13 6HU",
    "addr:housenumber":"8",
    "addr:postcode":"se13 6hu",
    "addr:street":"Lanier Rd",
    "iso:country":"GB",
    "sg:address":"8 Lanier Rd",
    "sg:city":"Lewisham",
    "sg:classifiers":[
        {
            "category":"Building & Trades",
            "subcategory":"Cleaning & Sanitation",
            "type":"Services"
        }
    ],
    "sg:phone":"+44 20 8318 1251",
    "sg:postcode":"SE13 6HU",
    "sg:province":"Greater London",
    "sg:tags":[
        "commercial"
    ],
    "wof:name":"Deep Kleen Services",
    "wof:placetype":"venue"
},
  "geometry": {"coordinates":[-0.007493,51.4519920349],"type":"Point"}
}