{
  "type": "Feature",
  "properties": {
    "iso:country":"GB",
    "sg:address":"40 Shannon Avenue",
    "sg:city":"Rayleigh",
    "sg:classifiers":[
        {
            "category":"Building & Trades",
            "subcategory":"Plumbing",
            "type":"Services"
        }
    ],
    "sg:phone":"+44 1268 774936",
    "sg:postcode":"SS6 7ST",
    "sg:province":"Essex",
    "sg:tags":[
        "heating"
    ],
    "wof:name":"T Stagg",
    "wof:placetype":"venue"
},
  "geometry": {"coordinates":[0.605208,51.579876],"type":"Point"}
}