{
  "type": "Feature",
  "properties": {
    "iso:country":"GB",
    "sg:address":"Thorncliffe Park Est",
    "sg:city":"Sheffield",
    "sg:classifiers":[
        {
            "category":"Manufacturing",
            "subcategory":"Metals",
            "type":"Manufacturing & Wholesale Goods"
        }
    ],
    "sg:phone":"+44 114 257 1110",
    "sg:postcode":"S35 2PH",
    "sg:province":"South Yorkshire",
    "sg:tags":[
        "steel",
        "fabricator",
        "erectors"
    ],
    "wof:name":"M J P Fabrications Ltd",
    "wof:placetype":"venue"
},
  "geometry": {"coordinates":[-1.475621,53.473679],"type":"Point"}
}