{
  "type": "Feature",
  "properties": {
    "iso:country":"GB",
    "sg:address":"56 Whifflet Street",
    "sg:city":"Coatbridge",
    "sg:classifiers":[
        {
            "category":"Government",
            "subcategory":"Post Office",
            "type":"Public Place"
        }
    ],
    "sg:phone":"+44 1236 424153",
    "sg:postcode":"ML5 4EL",
    "sg:province":"North Lanarkshire",
    "wof:name":"W K & D G Dick",
    "wof:placetype":"venue"
},
  "geometry": {"coordinates":[-4.020574,55.852699],"type":"Point"}
}