{
  "type": "Feature",
  "properties": {
    "addr:full":"21 Arden Way Market Harborough Leicestershire LE16 7DB",
    "addr:housenumber":"21",
    "addr:postcode":"le16 7db",
    "addr:street":"Arden Way",
    "iso:country":"GB",
    "sg:address":"21 Arden Way",
    "sg:city":"Market Harborough",
    "sg:classifiers":[
        {
            "category":"Professional",
            "subcategory":"Engineering",
            "type":"Services"
        }
    ],
    "sg:postcode":"LE16 7DB",
    "sg:province":"Leicestershire",
    "sg:tags":[
        "contractor",
        "electrical",
        "engineer"
    ],
    "wof:name":"A R Winters Electrical Contractors",
    "wof:placetype":"venue"
},
  "geometry": {"coordinates":[-0.9114739895,52.4840354919],"type":"Point"}
}