{
  "type": "Feature",
  "properties": {
    "addr:full":"10 Market Place, Whittlesey Peterborough Cambridgeshire PE7 1AB",
    "addr:housenumber":"10",
    "addr:postcode":"pe7 1ab",
    "addr:street":"Market Place",
    "iso:country":"GB",
    "sg:address":"10 Market Place, Whittlesey",
    "sg:city":"Peterborough",
    "sg:classifiers":[
        {
            "category":"Bars & Pubs",
            "type":"Food & Drink"
        },
        {
            "category":"Community Center",
            "subcategory":"Social",
            "type":"Public Place"
        }
    ],
    "sg:phone":"+44 1733 202516",
    "sg:postcode":"PE7 1AB",
    "sg:province":"Cambridgeshire",
    "sg:tags":[
        "pubs",
        "house",
        "inn",
        "activity"
    ],
    "wof:name":"GEORGE HOTEL",
    "wof:placetype":"venue"
},
  "geometry": {"coordinates":[-0.1283189952,52.5566520691],"type":"Point"}
}