{
  "type": "Feature",
  "properties": {
    "iso:country":"GB",
    "sg:address":"Fellowship House, Park Road",
    "sg:city":"Congleton",
    "sg:classifiers":[
        {
            "category":"Government",
            "subcategory":"Office",
            "type":"Public Place"
        }
    ],
    "sg:phone":"+44 1260 274300",
    "sg:postcode":"CW12 1DP",
    "sg:province":"Cheshire",
    "sg:tags":[
        "local"
    ],
    "wof:name":"Fellowship House Day Centre",
    "wof:placetype":"venue"
},
  "geometry": {"coordinates":[-2.210169,53.165321],"type":"Point"}
}