{
  "type": "Feature",
  "properties": {
    "addr:full":"Burlington Lodge, Buer Rd Fulham Greater London SW6 4JJ",
    "addr:postcode":"sw6 4jj",
    "addr:street":"Buer Rd",
    "iso:country":"GB",
    "sg:address":"Burlington Lodge, Buer Rd",
    "sg:city":"Fulham",
    "sg:classifiers":[
        {
            "category":"Health Services",
            "subcategory":"Clinic",
            "type":"Services"
        }
    ],
    "sg:phone":"+44 20 7371 8553",
    "sg:postcode":"SW6 4JJ",
    "sg:province":"Greater London",
    "sg:tags":[
        "private"
    ],
    "wof:name":"London Bedwetting Clinic",
    "wof:placetype":"venue"
},
  "geometry": {"coordinates":[-0.2105910033,51.4713859558],"type":"Point"}
}