{
  "type": "Feature",
  "properties": {
    "iso:country":"GB",
    "sg:address":"242 Howlands",
    "sg:city":"Welwyn Garden City",
    "sg:classifiers":[
        {
            "category":"Wholesale",
            "subcategory":"Electrical",
            "type":"Manufacturing & Wholesale Goods"
        }
    ],
    "sg:postcode":"AL7 4HF",
    "sg:province":"Hertfordshire",
    "sg:tags":[
        "equipment",
        "refrigeration"
    ],
    "wof:name":"Bond Display Equipment",
    "wof:placetype":"venue"
},
  "geometry": {"coordinates":[-0.186157003,51.7848815918],"type":"Point"}
}