{
  "type": "Feature",
  "properties": {
    "iso:country":"GB",
    "sg:address":"33 Warren Street",
    "sg:city":"Stockport",
    "sg:classifiers":[
        {
            "category":"Shopping",
            "subcategory":"Mobile Phones",
            "type":"Retail Goods"
        }
    ],
    "sg:phone":"+44 161 476 4761",
    "sg:postcode":"SK1 1UD",
    "sg:province":"Cheshire",
    "wof:name":"Raj Singh",
    "wof:placetype":"venue"
},
  "geometry": {"coordinates":[-2.155749,53.413021],"type":"Point"}
}