{
  "type": "Feature",
  "properties": {
    "iso:country":"GB",
    "sg:address":"69 Hull Road",
    "sg:city":"York",
    "sg:classifiers":[
        {
            "category":"Education",
            "subcategory":"Music School",
            "type":"Public Place"
        }
    ],
    "sg:postcode":"YO1 3JS",
    "sg:province":"North Yorkshire",
    "sg:tags":[
        "teacher"
    ],
    "wof:name":"K M White",
    "wof:placetype":"venue"
},
  "geometry": {"coordinates":[-1.054198,53.954018],"type":"Point"}
}