{
  "type": "Feature",
  "properties": {
    "iso:country":"GB",
    "sg:address":"Peterborough Road",
    "sg:city":"London",
    "sg:classifiers":[
        {
            "category":"Social Services",
            "subcategory":"Adult Care",
            "type":"Services"
        },
        {
            "category":"Government",
            "subcategory":"Office",
            "type":"Public Place"
        }
    ],
    "sg:phone":"+44 20 7731 6744",
    "sg:postcode":"SW6 3HQ",
    "sg:province":"Greater London",
    "sg:tags":[
        "housing",
        "local",
        "sheltered"
    ],
    "wof:name":"Philpott Square Sheltered Housing",
    "wof:placetype":"venue"
},
  "geometry": {"coordinates":[-0.199334,51.472569],"type":"Point"}
}