{
  "type": "Feature",
  "properties": {
    "iso:country":"GB",
    "sg:address":"82 Collieston Circle",
    "sg:city":"Aberdeen",
    "sg:classifiers":[
        {
            "category":"Personal",
            "type":"Services"
        }
    ],
    "sg:postcode":"AB22 8UT",
    "sg:province":"Aberdeen City",
    "sg:tags":[
        "tailor"
    ],
    "wof:name":"Jan Cederstrom",
    "wof:placetype":"venue"
},
  "geometry": {"coordinates":[-2.110068,57.190392],"type":"Point"}
}