{
  "type": "Feature",
  "properties": {
    "iso:country":"GB",
    "sg:address":"Market Chambers, Market Place",
    "sg:city":"Shifnal",
    "sg:classifiers":[
        {
            "category":"Professional",
            "subcategory":"Employment Agencies",
            "type":"Services"
        }
    ],
    "sg:phone":"+44 1952 462671",
    "sg:postcode":"TF11 9AZ",
    "sg:province":"Shropshire",
    "sg:tags":[
        "consultant"
    ],
    "wof:name":"S H L Recruitment",
    "wof:placetype":"venue"
},
  "geometry": {"coordinates":[-2.372779,52.665485],"type":"Point"}
}