{
  "type": "Feature",
  "properties": {
    "iso:country":"GB",
    "sg:address":"9 Rossall Close, Padiham",
    "sg:city":"Burnley",
    "sg:classifiers":[
        {
            "category":"Manufacturing",
            "subcategory":"Metals",
            "type":"Manufacturing & Wholesale Goods"
        },
        {
            "category":"Wholesale",
            "subcategory":"Scrap",
            "type":"Manufacturing & Wholesale Goods"
        }
    ],
    "sg:phone":"+44 1282 771694",
    "sg:postcode":"BB12 7DQ",
    "sg:province":"Lancashire",
    "sg:tags":[
        "waste"
    ],
    "wof:name":"R M Clark",
    "wof:placetype":"venue"
},
  "geometry": {"coordinates":[-2.3066079617,53.7915496826],"type":"Point"}
}