{
  "type": "Feature",
  "properties": {
    "iso:country":"GB",
    "sg:address":"10 Cromwell Hill",
    "sg:city":"Luton",
    "sg:classifiers":[
        {
            "category":"Real Estate",
            "subcategory":"Real Estate Operator",
            "type":"Services"
        }
    ],
    "sg:phone":"+44 1582 416565",
    "sg:postcode":"LU2 7PY",
    "sg:province":"Bedfordshire",
    "sg:tags":[
        "letting",
        "agent"
    ],
    "wof:name":"James Green & Nephew",
    "wof:placetype":"venue"
},
  "geometry": {"coordinates":[-0.420056,51.887493],"type":"Point"}
}