{
  "type": "Feature",
  "properties": {
    "iso:country":"GB",
    "sg:address":"8 New Court, Lordship Road",
    "sg:city":"London",
    "sg:classifiers":[
        {
            "category":"Professional",
            "subcategory":"Accounting & Tax Preparation",
            "type":"Services"
        }
    ],
    "sg:phone":"+44 20 8800 3943",
    "sg:postcode":"N16 5HJ",
    "sg:province":"Greater London",
    "sg:tags":[
        "accountant",
        "activity"
    ],
    "wof:name":"Manfred Storz",
    "wof:placetype":"venue"
},
  "geometry": {"coordinates":[-0.08684,51.568901],"type":"Point"}
}