{
  "type": "Feature",
  "properties": {
    "iso:country":"GB",
    "sg:address":"45 Brampton Gro",
    "sg:city":"London",
    "sg:classifiers":[
        {
            "category":"Organizations",
            "subcategory":"Non-profit Organization",
            "type":"Services"
        }
    ],
    "sg:phone":"+44 20 8202 0472",
    "sg:postcode":"NW4 4AH",
    "sg:province":"Greater London",
    "sg:tags":[
        "organisation",
        "voluntary",
        "charity"
    ],
    "wof:name":"Akim",
    "wof:placetype":"venue"
},
  "geometry": {"coordinates":[-0.233509,51.592522],"type":"Point"}
}