{
  "type": "Feature",
  "properties": {
    "iso:country":"GB",
    "sg:address":"Francis House, Totman Crescent",
    "sg:city":"Rayleigh",
    "sg:classifiers":[
        {
            "category":"Retail",
            "subcategory":"Auto Repair",
            "type":"Services"
        }
    ],
    "sg:phone":"+44 1268 774813",
    "sg:postcode":"SS6 7UY",
    "sg:province":"Essex",
    "sg:tags":[
        "modification",
        "garage"
    ],
    "wof:name":"Cambelt King",
    "wof:placetype":"venue"
},
  "geometry": {"coordinates":[0.6046299934,51.5780181885],"type":"Point"}
}