{
  "type": "Feature",
  "properties": {
    "addr:full":"1-28 The Broadway, Ealing London Greater London W5 2ND",
    "addr:housenumber":"1-28",
    "addr:postcode":"w5 2nd",
    "addr:street":"The Broadway",
    "iso:country":"GB",
    "sg:address":"1-28 The Broadway, Ealing",
    "sg:city":"London",
    "sg:classifiers":[
        {
            "category":"Shopping",
            "subcategory":"Baby Store",
            "type":"Retail Goods"
        }
    ],
    "sg:phone":"+44 20 8579 6181",
    "sg:postcode":"W5 2ND",
    "sg:province":"Greater London",
    "sg:tags":[
        "nursery",
        "accessory"
    ],
    "wof:name":"Mothercare (U K) Ltd.",
    "wof:placetype":"venue"
},
  "geometry": {"coordinates":[-0.302713,51.513931],"type":"Point"}
}