{
  "type": "Feature",
  "properties": {
    "addr:full":"23 Castle Square Caernarfon Gwynedd LL55 2NA",
    "addr:housenumber":"23",
    "addr:postcode":"ll55 2na",
    "addr:street":"Castle Square",
    "iso:country":"GB",
    "sg:address":"23 Castle Square",
    "sg:city":"Caernarfon",
    "sg:classifiers":[
        {
            "category":"Real Estate",
            "subcategory":"Real Estate Agent",
            "type":"Services"
        }
    ],
    "sg:phone":"+44 1286 673286",
    "sg:postcode":"LL55 2NA",
    "sg:province":"Gwynedd",
    "wof:name":"Bob Parry & Co. Ltd.",
    "wof:placetype":"venue"
},
  "geometry": {"coordinates":[-4.274994,53.139687],"type":"Point"}
}