{
  "type": "Feature",
  "properties": {
    "iso:country":"GB",
    "sg:address":"17-21 Newtown Street, Kilsyth",
    "sg:city":"Glasgow",
    "sg:classifiers":[
        {
            "category":"Wholesale",
            "subcategory":"Music Publishers",
            "type":"Manufacturing & Wholesale Goods"
        }
    ],
    "sg:phone":"+44 1236 821081",
    "sg:postcode":"G65 0JX",
    "sg:province":"East Dunbartonshire",
    "sg:tags":[
        "record"
    ],
    "wof:name":"B G S Productions Ltd.",
    "wof:placetype":"venue"
},
  "geometry": {"coordinates":[-4.057804,55.975212],"type":"Point"}
}