{
  "type": "Feature",
  "properties": {
    "addr:full":"10a Beechings Ways Industrial Estate Alford Lincolnshire LN13 9JE",
    "addr:housenumber":"10a;estate",
    "addr:postcode":"ln13 9je",
    "addr:street":"Beechings Ways Industrial",
    "iso:country":"GB",
    "sg:address":"10a Beechings Ways Industrial Estate",
    "sg:city":"Alford",
    "sg:classifiers":[
        {
            "category":"Shopping",
            "subcategory":"Computers & Home Electronics",
            "type":"Retail Goods"
        }
    ],
    "sg:postcode":"LN13 9JE",
    "sg:province":"Lincolnshire",
    "sg:tags":[
        "consumables"
    ],
    "wof:name":"Nec Computer Services",
    "wof:placetype":"venue"
},
  "geometry": {"coordinates":[0.180093,53.261505],"type":"Point"}
}