{
  "type": "Feature",
  "properties": {
    "addr:full":"11 Church Road, Bishops Cleeve Cheltenham Gloucestershire GL52 8LR",
    "addr:housenumber":"11",
    "addr:postcode":"gl52 8lr",
    "addr:street":"Church Road",
    "iso:country":"GB",
    "sg:address":"11 Church Road, Bishops Cleeve",
    "sg:city":"Cheltenham",
    "sg:classifiers":[
        {
            "category":"Fast Food",
            "type":"Food & Drink"
        },
        {
            "category":"Restaurant",
            "type":"Food & Drink"
        }
    ],
    "sg:phone":"+44 1242 676006",
    "sg:postcode":"GL52 8LR",
    "sg:province":"Gloucestershire",
    "sg:tags":[
        "away",
        "indian",
        "-",
        "take"
    ],
    "wof:name":"Taj Mahal Balti House",
    "wof:placetype":"venue"
},
  "geometry": {"coordinates":[-2.0613861084,51.9475250244],"type":"Point"}
}