{
  "type": "Feature",
  "properties": {
    "addr:full":"139 Neath Road, Hafod Swansea Neath Port Talbot SA1 2LG",
    "addr:housenumber":"139",
    "addr:postcode":"sa1 2lg",
    "addr:street":"Neath Road Hafod",
    "iso:country":"GB",
    "sg:address":"139 Neath Road, Hafod",
    "sg:city":"Swansea",
    "sg:classifiers":[
        {
            "category":"Autos & Motor Vehicles",
            "subcategory":"Auto Supplies",
            "type":"Retail Goods"
        }
    ],
    "sg:phone":"+44 1792 456379",
    "sg:postcode":"SA1 2LG",
    "sg:province":"Neath Port Talbot",
    "sg:tags":[
        "tyre"
    ],
    "wof:name":"Ats",
    "wof:placetype":"venue"
},
  "geometry": {"coordinates":[-3.9381370544,51.6362075806],"type":"Point"}
}