{
  "type": "Feature",
  "properties": {
    "addr:full":"Brettell Lane Brierley Hill West Midlands DY5 3LT",
    "addr:postcode":"dy5 3lt",
    "addr:street":"Lane",
    "iso:country":"GB",
    "sg:address":"Brettell Lane",
    "sg:city":"Brierley Hill",
    "sg:classifiers":[
        {
            "category":"Community Center",
            "type":"Public Place"
        },
        {
            "category":"Government",
            "subcategory":"Office",
            "type":"Public Place"
        }
    ],
    "sg:phone":"+44 1384 79188",
    "sg:postcode":"DY5 3LT",
    "sg:province":"West Midlands",
    "sg:tags":[
        "local",
        "centre"
    ],
    "wof:name":"Hawbush Community Centre",
    "wof:placetype":"venue"
},
  "geometry": {"coordinates":[-2.1339440346,52.4754905701],"type":"Point"}
}