{
  "type": "Feature",
  "properties": {
    "iso:country":"GB",
    "sg:address":"Unit 40, Camphill Industrial Estate, John Kempe Way",
    "sg:city":"Birmingham",
    "sg:classifiers":[
        {
            "category":"Shopping",
            "subcategory":"Clothing, Apparel, & Fashions",
            "type":"Retail Goods"
        }
    ],
    "sg:phone":"+44 121 753 0963",
    "sg:postcode":"B12 0HU",
    "sg:province":"West Midlands",
    "sg:tags":[
        "sportswear"
    ],
    "wof:name":"Gamebird Products Ltd.",
    "wof:placetype":"venue"
},
  "geometry": {"coordinates":[-1.908604,52.478596],"type":"Point"}
}