{
  "type": "Feature",
  "properties": {
    "iso:country":"GB",
    "sg:address":"Ladybrook La",
    "sg:city":"Mansfield",
    "sg:classifiers":[
        {
            "category":"Education",
            "subcategory":"Library",
            "type":"Public Place"
        }
    ],
    "sg:phone":"+44 1623 622835",
    "sg:postcode":"NG18 5JH",
    "sg:province":"Nottinghamshire",
    "sg:tags":[
        "book"
    ],
    "wof:name":"Ladybrook Library",
    "wof:placetype":"venue"
},
  "geometry": {"coordinates":[-1.207409,53.147549],"type":"Point"}
}