{
  "type": "Feature",
  "properties": {
    "iso:country":"GB",
    "sg:address":"Unit 10,smethwick Enterprise Centre, Rolfe St",
    "sg:city":"Smethwick",
    "sg:classifiers":[
        {
            "category":"Professional",
            "subcategory":"Printing & Photocopies",
            "type":"Services"
        }
    ],
    "sg:phone":"+44 121 680 1906",
    "sg:postcode":"B66 2AR",
    "sg:province":"West Midlands",
    "sg:tags":[
        "printer"
    ],
    "wof:name":"Bede Press Ltd",
    "wof:placetype":"venue"
},
  "geometry": {"coordinates":[-1.971184,52.495926],"type":"Point"}
}