{
  "type": "Feature",
  "properties": {
    "iso:country":"GB",
    "sg:address":"145 South Farm Road",
    "sg:city":"Worthing",
    "sg:classifiers":[
        {
            "category":"Banks & Credit Unions",
            "subcategory":"Financial Services",
            "type":"Services"
        }
    ],
    "sg:phone":"+44 1903 824415",
    "sg:postcode":"BN14 7AX",
    "sg:province":"West Sussex",
    "sg:tags":[
        "adviser"
    ],
    "wof:name":"A S C Independent Financial Advisers",
    "wof:placetype":"venue"
},
  "geometry": {"coordinates":[-0.379856,50.824978],"type":"Point"}
}