{
  "type": "Feature",
  "properties": {
    "addr:full":"18 Kings Road Harrogate North Yorkshire HG1 1BT",
    "addr:housenumber":"18",
    "addr:postcode":"hg1 1bt",
    "addr:street":"Kings Road",
    "iso:country":"GB",
    "sg:address":"18 Kings Road",
    "sg:city":"Harrogate",
    "sg:classifiers":[
        {
            "category":"Restaurant",
            "type":"Food & Drink"
        }
    ],
    "sg:phone":"+44 1423 563680",
    "sg:postcode":"HG1 1BT",
    "sg:province":"North Yorkshire",
    "sg:tags":[
        "indian"
    ],
    "wof:name":"TAPAS TREE RESTAURANT",
    "wof:placetype":"venue"
},
  "geometry": {"coordinates":[-1.5431879759,53.9952125549],"type":"Point"}
}