{
  "type": "Feature",
  "properties": {
    "addr:full":"111 Leagate, Harwood Bolton Lancashire BL2 4BQ",
    "addr:housenumber":"111",
    "addr:postcode":"bl2 4bq",
    "addr:street":"Leagate Harwood",
    "iso:country":"GB",
    "sg:address":"111 Leagate, Harwood",
    "sg:city":"Bolton",
    "sg:classifiers":[
        {
            "category":"Shopping",
            "subcategory":"News",
            "type":"Retail Goods"
        }
    ],
    "sg:phone":"+44 1204 304277",
    "sg:postcode":"BL2 4BQ",
    "sg:province":"Lancashire",
    "sg:tags":[
        "newsagent"
    ],
    "wof:name":"Leagate News",
    "wof:placetype":"venue"
},
  "geometry": {"coordinates":[-2.3965189457,53.6070098877],"type":"Point"}
}