{
  "type": "Feature",
  "properties": {
    "iso:country":"GB",
    "sg:address":"43 Parsonage Road, Heaton Moor",
    "sg:city":"Stockport",
    "sg:classifiers":[
        {
            "category":"Social Services",
            "subcategory":"Retirement Home",
            "type":"Services"
        }
    ],
    "sg:postcode":"SK4 4JW",
    "sg:province":"Cheshire",
    "sg:tags":[
        "residential",
        "care"
    ],
    "wof:name":"Redcroft Residential Care",
    "wof:placetype":"venue"
},
  "geometry": {"coordinates":[-2.181395,53.420685],"type":"Point"}
}