{
  "type": "Feature",
  "properties": {
    "addr:full":"15 The Square, Beeston Nottingham Nottinghamshire NG9 2JR",
    "addr:housenumber":"15",
    "addr:postcode":"ng9 2jr",
    "addr:street":"The Square",
    "iso:country":"GB",
    "sg:address":"15 The Square, Beeston",
    "sg:city":"Nottingham",
    "sg:classifiers":[
        {
            "category":"Sports & Exercise",
            "subcategory":"Sports Center",
            "type":"Entertainment"
        }
    ],
    "sg:phone":"+44 115 967 7892",
    "sg:postcode":"NG9 2JR",
    "sg:province":"Nottinghamshire",
    "sg:tags":[
        "shop",
        "good"
    ],
    "wof:name":"Robinson Sports Ltd",
    "wof:placetype":"venue"
},
  "geometry": {"coordinates":[-1.1990300417,52.9270591736],"type":"Point"}
}