{
  "type": "Feature",
  "properties": {
    "iso:country":"GB",
    "sg:address":"Amwell House",
    "sg:city":"Hoddesdon",
    "sg:classifiers":[
        {
            "category":"Professional",
            "subcategory":"Accounting & Tax Preparation",
            "type":"Services"
        }
    ],
    "sg:phone":"+44 1992 444466",
    "sg:postcode":"EN11 8TS",
    "sg:province":"Essex",
    "sg:tags":[
        "accountant"
    ],
    "wof:name":"Hardcastle Burton",
    "wof:placetype":"venue"
},
  "geometry": {"coordinates":[-0.012399,51.754623],"type":"Point"}
}