{
  "type": "Feature",
  "properties": {
    "iso:country":"GB",
    "sg:address":"62 Station Road",
    "sg:city":"Port Talbot",
    "sg:classifiers":[
        {
            "category":"Organizations",
            "subcategory":"Membership Organization",
            "type":"Services"
        }
    ],
    "sg:phone":"+44 1639 882040",
    "sg:postcode":"SA13 1LZ",
    "sg:province":"Neath Port Talbot",
    "sg:tags":[
        "club"
    ],
    "wof:name":"Port Talbot & Aberavon Constitutional Club",
    "wof:placetype":"venue"
},
  "geometry": {"coordinates":[-3.782814,51.595764],"type":"Point"}
}