{
  "type": "Feature",
  "properties": {
    "addr:full":"60 Tower Street Dudley West Midlands DY1 1NQ",
    "addr:housenumber":"60",
    "addr:postcode":"dy1 1nq",
    "addr:street":"Tower Street",
    "iso:country":"GB",
    "sg:address":"60 Tower Street",
    "sg:city":"Dudley",
    "sg:classifiers":[
        {
            "category":"Home & Garden",
            "subcategory":"Furniture",
            "type":"Retail Goods"
        }
    ],
    "sg:phone":"+44 1384 258616",
    "sg:postcode":"DY1 1NQ",
    "sg:province":"West Midlands",
    "wof:name":"James Gill",
    "wof:placetype":"venue"
},
  "geometry": {"coordinates":[-2.083119,52.511253],"type":"Point"}
}