{
  "type": "Feature",
  "properties": {
    "addr:full":"Priors Corner, North Warnborough Hook Hampshire RG29 1ES",
    "addr:postcode":"rg29 1es",
    "addr:street":"North;Hook",
    "iso:country":"GB",
    "sg:address":"Priors Corner, North Warnborough",
    "sg:city":"Hook",
    "sg:classifiers":[
        {
            "category":"Professional",
            "subcategory":"Engineering",
            "type":"Services"
        }
    ],
    "sg:phone":"+44 1256 701687",
    "sg:postcode":"RG29 1ES",
    "sg:province":"Hampshire",
    "sg:tags":[
        "consulting",
        "engineer"
    ],
    "wof:name":"Epizym Diosystems Ltd",
    "wof:placetype":"venue"
},
  "geometry": {"coordinates":[-0.9525129795,51.2594985962],"type":"Point"}
}