{
  "type": "Feature",
  "properties": {
    "iso:country":"GB",
    "sg:address":"20 Northfield Rd",
    "sg:city":"Birmingham",
    "sg:classifiers":[
        {
            "category":"Building & Trades",
            "subcategory":"Construction",
            "type":"Services"
        }
    ],
    "sg:phone":"+44 121 427 7499",
    "sg:postcode":"B17 0SU",
    "sg:province":"West Midlands",
    "sg:tags":[
        "roofing"
    ],
    "wof:name":"Able Craftmen",
    "wof:placetype":"venue"
},
  "geometry": {"coordinates":[-1.966258049,52.4547271729],"type":"Point"}
}