{
  "type": "Feature",
  "properties": {
    "addr:full":"85 Beckenham Lane, Shortlands Bromley Kent BR2 0DN",
    "addr:housenumber":"85",
    "addr:postcode":"br2 0dn",
    "addr:street":"Beckenham Lane",
    "iso:country":"GB",
    "sg:address":"85 Beckenham Lane, Shortlands",
    "sg:city":"Bromley",
    "sg:classifiers":[
        {
            "category":"Shopping",
            "subcategory":"Clothing, Apparel, & Fashions",
            "type":"Retail Goods"
        }
    ],
    "sg:phone":"+44 20 8466 1576",
    "sg:postcode":"BR2 0DN",
    "sg:province":"Kent",
    "sg:tags":[
        "shop"
    ],
    "wof:name":"Le Chic",
    "wof:placetype":"venue"
},
  "geometry": {"coordinates":[0.003339,51.406311],"type":"Point"}
}