{
  "type": "Feature",
  "properties": {
    "addr:full":"Unit 3 Holystone Indstl Est Hebburn Tyne and Wear NE31 1BJ",
    "addr:housenumber":"unit 3",
    "addr:postcode":"ne31 1bj",
    "addr:street":"Indstl Est",
    "iso:country":"GB",
    "sg:address":"Unit 3 Holystone Indstl Est",
    "sg:city":"Hebburn",
    "sg:classifiers":[
        {
            "category":"Manufacturing",
            "subcategory":"Pottery",
            "type":"Manufacturing & Wholesale Goods"
        }
    ],
    "sg:postcode":"NE31 1BJ",
    "sg:province":"Tyne and Wear",
    "wof:name":"Pritchard,Maria,",
    "wof:placetype":"venue"
},
  "geometry": {"coordinates":[-1.5196299553,54.9780082703],"type":"Point"}
}