{
  "type": "Feature",
  "properties": {
    "iso:country":"GB",
    "sg:address":"4 Church St",
    "sg:city":"Llangefni",
    "sg:classifiers":[
        {
            "category":"Food & Beverages",
            "subcategory":"Fruits & Vegetables",
            "type":"Retail Goods"
        }
    ],
    "sg:postcode":"LL77 7DU",
    "sg:province":"Gwynedd",
    "sg:tags":[
        "greengrocer"
    ],
    "wof:name":"Fowlies,Phillip,",
    "wof:placetype":"venue"
},
  "geometry": {"coordinates":[-4.3113718033,53.2572097778],"type":"Point"}
}