{
  "type": "Feature",
  "properties": {
    "addr:full":"7 Robert Way Wickford Essex SS11 8BR",
    "addr:housenumber":"7",
    "addr:postcode":"ss11 8br",
    "addr:street":"Robert Way",
    "iso:country":"GB",
    "sg:address":"7 Robert Way",
    "sg:city":"Wickford",
    "sg:classifiers":[
        {
            "category":"Home & Garden",
            "subcategory":"Home Furnishings",
            "type":"Retail Goods"
        }
    ],
    "sg:phone":"+44 1268 571799",
    "sg:postcode":"SS11 8BR",
    "sg:province":"Essex",
    "sg:tags":[
        "furnishers",
        "planner",
        "bedroom"
    ],
    "wof:name":"Designer Bedrooms",
    "wof:placetype":"venue"
},
  "geometry": {"coordinates":[0.535874,51.607208],"type":"Point"}
}