{
  "type": "Feature",
  "properties": {
    "addr:full":"Rustlings, Nyetimber Copse, West Chiltington Pulborough West Sussex RH20 2NE",
    "addr:postcode":"rh20 2ne",
    "addr:street":"West",
    "iso:country":"GB",
    "sg:address":"Rustlings, Nyetimber Copse, West Chiltington",
    "sg:city":"Pulborough",
    "sg:classifiers":[
        {
            "category":"Professional",
            "subcategory":"Management & Consulting",
            "type":"Services"
        }
    ],
    "sg:postcode":"RH20 2NE",
    "sg:province":"West Sussex",
    "sg:tags":[
        "consultant",
        "business"
    ],
    "wof:name":"Performance Consultants",
    "wof:placetype":"venue"
},
  "geometry": {"coordinates":[-0.5118790269,50.9570770264],"type":"Point"}
}