{
  "type": "Feature",
  "properties": {
    "addr:full":"7 Marton Road Bridlington East Riding of Yorkshire YO16 7AN",
    "addr:housenumber":"7",
    "addr:postcode":"yo16 7an",
    "addr:street":"Marton Road",
    "iso:country":"GB",
    "sg:address":"7 Marton Road",
    "sg:city":"Bridlington",
    "sg:classifiers":[
        {
            "category":"Health Services",
            "subcategory":"Nursing And Care Facility",
            "type":"Services"
        }
    ],
    "sg:phone":"+44 1262 672351",
    "sg:postcode":"YO16 7AN",
    "sg:province":"East Riding of Yorkshire",
    "sg:tags":[
        "home"
    ],
    "wof:name":"The Waynes",
    "wof:placetype":"venue"
},
  "geometry": {"coordinates":[-0.207255,54.09581],"type":"Point"}
}