{
  "type": "Feature",
  "properties": {
    "addr:full":"Silverknowes Golf Course, 118 Silverknowes Rd Edinburgh City of Edinburgh EH4 5ET",
    "addr:housenumber":"118",
    "addr:postcode":"eh4 5et",
    "addr:street":"Silverknowes Rd",
    "iso:country":"GB",
    "sg:address":"Silverknowes Golf Course, 118 Silverknowes Rd",
    "sg:city":"Edinburgh",
    "sg:classifiers":[
        {
            "category":"Government",
            "subcategory":"Office",
            "type":"Public Place"
        }
    ],
    "sg:phone":"+44 131 336 3843",
    "sg:postcode":"EH4 5ET",
    "sg:province":"City of Edinburgh",
    "sg:tags":[
        "local"
    ],
    "wof:name":"Edinburgh Leisure",
    "wof:placetype":"venue"
},
  "geometry": {"coordinates":[-3.268269062,55.9656982422],"type":"Point"}
}