{
  "type": "Feature",
  "properties": {
    "addr:full":"Long Leys, The Ridings, Shotover Oxford Oxfordshire OX3 8TB",
    "addr:postcode":"ox3 8tb",
    "addr:street":"Long Leys The;Shotover",
    "iso:country":"GB",
    "sg:address":"Long Leys, The Ridings, Shotover",
    "sg:city":"Oxford",
    "sg:classifiers":[
        {
            "category":"Professional",
            "subcategory":"Management & Consulting",
            "type":"Services"
        }
    ],
    "sg:phone":"+44 1865 741637",
    "sg:postcode":"OX3 8TB",
    "sg:province":"Oxfordshire",
    "sg:tags":[
        "consultant",
        "business"
    ],
    "wof:name":"Quatro Consulting International",
    "wof:placetype":"venue"
},
  "geometry": {"coordinates":[-1.1903799772,51.7489891052],"type":"Point"}
}