{
  "type": "Feature",
  "properties": {
    "addr:full":"Ebor House Bradford West Yorkshire BD13 3EL",
    "addr:postcode":"bd13 3el",
    "addr:street":"Bradford West",
    "iso:country":"GB",
    "sg:address":"Ebor House",
    "sg:city":"Bradford",
    "sg:classifiers":[
        {
            "category":"Manufacturing",
            "subcategory":"Tools & Machinery",
            "type":"Manufacturing & Wholesale Goods"
        }
    ],
    "sg:phone":"+44 1274 834764",
    "sg:postcode":"BD13 3EL",
    "sg:province":"West Yorkshire",
    "sg:tags":[
        "society",
        "friendly"
    ],
    "wof:name":"The Ebor Group Plc",
    "wof:placetype":"venue"
},
  "geometry": {"coordinates":[-1.849709034,53.7918014526],"type":"Point"}
}