{
  "type": "Feature",
  "properties": {
    "addr:full":"193 Lymington Rd Christchurch Dorset BH23 5EA",
    "addr:housenumber":"193",
    "addr:postcode":"bh23 5ea",
    "addr:street":"Lymington Rd",
    "iso:country":"GB",
    "sg:address":"193 Lymington Rd",
    "sg:city":"Christchurch",
    "sg:classifiers":[
        {
            "category":"Health Services",
            "subcategory":"Dentist",
            "type":"Services"
        }
    ],
    "sg:phone":"+44 1425 270247",
    "sg:postcode":"BH23 5EA",
    "sg:province":"Dorset",
    "wof:name":"M J Dillingham",
    "wof:placetype":"venue"
},
  "geometry": {"coordinates":[-1.706091,50.740234],"type":"Point"}
}