{
  "type": "Feature",
  "properties": {
    "iso:country":"GB",
    "sg:address":"8 Southpark Avenue",
    "sg:city":"Prestwick",
    "sg:classifiers":[
        {
            "category":"Autos & Motor Vehicles",
            "subcategory":"Motorcycle Sales",
            "type":"Retail Goods"
        }
    ],
    "sg:postcode":"KA9 1PY",
    "sg:province":"South Ayrshire",
    "sg:tags":[
        "chauffeur",
        "driven",
        "car"
    ],
    "wof:name":"Executive Chauffeur Drive",
    "wof:placetype":"venue"
},
  "geometry": {"coordinates":[-4.6154761314,55.4945411682],"type":"Point"}
}