{
  "type": "Feature",
  "properties": {
    "addr:full":"37-41 Nicolson Street Edinburgh City of Edinburgh EH8 9BE",
    "addr:housenumber":"37-41",
    "addr:postcode":"eh8 9be",
    "addr:street":"Nicolson Street",
    "iso:country":"GB",
    "sg:address":"37-41 Nicolson Street",
    "sg:city":"Edinburgh",
    "sg:classifiers":[
        {
            "category":"Shopping",
            "subcategory":"Computers & Home Electronics",
            "type":"Retail Goods"
        },
        {
            "category":"Shopping",
            "subcategory":"Used Merchandise",
            "type":"Retail Goods"
        }
    ],
    "sg:phone":"+44 131 668 2736",
    "sg:postcode":"EH8 9BE",
    "sg:province":"City of Edinburgh",
    "sg:tags":[
        "shop",
        "household",
        "second-hand",
        "store"
    ],
    "wof:name":"Pound Savers",
    "wof:placetype":"venue"
},
  "geometry": {"coordinates":[-3.1857209206,55.9464187622],"type":"Point"}
}