{
  "type": "Feature",
  "properties": {
    "iso:country":"GB",
    "sg:address":"64 Station Parade",
    "sg:city":"Harrogate",
    "sg:classifiers":[
        {
            "category":"Food & Beverages",
            "subcategory":"Specialty",
            "type":"Retail Goods"
        }
    ],
    "sg:postcode":"HG1 1TU",
    "sg:province":"North Yorkshire",
    "sg:tags":[
        "product",
        "health"
    ],
    "wof:name":"The Health Food",
    "wof:placetype":"venue"
},
  "geometry": {"coordinates":[-1.538527,53.993561],"type":"Point"}
}