{
  "type": "Feature",
  "properties": {
    "iso:country":"GB",
    "sg:address":"106 Coleridge St",
    "sg:city":"Hove",
    "sg:classifiers":[
        {
            "category":"Manufacturing",
            "subcategory":"Wood Products",
            "type":"Manufacturing & Wholesale Goods"
        },
        {
            "category":"Home & Garden",
            "subcategory":"Building Materials",
            "type":"Retail Goods"
        }
    ],
    "sg:postcode":"BN3 5AA",
    "sg:province":"East Sussex",
    "sg:tags":[
        "roofing",
        "rafter",
        "craftsman",
        "beams"
    ],
    "wof:name":"Taylor,Roy,",
    "wof:placetype":"venue"
},
  "geometry": {"coordinates":[-0.1826879978,50.8351898193],"type":"Point"}
}