{
  "type": "Feature",
  "properties": {
    "iso:country":"GB",
    "sg:address":"Fern House, 4 Onslow Close",
    "sg:city":"Basingstoke",
    "sg:classifiers":[
        {
            "category":"Coffee & Tea",
            "type":"Food & Drink"
        }
    ],
    "sg:phone":"+44 1256 355661",
    "sg:postcode":"RG24 8QL",
    "sg:province":"Hampshire",
    "sg:tags":[
        "merchant"
    ],
    "wof:name":"Layton Fern & Co Ltd",
    "wof:placetype":"venue"
},
  "geometry": {"coordinates":[-1.063947,51.283703],"type":"Point"}
}