{
  "type": "Feature",
  "properties": {
    "iso:country":"GB",
    "sg:address":"34 Moulsham St",
    "sg:city":"Chelmsford",
    "sg:classifiers":[
        {
            "category":"Restaurant",
            "type":"Food & Drink"
        }
    ],
    "sg:phone":"+44 1245 256003",
    "sg:postcode":"CM2 0HX",
    "sg:province":"Essex",
    "sg:tags":[
        "chinese"
    ],
    "wof:name":"I Ching",
    "wof:placetype":"venue"
},
  "geometry": {"coordinates":[0.4726620018,51.7299461365],"type":"Point"}
}