{
  "type": "Feature",
  "properties": {
    "iso:country":"GB",
    "sg:address":"11a Princes Square",
    "sg:city":"Harrogate",
    "sg:classifiers":[
        {
            "category":"Professional",
            "subcategory":"Accounting & Tax Preparation",
            "type":"Services"
        }
    ],
    "sg:phone":"+44 1423 564499",
    "sg:postcode":"HG1 1ND",
    "sg:province":"North Yorkshire",
    "sg:tags":[
        "accountant"
    ],
    "wof:name":"W S Morley & Co",
    "wof:placetype":"venue"
},
  "geometry": {"coordinates":[-1.539214,53.991264],"type":"Point"}
}