{
  "type": "Feature",
  "properties": {
    "iso:country":"GB",
    "sg:address":"23 Ogmore Crescent, Bridgend Industrial Estate",
    "sg:city":"Bridgend",
    "sg:classifiers":[
        {
            "category":"Manufacturing",
            "subcategory":"Wood Products",
            "type":"Manufacturing & Wholesale Goods"
        }
    ],
    "sg:phone":"+44 1656 658918",
    "sg:postcode":"CF31 3TE",
    "sg:province":"Bridgend",
    "sg:tags":[
        "packaging",
        "crate",
        "pallets"
    ],
    "wof:name":"Dove Assembly & Packaging Ltd.",
    "wof:placetype":"venue"
},
  "geometry": {"coordinates":[-3.5648341179,51.5009040833],"type":"Point"}
}