{
  "type": "Feature",
  "properties": {
    "iso:country":"GB",
    "sg:address":"The Street, Bramfield",
    "sg:city":"Halesworth",
    "sg:classifiers":[
        {
            "category":"Bars & Pubs",
            "type":"Food & Drink"
        }
    ],
    "sg:phone":"+44 1986 784214",
    "sg:postcode":"IP19 9HT",
    "sg:province":"Suffolk",
    "sg:tags":[
        "pubs",
        "inn"
    ],
    "wof:name":"The Queens Head",
    "wof:placetype":"venue"
},
  "geometry": {"coordinates":[1.59717,52.32095],"type":"Point"}
}