{
  "type": "Feature",
  "properties": {
    "addr:full":"148 Midsummer Arcade, Central Milton Keynes Milton Keynes Buckinghamshire MK9 3BA",
    "addr:housenumber":"148;arcade",
    "addr:postcode":"mk9 3ba",
    "addr:street":"Midsummer",
    "iso:country":"GB",
    "sg:address":"148 Midsummer Arcade, Central Milton Keynes",
    "sg:city":"Milton Keynes",
    "sg:classifiers":[
        {
            "category":"Shopping",
            "subcategory":"Clothing, Apparel, & Fashions",
            "type":"Retail Goods"
        }
    ],
    "sg:phone":"+44 1908 672182",
    "sg:postcode":"MK9 3BA",
    "sg:province":"Buckinghamshire",
    "sg:tags":[
        "ladieswear"
    ],
    "wof:name":"Oasis",
    "wof:placetype":"venue"
},
  "geometry": {"coordinates":[-0.7545589805,52.0413551331],"type":"Point"}
}