{
  "type": "Feature",
  "properties": {
    "addr:full":"3/77 Comeragh Road London Greater London W14 9HS",
    "addr:housenumber":"3 / 77",
    "addr:postcode":"w14 9hs",
    "addr:street":"Comeragh Road",
    "iso:country":"GB",
    "sg:address":"3/77 Comeragh Road",
    "sg:city":"London",
    "sg:classifiers":[
        {
            "category":"Professional",
            "subcategory":"Management & Consulting",
            "type":"Services"
        }
    ],
    "sg:postcode":"W14 9HS",
    "sg:province":"Greater London",
    "sg:tags":[
        "consultant",
        "business"
    ],
    "wof:name":"The Bush Shepherds (Uk) Ltd",
    "wof:placetype":"venue"
},
  "geometry": {"coordinates":[-0.207495,51.489697],"type":"Point"}
}