{
  "type": "Feature",
  "properties": {
    "iso:country":"GB",
    "sg:address":"31 Danesbury Road",
    "sg:city":"Feltham",
    "sg:classifiers":[
        {
            "category":"Real Estate",
            "subcategory":"Real Estate Services",
            "type":"Services"
        },
        {
            "category":"Building & Trades",
            "subcategory":"Equipment Rental",
            "type":"Services"
        }
    ],
    "sg:phone":"+44 20 8890 8481",
    "sg:postcode":"TW13 5BQ",
    "sg:province":"Greater London",
    "sg:tags":[
        "hire",
        "leasing",
        "plant",
        "machinery"
    ],
    "wof:name":"T J Cadden",
    "wof:placetype":"venue"
},
  "geometry": {"coordinates":[-0.40339,51.444687],"type":"Point"}
}