{
  "type": "Feature",
  "properties": {
    "addr:full":"17 Lewes Road Brighton East Sussex BN2 3HP",
    "addr:housenumber":"17",
    "addr:postcode":"bn2 3hp",
    "addr:street":"Lewes Road",
    "iso:country":"GB",
    "sg:address":"17 Lewes Road",
    "sg:city":"Brighton",
    "sg:classifiers":[
        {
            "category":"Food & Beverages",
            "subcategory":"Fruits & Vegetables",
            "type":"Retail Goods"
        }
    ],
    "sg:postcode":"BN2 3HP",
    "sg:province":"East Sussex",
    "sg:tags":[
        "greengrocer"
    ],
    "wof:name":"Zohra Exotic Foodstores",
    "wof:placetype":"venue"
},
  "geometry": {"coordinates":[-0.1276520044,50.8337364197],"type":"Point"}
}