{
  "type": "Feature",
  "properties": {
    "addr:full":"Key Hills, Martin Top Lane, Rimington Clitheroe Lancashire BB7 4EG",
    "addr:postcode":"bb7 4eg",
    "addr:street":"Top Lane",
    "iso:country":"GB",
    "sg:address":"Key Hills, Martin Top Lane, Rimington",
    "sg:city":"Clitheroe",
    "sg:classifiers":[
        {
            "category":"Manufacturing",
            "subcategory":"Textiles",
            "type":"Manufacturing & Wholesale Goods"
        }
    ],
    "sg:phone":"+44 1200 445362",
    "sg:postcode":"BB7 4EG",
    "sg:province":"Lancashire",
    "sg:tags":[
        "merchant",
        "agent"
    ],
    "wof:name":"Jeremy Grimshaw (1984) Ltd.",
    "wof:placetype":"venue"
},
  "geometry": {"coordinates":[-2.2866580486,53.908416748],"type":"Point"}
}