{
  "type": "Feature",
  "properties": {
    "addr:full":"Silver Street, Brownhills Brierley Hill Staffordshire WS8 6DZ",
    "addr:postcode":"ws8 6dz",
    "addr:street":"Silver Street",
    "iso:country":"GB",
    "sg:address":"Silver Street, Brownhills",
    "sg:city":"Brierley Hill",
    "sg:classifiers":[
        {
            "category":"Autos & Motor Vehicles",
            "subcategory":"Fuel & Gas Station",
            "type":"Retail Goods"
        },
        {
            "category":"Food & Beverages",
            "subcategory":"Supermarket",
            "type":"Retail Goods"
        }
    ],
    "sg:phone":"+44 845 677 9696",
    "sg:postcode":"WS8 6DZ",
    "sg:province":"Staffordshire",
    "sg:tags":[
        "petrol",
        "filling"
    ],
    "sg:website":"http://www.tesco.com",
    "wof:name":"Tesco Stores Ltd",
    "wof:placetype":"venue"
},
  "geometry": {"coordinates":[-1.935544014,52.6468162537],"type":"Point"}
}