{
  "type": "Feature",
  "properties": {
    "iso:country":"GB",
    "sg:address":"Deer House Farm, Stonyhurst",
    "sg:city":"Clitheroe",
    "sg:classifiers":[
        {
            "category":"Farming",
            "subcategory":"Livestock Farm",
            "type":"Manufacturing & Wholesale Goods"
        }
    ],
    "sg:phone":"+44 1254 826408",
    "sg:postcode":"BB7 9QX",
    "sg:province":"Lancashire",
    "sg:tags":[
        "others"
    ],
    "wof:name":"Roland Yates",
    "wof:placetype":"venue"
},
  "geometry": {"coordinates":[-2.465458,53.84874],"type":"Point"}
}