{
  "type": "Feature",
  "properties": {
    "iso:country":"GB",
    "sg:address":"60 Heaton Rd, Heaton",
    "sg:city":"Newcastle Upon Tyne",
    "sg:classifiers":[
        {
            "category":"Shopping",
            "subcategory":"News",
            "type":"Retail Goods"
        }
    ],
    "sg:phone":"+44 191 240 0411",
    "sg:postcode":"NE6 5HL",
    "sg:province":"Tyne and Wear",
    "sg:tags":[
        "newsagent"
    ],
    "wof:name":"Bulman J Newsagents",
    "wof:placetype":"venue"
},
  "geometry": {"coordinates":[-1.580697,54.980675],"type":"Point"}
}