{
  "type": "Feature",
  "properties": {
    "addr:full":"Unit 10a, Newhouse Farm Industrial Estate, Mathern Chepstow Gloucestershire NP16 6UD",
    "addr:housenumber":"unit 10a newhouse;industrial",
    "addr:postcode":"np16 6ud",
    "iso:country":"GB",
    "sg:address":"Unit 10a, Newhouse Farm Industrial Estate, Mathern",
    "sg:city":"Chepstow",
    "sg:classifiers":[
        {
            "category":"Wholesale",
            "subcategory":"Metals & Minerals",
            "type":"Manufacturing & Wholesale Goods"
        }
    ],
    "sg:phone":"+44 1291 638638",
    "sg:postcode":"NP16 6UD",
    "sg:province":"Gloucestershire",
    "sg:tags":[
        "non-ferrous"
    ],
    "wof:name":"Aalco",
    "wof:placetype":"venue"
},
  "geometry": {"coordinates":[-2.691454,51.617962],"type":"Point"}
}