{
  "type": "Feature",
  "properties": {
    "addr:full":"178-182 Regent Street London Greater London W1B 5AZ",
    "addr:housenumber":"178-182",
    "addr:postcode":"w1b 5az",
    "addr:street":"Regent Street",
    "iso:country":"GB",
    "sg:address":"178-182 Regent Street",
    "sg:city":"London",
    "sg:classifiers":[
        {
            "category":"Shopping",
            "subcategory":"Clothing, Apparel, & Fashions",
            "type":"Retail Goods"
        },
        {
            "category":"Shopping",
            "subcategory":"Gifts & Souvenirs",
            "type":"Retail Goods"
        }
    ],
    "sg:phone":"+44 20 7434 3334",
    "sg:postcode":"W1B 5AZ",
    "sg:province":"Greater London",
    "sg:tags":[
        "shop"
    ],
    "wof:name":"The Studio Store",
    "wof:placetype":"venue"
},
  "geometry": {"coordinates":[-0.1401280016,51.5127067566],"type":"Point"}
}