{
  "type": "Feature",
  "properties": {
    "addr:full":"Wrenthorpe Wakefield West Yorkshire WF2 0PD",
    "addr:postcode":"wf2 0pd",
    "addr:street":"West",
    "iso:country":"GB",
    "sg:address":"Wrenthorpe",
    "sg:city":"Wakefield",
    "sg:classifiers":[
        {
            "category":"Education",
            "subcategory":"School",
            "type":"Public Place"
        }
    ],
    "sg:phone":"+44 1924 885274",
    "sg:postcode":"WF2 0PD",
    "sg:province":"West Yorkshire",
    "sg:tags":[
        "independent",
        "preparatory"
    ],
    "wof:name":"Silcoates School Enterprises Ltd.",
    "wof:placetype":"venue"
},
  "geometry": {"coordinates":[-1.5304800272,53.6944198608],"type":"Point"}
}