{
  "type": "Feature",
  "properties": {
    "addr:full":"27 Church Street Littleborough Lancashire OL15 8DA",
    "addr:housenumber":"27",
    "addr:postcode":"ol15 8da",
    "addr:street":"Church Street",
    "iso:country":"GB",
    "sg:address":"27 Church Street",
    "sg:city":"Littleborough",
    "sg:classifiers":[
        {
            "category":"Restaurant",
            "type":"Food & Drink"
        }
    ],
    "sg:postcode":"OL15 8DA",
    "sg:province":"Lancashire",
    "wof:name":"Cafe Toppo",
    "wof:placetype":"venue"
},
  "geometry": {"coordinates":[-2.094635,53.643791],"type":"Point"}
}