{
  "type": "Feature",
  "properties": {
    "addr:full":"52 Glencoe Road, Stoke Coventry Warwickshire CV3 1GL",
    "addr:housenumber":"52",
    "addr:postcode":"cv3 1gl",
    "addr:street":"Glencoe Road",
    "iso:country":"GB",
    "sg:address":"52 Glencoe Road, Stoke",
    "sg:city":"Coventry",
    "sg:classifiers":[
        {
            "category":"Home & Garden",
            "subcategory":"Household Appliances",
            "type":"Retail Goods"
        }
    ],
    "sg:postcode":"CV3 1GL",
    "sg:province":"Warwickshire",
    "sg:tags":[
        "electrical"
    ],
    "wof:name":"Vincent Charles Cripps",
    "wof:placetype":"venue"
},
  "geometry": {"coordinates":[-1.4747070074,52.403049469],"type":"Point"}
}