{
  "type": "Feature",
  "properties": {
    "addr:full":"1 Osborne Street Grimsby Lincolnshire DN31 1EY",
    "addr:housenumber":"1",
    "addr:postcode":"dn31 1ey",
    "addr:street":"Osborne Street",
    "iso:country":"GB",
    "sg:address":"1 Osborne Street",
    "sg:city":"Grimsby",
    "sg:classifiers":[
        {
            "category":"Shopping",
            "subcategory":"Clothing, Apparel, & Fashions",
            "type":"Retail Goods"
        }
    ],
    "sg:postcode":"DN31 1EY",
    "sg:province":"Lincolnshire",
    "sg:tags":[
        "shop"
    ],
    "wof:name":"Balducci",
    "wof:placetype":"venue"
},
  "geometry": {"coordinates":[-0.085466,53.564728],"type":"Point"}
}