{
  "type": "Feature",
  "properties": {
    "addr:full":"7 Strathmoor Road Worthing West Sussex BN13 1PJ",
    "addr:housenumber":"7",
    "addr:postcode":"bn13 1pj",
    "addr:street":"Strathmoor Road",
    "iso:country":"GB",
    "sg:address":"7 Strathmoor Road",
    "sg:city":"Worthing",
    "sg:classifiers":[
        {
            "category":"Health Services",
            "subcategory":"Podiatrist",
            "type":"Services"
        }
    ],
    "sg:postcode":"BN13 1PJ",
    "sg:province":"West Sussex",
    "sg:tags":[
        "podiatrists",
        "chiropodist"
    ],
    "wof:name":"P J Poole",
    "wof:placetype":"venue"
},
  "geometry": {"coordinates":[-0.409619987,50.8216590881],"type":"Point"}
}