{
  "type": "Feature",
  "properties": {
    "addr:full":"13-17 New Burlington Place London Greater London W1S 2HL",
    "addr:housenumber":"13-17",
    "addr:postcode":"w1s 2hl",
    "addr:street":"New Burlington Place",
    "iso:country":"GB",
    "sg:address":"13-17 New Burlington Place",
    "sg:city":"London",
    "sg:classifiers":[
        {
            "category":"Professional",
            "subcategory":"Business Services",
            "type":"Services"
        }
    ],
    "sg:phone":"+44 20 8455 6075",
    "sg:postcode":"W1S 2HL",
    "sg:province":"Greater London",
    "sg:tags":[
        "accomodation"
    ],
    "wof:name":"Cyril Hepple & Sons Ltd.",
    "wof:placetype":"venue"
},
  "geometry": {"coordinates":[-0.140649,51.512421],"type":"Point"}
}