{
  "type": "Feature",
  "properties": {
    "addr:full":"The Mounts, The Mounts Totnes Devon TQ9 7QJ",
    "addr:postcode":"tq9 7qj",
    "iso:country":"GB",
    "sg:address":"The Mounts, The Mounts",
    "sg:city":"Totnes",
    "sg:classifiers":[
        {
            "category":"Freight",
            "type":"Transportation"
        }
    ],
    "sg:postcode":"TQ9 7QJ",
    "sg:province":"Devon",
    "sg:tags":[
        "haulage",
        "road"
    ],
    "wof:name":"D J B Haulage",
    "wof:placetype":"venue"
},
  "geometry": {"coordinates":[-3.7490301132,50.3260154724],"type":"Point"}
}