{
  "type": "Feature",
  "properties": {
    "addr:full":"Kingsbury Farm, Main Street, Gayton-le-marsh Alford Lincolnshire LN13 0NW",
    "addr:postcode":"ln13 0nw",
    "addr:street":"Main Street",
    "iso:country":"GB",
    "sg:address":"Kingsbury Farm, Main Street, Gayton-le-marsh",
    "sg:city":"Alford",
    "sg:classifiers":[
        {
            "category":"Home & Garden",
            "subcategory":"Garden Supply",
            "type":"Retail Goods"
        },
        {
            "category":"Farming",
            "subcategory":"Livestock Farm",
            "type":"Manufacturing & Wholesale Goods"
        }
    ],
    "sg:phone":"+44 1507 450470",
    "sg:postcode":"LN13 0NW",
    "sg:province":"Lincolnshire",
    "sg:tags":[
        "bulb",
        "grower",
        "others"
    ],
    "wof:name":"W D Barr & Son",
    "wof:placetype":"venue"
},
  "geometry": {"coordinates":[0.139465,53.335945],"type":"Point"}
}