{
  "type": "Feature",
  "properties": {
    "addr:full":"Long Lane, Tilehurst Reading Berkshire RG31 6YG",
    "addr:postcode":"rg31 6yg",
    "addr:street":"Long Lane",
    "iso:country":"GB",
    "sg:address":"Long Lane, Tilehurst",
    "sg:city":"Reading",
    "sg:classifiers":[
        {
            "category":"Education",
            "subcategory":"School",
            "type":"Public Place"
        },
        {
            "category":"Government",
            "subcategory":"Office",
            "type":"Public Place"
        }
    ],
    "sg:phone":"+44 118 942 7187",
    "sg:postcode":"RG31 6YG",
    "sg:province":"Berkshire",
    "sg:tags":[
        "local",
        "authority"
    ],
    "wof:name":"Long Lane County Primary School",
    "wof:placetype":"venue"
},
  "geometry": {"coordinates":[-1.0516109467,51.4787254333],"type":"Point"}
}