{
  "type": "Feature",
  "properties": {
    "iso:country":"GB",
    "sg:address":"Edgedale Rd",
    "sg:city":"Sheffield",
    "sg:classifiers":[
        {
            "category":"Place Of Worship",
            "type":"Public Place"
        }
    ],
    "sg:phone":"+44 114 249 2282",
    "sg:postcode":"S7 2BR",
    "sg:province":"South Yorkshire",
    "wof:name":"Carter Knowle Methodist Church",
    "wof:placetype":"venue"
},
  "geometry": {"coordinates":[-1.486154,53.354767],"type":"Point"}
}