{
  "type": "Feature",
  "properties": {
    "addr:full":"Pittenkerrie Farm Banchory Aberdeen City AB31 4DB",
    "addr:postcode":"ab31 4db",
    "addr:street":"Banchory Aberdeen",
    "iso:country":"GB",
    "sg:address":"Pittenkerrie Farm",
    "sg:city":"Banchory",
    "sg:classifiers":[
        {
            "category":"Home & Garden",
            "subcategory":"Garden Supply",
            "type":"Retail Goods"
        },
        {
            "category":"Farming",
            "subcategory":"Livestock Farm",
            "type":"Manufacturing & Wholesale Goods"
        }
    ],
    "sg:postcode":"AB31 4DB",
    "sg:province":"Aberdeen City",
    "sg:tags":[
        "bulb",
        "grower",
        "others"
    ],
    "wof:name":"Duncan William Low",
    "wof:placetype":"venue"
},
  "geometry": {"coordinates":[-2.501389,57.051174],"type":"Point"}
}