{
  "type": "Feature",
  "properties": {
    "addr:full":"Po Box 79, Edenthorpe Doncaster South Yorkshire DN3 2RF",
    "addr:housenumber":"po box 79",
    "addr:postcode":"dn3 2rf",
    "iso:country":"GB",
    "sg:address":"Po Box 79, Edenthorpe",
    "sg:city":"Doncaster",
    "sg:classifiers":[
        {
            "category":"Communications",
            "subcategory":"Film & Video Production",
            "type":"Services"
        }
    ],
    "sg:postcode":"DN3 2RF",
    "sg:province":"South Yorkshire",
    "sg:tags":[
        "tv"
    ],
    "wof:name":"Lake Vision",
    "wof:placetype":"venue"
},
  "geometry": {"coordinates":[-1.068179,53.552593],"type":"Point"}
}