{
  "type": "Feature",
  "properties": {
    "iso:country":"GB",
    "sg:address":"240 Brownhill Road",
    "sg:city":"London",
    "sg:classifiers":[
        {
            "category":"Building & Trades",
            "subcategory":"Cleaning & Sanitation",
            "type":"Services"
        }
    ],
    "sg:phone":"+44 20 8697 3444",
    "sg:postcode":"SE6 1AU",
    "sg:province":"Greater London",
    "sg:tags":[
        "contracting",
        "commercial"
    ],
    "wof:name":"London Cleaning Supplies Ltd.",
    "wof:placetype":"venue"
},
  "geometry": {"coordinates":[-0.0050550001,51.4448547363],"type":"Point"}
}