{
  "type": "Feature",
  "properties": {
    "iso:country":"GB",
    "sg:address":"High Edge Court, High Edge Drive, Heage",
    "sg:city":"Belper",
    "sg:classifiers":[
        {
            "category":"Manufacturing",
            "subcategory":"Metals",
            "type":"Manufacturing & Wholesale Goods"
        }
    ],
    "sg:phone":"+44 1773 857271",
    "sg:postcode":"DE56 2TB",
    "sg:province":"Derbyshire",
    "sg:tags":[
        "steel",
        "fabricator",
        "erectors"
    ],
    "wof:name":"Filigree Engineering",
    "wof:placetype":"venue"
},
  "geometry": {"coordinates":[-1.448585,53.044563],"type":"Point"}
}