{
  "type": "Feature",
  "properties": {
    "addr:full":"Glendale House, 18 Northgate, Baildon Shipley West Yorkshire BD17 6JX",
    "addr:housenumber":"18",
    "addr:postcode":"bd17 6jx",
    "addr:street":"Northgate",
    "iso:country":"GB",
    "sg:address":"Glendale House, 18 Northgate, Baildon",
    "sg:city":"Shipley",
    "sg:classifiers":[
        {
            "category":"Banks & Credit Unions",
            "subcategory":"Financial Services",
            "type":"Services"
        }
    ],
    "sg:phone":"+44 1274 587040",
    "sg:postcode":"BD17 6JX",
    "sg:province":"West Yorkshire",
    "sg:tags":[
        "building",
        "society"
    ],
    "wof:name":"Bradford & Bingley Plc",
    "wof:placetype":"venue"
},
  "geometry": {"coordinates":[-1.772899,53.837975],"type":"Point"}
}