{
  "type": "Feature",
  "properties": {
    "addr:full":"Station Road Chepstow Gloucestershire NP16 5PF",
    "addr:postcode":"np16 5pf",
    "addr:street":"Station Road",
    "iso:country":"GB",
    "sg:address":"Station Road",
    "sg:city":"Chepstow",
    "sg:classifiers":[
        {
            "category":"Manufacturing",
            "subcategory":"Watercraft",
            "type":"Manufacturing & Wholesale Goods"
        },
        {
            "category":"Real Estate",
            "subcategory":"Architect",
            "type":"Services"
        }
    ],
    "sg:phone":"+44 1291 624958",
    "sg:postcode":"NP16 5PF",
    "sg:province":"Gloucestershire",
    "sg:tags":[
        "repairer",
        "sailmaker",
        "architectural"
    ],
    "wof:name":"Architen Landrell Manufacturing Ltd.",
    "wof:placetype":"venue"
},
  "geometry": {"coordinates":[-2.673457,51.641205],"type":"Point"}
}