{
  "type": "Feature",
  "properties": {
    "addr:full":"4 Dickinson Pla Barnsley South Yorkshire S70 4LT",
    "addr:housenumber":"4",
    "addr:postcode":"s70 4lt",
    "addr:street":"Dickinson Pla;Yorkshire",
    "iso:country":"GB",
    "sg:address":"4 Dickinson Pla",
    "sg:city":"Barnsley",
    "sg:classifiers":[
        {
            "category":"Sports & Exercise",
            "subcategory":"Tennis Court",
            "type":"Entertainment"
        }
    ],
    "sg:phone":"+44 1226 771523",
    "sg:postcode":"S70 4LT",
    "sg:province":"South Yorkshire",
    "sg:tags":[
        "breakdown",
        "recovery"
    ],
    "wof:name":"B.I.T. Construction & Crane Services",
    "wof:placetype":"venue"
},
  "geometry": {"coordinates":[-1.478523,53.542355],"type":"Point"}
}