{
  "type": "Feature",
  "properties": {
    "addr:full":"5 Woodford Road, Poynton Stockport Cheshire SK12 1DY",
    "addr:housenumber":"5",
    "addr:postcode":"sk12 1dy",
    "addr:street":"Woodford Road",
    "iso:country":"GB",
    "sg:address":"5 Woodford Road, Poynton",
    "sg:city":"Stockport",
    "sg:classifiers":[
        {
            "category":"Professional",
            "subcategory":"Engineering",
            "type":"Services"
        }
    ],
    "sg:postcode":"SK12 1DY",
    "sg:province":"Cheshire",
    "sg:tags":[
        "contractor",
        "electrical",
        "engineer"
    ],
    "wof:name":"A H Leigh & Co.",
    "wof:placetype":"venue"
},
  "geometry": {"coordinates":[-2.14601,53.351589],"type":"Point"}
}