{
  "type": "Feature",
  "properties": {
    "iso:country":"GB",
    "sg:address":"40 Bolton Rd, Atherton",
    "sg:city":"Manchester",
    "sg:classifiers":[
        {
            "category":"Home & Garden",
            "subcategory":"Hardware",
            "type":"Retail Goods"
        }
    ],
    "sg:phone":"+44 1942 892001",
    "sg:postcode":"M46 9JY",
    "sg:province":"Greater Manchester",
    "sg:tags":[
        "device",
        "fixing",
        "fastener"
    ],
    "wof:name":"Associated Fixings Ltd",
    "wof:placetype":"venue"
},
  "geometry": {"coordinates":[-2.486321,53.526203],"type":"Point"}
}