{
  "type": "Feature",
  "properties": {
    "iso:country":"GB",
    "sg:address":"Plane Street",
    "sg:city":"Huddersfield",
    "sg:classifiers":[
        {
            "category":"Education",
            "subcategory":"School",
            "type":"Public Place"
        },
        {
            "category":"Government",
            "subcategory":"Office",
            "type":"Public Place"
        }
    ],
    "sg:phone":"+44 1484 226840",
    "sg:postcode":"HD4 6DF",
    "sg:province":"West Yorkshire",
    "sg:tags":[
        "local",
        "authority"
    ],
    "wof:name":"Stile Common Infant & Nursery School",
    "wof:placetype":"venue"
},
  "geometry": {"coordinates":[-1.781049,53.635777],"type":"Point"}
}