{
  "type": "Feature",
  "properties": {
    "iso:country":"GB",
    "sg:address":"551 Old Kent Rd",
    "sg:city":"Southwark",
    "sg:classifiers":[
        {
            "category":"Government",
            "subcategory":"Department Of Motor Vehicles",
            "type":"Public Place"
        }
    ],
    "sg:phone":"+44 20 7231 0357",
    "sg:postcode":"SE1 5EW",
    "sg:province":"Greater London",
    "sg:tags":[
        "engine",
        "component"
    ],
    "wof:name":"Reliable Rads",
    "wof:placetype":"venue"
},
  "geometry": {"coordinates":[-0.067585,51.484592],"type":"Point"}
}