{
  "type": "Feature",
  "properties": {
    "addr:full":"Highcroft, Claylake, Endon Stoke-on-trent Staffordshire ST9 9DD",
    "addr:postcode":"staffordshire st9 9dd",
    "iso:country":"GB",
    "sg:address":"Highcroft, Claylake, Endon",
    "sg:city":"Stoke-on-trent",
    "sg:classifiers":[
        {
            "category":"Professional",
            "subcategory":"Engineering",
            "type":"Services"
        }
    ],
    "sg:phone":"+44 1782 505000",
    "sg:postcode":"ST9 9DD",
    "sg:province":"Staffordshire",
    "sg:tags":[
        "contractor",
        "electrical",
        "engineer"
    ],
    "wof:name":"Moorlec Services",
    "wof:placetype":"venue"
},
  "geometry": {"coordinates":[-2.108759,53.078529],"type":"Point"}
}