{
  "type": "Feature",
  "properties": {
    "addr:full":"Shepwell Grn Willenhall West Midlands WV13 2QJ",
    "addr:postcode":"wv13 2qj",
    "addr:street":"Shepwell Grn",
    "iso:country":"GB",
    "sg:address":"Shepwell Grn",
    "sg:city":"Willenhall",
    "sg:classifiers":[
        {
            "category":"Autos & Motor Vehicles",
            "subcategory":"Fuel & Gas Station",
            "type":"Retail Goods"
        }
    ],
    "sg:postcode":"WV13 2QJ",
    "sg:province":"West Midlands",
    "sg:tags":[
        "petrol",
        "filling"
    ],
    "wof:name":"Broom,Frank, & A Ramani,",
    "wof:placetype":"venue"
},
  "geometry": {"coordinates":[-2.0412199497,52.5843544006],"type":"Point"}
}