{
  "type": "Feature",
  "properties": {
    "addr:full":"Impression Ho, Ashdale Dr Cheadle Cheshire SK8 3SX",
    "addr:postcode":"sk8 3sx",
    "addr:street":"Ashdale Dr Cheadle",
    "iso:country":"GB",
    "sg:address":"Impression Ho, Ashdale Dr",
    "sg:city":"Cheadle",
    "sg:classifiers":[
        {
            "category":"Recreation",
            "subcategory":"Gun Range",
            "type":"Entertainment"
        }
    ],
    "sg:phone":"+44 161 499 3971",
    "sg:postcode":"SK8 3SX",
    "sg:province":"Cheshire",
    "sg:tags":[
        "operator",
        "tour"
    ],
    "wof:name":"Lasting Impression Holidays Ltd",
    "wof:placetype":"venue"
},
  "geometry": {"coordinates":[-2.2122719288,53.3952484131],"type":"Point"}
}