{
  "type": "Feature",
  "properties": {
    "addr:full":"1 Bardwell Road Oxford Oxfordshire OX2 6SU",
    "addr:housenumber":"1",
    "addr:postcode":"ox2 6su",
    "addr:street":"Bardwell Road",
    "iso:country":"GB",
    "sg:address":"1 Bardwell Road",
    "sg:city":"Oxford",
    "sg:classifiers":[
        {
            "category":"Education",
            "subcategory":"School",
            "type":"Public Place"
        }
    ],
    "sg:phone":"+44 1865 515647",
    "sg:postcode":"OX2 6SU",
    "sg:province":"Oxfordshire",
    "sg:tags":[
        "independent",
        "preparatory"
    ],
    "wof:name":"Greycotes School",
    "wof:placetype":"venue"
},
  "geometry": {"coordinates":[-1.2605190277,51.767364502],"type":"Point"}
}