{
  "type": "Feature",
  "properties": {
    "addr:full":"126 London Road Boston Lincolnshire PE21 7HB",
    "addr:housenumber":"126",
    "addr:postcode":"pe21 7hb",
    "addr:street":"London Road",
    "iso:country":"GB",
    "sg:address":"126 London Road",
    "sg:city":"Boston",
    "sg:classifiers":[
        {
            "category":"Sports & Exercise",
            "subcategory":"Golf",
            "type":"Entertainment"
        }
    ],
    "sg:postcode":"PE21 7HB",
    "sg:province":"Lincolnshire",
    "sg:tags":[
        "club",
        "course"
    ],
    "wof:name":"Addlethorpe Golf and Country Club Ltd.",
    "wof:placetype":"venue"
},
  "geometry": {"coordinates":[-0.0324789993,52.9627456665],"type":"Point"}
}