{
  "type": "Feature",
  "properties": {
    "iso:country":"GB",
    "sg:address":"3 North Mall, Grays Town Centre",
    "sg:city":"Grays",
    "sg:classifiers":[
        {
            "category":"Cafe",
            "type":"Food & Drink"
        }
    ],
    "sg:phone":"+44 1375 394242",
    "sg:postcode":"RM17 6NB",
    "sg:province":"Essex",
    "sg:tags":[
        "tea",
        "room"
    ],
    "wof:name":"The Buttery",
    "wof:placetype":"venue"
},
  "geometry": {"coordinates":[0.326974988,51.4796142578],"type":"Point"}
}