{
  "type": "Feature",
  "properties": {
    "addr:full":"18 State Farm Avenue Orpington Kent BR6 7TN",
    "addr:housenumber":"18",
    "addr:postcode":"br6 7tn",
    "addr:street":"State Farm Avenue",
    "iso:country":"GB",
    "sg:address":"18 State Farm Avenue",
    "sg:city":"Orpington",
    "sg:classifiers":[
        {
            "category":"Arts & Performance",
            "subcategory":"Music",
            "type":"Entertainment"
        }
    ],
    "sg:phone":"+44 1689 861627",
    "sg:postcode":"BR6 7TN",
    "sg:province":"Kent",
    "sg:tags":[
        "musician",
        "composer"
    ],
    "wof:name":"Brass Farthings Live Music Service",
    "wof:placetype":"venue"
},
  "geometry": {"coordinates":[0.0675740018,51.3621444702],"type":"Point"}
}