{
  "type": "Feature",
  "properties": {
    "iso:country":"GB",
    "sg:address":"8 Mansfield Road",
    "sg:city":"Mauchline",
    "sg:postcode":"KA5 6AH",
    "sg:province":"East Ayrshire",
    "wof:name":"Scottish Breeders Services",
    "wof:placetype":"venue"
},
  "geometry": {"coordinates":[-4.377319,55.51609],"type":"Point"}
}