{
  "type": "Feature",
  "properties": {
    "addr:full":"38 New House Park St Albans Hertfordshire AL1 1UJ",
    "addr:housenumber":"38",
    "addr:postcode":"al1 1uj",
    "addr:street":"Park",
    "iso:country":"GB",
    "sg:address":"38 New House Park",
    "sg:city":"St Albans",
    "sg:classifiers":[
        {
            "category":"Shopping",
            "subcategory":"News",
            "type":"Retail Goods"
        }
    ],
    "sg:phone":"+44 1727 865565",
    "sg:postcode":"AL1 1UJ",
    "sg:province":"Hertfordshire",
    "sg:tags":[
        "newsagent"
    ],
    "wof:name":"Whitecroft News & Post Office",
    "wof:placetype":"venue"
},
  "geometry": {"coordinates":[-0.3144829869,51.7364959717],"type":"Point"}
}