{
  "type": "Feature",
  "properties": {
    "iso:country":"GB",
    "sg:address":"Unit 12, Lee Way Court, Lee Way Industrial Estate",
    "sg:city":"Newport",
    "sg:classifiers":[
        {
            "category":"Professional",
            "type":"Services"
        }
    ],
    "sg:postcode":"NP19 4YB",
    "sg:province":"Newport",
    "sg:tags":[
        "exhibition"
    ],
    "wof:name":"Exhibition 2000",
    "wof:placetype":"venue"
},
  "geometry": {"coordinates":[-2.950043,51.575996],"type":"Point"}
}