{
  "type": "Feature",
  "properties": {
    "addr:full":"60 Archway Road Liverpool Merseyside L36 9XE",
    "addr:housenumber":"60",
    "addr:postcode":"l36 9xe",
    "addr:street":"Archway Road",
    "iso:country":"GB",
    "sg:address":"60 Archway Road",
    "sg:city":"Liverpool",
    "sg:classifiers":[
        {
            "category":"Professional",
            "subcategory":"Employment Agencies",
            "type":"Services"
        }
    ],
    "sg:phone":"+44 151 480 6609",
    "sg:postcode":"L36 9XE",
    "sg:province":"Merseyside",
    "sg:tags":[
        "consultant",
        "recruitment"
    ],
    "wof:name":"Polemead Ltd.",
    "wof:placetype":"venue"
},
  "geometry": {"coordinates":[-2.8455610275,53.4104766846],"type":"Point"}
}