{
  "type": "Feature",
  "properties": {
    "iso:country":"GB",
    "sg:address":"4 Alexandra Rd",
    "sg:city":"Penzance",
    "sg:classifiers":[
        {
            "category":"Bus Charters",
            "type":"Transportation"
        },
        {
            "category":"Travel",
            "subcategory":"Travel Agent",
            "type":"Entertainment"
        }
    ],
    "sg:postcode":"TR18 4LY",
    "sg:province":"Cornwall",
    "sg:tags":[
        "hire",
        "coach"
    ],
    "wof:name":"Oxenham,Jeffrey M,",
    "wof:placetype":"venue"
},
  "geometry": {"coordinates":[-5.541232,50.112869],"type":"Point"}
}