{
  "type": "Feature",
  "properties": {
    "addr:full":"26 Penn Street Bristol City of Bristol BS1 3AS",
    "addr:housenumber":"26",
    "addr:postcode":"bs1 3as",
    "addr:street":"Penn Street",
    "iso:country":"GB",
    "sg:address":"26 Penn Street",
    "sg:city":"Bristol",
    "sg:classifiers":[
        {
            "category":"Banks & Credit Unions",
            "subcategory":"Financial Services",
            "type":"Services"
        }
    ],
    "sg:phone":"+44 117 929 7867",
    "sg:postcode":"BS1 3AS",
    "sg:province":"City of Bristol",
    "sg:tags":[
        "building",
        "society"
    ],
    "wof:name":"Chelsea Building Society",
    "wof:placetype":"venue"
},
  "geometry": {"coordinates":[-2.5865170956,51.4582023621],"type":"Point"}
}