{
  "type": "Feature",
  "properties": {
    "iso:country":"GB",
    "sg:address":"21 Church Road, Stretton",
    "sg:city":"Burton-on-trent",
    "sg:classifiers":[
        {
            "category":"Professional",
            "subcategory":"Management & Consulting",
            "type":"Services"
        }
    ],
    "sg:phone":"+44 1283 512987",
    "sg:postcode":"DE13 0HD",
    "sg:province":"Derbyshire",
    "sg:tags":[
        "consultant",
        "business"
    ],
    "wof:name":"St.Marys Consulting",
    "wof:placetype":"venue"
},
  "geometry": {"coordinates":[-1.6248749495,52.8351325989],"type":"Point"}
}