{
  "type": "Feature",
  "properties": {
    "addr:full":"Care Of The Vicarage, Church St Bridlington East Riding of Yorkshire YO15 1PE",
    "addr:postcode":"yo15 1pe",
    "addr:street":"St",
    "iso:country":"GB",
    "sg:address":"Care Of The Vicarage, Church St",
    "sg:city":"Bridlington",
    "sg:classifiers":[
        {
            "category":"Place Of Worship",
            "type":"Public Place"
        }
    ],
    "sg:phone":"+44 1262 850336",
    "sg:postcode":"YO15 1PE",
    "sg:province":"East Riding of Yorkshire",
    "wof:name":"St Peters C Of E Church At Reighton",
    "wof:placetype":"venue"
},
  "geometry": {"coordinates":[-0.1447889954,54.1127281189],"type":"Point"}
}