{
  "type": "Feature",
  "properties": {
    "iso:country":"GB",
    "sg:address":"18a Goswell Hill",
    "sg:city":"Windsor",
    "sg:classifiers":[
        {
            "category":"Wholesale",
            "subcategory":"Sporting Goods",
            "type":"Manufacturing & Wholesale Goods"
        }
    ],
    "sg:phone":"+44 1753 620737",
    "sg:postcode":"SL4 1RH",
    "sg:province":"Berkshire",
    "sg:tags":[
        "mnfr",
        "sport",
        "equipment"
    ],
    "wof:name":"Golf Ltd",
    "wof:placetype":"venue"
},
  "geometry": {"coordinates":[-0.610479,51.482765],"type":"Point"}
}