{
  "type": "Feature",
  "properties": {
    "addr:full":"5 Caradoc Close Coventry Warwickshire CV2 1QT",
    "addr:housenumber":"5",
    "addr:postcode":"cv2 1qt",
    "addr:street":"Caradoc Close",
    "iso:country":"GB",
    "sg:address":"5 Caradoc Close",
    "sg:city":"Coventry",
    "sg:classifiers":[
        {
            "category":"Health Services",
            "subcategory":"Dentist",
            "type":"Services"
        }
    ],
    "sg:phone":"+44 24 7661 3835",
    "sg:postcode":"CV2 1QT",
    "sg:province":"Warwickshire",
    "wof:name":"T C Craven",
    "wof:placetype":"venue"
},
  "geometry": {"coordinates":[-1.45678,52.428616],"type":"Point"}
}