{
  "type": "Feature",
  "properties": {
    "iso:country":"GB",
    "sg:address":"Matlock Street",
    "sg:city":"Bakewell",
    "sg:classifiers":[
        {
            "category":"Personal",
            "subcategory":"Beauty Salon",
            "type":"Services"
        }
    ],
    "sg:postcode":"DE45 1EE",
    "sg:province":"Derbyshire",
    "wof:name":"Beaute-de-Jour",
    "wof:placetype":"venue"
},
  "geometry": {"coordinates":[-1.6753330231,53.2125434875],"type":"Point"}
}