{
  "type": "Feature",
  "properties": {
    "addr:full":"190 Wythenshawe Road Manchester Cheshire M23 0PF",
    "addr:housenumber":"190",
    "addr:postcode":"m23 0pf",
    "addr:street":"Wythenshawe Road",
    "iso:country":"GB",
    "sg:address":"190 Wythenshawe Road",
    "sg:city":"Manchester",
    "sg:classifiers":[
        {
            "category":"Real Estate",
            "subcategory":"Architect",
            "type":"Services"
        }
    ],
    "sg:phone":"+44 161 945 8768",
    "sg:postcode":"M23 0PF",
    "sg:province":"Cheshire",
    "wof:name":"David Roberts & Co",
    "wof:placetype":"venue"
},
  "geometry": {"coordinates":[-2.277309,53.410919],"type":"Point"}
}