{
  "type": "Feature",
  "properties": {
    "iso:country":"GB",
    "sg:address":"28 Low St, Haxey",
    "sg:city":"Doncaster",
    "sg:classifiers":[
        {
            "category":"Shopping",
            "subcategory":"Computers & Home Electronics",
            "type":"Retail Goods"
        }
    ],
    "sg:phone":"+44 1427 753560",
    "sg:postcode":"DN9 2LE",
    "sg:province":"Lincolnshire",
    "sg:tags":[
        "sound",
        "equipment",
        "system"
    ],
    "wof:name":"Worx Sound Systems",
    "wof:placetype":"venue"
},
  "geometry": {"coordinates":[-0.833973,53.488533],"type":"Point"}
}