{
  "type": "Feature",
  "properties": {
    "addr:full":"Pasture St Grimsby Lincolnshire DN32 9EE",
    "addr:postcode":"dn32 9ee",
    "addr:street":"Pasture St",
    "iso:country":"GB",
    "sg:address":"Pasture St",
    "sg:city":"Grimsby",
    "sg:classifiers":[
        {
            "category":"Retail",
            "subcategory":"Auto Repair",
            "type":"Services"
        }
    ],
    "sg:phone":"+44 1472 358822",
    "sg:postcode":"DN32 9EE",
    "sg:province":"Lincolnshire",
    "sg:tags":[
        "modification",
        "garage"
    ],
    "wof:name":"Brian Genney",
    "wof:placetype":"venue"
},
  "geometry": {"coordinates":[-0.0772140026,53.5656394958],"type":"Point"}
}