{
  "type": "Feature",
  "properties": {
    "addr:full":"17 Spurling Works, Pindar Road Hoddesdon Essex EN11 0DB",
    "addr:housenumber":"17",
    "addr:postcode":"en11 0db",
    "addr:street":"Spurling Works Pindar Road",
    "iso:country":"GB",
    "sg:address":"17 Spurling Works, Pindar Road",
    "sg:city":"Hoddesdon",
    "sg:classifiers":[
        {
            "category":"Home & Garden",
            "subcategory":"Hardware",
            "type":"Retail Goods"
        }
    ],
    "sg:postcode":"EN11 0DB",
    "sg:province":"Essex",
    "sg:tags":[
        "retailer",
        "lighting"
    ],
    "wof:name":"Mainwend Ltd.",
    "wof:placetype":"venue"
},
  "geometry": {"coordinates":[-0.0132550001,51.7678413391],"type":"Point"}
}