{
  "type": "Feature",
  "properties": {
    "iso:country":"GB",
    "sg:address":"Lodge Farm, Braybrooke",
    "sg:city":"Leicester",
    "sg:classifiers":[
        {
            "category":"Farming",
            "subcategory":"Farm",
            "type":"Manufacturing & Wholesale Goods"
        }
    ],
    "sg:postcode":"LE16 8LF",
    "sg:province":"Leicestershire",
    "sg:tags":[
        "mixed",
        "crop"
    ],
    "wof:name":"Green,Joe D,",
    "wof:placetype":"venue"
},
  "geometry": {"coordinates":[-0.8771489859,52.4549636841],"type":"Point"}
}