{
  "type": "Feature",
  "properties": {
    "iso:country":"GB",
    "sg:address":"35 Summerfields, St Stephens",
    "sg:city":"Saltash",
    "sg:classifiers":[
        {
            "category":"Home & Garden",
            "subcategory":"Home Furnishings",
            "type":"Retail Goods"
        }
    ],
    "sg:postcode":"PL12 4AB",
    "sg:province":"Cornwall",
    "sg:tags":[
        "furnishers",
        "planner",
        "kitchen"
    ],
    "wof:name":"Fox Kitchens & Joinery",
    "wof:placetype":"venue"
},
  "geometry": {"coordinates":[-4.232186,50.403854],"type":"Point"}
}