{
  "type": "Feature",
  "properties": {
    "addr:full":"109 Ladywood Rd Hertford Hertfordshire SG14 2TA",
    "addr:housenumber":"109",
    "addr:postcode":"sg14 2ta",
    "addr:street":"Ladywood Rd",
    "iso:country":"GB",
    "sg:address":"109 Ladywood Rd",
    "sg:city":"Hertford",
    "sg:classifiers":[
        {
            "category":"Professional",
            "type":"Services"
        }
    ],
    "sg:phone":"+44 1992 554876",
    "sg:postcode":"SG14 2TA",
    "sg:province":"Hertfordshire",
    "sg:tags":[
        "entertainer"
    ],
    "wof:name":"Square Care Sound",
    "wof:placetype":"venue"
},
  "geometry": {"coordinates":[-0.104212001,51.7957611084],"type":"Point"}
}