{
  "type": "Feature",
  "properties": {
    "iso:country":"GB",
    "sg:address":"10 Wellfield Arcade, Wellfield Shopping Centre",
    "sg:city":"Bangor",
    "sg:classifiers":[
        {
            "category":"Shopping",
            "subcategory":"Antiques",
            "type":"Retail Goods"
        },
        {
            "category":"Shopping",
            "subcategory":"Comic Books",
            "type":"Retail Goods"
        }
    ],
    "sg:phone":"+44 1248 370898",
    "sg:postcode":"LL57 1EY",
    "sg:province":"Gwynedd",
    "sg:tags":[
        "jeweller"
    ],
    "wof:name":"Jones & Dyson Antique Jewellers",
    "wof:placetype":"venue"
},
  "geometry": {"coordinates":[-4.1260638237,53.2295951843],"type":"Point"}
}