{
  "type": "Feature",
  "properties": {
    "iso:country":"GB",
    "sg:address":"12 Chapel Lane",
    "sg:city":"Leeds",
    "sg:classifiers":[
        {
            "category":"Travel",
            "subcategory":"Hotels & Motels",
            "type":"Entertainment"
        }
    ],
    "sg:phone":"+44 113 278 6836",
    "sg:postcode":"LS6 3BW",
    "sg:province":"West Yorkshire",
    "wof:name":"Broomhurst Hotel",
    "wof:placetype":"venue"
},
  "geometry": {"coordinates":[-1.577829,53.816074],"type":"Point"}
}