{
  "type": "Feature",
  "properties": {
    "iso:country":"GB",
    "sg:address":"83 Coniston Avenue",
    "sg:city":"Upminster",
    "sg:classifiers":[
        {
            "category":"Retail",
            "subcategory":"Auto Repair",
            "type":"Services"
        }
    ],
    "sg:postcode":"RM14 3XL",
    "sg:province":"Essex",
    "sg:tags":[
        "modification",
        "garage"
    ],
    "wof:name":"Corbets Tey Motoring Service",
    "wof:placetype":"venue"
},
  "geometry": {"coordinates":[0.255315,51.549156],"type":"Point"}
}