{
  "type": "Feature",
  "properties": {
    "iso:country":"GB",
    "sg:address":"443 Holderness Road",
    "sg:city":"Hull",
    "sg:classifiers":[
        {
            "category":"Social Services",
            "subcategory":"Retirement Home",
            "type":"Services"
        }
    ],
    "sg:phone":"+44 1482 702077",
    "sg:postcode":"HU8 8JP",
    "sg:province":"East Riding of Yorkshire",
    "sg:tags":[
        "residential",
        "care"
    ],
    "wof:name":"Pink Panther Resource Centre",
    "wof:placetype":"venue"
},
  "geometry": {"coordinates":[-0.30426,53.76001],"type":"Point"}
}