{
  "type": "Feature",
  "properties": {
    "iso:country":"GB",
    "sg:address":"179 High Street",
    "sg:city":"Ryde",
    "sg:classifiers":[
        {
            "category":"Shopping",
            "subcategory":"Thrift Store",
            "type":"Retail Goods"
        }
    ],
    "sg:phone":"+44 1983 615265",
    "sg:postcode":"PO33 2HN",
    "sg:province":"Isle of Wight",
    "sg:tags":[
        "shop",
        "charity"
    ],
    "wof:name":"People'S Dispensary For Sick Animals",
    "wof:placetype":"venue"
},
  "geometry": {"coordinates":[-1.16344,50.729076],"type":"Point"}
}