{
  "type": "Feature",
  "properties": {
    "iso:country":"GB",
    "sg:address":"88 Harrogate Rd",
    "sg:city":"Leeds",
    "sg:classifiers":[
        {
            "category":"Building & Trades",
            "subcategory":"Equipment Rental",
            "type":"Services"
        },
        {
            "category":"Building & Trades",
            "subcategory":"Construction",
            "type":"Services"
        }
    ],
    "sg:phone":"+44 113 262 9696",
    "sg:postcode":"LS7 4LZ",
    "sg:province":"West Yorkshire",
    "sg:tags":[
        "plant",
        "tool",
        "hire"
    ],
    "wof:name":"D B Hire",
    "wof:placetype":"venue"
},
  "geometry": {"coordinates":[-1.537017,53.827736],"type":"Point"}
}