{
  "type": "Feature",
  "properties": {
    "addr:full":"760 Ecclesall Rd Sheffield Derbyshire S11 8TB",
    "addr:housenumber":"760",
    "addr:postcode":"s11 8tb",
    "addr:street":"Ecclesall Rd",
    "iso:country":"GB",
    "sg:address":"760 Ecclesall Rd",
    "sg:city":"Sheffield",
    "sg:classifiers":[
        {
            "category":"Cafe",
            "type":"Food & Drink"
        }
    ],
    "sg:phone":"+44 114 266 5608",
    "sg:postcode":"S11 8TB",
    "sg:province":"Derbyshire",
    "sg:tags":[
        "tea",
        "room"
    ],
    "wof:name":"Salina's Coffee House",
    "wof:placetype":"venue"
},
  "geometry": {"coordinates":[-1.5074379444,53.3659858704],"type":"Point"}
}