{
  "type": "Feature",
  "properties": {
    "iso:country":"GB",
    "sg:address":"Imperial Buildings, Glan-y-mor Road",
    "sg:city":"Llandudno",
    "sg:classifiers":[
        {
            "category":"Bus Charters",
            "type":"Transportation"
        }
    ],
    "sg:phone":"+44 1492 592111",
    "sg:postcode":"LL31 9RU",
    "sg:province":"Conwy",
    "sg:tags":[
        "coach"
    ],
    "wof:name":"Arriva Cymru Ltd.",
    "wof:placetype":"venue"
},
  "geometry": {"coordinates":[-3.8157699108,53.284450531],"type":"Point"}
}