{
  "type": "Feature",
  "properties": {
    "addr:full":"199 Albion Street Glasgow Glasgow City G1 1RU",
    "addr:housenumber":"199",
    "addr:postcode":"g1 1ru",
    "addr:street":"Albion Street",
    "iso:country":"GB",
    "sg:address":"199 Albion Street",
    "sg:city":"Glasgow",
    "sg:classifiers":[
        {
            "category":"Bars & Pubs",
            "type":"Food & Drink"
        }
    ],
    "sg:phone":"+44 141 552 5142",
    "sg:postcode":"G1 1RU",
    "sg:province":"Glasgow City",
    "sg:tags":[
        "pubs",
        "inn"
    ],
    "wof:name":"The Press Bar",
    "wof:placetype":"venue"
},
  "geometry": {"coordinates":[-4.2438969612,55.8604507446],"type":"Point"}
}