{
  "type": "Feature",
  "properties": {
    "addr:full":"4 Rectory Row Bracknell Berkshire RG12 7BN",
    "addr:housenumber":"4",
    "addr:postcode":"rg12 7bn",
    "addr:street":"Rectory Row",
    "iso:country":"GB",
    "sg:address":"4 Rectory Row",
    "sg:city":"Bracknell",
    "sg:classifiers":[
        {
            "category":"Shopping",
            "subcategory":"Crafts & Fabrics",
            "type":"Retail Goods"
        }
    ],
    "sg:phone":"+44 1344 421945",
    "sg:postcode":"RG12 7BN",
    "sg:province":"Berkshire",
    "sg:tags":[
        "shop",
        "needlecraft",
        "wool"
    ],
    "wof:name":"Dalby & Dalby",
    "wof:placetype":"venue"
},
  "geometry": {"coordinates":[-0.749332,51.407944],"type":"Point"}
}