{
  "type": "Feature",
  "properties": {
    "addr:full":"85 Moore Park Road London Greater London SW6 2DA",
    "addr:housenumber":"85",
    "addr:postcode":"sw6 2da",
    "addr:street":"Moore Park Road",
    "iso:country":"GB",
    "sg:address":"85 Moore Park Road",
    "sg:city":"London",
    "sg:classifiers":[
        {
            "category":"Deli",
            "type":"Food & Drink"
        }
    ],
    "sg:phone":"+44 20 7736 2087",
    "sg:postcode":"SW6 2DA",
    "sg:province":"Greater London",
    "sg:tags":[
        "delicatessen"
    ],
    "wof:name":"The Moore Park Delicatessen",
    "wof:placetype":"venue"
},
  "geometry": {"coordinates":[-0.192946,51.478809],"type":"Point"}
}