{
  "type": "Feature",
  "properties": {
    "addr:full":"The Croft Resource Centre, The Penningtons Amersham Buckinghamshire HP6 6EJ",
    "addr:postcode":"hp6 6ej",
    "addr:street":"The;Amersham",
    "iso:country":"GB",
    "sg:address":"The Croft Resource Centre, The Penningtons",
    "sg:city":"Amersham",
    "sg:classifiers":[
        {
            "category":"Social Services",
            "type":"Services"
        }
    ],
    "sg:phone":"+44 1494 732800",
    "sg:postcode":"HP6 6EJ",
    "sg:province":"Buckinghamshire",
    "wof:name":"Chiltern Home Care Team",
    "wof:placetype":"venue"
},
  "geometry": {"coordinates":[-0.596114,51.674656],"type":"Point"}
}