{
  "type": "Feature",
  "properties": {
    "addr:full":"The Media Village, Grampian T V, Queens Cross Aberdeen Aberdeen City AB15 4XJ",
    "addr:postcode":"ab15 4xj",
    "addr:street":"Queens Cross",
    "iso:country":"GB",
    "sg:address":"The Media Village, Grampian T V, Queens Cross",
    "sg:city":"Aberdeen",
    "sg:classifiers":[
        {
            "category":"Communications",
            "type":"Services"
        }
    ],
    "sg:postcode":"AB15 4XJ",
    "sg:province":"Aberdeen City",
    "sg:tags":[
        "broadcasting"
    ],
    "wof:name":"Northlight Productions Ltd.",
    "wof:placetype":"venue"
},
  "geometry": {"coordinates":[-2.12919,57.1436],"type":"Point"}
}