{
  "type": "Feature",
  "properties": {
    "iso:country":"GB",
    "sg:address":"11 Golborne Road",
    "sg:city":"London",
    "sg:classifiers":[
        {
            "category":"Shopping",
            "subcategory":"News",
            "type":"Retail Goods"
        }
    ],
    "sg:phone":"+44 20 8969 3906",
    "sg:postcode":"W10 5NY",
    "sg:province":"Greater London",
    "sg:tags":[
        "newsagent"
    ],
    "wof:name":"Star Newsagents",
    "wof:placetype":"venue"
},
  "geometry": {"coordinates":[-0.206196,51.52367],"type":"Point"}
}