{
  "type": "Feature",
  "properties": {
    "addr:full":"Unit 4 Newton Business Centre, Sprotbrough Rd Doncaster South Yorkshire DN5 8BD",
    "addr:housenumber":"unit 4",
    "addr:postcode":"dn5 8bd",
    "addr:street":"Newton Business Centre Sprotbrough Rd",
    "iso:country":"GB",
    "sg:address":"Unit 4 Newton Business Centre, Sprotbrough Rd",
    "sg:city":"Doncaster",
    "sg:classifiers":[
        {
            "category":"Manufacturing",
            "subcategory":"Petroleum Products",
            "type":"Manufacturing & Wholesale Goods"
        }
    ],
    "sg:phone":"+44 1302 391611",
    "sg:postcode":"DN5 8BD",
    "sg:province":"South Yorkshire",
    "sg:tags":[
        "double",
        "glazing"
    ],
    "wof:name":"Millenium Windows",
    "wof:placetype":"venue"
},
  "geometry": {"coordinates":[-1.1615899801,53.5228309631],"type":"Point"}
}