{
  "type": "Feature",
  "properties": {
    "addr:full":"Ball Haye Grn Leek Staffordshire ST13 6BH",
    "addr:postcode":"st13 6bh",
    "addr:street":"Ball Haye Grn",
    "iso:country":"GB",
    "sg:address":"Ball Haye Grn",
    "sg:city":"Leek",
    "sg:classifiers":[
        {
            "category":"Building & Trades",
            "subcategory":"Cleaning & Sanitation",
            "type":"Services"
        }
    ],
    "sg:postcode":"ST13 6BH",
    "sg:province":"Staffordshire",
    "sg:tags":[
        "commercial"
    ],
    "wof:name":"Onyx U K Ltd.",
    "wof:placetype":"venue"
},
  "geometry": {"coordinates":[-2.0171039104,53.1112937927],"type":"Point"}
}