{
  "type": "Feature",
  "properties": {
    "addr:full":"333 Ley St Ilford Essex IG1 4AA",
    "addr:housenumber":"333",
    "addr:postcode":"ig1 4aa",
    "addr:street":"Ley St",
    "iso:country":"GB",
    "sg:address":"333 Ley St",
    "sg:city":"Ilford",
    "sg:classifiers":[
        {
            "category":"Communications",
            "type":"Services"
        }
    ],
    "sg:phone":"+44 20 8553 5166",
    "sg:postcode":"IG1 4AA",
    "sg:province":"Essex",
    "sg:tags":[
        "tv",
        "video",
        "radio"
    ],
    "wof:name":"Ley Street Video & Satellite",
    "wof:placetype":"venue"
},
  "geometry": {"coordinates":[0.082863003,51.564201355],"type":"Point"}
}