{
  "type": "Feature",
  "properties": {
    "iso:country":"GB",
    "sg:address":"Struan House, The Square",
    "sg:city":"Aberfeldy",
    "sg:classifiers":[
        {
            "category":"Professional",
            "subcategory":"Advertising",
            "type":"Services"
        }
    ],
    "sg:phone":"+44 1887 820956",
    "sg:postcode":"PH15 2DD",
    "sg:province":"Perth and Kinross",
    "sg:tags":[
        "agency"
    ],
    "wof:name":"Brendan Murphy",
    "wof:placetype":"venue"
},
  "geometry": {"coordinates":[-3.941695,56.617607],"type":"Point"}
}