{
  "type": "Feature",
  "properties": {
    "iso:country":"GB",
    "sg:address":"Bushes Cottage, Bough Beech",
    "sg:city":"Edenbridge",
    "sg:classifiers":[
        {
            "category":"Building & Trades",
            "subcategory":"Construction",
            "type":"Services"
        }
    ],
    "sg:postcode":"TN8 7AS",
    "sg:province":"East Sussex",
    "sg:tags":[
        "decorator",
        "painter"
    ],
    "wof:name":"Des Kirby Painter & Decorator",
    "wof:placetype":"venue"
},
  "geometry": {"coordinates":[0.13355,51.200211],"type":"Point"}
}