{
  "type": "Feature",
  "properties": {
    "addr:full":"58 Station Road, Stannington Morpeth Northumberland NE61 6NH",
    "addr:housenumber":"58",
    "addr:postcode":"ne61 6nh",
    "addr:street":"Station Road",
    "iso:country":"GB",
    "sg:address":"58 Station Road, Stannington",
    "sg:city":"Morpeth",
    "sg:classifiers":[
        {
            "category":"Home & Garden",
            "subcategory":"Garden Supply",
            "type":"Retail Goods"
        }
    ],
    "sg:phone":"+44 1670 789377",
    "sg:postcode":"NE61 6NH",
    "sg:province":"Northumberland",
    "sg:tags":[
        "nursery",
        "centre"
    ],
    "wof:name":"Station Road Nurseries",
    "wof:placetype":"venue"
},
  "geometry": {"coordinates":[-1.666914,55.109169],"type":"Point"}
}