{
  "type": "Feature",
  "properties": {
    "addr:full":"16 Linden Road, Gosforth Newcastle-upon-tyne Tyne and Wear NE3 4EY",
    "addr:housenumber":"16",
    "addr:postcode":"ne3 4ey",
    "addr:street":"Linden Road",
    "iso:country":"GB",
    "sg:address":"16 Linden Road, Gosforth",
    "sg:city":"Newcastle-upon-tyne",
    "sg:classifiers":[
        {
            "category":"Social Services",
            "subcategory":"Retirement Home",
            "type":"Services"
        },
        {
            "category":"Organizations",
            "subcategory":"Community Association",
            "type":"Services"
        }
    ],
    "sg:phone":"+44 191 213 5634",
    "sg:postcode":"NE3 4EY",
    "sg:province":"Tyne and Wear",
    "sg:tags":[
        "society",
        "housing",
        "rest"
    ],
    "wof:name":"Abbeyfield Newcastle Upon Tyne Society",
    "wof:placetype":"venue"
},
  "geometry": {"coordinates":[-1.6239329576,55.0034980774],"type":"Point"}
}