{
  "type": "Feature",
  "properties": {
    "addr:full":"2b Harrow Road, Selly Oak Birmingham West Midlands B29 7DN",
    "addr:housenumber":"2b",
    "addr:postcode":"b29 7dn",
    "addr:street":"Harrow Road",
    "iso:country":"GB",
    "sg:address":"2b Harrow Road, Selly Oak",
    "sg:city":"Birmingham",
    "sg:classifiers":[
        {
            "category":"Shopping",
            "type":"Retail Goods"
        }
    ],
    "sg:postcode":"B29 7DN",
    "sg:province":"West Midlands",
    "sg:tags":[
        "part",
        "accessory"
    ],
    "wof:name":"Granada Parts Centre",
    "wof:placetype":"venue"
},
  "geometry": {"coordinates":[-1.931114,52.446159],"type":"Point"}
}