{
  "type": "Feature",
  "properties": {
    "iso:country":"GB",
    "sg:address":"Prentice Place, Potter Street",
    "sg:city":"Harlow",
    "sg:classifiers":[
        {
            "category":"Health Services",
            "subcategory":"Doctor",
            "type":"Services"
        },
        {
            "category":"Health Services",
            "subcategory":"Clinic",
            "type":"Services"
        }
    ],
    "sg:phone":"+44 1279 422664",
    "sg:postcode":"CM17 9BG",
    "sg:province":"Essex",
    "sg:tags":[
        "nh",
        "practitioners"
    ],
    "wof:name":"Osler House Surgery",
    "wof:placetype":"venue"
},
  "geometry": {"coordinates":[0.132645,51.758015],"type":"Point"}
}