{
  "type": "Feature",
  "properties": {
    "iso:country":"GB",
    "sg:address":"Westend Methodist Church, Trafalgar Square",
    "sg:city":"Ashton Under Lyne",
    "sg:classifiers":[
        {
            "category":"Organizations",
            "subcategory":"Non-profit Organization",
            "type":"Services"
        }
    ],
    "sg:phone":"+44 161 339 9299",
    "sg:postcode":"OL7 0LL",
    "sg:province":"Greater Manchester",
    "sg:tags":[
        "organisation",
        "voluntary",
        "charity"
    ],
    "wof:name":"Women's Royal Voluntary Service",
    "wof:placetype":"venue"
},
  "geometry": {"coordinates":[-2.10828,53.480179],"type":"Point"}
}