{
  "type": "Feature",
  "properties": {
    "addr:full":"114 High Rd South Woodford Greater London E18 2QS",
    "addr:housenumber":"114",
    "addr:postcode":"e18 2qs",
    "addr:street":"High Rd",
    "iso:country":"GB",
    "sg:address":"114 High Rd",
    "sg:city":"South Woodford",
    "sg:classifiers":[
        {
            "category":"Health Services",
            "subcategory":"Doctor",
            "type":"Services"
        }
    ],
    "sg:phone":"+44 20 8504 9163",
    "sg:postcode":"E18 2QS",
    "sg:province":"Greater London",
    "sg:tags":[
        "practitioners"
    ],
    "wof:name":"Drs Brohi & Jones",
    "wof:placetype":"venue"
},
  "geometry": {"coordinates":[0.0215419997,51.5970344543],"type":"Point"}
}