{
  "type": "Feature",
  "properties": {
    "iso:country":"GB",
    "sg:address":"Nova Scotia Works, Dale St",
    "sg:city":"Ossett",
    "sg:classifiers":[
        {
            "category":"Wholesale",
            "subcategory":"Electrical",
            "type":"Manufacturing & Wholesale Goods"
        }
    ],
    "sg:phone":"+44 1924 273537",
    "sg:postcode":"WF5 9HQ",
    "sg:province":"West Yorkshire",
    "sg:tags":[
        "equipment",
        "refrigeration"
    ],
    "wof:name":"G R Scott (Insulation) Ltd",
    "wof:placetype":"venue"
},
  "geometry": {"coordinates":[-1.587806,53.684235],"type":"Point"}
}