{
  "type": "Feature",
  "properties": {
    "addr:full":"Mountmill Farm, Stratford Road, Wicken Milton Keynes Buckinghamshire MK19 6DG",
    "addr:postcode":"mk19 6dg",
    "addr:street":"Stratford Road",
    "iso:country":"GB",
    "sg:address":"Mountmill Farm, Stratford Road, Wicken",
    "sg:city":"Milton Keynes",
    "sg:classifiers":[
        {
            "category":"Real Estate",
            "subcategory":"Real Estate Operator",
            "type":"Services"
        },
        {
            "category":"Farming",
            "subcategory":"Livestock Farm",
            "type":"Manufacturing & Wholesale Goods"
        },
        {
            "category":"Farming",
            "subcategory":"Farm",
            "type":"Manufacturing & Wholesale Goods"
        },
        {
            "category":"Professional",
            "subcategory":"Management & Consulting",
            "type":"Services"
        }
    ],
    "sg:phone":"+44 1908 263967",
    "sg:postcode":"MK19 6DG",
    "sg:province":"Buckinghamshire",
    "sg:tags":[
        "business",
        "consultant",
        "crop",
        "others",
        "mixed",
        "rental"
    ],
    "wof:name":"J Gurney",
    "wof:placetype":"venue"
},
  "geometry": {"coordinates":[-0.9121159911,52.0477561951],"type":"Point"}
}