{
  "type": "Feature",
  "properties": {
    "iso:country":"GB",
    "sg:address":"6 Uplands Close",
    "sg:city":"Uckfield",
    "sg:classifiers":[
        {
            "category":"Building & Trades",
            "subcategory":"Construction",
            "type":"Services"
        }
    ],
    "sg:postcode":"TN22 1BB",
    "sg:province":"East Sussex",
    "sg:tags":[
        "tiling",
        "contractor"
    ],
    "wof:name":"B Stevens",
    "wof:placetype":"venue"
},
  "geometry": {"coordinates":[0.097954,50.978916],"type":"Point"}
}