{
  "type": "Feature",
  "properties": {
    "addr:full":"7 Tai Dolawel Blaenau Ffestiniog Gwynedd LL41 3NR",
    "addr:housenumber":"7",
    "addr:postcode":"ll41 3nr",
    "addr:street":"Tai Dolawel",
    "iso:country":"GB",
    "sg:address":"7 Tai Dolawel",
    "sg:city":"Blaenau Ffestiniog",
    "sg:classifiers":[
        {
            "category":"Manufacturing",
            "subcategory":"Paper Products",
            "type":"Manufacturing & Wholesale Goods"
        }
    ],
    "sg:phone":"+44 1766 830562",
    "sg:postcode":"LL41 3NR",
    "sg:province":"Gwynedd",
    "sg:tags":[
        "slate"
    ],
    "wof:name":"Pant-Hwfa Fine Slate Crafts",
    "wof:placetype":"venue"
},
  "geometry": {"coordinates":[-3.9456140995,52.9981040955],"type":"Point"}
}