{
  "type": "Feature",
  "properties": {
    "addr:full":"Sports Pavilion Scaltback Middle, School, Elizabeth Avenue Newmarket Cambridgeshire CB8 0BJ",
    "addr:postcode":"cb8 0bj",
    "addr:street":"Elizabeth Avenue Newmarket",
    "iso:country":"GB",
    "sg:address":"Sports Pavilion Scaltback Middle, School, Elizabeth Avenue",
    "sg:city":"Newmarket",
    "sg:classifiers":[
        {
            "category":"Organizations",
            "subcategory":"Non-profit Organization",
            "type":"Services"
        }
    ],
    "sg:phone":"+44 1638 663082",
    "sg:postcode":"CB8 0BJ",
    "sg:province":"Cambridgeshire",
    "sg:tags":[
        "organisation",
        "voluntary",
        "charity"
    ],
    "wof:name":"Newmarket Sports Development Association",
    "wof:placetype":"venue"
},
  "geometry": {"coordinates":[0.399165988,52.2498168945],"type":"Point"}
}