{
  "type": "Feature",
  "properties": {
    "iso:country":"GB",
    "sg:address":"10 Calmore Gardens, Totton",
    "sg:city":"Southampton",
    "sg:classifiers":[
        {
            "category":"Building & Trades",
            "subcategory":"Construction",
            "type":"Services"
        }
    ],
    "sg:phone":"+44 23 8086 4315",
    "sg:postcode":"SO40 8ER",
    "sg:province":"Hampshire",
    "sg:tags":[
        "builder"
    ],
    "wof:name":"S D B Builders",
    "wof:placetype":"venue"
},
  "geometry": {"coordinates":[-1.5087679625,50.919254303],"type":"Point"}
}