{
  "type": "Feature",
  "properties": {
    "iso:country":"GB",
    "sg:address":"14 Park Street Leamington Spa",
    "sg:classifiers":[
        {
            "category":"Professional",
            "subcategory":"Computer Services",
            "type":"Services"
        }
    ],
    "sg:postcode":"CV32 4QN",
    "sg:tags":[
        "jewellery",
        "online-shopping",
        "e-commerce",
        "luxury"
    ],
    "sg:website":"http://www.rockokojewellery.com/",
    "wof:name":"Rockoko",
    "wof:placetype":"venue"
},
  "geometry": {"coordinates":[-1.533601,52.291474],"type":"Point"}
}