{
  "type": "Feature",
  "properties": {
    "addr:full":"31 Avondale Road Wigan Lancashire WN1 2BE",
    "addr:housenumber":"31",
    "addr:postcode":"wn1 2be",
    "addr:street":"Avondale Road",
    "iso:country":"GB",
    "sg:address":"31 Avondale Road",
    "sg:city":"Wigan",
    "sg:classifiers":[
        {
            "category":"Home & Garden",
            "subcategory":"Building Materials",
            "type":"Retail Goods"
        }
    ],
    "sg:postcode":"WN1 2BE",
    "sg:province":"Lancashire",
    "sg:tags":[
        "garage",
        "door"
    ],
    "wof:name":"Clive Middlehurst",
    "wof:placetype":"venue"
},
  "geometry": {"coordinates":[-2.6316180229,53.5530548096],"type":"Point"}
}