{
  "type": "Feature",
  "properties": {
    "addr:full":"Lower Alsworthy Farm, Bradworthy Holsworthy Cornwall EX22 7RW",
    "addr:postcode":"ex22 7rw",
    "iso:country":"GB",
    "sg:address":"Lower Alsworthy Farm, Bradworthy",
    "sg:city":"Holsworthy",
    "sg:classifiers":[
        {
            "category":"Farming",
            "subcategory":"Livestock Farm",
            "type":"Manufacturing & Wholesale Goods"
        },
        {
            "category":"Farming",
            "subcategory":"Farm",
            "type":"Manufacturing & Wholesale Goods"
        }
    ],
    "sg:postcode":"EX22 7RW",
    "sg:province":"Cornwall",
    "sg:tags":[
        "mixed",
        "crop",
        "others"
    ],
    "wof:name":"Norman L Grills",
    "wof:placetype":"venue"
},
  "geometry": {"coordinates":[-4.3865442276,50.8982124329],"type":"Point"}
}