{
  "type": "Feature",
  "properties": {
    "iso:country":"GB",
    "sg:address":"Station Yard, Station Road",
    "sg:city":"Sandbach",
    "sg:classifiers":[
        {
            "category":"Building & Trades",
            "subcategory":"Construction",
            "type":"Services"
        }
    ],
    "sg:phone":"+44 1270 753131",
    "sg:postcode":"CW11 3JG",
    "sg:province":"Cheshire",
    "sg:tags":[
        "builder"
    ],
    "wof:name":"Maywood Contractors Ltd.",
    "wof:placetype":"venue"
},
  "geometry": {"coordinates":[-2.3927540779,53.147644043],"type":"Point"}
}