{
  "type": "Feature",
  "properties": {
    "iso:country":"GB",
    "sg:address":"29 Western Rd",
    "sg:city":"Lewes",
    "sg:classifiers":[
        {
            "category":"Fast Food",
            "type":"Food & Drink"
        }
    ],
    "sg:phone":"+44 1273 488377",
    "sg:postcode":"BN7 1RL",
    "sg:province":"East Sussex",
    "sg:tags":[
        "away",
        "take"
    ],
    "wof:name":"Green,Ian,",
    "wof:placetype":"venue"
},
  "geometry": {"coordinates":[0.001203,50.8728408813],"type":"Point"}
}