{
  "type": "Feature",
  "properties": {
    "addr:full":"29 Sergeants La Manchester Lancashire M45 7TR",
    "addr:housenumber":"29",
    "addr:postcode":"m45 7tr",
    "addr:street":"Sergeants La Manchester",
    "iso:country":"GB",
    "sg:address":"29 Sergeants La",
    "sg:city":"Manchester",
    "sg:classifiers":[
        {
            "category":"Arts & Performance",
            "subcategory":"Art Gallery",
            "type":"Entertainment"
        }
    ],
    "sg:phone":"+44 161 796 1515",
    "sg:postcode":"M45 7TR",
    "sg:province":"Lancashire",
    "wof:name":"V Jardim",
    "wof:placetype":"venue"
},
  "geometry": {"coordinates":[-2.313481,53.542789],"type":"Point"}
}