{
  "type": "Feature",
  "properties": {
    "iso:country":"GB",
    "sg:address":"Unit 16, Excelsior Works",
    "sg:city":"Sheffield",
    "sg:classifiers":[
        {
            "category":"Home & Garden",
            "subcategory":"Kitchen Supply",
            "type":"Retail Goods"
        }
    ],
    "sg:postcode":"S35 9YR",
    "sg:province":"South Yorkshire",
    "sg:tags":[
        "supplier",
        "cutlery"
    ],
    "wof:name":"Geoffrey W Slattery",
    "wof:placetype":"venue"
},
  "geometry": {"coordinates":[-1.459719,53.44302],"type":"Point"}
}