{
  "type": "Feature",
  "properties": {
    "iso:country":"GB",
    "sg:address":"23 Quality Street",
    "sg:city":"North Berwick",
    "sg:classifiers":[
        {
            "category":"Shopping",
            "subcategory":"Used Merchandise",
            "type":"Retail Goods"
        }
    ],
    "sg:postcode":"EH39 4HR",
    "sg:province":"East Lothian",
    "sg:tags":[
        "shop",
        "second-hand"
    ],
    "wof:name":"Pennyfarthing",
    "wof:placetype":"venue"
},
  "geometry": {"coordinates":[-2.717441082,56.059261322],"type":"Point"}
}