{
  "type": "Feature",
  "properties": {
    "addr:full":"The Old Laundry, School Road, Penn High Wycombe Buckinghamshire HP10 8LX",
    "addr:postcode":"hp10 8lx",
    "addr:street":"School Road",
    "iso:country":"GB",
    "sg:address":"The Old Laundry, School Road, Penn",
    "sg:city":"High Wycombe",
    "sg:classifiers":[
        {
            "category":"Professional",
            "subcategory":"Engineering",
            "type":"Services"
        }
    ],
    "sg:postcode":"HP10 8LX",
    "sg:province":"Buckinghamshire",
    "sg:tags":[
        "electrical",
        "contractor",
        "electronic",
        "engineer"
    ],
    "wof:name":"Holmes Digital Electronics",
    "wof:placetype":"venue"
},
  "geometry": {"coordinates":[-0.676358,51.631306],"type":"Point"}
}