{
  "type": "Feature",
  "properties": {
    "iso:country":"GB",
    "sg:address":"17 Leys Road, Oxshott",
    "sg:city":"Leatherhead",
    "sg:classifiers":[
        {
            "category":"Shopping",
            "subcategory":"Catalog Store",
            "type":"Retail Goods"
        }
    ],
    "sg:phone":"+44 1372 842294",
    "sg:postcode":"KT22 0QE",
    "sg:province":"Surrey",
    "sg:tags":[
        "mail",
        "order"
    ],
    "wof:name":"Couture Linens",
    "wof:placetype":"venue"
},
  "geometry": {"coordinates":[-0.3521499932,51.3374481201],"type":"Point"}
}