{
  "type": "Feature",
  "properties": {
    "addr:full":"146 Lancaster Road Enfield Greater London EN2 0JS",
    "addr:housenumber":"146",
    "addr:postcode":"en2 0js",
    "addr:street":"Lancaster Road",
    "iso:country":"GB",
    "sg:address":"146 Lancaster Road",
    "sg:city":"Enfield",
    "sg:classifiers":[
        {
            "category":"Building & Trades",
            "subcategory":"Construction",
            "type":"Services"
        }
    ],
    "sg:postcode":"EN2 0JS",
    "sg:province":"Greater London",
    "sg:tags":[
        "roofing"
    ],
    "wof:name":"Drytime Roofing Co.",
    "wof:placetype":"venue"
},
  "geometry": {"coordinates":[-0.0836009979,51.6638717651],"type":"Point"}
}