{
  "type": "Feature",
  "properties": {
    "addr:full":"42 Grosvenor Road London Greater London W4 4EG",
    "addr:housenumber":"42",
    "addr:postcode":"w4 4eg",
    "addr:street":"Grosvenor Road",
    "iso:country":"GB",
    "sg:address":"42 Grosvenor Road",
    "sg:city":"London",
    "sg:classifiers":[
        {
            "category":"Landmark",
            "subcategory":"Tourist Information",
            "type":"Public Place"
        }
    ],
    "sg:phone":"+44 20 8995 0037",
    "sg:postcode":"W4 4EG",
    "sg:province":"Greater London",
    "sg:tags":[
        "tour",
        "guide",
        "sightseeing"
    ],
    "wof:name":"Audio Walks Ltd.",
    "wof:placetype":"venue"
},
  "geometry": {"coordinates":[-0.2740190029,51.4894752502],"type":"Point"}
}