{
  "type": "Feature",
  "properties": {
    "iso:country":"GB",
    "sg:address":"Brookdene Lodge, Haydon Wick",
    "sg:city":"Swindon",
    "sg:classifiers":[
        {
            "category":"Organizations",
            "subcategory":"Community Association",
            "type":"Services"
        }
    ],
    "sg:phone":"+44 1793 725558",
    "sg:postcode":"SN25 1RU",
    "sg:province":"Wiltshire",
    "sg:tags":[
        "co-operatives",
        "society",
        "housing",
        "trust"
    ],
    "wof:name":"John Grooms Housing Association",
    "wof:placetype":"venue"
},
  "geometry": {"coordinates":[-1.804518,51.589607],"type":"Point"}
}