{
  "type": "Feature",
  "properties": {
    "addr:full":"Tardis Studios, 52-56 Turnmill St Clerkenwell Greater London EC1M 5QR",
    "addr:housenumber":"52-56",
    "addr:postcode":"ec1m 5qr",
    "addr:street":"Turnmill St",
    "iso:country":"GB",
    "sg:address":"Tardis Studios, 52-56 Turnmill St",
    "sg:city":"Clerkenwell",
    "sg:classifiers":[
        {
            "category":"Organizations",
            "subcategory":"Non-profit Organization",
            "type":"Services"
        }
    ],
    "sg:phone":"+44 20 7566 0041",
    "sg:postcode":"EC1M 5QR",
    "sg:province":"Greater London",
    "sg:tags":[
        "organisation",
        "voluntary",
        "charity"
    ],
    "wof:name":"The Smithfield Trust",
    "wof:placetype":"venue"
},
  "geometry": {"coordinates":[-0.1048899963,51.5205802917],"type":"Point"}
}