{
  "type": "Feature",
  "properties": {
    "iso:country":"GB",
    "sg:address":"332 Shirley Road",
    "sg:city":"Southampton",
    "sg:classifiers":[
        {
            "category":"Manufacturing",
            "subcategory":"Tools & Machinery",
            "type":"Manufacturing & Wholesale Goods"
        }
    ],
    "sg:phone":"+44 23 8077 3343",
    "sg:postcode":"SO15 3HJ",
    "sg:province":"Hampshire",
    "wof:name":"Barron Tools",
    "wof:placetype":"venue"
},
  "geometry": {"coordinates":[-1.427518,50.917488],"type":"Point"}
}