{
  "type": "Feature",
  "properties": {
    "iso:country":"GB",
    "sg:address":"159 Sighthill Drive",
    "sg:city":"Edinburgh",
    "sg:classifiers":[
        {
            "category":"Place Of Worship",
            "type":"Public Place"
        }
    ],
    "sg:phone":"+44 131 453 5035",
    "sg:postcode":"EH11 4PY",
    "sg:province":"City of Edinburgh",
    "wof:name":"St John Ogilvie R C Church",
    "wof:placetype":"venue"
},
  "geometry": {"coordinates":[-3.2922990322,55.9244155884],"type":"Point"}
}