{
  "type": "Feature",
  "properties": {
    "addr:full":"Brown Rigg Farm, Bardon Mill Hexham Northumberland NE47 7EZ",
    "addr:postcode":"ne47 7ez",
    "addr:street":"Brown Rigg",
    "iso:country":"GB",
    "sg:address":"Brown Rigg Farm, Bardon Mill",
    "sg:city":"Hexham",
    "sg:classifiers":[
        {
            "category":"Farming",
            "subcategory":"Dairy Farm",
            "type":"Manufacturing & Wholesale Goods"
        }
    ],
    "sg:phone":"+44 1434 344447",
    "sg:postcode":"NE47 7EZ",
    "sg:province":"Northumberland",
    "wof:name":"Douglas Batey",
    "wof:placetype":"venue"
},
  "geometry": {"coordinates":[-2.3433868885,54.9764785767],"type":"Point"}
}