{
  "type": "Feature",
  "properties": {
    "iso:country":"GB",
    "sg:address":"24 Chester Road East, Shotton",
    "sg:city":"Deeside",
    "sg:classifiers":[
        {
            "category":"Shopping",
            "subcategory":"Bicycles & Sporting Goods",
            "type":"Retail Goods"
        }
    ],
    "sg:phone":"+44 1244 836583",
    "sg:postcode":"CH5 1QA",
    "sg:province":"Flintshire",
    "sg:tags":[
        "cycle",
        "accessory"
    ],
    "wof:name":"Shotton Cycles",
    "wof:placetype":"venue"
},
  "geometry": {"coordinates":[-3.038754,53.211182],"type":"Point"}
}