{
  "type": "Feature",
  "properties": {
    "addr:full":"Hinton House Station Road New Milton Hampshire BH25 6HZ",
    "addr:postcode":"bh25 6hz",
    "addr:street":"Station Road",
    "iso:country":"GB",
    "sg:address":"Hinton House Station Road",
    "sg:city":"New Milton",
    "sg:classifiers":[
        {
            "category":"Home & Garden",
            "subcategory":"Hardware",
            "type":"Retail Goods"
        }
    ],
    "sg:postcode":"BH25 6HZ",
    "sg:province":"Hampshire",
    "sg:tags":[
        "product",
        "wire",
        "electrical"
    ],
    "wof:name":"Rhemo Products Ltd.",
    "wof:placetype":"venue"
},
  "geometry": {"coordinates":[-1.6566040516,50.7559814453],"type":"Point"}
}