{
  "type": "Feature",
  "properties": {
    "addr:full":"74 Arnold Road, Shirley Solihull West Midlands B90 3JS",
    "addr:housenumber":"74",
    "addr:postcode":"b90 3js",
    "addr:street":"Arnold Road",
    "iso:country":"GB",
    "sg:address":"74 Arnold Road, Shirley",
    "sg:city":"Solihull",
    "sg:classifiers":[
        {
            "category":"Health Services",
            "subcategory":"Clinic",
            "type":"Services"
        }
    ],
    "sg:phone":"+44 121 744 0598",
    "sg:postcode":"B90 3JS",
    "sg:province":"West Midlands",
    "sg:tags":[
        "therapist",
        "injury",
        "sporting",
        "sport"
    ],
    "wof:name":"Active Associates Ltd.",
    "wof:placetype":"venue"
},
  "geometry": {"coordinates":[-1.8239059448,52.4172973633],"type":"Point"}
}