{
  "type": "Feature",
  "properties": {
    "addr:full":"43 Abbey Road Nottingham Nottinghamshire NG2 5NG",
    "addr:housenumber":"43",
    "addr:postcode":"ng2 5ng",
    "addr:street":"Abbey Road",
    "iso:country":"GB",
    "sg:address":"43 Abbey Road",
    "sg:city":"Nottingham",
    "sg:classifiers":[
        {
            "category":"Shopping",
            "subcategory":"Baby Store",
            "type":"Retail Goods"
        }
    ],
    "sg:phone":"+44 115 981 1257",
    "sg:postcode":"NG2 5NG",
    "sg:province":"Nottinghamshire",
    "sg:tags":[
        "babywear",
        "childrens"
    ],
    "wof:name":"Togs and Toys",
    "wof:placetype":"venue"
},
  "geometry": {"coordinates":[-1.120868,52.929585],"type":"Point"}
}