{
  "type": "Feature",
  "properties": {
    "addr:full":"162 St Marys Lane Upminster Essex RM14 3BS",
    "addr:housenumber":"162",
    "addr:postcode":"rm14 3bs",
    "addr:street":"St Marys Lane",
    "iso:country":"GB",
    "sg:address":"162 St Marys Lane",
    "sg:city":"Upminster",
    "sg:classifiers":[
        {
            "category":"Professional",
            "subcategory":"Detective & Security Services",
            "type":"Services"
        },
        {
            "category":"Military Area",
            "subcategory":"Air Force Base",
            "type":"Public Place"
        }
    ],
    "sg:phone":"+44 1708 224411",
    "sg:postcode":"RM14 3BS",
    "sg:province":"Essex",
    "sg:tags":[
        "water",
        "equipment",
        "treatment"
    ],
    "wof:name":"Eurotech Purewater Systems Ltd.",
    "wof:placetype":"venue"
},
  "geometry": {"coordinates":[0.250308,51.556114],"type":"Point"}
}