{
  "type": "Feature",
  "properties": {
    "iso:country":"GB",
    "sg:address":"The Old Mill, Park Road",
    "sg:city":"Shepton Mallet",
    "sg:classifiers":[
        {
            "category":"Professional",
            "subcategory":"Business Services",
            "type":"Services"
        }
    ],
    "sg:postcode":"BA4 5BS",
    "sg:province":"Somerset",
    "sg:tags":[
        "accomodation"
    ],
    "wof:name":"Rangelocal Ltd",
    "wof:placetype":"venue"
},
  "geometry": {"coordinates":[-2.546778,51.189732],"type":"Point"}
}