{
  "type": "Feature",
  "properties": {
    "addr:full":"37 Summerlands Road, Fair Oak Eastleigh Hampshire SO50 7AU",
    "addr:housenumber":"37",
    "addr:postcode":"so50 7au",
    "addr:street":"Summerlands Road",
    "iso:country":"GB",
    "sg:address":"37 Summerlands Road, Fair Oak",
    "sg:city":"Eastleigh",
    "sg:classifiers":[
        {
            "category":"Retail",
            "subcategory":"Laundry & Dry Cleaning",
            "type":"Services"
        }
    ],
    "sg:phone":"+44 23 8069 3322",
    "sg:postcode":"SO50 7AU",
    "sg:province":"Hampshire",
    "sg:tags":[
        "alteration"
    ],
    "wof:name":"Atlantic Dry Cleaners & Tailors",
    "wof:placetype":"venue"
},
  "geometry": {"coordinates":[-1.29949,50.964851],"type":"Point"}
}