{
  "type": "Feature",
  "properties": {
    "iso:country":"GB",
    "sg:address":"39-45 Washwood Heath Road, Saltley",
    "sg:city":"Birmingham",
    "sg:classifiers":[
        {
            "category":"Real Estate",
            "subcategory":"Real Estate Agent",
            "type":"Services"
        }
    ],
    "sg:postcode":"B8 1RS",
    "sg:province":"West Midlands",
    "wof:name":"Hillgate Estates Ltd.",
    "wof:placetype":"venue"
},
  "geometry": {"coordinates":[-1.85796,52.492821],"type":"Point"}
}