{
  "type": "Feature",
  "properties": {
    "addr:full":"23 High Street Halstead Essex CO9 2AA",
    "addr:housenumber":"23",
    "addr:postcode":"co9 2aa",
    "addr:street":"High Street",
    "iso:country":"GB",
    "sg:address":"23 High Street",
    "sg:city":"Halstead",
    "sg:classifiers":[
        {
            "category":"Fast Food",
            "type":"Food & Drink"
        }
    ],
    "sg:phone":"+44 1787 475813",
    "sg:postcode":"CO9 2AA",
    "sg:province":"Essex",
    "sg:tags":[
        "away",
        "take"
    ],
    "wof:name":"Mans Garden",
    "wof:placetype":"venue"
},
  "geometry": {"coordinates":[0.637913,51.944759],"type":"Point"}
}