{
  "type": "Feature",
  "properties": {
    "addr:full":"17 Carter Drive, Collier Row Romford Essex RM5 2NT",
    "addr:housenumber":"17",
    "addr:postcode":"rm5 2nt",
    "addr:street":"Carter Drive",
    "iso:country":"GB",
    "sg:address":"17 Carter Drive, Collier Row",
    "sg:city":"Romford",
    "sg:classifiers":[
        {
            "category":"Retail",
            "subcategory":"Driving School",
            "type":"Services"
        }
    ],
    "sg:phone":"+44 1708 720454",
    "sg:postcode":"RM5 2NT",
    "sg:province":"Essex",
    "wof:name":"A J R School of Motoring",
    "wof:placetype":"venue"
},
  "geometry": {"coordinates":[0.158397004,51.6014099121],"type":"Point"}
}