{
  "type": "Feature",
  "properties": {
    "iso:country":"GB",
    "sg:address":"57-63 Market Square",
    "sg:city":"Basildon",
    "sg:classifiers":[
        {
            "category":"Health Services",
            "subcategory":"Optometrist",
            "type":"Services"
        }
    ],
    "sg:phone":"+44 1268 524707",
    "sg:postcode":"SS14 1DE",
    "sg:province":"Essex",
    "sg:tags":[
        "optician"
    ],
    "wof:name":"Churchills of London Ltd.",
    "wof:placetype":"venue"
},
  "geometry": {"coordinates":[0.4573769867,51.5692443848],"type":"Point"}
}