{
  "type": "Feature",
  "properties": {
    "addr:full":"Brighton Road Lewes East Sussex BN7 3JL",
    "addr:postcode":"bn7 3jl",
    "addr:street":"Brighton Road",
    "iso:country":"GB",
    "sg:address":"Brighton Road",
    "sg:city":"Lewes",
    "sg:classifiers":[
        {
            "category":"Shopping",
            "subcategory":"Computers & Home Electronics",
            "type":"Retail Goods"
        }
    ],
    "sg:phone":"+44 1273 476456",
    "sg:postcode":"BN7 3JL",
    "sg:province":"East Sussex",
    "sg:tags":[
        "equipment",
        "radio"
    ],
    "wof:name":"Radio Relay",
    "wof:placetype":"venue"
},
  "geometry": {"coordinates":[-0.0161240008,50.8681945801],"type":"Point"}
}