{
  "type": "Feature",
  "properties": {
    "addr:full":"82 Kinmount Avenue Glasgow East Renfrewshire G44 4RT",
    "addr:housenumber":"82",
    "addr:postcode":"g44 4rt",
    "addr:street":"Kinmount Avenue",
    "iso:country":"GB",
    "sg:address":"82 Kinmount Avenue",
    "sg:city":"Glasgow",
    "sg:classifiers":[
        {
            "category":"Organizations",
            "subcategory":"Non-profit Organization",
            "type":"Services"
        }
    ],
    "sg:postcode":"G44 4RT",
    "sg:province":"East Renfrewshire",
    "sg:tags":[
        "organisation",
        "voluntary",
        "charity"
    ],
    "wof:name":"Multiple Sclerosis Society in Scotland",
    "wof:placetype":"venue"
},
  "geometry": {"coordinates":[-4.2507882118,55.8232803345],"type":"Point"}
}