{
  "type": "Feature",
  "properties": {
    "addr:full":"33 Gelliwastad Rd Pontypridd Caerphilly CF37 2BN",
    "addr:housenumber":"33",
    "addr:postcode":"cf37 2bn",
    "addr:street":"Gelliwastad Rd",
    "iso:country":"GB",
    "sg:address":"33 Gelliwastad Rd",
    "sg:city":"Pontypridd",
    "sg:classifiers":[
        {
            "category":"Professional",
            "subcategory":"Lawyer & Legal Services",
            "type":"Services"
        }
    ],
    "sg:phone":"+44 1443 403470",
    "sg:postcode":"CF37 2BN",
    "sg:province":"Caerphilly",
    "sg:tags":[
        "advice",
        "counselling"
    ],
    "wof:name":"Directus Youth Project",
    "wof:placetype":"venue"
},
  "geometry": {"coordinates":[-3.341776,51.602249],"type":"Point"}
}