{
  "type": "Feature",
  "properties": {
    "iso:country":"GB",
    "sg:address":"School Bungalow, St Olaves Road",
    "sg:city":"Bury St Edmunds",
    "sg:classifiers":[
        {
            "category":"Education",
            "subcategory":"School",
            "type":"Public Place"
        }
    ],
    "sg:phone":"+44 1284 754450",
    "sg:postcode":"IP32 6RW",
    "sg:province":"Suffolk",
    "sg:tags":[
        "local",
        "authority"
    ],
    "wof:name":"Howard Primary School",
    "wof:placetype":"venue"
},
  "geometry": {"coordinates":[0.69769,52.260586],"type":"Point"}
}