{
  "type": "Feature",
  "properties": {
    "iso:country":"GB",
    "sg:address":"75 Sandway",
    "sg:city":"Leeds",
    "sg:classifiers":[
        {
            "category":"Freight",
            "type":"Transportation"
        }
    ],
    "sg:phone":"+44 113 260 7109",
    "sg:postcode":"LS15 7NT",
    "sg:province":"West Yorkshire",
    "sg:tags":[
        "haulage",
        "road"
    ],
    "wof:name":"Freight Services for Export",
    "wof:placetype":"venue"
},
  "geometry": {"coordinates":[-1.461848,53.809078],"type":"Point"}
}