{
  "type": "Feature",
  "properties": {
    "addr:full":"329 Wellingborough Rd Northampton Northamptonshire NN1 4EW",
    "addr:housenumber":"329",
    "addr:postcode":"nn1 4ew",
    "addr:street":"Wellingborough Rd",
    "iso:country":"GB",
    "sg:address":"329 Wellingborough Rd",
    "sg:city":"Northampton",
    "sg:classifiers":[
        {
            "category":"Professional",
            "subcategory":"Management & Consulting",
            "type":"Services"
        }
    ],
    "sg:postcode":"NN1 4EW",
    "sg:province":"Northamptonshire",
    "sg:tags":[
        "consultant",
        "business"
    ],
    "wof:name":"Ddi Consultants",
    "wof:placetype":"venue"
},
  "geometry": {"coordinates":[-0.873082,52.243366],"type":"Point"}
}