{
  "type": "Feature",
  "properties": {
    "iso:country":"GB",
    "sg:address":"4 Dean Street",
    "sg:city":"Darwen",
    "sg:classifiers":[
        {
            "category":"Home & Garden",
            "subcategory":"Household Appliances",
            "type":"Retail Goods"
        },
        {
            "category":"Retail",
            "subcategory":"Repair Shop",
            "type":"Services"
        }
    ],
    "sg:postcode":"BB3 1HH",
    "sg:province":"Lancashire",
    "sg:tags":[
        "electrical",
        "television",
        "video",
        "radio"
    ],
    "wof:name":"D T V S",
    "wof:placetype":"venue"
},
  "geometry": {"coordinates":[-2.477318,53.707302],"type":"Point"}
}