{
  "type": "Feature",
  "properties": {
    "addr:full":"Ellison Rd Gateshead Tyne and Wear NE11 9SS",
    "addr:postcode":"ne11 9ss",
    "addr:street":"Ellison Rd",
    "iso:country":"GB",
    "sg:address":"Ellison Rd",
    "sg:city":"Gateshead",
    "sg:classifiers":[
        {
            "category":"Education",
            "subcategory":"Library",
            "type":"Public Place"
        }
    ],
    "sg:phone":"+44 191 460 5000",
    "sg:postcode":"NE11 9SS",
    "sg:province":"Tyne and Wear",
    "sg:tags":[
        "book"
    ],
    "wof:name":"Dunston Library",
    "wof:placetype":"venue"
},
  "geometry": {"coordinates":[-1.6393300295,54.9509315491],"type":"Point"}
}