{
  "type": "Feature",
  "properties": {
    "addr:full":"Centurion Ho, 129 Deansgate Manchester Greater Manchester M3 3WR",
    "addr:housenumber":"129",
    "addr:postcode":"m3 3wr",
    "addr:street":"Deansgate",
    "iso:country":"GB",
    "sg:address":"Centurion Ho, 129 Deansgate",
    "sg:city":"Manchester",
    "sg:classifiers":[
        {
            "category":"Insurance",
            "subcategory":"Insurance Agent",
            "type":"Services"
        }
    ],
    "sg:postcode":"M3 3WR",
    "sg:province":"Greater Manchester",
    "sg:tags":[
        "broker"
    ],
    "wof:name":"Corroon,W F,",
    "wof:placetype":"venue"
},
  "geometry": {"coordinates":[-2.2501089573,53.4795684814],"type":"Point"}
}