{
  "type": "Feature",
  "properties": {
    "addr:full":"1a Snowley Pde Bishops Stortford Essex CM23 5EP",
    "addr:housenumber":"1a",
    "addr:postcode":"cm23 5ep",
    "addr:street":"Snowley Pde",
    "iso:country":"GB",
    "sg:address":"1a Snowley Pde",
    "sg:city":"Bishops Stortford",
    "sg:classifiers":[
        {
            "category":"Professional",
            "subcategory":"Lawyer & Legal Services",
            "type":"Services"
        }
    ],
    "sg:phone":"+44 1279 657684",
    "sg:postcode":"CM23 5EP",
    "sg:province":"Essex",
    "sg:tags":[
        "advice",
        "counselling"
    ],
    "wof:name":"Parsonage Counselling Service",
    "wof:placetype":"venue"
},
  "geometry": {"coordinates":[0.173908,51.876865],"type":"Point"}
}