{
  "type": "Feature",
  "properties": {
    "addr:full":"60 Macdonald Smith Drive Carnoustie Angus DD7 7TB",
    "addr:housenumber":"60",
    "addr:postcode":"dd7 7tb",
    "addr:street":"Macdonald Smith Drive",
    "iso:country":"GB",
    "sg:address":"60 Macdonald Smith Drive",
    "sg:city":"Carnoustie",
    "sg:classifiers":[
        {
            "category":"Shopping",
            "subcategory":"Mobile Phones",
            "type":"Retail Goods"
        }
    ],
    "sg:postcode":"DD7 7TB",
    "sg:province":"Angus",
    "wof:name":"Carnoustie Cellular on Site",
    "wof:placetype":"venue"
},
  "geometry": {"coordinates":[-2.745555,56.49902],"type":"Point"}
}