{
  "type": "Feature",
  "properties": {
    "addr:full":"Shirland Rd London Greater London W9 2JD",
    "addr:postcode":"w9 2jd",
    "addr:street":"Shirland Rd",
    "iso:country":"GB",
    "sg:address":"Shirland Rd",
    "sg:city":"London",
    "sg:classifiers":[
        {
            "category":"Education",
            "subcategory":"School",
            "type":"Public Place"
        }
    ],
    "sg:postcode":"W9 2JD",
    "sg:province":"Greater London",
    "sg:tags":[
        "local",
        "authority"
    ],
    "wof:name":"Westminster City Council",
    "wof:placetype":"venue"
},
  "geometry": {"coordinates":[-0.197258994,51.5277481079],"type":"Point"}
}