{
  "type": "Feature",
  "properties": {
    "addr:full":"The Old Lindley Farm, Old Lindley, Holywell Green Halifax West Yorkshire HX4 9DF",
    "addr:postcode":"hx4 9df",
    "addr:street":"Old;Holywell Green",
    "iso:country":"GB",
    "sg:address":"The Old Lindley Farm, Old Lindley, Holywell Green",
    "sg:city":"Halifax",
    "sg:classifiers":[
        {
            "category":"Farming",
            "subcategory":"Dairy Farm",
            "type":"Manufacturing & Wholesale Goods"
        }
    ],
    "sg:postcode":"HX4 9DF",
    "sg:province":"West Yorkshire",
    "wof:name":"Smith Bros",
    "wof:placetype":"venue"
},
  "geometry": {"coordinates":[-1.8745059967,53.6737785339],"type":"Point"}
}