{
  "type": "Feature",
  "properties": {
    "iso:country":"GB",
    "sg:address":"Lichfield Road",
    "sg:city":"Cannock",
    "sg:classifiers":[
        {
            "category":"Home & Garden",
            "subcategory":"Hardware",
            "type":"Retail Goods"
        }
    ],
    "sg:phone":"+44 1543 570237",
    "sg:postcode":"WS11 3EE",
    "sg:province":"Staffordshire",
    "sg:tags":[
        "retailer",
        "diy"
    ],
    "wof:name":"Wickes Building Supplies Ltd.",
    "wof:placetype":"venue"
},
  "geometry": {"coordinates":[-2.0177400112,52.686668396],"type":"Point"}
}