{
  "type": "Feature",
  "properties": {
    "addr:full":"20 Princip Street Birmingham West Midlands B4 6LE",
    "addr:housenumber":"20",
    "addr:postcode":"b4 6le",
    "addr:street":"Princip Street",
    "iso:country":"GB",
    "sg:address":"20 Princip Street",
    "sg:city":"Birmingham",
    "sg:classifiers":[
        {
            "category":"Shopping",
            "subcategory":"Luggage & Leather Goods",
            "type":"Retail Goods"
        }
    ],
    "sg:phone":"+44 121 359 5116",
    "sg:postcode":"B4 6LE",
    "sg:province":"West Midlands",
    "wof:name":"Mallard Accessories Ltd.",
    "wof:placetype":"venue"
},
  "geometry": {"coordinates":[-1.895127,52.488033],"type":"Point"}
}