{
  "type": "Feature",
  "properties": {
    "iso:country":"GB",
    "sg:address":"122 Houghton Road, Hetton-le-hole",
    "sg:city":"Houghton-le-spring",
    "sg:classifiers":[
        {
            "category":"Building & Trades",
            "subcategory":"Plumbing",
            "type":"Services"
        }
    ],
    "sg:postcode":"DH5 9PL",
    "sg:province":"Durham",
    "sg:tags":[
        "heating"
    ],
    "wof:name":"Clean & Save",
    "wof:placetype":"venue"
},
  "geometry": {"coordinates":[-1.45571,54.828476],"type":"Point"}
}