{
  "type": "Feature",
  "properties": {
    "addr:full":"26 Spring Rd Southampton Hampshire SO31 7FH",
    "addr:housenumber":"26",
    "addr:postcode":"so31 7fh",
    "addr:street":"Spring Rd",
    "iso:country":"GB",
    "sg:address":"26 Spring Rd",
    "sg:city":"Southampton",
    "sg:classifiers":[
        {
            "category":"Building & Trades",
            "subcategory":"Pest Control",
            "type":"Services"
        }
    ],
    "sg:phone":"+44 1489 600744",
    "sg:postcode":"SO31 7FH",
    "sg:province":"Hampshire",
    "sg:tags":[
        "vermin"
    ],
    "wof:name":"R & I Pest Control",
    "wof:placetype":"venue"
},
  "geometry": {"coordinates":[-1.280383,50.876343],"type":"Point"}
}