{
  "type": "Feature",
  "properties": {
    "addr:full":"84 Mount Ambrose Redruth Cornwall TR15 1QR",
    "addr:housenumber":"84",
    "addr:postcode":"tr15 1qr",
    "addr:street":"Mount Ambrose",
    "iso:country":"GB",
    "sg:address":"84 Mount Ambrose",
    "sg:city":"Redruth",
    "sg:classifiers":[
        {
            "category":"Food & Beverages",
            "subcategory":"Fruits & Vegetables",
            "type":"Retail Goods"
        }
    ],
    "sg:phone":"+44 1209 211973",
    "sg:postcode":"TR15 1QR",
    "sg:province":"Cornwall",
    "sg:tags":[
        "greengrocer"
    ],
    "wof:name":"K.E.D Groceries",
    "wof:placetype":"venue"
},
  "geometry": {"coordinates":[-5.2107038498,50.2473182678],"type":"Point"}
}