{
  "type": "Feature",
  "properties": {
    "iso:country":"GB",
    "sg:address":"61 High St",
    "sg:city":"Colchester",
    "sg:classifiers":[
        {
            "category":"Shopping",
            "subcategory":"Clothing, Apparel, & Fashions",
            "type":"Retail Goods"
        }
    ],
    "sg:phone":"+44 1206 710111",
    "sg:postcode":"CO1 1DN",
    "sg:province":"Essex",
    "sg:tags":[
        "ladieswear"
    ],
    "wof:name":"Hunters",
    "wof:placetype":"venue"
},
  "geometry": {"coordinates":[0.902609,51.889458],"type":"Point"}
}