{
  "type": "Feature",
  "properties": {
    "addr:full":"56 Lowfield Road, Caversham Reading Berkshire RG4 6PB",
    "addr:housenumber":"56",
    "addr:postcode":"rg4 6pb",
    "addr:street":"Lowfield Road",
    "iso:country":"GB",
    "sg:address":"56 Lowfield Road, Caversham",
    "sg:city":"Reading",
    "sg:classifiers":[
        {
            "category":"Professional",
            "type":"Services"
        }
    ],
    "sg:postcode":"RG4 6PB",
    "sg:province":"Berkshire",
    "sg:tags":[
        "entertainer"
    ],
    "wof:name":"The Jazz Agency",
    "wof:placetype":"venue"
},
  "geometry": {"coordinates":[-0.950789988,51.4790649414],"type":"Point"}
}