{
  "type": "Feature",
  "properties": {
    "iso:country":"GB",
    "sg:address":"4a The Bull Ring, Sedgley",
    "sg:city":"Dudley",
    "sg:classifiers":[
        {
            "category":"Professional",
            "subcategory":"Accounting & Tax Preparation",
            "type":"Services"
        }
    ],
    "sg:phone":"+44 1902 662626",
    "sg:postcode":"DY3 1RU",
    "sg:province":"Staffordshire",
    "sg:tags":[
        "accountant"
    ],
    "wof:name":"Guy & Co",
    "wof:placetype":"venue"
},
  "geometry": {"coordinates":[-2.121511,52.548782],"type":"Point"}
}