{
  "type": "Feature",
  "properties": {
    "iso:country":"GB",
    "sg:address":"Enville Road, Kinver",
    "sg:city":"Stourbridge",
    "sg:classifiers":[
        {
            "category":"Community Center",
            "type":"Public Place"
        },
        {
            "category":"Government",
            "subcategory":"Office",
            "type":"Public Place"
        }
    ],
    "sg:phone":"+44 1384 873950",
    "sg:postcode":"DY7 6AA",
    "sg:province":"Shropshire",
    "sg:tags":[
        "recreation",
        "local",
        "leisure",
        "centre"
    ],
    "wof:name":"Kinver Leisure Centre",
    "wof:placetype":"venue"
},
  "geometry": {"coordinates":[-2.233058,52.452961],"type":"Point"}
}