{
  "type": "Feature",
  "properties": {
    "iso:country":"GB",
    "sg:address":"15-17 West Derby Village",
    "sg:city":"Liverpool",
    "sg:classifiers":[
        {
            "category":"Education",
            "subcategory":"Music School",
            "type":"Public Place"
        },
        {
            "category":"Building & Trades",
            "subcategory":"Construction",
            "type":"Services"
        }
    ],
    "sg:phone":"+44 151 256 8096",
    "sg:postcode":"L12 5HJ",
    "sg:province":"Merseyside",
    "sg:tags":[
        "specialised",
        "conservatory",
        "contractor"
    ],
    "wof:name":"SOUTHERN CONSERVATORIES LTD",
    "wof:placetype":"venue"
},
  "geometry": {"coordinates":[-2.91071105,53.4328269958],"type":"Point"}
}