{
  "type": "Feature",
  "properties": {
    "iso:country":"GB",
    "sg:address":"St Bernards Presbytery, 95a Kingsley Road",
    "sg:city":"Liverpool",
    "sg:classifiers":[
        {
            "category":"Place Of Worship",
            "type":"Public Place"
        }
    ],
    "sg:phone":"+44 151 709 4434",
    "sg:postcode":"L8 2TY",
    "sg:province":"Merseyside",
    "wof:name":"Our Lady Of Lourdes & St Bernard R C Church",
    "wof:placetype":"venue"
},
  "geometry": {"coordinates":[-2.954569,53.392971],"type":"Point"}
}