{
  "type": "Feature",
  "properties": {
    "addr:full":"Church House, 167 Rectory Lane Sidcup Kent DA14 5BU",
    "addr:housenumber":"167",
    "addr:postcode":"da14 5bu",
    "addr:street":"Rectory Lane",
    "iso:country":"GB",
    "sg:address":"Church House, 167 Rectory Lane",
    "sg:city":"Sidcup",
    "sg:classifiers":[
        {
            "category":"Education",
            "subcategory":"School",
            "type":"Public Place"
        }
    ],
    "sg:phone":"+44 20 8309 0619",
    "sg:postcode":"DA14 5BU",
    "sg:province":"Kent",
    "sg:tags":[
        "independent",
        "preparatory",
        "local",
        "authority"
    ],
    "wof:name":"Harenc School Trust",
    "wof:placetype":"venue"
},
  "geometry": {"coordinates":[0.1155449972,51.4240341187],"type":"Point"}
}