{
  "type": "Feature",
  "properties": {
    "iso:country":"GB",
    "sg:address":"30 Canterbury Road",
    "sg:city":"Worthing",
    "sg:classifiers":[
        {
            "category":"Building & Trades",
            "subcategory":"Cleaning & Sanitation",
            "type":"Services"
        }
    ],
    "sg:phone":"+44 1903 821354",
    "sg:postcode":"BN13 1AE",
    "sg:province":"West Sussex",
    "sg:tags":[
        "sweep",
        "chimney"
    ],
    "wof:name":"A & M Chimney Sweeps",
    "wof:placetype":"venue"
},
  "geometry": {"coordinates":[-0.393962,50.819645],"type":"Point"}
}