{
  "type": "Feature",
  "properties": {
    "addr:full":"47-51 Wallgate Wigan Lancashire WN1 1BE",
    "addr:housenumber":"47-51",
    "addr:postcode":"wn1 1be",
    "addr:street":"Wallgate Wigan",
    "iso:country":"GB",
    "sg:address":"47-51 Wallgate",
    "sg:city":"Wigan",
    "sg:classifiers":[
        {
            "category":"Home & Garden",
            "subcategory":"Furniture",
            "type":"Retail Goods"
        }
    ],
    "sg:phone":"+44 1942 242210",
    "sg:postcode":"WN1 1BE",
    "sg:province":"Lancashire",
    "wof:name":"Brian's Furnishing Stores Ltd.",
    "wof:placetype":"venue"
},
  "geometry": {"coordinates":[-2.6328310966,53.544670105],"type":"Point"}
}