{
  "type": "Feature",
  "properties": {
    "iso:country":"GB",
    "sg:address":"Peckforton Hall Lane, Spurstow",
    "sg:city":"Tarporley",
    "sg:classifiers":[
        {
            "category":"Farming",
            "subcategory":"Nursery",
            "type":"Manufacturing & Wholesale Goods"
        }
    ],
    "sg:phone":"+44 1829 260676",
    "sg:postcode":"CW6 9TG",
    "sg:province":"Cheshire",
    "sg:tags":[
        "creche"
    ],
    "wof:name":"Bramley Hedge Nursery",
    "wof:placetype":"venue"
},
  "geometry": {"coordinates":[-2.68978405,53.1034164429],"type":"Point"}
}