{
  "type": "Feature",
  "properties": {
    "iso:country":"GB",
    "sg:address":"Greyfriars Pl",
    "sg:city":"Stafford",
    "sg:classifiers":[
        {
            "category":"Building & Trades",
            "subcategory":"Construction",
            "type":"Services"
        }
    ],
    "sg:phone":"+44 1785 243304",
    "sg:postcode":"ST16 2SD",
    "sg:province":"Staffordshire",
    "sg:tags":[
        "platform",
        "work",
        "scaffolding"
    ],
    "wof:name":"North Staffs Scaffolding",
    "wof:placetype":"venue"
},
  "geometry": {"coordinates":[-2.1217679977,52.8039588928],"type":"Point"}
}