{
  "type": "Feature",
  "properties": {
    "addr:full":"183 Deptford High St, Deptford London Greater London SE8 3NT",
    "addr:housenumber":"183",
    "addr:postcode":"se8 3nt",
    "addr:street":"Deptford High St",
    "iso:country":"GB",
    "sg:address":"183 Deptford High St, Deptford",
    "sg:city":"London",
    "sg:classifiers":[
        {
            "category":"Professional",
            "subcategory":"Printing & Photocopies",
            "type":"Services"
        }
    ],
    "sg:postcode":"SE8 3NT",
    "sg:province":"Greater London",
    "sg:tags":[
        "printer"
    ],
    "wof:name":"Dante's Design & Print Shop Ltd",
    "wof:placetype":"venue"
},
  "geometry": {"coordinates":[-0.0261560008,51.4808425903],"type":"Point"}
}