{
  "type": "Feature",
  "properties": {
    "iso:country":"GB",
    "sg:address":"229 Kensington",
    "sg:city":"Liverpool",
    "sg:classifiers":[
        {
            "category":"Shopping",
            "subcategory":"Thrift Store",
            "type":"Retail Goods"
        }
    ],
    "sg:phone":"+44 151 263 3430",
    "sg:postcode":"L7 2RF",
    "sg:province":"Merseyside",
    "sg:tags":[
        "shop",
        "charity"
    ],
    "wof:name":"Nugent Care Society The",
    "wof:placetype":"venue"
},
  "geometry": {"coordinates":[-2.9480030537,53.4121627808],"type":"Point"}
}