{
  "type": "Feature",
  "properties": {
    "iso:country":"GB",
    "sg:address":"75 Lincoln Av",
    "sg:city":"Bognor Regis",
    "sg:classifiers":[
        {
            "category":"Building & Trades",
            "subcategory":"Construction",
            "type":"Services"
        }
    ],
    "sg:phone":"+44 1243 262235",
    "sg:postcode":"PO21 3EW",
    "sg:province":"West Sussex",
    "sg:tags":[
        "ceiling",
        "contractor"
    ],
    "wof:name":"A J W Suspended Ceilings",
    "wof:placetype":"venue"
},
  "geometry": {"coordinates":[-0.718571,50.789612],"type":"Point"}
}