{
  "type": "Feature",
  "properties": {
    "iso:country":"GB",
    "sg:address":"Regional Service Centre, Gowerton Rd, Rackmills Indust Est",
    "sg:city":"Northampton",
    "sg:classifiers":[
        {
            "category":"Food & Beverages",
            "subcategory":"Liquor & Beverages",
            "type":"Retail Goods"
        }
    ],
    "sg:phone":"+44 1604 731300",
    "sg:postcode":"NN4 7BJ",
    "sg:province":"Northamptonshire",
    "sg:tags":[
        "drink",
        "soft"
    ],
    "wof:name":"Coca Cola & Schweppes Beverages Ltd",
    "wof:placetype":"venue"
},
  "geometry": {"coordinates":[-0.8594599962,52.2139396667],"type":"Point"}
}