{
  "type": "Feature",
  "properties": {
    "iso:country":"GB",
    "sg:address":"2 Cranleigh Gardens",
    "sg:city":"Maidstone",
    "sg:classifiers":[
        {
            "category":"Building & Trades",
            "subcategory":"Construction",
            "type":"Services"
        }
    ],
    "sg:phone":"+44 1622 671996",
    "sg:postcode":"ME16 0TX",
    "sg:province":"Kent",
    "sg:tags":[
        "builder"
    ],
    "wof:name":"A Rocca",
    "wof:placetype":"venue"
},
  "geometry": {"coordinates":[0.500631,51.288422],"type":"Point"}
}