{
  "type": "Feature",
  "properties": {
    "addr:full":"Station Ho Bruton Somerset BA10 0PJ",
    "addr:postcode":"ba10 0pj",
    "iso:country":"GB",
    "sg:address":"Station Ho",
    "sg:city":"Bruton",
    "sg:classifiers":[
        {
            "category":"Health Services",
            "subcategory":"Clinic",
            "type":"Services"
        }
    ],
    "sg:phone":"+44 1749 813677",
    "sg:postcode":"BA10 0PJ",
    "sg:province":"Somerset",
    "sg:tags":[
        "abuse",
        "drug"
    ],
    "wof:name":"M A Risk Solutions",
    "wof:placetype":"venue"
},
  "geometry": {"coordinates":[-2.4524390697,51.1128845215],"type":"Point"}
}