{
  "type": "Feature",
  "properties": {
    "iso:country":"GB",
    "sg:address":"Park Hall Farm, Park Hall Road, Mansfield Woodhouse",
    "sg:city":"Mansfield",
    "sg:classifiers":[
        {
            "category":"Farming",
            "subcategory":"Farm",
            "type":"Manufacturing & Wholesale Goods"
        }
    ],
    "sg:phone":"+44 1623 626622",
    "sg:postcode":"NG19 8QX",
    "sg:province":"Derbyshire",
    "sg:tags":[
        "mixed",
        "crop"
    ],
    "wof:name":"John Brailsford",
    "wof:placetype":"venue"
},
  "geometry": {"coordinates":[-1.19029,53.178059],"type":"Point"}
}