{
  "type": "Feature",
  "properties": {
    "iso:country":"GB",
    "sg:address":"49 - 51 Oxbridge Lane",
    "sg:city":"Stockton-on-tees",
    "sg:classifiers":[
        {
            "category":"Professional",
            "subcategory":"Engineering",
            "type":"Services"
        }
    ],
    "sg:postcode":"TS18 4AP",
    "sg:province":"Durham",
    "sg:tags":[
        "contractor",
        "electrical",
        "engineer"
    ],
    "wof:name":"Trattles & Rushforth Ltd.",
    "wof:placetype":"venue"
},
  "geometry": {"coordinates":[-1.326664,54.561508],"type":"Point"}
}