{
  "type": "Feature",
  "properties": {
    "addr:full":"6 Forest Road Loughborough Leicestershire LE11 3NP",
    "addr:housenumber":"6",
    "addr:postcode":"le11 3np",
    "addr:street":"Forest Road",
    "iso:country":"GB",
    "sg:address":"6 Forest Road",
    "sg:city":"Loughborough",
    "sg:classifiers":[
        {
            "category":"Professional",
            "subcategory":"Accounting & Tax Preparation",
            "type":"Services"
        }
    ],
    "sg:postcode":"LE11 3NP",
    "sg:province":"Leicestershire",
    "sg:tags":[
        "accountant"
    ],
    "wof:name":"Newby Castleman",
    "wof:placetype":"venue"
},
  "geometry": {"coordinates":[-1.2092620134,52.7672691345],"type":"Point"}
}