{
  "type": "Feature",
  "properties": {
    "iso:country":"GB",
    "sg:address":"1 Severalls Indstl Pk, Clough Rd",
    "sg:city":"Colchester",
    "sg:classifiers":[
        {
            "category":"Farming",
            "subcategory":"Fish & Marine Products",
            "type":"Manufacturing & Wholesale Goods"
        }
    ],
    "sg:postcode":"CO4 4QS",
    "sg:province":"Essex",
    "sg:tags":[
        "fishmonger"
    ],
    "wof:name":"Direct Seafoods Ltd",
    "wof:placetype":"venue"
},
  "geometry": {"coordinates":[0.91336,51.924332],"type":"Point"}
}