{
  "type": "Feature",
  "properties": {
    "addr:full":"3 Verdun Avenue Salford Greater Manchester M6 8FS",
    "addr:housenumber":"3",
    "addr:postcode":"m6 8fs",
    "addr:street":"Verdun Avenue",
    "iso:country":"GB",
    "sg:address":"3 Verdun Avenue",
    "sg:city":"Salford",
    "sg:classifiers":[
        {
            "category":"Banks & Credit Unions",
            "subcategory":"Bank",
            "type":"Services"
        }
    ],
    "sg:postcode":"M6 8FS",
    "sg:province":"Greater Manchester",
    "sg:tags":[
        "stocktaking",
        "inventory"
    ],
    "wof:name":"Archers Stocktakers Associates",
    "wof:placetype":"venue"
},
  "geometry": {"coordinates":[-2.3239119053,53.4901809692],"type":"Point"}
}