{
  "type": "Feature",
  "properties": {
    "iso:country":"GB",
    "sg:address":"Butts Road, Sholing",
    "sg:city":"Southampton",
    "sg:classifiers":[
        {
            "category":"Bars & Pubs",
            "type":"Food & Drink"
        }
    ],
    "sg:phone":"+44 23 8044 8417",
    "sg:postcode":"SO19 7TH",
    "sg:province":"Hampshire",
    "sg:tags":[
        "pubs",
        "inn"
    ],
    "wof:name":"The Target",
    "wof:placetype":"venue"
},
  "geometry": {"coordinates":[-1.36789,50.907211],"type":"Point"}
}