{
  "type": "Feature",
  "properties": {
    "iso:country":"GB",
    "sg:address":"Station App, London Road",
    "sg:city":"Hemel Hempstead",
    "sg:classifiers":[
        {
            "category":"Fast Food",
            "type":"Food & Drink"
        }
    ],
    "sg:phone":"+44 1442 241034",
    "sg:postcode":"HP3 9BQ",
    "sg:province":"Hertfordshire",
    "sg:tags":[
        "away",
        "take"
    ],
    "wof:name":"Station Cafe Chinese Take Away",
    "wof:placetype":"venue"
},
  "geometry": {"coordinates":[-0.48947,51.743019],"type":"Point"}
}