{
  "type": "Feature",
  "properties": {
    "addr:full":"7 Admirals Hard Plymouth Devon PL1 3RJ",
    "addr:housenumber":"7",
    "addr:postcode":"pl1 3rj",
    "addr:street":"Admirals Hard",
    "iso:country":"GB",
    "sg:address":"7 Admirals Hard",
    "sg:city":"Plymouth",
    "sg:classifiers":[
        {
            "category":"Cafe",
            "type":"Food & Drink"
        }
    ],
    "sg:phone":"+44 1752 661015",
    "sg:postcode":"PL1 3RJ",
    "sg:province":"Devon",
    "sg:tags":[
        "tea",
        "snack",
        "bar",
        "room"
    ],
    "wof:name":"ALAN DOIDGE & TANIA BELL",
    "wof:placetype":"venue"
},
  "geometry": {"coordinates":[-4.1632390022,50.365688324],"type":"Point"}
}