{
  "type": "Feature",
  "properties": {
    "iso:country":"GB",
    "sg:address":"350 Sheffield Rd, Birdwell",
    "sg:city":"Barnsley",
    "sg:classifiers":[
        {
            "category":"Health Services",
            "subcategory":"Health Practitioner",
            "type":"Services"
        },
        {
            "category":"Shopping",
            "subcategory":"Pharmacy",
            "type":"Retail Goods"
        }
    ],
    "sg:phone":"+44 1226 744659",
    "sg:postcode":"S70 5TU",
    "sg:province":"South Yorkshire",
    "sg:tags":[
        "medicine",
        "medical",
        "therapy",
        "treatment",
        "alternative"
    ],
    "wof:name":"Aetherius Society",
    "wof:placetype":"venue"
},
  "geometry": {"coordinates":[-1.4788550138,53.5010147095],"type":"Point"}
}