{
  "type": "Feature",
  "properties": {
    "addr:full":"7 Greenwood St Dewsbury West Yorkshire WF13 2ND",
    "addr:housenumber":"7",
    "addr:postcode":"wf13 2nd",
    "addr:street":"Greenwood St",
    "iso:country":"GB",
    "sg:address":"7 Greenwood St",
    "sg:city":"Dewsbury",
    "sg:classifiers":[
        {
            "category":"Building & Trades",
            "subcategory":"Plumbing",
            "type":"Services"
        }
    ],
    "sg:phone":"+44 1924 450312",
    "sg:postcode":"WF13 2ND",
    "sg:province":"West Yorkshire",
    "sg:tags":[
        "central",
        "heating"
    ],
    "wof:name":"R Cooke",
    "wof:placetype":"venue"
},
  "geometry": {"coordinates":[-1.6394430399,53.6909332275],"type":"Point"}
}