{
  "type": "Feature",
  "properties": {
    "iso:country":"GB",
    "sg:address":"1 High Street",
    "sg:city":"Wolverhampton",
    "sg:classifiers":[
        {
            "category":"Home & Garden",
            "subcategory":"Hardware",
            "type":"Retail Goods"
        }
    ],
    "sg:phone":"+44 1902 700565",
    "sg:postcode":"WV6 7BB",
    "sg:province":"Shropshire",
    "wof:name":"Pattingham Hardware & Tools",
    "wof:placetype":"venue"
},
  "geometry": {"coordinates":[-2.263888,52.589249],"type":"Point"}
}