{
  "type": "Feature",
  "properties": {
    "iso:country":"GB",
    "sg:address":"64 Manchester Road",
    "sg:city":"Swindon",
    "sg:classifiers":[
        {
            "category":"Wholesale",
            "subcategory":"Machinery & Supplies",
            "type":"Manufacturing & Wholesale Goods"
        }
    ],
    "sg:phone":"+44 1793 511322",
    "sg:postcode":"SN1 2AQ",
    "sg:province":"Wiltshire",
    "sg:tags":[
        "hydraulic"
    ],
    "wof:name":"M P C (Brake & Hydraulic) Services Ltd.",
    "wof:placetype":"venue"
},
  "geometry": {"coordinates":[-1.7761349678,51.5659980774],"type":"Point"}
}