{
  "type": "Feature",
  "properties": {
    "addr:full":"Unit F Lomond Drive, Bishopbriggs Glasgow East Dunbartonshire G64 3BY",
    "addr:postcode":"g64 3by",
    "addr:street":"Lomond Drive",
    "iso:country":"GB",
    "sg:address":"Unit F Lomond Drive, Bishopbriggs",
    "sg:city":"Glasgow",
    "sg:classifiers":[
        {
            "category":"Cinema",
            "subcategory":"Movie Rental",
            "type":"Entertainment"
        }
    ],
    "sg:phone":"+44 141 772 4367",
    "sg:postcode":"G64 3BY",
    "sg:province":"East Dunbartonshire",
    "sg:tags":[
        "video",
        "library"
    ],
    "wof:name":"Global Video (U K)",
    "wof:placetype":"venue"
},
  "geometry": {"coordinates":[-4.2275891304,55.912525177],"type":"Point"}
}