{
  "type": "Feature",
  "properties": {
    "iso:country":"GB",
    "sg:address":"Glenthorne",
    "sg:city":"Corbridge",
    "sg:classifiers":[
        {
            "category":"Professional",
            "subcategory":"Management & Consulting",
            "type":"Services"
        }
    ],
    "sg:phone":"+44 1434 632523",
    "sg:postcode":"NE45 5LE",
    "sg:province":"Northumberland",
    "sg:tags":[
        "consultant",
        "business"
    ],
    "wof:name":"Rale Consultants Ltd.",
    "wof:placetype":"venue"
},
  "geometry": {"coordinates":[-2.013204,54.975937],"type":"Point"}
}