{
  "type": "Feature",
  "properties": {
    "addr:full":"Lock Farm Office, Lock Farm, Partridge Green Horsham West Sussex RH13 8EG",
    "addr:postcode":"rh13 8eg",
    "addr:street":"Green",
    "iso:country":"GB",
    "sg:address":"Lock Farm Office, Lock Farm, Partridge Green",
    "sg:city":"Horsham",
    "sg:classifiers":[
        {
            "category":"Farming",
            "subcategory":"Livestock Farm",
            "type":"Manufacturing & Wholesale Goods"
        }
    ],
    "sg:phone":"+44 1403 711614",
    "sg:postcode":"RH13 8EG",
    "sg:province":"West Sussex",
    "sg:tags":[
        "others"
    ],
    "wof:name":"Sentury Farming",
    "wof:placetype":"venue"
},
  "geometry": {"coordinates":[-0.32714,50.953789],"type":"Point"}
}