{
  "type": "Feature",
  "properties": {
    "addr:full":"10a Rutland Square Edinburgh City of Edinburgh EH1 2AS",
    "addr:housenumber":"10a",
    "addr:postcode":"eh1 2as",
    "addr:street":"Rutland Square",
    "iso:country":"GB",
    "sg:address":"10a Rutland Square",
    "sg:city":"Edinburgh",
    "sg:classifiers":[
        {
            "category":"Real Estate",
            "subcategory":"Surveying",
            "type":"Services"
        }
    ],
    "sg:phone":"+44 131 225 1212",
    "sg:postcode":"EH1 2AS",
    "sg:province":"City of Edinburgh",
    "sg:tags":[
        "surveyor",
        "valuer"
    ],
    "wof:name":"Speirs Gumley Surveyors",
    "wof:placetype":"venue"
},
  "geometry": {"coordinates":[-3.2087509632,55.9484138489],"type":"Point"}
}