{
  "type": "Feature",
  "properties": {
    "iso:country":"GB",
    "sg:address":"The Sale Room, Burkitts Lane",
    "sg:city":"Sudbury",
    "sg:classifiers":[
        {
            "category":"Professional",
            "type":"Services"
        }
    ],
    "sg:phone":"+44 1787 880305",
    "sg:postcode":"CO10 1HB",
    "sg:province":"Essex",
    "sg:tags":[
        "valuer",
        "auctioneer"
    ],
    "wof:name":"Olivers Auctioneers",
    "wof:placetype":"venue"
},
  "geometry": {"coordinates":[0.73439,52.038605],"type":"Point"}
}