{
  "type": "Feature",
  "properties": {
    "addr:full":"50 Main Street, Broughton, Astley Leicester Leicestershire LE9 6RD",
    "addr:housenumber":"50",
    "addr:postcode":"le9 6rd",
    "addr:street":"Main Street",
    "iso:country":"GB",
    "sg:address":"50 Main Street, Broughton, Astley",
    "sg:city":"Leicester",
    "sg:classifiers":[
        {
            "category":"Home & Garden",
            "subcategory":"Household Appliances",
            "type":"Retail Goods"
        },
        {
            "category":"Shopping",
            "subcategory":"Computers & Home Electronics",
            "type":"Retail Goods"
        }
    ],
    "sg:phone":"+44 1455 286603",
    "sg:postcode":"LE9 6RD",
    "sg:province":"Leicestershire",
    "sg:tags":[
        "equipment",
        "electrical",
        "audio-visual"
    ],
    "wof:name":"Wilmslow Audio Ltd.",
    "wof:placetype":"venue"
},
  "geometry": {"coordinates":[-1.228741,52.533104],"type":"Point"}
}