{
  "type": "Feature",
  "properties": {
    "iso:country":"GB",
    "sg:address":"63 Down Terrace",
    "sg:city":"Brighton",
    "sg:classifiers":[
        {
            "category":"Retail",
            "subcategory":"Auto Repair",
            "type":"Services"
        }
    ],
    "sg:postcode":"BN2 9ZJ",
    "sg:province":"East Sussex",
    "sg:tags":[
        "modification",
        "garage"
    ],
    "wof:name":"Mobile Mechanics",
    "wof:placetype":"venue"
},
  "geometry": {"coordinates":[-0.119564,50.828178],"type":"Point"}
}