{
  "type": "Feature",
  "properties": {
    "addr:full":"Torrs Warren Hotel, Stoneykirk Stranraer Dumfries and Galloway DG9 9DH",
    "addr:postcode":"dg9 9dh",
    "iso:country":"GB",
    "sg:address":"Torrs Warren Hotel, Stoneykirk",
    "sg:city":"Stranraer",
    "sg:classifiers":[
        {
            "category":"Travel",
            "subcategory":"Hotels & Motels",
            "type":"Entertainment"
        }
    ],
    "sg:phone":"+44 1776 830204",
    "sg:postcode":"DG9 9DH",
    "sg:province":"Dumfries and Galloway",
    "wof:name":"Torrs Warren Hotel",
    "wof:placetype":"venue"
},
  "geometry": {"coordinates":[-4.97544384,54.836643219],"type":"Point"}
}