{
  "type": "Feature",
  "properties": {
    "addr:full":"Highfield House, Princess Margaret Avenue Lincoln Lincolnshire LN4 3DA",
    "addr:postcode":"ln4 3da",
    "addr:street":"Princess Margaret Avenue",
    "iso:country":"GB",
    "sg:address":"Highfield House, Princess Margaret Avenue",
    "sg:city":"Lincoln",
    "sg:classifiers":[
        {
            "category":"Fast Food",
            "type":"Food & Drink"
        },
        {
            "category":"Food & Beverages",
            "subcategory":"Meat & Fish",
            "type":"Retail Goods"
        }
    ],
    "sg:phone":"+44 1526 322296",
    "sg:postcode":"LN4 3DA",
    "sg:province":"Lincolnshire",
    "sg:tags":[
        "chip",
        "away",
        "take"
    ],
    "wof:name":"Vernon's Fish and Chip Shop",
    "wof:placetype":"venue"
},
  "geometry": {"coordinates":[-0.4077909887,53.1374893188],"type":"Point"}
}