{
  "type": "Feature",
  "properties": {
    "addr:full":"34 Birkdale Road, Ealing London Greater London W5 1JZ",
    "addr:housenumber":"34",
    "addr:postcode":"w5 1jz",
    "addr:street":"Birkdale Road",
    "iso:country":"GB",
    "sg:address":"34 Birkdale Road, Ealing",
    "sg:city":"London",
    "sg:classifiers":[
        {
            "category":"Health Services",
            "subcategory":"Health Practitioner",
            "type":"Services"
        }
    ],
    "sg:phone":"+44 20 8998 9403",
    "sg:postcode":"W5 1JZ",
    "sg:province":"Greater London",
    "sg:tags":[
        "physiotherapist"
    ],
    "wof:name":"Farshideh Bondarenko",
    "wof:placetype":"venue"
},
  "geometry": {"coordinates":[-0.2997409999,51.5260276794],"type":"Point"}
}