{
  "type": "Feature",
  "properties": {
    "iso:country":"GB",
    "sg:address":"9a Poplar Close, Colnbrook",
    "sg:city":"Slough",
    "sg:classifiers":[
        {
            "category":"Professional",
            "type":"Services"
        },
        {
            "category":"Professional",
            "subcategory":"Business Services",
            "type":"Services"
        },
        {
            "category":"Building & Trades",
            "subcategory":"Construction",
            "type":"Services"
        }
    ],
    "sg:phone":"+44 1753 682965",
    "sg:postcode":"SL3 0PQ",
    "sg:province":"Berkshire",
    "sg:tags":[
        "joinery",
        "shopfitting",
        "carpentry",
        "shopfitters",
        "contractor"
    ],
    "wof:name":"C D S CONSTRUCTION SERVICES LTD",
    "wof:placetype":"venue"
},
  "geometry": {"coordinates":[-0.5130190253,51.4790611267],"type":"Point"}
}