{
  "type": "Feature",
  "properties": {
    "addr:full":"32 Malmesbury Rd Birmingham West Midlands B10 0JQ",
    "addr:housenumber":"32",
    "addr:postcode":"b10 0jq",
    "addr:street":"Malmesbury Rd",
    "iso:country":"GB",
    "sg:address":"32 Malmesbury Rd",
    "sg:city":"Birmingham",
    "sg:classifiers":[
        {
            "category":"Health Services",
            "subcategory":"Health Practitioner",
            "type":"Services"
        }
    ],
    "sg:phone":"+44 121 772 4253",
    "sg:postcode":"B10 0JQ",
    "sg:province":"West Midlands",
    "sg:tags":[
        "acupuncture"
    ],
    "wof:name":"Acupoint Magneto Clinic",
    "wof:placetype":"venue"
},
  "geometry": {"coordinates":[-1.8516490459,52.4625549316],"type":"Point"}
}