{
  "type": "Feature",
  "properties": {
    "iso:country":"GB",
    "sg:address":"27-29 High Street",
    "sg:city":"Denbigh",
    "sg:classifiers":[
        {
            "category":"Restaurant",
            "type":"Food & Drink"
        },
        {
            "category":"Cafe",
            "type":"Food & Drink"
        }
    ],
    "sg:phone":"+44 1745 813449",
    "sg:postcode":"LL16 3HY",
    "sg:province":"Conwy",
    "sg:tags":[
        "tea",
        "room"
    ],
    "wof:name":"The Forum",
    "wof:placetype":"venue"
},
  "geometry": {"coordinates":[-3.4200439453,53.1834259033],"type":"Point"}
}