{
  "type": "Feature",
  "properties": {
    "addr:full":"Dental Surgery, Grants Ho, 4 Willow Vale Frome Somerset BA11 1BG",
    "addr:housenumber":"4",
    "addr:postcode":"ba11 1bg",
    "addr:street":"Grants Ho;Willow Vale",
    "iso:country":"GB",
    "sg:address":"Dental Surgery, Grants Ho, 4 Willow Vale",
    "sg:city":"Frome",
    "sg:classifiers":[
        {
            "category":"Health Services",
            "subcategory":"Dentist",
            "type":"Services"
        }
    ],
    "sg:phone":"+44 1373 472684",
    "sg:postcode":"BA11 1BG",
    "sg:province":"Somerset",
    "sg:tags":[
        "technician",
        "dental"
    ],
    "wof:name":"N Paniccia",
    "wof:placetype":"venue"
},
  "geometry": {"coordinates":[-2.318807,51.228558],"type":"Point"}
}