{
  "type": "Feature",
  "properties": {
    "addr:full":"Verulam Road, Stafford Stafford Staffordshire ST16 3EA",
    "addr:postcode":"st16 3ea",
    "addr:street":"Verulam Road",
    "iso:country":"GB",
    "sg:address":"Verulam Road, Stafford",
    "sg:city":"Stafford",
    "sg:classifiers":[
        {
            "category":"Professional",
            "subcategory":"Lawyer & Legal Services",
            "type":"Services"
        }
    ],
    "sg:postcode":"ST16 3EA",
    "sg:province":"Staffordshire",
    "sg:tags":[
        "solicitor"
    ],
    "wof:name":"Cep Acoustics Ltd.",
    "wof:placetype":"venue"
},
  "geometry": {"coordinates":[-2.115464,52.825531],"type":"Point"}
}