{
  "type": "Feature",
  "properties": {
    "addr:full":"64a Marlborough Rd Archway Greater London N19 4NJ",
    "addr:housenumber":"64a",
    "addr:postcode":"n19 4nj",
    "addr:street":"Marlborough Rd",
    "iso:country":"GB",
    "sg:address":"64a Marlborough Rd",
    "sg:city":"Archway",
    "sg:classifiers":[
        {
            "category":"Professional",
            "subcategory":"Printing & Photocopies",
            "type":"Services"
        }
    ],
    "sg:phone":"+44 20 7272 1947",
    "sg:postcode":"N19 4NJ",
    "sg:province":"Greater London",
    "sg:tags":[
        "printer"
    ],
    "wof:name":"Orchard J & Co",
    "wof:placetype":"venue"
},
  "geometry": {"coordinates":[-0.126541,51.564907],"type":"Point"}
}