{
  "type": "Feature",
  "properties": {
    "addr:full":"Smithfield, Kirklinton Carlisle Cumbria CA6 6BP",
    "addr:postcode":"ca6 6bp",
    "iso:country":"GB",
    "sg:address":"Smithfield, Kirklinton",
    "sg:city":"Carlisle",
    "sg:classifiers":[
        {
            "category":"Retail",
            "subcategory":"Auto Repair",
            "type":"Services"
        }
    ],
    "sg:phone":"+44 1228 675467",
    "sg:postcode":"CA6 6BP",
    "sg:province":"Cumbria",
    "sg:tags":[
        "modification",
        "garage",
        "related"
    ],
    "wof:name":"Smithfield Garage",
    "wof:placetype":"venue"
},
  "geometry": {"coordinates":[-2.8865189552,54.9943199158],"type":"Point"}
}