{
  "type": "Feature",
  "properties": {
    "addr:full":"1 Woodend Place Aberdeen Aberdeen City AB15 6AL",
    "addr:housenumber":"1",
    "addr:postcode":"ab15 6al",
    "addr:street":"Woodend Place",
    "iso:country":"GB",
    "sg:address":"1 Woodend Place",
    "sg:city":"Aberdeen",
    "sg:classifiers":[
        {
            "category":"Building & Trades",
            "subcategory":"Construction",
            "type":"Services"
        }
    ],
    "sg:phone":"+44 1224 647771",
    "sg:postcode":"AB15 6AL",
    "sg:province":"Aberdeen City",
    "sg:tags":[
        "roofing"
    ],
    "wof:name":"William Rae (Aberdeen) Ltd.",
    "wof:placetype":"venue"
},
  "geometry": {"coordinates":[-2.161829,57.143135],"type":"Point"}
}