{
  "type": "Feature",
  "properties": {
    "addr:full":"552 Leeds Rd Bradford West Yorkshire BD3 9SB",
    "addr:housenumber":"552",
    "addr:postcode":"bd3 9sb",
    "addr:street":"Leeds Rd",
    "iso:country":"GB",
    "sg:address":"552 Leeds Rd",
    "sg:city":"Bradford",
    "sg:classifiers":[
        {
            "category":"Retail",
            "subcategory":"Auto Repair",
            "type":"Services"
        }
    ],
    "sg:postcode":"BD3 9SB",
    "sg:province":"West Yorkshire",
    "sg:tags":[
        "modification",
        "garage"
    ],
    "wof:name":"Bowling Bridge Service Station (Bradford",
    "wof:placetype":"venue"
},
  "geometry": {"coordinates":[-1.7349330187,53.7923088074],"type":"Point"}
}