{
  "type": "Feature",
  "properties": {
    "iso:country":"GB",
    "sg:address":"Jacobian House, 165 Ribbleton Avenue, Ribbleton",
    "sg:city":"Preston",
    "sg:classifiers":[
        {
            "category":"Shopping",
            "subcategory":"Computers & Home Electronics",
            "type":"Retail Goods"
        }
    ],
    "sg:postcode":"PR2 6AA",
    "sg:province":"Lancashire",
    "wof:name":"Dextrafile Computer Group",
    "wof:placetype":"venue"
},
  "geometry": {"coordinates":[-2.665023,53.774151],"type":"Point"}
}