{
  "type": "Feature",
  "properties": {
    "addr:full":"15 Darley Close Croydon Surrey CR0 7QH",
    "addr:housenumber":"15",
    "addr:postcode":"cr0 7qh",
    "addr:street":"Darley Close",
    "iso:country":"GB",
    "sg:address":"15 Darley Close",
    "sg:city":"Croydon",
    "sg:classifiers":[
        {
            "category":"Professional",
            "subcategory":"Engineering",
            "type":"Services"
        }
    ],
    "sg:postcode":"CR0 7QH",
    "sg:province":"Surrey",
    "sg:tags":[
        "contractor",
        "electrical",
        "engineer"
    ],
    "wof:name":"Seena Electrical & Building Services Ltd",
    "wof:placetype":"venue"
},
  "geometry": {"coordinates":[-0.045451,51.386185],"type":"Point"}
}