{
  "type": "Feature",
  "properties": {
    "iso:country":"GB",
    "sg:address":"Suite 12 Dennis House, Hawley Road",
    "sg:city":"Hinckley",
    "sg:classifiers":[
        {
            "category":"Professional",
            "subcategory":"Management & Consulting",
            "type":"Services"
        }
    ],
    "sg:postcode":"LE10 0PR",
    "sg:province":"Leicestershire",
    "sg:tags":[
        "consultant"
    ],
    "wof:name":"Martin Stephenson Associates Ltd.",
    "wof:placetype":"venue"
},
  "geometry": {"coordinates":[-1.374529,52.535767],"type":"Point"}
}