{
  "type": "Feature",
  "properties": {
    "addr:full":"129 Wilmslow Road Manchester Greater Manchester M14 5AW",
    "addr:housenumber":"129",
    "addr:postcode":"m14 5aw",
    "addr:street":"Wilmslow Road",
    "iso:country":"GB",
    "sg:address":"129 Wilmslow Road",
    "sg:city":"Manchester",
    "sg:classifiers":[
        {
            "category":"Fast Food",
            "type":"Food & Drink"
        }
    ],
    "sg:phone":"+44 161 256 3070",
    "sg:postcode":"M14 5AW",
    "sg:province":"Greater Manchester",
    "sg:tags":[
        "away",
        "take"
    ],
    "wof:name":"Saajan Takeaway",
    "wof:placetype":"venue"
},
  "geometry": {"coordinates":[-2.222544,53.452286],"type":"Point"}
}