{
  "type": "Feature",
  "properties": {
    "addr:full":"Grapes House, 79a High Street Esher Surrey KT10 9QA",
    "addr:housenumber":"79a",
    "addr:postcode":"kt10 9qa",
    "addr:street":"High Street",
    "iso:country":"GB",
    "sg:address":"Grapes House, 79a High Street",
    "sg:city":"Esher",
    "sg:classifiers":[
        {
            "category":"Professional",
            "subcategory":"Lawyer & Legal Services",
            "type":"Services"
        }
    ],
    "sg:phone":"+44 1372 469100",
    "sg:postcode":"KT10 9QA",
    "sg:province":"Surrey",
    "sg:tags":[
        "solicitor"
    ],
    "wof:name":"Andrew Wills & Co",
    "wof:placetype":"venue"
},
  "geometry": {"coordinates":[-0.365711,51.36887],"type":"Point"}
}