{
  "type": "Feature",
  "properties": {
    "iso:country":"GB",
    "sg:address":"236 Eastern Road",
    "sg:city":"Brighton",
    "sg:classifiers":[
        {
            "category":"Retail",
            "subcategory":"Car Wash",
            "type":"Services"
        }
    ],
    "sg:phone":"+44 1273 677477",
    "sg:postcode":"BN2 5JJ",
    "sg:province":"East Sussex",
    "sg:tags":[
        "polishing",
        "washing"
    ],
    "wof:name":"Wizard Wash",
    "wof:placetype":"venue"
},
  "geometry": {"coordinates":[-0.112098,50.81731],"type":"Point"}
}