{
  "type": "Feature",
  "properties": {
    "iso:country":"GB",
    "sg:address":"Shieldhall Works, 180 Hardgate Road",
    "sg:city":"Glasgow",
    "sg:classifiers":[
        {
            "category":"Manufacturing",
            "subcategory":"Metals",
            "type":"Manufacturing & Wholesale Goods"
        }
    ],
    "sg:phone":"+44 141 445 2898",
    "sg:postcode":"G51 4TB",
    "sg:province":"Glasgow City",
    "sg:tags":[
        "steel",
        "fabricator",
        "erectors"
    ],
    "wof:name":"Clydeside Steel Fabrications Ltd",
    "wof:placetype":"venue"
},
  "geometry": {"coordinates":[-4.34723,55.860661],"type":"Point"}
}