{
  "type": "Feature",
  "properties": {
    "addr:full":"40 Atkinson Road Sale Cheshire M33 1FY",
    "addr:housenumber":"40",
    "addr:postcode":"m33 1fy",
    "addr:street":"Atkinson Road",
    "iso:country":"GB",
    "sg:address":"40 Atkinson Road",
    "sg:city":"Sale",
    "sg:classifiers":[
        {
            "category":"Building & Trades",
            "subcategory":"Construction",
            "type":"Services"
        }
    ],
    "sg:postcode":"M33 1FY",
    "sg:province":"Cheshire",
    "sg:tags":[
        "builder"
    ],
    "wof:name":"A P B Services",
    "wof:placetype":"venue"
},
  "geometry": {"coordinates":[-2.3263809681,53.4289398193],"type":"Point"}
}