{
  "type": "Feature",
  "properties": {
    "iso:country":"GB",
    "sg:address":"New La",
    "sg:city":"Preston",
    "sg:classifiers":[
        {
            "category":"Building & Trades",
            "subcategory":"Equipment Rental",
            "type":"Services"
        }
    ],
    "sg:phone":"+44 1995 640406",
    "sg:postcode":"PR3 0GB",
    "sg:province":"Lancashire",
    "sg:tags":[
        "plant",
        "machinery"
    ],
    "wof:name":"Town Croft Farm",
    "wof:placetype":"venue"
},
  "geometry": {"coordinates":[-2.746943,53.869095],"type":"Point"}
}