{
  "type": "Feature",
  "properties": {
    "iso:country":"GB",
    "sg:address":"Chevening Road",
    "sg:city":"London",
    "sg:classifiers":[
        {
            "category":"Organizations",
            "subcategory":"Non-profit Organization",
            "type":"Services"
        }
    ],
    "sg:phone":"+44 20 7372 4049",
    "sg:postcode":"NW6 6TN",
    "sg:province":"Greater London",
    "sg:tags":[
        "organisation",
        "voluntary",
        "charity"
    ],
    "wof:name":"Al-Khoei Foundation",
    "wof:placetype":"venue"
},
  "geometry": {"coordinates":[-0.209854,51.539867],"type":"Point"}
}