{
  "type": "Feature",
  "properties": {
    "addr:full":"Buckland Road Reigate Surrey RH2 9RD",
    "addr:postcode":"rh2 9rd",
    "addr:street":"Buckland Road",
    "iso:country":"GB",
    "sg:address":"Buckland Road",
    "sg:city":"Reigate",
    "sg:classifiers":[
        {
            "category":"Manufacturing",
            "subcategory":"Petroleum Products",
            "type":"Manufacturing & Wholesale Goods"
        }
    ],
    "sg:phone":"+44 1737 226445",
    "sg:postcode":"RH2 9RD",
    "sg:province":"Surrey",
    "sg:tags":[
        "double",
        "glazing"
    ],
    "wof:name":"First Windows",
    "wof:placetype":"venue"
},
  "geometry": {"coordinates":[-0.231069,51.241131],"type":"Point"}
}