{
  "type": "Feature",
  "properties": {
    "addr:full":"The By-pass Romsey Hampshire SO51 8HL",
    "addr:postcode":"so51 8hl",
    "addr:street":"The",
    "iso:country":"GB",
    "sg:address":"The By-pass",
    "sg:city":"Romsey",
    "sg:classifiers":[
        {
            "category":"Autos & Motor Vehicles",
            "subcategory":"Automobile Sales",
            "type":"Retail Goods"
        }
    ],
    "sg:phone":"+44 1794 830033",
    "sg:postcode":"SO51 8HL",
    "sg:province":"Hampshire",
    "sg:tags":[
        "car"
    ],
    "wof:name":"Broadlands Motors (Romsey) Ltd",
    "wof:placetype":"venue"
},
  "geometry": {"coordinates":[-1.495391,50.988583],"type":"Point"}
}