{
  "type": "Feature",
  "properties": {
    "iso:country":"GB",
    "sg:address":"42 Cambridge Road",
    "sg:city":"Leicester",
    "sg:classifiers":[
        {
            "category":"Manufacturing",
            "subcategory":"Chemicals & Compounds",
            "type":"Manufacturing & Wholesale Goods"
        },
        {
            "category":"Retail",
            "subcategory":"Auto Repair",
            "type":"Services"
        }
    ],
    "sg:postcode":"LE9 5SH",
    "sg:province":"Leicestershire",
    "sg:tags":[
        "modification",
        "abrasive",
        "product",
        "cleaning",
        "garage"
    ],
    "wof:name":"Cambridge Road Garage",
    "wof:placetype":"venue"
},
  "geometry": {"coordinates":[-1.1523660421,52.6271057129],"type":"Point"}
}