{
  "type": "Feature",
  "properties": {
    "iso:country":"GB",
    "sg:address":"Longwood Road, Brookhill Industrial Estate, Pinxton",
    "sg:city":"Nottingham",
    "sg:classifiers":[
        {
            "category":"Autos & Motor Vehicles",
            "subcategory":"Auto Supplies",
            "type":"Retail Goods"
        }
    ],
    "sg:phone":"+44 1773 581458",
    "sg:postcode":"NG16 6NT",
    "sg:province":"Derbyshire",
    "sg:tags":[
        "windscreen"
    ],
    "wof:name":"Charles Pugh (Holdings) Ltd.",
    "wof:placetype":"venue"
},
  "geometry": {"coordinates":[-1.317955,53.095806],"type":"Point"}
}