{
  "type": "Feature",
  "properties": {
    "addr:full":"Ventnor Rd Portland Dorset DT5 1JE",
    "addr:postcode":"dt5 1je",
    "addr:street":"Ventnor Rd",
    "iso:country":"GB",
    "sg:address":"Ventnor Rd",
    "sg:city":"Portland",
    "sg:classifiers":[
        {
            "category":"Place Of Worship",
            "type":"Public Place"
        },
        {
            "category":"Organizations",
            "subcategory":"Non-profit Organization",
            "type":"Services"
        }
    ],
    "sg:phone":"+44 1305 820103",
    "sg:postcode":"DT5 1JE",
    "sg:province":"Dorset",
    "sg:tags":[
        "charitable",
        "organisation",
        "charity"
    ],
    "wof:name":"ST JOHNS VICARAGE",
    "wof:placetype":"venue"
},
  "geometry": {"coordinates":[-2.4359691143,50.5469017029],"type":"Point"}
}