{
  "type": "Feature",
  "properties": {
    "iso:country":"GB",
    "sg:address":"The School House",
    "sg:city":"Edinburgh",
    "sg:classifiers":[
        {
            "category":"Professional",
            "type":"Services"
        }
    ],
    "sg:phone":"+44 131 555 4425",
    "sg:postcode":"EH6 8BR",
    "sg:province":"City of Edinburgh",
    "sg:tags":[
        "archaeologist"
    ],
    "wof:name":"A O C (Scotland) Ltd.",
    "wof:placetype":"venue"
},
  "geometry": {"coordinates":[-3.16636,55.968361],"type":"Point"}
}