{
  "type": "Feature",
  "properties": {
    "addr:full":"Courtside House, Telford Square Telford Shropshire TF3 4EQ",
    "addr:postcode":"tf3 4eq",
    "addr:street":"Telford Square",
    "iso:country":"GB",
    "sg:address":"Courtside House, Telford Square",
    "sg:city":"Telford",
    "sg:classifiers":[
        {
            "category":"Organizations",
            "subcategory":"Community Association",
            "type":"Services"
        }
    ],
    "sg:phone":"+44 1952 293777",
    "sg:postcode":"TF3 4EQ",
    "sg:province":"Shropshire",
    "sg:tags":[
        "society",
        "housing"
    ],
    "wof:name":"Bournville Village Trust",
    "wof:placetype":"venue"
},
  "geometry": {"coordinates":[-2.524074,52.692871],"type":"Point"}
}