{
  "type": "Feature",
  "properties": {
    "addr:full":"The Avenue, 250 Ayr Road, Newton Mearns Glasgow East Ayrshire G77 6AA",
    "addr:housenumber":"250",
    "addr:postcode":"g77 6aa",
    "addr:street":"Ayr Road",
    "iso:country":"GB",
    "sg:address":"The Avenue, 250 Ayr Road, Newton Mearns",
    "sg:city":"Glasgow",
    "sg:classifiers":[
        {
            "category":"Shopping",
            "subcategory":"Department Store",
            "type":"Retail Goods"
        }
    ],
    "sg:phone":"+44 141 639 9536",
    "sg:postcode":"G77 6AA",
    "sg:province":"East Ayrshire",
    "wof:name":"Marks & Spencer Plc",
    "wof:placetype":"venue"
},
  "geometry": {"coordinates":[-4.3301959038,55.7747344971],"type":"Point"}
}