{
  "type": "Feature",
  "properties": {
    "addr:full":"184 High Street Scunthorpe Lincolnshire DN15 6EA",
    "addr:housenumber":"184",
    "addr:postcode":"dn15 6ea",
    "addr:street":"High Street",
    "iso:country":"GB",
    "sg:address":"184 High Street",
    "sg:city":"Scunthorpe",
    "sg:classifiers":[
        {
            "category":"Real Estate",
            "subcategory":"Surveying",
            "type":"Services"
        }
    ],
    "sg:postcode":"DN15 6EA",
    "sg:province":"Lincolnshire",
    "sg:tags":[
        "surveyor",
        "quantity"
    ],
    "wof:name":"Gardiner & Theobald",
    "wof:placetype":"venue"
},
  "geometry": {"coordinates":[-0.652891,53.59111],"type":"Point"}
}