{
  "type": "Feature",
  "properties": {
    "addr:full":"Farrell Court, The Laurels, High Road Dartford Kent DA2 7DT",
    "addr:postcode":"da2 7dt",
    "addr:street":"Farrell Court;High Road",
    "iso:country":"GB",
    "sg:address":"Farrell Court, The Laurels, High Road",
    "sg:city":"Dartford",
    "sg:classifiers":[
        {
            "category":"Social Services",
            "subcategory":"Retirement Home",
            "type":"Services"
        },
        {
            "category":"Government",
            "subcategory":"Office",
            "type":"Public Place"
        }
    ],
    "sg:phone":"+44 1322 222778",
    "sg:postcode":"DA2 7DT",
    "sg:province":"Kent",
    "sg:tags":[
        "accomodation",
        "housing",
        "local",
        "sheltered"
    ],
    "wof:name":"DARTFORD BOROUGH COUNCIL",
    "wof:placetype":"venue"
},
  "geometry": {"coordinates":[0.2061900049,51.4267692566],"type":"Point"}
}