{
  "type": "Feature",
  "properties": {
    "addr:full":"3 York Avenue East Cowes Isle of Wight PO32 6QY",
    "addr:housenumber":"3",
    "addr:postcode":"po32 6qy",
    "addr:street":"York Avenue",
    "iso:country":"GB",
    "sg:address":"3 York Avenue",
    "sg:city":"East Cowes",
    "sg:classifiers":[
        {
            "category":"Food & Beverages",
            "subcategory":"Candy",
            "type":"Retail Goods"
        }
    ],
    "sg:postcode":"PO32 6QY",
    "sg:province":"Isle of Wight",
    "sg:tags":[
        "confectioner"
    ],
    "wof:name":"Geraldines",
    "wof:placetype":"venue"
},
  "geometry": {"coordinates":[-1.2892600298,50.7580909729],"type":"Point"}
}