{
  "type": "Feature",
  "properties": {
    "iso:country":"GB",
    "sg:address":"Elderpark Workspace, Elderpark Street",
    "sg:city":"Glasgow",
    "sg:classifiers":[
        {
            "category":"Professional",
            "subcategory":"Art Services",
            "type":"Services"
        }
    ],
    "sg:phone":"+44 141 440 1146",
    "sg:postcode":"G51 3TR",
    "sg:province":"Glasgow City",
    "sg:tags":[
        "consultant",
        "design"
    ],
    "wof:name":"Hyland Freelance Design Services",
    "wof:placetype":"venue"
},
  "geometry": {"coordinates":[-4.32131,55.860611],"type":"Point"}
}