{
  "type": "Feature",
  "properties": {
    "iso:country":"GB",
    "sg:address":"Unit 4c, 14 Milton Street",
    "sg:city":"Dundee",
    "sg:classifiers":[
        {
            "category":"Retail",
            "subcategory":"Auto Repair",
            "type":"Services"
        }
    ],
    "sg:phone":"+44 1382 832075",
    "sg:postcode":"DD3 6QS",
    "sg:province":"Dundee City",
    "sg:tags":[
        "modification",
        "garage"
    ],
    "wof:name":"Milton Street Motors",
    "wof:placetype":"venue"
},
  "geometry": {"coordinates":[-2.982618,56.473648],"type":"Point"}
}