{
  "type": "Feature",
  "properties": {
    "addr:full":"Bernard Becker Studios, 1 Jerusalem Passage Clerkenwell Greater London EC1V 4JP",
    "addr:housenumber":"1",
    "addr:postcode":"ec1v 4jp",
    "addr:street":"Jerusalem Passage",
    "iso:country":"GB",
    "sg:address":"Bernard Becker Studios, 1 Jerusalem Passage",
    "sg:city":"Clerkenwell",
    "sg:classifiers":[
        {
            "category":"Manufacturing",
            "subcategory":"Glass & Minerals",
            "type":"Manufacturing & Wholesale Goods"
        }
    ],
    "sg:phone":"+44 20 7336 8780",
    "sg:postcode":"EC1V 4JP",
    "sg:province":"Greater London",
    "sg:tags":[
        "mnfrs",
        "fibre"
    ],
    "wof:name":"Tony Sandles",
    "wof:placetype":"venue"
},
  "geometry": {"coordinates":[-0.10369,51.523048],"type":"Point"}
}