{
  "type": "Feature",
  "properties": {
    "iso:country":"GB",
    "sg:address":"Carlton House, Livingstone Road",
    "sg:city":"Bilston",
    "sg:classifiers":[
        {
            "category":"Professional",
            "subcategory":"Testing Lab",
            "type":"Services"
        }
    ],
    "sg:phone":"+44 1902 402402",
    "sg:postcode":"WV14 0QZ",
    "sg:province":"West Midlands",
    "sg:tags":[
        "laboratory"
    ],
    "wof:name":"Scientific & Chemical Supplies Ltd.",
    "wof:placetype":"venue"
},
  "geometry": {"coordinates":[-2.0912489891,52.5653114319],"type":"Point"}
}