{
  "type": "Feature",
  "properties": {
    "addr:full":"174 Bellegrove Rd Welling Kent DA16 3RE",
    "addr:housenumber":"174",
    "addr:postcode":"da16 3re",
    "addr:street":"Bellegrove Rd",
    "iso:country":"GB",
    "sg:address":"174 Bellegrove Rd",
    "sg:city":"Welling",
    "sg:classifiers":[
        {
            "category":"Place Of Worship",
            "type":"Public Place"
        }
    ],
    "sg:phone":"+44 20 8303 1452",
    "sg:postcode":"DA16 3RE",
    "sg:province":"Kent",
    "wof:name":"Welling Methodist Church",
    "wof:placetype":"venue"
},
  "geometry": {"coordinates":[0.0952100009,51.4645690918],"type":"Point"}
}