{
  "type": "Feature",
  "properties": {
    "addr:full":"Unit B, Extension Road, Caxton Hill Hertford Hertfordshire SG13 7LY",
    "addr:postcode":"sg13 7ly",
    "addr:street":"Extension Road",
    "iso:country":"GB",
    "sg:address":"Unit B, Extension Road, Caxton Hill",
    "sg:city":"Hertford",
    "sg:classifiers":[
        {
            "category":"Home & Garden",
            "subcategory":"Furniture",
            "type":"Retail Goods"
        }
    ],
    "sg:postcode":"SG13 7LY",
    "sg:province":"Hertfordshire",
    "wof:name":"Tenbyfield Ltd.",
    "wof:placetype":"venue"
},
  "geometry": {"coordinates":[-0.0459249988,51.7829170227],"type":"Point"}
}