{
  "type": "Feature",
  "properties": {
    "iso:country":"GB",
    "sg:address":"Wispington House, Worster Road, Cookham",
    "sg:city":"Maidenhead",
    "sg:classifiers":[
        {
            "category":"Health Services",
            "subcategory":"Health Practitioner",
            "type":"Services"
        }
    ],
    "sg:phone":"+44 1628 520221",
    "sg:postcode":"SL6 9JG",
    "sg:province":"Berkshire",
    "sg:tags":[
        "psychotherapist"
    ],
    "wof:name":"Anita Sharples",
    "wof:placetype":"venue"
},
  "geometry": {"coordinates":[-0.727914,51.556034],"type":"Point"}
}