{
  "type": "Feature",
  "properties": {
    "iso:country":"GB",
    "sg:address":"45 King George V Avenue",
    "sg:city":"King's Lynn",
    "sg:classifiers":[
        {
            "category":"Building & Trades",
            "subcategory":"Construction",
            "type":"Services"
        }
    ],
    "sg:phone":"+44 1553 773100",
    "sg:postcode":"PE30 2QE",
    "sg:province":"Norfolk",
    "sg:tags":[
        "builder"
    ],
    "wof:name":"Michael B Evetts",
    "wof:placetype":"venue"
},
  "geometry": {"coordinates":[0.4120010138,52.7543487549],"type":"Point"}
}