{
  "type": "Feature",
  "properties": {
    "addr:full":"Unit 8 Crown Walk, West St Bourne Lincolnshire PE10 9NE",
    "addr:housenumber":"unit 8",
    "addr:postcode":"pe10 9ne",
    "addr:street":"Crown Walk West St",
    "iso:country":"GB",
    "sg:address":"Unit 8 Crown Walk, West St",
    "sg:city":"Bourne",
    "sg:classifiers":[
        {
            "category":"Shopping",
            "subcategory":"Gifts & Souvenirs",
            "type":"Retail Goods"
        }
    ],
    "sg:postcode":"PE10 9NE",
    "sg:province":"Lincolnshire",
    "sg:tags":[
        "shop"
    ],
    "wof:name":"Gibson,Glen,",
    "wof:placetype":"venue"
},
  "geometry": {"coordinates":[-0.3770880103,52.7691955566],"type":"Point"}
}