{
  "type": "Feature",
  "properties": {
    "addr:full":"331 Upper Town Street, Bramley Leeds West Yorkshire LS13 3JX",
    "addr:housenumber":"331",
    "addr:postcode":"ls13 3jx",
    "addr:street":"Upper Town Street",
    "iso:country":"GB",
    "sg:address":"331 Upper Town Street, Bramley",
    "sg:city":"Leeds",
    "sg:classifiers":[
        {
            "category":"Organizations",
            "subcategory":"Non-profit Organization",
            "type":"Services"
        }
    ],
    "sg:phone":"+44 113 236 1644",
    "sg:postcode":"LS13 3JX",
    "sg:province":"West Yorkshire",
    "sg:tags":[
        "charitable",
        "organisation",
        "voluntary",
        "charity"
    ],
    "wof:name":"Bramley Elderly Action",
    "wof:placetype":"venue"
},
  "geometry": {"coordinates":[-1.630076,53.813133],"type":"Point"}
}