{
  "type": "Feature",
  "properties": {
    "addr:full":"Farndon Street Wrexham Wrexham LL13 8DE",
    "addr:postcode":"ll13 8de",
    "addr:street":"Farndon Street",
    "iso:country":"GB",
    "sg:address":"Farndon Street",
    "sg:city":"Wrexham",
    "sg:classifiers":[
        {
            "category":"Restaurant",
            "type":"Food & Drink"
        }
    ],
    "sg:phone":"+44 1978 310700",
    "sg:postcode":"LL13 8DE",
    "sg:province":"Wrexham",
    "sg:tags":[
        "-",
        "chinese"
    ],
    "wof:name":"Sleepy Panda Restaurant",
    "wof:placetype":"venue"
},
  "geometry": {"coordinates":[-2.9885089397,53.0459785461],"type":"Point"}
}