{
  "type": "Feature",
  "properties": {
    "addr:full":"31 Argyle Place Edinburgh City of Edinburgh EH9 1LA",
    "addr:housenumber":"31",
    "addr:postcode":"eh9 1la",
    "addr:street":"Argyle Place Edinburgh",
    "iso:country":"GB",
    "sg:address":"31 Argyle Place",
    "sg:city":"Edinburgh",
    "sg:classifiers":[
        {
            "category":"Manufacturing",
            "subcategory":"Textiles",
            "type":"Manufacturing & Wholesale Goods"
        }
    ],
    "sg:postcode":"EH9 1LA",
    "sg:province":"City of Edinburgh",
    "sg:tags":[
        "merchant",
        "agent"
    ],
    "wof:name":"David Black & Co. (Deblax) Ltd.",
    "wof:placetype":"venue"
},
  "geometry": {"coordinates":[-3.191595,55.93898],"type":"Point"}
}