{
  "type": "Feature",
  "properties": {
    "addr:full":"277 Ashingdon Rd Rochford Essex SS4 1UA",
    "addr:housenumber":"277",
    "addr:postcode":"ss4 1ua",
    "addr:street":"Ashingdon Rd",
    "iso:country":"GB",
    "sg:address":"277 Ashingdon Rd",
    "sg:city":"Rochford",
    "sg:classifiers":[
        {
            "category":"Shopping",
            "subcategory":"Shoes",
            "type":"Retail Goods"
        }
    ],
    "sg:postcode":"SS4 1UA",
    "sg:province":"Essex",
    "sg:tags":[
        "shop"
    ],
    "wof:name":"George's Footwear",
    "wof:placetype":"venue"
},
  "geometry": {"coordinates":[0.6970329881,51.5954055786],"type":"Point"}
}