{
  "type": "Feature",
  "properties": {
    "addr:full":"Pont Hafren, Longbridge Street Newtown Powys SY16 2DY",
    "addr:postcode":"sy16 2dy",
    "addr:street":"Pont Hafren Longbridge Street",
    "iso:country":"GB",
    "sg:address":"Pont Hafren, Longbridge Street",
    "sg:city":"Newtown",
    "sg:classifiers":[
        {
            "category":"Organizations",
            "subcategory":"Non-profit Organization",
            "type":"Services"
        }
    ],
    "sg:phone":"+44 1686 621586",
    "sg:postcode":"SY16 2DY",
    "sg:province":"Powys",
    "sg:tags":[
        "organisation",
        "voluntary",
        "charity"
    ],
    "wof:name":"Pont Hafran Drop in Centre Association",
    "wof:placetype":"venue"
},
  "geometry": {"coordinates":[-3.320039,52.517895],"type":"Point"}
}