{
  "type": "Feature",
  "properties": {
    "addr:full":"Oak Road, Wrexham Industrial Estate Wrexham Wrexham LL13 9RG",
    "addr:postcode":"ll13 9rg",
    "addr:street":"Oak Road;Industrial Estate",
    "iso:country":"GB",
    "sg:address":"Oak Road, Wrexham Industrial Estate",
    "sg:city":"Wrexham",
    "sg:classifiers":[
        {
            "category":"Retail",
            "subcategory":"Auto Repair",
            "type":"Services"
        }
    ],
    "sg:phone":"+44 1978 660472",
    "sg:postcode":"LL13 9RG",
    "sg:province":"Wrexham",
    "sg:tags":[
        "body",
        "garage",
        "modification",
        "car"
    ],
    "wof:name":"D K Motor Services",
    "wof:placetype":"venue"
},
  "geometry": {"coordinates":[-2.9064719677,53.0356178284],"type":"Point"}
}