{
  "type": "Feature",
  "properties": {
    "iso:country":"GB",
    "sg:address":"38 Wellington Road",
    "sg:city":"Newport",
    "sg:classifiers":[
        {
            "category":"Home & Garden",
            "subcategory":"Building Materials",
            "type":"Retail Goods"
        },
        {
            "category":"Building & Trades",
            "subcategory":"Construction",
            "type":"Services"
        }
    ],
    "sg:postcode":"TF10 7HD",
    "sg:province":"Shropshire",
    "sg:tags":[
        "dry",
        "plasterers",
        "installers",
        "lining",
        "insulation",
        "screeders"
    ],
    "wof:name":"J A Good Plastering Contractors",
    "wof:placetype":"venue"
},
  "geometry": {"coordinates":[-2.3789160252,52.7653656006],"type":"Point"}
}