{
  "type": "Feature",
  "properties": {
    "addr:full":"Windsor House, Trent Valley Road Lichfield Staffordshire WS13 6EU",
    "addr:postcode":"ws13 6eu",
    "addr:street":"Trent Valley Road",
    "iso:country":"GB",
    "sg:address":"Windsor House, Trent Valley Road",
    "sg:city":"Lichfield",
    "sg:classifiers":[
        {
            "category":"Real Estate",
            "subcategory":"Real Estate Agent",
            "type":"Services"
        }
    ],
    "sg:phone":"+44 1543 256023",
    "sg:postcode":"WS13 6EU",
    "sg:province":"Staffordshire",
    "wof:name":"Birchforest Ltd.",
    "wof:placetype":"venue"
},
  "geometry": {"coordinates":[-1.8061840534,52.6870613098],"type":"Point"}
}