{
  "type": "Feature",
  "properties": {
    "addr:full":"389 Shenley Rd Borehamwood Hertfordshire WD6 1TW",
    "addr:housenumber":"389",
    "addr:postcode":"wd6 1tw",
    "addr:street":"Shenley Rd",
    "iso:country":"GB",
    "sg:address":"389 Shenley Rd",
    "sg:city":"Borehamwood",
    "sg:classifiers":[
        {
            "category":"Bus Charters",
            "type":"Transportation"
        }
    ],
    "sg:phone":"+44 20 8953 0224",
    "sg:postcode":"WD6 1TW",
    "sg:province":"Hertfordshire",
    "sg:tags":[
        "hire",
        "coach"
    ],
    "wof:name":"Travel O'Connor Coaches Ltd",
    "wof:placetype":"venue"
},
  "geometry": {"coordinates":[-0.266068995,51.6652488708],"type":"Point"}
}