{
  "type": "Feature",
  "properties": {
    "iso:country":"GB",
    "sg:address":"1 Loudoun Avenue",
    "sg:city":"Galston",
    "sg:classifiers":[
        {
            "category":"Freight",
            "type":"Transportation"
        }
    ],
    "sg:phone":"+44 1563 539444",
    "sg:postcode":"KA4 8DB",
    "sg:province":"East Ayrshire",
    "sg:tags":[
        "haulage",
        "road"
    ],
    "wof:name":"Mainline Taxis",
    "wof:placetype":"venue"
},
  "geometry": {"coordinates":[-4.3914070129,55.5979156494],"type":"Point"}
}