{
  "type": "Feature",
  "properties": {
    "addr:full":"Unit 12.target, Business Centre, Bircholt Rd, Parkwood Maidstone Kent ME15 9YY",
    "addr:postcode":"me15 9yy",
    "addr:street":"Bircholt Rd",
    "iso:country":"GB",
    "sg:address":"Unit 12.target, Business Centre, Bircholt Rd, Parkwood",
    "sg:city":"Maidstone",
    "sg:classifiers":[
        {
            "category":"Professional",
            "subcategory":"Business Services",
            "type":"Services"
        }
    ],
    "sg:phone":"+44 1622 755799",
    "sg:postcode":"ME15 9YY",
    "sg:province":"Kent",
    "sg:tags":[
        "shop",
        "cleaning"
    ],
    "wof:name":"M & J Cleaning Contractors Ltd",
    "wof:placetype":"venue"
},
  "geometry": {"coordinates":[0.5612000227,51.2349700928],"type":"Point"}
}