{
  "type": "Feature",
  "properties": {
    "iso:country":"GB",
    "sg:address":"Trapdoor Farm, East Orchard",
    "sg:city":"Shaftesbury",
    "sg:classifiers":[
        {
            "category":"Farming",
            "subcategory":"Dairy Farm",
            "type":"Manufacturing & Wholesale Goods"
        }
    ],
    "sg:phone":"+44 1747 811419",
    "sg:postcode":"SP7 0LG",
    "sg:province":"Dorset",
    "wof:name":"J H Bush",
    "wof:placetype":"venue"
},
  "geometry": {"coordinates":[-2.1871240139,51.0057640076],"type":"Point"}
}