{
  "type": "Feature",
  "properties": {
    "iso:country":"GB",
    "sg:address":"210 Pineapple Rd",
    "sg:city":"Birmingham",
    "sg:classifiers":[
        {
            "category":"Organizations",
            "subcategory":"Non-profit Organization",
            "type":"Services"
        }
    ],
    "sg:phone":"+44 121 444 6450",
    "sg:postcode":"B30 2TY",
    "sg:province":"West Midlands",
    "sg:tags":[
        "organisation",
        "voluntary",
        "charity"
    ],
    "wof:name":"Allergy Induced Autism",
    "wof:placetype":"venue"
},
  "geometry": {"coordinates":[-1.90968,52.428394],"type":"Point"}
}