{
  "type": "Feature",
  "properties": {
    "iso:country":"GB",
    "sg:address":"Bigdale Dr",
    "sg:city":"Liverpool",
    "sg:classifiers":[
        {
            "category":"Place Of Worship",
            "type":"Public Place"
        }
    ],
    "sg:phone":"+44 151 292 3846",
    "sg:postcode":"L33 6XG",
    "sg:province":"Lancashire",
    "wof:name":"Northwood Chapel",
    "wof:placetype":"venue"
},
  "geometry": {"coordinates":[-2.8740589619,53.4884986877],"type":"Point"}
}