{
  "type": "Feature",
  "properties": {
    "addr:full":"67 Chiltern Street London Greater London W1U 6NF",
    "addr:housenumber":"67",
    "addr:postcode":"w1u 6nf",
    "addr:street":"Chiltern Street",
    "iso:country":"GB",
    "sg:address":"67 Chiltern Street",
    "sg:city":"London",
    "sg:classifiers":[
        {
            "category":"Shopping",
            "subcategory":"News",
            "type":"Retail Goods"
        }
    ],
    "sg:phone":"+44 20 7935 0014",
    "sg:postcode":"W1U 6NF",
    "sg:province":"Greater London",
    "sg:tags":[
        "newsagent"
    ],
    "wof:name":"Fables News",
    "wof:placetype":"venue"
},
  "geometry": {"coordinates":[-0.1556389928,51.520488739],"type":"Point"}
}