{
  "type": "Feature",
  "properties": {
    "addr:full":"74 High St Alfreton Derbyshire DE55 5NX",
    "addr:housenumber":"74",
    "addr:postcode":"de55 5nx",
    "addr:street":"High St",
    "iso:country":"GB",
    "sg:address":"74 High St",
    "sg:city":"Alfreton",
    "sg:classifiers":[
        {
            "category":"Shopping",
            "subcategory":"News",
            "type":"Retail Goods"
        }
    ],
    "sg:phone":"+44 1773 590884",
    "sg:postcode":"DE55 5NX",
    "sg:province":"Derbyshire",
    "sg:tags":[
        "newsagent"
    ],
    "wof:name":"D J Hollis",
    "wof:placetype":"venue"
},
  "geometry": {"coordinates":[-1.345554,53.141659],"type":"Point"}
}