{
  "type": "Feature",
  "properties": {
    "addr:full":"Chard Street Axminster Devon EX13 5EA",
    "addr:postcode":"ex13 5ea",
    "addr:street":"Chard Street",
    "iso:country":"GB",
    "sg:address":"Chard Street",
    "sg:city":"Axminster",
    "sg:classifiers":[
        {
            "category":"Community Center",
            "type":"Public Place"
        },
        {
            "category":"Government",
            "subcategory":"Office",
            "type":"Public Place"
        }
    ],
    "sg:phone":"+44 1297 35235",
    "sg:postcode":"EX13 5EA",
    "sg:province":"Devon",
    "sg:tags":[
        "recreation",
        "local",
        "leisure",
        "centre"
    ],
    "wof:name":"Axe Valley Sports Centre",
    "wof:placetype":"venue"
},
  "geometry": {"coordinates":[-2.995974,50.783436],"type":"Point"}
}