{
  "type": "Feature",
  "properties": {
    "addr:full":"24 Upper Tachbrook Street London Greater London SW1V 1SW",
    "addr:housenumber":"24",
    "addr:postcode":"sw1v 1sw",
    "addr:street":"Upper Tachbrook Street",
    "iso:country":"GB",
    "sg:address":"24 Upper Tachbrook Street",
    "sg:city":"London",
    "sg:classifiers":[
        {
            "category":"Shopping",
            "subcategory":"Pharmacy",
            "type":"Retail Goods"
        }
    ],
    "sg:phone":"+44 20 7834 6182",
    "sg:postcode":"SW1V 1SW",
    "sg:province":"Greater London",
    "sg:tags":[
        "pharmacist",
        "chemist"
    ],
    "wof:name":"S S Basra Pharmacy",
    "wof:placetype":"venue"
},
  "geometry": {"coordinates":[-0.139449,51.492874],"type":"Point"}
}