{
  "type": "Feature",
  "properties": {
    "addr:full":"Sunnymead Business Centre, 1 Bromley Lane Chislehurst Kent BR7 6LH",
    "addr:housenumber":"1",
    "addr:postcode":"br7 6lh",
    "addr:street":"Bromley Lane",
    "iso:country":"GB",
    "sg:address":"Sunnymead Business Centre, 1 Bromley Lane",
    "sg:city":"Chislehurst",
    "sg:classifiers":[
        {
            "category":"Home & Garden",
            "subcategory":"Building Materials",
            "type":"Retail Goods"
        }
    ],
    "sg:phone":"+44 20 8467 4222",
    "sg:postcode":"BR7 6LH",
    "sg:province":"Kent",
    "sg:tags":[
        "equipment",
        "disability"
    ],
    "wof:name":"Concept Systems",
    "wof:placetype":"venue"
},
  "geometry": {"coordinates":[0.06639,51.419285],"type":"Point"}
}