{
  "type": "Feature",
  "properties": {
    "iso:country":"GB",
    "sg:address":"12 Prince Street",
    "sg:city":"Bridlington",
    "sg:classifiers":[
        {
            "category":"Personal",
            "subcategory":"Psychics & Astrologers",
            "type":"Services"
        }
    ],
    "sg:phone":"+44 1262 401121",
    "sg:postcode":"YO15 2NW",
    "sg:province":"East Riding of Yorkshire",
    "sg:tags":[
        "clairvoyant",
        "palmist"
    ],
    "wof:name":"Indian Palmist Ajmeri",
    "wof:placetype":"venue"
},
  "geometry": {"coordinates":[-0.187399,54.08749],"type":"Point"}
}