{
  "type": "Feature",
  "properties": {
    "addr:full":"26 Tinmans Grn, Redbrook Monmouth Gloucestershire NP25 4NB",
    "addr:housenumber":"26",
    "addr:postcode":"np25 4nb",
    "addr:street":"Tinmans Grn Redbrook",
    "iso:country":"GB",
    "sg:address":"26 Tinmans Grn, Redbrook",
    "sg:city":"Monmouth",
    "sg:classifiers":[
        {
            "category":"Professional",
            "subcategory":"Management & Consulting",
            "type":"Services"
        }
    ],
    "sg:phone":"+44 1600 715517",
    "sg:postcode":"NP25 4NB",
    "sg:province":"Gloucestershire",
    "sg:tags":[
        "consultant",
        "training"
    ],
    "wof:name":"The Worth Consultancy Co. Ltd.",
    "wof:placetype":"venue"
},
  "geometry": {"coordinates":[-2.6700348854,51.7944831848],"type":"Point"}
}