{
  "type": "Feature",
  "properties": {
    "addr:full":"Wymering Manor, Old Wymering Lane Portsmouth Hampshire PO6 3NL",
    "addr:housenumber":"wymering",
    "addr:postcode":"hampshire po6 3nl",
    "addr:street":"Manor Old Wymering Lane",
    "iso:country":"GB",
    "sg:address":"Wymering Manor, Old Wymering Lane",
    "sg:city":"Portsmouth",
    "sg:classifiers":[
        {
            "category":"Travel",
            "subcategory":"Hostel",
            "type":"Entertainment"
        }
    ],
    "sg:phone":"+44 23 9237 5661",
    "sg:postcode":"PO6 3NL",
    "sg:province":"Hampshire",
    "sg:tags":[
        "youth"
    ],
    "wof:name":"Youth Hostels Association",
    "wof:placetype":"venue"
},
  "geometry": {"coordinates":[-1.0783929825,50.846321106],"type":"Point"}
}