{
  "type": "Feature",
  "properties": {
    "addr:full":"Hubbards Lane, Linton Maidstone Kent ME17 4HX",
    "addr:postcode":"me17 4hx",
    "addr:street":"Hubbards Lane",
    "iso:country":"GB",
    "sg:address":"Hubbards Lane, Linton",
    "sg:city":"Maidstone",
    "sg:classifiers":[
        {
            "category":"Education",
            "subcategory":"University",
            "type":"Public Place"
        },
        {
            "category":"Education",
            "subcategory":"School",
            "type":"Public Place"
        }
    ],
    "sg:phone":"+44 1622 743152",
    "sg:postcode":"ME17 4HX",
    "sg:province":"Kent",
    "sg:tags":[
        "college",
        "adult"
    ],
    "wof:name":"The Cornwallis School",
    "wof:placetype":"venue"
},
  "geometry": {"coordinates":[0.5112460256,51.2179679871],"type":"Point"}
}