{
  "type": "Feature",
  "properties": {
    "iso:country":"GB",
    "sg:address":"122 St James Street",
    "sg:city":"Brighton",
    "sg:classifiers":[
        {
            "category":"Health Services",
            "subcategory":"Health Practitioner",
            "type":"Services"
        }
    ],
    "sg:phone":"+44 1273 699852",
    "sg:postcode":"BN2 1TH",
    "sg:province":"East Sussex",
    "sg:tags":[
        "acupuncture"
    ],
    "wof:name":"Chinese Medicine & Acupuncture Centre",
    "wof:placetype":"venue"
},
  "geometry": {"coordinates":[-0.1358820051,50.8209342957],"type":"Point"}
}