{
  "type": "Feature",
  "properties": {
    "iso:country":"GB",
    "sg:address":"The Cottage, Preston Lodge Farm, Preston Deanery",
    "sg:city":"Northampton",
    "sg:classifiers":[
        {
            "category":"Farming",
            "subcategory":"Livestock Farm",
            "type":"Manufacturing & Wholesale Goods"
        },
        {
            "category":"Farming",
            "subcategory":"Farm",
            "type":"Manufacturing & Wholesale Goods"
        }
    ],
    "sg:phone":"+44 1604 870246",
    "sg:postcode":"NN7 2DS",
    "sg:province":"Buckinghamshire",
    "sg:tags":[
        "mixed",
        "crop",
        "others"
    ],
    "wof:name":"Robert Norman & Margaret Ann Borwick",
    "wof:placetype":"venue"
},
  "geometry": {"coordinates":[-0.847114,52.193275],"type":"Point"}
}