{
  "type": "Feature",
  "properties": {
    "addr:full":"3 Woodgate Way South Glenrothes Fife KY7 4PF",
    "addr:housenumber":"3",
    "addr:postcode":"ky7 4pf",
    "addr:street":"Woodgate Way South",
    "iso:country":"GB",
    "sg:address":"3 Woodgate Way South",
    "sg:city":"Glenrothes",
    "sg:classifiers":[
        {
            "category":"Building & Trades",
            "subcategory":"Plumbing",
            "type":"Services"
        }
    ],
    "sg:phone":"+44 1592 775555",
    "sg:postcode":"KY7 4PF",
    "sg:province":"Fife",
    "sg:tags":[
        "merchant",
        "plumbers'"
    ],
    "wof:name":"Fife Plumbing Supplies",
    "wof:placetype":"venue"
},
  "geometry": {"coordinates":[-3.15077,56.186596],"type":"Point"}
}