{
  "type": "Feature",
  "properties": {
    "iso:country":"GB",
    "sg:address":"222 Redbridge Lane East",
    "sg:city":"Ilford",
    "sg:classifiers":[
        {
            "category":"Food & Beverages",
            "subcategory":"Fruits & Vegetables",
            "type":"Retail Goods"
        }
    ],
    "sg:phone":"+44 20 8550 8152",
    "sg:postcode":"IG4 5BQ",
    "sg:province":"Essex",
    "sg:tags":[
        "greengrocer"
    ],
    "wof:name":"Redbridge Wholesale Fruits",
    "wof:placetype":"venue"
},
  "geometry": {"coordinates":[0.045736,51.577],"type":"Point"}
}