{
  "type": "Feature",
  "properties": {
    "addr:full":"41 Albion St Leicester Leicestershire LE1 6LB",
    "addr:housenumber":"41",
    "addr:postcode":"le1 6lb",
    "addr:street":"Albion St",
    "iso:country":"GB",
    "sg:address":"41 Albion St",
    "sg:city":"Leicester",
    "sg:classifiers":[
        {
            "category":"Communications",
            "subcategory":"Film & Video Production",
            "type":"Services"
        }
    ],
    "sg:postcode":"LE1 6LB",
    "sg:province":"Leicestershire",
    "sg:tags":[
        "recording",
        "studio"
    ],
    "wof:name":"The Davis Media Group Ltd",
    "wof:placetype":"venue"
},
  "geometry": {"coordinates":[-1.130377,52.631542],"type":"Point"}
}