{
  "type": "Feature",
  "properties": {
    "iso:country":"GB",
    "sg:address":"15 Westell Close",
    "sg:city":"Baldock",
    "sg:classifiers":[
        {
            "category":"Professional",
            "subcategory":"Management & Consulting",
            "type":"Services"
        }
    ],
    "sg:phone":"+44 1462 490711",
    "sg:postcode":"SG7 6RY",
    "sg:province":"Bedfordshire",
    "sg:tags":[
        "consultant",
        "business"
    ],
    "wof:name":"Pathfinder Team Consulting Ltd.",
    "wof:placetype":"venue"
},
  "geometry": {"coordinates":[-0.1750160009,51.9890327454],"type":"Point"}
}