{
  "type": "Feature",
  "properties": {
    "addr:full":"12 Berkswell Hall Coventry Warwickshire CV7 7BG",
    "addr:housenumber":"12",
    "addr:postcode":"cv7 7bg",
    "addr:street":"Berkswell Hall",
    "iso:country":"GB",
    "sg:address":"12 Berkswell Hall",
    "sg:city":"Coventry",
    "sg:classifiers":[
        {
            "category":"Real Estate",
            "subcategory":"Surveying",
            "type":"Services"
        }
    ],
    "sg:phone":"+44 1676 534507",
    "sg:postcode":"CV7 7BG",
    "sg:province":"Warwickshire",
    "sg:tags":[
        "surveyor",
        "valuer"
    ],
    "wof:name":"Laurence Abrahams",
    "wof:placetype":"venue"
},
  "geometry": {"coordinates":[-1.650949,52.3993],"type":"Point"}
}