{
  "type": "Feature",
  "properties": {
    "addr:full":"Sheridan Centre Stafford Staffordshire ST16 2AD",
    "addr:postcode":"st16 2ad",
    "iso:country":"GB",
    "sg:address":"Sheridan Centre",
    "sg:city":"Stafford",
    "sg:classifiers":[
        {
            "category":"Shopping",
            "subcategory":"Thrift Store",
            "type":"Retail Goods"
        }
    ],
    "sg:postcode":"ST16 2AD",
    "sg:province":"Staffordshire",
    "sg:tags":[
        "shop",
        "charity"
    ],
    "wof:name":"Oxfam",
    "wof:placetype":"venue"
},
  "geometry": {"coordinates":[-2.121768,52.803959],"type":"Point"}
}