{
  "type": "Feature",
  "properties": {
    "addr:full":"Unit 7 Balfour Business Centre, Balfour Road Southall Greater London UB2 5BD",
    "addr:housenumber":"unit 7",
    "addr:postcode":"ub2 5bd",
    "addr:street":"Balfour Business Centre Balfour Road",
    "iso:country":"GB",
    "sg:address":"Unit 7 Balfour Business Centre, Balfour Road",
    "sg:city":"Southall",
    "sg:classifiers":[
        {
            "category":"Bus Charters",
            "type":"Transportation"
        }
    ],
    "sg:phone":"+44 20 8813 8534",
    "sg:postcode":"UB2 5BD",
    "sg:province":"Greater London",
    "sg:tags":[
        "hire",
        "coach"
    ],
    "wof:name":"P R Coaches",
    "wof:placetype":"venue"
},
  "geometry": {"coordinates":[-0.394579,51.50359],"type":"Point"}
}