{
  "type": "Feature",
  "properties": {
    "addr:full":"5 Fairmile Henley-on-thames Berkshire RG9 2JR",
    "addr:housenumber":"5;henley-on-thames",
    "addr:postcode":"rg9 2jr",
    "addr:street":"Fairmile",
    "iso:country":"GB",
    "sg:address":"5 Fairmile",
    "sg:city":"Henley-on-thames",
    "sg:classifiers":[
        {
            "category":"Professional",
            "subcategory":"Accounting & Tax Preparation",
            "type":"Services"
        }
    ],
    "sg:phone":"+44 1491 579866",
    "sg:postcode":"RG9 2JR",
    "sg:province":"Berkshire",
    "sg:tags":[
        "accountant"
    ],
    "wof:name":"Hurst Morrison Thomson",
    "wof:placetype":"venue"
},
  "geometry": {"coordinates":[-0.910459,51.544106],"type":"Point"}
}