{
  "type": "Feature",
  "properties": {
    "iso:country":"GB",
    "sg:address":"10 Lime Street",
    "sg:city":"Bedford",
    "sg:classifiers":[
        {
            "category":"Personal",
            "subcategory":"Beauty Salon",
            "type":"Services"
        }
    ],
    "sg:postcode":"MK40 1LD",
    "sg:province":"Bedfordshire",
    "sg:tags":[
        "unisex",
        "hairdresser"
    ],
    "wof:name":"Anton",
    "wof:placetype":"venue"
},
  "geometry": {"coordinates":[-0.467931,52.137901],"type":"Point"}
}