{
  "type": "Feature",
  "properties": {
    "addr:full":"12 Stirling Rd Solihull West Midlands B90 4NE",
    "addr:housenumber":"12",
    "addr:postcode":"b90 4ne",
    "addr:street":"Stirling Rd",
    "iso:country":"GB",
    "sg:address":"12 Stirling Rd",
    "sg:city":"Solihull",
    "sg:classifiers":[
        {
            "category":"Shopping",
            "subcategory":"Computers & Home Electronics",
            "type":"Retail Goods"
        }
    ],
    "sg:phone":"+44 121 704 3345",
    "sg:postcode":"B90 4NE",
    "sg:province":"West Midlands",
    "sg:tags":[
        "consumables"
    ],
    "wof:name":"Standard Continuous (Listings) Ltd",
    "wof:placetype":"venue"
},
  "geometry": {"coordinates":[-1.805234,52.397079],"type":"Point"}
}