{
  "type": "Feature",
  "properties": {
    "iso:country":"GB",
    "sg:address":"4 The Shires, Old Bedford Road",
    "sg:city":"Luton",
    "sg:classifiers":[
        {
            "category":"Health Services",
            "subcategory":"Health Practitioner",
            "type":"Services"
        }
    ],
    "sg:postcode":"LU2 7QA",
    "sg:province":"Bedfordshire",
    "sg:tags":[
        "acupuncture"
    ],
    "wof:name":"Rachael de Vere Marfleet",
    "wof:placetype":"venue"
},
  "geometry": {"coordinates":[-0.416959,51.88316],"type":"Point"}
}