{
  "type": "Feature",
  "properties": {
    "iso:country":"GB",
    "sg:address":"223 Powder Mill Lane",
    "sg:city":"Twickenham",
    "sg:classifiers":[
        {
            "category":"Shopping",
            "subcategory":"Florist",
            "type":"Retail Goods"
        }
    ],
    "sg:phone":"+44 20 8898 7333",
    "sg:postcode":"TW2 6EH",
    "sg:province":"Greater London",
    "wof:name":"Frances Shaw",
    "wof:placetype":"venue"
},
  "geometry": {"coordinates":[-0.378339,51.449173],"type":"Point"}
}