{
  "type": "Feature",
  "properties": {
    "addr:full":"33 St Peters Avenue Cleethorpes Lincolnshire DN35 8HF",
    "addr:housenumber":"33",
    "addr:postcode":"dn35 8hf",
    "addr:street":"St Peters Avenue",
    "iso:country":"GB",
    "sg:address":"33 St Peters Avenue",
    "sg:city":"Cleethorpes",
    "sg:classifiers":[
        {
            "category":"Shopping",
            "subcategory":"Shoes",
            "type":"Retail Goods"
        }
    ],
    "sg:phone":"+44 1472 699516",
    "sg:postcode":"DN35 8HF",
    "sg:province":"Lincolnshire",
    "sg:tags":[
        "shop"
    ],
    "wof:name":"Zone Property Ltd.",
    "wof:placetype":"venue"
},
  "geometry": {"coordinates":[-0.0316560008,53.5596847534],"type":"Point"}
}