{
  "type": "Feature",
  "properties": {
    "addr:full":"63 Bloxwich Road South Willenhall West Midlands WV13 1AZ",
    "addr:housenumber":"63",
    "addr:postcode":"wv13 1az",
    "addr:street":"Bloxwich Road South",
    "iso:country":"GB",
    "sg:address":"63 Bloxwich Road South",
    "sg:city":"Willenhall",
    "sg:classifiers":[
        {
            "category":"Health Services",
            "subcategory":"Clinic",
            "type":"Services"
        }
    ],
    "sg:phone":"+44 1902 608838",
    "sg:postcode":"WV13 1AZ",
    "sg:province":"West Midlands",
    "sg:tags":[
        "nh"
    ],
    "wof:name":"Ednam House Surgery",
    "wof:placetype":"venue"
},
  "geometry": {"coordinates":[-2.05439,52.591343],"type":"Point"}
}