{
  "type": "Feature",
  "properties": {
    "iso:country":"GB",
    "sg:address":"Station Rd",
    "sg:city":"Berkeley",
    "sg:classifiers":[
        {
            "category":"Manufacturing",
            "subcategory":"Building Materials",
            "type":"Manufacturing & Wholesale Goods"
        }
    ],
    "sg:phone":"+44 1453 511567",
    "sg:postcode":"GL13 9RL",
    "sg:province":"Gloucestershire",
    "sg:tags":[
        "tarmac",
        "asphalt"
    ],
    "wof:name":"Goulden Contracting Ltd",
    "wof:placetype":"venue"
},
  "geometry": {"coordinates":[-2.458019,51.696671],"type":"Point"}
}