{
  "type": "Feature",
  "properties": {
    "addr:full":"44 Huntingdon Street, St Neots Huntingdon Bedfordshire PE19 1DU",
    "addr:housenumber":"44",
    "addr:postcode":"pe19 1du",
    "addr:street":"Huntingdon Street",
    "iso:country":"GB",
    "sg:address":"44 Huntingdon Street, St Neots",
    "sg:city":"Huntingdon",
    "sg:classifiers":[
        {
            "category":"Organizations",
            "subcategory":"Community Association",
            "type":"Services"
        },
        {
            "category":"Organizations",
            "subcategory":"Membership Organization",
            "type":"Services"
        }
    ],
    "sg:phone":"+44 1480 386308",
    "sg:postcode":"PE19 1DU",
    "sg:province":"Bedfordshire",
    "sg:tags":[
        "club",
        "social"
    ],
    "wof:name":"R A F ASSOCIATION",
    "wof:placetype":"venue"
},
  "geometry": {"coordinates":[-0.263991,52.231747],"type":"Point"}
}