{
  "type": "Feature",
  "properties": {
    "addr:full":"Cannon House, 5 The Square, Chagford Newton Abbot Devon TQ13 8AA",
    "addr:housenumber":"5",
    "addr:postcode":"tq13 8aa",
    "addr:street":"The Square",
    "iso:country":"GB",
    "sg:address":"Cannon House, 5 The Square, Chagford",
    "sg:city":"Newton Abbot",
    "sg:classifiers":[
        {
            "category":"Shopping",
            "subcategory":"Pharmacy",
            "type":"Retail Goods"
        }
    ],
    "sg:phone":"+44 1647 433486",
    "sg:postcode":"TQ13 8AA",
    "sg:province":"Devon",
    "sg:tags":[
        "pharmacist",
        "chemist"
    ],
    "wof:name":"C F & W B Mee",
    "wof:placetype":"venue"
},
  "geometry": {"coordinates":[-3.840116,50.673065],"type":"Point"}
}