{
  "type": "Feature",
  "properties": {
    "addr:full":"Unit 22, Bartleet Rd Redditch Warwickshire B98 0DG",
    "addr:housenumber":"unit 22",
    "addr:postcode":"b98 0dg",
    "addr:street":"Bartleet Rd",
    "iso:country":"GB",
    "sg:address":"Unit 22, Bartleet Rd",
    "sg:city":"Redditch",
    "sg:classifiers":[
        {
            "category":"Wholesale",
            "subcategory":"Office Equipment",
            "type":"Manufacturing & Wholesale Goods"
        }
    ],
    "sg:phone":"+44 1527 502299",
    "sg:postcode":"B98 0DG",
    "sg:province":"Warwickshire",
    "sg:tags":[
        "partition",
        "cubicle"
    ],
    "wof:name":"WRG Partition Systems",
    "wof:placetype":"venue"
},
  "geometry": {"coordinates":[-1.896826,52.288616],"type":"Point"}
}