{
  "type": "Feature",
  "properties": {
    "iso:country":"GB",
    "sg:address":"49 High East Street",
    "sg:city":"Dorchester",
    "sg:classifiers":[
        {
            "category":"Travel",
            "subcategory":"Hotels & Motels",
            "type":"Entertainment"
        }
    ],
    "sg:phone":"+44 1305 264043",
    "sg:postcode":"DT1 1HU",
    "sg:province":"Dorset",
    "sg:tags":[
        "house",
        "guest"
    ],
    "wof:name":"Casterbridge Hotel",
    "wof:placetype":"venue"
},
  "geometry": {"coordinates":[-2.433527,50.71582],"type":"Point"}
}