{
  "type": "Feature",
  "properties": {
    "addr:full":"82 Melrose Avenue Mitcham Greater London CR4 2EJ",
    "addr:housenumber":"82",
    "addr:postcode":"cr4 2ej",
    "addr:street":"Melrose Avenue",
    "iso:country":"GB",
    "sg:address":"82 Melrose Avenue",
    "sg:city":"Mitcham",
    "sg:classifiers":[
        {
            "category":"Social Services",
            "subcategory":"Child Care",
            "type":"Services"
        }
    ],
    "sg:phone":"+44 20 8640 6660",
    "sg:postcode":"CR4 2EJ",
    "sg:province":"Greater London",
    "sg:tags":[
        "children's",
        "home"
    ],
    "wof:name":"Melrose House",
    "wof:placetype":"venue"
},
  "geometry": {"coordinates":[-0.1494099945,51.4154129028],"type":"Point"}
}