{
  "type": "Feature",
  "properties": {
    "addr:full":"443-445 Holloway Road London Greater London N7 6LW",
    "addr:housenumber":"443-445",
    "addr:postcode":"n7 6lw",
    "addr:street":"Holloway Road",
    "iso:country":"GB",
    "sg:address":"443-445 Holloway Road",
    "sg:city":"London",
    "sg:classifiers":[
        {
            "category":"Organizations",
            "subcategory":"Non-profit Organization",
            "type":"Services"
        }
    ],
    "sg:phone":"+44 20 7281 3863",
    "sg:postcode":"N7 6LW",
    "sg:province":"Greater London",
    "sg:tags":[
        "charitable",
        "organisation",
        "voluntary",
        "charity"
    ],
    "wof:name":"The National Youth Theatre of Great Britain Ltd.",
    "wof:placetype":"venue"
},
  "geometry": {"coordinates":[-0.1217940003,51.5592575073],"type":"Point"}
}