{
  "type": "Feature",
  "properties": {
    "addr:full":"Waddon Marsh Way, Purley Way Croydon Surrey CR9 4HT",
    "addr:postcode":"cr9 4ht",
    "addr:street":"Waddon Marsh Way Purley",
    "iso:country":"GB",
    "sg:address":"Waddon Marsh Way, Purley Way",
    "sg:city":"Croydon",
    "sg:classifiers":[
        {
            "category":"Professional",
            "subcategory":"Engineering",
            "type":"Services"
        }
    ],
    "sg:phone":"+44 20 8688 2791",
    "sg:postcode":"CR9 4HT",
    "sg:province":"Surrey",
    "sg:tags":[
        "chemical",
        "engineer"
    ],
    "wof:name":"Ravenhill Biotechnology & Systems Ltd.",
    "wof:placetype":"venue"
},
  "geometry": {"coordinates":[-0.1214409992,51.3788604736],"type":"Point"}
}