{
  "type": "Feature",
  "properties": {
    "iso:country":"GB",
    "sg:address":"Lancashire Hill",
    "sg:city":"Stockport",
    "sg:classifiers":[
        {
            "category":"Organizations",
            "subcategory":"Non-profit Organization",
            "type":"Services"
        }
    ],
    "sg:phone":"+44 161 477 6698",
    "sg:postcode":"SK4 1UB",
    "sg:province":"Cheshire",
    "sg:tags":[
        "organisation",
        "voluntary",
        "charity"
    ],
    "wof:name":"Stockport Ring & Ride",
    "wof:placetype":"venue"
},
  "geometry": {"coordinates":[-2.159853,53.41711],"type":"Point"}
}