{
  "type": "Feature",
  "properties": {
    "iso:country":"GB",
    "sg:address":"8 Brighton Place, Portobello",
    "sg:city":"Edinburgh",
    "sg:classifiers":[
        {
            "category":"Professional",
            "subcategory":"Management & Consulting",
            "type":"Services"
        }
    ],
    "sg:phone":"+44 131 468 1374",
    "sg:postcode":"EH15 1LJ",
    "sg:province":"City of Edinburgh",
    "sg:tags":[
        "consultant",
        "training"
    ],
    "wof:name":"Organisation & Social Development Consultants Ltd.",
    "wof:placetype":"venue"
},
  "geometry": {"coordinates":[-3.1148641109,55.9528083801],"type":"Point"}
}