{
  "type": "Feature",
  "properties": {
    "addr:full":"59-61 Exmouth Market London Greater London EC1R 4QL",
    "addr:housenumber":"59-61",
    "addr:postcode":"ec1r 4ql",
    "addr:street":"Exmouth Market",
    "iso:country":"GB",
    "sg:address":"59-61 Exmouth Market",
    "sg:city":"London",
    "sg:classifiers":[
        {
            "category":"Bars & Pubs",
            "type":"Food & Drink"
        }
    ],
    "sg:postcode":"EC1R 4QL",
    "sg:province":"Greater London",
    "sg:tags":[
        "pubs",
        "inn"
    ],
    "wof:name":"Rosebury Freehouse",
    "wof:placetype":"venue"
},
  "geometry": {"coordinates":[-0.108491,51.526321],"type":"Point"}
}