{
  "type": "Feature",
  "properties": {
    "addr:full":"Low Road, Hackford Wymondham Norfolk NR18 9HW",
    "addr:postcode":"nr18 9hw",
    "addr:street":"Low Road Hackford",
    "iso:country":"GB",
    "sg:address":"Low Road, Hackford",
    "sg:city":"Wymondham",
    "sg:classifiers":[
        {
            "category":"Farming",
            "subcategory":"Farm",
            "type":"Manufacturing & Wholesale Goods"
        }
    ],
    "sg:phone":"+44 1953 850707",
    "sg:postcode":"NR18 9HW",
    "sg:province":"Norfolk",
    "sg:tags":[
        "mixed",
        "crop"
    ],
    "wof:name":"A E Baker & Son",
    "wof:placetype":"venue"
},
  "geometry": {"coordinates":[1.036224,52.582626],"type":"Point"}
}