{
  "type": "Feature",
  "properties": {
    "iso:country":"GB",
    "sg:address":"Third Avenue",
    "sg:city":"Crewe",
    "sg:classifiers":[
        {
            "category":"Autos & Motor Vehicles",
            "subcategory":"Automobile Sales",
            "type":"Retail Goods"
        },
        {
            "category":"Retail",
            "subcategory":"Auto Rental",
            "type":"Services"
        }
    ],
    "sg:phone":"+44 1270 507050",
    "sg:postcode":"CW1 6XZ",
    "sg:province":"Cheshire",
    "sg:tags":[
        "car"
    ],
    "wof:name":"L C Charles Ltd.",
    "wof:placetype":"venue"
},
  "geometry": {"coordinates":[-2.423544,53.086319],"type":"Point"}
}