{
  "type": "Feature",
  "properties": {
    "addr:full":"Shalom, Smithfield Grn, Holt Wrexham Wrexham LL13 9AJ",
    "addr:postcode":"ll13 9aj",
    "addr:street":"Smithfield Grn Holt",
    "iso:country":"GB",
    "sg:address":"Shalom, Smithfield Grn, Holt",
    "sg:city":"Wrexham",
    "sg:classifiers":[
        {
            "category":"Building & Trades",
            "subcategory":"Construction",
            "type":"Services"
        }
    ],
    "sg:phone":"+44 1829 270940",
    "sg:postcode":"LL13 9AJ",
    "sg:province":"Wrexham",
    "sg:tags":[
        "builder"
    ],
    "wof:name":"Frank Bithell",
    "wof:placetype":"venue"
},
  "geometry": {"coordinates":[-2.885659,53.07933],"type":"Point"}
}