{
  "type": "Feature",
  "properties": {
    "addr:full":"May Road, Turvey Bedford Bedfordshire MK43 8DY",
    "addr:postcode":"mk43 8dy",
    "addr:street":"May Road",
    "iso:country":"GB",
    "sg:address":"May Road, Turvey",
    "sg:city":"Bedford",
    "sg:classifiers":[
        {
            "category":"Education",
            "subcategory":"School",
            "type":"Public Place"
        }
    ],
    "sg:phone":"+44 1234 881259",
    "sg:postcode":"MK43 8DY",
    "sg:province":"Bedfordshire",
    "sg:tags":[
        "local",
        "authority"
    ],
    "wof:name":"Turvey Lower School",
    "wof:placetype":"venue"
},
  "geometry": {"coordinates":[-0.62509799,52.1624488831],"type":"Point"}
}