{
  "type": "Feature",
  "properties": {
    "iso:country":"GB",
    "sg:address":"135 East Street",
    "sg:city":"South Molton",
    "sg:classifiers":[
        {
            "category":"Home & Garden",
            "subcategory":"Hardware",
            "type":"Retail Goods"
        }
    ],
    "sg:postcode":"EX36 3BU",
    "sg:province":"Devon",
    "sg:tags":[
        "lawnmowers",
        "machinery"
    ],
    "wof:name":"Michael Fook Engineering",
    "wof:placetype":"venue"
},
  "geometry": {"coordinates":[-3.832873,51.01799],"type":"Point"}
}