{
  "type": "Feature",
  "properties": {
    "addr:full":"66 Uphill Way Weston-super-mare Somerset BS23 4TN",
    "addr:housenumber":"66",
    "addr:postcode":"bs23 4tn",
    "addr:street":"Uphill Way",
    "iso:country":"GB",
    "sg:address":"66 Uphill Way",
    "sg:city":"Weston-super-mare",
    "sg:classifiers":[
        {
            "category":"Wholesale",
            "subcategory":"Sporting Goods",
            "type":"Manufacturing & Wholesale Goods"
        }
    ],
    "sg:phone":"+44 1934 613612",
    "sg:postcode":"BS23 4TN",
    "sg:province":"Somerset",
    "sg:tags":[
        "mnfr",
        "sport",
        "equipment"
    ],
    "wof:name":"Performance Kayaks",
    "wof:placetype":"venue"
},
  "geometry": {"coordinates":[-2.9806759357,51.3212051392],"type":"Point"}
}