{
  "type": "Feature",
  "properties": {
    "addr:full":"103a Kensington Rd Southport Lancashire PR9 0RZ",
    "addr:housenumber":"103a",
    "addr:postcode":"pr9 0rz",
    "addr:street":"Kensington Rd",
    "iso:country":"GB",
    "sg:address":"103a Kensington Rd",
    "sg:city":"Southport",
    "sg:classifiers":[
        {
            "category":"Personal",
            "subcategory":"Beauty Salon",
            "type":"Services"
        }
    ],
    "sg:phone":"+44 1704 534319",
    "sg:postcode":"PR9 0RZ",
    "sg:province":"Lancashire",
    "sg:tags":[
        "unisex",
        "hairdresser"
    ],
    "wof:name":"Limelight Studio",
    "wof:placetype":"venue"
},
  "geometry": {"coordinates":[-2.990628,53.644794],"type":"Point"}
}