{
  "type": "Feature",
  "properties": {
    "addr:full":"Unit 1/2, Boxmend Industrial Estate, Bircholt Road Maidstone Kent ME15 9YG",
    "addr:housenumber":"unit 1 / 2",
    "addr:postcode":"me15 9yg",
    "addr:street":"Boxmend Industrial;Bircholt Road",
    "iso:country":"GB",
    "sg:address":"Unit 1/2, Boxmend Industrial Estate, Bircholt Road",
    "sg:city":"Maidstone",
    "sg:classifiers":[
        {
            "category":"Professional",
            "type":"Services"
        },
        {
            "category":"Personal",
            "type":"Services"
        }
    ],
    "sg:phone":"+44 1622 763269",
    "sg:postcode":"ME15 9YG",
    "sg:province":"Kent",
    "sg:tags":[
        "caterer",
        "wedding"
    ],
    "wof:name":"Beaubray Catering Services",
    "wof:placetype":"venue"
},
  "geometry": {"coordinates":[0.56128,51.234909],"type":"Point"}
}