{
  "type": "Feature",
  "properties": {
    "iso:country":"GB",
    "sg:address":"Collier Works Industrial Estate, Bag Lane, Atherton",
    "sg:city":"Manchester",
    "sg:classifiers":[
        {
            "category":"Professional",
            "subcategory":"Art Services",
            "type":"Services"
        },
        {
            "category":"Government",
            "subcategory":"Post Office",
            "type":"Public Place"
        }
    ],
    "sg:phone":"+44 1942 871088",
    "sg:postcode":"M46 0LB",
    "sg:province":"Greater Manchester",
    "sg:tags":[
        "carver",
        "sculptor",
        "activity"
    ],
    "wof:name":"ROCHE DESIGN THEMATICS LTD",
    "wof:placetype":"venue"
},
  "geometry": {"coordinates":[-2.503452,53.528305],"type":"Point"}
}