{
  "type": "Feature",
  "properties": {
    "addr:full":"Everingham Rd Sheffield South Yorkshire S5 7LE",
    "addr:postcode":"s5 7le",
    "addr:street":"Everingham Rd",
    "iso:country":"GB",
    "sg:address":"Everingham Rd",
    "sg:city":"Sheffield",
    "sg:classifiers":[
        {
            "category":"Place Of Worship",
            "type":"Public Place"
        }
    ],
    "sg:phone":"+44 114 243 6689",
    "sg:postcode":"S5 7LE",
    "sg:province":"South Yorkshire",
    "wof:name":"St Leonards Vicarage",
    "wof:placetype":"venue"
},
  "geometry": {"coordinates":[-1.464483,53.415646],"type":"Point"}
}