{
  "type": "Feature",
  "properties": {
    "addr:full":"32 Newton Road Farnborough Hampshire GU14 8BN",
    "addr:housenumber":"32",
    "addr:postcode":"gu14 8bn",
    "addr:street":"Newton Road",
    "iso:country":"GB",
    "sg:address":"32 Newton Road",
    "sg:city":"Farnborough",
    "sg:classifiers":[
        {
            "category":"Banks & Credit Unions",
            "subcategory":"Bank",
            "type":"Services"
        }
    ],
    "sg:phone":"+44 1252 378297",
    "sg:postcode":"GU14 8BN",
    "sg:province":"Hampshire",
    "sg:tags":[
        "broker",
        "mortgage"
    ],
    "wof:name":"A J A Mortgages",
    "wof:placetype":"venue"
},
  "geometry": {"coordinates":[-0.7446110249,51.3042297363],"type":"Point"}
}