{
  "type": "Feature",
  "properties": {
    "addr:full":"233 Tamworth Road Sutton Coldfield Staffordshire B75 6DX",
    "addr:housenumber":"233",
    "addr:postcode":"b75 6dx",
    "addr:street":"Tamworth Road",
    "iso:country":"GB",
    "sg:address":"233 Tamworth Road",
    "sg:city":"Sutton Coldfield",
    "sg:classifiers":[
        {
            "category":"Health Services",
            "subcategory":"Doctor",
            "type":"Services"
        },
        {
            "category":"Health Services",
            "subcategory":"Clinic",
            "type":"Services"
        }
    ],
    "sg:phone":"+44 121 323 2121",
    "sg:postcode":"B75 6DX",
    "sg:province":"Staffordshire",
    "sg:tags":[
        "nh",
        "practitioners"
    ],
    "wof:name":"Ashfurlong Medical Centre",
    "wof:placetype":"venue"
},
  "geometry": {"coordinates":[-1.804659,52.57851],"type":"Point"}
}