{
  "type": "Feature",
  "properties": {
    "addr:full":"Parade Crescent Liverpool Merseyside L24 2SH",
    "addr:postcode":"l24 2sh",
    "addr:street":"Parade Crescent",
    "iso:country":"GB",
    "sg:address":"Parade Crescent",
    "sg:city":"Liverpool",
    "sg:classifiers":[
        {
            "category":"Social Services",
            "subcategory":"Retirement Home",
            "type":"Services"
        }
    ],
    "sg:phone":"+44 151 486 1507",
    "sg:postcode":"L24 2SH",
    "sg:province":"Merseyside",
    "sg:tags":[
        "residential",
        "care"
    ],
    "wof:name":"Crescent Lodge",
    "wof:placetype":"venue"
},
  "geometry": {"coordinates":[-2.8411300182,53.3404121399],"type":"Point"}
}