{
  "type": "Feature",
  "properties": {
    "addr:full":"Market Street, East Harling Norwich Norfolk NR16 2AD",
    "addr:postcode":"nr16 2ad",
    "addr:street":"Market Street East;Norwich",
    "iso:country":"GB",
    "sg:address":"Market Street, East Harling",
    "sg:city":"Norwich",
    "sg:classifiers":[
        {
            "category":"Government",
            "subcategory":"Post Office",
            "type":"Public Place"
        }
    ],
    "sg:postcode":"NR16 2AD",
    "sg:province":"Norfolk",
    "wof:name":"East Harling Post Office",
    "wof:placetype":"venue"
},
  "geometry": {"coordinates":[0.931885004,52.4397468567],"type":"Point"}
}