{
  "type": "Feature",
  "properties": {
    "iso:country":"GB",
    "sg:address":"Avon Office",
    "sg:city":"Bristol",
    "sg:classifiers":[
        {
            "category":"Building & Trades",
            "subcategory":"Landscaping Services",
            "type":"Services"
        }
    ],
    "sg:postcode":"BS37 6DA",
    "sg:province":"Gloucestershire",
    "sg:tags":[
        "consultant"
    ],
    "wof:name":"Beaver Group",
    "wof:placetype":"venue"
},
  "geometry": {"coordinates":[-2.3916,51.538429],"type":"Point"}
}