{
  "type": "Feature",
  "properties": {
    "iso:country":"GB",
    "sg:address":"Wellesley Road",
    "sg:city":"Clacton-on-sea",
    "sg:classifiers":[
        {
            "category":"Health Services",
            "subcategory":"Nursing And Care Facility",
            "type":"Services"
        },
        {
            "category":"Social Services",
            "subcategory":"Retirement Home",
            "type":"Services"
        }
    ],
    "sg:phone":"+44 1255 421122",
    "sg:postcode":"CO15 3PP",
    "sg:province":"Essex",
    "sg:tags":[
        "residential"
    ],
    "wof:name":"Regent House",
    "wof:placetype":"venue"
},
  "geometry": {"coordinates":[1.1519,51.799305],"type":"Point"}
}