{
  "type": "Feature",
  "properties": {
    "addr:full":"Lyndhurst Drive Hornchurch Essex RM11 1JW",
    "addr:postcode":"rm11 1jw",
    "addr:street":"Lyndhurst Drive",
    "iso:country":"GB",
    "sg:address":"Lyndhurst Drive",
    "sg:city":"Hornchurch",
    "sg:classifiers":[
        {
            "category":"Professional",
            "subcategory":"Accounting & Tax Preparation",
            "type":"Services"
        }
    ],
    "sg:postcode":"RM11 1JW",
    "sg:province":"Essex",
    "sg:tags":[
        "accountant"
    ],
    "wof:name":"E R Bookkeeping Services",
    "wof:placetype":"venue"
},
  "geometry": {"coordinates":[0.2125329971,51.5685501099],"type":"Point"}
}