{
  "type": "Feature",
  "properties": {
    "iso:country":"GB",
    "sg:address":"7a St Onge Parade, Southbury Road",
    "sg:city":"Enfield",
    "sg:classifiers":[
        {
            "category":"Health Services",
            "subcategory":"Dentist",
            "type":"Services"
        }
    ],
    "sg:phone":"+44 20 8363 1550",
    "sg:postcode":"EN1 1YU",
    "sg:province":"Greater London",
    "wof:name":"Andrew J Bridger",
    "wof:placetype":"venue"
},
  "geometry": {"coordinates":[-0.0801289976,51.6524505615],"type":"Point"}
}