{
  "type": "Feature",
  "properties": {
    "iso:country":"GB",
    "sg:address":"Unit A3 Meadow Bank Industrial Estate, Harrison Street",
    "sg:city":"Rotherham",
    "sg:classifiers":[
        {
            "category":"Food & Beverages",
            "subcategory":"Liquor & Beverages",
            "type":"Retail Goods"
        }
    ],
    "sg:postcode":"S61 1EE",
    "sg:province":"South Yorkshire",
    "sg:tags":[
        "drink",
        "soft"
    ],
    "wof:name":"Tony's Wholesale Supplies",
    "wof:placetype":"venue"
},
  "geometry": {"coordinates":[-1.3819839954,53.4310913086],"type":"Point"}
}