{
  "type": "Feature",
  "properties": {
    "iso:country":"GB",
    "sg:address":"Unit 5",
    "sg:city":"Redditch",
    "sg:classifiers":[
        {
            "category":"Bars & Pubs",
            "type":"Food & Drink"
        },
        {
            "category":"Community Center",
            "subcategory":"Social",
            "type":"Public Place"
        }
    ],
    "sg:phone":"+44 1527 524811",
    "sg:postcode":"B98 0EP",
    "sg:province":"Warwickshire",
    "sg:tags":[
        "pubs",
        "house",
        "inn",
        "activity"
    ],
    "wof:name":"The Old Sticky Wicket",
    "wof:placetype":"venue"
},
  "geometry": {"coordinates":[-1.903747,52.297615],"type":"Point"}
}