{
  "type": "Feature",
  "properties": {
    "addr:full":"17 Monton Green, Eccles Manchester Greater Manchester M30 9LE",
    "addr:housenumber":"17",
    "addr:postcode":"m30 9le",
    "addr:street":"Monton Green",
    "iso:country":"GB",
    "sg:address":"17 Monton Green, Eccles",
    "sg:city":"Manchester",
    "sg:classifiers":[
        {
            "category":"Health Services",
            "subcategory":"Podiatrist",
            "type":"Services"
        }
    ],
    "sg:phone":"+44 161 789 3770",
    "sg:postcode":"M30 9LE",
    "sg:province":"Greater Manchester",
    "sg:tags":[
        "podiatrists",
        "chiropodist"
    ],
    "wof:name":"C.E Jeffrey S.R.Ch M.Ch.S M.Pod.A.",
    "wof:placetype":"venue"
},
  "geometry": {"coordinates":[-2.354446,53.492016],"type":"Point"}
}