{
  "type": "Feature",
  "properties": {
    "iso:country":"GB",
    "sg:address":"16 Queens Road",
    "sg:city":"Aberdeen",
    "sg:classifiers":[
        {
            "category":"Professional",
            "subcategory":"Credit Reporting & Collection",
            "type":"Services"
        }
    ],
    "sg:phone":"+44 1224 627170",
    "sg:postcode":"AB15 4ZT",
    "sg:province":"Aberdeen City",
    "sg:tags":[
        "collecting",
        "agency"
    ],
    "wof:name":"Scott & Co.",
    "wof:placetype":"venue"
},
  "geometry": {"coordinates":[-2.131473,57.142284],"type":"Point"}
}