{
  "type": "Feature",
  "properties": {
    "addr:full":"Unit B Ings Rd Wakefield West Yorkshire WF1 1RN",
    "addr:postcode":"wf1 1rn",
    "addr:street":"Ings Rd",
    "iso:country":"GB",
    "sg:address":"Unit B Ings Rd",
    "sg:city":"Wakefield",
    "sg:classifiers":[
        {
            "category":"Professional",
            "subcategory":"Business Services",
            "type":"Services"
        }
    ],
    "sg:phone":"+44 1924 298995",
    "sg:postcode":"WF1 1RN",
    "sg:province":"West Yorkshire",
    "sg:tags":[
        "tile",
        "stockist"
    ],
    "wof:name":"Tile City",
    "wof:placetype":"venue"
},
  "geometry": {"coordinates":[-1.4955400229,53.6780204773],"type":"Point"}
}