{
  "type": "Feature",
  "properties": {
    "addr:full":"32b Church Street Stornoway Eilean Siar HS1 2JD",
    "addr:housenumber":"32b",
    "addr:postcode":"hs1 2jd",
    "addr:street":"Church Street",
    "iso:country":"GB",
    "sg:address":"32b Church Street",
    "sg:city":"Stornoway",
    "sg:classifiers":[
        {
            "category":"Manufacturing",
            "subcategory":"Building Materials",
            "type":"Manufacturing & Wholesale Goods"
        }
    ],
    "sg:phone":"+44 1851 705048",
    "sg:postcode":"HS1 2JD",
    "sg:province":"Eilean Siar",
    "sg:tags":[
        "stonemason"
    ],
    "wof:name":"Stornoway Memorials",
    "wof:placetype":"venue"
},
  "geometry": {"coordinates":[-6.3861608505,58.210357666],"type":"Point"}
}