{
  "type": "Feature",
  "properties": {
    "iso:country":"GB",
    "sg:address":"123 Market Street, South Normanton",
    "sg:city":"Alfreton",
    "sg:classifiers":[
        {
            "category":"Home & Garden",
            "subcategory":"Household Appliances",
            "type":"Retail Goods"
        }
    ],
    "sg:postcode":"DE55 2AA",
    "sg:province":"Derbyshire",
    "sg:tags":[
        "domestic",
        "electrical",
        "sales"
    ],
    "wof:name":"STEVE KERRY",
    "wof:placetype":"venue"
},
  "geometry": {"coordinates":[-1.3425010443,53.1055183411],"type":"Point"}
}