{
  "type": "Feature",
  "properties": {
    "iso:country":"GB",
    "sg:address":"17-19 Washington St",
    "sg:city":"Workington",
    "sg:classifiers":[
        {
            "category":"Manufacturing",
            "subcategory":"Textiles",
            "type":"Manufacturing & Wholesale Goods"
        }
    ],
    "sg:phone":"+44 1900 608050",
    "sg:postcode":"CA14 3AW",
    "sg:province":"Cumbria",
    "sg:tags":[
        "made-up"
    ],
    "wof:name":"And So To Bed",
    "wof:placetype":"venue"
},
  "geometry": {"coordinates":[-3.543099,54.642849],"type":"Point"}
}