{
  "type": "Feature",
  "properties": {
    "addr:full":"2 St. Pauls Rd Shipley West Yorkshire BD18 3EP",
    "addr:housenumber":"2",
    "addr:postcode":"bd18 3ep",
    "addr:street":"St. Pauls Rd",
    "iso:country":"GB",
    "sg:address":"2 St. Pauls Rd",
    "sg:city":"Shipley",
    "sg:classifiers":[
        {
            "category":"Health Services",
            "subcategory":"Health Practitioner",
            "type":"Services"
        }
    ],
    "sg:phone":"+44 1274 530580",
    "sg:postcode":"BD18 3EP",
    "sg:province":"West Yorkshire",
    "sg:tags":[
        "hypnotherapists"
    ],
    "wof:name":"M Bussunt",
    "wof:placetype":"venue"
},
  "geometry": {"coordinates":[-1.782686,53.833405],"type":"Point"}
}