{
  "type": "Feature",
  "properties": {
    "iso:country":"GB",
    "sg:address":"Unit 38, 38 Boss Hall Road",
    "sg:city":"Ipswich",
    "sg:classifiers":[
        {
            "category":"Home & Garden",
            "subcategory":"Hardware",
            "type":"Retail Goods"
        }
    ],
    "sg:phone":"+44 1473 740600",
    "sg:postcode":"IP1 5BN",
    "sg:province":"Suffolk",
    "sg:tags":[
        "device",
        "fixing",
        "fastener"
    ],
    "wof:name":"Suffolk Fastener Ipswich Ltd",
    "wof:placetype":"venue"
},
  "geometry": {"coordinates":[1.1437879801,52.0577774048],"type":"Point"}
}