{
  "type": "Feature",
  "properties": {
    "iso:country":"GB",
    "sg:address":"127 Waterloo Rd",
    "sg:city":"Wolverhampton",
    "sg:classifiers":[
        {
            "category":"Shopping",
            "subcategory":"Clothing, Apparel, & Fashions",
            "type":"Retail Goods"
        }
    ],
    "sg:phone":"+44 1902 711958",
    "sg:postcode":"WV1 4RB",
    "sg:province":"West Midlands",
    "sg:tags":[
        "clothing"
    ],
    "wof:name":"Aulak Textiles",
    "wof:placetype":"venue"
},
  "geometry": {"coordinates":[-2.1307210922,52.5941390991],"type":"Point"}
}