{
  "type": "Feature",
  "properties": {
    "iso:country":"GB",
    "sg:address":"107 Aylesbury Road, Aston Clinton",
    "sg:city":"Aylesbury",
    "sg:classifiers":[
        {
            "category":"Transit Center",
            "subcategory":"Passenger",
            "type":"Transportation"
        }
    ],
    "sg:postcode":"HP22 5AJ",
    "sg:province":"Buckinghamshire",
    "sg:tags":[
        "boarding",
        "kennel",
        "catteries"
    ],
    "wof:name":"Raglan House Boarding Kennels",
    "wof:placetype":"venue"
},
  "geometry": {"coordinates":[-0.733367,51.802109],"type":"Point"}
}