{
  "type": "Feature",
  "properties": {
    "addr:full":"17 Bank Street Irvine North Ayrshire KA12 0AJ",
    "addr:housenumber":"17",
    "addr:postcode":"ka12 0aj",
    "addr:street":"Bank Street",
    "iso:country":"GB",
    "sg:address":"17 Bank Street",
    "sg:city":"Irvine",
    "sg:classifiers":[
        {
            "category":"Personal",
            "subcategory":"Beauty Salon",
            "type":"Services"
        }
    ],
    "sg:phone":"+44 1294 278500",
    "sg:postcode":"KA12 0AJ",
    "sg:province":"North Ayrshire",
    "wof:name":"The Hair Daniel Studio",
    "wof:placetype":"venue"
},
  "geometry": {"coordinates":[-4.664949,55.6157],"type":"Point"}
}