{
  "type": "Feature",
  "properties": {
    "addr:full":"Unit 3 Firefly, Hamble Southampton Hampshire SO31 4JD",
    "addr:housenumber":"unit 3",
    "addr:postcode":"so31 4jd",
    "addr:street":"Firefly Hamble",
    "iso:country":"GB",
    "sg:address":"Unit 3 Firefly, Hamble",
    "sg:city":"Southampton",
    "sg:classifiers":[
        {
            "category":"Professional",
            "type":"Services"
        }
    ],
    "sg:phone":"+44 23 8045 8341",
    "sg:postcode":"SO31 4JD",
    "sg:province":"Hampshire",
    "sg:tags":[
        "marine"
    ],
    "wof:name":"Aramid Europe",
    "wof:placetype":"venue"
},
  "geometry": {"coordinates":[-1.3169,50.85577],"type":"Point"}
}