{
  "type": "Feature",
  "properties": {
    "addr:full":"Retail Market, Salop Street Wolverhampton Staffordshire WV3 0RX",
    "addr:postcode":"wv3 0rx",
    "addr:street":"Salop Street",
    "iso:country":"GB",
    "sg:address":"Retail Market, Salop Street",
    "sg:city":"Wolverhampton",
    "sg:classifiers":[
        {
            "category":"Fast Food",
            "type":"Food & Drink"
        }
    ],
    "sg:phone":"+44 1902 424496",
    "sg:postcode":"WV3 0RX",
    "sg:province":"Staffordshire",
    "sg:tags":[
        "away",
        "take"
    ],
    "wof:name":"The Snack Bar",
    "wof:placetype":"venue"
},
  "geometry": {"coordinates":[-2.13128,52.583488],"type":"Point"}
}