{
  "type": "Feature",
  "properties": {
    "addr:full":"Gerrydon Farm Winkleigh Devon EX19 8EZ",
    "addr:housenumber":"winkleigh",
    "addr:postcode":"ex19 8ez",
    "addr:street":"Devon",
    "iso:country":"GB",
    "sg:address":"Gerrydon Farm",
    "sg:city":"Winkleigh",
    "sg:classifiers":[
        {
            "category":"Shopping",
            "type":"Retail Goods"
        }
    ],
    "sg:postcode":"EX19 8EZ",
    "sg:province":"Devon",
    "sg:tags":[
        "merchant"
    ],
    "wof:name":"R E H Cottey",
    "wof:placetype":"venue"
},
  "geometry": {"coordinates":[-3.9423849583,50.8555793762],"type":"Point"}
}