{
  "type": "Feature",
  "properties": {
    "iso:country":"GB",
    "sg:address":"Halfway Garage, Mendham Lane",
    "sg:city":"Ipswich",
    "sg:classifiers":[
        {
            "category":"Retail",
            "subcategory":"Auto Repair",
            "type":"Services"
        }
    ],
    "sg:postcode":"IP2 9QZ",
    "sg:province":"Suffolk",
    "sg:tags":[
        "electrician"
    ],
    "wof:name":"Harleston Auto Electrics",
    "wof:placetype":"venue"
},
  "geometry": {"coordinates":[1.1138600111,52.0396995544],"type":"Point"}
}