{
  "type": "Feature",
  "properties": {
    "iso:country":"GB",
    "sg:address":"44 Longfield Rd, Ash",
    "sg:city":"Aldershot",
    "sg:classifiers":[
        {
            "category":"Building & Trades",
            "subcategory":"Cleaning & Sanitation",
            "type":"Services"
        }
    ],
    "sg:phone":"+44 1252 656089",
    "sg:postcode":"GU12 6NB",
    "sg:province":"Hampshire",
    "sg:tags":[
        "cleaner",
        "window"
    ],
    "wof:name":"Michael Budge",
    "wof:placetype":"venue"
},
  "geometry": {"coordinates":[-0.722178,51.247742],"type":"Point"}
}