{
  "type": "Feature",
  "properties": {
    "addr:full":"12/14 High Street Banstead Surrey SM7 2LJ",
    "addr:housenumber":"12 / 14",
    "addr:postcode":"sm7 2lj",
    "addr:street":"High Street",
    "iso:country":"GB",
    "sg:address":"12/14 High Street",
    "sg:city":"Banstead",
    "sg:classifiers":[
        {
            "category":"Shopping",
            "subcategory":"Clothing, Apparel, & Fashions",
            "type":"Retail Goods"
        }
    ],
    "sg:phone":"+44 1737 356789",
    "sg:postcode":"SM7 2LJ",
    "sg:province":"Surrey",
    "sg:tags":[
        "menswear"
    ],
    "wof:name":"R F Ltd.",
    "wof:placetype":"venue"
},
  "geometry": {"coordinates":[-0.204194,51.321922],"type":"Point"}
}