{
  "type": "Feature",
  "properties": {
    "addr:full":"9 Providence Place Pudsey West Yorkshire LS28 6AE",
    "addr:housenumber":"9",
    "addr:postcode":"ls28 6ae",
    "addr:street":"Providence Place Pudsey West",
    "iso:country":"GB",
    "sg:address":"9 Providence Place",
    "sg:city":"Pudsey",
    "sg:classifiers":[
        {
            "category":"Home & Garden",
            "subcategory":"Household Appliances",
            "type":"Retail Goods"
        }
    ],
    "sg:postcode":"LS28 6AE",
    "sg:province":"West Yorkshire",
    "sg:tags":[
        "electrical"
    ],
    "wof:name":"Alliance Washers",
    "wof:placetype":"venue"
},
  "geometry": {"coordinates":[-1.66618,53.802517],"type":"Point"}
}