{
  "type": "Feature",
  "properties": {
    "addr:full":"1 Aubrey Rd Hornsey Greater London N8 9HH",
    "addr:housenumber":"1",
    "addr:postcode":"n8 9hh",
    "addr:street":"Aubrey Rd",
    "iso:country":"GB",
    "sg:address":"1 Aubrey Rd",
    "sg:city":"Hornsey",
    "sg:classifiers":[
        {
            "category":"Professional",
            "subcategory":"Management & Consulting",
            "type":"Services"
        }
    ],
    "sg:phone":"+44 20 8347 5472",
    "sg:postcode":"N8 9HH",
    "sg:province":"Greater London",
    "sg:tags":[
        "consultant",
        "safety"
    ],
    "wof:name":"PM Securities & Wholesale",
    "wof:placetype":"venue"
},
  "geometry": {"coordinates":[-0.1190569997,51.5801925659],"type":"Point"}
}