{
  "type": "Feature",
  "properties": {
    "addr:full":"56 Polmuir Road Aberdeen Aberdeen City AB11 7RT",
    "addr:housenumber":"56",
    "addr:postcode":"ab11 7rt",
    "addr:street":"Polmuir Road",
    "iso:country":"GB",
    "sg:address":"56 Polmuir Road",
    "sg:city":"Aberdeen",
    "sg:classifiers":[
        {
            "category":"Travel",
            "subcategory":"Hotels & Motels",
            "type":"Entertainment"
        }
    ],
    "sg:phone":"+44 1224 584484",
    "sg:postcode":"AB11 7RT",
    "sg:province":"Aberdeen City",
    "sg:tags":[
        "house",
        "guest"
    ],
    "wof:name":"Allan Guest House",
    "wof:placetype":"venue"
},
  "geometry": {"coordinates":[-2.103214,57.133423],"type":"Point"}
}