{
  "type": "Feature",
  "properties": {
    "iso:country":"GB",
    "sg:address":"51a North St",
    "sg:city":"Sudbury",
    "sg:classifiers":[
        {
            "category":"Restaurant",
            "type":"Food & Drink"
        }
    ],
    "sg:postcode":"CO10 1RE",
    "sg:province":"Essex",
    "sg:tags":[
        "indian"
    ],
    "wof:name":"Malik,S A,",
    "wof:placetype":"venue"
},
  "geometry": {"coordinates":[0.729247,52.041843],"type":"Point"}
}