{
  "type": "Feature",
  "properties": {
    "iso:country":"GB",
    "sg:address":"Blaenyffos",
    "sg:city":"Boncath",
    "sg:classifiers":[
        {
            "category":"Home & Garden",
            "subcategory":"Garden Supply",
            "type":"Retail Goods"
        }
    ],
    "sg:phone":"+44 1239 841215",
    "sg:postcode":"SA37 0HU",
    "sg:province":"Carmarthenshire",
    "sg:tags":[
        "nursery",
        "centre"
    ],
    "wof:name":"New Inn Nurseries",
    "wof:placetype":"venue"
},
  "geometry": {"coordinates":[-4.6174740791,52.0140609741],"type":"Point"}
}