{
  "type": "Feature",
  "properties": {
    "iso:country":"GB",
    "sg:address":"57 Gwendolen Road",
    "sg:city":"Leicester",
    "sg:classifiers":[
        {
            "category":"Home & Garden",
            "subcategory":"Garden Supply",
            "type":"Retail Goods"
        },
        {
            "category":"Home & Garden",
            "subcategory":"Hardware",
            "type":"Retail Goods"
        }
    ],
    "sg:phone":"+44 116 273 4027",
    "sg:postcode":"LE5 5FL",
    "sg:province":"Leicestershire",
    "sg:tags":[
        "lawnmowers",
        "sales",
        "machinery"
    ],
    "wof:name":"City Mower Services",
    "wof:placetype":"venue"
},
  "geometry": {"coordinates":[-1.103886,52.631351],"type":"Point"}
}