{
  "type": "Feature",
  "properties": {
    "iso:country":"GB",
    "sg:address":"Gorse Covert Road, Gose Covert",
    "sg:city":"Warrington",
    "sg:classifiers":[
        {
            "category":"Bars & Pubs",
            "type":"Food & Drink"
        }
    ],
    "sg:phone":"+44 1925 831942",
    "sg:postcode":"WA3 6TS",
    "sg:province":"Cheshire",
    "sg:tags":[
        "pubs",
        "inn"
    ],
    "wof:name":"Punch Retail Ltd.",
    "wof:placetype":"venue"
},
  "geometry": {"coordinates":[-2.500233,53.430698],"type":"Point"}
}