{
  "type": "Feature",
  "properties": {
    "addr:full":"268 Kingston Road Leatherhead Surrey KT22 7QA",
    "addr:housenumber":"268",
    "addr:postcode":"kt22 7qa",
    "addr:street":"Kingston Road",
    "iso:country":"GB",
    "sg:address":"268 Kingston Road",
    "sg:city":"Leatherhead",
    "sg:classifiers":[
        {
            "category":"Retail",
            "subcategory":"Auto Repair",
            "type":"Services"
        }
    ],
    "sg:phone":"+44 1372 377405",
    "sg:postcode":"KT22 7QA",
    "sg:province":"Surrey",
    "sg:tags":[
        "modification",
        "garage"
    ],
    "wof:name":"D Thomson & Sons",
    "wof:placetype":"venue"
},
  "geometry": {"coordinates":[-0.3332340121,51.3110733032],"type":"Point"}
}