{
  "type": "Feature",
  "properties": {
    "iso:country":"GB",
    "sg:address":"St Pauls Street",
    "sg:city":"Worcester",
    "sg:classifiers":[
        {
            "category":"Manufacturing",
            "subcategory":"Metals",
            "type":"Manufacturing & Wholesale Goods"
        },
        {
            "category":"Government",
            "subcategory":"Office",
            "type":"Public Place"
        }
    ],
    "sg:phone":"+44 1905 23819",
    "sg:postcode":"WR1 2BA",
    "sg:province":"Worcestershire",
    "sg:tags":[
        "product",
        "local",
        "fabricated"
    ],
    "wof:name":"Worcestershire County Council",
    "wof:placetype":"venue"
},
  "geometry": {"coordinates":[-2.215214,52.191761],"type":"Point"}
}