{
  "type": "Feature",
  "properties": {
    "addr:full":"118 Newmarket Rd Cambridge Cambridgeshire CB5 8HE",
    "addr:housenumber":"118",
    "addr:postcode":"cb5 8he",
    "addr:street":"Newmarket Rd",
    "iso:country":"GB",
    "sg:address":"118 Newmarket Rd",
    "sg:city":"Cambridge",
    "sg:classifiers":[
        {
            "category":"Shopping",
            "subcategory":"Department Store",
            "type":"Retail Goods"
        }
    ],
    "sg:postcode":"CB5 8HE",
    "sg:province":"Cambridgeshire",
    "wof:name":"Watson,Christopher,",
    "wof:placetype":"venue"
},
  "geometry": {"coordinates":[0.13874,52.208401],"type":"Point"}
}