{
  "type": "Feature",
  "properties": {
    "addr:full":"898 Ecclesall Road Sheffield Derbyshire S11 8TP",
    "addr:housenumber":"898",
    "addr:postcode":"s11 8tp",
    "addr:street":"Ecclesall Road",
    "iso:country":"GB",
    "sg:address":"898 Ecclesall Road",
    "sg:city":"Sheffield",
    "sg:classifiers":[
        {
            "category":"Real Estate",
            "subcategory":"Real Estate Agent",
            "type":"Services"
        }
    ],
    "sg:phone":"+44 114 268 3333",
    "sg:postcode":"S11 8TP",
    "sg:province":"Derbyshire",
    "sg:website":"http://www.blundells.com",
    "wof:name":"Blundells",
    "wof:placetype":"venue"
},
  "geometry": {"coordinates":[-1.5083470345,53.3620643616],"type":"Point"}
}