{
  "type": "Feature",
  "properties": {
    "addr:full":"Homestead Care Home (Brownhills) Ltd, 208 Ogley Road Walsall Staffordshire WS8 6AN",
    "addr:housenumber":"208",
    "addr:postcode":"ws8 6an",
    "addr:street":"Ogley Road",
    "iso:country":"GB",
    "sg:address":"Homestead Care Home (Brownhills) Ltd, 208 Ogley Road",
    "sg:city":"Walsall",
    "sg:classifiers":[
        {
            "category":"Health Services",
            "subcategory":"Nursing And Care Facility",
            "type":"Services"
        },
        {
            "category":"Social Services",
            "subcategory":"Retirement Home",
            "type":"Services"
        }
    ],
    "sg:phone":"+44 1543 360120",
    "sg:postcode":"WS8 6AN",
    "sg:province":"Staffordshire",
    "sg:tags":[
        "residential"
    ],
    "wof:name":"The Homestead",
    "wof:placetype":"venue"
},
  "geometry": {"coordinates":[-1.923253,52.650528],"type":"Point"}
}