{
  "type": "Feature",
  "properties": {
    "addr:full":"Litton Cheney Youth Hostel, Litton Cheney Dorchester Dorset DT2 9AT",
    "addr:postcode":"dt2 9at",
    "addr:street":"Dorset",
    "iso:country":"GB",
    "sg:address":"Litton Cheney Youth Hostel, Litton Cheney",
    "sg:city":"Dorchester",
    "sg:classifiers":[
        {
            "category":"Travel",
            "subcategory":"Hostel",
            "type":"Entertainment"
        }
    ],
    "sg:phone":"+44 1308 482340",
    "sg:postcode":"DT2 9AT",
    "sg:province":"Dorset",
    "sg:tags":[
        "youth"
    ],
    "sg:website":"http://www.yha.org.uk",
    "wof:name":"Youth Hostels Association",
    "wof:placetype":"venue"
},
  "geometry": {"coordinates":[-2.6346859932,50.7140693665],"type":"Point"}
}