{
  "type": "Feature",
  "properties": {
    "addr:full":"32 Saltwell View Gateshead Tyne and Wear NE8 4NT",
    "addr:housenumber":"32",
    "addr:postcode":"ne8 4nt",
    "addr:street":"Saltwell View",
    "iso:country":"GB",
    "sg:address":"32 Saltwell View",
    "sg:city":"Gateshead",
    "sg:classifiers":[
        {
            "category":"Professional",
            "subcategory":"Accounting & Tax Preparation",
            "type":"Services"
        }
    ],
    "sg:postcode":"NE8 4NT",
    "sg:province":"Tyne and Wear",
    "sg:tags":[
        "accountant"
    ],
    "wof:name":"R Walker & Co Accountants",
    "wof:placetype":"venue"
},
  "geometry": {"coordinates":[-1.606147,54.947338],"type":"Point"}
}