{
  "type": "Feature",
  "properties": {
    "addr:full":"175 Walworth Rd Elephant And Castle Greater London SE17 1RW",
    "addr:housenumber":"175",
    "addr:postcode":"se17 1rw",
    "addr:street":"Walworth Rd",
    "iso:country":"GB",
    "sg:address":"175 Walworth Rd",
    "sg:city":"Elephant And Castle",
    "sg:classifiers":[
        {
            "category":"Shopping",
            "subcategory":"Florist",
            "type":"Retail Goods"
        }
    ],
    "sg:phone":"+44 20 7701 7951",
    "sg:postcode":"SE17 1RW",
    "sg:province":"Greater London",
    "wof:name":"Bluebells Florist",
    "wof:placetype":"venue"
},
  "geometry": {"coordinates":[-0.09682,51.490192],"type":"Point"}
}