{
  "type": "Feature",
  "properties": {
    "iso:country":"GB",
    "sg:address":"Rundle Rd",
    "sg:city":"Liverpool",
    "sg:classifiers":[
        {
            "category":"Place Of Worship",
            "type":"Public Place"
        }
    ],
    "sg:phone":"+44 151 726 0627",
    "sg:postcode":"L17 0AJ",
    "sg:province":"Merseyside",
    "wof:name":"St Thomas More R C Church",
    "wof:placetype":"venue"
},
  "geometry": {"coordinates":[-2.931059,53.372074],"type":"Point"}
}