{
  "type": "Feature",
  "properties": {
    "addr:full":"67 Jarvis Street Leicester Leicestershire LE3 5BN",
    "addr:housenumber":"67",
    "addr:postcode":"le3 5bn",
    "addr:street":"Jarvis Street",
    "iso:country":"GB",
    "sg:address":"67 Jarvis Street",
    "sg:city":"Leicester",
    "sg:classifiers":[
        {
            "category":"Retail",
            "subcategory":"Auto Repair",
            "type":"Services"
        }
    ],
    "sg:phone":"+44 116 253 0039",
    "sg:postcode":"LE3 5BN",
    "sg:province":"Leicestershire",
    "sg:tags":[
        "modification",
        "garage",
        "related"
    ],
    "wof:name":"Medina Motors",
    "wof:placetype":"venue"
},
  "geometry": {"coordinates":[-1.1425620317,52.6383552551],"type":"Point"}
}