{
  "type": "Feature",
  "properties": {
    "iso:country":"GB",
    "sg:address":"Ty Mawr, Llansilin",
    "sg:city":"Oswestry",
    "sg:classifiers":[
        {
            "category":"Farming",
            "subcategory":"Farm",
            "type":"Manufacturing & Wholesale Goods"
        }
    ],
    "sg:phone":"+44 1691 791244",
    "sg:postcode":"SY10 7JW",
    "sg:province":"Shropshire",
    "sg:tags":[
        "mixed",
        "crop"
    ],
    "wof:name":"W M & S E Jones",
    "wof:placetype":"venue"
},
  "geometry": {"coordinates":[-3.1755321026,52.8463363647],"type":"Point"}
}