{
  "type": "Feature",
  "properties": {
    "iso:country":"GB",
    "sg:address":"26 Laycock Gate",
    "sg:city":"Blackpool",
    "sg:classifiers":[
        {
            "category":"Food & Beverages",
            "subcategory":"Groceries & Convenience Stores",
            "type":"Retail Goods"
        }
    ],
    "sg:phone":"+44 1253 302740",
    "sg:postcode":"FY3 8BJ",
    "sg:province":"Lancashire",
    "wof:name":"Spar Shop",
    "wof:placetype":"venue"
},
  "geometry": {"coordinates":[-3.037364006,53.8240623474],"type":"Point"}
}