{
  "type": "Feature",
  "properties": {
    "iso:country":"GB",
    "sg:address":"Unit 15 Broughton Manor Business, Park, Broughton",
    "sg:city":"Milton Keynes",
    "sg:classifiers":[
        {
            "category":"Autos & Motor Vehicles",
            "subcategory":"Auto Supplies",
            "type":"Retail Goods"
        }
    ],
    "sg:phone":"+44 1908 665591",
    "sg:postcode":"MK16 0HF",
    "sg:province":"Buckinghamshire",
    "sg:tags":[
        "tyre"
    ],
    "wof:name":"Sinton Tyres Ltd.",
    "wof:placetype":"venue"
},
  "geometry": {"coordinates":[-0.6905170083,52.0483169556],"type":"Point"}
}