{
  "type": "Feature",
  "properties": {
    "iso:country":"GB",
    "sg:address":"197 Cheriton High St",
    "sg:city":"Folkestone",
    "sg:classifiers":[
        {
            "category":"Food & Beverages",
            "subcategory":"Fruits & Vegetables",
            "type":"Retail Goods"
        }
    ],
    "sg:postcode":"CT19 4HW",
    "sg:province":"Kent",
    "sg:tags":[
        "greengrocer"
    ],
    "wof:name":"Veg Plus",
    "wof:placetype":"venue"
},
  "geometry": {"coordinates":[1.138118,51.087162],"type":"Point"}
}