{
  "type": "Feature",
  "properties": {
    "iso:country":"GB",
    "sg:address":"11-12 Priory Meadow Shopping Cen, Queens Square",
    "sg:city":"Hastings",
    "sg:classifiers":[
        {
            "category":"Shopping",
            "subcategory":"Books",
            "type":"Retail Goods"
        }
    ],
    "sg:phone":"+44 1424 722253",
    "sg:postcode":"TN34 1PH",
    "sg:province":"East Sussex",
    "sg:tags":[
        "bookseller"
    ],
    "wof:name":"Ottakars",
    "wof:placetype":"venue"
},
  "geometry": {"coordinates":[0.577422,50.86142],"type":"Point"}
}