{
  "type": "Feature",
  "properties": {
    "addr:full":"73 Achray Road, Cumbernauld Glasgow Falkirk G67 4JG",
    "addr:housenumber":"73",
    "addr:postcode":"g67 4jg",
    "addr:street":"Achray Road",
    "iso:country":"GB",
    "sg:address":"73 Achray Road, Cumbernauld",
    "sg:city":"Glasgow",
    "sg:classifiers":[
        {
            "category":"Building & Trades",
            "subcategory":"Construction",
            "type":"Services"
        }
    ],
    "sg:phone":"+44 1236 730049",
    "sg:postcode":"G67 4JG",
    "sg:province":"Falkirk",
    "sg:tags":[
        "builder"
    ],
    "wof:name":"Pacific Ceilings Ltd.",
    "wof:placetype":"venue"
},
  "geometry": {"coordinates":[-4.018389,55.933456],"type":"Point"}
}