{
  "type": "Feature",
  "properties": {
    "iso:country":"GB",
    "sg:address":"30 The Headrow",
    "sg:city":"Leeds",
    "sg:classifiers":[
        {
            "category":"Shopping",
            "subcategory":"Photographic Equipment",
            "type":"Retail Goods"
        }
    ],
    "sg:phone":"+44 113 242 5010",
    "sg:postcode":"LS1 8EQ",
    "sg:province":"West Yorkshire",
    "sg:tags":[
        "supply"
    ],
    "wof:name":"Tecno Retail Ltd",
    "wof:placetype":"venue"
},
  "geometry": {"coordinates":[-1.5451380014,53.799571991],"type":"Point"}
}