{
  "type": "Feature",
  "properties": {
    "iso:country":"GB",
    "sg:address":"10 Granville Road, North Finchley",
    "sg:city":"London",
    "sg:classifiers":[
        {
            "category":"Professional",
            "type":"Services"
        }
    ],
    "sg:phone":"+44 20 8346 8989",
    "sg:postcode":"N12 0HJ",
    "sg:province":"Greater London",
    "sg:tags":[
        "interior",
        "furnishers",
        "designer"
    ],
    "wof:name":"Crystal Interiors",
    "wof:placetype":"venue"
},
  "geometry": {"coordinates":[-0.1810539961,51.6076889038],"type":"Point"}
}