{
  "type": "Feature",
  "properties": {
    "addr:full":"35 High Street Turriff Aberdeenshire AB53 4EJ",
    "addr:housenumber":"35",
    "addr:postcode":"ab53 4ej",
    "addr:street":"High Street",
    "iso:country":"GB",
    "sg:address":"35 High Street",
    "sg:city":"Turriff",
    "sg:classifiers":[
        {
            "category":"Government",
            "subcategory":"Post Office",
            "type":"Public Place"
        }
    ],
    "sg:phone":"+44 1888 563226",
    "sg:postcode":"AB53 4EJ",
    "sg:province":"Aberdeenshire",
    "wof:name":"Turriff Post Office",
    "wof:placetype":"venue"
},
  "geometry": {"coordinates":[-2.4624791145,57.5376739502],"type":"Point"}
}