{
  "type": "Feature",
  "properties": {
    "addr:full":"Rope Walk Littlehampton West Sussex BN17 5DL",
    "addr:postcode":"bn17 5dl",
    "addr:street":"Rope Walk",
    "iso:country":"GB",
    "sg:address":"Rope Walk",
    "sg:city":"Littlehampton",
    "sg:classifiers":[
        {
            "category":"Recreation",
            "subcategory":"Sailing Club",
            "type":"Entertainment"
        },
        {
            "category":"Education",
            "subcategory":"Special Training",
            "type":"Public Place"
        }
    ],
    "sg:phone":"+44 1903 714533",
    "sg:postcode":"BN17 5DL",
    "sg:province":"West Sussex",
    "sg:tags":[
        "school"
    ],
    "wof:name":"Arun Yacht Club Ltd",
    "wof:placetype":"venue"
},
  "geometry": {"coordinates":[-0.5504739881,50.8086051941],"type":"Point"}
}