{
  "type": "Feature",
  "properties": {
    "addr:full":"183-191 Ballards La, Finchley Central, London Greater London N3 1LP",
    "addr:postcode":"183-191;n3 1lp",
    "addr:street":"Ballards",
    "iso:country":"GB",
    "sg:address":"183-191 Ballards La, Finchley Central,",
    "sg:city":"London",
    "sg:classifiers":[
        {
            "category":"Professional",
            "subcategory":"Computer Services",
            "type":"Services"
        }
    ],
    "sg:postcode":"N3 1LP",
    "sg:province":"Greater London",
    "sg:tags":[
        "system",
        "software"
    ],
    "wof:name":"Micrograde Ltd",
    "wof:placetype":"venue"
},
  "geometry": {"coordinates":[-0.1875099987,51.6057891846],"type":"Point"}
}