{
  "type": "Feature",
  "properties": {
    "iso:country":"GB",
    "sg:address":"Woodchurch Crescent",
    "sg:city":"Gillingham",
    "sg:classifiers":[
        {
            "category":"Social Services",
            "subcategory":"Adult Care",
            "type":"Services"
        }
    ],
    "sg:phone":"+44 1634 372101",
    "sg:postcode":"ME8 6XN",
    "sg:province":"Kent",
    "sg:tags":[
        "housing",
        "sheltered"
    ],
    "wof:name":"Woodchurch House Sheltered Housing",
    "wof:placetype":"venue"
},
  "geometry": {"coordinates":[0.587043,51.371998],"type":"Point"}
}