{
  "type": "Feature",
  "properties": {
    "iso:country":"GB",
    "sg:address":"10 Balliol Close",
    "sg:city":"Bognor Regis",
    "sg:classifiers":[
        {
            "category":"Shopping",
            "subcategory":"Pharmacy",
            "type":"Retail Goods"
        }
    ],
    "sg:phone":"+44 1243 863720",
    "sg:postcode":"PO21 5QE",
    "sg:province":"West Sussex",
    "sg:tags":[
        "medicine",
        "therapy"
    ],
    "wof:name":"J Dunlop",
    "wof:placetype":"venue"
},
  "geometry": {"coordinates":[-0.7052,50.790977],"type":"Point"}
}