{
  "type": "Feature",
  "properties": {
    "addr:full":"337 Lymington Road, Highcliffe Christchurch Dorset BH23 5EG",
    "addr:housenumber":"337",
    "addr:postcode":"bh23 5eg",
    "addr:street":"Lymington Road",
    "iso:country":"GB",
    "sg:address":"337 Lymington Road, Highcliffe",
    "sg:city":"Christchurch",
    "sg:classifiers":[
        {
            "category":"Banks & Credit Unions",
            "subcategory":"Bureau De Change",
            "type":"Services"
        },
        {
            "category":"Food & Beverages",
            "subcategory":"Liquor & Beverages",
            "type":"Retail Goods"
        }
    ],
    "sg:phone":"+44 1425 271288",
    "sg:postcode":"BH23 5EG",
    "sg:province":"Dorset",
    "sg:tags":[
        "beer",
        "wine",
        "spirit",
        "wines"
    ],
    "wof:name":"Southern Wines",
    "wof:placetype":"venue"
},
  "geometry": {"coordinates":[-1.699123,50.741425],"type":"Point"}
}