{
  "type": "Feature",
  "properties": {
    "addr:full":"Unit B6, Backfield Farm Bristol Gloucestershire BS37 9XD",
    "addr:postcode":"bs37 9xd",
    "addr:street":"Backfield",
    "iso:country":"GB",
    "sg:address":"Unit B6, Backfield Farm",
    "sg:city":"Bristol",
    "sg:classifiers":[
        {
            "category":"Building & Trades",
            "subcategory":"Cleaning & Sanitation",
            "type":"Services"
        }
    ],
    "sg:phone":"+44 1454 228098",
    "sg:postcode":"BS37 9XD",
    "sg:province":"Gloucestershire",
    "sg:tags":[
        "blast"
    ],
    "wof:name":"Ian May",
    "wof:placetype":"venue"
},
  "geometry": {"coordinates":[-2.468219,51.548752],"type":"Point"}
}