{
  "type": "Feature",
  "properties": {
    "addr:full":"Unit 1 Edison Road Indust Est Huntingdon Cambridgeshire PE17 4LF",
    "addr:housenumber":"unit 1",
    "addr:postcode":"pe17 4lf",
    "addr:street":"Edison Road",
    "iso:country":"GB",
    "sg:address":"Unit 1 Edison Road Indust Est",
    "sg:city":"Huntingdon",
    "sg:classifiers":[
        {
            "category":"Shopping",
            "subcategory":"Computers & Home Electronics",
            "type":"Retail Goods"
        }
    ],
    "sg:phone":"+44 1480 466961",
    "sg:postcode":"PE17 4LF",
    "sg:province":"Cambridgeshire",
    "sg:tags":[
        "equipment",
        "audio-visual"
    ],
    "wof:name":"Protech Ltd",
    "wof:placetype":"venue"
},
  "geometry": {"coordinates":[-0.1893000007,52.3351402283],"type":"Point"}
}