{
  "type": "Feature",
  "properties": {
    "iso:country":"GB",
    "sg:address":"Sydney Rd",
    "sg:city":"Bath",
    "sg:classifiers":[
        {
            "category":"Conference Center",
            "type":"Public Place"
        }
    ],
    "sg:phone":"+44 1225 447733",
    "sg:postcode":"BA2 6JF",
    "sg:province":"Somerset",
    "wof:name":"Conference Link",
    "wof:placetype":"venue"
},
  "geometry": {"coordinates":[-2.349089,51.385353],"type":"Point"}
}