{
  "type": "Feature",
  "properties": {
    "addr:full":"12 Station Road Woodhall Spa Lincolnshire LN10 6QL",
    "addr:housenumber":"12",
    "addr:postcode":"ln10 6ql",
    "addr:street":"Station Road",
    "iso:country":"GB",
    "sg:address":"12 Station Road",
    "sg:city":"Woodhall Spa",
    "sg:classifiers":[
        {
            "category":"Fast Food",
            "type":"Food & Drink"
        }
    ],
    "sg:phone":"+44 1526 354089",
    "sg:postcode":"LN10 6QL",
    "sg:province":"Lincolnshire",
    "sg:tags":[
        "away",
        "take"
    ],
    "wof:name":"Pizza King",
    "wof:placetype":"venue"
},
  "geometry": {"coordinates":[-0.2173029929,53.1518058777],"type":"Point"}
}