{
  "type": "Feature",
  "properties": {
    "iso:country":"GB",
    "sg:address":"76 Caerau Road",
    "sg:city":"Newport",
    "sg:classifiers":[
        {
            "category":"Professional",
            "subcategory":"Lawyer & Legal Services",
            "type":"Services"
        }
    ],
    "sg:phone":"+44 1633 263316",
    "sg:postcode":"NP20 4HJ",
    "sg:province":"Newport",
    "sg:tags":[
        "solicitor"
    ],
    "wof:name":"Robin H Jones & Co.",
    "wof:placetype":"venue"
},
  "geometry": {"coordinates":[-3.00415,51.586739],"type":"Point"}
}