{
  "type": "Feature",
  "properties": {
    "addr:full":"101 Pinchbeck Rd Spalding Lincolnshire PE11 1QL",
    "addr:housenumber":"101",
    "addr:postcode":"pe11 1ql",
    "addr:street":"Pinchbeck Rd",
    "iso:country":"GB",
    "sg:address":"101 Pinchbeck Rd",
    "sg:city":"Spalding",
    "sg:classifiers":[
        {
            "category":"Bars & Pubs",
            "type":"Food & Drink"
        },
        {
            "category":"Community Center",
            "subcategory":"Social",
            "type":"Public Place"
        }
    ],
    "sg:phone":"+44 1775 722931",
    "sg:postcode":"PE11 1QL",
    "sg:province":"Lincolnshire",
    "sg:tags":[
        "pubs",
        "house",
        "inn",
        "activity"
    ],
    "wof:name":"The Royal Mail Cart",
    "wof:placetype":"venue"
},
  "geometry": {"coordinates":[-0.152955,52.796265],"type":"Point"}
}