{
  "type": "Feature",
  "properties": {
    "iso:country":"GB",
    "sg:address":"Tantarra Street",
    "sg:city":"Walsall",
    "sg:classifiers":[
        {
            "category":"Manufacturing",
            "subcategory":"Building Materials",
            "type":"Manufacturing & Wholesale Goods"
        }
    ],
    "sg:phone":"+44 1922 645707",
    "sg:postcode":"WS1 2HU",
    "sg:province":"West Midlands",
    "sg:tags":[
        "tile",
        "mnfrs"
    ],
    "wof:name":"Walsall Studio Ceramics",
    "wof:placetype":"venue"
},
  "geometry": {"coordinates":[-1.9713950157,52.5843772888],"type":"Point"}
}