{
  "type": "Feature",
  "properties": {
    "addr:full":"Units 2-3 Sheinwood Farm Industrial, Estate Much Wenlock Shropshire TF13 6NR",
    "addr:housenumber":"units 2-3 sheinwood;industrial",
    "addr:postcode":"tf13 6nr",
    "addr:street":"Estate Much",
    "iso:country":"GB",
    "sg:address":"Units 2-3 Sheinwood Farm Industrial, Estate",
    "sg:city":"Much Wenlock",
    "sg:classifiers":[
        {
            "category":"Building & Trades",
            "subcategory":"Plumbing",
            "type":"Services"
        }
    ],
    "sg:phone":"+44 1952 728605",
    "sg:postcode":"TF13 6NR",
    "sg:province":"Shropshire",
    "sg:tags":[
        "heating"
    ],
    "wof:name":"Boiler Spares International Ltd.",
    "wof:placetype":"venue"
},
  "geometry": {"coordinates":[-2.559925,52.594009],"type":"Point"}
}