{
  "type": "Feature",
  "properties": {
    "iso:country":"GB",
    "sg:address":"Bridge Farm, Shrawley",
    "sg:city":"Worcester",
    "sg:classifiers":[
        {
            "category":"Professional",
            "subcategory":"Business Services",
            "type":"Services"
        }
    ],
    "sg:postcode":"WR6 6TQ",
    "sg:province":"Herefordshire",
    "sg:tags":[
        "hospitality",
        "corporate"
    ],
    "wof:name":"The Astley Estate",
    "wof:placetype":"venue"
},
  "geometry": {"coordinates":[-2.285599,52.282345],"type":"Point"}
}