{
  "type": "Feature",
  "properties": {
    "addr:full":"30 Claremont Avenue Woking Surrey GU22 7SG",
    "addr:housenumber":"30",
    "addr:postcode":"gu22 7sg",
    "addr:street":"Claremont Avenue",
    "iso:country":"GB",
    "sg:address":"30 Claremont Avenue",
    "sg:city":"Woking",
    "sg:classifiers":[
        {
            "category":"Social Services",
            "type":"Services"
        },
        {
            "category":"Government",
            "subcategory":"Office",
            "type":"Public Place"
        }
    ],
    "sg:phone":"+44 1483 518518",
    "sg:postcode":"GU22 7SG",
    "sg:province":"Surrey",
    "sg:tags":[
        "local"
    ],
    "wof:name":"Rosedean",
    "wof:placetype":"venue"
},
  "geometry": {"coordinates":[-0.560816,51.308743],"type":"Point"}
}