{
  "type": "Feature",
  "properties": {
    "iso:country":"GB",
    "sg:address":"167 Shelford Road, Trumpington",
    "sg:city":"Cambridge",
    "sg:classifiers":[
        {
            "category":"Health Services",
            "subcategory":"Clinic",
            "type":"Services"
        }
    ],
    "sg:postcode":"CB2 2ND",
    "sg:province":"Cambridgeshire",
    "sg:tags":[
        "injury",
        "sport"
    ],
    "wof:name":"R Hall",
    "wof:placetype":"venue"
},
  "geometry": {"coordinates":[0.120353,52.165516],"type":"Point"}
}