{
  "type": "Feature",
  "properties": {
    "iso:country":"GB",
    "sg:address":"34 Lydford Court, Kingston Park",
    "sg:city":"Newcastle Upon Tyne",
    "sg:classifiers":[
        {
            "category":"Manufacturing",
            "subcategory":"Textiles",
            "type":"Manufacturing & Wholesale Goods"
        }
    ],
    "sg:phone":"+44 191 286 1264",
    "sg:postcode":"NE3 2RB",
    "sg:province":"Tyne and Wear",
    "sg:tags":[
        "made-up"
    ],
    "wof:name":"The Finishing Touch",
    "wof:placetype":"venue"
},
  "geometry": {"coordinates":[-1.672875,55.011494],"type":"Point"}
}