{
  "type": "Feature",
  "properties": {
    "addr:full":"Malt Kiln Farm, Narrow Lane, Halsall Ormskirk Lancashire L39 8RL",
    "addr:postcode":"l39 8rl",
    "addr:street":"Narrow Lane",
    "iso:country":"GB",
    "sg:address":"Malt Kiln Farm, Narrow Lane, Halsall",
    "sg:city":"Ormskirk",
    "sg:classifiers":[
        {
            "category":"Building & Trades",
            "subcategory":"Construction",
            "type":"Services"
        }
    ],
    "sg:phone":"+44 1704 840912",
    "sg:postcode":"L39 8RL",
    "sg:province":"Lancashire",
    "sg:tags":[
        "builder"
    ],
    "wof:name":"Richard Swift Builders & Joiners",
    "wof:placetype":"venue"
},
  "geometry": {"coordinates":[-2.9546189308,53.5842704773],"type":"Point"}
}