{
  "type": "Feature",
  "properties": {
    "addr:full":"Chapel Lane, Great Blakenham Ipswich Suffolk IP6 0JY",
    "addr:postcode":"ip6 0jy",
    "addr:street":"Chapel Lane",
    "iso:country":"GB",
    "sg:address":"Chapel Lane, Great Blakenham",
    "sg:city":"Ipswich",
    "sg:classifiers":[
        {
            "category":"Autos & Motor Vehicles",
            "subcategory":"Auto Supplies",
            "type":"Retail Goods"
        }
    ],
    "sg:phone":"+44 1473 832833",
    "sg:postcode":"IP6 0JY",
    "sg:province":"Suffolk",
    "sg:tags":[
        "equipment",
        "diesel"
    ],
    "wof:name":"E Rand & Sons Ltd.",
    "wof:placetype":"venue"
},
  "geometry": {"coordinates":[1.09703,52.105717],"type":"Point"}
}