{
  "type": "Feature",
  "properties": {
    "iso:country":"GB",
    "sg:address":"30 Benbow Court, Shenley Church End",
    "sg:city":"Milton Keynes",
    "sg:classifiers":[
        {
            "category":"Personal",
            "subcategory":"Beauty Salon",
            "type":"Services"
        }
    ],
    "sg:postcode":"MK5 6JG",
    "sg:province":"Buckinghamshire",
    "sg:tags":[
        "unisex",
        "hairdresser"
    ],
    "wof:name":"Raj Hair Studio",
    "wof:placetype":"venue"
},
  "geometry": {"coordinates":[-0.788749,52.026066],"type":"Point"}
}