{
  "type": "Feature",
  "properties": {
    "addr:full":"Oil Depot, Watleys End Road Bristol Gloucestershire BS36 1PQ",
    "addr:postcode":"bs36 1pq",
    "addr:street":"End Road",
    "iso:country":"GB",
    "sg:address":"Oil Depot, Watleys End Road",
    "sg:city":"Bristol",
    "sg:classifiers":[
        {
            "category":"Utilities",
            "subcategory":"Fuel Oil & Lpg",
            "type":"Services"
        }
    ],
    "sg:phone":"+44 1454 773203",
    "sg:postcode":"BS36 1PQ",
    "sg:province":"Gloucestershire",
    "sg:tags":[
        "distributor"
    ],
    "wof:name":"L C Burt & Son (Fuels) Ltd.",
    "wof:placetype":"venue"
},
  "geometry": {"coordinates":[-2.4931590557,51.5302200317],"type":"Point"}
}