{
  "type": "Feature",
  "properties": {
    "addr:full":"47 Friar Lane Leicester Leicestershire LE1 5QX",
    "addr:housenumber":"47",
    "addr:postcode":"le1 5qx",
    "addr:street":"Friar Lane",
    "iso:country":"GB",
    "sg:address":"47 Friar Lane",
    "sg:city":"Leicester",
    "sg:classifiers":[
        {
            "category":"Professional",
            "subcategory":"Lawyer & Legal Services",
            "type":"Services"
        }
    ],
    "sg:phone":"+44 116 251 7171",
    "sg:postcode":"LE1 5QX",
    "sg:province":"Leicestershire",
    "sg:tags":[
        "solicitor"
    ],
    "wof:name":"Philip J Hammond & Sons Solicitors",
    "wof:placetype":"venue"
},
  "geometry": {"coordinates":[-1.137286,52.632915],"type":"Point"}
}