{
  "type": "Feature",
  "properties": {
    "iso:country":"GB",
    "sg:address":"Haven Road, The Hythe",
    "sg:city":"Colchester",
    "sg:classifiers":[
        {
            "category":"Home & Garden",
            "subcategory":"Kitchen Supply",
            "type":"Retail Goods"
        }
    ],
    "sg:phone":"+44 1206 867770",
    "sg:postcode":"CO2 8HT",
    "sg:province":"Essex",
    "sg:tags":[
        "equipment",
        "catering"
    ],
    "wof:name":"Goldstar Fabrications Ltd.",
    "wof:placetype":"venue"
},
  "geometry": {"coordinates":[0.927023,51.879295],"type":"Point"}
}