{
  "type": "Feature",
  "properties": {
    "addr:full":"7 Langney Road Eastbourne East Sussex BN21 3QA",
    "addr:housenumber":"7",
    "addr:postcode":"bn21 3qa",
    "addr:street":"Langney Road",
    "iso:country":"GB",
    "sg:address":"7 Langney Road",
    "sg:city":"Eastbourne",
    "sg:classifiers":[
        {
            "category":"Retail",
            "subcategory":"Laundry & Dry Cleaning",
            "type":"Services"
        }
    ],
    "sg:phone":"+44 1323 645276",
    "sg:postcode":"BN21 3QA",
    "sg:province":"East Sussex",
    "sg:tags":[
        "alteration"
    ],
    "wof:name":"Express/Regal Dry Cleaners",
    "wof:placetype":"venue"
},
  "geometry": {"coordinates":[0.2873420119,50.7686347961],"type":"Point"}
}