{
  "type": "Feature",
  "properties": {
    "iso:country":"GB",
    "sg:address":"30 Mill Lane, Ryther",
    "sg:city":"Tadcaster",
    "sg:classifiers":[
        {
            "category":"Home & Garden",
            "subcategory":"Carpets & Floor Coverings",
            "type":"Retail Goods"
        }
    ],
    "sg:phone":"+44 1757 268681",
    "sg:postcode":"LS24 9EG",
    "sg:province":"North Yorkshire",
    "sg:tags":[
        "carpets",
        "retailer",
        "rug",
        "matting"
    ],
    "wof:name":"Kenyan Carpets",
    "wof:placetype":"venue"
},
  "geometry": {"coordinates":[-1.165548,53.844917],"type":"Point"}
}