{
  "type": "Feature",
  "properties": {
    "addr:full":"12 Woodfield Street, Morriston Swansea Swansea SA6 8AQ",
    "addr:housenumber":"12",
    "addr:postcode":"sa6 8aq",
    "addr:street":"Woodfield Street",
    "iso:country":"GB",
    "sg:address":"12 Woodfield Street, Morriston",
    "sg:city":"Swansea",
    "sg:classifiers":[
        {
            "category":"Bars & Pubs",
            "type":"Food & Drink"
        }
    ],
    "sg:phone":"+44 1792 411484",
    "sg:postcode":"SA6 8AQ",
    "sg:province":"Swansea",
    "sg:tags":[
        "pubs",
        "inn"
    ],
    "wof:name":"The Fountain Inn",
    "wof:placetype":"venue"
},
  "geometry": {"coordinates":[-3.925156,51.665684],"type":"Point"}
}