{
  "type": "Feature",
  "properties": {
    "addr:full":"9 Lyon Way Glenrothes Fife KY7 5NW",
    "addr:housenumber":"9",
    "addr:postcode":"ky7 5nw",
    "addr:street":"Lyon Way",
    "iso:country":"GB",
    "sg:address":"9 Lyon Way",
    "sg:city":"Glenrothes",
    "sg:classifiers":[
        {
            "category":"Food & Beverages",
            "subcategory":"Bakery",
            "type":"Retail Goods"
        }
    ],
    "sg:phone":"+44 1592 756157",
    "sg:postcode":"KY7 5NW",
    "sg:province":"Fife",
    "sg:tags":[
        "baker"
    ],
    "wof:name":"D S Crawford Ltd",
    "wof:placetype":"venue"
},
  "geometry": {"coordinates":[-3.173744,56.197208],"type":"Point"}
}