{
  "type": "Feature",
  "properties": {
    "iso:country":"GB",
    "sg:address":"Nevassa, Ashwater",
    "sg:city":"Beaworthy",
    "sg:classifiers":[
        {
            "category":"Professional",
            "type":"Services"
        },
        {
            "category":"Banks & Credit Unions",
            "subcategory":"Investment Brokerage",
            "type":"Services"
        }
    ],
    "sg:phone":"+44 1409 211403",
    "sg:postcode":"EX21 5EF",
    "sg:province":"Devon",
    "sg:tags":[
        "farm",
        "agricultural",
        "contractor"
    ],
    "wof:name":"EDWIN DANIEL SHADRICK",
    "wof:placetype":"venue"
},
  "geometry": {"coordinates":[-4.1833848953,50.7753067017],"type":"Point"}
}