{
  "type": "Feature",
  "properties": {
    "addr:full":"Decoy Rd Worthing West Sussex BN14 8ND",
    "addr:postcode":"bn14 8nd",
    "addr:street":"Decoy Rd",
    "iso:country":"GB",
    "sg:address":"Decoy Rd",
    "sg:city":"Worthing",
    "sg:classifiers":[
        {
            "category":"Social Services",
            "type":"Services"
        }
    ],
    "sg:phone":"+44 1903 237733",
    "sg:postcode":"BN14 8ND",
    "sg:province":"West Sussex",
    "sg:tags":[
        "disability"
    ],
    "wof:name":"Pilcher-Greene Europe Ltd",
    "wof:placetype":"venue"
},
  "geometry": {"coordinates":[-0.357804,50.824783],"type":"Point"}
}