{
  "type": "Feature",
  "properties": {
    "addr:full":"Unit G Eagle Clo Southampton Hampshire SO53 4NF",
    "addr:housenumber":"unit g",
    "addr:postcode":"hampshire so53 4nf",
    "iso:country":"GB",
    "sg:address":"Unit G Eagle Clo",
    "sg:city":"Southampton",
    "sg:classifiers":[
        {
            "category":"Retail",
            "subcategory":"Auto Repair",
            "type":"Services"
        }
    ],
    "sg:phone":"+44 23 8025 1188",
    "sg:postcode":"SO53 4NF",
    "sg:province":"Hampshire",
    "sg:tags":[
        "engine"
    ],
    "wof:name":"Engine Express Components Ltd",
    "wof:placetype":"venue"
},
  "geometry": {"coordinates":[-1.3913,50.976212],"type":"Point"}
}