{
  "type": "Feature",
  "properties": {
    "iso:country":"GB",
    "sg:address":"Three Acres, Clapton-on-the-hill",
    "sg:city":"Cheltenham",
    "sg:classifiers":[
        {
            "category":"Building & Trades",
            "subcategory":"Equipment Rental",
            "type":"Services"
        }
    ],
    "sg:phone":"+44 1451 820933",
    "sg:postcode":"GL54 2LG",
    "sg:province":"Gloucestershire",
    "sg:tags":[
        "plant",
        "machinery"
    ],
    "wof:name":"P.E Harding",
    "wof:placetype":"venue"
},
  "geometry": {"coordinates":[-1.7645850182,51.8591918945],"type":"Point"}
}