{
  "type": "Feature",
  "properties": {
    "addr:full":"4 Otley Road, Guiseley Leeds West Yorkshire LS20 8AH",
    "addr:housenumber":"4",
    "addr:postcode":"ls20 8ah",
    "addr:street":"Otley Road",
    "iso:country":"GB",
    "sg:address":"4 Otley Road, Guiseley",
    "sg:city":"Leeds",
    "sg:classifiers":[
        {
            "category":"Wholesale",
            "subcategory":"Apparel",
            "type":"Manufacturing & Wholesale Goods"
        }
    ],
    "sg:phone":"+44 1943 874270",
    "sg:postcode":"LS20 8AH",
    "sg:province":"West Yorkshire",
    "sg:tags":[
        "babywear",
        "childrens"
    ],
    "wof:name":"Wharfedale Textiles",
    "wof:placetype":"venue"
},
  "geometry": {"coordinates":[-1.7092900276,53.8725738525],"type":"Point"}
}