{
  "type": "Feature",
  "properties": {
    "addr:full":"63 Lawrence Road Southsea Hampshire PO5 1NU",
    "addr:housenumber":"63",
    "addr:postcode":"po5 1nu",
    "addr:street":"Lawrence Road",
    "iso:country":"GB",
    "sg:address":"63 Lawrence Road",
    "sg:city":"Southsea",
    "sg:classifiers":[
        {
            "category":"Bars & Pubs",
            "type":"Food & Drink"
        }
    ],
    "sg:phone":"+44 23 9282 1280",
    "sg:postcode":"PO5 1NU",
    "sg:province":"Hampshire",
    "sg:tags":[
        "pubs",
        "inn"
    ],
    "wof:name":"The Lawrence Arms",
    "wof:placetype":"venue"
},
  "geometry": {"coordinates":[-1.0766320229,50.7890472412],"type":"Point"}
}