{
  "type": "Feature",
  "properties": {
    "addr:full":"6 Vine Street Evesham Gloucestershire WR11 4RE",
    "addr:housenumber":"6",
    "addr:postcode":"wr11 4re",
    "addr:street":"Vine Street",
    "iso:country":"GB",
    "sg:address":"6 Vine Street",
    "sg:city":"Evesham",
    "sg:classifiers":[
        {
            "category":"Insurance",
            "subcategory":"Insurance Agent",
            "type":"Services"
        }
    ],
    "sg:phone":"+44 1386 421421",
    "sg:postcode":"WR11 4RE",
    "sg:province":"Gloucestershire",
    "wof:name":"A-Plan Insurance",
    "wof:placetype":"venue"
},
  "geometry": {"coordinates":[-1.948709,52.0919],"type":"Point"}
}