{
  "type": "Feature",
  "properties": {
    "addr:full":"19 Bell View Ebbw Vale Blaenau Gwent NP23 8UT",
    "addr:housenumber":"19",
    "addr:postcode":"np23 8ut",
    "addr:street":"Bell View",
    "iso:country":"GB",
    "sg:address":"19 Bell View",
    "sg:city":"Ebbw Vale",
    "sg:classifiers":[
        {
            "category":"Building & Trades",
            "subcategory":"Plumbing",
            "type":"Services"
        }
    ],
    "sg:phone":"+44 1495 308000",
    "sg:postcode":"NP23 8UT",
    "sg:province":"Blaenau Gwent",
    "sg:tags":[
        "heating"
    ],
    "wof:name":"Wood & Greenland Building & Plumbing",
    "wof:placetype":"venue"
},
  "geometry": {"coordinates":[-3.2146859169,51.7970275879],"type":"Point"}
}