{
  "type": "Feature",
  "properties": {
    "addr:full":"Unit 4 Cae Bach, Builder Street Llandudno Conwy LL30 1DR",
    "addr:housenumber":"unit 4",
    "addr:postcode":"ll30 1dr",
    "addr:street":"Cae Bach Builder Street",
    "iso:country":"GB",
    "sg:address":"Unit 4 Cae Bach, Builder Street",
    "sg:city":"Llandudno",
    "sg:classifiers":[
        {
            "category":"Wholesale",
            "subcategory":"Fruits & Vegetables",
            "type":"Manufacturing & Wholesale Goods"
        }
    ],
    "sg:phone":"+44 1492 877963",
    "sg:postcode":"LL30 1DR",
    "sg:province":"Conwy",
    "wof:name":"M Hughes & Sons",
    "wof:placetype":"venue"
},
  "geometry": {"coordinates":[-3.831372,53.316048],"type":"Point"}
}