{
  "type": "Feature",
  "properties": {
    "addr:full":"23 Claremont Road Seaford East Sussex BN25 2PF",
    "addr:housenumber":"23",
    "addr:postcode":"bn25 2pf",
    "addr:street":"Claremont Road",
    "iso:country":"GB",
    "sg:address":"23 Claremont Road",
    "sg:city":"Seaford",
    "sg:classifiers":[
        {
            "category":"Shopping",
            "subcategory":"News",
            "type":"Retail Goods"
        }
    ],
    "sg:phone":"+44 1323 892569",
    "sg:postcode":"BN25 2PF",
    "sg:province":"East Sussex",
    "sg:tags":[
        "newsagent"
    ],
    "wof:name":"Claremont Road Post Office",
    "wof:placetype":"venue"
},
  "geometry": {"coordinates":[0.088864997,50.7762794495],"type":"Point"}
}