{
  "type": "Feature",
  "properties": {
    "iso:country":"GB",
    "sg:address":"Marshfield Bank Employment Park, Marshfield Bank",
    "sg:city":"Crewe",
    "sg:classifiers":[
        {
            "category":"Autos & Motor Vehicles",
            "subcategory":"Automobile Sales",
            "type":"Retail Goods"
        }
    ],
    "sg:phone":"+44 1270 251212",
    "sg:postcode":"CW2 8UY",
    "sg:province":"Cheshire",
    "sg:tags":[
        "commercial"
    ],
    "wof:name":"Grenson Mitsubishi",
    "wof:placetype":"venue"
},
  "geometry": {"coordinates":[-2.485179,53.096455],"type":"Point"}
}