{
  "type": "Feature",
  "properties": {
    "iso:country":"GB",
    "sg:address":"158 Ashley Rd, Hale",
    "sg:city":"Altrincham",
    "sg:classifiers":[
        {
            "category":"Banks & Credit Unions",
            "subcategory":"Financial Services",
            "type":"Services"
        }
    ],
    "sg:phone":"+44 161 929 9797",
    "sg:postcode":"WA15 9SF",
    "sg:province":"Cheshire",
    "sg:tags":[
        "adviser"
    ],
    "wof:name":"Parkgate Financial Services",
    "wof:placetype":"venue"
},
  "geometry": {"coordinates":[-2.346829,53.377605],"type":"Point"}
}