{
  "type": "Feature",
  "properties": {
    "addr:full":"Idlicote Shipston-on-stour Warwickshire CV36 5DN",
    "addr:postcode":"cv36 5dn",
    "iso:country":"GB",
    "sg:address":"Idlicote",
    "sg:city":"Shipston-on-stour",
    "sg:classifiers":[
        {
            "category":"Farming",
            "subcategory":"Livestock Farm",
            "type":"Manufacturing & Wholesale Goods"
        }
    ],
    "sg:postcode":"CV36 5DN",
    "sg:province":"Warwickshire",
    "sg:tags":[
        "others"
    ],
    "wof:name":"White House Farm",
    "wof:placetype":"venue"
},
  "geometry": {"coordinates":[-1.6138290167,52.1040878296],"type":"Point"}
}