{
  "type": "Feature",
  "properties": {
    "addr:full":"97 The Avenue, Mayfield Ashbourne Derbyshire DE6 2JB",
    "addr:housenumber":"97",
    "addr:postcode":"de6 2jb",
    "addr:street":"The Avenue",
    "iso:country":"GB",
    "sg:address":"97 The Avenue, Mayfield",
    "sg:city":"Ashbourne",
    "sg:classifiers":[
        {
            "category":"Manufacturing",
            "subcategory":"Petroleum Products",
            "type":"Manufacturing & Wholesale Goods"
        }
    ],
    "sg:phone":"+44 1335 342129",
    "sg:postcode":"DE6 2JB",
    "sg:province":"Derbyshire",
    "sg:tags":[
        "double",
        "glazing"
    ],
    "wof:name":"Burford Window Systems",
    "wof:placetype":"venue"
},
  "geometry": {"coordinates":[-1.769299,53.006275],"type":"Point"}
}