{
  "type": "Feature",
  "properties": {
    "iso:country":"GB",
    "sg:address":"28 Bridge Street",
    "sg:city":"Penicuik",
    "sg:classifiers":[
        {
            "category":"Shopping",
            "subcategory":"Department Store",
            "type":"Retail Goods"
        },
        {
            "category":"Transit Center",
            "subcategory":"Freight",
            "type":"Transportation"
        }
    ],
    "sg:phone":"+44 1968 676222",
    "sg:postcode":"EH26 8LN",
    "sg:province":"Midlothian",
    "sg:tags":[
        "shop",
        "craft",
        "centre"
    ],
    "wof:name":"Keepsakes",
    "wof:placetype":"venue"
},
  "geometry": {"coordinates":[-3.221609,55.82468],"type":"Point"}
}