{
  "type": "Feature",
  "properties": {
    "iso:country":"GB",
    "sg:address":"Holden House, Holden Road",
    "sg:city":"Leigh",
    "sg:classifiers":[
        {
            "category":"Professional",
            "subcategory":"Accounting & Tax Preparation",
            "type":"Services"
        }
    ],
    "sg:phone":"+44 1942 608340",
    "sg:postcode":"WN7 1EX",
    "sg:province":"Lancashire",
    "sg:tags":[
        "accountant"
    ],
    "wof:name":"Spot on Book-Keeping Services",
    "wof:placetype":"venue"
},
  "geometry": {"coordinates":[-2.515159,53.500225],"type":"Point"}
}