{
  "type": "Feature",
  "properties": {
    "iso:country":"GB",
    "sg:address":"16 Prestwood Ct, Leacroft Rd",
    "sg:city":"Warrington",
    "sg:classifiers":[
        {
            "category":"Utilities",
            "subcategory":"Telephone",
            "type":"Services"
        }
    ],
    "sg:phone":"+44 1925 852100",
    "sg:postcode":"WA3 6SB",
    "sg:province":"Cheshire",
    "sg:tags":[
        "radio"
    ],
    "wof:name":"Network Radio Communications Ltd",
    "wof:placetype":"venue"
},
  "geometry": {"coordinates":[-2.5057790279,53.4340782166],"type":"Point"}
}