{
  "type": "Feature",
  "properties": {
    "addr:full":"Red House Farm, Morleys Lane, Gislingham Eye Suffolk IP23 8JF",
    "addr:postcode":"ip23 8jf",
    "addr:street":"Morleys Lane",
    "iso:country":"GB",
    "sg:address":"Red House Farm, Morleys Lane, Gislingham",
    "sg:city":"Eye",
    "sg:classifiers":[
        {
            "category":"Farming",
            "subcategory":"Livestock Farm",
            "type":"Manufacturing & Wholesale Goods"
        }
    ],
    "sg:phone":"+44 1449 781384",
    "sg:postcode":"IP23 8JF",
    "sg:province":"Suffolk",
    "sg:tags":[
        "others"
    ],
    "wof:name":"John W Gooderham",
    "wof:placetype":"venue"
},
  "geometry": {"coordinates":[1.0417300463,52.3047561646],"type":"Point"}
}