{
  "type": "Feature",
  "properties": {
    "iso:country":"GB",
    "sg:address":"51 Kershaw Cres, Luddendenfoot",
    "sg:city":"Halifax",
    "sg:classifiers":[
        {
            "category":"Social Services",
            "subcategory":"Adult Care",
            "type":"Services"
        },
        {
            "category":"Government",
            "subcategory":"Office",
            "type":"Public Place"
        }
    ],
    "sg:phone":"+44 1422 882741",
    "sg:postcode":"HX2 6NR",
    "sg:province":"West Yorkshire",
    "sg:tags":[
        "housing",
        "local",
        "sheltered"
    ],
    "wof:name":"Calderdale Metropolitan Borough Council",
    "wof:placetype":"venue"
},
  "geometry": {"coordinates":[-1.944266,53.724564],"type":"Point"}
}