{
  "type": "Feature",
  "properties": {
    "addr:full":"108 Lordship La East Dulwich Greater London SE22 8HF",
    "addr:housenumber":"108",
    "addr:postcode":"se22 8hf",
    "addr:street":"Lordship La East",
    "iso:country":"GB",
    "sg:address":"108 Lordship La",
    "sg:city":"East Dulwich",
    "sg:classifiers":[
        {
            "category":"Organizations",
            "subcategory":"Non-profit Organization",
            "type":"Services"
        }
    ],
    "sg:phone":"+44 20 8299 3733",
    "sg:postcode":"SE22 8HF",
    "sg:province":"Greater London",
    "sg:tags":[
        "organisation",
        "voluntary",
        "charity"
    ],
    "wof:name":"Dulwich Helpline",
    "wof:placetype":"venue"
},
  "geometry": {"coordinates":[-0.0757180005,51.457157135],"type":"Point"}
}