{
  "type": "Feature",
  "properties": {
    "iso:country":"GB",
    "sg:address":"21 Dendy Rd",
    "sg:city":"Paignton",
    "sg:classifiers":[
        {
            "category":"Health Services",
            "subcategory":"Health Practitioner",
            "type":"Services"
        }
    ],
    "sg:phone":"+44 1803 550539",
    "sg:postcode":"TQ4 5DB",
    "sg:province":"Devon",
    "sg:tags":[
        "osteopath"
    ],
    "wof:name":"Riviera Osteopathic Clinic",
    "wof:placetype":"venue"
},
  "geometry": {"coordinates":[-3.566933,50.436104],"type":"Point"}
}