{
  "type": "Feature",
  "properties": {
    "addr:full":"The Old Forge, East Kennet Swindon Berkshire SN8 4EY",
    "addr:postcode":"sn8 4ey",
    "addr:street":"East Kennet",
    "iso:country":"GB",
    "sg:address":"The Old Forge, East Kennet",
    "sg:city":"Swindon",
    "sg:classifiers":[
        {
            "category":"Professional",
            "subcategory":"Art Services",
            "type":"Services"
        }
    ],
    "sg:postcode":"SN8 4EY",
    "sg:province":"Berkshire",
    "sg:tags":[
        "graphic",
        "designer"
    ],
    "wof:name":"Simon Saunders Design",
    "wof:placetype":"venue"
},
  "geometry": {"coordinates":[-1.83095,51.406269],"type":"Point"}
}