{
  "type": "Feature",
  "properties": {
    "addr:full":"172-176 Windermere Avenue Southampton Hampshire SO16 9GA",
    "addr:housenumber":"172-176",
    "addr:postcode":"so16 9ga",
    "addr:street":"Windermere Avenue",
    "iso:country":"GB",
    "sg:address":"172-176 Windermere Avenue",
    "sg:city":"Southampton",
    "sg:classifiers":[
        {
            "category":"Food & Beverages",
            "subcategory":"Supermarket",
            "type":"Retail Goods"
        }
    ],
    "sg:postcode":"SO16 9GA",
    "sg:province":"Hampshire",
    "wof:name":"The Food Barn",
    "wof:placetype":"venue"
},
  "geometry": {"coordinates":[-1.4588979483,50.9303855896],"type":"Point"}
}