{
  "type": "Feature",
  "properties": {
    "iso:country":"GB",
    "sg:address":"Palmerston Street, Westwood",
    "sg:city":"Nottingham",
    "sg:classifiers":[
        {
            "category":"Bars & Pubs",
            "type":"Food & Drink"
        }
    ],
    "sg:phone":"+44 1773 608904",
    "sg:postcode":"NG16 5HY",
    "sg:province":"Derbyshire",
    "sg:tags":[
        "pubs",
        "inn"
    ],
    "wof:name":"D G & K M Johnson",
    "wof:placetype":"venue"
},
  "geometry": {"coordinates":[-1.327117,53.063538],"type":"Point"}
}