{
  "type": "Feature",
  "properties": {
    "iso:country":"GB",
    "sg:address":"101 Loke Road",
    "sg:city":"King's Lynn",
    "sg:classifiers":[
        {
            "category":"Utilities",
            "subcategory":"Fuel Oil & Lpg",
            "type":"Services"
        }
    ],
    "sg:postcode":"PE30 2AZ",
    "sg:province":"Norfolk",
    "wof:name":"Cooks Fuel Merchants",
    "wof:placetype":"venue"
},
  "geometry": {"coordinates":[0.40139,52.759739],"type":"Point"}
}