{
  "type": "Feature",
  "properties": {
    "iso:country":"GB",
    "sg:address":"Care Of Eardley School, Cunliffe Street",
    "sg:city":"London",
    "sg:classifiers":[
        {
            "category":"Education",
            "subcategory":"Preschool",
            "type":"Public Place"
        }
    ],
    "sg:phone":"+44 20 8769 7060",
    "sg:postcode":"SW16 6DS",
    "sg:province":"Greater London",
    "sg:tags":[
        "pre-school",
        "playgroups"
    ],
    "wof:name":"Trojan Kids City",
    "wof:placetype":"venue"
},
  "geometry": {"coordinates":[-0.14105,51.42189],"type":"Point"}
}