{
  "type": "Feature",
  "properties": {
    "addr:full":"Octavian Way, Team Valley Trad Est Gateshead Tyne and Wear NE11 0HZ",
    "addr:postcode":"ne11 0hz",
    "addr:street":"Octavian Way;Est",
    "iso:country":"GB",
    "sg:address":"Octavian Way, Team Valley Trad Est",
    "sg:city":"Gateshead",
    "sg:classifiers":[
        {
            "category":"Professional",
            "subcategory":"Printing & Photocopies",
            "type":"Services"
        }
    ],
    "sg:phone":"+44 191 422 2700",
    "sg:postcode":"NE11 0HZ",
    "sg:province":"Tyne and Wear",
    "sg:tags":[
        "photocopier",
        "copying",
        "duplicating"
    ],
    "wof:name":"United Office Systems Ltd",
    "wof:placetype":"venue"
},
  "geometry": {"coordinates":[-1.6203,54.925461],"type":"Point"}
}