{
  "type": "Feature",
  "properties": {
    "addr:full":"49b Lowthwaite Drive Nelson Lancashire BB9 0SU",
    "addr:housenumber":"49b",
    "addr:postcode":"bb9 0su",
    "addr:street":"Lowthwaite Drive",
    "iso:country":"GB",
    "sg:address":"49b Lowthwaite Drive",
    "sg:city":"Nelson",
    "sg:classifiers":[
        {
            "category":"Building & Trades",
            "subcategory":"Equipment Rental",
            "type":"Services"
        }
    ],
    "sg:phone":"+44 1282 692655",
    "sg:postcode":"BB9 0SU",
    "sg:province":"Lancashire",
    "sg:tags":[
        "plant",
        "machinery"
    ],
    "wof:name":"Shaw's Building Services",
    "wof:placetype":"venue"
},
  "geometry": {"coordinates":[-2.2078518867,53.8260574341],"type":"Point"}
}