{
  "type": "Feature",
  "properties": {
    "iso:country":"GB",
    "sg:address":"Brynglas, Cwmpengraig",
    "sg:city":"Llandysul",
    "sg:classifiers":[
        {
            "category":"Retail",
            "subcategory":"Repair Shop",
            "type":"Services"
        }
    ],
    "sg:phone":"+44 1559 371061",
    "sg:postcode":"SA44 5SS",
    "sg:province":"Carmarthenshire",
    "sg:tags":[
        "sharpening",
        "tool"
    ],
    "wof:name":"Dyfed Saws",
    "wof:placetype":"venue"
},
  "geometry": {"coordinates":[-4.383839,52.04755],"type":"Point"}
}