{
  "type": "Feature",
  "properties": {
    "addr:full":"36 Market Street Stalybridge Greater Manchester SK15 2AJ",
    "addr:housenumber":"36",
    "addr:postcode":"sk15 2aj",
    "addr:street":"Market Street",
    "iso:country":"GB",
    "sg:address":"36 Market Street",
    "sg:city":"Stalybridge",
    "sg:classifiers":[
        {
            "category":"Fast Food",
            "type":"Food & Drink"
        }
    ],
    "sg:phone":"+44 161 303 0304",
    "sg:postcode":"SK15 2AJ",
    "sg:province":"Greater Manchester",
    "sg:tags":[
        "away",
        "take"
    ],
    "wof:name":"British Raj",
    "wof:placetype":"venue"
},
  "geometry": {"coordinates":[-2.060041,53.484222],"type":"Point"}
}