{
  "type": "Feature",
  "properties": {
    "addr:full":"Stanford Rd, Orsett Grays Essex RM16 3BL",
    "addr:postcode":"rm16 3bl",
    "addr:street":"Stanford Rd",
    "iso:country":"GB",
    "sg:address":"Stanford Rd, Orsett",
    "sg:city":"Grays",
    "sg:classifiers":[
        {
            "category":"Restaurant",
            "type":"Food & Drink"
        }
    ],
    "sg:postcode":"RM16 3BL",
    "sg:province":"Essex",
    "wof:name":"Mex-A-Millions",
    "wof:placetype":"venue"
},
  "geometry": {"coordinates":[0.38961,51.507332],"type":"Point"}
}