{
  "type": "Feature",
  "properties": {
    "addr:full":"Unit 58c Mattesons Old Works, Arthur Street, Lakeside Redditch Warwickshire B98 8JY",
    "addr:housenumber":"unit 58c mattesons",
    "addr:postcode":"b98 8jy",
    "addr:street":"Old Works Arthur Street",
    "iso:country":"GB",
    "sg:address":"Unit 58c Mattesons Old Works, Arthur Street, Lakeside",
    "sg:city":"Redditch",
    "sg:classifiers":[
        {
            "category":"Freight",
            "type":"Transportation"
        }
    ],
    "sg:phone":"+44 1527 515055",
    "sg:postcode":"B98 8JY",
    "sg:province":"Warwickshire",
    "sg:tags":[
        "haulage",
        "road"
    ],
    "wof:name":"Go Man Couriers",
    "wof:placetype":"venue"
},
  "geometry": {"coordinates":[-1.92211,52.30373],"type":"Point"}
}