{
  "type": "Feature",
  "properties": {
    "iso:country":"GB",
    "sg:address":"Church Farm, Bobbing",
    "sg:city":"Sittingbourne",
    "sg:classifiers":[
        {
            "category":"Home & Garden",
            "subcategory":"Building Materials",
            "type":"Retail Goods"
        }
    ],
    "sg:postcode":"ME9 8PH",
    "sg:province":"Kent",
    "sg:tags":[
        "fencing"
    ],
    "wof:name":"Haymac Enterprises",
    "wof:placetype":"venue"
},
  "geometry": {"coordinates":[0.706027,51.351292],"type":"Point"}
}