{
  "type": "Feature",
  "properties": {
    "addr:full":"709 Attercliffe Road Sheffield South Yorkshire S9 3RE",
    "addr:housenumber":"709",
    "addr:postcode":"s9 3re",
    "addr:street":"Attercliffe Road",
    "iso:country":"GB",
    "sg:address":"709 Attercliffe Road",
    "sg:city":"Sheffield",
    "sg:classifiers":[
        {
            "category":"Bars & Pubs",
            "type":"Food & Drink"
        }
    ],
    "sg:phone":"+44 114 244 5757",
    "sg:postcode":"S9 3RE",
    "sg:province":"South Yorkshire",
    "sg:tags":[
        "pubs",
        "inn"
    ],
    "wof:name":"The Kings Head",
    "wof:placetype":"venue"
},
  "geometry": {"coordinates":[-1.431231,53.394787],"type":"Point"}
}