{
  "type": "Feature",
  "properties": {
    "iso:country":"GB",
    "sg:address":"8a St John St",
    "sg:city":"Galashiels",
    "sg:classifiers":[
        {
            "category":"Shopping",
            "subcategory":"Clothing, Apparel, & Fashions",
            "type":"Retail Goods"
        }
    ],
    "sg:phone":"+44 1896 752856",
    "sg:postcode":"TD1 3JX",
    "sg:province":"Scottish Borders",
    "sg:tags":[
        "shop"
    ],
    "wof:name":"Abigai's",
    "wof:placetype":"venue"
},
  "geometry": {"coordinates":[-2.8090369701,55.6108703613],"type":"Point"}
}