{
  "type": "Feature",
  "properties": {
    "addr:full":"3 Lavender Park, Swinley Rd Ascot Berkshire SL5 8BD",
    "addr:housenumber":"3",
    "addr:postcode":"sl5 8bd",
    "addr:street":"Lavender Park Swinley Rd",
    "iso:country":"GB",
    "sg:address":"3 Lavender Park, Swinley Rd",
    "sg:city":"Ascot",
    "sg:classifiers":[
        {
            "category":"Professional",
            "subcategory":"Accounting & Tax Preparation",
            "type":"Services"
        }
    ],
    "sg:phone":"+44 1344 886215",
    "sg:postcode":"SL5 8BD",
    "sg:province":"Berkshire",
    "sg:tags":[
        "accountant"
    ],
    "wof:name":"Hugh Jackson",
    "wof:placetype":"venue"
},
  "geometry": {"coordinates":[-0.686438024,51.4282684326],"type":"Point"}
}