{
  "type": "Feature",
  "properties": {
    "addr:full":"233-235 Dalton Road Barrow-in-furness Cumbria LA14 1RS",
    "addr:housenumber":"233-235",
    "addr:postcode":"la14 1rs",
    "addr:street":"Dalton Road",
    "iso:country":"GB",
    "sg:address":"233-235 Dalton Road",
    "sg:city":"Barrow-in-furness",
    "sg:classifiers":[
        {
            "category":"Banks & Credit Unions",
            "subcategory":"Bank",
            "type":"Services"
        }
    ],
    "sg:phone":"+44 845 605 0410",
    "sg:postcode":"LA14 1RS",
    "sg:province":"Cumbria",
    "wof:name":"Halifax Plc",
    "wof:placetype":"venue"
},
  "geometry": {"coordinates":[-3.227366,54.115383],"type":"Point"}
}