{
  "type": "Feature",
  "properties": {
    "addr:full":"50 Alexandra Road Blackpool Lancashire FY1 6BU",
    "addr:housenumber":"50",
    "addr:postcode":"fy1 6bu",
    "addr:street":"Alexandra Road",
    "iso:country":"GB",
    "sg:address":"50 Alexandra Road",
    "sg:city":"Blackpool",
    "sg:classifiers":[
        {
            "category":"Travel",
            "subcategory":"Hotels & Motels",
            "type":"Entertainment"
        }
    ],
    "sg:phone":"+44 1253 345494",
    "sg:postcode":"FY1 6BU",
    "sg:province":"Lancashire",
    "wof:name":"Orlando Hotel",
    "wof:placetype":"venue"
},
  "geometry": {"coordinates":[-3.051793,53.801537],"type":"Point"}
}