{
  "type": "Feature",
  "properties": {
    "iso:country":"GB",
    "sg:address":"1 London St",
    "sg:city":"Reading",
    "sg:classifiers":[
        {
            "category":"Communications",
            "type":"Services"
        }
    ],
    "sg:postcode":"RG1 4PN",
    "sg:province":"Berkshire",
    "sg:tags":[
        "tv",
        "video",
        "radio"
    ],
    "wof:name":"Stareware",
    "wof:placetype":"venue"
},
  "geometry": {"coordinates":[-0.96844,51.454048],"type":"Point"}
}