{
  "type": "Feature",
  "properties": {
    "addr:full":"56 Thornton Street, Kempston Bedford Bedfordshire MK42 8PD",
    "addr:housenumber":"56",
    "addr:postcode":"mk42 8pd",
    "addr:street":"Thornton Street",
    "iso:country":"GB",
    "sg:address":"56 Thornton Street, Kempston",
    "sg:city":"Bedford",
    "sg:classifiers":[
        {
            "category":"Manufacturing",
            "subcategory":"Signs",
            "type":"Manufacturing & Wholesale Goods"
        }
    ],
    "sg:phone":"+44 1234 851211",
    "sg:postcode":"MK42 8PD",
    "sg:province":"Bedfordshire",
    "sg:tags":[
        "writer"
    ],
    "wof:name":"Gilbert and Bell",
    "wof:placetype":"venue"
},
  "geometry": {"coordinates":[-0.485303998,52.1210174561],"type":"Point"}
}