{
  "type": "Feature",
  "properties": {
    "iso:country":"GB",
    "sg:address":"1 Queen Street, Shepshed",
    "sg:city":"Loughborough",
    "sg:classifiers":[
        {
            "category":"Professional",
            "subcategory":"Accounting & Tax Preparation",
            "type":"Services"
        }
    ],
    "sg:postcode":"LE12 9RZ",
    "sg:province":"Leicestershire",
    "sg:tags":[
        "accountant"
    ],
    "wof:name":"E A H Ltd.",
    "wof:placetype":"venue"
},
  "geometry": {"coordinates":[-1.289955,52.77177],"type":"Point"}
}