{
  "type": "Feature",
  "properties": {
    "addr:full":"Church Farm High Street, Collingbourne Ducis Marlborough Berkshire SN8 3EQ",
    "addr:postcode":"sn8 3eq",
    "addr:street":"High Street",
    "iso:country":"GB",
    "sg:address":"Church Farm High Street, Collingbourne Ducis",
    "sg:city":"Marlborough",
    "sg:classifiers":[
        {
            "category":"Freight",
            "type":"Transportation"
        }
    ],
    "sg:postcode":"SN8 3EQ",
    "sg:province":"Berkshire",
    "sg:tags":[
        "haulage",
        "road"
    ],
    "wof:name":"Colin J Bale & Sons Ltd.",
    "wof:placetype":"venue"
},
  "geometry": {"coordinates":[-1.6516100168,51.2836799622],"type":"Point"}
}