{
  "type": "Feature",
  "properties": {
    "iso:country":"GB",
    "sg:address":"39 Barrow Hill Road",
    "sg:city":"London",
    "sg:classifiers":[
        {
            "category":"Shopping",
            "subcategory":"News",
            "type":"Retail Goods"
        }
    ],
    "sg:phone":"+44 20 7722 4395",
    "sg:postcode":"NW8 7AH",
    "sg:province":"Greater London",
    "sg:tags":[
        "newsagent"
    ],
    "wof:name":"Azan Enterprises",
    "wof:placetype":"venue"
},
  "geometry": {"coordinates":[-0.168798998,51.5324134827],"type":"Point"}
}