{
  "type": "Feature",
  "properties": {
    "addr:full":"2 Church Lane Stevenage Hertfordshire SG1 3QR",
    "addr:housenumber":"2",
    "addr:postcode":"sg1 3qr",
    "addr:street":"Church Lane",
    "iso:country":"GB",
    "sg:address":"2 Church Lane",
    "sg:city":"Stevenage",
    "sg:classifiers":[
        {
            "category":"Insurance",
            "subcategory":"Insurance Agent",
            "type":"Services"
        }
    ],
    "sg:phone":"+44 1438 728686",
    "sg:postcode":"SG1 3QR",
    "sg:province":"Hertfordshire",
    "sg:tags":[
        "broker"
    ],
    "wof:name":"Tangent Insurance Brokers",
    "wof:placetype":"venue"
},
  "geometry": {"coordinates":[-0.2067440003,51.9129142761],"type":"Point"}
}