{
  "type": "Feature",
  "properties": {
    "addr:full":"43 Shenley Road Borehamwood Hertfordshire WD6 1AE",
    "addr:housenumber":"43",
    "addr:postcode":"wd6 1ae",
    "addr:street":"Shenley Road",
    "iso:country":"GB",
    "sg:address":"43 Shenley Road",
    "sg:city":"Borehamwood",
    "sg:classifiers":[
        {
            "category":"Professional",
            "type":"Services"
        }
    ],
    "sg:phone":"+44 20 8953 0443",
    "sg:postcode":"WD6 1AE",
    "sg:province":"Hertfordshire",
    "sg:tags":[
        "caterer"
    ],
    "wof:name":"Sea World Ltd.",
    "wof:placetype":"venue"
},
  "geometry": {"coordinates":[-0.27743,51.655163],"type":"Point"}
}