{
  "type": "Feature",
  "properties": {
    "iso:country":"GB",
    "sg:address":"2 Hamberts Road, Blackall Industrial Estate, South Woodham Ferrers",
    "sg:city":"Chelmsford",
    "sg:classifiers":[
        {
            "category":"Manufacturing",
            "subcategory":"Rubber & Plastics",
            "type":"Manufacturing & Wholesale Goods"
        }
    ],
    "sg:phone":"+44 1452 316500",
    "sg:postcode":"CM3 5ND",
    "sg:province":"Essex",
    "sg:tags":[
        "product"
    ],
    "wof:name":"Cookson Plastic Europe",
    "wof:placetype":"venue"
},
  "geometry": {"coordinates":[0.62176,51.651588],"type":"Point"}
}