{
  "type": "Feature",
  "properties": {
    "addr:full":"2nd Floor, Wycliffe House, 245 Cranbrook Road Ilford Essex IG1 4TD",
    "addr:housenumber":"2nd floor wycliffe;245",
    "addr:postcode":"ig1 4td",
    "addr:street":"Cranbrook Road",
    "iso:country":"GB",
    "sg:address":"2nd Floor, Wycliffe House, 245 Cranbrook Road",
    "sg:city":"Ilford",
    "sg:classifiers":[
        {
            "category":"Professional",
            "subcategory":"Accounting & Tax Preparation",
            "type":"Services"
        }
    ],
    "sg:phone":"+44 20 8554 4904",
    "sg:postcode":"IG1 4TD",
    "sg:province":"Essex",
    "sg:tags":[
        "accountant",
        "activity"
    ],
    "wof:name":"Peter Hubbard",
    "wof:placetype":"venue"
},
  "geometry": {"coordinates":[0.0672670007,51.5635032654],"type":"Point"}
}