{
  "type": "Feature",
  "properties": {
    "addr:full":"Calamankey, Longdowns Penryn Cornwall TR10 9DL",
    "addr:postcode":"tr10 9dl",
    "iso:country":"GB",
    "sg:address":"Calamankey, Longdowns",
    "sg:city":"Penryn",
    "sg:classifiers":[
        {
            "category":"Recreation",
            "subcategory":"Campground",
            "type":"Entertainment"
        }
    ],
    "sg:phone":"+44 1209 860314",
    "sg:postcode":"TR10 9DL",
    "sg:province":"Cornwall",
    "sg:tags":[
        "site",
        "camping"
    ],
    "wof:name":"Calamankey Farm Camp Site",
    "wof:placetype":"venue"
},
  "geometry": {"coordinates":[-5.1585998535,50.1640281677],"type":"Point"}
}