{
  "type": "Feature",
  "properties": {
    "addr:full":"Orrells Well Fm, Foden Lane Alderley Edge Cheshire SK9 7TH",
    "addr:postcode":"sk9 7th",
    "addr:street":"Foden Lane",
    "iso:country":"GB",
    "sg:address":"Orrells Well Fm, Foden Lane",
    "sg:city":"Alderley Edge",
    "sg:classifiers":[
        {
            "category":"Farming",
            "subcategory":"Livestock Farm",
            "type":"Manufacturing & Wholesale Goods"
        }
    ],
    "sg:phone":"+44 1625 582372",
    "sg:postcode":"SK9 7TH",
    "sg:province":"Cheshire",
    "sg:tags":[
        "others"
    ],
    "wof:name":"F Clayton",
    "wof:placetype":"venue"
},
  "geometry": {"coordinates":[-2.236334,53.302807],"type":"Point"}
}