{
  "type": "Feature",
  "properties": {
    "addr:full":"13 Astwood Mews London Greater London SW7 4DE",
    "addr:housenumber":"13",
    "addr:postcode":"sw7 4de",
    "addr:street":"Astwood Mews",
    "iso:country":"GB",
    "sg:address":"13 Astwood Mews",
    "sg:city":"London",
    "sg:classifiers":[
        {
            "category":"Retail",
            "subcategory":"Auto Repair",
            "type":"Services"
        }
    ],
    "sg:postcode":"SW7 4DE",
    "sg:province":"Greater London",
    "sg:tags":[
        "modification",
        "garage"
    ],
    "wof:name":"Able Engineering",
    "wof:placetype":"venue"
},
  "geometry": {"coordinates":[-0.1865009964,51.4938926697],"type":"Point"}
}