{
  "type": "Feature",
  "properties": {
    "iso:country":"GB",
    "sg:address":"149b Nightingale Road",
    "sg:city":"Derby",
    "sg:classifiers":[
        {
            "category":"Personal",
            "subcategory":"Beauty Salon",
            "type":"Services"
        },
        {
            "category":"Personal",
            "subcategory":"Barber",
            "type":"Services"
        }
    ],
    "sg:phone":"+44 1332 362534",
    "sg:postcode":"DE24 8BH",
    "sg:province":"Derbyshire",
    "sg:tags":[
        "unisex",
        "hairdresser"
    ],
    "wof:name":"Coopers Hair Studio",
    "wof:placetype":"venue"
},
  "geometry": {"coordinates":[-1.460953,52.897018],"type":"Point"}
}