{
  "type": "Feature",
  "properties": {
    "addr:full":"Pye Hill House, Jubilee Road Wokingham Berkshire RG40 3RU",
    "addr:postcode":"rg40 3ru",
    "addr:street":"Pye;Jubilee Road",
    "iso:country":"GB",
    "sg:address":"Pye Hill House, Jubilee Road",
    "sg:city":"Wokingham",
    "sg:classifiers":[
        {
            "category":"Retail",
            "subcategory":"Auto Repair",
            "type":"Services"
        }
    ],
    "sg:postcode":"RG40 3RU",
    "sg:province":"Berkshire",
    "sg:tags":[
        "body",
        "car"
    ],
    "wof:name":"J F Tyrrell",
    "wof:placetype":"venue"
},
  "geometry": {"coordinates":[-0.8561369777,51.3704109192],"type":"Point"}
}