{
  "type": "Feature",
  "properties": {
    "iso:country":"GB",
    "sg:address":"Unit 4, Harold Park Farm, Bumbles Grn",
    "sg:city":"Waltham Abbey",
    "sg:classifiers":[
        {
            "category":"Building & Trades",
            "subcategory":"Construction",
            "type":"Services"
        }
    ],
    "sg:phone":"+44 1992 892479",
    "sg:postcode":"EN9 2SA",
    "sg:province":"Essex",
    "sg:tags":[
        "joiner",
        "carpenter"
    ],
    "wof:name":"Rann Joinery",
    "wof:placetype":"venue"
},
  "geometry": {"coordinates":[0.00149,51.68642],"type":"Point"}
}