{
  "type": "Feature",
  "properties": {
    "iso:country":"GB",
    "sg:address":"29 Ridgeway Road",
    "sg:city":"Newton Abbot",
    "sg:classifiers":[
        {
            "category":"Organizations",
            "subcategory":"Non-profit Organization",
            "type":"Services"
        }
    ],
    "sg:postcode":"TQ12 4LS",
    "sg:province":"Devon",
    "sg:tags":[
        "organisation",
        "voluntary",
        "charity"
    ],
    "wof:name":"Multiple Sclerosis Society of Great Britain & Northern Ireland",
    "wof:placetype":"venue"
},
  "geometry": {"coordinates":[-3.5860950947,50.5197181702],"type":"Point"}
}