{
  "type": "Feature",
  "properties": {
    "iso:country":"GB",
    "sg:address":"529 Buxton Rd",
    "sg:city":"Stockport",
    "sg:classifiers":[
        {
            "category":"Building & Trades",
            "subcategory":"Construction",
            "type":"Services"
        }
    ],
    "sg:phone":"+44 161 487 3505",
    "sg:postcode":"SK2 7HJ",
    "sg:province":"Cheshire",
    "sg:tags":[
        "dry",
        "lining",
        "plasterers",
        "screeders"
    ],
    "wof:name":"A J Plasterers & Bricklayers",
    "wof:placetype":"venue"
},
  "geometry": {"coordinates":[-2.130519,53.386219],"type":"Point"}
}