{
  "type": "Feature",
  "properties": {
    "iso:country":"GB",
    "sg:address":"Avondale Business Center, Woodland Way",
    "sg:city":"Bristol",
    "sg:classifiers":[
        {
            "category":"Professional",
            "type":"Services"
        }
    ],
    "sg:postcode":"BS15 1AW",
    "sg:province":"City of Bristol",
    "sg:tags":[
        "archaeologist"
    ],
    "wof:name":"Avon Archaeological Unit",
    "wof:placetype":"venue"
},
  "geometry": {"coordinates":[-2.515534,51.471107],"type":"Point"}
}