{
  "type": "Feature",
  "properties": {
    "addr:full":"46 Whitburn Street Bridgnorth Shropshire WV16 4QT",
    "addr:housenumber":"46",
    "addr:postcode":"wv16 4qt",
    "addr:street":"Whitburn Street",
    "iso:country":"GB",
    "sg:address":"46 Whitburn Street",
    "sg:city":"Bridgnorth",
    "sg:classifiers":[
        {
            "category":"Travel",
            "subcategory":"Travel Agent",
            "type":"Entertainment"
        }
    ],
    "sg:postcode":"WV16 4QT",
    "sg:province":"Shropshire",
    "wof:name":"Bridgnorth Travel Centre",
    "wof:placetype":"venue"
},
  "geometry": {"coordinates":[-2.423871,52.535526],"type":"Point"}
}