{
  "type": "Feature",
  "properties": {
    "addr:full":"Alexandra Road Windermere Cumbria LA23 2DA",
    "addr:postcode":"la23 2da",
    "addr:street":"Alexandra Road",
    "iso:country":"GB",
    "sg:address":"Alexandra Road",
    "sg:city":"Windermere",
    "sg:classifiers":[
        {
            "category":"Building & Trades",
            "subcategory":"Construction",
            "type":"Services"
        }
    ],
    "sg:phone":"+44 15394 45836",
    "sg:postcode":"LA23 2DA",
    "sg:province":"Cumbria",
    "sg:tags":[
        "builder"
    ],
    "wof:name":"W Postlethwaite & Sons",
    "wof:placetype":"venue"
},
  "geometry": {"coordinates":[-2.905689,54.373718],"type":"Point"}
}