{
  "type": "Feature",
  "properties": {
    "addr:full":"37 Skylark Walk Chelmsford Essex CM2 8BA",
    "addr:housenumber":"37",
    "addr:postcode":"cm2 8ba",
    "addr:street":"Skylark Walk",
    "iso:country":"GB",
    "sg:address":"37 Skylark Walk",
    "sg:city":"Chelmsford",
    "sg:classifiers":[
        {
            "category":"Building & Trades",
            "subcategory":"Cleaning & Sanitation",
            "type":"Services"
        }
    ],
    "sg:phone":"+44 1245 355655",
    "sg:postcode":"CM2 8BA",
    "sg:province":"Essex",
    "sg:tags":[
        "computer",
        "telephone"
    ],
    "wof:name":"Professional Touch Regional",
    "wof:placetype":"venue"
},
  "geometry": {"coordinates":[0.4722940028,51.7124671936],"type":"Point"}
}