{
  "type": "Feature",
  "properties": {
    "addr:full":"Unit 4 St Andrews Technology Cen St Andrews Fife KY16 9EA",
    "addr:housenumber":"unit 4",
    "addr:postcode":"ky16 9ea",
    "addr:street":"St Andrews;Cen",
    "iso:country":"GB",
    "sg:address":"Unit 4 St Andrews Technology Cen",
    "sg:city":"St Andrews",
    "sg:classifiers":[
        {
            "category":"Utilities",
            "subcategory":"Mobile Phone",
            "type":"Services"
        },
        {
            "category":"Professional",
            "subcategory":"Business Services",
            "type":"Services"
        }
    ],
    "sg:postcode":"KY16 9EA",
    "sg:province":"Fife",
    "sg:tags":[
        "coding",
        "code",
        "bar"
    ],
    "wof:name":"Easyreader (Uk)",
    "wof:placetype":"venue"
},
  "geometry": {"coordinates":[-2.7961940765,56.3393096924],"type":"Point"}
}