{
  "type": "Feature",
  "properties": {
    "iso:country":"GB",
    "sg:address":"Newbridge Works, Whitting Valley Road, Old Whittington",
    "sg:city":"Chesterfield",
    "sg:classifiers":[
        {
            "category":"Manufacturing",
            "subcategory":"Metals",
            "type":"Manufacturing & Wholesale Goods"
        }
    ],
    "sg:phone":"+44 1246 454444",
    "sg:postcode":"S41 9EY",
    "sg:province":"Derbyshire",
    "sg:tags":[
        "steel",
        "fabricator",
        "erectors"
    ],
    "wof:name":"Glapwell Contracting Services Ltd.",
    "wof:placetype":"venue"
},
  "geometry": {"coordinates":[-1.426999,53.266666],"type":"Point"}
}