{
  "type": "Feature",
  "properties": {
    "addr:full":"West Eagle, Seahome Road Mablethorpe Lincolnshire LN12 2NX",
    "addr:postcode":"ln12 2nx",
    "addr:street":"West;Seahome Road",
    "iso:country":"GB",
    "sg:address":"West Eagle, Seahome Road",
    "sg:city":"Mablethorpe",
    "sg:classifiers":[
        {
            "category":"Building & Trades",
            "subcategory":"Construction",
            "type":"Services"
        }
    ],
    "sg:phone":"+44 1507 473742",
    "sg:postcode":"LN12 2NX",
    "sg:province":"Lincolnshire",
    "sg:tags":[
        "decorator",
        "painter"
    ],
    "wof:name":"Devlin Decorators",
    "wof:placetype":"venue"
},
  "geometry": {"coordinates":[0.2581970096,53.3406677246],"type":"Point"}
}