{
  "type": "Feature",
  "properties": {
    "addr:full":"11 Market Arc, High St Newport East Riding of Yorkshire NP9 1FS",
    "addr:housenumber":"11",
    "addr:postcode":"np9 1fs",
    "addr:street":"Market Arc High St",
    "iso:country":"GB",
    "sg:address":"11 Market Arc, High St",
    "sg:city":"Newport",
    "sg:classifiers":[
        {
            "category":"Professional",
            "subcategory":"Management & Consulting",
            "type":"Services"
        }
    ],
    "sg:phone":"+44 1633 263366",
    "sg:postcode":"NP9 1FS",
    "sg:province":"East Riding of Yorkshire",
    "sg:tags":[
        "music"
    ],
    "wof:name":"Just Us Record Distribution Ltd",
    "wof:placetype":"venue"
},
  "geometry": {"coordinates":[-2.9971940517,51.5893325806],"type":"Point"}
}