{
  "type": "Feature",
  "properties": {
    "iso:country":"GB",
    "sg:address":"Forty Hill",
    "sg:city":"Enfield",
    "sg:classifiers":[
        {
            "category":"Education",
            "subcategory":"School",
            "type":"Public Place"
        },
        {
            "category":"Government",
            "subcategory":"Office",
            "type":"Public Place"
        }
    ],
    "sg:phone":"+44 20 8363 0760",
    "sg:postcode":"EN2 9EY",
    "sg:province":"Greater London",
    "sg:tags":[
        "local",
        "authority"
    ],
    "wof:name":"Forty Hill C of E Primary School",
    "wof:placetype":"venue"
},
  "geometry": {"coordinates":[-0.0610300004,51.6709213257],"type":"Point"}
}