{
  "type": "Feature",
  "properties": {
    "addr:full":"210 High Street Brentford Greater London TW8 8AH",
    "addr:housenumber":"210",
    "addr:postcode":"tw8 8ah",
    "addr:street":"High Street",
    "iso:country":"GB",
    "sg:address":"210 High Street",
    "sg:city":"Brentford",
    "sg:classifiers":[
        {
            "category":"Shopping",
            "subcategory":"Clothing, Apparel, & Fashions",
            "type":"Retail Goods"
        }
    ],
    "sg:phone":"+44 20 8568 5179",
    "sg:postcode":"TW8 8AH",
    "sg:province":"Greater London",
    "sg:tags":[
        "shop"
    ],
    "wof:name":"Riaz Dar",
    "wof:placetype":"venue"
},
  "geometry": {"coordinates":[-0.3080570102,51.4833221436],"type":"Point"}
}