{
  "type": "Feature",
  "properties": {
    "iso:country":"GB",
    "sg:address":"Quaker Clo",
    "sg:city":"Nuneaton",
    "sg:classifiers":[
        {
            "category":"Bus Charters",
            "type":"Transportation"
        }
    ],
    "sg:phone":"+44 1827 717191",
    "sg:postcode":"CV13 6BS",
    "sg:province":"Leicestershire",
    "sg:tags":[
        "hire",
        "coach"
    ],
    "wof:name":"Whitewings Travel",
    "wof:placetype":"venue"
},
  "geometry": {"coordinates":[-1.4828360081,52.5688438416],"type":"Point"}
}