{
  "type": "Feature",
  "properties": {
    "addr:full":"31 Meadow Rd Gravesend Kent DA11 7LR",
    "addr:housenumber":"31",
    "addr:postcode":"da11 7lr",
    "addr:street":"Meadow Rd",
    "iso:country":"GB",
    "sg:address":"31 Meadow Rd",
    "sg:city":"Gravesend",
    "sg:classifiers":[
        {
            "category":"Real Estate",
            "subcategory":"Architect",
            "type":"Services"
        }
    ],
    "sg:phone":"+44 1474 534289",
    "sg:postcode":"DA11 7LR",
    "sg:province":"Kent",
    "wof:name":"P.W Gladwell",
    "wof:placetype":"venue"
},
  "geometry": {"coordinates":[0.363083005,51.4288597107],"type":"Point"}
}