{
  "type": "Feature",
  "properties": {
    "addr:full":"80 St Johns Road, Waterloo Liverpool Merseyside L22 9QQ",
    "addr:housenumber":"80",
    "addr:postcode":"l22 9qq",
    "addr:street":"St Johns Road",
    "iso:country":"GB",
    "sg:address":"80 St Johns Road, Waterloo",
    "sg:city":"Liverpool",
    "sg:classifiers":[
        {
            "category":"Personal",
            "subcategory":"Beauty Salon",
            "type":"Services"
        }
    ],
    "sg:postcode":"L22 9QQ",
    "sg:province":"Merseyside",
    "sg:tags":[
        "unisex",
        "hairdresser"
    ],
    "wof:name":"Anthony Keith Hair Salon",
    "wof:placetype":"venue"
},
  "geometry": {"coordinates":[-3.0249071121,53.4790763855],"type":"Point"}
}