{
  "type": "Feature",
  "properties": {
    "addr:full":"38 Kimpton Road, Kimpton Industrial Estate Sutton Surrey SM3 9QD",
    "addr:housenumber":"38",
    "addr:postcode":"sm3 9qd",
    "addr:street":"Kimpton Road;Industrial Estate",
    "iso:country":"GB",
    "sg:address":"38 Kimpton Road, Kimpton Industrial Estate",
    "sg:city":"Sutton",
    "sg:classifiers":[
        {
            "category":"Building & Trades",
            "subcategory":"Plumbing",
            "type":"Services"
        }
    ],
    "sg:postcode":"SM3 9QD",
    "sg:province":"Surrey",
    "sg:tags":[
        "heating"
    ],
    "wof:name":"First Fix Maintenance U K",
    "wof:placetype":"venue"
},
  "geometry": {"coordinates":[-0.2096190006,51.3763389587],"type":"Point"}
}