{
  "type": "Feature",
  "properties": {
    "addr:full":"Freshwater Library, 41 School Green Road Freshwater Isle of Wight PO40 9AP",
    "addr:housenumber":"41",
    "addr:postcode":"po40 9ap",
    "addr:street":"School Green Road",
    "iso:country":"GB",
    "sg:address":"Freshwater Library, 41 School Green Road",
    "sg:city":"Freshwater",
    "sg:classifiers":[
        {
            "category":"Education",
            "subcategory":"Library",
            "type":"Public Place"
        },
        {
            "category":"Government",
            "subcategory":"Office",
            "type":"Public Place"
        }
    ],
    "sg:phone":"+44 1983 752377",
    "sg:postcode":"PO40 9AP",
    "sg:province":"Isle of Wight",
    "sg:tags":[
        "book",
        "local"
    ],
    "sg:website":"http://www.iwight.com/freshwaterlibrary",
    "wof:name":"Freshwater Library",
    "wof:placetype":"venue"
},
  "geometry": {"coordinates":[-1.522962,50.682461],"type":"Point"}
}