{
  "type": "Feature",
  "properties": {
    "iso:country":"GB",
    "sg:address":"15 Alway Avenue",
    "sg:city":"Epsom",
    "sg:classifiers":[
        {
            "category":"Professional",
            "subcategory":"Business Services",
            "type":"Services"
        }
    ],
    "sg:phone":"+44 20 8873 0522",
    "sg:postcode":"KT19 9JY",
    "sg:province":"Surrey",
    "sg:tags":[
        "assessment",
        "quality"
    ],
    "wof:name":"J A S Consultancy Services",
    "wof:placetype":"venue"
},
  "geometry": {"coordinates":[-0.271149,51.363331],"type":"Point"}
}