{
  "type": "Feature",
  "properties": {
    "addr:full":"Dovehill Court, 163-179 Gallowgate Glasgow Glasgow City G1 5ED",
    "addr:housenumber":"163-179",
    "addr:postcode":"g1 5ed",
    "addr:street":"Gallowgate",
    "iso:country":"GB",
    "sg:address":"Dovehill Court, 163-179 Gallowgate",
    "sg:city":"Glasgow",
    "sg:classifiers":[
        {
            "category":"Shopping",
            "subcategory":"Clothing, Apparel, & Fashions",
            "type":"Retail Goods"
        }
    ],
    "sg:phone":"+44 141 552 5101",
    "sg:postcode":"G1 5ED",
    "sg:province":"Glasgow City",
    "sg:tags":[
        "lady",
        "fashionwear",
        "ladieswear"
    ],
    "wof:name":"Reeta Fashions",
    "wof:placetype":"venue"
},
  "geometry": {"coordinates":[-4.2390041351,55.8557701111],"type":"Point"}
}