{
  "type": "Feature",
  "properties": {
    "addr:full":"Spinkwell Mills, Bradford Rd Dewsbury West Yorkshire WF13 2DR",
    "addr:postcode":"wf13 2dr",
    "addr:street":"Bradford Rd",
    "iso:country":"GB",
    "sg:address":"Spinkwell Mills, Bradford Rd",
    "sg:city":"Dewsbury",
    "sg:classifiers":[
        {
            "category":"Home & Garden",
            "subcategory":"Furniture",
            "type":"Retail Goods"
        }
    ],
    "sg:phone":"+44 1924 466461",
    "sg:postcode":"WF13 2DR",
    "sg:province":"West Yorkshire",
    "wof:name":"F A South & Co",
    "wof:placetype":"venue"
},
  "geometry": {"coordinates":[-1.631109,53.691605],"type":"Point"}
}