{
  "type": "Feature",
  "properties": {
    "addr:full":"Davey Road Corby Northamptonshire NN17 5XX",
    "addr:postcode":"nn17 5xx",
    "addr:street":"Davey Road",
    "iso:country":"GB",
    "sg:address":"Davey Road",
    "sg:city":"Corby",
    "sg:classifiers":[
        {
            "category":"Home & Garden",
            "subcategory":"Building Materials",
            "type":"Retail Goods"
        },
        {
            "category":"Manufacturing",
            "subcategory":"Building Materials",
            "type":"Manufacturing & Wholesale Goods"
        }
    ],
    "sg:phone":"+44 1536 408400",
    "sg:postcode":"NN17 5XX",
    "sg:province":"Northamptonshire",
    "sg:tags":[
        "manufacture",
        "concrete",
        "mortar",
        "mixed",
        "ready",
        "distribution"
    ],
    "wof:name":"The Concrete Co",
    "wof:placetype":"venue"
},
  "geometry": {"coordinates":[-0.7026,52.485977],"type":"Point"}
}