{
  "type": "Feature",
  "properties": {
    "iso:country":"GB",
    "sg:address":"19-27 West Borough",
    "sg:city":"Wimborne",
    "sg:classifiers":[
        {
            "category":"Arts & Performance",
            "subcategory":"Theater",
            "type":"Entertainment"
        }
    ],
    "sg:phone":"+44 1202 849103",
    "sg:postcode":"BH21 1LT",
    "sg:province":"Dorset",
    "sg:tags":[
        "hall",
        "theatre",
        "concert"
    ],
    "wof:name":"Tivmanco Ltd.",
    "wof:placetype":"venue"
},
  "geometry": {"coordinates":[-1.988752,50.801044],"type":"Point"}
}