{
  "type": "Feature",
  "properties": {
    "addr:full":"14 Woodford Road, Bramhall Stockport Cheshire SK7 1LL",
    "addr:housenumber":"14",
    "addr:postcode":"sk7 1ll",
    "addr:street":"Woodford Road",
    "iso:country":"GB",
    "sg:address":"14 Woodford Road, Bramhall",
    "sg:city":"Stockport",
    "sg:classifiers":[
        {
            "category":"Banks & Credit Unions",
            "subcategory":"Bank",
            "type":"Services"
        }
    ],
    "sg:phone":"+44 161 251 3000",
    "sg:postcode":"SK7 1LL",
    "sg:province":"Cheshire",
    "sg:tags":[
        "financial",
        "institution"
    ],
    "wof:name":"BARCLAYS BANK PLC",
    "wof:placetype":"venue"
},
  "geometry": {"coordinates":[-2.1657440662,53.3567848206],"type":"Point"}
}