{
  "type": "Feature",
  "properties": {
    "iso:country":"GB",
    "sg:address":"17 Follaton, Plymouth Road",
    "sg:city":"Totnes",
    "sg:classifiers":[
        {
            "category":"Building & Trades",
            "subcategory":"Construction",
            "type":"Services"
        }
    ],
    "sg:phone":"+44 1803 862469",
    "sg:postcode":"TQ9 5NB",
    "sg:province":"Devon",
    "sg:tags":[
        "joiner",
        "carpenter"
    ],
    "wof:name":"A J Cater",
    "wof:placetype":"venue"
},
  "geometry": {"coordinates":[-3.688092947,50.4341468811],"type":"Point"}
}