{
  "type": "Feature",
  "properties": {
    "iso:country":"GB",
    "sg:address":"Unit 6 Lochlands Industrial Estate",
    "sg:city":"Larbert",
    "sg:classifiers":[
        {
            "category":"Building & Trades",
            "subcategory":"Electrical",
            "type":"Services"
        }
    ],
    "sg:phone":"+44 1324 553025",
    "sg:postcode":"FK5 3NS",
    "sg:province":"Falkirk",
    "sg:tags":[
        "consultant",
        "lighting"
    ],
    "wof:name":"Lightways (Contractors) Ltd.",
    "wof:placetype":"venue"
},
  "geometry": {"coordinates":[-3.8243689537,56.0243835449],"type":"Point"}
}