{
  "type": "Feature",
  "properties": {
    "addr:full":"Units 23-29 Upper Mall, Market Place Bolton Lancashire BL1 2AL",
    "addr:housenumber":"units 23-29",
    "addr:postcode":"bl1 2al",
    "addr:street":"Upper Mall Market Place",
    "iso:country":"GB",
    "sg:address":"Units 23-29 Upper Mall, Market Place",
    "sg:city":"Bolton",
    "sg:classifiers":[
        {
            "category":"Shopping",
            "subcategory":"Optician",
            "type":"Retail Goods"
        }
    ],
    "sg:phone":"+44 1204 532323",
    "sg:postcode":"BL1 2AL",
    "sg:province":"Lancashire",
    "sg:tags":[
        "ophthalmic"
    ],
    "sg:website":"http://www.visionexpress.com",
    "wof:name":"Vision Express (Uk) Ltd",
    "wof:placetype":"venue"
},
  "geometry": {"coordinates":[-2.426594,53.578289],"type":"Point"}
}