{
  "type": "Feature",
  "properties": {
    "iso:country":"GB",
    "sg:address":"209a High Street",
    "sg:city":"Dalbeattie",
    "sg:classifiers":[
        {
            "category":"Personal",
            "subcategory":"Beauty Salon",
            "type":"Services"
        },
        {
            "category":"Personal",
            "subcategory":"Barber",
            "type":"Services"
        }
    ],
    "sg:phone":"+44 1556 611300",
    "sg:postcode":"DG5 4DW",
    "sg:province":"Dumfries and Galloway",
    "sg:tags":[
        "unisex",
        "hairdresser"
    ],
    "wof:name":"Power Cuts",
    "wof:placetype":"venue"
},
  "geometry": {"coordinates":[-3.8194160461,54.9281272888],"type":"Point"}
}