{
  "type": "Feature",
  "properties": {
    "addr:full":"Brockhill Lane, Norton Barracks Norton Worcester Worcestershire WR5 2PP",
    "addr:housenumber":"barracks",
    "addr:postcode":"wr5 2pp",
    "addr:street":"Brockhill Lane",
    "iso:country":"GB",
    "sg:address":"Brockhill Lane, Norton Barracks Norton",
    "sg:city":"Worcester",
    "sg:classifiers":[
        {
            "category":"Arena",
            "subcategory":"Sports Club",
            "type":"Entertainment"
        }
    ],
    "sg:postcode":"WR5 2PP",
    "sg:province":"Worcestershire",
    "wof:name":"Worcester Norton Sports Club Limited",
    "wof:placetype":"venue"
},
  "geometry": {"coordinates":[-2.179164,52.158844],"type":"Point"}
}