{
  "type": "Feature",
  "properties": {
    "iso:country":"GB",
    "sg:address":"2 South Terrace",
    "sg:city":"Middlesbrough",
    "sg:classifiers":[
        {
            "category":"Shopping",
            "subcategory":"News",
            "type":"Retail Goods"
        }
    ],
    "sg:phone":"+44 1642 453085",
    "sg:postcode":"TS6 6HP",
    "sg:province":"North Yorkshire",
    "sg:tags":[
        "newsagent"
    ],
    "wof:name":"J I Wharry",
    "wof:placetype":"venue"
},
  "geometry": {"coordinates":[-1.174462,54.577839],"type":"Point"}
}