{
  "type": "Feature",
  "properties": {
    "addr:full":"7 Queens Avenue Widnes Cheshire WA8 8HR",
    "addr:housenumber":"7",
    "addr:postcode":"wa8 8hr",
    "addr:street":"Queens Avenue",
    "iso:country":"GB",
    "sg:address":"7 Queens Avenue",
    "sg:city":"Widnes",
    "sg:classifiers":[
        {
            "category":"Food & Beverages",
            "subcategory":"Fruits & Vegetables",
            "type":"Retail Goods"
        }
    ],
    "sg:postcode":"WA8 8HR",
    "sg:province":"Cheshire",
    "sg:tags":[
        "greengrocer"
    ],
    "wof:name":"G & L Manning",
    "wof:placetype":"venue"
},
  "geometry": {"coordinates":[-2.7691810131,53.3673667908],"type":"Point"}
}