{
  "type": "Feature",
  "properties": {
    "addr:full":"8a Pioneer Ho Coventry West Midlands CV1 5DX",
    "addr:housenumber":"8a",
    "addr:postcode":"cv1 5dx",
    "addr:street":"Pioneer Ho",
    "iso:country":"GB",
    "sg:address":"8a Pioneer Ho",
    "sg:city":"Coventry",
    "sg:classifiers":[
        {
            "category":"Retail",
            "subcategory":"Storage",
            "type":"Services"
        }
    ],
    "sg:phone":"+44 24 7663 1566",
    "sg:postcode":"CV1 5DX",
    "sg:province":"West Midlands",
    "sg:tags":[
        "household",
        "removal"
    ],
    "wof:name":"B & R Removals",
    "wof:placetype":"venue"
},
  "geometry": {"coordinates":[-1.507768,52.406986],"type":"Point"}
}