{
  "type": "Feature",
  "properties": {
    "iso:country":"GB",
    "sg:address":"13 Hams Road",
    "sg:city":"Lydney",
    "sg:classifiers":[
        {
            "category":"Manufacturing",
            "subcategory":"Tools & Machinery",
            "type":"Manufacturing & Wholesale Goods"
        }
    ],
    "sg:phone":"+44 1594 841104",
    "sg:postcode":"GL15 5PE",
    "sg:province":"Gloucestershire",
    "sg:tags":[
        "manufacture",
        "powertools",
        "power",
        "supply"
    ],
    "wof:name":"Toolbox Supplies Ltd.",
    "wof:placetype":"venue"
},
  "geometry": {"coordinates":[-2.526733,51.726665],"type":"Point"}
}