{
  "type": "Feature",
  "properties": {
    "addr:full":"164 Heath Park Road, Heath Park Romford Essex RM2 5XL",
    "addr:housenumber":"164",
    "addr:postcode":"rm2 5xl",
    "addr:street":"Heath Park Road Heath Park",
    "iso:country":"GB",
    "sg:address":"164 Heath Park Road, Heath Park",
    "sg:city":"Romford",
    "sg:classifiers":[
        {
            "category":"Food & Beverages",
            "subcategory":"Meat & Fish",
            "type":"Retail Goods"
        }
    ],
    "sg:phone":"+44 1708 446398",
    "sg:postcode":"RM2 5XL",
    "sg:province":"Essex",
    "sg:tags":[
        "butcher"
    ],
    "wof:name":"Wheelers",
    "wof:placetype":"venue"
},
  "geometry": {"coordinates":[0.2073349953,51.5779647827],"type":"Point"}
}