{
  "type": "Feature",
  "properties": {
    "addr:full":"49 North Street Wareham Dorset BH20 4AD",
    "addr:housenumber":"49",
    "addr:postcode":"bh20 4ad",
    "addr:street":"North Street",
    "iso:country":"GB",
    "sg:address":"49 North Street",
    "sg:city":"Wareham",
    "sg:classifiers":[
        {
            "category":"Real Estate",
            "subcategory":"Real Estate Agent",
            "type":"Services"
        }
    ],
    "sg:phone":"+44 1929 550066",
    "sg:postcode":"BH20 4AD",
    "sg:province":"Dorset",
    "wof:name":"Elldee Property Services Ltd.",
    "wof:placetype":"venue"
},
  "geometry": {"coordinates":[-2.1112389565,50.6879501343],"type":"Point"}
}