{
  "type": "Feature",
  "properties": {
    "iso:country":"GB",
    "sg:address":"The Beech House, Beech House Lane, Seisdon",
    "sg:city":"Wolverhampton",
    "sg:classifiers":[
        {
            "category":"Farming",
            "subcategory":"Farm",
            "type":"Manufacturing & Wholesale Goods"
        }
    ],
    "sg:phone":"+44 1902 893273",
    "sg:postcode":"WV5 7EP",
    "sg:province":"Shropshire",
    "sg:tags":[
        "mixed",
        "crop"
    ],
    "wof:name":"A & M Farquharson",
    "wof:placetype":"venue"
},
  "geometry": {"coordinates":[-2.244746,52.551552],"type":"Point"}
}