{
  "type": "Feature",
  "properties": {
    "iso:country":"GB",
    "sg:address":"224 Leagrave Rd",
    "sg:city":"Luton",
    "sg:classifiers":[
        {
            "category":"Professional",
            "subcategory":"Engineering",
            "type":"Services"
        }
    ],
    "sg:phone":"+44 1582 611061",
    "sg:postcode":"LU3 1JE",
    "sg:province":"Bedfordshire",
    "sg:tags":[
        "contractor",
        "electrical",
        "engineer"
    ],
    "wof:name":"Mechanical & Electrical Contract Services",
    "wof:placetype":"venue"
},
  "geometry": {"coordinates":[-0.433459,51.891365],"type":"Point"}
}