{
  "type": "Feature",
  "properties": {
    "iso:country":"GB",
    "sg:address":"99 Bellegrove Road",
    "sg:city":"Welling",
    "sg:classifiers":[
        {
            "category":"Personal",
            "subcategory":"Beauty Salon",
            "type":"Services"
        },
        {
            "category":"Personal",
            "subcategory":"Barber",
            "type":"Services"
        }
    ],
    "sg:phone":"+44 20 8303 9500",
    "sg:postcode":"DA16 3PG",
    "sg:province":"Kent",
    "sg:tags":[
        "unisex",
        "hairdresser"
    ],
    "wof:name":"Hairshapes",
    "wof:placetype":"venue"
},
  "geometry": {"coordinates":[0.102026999,51.4632225037],"type":"Point"}
}