{
  "type": "Feature",
  "properties": {
    "addr:full":"3 Viewfield St Nairn Highland IV12 4HW",
    "addr:housenumber":"3",
    "addr:postcode":"iv12 4hw",
    "addr:street":"Viewfield St",
    "iso:country":"GB",
    "sg:address":"3 Viewfield St",
    "sg:city":"Nairn",
    "sg:classifiers":[
        {
            "category":"Shopping",
            "subcategory":"Antiques",
            "type":"Retail Goods"
        }
    ],
    "sg:phone":"+44 1667 454660",
    "sg:postcode":"IV12 4HW",
    "sg:province":"Highland",
    "wof:name":"Workshop Antiques",
    "wof:placetype":"venue"
},
  "geometry": {"coordinates":[-3.8776650429,57.5873374939],"type":"Point"}
}