{
  "type": "Feature",
  "properties": {
    "addr:full":"4 Goodson Road, Harleden London Greater London NW10 9LR",
    "addr:housenumber":"4",
    "addr:postcode":"nw10 9lr",
    "addr:street":"Goodson Road",
    "iso:country":"GB",
    "sg:address":"4 Goodson Road, Harleden",
    "sg:city":"London",
    "sg:classifiers":[
        {
            "category":"Building & Trades",
            "subcategory":"Construction",
            "type":"Services"
        }
    ],
    "sg:phone":"+44 20 8961 3264",
    "sg:postcode":"NW10 9LR",
    "sg:province":"Greater London",
    "sg:tags":[
        "builder"
    ],
    "wof:name":"Circleworth Ltd.",
    "wof:placetype":"venue"
},
  "geometry": {"coordinates":[-0.250687,51.54446],"type":"Point"}
}