{
  "type": "Feature",
  "properties": {
    "addr:full":"31 Duke Street Henley-on-thames Berkshire RG9 1UR",
    "addr:housenumber":"31",
    "addr:postcode":"rg9 1ur",
    "addr:street":"Duke Street",
    "iso:country":"GB",
    "sg:address":"31 Duke Street",
    "sg:city":"Henley-on-thames",
    "sg:classifiers":[
        {
            "category":"Shopping",
            "subcategory":"Florist",
            "type":"Retail Goods"
        }
    ],
    "sg:phone":"+44 1491 410666",
    "sg:postcode":"RG9 1UR",
    "sg:province":"Berkshire",
    "wof:name":"The Soul Man",
    "wof:placetype":"venue"
},
  "geometry": {"coordinates":[-0.9040060043,51.5368881226],"type":"Point"}
}