{
  "type": "Feature",
  "properties": {
    "addr:full":"38 Hanbury Road Bargoed Caerphilly CF81 8QT",
    "addr:housenumber":"38",
    "addr:postcode":"cf81 8qt",
    "addr:street":"Hanbury Road",
    "iso:country":"GB",
    "sg:address":"38 Hanbury Road",
    "sg:city":"Bargoed",
    "sg:classifiers":[
        {
            "category":"Shopping",
            "subcategory":"Clothing, Apparel, & Fashions",
            "type":"Retail Goods"
        }
    ],
    "sg:phone":"+44 1443 835465",
    "sg:postcode":"CF81 8QT",
    "sg:province":"Caerphilly",
    "sg:tags":[
        "shop"
    ],
    "wof:name":"Impressions",
    "wof:placetype":"venue"
},
  "geometry": {"coordinates":[-3.229460001,51.688117981],"type":"Point"}
}