{
  "type": "Feature",
  "properties": {
    "addr:full":"Ffordd Brynsiencyn Llanfairpwllgwyngyll Isle of Anglesey LL61 6PS",
    "addr:postcode":"ll61 6ps",
    "addr:street":"Ffordd Brynsiencyn Llanfairpwllgwyngyll",
    "iso:country":"GB",
    "sg:address":"Ffordd Brynsiencyn",
    "sg:city":"Llanfairpwllgwyngyll",
    "sg:classifiers":[
        {
            "category":"Farming",
            "subcategory":"Livestock Farm",
            "type":"Manufacturing & Wholesale Goods"
        }
    ],
    "sg:phone":"+44 1248 714250",
    "sg:postcode":"LL61 6PS",
    "sg:province":"Isle of Anglesey",
    "sg:tags":[
        "others"
    ],
    "wof:name":"Edward Thomas Pearce",
    "wof:placetype":"venue"
},
  "geometry": {"coordinates":[-4.2016539574,53.2201538086],"type":"Point"}
}