{
  "type": "Feature",
  "properties": {
    "addr:full":"95 Station La Pontefract West Yorkshire WF7 5BJ",
    "addr:housenumber":"95",
    "addr:postcode":"wf7 5bj",
    "addr:street":"Station La Pontefract West",
    "iso:country":"GB",
    "sg:address":"95 Station La",
    "sg:city":"Pontefract",
    "sg:classifiers":[
        {
            "category":"Shopping",
            "subcategory":"News",
            "type":"Retail Goods"
        }
    ],
    "sg:phone":"+44 1977 791509",
    "sg:postcode":"WF7 5BJ",
    "sg:province":"West Yorkshire",
    "sg:tags":[
        "newsagent"
    ],
    "wof:name":"Scotts",
    "wof:placetype":"venue"
},
  "geometry": {"coordinates":[-1.358655,53.677788],"type":"Point"}
}