{
  "type": "Feature",
  "properties": {
    "addr:full":"Wardens House, Tangham Campsite, Tangham Woodbridge Suffolk IP12 3NF",
    "addr:postcode":"ip12 3nf",
    "iso:country":"GB",
    "sg:address":"Wardens House, Tangham Campsite, Tangham",
    "sg:city":"Woodbridge",
    "sg:classifiers":[
        {
            "category":"Recreation",
            "subcategory":"Campground",
            "type":"Entertainment"
        }
    ],
    "sg:phone":"+44 1394 450707",
    "sg:postcode":"IP12 3NF",
    "sg:province":"Suffolk",
    "sg:tags":[
        "operator",
        "site",
        "camping"
    ],
    "wof:name":"Forest Camping",
    "wof:placetype":"venue"
},
  "geometry": {"coordinates":[1.4348189831,52.0815734863],"type":"Point"}
}