{
  "type": "Feature",
  "properties": {
    "addr:full":"Railway Station Sunderland Tyne and Wear SR4 9JR",
    "addr:postcode":"sr4 9jr",
    "iso:country":"GB",
    "sg:address":"Railway Station",
    "sg:city":"Sunderland",
    "sg:classifiers":[
        {
            "category":"Shopping",
            "subcategory":"Florist",
            "type":"Retail Goods"
        }
    ],
    "sg:phone":"+44 191 514 2486",
    "sg:postcode":"SR4 9JR",
    "sg:province":"Tyne and Wear",
    "wof:name":"Forget-Me-Not Flowers",
    "wof:placetype":"venue"
},
  "geometry": {"coordinates":[-1.5012199879,54.8788490295],"type":"Point"}
}