{
  "type": "Feature",
  "properties": {
    "addr:full":"107-109 Streatham Vale London Greater London SW16 5SQ",
    "addr:housenumber":"107-109",
    "addr:postcode":"sw16 5sq",
    "addr:street":"Streatham Vale",
    "iso:country":"GB",
    "sg:address":"107-109 Streatham Vale",
    "sg:city":"London",
    "sg:classifiers":[
        {
            "category":"Food & Beverages",
            "subcategory":"Supermarket",
            "type":"Retail Goods"
        }
    ],
    "sg:phone":"+44 20 8764 4466",
    "sg:postcode":"SW16 5SQ",
    "sg:province":"Greater London",
    "wof:name":"The Late Late Supershop (U K) Ltd.",
    "wof:placetype":"venue"
},
  "geometry": {"coordinates":[-0.139381,51.415432],"type":"Point"}
}