{
  "type": "Feature",
  "properties": {
    "addr:full":"6-9 Lion Gate Gardens Richmond Greater London TW9 2DW",
    "addr:housenumber":"6-9",
    "addr:postcode":"tw9 2dw",
    "addr:street":"Lion Gate Gardens",
    "iso:country":"GB",
    "sg:address":"6-9 Lion Gate Gardens",
    "sg:city":"Richmond",
    "sg:classifiers":[
        {
            "category":"Professional",
            "subcategory":"Accounting & Tax Preparation",
            "type":"Services"
        }
    ],
    "sg:postcode":"TW9 2DW",
    "sg:province":"Greater London",
    "sg:tags":[
        "accountant"
    ],
    "wof:name":"Hillside Enterprises Ltd",
    "wof:placetype":"venue"
},
  "geometry": {"coordinates":[-0.291969,51.469368],"type":"Point"}
}