{
  "type": "Feature",
  "properties": {
    "iso:country":"GB",
    "sg:address":"Lane Heads Farm, May Lane",
    "sg:city":"Preston",
    "sg:classifiers":[
        {
            "category":"Farming",
            "subcategory":"Dairy Farm",
            "type":"Manufacturing & Wholesale Goods"
        }
    ],
    "sg:phone":"+44 1995 640428",
    "sg:postcode":"PR3 0PD",
    "sg:province":"Lancashire",
    "wof:name":"David R & Evelyn M Milner",
    "wof:placetype":"venue"
},
  "geometry": {"coordinates":[-2.70245,53.87627],"type":"Point"}
}