{
  "type": "Feature",
  "properties": {
    "iso:country":"GB",
    "sg:address":"Lloyds Road",
    "sg:city":"Corby",
    "sg:classifiers":[
        {
            "category":"Organizations",
            "subcategory":"Membership Organization",
            "type":"Services"
        }
    ],
    "sg:phone":"+44 1536 260528",
    "sg:postcode":"NN17 1AP",
    "sg:province":"Northamptonshire",
    "sg:tags":[
        "club"
    ],
    "wof:name":"Ex-Servicemen's Club",
    "wof:placetype":"venue"
},
  "geometry": {"coordinates":[-0.682137,52.492645],"type":"Point"}
}