{
  "type": "Feature",
  "properties": {
    "iso:country":"GB",
    "sg:address":"High Street, East Markham",
    "sg:city":"Newark",
    "sg:classifiers":[
        {
            "category":"Bars & Pubs",
            "type":"Food & Drink"
        }
    ],
    "sg:postcode":"NG22 0RE",
    "sg:province":"Nottinghamshire",
    "sg:tags":[
        "pubs",
        "inn"
    ],
    "wof:name":"Queens Hotel",
    "wof:placetype":"venue"
},
  "geometry": {"coordinates":[-0.901868999,53.2535667419],"type":"Point"}
}