{
  "type": "Feature",
  "properties": {
    "iso:country":"GB",
    "sg:address":"Stricklands Road",
    "sg:city":"Stowmarket",
    "sg:classifiers":[
        {
            "category":"Place Of Worship",
            "type":"Public Place"
        }
    ],
    "sg:phone":"+44 1449 612946",
    "sg:postcode":"IP14 1AW",
    "sg:province":"Suffolk",
    "wof:name":"Our Lady S Catholic Church Stowmarket",
    "wof:placetype":"venue"
},
  "geometry": {"coordinates":[0.997708,52.186054],"type":"Point"}
}