{
  "type": "Feature",
  "properties": {
    "iso:country":"GB",
    "sg:address":"Danygraig Farm, Cwmtaf",
    "sg:city":"Merthyr Tydfil",
    "sg:classifiers":[
        {
            "category":"Farming",
            "subcategory":"Livestock Farm",
            "type":"Manufacturing & Wholesale Goods"
        }
    ],
    "sg:phone":"+44 1685 385482",
    "sg:postcode":"CF48 2HS",
    "sg:province":"Caerphilly",
    "sg:tags":[
        "others"
    ],
    "wof:name":"C D & E M John",
    "wof:placetype":"venue"
},
  "geometry": {"coordinates":[-3.417509,51.772614],"type":"Point"}
}