{
  "type": "Feature",
  "properties": {
    "addr:full":"16 Blackthorn Clo Scunthorpe Lincolnshire DN15 8UT",
    "addr:housenumber":"16",
    "addr:postcode":"dn15 8ut",
    "addr:street":"Blackthorn Clo",
    "iso:country":"GB",
    "sg:address":"16 Blackthorn Clo",
    "sg:city":"Scunthorpe",
    "sg:classifiers":[
        {
            "category":"Professional",
            "subcategory":"Printing & Photocopies",
            "type":"Services"
        }
    ],
    "sg:phone":"+44 1724 279455",
    "sg:postcode":"DN15 8UT",
    "sg:province":"Lincolnshire",
    "sg:tags":[
        "printer"
    ],
    "wof:name":"Rainbow Graphics",
    "wof:placetype":"venue"
},
  "geometry": {"coordinates":[-0.684299,53.602757],"type":"Point"}
}