{
  "type": "Feature",
  "properties": {
    "addr:full":"85 Porlock Drive, Sully Penarth The Vale of Glamorgan CF64 5QB",
    "addr:housenumber":"85",
    "addr:postcode":"cf64 5qb",
    "addr:street":"Porlock Drive;Vale",
    "iso:country":"GB",
    "sg:address":"85 Porlock Drive, Sully",
    "sg:city":"Penarth",
    "sg:classifiers":[
        {
            "category":"Military Area",
            "subcategory":"Air Force Base",
            "type":"Public Place"
        }
    ],
    "sg:phone":"+44 29 2053 0847",
    "sg:postcode":"CF64 5QB",
    "sg:province":"The Vale of Glamorgan",
    "sg:tags":[
        "taxi",
        "hire",
        "private"
    ],
    "wof:name":"Sully Cars",
    "wof:placetype":"venue"
},
  "geometry": {"coordinates":[-3.212867,51.406841],"type":"Point"}
}