{
  "type": "Feature",
  "properties": {
    "iso:country":"GB",
    "sg:address":"Summervale House, Coldeast Way, Sarisbury Grn",
    "sg:city":"Southampton",
    "sg:classifiers":[
        {
            "category":"Social Services",
            "subcategory":"Retirement Home",
            "type":"Services"
        }
    ],
    "sg:phone":"+44 1489 577196",
    "sg:postcode":"SO31 7YD",
    "sg:province":"Hampshire",
    "sg:tags":[
        "residential",
        "care"
    ],
    "wof:name":"Summervale House",
    "wof:placetype":"venue"
},
  "geometry": {"coordinates":[-1.276949,50.873169],"type":"Point"}
}