{
  "type": "Feature",
  "properties": {
    "addr:full":"Colina House, Colina Mews London Greater London N15 3HS",
    "addr:postcode":"n15 3hs",
    "addr:street":"Colina Mews",
    "iso:country":"GB",
    "sg:address":"Colina House, Colina Mews",
    "sg:city":"London",
    "sg:classifiers":[
        {
            "category":"Building & Trades",
            "subcategory":"Cleaning & Sanitation",
            "type":"Services"
        }
    ],
    "sg:phone":"+44 20 8365 8029",
    "sg:postcode":"N15 3HS",
    "sg:province":"Greater London",
    "sg:tags":[
        "dry",
        "control",
        "damp",
        "rot"
    ],
    "wof:name":"Eric Morson",
    "wof:placetype":"venue"
},
  "geometry": {"coordinates":[-0.098722,51.584564],"type":"Point"}
}