{
  "type": "Feature",
  "properties": {
    "iso:country":"GB",
    "sg:address":"Unit 4, East Quay",
    "sg:city":"Bridgwater",
    "sg:classifiers":[
        {
            "category":"Manufacturing",
            "subcategory":"Rubber & Plastics",
            "type":"Manufacturing & Wholesale Goods"
        }
    ],
    "sg:phone":"+44 1278 422932",
    "sg:postcode":"TA6 4DB",
    "sg:province":"Somerset",
    "sg:tags":[
        "injection",
        "moulding"
    ],
    "wof:name":"Gillson Bros Ltd.",
    "wof:placetype":"venue"
},
  "geometry": {"coordinates":[-3.000159,51.136547],"type":"Point"}
}