{
  "type": "Feature",
  "properties": {
    "iso:country":"GB",
    "sg:address":"19 Lennox Street",
    "sg:city":"Bognor Regis",
    "sg:classifiers":[
        {
            "category":"Cafe",
            "type":"Food & Drink"
        }
    ],
    "sg:phone":"+44 1243 864818",
    "sg:postcode":"PO21 1NA",
    "sg:province":"West Sussex",
    "sg:tags":[
        "tea",
        "room"
    ],
    "wof:name":"The Lennox Cafe",
    "wof:placetype":"venue"
},
  "geometry": {"coordinates":[-0.6744620204,50.7822494507],"type":"Point"}
}