{
  "type": "Feature",
  "properties": {
    "addr:full":"2 Elliott Road London Greater London W4 1PE",
    "addr:housenumber":"2",
    "addr:postcode":"w4 1pe",
    "addr:street":"Elliott Road",
    "iso:country":"GB",
    "sg:address":"2 Elliott Road",
    "sg:city":"London",
    "sg:classifiers":[
        {
            "category":"Personal",
            "subcategory":"Barber",
            "type":"Services"
        }
    ],
    "sg:phone":"+44 20 8995 2017",
    "sg:postcode":"W4 1PE",
    "sg:province":"Greater London",
    "sg:tags":[
        "men's",
        "gents",
        "hairdresser"
    ],
    "wof:name":"Jimmy's",
    "wof:placetype":"venue"
},
  "geometry": {"coordinates":[-0.256231,51.492813],"type":"Point"}
}