{
  "type": "Feature",
  "properties": {
    "addr:full":"48 High Street Banstead Surrey SM7 2LX",
    "addr:housenumber":"48",
    "addr:postcode":"sm7 2lx",
    "addr:street":"High Street",
    "iso:country":"GB",
    "sg:address":"48 High Street",
    "sg:city":"Banstead",
    "sg:classifiers":[
        {
            "category":"Shopping",
            "subcategory":"Clothing, Apparel, & Fashions",
            "type":"Retail Goods"
        }
    ],
    "sg:phone":"+44 1737 371139",
    "sg:postcode":"SM7 2LX",
    "sg:province":"Surrey",
    "sg:tags":[
        "menswear"
    ],
    "wof:name":"Cactus Clothing Co",
    "wof:placetype":"venue"
},
  "geometry": {"coordinates":[-0.201846,51.32235],"type":"Point"}
}