{
  "type": "Feature",
  "properties": {
    "addr:full":"43a Prince Of Wales Road Norwich Norfolk NR1 1BL",
    "addr:housenumber":"43a",
    "addr:postcode":"nr1 1bl",
    "addr:street":"Prince Of Wales Road Norwich Norfolk",
    "iso:country":"GB",
    "sg:address":"43a Prince Of Wales Road",
    "sg:city":"Norwich",
    "sg:classifiers":[
        {
            "category":"Military Area",
            "subcategory":"Air Force Base",
            "type":"Public Place"
        }
    ],
    "sg:phone":"+44 1603 619280",
    "sg:postcode":"NR1 1BL",
    "sg:province":"Norfolk",
    "sg:tags":[
        "taxi",
        "hire",
        "private"
    ],
    "wof:name":"Five Star Taxis Ltd.",
    "wof:placetype":"venue"
},
  "geometry": {"coordinates":[1.301485,52.629211],"type":"Point"}
}