{
  "type": "Feature",
  "properties": {
    "addr:full":"Old Bank Chambers, Amersham Road, Hazlemere High Wycombe Buckinghamshire HP15 7LN",
    "addr:postcode":"hp15 7ln",
    "addr:street":"Chambers Amersham Road",
    "iso:country":"GB",
    "sg:address":"Old Bank Chambers, Amersham Road, Hazlemere",
    "sg:city":"High Wycombe",
    "sg:classifiers":[
        {
            "category":"Building & Trades",
            "subcategory":"Construction",
            "type":"Services"
        }
    ],
    "sg:phone":"+44 1494 465465",
    "sg:postcode":"HP15 7LN",
    "sg:province":"Buckinghamshire",
    "sg:tags":[
        "builder"
    ],
    "wof:name":"Scottwood Homes",
    "wof:placetype":"venue"
},
  "geometry": {"coordinates":[-0.708729,51.651031],"type":"Point"}
}