{
  "type": "Feature",
  "properties": {
    "addr:full":"1 Harbour Street Ardrossan North Ayrshire KA22 8BS",
    "addr:housenumber":"1",
    "addr:postcode":"ka22 8bs",
    "addr:street":"Harbour Street",
    "iso:country":"GB",
    "sg:address":"1 Harbour Street",
    "sg:city":"Ardrossan",
    "sg:classifiers":[
        {
            "category":"Organizations",
            "subcategory":"Community Association",
            "type":"Services"
        },
        {
            "category":"Organizations",
            "subcategory":"Membership Organization",
            "type":"Services"
        }
    ],
    "sg:phone":"+44 1294 462861",
    "sg:postcode":"KA22 8BS",
    "sg:province":"North Ayrshire",
    "sg:tags":[
        "club",
        "social"
    ],
    "wof:name":"320 Masonic Club",
    "wof:placetype":"venue"
},
  "geometry": {"coordinates":[-4.8149280548,55.6398200989],"type":"Point"}
}