{
  "type": "Feature",
  "properties": {
    "iso:country":"GB",
    "sg:address":"Cherry Trees, Sparkhayes Lane, Porlock",
    "sg:city":"Minehead",
    "sg:classifiers":[
        {
            "category":"Retail",
            "subcategory":"Funeral Services",
            "type":"Services"
        }
    ],
    "sg:phone":"+44 1643 862615",
    "sg:postcode":"TA24 8NE",
    "sg:province":"Somerset",
    "wof:name":"J & E Hayes",
    "wof:placetype":"venue"
},
  "geometry": {"coordinates":[-3.593579,51.209236],"type":"Point"}
}