{
  "type": "Feature",
  "properties": {
    "iso:country":"GB",
    "sg:address":"The Rear Of The Timbers, Old Odiham Road",
    "sg:city":"Alton",
    "sg:classifiers":[
        {
            "category":"Education",
            "subcategory":"Music School",
            "type":"Public Place"
        }
    ],
    "sg:postcode":"GU34 4BU",
    "sg:province":"Hampshire",
    "sg:tags":[
        "conservatory"
    ],
    "wof:name":"A H G",
    "wof:placetype":"venue"
},
  "geometry": {"coordinates":[-0.9743289948,51.1475601196],"type":"Point"}
}