{
  "type": "Feature",
  "properties": {
    "iso:country":"GB",
    "sg:address":"70-71 St. Philips Rd",
    "sg:city":"Cambridge",
    "sg:classifiers":[
        {
            "category":"Building & Trades",
            "subcategory":"Construction",
            "type":"Services"
        }
    ],
    "sg:postcode":"CB1 3AQ",
    "sg:province":"Cambridgeshire",
    "sg:tags":[
        "builder"
    ],
    "wof:name":"Sharpe,Brian,",
    "wof:placetype":"venue"
},
  "geometry": {"coordinates":[0.1509380043,52.1984329224],"type":"Point"}
}