{
  "type": "Feature",
  "properties": {
    "addr:full":"Elizabeth Road Ramsgate Kent CT11 8JA",
    "addr:postcode":"ct11 8ja",
    "addr:street":"Elizabeth Road Ramsgate",
    "iso:country":"GB",
    "sg:address":"Elizabeth Road",
    "sg:city":"Ramsgate",
    "sg:classifiers":[
        {
            "category":"Retail",
            "subcategory":"Auto Repair",
            "type":"Services"
        }
    ],
    "sg:phone":"+44 1843 593396",
    "sg:postcode":"CT11 8JA",
    "sg:province":"Kent",
    "sg:tags":[
        "modification",
        "garage",
        "related"
    ],
    "wof:name":"EAST CLIFF GARAGE",
    "wof:placetype":"venue"
},
  "geometry": {"coordinates":[1.42358,51.333817],"type":"Point"}
}