{
  "type": "Feature",
  "properties": {
    "addr:full":"Unit 39 2nd Floor, Vulcan Ho, Vulcan Rd Leicester Leicestershire LE5 3EF",
    "addr:housenumber":"unit 39 2nd floor",
    "addr:postcode":"le5 3ef",
    "addr:street":"Vulcan Ho Vulcan Rd",
    "iso:country":"GB",
    "sg:address":"Unit 39 2nd Floor, Vulcan Ho, Vulcan Rd",
    "sg:city":"Leicester",
    "sg:classifiers":[
        {
            "category":"Banks & Credit Unions",
            "subcategory":"Financial Services",
            "type":"Services"
        }
    ],
    "sg:phone":"+44 116 253 6392",
    "sg:postcode":"LE5 3EF",
    "sg:province":"Leicestershire",
    "sg:tags":[
        "consultant"
    ],
    "wof:name":"Taurus Financial Services",
    "wof:placetype":"venue"
},
  "geometry": {"coordinates":[-1.1148500443,52.6388511658],"type":"Point"}
}