{
  "type": "Feature",
  "properties": {
    "iso:country":"GB",
    "sg:address":"25 Windsor Drive",
    "sg:city":"Orpington",
    "sg:classifiers":[
        {
            "category":"Personal",
            "subcategory":"Beauty Salon",
            "type":"Services"
        }
    ],
    "sg:phone":"+44 1689 853004",
    "sg:postcode":"BR6 6EY",
    "sg:province":"Kent",
    "sg:tags":[
        "unisex",
        "hairdresser"
    ],
    "wof:name":"Clippings",
    "wof:placetype":"venue"
},
  "geometry": {"coordinates":[0.1051110029,51.3563041687],"type":"Point"}
}