{
  "type": "Feature",
  "properties": {
    "addr:full":"57 Fairburn Drive, Garforth Leeds North Yorkshire LS25 2AR",
    "addr:housenumber":"57",
    "addr:postcode":"ls25 2ar",
    "addr:street":"Fairburn Drive",
    "iso:country":"GB",
    "sg:address":"57 Fairburn Drive, Garforth",
    "sg:city":"Leeds",
    "sg:classifiers":[
        {
            "category":"Professional",
            "subcategory":"Computer Services",
            "type":"Services"
        }
    ],
    "sg:postcode":"LS25 2AR",
    "sg:province":"North Yorkshire",
    "sg:tags":[
        "consultant"
    ],
    "wof:name":"Magnum Consultants",
    "wof:placetype":"venue"
},
  "geometry": {"coordinates":[-1.3741680384,53.7875976562],"type":"Point"}
}