{
  "type": "Feature",
  "properties": {
    "addr:full":"Unit 4 The Manton Centre, Manton Lane Bedford Bedfordshire MK41 7PX",
    "addr:housenumber":"unit 4;manton",
    "addr:postcode":"mk41 7px",
    "addr:street":"The;Manton Lane",
    "iso:country":"GB",
    "sg:address":"Unit 4 The Manton Centre, Manton Lane",
    "sg:city":"Bedford",
    "sg:classifiers":[
        {
            "category":"Shopping",
            "subcategory":"Stationery & Office Supplies",
            "type":"Retail Goods"
        }
    ],
    "sg:phone":"+44 1234 342844",
    "sg:postcode":"MK41 7PX",
    "sg:province":"Bedfordshire",
    "wof:name":"Te-Co-Fa (U K) Ltd.",
    "wof:placetype":"venue"
},
  "geometry": {"coordinates":[-0.477326,52.151211],"type":"Point"}
}