{
  "type": "Feature",
  "properties": {
    "iso:country":"GB",
    "sg:address":"Burwash Lodge, Liphook Clo",
    "sg:city":"Brighton",
    "sg:classifiers":[
        {
            "category":"Government",
            "subcategory":"Office",
            "type":"Public Place"
        }
    ],
    "sg:phone":"+44 1273 295775",
    "sg:postcode":"BN1 7AZ",
    "sg:province":"East Sussex",
    "sg:tags":[
        "local"
    ],
    "wof:name":"Brighton & Hove Council",
    "wof:placetype":"venue"
},
  "geometry": {"coordinates":[-0.12488,50.842602],"type":"Point"}
}