{
  "type": "Feature",
  "properties": {
    "addr:full":"96 Parrock St Gravesend Kent DA12 1HA",
    "addr:housenumber":"96",
    "addr:postcode":"da12 1ha",
    "addr:street":"Parrock St",
    "iso:country":"GB",
    "sg:address":"96 Parrock St",
    "sg:city":"Gravesend",
    "sg:classifiers":[
        {
            "category":"Building & Trades",
            "subcategory":"Construction",
            "type":"Services"
        }
    ],
    "sg:phone":"+44 1474 567855",
    "sg:postcode":"DA12 1HA",
    "sg:province":"Kent",
    "sg:tags":[
        "builder"
    ],
    "wof:name":"W J Holland (Builders) Ltd",
    "wof:placetype":"venue"
},
  "geometry": {"coordinates":[0.3708699942,51.4406394958],"type":"Point"}
}