{
  "type": "Feature",
  "properties": {
    "addr:full":"13 Headlands, Fenstanton Huntingdon Bedfordshire PE28 9LN",
    "addr:housenumber":"13",
    "addr:postcode":"pe28 9ln",
    "addr:street":"Headlands",
    "iso:country":"GB",
    "sg:address":"13 Headlands, Fenstanton",
    "sg:city":"Huntingdon",
    "sg:classifiers":[
        {
            "category":"Building & Trades",
            "subcategory":"Plumbing",
            "type":"Services"
        }
    ],
    "sg:phone":"+44 1480 468247",
    "sg:postcode":"PE28 9LN",
    "sg:province":"Bedfordshire",
    "sg:tags":[
        "heating"
    ],
    "wof:name":"G I Plumbing & Heating",
    "wof:placetype":"venue"
},
  "geometry": {"coordinates":[-0.0645959973,52.2969818115],"type":"Point"}
}