{
  "type": "Feature",
  "properties": {
    "iso:country":"GB",
    "sg:address":"Parsonage Farm House, Marsh Baldon",
    "sg:city":"Oxford",
    "sg:classifiers":[
        {
            "category":"Farming",
            "subcategory":"Livestock Farm",
            "type":"Manufacturing & Wholesale Goods"
        }
    ],
    "sg:postcode":"OX44 9LJ",
    "sg:province":"Oxfordshire",
    "sg:tags":[
        "others"
    ],
    "wof:name":"Delafield Bros",
    "wof:placetype":"venue"
},
  "geometry": {"coordinates":[-1.189745,51.688122],"type":"Point"}
}