{
  "type": "Feature",
  "properties": {
    "addr:full":"132 Summers Lane London Greater London N12 0PX",
    "addr:housenumber":"132",
    "addr:postcode":"n12 0px",
    "addr:street":"Summers Lane",
    "iso:country":"GB",
    "sg:address":"132 Summers Lane",
    "sg:city":"London",
    "sg:classifiers":[
        {
            "category":"Building & Trades",
            "subcategory":"Plumbing",
            "type":"Services"
        }
    ],
    "sg:phone":"+44 20 8343 8629",
    "sg:postcode":"N12 0PX",
    "sg:province":"Greater London",
    "sg:tags":[
        "heating"
    ],
    "wof:name":"D & D Plumbing",
    "wof:placetype":"venue"
},
  "geometry": {"coordinates":[-0.1659789979,51.6078224182],"type":"Point"}
}