{
  "type": "Feature",
  "properties": {
    "addr:full":"Stotforth Hill House, Windlestone Park, Windlestone Ferryhill Durham DL17 0NF",
    "addr:postcode":"dl17 0nf",
    "addr:street":"Stotforth;Windlestone",
    "iso:country":"GB",
    "sg:address":"Stotforth Hill House, Windlestone Park, Windlestone",
    "sg:city":"Ferryhill",
    "sg:classifiers":[
        {
            "category":"Professional",
            "subcategory":"Engineering",
            "type":"Services"
        }
    ],
    "sg:phone":"+44 1325 311013",
    "sg:postcode":"DL17 0NF",
    "sg:province":"Durham",
    "sg:tags":[
        "civil",
        "engineer"
    ],
    "wof:name":"Hall Construction Services Ltd",
    "wof:placetype":"venue"
},
  "geometry": {"coordinates":[-1.58818,54.654984],"type":"Point"}
}