{
  "type": "Feature",
  "properties": {
    "addr:full":"21 Goodge St West End Hampshire W1P 1FD",
    "addr:housenumber":"21",
    "addr:postcode":"w1p 1fd",
    "addr:street":"Goodge St",
    "iso:country":"GB",
    "sg:address":"21 Goodge St",
    "sg:city":"West End",
    "sg:classifiers":[
        {
            "category":"Government",
            "subcategory":"Post Office",
            "type":"Public Place"
        }
    ],
    "sg:phone":"+44 20 7636 5549",
    "sg:postcode":"W1P 1FD",
    "sg:province":"Hampshire",
    "sg:tags":[
        "messenger",
        "courier"
    ],
    "wof:name":"Guarantee Couriers",
    "wof:placetype":"venue"
},
  "geometry": {"coordinates":[-0.1346970052,51.519618988],"type":"Point"}
}