{
  "type": "Feature",
  "properties": {
    "addr:full":"St Davids, Trefonen Road Oswestry Shropshire SY10 9NX",
    "addr:postcode":"sy10 9nx",
    "addr:street":"St;Trefonen Road",
    "iso:country":"GB",
    "sg:address":"St Davids, Trefonen Road",
    "sg:city":"Oswestry",
    "sg:classifiers":[
        {
            "category":"Professional",
            "subcategory":"Engineering",
            "type":"Services"
        }
    ],
    "sg:phone":"+44 1691 671545",
    "sg:postcode":"SY10 9NX",
    "sg:province":"Shropshire",
    "sg:tags":[
        "contractor",
        "electrical",
        "engineer"
    ],
    "wof:name":"A J Cockram",
    "wof:placetype":"venue"
},
  "geometry": {"coordinates":[-3.0987589359,52.8347206116],"type":"Point"}
}