{
  "type": "Feature",
  "properties": {
    "addr:full":"197 Meir Road Stoke-on-trent Staffordshire ST3 7JF",
    "addr:housenumber":"197",
    "addr:postcode":"st3 7jf",
    "addr:street":"Meir Road",
    "iso:country":"GB",
    "sg:address":"197 Meir Road",
    "sg:city":"Stoke-on-trent",
    "sg:classifiers":[
        {
            "category":"Organizations",
            "subcategory":"Membership Organization",
            "type":"Services"
        }
    ],
    "sg:phone":"+44 1782 312346",
    "sg:postcode":"ST3 7JF",
    "sg:province":"Staffordshire",
    "sg:tags":[
        "club"
    ],
    "wof:name":"Meir Longton & District British Legion Club Ltd.",
    "wof:placetype":"venue"
},
  "geometry": {"coordinates":[-2.111624,52.979992],"type":"Point"}
}