{
  "type": "Feature",
  "properties": {
    "iso:country":"GB",
    "sg:address":"Oak Hill, Bramfield",
    "sg:city":"Halesworth",
    "sg:classifiers":[
        {
            "category":"Recreation",
            "subcategory":"Fishing",
            "type":"Entertainment"
        },
        {
            "category":"Farming",
            "subcategory":"Livestock Farm",
            "type":"Manufacturing & Wholesale Goods"
        }
    ],
    "sg:phone":"+44 1986 872385",
    "sg:postcode":"IP19 9HN",
    "sg:province":"Suffolk",
    "sg:tags":[
        "equipment",
        "angling",
        "others"
    ],
    "wof:name":"Standard Bait Co",
    "wof:placetype":"venue"
},
  "geometry": {"coordinates":[1.519097,52.310383],"type":"Point"}
}