{
  "type": "Feature",
  "properties": {
    "iso:country":"GB",
    "sg:address":"23 London Road",
    "sg:city":"London",
    "sg:classifiers":[
        {
            "category":"Organizations",
            "subcategory":"Labor Organization",
            "type":"Services"
        },
        {
            "category":"Shopping",
            "subcategory":"Mobile Phones",
            "type":"Retail Goods"
        }
    ],
    "sg:phone":"+44 20 8333 4222",
    "sg:postcode":"SE23 3TY",
    "sg:province":"Greater London",
    "sg:tags":[
        "equipment",
        "paging",
        "system"
    ],
    "wof:name":"T C Communications",
    "wof:placetype":"venue"
},
  "geometry": {"coordinates":[-0.054847,51.43922],"type":"Point"}
}