{
  "type": "Feature",
  "properties": {
    "iso:country":"GB",
    "sg:address":"Charles Street, Neyland",
    "sg:city":"Milford Haven",
    "sg:classifiers":[
        {
            "category":"Health Services",
            "subcategory":"Clinic",
            "type":"Services"
        },
        {
            "category":"Education",
            "subcategory":"School",
            "type":"Public Place"
        }
    ],
    "sg:phone":"+44 1646 600882",
    "sg:postcode":"SA73 1SA",
    "sg:province":"Pembrokeshire",
    "sg:tags":[
        "nh",
        "local",
        "authority"
    ],
    "wof:name":"Neyland County Infants School",
    "wof:placetype":"venue"
},
  "geometry": {"coordinates":[-4.952589,51.711121],"type":"Point"}
}