{
  "type": "Feature",
  "properties": {
    "iso:country":"GB",
    "sg:address":"147 Havant Road",
    "sg:city":"Hayling Island",
    "sg:classifiers":[
        {
            "category":"Sports & Exercise",
            "subcategory":"Stables",
            "type":"Entertainment"
        }
    ],
    "sg:phone":"+44 23 9246 5512",
    "sg:postcode":"PO11 0LF",
    "sg:province":"Hampshire",
    "sg:tags":[
        "equestrian",
        "centre",
        "livery",
        "schools",
        "riding",
        "education"
    ],
    "wof:name":"Westcroft Stables & Livery Yard",
    "wof:placetype":"venue"
},
  "geometry": {"coordinates":[-0.980036,50.82914],"type":"Point"}
}