{
  "type": "Feature",
  "properties": {
    "addr:full":"Sycamore Farm, Finkle Street, Wortley Sheffield South Yorkshire S35 7DH",
    "addr:postcode":"s35 7dh",
    "addr:street":"Sycamore;Finkle Street",
    "iso:country":"GB",
    "sg:address":"Sycamore Farm, Finkle Street, Wortley",
    "sg:city":"Sheffield",
    "sg:classifiers":[
        {
            "category":"Farming",
            "subcategory":"Livestock Farm",
            "type":"Manufacturing & Wholesale Goods"
        }
    ],
    "sg:phone":"+44 114 288 3563",
    "sg:postcode":"S35 7DH",
    "sg:province":"South Yorkshire",
    "sg:tags":[
        "others"
    ],
    "wof:name":"T E White",
    "wof:placetype":"venue"
},
  "geometry": {"coordinates":[-1.5382310152,53.4908866882],"type":"Point"}
}