{
  "type": "Feature",
  "properties": {
    "iso:country":"GB",
    "sg:address":"112 Market Street",
    "sg:city":"Hyde",
    "sg:classifiers":[
        {
            "category":"Fast Food",
            "type":"Food & Drink"
        }
    ],
    "sg:phone":"+44 161 367 7592",
    "sg:postcode":"SK14 1ES",
    "sg:province":"Cheshire",
    "sg:tags":[
        "away",
        "take"
    ],
    "wof:name":"Indian Chef Takeaway",
    "wof:placetype":"venue"
},
  "geometry": {"coordinates":[-2.0782,53.449596],"type":"Point"}
}