{
  "type": "Feature",
  "properties": {
    "iso:country":"GB",
    "sg:address":"34 The Parade, Oadby",
    "sg:city":"Leicester",
    "sg:classifiers":[
        {
            "category":"Government",
            "subcategory":"Post Office",
            "type":"Public Place"
        }
    ],
    "sg:phone":"+44 116 272 0102",
    "sg:postcode":"LE2 5BF",
    "sg:province":"Leicestershire",
    "wof:name":"Oadby Sub Post Office",
    "wof:placetype":"venue"
},
  "geometry": {"coordinates":[-1.083945,52.599319],"type":"Point"}
}