{
  "type": "Feature",
  "properties": {
    "iso:country":"GB",
    "sg:address":"Cumberland Way",
    "sg:city":"Sheffield",
    "sg:classifiers":[
        {
            "category":"Bars & Pubs",
            "type":"Food & Drink"
        }
    ],
    "sg:phone":"+44 114 272 3650",
    "sg:postcode":"S1 4PU",
    "sg:province":"South Yorkshire",
    "sg:tags":[
        "pubs",
        "inn"
    ],
    "wof:name":"Punch Retail (Holdings) Ltd.",
    "wof:placetype":"venue"
},
  "geometry": {"coordinates":[-1.472744,53.37566],"type":"Point"}
}