{
  "type": "Feature",
  "properties": {
    "addr:full":"Linden Place, Seale Farnham Hampshire GU10 1HS",
    "addr:postcode":"gu10 1hs",
    "addr:street":"Linden Place",
    "iso:country":"GB",
    "sg:address":"Linden Place, Seale",
    "sg:city":"Farnham",
    "sg:classifiers":[
        {
            "category":"Professional",
            "subcategory":"Detective & Security Services",
            "type":"Services"
        }
    ],
    "sg:postcode":"GU10 1HS",
    "sg:province":"Hampshire",
    "wof:name":"Ian Johnson Associates Ltd.",
    "wof:placetype":"venue"
},
  "geometry": {"coordinates":[-0.716264,51.221729],"type":"Point"}
}