{
  "type": "Feature",
  "properties": {
    "iso:country":"GB",
    "sg:address":"Alpine Way",
    "sg:city":"London",
    "sg:classifiers":[
        {
            "category":"Shopping",
            "subcategory":"Clothing, Apparel, & Fashions",
            "type":"Retail Goods"
        }
    ],
    "sg:phone":"+44 20 7474 9414",
    "sg:postcode":"E6 6LA",
    "sg:province":"Greater London",
    "sg:tags":[
        "ladieswear"
    ],
    "wof:name":"Select",
    "wof:placetype":"venue"
},
  "geometry": {"coordinates":[0.063445,51.517635],"type":"Point"}
}