{
  "type": "Feature",
  "properties": {
    "addr:full":"16 Albion Street Cleckheaton West Yorkshire BD19 3JD",
    "addr:housenumber":"16",
    "addr:postcode":"bd19 3jd",
    "addr:street":"Albion Street",
    "iso:country":"GB",
    "sg:address":"16 Albion Street",
    "sg:city":"Cleckheaton",
    "sg:classifiers":[
        {
            "category":"Shopping",
            "subcategory":"Stationery & Office Supplies",
            "type":"Retail Goods"
        }
    ],
    "sg:phone":"+44 1274 873026",
    "sg:postcode":"BD19 3JD",
    "sg:province":"West Yorkshire",
    "sg:tags":[
        "commercial"
    ],
    "wof:name":"Spenborough Stationers",
    "wof:placetype":"venue"
},
  "geometry": {"coordinates":[-1.7128390074,53.724861145],"type":"Point"}
}