{
  "type": "Feature",
  "properties": {
    "iso:country":"GB",
    "sg:address":"2 Matts Hill Villas, Hartlip",
    "sg:city":"Sittingbourne",
    "sg:classifiers":[
        {
            "category":"Retail",
            "subcategory":"Repair Shop",
            "type":"Services"
        }
    ],
    "sg:postcode":"ME9 7UX",
    "sg:province":"Kent",
    "sg:tags":[
        "furniture"
    ],
    "wof:name":"Richard Edwards",
    "wof:placetype":"venue"
},
  "geometry": {"coordinates":[0.641981,51.350197],"type":"Point"}
}