{
  "type": "Feature",
  "properties": {
    "addr:full":"3 Tasmania Close Basingstoke Hampshire RG24 9PQ",
    "addr:housenumber":"3",
    "addr:postcode":"rg24 9pq",
    "addr:street":"Tasmania Close",
    "iso:country":"GB",
    "sg:address":"3 Tasmania Close",
    "sg:city":"Basingstoke",
    "sg:classifiers":[
        {
            "category":"Professional",
            "subcategory":"Computer Services",
            "type":"Services"
        }
    ],
    "sg:phone":"+44 1256 331957",
    "sg:postcode":"RG24 9PQ",
    "sg:province":"Hampshire",
    "sg:tags":[
        "system",
        "software"
    ],
    "wof:name":"Pettigrain Ltd.",
    "wof:placetype":"venue"
},
  "geometry": {"coordinates":[-1.082205,51.288177],"type":"Point"}
}