{
  "type": "Feature",
  "properties": {
    "addr:full":"Richmond Rise, Portchester Fareham Hampshire PO16 8DG",
    "addr:postcode":"po16 8dg",
    "addr:street":"Richmond Rise",
    "iso:country":"GB",
    "sg:address":"Richmond Rise, Portchester",
    "sg:city":"Fareham",
    "sg:classifiers":[
        {
            "category":"Education",
            "subcategory":"School",
            "type":"Public Place"
        }
    ],
    "sg:phone":"+44 23 9237 0693",
    "sg:postcode":"PO16 8DG",
    "sg:province":"Hampshire",
    "sg:tags":[
        "local",
        "authority"
    ],
    "wof:name":"Northern Infant School",
    "wof:placetype":"venue"
},
  "geometry": {"coordinates":[-1.1295340061,50.852180481],"type":"Point"}
}