{
  "type": "Feature",
  "properties": {
    "addr:full":"Office, 13 Transport Offices, Park, Paddocks Queensbury Rd Newmarket Cambridgeshire CB8 9AU",
    "addr:housenumber":"13",
    "addr:postcode":"cb8 9au",
    "addr:street":"Park Paddocks Queensbury Rd",
    "iso:country":"GB",
    "sg:address":"Office, 13 Transport Offices, Park, Paddocks Queensbury Rd",
    "sg:city":"Newmarket",
    "sg:classifiers":[
        {
            "category":"Retail",
            "subcategory":"Animal Services",
            "type":"Services"
        }
    ],
    "sg:phone":"+44 1638 667779",
    "sg:postcode":"CB8 9AU",
    "sg:province":"Cambridgeshire",
    "sg:tags":[
        "box",
        "horse",
        "transporting"
    ],
    "wof:name":"Weyhill Horse Transport",
    "wof:placetype":"venue"
},
  "geometry": {"coordinates":[0.399166,52.249817],"type":"Point"}
}