{
  "type": "Feature",
  "properties": {
    "addr:full":"The Lynch House, Welsh Street Bishops Castle Shropshire SY9 5BS",
    "addr:postcode":"sy9 5bs",
    "addr:street":"The;Welsh Street",
    "iso:country":"GB",
    "sg:address":"The Lynch House, Welsh Street",
    "sg:city":"Bishops Castle",
    "sg:classifiers":[
        {
            "category":"Farming",
            "subcategory":"Farm",
            "type":"Manufacturing & Wholesale Goods"
        }
    ],
    "sg:postcode":"SY9 5BS",
    "sg:province":"Shropshire",
    "sg:tags":[
        "mixed",
        "crop"
    ],
    "wof:name":"F T Bedell & Son",
    "wof:placetype":"venue"
},
  "geometry": {"coordinates":[-2.998866,52.494701],"type":"Point"}
}