{
  "type": "Feature",
  "properties": {
    "addr:full":"North Lane House, 9b North Lane Leeds West Yorkshire LS6 3HG",
    "addr:housenumber":"9b",
    "addr:postcode":"ls6 3hg",
    "addr:street":"North Lane House;North Lane",
    "iso:country":"GB",
    "sg:address":"North Lane House, 9b North Lane",
    "sg:city":"Leeds",
    "sg:classifiers":[
        {
            "category":"Professional",
            "subcategory":"Computer Services",
            "type":"Services"
        }
    ],
    "sg:phone":"+44 113 217 2506",
    "sg:postcode":"LS6 3HG",
    "sg:province":"West Yorkshire",
    "sg:tags":[
        "system",
        "software"
    ],
    "wof:name":"Prime Numbers",
    "wof:placetype":"venue"
},
  "geometry": {"coordinates":[-1.578798,53.821041],"type":"Point"}
}