{
  "type": "Feature",
  "properties": {
    "iso:country":"GB",
    "sg:address":"Heath End Road",
    "sg:city":"Nuneaton",
    "sg:classifiers":[
        {
            "category":"Home & Garden",
            "subcategory":"Hardware",
            "type":"Retail Goods"
        }
    ],
    "sg:phone":"+44 24 7664 1253",
    "sg:postcode":"CV10 7JB",
    "sg:province":"Leicestershire",
    "sg:tags":[
        "device",
        "fixing",
        "fastener"
    ],
    "wof:name":"Shautatali Abdulhyssein",
    "wof:placetype":"venue"
},
  "geometry": {"coordinates":[-1.4960540533,52.5151481628],"type":"Point"}
}