{
  "type": "Feature",
  "properties": {
    "addr:full":"22 Darrell Close Herne Bay Kent CT6 7QQ",
    "addr:housenumber":"22",
    "addr:postcode":"ct6 7qq",
    "addr:street":"Darrell Close",
    "iso:country":"GB",
    "sg:address":"22 Darrell Close",
    "sg:city":"Herne Bay",
    "sg:classifiers":[
        {
            "category":"Home & Garden",
            "subcategory":"Carpets & Floor Coverings",
            "type":"Retail Goods"
        }
    ],
    "sg:postcode":"CT6 7QQ",
    "sg:province":"Kent",
    "sg:tags":[
        "carpets",
        "rug",
        "matting"
    ],
    "wof:name":"Mark Dodge",
    "wof:placetype":"venue"
},
  "geometry": {"coordinates":[1.1060390472,51.3624191284],"type":"Point"}
}