{
  "type": "Feature",
  "properties": {
    "addr:full":"Marrowbone Slip, Sutton Rd Plymouth Devon PL4 0HX",
    "addr:postcode":"pl4 0hx",
    "addr:street":"Marrowbone Slip Sutton Rd",
    "iso:country":"GB",
    "sg:address":"Marrowbone Slip, Sutton Rd",
    "sg:city":"Plymouth",
    "sg:classifiers":[
        {
            "category":"Autos & Motor Vehicles",
            "subcategory":"Boat Sales",
            "type":"Retail Goods"
        },
        {
            "category":"Retail",
            "subcategory":"Event Space",
            "type":"Services"
        }
    ],
    "sg:phone":"+44 1752 228569",
    "sg:postcode":"PL4 0HX",
    "sg:province":"Devon",
    "sg:tags":[
        "repair",
        "builder"
    ],
    "wof:name":"Harbour Marine Leisure",
    "wof:placetype":"venue"
},
  "geometry": {"coordinates":[-4.130589962,50.3691902161],"type":"Point"}
}