{
  "type": "Feature",
  "properties": {
    "iso:country":"GB",
    "sg:address":"75 Lambhay Hill",
    "sg:city":"Plymouth",
    "sg:classifiers":[
        {
            "category":"Bars & Pubs",
            "type":"Food & Drink"
        }
    ],
    "sg:phone":"+44 1752 669687",
    "sg:postcode":"PL1 2NR",
    "sg:province":"Devon",
    "sg:tags":[
        "pubs",
        "inn"
    ],
    "wof:name":"Commercial Inn",
    "wof:placetype":"venue"
},
  "geometry": {"coordinates":[-4.134892,50.365597],"type":"Point"}
}