{
  "type": "Feature",
  "properties": {
    "iso:country":"GB",
    "sg:address":"Church Road",
    "sg:city":"Lytham St Annes",
    "sg:classifiers":[
        {
            "category":"Government",
            "subcategory":"City Hall",
            "type":"Public Place"
        },
        {
            "category":"Place Of Worship",
            "type":"Public Place"
        }
    ],
    "sg:phone":"+44 1253 796026",
    "sg:postcode":"FY8 5QL",
    "sg:province":"Lancashire",
    "wof:name":"St.Cuthberts Church of England Church Hall",
    "wof:placetype":"venue"
},
  "geometry": {"coordinates":[-2.980285,53.737759],"type":"Point"}
}