{
  "type": "Feature",
  "properties": {
    "iso:country":"GB",
    "sg:address":"Rice Lane",
    "sg:city":"Liverpool",
    "sg:classifiers":[
        {
            "category":"Autos & Motor Vehicles",
            "subcategory":"Fuel & Gas Station",
            "type":"Retail Goods"
        }
    ],
    "sg:phone":"+44 151 524 1478",
    "sg:postcode":"L9 1AE",
    "sg:province":"Merseyside",
    "sg:tags":[
        "hr",
        "petrol"
    ],
    "wof:name":"Elf Oil U K Ltd.",
    "wof:placetype":"venue"
},
  "geometry": {"coordinates":[-2.961719,53.45541],"type":"Point"}
}