{
  "type": "Feature",
  "properties": {
    "addr:full":"Wellbrook Court, Girton Road Cambridge Cambridgeshire CB3 0NA",
    "addr:postcode":"cb3 0na",
    "addr:street":"Wellbrook Court Girton Road",
    "iso:country":"GB",
    "sg:address":"Wellbrook Court, Girton Road",
    "sg:city":"Cambridge",
    "sg:classifiers":[
        {
            "category":"Professional",
            "subcategory":"Engineering",
            "type":"Services"
        }
    ],
    "sg:phone":"+44 1223 276002",
    "sg:postcode":"CB3 0NA",
    "sg:province":"Cambridgeshire",
    "sg:tags":[
        "consulting",
        "engineer"
    ],
    "wof:name":"Atkins Consultants Ltd.",
    "wof:placetype":"venue"
},
  "geometry": {"coordinates":[0.0859199986,52.2319564819],"type":"Point"}
}