{
  "type": "Feature",
  "properties": {
    "addr:full":"18 Finucane Gardens Rainham Essex RM13 7QA",
    "addr:housenumber":"18",
    "addr:postcode":"rm13 7qa",
    "addr:street":"Finucane Gardens",
    "iso:country":"GB",
    "sg:address":"18 Finucane Gardens",
    "sg:city":"Rainham",
    "sg:classifiers":[
        {
            "category":"Building & Trades",
            "subcategory":"Construction",
            "type":"Services"
        }
    ],
    "sg:phone":"+44 1708 559340",
    "sg:postcode":"RM13 7QA",
    "sg:province":"Essex",
    "sg:tags":[
        "roofing"
    ],
    "wof:name":"Laurick",
    "wof:placetype":"venue"
},
  "geometry": {"coordinates":[0.196377,51.542873],"type":"Point"}
}