{
  "type": "Feature",
  "properties": {
    "addr:full":"Ledbury House, Alexandra Way Tewkesbury Gloucestershire GL20 8NB",
    "addr:postcode":"gl20 8nb",
    "addr:street":"Alexandra Way",
    "iso:country":"GB",
    "sg:address":"Ledbury House, Alexandra Way",
    "sg:city":"Tewkesbury",
    "sg:classifiers":[
        {
            "category":"Professional",
            "type":"Services"
        }
    ],
    "sg:phone":"+44 1684 850650",
    "sg:postcode":"GL20 8NB",
    "sg:province":"Gloucestershire",
    "sg:tags":[
        "display",
        "maker"
    ],
    "wof:name":"Adglow (Installations) Ltd.",
    "wof:placetype":"venue"
},
  "geometry": {"coordinates":[-2.1197390556,51.9976844788],"type":"Point"}
}