{
  "type": "Feature",
  "properties": {
    "iso:country":"GB",
    "sg:address":"177 London Rd, Cowplain",
    "sg:city":"Havant",
    "sg:classifiers":[
        {
            "category":"Manufacturing",
            "subcategory":"Building Materials",
            "type":"Manufacturing & Wholesale Goods"
        }
    ],
    "sg:phone":"+44 23 9261 1221",
    "sg:postcode":"PO9 1BD",
    "sg:province":"Hampshire",
    "sg:tags":[
        "stonemason"
    ],
    "wof:name":"ABS",
    "wof:placetype":"venue"
},
  "geometry": {"coordinates":[-0.9855440259,50.8544960022],"type":"Point"}
}