{
  "type": "Feature",
  "properties": {
    "iso:country":"GB",
    "sg:address":"108 Cathays Terrace",
    "sg:city":"Cardiff",
    "sg:classifiers":[
        {
            "category":"Wholesale",
            "subcategory":"Office Equipment",
            "type":"Manufacturing & Wholesale Goods"
        }
    ],
    "sg:phone":"+44 1656 653251",
    "sg:postcode":"CF2 4HY",
    "sg:province":"Cardiff",
    "sg:tags":[
        "register",
        "cash",
        "accessory"
    ],
    "wof:name":"Alfa Cash Reg",
    "wof:placetype":"venue"
},
  "geometry": {"coordinates":[-3.181451,51.493553],"type":"Point"}
}