{
  "type": "Feature",
  "properties": {
    "addr:full":"The Coach House, Little Silver Stephenstone Torrington Devon EX38 7HX",
    "addr:postcode":"ex38 7hx",
    "iso:country":"GB",
    "sg:address":"The Coach House, Little Silver Stephenstone",
    "sg:city":"Torrington",
    "sg:classifiers":[
        {
            "category":"Building & Trades",
            "subcategory":"Construction",
            "type":"Services"
        }
    ],
    "sg:phone":"+44 1805 624525",
    "sg:postcode":"EX38 7HX",
    "sg:province":"Devon",
    "sg:tags":[
        "builder"
    ],
    "wof:name":"Graham Brend",
    "wof:placetype":"venue"
},
  "geometry": {"coordinates":[-4.1422548294,50.9531517029],"type":"Point"}
}