{
  "type": "Feature",
  "properties": {
    "iso:country":"GB",
    "sg:address":"Dairy House Lane, Dunham Massey",
    "sg:city":"Altrincham",
    "sg:classifiers":[
        {
            "category":"Retail",
            "subcategory":"Auto Repair",
            "type":"Services"
        }
    ],
    "sg:phone":"+44 161 928 0664",
    "sg:postcode":"WA14 5RD",
    "sg:province":"Cheshire",
    "sg:tags":[
        "modification",
        "garage"
    ],
    "wof:name":"Scoltock & Jones",
    "wof:placetype":"venue"
},
  "geometry": {"coordinates":[-2.369575,53.400215],"type":"Point"}
}