{
  "type": "Feature",
  "properties": {
    "addr:full":"40 Eld Lane Colchester Essex CO1 1LS",
    "addr:housenumber":"40",
    "addr:postcode":"co1 1ls",
    "addr:street":"Eld Lane",
    "iso:country":"GB",
    "sg:address":"40 Eld Lane",
    "sg:city":"Colchester",
    "sg:classifiers":[
        {
            "category":"Shopping",
            "subcategory":"Books",
            "type":"Retail Goods"
        }
    ],
    "sg:phone":"+44 1206 579665",
    "sg:postcode":"CO1 1LS",
    "sg:province":"Essex",
    "sg:tags":[
        "bookseller"
    ],
    "wof:name":"Sign of the Fish Christian Bookshop",
    "wof:placetype":"venue"
},
  "geometry": {"coordinates":[0.90068,51.887859],"type":"Point"}
}