{
  "type": "Feature",
  "properties": {
    "addr:full":"1450a London Rd Leigh-on-sea Essex SS9 2UW",
    "addr:housenumber":"1450a",
    "addr:postcode":"ss9 2uw",
    "addr:street":"London Rd",
    "iso:country":"GB",
    "sg:address":"1450a London Rd",
    "sg:city":"Leigh-on-sea",
    "sg:classifiers":[
        {
            "category":"Autos & Motor Vehicles",
            "subcategory":"Automobile Sales",
            "type":"Retail Goods"
        },
        {
            "category":"Building & Trades",
            "subcategory":"Construction",
            "type":"Services"
        }
    ],
    "sg:postcode":"SS9 2UW",
    "sg:province":"Essex",
    "sg:tags":[
        "car",
        "builder"
    ],
    "wof:name":"Specialist Building Services",
    "wof:placetype":"venue"
},
  "geometry": {"coordinates":[0.6339840293,51.5480728149],"type":"Point"}
}