{
  "type": "Feature",
  "properties": {
    "addr:full":"Maygay Machines Ltd, Maygay House Wolverhampton Staffordshire WV10 9NL",
    "addr:housenumber":"maygay",
    "addr:postcode":"wv10 9nl",
    "iso:country":"GB",
    "sg:address":"Maygay Machines Ltd, Maygay House",
    "sg:city":"Wolverhampton",
    "sg:classifiers":[
        {
            "category":"Professional",
            "subcategory":"Computer Services",
            "type":"Services"
        }
    ],
    "sg:postcode":"WV10 9NL",
    "sg:province":"Staffordshire",
    "sg:tags":[
        "system",
        "software"
    ],
    "wof:name":"Impulse Gaming Ltd.",
    "wof:placetype":"venue"
},
  "geometry": {"coordinates":[-2.1117839813,52.5999145508],"type":"Point"}
}