{
  "type": "Feature",
  "properties": {
    "addr:full":"The Byrth Farm, Weston Road, Baschurch Shrewsbury Shropshire SY4 2DE",
    "addr:postcode":"sy4 2de",
    "addr:street":"Weston Road",
    "iso:country":"GB",
    "sg:address":"The Byrth Farm, Weston Road, Baschurch",
    "sg:city":"Shrewsbury",
    "sg:classifiers":[
        {
            "category":"Farming",
            "subcategory":"Livestock Farm",
            "type":"Manufacturing & Wholesale Goods"
        }
    ],
    "sg:postcode":"SY4 2DE",
    "sg:province":"Shropshire",
    "sg:tags":[
        "others"
    ],
    "wof:name":"T H & I Ellis & Sons",
    "wof:placetype":"venue"
},
  "geometry": {"coordinates":[-2.85266,52.787228],"type":"Point"}
}