{
  "type": "Feature",
  "properties": {
    "addr:full":"The Surgery, St Marys Rd Newbury Berkshire RG14 1ES",
    "addr:postcode":"rg14 1es",
    "addr:street":"St Marys Rd",
    "iso:country":"GB",
    "sg:address":"The Surgery, St Marys Rd",
    "sg:city":"Newbury",
    "sg:classifiers":[
        {
            "category":"Health Services",
            "subcategory":"Doctor",
            "type":"Services"
        }
    ],
    "sg:phone":"+44 1635 31444",
    "sg:postcode":"RG14 1ES",
    "sg:province":"Berkshire",
    "sg:tags":[
        "practitioners"
    ],
    "wof:name":"Stiff, G H",
    "wof:placetype":"venue"
},
  "geometry": {"coordinates":[-1.319498,51.405293],"type":"Point"}
}