{
  "type": "Feature",
  "properties": {
    "addr:full":"20 Mill Road Ingatestone Essex CM4 9LJ",
    "addr:housenumber":"20",
    "addr:postcode":"cm4 9lj",
    "addr:street":"Mill Road",
    "iso:country":"GB",
    "sg:address":"20 Mill Road",
    "sg:city":"Ingatestone",
    "sg:classifiers":[
        {
            "category":"Food & Beverages",
            "subcategory":"Meat & Fish",
            "type":"Retail Goods"
        }
    ],
    "sg:postcode":"CM4 9LJ",
    "sg:province":"Essex",
    "sg:tags":[
        "chip"
    ],
    "wof:name":"Swift,Roger,",
    "wof:placetype":"venue"
},
  "geometry": {"coordinates":[0.4427709877,51.6630935669],"type":"Point"}
}