{
  "type": "Feature",
  "properties": {
    "addr:full":"Greenway Road Bilston West Midlands WV14 0TA",
    "addr:postcode":"wv14 0ta",
    "addr:street":"Greenway Road",
    "iso:country":"GB",
    "sg:address":"Greenway Road",
    "sg:city":"Bilston",
    "sg:classifiers":[
        {
            "category":"Retail",
            "subcategory":"Auto Repair",
            "type":"Services"
        }
    ],
    "sg:phone":"+44 1902 404855",
    "sg:postcode":"WV14 0TA",
    "sg:province":"West Midlands",
    "sg:tags":[
        "modification",
        "garage"
    ],
    "wof:name":"V S Motors",
    "wof:placetype":"venue"
},
  "geometry": {"coordinates":[-2.0744900703,52.5666351318],"type":"Point"}
}