{
  "type": "Feature",
  "properties": {
    "addr:full":"72 Tolworth Broadway Surbiton Surrey KT6 7HR",
    "addr:housenumber":"72",
    "addr:postcode":"kt6 7hr",
    "addr:street":"Tolworth Broadway",
    "iso:country":"GB",
    "sg:address":"72 Tolworth Broadway",
    "sg:city":"Surbiton",
    "sg:classifiers":[
        {
            "category":"Food & Beverages",
            "subcategory":"Fruits & Vegetables",
            "type":"Retail Goods"
        }
    ],
    "sg:phone":"+44 20 8390 6706",
    "sg:postcode":"KT6 7HR",
    "sg:province":"Surrey",
    "sg:tags":[
        "greengrocer"
    ],
    "wof:name":"SELECT A FRUITS",
    "wof:placetype":"venue"
},
  "geometry": {"coordinates":[-0.297672987,51.377243042],"type":"Point"}
}