{
  "type": "Feature",
  "properties": {
    "iso:country":"GB",
    "sg:address":"4 High Street, Botley",
    "sg:city":"Southampton",
    "sg:classifiers":[
        {
            "category":"Professional",
            "subcategory":"Art Services",
            "type":"Services"
        }
    ],
    "sg:phone":"+44 1489 785569",
    "sg:postcode":"SO30 2EA",
    "sg:province":"Hampshire",
    "sg:tags":[
        "photographer"
    ],
    "wof:name":"Gary Chase Photography",
    "wof:placetype":"venue"
},
  "geometry": {"coordinates":[-1.2701,50.914444],"type":"Point"}
}