{
  "type": "Feature",
  "properties": {
    "addr:full":"6 Northlands Road Southampton Hampshire SO15 2LF",
    "addr:housenumber":"6",
    "addr:postcode":"so15 2lf",
    "addr:street":"Northlands Road",
    "iso:country":"GB",
    "sg:address":"6 Northlands Road",
    "sg:city":"Southampton",
    "sg:classifiers":[
        {
            "category":"Professional",
            "subcategory":"Secretarial Services",
            "type":"Services"
        },
        {
            "category":"Wholesale",
            "subcategory":"Computers",
            "type":"Manufacturing & Wholesale Goods"
        },
        {
            "category":"Professional",
            "subcategory":"Computer Services",
            "type":"Services"
        }
    ],
    "sg:phone":"+44 23 8023 5280",
    "sg:postcode":"SO15 2LF",
    "sg:province":"Hampshire",
    "sg:tags":[
        "supplier",
        "consultant",
        "consumables"
    ],
    "wof:name":"J & T Systems Ltd.",
    "wof:placetype":"venue"
},
  "geometry": {"coordinates":[-1.408008,50.921196],"type":"Point"}
}