{
  "type": "Feature",
  "properties": {
    "iso:country":"GB",
    "sg:address":"24 Kirkland",
    "sg:city":"Kendal",
    "sg:classifiers":[
        {
            "category":"Health Services",
            "subcategory":"Dentist",
            "type":"Services"
        }
    ],
    "sg:postcode":"LA9 5AD",
    "sg:province":"Cumbria",
    "wof:name":"C T Tinn",
    "wof:placetype":"venue"
},
  "geometry": {"coordinates":[-2.746343,54.322548],"type":"Point"}
}