{
  "type": "Feature",
  "properties": {
    "iso:country":"GB",
    "sg:address":", Milton",
    "sg:city":"Tenby",
    "sg:classifiers":[
        {
            "category":"Bars & Pubs",
            "type":"Food & Drink"
        }
    ],
    "sg:phone":"+44 1646 651202",
    "sg:postcode":"SA70 8PH",
    "sg:province":"Pembrokeshire",
    "sg:tags":[
        "pubs",
        "inn"
    ],
    "wof:name":"Milton Brewery Inn",
    "wof:placetype":"venue"
},
  "geometry": {"coordinates":[-4.712056,51.6768],"type":"Point"}
}