{
  "type": "Feature",
  "properties": {
    "addr:full":"18 Warwick Road Redhill Surrey RH1 1BU",
    "addr:housenumber":"18",
    "addr:postcode":"rh1 1bu",
    "addr:street":"Warwick Road",
    "iso:country":"GB",
    "sg:address":"18 Warwick Road",
    "sg:city":"Redhill",
    "sg:classifiers":[
        {
            "category":"Organizations",
            "subcategory":"Political Organization",
            "type":"Services"
        }
    ],
    "sg:postcode":"RH1 1BU",
    "sg:province":"Surrey",
    "sg:tags":[
        "party"
    ],
    "wof:name":"Reigate Conservative Association",
    "wof:placetype":"venue"
},
  "geometry": {"coordinates":[-0.1703090072,51.2414131165],"type":"Point"}
}