{
  "type": "Feature",
  "properties": {
    "addr:full":"Fairview, Orby Road, Addlethorpe Skegness Lincolnshire PE24 4TR",
    "addr:postcode":"pe24 4tr",
    "addr:street":"Orby Road",
    "iso:country":"GB",
    "sg:address":"Fairview, Orby Road, Addlethorpe",
    "sg:city":"Skegness",
    "sg:classifiers":[
        {
            "category":"Park",
            "subcategory":"Provincial",
            "type":"Public Place"
        },
        {
            "category":"Farming",
            "subcategory":"Livestock Farm",
            "type":"Manufacturing & Wholesale Goods"
        },
        {
            "category":"Recreation",
            "subcategory":"Campground",
            "type":"Entertainment"
        }
    ],
    "sg:phone":"+44 1754 872598",
    "sg:postcode":"PE24 4TR",
    "sg:province":"Lincolnshire",
    "sg:tags":[
        "holiday",
        "camp",
        "others",
        "centre"
    ],
    "wof:name":"Cottage Farm Camp",
    "wof:placetype":"venue"
},
  "geometry": {"coordinates":[0.3173950016,53.1950645447],"type":"Point"}
}