{
  "type": "Feature",
  "properties": {
    "iso:country":"GB",
    "sg:address":"Newton Mill",
    "sg:city":"Hyde",
    "sg:classifiers":[
        {
            "category":"Retail",
            "subcategory":"Repair Shop",
            "type":"Services"
        }
    ],
    "sg:phone":"+44 161 366 8632",
    "sg:postcode":"SK14 4LE",
    "sg:province":"Cheshire",
    "sg:tags":[
        "plant",
        "machinery"
    ],
    "wof:name":"Woodrow Royale",
    "wof:placetype":"venue"
},
  "geometry": {"coordinates":[-2.083548,53.455353],"type":"Point"}
}