{
  "type": "Feature",
  "properties": {
    "addr:full":"15a Plains Road Nottingham Nottinghamshire NG3 5LG",
    "addr:housenumber":"15a",
    "addr:postcode":"ng3 5lg",
    "addr:street":"Plains Road",
    "iso:country":"GB",
    "sg:address":"15a Plains Road",
    "sg:city":"Nottingham",
    "sg:classifiers":[
        {
            "category":"Home & Garden",
            "subcategory":"Home Furnishings",
            "type":"Retail Goods"
        }
    ],
    "sg:phone":"+44 115 960 5221",
    "sg:postcode":"NG3 5LG",
    "sg:province":"Nottinghamshire",
    "sg:tags":[
        "beds",
        "bedding",
        "blanket"
    ],
    "wof:name":"Mapperley Bed Centre",
    "wof:placetype":"venue"
},
  "geometry": {"coordinates":[-1.1218990088,52.9842453003],"type":"Point"}
}