{
  "type": "Feature",
  "properties": {
    "addr:full":"12 Barken Road Chippenham Gloucestershire SN14 0JZ",
    "addr:housenumber":"12",
    "addr:postcode":"sn14 0jz",
    "addr:street":"Barken Road",
    "iso:country":"GB",
    "sg:address":"12 Barken Road",
    "sg:city":"Chippenham",
    "sg:classifiers":[
        {
            "category":"Building & Trades",
            "subcategory":"Plumbing",
            "type":"Services"
        }
    ],
    "sg:phone":"+44 1249 658981",
    "sg:postcode":"SN14 0JZ",
    "sg:province":"Gloucestershire",
    "sg:tags":[
        "central",
        "installation",
        "system",
        "servicing",
        "heating"
    ],
    "wof:name":"Colin Thom",
    "wof:placetype":"venue"
},
  "geometry": {"coordinates":[-2.140668,51.465061],"type":"Point"}
}