{
  "type": "Feature",
  "properties": {
    "iso:country":"GB",
    "sg:address":"89 Carnglas Road, Sketty",
    "sg:city":"Swansea",
    "sg:classifiers":[
        {
            "category":"Shopping",
            "subcategory":"Pharmacy",
            "type":"Retail Goods"
        }
    ],
    "sg:phone":"+44 1792 203193",
    "sg:postcode":"SA2 9BN",
    "sg:province":"Swansea",
    "sg:tags":[
        "pharmacist",
        "chemist"
    ],
    "wof:name":"Christine Jones",
    "wof:placetype":"venue"
},
  "geometry": {"coordinates":[-3.991702,51.622787],"type":"Point"}
}