{
  "type": "Feature",
  "properties": {
    "iso:country":"GB",
    "sg:address":"2 Rosethorn, Glade Wood, Middleton",
    "sg:city":"Manchester",
    "sg:classifiers":[
        {
            "category":"Professional",
            "subcategory":"Employment Agencies",
            "type":"Services"
        }
    ],
    "sg:postcode":"M24 6GP",
    "sg:province":"Greater Manchester",
    "sg:tags":[
        "consultant"
    ],
    "wof:name":"Flynn,John L,",
    "wof:placetype":"venue"
},
  "geometry": {"coordinates":[-2.203111,53.565594],"type":"Point"}
}