{
  "type": "Feature",
  "properties": {
    "iso:country":"GB",
    "sg:address":"87-89 Loch Street",
    "sg:city":"Aberdeen",
    "sg:classifiers":[
        {
            "category":"Bars & Pubs",
            "type":"Food & Drink"
        },
        {
            "category":"Community Center",
            "subcategory":"Social",
            "type":"Public Place"
        }
    ],
    "sg:phone":"+44 1224 636740",
    "sg:postcode":"AB25 1DH",
    "sg:province":"Aberdeen City",
    "sg:tags":[
        "pubs",
        "house",
        "inn",
        "activity"
    ],
    "wof:name":"Lochside Bar",
    "wof:placetype":"venue"
},
  "geometry": {"coordinates":[-2.101013,57.151173],"type":"Point"}
}