{
  "type": "Feature",
  "properties": {
    "iso:country":"GB",
    "sg:address":"6/7 Market Pl",
    "sg:city":"Devizes",
    "sg:classifiers":[
        {
            "category":"Building & Trades",
            "subcategory":"Construction",
            "type":"Services"
        }
    ],
    "sg:postcode":"SN10 1HT",
    "sg:province":"Wiltshire",
    "sg:tags":[
        "joiner",
        "carpenter"
    ],
    "wof:name":"Hazelcliff Ltd",
    "wof:placetype":"venue"
},
  "geometry": {"coordinates":[-1.995904,51.352276],"type":"Point"}
}