{
  "type": "Feature",
  "properties": {
    "addr:full":"6/7 Market Pl Devizes Wiltshire SN10 1HT",
    "addr:housenumber":"6 / 7",
    "addr:postcode":"sn10 1ht",
    "addr:street":"Market Pl",
    "iso:country":"GB",
    "sg:address":"6/7 Market Pl",
    "sg:city":"Devizes",
    "sg:classifiers":[
        {
            "category":"Building & Trades",
            "subcategory":"Construction",
            "type":"Services"
        }
    ],
    "sg:postcode":"SN10 1HT",
    "sg:province":"Wiltshire",
    "sg:tags":[
        "joiner",
        "carpenter"
    ],
    "wof:name":"Hazelcliff Ltd",
    "wof:placetype":"venue"
},
  "geometry": {"coordinates":[-1.995904,51.352276],"type":"Point"}
}