{
  "type": "Feature",
  "properties": {
    "addr:full":"270 Kentish Town Road London Greater London NW5 2AA",
    "addr:housenumber":"270",
    "addr:postcode":"nw5 2aa",
    "addr:street":"Kentish Town Road",
    "iso:country":"GB",
    "sg:address":"270 Kentish Town Road",
    "sg:city":"London",
    "sg:classifiers":[
        {
            "category":"Professional",
            "subcategory":"Business Services",
            "type":"Services"
        }
    ],
    "sg:phone":"+44 20 7485 9455",
    "sg:postcode":"NW5 2AA",
    "sg:province":"Greater London",
    "sg:tags":[
        "tile",
        "stockist"
    ],
    "wof:name":"T W S Ceramics Ltd.",
    "wof:placetype":"venue"
},
  "geometry": {"coordinates":[-0.140705,51.549747],"type":"Point"}
}