{
  "type": "Feature",
  "properties": {
    "addr:full":"43 Worple Road London Greater London SW19 4JZ",
    "addr:housenumber":"43",
    "addr:postcode":"sw19 4jz",
    "addr:street":"Worple Road",
    "iso:country":"GB",
    "sg:address":"43 Worple Road",
    "sg:city":"London",
    "sg:classifiers":[
        {
            "category":"Travel",
            "subcategory":"Hotels & Motels",
            "type":"Entertainment"
        }
    ],
    "sg:phone":"+44 20 8947 4271",
    "sg:postcode":"SW19 4JZ",
    "sg:province":"Greater London",
    "wof:name":"Justin James Hotel",
    "wof:placetype":"venue"
},
  "geometry": {"coordinates":[-0.2111420035,51.4201927185],"type":"Point"}
}