{
  "type": "Feature",
  "properties": {
    "iso:country":"GB",
    "sg:address":"250 Old Road West",
    "sg:city":"Gravesend",
    "sg:classifiers":[
        {
            "category":"Home & Garden",
            "subcategory":"Home Furnishings",
            "type":"Retail Goods"
        }
    ],
    "sg:postcode":"DA11 0LY",
    "sg:province":"Kent",
    "sg:tags":[
        "awning",
        "canopy",
        "blinds"
    ],
    "wof:name":"Deans Southern",
    "wof:placetype":"venue"
},
  "geometry": {"coordinates":[0.354962,51.43594],"type":"Point"}
}