{
  "type": "Feature",
  "properties": {
    "iso:country":"GB",
    "sg:address":"139 Hampton Lane",
    "sg:city":"Southampton",
    "sg:classifiers":[
        {
            "category":"Food & Beverages",
            "subcategory":"Bakery",
            "type":"Retail Goods"
        }
    ],
    "sg:phone":"+44 23 8089 8688",
    "sg:postcode":"SO45 1WE",
    "sg:province":"Hampshire",
    "sg:tags":[
        "baker"
    ],
    "wof:name":"Engels Bakery",
    "wof:placetype":"venue"
},
  "geometry": {"coordinates":[-1.372151,50.817402],"type":"Point"}
}