{
  "type": "Feature",
  "properties": {
    "addr:full":"4 Greens Yard, St Marys Road Frinton-on-sea Essex CO13 9HT",
    "addr:housenumber":"4",
    "addr:postcode":"co13 9ht",
    "addr:street":"Greens Yard;Marys Road",
    "iso:country":"GB",
    "sg:address":"4 Greens Yard, St Marys Road",
    "sg:city":"Frinton-on-sea",
    "sg:classifiers":[
        {
            "category":"Home & Garden",
            "subcategory":"Home Furnishings",
            "type":"Retail Goods"
        }
    ],
    "sg:postcode":"CO13 9HT",
    "sg:province":"Essex",
    "sg:tags":[
        "decorative",
        "glass",
        "mirror"
    ],
    "wof:name":"The Green Parrot Trading Co",
    "wof:placetype":"venue"
},
  "geometry": {"coordinates":[1.250405,51.834923],"type":"Point"}
}