{
  "type": "Feature",
  "properties": {
    "iso:country":"GB",
    "sg:address":"Mochdre",
    "sg:city":"Colwyn Bay",
    "sg:classifiers":[
        {
            "category":"Restaurant",
            "type":"Food & Drink"
        }
    ],
    "sg:postcode":"LL28 5AT",
    "sg:province":"Conwy",
    "wof:name":"Mountain View Hotel",
    "wof:placetype":"venue"
},
  "geometry": {"coordinates":[-3.76228,53.29007],"type":"Point"}
}