{
  "type": "Feature",
  "properties": {
    "addr:full":"The e.volve Centre, Rainton Bridge Business Park Cygnet Way Houghton le Spring DH4 5QY",
    "addr:postcode":"dh4 5qy",
    "addr:street":"Bridge Business Park Cygnet Way",
    "iso:country":"GB",
    "sg:address":"The e.volve Centre, Rainton Bridge Business Park Cygnet Way",
    "sg:city":"Houghton le Spring",
    "sg:classifiers":[
        {
            "category":"Professional",
            "subcategory":"Computer Services",
            "type":"Services"
        }
    ],
    "sg:postcode":"DH4 5QY",
    "sg:website":"http://www.guroo.co.uk",
    "wof:name":"Guroo",
    "wof:placetype":"venue"
},
  "geometry": {"coordinates":[-1.4865094,54.8447924],"type":"Point"}
}