{
  "type": "Feature",
  "properties": {
    "addr:full":"113 Cambridge Road Royston Bedfordshire SG8 5QB",
    "addr:housenumber":"113",
    "addr:postcode":"sg8 5qb",
    "addr:street":"Cambridge Road",
    "iso:country":"GB",
    "sg:address":"113 Cambridge Road",
    "sg:city":"Royston",
    "sg:classifiers":[
        {
            "category":"Cafe",
            "type":"Food & Drink"
        }
    ],
    "sg:phone":"+44 1223 207370",
    "sg:postcode":"SG8 5QB",
    "sg:province":"Bedfordshire",
    "sg:tags":[
        "tea",
        "room"
    ],
    "wof:name":"Autostop Cafe",
    "wof:placetype":"venue"
},
  "geometry": {"coordinates":[-0.0438910015,52.1254653931],"type":"Point"}
}