{
  "type": "Feature",
  "properties": {
    "addr:full":"14 Haredale Road London Greater London SE24 0AF",
    "addr:housenumber":"14",
    "addr:postcode":"se24 0af",
    "addr:street":"Haredale Road",
    "iso:country":"GB",
    "sg:address":"14 Haredale Road",
    "sg:city":"London",
    "sg:classifiers":[
        {
            "category":"Building & Trades",
            "subcategory":"Landscaping Services",
            "type":"Services"
        }
    ],
    "sg:postcode":"SE24 0AF",
    "sg:province":"Greater London",
    "sg:tags":[
        "gardening"
    ],
    "wof:name":"Green Man Gardening",
    "wof:placetype":"venue"
},
  "geometry": {"coordinates":[-0.0962330028,51.4602432251],"type":"Point"}
}