{
  "type": "Feature",
  "properties": {
    "addr:full":"24 Essington Light Industrial Estate, Bognop Road, Essington Wolverhampton Staffordshire WV11 2BH",
    "addr:housenumber":"24",
    "addr:postcode":"wv11 2bh",
    "addr:street":"Essington Light Industrial;Bognop Road",
    "iso:country":"GB",
    "sg:address":"24 Essington Light Industrial Estate, Bognop Road, Essington",
    "sg:city":"Wolverhampton",
    "sg:classifiers":[
        {
            "category":"Retail",
            "subcategory":"Auto Repair",
            "type":"Services"
        }
    ],
    "sg:phone":"+44 1922 409302",
    "sg:postcode":"WV11 2BH",
    "sg:province":"Staffordshire",
    "sg:tags":[
        "modification",
        "garage"
    ],
    "wof:name":"Husselbee Motor Services",
    "wof:placetype":"venue"
},
  "geometry": {"coordinates":[-2.121669,52.58865],"type":"Point"}
}