{
  "type": "Feature",
  "properties": {
    "addr:full":"Dale Road North, Darley Dale Matlock Derbyshire DE4 2HX",
    "addr:postcode":"de4 2hx",
    "addr:street":"Dale Road North;Dale",
    "iso:country":"GB",
    "sg:address":"Dale Road North, Darley Dale",
    "sg:city":"Matlock",
    "sg:classifiers":[
        {
            "category":"Professional",
            "subcategory":"Engineering",
            "type":"Services"
        },
        {
            "category":"Retail",
            "subcategory":"Auto Repair",
            "type":"Services"
        }
    ],
    "sg:phone":"+44 1629 734807",
    "sg:postcode":"DE4 2HX",
    "sg:province":"Derbyshire",
    "sg:tags":[
        "agricultural",
        "sales",
        "machinery"
    ],
    "wof:name":"PLATTS HARRIS LTD",
    "wof:placetype":"venue"
},
  "geometry": {"coordinates":[-1.599496,53.166992],"type":"Point"}
}