{
  "type": "Feature",
  "properties": {
    "addr:full":"Unit 11 Whitehall Trading Estate, Gerrish Avenue, Whitehall Bristol City of Bristol BS5 9DF",
    "addr:housenumber":"unit 11",
    "addr:postcode":"bs5 9df",
    "addr:street":"Whitehall Trading Estate Gerrish Avenue",
    "iso:country":"GB",
    "sg:address":"Unit 11 Whitehall Trading Estate, Gerrish Avenue, Whitehall",
    "sg:city":"Bristol",
    "sg:classifiers":[
        {
            "category":"Manufacturing",
            "subcategory":"Building Materials",
            "type":"Manufacturing & Wholesale Goods"
        }
    ],
    "sg:phone":"+44 117 955 3605",
    "sg:postcode":"BS5 9DF",
    "sg:province":"City of Bristol",
    "sg:tags":[
        "tile",
        "mnfrs"
    ],
    "wof:name":"Collards (Floors & Walls) Ltd.",
    "wof:placetype":"venue"
},
  "geometry": {"coordinates":[-2.559664011,51.4611663818],"type":"Point"}
}