{
  "type": "Feature",
  "properties": {
    "iso:country":"GB",
    "sg:address":"58 Cow Wynd",
    "sg:city":"Falkirk",
    "sg:classifiers":[
        {
            "category":"Organizations",
            "subcategory":"Political Organization",
            "type":"Services"
        }
    ],
    "sg:phone":"+44 1324 613372",
    "sg:postcode":"FK1 1PZ",
    "sg:province":"Falkirk",
    "sg:tags":[
        "party"
    ],
    "wof:name":"Conservative Party-Falkirkwest Constituency",
    "wof:placetype":"venue"
},
  "geometry": {"coordinates":[-3.783759,55.996941],"type":"Point"}
}