{
  "type": "Feature",
  "properties": {
    "addr:full":"Unit 1a 175 Long La Southwark Greater London SE1 4PN",
    "addr:housenumber":"unit 1a 175",
    "addr:postcode":"se1 4pn",
    "addr:street":"Long La",
    "iso:country":"GB",
    "sg:address":"Unit 1a 175 Long La",
    "sg:city":"Southwark",
    "sg:classifiers":[
        {
            "category":"Organizations",
            "subcategory":"Non-profit Organization",
            "type":"Services"
        }
    ],
    "sg:phone":"+44 20 7403 8644",
    "sg:postcode":"SE1 4PN",
    "sg:province":"Greater London",
    "sg:tags":[
        "organisation",
        "voluntary",
        "charity"
    ],
    "wof:name":"Crisis Clothing Run",
    "wof:placetype":"venue"
},
  "geometry": {"coordinates":[-0.0856460035,51.4992141724],"type":"Point"}
}