{
  "type": "Feature",
  "properties": {
    "addr:full":"Windmill Lane East Grinstead East Sussex RH19 2DS",
    "addr:postcode":"rh19 2ds",
    "addr:street":"Windmill Lane",
    "iso:country":"GB",
    "sg:address":"Windmill Lane",
    "sg:city":"East Grinstead",
    "sg:classifiers":[
        {
            "category":"Place Of Worship",
            "type":"Public Place"
        },
        {
            "category":"Education",
            "subcategory":"School",
            "type":"Public Place"
        }
    ],
    "sg:phone":"+44 1342 323858",
    "sg:postcode":"RH19 2DS",
    "sg:province":"East Sussex",
    "sg:tags":[
        "local",
        "authority"
    ],
    "wof:name":"St Mary's C of E Primary School",
    "wof:placetype":"venue"
},
  "geometry": {"coordinates":[-0.019793,51.136593],"type":"Point"}
}