{
  "type": "Feature",
  "properties": {
    "iso:country":"GB",
    "sg:address":"147 Union Street",
    "sg:city":"Oldham",
    "sg:classifiers":[
        {
            "category":"Professional",
            "subcategory":"Accounting & Tax Preparation",
            "type":"Services"
        }
    ],
    "sg:phone":"+44 161 627 1209",
    "sg:postcode":"OL1 1TD",
    "sg:province":"Lancashire",
    "sg:tags":[
        "accountant",
        "activity"
    ],
    "wof:name":"Stephen Senior & Co",
    "wof:placetype":"venue"
},
  "geometry": {"coordinates":[-2.1061429977,53.5416412354],"type":"Point"}
}