{
  "type": "Feature",
  "properties": {
    "iso:country":"GB",
    "sg:address":"Dee Road, Tilehurst",
    "sg:city":"Reading",
    "sg:classifiers":[
        {
            "category":"Education",
            "subcategory":"School",
            "type":"Public Place"
        }
    ],
    "sg:phone":"+44 118 901 5468",
    "sg:postcode":"RG30 4BE",
    "sg:province":"Berkshire",
    "sg:tags":[
        "local",
        "authority"
    ],
    "wof:name":"English Martyrs R C Primary School",
    "wof:placetype":"venue"
},
  "geometry": {"coordinates":[-1.013124,51.455093],"type":"Point"}
}