{
  "type": "Feature",
  "properties": {
    "addr:full":"3a Market Street Beccles Norfolk NR34 9AQ",
    "addr:housenumber":"3a",
    "addr:postcode":"nr34 9aq",
    "addr:street":"Market Street",
    "iso:country":"GB",
    "sg:address":"3a Market Street",
    "sg:city":"Beccles",
    "sg:classifiers":[
        {
            "category":"Food & Beverages",
            "subcategory":"Meat & Fish",
            "type":"Retail Goods"
        }
    ],
    "sg:phone":"+44 1502 717145",
    "sg:postcode":"NR34 9AQ",
    "sg:province":"Norfolk",
    "sg:tags":[
        "butcher"
    ],
    "wof:name":"Bob Knights",
    "wof:placetype":"venue"
},
  "geometry": {"coordinates":[1.5635650158,52.4580383301],"type":"Point"}
}