{
  "type": "Feature",
  "properties": {
    "iso:country":"GB",
    "sg:address":"38 Market Street, Rhosllanerchoug",
    "sg:city":"Wrexham",
    "sg:classifiers":[
        {
            "category":"Home & Garden",
            "subcategory":"Hardware",
            "type":"Retail Goods"
        }
    ],
    "sg:phone":"+44 1978 843333",
    "sg:postcode":"LL14 2HY",
    "sg:province":"Wrexham",
    "wof:name":"Tony & Cynthia Williams",
    "wof:placetype":"venue"
},
  "geometry": {"coordinates":[-3.057909,53.00938],"type":"Point"}
}