{
  "type": "Feature",
  "properties": {
    "addr:full":"2 The Regent Shopping Mall Wantage Berkshire OX12 8BU",
    "addr:housenumber":"2;regent shopping mall wantage",
    "addr:postcode":"ox12 8bu",
    "addr:street":"The",
    "iso:country":"GB",
    "sg:address":"2 The Regent Shopping Mall",
    "sg:city":"Wantage",
    "sg:classifiers":[
        {
            "category":"Cinema",
            "subcategory":"Movie Theater",
            "type":"Entertainment"
        },
        {
            "category":"Organizations",
            "subcategory":"Political Organization",
            "type":"Services"
        }
    ],
    "sg:phone":"+44 1235 767878",
    "sg:postcode":"OX12 8BU",
    "sg:province":"Berkshire",
    "sg:tags":[
        "promoter",
        "pool"
    ],
    "wof:name":"The Regent Cinema",
    "wof:placetype":"venue"
},
  "geometry": {"coordinates":[-1.3544319868,51.5988731384],"type":"Point"}
}