{
  "type": "Feature",
  "properties": {
    "iso:country":"GB",
    "sg:address":"Station Road, Great Bowden",
    "sg:city":"Market Harborough",
    "sg:classifiers":[
        {
            "category":"Professional",
            "subcategory":"Engineering",
            "type":"Services"
        },
        {
            "category":"Bars & Pubs",
            "type":"Food & Drink"
        }
    ],
    "sg:postcode":"LE16 7HL",
    "sg:province":"Leicestershire",
    "sg:tags":[
        "pubs",
        "inn",
        "engineer",
        "electrical",
        "contractor"
    ],
    "wof:name":"The Country Man",
    "wof:placetype":"venue"
},
  "geometry": {"coordinates":[-0.90317,52.49144],"type":"Point"}
}