{
  "type": "Feature",
  "properties": {
    "addr:full":"Building K, 2nd Avenue, Flixborough Industrial Estate Scunthorpe Lincolnshire DN15 8SD",
    "addr:postcode":"dn15 8sd",
    "addr:street":"2Nd Avenue;Industrial Estate",
    "iso:country":"GB",
    "sg:address":"Building K, 2nd Avenue, Flixborough Industrial Estate",
    "sg:city":"Scunthorpe",
    "sg:classifiers":[
        {
            "category":"Manufacturing",
            "subcategory":"Metals",
            "type":"Manufacturing & Wholesale Goods"
        }
    ],
    "sg:postcode":"DN15 8SD",
    "sg:province":"Lincolnshire",
    "sg:tags":[
        "steel",
        "fabricator",
        "erectors"
    ],
    "wof:name":"Sharpe Engineering Services Ltd.",
    "wof:placetype":"venue"
},
  "geometry": {"coordinates":[-0.702005,53.62252],"type":"Point"}
}