{
  "type": "Feature",
  "properties": {
    "iso:country":"GB",
    "sg:address":"Burleydam",
    "sg:city":"Whitchurch",
    "sg:classifiers":[
        {
            "category":"Bars & Pubs",
            "type":"Food & Drink"
        }
    ],
    "sg:phone":"+44 1948 871223",
    "sg:postcode":"SY13 4AT",
    "sg:province":"Cheshire",
    "sg:tags":[
        "pubs",
        "inn"
    ],
    "wof:name":"Combermere Arms",
    "wof:placetype":"venue"
},
  "geometry": {"coordinates":[-2.58842206,52.9800453186],"type":"Point"}
}