{
  "type": "Feature",
  "properties": {
    "iso:country":"GB",
    "sg:address":"Eden Concern Shop Resource Cen, Verdon House, Shap",
    "sg:city":"Penrith",
    "sg:classifiers":[
        {
            "category":"Organizations",
            "subcategory":"Non-profit Organization",
            "type":"Services"
        }
    ],
    "sg:phone":"+44 1931 716086",
    "sg:postcode":"CA10 3NG",
    "sg:province":"Cumbria",
    "sg:tags":[
        "organisation",
        "voluntary",
        "charity"
    ],
    "wof:name":"Age Concern England (National Council of",
    "wof:placetype":"venue"
},
  "geometry": {"coordinates":[-2.6038589478,54.5196990967],"type":"Point"}
}