{
  "type": "Feature",
  "properties": {
    "iso:country":"GB",
    "sg:address":"Unit 2, Lowfield Heath Industrial Estate",
    "sg:city":"Crawley",
    "sg:classifiers":[
        {
            "category":"Freight",
            "type":"Transportation"
        }
    ],
    "sg:phone":"+44 1293 520004",
    "sg:postcode":"RH11 0PQ",
    "sg:province":"West Sussex",
    "sg:tags":[
        "cargo",
        "handling",
        "forwarders"
    ],
    "wof:name":"Lexington Freight Forwarding Ltd.",
    "wof:placetype":"venue"
},
  "geometry": {"coordinates":[-0.179370001,51.1462211609],"type":"Point"}
}