{
  "type": "Feature",
  "properties": {
    "iso:country":"GB",
    "sg:address":"Harrison House, High Street, Byers Green",
    "sg:city":"Spennymoor",
    "sg:classifiers":[
        {
            "category":"Manufacturing",
            "subcategory":"Petroleum Products",
            "type":"Manufacturing & Wholesale Goods"
        }
    ],
    "sg:postcode":"DL16 7NX",
    "sg:province":"Durham",
    "sg:tags":[
        "double",
        "glazing"
    ],
    "wof:name":"Todd Bros",
    "wof:placetype":"venue"
},
  "geometry": {"coordinates":[-1.656492,54.702442],"type":"Point"}
}