{
  "type": "Feature",
  "properties": {
    "iso:country":"GB",
    "sg:address":"512 Portsmouth Rd",
    "sg:city":"Southampton",
    "sg:classifiers":[
        {
            "category":"Wholesale",
            "subcategory":"Non-durable Goods",
            "type":"Manufacturing & Wholesale Goods"
        }
    ],
    "sg:phone":"+44 23 8044 6767",
    "sg:postcode":"SO19 9LZ",
    "sg:province":"Hampshire",
    "sg:tags":[
        "carry",
        "cash"
    ],
    "wof:name":"Booker Foodservice Frozen",
    "wof:placetype":"venue"
},
  "geometry": {"coordinates":[-1.3454940319,50.8931884766],"type":"Point"}
}