{
  "type": "Feature",
  "properties": {
    "iso:country":"GB",
    "sg:address":"Fox Mill Farm, The Fox, Purton",
    "sg:city":"Swindon",
    "sg:classifiers":[
        {
            "category":"Farming",
            "subcategory":"Livestock Farm",
            "type":"Manufacturing & Wholesale Goods"
        }
    ],
    "sg:phone":"+44 1793 770496",
    "sg:postcode":"SN5 4EF",
    "sg:province":"Wiltshire",
    "sg:tags":[
        "others"
    ],
    "wof:name":"Hamish & Ann Orr-Ewing",
    "wof:placetype":"venue"
},
  "geometry": {"coordinates":[-1.866039,51.590374],"type":"Point"}
}