{
  "type": "Feature",
  "properties": {
    "iso:country":"GB",
    "sg:address":"Channelsea House, Canning Road",
    "sg:city":"London",
    "sg:classifiers":[
        {
            "category":"Freight",
            "type":"Transportation"
        }
    ],
    "sg:phone":"+44 20 8981 3752",
    "sg:postcode":"E15 3ND",
    "sg:province":"Greater London",
    "sg:tags":[
        "haulage",
        "road"
    ],
    "wof:name":"Jaymac Pallet Delivery Services Ltd.",
    "wof:placetype":"venue"
},
  "geometry": {"coordinates":[0.00396,51.530529],"type":"Point"}
}