{
  "type": "Feature",
  "properties": {
    "addr:full":"Stony Lane Christchurch Dorset BH23 1EZ",
    "addr:postcode":"bh23 1ez",
    "addr:street":"Stony Lane",
    "iso:country":"GB",
    "sg:address":"Stony Lane",
    "sg:city":"Christchurch",
    "sg:classifiers":[
        {
            "category":"Building & Trades",
            "subcategory":"Construction",
            "type":"Services"
        }
    ],
    "sg:phone":"+44 1202 499499",
    "sg:postcode":"BH23 1EZ",
    "sg:province":"Dorset",
    "sg:tags":[
        "joinery"
    ],
    "wof:name":"Boyland (Contracts)",
    "wof:placetype":"venue"
},
  "geometry": {"coordinates":[-1.7687410116,50.7365264893],"type":"Point"}
}