{
  "type": "Feature",
  "properties": {
    "addr:full":"28 Petersfield Road, Hall Grn Birmingham West Midlands B28 0AR",
    "addr:housenumber":"28",
    "addr:postcode":"b28 0ar",
    "addr:street":"Petersfield Road Hall Grn",
    "iso:country":"GB",
    "sg:address":"28 Petersfield Road, Hall Grn",
    "sg:city":"Birmingham",
    "sg:classifiers":[
        {
            "category":"Arena",
            "subcategory":"Sports Club",
            "type":"Entertainment"
        }
    ],
    "sg:phone":"+44 121 777 5509",
    "sg:postcode":"B28 0AR",
    "sg:province":"West Midlands",
    "wof:name":"Hall Green Tennis Club",
    "wof:placetype":"venue"
},
  "geometry": {"coordinates":[-1.847053051,52.4317398071],"type":"Point"}
}