{
  "type": "Feature",
  "properties": {
    "iso:country":"GB",
    "sg:address":"175 Streatham High Road",
    "sg:city":"London",
    "sg:classifiers":[
        {
            "category":"Shopping",
            "subcategory":"Baby Store",
            "type":"Retail Goods"
        }
    ],
    "sg:phone":"+44 20 8769 1106",
    "sg:postcode":"SW16 6EG",
    "sg:province":"Greater London",
    "sg:tags":[
        "babywear",
        "childrens"
    ],
    "wof:name":"Smarties",
    "wof:placetype":"venue"
},
  "geometry": {"coordinates":[-0.130804,51.428337],"type":"Point"}
}