{
  "type": "Feature",
  "properties": {
    "iso:country":"GB",
    "sg:address":"Ilsom Farm, Cirencester Road, Ilsom",
    "sg:city":"Tetbury",
    "sg:classifiers":[
        {
            "category":"Building & Trades",
            "subcategory":"Cleaning & Sanitation",
            "type":"Services"
        },
        {
            "category":"Home & Garden",
            "subcategory":"Home Furnishings",
            "type":"Retail Goods"
        },
        {
            "category":"Professional",
            "subcategory":"Art Services",
            "type":"Services"
        }
    ],
    "sg:phone":"+44 1666 504251",
    "sg:postcode":"GL8 8RX",
    "sg:province":"Gloucestershire",
    "sg:tags":[
        "mantelpiece",
        "stone",
        "restoration",
        "fireplace",
        "exterior"
    ],
    "wof:name":"Wells Masonry Services Ltd",
    "wof:placetype":"venue"
},
  "geometry": {"coordinates":[-2.152294,51.640903],"type":"Point"}
}