{
  "type": "Feature",
  "properties": {
    "addr:full":"Grosvenor House, Belgrave Lane, Mutley Plymouth Devon PL4 7DS",
    "addr:postcode":"pl4 7ds",
    "addr:street":"Belgrave Lane",
    "iso:country":"GB",
    "sg:address":"Grosvenor House, Belgrave Lane, Mutley",
    "sg:city":"Plymouth",
    "sg:classifiers":[
        {
            "category":"Shopping",
            "subcategory":"Clothing, Apparel, & Fashions",
            "type":"Retail Goods"
        }
    ],
    "sg:phone":"+44 1752 257300",
    "sg:postcode":"PL4 7DS",
    "sg:province":"Devon",
    "sg:tags":[
        "t-shirt"
    ],
    "wof:name":"P H D Advertising",
    "wof:placetype":"venue"
},
  "geometry": {"coordinates":[-4.1317,50.383339],"type":"Point"}
}