{
  "type": "Feature",
  "properties": {
    "addr:full":"6 Bramley Rise Rochester Kent ME2 3SU",
    "addr:housenumber":"6",
    "addr:postcode":"me2 3su",
    "addr:street":"Bramley Rise",
    "iso:country":"GB",
    "sg:address":"6 Bramley Rise",
    "sg:city":"Rochester",
    "sg:classifiers":[
        {
            "category":"Professional",
            "subcategory":"Detective & Security Services",
            "type":"Services"
        }
    ],
    "sg:phone":"+44 1634 714843",
    "sg:postcode":"ME2 3SU",
    "sg:province":"Kent",
    "sg:tags":[
        "alarm",
        "burglar",
        "system"
    ],
    "wof:name":"TAM Services",
    "wof:placetype":"venue"
},
  "geometry": {"coordinates":[0.4767760038,51.400894165],"type":"Point"}
}