{
  "type": "Feature",
  "properties": {
    "addr:full":"341 Rayners Lane Pinner Greater London HA5 5EN",
    "addr:housenumber":"341",
    "addr:postcode":"ha5 5en",
    "addr:street":"Rayners Lane",
    "iso:country":"GB",
    "sg:address":"341 Rayners Lane",
    "sg:city":"Pinner",
    "sg:classifiers":[
        {
            "category":"Retail",
            "subcategory":"Funeral Services",
            "type":"Services"
        }
    ],
    "sg:phone":"+44 20 8866 2211",
    "sg:postcode":"HA5 5EN",
    "sg:province":"Greater London",
    "sg:tags":[
        "director"
    ],
    "wof:name":"Sydney Hurry",
    "wof:placetype":"venue"
},
  "geometry": {"coordinates":[-0.371166,51.576031],"type":"Point"}
}