{
  "type": "Feature",
  "properties": {
    "addr:full":"Oaklands House, Coulsdon Road Caterham Surrey CR3 5YA",
    "addr:postcode":"cr3 5ya",
    "addr:street":"Coulsdon Road",
    "iso:country":"GB",
    "sg:address":"Oaklands House, Coulsdon Road",
    "sg:city":"Caterham",
    "sg:classifiers":[
        {
            "category":"Health Services",
            "subcategory":"Hospital",
            "type":"Services"
        },
        {
            "category":"Health Services",
            "subcategory":"Clinic",
            "type":"Services"
        }
    ],
    "sg:phone":"+44 1883 383838",
    "sg:postcode":"CR3 5YA",
    "sg:province":"Surrey",
    "sg:tags":[
        "nh"
    ],
    "wof:name":"Surrey Oaklands Nhs Trust",
    "wof:placetype":"venue"
},
  "geometry": {"coordinates":[-0.0769359991,51.281578064],"type":"Point"}
}