{
  "type": "Feature",
  "properties": {
    "iso:country":"GB",
    "sg:address":"Yapton Lane, Walberton",
    "sg:city":"Arundel",
    "sg:classifiers":[
        {
            "category":"Home & Garden",
            "subcategory":"Garden Supply",
            "type":"Retail Goods"
        }
    ],
    "sg:phone":"+44 1243 554952",
    "sg:postcode":"BN18 0LS",
    "sg:province":"West Sussex",
    "sg:tags":[
        "planting",
        "tree",
        "shrub"
    ],
    "wof:name":"Littlewoods Nursery",
    "wof:placetype":"venue"
},
  "geometry": {"coordinates":[-0.617679,50.852905],"type":"Point"}
}