{
  "type": "Feature",
  "properties": {
    "addr:full":"54 Butler Road Harrogate North Yorkshire HG1 4PF",
    "addr:housenumber":"54",
    "addr:postcode":"hg1 4pf",
    "addr:street":"Butler Road",
    "iso:country":"GB",
    "sg:address":"54 Butler Road",
    "sg:city":"Harrogate",
    "sg:classifiers":[
        {
            "category":"Building & Trades",
            "subcategory":"Construction",
            "type":"Services"
        }
    ],
    "sg:phone":"+44 1423 522215",
    "sg:postcode":"HG1 4PF",
    "sg:province":"North Yorkshire",
    "sg:tags":[
        "decorator",
        "painter"
    ],
    "wof:name":"P Alloway",
    "wof:placetype":"venue"
},
  "geometry": {"coordinates":[-1.529344,54.007072],"type":"Point"}
}