{
  "type": "Feature",
  "properties": {
    "addr:full":"Kingshill Court, Wigan Road, Standish Wigan Lancashire WN6 0AR",
    "addr:postcode":"wn6 0ar",
    "addr:street":"Kingshill Court Wigan Road",
    "iso:country":"GB",
    "sg:address":"Kingshill Court, Wigan Road, Standish",
    "sg:city":"Wigan",
    "sg:classifiers":[
        {
            "category":"Travel",
            "subcategory":"Hostel",
            "type":"Entertainment"
        }
    ],
    "sg:phone":"+44 1257 421332",
    "sg:postcode":"WN6 0AR",
    "sg:province":"Lancashire",
    "wof:name":"Making Space",
    "wof:placetype":"venue"
},
  "geometry": {"coordinates":[-2.656512,53.579651],"type":"Point"}
}