{
  "type": "Feature",
  "properties": {
    "addr:full":"10 Slimbridge Road Burgess Hill East Sussex RH15 8QE",
    "addr:housenumber":"10",
    "addr:postcode":"rh15 8qe",
    "addr:street":"Slimbridge Road",
    "iso:country":"GB",
    "sg:address":"10 Slimbridge Road",
    "sg:city":"Burgess Hill",
    "sg:classifiers":[
        {
            "category":"Professional",
            "subcategory":"Computer Services",
            "type":"Services"
        }
    ],
    "sg:postcode":"RH15 8QE",
    "sg:province":"East Sussex",
    "sg:tags":[
        "consultant"
    ],
    "wof:name":"D M Resources Ltd.",
    "wof:placetype":"venue"
},
  "geometry": {"coordinates":[-0.1402779967,50.9586677551],"type":"Point"}
}