{
  "type": "Feature",
  "properties": {
    "addr:full":"Hollygrove Farm, Upper Northam Drive, Hedge End Southampton Hampshire SO30 4BG",
    "addr:postcode":"so30 4bg",
    "addr:street":"Upper Northam Drive",
    "iso:country":"GB",
    "sg:address":"Hollygrove Farm, Upper Northam Drive, Hedge End",
    "sg:city":"Southampton",
    "sg:classifiers":[
        {
            "category":"Manufacturing",
            "subcategory":"Tools & Machinery",
            "type":"Manufacturing & Wholesale Goods"
        }
    ],
    "sg:postcode":"SO30 4BG",
    "sg:province":"Hampshire",
    "wof:name":"Tier Machine Tools",
    "wof:placetype":"venue"
},
  "geometry": {"coordinates":[-1.292531,50.91584],"type":"Point"}
}