{
  "type": "Feature",
  "properties": {
    "addr:full":"Leigh St School, Leigh Street Hyde Cheshire SK14 2RP",
    "addr:postcode":"sk14 2rp",
    "addr:street":"Leigh;Leigh Street",
    "iso:country":"GB",
    "sg:address":"Leigh St School, Leigh Street",
    "sg:city":"Hyde",
    "sg:classifiers":[
        {
            "category":"Education",
            "subcategory":"School",
            "type":"Public Place"
        }
    ],
    "sg:phone":"+44 161 367 8508",
    "sg:postcode":"SK14 2RP",
    "sg:province":"Cheshire",
    "sg:tags":[
        "local",
        "authority"
    ],
    "wof:name":"Attendance Support Centre",
    "wof:placetype":"venue"
},
  "geometry": {"coordinates":[-2.070614,53.450871],"type":"Point"}
}