{
  "type": "Feature",
  "properties": {
    "addr:full":"Meriden Works, Birmingham Rd Coventry West Midlands CV5 9GR",
    "addr:postcode":"cv5 9gr",
    "addr:street":"Birmingham Rd",
    "iso:country":"GB",
    "sg:address":"Meriden Works, Birmingham Rd",
    "sg:city":"Coventry",
    "sg:classifiers":[
        {
            "category":"Autos & Motor Vehicles",
            "subcategory":"Automobile Sales",
            "type":"Retail Goods"
        }
    ],
    "sg:phone":"+44 1676 521157",
    "sg:postcode":"CV5 9GR",
    "sg:province":"West Midlands",
    "sg:tags":[
        "commercial"
    ],
    "wof:name":"Millenium Motors",
    "wof:placetype":"venue"
},
  "geometry": {"coordinates":[-1.56445,52.423119],"type":"Point"}
}