{
  "type": "Feature",
  "properties": {
    "addr:full":"123 Woodlands Road Ilford Essex IG1 1JP",
    "addr:housenumber":"123",
    "addr:postcode":"ig1 1jp",
    "addr:street":"Woodlands Road",
    "iso:country":"GB",
    "sg:address":"123 Woodlands Road",
    "sg:city":"Ilford",
    "sg:classifiers":[
        {
            "category":"Professional",
            "subcategory":"Detective & Security Services",
            "type":"Services"
        }
    ],
    "sg:phone":"+44 20 8478 4083",
    "sg:postcode":"IG1 1JP",
    "sg:province":"Essex",
    "sg:tags":[
        "equipment",
        "installers"
    ],
    "wof:name":"Essex Electronics",
    "wof:placetype":"venue"
},
  "geometry": {"coordinates":[0.078649,51.554047],"type":"Point"}
}