{
  "type": "Feature",
  "properties": {
    "addr:full":"36 Station Road, Draycott Derby Derbyshire DE72 3QB",
    "addr:housenumber":"36",
    "addr:postcode":"de72 3qb",
    "addr:street":"Station Road",
    "iso:country":"GB",
    "sg:address":"36 Station Road, Draycott",
    "sg:city":"Derby",
    "sg:classifiers":[
        {
            "category":"Professional",
            "subcategory":"Computer Services",
            "type":"Services"
        }
    ],
    "sg:postcode":"DE72 3QB",
    "sg:province":"Derbyshire",
    "sg:tags":[
        "system",
        "software"
    ],
    "wof:name":"Simphoni H R D Ltd.",
    "wof:placetype":"venue"
},
  "geometry": {"coordinates":[-1.382586956,52.9045600891],"type":"Point"}
}