{
  "type": "Feature",
  "properties": {
    "addr:full":"Unit C4 Holly Farm Business Park, Holly Kenilworth Warwickshire CV8 1NP",
    "addr:housenumber":"business",
    "addr:postcode":"cv8 1np",
    "addr:street":"Park Holly",
    "iso:country":"GB",
    "sg:address":"Unit C4 Holly Farm Business Park, Holly",
    "sg:city":"Kenilworth",
    "sg:classifiers":[
        {
            "category":"Autos & Motor Vehicles",
            "subcategory":"Automobile Sales",
            "type":"Retail Goods"
        }
    ],
    "sg:phone":"+44 1926 484140",
    "sg:postcode":"CV8 1NP",
    "sg:province":"Warwickshire",
    "sg:tags":[
        "car",
        "specialist",
        "sales",
        "classic"
    ],
    "wof:name":"Boxridge Ltd.",
    "wof:placetype":"venue"
},
  "geometry": {"coordinates":[-1.5794409513,52.3429374695],"type":"Point"}
}