{
  "type": "Feature",
  "properties": {
    "addr:full":"38 Beechfields, Eccleston Chorley Lancashire PR7 5RE",
    "addr:housenumber":"38",
    "addr:postcode":"pr7 5re",
    "addr:street":"Beechfields",
    "iso:country":"GB",
    "sg:address":"38 Beechfields, Eccleston",
    "sg:city":"Chorley",
    "sg:classifiers":[
        {
            "category":"Professional",
            "subcategory":"Computer Services",
            "type":"Services"
        }
    ],
    "sg:phone":"+44 1257 452237",
    "sg:postcode":"PR7 5RE",
    "sg:province":"Lancashire",
    "sg:tags":[
        "system",
        "software"
    ],
    "wof:name":"J J A Ltd.",
    "wof:placetype":"venue"
},
  "geometry": {"coordinates":[-2.7300341129,53.6457138062],"type":"Point"}
}