{
  "type": "Feature",
  "properties": {
    "addr:full":"Sunnyside Farm, Kingsdon Somerton Somerset TA11 7LJ",
    "addr:postcode":"ta11 7lj",
    "iso:country":"GB",
    "sg:address":"Sunnyside Farm, Kingsdon",
    "sg:city":"Somerton",
    "sg:classifiers":[
        {
            "category":"Building & Trades",
            "subcategory":"Equipment Rental",
            "type":"Services"
        }
    ],
    "sg:postcode":"TA11 7LJ",
    "sg:province":"Somerset",
    "sg:tags":[
        "plant",
        "machinery"
    ],
    "wof:name":"F E Attwell & Sons",
    "wof:placetype":"venue"
},
  "geometry": {"coordinates":[-2.689554,51.034302],"type":"Point"}
}