{
  "type": "Feature",
  "properties": {
    "addr:full":"11 Harforde Court, John Tate Road Hertford Hertfordshire SG13 7NW",
    "addr:housenumber":"11",
    "addr:postcode":"sg13 7nw",
    "addr:street":"Harforde Court John Tate Road",
    "iso:country":"GB",
    "sg:address":"11 Harforde Court, John Tate Road",
    "sg:city":"Hertford",
    "sg:classifiers":[
        {
            "category":"Manufacturing",
            "subcategory":"Electronics",
            "type":"Manufacturing & Wholesale Goods"
        }
    ],
    "sg:phone":"+44 1992 535750",
    "sg:postcode":"SG13 7NW",
    "sg:province":"Hertfordshire",
    "sg:tags":[
        "mnfr",
        "component",
        "electronic"
    ],
    "wof:name":"B P Purchasing (Electronics) Ltd.",
    "wof:placetype":"venue"
},
  "geometry": {"coordinates":[-0.0586640015,51.7957267761],"type":"Point"}
}