{
  "type": "Feature",
  "properties": {
    "addr:full":"91-93 Woodcote Road Wallington Surrey SM6 0PU",
    "addr:housenumber":"91-93",
    "addr:postcode":"sm6 0pu",
    "addr:street":"Woodcote Road",
    "iso:country":"GB",
    "sg:address":"91-93 Woodcote Road",
    "sg:city":"Wallington",
    "sg:classifiers":[
        {
            "category":"Health Services",
            "subcategory":"Nursing And Care Facility",
            "type":"Services"
        }
    ],
    "sg:phone":"+44 20 8395 5668",
    "sg:postcode":"SM6 0PU",
    "sg:province":"Surrey",
    "sg:tags":[
        "home"
    ],
    "wof:name":"Cladagh Nursing Home",
    "wof:placetype":"venue"
},
  "geometry": {"coordinates":[-0.1478620023,51.3524665833],"type":"Point"}
}