{
  "type": "Feature",
  "properties": {
    "addr:full":"Golds Hill Way, Waterside Park, Great Bridge Tipton West Midlands DY4 0PU",
    "addr:postcode":"dy4 0pu",
    "addr:street":"Golds Hill Way;Park;Bridge Tipton",
    "iso:country":"GB",
    "sg:address":"Golds Hill Way, Waterside Park, Great Bridge",
    "sg:city":"Tipton",
    "sg:classifiers":[
        {
            "category":"Manufacturing",
            "subcategory":"Metals",
            "type":"Manufacturing & Wholesale Goods"
        }
    ],
    "sg:phone":"+44 121 522 0450",
    "sg:postcode":"DY4 0PU",
    "sg:province":"West Midlands",
    "sg:tags":[
        "merchant"
    ],
    "wof:name":"Amari Contract Services",
    "wof:placetype":"venue"
},
  "geometry": {"coordinates":[-2.033809,52.537766],"type":"Point"}
}