{
  "type": "Feature",
  "properties": {
    "addr:full":"Red Hill Garage Telford Shropshire TF2 9NZ",
    "addr:postcode":"tf2 9nz",
    "iso:country":"GB",
    "sg:address":"Red Hill Garage",
    "sg:city":"Telford",
    "sg:classifiers":[
        {
            "category":"Retail",
            "subcategory":"Auto Repair",
            "type":"Services"
        }
    ],
    "sg:phone":"+44 1952 612047",
    "sg:postcode":"TF2 9NZ",
    "sg:province":"Shropshire",
    "sg:tags":[
        "modification",
        "garage"
    ],
    "wof:name":"Don C Stanworth",
    "wof:placetype":"venue"
},
  "geometry": {"coordinates":[-2.429939,52.704205],"type":"Point"}
}