{
  "type": "Feature",
  "properties": {
    "addr:full":"Broadyates Road Birmingham West Midlands B25 8JF",
    "addr:postcode":"b25 8jf",
    "addr:street":"Broadyates Road",
    "iso:country":"GB",
    "sg:address":"Broadyates Road",
    "sg:city":"Birmingham",
    "sg:classifiers":[
        {
            "category":"Place Of Worship",
            "type":"Public Place"
        }
    ],
    "sg:phone":"+44 121 706 1336",
    "sg:postcode":"B25 8JF",
    "sg:province":"West Midlands",
    "wof:name":"Methodist Church South Yardley",
    "wof:placetype":"venue"
},
  "geometry": {"coordinates":[-1.8187509775,52.4607582092],"type":"Point"}
}