{
  "type": "Feature",
  "properties": {
    "addr:full":"1 East Gate Market Gloucester Gloucestershire GL1 1LP",
    "addr:housenumber":"1",
    "addr:postcode":"gl1 1lp",
    "addr:street":"East Gate Market",
    "iso:country":"GB",
    "sg:address":"1 East Gate Market",
    "sg:city":"Gloucester",
    "sg:classifiers":[
        {
            "category":"Shopping",
            "subcategory":"Florist",
            "type":"Retail Goods"
        }
    ],
    "sg:postcode":"GL1 1LP",
    "sg:province":"Gloucestershire",
    "wof:name":"The Flower Centre",
    "wof:placetype":"venue"
},
  "geometry": {"coordinates":[-2.2439661026,51.8642196655],"type":"Point"}
}