{
  "type": "Feature",
  "properties": {
    "addr:full":"80 Richardshaw Lane Pudsey West Yorkshire LS28 6BN",
    "addr:housenumber":"80",
    "addr:postcode":"ls28 6bn",
    "addr:street":"Richardshaw Lane",
    "iso:country":"GB",
    "sg:address":"80 Richardshaw Lane",
    "sg:city":"Pudsey",
    "sg:classifiers":[
        {
            "category":"Government",
            "subcategory":"Office",
            "type":"Public Place"
        }
    ],
    "sg:phone":"+44 113 227 3300",
    "sg:postcode":"LS28 6BN",
    "sg:province":"West Yorkshire",
    "sg:tags":[
        "education",
        "agency",
        "authority"
    ],
    "wof:name":"Qualifications for Industry",
    "wof:placetype":"venue"
},
  "geometry": {"coordinates":[-1.6648869514,53.8021354675],"type":"Point"}
}