{
  "type": "Feature",
  "properties": {
    "addr:full":"Kingston Park Centre Newcastle-upon-tyne Tyne and Wear NE3 2FP",
    "addr:postcode":"ne3 2fp",
    "addr:street":"Kingston Park Centre",
    "iso:country":"GB",
    "sg:address":"Kingston Park Centre",
    "sg:city":"Newcastle-upon-tyne",
    "sg:classifiers":[
        {
            "category":"Shopping",
            "subcategory":"Discount & Variety Stores",
            "type":"Retail Goods"
        }
    ],
    "sg:phone":"+44 191 271 5830",
    "sg:postcode":"NE3 2FP",
    "sg:province":"Tyne and Wear",
    "sg:tags":[
        "centre"
    ],
    "wof:name":"Poundstretcher Ltd.",
    "wof:placetype":"venue"
},
  "geometry": {"coordinates":[-1.670658946,55.0184402466],"type":"Point"}
}