{
  "type": "Feature",
  "properties": {
    "addr:full":"3 Swinstead Close, Wigman Road, Bilborough Nottingham Nottinghamshire NG8 3JG",
    "addr:housenumber":"3",
    "addr:postcode":"ng8 3jg",
    "addr:street":"Swinstead Close Wigman Road",
    "iso:country":"GB",
    "sg:address":"3 Swinstead Close, Wigman Road, Bilborough",
    "sg:city":"Nottingham",
    "sg:classifiers":[
        {
            "category":"Home & Garden",
            "subcategory":"Kitchen Supply",
            "type":"Retail Goods"
        }
    ],
    "sg:postcode":"NG8 3JG",
    "sg:province":"Nottinghamshire",
    "sg:tags":[
        "ware"
    ],
    "wof:name":"Pilot Housewares (U K) Ltd.",
    "wof:placetype":"venue"
},
  "geometry": {"coordinates":[-1.212767,52.961964],"type":"Point"}
}