{
  "type": "Feature",
  "properties": {
    "addr:full":"Care Of 17 The Avenue Totland Bay Isle of Wight PO39 0DH",
    "addr:postcode":"po39 0dh",
    "addr:street":"The Avenue Totland Bay",
    "iso:country":"GB",
    "sg:address":"Care Of 17 The Avenue",
    "sg:city":"Totland Bay",
    "sg:classifiers":[
        {
            "category":"Place Of Worship",
            "type":"Public Place"
        }
    ],
    "sg:phone":"+44 1983 753163",
    "sg:postcode":"PO39 0DH",
    "sg:province":"Isle of Wight",
    "wof:name":"Brook Methodist Church",
    "wof:placetype":"venue"
},
  "geometry": {"coordinates":[-1.546521,50.678787],"type":"Point"}
}