{
  "type": "Feature",
  "properties": {
    "iso:country":"GB",
    "sg:address":"147 Ealing Rd",
    "sg:city":"Wembley",
    "sg:classifiers":[
        {
            "category":"Wholesale",
            "subcategory":"Non-durable Goods",
            "type":"Manufacturing & Wholesale Goods"
        }
    ],
    "sg:phone":"+44 20 8795 0387",
    "sg:postcode":"HA0 4BU",
    "sg:province":"Greater London",
    "sg:tags":[
        "carry",
        "wholesaler",
        "cash"
    ],
    "wof:name":"V B & Sons",
    "wof:placetype":"venue"
},
  "geometry": {"coordinates":[-0.2967100143,51.5445899963],"type":"Point"}
}