{
  "type": "Feature",
  "properties": {
    "addr:full":"18 Canopus Close, Old Church Estate, St Melons Cardiff Caerphilly CF3 1NR",
    "addr:housenumber":"18",
    "addr:postcode":"cf3 1nr",
    "addr:street":"Canopus Close Old Church Estate St Melons",
    "iso:country":"GB",
    "sg:address":"18 Canopus Close, Old Church Estate, St Melons",
    "sg:city":"Cardiff",
    "sg:classifiers":[
        {
            "category":"Shopping",
            "subcategory":"Hobbies, Toys, & Games",
            "type":"Retail Goods"
        }
    ],
    "sg:postcode":"CF3 1NR",
    "sg:province":"Caerphilly",
    "sg:tags":[
        "toy"
    ],
    "wof:name":"Mechforce U K",
    "wof:placetype":"venue"
},
  "geometry": {"coordinates":[-3.113341,51.522289],"type":"Point"}
}