{
  "type": "Feature",
  "properties": {
    "iso:country":"GB",
    "sg:address":"11 The Exchange",
    "sg:city":"Leicester",
    "sg:classifiers":[
        {
            "category":"Farming",
            "subcategory":"Fish & Marine Products",
            "type":"Manufacturing & Wholesale Goods"
        }
    ],
    "sg:postcode":"LE2 9BA",
    "sg:province":"Leicestershire",
    "sg:tags":[
        "fishmonger"
    ],
    "wof:name":"Patterson,Kennrick,",
    "wof:placetype":"venue"
},
  "geometry": {"coordinates":[-1.144784,52.591518],"type":"Point"}
}