{
  "type": "Feature",
  "properties": {
    "iso:country":"GB",
    "sg:address":"32a High St, Clophill",
    "sg:city":"Milton Keynes",
    "sg:classifiers":[
        {
            "category":"Building & Trades",
            "subcategory":"Construction",
            "type":"Services"
        }
    ],
    "sg:postcode":"MK45 4AA",
    "sg:province":"Bedfordshire",
    "sg:tags":[
        "builder"
    ],
    "wof:name":"Wood,W J,",
    "wof:placetype":"venue"
},
  "geometry": {"coordinates":[-0.4204809964,52.0283813477],"type":"Point"}
}