{
  "type": "Feature",
  "properties": {
    "iso:country":"GB",
    "sg:address":"92 Penshurst Gardens",
    "sg:city":"Edgware",
    "sg:classifiers":[
        {
            "category":"Professional",
            "subcategory":"Computer Services",
            "type":"Services"
        }
    ],
    "sg:phone":"+44 20 8204 2228",
    "sg:postcode":"HA8 9TU",
    "sg:province":"Greater London",
    "sg:tags":[
        "development",
        "system",
        "software"
    ],
    "wof:name":"Kerdis Ltd.",
    "wof:placetype":"venue"
},
  "geometry": {"coordinates":[-0.2672890127,51.6172294617],"type":"Point"}
}