{
  "type": "Feature",
  "properties": {
    "addr:full":"Priory Lane, St Neotsa Huntingdon Bedfordshire PE19 2BH",
    "addr:postcode":"pe19 2bh",
    "addr:street":"Priory Lane",
    "iso:country":"GB",
    "sg:address":"Priory Lane, St Neotsa",
    "sg:city":"Huntingdon",
    "sg:classifiers":[
        {
            "category":"Professional",
            "subcategory":"Detective & Security Services",
            "type":"Services"
        }
    ],
    "sg:postcode":"PE19 2BH",
    "sg:province":"Bedfordshire",
    "wof:name":"Admiral Security",
    "wof:placetype":"venue"
},
  "geometry": {"coordinates":[-0.2721740007,52.2285385132],"type":"Point"}
}