{
  "type": "Feature",
  "properties": {
    "addr:full":"132 Weyside Green Reading Berkshire RG8 0QJ",
    "addr:housenumber":"132",
    "addr:postcode":"rg8 0qj",
    "addr:street":"Weyside Green",
    "iso:country":"GB",
    "sg:address":"132 Weyside Green",
    "sg:city":"Reading",
    "sg:classifiers":[
        {
            "category":"Health Services",
            "subcategory":"Clinic",
            "type":"Services"
        }
    ],
    "sg:phone":"+44 1491 682450",
    "sg:postcode":"RG8 0QJ",
    "sg:province":"Berkshire",
    "sg:tags":[
        "injury",
        "sport"
    ],
    "wof:name":"Tincknell Sue",
    "wof:placetype":"venue"
},
  "geometry": {"coordinates":[-1.076788,51.532566],"type":"Point"}
}