{
  "type": "Feature",
  "properties": {
    "iso:country":"GB",
    "sg:address":"22 Market Hill",
    "sg:city":"Royston",
    "sg:classifiers":[
        {
            "category":"Banks & Credit Unions",
            "subcategory":"Financial Services",
            "type":"Services"
        }
    ],
    "sg:phone":"+44 1763 243210",
    "sg:postcode":"SG8 9JG",
    "sg:province":"Bedfordshire",
    "sg:tags":[
        "adviser"
    ],
    "wof:name":"Saffron Walden Herts & Essex Building Society",
    "wof:placetype":"venue"
},
  "geometry": {"coordinates":[-0.022038,52.046551],"type":"Point"}
}