{
  "type": "Feature",
  "properties": {
    "iso:country":"GB",
    "sg:address":"Unit 5, Vagg Park, Vagg Hill",
    "sg:city":"Yeovil",
    "sg:classifiers":[
        {
            "category":"Shopping Center",
            "type":"Public Place"
        }
    ],
    "sg:phone":"+44 1935 410999",
    "sg:postcode":"BA21 3PR",
    "sg:province":"Somerset",
    "sg:tags":[
        "clutch",
        "brake",
        "centre"
    ],
    "wof:name":"V.A.G Disc Co",
    "wof:placetype":"venue"
},
  "geometry": {"coordinates":[-2.6726930141,50.96534729],"type":"Point"}
}