{
  "type": "Feature",
  "properties": {
    "iso:country":"GB",
    "sg:address":"181a Glaisnock Street",
    "sg:city":"Cumnock",
    "sg:classifiers":[
        {
            "category":"Education",
            "subcategory":"Music School",
            "type":"Public Place"
        }
    ],
    "sg:postcode":"KA18 1JT",
    "sg:province":"East Ayrshire",
    "sg:tags":[
        "conservatory"
    ],
    "wof:name":"Astraview",
    "wof:placetype":"venue"
},
  "geometry": {"coordinates":[-4.2598128319,55.4485588074],"type":"Point"}
}