{
  "type": "Feature",
  "properties": {
    "addr:full":"47 Woodville Drive, Marple Stockport Cheshire SK6 7QS",
    "addr:housenumber":"47",
    "addr:postcode":"sk6 7qs",
    "addr:street":"Woodville Drive",
    "iso:country":"GB",
    "sg:address":"47 Woodville Drive, Marple",
    "sg:city":"Stockport",
    "sg:classifiers":[
        {
            "category":"Manufacturing",
            "subcategory":"Metals",
            "type":"Manufacturing & Wholesale Goods"
        }
    ],
    "sg:phone":"+44 161 449 9952",
    "sg:postcode":"SK6 7QS",
    "sg:province":"Cheshire",
    "sg:tags":[
        "work",
        "sheet"
    ],
    "wof:name":"J Robinson & Co. Ltd.",
    "wof:placetype":"venue"
},
  "geometry": {"coordinates":[-2.0736210346,53.3881950378],"type":"Point"}
}