{
  "type": "Feature",
  "properties": {
    "addr:full":"7 Caledonian Rd, Fauldhouse Bathgate North Lanarkshire EH47 9DD",
    "addr:housenumber":"7",
    "addr:postcode":"eh47 9dd",
    "addr:street":"Caledonian Rd;Bathgate",
    "iso:country":"GB",
    "sg:address":"7 Caledonian Rd, Fauldhouse",
    "sg:city":"Bathgate",
    "sg:classifiers":[
        {
            "category":"Banks & Credit Unions",
            "subcategory":"Financial Services",
            "type":"Services"
        }
    ],
    "sg:phone":"+44 1501 770770",
    "sg:postcode":"EH47 9DD",
    "sg:province":"North Lanarkshire",
    "sg:tags":[
        "agent",
        "tied"
    ],
    "wof:name":"Alastair Fowler Associates",
    "wof:placetype":"venue"
},
  "geometry": {"coordinates":[-3.717383,55.824062],"type":"Point"}
}