{
  "type": "Feature",
  "properties": {
    "addr:full":"10 Eskdale Close Weston-super-mare Somerset BS22 8QG",
    "addr:housenumber":"10",
    "addr:postcode":"bs22 8qg",
    "addr:street":"Eskdale Close",
    "iso:country":"GB",
    "sg:address":"10 Eskdale Close",
    "sg:city":"Weston-super-mare",
    "sg:classifiers":[
        {
            "category":"Retail",
            "subcategory":"Storage",
            "type":"Services"
        }
    ],
    "sg:phone":"+44 1934 413415",
    "sg:postcode":"BS22 8QG",
    "sg:province":"Somerset",
    "sg:tags":[
        "household",
        "removal"
    ],
    "wof:name":"Man With Van",
    "wof:placetype":"venue"
},
  "geometry": {"coordinates":[-2.9399518967,51.3500289917],"type":"Point"}
}