{
  "type": "Feature",
  "properties": {
    "addr:full":"Pendwylan, Beulah Newcastle Emlyn Carmarthenshire SA38 9QP",
    "addr:postcode":"sa38 9qp",
    "addr:street":"Beulah",
    "iso:country":"GB",
    "sg:address":"Pendwylan, Beulah",
    "sg:city":"Newcastle Emlyn",
    "sg:classifiers":[
        {
            "category":"Home & Garden",
            "subcategory":"Household Appliances",
            "type":"Retail Goods"
        }
    ],
    "sg:postcode":"SA38 9QP",
    "sg:province":"Carmarthenshire",
    "sg:tags":[
        "electrical"
    ],
    "wof:name":"Aberteifi & West Wales Repair Service",
    "wof:placetype":"venue"
},
  "geometry": {"coordinates":[-4.467984,52.035919],"type":"Point"}
}