{
  "type": "Feature",
  "properties": {
    "addr:full":"Boswell Farm, Boswell Louth Lincolnshire LN11 0SG",
    "addr:postcode":"ln11 0sg",
    "addr:street":"Louth",
    "iso:country":"GB",
    "sg:address":"Boswell Farm, Boswell",
    "sg:city":"Louth",
    "sg:classifiers":[
        {
            "category":"Farming",
            "subcategory":"Crops",
            "type":"Manufacturing & Wholesale Goods"
        },
        {
            "category":"Farming",
            "subcategory":"Livestock Farm",
            "type":"Manufacturing & Wholesale Goods"
        }
    ],
    "sg:phone":"+44 1507 604214",
    "sg:postcode":"LN11 0SG",
    "sg:province":"Lincolnshire",
    "sg:tags":[
        "arable",
        "others"
    ],
    "wof:name":"Boswell Farming Co.",
    "wof:placetype":"venue"
},
  "geometry": {"coordinates":[-0.0073910002,53.3664970398],"type":"Point"}
}