{
  "type": "Feature",
  "properties": {
    "iso:country":"GB",
    "sg:address":"Beacon Rd",
    "sg:city":"Scarborough",
    "sg:classifiers":[
        {
            "category":"Personal",
            "type":"Services"
        }
    ],
    "sg:phone":"+44 1723 863738",
    "sg:postcode":"YO12 4HT",
    "sg:province":"North Yorkshire",
    "sg:tags":[
        "wedding"
    ],
    "wof:name":"AA Wedding Cars",
    "wof:placetype":"venue"
},
  "geometry": {"coordinates":[-0.43934,54.243084],"type":"Point"}
}