{
  "type": "Feature",
  "properties": {
    "addr:full":"6 High St, Hadleigh Ipswich Suffolk IP7 5AP",
    "addr:housenumber":"6",
    "addr:postcode":"ip7 5ap",
    "addr:street":"High St",
    "iso:country":"GB",
    "sg:address":"6 High St, Hadleigh",
    "sg:city":"Ipswich",
    "sg:classifiers":[
        {
            "category":"Shopping",
            "subcategory":"Beauty & Cosmetics",
            "type":"Retail Goods"
        }
    ],
    "sg:phone":"+44 1473 823222",
    "sg:postcode":"IP7 5AP",
    "sg:province":"Suffolk",
    "sg:tags":[
        "product"
    ],
    "wof:name":"San Suei Skincare Ltd",
    "wof:placetype":"venue"
},
  "geometry": {"coordinates":[0.954949,52.042561],"type":"Point"}
}