{
  "type": "Feature",
  "properties": {
    "addr:full":"7 Golf Road Aboyne Aberdeenshire AB34 5HP",
    "addr:housenumber":"7",
    "addr:postcode":"ab34 5hp",
    "addr:street":"Golf Road",
    "iso:country":"GB",
    "sg:address":"7 Golf Road",
    "sg:city":"Aboyne",
    "sg:classifiers":[
        {
            "category":"Building & Trades",
            "subcategory":"Construction",
            "type":"Services"
        }
    ],
    "sg:phone":"+44 1339 886810",
    "sg:postcode":"AB34 5HP",
    "sg:province":"Aberdeenshire",
    "sg:tags":[
        "joinery",
        "joiner",
        "carpenter",
        "carpentry"
    ],
    "wof:name":"Alan Ploughman",
    "wof:placetype":"venue"
},
  "geometry": {"coordinates":[-2.7729649544,57.0796012878],"type":"Point"}
}