{
  "type": "Feature",
  "properties": {
    "iso:country":"GB",
    "sg:address":"1500 Po Box, Springfield Road",
    "sg:city":"London",
    "sg:classifiers":[
        {
            "category":"Banks & Credit Unions",
            "subcategory":"Financial Services",
            "type":"Services"
        }
    ],
    "sg:phone":"+44 20 8368 9655",
    "sg:postcode":"N11 3DZ",
    "sg:province":"Greater London",
    "sg:tags":[
        "consultant",
        "finance"
    ],
    "wof:name":"London & Provincial Finance Ltd.",
    "wof:placetype":"venue"
},
  "geometry": {"coordinates":[-0.15132,51.613392],"type":"Point"}
}