{
  "type": "Feature",
  "properties": {
    "addr:full":"1b Old Orchard Poole Dorset BH15 1SD",
    "addr:housenumber":"1b",
    "addr:postcode":"bh15 1sd",
    "addr:street":"Old",
    "iso:country":"GB",
    "sg:address":"1b Old Orchard",
    "sg:city":"Poole",
    "sg:classifiers":[
        {
            "category":"Real Estate",
            "subcategory":"Developer",
            "type":"Services"
        }
    ],
    "sg:phone":"+44 1202 675707",
    "sg:postcode":"BH15 1SD",
    "sg:province":"Dorset",
    "sg:tags":[
        "property"
    ],
    "wof:name":"Malbury Properties Ltd",
    "wof:placetype":"venue"
},
  "geometry": {"coordinates":[-1.985701,50.713757],"type":"Point"}
}