{
  "type": "Feature",
  "properties": {
    "addr:full":"103 Manningham La Bradford West Yorkshire BD1 3BN",
    "addr:housenumber":"103",
    "addr:postcode":"bd1 3bn",
    "addr:street":"Manningham La Bradford West",
    "iso:country":"GB",
    "sg:address":"103 Manningham La",
    "sg:city":"Bradford",
    "sg:classifiers":[
        {
            "category":"Professional",
            "subcategory":"Detective & Security Services",
            "type":"Services"
        }
    ],
    "sg:phone":"+44 1274 306786",
    "sg:postcode":"BD1 3BN",
    "sg:province":"West Yorkshire",
    "sg:tags":[
        "alarm",
        "burglar",
        "system"
    ],
    "wof:name":"Bulldog Accessories",
    "wof:placetype":"venue"
},
  "geometry": {"coordinates":[-1.760345,53.801346],"type":"Point"}
}