{
  "type": "Feature",
  "properties": {
    "addr:full":"19-21 Victoria Square Bolton Lancashire BL1 1RJ",
    "addr:housenumber":"19-21",
    "addr:postcode":"bl1 1rj",
    "addr:street":"Victoria Square",
    "iso:country":"GB",
    "sg:address":"19-21 Victoria Square",
    "sg:city":"Bolton",
    "sg:classifiers":[
        {
            "category":"Shopping",
            "subcategory":"Shoes",
            "type":"Retail Goods"
        }
    ],
    "sg:phone":"+44 1204 388083",
    "sg:postcode":"BL1 1RJ",
    "sg:province":"Lancashire",
    "sg:tags":[
        "shop"
    ],
    "wof:name":"Barratt Shoes",
    "wof:placetype":"venue"
},
  "geometry": {"coordinates":[-2.4303839207,53.5786857605],"type":"Point"}
}