{
  "type": "Feature",
  "properties": {
    "addr:full":"Parkside House, South Broomhill Morpeth Northumberland NE65 9RR",
    "addr:postcode":"ne65 9rr",
    "addr:street":"South",
    "iso:country":"GB",
    "sg:address":"Parkside House, South Broomhill",
    "sg:city":"Morpeth",
    "sg:classifiers":[
        {
            "category":"Food & Beverages",
            "subcategory":"Meat & Fish",
            "type":"Retail Goods"
        }
    ],
    "sg:phone":"+44 1670 760217",
    "sg:postcode":"NE65 9RR",
    "sg:province":"Northumberland",
    "sg:tags":[
        "butcher"
    ],
    "wof:name":"John Thomas Wright",
    "wof:placetype":"venue"
},
  "geometry": {"coordinates":[-1.609309,55.2952],"type":"Point"}
}