{
  "type": "Feature",
  "properties": {
    "iso:country":"GB",
    "sg:address":"7 Shannon Centre",
    "sg:city":"Canvey Island",
    "sg:classifiers":[
        {
            "category":"Professional",
            "subcategory":"Printing & Photocopies",
            "type":"Services"
        }
    ],
    "sg:postcode":"SS8 0PE",
    "sg:province":"Essex",
    "sg:tags":[
        "printer"
    ],
    "wof:name":"Viking Reproductions",
    "wof:placetype":"venue"
},
  "geometry": {"coordinates":[0.5715000033,51.5198783875],"type":"Point"}
}