{
  "type": "Feature",
  "properties": {
    "iso:country":"GB",
    "sg:address":"Gourdieburn Farm, Potterton",
    "sg:city":"Aberdeen",
    "sg:classifiers":[
        {
            "category":"Food & Beverages",
            "subcategory":"Groceries & Convenience Stores",
            "type":"Retail Goods"
        }
    ],
    "sg:phone":"+44 1358 743352",
    "sg:postcode":"AB23 8UY",
    "sg:province":"Aberdeen City",
    "sg:tags":[
        "merchant",
        "potato"
    ],
    "wof:name":"Aberdeen Seed Potato Organisation Ltd.",
    "wof:placetype":"venue"
},
  "geometry": {"coordinates":[-2.102241,57.233044],"type":"Point"}
}