{
  "type": "Feature",
  "properties": {
    "iso:country":"GB",
    "sg:address":"The Garage, Grove Ave",
    "sg:city":"Weymouth",
    "sg:classifiers":[
        {
            "category":"Retail",
            "subcategory":"Auto Repair",
            "type":"Services"
        }
    ],
    "sg:phone":"+44 1305 785623",
    "sg:postcode":"DT4 7RA",
    "sg:province":"Dorset",
    "sg:tags":[
        "modification",
        "garage"
    ],
    "wof:name":"Polley,S G,& Co Ltd",
    "wof:placetype":"venue"
},
  "geometry": {"coordinates":[-2.459206,50.609901],"type":"Point"}
}