{
  "type": "Feature",
  "properties": {
    "iso:country":"GB",
    "sg:address":"36 Carlyon Road",
    "sg:city":"Wembley",
    "sg:classifiers":[
        {
            "category":"Shopping",
            "subcategory":"News",
            "type":"Retail Goods"
        },
        {
            "category":"Food & Beverages",
            "subcategory":"Groceries & Convenience Stores",
            "type":"Retail Goods"
        }
    ],
    "sg:phone":"+44 20 8997 7246",
    "sg:postcode":"HA0 1JE",
    "sg:province":"Greater London",
    "sg:tags":[
        "newsagent"
    ],
    "wof:name":"Abbey Corner",
    "wof:placetype":"venue"
},
  "geometry": {"coordinates":[-0.294471,51.537998],"type":"Point"}
}