{
  "type": "Feature",
  "properties": {
    "iso:country":"GB",
    "sg:address":"49 Cavendish Road",
    "sg:city":"London",
    "sg:classifiers":[
        {
            "category":"Professional",
            "subcategory":"Management & Consulting",
            "type":"Services"
        }
    ],
    "sg:phone":"+44 20 7228 7382",
    "sg:postcode":"SW12 0BL",
    "sg:province":"Greater London",
    "sg:tags":[
        "consultant",
        "business"
    ],
    "wof:name":"The Yellow Palette",
    "wof:placetype":"venue"
},
  "geometry": {"coordinates":[-0.142536,51.452808],"type":"Point"}
}