{
  "type": "Feature",
  "properties": {
    "addr:full":"43 Clayton Avenue, Upton Pontefract West Yorkshire WF9 1LA",
    "addr:housenumber":"43",
    "addr:postcode":"wf9 1la",
    "addr:street":"Clayton Avenue",
    "iso:country":"GB",
    "sg:address":"43 Clayton Avenue, Upton",
    "sg:city":"Pontefract",
    "sg:classifiers":[
        {
            "category":"Taxi",
            "type":"Transportation"
        },
        {
            "category":"Military Area",
            "subcategory":"Air Force Base",
            "type":"Public Place"
        }
    ],
    "sg:phone":"+44 1977 646150",
    "sg:postcode":"WF9 1LA",
    "sg:province":"West Yorkshire",
    "sg:tags":[
        "mini",
        "hire",
        "private",
        "cab"
    ],
    "wof:name":"Dale Cars",
    "wof:placetype":"venue"
},
  "geometry": {"coordinates":[-1.257079,53.617496],"type":"Point"}
}