{
  "type": "Feature",
  "properties": {
    "addr:full":"Shirley Road, Off Tong Street Bradford West Yorkshire BD4 9PX",
    "addr:postcode":"bd4 9px",
    "addr:street":"Shirley Road Off Tong Street",
    "iso:country":"GB",
    "sg:address":"Shirley Road, Off Tong Street",
    "sg:city":"Bradford",
    "sg:classifiers":[
        {
            "category":"Organizations",
            "subcategory":"Membership Organization",
            "type":"Services"
        }
    ],
    "sg:phone":"+44 1274 681010",
    "sg:postcode":"BD4 9PX",
    "sg:province":"West Yorkshire",
    "sg:tags":[
        "club"
    ],
    "wof:name":"Dudley Hill & Tong Working Mens Club",
    "wof:placetype":"venue"
},
  "geometry": {"coordinates":[-1.7164789438,53.769241333],"type":"Point"}
}