{
  "type": "Feature",
  "properties": {
    "addr:full":"10-12 Pilgrim Street Newcastle-upon-tyne Tyne and Wear NE1 6QG",
    "addr:housenumber":"10-12",
    "addr:postcode":"ne1 6qg",
    "addr:street":"Pilgrim Street",
    "iso:country":"GB",
    "sg:address":"10-12 Pilgrim Street",
    "sg:city":"Newcastle-upon-tyne",
    "sg:classifiers":[
        {
            "category":"Cafe",
            "type":"Food & Drink"
        }
    ],
    "sg:phone":"+44 191 261 9291",
    "sg:postcode":"NE1 6QG",
    "sg:province":"Tyne and Wear",
    "sg:tags":[
        "tea",
        "room"
    ],
    "wof:name":"The Tyneside Coffee Rooms",
    "wof:placetype":"venue"
},
  "geometry": {"coordinates":[-1.611901,54.974129],"type":"Point"}
}