{
  "type": "Feature",
  "properties": {
    "iso:country":"GB",
    "sg:address":"82 Cheltenham Road East",
    "sg:city":"Gloucester",
    "sg:classifiers":[
        {
            "category":"Professional",
            "subcategory":"Engineering",
            "type":"Services"
        }
    ],
    "sg:postcode":"GL3 1AD",
    "sg:province":"Gloucestershire",
    "sg:tags":[
        "contractor",
        "electrical",
        "engineer"
    ],
    "wof:name":"Freeman,Nathan,",
    "wof:placetype":"venue"
},
  "geometry": {"coordinates":[-2.198219,51.88073],"type":"Point"}
}