{
  "type": "Feature",
  "properties": {
    "iso:country":"GB",
    "sg:address":"Firs Farm, Holme Pierrepont Lane, Holme Pierrepont",
    "sg:city":"Nottingham",
    "sg:classifiers":[
        {
            "category":"Wholesale",
            "subcategory":"Meat",
            "type":"Manufacturing & Wholesale Goods"
        }
    ],
    "sg:phone":"+44 115 933 3772",
    "sg:postcode":"NG12 2LD",
    "sg:province":"Nottinghamshire",
    "sg:tags":[
        "-"
    ],
    "wof:name":"Sidney Hackett Ltd.",
    "wof:placetype":"venue"
},
  "geometry": {"coordinates":[-1.064099,52.945923],"type":"Point"}
}