{
  "type": "Feature",
  "properties": {
    "iso:country":"GB",
    "sg:address":"79 Friargate Walk, St Georges Shopping Centre",
    "sg:city":"Preston",
    "sg:classifiers":[
        {
            "category":"Shopping",
            "subcategory":"Clothing, Apparel, & Fashions",
            "type":"Retail Goods"
        }
    ],
    "sg:phone":"+44 1772 254856",
    "sg:postcode":"PR1 2NQ",
    "sg:province":"Lancashire",
    "sg:tags":[
        "ladieswear"
    ],
    "wof:name":"D B 2",
    "wof:placetype":"venue"
},
  "geometry": {"coordinates":[-2.705642,53.761749],"type":"Point"}
}