{
  "type": "Feature",
  "properties": {
    "iso:country":"GB",
    "sg:address":"14 Station Road",
    "sg:city":"Thirsk",
    "sg:classifiers":[
        {
            "category":"Parking",
            "type":"Transportation"
        }
    ],
    "sg:phone":"+44 1845 525258",
    "sg:postcode":"YO7 1QH",
    "sg:province":"North Yorkshire",
    "sg:tags":[
        "car",
        "valet"
    ],
    "wof:name":"Carsheen",
    "wof:placetype":"venue"
},
  "geometry": {"coordinates":[-1.354371,54.230492],"type":"Point"}
}