{
  "type": "Feature",
  "properties": {
    "iso:country":"GB",
    "sg:address":"Linwood Centre, Linwood La",
    "sg:city":"Leicester",
    "sg:classifiers":[
        {
            "category":"Organizations",
            "subcategory":"Non-profit Organization",
            "type":"Services"
        }
    ],
    "sg:postcode":"LE2 6QN",
    "sg:province":"Leicestershire",
    "sg:tags":[
        "organisation",
        "voluntary",
        "charity"
    ],
    "wof:name":"Young Carers Scheme (Leicestershire)",
    "wof:placetype":"venue"
},
  "geometry": {"coordinates":[-1.132686,52.59906],"type":"Point"}
}