{
  "type": "Feature",
  "properties": {
    "addr:full":"13 Rainhall Rd Colne Lancashire BB8 5AF",
    "addr:housenumber":"13",
    "addr:postcode":"bb8 5af",
    "addr:street":"Rainhall Rd",
    "iso:country":"GB",
    "sg:address":"13 Rainhall Rd",
    "sg:city":"Colne",
    "sg:classifiers":[
        {
            "category":"Personal",
            "subcategory":"Beauty Salon",
            "type":"Services"
        }
    ],
    "sg:phone":"+44 1282 816718",
    "sg:postcode":"BB8 5AF",
    "sg:province":"Lancashire",
    "sg:tags":[
        "unisex",
        "hairdresser"
    ],
    "wof:name":"Hairline",
    "wof:placetype":"venue"
},
  "geometry": {"coordinates":[-2.1868751049,53.9155883789],"type":"Point"}
}