{
  "type": "Feature",
  "properties": {
    "iso:country":"GB",
    "sg:address":"Longbeck Trading Estate, Marske",
    "sg:city":"Redcar",
    "sg:classifiers":[
        {
            "category":"Professional",
            "subcategory":"Engineering",
            "type":"Services"
        }
    ],
    "sg:postcode":"TS11 6HB",
    "sg:province":"North Yorkshire",
    "wof:name":"A M L Engineers (Teesside) Ltd.",
    "wof:placetype":"venue"
},
  "geometry": {"coordinates":[-1.029604,54.589569],"type":"Point"}
}