{
  "type": "Feature",
  "properties": {
    "addr:full":"Drewynt, Felinfach Lampeter Carmarthenshire SA48 7QD",
    "addr:postcode":"sa48 7qd",
    "addr:street":"Carmarthenshire",
    "iso:country":"GB",
    "sg:address":"Drewynt, Felinfach",
    "sg:city":"Lampeter",
    "sg:classifiers":[
        {
            "category":"Farming",
            "subcategory":"Dairy Farm",
            "type":"Manufacturing & Wholesale Goods"
        }
    ],
    "sg:postcode":"SA48 7QD",
    "sg:province":"Carmarthenshire",
    "wof:name":"J T Harwood",
    "wof:placetype":"venue"
},
  "geometry": {"coordinates":[-4.0774650574,52.1142616272],"type":"Point"}
}