{
  "type": "Feature",
  "properties": {
    "iso:country":"GB",
    "sg:address":"29 Charlotte St",
    "sg:city":"Portsmouth",
    "sg:classifiers":[
        {
            "category":"Professional",
            "subcategory":"Business Services",
            "type":"Services"
        }
    ],
    "sg:postcode":"PO1 4AH",
    "sg:province":"Hampshire",
    "sg:tags":[
        "import",
        "export",
        "agent"
    ],
    "wof:name":"Poundsworth",
    "wof:placetype":"venue"
},
  "geometry": {"coordinates":[-1.08894,50.801933],"type":"Point"}
}