{
  "type": "Feature",
  "properties": {
    "addr:full":"11-15 Gibbons Road, Stratford London Greater London E15 2HU",
    "addr:housenumber":"11-15",
    "addr:postcode":"e15 2hu",
    "addr:street":"Gibbons Road",
    "iso:country":"GB",
    "sg:address":"11-15 Gibbons Road, Stratford",
    "sg:city":"London",
    "sg:classifiers":[
        {
            "category":"Home & Garden",
            "subcategory":"Building Materials",
            "type":"Retail Goods"
        },
        {
            "category":"Building & Trades",
            "subcategory":"Construction",
            "type":"Services"
        }
    ],
    "sg:phone":"+44 20 8519 1515",
    "sg:postcode":"E15 2HU",
    "sg:province":"Greater London",
    "sg:tags":[
        "roofing"
    ],
    "wof:name":"Ruberoid Contracts Ltd",
    "wof:placetype":"venue"
},
  "geometry": {"coordinates":[-0.00395,51.539532],"type":"Point"}
}