{
  "type": "Feature",
  "properties": {
    "addr:full":"Manor Farm Bungalow Chinnor Buckinghamshire OX9 4AE",
    "addr:postcode":"ox9 4ae",
    "addr:street":"Manor",
    "iso:country":"GB",
    "sg:address":"Manor Farm Bungalow",
    "sg:city":"Chinnor",
    "sg:classifiers":[
        {
            "category":"Professional",
            "type":"Services"
        }
    ],
    "sg:phone":"+44 1844 354360",
    "sg:postcode":"OX9 4AE",
    "sg:province":"Buckinghamshire",
    "sg:tags":[
        "entertainer"
    ],
    "wof:name":"Rainbow Parties",
    "wof:placetype":"venue"
},
  "geometry": {"coordinates":[-0.9099199772,51.7020797729],"type":"Point"}
}