{
  "type": "Feature",
  "properties": {
    "addr:full":"Warehouse & Premises Ilkeston Derbyshire DE7 5EP",
    "addr:postcode":"de7 5ep",
    "iso:country":"GB",
    "sg:address":"Warehouse & Premises",
    "sg:city":"Ilkeston",
    "sg:classifiers":[
        {
            "category":"Retail",
            "subcategory":"Storage",
            "type":"Services"
        }
    ],
    "sg:postcode":"DE7 5EP",
    "sg:province":"Derbyshire",
    "sg:tags":[
        "household",
        "removal"
    ],
    "wof:name":"Centre Freight",
    "wof:placetype":"venue"
},
  "geometry": {"coordinates":[-1.29096,52.964062],"type":"Point"}
}