{
  "type": "Feature",
  "properties": {
    "addr:full":"Merseyside Campaign Office, 19 Hope St Liverpool Merseyside L1 9BQ",
    "addr:housenumber":"19",
    "addr:postcode":"l1 9bq",
    "addr:street":"Hope St",
    "iso:country":"GB",
    "sg:address":"Merseyside Campaign Office, 19 Hope St",
    "sg:city":"Liverpool",
    "sg:classifiers":[
        {
            "category":"Shopping",
            "subcategory":"Thrift Store",
            "type":"Retail Goods"
        }
    ],
    "sg:phone":"+44 151 708 9956",
    "sg:postcode":"L1 9BQ",
    "sg:province":"Merseyside",
    "sg:tags":[
        "shop",
        "charity"
    ],
    "wof:name":"Oxfam",
    "wof:placetype":"venue"
},
  "geometry": {"coordinates":[-2.9784810543,53.4097747803],"type":"Point"}
}