{
  "type": "Feature",
  "properties": {
    "addr:full":"2 St Marys Street Dumfries Dumfries and Galloway DG1 1HD",
    "addr:housenumber":"2",
    "addr:postcode":"dg1 1hd",
    "addr:street":"St Marys Street",
    "iso:country":"GB",
    "sg:address":"2 St Marys Street",
    "sg:city":"Dumfries",
    "sg:classifiers":[
        {
            "category":"Retail",
            "subcategory":"Auto Repair",
            "type":"Services"
        }
    ],
    "sg:phone":"+44 1387 255291",
    "sg:postcode":"DG1 1HD",
    "sg:province":"Dumfries and Galloway",
    "sg:tags":[
        "modification",
        "garage"
    ],
    "wof:name":"Ian Cole Ltd.",
    "wof:placetype":"venue"
},
  "geometry": {"coordinates":[-3.601657,55.072498],"type":"Point"}
}