{
  "type": "Feature",
  "properties": {
    "iso:country":"GB",
    "sg:address":"Somerset Road, Linford",
    "sg:city":"Stanford-le-hope",
    "sg:classifiers":[
        {
            "category":"Farming",
            "subcategory":"Nursery",
            "type":"Manufacturing & Wholesale Goods"
        }
    ],
    "sg:phone":"+44 1375 675139",
    "sg:postcode":"SS17 0QA",
    "sg:province":"Essex",
    "sg:tags":[
        "creche"
    ],
    "wof:name":"Little Angels",
    "wof:placetype":"venue"
},
  "geometry": {"coordinates":[0.40727,51.489513],"type":"Point"}
}