{
  "type": "Feature",
  "properties": {
    "addr:full":"28 Minster Precincts Peterborough Cambridgeshire PE1 1XT",
    "addr:housenumber":"28",
    "addr:postcode":"pe1 1xt",
    "addr:street":"Minster Precincts",
    "iso:country":"GB",
    "sg:address":"28 Minster Precincts",
    "sg:city":"Peterborough",
    "sg:classifiers":[
        {
            "category":"Real Estate",
            "subcategory":"Surveying",
            "type":"Services"
        }
    ],
    "sg:phone":"+44 1733 567231",
    "sg:postcode":"PE1 1XT",
    "sg:province":"Cambridgeshire",
    "sg:tags":[
        "surveyor",
        "valuer"
    ],
    "wof:name":"Smiths Gore Ltd.",
    "wof:placetype":"venue"
},
  "geometry": {"coordinates":[-0.2435899973,52.5724411011],"type":"Point"}
}