{
  "type": "Feature",
  "properties": {
    "iso:country":"GB",
    "sg:address":"Erwlon, Henfwlch Road",
    "sg:city":"Carmarthen",
    "sg:classifiers":[
        {
            "category":"Building & Trades",
            "subcategory":"Construction",
            "type":"Services"
        }
    ],
    "sg:phone":"+44 1267 237920",
    "sg:postcode":"SA33 6AA",
    "sg:province":"Carmarthenshire",
    "sg:tags":[
        "heating",
        "contractor"
    ],
    "wof:name":"M M Insulation",
    "wof:placetype":"venue"
},
  "geometry": {"coordinates":[-4.35045,51.874001],"type":"Point"}
}