{
  "type": "Feature",
  "properties": {
    "addr:full":"6a Cliff Road Harwich Essex CO12 3PP",
    "addr:housenumber":"6a",
    "addr:postcode":"co12 3pp",
    "addr:street":"Cliff Road",
    "iso:country":"GB",
    "sg:address":"6a Cliff Road",
    "sg:city":"Harwich",
    "sg:classifiers":[
        {
            "category":"Professional",
            "subcategory":"Engineering",
            "type":"Services"
        }
    ],
    "sg:postcode":"CO12 3PP",
    "sg:province":"Essex",
    "sg:tags":[
        "contractor",
        "electrical",
        "engineer"
    ],
    "wof:name":"Gk Electronics Ltd",
    "wof:placetype":"venue"
},
  "geometry": {"coordinates":[1.2792099714,51.935710907],"type":"Point"}
}