{
  "type": "Feature",
  "properties": {
    "addr:full":"42 Packhorse Road Gerrards Cross Buckinghamshire SL9 8EB",
    "addr:housenumber":"42",
    "addr:postcode":"sl9 8eb",
    "addr:street":"Packhorse Road",
    "iso:country":"GB",
    "sg:address":"42 Packhorse Road",
    "sg:city":"Gerrards Cross",
    "sg:classifiers":[
        {
            "category":"Professional",
            "subcategory":"Lawyer & Legal Services",
            "type":"Services"
        }
    ],
    "sg:phone":"+44 1753 892244",
    "sg:postcode":"SL9 8EB",
    "sg:province":"Buckinghamshire",
    "sg:tags":[
        "solicitor"
    ],
    "wof:name":"Stuarts",
    "wof:placetype":"venue"
},
  "geometry": {"coordinates":[-0.552638,51.588654],"type":"Point"}
}