{
  "type": "Feature",
  "properties": {
    "iso:country":"GB",
    "sg:address":"M5 Strensham Motorway Services Area, Hillcroome",
    "sg:city":"Worcester",
    "sg:classifiers":[
        {
            "category":"Shopping",
            "subcategory":"Mobile Phones",
            "type":"Retail Goods"
        }
    ],
    "sg:phone":"+44 1684 593800",
    "sg:postcode":"WR8 0BZ",
    "sg:province":"Gloucestershire",
    "wof:name":"Midland Mobile Communications Ltd",
    "wof:placetype":"venue"
},
  "geometry": {"coordinates":[-2.15837,52.066818],"type":"Point"}
}