{
  "type": "Feature",
  "properties": {
    "iso:country":"GB",
    "sg:address":"Holbeton, Battisborough Cross",
    "sg:city":"Plymouth",
    "sg:classifiers":[
        {
            "category":"Retail",
            "subcategory":"Auto Repair",
            "type":"Services"
        }
    ],
    "sg:postcode":"PL8 1JQ",
    "sg:province":"Devon",
    "sg:tags":[
        "modification",
        "garage"
    ],
    "wof:name":"Battisborough Garage",
    "wof:placetype":"venue"
},
  "geometry": {"coordinates":[-3.949378,50.335175],"type":"Point"}
}