{
  "type": "Feature",
  "properties": {
    "iso:country":"GB",
    "sg:address":"47 High Street",
    "sg:city":"West Malling",
    "sg:classifiers":[
        {
            "category":"Home & Garden",
            "subcategory":"Furniture",
            "type":"Retail Goods"
        }
    ],
    "sg:phone":"+44 1732 846386",
    "sg:postcode":"ME19 6QH",
    "sg:province":"Kent",
    "wof:name":"Ashley Russell Pine Studio",
    "wof:placetype":"venue"
},
  "geometry": {"coordinates":[0.409147,51.29496],"type":"Point"}
}