{
  "type": "Feature",
  "properties": {
    "iso:country":"GB",
    "sg:address":"Farm Office, Oad Street",
    "sg:city":"Sittingbourne",
    "sg:classifiers":[
        {
            "category":"Farming",
            "subcategory":"Livestock Farm",
            "type":"Manufacturing & Wholesale Goods"
        },
        {
            "category":"Farming",
            "subcategory":"Farm",
            "type":"Manufacturing & Wholesale Goods"
        }
    ],
    "sg:postcode":"ME9 8JP",
    "sg:province":"Kent",
    "sg:tags":[
        "mixed",
        "crop",
        "others"
    ],
    "wof:name":"A Hinge & Sons Ltd.",
    "wof:placetype":"venue"
},
  "geometry": {"coordinates":[0.6826099753,51.3274917603],"type":"Point"}
}