{
  "type": "Feature",
  "properties": {
    "iso:country":"GB",
    "sg:address":"4-6 Doncaster Road",
    "sg:city":"Bristol",
    "sg:classifiers":[
        {
            "category":"Shopping",
            "subcategory":"Used Merchandise",
            "type":"Retail Goods"
        }
    ],
    "sg:postcode":"BS10 5PL",
    "sg:province":"City of Bristol",
    "sg:tags":[
        "shop",
        "second-hand"
    ],
    "wof:name":"A Second Chance",
    "wof:placetype":"venue"
},
  "geometry": {"coordinates":[-2.5987889767,51.4980583191],"type":"Point"}
}