{
  "type": "Feature",
  "properties": {
    "addr:full":"Whitehouse Farm, Church Road, Terrington St John Wisbech Cambridgeshire PE14 7SA",
    "addr:postcode":"pe14 7sa",
    "addr:street":"Church Road Terrington St",
    "iso:country":"GB",
    "sg:address":"Whitehouse Farm, Church Road, Terrington St John",
    "sg:city":"Wisbech",
    "sg:classifiers":[
        {
            "category":"Farming",
            "subcategory":"Livestock Farm",
            "type":"Manufacturing & Wholesale Goods"
        },
        {
            "category":"Farming",
            "subcategory":"Farm",
            "type":"Manufacturing & Wholesale Goods"
        }
    ],
    "sg:postcode":"PE14 7SA",
    "sg:province":"Cambridgeshire",
    "sg:tags":[
        "mixed",
        "crop",
        "others"
    ],
    "wof:name":"Smart Bros",
    "wof:placetype":"venue"
},
  "geometry": {"coordinates":[0.281069994,52.7211799622],"type":"Point"}
}