{
  "type": "Feature",
  "properties": {
    "iso:country":"GB",
    "sg:address":"180 Belgrave Middleway, Highgate",
    "sg:city":"Birmingham",
    "sg:classifiers":[
        {
            "category":"Arena",
            "subcategory":"Sports Club",
            "type":"Entertainment"
        }
    ],
    "sg:phone":"+44 121 446 4642",
    "sg:postcode":"B12 0XS",
    "sg:province":"West Midlands",
    "wof:name":"Birmingham Pakistan Sports Forum",
    "wof:placetype":"venue"
},
  "geometry": {"coordinates":[-1.885796,52.463196],"type":"Point"}
}