{
  "type": "Feature",
  "properties": {
    "iso:country":"GB",
    "sg:address":"225 Mansfield Road, Skegby",
    "sg:city":"Sutton-in-ashfield",
    "sg:classifiers":[
        {
            "category":"Government",
            "subcategory":"Post Office",
            "type":"Public Place"
        }
    ],
    "sg:phone":"+44 1623 554060",
    "sg:postcode":"NG17 3DU",
    "sg:province":"Nottinghamshire",
    "wof:name":"Skegby Sub Post Office",
    "wof:placetype":"venue"
},
  "geometry": {"coordinates":[-1.2513799667,53.1405944824],"type":"Point"}
}