{
  "type": "Feature",
  "properties": {
    "addr:full":"74 Moulsham St Chelmsford Essex CM2 0JA",
    "addr:housenumber":"74",
    "addr:postcode":"cm2 0ja",
    "addr:street":"Moulsham St",
    "iso:country":"GB",
    "sg:address":"74 Moulsham St",
    "sg:city":"Chelmsford",
    "sg:classifiers":[
        {
            "category":"Real Estate",
            "subcategory":"Real Estate Agent",
            "type":"Services"
        }
    ],
    "sg:postcode":"CM2 0JA",
    "sg:province":"Essex",
    "wof:name":"Candler,Sean",
    "wof:placetype":"venue"
},
  "geometry": {"coordinates":[0.470007,51.728317],"type":"Point"}
}