{
  "type": "Feature",
  "properties": {
    "addr:full":"Oliver Close, Tuffley Gloucester Gloucestershire GL4 0HD",
    "addr:postcode":"gl4 0hd",
    "addr:street":"Oliver Close",
    "iso:country":"GB",
    "sg:address":"Oliver Close, Tuffley",
    "sg:city":"Gloucester",
    "sg:classifiers":[
        {
            "category":"Government",
            "subcategory":"Office",
            "type":"Public Place"
        },
        {
            "category":"Social Services",
            "subcategory":"Adult Care",
            "type":"Services"
        },
        {
            "category":"Social Services",
            "subcategory":"Retirement Home",
            "type":"Services"
        }
    ],
    "sg:phone":"+44 1452 305244",
    "sg:postcode":"GL4 0HD",
    "sg:province":"Gloucestershire",
    "sg:tags":[
        "housing",
        "local",
        "accommodation",
        "sheltered"
    ],
    "wof:name":"Sheltered Housing Scheme",
    "wof:placetype":"venue"
},
  "geometry": {"coordinates":[-2.2516739368,51.8291320801],"type":"Point"}
}