{
  "type": "Feature",
  "properties": {
    "addr:full":"37 Station App West Byfleet Surrey KT14 6NF",
    "addr:housenumber":"37",
    "addr:postcode":"kt14 6nf",
    "addr:street":"West",
    "iso:country":"GB",
    "sg:address":"37 Station App",
    "sg:city":"West Byfleet",
    "sg:classifiers":[
        {
            "category":"Fast Food",
            "type":"Food & Drink"
        },
        {
            "category":"Restaurant",
            "type":"Food & Drink"
        }
    ],
    "sg:phone":"+44 1932 353297",
    "sg:postcode":"KT14 6NF",
    "sg:province":"Surrey",
    "sg:tags":[
        "away",
        "indian",
        "take"
    ],
    "wof:name":"Suman Tandoori Restaurant",
    "wof:placetype":"venue"
},
  "geometry": {"coordinates":[-0.496921,51.338421],"type":"Point"}
}