{
  "type": "Feature",
  "properties": {
    "iso:country":"GB",
    "sg:address":"11 Luccombe Road",
    "sg:city":"Shanklin",
    "sg:classifiers":[
        {
            "category":"Travel",
            "subcategory":"Hotels & Motels",
            "type":"Entertainment"
        },
        {
            "category":"Retail",
            "subcategory":"Event Space",
            "type":"Services"
        }
    ],
    "sg:phone":"+44 1983 862820",
    "sg:postcode":"PO37 6RR",
    "sg:province":"Isle of Wight",
    "sg:tags":[
        "function",
        "room"
    ],
    "wof:name":"S & G Shears",
    "wof:placetype":"venue"
},
  "geometry": {"coordinates":[-1.1773879528,50.6226348877],"type":"Point"}
}