{
  "type": "Feature",
  "properties": {
    "addr:full":"831 Romford Rd Manor Park Greater London E12 6EA",
    "addr:housenumber":"831",
    "addr:postcode":"e12 6ea",
    "addr:street":"Romford Rd",
    "iso:country":"GB",
    "sg:address":"831 Romford Rd",
    "sg:city":"Manor Park",
    "sg:classifiers":[
        {
            "category":"Personal",
            "subcategory":"Beauty Salon",
            "type":"Services"
        }
    ],
    "sg:phone":"+44 20 8478 2580",
    "sg:postcode":"E12 6EA",
    "sg:province":"Greater London",
    "sg:tags":[
        "unisex",
        "hairdresser"
    ],
    "wof:name":"Hair by Tony Adem",
    "wof:placetype":"venue"
},
  "geometry": {"coordinates":[0.053372,51.552795],"type":"Point"}
}