{
  "type": "Feature",
  "properties": {
    "addr:full":"5 Wickham Lane London Greater London SE2 0XJ",
    "addr:housenumber":"5",
    "addr:postcode":"se2 0xj",
    "addr:street":"Wickham Lane",
    "iso:country":"GB",
    "sg:address":"5 Wickham Lane",
    "sg:city":"London",
    "sg:classifiers":[
        {
            "category":"Retail",
            "subcategory":"Repair Shop",
            "type":"Services"
        }
    ],
    "sg:phone":"+44 20 8310 1234",
    "sg:postcode":"SE2 0XJ",
    "sg:province":"Greater London",
    "sg:tags":[
        "upholsterer"
    ],
    "wof:name":"Perry's Upholsterers",
    "wof:placetype":"venue"
},
  "geometry": {"coordinates":[0.1025540009,51.485080719],"type":"Point"}
}