{
  "type": "Feature",
  "properties": {
    "addr:full":"17 Bridge St Morpeth Northumberland NE61 1NT",
    "addr:housenumber":"17",
    "addr:postcode":"ne61 1nt",
    "addr:street":"Bridge St",
    "iso:country":"GB",
    "sg:address":"17 Bridge St",
    "sg:city":"Morpeth",
    "sg:classifiers":[
        {
            "category":"Restaurant",
            "type":"Food & Drink"
        }
    ],
    "sg:phone":"+44 1670 512420",
    "sg:postcode":"NE61 1NT",
    "sg:province":"Northumberland",
    "wof:name":"Tandoor Mahal",
    "wof:placetype":"venue"
},
  "geometry": {"coordinates":[-1.6893839836,55.1675720215],"type":"Point"}
}