{
  "type": "Feature",
  "properties": {
    "addr:full":"Peacock House, Garden Place Livingston West Lothian EH54 6RA",
    "addr:postcode":"eh54 6ra",
    "addr:street":"Garden Place",
    "iso:country":"GB",
    "sg:address":"Peacock House, Garden Place",
    "sg:city":"Livingston",
    "sg:classifiers":[
        {
            "category":"Health Services",
            "subcategory":"Doctor",
            "type":"Services"
        }
    ],
    "sg:phone":"+44 1506 462546",
    "sg:postcode":"EH54 6RA",
    "sg:province":"West Lothian",
    "sg:tags":[
        "practitioners"
    ],
    "wof:name":"Jay & Co.",
    "wof:placetype":"venue"
},
  "geometry": {"coordinates":[-3.5352339745,55.8958015442],"type":"Point"}
}