{
  "type": "Feature",
  "properties": {
    "addr:full":"161 Thornberry Road Isleworth Greater London TW7 4QE",
    "addr:housenumber":"161",
    "addr:postcode":"tw7 4qe",
    "addr:street":"Thornberry Road",
    "iso:country":"GB",
    "sg:address":"161 Thornberry Road",
    "sg:city":"Isleworth",
    "sg:classifiers":[
        {
            "category":"Retail",
            "subcategory":"Laundry & Dry Cleaning",
            "type":"Services"
        }
    ],
    "sg:phone":"+44 20 8560 2610",
    "sg:postcode":"TW7 4QE",
    "sg:province":"Greater London",
    "sg:tags":[
        "alteration"
    ],
    "wof:name":"Osterley Dry Cleaners",
    "wof:placetype":"venue"
},
  "geometry": {"coordinates":[-0.3479009867,51.4833221436],"type":"Point"}
}