{
  "type": "Feature",
  "properties": {
    "addr:full":"Harold Place Hastings East Sussex TN34 1JA",
    "addr:postcode":"tn34 1ja",
    "addr:street":"Harold Place Hastings",
    "iso:country":"GB",
    "sg:address":"Harold Place",
    "sg:city":"Hastings",
    "sg:classifiers":[
        {
            "category":"Bars & Pubs",
            "type":"Food & Drink"
        }
    ],
    "sg:postcode":"TN34 1JA",
    "sg:province":"East Sussex",
    "sg:tags":[
        "pubs",
        "inn"
    ],
    "wof:name":"Papa Joe's",
    "wof:placetype":"venue"
},
  "geometry": {"coordinates":[0.5802099705,50.8551292419],"type":"Point"}
}