{
  "type": "Feature",
  "properties": {
    "addr:full":"Plymouth Garden Centre, Fort Austin Avenue Plymouth Devon PL6 5NU",
    "addr:postcode":"pl6 5nu",
    "addr:street":"Fort Austin Avenue",
    "iso:country":"GB",
    "sg:address":"Plymouth Garden Centre, Fort Austin Avenue",
    "sg:city":"Plymouth",
    "sg:classifiers":[
        {
            "category":"Education",
            "subcategory":"Music School",
            "type":"Public Place"
        }
    ],
    "sg:phone":"+44 1752 786015",
    "sg:postcode":"PL6 5NU",
    "sg:province":"Devon",
    "sg:tags":[
        "conservatory"
    ],
    "wof:name":"Southern Conservatories",
    "wof:placetype":"venue"
},
  "geometry": {"coordinates":[-4.1186299324,50.4051704407],"type":"Point"}
}