{
  "type": "Feature",
  "properties": {
    "iso:country":"GB",
    "sg:address":"Reeth Road",
    "sg:city":"Richmond",
    "sg:classifiers":[
        {
            "category":"Social Services",
            "subcategory":"Retirement Home",
            "type":"Services"
        },
        {
            "category":"Government",
            "subcategory":"Office",
            "type":"Public Place"
        }
    ],
    "sg:phone":"+44 1748 823135",
    "sg:postcode":"DL10 4EF",
    "sg:province":"North Yorkshire",
    "sg:tags":[
        "residential",
        "local",
        "care"
    ],
    "wof:name":"Richmond House Residential Care",
    "wof:placetype":"venue"
},
  "geometry": {"coordinates":[-1.746078968,54.4050598145],"type":"Point"}
}