{
  "type": "Feature",
  "properties": {
    "addr:full":"Park Terrace East Horsham West Sussex RH13 5DJ",
    "addr:postcode":"rh13 5dj",
    "addr:street":"Park Terrace East",
    "iso:country":"GB",
    "sg:address":"Park Terrace East",
    "sg:city":"Horsham",
    "sg:classifiers":[
        {
            "category":"Health Services",
            "subcategory":"Health Practitioner",
            "type":"Services"
        }
    ],
    "sg:postcode":"RH13 5DJ",
    "sg:province":"West Sussex",
    "sg:tags":[
        "hypnotherapists"
    ],
    "wof:name":"Hypnotherapy Centre",
    "wof:placetype":"venue"
},
  "geometry": {"coordinates":[-0.322301,51.062038],"type":"Point"}
}