{
  "type": "Feature",
  "properties": {
    "addr:full":"27 Hanover Street Bolton Lancashire BL1 4TG",
    "addr:housenumber":"27",
    "addr:postcode":"bl1 4tg",
    "addr:street":"Hanover Street",
    "iso:country":"GB",
    "sg:address":"27 Hanover Street",
    "sg:city":"Bolton",
    "sg:classifiers":[
        {
            "category":"Manufacturing",
            "subcategory":"Rubber & Plastics",
            "type":"Manufacturing & Wholesale Goods"
        },
        {
            "category":"Manufacturing",
            "subcategory":"Building Materials",
            "type":"Manufacturing & Wholesale Goods"
        }
    ],
    "sg:phone":"+44 1204 534915",
    "sg:postcode":"BL1 4TG",
    "sg:province":"Lancashire",
    "sg:tags":[
        "supplier",
        "extrusion",
        "stockist"
    ],
    "wof:name":"Plastic Developments Ltd.",
    "wof:placetype":"venue"
},
  "geometry": {"coordinates":[-2.435725,53.577473],"type":"Point"}
}