{
  "type": "Feature",
  "properties": {
    "addr:full":"P O Box 5222 Leicester Leicestershire LE4 8ZE",
    "addr:housenumber":"p o;5222",
    "addr:postcode":"le4 8ze",
    "iso:country":"GB",
    "sg:address":"P O Box 5222",
    "sg:city":"Leicester",
    "sg:phone":"+44 116 260 7744",
    "sg:postcode":"LE4 8ZE",
    "sg:province":"Leicestershire",
    "wof:name":"Fmb U K Ltd.",
    "wof:placetype":"venue"
},
  "geometry": {"coordinates":[-1.0882890224,52.6750297546],"type":"Point"}
}