{
  "type": "Feature",
  "properties": {
    "iso:country":"GB",
    "sg:address":"41-43 London Road, Cowplain",
    "sg:city":"Portsmouth",
    "sg:classifiers":[
        {
            "category":"Banks & Credit Unions",
            "subcategory":"Bank",
            "type":"Services"
        }
    ],
    "sg:phone":"+44 23 9230 5858",
    "sg:postcode":"PO8 8DF",
    "sg:province":"Hampshire",
    "sg:tags":[
        "financial",
        "institution"
    ],
    "wof:name":"Barclays Bank Plc",
    "wof:placetype":"venue"
},
  "geometry": {"coordinates":[-1.019214,50.8936],"type":"Point"}
}