{
  "type": "Feature",
  "properties": {
    "iso:country":"GB",
    "sg:address":"Unit 14, Perivale New Business Centre",
    "sg:city":"Greenford",
    "sg:classifiers":[
        {
            "category":"Shopping",
            "type":"Retail Goods"
        }
    ],
    "sg:phone":"+44 20 8810 4595",
    "sg:postcode":"UB6 7LF",
    "sg:province":"Greater London",
    "sg:tags":[
        "part",
        "accessory"
    ],
    "wof:name":"Old Car World",
    "wof:placetype":"venue"
},
  "geometry": {"coordinates":[-0.3199540079,51.5387840271],"type":"Point"}
}