{
  "type": "Feature",
  "properties": {
    "addr:full":"Safeways Stores, Newlandsfield Road Glasgow Glasgow City G43 2XU",
    "addr:postcode":"g43 2xu",
    "addr:street":"Newlandsfield Road",
    "iso:country":"GB",
    "sg:address":"Safeways Stores, Newlandsfield Road",
    "sg:city":"Glasgow",
    "sg:classifiers":[
        {
            "category":"Government",
            "subcategory":"Post Office",
            "type":"Public Place"
        }
    ],
    "sg:phone":"+44 141 632 0602",
    "sg:postcode":"G43 2XU",
    "sg:province":"Glasgow City",
    "wof:name":"Newlands Franchise Post Office",
    "wof:placetype":"venue"
},
  "geometry": {"coordinates":[-4.28774,55.823269],"type":"Point"}
}