{
  "type": "Feature",
  "properties": {
    "iso:country":"GB",
    "sg:address":"Unit B2, Brookside Business Pk, Green Gate, Middleton",
    "sg:city":"Manchester",
    "sg:classifiers":[
        {
            "category":"Utilities",
            "subcategory":"Telephone",
            "type":"Services"
        }
    ],
    "sg:phone":"+44 161 655 1100",
    "sg:postcode":"M24 1GS",
    "sg:province":"Greater Manchester",
    "sg:tags":[
        "telecommunication"
    ],
    "wof:name":"Securicor Telecoms Ltd",
    "wof:placetype":"venue"
},
  "geometry": {"coordinates":[-2.17247,53.53896],"type":"Point"}
}