{
  "type": "Feature",
  "properties": {
    "addr:full":"41 Artillery Lane London Greater London E1 7LP",
    "addr:housenumber":"41",
    "addr:postcode":"e1 7lp",
    "addr:street":"Artillery Lane",
    "iso:country":"GB",
    "sg:address":"41 Artillery Lane",
    "sg:city":"London",
    "sg:classifiers":[
        {
            "category":"Professional",
            "subcategory":"Accounting & Tax Preparation",
            "type":"Services"
        }
    ],
    "sg:postcode":"E1 7LP",
    "sg:province":"Greater London",
    "sg:tags":[
        "accountant"
    ],
    "wof:name":"McIntyre-Stuart",
    "wof:placetype":"venue"
},
  "geometry": {"coordinates":[-0.077177003,51.5184288025],"type":"Point"}
}