{
  "type": "Feature",
  "properties": {
    "addr:full":"42 High St Rowley Regis West Midlands B65 0DR",
    "addr:housenumber":"42",
    "addr:postcode":"b65 0dr",
    "addr:street":"High St",
    "iso:country":"GB",
    "sg:address":"42 High St",
    "sg:city":"Rowley Regis",
    "sg:classifiers":[
        {
            "category":"Shopping",
            "subcategory":"Pharmacy",
            "type":"Retail Goods"
        }
    ],
    "sg:postcode":"B65 0DR",
    "sg:province":"West Midlands",
    "sg:tags":[
        "store",
        "drug"
    ],
    "wof:name":"Patel,D S,",
    "wof:placetype":"venue"
},
  "geometry": {"coordinates":[-2.0430109501,52.4755897522],"type":"Point"}
}