{
  "type": "Feature",
  "properties": {
    "addr:full":"14 Daventry Rd Coventry Warwickshire CV3 5DP",
    "addr:housenumber":"14",
    "addr:postcode":"cv3 5dp",
    "addr:street":"Daventry Rd",
    "iso:country":"GB",
    "sg:address":"14 Daventry Rd",
    "sg:city":"Coventry",
    "sg:classifiers":[
        {
            "category":"Building & Trades",
            "subcategory":"Construction",
            "type":"Services"
        }
    ],
    "sg:phone":"+44 24 7677 0082",
    "sg:postcode":"CV3 5DP",
    "sg:province":"Warwickshire",
    "sg:tags":[
        "builder"
    ],
    "wof:name":"A H Stringer & Son",
    "wof:placetype":"venue"
},
  "geometry": {"coordinates":[-1.5147119761,52.3914642334],"type":"Point"}
}