{
  "type": "Feature",
  "properties": {
    "iso:country":"GB",
    "sg:address":"Carbeth Farm House, Killearn",
    "sg:city":"Glasgow",
    "sg:classifiers":[
        {
            "category":"Banks & Credit Unions",
            "subcategory":"Investment Brokerage",
            "type":"Services"
        }
    ],
    "sg:phone":"+44 1360 550123",
    "sg:postcode":"G63 9QB",
    "sg:province":"Argyll and Bute",
    "wof:name":"McNeil Investments",
    "wof:placetype":"venue"
},
  "geometry": {"coordinates":[-4.376809,56.04538],"type":"Point"}
}