{
  "type": "Feature",
  "properties": {
    "iso:country":"GB",
    "sg:address":"10 Argent Ct, Southfield Business Pk",
    "sg:city":"Basildon",
    "sg:classifiers":[
        {
            "category":"Professional",
            "subcategory":"Art Services",
            "type":"Services"
        }
    ],
    "sg:postcode":"SS15 6TH",
    "sg:province":"Essex",
    "sg:tags":[
        "consultant",
        "design"
    ],
    "wof:name":"Hawston Management Ltd",
    "wof:placetype":"venue"
},
  "geometry": {"coordinates":[0.4072299898,51.5781097412],"type":"Point"}
}