{
  "type": "Feature",
  "properties": {
    "addr:full":"Site Office, Moorfield Road Redruth Cornwall TR15 3QB",
    "addr:postcode":"tr15 3qb",
    "addr:street":"Moorfield Road",
    "iso:country":"GB",
    "sg:address":"Site Office, Moorfield Road",
    "sg:city":"Redruth",
    "sg:classifiers":[
        {
            "category":"Building & Trades",
            "subcategory":"Construction",
            "type":"Services"
        }
    ],
    "sg:postcode":"TR15 3QB",
    "sg:province":"Cornwall",
    "sg:tags":[
        "contractor"
    ],
    "wof:name":"Harrison Developments Ltd.",
    "wof:placetype":"venue"
},
  "geometry": {"coordinates":[-5.229434,50.23251],"type":"Point"}
}