{
  "type": "Feature",
  "properties": {
    "addr:full":"Watchetts Recreation Ground, Park Road Camberley Berkshire GU15 2SR",
    "addr:postcode":"gu15 2sr",
    "addr:street":"Park Road",
    "iso:country":"GB",
    "sg:address":"Watchetts Recreation Ground, Park Road",
    "sg:city":"Camberley",
    "sg:classifiers":[
        {
            "category":"Arena",
            "subcategory":"Sports Club",
            "type":"Entertainment"
        }
    ],
    "sg:phone":"+44 1276 25395",
    "sg:postcode":"GU15 2SR",
    "sg:province":"Berkshire",
    "wof:name":"Camberley Rugby Football Club",
    "wof:placetype":"venue"
},
  "geometry": {"coordinates":[-0.73423,51.336216],"type":"Point"}
}