{
  "type": "Feature",
  "properties": {
    "addr:full":"7 King Street Richmond North Yorkshire DL10 4HP",
    "addr:housenumber":"7",
    "addr:postcode":"dl10 4hp",
    "addr:street":"King Street",
    "iso:country":"GB",
    "sg:address":"7 King Street",
    "sg:city":"Richmond",
    "sg:classifiers":[
        {
            "category":"Professional",
            "subcategory":"Detective & Security Services",
            "type":"Services"
        }
    ],
    "sg:postcode":"DL10 4HP",
    "sg:province":"North Yorkshire",
    "wof:name":"Dacal Security Services Ltd.",
    "wof:placetype":"venue"
},
  "geometry": {"coordinates":[-1.737596,54.403778],"type":"Point"}
}