{
  "type": "Feature",
  "properties": {
    "iso:country":"GB",
    "sg:address":"Ladygrove Road, Two Dales",
    "sg:city":"Matlock",
    "sg:classifiers":[
        {
            "category":"Building & Trades",
            "subcategory":"Landscaping Services",
            "type":"Services"
        }
    ],
    "sg:postcode":"DE4 2FG",
    "sg:province":"Derbyshire",
    "sg:tags":[
        "preservation",
        "timber"
    ],
    "wof:name":"R Knowles (Home Maintenance) Ltd.",
    "wof:placetype":"venue"
},
  "geometry": {"coordinates":[-1.578275,53.162971],"type":"Point"}
}