{
  "type": "Feature",
  "properties": {
    "iso:country":"GB",
    "sg:address":"138 London Road",
    "sg:city":"Brighton",
    "sg:classifiers":[
        {
            "category":"Travel",
            "subcategory":"Travel Agent",
            "type":"Entertainment"
        }
    ],
    "sg:phone":"+44 1273 367800",
    "sg:postcode":"BN1 4JH",
    "sg:province":"East Sussex",
    "wof:name":"Thomas Cook Group",
    "wof:placetype":"venue"
},
  "geometry": {"coordinates":[-0.1356990039,50.8298912048],"type":"Point"}
}