{
  "type": "Feature",
  "properties": {
    "iso:country":"GB",
    "sg:address":"83 Ashcroft Drive, Old Whittington",
    "sg:city":"Chesterfield",
    "sg:classifiers":[
        {
            "category":"Building & Trades",
            "subcategory":"Construction",
            "type":"Services"
        }
    ],
    "sg:phone":"+44 1246 450897",
    "sg:postcode":"S41 9PE",
    "sg:province":"Derbyshire",
    "sg:tags":[
        "decorator",
        "painter"
    ],
    "wof:name":"Harrison & Fletcher",
    "wof:placetype":"venue"
},
  "geometry": {"coordinates":[-1.417652,53.27084],"type":"Point"}
}