{
  "type": "Feature",
  "properties": {
    "addr:full":"Rostrevor, Towpath Shepperton Surrey TW17 9LL",
    "addr:postcode":"tw17 9ll",
    "addr:street":"Shepperton",
    "iso:country":"GB",
    "sg:address":"Rostrevor, Towpath",
    "sg:city":"Shepperton",
    "sg:classifiers":[
        {
            "category":"Professional",
            "subcategory":"Engineering",
            "type":"Services"
        }
    ],
    "sg:phone":"+44 1932 231969",
    "sg:postcode":"TW17 9LL",
    "sg:province":"Surrey",
    "sg:tags":[
        "contractor",
        "electrical",
        "engineer"
    ],
    "wof:name":"Henry Lay Electrical Contractors",
    "wof:placetype":"venue"
},
  "geometry": {"coordinates":[-0.448547,51.394321],"type":"Point"}
}