{
  "type": "Feature",
  "properties": {
    "iso:country":"GB",
    "sg:address":"Unit 6 Brooks Lane Business Centre, Brook Lane North",
    "sg:city":"Brentford",
    "sg:classifiers":[
        {
            "category":"Professional",
            "subcategory":"Art Services",
            "type":"Services"
        }
    ],
    "sg:phone":"+44 20 8569 8932",
    "sg:postcode":"TW8 0PP",
    "sg:province":"Greater London",
    "sg:tags":[
        "photographer"
    ],
    "wof:name":"Simon Murrell Photogaphy",
    "wof:placetype":"venue"
},
  "geometry": {"coordinates":[-0.306189,51.490311],"type":"Point"}
}