{
  "type": "Feature",
  "properties": {
    "addr:full":"2 Baldock Close, Thelwall Warrington Cheshire WA4 2HG",
    "addr:housenumber":"2",
    "addr:postcode":"wa4 2hg",
    "addr:street":"Baldock Close",
    "iso:country":"GB",
    "sg:address":"2 Baldock Close, Thelwall",
    "sg:city":"Warrington",
    "sg:classifiers":[
        {
            "category":"Autos & Motor Vehicles",
            "subcategory":"Motorcycle Sales",
            "type":"Retail Goods"
        }
    ],
    "sg:postcode":"WA4 2HG",
    "sg:province":"Cheshire",
    "wof:name":"Les Hill Motor Cycles",
    "wof:placetype":"venue"
},
  "geometry": {"coordinates":[-2.538733,53.38158],"type":"Point"}
}