{
  "type": "Feature",
  "properties": {
    "iso:country":"GB",
    "sg:address":"452 Holdenhurst Rd",
    "sg:city":"Bournemouth",
    "sg:classifiers":[
        {
            "category":"Manufacturing",
            "subcategory":"Tools & Machinery",
            "type":"Manufacturing & Wholesale Goods"
        }
    ],
    "sg:phone":"+44 1202 302666",
    "sg:postcode":"BH8 9AF",
    "sg:province":"Dorset",
    "sg:tags":[
        "merchant"
    ],
    "wof:name":"Ccm Cash Registers",
    "wof:placetype":"venue"
},
  "geometry": {"coordinates":[-1.8470820189,50.7343254089],"type":"Point"}
}