{
  "type": "Feature",
  "properties": {
    "addr:full":"4 Thomas Street, Abertri Dwr Caerphilly Caerphilly CF83 4AZ",
    "addr:housenumber":"4",
    "addr:postcode":"cf83 4az",
    "addr:street":"Thomas Street",
    "iso:country":"GB",
    "sg:address":"4 Thomas Street, Abertri Dwr",
    "sg:city":"Caerphilly",
    "sg:classifiers":[
        {
            "category":"Wholesale",
            "subcategory":"Fruits & Vegetables",
            "type":"Manufacturing & Wholesale Goods"
        }
    ],
    "sg:postcode":"CF83 4AZ",
    "sg:province":"Caerphilly",
    "wof:name":"Roy J Flook",
    "wof:placetype":"venue"
},
  "geometry": {"coordinates":[-3.270902,51.59623],"type":"Point"}
}