{
  "type": "Feature",
  "properties": {
    "addr:full":"Fox Mill Wellington Devon TA21 0AB",
    "addr:postcode":"ta21 0ab",
    "iso:country":"GB",
    "sg:address":"Fox Mill",
    "sg:city":"Wellington",
    "sg:classifiers":[
        {
            "category":"Retail",
            "subcategory":"Auto Repair",
            "type":"Services"
        }
    ],
    "sg:phone":"+44 1823 664178",
    "sg:postcode":"TA21 0AB",
    "sg:province":"Devon",
    "sg:tags":[
        "body",
        "car"
    ],
    "wof:name":"South Street Motors Ltd Accident Repair",
    "wof:placetype":"venue"
},
  "geometry": {"coordinates":[-3.250004,50.978184],"type":"Point"}
}