{
  "type": "Feature",
  "properties": {
    "iso:country":"GB",
    "sg:address":"18 Chestnut Close",
    "sg:city":"Torpoint",
    "sg:classifiers":[
        {
            "category":"Building & Trades",
            "subcategory":"Construction",
            "type":"Services"
        }
    ],
    "sg:phone":"+44 1752 816557",
    "sg:postcode":"PL11 2NB",
    "sg:province":"Cornwall",
    "sg:tags":[
        "roofing",
        "contracting"
    ],
    "wof:name":"George W Brown",
    "wof:placetype":"venue"
},
  "geometry": {"coordinates":[-4.2099919319,50.3741531372],"type":"Point"}
}