{
  "type": "Feature",
  "properties": {
    "addr:full":"12 Princes St Stafford Staffordshire ST16 2BN",
    "addr:housenumber":"12",
    "addr:postcode":"st16 2bn",
    "addr:street":"Princes St",
    "iso:country":"GB",
    "sg:address":"12 Princes St",
    "sg:city":"Stafford",
    "sg:classifiers":[
        {
            "category":"Shopping",
            "subcategory":"Clothing, Apparel, & Fashions",
            "type":"Retail Goods"
        }
    ],
    "sg:phone":"+44 1785 256709",
    "sg:postcode":"ST16 2BN",
    "sg:province":"Staffordshire",
    "sg:tags":[
        "shop"
    ],
    "wof:name":"Thrifty",
    "wof:placetype":"venue"
},
  "geometry": {"coordinates":[-2.1194078922,52.8080635071],"type":"Point"}
}