{
  "type": "Feature",
  "properties": {
    "iso:country":"GB",
    "sg:address":"B21 The Arcadian, Hurst Street",
    "sg:city":"Birmingham",
    "sg:classifiers":[
        {
            "category":"Organizations",
            "subcategory":"Membership Organization",
            "type":"Services"
        }
    ],
    "sg:phone":"+44 121 685 8511",
    "sg:postcode":"B5 4TD",
    "sg:province":"West Midlands",
    "sg:tags":[
        "club"
    ],
    "wof:name":"Birmingham Chinese Youth Centre",
    "wof:placetype":"venue"
},
  "geometry": {"coordinates":[-1.89674,52.473999],"type":"Point"}
}