{
  "type": "Feature",
  "properties": {
    "addr:full":"79-81 Mottingham Road London Greater London SE9 4TJ",
    "addr:housenumber":"79-81",
    "addr:postcode":"se9 4tj",
    "addr:street":"Mottingham Road",
    "iso:country":"GB",
    "sg:address":"79-81 Mottingham Road",
    "sg:city":"London",
    "sg:classifiers":[
        {
            "category":"Professional",
            "type":"Services"
        }
    ],
    "sg:phone":"+44 20 8859 4735",
    "sg:postcode":"SE9 4TJ",
    "sg:province":"Greater London",
    "sg:tags":[
        "interior",
        "furnishers",
        "designer"
    ],
    "wof:name":"The Decor Centre",
    "wof:placetype":"venue"
},
  "geometry": {"coordinates":[0.0455100015,51.436050415],"type":"Point"}
}