{
  "type": "Feature",
  "properties": {
    "iso:country":"GB",
    "sg:address":"Mitchell House, 139 Richardshaw Lane, Stanningley",
    "sg:city":"Pudsey",
    "sg:classifiers":[
        {
            "category":"Social Services",
            "subcategory":"Job Training",
            "type":"Services"
        },
        {
            "category":"Education",
            "subcategory":"Special Training",
            "type":"Public Place"
        }
    ],
    "sg:phone":"+44 113 255 2417",
    "sg:postcode":"LS28 6AA",
    "sg:province":"West Yorkshire",
    "sg:tags":[
        "product",
        "centre"
    ],
    "wof:name":"Leeds Training Trust",
    "wof:placetype":"venue"
},
  "geometry": {"coordinates":[-1.6656750441,53.8024864197],"type":"Point"}
}