{
  "type": "Feature",
  "properties": {
    "addr:full":"23-24 Market Street Blyth Northumberland NE24 1BQ",
    "addr:housenumber":"23-24",
    "addr:postcode":"ne24 1bq",
    "addr:street":"Market Street;Northumberland",
    "iso:country":"GB",
    "sg:address":"23-24 Market Street",
    "sg:city":"Blyth",
    "sg:classifiers":[
        {
            "category":"Community Center",
            "subcategory":"Social",
            "type":"Public Place"
        }
    ],
    "sg:phone":"+44 1670 351275",
    "sg:postcode":"NE24 1BQ",
    "sg:province":"Northumberland",
    "sg:tags":[
        "frozen",
        "food",
        "freezer",
        "centre"
    ],
    "wof:name":"Iceland",
    "wof:placetype":"venue"
},
  "geometry": {"coordinates":[-1.510369,55.127312],"type":"Point"}
}