{
  "type": "Feature",
  "properties": {
    "addr:full":"61 Grafton Rd Kentish Town Greater London NW5 3EN",
    "addr:housenumber":"61",
    "addr:postcode":"nw5 3en",
    "addr:street":"Grafton Rd",
    "iso:country":"GB",
    "sg:address":"61 Grafton Rd",
    "sg:city":"Kentish Town",
    "sg:classifiers":[
        {
            "category":"Professional",
            "subcategory":"Printing & Photocopies",
            "type":"Services"
        }
    ],
    "sg:phone":"+44 20 7485 7447",
    "sg:postcode":"NW5 3EN",
    "sg:province":"Greater London",
    "sg:tags":[
        "printer"
    ],
    "wof:name":"Bowman Lithographic",
    "wof:placetype":"venue"
},
  "geometry": {"coordinates":[-0.1503449976,51.5514221191],"type":"Point"}
}