{
  "type": "Feature",
  "properties": {
    "addr:full":"8 Elliott Road Plymouth Devon PL4 9NH",
    "addr:housenumber":"8",
    "addr:postcode":"pl4 9nh",
    "addr:street":"Elliott Road",
    "iso:country":"GB",
    "sg:address":"8 Elliott Road",
    "sg:city":"Plymouth",
    "sg:classifiers":[
        {
            "category":"Cafe",
            "type":"Food & Drink"
        }
    ],
    "sg:phone":"+44 1752 662044",
    "sg:postcode":"PL4 9NH",
    "sg:province":"Devon",
    "sg:tags":[
        "tea",
        "room"
    ],
    "wof:name":"Curnows Cafe",
    "wof:placetype":"venue"
},
  "geometry": {"coordinates":[-4.1188278198,50.370464325],"type":"Point"}
}