{
  "type": "Feature",
  "properties": {
    "iso:country":"GB",
    "sg:address":"6 Beeches Wood",
    "sg:city":"Tadworth",
    "sg:classifiers":[
        {
            "category":"Professional",
            "subcategory":"Management & Consulting",
            "type":"Services"
        }
    ],
    "sg:postcode":"KT20 6PR",
    "sg:province":"Surrey",
    "sg:tags":[
        "consultant",
        "business"
    ],
    "wof:name":"Blue Anchor Enterprises Ltd.",
    "wof:placetype":"venue"
},
  "geometry": {"coordinates":[-0.205087,51.291023],"type":"Point"}
}