{
  "type": "Feature",
  "properties": {
    "addr:full":"49b Larkfield Rd Nottingham Derbyshire NG16 1ET",
    "addr:housenumber":"49b",
    "addr:postcode":"ng16 1et",
    "addr:street":"Larkfield Rd",
    "iso:country":"GB",
    "sg:address":"49b Larkfield Rd",
    "sg:city":"Nottingham",
    "sg:classifiers":[
        {
            "category":"Food & Beverages",
            "subcategory":"Meat & Fish",
            "type":"Retail Goods"
        }
    ],
    "sg:postcode":"NG16 1ET",
    "sg:province":"Derbyshire",
    "sg:tags":[
        "butcher"
    ],
    "wof:name":"Grant,Bob,",
    "wof:placetype":"venue"
},
  "geometry": {"coordinates":[-1.244719,52.996986],"type":"Point"}
}