{
  "type": "Feature",
  "properties": {
    "iso:country":"GB",
    "sg:address":"The Hollygate Albert Street",
    "sg:city":"Stockport",
    "sg:classifiers":[
        {
            "category":"Professional",
            "subcategory":"Advertising",
            "type":"Services"
        }
    ],
    "sg:postcode":"SK3 0BA",
    "sg:province":"Cheshire",
    "sg:tags":[
        "telemarketing"
    ],
    "wof:name":"Bryony Longdon Associates",
    "wof:placetype":"venue"
},
  "geometry": {"coordinates":[-2.1615159512,53.4084091187],"type":"Point"}
}