{
  "type": "Feature",
  "properties": {
    "iso:country":"GB",
    "sg:address":"12 Tewin Close",
    "sg:city":"St Albans",
    "sg:classifiers":[
        {
            "category":"Building & Trades",
            "subcategory":"Construction",
            "type":"Services"
        }
    ],
    "sg:phone":"+44 1727 844112",
    "sg:postcode":"AL4 9XL",
    "sg:province":"Hertfordshire",
    "sg:tags":[
        "roofing",
        "contracting"
    ],
    "wof:name":"Acorn Roofing & Renovations",
    "wof:placetype":"venue"
},
  "geometry": {"coordinates":[-0.3029179871,51.7693328857],"type":"Point"}
}