{
  "type": "Feature",
  "properties": {
    "addr:full":"Cambrian House, 509-511 Cranbrook Road, Gants Hill Ilford Essex IG2 6EY",
    "addr:housenumber":"509-511",
    "addr:postcode":"ig2 6ey",
    "addr:street":"Cranbrook Road",
    "iso:country":"GB",
    "sg:address":"Cambrian House, 509-511 Cranbrook Road, Gants Hill",
    "sg:city":"Ilford",
    "sg:classifiers":[
        {
            "category":"Shopping",
            "subcategory":"Beauty & Cosmetics",
            "type":"Retail Goods"
        }
    ],
    "sg:phone":"+44 20 8554 7000",
    "sg:postcode":"IG2 6EY",
    "sg:province":"Essex",
    "sg:tags":[
        "product"
    ],
    "wof:name":"E T Browne (U K) Ltd.",
    "wof:placetype":"venue"
},
  "geometry": {"coordinates":[0.0661050007,51.5746879578],"type":"Point"}
}