{
  "type": "Feature",
  "properties": {
    "iso:country":"GB",
    "sg:address":"295 Wood End Road",
    "sg:city":"Wolverhampton",
    "sg:classifiers":[
        {
            "category":"Shopping",
            "subcategory":"Pharmacy",
            "type":"Retail Goods"
        }
    ],
    "sg:phone":"+44 1902 732059",
    "sg:postcode":"WV11 1YQ",
    "sg:province":"Staffordshire",
    "sg:tags":[
        "pharmacist",
        "chemist"
    ],
    "wof:name":"J  Docter (Wednesfield) Ltd.",
    "wof:placetype":"venue"
},
  "geometry": {"coordinates":[-2.083113,52.611137],"type":"Point"}
}