{
  "type": "Feature",
  "properties": {
    "addr:full":"Links Road Bo'ness Falkirk EH51 9PW",
    "addr:postcode":"eh51 9pw",
    "addr:street":"Links Road",
    "iso:country":"GB",
    "sg:address":"Links Road",
    "sg:city":"Bo'ness",
    "sg:classifiers":[
        {
            "category":"Professional",
            "subcategory":"Engineering",
            "type":"Services"
        }
    ],
    "sg:phone":"+44 1506 822721",
    "sg:postcode":"EH51 9PW",
    "sg:province":"Falkirk",
    "wof:name":"Ballantine Engineering Ltd.",
    "wof:placetype":"venue"
},
  "geometry": {"coordinates":[-3.5974800587,56.0162010193],"type":"Point"}
}