{
  "type": "Feature",
  "properties": {
    "iso:country":"GB",
    "sg:address":"The Square",
    "sg:city":"Newquay",
    "sg:classifiers":[
        {
            "category":"Organizations",
            "subcategory":"Membership Organization",
            "type":"Services"
        }
    ],
    "sg:phone":"+44 1637 877473",
    "sg:postcode":"TR7 3HB",
    "sg:province":"Cornwall",
    "sg:tags":[
        "club",
        "social"
    ],
    "wof:name":"St Columb Minor Institute",
    "wof:placetype":"venue"
},
  "geometry": {"coordinates":[-5.0718588829,50.4120864868],"type":"Point"}
}