{
  "type": "Feature",
  "properties": {
    "addr:full":"30a College Grn Bristol City of Bristol BS1 5TB",
    "addr:housenumber":"30a",
    "addr:postcode":"bs1 5tb",
    "addr:street":"College Grn",
    "iso:country":"GB",
    "sg:address":"30a College Grn",
    "sg:city":"Bristol",
    "sg:classifiers":[
        {
            "category":"Professional",
            "subcategory":"Lawyer & Legal Services",
            "type":"Services"
        }
    ],
    "sg:postcode":"BS1 5TB",
    "sg:province":"City of Bristol",
    "sg:tags":[
        "solicitor"
    ],
    "wof:name":"P McKnight",
    "wof:placetype":"venue"
},
  "geometry": {"coordinates":[-2.6023240089,51.4511680603],"type":"Point"}
}