{
  "type": "Feature",
  "properties": {
    "iso:country":"GB",
    "sg:address":"Holly Bank, Windemere Road, Lindale",
    "sg:city":"Grange-over-sands",
    "sg:classifiers":[
        {
            "category":"Shopping",
            "subcategory":"Optician",
            "type":"Retail Goods"
        },
        {
            "category":"Professional",
            "subcategory":"Business Services",
            "type":"Services"
        }
    ],
    "sg:postcode":"LA11 6DL",
    "sg:province":"Cumbria",
    "sg:tags":[
        "import",
        "export",
        "agent"
    ],
    "wof:name":"Lakeland Microscopes",
    "wof:placetype":"venue"
},
  "geometry": {"coordinates":[-2.8944489956,54.2165718079],"type":"Point"}
}