{
  "type": "Feature",
  "properties": {
    "addr:full":", Duddon Tarporley Cheshire CW6 0EL",
    "addr:postcode":"cw6 0el",
    "addr:street":"Tarporley",
    "iso:country":"GB",
    "sg:address":", Duddon",
    "sg:city":"Tarporley",
    "sg:classifiers":[
        {
            "category":"Education",
            "subcategory":"School",
            "type":"Public Place"
        }
    ],
    "sg:phone":"+44 1829 781366",
    "sg:postcode":"CW6 0EL",
    "sg:province":"Cheshire",
    "sg:tags":[
        "local",
        "authority"
    ],
    "wof:name":"Duddon St. Peters C of E Primary School",
    "wof:placetype":"venue"
},
  "geometry": {"coordinates":[-2.6687550545,53.1593551636],"type":"Point"}
}