{
  "type": "Feature",
  "properties": {
    "addr:full":"Old Coach House Uttoxeter Derbyshire ST14 7JQ",
    "addr:postcode":"st14 7jq",
    "addr:street":"Old;Uttoxeter",
    "iso:country":"GB",
    "sg:address":"Old Coach House",
    "sg:city":"Uttoxeter",
    "sg:classifiers":[
        {
            "category":"Restaurant",
            "type":"Food & Drink"
        }
    ],
    "sg:phone":"+44 1889 565676",
    "sg:postcode":"ST14 7JQ",
    "sg:province":"Derbyshire",
    "wof:name":"Bel Paese Restaurant",
    "wof:placetype":"venue"
},
  "geometry": {"coordinates":[-1.869644,52.896523],"type":"Point"}
}