{
  "type": "Feature",
  "properties": {
    "iso:country":"GB",
    "sg:address":"Knowl Piece, Wilbury Way",
    "sg:city":"Hitchin",
    "sg:classifiers":[
        {
            "category":"Professional",
            "subcategory":"Engineering",
            "type":"Services"
        }
    ],
    "sg:phone":"+44 1462 442252",
    "sg:postcode":"SG4 0TY",
    "sg:province":"Hertfordshire",
    "sg:tags":[
        "precision",
        "engineer"
    ],
    "wof:name":"Highfield Engineering",
    "wof:placetype":"venue"
},
  "geometry": {"coordinates":[-0.2664240003,51.9680213928],"type":"Point"}
}