{
  "type": "Feature",
  "properties": {
    "iso:country":"GB",
    "sg:address":"57 Dee Street",
    "sg:city":"Aberdeen",
    "sg:classifiers":[
        {
            "category":"Organizations",
            "subcategory":"Non-profit Organization",
            "type":"Services"
        }
    ],
    "sg:phone":"+44 1224 592800",
    "sg:postcode":"AB11 6EE",
    "sg:province":"Aberdeen City",
    "sg:tags":[
        "charitable",
        "organisation",
        "voluntary",
        "charity"
    ],
    "wof:name":"Seabank House",
    "wof:placetype":"venue"
},
  "geometry": {"coordinates":[-2.1031639576,57.1429710388],"type":"Point"}
}