{
  "type": "Feature",
  "properties": {
    "addr:full":"Lulsgate Airport, Lulsgate Bristol Somerset BS48 3EP",
    "addr:postcode":"bs48 3ep",
    "addr:street":"Lulsgate;Lulsgate",
    "iso:country":"GB",
    "sg:address":"Lulsgate Airport, Lulsgate",
    "sg:city":"Bristol",
    "sg:classifiers":[
        {
            "category":"Education",
            "subcategory":"Special Training",
            "type":"Public Place"
        }
    ],
    "sg:phone":"+44 1275 474727",
    "sg:postcode":"BS48 3EP",
    "sg:province":"Somerset",
    "sg:tags":[
        "school",
        "flying"
    ],
    "wof:name":"Bristol Helicopters Ltd.",
    "wof:placetype":"venue"
},
  "geometry": {"coordinates":[-2.7060530186,51.3865509033],"type":"Point"}
}