{
  "type": "Feature",
  "properties": {
    "iso:country":"GB",
    "sg:address":"55 Fulton Road",
    "sg:city":"Sheffield",
    "sg:classifiers":[
        {
            "category":"Building & Trades",
            "subcategory":"Construction",
            "type":"Services"
        }
    ],
    "sg:phone":"+44 114 234 6005",
    "sg:postcode":"S6 3JL",
    "sg:province":"South Yorkshire",
    "sg:tags":[
        "decorator",
        "painter"
    ],
    "wof:name":"Grant Painting & Decorating",
    "wof:placetype":"venue"
},
  "geometry": {"coordinates":[-1.4957,53.390285],"type":"Point"}
}