{
  "type": "Feature",
  "properties": {
    "addr:full":"Drummoy Crosshill Rd, Bishopbriggs Glasgow East Dunbartonshire G64 2PZ",
    "addr:postcode":"g64 2pz",
    "addr:street":"Crosshill Rd",
    "iso:country":"GB",
    "sg:address":"Drummoy Crosshill Rd, Bishopbriggs",
    "sg:city":"Glasgow",
    "sg:classifiers":[
        {
            "category":"Shopping",
            "subcategory":"Crafts & Fabrics",
            "type":"Retail Goods"
        }
    ],
    "sg:postcode":"G64 2PZ",
    "sg:province":"East Dunbartonshire",
    "sg:tags":[
        "material",
        "art"
    ],
    "wof:name":"Crosshill Hobby Ceramics",
    "wof:placetype":"venue"
},
  "geometry": {"coordinates":[-4.224479,55.9053],"type":"Point"}
}