{
  "type": "Feature",
  "properties": {
    "addr:full":"295 High Road Benfleet Essex SS7 5LA",
    "addr:housenumber":"295",
    "addr:postcode":"ss7 5la",
    "addr:street":"High Road",
    "iso:country":"GB",
    "sg:address":"295 High Road",
    "sg:city":"Benfleet",
    "sg:classifiers":[
        {
            "category":"Food & Beverages",
            "subcategory":"Bakery",
            "type":"Retail Goods"
        }
    ],
    "sg:phone":"+44 1268 793157",
    "sg:postcode":"SS7 5LA",
    "sg:province":"Essex",
    "sg:tags":[
        "baker"
    ],
    "wof:name":"B B Grout Ltd.",
    "wof:placetype":"venue"
},
  "geometry": {"coordinates":[0.559022,51.553707],"type":"Point"}
}