{
  "type": "Feature",
  "properties": {
    "addr:full":"Unit 1 134 Ninian Park Rd Cardiff Cardiff CF1 8JE",
    "addr:housenumber":"unit 1",
    "addr:postcode":"134;cf1 8je",
    "addr:street":"Ninian Park Rd",
    "iso:country":"GB",
    "sg:address":"Unit 1 134 Ninian Park Rd",
    "sg:city":"Cardiff",
    "sg:classifiers":[
        {
            "category":"Manufacturing",
            "subcategory":"Signs",
            "type":"Manufacturing & Wholesale Goods"
        }
    ],
    "sg:phone":"+44 29 2022 9981",
    "sg:postcode":"CF1 8JE",
    "sg:province":"Cardiff",
    "sg:tags":[
        "nameplate"
    ],
    "wof:name":"Signcrafts (Cardiff)",
    "wof:placetype":"venue"
},
  "geometry": {"coordinates":[-3.1959500313,51.4775733948],"type":"Point"}
}