{
  "type": "Feature",
  "properties": {
    "addr:full":"372 Bilston Road Wolverhampton West Midlands WV2 2NW",
    "addr:housenumber":"372",
    "addr:postcode":"wv2 2nw",
    "addr:street":"Bilston Road",
    "iso:country":"GB",
    "sg:address":"372 Bilston Road",
    "sg:city":"Wolverhampton",
    "sg:classifiers":[
        {
            "category":"Autos & Motor Vehicles",
            "subcategory":"Automobile Sales",
            "type":"Retail Goods"
        }
    ],
    "sg:postcode":"WV2 2NW",
    "sg:province":"West Midlands",
    "sg:tags":[
        "commercial"
    ],
    "wof:name":"Wolverhampton Motor Mart",
    "wof:placetype":"venue"
},
  "geometry": {"coordinates":[-2.097858,52.572887],"type":"Point"}
}