{
  "type": "Feature",
  "properties": {
    "addr:full":"Walcote Road, South Kilworth Lutterworth Leicestershire LE17 6EG",
    "addr:postcode":"le17 6eg",
    "addr:street":"Walcote Road South",
    "iso:country":"GB",
    "sg:address":"Walcote Road, South Kilworth",
    "sg:city":"Lutterworth",
    "sg:classifiers":[
        {
            "category":"Education",
            "subcategory":"School",
            "type":"Public Place"
        }
    ],
    "sg:phone":"+44 1858 575307",
    "sg:postcode":"LE17 6EG",
    "sg:province":"Leicestershire",
    "sg:tags":[
        "local",
        "authority"
    ],
    "wof:name":"South Kilworth C of E Primary School",
    "wof:placetype":"venue"
},
  "geometry": {"coordinates":[-1.1240240335,52.4370193481],"type":"Point"}
}