{
  "type": "Feature",
  "properties": {
    "addr:full":"1 Town Hall Parade, Brixton Hill London Greater London SW2 1RJ",
    "addr:housenumber":"1",
    "addr:postcode":"sw2 1rj",
    "addr:street":"Town Hall Parade",
    "iso:country":"GB",
    "sg:address":"1 Town Hall Parade, Brixton Hill",
    "sg:city":"London",
    "sg:classifiers":[
        {
            "category":"Professional",
            "subcategory":"Management & Consulting",
            "type":"Services"
        }
    ],
    "sg:phone":"+44 20 7274 9913",
    "sg:postcode":"SW2 1RJ",
    "sg:province":"Greater London",
    "sg:tags":[
        "music"
    ],
    "wof:name":"Yoshiha Management",
    "wof:placetype":"venue"
},
  "geometry": {"coordinates":[-0.116414,51.460522],"type":"Point"}
}