{
  "type": "Feature",
  "properties": {
    "iso:country":"GB",
    "sg:address":"Blackburn Road, Whittle Le Woods",
    "sg:city":"Chorley",
    "sg:classifiers":[
        {
            "category":"Education",
            "subcategory":"School",
            "type":"Public Place"
        }
    ],
    "sg:phone":"+44 1257 264480",
    "sg:postcode":"PR6 8LL",
    "sg:province":"Lancashire",
    "sg:tags":[
        "local",
        "authority"
    ],
    "sg:website":"http://www.st-chads-rc.lancsngfl.ac.uk",
    "wof:name":"St Chad'S Catholic Primary School",
    "wof:placetype":"venue"
},
  "geometry": {"coordinates":[-2.616233,53.677696],"type":"Point"}
}