{
  "type": "Feature",
  "properties": {
    "iso:country":"GB",
    "sg:address":"382 Winchester Road",
    "sg:city":"Southampton",
    "sg:classifiers":[
        {
            "category":"Professional",
            "subcategory":"Engineering",
            "type":"Services"
        }
    ],
    "sg:phone":"+44 23 8032 2075",
    "sg:postcode":"SO16 7DH",
    "sg:province":"Hampshire",
    "sg:tags":[
        "consultant",
        "structural"
    ],
    "wof:name":"Barron & Partners Ltd.",
    "wof:placetype":"venue"
},
  "geometry": {"coordinates":[-1.418579,50.934578],"type":"Point"}
}