{
  "type": "Feature",
  "properties": {
    "addr:full":"Suite 1 3rd Floor, Merchants Court Liverpool Merseyside L2 1TS",
    "addr:housenumber":"suite 1 3rd floor",
    "addr:postcode":"l2 1ts",
    "addr:street":"Merchants Court",
    "iso:country":"GB",
    "sg:address":"Suite 1 3rd Floor, Merchants Court",
    "sg:city":"Liverpool",
    "sg:classifiers":[
        {
            "category":"Professional",
            "subcategory":"Employment Agencies",
            "type":"Services"
        }
    ],
    "sg:phone":"+44 151 706 7400",
    "sg:postcode":"L2 1TS",
    "sg:province":"Merseyside",
    "sg:tags":[
        "consultant"
    ],
    "wof:name":"Randstad",
    "wof:placetype":"venue"
},
  "geometry": {"coordinates":[-2.98943,53.404881],"type":"Point"}
}