{
  "type": "Feature",
  "properties": {
    "iso:country":"GB",
    "sg:address":"11 Bacon Lane",
    "sg:city":"Edgware",
    "sg:classifiers":[
        {
            "category":"Health Services",
            "subcategory":"Doctor",
            "type":"Services"
        },
        {
            "category":"Health Services",
            "subcategory":"Clinic",
            "type":"Services"
        }
    ],
    "sg:phone":"+44 20 8952 5073",
    "sg:postcode":"HA8 5AT",
    "sg:province":"Greater London",
    "sg:tags":[
        "nh",
        "practitioners"
    ],
    "wof:name":"The Bacon Lane Surgery",
    "wof:placetype":"venue"
},
  "geometry": {"coordinates":[-0.2757489979,51.6051559448],"type":"Point"}
}