{
  "type": "Feature",
  "properties": {
    "addr:full":"90 St Helens Road Leigh Lancashire WN7 4HW",
    "addr:housenumber":"90",
    "addr:postcode":"wn7 4hw",
    "addr:street":"St Helens Road Leigh",
    "iso:country":"GB",
    "sg:address":"90 St Helens Road",
    "sg:city":"Leigh",
    "sg:classifiers":[
        {
            "category":"Shopping",
            "subcategory":"News",
            "type":"Retail Goods"
        }
    ],
    "sg:phone":"+44 1942 671224",
    "sg:postcode":"WN7 4HW",
    "sg:province":"Lancashire",
    "sg:tags":[
        "newsagent"
    ],
    "wof:name":"Pennington News Agents",
    "wof:placetype":"venue"
},
  "geometry": {"coordinates":[-2.522911,53.490215],"type":"Point"}
}