{
  "type": "Feature",
  "properties": {
    "addr:full":"1 Market Pl Olney Buckinghamshire MK46 4EA",
    "addr:housenumber":"1",
    "addr:postcode":"mk46 4ea",
    "addr:street":"Market Pl",
    "iso:country":"GB",
    "sg:address":"1 Market Pl",
    "sg:city":"Olney",
    "sg:classifiers":[
        {
            "category":"Education",
            "subcategory":"Library",
            "type":"Public Place"
        }
    ],
    "sg:phone":"+44 1234 711506",
    "sg:postcode":"MK46 4EA",
    "sg:province":"Buckinghamshire",
    "sg:tags":[
        "reproduction",
        "furniture"
    ],
    "wof:name":"Olney Galleries Ltd",
    "wof:placetype":"venue"
},
  "geometry": {"coordinates":[-0.7018380165,52.1527137756],"type":"Point"}
}