{
  "type": "Feature",
  "properties": {
    "iso:country":"GB",
    "sg:address":"The Laurels, Burnt Hill, Yattendon",
    "sg:city":"Thatcham",
    "sg:classifiers":[
        {
            "category":"Professional",
            "subcategory":"Accounting & Tax Preparation",
            "type":"Services"
        }
    ],
    "sg:phone":"+44 1635 201930",
    "sg:postcode":"RG18 0XF",
    "sg:province":"Berkshire",
    "sg:tags":[
        "accountant"
    ],
    "wof:name":"Tan McLeod & Co",
    "wof:placetype":"venue"
},
  "geometry": {"coordinates":[-1.20576,51.465862],"type":"Point"}
}