{
  "type": "Feature",
  "properties": {
    "addr:full":"Ripley Road Bradford West Yorkshire BD4 7TP",
    "addr:postcode":"bd4 7tp",
    "addr:street":"Ripley Road",
    "iso:country":"GB",
    "sg:address":"Ripley Road",
    "sg:city":"Bradford",
    "sg:classifiers":[
        {
            "category":"Wholesale",
            "subcategory":"Construction Materials",
            "type":"Manufacturing & Wholesale Goods"
        }
    ],
    "sg:phone":"+44 1274 393161",
    "sg:postcode":"BD4 7TP",
    "sg:province":"West Yorkshire",
    "sg:tags":[
        "merchant",
        "glass"
    ],
    "wof:name":"Solaglas Ltd.",
    "wof:placetype":"venue"
},
  "geometry": {"coordinates":[-1.747106,53.781593],"type":"Point"}
}