{
  "type": "Feature",
  "properties": {
    "iso:country":"GB",
    "sg:address":"101 Central Road",
    "sg:city":"Morden",
    "sg:classifiers":[
        {
            "category":"Retail",
            "subcategory":"Veterinary Services",
            "type":"Services"
        }
    ],
    "sg:phone":"+44 20 8640 2064",
    "sg:postcode":"SM4 5SQ",
    "sg:province":"Surrey",
    "sg:tags":[
        "surgeon",
        "activity"
    ],
    "wof:name":"Heron Veterinary Surgery",
    "wof:placetype":"venue"
},
  "geometry": {"coordinates":[-0.192623,51.395309],"type":"Point"}
}