{
  "type": "Feature",
  "properties": {
    "iso:country":"GB",
    "sg:address":"649 Ashton New Road",
    "sg:city":"Manchester",
    "sg:classifiers":[
        {
            "category":"Taxi",
            "type":"Transportation"
        },
        {
            "category":"Military Area",
            "subcategory":"Air Force Base",
            "type":"Public Place"
        }
    ],
    "sg:phone":"+44 161 223 1111",
    "sg:postcode":"M11 4RX",
    "sg:province":"Greater Manchester",
    "sg:tags":[
        "hire",
        "private"
    ],
    "wof:name":"New Hastings Private Hire",
    "wof:placetype":"venue"
},
  "geometry": {"coordinates":[-2.183484,53.483196],"type":"Point"}
}