{
  "type": "Feature",
  "properties": {
    "addr:full":"75 Yardley Grn Road, Bordesley Grn Birmingham West Midlands B9 5PU",
    "addr:housenumber":"75",
    "addr:postcode":"b9 5pu",
    "addr:street":"Yardley Grn Road;Grn",
    "iso:country":"GB",
    "sg:address":"75 Yardley Grn Road, Bordesley Grn",
    "sg:city":"Birmingham",
    "sg:classifiers":[
        {
            "category":"Health Services",
            "subcategory":"Doctor",
            "type":"Services"
        },
        {
            "category":"Health Services",
            "subcategory":"Clinic",
            "type":"Services"
        }
    ],
    "sg:phone":"+44 121 773 8639",
    "sg:postcode":"B9 5PU",
    "sg:province":"West Midlands",
    "sg:tags":[
        "nh",
        "practitioners"
    ],
    "wof:name":"South Birmingham Primary Care Trust",
    "wof:placetype":"venue"
},
  "geometry": {"coordinates":[-1.8293620348,52.4803504944],"type":"Point"}
}