{
  "type": "Feature",
  "properties": {
    "addr:full":"5 Manor Road Chatham Kent ME4 6AG",
    "addr:housenumber":"5",
    "addr:postcode":"me4 6ag",
    "addr:street":"Manor Road",
    "iso:country":"GB",
    "sg:address":"5 Manor Road",
    "sg:city":"Chatham",
    "sg:classifiers":[
        {
            "category":"Organizations",
            "subcategory":"Membership Organization",
            "type":"Services"
        }
    ],
    "sg:postcode":"ME4 6AG",
    "sg:province":"Kent",
    "sg:tags":[
        "club"
    ],
    "wof:name":"Chatham Masonic Club",
    "wof:placetype":"venue"
},
  "geometry": {"coordinates":[0.5214110017,51.3834533691],"type":"Point"}
}