{
  "type": "Feature",
  "properties": {
    "addr:full":"68-70 Abbey Road Leeds West Yorkshire LS5 3JG",
    "addr:housenumber":"68-70",
    "addr:postcode":"ls5 3jg",
    "addr:street":"Abbey Road",
    "iso:country":"GB",
    "sg:address":"68-70 Abbey Road",
    "sg:city":"Leeds",
    "sg:classifiers":[
        {
            "category":"Restaurant",
            "type":"Food & Drink"
        }
    ],
    "sg:phone":"+44 113 228 3737",
    "sg:postcode":"LS5 3JG",
    "sg:province":"West Yorkshire",
    "sg:tags":[
        "-",
        "spanish"
    ],
    "wof:name":"Amigo'S",
    "wof:placetype":"venue"
},
  "geometry": {"coordinates":[-1.6036280394,53.8194389343],"type":"Point"}
}