{
  "type": "Feature",
  "properties": {
    "addr:full":"65 Hermit Street Dudley Staffordshire DY3 2BS",
    "addr:housenumber":"65",
    "addr:postcode":"dy3 2bs",
    "addr:street":"Hermit Street",
    "iso:country":"GB",
    "sg:address":"65 Hermit Street",
    "sg:city":"Dudley",
    "sg:classifiers":[
        {
            "category":"Home & Garden",
            "subcategory":"Hardware",
            "type":"Retail Goods"
        },
        {
            "category":"Home & Garden",
            "subcategory":"Building Materials",
            "type":"Retail Goods"
        }
    ],
    "sg:phone":"+44 1902 672609",
    "sg:postcode":"DY3 2BS",
    "sg:province":"Staffordshire",
    "sg:tags":[
        "garage",
        "door",
        "diy",
        "retailer"
    ],
    "wof:name":"Speedy Doors",
    "wof:placetype":"venue"
},
  "geometry": {"coordinates":[-2.117734,52.526382],"type":"Point"}
}