{
  "type": "Feature",
  "properties": {
    "iso:country":"GB",
    "sg:address":"Unit 6 Grange Rd, Geddington",
    "sg:city":"Kettering",
    "sg:classifiers":[
        {
            "category":"Shopping",
            "subcategory":"Catalog Store",
            "type":"Retail Goods"
        }
    ],
    "sg:postcode":"NN14 1AL",
    "sg:province":"Northamptonshire",
    "sg:tags":[
        "mail",
        "order"
    ],
    "wof:name":"Hands & Voices Ltd",
    "wof:placetype":"venue"
},
  "geometry": {"coordinates":[-0.6936590075,52.4351234436],"type":"Point"}
}