{
  "type": "Feature",
  "properties": {
    "iso:country":"GB",
    "sg:address":"Pontnewydd",
    "sg:city":"Caernarfon",
    "sg:classifiers":[
        {
            "category":"Building & Trades",
            "subcategory":"Landscaping Services",
            "type":"Services"
        }
    ],
    "sg:phone":"+44 1286 677778",
    "sg:postcode":"LL54 7UN",
    "sg:province":"Gwynedd",
    "sg:tags":[
        "pond",
        "aquarium"
    ],
    "wof:name":"Snowdon Aquatics",
    "wof:placetype":"venue"
},
  "geometry": {"coordinates":[-4.2603769302,53.090259552],"type":"Point"}
}