{
  "type": "Feature",
  "properties": {
    "iso:country":"GB",
    "sg:address":"Citizens House, Station Road",
    "sg:city":"Consett",
    "sg:classifiers":[
        {
            "category":"Organizations",
            "subcategory":"Non-profit Organization",
            "type":"Services"
        }
    ],
    "sg:phone":"+44 1207 580066",
    "sg:postcode":"DH8 5RL",
    "sg:province":"Durham",
    "sg:tags":[
        "organisation",
        "voluntary",
        "charity"
    ],
    "wof:name":"Consett Day Centre",
    "wof:placetype":"venue"
},
  "geometry": {"coordinates":[-1.8266559839,54.850944519],"type":"Point"}
}