{
  "type": "Feature",
  "properties": {
    "addr:full":"Beechgrove Moffat Dumfries and Galloway DG10 9RS",
    "addr:postcode":"dg10 9rs",
    "iso:country":"GB",
    "sg:address":"Beechgrove",
    "sg:city":"Moffat",
    "sg:classifiers":[
        {
            "category":"Travel",
            "subcategory":"Hotels & Motels",
            "type":"Entertainment"
        }
    ],
    "sg:postcode":"DG10 9RS",
    "sg:province":"Dumfries and Galloway",
    "sg:tags":[
        "house",
        "guest"
    ],
    "wof:name":"Gilbert House",
    "wof:placetype":"venue"
},
  "geometry": {"coordinates":[-3.447298,55.337273],"type":"Point"}
}