{
  "type": "Feature",
  "properties": {
    "addr:full":"75 Lees Rd Oldham Lancashire OL4 1JW",
    "addr:housenumber":"75",
    "addr:postcode":"ol4 1jw",
    "addr:street":"Lees Rd",
    "iso:country":"GB",
    "sg:address":"75 Lees Rd",
    "sg:city":"Oldham",
    "sg:classifiers":[
        {
            "category":"Personal",
            "subcategory":"Barber",
            "type":"Services"
        }
    ],
    "sg:phone":"+44 161 620 0036",
    "sg:postcode":"OL4 1JW",
    "sg:province":"Lancashire",
    "sg:tags":[
        "men's",
        "hairdresser"
    ],
    "wof:name":"Head Line",
    "wof:placetype":"venue"
},
  "geometry": {"coordinates":[-2.0969910622,53.5428466797],"type":"Point"}
}