{
  "type": "Feature",
  "properties": {
    "addr:full":"39 Sheppard Way, Minchinhampton Stroud Gloucestershire GL6 9BZ",
    "addr:housenumber":"39",
    "addr:postcode":"gl6 9bz",
    "addr:street":"Sheppard Way",
    "iso:country":"GB",
    "sg:address":"39 Sheppard Way, Minchinhampton",
    "sg:city":"Stroud",
    "sg:classifiers":[
        {
            "category":"Professional",
            "subcategory":"Management & Consulting",
            "type":"Services"
        }
    ],
    "sg:phone":"+44 1453 731774",
    "sg:postcode":"GL6 9BZ",
    "sg:province":"Gloucestershire",
    "sg:tags":[
        "consultant",
        "business"
    ],
    "wof:name":"Advanced Manufacturing Systems",
    "wof:placetype":"venue"
},
  "geometry": {"coordinates":[-2.1943719387,51.7084312439],"type":"Point"}
}