{
  "type": "Feature",
  "properties": {
    "addr:full":"Unit 16, Bilton Way Luton Bedfordshire LU1 1UU",
    "addr:housenumber":"unit 16",
    "addr:postcode":"lu1 1uu",
    "addr:street":"Bilton Way",
    "iso:country":"GB",
    "sg:address":"Unit 16, Bilton Way",
    "sg:city":"Luton",
    "sg:classifiers":[
        {
            "category":"Building & Trades",
            "subcategory":"Plumbing",
            "type":"Services"
        },
        {
            "category":"Home & Garden",
            "subcategory":"Hardware",
            "type":"Retail Goods"
        }
    ],
    "sg:phone":"+44 1582 431561",
    "sg:postcode":"LU1 1UU",
    "sg:province":"Bedfordshire",
    "sg:tags":[
        "merchant",
        "plumber",
        "plumbers'"
    ],
    "wof:name":"City Plumbing Supplies Holdings Ltd",
    "wof:placetype":"venue"
},
  "geometry": {"coordinates":[-0.452133,51.886295],"type":"Point"}
}