{
  "type": "Feature",
  "properties": {
    "iso:country":"GB",
    "sg:address":"1 Gaskell Road",
    "sg:city":"Altrincham",
    "sg:classifiers":[
        {
            "category":"Farming",
            "subcategory":"Nursery",
            "type":"Manufacturing & Wholesale Goods"
        }
    ],
    "sg:phone":"+44 161 941 7731",
    "sg:postcode":"WA14 1JF",
    "sg:province":"Cheshire",
    "sg:tags":[
        "creche"
    ],
    "wof:name":"Holyrood",
    "wof:placetype":"venue"
},
  "geometry": {"coordinates":[-2.3489038944,53.3929901123],"type":"Point"}
}