{
  "type": "Feature",
  "properties": {
    "iso:country":"GB",
    "sg:address":"152 St Neots Road",
    "sg:city":"Sandy",
    "sg:classifiers":[
        {
            "category":"Home & Garden",
            "subcategory":"Building Materials",
            "type":"Retail Goods"
        }
    ],
    "sg:phone":"+44 1767 682639",
    "sg:postcode":"SG19 1BS",
    "sg:province":"Bedfordshire",
    "sg:tags":[
        "furnishers",
        "bathroom",
        "planner"
    ],
    "wof:name":"S T A Sanitary Ware",
    "wof:placetype":"venue"
},
  "geometry": {"coordinates":[-0.295875,52.135445],"type":"Point"}
}