{
  "type": "Feature",
  "properties": {
    "addr:full":"10b High St Chesham Buckinghamshire HP5 1DE",
    "addr:housenumber":"10b",
    "addr:postcode":"hp5 1de",
    "addr:street":"High St",
    "iso:country":"GB",
    "sg:address":"10b High St",
    "sg:city":"Chesham",
    "sg:classifiers":[
        {
            "category":"Manufacturing",
            "subcategory":"Metals",
            "type":"Manufacturing & Wholesale Goods"
        }
    ],
    "sg:postcode":"HP5 1DE",
    "sg:province":"Buckinghamshire",
    "sg:tags":[
        "heat",
        "-",
        "treatment"
    ],
    "wof:name":"Humphrey,H J,",
    "wof:placetype":"venue"
},
  "geometry": {"coordinates":[-0.612379,51.705719],"type":"Point"}
}