{
  "type": "Feature",
  "properties": {
    "addr:full":"Metropolitan Centre, Upper May Day Green Arcade Barnsley South Yorkshire S70 1SX",
    "addr:postcode":"s70 1sx",
    "addr:street":"Upper May Day;Yorkshire",
    "iso:country":"GB",
    "sg:address":"Metropolitan Centre, Upper May Day Green Arcade",
    "sg:city":"Barnsley",
    "sg:classifiers":[
        {
            "category":"Professional",
            "subcategory":"Business Services",
            "type":"Services"
        }
    ],
    "sg:phone":"+44 1226 772239",
    "sg:postcode":"S70 1SX",
    "sg:province":"South Yorkshire",
    "sg:tags":[
        "operator",
        "market"
    ],
    "wof:name":"Barnsley Market Office",
    "wof:placetype":"venue"
},
  "geometry": {"coordinates":[-1.4847379923,53.5531921387],"type":"Point"}
}