{
  "type": "Feature",
  "properties": {
    "addr:full":"5 Blenheim Av Newport East Riding of Yorkshire NP6 3NB",
    "addr:housenumber":"5",
    "addr:street":"Blenheim Av",
    "iso:country":"GB",
    "sg:address":"5 Blenheim Av",
    "sg:city":"Newport",
    "sg:classifiers":[
        {
            "category":"Manufacturing",
            "subcategory":"Building Materials",
            "type":"Manufacturing & Wholesale Goods"
        }
    ],
    "sg:phone":"+44 1633 881567",
    "sg:postcode":"NP6 3NB",
    "sg:province":"East Riding of Yorkshire",
    "sg:tags":[
        "tarmac",
        "asphalt"
    ],
    "wof:name":"Pro-Mac",
    "wof:placetype":"venue"
},
  "geometry": {"coordinates":[-2.9674260616,51.5878448486],"type":"Point"}
}