{
  "type": "Feature",
  "properties": {
    "addr:full":"The Bakery, Barrow Street, Mere Warminster Somerset BA12 6AA",
    "addr:postcode":"ba12 6aa",
    "addr:street":"Barrow Street",
    "iso:country":"GB",
    "sg:address":"The Bakery, Barrow Street, Mere",
    "sg:city":"Warminster",
    "sg:classifiers":[
        {
            "category":"Personal",
            "type":"Services"
        },
        {
            "category":"Food & Beverages",
            "subcategory":"Bakery",
            "type":"Retail Goods"
        }
    ],
    "sg:phone":"+44 1747 830266",
    "sg:postcode":"BA12 6AA",
    "sg:province":"Somerset",
    "sg:tags":[
        "delivery",
        "shop",
        "baker"
    ],
    "wof:name":"STANLEY AVERY & SONS",
    "wof:placetype":"venue"
},
  "geometry": {"coordinates":[-2.270171,51.090511],"type":"Point"}
}