{
  "type": "Feature",
  "properties": {
    "addr:full":"111 Thornton Road Bradford West Yorkshire BD1 2EP",
    "addr:housenumber":"111",
    "addr:postcode":"bd1 2ep",
    "addr:street":"Thornton Road",
    "iso:country":"GB",
    "sg:address":"111 Thornton Road",
    "sg:city":"Bradford",
    "sg:classifiers":[
        {
            "category":"Autos & Motor Vehicles",
            "subcategory":"Automobile Sales",
            "type":"Retail Goods"
        },
        {
            "category":"Retail",
            "subcategory":"Auto Rental",
            "type":"Services"
        },
        {
            "category":"Retail",
            "subcategory":"Auto Repair",
            "type":"Services"
        }
    ],
    "sg:phone":"+44 1274 736440",
    "sg:postcode":"BD1 2EP",
    "sg:province":"West Yorkshire",
    "sg:tags":[
        "body",
        "car"
    ],
    "wof:name":"Sunwin Fiat Alfa Romeo",
    "wof:placetype":"venue"
},
  "geometry": {"coordinates":[-1.7687289715,53.7968597412],"type":"Point"}
}