{
  "type": "Feature",
  "properties": {
    "iso:country":"GB",
    "sg:address":"Langley Road",
    "sg:city":"Abbots Langley",
    "sg:classifiers":[
        {
            "category":"Home & Garden",
            "subcategory":"Carpets & Floor Coverings",
            "type":"Retail Goods"
        }
    ],
    "sg:phone":"+44 1923 269329",
    "sg:postcode":"WD5 0AB",
    "sg:province":"Hertfordshire",
    "sg:tags":[
        "carpets",
        "rug",
        "matting"
    ],
    "wof:name":"Carpet Rack",
    "wof:placetype":"venue"
},
  "geometry": {"coordinates":[-0.41688,51.705086],"type":"Point"}
}