{
  "type": "Feature",
  "properties": {
    "iso:country":"GB",
    "sg:address":"Pontrilas Road",
    "sg:city":"Hereford",
    "sg:classifiers":[
        {
            "category":"Retail",
            "subcategory":"Veterinary Services",
            "type":"Services"
        }
    ],
    "sg:phone":"+44 1981 240333",
    "sg:postcode":"HR2 0EL",
    "sg:province":"Herefordshire",
    "sg:tags":[
        "surgeon"
    ],
    "wof:name":"Cooper & Jinman",
    "wof:placetype":"venue"
},
  "geometry": {"coordinates":[-2.880731,51.94315],"type":"Point"}
}