{
  "type": "Feature",
  "properties": {
    "iso:country":"GB",
    "sg:address":"Unit 3, James Street",
    "sg:city":"Carlisle",
    "sg:classifiers":[
        {
            "category":"Shopping",
            "subcategory":"Stationery & Office Supplies",
            "type":"Retail Goods"
        }
    ],
    "sg:phone":"+44 1228 404600",
    "sg:postcode":"CA2 5AP",
    "sg:province":"Cumbria",
    "wof:name":"Carlisle Business Supplies",
    "wof:placetype":"venue"
},
  "geometry": {"coordinates":[-2.9351780415,54.8898086548],"type":"Point"}
}