{
  "type": "Feature",
  "properties": {
    "addr:full":"103 Lower Weybourne Lane Farnham Surrey GU9 9LG",
    "addr:housenumber":"103",
    "addr:postcode":"gu9 9lg",
    "addr:street":"Lower Weybourne Lane",
    "iso:country":"GB",
    "sg:address":"103 Lower Weybourne Lane",
    "sg:city":"Farnham",
    "sg:classifiers":[
        {
            "category":"Shopping",
            "type":"Retail Goods"
        }
    ],
    "sg:phone":"+44 1252 333891",
    "sg:postcode":"GU9 9LG",
    "sg:province":"Surrey",
    "sg:tags":[
        "part",
        "accessory"
    ],
    "wof:name":"Autocavan",
    "wof:placetype":"venue"
},
  "geometry": {"coordinates":[-0.78426,51.236721],"type":"Point"}
}