{
  "type": "Feature",
  "properties": {
    "addr:full":"Manor Court 26b Bancroft Hitchin Bedfordshire SG5 1JW",
    "addr:housenumber":"26b",
    "addr:postcode":"sg5 1jw",
    "addr:street":"Manor Court",
    "iso:country":"GB",
    "sg:address":"Manor Court 26b Bancroft",
    "sg:city":"Hitchin",
    "sg:classifiers":[
        {
            "category":"Communications",
            "type":"Services"
        }
    ],
    "sg:postcode":"SG5 1JW",
    "sg:province":"Bedfordshire",
    "sg:tags":[
        "audio-visual"
    ],
    "wof:name":"Blue Thread Ltd",
    "wof:placetype":"venue"
},
  "geometry": {"coordinates":[-0.276997,51.9504356384],"type":"Point"}
}