{
  "type": "Feature",
  "properties": {
    "addr:full":"387-389 Toquay Road Paignton Devon TQ3 3DJ",
    "addr:housenumber":"387-389",
    "addr:postcode":"tq3 3dj",
    "addr:street":"Toquay Road",
    "iso:country":"GB",
    "sg:address":"387-389 Toquay Road",
    "sg:city":"Paignton",
    "sg:classifiers":[
        {
            "category":"Building & Trades",
            "subcategory":"Construction",
            "type":"Services"
        }
    ],
    "sg:phone":"+44 1803 698199",
    "sg:postcode":"TQ3 3DJ",
    "sg:province":"Devon",
    "sg:tags":[
        "joiner",
        "carpenter"
    ],
    "wof:name":"Woodplas Ltd.",
    "wof:placetype":"venue"
},
  "geometry": {"coordinates":[-3.567689,50.437489],"type":"Point"}
}