{
  "type": "Feature",
  "properties": {
    "iso:country":"GB",
    "sg:address":"157/159 High Street",
    "sg:city":"Berkhamsted",
    "sg:classifiers":[
        {
            "category":"Restaurant",
            "type":"Food & Drink"
        }
    ],
    "sg:phone":"+44 1442 865940",
    "sg:postcode":"HP4 3HB",
    "sg:province":"Bedfordshire",
    "sg:tags":[
        "-",
        "chinese"
    ],
    "wof:name":"Regal Of Berkhamsted",
    "wof:placetype":"venue"
},
  "geometry": {"coordinates":[-0.564361,51.760181],"type":"Point"}
}