{
  "type": "Feature",
  "properties": {
    "addr:full":"33 Moreton Road Ongar Essex CM5 0AP",
    "addr:housenumber":"33",
    "addr:postcode":"cm5 0ap",
    "addr:street":"Moreton Road",
    "iso:country":"GB",
    "sg:address":"33 Moreton Road",
    "sg:city":"Ongar",
    "sg:classifiers":[
        {
            "category":"Home & Garden",
            "subcategory":"Building Materials",
            "type":"Retail Goods"
        }
    ],
    "sg:phone":"+44 1277 363651",
    "sg:postcode":"CM5 0AP",
    "sg:province":"Essex",
    "sg:tags":[
        "system",
        "staircase"
    ],
    "wof:name":"Truline Stairs",
    "wof:placetype":"venue"
},
  "geometry": {"coordinates":[0.2431100011,51.7161521912],"type":"Point"}
}