{
  "type": "Feature",
  "properties": {
    "iso:country":"GB",
    "sg:address":"Unit 11, Nortonthorpe Industrial Estate",
    "sg:city":"Huddersfield",
    "sg:classifiers":[
        {
            "category":"Shopping",
            "subcategory":"Stationery & Office Supplies",
            "type":"Retail Goods"
        },
        {
            "category":"Government",
            "subcategory":"Post Office",
            "type":"Public Place"
        }
    ],
    "sg:phone":"+44 1484 864205",
    "sg:postcode":"HD8 9LA",
    "sg:province":"South Yorkshire",
    "sg:tags":[
        "pc",
        "manufacturer"
    ],
    "wof:name":"Scott Office & Computer Services",
    "wof:placetype":"venue"
},
  "geometry": {"coordinates":[-1.6097,53.600319],"type":"Point"}
}