{
  "type": "Feature",
  "properties": {
    "addr:full":"122a Nelson Road, Whitton Twickenham Greater London TW2 7AY",
    "addr:housenumber":"122a",
    "addr:postcode":"tw2 7ay",
    "addr:street":"Nelson Road",
    "iso:country":"GB",
    "sg:address":"122a Nelson Road, Whitton",
    "sg:city":"Twickenham",
    "sg:classifiers":[
        {
            "category":"Fast Food",
            "type":"Food & Drink"
        }
    ],
    "sg:postcode":"TW2 7AY",
    "sg:province":"Greater London",
    "sg:tags":[
        "away",
        "take"
    ],
    "wof:name":"Keydene Limited",
    "wof:placetype":"venue"
},
  "geometry": {"coordinates":[-0.356633,51.453583],"type":"Point"}
}