{
  "type": "Feature",
  "properties": {
    "addr:full":"192 Main Rd, Biggin Hill Westerham Kent TN16 3BB",
    "addr:housenumber":"192",
    "addr:postcode":"tn16 3bb",
    "addr:street":"Main Rd",
    "iso:country":"GB",
    "sg:address":"192 Main Rd, Biggin Hill",
    "sg:city":"Westerham",
    "sg:classifiers":[
        {
            "category":"Professional",
            "subcategory":"Computer Services",
            "type":"Services"
        }
    ],
    "sg:postcode":"TN16 3BB",
    "sg:province":"Kent",
    "sg:tags":[
        "system",
        "software"
    ],
    "wof:name":"Arrow Business Services",
    "wof:placetype":"venue"
},
  "geometry": {"coordinates":[0.0391829982,51.3081970215],"type":"Point"}
}