{
  "type": "Feature",
  "properties": {
    "addr:full":"Wellington Road, Tharston Industrial Estate, Longstratton Norwich Norfolk NR15 2PE",
    "addr:postcode":"nr15 2pe",
    "addr:street":"Wellington Road Tharston Industrial Estate Longstratton Norwich",
    "iso:country":"GB",
    "sg:address":"Wellington Road, Tharston Industrial Estate, Longstratton",
    "sg:city":"Norwich",
    "sg:classifiers":[
        {
            "category":"Building & Trades",
            "subcategory":"Plumbing",
            "type":"Services"
        }
    ],
    "sg:phone":"+44 1508 31609",
    "sg:postcode":"NR15 2PE",
    "sg:province":"Norfolk",
    "sg:tags":[
        "merchant",
        "plumbers'"
    ],
    "wof:name":"Michael D Brown",
    "wof:placetype":"venue"
},
  "geometry": {"coordinates":[1.221175,52.48637],"type":"Point"}
}