{
  "type": "Feature",
  "properties": {
    "iso:country":"GB",
    "sg:address":"6 Brynhyfryd Square, Brynhyfryd",
    "sg:city":"Swansea",
    "sg:classifiers":[
        {
            "category":"Shopping",
            "subcategory":"News",
            "type":"Retail Goods"
        }
    ],
    "sg:phone":"+44 1792 654213",
    "sg:postcode":"SA5 9EB",
    "sg:province":"Swansea",
    "sg:tags":[
        "newsagent"
    ],
    "wof:name":"Williams T & Ja<",
    "wof:placetype":"venue"
},
  "geometry": {"coordinates":[-3.945303,51.643494],"type":"Point"}
}