{
  "type": "Feature",
  "properties": {
    "iso:country":"GB",
    "sg:address":"Dixon Blazes, 562/564 Lawmoor Street",
    "sg:city":"Glasgow",
    "sg:classifiers":[
        {
            "category":"Manufacturing",
            "subcategory":"Wood Products",
            "type":"Manufacturing & Wholesale Goods"
        }
    ],
    "sg:postcode":"G5 0TY",
    "sg:province":"Glasgow City",
    "sg:tags":[
        "packaging",
        "crate",
        "pallets"
    ],
    "wof:name":"Goggins Ltd.",
    "wof:placetype":"venue"
},
  "geometry": {"coordinates":[-4.24927,55.841511],"type":"Point"}
}