{
  "type": "Feature",
  "properties": {
    "addr:full":"96 Horsenden Lane South Greenford Greater London UB6 7NN",
    "addr:housenumber":"96",
    "addr:postcode":"ub6 7nn",
    "addr:street":"Horsenden Lane South",
    "iso:country":"GB",
    "sg:address":"96 Horsenden Lane South",
    "sg:city":"Greenford",
    "sg:classifiers":[
        {
            "category":"Travel",
            "subcategory":"Travel Agent",
            "type":"Entertainment"
        }
    ],
    "sg:phone":"+44 20 8998 7477",
    "sg:postcode":"UB6 7NN",
    "sg:province":"Greater London",
    "wof:name":"Zak Travel",
    "wof:placetype":"venue"
},
  "geometry": {"coordinates":[-0.3239560127,51.5380592346],"type":"Point"}
}