{
  "type": "Feature",
  "properties": {
    "addr:full":"Unit 8, Green Leaf Business Centre, Darkes La Potters Bar Greater London EN6 1AE",
    "addr:housenumber":"unit 8",
    "addr:postcode":"en6 1ae",
    "addr:street":"Green Leaf;Darkes",
    "iso:country":"GB",
    "sg:address":"Unit 8, Green Leaf Business Centre, Darkes La",
    "sg:city":"Potters Bar",
    "sg:classifiers":[
        {
            "category":"Building & Trades",
            "subcategory":"Construction",
            "type":"Services"
        }
    ],
    "sg:postcode":"EN6 1AE",
    "sg:province":"Greater London",
    "sg:tags":[
        "builder"
    ],
    "wof:name":"Jones,K,Construction,",
    "wof:placetype":"venue"
},
  "geometry": {"coordinates":[-0.1784240007,51.6930122375],"type":"Point"}
}