{
  "type": "Feature",
  "properties": {
    "addr:full":"4-5 Crown Walk Newmarket Cambridgeshire CB8 8NG",
    "addr:housenumber":"4-5",
    "addr:postcode":"cb8 8ng",
    "addr:street":"Crown Walk Newmarket",
    "iso:country":"GB",
    "sg:address":"4-5 Crown Walk",
    "sg:city":"Newmarket",
    "sg:classifiers":[
        {
            "category":"Bars & Pubs",
            "subcategory":"Wine Bar",
            "type":"Food & Drink"
        }
    ],
    "sg:phone":"+44 1638 668474",
    "sg:postcode":"CB8 8NG",
    "sg:province":"Cambridgeshire",
    "wof:name":"Silks Wine Bar & Delicatessen",
    "wof:placetype":"venue"
},
  "geometry": {"coordinates":[0.399165988,52.2498168945],"type":"Point"}
}