{
  "type": "Feature",
  "properties": {
    "addr:full":"110 Park Lane London Greater London N17 0JP",
    "addr:housenumber":"110",
    "addr:postcode":"n17 0jp",
    "addr:street":"Park Lane",
    "iso:country":"GB",
    "sg:address":"110 Park Lane",
    "sg:city":"London",
    "sg:classifiers":[
        {
            "category":"Shopping",
            "subcategory":"Gifts & Souvenirs",
            "type":"Retail Goods"
        }
    ],
    "sg:postcode":"N17 0JP",
    "sg:province":"Greater London",
    "sg:tags":[
        "shop"
    ],
    "wof:name":"Harry's Fancy Goods",
    "wof:placetype":"venue"
},
  "geometry": {"coordinates":[-0.060783,51.602295],"type":"Point"}
}