{
  "type": "Feature",
  "properties": {
    "iso:country":"GB",
    "sg:address":"235 Rookery Road Handsworth",
    "sg:city":"Birmingham",
    "sg:classifiers":[
        {
            "category":"Manufacturing",
            "subcategory":"Petroleum Products",
            "type":"Manufacturing & Wholesale Goods"
        }
    ],
    "sg:postcode":"B21 9PU",
    "sg:province":"West Midlands",
    "sg:tags":[
        "double",
        "glazing"
    ],
    "wof:name":"V F M Windows & Doors",
    "wof:placetype":"venue"
},
  "geometry": {"coordinates":[-1.939367,52.511749],"type":"Point"}
}