{
  "type": "Feature",
  "properties": {
    "addr:full":"Dennyloanhead Bonnybridge Falkirk FK4 1ST",
    "addr:postcode":"fk4 1st",
    "iso:country":"GB",
    "sg:address":"Dennyloanhead",
    "sg:city":"Bonnybridge",
    "sg:classifiers":[
        {
            "category":"Wholesale",
            "subcategory":"Scrap",
            "type":"Manufacturing & Wholesale Goods"
        }
    ],
    "sg:phone":"+44 1324 840209",
    "sg:postcode":"FK4 1ST",
    "sg:province":"Falkirk",
    "sg:tags":[
        "breaker",
        "dismantlers"
    ],
    "wof:name":"Underwood Car Mart",
    "wof:placetype":"venue"
},
  "geometry": {"coordinates":[-3.881618,56.002949],"type":"Point"}
}