{
  "type": "Feature",
  "properties": {
    "addr:full":"36 Back Piccadilly Manchester Greater Manchester M1 1HP",
    "addr:housenumber":"36",
    "addr:postcode":"m1 1hp",
    "addr:street":"Back Piccadilly",
    "iso:country":"GB",
    "sg:address":"36 Back Piccadilly",
    "sg:city":"Manchester",
    "sg:classifiers":[
        {
            "category":"Fast Food",
            "type":"Food & Drink"
        }
    ],
    "sg:phone":"+44 161 228 7377",
    "sg:postcode":"M1 1HP",
    "sg:province":"Greater Manchester",
    "sg:tags":[
        "away",
        "take"
    ],
    "wof:name":"Merhba Takeaway",
    "wof:placetype":"venue"
},
  "geometry": {"coordinates":[-2.234462,53.481071],"type":"Point"}
}