{
  "type": "Feature",
  "properties": {
    "iso:country":"GB",
    "sg:address":"47-49 Riley Square, Bell Green District Centre",
    "sg:city":"Coventry",
    "sg:classifiers":[
        {
            "category":"Shopping",
            "subcategory":"Pharmacy",
            "type":"Retail Goods"
        }
    ],
    "sg:phone":"+44 24 7668 3415",
    "sg:postcode":"CV2 1LW",
    "sg:province":"Warwickshire",
    "sg:tags":[
        "pharmacist",
        "dispensing",
        "chemist"
    ],
    "wof:name":"LLOYDS PHARMACY LTD",
    "wof:placetype":"venue"
},
  "geometry": {"coordinates":[-1.472685,52.436157],"type":"Point"}
}