{
  "type": "Feature",
  "properties": {
    "iso:country":"GB",
    "sg:address":"26 Chertsey Rd",
    "sg:city":"Woking",
    "sg:classifiers":[
        {
            "category":"Shopping",
            "type":"Retail Goods"
        }
    ],
    "sg:phone":"+44 1483 770095",
    "sg:postcode":"GU21 5AJ",
    "sg:province":"Surrey",
    "sg:tags":[
        "part",
        "accessory"
    ],
    "wof:name":"Les Smith Motorist & Cycle Supercentre",
    "wof:placetype":"venue"
},
  "geometry": {"coordinates":[-0.555706,51.320644],"type":"Point"}
}