{
  "type": "Feature",
  "properties": {
    "iso:country":"GB",
    "sg:address":"Unit 18, Church Road Business Centre",
    "sg:city":"Sittingbourne",
    "sg:classifiers":[
        {
            "category":"Building & Trades",
            "subcategory":"Construction",
            "type":"Services"
        }
    ],
    "sg:phone":"+44 1795 421533",
    "sg:postcode":"ME10 3RS",
    "sg:province":"Kent",
    "sg:tags":[
        "decorator",
        "painter"
    ],
    "wof:name":"L C Byne & Son",
    "wof:placetype":"venue"
},
  "geometry": {"coordinates":[0.752885,51.340225],"type":"Point"}
}