{
  "type": "Feature",
  "properties": {
    "iso:country":"GB",
    "sg:address":"111 Westbourne Gro",
    "sg:city":"London",
    "sg:classifiers":[
        {
            "category":"Restaurant",
            "type":"Food & Drink"
        }
    ],
    "sg:phone":"+44 20 7792 4035",
    "sg:postcode":"W2 4UW",
    "sg:province":"Greater London",
    "wof:name":"Rodizio Rico",
    "wof:placetype":"venue"
},
  "geometry": {"coordinates":[-0.193761,51.515114],"type":"Point"}
}