{
  "type": "Feature",
  "properties": {
    "addr:full":"75-77 Chequers La Dagenham Essex RM9 6QJ",
    "addr:housenumber":"75-77",
    "addr:postcode":"rm9 6qj",
    "addr:street":"Chequers La Dagenham",
    "iso:country":"GB",
    "sg:address":"75-77 Chequers La",
    "sg:city":"Dagenham",
    "sg:classifiers":[
        {
            "category":"Wholesale",
            "subcategory":"Scrap",
            "type":"Manufacturing & Wholesale Goods"
        }
    ],
    "sg:phone":"+44 20 8517 5678",
    "sg:postcode":"RM9 6QJ",
    "sg:province":"Essex",
    "sg:tags":[
        "salvage"
    ],
    "wof:name":"Discount Spares & Salvage",
    "wof:placetype":"venue"
},
  "geometry": {"coordinates":[0.1460620016,51.5235862732],"type":"Point"}
}