{
  "type": "Feature",
  "properties": {
    "iso:country":"GB",
    "sg:address":"27 Cambridge Road",
    "sg:city":"St Albans",
    "sg:classifiers":[
        {
            "category":"Health Services",
            "subcategory":"Hospital",
            "type":"Services"
        }
    ],
    "sg:phone":"+44 1707 274801",
    "sg:postcode":"AL1 5LD",
    "sg:province":"Hertfordshire",
    "wof:name":"Dental Craft",
    "wof:placetype":"venue"
},
  "geometry": {"coordinates":[-0.309217,51.748814],"type":"Point"}
}