{
  "type": "Feature",
  "properties": {
    "addr:full":"124 Dorchester Road Weymouth Dorset DT4 7LG",
    "addr:housenumber":"124",
    "addr:postcode":"dt4 7lg",
    "addr:street":"Dorchester Road",
    "iso:country":"GB",
    "sg:address":"124 Dorchester Road",
    "sg:city":"Weymouth",
    "sg:classifiers":[
        {
            "category":"Travel",
            "subcategory":"Hotels & Motels",
            "type":"Entertainment"
        }
    ],
    "sg:phone":"+44 1305 782670",
    "sg:postcode":"DT4 7LG",
    "sg:province":"Dorset",
    "sg:tags":[
        "house",
        "guest"
    ],
    "wof:name":"Lilac Villa Guest House",
    "wof:placetype":"venue"
},
  "geometry": {"coordinates":[-2.4585039616,50.6267852783],"type":"Point"}
}