{
  "type": "Feature",
  "properties": {
    "addr:full":"43 Bents Lane Dronfield Derbyshire S18 2EX",
    "addr:housenumber":"43",
    "addr:postcode":"s18 2ex",
    "addr:street":"Bents Lane",
    "iso:country":"GB",
    "sg:address":"43 Bents Lane",
    "sg:city":"Dronfield",
    "sg:classifiers":[
        {
            "category":"Real Estate",
            "subcategory":"Real Estate Services",
            "type":"Services"
        },
        {
            "category":"Building & Trades",
            "subcategory":"Construction",
            "type":"Services"
        }
    ],
    "sg:phone":"+44 1246 418458",
    "sg:postcode":"S18 2EX",
    "sg:province":"Derbyshire",
    "sg:tags":[
        "property",
        "joiner",
        "carpenter",
        "maintenance"
    ],
    "wof:name":"Dronfield Building & Joinery Services",
    "wof:placetype":"venue"
},
  "geometry": {"coordinates":[-1.4574010372,53.3095474243],"type":"Point"}
}