{
  "type": "Feature",
  "properties": {
    "addr:full":"Talbot Terrace Lewes East Sussex BN7 2DS",
    "addr:postcode":"bn7 2ds",
    "addr:street":"Talbot Terrace",
    "iso:country":"GB",
    "sg:address":"Talbot Terrace",
    "sg:city":"Lewes",
    "sg:classifiers":[
        {
            "category":"Education",
            "subcategory":"School",
            "type":"Public Place"
        }
    ],
    "sg:phone":"+44 1273 476708",
    "sg:postcode":"BN7 2DS",
    "sg:province":"East Sussex",
    "sg:tags":[
        "local",
        "authority"
    ],
    "wof:name":"Pells C of E Primary School",
    "wof:placetype":"venue"
},
  "geometry": {"coordinates":[0.0080749998,50.8763809204],"type":"Point"}
}