{
  "type": "Feature",
  "properties": {
    "addr:full":"Castle Hill Lancaster Lancashire LA1 1YZ",
    "addr:postcode":"la1 1yz",
    "iso:country":"GB",
    "sg:address":"Castle Hill",
    "sg:city":"Lancaster",
    "sg:classifiers":[
        {
            "category":"Place Of Worship",
            "type":"Public Place"
        }
    ],
    "sg:phone":"+44 1524 65338",
    "sg:postcode":"LA1 1YZ",
    "sg:province":"Lancashire",
    "wof:name":"Lancaster Priory Church",
    "wof:placetype":"venue"
},
  "geometry": {"coordinates":[-2.8042190075,54.049369812],"type":"Point"}
}