{
  "type": "Feature",
  "properties": {
    "addr:full":"6 The Commons Shaftesbury Dorset SP7 8JU",
    "addr:housenumber":"6",
    "addr:postcode":"sp7 8ju",
    "addr:street":"The Commons",
    "iso:country":"GB",
    "sg:address":"6 The Commons",
    "sg:city":"Shaftesbury",
    "sg:classifiers":[
        {
            "category":"Home & Garden",
            "subcategory":"Household Appliances",
            "type":"Retail Goods"
        }
    ],
    "sg:postcode":"SP7 8JU",
    "sg:province":"Dorset",
    "sg:tags":[
        "electrical",
        "domestic"
    ],
    "wof:name":"Mullins,Sarah,",
    "wof:placetype":"venue"
},
  "geometry": {"coordinates":[-2.1904790401,51.0071907043],"type":"Point"}
}