{
  "type": "Feature",
  "properties": {
    "iso:country":"GB",
    "sg:address":"7 Meadow Drive, Prestbury",
    "sg:city":"Macclesfield",
    "sg:classifiers":[
        {
            "category":"Professional",
            "subcategory":"Management & Consulting",
            "type":"Services"
        }
    ],
    "sg:phone":"+44 1625 827098",
    "sg:postcode":"SK10 4EY",
    "sg:province":"Cheshire",
    "sg:tags":[
        "consultant",
        "business"
    ],
    "wof:name":"Vivek Business Consultants",
    "wof:placetype":"venue"
},
  "geometry": {"coordinates":[-2.137148,53.289833],"type":"Point"}
}