{
  "type": "Feature",
  "properties": {
    "addr:full":"139 Malpas Road Runcorn Cheshire WA7 4AP",
    "addr:housenumber":"139",
    "addr:postcode":"wa7 4ap",
    "addr:street":"Malpas Road",
    "iso:country":"GB",
    "sg:address":"139 Malpas Road",
    "sg:city":"Runcorn",
    "sg:classifiers":[
        {
            "category":"Real Estate",
            "subcategory":"Architect",
            "type":"Services"
        }
    ],
    "sg:postcode":"WA7 4AP",
    "sg:province":"Cheshire",
    "wof:name":"Haltongate Engineering Ltd.",
    "wof:placetype":"venue"
},
  "geometry": {"coordinates":[-2.718998909,53.3215827942],"type":"Point"}
}