{
  "type": "Feature",
  "properties": {
    "iso:country":"GB",
    "sg:address":"Long Meadow Infants School, Oaks Cross",
    "sg:city":"Stevenage",
    "sg:classifiers":[
        {
            "category":"Education",
            "subcategory":"School",
            "type":"Public Place"
        }
    ],
    "sg:phone":"+44 1438 351087",
    "sg:postcode":"SG2 8LT",
    "sg:province":"Hertfordshire",
    "sg:tags":[
        "local",
        "authority"
    ],
    "wof:name":"Longmeadow Junior Mixed School",
    "wof:placetype":"venue"
},
  "geometry": {"coordinates":[-0.1673420072,51.8841438293],"type":"Point"}
}