{
  "type": "Feature",
  "properties": {
    "addr:full":"Unit 1, Archway Centre, Pond St Sheffield South Yorkshire S1 2BD",
    "addr:housenumber":"unit 1 archway centre",
    "addr:postcode":"s1 2bd",
    "addr:street":"Pond St",
    "iso:country":"GB",
    "sg:address":"Unit 1, Archway Centre, Pond St",
    "sg:city":"Sheffield",
    "sg:classifiers":[
        {
            "category":"Shopping",
            "subcategory":"Comic Books",
            "type":"Retail Goods"
        }
    ],
    "sg:postcode":"S1 2BD",
    "sg:province":"South Yorkshire",
    "sg:tags":[
        "jeweller"
    ],
    "wof:name":"Bharth,K S,",
    "wof:placetype":"venue"
},
  "geometry": {"coordinates":[-1.4645440578,53.3831100464],"type":"Point"}
}