{
  "type": "Feature",
  "properties": {
    "addr:full":"73 Canal Lane, Lofthouse Wakefield West Yorkshire WF3 3HP",
    "addr:housenumber":"73",
    "addr:postcode":"wf3 3hp",
    "addr:street":"Canal Lane;West",
    "iso:country":"GB",
    "sg:address":"73 Canal Lane, Lofthouse",
    "sg:city":"Wakefield",
    "sg:classifiers":[
        {
            "category":"Building & Trades",
            "subcategory":"Landscaping Services",
            "type":"Services"
        }
    ],
    "sg:postcode":"WF3 3HP",
    "sg:province":"West Yorkshire",
    "sg:tags":[
        "landscape",
        "contractor"
    ],
    "wof:name":"Largent Landscapes",
    "wof:placetype":"venue"
},
  "geometry": {"coordinates":[-1.4860520363,53.7169418335],"type":"Point"}
}