{
  "type": "Feature",
  "properties": {
    "addr:full":"11 Edgedale Rd Sheffield South Yorkshire S7 2BQ",
    "addr:housenumber":"11",
    "addr:postcode":"s7 2bq",
    "addr:street":"Edgedale Rd",
    "iso:country":"GB",
    "sg:address":"11 Edgedale Rd",
    "sg:city":"Sheffield",
    "sg:classifiers":[
        {
            "category":"Professional",
            "subcategory":"Engineering",
            "type":"Services"
        }
    ],
    "sg:phone":"+44 114 249 4142",
    "sg:postcode":"S7 2BQ",
    "sg:province":"South Yorkshire",
    "sg:tags":[
        "electronic",
        "engineer"
    ],
    "wof:name":"Micropower Ltd",
    "wof:placetype":"venue"
},
  "geometry": {"coordinates":[-1.487509,53.354759],"type":"Point"}
}