{
  "type": "Feature",
  "properties": {
    "iso:country":"GB",
    "sg:address":"34 Woodland Close",
    "sg:city":"Nottingham",
    "sg:classifiers":[
        {
            "category":"Home & Garden",
            "subcategory":"Household Appliances",
            "type":"Retail Goods"
        }
    ],
    "sg:postcode":"NG12 2HZ",
    "sg:province":"Nottinghamshire",
    "sg:tags":[
        "gas"
    ],
    "wof:name":"Derek Redshaw Gas Servicing",
    "wof:placetype":"venue"
},
  "geometry": {"coordinates":[-1.022768,52.946297],"type":"Point"}
}