{
  "type": "Feature",
  "properties": {
    "addr:full":"1 Chiserley Hall Hebden Bridge West Yorkshire HX7 8SD",
    "addr:housenumber":"1",
    "addr:postcode":"hx7 8sd",
    "addr:street":"Chiserley Hall;West",
    "iso:country":"GB",
    "sg:address":"1 Chiserley Hall",
    "sg:city":"Hebden Bridge",
    "sg:classifiers":[
        {
            "category":"Farming",
            "subcategory":"Livestock Farm",
            "type":"Manufacturing & Wholesale Goods"
        }
    ],
    "sg:phone":"+44 1422 842368",
    "sg:postcode":"HX7 8SD",
    "sg:province":"West Yorkshire",
    "sg:tags":[
        "others"
    ],
    "wof:name":"Kenneth Greenwood",
    "wof:placetype":"venue"
},
  "geometry": {"coordinates":[-1.9975390434,53.749786377],"type":"Point"}
}