{
  "type": "Feature",
  "properties": {
    "addr:full":"26 Chapel Street Llandudno Conwy LL30 2SY",
    "addr:housenumber":"26",
    "addr:postcode":"ll30 2sy",
    "addr:street":"Chapel Street",
    "iso:country":"GB",
    "sg:address":"26 Chapel Street",
    "sg:city":"Llandudno",
    "sg:classifiers":[
        {
            "category":"Travel",
            "subcategory":"Hotels & Motels",
            "type":"Entertainment"
        }
    ],
    "sg:postcode":"LL30 2SY",
    "sg:province":"Conwy",
    "sg:tags":[
        "house",
        "guest"
    ],
    "wof:name":"S Thomas",
    "wof:placetype":"venue"
},
  "geometry": {"coordinates":[-3.832296,53.324299],"type":"Point"}
}