{
  "type": "Feature",
  "properties": {
    "iso:country":"GB",
    "sg:address":"Jockey Lane, Huntington",
    "sg:city":"York",
    "sg:classifiers":[
        {
            "category":"Building & Trades",
            "subcategory":"Plumbing",
            "type":"Services"
        }
    ],
    "sg:phone":"+44 1904 612089",
    "sg:postcode":"YO32 9NE",
    "sg:province":"North Yorkshire",
    "sg:tags":[
        "heating"
    ],
    "wof:name":"E M & S Ltd.",
    "wof:placetype":"venue"
},
  "geometry": {"coordinates":[-1.068378,53.988235],"type":"Point"}
}