{
  "type": "Feature",
  "properties": {
    "addr:full":"A4 Newbury Industrial Centre, Faraday Road Newbury Berkshire RG14 2AD",
    "addr:postcode":"rg14 2ad",
    "addr:street":"Newbury;Faraday Road",
    "iso:country":"GB",
    "sg:address":"A4 Newbury Industrial Centre, Faraday Road",
    "sg:city":"Newbury",
    "sg:classifiers":[
        {
            "category":"Shopping",
            "subcategory":"Computers & Home Electronics",
            "type":"Retail Goods"
        }
    ],
    "sg:phone":"+44 1635 37273",
    "sg:postcode":"RG14 2AD",
    "sg:province":"Berkshire",
    "sg:tags":[
        "electrical"
    ],
    "wof:name":"Newey & Eyre Ltd.",
    "wof:placetype":"venue"
},
  "geometry": {"coordinates":[-1.3258719444,51.405872345],"type":"Point"}
}