{
  "type": "Feature",
  "properties": {
    "iso:country":"GB",
    "sg:address":"49 Red Road Crt",
    "sg:city":"Glasgow",
    "sg:classifiers":[
        {
            "category":"Shopping",
            "subcategory":"News",
            "type":"Retail Goods"
        }
    ],
    "sg:phone":"+44 141 557 0419",
    "sg:postcode":"G21 4PL",
    "sg:province":"East Dunbartonshire",
    "sg:tags":[
        "newsagent"
    ],
    "wof:name":"Sandher & Son",
    "wof:placetype":"venue"
},
  "geometry": {"coordinates":[-4.210984,55.881191],"type":"Point"}
}