{
  "type": "Feature",
  "properties": {
    "iso:country":"GB",
    "sg:address":"Hainey Farm, Barway Road",
    "sg:city":"Ely",
    "sg:classifiers":[
        {
            "category":"Farming",
            "subcategory":"Livestock Farm",
            "type":"Manufacturing & Wholesale Goods"
        }
    ],
    "sg:phone":"+44 1353 720427",
    "sg:postcode":"CB7 5TZ",
    "sg:province":"Cambridgeshire",
    "sg:tags":[
        "others"
    ],
    "wof:name":"G S Shropshire & Sons",
    "wof:placetype":"venue"
},
  "geometry": {"coordinates":[0.265946,52.357128],"type":"Point"}
}