{
  "type": "Feature",
  "properties": {
    "iso:country":"GB",
    "sg:address":"76 Kew Road",
    "sg:city":"Richmond",
    "sg:classifiers":[
        {
            "category":"Professional",
            "subcategory":"Lawyer & Legal Services",
            "type":"Services"
        }
    ],
    "sg:phone":"+44 20 8948 7879",
    "sg:postcode":"TW9 2PQ",
    "sg:province":"Greater London",
    "sg:tags":[
        "solicitor"
    ],
    "wof:name":"Price Carter",
    "wof:placetype":"venue"
},
  "geometry": {"coordinates":[-0.2986530066,51.4656410217],"type":"Point"}
}