{
  "type": "Feature",
  "properties": {
    "addr:full":"61 Kedleston Road Derby Derbyshire DE22 1FL",
    "addr:housenumber":"61",
    "addr:postcode":"de22 1fl",
    "addr:street":"Kedleston Road",
    "iso:country":"GB",
    "sg:address":"61 Kedleston Road",
    "sg:city":"Derby",
    "sg:classifiers":[
        {
            "category":"Autos & Motor Vehicles",
            "subcategory":"Auto Supplies",
            "type":"Retail Goods"
        }
    ],
    "sg:phone":"+44 1332 297878",
    "sg:postcode":"DE22 1FL",
    "sg:province":"Derbyshire",
    "sg:tags":[
        "tyre"
    ],
    "wof:name":"Associated Tyre Specialists Ltd.",
    "wof:placetype":"venue"
},
  "geometry": {"coordinates":[-1.486981988,52.9308776855],"type":"Point"}
}