{
  "type": "Feature",
  "properties": {
    "addr:full":"4 St Nicholas Close, Long Stratton Norwich Norfolk NR15 2JQ",
    "addr:housenumber":"4",
    "addr:postcode":"nr15 2jq",
    "addr:street":"St Nicholas Close",
    "iso:country":"GB",
    "sg:address":"4 St Nicholas Close, Long Stratton",
    "sg:city":"Norwich",
    "sg:classifiers":[
        {
            "category":"Parking",
            "type":"Transportation"
        }
    ],
    "sg:postcode":"NR15 2JQ",
    "sg:province":"Norfolk",
    "sg:tags":[
        "car",
        "valet"
    ],
    "wof:name":"1ST Class",
    "wof:placetype":"venue"
},
  "geometry": {"coordinates":[1.223108,52.48782],"type":"Point"}
}