{
  "type": "Feature",
  "properties": {
    "addr:full":"14 Cheapside Spennymoor Durham DL16 6DJ",
    "addr:housenumber":"14",
    "addr:postcode":"dl16 6dj",
    "addr:street":"Cheapside",
    "iso:country":"GB",
    "sg:address":"14 Cheapside",
    "sg:city":"Spennymoor",
    "sg:classifiers":[
        {
            "category":"Shopping",
            "subcategory":"Pharmacy",
            "type":"Retail Goods"
        },
        {
            "category":"Food & Beverages",
            "subcategory":"Groceries & Convenience Stores",
            "type":"Retail Goods"
        }
    ],
    "sg:phone":"+44 1388 816158",
    "sg:postcode":"DL16 6DJ",
    "sg:province":"Durham",
    "sg:tags":[
        "pharmacist",
        "dispensing",
        "chemist"
    ],
    "wof:name":"A D P Miller",
    "wof:placetype":"venue"
},
  "geometry": {"coordinates":[-1.5999289751,54.7000350952],"type":"Point"}
}