{
  "type": "Feature",
  "properties": {
    "addr:full":"3 Pevensey Rd, Forest Gate Forest Gate Greater London E7 0AR",
    "addr:housenumber":"3",
    "addr:postcode":"e7 0ar",
    "addr:street":"Pevensey Rd Forest Gate;Gate",
    "iso:country":"GB",
    "sg:address":"3 Pevensey Rd, Forest Gate",
    "sg:city":"Forest Gate",
    "sg:classifiers":[
        {
            "category":"Building & Trades",
            "subcategory":"Construction",
            "type":"Services"
        }
    ],
    "sg:phone":"+44 20 8534 0001",
    "sg:postcode":"E7 0AR",
    "sg:province":"Greater London",
    "sg:tags":[
        "roofing"
    ],
    "wof:name":"Access Roofing",
    "wof:placetype":"venue"
},
  "geometry": {"coordinates":[0.016536,51.554024],"type":"Point"}
}