{
  "type": "Feature",
  "properties": {
    "iso:country":"GB",
    "sg:address":"2 Turner Close, Market Weighton",
    "sg:city":"York",
    "sg:classifiers":[
        {
            "category":"Shopping",
            "subcategory":"Computers & Home Electronics",
            "type":"Retail Goods"
        }
    ],
    "sg:postcode":"YO43 3AD",
    "sg:province":"East Riding of Yorkshire",
    "sg:tags":[
        "aerial",
        "television",
        "radio"
    ],
    "wof:name":"Stephen C Ellerker",
    "wof:placetype":"venue"
},
  "geometry": {"coordinates":[-0.663966,53.861599],"type":"Point"}
}