{
  "type": "Feature",
  "properties": {
    "addr:full":"7 Whetley Gro, Off Whetley Lane Bradford West Yorkshire BD8 9ED",
    "addr:housenumber":"7",
    "addr:postcode":"bd8 9ed",
    "addr:street":"Whetley Gro Off Whetley Lane",
    "iso:country":"GB",
    "sg:address":"7 Whetley Gro, Off Whetley Lane",
    "sg:city":"Bradford",
    "sg:classifiers":[
        {
            "category":"Home & Garden",
            "subcategory":"Household Appliances",
            "type":"Retail Goods"
        }
    ],
    "sg:postcode":"BD8 9ED",
    "sg:province":"West Yorkshire",
    "sg:tags":[
        "electrical"
    ],
    "wof:name":"S D Electrical",
    "wof:placetype":"venue"
},
  "geometry": {"coordinates":[-1.7818180323,53.8020324707],"type":"Point"}
}