{
  "type": "Feature",
  "properties": {
    "addr:full":"106 London Road Liverpool Merseyside L3 5NL",
    "addr:housenumber":"106",
    "addr:postcode":"l3 5nl",
    "addr:street":"London Road",
    "iso:country":"GB",
    "sg:address":"106 London Road",
    "sg:city":"Liverpool",
    "sg:classifiers":[
        {
            "category":"Professional",
            "subcategory":"Business Services",
            "type":"Services"
        }
    ],
    "sg:phone":"+44 151 281 4305",
    "sg:postcode":"L3 5NL",
    "sg:province":"Merseyside",
    "sg:tags":[
        "accomodation"
    ],
    "wof:name":"London Road Business Centre",
    "wof:placetype":"venue"
},
  "geometry": {"coordinates":[-2.9721679688,53.409324646],"type":"Point"}
}