{
  "type": "Feature",
  "properties": {
    "iso:country":"GB",
    "sg:address":"57 Toler Rd",
    "sg:city":"Nuneaton",
    "sg:classifiers":[
        {
            "category":"Retail",
            "subcategory":"Driving School",
            "type":"Services"
        }
    ],
    "sg:phone":"+44 24 7634 1840",
    "sg:postcode":"CV11 5EP",
    "sg:province":"Leicestershire",
    "sg:tags":[
        "instruction",
        "cycling",
        "motor"
    ],
    "wof:name":"Ace",
    "wof:placetype":"venue"
},
  "geometry": {"coordinates":[-1.475076,52.528671],"type":"Point"}
}