{
  "type": "Feature",
  "properties": {
    "addr:full":"Abbeyfield House, 89-91 Stradella Road London Greater London SE24 9HL",
    "addr:housenumber":"89-91",
    "addr:postcode":"se24 9hl",
    "addr:street":"Stradella Road",
    "iso:country":"GB",
    "sg:address":"Abbeyfield House, 89-91 Stradella Road",
    "sg:city":"London",
    "sg:classifiers":[
        {
            "category":"Organizations",
            "subcategory":"Community Association",
            "type":"Services"
        }
    ],
    "sg:phone":"+44 20 7274 5177",
    "sg:postcode":"SE24 9HL",
    "sg:province":"Greater London",
    "sg:tags":[
        "society",
        "housing"
    ],
    "wof:name":"Abbeyfield Dulwich Society",
    "wof:placetype":"venue"
},
  "geometry": {"coordinates":[-0.0961000025,51.4505271912],"type":"Point"}
}