{
  "type": "Feature",
  "properties": {
    "iso:country":"GB",
    "sg:address":"40 The Ridgeway",
    "sg:city":"London",
    "sg:classifiers":[
        {
            "category":"Professional",
            "type":"Services"
        },
        {
            "category":"Building & Trades",
            "subcategory":"Cleaning & Sanitation",
            "type":"Services"
        }
    ],
    "sg:phone":"+44 20 8524 4320",
    "sg:postcode":"E4 6PU",
    "sg:province":"Greater London",
    "sg:tags":[
        "sweep",
        "chimney",
        "caterer"
    ],
    "wof:name":"Affordable Top Class Buffets",
    "wof:placetype":"venue"
},
  "geometry": {"coordinates":[-0.00832,51.626999],"type":"Point"}
}