{
  "type": "Feature",
  "properties": {
    "addr:full":"1c Station Square, Flitwick Bedford Bedfordshire MK45 1DP",
    "addr:housenumber":"1c",
    "addr:postcode":"mk45 1dp",
    "addr:street":"Station Square",
    "iso:country":"GB",
    "sg:address":"1c Station Square, Flitwick",
    "sg:city":"Bedford",
    "sg:classifiers":[
        {
            "category":"Fast Food",
            "type":"Food & Drink"
        }
    ],
    "sg:phone":"+44 1525 716000",
    "sg:postcode":"MK45 1DP",
    "sg:province":"Bedfordshire",
    "sg:tags":[
        "away",
        "take"
    ],
    "wof:name":"Flitwick Sandwich Bar",
    "wof:placetype":"venue"
},
  "geometry": {"coordinates":[-0.4940899909,52.0033912659],"type":"Point"}
}