{
  "type": "Feature",
  "properties": {
    "addr:full":"34 Loughborough Rd Loughborough Leicestershire LE12 8HT",
    "addr:housenumber":"34",
    "addr:postcode":"le12 8ht",
    "addr:street":"Loughborough Rd",
    "iso:country":"GB",
    "sg:address":"34 Loughborough Rd",
    "sg:city":"Loughborough",
    "sg:classifiers":[
        {
            "category":"Retail",
            "subcategory":"Driving School",
            "type":"Services"
        }
    ],
    "sg:phone":"+44 1509 880598",
    "sg:postcode":"LE12 8HT",
    "sg:province":"Leicestershire",
    "wof:name":"Rod Chapman Driving School",
    "wof:placetype":"venue"
},
  "geometry": {"coordinates":[-1.176381,52.745644],"type":"Point"}
}