{
  "type": "Feature",
  "properties": {
    "iso:country":"GB",
    "sg:address":"P O Box 44, Rutland Knitting Mill, Tootal Street",
    "sg:city":"Wakefield",
    "sg:classifiers":[
        {
            "category":"Manufacturing",
            "subcategory":"Textiles",
            "type":"Manufacturing & Wholesale Goods"
        }
    ],
    "sg:phone":"+44 1924 379707",
    "sg:postcode":"WF1 5JN",
    "sg:province":"West Yorkshire",
    "sg:tags":[
        "knitwear"
    ],
    "wof:name":"Caddies Wainwright Ltd.",
    "wof:placetype":"venue"
},
  "geometry": {"coordinates":[-1.49043,53.675442],"type":"Point"}
}