{
  "type": "Feature",
  "properties": {
    "addr:full":"101 Clarence Road Fleet Hampshire GU51 3RS",
    "addr:housenumber":"101",
    "addr:postcode":"gu51 3rs",
    "addr:street":"Clarence Road",
    "iso:country":"GB",
    "sg:address":"101 Clarence Road",
    "sg:city":"Fleet",
    "sg:classifiers":[
        {
            "category":"Professional",
            "subcategory":"Engineering",
            "type":"Services"
        },
        {
            "category":"Building & Trades",
            "subcategory":"Electrical",
            "type":"Services"
        }
    ],
    "sg:phone":"+44 1252 617873",
    "sg:postcode":"GU51 3RS",
    "sg:province":"Hampshire",
    "sg:tags":[
        "engineer",
        "electrician",
        "contractor"
    ],
    "wof:name":"Cooper & West Electrical Services",
    "wof:placetype":"venue"
},
  "geometry": {"coordinates":[-0.8396,51.279938],"type":"Point"}
}