{
  "type": "Feature",
  "properties": {
    "addr:full":"26 Speedwell Drive, Heswall Wirral Merseyside CH60 2SZ",
    "addr:housenumber":"26",
    "addr:postcode":"ch60 2sz",
    "addr:street":"Speedwell Drive",
    "iso:country":"GB",
    "sg:address":"26 Speedwell Drive, Heswall",
    "sg:city":"Wirral",
    "sg:classifiers":[
        {
            "category":"Professional",
            "subcategory":"Engineering",
            "type":"Services"
        },
        {
            "category":"Building & Trades",
            "subcategory":"Electrical",
            "type":"Services"
        }
    ],
    "sg:phone":"+44 151 342 7733",
    "sg:postcode":"CH60 2SZ",
    "sg:province":"Merseyside",
    "sg:tags":[
        "engineer",
        "electrician",
        "contractor"
    ],
    "wof:name":"Dee Electrical",
    "wof:placetype":"venue"
},
  "geometry": {"coordinates":[-3.078519,53.329094],"type":"Point"}
}