{
  "type": "Feature",
  "properties": {
    "addr:full":"18 Gwyndy Road, Undy, Magor Caldicot Monmouthshire NP26 3QE",
    "addr:housenumber":"18",
    "addr:postcode":"np26 3qe",
    "addr:street":"Gwyndy Road",
    "iso:country":"GB",
    "sg:address":"18 Gwyndy Road, Undy, Magor",
    "sg:city":"Caldicot",
    "sg:classifiers":[
        {
            "category":"Professional",
            "subcategory":"Management & Consulting",
            "type":"Services"
        }
    ],
    "sg:phone":"+44 1633 881339",
    "sg:postcode":"NP26 3QE",
    "sg:province":"Monmouthshire",
    "sg:tags":[
        "consultant",
        "business"
    ],
    "wof:name":"C N Huxtable Development",
    "wof:placetype":"venue"
},
  "geometry": {"coordinates":[-2.7480449677,51.5859565735],"type":"Point"}
}