{
  "type": "Feature",
  "properties": {
    "addr:full":"13 Whiston Vale, Whiston Rotherham South Yorkshire S60 4JJ",
    "addr:housenumber":"13",
    "addr:postcode":"s60 4jj",
    "addr:street":"Whiston Vale",
    "iso:country":"GB",
    "sg:address":"13 Whiston Vale, Whiston",
    "sg:city":"Rotherham",
    "sg:classifiers":[
        {
            "category":"Building & Trades",
            "subcategory":"Construction",
            "type":"Services"
        }
    ],
    "sg:phone":"+44 1709 378340",
    "sg:postcode":"S60 4JJ",
    "sg:province":"South Yorkshire",
    "sg:tags":[
        "dry",
        "lining",
        "plasterers",
        "screeders"
    ],
    "wof:name":"T Gormley & Son",
    "wof:placetype":"venue"
},
  "geometry": {"coordinates":[-1.3301019669,53.4030227661],"type":"Point"}
}