{
  "type": "Feature",
  "properties": {
    "addr:full":"11 Lon Fach Cardiff Cardiff CF14 6DY",
    "addr:housenumber":"11",
    "addr:postcode":"cf14 6dy",
    "addr:street":"Lon Fach",
    "iso:country":"GB",
    "sg:address":"11 Lon Fach",
    "sg:city":"Cardiff",
    "sg:classifiers":[
        {
            "category":"Shopping",
            "subcategory":"Clothing, Apparel, & Fashions",
            "type":"Retail Goods"
        }
    ],
    "sg:postcode":"CF14 6DY",
    "sg:province":"Cardiff",
    "sg:tags":[
        "shop"
    ],
    "wof:name":"Poppins",
    "wof:placetype":"venue"
},
  "geometry": {"coordinates":[-3.2128388882,51.5221786499],"type":"Point"}
}