{
  "type": "Feature",
  "properties": {
    "iso:country":"GB",
    "sg:address":"70 Sovereigns Arc, Kingsway Centre",
    "sg:city":"Newport",
    "sg:classifiers":[
        {
            "category":"Shopping",
            "subcategory":"Stationery & Office Supplies",
            "type":"Retail Goods"
        }
    ],
    "sg:phone":"+44 1633 220332",
    "sg:postcode":"NP9 1PL",
    "sg:province":"East Riding of Yorkshire",
    "wof:name":"Partners The Stationers",
    "wof:placetype":"venue"
},
  "geometry": {"coordinates":[-2.994498,51.588814],"type":"Point"}
}