{
  "type": "Feature",
  "properties": {
    "iso:country":"GB",
    "sg:address":"57 Lincoln Road",
    "sg:city":"Peterborough",
    "sg:classifiers":[
        {
            "category":"Organizations",
            "subcategory":"Community Association",
            "type":"Services"
        }
    ],
    "sg:phone":"+44 1733 295400",
    "sg:postcode":"PE1 2RR",
    "sg:province":"Cambridgeshire",
    "sg:tags":[
        "associations",
        "housing",
        "co-operatives",
        "society",
        "trust",
        "societies"
    ],
    "wof:name":"NENE HOUSING SOCIETY LTD",
    "wof:placetype":"venue"
},
  "geometry": {"coordinates":[-0.243486,52.57729],"type":"Point"}
}