{
  "type": "Feature",
  "properties": {
    "addr:full":"57 St James Avenue Farnham Surrey GU9 9QF",
    "addr:housenumber":"57",
    "addr:postcode":"gu9 9qf",
    "addr:street":"St James Avenue",
    "iso:country":"GB",
    "sg:address":"57 St James Avenue",
    "sg:city":"Farnham",
    "sg:classifiers":[
        {
            "category":"Building & Trades",
            "subcategory":"Construction",
            "type":"Services"
        }
    ],
    "sg:postcode":"GU9 9QF",
    "sg:province":"Surrey",
    "sg:tags":[
        "roofing"
    ],
    "wof:name":"Albert J Bryant",
    "wof:placetype":"venue"
},
  "geometry": {"coordinates":[-0.789798975,51.2203216553],"type":"Point"}
}