{
  "type": "Feature",
  "properties": {
    "addr:full":"6 King Cross Street Halifax West Yorkshire HX1 2SH",
    "addr:housenumber":"6",
    "addr:postcode":"hx1 2sh",
    "addr:street":"King Cross Street",
    "iso:country":"GB",
    "sg:address":"6 King Cross Street",
    "sg:city":"Halifax",
    "sg:classifiers":[
        {
            "category":"Wholesale",
            "subcategory":"Electrical",
            "type":"Manufacturing & Wholesale Goods"
        },
        {
            "category":"Shopping",
            "subcategory":"Computers & Home Electronics",
            "type":"Retail Goods"
        }
    ],
    "sg:phone":"+44 1422 342724",
    "sg:postcode":"HX1 2SH",
    "sg:province":"West Yorkshire",
    "sg:tags":[
        "wholesaler"
    ],
    "wof:name":"J & J Electrical Wholesalers",
    "wof:placetype":"venue"
},
  "geometry": {"coordinates":[-1.8654019833,53.7212715149],"type":"Point"}
}