{
  "type": "Feature",
  "properties": {
    "addr:full":"9 Priors Clo Blackburn Lancashire BB2 7BB",
    "addr:housenumber":"9",
    "addr:postcode":"bb2 7bb",
    "addr:street":"Priors Clo",
    "iso:country":"GB",
    "sg:address":"9 Priors Clo",
    "sg:city":"Blackburn",
    "sg:classifiers":[
        {
            "category":"Building & Trades",
            "subcategory":"Construction",
            "type":"Services"
        }
    ],
    "sg:postcode":"BB2 7BB",
    "sg:province":"Lancashire",
    "sg:tags":[
        "glazier"
    ],
    "wof:name":"J Dickinson",
    "wof:placetype":"venue"
},
  "geometry": {"coordinates":[-2.511254,53.753632],"type":"Point"}
}