{
  "type": "Feature",
  "properties": {
    "addr:full":"Unit 1 Macclesfield Cheshire SK10 3LN",
    "addr:housenumber":"unit 1",
    "addr:postcode":"sk10 3ln",
    "iso:country":"GB",
    "sg:address":"Unit 1",
    "sg:city":"Macclesfield",
    "sg:classifiers":[
        {
            "category":"Retail",
            "subcategory":"Auto Repair",
            "type":"Services"
        }
    ],
    "sg:phone":"+44 1625 501706",
    "sg:postcode":"SK10 3LN",
    "sg:province":"Cheshire",
    "sg:tags":[
        "modification",
        "garage"
    ],
    "wof:name":"Calvin Wyhatt Ford Specialist",
    "wof:placetype":"venue"
},
  "geometry": {"coordinates":[-2.16443,53.25845],"type":"Point"}
}