{
  "type": "Feature",
  "properties": {
    "addr:full":"Mapperley, Morley Ilkeston Derbyshire DE7 6DE",
    "addr:postcode":"de7 6de",
    "iso:country":"GB",
    "sg:address":"Mapperley, Morley",
    "sg:city":"Ilkeston",
    "sg:classifiers":[
        {
            "category":"Farming",
            "subcategory":"Livestock Farm",
            "type":"Manufacturing & Wholesale Goods"
        }
    ],
    "sg:phone":"+44 115 932 0600",
    "sg:postcode":"DE7 6DE",
    "sg:province":"Derbyshire",
    "sg:tags":[
        "others"
    ],
    "wof:name":"Thomas Shaw",
    "wof:placetype":"venue"
},
  "geometry": {"coordinates":[-1.353904,52.983421],"type":"Point"}
}