{
  "type": "Feature",
  "properties": {
    "addr:full":"52 Coldharbour La Brixton Greater London SW9 8PS",
    "addr:housenumber":"52",
    "addr:postcode":"sw9 8ps",
    "addr:street":"Coldharbour La Brixton",
    "iso:country":"GB",
    "sg:address":"52 Coldharbour La",
    "sg:city":"Brixton",
    "sg:classifiers":[
        {
            "category":"Shopping",
            "subcategory":"Clothing, Apparel, & Fashions",
            "type":"Retail Goods"
        }
    ],
    "sg:phone":"+44 20 7733 8115",
    "sg:postcode":"SW9 8PS",
    "sg:province":"Greater London",
    "sg:tags":[
        "ladieswear"
    ],
    "wof:name":"Tiffanys Boutique",
    "wof:placetype":"venue"
},
  "geometry": {"coordinates":[-0.101584,51.466259],"type":"Point"}
}