{
  "type": "Feature",
  "properties": {
    "iso:country":"GB",
    "sg:address":"Cedar Tree House, Main Street, Farthingstone",
    "sg:city":"Towcester",
    "sg:classifiers":[
        {
            "category":"Communications",
            "subcategory":"Film & Video Production",
            "type":"Services"
        },
        {
            "category":"Wholesale",
            "subcategory":"Music Publishers",
            "type":"Manufacturing & Wholesale Goods"
        }
    ],
    "sg:phone":"+44 1327 360820",
    "sg:postcode":"NN12 8EZ",
    "sg:province":"Buckinghamshire",
    "sg:tags":[
        "sound",
        "recording",
        "studio"
    ],
    "wof:name":"Studio G Ltd.",
    "wof:placetype":"venue"
},
  "geometry": {"coordinates":[-1.103199,52.190117],"type":"Point"}
}