{
  "type": "Feature",
  "properties": {
    "iso:country":"GB",
    "sg:address":"Unit 3, Cholton Park Trading Estate, 419-421 Barlow Moor Road",
    "sg:city":"Manchester",
    "sg:classifiers":[
        {
            "category":"Retail",
            "subcategory":"Auto Repair",
            "type":"Services"
        }
    ],
    "sg:phone":"+44 161 881 1101",
    "sg:postcode":"M21 8ER",
    "sg:province":"Cheshire",
    "sg:tags":[
        "modification",
        "garage"
    ],
    "wof:name":"International Body Styling",
    "wof:placetype":"venue"
},
  "geometry": {"coordinates":[-2.27313,53.43465],"type":"Point"}
}