{
  "type": "Feature",
  "properties": {
    "addr:full":"121 Week St Maidstone Kent ME14 1RB",
    "addr:housenumber":"121",
    "addr:postcode":"me14 1rb",
    "addr:street":"Week St",
    "iso:country":"GB",
    "sg:address":"121 Week St",
    "sg:city":"Maidstone",
    "sg:classifiers":[
        {
            "category":"Personal",
            "subcategory":"Nail Salon",
            "type":"Services"
        }
    ],
    "sg:phone":"+44 1622 687427",
    "sg:postcode":"ME14 1RB",
    "sg:province":"Kent",
    "sg:tags":[
        "solarium",
        "tanning"
    ],
    "wof:name":"The Tanning Shop",
    "wof:placetype":"venue"
},
  "geometry": {"coordinates":[0.521736,51.2771],"type":"Point"}
}