{
  "type": "Feature",
  "properties": {
    "iso:country":"GB",
    "sg:address":"33 Abbeygate St",
    "sg:city":"Bury St Edmunds",
    "sg:classifiers":[
        {
            "category":"Retail",
            "subcategory":"Photofinishing",
            "type":"Services"
        }
    ],
    "sg:phone":"+44 1284 753131",
    "sg:postcode":"IP33 1LW",
    "sg:province":"Suffolk",
    "sg:tags":[
        "photographic",
        "processor"
    ],
    "wof:name":"Fotostop Express",
    "wof:placetype":"venue"
},
  "geometry": {"coordinates":[0.7158460021,52.2449302673],"type":"Point"}
}