{
  "type": "Feature",
  "properties": {
    "addr:full":"17 Sherwood Road Bromsgrove Worcestershire B60 3DR",
    "addr:housenumber":"17",
    "addr:postcode":"b60 3dr",
    "addr:street":"Sherwood Road",
    "iso:country":"GB",
    "sg:address":"17 Sherwood Road",
    "sg:city":"Bromsgrove",
    "sg:classifiers":[
        {
            "category":"Home & Garden",
            "subcategory":"Hardware",
            "type":"Retail Goods"
        }
    ],
    "sg:phone":"+44 1527 870730",
    "sg:postcode":"B60 3DR",
    "sg:province":"Worcestershire",
    "sg:tags":[
        "heat",
        "mech",
        "exchanger"
    ],
    "wof:name":"ARRENSHAW (GENERAL ENGINEERS) LTD",
    "wof:placetype":"venue"
},
  "geometry": {"coordinates":[-2.056645,52.320236],"type":"Point"}
}