{
  "type": "Feature",
  "properties": {
    "addr:full":"13 Langdale Drive, Long Eaton Nottingham Derbyshire NG10 3PQ",
    "addr:housenumber":"13",
    "addr:postcode":"ng10 3pq",
    "addr:street":"Langdale Drive",
    "iso:country":"GB",
    "sg:address":"13 Langdale Drive, Long Eaton",
    "sg:city":"Nottingham",
    "sg:classifiers":[
        {
            "category":"Building & Trades",
            "subcategory":"Landscaping Services",
            "type":"Services"
        }
    ],
    "sg:phone":"+44 115 972 3124",
    "sg:postcode":"NG10 3PQ",
    "sg:province":"Derbyshire",
    "sg:tags":[
        "landscape",
        "contractor"
    ],
    "wof:name":"All Seasons Landscape & Gardening Services",
    "wof:placetype":"venue"
},
  "geometry": {"coordinates":[-1.3007169962,52.8896903992],"type":"Point"}
}