{
  "type": "Feature",
  "properties": {
    "addr:full":"8 Manchester Square London Greater London W1U 3PH",
    "addr:housenumber":"8",
    "addr:postcode":"w1u 3ph",
    "addr:street":"Manchester Square",
    "iso:country":"GB",
    "sg:address":"8 Manchester Square",
    "sg:city":"London",
    "sg:classifiers":[
        {
            "category":"Professional",
            "subcategory":"Business Services",
            "type":"Services"
        }
    ],
    "sg:phone":"+44 20 7535 3800",
    "sg:postcode":"W1U 3PH",
    "sg:province":"Greater London",
    "sg:tags":[
        "holding"
    ],
    "wof:name":"Pentland Group Plc",
    "wof:placetype":"venue"
},
  "geometry": {"coordinates":[-0.152653,51.516369],"type":"Point"}
}