{
  "type": "Feature",
  "properties": {
    "iso:country":"GB",
    "sg:address":"Shore Road",
    "sg:city":"Dornoch",
    "sg:classifiers":[
        {
            "category":"Health Services",
            "subcategory":"Doctor",
            "type":"Services"
        }
    ],
    "sg:phone":"+44 1862 810213",
    "sg:postcode":"IV25 3LS",
    "sg:province":"Highland",
    "sg:tags":[
        "practitioners"
    ],
    "wof:name":"Dornoch Medical Practice",
    "wof:placetype":"venue"
},
  "geometry": {"coordinates":[-4.028389,57.879475],"type":"Point"}
}