{
  "type": "Feature",
  "properties": {
    "iso:country":"GB",
    "sg:address":"Sadlers Green, Rusper Rd",
    "sg:city":"Crawley",
    "sg:classifiers":[
        {
            "category":"Building & Trades",
            "subcategory":"Construction",
            "type":"Services"
        }
    ],
    "sg:phone":"+44 1293 530532",
    "sg:postcode":"RH11 0HU",
    "sg:province":"West Sussex",
    "sg:tags":[
        "decorator",
        "painter"
    ],
    "wof:name":"Fourmost Decorating",
    "wof:placetype":"venue"
},
  "geometry": {"coordinates":[-0.21846,51.11689],"type":"Point"}
}