{
  "type": "Feature",
  "properties": {
    "iso:country":"GB",
    "sg:address":"1 Lynedoch Place",
    "sg:city":"Edinburgh",
    "sg:classifiers":[
        {
            "category":"Shopping",
            "subcategory":"Pharmacy",
            "type":"Retail Goods"
        }
    ],
    "sg:phone":"+44 131 225 5121",
    "sg:postcode":"EH3 7PX",
    "sg:province":"City of Edinburgh",
    "sg:tags":[
        "store",
        "drug"
    ],
    "wof:name":"A Mcwhinnie",
    "wof:placetype":"venue"
},
  "geometry": {"coordinates":[-3.214981,55.952438],"type":"Point"}
}