{
  "type": "Feature",
  "properties": {
    "iso:country":"GB",
    "sg:address":"61 Meredith Rd",
    "sg:city":"Clacton On Sea",
    "sg:classifiers":[
        {
            "category":"Health Services",
            "subcategory":"Podiatrist",
            "type":"Services"
        }
    ],
    "sg:phone":"+44 1255 254595",
    "sg:postcode":"CO15 3AG",
    "sg:province":"Essex",
    "sg:tags":[
        "podiatrists",
        "chiropodist"
    ],
    "wof:name":"Victor Graham A.Ch.p",
    "wof:placetype":"venue"
},
  "geometry": {"coordinates":[1.1487209797,51.7932891846],"type":"Point"}
}