{
  "type": "Feature",
  "properties": {
    "iso:country":"GB",
    "sg:address":"137 Moulsham Street",
    "sg:city":"Chelmsford",
    "sg:classifiers":[
        {
            "category":"Fast Food",
            "type":"Food & Drink"
        }
    ],
    "sg:phone":"+44 1245 496636",
    "sg:postcode":"CM2 0JT",
    "sg:province":"Essex",
    "sg:tags":[
        "away",
        "take"
    ],
    "wof:name":"Shapla Indian Takeaway",
    "wof:placetype":"venue"
},
  "geometry": {"coordinates":[0.467613,51.727074],"type":"Point"}
}