{
  "type": "Feature",
  "properties": {
    "addr:full":"Eurocam Technology Park, Chase Way Bradford West Yorkshire BD5 8HW",
    "addr:postcode":"bd5 8hw",
    "addr:street":"Chase Way",
    "iso:country":"GB",
    "sg:address":"Eurocam Technology Park, Chase Way",
    "sg:city":"Bradford",
    "sg:classifiers":[
        {
            "category":"Manufacturing",
            "subcategory":"Electronics",
            "type":"Manufacturing & Wholesale Goods"
        }
    ],
    "sg:phone":"+44 1274 225050",
    "sg:postcode":"BD5 8HW",
    "sg:province":"West Yorkshire",
    "sg:tags":[
        "control",
        "component",
        "-",
        "electronic"
    ],
    "wof:name":"Chase Advanced Technologies Ltd.",
    "wof:placetype":"venue"
},
  "geometry": {"coordinates":[-1.76024,53.7715],"type":"Point"}
}