{
  "type": "Feature",
  "properties": {
    "addr:full":"50 Moor Mead Road Twickenham Greater London TW1 1JS",
    "addr:housenumber":"50",
    "addr:postcode":"tw1 1js",
    "addr:street":"Moor Mead Road",
    "iso:country":"GB",
    "sg:address":"50 Moor Mead Road",
    "sg:city":"Twickenham",
    "sg:classifiers":[
        {
            "category":"Real Estate",
            "subcategory":"Architect",
            "type":"Services"
        }
    ],
    "sg:phone":"+44 20 8892 1475",
    "sg:postcode":"TW1 1JS",
    "sg:province":"Greater London",
    "wof:name":"Terry Thompson Associates",
    "wof:placetype":"venue"
},
  "geometry": {"coordinates":[-0.324825,51.453083],"type":"Point"}
}