{
  "type": "Feature",
  "properties": {
    "iso:country":"GB",
    "sg:address":"Lion St",
    "sg:city":"Brecon",
    "sg:classifiers":[
        {
            "category":"Government",
            "subcategory":"City Hall",
            "type":"Public Place"
        }
    ],
    "sg:phone":"+44 1874 622177",
    "sg:postcode":"LD3 7AY",
    "sg:province":"Powys",
    "wof:name":"Bishop Bevan Hall",
    "wof:placetype":"venue"
},
  "geometry": {"coordinates":[-3.32502,51.92905],"type":"Point"}
}