{
  "type": "Feature",
  "properties": {
    "addr:full":"200 Chester Road Sunderland Tyne and Wear SR4 7HF",
    "addr:housenumber":"200",
    "addr:postcode":"sr4 7hf",
    "addr:street":"Chester Road",
    "iso:country":"GB",
    "sg:address":"200 Chester Road",
    "sg:city":"Sunderland",
    "sg:classifiers":[
        {
            "category":"Retail",
            "subcategory":"Funeral Services",
            "type":"Services"
        },
        {
            "category":"Shopping",
            "subcategory":"Florist",
            "type":"Retail Goods"
        }
    ],
    "sg:phone":"+44 191 510 2960",
    "sg:postcode":"SR4 7HF",
    "sg:province":"Tyne and Wear",
    "wof:name":"A & N Duckworth's",
    "wof:placetype":"venue"
},
  "geometry": {"coordinates":[-1.401713,54.902229],"type":"Point"}
}