{
  "type": "Feature",
  "properties": {
    "iso:country":"GB",
    "sg:address":"129 Shanklin Dr",
    "sg:city":"Leicester",
    "sg:classifiers":[
        {
            "category":"Professional",
            "subcategory":"Advertising",
            "type":"Services"
        }
    ],
    "sg:postcode":"LE2 3QF",
    "sg:province":"Leicestershire",
    "sg:tags":[
        "agency"
    ],
    "wof:name":"Town Crier Promotions",
    "wof:placetype":"venue"
},
  "geometry": {"coordinates":[-1.105774,52.604862],"type":"Point"}
}