{
  "type": "Feature",
  "properties": {
    "addr:full":"1 Meadow End, Long Hope Gloucester Gloucestershire GL17 0LU",
    "addr:housenumber":"1",
    "addr:postcode":"gl17 0lu",
    "addr:street":"Meadow End Long",
    "iso:country":"GB",
    "sg:address":"1 Meadow End, Long Hope",
    "sg:city":"Gloucester",
    "sg:classifiers":[
        {
            "category":"Freight",
            "type":"Transportation"
        }
    ],
    "sg:postcode":"GL17 0LU",
    "sg:province":"Gloucestershire",
    "sg:tags":[
        "haulage",
        "road"
    ],
    "wof:name":"Pearce Transport",
    "wof:placetype":"venue"
},
  "geometry": {"coordinates":[-2.4584600925,51.8741950989],"type":"Point"}
}