{
  "type": "Feature",
  "properties": {
    "iso:country":"GB",
    "sg:address":"Studio B, 5a Towngate, Leyland",
    "sg:city":"Leyland",
    "sg:classifiers":[
        {
            "category":"Professional",
            "subcategory":"Computer Services",
            "type":"Services"
        }
    ],
    "sg:phone":"+44 1772 622668",
    "sg:postcode":"PR26 7QL",
    "sg:province":"Lancashire",
    "sg:tags":[
        "consultant"
    ],
    "wof:name":"Imptec Business I T Solutions Ltd",
    "wof:placetype":"venue"
},
  "geometry": {"coordinates":[-2.72154,53.701248],"type":"Point"}
}