{
  "type": "Feature",
  "properties": {
    "iso:country":"GB",
    "sg:address":"21 Between Towns Road, Cowley",
    "sg:city":"Oxford",
    "sg:classifiers":[
        {
            "category":"Wholesale",
            "subcategory":"Medical Equipment & Supplies",
            "type":"Manufacturing & Wholesale Goods"
        }
    ],
    "sg:phone":"+44 1865 748844",
    "sg:postcode":"OX4 3LY",
    "sg:province":"Oxfordshire",
    "sg:tags":[
        "hospital"
    ],
    "wof:name":"Becton Dickinson U K Ltd.",
    "wof:placetype":"venue"
},
  "geometry": {"coordinates":[-1.213528,51.732754],"type":"Point"}
}