{
  "type": "Feature",
  "properties": {
    "addr:full":"Ashtree Farm, Stockton Road Southam Warwickshire CV47 8LL",
    "addr:postcode":"cv47 8ll",
    "addr:street":"Stockton Road",
    "iso:country":"GB",
    "sg:address":"Ashtree Farm, Stockton Road",
    "sg:city":"Southam",
    "sg:classifiers":[
        {
            "category":"Manufacturing",
            "subcategory":"Lumber",
            "type":"Manufacturing & Wholesale Goods"
        }
    ],
    "sg:phone":"+44 1926 813911",
    "sg:postcode":"CV47 8LL",
    "sg:province":"Warwickshire",
    "sg:tags":[
        "importer",
        "merchants",
        "agent",
        "timber"
    ],
    "wof:name":"Acornchain Ltd.",
    "wof:placetype":"venue"
},
  "geometry": {"coordinates":[-1.361049,52.271946],"type":"Point"}
}