{
  "type": "Feature",
  "properties": {
    "addr:full":"190 Cross Lane Huddersfield West Yorkshire HD4 6DX",
    "addr:housenumber":"190",
    "addr:postcode":"hd4 6dx",
    "addr:street":"Cross Lane",
    "iso:country":"GB",
    "sg:address":"190 Cross Lane",
    "sg:city":"Huddersfield",
    "sg:classifiers":[
        {
            "category":"Food & Beverages",
            "subcategory":"Liquor & Beverages",
            "type":"Retail Goods"
        }
    ],
    "sg:phone":"+44 1484 300014",
    "sg:postcode":"HD4 6DX",
    "sg:province":"West Yorkshire",
    "sg:tags":[
        "beer",
        "spirit",
        "wines"
    ],
    "wof:name":"Virdees",
    "wof:placetype":"venue"
},
  "geometry": {"coordinates":[-1.787444,53.63171],"type":"Point"}
}