{
  "type": "Feature",
  "properties": {
    "addr:full":"9 Jubilee Cres Coventry Warwickshire CV6 3EX",
    "addr:housenumber":"9",
    "addr:postcode":"cv6 3ex",
    "addr:street":"Jubilee Cres",
    "iso:country":"GB",
    "sg:address":"9 Jubilee Cres",
    "sg:city":"Coventry",
    "sg:classifiers":[
        {
            "category":"Manufacturing",
            "subcategory":"Petroleum Products",
            "type":"Manufacturing & Wholesale Goods"
        }
    ],
    "sg:phone":"+44 24 7659 6622",
    "sg:postcode":"CV6 3EX",
    "sg:province":"Warwickshire",
    "sg:tags":[
        "double",
        "glazing"
    ],
    "wof:name":"Warmshield (Midlands) Ltd",
    "wof:placetype":"venue"
},
  "geometry": {"coordinates":[-1.5178749561,52.4313087463],"type":"Point"}
}