{
  "type": "Feature",
  "properties": {
    "addr:full":"Rectory Hall, St. Cuthberts Place Gateshead Tyne and Wear NE8 1TB",
    "addr:postcode":"ne8 1tb",
    "addr:street":"St. Cuthberts Place",
    "iso:country":"GB",
    "sg:address":"Rectory Hall, St. Cuthberts Place",
    "sg:city":"Gateshead",
    "sg:classifiers":[
        {
            "category":"Place Of Worship",
            "type":"Public Place"
        }
    ],
    "sg:phone":"+44 191 477 8588",
    "sg:postcode":"NE8 1TB",
    "sg:province":"Tyne and Wear",
    "wof:name":"Eden Progressive Spiritualist Church",
    "wof:placetype":"venue"
},
  "geometry": {"coordinates":[-1.6020460129,54.9610404968],"type":"Point"}
}