{
  "type": "Feature",
  "properties": {
    "iso:country":"GB",
    "sg:address":"Head Office, 5 King Charles Terr, Sovereign Clo",
    "sg:city":"Whitechapel",
    "sg:classifiers":[
        {
            "category":"Real Estate",
            "subcategory":"Developer",
            "type":"Services"
        }
    ],
    "sg:phone":"+44 20 7680 0400",
    "sg:postcode":"E1 9HL",
    "sg:province":"Greater London",
    "sg:tags":[
        "property"
    ],
    "wof:name":"First Continental Ltd",
    "wof:placetype":"venue"
},
  "geometry": {"coordinates":[-0.05736,51.517979],"type":"Point"}
}