{
  "type": "Feature",
  "properties": {
    "addr:full":"482 Ley Street Ilford Essex IG2 7BZ",
    "addr:housenumber":"482",
    "addr:postcode":"ig2 7bz",
    "addr:street":"Ley Street",
    "iso:country":"GB",
    "sg:address":"482 Ley Street",
    "sg:city":"Ilford",
    "sg:classifiers":[
        {
            "category":"Autos & Motor Vehicles",
            "subcategory":"Automobile Sales",
            "type":"Retail Goods"
        }
    ],
    "sg:phone":"+44 20 8518 6201",
    "sg:postcode":"IG2 7BZ",
    "sg:province":"Essex",
    "sg:tags":[
        "car"
    ],
    "wof:name":"Caledonia Motor Group",
    "wof:placetype":"venue"
},
  "geometry": {"coordinates":[0.0838290006,51.5707015991],"type":"Point"}
}