{
  "type": "Feature",
  "properties": {
    "iso:country":"GB",
    "sg:address":"250 Queensferry Rd",
    "sg:city":"Edinburgh",
    "sg:classifiers":[
        {
            "category":"Home & Garden",
            "subcategory":"Household Appliances",
            "type":"Retail Goods"
        }
    ],
    "sg:phone":"+44 131 315 4363",
    "sg:postcode":"EH4 2BR",
    "sg:province":"City of Edinburgh",
    "sg:tags":[
        "electrical"
    ],
    "wof:name":"Edinburgh Domestic Services",
    "wof:placetype":"venue"
},
  "geometry": {"coordinates":[-3.2483789921,55.9630050659],"type":"Point"}
}