{
  "type": "Feature",
  "properties": {
    "addr:full":"22-23 Market Cross Selby East Riding of Yorkshire YO8 4JS",
    "addr:housenumber":"22-23",
    "addr:postcode":"yo8 4js",
    "addr:street":"Market Cross",
    "iso:country":"GB",
    "sg:address":"22-23 Market Cross",
    "sg:city":"Selby",
    "sg:classifiers":[
        {
            "category":"Home & Garden",
            "subcategory":"Home Furnishings",
            "type":"Retail Goods"
        }
    ],
    "sg:phone":"+44 1757 702071",
    "sg:postcode":"YO8 4JS",
    "sg:province":"East Riding of Yorkshire",
    "sg:tags":[
        "wall",
        "wallpaper",
        "covering"
    ],
    "wof:name":"A G Stanley Ltd.",
    "wof:placetype":"venue"
},
  "geometry": {"coordinates":[-1.0703459978,53.783908844],"type":"Point"}
}