{
  "type": "Feature",
  "properties": {
    "addr:full":"Fellside, 3-4 Lane Ends, Elterwater Ambleside Cumbria LA22 9HN",
    "addr:housenumber":"3-4",
    "addr:postcode":"la22 9hn",
    "addr:street":"Lane Ends",
    "iso:country":"GB",
    "sg:address":"Fellside, 3-4 Lane Ends, Elterwater",
    "sg:city":"Ambleside",
    "sg:classifiers":[
        {
            "category":"Travel",
            "subcategory":"Hotels & Motels",
            "type":"Entertainment"
        }
    ],
    "sg:postcode":"LA22 9HN",
    "sg:province":"Cumbria",
    "sg:tags":[
        "house",
        "self",
        "guest",
        "catering"
    ],
    "wof:name":"Mary E Rice",
    "wof:placetype":"venue"
},
  "geometry": {"coordinates":[-2.9630889893,54.4326057434],"type":"Point"}
}