{
  "type": "Feature",
  "properties": {
    "addr:full":"106 Durnford Street, Stonehouse Plymouth Devon PL1 3QP",
    "addr:housenumber":"106",
    "addr:postcode":"pl1 3qp",
    "addr:street":"Durnford Street",
    "iso:country":"GB",
    "sg:address":"106 Durnford Street, Stonehouse",
    "sg:city":"Plymouth",
    "sg:classifiers":[
        {
            "category":"Building & Trades",
            "subcategory":"Construction",
            "type":"Services"
        }
    ],
    "sg:phone":"+44 1752 265121",
    "sg:postcode":"PL1 3QP",
    "sg:province":"Devon",
    "sg:tags":[
        "builder"
    ],
    "wof:name":"Mayflower Builders",
    "wof:placetype":"venue"
},
  "geometry": {"coordinates":[-4.161665,50.364357],"type":"Point"}
}