{
  "type": "Feature",
  "properties": {
    "iso:country":"GB",
    "sg:address":"79 Grove Park Road",
    "sg:city":"London",
    "sg:classifiers":[
        {
            "category":"Real Estate",
            "subcategory":"Surveying",
            "type":"Services"
        }
    ],
    "sg:phone":"+44 20 8857 4914",
    "sg:postcode":"SE9 4NS",
    "sg:province":"Greater London",
    "sg:tags":[
        "surveyor",
        "quantity"
    ],
    "wof:name":"Biscoe Taylor",
    "wof:placetype":"venue"
},
  "geometry": {"coordinates":[0.03606,51.433399],"type":"Point"}
}