{
  "type": "Feature",
  "properties": {
    "addr:full":"3 Mistletoe Gardens Southampton Hampshire SO31 7HZ",
    "addr:housenumber":"3",
    "addr:postcode":"so31 7hz",
    "addr:street":"Mistletoe Gardens",
    "iso:country":"GB",
    "sg:address":"3 Mistletoe Gardens",
    "sg:city":"Southampton",
    "sg:classifiers":[
        {
            "category":"Wholesale",
            "subcategory":"Electrical",
            "type":"Manufacturing & Wholesale Goods"
        }
    ],
    "sg:phone":"+44 1489 571660",
    "sg:postcode":"SO31 7HZ",
    "sg:province":"Hampshire",
    "sg:tags":[
        "equipment",
        "refrigeration"
    ],
    "wof:name":"N F Refrigeration Services",
    "wof:placetype":"venue"
},
  "geometry": {"coordinates":[-1.2877800465,50.8742294312],"type":"Point"}
}