{
  "type": "Feature",
  "properties": {
    "iso:country":"GB",
    "sg:address":"Queen Street, Thorne",
    "sg:city":"Doncaster",
    "sg:classifiers":[
        {
            "category":"Health Services",
            "subcategory":"Nursing And Care Facility",
            "type":"Services"
        },
        {
            "category":"Social Services",
            "subcategory":"Retirement Home",
            "type":"Services"
        }
    ],
    "sg:phone":"+44 1405 815512",
    "sg:postcode":"DN8 5AQ",
    "sg:province":"East Riding of Yorkshire",
    "sg:tags":[
        "residential"
    ],
    "wof:name":"Adeline House",
    "wof:placetype":"venue"
},
  "geometry": {"coordinates":[-0.961637,53.611591],"type":"Point"}
}