{
  "type": "Feature",
  "properties": {
    "addr:full":"1 Fairfield Street, Leckhampton Cheltenham Gloucestershire GL53 0HS",
    "addr:housenumber":"1",
    "addr:postcode":"gl53 0hs",
    "addr:street":"Fairfield Street",
    "iso:country":"GB",
    "sg:address":"1 Fairfield Street, Leckhampton",
    "sg:city":"Cheltenham",
    "sg:classifiers":[
        {
            "category":"Home & Garden",
            "subcategory":"Hardware",
            "type":"Retail Goods"
        }
    ],
    "sg:phone":"+44 1242 861015",
    "sg:postcode":"GL53 0HS",
    "sg:province":"Gloucestershire",
    "sg:tags":[
        "lawnmowers",
        "machinery"
    ],
    "wof:name":"R D Haidon Horticultural Engineer",
    "wof:placetype":"venue"
},
  "geometry": {"coordinates":[-2.080627,51.885887],"type":"Point"}
}