{
  "type": "Feature",
  "properties": {
    "iso:country":"GB",
    "sg:address":"3 Oak Gro, Bridge Street",
    "sg:city":"Preston",
    "sg:classifiers":[
        {
            "category":"Building & Trades",
            "subcategory":"Construction",
            "type":"Services"
        }
    ],
    "sg:postcode":"PR3 1YB",
    "sg:province":"Lancashire",
    "sg:tags":[
        "window",
        "sale"
    ],
    "wof:name":"Castle View Windows",
    "wof:placetype":"venue"
},
  "geometry": {"coordinates":[-2.77438,53.899349],"type":"Point"}
}