{
  "type": "Feature",
  "properties": {
    "addr:full":"34 Craighall Road Edinburgh City of Edinburgh EH6 4SA",
    "addr:housenumber":"34",
    "addr:postcode":"eh6 4sa",
    "addr:street":"Craighall Road",
    "iso:country":"GB",
    "sg:address":"34 Craighall Road",
    "sg:city":"Edinburgh",
    "sg:classifiers":[
        {
            "category":"Home & Garden",
            "subcategory":"Household Appliances",
            "type":"Retail Goods"
        }
    ],
    "sg:phone":"+44 131 552 0386",
    "sg:postcode":"EH6 4SA",
    "sg:province":"City of Edinburgh",
    "sg:tags":[
        "electrical"
    ],
    "wof:name":"Blackhall Domestic Appliance Centre",
    "wof:placetype":"venue"
},
  "geometry": {"coordinates":[-3.197312,55.977219],"type":"Point"}
}