{
  "type": "Feature",
  "properties": {
    "iso:country":"GB",
    "sg:address":"G5 Warrington Business Park, Long Lane",
    "sg:city":"Warrington",
    "sg:classifiers":[
        {
            "category":"Professional",
            "subcategory":"Computer Services",
            "type":"Services"
        }
    ],
    "sg:phone":"+44 1925 241400",
    "sg:postcode":"WA2 8TX",
    "sg:province":"Cheshire",
    "sg:tags":[
        "system",
        "software"
    ],
    "wof:name":"Webb Systems Ltd.",
    "wof:placetype":"venue"
},
  "geometry": {"coordinates":[-2.589254,53.393826],"type":"Point"}
}