{
  "type": "Feature",
  "properties": {
    "addr:full":"8 South Sq Bradford West Yorkshire BD13 3LD",
    "addr:housenumber":"8",
    "addr:postcode":"bd13 3ld",
    "addr:street":"South Sq",
    "iso:country":"GB",
    "sg:address":"8 South Sq",
    "sg:city":"Bradford",
    "sg:classifiers":[
        {
            "category":"Education",
            "subcategory":"Special Training",
            "type":"Public Place"
        }
    ],
    "sg:phone":"+44 1274 832445",
    "sg:postcode":"BD13 3LD",
    "sg:province":"West Yorkshire",
    "sg:tags":[
        "product",
        "centre"
    ],
    "wof:name":"Top Priority",
    "wof:placetype":"venue"
},
  "geometry": {"coordinates":[-1.851238966,53.7902908325],"type":"Point"}
}