{
  "type": "Feature",
  "properties": {
    "addr:full":"15 Windrush Drive Peterborough Cambridgeshire PE4 7XD",
    "addr:housenumber":"15",
    "addr:postcode":"pe4 7xd",
    "addr:street":"Windrush Drive",
    "iso:country":"GB",
    "sg:address":"15 Windrush Drive",
    "sg:city":"Peterborough",
    "sg:classifiers":[
        {
            "category":"Professional",
            "type":"Services"
        }
    ],
    "sg:phone":"+44 1733 326886",
    "sg:postcode":"PE4 7XD",
    "sg:province":"Cambridgeshire",
    "sg:tags":[
        "entertainer"
    ],
    "wof:name":"Ed Strong Magician",
    "wof:placetype":"venue"
},
  "geometry": {"coordinates":[-0.250528,52.60434],"type":"Point"}
}