{
  "type": "Feature",
  "properties": {
    "addr:full":"Globe Square Dukinfield Greater Manchester SK16 4RG",
    "addr:postcode":"sk16 4rg",
    "addr:street":"Globe Square",
    "iso:country":"GB",
    "sg:address":"Globe Square",
    "sg:city":"Dukinfield",
    "sg:classifiers":[
        {
            "category":"Building & Trades",
            "subcategory":"Construction",
            "type":"Services"
        }
    ],
    "sg:postcode":"SK16 4RG",
    "sg:province":"Greater Manchester",
    "sg:tags":[
        "joinery"
    ],
    "wof:name":"Gl Joinery Ltd",
    "wof:placetype":"venue"
},
  "geometry": {"coordinates":[-2.101294,53.47139],"type":"Point"}
}