{
  "type": "Feature",
  "properties": {
    "iso:country":"GB",
    "sg:address":"Hillhead Street, Milngavie",
    "sg:city":"Glasgow",
    "sg:classifiers":[
        {
            "category":"Education",
            "subcategory":"School",
            "type":"Public Place"
        }
    ],
    "sg:phone":"+44 141 956 1564",
    "sg:postcode":"G62 8AG",
    "sg:province":"East Dunbartonshire",
    "sg:tags":[
        "local",
        "authority"
    ],
    "wof:name":"Milngavie Primary School",
    "wof:placetype":"venue"
},
  "geometry": {"coordinates":[-4.3163108826,55.9426879883],"type":"Point"}
}