{
  "type": "Feature",
  "properties": {
    "iso:country":"GB",
    "sg:address":"3 Emery Down Drive",
    "sg:city":"Fleet",
    "sg:classifiers":[
        {
            "category":"Professional",
            "subcategory":"Management & Consulting",
            "type":"Services"
        }
    ],
    "sg:postcode":"GU51 1BL",
    "sg:province":"Hampshire",
    "sg:tags":[
        "consultant",
        "business"
    ],
    "wof:name":"Mhg Consulting Ltd",
    "wof:placetype":"venue"
},
  "geometry": {"coordinates":[-0.8618440032,51.2909317017],"type":"Point"}
}