{
  "type": "Feature",
  "properties": {
    "iso:country":"GB",
    "sg:address":"5 Barrhill Terrace",
    "sg:city":"Cumnock",
    "sg:classifiers":[
        {
            "category":"Health Services",
            "subcategory":"Podiatrist",
            "type":"Services"
        }
    ],
    "sg:postcode":"KA18 1PT",
    "sg:province":"East Ayrshire",
    "sg:tags":[
        "podiatrists",
        "chiropodist"
    ],
    "wof:name":"Simon Littlejohn",
    "wof:placetype":"venue"
},
  "geometry": {"coordinates":[-4.252785,55.456192],"type":"Point"}
}