{
  "type": "Feature",
  "properties": {
    "addr:full":"2 Orchard Gardens Sutton Surrey SM1 2QD",
    "addr:housenumber":"2",
    "addr:postcode":"sm1 2qd",
    "addr:street":"Orchard Gardens",
    "iso:country":"GB",
    "sg:address":"2 Orchard Gardens",
    "sg:city":"Sutton",
    "sg:classifiers":[
        {
            "category":"Autos & Motor Vehicles",
            "subcategory":"Motorcycle Sales",
            "type":"Retail Goods"
        }
    ],
    "sg:phone":"+44 20 8770 0257",
    "sg:postcode":"SM1 2QD",
    "sg:province":"Surrey",
    "sg:tags":[
        "chauffeur",
        "driven",
        "car"
    ],
    "wof:name":"Parr Chauffeur Hire",
    "wof:placetype":"venue"
},
  "geometry": {"coordinates":[-0.199361,51.366379],"type":"Point"}
}