{
  "type": "Feature",
  "properties": {
    "iso:country":"GB",
    "sg:address":"117 Mount Street",
    "sg:city":"London",
    "sg:classifiers":[
        {
            "category":"Food & Beverages",
            "subcategory":"Meat & Fish",
            "type":"Retail Goods"
        }
    ],
    "sg:phone":"+44 20 7499 5831",
    "sg:postcode":"W1K 3LA",
    "sg:province":"Greater London",
    "sg:tags":[
        "butcher"
    ],
    "wof:name":"Allens Ltd.",
    "wof:placetype":"venue"
},
  "geometry": {"coordinates":[-0.148625,51.510296],"type":"Point"}
}