{
  "type": "Feature",
  "properties": {
    "iso:country":"GB",
    "sg:address":"22 Picton Street",
    "sg:city":"Bristol",
    "sg:classifiers":[
        {
            "category":"Real Estate",
            "subcategory":"Real Estate Agent",
            "type":"Services"
        }
    ],
    "sg:phone":"+44 117 942 5803",
    "sg:postcode":"BS6 5QA",
    "sg:province":"City of Bristol",
    "wof:name":"Dembo & Co",
    "wof:placetype":"venue"
},
  "geometry": {"coordinates":[-2.58893,51.465389],"type":"Point"}
}