{
  "type": "Feature",
  "properties": {
    "iso:country":"GB",
    "sg:address":"60 Midstocket Road",
    "sg:city":"Aberdeen",
    "sg:classifiers":[
        {
            "category":"Health Services",
            "subcategory":"Health Practitioner",
            "type":"Services"
        }
    ],
    "sg:phone":"+44 1224 635644",
    "sg:postcode":"AB15 5JB",
    "sg:province":"Aberdeen City",
    "sg:tags":[
        "physiotherapist"
    ],
    "wof:name":"Beech Grove Clinic",
    "wof:placetype":"venue"
},
  "geometry": {"coordinates":[-2.148274,57.150307],"type":"Point"}
}