{
  "type": "Feature",
  "properties": {
    "iso:country":"GB",
    "sg:address":"61 Boden Road, Hall Grn",
    "sg:city":"Birmingham",
    "sg:classifiers":[
        {
            "category":"Farming",
            "subcategory":"Farm",
            "type":"Manufacturing & Wholesale Goods"
        }
    ],
    "sg:phone":"+44 121 778 1742",
    "sg:postcode":"B28 9DL",
    "sg:province":"West Midlands",
    "sg:tags":[
        "agricultural"
    ],
    "wof:name":"Export Supply International",
    "wof:placetype":"venue"
},
  "geometry": {"coordinates":[-1.8364280462,52.4298858643],"type":"Point"}
}