{
  "type": "Feature",
  "properties": {
    "iso:country":"GB",
    "sg:address":"24 Yarm Lane",
    "sg:city":"Stockton-on-tees",
    "sg:classifiers":[
        {
            "category":"Fast Food",
            "type":"Food & Drink"
        }
    ],
    "sg:phone":"+44 1642 679797",
    "sg:postcode":"TS18 1ET",
    "sg:province":"Durham",
    "sg:tags":[
        "away",
        "take"
    ],
    "wof:name":"The Bite Centre",
    "wof:placetype":"venue"
},
  "geometry": {"coordinates":[-1.3137509823,54.561706543],"type":"Point"}
}