{
  "type": "Feature",
  "properties": {
    "addr:full":"Park Road Newcastle-upon-tyne Tyne and Wear NE4 7EP",
    "addr:postcode":"ne4 7ep",
    "addr:street":"Park Road",
    "iso:country":"GB",
    "sg:address":"Park Road",
    "sg:city":"Newcastle-upon-tyne",
    "sg:classifiers":[
        {
            "category":"Parking",
            "type":"Transportation"
        }
    ],
    "sg:phone":"+44 191 273 0484",
    "sg:postcode":"NE4 7EP",
    "sg:province":"Tyne and Wear",
    "sg:tags":[
        "car",
        "park"
    ],
    "wof:name":"Hawthorns Multi Storey",
    "wof:placetype":"venue"
},
  "geometry": {"coordinates":[-1.637069,54.968922],"type":"Point"}
}