{
  "type": "Feature",
  "properties": {
    "iso:country":"GB",
    "sg:address":"60 Strathmoor Road, Balmore Industrial Estate",
    "sg:city":"Glasgow",
    "sg:classifiers":[
        {
            "category":"Building & Trades",
            "subcategory":"Construction",
            "type":"Services"
        }
    ],
    "sg:phone":"+44 141 336 3084",
    "sg:postcode":"G22 7DW",
    "sg:province":"Glasgow City",
    "sg:tags":[
        "builder"
    ],
    "wof:name":"Woodside Ltd.",
    "wof:placetype":"venue"
},
  "geometry": {"coordinates":[-4.2566590309,55.8986816406],"type":"Point"}
}