{
  "type": "Feature",
  "properties": {
    "addr:full":"Seadyke Road, Old Leake Boston Lincolnshire PE22 9HX",
    "addr:postcode":"pe22 9hx",
    "addr:street":"Seadyke Road",
    "iso:country":"GB",
    "sg:address":"Seadyke Road, Old Leake",
    "sg:city":"Boston",
    "sg:classifiers":[
        {
            "category":"Building & Trades",
            "subcategory":"Equipment Rental",
            "type":"Services"
        }
    ],
    "sg:phone":"+44 1205 870890",
    "sg:postcode":"PE22 9HX",
    "sg:province":"Lincolnshire",
    "sg:tags":[
        "plant",
        "machinery"
    ],
    "wof:name":"Jeff Royle Plant Hire",
    "wof:placetype":"venue"
},
  "geometry": {"coordinates":[0.097332,53.031929],"type":"Point"}
}