{
  "type": "Feature",
  "properties": {
    "iso:country":"GB",
    "sg:address":"4 Mitchell House, College Cross",
    "sg:city":"London",
    "sg:classifiers":[
        {
            "category":"Building & Trades",
            "subcategory":"Construction",
            "type":"Services"
        }
    ],
    "sg:postcode":"N1 1PS",
    "sg:province":"Greater London",
    "sg:tags":[
        "decorator",
        "painter"
    ],
    "wof:name":"P J Flavin",
    "wof:placetype":"venue"
},
  "geometry": {"coordinates":[-0.105063,51.542427],"type":"Point"}
}