{
  "type": "Feature",
  "properties": {
    "addr:full":"7-8 Osier Way Mitcham Greater London CR4 4NF",
    "addr:housenumber":"7-8",
    "addr:postcode":"cr4 4nf",
    "addr:street":"Osier Way",
    "iso:country":"GB",
    "sg:address":"7-8 Osier Way",
    "sg:city":"Mitcham",
    "sg:classifiers":[
        {
            "category":"Professional",
            "subcategory":"Engineering",
            "type":"Services"
        }
    ],
    "sg:phone":"+44 20 8640 1777",
    "sg:postcode":"CR4 4NF",
    "sg:province":"Greater London",
    "sg:tags":[
        "precision",
        "engineer"
    ],
    "wof:name":"Global Precision Engineering Co",
    "wof:placetype":"venue"
},
  "geometry": {"coordinates":[-0.1686570048,51.394405365],"type":"Point"}
}