{
  "type": "Feature",
  "properties": {
    "addr:full":"2 Canada Close Banbury Oxfordshire OX16 2RT",
    "addr:housenumber":"2",
    "addr:postcode":"ox16 2rt",
    "addr:street":"Canada Close",
    "iso:country":"GB",
    "sg:address":"2 Canada Close",
    "sg:city":"Banbury",
    "sg:classifiers":[
        {
            "category":"Wholesale",
            "subcategory":"Medical Equipment & Supplies",
            "type":"Manufacturing & Wholesale Goods"
        }
    ],
    "sg:phone":"+44 1295 256611",
    "sg:postcode":"OX16 2RT",
    "sg:province":"Oxfordshire",
    "sg:tags":[
        "lubricating",
        "lubrication"
    ],
    "wof:name":"Lincoln Industrial Ltd",
    "wof:placetype":"venue"
},
  "geometry": {"coordinates":[-1.3363,52.069107],"type":"Point"}
}