{
  "type": "Feature",
  "properties": {
    "addr:full":"Davenport Place Watlington Oxfordshire OX49 5QA",
    "addr:postcode":"ox49 5qa",
    "addr:street":"Davenport Place",
    "iso:country":"GB",
    "sg:address":"Davenport Place",
    "sg:city":"Watlington",
    "sg:classifiers":[
        {
            "category":"Education",
            "subcategory":"School",
            "type":"Public Place"
        }
    ],
    "sg:phone":"+44 1491 612474",
    "sg:postcode":"OX49 5QA",
    "sg:province":"Oxfordshire",
    "sg:tags":[
        "local",
        "authority"
    ],
    "wof:name":"Watlington County Primary School",
    "wof:placetype":"venue"
},
  "geometry": {"coordinates":[-1.007488,51.644009],"type":"Point"}
}