{
  "type": "Feature",
  "properties": {
    "addr:full":"20 Church St Norwich Norfolk NR11 8NP",
    "addr:housenumber":"20",
    "addr:postcode":"nr11 8np",
    "addr:street":"Church St",
    "iso:country":"GB",
    "sg:address":"20 Church St",
    "sg:city":"Norwich",
    "sg:classifiers":[
        {
            "category":"Home & Garden",
            "subcategory":"Hardware",
            "type":"Retail Goods"
        }
    ],
    "sg:phone":"+44 1263 834969",
    "sg:postcode":"NR11 8NP",
    "sg:province":"Norfolk",
    "sg:tags":[
        "equipment",
        "heating"
    ],
    "wof:name":"Heatstor UK",
    "wof:placetype":"venue"
},
  "geometry": {"coordinates":[1.3526550531,52.8805885315],"type":"Point"}
}