{
  "type": "Feature",
  "properties": {
    "addr:full":"49 Green St, Old Town Eastbourne East Sussex BN21 1QU",
    "addr:housenumber":"49",
    "addr:postcode":"bn21 1qu",
    "addr:street":"Green St",
    "iso:country":"GB",
    "sg:address":"49 Green St, Old Town",
    "sg:city":"Eastbourne",
    "sg:classifiers":[
        {
            "category":"Shopping",
            "subcategory":"Party Supplies",
            "type":"Retail Goods"
        }
    ],
    "sg:postcode":"BN21 1QU",
    "sg:province":"East Sussex",
    "sg:tags":[
        "equipment",
        "disco"
    ],
    "wof:name":"Eastbourne Disco Supplies",
    "wof:placetype":"venue"
},
  "geometry": {"coordinates":[0.2605729997,50.7738494873],"type":"Point"}
}