{
  "type": "Feature",
  "properties": {
    "addr:full":"Common Rd Retford Nottinghamshire DN22 6LH",
    "addr:postcode":"dn22 6lh",
    "addr:street":"Common Rd",
    "iso:country":"GB",
    "sg:address":"Common Rd",
    "sg:city":"Retford",
    "sg:classifiers":[
        {
            "category":"Building & Trades",
            "subcategory":"Construction",
            "type":"Services"
        }
    ],
    "sg:phone":"+44 1777 705792",
    "sg:postcode":"DN22 6LH",
    "sg:province":"Nottinghamshire",
    "sg:tags":[
        "joinery"
    ],
    "wof:name":"Presley's Bespoke Joinery",
    "wof:placetype":"venue"
},
  "geometry": {"coordinates":[-0.9377670288,53.3217544556],"type":"Point"}
}