{
  "type": "Feature",
  "properties": {
    "addr:full":"White Heather Garage, Richmond Rd Southsea Hampshire PO5 2LN",
    "addr:postcode":"po5 2ln",
    "addr:street":"White;Richmond Rd",
    "iso:country":"GB",
    "sg:address":"White Heather Garage, Richmond Rd",
    "sg:city":"Southsea",
    "sg:classifiers":[
        {
            "category":"Retail",
            "subcategory":"Auto Repair",
            "type":"Services"
        }
    ],
    "sg:postcode":"PO5 2LN",
    "sg:province":"Hampshire",
    "sg:tags":[
        "modification",
        "garage"
    ],
    "wof:name":"Richmond Auto Repairs",
    "wof:placetype":"venue"
},
  "geometry": {"coordinates":[-1.088164,50.784664],"type":"Point"}
}