{
  "type": "Feature",
  "properties": {
    "iso:country":"GB",
    "sg:address":"76a Springett Avenue, Ringmer",
    "sg:city":"Lewes",
    "sg:classifiers":[
        {
            "category":"Personal",
            "subcategory":"Beauty Salon",
            "type":"Services"
        },
        {
            "category":"Personal",
            "subcategory":"Barber",
            "type":"Services"
        }
    ],
    "sg:phone":"+44 1273 812476",
    "sg:postcode":"BN8 5QX",
    "sg:province":"East Sussex",
    "sg:tags":[
        "unisex",
        "hairdresser"
    ],
    "wof:name":"Janet Goldsmith",
    "wof:placetype":"venue"
},
  "geometry": {"coordinates":[0.057556,50.89349],"type":"Point"}
}