{
  "type": "Feature",
  "properties": {
    "iso:country":"GB",
    "sg:address":"12 Heath Terrace",
    "sg:city":"Leamington Spa",
    "sg:classifiers":[
        {
            "category":"Education",
            "subcategory":"Special Training",
            "type":"Public Place"
        }
    ],
    "sg:phone":"+44 1926 335833",
    "sg:postcode":"CV32 5LY",
    "sg:province":"Warwickshire",
    "sg:tags":[
        "product",
        "centre"
    ],
    "wof:name":"Triangle Training",
    "wof:placetype":"venue"
},
  "geometry": {"coordinates":[-1.545741,52.292831],"type":"Point"}
}