{
  "type": "Feature",
  "properties": {
    "addr:full":"278 Derby Road Nottingham Nottinghamshire NG7 1PZ",
    "addr:housenumber":"278",
    "addr:postcode":"ng7 1pz",
    "addr:street":"Derby Road",
    "iso:country":"GB",
    "sg:address":"278 Derby Road",
    "sg:city":"Nottingham",
    "sg:classifiers":[
        {
            "category":"Health Services",
            "subcategory":"Dentist",
            "type":"Services"
        }
    ],
    "sg:phone":"+44 115 941 9015",
    "sg:postcode":"NG7 1PZ",
    "sg:province":"Nottinghamshire",
    "sg:tags":[
        "technician",
        "instrument",
        "dental"
    ],
    "wof:name":"P Gleeson",
    "wof:placetype":"venue"
},
  "geometry": {"coordinates":[-1.1720269918,52.9523200989],"type":"Point"}
}