{
  "type": "Feature",
  "properties": {
    "addr:full":"Pickwell House, Immingham Dock Grimsby Lincolnshire DN40 2LZ",
    "addr:housenumber":"immingham",
    "addr:postcode":"dn40 2lz",
    "addr:street":"Dock Grimsby",
    "iso:country":"GB",
    "sg:address":"Pickwell House, Immingham Dock",
    "sg:city":"Grimsby",
    "sg:classifiers":[
        {
            "category":"Freight",
            "type":"Transportation"
        }
    ],
    "sg:phone":"+44 1469 572415",
    "sg:postcode":"DN40 2LZ",
    "sg:province":"Lincolnshire",
    "sg:tags":[
        "shipping"
    ],
    "wof:name":"Jacob Pickwell & Co. Ltd.",
    "wof:placetype":"venue"
},
  "geometry": {"coordinates":[-0.1862500012,53.6278915405],"type":"Point"}
}