{
  "type": "Feature",
  "properties": {
    "addr:full":"First Floor 44a Charlotte Rd Moorgate Greater London EC2A 3PD",
    "addr:housenumber":"44a",
    "addr:postcode":"ec2a 3pd",
    "addr:street":"Charlotte Rd",
    "iso:country":"GB",
    "sg:address":"First Floor 44a Charlotte Rd",
    "sg:city":"Moorgate",
    "sg:classifiers":[
        {
            "category":"Wholesale",
            "subcategory":"Music Publishers",
            "type":"Manufacturing & Wholesale Goods"
        }
    ],
    "sg:phone":"+44 20 7613 0404",
    "sg:postcode":"EC2A 3PD",
    "sg:province":"Greater London",
    "sg:tags":[
        "record"
    ],
    "wof:name":"Black On Black Records",
    "wof:placetype":"venue"
},
  "geometry": {"coordinates":[-0.080888,51.525295],"type":"Point"}
}