{
  "type": "Feature",
  "properties": {
    "iso:country":"GB",
    "sg:address":"Unit 2 The House Carpenter Shop, The Historic Dockyard",
    "sg:city":"Chatham",
    "sg:classifiers":[
        {
            "category":"Wholesale",
            "subcategory":"Machinery & Supplies",
            "type":"Manufacturing & Wholesale Goods"
        }
    ],
    "sg:phone":"+44 1634 818882",
    "sg:postcode":"ME4 4TE",
    "sg:province":"Kent",
    "sg:tags":[
        "theatrical"
    ],
    "wof:name":"All Hands Designs Uk",
    "wof:placetype":"venue"
},
  "geometry": {"coordinates":[0.52244,51.381889],"type":"Point"}
}