{
  "type": "Feature",
  "properties": {
    "iso:country":"GB",
    "sg:address":"Gatefields Meadow, Shimpling",
    "sg:city":"Bury St Edmunds",
    "sg:classifiers":[
        {
            "category":"Building & Trades",
            "subcategory":"Landscaping Services",
            "type":"Services"
        },
        {
            "category":"Home & Garden",
            "subcategory":"Garden Supply",
            "type":"Retail Goods"
        }
    ],
    "sg:phone":"+44 1284 830171",
    "sg:postcode":"IP29 4EX",
    "sg:province":"Suffolk",
    "sg:tags":[
        "designer",
        "centre",
        "contractor",
        "nursery",
        "architect",
        "landscape"
    ],
    "wof:name":"Landmark Landscape",
    "wof:placetype":"venue"
},
  "geometry": {"coordinates":[0.69389,52.130932],"type":"Point"}
}