{
  "type": "Feature",
  "properties": {
    "addr:full":"The North Street Clinic, 34a North Street, Clapham Old Town London Greater London SW4 0HD",
    "addr:housenumber":"34a",
    "addr:postcode":"sw4 0hd",
    "addr:street":"North Street",
    "iso:country":"GB",
    "sg:address":"The North Street Clinic, 34a North Street, Clapham Old Town",
    "sg:city":"London",
    "sg:classifiers":[
        {
            "category":"Health Services",
            "subcategory":"Health Practitioner",
            "type":"Services"
        },
        {
            "category":"Health Services",
            "subcategory":"Podiatrist",
            "type":"Services"
        }
    ],
    "sg:phone":"+44 20 7627 4901",
    "sg:postcode":"SW4 0HD",
    "sg:province":"Greater London",
    "sg:tags":[
        "podiatrists",
        "osteopath",
        "chiropodist"
    ],
    "wof:name":"Deryck Breinburg",
    "wof:placetype":"venue"
},
  "geometry": {"coordinates":[-0.142602995,51.4668998718],"type":"Point"}
}