{
  "type": "Feature",
  "properties": {
    "addr:full":"89 Belvidere Rd Wallasey Merseyside L45 4RX",
    "addr:housenumber":"89",
    "addr:postcode":"l45 4rx",
    "addr:street":"Belvidere Rd",
    "iso:country":"GB",
    "sg:address":"89 Belvidere Rd",
    "sg:city":"Wallasey",
    "sg:classifiers":[
        {
            "category":"Shopping",
            "subcategory":"Florist",
            "type":"Retail Goods"
        }
    ],
    "sg:phone":"+44 151 691 1257",
    "sg:postcode":"L45 4RX",
    "sg:province":"Merseyside",
    "wof:name":"Peaches & Herbs Florist",
    "wof:placetype":"venue"
},
  "geometry": {"coordinates":[-3.0540859699,53.4235687256],"type":"Point"}
}