{
  "type": "Feature",
  "properties": {
    "addr:full":"116 Kensington Road Southport Lancashire PR9 0SD",
    "addr:housenumber":"116",
    "addr:postcode":"pr9 0sd",
    "addr:street":"Kensington Road",
    "iso:country":"GB",
    "sg:address":"116 Kensington Road",
    "sg:city":"Southport",
    "sg:classifiers":[
        {
            "category":"Professional",
            "subcategory":"Engineering",
            "type":"Services"
        },
        {
            "category":"Building & Trades",
            "subcategory":"Electrical",
            "type":"Services"
        }
    ],
    "sg:phone":"+44 1704 500308",
    "sg:postcode":"PR9 0SD",
    "sg:province":"Lancashire",
    "sg:tags":[
        "engineer",
        "electrician",
        "contractor"
    ],
    "wof:name":"Electrical Contracting Services",
    "wof:placetype":"venue"
},
  "geometry": {"coordinates":[-2.9891560078,53.6440963745],"type":"Point"}
}