{
  "type": "Feature",
  "properties": {
    "addr:full":"Ferry Place, Woolwich High Street, Woolwich London Greater London SE18 6DN",
    "addr:postcode":"se18 6dn",
    "addr:street":"Ferry Place;High Street",
    "iso:country":"GB",
    "sg:address":"Ferry Place, Woolwich High Street, Woolwich",
    "sg:city":"London",
    "sg:classifiers":[
        {
            "category":"Retail",
            "subcategory":"Auto Repair",
            "type":"Services"
        }
    ],
    "sg:phone":"+44 20 8855 7890",
    "sg:postcode":"SE18 6DN",
    "sg:province":"Greater London",
    "sg:tags":[
        "body",
        "car"
    ],
    "wof:name":"Payne Autos",
    "wof:placetype":"venue"
},
  "geometry": {"coordinates":[0.0637800023,51.4937400818],"type":"Point"}
}