{
  "type": "Feature",
  "properties": {
    "addr:full":"39 Balfern Street London Greater London SW11 3EL",
    "addr:housenumber":"39",
    "addr:postcode":"sw11 3el",
    "addr:street":"Balfern Street",
    "iso:country":"GB",
    "sg:address":"39 Balfern Street",
    "sg:city":"London",
    "sg:classifiers":[
        {
            "category":"Wholesale",
            "subcategory":"Office Equipment",
            "type":"Manufacturing & Wholesale Goods"
        },
        {
            "category":"Wholesale",
            "subcategory":"Music Publishers",
            "type":"Manufacturing & Wholesale Goods"
        }
    ],
    "sg:phone":"+44 20 7228 3671",
    "sg:postcode":"SW11 3EL",
    "sg:province":"Greater London",
    "sg:tags":[
        "sound",
        "record",
        "recording",
        "apparatus"
    ],
    "wof:name":"Curious Records Ltd.",
    "wof:placetype":"venue"
},
  "geometry": {"coordinates":[-0.167761,51.472752],"type":"Point"}
}