{
  "type": "Feature",
  "properties": {
    "addr:full":"Dartmouth House, Ryecroft Place Walsall Staffordshire WS3 1SW",
    "addr:postcode":"ws3 1sw",
    "addr:street":"Ryecroft Place",
    "iso:country":"GB",
    "sg:address":"Dartmouth House, Ryecroft Place",
    "sg:city":"Walsall",
    "sg:classifiers":[
        {
            "category":"Community Center",
            "type":"Public Place"
        }
    ],
    "sg:phone":"+44 1922 746328",
    "sg:postcode":"WS3 1SW",
    "sg:province":"Staffordshire",
    "sg:tags":[
        "centre"
    ],
    "wof:name":"Ryecroft Coalpool Resource Centre",
    "wof:placetype":"venue"
},
  "geometry": {"coordinates":[-1.975609,52.60545],"type":"Point"}
}