{
  "type": "Feature",
  "properties": {
    "iso:country":"GB",
    "sg:address":"58 Thorns Rd",
    "sg:city":"Bolton",
    "sg:classifiers":[
        {
            "category":"Shopping",
            "subcategory":"Optical Goods",
            "type":"Retail Goods"
        }
    ],
    "sg:phone":"+44 161 839 9491",
    "sg:postcode":"BL1 6PD",
    "sg:province":"Lancashire",
    "wof:name":"John Mac Spec Cases",
    "wof:placetype":"venue"
},
  "geometry": {"coordinates":[-2.4436180592,53.5990715027],"type":"Point"}
}