{
  "type": "Feature",
  "properties": {
    "iso:country":"GB",
    "sg:address":"5 Ely Valley Road, Talbot Grn",
    "sg:city":"Pontyclun",
    "sg:classifiers":[
        {
            "category":"Personal",
            "subcategory":"Beauty Salon",
            "type":"Services"
        }
    ],
    "sg:phone":"+44 1443 229292",
    "sg:postcode":"CF72 8AL",
    "sg:province":"Bridgend",
    "sg:tags":[
        "unisex",
        "hairdresser"
    ],
    "wof:name":"Shaltons",
    "wof:placetype":"venue"
},
  "geometry": {"coordinates":[-3.3852050304,51.5392341614],"type":"Point"}
}