{
  "type": "Feature",
  "properties": {
    "iso:country":"GB",
    "sg:address":"Black Arrow House, 2 Chandos Road",
    "sg:city":"London",
    "sg:classifiers":[
        {
            "category":"Travel",
            "subcategory":"Travel Agent",
            "type":"Entertainment"
        },
        {
            "category":"Community Center",
            "subcategory":"Youth",
            "type":"Public Place"
        }
    ],
    "sg:phone":"+44 20 8961 1122",
    "sg:postcode":"NW10 6NF",
    "sg:province":"Greater London",
    "sg:tags":[
        "organisation",
        "centre"
    ],
    "wof:name":"World Challenge Expeditions Ltd.",
    "wof:placetype":"venue"
},
  "geometry": {"coordinates":[-0.254867,51.52644],"type":"Point"}
}