{
  "type": "Feature",
  "properties": {
    "addr:full":"Great Ormond St Hospital Fund, 86 Tanners Drive Milton Keynes Buckinghamshire MK14 5BP",
    "addr:housenumber":"86",
    "addr:postcode":"mk14 5bp",
    "addr:street":"Great Ormond St;Tanners Drive",
    "iso:country":"GB",
    "sg:address":"Great Ormond St Hospital Fund, 86 Tanners Drive",
    "sg:city":"Milton Keynes",
    "sg:classifiers":[
        {
            "category":"Organizations",
            "subcategory":"Non-profit Organization",
            "type":"Services"
        }
    ],
    "sg:postcode":"MK14 5BP",
    "sg:province":"Buckinghamshire",
    "sg:tags":[
        "organisation",
        "voluntary",
        "charity"
    ],
    "wof:name":"Clothes Aid",
    "wof:placetype":"venue"
},
  "geometry": {"coordinates":[-0.727749,52.005856],"type":"Point"}
}