{
  "type": "Feature",
  "properties": {
    "iso:country":"GB",
    "sg:address":"Upper Northend, St Catherines",
    "sg:city":"Bath",
    "sg:classifiers":[
        {
            "category":"Transit Center",
            "subcategory":"Passenger",
            "type":"Transportation"
        }
    ],
    "sg:postcode":"BA1 8ES",
    "sg:province":"Bath and North East Somerset",
    "sg:tags":[
        "boarding",
        "kennel",
        "catteries"
    ],
    "wof:name":"New House Farm Kennels",
    "wof:placetype":"venue"
},
  "geometry": {"coordinates":[-2.361167,51.385071],"type":"Point"}
}