{
  "type": "Feature",
  "properties": {
    "addr:full":"177-179 Southwark Bridge Rd Southwark Greater London SE1 0ED",
    "addr:housenumber":"177-179",
    "addr:postcode":"se1 0ed",
    "addr:street":"Southwark Bridge Rd",
    "iso:country":"GB",
    "sg:address":"177-179 Southwark Bridge Rd",
    "sg:city":"Southwark",
    "sg:classifiers":[
        {
            "category":"Health Services",
            "subcategory":"Clinic",
            "type":"Services"
        }
    ],
    "sg:phone":"+44 20 7357 0090",
    "sg:postcode":"SE1 0ED",
    "sg:province":"Greater London",
    "sg:tags":[
        "misuse",
        "alcohol"
    ],
    "wof:name":"Community Alcohol Service",
    "wof:placetype":"venue"
},
  "geometry": {"coordinates":[-0.0979,51.501583],"type":"Point"}
}