{
  "type": "Feature",
  "properties": {
    "iso:country":"GB",
    "sg:address":"122-129 East Reach",
    "sg:city":"Taunton",
    "sg:classifiers":[
        {
            "category":"Autos & Motor Vehicles",
            "subcategory":"Automobile Sales",
            "type":"Retail Goods"
        }
    ],
    "sg:phone":"+44 1823 337258",
    "sg:postcode":"TA1 3HL",
    "sg:province":"Somerset",
    "sg:tags":[
        "car"
    ],
    "wof:name":"East Reach Car Sales",
    "wof:placetype":"venue"
},
  "geometry": {"coordinates":[-3.092779,51.015423],"type":"Point"}
}