{
  "type": "Feature",
  "properties": {
    "addr:full":"Garratt Street Brierley Hill West Midlands DY5 1JU",
    "addr:postcode":"dy5 1ju",
    "addr:street":"Garratt Street",
    "iso:country":"GB",
    "sg:address":"Garratt Street",
    "sg:city":"Brierley Hill",
    "sg:classifiers":[
        {
            "category":"Manufacturing",
            "subcategory":"Metals",
            "type":"Manufacturing & Wholesale Goods"
        },
        {
            "category":"Building & Trades",
            "subcategory":"Construction",
            "type":"Services"
        }
    ],
    "sg:postcode":"DY5 1JU",
    "sg:province":"West Midlands",
    "sg:tags":[
        "steel",
        "fabricator",
        "builder",
        "erectors"
    ],
    "wof:name":"Aztec Building & Fabrication",
    "wof:placetype":"venue"
},
  "geometry": {"coordinates":[-2.114709,52.492081],"type":"Point"}
}