{
  "type": "Feature",
  "properties": {
    "addr:full":"29 St Helens Road Swansea Neath Port Talbot SA1 4AP",
    "addr:housenumber":"29",
    "addr:postcode":"sa1 4ap",
    "addr:street":"St Helens Road",
    "iso:country":"GB",
    "sg:address":"29 St Helens Road",
    "sg:city":"Swansea",
    "sg:classifiers":[
        {
            "category":"Real Estate",
            "subcategory":"Architect",
            "type":"Services"
        }
    ],
    "sg:phone":"+44 1792 455605",
    "sg:postcode":"SA1 4AP",
    "sg:province":"Neath Port Talbot",
    "wof:name":"Owen Short",
    "wof:placetype":"venue"
},
  "geometry": {"coordinates":[-3.952754,51.618053],"type":"Point"}
}