{
  "type": "Feature",
  "properties": {
    "iso:country":"GB",
    "sg:address":"Hillside, London Road",
    "sg:city":"Pulborough",
    "sg:classifiers":[
        {
            "category":"Manufacturing",
            "subcategory":"Rubber & Plastics",
            "type":"Manufacturing & Wholesale Goods"
        }
    ],
    "sg:phone":"+44 1903 892023",
    "sg:postcode":"RH20 3BN",
    "sg:province":"West Sussex",
    "sg:tags":[
        "injection",
        "moulding"
    ],
    "wof:name":"Burrwill Moulds",
    "wof:placetype":"venue"
},
  "geometry": {"coordinates":[-0.403189,50.915016],"type":"Point"}
}