{
  "type": "Feature",
  "properties": {
    "addr:full":"Sudeley House, High Street, Winchcombe Cheltenham Gloucestershire GL54 5LJ",
    "addr:postcode":"gl54 5lj",
    "addr:street":"High Street",
    "iso:country":"GB",
    "sg:address":"Sudeley House, High Street, Winchcombe",
    "sg:city":"Cheltenham",
    "sg:classifiers":[
        {
            "category":"Food & Beverages",
            "subcategory":"Meat & Fish",
            "type":"Retail Goods"
        }
    ],
    "sg:phone":"+44 1242 602998",
    "sg:postcode":"GL54 5LJ",
    "sg:province":"Gloucestershire",
    "sg:tags":[
        "butcher"
    ],
    "wof:name":"Pilcher & Newman",
    "wof:placetype":"venue"
},
  "geometry": {"coordinates":[-1.964353,51.953388],"type":"Point"}
}