{
  "type": "Feature",
  "properties": {
    "addr:full":"51 Station Road, Banks Southport Lancashire PR9 8BB",
    "addr:housenumber":"51",
    "addr:postcode":"pr9 8bb",
    "addr:street":"Station Road",
    "iso:country":"GB",
    "sg:address":"51 Station Road, Banks",
    "sg:city":"Southport",
    "sg:classifiers":[
        {
            "category":"Home & Garden",
            "subcategory":"Garden Supply",
            "type":"Retail Goods"
        }
    ],
    "sg:phone":"+44 1704 507777",
    "sg:postcode":"PR9 8BB",
    "sg:province":"Lancashire",
    "sg:tags":[
        "fertiliser"
    ],
    "wof:name":"Vitagrow (Fertilisers) Ltd",
    "wof:placetype":"venue"
},
  "geometry": {"coordinates":[-2.9269850254,53.6775894165],"type":"Point"}
}