{
  "type": "Feature",
  "properties": {
    "addr:full":"26 High Street Thatcham Berkshire RG19 3JD",
    "addr:housenumber":"26",
    "addr:postcode":"rg19 3jd",
    "addr:street":"High Street",
    "iso:country":"GB",
    "sg:address":"26 High Street",
    "sg:city":"Thatcham",
    "sg:classifiers":[
        {
            "category":"Shopping",
            "subcategory":"Thrift Store",
            "type":"Retail Goods"
        }
    ],
    "sg:phone":"+44 1635 868838",
    "sg:postcode":"RG19 3JD",
    "sg:province":"Berkshire",
    "sg:tags":[
        "shop",
        "charity"
    ],
    "wof:name":"Age Concern England (National Council of",
    "wof:placetype":"venue"
},
  "geometry": {"coordinates":[-1.2594599724,51.4033851624],"type":"Point"}
}