{
  "type": "Feature",
  "properties": {
    "iso:country":"GB",
    "sg:address":"31 Higher Bugle, Bugle",
    "sg:city":"St Austell",
    "sg:classifiers":[
        {
            "category":"Social Services",
            "subcategory":"Retirement Home",
            "type":"Services"
        }
    ],
    "sg:phone":"+44 1726 850472",
    "sg:postcode":"PL26 8PY",
    "sg:province":"Cornwall",
    "sg:tags":[
        "rest"
    ],
    "wof:name":"Elizabeth Rest Home",
    "wof:placetype":"venue"
},
  "geometry": {"coordinates":[-4.794336,50.39278],"type":"Point"}
}