{
  "type": "Feature",
  "properties": {
    "iso:country":"GB",
    "sg:address":"Lewis House, Alexandra Docks",
    "sg:city":"Newport",
    "sg:classifiers":[
        {
            "category":"Wholesale",
            "subcategory":"Machinery & Supplies",
            "type":"Manufacturing & Wholesale Goods"
        }
    ],
    "sg:phone":"+44 1633 221300",
    "sg:postcode":"NP20 2NP",
    "sg:province":"Newport",
    "sg:tags":[
        "equipment",
        "pneumatic",
        "system"
    ],
    "wof:name":"Glamair Pneumatic Centre",
    "wof:placetype":"venue"
},
  "geometry": {"coordinates":[-2.9882190228,51.5749053955],"type":"Point"}
}