{
  "type": "Feature",
  "properties": {
    "addr:full":"4 The Broadway, Farnham Common Slough Berkshire SL2 3PQ",
    "addr:housenumber":"4",
    "addr:postcode":"sl2 3pq",
    "addr:street":"The Broadway",
    "iso:country":"GB",
    "sg:address":"4 The Broadway, Farnham Common",
    "sg:city":"Slough",
    "sg:classifiers":[
        {
            "category":"Manufacturing",
            "subcategory":"Tools & Machinery",
            "type":"Manufacturing & Wholesale Goods"
        }
    ],
    "sg:phone":"+44 1753 643672",
    "sg:postcode":"SL2 3PQ",
    "sg:province":"Berkshire",
    "sg:tags":[
        "society",
        "friendly"
    ],
    "wof:name":"C V Southerden & Co.",
    "wof:placetype":"venue"
},
  "geometry": {"coordinates":[-0.6153389812,51.5552864075],"type":"Point"}
}