{
  "type": "Feature",
  "properties": {
    "addr:full":"1a Granville St Gloucester Gloucestershire GL1 5HL",
    "addr:housenumber":"1a",
    "addr:postcode":"gl1 5hl",
    "addr:street":"Granville St",
    "iso:country":"GB",
    "sg:address":"1a Granville St",
    "sg:city":"Gloucester",
    "sg:classifiers":[
        {
            "category":"Autos & Motor Vehicles",
            "subcategory":"Automobile Sales",
            "type":"Retail Goods"
        }
    ],
    "sg:phone":"+44 1452 416425",
    "sg:postcode":"GL1 5HL",
    "sg:province":"Gloucestershire",
    "sg:tags":[
        "car"
    ],
    "wof:name":"J B Autos",
    "wof:placetype":"venue"
},
  "geometry": {"coordinates":[-2.256565094,51.8516044617],"type":"Point"}
}