{
  "type": "Feature",
  "properties": {
    "addr:full":"3 Jubilee House, Altcar Road, Formby Liverpool Lancashire L37 8DL",
    "addr:housenumber":"3 jubilee house",
    "addr:postcode":"l37 8dl",
    "addr:street":"Altcar Road",
    "iso:country":"GB",
    "sg:address":"3 Jubilee House, Altcar Road, Formby",
    "sg:city":"Liverpool",
    "sg:classifiers":[
        {
            "category":"Professional",
            "subcategory":"Accounting & Tax Preparation",
            "type":"Services"
        }
    ],
    "sg:postcode":"L37 8DL",
    "sg:province":"Lancashire",
    "sg:tags":[
        "accountant"
    ],
    "wof:name":"Alan Rumph & Co",
    "wof:placetype":"venue"
},
  "geometry": {"coordinates":[-3.04319,53.554161],"type":"Point"}
}