{
  "type": "Feature",
  "properties": {
    "iso:country":"GB",
    "sg:address":"Oak Farm, Braydon",
    "sg:city":"Swindon",
    "sg:classifiers":[
        {
            "category":"Shopping",
            "subcategory":"Department Store",
            "type":"Retail Goods"
        },
        {
            "category":"Autos & Motor Vehicles",
            "subcategory":"Motorcycle Sales",
            "type":"Retail Goods"
        }
    ],
    "sg:phone":"+44 1666 860577",
    "sg:postcode":"SN5 0AG",
    "sg:province":"Wiltshire",
    "sg:tags":[
        "scooter",
        "cycle"
    ],
    "wof:name":"BILL LITTLE MOTORCYCLES",
    "wof:placetype":"venue"
},
  "geometry": {"coordinates":[-1.919719,51.587074],"type":"Point"}
}