{
  "type": "Feature",
  "properties": {
    "addr:full":"170 Lancsaster Rd Enfield Greater London EN2 0JT",
    "addr:housenumber":"170",
    "addr:postcode":"en2 0jt",
    "addr:street":"Lancsaster Rd",
    "iso:country":"GB",
    "sg:address":"170 Lancsaster Rd",
    "sg:city":"Enfield",
    "sg:classifiers":[
        {
            "category":"Building & Trades",
            "subcategory":"Construction",
            "type":"Services"
        }
    ],
    "sg:phone":"+44 20 8350 0448",
    "sg:postcode":"EN2 0JT",
    "sg:province":"Greater London",
    "sg:tags":[
        "flooring"
    ],
    "wof:name":"M.H Block Paving",
    "wof:placetype":"venue"
},
  "geometry": {"coordinates":[-0.0846090019,51.6638755798],"type":"Point"}
}