{
  "type": "Feature",
  "properties": {
    "addr:full":"37 Manor Rd Colchester Essex CO3 3LX",
    "addr:housenumber":"37",
    "addr:postcode":"co3 3lx",
    "addr:street":"Manor Rd",
    "iso:country":"GB",
    "sg:address":"37 Manor Rd",
    "sg:city":"Colchester",
    "sg:classifiers":[
        {
            "category":"Professional",
            "type":"Services"
        }
    ],
    "sg:phone":"+44 1206 543211",
    "sg:postcode":"CO3 3LX",
    "sg:province":"Essex",
    "sg:tags":[
        "exhibition"
    ],
    "wof:name":"Total Production Co The",
    "wof:placetype":"venue"
},
  "geometry": {"coordinates":[0.89131,51.88813],"type":"Point"}
}