{
  "type": "Feature",
  "properties": {
    "iso:country":"GB",
    "sg:address":"Evelyn Rd",
    "sg:city":"Birmingham",
    "sg:classifiers":[
        {
            "category":"Home & Garden",
            "subcategory":"Hardware",
            "type":"Retail Goods"
        }
    ],
    "sg:phone":"+44 121 771 1221",
    "sg:postcode":"B11 3JJ",
    "sg:province":"West Midlands",
    "sg:tags":[
        "compressor",
        "air"
    ],
    "wof:name":"Airman Industrial Products Ltd",
    "wof:placetype":"venue"
},
  "geometry": {"coordinates":[-1.859419,52.451744],"type":"Point"}
}