{
  "type": "Feature",
  "properties": {
    "addr:full":"11 Howitt Road London Greater London NW3 4LT",
    "addr:housenumber":"11",
    "addr:postcode":"nw3 4lt",
    "addr:street":"Howitt Road",
    "iso:country":"GB",
    "sg:address":"11 Howitt Road",
    "sg:city":"London",
    "sg:classifiers":[
        {
            "category":"Professional",
            "subcategory":"Accounting & Tax Preparation",
            "type":"Services"
        }
    ],
    "sg:postcode":"NW3 4LT",
    "sg:province":"Greater London",
    "sg:tags":[
        "accountant"
    ],
    "wof:name":"S Sebarajah",
    "wof:placetype":"venue"
},
  "geometry": {"coordinates":[-0.164583,51.549831],"type":"Point"}
}