{
  "type": "Feature",
  "properties": {
    "addr:full":"Tutor House, 52 Braunston Gate Leicester Leicestershire LE3 5LG",
    "addr:housenumber":"52",
    "addr:postcode":"le3 5lg",
    "addr:street":"Braunston Gate",
    "iso:country":"GB",
    "sg:address":"Tutor House, 52 Braunston Gate",
    "sg:city":"Leicester",
    "sg:classifiers":[
        {
            "category":"Building & Trades",
            "subcategory":"Plumbing",
            "type":"Services"
        }
    ],
    "sg:phone":"+44 116 254 6798",
    "sg:postcode":"LE3 5LG",
    "sg:province":"Leicestershire",
    "sg:tags":[
        "drain",
        "clearance",
        "sewer"
    ],
    "wof:name":"Tutorhall Ltd.",
    "wof:placetype":"venue"
},
  "geometry": {"coordinates":[-1.1458749771,52.6308746338],"type":"Point"}
}