{
  "type": "Feature",
  "properties": {
    "addr:full":"Cuba Industrial Estate, Bolton Road North, Stubbins Ramsbotton Bolton Lancashire BL0 0NE",
    "addr:postcode":"bl0 0ne",
    "addr:street":"Cuba Industrial Estate Bolton Road North Stubbins Ramsbotton",
    "iso:country":"GB",
    "sg:address":"Cuba Industrial Estate, Bolton Road North, Stubbins Ramsbotton",
    "sg:city":"Bolton",
    "sg:classifiers":[
        {
            "category":"Home & Garden",
            "subcategory":"Building Materials",
            "type":"Retail Goods"
        },
        {
            "category":"Building & Trades",
            "subcategory":"Equipment Rental",
            "type":"Services"
        }
    ],
    "sg:phone":"+44 1706 828888",
    "sg:postcode":"BL0 0NE",
    "sg:province":"Lancashire",
    "sg:tags":[
        "access",
        "drain",
        "clearance"
    ],
    "wof:name":"Jetchem Systems Ltd",
    "wof:placetype":"venue"
},
  "geometry": {"coordinates":[-2.3159799576,53.6566886902],"type":"Point"}
}