{
  "type": "Feature",
  "properties": {
    "addr:full":"41 Marina St Leonards-on-sea East Sussex TN38 0BU",
    "addr:housenumber":"41",
    "addr:postcode":"tn38 0bu",
    "addr:street":"Marina St",
    "iso:country":"GB",
    "sg:address":"41 Marina",
    "sg:city":"St Leonards-on-sea",
    "sg:classifiers":[
        {
            "category":"Food & Beverages",
            "subcategory":"Liquor & Beverages",
            "type":"Retail Goods"
        }
    ],
    "sg:phone":"+44 1424 446210",
    "sg:postcode":"TN38 0BU",
    "sg:province":"East Sussex",
    "sg:tags":[
        "beer",
        "spirit",
        "wines"
    ],
    "wof:name":"Thresher",
    "wof:placetype":"venue"
},
  "geometry": {"coordinates":[0.556094,50.851009],"type":"Point"}
}