{
  "type": "Feature",
  "properties": {
    "addr:full":"21 Paradise Rd Richmond Greater London TW9 1SA",
    "addr:housenumber":"21",
    "addr:postcode":"tw9 1sa",
    "addr:street":"Paradise Rd",
    "iso:country":"GB",
    "sg:address":"21 Paradise Rd",
    "sg:city":"Richmond",
    "sg:classifiers":[
        {
            "category":"Professional",
            "subcategory":"Lawyer & Legal Services",
            "type":"Services"
        }
    ],
    "sg:phone":"+44 20 8332 1535",
    "sg:postcode":"TW9 1SA",
    "sg:province":"Greater London",
    "sg:tags":[
        "advice",
        "counselling"
    ],
    "wof:name":"Richmond Money Advice Unit",
    "wof:placetype":"venue"
},
  "geometry": {"coordinates":[-0.302163,51.460052],"type":"Point"}
}