{
  "type": "Feature",
  "properties": {
    "iso:country":"GB",
    "sg:address":"Laurel Gro, Waste Lane, Balsall Common",
    "sg:city":"Coventry",
    "sg:classifiers":[
        {
            "category":"Professional",
            "subcategory":"Art Services",
            "type":"Services"
        }
    ],
    "sg:phone":"+44 1676 535025",
    "sg:postcode":"CV7 7GF",
    "sg:province":"Warwickshire",
    "sg:tags":[
        "consultant",
        "design"
    ],
    "wof:name":"Psv International",
    "wof:placetype":"venue"
},
  "geometry": {"coordinates":[-1.646134,52.385899],"type":"Point"}
}