{
  "type": "Feature",
  "properties": {
    "addr:full":"383 Brettell Lane Brierley Hill West Midlands DY5 3LQ",
    "addr:housenumber":"383",
    "addr:postcode":"dy5 3lq",
    "addr:street":"Brettell Lane",
    "iso:country":"GB",
    "sg:address":"383 Brettell Lane",
    "sg:city":"Brierley Hill",
    "sg:classifiers":[
        {
            "category":"Bars & Pubs",
            "type":"Food & Drink"
        }
    ],
    "sg:phone":"+44 1384 483755",
    "sg:postcode":"DY5 3LQ",
    "sg:province":"West Midlands",
    "sg:tags":[
        "pubs",
        "house",
        "inn",
        "public",
        "activity"
    ],
    "wof:name":"The New Wellington",
    "wof:placetype":"venue"
},
  "geometry": {"coordinates":[-2.1371099949,52.4745445251],"type":"Point"}
}