{
  "type": "Feature",
  "properties": {
    "addr:full":"27 Elswick Road, Armstrong Washington Tyne and Wear NE37 1PB",
    "addr:housenumber":"27",
    "addr:postcode":"tyne and;ne37 1pb",
    "addr:street":"Elswick Road",
    "iso:country":"GB",
    "sg:address":"27 Elswick Road, Armstrong",
    "sg:city":"Washington",
    "sg:classifiers":[
        {
            "category":"Building & Trades",
            "subcategory":"Construction",
            "type":"Services"
        },
        {
            "category":"Building & Trades",
            "subcategory":"Locksmith",
            "type":"Services"
        }
    ],
    "sg:phone":"+44 191 417 3135",
    "sg:postcode":"NE37 1PB",
    "sg:province":"Tyne and Wear",
    "sg:tags":[
        "contracting",
        "roofing",
        "balustrade",
        "handrail"
    ],
    "wof:name":"Clifford Chapman Metalworks Ltd.",
    "wof:placetype":"venue"
},
  "geometry": {"coordinates":[-1.546907,54.908409],"type":"Point"}
}