{
  "type": "Feature",
  "properties": {
    "iso:country":"GB",
    "sg:address":"25 Camford Way",
    "sg:city":"Luton",
    "sg:classifiers":[
        {
            "category":"Professional",
            "subcategory":"Engineering",
            "type":"Services"
        }
    ],
    "sg:phone":"+44 1582 599610",
    "sg:postcode":"LU3 3AN",
    "sg:province":"Bedfordshire",
    "sg:tags":[
        "precision",
        "engineer"
    ],
    "wof:name":"Infratool Systems Ltd.",
    "wof:placetype":"venue"
},
  "geometry": {"coordinates":[-0.478364,51.923134],"type":"Point"}
}