{
  "type": "Feature",
  "properties": {
    "iso:country":"GB",
    "sg:address":"47 Easthouses Rd, Easthouses",
    "sg:city":"Dalkeith",
    "sg:classifiers":[
        {
            "category":"Building & Trades",
            "subcategory":"Construction",
            "type":"Services"
        }
    ],
    "sg:postcode":"EH22 4EB",
    "sg:province":"City of Edinburgh",
    "sg:tags":[
        "joiner",
        "carpenter"
    ],
    "wof:name":"Stobbart,Robert S,",
    "wof:placetype":"venue"
},
  "geometry": {"coordinates":[-3.049318,55.879765],"type":"Point"}
}