{
  "type": "Feature",
  "properties": {
    "addr:full":"140a Hampton Road Southport Lancashire PR8 5DJ",
    "addr:housenumber":"140a",
    "addr:postcode":"pr8 5dj",
    "addr:street":"Hampton Road",
    "iso:country":"GB",
    "sg:address":"140a Hampton Road",
    "sg:city":"Southport",
    "sg:classifiers":[
        {
            "category":"Shopping",
            "subcategory":"Gifts & Souvenirs",
            "type":"Retail Goods"
        }
    ],
    "sg:postcode":"PR8 5DJ",
    "sg:province":"Lancashire",
    "sg:tags":[
        "window",
        "leaded"
    ],
    "wof:name":"J & G Kitching",
    "wof:placetype":"venue"
},
  "geometry": {"coordinates":[-3.002459,53.635609],"type":"Point"}
}