{
  "type": "Feature",
  "properties": {
    "iso:country":"GB",
    "sg:address":"Little Brookhouse Farm, Brookhouse Lane, Cheddleton",
    "sg:city":"Leek",
    "sg:classifiers":[
        {
            "category":"Farming",
            "subcategory":"Livestock Farm",
            "type":"Manufacturing & Wholesale Goods"
        }
    ],
    "sg:postcode":"ST13 7DF",
    "sg:province":"Staffordshire",
    "sg:tags":[
        "others"
    ],
    "wof:name":"Sherratt's Bed & Breakfast",
    "wof:placetype":"venue"
},
  "geometry": {"coordinates":[-2.043203,53.064342],"type":"Point"}
}