{
  "type": "Feature",
  "properties": {
    "iso:country":"GB",
    "sg:address":"1 Smith Lane",
    "sg:city":"Bradford",
    "sg:classifiers":[
        {
            "category":"Health Services",
            "subcategory":"Doctor",
            "type":"Services"
        }
    ],
    "sg:phone":"+44 1274 544926",
    "sg:postcode":"BD9 5HE",
    "sg:province":"West Yorkshire",
    "sg:tags":[
        "practitioners"
    ],
    "wof:name":"Bradford District Health Authority",
    "wof:placetype":"venue"
},
  "geometry": {"coordinates":[-1.7903490067,53.8073692322],"type":"Point"}
}