{
  "type": "Feature",
  "properties": {
    "iso:country":"GB",
    "sg:address":"18 London Road",
    "sg:city":"Tunbridge Wells",
    "sg:classifiers":[
        {
            "category":"Insurance",
            "subcategory":"Insurance Agent",
            "type":"Services"
        }
    ],
    "sg:postcode":"TN1 1DA",
    "sg:province":"Kent",
    "sg:tags":[
        "broker"
    ],
    "wof:name":"Langton Insurance Services",
    "wof:placetype":"venue"
},
  "geometry": {"coordinates":[0.260507,51.127926],"type":"Point"}
}