{
  "type": "Feature",
  "properties": {
    "addr:full":"23 Royal Arcade Cardiff Cardiff CF10 1AE",
    "addr:housenumber":"23",
    "addr:postcode":"cf10 1ae",
    "addr:street":"Royal",
    "iso:country":"GB",
    "sg:address":"23 Royal Arcade",
    "sg:city":"Cardiff",
    "sg:classifiers":[
        {
            "category":"Shopping",
            "subcategory":"Clothing, Apparel, & Fashions",
            "type":"Retail Goods"
        }
    ],
    "sg:phone":"+44 29 2038 2084",
    "sg:postcode":"CF10 1AE",
    "sg:province":"Cardiff",
    "sg:tags":[
        "menswear"
    ],
    "wof:name":"Skin Shop",
    "wof:placetype":"venue"
},
  "geometry": {"coordinates":[-3.17673,51.478401],"type":"Point"}
}