{
  "type": "Feature",
  "properties": {
    "addr:full":"18 New Road, Hythe Southampton Hampshire SO45 6BP",
    "addr:housenumber":"18",
    "addr:postcode":"so45 6bp",
    "addr:street":"New Road",
    "iso:country":"GB",
    "sg:address":"18 New Road, Hythe",
    "sg:city":"Southampton",
    "sg:classifiers":[
        {
            "category":"Professional",
            "subcategory":"Engineering",
            "type":"Services"
        }
    ],
    "sg:phone":"+44 23 8084 2010",
    "sg:postcode":"SO45 6BP",
    "sg:province":"Hampshire",
    "sg:tags":[
        "engineer"
    ],
    "wof:name":"Taylor Engineering Services",
    "wof:placetype":"venue"
},
  "geometry": {"coordinates":[-1.3989520073,50.8679122925],"type":"Point"}
}