{
  "type": "Feature",
  "properties": {
    "iso:country":"GB",
    "sg:address":"7 Claymill Road",
    "sg:city":"Leicester",
    "sg:classifiers":[
        {
            "category":"Home & Garden",
            "subcategory":"Hardware",
            "type":"Retail Goods"
        }
    ],
    "sg:postcode":"LE4 7JJ",
    "sg:province":"Leicestershire",
    "sg:tags":[
        "gear",
        "cutter"
    ],
    "wof:name":"Sovereign Gears Ltd.",
    "wof:placetype":"venue"
},
  "geometry": {"coordinates":[-1.089901,52.663647],"type":"Point"}
}