{
  "type": "Feature",
  "properties": {
    "iso:country":"GB",
    "sg:address":"20 St Briavels Drive",
    "sg:city":"Bristol",
    "sg:classifiers":[
        {
            "category":"Home & Garden",
            "subcategory":"Hardware",
            "type":"Retail Goods"
        },
        {
            "category":"Home & Garden",
            "subcategory":"Building Materials",
            "type":"Retail Goods"
        }
    ],
    "sg:postcode":"BS37 4EZ",
    "sg:province":"Gloucestershire",
    "sg:tags":[
        "garage",
        "door",
        "diy",
        "retailer"
    ],
    "wof:name":"Simmons Up & Over Garage Doors",
    "wof:placetype":"venue"
},
  "geometry": {"coordinates":[-2.417743,51.532925],"type":"Point"}
}