{
  "type": "Feature",
  "properties": {
    "addr:full":"92 Victoria Dock Road London Greater London E16 1DA",
    "addr:housenumber":"92",
    "addr:postcode":"e16 1da",
    "addr:street":"Victoria Dock Road",
    "iso:country":"GB",
    "sg:address":"92 Victoria Dock Road",
    "sg:city":"London",
    "sg:classifiers":[
        {
            "category":"Bars & Pubs",
            "type":"Food & Drink"
        },
        {
            "category":"Community Center",
            "subcategory":"Social",
            "type":"Public Place"
        }
    ],
    "sg:phone":"+44 20 7473 3380",
    "sg:postcode":"E16 1DA",
    "sg:province":"Greater London",
    "sg:tags":[
        "pubs",
        "house",
        "inn",
        "activity"
    ],
    "wof:name":"The Peacock",
    "wof:placetype":"venue"
},
  "geometry": {"coordinates":[0.010873,51.510986],"type":"Point"}
}