{
  "type": "Feature",
  "properties": {
    "iso:country":"GB",
    "sg:address":"1a The Parade, Placehouse Lane",
    "sg:city":"Coulsdon",
    "sg:classifiers":[
        {
            "category":"Manufacturing",
            "subcategory":"Tools & Machinery",
            "type":"Manufacturing & Wholesale Goods"
        },
        {
            "category":"Banks & Credit Unions",
            "subcategory":"Financial Services",
            "type":"Services"
        }
    ],
    "sg:postcode":"CR5 1EH",
    "sg:province":"Surrey",
    "sg:tags":[
        "adviser",
        "friendly",
        "society"
    ],
    "wof:name":"Woodacre Financial Services",
    "wof:placetype":"venue"
},
  "geometry": {"coordinates":[-0.1198839992,51.3065567017],"type":"Point"}
}