{
  "type": "Feature",
  "properties": {
    "addr:full":"152 Whitefield, West Morden Wareham Dorset BH20 7DU",
    "addr:housenumber":"152",
    "addr:postcode":"bh20 7du",
    "addr:street":"Whitefield West",
    "iso:country":"GB",
    "sg:address":"152 Whitefield, West Morden",
    "sg:city":"Wareham",
    "sg:classifiers":[
        {
            "category":"Retail",
            "subcategory":"Auto Repair",
            "type":"Services"
        }
    ],
    "sg:phone":"+44 1929 459545",
    "sg:postcode":"BH20 7DU",
    "sg:province":"Dorset",
    "sg:tags":[
        "engine",
        "car",
        "specialist"
    ],
    "wof:name":"P M Gardiner",
    "wof:placetype":"venue"
},
  "geometry": {"coordinates":[-2.1632111073,50.7275695801],"type":"Point"}
}