{
  "type": "Feature",
  "properties": {
    "addr:full":"Bansons Yard, High St Ongar Essex CM5 9AA",
    "addr:postcode":"cm5 9aa",
    "addr:street":"High St",
    "iso:country":"GB",
    "sg:address":"Bansons Yard, High St",
    "sg:city":"Ongar",
    "sg:classifiers":[
        {
            "category":"Home & Garden",
            "subcategory":"Home Furnishings",
            "type":"Retail Goods"
        }
    ],
    "sg:phone":"+44 1277 365870",
    "sg:postcode":"CM5 9AA",
    "sg:province":"Essex",
    "sg:tags":[
        "homefurnishings"
    ],
    "wof:name":"Tinder Box",
    "wof:placetype":"venue"
},
  "geometry": {"coordinates":[0.244016,51.707535],"type":"Point"}
}