{
  "type": "Feature",
  "properties": {
    "iso:country":"GB",
    "sg:address":"99 Accrington Road",
    "sg:city":"Blackburn",
    "sg:classifiers":[
        {
            "category":"Fast Food",
            "type":"Food & Drink"
        },
        {
            "category":"Food & Beverages",
            "subcategory":"Meat & Fish",
            "type":"Retail Goods"
        }
    ],
    "sg:phone":"+44 1254 54965",
    "sg:postcode":"BB1 2AF",
    "sg:province":"Lancashire",
    "sg:tags":[
        "outlet",
        "chip",
        "meal",
        "away",
        "take"
    ],
    "wof:name":"Empire Fish N Chips",
    "wof:placetype":"venue"
},
  "geometry": {"coordinates":[-2.453929,53.748302],"type":"Point"}
}