{
  "type": "Feature",
  "properties": {
    "addr:full":"Letchworth Cross, Common Road Dinas Powys The Vale of Glamorgan CF64 4TP",
    "addr:postcode":"cf64 4tp",
    "addr:street":"Letchworth Cross Common Road;Vale",
    "iso:country":"GB",
    "sg:address":"Letchworth Cross, Common Road",
    "sg:city":"Dinas Powys",
    "sg:classifiers":[
        {
            "category":"Shopping",
            "subcategory":"Gifts & Souvenirs",
            "type":"Retail Goods"
        }
    ],
    "sg:phone":"+44 29 2051 3650",
    "sg:postcode":"CF64 4TP",
    "sg:province":"The Vale of Glamorgan",
    "sg:tags":[
        "watch",
        "clock"
    ],
    "wof:name":"M Wharf Clockmaker",
    "wof:placetype":"venue"
},
  "geometry": {"coordinates":[-3.2163169384,51.4279670715],"type":"Point"}
}