{
  "type": "Feature",
  "properties": {
    "iso:country":"GB",
    "sg:address":"20 Todshill Street",
    "sg:city":"Strathaven",
    "sg:classifiers":[
        {
            "category":"Home & Garden",
            "subcategory":"Household Appliances",
            "type":"Retail Goods"
        },
        {
            "category":"Retail",
            "subcategory":"Repair Shop",
            "type":"Services"
        }
    ],
    "sg:postcode":"ML10 6DD",
    "sg:province":"South Lanarkshire",
    "sg:tags":[
        "machine",
        "electrical",
        "washing"
    ],
    "wof:name":"J & S Patrick Domestic Appliances",
    "wof:placetype":"venue"
},
  "geometry": {"coordinates":[-4.0636310577,55.6754722595],"type":"Point"}
}