{
  "type": "Feature",
  "properties": {
    "addr:full":"56 Bell Street Henley-on-thames Berkshire RG9 2BG",
    "addr:housenumber":"56",
    "addr:postcode":"rg9 2bg",
    "addr:street":"Bell Street",
    "iso:country":"GB",
    "sg:address":"56 Bell Street",
    "sg:city":"Henley-on-thames",
    "sg:classifiers":[
        {
            "category":"Professional",
            "subcategory":"Business Services",
            "type":"Services"
        }
    ],
    "sg:phone":"+44 1491 412455",
    "sg:postcode":"RG9 2BG",
    "sg:province":"Berkshire",
    "sg:tags":[
        "tile",
        "stockist"
    ],
    "wof:name":"Ceramica",
    "wof:placetype":"venue"
},
  "geometry": {"coordinates":[-0.904356,51.539303],"type":"Point"}
}