{
  "type": "Feature",
  "properties": {
    "iso:country":"GB",
    "sg:address":"5 Aston Rd North",
    "sg:city":"Birmingham",
    "sg:classifiers":[
        {
            "category":"Professional",
            "subcategory":"Printing & Photocopies",
            "type":"Services"
        }
    ],
    "sg:postcode":"B6 4DS",
    "sg:province":"West Midlands",
    "sg:tags":[
        "printer"
    ],
    "wof:name":"Rogers,Barry,",
    "wof:placetype":"venue"
},
  "geometry": {"coordinates":[-1.888749,52.492943],"type":"Point"}
}