{
  "type": "Feature",
  "properties": {
    "addr:full":"1 Crown Walk, High St Taunton Somerset TA1 3PU",
    "addr:housenumber":"1",
    "addr:postcode":"ta1 3pu",
    "addr:street":"Crown Walk High St",
    "iso:country":"GB",
    "sg:address":"1 Crown Walk, High St",
    "sg:city":"Taunton",
    "sg:classifiers":[
        {
            "category":"Shopping",
            "subcategory":"Thrift Store",
            "type":"Retail Goods"
        }
    ],
    "sg:phone":"+44 1823 354990",
    "sg:postcode":"TA1 3PU",
    "sg:province":"Somerset",
    "sg:tags":[
        "shop",
        "charity"
    ],
    "wof:name":"Sue Ryder Foundation",
    "wof:placetype":"venue"
},
  "geometry": {"coordinates":[-3.1037290096,51.0133590698],"type":"Point"}
}