{
  "type": "Feature",
  "properties": {
    "iso:country":"GB",
    "sg:address":"1 Marsh Lane, Cannington",
    "sg:city":"Bridgwater",
    "sg:classifiers":[
        {
            "category":"Professional",
            "subcategory":"Engineering",
            "type":"Services"
        }
    ],
    "sg:phone":"+44 1278 653394",
    "sg:postcode":"TA5 2HZ",
    "sg:province":"Somerset",
    "sg:tags":[
        "contractor",
        "electrical",
        "engineer"
    ],
    "wof:name":"Ainsdale Engineering Ltd.",
    "wof:placetype":"venue"
},
  "geometry": {"coordinates":[-3.0570960045,51.1518516541],"type":"Point"}
}