{
  "type": "Feature",
  "properties": {
    "addr:full":"24 Willesden Lane Kilburn Greater London NW6 7ST",
    "addr:housenumber":"24",
    "addr:postcode":"nw6 7st",
    "addr:street":"Willesden Lane",
    "iso:country":"GB",
    "sg:address":"24 Willesden Lane",
    "sg:city":"Kilburn",
    "sg:classifiers":[
        {
            "category":"Restaurant",
            "type":"Food & Drink"
        }
    ],
    "sg:phone":"+44 20 7624 5773",
    "sg:postcode":"NW6 7ST",
    "sg:province":"Greater London",
    "sg:tags":[
        "chinese"
    ],
    "wof:name":"Charlie Chen",
    "wof:placetype":"venue"
},
  "geometry": {"coordinates":[-0.199308,51.541538],"type":"Point"}
}