{
  "type": "Feature",
  "properties": {
    "iso:country":"GB",
    "sg:address":"9 Woodgate, Rothley",
    "sg:city":"Leicester",
    "sg:classifiers":[
        {
            "category":"Government",
            "subcategory":"Post Office",
            "type":"Public Place"
        }
    ],
    "sg:phone":"+44 116 230 2150",
    "sg:postcode":"LE7 7LL",
    "sg:province":"Leicestershire",
    "wof:name":"Rothley Post Office",
    "wof:placetype":"venue"
},
  "geometry": {"coordinates":[-1.1835589409,52.6738357544],"type":"Point"}
}