{
  "type": "Feature",
  "properties": {
    "iso:country":"GB",
    "sg:address":"156 Heathfield",
    "sg:city":"Crawley",
    "sg:classifiers":[
        {
            "category":"Professional",
            "subcategory":"Management & Consulting",
            "type":"Services"
        }
    ],
    "sg:postcode":"RH10 3UP",
    "sg:province":"Surrey",
    "sg:tags":[
        "consultant",
        "business"
    ],
    "wof:name":"Preview Consultants Ltd.",
    "wof:placetype":"venue"
},
  "geometry": {"coordinates":[-0.143088,51.12701],"type":"Point"}
}