{
  "type": "Feature",
  "properties": {
    "addr:full":"11-15 The Street Fakenham Norfolk NR21 9QD",
    "addr:housenumber":"11-15",
    "addr:postcode":"nr21 9qd",
    "addr:street":"The Street",
    "iso:country":"GB",
    "sg:address":"11-15 The Street",
    "sg:city":"Fakenham",
    "sg:classifiers":[
        {
            "category":"Professional",
            "subcategory":"Testing Lab",
            "type":"Services"
        }
    ],
    "sg:phone":"+44 1328 862135",
    "sg:postcode":"NR21 9QD",
    "sg:province":"Norfolk",
    "sg:tags":[
        "mot"
    ],
    "wof:name":"Sculthorpe Service Station",
    "wof:placetype":"venue"
},
  "geometry": {"coordinates":[0.9114590287,52.8434486389],"type":"Point"}
}