{
  "type": "Feature",
  "properties": {
    "iso:country":"GB",
    "sg:address":"16 Burns Road",
    "sg:city":"Royston",
    "sg:classifiers":[
        {
            "category":"Food & Beverages",
            "subcategory":"Groceries & Convenience Stores",
            "type":"Retail Goods"
        }
    ],
    "sg:phone":"+44 1763 247001",
    "sg:postcode":"SG8 5PN",
    "sg:province":"Bedfordshire",
    "wof:name":"Co-Operative Welcome",
    "wof:placetype":"venue"
},
  "geometry": {"coordinates":[-0.020412,52.058247],"type":"Point"}
}