{
  "type": "Feature",
  "properties": {
    "iso:country":"GB",
    "sg:address":"81 Stourport Road",
    "sg:city":"Kidderminster",
    "sg:classifiers":[
        {
            "category":"Shopping",
            "subcategory":"Pharmacy",
            "type":"Retail Goods"
        }
    ],
    "sg:phone":"+44 1562 753046",
    "sg:postcode":"DY11 7BQ",
    "sg:province":"Staffordshire",
    "sg:tags":[
        "pharmacist",
        "chemist"
    ],
    "wof:name":"West Midlands Co-Operative Society Ltd.",
    "wof:placetype":"venue"
},
  "geometry": {"coordinates":[-2.259817,52.375786],"type":"Point"}
}