{
  "type": "Feature",
  "properties": {
    "iso:country":"GB",
    "sg:address":"3 Church House, Old Hall Street",
    "sg:city":"Stoke-on-trent",
    "sg:classifiers":[
        {
            "category":"Professional",
            "subcategory":"Employment Agencies",
            "type":"Services"
        }
    ],
    "sg:phone":"+44 1782 263333",
    "sg:postcode":"ST1 3AU",
    "sg:province":"Staffordshire",
    "sg:tags":[
        "consultant"
    ],
    "wof:name":"Parker Employment Ltd.",
    "wof:placetype":"venue"
},
  "geometry": {"coordinates":[-2.175069,53.029369],"type":"Point"}
}