{
  "type": "Feature",
  "properties": {
    "addr:full":"Market Street, Hetton Leigh-hall Houghton-le-spring Durham DH5 9DZ",
    "addr:postcode":"dh5 9dz",
    "addr:street":"Market Street;Leigh-Hall",
    "iso:country":"GB",
    "sg:address":"Market Street, Hetton Leigh-hall",
    "sg:city":"Houghton-le-spring",
    "sg:classifiers":[
        {
            "category":"Home & Garden",
            "subcategory":"Carpets & Floor Coverings",
            "type":"Retail Goods"
        }
    ],
    "sg:phone":"+44 191 526 1770",
    "sg:postcode":"DH5 9DZ",
    "sg:province":"Durham",
    "sg:tags":[
        "carpets",
        "rug",
        "matting"
    ],
    "wof:name":"Hetton Carpet Centre",
    "wof:placetype":"venue"
},
  "geometry": {"coordinates":[-1.448168993,54.8259353638],"type":"Point"}
}