{
  "type": "Feature",
  "properties": {
    "addr:full":"50 Fenchurch St Monument Greater London EC3M 3JY",
    "addr:housenumber":"50",
    "addr:postcode":"ec3m 3jy",
    "addr:street":"Fenchurch St",
    "iso:country":"GB",
    "sg:address":"50 Fenchurch St",
    "sg:city":"Monument",
    "sg:classifiers":[
        {
            "category":"Manufacturing",
            "subcategory":"Tools & Machinery",
            "type":"Manufacturing & Wholesale Goods"
        }
    ],
    "sg:phone":"+44 20 7390 9300",
    "sg:postcode":"EC3M 3JY",
    "sg:province":"Greater London",
    "sg:tags":[
        "society",
        "friendly"
    ],
    "wof:name":"Highgate Managing Agencies",
    "wof:placetype":"venue"
},
  "geometry": {"coordinates":[-0.0815190002,51.5117111206],"type":"Point"}
}