{
  "type": "Feature",
  "properties": {
    "addr:full":"Plas Newydd, Abergorlech Road Carmarthen Carmarthenshire SA32 7JS",
    "addr:postcode":"sa32 7js",
    "addr:street":"Abergorlech Road",
    "iso:country":"GB",
    "sg:address":"Plas Newydd, Abergorlech Road",
    "sg:city":"Carmarthen",
    "sg:classifiers":[
        {
            "category":"Building & Trades",
            "subcategory":"Plumbing",
            "type":"Services"
        }
    ],
    "sg:phone":"+44 1267 202318",
    "sg:postcode":"SA32 7JS",
    "sg:province":"Carmarthenshire",
    "sg:tags":[
        "heating"
    ],
    "wof:name":"D Mitchell",
    "wof:placetype":"venue"
},
  "geometry": {"coordinates":[-4.061306,51.983166],"type":"Point"}
}