{
  "type": "Feature",
  "properties": {
    "iso:country":"GB",
    "sg:address":"158 Nevendon Road",
    "sg:city":"Wickford",
    "sg:classifiers":[
        {
            "category":"Building & Trades",
            "subcategory":"Plumbing",
            "type":"Services"
        }
    ],
    "sg:phone":"+44 1268 733158",
    "sg:postcode":"SS12 0NX",
    "sg:province":"Essex",
    "sg:tags":[
        "heating"
    ],
    "wof:name":"G A Hart Registered Plumber",
    "wof:placetype":"venue"
},
  "geometry": {"coordinates":[0.5152620077,51.6041717529],"type":"Point"}
}