{
  "type": "Feature",
  "properties": {
    "addr:full":"Unit F16, Park Business Centre, Kilburn Park Road London Greater London NW6 5LF",
    "addr:housenumber":"f16",
    "addr:postcode":"nw6 5lf",
    "addr:street":"Kilburn Park Road",
    "iso:country":"GB",
    "sg:address":"Unit F16, Park Business Centre, Kilburn Park Road",
    "sg:city":"London",
    "sg:classifiers":[
        {
            "category":"Shopping",
            "subcategory":"Stationery & Office Supplies",
            "type":"Retail Goods"
        }
    ],
    "sg:phone":"+44 20 7328 5455",
    "sg:postcode":"NW6 5LF",
    "sg:province":"Greater London",
    "sg:tags":[
        "item",
        "promotional"
    ],
    "wof:name":"Corporate Merchandising Solutions Ltd.",
    "wof:placetype":"venue"
},
  "geometry": {"coordinates":[-0.19567,51.52911],"type":"Point"}
}