{
  "type": "Feature",
  "properties": {
    "iso:country":"GB",
    "sg:address":"Unit 3, Keyway Retail Park",
    "sg:city":"Willenhall",
    "sg:classifiers":[
        {
            "category":"Shopping",
            "subcategory":"Stationery & Office Supplies",
            "type":"Retail Goods"
        }
    ],
    "sg:phone":"+44 1902 637517",
    "sg:postcode":"WV13 2QU",
    "sg:province":"West Midlands",
    "wof:name":"Staples the Office Superstore",
    "wof:placetype":"venue"
},
  "geometry": {"coordinates":[-2.0471539497,52.5765266418],"type":"Point"}
}