{
  "type": "Feature",
  "properties": {
    "addr:full":"23 Phorpres Ct, Old Fletton Peterborough Cambridgeshire PE2 9EL",
    "addr:housenumber":"23",
    "addr:postcode":"pe2 9el",
    "addr:street":"Phorpres Ct",
    "iso:country":"GB",
    "sg:address":"23 Phorpres Ct, Old Fletton",
    "sg:city":"Peterborough",
    "sg:classifiers":[
        {
            "category":"Education",
            "subcategory":"College",
            "type":"Public Place"
        }
    ],
    "sg:postcode":"PE2 9EL",
    "sg:province":"Cambridgeshire",
    "sg:tags":[
        "technical",
        "agricultural"
    ],
    "wof:name":"Miller,Ruby,",
    "wof:placetype":"venue"
},
  "geometry": {"coordinates":[-0.246969,52.557735],"type":"Point"}
}