{
  "type": "Feature",
  "properties": {
    "iso:country":"GB",
    "sg:address":"Pavilion, The Common, Chipperfield",
    "sg:city":"King's Langley",
    "sg:classifiers":[
        {
            "category":"Arena",
            "subcategory":"Sports Club",
            "type":"Entertainment"
        }
    ],
    "sg:phone":"+44 1923 264681",
    "sg:postcode":"WD4 9BS",
    "sg:province":"Hertfordshire",
    "wof:name":"Chipperfield Cricket Club",
    "wof:placetype":"venue"
},
  "geometry": {"coordinates":[-0.4921799898,51.703289032],"type":"Point"}
}