{
  "type": "Feature",
  "properties": {
    "iso:country":"GB",
    "sg:address":"Creaton Ho, 24 The Green",
    "sg:city":"Northampton",
    "sg:classifiers":[
        {
            "category":"Health Services",
            "subcategory":"Doctor",
            "type":"Services"
        }
    ],
    "sg:phone":"+44 1604 505722",
    "sg:postcode":"NN6 8ND",
    "sg:province":"Northamptonshire",
    "sg:tags":[
        "practitioners"
    ],
    "wof:name":"H De La Haye Davies",
    "wof:placetype":"venue"
},
  "geometry": {"coordinates":[-0.981474,52.325779],"type":"Point"}
}