{
  "type": "Feature",
  "properties": {
    "addr:full":"13 Market Sq Tenbury Wells Herefordshire WR15 8BL",
    "addr:housenumber":"13",
    "addr:postcode":"wr15 8bl",
    "addr:street":"Market Sq",
    "iso:country":"GB",
    "sg:address":"13 Market Sq",
    "sg:city":"Tenbury Wells",
    "sg:classifiers":[
        {
            "category":"Shopping",
            "subcategory":"Baby Store",
            "type":"Retail Goods"
        }
    ],
    "sg:phone":"+44 1584 819992",
    "sg:postcode":"WR15 8BL",
    "sg:province":"Herefordshire",
    "sg:tags":[
        "babywear",
        "childrens"
    ],
    "wof:name":"Westons",
    "wof:placetype":"venue"
},
  "geometry": {"coordinates":[-2.595375,52.31065],"type":"Point"}
}