{
  "type": "Feature",
  "properties": {
    "iso:country":"GB",
    "sg:address":"Berrymore Road Shopping Centre",
    "sg:city":"Wellingborough",
    "sg:classifiers":[
        {
            "category":"Food & Beverages",
            "subcategory":"Meat & Fish",
            "type":"Retail Goods"
        }
    ],
    "sg:phone":"+44 1933 276766",
    "sg:postcode":"NN8 2HR",
    "sg:province":"Northamptonshire",
    "sg:tags":[
        "chip"
    ],
    "wof:name":"K S Lo",
    "wof:placetype":"venue"
},
  "geometry": {"coordinates":[-0.702619,52.290871],"type":"Point"}
}