{
  "type": "Feature",
  "properties": {
    "iso:country":"GB",
    "sg:address":"Chaucer Road",
    "sg:city":"Fleetwood",
    "sg:classifiers":[
        {
            "category":"Education",
            "subcategory":"School",
            "type":"Public Place"
        }
    ],
    "sg:phone":"+44 1253 873795",
    "sg:postcode":"FY7 6QN",
    "sg:province":"Lancashire",
    "sg:tags":[
        "local",
        "authority"
    ],
    "wof:name":"Chaucer Community Primary School",
    "wof:placetype":"venue"
},
  "geometry": {"coordinates":[-3.0197789669,53.9224433899],"type":"Point"}
}