{
  "type": "Feature",
  "properties": {
    "iso:country":"GB",
    "sg:address":"24-26 Hogshill Street",
    "sg:city":"Beaminster",
    "sg:classifiers":[
        {
            "category":"Food & Beverages",
            "subcategory":"Groceries & Convenience Stores",
            "type":"Retail Goods"
        }
    ],
    "sg:postcode":"DT8 3AA",
    "sg:province":"Dorset",
    "wof:name":"Countryside Spar Shop",
    "wof:placetype":"venue"
},
  "geometry": {"coordinates":[-2.7402999401,50.8097381592],"type":"Point"}
}