{
  "type": "Feature",
  "properties": {
    "addr:full":"55a Radcliffe Road, West Bridgford Nottingham Nottinghamshire NG2 5FX",
    "addr:housenumber":"55a",
    "addr:postcode":"ng2 5fx",
    "addr:street":"Radcliffe Road",
    "iso:country":"GB",
    "sg:address":"55a Radcliffe Road, West Bridgford",
    "sg:city":"Nottingham",
    "sg:classifiers":[
        {
            "category":"Fast Food",
            "type":"Food & Drink"
        },
        {
            "category":"Restaurant",
            "type":"Food & Drink"
        }
    ],
    "sg:phone":"+44 115 981 4122",
    "sg:postcode":"NG2 5FX",
    "sg:province":"Nottinghamshire",
    "sg:tags":[
        "american",
        "-",
        "away",
        "take"
    ],
    "wof:name":"McDonald's Restaurants Ltd",
    "wof:placetype":"venue"
},
  "geometry": {"coordinates":[-1.1301490068,52.938457489],"type":"Point"}
}