{
  "type": "Feature",
  "properties": {
    "iso:country":"GB",
    "sg:address":"16a Beach Road West, Portishead",
    "sg:city":"Bristol",
    "sg:classifiers":[
        {
            "category":"Professional",
            "subcategory":"Computer Services",
            "type":"Services"
        },
        {
            "category":"Utilities",
            "type":"Services"
        }
    ],
    "sg:postcode":"BS20 7HR",
    "sg:province":"Somerset",
    "sg:tags":[
        "software",
        "system",
        "internet"
    ],
    "wof:name":"M A Fielden & Co. Ltd.",
    "wof:placetype":"venue"
},
  "geometry": {"coordinates":[-2.772927,51.487728],"type":"Point"}
}