{
  "type": "Feature",
  "properties": {
    "addr:full":"School Close, Ludham Great Yarmouth Norfolk NR29 5QW",
    "addr:postcode":"nr29 5qw",
    "addr:street":"School Close Ludham Great Yarmouth",
    "iso:country":"GB",
    "sg:address":"School Close, Ludham",
    "sg:city":"Great Yarmouth",
    "sg:classifiers":[
        {
            "category":"Social Services",
            "subcategory":"Retirement Home",
            "type":"Services"
        },
        {
            "category":"Real Estate",
            "subcategory":"Real Estate Agent",
            "type":"Services"
        }
    ],
    "sg:phone":"+44 1692 678411",
    "sg:postcode":"NR29 5QW",
    "sg:province":"Norfolk",
    "sg:tags":[
        "rest"
    ],
    "wof:name":"Grouped Homes for Aged Persons",
    "wof:placetype":"venue"
},
  "geometry": {"coordinates":[1.535982,52.709888],"type":"Point"}
}