{
  "type": "Feature",
  "properties": {
    "iso:country":"GB",
    "sg:address":"28a Blantyre Terrace",
    "sg:city":"Edinburgh",
    "sg:classifiers":[
        {
            "category":"Professional",
            "subcategory":"Art Services",
            "type":"Services"
        }
    ],
    "sg:phone":"+44 131 447 0617",
    "sg:postcode":"EH10 5AE",
    "sg:province":"City of Edinburgh",
    "sg:tags":[
        "consultant",
        "design"
    ],
    "wof:name":"Art Dept",
    "wof:placetype":"venue"
},
  "geometry": {"coordinates":[-3.213205,55.934021],"type":"Point"}
}