{
  "type": "Feature",
  "properties": {
    "addr:full":"104 Arlington Road London Greater London NW1 7HP",
    "addr:housenumber":"104",
    "addr:postcode":"nw1 7hp",
    "addr:street":"Arlington Road",
    "iso:country":"GB",
    "sg:address":"104 Arlington Road",
    "sg:city":"London",
    "sg:classifiers":[
        {
            "category":"Retail",
            "subcategory":"Auto Rental",
            "type":"Services"
        }
    ],
    "sg:phone":"+44 20 7482 2727",
    "sg:postcode":"NW1 7HP",
    "sg:province":"Greater London",
    "sg:tags":[
        "car"
    ],
    "wof:name":"Acton Car Rental Co. Ltd.",
    "wof:placetype":"venue"
},
  "geometry": {"coordinates":[-0.142335996,51.5370521545],"type":"Point"}
}