{
  "type": "Feature",
  "properties": {
    "addr:full":"1-2 Spitfire House, Turnhouse Road Edinburgh City of Edinburgh EH12 0AL",
    "addr:housenumber":"1-2",
    "addr:postcode":"eh12 0al",
    "addr:street":"Turnhouse Road",
    "iso:country":"GB",
    "sg:address":"1-2 Spitfire House, Turnhouse Road",
    "sg:city":"Edinburgh",
    "sg:classifiers":[
        {
            "category":"Freight",
            "type":"Transportation"
        }
    ],
    "sg:postcode":"EH12 0AL",
    "sg:province":"City of Edinburgh",
    "sg:tags":[
        "haulage",
        "road"
    ],
    "wof:name":"Charlie Dyer",
    "wof:placetype":"venue"
},
  "geometry": {"coordinates":[-3.35073,55.951881],"type":"Point"}
}