{
  "type": "Feature",
  "properties": {
    "addr:full":"South Studio, Walker House London Greater London E2 7JE",
    "addr:postcode":"e2 7je",
    "iso:country":"GB",
    "sg:address":"South Studio, Walker House",
    "sg:city":"London",
    "sg:classifiers":[
        {
            "category":"Shopping",
            "subcategory":"Gifts & Souvenirs",
            "type":"Retail Goods"
        }
    ],
    "sg:postcode":"E2 7JE",
    "sg:province":"Greater London",
    "sg:tags":[
        "giftware"
    ],
    "wof:name":"Kikass Ltd.",
    "wof:placetype":"venue"
},
  "geometry": {"coordinates":[-0.0688640028,51.5306739807],"type":"Point"}
}