{
  "type": "Feature",
  "properties": {
    "addr:full":"Queens Road Ilkley North Yorkshire LS29 9QL",
    "addr:postcode":"ls29 9ql",
    "addr:street":"Queens Road",
    "iso:country":"GB",
    "sg:address":"Queens Road",
    "sg:city":"Ilkley",
    "sg:classifiers":[
        {
            "category":"Social Services",
            "subcategory":"Retirement Home",
            "type":"Services"
        }
    ],
    "sg:phone":"+44 1943 607063",
    "sg:postcode":"LS29 9QL",
    "sg:province":"North Yorkshire",
    "sg:tags":[
        "residential",
        "care"
    ],
    "wof:name":"Straven House",
    "wof:placetype":"venue"
},
  "geometry": {"coordinates":[-1.8310240507,53.9199142456],"type":"Point"}
}