{
  "type": "Feature",
  "properties": {
    "iso:country":"GB",
    "sg:address":"Newland Park, Gorelands Lane",
    "sg:city":"Chalfont St Giles",
    "sg:classifiers":[
        {
            "category":"Education",
            "subcategory":"Special Training",
            "type":"Public Place"
        }
    ],
    "sg:phone":"+44 1494 876262",
    "sg:postcode":"HP8 4AD",
    "sg:province":"Buckinghamshire",
    "sg:tags":[
        "product",
        "centre"
    ],
    "wof:name":"Hawk & Owl Trust National Conservation & Education Centre",
    "wof:placetype":"venue"
},
  "geometry": {"coordinates":[-0.576629,51.629925],"type":"Point"}
}