{
  "type": "Feature",
  "properties": {
    "iso:country":"GB",
    "sg:address":"35-37 Midland Road",
    "sg:city":"Bedford",
    "sg:classifiers":[
        {
            "category":"Banks & Credit Unions",
            "subcategory":"Bank",
            "type":"Services"
        }
    ],
    "sg:phone":"+44 845 765 4321",
    "sg:postcode":"MK40 1PW",
    "sg:province":"Bedfordshire",
    "wof:name":"Abbey National Plc",
    "wof:placetype":"venue"
},
  "geometry": {"coordinates":[-0.470542,52.136551],"type":"Point"}
}