{
  "type": "Feature",
  "properties": {
    "iso:country":"GB",
    "sg:address":"Pomphlett Jetty, Breakwater Rd",
    "sg:city":"Plymouth",
    "sg:classifiers":[
        {
            "category":"Manufacturing",
            "subcategory":"Glass & Minerals",
            "type":"Manufacturing & Wholesale Goods"
        }
    ],
    "sg:phone":"+44 1752 401958",
    "sg:postcode":"PL9 7HJ",
    "sg:province":"Devon",
    "sg:tags":[
        "chalk",
        "stone",
        "slate"
    ],
    "wof:name":"Bardon Aggregates",
    "wof:placetype":"venue"
},
  "geometry": {"coordinates":[-4.098151,50.362995],"type":"Point"}
}