{
  "type": "Feature",
  "properties": {
    "addr:full":"4 Nutash Fareham Hampshire PO14 4SG",
    "addr:housenumber":"4",
    "addr:postcode":"po14 4sg",
    "addr:street":"Nutash",
    "iso:country":"GB",
    "sg:address":"4 Nutash",
    "sg:city":"Fareham",
    "sg:classifiers":[
        {
            "category":"Building & Trades",
            "subcategory":"Construction",
            "type":"Services"
        }
    ],
    "sg:phone":"+44 1489 885003",
    "sg:postcode":"PO14 4SG",
    "sg:province":"Hampshire",
    "sg:tags":[
        "dry",
        "lining",
        "plasterers",
        "screeders"
    ],
    "wof:name":"R J Woodford Plastering Ltd.",
    "wof:placetype":"venue"
},
  "geometry": {"coordinates":[-1.259471,50.866478],"type":"Point"}
}