{
  "type": "Feature",
  "properties": {
    "addr:full":"Alice Ho, 10 Homer Rd Solihull West Midlands B91 3QQ",
    "addr:housenumber":"10",
    "addr:postcode":"b91 3qq",
    "addr:street":"Homer Rd",
    "iso:country":"GB",
    "sg:address":"Alice Ho, 10 Homer Rd",
    "sg:city":"Solihull",
    "sg:classifiers":[
        {
            "category":"Professional",
            "subcategory":"Lawyer & Legal Services",
            "type":"Services"
        }
    ],
    "sg:phone":"+44 121 705 2211",
    "sg:postcode":"B91 3QQ",
    "sg:province":"West Midlands",
    "sg:tags":[
        "advice",
        "counselling"
    ],
    "wof:name":"Citizens Advice Bureau",
    "wof:placetype":"venue"
},
  "geometry": {"coordinates":[-1.777848959,52.4150657654],"type":"Point"}
}