{
  "type": "Feature",
  "properties": {
    "iso:country":"GB",
    "sg:address":"Age Care Home Support Services Ltd, 23-25 Church Road, Kirby Muxloe",
    "sg:city":"Leicester",
    "sg:classifiers":[
        {
            "category":"Health Services",
            "subcategory":"Nursing And Care Facility",
            "type":"Services"
        },
        {
            "category":"Social Services",
            "subcategory":"Adult Care",
            "type":"Services"
        }
    ],
    "sg:phone":"+44 116 239 0333",
    "sg:postcode":"LE9 2AD",
    "sg:province":"Leicestershire",
    "sg:tags":[
        "home",
        "agency",
        "provider"
    ],
    "wof:name":"Age Care Home Support Services Ltd",
    "wof:placetype":"venue"
},
  "geometry": {"coordinates":[-1.235514,52.633579],"type":"Point"}
}