{
  "type": "Feature",
  "properties": {
    "addr:full":"142 Engineer Road, West Wilts Trading Estate Westbury Wiltshire BA13 4JW",
    "addr:housenumber":"142",
    "addr:postcode":"ba13 4jw",
    "addr:street":"Engineer Road West Wilts Trading Estate",
    "iso:country":"GB",
    "sg:address":"142 Engineer Road, West Wilts Trading Estate",
    "sg:city":"Westbury",
    "sg:classifiers":[
        {
            "category":"Retail",
            "subcategory":"Auto Repair",
            "type":"Services"
        }
    ],
    "sg:phone":"+44 1373 864717",
    "sg:postcode":"BA13 4JW",
    "sg:province":"Wiltshire",
    "sg:tags":[
        "modification",
        "garage"
    ],
    "wof:name":"Bodycraft",
    "wof:placetype":"venue"
},
  "geometry": {"coordinates":[-2.21223,51.274849],"type":"Point"}
}