{
  "type": "Feature",
  "properties": {
    "iso:country":"GB",
    "sg:address":"4 Old Rectory Gardens, Busbridge",
    "sg:city":"Godalming",
    "sg:classifiers":[
        {
            "category":"Professional",
            "subcategory":"Management & Consulting",
            "type":"Services"
        }
    ],
    "sg:postcode":"GU7 1XB",
    "sg:province":"Surrey",
    "sg:tags":[
        "consultant",
        "business"
    ],
    "wof:name":"Xalient Ltd",
    "wof:placetype":"venue"
},
  "geometry": {"coordinates":[-0.6005030274,51.1763458252],"type":"Point"}
}