{
  "type": "Feature",
  "properties": {
    "addr:full":"37 Wollaton Avenue Sheffield Derbyshire S17 4LA",
    "addr:housenumber":"37",
    "addr:postcode":"s17 4la",
    "addr:street":"Wollaton Avenue",
    "iso:country":"GB",
    "sg:address":"37 Wollaton Avenue",
    "sg:city":"Sheffield",
    "sg:classifiers":[
        {
            "category":"Retail",
            "subcategory":"Driving School",
            "type":"Services"
        }
    ],
    "sg:phone":"+44 114 236 6564",
    "sg:postcode":"S17 4LA",
    "sg:province":"Derbyshire",
    "wof:name":"Progressive School of Motoring",
    "wof:placetype":"venue"
},
  "geometry": {"coordinates":[-1.5196470022,53.3185958862],"type":"Point"}
}