{
  "type": "Feature",
  "properties": {
    "addr:full":"144 Windsor Road Newmarket Cambridgeshire CB8 0QA",
    "addr:housenumber":"144",
    "addr:postcode":"cb8 0qa",
    "addr:street":"Windsor Road",
    "iso:country":"GB",
    "sg:address":"144 Windsor Road",
    "sg:city":"Newmarket",
    "sg:classifiers":[
        {
            "category":"Professional",
            "subcategory":"Art Services",
            "type":"Services"
        },
        {
            "category":"Building & Trades",
            "subcategory":"Construction",
            "type":"Services"
        }
    ],
    "sg:phone":"+44 1638 664664",
    "sg:postcode":"CB8 0QA",
    "sg:province":"Cambridgeshire",
    "sg:tags":[
        "decorator",
        "painter"
    ],
    "wof:name":"Mitchell Bros & Son",
    "wof:placetype":"venue"
},
  "geometry": {"coordinates":[0.3921999931,52.2469482422],"type":"Point"}
}