{
  "type": "Feature",
  "properties": {
    "iso:country":"GB",
    "sg:address":"72 Princes Road",
    "sg:city":"Torquay",
    "sg:classifiers":[
        {
            "category":"Shopping",
            "subcategory":"Pets & Pet Supplies",
            "type":"Retail Goods"
        }
    ],
    "sg:postcode":"TQ1 1NP",
    "sg:province":"Devon",
    "wof:name":"Ellacombe Pet & Garden",
    "wof:placetype":"venue"
},
  "geometry": {"coordinates":[-3.5243549347,50.4703788757],"type":"Point"}
}