{
  "type": "Feature",
  "properties": {
    "addr:full":"142 Old Christchurch Road Bournemouth Dorset BH1 1NL",
    "addr:housenumber":"142",
    "addr:postcode":"bh1 1nl",
    "addr:street":"Old Christchurch Road",
    "iso:country":"GB",
    "sg:address":"142 Old Christchurch Road",
    "sg:city":"Bournemouth",
    "sg:classifiers":[
        {
            "category":"Fast Food",
            "type":"Food & Drink"
        }
    ],
    "sg:phone":"+44 1202 780549",
    "sg:postcode":"BH1 1NL",
    "sg:province":"Dorset",
    "sg:tags":[
        "away",
        "take"
    ],
    "wof:name":"Marinades",
    "wof:placetype":"venue"
},
  "geometry": {"coordinates":[-1.8736280203,50.7223396301],"type":"Point"}
}