{
  "type": "Feature",
  "properties": {
    "iso:country":"GB",
    "sg:address":"Marina Ho, Tor Vale",
    "sg:city":"Torquay",
    "sg:classifiers":[
        {
            "category":"Building & Trades",
            "subcategory":"Construction",
            "type":"Services"
        }
    ],
    "sg:phone":"+44 1803 327626",
    "sg:postcode":"TQ1 4EB",
    "sg:province":"Devon",
    "sg:tags":[
        "decorator",
        "painter"
    ],
    "wof:name":"H Macdonald",
    "wof:placetype":"venue"
},
  "geometry": {"coordinates":[-3.53814,50.473511],"type":"Point"}
}