{
  "type": "Feature",
  "properties": {
    "addr:full":"Unit 22 Robberds Way, Bowthorpe Industrial Park Norwich Norfolk NR5 9JF",
    "addr:housenumber":"unit 22",
    "addr:postcode":"nr5 9jf",
    "addr:street":"Robberds Way",
    "iso:country":"GB",
    "sg:address":"Unit 22 Robberds Way, Bowthorpe Industrial Park",
    "sg:city":"Norwich",
    "sg:classifiers":[
        {
            "category":"Communications",
            "subcategory":"Newspaper",
            "type":"Services"
        }
    ],
    "sg:phone":"+44 1603 740222",
    "sg:postcode":"NR5 9JF",
    "sg:province":"Norfolk",
    "sg:tags":[
        "magazine"
    ],
    "wof:name":"Norwich Advertiser",
    "wof:placetype":"venue"
},
  "geometry": {"coordinates":[1.210717,52.642574],"type":"Point"}
}