{
  "type": "Feature",
  "properties": {
    "addr:full":"46 Syon Lane, Osterley Isleworth Greater London TW7 5NQ",
    "addr:housenumber":"46",
    "addr:postcode":"tw7 5nq",
    "addr:street":"Syon Lane",
    "iso:country":"GB",
    "sg:address":"46 Syon Lane, Osterley",
    "sg:city":"Isleworth",
    "sg:classifiers":[
        {
            "category":"Professional",
            "subcategory":"Accounting & Tax Preparation",
            "type":"Services"
        }
    ],
    "sg:phone":"+44 20 8569 8887",
    "sg:postcode":"TW7 5NQ",
    "sg:province":"Greater London",
    "sg:tags":[
        "consultant"
    ],
    "wof:name":"B S Chowdhary",
    "wof:placetype":"venue"
},
  "geometry": {"coordinates":[-0.328363,51.483597],"type":"Point"}
}