{
  "type": "Feature",
  "properties": {
    "addr:full":"14 Coronation Rd Sheffield Derbyshire S30 5AX",
    "addr:housenumber":"14",
    "addr:postcode":"s30 5ax",
    "addr:street":"Coronation Rd",
    "iso:country":"GB",
    "sg:address":"14 Coronation Rd",
    "sg:city":"Sheffield",
    "sg:classifiers":[
        {
            "category":"Shopping",
            "type":"Retail Goods"
        }
    ],
    "sg:phone":"+44 114 288 7983",
    "sg:postcode":"S30 5AX",
    "sg:province":"Derbyshire",
    "sg:tags":[
        "part",
        "accessory"
    ],
    "wof:name":"K Wallis",
    "wof:placetype":"venue"
},
  "geometry": {"coordinates":[-1.6007779837,53.4811820984],"type":"Point"}
}