{
  "type": "Feature",
  "properties": {
    "iso:country":"GB",
    "sg:address":"25 Church Grn, Stanford-in-the-valechurch",
    "sg:city":"Faringdon",
    "sg:classifiers":[
        {
            "category":"Health Services",
            "subcategory":"Nursing And Care Facility",
            "type":"Services"
        }
    ],
    "sg:phone":"+44 1367 718836",
    "sg:postcode":"SN7 8HU",
    "sg:province":"Oxfordshire",
    "sg:tags":[
        "home"
    ],
    "wof:name":"Grange Nursing Home",
    "wof:placetype":"venue"
},
  "geometry": {"coordinates":[-1.5065850019,51.6393737793],"type":"Point"}
}