{
  "type": "Feature",
  "properties": {
    "addr:full":"Waterloo Road Wellington Devon TA21 8JQ",
    "addr:postcode":"ta21 8jq",
    "addr:street":"Waterloo Road",
    "iso:country":"GB",
    "sg:address":"Waterloo Road",
    "sg:city":"Wellington",
    "sg:classifiers":[
        {
            "category":"Place Of Worship",
            "type":"Public Place"
        }
    ],
    "sg:phone":"+44 1823 661676",
    "sg:postcode":"TA21 8JQ",
    "sg:province":"Devon",
    "wof:name":"Wellington Methodist Church",
    "wof:placetype":"venue"
},
  "geometry": {"coordinates":[-3.2365350723,50.9806900024],"type":"Point"}
}