{
  "type": "Feature",
  "properties": {
    "iso:country":"GB",
    "sg:address":"Welton Road, Croft Business Park",
    "sg:city":"Wirral",
    "sg:classifiers":[
        {
            "category":"Bars & Pubs",
            "subcategory":"Nightclub",
            "type":"Food & Drink"
        }
    ],
    "sg:phone":"+44 151 334 7494",
    "sg:postcode":"CH62 3PN",
    "sg:province":"Cheshire",
    "sg:tags":[
        "club",
        "night"
    ],
    "wof:name":"Ritzy 1 & 2 Discotheque",
    "wof:placetype":"venue"
},
  "geometry": {"coordinates":[-2.9767889977,53.3408927917],"type":"Point"}
}