{
  "type": "Feature",
  "properties": {
    "addr:full":"24 The Fairway, Blaby Leicester Leicestershire LE8 4EL",
    "addr:housenumber":"24",
    "addr:postcode":"le8 4el",
    "addr:street":"The Fairway",
    "iso:country":"GB",
    "sg:address":"24 The Fairway, Blaby",
    "sg:city":"Leicester",
    "sg:classifiers":[
        {
            "category":"Professional",
            "subcategory":"Art Services",
            "type":"Services"
        }
    ],
    "sg:postcode":"LE8 4EL",
    "sg:province":"Leicestershire",
    "sg:tags":[
        "graphic",
        "designer"
    ],
    "wof:name":"K M Graphics",
    "wof:placetype":"venue"
},
  "geometry": {"coordinates":[-1.170299,52.570454],"type":"Point"}
}