{
  "type": "Feature",
  "properties": {
    "addr:full":"12 Enderby Road Industrial Estat, E, Whetstone Leicester Leicestershire LE8 6HZ",
    "addr:housenumber":"12",
    "addr:postcode":"le8 6hz",
    "addr:street":"Enderby Road Industrial Estat E",
    "iso:country":"GB",
    "sg:address":"12 Enderby Road Industrial Estat, E, Whetstone",
    "sg:city":"Leicester",
    "sg:classifiers":[
        {
            "category":"Retail",
            "subcategory":"Auto Repair",
            "type":"Services"
        }
    ],
    "sg:phone":"+44 116 275 3307",
    "sg:postcode":"LE8 6HZ",
    "sg:province":"Leicestershire",
    "sg:tags":[
        "body",
        "car"
    ],
    "wof:name":"P K Bodyworks",
    "wof:placetype":"venue"
},
  "geometry": {"coordinates":[-1.1720490456,52.5754089355],"type":"Point"}
}