{
  "type": "Feature",
  "properties": {
    "addr:full":"Park Road Bracknell Berkshire RG12 2LU",
    "addr:postcode":"rg12 2lu",
    "addr:street":"Park Road",
    "iso:country":"GB",
    "sg:address":"Park Road",
    "sg:city":"Bracknell",
    "sg:classifiers":[
        {
            "category":"Bars & Pubs",
            "type":"Food & Drink"
        }
    ],
    "sg:phone":"+44 1344 454532",
    "sg:postcode":"RG12 2LU",
    "sg:province":"Berkshire",
    "sg:tags":[
        "pubs",
        "inn"
    ],
    "wof:name":"Greene King Leasing No 1 Ltd.",
    "wof:placetype":"venue"
},
  "geometry": {"coordinates":[-0.7373930216,51.419418335],"type":"Point"}
}