{
  "type": "Feature",
  "properties": {
    "addr:full":"Main Road, Lower Quinton Stratford-upon-avon Warwickshire CV37 8RY",
    "addr:postcode":"cv37 8ry",
    "addr:street":"Main Road Lower",
    "iso:country":"GB",
    "sg:address":"Main Road, Lower Quinton",
    "sg:city":"Stratford-upon-avon",
    "sg:classifiers":[
        {
            "category":"Food & Beverages",
            "subcategory":"Meat & Fish",
            "type":"Retail Goods"
        }
    ],
    "sg:phone":"+44 1789 720551",
    "sg:postcode":"CV37 8RY",
    "sg:province":"Warwickshire",
    "sg:tags":[
        "chip"
    ],
    "wof:name":"Seaspray",
    "wof:placetype":"venue"
},
  "geometry": {"coordinates":[-1.7437490225,52.1227264404],"type":"Point"}
}