{
  "type": "Feature",
  "properties": {
    "addr:full":"Perth Agricultural Centre Perth Perth and Kinross PH1 3JJ",
    "addr:postcode":"ph1 3jj",
    "iso:country":"GB",
    "sg:address":"Perth Agricultural Centre",
    "sg:city":"Perth",
    "sg:classifiers":[
        {
            "category":"Banks & Credit Unions",
            "subcategory":"Investment Brokerage",
            "type":"Services"
        }
    ],
    "sg:phone":"+44 1738 631700",
    "sg:postcode":"PH1 3JJ",
    "sg:province":"Perth and Kinross",
    "sg:tags":[
        "contractor"
    ],
    "wof:name":"D Murray",
    "wof:placetype":"venue"
},
  "geometry": {"coordinates":[-3.5126390457,56.4157905579],"type":"Point"}
}