{
  "type": "Feature",
  "properties": {
    "addr:full":"23 Princess Street Manchester Greater Manchester M2 4ER",
    "addr:housenumber":"23",
    "addr:postcode":"m2 4er",
    "addr:street":"Princess Street",
    "iso:country":"GB",
    "sg:address":"23 Princess Street",
    "sg:city":"Manchester",
    "sg:classifiers":[
        {
            "category":"Professional",
            "subcategory":"Lawyer & Legal Services",
            "type":"Services"
        }
    ],
    "sg:phone":"+44 161 228 2061",
    "sg:postcode":"M2 4ER",
    "sg:province":"Greater Manchester",
    "sg:tags":[
        "solicitor"
    ],
    "wof:name":"Whittles",
    "wof:placetype":"venue"
},
  "geometry": {"coordinates":[-2.244332,53.479916],"type":"Point"}
}