{
  "type": "Feature",
  "properties": {
    "addr:full":"18 Cathedral Yard Exeter Devon EX1 1HE",
    "addr:housenumber":"18",
    "addr:postcode":"ex1 1he",
    "addr:street":"Cathedral Yard",
    "iso:country":"GB",
    "sg:address":"18 Cathedral Yard",
    "sg:city":"Exeter",
    "sg:classifiers":[
        {
            "category":"Real Estate",
            "subcategory":"Real Estate Agent",
            "type":"Services"
        }
    ],
    "sg:phone":"+44 1392 436244",
    "sg:postcode":"EX1 1HE",
    "sg:province":"Devon",
    "wof:name":"Michelmores Properties Ltd.",
    "wof:placetype":"venue"
},
  "geometry": {"coordinates":[-3.530796051,50.7232322693],"type":"Point"}
}