{
  "type": "Feature",
  "properties": {
    "addr:full":"Overshiel Farm, Midcalder Livingston City of Edinburgh EH53 0HT",
    "addr:postcode":"eh53 0ht",
    "addr:street":"Midcalder",
    "iso:country":"GB",
    "sg:address":"Overshiel Farm, Midcalder",
    "sg:city":"Livingston",
    "sg:classifiers":[
        {
            "category":"Building & Trades",
            "subcategory":"Construction",
            "type":"Services"
        }
    ],
    "sg:phone":"+44 1506 883006",
    "sg:postcode":"EH53 0HT",
    "sg:province":"City of Edinburgh",
    "sg:tags":[
        "window",
        "replacement"
    ],
    "wof:name":"Almond Valley Glazing Ltd.",
    "wof:placetype":"venue"
},
  "geometry": {"coordinates":[-3.4412000179,55.9051895142],"type":"Point"}
}