{
  "type": "Feature",
  "properties": {
    "addr:full":"1 Conington Rd London Greater London SE13 7LH",
    "addr:housenumber":"1",
    "addr:postcode":"se13 7lh",
    "addr:street":"Conington Rd",
    "iso:country":"GB",
    "sg:address":"1 Conington Rd",
    "sg:city":"London",
    "sg:classifiers":[
        {
            "category":"Shopping",
            "subcategory":"News",
            "type":"Retail Goods"
        }
    ],
    "sg:phone":"+44 20 8692 4465",
    "sg:postcode":"SE13 7LH",
    "sg:province":"Greater London",
    "sg:tags":[
        "newsagent"
    ],
    "wof:name":"Hardings News",
    "wof:placetype":"venue"
},
  "geometry": {"coordinates":[-0.016395,51.469185],"type":"Point"}
}