{
  "type": "Feature",
  "properties": {
    "iso:country":"GB",
    "sg:address":"Horn Hill, Barford St Michael",
    "sg:city":"Banbury",
    "sg:classifiers":[
        {
            "category":"Building & Trades",
            "subcategory":"Construction",
            "type":"Services"
        }
    ],
    "sg:phone":"+44 1869 338250",
    "sg:postcode":"OX15 0RQ",
    "sg:province":"Oxfordshire",
    "sg:tags":[
        "builder"
    ],
    "wof:name":"David Tew Builders",
    "wof:placetype":"venue"
},
  "geometry": {"coordinates":[-1.363634,51.989937],"type":"Point"}
}