{
  "type": "Feature",
  "properties": {
    "iso:country":"GB",
    "sg:address":"58 Gilbert Road, Bucksburn",
    "sg:city":"Aberdeen",
    "sg:classifiers":[
        {
            "category":"Home & Garden",
            "subcategory":"Household Appliances",
            "type":"Retail Goods"
        }
    ],
    "sg:postcode":"AB21 9AN",
    "sg:province":"Aberdeen City",
    "sg:tags":[
        "electrical"
    ],
    "wof:name":"Reid's Electrical Appliances",
    "wof:placetype":"venue"
},
  "geometry": {"coordinates":[-2.175329,57.177502],"type":"Point"}
}