{
  "type": "Feature",
  "properties": {
    "iso:country":"GB",
    "sg:address":"Radstock Road, Midsomer Norton",
    "sg:city":"Bath",
    "sg:classifiers":[
        {
            "category":"Retail",
            "subcategory":"Auto Repair",
            "type":"Services"
        }
    ],
    "sg:phone":"+44 1761 416444",
    "sg:postcode":"BA3 2AA",
    "sg:province":"Somerset",
    "sg:tags":[
        "body",
        "car",
        "repairer"
    ],
    "wof:name":"Riverside Bodyworks",
    "wof:placetype":"venue"
},
  "geometry": {"coordinates":[-2.469501,51.290562],"type":"Point"}
}