{
  "type": "Feature",
  "properties": {
    "iso:country":"GB",
    "sg:address":"Sherdley Road",
    "sg:city":"St Helens",
    "sg:classifiers":[
        {
            "category":"Travel",
            "subcategory":"Hostel",
            "type":"Entertainment"
        }
    ],
    "sg:phone":"+44 1744 451927",
    "sg:postcode":"WA9 5DQ",
    "sg:province":"Cheshire",
    "wof:name":"Sherdley House",
    "wof:placetype":"venue"
},
  "geometry": {"coordinates":[-2.7234539986,53.4434890747],"type":"Point"}
}