{
  "type": "Feature",
  "properties": {
    "addr:full":"Marcon House, Wyther Lane Industrial Estate Leeds West Yorkshire LS5 3BT",
    "addr:postcode":"ls5 3bt",
    "addr:street":"Wyther Lane Industrial Estate",
    "iso:country":"GB",
    "sg:address":"Marcon House, Wyther Lane Industrial Estate",
    "sg:city":"Leeds",
    "sg:classifiers":[
        {
            "category":"Professional",
            "subcategory":"Printing & Photocopies",
            "type":"Services"
        },
        {
            "category":"Manufacturing",
            "subcategory":"Signs",
            "type":"Manufacturing & Wholesale Goods"
        }
    ],
    "sg:phone":"+44 113 224 2124",
    "sg:postcode":"LS5 3BT",
    "sg:province":"West Yorkshire",
    "sg:tags":[
        "engraving",
        "supplier",
        "nameplate"
    ],
    "wof:name":"Ice Signs & Engraving",
    "wof:placetype":"venue"
},
  "geometry": {"coordinates":[-1.6071909666,53.8131752014],"type":"Point"}
}