{
  "type": "Feature",
  "properties": {
    "iso:country":"GB",
    "sg:address":"New Road, Wrockwardine Wood",
    "sg:city":"Telford",
    "sg:classifiers":[
        {
            "category":"Retail",
            "subcategory":"Auto Repair",
            "type":"Services"
        }
    ],
    "sg:phone":"+44 1952 614461",
    "sg:postcode":"TF2 7AA",
    "sg:province":"Shropshire",
    "sg:tags":[
        "body",
        "car"
    ],
    "wof:name":"Classic Bodycraft",
    "wof:placetype":"venue"
},
  "geometry": {"coordinates":[-2.4445819855,52.7077598572],"type":"Point"}
}