{
  "type": "Feature",
  "properties": {
    "addr:full":"31-33 Grimsby Road Cleethorpes Lincolnshire DN35 7AQ",
    "addr:housenumber":"31-33",
    "addr:postcode":"dn35 7aq",
    "addr:street":"Grimsby Road",
    "iso:country":"GB",
    "sg:address":"31-33 Grimsby Road",
    "sg:city":"Cleethorpes",
    "sg:classifiers":[
        {
            "category":"Professional",
            "subcategory":"Computer Services",
            "type":"Services"
        }
    ],
    "sg:phone":"+44 1472 362672",
    "sg:postcode":"DN35 7AQ",
    "sg:province":"Lincolnshire",
    "sg:tags":[
        "system",
        "software"
    ],
    "wof:name":"Vixsoft Systems Ltd.",
    "wof:placetype":"venue"
},
  "geometry": {"coordinates":[-0.054986,53.571266],"type":"Point"}
}