{
  "type": "Feature",
  "properties": {
    "iso:country":"GB",
    "sg:address":"Column House, 7 London Road",
    "sg:city":"Shrewsbury",
    "sg:classifiers":[
        {
            "category":"Education",
            "subcategory":"Library",
            "type":"Public Place"
        }
    ],
    "sg:phone":"+44 1743 255030",
    "sg:postcode":"SY2 6NW",
    "sg:province":"Shropshire",
    "sg:tags":[
        "book"
    ],
    "wof:name":"School Library Service",
    "wof:placetype":"venue"
},
  "geometry": {"coordinates":[-2.730876,52.703056],"type":"Point"}
}