{
  "type": "Feature",
  "properties": {
    "iso:country":"GB",
    "sg:address":"Holcombe Down Road",
    "sg:city":"Teignmouth",
    "sg:classifiers":[
        {
            "category":"Recreation",
            "subcategory":"Water Park",
            "type":"Entertainment"
        }
    ],
    "sg:phone":"+44 1626 770550",
    "sg:postcode":"TQ14 9NT",
    "sg:province":"Devon",
    "sg:tags":[
        "supplier",
        "bottled"
    ],
    "wof:name":"Haldon Springs",
    "wof:placetype":"venue"
},
  "geometry": {"coordinates":[-3.4982199669,50.5690040588],"type":"Point"}
}