{
  "type": "Feature",
  "properties": {
    "addr:full":"55 Regent Road Leicester Leicestershire LE1 6YF",
    "addr:housenumber":"55",
    "addr:postcode":"le1 6yf",
    "addr:street":"Regent Road",
    "iso:country":"GB",
    "sg:address":"55 Regent Road",
    "sg:city":"Leicester",
    "sg:classifiers":[
        {
            "category":"Professional",
            "subcategory":"Art Services",
            "type":"Services"
        }
    ],
    "sg:phone":"+44 116 285 5725",
    "sg:postcode":"LE1 6YF",
    "sg:province":"Leicestershire",
    "sg:tags":[
        "graphic",
        "designer"
    ],
    "wof:name":"Helen Dyson & Co",
    "wof:placetype":"venue"
},
  "geometry": {"coordinates":[-1.130503,52.628536],"type":"Point"}
}