{
  "type": "Feature",
  "properties": {
    "addr:full":"7 Upper St North, New Ash Grn Longfield Kent DA3 8JR",
    "addr:housenumber":"7",
    "addr:postcode":"da3 8jr",
    "addr:street":"Upper St North New Ash Grn Longfield",
    "iso:country":"GB",
    "sg:address":"7 Upper St North, New Ash Grn",
    "sg:city":"Longfield",
    "sg:classifiers":[
        {
            "category":"Personal",
            "subcategory":"Beauty Salon",
            "type":"Services"
        }
    ],
    "sg:phone":"+44 1474 873503",
    "sg:postcode":"DA3 8JR",
    "sg:province":"Kent",
    "sg:tags":[
        "unisex",
        "hairdresser"
    ],
    "wof:name":"Mario Edmund Hair Fashions",
    "wof:placetype":"venue"
},
  "geometry": {"coordinates":[0.30525,51.36615],"type":"Point"}
}