{
  "type": "Feature",
  "properties": {
    "iso:country":"GB",
    "sg:address":"14 Shearbridge Rd",
    "sg:city":"Bradford",
    "sg:classifiers":[
        {
            "category":"Organizations",
            "subcategory":"Non-profit Organization",
            "type":"Services"
        }
    ],
    "sg:phone":"+44 1274 721179",
    "sg:postcode":"BD7 1NP",
    "sg:province":"West Yorkshire",
    "sg:tags":[
        "organisation",
        "voluntary",
        "charity"
    ],
    "wof:name":"Polish Ex-Servicemens Club",
    "wof:placetype":"venue"
},
  "geometry": {"coordinates":[-1.771209,53.791538],"type":"Point"}
}