{
  "type": "Feature",
  "properties": {
    "iso:country":"GB",
    "sg:address":"Ash Gro",
    "sg:city":"Prescot",
    "sg:classifiers":[
        {
            "category":"Organizations",
            "subcategory":"Non-profit Organization",
            "type":"Services"
        }
    ],
    "sg:phone":"+44 151 426 3405",
    "sg:postcode":"L35 5BD",
    "sg:province":"Cheshire",
    "sg:tags":[
        "organisation",
        "voluntary",
        "charity"
    ],
    "wof:name":"The Salvation Army",
    "wof:placetype":"venue"
},
  "geometry": {"coordinates":[-2.7929449081,53.4243240356],"type":"Point"}
}