{
  "type": "Feature",
  "properties": {
    "addr:full":"7 Talbot Street Maesteg Bridgend CF34 9BT",
    "addr:housenumber":"7",
    "addr:postcode":"cf34 9bt",
    "addr:street":"Talbot Street",
    "iso:country":"GB",
    "sg:address":"7 Talbot Street",
    "sg:city":"Maesteg",
    "sg:classifiers":[
        {
            "category":"Shopping",
            "subcategory":"Clothing, Apparel, & Fashions",
            "type":"Retail Goods"
        }
    ],
    "sg:phone":"+44 1656 733931",
    "sg:postcode":"CF34 9BT",
    "sg:province":"Bridgend",
    "sg:tags":[
        "shop"
    ],
    "wof:name":"New Look",
    "wof:placetype":"venue"
},
  "geometry": {"coordinates":[-3.659916,51.608913],"type":"Point"}
}