{
  "type": "Feature",
  "properties": {
    "addr:full":"20 Sandgate Road Folkestone Kent CT20 1DP",
    "addr:housenumber":"20",
    "addr:postcode":"ct20 1dp",
    "addr:street":"Sandgate Road",
    "iso:country":"GB",
    "sg:address":"20 Sandgate Road",
    "sg:city":"Folkestone",
    "sg:classifiers":[
        {
            "category":"Shopping",
            "subcategory":"Shoes",
            "type":"Retail Goods"
        }
    ],
    "sg:phone":"+44 844 499 7432",
    "sg:postcode":"CT20 1DP",
    "sg:province":"Kent",
    "sg:tags":[
        "shop",
        "retailer",
        "footwear"
    ],
    "wof:name":"Clarks Shoes Ltd",
    "wof:placetype":"venue"
},
  "geometry": {"coordinates":[1.153461,51.075897],"type":"Point"}
}