{
  "type": "Feature",
  "properties": {
    "addr:full":"8 Franklin Pl Dumfries Dumfries and Galloway DG2 7RF",
    "addr:housenumber":"8",
    "addr:postcode":"dg2 7rf",
    "addr:street":"Franklin Pl",
    "iso:country":"GB",
    "sg:address":"8 Franklin Pl",
    "sg:city":"Dumfries",
    "sg:classifiers":[
        {
            "category":"Government",
            "subcategory":"Post Office",
            "type":"Public Place"
        }
    ],
    "sg:postcode":"DG2 7RF",
    "sg:province":"Dumfries and Galloway",
    "wof:name":"Troqueer Road Sub Post Office",
    "wof:placetype":"venue"
},
  "geometry": {"coordinates":[-3.6233139038,55.0661697388],"type":"Point"}
}