{
  "type": "Feature",
  "properties": {
    "iso:country":"GB",
    "sg:address":"56 The Grove, Iford",
    "sg:city":"Christchurch",
    "sg:classifiers":[
        {
            "category":"Wholesale",
            "subcategory":"Construction Materials",
            "type":"Manufacturing & Wholesale Goods"
        }
    ],
    "sg:postcode":"BH23 2HB",
    "sg:province":"Dorset",
    "sg:tags":[
        "merchant",
        "glass"
    ],
    "wof:name":"Swanston Glass Works",
    "wof:placetype":"venue"
},
  "geometry": {"coordinates":[-1.80243,50.746895],"type":"Point"}
}