{
  "type": "Feature",
  "properties": {
    "addr:full":"Care Of Harrods Brompton Road, Knightsbridge London Greater London SW1X 7QN",
    "addr:postcode":"sw1x 7qn",
    "addr:street":"Brompton Road",
    "iso:country":"GB",
    "sg:address":"Care Of Harrods Brompton Road, Knightsbridge",
    "sg:city":"London",
    "sg:classifiers":[
        {
            "category":"Retail",
            "subcategory":"Portrait Studio",
            "type":"Services"
        }
    ],
    "sg:phone":"+44 20 7722 9070",
    "sg:postcode":"SW1X 7QN",
    "sg:province":"Greater London",
    "sg:tags":[
        "photographic"
    ],
    "wof:name":"The Italiaander Portrait Studio",
    "wof:placetype":"venue"
},
  "geometry": {"coordinates":[-0.16135,51.50124],"type":"Point"}
}