{
  "type": "Feature",
  "properties": {
    "iso:country":"GB",
    "sg:address":"Thornhill Park Road",
    "sg:city":"Southampton",
    "sg:classifiers":[
        {
            "category":"Autos & Motor Vehicles",
            "subcategory":"Fuel & Gas Station",
            "type":"Retail Goods"
        }
    ],
    "sg:phone":"+44 23 8046 7940",
    "sg:postcode":"SO18 5TQ",
    "sg:province":"Hampshire",
    "sg:tags":[
        "petrol",
        "filling"
    ],
    "wof:name":"Star-Thornhill Service Station",
    "wof:placetype":"venue"
},
  "geometry": {"coordinates":[-1.33078897,50.9150161743],"type":"Point"}
}