{
  "type": "Feature",
  "properties": {
    "iso:country":"GB",
    "sg:address":"23 Duke Street",
    "sg:city":"St Helens",
    "sg:classifiers":[
        {
            "category":"Fast Food",
            "type":"Food & Drink"
        }
    ],
    "sg:phone":"+44 1744 29878",
    "sg:postcode":"WA10 2JE",
    "sg:province":"Merseyside",
    "sg:tags":[
        "away",
        "take"
    ],
    "wof:name":"Geno's",
    "wof:placetype":"venue"
},
  "geometry": {"coordinates":[-2.7402489185,53.4554595947],"type":"Point"}
}