{
  "type": "Feature",
  "properties": {
    "iso:country":"GB",
    "sg:address":"262 Wimborne Road West",
    "sg:city":"Wimborne",
    "sg:classifiers":[
        {
            "category":"Home & Garden",
            "subcategory":"Garden Supply",
            "type":"Retail Goods"
        }
    ],
    "sg:phone":"+44 1202 874283",
    "sg:postcode":"BH21 2DZ",
    "sg:province":"Dorset",
    "sg:tags":[
        "nursery",
        "centre"
    ],
    "wof:name":"Barthelemy & Co",
    "wof:placetype":"venue"
},
  "geometry": {"coordinates":[-1.932349,50.803501],"type":"Point"}
}