{
  "type": "Feature",
  "properties": {
    "iso:country":"GB",
    "sg:address":"Castle Hill House, School Lane",
    "sg:city":"St. Neots",
    "sg:classifiers":[
        {
            "category":"Real Estate",
            "subcategory":"Developer",
            "type":"Services"
        }
    ],
    "sg:phone":"+44 1480 212716",
    "sg:postcode":"PE19 8HN",
    "sg:province":"Bedfordshire",
    "sg:tags":[
        "property"
    ],
    "wof:name":"Castle Hills Securities Plc",
    "wof:placetype":"venue"
},
  "geometry": {"coordinates":[-0.2855089903,52.214630127],"type":"Point"}
}