{
  "type": "Feature",
  "properties": {
    "addr:full":"Kingsley House Small Business, Centre  20 Winmarleigh Street Warrington Cheshire WA1 1JY",
    "addr:housenumber":"20",
    "addr:postcode":"wa1 1jy",
    "addr:street":"Winmarleigh Street",
    "iso:country":"GB",
    "sg:address":"Kingsley House Small Business, Centre  20 Winmarleigh Street",
    "sg:city":"Warrington",
    "sg:classifiers":[
        {
            "category":"Building & Trades",
            "subcategory":"Construction",
            "type":"Services"
        }
    ],
    "sg:postcode":"WA1 1JY",
    "sg:province":"Cheshire",
    "sg:tags":[
        "contractor"
    ],
    "wof:name":"Freeman Construction Ltd",
    "wof:placetype":"venue"
},
  "geometry": {"coordinates":[-2.598870039,53.3862800598],"type":"Point"}
}