{
  "type": "Feature",
  "properties": {
    "iso:country":"GB",
    "sg:address":"Farthing Grove",
    "sg:city":"Milton Keynes",
    "sg:classifiers":[
        {
            "category":"Health Services",
            "subcategory":"Doctor",
            "type":"Services"
        }
    ],
    "sg:phone":"+44 1908 668453",
    "sg:postcode":"MK6 4JH",
    "sg:province":"Buckinghamshire",
    "sg:tags":[
        "practitioners"
    ],
    "wof:name":"The Grove Surgery",
    "wof:placetype":"venue"
},
  "geometry": {"coordinates":[-0.7308840156,52.0175361633],"type":"Point"}
}