{
  "type": "Feature",
  "properties": {
    "addr:full":"Unit 3 Forest Gate, White Lund Industrial Estate Morecambe Lancashire LA3 3PD",
    "addr:housenumber":"unit 3",
    "addr:postcode":"la3 3pd",
    "addr:street":"Forest Gate White Lund Industrial Estate",
    "iso:country":"GB",
    "sg:address":"Unit 3 Forest Gate, White Lund Industrial Estate",
    "sg:city":"Morecambe",
    "sg:classifiers":[
        {
            "category":"Shopping",
            "subcategory":"Discount & Variety Stores",
            "type":"Retail Goods"
        }
    ],
    "sg:phone":"+44 1524 842795",
    "sg:postcode":"LA3 3PD",
    "sg:province":"Lancashire",
    "sg:tags":[
        "cleaning",
        "supply"
    ],
    "wof:name":"Precision Plastics (Morecombe)",
    "wof:placetype":"venue"
},
  "geometry": {"coordinates":[-2.8349239826,54.059135437],"type":"Point"}
}