{
  "type": "Feature",
  "properties": {
    "addr:full":"Park Avenue South Shields Tyne and Wear NE34 8AB",
    "addr:postcode":"ne34 8ab",
    "addr:street":"Park Avenue",
    "iso:country":"GB",
    "sg:address":"Park Avenue",
    "sg:city":"South Shields",
    "sg:classifiers":[
        {
            "category":"Education",
            "subcategory":"School",
            "type":"Public Place"
        },
        {
            "category":"Government",
            "subcategory":"Office",
            "type":"Public Place"
        }
    ],
    "sg:phone":"+44 191 455 2865",
    "sg:postcode":"NE34 8AB",
    "sg:province":"Tyne and Wear",
    "sg:tags":[
        "local",
        "authority"
    ],
    "wof:name":"Ridgeway Junior Mixed & Infant School",
    "wof:placetype":"venue"
},
  "geometry": {"coordinates":[-1.4096690416,54.9686546326],"type":"Point"}
}