{
  "type": "Feature",
  "properties": {
    "addr:full":"Palmerston Road Chatham Kent ME4 6LU",
    "addr:postcode":"me4 6lu",
    "addr:street":"Palmerston Road",
    "iso:country":"GB",
    "sg:address":"Palmerston Road",
    "sg:city":"Chatham",
    "sg:classifiers":[
        {
            "category":"Social Services",
            "subcategory":"Retirement Home",
            "type":"Services"
        }
    ],
    "sg:phone":"+44 1634 843745",
    "sg:postcode":"ME4 6LU",
    "sg:province":"Kent",
    "sg:tags":[
        "rest"
    ],
    "wof:name":"Churchlands Old Peoples Home",
    "wof:placetype":"venue"
},
  "geometry": {"coordinates":[0.5254,51.371525],"type":"Point"}
}