{
  "type": "Feature",
  "properties": {
    "iso:country":"GB",
    "sg:address":"49 Museum Street",
    "sg:city":"Warrington",
    "sg:classifiers":[
        {
            "category":"Banks & Credit Unions",
            "subcategory":"Bank",
            "type":"Services"
        },
        {
            "category":"Banks & Credit Unions",
            "subcategory":"Financial Services",
            "type":"Services"
        }
    ],
    "sg:postcode":"WA1 1LD",
    "sg:province":"Cheshire",
    "sg:tags":[
        "consultant",
        "institution"
    ],
    "wof:name":"The Barstow Trust Ltd.",
    "wof:placetype":"venue"
},
  "geometry": {"coordinates":[-2.60014,53.386742],"type":"Point"}
}