{
  "type": "Feature",
  "properties": {
    "addr:full":"Huntington Farm, Little Wenlock Telford Shropshire TF6 5AP",
    "addr:postcode":"tf6 5ap",
    "iso:country":"GB",
    "sg:address":"Huntington Farm, Little Wenlock",
    "sg:city":"Telford",
    "sg:classifiers":[
        {
            "category":"Farming",
            "subcategory":"Farm",
            "type":"Manufacturing & Wholesale Goods"
        }
    ],
    "sg:postcode":"TF6 5AP",
    "sg:province":"Shropshire",
    "sg:tags":[
        "mixed",
        "crop"
    ],
    "wof:name":"Stephen J L Roberts",
    "wof:placetype":"venue"
},
  "geometry": {"coordinates":[-2.5229980946,52.6593818665],"type":"Point"}
}