{
  "type": "Feature",
  "properties": {
    "iso:country":"GB",
    "sg:address":"Giffords Lane, Clopton",
    "sg:city":"Newmarket",
    "sg:classifiers":[
        {
            "category":"Farming",
            "subcategory":"Livestock Farm",
            "type":"Manufacturing & Wholesale Goods"
        },
        {
            "category":"Wholesale",
            "subcategory":"Fruits & Vegetables",
            "type":"Manufacturing & Wholesale Goods"
        }
    ],
    "sg:phone":"+44 1440 820200",
    "sg:postcode":"CB8 8PQ",
    "sg:province":"Cambridgeshire",
    "sg:tags":[
        "others"
    ],
    "wof:name":"Clopton Hall Farms Ltd.",
    "wof:placetype":"venue"
},
  "geometry": {"coordinates":[0.58438,52.158871],"type":"Point"}
}