{
  "type": "Feature",
  "properties": {
    "iso:country":"GB",
    "sg:address":"7 Gregson Close",
    "sg:city":"Gosport",
    "sg:classifiers":[
        {
            "category":"Building & Trades",
            "subcategory":"Construction",
            "type":"Services"
        }
    ],
    "sg:phone":"+44 1329 826563",
    "sg:postcode":"PO13 0PL",
    "sg:province":"Hampshire",
    "sg:tags":[
        "dry",
        "lining",
        "plasterers",
        "screeders"
    ],
    "wof:name":"D S Plastering & Floor Screeding Services",
    "wof:placetype":"venue"
},
  "geometry": {"coordinates":[-1.177683,50.827312],"type":"Point"}
}