{
  "type": "Feature",
  "properties": {
    "iso:country":"GB",
    "sg:address":"1 Rangemore Hall Mews, Rangemore",
    "sg:city":"Burton-on-trent",
    "sg:classifiers":[
        {
            "category":"Professional",
            "subcategory":"Computer Services",
            "type":"Services"
        }
    ],
    "sg:phone":"+44 1283 716400",
    "sg:postcode":"DE13 9RE",
    "sg:province":"Derbyshire",
    "sg:tags":[
        "system",
        "software"
    ],
    "wof:name":"Rangemore Software Ltd.",
    "wof:placetype":"venue"
},
  "geometry": {"coordinates":[-1.737909,52.799999],"type":"Point"}
}