{
  "type": "Feature",
  "properties": {
    "addr:full":"2 Hillmarton Road London Greater London N7 9JR",
    "addr:housenumber":"2",
    "addr:postcode":"n7 9jr",
    "addr:street":"Hillmarton Road",
    "iso:country":"GB",
    "sg:address":"2 Hillmarton Road",
    "sg:city":"London",
    "sg:classifiers":[
        {
            "category":"Personal",
            "subcategory":"Beauty Salon",
            "type":"Services"
        }
    ],
    "sg:phone":"+44 20 7607 2006",
    "sg:postcode":"N7 9JR",
    "sg:province":"Greater London",
    "sg:tags":[
        "unisex",
        "hairdresser"
    ],
    "wof:name":"Salem",
    "wof:placetype":"venue"
},
  "geometry": {"coordinates":[-0.123409,51.553066],"type":"Point"}
}