{
  "type": "Feature",
  "properties": {
    "addr:full":"41 Hallington Drive Heanor Derbyshire DE75 7QX",
    "addr:housenumber":"41",
    "addr:postcode":"de75 7qx",
    "addr:street":"Hallington Drive",
    "iso:country":"GB",
    "sg:address":"41 Hallington Drive",
    "sg:city":"Heanor",
    "sg:classifiers":[
        {
            "category":"Building & Trades",
            "subcategory":"Construction",
            "type":"Services"
        }
    ],
    "sg:phone":"+44 1773 761948",
    "sg:postcode":"DE75 7QX",
    "sg:province":"Derbyshire",
    "sg:tags":[
        "builder"
    ],
    "wof:name":"Christopher Havill",
    "wof:placetype":"venue"
},
  "geometry": {"coordinates":[-1.365634,53.013176],"type":"Point"}
}