{
  "type": "Feature",
  "properties": {
    "addr:full":"30 Station Road Newbridge City of Edinburgh EH28 8PT",
    "addr:housenumber":"30",
    "addr:postcode":"eh28 8pt",
    "addr:street":"Station Road",
    "iso:country":"GB",
    "sg:address":"30 Station Road",
    "sg:city":"Newbridge",
    "sg:classifiers":[
        {
            "category":"Food & Beverages",
            "subcategory":"Fruits & Vegetables",
            "type":"Retail Goods"
        }
    ],
    "sg:postcode":"EH28 8PT",
    "sg:province":"City of Edinburgh",
    "sg:tags":[
        "greengrocer"
    ],
    "wof:name":"McClouds",
    "wof:placetype":"venue"
},
  "geometry": {"coordinates":[-3.391239,55.93745],"type":"Point"}
}