{
  "type": "Feature",
  "properties": {
    "addr:full":"31 Pheasant Road, Trebanos Pontdawe Swansea Neath Port Talbot SA8 4DP",
    "addr:housenumber":"31",
    "addr:postcode":"sa8 4dp",
    "addr:street":"Pheasant Road Trebanos Pontdawe",
    "iso:country":"GB",
    "sg:address":"31 Pheasant Road, Trebanos Pontdawe",
    "sg:city":"Swansea",
    "sg:classifiers":[
        {
            "category":"Building & Trades",
            "subcategory":"Construction",
            "type":"Services"
        }
    ],
    "sg:phone":"+44 1792 830852",
    "sg:postcode":"SA8 4DP",
    "sg:province":"Neath Port Talbot",
    "sg:tags":[
        "builder"
    ],
    "wof:name":"R Roderick Building & Roofing",
    "wof:placetype":"venue"
},
  "geometry": {"coordinates":[-3.8694450855,51.7086219788],"type":"Point"}
}