{
  "type": "Feature",
  "properties": {
    "iso:country":"GB",
    "sg:address":"Pudding Mill Lane",
    "sg:city":"London",
    "sg:classifiers":[
        {
            "category":"Home & Garden",
            "subcategory":"Building Materials",
            "type":"Retail Goods"
        }
    ],
    "sg:phone":"+44 20 8519 5114",
    "sg:postcode":"E15 2PJ",
    "sg:province":"Greater London",
    "sg:tags":[
        "ready",
        "mixed",
        "concrete"
    ],
    "wof:name":"Tarmac Topmix Ltd.",
    "wof:placetype":"venue"
},
  "geometry": {"coordinates":[-0.012564,51.533596],"type":"Point"}
}