{
  "type": "Feature",
  "properties": {
    "addr:full":"Lyde Hill Farm, Woodville Gillingham Dorset SP8 5LX",
    "addr:postcode":"sp8 5lx",
    "addr:street":"Lyde Hill;Woodville",
    "iso:country":"GB",
    "sg:address":"Lyde Hill Farm, Woodville",
    "sg:city":"Gillingham",
    "sg:classifiers":[
        {
            "category":"Farming",
            "subcategory":"Dairy Farm",
            "type":"Manufacturing & Wholesale Goods"
        }
    ],
    "sg:postcode":"SP8 5LX",
    "sg:province":"Dorset",
    "wof:name":"C N Trim",
    "wof:placetype":"venue"
},
  "geometry": {"coordinates":[-2.2786200047,51.0380973816],"type":"Point"}
}