{
  "type": "Feature",
  "properties": {
    "iso:country":"GB",
    "sg:address":"Lodge Farm, Redenhall",
    "sg:city":"Harleston",
    "sg:classifiers":[
        {
            "category":"Farming",
            "subcategory":"Crops",
            "type":"Manufacturing & Wholesale Goods"
        },
        {
            "category":"Farming",
            "subcategory":"Farm",
            "type":"Manufacturing & Wholesale Goods"
        }
    ],
    "sg:phone":"+44 1379 852280",
    "sg:postcode":"IP20 9NY",
    "sg:province":"Norfolk",
    "sg:tags":[
        "mixed",
        "arable"
    ],
    "wof:name":"Gawdy Hall Estates Ltd",
    "wof:placetype":"venue"
},
  "geometry": {"coordinates":[1.298415,52.401409],"type":"Point"}
}