{
  "type": "Feature",
  "properties": {
    "iso:country":"GB",
    "sg:address":"84 Station Rd",
    "sg:city":"New Milton",
    "sg:classifiers":[
        {
            "category":"Education",
            "subcategory":"College",
            "type":"Public Place"
        }
    ],
    "sg:phone":"+44 1425 617277",
    "sg:postcode":"BH25 6LE",
    "sg:province":"Hampshire",
    "sg:tags":[
        "school"
    ],
    "wof:name":"Impact School Wear Centre",
    "wof:placetype":"venue"
},
  "geometry": {"coordinates":[-1.6554269791,50.7532806396],"type":"Point"}
}