{
  "type": "Feature",
  "properties": {
    "iso:country":"GB",
    "sg:address":"172 Copenhagen Street",
    "sg:city":"London",
    "sg:classifiers":[
        {
            "category":"Building & Trades",
            "subcategory":"Plumbing",
            "type":"Services"
        }
    ],
    "sg:phone":"+44 20 7837 3793",
    "sg:postcode":"N1 0ST",
    "sg:province":"Greater London",
    "sg:tags":[
        "heating"
    ],
    "wof:name":"Heddonglow Exhibitions Ltd.",
    "wof:placetype":"venue"
},
  "geometry": {"coordinates":[-0.119463,51.537136],"type":"Point"}
}