{
  "type": "Feature",
  "properties": {
    "addr:full":"79 Alexandra Road Blackpool Lancashire FY1 6HW",
    "addr:housenumber":"79",
    "addr:postcode":"fy1 6hw",
    "addr:street":"Alexandra Road",
    "iso:country":"GB",
    "sg:address":"79 Alexandra Road",
    "sg:city":"Blackpool",
    "sg:classifiers":[
        {
            "category":"Travel",
            "subcategory":"Hotels & Motels",
            "type":"Entertainment"
        }
    ],
    "sg:phone":"+44 1253 346170",
    "sg:postcode":"FY1 6HW",
    "sg:province":"Lancashire",
    "wof:name":"Rivelin House",
    "wof:placetype":"venue"
},
  "geometry": {"coordinates":[-3.0501461029,53.8014068604],"type":"Point"}
}