{
  "type": "Feature",
  "properties": {
    "addr:full":"11 Westwood View West Calder South Lanarkshire EH55 8PY",
    "addr:housenumber":"11",
    "addr:postcode":"eh55 8py",
    "addr:street":"Westwood View West",
    "iso:country":"GB",
    "sg:address":"11 Westwood View",
    "sg:city":"West Calder",
    "sg:classifiers":[
        {
            "category":"Building & Trades",
            "subcategory":"Plumbing",
            "type":"Services"
        }
    ],
    "sg:phone":"+44 1506 872208",
    "sg:postcode":"EH55 8PY",
    "sg:province":"South Lanarkshire",
    "sg:tags":[
        "heating"
    ],
    "wof:name":"Almond Valley Homes Ltd.",
    "wof:placetype":"venue"
},
  "geometry": {"coordinates":[-3.5723719597,55.8511238098],"type":"Point"}
}