{
  "type": "Feature",
  "properties": {
    "iso:country":"GB",
    "sg:address":"Foxley Lane",
    "sg:city":"Stoke-on-trent",
    "sg:classifiers":[
        {
            "category":"Professional",
            "subcategory":"Engineering",
            "type":"Services"
        }
    ],
    "sg:phone":"+44 1782 536503",
    "sg:postcode":"ST2 7EH",
    "sg:province":"Staffordshire",
    "wof:name":"Industrial & Agricultural Engineers",
    "wof:placetype":"venue"
},
  "geometry": {"coordinates":[-2.150219,53.049919],"type":"Point"}
}