{
  "type": "Feature",
  "properties": {
    "iso:country":"GB",
    "sg:address":"St Stephens La",
    "sg:city":"Ipswich",
    "sg:classifiers":[
        {
            "category":"Personal",
            "subcategory":"Beauty Salon",
            "type":"Services"
        }
    ],
    "sg:phone":"+44 1473 287077",
    "sg:postcode":"IP1 1DP",
    "sg:province":"Suffolk",
    "sg:tags":[
        "unisex",
        "hairdresser"
    ],
    "wof:name":"Supercuts",
    "wof:placetype":"venue"
},
  "geometry": {"coordinates":[1.155373,52.056587],"type":"Point"}
}