{
  "type": "Feature",
  "properties": {
    "iso:country":"GB",
    "sg:address":"Aincroft, Cove Road",
    "sg:city":"Fleet",
    "sg:classifiers":[
        {
            "category":"Building & Trades",
            "subcategory":"Plumbing",
            "type":"Services"
        }
    ],
    "sg:phone":"+44 1252 616292",
    "sg:postcode":"GU51 2RT",
    "sg:province":"Hampshire",
    "sg:tags":[
        "heating"
    ],
    "wof:name":"David Richard Clapson Heating & Plumbing",
    "wof:placetype":"venue"
},
  "geometry": {"coordinates":[-0.81013,51.292839],"type":"Point"}
}