{
  "type": "Feature",
  "properties": {
    "addr:full":"109 Alum Rock Road Birmingham West Midlands B8 1ND",
    "addr:housenumber":"109;b8",
    "addr:postcode":"1nd",
    "addr:street":"Alum Rock Road",
    "iso:country":"GB",
    "sg:address":"109 Alum Rock Road",
    "sg:city":"Birmingham",
    "sg:classifiers":[
        {
            "category":"Food & Beverages",
            "subcategory":"Meat & Fish",
            "type":"Retail Goods"
        }
    ],
    "sg:phone":"+44 121 327 3329",
    "sg:postcode":"B8 1ND",
    "sg:province":"West Midlands",
    "sg:tags":[
        "butcher"
    ],
    "wof:name":"M Zaffer",
    "wof:placetype":"venue"
},
  "geometry": {"coordinates":[-1.854823947,52.4899597168],"type":"Point"}
}