{
  "type": "Feature",
  "properties": {
    "iso:country":"GB",
    "sg:address":"23 Downie Park",
    "sg:city":"Dundee",
    "sg:classifiers":[
        {
            "category":"Shopping",
            "subcategory":"Computers & Home Electronics",
            "type":"Retail Goods"
        }
    ],
    "sg:phone":"+44 1382 811021",
    "sg:postcode":"DD3 8JW",
    "sg:province":"Dundee City",
    "sg:tags":[
        "aerial",
        "television",
        "radio"
    ],
    "wof:name":"Connachan Aerials",
    "wof:placetype":"venue"
},
  "geometry": {"coordinates":[-2.973735,56.481071],"type":"Point"}
}