{
  "type": "Feature",
  "properties": {
    "iso:country":"GB",
    "sg:address":"The Cottage, Gay Street Lane, North Heath",
    "sg:city":"Pulborough",
    "sg:classifiers":[
        {
            "category":"Shopping",
            "subcategory":"Department Store",
            "type":"Retail Goods"
        },
        {
            "category":"Retail",
            "subcategory":"Repair Shop",
            "type":"Services"
        }
    ],
    "sg:phone":"+44 1798 875591",
    "sg:postcode":"RH20 2HW",
    "sg:province":"West Sussex",
    "sg:tags":[
        "watch",
        "sale",
        "clock"
    ],
    "wof:name":"The Clock Doctor",
    "wof:placetype":"venue"
},
  "geometry": {"coordinates":[-0.511879,50.957077],"type":"Point"}
}