{
  "type": "Feature",
  "properties": {
    "addr:full":"99 Spring Road, Tyseley Birmingham West Midlands B11 3DJ",
    "addr:housenumber":"99",
    "addr:postcode":"b11 3dj",
    "addr:street":"Spring Road",
    "iso:country":"GB",
    "sg:address":"99 Spring Road, Tyseley",
    "sg:city":"Birmingham",
    "sg:classifiers":[
        {
            "category":"Home & Garden",
            "subcategory":"Hardware",
            "type":"Retail Goods"
        }
    ],
    "sg:postcode":"B11 3DJ",
    "sg:province":"West Midlands",
    "sg:tags":[
        "fixing",
        "nuts",
        "bolt"
    ],
    "wof:name":"Thomas Eaves Ltd.",
    "wof:placetype":"venue"
},
  "geometry": {"coordinates":[-1.841809,52.446098],"type":"Point"}
}