{
  "type": "Feature",
  "properties": {
    "addr:full":"345 Upper Richmond Road West London Greater London SW14 8QN",
    "addr:housenumber":"345",
    "addr:postcode":"sw14 8qn",
    "addr:street":"Upper Richmond Road West",
    "iso:country":"GB",
    "sg:address":"345 Upper Richmond Road West",
    "sg:city":"London",
    "sg:classifiers":[
        {
            "category":"Professional",
            "subcategory":"Accounting & Tax Preparation",
            "type":"Services"
        }
    ],
    "sg:phone":"+44 20 8876 7196",
    "sg:postcode":"SW14 8QN",
    "sg:province":"Greater London",
    "sg:tags":[
        "accountant"
    ],
    "wof:name":"Finch & Co.",
    "wof:placetype":"venue"
},
  "geometry": {"coordinates":[-0.265666,51.464725],"type":"Point"}
}