{
  "type": "Feature",
  "properties": {
    "addr:full":"Clay Cottage, Southburgh Road, Cranworth Thetford Norfolk IP25 7SG",
    "addr:postcode":"ip25 7sg",
    "addr:street":"Southburgh Road",
    "iso:country":"GB",
    "sg:address":"Clay Cottage, Southburgh Road, Cranworth",
    "sg:city":"Thetford",
    "sg:classifiers":[
        {
            "category":"Transit Center",
            "subcategory":"Passenger",
            "type":"Transportation"
        },
        {
            "category":"Retail",
            "subcategory":"Pet Boarding",
            "type":"Services"
        }
    ],
    "sg:phone":"+44 1362 820694",
    "sg:postcode":"IP25 7SG",
    "sg:province":"Norfolk",
    "sg:tags":[
        "kennel",
        "catteries"
    ],
    "wof:name":"Clay Cottage Cattery",
    "wof:placetype":"venue"
},
  "geometry": {"coordinates":[0.947821,52.603485],"type":"Point"}
}