{
  "type": "Feature",
  "properties": {
    "addr:full":"5 Whitehall Crescent Dundee Dundee City DD1 4AR",
    "addr:housenumber":"5",
    "addr:postcode":"dd1 4ar",
    "addr:street":"Whitehall Crescent",
    "iso:country":"GB",
    "sg:address":"5 Whitehall Crescent",
    "sg:city":"Dundee",
    "sg:classifiers":[
        {
            "category":"Insurance",
            "subcategory":"Insurance Agent",
            "type":"Services"
        }
    ],
    "sg:phone":"+44 1382 227881",
    "sg:postcode":"DD1 4AR",
    "sg:province":"Dundee City",
    "wof:name":"Royal & SunAlliance",
    "wof:placetype":"venue"
},
  "geometry": {"coordinates":[-2.9695279598,56.4595794678],"type":"Point"}
}