{
  "type": "Feature",
  "properties": {
    "addr:full":"Funerals & Protection Of Property, 1 Duchess Pl Birmingham West Midlands B16 8NX",
    "addr:housenumber":"1",
    "addr:postcode":"b16 8nx",
    "addr:street":"Duchess Pl",
    "iso:country":"GB",
    "sg:address":"Funerals & Protection Of Property, 1 Duchess Pl",
    "sg:city":"Birmingham",
    "sg:classifiers":[
        {
            "category":"Government",
            "subcategory":"Office",
            "type":"Public Place"
        }
    ],
    "sg:phone":"+44 121 303 4012",
    "sg:postcode":"B16 8NX",
    "sg:province":"West Midlands",
    "sg:tags":[
        "local"
    ],
    "wof:name":"Birmingham City Council",
    "wof:placetype":"venue"
},
  "geometry": {"coordinates":[-1.9235589504,52.4734306335],"type":"Point"}
}