{
  "type": "Feature",
  "properties": {
    "addr:full":"The Priory, West End, Middleham Leyburn North Yorkshire DL8 4QG",
    "addr:postcode":"dl8 4qg",
    "addr:street":"West",
    "iso:country":"GB",
    "sg:address":"The Priory, West End, Middleham",
    "sg:city":"Leyburn",
    "sg:classifiers":[
        {
            "category":"Travel",
            "subcategory":"Hotels & Motels",
            "type":"Entertainment"
        }
    ],
    "sg:postcode":"DL8 4QG",
    "sg:province":"North Yorkshire",
    "sg:tags":[
        "house",
        "guest"
    ],
    "wof:name":"S & E Frisby",
    "wof:placetype":"venue"
},
  "geometry": {"coordinates":[-1.805319,54.285255],"type":"Point"}
}