{
  "type": "Feature",
  "properties": {
    "iso:country":"GB",
    "sg:address":"15 Clinton Drive",
    "sg:city":"Sleaford",
    "sg:classifiers":[
        {
            "category":"Retail",
            "subcategory":"Driving School",
            "type":"Services"
        }
    ],
    "sg:postcode":"NG34 7LU",
    "sg:province":"Lincolnshire",
    "wof:name":"Causeway School of Motoring",
    "wof:placetype":"venue"
},
  "geometry": {"coordinates":[-0.420338,52.990288],"type":"Point"}
}