{
  "type": "Feature",
  "properties": {
    "iso:country":"GB",
    "sg:address":"Oak Tree Farm, West Street Lane, Maynards Green",
    "sg:city":"Heathfield",
    "sg:classifiers":[
        {
            "category":"Manufacturing",
            "subcategory":"Wood Products",
            "type":"Manufacturing & Wholesale Goods"
        }
    ],
    "sg:phone":"+44 1435 813505",
    "sg:postcode":"TN21 0DB",
    "sg:province":"East Sussex",
    "wof:name":"The Timber Workshop (Design) Ltd.",
    "wof:placetype":"venue"
},
  "geometry": {"coordinates":[0.250381,50.945225],"type":"Point"}
}