{
  "type": "Feature",
  "properties": {
    "addr:full":"Harrisons Drove, Upware Fen Ely Cambridgeshire CB7 5YQ",
    "addr:postcode":"cb7 5yq",
    "iso:country":"GB",
    "sg:address":"Harrisons Drove, Upware Fen",
    "sg:city":"Ely",
    "sg:classifiers":[
        {
            "category":"Farming",
            "subcategory":"Livestock Farm",
            "type":"Manufacturing & Wholesale Goods"
        }
    ],
    "sg:phone":"+44 1223 860844",
    "sg:postcode":"CB7 5YQ",
    "sg:province":"Cambridgeshire",
    "sg:tags":[
        "others"
    ],
    "wof:name":"Percy Watts",
    "wof:placetype":"venue"
},
  "geometry": {"coordinates":[0.258706,52.297707],"type":"Point"}
}