{
  "type": "Feature",
  "properties": {
    "addr:full":"Cavour Street Burnley Lancashire BB12 0BQ",
    "addr:postcode":"bb12 0bq",
    "addr:street":"Cavour Street",
    "iso:country":"GB",
    "sg:address":"Cavour Street",
    "sg:city":"Burnley",
    "sg:classifiers":[
        {
            "category":"Professional",
            "subcategory":"Printing & Photocopies",
            "type":"Services"
        }
    ],
    "sg:postcode":"BB12 0BQ",
    "sg:province":"Lancashire",
    "sg:tags":[
        "printer"
    ],
    "wof:name":"Derek Murray",
    "wof:placetype":"venue"
},
  "geometry": {"coordinates":[-2.2512440681,53.7965698242],"type":"Point"}
}