{
  "type": "Feature",
  "properties": {
    "iso:country":"GB",
    "sg:address":"Arthur St, Lakeside",
    "sg:city":"Redditch",
    "sg:classifiers":[
        {
            "category":"Professional",
            "subcategory":"Printing & Photocopies",
            "type":"Services"
        }
    ],
    "sg:postcode":"B98 8JY",
    "sg:province":"Warwickshire",
    "sg:tags":[
        "printer"
    ],
    "wof:name":"Kingfisher Print Ltd",
    "wof:placetype":"venue"
},
  "geometry": {"coordinates":[-1.919659,52.305103],"type":"Point"}
}