{
  "type": "Feature",
  "properties": {
    "addr:full":"Panther House London Greater London WC1X 0AP",
    "addr:postcode":"wc1x 0ap",
    "iso:country":"GB",
    "sg:address":"Panther House",
    "sg:city":"London",
    "sg:classifiers":[
        {
            "category":"Shopping",
            "subcategory":"Music",
            "type":"Retail Goods"
        }
    ],
    "sg:postcode":"WC1X 0AP",
    "sg:province":"Greater London",
    "sg:tags":[
        "record",
        "tape",
        "cd"
    ],
    "wof:name":"Rd",
    "wof:placetype":"venue"
},
  "geometry": {"coordinates":[-0.0879139975,51.5073699951],"type":"Point"}
}