{
  "type": "Feature",
  "properties": {
    "iso:country":"GB",
    "sg:address":"9 Brierydale Lane, Stainburn",
    "sg:city":"Workington",
    "sg:classifiers":[
        {
            "category":"Retail",
            "subcategory":"Driving School",
            "type":"Services"
        }
    ],
    "sg:phone":"+44 1900 64058",
    "sg:postcode":"CA14 4UH",
    "sg:province":"Cumbria",
    "wof:name":"Harold Heaton",
    "wof:placetype":"venue"
},
  "geometry": {"coordinates":[-3.521649,54.645721],"type":"Point"}
}