{
  "type": "Feature",
  "properties": {
    "addr:full":"17 Eagle Gardens Bedford Bedfordshire MK41 7FE",
    "addr:housenumber":"17",
    "addr:postcode":"mk41 7fe",
    "addr:street":"Eagle Gardens",
    "iso:country":"GB",
    "sg:address":"17 Eagle Gardens",
    "sg:city":"Bedford",
    "sg:classifiers":[
        {
            "category":"Professional",
            "subcategory":"Detective & Security Services",
            "type":"Services"
        }
    ],
    "sg:phone":"+44 1234 340440",
    "sg:postcode":"MK41 7FE",
    "sg:province":"Bedfordshire",
    "sg:tags":[
        "locksmith"
    ],
    "wof:name":"Ashtons Locksmiths",
    "wof:placetype":"venue"
},
  "geometry": {"coordinates":[-0.4707329869,52.1513214111],"type":"Point"}
}