{
  "type": "Feature",
  "properties": {
    "iso:country":"GB",
    "sg:address":"North Lane",
    "sg:city":"Weston-super-mare",
    "sg:classifiers":[
        {
            "category":"Building & Trades",
            "subcategory":"Plumbing",
            "type":"Services"
        }
    ],
    "sg:phone":"+44 1934 621496",
    "sg:postcode":"BS23 1QR",
    "sg:province":"Somerset",
    "sg:tags":[
        "heating"
    ],
    "wof:name":"Frys Plumbing & Heating",
    "wof:placetype":"venue"
},
  "geometry": {"coordinates":[-2.977859,51.34922],"type":"Point"}
}