{
  "type": "Feature",
  "properties": {
    "iso:country":"GB",
    "sg:address":"Chelsea House, Heysham Rd",
    "sg:city":"Bootle",
    "sg:classifiers":[
        {
            "category":"Home & Garden",
            "subcategory":"Home Furnishings",
            "type":"Retail Goods"
        },
        {
            "category":"Manufacturing",
            "subcategory":"Furniture",
            "type":"Manufacturing & Wholesale Goods"
        }
    ],
    "sg:phone":"+44 151 523 3773",
    "sg:postcode":"L30 6UZ",
    "sg:province":"Merseyside",
    "sg:tags":[
        "homefurnishings",
        "soft",
        "manufacturer"
    ],
    "wof:name":"Chelsea Kitchens & Bedrooms Ltd",
    "wof:placetype":"venue"
},
  "geometry": {"coordinates":[-2.961499,53.483002],"type":"Point"}
}