{
  "type": "Feature",
  "properties": {
    "addr:full":"Unit G38, Middleton Shopping Centre, Middleton Manchester Greater Manchester M24 4EL",
    "addr:housenumber":"g38",
    "addr:postcode":"m24 4el",
    "addr:street":"Middleton Shopping",
    "iso:country":"GB",
    "sg:address":"Unit G38, Middleton Shopping Centre, Middleton",
    "sg:city":"Manchester",
    "sg:classifiers":[
        {
            "category":"Professional",
            "subcategory":"Art Services",
            "type":"Services"
        }
    ],
    "sg:phone":"+44 161 653 6951",
    "sg:postcode":"M24 4EL",
    "sg:province":"Greater Manchester",
    "sg:tags":[
        "photographer"
    ],
    "wof:name":"The & Shop",
    "wof:placetype":"venue"
},
  "geometry": {"coordinates":[-2.235722,53.54147],"type":"Point"}
}