{
  "type": "Feature",
  "properties": {
    "addr:full":"12a Vauxhall Bridge Road London Greater London SW1V 2SD",
    "addr:housenumber":"12a",
    "addr:postcode":"sw1v 2sd",
    "addr:street":"Vauxhall Bridge Road",
    "iso:country":"GB",
    "sg:address":"12a Vauxhall Bridge Road",
    "sg:city":"London",
    "sg:classifiers":[
        {
            "category":"Cafe",
            "type":"Food & Drink"
        }
    ],
    "sg:postcode":"SW1V 2SD",
    "sg:province":"Greater London",
    "sg:tags":[
        "tea",
        "room"
    ],
    "wof:name":"Cafe D'Art",
    "wof:placetype":"venue"
},
  "geometry": {"coordinates":[-0.1315679997,51.4897232056],"type":"Point"}
}