{
  "type": "Feature",
  "properties": {
    "iso:country":"GB",
    "sg:address":"249 Northdown Road, Cliftonville",
    "sg:city":"Margate",
    "sg:classifiers":[
        {
            "category":"Fast Food",
            "type":"Food & Drink"
        }
    ],
    "sg:phone":"+44 1843 226888",
    "sg:postcode":"CT9 2PN",
    "sg:province":"Kent",
    "sg:tags":[
        "away",
        "meal",
        "outlet",
        "take"
    ],
    "wof:name":"Pagoda Chinese Take Away",
    "wof:placetype":"venue"
},
  "geometry": {"coordinates":[1.39641,51.387959],"type":"Point"}
}