{
  "type": "Feature",
  "properties": {
    "addr:full":"Unit 9 Asquith Bottom Mills, Asquith Bottom Sowerby Bridge West Yorkshire HX6 3BT",
    "addr:housenumber":"unit 9",
    "addr:postcode":"hx6 3bt",
    "addr:street":"Bottom;Bottom;West",
    "iso:country":"GB",
    "sg:address":"Unit 9 Asquith Bottom Mills, Asquith Bottom",
    "sg:city":"Sowerby Bridge",
    "sg:classifiers":[
        {
            "category":"Manufacturing",
            "subcategory":"Petroleum Products",
            "type":"Manufacturing & Wholesale Goods"
        }
    ],
    "sg:phone":"+44 1422 316663",
    "sg:postcode":"HX6 3BT",
    "sg:province":"West Yorkshire",
    "sg:tags":[
        "double",
        "glazing"
    ],
    "wof:name":"Clear Vision Glass",
    "wof:placetype":"venue"
},
  "geometry": {"coordinates":[-1.913934,53.706539],"type":"Point"}
}