{
  "type": "Feature",
  "properties": {
    "iso:country":"GB",
    "sg:address":"Water Lane, West Runton",
    "sg:city":"Cromer",
    "sg:classifiers":[
        {
            "category":"Travel",
            "subcategory":"Hotels & Motels",
            "type":"Entertainment"
        },
        {
            "category":"Recreation",
            "subcategory":"Campground",
            "type":"Entertainment"
        }
    ],
    "sg:phone":"+44 1263 837473",
    "sg:postcode":"NR27 9QP",
    "sg:province":"Norfolk",
    "sg:tags":[
        "caravan",
        "self",
        "park",
        "catering"
    ],
    "wof:name":"M & J Y Randell",
    "wof:placetype":"venue"
},
  "geometry": {"coordinates":[1.2482529879,52.9406661987],"type":"Point"}
}