{
  "type": "Feature",
  "properties": {
    "addr:full":"617 Moston La Manchester Greater Manchester M40 5QD",
    "addr:housenumber":"617",
    "addr:postcode":"m40 5qd",
    "addr:street":"Moston La Manchester",
    "iso:country":"GB",
    "sg:address":"617 Moston La",
    "sg:city":"Manchester",
    "sg:classifiers":[
        {
            "category":"Building & Trades",
            "subcategory":"Construction",
            "type":"Services"
        }
    ],
    "sg:phone":"+44 161 681 8470",
    "sg:postcode":"M40 5QD",
    "sg:province":"Greater Manchester",
    "sg:tags":[
        "roofing"
    ],
    "wof:name":"G Lang",
    "wof:placetype":"venue"
},
  "geometry": {"coordinates":[-2.183977,53.519115],"type":"Point"}
}