{
  "type": "Feature",
  "properties": {
    "addr:full":"11 Farriers Way Bootle Merseyside L30 4XL",
    "addr:housenumber":"11",
    "addr:postcode":"l30 4xl",
    "addr:street":"Farriers Way",
    "iso:country":"GB",
    "sg:address":"11 Farriers Way",
    "sg:city":"Bootle",
    "sg:classifiers":[
        {
            "category":"Building & Trades",
            "subcategory":"Landscaping Services",
            "type":"Services"
        }
    ],
    "sg:phone":"+44 151 524 1962",
    "sg:postcode":"L30 4XL",
    "sg:province":"Merseyside",
    "sg:tags":[
        "landscape",
        "contractor"
    ],
    "wof:name":"Regal Landscapes",
    "wof:placetype":"venue"
},
  "geometry": {"coordinates":[-2.970813036,53.4730834961],"type":"Point"}
}