{
  "type": "Feature",
  "properties": {
    "iso:country":"GB",
    "sg:address":"Castle Hayes Park, Castle Hayes Lane",
    "sg:city":"Burton-on-trent",
    "sg:classifiers":[
        {
            "category":"Farming",
            "subcategory":"Farm",
            "type":"Manufacturing & Wholesale Goods"
        }
    ],
    "sg:phone":"+44 1283 812244",
    "sg:postcode":"DE13 9HL",
    "sg:province":"Derbyshire",
    "sg:tags":[
        "mixed",
        "crop"
    ],
    "wof:name":"The Major Storage Co. Ltd.",
    "wof:placetype":"venue"
},
  "geometry": {"coordinates":[-1.703073,52.848408],"type":"Point"}
}