{
  "type": "Feature",
  "properties": {
    "addr:full":"Care Of Asda, Maynard Road, Totton Southampton Hampshire SO40 3ZA",
    "addr:postcode":"so40 3za",
    "addr:street":"Maynard Road",
    "iso:country":"GB",
    "sg:address":"Care Of Asda, Maynard Road, Totton",
    "sg:city":"Southampton",
    "sg:classifiers":[
        {
            "category":"Ice Cream",
            "type":"Food & Drink"
        }
    ],
    "sg:phone":"+44 23 8087 0097",
    "sg:postcode":"SO40 3ZA",
    "sg:province":"Hampshire",
    "sg:tags":[
        "shop",
        "mobile",
        "parlour"
    ],
    "wof:name":"Baileys Retail Foods",
    "wof:placetype":"venue"
},
  "geometry": {"coordinates":[-1.491189003,50.9199104309],"type":"Point"}
}