{
  "type": "Feature",
  "properties": {
    "iso:country":"GB",
    "sg:address":"Brineton Street",
    "sg:city":"Walsall",
    "sg:classifiers":[
        {
            "category":"Manufacturing",
            "subcategory":"Metals",
            "type":"Manufacturing & Wholesale Goods"
        }
    ],
    "sg:phone":"+44 1922 645177",
    "sg:postcode":"WS2 9EP",
    "sg:province":"West Midlands",
    "wof:name":"D Acorn Polishing",
    "wof:placetype":"venue"
},
  "geometry": {"coordinates":[-1.997497,52.579742],"type":"Point"}
}