{
  "type": "Feature",
  "properties": {
    "iso:country":"GB",
    "sg:address":"1 Stonehills Ho, Stonehills",
    "sg:city":"Welwyn Garden City",
    "sg:classifiers":[
        {
            "category":"Shopping",
            "subcategory":"Books",
            "type":"Retail Goods"
        }
    ],
    "sg:phone":"+44 1707 396698",
    "sg:postcode":"AL8 6NH",
    "sg:province":"Hertfordshire",
    "wof:name":"Griffin Multimedia",
    "wof:placetype":"venue"
},
  "geometry": {"coordinates":[-0.2057289928,51.8014297485],"type":"Point"}
}