{
  "type": "Feature",
  "properties": {
    "addr:full":"56 St Marks Road Mitcham Greater London CR4 2LE",
    "addr:housenumber":"56",
    "addr:postcode":"cr4 2le",
    "addr:street":"St Marks Road",
    "iso:country":"GB",
    "sg:address":"56 St Marks Road",
    "sg:city":"Mitcham",
    "sg:classifiers":[
        {
            "category":"Building & Trades",
            "subcategory":"Plumbing",
            "type":"Services"
        }
    ],
    "sg:phone":"+44 20 8646 3578",
    "sg:postcode":"CR4 2LE",
    "sg:province":"Greater London",
    "sg:tags":[
        "central",
        "heating"
    ],
    "wof:name":"David Harnden",
    "wof:placetype":"venue"
},
  "geometry": {"coordinates":[-0.160105,51.406555],"type":"Point"}
}