{
  "type": "Feature",
  "properties": {
    "iso:country":"GB",
    "sg:address":"238-246 King Street",
    "sg:city":"London",
    "sg:classifiers":[
        {
            "category":"Education",
            "subcategory":"Library",
            "type":"Public Place"
        }
    ],
    "sg:phone":"+44 20 8741 0474",
    "sg:postcode":"W6 0QX",
    "sg:province":"Greater London",
    "sg:tags":[
        "book"
    ],
    "wof:name":"The Polish Library",
    "wof:placetype":"venue"
},
  "geometry": {"coordinates":[-0.2374240011,51.493396759],"type":"Point"}
}