{
  "type": "Feature",
  "properties": {
    "iso:country":"GB",
    "sg:address":"103 Fitzneal Street",
    "sg:city":"London",
    "sg:classifiers":[
        {
            "category":"Professional",
            "subcategory":"Detective & Security Services",
            "type":"Services"
        },
        {
            "category":"Building & Trades",
            "subcategory":"Locksmith",
            "type":"Services"
        }
    ],
    "sg:phone":"+44 20 8749 3524",
    "sg:postcode":"W12 0BA",
    "sg:province":"Greater London",
    "wof:name":"Astra Lockouts",
    "wof:placetype":"venue"
},
  "geometry": {"coordinates":[-0.249812007,51.5175857544],"type":"Point"}
}