{
  "type": "Feature",
  "properties": {
    "iso:country":"GB",
    "sg:address":"6 Albert Road",
    "sg:city":"Southsea",
    "sg:classifiers":[
        {
            "category":"Shopping",
            "subcategory":"Gifts & Souvenirs",
            "type":"Retail Goods"
        }
    ],
    "sg:postcode":"PO5 2SH",
    "sg:province":"Hampshire",
    "sg:tags":[
        "shop"
    ],
    "wof:name":"H D & P McCullough",
    "wof:placetype":"venue"
},
  "geometry": {"coordinates":[-1.082045,50.787724],"type":"Point"}
}