{
  "type": "Feature",
  "properties": {
    "addr:full":"41 Summerleaze Rd Maidenhead Berkshire SL6 8EW",
    "addr:housenumber":"41",
    "addr:postcode":"sl6 8ew",
    "addr:street":"Summerleaze Rd",
    "iso:country":"GB",
    "sg:address":"41 Summerleaze Rd",
    "sg:city":"Maidenhead",
    "sg:classifiers":[
        {
            "category":"Real Estate",
            "subcategory":"Real Estate Operator",
            "type":"Services"
        },
        {
            "category":"Real Estate",
            "subcategory":"Real Estate Agent",
            "type":"Services"
        }
    ],
    "sg:postcode":"SL6 8EW",
    "sg:province":"Berkshire",
    "sg:tags":[
        "letting"
    ],
    "wof:name":"Owens,J K,",
    "wof:placetype":"venue"
},
  "geometry": {"coordinates":[-0.7117530107,51.534034729],"type":"Point"}
}