{
  "type": "Feature",
  "properties": {
    "iso:country":"GB",
    "sg:address":"15 Tweed Avenue",
    "sg:city":"Paisley",
    "sg:classifiers":[
        {
            "category":"Building & Trades",
            "subcategory":"Construction",
            "type":"Services"
        }
    ],
    "sg:postcode":"PA2 0NR",
    "sg:province":"East Renfrewshire",
    "sg:tags":[
        "roofing"
    ],
    "wof:name":"D Gray Roofing",
    "wof:placetype":"venue"
},
  "geometry": {"coordinates":[-4.4636478424,55.8315505981],"type":"Point"}
}