{
  "type": "Feature",
  "properties": {
    "iso:country":"GB",
    "sg:address":"21 Mill Street",
    "sg:city":"Bideford",
    "sg:classifiers":[
        {
            "category":"Shopping",
            "subcategory":"Comic Books",
            "type":"Retail Goods"
        }
    ],
    "sg:phone":"+44 1237 472864",
    "sg:postcode":"EX39 2JW",
    "sg:province":"Devon",
    "sg:tags":[
        "jeweller"
    ],
    "wof:name":"Thomas & Son Jewellers",
    "wof:placetype":"venue"
},
  "geometry": {"coordinates":[-4.2064919472,51.0188522339],"type":"Point"}
}