{
  "type": "Feature",
  "properties": {
    "addr:full":"Units 1-5 Delves Industrial Estate Consett Durham DH8 9HU",
    "addr:housenumber":"units 1-5",
    "addr:postcode":"dh8 9hu",
    "addr:street":"Delves Industrial Estate",
    "iso:country":"GB",
    "sg:address":"Units 1-5 Delves Industrial Estate",
    "sg:city":"Consett",
    "sg:classifiers":[
        {
            "category":"Manufacturing",
            "subcategory":"Metals",
            "type":"Manufacturing & Wholesale Goods"
        }
    ],
    "sg:phone":"+44 1207 500937",
    "sg:postcode":"DH8 9HU",
    "sg:province":"Durham",
    "sg:tags":[
        "heat",
        "-",
        "treatment"
    ],
    "wof:name":"Metaltech Ltd.",
    "wof:placetype":"venue"
},
  "geometry": {"coordinates":[-1.835914,54.860989],"type":"Point"}
}