{
  "type": "Feature",
  "properties": {
    "addr:full":"Winchester Rd Southampton Hampshire SO16 6UN",
    "addr:postcode":"so16 6un",
    "addr:street":"Winchester Rd",
    "iso:country":"GB",
    "sg:address":"Winchester Rd",
    "sg:city":"Southampton",
    "sg:classifiers":[
        {
            "category":"Food & Beverages",
            "subcategory":"Meat & Fish",
            "type":"Retail Goods"
        }
    ],
    "sg:phone":"+44 1489 893120",
    "sg:postcode":"SO16 6UN",
    "sg:province":"Hampshire",
    "sg:tags":[
        "chip"
    ],
    "wof:name":"Vines Take Away",
    "wof:placetype":"venue"
},
  "geometry": {"coordinates":[-1.4193140268,50.9341239929],"type":"Point"}
}