{
  "type": "Feature",
  "properties": {
    "addr:full":"Unit 1 Oaklands Court, Martock Business Park Martock Somerset TA12 6HP",
    "addr:housenumber":"unit 1",
    "addr:postcode":"ta12 6hp",
    "addr:street":"Oaklands Court Martock Business Park",
    "iso:country":"GB",
    "sg:address":"Unit 1 Oaklands Court, Martock Business Park",
    "sg:city":"Martock",
    "sg:classifiers":[
        {
            "category":"Retail",
            "subcategory":"Auto Repair",
            "type":"Services"
        }
    ],
    "sg:phone":"+44 1935 824636",
    "sg:postcode":"TA12 6HP",
    "sg:province":"Somerset",
    "sg:tags":[
        "caravan",
        "servicing"
    ],
    "wof:name":"Somerset Caravan Services Ltd.",
    "wof:placetype":"venue"
},
  "geometry": {"coordinates":[-2.769779,50.980675],"type":"Point"}
}