{
  "type": "Feature",
  "properties": {
    "iso:country":"GB",
    "sg:address":"Ty Twyn Teg, Caewern",
    "sg:city":"Neath",
    "sg:classifiers":[
        {
            "category":"Social Services",
            "subcategory":"Adult Care",
            "type":"Services"
        }
    ],
    "sg:phone":"+44 1639 645878",
    "sg:postcode":"SA10 7RP",
    "sg:province":"Neath Port Talbot",
    "sg:tags":[
        "housing",
        "sheltered"
    ],
    "wof:name":"Ty Twyn Teg Sheltered Flats",
    "wof:placetype":"venue"
},
  "geometry": {"coordinates":[-3.8138120174,51.6691741943],"type":"Point"}
}