{
  "type": "Feature",
  "properties": {
    "addr:full":"21 Spittal Street Sheffield South Yorkshire S3 9LB",
    "addr:housenumber":"21",
    "addr:postcode":"s3 9lb",
    "addr:street":"Spittal Street",
    "iso:country":"GB",
    "sg:address":"21 Spittal Street",
    "sg:city":"Sheffield",
    "sg:classifiers":[
        {
            "category":"Health Services",
            "subcategory":"Doctor",
            "type":"Services"
        }
    ],
    "sg:phone":"+44 114 272 5552",
    "sg:postcode":"S3 9LB",
    "sg:province":"South Yorkshire",
    "sg:tags":[
        "practitioners"
    ],
    "wof:name":"Sheffield Medical Centre",
    "wof:placetype":"venue"
},
  "geometry": {"coordinates":[-1.460833,53.39043],"type":"Point"}
}