{
  "type": "Feature",
  "properties": {
    "iso:country":"GB",
    "sg:address":"7 Millfield Road",
    "sg:city":"Luton",
    "sg:classifiers":[
        {
            "category":"Professional",
            "subcategory":"Management & Consulting",
            "type":"Services"
        }
    ],
    "sg:phone":"+44 1582 503291",
    "sg:postcode":"LU3 1RT",
    "sg:province":"Bedfordshire",
    "sg:tags":[
        "consultant",
        "business"
    ],
    "wof:name":"Zaria Consultants Ltd.",
    "wof:placetype":"venue"
},
  "geometry": {"coordinates":[-0.439648,51.895973],"type":"Point"}
}