{
  "type": "Feature",
  "properties": {
    "addr:full":"59 St Mildreds Road Westgate-on-sea Kent CT8 8RL",
    "addr:housenumber":"59",
    "addr:postcode":"ct8 8rl",
    "addr:street":"St Mildreds Road Westgate-On-Sea",
    "iso:country":"GB",
    "sg:address":"59 St Mildreds Road",
    "sg:city":"Westgate-on-sea",
    "sg:classifiers":[
        {
            "category":"Social Services",
            "subcategory":"Retirement Home",
            "type":"Services"
        }
    ],
    "sg:phone":"+44 1843 831427",
    "sg:postcode":"CT8 8RL",
    "sg:province":"Kent",
    "sg:tags":[
        "residential",
        "care"
    ],
    "wof:name":"Barnsley",
    "wof:placetype":"venue"
},
  "geometry": {"coordinates":[1.3367760181,51.384021759],"type":"Point"}
}