{
  "type": "Feature",
  "properties": {
    "iso:country":"GB",
    "sg:address":"318 Buxton Rd",
    "sg:city":"Stockport",
    "sg:classifiers":[
        {
            "category":"Manufacturing",
            "subcategory":"Petroleum Products",
            "type":"Manufacturing & Wholesale Goods"
        }
    ],
    "sg:phone":"+44 161 456 0404",
    "sg:postcode":"SK2 7DD",
    "sg:province":"Cheshire",
    "sg:tags":[
        "double",
        "glazing"
    ],
    "wof:name":"Storm Guard Windows & Conservatories",
    "wof:placetype":"venue"
},
  "geometry": {"coordinates":[-2.13657,53.388489],"type":"Point"}
}