{
  "type": "Feature",
  "properties": {
    "addr:full":"Debmarc House, 193 London Road Staines Berkshire TW18 4HR",
    "addr:housenumber":"193",
    "addr:postcode":"tw18 4hr",
    "addr:street":"London Road",
    "iso:country":"GB",
    "sg:address":"Debmarc House, 193 London Road",
    "sg:city":"Staines",
    "sg:classifiers":[
        {
            "category":"Insurance",
            "subcategory":"Health Insurance",
            "type":"Services"
        }
    ],
    "sg:phone":"+44 1784 449100",
    "sg:postcode":"TW18 4HR",
    "sg:province":"Berkshire",
    "wof:name":"Corporate Medical Insurance Consultants",
    "wof:placetype":"venue"
},
  "geometry": {"coordinates":[-0.4987449944,51.43699646],"type":"Point"}
}