{
  "type": "Feature",
  "properties": {
    "addr:full":"265 Westdale Lane, Carlton Nottingham Nottinghamshire NG4 4FL",
    "addr:housenumber":"265",
    "addr:postcode":"ng4 4fl",
    "addr:street":"Westdale Lane",
    "iso:country":"GB",
    "sg:address":"265 Westdale Lane, Carlton",
    "sg:city":"Nottingham",
    "sg:classifiers":[
        {
            "category":"Home & Garden",
            "subcategory":"Carpets & Floor Coverings",
            "type":"Retail Goods"
        }
    ],
    "sg:phone":"+44 115 961 7566",
    "sg:postcode":"NG4 4FL",
    "sg:province":"Nottinghamshire",
    "sg:tags":[
        "carpets",
        "rug",
        "matting"
    ],
    "wof:name":"Gedling Carpets",
    "wof:placetype":"venue"
},
  "geometry": {"coordinates":[-1.099549,52.979038],"type":"Point"}
}