{
  "type": "Feature",
  "properties": {
    "addr:full":"Common Hill, Cricklade Swindon Gloucestershire SN6 6HA",
    "addr:postcode":"sn6 6ha",
    "addr:street":"Common Hill",
    "iso:country":"GB",
    "sg:address":"Common Hill, Cricklade",
    "sg:city":"Swindon",
    "sg:classifiers":[
        {
            "category":"Professional",
            "subcategory":"Engineering",
            "type":"Services"
        }
    ],
    "sg:postcode":"SN6 6HA",
    "sg:province":"Gloucestershire",
    "sg:tags":[
        "contractor",
        "electrical",
        "engineer"
    ],
    "wof:name":"Fernades Electrical Contracting Ltd",
    "wof:placetype":"venue"
},
  "geometry": {"coordinates":[-1.85699,51.640049],"type":"Point"}
}