{
  "type": "Feature",
  "properties": {
    "iso:country":"GB",
    "sg:address":"Taw Trade Park, Braunton Road",
    "sg:city":"Barnstaple",
    "sg:classifiers":[
        {
            "category":"Manufacturing",
            "subcategory":"Petroleum Products",
            "type":"Manufacturing & Wholesale Goods"
        }
    ],
    "sg:phone":"+44 1271 321691",
    "sg:postcode":"EX31 1JZ",
    "sg:province":"Devon",
    "sg:tags":[
        "double",
        "glazing"
    ],
    "wof:name":"The Door & Window Centre Ltd.",
    "wof:placetype":"venue"
},
  "geometry": {"coordinates":[-4.0694131851,51.0850830078],"type":"Point"}
}