{
  "type": "Feature",
  "properties": {
    "addr:full":"130-132 Cumbernauld Road, Muirhead Glasgow East Dunbartonshire G69 9DY",
    "addr:postcode":"130-132;g69 9dy",
    "addr:street":"Cumbernauld Road",
    "iso:country":"GB",
    "sg:address":"130-132 Cumbernauld Road, Muirhead",
    "sg:city":"Glasgow",
    "sg:classifiers":[
        {
            "category":"Banks & Credit Unions",
            "subcategory":"Bank",
            "type":"Services"
        }
    ],
    "sg:phone":"+44 141 779 2175",
    "sg:postcode":"G69 9DY",
    "sg:province":"East Dunbartonshire",
    "sg:tags":[
        "financial",
        "institution"
    ],
    "wof:name":"Airdrie Savings Bank",
    "wof:placetype":"venue"
},
  "geometry": {"coordinates":[-4.106915,55.899784],"type":"Point"}
}