{
  "type": "Feature",
  "properties": {
    "iso:country":"GB",
    "sg:address":"81 Fintry Road",
    "sg:city":"Dundee",
    "sg:classifiers":[
        {
            "category":"Shopping",
            "subcategory":"Department Store",
            "type":"Retail Goods"
        }
    ],
    "sg:phone":"+44 1382 507031",
    "sg:postcode":"DD4 9JB",
    "sg:province":"Dundee City",
    "wof:name":"Pricekrackers",
    "wof:placetype":"venue"
},
  "geometry": {"coordinates":[-2.938649,56.48999],"type":"Point"}
}