{
  "type": "Feature",
  "properties": {
    "addr:full":"30 Highgate Road London Greater London NW5 1NS",
    "addr:housenumber":"30",
    "addr:postcode":"nw5 1ns",
    "addr:street":"Highgate Road",
    "iso:country":"GB",
    "sg:address":"30 Highgate Road",
    "sg:city":"London",
    "sg:classifiers":[
        {
            "category":"Transit Center",
            "subcategory":"Freight",
            "type":"Transportation"
        }
    ],
    "sg:postcode":"NW5 1NS",
    "sg:province":"Greater London",
    "sg:tags":[
        "piano",
        "accessory"
    ],
    "wof:name":"Piano Warehouse Ltd.",
    "wof:placetype":"venue"
},
  "geometry": {"coordinates":[-0.1417939961,51.5526428223],"type":"Point"}
}