{
  "type": "Feature",
  "properties": {
    "addr:full":"Unit 3 Bull Lane Industrial Estate, Acton Sudbury Essex CO10 0BD",
    "addr:housenumber":"unit 3",
    "addr:postcode":"co10 0bd",
    "addr:street":"Bull Lane Industrial Estate",
    "iso:country":"GB",
    "sg:address":"Unit 3 Bull Lane Industrial Estate, Acton",
    "sg:city":"Sudbury",
    "sg:classifiers":[
        {
            "category":"Sports & Exercise",
            "subcategory":"Golf",
            "type":"Entertainment"
        }
    ],
    "sg:phone":"+44 1787 372536",
    "sg:postcode":"CO10 0BD",
    "sg:province":"Essex",
    "sg:tags":[
        "equipment"
    ],
    "wof:name":"Westgolf",
    "wof:placetype":"venue"
},
  "geometry": {"coordinates":[0.741624,52.080555],"type":"Point"}
}