{
  "type": "Feature",
  "properties": {
    "addr:full":"Godstone Hill Godstone Surrey RH9 8DH",
    "addr:postcode":"rh9 8dh",
    "addr:street":"Godstone Hill",
    "iso:country":"GB",
    "sg:address":"Godstone Hill",
    "sg:city":"Godstone",
    "sg:classifiers":[
        {
            "category":"Transit Center",
            "subcategory":"Passenger",
            "type":"Transportation"
        }
    ],
    "sg:phone":"+44 1883 743733",
    "sg:postcode":"RH9 8DH",
    "sg:province":"Surrey",
    "sg:tags":[
        "boarding",
        "kennel",
        "catteries"
    ],
    "wof:name":"Freer Farm",
    "wof:placetype":"venue"
},
  "geometry": {"coordinates":[-0.0673559979,51.2633056641],"type":"Point"}
}