{
  "type": "Feature",
  "properties": {
    "iso:country":"GB",
    "sg:address":"11 Blenheim Close, Chandlers Ford",
    "sg:city":"Southampton",
    "sg:classifiers":[
        {
            "category":"Professional",
            "subcategory":"Accounting & Tax Preparation",
            "type":"Services"
        }
    ],
    "sg:phone":"+44 23 8027 5757",
    "sg:postcode":"SO53 4LD",
    "sg:province":"Hampshire",
    "sg:tags":[
        "accountant"
    ],
    "wof:name":"Accord Accountants",
    "wof:placetype":"venue"
},
  "geometry": {"coordinates":[-1.40687,50.975498],"type":"Point"}
}