{
  "type": "Feature",
  "properties": {
    "addr:full":"Ingsman, Back Lane, Ellerton York East Riding of Yorkshire YO42 4PE",
    "addr:postcode":"yo42 4pe",
    "addr:street":"Back Lane",
    "iso:country":"GB",
    "sg:address":"Ingsman, Back Lane, Ellerton",
    "sg:city":"York",
    "sg:classifiers":[
        {
            "category":"Building & Trades",
            "subcategory":"Construction",
            "type":"Services"
        }
    ],
    "sg:phone":"+44 1757 288153",
    "sg:postcode":"YO42 4PE",
    "sg:province":"East Riding of Yorkshire",
    "sg:tags":[
        "builder"
    ],
    "wof:name":"G H Alden",
    "wof:placetype":"venue"
},
  "geometry": {"coordinates":[-0.930554986,53.8502655029],"type":"Point"}
}