{
  "type": "Feature",
  "properties": {
    "iso:country":"GB",
    "sg:address":"Littlemill",
    "sg:city":"Ayr",
    "sg:classifiers":[
        {
            "category":"Farming",
            "subcategory":"Farm",
            "type":"Manufacturing & Wholesale Goods"
        }
    ],
    "sg:postcode":"KA6 7HJ",
    "sg:province":"East Ayrshire",
    "sg:tags":[
        "mixed",
        "crop"
    ],
    "wof:name":"James Purdie Esq",
    "wof:placetype":"venue"
},
  "geometry": {"coordinates":[-4.4576039314,55.4368896484],"type":"Point"}
}