{
  "type": "Feature",
  "properties": {
    "addr:full":"6 Darin Court, Crown Hill Milton Keynes Buckinghamshire MK8 0AD",
    "addr:housenumber":"6",
    "addr:postcode":"mk8 0ad",
    "addr:street":"Darin Court",
    "iso:country":"GB",
    "sg:address":"6 Darin Court, Crown Hill",
    "sg:city":"Milton Keynes",
    "sg:classifiers":[
        {
            "category":"Building & Trades",
            "subcategory":"Construction",
            "type":"Services"
        }
    ],
    "sg:postcode":"MK8 0AD",
    "sg:province":"Buckinghamshire",
    "sg:tags":[
        "joinery"
    ],
    "wof:name":"A & B Joinery",
    "wof:placetype":"venue"
},
  "geometry": {"coordinates":[-0.798762,52.030689],"type":"Point"}
}