{
  "type": "Feature",
  "properties": {
    "addr:full":"Parkfield Road Wolverhampton Staffordshire WV4 6EN",
    "addr:postcode":"wv4 6en",
    "addr:street":"Parkfield Road",
    "iso:country":"GB",
    "sg:address":"Parkfield Road",
    "sg:city":"Wolverhampton",
    "sg:classifiers":[
        {
            "category":"Retail",
            "subcategory":"Auto Repair",
            "type":"Services"
        }
    ],
    "sg:phone":"+44 1902 405890",
    "sg:postcode":"WV4 6EN",
    "sg:province":"Staffordshire",
    "sg:tags":[
        "modification",
        "garage"
    ],
    "wof:name":"Parkfield Hire Services",
    "wof:placetype":"venue"
},
  "geometry": {"coordinates":[-2.1213190556,52.5670509338],"type":"Point"}
}