{
  "type": "Feature",
  "properties": {
    "iso:country":"GB",
    "sg:address":"582-600 Ringwood Rd",
    "sg:city":"Poole",
    "sg:classifiers":[
        {
            "category":"Autos & Motor Vehicles",
            "subcategory":"Automobile Sales",
            "type":"Retail Goods"
        }
    ],
    "sg:phone":"+44 1202 775000",
    "sg:postcode":"BH12 4LW",
    "sg:province":"Dorset",
    "sg:tags":[
        "car"
    ],
    "wof:name":"Page Motors",
    "wof:placetype":"venue"
},
  "geometry": {"coordinates":[-1.944347,50.745079],"type":"Point"}
}