{
  "type": "Feature",
  "properties": {
    "addr:full":"162 Kentish Town Road London Greater London NW5 2AG",
    "addr:housenumber":"162",
    "addr:postcode":"nw5 2ag",
    "addr:street":"Kentish Town Road",
    "iso:country":"GB",
    "sg:address":"162 Kentish Town Road",
    "sg:city":"London",
    "sg:classifiers":[
        {
            "category":"Travel",
            "subcategory":"Travel Agent",
            "type":"Entertainment"
        }
    ],
    "sg:phone":"+44 20 7482 1604",
    "sg:postcode":"NW5 2AG",
    "sg:province":"Greater London",
    "wof:name":"Slatterys Travel Agency",
    "wof:placetype":"venue"
},
  "geometry": {"coordinates":[-0.141457,51.546822],"type":"Point"}
}