{
  "type": "Feature",
  "properties": {
    "addr:full":"Mill Lane Durham Durham DH1 2JG",
    "addr:postcode":"dh1 2jg",
    "addr:street":"Mill Lane",
    "iso:country":"GB",
    "sg:address":"Mill Lane",
    "sg:city":"Durham",
    "sg:classifiers":[
        {
            "category":"Organizations",
            "subcategory":"Community Association",
            "type":"Services"
        },
        {
            "category":"Organizations",
            "subcategory":"Membership Organization",
            "type":"Services"
        }
    ],
    "sg:phone":"+44 191 386 9824",
    "sg:postcode":"DH1 2JG",
    "sg:province":"Durham",
    "sg:tags":[
        "club",
        "social"
    ],
    "wof:name":"New Durham & District Workmens Club",
    "wof:placetype":"venue"
},
  "geometry": {"coordinates":[-1.546043992,54.7799110413],"type":"Point"}
}