{
  "type": "Feature",
  "properties": {
    "addr:full":"Seven Dale House, 35 Dale Street Manchester Greater Manchester M1 2HF",
    "addr:housenumber":"35",
    "addr:postcode":"m1 2hf",
    "addr:street":"Dale Street",
    "iso:country":"GB",
    "sg:address":"Seven Dale House, 35 Dale Street",
    "sg:city":"Manchester",
    "sg:classifiers":[
        {
            "category":"Restaurant",
            "type":"Food & Drink"
        }
    ],
    "sg:phone":"+44 161 237 3441",
    "sg:postcode":"M1 2HF",
    "sg:province":"Greater Manchester",
    "wof:name":"Copacabana Restaurant",
    "wof:placetype":"venue"
},
  "geometry": {"coordinates":[-2.233188,53.481285],"type":"Point"}
}