{
  "type": "Feature",
  "properties": {
    "addr:full":"21 Mancroft Road, Tettenhall Wolverhampton Shropshire WV6 8RP",
    "addr:housenumber":"21",
    "addr:postcode":"wv6 8rp",
    "addr:street":"Mancroft Road",
    "iso:country":"GB",
    "sg:address":"21 Mancroft Road, Tettenhall",
    "sg:city":"Wolverhampton",
    "sg:classifiers":[
        {
            "category":"Building & Trades",
            "subcategory":"Construction",
            "type":"Services"
        }
    ],
    "sg:phone":"+44 1902 751715",
    "sg:postcode":"WV6 8RP",
    "sg:province":"Shropshire",
    "sg:tags":[
        "builder"
    ],
    "wof:name":"Tettenhall Builders",
    "wof:placetype":"venue"
},
  "geometry": {"coordinates":[-2.1773109436,52.5986824036],"type":"Point"}
}