{
  "type": "Feature",
  "properties": {
    "iso:country":"GB",
    "sg:address":"Underfleet Way",
    "sg:city":"Seaton",
    "sg:classifiers":[
        {
            "category":"Food & Beverages",
            "subcategory":"Supermarket",
            "type":"Retail Goods"
        }
    ],
    "sg:phone":"+44 1297 21086",
    "sg:postcode":"EX12 2PQ",
    "sg:province":"Devon",
    "wof:name":"Co-Operative Pioneer",
    "wof:placetype":"venue"
},
  "geometry": {"coordinates":[-3.075809,50.70454],"type":"Point"}
}