{
  "type": "Feature",
  "properties": {
    "addr:full":"4 Albion Place, Bennetthorpe Doncaster South Yorkshire DN1 2EQ",
    "addr:housenumber":"4",
    "addr:postcode":"dn1 2eq",
    "addr:street":"Albion Place Bennetthorpe",
    "iso:country":"GB",
    "sg:address":"4 Albion Place, Bennetthorpe",
    "sg:city":"Doncaster",
    "sg:classifiers":[
        {
            "category":"Health Services",
            "subcategory":"Health Practitioner",
            "type":"Services"
        }
    ],
    "sg:postcode":"DN1 2EQ",
    "sg:province":"South Yorkshire",
    "sg:tags":[
        "homoeopathic"
    ],
    "wof:name":"Susan Bedford",
    "wof:placetype":"venue"
},
  "geometry": {"coordinates":[-1.1235589981,53.5206298828],"type":"Point"}
}