{
  "type": "Feature",
  "properties": {
    "iso:country":"GB",
    "sg:address":"Booking Hall Shop, Stockwell Station, Clapham Rd",
    "sg:city":"Brixton",
    "sg:classifiers":[
        {
            "category":"Shopping",
            "subcategory":"Pharmacy",
            "type":"Retail Goods"
        }
    ],
    "sg:phone":"+44 20 7622 8181",
    "sg:postcode":"SW9 9AE",
    "sg:province":"Greater London",
    "sg:tags":[
        "pharmacist",
        "chemist"
    ],
    "wof:name":"Mr Patel Wisebuys",
    "wof:placetype":"venue"
},
  "geometry": {"coordinates":[-0.1253799945,51.4698982239],"type":"Point"}
}