{
  "type": "Feature",
  "properties": {
    "addr:full":"1 Cromwell Court Ipswich Suffolk IP1 1XG",
    "addr:housenumber":"1",
    "addr:postcode":"ip1 1xg",
    "addr:street":"Cromwell Court",
    "iso:country":"GB",
    "sg:address":"1 Cromwell Court",
    "sg:city":"Ipswich",
    "sg:classifiers":[
        {
            "category":"Utilities",
            "type":"Services"
        }
    ],
    "sg:phone":"+44 870 710 4444",
    "sg:postcode":"IP1 1XG",
    "sg:province":"Suffolk",
    "sg:tags":[
        "internet"
    ],
    "wof:name":"Guildbridge Consultants Ltd.",
    "wof:placetype":"venue"
},
  "geometry": {"coordinates":[1.151878953,52.0550498962],"type":"Point"}
}