{
  "type": "Feature",
  "properties": {
    "iso:country":"GB",
    "sg:address":"Aketon Road",
    "sg:city":"Castleford",
    "sg:classifiers":[
        {
            "category":"Bars & Pubs",
            "type":"Food & Drink"
        }
    ],
    "sg:postcode":"WF10 5DW",
    "sg:province":"West Yorkshire",
    "sg:tags":[
        "pubs",
        "inn"
    ],
    "wof:name":"The Yorkshire Rose Hotel",
    "wof:placetype":"venue"
},
  "geometry": {"coordinates":[-1.3631639481,53.7165298462],"type":"Point"}
}