{
  "type": "Feature",
  "properties": {
    "iso:country":"GB",
    "sg:address":"72 Hawthorn Road",
    "sg:city":"Wednesbury",
    "sg:classifiers":[
        {
            "category":"Building & Trades",
            "subcategory":"Construction",
            "type":"Services"
        }
    ],
    "sg:postcode":"WS10 9NA",
    "sg:province":"West Midlands",
    "sg:tags":[
        "builder"
    ],
    "wof:name":"R J Young",
    "wof:placetype":"venue"
},
  "geometry": {"coordinates":[-2.0226199627,52.560546875],"type":"Point"}
}