{
  "type": "Feature",
  "properties": {
    "iso:country":"GB",
    "sg:address":"Cae Nest Hall Hotel",
    "sg:city":"Llanbedr",
    "sg:classifiers":[
        {
            "category":"Travel",
            "subcategory":"Hotels & Motels",
            "type":"Entertainment"
        }
    ],
    "sg:postcode":"LL45 2NL",
    "sg:province":"Gwynedd",
    "wof:name":"Cae Nest Hall Hotel",
    "wof:placetype":"venue"
},
  "geometry": {"coordinates":[-4.100938797,52.8197250366],"type":"Point"}
}