{
  "type": "Feature",
  "properties": {
    "addr:full":"18 Willshaw Road Blackpool Lancashire FY2 9SH",
    "addr:housenumber":"18",
    "addr:postcode":"fy2 9sh",
    "addr:street":"Willshaw Road",
    "iso:country":"GB",
    "sg:address":"18 Willshaw Road",
    "sg:city":"Blackpool",
    "sg:classifiers":[
        {
            "category":"Travel",
            "subcategory":"Hotels & Motels",
            "type":"Entertainment"
        }
    ],
    "sg:phone":"+44 1253 351021",
    "sg:postcode":"FY2 9SH",
    "sg:province":"Lancashire",
    "wof:name":"Parkside Private Hotel",
    "wof:placetype":"venue"
},
  "geometry": {"coordinates":[-3.052998,53.833904],"type":"Point"}
}