{
  "type": "Feature",
  "properties": {
    "addr:full":"159 Birling Road Snodland Kent ME6 5ET",
    "addr:housenumber":"159",
    "addr:postcode":"me6 5et",
    "addr:street":"Birling Road",
    "iso:country":"GB",
    "sg:address":"159 Birling Road",
    "sg:city":"Snodland",
    "sg:classifiers":[
        {
            "category":"Building & Trades",
            "subcategory":"Plumbing",
            "type":"Services"
        }
    ],
    "sg:postcode":"ME6 5ET",
    "sg:province":"Kent",
    "sg:tags":[
        "central",
        "heating"
    ],
    "wof:name":"M S M Heating",
    "wof:placetype":"venue"
},
  "geometry": {"coordinates":[0.433912009,51.3262825012],"type":"Point"}
}