{
  "type": "Feature",
  "properties": {
    "iso:country":"GB",
    "sg:address":"39 Grant Street",
    "sg:city":"Inverness",
    "sg:classifiers":[
        {
            "category":"Shopping",
            "subcategory":"Bicycles & Sporting Goods",
            "type":"Retail Goods"
        }
    ],
    "sg:phone":"+44 1463 225965",
    "sg:postcode":"IV3 8BP",
    "sg:province":"Highland",
    "sg:tags":[
        "shop",
        "cycle",
        "accessory"
    ],
    "wof:name":"Bikes of Inverness",
    "wof:placetype":"venue"
},
  "geometry": {"coordinates":[-4.2349262238,57.4846534729],"type":"Point"}
}