{
  "type": "Feature",
  "properties": {
    "addr:full":"526 Roman Road London Greater London E3 5ES",
    "addr:housenumber":"526",
    "addr:postcode":"e3 5es",
    "addr:street":"Roman Road",
    "iso:country":"GB",
    "sg:address":"526 Roman Road",
    "sg:city":"London",
    "sg:classifiers":[
        {
            "category":"Fast Food",
            "type":"Food & Drink"
        },
        {
            "category":"Restaurant",
            "type":"Food & Drink"
        }
    ],
    "sg:phone":"+44 20 8980 3165",
    "sg:postcode":"E3 5ES",
    "sg:province":"Greater London",
    "sg:tags":[
        "away",
        "take"
    ],
    "wof:name":"G F Kelly",
    "wof:placetype":"venue"
},
  "geometry": {"coordinates":[-0.030826,51.532837],"type":"Point"}
}