{
  "type": "Feature",
  "properties": {
    "iso:country":"GB",
    "sg:address":"58 Hursley Road Chandlers Ford",
    "sg:city":"Eastleigh",
    "sg:classifiers":[
        {
            "category":"Professional",
            "subcategory":"Advertising",
            "type":"Services"
        }
    ],
    "sg:postcode":"SO53 2FT",
    "sg:province":"Hampshire",
    "sg:tags":[
        "agency"
    ],
    "wof:name":"Fenn Ltd.",
    "wof:placetype":"venue"
},
  "geometry": {"coordinates":[-1.387372,50.987923],"type":"Point"}
}