{
  "type": "Feature",
  "properties": {
    "iso:country":"GB",
    "sg:address":"9 Northburgh St",
    "sg:city":"London",
    "sg:classifiers":[
        {
            "category":"Professional",
            "subcategory":"Computer Services",
            "type":"Services"
        }
    ],
    "sg:postcode":"EC1V 0AH",
    "sg:province":"Greater London",
    "sg:tags":[
        "system",
        "software"
    ],
    "wof:name":"S M E Connect Ltd",
    "wof:placetype":"venue"
},
  "geometry": {"coordinates":[-0.0998440012,51.5239944458],"type":"Point"}
}