{
  "type": "Feature",
  "properties": {
    "addr:full":"Beccles Road, Belton Great Yarmouth Norfolk NR31 9JQ",
    "addr:postcode":"nr31 9jq",
    "addr:street":"Beccles Road;Great Yarmouth",
    "iso:country":"GB",
    "sg:address":"Beccles Road, Belton",
    "sg:city":"Great Yarmouth",
    "sg:classifiers":[
        {
            "category":"Farming",
            "subcategory":"Livestock Farm",
            "type":"Manufacturing & Wholesale Goods"
        }
    ],
    "sg:phone":"+44 1493 780214",
    "sg:postcode":"NR31 9JQ",
    "sg:province":"Norfolk",
    "sg:tags":[
        "others"
    ],
    "wof:name":"H Botwright",
    "wof:placetype":"venue"
},
  "geometry": {"coordinates":[1.6606110334,52.5682220459],"type":"Point"}
}