{
  "type": "Feature",
  "properties": {
    "addr:full":"12 Asmun's Hill London Greater London NW11 6ET",
    "addr:housenumber":"12",
    "addr:postcode":"nw11 6et",
    "addr:street":"Asmun'S Hill",
    "iso:country":"GB",
    "sg:address":"12 Asmun's Hill",
    "sg:city":"London",
    "sg:classifiers":[
        {
            "category":"Health Services",
            "subcategory":"Health Practitioner",
            "type":"Services"
        }
    ],
    "sg:postcode":"NW11 6ET",
    "sg:province":"Greater London",
    "sg:tags":[
        "technique",
        "alexander"
    ],
    "wof:name":"Carolyn Simon",
    "wof:placetype":"venue"
},
  "geometry": {"coordinates":[-0.1966300011,51.5834197998],"type":"Point"}
}