{
  "type": "Feature",
  "properties": {
    "addr:full":"Unit 19 Armytage Road Brighouse West Yorkshire HD6 1PT",
    "addr:housenumber":"unit 19",
    "addr:postcode":"hd6 1pt",
    "addr:street":"Armytage Road",
    "iso:country":"GB",
    "sg:address":"Unit 19 Armytage Road",
    "sg:city":"Brighouse",
    "sg:classifiers":[
        {
            "category":"Manufacturing",
            "subcategory":"Wood Products",
            "type":"Manufacturing & Wholesale Goods"
        }
    ],
    "sg:postcode":"HD6 1PT",
    "sg:province":"West Yorkshire",
    "sg:tags":[
        "packaging",
        "crate",
        "pallets"
    ],
    "wof:name":"Woodside Pallets",
    "wof:placetype":"venue"
},
  "geometry": {"coordinates":[-1.772619,53.700161],"type":"Point"}
}