{
  "type": "Feature",
  "properties": {
    "addr:full":"G4 Unit, Hilton Main Indstl Est, Bognop Rd, Essington Wolverhampton Staffordshire WV11 2BE",
    "addr:housenumber":"unit",
    "addr:postcode":"wv11 2be",
    "addr:street":"Indstl;Bognop Rd",
    "iso:country":"GB",
    "sg:address":"G4 Unit, Hilton Main Indstl Est, Bognop Rd, Essington",
    "sg:city":"Wolverhampton",
    "sg:classifiers":[
        {
            "category":"Retail",
            "subcategory":"Auto Repair",
            "type":"Services"
        }
    ],
    "sg:phone":"+44 1902 739691",
    "sg:postcode":"WV11 2BE",
    "sg:province":"Staffordshire",
    "sg:tags":[
        "engine",
        "car",
        "specialist"
    ],
    "wof:name":"Ferriday Engineering Ltd",
    "wof:placetype":"venue"
},
  "geometry": {"coordinates":[-2.088059,52.635571],"type":"Point"}
}