{
  "type": "Feature",
  "properties": {
    "iso:country":"GB",
    "sg:address":"Unit 12, Somerton Business Park, Bancombe Road",
    "sg:city":"Somerton",
    "sg:classifiers":[
        {
            "category":"Shopping",
            "subcategory":"Computers & Home Electronics",
            "type":"Retail Goods"
        }
    ],
    "sg:phone":"+44 1458 274669",
    "sg:postcode":"TA11 6SB",
    "sg:province":"Somerset",
    "sg:tags":[
        "equipment",
        "radio"
    ],
    "wof:name":"A H Canvin",
    "wof:placetype":"venue"
},
  "geometry": {"coordinates":[-2.7483689785,51.059879303],"type":"Point"}
}