{
  "type": "Feature",
  "properties": {
    "iso:country":"GB",
    "sg:address":"23 Eastern Esplanade, Cliftonville",
    "sg:city":"Margate",
    "sg:classifiers":[
        {
            "category":"Travel",
            "subcategory":"Hotels & Motels",
            "type":"Entertainment"
        }
    ],
    "sg:phone":"+44 1843 222310",
    "sg:postcode":"CT9 2HL",
    "sg:province":"Kent",
    "wof:name":"Smith's Court Hotel",
    "wof:placetype":"venue"
},
  "geometry": {"coordinates":[1.4012600183,51.3851013184],"type":"Point"}
}