{
  "type": "Feature",
  "properties": {
    "iso:country":"GB",
    "sg:address":"Melunah, Allercombe",
    "sg:city":"Exeter",
    "sg:classifiers":[
        {
            "category":"Farming",
            "subcategory":"Livestock Farm",
            "type":"Manufacturing & Wholesale Goods"
        }
    ],
    "sg:postcode":"EX5 2HD",
    "sg:province":"Devon",
    "sg:tags":[
        "others"
    ],
    "wof:name":"J Wotton",
    "wof:placetype":"venue"
},
  "geometry": {"coordinates":[-3.348264,50.742889],"type":"Point"}
}