{
  "type": "Feature",
  "properties": {
    "iso:country":"GB",
    "sg:address":"Elswick Road",
    "sg:city":"Southport",
    "sg:classifiers":[
        {
            "category":"Education",
            "subcategory":"School",
            "type":"Public Place"
        }
    ],
    "sg:phone":"+44 1704 211177",
    "sg:postcode":"PR9 9XA",
    "sg:province":"Lancashire",
    "sg:tags":[
        "local",
        "authority"
    ],
    "wof:name":"Marshside County Primary School",
    "wof:placetype":"venue"
},
  "geometry": {"coordinates":[-2.970581,53.672985],"type":"Point"}
}