{
  "type": "Feature",
  "properties": {
    "iso:country":"GB",
    "sg:address":"16 Quay Street",
    "sg:city":"Penzance",
    "sg:classifiers":[
        {
            "category":"Shopping",
            "subcategory":"Books",
            "type":"Retail Goods"
        }
    ],
    "sg:phone":"+44 1736 369446",
    "sg:postcode":"TR18 4BP",
    "sg:province":"Cornwall",
    "sg:tags":[
        "bookseller"
    ],
    "wof:name":"The Quay Book Shop",
    "wof:placetype":"venue"
},
  "geometry": {"coordinates":[-5.53134,50.116024],"type":"Point"}
}