{
  "type": "Feature",
  "properties": {
    "addr:full":"1 Ffald Road, Pyle Bridgend Bridgend CF33 6AA",
    "addr:housenumber":"1",
    "addr:postcode":"cf33 6aa",
    "addr:street":"Ffald Road",
    "iso:country":"GB",
    "sg:address":"1 Ffald Road, Pyle",
    "sg:city":"Bridgend",
    "sg:classifiers":[
        {
            "category":"Food & Beverages",
            "subcategory":"Meat & Fish",
            "type":"Retail Goods"
        }
    ],
    "sg:phone":"+44 1656 745636",
    "sg:postcode":"CF33 6AA",
    "sg:province":"Bridgend",
    "sg:tags":[
        "chip"
    ],
    "wof:name":"Pyle Fish Bar",
    "wof:placetype":"venue"
},
  "geometry": {"coordinates":[-3.6898639202,51.5295906067],"type":"Point"}
}