{
  "type": "Feature",
  "properties": {
    "addr:full":"104 Billericay Road Billericay Essex CM12 9SL",
    "addr:housenumber":"104",
    "addr:postcode":"cm12 9sl",
    "addr:street":"Billericay Road",
    "iso:country":"GB",
    "sg:address":"104 Billericay Road",
    "sg:city":"Billericay",
    "sg:classifiers":[
        {
            "category":"Transit Center",
            "subcategory":"Passenger",
            "type":"Transportation"
        }
    ],
    "sg:postcode":"CM12 9SL",
    "sg:province":"Essex",
    "sg:tags":[
        "boarding",
        "kennel",
        "catteries"
    ],
    "wof:name":"Herongate Village Cattery",
    "wof:placetype":"venue"
},
  "geometry": {"coordinates":[0.38267,51.599388],"type":"Point"}
}