{
  "type": "Feature",
  "properties": {
    "addr:full":"345 Purley Way Croydon Surrey CR0 4NW",
    "addr:housenumber":"345",
    "addr:postcode":"cr0 4nw",
    "addr:street":"Purley Way",
    "iso:country":"GB",
    "sg:address":"345 Purley Way",
    "sg:city":"Croydon",
    "sg:classifiers":[
        {
            "category":"Fast Food",
            "type":"Food & Drink"
        }
    ],
    "sg:phone":"+44 20 8688 9153",
    "sg:postcode":"CR0 4NW",
    "sg:province":"Surrey",
    "sg:tags":[
        "away",
        "take"
    ],
    "wof:name":"Laus Gardens",
    "wof:placetype":"venue"
},
  "geometry": {"coordinates":[-0.1169719994,51.3710289001],"type":"Point"}
}