{
  "type": "Feature",
  "properties": {
    "addr:full":"9 Gloucester Road Stonehouse Gloucestershire GL10 2NZ",
    "addr:housenumber":"9",
    "addr:postcode":"gl10 2nz",
    "addr:street":"Gloucester Road",
    "iso:country":"GB",
    "sg:address":"9 Gloucester Road",
    "sg:city":"Stonehouse",
    "sg:classifiers":[
        {
            "category":"Autos & Motor Vehicles",
            "subcategory":"Automobile Sales",
            "type":"Retail Goods"
        }
    ],
    "sg:postcode":"GL10 2NZ",
    "sg:province":"Gloucestershire",
    "sg:tags":[
        "car"
    ],
    "wof:name":"Stonehouse Motors",
    "wof:placetype":"venue"
},
  "geometry": {"coordinates":[-2.28289,51.75021],"type":"Point"}
}