{
  "type": "Feature",
  "properties": {
    "addr:full":"Station Yard Irvine East Ayrshire KA11 5BZ",
    "addr:postcode":"ka11 5bz",
    "addr:street":"Yard",
    "iso:country":"GB",
    "sg:address":"Station Yard",
    "sg:city":"Irvine",
    "sg:classifiers":[
        {
            "category":"Wholesale",
            "subcategory":"Scrap",
            "type":"Manufacturing & Wholesale Goods"
        },
        {
            "category":"Wholesale",
            "subcategory":"Auto Parts",
            "type":"Manufacturing & Wholesale Goods"
        }
    ],
    "sg:phone":"+44 1294 311286",
    "sg:postcode":"KA11 5BZ",
    "sg:province":"East Ayrshire",
    "sg:tags":[
        "car",
        "breaker",
        "dismantlers"
    ],
    "wof:name":"Drybridge Auto Salvage",
    "wof:placetype":"venue"
},
  "geometry": {"coordinates":[-4.655709,55.597473],"type":"Point"}
}