{
  "type": "Feature",
  "properties": {
    "addr:full":"Fotostop House, 159 Fallsbrook Road London Greater London SW16 6DY",
    "addr:housenumber":"159",
    "addr:postcode":"sw16 6dy",
    "addr:street":"Fallsbrook Road",
    "iso:country":"GB",
    "sg:address":"Fotostop House, 159 Fallsbrook Road",
    "sg:city":"London",
    "sg:classifiers":[
        {
            "category":"Retail",
            "subcategory":"Photofinishing",
            "type":"Services"
        }
    ],
    "sg:phone":"+44 20 8769 5252",
    "sg:postcode":"SW16 6DY",
    "sg:province":"Greater London",
    "sg:tags":[
        "photographic",
        "processor"
    ],
    "wof:name":"Valuegraph Ltd.",
    "wof:placetype":"venue"
},
  "geometry": {"coordinates":[-0.14455,51.418369],"type":"Point"}
}