{
  "type": "Feature",
  "properties": {
    "addr:full":"Allington Road, St Neots Huntingdon Bedfordshire PE19 2RD",
    "addr:postcode":"pe19 2rd",
    "addr:street":"Allington Road",
    "iso:country":"GB",
    "sg:address":"Allington Road, St Neots",
    "sg:city":"Huntingdon",
    "sg:classifiers":[
        {
            "category":"Autos & Motor Vehicles",
            "subcategory":"Automobile Sales",
            "type":"Retail Goods"
        }
    ],
    "sg:phone":"+44 1480 212845",
    "sg:postcode":"PE19 2RD",
    "sg:province":"Bedfordshire",
    "sg:tags":[
        "car"
    ],
    "wof:name":"Chateau Caravans Ltd.",
    "wof:placetype":"venue"
},
  "geometry": {"coordinates":[-0.2638300061,52.2169799805],"type":"Point"}
}