{
  "type": "Feature",
  "properties": {
    "addr:full":"636 Doncaster Road Barnsley South Yorkshire S71 5EE",
    "addr:housenumber":"636",
    "addr:postcode":"s71 5ee",
    "addr:street":"Doncaster Road;Yorkshire",
    "iso:country":"GB",
    "sg:address":"636 Doncaster Road",
    "sg:city":"Barnsley",
    "sg:classifiers":[
        {
            "category":"Bars & Pubs",
            "type":"Food & Drink"
        }
    ],
    "sg:phone":"+44 1226 213969",
    "sg:postcode":"S71 5EE",
    "sg:province":"South Yorkshire",
    "sg:tags":[
        "pubs",
        "inn"
    ],
    "wof:name":"Enterprise Inns Plc",
    "wof:placetype":"venue"
},
  "geometry": {"coordinates":[-1.419157,53.546005],"type":"Point"}
}