{
  "type": "Feature",
  "properties": {
    "iso:country":"GB",
    "sg:address":"Arbroath House, High St Loftus",
    "sg:city":"Saltburn-by-the-sea",
    "sg:classifiers":[
        {
            "category":"Health Services",
            "subcategory":"Dentist",
            "type":"Services"
        }
    ],
    "sg:phone":"+44 1287 642974",
    "sg:postcode":"TS13 4HA",
    "sg:province":"North Yorkshire",
    "wof:name":"N P Plahe",
    "wof:placetype":"venue"
},
  "geometry": {"coordinates":[-0.8986679912,54.5698280334],"type":"Point"}
}