{
  "type": "Feature",
  "properties": {
    "iso:country":"GB",
    "sg:address":"1 High Street",
    "sg:city":"Haslemere",
    "sg:classifiers":[
        {
            "category":"Professional",
            "type":"Services"
        }
    ],
    "sg:phone":"+44 1428 643883",
    "sg:postcode":"GU27 2HG",
    "sg:province":"Hampshire",
    "sg:tags":[
        "interior",
        "furnishers",
        "designer"
    ],
    "wof:name":"F G Avery Ltd.",
    "wof:placetype":"venue"
},
  "geometry": {"coordinates":[-0.709549,51.087662],"type":"Point"}
}