{
  "type": "Feature",
  "properties": {
    "addr:full":"Keyford Garage Frome Somerset BA11 1JJ",
    "addr:postcode":"ba11 1jj",
    "iso:country":"GB",
    "sg:address":"Keyford Garage",
    "sg:city":"Frome",
    "sg:classifiers":[
        {
            "category":"Autos & Motor Vehicles",
            "subcategory":"Automobile Sales",
            "type":"Retail Goods"
        }
    ],
    "sg:postcode":"BA11 1JJ",
    "sg:province":"Somerset",
    "sg:tags":[
        "car"
    ],
    "wof:name":"Barrow,Justin,",
    "wof:placetype":"venue"
},
  "geometry": {"coordinates":[-2.3188068867,51.2285575867],"type":"Point"}
}