{
  "type": "Feature",
  "properties": {
    "iso:country":"GB",
    "sg:address":"Unit 3 The South West Centre, 4 Archer Road",
    "sg:city":"Sheffield",
    "sg:classifiers":[
        {
            "category":"Professional",
            "subcategory":"Engineering",
            "type":"Services"
        }
    ],
    "sg:phone":"+44 114 249 3333",
    "sg:postcode":"S8 0JR",
    "sg:province":"Derbyshire",
    "sg:tags":[
        "engineer"
    ],
    "wof:name":"Vulcan Engineering Ltd.",
    "wof:placetype":"venue"
},
  "geometry": {"coordinates":[-1.48806,53.349838],"type":"Point"}
}