{
  "type": "Feature",
  "properties": {
    "addr:full":"Unit 11 Thornton Industrial Trading Est Milford Haven Pembrokeshire SA73 2RR",
    "addr:housenumber":"unit 11",
    "addr:postcode":"sa73 2rr",
    "addr:street":"Thornton",
    "iso:country":"GB",
    "sg:address":"Unit 11 Thornton Industrial Trading Est",
    "sg:city":"Milford Haven",
    "sg:classifiers":[
        {
            "category":"Parking",
            "type":"Transportation"
        }
    ],
    "sg:phone":"+44 1646 699101",
    "sg:postcode":"SA73 2RR",
    "sg:province":"Pembrokeshire",
    "sg:tags":[
        "car",
        "valet"
    ],
    "wof:name":"Clean Getaway",
    "wof:placetype":"venue"
},
  "geometry": {"coordinates":[-5.027044,51.716808],"type":"Point"}
}