{
  "type": "Feature",
  "properties": {
    "iso:country":"GB",
    "sg:address":"160 Rural Lane",
    "sg:city":"Sheffield",
    "sg:classifiers":[
        {
            "category":"Retail",
            "subcategory":"Repair Shop",
            "type":"Services"
        }
    ],
    "sg:postcode":"S6 4BL",
    "sg:province":"South Yorkshire",
    "sg:tags":[
        "maintenance"
    ],
    "wof:name":"G Reaney & Sons",
    "wof:placetype":"venue"
},
  "geometry": {"coordinates":[-1.5204509497,53.4116325378],"type":"Point"}
}