{
  "type": "Feature",
  "properties": {
    "iso:country":"GB",
    "sg:address":"Lancing Rd",
    "sg:city":"Orpington",
    "sg:classifiers":[
        {
            "category":"Autos & Motor Vehicles",
            "subcategory":"Automobile Sales",
            "type":"Retail Goods"
        }
    ],
    "sg:postcode":"BR6 0QY",
    "sg:province":"Kent",
    "sg:tags":[
        "car"
    ],
    "wof:name":"All Cars of Orpington",
    "wof:placetype":"venue"
},
  "geometry": {"coordinates":[0.10767,51.373177],"type":"Point"}
}