{
  "type": "Feature",
  "properties": {
    "addr:full":"792 Queens Drive Liverpool Merseyside L13 4BT",
    "addr:housenumber":"792",
    "addr:postcode":"l13 4bt",
    "addr:street":"Queens Drive",
    "iso:country":"GB",
    "sg:address":"792 Queens Drive",
    "sg:city":"Liverpool",
    "sg:classifiers":[
        {
            "category":"Food & Beverages",
            "subcategory":"Liquor & Beverages",
            "type":"Retail Goods"
        }
    ],
    "sg:phone":"+44 151 259 6307",
    "sg:postcode":"L13 4BT",
    "sg:province":"Merseyside",
    "sg:tags":[
        "beer",
        "spirit",
        "wines"
    ],
    "wof:name":"The Rocket Wine & Spirit Cellars",
    "wof:placetype":"venue"
},
  "geometry": {"coordinates":[-2.902029,53.410713],"type":"Point"}
}