{
  "type": "Feature",
  "properties": {
    "addr:full":"Archway Theatre, The Drive Horley Surrey RH6 7NQ",
    "addr:postcode":"rh6 7nq",
    "addr:street":"The Drive",
    "iso:country":"GB",
    "sg:address":"Archway Theatre, The Drive",
    "sg:city":"Horley",
    "sg:classifiers":[
        {
            "category":"Arts & Performance",
            "subcategory":"Theater",
            "type":"Entertainment"
        }
    ],
    "sg:phone":"+44 1293 401999",
    "sg:postcode":"RH6 7NQ",
    "sg:province":"Surrey",
    "sg:tags":[
        "hall",
        "theatre",
        "concert"
    ],
    "wof:name":"Archway Theatre Co. Ltd.",
    "wof:placetype":"venue"
},
  "geometry": {"coordinates":[-0.169289,51.175365],"type":"Point"}
}