{
  "type": "Feature",
  "properties": {
    "iso:country":"GB",
    "sg:address":"Dunorlan Medical Group, 64 Pembury Road",
    "sg:city":"Tonbridge",
    "sg:classifiers":[
        {
            "category":"Health Services",
            "subcategory":"Doctor",
            "type":"Services"
        },
        {
            "category":"Health Services",
            "subcategory":"Clinic",
            "type":"Services"
        }
    ],
    "sg:phone":"+44 1732 352907",
    "sg:postcode":"TN9 2JG",
    "sg:province":"Kent",
    "sg:tags":[
        "nh",
        "practitioners"
    ],
    "wof:name":"Dunorlan Medical Group",
    "wof:placetype":"venue"
},
  "geometry": {"coordinates":[0.27634,51.199829],"type":"Point"}
}