{
  "type": "Feature",
  "properties": {
    "iso:country":"GB",
    "sg:address":"Cavendish Road, Stretford",
    "sg:city":"Manchester",
    "sg:classifiers":[
        {
            "category":"Community Center",
            "subcategory":"Youth",
            "type":"Public Place"
        }
    ],
    "sg:phone":"+44 161 864 2853",
    "sg:postcode":"M32 0PS",
    "sg:province":"Cheshire",
    "sg:tags":[
        "organisation",
        "centre"
    ],
    "wof:name":"Gorse Hill Youth Centre",
    "wof:placetype":"venue"
},
  "geometry": {"coordinates":[-2.3000540733,53.4572563171],"type":"Point"}
}