{
  "type": "Feature",
  "properties": {
    "addr:full":"Office& Workshop, Woone Lane Clitheroe Lancashire BB7 1BG",
    "addr:postcode":"bb7 1bg",
    "addr:street":"Woone Lane",
    "iso:country":"GB",
    "sg:address":"Office& Workshop, Woone Lane",
    "sg:city":"Clitheroe",
    "sg:classifiers":[
        {
            "category":"Building & Trades",
            "subcategory":"Plumbing",
            "type":"Services"
        }
    ],
    "sg:phone":"+44 1200 423367",
    "sg:postcode":"BB7 1BG",
    "sg:province":"Lancashire",
    "sg:tags":[
        "plumber",
        "heating"
    ],
    "wof:name":"G D Porter",
    "wof:placetype":"venue"
},
  "geometry": {"coordinates":[-2.394039,53.868683],"type":"Point"}
}