{
  "type": "Feature",
  "properties": {
    "iso:country":"GB",
    "sg:address":"Spa Lodge, Spa Road, Braceborough",
    "sg:city":"Stamford",
    "sg:classifiers":[
        {
            "category":"Utilities",
            "subcategory":"Refuse",
            "type":"Services"
        }
    ],
    "sg:phone":"+44 1778 560876",
    "sg:postcode":"PE9 4NS",
    "sg:province":"Cambridgeshire",
    "sg:tags":[
        "disposal",
        "waste"
    ],
    "wof:name":"Aquameter",
    "wof:placetype":"venue"
},
  "geometry": {"coordinates":[-0.405364,52.700787],"type":"Point"}
}