{
  "type": "Feature",
  "properties": {
    "iso:country":"GB",
    "sg:address":"Flat 9, 9 The Parade Wharf Rd",
    "sg:city":"Aldershot",
    "sg:classifiers":[
        {
            "category":"Personal",
            "type":"Services"
        }
    ],
    "sg:phone":"+44 1252 321478",
    "sg:postcode":"GU12 5AZ",
    "sg:province":"Hampshire",
    "sg:tags":[
        "dressmaker"
    ],
    "wof:name":"Vivienne Designer-dressmaker",
    "wof:placetype":"venue"
},
  "geometry": {"coordinates":[-0.75934,51.249599],"type":"Point"}
}