{
  "type": "Feature",
  "properties": {
    "addr:full":"1 Burnham Ho, The Market Pl Gerrards Cross Buckinghamshire SL9 9DU",
    "addr:housenumber":"1",
    "addr:postcode":"sl9 9du",
    "addr:street":"Burnham Ho The Market Pl",
    "iso:country":"GB",
    "sg:address":"1 Burnham Ho, The Market Pl",
    "sg:city":"Gerrards Cross",
    "sg:classifiers":[
        {
            "category":"Shopping",
            "type":"Retail Goods"
        }
    ],
    "sg:phone":"+44 1753 886367",
    "sg:postcode":"SL9 9DU",
    "sg:province":"Buckinghamshire",
    "sg:tags":[
        "part",
        "accessory"
    ],
    "wof:name":"Car Care",
    "wof:placetype":"venue"
},
  "geometry": {"coordinates":[-0.5625789762,51.5789756775],"type":"Point"}
}