{
  "type": "Feature",
  "properties": {
    "iso:country":"GB",
    "sg:address":"Coldwell Hall, 8 Coldwell Street, Felling",
    "sg:city":"Gateshead",
    "sg:classifiers":[
        {
            "category":"Autos & Motor Vehicles",
            "subcategory":"Fuel & Gas Station",
            "type":"Retail Goods"
        },
        {
            "category":"Autos & Motor Vehicles",
            "subcategory":"Boat Sales",
            "type":"Retail Goods"
        }
    ],
    "sg:phone":"+44 191 420 0909",
    "sg:postcode":"NE10 9HH",
    "sg:province":"Tyne and Wear",
    "sg:tags":[
        "gaming",
        "bottling",
        "machine",
        "bottle",
        "supplier",
        "amusement"
    ],
    "wof:name":"Tyneside Leisure",
    "wof:placetype":"venue"
},
  "geometry": {"coordinates":[-1.569119,54.952229],"type":"Point"}
}