{
  "type": "Feature",
  "properties": {
    "iso:country":"GB",
    "sg:address":"Kilnknowe Farm",
    "sg:city":"Lockerbie",
    "sg:classifiers":[
        {
            "category":"Banks & Credit Unions",
            "subcategory":"Investment Brokerage",
            "type":"Services"
        }
    ],
    "sg:phone":"+44 1461 500201",
    "sg:postcode":"DG11 3NB",
    "sg:province":"Dumfries and Galloway",
    "sg:tags":[
        "contractor"
    ],
    "wof:name":"A P & H M Marshall",
    "wof:placetype":"venue"
},
  "geometry": {"coordinates":[-3.2055990696,55.055770874],"type":"Point"}
}