{
  "type": "Feature",
  "properties": {
    "iso:country":"GB",
    "sg:address":"Sydney House, School Gardens, Castle Gates",
    "sg:city":"Shrewsbury",
    "sg:classifiers":[
        {
            "category":"Health Services",
            "subcategory":"Health Practitioner",
            "type":"Services"
        }
    ],
    "sg:phone":"+44 1743 358785",
    "sg:postcode":"SY1 2AJ",
    "sg:province":"Shropshire",
    "sg:tags":[
        "osteopath"
    ],
    "wof:name":"J Williams",
    "wof:placetype":"venue"
},
  "geometry": {"coordinates":[-2.751227,52.710072],"type":"Point"}
}