{
  "type": "Feature",
  "properties": {
    "addr:full":"2250 Park Way, Kettering Venture Park Kettering Northamptonshire NN15 6XR",
    "addr:housenumber":"2250",
    "addr:postcode":"nn15 6xr",
    "addr:street":"Park Way;Venture Park",
    "iso:country":"GB",
    "sg:address":"2250 Park Way, Kettering Venture Park",
    "sg:city":"Kettering",
    "sg:classifiers":[
        {
            "category":"Manufacturing",
            "subcategory":"Apparel",
            "type":"Manufacturing & Wholesale Goods"
        }
    ],
    "sg:phone":"+44 1536 512804",
    "sg:postcode":"NN15 6XR",
    "sg:province":"Northamptonshire",
    "sg:tags":[
        "mnfr",
        "footwear"
    ],
    "wof:name":"County Footwear (U K) Ltd.",
    "wof:placetype":"venue"
},
  "geometry": {"coordinates":[-0.7225040197,52.3782043457],"type":"Point"}
}