{
  "type": "Feature",
  "properties": {
    "iso:country":"GB",
    "sg:address":"Builders Yard, Wool Road, Parkstone",
    "sg:city":"Poole",
    "sg:classifiers":[
        {
            "category":"Manufacturing",
            "subcategory":"Buildings",
            "type":"Manufacturing & Wholesale Goods"
        }
    ],
    "sg:phone":"+44 1202 580733",
    "sg:postcode":"BH12 4HG",
    "sg:province":"Dorset",
    "sg:tags":[
        "portable"
    ],
    "wof:name":"County Cabins",
    "wof:placetype":"venue"
},
  "geometry": {"coordinates":[-1.92219,50.73988],"type":"Point"}
}