{
  "type": "Feature",
  "properties": {
    "iso:country":"GB",
    "sg:address":"319 Station Road",
    "sg:city":"Harrow",
    "sg:classifiers":[
        {
            "category":"Fast Food",
            "type":"Food & Drink"
        }
    ],
    "sg:phone":"+44 20 8861 2345",
    "sg:postcode":"HA1 2AA",
    "sg:province":"Greater London",
    "sg:tags":[
        "away",
        "take"
    ],
    "wof:name":"Cafeworks",
    "wof:placetype":"venue"
},
  "geometry": {"coordinates":[-0.333937,51.58112],"type":"Point"}
}