{
  "type": "Feature",
  "properties": {
    "addr:full":"Jml House, Regis Rd, Kentish Town Kentish Town Greater London NW5 3EG",
    "addr:postcode":"nw5 3eg",
    "addr:street":"Regis Rd",
    "iso:country":"GB",
    "sg:address":"Jml House, Regis Rd, Kentish Town",
    "sg:city":"Kentish Town",
    "sg:classifiers":[
        {
            "category":"Shopping",
            "subcategory":"Stationery & Office Supplies",
            "type":"Retail Goods"
        }
    ],
    "sg:phone":"+44 20 7691 3800",
    "sg:postcode":"NW5 3EG",
    "sg:province":"Greater London",
    "sg:tags":[
        "item",
        "promotional"
    ],
    "wof:name":"Jml Video Promotion",
    "wof:placetype":"venue"
},
  "geometry": {"coordinates":[-0.1481100023,51.5492095947],"type":"Point"}
}