{
  "type": "Feature",
  "properties": {
    "addr:full":"80 Coleman Street London Greater London EC2R 5BJ",
    "addr:housenumber":"80",
    "addr:postcode":"ec2r 5bj",
    "addr:street":"Coleman Street",
    "iso:country":"GB",
    "sg:address":"80 Coleman Street",
    "sg:city":"London",
    "sg:classifiers":[
        {
            "category":"Professional",
            "subcategory":"Business Services",
            "type":"Services"
        }
    ],
    "sg:phone":"+44 20 7382 2601",
    "sg:postcode":"EC2R 5BJ",
    "sg:province":"Greater London",
    "sg:tags":[
        "trade"
    ],
    "wof:name":"The Society for Underwater Technology",
    "wof:placetype":"venue"
},
  "geometry": {"coordinates":[-0.08931,51.516731],"type":"Point"}
}