{
  "type": "Feature",
  "properties": {
    "addr:full":"31 Homecroft Drive, Uckington Cheltenham Gloucestershire GL51 9SN",
    "addr:housenumber":"31",
    "addr:postcode":"gl51 9sn",
    "addr:street":"Homecroft Drive",
    "iso:country":"GB",
    "sg:address":"31 Homecroft Drive, Uckington",
    "sg:city":"Cheltenham",
    "sg:classifiers":[
        {
            "category":"Retail",
            "subcategory":"Repair Shop",
            "type":"Services"
        }
    ],
    "sg:phone":"+44 1242 680801",
    "sg:postcode":"GL51 9SN",
    "sg:province":"Gloucestershire",
    "sg:tags":[
        "maintenance"
    ],
    "wof:name":"D R Butler",
    "wof:placetype":"venue"
},
  "geometry": {"coordinates":[-2.115923,51.920094],"type":"Point"}
}