{
  "type": "Feature",
  "properties": {
    "iso:country":"GB",
    "sg:address":"28c High St",
    "sg:city":"Princes Risborough",
    "sg:classifiers":[
        {
            "category":"Professional",
            "subcategory":"Engineering",
            "type":"Services"
        }
    ],
    "sg:phone":"+44 1844 275036",
    "sg:postcode":"HP27 0AX",
    "sg:province":"Buckinghamshire",
    "sg:tags":[
        "consulting",
        "engineer"
    ],
    "wof:name":"Tracer Research Corporation",
    "wof:placetype":"venue"
},
  "geometry": {"coordinates":[-0.8307409883,51.7235832214],"type":"Point"}
}