{
  "type": "Feature",
  "properties": {
    "iso:country":"GB",
    "sg:address":"30a Woodford Avenue",
    "sg:city":"Ilford",
    "sg:classifiers":[
        {
            "category":"Fast Food",
            "type":"Food & Drink"
        }
    ],
    "sg:phone":"+44 20 8551 6427",
    "sg:postcode":"IG2 6XG",
    "sg:province":"Essex",
    "sg:tags":[
        "away",
        "take"
    ],
    "wof:name":"Lucky River Chinese Take Away",
    "wof:placetype":"venue"
},
  "geometry": {"coordinates":[0.065497,51.577705],"type":"Point"}
}