{
  "type": "Feature",
  "properties": {
    "addr:full":"8 First Aveune, Sherwood Rise Nottingham Nottinghamshire NG7 6JL",
    "addr:housenumber":"8",
    "addr:postcode":"ng7 6jl",
    "addr:street":"First Aveune",
    "iso:country":"GB",
    "sg:address":"8 First Aveune, Sherwood Rise",
    "sg:city":"Nottingham",
    "sg:classifiers":[
        {
            "category":"Organizations",
            "subcategory":"Community Association",
            "type":"Services"
        }
    ],
    "sg:phone":"+44 115 969 1608",
    "sg:postcode":"NG7 6JL",
    "sg:province":"Nottinghamshire",
    "sg:tags":[
        "society",
        "housing"
    ],
    "wof:name":"Mansfield Road (Nottingham) baptist Housing Association Ltd.",
    "wof:placetype":"venue"
},
  "geometry": {"coordinates":[-1.1577999592,52.9686012268],"type":"Point"}
}