{
  "type": "Feature",
  "properties": {
    "addr:full":"1 Heathfield Mews, Golcar Huddersfield West Yorkshire HD7 4BH",
    "addr:housenumber":"1",
    "addr:postcode":"hd7 4bh",
    "addr:street":"Heathfield Mews;West",
    "iso:country":"GB",
    "sg:address":"1 Heathfield Mews, Golcar",
    "sg:city":"Huddersfield",
    "sg:classifiers":[
        {
            "category":"Manufacturing",
            "subcategory":"Petroleum Products",
            "type":"Manufacturing & Wholesale Goods"
        },
        {
            "category":"Building & Trades",
            "subcategory":"Construction",
            "type":"Services"
        }
    ],
    "sg:phone":"+44 1484 460194",
    "sg:postcode":"HD7 4BH",
    "sg:province":"West Yorkshire",
    "sg:tags":[
        "double",
        "glazing",
        "installers"
    ],
    "wof:name":"Golcar Windows",
    "wof:placetype":"venue"
},
  "geometry": {"coordinates":[-1.8449339867,53.6391868591],"type":"Point"}
}