{
  "type": "Feature",
  "properties": {
    "addr:full":"77 Mansfield Road, Blidworth Mansfield Nottinghamshire NG21 0RB",
    "addr:housenumber":"77",
    "addr:postcode":"ng21 0rb",
    "addr:street":"Mansfield Road",
    "iso:country":"GB",
    "sg:address":"77 Mansfield Road, Blidworth",
    "sg:city":"Mansfield",
    "sg:classifiers":[
        {
            "category":"Personal",
            "subcategory":"Beauty Salon",
            "type":"Services"
        }
    ],
    "sg:phone":"+44 1623 796113",
    "sg:postcode":"NG21 0RB",
    "sg:province":"Nottinghamshire",
    "sg:tags":[
        "unisex",
        "hairdresser"
    ],
    "wof:name":"Unique",
    "wof:placetype":"venue"
},
  "geometry": {"coordinates":[-1.119439,53.101421],"type":"Point"}
}