{
  "type": "Feature",
  "properties": {
    "addr:full":"Lawton Manor Nursing Home, Church Lane Stoke-on-trent Cheshire ST7 3DD",
    "addr:postcode":"st7 3dd",
    "addr:street":"Church Lane",
    "iso:country":"GB",
    "sg:address":"Lawton Manor Nursing Home, Church Lane",
    "sg:city":"Stoke-on-trent",
    "sg:classifiers":[
        {
            "category":"Health Services",
            "subcategory":"Nursing And Care Facility",
            "type":"Services"
        }
    ],
    "sg:phone":"+44 1270 844200",
    "sg:postcode":"ST7 3DD",
    "sg:province":"Cheshire",
    "sg:tags":[
        "home"
    ],
    "wof:name":"Lawton Healthcare Ltd.",
    "wof:placetype":"venue"
},
  "geometry": {"coordinates":[-2.293002,53.107063],"type":"Point"}
}