{
  "type": "Feature",
  "properties": {
    "iso:country":"GB",
    "sg:address":"242 Francis Road, Leyton",
    "sg:city":"London",
    "sg:classifiers":[
        {
            "category":"Community Center",
            "type":"Public Place"
        }
    ],
    "sg:phone":"+44 20 8558 8403",
    "sg:postcode":"E10 6NJ",
    "sg:province":"Greater London",
    "sg:tags":[
        "centre"
    ],
    "wof:name":"Bengali International Ltd.",
    "wof:placetype":"venue"
},
  "geometry": {"coordinates":[-0.007134,51.564514],"type":"Point"}
}