{
  "type": "Feature",
  "properties": {
    "addr:full":"High Bickington Umberleigh Devon EX37 9BU",
    "addr:postcode":"ex37 9bu",
    "iso:country":"GB",
    "sg:address":"High Bickington",
    "sg:city":"Umberleigh",
    "sg:classifiers":[
        {
            "category":"Farming",
            "subcategory":"Livestock Farm",
            "type":"Manufacturing & Wholesale Goods"
        }
    ],
    "sg:phone":"+44 1769 560321",
    "sg:postcode":"EX37 9BU",
    "sg:province":"Devon",
    "sg:tags":[
        "others"
    ],
    "wof:name":"A C Holland",
    "wof:placetype":"venue"
},
  "geometry": {"coordinates":[-3.9853448868,50.9958152771],"type":"Point"}
}