{
  "type": "Feature",
  "properties": {
    "addr:full":"High Street Whitstable Kent CT5 1AY",
    "addr:postcode":"ct5 1ay",
    "addr:street":"High Street",
    "iso:country":"GB",
    "sg:address":"High Street",
    "sg:city":"Whitstable",
    "sg:classifiers":[
        {
            "category":"Shopping",
            "subcategory":"News",
            "type":"Retail Goods"
        },
        {
            "category":"Education",
            "subcategory":"School",
            "type":"Public Place"
        }
    ],
    "sg:phone":"+44 1227 273630",
    "sg:postcode":"CT5 1AY",
    "sg:province":"Kent",
    "sg:tags":[
        "local",
        "newsagent",
        "authority"
    ],
    "wof:name":"Whitstable Endowed C of E Junior School",
    "wof:placetype":"venue"
},
  "geometry": {"coordinates":[1.02448,51.358871],"type":"Point"}
}