{
  "type": "Feature",
  "properties": {
    "addr:full":"22 Strand St Poole Dorset BH15 1SB",
    "addr:housenumber":"22",
    "addr:postcode":"bh15 1sb",
    "addr:street":"Strand St",
    "iso:country":"GB",
    "sg:address":"22 Strand St",
    "sg:city":"Poole",
    "sg:classifiers":[
        {
            "category":"Wholesale",
            "subcategory":"Books, Periodicals, & Newspapers",
            "type":"Manufacturing & Wholesale Goods"
        }
    ],
    "sg:phone":"+44 1202 679000",
    "sg:postcode":"BH15 1SB",
    "sg:province":"Dorset",
    "sg:tags":[
        "publishing"
    ],
    "wof:name":"Quay Magazine Publishing Ltd",
    "wof:placetype":"venue"
},
  "geometry": {"coordinates":[-1.986745,50.71286],"type":"Point"}
}