{
  "type": "Feature",
  "properties": {
    "iso:country":"GB",
    "sg:address":"54 Townley St, Middleton",
    "sg:city":"Manchester",
    "sg:classifiers":[
        {
            "category":"Bars & Pubs",
            "type":"Food & Drink"
        }
    ],
    "sg:phone":"+44 161 654 4346",
    "sg:postcode":"M24 1BT",
    "sg:province":"Greater Manchester",
    "sg:tags":[
        "pubs",
        "inn"
    ],
    "wof:name":"The Railway Hotel",
    "wof:placetype":"venue"
},
  "geometry": {"coordinates":[-2.1923539639,53.5487594604],"type":"Point"}
}