{
  "type": "Feature",
  "properties": {
    "iso:country":"GB",
    "sg:address":"38 Rookery Lane, Spring Park, Kingsthorpe",
    "sg:city":"Northampton",
    "sg:classifiers":[
        {
            "category":"Building & Trades",
            "subcategory":"Construction",
            "type":"Services"
        }
    ],
    "sg:phone":"+44 1604 844050",
    "sg:postcode":"NN2 8BQ",
    "sg:province":"Northamptonshire",
    "sg:tags":[
        "builder",
        "joiner",
        "carpenter"
    ],
    "wof:name":"Midland Carpentry Services",
    "wof:placetype":"venue"
},
  "geometry": {"coordinates":[-0.9108970165,52.2722702026],"type":"Point"}
}