{
  "type": "Feature",
  "properties": {
    "addr:full":"6 Highfield Road Birmingham West Midlands B8 3QX",
    "addr:housenumber":"6",
    "addr:postcode":"b8 3qx",
    "addr:street":"Highfield Road",
    "iso:country":"GB",
    "sg:address":"6 Highfield Road",
    "sg:city":"Birmingham",
    "sg:classifiers":[
        {
            "category":"Food & Beverages",
            "subcategory":"Meat & Fish",
            "type":"Retail Goods"
        }
    ],
    "sg:phone":"+44 121 327 4126",
    "sg:postcode":"B8 3QX",
    "sg:province":"West Midlands",
    "sg:tags":[
        "chip"
    ],
    "wof:name":"Highfield Fish Shop",
    "wof:placetype":"venue"
},
  "geometry": {"coordinates":[-1.851427,52.489227],"type":"Point"}
}