{
  "type": "Feature",
  "properties": {
    "iso:country":"GB",
    "sg:address":"23 High Street",
    "sg:city":"Swansea",
    "sg:classifiers":[
        {
            "category":"Fast Food",
            "type":"Food & Drink"
        }
    ],
    "sg:phone":"+44 1792 895182",
    "sg:postcode":"SA4 4BX",
    "sg:province":"Carmarthenshire",
    "sg:tags":[
        "away",
        "take"
    ],
    "wof:name":"Taj Balti Takeaway",
    "wof:placetype":"venue"
},
  "geometry": {"coordinates":[-4.035769,51.668278],"type":"Point"}
}