{
  "type": "Feature",
  "properties": {
    "addr:full":"167 Boroughbridge Road York North Yorkshire YO26 6AN",
    "addr:housenumber":"167",
    "addr:postcode":"yo26 6an",
    "addr:street":"Boroughbridge Road",
    "iso:country":"GB",
    "sg:address":"167 Boroughbridge Road",
    "sg:city":"York",
    "sg:classifiers":[
        {
            "category":"Wholesale",
            "subcategory":"Office Equipment",
            "type":"Manufacturing & Wholesale Goods"
        }
    ],
    "sg:postcode":"YO26 6AN",
    "sg:province":"North Yorkshire",
    "sg:tags":[
        "register",
        "cash",
        "accessory"
    ],
    "wof:name":"G & B Cash Registers",
    "wof:placetype":"venue"
},
  "geometry": {"coordinates":[-1.127892971,53.9669876099],"type":"Point"}
}