{
  "type": "Feature",
  "properties": {
    "addr:full":"679-681 Green Lane Dagenham Essex RM8 1UU",
    "addr:housenumber":"679-681",
    "addr:postcode":"rm8 1uu",
    "addr:street":"Green Lane",
    "iso:country":"GB",
    "sg:address":"679-681 Green Lane",
    "sg:city":"Dagenham",
    "sg:classifiers":[
        {
            "category":"Home & Garden",
            "subcategory":"Carpets & Floor Coverings",
            "type":"Retail Goods"
        }
    ],
    "sg:phone":"+44 20 8597 0909",
    "sg:postcode":"RM8 1UU",
    "sg:province":"Essex",
    "sg:tags":[
        "carpets",
        "rug",
        "matting"
    ],
    "wof:name":"Carpet Matters Ltd.",
    "wof:placetype":"venue"
},
  "geometry": {"coordinates":[0.122389,51.562504],"type":"Point"}
}