{
  "type": "Feature",
  "properties": {
    "addr:full":"385 Cricklade Road Swindon Wiltshire SN2 1AQ",
    "addr:housenumber":"385",
    "addr:postcode":"sn2 1aq",
    "addr:street":"Cricklade Road",
    "iso:country":"GB",
    "sg:address":"385 Cricklade Road",
    "sg:city":"Swindon",
    "sg:classifiers":[
        {
            "category":"Professional",
            "subcategory":"Detective & Security Services",
            "type":"Services"
        }
    ],
    "sg:phone":"+44 1793 525433",
    "sg:postcode":"SN2 1AQ",
    "sg:province":"Wiltshire",
    "sg:tags":[
        "locksmith"
    ],
    "wof:name":"Emergency Security Services (Swindon) Ltd.",
    "wof:placetype":"venue"
},
  "geometry": {"coordinates":[-1.7768390179,51.5791816711],"type":"Point"}
}