{
  "type": "Feature",
  "properties": {
    "iso:country":"GB",
    "sg:address":"378 South Coast Road, Telscombe Cliffs",
    "sg:city":"Peacehaven",
    "sg:classifiers":[
        {
            "category":"Retail",
            "subcategory":"Auto Repair",
            "type":"Services"
        }
    ],
    "sg:phone":"+44 1273 586203",
    "sg:postcode":"BN10 7ET",
    "sg:province":"East Sussex",
    "sg:tags":[
        "modification",
        "garage"
    ],
    "wof:name":"Saltdean Garage Ltd.",
    "wof:placetype":"venue"
},
  "geometry": {"coordinates":[-0.012549,50.793652],"type":"Point"}
}