{
  "type": "Feature",
  "properties": {
    "iso:country":"GB",
    "sg:address":"Kirkthorne, Northside",
    "sg:city":"Driffield",
    "sg:classifiers":[
        {
            "category":"Building & Trades",
            "subcategory":"Construction",
            "type":"Services"
        }
    ],
    "sg:phone":"+44 1262 420155",
    "sg:postcode":"YO25 0RX",
    "sg:province":"East Riding of Yorkshire",
    "sg:tags":[
        "decorator",
        "painter"
    ],
    "wof:name":"Wain's Decorators",
    "wof:placetype":"venue"
},
  "geometry": {"coordinates":[-0.4363,54.008968],"type":"Point"}
}