{
  "type": "Feature",
  "properties": {
    "iso:country":"GB",
    "sg:address":"488 Hale Road",
    "sg:city":"Widnes",
    "sg:classifiers":[
        {
            "category":"Food & Beverages",
            "subcategory":"Meat & Fish",
            "type":"Retail Goods"
        }
    ],
    "sg:phone":"+44 151 425 2041",
    "sg:postcode":"WA8 8XQ",
    "sg:province":"Cheshire",
    "sg:tags":[
        "chip"
    ],
    "wof:name":"Lukes",
    "wof:placetype":"venue"
},
  "geometry": {"coordinates":[-2.775173,53.349472],"type":"Point"}
}