{
  "type": "Feature",
  "properties": {
    "addr:full":"155 Epsom Road Sutton Surrey SM3 9EY",
    "addr:housenumber":"155",
    "addr:postcode":"sm3 9ey",
    "addr:street":"Epsom Road",
    "iso:country":"GB",
    "sg:address":"155 Epsom Road",
    "sg:city":"Sutton",
    "sg:classifiers":[
        {
            "category":"Professional",
            "subcategory":"Printing & Photocopies",
            "type":"Services"
        }
    ],
    "sg:phone":"+44 20 8641 5041",
    "sg:postcode":"SM3 9EY",
    "sg:province":"Surrey",
    "sg:tags":[
        "printer"
    ],
    "wof:name":"66 Printers & Stationers",
    "wof:placetype":"venue"
},
  "geometry": {"coordinates":[-0.210754,51.386124],"type":"Point"}
}