{
  "type": "Feature",
  "properties": {
    "addr:full":"121 Western Road Hove East Sussex BN3 1DB",
    "addr:housenumber":"121",
    "addr:postcode":"bn3 1db",
    "addr:street":"Western Road",
    "iso:country":"GB",
    "sg:address":"121 Western Road",
    "sg:city":"Hove",
    "sg:classifiers":[
        {
            "category":"Restaurant",
            "type":"Food & Drink"
        }
    ],
    "sg:phone":"+44 1273 779474",
    "sg:postcode":"BN3 1DB",
    "sg:province":"East Sussex",
    "wof:name":"Ipanema",
    "wof:placetype":"venue"
},
  "geometry": {"coordinates":[-0.1567949951,50.8255271912],"type":"Point"}
}