{
  "type": "Feature",
  "properties": {
    "iso:country":"GB",
    "sg:address":"3 Meadow Rd",
    "sg:city":"Stoke On Trent",
    "sg:classifiers":[
        {
            "category":"Freight",
            "type":"Transportation"
        }
    ],
    "sg:phone":"+44 1782 503681",
    "sg:postcode":"ST6 8SQ",
    "sg:province":"Staffordshire",
    "sg:tags":[
        "haulage",
        "road"
    ],
    "wof:name":"3a Transports",
    "wof:placetype":"venue"
},
  "geometry": {"coordinates":[-2.137957,53.074039],"type":"Point"}
}