{
  "type": "Feature",
  "properties": {
    "addr:full":"159 Parklands Rd Chichester West Sussex PO19 3ED",
    "addr:housenumber":"159",
    "addr:postcode":"po19 3ed",
    "addr:street":"Parklands Rd",
    "iso:country":"GB",
    "sg:address":"159 Parklands Rd",
    "sg:city":"Chichester",
    "sg:classifiers":[
        {
            "category":"Professional",
            "subcategory":"Accounting & Tax Preparation",
            "type":"Services"
        }
    ],
    "sg:phone":"+44 1243 533651",
    "sg:postcode":"PO19 3ED",
    "sg:province":"West Sussex",
    "sg:tags":[
        "accountant"
    ],
    "wof:name":"Freelance Accountancy Service",
    "wof:placetype":"venue"
},
  "geometry": {"coordinates":[-0.784552,50.843365],"type":"Point"}
}