{
  "type": "Feature",
  "properties": {
    "iso:country":"GB",
    "sg:address":"Unit 17 Honeyborough Industrial Estate, Neyland",
    "sg:city":"Milford Haven",
    "sg:classifiers":[
        {
            "category":"Wholesale",
            "subcategory":"Construction Materials",
            "type":"Manufacturing & Wholesale Goods"
        }
    ],
    "sg:postcode":"SA73 1SE",
    "sg:province":"Pembrokeshire",
    "sg:tags":[
        "lift"
    ],
    "wof:name":"Simon Safety & Lifting Centre Ltd.",
    "wof:placetype":"venue"
},
  "geometry": {"coordinates":[-4.95387,51.715408],"type":"Point"}
}