{
  "type": "Feature",
  "properties": {
    "iso:country":"GB",
    "sg:address":"Main Street, Kirkby Malzeard",
    "sg:city":"Ripon",
    "sg:classifiers":[
        {
            "category":"Retail",
            "subcategory":"Auto Repair",
            "type":"Services"
        }
    ],
    "sg:phone":"+44 1765 658468",
    "sg:postcode":"HG4 3SE",
    "sg:province":"North Yorkshire",
    "sg:tags":[
        "modification",
        "garage",
        "related"
    ],
    "wof:name":"Kirkby Motors",
    "wof:placetype":"venue"
},
  "geometry": {"coordinates":[-1.642475009,54.1646461487],"type":"Point"}
}