{
  "type": "Feature",
  "properties": {
    "iso:country":"GB",
    "sg:address":"8 Broad Street",
    "sg:city":"Barry",
    "sg:classifiers":[
        {
            "category":"Professional",
            "subcategory":"Lawyer & Legal Services",
            "type":"Services"
        }
    ],
    "sg:phone":"+44 1446 720444",
    "sg:postcode":"CF62 7AA",
    "sg:province":"The Vale of Glamorgan",
    "sg:tags":[
        "solicitor"
    ],
    "wof:name":"CRANES SOLICITORS",
    "wof:placetype":"venue"
},
  "geometry": {"coordinates":[-3.28357,51.39909],"type":"Point"}
}