{
  "type": "Feature",
  "properties": {
    "addr:full":"28 Embassy Court Welling Kent DA16 1TH",
    "addr:housenumber":"28",
    "addr:postcode":"da16 1th",
    "addr:street":"Embassy Court",
    "iso:country":"GB",
    "sg:address":"28 Embassy Court",
    "sg:city":"Welling",
    "sg:classifiers":[
        {
            "category":"Food & Beverages",
            "subcategory":"Supermarket",
            "type":"Retail Goods"
        }
    ],
    "sg:phone":"+44 20 8303 5987",
    "sg:postcode":"DA16 1TH",
    "sg:province":"Kent",
    "wof:name":"Tesco Stores Ltd.",
    "wof:placetype":"venue"
},
  "geometry": {"coordinates":[0.109480001,51.461971283],"type":"Point"}
}