{
  "type": "Feature",
  "properties": {
    "iso:country":"GB",
    "sg:address":"Hampden Estate Office, Great Hampden",
    "sg:city":"Great Missenden",
    "sg:classifiers":[
        {
            "category":"Professional",
            "subcategory":"Management & Consulting",
            "type":"Services"
        }
    ],
    "sg:phone":"+44 1494 488744",
    "sg:postcode":"HP16 9RE",
    "sg:province":"Buckinghamshire",
    "sg:tags":[
        "marketing",
        "consultant"
    ],
    "wof:name":"Hampden Estate Office",
    "wof:placetype":"venue"
},
  "geometry": {"coordinates":[-0.709043026,51.7040672302],"type":"Point"}
}