{
  "type": "Feature",
  "properties": {
    "addr:full":"Benham Stud Newbury Berkshire RG16 8EP",
    "addr:postcode":"rg16 8ep",
    "addr:street":"Newbury",
    "iso:country":"GB",
    "sg:address":"Benham Stud",
    "sg:city":"Newbury",
    "sg:classifiers":[
        {
            "category":"Farming",
            "subcategory":"Livestock Farm",
            "type":"Manufacturing & Wholesale Goods"
        }
    ],
    "sg:phone":"+44 1635 41030",
    "sg:postcode":"RG16 8EP",
    "sg:province":"Berkshire",
    "sg:tags":[
        "others"
    ],
    "wof:name":"Denton Roger C",
    "wof:placetype":"venue"
},
  "geometry": {"coordinates":[-1.32587,51.405869],"type":"Point"}
}