{
  "type": "Feature",
  "properties": {
    "addr:full":"Rear Of 137 Hook Road Surbiton Surrey KT6 5AR",
    "addr:postcode":"kt6 5ar",
    "addr:street":"Hook Road",
    "iso:country":"GB",
    "sg:address":"Rear Of 137 Hook Road",
    "sg:city":"Surbiton",
    "sg:classifiers":[
        {
            "category":"Retail",
            "subcategory":"Auto Repair",
            "type":"Services"
        }
    ],
    "sg:phone":"+44 20 8391 1999",
    "sg:postcode":"KT6 5AR",
    "sg:province":"Surrey",
    "sg:tags":[
        "car",
        "specialist",
        "customizing"
    ],
    "wof:name":"Convert-A-Car",
    "wof:placetype":"venue"
},
  "geometry": {"coordinates":[-0.306949,51.392059],"type":"Point"}
}