{
  "type": "Feature",
  "properties": {
    "addr:full":"2 Pilmuir Holdings, Newton Mearns Glasgow East Ayrshire G77 6PS",
    "addr:housenumber":"2",
    "addr:postcode":"g77 6ps",
    "addr:street":"Pilmuir Holdings",
    "iso:country":"GB",
    "sg:address":"2 Pilmuir Holdings, Newton Mearns",
    "sg:city":"Glasgow",
    "sg:classifiers":[
        {
            "category":"Retail",
            "subcategory":"Auto Repair",
            "type":"Services"
        }
    ],
    "sg:postcode":"G77 6PS",
    "sg:province":"East Ayrshire",
    "sg:tags":[
        "modification",
        "garage"
    ],
    "wof:name":"D Paterson Garages Services",
    "wof:placetype":"venue"
},
  "geometry": {"coordinates":[-4.364573,55.763412],"type":"Point"}
}