{
  "type": "Feature",
  "properties": {
    "iso:country":"GB",
    "sg:address":"The Barn Office, Rookwood Lane, Preston St Mary",
    "sg:city":"Sudbury",
    "sg:classifiers":[
        {
            "category":"Real Estate",
            "subcategory":"Surveying",
            "type":"Services"
        }
    ],
    "sg:phone":"+44 1787 247089",
    "sg:postcode":"CO10 9LY",
    "sg:province":"Essex",
    "sg:tags":[
        "building",
        "surveyor"
    ],
    "wof:name":"Ian Wilson & Co",
    "wof:placetype":"venue"
},
  "geometry": {"coordinates":[0.8322,52.125992],"type":"Point"}
}