{
  "type": "Feature",
  "properties": {
    "iso:country":"GB",
    "sg:address":"45 Palace Avenue",
    "sg:city":"Paignton",
    "sg:classifiers":[
        {
            "category":"Food & Beverages",
            "subcategory":"Bakery",
            "type":"Retail Goods"
        }
    ],
    "sg:phone":"+44 1803 528726",
    "sg:postcode":"TQ3 3EN",
    "sg:province":"Devon",
    "sg:tags":[
        "baker"
    ],
    "wof:name":"Swayne's Bakery",
    "wof:placetype":"venue"
},
  "geometry": {"coordinates":[-3.570515,50.435497],"type":"Point"}
}