{
  "type": "Feature",
  "properties": {
    "addr:full":"20 Chichester Drive, Oulton Broad Lowestoft Suffolk NR33 8PX",
    "addr:housenumber":"20",
    "addr:postcode":"nr33 8px",
    "addr:street":"Chichester Drive",
    "iso:country":"GB",
    "sg:address":"20 Chichester Drive, Oulton Broad",
    "sg:city":"Lowestoft",
    "sg:classifiers":[
        {
            "category":"Real Estate",
            "subcategory":"Architect",
            "type":"Services"
        }
    ],
    "sg:phone":"+44 1502 514045",
    "sg:postcode":"NR33 8PX",
    "sg:province":"Suffolk",
    "wof:name":"Chichester Associates Ltd",
    "wof:placetype":"venue"
},
  "geometry": {"coordinates":[1.7030800581,52.4634208679],"type":"Point"}
}