{
  "type": "Feature",
  "properties": {
    "addr:full":"8 Temple Lane Liverpool Merseyside L2 5RL",
    "addr:housenumber":"8",
    "addr:postcode":"l2 5rl",
    "addr:street":"Temple Lane",
    "iso:country":"GB",
    "sg:address":"8 Temple Lane",
    "sg:city":"Liverpool",
    "sg:classifiers":[
        {
            "category":"Organizations",
            "subcategory":"Membership Organization",
            "type":"Services"
        }
    ],
    "sg:phone":"+44 151 236 5160",
    "sg:postcode":"L2 5RL",
    "sg:province":"Merseyside",
    "sg:tags":[
        "club"
    ],
    "wof:name":"The Curzon Club",
    "wof:placetype":"venue"
},
  "geometry": {"coordinates":[-2.9882760048,53.4071960449],"type":"Point"}
}