{
  "type": "Feature",
  "properties": {
    "addr:full":"36 Saddler St Durham Durham DH1 3NU",
    "addr:housenumber":"36",
    "addr:postcode":"dh1 3nu",
    "addr:street":"Saddler St",
    "iso:country":"GB",
    "sg:address":"36 Saddler St",
    "sg:city":"Durham",
    "sg:classifiers":[
        {
            "category":"Real Estate",
            "subcategory":"Real Estate Operator",
            "type":"Services"
        }
    ],
    "sg:phone":"+44 191 384 6866",
    "sg:postcode":"DH1 3NU",
    "sg:province":"Durham",
    "sg:tags":[
        "letting",
        "agent"
    ],
    "wof:name":"Whitegate Lettings",
    "wof:placetype":"venue"
},
  "geometry": {"coordinates":[-1.574745059,54.7763214111],"type":"Point"}
}