{
  "type": "Feature",
  "properties": {
    "addr:full":"Knife Hill Farm, Winterborne Stickland Blandford Forum Dorset DT11 0NA",
    "addr:housenumber":"stickland",
    "addr:postcode":"dt11 0na",
    "addr:street":"Knife Hill",
    "iso:country":"GB",
    "sg:address":"Knife Hill Farm, Winterborne Stickland",
    "sg:city":"Blandford Forum",
    "sg:classifiers":[
        {
            "category":"Farming",
            "subcategory":"Dairy Farm",
            "type":"Manufacturing & Wholesale Goods"
        },
        {
            "category":"Farming",
            "subcategory":"Livestock Farm",
            "type":"Manufacturing & Wholesale Goods"
        }
    ],
    "sg:phone":"+44 1258 880696",
    "sg:postcode":"DT11 0NA",
    "sg:province":"Dorset",
    "sg:tags":[
        "others",
        "farmer"
    ],
    "wof:name":"R & P Britton",
    "wof:placetype":"venue"
},
  "geometry": {"coordinates":[-2.236914,50.843891],"type":"Point"}
}