{
  "type": "Feature",
  "properties": {
    "iso:country":"GB",
    "sg:address":"Phoenix Court, Alexandra Road",
    "sg:city":"Basingstoke",
    "sg:classifiers":[
        {
            "category":"Building & Trades",
            "subcategory":"Construction",
            "type":"Services"
        }
    ],
    "sg:phone":"+44 1256 477884",
    "sg:postcode":"RG21 7RQ",
    "sg:province":"Hampshire",
    "sg:tags":[
        "conversion",
        "loft"
    ],
    "wof:name":"Loftplan Ltd.",
    "wof:placetype":"venue"
},
  "geometry": {"coordinates":[-1.0993289948,51.2642593384],"type":"Point"}
}