{
  "type": "Feature",
  "properties": {
    "addr:full":"Pasadena Yard, Toms Lane King's Langley Hertfordshire WD4 8NH",
    "addr:postcode":"wd4 8nh",
    "addr:street":"Pasadena;Toms Lane",
    "iso:country":"GB",
    "sg:address":"Pasadena Yard, Toms Lane",
    "sg:city":"King's Langley",
    "sg:classifiers":[
        {
            "category":"Manufacturing",
            "subcategory":"Wood Products",
            "type":"Manufacturing & Wholesale Goods"
        }
    ],
    "sg:postcode":"WD4 8NH",
    "sg:province":"Hertfordshire",
    "sg:tags":[
        "maker",
        "cabinet"
    ],
    "wof:name":"Phillip Batten",
    "wof:placetype":"venue"
},
  "geometry": {"coordinates":[-0.4345400035,51.7172584534],"type":"Point"}
}