{
  "type": "Feature",
  "properties": {
    "addr:full":"163 Prince Edward Road South Shields Tyne and Wear NE34 8PL",
    "addr:housenumber":"163",
    "addr:postcode":"ne34 8pl",
    "addr:street":"Prince Edward Road",
    "iso:country":"GB",
    "sg:address":"163 Prince Edward Road",
    "sg:city":"South Shields",
    "sg:classifiers":[
        {
            "category":"Travel",
            "subcategory":"Travel Agent",
            "type":"Entertainment"
        }
    ],
    "sg:phone":"+44 191 455 6411",
    "sg:postcode":"NE34 8PL",
    "sg:province":"Tyne and Wear",
    "wof:name":"Hays Travel Ltd.",
    "wof:placetype":"venue"
},
  "geometry": {"coordinates":[-1.4122949839,54.9720687866],"type":"Point"}
}