{
  "type": "Feature",
  "properties": {
    "iso:country":"GB",
    "sg:address":"Unit 8, Phoenix Industrial Park",
    "sg:city":"Eastleigh",
    "sg:classifiers":[
        {
            "category":"Health Services",
            "subcategory":"Dentist",
            "type":"Services"
        }
    ],
    "sg:phone":"+44 23 8062 0996",
    "sg:postcode":"SO50 6PQ",
    "sg:province":"Hampshire",
    "sg:tags":[
        "technician",
        "dental"
    ],
    "wof:name":"Quality Smiles Ltd.",
    "wof:placetype":"venue"
},
  "geometry": {"coordinates":[-1.3505929708,50.9683227539],"type":"Point"}
}