{
  "type": "Feature",
  "properties": {
    "addr:full":"Brockhollands Road, Bream Lydney Gloucestershire GL15 6ND",
    "addr:postcode":"gl15 6nd",
    "addr:street":"Brockhollands Road",
    "iso:country":"GB",
    "sg:address":"Brockhollands Road, Bream",
    "sg:city":"Lydney",
    "sg:classifiers":[
        {
            "category":"Personal",
            "subcategory":"Beauty Salon",
            "type":"Services"
        },
        {
            "category":"Personal",
            "subcategory":"Barber",
            "type":"Services"
        }
    ],
    "sg:phone":"+44 1594 562221",
    "sg:postcode":"GL15 6ND",
    "sg:province":"Gloucestershire",
    "sg:tags":[
        "unisex",
        "hairdresser"
    ],
    "wof:name":"Snips",
    "wof:placetype":"venue"
},
  "geometry": {"coordinates":[-2.574489,51.750587],"type":"Point"}
}