{
  "type": "Feature",
  "properties": {
    "addr:full":"3a Roberts Road Leicester Leicestershire LE4 5HG",
    "addr:housenumber":"3a",
    "addr:postcode":"le4 5hg",
    "addr:street":"Roberts Road",
    "iso:country":"GB",
    "sg:address":"3a Roberts Road",
    "sg:city":"Leicester",
    "sg:classifiers":[
        {
            "category":"Fast Food",
            "type":"Food & Drink"
        }
    ],
    "sg:postcode":"LE4 5HG",
    "sg:province":"Leicestershire",
    "sg:tags":[
        "away",
        "take"
    ],
    "wof:name":"Sangam Pan House",
    "wof:placetype":"venue"
},
  "geometry": {"coordinates":[-1.123918,52.648701],"type":"Point"}
}