{
  "type": "Feature",
  "properties": {
    "iso:country":"GB",
    "sg:address":"47 The Great Meadow, Higher Crompton",
    "sg:city":"Oldham",
    "sg:classifiers":[
        {
            "category":"Professional",
            "subcategory":"Detective & Security Services",
            "type":"Services"
        },
        {
            "category":"Building & Trades",
            "subcategory":"Construction",
            "type":"Services"
        }
    ],
    "sg:phone":"+44 1706 840077",
    "sg:postcode":"OL2 7PX",
    "sg:province":"Lancashire",
    "sg:tags":[
        "builder",
        "burglar",
        "alarm",
        "system"
    ],
    "wof:name":"Kevin Walsh",
    "wof:placetype":"venue"
},
  "geometry": {"coordinates":[-2.1063320637,53.5869522095],"type":"Point"}
}