{
  "type": "Feature",
  "properties": {
    "iso:country":"GB",
    "sg:address":"White Pines Greaves Rd",
    "sg:city":"Wilmslow",
    "sg:classifiers":[
        {
            "category":"Health Services",
            "subcategory":"Doctor",
            "type":"Services"
        }
    ],
    "sg:phone":"+44 1625 528773",
    "sg:postcode":"SK9 5NJ",
    "sg:province":"Cheshire",
    "sg:tags":[
        "practitioners"
    ],
    "wof:name":"Railton",
    "wof:placetype":"venue"
},
  "geometry": {"coordinates":[-2.227897,53.326797],"type":"Point"}
}