{
  "type": "Feature",
  "properties": {
    "addr:full":"Kings Hall, St Ives Business Park, Parsons Green St Ives Cambridgeshire PE27 4WY",
    "addr:postcode":"pe27 4wy",
    "addr:street":"Business Park",
    "iso:country":"GB",
    "sg:address":"Kings Hall, St Ives Business Park, Parsons Green",
    "sg:city":"St Ives",
    "sg:classifiers":[
        {
            "category":"Professional",
            "subcategory":"Printing & Photocopies",
            "type":"Services"
        },
        {
            "category":"Professional",
            "subcategory":"Computer Services",
            "type":"Services"
        }
    ],
    "sg:phone":"+44 1480 464618",
    "sg:postcode":"PE27 4WY",
    "sg:province":"Cambridgeshire",
    "sg:tags":[
        "development",
        "image",
        "processing",
        "system",
        "software"
    ],
    "wof:name":"COLORTRAC LTD",
    "wof:placetype":"venue"
},
  "geometry": {"coordinates":[-0.05866,52.328449],"type":"Point"}
}