{
  "type": "Feature",
  "properties": {
    "iso:country":"GB",
    "sg:address":"Rowledge",
    "sg:city":"Farnham",
    "sg:classifiers":[
        {
            "category":"Education",
            "subcategory":"School",
            "type":"Public Place"
        }
    ],
    "sg:phone":"+44 1252 792006",
    "sg:postcode":"GU10 4EA",
    "sg:province":"Hampshire",
    "sg:tags":[
        "independent",
        "preparatory"
    ],
    "wof:name":"The Frensham Heights Junior School",
    "wof:placetype":"venue"
},
  "geometry": {"coordinates":[-0.81153,51.17709],"type":"Point"}
}