{
  "type": "Feature",
  "properties": {
    "addr:full":"30a High Street Maldon Essex CM9 5ET",
    "addr:housenumber":"30a",
    "addr:postcode":"cm9 5et",
    "addr:street":"High Street",
    "iso:country":"GB",
    "sg:address":"30a High Street",
    "sg:city":"Maldon",
    "sg:classifiers":[
        {
            "category":"Shopping",
            "subcategory":"Clothing, Apparel, & Fashions",
            "type":"Retail Goods"
        }
    ],
    "sg:phone":"+44 1621 857070",
    "sg:postcode":"CM9 5ET",
    "sg:province":"Essex",
    "sg:tags":[
        "shop"
    ],
    "wof:name":"Howards",
    "wof:placetype":"venue"
},
  "geometry": {"coordinates":[0.676528,51.731441],"type":"Point"}
}