{
  "type": "Feature",
  "properties": {
    "addr:full":"37 Frensham Road, Lower Bourne Farnham Hampshire GU10 3PZ",
    "addr:housenumber":"37",
    "addr:postcode":"gu10 3pz",
    "addr:street":"Frensham Road Lower",
    "iso:country":"GB",
    "sg:address":"37 Frensham Road, Lower Bourne",
    "sg:city":"Farnham",
    "sg:classifiers":[
        {
            "category":"Professional",
            "type":"Services"
        }
    ],
    "sg:phone":"+44 1252 727054",
    "sg:postcode":"GU10 3PZ",
    "sg:province":"Hampshire",
    "sg:tags":[
        "interior",
        "furnishers",
        "designer"
    ],
    "wof:name":"Church Lane Interiors Ltd.",
    "wof:placetype":"venue"
},
  "geometry": {"coordinates":[-0.789116,51.195396],"type":"Point"}
}