{
  "type": "Feature",
  "properties": {
    "iso:country":"GB",
    "sg:address":"12 Sheep Street",
    "sg:city":"Skipton",
    "sg:classifiers":[
        {
            "category":"Shopping",
            "subcategory":"Books",
            "type":"Retail Goods"
        }
    ],
    "sg:phone":"+44 1756 798769",
    "sg:postcode":"BD23 1HY",
    "sg:province":"Lancashire",
    "sg:tags":[
        "bookseller"
    ],
    "wof:name":"Dovechaste Ltd.",
    "wof:placetype":"venue"
},
  "geometry": {"coordinates":[-2.017289,53.961334],"type":"Point"}
}