{
  "type": "Feature",
  "properties": {
    "iso:country":"GB",
    "sg:address":"Melrose Ho, 15-23 Cadogan St",
    "sg:city":"Glasgow",
    "sg:classifiers":[
        {
            "category":"Professional",
            "subcategory":"Lawyer & Legal Services",
            "type":"Services"
        }
    ],
    "sg:postcode":"G2 6QQ",
    "sg:province":"Glasgow City",
    "sg:tags":[
        "advice",
        "counselling"
    ],
    "wof:name":"Harken Ecosse Ltd",
    "wof:placetype":"venue"
},
  "geometry": {"coordinates":[-4.26024,55.859631],"type":"Point"}
}