{
  "type": "Feature",
  "properties": {
    "iso:country":"GB",
    "sg:address":"41 Shaw Road",
    "sg:city":"Blackpool",
    "sg:classifiers":[
        {
            "category":"Travel",
            "subcategory":"Hotels & Motels",
            "type":"Entertainment"
        }
    ],
    "sg:postcode":"FY1 6HA",
    "sg:province":"Lancashire",
    "sg:tags":[
        "house",
        "guest"
    ],
    "wof:name":"Bluebell Guest House",
    "wof:placetype":"venue"
},
  "geometry": {"coordinates":[-3.0518279076,53.8000488281],"type":"Point"}
}