{
  "type": "Feature",
  "properties": {
    "iso:country":"GB",
    "sg:address":"7 Pound Road",
    "sg:city":"Chertsey",
    "sg:classifiers":[
        {
            "category":"Real Estate",
            "subcategory":"Real Estate Agent",
            "type":"Services"
        }
    ],
    "sg:postcode":"KT16 8EH",
    "sg:province":"Surrey",
    "wof:name":"Torbury Properties Ltd.",
    "wof:placetype":"venue"
},
  "geometry": {"coordinates":[-0.498941,51.389961],"type":"Point"}
}