{
  "type": "Feature",
  "properties": {
    "addr:full":"116 Earlstone Crescent, Cadburyheath Bristol Gloucestershire BS30 8AF",
    "addr:housenumber":"116",
    "addr:postcode":"bs30 8af",
    "addr:street":"Earlstone Crescent Cadburyheath",
    "iso:country":"GB",
    "sg:address":"116 Earlstone Crescent, Cadburyheath",
    "sg:city":"Bristol",
    "sg:classifiers":[
        {
            "category":"Taxi",
            "type":"Transportation"
        }
    ],
    "sg:phone":"+44 117 904 6753",
    "sg:postcode":"BS30 8AF",
    "sg:province":"Gloucestershire",
    "sg:tags":[
        "mini",
        "cab"
    ],
    "wof:name":"Cadburyheath Taxis",
    "wof:placetype":"venue"
},
  "geometry": {"coordinates":[-2.487606,51.443516],"type":"Point"}
}