{
  "type": "Feature",
  "properties": {
    "addr:full":"3 Ryan Business Pk, Sandford Lane Indstl Est Wareham Dorset BH20 4DY",
    "addr:housenumber":"3",
    "addr:postcode":"bh20 4dy",
    "addr:street":"Ryan Business Pk Sandford Lane Indstl Est",
    "iso:country":"GB",
    "sg:address":"3 Ryan Business Pk, Sandford Lane Indstl Est",
    "sg:city":"Wareham",
    "sg:classifiers":[
        {
            "category":"Retail",
            "subcategory":"Repair Shop",
            "type":"Services"
        }
    ],
    "sg:phone":"+44 1929 554898",
    "sg:postcode":"BH20 4DY",
    "sg:province":"Dorset",
    "sg:tags":[
        "upholsterer"
    ],
    "wof:name":"L & M Upholstery",
    "wof:placetype":"venue"
},
  "geometry": {"coordinates":[-2.1081590652,50.6942367554],"type":"Point"}
}