{
  "type": "Feature",
  "properties": {
    "iso:country":"GB",
    "sg:address":"1 The Arcade, Eltham High Street",
    "sg:city":"London",
    "sg:classifiers":[
        {
            "category":"Professional",
            "subcategory":"Art Services",
            "type":"Services"
        }
    ],
    "sg:phone":"+44 20 8850 2228",
    "sg:postcode":"SE9 1BE",
    "sg:province":"Greater London",
    "sg:tags":[
        "photographer"
    ],
    "wof:name":"Eltham One Hour Photos",
    "wof:placetype":"venue"
},
  "geometry": {"coordinates":[0.0584,51.450691],"type":"Point"}
}