{
  "type": "Feature",
  "properties": {
    "iso:country":"GB",
    "sg:address":"Peacock Square, Blenheim Way",
    "sg:city":"Peterborough",
    "sg:classifiers":[
        {
            "category":"Building & Trades",
            "subcategory":"Construction",
            "type":"Services"
        }
    ],
    "sg:postcode":"PE6 8LW",
    "sg:province":"Cambridgeshire",
    "sg:tags":[
        "window",
        "replacement"
    ],
    "wof:name":"S & J Windows",
    "wof:placetype":"venue"
},
  "geometry": {"coordinates":[-0.31632,52.687229],"type":"Point"}
}