{
  "type": "Feature",
  "properties": {
    "iso:country":"GB",
    "sg:address":"Unit C16 Taylors Ct",
    "sg:city":"Rotherham",
    "sg:classifiers":[
        {
            "category":"Retail",
            "subcategory":"Event Space",
            "type":"Services"
        }
    ],
    "sg:postcode":"S62 6NU",
    "sg:province":"South Yorkshire",
    "sg:tags":[
        "pipeline"
    ],
    "wof:name":"Consplit Limited",
    "wof:placetype":"venue"
},
  "geometry": {"coordinates":[-1.346059,53.449783],"type":"Point"}
}