{
  "type": "Feature",
  "properties": {
    "iso:country":"GB",
    "sg:address":"Dyffryn House, Felin Road",
    "sg:city":"Cardigan",
    "sg:classifiers":[
        {
            "category":"Building & Trades",
            "subcategory":"Plumbing",
            "type":"Services"
        }
    ],
    "sg:postcode":"SA43 2ER",
    "sg:province":"Ceredigion",
    "sg:tags":[
        "central",
        "heating"
    ],
    "wof:name":"John Every Plumbing & Heating Engineer",
    "wof:placetype":"venue"
},
  "geometry": {"coordinates":[-4.54496,52.130444],"type":"Point"}
}