{
  "type": "Feature",
  "properties": {
    "iso:country":"GB",
    "sg:address":"Cheltenham Road",
    "sg:city":"Gloucester",
    "sg:classifiers":[
        {
            "category":"Bars & Pubs",
            "type":"Food & Drink"
        }
    ],
    "sg:phone":"+44 1452 412988",
    "sg:postcode":"GL2 0LX",
    "sg:province":"Gloucestershire",
    "sg:tags":[
        "pubs",
        "inn"
    ],
    "wof:name":"The Double Gloucester",
    "wof:placetype":"venue"
},
  "geometry": {"coordinates":[-2.2252221107,51.8702735901],"type":"Point"}
}