{
  "type": "Feature",
  "properties": {
    "iso:country":"GB",
    "sg:address":"14 Broad Street",
    "sg:city":"Lyme Regis",
    "sg:classifiers":[
        {
            "category":"Deli",
            "type":"Food & Drink"
        }
    ],
    "sg:phone":"+44 1297 445008",
    "sg:postcode":"DT7 3QE",
    "sg:province":"Devon",
    "sg:tags":[
        "delicatessen"
    ],
    "wof:name":"Galito's",
    "wof:placetype":"venue"
},
  "geometry": {"coordinates":[-2.934662,50.724609],"type":"Point"}
}