{
  "type": "Feature",
  "properties": {
    "iso:country":"GB",
    "sg:address":"21 High Street",
    "sg:city":"Dalkeith",
    "sg:classifiers":[
        {
            "category":"Health Services",
            "subcategory":"Dentist",
            "type":"Services"
        }
    ],
    "sg:phone":"+44 131 663 2431",
    "sg:postcode":"EH22 1JB",
    "sg:province":"City of Edinburgh",
    "wof:name":"William S Mochrie",
    "wof:placetype":"venue"
},
  "geometry": {"coordinates":[-3.0720748901,55.8936729431],"type":"Point"}
}