{
  "type": "Feature",
  "properties": {
    "iso:country":"GB",
    "sg:address":"5 Hornchurch Road",
    "sg:city":"Plymouth",
    "sg:classifiers":[
        {
            "category":"Shopping",
            "subcategory":"Crafts & Fabrics",
            "type":"Retail Goods"
        }
    ],
    "sg:phone":"+44 1752 362592",
    "sg:postcode":"PL5 2TQ",
    "sg:province":"Devon",
    "sg:tags":[
        "shop",
        "needlecraft",
        "wool"
    ],
    "wof:name":"Colours",
    "wof:placetype":"venue"
},
  "geometry": {"coordinates":[-4.1789031029,50.4186515808],"type":"Point"}
}