{
  "type": "Feature",
  "properties": {
    "addr:full":"70 Hollingdean Terr Brighton East Sussex BN1 7HA",
    "addr:housenumber":"70",
    "addr:postcode":"bn1 7ha",
    "addr:street":"Hollingdean Terr",
    "iso:country":"GB",
    "sg:address":"70 Hollingdean Terr",
    "sg:city":"Brighton",
    "sg:classifiers":[
        {
            "category":"Building & Trades",
            "subcategory":"Construction",
            "type":"Services"
        }
    ],
    "sg:postcode":"BN1 7HA",
    "sg:province":"East Sussex",
    "sg:tags":[
        "glazier"
    ],
    "wof:name":"Pullen,Spencer,",
    "wof:placetype":"venue"
},
  "geometry": {"coordinates":[-0.131174,50.843033],"type":"Point"}
}