{
  "type": "Feature",
  "properties": {
    "addr:full":"113 South Farm Road Worthing West Sussex BN14 7AX",
    "addr:housenumber":"113",
    "addr:postcode":"bn14 7ax",
    "addr:street":"South Farm Road",
    "iso:country":"GB",
    "sg:address":"113 South Farm Road",
    "sg:city":"Worthing",
    "sg:classifiers":[
        {
            "category":"Shopping",
            "subcategory":"Stationery & Office Supplies",
            "type":"Retail Goods"
        }
    ],
    "sg:phone":"+44 1903 214441",
    "sg:postcode":"BN14 7AX",
    "sg:province":"West Sussex",
    "wof:name":"Safeguard Systems Southeast",
    "wof:placetype":"venue"
},
  "geometry": {"coordinates":[-0.379792,50.8242],"type":"Point"}
}