{
  "type": "Feature",
  "properties": {
    "iso:country":"GB",
    "sg:address":"2 Chilham Close",
    "sg:city":"Winsford",
    "sg:classifiers":[
        {
            "category":"Professional",
            "subcategory":"Detective & Security Services",
            "type":"Services"
        }
    ],
    "sg:phone":"+44 1606 551327",
    "sg:postcode":"CW7 1LS",
    "sg:province":"Cheshire",
    "wof:name":"Capitol Sound & Communications",
    "wof:placetype":"venue"
},
  "geometry": {"coordinates":[-2.538728,53.183472],"type":"Point"}
}