{
  "type": "Feature",
  "properties": {
    "addr:full":"27 Cromwell Road Cambridge Cambridgeshire CB1 3EB",
    "addr:housenumber":"27",
    "addr:postcode":"cb1 3eb",
    "addr:street":"Cromwell Road",
    "iso:country":"GB",
    "sg:address":"27 Cromwell Road",
    "sg:city":"Cambridge",
    "sg:classifiers":[
        {
            "category":"Shopping",
            "subcategory":"Clothing, Apparel, & Fashions",
            "type":"Retail Goods"
        },
        {
            "category":"Communications",
            "subcategory":"Film & Video Production",
            "type":"Services"
        }
    ],
    "sg:phone":"+44 1223 518303",
    "sg:postcode":"CB1 3EB",
    "sg:province":"Cambridgeshire",
    "sg:tags":[
        "shop",
        "dress",
        "product",
        "novelty",
        "fancy"
    ],
    "wof:name":"Wardrobe",
    "wof:placetype":"venue"
},
  "geometry": {"coordinates":[0.146492,52.20248],"type":"Point"}
}