{
  "type": "Feature",
  "properties": {
    "iso:country":"GB",
    "sg:address":"62 Edgbaston Street",
    "sg:city":"Birmingham",
    "sg:classifiers":[
        {
            "category":"Cafe",
            "type":"Food & Drink"
        }
    ],
    "sg:phone":"+44 121 622 4093",
    "sg:postcode":"B5 4QL",
    "sg:province":"West Midlands",
    "sg:tags":[
        "tea",
        "room"
    ],
    "wof:name":"Martin's Grill",
    "wof:placetype":"venue"
},
  "geometry": {"coordinates":[-1.8950899839,52.4764556885],"type":"Point"}
}