{
  "type": "Feature",
  "properties": {
    "iso:country":"GB",
    "sg:address":"18 High Street",
    "sg:city":"Hitchin",
    "sg:classifiers":[
        {
            "category":"Autos & Motor Vehicles",
            "subcategory":"Automobile Sales",
            "type":"Retail Goods"
        }
    ],
    "sg:phone":"+44 1438 316177",
    "sg:postcode":"SG4 7LB",
    "sg:province":"Hertfordshire",
    "sg:tags":[
        "car"
    ],
    "wof:name":"Graveley Motor Co",
    "wof:placetype":"venue"
},
  "geometry": {"coordinates":[-0.210364,51.935894],"type":"Point"}
}