{
  "type": "Feature",
  "properties": {
    "iso:country":"GB",
    "sg:address":"138 Downhills Park Road, Tottenham",
    "sg:city":"London",
    "sg:classifiers":[
        {
            "category":"Building & Trades",
            "subcategory":"Equipment Rental",
            "type":"Services"
        }
    ],
    "sg:phone":"+44 20 8881 3572",
    "sg:postcode":"N17 6BP",
    "sg:province":"Greater London",
    "sg:tags":[
        "plant",
        "machinery"
    ],
    "wof:name":"T F Sammon (Plant Hire) Ltd.",
    "wof:placetype":"venue"
},
  "geometry": {"coordinates":[-0.0910670012,51.5909080505],"type":"Point"}
}