{
  "type": "Feature",
  "properties": {
    "addr:full":"210 Caledonian Road London Greater London N1 0SQ",
    "addr:housenumber":"210",
    "addr:postcode":"n1 0sq",
    "addr:street":"Caledonian Road",
    "iso:country":"GB",
    "sg:address":"210 Caledonian Road",
    "sg:city":"London",
    "sg:classifiers":[
        {
            "category":"Autos & Motor Vehicles",
            "subcategory":"Automobile Sales",
            "type":"Retail Goods"
        }
    ],
    "sg:phone":"+44 20 7278 4566",
    "sg:postcode":"N1 0SQ",
    "sg:province":"Greater London",
    "sg:tags":[
        "car"
    ],
    "wof:name":"President Motor Co. Ltd.",
    "wof:placetype":"venue"
},
  "geometry": {"coordinates":[-0.1164420024,51.5368385315],"type":"Point"}
}