{
  "type": "Feature",
  "properties": {
    "addr:full":"3 High St, Llanbradach Caerphilly Caerphilly CF83 3LP",
    "addr:housenumber":"3",
    "addr:postcode":"cf83 3lp",
    "addr:street":"High St",
    "iso:country":"GB",
    "sg:address":"3 High St, Llanbradach",
    "sg:city":"Caerphilly",
    "sg:classifiers":[
        {
            "category":"Wholesale",
            "subcategory":"Toys & Hobbies",
            "type":"Manufacturing & Wholesale Goods"
        }
    ],
    "sg:postcode":"CF83 3LP",
    "sg:province":"Caerphilly",
    "sg:tags":[
        "balloon",
        "novelty"
    ],
    "wof:name":"Partyworld",
    "wof:placetype":"venue"
},
  "geometry": {"coordinates":[-3.230943,51.604233],"type":"Point"}
}