{
  "type": "Feature",
  "properties": {
    "iso:country":"GB",
    "sg:address":"Stanwell Place, Montilo Lane",
    "sg:city":"Rugby",
    "sg:classifiers":[
        {
            "category":"Professional",
            "subcategory":"Computer Services",
            "type":"Services"
        }
    ],
    "sg:phone":"+44 1788 834800",
    "sg:postcode":"CV23 0HE",
    "sg:province":"Northamptonshire",
    "sg:tags":[
        "consultant"
    ],
    "wof:name":"Office Equipment Marketing Ltd.",
    "wof:placetype":"venue"
},
  "geometry": {"coordinates":[-1.28465,52.41909],"type":"Point"}
}