{
  "type": "Feature",
  "properties": {
    "addr:full":"68-69 Kingsway Cleethorpes Lincolnshire DN35 0AB",
    "addr:housenumber":"68-69",
    "addr:postcode":"dn35 0ab",
    "addr:street":"Kingsway",
    "iso:country":"GB",
    "sg:address":"68-69 Kingsway",
    "sg:city":"Cleethorpes",
    "sg:classifiers":[
        {
            "category":"Travel",
            "subcategory":"Hotels & Motels",
            "type":"Entertainment"
        }
    ],
    "sg:postcode":"DN35 0AB",
    "sg:province":"Lincolnshire",
    "wof:name":"Maplethorpe,Mary,",
    "wof:placetype":"venue"
},
  "geometry": {"coordinates":[-0.019819,53.553719],"type":"Point"}
}