{
  "type": "Feature",
  "properties": {
    "iso:country":"GB",
    "sg:address":"1 Brassington Avenue",
    "sg:city":"Sutton Coldfield",
    "sg:classifiers":[
        {
            "category":"Organizations",
            "subcategory":"Non-profit Organization",
            "type":"Services"
        }
    ],
    "sg:phone":"+44 121 321 2277",
    "sg:postcode":"B73 6AA",
    "sg:province":"West Midlands",
    "sg:tags":[
        "organisation",
        "voluntary",
        "charity"
    ],
    "wof:name":"Sutton Coldfield Home Start",
    "wof:placetype":"venue"
},
  "geometry": {"coordinates":[-1.824872,52.563824],"type":"Point"}
}