{
  "type": "Feature",
  "properties": {
    "addr:full":"36a Church Hill Loughton Essex IG10 1LA",
    "addr:housenumber":"36a",
    "addr:postcode":"ig10 1la",
    "addr:street":"Church Hill",
    "iso:country":"GB",
    "sg:address":"36a Church Hill",
    "sg:city":"Loughton",
    "sg:classifiers":[
        {
            "category":"Shopping",
            "subcategory":"Mobile Phones",
            "type":"Retail Goods"
        }
    ],
    "sg:phone":"+44 20 8281 4752",
    "sg:postcode":"IG10 1LA",
    "sg:province":"Essex",
    "wof:name":"A B M Communications",
    "wof:placetype":"venue"
},
  "geometry": {"coordinates":[0.0597990006,51.6517486572],"type":"Point"}
}