{
  "type": "Feature",
  "properties": {
    "addr:full":"Fairends, Cathrine St West, Denton Manchester Greater Manchester M34 3SY",
    "addr:postcode":"m34 3sy",
    "addr:street":"Cathrine St",
    "iso:country":"GB",
    "sg:address":"Fairends, Cathrine St West, Denton",
    "sg:city":"Manchester",
    "sg:classifiers":[
        {
            "category":"Recreation",
            "subcategory":"Amusement Park",
            "type":"Entertainment"
        }
    ],
    "sg:phone":"+44 161 336 9875",
    "sg:postcode":"M34 3SY",
    "sg:province":"Greater Manchester",
    "sg:tags":[
        "arcade"
    ],
    "wof:name":"John Walter Shaw",
    "wof:placetype":"venue"
},
  "geometry": {"coordinates":[-2.129274,53.455811],"type":"Point"}
}