{
  "type": "Feature",
  "properties": {
    "addr:full":"Evenlode Avenue Penarth The Vale of Glamorgan CF64 3PD",
    "addr:postcode":"cf64 3pd",
    "addr:street":"Evenlode Avenue;Vale",
    "iso:country":"GB",
    "sg:address":"Evenlode Avenue",
    "sg:city":"Penarth",
    "sg:classifiers":[
        {
            "category":"Education",
            "subcategory":"School",
            "type":"Public Place"
        },
        {
            "category":"Government",
            "subcategory":"Office",
            "type":"Public Place"
        }
    ],
    "sg:phone":"+44 29 2070 2168",
    "sg:postcode":"CF64 3PD",
    "sg:province":"The Vale of Glamorgan",
    "sg:tags":[
        "local",
        "authority"
    ],
    "wof:name":"Evenlode Primary School",
    "wof:placetype":"venue"
},
  "geometry": {"coordinates":[-3.181667,51.429852],"type":"Point"}
}