{
  "type": "Feature",
  "properties": {
    "addr:full":"Park Road, Holmwood Industrial Park Chesterfield Derbyshire S42 5UY",
    "addr:postcode":"s42 5uy",
    "addr:street":"Park Road",
    "iso:country":"GB",
    "sg:address":"Park Road, Holmwood Industrial Park",
    "sg:city":"Chesterfield",
    "sg:classifiers":[
        {
            "category":"Train Station",
            "subcategory":"Rail",
            "type":"Transportation"
        },
        {
            "category":"Retail",
            "subcategory":"Auto Repair",
            "type":"Services"
        }
    ],
    "sg:phone":"+44 1246 856685",
    "sg:postcode":"S42 5UY",
    "sg:province":"Derbyshire",
    "sg:tags":[
        "caravan",
        "bodybuilder",
        "repairer"
    ],
    "wof:name":"Central Truck Bodies Ltd.",
    "wof:placetype":"venue"
},
  "geometry": {"coordinates":[-1.355463,53.192085],"type":"Point"}
}