{
  "type": "Feature",
  "properties": {
    "addr:full":"Charles Darwin Shopping Centre, Castle St Shrewsbury Shropshire SY1 2BD",
    "addr:postcode":"sy1 2bd",
    "addr:street":"Castle St",
    "iso:country":"GB",
    "sg:address":"Charles Darwin Shopping Centre, Castle St",
    "sg:city":"Shrewsbury",
    "sg:classifiers":[
        {
            "category":"Shopping",
            "subcategory":"Catalog Store",
            "type":"Retail Goods"
        }
    ],
    "sg:phone":"+44 1743 272417",
    "sg:postcode":"SY1 2BD",
    "sg:province":"Shropshire",
    "sg:tags":[
        "catalogue",
        "showroom"
    ],
    "wof:name":"Index The Catalogue Shop",
    "wof:placetype":"venue"
},
  "geometry": {"coordinates":[-2.751283884,52.7065658569],"type":"Point"}
}