{
  "type": "Feature",
  "properties": {
    "addr:full":"Keith Ho, 2 Redheughs Rigg Edinburgh City of Edinburgh EH12 9DQ",
    "addr:housenumber":"2",
    "addr:postcode":"eh12 9dq",
    "addr:street":"Redheughs Rigg",
    "iso:country":"GB",
    "sg:address":"Keith Ho, 2 Redheughs Rigg",
    "sg:city":"Edinburgh",
    "sg:classifiers":[
        {
            "category":"Banks & Credit Unions",
            "subcategory":"Bank",
            "type":"Services"
        }
    ],
    "sg:postcode":"EH12 9DQ",
    "sg:province":"City of Edinburgh",
    "wof:name":"Halifax Plc",
    "wof:placetype":"venue"
},
  "geometry": {"coordinates":[-3.3615040779,55.944644928],"type":"Point"}
}