{
  "type": "Feature",
  "properties": {
    "addr:full":"North Barn Skipton Lancashire BD23 3AE",
    "addr:postcode":"bd23 3ae",
    "addr:street":"North Barn",
    "iso:country":"GB",
    "sg:address":"North Barn",
    "sg:city":"Skipton",
    "sg:classifiers":[
        {
            "category":"Professional",
            "subcategory":"Accounting & Tax Preparation",
            "type":"Services"
        }
    ],
    "sg:postcode":"BD23 3AE",
    "sg:province":"Lancashire",
    "sg:tags":[
        "accountant"
    ],
    "wof:name":"Pearson & Associates",
    "wof:placetype":"venue"
},
  "geometry": {"coordinates":[-2.104432106,53.9846916199],"type":"Point"}
}