{
  "type": "Feature",
  "properties": {
    "addr:full":"41 The Cliff Brighton East Sussex BN2 5RF",
    "addr:housenumber":"41",
    "addr:postcode":"bn2 5rf",
    "addr:street":"The Cliff",
    "iso:country":"GB",
    "sg:address":"41 The Cliff",
    "sg:city":"Brighton",
    "sg:classifiers":[
        {
            "category":"Health Services",
            "subcategory":"Health Practitioner",
            "type":"Services"
        }
    ],
    "sg:postcode":"BN2 5RF",
    "sg:province":"East Sussex",
    "sg:tags":[
        "psychotherapist"
    ],
    "wof:name":"P M Vallely",
    "wof:placetype":"venue"
},
  "geometry": {"coordinates":[-0.09823,50.815292],"type":"Point"}
}