{
  "type": "Feature",
  "properties": {
    "addr:full":"34 Main Street, Kirby Muxloe Leicester Leicestershire LE9 2AL",
    "addr:housenumber":"34",
    "addr:postcode":"le9 2al",
    "addr:street":"Main Street",
    "iso:country":"GB",
    "sg:address":"34 Main Street, Kirby Muxloe",
    "sg:city":"Leicester",
    "sg:classifiers":[
        {
            "category":"Government",
            "subcategory":"Post Office",
            "type":"Public Place"
        }
    ],
    "sg:postcode":"LE9 2AL",
    "sg:province":"Leicestershire",
    "wof:name":"Malcolm David Peck",
    "wof:placetype":"venue"
},
  "geometry": {"coordinates":[-1.233882,52.635479],"type":"Point"}
}