{
  "type": "Feature",
  "properties": {
    "addr:full":"31 Downside Crescent London Greater London NW3 2AN",
    "addr:housenumber":"31",
    "addr:postcode":"nw3 2an",
    "addr:street":"Downside Crescent",
    "iso:country":"GB",
    "sg:address":"31 Downside Crescent",
    "sg:city":"London",
    "sg:classifiers":[
        {
            "category":"Communications",
            "subcategory":"Film & Video Production",
            "type":"Services"
        }
    ],
    "sg:phone":"+44 20 7794 3824",
    "sg:postcode":"NW3 2AN",
    "sg:province":"Greater London",
    "sg:tags":[
        "tv",
        "studio"
    ],
    "wof:name":"Upside Films",
    "wof:placetype":"venue"
},
  "geometry": {"coordinates":[-0.1624439955,51.5511741638],"type":"Point"}
}