{
  "type": "Feature",
  "properties": {
    "iso:country":"GB",
    "sg:address":"29 Ogden La, Denholme",
    "sg:city":"Bradford",
    "sg:classifiers":[
        {
            "category":"Retail",
            "subcategory":"Auto Repair",
            "type":"Services"
        }
    ],
    "sg:postcode":"BD13 4LA",
    "sg:province":"West Yorkshire",
    "sg:tags":[
        "modification",
        "garage"
    ],
    "wof:name":"Huby,Richard,",
    "wof:placetype":"venue"
},
  "geometry": {"coordinates":[-1.8981050253,53.8067474365],"type":"Point"}
}