{
  "type": "Feature",
  "properties": {
    "addr:full":"98 Upper Wickham Lane Welling Kent DA16 3HQ",
    "addr:housenumber":"98",
    "addr:postcode":"da16 3hq",
    "addr:street":"Upper Wickham Lane",
    "iso:country":"GB",
    "sg:address":"98 Upper Wickham Lane",
    "sg:city":"Welling",
    "sg:classifiers":[
        {
            "category":"Shopping",
            "subcategory":"News",
            "type":"Retail Goods"
        }
    ],
    "sg:phone":"+44 20 8854 6534",
    "sg:postcode":"DA16 3HQ",
    "sg:province":"Kent",
    "sg:tags":[
        "newsagent"
    ],
    "wof:name":"The Welling News Box",
    "wof:placetype":"venue"
},
  "geometry": {"coordinates":[0.1101220027,51.4662284851],"type":"Point"}
}