{
  "type": "Feature",
  "properties": {
    "addr:full":"Brooks Lane Middlewich Cheshire CW10 0JG",
    "addr:postcode":"cw10 0jg",
    "addr:street":"Brooks Lane",
    "iso:country":"GB",
    "sg:address":"Brooks Lane",
    "sg:city":"Middlewich",
    "sg:classifiers":[
        {
            "category":"Sports & Exercise",
            "subcategory":"Gym",
            "type":"Entertainment"
        }
    ],
    "sg:phone":"+44 1606 737407",
    "sg:postcode":"CW10 0JG",
    "sg:province":"Cheshire",
    "sg:tags":[
        "club",
        "fitness",
        "health",
        "centre"
    ],
    "wof:name":"Unique Fitness Gym",
    "wof:placetype":"venue"
},
  "geometry": {"coordinates":[-2.439489,53.191139],"type":"Point"}
}