{
  "type": "Feature",
  "properties": {
    "iso:country":"GB",
    "sg:address":"91 St Neots Road",
    "sg:city":"Sandy",
    "sg:classifiers":[
        {
            "category":"Professional",
            "subcategory":"Computer Services",
            "type":"Services"
        }
    ],
    "sg:phone":"+44 1767 680433",
    "sg:postcode":"SG19 1BP",
    "sg:province":"Bedfordshire",
    "sg:tags":[
        "system",
        "software"
    ],
    "wof:name":"Hazco Ltd.",
    "wof:placetype":"venue"
},
  "geometry": {"coordinates":[-0.29555,52.134426],"type":"Point"}
}