{
  "type": "Feature",
  "properties": {
    "addr:full":"32 Creffield Rd London Greater London W5 3RP",
    "addr:housenumber":"32",
    "addr:postcode":"w5 3rp",
    "addr:street":"Creffield Rd",
    "iso:country":"GB",
    "sg:address":"32 Creffield Rd",
    "sg:city":"London",
    "sg:classifiers":[
        {
            "category":"Travel",
            "subcategory":"Hotels & Motels",
            "type":"Entertainment"
        }
    ],
    "sg:postcode":"W5 3RP",
    "sg:province":"Greater London",
    "sg:tags":[
        "house",
        "guest"
    ],
    "wof:name":"Vera Guest House",
    "wof:placetype":"venue"
},
  "geometry": {"coordinates":[-0.287187,51.511917],"type":"Point"}
}