{
  "type": "Feature",
  "properties": {
    "iso:country":"GB",
    "sg:address":"8 High Street, Earith",
    "sg:city":"Huntingdon",
    "sg:classifiers":[
        {
            "category":"Government",
            "subcategory":"Post Office",
            "type":"Public Place"
        },
        {
            "category":"Food & Beverages",
            "subcategory":"Groceries & Convenience Stores",
            "type":"Retail Goods"
        }
    ],
    "sg:phone":"+44 1487 841409",
    "sg:postcode":"PE28 3PP",
    "sg:province":"Bedfordshire",
    "wof:name":"EARITH POST OFFICE & BRIDGE END STORES",
    "wof:placetype":"venue"
},
  "geometry": {"coordinates":[0.006386,52.351585],"type":"Point"}
}