{
  "type": "Feature",
  "properties": {
    "addr:full":"60 Lower Market Street, Farnworth Bolton Lancashire BL4 7NY",
    "addr:housenumber":"60",
    "addr:postcode":"bl4 7ny",
    "addr:street":"Lower Market Street",
    "iso:country":"GB",
    "sg:address":"60 Lower Market Street, Farnworth",
    "sg:city":"Bolton",
    "sg:classifiers":[
        {
            "category":"Personal",
            "subcategory":"Beauty Salon",
            "type":"Services"
        }
    ],
    "sg:postcode":"BL4 7NY",
    "sg:province":"Lancashire",
    "sg:tags":[
        "unisex",
        "hairdresser"
    ],
    "wof:name":"Skin-Versus-Age",
    "wof:placetype":"venue"
},
  "geometry": {"coordinates":[-2.395162,53.549973],"type":"Point"}
}