{
  "type": "Feature",
  "properties": {
    "addr:full":"Fairfield Garage, Rawfield Lane, Fairburn Knottingley North Yorkshire WF11 9LB",
    "addr:postcode":"wf11 9lb",
    "addr:street":"Rawfield Lane",
    "iso:country":"GB",
    "sg:address":"Fairfield Garage, Rawfield Lane, Fairburn",
    "sg:city":"Knottingley",
    "sg:classifiers":[
        {
            "category":"Building & Trades",
            "subcategory":"Construction",
            "type":"Services"
        }
    ],
    "sg:phone":"+44 1977 672105",
    "sg:postcode":"WF11 9LB",
    "sg:province":"North Yorkshire",
    "sg:tags":[
        "builder"
    ],
    "wof:name":"Fairfield Homes & Construction Ltd.",
    "wof:placetype":"venue"
},
  "geometry": {"coordinates":[-1.2855110168,53.7437705994],"type":"Point"}
}