{
  "type": "Feature",
  "properties": {
    "iso:country":"GB",
    "sg:address":"23 Tithe Barn Road, Wootton",
    "sg:city":"Bedford",
    "sg:classifiers":[
        {
            "category":"Building & Trades",
            "subcategory":"Landscaping Services",
            "type":"Services"
        }
    ],
    "sg:postcode":"MK43 9EY",
    "sg:province":"Bedfordshire",
    "sg:tags":[
        "landscape",
        "contractor"
    ],
    "wof:name":"B W Richardson Landscapes",
    "wof:placetype":"venue"
},
  "geometry": {"coordinates":[-0.5331040025,52.0958518982],"type":"Point"}
}