{
  "type": "Feature",
  "properties": {
    "addr:full":"307 Studio, 11 Building, Clarendon Rd, Wood Green Wood Green Greater London N22 6XJ",
    "addr:housenumber":"307;11 building",
    "addr:postcode":"n22 6xj",
    "addr:street":"Clarendon Rd",
    "iso:country":"GB",
    "sg:address":"307 Studio, 11 Building, Clarendon Rd, Wood Green",
    "sg:city":"Wood Green",
    "sg:classifiers":[
        {
            "category":"Home & Garden",
            "subcategory":"Home Furnishings",
            "type":"Retail Goods"
        }
    ],
    "sg:phone":"+44 20 8881 1711",
    "sg:postcode":"N22 6XJ",
    "sg:province":"Greater London",
    "sg:tags":[
        "homefurnishings"
    ],
    "wof:name":"Daniel Hacker",
    "wof:placetype":"venue"
},
  "geometry": {"coordinates":[-0.1082430035,51.5942077637],"type":"Point"}
}