{
  "type": "Feature",
  "properties": {
    "addr:full":"30 Rutland Square Edinburgh City of Edinburgh EH1 2BW",
    "addr:housenumber":"30",
    "addr:postcode":"eh1 2bw",
    "addr:street":"Rutland Square",
    "iso:country":"GB",
    "sg:address":"30 Rutland Square",
    "sg:city":"Edinburgh",
    "sg:classifiers":[
        {
            "category":"Real Estate",
            "subcategory":"Surveying",
            "type":"Services"
        }
    ],
    "sg:phone":"+44 131 229 5587",
    "sg:postcode":"EH1 2BW",
    "sg:province":"City of Edinburgh",
    "sg:tags":[
        "surveyor",
        "quantity"
    ],
    "wof:name":"Ross & Morton",
    "wof:placetype":"venue"
},
  "geometry": {"coordinates":[-3.20926404,55.9490127563],"type":"Point"}
}