{
  "type": "Feature",
  "properties": {
    "iso:country":"GB",
    "sg:address":"41 Lexham Green Clo",
    "sg:city":"Buckley",
    "sg:classifiers":[
        {
            "category":"Building & Trades",
            "subcategory":"Plumbing",
            "type":"Services"
        }
    ],
    "sg:phone":"+44 1244 550958",
    "sg:postcode":"CH7 2HS",
    "sg:province":"Denbighshire",
    "sg:tags":[
        "heating"
    ],
    "wof:name":"Mac Williams",
    "wof:placetype":"venue"
},
  "geometry": {"coordinates":[-3.074194,53.167431],"type":"Point"}
}