{
  "type": "Feature",
  "properties": {
    "addr:full":"16 Wood Street Ashton Under Lyne Greater Manchester OL6 6AT",
    "addr:housenumber":"16",
    "addr:postcode":"ol6 6at",
    "addr:street":"Wood Street;Under Lyne",
    "iso:country":"GB",
    "sg:address":"16 Wood Street",
    "sg:city":"Ashton Under Lyne",
    "sg:classifiers":[
        {
            "category":"Personal",
            "subcategory":"Beauty Salon",
            "type":"Services"
        },
        {
            "category":"Personal",
            "subcategory":"Barber",
            "type":"Services"
        }
    ],
    "sg:phone":"+44 161 343 4654",
    "sg:postcode":"OL6 6AT",
    "sg:province":"Greater Manchester",
    "sg:tags":[
        "unisex",
        "hairdresser"
    ],
    "wof:name":"The Chopping Block",
    "wof:placetype":"venue"
},
  "geometry": {"coordinates":[-2.0920639038,53.4881057739],"type":"Point"}
}