{
  "type": "Feature",
  "properties": {
    "addr:full":"60 New Road Chippenham Wiltshire SN15 1ES",
    "addr:housenumber":"60",
    "addr:postcode":"sn15 1es",
    "addr:street":"New Road",
    "iso:country":"GB",
    "sg:address":"60 New Road",
    "sg:city":"Chippenham",
    "sg:classifiers":[
        {
            "category":"Professional",
            "subcategory":"Printing & Photocopies",
            "type":"Services"
        }
    ],
    "sg:phone":"+44 1249 654016",
    "sg:postcode":"SN15 1ES",
    "sg:province":"Wiltshire",
    "sg:tags":[
        "embroiderer"
    ],
    "wof:name":"Smart Alec Ltd.",
    "wof:placetype":"venue"
},
  "geometry": {"coordinates":[-2.118423,51.460571],"type":"Point"}
}