{
  "type": "Feature",
  "properties": {
    "iso:country":"GB",
    "sg:address":"The New Boathouse, Mill Lane",
    "sg:city":"Maidenhead",
    "sg:classifiers":[
        {
            "category":"Manufacturing",
            "subcategory":"Tools & Machinery",
            "type":"Manufacturing & Wholesale Goods"
        }
    ],
    "sg:phone":"+44 1628 780011",
    "sg:postcode":"SL6 0AA",
    "sg:province":"Berkshire",
    "sg:tags":[
        "society",
        "friendly"
    ],
    "wof:name":"Vision Vehicle Hire Ltd.",
    "wof:placetype":"venue"
},
  "geometry": {"coordinates":[-0.727257,51.522373],"type":"Point"}
}