{
  "type": "Feature",
  "properties": {
    "addr:full":"51 John Street Rowley Regis West Midlands B65 0EP",
    "addr:housenumber":"51",
    "addr:postcode":"b65 0ep",
    "addr:street":"John Street",
    "iso:country":"GB",
    "sg:address":"51 John Street",
    "sg:city":"Rowley Regis",
    "sg:classifiers":[
        {
            "category":"Organizations",
            "subcategory":"Community Association",
            "type":"Services"
        },
        {
            "category":"Organizations",
            "subcategory":"Membership Organization",
            "type":"Services"
        }
    ],
    "sg:phone":"+44 121 559 1769",
    "sg:postcode":"B65 0EP",
    "sg:province":"West Midlands",
    "sg:tags":[
        "club",
        "social"
    ],
    "wof:name":"Blackheath & District Liberal Club",
    "wof:placetype":"venue"
},
  "geometry": {"coordinates":[-2.0441589355,52.474319458],"type":"Point"}
}