{
  "type": "Feature",
  "properties": {
    "iso:country":"GB",
    "sg:address":"Blackfen Road",
    "sg:city":"Sidcup",
    "sg:classifiers":[
        {
            "category":"Farming",
            "subcategory":"Nursery",
            "type":"Manufacturing & Wholesale Goods"
        }
    ],
    "sg:phone":"+44 20 8301 2636",
    "sg:postcode":"DA15 9NU",
    "sg:province":"Kent",
    "sg:tags":[
        "creche"
    ],
    "wof:name":"Chatterbox Day Nursery",
    "wof:placetype":"venue"
},
  "geometry": {"coordinates":[0.104135,51.450436],"type":"Point"}
}