{
  "type": "Feature",
  "properties": {
    "addr:full":"56 Langer Lane Chesterfield Derbyshire S40 2JG",
    "addr:postcode":"s40 2jg",
    "addr:street":"Langer Lane",
    "iso:country":"GB",
    "sg:address":"56 Langer Lane",
    "sg:city":"Chesterfield",
    "sg:classifiers":[
        {
            "category":"Retail",
            "subcategory":"Repair Shop",
            "type":"Services"
        }
    ],
    "sg:phone":"+44 1246 204257",
    "sg:postcode":"S40 2JG",
    "sg:province":"Derbyshire",
    "sg:tags":[
        "maintenance"
    ],
    "wof:name":"K Thompson Builders",
    "wof:placetype":"venue"
},
  "geometry": {"coordinates":[-1.4318139553,53.2164726257],"type":"Point"}
}