{
  "type": "Feature",
  "properties": {
    "iso:country":"GB",
    "sg:address":"16 Sunnyhill Road",
    "sg:city":"Herne Bay",
    "sg:classifiers":[
        {
            "category":"Shopping",
            "subcategory":"Pharmacy",
            "type":"Retail Goods"
        }
    ],
    "sg:postcode":"CT6 8LT",
    "sg:province":"Kent",
    "sg:tags":[
        "medicine",
        "therapy"
    ],
    "wof:name":"Sandra Kemp Shiatsu",
    "wof:placetype":"venue"
},
  "geometry": {"coordinates":[1.1019419432,51.3652305603],"type":"Point"}
}