{
  "type": "Feature",
  "properties": {
    "iso:country":"GB",
    "sg:address":"Sheriff Court Ho",
    "sg:city":"Forfar",
    "sg:classifiers":[
        {
            "category":"Government",
            "subcategory":"Court House",
            "type":"Public Place"
        }
    ],
    "sg:phone":"+44 1307 463296",
    "sg:postcode":"DD8 3LA",
    "sg:province":"Angus",
    "wof:name":"Procurator Fiscal",
    "wof:placetype":"venue"
},
  "geometry": {"coordinates":[-2.889001,56.648251],"type":"Point"}
}