{
  "type": "Feature",
  "properties": {
    "iso:country":"GB",
    "sg:address":"108 Nags Head Hill",
    "sg:city":"Bristol",
    "sg:classifiers":[
        {
            "category":"Food & Beverages",
            "subcategory":"Meat & Fish",
            "type":"Retail Goods"
        }
    ],
    "sg:phone":"+44 117 967 6246",
    "sg:postcode":"BS5 8QP",
    "sg:province":"City of Bristol",
    "sg:tags":[
        "chip"
    ],
    "wof:name":"Hill Top Fish Bar",
    "wof:placetype":"venue"
},
  "geometry": {"coordinates":[-2.527178,51.454739],"type":"Point"}
}