{
  "type": "Feature",
  "properties": {
    "addr:full":"8 St Mark Street London Greater London E1 8DJ",
    "addr:housenumber":"8",
    "addr:postcode":"e1 8dj",
    "addr:street":"St Mark Street",
    "iso:country":"GB",
    "sg:address":"8 St Mark Street",
    "sg:city":"London",
    "sg:classifiers":[
        {
            "category":"Food & Beverages",
            "subcategory":"Candy",
            "type":"Retail Goods"
        }
    ],
    "sg:phone":"+44 20 7702 4266",
    "sg:postcode":"E1 8DJ",
    "sg:province":"Greater London",
    "sg:tags":[
        "confectioner"
    ],
    "wof:name":"Rehena Food Store",
    "wof:placetype":"venue"
},
  "geometry": {"coordinates":[-0.0710949972,51.5131492615],"type":"Point"}
}