{
  "type": "Feature",
  "properties": {
    "addr:full":"23 High Street Penicuik Midlothian EH26 8HS",
    "addr:housenumber":"23",
    "addr:postcode":"eh26 8hs",
    "addr:street":"High Street",
    "iso:country":"GB",
    "sg:address":"23 High Street",
    "sg:city":"Penicuik",
    "sg:classifiers":[
        {
            "category":"Home & Garden",
            "subcategory":"Hardware",
            "type":"Retail Goods"
        },
        {
            "category":"Personal",
            "subcategory":"Skin Care",
            "type":"Services"
        }
    ],
    "sg:phone":"+44 1968 670455",
    "sg:postcode":"EH26 8HS",
    "sg:province":"Midlothian",
    "sg:tags":[
        "part",
        "motorcycle",
        "manufacturer",
        "accessory"
    ],
    "wof:name":"Ecosse Motocross Ltd.",
    "wof:placetype":"venue"
},
  "geometry": {"coordinates":[-3.220005,55.826786],"type":"Point"}
}