{
  "type": "Feature",
  "properties": {
    "iso:country":"GB",
    "sg:address":"Unit 4a, Birkdale Avenue, Selly Oak",
    "sg:city":"Birmingham",
    "sg:classifiers":[
        {
            "category":"Food & Beverages",
            "subcategory":"Liquor & Beverages",
            "type":"Retail Goods"
        }
    ],
    "sg:phone":"+44 121 415 4145",
    "sg:postcode":"B29 6UA",
    "sg:province":"West Midlands",
    "sg:tags":[
        "drink",
        "soft"
    ],
    "wof:name":"Swallow (Soft Drinks  Beer & Cider Wholesalers) Ltd.",
    "wof:placetype":"venue"
},
  "geometry": {"coordinates":[-1.9317589998,52.4386901855],"type":"Point"}
}