{
  "type": "Feature",
  "properties": {
    "iso:country":"GB",
    "sg:address":"Unit 10 Underwood Business Park, Underwood Lane",
    "sg:city":"Crewe",
    "sg:classifiers":[
        {
            "category":"Taxi",
            "type":"Transportation"
        }
    ],
    "sg:phone":"+44 1270 254595",
    "sg:postcode":"CW1 3TJ",
    "sg:province":"Cheshire",
    "sg:tags":[
        "mini",
        "cab"
    ],
    "wof:name":"A to B R Uss Private Hire",
    "wof:placetype":"venue"
},
  "geometry": {"coordinates":[-2.446105,53.100578],"type":"Point"}
}