{
  "type": "Feature",
  "properties": {
    "iso:country":"GB",
    "sg:address":"Typrydd, Glasbury On Wye",
    "sg:city":"Hereford",
    "sg:classifiers":[
        {
            "category":"Professional",
            "type":"Services"
        }
    ],
    "sg:phone":"+44 1497 847802",
    "sg:postcode":"HR3 5NT",
    "sg:province":"Herefordshire",
    "sg:tags":[
        "entertainer"
    ],
    "wof:name":"H.S.W Entertainments",
    "wof:placetype":"venue"
},
  "geometry": {"coordinates":[-3.19675,52.043961],"type":"Point"}
}