{
  "type": "Feature",
  "properties": {
    "addr:full":"North End Buckhurst Hill Essex IG9 5QY",
    "addr:postcode":"ig9 5qy",
    "addr:street":"North End",
    "iso:country":"GB",
    "sg:address":"North End",
    "sg:city":"Buckhurst Hill",
    "sg:classifiers":[
        {
            "category":"Travel",
            "subcategory":"Hotels & Motels",
            "type":"Entertainment"
        }
    ],
    "sg:phone":"+44 20 8505 4636",
    "sg:postcode":"IG9 5QY",
    "sg:province":"Essex",
    "wof:name":"Roebuck Hotel",
    "wof:placetype":"venue"
},
  "geometry": {"coordinates":[0.0389119983,51.6331634521],"type":"Point"}
}