{
  "type": "Feature",
  "properties": {
    "addr:full":"31 Eastern Road Sutton Coldfield West Midlands B73 5PA",
    "addr:housenumber":"31",
    "addr:postcode":"b73 5pa",
    "addr:street":"Eastern Road",
    "iso:country":"GB",
    "sg:address":"31 Eastern Road",
    "sg:city":"Sutton Coldfield",
    "sg:classifiers":[
        {
            "category":"Building & Trades",
            "subcategory":"Plumbing",
            "type":"Services"
        }
    ],
    "sg:postcode":"B73 5PA",
    "sg:province":"West Midlands",
    "sg:tags":[
        "central",
        "heating"
    ],
    "wof:name":"R E Heating",
    "wof:placetype":"venue"
},
  "geometry": {"coordinates":[-1.8305219412,52.5478096008],"type":"Point"}
}