{
  "type": "Feature",
  "properties": {
    "addr:full":"4-5 Dorset Street Sevenoaks Kent TN13 1LN",
    "addr:housenumber":"4-5",
    "addr:postcode":"tn13 1ln",
    "addr:street":"Dorset Street",
    "iso:country":"GB",
    "sg:address":"4-5 Dorset Street",
    "sg:city":"Sevenoaks",
    "sg:classifiers":[
        {
            "category":"Travel",
            "subcategory":"Travel Agent",
            "type":"Entertainment"
        }
    ],
    "sg:phone":"+44 1732 458255",
    "sg:postcode":"TN13 1LN",
    "sg:province":"Kent",
    "wof:name":"Sevenoaks Travel Ltd.",
    "wof:placetype":"venue"
},
  "geometry": {"coordinates":[0.1920219958,51.2706413269],"type":"Point"}
}