{
  "type": "Feature",
  "properties": {
    "addr:full":"166 Dunstable Road Luton Bedfordshire LU1 1EW",
    "addr:housenumber":"166",
    "addr:postcode":"lu1 1ew",
    "addr:street":"Dunstable Road",
    "iso:country":"GB",
    "sg:address":"166 Dunstable Road",
    "sg:city":"Luton",
    "sg:classifiers":[
        {
            "category":"Food & Beverages",
            "subcategory":"Fruits & Vegetables",
            "type":"Retail Goods"
        },
        {
            "category":"Food & Beverages",
            "subcategory":"Supermarket",
            "type":"Retail Goods"
        },
        {
            "category":"Food & Beverages",
            "subcategory":"Groceries & Convenience Stores",
            "type":"Retail Goods"
        }
    ],
    "sg:phone":"+44 1582 737268",
    "sg:postcode":"LU1 1EW",
    "sg:province":"Bedfordshire",
    "sg:tags":[
        "grocer",
        "greengrocer"
    ],
    "wof:name":"Bangla Bazaar",
    "wof:placetype":"venue"
},
  "geometry": {"coordinates":[-0.4294849932,51.8862609863],"type":"Point"}
}