{
  "type": "Feature",
  "properties": {
    "addr:full":"Unit 1 Lancaster Road Shrewsbury Shropshire SY1 3LG",
    "addr:housenumber":"unit 1",
    "addr:postcode":"sy1 3lg",
    "addr:street":"Lancaster Road",
    "iso:country":"GB",
    "sg:address":"Unit 1 Lancaster Road",
    "sg:city":"Shrewsbury",
    "sg:classifiers":[
        {
            "category":"Organizations",
            "subcategory":"Non-profit Organization",
            "type":"Services"
        }
    ],
    "sg:phone":"+44 1743 450270",
    "sg:postcode":"SY1 3LG",
    "sg:province":"Shropshire",
    "sg:tags":[
        "organisation",
        "voluntary",
        "charity"
    ],
    "wof:name":"Shrewsbury Community Transport Initiative Ltd.",
    "wof:placetype":"venue"
},
  "geometry": {"coordinates":[-2.731524,52.738377],"type":"Point"}
}