{
  "type": "Feature",
  "properties": {
    "iso:country":"GB",
    "sg:address":"Woodhouse Farm, Old Road, Leconfield",
    "sg:city":"Beverley",
    "sg:classifiers":[
        {
            "category":"Farming",
            "subcategory":"Farm",
            "type":"Manufacturing & Wholesale Goods"
        }
    ],
    "sg:postcode":"HU17 7NJ",
    "sg:province":"East Riding of Yorkshire",
    "sg:tags":[
        "mixed",
        "crop"
    ],
    "wof:name":"H Lount & Sons",
    "wof:placetype":"venue"
},
  "geometry": {"coordinates":[-0.4592890143,53.8782958984],"type":"Point"}
}