{
  "type": "Feature",
  "properties": {
    "iso:country":"GB",
    "sg:address":"117 North Road, Kirkburton",
    "sg:city":"Huddersfield",
    "sg:classifiers":[
        {
            "category":"Home & Garden",
            "subcategory":"Building Materials",
            "type":"Retail Goods"
        },
        {
            "category":"Building & Trades",
            "subcategory":"Construction",
            "type":"Services"
        }
    ],
    "sg:postcode":"HD8 0RN",
    "sg:province":"South Yorkshire",
    "sg:tags":[
        "fencing",
        "builder"
    ],
    "wof:name":"Robinson Fencing",
    "wof:placetype":"venue"
},
  "geometry": {"coordinates":[-1.703073,53.611618],"type":"Point"}
}