{
  "type": "Feature",
  "properties": {
    "iso:country":"GB",
    "sg:address":"8 Blagrove Drive",
    "sg:city":"Wokingham",
    "sg:classifiers":[
        {
            "category":"Professional",
            "subcategory":"Management & Consulting",
            "type":"Services"
        }
    ],
    "sg:phone":"+44 118 979 2533",
    "sg:postcode":"RG41 4BB",
    "sg:province":"Berkshire",
    "sg:tags":[
        "consultant",
        "business"
    ],
    "wof:name":"Q B S Associates",
    "wof:placetype":"venue"
},
  "geometry": {"coordinates":[-0.8524739742,51.4020881653],"type":"Point"}
}