{
  "type": "Feature",
  "properties": {
    "addr:full":"1618-1620 Coventry Road, Yardley Birmingham West Midlands B26 1AL",
    "addr:housenumber":"1618-1620",
    "addr:postcode":"b26 1al",
    "addr:street":"Coventry Road",
    "iso:country":"GB",
    "sg:address":"1618-1620 Coventry Road, Yardley",
    "sg:city":"Birmingham",
    "sg:classifiers":[
        {
            "category":"Professional",
            "subcategory":"Lawyer & Legal Services",
            "type":"Services"
        }
    ],
    "sg:phone":"+44 121 707 9211",
    "sg:postcode":"B26 1AL",
    "sg:province":"West Midlands",
    "sg:tags":[
        "solicitor"
    ],
    "wof:name":"Prior Cumberlidge & Pugh",
    "wof:placetype":"venue"
},
  "geometry": {"coordinates":[-1.8107119799,52.4619674683],"type":"Point"}
}