{
  "type": "Feature",
  "properties": {
    "addr:full":"The Saltings, Marsh La Flint Flintshire CH6 5PJ",
    "addr:postcode":"ch6 5pj",
    "addr:street":"Marsh;Flint",
    "iso:country":"GB",
    "sg:address":"The Saltings, Marsh La",
    "sg:city":"Flint",
    "sg:classifiers":[
        {
            "category":"Building & Trades",
            "subcategory":"Construction",
            "type":"Services"
        }
    ],
    "sg:phone":"+44 1352 732775",
    "sg:postcode":"CH6 5PJ",
    "sg:province":"Flintshire",
    "sg:tags":[
        "bricklaying"
    ],
    "wof:name":"Edward Bevan",
    "wof:placetype":"venue"
},
  "geometry": {"coordinates":[-3.129534,53.247379],"type":"Point"}
}