{
  "type": "Feature",
  "properties": {
    "addr:full":", Little Linford Milton Keynes Buckinghamshire MK19 7EB",
    "addr:postcode":"mk19 7eb",
    "addr:street":"Little Linford",
    "iso:country":"GB",
    "sg:address":", Little Linford",
    "sg:city":"Milton Keynes",
    "sg:classifiers":[
        {
            "category":"Freight",
            "type":"Transportation"
        }
    ],
    "sg:phone":"+44 1908 615070",
    "sg:postcode":"MK19 7EB",
    "sg:province":"Buckinghamshire",
    "sg:tags":[
        "haulage",
        "road"
    ],
    "wof:name":"Equipment Exchange",
    "wof:placetype":"venue"
},
  "geometry": {"coordinates":[-0.771324,52.090569],"type":"Point"}
}