{
  "type": "Feature",
  "properties": {
    "addr:full":"Newton Cottage, Newton Of Falkland Cupar Fife KY15 7RZ",
    "addr:postcode":"ky15 7rz",
    "addr:street":"Newton;Falkland Cupar",
    "iso:country":"GB",
    "sg:address":"Newton Cottage, Newton Of Falkland",
    "sg:city":"Cupar",
    "sg:classifiers":[
        {
            "category":"Government",
            "subcategory":"Post Office",
            "type":"Public Place"
        }
    ],
    "sg:postcode":"KY15 7RZ",
    "sg:province":"Fife",
    "wof:name":"Newton of Falkland Post Office",
    "wof:placetype":"venue"
},
  "geometry": {"coordinates":[-3.2017700672,56.2522850037],"type":"Point"}
}