{
  "type": "Feature",
  "properties": {
    "iso:country":"GB",
    "sg:address":"70 High St",
    "sg:city":"Wells",
    "sg:classifiers":[
        {
            "category":"Shopping",
            "subcategory":"Clothing, Apparel, & Fashions",
            "type":"Retail Goods"
        }
    ],
    "sg:phone":"+44 1749 677454",
    "sg:postcode":"BA5 2SG",
    "sg:province":"Somerset",
    "sg:tags":[
        "shop"
    ],
    "wof:name":"Woolea Retail Ltd",
    "wof:placetype":"venue"
},
  "geometry": {"coordinates":[-2.648079,51.208324],"type":"Point"}
}