{
  "type": "Feature",
  "properties": {
    "addr:full":"Arlais Road Llandrindod Wells Powys LD1 5HE",
    "addr:postcode":"ld1 5he",
    "addr:street":"Arlais Road",
    "iso:country":"GB",
    "sg:address":"Arlais Road",
    "sg:city":"Llandrindod Wells",
    "sg:classifiers":[
        {
            "category":"Education",
            "subcategory":"Dance Studio",
            "type":"Public Place"
        }
    ],
    "sg:postcode":"LD1 5HE",
    "sg:province":"Powys",
    "sg:tags":[
        "school",
        "dancing"
    ],
    "wof:name":"Powys Dance Centre",
    "wof:placetype":"venue"
},
  "geometry": {"coordinates":[-3.378614,52.23872],"type":"Point"}
}