{
  "type": "Feature",
  "properties": {
    "addr:full":"10-12 High Street, Standish Wigan Lancashire WN6 0HL",
    "addr:housenumber":"10-12",
    "addr:postcode":"wn6 0hl",
    "addr:street":"High Street",
    "iso:country":"GB",
    "sg:address":"10-12 High Street, Standish",
    "sg:city":"Wigan",
    "sg:classifiers":[
        {
            "category":"Shopping",
            "subcategory":"Gifts & Souvenirs",
            "type":"Retail Goods"
        }
    ],
    "sg:phone":"+44 1257 422729",
    "sg:postcode":"WN6 0HL",
    "sg:province":"Lancashire",
    "sg:tags":[
        "shop"
    ],
    "wof:name":"Telford & Clarkson (Standish) Ltd.",
    "wof:placetype":"venue"
},
  "geometry": {"coordinates":[-2.6635630131,53.5863342285],"type":"Point"}
}