{
  "type": "Feature",
  "properties": {
    "iso:country":"GB",
    "sg:address":"101 High Street, Wheatley",
    "sg:city":"Oxford",
    "sg:classifiers":[
        {
            "category":"Shopping",
            "subcategory":"Musical Instruments",
            "type":"Retail Goods"
        }
    ],
    "sg:postcode":"OX33 1XP",
    "sg:province":"Buckinghamshire",
    "wof:name":"Ian White",
    "wof:placetype":"venue"
},
  "geometry": {"coordinates":[-1.13618,51.746849],"type":"Point"}
}