{
  "type": "Feature",
  "properties": {
    "iso:country":"GB",
    "sg:address":"63 Carr House Road, Springhead",
    "sg:city":"Oldham",
    "sg:classifiers":[
        {
            "category":"Food & Beverages",
            "subcategory":"Liquor & Beverages",
            "type":"Retail Goods"
        }
    ],
    "sg:phone":"+44 161 678 9460",
    "sg:postcode":"OL4 4NW",
    "sg:province":"Lancashire",
    "sg:tags":[
        "beer",
        "spirit",
        "wines"
    ],
    "wof:name":"Formstone's",
    "wof:placetype":"venue"
},
  "geometry": {"coordinates":[-2.0655269623,53.5421905518],"type":"Point"}
}