{
  "type": "Feature",
  "properties": {
    "addr:full":"1b St Johns Warwick Warwickshire CV34 4NE",
    "addr:housenumber":"1b",
    "addr:postcode":"cv34 4ne",
    "addr:street":"St Johns",
    "iso:country":"GB",
    "sg:address":"1b St Johns",
    "sg:city":"Warwick",
    "sg:classifiers":[
        {
            "category":"Professional",
            "subcategory":"Art Services",
            "type":"Services"
        }
    ],
    "sg:phone":"+44 1926 402932",
    "sg:postcode":"CV34 4NE",
    "sg:province":"Warwickshire",
    "sg:tags":[
        "model",
        "maker"
    ],
    "wof:name":"Scale Model Production",
    "wof:placetype":"venue"
},
  "geometry": {"coordinates":[-1.5813670158,52.2833900452],"type":"Point"}
}