{
  "type": "Feature",
  "properties": {
    "iso:country":"GB",
    "sg:address":"Kingsgate",
    "sg:city":"Bridlington",
    "sg:classifiers":[
        {
            "category":"Restaurant",
            "type":"Food & Drink"
        }
    ],
    "sg:phone":"+44 1262 601175",
    "sg:postcode":"YO15 3NG",
    "sg:province":"East Riding of Yorkshire",
    "wof:name":"Broadacres",
    "wof:placetype":"venue"
},
  "geometry": {"coordinates":[-0.2044640034,54.0814781189],"type":"Point"}
}