{
  "type": "Feature",
  "properties": {
    "iso:country":"GB",
    "sg:address":"Lane Side, Furzehill Road",
    "sg:city":"Torquay",
    "sg:classifiers":[
        {
            "category":"Building & Trades",
            "subcategory":"Construction",
            "type":"Services"
        }
    ],
    "sg:phone":"+44 1803 297546",
    "sg:postcode":"TQ1 3JG",
    "sg:province":"Devon",
    "sg:tags":[
        "decorator",
        "painter"
    ],
    "wof:name":"Kenneth J Cornwell",
    "wof:placetype":"venue"
},
  "geometry": {"coordinates":[-3.531799,50.472412],"type":"Point"}
}