{
  "type": "Feature",
  "properties": {
    "addr:full":"19 Hampden Avenue Chesham Buckinghamshire HP5 2HL",
    "addr:housenumber":"19",
    "addr:postcode":"hp5 2hl",
    "addr:street":"Hampden Avenue",
    "iso:country":"GB",
    "sg:address":"19 Hampden Avenue",
    "sg:city":"Chesham",
    "sg:classifiers":[
        {
            "category":"Building & Trades",
            "subcategory":"Plumbing",
            "type":"Services"
        }
    ],
    "sg:postcode":"HP5 2HL",
    "sg:province":"Buckinghamshire",
    "sg:tags":[
        "central",
        "heating"
    ],
    "wof:name":"Brian A Franklin",
    "wof:placetype":"venue"
},
  "geometry": {"coordinates":[-0.6192409992,51.710231781],"type":"Point"}
}