{
  "type": "Feature",
  "properties": {
    "addr:full":"Unit 10, The Spithead Business Centre, New Road Lake Freshwater Isle of Wight PO36 9PH",
    "addr:housenumber":"unit 10;business centre",
    "addr:postcode":"po36 9ph",
    "addr:street":"The Spithead;New Road",
    "iso:country":"GB",
    "sg:address":"Unit 10, The Spithead Business Centre, New Road Lake",
    "sg:city":"Freshwater",
    "sg:classifiers":[
        {
            "category":"Bus Charters",
            "type":"Transportation"
        }
    ],
    "sg:phone":"+44 1983 408080",
    "sg:postcode":"PO36 9PH",
    "sg:province":"Isle of Wight",
    "sg:tags":[
        "hire",
        "coach"
    ],
    "wof:name":"Island Coach Services Ltd.",
    "wof:placetype":"venue"
},
  "geometry": {"coordinates":[-1.18136,50.644932],"type":"Point"}
}