{
  "type": "Feature",
  "properties": {
    "addr:full":"Unit 21 Orleton Road, Ludlow Business Park Ludlow Herefordshire SY8 1XF",
    "addr:housenumber":"unit 21",
    "addr:postcode":"sy8 1xf",
    "addr:street":"Orleton Road;Business Park",
    "iso:country":"GB",
    "sg:address":"Unit 21 Orleton Road, Ludlow Business Park",
    "sg:city":"Ludlow",
    "sg:classifiers":[
        {
            "category":"Professional",
            "subcategory":"Business Services",
            "type":"Services"
        }
    ],
    "sg:phone":"+44 1584 877771",
    "sg:postcode":"SY8 1XF",
    "sg:province":"Herefordshire",
    "sg:tags":[
        "import",
        "export",
        "agent"
    ],
    "wof:name":"Well Communications",
    "wof:placetype":"venue"
},
  "geometry": {"coordinates":[-2.695589,52.366131],"type":"Point"}
}