{
  "type": "Feature",
  "properties": {
    "iso:country":"GB",
    "sg:address":"Ezekiel Lane",
    "sg:city":"Willenhall",
    "sg:classifiers":[
        {
            "category":"Retail",
            "subcategory":"Auto Repair",
            "type":"Services"
        }
    ],
    "sg:phone":"+44 1922 409595",
    "sg:postcode":"WV12 5QU",
    "sg:province":"West Midlands",
    "sg:tags":[
        "modification",
        "garage"
    ],
    "wof:name":"Dale & Julie Ratledge",
    "wof:placetype":"venue"
},
  "geometry": {"coordinates":[-2.039459,52.603951],"type":"Point"}
}