{
  "type": "Feature",
  "properties": {
    "addr:full":"17 The Parade, Colchester Road Romford Essex RM3 0AQ",
    "addr:housenumber":"17",
    "addr:postcode":"rm3 0aq",
    "addr:street":"The Parade Colchester Road",
    "iso:country":"GB",
    "sg:address":"17 The Parade, Colchester Road",
    "sg:city":"Romford",
    "sg:classifiers":[
        {
            "category":"Shopping",
            "subcategory":"Department Store",
            "type":"Retail Goods"
        }
    ],
    "sg:postcode":"RM3 0AQ",
    "sg:province":"Essex",
    "wof:name":"Sethi Stores",
    "wof:placetype":"venue"
},
  "geometry": {"coordinates":[0.250135,51.604],"type":"Point"}
}