{
  "type": "Feature",
  "properties": {
    "addr:full":"141 Hamstead Rd Birmingham West Midlands B43 5BG",
    "addr:housenumber":"141",
    "addr:postcode":"b43 5bg",
    "addr:street":"Hamstead Rd",
    "iso:country":"GB",
    "sg:address":"141 Hamstead Rd",
    "sg:city":"Birmingham",
    "sg:classifiers":[
        {
            "category":"Food & Beverages",
            "subcategory":"Fruits & Vegetables",
            "type":"Retail Goods"
        }
    ],
    "sg:postcode":"B43 5BG",
    "sg:province":"West Midlands",
    "sg:tags":[
        "greengrocer"
    ],
    "wof:name":"Simkins",
    "wof:placetype":"venue"
},
  "geometry": {"coordinates":[-1.9496079683,52.5386619568],"type":"Point"}
}