{
  "type": "Feature",
  "properties": {
    "addr:full":"17 The Frenches Redhill Surrey RH1 2HF",
    "addr:housenumber":"17",
    "addr:postcode":"rh1 2hf",
    "addr:street":"The Frenches Redhill",
    "iso:country":"GB",
    "sg:address":"17 The Frenches",
    "sg:city":"Redhill",
    "sg:classifiers":[
        {
            "category":"Personal",
            "type":"Services"
        }
    ],
    "sg:phone":"+44 1737 370056",
    "sg:postcode":"RH1 2HF",
    "sg:province":"Surrey",
    "sg:tags":[
        "consultant",
        "fitness"
    ],
    "wof:name":"Unique Training Co Ltd",
    "wof:placetype":"venue"
},
  "geometry": {"coordinates":[-0.1647659987,51.2470016479],"type":"Point"}
}