{
  "type": "Feature",
  "properties": {
    "addr:full":"Club House, Cottage Road Faringdon Oxfordshire SN7 8NX",
    "addr:postcode":"sn7 8nx",
    "addr:street":"Club;Cottage Road",
    "iso:country":"GB",
    "sg:address":"Club House, Cottage Road",
    "sg:city":"Faringdon",
    "sg:classifiers":[
        {
            "category":"Arena",
            "subcategory":"Sports Club",
            "type":"Entertainment"
        }
    ],
    "sg:phone":"+44 1367 718823",
    "sg:postcode":"SN7 8NX",
    "sg:province":"Oxfordshire",
    "wof:name":"Stanford in the Vale Football Club",
    "wof:placetype":"venue"
},
  "geometry": {"coordinates":[-1.510959,51.641953],"type":"Point"}
}