{
  "type": "Feature",
  "properties": {
    "addr:full":"61 Newteswell Drive Waltham Abbey Essex EN9 1QF",
    "addr:housenumber":"61",
    "addr:postcode":"en9 1qf",
    "addr:street":"Newteswell Drive",
    "iso:country":"GB",
    "sg:address":"61 Newteswell Drive",
    "sg:city":"Waltham Abbey",
    "sg:classifiers":[
        {
            "category":"Building & Trades",
            "subcategory":"Plumbing",
            "type":"Services"
        }
    ],
    "sg:phone":"+44 1992 716320",
    "sg:postcode":"EN9 1QF",
    "sg:province":"Essex",
    "sg:tags":[
        "heating"
    ],
    "wof:name":"Aiden Potter Plumbers",
    "wof:placetype":"venue"
},
  "geometry": {"coordinates":[0.0074120001,51.6910514832],"type":"Point"}
}