{
  "type": "Feature",
  "properties": {
    "addr:full":"Eastern Esplanade Southend-on-sea Essex SS1 2YH",
    "addr:postcode":"ss1 2yh",
    "addr:street":"Eastern Esplanade",
    "iso:country":"GB",
    "sg:address":"Eastern Esplanade",
    "sg:city":"Southend-on-sea",
    "sg:classifiers":[
        {
            "category":"Recreation",
            "subcategory":"Water Park",
            "type":"Entertainment"
        },
        {
            "category":"Government",
            "subcategory":"Office",
            "type":"Public Place"
        }
    ],
    "sg:phone":"+44 1702 612770",
    "sg:postcode":"SS1 2YH",
    "sg:province":"Essex",
    "sg:tags":[
        "sport",
        "local"
    ],
    "wof:name":"Southend Environmental & Outdoor Education Centre",
    "wof:placetype":"venue"
},
  "geometry": {"coordinates":[0.729053,51.530964],"type":"Point"}
}