{
  "type": "Feature",
  "properties": {
    "iso:country":"GB",
    "sg:address":"24 Avenue Mews",
    "sg:city":"Muswell Hill",
    "sg:classifiers":[
        {
            "category":"Bakery",
            "type":"Food & Drink"
        }
    ],
    "sg:phone":"+44 20 8444 8700",
    "sg:postcode":"N10 3NP",
    "sg:province":"Greater London",
    "sg:tags":[
        "cake",
        "maker"
    ],
    "wof:name":"Cake Box The",
    "wof:placetype":"venue"
},
  "geometry": {"coordinates":[-0.143009,51.59124],"type":"Point"}
}