{
  "type": "Feature",
  "properties": {
    "addr:full":"48 Marsh Road Middlesbrough North Yorkshire TS1 5LB",
    "addr:housenumber":"48",
    "addr:postcode":"ts1 5lb",
    "addr:street":"Marsh Road",
    "iso:country":"GB",
    "sg:address":"48 Marsh Road",
    "sg:city":"Middlesbrough",
    "sg:classifiers":[
        {
            "category":"Building & Trades",
            "subcategory":"Construction",
            "type":"Services"
        }
    ],
    "sg:phone":"+44 1642 245828",
    "sg:postcode":"TS1 5LB",
    "sg:province":"North Yorkshire",
    "sg:tags":[
        "builder"
    ],
    "wof:name":"J K Shannon",
    "wof:placetype":"venue"
},
  "geometry": {"coordinates":[-1.2442649603,54.5789680481],"type":"Point"}
}