{
  "type": "Feature",
  "properties": {
    "addr:full":"2 Westbourne Avenue Clevedon Somerset BS21 7UA",
    "addr:housenumber":"2",
    "addr:postcode":"bs21 7ua",
    "addr:street":"Westbourne Avenue",
    "iso:country":"GB",
    "sg:address":"2 Westbourne Avenue",
    "sg:city":"Clevedon",
    "sg:classifiers":[
        {
            "category":"Home & Garden",
            "subcategory":"Household Appliances",
            "type":"Retail Goods"
        }
    ],
    "sg:postcode":"BS21 7UA",
    "sg:province":"Somerset",
    "sg:tags":[
        "electrical"
    ],
    "wof:name":"Europer",
    "wof:placetype":"venue"
},
  "geometry": {"coordinates":[-2.8689599037,51.432964325],"type":"Point"}
}