{
  "type": "Feature",
  "properties": {
    "addr:full":"Toll Bridge House, Toll Bridge Road, Batheaston Bath Bath and North East Somerset BA1 7DF",
    "addr:postcode":"ba1 7df",
    "addr:street":"Toll;Toll Bridge Road",
    "iso:country":"GB",
    "sg:address":"Toll Bridge House, Toll Bridge Road, Batheaston",
    "sg:city":"Bath",
    "sg:classifiers":[
        {
            "category":"Professional",
            "subcategory":"Printing & Photocopies",
            "type":"Services"
        }
    ],
    "sg:phone":"+44 1225 858217",
    "sg:postcode":"BA1 7DF",
    "sg:province":"Bath and North East Somerset",
    "sg:tags":[
        "plate",
        "lithographic",
        "maker"
    ],
    "wof:name":"T Harding Son & Co. Ltd.",
    "wof:placetype":"venue"
},
  "geometry": {"coordinates":[-2.32726,51.402275],"type":"Point"}
}