{
  "type": "Feature",
  "properties": {
    "iso:country":"GB",
    "sg:address":"128 Chestnut Grove",
    "sg:city":"Mitcham",
    "sg:classifiers":[
        {
            "category":"Manufacturing",
            "subcategory":"Rubber & Plastics",
            "type":"Manufacturing & Wholesale Goods"
        }
    ],
    "sg:postcode":"CR4 1RB",
    "sg:province":"Greater London",
    "sg:tags":[
        "product",
        "moulding",
        "injection"
    ],
    "wof:name":"Hr Engineering Ltd.",
    "wof:placetype":"venue"
},
  "geometry": {"coordinates":[-0.133465,51.39843],"type":"Point"}
}