{
  "type": "Feature",
  "properties": {
    "addr:full":"152a Manchester Road East Manchester Greater Manchester M38 0LQ",
    "addr:housenumber":"152a",
    "addr:postcode":"m38 0lq",
    "addr:street":"Manchester Road East",
    "iso:country":"GB",
    "sg:address":"152a Manchester Road East",
    "sg:city":"Manchester",
    "sg:classifiers":[
        {
            "category":"Health Services",
            "subcategory":"Doctor",
            "type":"Services"
        }
    ],
    "sg:phone":"+44 161 799 9997",
    "sg:postcode":"M38 0LQ",
    "sg:province":"Greater Manchester",
    "sg:tags":[
        "practitioners"
    ],
    "wof:name":"Naqvi, S M H",
    "wof:placetype":"venue"
},
  "geometry": {"coordinates":[-2.4104399681,53.5268516541],"type":"Point"}
}