{
  "type": "Feature",
  "properties": {
    "addr:full":"68 The Coppins, New Addington Croydon Surrey CR0 9DS",
    "addr:housenumber":"68",
    "addr:postcode":"cr0 9ds",
    "addr:street":"The Coppins",
    "iso:country":"GB",
    "sg:address":"68 The Coppins, New Addington",
    "sg:city":"Croydon",
    "sg:classifiers":[
        {
            "category":"Building & Trades",
            "subcategory":"Construction",
            "type":"Services"
        }
    ],
    "sg:postcode":"CR0 9DS",
    "sg:province":"Surrey",
    "sg:tags":[
        "builder"
    ],
    "wof:name":"I B Builders",
    "wof:placetype":"venue"
},
  "geometry": {"coordinates":[-0.0212190002,51.3551712036],"type":"Point"}
}