{
  "type": "Feature",
  "properties": {
    "addr:full":"71 Abingdon Street Blackpool Lancashire FY1 1NH",
    "addr:housenumber":"71",
    "addr:postcode":"fy1 1nh",
    "addr:street":"Abingdon Street",
    "iso:country":"GB",
    "sg:address":"71 Abingdon Street",
    "sg:city":"Blackpool",
    "sg:classifiers":[
        {
            "category":"Sports & Exercise",
            "subcategory":"Gym",
            "type":"Entertainment"
        }
    ],
    "sg:postcode":"FY1 1NH",
    "sg:province":"Lancashire",
    "sg:tags":[
        "fitness",
        "health",
        "centre"
    ],
    "wof:name":"Just Jane's",
    "wof:placetype":"venue"
},
  "geometry": {"coordinates":[-3.053204,53.81992],"type":"Point"}
}