{
  "type": "Feature",
  "properties": {
    "addr:full":"Dell Rd Rochdale Lancashire OL12 6BZ",
    "addr:postcode":"ol12 6bz",
    "addr:street":"Dell Rd",
    "iso:country":"GB",
    "sg:address":"Dell Rd",
    "sg:city":"Rochdale",
    "sg:classifiers":[
        {
            "category":"Military Area",
            "subcategory":"Air Force Base",
            "type":"Public Place"
        }
    ],
    "sg:phone":"+44 1706 359155",
    "sg:postcode":"OL12 6BZ",
    "sg:province":"Lancashire",
    "sg:tags":[
        "water",
        "treatment"
    ],
    "wof:name":"Invent Water Treatment Ltd",
    "wof:placetype":"venue"
},
  "geometry": {"coordinates":[-2.1837410927,53.63539505],"type":"Point"}
}