{
  "type": "Feature",
  "properties": {
    "iso:country":"GB",
    "sg:address":"13 Richmond Hill",
    "sg:city":"Richmond",
    "sg:classifiers":[
        {
            "category":"Shopping",
            "subcategory":"Clothing, Apparel, & Fashions",
            "type":"Retail Goods"
        }
    ],
    "sg:phone":"+44 20 8940 0514",
    "sg:postcode":"TW10 6RE",
    "sg:province":"Greater London",
    "sg:tags":[
        "shop",
        "lady",
        "fashionwear"
    ],
    "wof:name":"Yvonne Damant",
    "wof:placetype":"venue"
},
  "geometry": {"coordinates":[-0.3031300008,51.4566574097],"type":"Point"}
}