{
  "type": "Feature",
  "properties": {
    "addr:full":"Monmouth Road Usk Monmouthshire NP5 1SE",
    "addr:postcode":"np5 1se",
    "addr:street":"Monmouth Road",
    "iso:country":"GB",
    "sg:address":"Monmouth Road",
    "sg:city":"Usk",
    "sg:classifiers":[
        {
            "category":"Education",
            "subcategory":"School",
            "type":"Public Place"
        }
    ],
    "sg:phone":"+44 1291 673818",
    "sg:postcode":"NP5 1SE",
    "sg:province":"Monmouthshire",
    "sg:tags":[
        "local",
        "authority"
    ],
    "wof:name":"Usk Primary School",
    "wof:placetype":"venue"
},
  "geometry": {"coordinates":[-2.9001789093,51.7048912048],"type":"Point"}
}