{
  "type": "Feature",
  "properties": {
    "iso:country":"GB",
    "sg:address":"5-7 Headcorn Rd, Biddenden",
    "sg:city":"Ashford",
    "sg:classifiers":[
        {
            "category":"Restaurant",
            "type":"Food & Drink"
        }
    ],
    "sg:phone":"+44 1580 291485",
    "sg:postcode":"TN27 8JA",
    "sg:province":"Kent",
    "sg:tags":[
        "indian"
    ],
    "wof:name":"Maharja Indian Restaurant",
    "wof:placetype":"venue"
},
  "geometry": {"coordinates":[0.6483899951,51.1239891052],"type":"Point"}
}