{
  "type": "Feature",
  "properties": {
    "iso:country":"GB",
    "sg:address":"1 Hollington Crescent",
    "sg:city":"Birmingham",
    "sg:classifiers":[
        {
            "category":"Professional",
            "subcategory":"Accounting & Tax Preparation",
            "type":"Services"
        }
    ],
    "sg:phone":"+44 121 783 6810",
    "sg:postcode":"B33 9LS",
    "sg:province":"West Midlands",
    "sg:tags":[
        "accountant"
    ],
    "wof:name":"Denis Meehan",
    "wof:placetype":"venue"
},
  "geometry": {"coordinates":[-1.7919709682,52.4891052246],"type":"Point"}
}