{
  "type": "Feature",
  "properties": {
    "addr:full":"37 Chapel Market Islington Greater London N1 9EN",
    "addr:housenumber":"37",
    "addr:postcode":"n1 9en",
    "addr:street":"Chapel Market",
    "iso:country":"GB",
    "sg:address":"37 Chapel Market",
    "sg:city":"Islington",
    "sg:classifiers":[
        {
            "category":"Cafe",
            "type":"Food & Drink"
        }
    ],
    "sg:phone":"+44 20 7278 5330",
    "sg:postcode":"N1 9EN",
    "sg:province":"Greater London",
    "sg:tags":[
        "tea",
        "room"
    ],
    "wof:name":"Jenny's Restaurant",
    "wof:placetype":"venue"
},
  "geometry": {"coordinates":[-0.1077010036,51.5336685181],"type":"Point"}
}