{
  "type": "Feature",
  "properties": {
    "addr:full":"Headquarters, Croesyceiliog Cwmbran Monmouthshire NP44 2XJ",
    "addr:postcode":"np44 2xj",
    "iso:country":"GB",
    "sg:address":"Headquarters, Croesyceiliog",
    "sg:city":"Cwmbran",
    "sg:classifiers":[
        {
            "category":"Government",
            "subcategory":"Police Station",
            "type":"Public Place"
        }
    ],
    "sg:phone":"+44 1633 838111",
    "sg:postcode":"NP44 2XJ",
    "sg:province":"Monmouthshire",
    "sg:tags":[
        "support"
    ],
    "wof:name":"Gwent Constabulary",
    "wof:placetype":"venue"
},
  "geometry": {"coordinates":[-3.007425,51.660568],"type":"Point"}
}