{
  "type": "Feature",
  "properties": {
    "iso:country":"GB",
    "sg:address":"29 West Street",
    "sg:city":"Leek",
    "sg:classifiers":[
        {
            "category":"Personal",
            "subcategory":"Beauty Salon",
            "type":"Services"
        }
    ],
    "sg:phone":"+44 1538 386326",
    "sg:postcode":"ST13 8AF",
    "sg:province":"Staffordshire",
    "sg:tags":[
        "unisex",
        "hairdresser"
    ],
    "wof:name":"Streaks Ahead",
    "wof:placetype":"venue"
},
  "geometry": {"coordinates":[-2.0310959816,53.1064872742],"type":"Point"}
}