{
  "type": "Feature",
  "properties": {
    "iso:country":"GB",
    "sg:address":"18 Branscombe Rd, Stoke Bishop",
    "sg:city":"Bristol",
    "sg:classifiers":[
        {
            "category":"Professional",
            "subcategory":"Management & Consulting",
            "type":"Services"
        }
    ],
    "sg:phone":"+44 7976 830995",
    "sg:postcode":"BS9 1SN",
    "sg:province":"City of Bristol",
    "sg:tags":[
        "consultant",
        "business"
    ],
    "wof:name":"Brindley Kerr Consulting Ltd",
    "wof:placetype":"venue"
},
  "geometry": {"coordinates":[-2.644561,51.481281],"type":"Point"}
}