{
  "type": "Feature",
  "properties": {
    "addr:full":"11 East Hill Park, Knatts Valley Sevenoaks Kent TN15 6YF",
    "addr:housenumber":"11",
    "addr:postcode":"tn15 6yf",
    "addr:street":"East Hill Park Knatts Valley",
    "iso:country":"GB",
    "sg:address":"11 East Hill Park, Knatts Valley",
    "sg:city":"Sevenoaks",
    "sg:classifiers":[
        {
            "category":"Home & Garden",
            "subcategory":"Carpets & Floor Coverings",
            "type":"Retail Goods"
        }
    ],
    "sg:phone":"+44 1959 524972",
    "sg:postcode":"TN15 6YF",
    "sg:province":"Kent",
    "sg:tags":[
        "cleaner",
        "upholstery"
    ],
    "wof:name":"Capricorn Cleaning",
    "wof:placetype":"venue"
},
  "geometry": {"coordinates":[0.2488359958,51.3339271545],"type":"Point"}
}