{
  "type": "Feature",
  "properties": {
    "iso:country":"GB",
    "sg:address":"Frondeg, Clyngwyn Rd, Ystalyfera",
    "sg:city":"Swansea",
    "sg:classifiers":[
        {
            "category":"Utilities",
            "subcategory":"Fuel Oil & Lpg",
            "type":"Services"
        }
    ],
    "sg:phone":"+44 1639 842652",
    "sg:postcode":"SA9 2AE",
    "sg:province":"Carmarthenshire",
    "wof:name":"Glantawe Fuels",
    "wof:placetype":"venue"
},
  "geometry": {"coordinates":[-3.791884,51.75769],"type":"Point"}
}