{
  "type": "Feature",
  "properties": {
    "iso:country":"GB",
    "sg:address":"22a Bellside Road, Cleland",
    "sg:city":"Motherwell",
    "sg:classifiers":[
        {
            "category":"Wholesale",
            "subcategory":"Computers",
            "type":"Manufacturing & Wholesale Goods"
        },
        {
            "category":"Professional",
            "subcategory":"Computer Services",
            "type":"Services"
        }
    ],
    "sg:phone":"+44 1698 861849",
    "sg:postcode":"ML1 5NP",
    "sg:province":"North Lanarkshire",
    "sg:tags":[
        "supplier",
        "consultant",
        "consumables"
    ],
    "wof:name":"Computer Consultants",
    "wof:placetype":"venue"
},
  "geometry": {"coordinates":[-3.9078500271,55.804019928],"type":"Point"}
}