{
  "type": "Feature",
  "properties": {
    "iso:country":"GB",
    "sg:address":"98 London Road",
    "sg:city":"Leicester",
    "sg:classifiers":[
        {
            "category":"Real Estate",
            "subcategory":"Surveying",
            "type":"Services"
        }
    ],
    "sg:phone":"+44 116 255 1933",
    "sg:postcode":"LE2 0QS",
    "sg:province":"Leicestershire",
    "sg:tags":[
        "surveyor",
        "valuer"
    ],
    "wof:name":"Naylor Parkes",
    "wof:placetype":"venue"
},
  "geometry": {"coordinates":[-1.1212069988,52.6284332275],"type":"Point"}
}