{
  "type": "Feature",
  "properties": {
    "addr:full":"Cornwallis Cres Bristol City of Bristol BS8 4PH",
    "addr:postcode":"bs8 4ph",
    "addr:street":"Cornwallis Cres",
    "iso:country":"GB",
    "sg:address":"Cornwallis Cres",
    "sg:city":"Bristol",
    "sg:classifiers":[
        {
            "category":"Education",
            "subcategory":"Music School",
            "type":"Public Place"
        }
    ],
    "sg:phone":"+44 117 973 4652",
    "sg:postcode":"BS8 4PH",
    "sg:province":"City of Bristol",
    "wof:name":"O'Grady Drama Academy",
    "wof:placetype":"venue"
},
  "geometry": {"coordinates":[-2.6176290512,51.4501495361],"type":"Point"}
}