{
  "type": "Feature",
  "properties": {
    "addr:full":"64 Hotspur Street Glasgow Glasgow City G20 8LP",
    "addr:housenumber":"64",
    "addr:postcode":"g20 8lp",
    "addr:street":"Hotspur Street",
    "iso:country":"GB",
    "sg:address":"64 Hotspur Street",
    "sg:city":"Glasgow",
    "sg:classifiers":[
        {
            "category":"Professional",
            "subcategory":"Art Services",
            "type":"Services"
        }
    ],
    "sg:postcode":"G20 8LP",
    "sg:province":"Glasgow City",
    "sg:tags":[
        "photographer"
    ],
    "wof:name":"Robert Scott Photography",
    "wof:placetype":"venue"
},
  "geometry": {"coordinates":[-4.28467,55.883286],"type":"Point"}
}