{
  "type": "Feature",
  "properties": {
    "addr:full":"Glen Arroch, East Kilbride Glasgow South Lanarkshire G74 2BP",
    "addr:postcode":"g74 2bp",
    "iso:country":"GB",
    "sg:address":"Glen Arroch, East Kilbride",
    "sg:city":"Glasgow",
    "sg:classifiers":[
        {
            "category":"Education",
            "subcategory":"School",
            "type":"Public Place"
        },
        {
            "category":"Government",
            "subcategory":"Office",
            "type":"Public Place"
        }
    ],
    "sg:phone":"+44 1355 232064",
    "sg:postcode":"G74 2BP",
    "sg:province":"South Lanarkshire",
    "sg:tags":[
        "local",
        "authority"
    ],
    "wof:name":"Blacklaw Primary School",
    "wof:placetype":"venue"
},
  "geometry": {"coordinates":[-4.156859,55.761856],"type":"Point"}
}