{
  "type": "Feature",
  "properties": {
    "addr:full":"Timbers Clinic, Brookshill Harrow Greater London HA3 6RT",
    "addr:postcode":"ha3 6rt",
    "iso:country":"GB",
    "sg:address":"Timbers Clinic, Brookshill",
    "sg:city":"Harrow",
    "sg:classifiers":[
        {
            "category":"Health Services",
            "subcategory":"Clinic",
            "type":"Services"
        }
    ],
    "sg:postcode":"HA3 6RT",
    "sg:province":"Greater London",
    "sg:tags":[
        "private"
    ],
    "wof:name":"The Lancer Medical Group",
    "wof:placetype":"venue"
},
  "geometry": {"coordinates":[-0.3402439952,51.6063499451],"type":"Point"}
}