{
  "type": "Feature",
  "properties": {
    "addr:full":"Market Place, Long Sutton Spalding Cambridgeshire PE12 9JA",
    "addr:postcode":"pe12 9ja",
    "addr:street":"Market Place",
    "iso:country":"GB",
    "sg:address":"Market Place, Long Sutton",
    "sg:city":"Spalding",
    "sg:classifiers":[
        {
            "category":"Shopping",
            "subcategory":"Clothing, Apparel, & Fashions",
            "type":"Retail Goods"
        },
        {
            "category":"Shopping",
            "subcategory":"Shoes",
            "type":"Retail Goods"
        }
    ],
    "sg:phone":"+44 1406 363433",
    "sg:postcode":"PE12 9JA",
    "sg:province":"Cambridgeshire",
    "sg:tags":[
        "shop"
    ],
    "wof:name":"Sheila Tiller Fashions",
    "wof:placetype":"venue"
},
  "geometry": {"coordinates":[0.122578,52.785255],"type":"Point"}
}