{
  "type": "Feature",
  "properties": {
    "addr:full":"1 Rosemount Terrace Dundee Dundee City DD3 6JQ",
    "addr:housenumber":"1",
    "addr:postcode":"dd3 6jq",
    "addr:street":"Rosemount Terrace",
    "iso:country":"GB",
    "sg:address":"1 Rosemount Terrace",
    "sg:city":"Dundee",
    "sg:classifiers":[
        {
            "category":"Travel",
            "subcategory":"Hotels & Motels",
            "type":"Entertainment"
        }
    ],
    "sg:phone":"+44 1382 322154",
    "sg:postcode":"DD3 6JQ",
    "sg:province":"Dundee City",
    "sg:tags":[
        "house",
        "guest"
    ],
    "wof:name":"Cullaig Guest House",
    "wof:placetype":"venue"
},
  "geometry": {"coordinates":[-3.0540480614,56.4959220886],"type":"Point"}
}