{
  "type": "Feature",
  "properties": {
    "addr:full":"22 Mayfair, Pedmore Stourbridge West Midlands DY9 0XE",
    "addr:housenumber":"22",
    "addr:postcode":"dy9 0xe",
    "addr:street":"Mayfair Pedmore",
    "iso:country":"GB",
    "sg:address":"22 Mayfair, Pedmore",
    "sg:city":"Stourbridge",
    "sg:classifiers":[
        {
            "category":"Professional",
            "type":"Services"
        }
    ],
    "sg:postcode":"DY9 0XE",
    "sg:province":"West Midlands",
    "sg:tags":[
        "reflexologists"
    ],
    "wof:name":"Pathways 2 Health",
    "wof:placetype":"venue"
},
  "geometry": {"coordinates":[-2.119888,52.441822],"type":"Point"}
}