{
  "type": "Feature",
  "properties": {
    "iso:country":"GB",
    "sg:address":"102 Lansbury Drive",
    "sg:city":"Hayes",
    "sg:classifiers":[
        {
            "category":"Shopping",
            "subcategory":"Pharmacy",
            "type":"Retail Goods"
        }
    ],
    "sg:phone":"+44 20 8573 0837",
    "sg:postcode":"UB4 8SE",
    "sg:province":"Greater London",
    "sg:tags":[
        "pharmacist",
        "chemist"
    ],
    "wof:name":"Lansbury Pharmacy",
    "wof:placetype":"venue"
},
  "geometry": {"coordinates":[-0.4190639853,51.5262908936],"type":"Point"}
}