{
  "type": "Feature",
  "properties": {
    "addr:full":"14 Dollar Street Cirencester Gloucestershire GL7 2AJ",
    "addr:housenumber":"14",
    "addr:postcode":"gl7 2aj",
    "addr:street":"Dollar Street",
    "iso:country":"GB",
    "sg:address":"14 Dollar Street",
    "sg:city":"Cirencester",
    "sg:classifiers":[
        {
            "category":"Shopping",
            "subcategory":"Antiques",
            "type":"Retail Goods"
        }
    ],
    "sg:phone":"+44 1285 644485",
    "sg:postcode":"GL7 2AJ",
    "sg:province":"Gloucestershire",
    "wof:name":"Woodminster Antiques",
    "wof:placetype":"venue"
},
  "geometry": {"coordinates":[-1.9692670107,51.7187576294],"type":"Point"}
}