{
  "type": "Feature",
  "properties": {
    "addr:full":"High Street, Ynysddu Newport Blaenau Gwent NP11 7JH",
    "addr:postcode":"np11 7jh",
    "addr:street":"High Street",
    "iso:country":"GB",
    "sg:address":"High Street, Ynysddu",
    "sg:city":"Newport",
    "sg:classifiers":[
        {
            "category":"Education",
            "subcategory":"School",
            "type":"Public Place"
        }
    ],
    "sg:phone":"+44 1495 200377",
    "sg:postcode":"NP11 7JH",
    "sg:province":"Blaenau Gwent",
    "sg:tags":[
        "local",
        "authority"
    ],
    "wof:name":"Ynysddu Primary School",
    "wof:placetype":"venue"
},
  "geometry": {"coordinates":[-3.1276888847,51.6250038147],"type":"Point"}
}