{
  "type": "Feature",
  "properties": {
    "addr:full":"9b Sunrise Business Park, Higher Shaftesbury Road Blandford Forum Dorset DT11 8SS",
    "addr:housenumber":"9b",
    "addr:postcode":"dt11 8ss",
    "addr:street":"Sunrise Business Park Higher Shaftesbury Road",
    "iso:country":"GB",
    "sg:address":"9b Sunrise Business Park, Higher Shaftesbury Road",
    "sg:city":"Blandford Forum",
    "sg:classifiers":[
        {
            "category":"Autos & Motor Vehicles",
            "subcategory":"Auto Supplies",
            "type":"Retail Goods"
        }
    ],
    "sg:phone":"+44 1258 480181",
    "sg:postcode":"DT11 8SS",
    "sg:province":"Dorset",
    "sg:tags":[
        "tyre"
    ],
    "wof:name":"Blandford Tyre & Battery Services",
    "wof:placetype":"venue"
},
  "geometry": {"coordinates":[-2.119489,50.869389],"type":"Point"}
}