{
  "type": "Feature",
  "properties": {
    "addr:full":"49 Brewer Street London Greater London W1F 9UG",
    "addr:housenumber":"49",
    "addr:postcode":"w1f 9ug",
    "addr:street":"Brewer Street",
    "iso:country":"GB",
    "sg:address":"49 Brewer Street",
    "sg:city":"London",
    "sg:classifiers":[
        {
            "category":"Real Estate",
            "subcategory":"Real Estate Agent",
            "type":"Services"
        }
    ],
    "sg:phone":"+44 20 7494 9000",
    "sg:postcode":"W1F 9UG",
    "sg:province":"Greater London",
    "wof:name":"Hallmark Estates Ltd.",
    "wof:placetype":"venue"
},
  "geometry": {"coordinates":[-0.1351100057,51.5116004944],"type":"Point"}
}