{
  "type": "Feature",
  "properties": {
    "iso:country":"GB",
    "sg:address":"5 Greenfield Drive",
    "sg:city":"Irvine",
    "sg:classifiers":[
        {
            "category":"Government",
            "subcategory":"Office",
            "type":"Public Place"
        }
    ],
    "sg:postcode":"KA12 0ED",
    "sg:province":"North Ayrshire",
    "sg:tags":[
        "mp",
        "meps"
    ],
    "wof:name":"Brian Donohoe",
    "wof:placetype":"venue"
},
  "geometry": {"coordinates":[-4.656843,55.611626],"type":"Point"}
}