{
  "type": "Feature",
  "properties": {
    "iso:country":"GB",
    "sg:address":"68 Gores Lane",
    "sg:city":"Liverpool",
    "sg:classifiers":[
        {
            "category":"Professional",
            "subcategory":"Management & Consulting",
            "type":"Services"
        }
    ],
    "sg:postcode":"L37 7DF",
    "sg:province":"Lancashire",
    "sg:tags":[
        "consultant",
        "business"
    ],
    "wof:name":"Ken Tipping Ltd.",
    "wof:placetype":"venue"
},
  "geometry": {"coordinates":[-3.0644640923,53.5639533997],"type":"Point"}
}