{
  "type": "Feature",
  "properties": {
    "addr:full":"6 Antrim Mansions, Antrim Road London Greater London NW3 4XT",
    "addr:housenumber":"6",
    "addr:postcode":"nw3 4xt",
    "addr:street":"Antrim Road",
    "iso:country":"GB",
    "sg:address":"6 Antrim Mansions, Antrim Road",
    "sg:city":"London",
    "sg:classifiers":[
        {
            "category":"Real Estate",
            "subcategory":"Surveying",
            "type":"Services"
        }
    ],
    "sg:phone":"+44 20 7586 6659",
    "sg:postcode":"NW3 4XT",
    "sg:province":"Greater London",
    "sg:tags":[
        "surveyor",
        "valuer"
    ],
    "wof:name":"Martin Schotness & Co",
    "wof:placetype":"venue"
},
  "geometry": {"coordinates":[-0.1612910032,51.5468978882],"type":"Point"}
}