{
  "type": "Feature",
  "properties": {
    "addr:full":"The Flat, Brooks View, Knole Langport Somerset TA10 9HZ",
    "addr:postcode":"ta10 9hz",
    "addr:street":"Brooks View",
    "iso:country":"GB",
    "sg:address":"The Flat, Brooks View, Knole",
    "sg:city":"Langport",
    "sg:classifiers":[
        {
            "category":"Farming",
            "subcategory":"Livestock Farm",
            "type":"Manufacturing & Wholesale Goods"
        }
    ],
    "sg:postcode":"TA10 9HZ",
    "sg:province":"Somerset",
    "sg:tags":[
        "others"
    ],
    "wof:name":"Peter Calves Harpham",
    "wof:placetype":"venue"
},
  "geometry": {"coordinates":[-2.8242840767,51.042049408],"type":"Point"}
}