{
  "type": "Feature",
  "properties": {
    "iso:country":"GB",
    "sg:address":"Bryan Road, Edgerton",
    "sg:city":"Huddersfield",
    "sg:classifiers":[
        {
            "category":"Health Services",
            "subcategory":"Nursing And Care Facility",
            "type":"Services"
        },
        {
            "category":"Social Services",
            "subcategory":"Retirement Home",
            "type":"Services"
        }
    ],
    "sg:postcode":"HD2 2AH",
    "sg:province":"West Yorkshire",
    "sg:tags":[
        "residential"
    ],
    "wof:name":"Beechwood Cheshire Home",
    "wof:placetype":"venue"
},
  "geometry": {"coordinates":[-1.8060239553,53.659198761],"type":"Point"}
}