{
  "type": "Feature",
  "properties": {
    "iso:country":"GB",
    "sg:address":"46 Hylton Street",
    "sg:city":"Birmingham",
    "sg:classifiers":[
        {
            "category":"Real Estate",
            "subcategory":"Real Estate Services",
            "type":"Services"
        },
        {
            "category":"Real Estate",
            "subcategory":"Developer",
            "type":"Services"
        }
    ],
    "sg:phone":"+44 1564 776707",
    "sg:postcode":"B18 6HN",
    "sg:province":"West Midlands",
    "sg:tags":[
        "property",
        "management"
    ],
    "wof:name":"C M Douglas Ltd.",
    "wof:placetype":"venue"
},
  "geometry": {"coordinates":[-1.91253,52.491318],"type":"Point"}
}