{
  "type": "Feature",
  "properties": {
    "addr:full":"297 Fullwell Avenue Ilford Essex IG5 0RG",
    "addr:housenumber":"297",
    "addr:postcode":"ig5 0rg",
    "addr:street":"Fullwell Avenue Ilford",
    "iso:country":"GB",
    "sg:address":"297 Fullwell Avenue",
    "sg:city":"Ilford",
    "sg:classifiers":[
        {
            "category":"Wholesale",
            "subcategory":"Machinery & Supplies",
            "type":"Manufacturing & Wholesale Goods"
        },
        {
            "category":"Shopping",
            "subcategory":"Crafts & Fabrics",
            "type":"Retail Goods"
        }
    ],
    "sg:phone":"+44 20 8550 6162",
    "sg:postcode":"IG5 0RG",
    "sg:province":"Essex",
    "sg:tags":[
        "machine",
        "supplier",
        "sewing",
        "knitting"
    ],
    "wof:name":"Mobile Sewing Machines",
    "wof:placetype":"venue"
},
  "geometry": {"coordinates":[0.065602,51.597282],"type":"Point"}
}