{
  "type": "Feature",
  "properties": {
    "iso:country":"GB",
    "sg:address":"25 Goodwood, Great Holm",
    "sg:city":"Milton Keynes",
    "sg:classifiers":[
        {
            "category":"Building & Trades",
            "subcategory":"Cleaning & Sanitation",
            "type":"Services"
        }
    ],
    "sg:postcode":"MK8 9AZ",
    "sg:province":"Buckinghamshire",
    "sg:tags":[
        "cleaner",
        "window"
    ],
    "wof:name":"Robert John Moore",
    "wof:placetype":"venue"
},
  "geometry": {"coordinates":[-0.79809,52.03326],"type":"Point"}
}