{
  "type": "Feature",
  "properties": {
    "addr:full":"47 Beechdale, Winchmore Hill London Greater London N21 3QE",
    "addr:housenumber":"47",
    "addr:postcode":"n21 3qe",
    "addr:street":"Beechdale",
    "iso:country":"GB",
    "sg:address":"47 Beechdale, Winchmore Hill",
    "sg:city":"London",
    "sg:classifiers":[
        {
            "category":"Personal",
            "type":"Services"
        }
    ],
    "sg:postcode":"N21 3QE",
    "sg:province":"Greater London",
    "sg:tags":[
        "dressmaker"
    ],
    "wof:name":"Jayton Ltd",
    "wof:placetype":"venue"
},
  "geometry": {"coordinates":[-0.1088059992,51.6270332336],"type":"Point"}
}