{
  "type": "Feature",
  "properties": {
    "addr:full":"Hillside, Hopton, Nesscliffe Shrewsbury Shropshire SY4 1DG",
    "addr:postcode":"sy4 1dg",
    "addr:street":"Nesscliffe",
    "iso:country":"GB",
    "sg:address":"Hillside, Hopton, Nesscliffe",
    "sg:city":"Shrewsbury",
    "sg:classifiers":[
        {
            "category":"Health Services",
            "subcategory":"Health Practitioner",
            "type":"Services"
        }
    ],
    "sg:postcode":"SY4 1DG",
    "sg:province":"Shropshire",
    "sg:tags":[
        "physiotherapist"
    ],
    "wof:name":"Robert Booth",
    "wof:placetype":"venue"
},
  "geometry": {"coordinates":[-2.916918,52.768398],"type":"Point"}
}