{
  "type": "Feature",
  "properties": {
    "addr:full":"29 Moor Street Coventry West Midlands CV5 6EQ",
    "addr:housenumber":"29",
    "addr:postcode":"cv5 6eq",
    "addr:street":"Moor Street",
    "iso:country":"GB",
    "sg:address":"29 Moor Street",
    "sg:city":"Coventry",
    "sg:classifiers":[
        {
            "category":"Parking",
            "type":"Transportation"
        }
    ],
    "sg:postcode":"CV5 6EQ",
    "sg:province":"West Midlands",
    "sg:tags":[
        "car",
        "valet"
    ],
    "wof:name":"Five Ways",
    "wof:placetype":"venue"
},
  "geometry": {"coordinates":[-1.5313349962,52.3989181519],"type":"Point"}
}