{
  "type": "Feature",
  "properties": {
    "addr:full":"Hanover Court, 5 Queen Street Lichfield Staffordshire WS13 6QD",
    "addr:housenumber":"5",
    "addr:postcode":"ws13 6qd",
    "addr:street":"Hanover Court;Queen Street",
    "iso:country":"GB",
    "sg:address":"Hanover Court, 5 Queen Street",
    "sg:city":"Lichfield",
    "sg:classifiers":[
        {
            "category":"Professional",
            "subcategory":"Accounting & Tax Preparation",
            "type":"Services"
        }
    ],
    "sg:phone":"+44 1543 255612",
    "sg:postcode":"WS13 6QD",
    "sg:province":"Staffordshire",
    "sg:tags":[
        "accountant"
    ],
    "wof:name":"Tomkinson Teal",
    "wof:placetype":"venue"
},
  "geometry": {"coordinates":[-1.832807,52.681389],"type":"Point"}
}