{
  "type": "Feature",
  "properties": {
    "addr:full":"Park Farm South, Willingham Road, Knaith Gainsborough Lincolnshire DN21 5EU",
    "addr:postcode":"dn21 5eu",
    "addr:street":"South Willingham Road",
    "iso:country":"GB",
    "sg:address":"Park Farm South, Willingham Road, Knaith",
    "sg:city":"Gainsborough",
    "sg:classifiers":[
        {
            "category":"Home & Garden",
            "subcategory":"Garden Supply",
            "type":"Retail Goods"
        },
        {
            "category":"Farming",
            "subcategory":"Farm",
            "type":"Manufacturing & Wholesale Goods"
        }
    ],
    "sg:phone":"+44 1427 617914",
    "sg:postcode":"DN21 5EU",
    "sg:province":"Lincolnshire",
    "sg:tags":[
        "mixed",
        "bulb",
        "crop",
        "grower"
    ],
    "wof:name":"B Fox & Sons",
    "wof:placetype":"venue"
},
  "geometry": {"coordinates":[-0.7550190091,53.3533248901],"type":"Point"}
}