{
  "type": "Feature",
  "properties": {
    "addr:full":"1 West Hill Hitchin Bedfordshire SG5 2HZ",
    "addr:housenumber":"1",
    "addr:postcode":"sg5 2hz",
    "addr:street":"West Hill",
    "iso:country":"GB",
    "sg:address":"1 West Hill",
    "sg:city":"Hitchin",
    "sg:classifiers":[
        {
            "category":"Retail",
            "subcategory":"Auto Repair",
            "type":"Services"
        }
    ],
    "sg:postcode":"SG5 2HZ",
    "sg:province":"Bedfordshire",
    "sg:tags":[
        "modification",
        "garage"
    ],
    "wof:name":"West Hill Garage",
    "wof:placetype":"venue"
},
  "geometry": {"coordinates":[-0.2829290032,51.9496383667],"type":"Point"}
}