{
  "type": "Feature",
  "properties": {
    "iso:country":"GB",
    "sg:address":"50 London Hill",
    "sg:city":"Rayleigh",
    "sg:classifiers":[
        {
            "category":"Place Of Worship",
            "type":"Public Place"
        }
    ],
    "sg:phone":"+44 1268 742229",
    "sg:postcode":"SS6 7HP",
    "sg:province":"Essex",
    "wof:name":"Our Lady of Ransom Roman Catholic Church",
    "wof:placetype":"venue"
},
  "geometry": {"coordinates":[0.60564,51.589821],"type":"Point"}
}