{
  "type": "Feature",
  "properties": {
    "addr:full":"Unit 2, Chulsey Street Bolton Lancashire BL3 4EH",
    "addr:housenumber":"unit 2",
    "addr:postcode":"bl3 4eh",
    "addr:street":"Chulsey Street",
    "iso:country":"GB",
    "sg:address":"Unit 2, Chulsey Street",
    "sg:city":"Bolton",
    "sg:classifiers":[
        {
            "category":"Building & Trades",
            "subcategory":"Construction",
            "type":"Services"
        }
    ],
    "sg:postcode":"BL3 4EH",
    "sg:province":"Lancashire",
    "sg:tags":[
        "heating",
        "contractor"
    ],
    "wof:name":"Burnertech",
    "wof:placetype":"venue"
},
  "geometry": {"coordinates":[-2.454744,53.563614],"type":"Point"}
}