{
  "type": "Feature",
  "properties": {
    "iso:country":"GB",
    "sg:address":"Glasgow Crematorium, Maryhill",
    "sg:city":"Glasgow",
    "sg:classifiers":[
        {
            "category":"Retail",
            "subcategory":"Funeral Services",
            "type":"Services"
        }
    ],
    "sg:phone":"+44 141 946 2895",
    "sg:postcode":"G23 5AA",
    "sg:province":"Glasgow City",
    "sg:tags":[
        "cemetery",
        "crematorium"
    ],
    "wof:name":"The Scottish Cremation Society Ltd.",
    "wof:placetype":"venue"
},
  "geometry": {"coordinates":[-4.2763900757,55.8990516663],"type":"Point"}
}