{
  "type": "Feature",
  "properties": {
    "addr:full":"Thainstone Agricultural Centre Inverurie Aberdeenshire AB51 5WU",
    "addr:postcode":"ab51 5wu",
    "iso:country":"GB",
    "sg:address":"Thainstone Agricultural Centre",
    "sg:city":"Inverurie",
    "sg:classifiers":[
        {
            "category":"Shopping",
            "type":"Retail Goods"
        }
    ],
    "sg:phone":"+44 1467 625544",
    "sg:postcode":"AB51 5WU",
    "sg:province":"Aberdeenshire",
    "sg:tags":[
        "merchant"
    ],
    "wof:name":"J Bibby Agriculture",
    "wof:placetype":"venue"
},
  "geometry": {"coordinates":[-2.371128,57.256893],"type":"Point"}
}