{
  "type": "Feature",
  "properties": {
    "iso:country":"GB",
    "sg:address":"38a Ford Road",
    "sg:city":"Wirral",
    "sg:classifiers":[
        {
            "category":"Retail",
            "subcategory":"Auto Repair",
            "type":"Services"
        }
    ],
    "sg:postcode":"CH49 0TF",
    "sg:province":"Merseyside",
    "sg:tags":[
        "body",
        "car"
    ],
    "wof:name":"Crash Repair Centre Limited",
    "wof:placetype":"venue"
},
  "geometry": {"coordinates":[-3.089351,53.385017],"type":"Point"}
}