{
  "type": "Feature",
  "properties": {
    "iso:country":"GB",
    "sg:address":"390 Maidstone Road",
    "sg:city":"Gillingham",
    "sg:classifiers":[
        {
            "category":"Restaurant",
            "type":"Food & Drink"
        }
    ],
    "sg:phone":"+44 1634 231313",
    "sg:postcode":"ME8 0HT",
    "sg:province":"Kent",
    "sg:tags":[
        "-",
        "english"
    ],
    "wof:name":"The Queens Head Harvester",
    "wof:placetype":"venue"
},
  "geometry": {"coordinates":[0.590635,51.352501],"type":"Point"}
}