{
  "type": "Feature",
  "properties": {
    "iso:country":"GB",
    "sg:address":"Wire Mill Lane, Newchapel",
    "sg:city":"Lingfield",
    "sg:classifiers":[
        {
            "category":"Bars & Pubs",
            "type":"Food & Drink"
        }
    ],
    "sg:phone":"+44 1342 832263",
    "sg:postcode":"RH7 6HJ",
    "sg:province":"Surrey",
    "sg:tags":[
        "pubs",
        "inn"
    ],
    "wof:name":"The Wiremill Inn",
    "wof:placetype":"venue"
},
  "geometry": {"coordinates":[-0.019686,51.17482],"type":"Point"}
}