{
  "type": "Feature",
  "properties": {
    "iso:country":"GB",
    "sg:address":"Unit 6 High Grounds Way, High Grounds Industrial Estate",
    "sg:city":"Worksop",
    "sg:classifiers":[
        {
            "category":"Home & Garden",
            "subcategory":"Home Furnishings",
            "type":"Retail Goods"
        }
    ],
    "sg:phone":"+44 1909 500666",
    "sg:postcode":"S80 3AF",
    "sg:province":"Nottinghamshire",
    "sg:tags":[
        "furnishers",
        "planner",
        "kitchen"
    ],
    "wof:name":"The Little Kitchen Factory",
    "wof:placetype":"venue"
},
  "geometry": {"coordinates":[-1.14672,53.31023],"type":"Point"}
}