{
  "type": "Feature",
  "properties": {
    "addr:full":"49 Kirkgate, Silsden Keighley North Yorkshire BD20 0AQ",
    "addr:housenumber":"49",
    "addr:postcode":"bd20 0aq",
    "addr:street":"Kirkgate",
    "iso:country":"GB",
    "sg:address":"49 Kirkgate, Silsden",
    "sg:city":"Keighley",
    "sg:classifiers":[
        {
            "category":"Shopping",
            "subcategory":"Pharmacy",
            "type":"Retail Goods"
        }
    ],
    "sg:phone":"+44 1535 653616",
    "sg:postcode":"BD20 0AQ",
    "sg:province":"North Yorkshire",
    "sg:tags":[
        "pharmacist",
        "chemist"
    ],
    "wof:name":"Buchanan (Bingley)",
    "wof:placetype":"venue"
},
  "geometry": {"coordinates":[-1.937827,53.913277],"type":"Point"}
}