{
  "type": "Feature",
  "properties": {
    "iso:country":"GB",
    "sg:address":"122 South Street, Tarring",
    "sg:city":"Worthing",
    "sg:classifiers":[
        {
            "category":"Fast Food",
            "type":"Food & Drink"
        }
    ],
    "sg:postcode":"BN14 7NB",
    "sg:province":"West Sussex",
    "sg:tags":[
        "away",
        "take"
    ],
    "wof:name":"Happy Valley",
    "wof:placetype":"venue"
},
  "geometry": {"coordinates":[-0.392227,50.821701],"type":"Point"}
}