{
  "type": "Feature",
  "properties": {
    "iso:country":"GB",
    "sg:address":"42 Whins Road",
    "sg:city":"Alloa",
    "sg:classifiers":[
        {
            "category":"Travel",
            "subcategory":"Travel Agent",
            "type":"Entertainment"
        }
    ],
    "sg:postcode":"FK10 3RE",
    "sg:province":"Clackmannanshire",
    "wof:name":"Instant Holidays",
    "wof:placetype":"venue"
},
  "geometry": {"coordinates":[-3.782603,56.119274],"type":"Point"}
}