{
  "type": "Feature",
  "properties": {
    "addr:full":"High Cross Street Brampton Cumbria CA8 1RP",
    "addr:postcode":"ca8 1rp",
    "addr:street":"High Cross Street",
    "iso:country":"GB",
    "sg:address":"High Cross Street",
    "sg:city":"Brampton",
    "sg:classifiers":[
        {
            "category":"Professional",
            "subcategory":"Art Services",
            "type":"Services"
        }
    ],
    "sg:phone":"+44 16977 41554",
    "sg:postcode":"CA8 1RP",
    "sg:province":"Cumbria",
    "sg:tags":[
        "framing"
    ],
    "wof:name":"Studio 2000",
    "wof:placetype":"venue"
},
  "geometry": {"coordinates":[-2.734503,54.942696],"type":"Point"}
}