{
  "type": "Feature",
  "properties": {
    "addr:full":"31-33 The Mall, Clifton Village Bristol City of Bristol BS8 4JG",
    "addr:housenumber":"31-33",
    "addr:postcode":"bs8 4jg",
    "addr:street":"The Mall",
    "iso:country":"GB",
    "sg:address":"31-33 The Mall, Clifton Village",
    "sg:city":"Bristol",
    "sg:classifiers":[
        {
            "category":"Shopping",
            "subcategory":"Gifts & Souvenirs",
            "type":"Retail Goods"
        }
    ],
    "sg:phone":"+44 117 923 8055",
    "sg:postcode":"BS8 4JG",
    "sg:province":"City of Bristol",
    "sg:tags":[
        "shop"
    ],
    "wof:name":"Abode Creations Ltd.",
    "wof:placetype":"venue"
},
  "geometry": {"coordinates":[-2.621592,51.456348],"type":"Point"}
}