{
  "type": "Feature",
  "properties": {
    "addr:full":"The Compound, Hempton Road Fakenham Norfolk NR21 7LA",
    "addr:postcode":"nr21 7la",
    "addr:street":"Hempton Road",
    "iso:country":"GB",
    "sg:address":"The Compound, Hempton Road",
    "sg:city":"Fakenham",
    "sg:classifiers":[
        {
            "category":"Home & Garden",
            "subcategory":"Building Materials",
            "type":"Retail Goods"
        }
    ],
    "sg:phone":"+44 1328 856516",
    "sg:postcode":"NR21 7LA",
    "sg:province":"Norfolk",
    "sg:tags":[
        "shutter",
        "door"
    ],
    "wof:name":"Wards of Fakenham",
    "wof:placetype":"venue"
},
  "geometry": {"coordinates":[0.8364800215,52.8267707825],"type":"Point"}
}