{
  "type": "Feature",
  "properties": {
    "iso:country":"GB",
    "sg:address":"14 High St",
    "sg:city":"Kingswinford",
    "sg:classifiers":[
        {
            "category":"Bars & Pubs",
            "type":"Food & Drink"
        }
    ],
    "sg:phone":"+44 1384 287319",
    "sg:postcode":"DY6 0HB",
    "sg:province":"Staffordshire",
    "sg:tags":[
        "pubs",
        "inn"
    ],
    "wof:name":"Wallheath Tavern",
    "wof:placetype":"venue"
},
  "geometry": {"coordinates":[-2.17937,52.504154],"type":"Point"}
}