{
  "type": "Feature",
  "properties": {
    "addr:full":"54 Rhos Road, Rhos On Sea Colwyn Bay Conwy LL28 4RY",
    "addr:housenumber":"54",
    "addr:postcode":"ll28 4ry",
    "addr:street":"Rhos Road",
    "iso:country":"GB",
    "sg:address":"54 Rhos Road, Rhos On Sea",
    "sg:city":"Colwyn Bay",
    "sg:classifiers":[
        {
            "category":"Health Services",
            "subcategory":"Nursing And Care Facility",
            "type":"Services"
        },
        {
            "category":"Social Services",
            "subcategory":"Retirement Home",
            "type":"Services"
        }
    ],
    "sg:phone":"+44 1492 546877",
    "sg:postcode":"LL28 4RY",
    "sg:province":"Conwy",
    "sg:tags":[
        "residential",
        "rest"
    ],
    "wof:name":"Brompton Lodge Rest Home",
    "wof:placetype":"venue"
},
  "geometry": {"coordinates":[-3.74464,53.30822],"type":"Point"}
}