{
  "type": "Feature",
  "properties": {
    "iso:country":"GB",
    "sg:address":"102 Harrow Court",
    "sg:city":"Stevenage",
    "sg:classifiers":[
        {
            "category":"Health Services",
            "subcategory":"Podiatrist",
            "type":"Services"
        }
    ],
    "sg:postcode":"SG1 1JT",
    "sg:province":"Hertfordshire",
    "sg:tags":[
        "podiatrists",
        "chiropodist"
    ],
    "wof:name":"Jacqueline Sellers",
    "wof:placetype":"venue"
},
  "geometry": {"coordinates":[-0.197171,51.904572],"type":"Point"}
}