{
  "type": "Feature",
  "properties": {
    "addr:full":"2 The Hilton, Warren St Tenby Pembrokeshire SA70 7JY",
    "addr:housenumber":"2",
    "addr:postcode":"sa70 7jy",
    "addr:street":"The;Warren St",
    "iso:country":"GB",
    "sg:address":"2 The Hilton, Warren St",
    "sg:city":"Tenby",
    "sg:classifiers":[
        {
            "category":"Professional",
            "subcategory":"Printing & Photocopies",
            "type":"Services"
        }
    ],
    "sg:postcode":"SA70 7JY",
    "sg:province":"Pembrokeshire",
    "sg:tags":[
        "tag",
        "label"
    ],
    "wof:name":"Label It Printers",
    "wof:placetype":"venue"
},
  "geometry": {"coordinates":[-4.71205616,51.6767997742],"type":"Point"}
}