{
  "type": "Feature",
  "properties": {
    "addr:full":"146 Walm Lane London Greater London NW2 4RU",
    "addr:housenumber":"146",
    "addr:postcode":"nw2 4ru",
    "addr:street":"Walm Lane",
    "iso:country":"GB",
    "sg:address":"146 Walm Lane",
    "sg:city":"London",
    "sg:classifiers":[
        {
            "category":"Health Services",
            "subcategory":"Doctor",
            "type":"Services"
        }
    ],
    "sg:postcode":"NW2 4RU",
    "sg:province":"Greater London",
    "sg:tags":[
        "practitioners"
    ],
    "wof:name":"J Slome",
    "wof:placetype":"venue"
},
  "geometry": {"coordinates":[-0.2190629989,51.5513038635],"type":"Point"}
}