{
  "type": "Feature",
  "properties": {
    "iso:country":"GB",
    "sg:address":"Vittoria House, Vittoria Walk",
    "sg:city":"Cheltenham",
    "sg:classifiers":[
        {
            "category":"Real Estate",
            "subcategory":"Surveying",
            "type":"Services"
        }
    ],
    "sg:phone":"+44 1242 521102",
    "sg:postcode":"GL50 1TW",
    "sg:province":"Gloucestershire",
    "sg:tags":[
        "surveyor",
        "valuer"
    ],
    "wof:name":"Bayley Donaldson",
    "wof:placetype":"venue"
},
  "geometry": {"coordinates":[-2.076492,51.895889],"type":"Point"}
}