{
  "type": "Feature",
  "properties": {
    "addr:full":"Trinity Lane Leicester Leicestershire LE1 6WP",
    "addr:postcode":"le1 6wp",
    "addr:street":"Trinity Lane",
    "iso:country":"GB",
    "sg:address":"Trinity Lane",
    "sg:city":"Leicester",
    "sg:classifiers":[
        {
            "category":"Professional",
            "subcategory":"Art Services",
            "type":"Services"
        }
    ],
    "sg:phone":"+44 116 254 1286",
    "sg:postcode":"LE1 6WP",
    "sg:province":"Leicestershire",
    "sg:tags":[
        "graphic",
        "designer"
    ],
    "wof:name":"H N Advertising Studios Ltd.",
    "wof:placetype":"venue"
},
  "geometry": {"coordinates":[-1.132069,52.628609],"type":"Point"}
}