{
  "type": "Feature",
  "properties": {
    "addr:full":"Lochill, Cumnock Road Cumnock East Ayrshire KA18 4BQ",
    "addr:postcode":"ka18 4bq",
    "addr:street":"Cumnock Road",
    "iso:country":"GB",
    "sg:address":"Lochill, Cumnock Road",
    "sg:city":"Cumnock",
    "sg:classifiers":[
        {
            "category":"Sports & Exercise",
            "subcategory":"Golf",
            "type":"Entertainment"
        }
    ],
    "sg:postcode":"KA18 4BQ",
    "sg:province":"East Ayrshire",
    "sg:tags":[
        "club",
        "course"
    ],
    "wof:name":"New Cumnock Golf Club",
    "wof:placetype":"venue"
},
  "geometry": {"coordinates":[-4.1835689545,55.3990058899],"type":"Point"}
}