{
  "type": "Feature",
  "properties": {
    "iso:country":"GB",
    "sg:address":"9 Rides Court, Moulton",
    "sg:city":"Northampton",
    "sg:classifiers":[
        {
            "category":"Building & Trades",
            "subcategory":"Construction",
            "type":"Services"
        }
    ],
    "sg:postcode":"NN3 7UA",
    "sg:province":"Northamptonshire",
    "sg:tags":[
        "decorator",
        "painter"
    ],
    "wof:name":"N R Haynes",
    "wof:placetype":"venue"
},
  "geometry": {"coordinates":[-0.8550670147,52.2793388367],"type":"Point"}
}