{
  "type": "Feature",
  "properties": {
    "iso:country":"GB",
    "sg:address":"P O Box 95, Wergs Hall, Wergs Hall Rd",
    "sg:city":"Wolverhampton",
    "sg:classifiers":[
        {
            "category":"Manufacturing",
            "subcategory":"Building Materials",
            "type":"Manufacturing & Wholesale Goods"
        }
    ],
    "sg:phone":"+44 1902 774000",
    "sg:postcode":"WV8 2HZ",
    "sg:province":"Shropshire",
    "sg:tags":[
        "distributor",
        "concrete",
        "mnfrs"
    ],
    "wof:name":"Tarmac Building Materials Ltd",
    "wof:placetype":"venue"
},
  "geometry": {"coordinates":[-2.19501,52.6101],"type":"Point"}
}