{
  "type": "Feature",
  "properties": {
    "addr:full":"22a Longworth Road, Horwich Bolton Lancashire BL6 7BA",
    "addr:housenumber":"22a",
    "addr:postcode":"bl6 7ba",
    "addr:street":"Longworth Road",
    "iso:country":"GB",
    "sg:address":"22a Longworth Road, Horwich",
    "sg:city":"Bolton",
    "sg:classifiers":[
        {
            "category":"Building & Trades",
            "subcategory":"Construction",
            "type":"Services"
        }
    ],
    "sg:phone":"+44 1204 667522",
    "sg:postcode":"BL6 7BA",
    "sg:province":"Lancashire",
    "sg:tags":[
        "joiner",
        "carpenter"
    ],
    "wof:name":"Fielding Joinery Ltd.",
    "wof:placetype":"venue"
},
  "geometry": {"coordinates":[-2.5470790863,53.6006851196],"type":"Point"}
}