{
  "type": "Feature",
  "properties": {
    "iso:country":"GB",
    "sg:address":"67 East Road",
    "sg:city":"Irvine",
    "sg:classifiers":[
        {
            "category":"Food & Beverages",
            "subcategory":"Groceries & Convenience Stores",
            "type":"Retail Goods"
        }
    ],
    "sg:phone":"+44 1294 274383",
    "sg:postcode":"KA12 0AA",
    "sg:province":"North Ayrshire",
    "wof:name":"Thomas Farquhar",
    "wof:placetype":"venue"
},
  "geometry": {"coordinates":[-4.66544,55.615814],"type":"Point"}
}