{
  "type": "Feature",
  "properties": {
    "addr:full":"74 Holland Street Salford Greater Manchester M6 6FE",
    "addr:housenumber":"74",
    "addr:postcode":"m6 6fe",
    "addr:street":"Holland Street",
    "iso:country":"GB",
    "sg:address":"74 Holland Street",
    "sg:city":"Salford",
    "sg:classifiers":[
        {
            "category":"Bars & Pubs",
            "type":"Food & Drink"
        },
        {
            "category":"Community Center",
            "subcategory":"Social",
            "type":"Public Place"
        }
    ],
    "sg:phone":"+44 161 745 7623",
    "sg:postcode":"M6 6FE",
    "sg:province":"Greater Manchester",
    "sg:tags":[
        "pubs",
        "house",
        "inn",
        "activity"
    ],
    "wof:name":"F & J MOON",
    "wof:placetype":"venue"
},
  "geometry": {"coordinates":[-2.287405,53.49728],"type":"Point"}
}