{
  "type": "Feature",
  "properties": {
    "iso:country":"GB",
    "sg:address":"17 The Crescent",
    "sg:city":"Walsall",
    "sg:classifiers":[
        {
            "category":"Professional",
            "subcategory":"Computer Services",
            "type":"Services"
        }
    ],
    "sg:phone":"+44 1922 637820",
    "sg:postcode":"WS1 2BX",
    "sg:province":"West Midlands",
    "sg:tags":[
        "system",
        "software"
    ],
    "wof:name":"Crescent Software Services Ltd.",
    "wof:placetype":"venue"
},
  "geometry": {"coordinates":[-1.9684000015,52.5797538757],"type":"Point"}
}