{
  "type": "Feature",
  "properties": {
    "iso:country":"GB",
    "sg:address":"79 High Street, Bugbrooke",
    "sg:city":"Northampton",
    "sg:classifiers":[
        {
            "category":"Shopping",
            "subcategory":"Pets & Pet Supplies",
            "type":"Retail Goods"
        }
    ],
    "sg:phone":"+44 1604 832702",
    "sg:postcode":"NN7 3PG",
    "sg:province":"Buckinghamshire",
    "sg:tags":[
        "shop"
    ],
    "wof:name":"Pet Stop",
    "wof:placetype":"venue"
},
  "geometry": {"coordinates":[-1.010119,52.208942],"type":"Point"}
}