{
  "type": "Feature",
  "properties": {
    "addr:full":"Princes St Bexleyheath Kent DA7 4BQ",
    "addr:postcode":"da7 4bq",
    "addr:street":"Princes St",
    "iso:country":"GB",
    "sg:address":"Princes St",
    "sg:city":"Bexleyheath",
    "sg:classifiers":[
        {
            "category":"Retail",
            "subcategory":"Auto Repair",
            "type":"Services"
        }
    ],
    "sg:phone":"+44 20 8303 8497",
    "sg:postcode":"DA7 4BQ",
    "sg:province":"Kent",
    "sg:tags":[
        "car",
        "upholsterer"
    ],
    "wof:name":"Cooper J Coach Trimming",
    "wof:placetype":"venue"
},
  "geometry": {"coordinates":[0.13721,51.459885],"type":"Point"}
}