{
  "type": "Feature",
  "properties": {
    "iso:country":"GB",
    "sg:address":"24 Broadwater Road",
    "sg:city":"Worthing",
    "sg:classifiers":[
        {
            "category":"Health Services",
            "subcategory":"Doctor",
            "type":"Services"
        }
    ],
    "sg:phone":"+44 1903 203131",
    "sg:postcode":"BN14 8AB",
    "sg:province":"West Sussex",
    "sg:tags":[
        "practitioners"
    ],
    "wof:name":"Willis, K",
    "wof:placetype":"venue"
},
  "geometry": {"coordinates":[-0.372735,50.820702],"type":"Point"}
}