{
  "type": "Feature",
  "properties": {
    "iso:country":"GB",
    "sg:address":"87 Commercial Road",
    "sg:city":"Poole",
    "sg:classifiers":[
        {
            "category":"Shopping",
            "subcategory":"Antiques",
            "type":"Retail Goods"
        },
        {
            "category":"Military Area",
            "subcategory":"Restricted Area",
            "type":"Public Place"
        }
    ],
    "sg:phone":"+44 1202 723335",
    "sg:postcode":"BH14 0JD",
    "sg:province":"Dorset",
    "wof:name":"The Queen's Shilling",
    "wof:placetype":"venue"
},
  "geometry": {"coordinates":[-1.953322,50.72327],"type":"Point"}
}