{
  "type": "Feature",
  "properties": {
    "iso:country":"GB",
    "sg:address":"Rdl House",
    "sg:city":"Woking",
    "sg:classifiers":[
        {
            "category":"Professional",
            "subcategory":"Employment Agencies",
            "type":"Services"
        }
    ],
    "sg:postcode":"GU21 5AD",
    "sg:province":"Surrey",
    "sg:tags":[
        "consultant"
    ],
    "wof:name":"Flv Computers Ltd.",
    "wof:placetype":"venue"
},
  "geometry": {"coordinates":[-0.535919,51.32811],"type":"Point"}
}