{
  "type": "Feature",
  "properties": {
    "iso:country":"GB",
    "sg:address":"67 Farnham Road",
    "sg:city":"Guildford",
    "sg:classifiers":[
        {
            "category":"Social Services",
            "subcategory":"Retirement Home",
            "type":"Services"
        }
    ],
    "sg:phone":"+44 1483 579149",
    "sg:postcode":"GU2 7LX",
    "sg:province":"Surrey",
    "sg:tags":[
        "residential",
        "care"
    ],
    "wof:name":"Westover",
    "wof:placetype":"venue"
},
  "geometry": {"coordinates":[-0.585915029,51.2347068787],"type":"Point"}
}