{
  "type": "Feature",
  "properties": {
    "iso:country":"GB",
    "sg:address":"Unit 9 Tower Workshops, 58 Riley Road",
    "sg:city":"London",
    "sg:classifiers":[
        {
            "category":"Professional",
            "subcategory":"Printing & Photocopies",
            "type":"Services"
        }
    ],
    "sg:phone":"+44 20 7252 8222",
    "sg:postcode":"SE1 3DG",
    "sg:province":"Greater London",
    "sg:tags":[
        "printer"
    ],
    "wof:name":"Apollo Print Generation Ltd.",
    "wof:placetype":"venue"
},
  "geometry": {"coordinates":[-0.07759,51.498829],"type":"Point"}
}