{
  "type": "Feature",
  "properties": {
    "addr:full":"32 Crossgate Cupar Fife KY15 5HH",
    "addr:housenumber":"32",
    "addr:postcode":"ky15 5hh",
    "addr:street":"Crossgate Cupar",
    "iso:country":"GB",
    "sg:address":"32 Crossgate",
    "sg:city":"Cupar",
    "sg:classifiers":[
        {
            "category":"Shopping",
            "subcategory":"Shoes",
            "type":"Retail Goods"
        }
    ],
    "sg:postcode":"KY15 5HH",
    "sg:province":"Fife",
    "sg:tags":[
        "shop"
    ],
    "wof:name":"D E Shoes",
    "wof:placetype":"venue"
},
  "geometry": {"coordinates":[-3.011461,56.318882],"type":"Point"}
}