{
  "type": "Feature",
  "properties": {
    "iso:country":"GB",
    "sg:address":"Hanbury Road",
    "sg:city":"Droitwich",
    "sg:classifiers":[
        {
            "category":"Bars & Pubs",
            "type":"Food & Drink"
        }
    ],
    "sg:phone":"+44 1905 770130",
    "sg:postcode":"WR9 7DX",
    "sg:province":"Worcestershire",
    "sg:tags":[
        "pubs",
        "inn"
    ],
    "wof:name":"Audra Colbourne",
    "wof:placetype":"venue"
},
  "geometry": {"coordinates":[-2.124509,52.265881],"type":"Point"}
}