{
  "type": "Feature",
  "properties": {
    "addr:full":"35 Commercial Street Tredegar Blaenau Gwent NP22 3DJ",
    "addr:housenumber":"35",
    "addr:postcode":"np22 3dj",
    "addr:street":"Commercial Street;Gwent",
    "iso:country":"GB",
    "sg:address":"35 Commercial Street",
    "sg:city":"Tredegar",
    "sg:classifiers":[
        {
            "category":"Food & Beverages",
            "subcategory":"Meat & Fish",
            "type":"Retail Goods"
        },
        {
            "category":"Food & Beverages",
            "subcategory":"Groceries & Convenience Stores",
            "type":"Retail Goods"
        }
    ],
    "sg:phone":"+44 1495 724197",
    "sg:postcode":"NP22 3DJ",
    "sg:province":"Blaenau Gwent",
    "sg:tags":[
        "shop",
        "chip"
    ],
    "wof:name":"Central Fish Bar",
    "wof:placetype":"venue"
},
  "geometry": {"coordinates":[-3.24646,51.774635],"type":"Point"}
}