{
  "type": "Feature",
  "properties": {
    "iso:country":"GB",
    "sg:address":"1 Greenways, Wolsingham",
    "sg:city":"Bishop Auckland",
    "sg:classifiers":[
        {
            "category":"Social Services",
            "subcategory":"Job Training",
            "type":"Services"
        },
        {
            "category":"Education",
            "subcategory":"Special Training",
            "type":"Public Place"
        }
    ],
    "sg:phone":"+44 1388 526903",
    "sg:postcode":"DL13 3HN",
    "sg:province":"Durham",
    "sg:tags":[
        "product",
        "centre"
    ],
    "wof:name":"Weston Associates",
    "wof:placetype":"venue"
},
  "geometry": {"coordinates":[-1.8779129982,54.7340583801],"type":"Point"}
}