{
  "type": "Feature",
  "properties": {
    "iso:country":"GB",
    "sg:address":"45 Millcroft",
    "sg:city":"Ely",
    "sg:classifiers":[
        {
            "category":"Military Area",
            "subcategory":"Air Force Base",
            "type":"Public Place"
        }
    ],
    "sg:phone":"+44 1353 723036",
    "sg:postcode":"CB7 5AP",
    "sg:province":"Cambridgeshire",
    "sg:tags":[
        "taxi",
        "hire",
        "private"
    ],
    "wof:name":"Oland Taxis",
    "wof:placetype":"venue"
},
  "geometry": {"coordinates":[0.34941,52.334839],"type":"Point"}
}