{
  "type": "Feature",
  "properties": {
    "iso:country":"GB",
    "sg:address":"54 Bridge Street",
    "sg:city":"Belper",
    "sg:classifiers":[
        {
            "category":"Home & Garden",
            "subcategory":"Furniture",
            "type":"Retail Goods"
        }
    ],
    "sg:phone":"+44 1773 822581",
    "sg:postcode":"DE56 1AZ",
    "sg:province":"Derbyshire",
    "wof:name":"Greaves House Furnishers",
    "wof:placetype":"venue"
},
  "geometry": {"coordinates":[-1.484911,53.025406],"type":"Point"}
}