{
  "type": "Feature",
  "properties": {
    "addr:full":"9 Kempton Clo Benfleet Essex SS7 3SG",
    "addr:housenumber":"9",
    "addr:postcode":"ss7 3sg",
    "addr:street":"Kempton Clo Benfleet",
    "iso:country":"GB",
    "sg:address":"9 Kempton Clo",
    "sg:city":"Benfleet",
    "sg:classifiers":[
        {
            "category":"Retail",
            "subcategory":"Driving School",
            "type":"Services"
        }
    ],
    "sg:phone":"+44 1268 774614",
    "sg:postcode":"SS7 3SG",
    "sg:province":"Essex",
    "wof:name":"Bill's Driving School",
    "wof:placetype":"venue"
},
  "geometry": {"coordinates":[0.5946620107,51.5753746033],"type":"Point"}
}