{
  "type": "Feature",
  "properties": {
    "iso:country":"GB",
    "sg:address":"Regent House, 5 Broadhurst Gardens, Swiss Cottage",
    "sg:city":"London",
    "sg:classifiers":[
        {
            "category":"Professional",
            "subcategory":"Lawyer & Legal Services",
            "type":"Services"
        }
    ],
    "sg:phone":"+44 20 7328 9111",
    "sg:postcode":"NW6 3RZ",
    "sg:province":"Greater London",
    "sg:tags":[
        "solicitor"
    ],
    "wof:name":"Roiter Zucker",
    "wof:placetype":"venue"
},
  "geometry": {"coordinates":[-0.18883,51.546391],"type":"Point"}
}