{
  "type": "Feature",
  "properties": {
    "addr:full":"3-7 Bridge Street Castleford West Yorkshire WF10 1JP",
    "addr:housenumber":"3-7",
    "addr:postcode":"wf10 1jp",
    "addr:street":"Bridge Street",
    "iso:country":"GB",
    "sg:address":"3-7 Bridge Street",
    "sg:city":"Castleford",
    "sg:classifiers":[
        {
            "category":"Autos & Motor Vehicles",
            "subcategory":"Motorcycle Sales",
            "type":"Retail Goods"
        }
    ],
    "sg:phone":"+44 1977 553523",
    "sg:postcode":"WF10 1JP",
    "sg:province":"West Yorkshire",
    "wof:name":"Castle Motorcycles",
    "wof:placetype":"venue"
},
  "geometry": {"coordinates":[-1.3490389585,53.7275390625],"type":"Point"}
}