{
  "type": "Feature",
  "properties": {
    "iso:country":"GB",
    "sg:address":"Tudweiliog, Nefyn",
    "sg:city":"Pwllheli",
    "sg:classifiers":[
        {
            "category":"Professional",
            "subcategory":"Engineering",
            "type":"Services"
        }
    ],
    "sg:phone":"+44 1758 770659",
    "sg:postcode":"LL53 8NB",
    "sg:province":"Gwynedd",
    "wof:name":"The Smithy",
    "wof:placetype":"venue"
},
  "geometry": {"coordinates":[-4.6216039658,52.8992614746],"type":"Point"}
}