{
  "type": "Feature",
  "properties": {
    "addr:full":"Old Hills Farm, Stonebow, Ashleworth Gloucester Gloucestershire GL19 4LB",
    "addr:postcode":"gl19 4lb",
    "addr:street":"Old Hills Farm Stonebow",
    "iso:country":"GB",
    "sg:address":"Old Hills Farm, Stonebow, Ashleworth",
    "sg:city":"Gloucester",
    "sg:classifiers":[
        {
            "category":"Farming",
            "subcategory":"Livestock Farm",
            "type":"Manufacturing & Wholesale Goods"
        }
    ],
    "sg:phone":"+44 1452 700282",
    "sg:postcode":"GL19 4LB",
    "sg:province":"Gloucestershire",
    "sg:tags":[
        "others"
    ],
    "wof:name":"J P Bullock",
    "wof:placetype":"venue"
},
  "geometry": {"coordinates":[-2.2744410038,51.929851532],"type":"Point"}
}