{
  "type": "Feature",
  "properties": {
    "iso:country":"GB",
    "sg:address":"373 Wimborne Rd",
    "sg:city":"Bournemouth",
    "sg:classifiers":[
        {
            "category":"Shopping",
            "type":"Retail Goods"
        }
    ],
    "sg:phone":"+44 1202 536620",
    "sg:postcode":"BH9 2AQ",
    "sg:province":"Dorset",
    "sg:tags":[
        "part",
        "accessory"
    ],
    "wof:name":"Happy Motoring",
    "wof:placetype":"venue"
},
  "geometry": {"coordinates":[-1.878933,50.741528],"type":"Point"}
}