{
  "type": "Feature",
  "properties": {
    "iso:country":"GB",
    "sg:address":"Pike House, Dixton Road",
    "sg:city":"Monmouth",
    "sg:classifiers":[
        {
            "category":"Retail",
            "subcategory":"Storage",
            "type":"Services"
        }
    ],
    "sg:phone":"+44 1600 715509",
    "sg:postcode":"NP25 3SJ",
    "sg:province":"Gloucestershire",
    "sg:tags":[
        "household",
        "removal"
    ],
    "wof:name":"Old Dixton Removals & Light Haulage",
    "wof:placetype":"venue"
},
  "geometry": {"coordinates":[-2.707923,51.816769],"type":"Point"}
}