{
  "type": "Feature",
  "properties": {
    "addr:full":"46 Gray Street Glasgow Glasgow City G3 7SE",
    "addr:housenumber":"46",
    "addr:postcode":"g3 7se",
    "addr:street":"Gray Street",
    "iso:country":"GB",
    "sg:address":"46 Gray Street",
    "sg:city":"Glasgow",
    "sg:classifiers":[
        {
            "category":"Travel",
            "subcategory":"Hotels & Motels",
            "type":"Entertainment"
        }
    ],
    "sg:phone":"+44 141 339 2395",
    "sg:postcode":"G3 7SE",
    "sg:province":"Glasgow City",
    "sg:tags":[
        "house",
        "guest"
    ],
    "wof:name":"Alamo Guest House",
    "wof:placetype":"venue"
},
  "geometry": {"coordinates":[-4.286143,55.866993],"type":"Point"}
}