{
  "type": "Feature",
  "properties": {
    "iso:country":"GB",
    "sg:address":"77-79 Station Approach",
    "sg:city":"Ruislip",
    "sg:classifiers":[
        {
            "category":"Taxi",
            "type":"Transportation"
        }
    ],
    "sg:phone":"+44 181 841 4444",
    "sg:postcode":"HA4 6SD",
    "sg:province":"Greater London",
    "sg:tags":[
        "mini",
        "cab"
    ],
    "wof:name":"Global Radio Cars",
    "wof:placetype":"venue"
},
  "geometry": {"coordinates":[-0.3986960053,51.5565032959],"type":"Point"}
}