{
  "type": "Feature",
  "properties": {
    "addr:full":"16 Alliance Court, Alliance Road London Greater London W3 0RB",
    "addr:housenumber":"16",
    "addr:postcode":"w3 0rb",
    "addr:street":"Alliance Court Alliance Road",
    "iso:country":"GB",
    "sg:address":"16 Alliance Court, Alliance Road",
    "sg:city":"London",
    "sg:classifiers":[
        {
            "category":"Manufacturing",
            "subcategory":"Metals",
            "type":"Manufacturing & Wholesale Goods"
        }
    ],
    "sg:phone":"+44 20 8896 0222",
    "sg:postcode":"W3 0RB",
    "sg:province":"Greater London",
    "wof:name":"Guartel Ltd.",
    "wof:placetype":"venue"
},
  "geometry": {"coordinates":[-0.2756370008,51.5249633789],"type":"Point"}
}