{
  "type": "Feature",
  "properties": {
    "addr:full":"16 Market P Guisborough North Yorkshire TS14 6AD",
    "addr:housenumber":"16",
    "addr:postcode":"ts14 6ad",
    "addr:street":"Market P Guisborough",
    "iso:country":"GB",
    "sg:address":"16 Market P",
    "sg:city":"Guisborough",
    "sg:classifiers":[
        {
            "category":"Fast Food",
            "type":"Food & Drink"
        }
    ],
    "sg:phone":"+44 1287 633210",
    "sg:postcode":"TS14 6AD",
    "sg:province":"North Yorkshire",
    "sg:tags":[
        "away",
        "take"
    ],
    "wof:name":"Benvenuto",
    "wof:placetype":"venue"
},
  "geometry": {"coordinates":[-1.0526319742,54.5356941223],"type":"Point"}
}