{
  "type": "Feature",
  "properties": {
    "addr:full":"76 Broad Street Fraserburgh Aberdeenshire AB43 9AS",
    "addr:housenumber":"76",
    "addr:postcode":"ab43 9as",
    "addr:street":"Broad Street",
    "iso:country":"GB",
    "sg:address":"76 Broad Street",
    "sg:city":"Fraserburgh",
    "sg:classifiers":[
        {
            "category":"Shopping",
            "type":"Retail Goods"
        }
    ],
    "sg:postcode":"AB43 9AS",
    "sg:province":"Aberdeenshire",
    "sg:tags":[
        "part",
        "accessory"
    ],
    "wof:name":"Topgear",
    "wof:placetype":"venue"
},
  "geometry": {"coordinates":[-2.005021,57.691483],"type":"Point"}
}