{
  "type": "Feature",
  "properties": {
    "addr:full":"33 Lees La, Southoe Huntingdon Cambridgeshire PE18 9YG",
    "addr:housenumber":"33",
    "addr:postcode":"pe18 9yg",
    "addr:street":"Lees La Southoe Huntingdon",
    "iso:country":"GB",
    "sg:address":"33 Lees La, Southoe",
    "sg:city":"Huntingdon",
    "sg:classifiers":[
        {
            "category":"Building & Trades",
            "subcategory":"Construction",
            "type":"Services"
        }
    ],
    "sg:phone":"+44 1480 471700",
    "sg:postcode":"PE18 9YG",
    "sg:province":"Cambridgeshire",
    "sg:tags":[
        "contractor",
        "paving",
        "driveway"
    ],
    "wof:name":"Sedgemoor Homes Ltd",
    "wof:placetype":"venue"
},
  "geometry": {"coordinates":[-0.2678200006,52.2644996643],"type":"Point"}
}