{
  "type": "Feature",
  "properties": {
    "addr:full":"102a Bentham Drive Liverpool Merseyside L16 5EX",
    "addr:housenumber":"102a",
    "addr:postcode":"l16 5ex",
    "addr:street":"Bentham Drive",
    "iso:country":"GB",
    "sg:address":"102a Bentham Drive",
    "sg:city":"Liverpool",
    "sg:classifiers":[
        {
            "category":"Personal",
            "subcategory":"Beauty Salon",
            "type":"Services"
        },
        {
            "category":"Personal",
            "subcategory":"Barber",
            "type":"Services"
        }
    ],
    "sg:phone":"+44 151 722 3433",
    "sg:postcode":"L16 5EX",
    "sg:province":"Merseyside",
    "sg:tags":[
        "unisex",
        "hairdresser"
    ],
    "wof:name":"Shape 'N' Shade",
    "wof:placetype":"venue"
},
  "geometry": {"coordinates":[-2.894289,53.402313],"type":"Point"}
}