{
  "type": "Feature",
  "properties": {
    "addr:full":"167 Uplands Road, Oadby Leicester Leicestershire LE2 4NW",
    "addr:housenumber":"167",
    "addr:postcode":"le2 4nw",
    "addr:street":"Uplands Road",
    "iso:country":"GB",
    "sg:address":"167 Uplands Road, Oadby",
    "sg:city":"Leicester",
    "sg:classifiers":[
        {
            "category":"Bars & Pubs",
            "type":"Food & Drink"
        }
    ],
    "sg:phone":"+44 116 271 8928",
    "sg:postcode":"LE2 4NW",
    "sg:province":"Leicestershire",
    "sg:tags":[
        "pubs",
        "inn"
    ],
    "wof:name":"The Blues",
    "wof:placetype":"venue"
},
  "geometry": {"coordinates":[-1.0627319813,52.5990066528],"type":"Point"}
}