{
  "type": "Feature",
  "properties": {
    "iso:country":"GB",
    "sg:address":"44 Tulketh Brow, Ashton On Ribble",
    "sg:city":"Preston",
    "sg:classifiers":[
        {
            "category":"Shopping",
            "subcategory":"Clothing, Apparel, & Fashions",
            "type":"Retail Goods"
        }
    ],
    "sg:phone":"+44 1772 723773",
    "sg:postcode":"PR2 2SD",
    "sg:province":"Lancashire",
    "sg:tags":[
        "shop",
        "dress",
        "outlet",
        "fancy"
    ],
    "sg:website":"http://www.threesistersemporium.co.uk",
    "wof:name":"Cabaret Fancy Dress Hire",
    "wof:placetype":"venue"
},
  "geometry": {"coordinates":[-2.7229700089,53.7662239075],"type":"Point"}
}