{
  "type": "Feature",
  "properties": {
    "iso:country":"GB",
    "sg:address":"Pullens Rd",
    "sg:city":"Stroud",
    "sg:classifiers":[
        {
            "category":"Government",
            "subcategory":"Police Station",
            "type":"Public Place"
        }
    ],
    "sg:phone":"+44 1452 335674",
    "sg:postcode":"GL6 6QZ",
    "sg:province":"Gloucestershire",
    "sg:tags":[
        "support"
    ],
    "wof:name":"Painswick Police Station",
    "wof:placetype":"venue"
},
  "geometry": {"coordinates":[-2.193109,51.788448],"type":"Point"}
}