{
  "type": "Feature",
  "properties": {
    "iso:country":"GB",
    "sg:address":"193 Brook Street, Broughty Ferry",
    "sg:city":"Dundee",
    "sg:classifiers":[
        {
            "category":"Travel",
            "subcategory":"Travel Agent",
            "type":"Entertainment"
        }
    ],
    "sg:phone":"+44 1382 737933",
    "sg:postcode":"DD5 2AG",
    "sg:province":"Angus",
    "sg:tags":[
        "agency",
        "activity"
    ],
    "wof:name":"Thomas Cook",
    "wof:placetype":"venue"
},
  "geometry": {"coordinates":[-2.874973,56.467419],"type":"Point"}
}