{
  "type": "Feature",
  "properties": {
    "iso:country":"GB",
    "sg:address":"8 Middle Row",
    "sg:city":"Chipping Norton",
    "sg:classifiers":[
        {
            "category":"Personal",
            "subcategory":"Beauty Salon",
            "type":"Services"
        },
        {
            "category":"Personal",
            "type":"Services"
        }
    ],
    "sg:phone":"+44 1608 643862",
    "sg:postcode":"OX7 5NH",
    "sg:province":"Gloucestershire",
    "sg:tags":[
        "unisex",
        "consultant",
        "hairdresser"
    ],
    "wof:name":"Lady Beautiful Salon",
    "wof:placetype":"venue"
},
  "geometry": {"coordinates":[-1.545019,51.942074],"type":"Point"}
}