{
  "type": "Feature",
  "properties": {
    "iso:country":"GB",
    "sg:address":"32 Fowlers Road",
    "sg:city":"Salisbury",
    "sg:classifiers":[
        {
            "category":"Real Estate",
            "subcategory":"Surveying",
            "type":"Services"
        },
        {
            "category":"Real Estate",
            "subcategory":"Architect",
            "type":"Services"
        }
    ],
    "sg:postcode":"SP1 2QU",
    "sg:province":"Wiltshire",
    "sg:tags":[
        "surveyor",
        "land"
    ],
    "wof:name":"Collings & Co",
    "wof:placetype":"venue"
},
  "geometry": {"coordinates":[-1.7873849869,51.0674095154],"type":"Point"}
}