{
  "type": "Feature",
  "properties": {
    "addr:full":"146 Willow Street Bury Lancashire BL9 7PS",
    "addr:housenumber":"146",
    "addr:postcode":"bl9 7ps",
    "addr:street":"Willow Street",
    "iso:country":"GB",
    "sg:address":"146 Willow Street",
    "sg:city":"Bury",
    "sg:classifiers":[
        {
            "category":"Retail",
            "subcategory":"Laundry & Dry Cleaning",
            "type":"Services"
        }
    ],
    "sg:phone":"+44 161 764 1719",
    "sg:postcode":"BL9 7PS",
    "sg:province":"Lancashire",
    "sg:tags":[
        "launderette"
    ],
    "wof:name":"The Cleaning Centre",
    "wof:placetype":"venue"
},
  "geometry": {"coordinates":[-2.2753009796,53.5970687866],"type":"Point"}
}