{
  "type": "Feature",
  "properties": {
    "addr:full":"23 Park St Deal Kent CT14 6AG",
    "addr:housenumber":"23",
    "addr:postcode":"ct14 6ag",
    "addr:street":"Park St Deal",
    "iso:country":"GB",
    "sg:address":"23 Park St",
    "sg:city":"Deal",
    "sg:classifiers":[
        {
            "category":"Cafe",
            "type":"Food & Drink"
        }
    ],
    "sg:phone":"+44 1304 369022",
    "sg:postcode":"CT14 6AG",
    "sg:province":"Kent",
    "sg:tags":[
        "tea",
        "room"
    ],
    "wof:name":"Names Cafeteria",
    "wof:placetype":"venue"
},
  "geometry": {"coordinates":[1.400795,51.22401],"type":"Point"}
}