{
  "type": "Feature",
  "properties": {
    "addr:full":"Brittania Rd Waltham Cross Essex EN8 7NY",
    "addr:postcode":"en8 7ny",
    "addr:street":"Brittania Rd;Cross",
    "iso:country":"GB",
    "sg:address":"Brittania Rd",
    "sg:city":"Waltham Cross",
    "sg:classifiers":[
        {
            "category":"Farming",
            "subcategory":"Crops",
            "type":"Manufacturing & Wholesale Goods"
        }
    ],
    "sg:postcode":"EN8 7NY",
    "sg:province":"Essex",
    "sg:tags":[
        "warehousing"
    ],
    "wof:name":"Teamstart Ltd",
    "wof:placetype":"venue"
},
  "geometry": {"coordinates":[-0.023654,51.68399],"type":"Point"}
}