{
  "type": "Feature",
  "properties": {
    "iso:country":"GB",
    "sg:address":"12 Cleveland Row",
    "sg:city":"Westminster",
    "sg:classifiers":[
        {
            "category":"Banks & Credit Unions",
            "subcategory":"Financial Services",
            "type":"Services"
        }
    ],
    "sg:phone":"+44 20 7930 0055",
    "sg:postcode":"SW1A 1DH",
    "sg:province":"Greater London",
    "sg:tags":[
        "agent",
        "tied"
    ],
    "wof:name":"Transatlantic Financial Services",
    "wof:placetype":"venue"
},
  "geometry": {"coordinates":[-0.139415,51.504303],"type":"Point"}
}