{
  "type": "Feature",
  "properties": {
    "addr:full":"4 Isleworth Road Exeter Devon EX4 1QU",
    "addr:housenumber":"4",
    "addr:postcode":"ex4 1qu",
    "addr:street":"Isleworth Road",
    "iso:country":"GB",
    "sg:address":"4 Isleworth Road",
    "sg:city":"Exeter",
    "sg:classifiers":[
        {
            "category":"Personal",
            "subcategory":"Beauty Salon",
            "type":"Services"
        }
    ],
    "sg:phone":"+44 1392 273521",
    "sg:postcode":"EX4 1QU",
    "sg:province":"Devon",
    "sg:tags":[
        "unisex",
        "hairdresser"
    ],
    "wof:name":"Hair-Tech",
    "wof:placetype":"venue"
},
  "geometry": {"coordinates":[-3.5499079227,50.7204475403],"type":"Point"}
}