{
  "type": "Feature",
  "properties": {
    "addr:full":"High St Grimsby Lincolnshire DN36 5PL",
    "addr:postcode":"dn36 5pl",
    "addr:street":"High St",
    "iso:country":"GB",
    "sg:address":"High St",
    "sg:city":"Grimsby",
    "sg:classifiers":[
        {
            "category":"Bars & Pubs",
            "type":"Food & Drink"
        }
    ],
    "sg:phone":"+44 1472 840306",
    "sg:postcode":"DN36 5PL",
    "sg:province":"Lincolnshire",
    "sg:tags":[
        "pubs",
        "inn"
    ],
    "wof:name":"Granby Inn The",
    "wof:placetype":"venue"
},
  "geometry": {"coordinates":[-0.0600639991,53.4667205811],"type":"Point"}
}