{
  "type": "Feature",
  "properties": {
    "iso:country":"GB",
    "sg:address":"Gate House Farm, Culworth",
    "sg:city":"Banbury",
    "sg:classifiers":[
        {
            "category":"Farming",
            "subcategory":"Livestock Farm",
            "type":"Manufacturing & Wholesale Goods"
        }
    ],
    "sg:postcode":"OX17 2BG",
    "sg:province":"Northamptonshire",
    "sg:tags":[
        "others"
    ],
    "wof:name":"T H & H J Field",
    "wof:placetype":"venue"
},
  "geometry": {"coordinates":[-1.204917,52.117519],"type":"Point"}
}