{
  "type": "Feature",
  "properties": {
    "addr:full":"The Chantry, Hadham Road Bishops Stortford Essex CM23 2QR",
    "addr:postcode":"cm23 2qr",
    "addr:street":"Hadham Road",
    "iso:country":"GB",
    "sg:address":"The Chantry, Hadham Road",
    "sg:city":"Bishops Stortford",
    "sg:classifiers":[
        {
            "category":"Professional",
            "type":"Services"
        }
    ],
    "sg:postcode":"CM23 2QR",
    "sg:province":"Essex",
    "sg:tags":[
        "interior",
        "furnishers",
        "designer"
    ],
    "wof:name":"Hone Edwards Associates Llp",
    "wof:placetype":"venue"
},
  "geometry": {"coordinates":[0.1619559973,51.8723564148],"type":"Point"}
}