{
  "type": "Feature",
  "properties": {
    "iso:country":"GB",
    "sg:address":"2 Willow View",
    "sg:city":"Sowerby Bridge",
    "sg:classifiers":[
        {
            "category":"Building & Trades",
            "subcategory":"Plumbing",
            "type":"Services"
        }
    ],
    "sg:postcode":"HX6 2SU",
    "sg:province":"West Yorkshire",
    "sg:tags":[
        "heating"
    ],
    "wof:name":"Roger D Hoyle",
    "wof:placetype":"venue"
},
  "geometry": {"coordinates":[-1.901085,53.711464],"type":"Point"}
}