{
  "type": "Feature",
  "properties": {
    "iso:country":"GB",
    "sg:address":"27 Kirkgate",
    "sg:city":"Leeds",
    "sg:classifiers":[
        {
            "category":"Real Estate",
            "subcategory":"Real Estate Agent",
            "type":"Services"
        }
    ],
    "sg:phone":"+44 113 234 3449",
    "sg:postcode":"LS2 7DR",
    "sg:province":"West Yorkshire",
    "wof:name":"Ridings Estate Agency",
    "wof:placetype":"venue"
},
  "geometry": {"coordinates":[-1.538918972,53.7963867188],"type":"Point"}
}