{
  "type": "Feature",
  "properties": {
    "addr:full":"19 Craven Court, High Street Skipton Lancashire BD23 1DG",
    "addr:housenumber":"19",
    "addr:postcode":"bd23 1dg",
    "addr:street":"Craven Court High Street",
    "iso:country":"GB",
    "sg:address":"19 Craven Court, High Street",
    "sg:city":"Skipton",
    "sg:classifiers":[
        {
            "category":"Shopping",
            "subcategory":"Department Store",
            "type":"Retail Goods"
        },
        {
            "category":"Shopping",
            "subcategory":"Gifts & Souvenirs",
            "type":"Retail Goods"
        }
    ],
    "sg:phone":"+44 1756 700570",
    "sg:postcode":"BD23 1DG",
    "sg:province":"Lancashire",
    "sg:tags":[
        "shop"
    ],
    "wof:name":"The Oriental Shop",
    "wof:placetype":"venue"
},
  "geometry": {"coordinates":[-2.0185139179,53.9602012634],"type":"Point"}
}