{
  "type": "Feature",
  "properties": {
    "addr:full":"Main St, Thurgarton Nottingham Nottinghamshire NG14 7GY",
    "addr:postcode":"ng14 7gy",
    "addr:street":"Main St",
    "iso:country":"GB",
    "sg:address":"Main St, Thurgarton",
    "sg:city":"Nottingham",
    "sg:classifiers":[
        {
            "category":"Bars & Pubs",
            "type":"Food & Drink"
        }
    ],
    "sg:phone":"+44 1636 830257",
    "sg:postcode":"NG14 7GY",
    "sg:province":"Nottinghamshire",
    "sg:tags":[
        "pubs",
        "inn"
    ],
    "wof:name":"Coach & Horses",
    "wof:placetype":"venue"
},
  "geometry": {"coordinates":[-0.965195,53.035206],"type":"Point"}
}