{
  "type": "Feature",
  "properties": {
    "iso:country":"GB",
    "sg:address":"4 All Hallows Road, Bispham",
    "sg:city":"Blackpool",
    "sg:classifiers":[
        {
            "category":"Travel",
            "subcategory":"Travel Agent",
            "type":"Entertainment"
        }
    ],
    "sg:phone":"+44 1253 595555",
    "sg:postcode":"FY2 0AS",
    "sg:province":"Lancashire",
    "wof:name":"Railsaver/Fleur Holidays",
    "wof:placetype":"venue"
},
  "geometry": {"coordinates":[-3.039434,53.852741],"type":"Point"}
}