{
  "type": "Feature",
  "properties": {
    "addr:full":"Unit C5 Northfleet Industrial Estate, Lower Road, Northfleet Gravesend Kent DA11 9SN",
    "addr:postcode":"da11 9sn",
    "addr:street":"Industrial Estate Lower Road",
    "iso:country":"GB",
    "sg:address":"Unit C5 Northfleet Industrial Estate, Lower Road, Northfleet",
    "sg:city":"Gravesend",
    "sg:classifiers":[
        {
            "category":"Shopping",
            "subcategory":"Stationery & Office Supplies",
            "type":"Retail Goods"
        }
    ],
    "sg:phone":"+44 1322 387373",
    "sg:postcode":"DA11 9SN",
    "sg:province":"Kent",
    "sg:tags":[
        "box",
        "carton"
    ],
    "wof:name":"March Packaging (Thames) Ltd.",
    "wof:placetype":"venue"
},
  "geometry": {"coordinates":[0.3264699876,51.4461402893],"type":"Point"}
}