{
  "type": "Feature",
  "properties": {
    "iso:country":"GB",
    "sg:address":"17 Kenilworth Close, Duston",
    "sg:city":"Northampton",
    "sg:classifiers":[
        {
            "category":"Building & Trades",
            "subcategory":"Cleaning & Sanitation",
            "type":"Services"
        }
    ],
    "sg:postcode":"NN5 6LD",
    "sg:province":"Northamptonshire",
    "sg:tags":[
        "commercial"
    ],
    "wof:name":"Frederick Colin Howlett-Butler",
    "wof:placetype":"venue"
},
  "geometry": {"coordinates":[-0.9481809735,52.2485389709],"type":"Point"}
}