{
  "type": "Feature",
  "properties": {
    "addr:full":"34 Mill Street, Ashton-in-makerfieldmill Wigan Lancashire WN4 9HP",
    "addr:housenumber":"34",
    "addr:postcode":"wn4 9hp",
    "addr:street":"Mill Street",
    "iso:country":"GB",
    "sg:address":"34 Mill Street, Ashton-in-makerfieldmill",
    "sg:city":"Wigan",
    "sg:classifiers":[
        {
            "category":"Freight",
            "type":"Transportation"
        }
    ],
    "sg:postcode":"WN4 9HP",
    "sg:province":"Lancashire",
    "sg:tags":[
        "haulage",
        "road"
    ],
    "wof:name":"Trevor J Arnold",
    "wof:placetype":"venue"
},
  "geometry": {"coordinates":[-2.628511,53.485954],"type":"Point"}
}