{
  "type": "Feature",
  "properties": {
    "iso:country":"GB",
    "sg:address":"Angel Lane, Mere",
    "sg:city":"Warminster",
    "sg:classifiers":[
        {
            "category":"Government",
            "subcategory":"Office",
            "type":"Public Place"
        }
    ],
    "sg:postcode":"BA12 6DH",
    "sg:province":"Somerset",
    "sg:tags":[
        "local"
    ],
    "wof:name":"Fives Court Residential Care",
    "wof:placetype":"venue"
},
  "geometry": {"coordinates":[-2.268792,51.088902],"type":"Point"}
}