{
  "type": "Feature",
  "properties": {
    "addr:full":"39 Church Street, Baillieston Glasgow East Dunbartonshire G69 7EU",
    "addr:housenumber":"39",
    "addr:postcode":"g69 7eu",
    "addr:street":"Church Street",
    "iso:country":"GB",
    "sg:address":"39 Church Street, Baillieston",
    "sg:city":"Glasgow",
    "sg:classifiers":[
        {
            "category":"Organizations",
            "subcategory":"Community Association",
            "type":"Services"
        },
        {
            "category":"Organizations",
            "subcategory":"Membership Organization",
            "type":"Services"
        }
    ],
    "sg:phone":"+44 141 771 6992",
    "sg:postcode":"G69 7EU",
    "sg:province":"East Dunbartonshire",
    "sg:tags":[
        "club",
        "social"
    ],
    "wof:name":"Masonic Lodge Social Club",
    "wof:placetype":"venue"
},
  "geometry": {"coordinates":[-4.0750541687,55.8539810181],"type":"Point"}
}