{
  "type": "Feature",
  "properties": {
    "addr:full":"51 High Street Brandon Norfolk IP27 0AZ",
    "addr:housenumber":"51",
    "addr:postcode":"ip27 0az",
    "addr:street":"High Street",
    "iso:country":"GB",
    "sg:address":"51 High Street",
    "sg:city":"Brandon",
    "sg:classifiers":[
        {
            "category":"Building & Trades",
            "subcategory":"Construction",
            "type":"Services"
        }
    ],
    "sg:phone":"+44 1842 811321",
    "sg:postcode":"IP27 0AZ",
    "sg:province":"Norfolk",
    "sg:tags":[
        "builder"
    ],
    "wof:name":"Laughton Construction Co. Ltd.",
    "wof:placetype":"venue"
},
  "geometry": {"coordinates":[0.6234049797,52.4495124817],"type":"Point"}
}