{
  "type": "Feature",
  "properties": {
    "iso:country":"GB",
    "sg:address":"51 Gravel Walk",
    "sg:city":"Faringdon",
    "sg:classifiers":[
        {
            "category":"Shopping",
            "type":"Retail Goods"
        }
    ],
    "sg:postcode":"SN7 7JN",
    "sg:province":"Oxfordshire",
    "sg:tags":[
        "part",
        "accessory"
    ],
    "wof:name":"Faringdon Motor Parts",
    "wof:placetype":"venue"
},
  "geometry": {"coordinates":[-1.588596,51.657734],"type":"Point"}
}