{
  "type": "Feature",
  "properties": {
    "iso:country":"GB",
    "sg:address":"60 St Faiths Lane",
    "sg:city":"Norwich",
    "sg:classifiers":[
        {
            "category":"Insurance",
            "subcategory":"Insurance Agent",
            "type":"Services"
        }
    ],
    "sg:phone":"+44 1603 626197",
    "sg:postcode":"NR1 1JT",
    "sg:province":"Norfolk",
    "sg:tags":[
        "broker"
    ],
    "wof:name":"Lambert Fenchurch U K Group Ltd.",
    "wof:placetype":"venue"
},
  "geometry": {"coordinates":[1.30212605,52.6298866272],"type":"Point"}
}