{
  "type": "Feature",
  "properties": {
    "iso:country":"GB",
    "sg:address":"20 Woodfield Avenue",
    "sg:city":"Mexborough",
    "sg:classifiers":[
        {
            "category":"Building & Trades",
            "subcategory":"Construction",
            "type":"Services"
        }
    ],
    "sg:phone":"+44 1709 585520",
    "sg:postcode":"S64 0AE",
    "sg:province":"South Yorkshire",
    "sg:tags":[
        "builder"
    ],
    "wof:name":"A B Worley",
    "wof:placetype":"venue"
},
  "geometry": {"coordinates":[-1.283225,53.496571],"type":"Point"}
}