{
  "type": "Feature",
  "properties": {
    "addr:full":"579 Garratt La Wandsworth Greater London SW18 4ST",
    "addr:housenumber":"579",
    "addr:postcode":"sw18 4st",
    "addr:street":"Garratt La Wandsworth",
    "iso:country":"GB",
    "sg:address":"579 Garratt La",
    "sg:city":"Wandsworth",
    "sg:classifiers":[
        {
            "category":"Health Services",
            "subcategory":"Dentist",
            "type":"Services"
        }
    ],
    "sg:phone":"+44 20 8946 2732",
    "sg:postcode":"SW18 4ST",
    "sg:province":"Greater London",
    "wof:name":"S Barnes Dental Practice",
    "wof:placetype":"venue"
},
  "geometry": {"coordinates":[-0.186652,51.43961],"type":"Point"}
}