{
  "type": "Feature",
  "properties": {
    "addr:full":"Berkhamsted Centre, The Chapel, Parkview Rd Berkhamsted Bedfordshire HP4 2EY",
    "addr:postcode":"hp4 2ey",
    "addr:street":"The;Parkview Rd",
    "iso:country":"GB",
    "sg:address":"Berkhamsted Centre, The Chapel, Parkview Rd",
    "sg:city":"Berkhamsted",
    "sg:classifiers":[
        {
            "category":"Organizations",
            "subcategory":"Non-profit Organization",
            "type":"Services"
        }
    ],
    "sg:phone":"+44 1442 865438",
    "sg:postcode":"HP4 2EY",
    "sg:province":"Bedfordshire",
    "sg:tags":[
        "organisation",
        "voluntary",
        "charity"
    ],
    "wof:name":"British Red Cross",
    "wof:placetype":"venue"
},
  "geometry": {"coordinates":[-0.5645589828,51.7604141235],"type":"Point"}
}