{
  "type": "Feature",
  "properties": {
    "addr:full":"239 Batley Road, Kirkhamgate Wakefield West Yorkshire WF2 0RZ",
    "addr:housenumber":"239",
    "addr:postcode":"wf2 0rz",
    "addr:street":"Batley Road Kirkhamgate",
    "iso:country":"GB",
    "sg:address":"239 Batley Road, Kirkhamgate",
    "sg:city":"Wakefield",
    "sg:classifiers":[
        {
            "category":"Manufacturing",
            "subcategory":"Petroleum Products",
            "type":"Manufacturing & Wholesale Goods"
        },
        {
            "category":"Building & Trades",
            "subcategory":"Construction",
            "type":"Services"
        }
    ],
    "sg:phone":"+44 1924 200532",
    "sg:postcode":"WF2 0RZ",
    "sg:province":"West Yorkshire",
    "sg:tags":[
        "double",
        "glazing",
        "installers"
    ],
    "sg:website":"http://www.thewindowclinic.co.uk",
    "wof:name":"The Window Clinic",
    "wof:placetype":"venue"
},
  "geometry": {"coordinates":[-1.5329899788,53.6902351379],"type":"Point"}
}