{
  "type": "Feature",
  "properties": {
    "addr:full":"3 Maxted Road Hemel Hempstead Hertfordshire HP2 7DX",
    "addr:housenumber":"3",
    "addr:postcode":"hp2 7dx",
    "addr:street":"Maxted Road",
    "iso:country":"GB",
    "sg:address":"3 Maxted Road",
    "sg:city":"Hemel Hempstead",
    "sg:classifiers":[
        {
            "category":"Professional",
            "type":"Services"
        }
    ],
    "sg:phone":"+44 1442 213412",
    "sg:postcode":"HP2 7DX",
    "sg:province":"Hertfordshire",
    "sg:tags":[
        "shopfitters"
    ],
    "wof:name":"Europa Shopfitting & Interiors Ltd.",
    "wof:placetype":"venue"
},
  "geometry": {"coordinates":[-0.4353539944,51.7650909424],"type":"Point"}
}