{
  "type": "Feature",
  "properties": {
    "iso:country":"GB",
    "sg:address":"Blackstable House",
    "sg:city":"Stroud",
    "sg:classifiers":[
        {
            "category":"Mining & Drilling",
            "type":"Manufacturing & Wholesale Goods"
        }
    ],
    "sg:postcode":"GL6 7QX",
    "sg:province":"Gloucestershire",
    "sg:tags":[
        "oil",
        "petroleum"
    ],
    "wof:name":"Bow Valley Petroleum (U K) Ltd.",
    "wof:placetype":"venue"
},
  "geometry": {"coordinates":[-2.142516,51.756252],"type":"Point"}
}