{
  "type": "Feature",
  "properties": {
    "iso:country":"GB",
    "sg:address":"42 Honor Oak Park",
    "sg:city":"London",
    "sg:classifiers":[
        {
            "category":"Retail",
            "subcategory":"Laundry & Dry Cleaning",
            "type":"Services"
        },
        {
            "category":"Travel",
            "subcategory":"Travel Agent",
            "type":"Entertainment"
        }
    ],
    "sg:phone":"+44 20 8699 3688",
    "sg:postcode":"SE23 1DY",
    "sg:province":"Greater London",
    "sg:tags":[
        "alteration"
    ],
    "wof:name":"Honor Oak Dry Cleaners",
    "wof:placetype":"venue"
},
  "geometry": {"coordinates":[-0.0433599986,51.4493942261],"type":"Point"}
}