{
  "type": "Feature",
  "properties": {
    "addr:full":"9 Priory Road Newbury Berkshire RG14 7QS",
    "addr:housenumber":"9",
    "addr:postcode":"rg14 7qs",
    "addr:street":"Priory Road",
    "iso:country":"GB",
    "sg:address":"9 Priory Road",
    "sg:city":"Newbury",
    "sg:classifiers":[
        {
            "category":"Freight",
            "type":"Transportation"
        }
    ],
    "sg:postcode":"RG14 7QS",
    "sg:province":"Berkshire",
    "sg:tags":[
        "haulage",
        "road"
    ],
    "wof:name":"Logistics Systems Consulting Ltd.",
    "wof:placetype":"venue"
},
  "geometry": {"coordinates":[-1.3235390186,51.3919219971],"type":"Point"}
}