{
  "type": "Feature",
  "properties": {
    "iso:country":"GB",
    "sg:address":"2 Church Lane, Sutton Maddock",
    "sg:city":"Shifnal",
    "sg:classifiers":[
        {
            "category":"Building & Trades",
            "subcategory":"Construction",
            "type":"Services"
        }
    ],
    "sg:phone":"+44 1952 730695",
    "sg:postcode":"TF11 9NQ",
    "sg:province":"Shropshire",
    "sg:tags":[
        "joinery",
        "joiner",
        "carpenter",
        "carpentry"
    ],
    "wof:name":"J J Holdsworth",
    "wof:placetype":"venue"
},
  "geometry": {"coordinates":[-2.373052,52.665699],"type":"Point"}
}