{
  "type": "Feature",
  "properties": {
    "addr:full":"Unit 5 Clarks Village, Farm Road Street Somerset BA16 0BB",
    "addr:housenumber":"unit 5",
    "addr:postcode":"ba16 0bb",
    "addr:street":"Clarks Village Farm Road Street",
    "iso:country":"GB",
    "sg:address":"Unit 5 Clarks Village, Farm Road",
    "sg:city":"Street",
    "sg:classifiers":[
        {
            "category":"Shopping",
            "subcategory":"Clothing, Apparel, & Fashions",
            "type":"Retail Goods"
        }
    ],
    "sg:phone":"+44 1458 840405",
    "sg:postcode":"BA16 0BB",
    "sg:province":"Somerset",
    "sg:tags":[
        "shop"
    ],
    "wof:name":"Laura Ashley Ltd.",
    "wof:placetype":"venue"
},
  "geometry": {"coordinates":[-2.74872,51.127872],"type":"Point"}
}