{
  "type": "Feature",
  "properties": {
    "addr:full":"17 Crown Street Ayr South Ayrshire KA8 8BY",
    "addr:housenumber":"17",
    "addr:postcode":"ka8 8by",
    "addr:street":"Crown Street",
    "iso:country":"GB",
    "sg:address":"17 Crown Street",
    "sg:city":"Ayr",
    "sg:classifiers":[
        {
            "category":"Fast Food",
            "type":"Food & Drink"
        }
    ],
    "sg:phone":"+44 1292 289669",
    "sg:postcode":"KA8 8BY",
    "sg:province":"South Ayrshire",
    "sg:tags":[
        "away",
        "meal",
        "outlet",
        "take"
    ],
    "wof:name":"Peggy Sues",
    "wof:placetype":"venue"
},
  "geometry": {"coordinates":[-4.6336379051,55.4682617188],"type":"Point"}
}