{
  "type": "Feature",
  "properties": {
    "iso:country":"GB",
    "sg:address":"7 Woburn Road, Woburn Sands",
    "sg:city":"Milton Keynes",
    "sg:classifiers":[
        {
            "category":"Fast Food",
            "type":"Food & Drink"
        }
    ],
    "sg:postcode":"MK17 8SX",
    "sg:province":"Bedfordshire",
    "sg:tags":[
        "away",
        "take"
    ],
    "wof:name":"Sun Kwong Chinese Takeaway",
    "wof:placetype":"venue"
},
  "geometry": {"coordinates":[-0.6433349848,52.0052757263],"type":"Point"}
}