{
  "type": "Feature",
  "properties": {
    "iso:country":"GB",
    "sg:address":"581-587 Harrow Road",
    "sg:city":"London",
    "sg:classifiers":[
        {
            "category":"Retail",
            "subcategory":"Auto Repair",
            "type":"Services"
        }
    ],
    "sg:phone":"+44 20 8969 1590",
    "sg:postcode":"W10 4RA",
    "sg:province":"Greater London",
    "sg:tags":[
        "modification",
        "garage"
    ],
    "wof:name":"Ladbroke Tyre & Auto Ltd.",
    "wof:placetype":"venue"
},
  "geometry": {"coordinates":[-0.2169000059,51.5283813477],"type":"Point"}
}