{
  "type": "Feature",
  "properties": {
    "addr:full":"Lower Lydbrook Lydbrook Gloucestershire GL17 9NB",
    "addr:postcode":"gl17 9nb",
    "addr:street":"Lower Lydbrook",
    "iso:country":"GB",
    "sg:address":"Lower Lydbrook",
    "sg:city":"Lydbrook",
    "sg:classifiers":[
        {
            "category":"Manufacturing",
            "subcategory":"Wood Products",
            "type":"Manufacturing & Wholesale Goods"
        }
    ],
    "sg:postcode":"GL17 9NB",
    "sg:province":"Gloucestershire",
    "sg:tags":[
        "woodturning"
    ],
    "wof:name":"Lydwood (Glos) Ltd.",
    "wof:placetype":"venue"
},
  "geometry": {"coordinates":[-2.580163002,51.8399353027],"type":"Point"}
}