{
  "type": "Feature",
  "properties": {
    "iso:country":"GB",
    "sg:address":"Stratford Road, Wootton Wawen",
    "sg:city":"Solihull",
    "sg:classifiers":[
        {
            "category":"Bars & Pubs",
            "type":"Food & Drink"
        }
    ],
    "sg:phone":"+44 1564 792511",
    "sg:postcode":"B95 6BD",
    "sg:province":"Warwickshire",
    "sg:tags":[
        "pubs",
        "inn"
    ],
    "wof:name":"The Bulls Head",
    "wof:placetype":"venue"
},
  "geometry": {"coordinates":[-1.780899,52.286125],"type":"Point"}
}