{
  "type": "Feature",
  "properties": {
    "addr:full":"Sunny Brow Off Chapel La, Coppull Chorley Lancashire PR7 4PF",
    "addr:postcode":"pr7 4pf",
    "addr:street":"Sunny",
    "iso:country":"GB",
    "sg:address":"Sunny Brow Off Chapel La, Coppull",
    "sg:city":"Chorley",
    "sg:classifiers":[
        {
            "category":"Health Services",
            "subcategory":"Nursing And Care Facility",
            "type":"Services"
        }
    ],
    "sg:phone":"+44 1257 471571",
    "sg:postcode":"PR7 4PF",
    "sg:province":"Lancashire",
    "sg:tags":[
        "home"
    ],
    "wof:name":"Finecare Plc",
    "wof:placetype":"venue"
},
  "geometry": {"coordinates":[-2.6499619484,53.6261405945],"type":"Point"}
}