{
  "type": "Feature",
  "properties": {
    "addr:full":"55 Wiltonburn Rd Glasgow East Renfrewshire G53 7NY",
    "addr:housenumber":"55",
    "addr:postcode":"g53 7ny",
    "addr:street":"Wiltonburn Rd",
    "iso:country":"GB",
    "sg:address":"55 Wiltonburn Rd",
    "sg:city":"Glasgow",
    "sg:classifiers":[
        {
            "category":"Shopping",
            "subcategory":"Baby Store",
            "type":"Retail Goods"
        }
    ],
    "sg:phone":"+44 141 881 1067",
    "sg:postcode":"G53 7NY",
    "sg:province":"East Renfrewshire",
    "sg:tags":[
        "nursery",
        "accessory"
    ],
    "wof:name":"Abdine Manufacturing Ltd",
    "wof:placetype":"venue"
},
  "geometry": {"coordinates":[-4.3581519127,55.8109283447],"type":"Point"}
}