{
  "type": "Feature",
  "properties": {
    "iso:country":"GB",
    "sg:address":"31 North Street, Barrow-on-soar",
    "sg:city":"Loughborough",
    "sg:classifiers":[
        {
            "category":"Food & Beverages",
            "subcategory":"Groceries & Convenience Stores",
            "type":"Retail Goods"
        }
    ],
    "sg:postcode":"LE12 8PZ",
    "sg:province":"Leicestershire",
    "wof:name":"Spar",
    "wof:placetype":"venue"
},
  "geometry": {"coordinates":[-1.147788,52.753521],"type":"Point"}
}