{
  "type": "Feature",
  "properties": {
    "addr:full":"Vinnetrow Rd Chichester West Sussex PO20 6QB",
    "addr:postcode":"po20 6qb",
    "addr:street":"Vinnetrow Rd",
    "iso:country":"GB",
    "sg:address":"Vinnetrow Rd",
    "sg:city":"Chichester",
    "sg:classifiers":[
        {
            "category":"Food & Beverages",
            "subcategory":"Candy",
            "type":"Retail Goods"
        }
    ],
    "sg:phone":"+44 1243 789333",
    "sg:postcode":"PO20 6QB",
    "sg:province":"West Sussex",
    "sg:tags":[
        "merchant",
        "produce"
    ],
    "wof:name":"Natures Way",
    "wof:placetype":"venue"
},
  "geometry": {"coordinates":[-0.754011,50.827023],"type":"Point"}
}