{
  "type": "Feature",
  "properties": {
    "addr:full":"22 Larlholm Parade Fleetwood Lancashire FY7 8NE",
    "addr:housenumber":"22",
    "addr:postcode":"fy7 8ne",
    "addr:street":"Larlholm Parade",
    "iso:country":"GB",
    "sg:address":"22 Larlholm Parade",
    "sg:city":"Fleetwood",
    "sg:classifiers":[
        {
            "category":"Shopping",
            "subcategory":"Used Merchandise",
            "type":"Retail Goods"
        }
    ],
    "sg:postcode":"FY7 8NE",
    "sg:province":"Lancashire",
    "sg:tags":[
        "furniture"
    ],
    "wof:name":"Steptoe's",
    "wof:placetype":"venue"
},
  "geometry": {"coordinates":[-3.031339,53.906288],"type":"Point"}
}