{
  "type": "Feature",
  "properties": {
    "iso:country":"GB",
    "sg:address":"6 Southway, Raynes Park",
    "sg:city":"London",
    "sg:classifiers":[
        {
            "category":"Professional",
            "subcategory":"Engineering",
            "type":"Services"
        }
    ],
    "sg:phone":"+44 20 8543 1176",
    "sg:postcode":"SW20 9JQ",
    "sg:province":"Greater London",
    "sg:tags":[
        "contractor",
        "electrical",
        "engineer"
    ],
    "wof:name":"A Z Electrical",
    "wof:placetype":"venue"
},
  "geometry": {"coordinates":[-0.2281579971,51.3975791931],"type":"Point"}
}