{
  "type": "Feature",
  "properties": {
    "addr:full":"Care Of St Martins House, Westwick Street Norwich Norfolk NR2 4SZ",
    "addr:postcode":"nr2 4sz",
    "addr:street":"Westwick Street",
    "iso:country":"GB",
    "sg:address":"Care Of St Martins House, Westwick Street",
    "sg:city":"Norwich",
    "sg:classifiers":[
        {
            "category":"Organizations",
            "subcategory":"Non-profit Organization",
            "type":"Services"
        }
    ],
    "sg:phone":"+44 1603 613865",
    "sg:postcode":"NR2 4SZ",
    "sg:province":"Norfolk",
    "sg:tags":[
        "organisation",
        "voluntary",
        "charity"
    ],
    "wof:name":"Big Issue",
    "wof:placetype":"venue"
},
  "geometry": {"coordinates":[1.28799,52.632721],"type":"Point"}
}