{
  "type": "Feature",
  "properties": {
    "addr:full":"Park Church Office, Francis St Halifax West Yorkshire HX1 5JY",
    "addr:postcode":"hx1 5jy",
    "addr:street":"Park;Francis St",
    "iso:country":"GB",
    "sg:address":"Park Church Office, Francis St",
    "sg:city":"Halifax",
    "sg:classifiers":[
        {
            "category":"Bus Charters",
            "type":"Transportation"
        }
    ],
    "sg:phone":"+44 1422 345322",
    "sg:postcode":"HX1 5JY",
    "sg:province":"West Yorkshire",
    "sg:tags":[
        "mini",
        "hire",
        "leasing"
    ],
    "wof:name":"U R C Transport",
    "wof:placetype":"venue"
},
  "geometry": {"coordinates":[-1.869269,53.72224],"type":"Point"}
}