{
  "type": "Feature",
  "properties": {
    "addr:full":"P O Box 1919 Highgate Greater London N6 4PE",
    "addr:housenumber":"p o;1919",
    "addr:postcode":"n6 4pe",
    "addr:street":"Highgate",
    "iso:country":"GB",
    "sg:address":"P O Box 1919",
    "sg:city":"Highgate",
    "sg:classifiers":[
        {
            "category":"Wholesale",
            "subcategory":"Music Publishers",
            "type":"Manufacturing & Wholesale Goods"
        }
    ],
    "sg:phone":"+44 20 8444 5819",
    "sg:postcode":"N6 4PE",
    "sg:province":"Greater London",
    "sg:tags":[
        "record"
    ],
    "wof:name":"Droffig Recordings",
    "wof:placetype":"venue"
},
  "geometry": {"coordinates":[-0.1582800001,51.5782585144],"type":"Point"}
}