{
  "type": "Feature",
  "properties": {
    "iso:country":"GB",
    "sg:address":"Unit 1 23 Lotland St",
    "sg:city":"Inverness",
    "sg:classifiers":[
        {
            "category":"Shopping",
            "subcategory":"Computers & Home Electronics",
            "type":"Retail Goods"
        }
    ],
    "sg:phone":"+44 1463 713484",
    "sg:postcode":"IV1 1ST",
    "sg:province":"Highland",
    "sg:tags":[
        "electrical"
    ],
    "wof:name":"Avco Supplies",
    "wof:placetype":"venue"
},
  "geometry": {"coordinates":[-4.226934,57.488148],"type":"Point"}
}