{
  "type": "Feature",
  "properties": {
    "addr:full":"Abbey Street Elgin Moray IV30 1DA",
    "addr:postcode":"iv30 1da",
    "addr:street":"Abbey Street",
    "iso:country":"GB",
    "sg:address":"Abbey Street",
    "sg:city":"Elgin",
    "sg:classifiers":[
        {
            "category":"Education",
            "subcategory":"School",
            "type":"Public Place"
        },
        {
            "category":"Government",
            "subcategory":"Office",
            "type":"Public Place"
        }
    ],
    "sg:phone":"+44 1343 541453",
    "sg:postcode":"IV30 1DA",
    "sg:province":"Moray",
    "sg:tags":[
        "local",
        "authority"
    ],
    "wof:name":"St Sylvester's Primary School",
    "wof:placetype":"venue"
},
  "geometry": {"coordinates":[-3.3101038933,57.6473083496],"type":"Point"}
}