{
  "type": "Feature",
  "properties": {
    "addr:full":"8 The Square Richmond Greater London TW9 1DZ",
    "addr:housenumber":"8",
    "addr:postcode":"tw9 1dz",
    "addr:street":"The Square",
    "iso:country":"GB",
    "sg:address":"8 The Square",
    "sg:city":"Richmond",
    "sg:classifiers":[
        {
            "category":"Personal",
            "subcategory":"Beauty Salon",
            "type":"Services"
        }
    ],
    "sg:phone":"+44 20 8287 2222",
    "sg:postcode":"TW9 1DZ",
    "sg:province":"Greater London",
    "sg:tags":[
        "unisex",
        "hairdresser"
    ],
    "wof:name":"Headmasters",
    "wof:placetype":"venue"
},
  "geometry": {"coordinates":[-0.3028700054,51.4611625671],"type":"Point"}
}