{
  "type": "Feature",
  "properties": {
    "addr:full":"Hopcott Rd Minehead Somerset TA24 6DJ",
    "addr:postcode":"ta24 6dj",
    "addr:street":"Hopcott Rd",
    "iso:country":"GB",
    "sg:address":"Hopcott Rd",
    "sg:city":"Minehead",
    "sg:classifiers":[
        {
            "category":"Government",
            "subcategory":"Fire Station",
            "type":"Public Place"
        }
    ],
    "sg:phone":"+44 1643 702732",
    "sg:postcode":"TA24 6DJ",
    "sg:province":"Somerset",
    "wof:name":"Minehead Fire Brigade",
    "wof:placetype":"venue"
},
  "geometry": {"coordinates":[-3.4729840755,51.1985206604],"type":"Point"}
}