{
  "type": "Feature",
  "properties": {
    "addr:full":"23a Minto St Edinburgh City of Edinburgh EH9 1RQ",
    "addr:housenumber":"23a",
    "addr:postcode":"eh9 1rq",
    "addr:street":"Minto St Edinburgh",
    "iso:country":"GB",
    "sg:address":"23a Minto St",
    "sg:city":"Edinburgh",
    "sg:classifiers":[
        {
            "category":"Travel",
            "subcategory":"Hotels & Motels",
            "type":"Entertainment"
        }
    ],
    "sg:phone":"+44 131 667 3967",
    "sg:postcode":"EH9 1RQ",
    "sg:province":"City of Edinburgh",
    "sg:tags":[
        "house",
        "guest"
    ],
    "wof:name":"Arlington Guest House",
    "wof:placetype":"venue"
},
  "geometry": {"coordinates":[-3.188699,55.938049],"type":"Point"}
}