{
  "type": "Feature",
  "properties": {
    "iso:country":"GB",
    "sg:address":"62 Unthank Road",
    "sg:city":"Norwich",
    "sg:classifiers":[
        {
            "category":"Health Services",
            "subcategory":"Health Practitioner",
            "type":"Services"
        }
    ],
    "sg:phone":"+44 1603 663186",
    "sg:postcode":"NR2 2RN",
    "sg:province":"Norfolk",
    "sg:tags":[
        "acupuncture"
    ],
    "wof:name":"Alderbury Clinic",
    "wof:placetype":"venue"
},
  "geometry": {"coordinates":[1.2806,52.626694],"type":"Point"}
}