{
  "type": "Feature",
  "properties": {
    "addr:full":"High Street, Maiden Bradley Warminster Somerset BA12 7JG",
    "addr:postcode":"ba12 7jg",
    "addr:street":"High Street",
    "iso:country":"GB",
    "sg:address":"High Street, Maiden Bradley",
    "sg:city":"Warminster",
    "sg:classifiers":[
        {
            "category":"Bus Charters",
            "type":"Transportation"
        }
    ],
    "sg:phone":"+44 1985 844339",
    "sg:postcode":"BA12 7JG",
    "sg:province":"Somerset",
    "sg:tags":[
        "coach"
    ],
    "wof:name":"Leathers Coaches",
    "wof:placetype":"venue"
},
  "geometry": {"coordinates":[-2.2852790356,51.1486434937],"type":"Point"}
}