{
  "type": "Feature",
  "properties": {
    "iso:country":"GB",
    "sg:address":"7 Hankelow Close",
    "sg:city":"Middlewich",
    "sg:classifiers":[
        {
            "category":"Building & Trades",
            "subcategory":"Construction",
            "type":"Services"
        }
    ],
    "sg:phone":"+44 1606 837053",
    "sg:postcode":"CW10 0RQ",
    "sg:province":"Cheshire",
    "sg:tags":[
        "builder"
    ],
    "wof:name":"Firm Foundations",
    "wof:placetype":"venue"
},
  "geometry": {"coordinates":[-2.446674,53.179626],"type":"Point"}
}