{
  "type": "Feature",
  "properties": {
    "iso:country":"GB",
    "sg:address":"104 Preston Drive",
    "sg:city":"Bexleyheath",
    "sg:classifiers":[
        {
            "category":"Professional",
            "subcategory":"Accounting & Tax Preparation",
            "type":"Services"
        }
    ],
    "sg:phone":"+44 20 8303 4794",
    "sg:postcode":"DA7 4UE",
    "sg:province":"Kent",
    "sg:tags":[
        "accountant"
    ],
    "wof:name":"John W Clark",
    "wof:placetype":"venue"
},
  "geometry": {"coordinates":[0.127552,51.472473],"type":"Point"}
}