{
  "type": "Feature",
  "properties": {
    "addr:full":"304 High St Sutton Surrey SM1 1PQ",
    "addr:housenumber":"304",
    "addr:postcode":"sm1 1pq",
    "addr:street":"High St",
    "iso:country":"GB",
    "sg:address":"304 High St",
    "sg:city":"Sutton",
    "sg:classifiers":[
        {
            "category":"Shopping",
            "subcategory":"Computers & Home Electronics",
            "type":"Retail Goods"
        }
    ],
    "sg:phone":"+44 20 8643 9400",
    "sg:postcode":"SM1 1PQ",
    "sg:province":"Surrey",
    "sg:tags":[
        "electrical"
    ],
    "wof:name":"Electrical Supplies",
    "wof:placetype":"venue"
},
  "geometry": {"coordinates":[-0.1948900074,51.36901474],"type":"Point"}
}