{
  "type": "Feature",
  "properties": {
    "addr:full":"Lorna Mead House, Kings Place London Greater London SE1 6ED",
    "addr:postcode":"se1 6ed",
    "addr:street":"Lorna;Kings Place",
    "iso:country":"GB",
    "sg:address":"Lorna Mead House, Kings Place",
    "sg:city":"London",
    "sg:classifiers":[
        {
            "category":"Real Estate",
            "subcategory":"Real Estate Agent",
            "type":"Services"
        }
    ],
    "sg:postcode":"SE1 6ED",
    "sg:province":"Greater London",
    "wof:name":"Telford Properties Ltd",
    "wof:placetype":"venue"
},
  "geometry": {"coordinates":[-0.0964599997,51.4990692139],"type":"Point"}
}