{
  "type": "Feature",
  "properties": {
    "addr:full":"Unit 3, Avon Works, Avondale Rd Kettering Northamptonshire NN16 8PL",
    "addr:housenumber":"unit 3;works",
    "addr:postcode":"nn16 8pl",
    "addr:street":"Avon;Avondale Rd",
    "iso:country":"GB",
    "sg:address":"Unit 3, Avon Works, Avondale Rd",
    "sg:city":"Kettering",
    "sg:classifiers":[
        {
            "category":"Education",
            "subcategory":"Music School",
            "type":"Public Place"
        }
    ],
    "sg:phone":"+44 1536 310090",
    "sg:postcode":"NN16 8PL",
    "sg:province":"Northamptonshire",
    "sg:tags":[
        "conservatory"
    ],
    "wof:name":"High-light Windows",
    "wof:placetype":"venue"
},
  "geometry": {"coordinates":[-0.7258039713,52.3988342285],"type":"Point"}
}