{
  "type": "Feature",
  "properties": {
    "addr:full":"9 School Lane Kenilworth Warwickshire CV8 2GU",
    "addr:housenumber":"9",
    "addr:postcode":"cv8 2gu",
    "addr:street":"School Lane",
    "iso:country":"GB",
    "sg:address":"9 School Lane",
    "sg:city":"Kenilworth",
    "sg:classifiers":[
        {
            "category":"Building & Trades",
            "subcategory":"Construction",
            "type":"Services"
        }
    ],
    "sg:phone":"+44 1926 857753",
    "sg:postcode":"CV8 2GU",
    "sg:province":"Warwickshire",
    "sg:tags":[
        "builder"
    ],
    "wof:name":"John Bradley Builders (Kenilworth) Ltd.",
    "wof:placetype":"venue"
},
  "geometry": {"coordinates":[-1.5785410404,52.3482208252],"type":"Point"}
}