{
  "type": "Feature",
  "properties": {
    "addr:full":"12 Park Street Minehead Somerset TA24 5NQ",
    "addr:housenumber":"12",
    "addr:postcode":"ta24 5nq",
    "addr:street":"Park Street",
    "iso:country":"GB",
    "sg:address":"12 Park Street",
    "sg:city":"Minehead",
    "sg:classifiers":[
        {
            "category":"Health Services",
            "subcategory":"Optometrist",
            "type":"Services"
        },
        {
            "category":"Shopping",
            "subcategory":"Optician",
            "type":"Retail Goods"
        }
    ],
    "sg:phone":"+44 1643 702204",
    "sg:postcode":"TA24 5NQ",
    "sg:province":"Somerset",
    "sg:tags":[
        "ophthalmic"
    ],
    "wof:name":"Cranmers Opticians",
    "wof:placetype":"venue"
},
  "geometry": {"coordinates":[-3.4798970222,51.2052764893],"type":"Point"}
}