{
  "type": "Feature",
  "properties": {
    "iso:country":"GB",
    "sg:address":"Unit N, Mill Street Industrial Estate, 12 Upper Mill Street",
    "sg:city":"Airdrie",
    "sg:classifiers":[
        {
            "category":"Manufacturing",
            "subcategory":"Metals",
            "type":"Manufacturing & Wholesale Goods"
        }
    ],
    "sg:phone":"+44 1236 755525",
    "sg:postcode":"ML6 7QB",
    "sg:province":"North Lanarkshire",
    "sg:tags":[
        "steel",
        "fabricator",
        "erectors"
    ],
    "wof:name":"Systems Stainless",
    "wof:placetype":"venue"
},
  "geometry": {"coordinates":[-3.980784,55.865864],"type":"Point"}
}