{
  "type": "Feature",
  "properties": {
    "addr:full":"19-21 Springfield Road Chelmsford Essex CM2 6JE",
    "addr:housenumber":"19-21",
    "addr:postcode":"cm2 6je",
    "addr:street":"Springfield Road",
    "iso:country":"GB",
    "sg:address":"19-21 Springfield Road",
    "sg:city":"Chelmsford",
    "sg:classifiers":[
        {
            "category":"Home & Garden",
            "subcategory":"Furniture",
            "type":"Retail Goods"
        }
    ],
    "sg:phone":"+44 1245 250250",
    "sg:postcode":"CM2 6JE",
    "sg:province":"Essex",
    "wof:name":"Matts & Slatts Ltd.",
    "wof:placetype":"venue"
},
  "geometry": {"coordinates":[0.475479,51.732597],"type":"Point"}
}