{
  "type": "Feature",
  "properties": {
    "addr:full":"571 Cheetham Hill Road Manchester Greater Manchester M8 9JE",
    "addr:housenumber":"571",
    "addr:postcode":"m8 9je",
    "addr:street":"Cheetham Hill Road",
    "iso:country":"GB",
    "sg:address":"571 Cheetham Hill Road",
    "sg:city":"Manchester",
    "sg:classifiers":[
        {
            "category":"Professional",
            "subcategory":"Lawyer & Legal Services",
            "type":"Services"
        }
    ],
    "sg:phone":"+44 161 795 5700",
    "sg:postcode":"M8 9JE",
    "sg:province":"Greater Manchester",
    "sg:tags":[
        "solicitor"
    ],
    "wof:name":"Glaisyers",
    "wof:placetype":"venue"
},
  "geometry": {"coordinates":[-2.244689,53.511295],"type":"Point"}
}