{
  "type": "Feature",
  "properties": {
    "iso:country":"GB",
    "sg:address":"Pinegrove, Colliston",
    "sg:city":"Arbroath",
    "sg:classifiers":[
        {
            "category":"Food & Beverages",
            "subcategory":"Groceries & Convenience Stores",
            "type":"Retail Goods"
        }
    ],
    "sg:phone":"+44 1241 890235",
    "sg:postcode":"DD11 3RP",
    "sg:province":"Angus",
    "sg:tags":[
        "merchant",
        "potato"
    ],
    "wof:name":"Ian Caird",
    "wof:placetype":"venue"
},
  "geometry": {"coordinates":[-2.5908410549,56.5629081726],"type":"Point"}
}