{
  "type": "Feature",
  "properties": {
    "iso:country":"GB",
    "sg:address":"9 Tower Road, Terrington St Clement",
    "sg:city":"King's Lynn",
    "sg:classifiers":[
        {
            "category":"Building & Trades",
            "subcategory":"Landscaping Services",
            "type":"Services"
        }
    ],
    "sg:phone":"+44 1553 829185",
    "sg:postcode":"PE34 4LP",
    "sg:province":"Lincolnshire",
    "sg:tags":[
        "landscape",
        "contractor"
    ],
    "wof:name":"P Kisby",
    "wof:placetype":"venue"
},
  "geometry": {"coordinates":[0.2993499935,52.7665405273],"type":"Point"}
}