{
  "type": "Feature",
  "properties": {
    "addr:full":"9 Winsbury Court Plymouth Devon PL6 5JU",
    "addr:housenumber":"9",
    "addr:postcode":"pl6 5ju",
    "addr:street":"Winsbury Court",
    "iso:country":"GB",
    "sg:address":"9 Winsbury Court",
    "sg:city":"Plymouth",
    "sg:classifiers":[
        {
            "category":"Arts & Performance",
            "subcategory":"Music",
            "type":"Entertainment"
        }
    ],
    "sg:postcode":"PL6 5JU",
    "sg:province":"Devon",
    "sg:tags":[
        "mobile",
        "disco"
    ],
    "wof:name":"Lazer Disco",
    "wof:placetype":"venue"
},
  "geometry": {"coordinates":[-4.126553,50.405006],"type":"Point"}
}