{
  "type": "Feature",
  "properties": {
    "addr:full":"35&37 Pringle Street Blackburn Lancashire BB1 1SD",
    "addr:housenumber":"35 & 37",
    "addr:postcode":"bb1 1sd",
    "addr:street":"Pringle Street",
    "iso:country":"GB",
    "sg:address":"35&37 Pringle Street",
    "sg:city":"Blackburn",
    "sg:classifiers":[
        {
            "category":"Food & Beverages",
            "subcategory":"Supermarket",
            "type":"Retail Goods"
        }
    ],
    "sg:postcode":"BB1 1SD",
    "sg:province":"Lancashire",
    "wof:name":"Mohammed & Sons",
    "wof:placetype":"venue"
},
  "geometry": {"coordinates":[-2.4667720795,53.7425193787],"type":"Point"}
}