{
  "type": "Feature",
  "properties": {
    "addr:full":"Polmaise Road Stirling Falkirk FK7 9PU",
    "addr:postcode":"fk7 9pu",
    "addr:street":"Polmaise Road",
    "iso:country":"GB",
    "sg:address":"Polmaise Road",
    "sg:city":"Stirling",
    "sg:classifiers":[
        {
            "category":"Health Services",
            "subcategory":"Hospital",
            "type":"Services"
        }
    ],
    "sg:phone":"+44 1786 451669",
    "sg:postcode":"FK7 9PU",
    "sg:province":"Falkirk",
    "wof:name":"Abbey Hospitals Ltd.",
    "wof:placetype":"venue"
},
  "geometry": {"coordinates":[-3.9536221027,56.1077194214],"type":"Point"}
}