{
  "type": "Feature",
  "properties": {
    "iso:country":"GB",
    "sg:address":"Caerphilly Road, Nelson",
    "sg:city":"Treharris",
    "sg:classifiers":[
        {
            "category":"Bars & Pubs",
            "type":"Food & Drink"
        },
        {
            "category":"Community Center",
            "subcategory":"Social",
            "type":"Public Place"
        }
    ],
    "sg:phone":"+44 1443 450265",
    "sg:postcode":"CF46 6PR",
    "sg:province":"Caerphilly",
    "sg:tags":[
        "pubs",
        "house",
        "inn",
        "activity"
    ],
    "wof:name":"The Rowan Tree Inn",
    "wof:placetype":"venue"
},
  "geometry": {"coordinates":[-3.284113884,51.6526794434],"type":"Point"}
}