{
  "type": "Feature",
  "properties": {
    "addr:full":"2 Hamilton Road Colchester Essex CO3 3DZ",
    "addr:housenumber":"2",
    "addr:postcode":"co3 3dz",
    "addr:street":"Hamilton Road Colchester",
    "iso:country":"GB",
    "sg:address":"2 Hamilton Road",
    "sg:city":"Colchester",
    "sg:classifiers":[
        {
            "category":"Education",
            "subcategory":"School",
            "type":"Public Place"
        }
    ],
    "sg:phone":"+44 1206 768277",
    "sg:postcode":"CO3 3DZ",
    "sg:province":"Essex",
    "sg:tags":[
        "private",
        "tuition"
    ],
    "wof:name":"George Gallagher",
    "wof:placetype":"venue"
},
  "geometry": {"coordinates":[0.8880919814,51.8813896179],"type":"Point"}
}