{
  "type": "Feature",
  "properties": {
    "addr:full":"Common Road Ingatestone Essex CM4 9NF",
    "addr:postcode":"cm4 9nf",
    "addr:street":"Common Road",
    "iso:country":"GB",
    "sg:address":"Common Road",
    "sg:city":"Ingatestone",
    "sg:classifiers":[
        {
            "category":"Restaurant",
            "type":"Food & Drink"
        }
    ],
    "sg:phone":"+44 1277 841831",
    "sg:postcode":"CM4 9NF",
    "sg:province":"Essex",
    "wof:name":"Bakers Arms Restaurant",
    "wof:placetype":"venue"
},
  "geometry": {"coordinates":[0.4495410025,51.6637001038],"type":"Point"}
}