{
  "type": "Feature",
  "properties": {
    "addr:full":"Field Gate Lane, Ugley Grn Bishops Stortford Essex CM22 6HJ",
    "addr:postcode":"cm22 6hj",
    "addr:street":"Field Gate Lane;Stortford",
    "iso:country":"GB",
    "sg:address":"Field Gate Lane, Ugley Grn",
    "sg:city":"Bishops Stortford",
    "sg:classifiers":[
        {
            "category":"Military Area",
            "subcategory":"Air Force Base",
            "type":"Public Place"
        }
    ],
    "sg:postcode":"CM22 6HJ",
    "sg:province":"Essex",
    "sg:tags":[
        "water",
        "treatment"
    ],
    "wof:name":"C C Camp & Co.",
    "wof:placetype":"venue"
},
  "geometry": {"coordinates":[0.2156569958,51.9247016907],"type":"Point"}
}