{
  "type": "Feature",
  "properties": {
    "addr:full":"1 Grenfell Road Maidenhead Berkshire SL6 1HN",
    "addr:housenumber":"1",
    "addr:postcode":"sl6 1hn",
    "addr:street":"Grenfell Road",
    "iso:country":"GB",
    "sg:address":"1 Grenfell Road",
    "sg:city":"Maidenhead",
    "sg:classifiers":[
        {
            "category":"Professional",
            "subcategory":"Computer Services",
            "type":"Services"
        }
    ],
    "sg:postcode":"SL6 1HN",
    "sg:province":"Berkshire",
    "sg:tags":[
        "system",
        "software"
    ],
    "wof:name":"Cincom Systems (U K) Ltd.",
    "wof:placetype":"venue"
},
  "geometry": {"coordinates":[-0.7233880162,51.5194778442],"type":"Point"}
}