{
  "type": "Feature",
  "properties": {
    "iso:country":"GB",
    "sg:address":"49 Kingshill Avenue",
    "sg:city":"Romford",
    "sg:classifiers":[
        {
            "category":"Professional",
            "subcategory":"Secretarial Services",
            "type":"Services"
        }
    ],
    "sg:phone":"+44 1708 750587",
    "sg:postcode":"RM5 2SB",
    "sg:province":"Essex",
    "wof:name":"Typing Services",
    "wof:placetype":"venue"
},
  "geometry": {"coordinates":[0.1696469933,51.6071510315],"type":"Point"}
}