{
  "type": "Feature",
  "properties": {
    "addr:full":"49 Kingshill Avenue Romford Essex RM5 2SB",
    "addr:housenumber":"49",
    "addr:postcode":"rm5 2sb",
    "addr:street":"Kingshill Avenue",
    "iso:country":"GB",
    "sg:address":"49 Kingshill Avenue",
    "sg:city":"Romford",
    "sg:classifiers":[
        {
            "category":"Professional",
            "subcategory":"Secretarial Services",
            "type":"Services"
        }
    ],
    "sg:phone":"+44 1708 750587",
    "sg:postcode":"RM5 2SB",
    "sg:province":"Essex",
    "wof:name":"Typing Services",
    "wof:placetype":"venue"
},
  "geometry": {"coordinates":[0.1696469933,51.6071510315],"type":"Point"}
}