{
  "type": "Feature",
  "properties": {
    "iso:country":"GB",
    "sg:address":"Broadmead Av",
    "sg:city":"Northampton",
    "sg:classifiers":[
        {
            "category":"Place Of Worship",
            "type":"Public Place"
        }
    ],
    "sg:phone":"+44 1604 407074",
    "sg:postcode":"NN3 2RA",
    "sg:province":"Northamptonshire",
    "wof:name":"St Alban The Martyr C of E",
    "wof:placetype":"venue"
},
  "geometry": {"coordinates":[-0.857785,52.260651],"type":"Point"}
}