{
  "type": "Feature",
  "properties": {
    "addr:full":"K9 Ind Est, Ferry Lane Rainham Essex RM13 9BY",
    "addr:postcode":"rm13 9by",
    "addr:street":"Est Ferry Lane",
    "iso:country":"GB",
    "sg:address":"K9 Ind Est, Ferry Lane",
    "sg:city":"Rainham",
    "sg:classifiers":[
        {
            "category":"Freight",
            "type":"Transportation"
        }
    ],
    "sg:phone":"+44 1708 526177",
    "sg:postcode":"RM13 9BY",
    "sg:province":"Essex",
    "sg:tags":[
        "haulage",
        "road"
    ],
    "wof:name":"Stalkers European Transport Services Ltd",
    "wof:placetype":"venue"
},
  "geometry": {"coordinates":[0.190426,51.517914],"type":"Point"}
}