{
  "type": "Feature",
  "properties": {
    "addr:full":"Chart Clo Croydon Surrey CR0 7YF",
    "addr:postcode":"cr0 7yf",
    "iso:country":"GB",
    "sg:address":"Chart Clo",
    "sg:city":"Croydon",
    "sg:classifiers":[
        {
            "category":"Social Services",
            "subcategory":"Adult Care",
            "type":"Services"
        }
    ],
    "sg:phone":"+44 20 8656 4781",
    "sg:postcode":"CR0 7YF",
    "sg:province":"Surrey",
    "sg:tags":[
        "housing",
        "sheltered"
    ],
    "wof:name":"Allington Court Sheltered Housing",
    "wof:placetype":"venue"
},
  "geometry": {"coordinates":[-0.0591589995,51.3892822266],"type":"Point"}
}