{
  "type": "Feature",
  "properties": {
    "addr:full":"15 Pepperscoombe Lane, Beeding Steyning West Sussex BN44 3HS",
    "addr:housenumber":"15",
    "addr:postcode":"bn44 3hs",
    "addr:street":"Pepperscoombe Lane",
    "iso:country":"GB",
    "sg:address":"15 Pepperscoombe Lane, Beeding",
    "sg:city":"Steyning",
    "sg:classifiers":[
        {
            "category":"Building & Trades",
            "subcategory":"Construction",
            "type":"Services"
        }
    ],
    "sg:phone":"+44 1903 879560",
    "sg:postcode":"BN44 3HS",
    "sg:province":"West Sussex",
    "sg:tags":[
        "roofing"
    ],
    "wof:name":"Gary Standing Roofing",
    "wof:placetype":"venue"
},
  "geometry": {"coordinates":[-0.303574,50.886147],"type":"Point"}
}