{
  "type": "Feature",
  "properties": {
    "addr:full":"182 Preston Road, Standish Wigan Lancashire WN6 0NP",
    "addr:housenumber":"182",
    "addr:postcode":"wn6 0np",
    "addr:street":"Preston Road",
    "iso:country":"GB",
    "sg:address":"182 Preston Road, Standish",
    "sg:city":"Wigan",
    "sg:classifiers":[
        {
            "category":"Retail",
            "subcategory":"Driving School",
            "type":"Services"
        }
    ],
    "sg:postcode":"WN6 0NP",
    "sg:province":"Lancashire",
    "wof:name":"John Fairhurst",
    "wof:placetype":"venue"
},
  "geometry": {"coordinates":[-2.6698269844,53.5908584595],"type":"Point"}
}