{
  "type": "Feature",
  "properties": {
    "iso:country":"GB",
    "sg:address":"141 Cricklade Street",
    "sg:city":"Cirencester",
    "sg:classifiers":[
        {
            "category":"Personal",
            "subcategory":"Beauty Salon",
            "type":"Services"
        }
    ],
    "sg:phone":"+44 1285 651903",
    "sg:postcode":"GL7 1JF",
    "sg:province":"Gloucestershire",
    "sg:tags":[
        "unisex",
        "hairdresser"
    ],
    "wof:name":"Robert John",
    "wof:placetype":"venue"
},
  "geometry": {"coordinates":[-1.966404,51.714291],"type":"Point"}
}