{
  "type": "Feature",
  "properties": {
    "addr:full":"50b Murray Place Stirling Stirling FK8 2BX",
    "addr:housenumber":"50b",
    "addr:postcode":"fk8 2bx",
    "addr:street":"Murray Place",
    "iso:country":"GB",
    "sg:address":"50b Murray Place",
    "sg:city":"Stirling",
    "sg:classifiers":[
        {
            "category":"Shopping",
            "subcategory":"Catalog Store",
            "type":"Retail Goods"
        }
    ],
    "sg:phone":"+44 1786 472115",
    "sg:postcode":"FK8 2BX",
    "sg:province":"Stirling",
    "sg:tags":[
        "shop",
        "catalogue",
        "showroom"
    ],
    "wof:name":"Argos Ltd",
    "wof:placetype":"venue"
},
  "geometry": {"coordinates":[-3.9371440411,56.1195106506],"type":"Point"}
}