{
  "type": "Feature",
  "properties": {
    "iso:country":"GB",
    "sg:address":"242 Kingston Road",
    "sg:city":"New Malden",
    "sg:classifiers":[
        {
            "category":"Manufacturing",
            "subcategory":"Tools & Machinery",
            "type":"Manufacturing & Wholesale Goods"
        }
    ],
    "sg:postcode":"KT3 3RN",
    "sg:province":"Surrey",
    "sg:tags":[
        "society",
        "friendly"
    ],
    "wof:name":"Chewvale Insurance Consultants",
    "wof:placetype":"venue"
},
  "geometry": {"coordinates":[-0.274221,51.403275],"type":"Point"}
}