{
  "type": "Feature",
  "properties": {
    "iso:country":"GB",
    "sg:address":"97 Charleston Drive",
    "sg:city":"Dundee",
    "sg:classifiers":[
        {
            "category":"Food & Beverages",
            "subcategory":"Groceries & Convenience Stores",
            "type":"Retail Goods"
        }
    ],
    "sg:phone":"+44 1382 645801",
    "sg:postcode":"DD2 2HB",
    "sg:province":"Dundee City",
    "wof:name":"Mace",
    "wof:placetype":"venue"
},
  "geometry": {"coordinates":[-3.0248548985,56.4699630737],"type":"Point"}
}