{
  "type": "Feature",
  "properties": {
    "addr:full":"Aberford Rd Leeds West Yorkshire LS15 4EF",
    "addr:postcode":"ls15 4ef",
    "addr:street":"Aberford Rd",
    "iso:country":"GB",
    "sg:address":"Aberford Rd",
    "sg:city":"Leeds",
    "sg:classifiers":[
        {
            "category":"Autos & Motor Vehicles",
            "subcategory":"Automobile Sales",
            "type":"Retail Goods"
        }
    ],
    "sg:phone":"+44 113 281 3811",
    "sg:postcode":"LS15 4EF",
    "sg:province":"West Yorkshire",
    "sg:tags":[
        "car"
    ],
    "wof:name":"Capitol Car Sales",
    "wof:placetype":"venue"
},
  "geometry": {"coordinates":[-1.392936945,53.831401825],"type":"Point"}
}