{
  "type": "Feature",
  "properties": {
    "iso:country":"GB",
    "sg:address":"9 Wharf Street",
    "sg:city":"Sowerby Bridge",
    "sg:classifiers":[
        {
            "category":"Shopping",
            "subcategory":"Baby Store",
            "type":"Retail Goods"
        }
    ],
    "sg:postcode":"HX6 2EG",
    "sg:province":"West Yorkshire",
    "sg:tags":[
        "babywear",
        "childrens"
    ],
    "wof:name":"Deb Ann Fashions",
    "wof:placetype":"venue"
},
  "geometry": {"coordinates":[-1.9096479416,53.7091407776],"type":"Point"}
}