{
  "type": "Feature",
  "properties": {
    "addr:full":"224 Cateswell Rd, Sparkhill Birmingham West Midlands B11 3DZ",
    "addr:housenumber":"224",
    "addr:postcode":"b11 3dz",
    "addr:street":"Cateswell Rd",
    "iso:country":"GB",
    "sg:address":"224 Cateswell Rd, Sparkhill",
    "sg:city":"Birmingham",
    "sg:classifiers":[
        {
            "category":"Social Services",
            "subcategory":"Job Training",
            "type":"Services"
        }
    ],
    "sg:phone":"+44 121 706 8743",
    "sg:postcode":"B11 3DZ",
    "sg:province":"West Midlands",
    "sg:tags":[
        "translator",
        "interpreter"
    ],
    "wof:name":"Griffiths,Alun,",
    "wof:placetype":"venue"
},
  "geometry": {"coordinates":[-1.842459,52.444794],"type":"Point"}
}