{
  "type": "Feature",
  "properties": {
    "addr:full":"Unit, 18, South Grove Walthamstow Greater London E17 7NX",
    "addr:housenumber":"unit 18",
    "addr:postcode":"e17 7nx",
    "addr:street":"South Grove",
    "iso:country":"GB",
    "sg:address":"Unit, 18, South Grove",
    "sg:city":"Walthamstow",
    "sg:classifiers":[
        {
            "category":"Shopping",
            "subcategory":"Computers & Home Electronics",
            "type":"Retail Goods"
        }
    ],
    "sg:phone":"+44 20 8521 0021",
    "sg:postcode":"E17 7NX",
    "sg:province":"Greater London",
    "wof:name":"Joshua Enterprises Ltd",
    "wof:placetype":"venue"
},
  "geometry": {"coordinates":[-0.0298439991,51.5805053711],"type":"Point"}
}