{
  "type": "Feature",
  "properties": {
    "iso:country":"GB",
    "sg:address":"Brix Courtyard",
    "sg:city":"Great Missenden",
    "sg:classifiers":[
        {
            "category":"Professional",
            "subcategory":"Computer Services",
            "type":"Services"
        }
    ],
    "sg:phone":"+44 1494 866031",
    "sg:postcode":"HP16 9BH",
    "sg:province":"Buckinghamshire",
    "sg:tags":[
        "system",
        "software"
    ],
    "wof:name":"Medical Systems Ltd.",
    "wof:placetype":"venue"
},
  "geometry": {"coordinates":[-0.709043,51.704067],"type":"Point"}
}