{
  "type": "Feature",
  "properties": {
    "addr:full":"Bog House Farm, Mickleby Saltburn-by-the-sea North Yorkshire TS13 5NA",
    "addr:housenumber":"mickleby",
    "addr:postcode":"ts13 5na",
    "addr:street":"Saltburn-By-The-Sea",
    "iso:country":"GB",
    "sg:address":"Bog House Farm, Mickleby",
    "sg:city":"Saltburn-by-the-sea",
    "sg:classifiers":[
        {
            "category":"Farming",
            "subcategory":"Livestock Farm",
            "type":"Manufacturing & Wholesale Goods"
        }
    ],
    "sg:phone":"+44 1947 840075",
    "sg:postcode":"TS13 5NA",
    "sg:province":"North Yorkshire",
    "sg:tags":[
        "others"
    ],
    "wof:name":"Summerson R & Sons",
    "wof:placetype":"venue"
},
  "geometry": {"coordinates":[-0.7720580101,54.5102653503],"type":"Point"}
}