{
  "type": "Feature",
  "properties": {
    "iso:country":"GB",
    "sg:address":"Castle St",
    "sg:city":"Kingston Upon Thames",
    "sg:classifiers":[
        {
            "category":"Organizations",
            "subcategory":"Non-profit Organization",
            "type":"Services"
        }
    ],
    "sg:phone":"+44 20 8547 3937",
    "sg:postcode":"KT1 1SS",
    "sg:province":"Greater London",
    "sg:tags":[
        "organisation",
        "voluntary",
        "charity"
    ],
    "wof:name":"National Schizophrenia Fellowship",
    "wof:placetype":"venue"
},
  "geometry": {"coordinates":[-0.301934,51.411461],"type":"Point"}
}