{
  "type": "Feature",
  "properties": {
    "addr:full":"15 Macklin Street London Greater London WC2B 5NG",
    "addr:housenumber":"15",
    "addr:postcode":"wc2b 5ng",
    "addr:street":"Macklin Street",
    "iso:country":"GB",
    "sg:address":"15 Macklin Street",
    "sg:city":"London",
    "sg:classifiers":[
        {
            "category":"Education",
            "subcategory":"University",
            "type":"Public Place"
        }
    ],
    "sg:phone":"+44 20 7419 4400",
    "sg:postcode":"WC2B 5NG",
    "sg:province":"Greater London",
    "sg:tags":[
        "higher"
    ],
    "wof:name":"Martran College Ltd.",
    "wof:placetype":"venue"
},
  "geometry": {"coordinates":[-0.122676,51.5160255432],"type":"Point"}
}