{
  "type": "Feature",
  "properties": {
    "addr:full":"St Augustines Cottage, High St Mill Hill Greater London NW7 1QY",
    "addr:postcode":"nw7 1qy",
    "addr:street":"High St",
    "iso:country":"GB",
    "sg:address":"St Augustines Cottage, High St",
    "sg:city":"Mill Hill",
    "sg:classifiers":[
        {
            "category":"Wholesale",
            "subcategory":"Books, Periodicals, & Newspapers",
            "type":"Manufacturing & Wholesale Goods"
        }
    ],
    "sg:phone":"+44 20 8959 3321",
    "sg:postcode":"NW7 1QY",
    "sg:province":"Greater London",
    "sg:tags":[
        "publishing"
    ],
    "wof:name":"Koeksuster Publications",
    "wof:placetype":"venue"
},
  "geometry": {"coordinates":[-0.22849,51.618279],"type":"Point"}
}