{
  "type": "Feature",
  "properties": {
    "iso:country":"GB",
    "sg:address":"91 Fulham Palace Road",
    "sg:city":"London",
    "sg:classifiers":[
        {
            "category":"Real Estate",
            "subcategory":"Real Estate Agent",
            "type":"Services"
        }
    ],
    "sg:phone":"+44 20 8748 9797",
    "sg:postcode":"W6 8JA",
    "sg:province":"Greater London",
    "wof:name":"Shield Property Services Ltd",
    "wof:placetype":"venue"
},
  "geometry": {"coordinates":[-0.222829,51.488937],"type":"Point"}
}