{
  "type": "Feature",
  "properties": {
    "addr:full":"13 Trenchard Rd Lydney Gloucestershire GL15 6AR",
    "addr:housenumber":"13",
    "addr:postcode":"gl15 6ar",
    "addr:street":"Trenchard Rd",
    "iso:country":"GB",
    "sg:address":"13 Trenchard Rd",
    "sg:city":"Lydney",
    "sg:classifiers":[
        {
            "category":"Professional",
            "subcategory":"Employment Agencies",
            "type":"Services"
        }
    ],
    "sg:phone":"+44 1594 564515",
    "sg:postcode":"GL15 6AR",
    "sg:province":"Gloucestershire",
    "sg:tags":[
        "consultant"
    ],
    "wof:name":"Quartet Employment",
    "wof:placetype":"venue"
},
  "geometry": {"coordinates":[-2.5710589886,51.7469902039],"type":"Point"}
}