{
  "type": "Feature",
  "properties": {
    "addr:full":"Tickenham Forge, Stone-edge Batch, Tickenham Clevedon Somerset BS21 6SE",
    "addr:housenumber":"tickenham;tickenham",
    "addr:postcode":"bs21 6se",
    "addr:street":"Stone-Edge",
    "iso:country":"GB",
    "sg:address":"Tickenham Forge, Stone-edge Batch, Tickenham",
    "sg:city":"Clevedon",
    "sg:classifiers":[
        {
            "category":"Manufacturing",
            "subcategory":"Metals",
            "type":"Manufacturing & Wholesale Goods"
        }
    ],
    "sg:postcode":"BS21 6SE",
    "sg:province":"Somerset",
    "sg:tags":[
        "blacksmith",
        "forgemasters"
    ],
    "wof:name":"Strawberry Steel",
    "wof:placetype":"venue"
},
  "geometry": {"coordinates":[-2.8550388813,51.43592453],"type":"Point"}
}