{
  "type": "Feature",
  "properties": {
    "addr:full":"7 The Green, Blakesley Towcester Buckinghamshire NN12 8RD",
    "addr:housenumber":"7",
    "addr:postcode":"nn12 8rd",
    "addr:street":"The Green",
    "iso:country":"GB",
    "sg:address":"7 The Green, Blakesley",
    "sg:city":"Towcester",
    "sg:classifiers":[
        {
            "category":"Home & Garden",
            "subcategory":"Garden Supply",
            "type":"Retail Goods"
        },
        {
            "category":"Farming",
            "subcategory":"Crops",
            "type":"Manufacturing & Wholesale Goods"
        },
        {
            "category":"Farming",
            "subcategory":"Livestock Farm",
            "type":"Manufacturing & Wholesale Goods"
        }
    ],
    "sg:phone":"+44 1327 860266",
    "sg:postcode":"NN12 8RD",
    "sg:province":"Buckinghamshire",
    "sg:tags":[
        "bulb",
        "arable",
        "grower",
        "others"
    ],
    "wof:name":"S M Sheppard & Sons",
    "wof:placetype":"venue"
},
  "geometry": {"coordinates":[-1.122367,52.118122],"type":"Point"}
}