{
  "type": "Feature",
  "properties": {
    "addr:full":"54-56 Rabans Close, Rabans Lane Industrial Area Aylesbury Buckinghamshire HP19 8RS",
    "addr:housenumber":"54-56",
    "addr:postcode":"hp19 8rs",
    "addr:street":"Rabans Close Rabans Lane",
    "iso:country":"GB",
    "sg:address":"54-56 Rabans Close, Rabans Lane Industrial Area",
    "sg:city":"Aylesbury",
    "sg:classifiers":[
        {
            "category":"Wholesale",
            "subcategory":"Office Equipment",
            "type":"Manufacturing & Wholesale Goods"
        },
        {
            "category":"Professional",
            "type":"Services"
        }
    ],
    "sg:phone":"+44 1296 420444",
    "sg:postcode":"HP19 8RS",
    "sg:province":"Buckinghamshire",
    "sg:tags":[
        "control",
        "system"
    ],
    "wof:name":"Negretti Systems Ltd.",
    "wof:placetype":"venue"
},
  "geometry": {"coordinates":[-0.848918,51.823307],"type":"Point"}
}