{
  "type": "Feature",
  "properties": {
    "addr:full":"50 Laburnum Clo Great Yarmouth Norfolk NR31 8JB",
    "addr:housenumber":"50",
    "addr:postcode":"nr31 8jb",
    "addr:street":"Laburnum Clo Great Yarmouth",
    "iso:country":"GB",
    "sg:address":"50 Laburnum Clo",
    "sg:city":"Great Yarmouth",
    "sg:classifiers":[
        {
            "category":"Taxi",
            "type":"Transportation"
        }
    ],
    "sg:phone":"+44 1493 603082",
    "sg:postcode":"NR31 8JB",
    "sg:province":"Norfolk",
    "sg:tags":[
        "mini",
        "cab"
    ],
    "wof:name":"A A A Minibuses",
    "wof:placetype":"venue"
},
  "geometry": {"coordinates":[1.696533,52.581516],"type":"Point"}
}