{
  "type": "Feature",
  "properties": {
    "iso:country":"GB",
    "sg:address":"Damson Way, Fountain Dr, Queenn Marys Av",
    "sg:city":"Carshalton",
    "sg:classifiers":[
        {
            "category":"Social Services",
            "type":"Services"
        },
        {
            "category":"Retail",
            "subcategory":"Driving School",
            "type":"Services"
        }
    ],
    "sg:phone":"+44 20 8770 1151",
    "sg:postcode":"SM5 4NR",
    "sg:province":"Surrey",
    "sg:tags":[
        "disability"
    ],
    "sg:website":"http://www.qefd.org",
    "wof:name":"Queen Elizabeth's Foundation Mobility Centre",
    "wof:placetype":"venue"
},
  "geometry": {"coordinates":[-0.16674,51.347748],"type":"Point"}
}