{
  "type": "Feature",
  "properties": {
    "addr:full":"Falcongate House, Marine Park, Gapton Hall Road Great Yarmouth Norfolk NR31 0NB",
    "addr:postcode":"nr31 0nb",
    "addr:street":"Falcongate;Hall Road",
    "iso:country":"GB",
    "sg:address":"Falcongate House, Marine Park, Gapton Hall Road",
    "sg:city":"Great Yarmouth",
    "sg:classifiers":[
        {
            "category":"Freight",
            "type":"Transportation"
        }
    ],
    "sg:phone":"+44 1493 44144",
    "sg:postcode":"NR31 0NB",
    "sg:province":"Norfolk",
    "sg:tags":[
        "haulage",
        "road",
        "forwarders"
    ],
    "wof:name":"F S L",
    "wof:placetype":"venue"
},
  "geometry": {"coordinates":[1.71314,52.598476],"type":"Point"}
}