{
  "type": "Feature",
  "properties": {
    "addr:full":"288 Two Mile Hill Rd Bristol City of Bristol BS15 1AT",
    "addr:housenumber":"288",
    "addr:postcode":"bs15 1at",
    "addr:street":"Two Mile Hill Rd",
    "iso:country":"GB",
    "sg:address":"288 Two Mile Hill Rd",
    "sg:city":"Bristol",
    "sg:classifiers":[
        {
            "category":"Professional",
            "type":"Services"
        }
    ],
    "sg:postcode":"BS15 1AT",
    "sg:province":"City of Bristol",
    "sg:tags":[
        "directory",
        "pub"
    ],
    "wof:name":"Naish,R P & V E,",
    "wof:placetype":"venue"
},
  "geometry": {"coordinates":[-2.5149190426,51.4632339478],"type":"Point"}
}