{
  "type": "Feature",
  "properties": {
    "iso:country":"GB",
    "sg:address":"49 Kingsley Rd, Kings Norton",
    "sg:city":"Birmingham",
    "sg:classifiers":[
        {
            "category":"Health Services",
            "subcategory":"Health Practitioner",
            "type":"Services"
        }
    ],
    "sg:phone":"+44 121 459 3179",
    "sg:postcode":"B30 1EH",
    "sg:province":"West Midlands",
    "sg:tags":[
        "therapist",
        "speech"
    ],
    "wof:name":"The How to Stop Stammering Centre",
    "wof:placetype":"venue"
},
  "geometry": {"coordinates":[-1.945804,52.418037],"type":"Point"}
}