{
  "type": "Feature",
  "properties": {
    "addr:full":"26 Gilman Place Stoke-on-trent Staffordshire ST1 3PG",
    "addr:housenumber":"26",
    "addr:postcode":"st1 3pg",
    "addr:street":"Gilman Place",
    "iso:country":"GB",
    "sg:address":"26 Gilman Place",
    "sg:city":"Stoke-on-trent",
    "sg:classifiers":[
        {
            "category":"Manufacturing",
            "subcategory":"Tools & Machinery",
            "type":"Manufacturing & Wholesale Goods"
        }
    ],
    "sg:postcode":"ST1 3PG",
    "sg:province":"Staffordshire",
    "sg:tags":[
        "society",
        "friendly"
    ],
    "wof:name":"Bridamar Investments & Holding Co.  Ltd.",
    "wof:placetype":"venue"
},
  "geometry": {"coordinates":[-2.1722450256,53.0250968933],"type":"Point"}
}