{
  "type": "Feature",
  "properties": {
    "iso:country":"GB",
    "sg:address":"Nutnall Wks, Warbage La",
    "sg:city":"Stourbridge",
    "sg:classifiers":[
        {
            "category":"Autos & Motor Vehicles",
            "subcategory":"Automobile Sales",
            "type":"Retail Goods"
        },
        {
            "category":"Retail",
            "subcategory":"Auto Repair",
            "type":"Services"
        }
    ],
    "sg:postcode":"DY9 0AR",
    "sg:province":"West Midlands",
    "sg:tags":[
        "modification",
        "garage",
        "car"
    ],
    "wof:name":"Jones,R,",
    "wof:placetype":"venue"
},
  "geometry": {"coordinates":[-2.10915,52.361881],"type":"Point"}
}