{
  "type": "Feature",
  "properties": {
    "iso:country":"GB",
    "sg:address":"15 Westfield Street",
    "sg:city":"St Helens",
    "sg:classifiers":[
        {
            "category":"Food & Beverages",
            "subcategory":"Meat & Fish",
            "type":"Retail Goods"
        }
    ],
    "sg:phone":"+44 1744 23583",
    "sg:postcode":"WA10 1QA",
    "sg:province":"Merseyside",
    "sg:tags":[
        "chip"
    ],
    "wof:name":"Chipmunks",
    "wof:placetype":"venue"
},
  "geometry": {"coordinates":[-2.7394440174,53.4535217285],"type":"Point"}
}