{
  "type": "Feature",
  "properties": {
    "addr:full":"Kingskerswell Road Torquay Devon TQ2 8JY",
    "addr:postcode":"tq2 8jy",
    "addr:street":"Kingskerswell Road",
    "iso:country":"GB",
    "sg:address":"Kingskerswell Road",
    "sg:city":"Torquay",
    "sg:classifiers":[
        {
            "category":"Arena",
            "subcategory":"Sports Club",
            "type":"Entertainment"
        }
    ],
    "sg:phone":"+44 1803 313350",
    "sg:postcode":"TQ2 8JY",
    "sg:province":"Devon",
    "wof:name":"Wessex Ski Club",
    "wof:placetype":"venue"
},
  "geometry": {"coordinates":[-3.544189,50.49712],"type":"Point"}
}