{
  "type": "Feature",
  "properties": {
    "iso:country":"GB",
    "sg:address":"318 Haydons Road",
    "sg:city":"London",
    "sg:classifiers":[
        {
            "category":"Retail",
            "subcategory":"Auto Repair",
            "type":"Services"
        }
    ],
    "sg:phone":"+44 20 8540 4034",
    "sg:postcode":"SW19 8JZ",
    "sg:province":"Greater London",
    "sg:tags":[
        "body",
        "car"
    ],
    "wof:name":"Dowell Bros Coachworks",
    "wof:placetype":"venue"
},
  "geometry": {"coordinates":[-0.190148,51.426456],"type":"Point"}
}