{
  "type": "Feature",
  "properties": {
    "addr:full":"Upper Elms Road Aldershot Hampshire GU11 3ES",
    "addr:postcode":"gu11 3es",
    "addr:street":"Upper Elms Road",
    "iso:country":"GB",
    "sg:address":"Upper Elms Road",
    "sg:city":"Aldershot",
    "sg:classifiers":[
        {
            "category":"Place Of Worship",
            "type":"Public Place"
        }
    ],
    "sg:phone":"+44 1252 321645",
    "sg:postcode":"GU11 3ES",
    "sg:province":"Hampshire",
    "wof:name":"Aldershot Baptist Church",
    "wof:placetype":"venue"
},
  "geometry": {"coordinates":[-0.7666689754,51.2467498779],"type":"Point"}
}