{
  "type": "Feature",
  "properties": {
    "addr:full":"18 College Street Burnham-on-sea Somerset TA8 1AE",
    "addr:housenumber":"18",
    "addr:postcode":"ta8 1ae",
    "addr:street":"College Street",
    "iso:country":"GB",
    "sg:address":"18 College Street",
    "sg:city":"Burnham-on-sea",
    "sg:classifiers":[
        {
            "category":"Real Estate",
            "subcategory":"Real Estate Agent",
            "type":"Services"
        }
    ],
    "sg:phone":"+44 1278 782266",
    "sg:postcode":"TA8 1AE",
    "sg:province":"Somerset",
    "wof:name":"Abbott & Frost",
    "wof:placetype":"venue"
},
  "geometry": {"coordinates":[-2.996913,51.237053],"type":"Point"}
}