{
  "type": "Feature",
  "properties": {
    "iso:country":"GB",
    "sg:address":"Maghull Business Centre, Maghull",
    "sg:city":"Liverpool",
    "sg:classifiers":[
        {
            "category":"Professional",
            "subcategory":"Engineering",
            "type":"Services"
        }
    ],
    "sg:phone":"+44 151 949 0324",
    "sg:postcode":"L31 2HB",
    "sg:province":"Lancashire",
    "sg:tags":[
        "contractor",
        "electrical",
        "engineer"
    ],
    "wof:name":"Richard Williams",
    "wof:placetype":"venue"
},
  "geometry": {"coordinates":[-2.94491,53.51302],"type":"Point"}
}