{
  "type": "Feature",
  "properties": {
    "iso:country":"GB",
    "sg:address":"130 Canada Drive, Cherry Burton",
    "sg:city":"Beverley",
    "sg:classifiers":[
        {
            "category":"Shopping",
            "subcategory":"Books",
            "type":"Retail Goods"
        }
    ],
    "sg:phone":"+44 1964 550573",
    "sg:postcode":"HU17 7SB",
    "sg:province":"East Riding of Yorkshire",
    "wof:name":"The Hutton Press Ltd.",
    "wof:placetype":"venue"
},
  "geometry": {"coordinates":[-0.496882,53.867828],"type":"Point"}
}