{
  "type": "Feature",
  "properties": {
    "iso:country":"GB",
    "sg:address":"15 Lilac Av",
    "sg:city":"Wickford",
    "sg:classifiers":[
        {
            "category":"Freight",
            "type":"Transportation"
        }
    ],
    "sg:phone":"+44 1268 733436",
    "sg:postcode":"SS12 0BW",
    "sg:province":"Essex",
    "sg:tags":[
        "shipping"
    ],
    "wof:name":"Rossmoor Agencies Ltd",
    "wof:placetype":"venue"
},
  "geometry": {"coordinates":[0.512477994,51.6089401245],"type":"Point"}
}