{
  "type": "Feature",
  "properties": {
    "iso:country":"GB",
    "sg:address":"2 Alder Close, Parkside",
    "sg:city":"Lichfield",
    "sg:classifiers":[
        {
            "category":"Home & Garden",
            "subcategory":"Kitchen Supply",
            "type":"Retail Goods"
        }
    ],
    "sg:phone":"+44 1543 257199",
    "sg:postcode":"WS14 9UT",
    "sg:province":"Staffordshire",
    "sg:tags":[
        "ware"
    ],
    "wof:name":"J.T Ellis & Co",
    "wof:placetype":"venue"
},
  "geometry": {"coordinates":[-1.8015409708,52.6812705994],"type":"Point"}
}