{
  "type": "Feature",
  "properties": {
    "iso:country":"GB",
    "sg:address":"Highway House, 83 The Highway",
    "sg:city":"Stanmore",
    "sg:classifiers":[
        {
            "category":"Shopping",
            "subcategory":"Stationery & Office Supplies",
            "type":"Retail Goods"
        }
    ],
    "sg:phone":"+44 20 8954 0606",
    "sg:postcode":"HA7 3PL",
    "sg:province":"Greater London",
    "sg:tags":[
        "item",
        "promotional"
    ],
    "wof:name":"Chocolate Heaven A Sweet Inspiration",
    "wof:placetype":"venue"
},
  "geometry": {"coordinates":[-0.3260560036,51.6090660095],"type":"Point"}
}