{
  "type": "Feature",
  "properties": {
    "addr:full":"Cobbs Cottage, Kingston Common Ringwood Dorset BH24 3AY",
    "addr:postcode":"bh24 3ay",
    "iso:country":"GB",
    "sg:address":"Cobbs Cottage, Kingston Common",
    "sg:city":"Ringwood",
    "sg:classifiers":[
        {
            "category":"Organizations",
            "subcategory":"Non-profit Organization",
            "type":"Services"
        }
    ],
    "sg:phone":"+44 1425 477676",
    "sg:postcode":"BH24 3AY",
    "sg:province":"Dorset",
    "sg:tags":[
        "organisation",
        "voluntary",
        "charity"
    ],
    "wof:name":"Happy Dogs",
    "wof:placetype":"venue"
},
  "geometry": {"coordinates":[-1.789763,50.818642],"type":"Point"}
}