{
  "type": "Feature",
  "properties": {
    "iso:country":"GB",
    "sg:address":"1 Potters Lane, Kiln Farm",
    "sg:city":"Milton Keynes",
    "sg:classifiers":[
        {
            "category":"Professional",
            "subcategory":"Testing Lab",
            "type":"Services"
        }
    ],
    "sg:phone":"+44 1908 568844",
    "sg:postcode":"MK11 3LA",
    "sg:province":"Buckinghamshire",
    "sg:tags":[
        "laboratory"
    ],
    "wof:name":"S G E Europe Ltd.",
    "wof:placetype":"venue"
},
  "geometry": {"coordinates":[-0.8204770088,52.0485954285],"type":"Point"}
}