{
  "type": "Feature",
  "properties": {
    "iso:country":"GB",
    "sg:address":"179 Shirley Road",
    "sg:city":"Southampton",
    "sg:classifiers":[
        {
            "category":"Building & Trades",
            "subcategory":"Equipment Rental",
            "type":"Services"
        }
    ],
    "sg:phone":"+44 23 8033 3093",
    "sg:postcode":"SO15 3FG",
    "sg:province":"Hampshire",
    "sg:tags":[
        "hire",
        "centre"
    ],
    "wof:name":"Hss Hire Shops",
    "wof:placetype":"venue"
},
  "geometry": {"coordinates":[-1.422639966,50.9141082764],"type":"Point"}
}