{
  "type": "Feature",
  "properties": {
    "addr:full":"Ryehill Rd Glasgow East Dunbartonshire G21 3EN",
    "addr:postcode":"g21 3en",
    "addr:street":"Ryehill Rd",
    "iso:country":"GB",
    "sg:address":"Ryehill Rd",
    "sg:city":"Glasgow",
    "sg:classifiers":[
        {
            "category":"Place Of Worship",
            "type":"Public Place"
        }
    ],
    "sg:phone":"+44 141 558 8377",
    "sg:postcode":"G21 3EN",
    "sg:province":"East Dunbartonshire",
    "wof:name":"Barmulloch Parish Church",
    "wof:placetype":"venue"
},
  "geometry": {"coordinates":[-4.2048840523,55.8890113831],"type":"Point"}
}