{
  "type": "Feature",
  "properties": {
    "iso:country":"GB",
    "sg:address":"Milngavie Road, Bearsden",
    "sg:city":"Glasgow",
    "sg:classifiers":[
        {
            "category":"Travel",
            "subcategory":"Hotels & Motels",
            "type":"Entertainment"
        }
    ],
    "sg:phone":"+44 141 942 5951",
    "sg:postcode":"G61 3TA",
    "sg:province":"East Dunbartonshire",
    "wof:name":"The Burnbrae",
    "wof:placetype":"venue"
},
  "geometry": {"coordinates":[-4.3152928352,55.9260292053],"type":"Point"}
}