{
  "type": "Feature",
  "properties": {
    "iso:country":"GB",
    "sg:address":"Unit 1 Bristol Rd, Quedgeley",
    "sg:city":"Gloucester",
    "sg:classifiers":[
        {
            "category":"Shopping",
            "subcategory":"Pets & Pet Supplies",
            "type":"Retail Goods"
        }
    ],
    "sg:phone":"+44 1452 506899",
    "sg:postcode":"GL2 4SE",
    "sg:province":"Gloucestershire",
    "wof:name":"Pet City Ltd",
    "wof:placetype":"venue"
},
  "geometry": {"coordinates":[-2.272706,51.836926],"type":"Point"}
}