{
  "type": "Feature",
  "properties": {
    "addr:full":"8 Wyndham Street Sheringham Norfolk NR26 8BA",
    "addr:housenumber":"8",
    "addr:postcode":"nr26 8ba",
    "addr:street":"Wyndham Street",
    "iso:country":"GB",
    "sg:address":"8 Wyndham Street",
    "sg:city":"Sheringham",
    "sg:classifiers":[
        {
            "category":"Shopping",
            "subcategory":"Department Store",
            "type":"Retail Goods"
        },
        {
            "category":"Recreation",
            "subcategory":"Fishing",
            "type":"Entertainment"
        }
    ],
    "sg:phone":"+44 1263 825858",
    "sg:postcode":"NR26 8BA",
    "sg:province":"Norfolk",
    "sg:tags":[
        "angling"
    ],
    "wof:name":"The Bright Outdoor Man",
    "wof:placetype":"venue"
},
  "geometry": {"coordinates":[1.212396,52.944473],"type":"Point"}
}