{
  "type": "Feature",
  "properties": {
    "addr:full":"5 Greywood Close Hartlepool Durham TS27 3QJ",
    "addr:housenumber":"5",
    "addr:postcode":"ts27 3qj",
    "addr:street":"Greywood Close",
    "iso:country":"GB",
    "sg:address":"5 Greywood Close",
    "sg:city":"Hartlepool",
    "sg:classifiers":[
        {
            "category":"Professional",
            "subcategory":"Art Services",
            "type":"Services"
        },
        {
            "category":"Building & Trades",
            "subcategory":"Construction",
            "type":"Services"
        }
    ],
    "sg:phone":"+44 1429 267698",
    "sg:postcode":"TS27 3QJ",
    "sg:province":"Durham",
    "sg:tags":[
        "decorator",
        "painter"
    ],
    "wof:name":"MODERN DECOR",
    "wof:placetype":"venue"
},
  "geometry": {"coordinates":[-1.2534600496,54.7168807983],"type":"Point"}
}