{
  "type": "Feature",
  "properties": {
    "addr:full":"24 Sydney Road Sutton Surrey SM1 2QL",
    "addr:housenumber":"24",
    "addr:postcode":"sm1 2ql",
    "addr:street":"Sydney Road",
    "iso:country":"GB",
    "sg:address":"24 Sydney Road",
    "sg:city":"Sutton",
    "sg:classifiers":[
        {
            "category":"Building & Trades",
            "subcategory":"Construction",
            "type":"Services"
        }
    ],
    "sg:phone":"+44 20 8715 3876",
    "sg:postcode":"SM1 2QL",
    "sg:province":"Surrey",
    "sg:tags":[
        "roofing",
        "contracting"
    ],
    "wof:name":"Ridge Valley",
    "wof:placetype":"venue"
},
  "geometry": {"coordinates":[-0.201285,51.367485],"type":"Point"}
}