{
  "type": "Feature",
  "properties": {
    "addr:full":"58a Chiswick Lane, Chiswick London Greater London W4 2LA",
    "addr:housenumber":"58a",
    "addr:postcode":"w4 2la",
    "addr:street":"Chiswick Lane",
    "iso:country":"GB",
    "sg:address":"58a Chiswick Lane, Chiswick",
    "sg:city":"London",
    "sg:classifiers":[
        {
            "category":"Professional",
            "subcategory":"Accounting & Tax Preparation",
            "type":"Services"
        }
    ],
    "sg:postcode":"W4 2LA",
    "sg:province":"Greater London",
    "sg:tags":[
        "accountant"
    ],
    "wof:name":"4-Way Specialists Ltd",
    "wof:placetype":"venue"
},
  "geometry": {"coordinates":[-0.2507640123,51.4893531799],"type":"Point"}
}