{
  "type": "Feature",
  "properties": {
    "addr:full":"67 High Street Paisley Renfrewshire PA1 2AY",
    "addr:housenumber":"67",
    "addr:postcode":"pa1 2ay",
    "addr:street":"High Street",
    "iso:country":"GB",
    "sg:address":"67 High Street",
    "sg:city":"Paisley",
    "sg:classifiers":[
        {
            "category":"Shopping",
            "subcategory":"Clothing, Apparel, & Fashions",
            "type":"Retail Goods"
        },
        {
            "category":"Real Estate",
            "subcategory":"Architect",
            "type":"Services"
        }
    ],
    "sg:postcode":"PA1 2AY",
    "sg:province":"Renfrewshire",
    "sg:tags":[
        "kilt",
        "menswear",
        "accessory"
    ],
    "wof:name":"Houston Menswear",
    "wof:placetype":"venue"
},
  "geometry": {"coordinates":[-4.4301052094,55.8447532654],"type":"Point"}
}