{
  "type": "Feature",
  "properties": {
    "addr:full":"79 Blake Avenue Barking Essex IG11 9SF",
    "addr:housenumber":"79",
    "addr:postcode":"ig11 9sf",
    "addr:street":"Blake Avenue",
    "iso:country":"GB",
    "sg:address":"79 Blake Avenue",
    "sg:city":"Barking",
    "sg:classifiers":[
        {
            "category":"Government",
            "subcategory":"City Hall",
            "type":"Public Place"
        },
        {
            "category":"Organizations",
            "subcategory":"Community Association",
            "type":"Services"
        }
    ],
    "sg:phone":"+44 20 8591 1002",
    "sg:postcode":"IG11 9SF",
    "sg:province":"Essex",
    "sg:tags":[
        "club",
        "social"
    ],
    "wof:name":"Barking United Services Club Ltd",
    "wof:placetype":"venue"
},
  "geometry": {"coordinates":[0.0989419967,51.5329818726],"type":"Point"}
}