{
  "type": "Feature",
  "properties": {
    "addr:full":"25 Holly Rd Ipswich Suffolk IP5 7HX",
    "addr:housenumber":"25",
    "addr:postcode":"ip5 7hx",
    "addr:street":"Holly Rd",
    "iso:country":"GB",
    "sg:address":"25 Holly Rd",
    "sg:city":"Ipswich",
    "sg:classifiers":[
        {
            "category":"Real Estate",
            "subcategory":"Real Estate Agent",
            "type":"Services"
        }
    ],
    "sg:phone":"+44 1473 626043",
    "sg:postcode":"IP5 7HX",
    "sg:province":"Suffolk",
    "wof:name":"Bolton Property Management Services",
    "wof:placetype":"venue"
},
  "geometry": {"coordinates":[1.2205940485,52.0630378723],"type":"Point"}
}