{
  "type": "Feature",
  "properties": {
    "addr:full":"75a Gloucester Avenue, Primrose Hill London Greater London NW1 8LD",
    "addr:housenumber":"75a",
    "addr:postcode":"nw1 8ld",
    "addr:street":"Gloucester Avenue",
    "iso:country":"GB",
    "sg:address":"75a Gloucester Avenue, Primrose Hill",
    "sg:city":"London",
    "sg:classifiers":[
        {
            "category":"Fast Food",
            "type":"Food & Drink"
        }
    ],
    "sg:phone":"+44 20 7483 0433",
    "sg:postcode":"NW1 8LD",
    "sg:province":"Greater London",
    "sg:tags":[
        "away",
        "take"
    ],
    "wof:name":"The Curly Dog Co. Ltd.",
    "wof:placetype":"venue"
},
  "geometry": {"coordinates":[-0.1513980031,51.5402908325],"type":"Point"}
}