{
  "type": "Feature",
  "properties": {
    "addr:full":"Tamworth Road, Two Gates Tamworth Staffordshire B77 1EA",
    "addr:postcode":"b77 1ea",
    "addr:street":"Tamworth Road Two",
    "iso:country":"GB",
    "sg:address":"Tamworth Road, Two Gates",
    "sg:city":"Tamworth",
    "sg:classifiers":[
        {
            "category":"Wholesale",
            "subcategory":"Scrap",
            "type":"Manufacturing & Wholesale Goods"
        }
    ],
    "sg:phone":"+44 1827 285555",
    "sg:postcode":"B77 1EA",
    "sg:province":"Staffordshire",
    "sg:tags":[
        "waste",
        "metal"
    ],
    "wof:name":"Mormet (Alloys) Ltd.",
    "wof:placetype":"venue"
},
  "geometry": {"coordinates":[-1.682714,52.608887],"type":"Point"}
}