{
  "type": "Feature",
  "properties": {
    "addr:full":"73 Hundred Acres Lane Amersham Buckinghamshire HP7 9BX",
    "addr:housenumber":"73",
    "addr:postcode":"hp7 9bx",
    "addr:street":"Hundred Acres Lane",
    "iso:country":"GB",
    "sg:address":"73 Hundred Acres Lane",
    "sg:city":"Amersham",
    "sg:classifiers":[
        {
            "category":"Health Services",
            "subcategory":"Clinic",
            "type":"Services"
        }
    ],
    "sg:postcode":"HP7 9BX",
    "sg:province":"Buckinghamshire",
    "sg:tags":[
        "aromatherapy"
    ],
    "wof:name":"Lia Holdcroft",
    "wof:placetype":"venue"
},
  "geometry": {"coordinates":[-0.60166502,51.6685943604],"type":"Point"}
}