{
  "type": "Feature",
  "properties": {
    "addr:full":"218 High Street Uckfield East Sussex TN22 1RE",
    "addr:housenumber":"218",
    "addr:postcode":"tn22 1re",
    "addr:street":"High Street",
    "iso:country":"GB",
    "sg:address":"218 High Street",
    "sg:city":"Uckfield",
    "sg:classifiers":[
        {
            "category":"Real Estate",
            "subcategory":"Surveying",
            "type":"Services"
        }
    ],
    "sg:phone":"+44 1825 761618",
    "sg:postcode":"TN22 1RE",
    "sg:province":"East Sussex",
    "sg:tags":[
        "surveyor",
        "valuer"
    ],
    "wof:name":"South East Surveys",
    "wof:placetype":"venue"
},
  "geometry": {"coordinates":[0.097658,50.973553],"type":"Point"}
}