{
  "type": "Feature",
  "properties": {
    "iso:country":"GB",
    "sg:address":"114 Westgate",
    "sg:city":"Skelmersdale",
    "sg:classifiers":[
        {
            "category":"Shopping",
            "subcategory":"Florist",
            "type":"Retail Goods"
        }
    ],
    "sg:phone":"+44 1695 721673",
    "sg:postcode":"WN8 8LP",
    "sg:province":"Lancashire",
    "wof:name":"Skelmersdale Flower Centre",
    "wof:placetype":"venue"
},
  "geometry": {"coordinates":[-2.8039419651,53.546749115],"type":"Point"}
}