{
  "type": "Feature",
  "properties": {
    "iso:country":"GB",
    "sg:address":"Rebecca Street",
    "sg:city":"Bradford",
    "sg:classifiers":[
        {
            "category":"Organizations",
            "subcategory":"Community Association",
            "type":"Services"
        },
        {
            "category":"Organizations",
            "subcategory":"Membership Organization",
            "type":"Services"
        }
    ],
    "sg:phone":"+44 1274 732000",
    "sg:postcode":"BD1 2RX",
    "sg:province":"West Yorkshire",
    "sg:tags":[
        "club",
        "social"
    ],
    "wof:name":"Bradford Irish Democratics League Club",
    "wof:placetype":"venue"
},
  "geometry": {"coordinates":[-1.763734,53.79752],"type":"Point"}
}