{
  "type": "Feature",
  "properties": {
    "iso:country":"GB",
    "sg:address":"2 Crown Passage, Off High St East, Uppingham",
    "sg:city":"Oakham",
    "sg:classifiers":[
        {
            "category":"Personal",
            "subcategory":"Beauty Salon",
            "type":"Services"
        }
    ],
    "sg:postcode":"LE15 9PY",
    "sg:province":"Leicestershire",
    "sg:tags":[
        "unisex",
        "hairdresser"
    ],
    "wof:name":"Roma Hair Nails & Beauty",
    "wof:placetype":"venue"
},
  "geometry": {"coordinates":[-0.7226520181,52.5878257751],"type":"Point"}
}