{
  "type": "Feature",
  "properties": {
    "iso:country":"GB",
    "sg:address":"5 Hood Street",
    "sg:city":"Hull",
    "sg:classifiers":[
        {
            "category":"Manufacturing",
            "subcategory":"Signs",
            "type":"Manufacturing & Wholesale Goods"
        }
    ],
    "sg:phone":"+44 1482 224670",
    "sg:postcode":"HU8 7AL",
    "sg:province":"East Riding of Yorkshire",
    "sg:tags":[
        "nameplate"
    ],
    "wof:name":"Newlove Engravers & Signs Ltd.",
    "wof:placetype":"venue"
},
  "geometry": {"coordinates":[-0.329525,53.751755],"type":"Point"}
}