{
  "type": "Feature",
  "properties": {
    "addr:full":"9 Litell Royd Pontefract West Yorkshire WF7 6EA",
    "addr:housenumber":"9",
    "addr:postcode":"wf7 6ea",
    "addr:street":"Litell Royd Pontefract West",
    "iso:country":"GB",
    "sg:address":"9 Litell Royd",
    "sg:city":"Pontefract",
    "sg:classifiers":[
        {
            "category":"Food & Beverages",
            "subcategory":"Supermarket",
            "type":"Retail Goods"
        }
    ],
    "sg:phone":"+44 1977 791567",
    "sg:postcode":"WF7 6EA",
    "sg:province":"West Yorkshire",
    "wof:name":"Late General Store",
    "wof:placetype":"venue"
},
  "geometry": {"coordinates":[-1.4021689892,53.6783905029],"type":"Point"}
}