{
  "type": "Feature",
  "properties": {
    "addr:full":"3 Fifield Farm Barns, Benson Wallingford Oxfordshire OX10 6EZ",
    "addr:housenumber":"3",
    "addr:postcode":"ox10 6ez",
    "addr:street":"Fifield Farm;Benson",
    "iso:country":"GB",
    "sg:address":"3 Fifield Farm Barns, Benson",
    "sg:city":"Wallingford",
    "sg:classifiers":[
        {
            "category":"Professional",
            "type":"Services"
        }
    ],
    "sg:phone":"+44 1491 838588",
    "sg:postcode":"OX10 6EZ",
    "sg:province":"Oxfordshire",
    "sg:tags":[
        "hire",
        "agency",
        "driver"
    ],
    "wof:name":"Chauffeur Driven Services",
    "wof:placetype":"venue"
},
  "geometry": {"coordinates":[-1.107081,51.624657],"type":"Point"}
}