{
  "type": "Feature",
  "properties": {
    "iso:country":"GB",
    "sg:address":"13 Hope Street",
    "sg:city":"Lanark",
    "sg:classifiers":[
        {
            "category":"Sports & Exercise",
            "subcategory":"Golf",
            "type":"Entertainment"
        }
    ],
    "sg:phone":"+44 1555 870015",
    "sg:postcode":"ML11 7NL",
    "sg:province":"South Lanarkshire",
    "sg:tags":[
        "club",
        "course"
    ],
    "wof:name":"Mouse Valley Golf & Leisure Ltd.",
    "wof:placetype":"venue"
},
  "geometry": {"coordinates":[-3.7816870213,55.6747665405],"type":"Point"}
}