{
  "type": "Feature",
  "properties": {
    "addr:full":"Unit 4, Borough Road, Buckingham Road Industrial Estat Brackley Buckinghamshire NN13 7BE",
    "addr:housenumber":"unit 4",
    "addr:postcode":"nn13 7be",
    "addr:street":"Borough Road Buckingham Road Industrial Estat",
    "iso:country":"GB",
    "sg:address":"Unit 4, Borough Road, Buckingham Road Industrial Estat",
    "sg:city":"Brackley",
    "sg:classifiers":[
        {
            "category":"Professional",
            "type":"Services"
        }
    ],
    "sg:phone":"+44 1280 701611",
    "sg:postcode":"NN13 7BE",
    "sg:province":"Buckinghamshire",
    "sg:tags":[
        "caterer"
    ],
    "wof:name":"Gilmour & Pether Ltd.",
    "wof:placetype":"venue"
},
  "geometry": {"coordinates":[-1.141674,52.023457],"type":"Point"}
}