{
  "type": "Feature",
  "properties": {
    "addr:full":"182 Trinity Road London Greater London SW17 7HR",
    "addr:housenumber":"182",
    "addr:postcode":"sw17 7hr",
    "addr:street":"Trinity Road",
    "iso:country":"GB",
    "sg:address":"182 Trinity Road",
    "sg:city":"London",
    "sg:classifiers":[
        {
            "category":"Real Estate",
            "subcategory":"Architect",
            "type":"Services"
        }
    ],
    "sg:phone":"+44 20 8767 5111",
    "sg:postcode":"SW17 7HR",
    "sg:province":"Greater London",
    "wof:name":"Martin Hewitt Practice",
    "wof:placetype":"venue"
},
  "geometry": {"coordinates":[-0.16631,51.442383],"type":"Point"}
}