{
  "type": "Feature",
  "properties": {
    "iso:country":"GB",
    "sg:address":"18 Brookwood Clo, Worlingham",
    "sg:city":"Beccles",
    "sg:classifiers":[
        {
            "category":"Professional",
            "subcategory":"Engineering",
            "type":"Services"
        }
    ],
    "sg:phone":"+44 1502 716035",
    "sg:postcode":"NR34 7RJ",
    "sg:province":"Norfolk",
    "sg:tags":[
        "consulting",
        "engineer"
    ],
    "wof:name":"Glencrown Consultants Ltd",
    "wof:placetype":"venue"
},
  "geometry": {"coordinates":[1.5978809595,52.448009491],"type":"Point"}
}