{
  "type": "Feature",
  "properties": {
    "addr:full":"40 Hereward Arcade Peterborough Cambridgeshire PE1 1TF",
    "addr:housenumber":"40",
    "addr:postcode":"pe1 1tf",
    "addr:street":"Hereward Arcade",
    "iso:country":"GB",
    "sg:address":"40 Hereward Arcade",
    "sg:city":"Peterborough",
    "sg:classifiers":[
        {
            "category":"Travel",
            "subcategory":"Travel Agent",
            "type":"Entertainment"
        }
    ],
    "sg:phone":"+44 1733 560381",
    "sg:postcode":"PE1 1TF",
    "sg:province":"Cambridgeshire",
    "wof:name":"Lunn Poly Ltd.",
    "wof:placetype":"venue"
},
  "geometry": {"coordinates":[-0.241794,52.574455],"type":"Point"}
}