{
  "type": "Feature",
  "properties": {
    "iso:country":"GB",
    "sg:address":"44 Station Road",
    "sg:city":"Billingham",
    "sg:classifiers":[
        {
            "category":"Retail",
            "subcategory":"Veterinary Services",
            "type":"Services"
        }
    ],
    "sg:phone":"+44 1642 555975",
    "sg:postcode":"TS23 1AB",
    "sg:province":"Durham",
    "sg:tags":[
        "surgeon"
    ],
    "wof:name":"Clifton Lodge Veterinary Group",
    "wof:placetype":"venue"
},
  "geometry": {"coordinates":[-1.2935119867,54.5968093872],"type":"Point"}
}