{
  "type": "Feature",
  "properties": {
    "addr:full":"Hillcrest House 4 Market Hill Maldon Essex CM9 4PZ",
    "addr:housenumber":"4",
    "addr:postcode":"cm9 4pz",
    "addr:street":"Market Hill",
    "iso:country":"GB",
    "sg:address":"Hillcrest House 4 Market Hill",
    "sg:city":"Maldon",
    "sg:classifiers":[
        {
            "category":"Freight",
            "type":"Transportation"
        }
    ],
    "sg:postcode":"CM9 4PZ",
    "sg:province":"Essex",
    "sg:tags":[
        "haulage",
        "road"
    ],
    "wof:name":"Translane International Ltd",
    "wof:placetype":"venue"
},
  "geometry": {"coordinates":[0.6785950065,51.732334137],"type":"Point"}
}