{
  "type": "Feature",
  "properties": {
    "iso:country":"GB",
    "sg:address":"60 Easedale Drive",
    "sg:city":"Southport",
    "sg:classifiers":[
        {
            "category":"Building & Trades",
            "subcategory":"Construction",
            "type":"Services"
        }
    ],
    "sg:phone":"+44 1704 579863",
    "sg:postcode":"PR8 3TS",
    "sg:province":"Lancashire",
    "sg:tags":[
        "builder"
    ],
    "wof:name":"Dave Coulter Building Contractors",
    "wof:placetype":"venue"
},
  "geometry": {"coordinates":[-3.0472431183,53.5963630676],"type":"Point"}
}