{
  "type": "Feature",
  "properties": {
    "addr:full":"4 Granville Terrace, New Ellerby Hull East Riding of Yorkshire HU11 5AR",
    "addr:housenumber":"4",
    "addr:postcode":"hu11 5ar",
    "addr:street":"Granville Terrace",
    "iso:country":"GB",
    "sg:address":"4 Granville Terrace, New Ellerby",
    "sg:city":"Hull",
    "sg:classifiers":[
        {
            "category":"Building & Trades",
            "subcategory":"Construction",
            "type":"Services"
        }
    ],
    "sg:phone":"+44 1964 562770",
    "sg:postcode":"HU11 5AR",
    "sg:province":"East Riding of Yorkshire",
    "sg:tags":[
        "conversion",
        "loft"
    ],
    "wof:name":"R Walker Joiner",
    "wof:placetype":"venue"
},
  "geometry": {"coordinates":[-0.221354,53.832649],"type":"Point"}
}