{
  "type": "Feature",
  "properties": {
    "addr:full":"24 New Market Beccles Norfolk NR34 9HD",
    "addr:housenumber":"24",
    "addr:postcode":"nr34 9hd",
    "addr:street":"New Market",
    "iso:country":"GB",
    "sg:address":"24 New Market",
    "sg:city":"Beccles",
    "sg:classifiers":[
        {
            "category":"Shopping",
            "subcategory":"Jewelry",
            "type":"Retail Goods"
        },
        {
            "category":"Shopping",
            "subcategory":"Comic Books",
            "type":"Retail Goods"
        }
    ],
    "sg:phone":"+44 1502 713714",
    "sg:postcode":"NR34 9HD",
    "sg:province":"Norfolk",
    "sg:tags":[
        "jeweller",
        "sale",
        "jewellery"
    ],
    "wof:name":"Copperfield Jewellers",
    "wof:placetype":"venue"
},
  "geometry": {"coordinates":[1.562664,52.457672],"type":"Point"}
}