{
  "type": "Feature",
  "properties": {
    "iso:country":"GB",
    "sg:address":"20-21 Shepherds Bush Market",
    "sg:city":"London",
    "sg:classifiers":[
        {
            "category":"Food & Beverages",
            "subcategory":"Fruits & Vegetables",
            "type":"Retail Goods"
        }
    ],
    "sg:phone":"+44 20 8749 9508",
    "sg:postcode":"W12 8DF",
    "sg:province":"Greater London",
    "sg:tags":[
        "greengrocer"
    ],
    "wof:name":"Steve Hill",
    "wof:placetype":"venue"
},
  "geometry": {"coordinates":[-0.21869,51.505062],"type":"Point"}
}