{
  "type": "Feature",
  "properties": {
    "addr:full":"Fonthill Bishop Salisbury Wiltshire SP3 5SH",
    "addr:postcode":"sp3 5sh",
    "iso:country":"GB",
    "sg:address":"Fonthill Bishop",
    "sg:city":"Salisbury",
    "sg:classifiers":[
        {
            "category":"Professional",
            "subcategory":"Management & Consulting",
            "type":"Services"
        }
    ],
    "sg:postcode":"SP3 5SH",
    "sg:province":"Wiltshire",
    "sg:tags":[
        "consultant",
        "business"
    ],
    "wof:name":"Svgc Ltd.",
    "wof:placetype":"venue"
},
  "geometry": {"coordinates":[-2.0930800438,51.0952110291],"type":"Point"}
}