{
  "type": "Feature",
  "properties": {
    "addr:full":"28 Riding Clo, Warning Tongue La Doncaster South Yorkshire DN4 6UZ",
    "addr:housenumber":"28",
    "addr:postcode":"dn4 6uz",
    "addr:street":"Riding Clo Warning Tongue La Doncaster South",
    "iso:country":"GB",
    "sg:address":"28 Riding Clo, Warning Tongue La",
    "sg:city":"Doncaster",
    "sg:classifiers":[
        {
            "category":"Health Services",
            "subcategory":"Health Practitioner",
            "type":"Services"
        }
    ],
    "sg:phone":"+44 1302 537464",
    "sg:postcode":"DN4 6UZ",
    "sg:province":"South Yorkshire",
    "sg:tags":[
        "physiotherapist"
    ],
    "wof:name":"Injury Treatment Clinic",
    "wof:placetype":"venue"
},
  "geometry": {"coordinates":[-1.0530389547,53.4981651306],"type":"Point"}
}