{
  "type": "Feature",
  "properties": {
    "addr:full":"302a Broadway Bexleyheath Kent DA6 8AH",
    "addr:housenumber":"302a",
    "addr:postcode":"da6 8ah",
    "addr:street":"Broadway",
    "iso:country":"GB",
    "sg:address":"302a Broadway",
    "sg:city":"Bexleyheath",
    "sg:classifiers":[
        {
            "category":"Building & Trades",
            "subcategory":"Construction",
            "type":"Services"
        }
    ],
    "sg:postcode":"DA6 8AH",
    "sg:province":"Kent",
    "sg:tags":[
        "builder"
    ],
    "wof:name":"Choiceflow Limited",
    "wof:placetype":"venue"
},
  "geometry": {"coordinates":[0.133401,51.458344],"type":"Point"}
}