{
  "type": "Feature",
  "properties": {
    "iso:country":"GB",
    "sg:address":"2/3 Low Farm Place, Moulton Park Industrial Estate",
    "sg:city":"Northampton",
    "sg:classifiers":[
        {
            "category":"Manufacturing",
            "subcategory":"Food",
            "type":"Manufacturing & Wholesale Goods"
        }
    ],
    "sg:phone":"+44 1604 643999",
    "sg:postcode":"NN3 6HY",
    "sg:province":"Northamptonshire",
    "sg:tags":[
        "mech",
        "processing"
    ],
    "wof:name":"V C 999 U K Ltd.",
    "wof:placetype":"venue"
},
  "geometry": {"coordinates":[-0.8774219751,52.2800598145],"type":"Point"}
}