{
  "type": "Feature",
  "properties": {
    "addr:full":"Hayward House, 1 Portesbery Road Camberley Berkshire GU15 3SZ",
    "addr:housenumber":"1",
    "addr:postcode":"gu15 3sz",
    "addr:street":"Portesbery Road",
    "iso:country":"GB",
    "sg:address":"Hayward House, 1 Portesbery Road",
    "sg:city":"Camberley",
    "sg:classifiers":[
        {
            "category":"Professional",
            "subcategory":"Employment Agencies",
            "type":"Services"
        }
    ],
    "sg:postcode":"GU15 3SZ",
    "sg:province":"Berkshire",
    "sg:tags":[
        "consultant"
    ],
    "wof:name":"P S Corporate Services",
    "wof:placetype":"venue"
},
  "geometry": {"coordinates":[-0.7331640124,51.3403511047],"type":"Point"}
}