{
  "type": "Feature",
  "properties": {
    "addr:full":"The Vicarage, 85 High St Brandon Norfolk IP27 9EW",
    "addr:housenumber":"85",
    "addr:postcode":"ip27 9ew",
    "addr:street":"High St",
    "iso:country":"GB",
    "sg:address":"The Vicarage, 85 High St",
    "sg:city":"Brandon",
    "sg:classifiers":[
        {
            "category":"Place Of Worship",
            "type":"Public Place"
        }
    ],
    "sg:phone":"+44 1842 860683",
    "sg:postcode":"IP27 9EW",
    "sg:province":"Norfolk",
    "wof:name":"St Mary The Virgin C of E Church",
    "wof:placetype":"venue"
},
  "geometry": {"coordinates":[0.626205,52.442741],"type":"Point"}
}