{
  "type": "Feature",
  "properties": {
    "addr:full":"54 Avenue Road Bexleyheath Kent DA7 4EQ",
    "addr:housenumber":"54",
    "addr:postcode":"da7 4eq",
    "addr:street":"Avenue Road",
    "iso:country":"GB",
    "sg:address":"54 Avenue Road",
    "sg:city":"Bexleyheath",
    "sg:classifiers":[
        {
            "category":"Restaurant",
            "type":"Food & Drink"
        }
    ],
    "sg:phone":"+44 20 8304 7227",
    "sg:postcode":"DA7 4EQ",
    "sg:province":"Kent",
    "sg:tags":[
        "chinese"
    ],
    "wof:name":"Ming of the Avenue Ltd.",
    "wof:placetype":"venue"
},
  "geometry": {"coordinates":[0.132495,51.462677],"type":"Point"}
}