{
  "type": "Feature",
  "properties": {
    "iso:country":"GB",
    "sg:address":"219 Elm Gro",
    "sg:city":"Brighton",
    "sg:classifiers":[
        {
            "category":"Shopping",
            "subcategory":"News",
            "type":"Retail Goods"
        }
    ],
    "sg:phone":"+44 1273 680740",
    "sg:postcode":"BN2 3EL",
    "sg:province":"East Sussex",
    "sg:tags":[
        "newsagent"
    ],
    "wof:name":"Homewood Stores",
    "wof:placetype":"venue"
},
  "geometry": {"coordinates":[-0.118014,50.831516],"type":"Point"}
}