{
  "type": "Feature",
  "properties": {
    "addr:full":"Community Link Centre, Council Offices, Knowle Grn Staines Berkshire TW18 1XD",
    "addr:postcode":"tw18 1xd",
    "addr:street":"Knowle",
    "iso:country":"GB",
    "sg:address":"Community Link Centre, Council Offices, Knowle Grn",
    "sg:city":"Staines",
    "sg:classifiers":[
        {
            "category":"Professional",
            "subcategory":"Lawyer & Legal Services",
            "type":"Services"
        }
    ],
    "sg:phone":"+44 1784 248832",
    "sg:postcode":"TW18 1XD",
    "sg:province":"Berkshire",
    "sg:tags":[
        "advice",
        "counselling"
    ],
    "wof:name":"Tasha Foundation",
    "wof:placetype":"venue"
},
  "geometry": {"coordinates":[-0.506604,51.435162],"type":"Point"}
}