{
  "type": "Feature",
  "properties": {
    "addr:full":"3 Rydal Aveune York North Yorkshire YO31 0LS",
    "addr:housenumber":"3",
    "addr:postcode":"yo31 0ls",
    "addr:street":"Rydal Aveune",
    "iso:country":"GB",
    "sg:address":"3 Rydal Aveune",
    "sg:city":"York",
    "sg:classifiers":[
        {
            "category":"Utilities",
            "subcategory":"Natural Gas",
            "type":"Services"
        }
    ],
    "sg:phone":"+44 1904 414745",
    "sg:postcode":"YO31 0LS",
    "sg:province":"North Yorkshire",
    "sg:tags":[
        "control",
        "energy",
        "management",
        "system"
    ],
    "wof:name":"Alwyn Glover",
    "wof:placetype":"venue"
},
  "geometry": {"coordinates":[-1.0482189655,53.9650192261],"type":"Point"}
}