{
  "type": "Feature",
  "properties": {
    "iso:country":"GB",
    "sg:address":"1 New Mills Industrial Estate, Modbury",
    "sg:city":"Ivybridge",
    "sg:classifiers":[
        {
            "category":"Building & Trades",
            "subcategory":"Construction",
            "type":"Services"
        }
    ],
    "sg:phone":"+44 1548 830030",
    "sg:postcode":"PL21 0TP",
    "sg:province":"Devon",
    "sg:tags":[
        "fork",
        "lift",
        "truck"
    ],
    "wof:name":"Westcountry Training Services",
    "wof:placetype":"venue"
},
  "geometry": {"coordinates":[-3.887866,50.349178],"type":"Point"}
}