{
  "type": "Feature",
  "properties": {
    "addr:full":"28 Heights Drive Leeds West Yorkshire LS12 3SU",
    "addr:housenumber":"28",
    "addr:postcode":"ls12 3su",
    "addr:street":"Heights Drive",
    "iso:country":"GB",
    "sg:address":"28 Heights Drive",
    "sg:city":"Leeds",
    "sg:classifiers":[
        {
            "category":"Personal",
            "subcategory":"Beauty Salon",
            "type":"Services"
        }
    ],
    "sg:phone":"+44 113 263 9223",
    "sg:postcode":"LS12 3SU",
    "sg:province":"West Yorkshire",
    "sg:tags":[
        "unisex",
        "hairdresser"
    ],
    "wof:name":"Flying Scissors",
    "wof:placetype":"venue"
},
  "geometry": {"coordinates":[-1.6167860031,53.7964172363],"type":"Point"}
}