{
  "type": "Feature",
  "properties": {
    "addr:full":"151 Point Clear Road, St Osyth Clacton-on-sea Essex CO16 8JB",
    "addr:housenumber":"151",
    "addr:postcode":"co16 8jb",
    "addr:street":"Point Clear Road",
    "iso:country":"GB",
    "sg:address":"151 Point Clear Road, St Osyth",
    "sg:city":"Clacton-on-sea",
    "sg:classifiers":[
        {
            "category":"Shopping",
            "subcategory":"Department Store",
            "type":"Retail Goods"
        },
        {
            "category":"Food & Beverages",
            "subcategory":"Groceries & Convenience Stores",
            "type":"Retail Goods"
        }
    ],
    "sg:phone":"+44 1255 820271",
    "sg:postcode":"CO16 8JB",
    "sg:province":"Essex",
    "wof:name":"The Stores",
    "wof:placetype":"venue"
},
  "geometry": {"coordinates":[1.0539200306,51.793762207],"type":"Point"}
}