{
  "type": "Feature",
  "properties": {
    "addr:full":"18 Bluebell Drive Leicester Leicestershire LE2 6TZ",
    "addr:housenumber":"18",
    "addr:postcode":"le2 6tz",
    "addr:street":"Bluebell Drive",
    "iso:country":"GB",
    "sg:address":"18 Bluebell Drive",
    "sg:city":"Leicester",
    "sg:classifiers":[
        {
            "category":"Building & Trades",
            "subcategory":"Landscaping Services",
            "type":"Services"
        }
    ],
    "sg:phone":"+44 116 283 3380",
    "sg:postcode":"LE2 6TZ",
    "sg:province":"Leicestershire",
    "sg:tags":[
        "landscape",
        "contractor"
    ],
    "wof:name":"B Driver",
    "wof:placetype":"venue"
},
  "geometry": {"coordinates":[-1.1347949505,52.593547821],"type":"Point"}
}