{
  "type": "Feature",
  "properties": {
    "iso:country":"GB",
    "sg:address":", Downderry",
    "sg:city":"Torpoint",
    "sg:classifiers":[
        {
            "category":"Health Services",
            "subcategory":"Nursing And Care Facility",
            "type":"Services"
        }
    ],
    "sg:phone":"+44 1503 250240",
    "sg:postcode":"PL11 3LB",
    "sg:province":"Cornwall",
    "sg:tags":[
        "home"
    ],
    "wof:name":"Wide Sea Nursing Home",
    "wof:placetype":"venue"
},
  "geometry": {"coordinates":[-4.308308,50.371128],"type":"Point"}
}