{
  "type": "Feature",
  "properties": {
    "iso:country":"GB",
    "sg:address":"19 Bennetts Gate, Bennetts End",
    "sg:city":"Hemel Hempstead",
    "sg:classifiers":[
        {
            "category":"Professional",
            "subcategory":"Detective & Security Services",
            "type":"Services"
        }
    ],
    "sg:phone":"+44 1442 240140",
    "sg:postcode":"HP3 8EW",
    "sg:province":"Hertfordshire",
    "sg:tags":[
        "alarm",
        "burglar",
        "system"
    ],
    "wof:name":"Aegis Alarm Systems Ltd.",
    "wof:placetype":"venue"
},
  "geometry": {"coordinates":[-0.452061,51.746422],"type":"Point"}
}