{
  "type": "Feature",
  "properties": {
    "addr:full":"47 Fircroft Road Chessington Surrey KT9 1RN",
    "addr:housenumber":"47",
    "addr:postcode":"kt9 1rn",
    "addr:street":"Fircroft Road",
    "iso:country":"GB",
    "sg:address":"47 Fircroft Road",
    "sg:city":"Chessington",
    "sg:classifiers":[
        {
            "category":"Personal",
            "subcategory":"Beauty Salon",
            "type":"Services"
        }
    ],
    "sg:phone":"+44 20 8391 0430",
    "sg:postcode":"KT9 1RN",
    "sg:province":"Surrey",
    "sg:tags":[
        "unisex",
        "hairdresser"
    ],
    "wof:name":"Joannes Mobile Hairdressing",
    "wof:placetype":"venue"
},
  "geometry": {"coordinates":[-0.297183007,51.3697738647],"type":"Point"}
}