{
  "type": "Feature",
  "properties": {
    "iso:country":"GB",
    "sg:address":"Community Centre, Pendennis Rd",
    "sg:city":"Torquay",
    "sg:classifiers":[
        {
            "category":"Community Center",
            "type":"Public Place"
        }
    ],
    "sg:phone":"+44 1803 315155",
    "sg:postcode":"TQ2 7QR",
    "sg:province":"Devon",
    "sg:tags":[
        "centre"
    ],
    "wof:name":"Hill Village Community Association",
    "wof:placetype":"venue"
},
  "geometry": {"coordinates":[-3.543464,50.467194],"type":"Point"}
}