{
  "type": "Feature",
  "properties": {
    "iso:country":"GB",
    "sg:address":"46 Percival Road",
    "sg:city":"Rugby",
    "sg:classifiers":[
        {
            "category":"Real Estate",
            "subcategory":"Architect",
            "type":"Services"
        }
    ],
    "sg:postcode":"CV22 5JT",
    "sg:province":"Warwickshire",
    "sg:tags":[
        "technician",
        "technologist",
        "architectural"
    ],
    "wof:name":"BERNARD L F COLLINS",
    "wof:placetype":"venue"
},
  "geometry": {"coordinates":[-1.243815,52.360847],"type":"Point"}
}