{
  "type": "Feature",
  "properties": {
    "iso:country":"GB",
    "sg:address":"81 Goodison Cres",
    "sg:city":"Sheffield",
    "sg:classifiers":[
        {
            "category":"Building & Trades",
            "subcategory":"Construction",
            "type":"Services"
        }
    ],
    "sg:postcode":"S6 5HU",
    "sg:province":"South Yorkshire",
    "sg:tags":[
        "decorator",
        "painter"
    ],
    "wof:name":"Chadwick,E R,",
    "wof:placetype":"venue"
},
  "geometry": {"coordinates":[-1.5228689909,53.3959922791],"type":"Point"}
}