{
  "type": "Feature",
  "properties": {
    "iso:country":"GB",
    "sg:address":"Arch 197 Morning Lane, Hackney",
    "sg:city":"London",
    "sg:classifiers":[
        {
            "category":"Retail",
            "subcategory":"Auto Repair",
            "type":"Services"
        }
    ],
    "sg:phone":"+44 20 8985 5174",
    "sg:postcode":"E9 6LG",
    "sg:province":"Greater London",
    "sg:tags":[
        "engine",
        "specialist",
        "diagnostic",
        "tuning",
        "car"
    ],
    "wof:name":"Car Valet Mechanical",
    "wof:placetype":"venue"
},
  "geometry": {"coordinates":[-0.04971,51.547199],"type":"Point"}
}