{
  "type": "Feature",
  "properties": {
    "addr:full":"Woodlands, Meadowlands Addlestone Surrey KT15 2RQ",
    "addr:postcode":"kt15 2rq",
    "addr:street":"Addlestone",
    "iso:country":"GB",
    "sg:address":"Woodlands, Meadowlands",
    "sg:city":"Addlestone",
    "sg:classifiers":[
        {
            "category":"Manufacturing",
            "subcategory":"Buildings",
            "type":"Manufacturing & Wholesale Goods"
        }
    ],
    "sg:phone":"+44 1932 844165",
    "sg:postcode":"KT15 2RQ",
    "sg:province":"Surrey",
    "sg:tags":[
        "mobile",
        "home"
    ],
    "sg:website":"http://www.haulfryn.co.uk",
    "wof:name":"Haulfryn Park Homes Ltd",
    "wof:placetype":"venue"
},
  "geometry": {"coordinates":[-0.493514,51.371666],"type":"Point"}
}