{
  "type": "Feature",
  "properties": {
    "addr:full":"13 Follet Drive Abbots Langley Hertfordshire WD5 0LP",
    "addr:housenumber":"13",
    "addr:postcode":"wd5 0lp",
    "addr:street":"Follet Drive",
    "iso:country":"GB",
    "sg:address":"13 Follet Drive",
    "sg:city":"Abbots Langley",
    "sg:classifiers":[
        {
            "category":"Building & Trades",
            "subcategory":"Landscaping Services",
            "type":"Services"
        },
        {
            "category":"Building & Trades",
            "subcategory":"Construction",
            "type":"Services"
        }
    ],
    "sg:phone":"+44 1923 443761",
    "sg:postcode":"WD5 0LP",
    "sg:province":"Hertfordshire",
    "sg:tags":[
        "consultant",
        "contractor"
    ],
    "wof:name":"Follett Construction Ltd.",
    "wof:placetype":"venue"
},
  "geometry": {"coordinates":[-0.412514,51.702736],"type":"Point"}
}