{
  "type": "Feature",
  "properties": {
    "addr:full":"Ruabon Road Wrexham Wrexham LL13 7PL",
    "addr:postcode":"ll13 7pl",
    "addr:street":"Ruabon Road",
    "iso:country":"GB",
    "sg:address":"Ruabon Road",
    "sg:city":"Wrexham",
    "sg:classifiers":[
        {
            "category":"Bars & Pubs",
            "type":"Food & Drink"
        }
    ],
    "sg:phone":"+44 1978 261450",
    "sg:postcode":"LL13 7PL",
    "sg:province":"Wrexham",
    "sg:tags":[
        "pubs",
        "inn"
    ],
    "wof:name":"Oak Tree Tavern",
    "wof:placetype":"venue"
},
  "geometry": {"coordinates":[-2.9976890087,53.0415000916],"type":"Point"}
}