{
  "type": "Feature",
  "properties": {
    "iso:country":"GB",
    "sg:address":"Wolverhampton Road, Penkridge",
    "sg:city":"Stafford",
    "sg:classifiers":[
        {
            "category":"Food & Beverages",
            "subcategory":"Supermarket",
            "type":"Retail Goods"
        }
    ],
    "sg:phone":"+44 1785 715092",
    "sg:postcode":"ST19 5NS",
    "sg:province":"Shropshire",
    "wof:name":"Kwik Save Stores Ltd.",
    "wof:placetype":"venue"
},
  "geometry": {"coordinates":[-2.11634,52.722607],"type":"Point"}
}