{
  "type": "Feature",
  "properties": {
    "addr:full":"Tower Hill Birmingham West Midlands B42 1LG",
    "addr:postcode":"b42 1lg",
    "addr:street":"Tower Hill",
    "iso:country":"GB",
    "sg:address":"Tower Hill",
    "sg:city":"Birmingham",
    "sg:classifiers":[
        {
            "category":"Education",
            "subcategory":"Library",
            "type":"Public Place"
        }
    ],
    "sg:phone":"+44 121 464 1948",
    "sg:postcode":"B42 1LG",
    "sg:province":"West Midlands",
    "sg:tags":[
        "book"
    ],
    "wof:name":"Tower Hill Library",
    "wof:placetype":"venue"
},
  "geometry": {"coordinates":[-1.919729948,52.533821106],"type":"Point"}
}