{
  "type": "Feature",
  "properties": {
    "addr:full":"48 Pall Mall London Greater London SW1Y 5JY",
    "addr:housenumber":"48",
    "addr:postcode":"sw1y 5jy",
    "addr:street":"Pall Mall",
    "iso:country":"GB",
    "sg:address":"48 Pall Mall",
    "sg:city":"London",
    "sg:classifiers":[
        {
            "category":"Organizations",
            "subcategory":"Non-profit Organization",
            "type":"Services"
        }
    ],
    "sg:phone":"+44 20 7930 0125",
    "sg:postcode":"SW1Y 5JY",
    "sg:province":"Greater London",
    "sg:tags":[
        "organisation",
        "voluntary",
        "charity"
    ],
    "wof:name":"The Officers Association",
    "wof:placetype":"venue"
},
  "geometry": {"coordinates":[-0.136442,51.50592],"type":"Point"}
}