{
  "type": "Feature",
  "properties": {
    "iso:country":"GB",
    "sg:address":"67 Mill Lane",
    "sg:city":"Wolverhampton",
    "sg:classifiers":[
        {
            "category":"Professional",
            "type":"Services"
        }
    ],
    "sg:postcode":"WV11 1DQ",
    "sg:province":"Staffordshire",
    "sg:tags":[
        "caterer"
    ],
    "wof:name":"Lunchbox Catering Services",
    "wof:placetype":"venue"
},
  "geometry": {"coordinates":[-2.096161,52.6106],"type":"Point"}
}