{
  "type": "Feature",
  "properties": {
    "iso:country":"GB",
    "sg:address":"55 Selwood Road",
    "sg:city":"Chessington",
    "sg:classifiers":[
        {
            "category":"Professional",
            "subcategory":"Engineering",
            "type":"Services"
        }
    ],
    "sg:postcode":"KT9 1PT",
    "sg:province":"Surrey",
    "sg:tags":[
        "consulting",
        "engineer"
    ],
    "wof:name":"Visuals",
    "wof:placetype":"venue"
},
  "geometry": {"coordinates":[-0.3113650084,51.368473053],"type":"Point"}
}