{
  "type": "Feature",
  "properties": {
    "iso:country":"GB",
    "sg:address":"12 St Johns Rd",
    "sg:city":"London",
    "sg:classifiers":[
        {
            "category":"Shopping",
            "subcategory":"Shoes",
            "type":"Retail Goods"
        }
    ],
    "sg:postcode":"SW11 1PN",
    "sg:province":"Greater London",
    "sg:tags":[
        "shop"
    ],
    "wof:name":"Stead & Simpson Ltd",
    "wof:placetype":"venue"
},
  "geometry": {"coordinates":[-0.167966,51.463268],"type":"Point"}
}