{
  "type": "Feature",
  "properties": {
    "addr:full":"13 High Street, Dorchester On Thames Wallingford Oxfordshire OX10 7HH",
    "addr:housenumber":"13",
    "addr:postcode":"ox10 7hh",
    "addr:street":"High Street",
    "iso:country":"GB",
    "sg:address":"13 High Street, Dorchester On Thames",
    "sg:city":"Wallingford",
    "sg:classifiers":[
        {
            "category":"Professional",
            "subcategory":"Engineering",
            "type":"Services"
        }
    ],
    "sg:postcode":"OX10 7HH",
    "sg:province":"Oxfordshire",
    "sg:tags":[
        "contractor",
        "electrical",
        "engineer"
    ],
    "wof:name":"N W Clarke",
    "wof:placetype":"venue"
},
  "geometry": {"coordinates":[-1.166034,51.644142],"type":"Point"}
}