{
  "type": "Feature",
  "properties": {
    "addr:full":"50 Windsor Road Woking Surrey GU24 8LD",
    "addr:housenumber":"50",
    "addr:postcode":"gu24 8ld",
    "addr:street":"Windsor Road",
    "iso:country":"GB",
    "sg:address":"50 Windsor Road",
    "sg:city":"Woking",
    "sg:classifiers":[
        {
            "category":"Organizations",
            "subcategory":"Membership Organization",
            "type":"Services"
        }
    ],
    "sg:phone":"+44 1276 857116",
    "sg:postcode":"GU24 8LD",
    "sg:province":"Surrey",
    "sg:tags":[
        "club"
    ],
    "wof:name":"Chobham Club Ltd.",
    "wof:placetype":"venue"
},
  "geometry": {"coordinates":[-0.605347,51.352581],"type":"Point"}
}