{
  "type": "Feature",
  "properties": {
    "addr:full":"15 Tyler Court, Jaffray Road Birmingham West Midlands B24 8AY",
    "addr:housenumber":"15",
    "addr:postcode":"b24 8ay",
    "addr:street":"Tyler Court Jaffray Road",
    "iso:country":"GB",
    "sg:address":"15 Tyler Court, Jaffray Road",
    "sg:city":"Birmingham",
    "sg:classifiers":[
        {
            "category":"Professional",
            "subcategory":"Credit Reporting & Collection",
            "type":"Services"
        }
    ],
    "sg:phone":"+44 121 386 1116",
    "sg:postcode":"B24 8AY",
    "sg:province":"West Midlands",
    "sg:tags":[
        "collecting",
        "agency"
    ],
    "wof:name":"Barrington Rowe Collections",
    "wof:placetype":"venue"
},
  "geometry": {"coordinates":[-1.84573,52.518028],"type":"Point"}
}