{
  "type": "Feature",
  "properties": {
    "iso:country":"GB",
    "sg:address":"13 Lichfield Close",
    "sg:city":"Chelmsford",
    "sg:classifiers":[
        {
            "category":"Real Estate",
            "subcategory":"Surveying",
            "type":"Services"
        }
    ],
    "sg:postcode":"CM1 2XW",
    "sg:province":"Essex",
    "sg:tags":[
        "surveyor",
        "quantity"
    ],
    "wof:name":"Timothy Woods Project Services Ltd.",
    "wof:placetype":"venue"
},
  "geometry": {"coordinates":[0.453513,51.74226],"type":"Point"}
}