{
  "type": "Feature",
  "properties": {
    "addr:full":"54 Town Park Torrington Devon EX38 7AH",
    "addr:housenumber":"54",
    "addr:postcode":"ex38 7ah",
    "addr:street":"Town Park",
    "iso:country":"GB",
    "sg:address":"54 Town Park",
    "sg:city":"Torrington",
    "sg:classifiers":[
        {
            "category":"Building & Trades",
            "subcategory":"Construction",
            "type":"Services"
        }
    ],
    "sg:phone":"+44 1805 623509",
    "sg:postcode":"EX38 7AH",
    "sg:province":"Devon",
    "sg:tags":[
        "decorator",
        "painter"
    ],
    "wof:name":"M O Cockwill Decorators",
    "wof:placetype":"venue"
},
  "geometry": {"coordinates":[-4.1494588852,50.9537582397],"type":"Point"}
}