{
  "type": "Feature",
  "properties": {
    "addr:full":"156 Oxford St West End Hampshire W1N 9DL",
    "addr:housenumber":"156",
    "addr:postcode":"w1n 9dl",
    "addr:street":"Oxford St",
    "iso:country":"GB",
    "sg:address":"156 Oxford St",
    "sg:city":"West End",
    "sg:classifiers":[
        {
            "category":"Shopping",
            "subcategory":"Clothing, Apparel, & Fashions",
            "type":"Retail Goods"
        }
    ],
    "sg:phone":"+44 20 7637 1232",
    "sg:postcode":"W1N 9DL",
    "sg:province":"Hampshire",
    "sg:tags":[
        "menswear"
    ],
    "wof:name":"Oakland",
    "wof:placetype":"venue"
},
  "geometry": {"coordinates":[-0.1380379945,51.5158500671],"type":"Point"}
}