{
  "type": "Feature",
  "properties": {
    "iso:country":"GB",
    "sg:address":"355 Newmarket Rd",
    "sg:city":"Cambridge",
    "sg:classifiers":[
        {
            "category":"Retail",
            "subcategory":"Driving School",
            "type":"Services"
        }
    ],
    "sg:phone":"+44 1223 576713",
    "sg:postcode":"CB5 8JG",
    "sg:province":"Cambridgeshire",
    "wof:name":"L S D School Of Driving",
    "wof:placetype":"venue"
},
  "geometry": {"coordinates":[0.146869,52.211323],"type":"Point"}
}