{
  "type": "Feature",
  "properties": {
    "addr:full":"22 Goldcroft Common, Caerleon Newport Monmouthshire NP18 1NG",
    "addr:housenumber":"22",
    "addr:postcode":"np18 1ng",
    "addr:street":"Goldcroft Common",
    "iso:country":"GB",
    "sg:address":"22 Goldcroft Common, Caerleon",
    "sg:city":"Newport",
    "sg:classifiers":[
        {
            "category":"Health Services",
            "subcategory":"Health Practitioner",
            "type":"Services"
        }
    ],
    "sg:phone":"+44 1633 211586",
    "sg:postcode":"NP18 1NG",
    "sg:province":"Monmouthshire",
    "sg:tags":[
        "hypnotherapists"
    ],
    "wof:name":"John Plowman",
    "wof:placetype":"venue"
},
  "geometry": {"coordinates":[-2.95733,51.612446],"type":"Point"}
}