{
  "type": "Feature",
  "properties": {
    "addr:full":"261 Lower Addiscombe Road Croydon Surrey CR9 6DB",
    "addr:housenumber":"261",
    "addr:postcode":"cr9 6db",
    "addr:street":"Lower Addiscombe Road",
    "iso:country":"GB",
    "sg:address":"261 Lower Addiscombe Road",
    "sg:city":"Croydon",
    "sg:classifiers":[
        {
            "category":"Shopping",
            "subcategory":"Department Store",
            "type":"Retail Goods"
        }
    ],
    "sg:phone":"+44 20 8654 3344",
    "sg:postcode":"CR9 6DB",
    "sg:province":"Surrey",
    "sg:tags":[
        "departmental"
    ],
    "wof:name":"Woolworths plc",
    "wof:placetype":"venue"
},
  "geometry": {"coordinates":[-0.0717800036,51.3807868958],"type":"Point"}
}