{
  "type": "Feature",
  "properties": {
    "iso:country":"GB",
    "sg:address":"222 Kensal Road",
    "sg:city":"London",
    "sg:classifiers":[
        {
            "category":"Professional",
            "subcategory":"Art Services",
            "type":"Services"
        }
    ],
    "sg:phone":"+44 20 8964 9989",
    "sg:postcode":"W10 5BN",
    "sg:province":"Greater London",
    "sg:tags":[
        "graphic",
        "designer"
    ],
    "wof:name":"RED CLOUD",
    "wof:placetype":"venue"
},
  "geometry": {"coordinates":[-0.206159994,51.5249824524],"type":"Point"}
}