{
  "type": "Feature",
  "properties": {
    "iso:country":"GB",
    "sg:address":"Aylsham Road",
    "sg:city":"Norwich",
    "sg:classifiers":[
        {
            "category":"Retail",
            "subcategory":"Auto Repair",
            "type":"Services"
        }
    ],
    "sg:phone":"+44 1603 279215",
    "sg:postcode":"NR10 5EZ",
    "sg:province":"Norfolk",
    "sg:tags":[
        "modification",
        "garage"
    ],
    "wof:name":"Bure Vally Garage & Coaches",
    "wof:placetype":"venue"
},
  "geometry": {"coordinates":[1.30713,52.755505],"type":"Point"}
}