{
  "type": "Feature",
  "properties": {
    "addr:full":"7 Kings Stone Avenue Steyning West Sussex BN44 3FJ",
    "addr:housenumber":"7",
    "addr:postcode":"bn44 3fj",
    "addr:street":"Kings Stone Avenue",
    "iso:country":"GB",
    "sg:address":"7 Kings Stone Avenue",
    "sg:city":"Steyning",
    "sg:classifiers":[
        {
            "category":"Building & Trades",
            "subcategory":"Construction",
            "type":"Services"
        }
    ],
    "sg:phone":"+44 1903 813778",
    "sg:postcode":"BN44 3FJ",
    "sg:province":"West Sussex",
    "sg:tags":[
        "glazier",
        "decorator",
        "painter"
    ],
    "wof:name":"Graham G Stephenson",
    "wof:placetype":"venue"
},
  "geometry": {"coordinates":[-0.314055,50.889736],"type":"Point"}
}