{
  "type": "Feature",
  "properties": {
    "iso:country":"GB",
    "sg:address":"84 Sleaford Road",
    "sg:city":"Boston",
    "sg:classifiers":[
        {
            "category":"Professional",
            "subcategory":"Detective & Security Services",
            "type":"Services"
        }
    ],
    "sg:phone":"+44 1205 369934",
    "sg:postcode":"PE21 8EU",
    "sg:province":"Lincolnshire",
    "sg:tags":[
        "alarm",
        "burglar",
        "system"
    ],
    "wof:name":"Telesat Communications",
    "wof:placetype":"venue"
},
  "geometry": {"coordinates":[-0.038517,52.977463],"type":"Point"}
}