{
  "type": "Feature",
  "properties": {
    "addr:full":"215 West Drive Thornton-cleveleys Lancashire FY5 2EH",
    "addr:housenumber":"215",
    "addr:postcode":"fy5 2eh",
    "addr:street":"West Drive",
    "iso:country":"GB",
    "sg:address":"215 West Drive",
    "sg:city":"Thornton-cleveleys",
    "sg:classifiers":[
        {
            "category":"Place Of Worship",
            "type":"Public Place"
        },
        {
            "category":"Arena",
            "subcategory":"Sports Club",
            "type":"Entertainment"
        }
    ],
    "sg:postcode":"FY5 2EH",
    "sg:province":"Lancashire",
    "wof:name":"Cleveleys Properties Ltd.",
    "wof:placetype":"venue"
},
  "geometry": {"coordinates":[-3.018928051,53.8831596375],"type":"Point"}
}