{
  "type": "Feature",
  "properties": {
    "addr:full":"40 Monks Walk Reigate Surrey RH2 0SS",
    "addr:housenumber":"40",
    "addr:postcode":"rh2 0ss",
    "addr:street":"Monks Walk",
    "iso:country":"GB",
    "sg:address":"40 Monks Walk",
    "sg:city":"Reigate",
    "sg:classifiers":[
        {
            "category":"Building & Trades",
            "subcategory":"Construction",
            "type":"Services"
        }
    ],
    "sg:phone":"+44 1737 246374",
    "sg:postcode":"RH2 0SS",
    "sg:province":"Surrey",
    "sg:tags":[
        "supplier",
        "installers",
        "cladding"
    ],
    "wof:name":"European Profile",
    "wof:placetype":"venue"
},
  "geometry": {"coordinates":[-0.199181,51.237507],"type":"Point"}
}