{
  "type": "Feature",
  "properties": {
    "addr:full":"16 Station Road, Bardowie Glasgow East Dunbartonshire G62 6ET",
    "addr:housenumber":"16",
    "addr:postcode":"g62 6et",
    "addr:street":"Station Road",
    "iso:country":"GB",
    "sg:address":"16 Station Road, Bardowie",
    "sg:city":"Glasgow",
    "sg:classifiers":[
        {
            "category":"Personal",
            "subcategory":"Beauty Salon",
            "type":"Services"
        }
    ],
    "sg:phone":"+44 141 956 5899",
    "sg:postcode":"G62 6ET",
    "sg:province":"East Dunbartonshire",
    "sg:tags":[
        "unisex",
        "hairdresser"
    ],
    "wof:name":"The Fringe Hair Salon",
    "wof:placetype":"venue"
},
  "geometry": {"coordinates":[-4.2661180496,55.9323310852],"type":"Point"}
}