{
  "type": "Feature",
  "properties": {
    "iso:country":"GB",
    "sg:address":"124 Baker Street",
    "sg:city":"London",
    "sg:classifiers":[
        {
            "category":"Education",
            "subcategory":"Special Training",
            "type":"Public Place"
        }
    ],
    "sg:phone":"+44 20 7935 4676",
    "sg:postcode":"W1U 6TY",
    "sg:province":"Greater London",
    "sg:tags":[
        "school",
        "language"
    ],
    "wof:name":"Rose of York Ltd.",
    "wof:placetype":"venue"
},
  "geometry": {"coordinates":[-0.1570640057,51.5214271545],"type":"Point"}
}