{
  "type": "Feature",
  "properties": {
    "iso:country":"GB",
    "sg:address":"12-14 Thornfield Avenue, Connah's Quay",
    "sg:city":"Deeside",
    "sg:classifiers":[
        {
            "category":"Food & Beverages",
            "subcategory":"Meat & Fish",
            "type":"Retail Goods"
        }
    ],
    "sg:phone":"+44 1244 816222",
    "sg:postcode":"CH5 4HX",
    "sg:province":"Flintshire",
    "sg:tags":[
        "butcher"
    ],
    "wof:name":"Chillfresh Catering Butchers Ltd.",
    "wof:placetype":"venue"
},
  "geometry": {"coordinates":[-3.055797,53.210888],"type":"Point"}
}