{
  "type": "Feature",
  "properties": {
    "addr:full":"82 Bridge Road East Molesey Greater London KT8 9HF",
    "addr:housenumber":"82",
    "addr:postcode":"kt8 9hf",
    "addr:street":"Bridge Road",
    "iso:country":"GB",
    "sg:address":"82 Bridge Road",
    "sg:city":"East Molesey",
    "sg:classifiers":[
        {
            "category":"Real Estate",
            "subcategory":"Architect",
            "type":"Services"
        }
    ],
    "sg:phone":"+44 20 8941 0606",
    "sg:postcode":"KT8 9HF",
    "sg:province":"Greater London",
    "wof:name":"P R P Management Ltd.",
    "wof:placetype":"venue"
},
  "geometry": {"coordinates":[-0.347296,51.400967],"type":"Point"}
}