{
  "type": "Feature",
  "properties": {
    "addr:full":"11 Sprucedale Gardens Croydon Surrey CR0 5HU",
    "addr:housenumber":"11",
    "addr:postcode":"cr0 5hu",
    "addr:street":"Sprucedale Gardens",
    "iso:country":"GB",
    "sg:address":"11 Sprucedale Gardens",
    "sg:city":"Croydon",
    "sg:classifiers":[
        {
            "category":"Professional",
            "subcategory":"Management & Consulting",
            "type":"Services"
        }
    ],
    "sg:phone":"+44 20 8656 6843",
    "sg:postcode":"CR0 5HU",
    "sg:province":"Surrey",
    "sg:tags":[
        "consultant",
        "business"
    ],
    "wof:name":"G.J.M Franklin",
    "wof:placetype":"venue"
},
  "geometry": {"coordinates":[-0.0507230014,51.3659057617],"type":"Point"}
}