{
  "type": "Feature",
  "properties": {
    "addr:full":"Store No 1, Vulcan Road North Norwich Norfolk NR6 6AQ",
    "addr:postcode":"nr6 6aq",
    "addr:street":"Vulcan Road North Norwich Norfolk",
    "iso:country":"GB",
    "sg:address":"Store No 1, Vulcan Road North",
    "sg:city":"Norwich",
    "sg:classifiers":[
        {
            "category":"Recreation",
            "subcategory":"Go Karts",
            "type":"Entertainment"
        }
    ],
    "sg:phone":"+44 1603 486655",
    "sg:postcode":"NR6 6AQ",
    "sg:province":"Norfolk",
    "sg:tags":[
        "karting"
    ],
    "wof:name":"Norwich Indoor Kart Centre Ltd.",
    "wof:placetype":"venue"
},
  "geometry": {"coordinates":[1.2737849951,52.6691360474],"type":"Point"}
}