{
  "type": "Feature",
  "properties": {
    "addr:full":"Wilmington House, High Street East Grinstead East Sussex RH19 3AU",
    "addr:postcode":"rh19 3au",
    "addr:street":"High Street",
    "iso:country":"GB",
    "sg:address":"Wilmington House, High Street",
    "sg:city":"East Grinstead",
    "sg:classifiers":[
        {
            "category":"Organizations",
            "subcategory":"Membership Organization",
            "type":"Services"
        }
    ],
    "sg:postcode":"RH19 3AU",
    "sg:province":"East Sussex",
    "sg:tags":[
        "club"
    ],
    "wof:name":"Verdi Project Management Ltd.",
    "wof:placetype":"venue"
},
  "geometry": {"coordinates":[-0.004248,51.123974],"type":"Point"}
}