{
  "type": "Feature",
  "properties": {
    "addr:full":"Farley Farm, Muddles Grn Lewes East Sussex BN8 6HW",
    "addr:postcode":"bn8 6hw",
    "addr:street":"Muddles Grn",
    "iso:country":"GB",
    "sg:address":"Farley Farm, Muddles Grn",
    "sg:city":"Lewes",
    "sg:classifiers":[
        {
            "category":"Shopping",
            "subcategory":"Gifts & Souvenirs",
            "type":"Retail Goods"
        }
    ],
    "sg:phone":"+44 1825 872856",
    "sg:postcode":"BN8 6HW",
    "sg:province":"East Sussex",
    "sg:tags":[
        "giftware"
    ],
    "wof:name":"Wooden Wonders Ltd.",
    "wof:placetype":"venue"
},
  "geometry": {"coordinates":[0.1968799978,50.8996391296],"type":"Point"}
}