{
  "type": "Feature",
  "properties": {
    "iso:country":"GB",
    "sg:address":"30-34 Wood Street",
    "sg:city":"Lytham St Annes",
    "sg:classifiers":[
        {
            "category":"Wholesale",
            "subcategory":"Toys & Hobbies",
            "type":"Manufacturing & Wholesale Goods"
        }
    ],
    "sg:postcode":"FY8 1QR",
    "sg:province":"Lancashire",
    "sg:tags":[
        "balloon",
        "novelty"
    ],
    "wof:name":"Celebrations",
    "wof:placetype":"venue"
},
  "geometry": {"coordinates":[-3.029709,53.751041],"type":"Point"}
}