{
  "type": "Feature",
  "properties": {
    "addr:full":"169 Bury New Road, Whitefield Manchester Lancashire M45 6AB",
    "addr:housenumber":"169",
    "addr:postcode":"m45 6ab",
    "addr:street":"Bury New Road",
    "iso:country":"GB",
    "sg:address":"169 Bury New Road, Whitefield",
    "sg:city":"Manchester",
    "sg:classifiers":[
        {
            "category":"Professional",
            "subcategory":"Secretarial Services",
            "type":"Services"
        }
    ],
    "sg:postcode":"M45 6AB",
    "sg:province":"Lancashire",
    "wof:name":"Mayfield Secretarial Services",
    "wof:placetype":"venue"
},
  "geometry": {"coordinates":[-2.292815,53.546738],"type":"Point"}
}