{
  "type": "Feature",
  "properties": {
    "addr:full":"86 High Street Montrose Aberdeenshire DD10 8JE",
    "addr:housenumber":"86",
    "addr:postcode":"dd10 8je",
    "addr:street":"High Street",
    "iso:country":"GB",
    "sg:address":"86 High Street",
    "sg:city":"Montrose",
    "sg:classifiers":[
        {
            "category":"Banks & Credit Unions",
            "subcategory":"Financial Services",
            "type":"Services"
        }
    ],
    "sg:phone":"+44 1674 673363",
    "sg:postcode":"DD10 8JE",
    "sg:province":"Aberdeenshire",
    "sg:tags":[
        "building",
        "society"
    ],
    "wof:name":"Dunfermline Building Society",
    "wof:placetype":"venue"
},
  "geometry": {"coordinates":[-2.4684829712,56.7120285034],"type":"Point"}
}