{
  "type": "Feature",
  "properties": {
    "addr:full":"Berry Green Farm, Stretham Ely Cambridgeshire CB6 3JS",
    "addr:postcode":"cb6 3js",
    "addr:street":"Berry Green",
    "iso:country":"GB",
    "sg:address":"Berry Green Farm, Stretham",
    "sg:city":"Ely",
    "sg:classifiers":[
        {
            "category":"Farming",
            "subcategory":"Livestock Farm",
            "type":"Manufacturing & Wholesale Goods"
        }
    ],
    "sg:phone":"+44 1353 649216",
    "sg:postcode":"CB6 3JS",
    "sg:province":"Cambridgeshire",
    "sg:tags":[
        "others"
    ],
    "wof:name":"W R Gill",
    "wof:placetype":"venue"
},
  "geometry": {"coordinates":[0.216629,52.347069],"type":"Point"}
}