{
  "type": "Feature",
  "properties": {
    "iso:country":"GB",
    "sg:address":"Anerley Hill",
    "sg:city":"London",
    "sg:classifiers":[
        {
            "category":"Museum",
            "subcategory":"Art Museum",
            "type":"Entertainment"
        }
    ],
    "sg:phone":"+44 20 8676 0700",
    "sg:postcode":"SE19 2BA",
    "sg:province":"Greater London",
    "sg:tags":[
        "gallery"
    ],
    "wof:name":"The Crystal Palace Museum",
    "wof:placetype":"venue"
},
  "geometry": {"coordinates":[-0.074793,51.418522],"type":"Point"}
}