{
  "type": "Feature",
  "properties": {
    "iso:country":"GB",
    "sg:address":"4a Castle St",
    "sg:city":"Stamford",
    "sg:classifiers":[
        {
            "category":"Organizations",
            "subcategory":"Non-profit Organization",
            "type":"Services"
        }
    ],
    "sg:phone":"+44 1780 766689",
    "sg:postcode":"PE9 2RA",
    "sg:province":"Cambridgeshire",
    "sg:tags":[
        "alarm",
        "system"
    ],
    "wof:name":"Protec Security Systems",
    "wof:placetype":"venue"
},
  "geometry": {"coordinates":[-0.480588,52.651218],"type":"Point"}
}