{
  "type": "Feature",
  "properties": {
    "addr:full":"George St Heckmondwike West Yorkshire WF16 9QP",
    "addr:postcode":"wf16 9qp",
    "addr:street":"George St",
    "iso:country":"GB",
    "sg:address":"George St",
    "sg:city":"Heckmondwike",
    "sg:classifiers":[
        {
            "category":"Manufacturing",
            "subcategory":"Textiles",
            "type":"Manufacturing & Wholesale Goods"
        }
    ],
    "sg:phone":"+44 1924 409683",
    "sg:postcode":"WF16 9QP",
    "sg:province":"West Yorkshire",
    "sg:tags":[
        "mnfr",
        "rug",
        "carpet"
    ],
    "wof:name":"Byrne Prospect Rugs Ltd",
    "wof:placetype":"venue"
},
  "geometry": {"coordinates":[-1.675374,53.708237],"type":"Point"}
}