{
  "type": "Feature",
  "properties": {
    "iso:country":"GB",
    "sg:address":"238 High Street, Cottenham",
    "sg:city":"Cambridge",
    "sg:classifiers":[
        {
            "category":"Professional",
            "subcategory":"Lawyer & Legal Services",
            "type":"Services"
        }
    ],
    "sg:phone":"+44 1954 251818",
    "sg:postcode":"CB4 8RZ",
    "sg:province":"Cambridgeshire",
    "sg:tags":[
        "solicitor"
    ],
    "wof:name":"King & Co Solicitors",
    "wof:placetype":"venue"
},
  "geometry": {"coordinates":[0.1256339997,52.2868766785],"type":"Point"}
}