{
  "type": "Feature",
  "properties": {
    "addr:full":"17 Orwell Road Clacton-on-sea Essex CO15 1PP",
    "addr:housenumber":"17",
    "addr:postcode":"co15 1pp",
    "addr:street":"Orwell Road",
    "iso:country":"GB",
    "sg:address":"17 Orwell Road",
    "sg:city":"Clacton-on-sea",
    "sg:classifiers":[
        {
            "category":"Wholesale",
            "subcategory":"Books, Periodicals, & Newspapers",
            "type":"Manufacturing & Wholesale Goods"
        }
    ],
    "sg:postcode":"CO15 1PP",
    "sg:province":"Essex",
    "sg:tags":[
        "publishing"
    ],
    "wof:name":"Mason Publications",
    "wof:placetype":"venue"
},
  "geometry": {"coordinates":[1.1551150084,51.7888870239],"type":"Point"}
}