{
  "type": "Feature",
  "properties": {
    "addr:full":"97-101 North Road Richmond Greater London TW9 4HJ",
    "addr:housenumber":"97-101",
    "addr:postcode":"tw9 4hj",
    "addr:street":"North Road",
    "iso:country":"GB",
    "sg:address":"97-101 North Road",
    "sg:city":"Richmond",
    "sg:classifiers":[
        {
            "category":"Autos & Motor Vehicles",
            "subcategory":"Automobile Sales",
            "type":"Retail Goods"
        }
    ],
    "sg:phone":"+44 20 8255 6900",
    "sg:postcode":"TW9 4HJ",
    "sg:province":"Greater London",
    "sg:tags":[
        "car"
    ],
    "wof:name":"Alexander Wright & Young",
    "wof:placetype":"venue"
},
  "geometry": {"coordinates":[-0.2851389945,51.4759902954],"type":"Point"}
}