{
  "type": "Feature",
  "properties": {
    "addr:full":"3a Tindal Square Chelmsford Essex CM1 1EW",
    "addr:housenumber":"3a",
    "addr:postcode":"cm1 1ew",
    "addr:street":"Tindal Square",
    "iso:country":"GB",
    "sg:address":"3a Tindal Square",
    "sg:city":"Chelmsford",
    "sg:classifiers":[
        {
            "category":"Real Estate",
            "subcategory":"Surveying",
            "type":"Services"
        }
    ],
    "sg:phone":"+44 1245 496564",
    "sg:postcode":"CM1 1EW",
    "sg:province":"Essex",
    "sg:tags":[
        "surveyor",
        "valuer"
    ],
    "wof:name":"Balch & Balch",
    "wof:placetype":"venue"
},
  "geometry": {"coordinates":[0.4728589952,51.7345581055],"type":"Point"}
}