{
  "type": "Feature",
  "properties": {
    "iso:country":"GB",
    "sg:address":"77 Aigburth Hall Avenue",
    "sg:city":"Liverpool",
    "sg:classifiers":[
        {
            "category":"Building & Trades",
            "subcategory":"Construction",
            "type":"Services"
        }
    ],
    "sg:postcode":"L19 3PR",
    "sg:province":"Merseyside",
    "sg:tags":[
        "builder"
    ],
    "wof:name":"Aigburth Hall Contractors",
    "wof:placetype":"venue"
},
  "geometry": {"coordinates":[-2.913199,53.36795],"type":"Point"}
}