{
  "type": "Feature",
  "properties": {
    "iso:country":"GB",
    "sg:address":"13 Eskdale Court",
    "sg:city":"Dalkeith",
    "sg:classifiers":[
        {
            "category":"Farming",
            "subcategory":"Fish & Marine Products",
            "type":"Manufacturing & Wholesale Goods"
        }
    ],
    "sg:phone":"+44 131 663 2579",
    "sg:postcode":"EH22 1AG",
    "sg:province":"City of Edinburgh",
    "sg:tags":[
        "fishmonger"
    ],
    "wof:name":"John Aytoun Butchers",
    "wof:placetype":"venue"
},
  "geometry": {"coordinates":[-3.0714130402,55.8930892944],"type":"Point"}
}