{
  "type": "Feature",
  "properties": {
    "iso:country":"GB",
    "sg:address":"Corvedale Road",
    "sg:city":"Craven Arms",
    "sg:classifiers":[
        {
            "category":"Real Estate",
            "subcategory":"Real Estate Agent",
            "type":"Services"
        }
    ],
    "sg:phone":"+44 1588 672385",
    "sg:postcode":"SY7 9NE",
    "sg:province":"Herefordshire",
    "wof:name":"McCartneys",
    "wof:placetype":"venue"
},
  "geometry": {"coordinates":[-2.834729,52.440296],"type":"Point"}
}