{
  "type": "Feature",
  "properties": {
    "addr:full":"6 Broadwater Boulevard Worthing West Sussex BN14 8JE",
    "addr:housenumber":"6",
    "addr:postcode":"bn14 8je",
    "addr:street":"Broadwater Boulevard",
    "iso:country":"GB",
    "sg:address":"6 Broadwater Boulevard",
    "sg:city":"Worthing",
    "sg:classifiers":[
        {
            "category":"Building & Trades",
            "subcategory":"Construction",
            "type":"Services"
        }
    ],
    "sg:phone":"+44 1903 213300",
    "sg:postcode":"BN14 8JE",
    "sg:province":"West Sussex",
    "sg:tags":[
        "conversion",
        "loft"
    ],
    "wof:name":"Loftworld Conversions Ltd",
    "wof:placetype":"venue"
},
  "geometry": {"coordinates":[-0.372743994,50.8199958801],"type":"Point"}
}