{
  "type": "Feature",
  "properties": {
    "addr:full":"186 Bowes Rd London Greater London N11 2JG",
    "addr:housenumber":"186",
    "addr:postcode":"n11 2jg",
    "addr:street":"Bowes Rd",
    "iso:country":"GB",
    "sg:address":"186 Bowes Rd",
    "sg:city":"London",
    "sg:classifiers":[
        {
            "category":"Autos & Motor Vehicles",
            "subcategory":"Auto Supplies",
            "type":"Retail Goods"
        }
    ],
    "sg:postcode":"N11 2JG",
    "sg:province":"Greater London",
    "sg:tags":[
        "tyre"
    ],
    "wof:name":"Bowes Road Second Hand Tyres",
    "wof:placetype":"venue"
},
  "geometry": {"coordinates":[-0.1272239983,51.614780426],"type":"Point"}
}