{
  "type": "Feature",
  "properties": {
    "addr:full":"402 Stretford Road Manchester Cheshire M15 4AE",
    "addr:housenumber":"402",
    "addr:postcode":"m15 4ae",
    "addr:street":"Stretford Road",
    "iso:country":"GB",
    "sg:address":"402 Stretford Road",
    "sg:city":"Manchester",
    "sg:classifiers":[
        {
            "category":"Bars & Pubs",
            "type":"Food & Drink"
        }
    ],
    "sg:phone":"+44 161 226 1882",
    "sg:postcode":"M15 4AE",
    "sg:province":"Cheshire",
    "sg:tags":[
        "pubs",
        "inn"
    ],
    "wof:name":"Three Legs of Man",
    "wof:placetype":"venue"
},
  "geometry": {"coordinates":[-2.258299,53.465782],"type":"Point"}
}