{
  "type": "Feature",
  "properties": {
    "iso:country":"GB",
    "sg:address":"32 Market Street",
    "sg:city":"Galashiels",
    "sg:classifiers":[
        {
            "category":"Military Area",
            "subcategory":"Air Force Base",
            "type":"Public Place"
        }
    ],
    "sg:phone":"+44 1896 756057",
    "sg:postcode":"TD1 3AA",
    "sg:province":"Scottish Borders",
    "sg:tags":[
        "taxi",
        "hire",
        "private"
    ],
    "wof:name":"Dolphin Taxis",
    "wof:placetype":"venue"
},
  "geometry": {"coordinates":[-2.8063070774,55.6153640747],"type":"Point"}
}