{
  "type": "Feature",
  "properties": {
    "addr:full":"48 Berkeley Drive West Molesey Greater London KT8 1RA",
    "addr:housenumber":"48",
    "addr:postcode":"kt8 1ra",
    "addr:street":"Berkeley Drive",
    "iso:country":"GB",
    "sg:address":"48 Berkeley Drive",
    "sg:city":"West Molesey",
    "sg:classifiers":[
        {
            "category":"Retail",
            "subcategory":"Auto Repair",
            "type":"Services"
        }
    ],
    "sg:phone":"+44 20 8979 6415",
    "sg:postcode":"KT8 1RA",
    "sg:province":"Greater London",
    "sg:tags":[
        "body",
        "car"
    ],
    "wof:name":"A Brooks Mobile Repairs",
    "wof:placetype":"venue"
},
  "geometry": {"coordinates":[-0.376451,51.403881],"type":"Point"}
}