{
  "type": "Feature",
  "properties": {
    "addr:full":"Unit 9, Lightburn Trading Estate, Lightburn Road Ulverston Cumbria LA12 7NE",
    "addr:housenumber":"unit 9",
    "addr:postcode":"la12 7ne",
    "addr:street":"Trading Estate Lightburn Road",
    "iso:country":"GB",
    "sg:address":"Unit 9, Lightburn Trading Estate, Lightburn Road",
    "sg:city":"Ulverston",
    "sg:classifiers":[
        {
            "category":"Home & Garden",
            "subcategory":"Home Furnishings",
            "type":"Retail Goods"
        },
        {
            "category":"Home & Garden",
            "subcategory":"Building Materials",
            "type":"Retail Goods"
        }
    ],
    "sg:phone":"+44 1229 586268",
    "sg:postcode":"LA12 7NE",
    "sg:province":"Cumbria",
    "sg:tags":[
        "installers",
        "planner",
        "kitchen",
        "furnishers"
    ],
    "wof:name":"Les Johnston",
    "wof:placetype":"venue"
},
  "geometry": {"coordinates":[-3.098418951,54.1928443909],"type":"Point"}
}