{
  "type": "Feature",
  "properties": {
    "addr:full":"23 Briar Clo Luton Bedfordshire LU2 8EA",
    "addr:housenumber":"23",
    "addr:postcode":"lu2 8ea",
    "addr:street":"Briar Clo",
    "iso:country":"GB",
    "sg:address":"23 Briar Clo",
    "sg:city":"Luton",
    "sg:classifiers":[
        {
            "category":"Building & Trades",
            "subcategory":"Construction",
            "type":"Services"
        }
    ],
    "sg:phone":"+44 1582 419060",
    "sg:postcode":"LU2 8EA",
    "sg:province":"Bedfordshire",
    "sg:tags":[
        "roofing"
    ],
    "wof:name":"R J Keating",
    "wof:placetype":"venue"
},
  "geometry": {"coordinates":[-0.3847700059,51.9011573792],"type":"Point"}
}