{
  "type": "Feature",
  "properties": {
    "addr:full":"12 Stephen Mews London Greater London W1T 1AH",
    "addr:housenumber":"12",
    "addr:postcode":"w1t 1ah",
    "addr:street":"Stephen Mews",
    "iso:country":"GB",
    "sg:address":"12 Stephen Mews",
    "sg:city":"London",
    "sg:classifiers":[
        {
            "category":"Retail",
            "subcategory":"Photofinishing",
            "type":"Services"
        }
    ],
    "sg:phone":"+44 20 7580 8585",
    "sg:postcode":"W1T 1AH",
    "sg:province":"Greater London",
    "sg:tags":[
        "photographic",
        "processor"
    ],
    "wof:name":"Graham Nash (Laboratories) Ltd.",
    "wof:placetype":"venue"
},
  "geometry": {"coordinates":[-0.133513,51.517799],"type":"Point"}
}