{
  "type": "Feature",
  "properties": {
    "addr:full":"The Enterprise Centre, Stn Pde Eastbourne East Sussex BN21 1BD",
    "addr:postcode":"bn21 1bd",
    "iso:country":"GB",
    "sg:address":"The Enterprise Centre, Stn Pde",
    "sg:city":"Eastbourne",
    "sg:classifiers":[
        {
            "category":"Personal",
            "type":"Services"
        }
    ],
    "sg:postcode":"BN21 1BD",
    "sg:province":"East Sussex",
    "sg:tags":[
        "dressmaker"
    ],
    "wof:name":"Needlebox",
    "wof:placetype":"venue"
},
  "geometry": {"coordinates":[0.28535,50.766911],"type":"Point"}
}