{
  "type": "Feature",
  "properties": {
    "iso:country":"GB",
    "sg:address":"The Fire Station, Newtown Road",
    "sg:city":"Nuneaton",
    "sg:classifiers":[
        {
            "category":"Government",
            "subcategory":"Fire Station",
            "type":"Public Place"
        }
    ],
    "sg:phone":"+44 24 7638 3486",
    "sg:postcode":"CV11 4HR",
    "sg:province":"Leicestershire",
    "wof:name":"Warwickshire Fire & Rescue Service",
    "wof:placetype":"venue"
},
  "geometry": {"coordinates":[-1.46445,52.52137],"type":"Point"}
}