{
  "type": "Feature",
  "properties": {
    "iso:country":"GB",
    "sg:address":"Sixteen Foot Bank, Christchurch",
    "sg:city":"Wisbech",
    "sg:classifiers":[
        {
            "category":"Farming",
            "subcategory":"Farm",
            "type":"Manufacturing & Wholesale Goods"
        }
    ],
    "sg:postcode":"PE14 9NR",
    "sg:province":"Cambridgeshire",
    "sg:tags":[
        "mixed",
        "crop"
    ],
    "wof:name":"Bedlam Farm",
    "wof:placetype":"venue"
},
  "geometry": {"coordinates":[0.19397,52.560558],"type":"Point"}
}