{
  "type": "Feature",
  "properties": {
    "addr:full":"Tarbock Rd, Huyton Liverpool Merseyside L36 5XW",
    "addr:postcode":"l36 5xw",
    "addr:street":"Tarbock Rd",
    "iso:country":"GB",
    "sg:address":"Tarbock Rd, Huyton",
    "sg:city":"Liverpool",
    "sg:classifiers":[
        {
            "category":"Organizations",
            "subcategory":"Non-profit Organization",
            "type":"Services"
        }
    ],
    "sg:phone":"+44 151 480 9223",
    "sg:postcode":"L36 5XW",
    "sg:province":"Merseyside",
    "sg:tags":[
        "organisation",
        "voluntary",
        "charity"
    ],
    "wof:name":"The Connaughtons Day Centre",
    "wof:placetype":"venue"
},
  "geometry": {"coordinates":[-2.84721,53.408207],"type":"Point"}
}