{
  "type": "Feature",
  "properties": {
    "addr:full":"112 Twickenham Road Isleworth Greater London TW7 6DL",
    "addr:housenumber":"112",
    "addr:postcode":"tw7 6dl",
    "addr:street":"Twickenham Road",
    "iso:country":"GB",
    "sg:address":"112 Twickenham Road",
    "sg:city":"Isleworth",
    "sg:classifiers":[
        {
            "category":"Place Of Worship",
            "type":"Public Place"
        }
    ],
    "sg:phone":"+44 20 8560 1431",
    "sg:postcode":"TW7 6DL",
    "sg:province":"Greater London",
    "wof:name":"St.Bridget R C Church",
    "wof:placetype":"venue"
},
  "geometry": {"coordinates":[-0.328401,51.469536],"type":"Point"}
}