{
  "type": "Feature",
  "properties": {
    "addr:full":"12 High St Wallingford Oxfordshire OX10 7HH",
    "addr:housenumber":"12",
    "addr:postcode":"ox10 7hh",
    "addr:street":"High St",
    "iso:country":"GB",
    "sg:address":"12 High St",
    "sg:city":"Wallingford",
    "sg:classifiers":[
        {
            "category":"Shopping",
            "subcategory":"Pharmacy",
            "type":"Retail Goods"
        }
    ],
    "sg:phone":"+44 1865 343866",
    "sg:postcode":"OX10 7HH",
    "sg:province":"Oxfordshire",
    "sg:tags":[
        "medicine",
        "therapy"
    ],
    "wof:name":"Allergy Care",
    "wof:placetype":"venue"
},
  "geometry": {"coordinates":[-1.165797,51.644238],"type":"Point"}
}