{
  "type": "Feature",
  "properties": {
    "iso:country":"GB",
    "sg:address":"86 The Cut",
    "sg:city":"London",
    "sg:classifiers":[
        {
            "category":"Bars & Pubs",
            "type":"Food & Drink"
        }
    ],
    "sg:phone":"+44 20 7207 3984",
    "sg:postcode":"SE1 8LW",
    "sg:province":"Greater London",
    "sg:tags":[
        "pubs",
        "inn"
    ],
    "wof:name":"The Windmill Tavern",
    "wof:placetype":"venue"
},
  "geometry": {"coordinates":[-0.1078630015,51.5030212402],"type":"Point"}
}