{
  "type": "Feature",
  "properties": {
    "iso:country":"GB",
    "sg:address":"19 Westland Drive",
    "sg:city":"Glasgow",
    "sg:classifiers":[
        {
            "category":"Social Services",
            "subcategory":"Adult Care",
            "type":"Services"
        },
        {
            "category":"Social Services",
            "subcategory":"Retirement Home",
            "type":"Services"
        }
    ],
    "sg:phone":"+44 141 950 1611",
    "sg:postcode":"G14 9NY",
    "sg:province":"Glasgow City",
    "sg:tags":[
        "accomodation",
        "housing",
        "sheltered"
    ],
    "wof:name":"WHITEINCH HOMES",
    "wof:placetype":"venue"
},
  "geometry": {"coordinates":[-4.3393940926,55.8775749207],"type":"Point"}
}