{
  "type": "Feature",
  "properties": {
    "iso:country":"GB",
    "sg:address":"19 Church Street, Alfreton",
    "sg:city":"Derby",
    "sg:classifiers":[
        {
            "category":"Home & Garden",
            "subcategory":"Carpets & Floor Coverings",
            "type":"Retail Goods"
        }
    ],
    "sg:phone":"+44 1773 831328",
    "sg:postcode":"DE55 7AH",
    "sg:province":"Derbyshire",
    "sg:tags":[
        "carpets",
        "rug",
        "matting"
    ],
    "wof:name":"Marshall Carpets",
    "wof:placetype":"venue"
},
  "geometry": {"coordinates":[-1.4372620583,53.0962295532],"type":"Point"}
}