{
  "type": "Feature",
  "properties": {
    "addr:full":"Shortmead House, Fairfield Road Biggleswade Bedfordshire SG18 0AA",
    "addr:postcode":"sg18 0aa",
    "addr:street":"Fairfield Road",
    "iso:country":"GB",
    "sg:address":"Shortmead House, Fairfield Road",
    "sg:city":"Biggleswade",
    "sg:classifiers":[
        {
            "category":"Professional",
            "subcategory":"Management & Consulting",
            "type":"Services"
        }
    ],
    "sg:postcode":"SG18 0AA",
    "sg:province":"Bedfordshire",
    "sg:tags":[
        "consultant",
        "business"
    ],
    "wof:name":"Mark Guest Associates",
    "wof:placetype":"venue"
},
  "geometry": {"coordinates":[-0.266051,52.094879],"type":"Point"}
}