{
  "type": "Feature",
  "properties": {
    "iso:country":"GB",
    "sg:address":"Hob Lane, Burton Grn",
    "sg:city":"Kenilworth",
    "sg:classifiers":[
        {
            "category":"Education",
            "subcategory":"School",
            "type":"Public Place"
        }
    ],
    "sg:phone":"+44 24 7646 4130",
    "sg:postcode":"CV8 1QB",
    "sg:province":"Warwickshire",
    "sg:tags":[
        "local",
        "authority"
    ],
    "wof:name":"Burton Green C of E Primary School",
    "wof:placetype":"venue"
},
  "geometry": {"coordinates":[-1.616859,52.375336],"type":"Point"}
}