{
  "type": "Feature",
  "properties": {
    "iso:country":"GB",
    "sg:address":"11 Station Road",
    "sg:city":"Carnoustie",
    "sg:classifiers":[
        {
            "category":"Shopping",
            "subcategory":"Bicycles & Sporting Goods",
            "type":"Retail Goods"
        }
    ],
    "sg:phone":"+44 1241 852533",
    "sg:postcode":"DD7 6AR",
    "sg:province":"Angus",
    "sg:tags":[
        "dance",
        "balletwear"
    ],
    "wof:name":"Tayside Dancewear Centre",
    "wof:placetype":"venue"
},
  "geometry": {"coordinates":[-2.70682,56.501465],"type":"Point"}
}