{
  "type": "Feature",
  "properties": {
    "addr:full":"Unit 9, Moy Rd, Taffs Well Cardiff Caerphilly CF15 7PW",
    "addr:housenumber":"unit 9",
    "addr:postcode":"cf15 7pw",
    "addr:street":"Moy Rd;Well",
    "iso:country":"GB",
    "sg:address":"Unit 9, Moy Rd, Taffs Well",
    "sg:city":"Cardiff",
    "sg:classifiers":[
        {
            "category":"Professional",
            "subcategory":"Management & Consulting",
            "type":"Services"
        }
    ],
    "sg:phone":"+44 29 2081 3400",
    "sg:postcode":"CF15 7PW",
    "sg:province":"Caerphilly",
    "sg:tags":[
        "consultant"
    ],
    "wof:name":"Business Telecommunications & Technologies Ltd",
    "wof:placetype":"venue"
},
  "geometry": {"coordinates":[-3.26804,51.54549],"type":"Point"}
}