{
  "type": "Feature",
  "properties": {
    "addr:full":"40 West Gate Mansfield Nottinghamshire NG18 1RS",
    "addr:housenumber":"40",
    "addr:postcode":"ng18 1rs",
    "addr:street":"West Gate",
    "iso:country":"GB",
    "sg:address":"40 West Gate",
    "sg:city":"Mansfield",
    "sg:classifiers":[
        {
            "category":"Shopping",
            "subcategory":"Department Store",
            "type":"Retail Goods"
        }
    ],
    "sg:phone":"+44 1623 424082",
    "sg:postcode":"NG18 1RS",
    "sg:province":"Nottinghamshire",
    "wof:name":"Fancytex",
    "wof:placetype":"venue"
},
  "geometry": {"coordinates":[-1.1980750561,53.1458091736],"type":"Point"}
}