{
  "type": "Feature",
  "properties": {
    "iso:country":"GB",
    "sg:address":"27 Osborne St,",
    "sg:city":"Grimsby",
    "sg:classifiers":[
        {
            "category":"Farming",
            "subcategory":"Fish & Marine Products",
            "type":"Manufacturing & Wholesale Goods"
        }
    ],
    "sg:postcode":"DN31 1EY",
    "sg:province":"Lincolnshire",
    "sg:tags":[
        "fisherman"
    ],
    "wof:name":"Euro Shellfish (Boston) Ltd",
    "wof:placetype":"venue"
},
  "geometry": {"coordinates":[-0.083853,53.56498],"type":"Point"}
}