{
  "type": "Feature",
  "properties": {
    "addr:full":"75 London Rd Macclesfield Cheshire SK11 7RL",
    "addr:housenumber":"75",
    "addr:postcode":"sk11 7rl",
    "addr:street":"London Rd",
    "iso:country":"GB",
    "sg:address":"75 London Rd",
    "sg:city":"Macclesfield",
    "sg:classifiers":[
        {
            "category":"Retail",
            "subcategory":"Storage",
            "type":"Services"
        }
    ],
    "sg:postcode":"SK11 7RL",
    "sg:province":"Cheshire",
    "sg:tags":[
        "household",
        "removal"
    ],
    "wof:name":"Easy Move Transport",
    "wof:placetype":"venue"
},
  "geometry": {"coordinates":[-2.122637,53.248013],"type":"Point"}
}