{
  "type": "Feature",
  "properties": {
    "iso:country":"GB",
    "sg:address":"75 London Rd",
    "sg:city":"Macclesfield",
    "sg:classifiers":[
        {
            "category":"Retail",
            "subcategory":"Storage",
            "type":"Services"
        }
    ],
    "sg:postcode":"SK11 7RL",
    "sg:province":"Cheshire",
    "sg:tags":[
        "household",
        "removal"
    ],
    "wof:name":"Easy Move Transport",
    "wof:placetype":"venue"
},
  "geometry": {"coordinates":[-2.122637,53.248013],"type":"Point"}
}