{
  "type": "Feature",
  "properties": {
    "iso:country":"GB",
    "sg:address":"22 Holmethorpe Avenue",
    "sg:city":"Redhill",
    "sg:classifiers":[
        {
            "category":"Retail",
            "subcategory":"Auto Repair",
            "type":"Services"
        }
    ],
    "sg:phone":"+44 1737 779988",
    "sg:postcode":"RH1 2NL",
    "sg:province":"Surrey",
    "sg:tags":[
        "modification",
        "garage"
    ],
    "wof:name":"Michael S Parren",
    "wof:placetype":"venue"
},
  "geometry": {"coordinates":[-0.158873,51.249577],"type":"Point"}
}