{
  "type": "Feature",
  "properties": {
    "addr:full":"The Beehive, Hernhill Faversham Kent ME13 9JR",
    "addr:postcode":"me13 9jr",
    "addr:street":"Hernhill",
    "iso:country":"GB",
    "sg:address":"The Beehive, Hernhill",
    "sg:city":"Faversham",
    "sg:classifiers":[
        {
            "category":"Professional",
            "subcategory":"Management & Consulting",
            "type":"Services"
        }
    ],
    "sg:phone":"+44 1227 752444",
    "sg:postcode":"ME13 9JR",
    "sg:province":"Kent",
    "sg:tags":[
        "marketing",
        "consultant"
    ],
    "wof:name":"M B F",
    "wof:placetype":"venue"
},
  "geometry": {"coordinates":[0.9613299966,51.3082084656],"type":"Point"}
}