{
  "type": "Feature",
  "properties": {
    "iso:country":"GB",
    "sg:address":"1st Floor Offices, 1 George Street",
    "sg:city":"Hailsham",
    "sg:classifiers":[
        {
            "category":"Insurance",
            "subcategory":"Insurance Agent",
            "type":"Services"
        }
    ],
    "sg:phone":"+44 1323 431804",
    "sg:postcode":"BN27 1AD",
    "sg:province":"East Sussex",
    "sg:tags":[
        "broker"
    ],
    "wof:name":"Meads Financial Consultants",
    "wof:placetype":"venue"
},
  "geometry": {"coordinates":[0.25652,50.865383],"type":"Point"}
}