{
  "type": "Feature",
  "properties": {
    "addr:full":"Unit 7, The Bridge Business Centre Southall Greater London UB2 4AY",
    "addr:housenumber":"unit 7",
    "addr:postcode":"ub2 4ay",
    "iso:country":"GB",
    "sg:address":"Unit 7, The Bridge Business Centre",
    "sg:city":"Southall",
    "sg:classifiers":[
        {
            "category":"Coffee & Tea",
            "type":"Food & Drink"
        }
    ],
    "sg:phone":"+44 20 8571 0111",
    "sg:postcode":"UB2 4AY",
    "sg:province":"Greater London",
    "sg:tags":[
        "machine"
    ],
    "wof:name":"Aroma Coffee",
    "wof:placetype":"venue"
},
  "geometry": {"coordinates":[-0.3534939885,51.5087852478],"type":"Point"}
}