{
  "type": "Feature",
  "properties": {
    "addr:full":"18 Lee Terrace, Blackheath London Greater London SE3 9TZ",
    "addr:housenumber":"18",
    "addr:postcode":"se3 9tz",
    "addr:street":"Lee Terrace",
    "iso:country":"GB",
    "sg:address":"18 Lee Terrace, Blackheath",
    "sg:city":"London",
    "sg:classifiers":[
        {
            "category":"Real Estate",
            "subcategory":"Developer",
            "type":"Services"
        }
    ],
    "sg:postcode":"SE3 9TZ",
    "sg:province":"Greater London",
    "sg:tags":[
        "property"
    ],
    "wof:name":"Lee Terrors Ltd",
    "wof:placetype":"venue"
},
  "geometry": {"coordinates":[0.002787,51.463238],"type":"Point"}
}