{
  "type": "Feature",
  "properties": {
    "iso:country":"GB",
    "sg:address":"Brittania Works, Melton Road",
    "sg:city":"Leicester",
    "sg:classifiers":[
        {
            "category":"Building & Trades",
            "subcategory":"Construction",
            "type":"Services"
        }
    ],
    "sg:phone":"+44 116 269 4743",
    "sg:postcode":"LE4 8BD",
    "sg:province":"Leicestershire",
    "sg:tags":[
        "window",
        "replacement"
    ],
    "wof:name":"Norman K Antcliffe Joinery",
    "wof:placetype":"venue"
},
  "geometry": {"coordinates":[-1.0939069986,52.6871528625],"type":"Point"}
}