{
  "type": "Feature",
  "properties": {
    "iso:country":"GB",
    "sg:address":"Craft Arcade, Granary Wharf, Dark Neville Street",
    "sg:city":"Leeds",
    "sg:classifiers":[
        {
            "category":"Education",
            "subcategory":"Library",
            "type":"Public Place"
        },
        {
            "category":"Home & Garden",
            "subcategory":"Home Furnishings",
            "type":"Retail Goods"
        }
    ],
    "sg:phone":"+44 1709 368117",
    "sg:postcode":"LS1 4BR",
    "sg:province":"West Yorkshire",
    "sg:tags":[
        "reproduction",
        "pine",
        "furniture"
    ],
    "wof:name":"Woodlands Pine",
    "wof:placetype":"venue"
},
  "geometry": {"coordinates":[-1.546587,53.794495],"type":"Point"}
}