{
  "type": "Feature",
  "properties": {
    "iso:country":"GB",
    "sg:address":"9 Mary Street",
    "sg:city":"Sheffield",
    "sg:classifiers":[
        {
            "category":"Home & Garden",
            "subcategory":"Carpets & Floor Coverings",
            "type":"Retail Goods"
        }
    ],
    "sg:phone":"+44 114 275 1559",
    "sg:postcode":"S1 4RT",
    "sg:province":"South Yorkshire",
    "sg:tags":[
        "carpets",
        "rug",
        "matting"
    ],
    "wof:name":"Carpetworld Ltd.",
    "wof:placetype":"venue"
},
  "geometry": {"coordinates":[-1.47071,53.373806],"type":"Point"}
}