{
  "type": "Feature",
  "properties": {
    "addr:full":"34 Oxford Street Harrogate North Yorkshire HG1 1PP",
    "addr:housenumber":"34",
    "addr:postcode":"hg1 1pp",
    "addr:street":"Oxford Street",
    "iso:country":"GB",
    "sg:address":"34 Oxford Street",
    "sg:city":"Harrogate",
    "sg:classifiers":[
        {
            "category":"Home & Garden",
            "subcategory":"Household Appliances",
            "type":"Retail Goods"
        }
    ],
    "sg:phone":"+44 1423 568477",
    "sg:postcode":"HG1 1PP",
    "sg:province":"North Yorkshire",
    "sg:tags":[
        "electrical",
        "domestic"
    ],
    "wof:name":"Tandy",
    "wof:placetype":"venue"
},
  "geometry": {"coordinates":[-1.5423920155,53.9938964844],"type":"Point"}
}