{
  "type": "Feature",
  "properties": {
    "iso:country":"GB",
    "sg:address":"371 Poplars Ave, Orford",
    "sg:city":"Warrington",
    "sg:classifiers":[
        {
            "category":"Building & Trades",
            "subcategory":"Construction",
            "type":"Services"
        }
    ],
    "sg:phone":"+44 1925 636534",
    "sg:postcode":"WA2 9UH",
    "sg:province":"Cheshire",
    "sg:tags":[
        "builder"
    ],
    "wof:name":"Wymac Ltd",
    "wof:placetype":"venue"
},
  "geometry": {"coordinates":[-2.583494,53.416206],"type":"Point"}
}