{
  "type": "Feature",
  "properties": {
    "addr:full":"13 Linden Street Romford Essex RM7 7DP",
    "addr:housenumber":"13",
    "addr:postcode":"rm7 7dp",
    "addr:street":"Linden Street",
    "iso:country":"GB",
    "sg:address":"13 Linden Street",
    "sg:city":"Romford",
    "sg:classifiers":[
        {
            "category":"Building & Trades",
            "subcategory":"Construction",
            "type":"Services"
        }
    ],
    "sg:postcode":"RM7 7DP",
    "sg:province":"Essex",
    "sg:tags":[
        "joiner",
        "carpenter"
    ],
    "wof:name":"Blair Carpentry",
    "wof:placetype":"venue"
},
  "geometry": {"coordinates":[0.1764679998,51.5792236328],"type":"Point"}
}