{
  "type": "Feature",
  "properties": {
    "addr:full":"25-27 Park Street Weymouth Dorset DT4 7DF",
    "addr:housenumber":"25-27",
    "addr:postcode":"dt4 7df",
    "addr:street":"Park Street",
    "iso:country":"GB",
    "sg:address":"25-27 Park Street",
    "sg:city":"Weymouth",
    "sg:classifiers":[
        {
            "category":"Organizations",
            "subcategory":"Community Association",
            "type":"Services"
        },
        {
            "category":"Organizations",
            "subcategory":"Membership Organization",
            "type":"Services"
        }
    ],
    "sg:phone":"+44 1305 785757",
    "sg:postcode":"DT4 7DF",
    "sg:province":"Dorset",
    "sg:tags":[
        "club",
        "social"
    ],
    "wof:name":"Royal Naval Association",
    "wof:placetype":"venue"
},
  "geometry": {"coordinates":[-2.455312,50.61311],"type":"Point"}
}