{
  "type": "Feature",
  "properties": {
    "addr:full":"Interserve House, Ruscombe Park Reading Berkshire RG10 9JU",
    "addr:postcode":"rg10 9ju",
    "addr:street":"Ruscombe Park",
    "iso:country":"GB",
    "sg:address":"Interserve House, Ruscombe Park",
    "sg:city":"Reading",
    "sg:classifiers":[
        {
            "category":"Professional",
            "subcategory":"Business Services",
            "type":"Services"
        }
    ],
    "sg:phone":"+44 118 932 0123",
    "sg:postcode":"RG10 9JU",
    "sg:province":"Berkshire",
    "sg:tags":[
        "holding"
    ],
    "wof:name":"Tilbury Investments Ltd.",
    "wof:placetype":"venue"
},
  "geometry": {"coordinates":[-0.8547589779,51.4799690247],"type":"Point"}
}