{
  "type": "Feature",
  "properties": {
    "iso:country":"GB",
    "sg:address":"Akenham Hall Farm, Henley Rd, Akenham",
    "sg:city":"Ipswich",
    "sg:classifiers":[
        {
            "category":"Manufacturing",
            "subcategory":"Building Materials",
            "type":"Manufacturing & Wholesale Goods"
        }
    ],
    "sg:phone":"+44 1473 219063",
    "sg:postcode":"IP1 6TE",
    "sg:province":"Suffolk",
    "sg:tags":[
        "mnfr",
        "maker",
        "cabinet"
    ],
    "wof:name":"D Watts",
    "wof:placetype":"venue"
},
  "geometry": {"coordinates":[1.133573,52.090954],"type":"Point"}
}