{
  "type": "Feature",
  "properties": {
    "iso:country":"GB",
    "sg:address":"144 Walkden Road, Worsley",
    "sg:city":"Manchester",
    "sg:classifiers":[
        {
            "category":"Insurance",
            "subcategory":"Insurance Agent",
            "type":"Services"
        }
    ],
    "sg:phone":"+44 161 799 7771",
    "sg:postcode":"M28 7DP",
    "sg:province":"Greater Manchester",
    "sg:tags":[
        "broker"
    ],
    "wof:name":"Hannah & Lawton (Insurance Brokers) Ltd.",
    "wof:placetype":"venue"
},
  "geometry": {"coordinates":[-2.3964989185,53.518951416],"type":"Point"}
}