{
  "type": "Feature",
  "properties": {
    "addr:full":"Jubilee Works, Cradley Road Cradley Heath West Midlands B64 7BA",
    "addr:postcode":"b64 7ba",
    "addr:street":"Cradley Road",
    "iso:country":"GB",
    "sg:address":"Jubilee Works, Cradley Road",
    "sg:city":"Cradley Heath",
    "sg:classifiers":[
        {
            "category":"Wholesale",
            "subcategory":"Construction Materials",
            "type":"Manufacturing & Wholesale Goods"
        }
    ],
    "sg:phone":"+44 1384 560611",
    "sg:postcode":"B64 7BA",
    "sg:province":"West Midlands",
    "sg:tags":[
        "lift"
    ],
    "wof:name":"Holtite Ltd.",
    "wof:placetype":"venue"
},
  "geometry": {"coordinates":[-2.081574,52.472416],"type":"Point"}
}