{
  "type": "Feature",
  "properties": {
    "addr:full":"Flat 10 Edinburgh City of Edinburgh EH1 1QN",
    "addr:housenumber":"flat 10",
    "addr:postcode":"eh1 1qn",
    "iso:country":"GB",
    "sg:address":"Flat 10",
    "sg:city":"Edinburgh",
    "sg:classifiers":[
        {
            "category":"Recreation",
            "subcategory":"Amusement Park",
            "type":"Entertainment"
        }
    ],
    "sg:postcode":"EH1 1QN",
    "sg:province":"City of Edinburgh",
    "sg:tags":[
        "arcade"
    ],
    "wof:name":"Johnny's Entertainments (Edingburgh) Ltd",
    "wof:placetype":"venue"
},
  "geometry": {"coordinates":[-3.188509,55.949169],"type":"Point"}
}