{
  "type": "Feature",
  "properties": {
    "iso:country":"GB",
    "sg:address":"Braefield Road, Portpatrick",
    "sg:city":"Stranraer",
    "sg:classifiers":[
        {
            "category":"Travel",
            "subcategory":"Hotels & Motels",
            "type":"Entertainment"
        }
    ],
    "sg:phone":"+44 1776 810255",
    "sg:postcode":"DG9 8TA",
    "sg:province":"Dumfries and Galloway",
    "sg:tags":[
        "house",
        "guest"
    ],
    "wof:name":"Braefield House Hotel",
    "wof:placetype":"venue"
},
  "geometry": {"coordinates":[-5.0164442062,54.9056358337],"type":"Point"}
}