{
  "type": "Feature",
  "properties": {
    "iso:country":"GB",
    "sg:address":"Waterloo Street",
    "sg:city":"Teignmouth",
    "sg:classifiers":[
        {
            "category":"Food & Beverages",
            "subcategory":"Bakery",
            "type":"Retail Goods"
        }
    ],
    "sg:phone":"+44 1626 773960",
    "sg:postcode":"TQ14 8AS",
    "sg:province":"Devon",
    "sg:tags":[
        "baker"
    ],
    "wof:name":"Luder's Swiss Patisserie Ltd.",
    "wof:placetype":"venue"
},
  "geometry": {"coordinates":[-3.4954090118,50.5459632874],"type":"Point"}
}