{
  "type": "Feature",
  "properties": {
    "addr:full":"103 Old Church Rd London Greater London E4 6ST",
    "addr:housenumber":"103",
    "addr:postcode":"e4 6st",
    "addr:street":"Old Church Rd",
    "iso:country":"GB",
    "sg:address":"103 Old Church Rd",
    "sg:city":"London",
    "sg:classifiers":[
        {
            "category":"Shopping",
            "subcategory":"Florist",
            "type":"Retail Goods"
        }
    ],
    "sg:postcode":"E4 6ST",
    "sg:province":"Greater London",
    "wof:name":"Julia,Shutle,",
    "wof:placetype":"venue"
},
  "geometry": {"coordinates":[-0.0169539992,51.6197891235],"type":"Point"}
}