{
  "type": "Feature",
  "properties": {
    "addr:full":"Flat 7 Davids Court, 14 Frant Road Tunbridge Wells East Sussex TN2 5SN",
    "addr:housenumber":"14",
    "addr:postcode":"tn2 5sn",
    "addr:street":"Davids;Frant Road",
    "iso:country":"GB",
    "sg:address":"Flat 7 Davids Court, 14 Frant Road",
    "sg:city":"Tunbridge Wells",
    "sg:classifiers":[
        {
            "category":"Communications",
            "type":"Services"
        }
    ],
    "sg:postcode":"TN2 5SN",
    "sg:province":"East Sussex",
    "sg:tags":[
        "data",
        "network"
    ],
    "wof:name":"Yalza Data Ltd",
    "wof:placetype":"venue"
},
  "geometry": {"coordinates":[0.2595700026,51.123210907],"type":"Point"}
}