{
  "type": "Feature",
  "properties": {
    "addr:full":"62 Chantal Ave, Pen-y-fai Bridgend Bridgend CF31 4NW",
    "addr:housenumber":"62",
    "addr:postcode":"cf31 4nw",
    "addr:street":"Chantal Ave",
    "iso:country":"GB",
    "sg:address":"62 Chantal Ave, Pen-y-fai",
    "sg:city":"Bridgend",
    "sg:classifiers":[
        {
            "category":"Professional",
            "subcategory":"Computer Services",
            "type":"Services"
        }
    ],
    "sg:postcode":"CF31 4NW",
    "sg:province":"Bridgend",
    "sg:tags":[
        "system",
        "software"
    ],
    "wof:name":"Bellinghan,Anne,",
    "wof:placetype":"venue"
},
  "geometry": {"coordinates":[-3.59327,51.528934],"type":"Point"}
}