{
  "type": "Feature",
  "properties": {
    "addr:full":"Unit 3, Platts Rd Stourbridge Staffordshire DY8 4YR",
    "addr:housenumber":"unit 3",
    "addr:postcode":"dy8 4yr",
    "addr:street":"Platts Rd",
    "iso:country":"GB",
    "sg:address":"Unit 3, Platts Rd",
    "sg:city":"Stourbridge",
    "sg:classifiers":[
        {
            "category":"Communications",
            "subcategory":"News Services",
            "type":"Services"
        }
    ],
    "sg:phone":"+44 1384 393124",
    "sg:postcode":"DY8 4YR",
    "sg:province":"Staffordshire",
    "sg:tags":[
        "press"
    ],
    "wof:name":"Integrity Craftsmanship",
    "wof:placetype":"venue"
},
  "geometry": {"coordinates":[-2.1561560631,52.4701805115],"type":"Point"}
}