{
  "type": "Feature",
  "properties": {
    "iso:country":"GB",
    "sg:address":"Red House Farm, Gt Orton",
    "sg:city":"Carlisle",
    "sg:classifiers":[
        {
            "category":"Farming",
            "subcategory":"Farm",
            "type":"Manufacturing & Wholesale Goods"
        }
    ],
    "sg:postcode":"CA5 6JS",
    "sg:province":"Cumbria",
    "sg:tags":[
        "mixed",
        "crop"
    ],
    "wof:name":"Addison,John & Son,",
    "wof:placetype":"venue"
},
  "geometry": {"coordinates":[-3.01267,54.873718],"type":"Point"}
}