{
  "type": "Feature",
  "properties": {
    "iso:country":"GB",
    "sg:address":"Unit 3a Wayside Busines Park, Wilsons Lane",
    "sg:city":"Coventry",
    "sg:classifiers":[
        {
            "category":"Freight",
            "type":"Transportation"
        },
        {
            "category":"Shopping",
            "subcategory":"Music",
            "type":"Retail Goods"
        }
    ],
    "sg:postcode":"CV6 6JA",
    "sg:province":"Warwickshire",
    "sg:tags":[
        "haulage",
        "record",
        "tape",
        "road",
        "cd"
    ],
    "wof:name":"W G Goddard & Son Ltd.",
    "wof:placetype":"venue"
},
  "geometry": {"coordinates":[-1.486899972,52.4566001892],"type":"Point"}
}