{
  "type": "Feature",
  "properties": {
    "iso:country":"GB",
    "sg:address":"20 Cambridge Road, St Marychurch",
    "sg:city":"Torquay",
    "sg:classifiers":[
        {
            "category":"Travel",
            "subcategory":"Hotels & Motels",
            "type":"Entertainment"
        }
    ],
    "sg:postcode":"TQ1 4QN",
    "sg:province":"Devon",
    "sg:tags":[
        "house",
        "guest"
    ],
    "wof:name":"The Cambridge",
    "wof:placetype":"venue"
},
  "geometry": {"coordinates":[-3.526706934,50.4865036011],"type":"Point"}
}