{
  "type": "Feature",
  "properties": {
    "iso:country":"GB",
    "sg:address":"6 Tan Lan, Llanfrothen",
    "sg:city":"Porthmadog",
    "sg:classifiers":[
        {
            "category":"Home & Garden",
            "subcategory":"Building Materials",
            "type":"Retail Goods"
        },
        {
            "category":"Building & Trades",
            "subcategory":"Construction",
            "type":"Services"
        }
    ],
    "sg:postcode":"LL48 6SG",
    "sg:province":"Gwynedd",
    "sg:tags":[
        "dry",
        "plasterers",
        "installers",
        "lining",
        "insulation",
        "screeders"
    ],
    "wof:name":"Chamberlain Plastering & Dry Lining Contractors",
    "wof:placetype":"venue"
},
  "geometry": {"coordinates":[-4.053285,52.952103],"type":"Point"}
}