{
  "type": "Feature",
  "properties": {
    "addr:full":"Unit 7, Curran Rd Cardiff Cardiff CF10 5DF",
    "addr:housenumber":"unit 7",
    "addr:postcode":"cf10 5df",
    "addr:street":"Curran Rd",
    "iso:country":"GB",
    "sg:address":"Unit 7, Curran Rd",
    "sg:city":"Cardiff",
    "sg:classifiers":[
        {
            "category":"Autos & Motor Vehicles",
            "subcategory":"Automobile Sales",
            "type":"Retail Goods"
        }
    ],
    "sg:phone":"+44 29 2038 4848",
    "sg:postcode":"CF10 5DF",
    "sg:province":"Cardiff",
    "sg:tags":[
        "commercial"
    ],
    "wof:name":"Japanese Direct Import Agency",
    "wof:placetype":"venue"
},
  "geometry": {"coordinates":[-3.176906,51.472137],"type":"Point"}
}