{
  "type": "Feature",
  "properties": {
    "addr:full":"3 Stanley Lane, Outwood Wakefield West Yorkshire WF1 3EB",
    "addr:housenumber":"3",
    "addr:postcode":"wf1 3eb",
    "addr:street":"Stanley Lane;West",
    "iso:country":"GB",
    "sg:address":"3 Stanley Lane, Outwood",
    "sg:city":"Wakefield",
    "sg:classifiers":[
        {
            "category":"Farming",
            "subcategory":"Poultry Farm",
            "type":"Manufacturing & Wholesale Goods"
        }
    ],
    "sg:phone":"+44 1924 823006",
    "sg:postcode":"WF1 3EB",
    "sg:province":"West Yorkshire",
    "wof:name":"Stanacre Poultry Co. Ltd.",
    "wof:placetype":"venue"
},
  "geometry": {"coordinates":[-1.491044,53.708878],"type":"Point"}
}