{
  "type": "Feature",
  "properties": {
    "iso:country":"GB",
    "sg:address":"5 Queens Square",
    "sg:city":"Poulton Le Fylde",
    "sg:classifiers":[
        {
            "category":"Insurance",
            "subcategory":"Insurance Agent",
            "type":"Services"
        }
    ],
    "sg:phone":"+44 1253 892136",
    "sg:postcode":"FY6 7BW",
    "sg:province":"Lancashire",
    "wof:name":"Breck Insurance",
    "wof:placetype":"venue"
},
  "geometry": {"coordinates":[-2.9918279648,53.8463516235],"type":"Point"}
}