{
  "type": "Feature",
  "properties": {
    "addr:full":"44 The Brendons, Sampford Peverell Tiverton Devon EX16 7BG",
    "addr:housenumber":"44;peverell",
    "addr:postcode":"ex16 7bg",
    "addr:street":"The Brendons",
    "iso:country":"GB",
    "sg:address":"44 The Brendons, Sampford Peverell",
    "sg:city":"Tiverton",
    "sg:classifiers":[
        {
            "category":"Manufacturing",
            "subcategory":"Paper Products",
            "type":"Manufacturing & Wholesale Goods"
        }
    ],
    "sg:phone":"+44 1884 820675",
    "sg:postcode":"EX16 7BG",
    "sg:province":"Devon",
    "sg:tags":[
        "cardboard"
    ],
    "wof:name":"Andrew Newton",
    "wof:placetype":"venue"
},
  "geometry": {"coordinates":[-3.3800508976,50.9225196838],"type":"Point"}
}