{
  "type": "Feature",
  "properties": {
    "addr:full":"Distribution Only, 230-236 Lavender Hill London Greater London SW11 1LE",
    "addr:housenumber":"230-236",
    "addr:postcode":"sw11 1le",
    "addr:street":"Lavender Hill",
    "iso:country":"GB",
    "sg:address":"Distribution Only, 230-236 Lavender Hill",
    "sg:city":"London",
    "sg:classifiers":[
        {
            "category":"Professional",
            "subcategory":"Business Services",
            "type":"Services"
        }
    ],
    "sg:phone":"+44 20 7223 9971",
    "sg:postcode":"SW11 1LE",
    "sg:province":"Greater London",
    "sg:tags":[
        "distribution"
    ],
    "wof:name":"Private Eye Publications Ltd.",
    "wof:placetype":"venue"
},
  "geometry": {"coordinates":[-0.1655,51.464062],"type":"Point"}
}