{
  "type": "Feature",
  "properties": {
    "addr:full":"19a Stoke Old Road, Hartshill Stoke-on-trent Staffordshire ST4 6ES",
    "addr:housenumber":"19a",
    "addr:postcode":"staffordshire st4 6es",
    "addr:street":"Stoke Old Road",
    "iso:country":"GB",
    "sg:address":"19a Stoke Old Road, Hartshill",
    "sg:city":"Stoke-on-trent",
    "sg:classifiers":[
        {
            "category":"Personal",
            "subcategory":"Beauty Salon",
            "type":"Services"
        }
    ],
    "sg:phone":"+44 1782 629373",
    "sg:postcode":"ST4 6ES",
    "sg:province":"Staffordshire",
    "sg:tags":[
        "unisex",
        "hairdresser"
    ],
    "wof:name":"Carol Rose Hair & Beauty",
    "wof:placetype":"venue"
},
  "geometry": {"coordinates":[-2.211184,53.0117],"type":"Point"}
}