{
  "type": "Feature",
  "properties": {
    "addr:full":"324 Stafford Rd Croydon Surrey CR0 4NH",
    "addr:housenumber":"324",
    "addr:postcode":"cr0 4nh",
    "addr:street":"Stafford Rd",
    "iso:country":"GB",
    "sg:address":"324 Stafford Rd",
    "sg:city":"Croydon",
    "sg:classifiers":[
        {
            "category":"Professional",
            "subcategory":"Detective & Security Services",
            "type":"Services"
        }
    ],
    "sg:phone":"+44 20 8680 3363",
    "sg:postcode":"CR0 4NH",
    "sg:province":"Surrey",
    "sg:tags":[
        "agency"
    ],
    "wof:name":"Bishop Investigations",
    "wof:placetype":"venue"
},
  "geometry": {"coordinates":[-0.1215410009,51.3624153137],"type":"Point"}
}