{
  "type": "Feature",
  "properties": {
    "iso:country":"GB",
    "sg:address":"Ruxley Manor, Maidstone Road",
    "sg:city":"Sidcup",
    "sg:classifiers":[
        {
            "category":"Home & Garden",
            "subcategory":"Garden Supply",
            "type":"Retail Goods"
        }
    ],
    "sg:phone":"+44 20 8309 0600",
    "sg:postcode":"DA14 5BQ",
    "sg:province":"Kent",
    "sg:tags":[
        "pool",
        "swimming"
    ],
    "wof:name":"Ruxley Electronics & Construction Ltd.",
    "wof:placetype":"venue"
},
  "geometry": {"coordinates":[0.1388709992,51.4110794067],"type":"Point"}
}