{
  "type": "Feature",
  "properties": {
    "addr:full":"Unit 35-37, Sketchley Meadow Industrial Estate Hinckley Leicestershire LE10 3ES",
    "addr:housenumber":"unit 35-37",
    "addr:postcode":"le10 3es",
    "addr:street":"Sketchley Meadow Industrial Estate",
    "iso:country":"GB",
    "sg:address":"Unit 35-37, Sketchley Meadow Industrial Estate",
    "sg:city":"Hinckley",
    "sg:classifiers":[
        {
            "category":"Professional",
            "subcategory":"Engineering",
            "type":"Services"
        }
    ],
    "sg:phone":"+44 1455 616606",
    "sg:postcode":"LE10 3ES",
    "sg:province":"Leicestershire",
    "wof:name":"Transmission of Power Ltd.",
    "wof:placetype":"venue"
},
  "geometry": {"coordinates":[-1.380667,52.526371],"type":"Point"}
}