{
  "type": "Feature",
  "properties": {
    "iso:country":"GB",
    "sg:address":"10 Meadow Bank, Penwortham",
    "sg:city":"Preston",
    "sg:classifiers":[
        {
            "category":"Personal",
            "type":"Services"
        }
    ],
    "sg:phone":"+44 1772 463964",
    "sg:postcode":"PR1 9BL",
    "sg:province":"Lancashire",
    "sg:tags":[
        "stress",
        "management"
    ],
    "wof:name":"Caring Words Counselling & Physcotherapy",
    "wof:placetype":"venue"
},
  "geometry": {"coordinates":[-2.7265479565,53.7382392883],"type":"Point"}
}