{
  "type": "Feature",
  "properties": {
    "iso:country":"GB",
    "sg:address":"83 Bridle Road, Shirley",
    "sg:city":"Croydon",
    "sg:classifiers":[
        {
            "category":"Retail",
            "subcategory":"Repair Shop",
            "type":"Services"
        }
    ],
    "sg:phone":"+44 20 8777 0867",
    "sg:postcode":"CR0 8HQ",
    "sg:province":"Surrey",
    "sg:tags":[
        "radio",
        "television",
        "video"
    ],
    "wof:name":"Univision",
    "wof:placetype":"venue"
},
  "geometry": {"coordinates":[-0.0305920001,51.3728904724],"type":"Point"}
}