{
  "type": "Feature",
  "properties": {
    "addr:full":"Aldwickbury Park Golf Club, Piggottshill Lane Harpenden Hertfordshire AL5 1AB",
    "addr:postcode":"al5 1ab",
    "addr:street":"Piggottshill Lane",
    "iso:country":"GB",
    "sg:address":"Aldwickbury Park Golf Club, Piggottshill Lane",
    "sg:city":"Harpenden",
    "sg:classifiers":[
        {
            "category":"Restaurant",
            "type":"Food & Drink"
        }
    ],
    "sg:phone":"+44 1582 766463",
    "sg:postcode":"AL5 1AB",
    "sg:province":"Hertfordshire",
    "wof:name":"19th Catering Co",
    "wof:placetype":"venue"
},
  "geometry": {"coordinates":[-0.356559,51.816216],"type":"Point"}
}