{
  "type": "Feature",
  "properties": {
    "iso:country":"GB",
    "sg:address":"5-6 Forge Close, Eaton Socon",
    "sg:city":"St Neots",
    "sg:classifiers":[
        {
            "category":"Wholesale",
            "subcategory":"Photographic Equipment",
            "type":"Manufacturing & Wholesale Goods"
        }
    ],
    "sg:phone":"+44 1480 472233",
    "sg:postcode":"PE19 8TP",
    "sg:province":"Bedfordshire",
    "sg:tags":[
        "w'sale",
        "supply"
    ],
    "sg:website":"http://www.capix.com",
    "wof:name":"Capix Ltd",
    "wof:placetype":"venue"
},
  "geometry": {"coordinates":[-0.294752,52.212639],"type":"Point"}
}