{
  "type": "Feature",
  "properties": {
    "addr:full":"73 High Street Barry The Vale of Glamorgan CF62 7DW",
    "addr:housenumber":"73",
    "addr:postcode":"cf62 7dw",
    "addr:street":"High Street;Vale",
    "iso:country":"GB",
    "sg:address":"73 High Street",
    "sg:city":"Barry",
    "sg:classifiers":[
        {
            "category":"Shopping",
            "subcategory":"Shoes",
            "type":"Retail Goods"
        }
    ],
    "sg:phone":"+44 1446 743072",
    "sg:postcode":"CF62 7DW",
    "sg:province":"The Vale of Glamorgan",
    "sg:tags":[
        "shop",
        "retailer",
        "footwear"
    ],
    "wof:name":"PITMAN FOOTWEAR",
    "wof:placetype":"venue"
},
  "geometry": {"coordinates":[-3.2842879295,51.3993644714],"type":"Point"}
}