{
  "type": "Feature",
  "properties": {
    "addr:full":"Woodlands, Barrhill Rd Dalbeattie Dumfries and Galloway DG5 4JD",
    "addr:postcode":"dg5 4jd",
    "addr:street":"Barrhill Rd",
    "iso:country":"GB",
    "sg:address":"Woodlands, Barrhill Rd",
    "sg:city":"Dalbeattie",
    "sg:classifiers":[
        {
            "category":"Professional",
            "subcategory":"Management & Consulting",
            "type":"Services"
        }
    ],
    "sg:phone":"+44 1556 611122",
    "sg:postcode":"DG5 4JD",
    "sg:province":"Dumfries and Galloway",
    "sg:tags":[
        "consultant",
        "business"
    ],
    "wof:name":"W.d Millar",
    "wof:placetype":"venue"
},
  "geometry": {"coordinates":[-3.823039,54.933456],"type":"Point"}
}