{
  "type": "Feature",
  "properties": {
    "addr:full":"Unit 2 Drummers Corner Peterhead Aberdeenshire AB42 6ZP",
    "addr:housenumber":"unit 2",
    "addr:postcode":"ab42 6zp",
    "addr:street":"Drummers Corner",
    "iso:country":"GB",
    "sg:address":"Unit 2 Drummers Corner",
    "sg:city":"Peterhead",
    "sg:classifiers":[
        {
            "category":"Food & Beverages",
            "subcategory":"Bakery",
            "type":"Retail Goods"
        }
    ],
    "sg:phone":"+44 1779 478638",
    "sg:postcode":"AB42 6ZP",
    "sg:province":"Aberdeenshire",
    "sg:tags":[
        "baker"
    ],
    "wof:name":"D S C (Realisations) Ltd.",
    "wof:placetype":"venue"
},
  "geometry": {"coordinates":[-1.797219038,57.5065345764],"type":"Point"}
}