{
  "type": "Feature",
  "properties": {
    "addr:full":"Craigend Rd Troon South Ayrshire KA10 6HD",
    "addr:postcode":"ka10 6hd",
    "addr:street":"Craigend Rd",
    "iso:country":"GB",
    "sg:address":"Craigend Rd",
    "sg:city":"Troon",
    "sg:classifiers":[
        {
            "category":"Travel",
            "subcategory":"Hotels & Motels",
            "type":"Entertainment"
        }
    ],
    "sg:phone":"+44 1292 317185",
    "sg:postcode":"KA10 6HD",
    "sg:province":"South Ayrshire",
    "wof:name":"Aristo Hotel",
    "wof:placetype":"venue"
},
  "geometry": {"coordinates":[-4.6537041664,55.5463142395],"type":"Point"}
}