{
  "type": "Feature",
  "properties": {
    "iso:country":"GB",
    "sg:address":"40 Downside Close",
    "sg:city":"Blandford Forum",
    "sg:classifiers":[
        {
            "category":"Building & Trades",
            "subcategory":"Landscaping Services",
            "type":"Services"
        }
    ],
    "sg:phone":"+44 1258 454415",
    "sg:postcode":"DT11 7SD",
    "sg:province":"Dorset",
    "sg:tags":[
        "gardening"
    ],
    "wof:name":"Oasis Garden Services",
    "wof:placetype":"venue"
},
  "geometry": {"coordinates":[-2.150443,50.861309],"type":"Point"}
}