{
  "type": "Feature",
  "properties": {
    "iso:country":"GB",
    "sg:address":"Walton Street, Long Eaton",
    "sg:city":"Nottingham",
    "sg:classifiers":[
        {
            "category":"Professional",
            "subcategory":"Art Services",
            "type":"Services"
        }
    ],
    "sg:postcode":"NG10 1PE",
    "sg:province":"Derbyshire",
    "sg:tags":[
        "consultant",
        "design"
    ],
    "wof:name":"Arena Design Associates Ltd.",
    "wof:placetype":"venue"
},
  "geometry": {"coordinates":[-1.27433002,52.901676178],"type":"Point"}
}