{
  "type": "Feature",
  "properties": {
    "addr:full":"23 Stanhope Dr Harrogate North Yorkshire HG2 7RJ",
    "addr:housenumber":"23",
    "addr:postcode":"hg2 7rj",
    "addr:street":"Stanhope Dr",
    "iso:country":"GB",
    "sg:address":"23 Stanhope Dr",
    "sg:city":"Harrogate",
    "sg:classifiers":[
        {
            "category":"Professional",
            "subcategory":"Detective & Security Services",
            "type":"Services"
        }
    ],
    "sg:phone":"+44 1423 889619",
    "sg:postcode":"HG2 7RJ",
    "sg:province":"North Yorkshire",
    "sg:tags":[
        "locksmith"
    ],
    "wof:name":"Dyno Locks",
    "wof:placetype":"venue"
},
  "geometry": {"coordinates":[-1.509303,53.994759],"type":"Point"}
}