{
  "type": "Feature",
  "properties": {
    "iso:country":"GB",
    "sg:address":"226 Stamford Hill",
    "sg:city":"Stoke Newington",
    "sg:classifiers":[
        {
            "category":"Banks & Credit Unions",
            "subcategory":"Bank",
            "type":"Services"
        }
    ],
    "sg:phone":"+44 18180738",
    "sg:postcode":"N16 6TT",
    "sg:province":"Greater London",
    "wof:name":"Woolwich plc",
    "wof:placetype":"venue"
},
  "geometry": {"coordinates":[-0.0730660036,51.5635032654],"type":"Point"}
}