{
  "type": "Feature",
  "properties": {
    "iso:country":"GB",
    "sg:address":"23 Castlegate",
    "sg:city":"Berwick-upon-tweed",
    "sg:classifiers":[
        {
            "category":"Education",
            "subcategory":"Special Training",
            "type":"Public Place"
        }
    ],
    "sg:phone":"+44 1289 302529",
    "sg:postcode":"TD15 1LF",
    "sg:province":"Northumberland",
    "sg:tags":[
        "product",
        "centre"
    ],
    "wof:name":"Castlegate Ltd.",
    "wof:placetype":"venue"
},
  "geometry": {"coordinates":[-2.0080690384,55.7719993591],"type":"Point"}
}