{
  "type": "Feature",
  "properties": {
    "iso:country":"GB",
    "sg:address":"Sir Frank Whittle Business Cntr, Great Central Way",
    "sg:city":"Rugby",
    "sg:classifiers":[
        {
            "category":"Wholesale",
            "subcategory":"Electrical",
            "type":"Manufacturing & Wholesale Goods"
        }
    ],
    "sg:postcode":"CV21 3XH",
    "sg:province":"Warwickshire",
    "sg:tags":[
        "equipment",
        "refrigeration"
    ],
    "wof:name":"Flamex",
    "wof:placetype":"venue"
},
  "geometry": {"coordinates":[-1.242538,52.380077],"type":"Point"}
}