{
  "type": "Feature",
  "properties": {
    "iso:country":"GB",
    "sg:address":"Elham Valley Rd",
    "sg:city":"Canterbury",
    "sg:classifiers":[
        {
            "category":"Social Services",
            "subcategory":"Retirement Home",
            "type":"Services"
        }
    ],
    "sg:phone":"+44 1227 832230",
    "sg:postcode":"CT4 6LN",
    "sg:province":"Kent",
    "sg:tags":[
        "residential",
        "care"
    ],
    "wof:name":"Valley House",
    "wof:placetype":"venue"
},
  "geometry": {"coordinates":[1.10943,51.152634],"type":"Point"}
}