{
  "type": "Feature",
  "properties": {
    "iso:country":"GB",
    "sg:address":"4 Watson Gardens",
    "sg:city":"Romford",
    "sg:classifiers":[
        {
            "category":"Building & Trades",
            "subcategory":"Plumbing",
            "type":"Services"
        }
    ],
    "sg:phone":"+44 1708 345700",
    "sg:postcode":"RM3 0WZ",
    "sg:province":"Essex",
    "sg:tags":[
        "heating"
    ],
    "wof:name":"Btm Plumbing Heating & Water Treatment Engineers",
    "wof:placetype":"venue"
},
  "geometry": {"coordinates":[0.2217320055,51.5903625488],"type":"Point"}
}