{
  "type": "Feature",
  "properties": {
    "addr:full":"9 Borrowbydale Avenue Knaresborough North Yorkshire HG5 0NF",
    "addr:housenumber":"9",
    "addr:postcode":"hg5 0nf",
    "addr:street":"Borrowbydale Avenue",
    "iso:country":"GB",
    "sg:address":"9 Borrowbydale Avenue",
    "sg:city":"Knaresborough",
    "sg:classifiers":[
        {
            "category":"Home & Garden",
            "subcategory":"Household Appliances",
            "type":"Retail Goods"
        },
        {
            "category":"Retail",
            "subcategory":"Repair Shop",
            "type":"Services"
        }
    ],
    "sg:phone":"+44 1423 865954",
    "sg:postcode":"HG5 0NF",
    "sg:province":"North Yorkshire",
    "sg:tags":[
        "machine",
        "electrical",
        "washing"
    ],
    "wof:name":"F Stephen Limbert",
    "wof:placetype":"venue"
},
  "geometry": {"coordinates":[-1.449117,54.010448],"type":"Point"}
}