{
  "type": "Feature",
  "properties": {
    "addr:full":"Unit 7, Waterloo Industrial Estate, Waterloo Pembroke Dock Pembrokeshire SA72 4RT",
    "addr:housenumber":"unit 7 waterloo",
    "addr:postcode":"sa72 4rt",
    "addr:street":"Industrial Estate",
    "iso:country":"GB",
    "sg:address":"Unit 7, Waterloo Industrial Estate, Waterloo",
    "sg:city":"Pembroke Dock",
    "sg:classifiers":[
        {
            "category":"Military Area",
            "subcategory":"Air Force Base",
            "type":"Public Place"
        }
    ],
    "sg:phone":"+44 1646 621443",
    "sg:postcode":"SA72 4RT",
    "sg:province":"Pembrokeshire",
    "sg:tags":[
        "taxi",
        "hire",
        "private"
    ],
    "wof:name":"Ferry Cabs",
    "wof:placetype":"venue"
},
  "geometry": {"coordinates":[-4.92599,51.69471],"type":"Point"}
}