{
  "type": "Feature",
  "properties": {
    "iso:country":"GB",
    "sg:address":"2 St Martins Place",
    "sg:city":"London",
    "sg:classifiers":[
        {
            "category":"Museum",
            "subcategory":"Art Museum",
            "type":"Entertainment"
        }
    ],
    "sg:phone":"+44 20 7306 0055",
    "sg:postcode":"WC2H 0HE",
    "sg:province":"Greater London",
    "sg:tags":[
        "gallery"
    ],
    "wof:name":"National Portrait Gallery",
    "wof:placetype":"venue"
},
  "geometry": {"coordinates":[-0.1275220066,51.509311676],"type":"Point"}
}