{
  "type": "Feature",
  "properties": {
    "addr:full":"50-60 Shawbridge Street, Pollokshaws Glasgow Glasgow City G43 1RW",
    "addr:housenumber":"50-60",
    "addr:postcode":"g43 1rw",
    "addr:street":"Shawbridge Street",
    "iso:country":"GB",
    "sg:address":"50-60 Shawbridge Street, Pollokshaws",
    "sg:city":"Glasgow",
    "sg:classifiers":[
        {
            "category":"Education",
            "subcategory":"Library",
            "type":"Public Place"
        },
        {
            "category":"Government",
            "subcategory":"Office",
            "type":"Public Place"
        }
    ],
    "sg:phone":"+44 141 632 3544",
    "sg:postcode":"G43 1RW",
    "sg:province":"Glasgow City",
    "sg:tags":[
        "book",
        "local"
    ],
    "wof:name":"Pollokshaws Library",
    "wof:placetype":"venue"
},
  "geometry": {"coordinates":[-4.2951002121,55.8252334595],"type":"Point"}
}