{
  "type": "Feature",
  "properties": {
    "iso:country":"GB",
    "sg:address":"Coachgap Lane, Langar",
    "sg:city":"Nottingham",
    "sg:classifiers":[
        {
            "category":"Landmark",
            "subcategory":"Tourist Attraction",
            "type":"Public Place"
        }
    ],
    "sg:postcode":"NG13 9HP",
    "sg:province":"Leicestershire",
    "sg:tags":[
        "interest"
    ],
    "wof:name":"Naturescape Wild Flower Farm",
    "wof:placetype":"venue"
},
  "geometry": {"coordinates":[-0.917214,52.899624],"type":"Point"}
}