{
  "type": "Feature",
  "properties": {
    "iso:country":"GB",
    "sg:address":"1 Waterloo Road",
    "sg:city":"Epsom",
    "sg:classifiers":[
        {
            "category":"Food & Beverages",
            "subcategory":"Specialty",
            "type":"Retail Goods"
        }
    ],
    "sg:phone":"+44 1372 742095",
    "sg:postcode":"KT19 8AY",
    "sg:province":"Surrey",
    "sg:tags":[
        "retailer",
        "product",
        "health"
    ],
    "wof:name":"Good Life Health Foods",
    "wof:placetype":"venue"
},
  "geometry": {"coordinates":[-0.267357,51.333679],"type":"Point"}
}