{
  "type": "Feature",
  "properties": {
    "iso:country":"GB",
    "sg:address":"Castle Meadow Retail Park",
    "sg:city":"Nottingham",
    "sg:classifiers":[
        {
            "category":"Home & Garden",
            "subcategory":"Carpets & Floor Coverings",
            "type":"Retail Goods"
        }
    ],
    "sg:phone":"+44 115 924 1850",
    "sg:postcode":"NG7 1GX",
    "sg:province":"Nottinghamshire",
    "sg:tags":[
        "carpets",
        "rug",
        "matting"
    ],
    "wof:name":"Carpet Right",
    "wof:placetype":"venue"
},
  "geometry": {"coordinates":[-1.160122,52.945518],"type":"Point"}
}