{
  "type": "Feature",
  "properties": {
    "addr:full":"The Jays, Lowdells Lane East Grinstead East Sussex RH19 2AY",
    "addr:postcode":"rh19 2ay",
    "addr:street":"Lowdells Lane",
    "iso:country":"GB",
    "sg:address":"The Jays, Lowdells Lane",
    "sg:city":"East Grinstead",
    "sg:classifiers":[
        {
            "category":"Professional",
            "subcategory":"Engineering",
            "type":"Services"
        }
    ],
    "sg:postcode":"RH19 2AY",
    "sg:province":"East Sussex",
    "sg:tags":[
        "contractor",
        "electrical",
        "engineer"
    ],
    "wof:name":"McDonald Electrical",
    "wof:placetype":"venue"
},
  "geometry": {"coordinates":[-0.0298599992,51.1382675171],"type":"Point"}
}