{
  "type": "Feature",
  "properties": {
    "addr:full":"1-5 Queen Street Horsham West Sussex RH13 5AA",
    "addr:housenumber":"1-5",
    "addr:postcode":"rh13 5aa",
    "addr:street":"Queen Street",
    "iso:country":"GB",
    "sg:address":"1-5 Queen Street",
    "sg:city":"Horsham",
    "sg:classifiers":[
        {
            "category":"Transit Center",
            "subcategory":"Freight",
            "type":"Transportation"
        }
    ],
    "sg:phone":"+44 1403 254223",
    "sg:postcode":"RH13 5AA",
    "sg:province":"West Sussex",
    "sg:tags":[
        "piano",
        "accessory"
    ],
    "wof:name":"Horsham Piano Centre",
    "wof:placetype":"venue"
},
  "geometry": {"coordinates":[-0.3231129944,51.0606498718],"type":"Point"}
}