{
  "type": "Feature",
  "properties": {
    "addr:full":"230-232 Hale Lane Edgware Greater London HA8 9PZ",
    "addr:housenumber":"230-232",
    "addr:postcode":"ha8 9pz",
    "addr:street":"Hale Lane",
    "iso:country":"GB",
    "sg:address":"230-232 Hale Lane",
    "sg:city":"Edgware",
    "sg:classifiers":[
        {
            "category":"Organizations",
            "subcategory":"Non-profit Organization",
            "type":"Services"
        },
        {
            "category":"Organizations",
            "subcategory":"Religious Organization",
            "type":"Services"
        }
    ],
    "sg:phone":"+44 20 8905 4141",
    "sg:postcode":"HA8 9PZ",
    "sg:province":"Greater London",
    "sg:tags":[
        "charitable",
        "organisation",
        "place",
        "worship",
        "charity"
    ],
    "wof:name":"Lubavitch of Edgware",
    "wof:placetype":"venue"
},
  "geometry": {"coordinates":[-0.2691139877,51.6182861328],"type":"Point"}
}