{
  "type": "Feature",
  "properties": {
    "addr:full":"50 Vineyard Path London Greater London SW14 8ET",
    "addr:housenumber":"50",
    "addr:postcode":"sw14 8et",
    "addr:street":"Vineyard Path",
    "iso:country":"GB",
    "sg:address":"50 Vineyard Path",
    "sg:city":"London",
    "sg:classifiers":[
        {
            "category":"Utilities",
            "type":"Services"
        }
    ],
    "sg:postcode":"SW14 8ET",
    "sg:province":"Greater London",
    "sg:tags":[
        "internet"
    ],
    "wof:name":"Complinet",
    "wof:placetype":"venue"
},
  "geometry": {"coordinates":[-0.2659550011,51.4690666199],"type":"Point"}
}