{
  "type": "Feature",
  "properties": {
    "addr:full":"6 Reighton Drive, Rawcliffe York North Yorkshire YO30 5QH",
    "addr:housenumber":"6",
    "addr:postcode":"yo30 5qh",
    "addr:street":"Reighton Drive",
    "iso:country":"GB",
    "sg:address":"6 Reighton Drive, Rawcliffe",
    "sg:city":"York",
    "sg:classifiers":[
        {
            "category":"Recreation",
            "subcategory":"Dance Hall",
            "type":"Entertainment"
        }
    ],
    "sg:postcode":"YO30 5QH",
    "sg:province":"North Yorkshire",
    "sg:tags":[
        "disco"
    ],
    "wof:name":"Soundout Disco",
    "wof:placetype":"venue"
},
  "geometry": {"coordinates":[-1.1008290052,53.9792900085],"type":"Point"}
}