{
  "type": "Feature",
  "properties": {
    "iso:country":"GB",
    "sg:address":"153 Byres Road",
    "sg:city":"Glasgow",
    "sg:classifiers":[
        {
            "category":"Insurance",
            "subcategory":"Insurance Agent",
            "type":"Services"
        }
    ],
    "sg:phone":"+44 141 334 4006",
    "sg:postcode":"G12 8TS",
    "sg:province":"Glasgow City",
    "wof:name":"Endsleigh Insurance Services Ltd",
    "wof:placetype":"venue"
},
  "geometry": {"coordinates":[-4.295946,55.873657],"type":"Point"}
}