{
  "type": "Feature",
  "properties": {
    "addr:full":"84 Fulham Park Gardens London Greater London SW6 4LQ",
    "addr:housenumber":"84",
    "addr:postcode":"sw6 4lq",
    "addr:street":"Fulham Park Gardens",
    "iso:country":"GB",
    "sg:address":"84 Fulham Park Gardens",
    "sg:city":"London",
    "sg:classifiers":[
        {
            "category":"Shopping",
            "subcategory":"Clothing, Apparel, & Fashions",
            "type":"Retail Goods"
        },
        {
            "category":"Shopping",
            "subcategory":"Shoes",
            "type":"Retail Goods"
        }
    ],
    "sg:postcode":"SW6 4LQ",
    "sg:province":"Greater London",
    "sg:tags":[
        "clothing",
        "footwear"
    ],
    "wof:name":"Meredith Smith",
    "wof:placetype":"venue"
},
  "geometry": {"coordinates":[-0.207191,51.472771],"type":"Point"}
}