{
  "type": "Feature",
  "properties": {
    "addr:full":"31 North Road St Helens Merseyside WA10 2TN",
    "addr:housenumber":"31",
    "addr:postcode":"wa10 2tn",
    "addr:street":"North Road",
    "iso:country":"GB",
    "sg:address":"31 North Road",
    "sg:city":"St Helens",
    "sg:classifiers":[
        {
            "category":"Fast Food",
            "type":"Food & Drink"
        }
    ],
    "sg:postcode":"WA10 2TN",
    "sg:province":"Merseyside",
    "sg:tags":[
        "away",
        "take"
    ],
    "wof:name":"Sanam Balti Takeaway Ltd",
    "wof:placetype":"venue"
},
  "geometry": {"coordinates":[-2.739543,53.456551],"type":"Point"}
}