{
  "type": "Feature",
  "properties": {
    "addr:full":"Metropolitan Business Centre, Kingsland Road London Greater London N1 5AZ",
    "addr:postcode":"n1 5az",
    "addr:street":"Kingsland Road",
    "iso:country":"GB",
    "sg:address":"Metropolitan Business Centre, Kingsland Road",
    "sg:city":"London",
    "sg:classifiers":[
        {
            "category":"Professional",
            "subcategory":"Business Services",
            "type":"Services"
        }
    ],
    "sg:phone":"+44 20 7254 5526",
    "sg:postcode":"N1 5AZ",
    "sg:province":"Greater London",
    "sg:tags":[
        "import",
        "export",
        "agent"
    ],
    "wof:name":"Chat International Ltd.",
    "wof:placetype":"venue"
},
  "geometry": {"coordinates":[-0.0768899992,51.5395011902],"type":"Point"}
}