{
  "type": "Feature",
  "properties": {
    "iso:country":"GB",
    "sg:address":"Shire Lane, Chorley Wood",
    "sg:city":"Rickmansworth",
    "sg:classifiers":[
        {
            "category":"Retail",
            "subcategory":"Auto Repair",
            "type":"Services"
        }
    ],
    "sg:phone":"+44 1923 283753",
    "sg:postcode":"WD3 5NH",
    "sg:province":"Hertfordshire",
    "sg:tags":[
        "modification",
        "garage"
    ],
    "wof:name":"Churleswood Service Station",
    "wof:placetype":"venue"
},
  "geometry": {"coordinates":[-0.523043,51.653587],"type":"Point"}
}