{
  "type": "Feature",
  "properties": {
    "iso:country":"GB",
    "sg:address":"The Cot, St Arvans",
    "sg:city":"Chepstow",
    "sg:classifiers":[
        {
            "category":"Recreation",
            "subcategory":"Fishing",
            "type":"Entertainment"
        }
    ],
    "sg:postcode":"NP16 6HQ",
    "sg:province":"Gloucestershire",
    "sg:tags":[
        "angling"
    ],
    "wof:name":"Fairoak Fishery",
    "wof:placetype":"venue"
},
  "geometry": {"coordinates":[-2.698674,51.666161],"type":"Point"}
}