{
  "type": "Feature",
  "properties": {
    "iso:country":"GB",
    "sg:address":"18 Lochburn Road",
    "sg:city":"Glasgow",
    "sg:classifiers":[
        {
            "category":"Sports & Exercise",
            "subcategory":"Gym",
            "type":"Entertainment"
        }
    ],
    "sg:postcode":"G20 9AQ",
    "sg:province":"Glasgow City",
    "sg:tags":[
        "fitness",
        "health",
        "centre"
    ],
    "wof:name":"The Terraces Gym & Health Club",
    "wof:placetype":"venue"
},
  "geometry": {"coordinates":[-4.2897510529,55.8911552429],"type":"Point"}
}