{
  "type": "Feature",
  "properties": {
    "addr:full":"806 Carntyne Road Glasgow Glasgow City G32 6NQ",
    "addr:housenumber":"806",
    "addr:postcode":"g32 6nq",
    "addr:street":"Carntyne Road",
    "iso:country":"GB",
    "sg:address":"806 Carntyne Road",
    "sg:city":"Glasgow",
    "sg:classifiers":[
        {
            "category":"Food & Beverages",
            "subcategory":"Groceries & Convenience Stores",
            "type":"Retail Goods"
        }
    ],
    "sg:phone":"+44 141 778 3141",
    "sg:postcode":"G32 6NQ",
    "sg:province":"Glasgow City",
    "wof:name":"Carntyne Mini Market",
    "wof:placetype":"venue"
},
  "geometry": {"coordinates":[-4.1764950752,55.8617782593],"type":"Point"}
}