{
  "type": "Feature",
  "properties": {
    "iso:country":"GB",
    "sg:address":"Unit 19 White Road, Charsleets Industrial Estate",
    "sg:city":"Canvey Island",
    "sg:classifiers":[
        {
            "category":"Building & Trades",
            "subcategory":"Construction",
            "type":"Services"
        }
    ],
    "sg:phone":"+44 1268 690114",
    "sg:postcode":"SS8 0PQ",
    "sg:province":"Essex",
    "sg:tags":[
        "heating",
        "contractor"
    ],
    "wof:name":"Kent Heating Services Ltd.",
    "wof:placetype":"venue"
},
  "geometry": {"coordinates":[0.5911200047,51.5203742981],"type":"Point"}
}