{
  "type": "Feature",
  "properties": {
    "iso:country":"GB",
    "sg:address":"19 Market Place",
    "sg:city":"Thirsk",
    "sg:classifiers":[
        {
            "category":"Real Estate",
            "subcategory":"Real Estate Agent",
            "type":"Services"
        }
    ],
    "sg:phone":"+44 1845 522680",
    "sg:postcode":"YO7 1HD",
    "sg:province":"North Yorkshire",
    "wof:name":"Joplings",
    "wof:placetype":"venue"
},
  "geometry": {"coordinates":[-1.3430119753,54.2325553894],"type":"Point"}
}