{
  "type": "Feature",
  "properties": {
    "addr:full":"26 Sycamore Close Watford Hertfordshire WD25 0DF",
    "addr:housenumber":"26",
    "addr:postcode":"wd25 0df",
    "addr:street":"Sycamore Close",
    "iso:country":"GB",
    "sg:address":"26 Sycamore Close",
    "sg:city":"Watford",
    "sg:classifiers":[
        {
            "category":"Health Services",
            "subcategory":"Podiatrist",
            "type":"Services"
        }
    ],
    "sg:postcode":"WD25 0DF",
    "sg:province":"Hertfordshire",
    "sg:tags":[
        "podiatrists",
        "chiropodist"
    ],
    "wof:name":"Claire Catanach",
    "wof:placetype":"venue"
},
  "geometry": {"coordinates":[-0.399393,51.687031],"type":"Point"}
}