{
  "type": "Feature",
  "properties": {
    "iso:country":"GB",
    "sg:address":"73 Peascod Street",
    "sg:city":"Windsor",
    "sg:classifiers":[
        {
            "category":"Bars & Pubs",
            "subcategory":"Wine Bar",
            "type":"Food & Drink"
        }
    ],
    "sg:phone":"+44 1753 862867",
    "sg:postcode":"SL4 1DH",
    "sg:province":"Berkshire",
    "wof:name":"Crosses Corner",
    "wof:placetype":"venue"
},
  "geometry": {"coordinates":[-0.611659,51.480869],"type":"Point"}
}