{
  "type": "Feature",
  "properties": {
    "iso:country":"GB",
    "sg:address":"57 Windmill Street",
    "sg:city":"Gravesend",
    "sg:classifiers":[
        {
            "category":"Real Estate",
            "subcategory":"Surveying",
            "type":"Services"
        }
    ],
    "sg:phone":"+44 1474 357181",
    "sg:postcode":"DA12 1BB",
    "sg:province":"Kent",
    "sg:tags":[
        "surveyor",
        "marine"
    ],
    "wof:name":"Perfect Lambert & Co.",
    "wof:placetype":"venue"
},
  "geometry": {"coordinates":[0.369156,51.438789],"type":"Point"}
}