{
  "type": "Feature",
  "properties": {
    "iso:country":"GB",
    "sg:address":"12 Frederick St",
    "sg:city":"Birmingham",
    "sg:classifiers":[
        {
            "category":"Banks & Credit Unions",
            "subcategory":"Bank",
            "type":"Services"
        }
    ],
    "sg:phone":"+44 121 212 3123",
    "sg:postcode":"B1 3HE",
    "sg:province":"West Midlands",
    "sg:tags":[
        "broker",
        "mortgage"
    ],
    "wof:name":"The Mortgage World",
    "wof:placetype":"venue"
},
  "geometry": {"coordinates":[-1.91135,52.484745],"type":"Point"}
}