{
  "type": "Feature",
  "properties": {
    "addr:full":"Pascall House Crawley Surrey RH10 9RS",
    "addr:postcode":"rh10 9rs",
    "iso:country":"GB",
    "sg:address":"Pascall House",
    "sg:city":"Crawley",
    "sg:classifiers":[
        {
            "category":"Professional",
            "subcategory":"Printing & Photocopies",
            "type":"Services"
        }
    ],
    "sg:phone":"+44 1293 539309",
    "sg:postcode":"RH10 9RS",
    "sg:province":"Surrey",
    "sg:tags":[
        "plate",
        "lithographic",
        "maker"
    ],
    "wof:name":"Minuteman Press",
    "wof:placetype":"venue"
},
  "geometry": {"coordinates":[-0.184753,51.118458],"type":"Point"}
}