{
  "type": "Feature",
  "properties": {
    "addr:full":"Rother Way, Euroway Trading Estate Rotherham South Yorkshire S66 8QN",
    "addr:postcode":"s66 8qn",
    "addr:street":"Rother Way;South",
    "iso:country":"GB",
    "sg:address":"Rother Way, Euroway Trading Estate",
    "sg:city":"Rotherham",
    "sg:classifiers":[
        {
            "category":"Personal",
            "type":"Services"
        }
    ],
    "sg:phone":"+44 1709 702702",
    "sg:postcode":"S66 8QN",
    "sg:province":"South Yorkshire",
    "sg:tags":[
        "delivery"
    ],
    "wof:name":"T N T Transport Ltd.",
    "wof:placetype":"venue"
},
  "geometry": {"coordinates":[-1.2445579767,53.4283332825],"type":"Point"}
}