{
  "type": "Feature",
  "properties": {
    "addr:full":"22 Douglas Street Barrow-in-furness Cumbria LA14 3QQ",
    "addr:housenumber":"22",
    "addr:postcode":"la14 3qq",
    "addr:street":"Douglas Street",
    "iso:country":"GB",
    "sg:address":"22 Douglas Street",
    "sg:city":"Barrow-in-furness",
    "sg:classifiers":[
        {
            "category":"Shopping",
            "subcategory":"News",
            "type":"Retail Goods"
        }
    ],
    "sg:postcode":"LA14 3QQ",
    "sg:province":"Cumbria",
    "sg:tags":[
        "newsagent"
    ],
    "wof:name":"A & C V Roach",
    "wof:placetype":"venue"
},
  "geometry": {"coordinates":[-3.249448,54.111282],"type":"Point"}
}