{
  "type": "Feature",
  "properties": {
    "iso:country":"GB",
    "sg:address":"Erme Court, Leonards Road",
    "sg:city":"Ivybridge",
    "sg:classifiers":[
        {
            "category":"Shopping",
            "subcategory":"Clothing, Apparel, & Fashions",
            "type":"Retail Goods"
        }
    ],
    "sg:phone":"+44 1752 894104",
    "sg:postcode":"PL21 0SZ",
    "sg:province":"Devon",
    "sg:tags":[
        "shop"
    ],
    "wof:name":"Peacocks Stores",
    "wof:placetype":"venue"
},
  "geometry": {"coordinates":[-3.918658,50.389408],"type":"Point"}
}