{
  "type": "Feature",
  "properties": {
    "addr:full":"989 Christchurch Road Bournemouth Dorset BH7 6BB",
    "addr:housenumber":"989",
    "addr:postcode":"bh7 6bb",
    "addr:street":"Christchurch Road",
    "iso:country":"GB",
    "sg:address":"989 Christchurch Road",
    "sg:city":"Bournemouth",
    "sg:classifiers":[
        {
            "category":"Food & Beverages",
            "subcategory":"Meat & Fish",
            "type":"Retail Goods"
        }
    ],
    "sg:phone":"+44 1202 424821",
    "sg:postcode":"BH7 6BB",
    "sg:province":"Dorset",
    "sg:tags":[
        "chip"
    ],
    "wof:name":"The Chip Box",
    "wof:placetype":"venue"
},
  "geometry": {"coordinates":[-1.821007967,50.7322158813],"type":"Point"}
}