{
  "type": "Feature",
  "properties": {
    "addr:full":"King St Garage, Kings Street Honiton Devon EX14 1AG",
    "addr:postcode":"ex14 1ag",
    "addr:street":"King;Kings Street",
    "iso:country":"GB",
    "sg:address":"King St Garage, Kings Street",
    "sg:city":"Honiton",
    "sg:classifiers":[
        {
            "category":"Autos & Motor Vehicles",
            "subcategory":"Auto Supplies",
            "type":"Retail Goods"
        }
    ],
    "sg:phone":"+44 1404 43204",
    "sg:postcode":"EX14 1AG",
    "sg:province":"Devon",
    "sg:tags":[
        "tyre"
    ],
    "wof:name":"Motorway Tyres & Accessories Ltd",
    "wof:placetype":"venue"
},
  "geometry": {"coordinates":[-3.19118,50.797993],"type":"Point"}
}