{
  "type": "Feature",
  "properties": {
    "iso:country":"GB",
    "sg:address":"Cressage House, Cressage",
    "sg:city":"Shrewsbury",
    "sg:classifiers":[
        {
            "category":"Farming",
            "subcategory":"Livestock Farm",
            "type":"Manufacturing & Wholesale Goods"
        }
    ],
    "sg:phone":"+44 1952 510206",
    "sg:postcode":"SY5 6EA",
    "sg:province":"Shropshire",
    "sg:tags":[
        "others"
    ],
    "wof:name":"J & A R Preece",
    "wof:placetype":"venue"
},
  "geometry": {"coordinates":[-2.604337,52.63147],"type":"Point"}
}