{
  "type": "Feature",
  "properties": {
    "iso:country":"GB",
    "sg:address":"41 South View, Woodley",
    "sg:city":"Stockport",
    "sg:classifiers":[
        {
            "category":"Shopping",
            "subcategory":"Computers & Home Electronics",
            "type":"Retail Goods"
        }
    ],
    "sg:phone":"+44 161 430 5245",
    "sg:postcode":"SK6 1PD",
    "sg:province":"Cheshire",
    "sg:tags":[
        "aerial",
        "television",
        "radio"
    ],
    "wof:name":"J N Cox Elect",
    "wof:placetype":"venue"
},
  "geometry": {"coordinates":[-2.0884439945,53.4310417175],"type":"Point"}
}