{
  "type": "Feature",
  "properties": {
    "iso:country":"GB",
    "sg:address":"385a Reading Road, Winnersh",
    "sg:city":"Wokingham",
    "sg:classifiers":[
        {
            "category":"Shopping",
            "subcategory":"Bicycles & Sporting Goods",
            "type":"Retail Goods"
        }
    ],
    "sg:phone":"+44 118 979 0797",
    "sg:postcode":"RG41 5LT",
    "sg:province":"Berkshire",
    "sg:tags":[
        "cycle",
        "accessory"
    ],
    "wof:name":"Berkshire Cycle Co",
    "wof:placetype":"venue"
},
  "geometry": {"coordinates":[-0.8762059808,51.4283638],"type":"Point"}
}