{
  "type": "Feature",
  "properties": {
    "addr:full":"23 Worsley Rd North, Walkden Manchester Greater Manchester M28 3GB",
    "addr:housenumber":"23",
    "addr:postcode":"m28 3gb",
    "addr:street":"Worsley Rd",
    "iso:country":"GB",
    "sg:address":"23 Worsley Rd North, Walkden",
    "sg:city":"Manchester",
    "sg:classifiers":[
        {
            "category":"Home & Garden",
            "subcategory":"Building Materials",
            "type":"Retail Goods"
        }
    ],
    "sg:phone":"+44 161 702 8858",
    "sg:postcode":"M28 3GB",
    "sg:province":"Greater Manchester",
    "sg:tags":[
        "equipment",
        "disability"
    ],
    "wof:name":"M.T.C Services",
    "wof:placetype":"venue"
},
  "geometry": {"coordinates":[-2.375661,53.499416],"type":"Point"}
}