{
  "type": "Feature",
  "properties": {
    "iso:country":"GB",
    "sg:address":"Unit 11a Nortonthorp Mill, Wakefiled Road, Scissett",
    "sg:city":"Huddersfield",
    "sg:classifiers":[
        {
            "category":"Shopping",
            "subcategory":"Department Store",
            "type":"Retail Goods"
        },
        {
            "category":"Transit Center",
            "subcategory":"Freight",
            "type":"Transportation"
        }
    ],
    "sg:postcode":"HD8 9LA",
    "sg:province":"South Yorkshire",
    "sg:tags":[
        "shop",
        "craft",
        "centre"
    ],
    "wof:name":"Meadow Sweet Decoupage Centre",
    "wof:placetype":"venue"
},
  "geometry": {"coordinates":[-1.628254,53.587299],"type":"Point"}
}