{
  "type": "Feature",
  "properties": {
    "iso:country":"GB",
    "sg:address":"35 High Street, Sandridge",
    "sg:city":"St Albans",
    "sg:classifiers":[
        {
            "category":"Professional",
            "subcategory":"Computer Services",
            "type":"Services"
        }
    ],
    "sg:phone":"+44 1727 869914",
    "sg:postcode":"AL4 9DD",
    "sg:province":"Hertfordshire",
    "sg:tags":[
        "system",
        "software"
    ],
    "wof:name":"Creative Consultancy Co",
    "wof:placetype":"venue"
},
  "geometry": {"coordinates":[-0.3064779937,51.7800292969],"type":"Point"}
}