{
  "type": "Feature",
  "properties": {
    "iso:country":"GB",
    "sg:address":"9 Ironbridge House, Windmill Place, 2-4 Windmill Lane",
    "sg:city":"Southall",
    "sg:classifiers":[
        {
            "category":"Wholesale",
            "subcategory":"Medical Equipment & Supplies",
            "type":"Manufacturing & Wholesale Goods"
        }
    ],
    "sg:phone":"+44 20 8606 9955",
    "sg:postcode":"UB2 4NJ",
    "sg:province":"Greater London",
    "wof:name":"American Medical Systems U.K",
    "wof:placetype":"venue"
},
  "geometry": {"coordinates":[-0.35315,51.50198],"type":"Point"}
}