{
  "type": "Feature",
  "properties": {
    "addr:full":"Park Avenue, Upper Edmonton London Greater London N18 2UH",
    "addr:postcode":"n18 2uh",
    "addr:street":"Park Avenue",
    "iso:country":"GB",
    "sg:address":"Park Avenue, Upper Edmonton",
    "sg:city":"London",
    "sg:classifiers":[
        {
            "category":"Home & Garden",
            "subcategory":"Building Materials",
            "type":"Retail Goods"
        }
    ],
    "sg:phone":"+44 20 8803 4824",
    "sg:postcode":"N18 2UH",
    "sg:province":"Greater London",
    "sg:tags":[
        "furnishers",
        "bathroom",
        "planner"
    ],
    "wof:name":"Godfreys of Enfield (Holdings) Ltd.",
    "wof:placetype":"venue"
},
  "geometry": {"coordinates":[-0.0659,51.61713],"type":"Point"}
}