{
  "type": "Feature",
  "properties": {
    "iso:country":"GB",
    "sg:address":"61 Leighton Road",
    "sg:city":"London",
    "sg:classifiers":[
        {
            "category":"Bars & Pubs",
            "type":"Food & Drink"
        }
    ],
    "sg:postcode":"NW5 2QH",
    "sg:province":"Greater London",
    "sg:tags":[
        "pubs",
        "inn"
    ],
    "wof:name":"The Gloucester Arms",
    "wof:placetype":"venue"
},
  "geometry": {"coordinates":[-0.139339,51.555565],"type":"Point"}
}