{
  "type": "Feature",
  "properties": {
    "iso:country":"GB",
    "sg:address":"1 Oak Tree Lane, Selly Oak",
    "sg:city":"Birmingham",
    "sg:classifiers":[
        {
            "category":"Food & Beverages",
            "subcategory":"Meat & Fish",
            "type":"Retail Goods"
        }
    ],
    "sg:phone":"+44 121 472 0598",
    "sg:postcode":"B29 6JE",
    "sg:province":"West Midlands",
    "sg:tags":[
        "butcher"
    ],
    "wof:name":"S R Checketts Retail Butchers Ltd.",
    "wof:placetype":"venue"
},
  "geometry": {"coordinates":[-1.939657,52.439468],"type":"Point"}
}