{
  "type": "Feature",
  "properties": {
    "addr:full":"Unit 1 Lady Lane, Longford Coventry Warwickshire CV6 6AZ",
    "addr:housenumber":"unit 1",
    "addr:postcode":"cv6 6az",
    "addr:street":"Lady Lane",
    "iso:country":"GB",
    "sg:address":"Unit 1 Lady Lane, Longford",
    "sg:city":"Coventry",
    "sg:classifiers":[
        {
            "category":"Wholesale",
            "subcategory":"Scrap",
            "type":"Manufacturing & Wholesale Goods"
        }
    ],
    "sg:phone":"+44 24 7649 4040",
    "sg:postcode":"CV6 6AZ",
    "sg:province":"Warwickshire",
    "sg:tags":[
        "breaker",
        "dismantlers"
    ],
    "wof:name":"Auto Busters",
    "wof:placetype":"venue"
},
  "geometry": {"coordinates":[-1.487419,52.451279],"type":"Point"}
}