{
  "type": "Feature",
  "properties": {
    "addr:full":"Buarth-y-foel Amlwch Isle of Anglesey LL68 9ET",
    "addr:postcode":"ll68 9et",
    "addr:street":"Amlwch",
    "iso:country":"GB",
    "sg:address":"Buarth-y-foel",
    "sg:city":"Amlwch",
    "sg:classifiers":[
        {
            "category":"Professional",
            "subcategory":"Business Services",
            "type":"Services"
        },
        {
            "category":"Utilities",
            "subcategory":"Natural Gas",
            "type":"Services"
        }
    ],
    "sg:phone":"+44 1407 830320",
    "sg:postcode":"LL68 9ET",
    "sg:province":"Isle of Anglesey",
    "sg:tags":[
        "supplier",
        "import",
        "export",
        "agent"
    ],
    "wof:name":"John Roberts & Son",
    "wof:placetype":"venue"
},
  "geometry": {"coordinates":[-4.346377,53.409103],"type":"Point"}
}