{
  "type": "Feature",
  "properties": {
    "addr:full":"104 Watling Street Towcester Buckinghamshire NN12 6BT",
    "addr:housenumber":"104",
    "addr:postcode":"nn12 6bt",
    "addr:street":"Watling Street",
    "iso:country":"GB",
    "sg:address":"104 Watling Street",
    "sg:city":"Towcester",
    "sg:classifiers":[
        {
            "category":"Bars & Pubs",
            "type":"Food & Drink"
        }
    ],
    "sg:phone":"+44 1327 358255",
    "sg:postcode":"NN12 6BT",
    "sg:province":"Buckinghamshire",
    "sg:tags":[
        "pubs",
        "inn"
    ],
    "wof:name":"Brave Old Oak Hotel",
    "wof:placetype":"venue"
},
  "geometry": {"coordinates":[-0.987009,52.130508],"type":"Point"}
}