{
  "type": "Feature",
  "properties": {
    "iso:country":"GB",
    "sg:address":"44 Morris St",
    "sg:city":"Whitechapel",
    "sg:classifiers":[
        {
            "category":"Bars & Pubs",
            "type":"Food & Drink"
        }
    ],
    "sg:phone":"+44 20 7790 2664",
    "sg:postcode":"E1 2NP",
    "sg:province":"Greater London",
    "sg:tags":[
        "pubs",
        "inn"
    ],
    "wof:name":"Britannia The",
    "wof:placetype":"venue"
},
  "geometry": {"coordinates":[-0.0572290011,51.5125999451],"type":"Point"}
}