{
  "type": "Feature",
  "properties": {
    "iso:country":"GB",
    "sg:address":"8 Brill Close",
    "sg:city":"Marlow",
    "sg:classifiers":[
        {
            "category":"Professional",
            "subcategory":"Employment Agencies",
            "type":"Services"
        }
    ],
    "sg:postcode":"SL7 2RH",
    "sg:province":"Berkshire",
    "sg:tags":[
        "career",
        "guidance"
    ],
    "wof:name":"Amson Associates",
    "wof:placetype":"venue"
},
  "geometry": {"coordinates":[-0.787936,51.57262],"type":"Point"}
}