{
  "type": "Feature",
  "properties": {
    "addr:full":"Unit 7, Taylors Court, Todd Hall Road Rossendale Lancashire BB4 5LA",
    "addr:housenumber":"unit 7",
    "addr:postcode":"bb4 5la",
    "addr:street":"Taylors Court;Hall Road",
    "iso:country":"GB",
    "sg:address":"Unit 7, Taylors Court, Todd Hall Road",
    "sg:city":"Rossendale",
    "sg:classifiers":[
        {
            "category":"Home & Garden",
            "subcategory":"Household Appliances",
            "type":"Retail Goods"
        }
    ],
    "sg:phone":"+44 1706 228850",
    "sg:postcode":"BB4 5LA",
    "sg:province":"Lancashire",
    "sg:tags":[
        "equipment",
        "refrigeration",
        "air conditioning"
    ],
    "wof:name":"E T L Air Conditioning",
    "wof:placetype":"venue"
},
  "geometry": {"coordinates":[-2.33414,53.706871],"type":"Point"}
}