{
  "type": "Feature",
  "properties": {
    "iso:country":"GB",
    "sg:address":"746a Melton Road, Thurmaston",
    "sg:city":"Leicester",
    "sg:classifiers":[
        {
            "category":"Retail",
            "subcategory":"Auto Repair",
            "type":"Services"
        }
    ],
    "sg:phone":"+44 116 269 4725",
    "sg:postcode":"LE4 8BD",
    "sg:province":"Leicestershire",
    "sg:tags":[
        "body",
        "car"
    ],
    "wof:name":"Thurmaston Bodyworks",
    "wof:placetype":"venue"
},
  "geometry": {"coordinates":[-1.0994499922,52.678855896],"type":"Point"}
}