{
  "type": "Feature",
  "properties": {
    "iso:country":"GB",
    "sg:address":"The Inch",
    "sg:city":"Brechin",
    "sg:classifiers":[
        {
            "category":"Community Center",
            "type":"Public Place"
        },
        {
            "category":"Government",
            "subcategory":"Office",
            "type":"Public Place"
        }
    ],
    "sg:phone":"+44 1356 623088",
    "sg:postcode":"DD9 6RP",
    "sg:province":"Aberdeenshire",
    "sg:tags":[
        "recreation",
        "local",
        "leisure",
        "centre"
    ],
    "wof:name":"Brechin Leisure Centre",
    "wof:placetype":"venue"
},
  "geometry": {"coordinates":[-2.6815040112,56.7536048889],"type":"Point"}
}