{
  "type": "Feature",
  "properties": {
    "addr:full":"19 Crompton Road, Aylsham Norwich Norfolk NR11 6JS",
    "addr:housenumber":"19",
    "addr:postcode":"nr11 6js",
    "addr:street":"Crompton Road;Norwich",
    "iso:country":"GB",
    "sg:address":"19 Crompton Road, Aylsham",
    "sg:city":"Norwich",
    "sg:classifiers":[
        {
            "category":"Shopping",
            "subcategory":"Department Store",
            "type":"Retail Goods"
        }
    ],
    "sg:postcode":"NR11 6JS",
    "sg:province":"Norfolk",
    "wof:name":"The Corner Shop",
    "wof:placetype":"venue"
},
  "geometry": {"coordinates":[1.253141,52.785862],"type":"Point"}
}