{
  "type": "Feature",
  "properties": {
    "iso:country":"GB",
    "sg:address":"18 High St",
    "sg:city":"Ringwood",
    "sg:classifiers":[
        {
            "category":"Real Estate",
            "subcategory":"Real Estate Agent",
            "type":"Services"
        }
    ],
    "sg:phone":"+44 1425 479001",
    "sg:postcode":"BH24 1AF",
    "sg:province":"Dorset",
    "wof:name":"Palmer Snell",
    "wof:placetype":"venue"
},
  "geometry": {"coordinates":[-1.7918980122,50.8462028503],"type":"Point"}
}