{
  "type": "Feature",
  "properties": {
    "addr:full":"Kentsboro, Middle Wallop Stockbridge Hampshire SO20 8DZ",
    "addr:postcode":"so20 8dz",
    "addr:street":"Middle Wallop",
    "iso:country":"GB",
    "sg:address":"Kentsboro, Middle Wallop",
    "sg:city":"Stockbridge",
    "sg:classifiers":[
        {
            "category":"Bus Charters",
            "type":"Transportation"
        }
    ],
    "sg:phone":"+44 1264 781283",
    "sg:postcode":"SO20 8DZ",
    "sg:province":"Hampshire",
    "sg:tags":[
        "hire",
        "coach"
    ],
    "wof:name":"Clegg & Brooking Ltd.",
    "wof:placetype":"venue"
},
  "geometry": {"coordinates":[-1.5616799593,51.1586112976],"type":"Point"}
}