{
  "type": "Feature",
  "properties": {
    "iso:country":"GB",
    "sg:address":"159b Balby Road",
    "sg:city":"Doncaster",
    "sg:classifiers":[
        {
            "category":"Professional",
            "subcategory":"Art Services",
            "type":"Services"
        }
    ],
    "sg:phone":"+44 1302 343000",
    "sg:postcode":"DN4 0RG",
    "sg:province":"South Yorkshire",
    "sg:tags":[
        "graphic",
        "designer"
    ],
    "wof:name":"Cadmus (U K) Ltd.",
    "wof:placetype":"venue"
},
  "geometry": {"coordinates":[-1.147066,53.508633],"type":"Point"}
}