{
  "type": "Feature",
  "properties": {
    "addr:full":"451-473 Cannock Road Wolverhampton Staffordshire WV10 0RA",
    "addr:postcode":"451-473;wv10 0ra",
    "addr:street":"Cannock Road",
    "iso:country":"GB",
    "sg:address":"451-473 Cannock Road",
    "sg:city":"Wolverhampton",
    "sg:classifiers":[
        {
            "category":"Autos & Motor Vehicles",
            "subcategory":"Fuel & Gas Station",
            "type":"Retail Goods"
        }
    ],
    "sg:phone":"+44 1902 731428",
    "sg:postcode":"WV10 0RA",
    "sg:province":"Staffordshire",
    "sg:tags":[
        "hr",
        "filling",
        "petrol"
    ],
    "wof:name":"Oakstead",
    "wof:placetype":"venue"
},
  "geometry": {"coordinates":[-2.111969,52.597469],"type":"Point"}
}