{
  "type": "Feature",
  "properties": {
    "addr:full":"99 Gloucester Road Cheltenham Gloucestershire GL51 8NG",
    "addr:housenumber":"99",
    "addr:postcode":"gl51 8ng",
    "addr:street":"Gloucester Road",
    "iso:country":"GB",
    "sg:address":"99 Gloucester Road",
    "sg:city":"Cheltenham",
    "sg:classifiers":[
        {
            "category":"Retail",
            "subcategory":"Repair Shop",
            "type":"Services"
        },
        {
            "category":"Home & Garden",
            "subcategory":"Furniture",
            "type":"Retail Goods"
        }
    ],
    "sg:phone":"+44 1242 234361",
    "sg:postcode":"GL51 8NG",
    "sg:province":"Gloucestershire",
    "sg:tags":[
        "outlet",
        "upholsterer"
    ],
    "wof:name":"S Rouse & Co",
    "wof:placetype":"venue"
},
  "geometry": {"coordinates":[-2.092508,51.9016],"type":"Point"}
}