{
  "type": "Feature",
  "properties": {
    "iso:country":"GB",
    "sg:address":"The Law Library, 8 Temple Street",
    "sg:city":"Birmingham",
    "sg:classifiers":[
        {
            "category":"Professional",
            "subcategory":"Lawyer & Legal Services",
            "type":"Services"
        }
    ],
    "sg:postcode":"B2 5BT",
    "sg:province":"West Midlands",
    "sg:tags":[
        "solicitor"
    ],
    "wof:name":"Birmingham Trainee Solicitors' Society Ltd.",
    "wof:placetype":"venue"
},
  "geometry": {"coordinates":[-1.89941,52.48019],"type":"Point"}
}