{
  "type": "Feature",
  "properties": {
    "addr:full":"Rowlandson House, 289/293 Ballards Lane London Greater London N12 8NP",
    "addr:housenumber":"289 / 293",
    "addr:postcode":"n12 8np",
    "addr:street":"Ballards Lane",
    "iso:country":"GB",
    "sg:address":"Rowlandson House, 289/293 Ballards Lane",
    "sg:city":"London",
    "sg:classifiers":[
        {
            "category":"Autos & Motor Vehicles",
            "subcategory":"Fuel & Gas Station",
            "type":"Retail Goods"
        }
    ],
    "sg:postcode":"N12 8NP",
    "sg:province":"Greater London",
    "sg:tags":[
        "petrol",
        "filling"
    ],
    "wof:name":"The Garage Centre Ltd",
    "wof:placetype":"venue"
},
  "geometry": {"coordinates":[-0.1767240018,51.6149787903],"type":"Point"}
}