{
  "type": "Feature",
  "properties": {
    "addr:full":"11-12 Quarry Street Guildford Surrey GU1 3UY",
    "addr:housenumber":"11-12",
    "addr:postcode":"gu1 3uy",
    "addr:street":"Quarry Street",
    "iso:country":"GB",
    "sg:address":"11-12 Quarry Street",
    "sg:city":"Guildford",
    "sg:classifiers":[
        {
            "category":"Education",
            "subcategory":"Special Training",
            "type":"Public Place"
        },
        {
            "category":"Wholesale",
            "subcategory":"Chemicals & Plastics",
            "type":"Manufacturing & Wholesale Goods"
        }
    ],
    "sg:phone":"+44 1483 454888",
    "sg:postcode":"GU1 3UY",
    "sg:province":"Surrey",
    "sg:tags":[
        "product",
        "allied",
        "centre"
    ],
    "wof:name":"C J Petrow International Ltd.",
    "wof:placetype":"venue"
},
  "geometry": {"coordinates":[-0.5737820268,51.2336120605],"type":"Point"}
}