{
  "type": "Feature",
  "properties": {
    "iso:country":"GB",
    "sg:address":"Fairfield Mains",
    "sg:city":"Arbroath",
    "sg:classifiers":[
        {
            "category":"Real Estate",
            "subcategory":"Architect",
            "type":"Services"
        }
    ],
    "sg:postcode":"DD11 3RX",
    "sg:province":"Angus",
    "wof:name":"Susan Burness Architects",
    "wof:placetype":"venue"
},
  "geometry": {"coordinates":[-2.5908410549,56.5629081726],"type":"Point"}
}