{
  "type": "Feature",
  "properties": {
    "addr:full":"Lawrence Hill Business Park Wincanton Somerset BA9 9RT",
    "addr:postcode":"ba9 9rt",
    "addr:street":"Lawrence Hill Business Park",
    "iso:country":"GB",
    "sg:address":"Lawrence Hill Business Park",
    "sg:city":"Wincanton",
    "sg:classifiers":[
        {
            "category":"Shopping",
            "subcategory":"Department Store",
            "type":"Retail Goods"
        },
        {
            "category":"Home & Garden",
            "subcategory":"Carpets & Floor Coverings",
            "type":"Retail Goods"
        }
    ],
    "sg:phone":"+44 1963 33574",
    "sg:postcode":"BA9 9RT",
    "sg:province":"Somerset",
    "sg:tags":[
        "retailer",
        "rug"
    ],
    "wof:name":"S CULLINGFORD CARPETS",
    "wof:placetype":"venue"
},
  "geometry": {"coordinates":[-2.413179,51.0578],"type":"Point"}
}