{
  "type": "Feature",
  "properties": {
    "iso:country":"GB",
    "sg:address":"6a Jackson Street",
    "sg:city":"Coalville",
    "sg:classifiers":[
        {
            "category":"Shopping",
            "subcategory":"Pets & Pet Supplies",
            "type":"Retail Goods"
        }
    ],
    "sg:phone":"+44 1530 831183",
    "sg:postcode":"LE67 3LT",
    "sg:province":"Leicestershire",
    "wof:name":"Pets World",
    "wof:placetype":"venue"
},
  "geometry": {"coordinates":[-1.374554,52.724178],"type":"Point"}
}