{
  "type": "Feature",
  "properties": {
    "addr:full":"163 Whitecross Abingdon Oxfordshire OX13 6BP",
    "addr:housenumber":"163",
    "addr:postcode":"ox13 6bp",
    "iso:country":"GB",
    "sg:address":"163 Whitecross",
    "sg:city":"Abingdon",
    "sg:classifiers":[
        {
            "category":"Building & Trades",
            "subcategory":"Landscaping Services",
            "type":"Services"
        }
    ],
    "sg:phone":"+44 1235 522583",
    "sg:postcode":"OX13 6BP",
    "sg:province":"Oxfordshire",
    "sg:tags":[
        "preservation",
        "timber"
    ],
    "wof:name":"Central Preservations",
    "wof:placetype":"venue"
},
  "geometry": {"coordinates":[-1.301719,51.698391],"type":"Point"}
}