{
  "type": "Feature",
  "properties": {
    "iso:country":"GB",
    "sg:address":"2 Riley Square, Bell Green",
    "sg:city":"Coventry",
    "sg:classifiers":[
        {
            "category":"Personal",
            "subcategory":"Beauty Salon",
            "type":"Services"
        },
        {
            "category":"Personal",
            "subcategory":"Barber",
            "type":"Services"
        }
    ],
    "sg:phone":"+44 24 7668 9477",
    "sg:postcode":"CV2 1LX",
    "sg:province":"Warwickshire",
    "sg:tags":[
        "unisex",
        "hairdresser"
    ],
    "wof:name":"Grant's Hairdressers",
    "wof:placetype":"venue"
},
  "geometry": {"coordinates":[-1.465052,52.431873],"type":"Point"}
}