{
  "type": "Feature",
  "properties": {
    "addr:full":"154 Stoke Newington Church Street London Greater London N16 0JU",
    "addr:housenumber":"154",
    "addr:postcode":"n16 0ju",
    "addr:street":"Stoke Newington Church Street",
    "iso:country":"GB",
    "sg:address":"154 Stoke Newington Church Street",
    "sg:city":"London",
    "sg:classifiers":[
        {
            "category":"Health Services",
            "subcategory":"Health Practitioner",
            "type":"Services"
        }
    ],
    "sg:postcode":"N16 0JU",
    "sg:province":"Greater London",
    "sg:tags":[
        "osteopath"
    ],
    "wof:name":"Lynn Haller",
    "wof:placetype":"venue"
},
  "geometry": {"coordinates":[-0.081919,51.561653],"type":"Point"}
}