{
  "type": "Feature",
  "properties": {
    "iso:country":"GB",
    "sg:address":"351 Bath Road",
    "sg:city":"Slough",
    "sg:classifiers":[
        {
            "category":"Autos & Motor Vehicles",
            "subcategory":"Motorcycle Sales",
            "type":"Retail Goods"
        }
    ],
    "sg:postcode":"SL1 5PR",
    "sg:province":"Berkshire",
    "sg:tags":[
        "scooter",
        "cycle"
    ],
    "wof:name":"SUPERBIKING",
    "wof:placetype":"venue"
},
  "geometry": {"coordinates":[-0.639341,51.520424],"type":"Point"}
}