{
  "type": "Feature",
  "properties": {
    "iso:country":"GB",
    "sg:address":"39 Rose Park, Rowtoen",
    "sg:city":"Addlestone",
    "sg:classifiers":[
        {
            "category":"Conference Center",
            "type":"Public Place"
        }
    ],
    "sg:phone":"+44 1263 741039",
    "sg:postcode":"KT15 1HN",
    "sg:province":"Surrey",
    "wof:name":"International Conference Productions Ltd.",
    "wof:placetype":"venue"
},
  "geometry": {"coordinates":[-0.5169,51.354576],"type":"Point"}
}