{
  "type": "Feature",
  "properties": {
    "iso:country":"GB",
    "sg:address":"21 Colwick Road, Sneinton",
    "sg:city":"Nottingham",
    "sg:classifiers":[
        {
            "category":"Personal",
            "subcategory":"Beauty Salon",
            "type":"Services"
        }
    ],
    "sg:postcode":"NG2 4AL",
    "sg:province":"Nottinghamshire",
    "sg:tags":[
        "lady",
        "hairdresser"
    ],
    "wof:name":"Shahnaz Hair Studio",
    "wof:placetype":"venue"
},
  "geometry": {"coordinates":[-1.127359,52.949703],"type":"Point"}
}