{
  "type": "Feature",
  "properties": {
    "addr:full":"Opus House, Basingstoke Road, Riseley Reading Berkshire RG7 1QQ",
    "addr:postcode":"rg7 1qq",
    "addr:street":"Basingstoke Road",
    "iso:country":"GB",
    "sg:address":"Opus House, Basingstoke Road, Riseley",
    "sg:city":"Reading",
    "sg:classifiers":[
        {
            "category":"Professional",
            "subcategory":"Management & Consulting",
            "type":"Services"
        }
    ],
    "sg:phone":"+44 118 988 0400",
    "sg:postcode":"RG7 1QQ",
    "sg:province":"Berkshire",
    "sg:tags":[
        "marketing",
        "consultant"
    ],
    "wof:name":"Perception Creative Marketing Ltd.",
    "wof:placetype":"venue"
},
  "geometry": {"coordinates":[-0.973149,51.411114],"type":"Point"}
}