{
  "type": "Feature",
  "properties": {
    "addr:full":"Blaenpentre, Trisant Aberystwyth Ceredigion SY23 4RL",
    "addr:postcode":"sy23 4rl",
    "iso:country":"GB",
    "sg:address":"Blaenpentre, Trisant",
    "sg:city":"Aberystwyth",
    "sg:classifiers":[
        {
            "category":"Farming",
            "subcategory":"Livestock Farm",
            "type":"Manufacturing & Wholesale Goods"
        }
    ],
    "sg:phone":"+44 1974 282279",
    "sg:postcode":"SY23 4RL",
    "sg:province":"Ceredigion",
    "sg:tags":[
        "others"
    ],
    "wof:name":"J M Powell",
    "wof:placetype":"venue"
},
  "geometry": {"coordinates":[-3.8828039169,52.3635482788],"type":"Point"}
}