{
  "type": "Feature",
  "properties": {
    "iso:country":"GB",
    "sg:address":"6 Tufton Road",
    "sg:city":"Ashford",
    "sg:classifiers":[
        {
            "category":"Building & Trades",
            "subcategory":"Construction",
            "type":"Services"
        }
    ],
    "sg:postcode":"TN24 8AU",
    "sg:province":"Kent",
    "sg:tags":[
        "joiner",
        "carpenter"
    ],
    "wof:name":"B M Carpentry & General Building",
    "wof:placetype":"venue"
},
  "geometry": {"coordinates":[0.882563,51.14785],"type":"Point"}
}