{
  "type": "Feature",
  "properties": {
    "addr:full":"106 Burlington Road Blackpool Lancashire FY4 1JR",
    "addr:housenumber":"106",
    "addr:postcode":"fy4 1jr",
    "addr:street":"Burlington Road",
    "iso:country":"GB",
    "sg:address":"106 Burlington Road",
    "sg:city":"Blackpool",
    "sg:classifiers":[
        {
            "category":"Travel",
            "subcategory":"Hotels & Motels",
            "type":"Entertainment"
        }
    ],
    "sg:postcode":"FY4 1JR",
    "sg:province":"Lancashire",
    "wof:name":"The Blarney Hotel",
    "wof:placetype":"venue"
},
  "geometry": {"coordinates":[-3.0530130863,53.7879753113],"type":"Point"}
}