{
  "type": "Feature",
  "properties": {
    "addr:full":"92 Liverpool Road Southport Lancashire PR8 4DA",
    "addr:housenumber":"92",
    "addr:postcode":"pr8 4da",
    "addr:street":"Liverpool Road",
    "iso:country":"GB",
    "sg:address":"92 Liverpool Road",
    "sg:city":"Southport",
    "sg:classifiers":[
        {
            "category":"Building & Trades",
            "subcategory":"Construction",
            "type":"Services"
        }
    ],
    "sg:phone":"+44 1704 550440",
    "sg:postcode":"PR8 4DA",
    "sg:province":"Lancashire",
    "sg:tags":[
        "dry",
        "plastering",
        "plasterers",
        "lining",
        "related",
        "screeders"
    ],
    "wof:name":"J K Doyle",
    "wof:placetype":"venue"
},
  "geometry": {"coordinates":[-3.011942,53.629452],"type":"Point"}
}