{
  "type": "Feature",
  "properties": {
    "addr:full":"Mill Lane, Coppull Chorley Lancashire PR7 5AW",
    "addr:postcode":"pr7 5aw",
    "addr:street":"Mill Lane",
    "iso:country":"GB",
    "sg:address":"Mill Lane, Coppull",
    "sg:city":"Chorley",
    "sg:classifiers":[
        {
            "category":"Home & Garden",
            "subcategory":"Carpets & Floor Coverings",
            "type":"Retail Goods"
        }
    ],
    "sg:phone":"+44 1257 793487",
    "sg:postcode":"PR7 5AW",
    "sg:province":"Lancashire",
    "sg:tags":[
        "rubber",
        "plastic"
    ],
    "wof:name":"S L R (Uk) Ltd.",
    "wof:placetype":"venue"
},
  "geometry": {"coordinates":[-2.691847086,53.6293678284],"type":"Point"}
}