{
  "type": "Feature",
  "properties": {
    "iso:country":"GB",
    "sg:address":"British Museum, Great Russell Street",
    "sg:city":"London",
    "sg:classifiers":[
        {
            "category":"Restaurant",
            "type":"Food & Drink"
        }
    ],
    "sg:phone":"+44 20 7580 9212",
    "sg:postcode":"WC1B 3DG",
    "sg:province":"Greater London",
    "wof:name":"Milburns Restaurants Ltd.",
    "wof:placetype":"venue"
},
  "geometry": {"coordinates":[-0.1273639947,51.5178413391],"type":"Point"}
}