{
  "type": "Feature",
  "properties": {
    "iso:country":"GB",
    "sg:address":"61b South View Road",
    "sg:city":"Benfleet",
    "sg:classifiers":[
        {
            "category":"Retail",
            "subcategory":"Driving School",
            "type":"Services"
        }
    ],
    "sg:phone":"+44 1268 757033",
    "sg:postcode":"SS7 5NE",
    "sg:province":"Essex",
    "wof:name":"Premier School of Motoring",
    "wof:placetype":"venue"
},
  "geometry": {"coordinates":[0.555821,51.558723],"type":"Point"}
}