{
  "type": "Feature",
  "properties": {
    "addr:full":"Tozer House, Tozer Way Chichester West Sussex PO19 7NX",
    "addr:postcode":"po19 7nx",
    "addr:street":"Tozer Way",
    "iso:country":"GB",
    "sg:address":"Tozer House, Tozer Way",
    "sg:city":"Chichester",
    "sg:classifiers":[
        {
            "category":"Social Services",
            "type":"Services"
        },
        {
            "category":"Health Services",
            "subcategory":"Nursing And Care Facility",
            "type":"Services"
        },
        {
            "category":"Government",
            "subcategory":"Office",
            "type":"Public Place"
        }
    ],
    "sg:phone":"+44 1243 776703",
    "sg:postcode":"PO19 7NX",
    "sg:province":"West Sussex",
    "sg:tags":[
        "residential",
        "local"
    ],
    "wof:name":"Tozer House",
    "wof:placetype":"venue"
},
  "geometry": {"coordinates":[-0.768909,50.837769],"type":"Point"}
}