{
  "type": "Feature",
  "properties": {
    "addr:full":"78 Fore Street Kingsbridge Devon TQ7 1PP",
    "addr:housenumber":"78",
    "addr:postcode":"tq7 1pp",
    "addr:street":"Fore Street",
    "iso:country":"GB",
    "sg:address":"78 Fore Street",
    "sg:city":"Kingsbridge",
    "sg:classifiers":[
        {
            "category":"Shopping",
            "subcategory":"Gifts & Souvenirs",
            "type":"Retail Goods"
        }
    ],
    "sg:postcode":"TQ7 1PP",
    "sg:province":"Devon",
    "sg:tags":[
        "shop"
    ],
    "wof:name":"Eves Baubles & Baskets",
    "wof:placetype":"venue"
},
  "geometry": {"coordinates":[-3.7781579494,50.2862892151],"type":"Point"}
}