{
  "type": "Feature",
  "properties": {
    "iso:country":"GB",
    "sg:address":"Kingdom Hall, Marlow Rd",
    "sg:city":"Henley On Thames",
    "sg:classifiers":[
        {
            "category":"Place Of Worship",
            "type":"Public Place"
        }
    ],
    "sg:phone":"+44 1491 577083",
    "sg:postcode":"RG9 2JA",
    "sg:province":"Berkshire",
    "wof:name":"Jehovah's Witnesses",
    "wof:placetype":"venue"
},
  "geometry": {"coordinates":[-0.903189,51.535297],"type":"Point"}
}