{
  "type": "Feature",
  "properties": {
    "iso:country":"GB",
    "sg:address":"62 Cheapside West",
    "sg:city":"Rayleigh",
    "sg:classifiers":[
        {
            "category":"Government",
            "subcategory":"Post Office",
            "type":"Public Place"
        }
    ],
    "sg:phone":"+44 1268 785555",
    "sg:postcode":"SS6 9DE",
    "sg:province":"Essex",
    "sg:tags":[
        "messenger",
        "courier"
    ],
    "wof:name":"Deadline Despatch",
    "wof:placetype":"venue"
},
  "geometry": {"coordinates":[0.601758,51.595108],"type":"Point"}
}