{
  "type": "Feature",
  "properties": {
    "addr:full":"45 Cornwall Street Glasgow Glasgow City G41 1BA",
    "addr:housenumber":"45",
    "addr:postcode":"g41 1ba",
    "addr:street":"Cornwall Street",
    "iso:country":"GB",
    "sg:address":"45 Cornwall Street",
    "sg:city":"Glasgow",
    "sg:classifiers":[
        {
            "category":"Building & Trades",
            "subcategory":"Landscaping Services",
            "type":"Services"
        }
    ],
    "sg:phone":"+44 141 427 1273",
    "sg:postcode":"G41 1BA",
    "sg:province":"Glasgow City",
    "sg:tags":[
        "gardening"
    ],
    "wof:name":"Jungle Warfare",
    "wof:placetype":"venue"
},
  "geometry": {"coordinates":[-4.2874097824,55.8504714966],"type":"Point"}
}