{
  "type": "Feature",
  "properties": {
    "iso:country":"GB",
    "sg:address":"11 Whitehouse Avenue",
    "sg:city":"Liverpool",
    "sg:classifiers":[
        {
            "category":"Building & Trades",
            "subcategory":"Landscaping Services",
            "type":"Services"
        }
    ],
    "sg:phone":"+44 1704 833150",
    "sg:postcode":"L37 3LR",
    "sg:province":"Lancashire",
    "sg:tags":[
        "landscape",
        "contractor"
    ],
    "wof:name":"Fornby Landscapes",
    "wof:placetype":"venue"
},
  "geometry": {"coordinates":[-3.0545809269,53.5582695007],"type":"Point"}
}