{
  "type": "Feature",
  "properties": {
    "addr:full":"129 Bath Street Ilkeston Derbyshire DE7 8AP",
    "addr:housenumber":"129",
    "addr:postcode":"de7 8ap",
    "addr:street":"Bath Street",
    "iso:country":"GB",
    "sg:address":"129 Bath Street",
    "sg:city":"Ilkeston",
    "sg:classifiers":[
        {
            "category":"Professional",
            "subcategory":"Lawyer & Legal Services",
            "type":"Services"
        }
    ],
    "sg:phone":"+44 115 930 4994",
    "sg:postcode":"DE7 8AP",
    "sg:province":"Derbyshire",
    "sg:tags":[
        "solicitor"
    ],
    "wof:name":"Maclaren Warner",
    "wof:placetype":"venue"
},
  "geometry": {"coordinates":[-1.309458971,52.9759216309],"type":"Point"}
}