{
  "type": "Feature",
  "properties": {
    "iso:country":"GB",
    "sg:address":"31 Maltravers Place",
    "sg:city":"Sheffield",
    "sg:classifiers":[
        {
            "category":"Professional",
            "subcategory":"Art Services",
            "type":"Services"
        },
        {
            "category":"Building & Trades",
            "subcategory":"Construction",
            "type":"Services"
        }
    ],
    "sg:phone":"+44 114 275 9336",
    "sg:postcode":"S2 5AN",
    "sg:province":"South Yorkshire",
    "sg:tags":[
        "decorator",
        "painter"
    ],
    "wof:name":"Brian Oates",
    "wof:placetype":"venue"
},
  "geometry": {"coordinates":[-1.444329,53.382206],"type":"Point"}
}