{
  "type": "Feature",
  "properties": {
    "addr:full":"14 Swinegate York North Yorkshire YO1 8AZ",
    "addr:housenumber":"14",
    "addr:postcode":"yo1 8az",
    "addr:street":"Swinegate York",
    "iso:country":"GB",
    "sg:address":"14 Swinegate",
    "sg:city":"York",
    "sg:classifiers":[
        {
            "category":"Personal",
            "type":"Services"
        },
        {
            "category":"Commercial Area",
            "type":"Public Place"
        }
    ],
    "sg:phone":"+44 1904 621001",
    "sg:postcode":"YO1 8AZ",
    "sg:province":"North Yorkshire",
    "sg:tags":[
        "shop",
        "tailor",
        "centre"
    ],
    "wof:name":"Stonegate Tailors",
    "wof:placetype":"venue"
},
  "geometry": {"coordinates":[-1.081269,53.960129],"type":"Point"}
}