{
  "type": "Feature",
  "properties": {
    "iso:country":"GB",
    "sg:address":"3 Anderson Rd",
    "sg:city":"Bishopton",
    "sg:classifiers":[
        {
            "category":"Organizations",
            "subcategory":"Non-profit Organization",
            "type":"Services"
        }
    ],
    "sg:postcode":"PA7 5EN",
    "sg:province":"Renfrewshire",
    "sg:tags":[
        "organisation",
        "animal",
        "welfare"
    ],
    "wof:name":"Scottish Society for the Prevention of C",
    "wof:placetype":"venue"
},
  "geometry": {"coordinates":[-4.506865,55.912041],"type":"Point"}
}