{
  "type": "Feature",
  "properties": {
    "iso:country":"GB",
    "sg:address":"11 Dull Grove Avenue",
    "sg:city":"Yeovil",
    "sg:classifiers":[
        {
            "category":"Autos & Motor Vehicles",
            "subcategory":"Fuel & Gas Station",
            "type":"Retail Goods"
        },
        {
            "category":"Home & Garden",
            "subcategory":"Household Appliances",
            "type":"Retail Goods"
        },
        {
            "category":"Utilities",
            "subcategory":"Natural Gas",
            "type":"Services"
        }
    ],
    "sg:postcode":"BA20 2LP",
    "sg:province":"Somerset",
    "sg:tags":[
        "control",
        "management",
        "centre",
        "energy",
        "cooker",
        "domestic",
        "system",
        "aga"
    ],
    "wof:name":"Hider Heating",
    "wof:placetype":"venue"
},
  "geometry": {"coordinates":[-2.643647,50.942867],"type":"Point"}
}