{
  "type": "Feature",
  "properties": {
    "iso:country":"GB",
    "sg:address":"3 Hall Green Clo",
    "sg:city":"Skelmersdale",
    "sg:classifiers":[
        {
            "category":"Social Services",
            "subcategory":"Adult Care",
            "type":"Services"
        }
    ],
    "sg:phone":"+44 1695 632628",
    "sg:postcode":"WN8 0DY",
    "sg:province":"Lancashire",
    "sg:tags":[
        "housing",
        "sheltered"
    ],
    "wof:name":"Greenhaven",
    "wof:placetype":"venue"
},
  "geometry": {"coordinates":[-2.7282419205,53.5414161682],"type":"Point"}
}