{
  "type": "Feature",
  "properties": {
    "addr:full":"280 Green Street London Greater London E7 8LF",
    "addr:housenumber":"280",
    "addr:postcode":"e7 8lf",
    "addr:street":"Green Street",
    "iso:country":"GB",
    "sg:address":"280 Green Street",
    "sg:city":"London",
    "sg:classifiers":[
        {
            "category":"Shopping",
            "subcategory":"Luggage & Leather Goods",
            "type":"Retail Goods"
        }
    ],
    "sg:phone":"+44 20 8472 4803",
    "sg:postcode":"E7 8LF",
    "sg:province":"Greater London",
    "wof:name":"The Luggage Centre",
    "wof:placetype":"venue"
},
  "geometry": {"coordinates":[0.0333629996,51.5382804871],"type":"Point"}
}