{
  "type": "Feature",
  "properties": {
    "addr:full":"Manor Buildings, Manor Row Bradford West Yorkshire BD1 4NL",
    "addr:postcode":"bd1 4nl",
    "addr:street":"Manor Buildings Manor Row Bradford West",
    "iso:country":"GB",
    "sg:address":"Manor Buildings, Manor Row",
    "sg:city":"Bradford",
    "sg:classifiers":[
        {
            "category":"Professional",
            "subcategory":"Employment Agencies",
            "type":"Services"
        }
    ],
    "sg:phone":"+44 1274 731666",
    "sg:postcode":"BD1 4NL",
    "sg:province":"West Yorkshire",
    "sg:tags":[
        "consultant"
    ],
    "wof:name":"Hays Specialist Recruitment Ltd.",
    "wof:placetype":"venue"
},
  "geometry": {"coordinates":[-1.7568039894,53.7979049683],"type":"Point"}
}