{
  "type": "Feature",
  "properties": {
    "iso:country":"GB",
    "sg:address":"101 Station Road",
    "sg:city":"Kelty",
    "sg:classifiers":[
        {
            "category":"Home & Garden",
            "subcategory":"Home Furnishings",
            "type":"Retail Goods"
        },
        {
            "category":"Home & Garden",
            "subcategory":"Carpets & Floor Coverings",
            "type":"Retail Goods"
        }
    ],
    "sg:phone":"+44 1383 830389",
    "sg:postcode":"KY4 0BL",
    "sg:province":"Fife",
    "sg:tags":[
        "fitting",
        "rug",
        "matting",
        "carpets"
    ],
    "wof:name":"JOHN COLLINS",
    "wof:placetype":"venue"
},
  "geometry": {"coordinates":[-3.3759651184,56.1336593628],"type":"Point"}
}