{
  "type": "Feature",
  "properties": {
    "addr:full":"85 Quaker Lane Southall Greater London UB2 4RE",
    "addr:housenumber":"85",
    "addr:postcode":"ub2 4re",
    "addr:street":"Quaker Lane",
    "iso:country":"GB",
    "sg:address":"85 Quaker Lane",
    "sg:city":"Southall",
    "sg:classifiers":[
        {
            "category":"Building & Trades",
            "subcategory":"Plumbing",
            "type":"Services"
        }
    ],
    "sg:phone":"+44 20 8843 0138",
    "sg:postcode":"UB2 4RE",
    "sg:province":"Greater London",
    "sg:tags":[
        "central",
        "heating"
    ],
    "wof:name":"Adonis Plumbing Services",
    "wof:placetype":"venue"
},
  "geometry": {"coordinates":[-0.369683,51.502876],"type":"Point"}
}