{
  "type": "Feature",
  "properties": {
    "addr:full":"Pillaton Saltash Cornwall PL12 6QS",
    "addr:housenumber":"pillaton",
    "addr:postcode":"pl12 6qs",
    "iso:country":"GB",
    "sg:address":"Pillaton",
    "sg:city":"Saltash",
    "sg:classifiers":[
        {
            "category":"Restaurant",
            "type":"Food & Drink"
        }
    ],
    "sg:phone":"+44 1579 350238",
    "sg:postcode":"PL12 6QS",
    "sg:province":"Cornwall",
    "wof:name":"Weary Friar Inn",
    "wof:placetype":"venue"
},
  "geometry": {"coordinates":[-4.3034601212,50.455078125],"type":"Point"}
}