{
  "type": "Feature",
  "properties": {
    "addr:full":"Nash Court, Boughton Faversham Kent ME13 9SW",
    "addr:postcode":"me13 9sw",
    "addr:street":"Nash Court",
    "iso:country":"GB",
    "sg:address":"Nash Court, Boughton",
    "sg:city":"Faversham",
    "sg:classifiers":[
        {
            "category":"Farming",
            "subcategory":"Farm",
            "type":"Manufacturing & Wholesale Goods"
        }
    ],
    "sg:postcode":"ME13 9SW",
    "sg:province":"Kent",
    "sg:tags":[
        "mixed",
        "crop"
    ],
    "wof:name":"T G Redsell Ltd.",
    "wof:placetype":"venue"
},
  "geometry": {"coordinates":[0.937095,51.299198],"type":"Point"}
}