{
  "type": "Feature",
  "properties": {
    "addr:full":"Unit 1, Canal St, Sandiacre Nottingham Derbyshire NG10 5AZ",
    "addr:housenumber":"unit 1",
    "addr:postcode":"ng10 5az",
    "addr:street":"Canal St",
    "iso:country":"GB",
    "sg:address":"Unit 1, Canal St, Sandiacre",
    "sg:city":"Nottingham",
    "sg:classifiers":[
        {
            "category":"Manufacturing",
            "subcategory":"Signs",
            "type":"Manufacturing & Wholesale Goods"
        }
    ],
    "sg:phone":"+44 115 949 7308",
    "sg:postcode":"NG10 5AZ",
    "sg:province":"Derbyshire",
    "sg:tags":[
        "writer"
    ],
    "wof:name":"Heritage Signs",
    "wof:placetype":"venue"
},
  "geometry": {"coordinates":[-1.287404,52.923786],"type":"Point"}
}