{
  "type": "Feature",
  "properties": {
    "iso:country":"GB",
    "sg:address":"Wayside Farm, Chinnor Road, Bledlow Ridge",
    "sg:city":"High Wycombe",
    "sg:classifiers":[
        {
            "category":"Farming",
            "subcategory":"Livestock Farm",
            "type":"Manufacturing & Wholesale Goods"
        }
    ],
    "sg:postcode":"HP14 4AA",
    "sg:province":"Buckinghamshire",
    "sg:tags":[
        "others"
    ],
    "wof:name":"J & A Keen",
    "wof:placetype":"venue"
},
  "geometry": {"coordinates":[-0.846414,51.67078],"type":"Point"}
}