{
  "type": "Feature",
  "properties": {
    "addr:full":"Castle House, Southern Street Caerphilly Caerphilly CF83 1LH",
    "addr:postcode":"cf83 1lh",
    "addr:street":"Southern Street",
    "iso:country":"GB",
    "sg:address":"Castle House, Southern Street",
    "sg:city":"Caerphilly",
    "sg:classifiers":[
        {
            "category":"Building & Trades",
            "subcategory":"Plumbing",
            "type":"Services"
        }
    ],
    "sg:postcode":"CF83 1LH",
    "sg:province":"Caerphilly",
    "sg:tags":[
        "central",
        "heating"
    ],
    "wof:name":"Gas Care Central Heating Ltd.",
    "wof:placetype":"venue"
},
  "geometry": {"coordinates":[-3.214486,51.574684],"type":"Point"}
}