{
  "type": "Feature",
  "properties": {
    "iso:country":"GB",
    "sg:address":"172 Citadel Road",
    "sg:city":"Plymouth",
    "sg:classifiers":[
        {
            "category":"Travel",
            "subcategory":"Hotels & Motels",
            "type":"Entertainment"
        }
    ],
    "sg:phone":"+44 1752 225158",
    "sg:postcode":"PL1 3BD",
    "sg:province":"Devon",
    "wof:name":"Plymouth Backpackers Hotel",
    "wof:placetype":"venue"
},
  "geometry": {"coordinates":[-4.147485,50.366791],"type":"Point"}
}