{
  "type": "Feature",
  "properties": {
    "addr:full":"12 Central Way Willesden Greater London NW10 7XN",
    "addr:housenumber":"12",
    "addr:postcode":"nw10 7xn",
    "addr:street":"Central Way",
    "iso:country":"GB",
    "sg:address":"12 Central Way",
    "sg:city":"Willesden",
    "sg:classifiers":[
        {
            "category":"Food & Beverages",
            "subcategory":"Liquor & Beverages",
            "type":"Retail Goods"
        },
        {
            "category":"Professional",
            "subcategory":"Business Services",
            "type":"Services"
        },
        {
            "category":"Utilities",
            "subcategory":"Natural Gas",
            "type":"Services"
        }
    ],
    "sg:phone":"+44 20 8838 0660",
    "sg:postcode":"NW10 7XN",
    "sg:province":"Greater London",
    "sg:tags":[
        "wines",
        "wholesale",
        "agent",
        "beer",
        "export",
        "import",
        "spirit",
        "wine"
    ],
    "wof:name":"Matthew Clarke",
    "wof:placetype":"venue"
},
  "geometry": {"coordinates":[-0.270678997,51.5312042236],"type":"Point"}
}