{
  "type": "Feature",
  "properties": {
    "addr:full":"138 Chepstow Rd Newport East Riding of Yorkshire NP9 8EG",
    "addr:housenumber":"138",
    "addr:postcode":"np9 8eg",
    "addr:street":"Chepstow Rd",
    "iso:country":"GB",
    "sg:address":"138 Chepstow Rd",
    "sg:city":"Newport",
    "sg:classifiers":[
        {
            "category":"Food & Beverages",
            "subcategory":"Meat & Fish",
            "type":"Retail Goods"
        }
    ],
    "sg:phone":"+44 1633 244508",
    "sg:postcode":"NP9 8EG",
    "sg:province":"East Riding of Yorkshire",
    "sg:tags":[
        "butcher"
    ],
    "wof:name":"Charter Foods Ltd",
    "wof:placetype":"venue"
},
  "geometry": {"coordinates":[-2.961369,51.5882],"type":"Point"}
}