{
  "type": "Feature",
  "properties": {
    "addr:full":"1 Rivers Street Place Bath Bath and North East Somerset BA1 2RS",
    "addr:housenumber":"1",
    "addr:postcode":"ba1 2rs",
    "addr:street":"Rivers Street Place",
    "iso:country":"GB",
    "sg:address":"1 Rivers Street Place",
    "sg:city":"Bath",
    "sg:classifiers":[
        {
            "category":"Retail",
            "subcategory":"Veterinary Services",
            "type":"Services"
        }
    ],
    "sg:phone":"+44 1225 313995",
    "sg:postcode":"BA1 2RS",
    "sg:province":"Bath and North East Somerset",
    "sg:tags":[
        "surgeon",
        "activity"
    ],
    "sg:website":"http://www.bathveterinarycentre.co.uk",
    "wof:name":"The Veterinary Centre",
    "wof:placetype":"venue"
},
  "geometry": {"coordinates":[-2.3661201,51.3878173828],"type":"Point"}
}