{
  "type": "Feature",
  "properties": {
    "iso:country":"GB",
    "sg:address":"56 Bollin Dr",
    "sg:city":"Congleton",
    "sg:classifiers":[
        {
            "category":"Bus Charters",
            "type":"Transportation"
        }
    ],
    "sg:phone":"+44 1260 273543",
    "sg:postcode":"CW12 3SJ",
    "sg:province":"Cheshire",
    "sg:tags":[
        "hire",
        "coach"
    ],
    "wof:name":"Jonathan Lee Hill",
    "wof:placetype":"venue"
},
  "geometry": {"coordinates":[-2.2016530037,53.1585731506],"type":"Point"}
}