{
  "type": "Feature",
  "properties": {
    "addr:full":"14d Sunderland Terr London Greater London W2 5PA",
    "addr:housenumber":"14d",
    "addr:postcode":"w2 5pa",
    "addr:street":"Sunderland Terr",
    "iso:country":"GB",
    "sg:address":"14d Sunderland Terr",
    "sg:city":"London",
    "sg:classifiers":[
        {
            "category":"Wholesale",
            "subcategory":"Books, Periodicals, & Newspapers",
            "type":"Manufacturing & Wholesale Goods"
        }
    ],
    "sg:postcode":"W2 5PA",
    "sg:province":"Greater London",
    "sg:tags":[
        "publishing"
    ],
    "wof:name":"Ex Catherdra Publishing",
    "wof:placetype":"venue"
},
  "geometry": {"coordinates":[-0.192078,51.516594],"type":"Point"}
}