{
  "type": "Feature",
  "properties": {
    "iso:country":"GB",
    "sg:address":"15 Firwood Terrace",
    "sg:city":"Ferryhill",
    "sg:classifiers":[
        {
            "category":"Building & Trades",
            "subcategory":"Construction",
            "type":"Services"
        }
    ],
    "sg:phone":"+44 1740 656516",
    "sg:postcode":"DL17 0DG",
    "sg:province":"Durham",
    "sg:tags":[
        "decorator",
        "painter"
    ],
    "wof:name":"S H Decorators",
    "wof:placetype":"venue"
},
  "geometry": {"coordinates":[-1.529176,54.673313],"type":"Point"}
}