{
  "type": "Feature",
  "properties": {
    "iso:country":"GB",
    "sg:address":"Home Orchard Cottage, Manor Lane, Gotherington",
    "sg:city":"Cheltenham",
    "sg:classifiers":[
        {
            "category":"Manufacturing",
            "subcategory":"Signs",
            "type":"Manufacturing & Wholesale Goods"
        }
    ],
    "sg:phone":"+44 1242 673774",
    "sg:postcode":"GL52 9QX",
    "sg:province":"Gloucestershire",
    "sg:tags":[
        "supplier",
        "nameplate"
    ],
    "wof:name":"Simon Lloyd Signs",
    "wof:placetype":"venue"
},
  "geometry": {"coordinates":[-2.0561490059,51.9652404785],"type":"Point"}
}