{
  "type": "Feature",
  "properties": {
    "addr:full":"Pennypot Industrial Estate, Pennypot Hythe Kent CT21 6PE",
    "addr:postcode":"ct21 6pe",
    "addr:street":"Estate Pennypot Hythe",
    "iso:country":"GB",
    "sg:address":"Pennypot Industrial Estate, Pennypot",
    "sg:city":"Hythe",
    "sg:classifiers":[
        {
            "category":"Professional",
            "subcategory":"Printing & Photocopies",
            "type":"Services"
        }
    ],
    "sg:phone":"+44 1303 267060",
    "sg:postcode":"CT21 6PE",
    "sg:province":"Kent",
    "sg:tags":[
        "printer"
    ],
    "wof:name":"Hythe Printers Ltd.",
    "wof:placetype":"venue"
},
  "geometry": {"coordinates":[1.063830018,51.0676612854],"type":"Point"}
}