{
  "type": "Feature",
  "properties": {
    "iso:country":"GB",
    "sg:address":"Mainway East",
    "sg:city":"Manchester",
    "sg:classifiers":[
        {
            "category":"Community Center",
            "type":"Public Place"
        }
    ],
    "sg:phone":"+44 161 287 6654",
    "sg:postcode":"M24 1RQ",
    "sg:province":"Greater Manchester",
    "sg:tags":[
        "centre"
    ],
    "wof:name":"Brookside Community Centre",
    "wof:placetype":"venue"
},
  "geometry": {"coordinates":[-2.194949,53.537476],"type":"Point"}
}