{
  "type": "Feature",
  "properties": {
    "addr:full":"1 Hill Street Lydney Gloucestershire GL15 5HB",
    "addr:housenumber":"1",
    "addr:postcode":"gl15 5hb",
    "addr:street":"Hill Street",
    "iso:country":"GB",
    "sg:address":"1 Hill Street",
    "sg:city":"Lydney",
    "sg:classifiers":[
        {
            "category":"Professional",
            "subcategory":"Accounting & Tax Preparation",
            "type":"Services"
        }
    ],
    "sg:phone":"+44 1594 842188",
    "sg:postcode":"GL15 5HB",
    "sg:province":"Gloucestershire",
    "sg:tags":[
        "accountant",
        "activity"
    ],
    "wof:name":"Makinson & Co",
    "wof:placetype":"venue"
},
  "geometry": {"coordinates":[-2.534423,51.725464],"type":"Point"}
}