{
  "type": "Feature",
  "properties": {
    "addr:full":"Barracks Lane Bristol City of Bristol BS11 9NG",
    "addr:postcode":"bs11 9ng",
    "addr:street":"Barracks Lane",
    "iso:country":"GB",
    "sg:address":"Barracks Lane",
    "sg:city":"Bristol",
    "sg:classifiers":[
        {
            "category":"Education",
            "subcategory":"School",
            "type":"Public Place"
        },
        {
            "category":"Government",
            "subcategory":"Office",
            "type":"Public Place"
        }
    ],
    "sg:phone":"+44 117 982 2915",
    "sg:postcode":"BS11 9NG",
    "sg:province":"City of Bristol",
    "sg:tags":[
        "local",
        "authority"
    ],
    "wof:name":"Bristol City Council",
    "wof:placetype":"venue"
},
  "geometry": {"coordinates":[-2.682807,51.496666],"type":"Point"}
}