{
  "type": "Feature",
  "properties": {
    "addr:full":"Unit 18 Stephenson Way Liverpool Lancashire L37 8EG",
    "addr:housenumber":"unit 18",
    "addr:postcode":"l37 8eg",
    "addr:street":"Stephenson Way",
    "iso:country":"GB",
    "sg:address":"Unit 18 Stephenson Way",
    "sg:city":"Liverpool",
    "sg:classifiers":[
        {
            "category":"Home & Garden",
            "subcategory":"Building Materials",
            "type":"Retail Goods"
        }
    ],
    "sg:postcode":"L37 8EG",
    "sg:province":"Lancashire",
    "sg:tags":[
        "fencing"
    ],
    "wof:name":"M C Dencing",
    "wof:placetype":"venue"
},
  "geometry": {"coordinates":[-3.041096,53.554138],"type":"Point"}
}