{
  "type": "Feature",
  "properties": {
    "iso:country":"GB",
    "sg:address":"51 Roper Street",
    "sg:city":"Whitehaven",
    "sg:classifiers":[
        {
            "category":"Home & Garden",
            "subcategory":"Household Appliances",
            "type":"Retail Goods"
        }
    ],
    "sg:postcode":"CA28 7AU",
    "sg:province":"Cumbria",
    "sg:tags":[
        "domestic",
        "centre"
    ],
    "wof:name":"Masons of Whitehaven",
    "wof:placetype":"venue"
},
  "geometry": {"coordinates":[-3.590114,54.547245],"type":"Point"}
}