{
  "type": "Feature",
  "properties": {
    "addr:full":"3 Middleton Road Walsall Staffordshire WS8 6JF",
    "addr:housenumber":"3",
    "addr:postcode":"ws8 6jf",
    "addr:street":"Middleton Road",
    "iso:country":"GB",
    "sg:address":"3 Middleton Road",
    "sg:city":"Walsall",
    "sg:classifiers":[
        {
            "category":"Manufacturing",
            "subcategory":"Furniture",
            "type":"Manufacturing & Wholesale Goods"
        }
    ],
    "sg:phone":"+44 1543 373576",
    "sg:postcode":"WS8 6JF",
    "sg:province":"Staffordshire",
    "sg:tags":[
        "polishing",
        "french"
    ],
    "wof:name":"Paul Eley French Polishing",
    "wof:placetype":"venue"
},
  "geometry": {"coordinates":[-1.923514,52.654537],"type":"Point"}
}