{
  "type": "Feature",
  "properties": {
    "iso:country":"GB",
    "sg:address":"37 Bridge Street",
    "sg:city":"Usk",
    "sg:classifiers":[
        {
            "category":"Food & Beverages",
            "subcategory":"Bakery",
            "type":"Retail Goods"
        }
    ],
    "sg:postcode":"NP15 1BQ",
    "sg:province":"Monmouthshire",
    "sg:tags":[
        "confectionery"
    ],
    "wof:name":"C J Coughlin",
    "wof:placetype":"venue"
},
  "geometry": {"coordinates":[-2.904764,51.702568],"type":"Point"}
}