{
  "type": "Feature",
  "properties": {
    "iso:country":"GB",
    "sg:address":"31 Mervan Road",
    "sg:city":"London",
    "sg:classifiers":[
        {
            "category":"Organizations",
            "subcategory":"Professional Association",
            "type":"Services"
        }
    ],
    "sg:phone":"+44 20 7274 9241",
    "sg:postcode":"SW2 1DP",
    "sg:province":"Greater London",
    "sg:tags":[
        "union",
        "trade"
    ],
    "wof:name":"The Public Transport Staff Consortium",
    "wof:placetype":"venue"
},
  "geometry": {"coordinates":[-0.113007,51.459576],"type":"Point"}
}