{
  "type": "Feature",
  "properties": {
    "iso:country":"GB",
    "sg:address":"16 Shaftesbury Avenue, Vicars Cross",
    "sg:city":"Chester",
    "sg:classifiers":[
        {
            "category":"Retail",
            "subcategory":"Driving School",
            "type":"Services"
        }
    ],
    "sg:postcode":"CH3 5LQ",
    "sg:province":"Cheshire",
    "wof:name":"PETER TAYLOR",
    "wof:placetype":"venue"
},
  "geometry": {"coordinates":[-2.854186,53.195644],"type":"Point"}
}