{
  "type": "Feature",
  "properties": {
    "iso:country":"GB",
    "sg:address":"The Chimes, Bell Lane, Lower Broadheath",
    "sg:city":"Worcester",
    "sg:classifiers":[
        {
            "category":"Home & Garden",
            "subcategory":"Household Appliances",
            "type":"Retail Goods"
        }
    ],
    "sg:postcode":"WR2 6RR",
    "sg:province":"Worcestershire",
    "sg:tags":[
        "electrical"
    ],
    "wof:name":"R A Carver",
    "wof:placetype":"venue"
},
  "geometry": {"coordinates":[-2.278581,52.212254],"type":"Point"}
}