{
  "type": "Feature",
  "properties": {
    "iso:country":"GB",
    "sg:address":"Lower Beamsworthy Farm",
    "sg:city":"Beaworthy",
    "sg:classifiers":[
        {
            "category":"Farming",
            "subcategory":"Livestock Farm",
            "type":"Manufacturing & Wholesale Goods"
        }
    ],
    "sg:phone":"+44 1409 221288",
    "sg:postcode":"EX21 5AN",
    "sg:province":"Devon",
    "sg:tags":[
        "others"
    ],
    "wof:name":"M J & M J Johns",
    "wof:placetype":"venue"
},
  "geometry": {"coordinates":[-4.183385,50.775307],"type":"Point"}
}