{
  "type": "Feature",
  "properties": {
    "iso:country":"GB",
    "sg:address":"Unit C7, Enterprise Way, Bradford Road",
    "sg:city":"Bradford",
    "sg:classifiers":[
        {
            "category":"Professional",
            "subcategory":"Computer Services",
            "type":"Services"
        }
    ],
    "sg:phone":"+44 1274 610503",
    "sg:postcode":"BD10 8EW",
    "sg:province":"West Yorkshire",
    "sg:tags":[
        "system",
        "software"
    ],
    "wof:name":"Visionsoft Ltd.",
    "wof:placetype":"venue"
},
  "geometry": {"coordinates":[-1.731586,53.825813],"type":"Point"}
}