{
  "type": "Feature",
  "properties": {
    "iso:country":"GB",
    "sg:address":"13 Watchet Lane, Holmer Grn",
    "sg:city":"High Wycombe",
    "sg:classifiers":[
        {
            "category":"Professional",
            "subcategory":"Accounting & Tax Preparation",
            "type":"Services"
        }
    ],
    "sg:phone":"+44 1494 711210",
    "sg:postcode":"HP15 6UA",
    "sg:province":"Buckinghamshire",
    "sg:tags":[
        "accountant",
        "activity"
    ],
    "wof:name":"Allied Accountancy Services",
    "wof:placetype":"venue"
},
  "geometry": {"coordinates":[-0.705594,51.6623],"type":"Point"}
}