{
  "type": "Feature",
  "properties": {
    "iso:country":"GB",
    "sg:address":"The Guildhall, Fore Street",
    "sg:city":"Looe",
    "sg:classifiers":[
        {
            "category":"Government",
            "subcategory":"Office",
            "type":"Public Place"
        }
    ],
    "sg:phone":"+44 1503 262255",
    "sg:postcode":"PL13 1AA",
    "sg:province":"Cornwall",
    "sg:tags":[
        "local"
    ],
    "wof:name":"Looe Parish Town Council",
    "wof:placetype":"venue"
},
  "geometry": {"coordinates":[-4.4551510811,50.3570518494],"type":"Point"}
}