{
  "type": "Feature",
  "properties": {
    "addr:full":"85 Netley Road Ilford Essex IG2 7NP",
    "addr:housenumber":"85",
    "addr:postcode":"ig2 7np",
    "addr:street":"Netley Road",
    "iso:country":"GB",
    "sg:address":"85 Netley Road",
    "sg:city":"Ilford",
    "sg:classifiers":[
        {
            "category":"Building & Trades",
            "subcategory":"Construction",
            "type":"Services"
        }
    ],
    "sg:phone":"+44 20 7518 4443",
    "sg:postcode":"IG2 7NP",
    "sg:province":"Essex",
    "sg:tags":[
        "builder"
    ],
    "wof:name":"Justice & Sons Ltd.",
    "wof:placetype":"venue"
},
  "geometry": {"coordinates":[0.087710999,51.5779342651],"type":"Point"}
}