{
  "type": "Feature",
  "properties": {
    "addr:full":"Rockery Cottage, Moorhead, Preston Upon The Wealdmoor Telford Shropshire TF6 6DN",
    "addr:postcode":"tf6 6dn",
    "addr:street":"Moorhead",
    "iso:country":"GB",
    "sg:address":"Rockery Cottage, Moorhead, Preston Upon The Wealdmoor",
    "sg:city":"Telford",
    "sg:classifiers":[
        {
            "category":"Manufacturing",
            "subcategory":"Building Materials",
            "type":"Manufacturing & Wholesale Goods"
        }
    ],
    "sg:phone":"+44 1952 670280",
    "sg:postcode":"TF6 6DN",
    "sg:province":"Shropshire",
    "sg:tags":[
        "extrusion"
    ],
    "wof:name":"D C S Automotive",
    "wof:placetype":"venue"
},
  "geometry": {"coordinates":[-2.4731969833,52.7347221375],"type":"Point"}
}