{
  "type": "Feature",
  "properties": {
    "iso:country":"GB",
    "sg:address":"Unit 3 Blezard Business Park, Brenkley Way",
    "sg:city":"Newcastle Upon Tyne",
    "sg:classifiers":[
        {
            "category":"Professional",
            "subcategory":"Computer Services",
            "type":"Services"
        }
    ],
    "sg:phone":"+44 191 217 0322",
    "sg:postcode":"NE13 6DS",
    "sg:province":"Northumberland",
    "sg:tags":[
        "system",
        "software"
    ],
    "wof:name":"Sanderson General Automation",
    "wof:placetype":"venue"
},
  "geometry": {"coordinates":[-1.63063,55.060959],"type":"Point"}
}