{
  "type": "Feature",
  "properties": {
    "iso:country":"GB",
    "sg:address":"7 Chatsworth Grove",
    "sg:city":"Harrogate",
    "sg:classifiers":[
        {
            "category":"Building & Trades",
            "subcategory":"Construction",
            "type":"Services"
        }
    ],
    "sg:phone":"+44 1423 521488",
    "sg:postcode":"HG1 2AS",
    "sg:province":"North Yorkshire",
    "sg:tags":[
        "roofing"
    ],
    "wof:name":"All Weather",
    "wof:placetype":"venue"
},
  "geometry": {"coordinates":[-1.539312,54.001629],"type":"Point"}
}