{
  "type": "Feature",
  "properties": {
    "iso:country":"GB",
    "sg:address":"Dew Point Farm, Division Lane",
    "sg:city":"Blackpool",
    "sg:classifiers":[
        {
            "category":"Education",
            "subcategory":"Library",
            "type":"Public Place"
        }
    ],
    "sg:postcode":"FY4 5DZ",
    "sg:province":"Lancashire",
    "sg:tags":[
        "reproduction",
        "furniture"
    ],
    "wof:name":"Stephen Padgett",
    "wof:placetype":"venue"
},
  "geometry": {"coordinates":[-3.00751,53.77454],"type":"Point"}
}