{
  "type": "Feature",
  "properties": {
    "addr:full":"Caple House, Guinness Building, Kings Road London Greater London SW10 0TT",
    "addr:postcode":"sw10 0tt",
    "addr:street":"Kings Road",
    "iso:country":"GB",
    "sg:address":"Caple House, Guinness Building, Kings Road",
    "sg:city":"London",
    "sg:classifiers":[
        {
            "category":"Organizations",
            "subcategory":"Community Association",
            "type":"Services"
        }
    ],
    "sg:phone":"+44 20 7352 6559",
    "sg:postcode":"SW10 0TT",
    "sg:province":"Greater London",
    "sg:tags":[
        "co-operatives",
        "society",
        "housing",
        "trust"
    ],
    "sg:website":"http://www.guinnesstrust.org.uk",
    "wof:name":"The Guinness Trust",
    "wof:placetype":"venue"
},
  "geometry": {"coordinates":[-0.182191,51.48151],"type":"Point"}
}