{
  "type": "Feature",
  "properties": {
    "addr:full":"Cwmdu Institute, Bridgend Road Maesteg Bridgend CF34 0NW",
    "addr:postcode":"cf34 0nw",
    "addr:street":"Bridgend Road",
    "iso:country":"GB",
    "sg:address":"Cwmdu Institute, Bridgend Road",
    "sg:city":"Maesteg",
    "sg:classifiers":[
        {
            "category":"Professional",
            "subcategory":"Engineering",
            "type":"Services"
        }
    ],
    "sg:phone":"+44 1656 733455",
    "sg:postcode":"CF34 0NW",
    "sg:province":"Bridgend",
    "sg:tags":[
        "precision",
        "engineer"
    ],
    "wof:name":"Fairfield Tool & Die Co Maesteg Ltd",
    "wof:placetype":"venue"
},
  "geometry": {"coordinates":[-3.621958971,51.601360321],"type":"Point"}
}