{
  "type": "Feature",
  "properties": {
    "iso:country":"GB",
    "sg:address":"Uniy 5 42 Bayton Road, Exhall",
    "sg:city":"Coventry",
    "sg:classifiers":[
        {
            "category":"Manufacturing",
            "subcategory":"Building Materials",
            "type":"Manufacturing & Wholesale Goods"
        }
    ],
    "sg:postcode":"CV7 9EL",
    "sg:province":"Warwickshire",
    "sg:tags":[
        "tube",
        "manipulator",
        "bender"
    ],
    "wof:name":"P R G  Fabrications Ltd.",
    "wof:placetype":"venue"
},
  "geometry": {"coordinates":[-1.482574,52.465111],"type":"Point"}
}