{
  "type": "Feature",
  "properties": {
    "iso:country":"GB",
    "sg:address":"The Avenue, Burnhope",
    "sg:city":"Durham",
    "sg:classifiers":[
        {
            "category":"Bars & Pubs",
            "type":"Food & Drink"
        }
    ],
    "sg:phone":"+44 1207 529247",
    "sg:postcode":"DH7 0DB",
    "sg:province":"Durham",
    "sg:tags":[
        "pubs",
        "inn"
    ],
    "wof:name":"The Wishing Well",
    "wof:placetype":"venue"
},
  "geometry": {"coordinates":[-1.704504,54.828979],"type":"Point"}
}