{
  "type": "Feature",
  "properties": {
    "addr:full":"10-16 West Blackhall St Greenock Inverclyde PA15 1UE",
    "addr:housenumber":"10-16",
    "addr:postcode":"pa15 1ue",
    "addr:street":"West Blackhall St Greenock",
    "iso:country":"GB",
    "sg:address":"10-16 West Blackhall St",
    "sg:city":"Greenock",
    "sg:classifiers":[
        {
            "category":"Home & Garden",
            "subcategory":"Home Furnishings",
            "type":"Retail Goods"
        }
    ],
    "sg:phone":"+44 1475 728888",
    "sg:postcode":"PA15 1UE",
    "sg:province":"Inverclyde",
    "sg:tags":[
        "wall",
        "wallpaper",
        "covering"
    ],
    "wof:name":"Stanley,A G,Ltd",
    "wof:placetype":"venue"
},
  "geometry": {"coordinates":[-4.761074,55.950226],"type":"Point"}
}