{
  "type": "Feature",
  "properties": {
    "addr:full":"Bon Accord Nutts Lane Hinckley Leicestershire LE10 3EG",
    "addr:postcode":"le10 3eg",
    "addr:street":"Nutts Lane",
    "iso:country":"GB",
    "sg:address":"Bon Accord Nutts Lane",
    "sg:city":"Hinckley",
    "sg:classifiers":[
        {
            "category":"Building & Trades",
            "subcategory":"Construction",
            "type":"Services"
        }
    ],
    "sg:phone":"+44 1455 250851",
    "sg:postcode":"LE10 3EG",
    "sg:province":"Leicestershire",
    "sg:tags":[
        "fork",
        "lift",
        "truck"
    ],
    "wof:name":"ICT Services",
    "wof:placetype":"venue"
},
  "geometry": {"coordinates":[-1.372754,52.542439],"type":"Point"}
}