{
  "type": "Feature",
  "properties": {
    "addr:full":"34 Adelaide Crescent Hove East Sussex BN3 2JJ",
    "addr:housenumber":"34",
    "addr:postcode":"bn3 2jj",
    "addr:street":"Adelaide Crescent",
    "iso:country":"GB",
    "sg:address":"34 Adelaide Crescent",
    "sg:city":"Hove",
    "sg:classifiers":[
        {
            "category":"Food & Beverages",
            "subcategory":"Specialty",
            "type":"Retail Goods"
        }
    ],
    "sg:postcode":"BN3 2JJ",
    "sg:province":"East Sussex",
    "sg:tags":[
        "product",
        "health"
    ],
    "wof:name":"Vital Source",
    "wof:placetype":"venue"
},
  "geometry": {"coordinates":[-0.165148,50.824322],"type":"Point"}
}