{
  "type": "Feature",
  "properties": {
    "addr:full":"Park Rd Abingdon Oxfordshire OX14 1DA",
    "addr:postcode":"ox14 1da",
    "addr:street":"Park Rd",
    "iso:country":"GB",
    "sg:address":"Park Rd",
    "sg:city":"Abingdon",
    "sg:classifiers":[
        {
            "category":"Organizations",
            "subcategory":"Membership Organization",
            "type":"Services"
        }
    ],
    "sg:phone":"+44 1235 523470",
    "sg:postcode":"OX14 1DA",
    "sg:province":"Oxfordshire",
    "sg:tags":[
        "club"
    ],
    "wof:name":"Abingdon Youth & Community Centre",
    "wof:placetype":"venue"
},
  "geometry": {"coordinates":[-1.2867050171,51.671710968],"type":"Point"}
}