{
  "type": "Feature",
  "properties": {
    "iso:country":"GB",
    "sg:address":"20 Steppingley Road, Flitwick",
    "sg:city":"Bedford",
    "sg:classifiers":[
        {
            "category":"Education",
            "subcategory":"School",
            "type":"Public Place"
        }
    ],
    "sg:phone":"+44 1525 718866",
    "sg:postcode":"MK45 1AJ",
    "sg:province":"Bedfordshire",
    "sg:tags":[
        "independent",
        "preparatory"
    ],
    "wof:name":"Waverly Preparatory School",
    "wof:placetype":"venue"
},
  "geometry": {"coordinates":[-0.501859,52.005878],"type":"Point"}
}