{
  "type": "Feature",
  "properties": {
    "addr:full":"Pontrhondda Road Tonypandy Rhondda, Cynon, Taff CF40 2SZ",
    "addr:postcode":"cf40 2sz",
    "addr:street":"Pontrhondda Road;Cynon Taff",
    "iso:country":"GB",
    "sg:address":"Pontrhondda Road",
    "sg:city":"Tonypandy",
    "sg:classifiers":[
        {
            "category":"Education",
            "subcategory":"School",
            "type":"Public Place"
        }
    ],
    "sg:phone":"+44 1443 433004",
    "sg:postcode":"CF40 2SZ",
    "sg:province":"Rhondda, Cynon, Taff",
    "sg:tags":[
        "local",
        "authority"
    ],
    "wof:name":"Pontrhondda Primary School",
    "wof:placetype":"venue"
},
  "geometry": {"coordinates":[-3.452697,51.638962],"type":"Point"}
}