{
  "type": "Feature",
  "properties": {
    "addr:full":"22 Sheddick Court Dereham Norfolk NR19 2DT",
    "addr:housenumber":"22",
    "addr:postcode":"nr19 2dt",
    "addr:street":"Sheddick Court",
    "iso:country":"GB",
    "sg:address":"22 Sheddick Court",
    "sg:city":"Dereham",
    "sg:classifiers":[
        {
            "category":"Manufacturing",
            "subcategory":"Signs",
            "type":"Manufacturing & Wholesale Goods"
        }
    ],
    "sg:phone":"+44 1362 693945",
    "sg:postcode":"NR19 2DT",
    "sg:province":"Norfolk",
    "sg:tags":[
        "commercial",
        "maker"
    ],
    "wof:name":"The Breckland Sign Co",
    "wof:placetype":"venue"
},
  "geometry": {"coordinates":[0.937288,52.685158],"type":"Point"}
}