{
  "type": "Feature",
  "properties": {
    "addr:full":"Maypole Road East Grinstead East Sussex RH19 1HL",
    "addr:postcode":"rh19 1hl",
    "addr:street":"Maypole Road",
    "iso:country":"GB",
    "sg:address":"Maypole Road",
    "sg:city":"East Grinstead",
    "sg:classifiers":[
        {
            "category":"Professional",
            "subcategory":"Management & Consulting",
            "type":"Services"
        }
    ],
    "sg:postcode":"RH19 1HL",
    "sg:province":"East Sussex",
    "sg:tags":[
        "marketing",
        "consultant"
    ],
    "wof:name":"Tca",
    "wof:placetype":"venue"
},
  "geometry": {"coordinates":[-0.019031,51.129539],"type":"Point"}
}