{
  "type": "Feature",
  "properties": {
    "iso:country":"GB",
    "sg:address":"54 The Park, Penketh",
    "sg:city":"Warrington",
    "sg:classifiers":[
        {
            "category":"Real Estate",
            "subcategory":"Architect",
            "type":"Services"
        }
    ],
    "sg:postcode":"WA5 2SG",
    "sg:province":"Cheshire",
    "wof:name":"Forshaw Engineering Services Ltd",
    "wof:placetype":"venue"
},
  "geometry": {"coordinates":[-2.664874,53.380238],"type":"Point"}
}