{
  "type": "Feature",
  "properties": {
    "addr:full":"Offchurch House, Offchurch Leamington Spa Warwickshire CV33 9AW",
    "addr:housenumber":"offchurch",
    "addr:postcode":"cv33 9aw",
    "iso:country":"GB",
    "sg:address":"Offchurch House, Offchurch",
    "sg:city":"Leamington Spa",
    "sg:classifiers":[
        {
            "category":"Sports & Exercise",
            "subcategory":"Stables",
            "type":"Entertainment"
        }
    ],
    "sg:postcode":"CV33 9AW",
    "sg:province":"Warwickshire",
    "sg:tags":[
        "education",
        "equestrian"
    ],
    "wof:name":"Offchurch House Livery Stables",
    "wof:placetype":"venue"
},
  "geometry": {"coordinates":[-1.497549,52.240101],"type":"Point"}
}