{
  "type": "Feature",
  "properties": {
    "addr:full":"63 Holmfield Road Blackpool Lancashire FY2 9RU",
    "addr:housenumber":"63",
    "addr:postcode":"fy2 9ru",
    "addr:street":"Holmfield Road",
    "iso:country":"GB",
    "sg:address":"63 Holmfield Road",
    "sg:city":"Blackpool",
    "sg:classifiers":[
        {
            "category":"Travel",
            "subcategory":"Hotels & Motels",
            "type":"Entertainment"
        }
    ],
    "sg:phone":"+44 1253 352413",
    "sg:postcode":"FY2 9RU",
    "sg:province":"Lancashire",
    "wof:name":"Oban House Hotel",
    "wof:placetype":"venue"
},
  "geometry": {"coordinates":[-3.052124,53.836792],"type":"Point"}
}