{
  "type": "Feature",
  "properties": {
    "addr:full":"Vesta Street, Old Mill Street Manchester Greater Manchester M4 6DS",
    "addr:postcode":"m4 6ds",
    "addr:street":"Vesta Street Old Mill Street",
    "iso:country":"GB",
    "sg:address":"Vesta Street, Old Mill Street",
    "sg:city":"Manchester",
    "sg:classifiers":[
        {
            "category":"Retail",
            "subcategory":"Auto Repair",
            "type":"Services"
        }
    ],
    "sg:postcode":"M4 6DS",
    "sg:province":"Greater Manchester",
    "sg:tags":[
        "modification",
        "garage"
    ],
    "wof:name":"F  Dunn & Sons Ltd.",
    "wof:placetype":"venue"
},
  "geometry": {"coordinates":[-2.222,53.480598],"type":"Point"}
}