{
  "type": "Feature",
  "properties": {
    "iso:country":"GB",
    "sg:address":"19 Shorts Gardens",
    "sg:city":"London",
    "sg:classifiers":[
        {
            "category":"Shopping",
            "subcategory":"Gifts & Souvenirs",
            "type":"Retail Goods"
        }
    ],
    "sg:phone":"+44 20 7379 4454",
    "sg:postcode":"WC2H 9AW",
    "sg:province":"Greater London",
    "sg:tags":[
        "shop"
    ],
    "wof:name":"On Show Covent Garden Ltd.",
    "wof:placetype":"venue"
},
  "geometry": {"coordinates":[-0.126321,51.514301],"type":"Point"}
}