{
  "type": "Feature",
  "properties": {
    "iso:country":"GB",
    "sg:address":"11 Great George Street",
    "sg:city":"Bristol",
    "sg:classifiers":[
        {
            "category":"Shopping",
            "subcategory":"Books",
            "type":"Retail Goods"
        }
    ],
    "sg:postcode":"BS1 5RR",
    "sg:province":"City of Bristol",
    "sg:tags":[
        "second-hand"
    ],
    "wof:name":"David Slade Rare Books",
    "wof:placetype":"venue"
},
  "geometry": {"coordinates":[-2.603989,51.453503],"type":"Point"}
}