{
  "type": "Feature",
  "properties": {
    "addr:full":"Unit 4 Kingsdown Industrial Estate, Upper Stratton Swindon Wiltshire SN25 6PB",
    "addr:housenumber":"unit 4",
    "addr:postcode":"sn25 6pb",
    "addr:street":"Industrial Estate",
    "iso:country":"GB",
    "sg:address":"Unit 4 Kingsdown Industrial Estate, Upper Stratton",
    "sg:city":"Swindon",
    "sg:classifiers":[
        {
            "category":"Home & Garden",
            "subcategory":"Hardware",
            "type":"Retail Goods"
        }
    ],
    "sg:phone":"+44 1793 826860",
    "sg:postcode":"SN25 6PB",
    "sg:province":"Wiltshire",
    "sg:tags":[
        "equipment",
        "welding"
    ],
    "wof:name":"Allen Welding Supplies",
    "wof:placetype":"venue"
},
  "geometry": {"coordinates":[-1.7539319992,51.5966567993],"type":"Point"}
}