{
  "type": "Feature",
  "properties": {
    "iso:country":"GB",
    "sg:address":"Unit F6 Welland Industrial Estat, E Valley Way",
    "sg:city":"Market Harborough",
    "sg:classifiers":[
        {
            "category":"Professional",
            "type":"Services"
        }
    ],
    "sg:phone":"+44 1858 465049",
    "sg:postcode":"LE16 7PS",
    "sg:province":"Leicestershire",
    "sg:tags":[
        "services",
        "belt",
        "conveyor"
    ],
    "wof:name":"Okay Engineering Services Ltd.",
    "wof:placetype":"venue"
},
  "geometry": {"coordinates":[-0.922579,52.479397],"type":"Point"}
}