{
  "type": "Feature",
  "properties": {
    "addr:full":"Kathryn Avenue, Huntingdon York East Riding of Yorkshire YO3 9TG",
    "addr:postcode":"yo3 9tg",
    "addr:street":"Kathryn Avenue",
    "iso:country":"GB",
    "sg:address":"Kathryn Avenue, Huntingdon",
    "sg:city":"York",
    "sg:classifiers":[
        {
            "category":"Autos & Motor Vehicles",
            "subcategory":"Auto Supplies",
            "type":"Retail Goods"
        }
    ],
    "sg:phone":"+44 1904 615011",
    "sg:postcode":"YO3 9TG",
    "sg:province":"East Riding of Yorkshire",
    "sg:tags":[
        "tyre"
    ],
    "wof:name":"Rapid Fit",
    "wof:placetype":"venue"
},
  "geometry": {"coordinates":[-1.0834200382,53.9533309937],"type":"Point"}
}