{
  "type": "Feature",
  "properties": {
    "addr:full":"Warren Lane Stanmore Greater London HA7 4LE",
    "addr:postcode":"ha7 4le",
    "addr:street":"Warren Lane",
    "iso:country":"GB",
    "sg:address":"Warren Lane",
    "sg:city":"Stanmore",
    "sg:classifiers":[
        {
            "category":"Sports & Exercise",
            "subcategory":"Stables",
            "type":"Entertainment"
        }
    ],
    "sg:phone":"+44 20 8954 5443",
    "sg:postcode":"HA7 4LE",
    "sg:province":"Greater London",
    "sg:tags":[
        "education",
        "equestrian"
    ],
    "wof:name":"Grove Farm",
    "wof:placetype":"venue"
},
  "geometry": {"coordinates":[-0.317292,51.627815],"type":"Point"}
}