{
  "type": "Feature",
  "properties": {
    "addr:full":"2 Watermeetings Lane Stockport Cheshire SK6 4HJ",
    "addr:housenumber":"2",
    "addr:postcode":"sk6 4hj",
    "addr:street":"Watermeetings Lane",
    "iso:country":"GB",
    "sg:address":"2 Watermeetings Lane",
    "sg:city":"Stockport",
    "sg:classifiers":[
        {
            "category":"Building & Trades",
            "subcategory":"Construction",
            "type":"Services"
        }
    ],
    "sg:phone":"+44 161 449 9904",
    "sg:postcode":"SK6 4HJ",
    "sg:province":"Cheshire",
    "sg:tags":[
        "builder"
    ],
    "wof:name":"D Hough",
    "wof:placetype":"venue"
},
  "geometry": {"coordinates":[-2.0705599785,53.4122467041],"type":"Point"}
}