{
  "type": "Feature",
  "properties": {
    "iso:country":"GB",
    "sg:address":"48 Greenwood Avenue, Bolton-le-sands",
    "sg:city":"Carnforth",
    "sg:classifiers":[
        {
            "category":"Building & Trades",
            "subcategory":"Landscaping Services",
            "type":"Services"
        }
    ],
    "sg:phone":"+44 1524 823335",
    "sg:postcode":"LA5 8AW",
    "sg:province":"Cumbria",
    "sg:tags":[
        "landscape",
        "contractor"
    ],
    "wof:name":"J Ashton Landscapes",
    "wof:placetype":"venue"
},
  "geometry": {"coordinates":[-2.797535,54.095329],"type":"Point"}
}