{
  "type": "Feature",
  "properties": {
    "iso:country":"GB",
    "sg:address":"15 Eastmont Rd",
    "sg:city":"Esher",
    "sg:classifiers":[
        {
            "category":"Real Estate",
            "subcategory":"Surveying",
            "type":"Services"
        }
    ],
    "sg:phone":"+44 20 8398 6888",
    "sg:postcode":"KT10 9AY",
    "sg:province":"Surrey",
    "sg:tags":[
        "surveyor",
        "valuer"
    ],
    "wof:name":"Swire Commercial",
    "wof:placetype":"venue"
},
  "geometry": {"coordinates":[-0.3414129913,51.3777656555],"type":"Point"}
}