{
  "type": "Feature",
  "properties": {
    "iso:country":"GB",
    "sg:address":"452 Linthorpe Road",
    "sg:city":"Middlesbrough",
    "sg:classifiers":[
        {
            "category":"Food & Beverages",
            "subcategory":"Fruits & Vegetables",
            "type":"Retail Goods"
        }
    ],
    "sg:phone":"+44 1642 819985",
    "sg:postcode":"TS5 6JG",
    "sg:province":"North Yorkshire",
    "sg:tags":[
        "greengrocer"
    ],
    "wof:name":"Honeymans Fruiterers",
    "wof:placetype":"venue"
},
  "geometry": {"coordinates":[-1.242514,54.560795],"type":"Point"}
}