{
  "type": "Feature",
  "properties": {
    "addr:full":"15 Charter Place Watford Hertfordshire WD17 2RS",
    "addr:housenumber":"15",
    "addr:postcode":"wd17 2rs",
    "addr:street":"Charter Place",
    "iso:country":"GB",
    "sg:address":"15 Charter Place",
    "sg:city":"Watford",
    "sg:classifiers":[
        {
            "category":"Shopping",
            "subcategory":"Computers & Home Electronics",
            "type":"Retail Goods"
        }
    ],
    "sg:phone":"+44 1923 226169",
    "sg:postcode":"WD17 2RS",
    "sg:province":"Hertfordshire",
    "sg:tags":[
        "hi-fi",
        "centre"
    ],
    "wof:name":"Hi-Fi City Ltd.",
    "wof:placetype":"venue"
},
  "geometry": {"coordinates":[-0.396648,51.657326],"type":"Point"}
}