{
  "type": "Feature",
  "properties": {
    "addr:full":"Clavicera, Brock Hill Wickford Essex SS11 7PD",
    "addr:postcode":"ss11 7pd",
    "addr:street":"Brock Hill",
    "iso:country":"GB",
    "sg:address":"Clavicera, Brock Hill",
    "sg:city":"Wickford",
    "sg:classifiers":[
        {
            "category":"Building & Trades",
            "subcategory":"Construction",
            "type":"Services"
        }
    ],
    "sg:phone":"+44 1268 710533",
    "sg:postcode":"SS11 7PD",
    "sg:province":"Essex",
    "sg:tags":[
        "builder"
    ],
    "wof:name":"Ross Developments & Contracts",
    "wof:placetype":"venue"
},
  "geometry": {"coordinates":[0.5167,51.630161],"type":"Point"}
}