{
  "type": "Feature",
  "properties": {
    "addr:full":"Moushill Court, Lower Moushill Lane, Milford Godalming Surrey GU8 5EA",
    "addr:postcode":"gu8 5ea",
    "addr:street":"Lower Moushill Lane",
    "iso:country":"GB",
    "sg:address":"Moushill Court, Lower Moushill Lane, Milford",
    "sg:city":"Godalming",
    "sg:classifiers":[
        {
            "category":"Wholesale",
            "subcategory":"Toys & Hobbies",
            "type":"Manufacturing & Wholesale Goods"
        }
    ],
    "sg:phone":"+44 1483 417357",
    "sg:postcode":"GU8 5EA",
    "sg:province":"Surrey",
    "sg:tags":[
        "game"
    ],
    "wof:name":"Elizabeth Designs",
    "wof:placetype":"venue"
},
  "geometry": {"coordinates":[-0.6516799927,51.1723098755],"type":"Point"}
}