{
  "type": "Feature",
  "properties": {
    "addr:full":"Unit 1 Cronin Rd, Weldon South Industrial Est Corby Northamptonshire NN18 8AQ",
    "addr:housenumber":"unit 1",
    "addr:postcode":"nn18 8aq",
    "addr:street":"Cronin Rd;Est",
    "iso:country":"GB",
    "sg:address":"Unit 1 Cronin Rd, Weldon South Industrial Est",
    "sg:city":"Corby",
    "sg:classifiers":[
        {
            "category":"Manufacturing",
            "subcategory":"Wood Products",
            "type":"Manufacturing & Wholesale Goods"
        },
        {
            "category":"Home & Garden",
            "subcategory":"Home Furnishings",
            "type":"Retail Goods"
        }
    ],
    "sg:phone":"+44 1536 264544",
    "sg:postcode":"NN18 8AQ",
    "sg:province":"Northamptonshire",
    "sg:tags":[
        "furnishers",
        "planner",
        "maker",
        "kitchen",
        "cabinet"
    ],
    "wof:name":"Pullman Furniture Ltd",
    "wof:placetype":"venue"
},
  "geometry": {"coordinates":[-0.6557840109,52.4937858582],"type":"Point"}
}