{
  "type": "Feature",
  "properties": {
    "iso:country":"GB",
    "sg:address":"1 Bryn Clywedog, Coedpoeth",
    "sg:city":"Wrexham",
    "sg:classifiers":[
        {
            "category":"Bus Charters",
            "type":"Transportation"
        }
    ],
    "sg:phone":"+44 1978 720366",
    "sg:postcode":"LL11 3SR",
    "sg:province":"Wrexham",
    "sg:tags":[
        "hire",
        "coach"
    ],
    "wof:name":"M & R Minibuses",
    "wof:placetype":"venue"
},
  "geometry": {"coordinates":[-3.065696,53.055458],"type":"Point"}
}