{
  "type": "Feature",
  "properties": {
    "addr:full":"35 Salisbury Street Blandford Forum Dorset DT11 7AY",
    "addr:housenumber":"35",
    "addr:postcode":"dt11 7ay",
    "addr:street":"Salisbury Street",
    "iso:country":"GB",
    "sg:address":"35 Salisbury Street",
    "sg:city":"Blandford Forum",
    "sg:classifiers":[
        {
            "category":"Personal",
            "subcategory":"Beauty Salon",
            "type":"Services"
        }
    ],
    "sg:postcode":"DT11 7AY",
    "sg:province":"Dorset",
    "sg:tags":[
        "unisex",
        "hairdresser"
    ],
    "wof:name":"Hairtique",
    "wof:placetype":"venue"
},
  "geometry": {"coordinates":[-2.165175,50.857143],"type":"Point"}
}