{
  "type": "Feature",
  "properties": {
    "iso:country":"GB",
    "sg:address":"37 Reading Road, Pangbourne",
    "sg:city":"Reading",
    "sg:classifiers":[
        {
            "category":"Real Estate",
            "subcategory":"Real Estate Operator",
            "type":"Services"
        },
        {
            "category":"Real Estate",
            "subcategory":"Real Estate Agent",
            "type":"Services"
        }
    ],
    "sg:phone":"+44 118 984 4444",
    "sg:postcode":"RG8 7HY",
    "sg:province":"Berkshire",
    "sg:tags":[
        "letting"
    ],
    "wof:name":"Patrick Williams",
    "wof:placetype":"venue"
},
  "geometry": {"coordinates":[-1.083554,51.483631],"type":"Point"}
}