{
  "type": "Feature",
  "properties": {
    "addr:full":"91 Brixton Road London Greater London SW9 6EE",
    "addr:housenumber":"91",
    "addr:postcode":"sw9 6ee",
    "addr:street":"Brixton Road",
    "iso:country":"GB",
    "sg:address":"91 Brixton Road",
    "sg:city":"London",
    "sg:classifiers":[
        {
            "category":"Health Services",
            "subcategory":"Nursing And Care Facility",
            "type":"Services"
        },
        {
            "category":"Government",
            "subcategory":"Office",
            "type":"Public Place"
        }
    ],
    "sg:phone":"+44 20 7820 3494",
    "sg:postcode":"SW9 6EE",
    "sg:province":"Greater London",
    "sg:tags":[
        "residential",
        "local"
    ],
    "wof:name":"Holland Town Tenant Management Co-Operative Ltd",
    "wof:placetype":"venue"
},
  "geometry": {"coordinates":[-0.1119979993,51.4783325195],"type":"Point"}
}