{
  "type": "Feature",
  "properties": {
    "iso:country":"GB",
    "sg:address":"Linden Mill, Linden Road",
    "sg:city":"Hebden Bridge",
    "sg:classifiers":[
        {
            "category":"Professional",
            "type":"Services"
        }
    ],
    "sg:postcode":"HX7 7DN",
    "sg:province":"West Yorkshire",
    "sg:tags":[
        "interior",
        "furnishers",
        "designer"
    ],
    "wof:name":"Innerspace",
    "wof:placetype":"venue"
},
  "geometry": {"coordinates":[-2.0144910812,53.7412261963],"type":"Point"}
}