{
  "type": "Feature",
  "properties": {
    "addr:full":"16 Belmont Street Bristol City of Bristol BS5 0NQ",
    "addr:housenumber":"16",
    "addr:postcode":"bs5 0nq",
    "addr:street":"Belmont Street",
    "iso:country":"GB",
    "sg:address":"16 Belmont Street",
    "sg:city":"Bristol",
    "sg:classifiers":[
        {
            "category":"Building & Trades",
            "subcategory":"Cleaning & Sanitation",
            "type":"Services"
        }
    ],
    "sg:phone":"+44 117 951 3888",
    "sg:postcode":"BS5 0NQ",
    "sg:province":"City of Bristol",
    "sg:tags":[
        "commercial"
    ],
    "wof:name":"D & E Industrial Cleaning Ltd.",
    "wof:placetype":"venue"
},
  "geometry": {"coordinates":[-2.5676929951,51.4667930603],"type":"Point"}
}