{
  "type": "Feature",
  "properties": {
    "iso:country":"GB",
    "sg:address":"The Park Gallery, Station Road, Chobham",
    "sg:city":"Woking",
    "sg:classifiers":[
        {
            "category":"Building & Trades",
            "subcategory":"Construction",
            "type":"Services"
        }
    ],
    "sg:postcode":"GU24 9AQ",
    "sg:province":"Surrey",
    "sg:tags":[
        "platform",
        "work",
        "scaffolding"
    ],
    "wof:name":"G A P Scaffolding Ltd.",
    "wof:placetype":"venue"
},
  "geometry": {"coordinates":[-0.640877,51.327488],"type":"Point"}
}