{
  "type": "Feature",
  "properties": {
    "addr:full":"New Street Dunmow Essex CM6 3AT",
    "addr:postcode":"cm6 3at",
    "addr:street":"New Street",
    "iso:country":"GB",
    "sg:address":"New Street",
    "sg:city":"Dunmow",
    "sg:classifiers":[
        {
            "category":"Government",
            "subcategory":"Office",
            "type":"Public Place"
        }
    ],
    "sg:phone":"+44 1371 872854",
    "sg:postcode":"CM6 3AT",
    "sg:province":"Essex",
    "sg:tags":[
        "education",
        "agency",
        "authority"
    ],
    "wof:name":"Lipman Ida",
    "wof:placetype":"venue"
},
  "geometry": {"coordinates":[0.363491,51.870476],"type":"Point"}
}