{
  "type": "Feature",
  "properties": {
    "addr:full":"Old Dairy Yard, Shorts Road Carshalton Surrey SM5 2PB",
    "addr:postcode":"sm5 2pb",
    "addr:street":"Old;Shorts Road",
    "iso:country":"GB",
    "sg:address":"Old Dairy Yard, Shorts Road",
    "sg:city":"Carshalton",
    "sg:classifiers":[
        {
            "category":"Retail",
            "subcategory":"Auto Repair",
            "type":"Services"
        }
    ],
    "sg:postcode":"SM5 2PB",
    "sg:province":"Surrey",
    "sg:tags":[
        "modification",
        "garage"
    ],
    "wof:name":"Reliable Auto Care",
    "wof:placetype":"venue"
},
  "geometry": {"coordinates":[-0.161094,51.365288],"type":"Point"}
}