{
  "type": "Feature",
  "properties": {
    "addr:full":"Shaws Lane, Eccleshall Stafford Staffordshire ST21 6AU",
    "addr:postcode":"st21 6au",
    "addr:street":"Shaws Lane",
    "iso:country":"GB",
    "sg:address":"Shaws Lane, Eccleshall",
    "sg:city":"Stafford",
    "sg:classifiers":[
        {
            "category":"Education",
            "subcategory":"School",
            "type":"Public Place"
        }
    ],
    "sg:phone":"+44 1785 850388",
    "sg:postcode":"ST21 6AU",
    "sg:province":"Staffordshire",
    "sg:tags":[
        "local",
        "authority"
    ],
    "wof:name":"The Lonsdale C of E Primary School",
    "wof:placetype":"venue"
},
  "geometry": {"coordinates":[-2.2514541149,52.859287262],"type":"Point"}
}