{
  "type": "Feature",
  "properties": {
    "iso:country":"GB",
    "sg:address":"1 Coxwell St",
    "sg:city":"Cirencester",
    "sg:classifiers":[
        {
            "category":"Place Of Worship",
            "type":"Public Place"
        }
    ],
    "sg:phone":"+44 1285 659317",
    "sg:postcode":"GL7 2BQ",
    "sg:province":"Gloucestershire",
    "wof:name":"Parish Office",
    "wof:placetype":"venue"
},
  "geometry": {"coordinates":[-1.9694440365,51.7182998657],"type":"Point"}
}