{
  "type": "Feature",
  "properties": {
    "addr:full":"5 Castle Road, Kirby, Muxlowe Leicester Leicestershire LE9 2AB",
    "addr:housenumber":"5",
    "addr:postcode":"le9 2ab",
    "addr:street":"Castle Road;Muxlowe",
    "iso:country":"GB",
    "sg:address":"5 Castle Road, Kirby, Muxlowe",
    "sg:city":"Leicester",
    "sg:classifiers":[
        {
            "category":"Manufacturing",
            "subcategory":"Rubber & Plastics",
            "type":"Manufacturing & Wholesale Goods"
        }
    ],
    "sg:phone":"+44 116 239 3280",
    "sg:postcode":"LE9 2AB",
    "sg:province":"Leicestershire",
    "sg:tags":[
        "supplier",
        "stockist"
    ],
    "wof:name":"Maurice Bradley",
    "wof:placetype":"venue"
},
  "geometry": {"coordinates":[-1.235194,52.634304],"type":"Point"}
}