{
  "type": "Feature",
  "properties": {
    "addr:full":"22 Sterndale Road Sheffield South Yorkshire S7 2LB",
    "addr:housenumber":"22",
    "addr:postcode":"s7 2lb",
    "addr:street":"Sterndale Road",
    "iso:country":"GB",
    "sg:address":"22 Sterndale Road",
    "sg:city":"Sheffield",
    "sg:classifiers":[
        {
            "category":"Professional",
            "subcategory":"Computer Services",
            "type":"Services"
        }
    ],
    "sg:phone":"+44 114 249 3102",
    "sg:postcode":"S7 2LB",
    "sg:province":"South Yorkshire",
    "sg:tags":[
        "system",
        "software"
    ],
    "wof:name":"J N R Website Design Ltd.",
    "wof:placetype":"venue"
},
  "geometry": {"coordinates":[-1.4995570183,53.3453865051],"type":"Point"}
}