{
  "type": "Feature",
  "properties": {
    "addr:full":"Tettenhall Road Wolverhampton Shropshire WV6 0BY",
    "addr:postcode":"wv6 0by",
    "addr:street":"Tettenhall Road",
    "iso:country":"GB",
    "sg:address":"Tettenhall Road",
    "sg:city":"Wolverhampton",
    "sg:classifiers":[
        {
            "category":"Education",
            "subcategory":"School",
            "type":"Public Place"
        }
    ],
    "sg:phone":"+44 1902 312186",
    "sg:postcode":"WV6 0BY",
    "sg:province":"Shropshire",
    "sg:tags":[
        "college"
    ],
    "wof:name":"Wolverhampton Girl's High School",
    "wof:placetype":"venue"
},
  "geometry": {"coordinates":[-2.159634,52.596859],"type":"Point"}
}