{
  "type": "Feature",
  "properties": {
    "addr:full":"Pulnix House, Aviary Court, Wade Road Basingstoke Hampshire RG24 8PE",
    "addr:postcode":"rg24 8pe",
    "addr:street":"Aviary Court Wade Road",
    "iso:country":"GB",
    "sg:address":"Pulnix House, Aviary Court, Wade Road",
    "sg:city":"Basingstoke",
    "sg:classifiers":[
        {
            "category":"Professional",
            "subcategory":"Detective & Security Services",
            "type":"Services"
        }
    ],
    "sg:phone":"+44 1256 475555",
    "sg:postcode":"RG24 8PE",
    "sg:province":"Hampshire",
    "sg:tags":[
        "equipment"
    ],
    "wof:name":"Takex Europe Ltd.",
    "wof:placetype":"venue"
},
  "geometry": {"coordinates":[-1.062665,51.283726],"type":"Point"}
}