{
  "type": "Feature",
  "properties": {
    "addr:full":"51 Calverley Road Tunbridge Wells Kent TN1 2TT",
    "addr:housenumber":"51",
    "addr:postcode":"tn1 2tt",
    "addr:street":"Calverley Road",
    "iso:country":"GB",
    "sg:address":"51 Calverley Road",
    "sg:city":"Tunbridge Wells",
    "sg:classifiers":[
        {
            "category":"Shopping",
            "subcategory":"Mobile Phones",
            "type":"Retail Goods"
        }
    ],
    "sg:phone":"+44 1892 516565",
    "sg:postcode":"TN1 2TT",
    "sg:province":"Kent",
    "wof:name":"M O C O",
    "wof:placetype":"venue"
},
  "geometry": {"coordinates":[0.2683899999,51.1327781677],"type":"Point"}
}