{
  "type": "Feature",
  "properties": {
    "addr:full":"159 Northfield Avenue London Greater London W13 9QT",
    "addr:housenumber":"159",
    "addr:postcode":"w13 9qt",
    "addr:street":"Northfield Avenue",
    "iso:country":"GB",
    "sg:address":"159 Northfield Avenue",
    "sg:city":"London",
    "sg:classifiers":[
        {
            "category":"Shopping",
            "subcategory":"Florist",
            "type":"Retail Goods"
        }
    ],
    "sg:postcode":"W13 9QT",
    "sg:province":"Greater London",
    "wof:name":"Flowers by Valerie",
    "wof:placetype":"venue"
},
  "geometry": {"coordinates":[-0.316091001,51.5023612976],"type":"Point"}
}