{
  "type": "Feature",
  "properties": {
    "addr:full":"Clerk & Superintendant Office, 14-18 Allen House, 23 Sherrin Road London Greater London E10 5SQ",
    "addr:housenumber":"14-18;23",
    "addr:postcode":"e10 5sq",
    "addr:street":"Allen;Sherrin Road",
    "iso:country":"GB",
    "sg:address":"Clerk & Superintendant Office, 14-18 Allen House, 23 Sherrin Road",
    "sg:city":"London",
    "sg:classifiers":[
        {
            "category":"Wholesale",
            "subcategory":"Fruits & Vegetables",
            "type":"Manufacturing & Wholesale Goods"
        },
        {
            "category":"Government",
            "subcategory":"Office",
            "type":"Public Place"
        }
    ],
    "sg:phone":"+44 20 8518 7670",
    "sg:postcode":"E10 5SQ",
    "sg:province":"Greater London",
    "sg:tags":[
        "local"
    ],
    "wof:name":"New Spitalfields Market",
    "wof:placetype":"venue"
},
  "geometry": {"coordinates":[-0.0176190007,51.5551948547],"type":"Point"}
}