{
  "type": "Feature",
  "properties": {
    "iso:country":"GB",
    "sg:address":"11 The Mall, Arndale Centre, Stretford Square",
    "sg:city":"Manchester",
    "sg:classifiers":[
        {
            "category":"Home & Garden",
            "subcategory":"Household Appliances",
            "type":"Retail Goods"
        }
    ],
    "sg:phone":"+44 161 865 0711",
    "sg:postcode":"M32 9BA",
    "sg:province":"Cheshire",
    "sg:tags":[
        "electrical",
        "domestic"
    ],
    "wof:name":"Dixons Ltd",
    "wof:placetype":"venue"
},
  "geometry": {"coordinates":[-2.313732,53.445087],"type":"Point"}
}