{
  "type": "Feature",
  "properties": {
    "iso:country":"GB",
    "sg:address":"65 Goldhawk Road",
    "sg:city":"London",
    "sg:classifiers":[
        {
            "category":"Communications",
            "type":"Services"
        }
    ],
    "sg:phone":"+44 20 8743 5100",
    "sg:postcode":"W12 8EG",
    "sg:province":"Greater London",
    "sg:tags":[
        "audio-visual"
    ],
    "wof:name":"Simon Holland Ltd.",
    "wof:placetype":"venue"
},
  "geometry": {"coordinates":[-0.2270019948,51.5022277832],"type":"Point"}
}