{
  "type": "Feature",
  "properties": {
    "addr:full":"36 Gloucester Rd Bournemouth Dorset BH7 6HZ",
    "addr:housenumber":"36",
    "addr:postcode":"bh7 6hz",
    "addr:street":"Gloucester Rd",
    "iso:country":"GB",
    "sg:address":"36 Gloucester Rd",
    "sg:city":"Bournemouth",
    "sg:classifiers":[
        {
            "category":"Shopping",
            "subcategory":"Stationery & Office Supplies",
            "type":"Retail Goods"
        }
    ],
    "sg:phone":"+44 1202 392337",
    "sg:postcode":"BH7 6HZ",
    "sg:province":"Dorset",
    "sg:tags":[
        "mobile",
        "catering"
    ],
    "wof:name":"Turnburg Fast Food Catering",
    "wof:placetype":"venue"
},
  "geometry": {"coordinates":[-1.832575,50.729946],"type":"Point"}
}