{
  "type": "Feature",
  "properties": {
    "iso:country":"GB",
    "sg:address":"35 Rosebery Rd",
    "sg:city":"Chelmsford",
    "sg:classifiers":[
        {
            "category":"Professional",
            "subcategory":"Management & Consulting",
            "type":"Services"
        }
    ],
    "sg:phone":"+44 1245 346387",
    "sg:postcode":"CM2 0TU",
    "sg:province":"Essex",
    "sg:tags":[
        "marketing",
        "consultant"
    ],
    "wof:name":"Lexicon Marketing",
    "wof:placetype":"venue"
},
  "geometry": {"coordinates":[0.473126,51.725124],"type":"Point"}
}