{
  "type": "Feature",
  "properties": {
    "iso:country":"GB",
    "sg:address":"Malden Lodge, Crawley Ridge",
    "sg:city":"Camberley",
    "sg:classifiers":[
        {
            "category":"Professional",
            "subcategory":"Management & Consulting",
            "type":"Services"
        }
    ],
    "sg:postcode":"GU15 2AD",
    "sg:province":"Berkshire",
    "sg:tags":[
        "marketing",
        "consultant"
    ],
    "wof:name":"Rod Brassington",
    "wof:placetype":"venue"
},
  "geometry": {"coordinates":[-0.73423,51.336216],"type":"Point"}
}