{
  "type": "Feature",
  "properties": {
    "iso:country":"GB",
    "sg:address":"New Barn Farm, Harrop Grn, Diggle",
    "sg:city":"Oldham",
    "sg:classifiers":[
        {
            "category":"Travel",
            "subcategory":"Hotels & Motels",
            "type":"Entertainment"
        }
    ],
    "sg:postcode":"OL3 5LW",
    "sg:province":"Lancashire",
    "sg:tags":[
        "house",
        "guest"
    ],
    "wof:name":"A & D Rhodes",
    "wof:placetype":"venue"
},
  "geometry": {"coordinates":[-2.0430140495,53.5768661499],"type":"Point"}
}