{
  "type": "Feature",
  "properties": {
    "addr:full":"2nd Floor St Albans Ho, 181 The Parade, High St Watford Hertfordshire WD1 1NJ",
    "addr:housenumber":"2nd floor;181",
    "addr:postcode":"wd1 1nj",
    "addr:street":"St;The Parade High St",
    "iso:country":"GB",
    "sg:address":"2nd Floor St Albans Ho, 181 The Parade, High St",
    "sg:city":"Watford",
    "sg:classifiers":[
        {
            "category":"Health Services",
            "subcategory":"Clinic",
            "type":"Services"
        }
    ],
    "sg:phone":"+44 1923 221037",
    "sg:postcode":"WD1 1NJ",
    "sg:province":"Hertfordshire",
    "sg:tags":[
        "misuse",
        "alcohol"
    ],
    "wof:name":"Alcohol Advice Centre",
    "wof:placetype":"venue"
},
  "geometry": {"coordinates":[-0.39072,51.652119],"type":"Point"}
}