{
  "type": "Feature",
  "properties": {
    "addr:full":"36 Sheep Street Shipston-on-stour Warwickshire CV36 4AF",
    "addr:housenumber":"36",
    "addr:postcode":"cv36 4af",
    "addr:street":"Sheep Street",
    "iso:country":"GB",
    "sg:address":"36 Sheep Street",
    "sg:city":"Shipston-on-stour",
    "sg:classifiers":[
        {
            "category":"Food & Beverages",
            "subcategory":"Specialty",
            "type":"Retail Goods"
        }
    ],
    "sg:phone":"+44 1608 664116",
    "sg:postcode":"CV36 4AF",
    "sg:province":"Warwickshire",
    "sg:tags":[
        "retailer",
        "product",
        "health"
    ],
    "wof:name":"Ruperts Health Foods",
    "wof:placetype":"venue"
},
  "geometry": {"coordinates":[-1.625745,52.063374],"type":"Point"}
}