{
  "type": "Feature",
  "properties": {
    "addr:full":"High Street Cinderford Gloucestershire GL14 2SU",
    "addr:postcode":"gl14 2su",
    "addr:street":"High Street",
    "iso:country":"GB",
    "sg:address":"High Street",
    "sg:city":"Cinderford",
    "sg:classifiers":[
        {
            "category":"Communications",
            "subcategory":"Newspaper",
            "type":"Services"
        }
    ],
    "sg:phone":"+44 1594 823166",
    "sg:postcode":"GL14 2SU",
    "sg:province":"Gloucestershire",
    "sg:tags":[
        "magazine"
    ],
    "wof:name":"Gloucestershire Newspapers Ltd.",
    "wof:placetype":"venue"
},
  "geometry": {"coordinates":[-2.504475,51.829868],"type":"Point"}
}