{
  "type": "Feature",
  "properties": {
    "addr:full":"13 Manor Pde Salvington Rd Worthing West Sussex BN13 2JP",
    "addr:housenumber":"13",
    "addr:postcode":"bn13 2jp",
    "addr:street":"Manor Pde Salvington Rd",
    "iso:country":"GB",
    "sg:address":"13 Manor Pde Salvington Rd",
    "sg:city":"Worthing",
    "sg:classifiers":[
        {
            "category":"Fast Food",
            "type":"Food & Drink"
        }
    ],
    "sg:postcode":"BN13 2JP",
    "sg:province":"West Sussex",
    "sg:tags":[
        "away",
        "take"
    ],
    "wof:name":"Domino's Pizza",
    "wof:placetype":"venue"
},
  "geometry": {"coordinates":[-0.4002160132,50.8349151611],"type":"Point"}
}