{
  "type": "Feature",
  "properties": {
    "iso:country":"GB",
    "sg:address":"Waverley Terminal, 36 Lancefield Quay",
    "sg:city":"Glasgow",
    "sg:classifiers":[
        {
            "category":"Freight",
            "type":"Transportation"
        },
        {
            "category":"Landmark",
            "subcategory":"Tourist Information",
            "type":"Public Place"
        }
    ],
    "sg:phone":"+44 141 243 2224",
    "sg:postcode":"G3 8HA",
    "sg:province":"Glasgow City",
    "sg:tags":[
        "tour",
        "guide",
        "shipping",
        "sightseeing"
    ],
    "wof:name":"Waverley Excursions Ltd.",
    "wof:placetype":"venue"
},
  "geometry": {"coordinates":[-4.2755,55.856991],"type":"Point"}
}