{
  "type": "Feature",
  "properties": {
    "addr:full":"Osman Terrace, Sedgeletch Road Houghton-le-spring Durham DH4 5NQ",
    "addr:postcode":"dh4 5nq",
    "addr:street":"Osman Terrace Sedgeletch Road",
    "iso:country":"GB",
    "sg:address":"Osman Terrace, Sedgeletch Road",
    "sg:city":"Houghton-le-spring",
    "sg:classifiers":[
        {
            "category":"Social Services",
            "subcategory":"Retirement Home",
            "type":"Services"
        }
    ],
    "sg:phone":"+44 191 385 8306",
    "sg:postcode":"DH4 5NQ",
    "sg:province":"Durham",
    "sg:tags":[
        "residential",
        "care"
    ],
    "wof:name":"Braeside",
    "wof:placetype":"venue"
},
  "geometry": {"coordinates":[-1.495819,54.849499],"type":"Point"}
}