{
  "type": "Feature",
  "properties": {
    "iso:country":"GB",
    "sg:address":"3 Altway",
    "sg:city":"Liverpool",
    "sg:classifiers":[
        {
            "category":"Food & Beverages",
            "subcategory":"Liquor & Beverages",
            "type":"Retail Goods"
        }
    ],
    "sg:phone":"+44 151 520 0881",
    "sg:postcode":"L10 3JA",
    "sg:province":"Merseyside",
    "sg:tags":[
        "beer",
        "wine",
        "spirit",
        "wines"
    ],
    "wof:name":"Victoria Wine",
    "wof:placetype":"venue"
},
  "geometry": {"coordinates":[-2.949327,53.485924],"type":"Point"}
}