{
  "type": "Feature",
  "properties": {
    "addr:full":"51 Halfmoon Lane Dunstable Bedfordshire LU5 4AB",
    "addr:housenumber":"51",
    "addr:postcode":"lu5 4ab",
    "addr:street":"Halfmoon Lane",
    "iso:country":"GB",
    "sg:address":"51 Halfmoon Lane",
    "sg:city":"Dunstable",
    "sg:classifiers":[
        {
            "category":"Building & Trades",
            "subcategory":"Landscaping Services",
            "type":"Services"
        }
    ],
    "sg:postcode":"LU5 4AB",
    "sg:province":"Bedfordshire",
    "sg:tags":[
        "landscape",
        "contractor"
    ],
    "wof:name":"Brian Evans",
    "wof:placetype":"venue"
},
  "geometry": {"coordinates":[-0.5054939985,51.882484436],"type":"Point"}
}