{
  "type": "Feature",
  "properties": {
    "addr:full":"3 Clifton Villas Bradford West Yorkshire BD8 7BY",
    "addr:housenumber":"3",
    "addr:postcode":"bd8 7by",
    "addr:street":"Clifton Villas",
    "iso:country":"GB",
    "sg:address":"3 Clifton Villas",
    "sg:city":"Bradford",
    "sg:classifiers":[
        {
            "category":"Professional",
            "subcategory":"Engineering",
            "type":"Services"
        }
    ],
    "sg:phone":"+44 1274 200108",
    "sg:postcode":"BD8 7BY",
    "sg:province":"West Yorkshire",
    "sg:tags":[
        "consultant",
        "structural"
    ],
    "wof:name":"Tony Oates Associates",
    "wof:placetype":"venue"
},
  "geometry": {"coordinates":[-1.7636350393,53.8061256409],"type":"Point"}
}