{
  "type": "Feature",
  "properties": {
    "addr:full":"41 Church Road Southport Lancashire PR9 8ET",
    "addr:housenumber":"41",
    "addr:postcode":"pr9 8et",
    "addr:street":"Church Road",
    "iso:country":"GB",
    "sg:address":"41 Church Road",
    "sg:city":"Southport",
    "sg:classifiers":[
        {
            "category":"Health Services",
            "subcategory":"Nursing And Care Facility",
            "type":"Services"
        }
    ],
    "sg:phone":"+44 1704 220061",
    "sg:postcode":"PR9 8ET",
    "sg:province":"Lancashire",
    "sg:tags":[
        "home"
    ],
    "sg:website":"http://www.craegmoor.co.uk",
    "wof:name":"Village Nursing Home",
    "wof:placetype":"venue"
},
  "geometry": {"coordinates":[-2.9181349277,53.6818847656],"type":"Point"}
}