{
  "type": "Feature",
  "properties": {
    "iso:country":"GB",
    "sg:address":"Sutton Bank",
    "sg:city":"Thirsk",
    "sg:classifiers":[
        {
            "category":"Bars & Pubs",
            "type":"Food & Drink"
        }
    ],
    "sg:postcode":"YO7 2HA",
    "sg:province":"North Yorkshire",
    "sg:tags":[
        "pubs",
        "inn"
    ],
    "wof:name":"Hambleton Inn",
    "wof:placetype":"venue"
},
  "geometry": {"coordinates":[-1.321549058,54.2350616455],"type":"Point"}
}