{
  "type": "Feature",
  "properties": {
    "iso:country":"GB",
    "sg:address":"Droylsden Road, Newton Heath",
    "sg:city":"Manchester",
    "sg:classifiers":[
        {
            "category":"Education",
            "subcategory":"Preschool",
            "type":"Public Place"
        }
    ],
    "sg:phone":"+44 161 682 2882",
    "sg:postcode":"M34 5SJ",
    "sg:province":"Greater Manchester",
    "sg:tags":[
        "pre-school",
        "playgroups"
    ],
    "wof:name":"Brookdale Park Beehive",
    "wof:placetype":"venue"
},
  "geometry": {"coordinates":[-2.140259,53.479111],"type":"Point"}
}