{
  "type": "Feature",
  "properties": {
    "iso:country":"GB",
    "sg:address":"18 Kenchester Clo",
    "sg:city":"Redditch",
    "sg:classifiers":[
        {
            "category":"Professional",
            "subcategory":"Detective & Security Services",
            "type":"Services"
        }
    ],
    "sg:phone":"+44 1527 529050",
    "sg:postcode":"B98 0BT",
    "sg:province":"Warwickshire",
    "sg:tags":[
        "alarm",
        "burglar",
        "system"
    ],
    "wof:name":"E S T Alarms",
    "wof:placetype":"venue"
},
  "geometry": {"coordinates":[-1.89147,52.298042],"type":"Point"}
}