{
  "type": "Feature",
  "properties": {
    "addr:full":"89 Cardiff Road Cardiff Caerphilly CF15 7PL",
    "addr:housenumber":"89",
    "addr:postcode":"cf15 7pl",
    "addr:street":"Cardiff Road",
    "iso:country":"GB",
    "sg:address":"89 Cardiff Road",
    "sg:city":"Cardiff",
    "sg:classifiers":[
        {
            "category":"Social Services",
            "subcategory":"Child Care",
            "type":"Services"
        }
    ],
    "sg:phone":"+44 29 2081 1344",
    "sg:postcode":"CF15 7PL",
    "sg:province":"Caerphilly",
    "sg:tags":[
        "children's",
        "home"
    ],
    "wof:name":"Pathway Care One Ltd.",
    "wof:placetype":"venue"
},
  "geometry": {"coordinates":[-3.2686319351,51.5437469482],"type":"Point"}
}