{
  "type": "Feature",
  "properties": {
    "addr:full":"6 Cluntergate, Horbury Wakefield West Yorkshire WF4 5AG",
    "addr:housenumber":"6",
    "addr:postcode":"wf4 5ag",
    "addr:street":"Cluntergate Horbury",
    "iso:country":"GB",
    "sg:address":"6 Cluntergate, Horbury",
    "sg:city":"Wakefield",
    "sg:classifiers":[
        {
            "category":"Fast Food",
            "type":"Food & Drink"
        }
    ],
    "sg:phone":"+44 1924 262627",
    "sg:postcode":"WF4 5AG",
    "sg:province":"West Yorkshire",
    "sg:tags":[
        "away",
        "meal",
        "outlet",
        "take"
    ],
    "wof:name":"Pizza Pranzo",
    "wof:placetype":"venue"
},
  "geometry": {"coordinates":[-1.553157,53.659203],"type":"Point"}
}