{
  "type": "Feature",
  "properties": {
    "addr:full":"2 Ravensdale Av North Finchley Greater London N12 9HS",
    "addr:housenumber":"2",
    "addr:postcode":"n12 9hs",
    "addr:street":"Ravensdale Av",
    "iso:country":"GB",
    "sg:address":"2 Ravensdale Av",
    "sg:city":"North Finchley",
    "sg:classifiers":[
        {
            "category":"Health Services",
            "subcategory":"Dentist",
            "type":"Services"
        }
    ],
    "sg:phone":"+44 20 8445 4579",
    "sg:postcode":"N12 9HS",
    "sg:province":"Greater London",
    "wof:name":"M Alexander",
    "wof:placetype":"venue"
},
  "geometry": {"coordinates":[-0.1760620028,51.6180915833],"type":"Point"}
}