{
  "type": "Feature",
  "properties": {
    "addr:full":"18-20 Millers Hill, Herrington Burn Houghton-le-spring Durham DH4 7AJ",
    "addr:housenumber":"18-20",
    "addr:postcode":"dh4 7aj",
    "addr:street":"Millers Hill",
    "iso:country":"GB",
    "sg:address":"18-20 Millers Hill, Herrington Burn",
    "sg:city":"Houghton-le-spring",
    "sg:classifiers":[
        {
            "category":"Utilities",
            "subcategory":"Natural Gas",
            "type":"Services"
        }
    ],
    "sg:postcode":"DH4 7AJ",
    "sg:province":"Durham",
    "sg:tags":[
        "supplier"
    ],
    "wof:name":"Cairns Heatway Ltd.",
    "wof:placetype":"venue"
},
  "geometry": {"coordinates":[-1.484777,54.866867],"type":"Point"}
}