{
  "type": "Feature",
  "properties": {
    "iso:country":"GB",
    "sg:address":"Unit 6/7, Hale Trading Estate, Lower Church Lane",
    "sg:city":"Tipton",
    "sg:classifiers":[
        {
            "category":"Home & Garden",
            "subcategory":"Building Materials",
            "type":"Retail Goods"
        },
        {
            "category":"Home & Garden",
            "subcategory":"Hardware",
            "type":"Retail Goods"
        }
    ],
    "sg:phone":"+44 121 520 5346",
    "sg:postcode":"DY4 7PQ",
    "sg:province":"West Midlands",
    "sg:tags":[
        "furnishers",
        "bathroom",
        "planner",
        "fitting",
        "equipment"
    ],
    "wof:name":"Water Front Ltd.",
    "wof:placetype":"venue"
},
  "geometry": {"coordinates":[-2.050087,52.529575],"type":"Point"}
}