{
  "type": "Feature",
  "properties": {
    "iso:country":"GB",
    "sg:address":"15 St Helen's Place",
    "sg:city":"London",
    "sg:classifiers":[
        {
            "category":"Professional",
            "subcategory":"Employment Agencies",
            "type":"Services"
        }
    ],
    "sg:phone":"+44 20 7860 2222",
    "sg:postcode":"EC3A 6DE",
    "sg:province":"Greater London",
    "sg:tags":[
        "consultant"
    ],
    "wof:name":"The Kennedy Partnership Ltd.",
    "wof:placetype":"venue"
},
  "geometry": {"coordinates":[-0.08119,51.515179],"type":"Point"}
}