{
  "type": "Feature",
  "properties": {
    "addr:full":"5 Frederick Place Weymouth Dorset DT4 8HQ",
    "addr:housenumber":"5",
    "addr:postcode":"dt4 8hq",
    "addr:street":"Frederick Place",
    "iso:country":"GB",
    "sg:address":"5 Frederick Place",
    "sg:city":"Weymouth",
    "sg:classifiers":[
        {
            "category":"Shopping",
            "subcategory":"Hobbies, Toys, & Games",
            "type":"Retail Goods"
        }
    ],
    "sg:phone":"+44 1305 779255",
    "sg:postcode":"DT4 8HQ",
    "sg:province":"Dorset",
    "sg:tags":[
        "shop",
        "toy",
        "sale"
    ],
    "wof:name":"HOWLEYS TOYMASTER",
    "wof:placetype":"venue"
},
  "geometry": {"coordinates":[-2.454249,50.610886],"type":"Point"}
}