{
  "type": "Feature",
  "properties": {
    "iso:country":"GB",
    "sg:address":"Phoenix House, Faverdale Industrial Estate",
    "sg:city":"Darlington",
    "sg:classifiers":[
        {
            "category":"Professional",
            "subcategory":"Printing & Photocopies",
            "type":"Services"
        }
    ],
    "sg:phone":"+44 1325 486641",
    "sg:postcode":"DL3 0QE",
    "sg:province":"Durham",
    "sg:tags":[
        "printer"
    ],
    "wof:name":"G Prudhoe & Co. Ltd.",
    "wof:placetype":"venue"
},
  "geometry": {"coordinates":[-1.5771440268,54.5432434082],"type":"Point"}
}