{
  "type": "Feature",
  "properties": {
    "addr:full":"33a Cauldwell Hall Road Ipswich Suffolk IP4 4QD",
    "addr:housenumber":"33a",
    "addr:postcode":"ip4 4qd",
    "addr:street":"Cauldwell Hall Road",
    "iso:country":"GB",
    "sg:address":"33a Cauldwell Hall Road",
    "sg:city":"Ipswich",
    "sg:classifiers":[
        {
            "category":"Professional",
            "subcategory":"Printing & Photocopies",
            "type":"Services"
        }
    ],
    "sg:phone":"+44 1473 715191",
    "sg:postcode":"IP4 4QD",
    "sg:province":"Suffolk",
    "sg:tags":[
        "printer"
    ],
    "wof:name":"Anglian Print Works Ltd.",
    "wof:placetype":"venue"
},
  "geometry": {"coordinates":[1.182621,52.060535],"type":"Point"}
}