{
  "type": "Feature",
  "properties": {
    "iso:country":"GB",
    "sg:address":"Albert Street",
    "sg:city":"Huddersfield",
    "sg:classifiers":[
        {
            "category":"Organizations",
            "subcategory":"Non-profit Organization",
            "type":"Services"
        }
    ],
    "sg:postcode":"HD1 3PX",
    "sg:province":"West Yorkshire",
    "sg:tags":[
        "organisation",
        "voluntary",
        "charity"
    ],
    "wof:name":"National Council of Young Men's Christian Associations (Incorporatedp",
    "wof:placetype":"venue"
},
  "geometry": {"coordinates":[-1.787784,53.638241],"type":"Point"}
}