{
  "type": "Feature",
  "properties": {
    "iso:country":"GB",
    "sg:address":"Dawson House, Dawson Street, Oxford",
    "sg:city":"Oxford",
    "sg:classifiers":[
        {
            "category":"Conference Center",
            "type":"Public Place"
        }
    ],
    "sg:phone":"+44 1865 242224",
    "sg:postcode":"OX4 1AT",
    "sg:province":"Oxfordshire",
    "wof:name":"Read Edge Events Ltd",
    "wof:placetype":"venue"
},
  "geometry": {"coordinates":[-1.242612,51.749836],"type":"Point"}
}