{
  "type": "Feature",
  "properties": {
    "addr:full":"128 St Pauls Road, Islington London Greater London N1 2LP",
    "addr:housenumber":"128",
    "addr:postcode":"n1 2lp",
    "addr:street":"St Pauls Road",
    "iso:country":"GB",
    "sg:address":"128 St Pauls Road, Islington",
    "sg:city":"London",
    "sg:classifiers":[
        {
            "category":"Building & Trades",
            "subcategory":"Construction",
            "type":"Services"
        }
    ],
    "sg:phone":"+44 20 7288 1440",
    "sg:postcode":"N1 2LP",
    "sg:province":"Greater London",
    "sg:tags":[
        "builder",
        "contractor",
        "paving",
        "decorator",
        "painter",
        "driveway"
    ],
    "wof:name":"Clarke Paving & Driveways",
    "wof:placetype":"venue"
},
  "geometry": {"coordinates":[-0.0946860015,51.5473442078],"type":"Point"}
}