{
  "type": "Feature",
  "properties": {
    "addr:full":"Cawdor Hotel, Sycamore St Newcastle Emlyn Carmarthenshire SA38 9AJ",
    "addr:postcode":"sa38 9aj",
    "addr:street":"St",
    "iso:country":"GB",
    "sg:address":"Cawdor Hotel, Sycamore St",
    "sg:city":"Newcastle Emlyn",
    "sg:classifiers":[
        {
            "category":"Restaurant",
            "type":"Food & Drink"
        }
    ],
    "sg:phone":"+44 1239 711305",
    "sg:postcode":"SA38 9AJ",
    "sg:province":"Carmarthenshire",
    "sg:tags":[
        "indian"
    ],
    "wof:name":"Priya Balti Tandoori",
    "wof:placetype":"venue"
},
  "geometry": {"coordinates":[-4.4679841995,52.0359191895],"type":"Point"}
}