{
  "type": "Feature",
  "properties": {
    "iso:country":"GB",
    "sg:address":"Benmore",
    "sg:city":"Dundee",
    "sg:classifiers":[
        {
            "category":"Landmark",
            "subcategory":"Tourist Attraction",
            "type":"Public Place"
        }
    ],
    "sg:postcode":"PA23 8QU",
    "sg:province":"Argyll and Bute",
    "sg:tags":[
        "interest"
    ],
    "wof:name":"Younger Botani Gardens",
    "wof:placetype":"venue"
},
  "geometry": {"coordinates":[-4.9298291206,55.979309082],"type":"Point"}
}