{
  "type": "Feature",
  "properties": {
    "addr:full":"19 Station Road Swanage Dorset BH19 1AB",
    "addr:housenumber":"19",
    "addr:postcode":"bh19 1ab",
    "addr:street":"Station Road",
    "iso:country":"GB",
    "sg:address":"19 Station Road",
    "sg:city":"Swanage",
    "sg:classifiers":[
        {
            "category":"Food & Beverages",
            "subcategory":"Specialty",
            "type":"Retail Goods"
        }
    ],
    "sg:phone":"+44 1929 427057",
    "sg:postcode":"BH19 1AB",
    "sg:province":"Dorset",
    "sg:tags":[
        "product",
        "health"
    ],
    "wof:name":"Country Foods",
    "wof:placetype":"venue"
},
  "geometry": {"coordinates":[-1.958154,50.609337],"type":"Point"}
}