{
  "type": "Feature",
  "properties": {
    "iso:country":"GB",
    "sg:address":"Minsterley",
    "sg:city":"Shrewsbury",
    "sg:classifiers":[
        {
            "category":"Travel",
            "subcategory":"Hotels & Motels",
            "type":"Entertainment"
        }
    ],
    "sg:phone":"+44 1743 791244",
    "sg:postcode":"SY5 0BA",
    "sg:province":"Shropshire",
    "wof:name":"Bridge Hotel",
    "wof:placetype":"venue"
},
  "geometry": {"coordinates":[-2.925398,52.638226],"type":"Point"}
}