{
  "type": "Feature",
  "properties": {
    "iso:country":"GB",
    "sg:address":"Unit 22, Slingsby Close, Atleborough Fields Industrial Es",
    "sg:city":"Nuneaton",
    "sg:classifiers":[
        {
            "category":"Manufacturing",
            "subcategory":"Metals",
            "type":"Manufacturing & Wholesale Goods"
        },
        {
            "category":"Wholesale",
            "subcategory":"Metals & Minerals",
            "type":"Manufacturing & Wholesale Goods"
        }
    ],
    "sg:phone":"+44 24 7638 4728",
    "sg:postcode":"CV11 6RP",
    "sg:province":"Leicestershire",
    "sg:tags":[
        "fabricator",
        "work",
        "sheet"
    ],
    "wof:name":"Leniks Motor Panels Ltd",
    "wof:placetype":"venue"
},
  "geometry": {"coordinates":[-1.4481090307,52.514881134],"type":"Point"}
}