{
  "type": "Feature",
  "properties": {
    "iso:country":"GB",
    "sg:address":"24 Haynes Road",
    "sg:city":"Westbury",
    "sg:classifiers":[
        {
            "category":"Personal",
            "subcategory":"Beauty Salon",
            "type":"Services"
        },
        {
            "category":"Personal",
            "subcategory":"Barber",
            "type":"Services"
        }
    ],
    "sg:phone":"+44 1373 822692",
    "sg:postcode":"BA13 3HD",
    "sg:province":"Wiltshire",
    "sg:tags":[
        "unisex",
        "hairdresser"
    ],
    "wof:name":"Wendy's Hair Stylist",
    "wof:placetype":"venue"
},
  "geometry": {"coordinates":[-2.184827,51.259735],"type":"Point"}
}