{
  "type": "Feature",
  "properties": {
    "iso:country":"GB",
    "sg:address":"Unit 20, Marsh Lane Trading Estate",
    "sg:city":"Bristol",
    "sg:classifiers":[
        {
            "category":"Wholesale",
            "subcategory":"Scrap",
            "type":"Manufacturing & Wholesale Goods"
        }
    ],
    "sg:phone":"+44 1275 372946",
    "sg:postcode":"BS20 0NH",
    "sg:province":"Somerset",
    "sg:tags":[
        "breaker",
        "dismantlers"
    ],
    "wof:name":"Portbury Car Breakers",
    "wof:placetype":"venue"
},
  "geometry": {"coordinates":[-2.706399,51.482159],"type":"Point"}
}