{
  "type": "Feature",
  "properties": {
    "addr:full":"91 Bedford Avenue Barnet Hertfordshire EN5 2ES",
    "addr:housenumber":"91",
    "addr:postcode":"en5 2es",
    "addr:street":"Bedford Avenue",
    "iso:country":"GB",
    "sg:address":"91 Bedford Avenue",
    "sg:city":"Barnet",
    "sg:classifiers":[
        {
            "category":"Retail",
            "subcategory":"Repair Shop",
            "type":"Services"
        }
    ],
    "sg:postcode":"EN5 2ES",
    "sg:province":"Hertfordshire",
    "sg:tags":[
        "clocks",
        "watch"
    ],
    "wof:name":"Clock Repairs",
    "wof:placetype":"venue"
},
  "geometry": {"coordinates":[-0.199606,51.646851],"type":"Point"}
}