{
  "type": "Feature",
  "properties": {
    "addr:full":"45 Weymouth St West End Hampshire W1N 4BY",
    "addr:housenumber":"45",
    "addr:postcode":"w1n 4by",
    "addr:street":"Weymouth St",
    "iso:country":"GB",
    "sg:address":"45 Weymouth St",
    "sg:city":"West End",
    "sg:classifiers":[
        {
            "category":"Shopping",
            "subcategory":"Hobbies, Toys, & Games",
            "type":"Retail Goods"
        }
    ],
    "sg:phone":"+44 20 8450 0911",
    "sg:postcode":"W1N 4BY",
    "sg:province":"Hampshire",
    "sg:tags":[
        "computer"
    ],
    "wof:name":"Owie Wowies Ltd",
    "wof:placetype":"venue"
},
  "geometry": {"coordinates":[-0.149582997,51.5201225281],"type":"Point"}
}