{
  "type": "Feature",
  "properties": {
    "iso:country":"GB",
    "sg:address":"106 Y Gerddi, Trimsaran",
    "sg:city":"Kidwelly",
    "sg:classifiers":[
        {
            "category":"Retail",
            "subcategory":"Funeral Services",
            "type":"Services"
        }
    ],
    "sg:phone":"+44 1554 810604",
    "sg:postcode":"SA17 4AE",
    "sg:province":"Carmarthenshire",
    "wof:name":"Achibald R Evans",
    "wof:placetype":"venue"
},
  "geometry": {"coordinates":[-4.303438,51.736519],"type":"Point"}
}