{
  "type": "Feature",
  "properties": {
    "addr:full":"132-134 Mill Road Motherwell North Lanarkshire ML1 1LH",
    "addr:housenumber":"132-134",
    "addr:postcode":"ml1 1lh",
    "addr:street":"Mill Road",
    "iso:country":"GB",
    "sg:address":"132-134 Mill Road",
    "sg:city":"Motherwell",
    "sg:classifiers":[
        {
            "category":"Building & Trades",
            "subcategory":"Plumbing",
            "type":"Services"
        }
    ],
    "sg:postcode":"ML1 1LH",
    "sg:province":"North Lanarkshire",
    "sg:tags":[
        "heating"
    ],
    "wof:name":"John Wilkie",
    "wof:placetype":"venue"
},
  "geometry": {"coordinates":[-3.9857239723,55.7968444824],"type":"Point"}
}