{
  "type": "Feature",
  "properties": {
    "iso:country":"GB",
    "sg:address":"E S S Ho, 96-98 Chapel St",
    "sg:city":"Leigh",
    "sg:classifiers":[
        {
            "category":"Communications",
            "type":"Services"
        }
    ],
    "sg:postcode":"WN7 2DB",
    "sg:province":"Lancashire",
    "sg:tags":[
        "data",
        "network"
    ],
    "wof:name":"P P S Computer Services Ltd",
    "wof:placetype":"venue"
},
  "geometry": {"coordinates":[-2.518994,53.496971],"type":"Point"}
}