{
  "type": "Feature",
  "properties": {
    "iso:country":"GB",
    "sg:address":"21 Woodborough Road",
    "sg:city":"Winscombe",
    "sg:classifiers":[
        {
            "category":"Shopping",
            "subcategory":"Florist",
            "type":"Retail Goods"
        }
    ],
    "sg:phone":"+44 1934 842220",
    "sg:postcode":"BS25 1AB",
    "sg:province":"Somerset",
    "wof:name":"The Conservatory",
    "wof:placetype":"venue"
},
  "geometry": {"coordinates":[-2.8327469826,51.3140678406],"type":"Point"}
}