{
  "type": "Feature",
  "properties": {
    "addr:full":"57-61 Crieff Road, Hillyland Perth Perth and Kinross PH1 2NU",
    "addr:housenumber":"57-61",
    "addr:postcode":"ph1 2nu",
    "addr:street":"Crieff Road Hillyland",
    "iso:country":"GB",
    "sg:address":"57-61 Crieff Road, Hillyland",
    "sg:city":"Perth",
    "sg:classifiers":[
        {
            "category":"Freight",
            "type":"Transportation"
        }
    ],
    "sg:postcode":"PH1 2NU",
    "sg:province":"Perth and Kinross",
    "sg:tags":[
        "haulage",
        "road"
    ],
    "wof:name":"Morris Young & Sons",
    "wof:placetype":"venue"
},
  "geometry": {"coordinates":[-3.4576470852,56.405128479],"type":"Point"}
}