{
  "type": "Feature",
  "properties": {
    "addr:full":"10 Woodperry Avenue Solihull West Midlands B91 3GN",
    "addr:housenumber":"10",
    "addr:postcode":"b91 3gn",
    "addr:street":"Woodperry Avenue",
    "iso:country":"GB",
    "sg:address":"10 Woodperry Avenue",
    "sg:city":"Solihull",
    "sg:classifiers":[
        {
            "category":"Professional",
            "subcategory":"Engineering",
            "type":"Services"
        }
    ],
    "sg:phone":"+44 121 705 7408",
    "sg:postcode":"B91 3GN",
    "sg:province":"West Midlands",
    "sg:tags":[
        "contractor",
        "electrical",
        "engineer"
    ],
    "wof:name":"A E C Electrical Contractors",
    "wof:placetype":"venue"
},
  "geometry": {"coordinates":[-1.7803230286,52.4031181335],"type":"Point"}
}