{
  "type": "Feature",
  "properties": {
    "iso:country":"GB",
    "sg:address":"Pembroke Pastures, Whissendine",
    "sg:city":"Oakham",
    "sg:classifiers":[
        {
            "category":"Wholesale",
            "subcategory":"Sporting Goods",
            "type":"Manufacturing & Wholesale Goods"
        },
        {
            "category":"Shopping",
            "subcategory":"Crafts & Fabrics",
            "type":"Retail Goods"
        }
    ],
    "sg:phone":"+44 1664 474344",
    "sg:postcode":"LE15 7BS",
    "sg:province":"Leicestershire",
    "sg:tags":[
        "yarn",
        "supply"
    ],
    "wof:name":"Barker Textiles",
    "wof:placetype":"venue"
},
  "geometry": {"coordinates":[-0.779598,52.719593],"type":"Point"}
}