{
  "type": "Feature",
  "properties": {
    "addr:full":"Beanstalk Cottage, Ipsley Lane, Ipsley Redditch Warwickshire B98 0AP",
    "addr:postcode":"b98 0ap",
    "addr:street":"Ipsley Lane",
    "iso:country":"GB",
    "sg:address":"Beanstalk Cottage, Ipsley Lane, Ipsley",
    "sg:city":"Redditch",
    "sg:classifiers":[
        {
            "category":"Shopping",
            "subcategory":"Stationery & Office Supplies",
            "type":"Retail Goods"
        }
    ],
    "sg:phone":"+44 1527 515550",
    "sg:postcode":"B98 0AP",
    "sg:province":"Warwickshire",
    "sg:tags":[
        "equipment",
        "printing",
        "mech"
    ],
    "wof:name":"P G Marketing Services Ltd.",
    "wof:placetype":"venue"
},
  "geometry": {"coordinates":[-1.903747,52.297615],"type":"Point"}
}