{
  "type": "Feature",
  "properties": {
    "addr:full":"134 Park Lane Hornchurch Essex RM11 1BE",
    "addr:housenumber":"134",
    "addr:postcode":"rm11 1be",
    "addr:street":"Park Lane",
    "iso:country":"GB",
    "sg:address":"134 Park Lane",
    "sg:city":"Hornchurch",
    "sg:classifiers":[
        {
            "category":"Shopping",
            "subcategory":"Computers & Home Electronics",
            "type":"Retail Goods"
        }
    ],
    "sg:phone":"+44 1708 730591",
    "sg:postcode":"RM11 1BE",
    "sg:province":"Essex",
    "sg:tags":[
        "electrical"
    ],
    "wof:name":"C H Electrical Wholesalers Ltd.",
    "wof:placetype":"venue"
},
  "geometry": {"coordinates":[0.193023,51.568806],"type":"Point"}
}