{
  "type": "Feature",
  "properties": {
    "addr:full":"Trefula Farm Redruth Cornwall TR16 5ET",
    "addr:housenumber":"redruth",
    "addr:postcode":"tr16 5et",
    "iso:country":"GB",
    "sg:address":"Trefula Farm",
    "sg:city":"Redruth",
    "sg:classifiers":[
        {
            "category":"Farming",
            "subcategory":"Livestock Farm",
            "type":"Manufacturing & Wholesale Goods"
        }
    ],
    "sg:postcode":"TR16 5ET",
    "sg:province":"Cornwall",
    "sg:tags":[
        "others"
    ],
    "wof:name":"D & C Waters",
    "wof:placetype":"venue"
},
  "geometry": {"coordinates":[-5.199494,50.238186],"type":"Point"}
}