{
  "type": "Feature",
  "properties": {
    "addr:full":"29 Kingswear Parade Leeds West Yorkshire LS15 8LJ",
    "addr:housenumber":"29",
    "addr:postcode":"ls15 8lj",
    "addr:street":"Kingswear Parade",
    "iso:country":"GB",
    "sg:address":"29 Kingswear Parade",
    "sg:city":"Leeds",
    "sg:classifiers":[
        {
            "category":"Personal",
            "subcategory":"Beauty Salon",
            "type":"Services"
        }
    ],
    "sg:phone":"+44 113 264 9073",
    "sg:postcode":"LS15 8LJ",
    "sg:province":"West Yorkshire",
    "sg:tags":[
        "ladies",
        "lady",
        "hairdresser"
    ],
    "wof:name":"Christines Hair Fashions",
    "wof:placetype":"venue"
},
  "geometry": {"coordinates":[-1.4449230433,53.8025131226],"type":"Point"}
}