{
  "type": "Feature",
  "properties": {
    "addr:full":"6 Chipstead Valley Road Coulsdon Surrey CR5 2RA",
    "addr:housenumber":"6",
    "addr:postcode":"cr5 2ra",
    "addr:street":"Chipstead Valley Road",
    "iso:country":"GB",
    "sg:address":"6 Chipstead Valley Road",
    "sg:city":"Coulsdon",
    "sg:classifiers":[
        {
            "category":"Restaurant",
            "type":"Food & Drink"
        }
    ],
    "sg:phone":"+44 20 8668 4459",
    "sg:postcode":"CR5 2RA",
    "sg:province":"Surrey",
    "wof:name":"E Mehmet",
    "wof:placetype":"venue"
},
  "geometry": {"coordinates":[-0.138661,51.320999],"type":"Point"}
}