{
  "type": "Feature",
  "properties": {
    "addr:full":"Commercial Parade, 232-234 Railton Road, Herne Hill London Greater London SE24 0JT",
    "addr:postcode":"232-234;se24 0jt",
    "addr:street":"Commercial;Railton Road",
    "iso:country":"GB",
    "sg:address":"Commercial Parade, 232-234 Railton Road, Herne Hill",
    "sg:city":"London",
    "sg:classifiers":[
        {
            "category":"Professional",
            "subcategory":"Art Services",
            "type":"Services"
        }
    ],
    "sg:phone":"+44 20 7274 7046",
    "sg:postcode":"SE24 0JT",
    "sg:province":"Greater London",
    "sg:tags":[
        "framing"
    ],
    "wof:name":"Brockwell Art Services",
    "wof:placetype":"venue"
},
  "geometry": {"coordinates":[-0.1023800001,51.4528503418],"type":"Point"}
}