{
  "type": "Feature",
  "properties": {
    "iso:country":"GB",
    "sg:address":"4 Central Parade, Badsley Moor Lane",
    "sg:city":"Rotherham",
    "sg:classifiers":[
        {
            "category":"Shopping",
            "subcategory":"Department Store",
            "type":"Retail Goods"
        }
    ],
    "sg:phone":"+44 1709 837590",
    "sg:postcode":"S65 2QN",
    "sg:province":"South Yorkshire",
    "wof:name":"Bazs Off Licence",
    "wof:placetype":"venue"
},
  "geometry": {"coordinates":[-1.328409,53.430908],"type":"Point"}
}