{
  "type": "Feature",
  "properties": {
    "iso:country":"GB",
    "sg:address":"The Old Farmhouse, 68 Birches Barn Rd, Bradmore",
    "sg:city":"Wolverhampton",
    "sg:classifiers":[
        {
            "category":"Building & Trades",
            "subcategory":"Landscaping Services",
            "type":"Services"
        }
    ],
    "sg:postcode":"WV3 7BN",
    "sg:province":"Staffordshire",
    "sg:tags":[
        "forestry",
        "tree"
    ],
    "wof:name":"Lewis,Rupert,",
    "wof:placetype":"venue"
},
  "geometry": {"coordinates":[-2.1578419209,52.5754776001],"type":"Point"}
}