{
  "type": "Feature",
  "properties": {
    "addr:full":"High Street, Limpsfield Oxted Surrey RH8 0DR",
    "addr:postcode":"rh8 0dr",
    "addr:street":"High Street",
    "iso:country":"GB",
    "sg:address":"High Street, Limpsfield",
    "sg:city":"Oxted",
    "sg:classifiers":[
        {
            "category":"Military Area",
            "subcategory":"Air Force Base",
            "type":"Public Place"
        }
    ],
    "sg:phone":"+44 1883 730531",
    "sg:postcode":"RH8 0DR",
    "sg:province":"Surrey",
    "sg:tags":[
        "taxi",
        "hire",
        "private"
    ],
    "wof:name":"Adam Witcombe Executive Car Hire",
    "wof:placetype":"venue"
},
  "geometry": {"coordinates":[0.0041149999,51.2569503784],"type":"Point"}
}