{
  "type": "Feature",
  "properties": {
    "iso:country":"GB",
    "sg:address":"Kingsbourne House, Nightingale Park",
    "sg:city":"Slough",
    "sg:classifiers":[
        {
            "category":"Professional",
            "subcategory":"Management & Consulting",
            "type":"Services"
        }
    ],
    "sg:postcode":"SL2 3SN",
    "sg:province":"Berkshire",
    "sg:tags":[
        "consultant",
        "business"
    ],
    "wof:name":"The Kingsbourne Group",
    "wof:placetype":"venue"
},
  "geometry": {"coordinates":[-0.6372849941,51.5506248474],"type":"Point"}
}