{
  "type": "Feature",
  "properties": {
    "iso:country":"GB",
    "sg:address":"Pensford Hill, Pensford",
    "sg:city":"Bristol",
    "sg:classifiers":[
        {
            "category":"Professional",
            "subcategory":"Printing & Photocopies",
            "type":"Services"
        }
    ],
    "sg:postcode":"BS39 4AA",
    "sg:province":"Somerset",
    "sg:tags":[
        "printer"
    ],
    "wof:name":"K C Printing",
    "wof:placetype":"venue"
},
  "geometry": {"coordinates":[-2.5531189442,51.3780555725],"type":"Point"}
}