{
  "type": "Feature",
  "properties": {
    "iso:country":"GB",
    "sg:address":"Waldridge Farm, Wiveliscombe",
    "sg:city":"Taunton",
    "sg:classifiers":[
        {
            "category":"Manufacturing",
            "subcategory":"Metals",
            "type":"Manufacturing & Wholesale Goods"
        }
    ],
    "sg:phone":"+44 1984 624621",
    "sg:postcode":"TA4 2BL",
    "sg:province":"Devon",
    "sg:tags":[
        "steel",
        "fabricator",
        "erectors"
    ],
    "wof:name":"Waldridge Engineering",
    "wof:placetype":"venue"
},
  "geometry": {"coordinates":[-3.308854,51.041458],"type":"Point"}
}