{
  "type": "Feature",
  "properties": {
    "addr:full":"39 Boothroyd Lane Dewsbury West Yorkshire WF13 2RB",
    "addr:housenumber":"39",
    "addr:postcode":"wf13 2rb",
    "addr:street":"Boothroyd Lane",
    "iso:country":"GB",
    "sg:address":"39 Boothroyd Lane",
    "sg:city":"Dewsbury",
    "sg:classifiers":[
        {
            "category":"Professional",
            "subcategory":"Business Services",
            "type":"Services"
        }
    ],
    "sg:postcode":"WF13 2RB",
    "sg:province":"West Yorkshire",
    "sg:tags":[
        "bookmaker"
    ],
    "wof:name":"Whirlys",
    "wof:placetype":"venue"
},
  "geometry": {"coordinates":[-1.6408170462,53.6906471252],"type":"Point"}
}