{
  "type": "Feature",
  "properties": {
    "addr:full":"6 Trafalgar St Sheffield South Yorkshire S1 4GL",
    "addr:housenumber":"6",
    "addr:postcode":"s1 4gl",
    "addr:street":"Trafalgar St",
    "iso:country":"GB",
    "sg:address":"6 Trafalgar St",
    "sg:city":"Sheffield",
    "sg:classifiers":[
        {
            "category":"Utilities",
            "subcategory":"Natural Gas",
            "type":"Services"
        }
    ],
    "sg:phone":"+44 114 276 8010",
    "sg:postcode":"S1 4GL",
    "sg:province":"South Yorkshire",
    "wof:name":"Nationwide Gas Services Ltd",
    "wof:placetype":"venue"
},
  "geometry": {"coordinates":[-1.497317,53.42004],"type":"Point"}
}