{
  "type": "Feature",
  "properties": {
    "iso:country":"GB",
    "sg:address":"Wylds Road",
    "sg:city":"Bridgwater",
    "sg:classifiers":[
        {
            "category":"Home & Garden",
            "subcategory":"Home Furnishings",
            "type":"Retail Goods"
        }
    ],
    "sg:phone":"+44 1278 458808",
    "sg:postcode":"TA6 4DH",
    "sg:province":"Somerset",
    "sg:tags":[
        "soft"
    ],
    "wof:name":"Norian (U K) Ltd.",
    "wof:placetype":"venue"
},
  "geometry": {"coordinates":[-2.992689,51.139999],"type":"Point"}
}