{
  "type": "Feature",
  "properties": {
    "iso:country":"GB",
    "sg:address":"Carlton, Aldbrough St John",
    "sg:city":"Richmond",
    "sg:classifiers":[
        {
            "category":"Transit Center",
            "subcategory":"Passenger",
            "type":"Transportation"
        }
    ],
    "sg:phone":"+44 1325 374309",
    "sg:postcode":"DL11 7AG",
    "sg:province":"Durham",
    "sg:tags":[
        "boarding",
        "kennel",
        "catteries"
    ],
    "wof:name":"Oakwood Boarding Kennels",
    "wof:placetype":"venue"
},
  "geometry": {"coordinates":[-1.7049599886,54.5052909851],"type":"Point"}
}