{
  "type": "Feature",
  "properties": {
    "iso:country":"GB",
    "sg:address":"168 Old Shoreham Road",
    "sg:city":"Hove",
    "sg:classifiers":[
        {
            "category":"Insurance",
            "subcategory":"Insurance Agent",
            "type":"Services"
        }
    ],
    "sg:phone":"+44 1273 770454",
    "sg:postcode":"BN3 7AR",
    "sg:province":"East Sussex",
    "sg:tags":[
        "broker"
    ],
    "wof:name":"Scullard & Prosser",
    "wof:placetype":"venue"
},
  "geometry": {"coordinates":[-0.182273,50.839081],"type":"Point"}
}