{
  "type": "Feature",
  "properties": {
    "iso:country":"GB",
    "sg:address":"Coach House Cottage, Little Trewince, Stithians",
    "sg:city":"Truro",
    "sg:classifiers":[
        {
            "category":"Government",
            "subcategory":"Department Of Motor Vehicles",
            "type":"Public Place"
        }
    ],
    "sg:phone":"+44 1209 861235",
    "sg:postcode":"TR3 7BZ",
    "sg:province":"Cornwall",
    "sg:tags":[
        "drawn",
        "horse",
        "hire"
    ],
    "wof:name":"Manhire",
    "wof:placetype":"venue"
},
  "geometry": {"coordinates":[-5.173534,50.18663],"type":"Point"}
}