{
  "type": "Feature",
  "properties": {
    "addr:full":"Rayleigh & Needwood House Social Centre, Woodcock La Birmingham West Midlands B27 6DD",
    "addr:postcode":"b27 6dd",
    "addr:street":"Woodcock La Birmingham",
    "iso:country":"GB",
    "sg:address":"Rayleigh & Needwood House Social Centre, Woodcock La",
    "sg:city":"Birmingham",
    "sg:classifiers":[
        {
            "category":"Government",
            "subcategory":"Office",
            "type":"Public Place"
        }
    ],
    "sg:phone":"+44 121 707 5898",
    "sg:postcode":"B27 6DD",
    "sg:province":"West Midlands",
    "sg:tags":[
        "local"
    ],
    "wof:name":"Birmingham City Council",
    "wof:placetype":"venue"
},
  "geometry": {"coordinates":[-1.81489,52.445431],"type":"Point"}
}