{
  "type": "Feature",
  "properties": {
    "iso:country":"GB",
    "sg:address":"12 Home Rule Road, Locks Heath",
    "sg:city":"Southampton",
    "sg:classifiers":[
        {
            "category":"Building & Trades",
            "subcategory":"Construction",
            "type":"Services"
        }
    ],
    "sg:phone":"+44 1489 584550",
    "sg:postcode":"SO31 6LG",
    "sg:province":"Hampshire",
    "sg:tags":[
        "roofing"
    ],
    "wof:name":"B J Dawkins Felt Roofing",
    "wof:placetype":"venue"
},
  "geometry": {"coordinates":[-1.2689729929,50.8650398254],"type":"Point"}
}