{
  "type": "Feature",
  "properties": {
    "addr:full":"Salamander Quay West, Park Lane, Harefield Uxbridge Buckinghamshire UB9 6NZ",
    "addr:postcode":"ub9 6nz",
    "addr:street":"Salamander Quay West Park Lane",
    "iso:country":"GB",
    "sg:address":"Salamander Quay West, Park Lane, Harefield",
    "sg:city":"Uxbridge",
    "sg:classifiers":[
        {
            "category":"Shopping",
            "subcategory":"Stationery & Office Supplies",
            "type":"Retail Goods"
        }
    ],
    "sg:phone":"+44 1895 825700",
    "sg:postcode":"UB9 6NZ",
    "sg:province":"Buckinghamshire",
    "sg:tags":[
        "item",
        "promotional"
    ],
    "wof:name":"T C Advertising Gifts Ltd.",
    "wof:placetype":"venue"
},
  "geometry": {"coordinates":[-0.4820719957,51.604019165],"type":"Point"}
}