{
  "type": "Feature",
  "properties": {
    "iso:country":"GB",
    "sg:address":"Cheshire House, New Smithfield Market, Openshaw",
    "sg:city":"Manchester",
    "sg:classifiers":[
        {
            "category":"Wholesale",
            "subcategory":"Groceries",
            "type":"Manufacturing & Wholesale Goods"
        }
    ],
    "sg:phone":"+44 161 223 9525",
    "sg:postcode":"M11 2WJ",
    "sg:province":"Greater Manchester",
    "sg:tags":[
        "food",
        "supplier",
        "drink"
    ],
    "wof:name":"CHESHIRE PRODUCE COMPANY",
    "wof:placetype":"venue"
},
  "geometry": {"coordinates":[-2.1789040565,53.4725608826],"type":"Point"}
}