{
  "type": "Feature",
  "properties": {
    "addr:full":"18 Eley Road, Edmonton London Greater London N18 3BB",
    "addr:housenumber":"18",
    "addr:postcode":"n18 3bb",
    "addr:street":"Eley Road Edmonton",
    "iso:country":"GB",
    "sg:address":"18 Eley Road, Edmonton",
    "sg:city":"London",
    "sg:classifiers":[
        {
            "category":"Wholesale",
            "subcategory":"Non-durable Goods",
            "type":"Manufacturing & Wholesale Goods"
        }
    ],
    "sg:phone":"+44 20 8807 2211",
    "sg:postcode":"N18 3BB",
    "sg:province":"Greater London",
    "sg:tags":[
        "carry",
        "wholesaler",
        "cash"
    ],
    "wof:name":"Imperial Cash & Carry Ltd.",
    "wof:placetype":"venue"
},
  "geometry": {"coordinates":[-0.045519,51.615429],"type":"Point"}
}