{
  "type": "Feature",
  "properties": {
    "addr:full":"Unit 3, Downend Business Park, North Street Bristol City of Bristol BS16 5SE",
    "addr:housenumber":"unit 3 downend",
    "addr:postcode":"bs16 5se",
    "addr:street":"Business Park North Street",
    "iso:country":"GB",
    "sg:address":"Unit 3, Downend Business Park, North Street",
    "sg:city":"Bristol",
    "sg:classifiers":[
        {
            "category":"Manufacturing",
            "subcategory":"Food",
            "type":"Manufacturing & Wholesale Goods"
        }
    ],
    "sg:phone":"+44 117 940 6001",
    "sg:postcode":"BS16 5SE",
    "sg:province":"City of Bristol",
    "sg:tags":[
        "processing"
    ],
    "wof:name":"Simo Industries (U K) Ltd.",
    "wof:placetype":"venue"
},
  "geometry": {"coordinates":[-2.591429,51.453667],"type":"Point"}
}