{
  "type": "Feature",
  "properties": {
    "addr:full":"33 Carlton Avenue Bognor Regis West Sussex PO21 3LR",
    "addr:housenumber":"33",
    "addr:postcode":"po21 3lr",
    "addr:street":"Carlton Avenue",
    "iso:country":"GB",
    "sg:address":"33 Carlton Avenue",
    "sg:city":"Bognor Regis",
    "sg:classifiers":[
        {
            "category":"Building & Trades",
            "subcategory":"Plumbing",
            "type":"Services"
        }
    ],
    "sg:phone":"+44 1243 265887",
    "sg:postcode":"PO21 3LR",
    "sg:province":"West Sussex",
    "sg:tags":[
        "plumber",
        "heating"
    ],
    "wof:name":"Victor J Fowler",
    "wof:placetype":"venue"
},
  "geometry": {"coordinates":[-0.722637,50.783772],"type":"Point"}
}