{
  "type": "Feature",
  "properties": {
    "addr:full":"27 Broadfield Road Barnstaple Devon EX32 9JW",
    "addr:housenumber":"27",
    "addr:postcode":"ex32 9jw",
    "addr:street":"Broadfield Road",
    "iso:country":"GB",
    "sg:address":"27 Broadfield Road",
    "sg:city":"Barnstaple",
    "sg:classifiers":[
        {
            "category":"Building & Trades",
            "subcategory":"Construction",
            "type":"Services"
        }
    ],
    "sg:phone":"+44 1271 372948",
    "sg:postcode":"EX32 9JW",
    "sg:province":"Devon",
    "sg:tags":[
        "dry",
        "lining",
        "plasterers",
        "screeders"
    ],
    "wof:name":"Winston Ley",
    "wof:placetype":"venue"
},
  "geometry": {"coordinates":[-4.0502700806,51.0744743347],"type":"Point"}
}