{
  "type": "Feature",
  "properties": {
    "iso:country":"GB",
    "sg:address":"70 Fulmer Drive",
    "sg:city":"Gerrards Cross",
    "sg:classifiers":[
        {
            "category":"Professional",
            "subcategory":"Engineering",
            "type":"Services"
        }
    ],
    "sg:postcode":"SL9 7HL",
    "sg:province":"Buckinghamshire",
    "sg:tags":[
        "consulting",
        "engineer"
    ],
    "wof:name":"DAVMARK LTD",
    "wof:placetype":"venue"
},
  "geometry": {"coordinates":[-0.536402,51.574593],"type":"Point"}
}