{
  "type": "Feature",
  "properties": {
    "iso:country":"GB",
    "sg:address":"22 Chatsworth Road",
    "sg:city":"Eastleigh",
    "sg:classifiers":[
        {
            "category":"Building & Trades",
            "subcategory":"Construction",
            "type":"Services"
        }
    ],
    "sg:phone":"+44 23 8061 3118",
    "sg:postcode":"SO50 4PE",
    "sg:province":"Hampshire",
    "sg:tags":[
        "dry",
        "lining",
        "plasterers",
        "screeders"
    ],
    "wof:name":"C Ford Plastering",
    "wof:placetype":"venue"
},
  "geometry": {"coordinates":[-1.352448,50.983376],"type":"Point"}
}