{
  "type": "Feature",
  "properties": {
    "addr:full":"69a John Street Porthcawl Bridgend CF36 3AY",
    "addr:housenumber":"69a",
    "addr:postcode":"cf36 3ay",
    "addr:street":"John Street",
    "iso:country":"GB",
    "sg:address":"69a John Street",
    "sg:city":"Porthcawl",
    "sg:classifiers":[
        {
            "category":"Real Estate",
            "subcategory":"Real Estate Agent",
            "type":"Services"
        }
    ],
    "sg:phone":"+44 1656 783307",
    "sg:postcode":"CF36 3AY",
    "sg:province":"Bridgend",
    "wof:name":"Prestons",
    "wof:placetype":"venue"
},
  "geometry": {"coordinates":[-3.7033650875,51.4787712097],"type":"Point"}
}