{
  "type": "Feature",
  "properties": {
    "iso:country":"GB",
    "sg:address":"48 Montgomery Avenue",
    "sg:city":"Chatham",
    "sg:classifiers":[
        {
            "category":"Building & Trades",
            "subcategory":"Construction",
            "type":"Services"
        }
    ],
    "sg:phone":"+44 1634 300425",
    "sg:postcode":"ME5 0HA",
    "sg:province":"Kent",
    "sg:tags":[
        "joinery",
        "joiner",
        "carpenter",
        "carpentry"
    ],
    "wof:name":"G S Carpentry Ltd",
    "wof:placetype":"venue"
},
  "geometry": {"coordinates":[0.532415,51.360687],"type":"Point"}
}