{
  "type": "Feature",
  "properties": {
    "addr:full":"1 The Southend Ledbury Gloucestershire HR8 2EY",
    "addr:housenumber":"1",
    "addr:postcode":"hr8 2ey",
    "addr:street":"The Southend",
    "iso:country":"GB",
    "sg:address":"1 The Southend",
    "sg:city":"Ledbury",
    "sg:classifiers":[
        {
            "category":"Shopping",
            "subcategory":"Thrift Store",
            "type":"Retail Goods"
        }
    ],
    "sg:phone":"+44 1531 635155",
    "sg:postcode":"HR8 2EY",
    "sg:province":"Gloucestershire",
    "sg:tags":[
        "shop",
        "charity"
    ],
    "wof:name":"Age Concern",
    "wof:placetype":"venue"
},
  "geometry": {"coordinates":[-2.4225389957,52.0355567932],"type":"Point"}
}