{
  "type": "Feature",
  "properties": {
    "iso:country":"GB",
    "sg:address":"160 Dudley Road",
    "sg:city":"Wolverhampton",
    "sg:classifiers":[
        {
            "category":"Education",
            "subcategory":"Special Training",
            "type":"Public Place"
        },
        {
            "category":"Government",
            "subcategory":"Office",
            "type":"Public Place"
        }
    ],
    "sg:phone":"+44 1902 351252",
    "sg:postcode":"WV2 3DN",
    "sg:province":"West Midlands",
    "sg:tags":[
        "product",
        "local",
        "centre"
    ],
    "wof:name":"Blakenhall & St.Peter's Community Enterprise Project Ltd.",
    "wof:placetype":"venue"
},
  "geometry": {"coordinates":[-2.126456,52.575722],"type":"Point"}
}