{
  "type": "Feature",
  "properties": {
    "addr:full":"Bridlington Road Filey North Yorkshire YO14 9QH",
    "addr:postcode":"yo14 9qh",
    "addr:street":"Bridlington Road",
    "iso:country":"GB",
    "sg:address":"Bridlington Road",
    "sg:city":"Filey",
    "sg:classifiers":[
        {
            "category":"Home & Garden",
            "subcategory":"Garden Supply",
            "type":"Retail Goods"
        },
        {
            "category":"Farming",
            "subcategory":"Farm",
            "type":"Manufacturing & Wholesale Goods"
        }
    ],
    "sg:phone":"+44 1723 512054",
    "sg:postcode":"YO14 9QH",
    "sg:province":"North Yorkshire",
    "sg:tags":[
        "mixed",
        "bulb",
        "crop",
        "grower"
    ],
    "wof:name":"H Sutton & Sons",
    "wof:placetype":"venue"
},
  "geometry": {"coordinates":[-0.290749,54.211845],"type":"Point"}
}