{
  "type": "Feature",
  "properties": {
    "iso:country":"GB",
    "sg:address":"188 Forstal Road",
    "sg:city":"Aylesford",
    "sg:classifiers":[
        {
            "category":"Professional",
            "subcategory":"Printing & Photocopies",
            "type":"Services"
        }
    ],
    "sg:phone":"+44 1622 710759",
    "sg:postcode":"ME20 7DB",
    "sg:province":"Kent",
    "sg:tags":[
        "printer"
    ],
    "wof:name":"Offset Productions Ltd.",
    "wof:placetype":"venue"
},
  "geometry": {"coordinates":[0.4832699895,51.3031196594],"type":"Point"}
}