{
  "type": "Feature",
  "properties": {
    "addr:full":"23 New Street Bristol City of Bristol BS2 9DX",
    "addr:housenumber":"23",
    "addr:postcode":"bs2 9dx",
    "addr:street":"New Street",
    "iso:country":"GB",
    "sg:address":"23 New Street",
    "sg:city":"Bristol",
    "sg:classifiers":[
        {
            "category":"Bars & Pubs",
            "type":"Food & Drink"
        }
    ],
    "sg:postcode":"BS2 9DX",
    "sg:province":"City of Bristol",
    "sg:tags":[
        "pubs",
        "inn"
    ],
    "wof:name":"Sevenways Tavern",
    "wof:placetype":"venue"
},
  "geometry": {"coordinates":[-2.582679987,51.4575920105],"type":"Point"}
}