{
  "type": "Feature",
  "properties": {
    "iso:country":"GB",
    "sg:address":"39 Molesworth Street",
    "sg:city":"Wadebridge",
    "sg:classifiers":[
        {
            "category":"Shopping",
            "subcategory":"Gifts & Souvenirs",
            "type":"Retail Goods"
        }
    ],
    "sg:postcode":"PL27 7DH",
    "sg:province":"Cornwall",
    "sg:tags":[
        "poster",
        "card"
    ],
    "wof:name":"Occasions",
    "wof:placetype":"venue"
},
  "geometry": {"coordinates":[-4.838168,50.516182],"type":"Point"}
}