{
  "type": "Feature",
  "properties": {
    "addr:full":"8 Moat Place Edinburgh City of Edinburgh EH14 1NY",
    "addr:housenumber":"8",
    "addr:postcode":"eh14 1ny",
    "addr:street":"Moat Place Edinburgh",
    "iso:country":"GB",
    "sg:address":"8 Moat Place",
    "sg:city":"Edinburgh",
    "sg:classifiers":[
        {
            "category":"Shopping",
            "subcategory":"News",
            "type":"Retail Goods"
        }
    ],
    "sg:phone":"+44 131 455 7218",
    "sg:postcode":"EH14 1NY",
    "sg:province":"City of Edinburgh",
    "sg:tags":[
        "newsagent"
    ],
    "wof:name":"Moat Newsagents",
    "wof:placetype":"venue"
},
  "geometry": {"coordinates":[-3.2388219833,55.9312133789],"type":"Point"}
}