{
  "type": "Feature",
  "properties": {
    "addr:full":"The Terrace Penryn Cornwall TR10 8RW",
    "addr:postcode":"tr10 8rw",
    "addr:street":"Terrace",
    "iso:country":"GB",
    "sg:address":"The Terrace",
    "sg:city":"Penryn",
    "sg:classifiers":[
        {
            "category":"Place Of Worship",
            "type":"Public Place"
        }
    ],
    "sg:phone":"+44 1326 372543",
    "sg:postcode":"TR10 8RW",
    "sg:province":"Cornwall",
    "wof:name":"Penryn Methodist Church",
    "wof:placetype":"venue"
},
  "geometry": {"coordinates":[-5.1076140404,50.171169281],"type":"Point"}
}