{
  "type": "Feature",
  "properties": {
    "iso:country":"GB",
    "sg:address":"58 Lynher Dr",
    "sg:city":"Saltash",
    "sg:classifiers":[
        {
            "category":"Retail",
            "subcategory":"Auto Repair",
            "type":"Services"
        }
    ],
    "sg:phone":"+44 1752 721007",
    "sg:postcode":"PL12 4PA",
    "sg:province":"Cornwall",
    "sg:tags":[
        "engine",
        "car",
        "specialist"
    ],
    "wof:name":"Computa Tune",
    "wof:placetype":"venue"
},
  "geometry": {"coordinates":[-4.218427,50.403542],"type":"Point"}
}