{
  "type": "Feature",
  "properties": {
    "addr:full":"The Village, Chaddesley Corbett Kidderminster Staffordshire DY10 4SD",
    "addr:postcode":"dy10 4sd",
    "iso:country":"GB",
    "sg:address":"The Village, Chaddesley Corbett",
    "sg:city":"Kidderminster",
    "sg:classifiers":[
        {
            "category":"Education",
            "subcategory":"School",
            "type":"Public Place"
        }
    ],
    "sg:phone":"+44 1562 777312",
    "sg:postcode":"DY10 4SD",
    "sg:province":"Staffordshire",
    "sg:tags":[
        "local",
        "authority"
    ],
    "wof:name":"Chaddesley Corbett Endowed First School",
    "wof:placetype":"venue"
},
  "geometry": {"coordinates":[-2.158926,52.363029],"type":"Point"}
}