{
  "type": "Feature",
  "properties": {
    "addr:full":"32 Main St Glasgow East Renfrewshire G76 8DX",
    "addr:housenumber":"32",
    "addr:postcode":"g76 8dx",
    "addr:street":"Main St",
    "iso:country":"GB",
    "sg:address":"32 Main St",
    "sg:city":"Glasgow",
    "sg:classifiers":[
        {
            "category":"Building & Trades",
            "subcategory":"Construction",
            "type":"Services"
        }
    ],
    "sg:phone":"+44 141 644 4060",
    "sg:postcode":"G76 8DX",
    "sg:province":"East Renfrewshire",
    "sg:tags":[
        "builder"
    ],
    "wof:name":"Odin Contracts",
    "wof:placetype":"venue"
},
  "geometry": {"coordinates":[-4.267274,55.781857],"type":"Point"}
}