{
  "type": "Feature",
  "properties": {
    "addr:full":"114 Birley Spa Lane Sheffield Derbyshire S12 4EJ",
    "addr:housenumber":"114",
    "addr:postcode":"s12 4ej",
    "addr:street":"Birley Spa Lane",
    "iso:country":"GB",
    "sg:address":"114 Birley Spa Lane",
    "sg:city":"Sheffield",
    "sg:classifiers":[
        {
            "category":"Shopping",
            "subcategory":"News",
            "type":"Retail Goods"
        }
    ],
    "sg:phone":"+44 114 248 7794",
    "sg:postcode":"S12 4EJ",
    "sg:province":"Derbyshire",
    "sg:tags":[
        "newsagent"
    ],
    "wof:name":"GT News",
    "wof:placetype":"venue"
},
  "geometry": {"coordinates":[-1.3782980442,53.3473320007],"type":"Point"}
}