{
  "type": "Feature",
  "properties": {
    "iso:country":"GB",
    "sg:address":"108 Brighton Road",
    "sg:city":"Coulsdon",
    "sg:classifiers":[
        {
            "category":"Retail",
            "subcategory":"Auto Repair",
            "type":"Services"
        }
    ],
    "sg:phone":"+44 20 8660 7726",
    "sg:postcode":"CR5 3EF",
    "sg:province":"Surrey",
    "sg:tags":[
        "body",
        "car"
    ],
    "wof:name":"Doble Motors",
    "wof:placetype":"venue"
},
  "geometry": {"coordinates":[-0.1391790062,51.3189086914],"type":"Point"}
}