{
  "type": "Feature",
  "properties": {
    "iso:country":"GB",
    "sg:address":"Braich Dinas, Cwn Pennant",
    "sg:city":"Garndolbenmaen",
    "sg:classifiers":[
        {
            "category":"Farming",
            "subcategory":"Farm",
            "type":"Manufacturing & Wholesale Goods"
        }
    ],
    "sg:phone":"+44 1766 530273",
    "sg:postcode":"LL51 9AX",
    "sg:province":"Gwynedd",
    "sg:tags":[
        "mixed",
        "crop"
    ],
    "wof:name":"John R R Evans",
    "wof:placetype":"venue"
},
  "geometry": {"coordinates":[-4.239294,52.97353],"type":"Point"}
}