{
  "type": "Feature",
  "properties": {
    "addr:full":"P O Box 153 Manchester Greater Manchester M60 1LP",
    "addr:housenumber":"153",
    "addr:postcode":"m60 1lp",
    "addr:street":"P O Box",
    "iso:country":"GB",
    "sg:address":"P O Box 153",
    "sg:city":"Manchester",
    "sg:classifiers":[
        {
            "category":"Professional",
            "subcategory":"Lawyer & Legal Services",
            "type":"Services"
        }
    ],
    "sg:phone":"+44 161 274 3990",
    "sg:postcode":"M60 1LP",
    "sg:province":"Greater Manchester",
    "sg:tags":[
        "advice",
        "counselling"
    ],
    "wof:name":"Manchester Lesbian & Gay Switchboard Services",
    "wof:placetype":"venue"
},
  "geometry": {"coordinates":[-2.2488100529,53.4796218872],"type":"Point"}
}