{
  "type": "Feature",
  "properties": {
    "addr:full":"Coombe Cottage, Spring Hill, Fordcombe Tunbridge Wells East Sussex TN3 0SB",
    "addr:postcode":"tn3 0sb",
    "addr:street":"Spring Hill Fordcombe",
    "iso:country":"GB",
    "sg:address":"Coombe Cottage, Spring Hill, Fordcombe",
    "sg:city":"Tunbridge Wells",
    "sg:classifiers":[
        {
            "category":"Professional",
            "subcategory":"Management & Consulting",
            "type":"Services"
        }
    ],
    "sg:phone":"+44 1892 740952",
    "sg:postcode":"TN3 0SB",
    "sg:province":"East Sussex",
    "sg:tags":[
        "consultant",
        "business"
    ],
    "wof:name":"John Cunliffe",
    "wof:placetype":"venue"
},
  "geometry": {"coordinates":[0.1826030016,51.1399803162],"type":"Point"}
}