{
  "type": "Feature",
  "properties": {
    "iso:country":"GB",
    "sg:address":"5th Floor, Bridewell House, 9 Bridewell Place",
    "sg:city":"London",
    "sg:classifiers":[
        {
            "category":"Professional",
            "subcategory":"Research",
            "type":"Services"
        }
    ],
    "sg:phone":"+44 20 7896 1900",
    "sg:postcode":"EC4V 6AY",
    "sg:province":"Greater London",
    "sg:tags":[
        "market"
    ],
    "wof:name":"LightspeedReasearch.com",
    "wof:placetype":"venue"
},
  "geometry": {"coordinates":[-0.104783,51.512749],"type":"Point"}
}