{
  "type": "Feature",
  "properties": {
    "iso:country":"GB",
    "sg:address":"Unit B305, The Sanderson Centre, Lees Lane",
    "sg:city":"Gosport",
    "sg:classifiers":[
        {
            "category":"Building & Trades",
            "subcategory":"Plumbing",
            "type":"Services"
        },
        {
            "category":"Building & Trades",
            "subcategory":"Construction",
            "type":"Services"
        }
    ],
    "sg:phone":"+44 23 9252 5973",
    "sg:postcode":"PO12 3UL",
    "sg:province":"Hampshire",
    "sg:tags":[
        "central",
        "installation",
        "system",
        "servicing",
        "heating"
    ],
    "wof:name":"Hot House Heating",
    "wof:placetype":"venue"
},
  "geometry": {"coordinates":[-1.121534,50.794361],"type":"Point"}
}