{
  "type": "Feature",
  "properties": {
    "addr:full":"6 Westgate Street Launceston Cornwall PL15 7AB",
    "addr:housenumber":"6",
    "addr:postcode":"pl15 7ab",
    "addr:street":"Westgate Street",
    "iso:country":"GB",
    "sg:address":"6 Westgate Street",
    "sg:city":"Launceston",
    "sg:classifiers":[
        {
            "category":"Shopping",
            "subcategory":"Gifts & Souvenirs",
            "type":"Retail Goods"
        }
    ],
    "sg:phone":"+44 1566 773173",
    "sg:postcode":"PL15 7AB",
    "sg:province":"Cornwall",
    "sg:tags":[
        "poster",
        "card"
    ],
    "wof:name":"Pats Greeting Cards",
    "wof:placetype":"venue"
},
  "geometry": {"coordinates":[-4.3612499237,50.6363105774],"type":"Point"}
}