{
  "type": "Feature",
  "properties": {
    "addr:full":"159 High St Rayleigh Essex SS6 7QA",
    "addr:housenumber":"159",
    "addr:postcode":"ss6 7qa",
    "addr:street":"High St Rayleigh",
    "iso:country":"GB",
    "sg:address":"159 High St",
    "sg:city":"Rayleigh",
    "sg:classifiers":[
        {
            "category":"Fast Food",
            "type":"Food & Drink"
        }
    ],
    "sg:phone":"+44 1268 770768",
    "sg:postcode":"SS6 7QA",
    "sg:province":"Essex",
    "sg:tags":[
        "away",
        "take"
    ],
    "wof:name":"Rayleigh Spicy",
    "wof:placetype":"venue"
},
  "geometry": {"coordinates":[0.603158,51.584496],"type":"Point"}
}