{
  "type": "Feature",
  "properties": {
    "addr:full":"High St Bridgwater Somerset TA6 3BE",
    "addr:postcode":"ta6 3be",
    "addr:street":"High St",
    "iso:country":"GB",
    "sg:address":"High St",
    "sg:city":"Bridgwater",
    "sg:classifiers":[
        {
            "category":"Professional",
            "subcategory":"Business Services",
            "type":"Services"
        }
    ],
    "sg:phone":"+44 1278 451767",
    "sg:postcode":"TA6 3BE",
    "sg:province":"Somerset",
    "sg:tags":[
        "operator",
        "market"
    ],
    "wof:name":"Cornhill Market",
    "wof:placetype":"venue"
},
  "geometry": {"coordinates":[-3.0052990913,51.1281547546],"type":"Point"}
}