{
  "type": "Feature",
  "properties": {
    "addr:full":"169 Walford Road Birmingham West Midlands B11 1QJ",
    "addr:housenumber":"169",
    "addr:postcode":"b11 1qj",
    "addr:street":"Walford Road",
    "iso:country":"GB",
    "sg:address":"169 Walford Road",
    "sg:city":"Birmingham",
    "sg:classifiers":[
        {
            "category":"Food & Beverages",
            "subcategory":"Meat & Fish",
            "type":"Retail Goods"
        }
    ],
    "sg:phone":"+44 121 772 1749",
    "sg:postcode":"B11 1QJ",
    "sg:province":"West Midlands",
    "sg:tags":[
        "chip"
    ],
    "wof:name":"The Best Chip Shop",
    "wof:placetype":"venue"
},
  "geometry": {"coordinates":[-1.863732,52.459583],"type":"Point"}
}