{
  "type": "Feature",
  "properties": {
    "addr:full":"Buckfastleigh Medical Centre, Bossell Rd Buckfastleigh Devon TQ11 0DD",
    "addr:postcode":"tq11 0dd",
    "addr:street":"Bossell Rd",
    "iso:country":"GB",
    "sg:address":"Buckfastleigh Medical Centre, Bossell Rd",
    "sg:city":"Buckfastleigh",
    "sg:classifiers":[
        {
            "category":"Health Services",
            "subcategory":"Doctor",
            "type":"Services"
        }
    ],
    "sg:phone":"+44 1364 642534",
    "sg:postcode":"TQ11 0DD",
    "sg:province":"Devon",
    "sg:tags":[
        "practitioners"
    ],
    "wof:name":"Barton, T",
    "wof:placetype":"venue"
},
  "geometry": {"coordinates":[-3.779209,50.481369],"type":"Point"}
}