{
  "type": "Feature",
  "properties": {
    "addr:full":"Leabank 5 Mcbey Way, Foveran Ellon Aberdeenshire AB41 6AG",
    "addr:housenumber":"5",
    "addr:postcode":"ab41 6ag",
    "addr:street":"Leabank;Mcbey Way",
    "iso:country":"GB",
    "sg:address":"Leabank 5 Mcbey Way, Foveran",
    "sg:city":"Ellon",
    "sg:classifiers":[
        {
            "category":"Banks & Credit Unions",
            "subcategory":"Bank",
            "type":"Services"
        }
    ],
    "sg:phone":"+44 1358 789399",
    "sg:postcode":"AB41 6AG",
    "sg:province":"Aberdeenshire",
    "sg:tags":[
        "broker",
        "mortgage"
    ],
    "wof:name":"Fisher Financial Services",
    "wof:placetype":"venue"
},
  "geometry": {"coordinates":[-2.046583,57.305706],"type":"Point"}
}