{
  "type": "Feature",
  "properties": {
    "addr:full":"32 East Hill Colchester Essex CO1 2QX",
    "addr:housenumber":"32",
    "addr:postcode":"co1 2qx",
    "addr:street":"East Hill Colchester",
    "iso:country":"GB",
    "sg:address":"32 East Hill",
    "sg:city":"Colchester",
    "sg:classifiers":[
        {
            "category":"Insurance",
            "subcategory":"Insurance Agent",
            "type":"Services"
        }
    ],
    "sg:phone":"+44 1206 792927",
    "sg:postcode":"CO1 2QX",
    "sg:province":"Essex",
    "wof:name":"Colchester Insurance Centre",
    "wof:placetype":"venue"
},
  "geometry": {"coordinates":[0.9109209776,51.8897781372],"type":"Point"}
}