{
  "type": "Feature",
  "properties": {
    "addr:full":"341 Goldington Road Bedford Bedfordshire MK41 9PA",
    "addr:housenumber":"341",
    "addr:postcode":"mk41 9pa",
    "addr:street":"Goldington Road",
    "iso:country":"GB",
    "sg:address":"341 Goldington Road",
    "sg:city":"Bedford",
    "sg:classifiers":[
        {
            "category":"Autos & Motor Vehicles",
            "subcategory":"Auto Supplies",
            "type":"Retail Goods"
        }
    ],
    "sg:postcode":"MK41 9PA",
    "sg:province":"Bedfordshire",
    "sg:tags":[
        "car",
        "audio"
    ],
    "wof:name":"Inca Bedford",
    "wof:placetype":"venue"
},
  "geometry": {"coordinates":[-0.431939,52.14246],"type":"Point"}
}