{
  "type": "Feature",
  "properties": {
    "addr:full":"40 Main Street Mexborough South Yorkshire S64 9DU",
    "addr:housenumber":"40",
    "addr:postcode":"s64 9du",
    "addr:street":"Main Street",
    "iso:country":"GB",
    "sg:address":"40 Main Street",
    "sg:city":"Mexborough",
    "sg:classifiers":[
        {
            "category":"Organizations",
            "subcategory":"Membership Organization",
            "type":"Services"
        }
    ],
    "sg:phone":"+44 1709 582136",
    "sg:postcode":"S64 9DU",
    "sg:province":"South Yorkshire",
    "sg:tags":[
        "club"
    ],
    "wof:name":"Main Street Working Mens Club & Institute",
    "wof:placetype":"venue"
},
  "geometry": {"coordinates":[-1.2950960398,53.4943733215],"type":"Point"}
}