{
  "type": "Feature",
  "properties": {
    "addr:full":"58 Barrington Road Altrincham Cheshire WA14 1HY",
    "addr:housenumber":"58",
    "addr:postcode":"wa14 1hy",
    "addr:street":"Barrington Road",
    "iso:country":"GB",
    "sg:address":"58 Barrington Road",
    "sg:city":"Altrincham",
    "sg:classifiers":[
        {
            "category":"Travel",
            "subcategory":"Hotels & Motels",
            "type":"Entertainment"
        }
    ],
    "sg:postcode":"WA14 1HY",
    "sg:province":"Cheshire",
    "sg:tags":[
        "house",
        "guest"
    ],
    "wof:name":"Belvedere Guest House",
    "wof:placetype":"venue"
},
  "geometry": {"coordinates":[-2.3493230343,53.3937416077],"type":"Point"}
}