{
  "type": "Feature",
  "properties": {
    "addr:full":"32-34 Station Street Keswick Cumbria CA12 5HF",
    "addr:housenumber":"32-34",
    "addr:postcode":"ca12 5hf",
    "addr:street":"Station Street",
    "iso:country":"GB",
    "sg:address":"32-34 Station Street",
    "sg:city":"Keswick",
    "sg:classifiers":[
        {
            "category":"Communications",
            "subcategory":"Newspaper",
            "type":"Services"
        },
        {
            "category":"Professional",
            "subcategory":"Printing & Photocopies",
            "type":"Services"
        }
    ],
    "sg:phone":"+44 17687 72140",
    "sg:postcode":"CA12 5HF",
    "sg:province":"Cumbria",
    "sg:tags":[
        "magazine",
        "printer"
    ],
    "wof:name":"G W McKane & Son",
    "wof:placetype":"venue"
},
  "geometry": {"coordinates":[-3.1347589493,54.600933075],"type":"Point"}
}