{
  "type": "Feature",
  "properties": {
    "addr:full":"11c South Park Road Scunthorpe Lincolnshire DN17 2BY",
    "addr:housenumber":"11c",
    "addr:postcode":"dn17 2by",
    "addr:street":"South Park Road",
    "iso:country":"GB",
    "sg:address":"11c South Park Road",
    "sg:city":"Scunthorpe",
    "sg:classifiers":[
        {
            "category":"Freight",
            "type":"Transportation"
        }
    ],
    "sg:phone":"+44 1724 289727",
    "sg:postcode":"DN17 2BY",
    "sg:province":"Lincolnshire",
    "sg:tags":[
        "haulage",
        "road"
    ],
    "wof:name":"M.B.K Transport",
    "wof:placetype":"venue"
},
  "geometry": {"coordinates":[-0.680591,53.556316],"type":"Point"}
}