{
  "type": "Feature",
  "properties": {
    "iso:country":"GB",
    "sg:address":"190 Trundleys Road",
    "sg:city":"London",
    "sg:classifiers":[
        {
            "category":"Fast Food",
            "type":"Food & Drink"
        }
    ],
    "sg:postcode":"SE8 5JE",
    "sg:province":"Greater London",
    "sg:tags":[
        "away",
        "take"
    ],
    "wof:name":"Heather's Cafe",
    "wof:placetype":"venue"
},
  "geometry": {"coordinates":[-0.041751,51.483372],"type":"Point"}
}