{
  "type": "Feature",
  "properties": {
    "addr:full":"7 Stour Road, Bathside Harwich Essex CO12 3HF",
    "addr:housenumber":"7",
    "addr:postcode":"co12 3hf",
    "addr:street":"Stour Road Bathside Harwich",
    "iso:country":"GB",
    "sg:address":"7 Stour Road, Bathside",
    "sg:city":"Harwich",
    "sg:classifiers":[
        {
            "category":"Bars & Pubs",
            "type":"Food & Drink"
        }
    ],
    "sg:postcode":"CO12 3HF",
    "sg:province":"Essex",
    "sg:tags":[
        "pubs",
        "inn"
    ],
    "wof:name":"The Anchor",
    "wof:placetype":"venue"
},
  "geometry": {"coordinates":[1.285665,51.944859],"type":"Point"}
}