{
  "type": "Feature",
  "properties": {
    "addr:full":"The Dods Lauder Scottish Borders TD2 6SD",
    "addr:postcode":"td2 6sd",
    "iso:country":"GB",
    "sg:address":"The Dods",
    "sg:city":"Lauder",
    "sg:classifiers":[
        {
            "category":"Farming",
            "subcategory":"Dairy Farm",
            "type":"Manufacturing & Wholesale Goods"
        }
    ],
    "sg:phone":"+44 15395 36419",
    "sg:postcode":"TD2 6SD",
    "sg:province":"Scottish Borders",
    "wof:name":"Lauder Farms Ltd.",
    "wof:placetype":"venue"
},
  "geometry": {"coordinates":[-2.750079,55.720119],"type":"Point"}
}