{
  "type": "Feature",
  "properties": {
    "addr:full":"390 Bolton Road, Aspull Wigan Lancashire WN2 1PR",
    "addr:housenumber":"390",
    "addr:postcode":"wn2 1pr",
    "addr:street":"Bolton Road Aspull",
    "iso:country":"GB",
    "sg:address":"390 Bolton Road, Aspull",
    "sg:city":"Wigan",
    "sg:classifiers":[
        {
            "category":"Professional",
            "subcategory":"Computer Services",
            "type":"Services"
        }
    ],
    "sg:phone":"+44 1942 833402",
    "sg:postcode":"WN2 1PR",
    "sg:province":"Lancashire",
    "sg:tags":[
        "system",
        "software"
    ],
    "wof:name":"R & R Associates",
    "wof:placetype":"venue"
},
  "geometry": {"coordinates":[-2.5730259418,53.5633621216],"type":"Point"}
}