{
  "type": "Feature",
  "properties": {
    "iso:country":"GB",
    "sg:address":"Enquires, Crewe Rd",
    "sg:city":"Crewe",
    "sg:classifiers":[
        {
            "category":"Health Services",
            "subcategory":"Doctor",
            "type":"Services"
        }
    ],
    "sg:phone":"+44 1270 581259",
    "sg:postcode":"CW1 5QX",
    "sg:province":"Cheshire",
    "sg:tags":[
        "practitioners"
    ],
    "wof:name":"Haslington Surgery",
    "wof:placetype":"venue"
},
  "geometry": {"coordinates":[-2.409806,53.095119],"type":"Point"}
}