{
  "type": "Feature",
  "properties": {
    "iso:country":"GB",
    "sg:address":"6 Elystan Street",
    "sg:city":"London",
    "sg:classifiers":[
        {
            "category":"Shopping",
            "subcategory":"Pharmacy",
            "type":"Retail Goods"
        }
    ],
    "sg:phone":"+44 20 7584 5424",
    "sg:postcode":"SW3 3NS",
    "sg:province":"Greater London",
    "sg:tags":[
        "pharmacist",
        "chemist"
    ],
    "wof:name":"Astell Pharmacy",
    "wof:placetype":"venue"
},
  "geometry": {"coordinates":[-0.16607,51.490799],"type":"Point"}
}