{
  "type": "Feature",
  "properties": {
    "iso:country":"GB",
    "sg:address":"Mansion House, 19 Kingfield Road",
    "sg:city":"Sheffield",
    "sg:classifiers":[
        {
            "category":"Wholesale",
            "subcategory":"Books, Periodicals, & Newspapers",
            "type":"Manufacturing & Wholesale Goods"
        }
    ],
    "sg:phone":"+44 114 255 4433",
    "sg:postcode":"S11 9AS",
    "sg:province":"Derbyshire",
    "sg:tags":[
        "publishing"
    ],
    "wof:name":"Sheffield Academic Press Ltd.",
    "wof:placetype":"venue"
},
  "geometry": {"coordinates":[-1.4965820312,53.3632354736],"type":"Point"}
}