{
  "type": "Feature",
  "properties": {
    "addr:full":"507 Bradford Road Batley West Yorkshire WF17 8LL",
    "addr:housenumber":"507",
    "addr:postcode":"wf17 8ll",
    "addr:street":"Bradford Road",
    "iso:country":"GB",
    "sg:address":"507 Bradford Road",
    "sg:city":"Batley",
    "sg:classifiers":[
        {
            "category":"Museum",
            "subcategory":"Aquarium",
            "type":"Entertainment"
        }
    ],
    "sg:postcode":"WF17 8LL",
    "sg:province":"West Yorkshire",
    "sg:tags":[
        "vivarium",
        "mnfrs"
    ],
    "wof:name":"System 2000 Uk Ltd",
    "wof:placetype":"venue"
},
  "geometry": {"coordinates":[-1.639434,53.718502],"type":"Point"}
}