{
  "type": "Feature",
  "properties": {
    "addr:full":"Unit 11 Crompton Road, Hadleigh Road Industrial Estate Ipswich Suffolk IP2 0UQ",
    "addr:housenumber":"unit 11",
    "addr:postcode":"ip2 0uq",
    "addr:street":"Crompton Road Hadleigh Road Industrial Estate",
    "iso:country":"GB",
    "sg:address":"Unit 11 Crompton Road, Hadleigh Road Industrial Estate",
    "sg:city":"Ipswich",
    "sg:classifiers":[
        {
            "category":"Structure",
            "subcategory":"Warehouse",
            "type":"Public Place"
        }
    ],
    "sg:phone":"+44 1473 210459",
    "sg:postcode":"IP2 0UQ",
    "sg:province":"Suffolk",
    "wof:name":"Arrowpak International",
    "wof:placetype":"venue"
},
  "geometry": {"coordinates":[1.1284400225,52.0624465942],"type":"Point"}
}