{
  "type": "Feature",
  "properties": {
    "iso:country":"GB",
    "sg:address":"J S S Pinnacle House, 35 Battersea Square",
    "sg:city":"London",
    "sg:classifiers":[
        {
            "category":"Professional",
            "subcategory":"Management & Consulting",
            "type":"Services"
        }
    ],
    "sg:postcode":"SW11 3RA",
    "sg:province":"Greater London",
    "sg:tags":[
        "consultant",
        "business"
    ],
    "wof:name":"Seventeen Cadogan Square Management Ltd",
    "wof:placetype":"venue"
},
  "geometry": {"coordinates":[-0.17496,51.47472],"type":"Point"}
}