{
  "type": "Feature",
  "properties": {
    "iso:country":"GB",
    "sg:address":"Oxford La",
    "sg:city":"Halstead",
    "sg:classifiers":[
        {
            "category":"Retail",
            "subcategory":"Auto Rental",
            "type":"Services"
        }
    ],
    "sg:phone":"+44 1787 461633",
    "sg:postcode":"CO9 3LE",
    "sg:province":"Essex",
    "sg:tags":[
        "truck",
        "hire",
        "van"
    ],
    "wof:name":"Transfleet Services Ltd",
    "wof:placetype":"venue"
},
  "geometry": {"coordinates":[0.583801,51.982655],"type":"Point"}
}