{
  "type": "Feature",
  "properties": {
    "iso:country":"GB",
    "sg:address":"298-300 Maxwell Rd",
    "sg:city":"Glasgow",
    "sg:classifiers":[
        {
            "category":"Professional",
            "subcategory":"Lawyer & Legal Services",
            "type":"Services"
        }
    ],
    "sg:phone":"+44 141 429 4545",
    "sg:postcode":"G41 1PJ",
    "sg:province":"Glasgow City",
    "sg:tags":[
        "patent",
        "agent"
    ],
    "wof:name":"Churahi Enterprises Ltd",
    "wof:placetype":"venue"
},
  "geometry": {"coordinates":[-4.2734298706,55.8444786072],"type":"Point"}
}