{
  "type": "Feature",
  "properties": {
    "iso:country":"GB",
    "sg:address":"Manor Farm, Winterbourne Earls",
    "sg:city":"Salisbury",
    "sg:classifiers":[
        {
            "category":"Farming",
            "subcategory":"Farm",
            "type":"Manufacturing & Wholesale Goods"
        }
    ],
    "sg:phone":"+44 1980 611260",
    "sg:postcode":"SP4 6HD",
    "sg:province":"Hampshire",
    "sg:tags":[
        "mixed",
        "crop"
    ],
    "wof:name":"D B Harvey Partnership",
    "wof:placetype":"venue"
},
  "geometry": {"coordinates":[-1.779029,51.097065],"type":"Point"}
}