{
  "type": "Feature",
  "properties": {
    "addr:full":"Olde Farm, Woolscott Road Rugby Northamptonshire CV23 8DA",
    "addr:postcode":"cv23 8da",
    "addr:street":"Woolscott Road",
    "iso:country":"GB",
    "sg:address":"Olde Farm, Woolscott Road",
    "sg:city":"Rugby",
    "sg:classifiers":[
        {
            "category":"Farming",
            "subcategory":"Farm",
            "type":"Manufacturing & Wholesale Goods"
        }
    ],
    "sg:phone":"+44 1788 810285",
    "sg:postcode":"CV23 8DA",
    "sg:province":"Northamptonshire",
    "sg:tags":[
        "mixed",
        "crop"
    ],
    "wof:name":"D N Carter & Co.",
    "wof:placetype":"venue"
},
  "geometry": {"coordinates":[-1.2745460272,52.3078308105],"type":"Point"}
}