{
  "type": "Feature",
  "properties": {
    "addr:full":"492 Stafford Road Wolverhampton Staffordshire WV10 6AN",
    "addr:housenumber":"492",
    "addr:postcode":"wv10 6an",
    "addr:street":"Stafford Road",
    "iso:country":"GB",
    "sg:address":"492 Stafford Road",
    "sg:city":"Wolverhampton",
    "sg:classifiers":[
        {
            "category":"Retail",
            "subcategory":"Funeral Services",
            "type":"Services"
        },
        {
            "category":"Food & Beverages",
            "subcategory":"Supermarket",
            "type":"Retail Goods"
        }
    ],
    "sg:postcode":"WV10 6AN",
    "sg:province":"Staffordshire",
    "wof:name":"Co-Operative Funeral Services",
    "wof:placetype":"venue"
},
  "geometry": {"coordinates":[-2.1298189163,52.6193122864],"type":"Point"}
}