{
  "type": "Feature",
  "properties": {
    "addr:full":"Birchwood La Alfreton Derbyshire DE55 4LZ",
    "addr:postcode":"de55 4lz",
    "addr:street":"Birchwood La Alfreton",
    "iso:country":"GB",
    "sg:address":"Birchwood La",
    "sg:city":"Alfreton",
    "sg:classifiers":[
        {
            "category":"Place Of Worship",
            "type":"Public Place"
        }
    ],
    "sg:phone":"+44 1773 602994",
    "sg:postcode":"DE55 4LZ",
    "sg:province":"Derbyshire",
    "wof:name":"Birchwood Methodist Church",
    "wof:placetype":"venue"
},
  "geometry": {"coordinates":[-1.3561580181,53.0816192627],"type":"Point"}
}