{
  "type": "Feature",
  "properties": {
    "addr:full":"Joinery Works, Main Street, Kirbymisterton Malton North Yorkshire YO17 6XL",
    "addr:postcode":"yo17 6xl",
    "addr:street":"Main Street Kirbymisterton",
    "iso:country":"GB",
    "sg:address":"Joinery Works, Main Street, Kirbymisterton",
    "sg:city":"Malton",
    "sg:classifiers":[
        {
            "category":"Building & Trades",
            "subcategory":"Construction",
            "type":"Services"
        }
    ],
    "sg:postcode":"YO17 6XL",
    "sg:province":"North Yorkshire",
    "sg:tags":[
        "joinery"
    ],
    "wof:name":"W Harding & Sons",
    "wof:placetype":"venue"
},
  "geometry": {"coordinates":[-0.7880430222,54.1468658447],"type":"Point"}
}