{
  "type": "Feature",
  "properties": {
    "addr:full":"178 Queensway, Bletchley Milton Keynes Buckinghamshire MK2 2SW",
    "addr:housenumber":"178",
    "addr:postcode":"mk2 2sw",
    "addr:street":"Queensway",
    "iso:country":"GB",
    "sg:address":"178 Queensway, Bletchley",
    "sg:city":"Milton Keynes",
    "sg:classifiers":[
        {
            "category":"Travel",
            "subcategory":"Travel Agent",
            "type":"Entertainment"
        }
    ],
    "sg:phone":"+44 1908 632634",
    "sg:postcode":"MK2 2SW",
    "sg:province":"Buckinghamshire",
    "wof:name":"Bailey's Travel Business Line",
    "wof:placetype":"venue"
},
  "geometry": {"coordinates":[-0.7276219726,51.9950180054],"type":"Point"}
}