{
  "type": "Feature",
  "properties": {
    "iso:country":"GB",
    "sg:address":"Stone Rd, Hanford",
    "sg:city":"Stoke On Trent",
    "sg:classifiers":[
        {
            "category":"Autos & Motor Vehicles",
            "subcategory":"Fuel & Gas Station",
            "type":"Retail Goods"
        }
    ],
    "sg:phone":"+44 1782 654800",
    "sg:postcode":"ST4 4QA",
    "sg:province":"Staffordshire",
    "sg:tags":[
        "petrol",
        "filling"
    ],
    "wof:name":"Total Convenience Stores",
    "wof:placetype":"venue"
},
  "geometry": {"coordinates":[-2.199499,52.980663],"type":"Point"}
}