{
  "type": "Feature",
  "properties": {
    "addr:full":"Piccadilly House, 40 Stott Hill Bradford West Yorkshire BD1 4EH",
    "addr:housenumber":"40",
    "addr:postcode":"bd1 4eh",
    "addr:street":"Stott Hill Bradford West",
    "iso:country":"GB",
    "sg:address":"Piccadilly House, 40 Stott Hill",
    "sg:city":"Bradford",
    "sg:classifiers":[
        {
            "category":"Building & Trades",
            "subcategory":"Construction",
            "type":"Services"
        }
    ],
    "sg:phone":"+44 1274 737890",
    "sg:postcode":"BD1 4EH",
    "sg:province":"West Yorkshire",
    "sg:tags":[
        "builder"
    ],
    "wof:name":"Stainforth Construction Ltd.",
    "wof:placetype":"venue"
},
  "geometry": {"coordinates":[-1.7477259636,53.7960395813],"type":"Point"}
}