{
  "type": "Feature",
  "properties": {
    "iso:country":"GB",
    "sg:address":"85 Darlington Street",
    "sg:city":"Wolverhampton",
    "sg:classifiers":[
        {
            "category":"Home & Garden",
            "subcategory":"Home Furnishings",
            "type":"Retail Goods"
        }
    ],
    "sg:phone":"+44 1902 425616",
    "sg:postcode":"WV1 4NG",
    "sg:province":"West Midlands",
    "sg:tags":[
        "beds",
        "bedding",
        "blanket"
    ],
    "wof:name":"Baynell Ltd.",
    "wof:placetype":"venue"
},
  "geometry": {"coordinates":[-2.1311540604,52.5854873657],"type":"Point"}
}