{
  "type": "Feature",
  "properties": {
    "iso:country":"GB",
    "sg:address":"Woodhouse Lane",
    "sg:city":"Manchester",
    "sg:classifiers":[
        {
            "category":"Education",
            "subcategory":"School",
            "type":"Public Place"
        }
    ],
    "sg:phone":"+44 161 998 3422",
    "sg:postcode":"M22 9NW",
    "sg:province":"Greater Manchester",
    "sg:tags":[
        "local",
        "authority"
    ],
    "wof:name":"ST JOHN FISHER & ST THOMAS MORE R C PRIMARY SCHOOL",
    "wof:placetype":"venue"
},
  "geometry": {"coordinates":[-2.261819,53.381554],"type":"Point"}
}