{
  "type": "Feature",
  "properties": {
    "iso:country":"GB",
    "sg:address":"3 Priory Rd, Bicknacre",
    "sg:city":"Chelmsford",
    "sg:classifiers":[
        {
            "category":"Health Services",
            "subcategory":"Doctor",
            "type":"Services"
        }
    ],
    "sg:phone":"+44 1245 224253",
    "sg:postcode":"CM3 4EY",
    "sg:province":"Essex",
    "sg:tags":[
        "practitioners"
    ],
    "wof:name":"S.G Wagle",
    "wof:placetype":"venue"
},
  "geometry": {"coordinates":[0.58252,51.69342],"type":"Point"}
}