{
  "type": "Feature",
  "properties": {
    "iso:country":"GB",
    "sg:address":"1 Bank Street, Williton",
    "sg:city":"Taunton",
    "sg:classifiers":[
        {
            "category":"Insurance",
            "subcategory":"Insurance Agent",
            "type":"Services"
        }
    ],
    "sg:phone":"+44 1984 633220",
    "sg:postcode":"TA4 4NG",
    "sg:province":"Devon",
    "wof:name":"The National Farmers Union",
    "wof:placetype":"venue"
},
  "geometry": {"coordinates":[-3.3214719296,51.1600341797],"type":"Point"}
}