{
  "type": "Feature",
  "properties": {
    "iso:country":"GB",
    "sg:address":"Watkins Rise",
    "sg:city":"Potters Bar",
    "sg:classifiers":[
        {
            "category":"Education",
            "subcategory":"School",
            "type":"Public Place"
        }
    ],
    "sg:phone":"+44 1707 652882",
    "sg:postcode":"EN6 1QB",
    "sg:province":"Greater London",
    "sg:tags":[
        "local",
        "authority"
    ],
    "wof:name":"Ladbrooke Junior Mixed Infant School",
    "wof:placetype":"venue"
},
  "geometry": {"coordinates":[-0.1793989986,51.6957397461],"type":"Point"}
}