{
  "type": "Feature",
  "properties": {
    "addr:full":"Huxley Close, Newnham Industrial Estate, Plympton Plymouth Devon PL7 4JN",
    "addr:postcode":"pl7 4jn",
    "addr:street":"Huxley Close;Industrial Estate",
    "iso:country":"GB",
    "sg:address":"Huxley Close, Newnham Industrial Estate, Plympton",
    "sg:city":"Plymouth",
    "sg:classifiers":[
        {
            "category":"Retail",
            "subcategory":"Auto Repair",
            "type":"Services"
        }
    ],
    "sg:phone":"+44 1752 343368",
    "sg:postcode":"PL7 4JN",
    "sg:province":"Devon",
    "sg:tags":[
        "modification",
        "garage",
        "related"
    ],
    "wof:name":"D J Transmissions Ltd.",
    "wof:placetype":"venue"
},
  "geometry": {"coordinates":[-4.0462050438,50.3953056335],"type":"Point"}
}