{
  "type": "Feature",
  "properties": {
    "addr:full":", Whatlington Battle East Sussex TN33 0NJ",
    "addr:housenumber":"whatlington",
    "addr:postcode":"tn33 0nj",
    "addr:street":"Battle",
    "iso:country":"GB",
    "sg:address":", Whatlington",
    "sg:city":"Battle",
    "sg:classifiers":[
        {
            "category":"Bars & Pubs",
            "type":"Food & Drink"
        }
    ],
    "sg:phone":"+44 1424 870492",
    "sg:postcode":"TN33 0NJ",
    "sg:province":"East Sussex",
    "sg:tags":[
        "pubs",
        "inn"
    ],
    "wof:name":"Royal Oak",
    "wof:placetype":"venue"
},
  "geometry": {"coordinates":[0.4890249968,50.9146156311],"type":"Point"}
}