{
  "type": "Feature",
  "properties": {
    "addr:full":"4 Dunhill Crescent Leeds West Yorkshire LS9 0EN",
    "addr:housenumber":"4",
    "addr:postcode":"ls9 0en",
    "addr:street":"Dunhill Crescent",
    "iso:country":"GB",
    "sg:address":"4 Dunhill Crescent",
    "sg:city":"Leeds",
    "sg:classifiers":[
        {
            "category":"Building & Trades",
            "subcategory":"Plumbing",
            "type":"Services"
        },
        {
            "category":"Building & Trades",
            "subcategory":"Construction",
            "type":"Services"
        }
    ],
    "sg:phone":"+44 113 248 6757",
    "sg:postcode":"LS9 0EN",
    "sg:province":"West Yorkshire",
    "sg:tags":[
        "central",
        "installation",
        "system",
        "servicing",
        "heating"
    ],
    "wof:name":"Greaves Plumbing Services",
    "wof:placetype":"venue"
},
  "geometry": {"coordinates":[-1.481233,53.800747],"type":"Point"}
}