{
  "type": "Feature",
  "properties": {
    "addr:full":"184 Tottenham Lane London Greater London N8 8SG",
    "addr:housenumber":"184",
    "addr:postcode":"n8 8sg",
    "addr:street":"Tottenham Lane",
    "iso:country":"GB",
    "sg:address":"184 Tottenham Lane",
    "sg:city":"London",
    "sg:classifiers":[
        {
            "category":"Social Services",
            "subcategory":"Child Care",
            "type":"Services"
        },
        {
            "category":"Arena",
            "subcategory":"Sports Club",
            "type":"Entertainment"
        }
    ],
    "sg:phone":"+44 20 8340 2345",
    "sg:postcode":"N8 8SG",
    "sg:province":"Greater London",
    "sg:tags":[
        "school"
    ],
    "wof:name":"Hornsey Ymca Ltd",
    "wof:placetype":"venue"
},
  "geometry": {"coordinates":[-0.120352,51.582016],"type":"Point"}
}