{
  "type": "Feature",
  "properties": {
    "addr:full":"23 Broadway, Ponteland Newcastle-upon-tyne Northumberland NE20 9PW",
    "addr:housenumber":"23",
    "addr:postcode":"ne20 9pw",
    "addr:street":"Broadway",
    "iso:country":"GB",
    "sg:address":"23 Broadway, Ponteland",
    "sg:city":"Newcastle-upon-tyne",
    "sg:classifiers":[
        {
            "category":"Banks & Credit Unions",
            "subcategory":"Financial Services",
            "type":"Services"
        }
    ],
    "sg:phone":"+44 1661 821828",
    "sg:postcode":"NE20 9PW",
    "sg:province":"Northumberland",
    "sg:tags":[
        "building",
        "society"
    ],
    "wof:name":"Universal Building Society",
    "wof:placetype":"venue"
},
  "geometry": {"coordinates":[-1.7646729946,55.0366020203],"type":"Point"}
}