{
  "type": "Feature",
  "properties": {
    "addr:full":"19 Natal Rd Thornton Heath Surrey CR7 8QH",
    "addr:housenumber":"19",
    "addr:postcode":"cr7 8qh",
    "addr:street":"Natal Rd",
    "iso:country":"GB",
    "sg:address":"19 Natal Rd",
    "sg:city":"Thornton Heath",
    "sg:classifiers":[
        {
            "category":"Social Services",
            "subcategory":"Retirement Home",
            "type":"Services"
        }
    ],
    "sg:phone":"+44 20 8653 6134",
    "sg:postcode":"CR7 8QH",
    "sg:province":"Surrey",
    "sg:tags":[
        "residential",
        "care"
    ],
    "wof:name":"Natal Lodge Residential Home",
    "wof:placetype":"venue"
},
  "geometry": {"coordinates":[-0.095579,51.401985],"type":"Point"}
}