{
  "type": "Feature",
  "properties": {
    "addr:full":"Crowcroft House Farm, Crowcroft, Leigh Sinton Malvern Gloucestershire WR13 5ED",
    "addr:postcode":"wr13 5ed",
    "addr:street":"Crowcroft",
    "iso:country":"GB",
    "sg:address":"Crowcroft House Farm, Crowcroft, Leigh Sinton",
    "sg:city":"Malvern",
    "sg:classifiers":[
        {
            "category":"Home & Garden",
            "subcategory":"Garden Supply",
            "type":"Retail Goods"
        }
    ],
    "sg:phone":"+44 1886 833786",
    "sg:postcode":"WR13 5ED",
    "sg:province":"Gloucestershire",
    "sg:tags":[
        "nursery",
        "tree",
        "shrub",
        "centre"
    ],
    "wof:name":"Clem Rose Nurseries",
    "wof:placetype":"venue"
},
  "geometry": {"coordinates":[-2.3226940632,52.1554718018],"type":"Point"}
}