{
  "type": "Feature",
  "properties": {
    "addr:full":"Winnington Northwich Cheshire CW8 4DN",
    "addr:postcode":"cw8 4dn",
    "iso:country":"GB",
    "sg:address":"Winnington",
    "sg:city":"Northwich",
    "sg:classifiers":[
        {
            "category":"Place Of Worship",
            "type":"Public Place"
        }
    ],
    "sg:phone":"+44 1606 74632",
    "sg:postcode":"CW8 4DN",
    "sg:province":"Cheshire",
    "wof:name":"St Luke C Of E Church",
    "wof:placetype":"venue"
},
  "geometry": {"coordinates":[-2.53096,53.26432],"type":"Point"}
}