{
  "type": "Feature",
  "properties": {
    "addr:full":"Grange Farm Road, Grangetown Middlesbrough North Yorkshire TS6 7HP",
    "addr:postcode":"ts6 7hp",
    "addr:street":"Farm Road",
    "iso:country":"GB",
    "sg:address":"Grange Farm Road, Grangetown",
    "sg:city":"Middlesbrough",
    "sg:classifiers":[
        {
            "category":"Organizations",
            "subcategory":"Membership Organization",
            "type":"Services"
        }
    ],
    "sg:phone":"+44 1642 466686",
    "sg:postcode":"TS6 7HP",
    "sg:province":"North Yorkshire",
    "sg:tags":[
        "club"
    ],
    "wof:name":"St.Mary's Social Club",
    "wof:placetype":"venue"
},
  "geometry": {"coordinates":[-1.1445590258,54.5743484497],"type":"Point"}
}