{
  "type": "Feature",
  "properties": {
    "addr:full":"14 Waun Gron Rd, Treboeth Swansea Swansea SA5 7DG",
    "addr:housenumber":"14",
    "addr:postcode":"sa5 7dg",
    "addr:street":"Waun Gron Rd Treboeth",
    "iso:country":"GB",
    "sg:address":"14 Waun Gron Rd, Treboeth",
    "sg:city":"Swansea",
    "sg:classifiers":[
        {
            "category":"Retail",
            "subcategory":"Driving School",
            "type":"Services"
        }
    ],
    "sg:phone":"+44 1792 583626",
    "sg:postcode":"SA5 7DG",
    "sg:province":"Swansea",
    "wof:name":"Aztec School of Motoring",
    "wof:placetype":"venue"
},
  "geometry": {"coordinates":[-3.950599,51.65295],"type":"Point"}
}