{
  "type": "Feature",
  "properties": {
    "iso:country":"GB",
    "sg:address":"117 South Road",
    "sg:city":"Haywards Heath",
    "sg:classifiers":[
        {
            "category":"Shopping",
            "subcategory":"Thrift Store",
            "type":"Retail Goods"
        },
        {
            "category":"Organizations",
            "subcategory":"Non-profit Organization",
            "type":"Services"
        }
    ],
    "sg:phone":"+44 1444 458776",
    "sg:postcode":"RH16 4LR",
    "sg:province":"East Sussex",
    "sg:tags":[
        "shop",
        "charitable",
        "organisation",
        "charity"
    ],
    "wof:name":"Imperial Cancer Research Fund",
    "wof:placetype":"venue"
},
  "geometry": {"coordinates":[-0.104517,50.997993],"type":"Point"}
}