{
  "type": "Feature",
  "properties": {
    "iso:country":"GB",
    "sg:address":"16 Romsey Crescent",
    "sg:city":"Benfleet",
    "sg:classifiers":[
        {
            "category":"Building & Trades",
            "subcategory":"Construction",
            "type":"Services"
        }
    ],
    "sg:postcode":"SS7 5TR",
    "sg:province":"Essex",
    "sg:tags":[
        "builder"
    ],
    "wof:name":"R R Foster Building Contractor",
    "wof:placetype":"venue"
},
  "geometry": {"coordinates":[0.545245,51.565765],"type":"Point"}
}