{
  "type": "Feature",
  "properties": {
    "iso:country":"GB",
    "sg:address":"Highgate Road, Woodside",
    "sg:city":"Dudley",
    "sg:classifiers":[
        {
            "category":"Education",
            "subcategory":"School",
            "type":"Public Place"
        },
        {
            "category":"Government",
            "subcategory":"Office",
            "type":"Public Place"
        }
    ],
    "sg:phone":"+44 1384 818245",
    "sg:postcode":"DY2 0SN",
    "sg:province":"West Midlands",
    "sg:tags":[
        "local",
        "authority"
    ],
    "wof:name":"Highgate Primary School",
    "wof:placetype":"venue"
},
  "geometry": {"coordinates":[-2.108795,52.498058],"type":"Point"}
}