{
  "type": "Feature",
  "properties": {
    "addr:full":"Plas Waen, Llansorda Oswestry Shropshire SY10 7HJ",
    "addr:postcode":"sy10 7hj",
    "iso:country":"GB",
    "sg:address":"Plas Waen, Llansorda",
    "sg:city":"Oswestry",
    "sg:classifiers":[
        {
            "category":"Organizations",
            "subcategory":"Community Association",
            "type":"Services"
        }
    ],
    "sg:phone":"+44 1691 670803",
    "sg:postcode":"SY10 7HJ",
    "sg:province":"Shropshire",
    "sg:tags":[
        "society",
        "housing"
    ],
    "wof:name":"Telford Housing Co. Ltd.",
    "wof:placetype":"venue"
},
  "geometry": {"coordinates":[-3.06855,52.915852],"type":"Point"}
}