{
  "type": "Feature",
  "properties": {
    "addr:full":"Midland Road Peterborough Cambridgeshire PE3 6DD",
    "addr:postcode":"pe3 6dd",
    "addr:street":"Midland Road",
    "iso:country":"GB",
    "sg:address":"Midland Road",
    "sg:city":"Peterborough",
    "sg:classifiers":[
        {
            "category":"Retail",
            "subcategory":"Auto Rental",
            "type":"Services"
        }
    ],
    "sg:phone":"+44 1733 349489",
    "sg:postcode":"PE3 6DD",
    "sg:province":"Cambridgeshire",
    "sg:tags":[
        "car",
        "vehicle"
    ],
    "sg:website":"http://www.avis.co.uk",
    "wof:name":"Avis Rent A Car Ltd",
    "wof:placetype":"venue"
},
  "geometry": {"coordinates":[-0.2553890049,52.5781211853],"type":"Point"}
}