{
  "type": "Feature",
  "properties": {
    "addr:full":"Auchencheyne, Moniaive Thornhill Dumfries and Galloway DG3 4EW",
    "addr:postcode":"dg3 4ew",
    "iso:country":"GB",
    "sg:address":"Auchencheyne, Moniaive",
    "sg:city":"Thornhill",
    "sg:classifiers":[
        {
            "category":"Farming",
            "subcategory":"Livestock Farm",
            "type":"Manufacturing & Wholesale Goods"
        }
    ],
    "sg:phone":"+44 1848 200285",
    "sg:postcode":"DG3 4EW",
    "sg:province":"Dumfries and Galloway",
    "sg:tags":[
        "others"
    ],
    "wof:name":"Auchencheyne Ltd.",
    "wof:placetype":"venue"
},
  "geometry": {"coordinates":[-3.91927,55.197594],"type":"Point"}
}