{
  "type": "Feature",
  "properties": {
    "addr:full":"106 Purbrook Gardens, Purbrook Waterlooville Hampshire PO7 5LE",
    "addr:housenumber":"106",
    "addr:postcode":"po7 5le",
    "addr:street":"Purbrook Gardens",
    "iso:country":"GB",
    "sg:address":"106 Purbrook Gardens, Purbrook",
    "sg:city":"Waterlooville",
    "sg:classifiers":[
        {
            "category":"Building & Trades",
            "subcategory":"Construction",
            "type":"Services"
        }
    ],
    "sg:phone":"+44 23 9226 7841",
    "sg:postcode":"PO7 5LE",
    "sg:province":"Hampshire",
    "sg:tags":[
        "builder"
    ],
    "wof:name":"Barnes Building Contractors",
    "wof:placetype":"venue"
},
  "geometry": {"coordinates":[-1.045544,50.870174],"type":"Point"}
}