{
  "type": "Feature",
  "properties": {
    "iso:country":"GB",
    "sg:address":"2nd Floor Linden House 21 Dormer Place, 21 Dormer Place",
    "sg:city":"Leamington Spa",
    "sg:classifiers":[
        {
            "category":"Shopping",
            "subcategory":"Hobbies, Toys, & Games",
            "type":"Retail Goods"
        }
    ],
    "sg:phone":"+44 1926 883300",
    "sg:postcode":"CV32 5AA",
    "sg:province":"Warwickshire",
    "sg:tags":[
        "toy"
    ],
    "wof:name":"Dragon Toys",
    "wof:placetype":"venue"
},
  "geometry": {"coordinates":[-1.535324,52.289139],"type":"Point"}
}