{
  "type": "Feature",
  "properties": {
    "addr:full":"200 Ifield Drive Crawley West Sussex RH11 0DQ",
    "addr:housenumber":"200",
    "addr:postcode":"rh11 0dq",
    "addr:street":"Ifield Drive",
    "iso:country":"GB",
    "sg:address":"200 Ifield Drive",
    "sg:city":"Crawley",
    "sg:classifiers":[
        {
            "category":"Retail",
            "subcategory":"Repair Shop",
            "type":"Services"
        }
    ],
    "sg:postcode":"RH11 0DQ",
    "sg:province":"West Sussex",
    "sg:tags":[
        "radio",
        "television",
        "video"
    ],
    "wof:name":"Adams & Cliff Ltd",
    "wof:placetype":"venue"
},
  "geometry": {"coordinates":[-0.213034,51.121948],"type":"Point"}
}