{
  "type": "Feature",
  "properties": {
    "iso:country":"GB",
    "sg:address":"Unit 7 Old Mill Road, Portishead",
    "sg:city":"Bristol",
    "sg:classifiers":[
        {
            "category":"Shopping",
            "subcategory":"Stationery & Office Supplies",
            "type":"Retail Goods"
        }
    ],
    "sg:phone":"+44 1275 849771",
    "sg:postcode":"BS20 7BX",
    "sg:province":"Somerset",
    "sg:tags":[
        "printers'"
    ],
    "wof:name":"Church Finance Supplies Ltd.",
    "wof:placetype":"venue"
},
  "geometry": {"coordinates":[-2.7646579742,51.4846878052],"type":"Point"}
}