{
  "type": "Feature",
  "properties": {
    "addr:full":"Landgate Yard, Well Lane Cheltenham Gloucestershire GL54 1DG",
    "addr:postcode":"gl54 1dg",
    "addr:street":"Landgate;Well Lane",
    "iso:country":"GB",
    "sg:address":"Landgate Yard, Well Lane",
    "sg:city":"Cheltenham",
    "sg:classifiers":[
        {
            "category":"Professional",
            "subcategory":"Printing & Photocopies",
            "type":"Services"
        }
    ],
    "sg:phone":"+44 1993 201370",
    "sg:postcode":"GL54 1DG",
    "sg:province":"Gloucestershire",
    "sg:tags":[
        "printer"
    ],
    "wof:name":"Landgate Finishers",
    "wof:placetype":"venue"
},
  "geometry": {"coordinates":[-1.720129,51.930962],"type":"Point"}
}