{
  "type": "Feature",
  "properties": {
    "addr:full":"16 St Marys Row, Moseley Birmingham West Midlands B13 8JG",
    "addr:housenumber":"16",
    "addr:postcode":"b13 8jg",
    "addr:street":"St Marys Row",
    "iso:country":"GB",
    "sg:address":"16 St Marys Row, Moseley",
    "sg:city":"Birmingham",
    "sg:classifiers":[
        {
            "category":"Shopping",
            "subcategory":"Florist",
            "type":"Retail Goods"
        }
    ],
    "sg:phone":"+44 121 449 1084",
    "sg:postcode":"B13 8JG",
    "sg:province":"West Midlands",
    "wof:name":"Diane Lawson Artistic Florists",
    "wof:placetype":"venue"
},
  "geometry": {"coordinates":[-1.8875850439,52.4462814331],"type":"Point"}
}