{
  "type": "Feature",
  "properties": {
    "addr:full":"109 Oxford Rd, Cowley Oxford Oxfordshire OX4 2ER",
    "addr:housenumber":"109",
    "addr:postcode":"ox4 2er",
    "addr:street":"Oxford Rd",
    "iso:country":"GB",
    "sg:address":"109 Oxford Rd, Cowley",
    "sg:city":"Oxford",
    "sg:classifiers":[
        {
            "category":"Communications",
            "subcategory":"Newspaper",
            "type":"Services"
        }
    ],
    "sg:postcode":"OX4 2ER",
    "sg:province":"Oxfordshire",
    "sg:tags":[
        "magazine"
    ],
    "wof:name":"Dickerson,John,",
    "wof:placetype":"venue"
},
  "geometry": {"coordinates":[-1.2159290314,51.7355003357],"type":"Point"}
}