{
  "type": "Feature",
  "properties": {
    "addr:full":"Bush Corner, London Road Isleworth Greater London TW7 5BB",
    "addr:postcode":"tw7 5bb",
    "addr:street":"Corner London Road",
    "iso:country":"GB",
    "sg:address":"Bush Corner, London Road",
    "sg:city":"Isleworth",
    "sg:classifiers":[
        {
            "category":"Education",
            "subcategory":"School",
            "type":"Public Place"
        }
    ],
    "sg:phone":"+44 20 8321 8080",
    "sg:postcode":"TW7 5BB",
    "sg:province":"Greater London",
    "sg:tags":[
        "local",
        "authority"
    ],
    "wof:name":"Green School",
    "wof:placetype":"venue"
},
  "geometry": {"coordinates":[-0.338233,51.473915],"type":"Point"}
}