{
  "type": "Feature",
  "properties": {
    "addr:full":"Caverswall Road Stoke-on-trent Staffordshire ST3 6PJ",
    "addr:postcode":"st3 6pj",
    "addr:street":"Caverswall Road",
    "iso:country":"GB",
    "sg:address":"Caverswall Road",
    "sg:city":"Stoke-on-trent",
    "sg:classifiers":[
        {
            "category":"Arena",
            "subcategory":"Sports Club",
            "type":"Entertainment"
        }
    ],
    "sg:phone":"+44 1782 319061",
    "sg:postcode":"ST3 6PJ",
    "sg:province":"Staffordshire",
    "wof:name":"Caverswall Cricket Club",
    "wof:placetype":"venue"
},
  "geometry": {"coordinates":[-2.097243,52.992077],"type":"Point"}
}