{
  "type": "Feature",
  "properties": {
    "iso:country":"GB",
    "sg:address":"28 Old Dean Rd",
    "sg:city":"Mitcheldean",
    "sg:classifiers":[
        {
            "category":"Utilities",
            "subcategory":"Fuel Oil & Lpg",
            "type":"Services"
        }
    ],
    "sg:phone":"+44 1594 542668",
    "sg:postcode":"GL17 0BH",
    "sg:province":"Gloucestershire",
    "sg:tags":[
        "coal",
        "smokeless"
    ],
    "wof:name":"R A Matthews Fuels Ltd",
    "wof:placetype":"venue"
},
  "geometry": {"coordinates":[-2.4904150963,51.8696289062],"type":"Point"}
}