{
  "type": "Feature",
  "properties": {
    "addr:full":"18 Brougham Street Edinburgh City of Edinburgh EH3 9JH",
    "addr:housenumber":"18",
    "addr:postcode":"eh3 9jh",
    "addr:street":"Brougham Street",
    "iso:country":"GB",
    "sg:address":"18 Brougham Street",
    "sg:city":"Edinburgh",
    "sg:classifiers":[
        {
            "category":"Food & Beverages",
            "subcategory":"Fruits & Vegetables",
            "type":"Retail Goods"
        },
        {
            "category":"Food & Beverages",
            "subcategory":"Groceries & Convenience Stores",
            "type":"Retail Goods"
        }
    ],
    "sg:phone":"+44 131 622 7016",
    "sg:postcode":"EH3 9JH",
    "sg:province":"City of Edinburgh",
    "sg:tags":[
        "grocer",
        "greengrocer"
    ],
    "wof:name":"Nina's Minimarket",
    "wof:placetype":"venue"
},
  "geometry": {"coordinates":[-3.2022869587,55.943447113],"type":"Point"}
}