{
  "type": "Feature",
  "properties": {
    "addr:full":"Westfield, Waterworks La Dover Kent CT15 5JW",
    "addr:postcode":"ct15 5jw",
    "iso:country":"GB",
    "sg:address":"Westfield, Waterworks La",
    "sg:city":"Dover",
    "sg:classifiers":[
        {
            "category":"Building & Trades",
            "subcategory":"Plumbing",
            "type":"Services"
        }
    ],
    "sg:phone":"+44 1304 852148",
    "sg:postcode":"CT15 5JW",
    "sg:province":"Kent",
    "sg:tags":[
        "heating"
    ],
    "wof:name":"Ray Orpin Plumbing & Heating",
    "wof:placetype":"venue"
},
  "geometry": {"coordinates":[1.3429100513,51.1760902405],"type":"Point"}
}