{
  "type": "Feature",
  "properties": {
    "addr:full":"3 Gorton St, Farnworth Bolton Lancashire BL4 9RL",
    "addr:housenumber":"3",
    "addr:postcode":"bl4 9rl",
    "addr:street":"Gorton St",
    "iso:country":"GB",
    "sg:address":"3 Gorton St, Farnworth",
    "sg:city":"Bolton",
    "sg:classifiers":[
        {
            "category":"Professional",
            "subcategory":"Business Services",
            "type":"Services"
        }
    ],
    "sg:phone":"+44 1204 576826",
    "sg:postcode":"BL4 9RL",
    "sg:province":"Lancashire",
    "sg:tags":[
        "distributor",
        "film"
    ],
    "wof:name":"Roadrunner Video",
    "wof:placetype":"venue"
},
  "geometry": {"coordinates":[-2.4133620262,53.5439567566],"type":"Point"}
}