{
  "type": "Feature",
  "properties": {
    "iso:country":"GB",
    "sg:address":"351 Ugg Mere Court Road, Ramsey Heights, Ramsey",
    "sg:city":"Huntingdon",
    "sg:classifiers":[
        {
            "category":"Recreation",
            "subcategory":"Dog Park",
            "type":"Entertainment"
        }
    ],
    "sg:phone":"+44 1487 812939",
    "sg:postcode":"PE26 2RL",
    "sg:province":"Cambridgeshire",
    "wof:name":"Acresway German Shepherds",
    "wof:placetype":"venue"
},
  "geometry": {"coordinates":[-0.154367,52.467506],"type":"Point"}
}