{
  "type": "Feature",
  "properties": {
    "addr:full":"Elms Court Oxford Oxfordshire OX2 9LP",
    "addr:postcode":"ox2 9lp",
    "addr:street":"Elms Court",
    "iso:country":"GB",
    "sg:address":"Elms Court",
    "sg:city":"Oxford",
    "sg:classifiers":[
        {
            "category":"Professional",
            "subcategory":"Computer Services",
            "type":"Services"
        }
    ],
    "sg:postcode":"OX2 9LP",
    "sg:province":"Oxfordshire",
    "sg:tags":[
        "system",
        "software"
    ],
    "wof:name":"Liric Associates Ltd.",
    "wof:placetype":"venue"
},
  "geometry": {"coordinates":[-1.2971899509,51.7514266968],"type":"Point"}
}