{
  "type": "Feature",
  "properties": {
    "addr:full":"Bellmount Wood Avenue Watford Hertfordshire WD17 3BN",
    "addr:postcode":"wd17 3bn",
    "addr:street":"Bellmount Wood Avenue",
    "iso:country":"GB",
    "sg:address":"Bellmount Wood Avenue",
    "sg:city":"Watford",
    "sg:classifiers":[
        {
            "category":"Education",
            "subcategory":"School",
            "type":"Public Place"
        }
    ],
    "sg:phone":"+44 1923 222782",
    "sg:postcode":"WD17 3BN",
    "sg:province":"Hertfordshire",
    "sg:tags":[
        "local",
        "authority"
    ],
    "wof:name":"Cassiobury Infants School",
    "wof:placetype":"venue"
},
  "geometry": {"coordinates":[-0.421696,51.667717],"type":"Point"}
}