{
  "type": "Feature",
  "properties": {
    "addr:full":"4 North Street Tavistock Devon PL19 0AN",
    "addr:housenumber":"4",
    "addr:postcode":"pl19 0an",
    "addr:street":"North Street",
    "iso:country":"GB",
    "sg:address":"4 North Street",
    "sg:city":"Tavistock",
    "sg:classifiers":[
        {
            "category":"Manufacturing",
            "subcategory":"Tools & Machinery",
            "type":"Manufacturing & Wholesale Goods"
        }
    ],
    "sg:phone":"+44 1822 617173",
    "sg:postcode":"PL19 0AN",
    "sg:province":"Devon",
    "sg:tags":[
        "society",
        "friendly"
    ],
    "wof:name":"Folley & Co",
    "wof:placetype":"venue"
},
  "geometry": {"coordinates":[-4.1456198692,50.5501327515],"type":"Point"}
}