{
  "type": "Feature",
  "properties": {
    "addr:full":"Care Of Chancellors, 23 The Quadrant Richmond Greater London TW9 1BP",
    "addr:housenumber":"23",
    "addr:postcode":"tw9 1bp",
    "addr:street":"The Quadrant",
    "iso:country":"GB",
    "sg:address":"Care Of Chancellors, 23 The Quadrant",
    "sg:city":"Richmond",
    "sg:classifiers":[
        {
            "category":"Banks & Credit Unions",
            "subcategory":"Financial Services",
            "type":"Services"
        }
    ],
    "sg:phone":"+44 20 8940 9925",
    "sg:postcode":"TW9 1BP",
    "sg:province":"Greater London",
    "sg:tags":[
        "adviser"
    ],
    "wof:name":"The Radnor Group",
    "wof:placetype":"venue"
},
  "geometry": {"coordinates":[-0.302784,51.462349],"type":"Point"}
}