{
  "type": "Feature",
  "properties": {
    "iso:country":"GB",
    "sg:address":"Unit 23 Irlam Industrial Estate, 656 Liverpool Road, Irlam",
    "sg:city":"Manchester",
    "sg:classifiers":[
        {
            "category":"Wholesale",
            "subcategory":"Fruits & Vegetables",
            "type":"Manufacturing & Wholesale Goods"
        }
    ],
    "sg:phone":"+44 161 775 7173",
    "sg:postcode":"M44 5AZ",
    "sg:province":"Greater Manchester",
    "wof:name":"Kwikfruits (Northern) Ltd.",
    "wof:placetype":"venue"
},
  "geometry": {"coordinates":[-2.43274,53.432751],"type":"Point"}
}