{
  "type": "Feature",
  "properties": {
    "addr:full":"56 Windsor Way Polegate East Sussex BN26 6QF",
    "addr:housenumber":"56",
    "addr:postcode":"bn26 6qf",
    "addr:street":"Windsor Way",
    "iso:country":"GB",
    "sg:address":"56 Windsor Way",
    "sg:city":"Polegate",
    "sg:classifiers":[
        {
            "category":"Manufacturing",
            "subcategory":"Buildings",
            "type":"Manufacturing & Wholesale Goods"
        }
    ],
    "sg:phone":"+44 1323 488055",
    "sg:postcode":"BN26 6QF",
    "sg:province":"East Sussex",
    "sg:tags":[
        "system",
        "air conditioning"
    ],
    "wof:name":"V A C (Viscount) Ltd.",
    "wof:placetype":"venue"
},
  "geometry": {"coordinates":[0.2458689958,50.824432373],"type":"Point"}
}