{
  "type": "Feature",
  "properties": {
    "addr:full":"113 Lower Manor Lane Burnley Lancashire BB12 0EF",
    "addr:housenumber":"113",
    "addr:postcode":"bb12 0ef",
    "addr:street":"Lower Manor Lane",
    "iso:country":"GB",
    "sg:address":"113 Lower Manor Lane",
    "sg:city":"Burnley",
    "sg:classifiers":[
        {
            "category":"Building & Trades",
            "subcategory":"Construction",
            "type":"Services"
        }
    ],
    "sg:phone":"+44 7973 855193",
    "sg:postcode":"BB12 0EF",
    "sg:province":"Lancashire",
    "sg:tags":[
        "builder"
    ],
    "wof:name":"Duncan J Beharrell",
    "wof:placetype":"venue"
},
  "geometry": {"coordinates":[-2.248233,53.807545],"type":"Point"}
}