{
  "type": "Feature",
  "properties": {
    "addr:full":"126 Queensway Billingham Durham TS23 2NT",
    "addr:housenumber":"126",
    "addr:postcode":"ts23 2nt",
    "addr:street":"Queensway Billingham",
    "iso:country":"GB",
    "sg:address":"126 Queensway",
    "sg:city":"Billingham",
    "sg:classifiers":[
        {
            "category":"Health Services",
            "subcategory":"Optometrist",
            "type":"Services"
        }
    ],
    "sg:phone":"+44 1642 552161",
    "sg:postcode":"TS23 2NT",
    "sg:province":"Durham",
    "sg:tags":[
        "optician"
    ],
    "wof:name":"McCormick & Gorman Opticians",
    "wof:placetype":"venue"
},
  "geometry": {"coordinates":[-1.293864,54.608028],"type":"Point"}
}