{
  "type": "Feature",
  "properties": {
    "iso:country":"GB",
    "sg:address":"Riverfield Farm, Marden",
    "sg:city":"Tonbridge",
    "sg:classifiers":[
        {
            "category":"Farming",
            "subcategory":"Farm",
            "type":"Manufacturing & Wholesale Goods"
        }
    ],
    "sg:phone":"+44 1580 891474",
    "sg:postcode":"TN12 9BU",
    "sg:province":"Kent",
    "sg:tags":[
        "hatchery"
    ],
    "wof:name":"Riverfield Carp",
    "wof:placetype":"venue"
},
  "geometry": {"coordinates":[0.489726007,51.176322937],"type":"Point"}
}