{
  "type": "Feature",
  "properties": {
    "iso:country":"GB",
    "sg:address":"10 Kenwood Park Road",
    "sg:city":"Sheffield",
    "sg:classifiers":[
        {
            "category":"Social Services",
            "subcategory":"Retirement Home",
            "type":"Services"
        }
    ],
    "sg:postcode":"S7 1NF",
    "sg:province":"South Yorkshire",
    "sg:tags":[
        "residential",
        "care"
    ],
    "wof:name":"Rothbury",
    "wof:placetype":"venue"
},
  "geometry": {"coordinates":[-1.483982,53.36459],"type":"Point"}
}