{
  "type": "Feature",
  "properties": {
    "iso:country":"GB",
    "sg:address":"30 The Piazza, Covent Garden",
    "sg:city":"Holborn",
    "sg:classifiers":[
        {
            "category":"Health Services",
            "subcategory":"Doctor",
            "type":"Services"
        }
    ],
    "sg:phone":"+44 20 7836 4835",
    "sg:postcode":"WC2E 8BE",
    "sg:province":"Greater London",
    "sg:tags":[
        "nutritionist",
        "dietician"
    ],
    "wof:name":"Maria Davies",
    "wof:placetype":"venue"
},
  "geometry": {"coordinates":[-0.1229399964,51.512008667],"type":"Point"}
}