{
  "type": "Feature",
  "properties": {
    "iso:country":"GB",
    "sg:address":"Lower Wickham Lodge, Winchester Road, Wickham",
    "sg:city":"Fareham",
    "sg:classifiers":[
        {
            "category":"Building & Trades",
            "subcategory":"Landscaping Services",
            "type":"Services"
        }
    ],
    "sg:postcode":"PO17 5EX",
    "sg:province":"Hampshire",
    "sg:tags":[
        "landscape",
        "contractor"
    ],
    "wof:name":"Miles Towlson",
    "wof:placetype":"venue"
},
  "geometry": {"coordinates":[-1.1891089678,50.8998184204],"type":"Point"}
}