{
  "type": "Feature",
  "properties": {
    "addr:full":"500 Slade Road Birmingham West Midlands B23 7JH",
    "addr:housenumber":"500",
    "addr:postcode":"b23 7jh",
    "addr:street":"Slade Road",
    "iso:country":"GB",
    "sg:address":"500 Slade Road",
    "sg:city":"Birmingham",
    "sg:classifiers":[
        {
            "category":"Home & Garden",
            "subcategory":"Hardware",
            "type":"Retail Goods"
        }
    ],
    "sg:postcode":"B23 7JH",
    "sg:province":"West Midlands",
    "sg:tags":[
        "retailer",
        "diy"
    ],
    "wof:name":"Rapid Home Care",
    "wof:placetype":"venue"
},
  "geometry": {"coordinates":[-1.8594130278,52.5235290527],"type":"Point"}
}