{
  "type": "Feature",
  "properties": {
    "iso:country":"GB",
    "sg:address":"Lukes Lane, St Hilary",
    "sg:city":"Penzance",
    "sg:classifiers":[
        {
            "category":"Professional",
            "subcategory":"Art Services",
            "type":"Services"
        }
    ],
    "sg:postcode":"TR20 9DY",
    "sg:province":"Cornwall",
    "sg:tags":[
        "framing"
    ],
    "wof:name":"P & T Framing",
    "wof:placetype":"venue"
},
  "geometry": {"coordinates":[-5.418461,50.131142],"type":"Point"}
}