{
  "type": "Feature",
  "properties": {
    "iso:country":"GB",
    "sg:address":"184 Horninglow Street",
    "sg:city":"Burton-on-trent",
    "sg:classifiers":[
        {
            "category":"Real Estate",
            "subcategory":"Surveying",
            "type":"Services"
        }
    ],
    "sg:phone":"+44 1283 500030",
    "sg:postcode":"DE14 1NG",
    "sg:province":"Derbyshire",
    "sg:tags":[
        "surveyor",
        "valuer"
    ],
    "wof:name":"Salloway & Associates",
    "wof:placetype":"venue"
},
  "geometry": {"coordinates":[-1.627603,52.80719],"type":"Point"}
}