{
  "type": "Feature",
  "properties": {
    "iso:country":"GB",
    "sg:address":"48 Bank Street",
    "sg:city":"Galashiels",
    "sg:classifiers":[
        {
            "category":"Banks & Credit Unions",
            "subcategory":"Financial Services",
            "type":"Services"
        }
    ],
    "sg:phone":"+44 1896 753682",
    "sg:postcode":"TD1 1EP",
    "sg:province":"Scottish Borders",
    "sg:tags":[
        "building",
        "society"
    ],
    "wof:name":"Scottish Building Society",
    "wof:placetype":"venue"
},
  "geometry": {"coordinates":[-2.807399,55.615379],"type":"Point"}
}