{
  "type": "Feature",
  "properties": {
    "addr:full":"Bryn Aethwy Y Felinheli Gwynedd LL56 4JZ",
    "addr:postcode":"ll56 4jz",
    "iso:country":"GB",
    "sg:address":"Bryn Aethwy",
    "sg:city":"Y Felinheli",
    "sg:classifiers":[
        {
            "category":"Sports & Exercise",
            "subcategory":"Bowling",
            "type":"Entertainment"
        }
    ],
    "sg:phone":"+44 1248 671116",
    "sg:postcode":"LL56 4JZ",
    "sg:province":"Gwynedd",
    "sg:tags":[
        "photography"
    ],
    "wof:name":"Photo Assignments",
    "wof:placetype":"venue"
},
  "geometry": {"coordinates":[-4.2096090317,53.1836547852],"type":"Point"}
}