{
  "type": "Feature",
  "properties": {
    "addr:full":"51 The Crescent Salford Greater Manchester M5 5WX",
    "addr:housenumber":"51",
    "addr:postcode":"m5 5wx",
    "addr:street":"The Crescent",
    "iso:country":"GB",
    "sg:address":"51 The Crescent",
    "sg:city":"Salford",
    "sg:classifiers":[
        {
            "category":"Education",
            "subcategory":"Library",
            "type":"Public Place"
        }
    ],
    "sg:phone":"+44 161 736 3601",
    "sg:postcode":"M5 5WX",
    "sg:province":"Greater Manchester",
    "sg:tags":[
        "book"
    ],
    "wof:name":"Working Class Movement Library",
    "wof:placetype":"venue"
},
  "geometry": {"coordinates":[-2.302999,53.48666],"type":"Point"}
}