{
  "type": "Feature",
  "properties": {
    "addr:full":"235 Lower House Lane Liverpool Merseyside L11 2SF",
    "addr:housenumber":"235",
    "addr:postcode":"l11 2sf",
    "addr:street":"Lower House Lane",
    "iso:country":"GB",
    "sg:address":"235 Lower House Lane",
    "sg:city":"Liverpool",
    "sg:classifiers":[
        {
            "category":"Fast Food",
            "type":"Food & Drink"
        }
    ],
    "sg:phone":"+44 151 546 0711",
    "sg:postcode":"L11 2SF",
    "sg:province":"Merseyside",
    "sg:tags":[
        "away",
        "meal",
        "outlet",
        "take"
    ],
    "wof:name":"Oriental Chinese & English Takeaway",
    "wof:placetype":"venue"
},
  "geometry": {"coordinates":[-2.912581,53.449142],"type":"Point"}
}