{
  "type": "Feature",
  "properties": {
    "addr:full":"96-98 St Leonards Road Lowestoft Suffolk NR33 0EL",
    "addr:housenumber":"96-98",
    "addr:postcode":"nr33 0el",
    "addr:street":"St Leonards Road",
    "iso:country":"GB",
    "sg:address":"96-98 St Leonards Road",
    "sg:city":"Lowestoft",
    "sg:classifiers":[
        {
            "category":"Personal",
            "subcategory":"Beauty Salon",
            "type":"Services"
        },
        {
            "category":"Personal",
            "subcategory":"Barber",
            "type":"Services"
        }
    ],
    "sg:phone":"+44 1502 587927",
    "sg:postcode":"NR33 0EL",
    "sg:province":"Suffolk",
    "sg:tags":[
        "unisex",
        "hairdresser"
    ],
    "wof:name":"Mirror Image Hair Studio",
    "wof:placetype":"venue"
},
  "geometry": {"coordinates":[1.740204,52.465031],"type":"Point"}
}