{
  "type": "Feature",
  "properties": {
    "addr:full":"Unit 2 Douglas Court, West Hendersons Wynd Dundee Dundee City DD1 5BY",
    "addr:housenumber":"unit 2",
    "addr:postcode":"dd1 5by",
    "addr:street":"Douglas Court West Hendersons Wynd",
    "iso:country":"GB",
    "sg:address":"Unit 2 Douglas Court, West Hendersons Wynd",
    "sg:city":"Dundee",
    "sg:classifiers":[
        {
            "category":"Professional",
            "subcategory":"Employment Agencies",
            "type":"Services"
        }
    ],
    "sg:phone":"+44 1382 877866",
    "sg:postcode":"DD1 5BY",
    "sg:province":"Dundee City",
    "sg:tags":[
        "consultant"
    ],
    "wof:name":"Pitstop Motorcycles",
    "wof:placetype":"venue"
},
  "geometry": {"coordinates":[-2.981594,56.4631],"type":"Point"}
}