{
  "type": "Feature",
  "properties": {
    "addr:full":"18 Bridgeway East, Pentre Maelor Wrexham Wrexham LL13 9RB",
    "addr:housenumber":"18",
    "addr:postcode":"ll13 9rb",
    "addr:street":"Bridgeway East Pentre Maelor",
    "iso:country":"GB",
    "sg:address":"18 Bridgeway East, Pentre Maelor",
    "sg:city":"Wrexham",
    "sg:classifiers":[
        {
            "category":"Government",
            "subcategory":"Post Office",
            "type":"Public Place"
        }
    ],
    "sg:phone":"+44 1978 660177",
    "sg:postcode":"LL13 9RB",
    "sg:province":"Wrexham",
    "wof:name":"Pentre Maelor Post Office Stores",
    "wof:placetype":"venue"
},
  "geometry": {"coordinates":[-2.915790081,53.0391082764],"type":"Point"}
}