{
  "type": "Feature",
  "properties": {
    "iso:country":"GB",
    "sg:address":"Unit D, Sheepscar House, Sheepscar St South",
    "sg:city":"Leeds",
    "sg:classifiers":[
        {
            "category":"Home & Garden",
            "subcategory":"Building Materials",
            "type":"Retail Goods"
        }
    ],
    "sg:phone":"+44 113 242 5005",
    "sg:postcode":"LS7 1AD",
    "sg:province":"West Yorkshire",
    "sg:tags":[
        "window",
        "frame"
    ],
    "wof:name":"Paul Bennett",
    "wof:placetype":"venue"
},
  "geometry": {"coordinates":[-1.534638,53.807739],"type":"Point"}
}