{
  "type": "Feature",
  "properties": {
    "addr:full":"2 Market Street Craven Arms Herefordshire SY7 9NN",
    "addr:housenumber":"2",
    "addr:postcode":"sy7 9nn",
    "addr:street":"Market Street",
    "iso:country":"GB",
    "sg:address":"2 Market Street",
    "sg:city":"Craven Arms",
    "sg:classifiers":[
        {
            "category":"Professional",
            "subcategory":"Computer Services",
            "type":"Services"
        }
    ],
    "sg:postcode":"SY7 9NN",
    "sg:province":"Herefordshire",
    "sg:tags":[
        "system",
        "software"
    ],
    "wof:name":"Pricelynx Ltd",
    "wof:placetype":"venue"
},
  "geometry": {"coordinates":[-2.833438,52.439041],"type":"Point"}
}