{
  "type": "Feature",
  "properties": {
    "addr:full":"Unit 40-44 Savoy Cntr, 140 Sauchiehall Street Glasgow Glasgow City G2 3DH",
    "addr:housenumber":"unit 40-44;140",
    "addr:postcode":"g2 3dh",
    "addr:street":"Cntr;Sauchiehall Street",
    "iso:country":"GB",
    "sg:address":"Unit 40-44 Savoy Cntr, 140 Sauchiehall Street",
    "sg:city":"Glasgow",
    "sg:classifiers":[
        {
            "category":"Professional",
            "subcategory":"Printing & Photocopies",
            "type":"Services"
        }
    ],
    "sg:phone":"+44 141 331 2095",
    "sg:postcode":"G2 3DH",
    "sg:province":"Glasgow City",
    "sg:tags":[
        "trophy"
    ],
    "wof:name":"The Trophy Centre Ltd.",
    "wof:placetype":"venue"
},
  "geometry": {"coordinates":[-4.26242,55.865349],"type":"Point"}
}