{
  "type": "Feature",
  "properties": {
    "iso:country":"GB",
    "sg:address":"10 Ironside Close, Hales Park",
    "sg:city":"Bewdley",
    "sg:classifiers":[
        {
            "category":"Professional",
            "subcategory":"Engineering",
            "type":"Services"
        },
        {
            "category":"Building & Trades",
            "subcategory":"Electrical",
            "type":"Services"
        }
    ],
    "sg:phone":"+44 1299 402626",
    "sg:postcode":"DY12 2HX",
    "sg:province":"Shropshire",
    "sg:tags":[
        "engineer",
        "electrician",
        "contractor"
    ],
    "wof:name":"M & D Services",
    "wof:placetype":"venue"
},
  "geometry": {"coordinates":[-2.32813,52.373047],"type":"Point"}
}