{
  "type": "Feature",
  "properties": {
    "addr:full":"5 Peterhouse Parade Crawley Surrey RH10 3BA",
    "addr:housenumber":"5",
    "addr:postcode":"rh10 3ba",
    "addr:street":"Peterhouse Parade",
    "iso:country":"GB",
    "sg:address":"5 Peterhouse Parade",
    "sg:city":"Crawley",
    "sg:classifiers":[
        {
            "category":"Shopping",
            "subcategory":"Florist",
            "type":"Retail Goods"
        }
    ],
    "sg:phone":"+44 1293 408358",
    "sg:postcode":"RH10 3BA",
    "sg:province":"Surrey",
    "wof:name":"The Flower Shop",
    "wof:placetype":"venue"
},
  "geometry": {"coordinates":[-0.155024007,51.1272583008],"type":"Point"}
}