{
  "type": "Feature",
  "properties": {
    "iso:country":"GB",
    "sg:address":"Unit 4 Old Mil Parl Edingburgh Rd Earn",
    "sg:city":"Perth",
    "sg:classifiers":[
        {
            "category":"Home & Garden",
            "subcategory":"Home Furnishings",
            "type":"Retail Goods"
        }
    ],
    "sg:phone":"+44 1356 626011",
    "sg:postcode":"PH2 9PS",
    "sg:province":"Perth and Kinross",
    "sg:tags":[
        "awning",
        "canopy",
        "blinds"
    ],
    "wof:name":"Vantana Window Blinds",
    "wof:placetype":"venue"
},
  "geometry": {"coordinates":[-3.405,56.346779],"type":"Point"}
}