{
  "type": "Feature",
  "properties": {
    "iso:country":"GB",
    "sg:address":"50 Church St",
    "sg:city":"Broseley",
    "sg:classifiers":[
        {
            "category":"Food & Beverages",
            "subcategory":"Meat & Fish",
            "type":"Retail Goods"
        }
    ],
    "sg:phone":"+44 1952 884682",
    "sg:postcode":"TF12 5BX",
    "sg:province":"Shropshire",
    "sg:tags":[
        "butcher"
    ],
    "wof:name":"Thomas Nick",
    "wof:placetype":"venue"
},
  "geometry": {"coordinates":[-2.480239,52.611645],"type":"Point"}
}