{
  "type": "Feature",
  "properties": {
    "addr:full":"St Peters Church Hall, St Peters Way, Harlington Hayes Greater London UB3 5AB",
    "addr:postcode":"ub3 5ab",
    "addr:street":"St Peters Way",
    "iso:country":"GB",
    "sg:address":"St Peters Church Hall, St Peters Way, Harlington",
    "sg:city":"Hayes",
    "sg:classifiers":[
        {
            "category":"Recreation",
            "subcategory":"Dog Park",
            "type":"Entertainment"
        }
    ],
    "sg:phone":"+44 20 8890 3358",
    "sg:postcode":"UB3 5AB",
    "sg:province":"Greater London",
    "wof:name":"The Middlesex Dog Handling Group",
    "wof:placetype":"venue"
},
  "geometry": {"coordinates":[-0.43415,51.492901],"type":"Point"}
}