{
  "type": "Feature",
  "properties": {
    "addr:full":"Design House, Storeys Bar Road, Stonegate Peterborough Cambridgeshire PE1 5YS",
    "addr:postcode":"pe1 5ys",
    "addr:street":"Bar Road",
    "iso:country":"GB",
    "sg:address":"Design House, Storeys Bar Road, Stonegate",
    "sg:city":"Peterborough",
    "sg:classifiers":[
        {
            "category":"Education",
            "subcategory":"Music School",
            "type":"Public Place"
        }
    ],
    "sg:phone":"+44 1733 345860",
    "sg:postcode":"PE1 5YS",
    "sg:province":"Cambridgeshire",
    "sg:tags":[
        "conservatory"
    ],
    "wof:name":"Breckenridge Conservatories Ltd.",
    "wof:placetype":"venue"
},
  "geometry": {"coordinates":[-0.195191,52.579044],"type":"Point"}
}