{
  "type": "Feature",
  "properties": {
    "addr:full":"33 Fordell Way Inverkeithing Fife KY11 1PN",
    "addr:housenumber":"33",
    "addr:postcode":"ky11 1pn",
    "addr:street":"Fordell Way",
    "iso:country":"GB",
    "sg:address":"33 Fordell Way",
    "sg:city":"Inverkeithing",
    "sg:classifiers":[
        {
            "category":"Retail",
            "subcategory":"Driving School",
            "type":"Services"
        }
    ],
    "sg:phone":"+44 1383 415239",
    "sg:postcode":"KY11 1PN",
    "sg:province":"Fife",
    "wof:name":"Bill Cook School of Motoring",
    "wof:placetype":"venue"
},
  "geometry": {"coordinates":[-3.385132,56.031898],"type":"Point"}
}