{
  "type": "Feature",
  "properties": {
    "iso:country":"GB",
    "sg:address":"51 Springfield Road",
    "sg:city":"Southwell",
    "sg:classifiers":[
        {
            "category":"Communications",
            "type":"Services"
        },
        {
            "category":"Communications",
            "subcategory":"Television Station",
            "type":"Services"
        }
    ],
    "sg:phone":"+44 1636 815490",
    "sg:postcode":"NG25 0BS",
    "sg:province":"Nottinghamshire",
    "sg:tags":[
        "satellite",
        "tv",
        "related",
        "equipment",
        "video",
        "radio"
    ],
    "wof:name":"GOGGLEBOX",
    "wof:placetype":"venue"
},
  "geometry": {"coordinates":[-0.960464,53.084209],"type":"Point"}
}