{
  "type": "Feature",
  "properties": {
    "addr:full":"3 Alder Grove Yateley Hampshire GU46 6EN",
    "addr:housenumber":"3",
    "addr:postcode":"gu46 6en",
    "addr:street":"Alder Grove",
    "iso:country":"GB",
    "sg:address":"3 Alder Grove",
    "sg:city":"Yateley",
    "sg:classifiers":[
        {
            "category":"Building & Trades",
            "subcategory":"Construction",
            "type":"Services"
        }
    ],
    "sg:phone":"+44 1252 660112",
    "sg:postcode":"GU46 6EN",
    "sg:province":"Hampshire",
    "sg:tags":[
        "builder"
    ],
    "wof:name":"A S Cann",
    "wof:placetype":"venue"
},
  "geometry": {"coordinates":[-0.8350999951,51.3352966309],"type":"Point"}
}