{
  "type": "Feature",
  "properties": {
    "addr:full":"35 Upper Wickham Lane Welling Kent DA16 3AB",
    "addr:housenumber":"35",
    "addr:postcode":"da16 3ab",
    "addr:street":"Upper Wickham Lane",
    "iso:country":"GB",
    "sg:address":"35 Upper Wickham Lane",
    "sg:city":"Welling",
    "sg:classifiers":[
        {
            "category":"Shopping",
            "subcategory":"Crafts & Fabrics",
            "type":"Retail Goods"
        },
        {
            "category":"Shopping",
            "subcategory":"Discount & Variety Stores",
            "type":"Retail Goods"
        }
    ],
    "sg:phone":"+44 20 8301 1777",
    "sg:postcode":"DA16 3AB",
    "sg:province":"Kent",
    "sg:tags":[
        "upholstery",
        "upholsterers'",
        "supply"
    ],
    "wof:name":"Bonners Of Welling Furnishers Ltd",
    "wof:placetype":"venue"
},
  "geometry": {"coordinates":[0.1085039973,51.4636039734],"type":"Point"}
}