{
  "type": "Feature",
  "properties": {
    "addr:full":"Sutton House, 30b Cowbridge Road Pontyclun Bridgend CF72 9EE",
    "addr:housenumber":"30b",
    "addr:postcode":"cf72 9ee",
    "addr:street":"Cowbridge Road",
    "iso:country":"GB",
    "sg:address":"Sutton House, 30b Cowbridge Road",
    "sg:city":"Pontyclun",
    "sg:classifiers":[
        {
            "category":"Shopping",
            "subcategory":"Florist",
            "type":"Retail Goods"
        }
    ],
    "sg:phone":"+44 1443 226090",
    "sg:postcode":"CF72 9EE",
    "sg:province":"Bridgend",
    "wof:name":"Florabundi Designs",
    "wof:placetype":"venue"
},
  "geometry": {"coordinates":[-3.3922660351,51.5223350525],"type":"Point"}
}