{
  "type": "Feature",
  "properties": {
    "iso:country":"GB",
    "sg:address":"Globe Ho, Modder St",
    "sg:city":"Scunthorpe",
    "sg:classifiers":[
        {
            "category":"Education",
            "subcategory":"Special Training",
            "type":"Public Place"
        }
    ],
    "sg:phone":"+44 1724 280414",
    "sg:postcode":"DN16 2SH",
    "sg:province":"Lincolnshire",
    "sg:tags":[
        "product",
        "centre"
    ],
    "wof:name":"J H P Training",
    "wof:placetype":"venue"
},
  "geometry": {"coordinates":[-0.64938,53.567551],"type":"Point"}
}