{
  "type": "Feature",
  "properties": {
    "addr:full":"1 Boscawen Street Truro Cornwall TR1 2QU",
    "addr:housenumber":"1",
    "addr:postcode":"tr1 2qu",
    "addr:street":"Boscawen Street",
    "iso:country":"GB",
    "sg:address":"1 Boscawen Street",
    "sg:city":"Truro",
    "sg:classifiers":[
        {
            "category":"Cafe",
            "type":"Food & Drink"
        }
    ],
    "sg:phone":"+44 1872 263706",
    "sg:postcode":"TR1 2QU",
    "sg:province":"Cornwall",
    "sg:tags":[
        "tea",
        "room"
    ],
    "wof:name":"Charlottes Tea House",
    "wof:placetype":"venue"
},
  "geometry": {"coordinates":[-5.0519318581,50.2631988525],"type":"Point"}
}