{
  "type": "Feature",
  "properties": {
    "addr:full":"93 The Knares Basildon Essex SS16 5SB",
    "addr:housenumber":"93",
    "addr:postcode":"ss16 5sb",
    "addr:street":"The Knares",
    "iso:country":"GB",
    "sg:address":"93 The Knares",
    "sg:city":"Basildon",
    "sg:classifiers":[
        {
            "category":"Health Services",
            "subcategory":"Doctor",
            "type":"Services"
        }
    ],
    "sg:phone":"+44 1268 542866",
    "sg:postcode":"SS16 5SB",
    "sg:province":"Essex",
    "sg:tags":[
        "practitioners"
    ],
    "wof:name":"Cornforth Degun & Ferris Drs",
    "wof:placetype":"venue"
},
  "geometry": {"coordinates":[0.443939,51.564018],"type":"Point"}
}