{
  "type": "Feature",
  "properties": {
    "addr:full":"Gladstone House, Church Road, Wavertree Liverpool Merseyside L15 9EG",
    "addr:postcode":"l15 9eg",
    "addr:street":"Church Road",
    "iso:country":"GB",
    "sg:address":"Gladstone House, Church Road, Wavertree",
    "sg:city":"Liverpool",
    "sg:classifiers":[
        {
            "category":"Banks & Credit Unions",
            "subcategory":"Financial Services",
            "type":"Services"
        }
    ],
    "sg:phone":"+44 151 708 7727",
    "sg:postcode":"L15 9EG",
    "sg:province":"Merseyside",
    "sg:tags":[
        "consultant"
    ],
    "wof:name":"K B Financial Consultants",
    "wof:placetype":"venue"
},
  "geometry": {"coordinates":[-2.914494,53.389416],"type":"Point"}
}