{
  "type": "Feature",
  "properties": {
    "addr:full":"48 Beechwood Gardens Rainham Essex RM13 9HU",
    "addr:housenumber":"48",
    "addr:postcode":"rm13 9hu",
    "addr:street":"Beechwood Gardens",
    "iso:country":"GB",
    "sg:address":"48 Beechwood Gardens",
    "sg:city":"Rainham",
    "sg:classifiers":[
        {
            "category":"Building & Trades",
            "subcategory":"Construction",
            "type":"Services"
        }
    ],
    "sg:phone":"+44 1708 523129",
    "sg:postcode":"RM13 9HU",
    "sg:province":"Essex",
    "sg:tags":[
        "builder"
    ],
    "wof:name":"Ellis Building",
    "wof:placetype":"venue"
},
  "geometry": {"coordinates":[0.2007199973,51.5135955811],"type":"Point"}
}