{
  "type": "Feature",
  "properties": {
    "addr:full":"91 Fenby Avenue Bradford West Yorkshire BD4 8RA",
    "addr:housenumber":"91",
    "addr:postcode":"bd4 8ra",
    "addr:street":"Fenby Avenue",
    "iso:country":"GB",
    "sg:address":"91 Fenby Avenue",
    "sg:city":"Bradford",
    "sg:classifiers":[
        {
            "category":"Bakery",
            "type":"Food & Drink"
        }
    ],
    "sg:postcode":"BD4 8RA",
    "sg:province":"West Yorkshire",
    "sg:tags":[
        "cake",
        "maker"
    ],
    "wof:name":"Icing on the Cake",
    "wof:placetype":"venue"
},
  "geometry": {"coordinates":[-1.7235310078,53.7790184021],"type":"Point"}
}