{
  "type": "Feature",
  "properties": {
    "addr:full":"2 Radcliffe Close, Frimley Camberley Hampshire GU16 9FF",
    "addr:housenumber":"2",
    "addr:postcode":"gu16 9ff",
    "addr:street":"Radcliffe Close",
    "iso:country":"GB",
    "sg:address":"2 Radcliffe Close, Frimley",
    "sg:city":"Camberley",
    "sg:classifiers":[
        {
            "category":"Professional",
            "subcategory":"Computer Services",
            "type":"Services"
        }
    ],
    "sg:phone":"+44 1276 507854",
    "sg:postcode":"GU16 9FF",
    "sg:province":"Hampshire",
    "sg:tags":[
        "system",
        "software"
    ],
    "wof:name":"Checkmate Associates Ltd",
    "wof:placetype":"venue"
},
  "geometry": {"coordinates":[-0.724374,51.306576],"type":"Point"}
}