{
  "type": "Feature",
  "properties": {
    "addr:full":"6 Peterborough Rd Exeter Devon EX4 2EG",
    "addr:housenumber":"6",
    "addr:postcode":"ex4 2eg",
    "addr:street":"Peterborough Rd",
    "iso:country":"GB",
    "sg:address":"6 Peterborough Rd",
    "sg:city":"Exeter",
    "sg:classifiers":[
        {
            "category":"Professional",
            "subcategory":"Engineering",
            "type":"Services"
        }
    ],
    "sg:phone":"+44 1392 216405",
    "sg:postcode":"EX4 2EG",
    "sg:province":"Devon",
    "sg:tags":[
        "contractor",
        "electrical",
        "engineer"
    ],
    "wof:name":"S M Electrics",
    "wof:placetype":"venue"
},
  "geometry": {"coordinates":[-3.555976,50.726784],"type":"Point"}
}