{
  "type": "Feature",
  "properties": {
    "addr:full":"6 Crusader Industrial Estate, Stirling Road, Cressex Business Park High Wycombe Buckinghamshire HP12 3ST",
    "addr:housenumber":"6",
    "addr:postcode":"hp12 3st",
    "addr:street":"Crusader Industrial Estate Stirling Road Cressex Business Park High",
    "iso:country":"GB",
    "sg:address":"6 Crusader Industrial Estate, Stirling Road, Cressex Business Park",
    "sg:city":"High Wycombe",
    "sg:classifiers":[
        {
            "category":"Manufacturing",
            "subcategory":"Metals",
            "type":"Manufacturing & Wholesale Goods"
        }
    ],
    "sg:phone":"+44 1494 450485",
    "sg:postcode":"HP12 3ST",
    "sg:province":"Buckinghamshire",
    "sg:tags":[
        "work",
        "sheet"
    ],
    "wof:name":"Morgan Wright Ltd.",
    "wof:placetype":"venue"
},
  "geometry": {"coordinates":[-0.7682160139,51.6189613342],"type":"Point"}
}