{
  "type": "Feature",
  "properties": {
    "iso:country":"GB",
    "sg:address":"Unit E, Swains Industrial Estate, Ashingdon Rd",
    "sg:city":"Rochford",
    "sg:classifiers":[
        {
            "category":"Autos & Motor Vehicles",
            "subcategory":"Auto Supplies",
            "type":"Retail Goods"
        }
    ],
    "sg:phone":"+44 1268 681681",
    "sg:postcode":"SS4 1RG",
    "sg:province":"Essex",
    "sg:tags":[
        "component"
    ],
    "wof:name":"Cps",
    "wof:placetype":"venue"
},
  "geometry": {"coordinates":[0.701389,51.583221],"type":"Point"}
}