{
  "type": "Feature",
  "properties": {
    "addr:full":"18 The Friars Canterbury Kent CT1 2AS",
    "addr:housenumber":"18",
    "addr:postcode":"ct1 2as",
    "addr:street":"The Friars",
    "iso:country":"GB",
    "sg:address":"18 The Friars",
    "sg:city":"Canterbury",
    "sg:classifiers":[
        {
            "category":"Travel",
            "subcategory":"Hotels & Motels",
            "type":"Entertainment"
        }
    ],
    "sg:phone":"+44 1227 464531",
    "sg:postcode":"CT1 2AS",
    "sg:province":"Kent",
    "wof:name":"The Pilgrims Hotel",
    "wof:placetype":"venue"
},
  "geometry": {"coordinates":[1.0782370567,51.2804756165],"type":"Point"}
}