{
  "type": "Feature",
  "properties": {
    "addr:full":"102 Walford Road Birmingham West Midlands B11 1QB",
    "addr:housenumber":"102",
    "addr:postcode":"b11 1qb",
    "addr:street":"Walford Road",
    "iso:country":"GB",
    "sg:address":"102 Walford Road",
    "sg:city":"Birmingham",
    "sg:classifiers":[
        {
            "category":"Food & Beverages",
            "subcategory":"Fruits & Vegetables",
            "type":"Retail Goods"
        }
    ],
    "sg:phone":"+44 121 772 7539",
    "sg:postcode":"B11 1QB",
    "sg:province":"West Midlands",
    "sg:tags":[
        "greengrocer"
    ],
    "wof:name":"HAMZA FOOD STORE",
    "wof:placetype":"venue"
},
  "geometry": {"coordinates":[-1.86631,52.459507],"type":"Point"}
}