{
  "type": "Feature",
  "properties": {
    "addr:full":"1 St Peters Way Derby Derbyshire DE1 2NR",
    "addr:housenumber":"1",
    "addr:postcode":"de1 2nr",
    "addr:street":"St Peters Way",
    "iso:country":"GB",
    "sg:address":"1 St Peters Way",
    "sg:city":"Derby",
    "sg:classifiers":[
        {
            "category":"Personal",
            "subcategory":"Beauty Salon",
            "type":"Services"
        }
    ],
    "sg:phone":"+44 1332 372237",
    "sg:postcode":"DE1 2NR",
    "sg:province":"Derbyshire",
    "sg:tags":[
        "unisex",
        "lady",
        "hairdresser"
    ],
    "wof:name":"Keith Hall Salons Ltd.",
    "wof:placetype":"venue"
},
  "geometry": {"coordinates":[-1.4764889479,52.921459198],"type":"Point"}
}