{
  "type": "Feature",
  "properties": {
    "addr:full":"Fields Farm Road, Long Eaton Nottingham Derbyshire NG10 1GT",
    "addr:postcode":"ng10 1gt",
    "addr:street":"Fields Farm Road",
    "iso:country":"GB",
    "sg:address":"Fields Farm Road, Long Eaton",
    "sg:city":"Nottingham",
    "sg:classifiers":[
        {
            "category":"Shopping",
            "subcategory":"Crafts & Fabrics",
            "type":"Retail Goods"
        }
    ],
    "sg:phone":"+44 115 946 1070",
    "sg:postcode":"NG10 1GT",
    "sg:province":"Derbyshire",
    "sg:tags":[
        "yarn",
        "supply"
    ],
    "wof:name":"Sherwood Group (Trading) Ltd.",
    "wof:placetype":"venue"
},
  "geometry": {"coordinates":[-1.2649890184,52.8931541443],"type":"Point"}
}