{
  "type": "Feature",
  "properties": {
    "iso:country":"GB",
    "sg:address":"1 The Royal Corner",
    "sg:city":"Crook",
    "sg:classifiers":[
        {
            "category":"Shopping",
            "subcategory":"Crafts & Fabrics",
            "type":"Retail Goods"
        }
    ],
    "sg:phone":"+44 1388 762568",
    "sg:postcode":"DL15 9UA",
    "sg:province":"Durham",
    "sg:tags":[
        "shop"
    ],
    "wof:name":"Sheiler's Fashions & Fabrics",
    "wof:placetype":"venue"
},
  "geometry": {"coordinates":[-1.747504,54.718376],"type":"Point"}
}