{
  "type": "Feature",
  "properties": {
    "iso:country":"GB",
    "sg:address":"1 Squirrel La",
    "sg:city":"High Wycombe",
    "sg:classifiers":[
        {
            "category":"Bus Charters",
            "type":"Transportation"
        }
    ],
    "sg:phone":"+44 1494 520347",
    "sg:postcode":"HP12 4RX",
    "sg:province":"Buckinghamshire",
    "sg:tags":[
        "hire",
        "coach"
    ],
    "wof:name":"Stigwood Coaches",
    "wof:placetype":"venue"
},
  "geometry": {"coordinates":[-0.7845550179,51.6204910278],"type":"Point"}
}