{
  "type": "Feature",
  "properties": {
    "addr:full":"Grosvenor Street Mold Denbighshire CH7 1EJ",
    "addr:postcode":"ch7 1ej",
    "addr:street":"Grosvenor Street",
    "iso:country":"GB",
    "sg:address":"Grosvenor Street",
    "sg:city":"Mold",
    "sg:classifiers":[
        {
            "category":"Organizations",
            "subcategory":"Membership Organization",
            "type":"Services"
        }
    ],
    "sg:phone":"+44 1352 756088",
    "sg:postcode":"CH7 1EJ",
    "sg:province":"Denbighshire",
    "sg:tags":[
        "club"
    ],
    "wof:name":"Derby & Joan Club",
    "wof:placetype":"venue"
},
  "geometry": {"coordinates":[-3.139064,53.166908],"type":"Point"}
}