{
  "type": "Feature",
  "properties": {
    "iso:country":"GB",
    "sg:address":"900 Kingsbury Rd, Erdington",
    "sg:city":"Birmingham",
    "sg:classifiers":[
        {
            "category":"Health Services",
            "subcategory":"Clinic",
            "type":"Services"
        }
    ],
    "sg:phone":"+44 121 608 7200",
    "sg:postcode":"B24 9PY",
    "sg:province":"West Midlands",
    "sg:tags":[
        "aromatherapy"
    ],
    "wof:name":"Aroma Health International Ltd",
    "wof:placetype":"venue"
},
  "geometry": {"coordinates":[-1.806348,52.518135],"type":"Point"}
}