{
  "type": "Feature",
  "properties": {
    "iso:country":"GB",
    "sg:address":"55 Kirkgate",
    "sg:city":"Otley",
    "sg:classifiers":[
        {
            "category":"Education",
            "subcategory":"Dance Studio",
            "type":"Public Place"
        }
    ],
    "sg:phone":"+44 1943 466452",
    "sg:postcode":"LS21 3HN",
    "sg:province":"North Yorkshire",
    "sg:tags":[
        "school",
        "dancing"
    ],
    "wof:name":"Newall School Of Theatre Dancing",
    "wof:placetype":"venue"
},
  "geometry": {"coordinates":[-1.694273,53.904266],"type":"Point"}
}