{
  "type": "Feature",
  "properties": {
    "addr:full":"300 Harwich Road Colchester Essex CO4 3DL",
    "addr:housenumber":"300",
    "addr:postcode":"co4 3dl",
    "addr:street":"Harwich Road Colchester",
    "iso:country":"GB",
    "sg:address":"300 Harwich Road",
    "sg:city":"Colchester",
    "sg:classifiers":[
        {
            "category":"Building & Trades",
            "subcategory":"Construction",
            "type":"Services"
        }
    ],
    "sg:phone":"+44 1206 864332",
    "sg:postcode":"CO4 3DL",
    "sg:province":"Essex",
    "sg:tags":[
        "builder"
    ],
    "wof:name":"D J Thompson (Builders) Ltd.",
    "wof:placetype":"venue"
},
  "geometry": {"coordinates":[0.9307100177,51.8959617615],"type":"Point"}
}