{
  "type": "Feature",
  "properties": {
    "addr:full":"Cowbridge Road East Cardiff Cardiff CF5 1HE",
    "addr:postcode":"cf5 1he",
    "addr:street":"Cowbridge Road East",
    "iso:country":"GB",
    "sg:address":"Cowbridge Road East",
    "sg:city":"Cardiff",
    "sg:classifiers":[
        {
            "category":"Bars & Pubs",
            "type":"Food & Drink"
        }
    ],
    "sg:phone":"+44 29 2037 7053",
    "sg:postcode":"CF5 1HE",
    "sg:province":"Cardiff",
    "sg:tags":[
        "pubs",
        "inn"
    ],
    "wof:name":"Clive Arms",
    "wof:placetype":"venue"
},
  "geometry": {"coordinates":[-3.2276339531,51.4847831726],"type":"Point"}
}