{
  "type": "Feature",
  "properties": {
    "iso:country":"GB",
    "sg:address":"67 Haig Rd, West Plaistow",
    "sg:city":"London",
    "sg:classifiers":[
        {
            "category":"Professional",
            "subcategory":"Engineering",
            "type":"Services"
        }
    ],
    "sg:postcode":"E13 9LJ",
    "sg:province":"Greater London",
    "sg:tags":[
        "contractor",
        "electrical",
        "engineer"
    ],
    "wof:name":"Harris Electrical Services",
    "wof:placetype":"venue"
},
  "geometry": {"coordinates":[0.033668,51.527302],"type":"Point"}
}