{
  "type": "Feature",
  "properties": {
    "iso:country":"GB",
    "sg:address":"1 Hampton Road",
    "sg:city":"Scarborough",
    "sg:classifiers":[
        {
            "category":"Personal",
            "subcategory":"Barber",
            "type":"Services"
        }
    ],
    "sg:postcode":"YO12 5PU",
    "sg:province":"North Yorkshire",
    "sg:tags":[
        "men's",
        "hairdresser"
    ],
    "wof:name":"Barbers Chair",
    "wof:placetype":"venue"
},
  "geometry": {"coordinates":[-0.4194320142,54.2783889771],"type":"Point"}
}