{
  "type": "Feature",
  "properties": {
    "addr:full":"Arch 293 Cambridge Heath Road, Bethnal Grn London Greater London E2 9HA",
    "addr:housenumber":"293",
    "addr:postcode":"e2 9ha",
    "addr:street":"Arch;Cambridge Heath Road Bethnal Grn",
    "iso:country":"GB",
    "sg:address":"Arch 293 Cambridge Heath Road, Bethnal Grn",
    "sg:city":"London",
    "sg:classifiers":[
        {
            "category":"Professional",
            "subcategory":"Testing Lab",
            "type":"Services"
        }
    ],
    "sg:phone":"+44 20 7739 4718",
    "sg:postcode":"E2 9HA",
    "sg:province":"Greater London",
    "sg:tags":[
        "mot"
    ],
    "wof:name":"Batt Bros",
    "wof:placetype":"venue"
},
  "geometry": {"coordinates":[-0.05678,51.531261],"type":"Point"}
}