{
  "type": "Feature",
  "properties": {
    "addr:full":"349 Bowes Rd, Arnos Gro London Greater London N11 1AA",
    "addr:housenumber":"349",
    "addr:postcode":"n11 1aa",
    "addr:street":"Bowes Rd",
    "iso:country":"GB",
    "sg:address":"349 Bowes Rd, Arnos Gro",
    "sg:city":"London",
    "sg:classifiers":[
        {
            "category":"Food & Beverages",
            "subcategory":"Supermarket",
            "type":"Retail Goods"
        }
    ],
    "sg:phone":"+44 20 8361 4657",
    "sg:postcode":"N11 1AA",
    "sg:province":"Greater London",
    "wof:name":"Dadyal Food & Wine Ltd",
    "wof:placetype":"venue"
},
  "geometry": {"coordinates":[-0.134352,51.615932],"type":"Point"}
}