{
  "type": "Feature",
  "properties": {
    "iso:country":"GB",
    "sg:address":"6 Fleet Close Page Hill, Buckingham",
    "sg:city":"Buckingham",
    "sg:classifiers":[
        {
            "category":"Professional",
            "subcategory":"Management & Consulting",
            "type":"Services"
        }
    ],
    "sg:postcode":"MK18 1YN",
    "sg:province":"Buckinghamshire",
    "sg:tags":[
        "consultant",
        "safety",
        "environmental"
    ],
    "wof:name":"Pristine Condition Ltd",
    "wof:placetype":"venue"
},
  "geometry": {"coordinates":[-0.9727569818,52.0047225952],"type":"Point"}
}