{
  "type": "Feature",
  "properties": {
    "addr:full":"Crown Farm, Goole Road, Moorends Doncaster East Riding of Yorkshire DN8 4JX",
    "addr:postcode":"dn8 4jx",
    "addr:street":"Goole Road;Riding",
    "iso:country":"GB",
    "sg:address":"Crown Farm, Goole Road, Moorends",
    "sg:city":"Doncaster",
    "sg:classifiers":[
        {
            "category":"Farming",
            "subcategory":"Livestock Farm",
            "type":"Manufacturing & Wholesale Goods"
        }
    ],
    "sg:phone":"+44 1405 812659",
    "sg:postcode":"DN8 4JX",
    "sg:province":"East Riding of Yorkshire",
    "sg:tags":[
        "others"
    ],
    "wof:name":"C Measures & Son",
    "wof:placetype":"venue"
},
  "geometry": {"coordinates":[-0.9515540004,53.6278648376],"type":"Point"}
}