{
  "type": "Feature",
  "properties": {
    "addr:full":"Market Yard, Justice Lane Frome Somerset BA11 1BE",
    "addr:postcode":"ba11 1be",
    "addr:street":"Justice Lane",
    "iso:country":"GB",
    "sg:address":"Market Yard, Justice Lane",
    "sg:city":"Frome",
    "sg:classifiers":[
        {
            "category":"Community Center",
            "type":"Public Place"
        },
        {
            "category":"Arts & Performance",
            "subcategory":"Theater",
            "type":"Entertainment"
        }
    ],
    "sg:phone":"+44 1373 455768",
    "sg:postcode":"BA11 1BE",
    "sg:province":"Somerset",
    "sg:tags":[
        "hall",
        "concert",
        "theatre",
        "centre"
    ],
    "wof:name":"Cheese & Grain Bar",
    "wof:placetype":"venue"
},
  "geometry": {"coordinates":[-2.318807,51.228558],"type":"Point"}
}