{
  "type": "Feature",
  "properties": {
    "addr:full":"14 Penhall Rd, Charlton London Greater London SE7 8RX",
    "addr:housenumber":"14",
    "addr:postcode":"se7 8rx",
    "addr:street":"Penhall Rd",
    "iso:country":"GB",
    "sg:address":"14 Penhall Rd, Charlton",
    "sg:city":"London",
    "sg:classifiers":[
        {
            "category":"Shopping",
            "type":"Retail Goods"
        }
    ],
    "sg:postcode":"SE7 8RX",
    "sg:province":"Greater London",
    "sg:tags":[
        "part",
        "accessory"
    ],
    "wof:name":"Lympne Motor Services Ltd",
    "wof:placetype":"venue"
},
  "geometry": {"coordinates":[0.037162,51.490971],"type":"Point"}
}