{
  "type": "Feature",
  "properties": {
    "addr:full":"Suit, 1-7 Artillery Row Westminster Greater London SW1P 1RL",
    "addr:housenumber":"1-7",
    "addr:postcode":"sw1p 1rl",
    "addr:street":"Artillery Row",
    "iso:country":"GB",
    "sg:address":"Suit, 1-7 Artillery Row",
    "sg:city":"Westminster",
    "sg:classifiers":[
        {
            "category":"Professional",
            "subcategory":"Accounting & Tax Preparation",
            "type":"Services"
        }
    ],
    "sg:phone":"+44 20 7799 3717",
    "sg:postcode":"SW1P 1RL",
    "sg:province":"Greater London",
    "sg:tags":[
        "accountant"
    ],
    "wof:name":"Gabem Group Ltd",
    "wof:placetype":"venue"
},
  "geometry": {"coordinates":[-0.127994,51.500065],"type":"Point"}
}