{
  "type": "Feature",
  "properties": {
    "iso:country":"GB",
    "sg:address":"Morrison Road",
    "sg:city":"Port Talbot",
    "sg:classifiers":[
        {
            "category":"Health Services",
            "subcategory":"Doctor",
            "type":"Services"
        }
    ],
    "sg:phone":"+44 1639 887790",
    "sg:postcode":"SA12 6TH",
    "sg:province":"Neath Port Talbot",
    "sg:tags":[
        "practitioners"
    ],
    "wof:name":"Morrison Road Surgery",
    "wof:placetype":"venue"
},
  "geometry": {"coordinates":[-3.8023691177,51.5913848877],"type":"Point"}
}