{
  "type": "Feature",
  "properties": {
    "addr:full":"4 Boyces Avenue, Clifton Bristol City of Bristol BS8 4AA",
    "addr:housenumber":"4",
    "addr:postcode":"bs8 4aa",
    "addr:street":"Boyces Avenue",
    "iso:country":"GB",
    "sg:address":"4 Boyces Avenue, Clifton",
    "sg:city":"Bristol",
    "sg:classifiers":[
        {
            "category":"Museum",
            "subcategory":"Art Museum",
            "type":"Entertainment"
        }
    ],
    "sg:phone":"+44 1453 43357",
    "sg:postcode":"BS8 4AA",
    "sg:province":"City of Bristol",
    "sg:tags":[
        "gallery"
    ],
    "wof:name":"Michael Wright Fine Art",
    "wof:placetype":"venue"
},
  "geometry": {"coordinates":[-2.618278,51.455383],"type":"Point"}
}