{
  "type": "Feature",
  "properties": {
    "addr:full":"St Cross Road Winchester Hampshire SO23 9HZ",
    "addr:postcode":"so23 9hz",
    "addr:street":"St Cross Road",
    "iso:country":"GB",
    "sg:address":"St Cross Road",
    "sg:city":"Winchester",
    "sg:classifiers":[
        {
            "category":"Autos & Motor Vehicles",
            "subcategory":"Auto Supplies",
            "type":"Retail Goods"
        }
    ],
    "sg:phone":"+44 1962 866183",
    "sg:postcode":"SO23 9HZ",
    "sg:province":"Hampshire",
    "sg:tags":[
        "tyre"
    ],
    "wof:name":"National Tyre Service Ltd.",
    "wof:placetype":"venue"
},
  "geometry": {"coordinates":[-1.318479,51.060146],"type":"Point"}
}