{
  "type": "Feature",
  "properties": {
    "iso:country":"GB",
    "sg:address":"86 High St",
    "sg:city":"Marlborough",
    "sg:classifiers":[
        {
            "category":"Shopping",
            "subcategory":"Pharmacy",
            "type":"Retail Goods"
        }
    ],
    "sg:phone":"+44 1672 515151",
    "sg:postcode":"SN8 1HF",
    "sg:province":"Berkshire",
    "sg:tags":[
        "medicine",
        "therapy"
    ],
    "wof:name":"High Street Clinic Malborough The",
    "wof:placetype":"venue"
},
  "geometry": {"coordinates":[-1.734008,51.418461],"type":"Point"}
}