{
  "type": "Feature",
  "properties": {
    "iso:country":"GB",
    "sg:address":"Smithfield",
    "sg:city":"London",
    "sg:classifiers":[
        {
            "category":"Wholesale",
            "subcategory":"Meat",
            "type":"Manufacturing & Wholesale Goods"
        }
    ],
    "sg:phone":"+44 20 7236 4030",
    "sg:postcode":"EC1A 9AU",
    "sg:province":"Greater London",
    "sg:tags":[
        "-"
    ],
    "wof:name":"Reeve & Co. Ltd.",
    "wof:placetype":"venue"
},
  "geometry": {"coordinates":[-0.10196,51.517841],"type":"Point"}
}