{
  "type": "Feature",
  "properties": {
    "addr:full":"484 Blackpool Road, Ashton-on-ribble Preston Lancashire PR2 1HX",
    "addr:housenumber":"484",
    "addr:postcode":"pr2 1hx",
    "addr:street":"Blackpool Road",
    "iso:country":"GB",
    "sg:address":"484 Blackpool Road, Ashton-on-ribble",
    "sg:city":"Preston",
    "sg:classifiers":[
        {
            "category":"Organizations",
            "subcategory":"Non-profit Organization",
            "type":"Services"
        }
    ],
    "sg:phone":"+44 1772 736844",
    "sg:postcode":"PR2 1HX",
    "sg:province":"Lancashire",
    "sg:tags":[
        "charitable",
        "organisation",
        "voluntary",
        "charity"
    ],
    "wof:name":"The Samaritans",
    "wof:placetype":"venue"
},
  "geometry": {"coordinates":[-2.7512090206,53.7686080933],"type":"Point"}
}