{
  "type": "Feature",
  "properties": {
    "addr:full":"Provision Market Norwich Norfolk NR2 1ND",
    "addr:postcode":"nr2 1nd",
    "addr:street":"Norwich Norfolk",
    "iso:country":"GB",
    "sg:address":"Provision Market",
    "sg:city":"Norwich",
    "sg:classifiers":[
        {
            "category":"Shopping",
            "subcategory":"Photographic Equipment",
            "type":"Retail Goods"
        }
    ],
    "sg:phone":"+44 1603 764893",
    "sg:postcode":"NR2 1ND",
    "sg:province":"Norfolk",
    "sg:tags":[
        "supply"
    ],
    "wof:name":"Neville G Reid",
    "wof:placetype":"venue"
},
  "geometry": {"coordinates":[1.293,52.628502],"type":"Point"}
}