{
  "type": "Feature",
  "properties": {
    "iso:country":"GB",
    "sg:address":"77 Warbreck Drive",
    "sg:city":"Blackpool",
    "sg:classifiers":[
        {
            "category":"Travel",
            "subcategory":"Hotels & Motels",
            "type":"Entertainment"
        }
    ],
    "sg:phone":"+44 1253 351977",
    "sg:postcode":"FY2 9RZ",
    "sg:province":"Lancashire",
    "sg:tags":[
        "house",
        "self",
        "guest",
        "catering"
    ],
    "wof:name":"Sunrise Holiday Flat",
    "wof:placetype":"venue"
},
  "geometry": {"coordinates":[-3.05036,53.837234],"type":"Point"}
}