{
  "type": "Feature",
  "properties": {
    "addr:full":"Clarence Road, Bollington Macclesfield Cheshire SK10 5JZ",
    "addr:postcode":"sk10 5jz",
    "addr:street":"Clarence Road",
    "iso:country":"GB",
    "sg:address":"Clarence Road, Bollington",
    "sg:city":"Macclesfield",
    "sg:classifiers":[
        {
            "category":"Manufacturing",
            "subcategory":"Building Materials",
            "type":"Manufacturing & Wholesale Goods"
        }
    ],
    "sg:phone":"+44 1625 573697",
    "sg:postcode":"SK10 5JZ",
    "sg:province":"Cheshire",
    "sg:tags":[
        "extrusion"
    ],
    "wof:name":"Extruded Plastics Ltd.",
    "wof:placetype":"venue"
},
  "geometry": {"coordinates":[-2.1103689671,53.2933883667],"type":"Point"}
}