{
  "type": "Feature",
  "properties": {
    "addr:full":"Newater House, 11 Newhall Street Birmingham West Midlands B3 3NY",
    "addr:housenumber":"11",
    "addr:postcode":"b3 3ny",
    "addr:street":"Newhall Street",
    "iso:country":"GB",
    "sg:address":"Newater House, 11 Newhall Street",
    "sg:city":"Birmingham",
    "sg:classifiers":[
        {
            "category":"Professional",
            "subcategory":"Management & Consulting",
            "type":"Services"
        },
        {
            "category":"Professional",
            "subcategory":"Computer Services",
            "type":"Services"
        }
    ],
    "sg:postcode":"B3 3NY",
    "sg:province":"West Midlands",
    "sg:tags":[
        "software",
        "system",
        "holding",
        "activity"
    ],
    "wof:name":"SANDERSON COMPUTER SERVICES LTD",
    "wof:placetype":"venue"
},
  "geometry": {"coordinates":[-1.9017330408,52.4814224243],"type":"Point"}
}