{
  "type": "Feature",
  "properties": {
    "addr:full":"3 Doddington Place Pontypridd Caerphilly CF37 4LN",
    "addr:housenumber":"3",
    "addr:postcode":"cf37 4ln",
    "addr:street":"Doddington Place",
    "iso:country":"GB",
    "sg:address":"3 Doddington Place",
    "sg:city":"Pontypridd",
    "sg:classifiers":[
        {
            "category":"Military Area",
            "subcategory":"Air Force Base",
            "type":"Public Place"
        }
    ],
    "sg:postcode":"CF37 4LN",
    "sg:province":"Caerphilly",
    "sg:tags":[
        "taxi",
        "hire",
        "private"
    ],
    "wof:name":"Cavalier Cabs",
    "wof:placetype":"venue"
},
  "geometry": {"coordinates":[-3.3297240734,51.6092605591],"type":"Point"}
}