{
  "type": "Feature",
  "properties": {
    "iso:country":"GB",
    "sg:address":"15 Telford Road, Ferndown Industrial Estate, Ferndown",
    "sg:city":"Wimborne",
    "sg:classifiers":[
        {
            "category":"Professional",
            "subcategory":"Engineering",
            "type":"Services"
        }
    ],
    "sg:postcode":"BH21 7QR",
    "sg:province":"Dorset",
    "sg:tags":[
        "precision",
        "engineer"
    ],
    "wof:name":"J P Engineering",
    "wof:placetype":"venue"
},
  "geometry": {"coordinates":[-1.91608,50.813904],"type":"Point"}
}