{
  "type": "Feature",
  "properties": {
    "addr:full":"Unit 1 Glasgow Glasgow City G41 1EZ",
    "addr:housenumber":"unit 1",
    "addr:postcode":"g41 1ez",
    "iso:country":"GB",
    "sg:address":"Unit 1",
    "sg:city":"Glasgow",
    "sg:classifiers":[
        {
            "category":"Manufacturing",
            "subcategory":"Metals",
            "type":"Manufacturing & Wholesale Goods"
        }
    ],
    "sg:postcode":"G41 1EZ",
    "sg:province":"Glasgow City",
    "sg:tags":[
        "blacksmith",
        "forgemasters"
    ],
    "wof:name":"Lawrence Fabrication",
    "wof:placetype":"venue"
},
  "geometry": {"coordinates":[-4.28145,55.850819],"type":"Point"}
}