{
  "type": "Feature",
  "properties": {
    "iso:country":"GB",
    "sg:address":"Unit 11 Apex Business Park, Diplocks Way",
    "sg:city":"Hailsham",
    "sg:classifiers":[
        {
            "category":"Wholesale",
            "subcategory":"Machinery & Supplies",
            "type":"Manufacturing & Wholesale Goods"
        }
    ],
    "sg:phone":"+44 1323 849849",
    "sg:postcode":"BN27 3JF",
    "sg:province":"East Sussex",
    "sg:tags":[
        "pump"
    ],
    "wof:name":"Fristam Pumps (U K) Ltd.",
    "wof:placetype":"venue"
},
  "geometry": {"coordinates":[0.25652,50.865383],"type":"Point"}
}