{
  "type": "Feature",
  "properties": {
    "addr:full":"5a Cameron Square Fort William Highland PH33 6AJ",
    "addr:housenumber":"5a",
    "addr:postcode":"ph33 6aj",
    "addr:street":"Cameron Square",
    "iso:country":"GB",
    "sg:address":"5a Cameron Square",
    "sg:city":"Fort William",
    "sg:classifiers":[
        {
            "category":"Organizations",
            "subcategory":"Non-profit Organization",
            "type":"Services"
        }
    ],
    "sg:phone":"+44 1397 705811",
    "sg:postcode":"PH33 6AJ",
    "sg:province":"Highland",
    "sg:tags":[
        "organisation",
        "voluntary",
        "charity"
    ],
    "wof:name":"Save The Children Charity Shop",
    "wof:placetype":"venue"
},
  "geometry": {"coordinates":[-5.11069,56.817837],"type":"Point"}
}