{
  "type": "Feature",
  "properties": {
    "iso:country":"GB",
    "sg:address":"10 Shrewsbury Mews",
    "sg:city":"London",
    "sg:classifiers":[
        {
            "category":"Professional",
            "subcategory":"Lawyer & Legal Services",
            "type":"Services"
        }
    ],
    "sg:postcode":"W2 5PN",
    "sg:province":"Greater London",
    "wof:name":"Stebbing & Co",
    "wof:placetype":"venue"
},
  "geometry": {"coordinates":[-0.196733,51.518776],"type":"Point"}
}