{
  "type": "Feature",
  "properties": {
    "addr:full":"Lacey House, St Clare Business Park, Holly Road Hampton Greater London TW12 1QQ",
    "addr:postcode":"tw12 1qq",
    "addr:street":"St;Business Park Holly Road",
    "iso:country":"GB",
    "sg:address":"Lacey House, St Clare Business Park, Holly Road",
    "sg:city":"Hampton",
    "sg:classifiers":[
        {
            "category":"Travel",
            "subcategory":"Travel Agent",
            "type":"Entertainment"
        }
    ],
    "sg:phone":"+44 1256 703474",
    "sg:postcode":"TW12 1QQ",
    "sg:province":"Greater London",
    "wof:name":"Peregrine Travel Ltd.",
    "wof:placetype":"venue"
},
  "geometry": {"coordinates":[-0.358914,51.424904],"type":"Point"}
}