{
  "type": "Feature",
  "properties": {
    "addr:full":"92 Caledonia St Glasgow Glasgow City G5 0XG",
    "addr:housenumber":"92",
    "addr:postcode":"g5 0xg",
    "addr:street":"Caledonia St",
    "iso:country":"GB",
    "sg:address":"92 Caledonia St",
    "sg:city":"Glasgow",
    "sg:classifiers":[
        {
            "category":"Banks & Credit Unions",
            "subcategory":"Investment Brokerage",
            "type":"Services"
        }
    ],
    "sg:phone":"+44 141 429 2868",
    "sg:postcode":"G5 0XG",
    "sg:province":"Glasgow City",
    "sg:tags":[
        "agent"
    ],
    "wof:name":"J Cameron",
    "wof:placetype":"venue"
},
  "geometry": {"coordinates":[-4.245716095,55.8407020569],"type":"Point"}
}