{
  "type": "Feature",
  "properties": {
    "addr:full":"1 Vernon Av Manchester Greater Manchester M30 0UE",
    "addr:housenumber":"1",
    "addr:postcode":"m30 0ue",
    "addr:street":"Vernon Av",
    "iso:country":"GB",
    "sg:address":"1 Vernon Av",
    "sg:city":"Manchester",
    "sg:classifiers":[
        {
            "category":"Building & Trades",
            "subcategory":"Construction",
            "type":"Services"
        }
    ],
    "sg:phone":"+44 161 789 7650",
    "sg:postcode":"M30 0UE",
    "sg:province":"Greater Manchester",
    "sg:tags":[
        "joiner",
        "carpenter"
    ],
    "wof:name":"B Smart",
    "wof:placetype":"venue"
},
  "geometry": {"coordinates":[-2.340071,53.485153],"type":"Point"}
}