{
  "type": "Feature",
  "properties": {
    "iso:country":"GB",
    "sg:address":"Westacre, Hurst Lane",
    "sg:city":"Egham",
    "sg:classifiers":[
        {
            "category":"Transit Center",
            "subcategory":"Passenger",
            "type":"Transportation"
        }
    ],
    "sg:postcode":"TW20 8QJ",
    "sg:province":"Surrey",
    "sg:tags":[
        "boarding",
        "kennel",
        "catteries"
    ],
    "wof:name":"Egham Boarding Cattery",
    "wof:placetype":"venue"
},
  "geometry": {"coordinates":[-0.547489,51.430897],"type":"Point"}
}