{
  "type": "Feature",
  "properties": {
    "addr:full":"5 Castle Walk, Lwr St Stansted Essex CM24 8LY",
    "addr:housenumber":"5",
    "addr:postcode":"cm24 8ly",
    "addr:street":"Castle Walk;St",
    "iso:country":"GB",
    "sg:address":"5 Castle Walk, Lwr St",
    "sg:city":"Stansted",
    "sg:classifiers":[
        {
            "category":"Retail",
            "subcategory":"Laundry & Dry Cleaning",
            "type":"Services"
        }
    ],
    "sg:phone":"+44 1279 814021",
    "sg:postcode":"CM24 8LY",
    "sg:province":"Essex",
    "sg:tags":[
        "alteration"
    ],
    "wof:name":"Deans,David A,Ltd",
    "wof:placetype":"venue"
},
  "geometry": {"coordinates":[0.2005199939,51.9026184082],"type":"Point"}
}