{
  "type": "Feature",
  "properties": {
    "addr:full":"436 Chepstow Road Newport Newport NP19 8JG",
    "addr:housenumber":"436",
    "addr:postcode":"np19 8jg",
    "addr:street":"Chepstow Road",
    "iso:country":"GB",
    "sg:address":"436 Chepstow Road",
    "sg:city":"Newport",
    "sg:classifiers":[
        {
            "category":"Personal",
            "subcategory":"Beauty Salon",
            "type":"Services"
        },
        {
            "category":"Personal",
            "subcategory":"Barber",
            "type":"Services"
        }
    ],
    "sg:phone":"+44 1633 278338",
    "sg:postcode":"NP19 8JG",
    "sg:province":"Newport",
    "sg:tags":[
        "unisex",
        "hairdresser"
    ],
    "wof:name":"Boomerang Hair Studio",
    "wof:placetype":"venue"
},
  "geometry": {"coordinates":[-2.963807,51.587997],"type":"Point"}
}