{
  "type": "Feature",
  "properties": {
    "addr:full":"9 Queens Way, Nescliffe Shrewsbury Shropshire SY4 1BD",
    "addr:housenumber":"9",
    "addr:postcode":"sy4 1bd",
    "addr:street":"Queens Way Nescliffe",
    "iso:country":"GB",
    "sg:address":"9 Queens Way, Nescliffe",
    "sg:city":"Shrewsbury",
    "sg:classifiers":[
        {
            "category":"Building & Trades",
            "subcategory":"Cleaning & Sanitation",
            "type":"Services"
        }
    ],
    "sg:postcode":"SY4 1BD",
    "sg:province":"Shropshire",
    "sg:tags":[
        "sweep",
        "chimney"
    ],
    "wof:name":"John Thomson",
    "wof:placetype":"venue"
},
  "geometry": {"coordinates":[-2.9240860939,52.763885498],"type":"Point"}
}