{
  "type": "Feature",
  "properties": {
    "addr:full":"1 Northumberland Avenue London Greater London WC2N 5BW",
    "addr:housenumber":"1",
    "addr:postcode":"wc2n 5bw",
    "addr:street":"Northumberland Avenue",
    "iso:country":"GB",
    "sg:address":"1 Northumberland Avenue",
    "sg:city":"London",
    "sg:classifiers":[
        {
            "category":"Professional",
            "subcategory":"Computer Services",
            "type":"Services"
        }
    ],
    "sg:phone":"+44 20 7872 5530",
    "sg:postcode":"WC2N 5BW",
    "sg:province":"Greater London",
    "sg:tags":[
        "system",
        "software"
    ],
    "wof:name":"Trema",
    "wof:placetype":"venue"
},
  "geometry": {"coordinates":[-0.122912,51.506744],"type":"Point"}
}