{
  "type": "Feature",
  "properties": {
    "iso:country":"GB",
    "sg:address":"West Mills",
    "sg:city":"Haddington",
    "sg:classifiers":[
        {
            "category":"Shopping",
            "subcategory":"Crafts & Fabrics",
            "type":"Retail Goods"
        }
    ],
    "sg:postcode":"EH41 4DR",
    "sg:province":"East Lothian",
    "sg:tags":[
        "knitwear",
        "yarn"
    ],
    "wof:name":"Kerr Knitwear Ltd",
    "wof:placetype":"venue"
},
  "geometry": {"coordinates":[-2.776574,55.955471],"type":"Point"}
}