{
  "type": "Feature",
  "properties": {
    "addr:full":"253 Chipstead Valley Rd Coulsdon Surrey CR5 3BY",
    "addr:housenumber":"253",
    "addr:postcode":"cr5 3by",
    "addr:street":"Chipstead Valley Rd",
    "iso:country":"GB",
    "sg:address":"253 Chipstead Valley Rd",
    "sg:city":"Coulsdon",
    "sg:classifiers":[
        {
            "category":"Utilities",
            "subcategory":"Refuse",
            "type":"Services"
        }
    ],
    "sg:phone":"+44 1737 557077",
    "sg:postcode":"CR5 3BY",
    "sg:province":"Surrey",
    "sg:tags":[
        "disposal",
        "waste"
    ],
    "wof:name":"Parson's Rubbish Removal",
    "wof:placetype":"venue"
},
  "geometry": {"coordinates":[-0.1521490067,51.3181915283],"type":"Point"}
}