{
  "type": "Feature",
  "properties": {
    "iso:country":"GB",
    "sg:address":"Flowers Drove, Lytchett Matravers",
    "sg:city":"Poole",
    "sg:classifiers":[
        {
            "category":"Travel",
            "subcategory":"Hotels & Motels",
            "type":"Entertainment"
        },
        {
            "category":"Building & Trades",
            "subcategory":"Plumbing",
            "type":"Services"
        }
    ],
    "sg:phone":"+44 1202 632337",
    "sg:postcode":"BH16 6BX",
    "sg:province":"Dorset",
    "sg:tags":[
        "house",
        "heating",
        "guest"
    ],
    "wof:name":"STEVE & KERRY ASH",
    "wof:placetype":"venue"
},
  "geometry": {"coordinates":[-2.076454,50.761681],"type":"Point"}
}