{
  "type": "Feature",
  "properties": {
    "addr:full":"106 Great Russell Street London Greater London WC1B 3NB",
    "addr:housenumber":"106",
    "addr:postcode":"wc1b 3nb",
    "addr:street":"Great Russell Street",
    "iso:country":"GB",
    "sg:address":"106 Great Russell Street",
    "sg:city":"London",
    "sg:classifiers":[
        {
            "category":"Shopping",
            "subcategory":"Books",
            "type":"Retail Goods"
        }
    ],
    "sg:phone":"+44 20 7580 2311",
    "sg:postcode":"WC1B 3NB",
    "sg:province":"Greater London",
    "sg:tags":[
        "second-hand"
    ],
    "wof:name":"Robert Frew Ltd.",
    "wof:placetype":"venue"
},
  "geometry": {"coordinates":[-0.12915,51.51759],"type":"Point"}
}