{
  "type": "Feature",
  "properties": {
    "addr:full":"105 Ormskirk Road, Newtown Wigan Lancashire WN5 9EA",
    "addr:housenumber":"105",
    "addr:postcode":"wn5 9ea",
    "addr:street":"Ormskirk Road",
    "iso:country":"GB",
    "sg:address":"105 Ormskirk Road, Newtown",
    "sg:city":"Wigan",
    "sg:classifiers":[
        {
            "category":"Shopping",
            "subcategory":"Thrift Store",
            "type":"Retail Goods"
        }
    ],
    "sg:phone":"+44 1942 201383",
    "sg:postcode":"WN5 9EA",
    "sg:province":"Lancashire",
    "sg:tags":[
        "shop",
        "charity"
    ],
    "wof:name":"Butterflies",
    "wof:placetype":"venue"
},
  "geometry": {"coordinates":[-2.653177,53.539558],"type":"Point"}
}