{
  "type": "Feature",
  "properties": {
    "addr:full":"Chalet Pavilion, Carding Mill Valley Church Stretton Shropshire SY6 6JG",
    "addr:postcode":"sy6 6jg",
    "addr:street":"Carding Mill",
    "iso:country":"GB",
    "sg:address":"Chalet Pavilion, Carding Mill Valley",
    "sg:city":"Church Stretton",
    "sg:classifiers":[
        {
            "category":"Professional",
            "subcategory":"Management & Consulting",
            "type":"Services"
        },
        {
            "category":"Cafe",
            "type":"Food & Drink"
        }
    ],
    "sg:phone":"+44 1694 722631",
    "sg:postcode":"SY6 6JG",
    "sg:province":"Shropshire",
    "sg:tags":[
        "tea",
        "conservation",
        "room"
    ],
    "wof:name":"National Trust (The)",
    "wof:placetype":"venue"
},
  "geometry": {"coordinates":[-2.8187990189,52.5205421448],"type":"Point"}
}