{
  "type": "Feature",
  "properties": {
    "addr:full":"550 Bath Road West Drayton Greater London UB7 0EE",
    "addr:housenumber":"550",
    "addr:postcode":"ub7 0ee",
    "addr:street":"Bath Road",
    "iso:country":"GB",
    "sg:address":"550 Bath Road",
    "sg:city":"West Drayton",
    "sg:classifiers":[
        {
            "category":"Travel",
            "subcategory":"Hotels & Motels",
            "type":"Entertainment"
        }
    ],
    "sg:phone":"+44 1753 682969",
    "sg:postcode":"UB7 0EE",
    "sg:province":"Greater London",
    "sg:tags":[
        "house",
        "guest"
    ],
    "wof:name":"Longford Guest House",
    "wof:placetype":"venue"
},
  "geometry": {"coordinates":[-0.491294,51.480152],"type":"Point"}
}