{
  "type": "Feature",
  "properties": {
    "iso:country":"GB",
    "sg:address":"The Woodlands, Hallcourt Cres, Walsall Rd",
    "sg:city":"Cannock",
    "sg:classifiers":[
        {
            "category":"Professional",
            "subcategory":"Engineering",
            "type":"Services"
        }
    ],
    "sg:phone":"+44 1543 504114",
    "sg:postcode":"WS11 3AB",
    "sg:province":"Staffordshire",
    "sg:tags":[
        "consulting",
        "engineer"
    ],
    "wof:name":"W H Thomas & Parnters",
    "wof:placetype":"venue"
},
  "geometry": {"coordinates":[-2.033145,52.690952],"type":"Point"}
}