{
  "type": "Feature",
  "properties": {
    "addr:full":"Braidland, Stewarton Kilmarnock East Ayrshire KA3 5JR",
    "addr:postcode":"ka3 5jr",
    "addr:street":"Braidland;East",
    "iso:country":"GB",
    "sg:address":"Braidland, Stewarton",
    "sg:city":"Kilmarnock",
    "sg:classifiers":[
        {
            "category":"Farming",
            "subcategory":"Livestock Farm",
            "type":"Manufacturing & Wholesale Goods"
        }
    ],
    "sg:phone":"+44 1560 484227",
    "sg:postcode":"KA3 5JR",
    "sg:province":"East Ayrshire",
    "sg:tags":[
        "others"
    ],
    "wof:name":"James Barr & Son",
    "wof:placetype":"venue"
},
  "geometry": {"coordinates":[-4.515129,55.680191],"type":"Point"}
}