{
  "type": "Feature",
  "properties": {
    "addr:full":"121 High Street, Tibshelf Alfreton Derbyshire DE55 5PP",
    "addr:housenumber":"121",
    "addr:postcode":"de55 5pp",
    "addr:street":"High Street",
    "iso:country":"GB",
    "sg:address":"121 High Street, Tibshelf",
    "sg:city":"Alfreton",
    "sg:classifiers":[
        {
            "category":"Organizations",
            "subcategory":"Membership Organization",
            "type":"Services"
        }
    ],
    "sg:phone":"+44 1773 873234",
    "sg:postcode":"DE55 5PP",
    "sg:province":"Derbyshire",
    "sg:tags":[
        "club"
    ],
    "wof:name":"National Union of Club Stewards",
    "wof:placetype":"venue"
},
  "geometry": {"coordinates":[-1.340081,53.144604],"type":"Point"}
}