{
  "type": "Feature",
  "properties": {
    "addr:full":"Bilbrook Road, Bilbrook Wolverhampton Shropshire WV8 1EU",
    "addr:postcode":"wv8 1eu",
    "addr:street":"Bilbrook Road",
    "iso:country":"GB",
    "sg:address":"Bilbrook Road, Bilbrook",
    "sg:city":"Wolverhampton",
    "sg:classifiers":[
        {
            "category":"Education",
            "subcategory":"School",
            "type":"Public Place"
        }
    ],
    "sg:phone":"+44 1902 434300",
    "sg:postcode":"WV8 1EU",
    "sg:province":"Shropshire",
    "sg:tags":[
        "local",
        "authority"
    ],
    "wof:name":"Lane Green First School",
    "wof:placetype":"venue"
},
  "geometry": {"coordinates":[-2.184948,52.631096],"type":"Point"}
}