{
  "type": "Feature",
  "properties": {
    "addr:full":"71a High Street, Bathford Bath Bath and North East Somerset BA1 7TF",
    "addr:housenumber":"71a",
    "addr:postcode":"ba1 7tf",
    "addr:street":"High Street",
    "iso:country":"GB",
    "sg:address":"71a High Street, Bathford",
    "sg:city":"Bath",
    "sg:classifiers":[
        {
            "category":"Building & Trades",
            "subcategory":"Construction",
            "type":"Services"
        }
    ],
    "sg:phone":"+44 1225 858534",
    "sg:postcode":"BA1 7TF",
    "sg:province":"Bath and North East Somerset",
    "sg:tags":[
        "builder"
    ],
    "wof:name":"Hawkins Bros",
    "wof:placetype":"venue"
},
  "geometry": {"coordinates":[-2.296181,51.399578],"type":"Point"}
}