{
  "type": "Feature",
  "properties": {
    "addr:full":"229 Deptford High Street London Greater London SE8 3NT",
    "addr:housenumber":"229",
    "addr:postcode":"se8 3nt",
    "addr:street":"Deptford High Street",
    "iso:country":"GB",
    "sg:address":"229 Deptford High Street",
    "sg:city":"London",
    "sg:classifiers":[
        {
            "category":"Professional",
            "subcategory":"Lawyer & Legal Services",
            "type":"Services"
        }
    ],
    "sg:phone":"+44 20 8692 8181",
    "sg:postcode":"SE8 3NT",
    "sg:province":"Greater London",
    "sg:tags":[
        "solicitor"
    ],
    "wof:name":"Brady Eastwood Pierce & Stewart",
    "wof:placetype":"venue"
},
  "geometry": {"coordinates":[-0.0263989996,51.4814796448],"type":"Point"}
}