{
  "type": "Feature",
  "properties": {
    "iso:country":"GB",
    "sg:address":"Trout Lane Depot, Rainbow Industrial Estate",
    "sg:city":"West Drayton",
    "sg:classifiers":[
        {
            "category":"Freight",
            "type":"Transportation"
        }
    ],
    "sg:phone":"+44 1895 448258",
    "sg:postcode":"UB7 7SA",
    "sg:province":"Greater London",
    "sg:tags":[
        "haulage",
        "road"
    ],
    "wof:name":"Sweeney Transport Ltd.",
    "wof:placetype":"venue"
},
  "geometry": {"coordinates":[-0.4824149907,51.5147285461],"type":"Point"}
}