{
  "type": "Feature",
  "properties": {
    "addr:full":"591-593 New South Promenade Blackpool Lancashire FY4 1NG",
    "addr:housenumber":"591-593",
    "addr:postcode":"fy4 1ng",
    "addr:street":"New South Promenade",
    "iso:country":"GB",
    "sg:address":"591-593 New South Promenade",
    "sg:city":"Blackpool",
    "sg:classifiers":[
        {
            "category":"Travel",
            "subcategory":"Hotels & Motels",
            "type":"Entertainment"
        }
    ],
    "sg:phone":"+44 1253 341143",
    "sg:postcode":"FY4 1NG",
    "sg:province":"Lancashire",
    "wof:name":"Waldorf Hotel",
    "wof:placetype":"venue"
},
  "geometry": {"coordinates":[-3.0575039387,53.7854232788],"type":"Point"}
}