{
  "type": "Feature",
  "properties": {
    "addr:full":"9-17 Marsh Green Rd, Marsh Barton Exeter Devon EX2 8NY",
    "addr:housenumber":"9-17",
    "addr:postcode":"ex2 8ny",
    "addr:street":"Marsh Green Rd",
    "iso:country":"GB",
    "sg:address":"9-17 Marsh Green Rd, Marsh Barton",
    "sg:city":"Exeter",
    "sg:classifiers":[
        {
            "category":"Home & Garden",
            "subcategory":"Hardware",
            "type":"Retail Goods"
        }
    ],
    "sg:phone":"+44 1392 277370",
    "sg:postcode":"EX2 8NY",
    "sg:province":"Devon",
    "sg:tags":[
        "paint"
    ],
    "wof:name":"Dulux Decorator Centre",
    "wof:placetype":"venue"
},
  "geometry": {"coordinates":[-3.5271320343,50.7088050842],"type":"Point"}
}