{
  "type": "Feature",
  "properties": {
    "iso:country":"GB",
    "sg:address":"Broadgate",
    "sg:city":"Coventry",
    "sg:classifiers":[
        {
            "category":"Commercial Area",
            "type":"Public Place"
        }
    ],
    "sg:phone":"+44 24 7663 2532",
    "sg:postcode":"CV1 1LL",
    "sg:province":"West Midlands",
    "sg:tags":[
        "shop",
        "centre"
    ],
    "wof:name":"Cathedral Lanes Shopping Centre",
    "wof:placetype":"venue"
},
  "geometry": {"coordinates":[-1.5101089478,52.4076461792],"type":"Point"}
}