{
  "type": "Feature",
  "properties": {
    "addr:full":"11 Pittlesden Tenterden Kent TN30 6HJ",
    "addr:housenumber":"11",
    "addr:postcode":"tn30 6hj",
    "addr:street":"Pittlesden Tenterden",
    "iso:country":"GB",
    "sg:address":"11 Pittlesden",
    "sg:city":"Tenterden",
    "sg:classifiers":[
        {
            "category":"Health Services",
            "subcategory":"Health Practitioner",
            "type":"Services"
        },
        {
            "category":"Building & Trades",
            "subcategory":"Construction",
            "type":"Services"
        }
    ],
    "sg:postcode":"TN30 6HJ",
    "sg:province":"Kent",
    "sg:tags":[
        "homoeopathic",
        "decorator",
        "painter"
    ],
    "wof:name":"Osborne Jean",
    "wof:placetype":"venue"
},
  "geometry": {"coordinates":[0.683486,51.069092],"type":"Point"}
}