{
  "type": "Feature",
  "properties": {
    "iso:country":"GB",
    "sg:address":"41 Woodhall Street, Chapelhall",
    "sg:city":"Airdrie",
    "sg:classifiers":[
        {
            "category":"Food & Beverages",
            "subcategory":"Fruits & Vegetables",
            "type":"Retail Goods"
        }
    ],
    "sg:postcode":"ML6 8SH",
    "sg:province":"North Lanarkshire",
    "sg:tags":[
        "greengrocer"
    ],
    "wof:name":"William Glass",
    "wof:placetype":"venue"
},
  "geometry": {"coordinates":[-3.952493,55.840305],"type":"Point"}
}