{
  "type": "Feature",
  "properties": {
    "addr:full":"Cannon Street Stoke-on-trent Staffordshire ST1 4EB",
    "addr:postcode":"st1 4eb",
    "addr:street":"Cannon Street",
    "iso:country":"GB",
    "sg:address":"Cannon Street",
    "sg:city":"Stoke-on-trent",
    "sg:classifiers":[
        {
            "category":"Bars & Pubs",
            "type":"Food & Drink"
        }
    ],
    "sg:phone":"+44 1782 289760",
    "sg:postcode":"ST1 4EB",
    "sg:province":"Staffordshire",
    "sg:tags":[
        "pubs",
        "inn"
    ],
    "wof:name":"The Locker Room",
    "wof:placetype":"venue"
},
  "geometry": {"coordinates":[-2.178739,53.02177],"type":"Point"}
}