{
  "type": "Feature",
  "properties": {
    "iso:country":"GB",
    "sg:address":"20 St Peters Street",
    "sg:city":"Glasgow",
    "sg:classifiers":[
        {
            "category":"Education",
            "subcategory":"School",
            "type":"Public Place"
        }
    ],
    "sg:phone":"+44 141 332 6210",
    "sg:postcode":"G4 9PW",
    "sg:province":"Glasgow City",
    "sg:tags":[
        "local",
        "authority"
    ],
    "wof:name":"Oakgrove Primary School",
    "wof:placetype":"venue"
},
  "geometry": {"coordinates":[-4.2646079063,55.8716697693],"type":"Point"}
}