{
  "type": "Feature",
  "properties": {
    "iso:country":"GB",
    "sg:address":"101 Sidbury",
    "sg:city":"Worcester",
    "sg:classifiers":[
        {
            "category":"Government",
            "subcategory":"Post Office",
            "type":"Public Place"
        }
    ],
    "sg:phone":"+44 1905 353718",
    "sg:postcode":"WR1 2HU",
    "sg:province":"Worcestershire",
    "wof:name":"Sidbury Post Office",
    "wof:placetype":"venue"
},
  "geometry": {"coordinates":[-2.2167088985,52.1874313354],"type":"Point"}
}