{
  "type": "Feature",
  "properties": {
    "addr:full":"Brisbane Cottage, Main St Gordon Scottish Borders TD3 6JN",
    "addr:postcode":"td3 6jn",
    "addr:street":"Main St",
    "iso:country":"GB",
    "sg:address":"Brisbane Cottage, Main St",
    "sg:city":"Gordon",
    "sg:classifiers":[
        {
            "category":"Recreation",
            "type":"Entertainment"
        }
    ],
    "sg:phone":"+44 1573 410363",
    "sg:postcode":"TD3 6JN",
    "sg:province":"Scottish Borders",
    "sg:tags":[
        "corporate",
        "leisure"
    ],
    "wof:name":"Magic Bob",
    "wof:placetype":"venue"
},
  "geometry": {"coordinates":[-2.5746400356,55.694355011],"type":"Point"}
}