{
  "type": "Feature",
  "properties": {
    "iso:country":"GB",
    "sg:address":"Care Of Anvil Inn, 41 Blacksmith La",
    "sg:city":"Chesterfield",
    "sg:classifiers":[
        {
            "category":"Arts & Performance",
            "subcategory":"Music",
            "type":"Entertainment"
        }
    ],
    "sg:phone":"+44 1246 555094",
    "sg:postcode":"S44 5TT",
    "sg:province":"Derbyshire",
    "sg:tags":[
        "mobile",
        "disco"
    ],
    "wof:name":"A J'S",
    "wof:placetype":"venue"
},
  "geometry": {"coordinates":[-1.3848099709,53.2385902405],"type":"Point"}
}