{
  "type": "Feature",
  "properties": {
    "iso:country":"GB",
    "sg:address":"588 Moor Road, Bestwood Village",
    "sg:city":"Nottingham",
    "sg:classifiers":[
        {
            "category":"Autos & Motor Vehicles",
            "subcategory":"Fuel & Gas Station",
            "type":"Retail Goods"
        },
        {
            "category":"Parking",
            "subcategory":"Lot",
            "type":"Transportation"
        }
    ],
    "sg:phone":"+44 115 927 9405",
    "sg:postcode":"NG6 8TE",
    "sg:province":"Nottinghamshire",
    "sg:tags":[
        "repairing",
        "tank",
        "petrol",
        "pump",
        "cleaning",
        "maintenance"
    ],
    "wof:name":"D E Pump & Tank Services",
    "wof:placetype":"venue"
},
  "geometry": {"coordinates":[-1.1795350313,53.0261077881],"type":"Point"}
}