{
  "type": "Feature",
  "properties": {
    "iso:country":"GB",
    "sg:address":"Taswood Lakes Fish Farm& Fishery, Mill Road, Flordon",
    "sg:city":"Norwich",
    "sg:classifiers":[
        {
            "category":"Recreation",
            "subcategory":"Fishing",
            "type":"Entertainment"
        },
        {
            "category":"Train Station",
            "subcategory":"Rail",
            "type":"Transportation"
        }
    ],
    "sg:phone":"+44 1508 470919",
    "sg:postcode":"NR15 1LX",
    "sg:province":"Norfolk",
    "sg:tags":[
        "angling"
    ],
    "wof:name":"Taswood Lakes Fish Farm & Fishery",
    "wof:placetype":"venue"
},
  "geometry": {"coordinates":[1.259285,52.536518],"type":"Point"}
}