{
  "type": "Feature",
  "properties": {
    "iso:country":"GB",
    "sg:address":"1a Cedars Avenue",
    "sg:city":"Walthamstow",
    "sg:classifiers":[
        {
            "category":"Communications",
            "type":"Services"
        }
    ],
    "sg:phone":"+44 20 8520 2005",
    "sg:postcode":"E17 7QL",
    "sg:province":"Greater London",
    "sg:tags":[
        "telecommunication"
    ],
    "wof:name":"Telemaster",
    "wof:placetype":"venue"
},
  "geometry": {"coordinates":[-0.018669,51.581547],"type":"Point"}
}