{
  "type": "Feature",
  "properties": {
    "iso:country":"GB",
    "sg:address":"6th Floor, 90 St Vincent Street",
    "sg:city":"Glasgow",
    "sg:classifiers":[
        {
            "category":"Real Estate",
            "subcategory":"Surveying",
            "type":"Services"
        }
    ],
    "sg:phone":"+44 141 221 2871",
    "sg:postcode":"G2 5UQ",
    "sg:province":"Glasgow City",
    "sg:tags":[
        "surveyor",
        "valuer"
    ],
    "wof:name":"Donaldsons",
    "wof:placetype":"venue"
},
  "geometry": {"coordinates":[-4.256659,55.861481],"type":"Point"}
}