{
  "type": "Feature",
  "properties": {
    "addr:full":"2 Alice St Bradford West Yorkshire BD8 7RT",
    "addr:housenumber":"2",
    "addr:postcode":"bd8 7rt",
    "addr:street":"Alice St",
    "iso:country":"GB",
    "sg:address":"2 Alice St",
    "sg:city":"Bradford",
    "sg:classifiers":[
        {
            "category":"Manufacturing",
            "subcategory":"Furniture",
            "type":"Manufacturing & Wholesale Goods"
        }
    ],
    "sg:phone":"+44 1274 394389",
    "sg:postcode":"BD8 7RT",
    "sg:province":"West Yorkshire",
    "sg:tags":[
        "mnfr",
        "upholsterer"
    ],
    "wof:name":"S & S Upholstery",
    "wof:placetype":"venue"
},
  "geometry": {"coordinates":[-1.763023,53.801437],"type":"Point"}
}