{
  "type": "Feature",
  "properties": {
    "addr:full":"86 Old Brompton Road London Greater London SW7 3LQ",
    "addr:housenumber":"86",
    "addr:postcode":"sw7 3lq",
    "addr:street":"Old Brompton Road",
    "iso:country":"GB",
    "sg:address":"86 Old Brompton Road",
    "sg:city":"London",
    "sg:classifiers":[
        {
            "category":"Travel",
            "subcategory":"Travel Agent",
            "type":"Entertainment"
        }
    ],
    "sg:phone":"+44 20 7581 4132",
    "sg:postcode":"SW7 3LQ",
    "sg:province":"Greater London",
    "wof:name":"S T A Travel Ltd.",
    "wof:placetype":"venue"
},
  "geometry": {"coordinates":[-0.1775269955,51.4926261902],"type":"Point"}
}