{
  "type": "Feature",
  "properties": {
    "addr:full":"12 Howard Avenue Bristol City of Bristol BS5 7BB",
    "addr:housenumber":"12",
    "addr:postcode":"bs5 7bb",
    "addr:street":"Howard Avenue",
    "iso:country":"GB",
    "sg:address":"12 Howard Avenue",
    "sg:city":"Bristol",
    "sg:classifiers":[
        {
            "category":"Retail",
            "subcategory":"Repair Shop",
            "type":"Services"
        }
    ],
    "sg:postcode":"BS5 7BB",
    "sg:province":"City of Bristol",
    "sg:tags":[
        "maintenance"
    ],
    "wof:name":"Darren G Richardson",
    "wof:placetype":"venue"
},
  "geometry": {"coordinates":[-2.5448920727,51.4633522034],"type":"Point"}
}