{
  "type": "Feature",
  "properties": {
    "addr:full":"107 Station Rd, Hadfield Glossop Derbyshire SK13 1AA",
    "addr:housenumber":"107",
    "addr:postcode":"sk13 1aa",
    "addr:street":"Station Rd",
    "iso:country":"GB",
    "sg:address":"107 Station Rd, Hadfield",
    "sg:city":"Glossop",
    "sg:classifiers":[
        {
            "category":"Real Estate",
            "subcategory":"Real Estate Agent",
            "type":"Services"
        }
    ],
    "sg:postcode":"SK13 1AA",
    "sg:province":"Derbyshire",
    "wof:name":"Warrington,James,",
    "wof:placetype":"venue"
},
  "geometry": {"coordinates":[-1.9671139717,53.4623527527],"type":"Point"}
}