{
  "type": "Feature",
  "properties": {
    "addr:full":"Milburn House, Dean Street Newcastle-upon-tyne Tyne and Wear NE1 1NR",
    "addr:postcode":"ne1 1nr",
    "addr:street":"Dean Street",
    "iso:country":"GB",
    "sg:address":"Milburn House, Dean Street",
    "sg:city":"Newcastle-upon-tyne",
    "sg:classifiers":[
        {
            "category":"Professional",
            "subcategory":"Lawyer & Legal Services",
            "type":"Services"
        }
    ],
    "sg:phone":"+44 191 232 8628",
    "sg:postcode":"NE1 1NR",
    "sg:province":"Tyne and Wear",
    "sg:tags":[
        "solicitor"
    ],
    "wof:name":"L A Caisley",
    "wof:placetype":"venue"
},
  "geometry": {"coordinates":[-1.6099560261,54.9703674316],"type":"Point"}
}