{
  "type": "Feature",
  "properties": {
    "addr:full":"373 Evesham Road, Crabs Cross Redditch Warwickshire B97 5JA",
    "addr:housenumber":"373",
    "addr:postcode":"b97 5ja",
    "addr:street":"Evesham Road Crabs Cross",
    "iso:country":"GB",
    "sg:address":"373 Evesham Road, Crabs Cross",
    "sg:city":"Redditch",
    "sg:classifiers":[
        {
            "category":"Sports & Exercise",
            "subcategory":"Bowling",
            "type":"Entertainment"
        }
    ],
    "sg:phone":"+44 1527 402082",
    "sg:postcode":"B97 5JA",
    "sg:province":"Warwickshire",
    "sg:tags":[
        "photography"
    ],
    "wof:name":"A D Cellular",
    "wof:placetype":"venue"
},
  "geometry": {"coordinates":[-1.942344,52.282623],"type":"Point"}
}