{
  "type": "Feature",
  "properties": {
    "addr:full":"5a Molyneux Park Road Tunbridge Wells Kent TN4 8DG",
    "addr:housenumber":"5a",
    "addr:postcode":"tn4 8dg",
    "addr:street":"Molyneux Park Road",
    "iso:country":"GB",
    "sg:address":"5a Molyneux Park Road",
    "sg:city":"Tunbridge Wells",
    "sg:classifiers":[
        {
            "category":"Health Services",
            "subcategory":"Dentist",
            "type":"Services"
        }
    ],
    "sg:phone":"+44 1892 538078",
    "sg:postcode":"TN4 8DG",
    "sg:province":"Kent",
    "wof:name":"M Blake",
    "wof:placetype":"venue"
},
  "geometry": {"coordinates":[0.2536759973,51.1343307495],"type":"Point"}
}