{
  "type": "Feature",
  "properties": {
    "addr:full":"Unit 21 Enterprise Centre, Bryn Rd Bridgend Bridgend CF32 9BS",
    "addr:housenumber":"unit 21",
    "addr:postcode":"cf32 9bs",
    "addr:street":"Enterprise Centre Bryn Rd",
    "iso:country":"GB",
    "sg:address":"Unit 21 Enterprise Centre, Bryn Rd",
    "sg:city":"Bridgend",
    "sg:classifiers":[
        {
            "category":"Professional",
            "subcategory":"Computer Services",
            "type":"Services"
        }
    ],
    "sg:phone":"+44 1656 729395",
    "sg:postcode":"CF32 9BS",
    "sg:province":"Bridgend",
    "sg:tags":[
        "aided",
        "design"
    ],
    "wof:name":"Mastercrest Developements",
    "wof:placetype":"venue"
},
  "geometry": {"coordinates":[-3.5906600952,51.5474395752],"type":"Point"}
}