{
  "type": "Feature",
  "properties": {
    "addr:full":"96 Palmerston Park Tiverton Devon EX16 5PG",
    "addr:housenumber":"96",
    "addr:postcode":"ex16 5pg",
    "addr:street":"Palmerston Park",
    "iso:country":"GB",
    "sg:address":"96 Palmerston Park",
    "sg:city":"Tiverton",
    "sg:classifiers":[
        {
            "category":"Building & Trades",
            "subcategory":"Construction",
            "type":"Services"
        }
    ],
    "sg:phone":"+44 1884 258766",
    "sg:postcode":"EX16 5PG",
    "sg:province":"Devon",
    "sg:tags":[
        "builder"
    ],
    "wof:name":"A T G Building Services",
    "wof:placetype":"venue"
},
  "geometry": {"coordinates":[-3.4982440472,50.894657135],"type":"Point"}
}