{
  "type": "Feature",
  "properties": {
    "iso:country":"GB",
    "sg:address":"95a Swan Street, Sileby",
    "sg:city":"Loughborough",
    "sg:classifiers":[
        {
            "category":"Real Estate",
            "subcategory":"Developer",
            "type":"Services"
        }
    ],
    "sg:phone":"+44 1509 816388",
    "sg:postcode":"LE12 7NN",
    "sg:province":"Leicestershire",
    "sg:tags":[
        "property"
    ],
    "wof:name":"Glencoe Homes Ltd.",
    "wof:placetype":"venue"
},
  "geometry": {"coordinates":[-1.10482,52.731743],"type":"Point"}
}