{
  "type": "Feature",
  "properties": {
    "iso:country":"GB",
    "sg:address":"15b North Seaton Road",
    "sg:city":"Ashington",
    "sg:classifiers":[
        {
            "category":"Personal",
            "subcategory":"Tattoo Parlor",
            "type":"Services"
        }
    ],
    "sg:phone":"+44 1670 856683",
    "sg:postcode":"NE63 0SN",
    "sg:province":"Northumberland",
    "sg:tags":[
        "tattooing",
        "piercing"
    ],
    "wof:name":"Dragons Lair",
    "wof:placetype":"venue"
},
  "geometry": {"coordinates":[-1.568648,55.182411],"type":"Point"}
}