{
  "type": "Feature",
  "properties": {
    "addr:full":"Siop Y Bont Cemaes Bay Isle of Anglesey LL67 0NW",
    "addr:postcode":"ll67 0nw",
    "addr:street":"Cemaes Bay",
    "iso:country":"GB",
    "sg:address":"Siop Y Bont",
    "sg:city":"Cemaes Bay",
    "sg:classifiers":[
        {
            "category":"Shopping",
            "subcategory":"Department Store",
            "type":"Retail Goods"
        },
        {
            "category":"Food & Beverages",
            "subcategory":"Groceries & Convenience Stores",
            "type":"Retail Goods"
        }
    ],
    "sg:phone":"+44 1407 711211",
    "sg:postcode":"LL67 0NW",
    "sg:province":"Isle of Anglesey",
    "wof:name":"Parry'S Of Cemaes Bay",
    "wof:placetype":"venue"
},
  "geometry": {"coordinates":[-4.4518017769,53.4122467041],"type":"Point"}
}