{
  "type": "Feature",
  "properties": {
    "iso:country":"GB",
    "sg:address":"2 The Beeches, Woodfield Park",
    "sg:city":"Amersham",
    "sg:classifiers":[
        {
            "category":"Building & Trades",
            "subcategory":"Construction",
            "type":"Services"
        }
    ],
    "sg:phone":"+44 1494 726592",
    "sg:postcode":"HP6 5QJ",
    "sg:province":"Buckinghamshire",
    "sg:tags":[
        "builder"
    ],
    "wof:name":"Avenue Builders",
    "wof:placetype":"venue"
},
  "geometry": {"coordinates":[-0.62038,51.683235],"type":"Point"}
}