{
  "type": "Feature",
  "properties": {
    "iso:country":"GB",
    "sg:address":"213 Leach Lane, Sutton Leach",
    "sg:city":"St Helens",
    "sg:classifiers":[
        {
            "category":"Professional",
            "type":"Services"
        }
    ],
    "sg:phone":"+44 1744 818444",
    "sg:postcode":"WA9 4PH",
    "sg:province":"Cheshire",
    "sg:tags":[
        "reflexologists"
    ],
    "wof:name":"Lynne Bond Reflexologist",
    "wof:placetype":"venue"
},
  "geometry": {"coordinates":[-2.7118070126,53.4263000488],"type":"Point"}
}