{
  "type": "Feature",
  "properties": {
    "addr:full":"100 Vale Road Windsor Berkshire SL4 5JL",
    "addr:housenumber":"100",
    "addr:postcode":"sl4 5jl",
    "addr:street":"Vale Road",
    "iso:country":"GB",
    "sg:address":"100 Vale Road",
    "sg:city":"Windsor",
    "sg:classifiers":[
        {
            "category":"Professional",
            "type":"Services"
        }
    ],
    "sg:phone":"+44 1753 829449",
    "sg:postcode":"SL4 5JL",
    "sg:province":"Berkshire",
    "sg:tags":[
        "control",
        "system"
    ],
    "wof:name":"Servitherm",
    "wof:placetype":"venue"
},
  "geometry": {"coordinates":[-0.6348749995,51.482093811],"type":"Point"}
}