{
  "type": "Feature",
  "properties": {
    "iso:country":"GB",
    "sg:address":"28 Greenock Road",
    "sg:city":"Paisley",
    "sg:classifiers":[
        {
            "category":"Arena",
            "subcategory":"Sports Club",
            "type":"Entertainment"
        }
    ],
    "sg:phone":"+44 141 889 6067",
    "sg:postcode":"PA3 2LA",
    "sg:province":"Renfrewshire",
    "wof:name":"Caledonia Bowling Club",
    "wof:placetype":"venue"
},
  "geometry": {"coordinates":[-4.4321489334,55.8531494141],"type":"Point"}
}