{
  "type": "Feature",
  "properties": {
    "addr:full":"Helliers Road Chard Devon TA20 1LL",
    "addr:postcode":"ta20 1ll",
    "addr:street":"Helliers Road",
    "iso:country":"GB",
    "sg:address":"Helliers Road",
    "sg:city":"Chard",
    "sg:classifiers":[
        {
            "category":"Home & Garden",
            "subcategory":"Home Furnishings",
            "type":"Retail Goods"
        }
    ],
    "sg:phone":"+44 1460 67804",
    "sg:postcode":"TA20 1LL",
    "sg:province":"Devon",
    "sg:tags":[
        "blind",
        "curtain",
        "fitting"
    ],
    "wof:name":"Somer Blinds",
    "wof:placetype":"venue"
},
  "geometry": {"coordinates":[-2.9702990055,50.8752403259],"type":"Point"}
}