{
  "type": "Feature",
  "properties": {
    "addr:full":"The Old Bakery, Main Street, Tingewick Buckingham Buckinghamshire MK18 4NN",
    "addr:postcode":"mk18 4nn",
    "addr:street":"Main Street",
    "iso:country":"GB",
    "sg:address":"The Old Bakery, Main Street, Tingewick",
    "sg:city":"Buckingham",
    "sg:classifiers":[
        {
            "category":"Professional",
            "subcategory":"Management & Consulting",
            "type":"Services"
        }
    ],
    "sg:phone":"+44 1280 848609",
    "sg:postcode":"MK18 4NN",
    "sg:province":"Buckinghamshire",
    "sg:tags":[
        "consultant",
        "business"
    ],
    "wof:name":"County Management Consultants Ltd.",
    "wof:placetype":"venue"
},
  "geometry": {"coordinates":[-1.0444689989,51.9903755188],"type":"Point"}
}