{
  "type": "Feature",
  "properties": {
    "iso:country":"GB",
    "sg:address":"38 Mason Road",
    "sg:city":"Norwich",
    "sg:classifiers":[
        {
            "category":"Manufacturing",
            "subcategory":"Tools & Machinery",
            "type":"Manufacturing & Wholesale Goods"
        }
    ],
    "sg:phone":"+44 1603 404964",
    "sg:postcode":"NR6 6RF",
    "sg:province":"Norfolk",
    "sg:tags":[
        "manufacture",
        "powertools",
        "power",
        "supply"
    ],
    "wof:name":"C A N Fixings Ltd",
    "wof:placetype":"venue"
},
  "geometry": {"coordinates":[1.2816699743,52.6547584534],"type":"Point"}
}