{
  "type": "Feature",
  "properties": {
    "addr:full":"29 Lansdowne Rd Studley Warwickshire B80 7RB",
    "addr:housenumber":"29",
    "addr:postcode":"b80 7rb",
    "addr:street":"Lansdowne Rd",
    "iso:country":"GB",
    "sg:address":"29 Lansdowne Rd",
    "sg:city":"Studley",
    "sg:classifiers":[
        {
            "category":"Building & Trades",
            "subcategory":"Construction",
            "type":"Services"
        }
    ],
    "sg:postcode":"B80 7RB",
    "sg:province":"Warwickshire",
    "sg:tags":[
        "decorator",
        "painter"
    ],
    "wof:name":"Newell,Don,",
    "wof:placetype":"venue"
},
  "geometry": {"coordinates":[-1.902721,52.268906],"type":"Point"}
}