{
  "type": "Feature",
  "properties": {
    "iso:country":"GB",
    "sg:address":"147 Ladypool Road",
    "sg:city":"Birmingham",
    "sg:classifiers":[
        {
            "category":"Food & Beverages",
            "subcategory":"Meat & Fish",
            "type":"Retail Goods"
        },
        {
            "category":"Food & Beverages",
            "subcategory":"Groceries & Convenience Stores",
            "type":"Retail Goods"
        }
    ],
    "sg:phone":"+44 121 440 4562",
    "sg:postcode":"B12 8LH",
    "sg:province":"West Midlands",
    "sg:tags":[
        "shop",
        "chip"
    ],
    "wof:name":"ABDUL & K MALIK",
    "wof:placetype":"venue"
},
  "geometry": {"coordinates":[-1.876882,52.457958],"type":"Point"}
}