{
  "type": "Feature",
  "properties": {
    "iso:country":"GB",
    "sg:address":"Westbourne House, Billingborough Road, Horbling",
    "sg:city":"Sleaford",
    "sg:classifiers":[
        {
            "category":"Communications",
            "subcategory":"Film & Video Production",
            "type":"Services"
        }
    ],
    "sg:phone":"+44 1529 240855",
    "sg:postcode":"NG34 0PA",
    "sg:province":"Lincolnshire",
    "sg:tags":[
        "illustrator",
        "artist"
    ],
    "wof:name":"John Bangay",
    "wof:placetype":"venue"
},
  "geometry": {"coordinates":[-0.33961,52.899101],"type":"Point"}
}