{
  "type": "Feature",
  "properties": {
    "iso:country":"GB",
    "sg:address":"52 Millwood End, Long Hanborough",
    "sg:city":"Witney",
    "sg:classifiers":[
        {
            "category":"Real Estate",
            "subcategory":"Surveying",
            "type":"Services"
        },
        {
            "category":"Real Estate",
            "subcategory":"Architect",
            "type":"Services"
        }
    ],
    "sg:phone":"+44 1993 883250",
    "sg:postcode":"OX29 8BY",
    "sg:province":"Oxfordshire",
    "sg:tags":[
        "building",
        "surveyor"
    ],
    "wof:name":"Surtec",
    "wof:placetype":"venue"
},
  "geometry": {"coordinates":[-1.404306,51.828144],"type":"Point"}
}