{
  "type": "Feature",
  "properties": {
    "addr:full":"14-15 Annes Walk, Anglia Square Norwich Norfolk NR3 1EB",
    "addr:housenumber":"14-15",
    "addr:postcode":"nr3 1eb",
    "addr:street":"Annes Walk Anglia Square Norwich Norfolk",
    "iso:country":"GB",
    "sg:address":"14-15 Annes Walk, Anglia Square",
    "sg:city":"Norwich",
    "sg:classifiers":[
        {
            "category":"Organizations",
            "subcategory":"Non-profit Organization",
            "type":"Services"
        }
    ],
    "sg:phone":"+44 1603 610966",
    "sg:postcode":"NR3 1EB",
    "sg:province":"Norfolk",
    "sg:tags":[
        "organisation",
        "voluntary",
        "charity"
    ],
    "wof:name":"The Childrens Society",
    "wof:placetype":"venue"
},
  "geometry": {"coordinates":[1.296110034,52.6363182068],"type":"Point"}
}