{
  "type": "Feature",
  "properties": {
    "addr:full":"Unit 3 Albert St Works, Albert Street Manchester Greater Manchester M43 7BA",
    "addr:housenumber":"unit 3",
    "addr:postcode":"m43 7ba",
    "addr:street":"Albert St;Albert Street",
    "iso:country":"GB",
    "sg:address":"Unit 3 Albert St Works, Albert Street",
    "sg:city":"Manchester",
    "sg:classifiers":[
        {
            "category":"Retail",
            "subcategory":"Auto Repair",
            "type":"Services"
        }
    ],
    "sg:postcode":"M43 7BA",
    "sg:province":"Greater Manchester",
    "sg:tags":[
        "modification",
        "garage"
    ],
    "wof:name":"G T S Motors",
    "wof:placetype":"venue"
},
  "geometry": {"coordinates":[-2.1426439285,53.4818305969],"type":"Point"}
}