{
  "type": "Feature",
  "properties": {
    "addr:full":"1 Broad Meadows, Leeds Road, Outwood Wakefield West Yorkshire WF1 3TR",
    "addr:housenumber":"1",
    "addr:postcode":"wf1 3tr",
    "addr:street":"Broad Meadows Leeds Road;West",
    "iso:country":"GB",
    "sg:address":"1 Broad Meadows, Leeds Road, Outwood",
    "sg:city":"Wakefield",
    "sg:classifiers":[
        {
            "category":"Food & Beverages",
            "subcategory":"Supermarket",
            "type":"Retail Goods"
        }
    ],
    "sg:phone":"+44 1924 870187",
    "sg:postcode":"WF1 3TR",
    "sg:province":"West Yorkshire",
    "wof:name":"G T Smith Ltd.",
    "wof:placetype":"venue"
},
  "geometry": {"coordinates":[-1.4941300154,53.7140388489],"type":"Point"}
}