{
  "type": "Feature",
  "properties": {
    "iso:country":"GB",
    "sg:address":"4 Dunkirk Clo",
    "sg:city":"Gravesend",
    "sg:classifiers":[
        {
            "category":"Bakery",
            "type":"Food & Drink"
        }
    ],
    "sg:phone":"+44 1322 350488",
    "sg:postcode":"DA12 5ND",
    "sg:province":"Kent",
    "sg:tags":[
        "cake",
        "maker"
    ],
    "wof:name":"Audrey Towner",
    "wof:placetype":"venue"
},
  "geometry": {"coordinates":[0.376926,51.418476],"type":"Point"}
}