{
  "type": "Feature",
  "properties": {
    "addr:full":"The Grove West Wickham Kent BR4 9JT",
    "addr:postcode":"br4 9jt",
    "addr:street":"Grove",
    "iso:country":"GB",
    "sg:address":"The Grove",
    "sg:city":"West Wickham",
    "sg:classifiers":[
        {
            "category":"Real Estate",
            "subcategory":"Architect",
            "type":"Services"
        }
    ],
    "sg:postcode":"BR4 9JT",
    "sg:province":"Kent",
    "wof:name":"Escher Engineering Ltd.",
    "wof:placetype":"venue"
},
  "geometry": {"coordinates":[-0.0180699993,51.3717193604],"type":"Point"}
}