{
  "type": "Feature",
  "properties": {
    "addr:full":"Care Of Cosalt, 210 Dock St Fleetwood Lancashire FY7 6PB",
    "addr:housenumber":"210",
    "addr:postcode":"fy7 6pb",
    "addr:street":"Dock St",
    "iso:country":"GB",
    "sg:address":"Care Of Cosalt, 210 Dock St",
    "sg:city":"Fleetwood",
    "sg:classifiers":[
        {
            "category":"Manufacturing",
            "subcategory":"Glass & Minerals",
            "type":"Manufacturing & Wholesale Goods"
        }
    ],
    "sg:phone":"+44 1253 873503",
    "sg:postcode":"FY7 6PB",
    "sg:province":"Lancashire",
    "sg:tags":[
        "stained"
    ],
    "wof:name":"Abbott & Co Lancaster",
    "wof:placetype":"venue"
},
  "geometry": {"coordinates":[-3.014669,53.92128],"type":"Point"}
}