{
  "type": "Feature",
  "properties": {
    "iso:country":"GB",
    "sg:address":"21-22 The Square",
    "sg:city":"Choppington",
    "sg:classifiers":[
        {
            "category":"Food & Beverages",
            "subcategory":"Groceries & Convenience Stores",
            "type":"Retail Goods"
        }
    ],
    "sg:phone":"+44 1670 822074",
    "sg:postcode":"NE62 5DA",
    "sg:province":"Northumberland",
    "wof:name":"Choppington Wine Centre",
    "wof:placetype":"venue"
},
  "geometry": {"coordinates":[-1.601033,55.159409],"type":"Point"}
}