{
  "type": "Feature",
  "properties": {
    "addr:full":"170 Well Lane Walsall Staffordshire WS3 1JU",
    "addr:housenumber":"170",
    "addr:postcode":"ws3 1ju",
    "addr:street":"Well Lane",
    "iso:country":"GB",
    "sg:address":"170 Well Lane",
    "sg:city":"Walsall",
    "sg:classifiers":[
        {
            "category":"Shopping",
            "subcategory":"News",
            "type":"Retail Goods"
        }
    ],
    "sg:postcode":"WS3 1JU",
    "sg:province":"Staffordshire",
    "sg:tags":[
        "newsagent"
    ],
    "wof:name":"Stars News Shops",
    "wof:placetype":"venue"
},
  "geometry": {"coordinates":[-1.981664,52.615627],"type":"Point"}
}