{
  "type": "Feature",
  "properties": {
    "iso:country":"GB",
    "sg:address":"West Park Centre, 7 Raglan St",
    "sg:city":"Harrogate",
    "sg:classifiers":[
        {
            "category":"Professional",
            "subcategory":"Lawyer & Legal Services",
            "type":"Services"
        }
    ],
    "sg:phone":"+44 1423 536425",
    "sg:postcode":"HG1 1LE",
    "sg:province":"North Yorkshire",
    "sg:tags":[
        "advice",
        "counselling"
    ],
    "wof:name":"Survivors",
    "wof:placetype":"venue"
},
  "geometry": {"coordinates":[-1.544524,53.99469],"type":"Point"}
}