{
  "type": "Feature",
  "properties": {
    "addr:full":"59 North Eyot Gardens, St Peters Square London Greater London W6 9NL",
    "addr:housenumber":"59",
    "addr:postcode":"w6 9nl",
    "addr:street":"North Eyot Gardens St;Square",
    "iso:country":"GB",
    "sg:address":"59 North Eyot Gardens, St Peters Square",
    "sg:city":"London",
    "sg:classifiers":[
        {
            "category":"Communications",
            "subcategory":"Film & Video Production",
            "type":"Services"
        }
    ],
    "sg:phone":"+44 20 8748 9641",
    "sg:postcode":"W6 9NL",
    "sg:province":"Greater London",
    "sg:tags":[
        "tv",
        "studio"
    ],
    "wof:name":"F J Associates",
    "wof:placetype":"venue"
},
  "geometry": {"coordinates":[-0.2444899976,51.4907608032],"type":"Point"}
}