{
  "type": "Feature",
  "properties": {
    "iso:country":"GB",
    "sg:address":"Gainsborough House, Sheering Lower Road",
    "sg:city":"Sawbridgeworth",
    "sg:classifiers":[
        {
            "category":"Professional",
            "subcategory":"Accounting & Tax Preparation",
            "type":"Services"
        },
        {
            "category":"Professional",
            "subcategory":"Management & Consulting",
            "type":"Services"
        }
    ],
    "sg:phone":"+44 1279 725050",
    "sg:postcode":"CM21 9RG",
    "sg:province":"Essex",
    "sg:tags":[
        "consultant",
        "accountant",
        "business",
        "activity"
    ],
    "wof:name":"Hills Jarrett Llp",
    "wof:placetype":"venue"
},
  "geometry": {"coordinates":[0.1578170061,51.8012237549],"type":"Point"}
}