{
  "type": "Feature",
  "properties": {
    "addr:full":"44 Manor Park Way, Lepton Huddersfield South Yorkshire HD8 0AJ",
    "addr:housenumber":"44",
    "addr:postcode":"hd8 0aj",
    "addr:street":"Manor Park Way",
    "iso:country":"GB",
    "sg:address":"44 Manor Park Way, Lepton",
    "sg:city":"Huddersfield",
    "sg:classifiers":[
        {
            "category":"Professional",
            "subcategory":"Art Services",
            "type":"Services"
        },
        {
            "category":"Building & Trades",
            "subcategory":"Construction",
            "type":"Services"
        }
    ],
    "sg:phone":"+44 1484 603944",
    "sg:postcode":"HD8 0AJ",
    "sg:province":"South Yorkshire",
    "sg:tags":[
        "decorator",
        "painter"
    ],
    "wof:name":"Gibson & Wilson",
    "wof:placetype":"venue"
},
  "geometry": {"coordinates":[-1.7169280052,53.6300582886],"type":"Point"}
}