{
  "type": "Feature",
  "properties": {
    "iso:country":"GB",
    "sg:address":"The Hall, 100 Old Station Road",
    "sg:city":"Bromsgrove",
    "sg:classifiers":[
        {
            "category":"Health Services",
            "subcategory":"Nursing And Care Facility",
            "type":"Services"
        }
    ],
    "sg:postcode":"B60 2AS",
    "sg:province":"Worcestershire",
    "sg:tags":[
        "home"
    ],
    "wof:name":"Worcestershire Care Group Ltd.",
    "wof:placetype":"venue"
},
  "geometry": {"coordinates":[-2.05463,52.32761],"type":"Point"}
}