{
  "type": "Feature",
  "properties": {
    "iso:country":"GB",
    "sg:address":"143 Great Portland Street",
    "sg:city":"London",
    "sg:classifiers":[
        {
            "category":"Utilities",
            "subcategory":"Natural Gas",
            "type":"Services"
        }
    ],
    "sg:postcode":"W1W 6QN",
    "sg:province":"Greater London",
    "sg:tags":[
        "supplier"
    ],
    "wof:name":"Hartwork Pure Products Ltd",
    "wof:placetype":"venue"
},
  "geometry": {"coordinates":[-0.1432639956,51.520866394],"type":"Point"}
}