{
  "type": "Feature",
  "properties": {
    "addr:full":"184 Stourbridge Rd Halesowen West Midlands B63 3UJ",
    "addr:housenumber":"184",
    "addr:postcode":"b63 3uj",
    "addr:street":"Stourbridge Rd",
    "iso:country":"GB",
    "sg:address":"184 Stourbridge Rd",
    "sg:city":"Halesowen",
    "sg:classifiers":[
        {
            "category":"Shopping",
            "subcategory":"Florist",
            "type":"Retail Goods"
        }
    ],
    "sg:postcode":"B63 3UJ",
    "sg:province":"West Midlands",
    "wof:name":"Moore,Catherine,",
    "wof:placetype":"venue"
},
  "geometry": {"coordinates":[-2.0625269413,52.4534683228],"type":"Point"}
}