{
  "type": "Feature",
  "properties": {
    "addr:full":"High Street, Hawkesbury Upton Badminton Gloucestershire GL9 1AU",
    "addr:postcode":"gl9 1au",
    "addr:street":"High Street",
    "iso:country":"GB",
    "sg:address":"High Street, Hawkesbury Upton",
    "sg:city":"Badminton",
    "sg:classifiers":[
        {
            "category":"Personal",
            "subcategory":"Beauty Salon",
            "type":"Services"
        },
        {
            "category":"Personal",
            "subcategory":"Barber",
            "type":"Services"
        }
    ],
    "sg:phone":"+44 1454 238823",
    "sg:postcode":"GL9 1AU",
    "sg:province":"Gloucestershire",
    "sg:tags":[
        "unisex",
        "hairdresser"
    ],
    "wof:name":"Headstart Studio The",
    "wof:placetype":"venue"
},
  "geometry": {"coordinates":[-2.286138,51.542645],"type":"Point"}
}