{
  "type": "Feature",
  "properties": {
    "addr:full":"Skinners Ash Farm, Fenny Bridges Honiton Devon EX14 3BH",
    "addr:postcode":"ex14 3bh",
    "addr:street":"Ash",
    "iso:country":"GB",
    "sg:address":"Skinners Ash Farm, Fenny Bridges",
    "sg:city":"Honiton",
    "sg:classifiers":[
        {
            "category":"Farming",
            "subcategory":"Livestock Farm",
            "type":"Manufacturing & Wholesale Goods"
        }
    ],
    "sg:postcode":"EX14 3BH",
    "sg:province":"Devon",
    "sg:tags":[
        "others"
    ],
    "wof:name":"B J GODFREY & SON",
    "wof:placetype":"venue"
},
  "geometry": {"coordinates":[-3.266917,50.779453],"type":"Point"}
}