{
  "type": "Feature",
  "properties": {
    "addr:full":"15 Maylands Road Havant Hampshire PO9 3NP",
    "addr:housenumber":"15",
    "addr:postcode":"po9 3np",
    "addr:street":"Maylands Road",
    "iso:country":"GB",
    "sg:address":"15 Maylands Road",
    "sg:city":"Havant",
    "sg:classifiers":[
        {
            "category":"Building & Trades",
            "subcategory":"Plumbing",
            "type":"Services"
        }
    ],
    "sg:postcode":"PO9 3NP",
    "sg:province":"Hampshire",
    "sg:tags":[
        "heating"
    ],
    "wof:name":"Abbey Plumbing",
    "wof:placetype":"venue"
},
  "geometry": {"coordinates":[-1.0087419748,50.8550949097],"type":"Point"}
}