{
  "type": "Feature",
  "properties": {
    "addr:full":"5 Prospect Close London Greater London SE26 6LB",
    "addr:housenumber":"5",
    "addr:postcode":"se26 6lb",
    "addr:street":"Prospect Close",
    "iso:country":"GB",
    "sg:address":"5 Prospect Close",
    "sg:city":"London",
    "sg:classifiers":[
        {
            "category":"Shopping",
            "subcategory":"Computers & Home Electronics",
            "type":"Retail Goods"
        }
    ],
    "sg:phone":"+44 20 8301 2043",
    "sg:postcode":"SE26 6LB",
    "sg:province":"Greater London",
    "sg:tags":[
        "aerial",
        "television",
        "radio"
    ],
    "wof:name":"S C S Aerials",
    "wof:placetype":"venue"
},
  "geometry": {"coordinates":[-0.0638590008,51.4302558899],"type":"Point"}
}