{
  "type": "Feature",
  "properties": {
    "iso:country":"GB",
    "sg:address":"67 Alexandra Rd",
    "sg:city":"Sheffield",
    "sg:classifiers":[
        {
            "category":"Utilities",
            "subcategory":"Recycling",
            "type":"Services"
        }
    ],
    "sg:phone":"+44 114 258 0483",
    "sg:postcode":"S2 3EE",
    "sg:province":"South Yorkshire",
    "sg:tags":[
        "centre"
    ],
    "wof:name":"The Community Composting Network",
    "wof:placetype":"venue"
},
  "geometry": {"coordinates":[-1.466859,53.362751],"type":"Point"}
}