{
  "type": "Feature",
  "properties": {
    "addr:full":"9-10 Havercroft Buildings, North Street Worthing West Sussex BN11 1DY",
    "addr:housenumber":"9-10",
    "addr:postcode":"bn11 1dy",
    "addr:street":"Havercroft Buildings North Street",
    "iso:country":"GB",
    "sg:address":"9-10 Havercroft Buildings, North Street",
    "sg:city":"Worthing",
    "sg:classifiers":[
        {
            "category":"Transit Center",
            "subcategory":"Freight",
            "type":"Transportation"
        }
    ],
    "sg:postcode":"BN11 1DY",
    "sg:province":"West Sussex",
    "sg:tags":[
        "shop",
        "craft",
        "centre"
    ],
    "wof:name":"The Quilt Loft",
    "wof:placetype":"venue"
},
  "geometry": {"coordinates":[-0.3754239976,50.8136253357],"type":"Point"}
}