{
  "type": "Feature",
  "properties": {
    "addr:full":"Garrow House, Kensal Rd Ladbroke Grove Greater London W10 5BN",
    "addr:postcode":"w10 5bn",
    "addr:street":"Kensal Rd",
    "iso:country":"GB",
    "sg:address":"Garrow House, Kensal Rd",
    "sg:city":"Ladbroke Grove",
    "sg:classifiers":[
        {
            "category":"Organizations",
            "subcategory":"Non-profit Organization",
            "type":"Services"
        }
    ],
    "sg:phone":"+44 20 8960 9735",
    "sg:postcode":"W10 5BN",
    "sg:province":"Greater London",
    "sg:tags":[
        "organisation",
        "voluntary",
        "charity"
    ],
    "wof:name":"The Amber Trust",
    "wof:placetype":"venue"
},
  "geometry": {"coordinates":[-0.213459,51.5232849121],"type":"Point"}
}