{
  "type": "Feature",
  "properties": {
    "addr:full":"37 The Hays Birmingham West Midlands B26 2DL",
    "addr:housenumber":"37",
    "addr:postcode":"b26 2dl",
    "addr:street":"The Hays",
    "iso:country":"GB",
    "sg:address":"37 The Hays",
    "sg:city":"Birmingham",
    "sg:classifiers":[
        {
            "category":"Shopping",
            "subcategory":"Pharmacy",
            "type":"Retail Goods"
        }
    ],
    "sg:phone":"+44 121 785 2915",
    "sg:postcode":"B26 2DL",
    "sg:province":"West Midlands",
    "sg:tags":[
        "medicine",
        "therapy"
    ],
    "wof:name":"Moira Cane-brooks",
    "wof:placetype":"venue"
},
  "geometry": {"coordinates":[-1.7900700569,52.4735603333],"type":"Point"}
}