{
  "type": "Feature",
  "properties": {
    "addr:full":"25 High Street Banstead Surrey SM7 2NE",
    "addr:housenumber":"25",
    "addr:postcode":"sm7 2ne",
    "addr:street":"High Street",
    "iso:country":"GB",
    "sg:address":"25 High Street",
    "sg:city":"Banstead",
    "sg:classifiers":[
        {
            "category":"Real Estate",
            "subcategory":"Real Estate Agent",
            "type":"Services"
        }
    ],
    "sg:phone":"+44 1737 371700",
    "sg:postcode":"SM7 2NE",
    "sg:province":"Surrey",
    "wof:name":"Lancasters Estate Agents",
    "wof:placetype":"venue"
},
  "geometry": {"coordinates":[-0.203404,51.322327],"type":"Point"}
}