{
  "type": "Feature",
  "properties": {
    "addr:full":"13 Suez Street Warrington Cheshire WA1 1EF",
    "addr:housenumber":"13",
    "addr:postcode":"wa1 1ef",
    "addr:street":"Suez Street",
    "iso:country":"GB",
    "sg:address":"13 Suez Street",
    "sg:city":"Warrington",
    "sg:classifiers":[
        {
            "category":"Real Estate",
            "subcategory":"Surveying",
            "type":"Services"
        }
    ],
    "sg:phone":"+44 1925 234804",
    "sg:postcode":"WA1 1EF",
    "sg:province":"Cheshire",
    "sg:tags":[
        "surveyor",
        "land"
    ],
    "wof:name":"Countrywide Surveyors",
    "wof:placetype":"venue"
},
  "geometry": {"coordinates":[-2.595601,53.387737],"type":"Point"}
}