{
  "type": "Feature",
  "properties": {
    "addr:full":"51 Park Avenue Wrexham Wrexham LL12 7AW",
    "addr:housenumber":"51",
    "addr:postcode":"ll12 7aw",
    "addr:street":"Park Avenue",
    "iso:country":"GB",
    "sg:address":"51 Park Avenue",
    "sg:city":"Wrexham",
    "sg:classifiers":[
        {
            "category":"Building & Trades",
            "subcategory":"Construction",
            "type":"Services"
        }
    ],
    "sg:phone":"+44 1978 354365",
    "sg:postcode":"LL12 7AW",
    "sg:province":"Wrexham",
    "sg:tags":[
        "roofing"
    ],
    "wof:name":"Pritchard Roofing",
    "wof:placetype":"venue"
},
  "geometry": {"coordinates":[-2.984373,53.053818],"type":"Point"}
}