{
  "type": "Feature",
  "properties": {
    "addr:full":"8 Natalie Close Feltham Greater London TW14 8PJ",
    "addr:housenumber":"8",
    "addr:postcode":"tw14 8pj",
    "addr:street":"Natalie Close",
    "iso:country":"GB",
    "sg:address":"8 Natalie Close",
    "sg:city":"Feltham",
    "sg:classifiers":[
        {
            "category":"Travel",
            "subcategory":"Travel Agent",
            "type":"Entertainment"
        }
    ],
    "sg:phone":"+44 20 8890 6444",
    "sg:postcode":"TW14 8PJ",
    "sg:province":"Greater London",
    "wof:name":"Holiday Direct",
    "wof:placetype":"venue"
},
  "geometry": {"coordinates":[-0.4386030138,51.4507331848],"type":"Point"}
}