{
  "type": "Feature",
  "properties": {
    "iso:country":"GB",
    "sg:address":"7 Lordship La",
    "sg:city":"East Dulwich",
    "sg:classifiers":[
        {
            "category":"Travel",
            "subcategory":"Travel Agent",
            "type":"Entertainment"
        }
    ],
    "sg:phone":"+44 20 8693 1100",
    "sg:postcode":"SE22 8EW",
    "sg:province":"Greater London",
    "wof:name":"Meritline Travel",
    "wof:placetype":"venue"
},
  "geometry": {"coordinates":[-0.075067,51.460224],"type":"Point"}
}