{
  "type": "Feature",
  "properties": {
    "addr:full":"21 Grosvenor Rd Wrexham Wrexham LL11 1BT",
    "addr:housenumber":"21",
    "addr:postcode":"ll11 1bt",
    "addr:street":"Grosvenor Rd",
    "iso:country":"GB",
    "sg:address":"21 Grosvenor Rd",
    "sg:city":"Wrexham",
    "sg:classifiers":[
        {
            "category":"Government",
            "subcategory":"Office",
            "type":"Public Place"
        }
    ],
    "sg:phone":"+44 1978 262729",
    "sg:postcode":"LL11 1BT",
    "sg:province":"Wrexham",
    "sg:tags":[
        "local"
    ],
    "wof:name":"Community Mental Health Team",
    "wof:placetype":"venue"
},
  "geometry": {"coordinates":[-2.997174,53.049431],"type":"Point"}
}