{
  "type": "Feature",
  "properties": {
    "iso:country":"GB",
    "sg:address":"The Girnel, Harbour Street",
    "sg:city":"Kirkwall",
    "sg:classifiers":[
        {
            "category":"Arena",
            "subcategory":"Sports Club",
            "type":"Entertainment"
        }
    ],
    "sg:phone":"+44 1856 872331",
    "sg:postcode":"KW15 1LE",
    "sg:province":"Orkney Islands",
    "wof:name":"Orkney Sailing Club",
    "wof:placetype":"venue"
},
  "geometry": {"coordinates":[-2.9604189396,58.9817314148],"type":"Point"}
}