{
  "type": "Feature",
  "properties": {
    "addr:full":"291 Brunswick Park Rd Friern Barnet Greater London N11 1JJ",
    "addr:housenumber":"291",
    "addr:postcode":"n11 1jj",
    "addr:street":"Brunswick Park Rd",
    "iso:country":"GB",
    "sg:address":"291 Brunswick Park Rd",
    "sg:city":"Friern Barnet",
    "sg:classifiers":[
        {
            "category":"Home & Garden",
            "subcategory":"Home Furnishings",
            "type":"Retail Goods"
        }
    ],
    "sg:phone":"+44 20 8361 9421",
    "sg:postcode":"N11 1JJ",
    "sg:province":"Greater London",
    "sg:tags":[
        "blind",
        "manufacture",
        "fitting",
        "curtain"
    ],
    "wof:name":"Just Tracks",
    "wof:placetype":"venue"
},
  "geometry": {"coordinates":[-0.1440490037,51.6182403564],"type":"Point"}
}