{
  "type": "Feature",
  "properties": {
    "addr:full":"127 City Road, Old Street London Greater London E2 0AA",
    "addr:housenumber":"127",
    "addr:postcode":"e2 0aa",
    "addr:street":"City Road Old Street",
    "iso:country":"GB",
    "sg:address":"127 City Road, Old Street",
    "sg:city":"London",
    "sg:classifiers":[
        {
            "category":"Health Services",
            "subcategory":"Health Practitioner",
            "type":"Services"
        }
    ],
    "sg:phone":"+44 20 7490 3311",
    "sg:postcode":"E2 0AA",
    "sg:province":"Greater London",
    "sg:tags":[
        "psychotherapist"
    ],
    "wof:name":"Avenue Psychotherapy Services Ltd.",
    "wof:placetype":"venue"
},
  "geometry": {"coordinates":[-0.0877000019,51.5255813599],"type":"Point"}
}