{
  "type": "Feature",
  "properties": {
    "iso:country":"GB",
    "sg:address":"52 Church Side",
    "sg:city":"Chesterfield",
    "sg:classifiers":[
        {
            "category":"Building & Trades",
            "subcategory":"Construction",
            "type":"Services"
        }
    ],
    "sg:phone":"+44 1246 209735",
    "sg:postcode":"S41 0LB",
    "sg:province":"Derbyshire",
    "sg:tags":[
        "builder"
    ],
    "wof:name":"Littlewood Construction",
    "wof:placetype":"venue"
},
  "geometry": {"coordinates":[-1.410044,53.215965],"type":"Point"}
}