{
  "type": "Feature",
  "properties": {
    "addr:full":"Green Lane Dronfield Derbyshire S18 2FZ",
    "addr:postcode":"s18 2fz",
    "addr:street":"Green Lane",
    "iso:country":"GB",
    "sg:address":"Green Lane",
    "sg:city":"Dronfield",
    "sg:classifiers":[
        {
            "category":"Education",
            "subcategory":"School",
            "type":"Public Place"
        }
    ],
    "sg:phone":"+44 1246 412372",
    "sg:postcode":"S18 2FZ",
    "sg:province":"Derbyshire",
    "sg:tags":[
        "local",
        "authority"
    ],
    "wof:name":"The Dronfield School",
    "wof:placetype":"venue"
},
  "geometry": {"coordinates":[-1.4620740414,53.3096122742],"type":"Point"}
}