{
  "type": "Feature",
  "properties": {
    "addr:full":"Dorton Park Aylesbury Buckinghamshire HP18 9NR",
    "addr:postcode":"hp18 9nr",
    "addr:street":"Dorton Park",
    "iso:country":"GB",
    "sg:address":"Dorton Park",
    "sg:city":"Aylesbury",
    "sg:classifiers":[
        {
            "category":"Shopping",
            "subcategory":"Stationery & Office Supplies",
            "type":"Retail Goods"
        }
    ],
    "sg:phone":"+44 1844 237561",
    "sg:postcode":"HP18 9NR",
    "sg:province":"Buckinghamshire",
    "sg:tags":[
        "equipment"
    ],
    "wof:name":"Scandia Contract Furniture",
    "wof:placetype":"venue"
},
  "geometry": {"coordinates":[-1.013319,51.822796],"type":"Point"}
}