{
  "type": "Feature",
  "properties": {
    "iso:country":"GB",
    "sg:address":"Telemere Industrial Estate, Albert Road",
    "sg:city":"Luton",
    "sg:classifiers":[
        {
            "category":"Food & Beverages",
            "subcategory":"Liquor & Beverages",
            "type":"Retail Goods"
        }
    ],
    "sg:phone":"+44 1582 457799",
    "sg:postcode":"LU1 3QF",
    "sg:province":"Bedfordshire",
    "sg:tags":[
        "beer",
        "spirit",
        "wines"
    ],
    "wof:name":"Barrel Booze",
    "wof:placetype":"venue"
},
  "geometry": {"coordinates":[-0.415615,51.881336],"type":"Point"}
}