{
  "type": "Feature",
  "properties": {
    "addr:full":"Unit 6 Springmill Indstl Est, Avening Rd, Nailsworth Stroud Gloucestershire GL6 0BS",
    "addr:housenumber":"unit 6",
    "addr:postcode":"gl6 0bs",
    "addr:street":"Springmill Indstl Est Avening Rd",
    "iso:country":"GB",
    "sg:address":"Unit 6 Springmill Indstl Est, Avening Rd, Nailsworth",
    "sg:city":"Stroud",
    "sg:classifiers":[
        {
            "category":"Home & Garden",
            "subcategory":"Furniture",
            "type":"Retail Goods"
        }
    ],
    "sg:phone":"+44 1453 835116",
    "sg:postcode":"GL6 0BS",
    "sg:province":"Gloucestershire",
    "sg:tags":[
        "bed",
        "mattress"
    ],
    "wof:name":"Morpheus Beds Ltd",
    "wof:placetype":"venue"
},
  "geometry": {"coordinates":[-2.217984,51.695816],"type":"Point"}
}