{
  "type": "Feature",
  "properties": {
    "addr:full":"4 Fielder Drive, Newgate Lane Industrial Estate, Newgate Lane Fareham Hampshire PO14 1JE",
    "addr:housenumber":"4;estate",
    "addr:postcode":"po14 1je",
    "addr:street":"Fielder Drive Newgate Lane Industrial;Newgate Lane",
    "iso:country":"GB",
    "sg:address":"4 Fielder Drive, Newgate Lane Industrial Estate, Newgate Lane",
    "sg:city":"Fareham",
    "sg:classifiers":[
        {
            "category":"Home & Garden",
            "subcategory":"Carpets & Floor Coverings",
            "type":"Retail Goods"
        }
    ],
    "sg:phone":"+44 1329 287955",
    "sg:postcode":"PO14 1JE",
    "sg:province":"Hampshire",
    "sg:tags":[
        "rubber",
        "plastic"
    ],
    "wof:name":"Silicone Polymers Ltd.",
    "wof:placetype":"venue"
},
  "geometry": {"coordinates":[-1.1846109629,50.8394241333],"type":"Point"}
}