{
  "type": "Feature",
  "properties": {
    "addr:full":"11a Sheridan Terrace Hove East Sussex BN3 5AE",
    "addr:housenumber":"11a",
    "addr:postcode":"bn3 5ae",
    "addr:street":"Sheridan Terrace",
    "iso:country":"GB",
    "sg:address":"11a Sheridan Terrace",
    "sg:city":"Hove",
    "sg:classifiers":[
        {
            "category":"Home & Garden",
            "subcategory":"Home Furnishings",
            "type":"Retail Goods"
        }
    ],
    "sg:phone":"+44 1273 207303",
    "sg:postcode":"BN3 5AE",
    "sg:province":"East Sussex",
    "sg:tags":[
        "furnishers",
        "planner",
        "kitchen"
    ],
    "wof:name":"Russell Kitchens",
    "wof:placetype":"venue"
},
  "geometry": {"coordinates":[-0.1801410019,50.8357925415],"type":"Point"}
}