{
  "type": "Feature",
  "properties": {
    "addr:full":"Great Horton Indust Est, Copper La Bradford West Yorkshire BD6 3ND",
    "addr:postcode":"bd6 3nd",
    "addr:street":"Indust Est Copper La Bradford West",
    "iso:country":"GB",
    "sg:address":"Great Horton Indust Est, Copper La",
    "sg:city":"Bradford",
    "sg:classifiers":[
        {
            "category":"Professional",
            "subcategory":"Business Services",
            "type":"Services"
        }
    ],
    "sg:phone":"+44 1274 770306",
    "sg:postcode":"BD6 3ND",
    "sg:province":"West Yorkshire",
    "sg:tags":[
        "operator",
        "market"
    ],
    "wof:name":"Ashley Mills",
    "wof:placetype":"venue"
},
  "geometry": {"coordinates":[-1.809409976,53.7721595764],"type":"Point"}
}