{
  "type": "Feature",
  "properties": {
    "addr:full":"32 Newbridge Street Ayr South Ayrshire KA7 1JX",
    "addr:housenumber":"32",
    "addr:postcode":"ka7 1jx",
    "addr:street":"Newbridge Street",
    "iso:country":"GB",
    "sg:address":"32 Newbridge Street",
    "sg:city":"Ayr",
    "sg:classifiers":[
        {
            "category":"Cafe",
            "type":"Food & Drink"
        }
    ],
    "sg:phone":"+44 1292 289919",
    "sg:postcode":"KA7 1JX",
    "sg:province":"South Ayrshire",
    "sg:tags":[
        "tea",
        "room"
    ],
    "wof:name":"Pandora",
    "wof:placetype":"venue"
},
  "geometry": {"coordinates":[-4.632286,55.464546],"type":"Point"}
}