{
  "type": "Feature",
  "properties": {
    "addr:full":"Rozelle Park Ayr South Ayrshire KA7 4NQ",
    "addr:postcode":"ka7 4nq",
    "iso:country":"GB",
    "sg:address":"Rozelle Park",
    "sg:city":"Ayr",
    "sg:classifiers":[
        {
            "category":"Arts & Performance",
            "subcategory":"Art Gallery",
            "type":"Entertainment"
        },
        {
            "category":"Museum",
            "subcategory":"Art Museum",
            "type":"Entertainment"
        }
    ],
    "sg:phone":"+44 1292 443708",
    "sg:postcode":"KA7 4NQ",
    "sg:province":"South Ayrshire",
    "wof:name":"The Maclaurin Art Gallery",
    "wof:placetype":"venue"
},
  "geometry": {"coordinates":[-4.612924,55.431973],"type":"Point"}
}