{
  "type": "Feature",
  "properties": {
    "addr:full":"Timberdine Close Worcester Worcestershire WR5 2BD",
    "addr:postcode":"wr5 2bd",
    "addr:street":"Timberdine Close",
    "iso:country":"GB",
    "sg:address":"Timberdine Close",
    "sg:city":"Worcester",
    "sg:classifiers":[
        {
            "category":"Education",
            "subcategory":"School",
            "type":"Public Place"
        }
    ],
    "sg:postcode":"WR5 2BD",
    "sg:province":"Worcestershire",
    "sg:tags":[
        "local",
        "authority"
    ],
    "wof:name":"Cherry Orchard Primary School",
    "wof:placetype":"venue"
},
  "geometry": {"coordinates":[-2.213229,52.17836],"type":"Point"}
}