{
  "type": "Feature",
  "properties": {
    "iso:country":"GB",
    "sg:address":"Unit 1, The Crown Center, Bond Street",
    "sg:city":"Macclesfield",
    "sg:classifiers":[
        {
            "category":"Professional",
            "subcategory":"Printing & Photocopies",
            "type":"Services"
        }
    ],
    "sg:phone":"+44 1625 425676",
    "sg:postcode":"SK11 6QS",
    "sg:province":"Cheshire",
    "sg:tags":[
        "printer"
    ],
    "wof:name":"Basicfare Ltd.",
    "wof:placetype":"venue"
},
  "geometry": {"coordinates":[-2.125756,53.255669],"type":"Point"}
}