{
  "type": "Feature",
  "properties": {
    "addr:full":"35 Horn Lane London Greater London W3 9NJ",
    "addr:housenumber":"35",
    "addr:postcode":"w3 9nj",
    "addr:street":"Horn Lane",
    "iso:country":"GB",
    "sg:address":"35 Horn Lane",
    "sg:city":"London",
    "sg:classifiers":[
        {
            "category":"Professional",
            "subcategory":"Lawyer & Legal Services",
            "type":"Services"
        }
    ],
    "sg:phone":"+44 20 8993 5208",
    "sg:postcode":"W3 9NJ",
    "sg:province":"Greater London",
    "sg:tags":[
        "solicitor"
    ],
    "wof:name":"Robert Layton & Co",
    "wof:placetype":"venue"
},
  "geometry": {"coordinates":[-0.2716850042,51.5088233948],"type":"Point"}
}