{
  "type": "Feature",
  "properties": {
    "addr:full":"8 Brandon Village, Brandon Durham Durham DH7 8ST",
    "addr:housenumber":"8",
    "addr:postcode":"dh7 8st",
    "addr:street":"Brandon Village",
    "iso:country":"GB",
    "sg:address":"8 Brandon Village, Brandon",
    "sg:city":"Durham",
    "sg:classifiers":[
        {
            "category":"Travel",
            "subcategory":"Hotels & Motels",
            "type":"Entertainment"
        },
        {
            "category":"Community Center",
            "subcategory":"Social",
            "type":"Public Place"
        }
    ],
    "sg:phone":"+44 191 378 0498",
    "sg:postcode":"DH7 8ST",
    "sg:province":"Durham",
    "sg:tags":[
        "house",
        "activity"
    ],
    "wof:name":"The Bay Horse Inn",
    "wof:placetype":"venue"
},
  "geometry": {"coordinates":[-1.6364250183,54.7509689331],"type":"Point"}
}