{
  "type": "Feature",
  "properties": {
    "addr:full":"Woodhow, Wasdale Seascale Cumbria CA20 1ET",
    "addr:postcode":"ca20 1et",
    "iso:country":"GB",
    "sg:address":"Woodhow, Wasdale",
    "sg:city":"Seascale",
    "sg:classifiers":[
        {
            "category":"Farming",
            "subcategory":"Livestock Farm",
            "type":"Manufacturing & Wholesale Goods"
        }
    ],
    "sg:postcode":"CA20 1ET",
    "sg:province":"Cumbria",
    "sg:tags":[
        "others"
    ],
    "wof:name":"Lancaster,Annie M,",
    "wof:placetype":"venue"
},
  "geometry": {"coordinates":[-3.4846200943,54.394821167],"type":"Point"}
}