{
  "type": "Feature",
  "properties": {
    "iso:country":"GB",
    "sg:address":"Unit 8 Plot 9 Lion Barn Industri, Al E, St Needham Market",
    "sg:city":"Ipswich",
    "sg:classifiers":[
        {
            "category":"Retail",
            "subcategory":"Auto Repair",
            "type":"Services"
        }
    ],
    "sg:phone":"+44 1449 723006",
    "sg:postcode":"IP6 8NG",
    "sg:province":"Suffolk",
    "sg:tags":[
        "car",
        "body"
    ],
    "wof:name":"The Car Body Shop",
    "wof:placetype":"venue"
},
  "geometry": {"coordinates":[1.07103,52.171909],"type":"Point"}
}