{
  "type": "Feature",
  "properties": {
    "iso:country":"GB",
    "sg:address":"18-28 Victoria La",
    "sg:city":"Huddersfield",
    "sg:classifiers":[
        {
            "category":"Shopping",
            "subcategory":"Catalog Store",
            "type":"Retail Goods"
        }
    ],
    "sg:phone":"+44 1484 513832",
    "sg:postcode":"HD1 2QF",
    "sg:province":"West Yorkshire",
    "sg:tags":[
        "catalogue",
        "showroom"
    ],
    "wof:name":"Index The Catalogue Shop",
    "wof:placetype":"venue"
},
  "geometry": {"coordinates":[-1.781946,53.645176],"type":"Point"}
}