{
  "type": "Feature",
  "properties": {
    "addr:full":"46 Dudley Street Wolverhampton West Midlands WV1 3ER",
    "addr:housenumber":"46",
    "addr:postcode":"wv1 3er",
    "addr:street":"Dudley Street",
    "iso:country":"GB",
    "sg:address":"46 Dudley Street",
    "sg:city":"Wolverhampton",
    "sg:classifiers":[
        {
            "category":"Shopping",
            "subcategory":"Clothing, Apparel, & Fashions",
            "type":"Retail Goods"
        }
    ],
    "sg:phone":"+44 1902 420389",
    "sg:postcode":"WV1 3ER",
    "sg:province":"West Midlands",
    "sg:tags":[
        "shop"
    ],
    "wof:name":"River Island Clothing Co",
    "wof:placetype":"venue"
},
  "geometry": {"coordinates":[-2.126573,52.584335],"type":"Point"}
}