{
  "type": "Feature",
  "properties": {
    "iso:country":"GB",
    "sg:address":"13 Sowerberry Close",
    "sg:city":"Chelmsford",
    "sg:classifiers":[
        {
            "category":"Professional",
            "type":"Services"
        }
    ],
    "sg:postcode":"CM1 4YB",
    "sg:province":"Essex",
    "sg:tags":[
        "reflexologists"
    ],
    "wof:name":"Susan Moore",
    "wof:placetype":"venue"
},
  "geometry": {"coordinates":[0.456499,51.755676],"type":"Point"}
}