{
  "type": "Feature",
  "properties": {
    "addr:full":"7-9 Head Street Colchester Essex CO1 1NX",
    "addr:housenumber":"7-9",
    "addr:postcode":"co1 1nx",
    "addr:street":"Head Street",
    "iso:country":"GB",
    "sg:address":"7-9 Head Street",
    "sg:city":"Colchester",
    "sg:classifiers":[
        {
            "category":"Sports & Exercise",
            "subcategory":"Sports Center",
            "type":"Entertainment"
        }
    ],
    "sg:postcode":"CO1 1NX",
    "sg:province":"Essex",
    "sg:tags":[
        "shop",
        "good"
    ],
    "wof:name":"Harpers Sports",
    "wof:placetype":"venue"
},
  "geometry": {"coordinates":[0.896055,51.888844],"type":"Point"}
}