{
  "type": "Feature",
  "properties": {
    "addr:full":", Bagborough Taunton Devon TA4 3EF",
    "addr:postcode":"ta4 3ef",
    "addr:street":"Bagborough",
    "iso:country":"GB",
    "sg:address":", Bagborough",
    "sg:city":"Taunton",
    "sg:classifiers":[
        {
            "category":"Travel",
            "subcategory":"Hotels & Motels",
            "type":"Entertainment"
        }
    ],
    "sg:phone":"+44 1823 432996",
    "sg:postcode":"TA4 3EF",
    "sg:province":"Devon",
    "sg:tags":[
        "house",
        "guest"
    ],
    "wof:name":"Higher House",
    "wof:placetype":"venue"
},
  "geometry": {"coordinates":[-3.198494,51.094807],"type":"Point"}
}