{
  "type": "Feature",
  "properties": {
    "iso:country":"GB",
    "sg:address":"12 Rawson Market, New Development",
    "sg:city":"Bradford",
    "sg:classifiers":[
        {
            "category":"Food & Beverages",
            "subcategory":"Meat & Fish",
            "type":"Retail Goods"
        }
    ],
    "sg:postcode":"BD1 3QF",
    "sg:province":"West Yorkshire",
    "sg:tags":[
        "butcher"
    ],
    "wof:name":"D J Lovell",
    "wof:placetype":"venue"
},
  "geometry": {"coordinates":[-1.756124,53.796436],"type":"Point"}
}