{
  "type": "Feature",
  "properties": {
    "iso:country":"GB",
    "sg:address":"Spinney House, Wilcox Close, Aylesham Industrial Estate",
    "sg:city":"Canterbury",
    "sg:classifiers":[
        {
            "category":"Personal",
            "type":"Services"
        }
    ],
    "sg:phone":"+44 1304 841654",
    "sg:postcode":"CT3 3EP",
    "sg:province":"Kent",
    "sg:tags":[
        "delivery"
    ],
    "wof:name":"D H L",
    "wof:placetype":"venue"
},
  "geometry": {"coordinates":[1.190668,51.223976],"type":"Point"}
}