{
  "type": "Feature",
  "properties": {
    "iso:country":"GB",
    "sg:address":"7 Clos-yr-wenallt, Rhiwbina",
    "sg:city":"Cardiff",
    "sg:classifiers":[
        {
            "category":"Organizations",
            "subcategory":"Non-profit Organization",
            "type":"Services"
        }
    ],
    "sg:phone":"+44 1708 731251",
    "sg:postcode":"CF14 6TW",
    "sg:province":"Cardiff",
    "sg:tags":[
        "organisation",
        "voluntary",
        "charity"
    ],
    "wof:name":"South Wales Lupus Group",
    "wof:placetype":"venue"
},
  "geometry": {"coordinates":[-3.21956,51.53133],"type":"Point"}
}