{
  "type": "Feature",
  "properties": {
    "addr:full":"114 Acre Lane London Greater London SW2 5RA",
    "addr:housenumber":"114",
    "addr:postcode":"sw2 5ra",
    "addr:street":"Acre Lane",
    "iso:country":"GB",
    "sg:address":"114 Acre Lane",
    "sg:city":"London",
    "sg:classifiers":[
        {
            "category":"Professional",
            "subcategory":"Lawyer & Legal Services",
            "type":"Services"
        }
    ],
    "sg:postcode":"SW2 5RA",
    "sg:province":"Greater London",
    "sg:tags":[
        "solicitor"
    ],
    "wof:name":"Russell Henry & Co",
    "wof:placetype":"venue"
},
  "geometry": {"coordinates":[-0.123647,51.459732],"type":"Point"}
}