{
  "type": "Feature",
  "properties": {
    "addr:full":"Turret Ho, Station Rd Amersham Buckinghamshire HP7 0AB",
    "addr:postcode":"hp7 0ab",
    "addr:street":"Turret;Station Rd",
    "iso:country":"GB",
    "sg:address":"Turret Ho, Station Rd",
    "sg:city":"Amersham",
    "sg:classifiers":[
        {
            "category":"Real Estate",
            "subcategory":"Developer",
            "type":"Services"
        }
    ],
    "sg:postcode":"HP7 0AB",
    "sg:province":"Buckinghamshire",
    "sg:tags":[
        "property"
    ],
    "wof:name":"Keebee Homes Ltd",
    "wof:placetype":"venue"
},
  "geometry": {"coordinates":[-0.60796,51.673649],"type":"Point"}
}