{
  "type": "Feature",
  "properties": {
    "iso:country":"GB",
    "sg:address":"32a Victoria Road",
    "sg:city":"Hartlepool",
    "sg:classifiers":[
        {
            "category":"Professional",
            "subcategory":"Lawyer & Legal Services",
            "type":"Services"
        }
    ],
    "sg:phone":"+44 1429 273165",
    "sg:postcode":"TS26 8DD",
    "sg:province":"Durham",
    "sg:tags":[
        "solicitor"
    ],
    "wof:name":"R Bell & Son",
    "wof:placetype":"venue"
},
  "geometry": {"coordinates":[-1.218476,54.685612],"type":"Point"}
}