{
  "type": "Feature",
  "properties": {
    "addr:full":"36 Ballmoor, Buckingham Industrial Park Buckingham Buckinghamshire MK18 1RQ",
    "addr:housenumber":"36",
    "addr:postcode":"mk18 1rq",
    "addr:street":"Ballmoor Buckingham Industrial Park",
    "iso:country":"GB",
    "sg:address":"36 Ballmoor, Buckingham Industrial Park",
    "sg:city":"Buckingham",
    "sg:classifiers":[
        {
            "category":"Shopping",
            "type":"Retail Goods"
        }
    ],
    "sg:phone":"+44 1280 822818",
    "sg:postcode":"MK18 1RQ",
    "sg:province":"Buckinghamshire",
    "sg:tags":[
        "part",
        "accessory"
    ],
    "wof:name":"Automec Equipment & Parts Ltd.",
    "wof:placetype":"venue"
},
  "geometry": {"coordinates":[-0.986479,52.000751],"type":"Point"}
}