{
  "type": "Feature",
  "properties": {
    "addr:full":"1 Russell Pl Faversham Kent ME13 0QF",
    "addr:housenumber":"1",
    "addr:postcode":"me13 0qf",
    "addr:street":"Russell Pl",
    "iso:country":"GB",
    "sg:address":"1 Russell Pl",
    "sg:city":"Faversham",
    "sg:classifiers":[
        {
            "category":"Utilities",
            "type":"Services"
        }
    ],
    "sg:phone":"+44 1795 534637",
    "sg:postcode":"ME13 0QF",
    "sg:province":"Kent",
    "sg:tags":[
        "internet"
    ],
    "wof:name":"Netconsultancy",
    "wof:placetype":"venue"
},
  "geometry": {"coordinates":[0.877820015,51.33070755],"type":"Point"}
}