{
  "type": "Feature",
  "properties": {
    "addr:full":"36 Middlemore Rd, Middlemore Industrial Estate Smethwick West Midlands B66 2EA",
    "addr:housenumber":"36",
    "addr:postcode":"b66 2ea",
    "addr:street":"Middlemore Rd;Industrial Estate Smethwick",
    "iso:country":"GB",
    "sg:address":"36 Middlemore Rd, Middlemore Industrial Estate",
    "sg:city":"Smethwick",
    "sg:classifiers":[
        {
            "category":"Manufacturing",
            "subcategory":"Wood Products",
            "type":"Manufacturing & Wholesale Goods"
        }
    ],
    "sg:phone":"+44 121 558 3921",
    "sg:postcode":"B66 2EA",
    "sg:province":"West Midlands",
    "sg:tags":[
        "packaging",
        "crate",
        "pallets"
    ],
    "wof:name":"Beck & Pollitzer Engineering Ltd",
    "wof:placetype":"venue"
},
  "geometry": {"coordinates":[-1.9637789726,52.5013809204],"type":"Point"}
}