{
  "type": "Feature",
  "properties": {
    "iso:country":"GB",
    "sg:address":"9 Pylle Hill Crescent, Totterdown",
    "sg:city":"Bristol",
    "sg:classifiers":[
        {
            "category":"Professional",
            "subcategory":"Management & Consulting",
            "type":"Services"
        }
    ],
    "sg:postcode":"BS3 4TZ",
    "sg:province":"City of Bristol",
    "sg:tags":[
        "consultant",
        "business"
    ],
    "wof:name":"Thinking Heads Consulting Ltd",
    "wof:placetype":"venue"
},
  "geometry": {"coordinates":[-2.582362,51.442181],"type":"Point"}
}