{
  "type": "Feature",
  "properties": {
    "addr:full":"Abbey Wood Rd Abbey Wood Greater London SE2 9DZ",
    "addr:postcode":"se2 9dz",
    "addr:street":"Abbey Wood Rd",
    "iso:country":"GB",
    "sg:address":"Abbey Wood Rd",
    "sg:city":"Abbey Wood",
    "sg:classifiers":[
        {
            "category":"Place Of Worship",
            "type":"Public Place"
        }
    ],
    "sg:phone":"+44 20 8311 0369",
    "sg:postcode":"SE2 9DZ",
    "sg:province":"Greater London",
    "wof:name":"St. Michael & All Angels Church",
    "wof:placetype":"venue"
},
  "geometry": {"coordinates":[0.12124,51.492447],"type":"Point"}
}