{
  "type": "Feature",
  "properties": {
    "addr:full":"Fountain Street Ashton-under-lyne Greater Manchester OL6 9RW",
    "addr:postcode":"ol6 9rw",
    "addr:street":"Fountain Street",
    "iso:country":"GB",
    "sg:address":"Fountain Street",
    "sg:city":"Ashton-under-lyne",
    "sg:classifiers":[
        {
            "category":"Health Services",
            "subcategory":"Hospital",
            "type":"Services"
        }
    ],
    "sg:phone":"+44 161 331 5151",
    "sg:postcode":"OL6 9RW",
    "sg:province":"Greater Manchester",
    "wof:name":"Tameside & Glossop Community & Priority Services N H S Trust",
    "wof:placetype":"venue"
},
  "geometry": {"coordinates":[-2.0737540722,53.4942436218],"type":"Point"}
}