{
  "type": "Feature",
  "properties": {
    "iso:country":"GB",
    "sg:address":"Verdon St",
    "sg:city":"Sheffield",
    "sg:classifiers":[
        {
            "category":"Community Center",
            "type":"Public Place"
        }
    ],
    "sg:phone":"+44 114 249 1626",
    "sg:postcode":"S3 9QS",
    "sg:province":"South Yorkshire",
    "sg:tags":[
        "centre"
    ],
    "wof:name":"6",
    "wof:placetype":"venue"
},
  "geometry": {"coordinates":[-1.465401,53.392693],"type":"Point"}
}