{
  "type": "Feature",
  "properties": {
    "iso:country":"GB",
    "sg:address":"39 Diamond Avenue, Kirkby In Ashfield",
    "sg:city":"Nottingham",
    "sg:classifiers":[
        {
            "category":"Health Services",
            "subcategory":"Dentist",
            "type":"Services"
        }
    ],
    "sg:phone":"+44 1623 752237",
    "sg:postcode":"NG17 7GQ",
    "sg:province":"Nottinghamshire",
    "wof:name":"Diamond Avenue Dental Surgery",
    "wof:placetype":"venue"
},
  "geometry": {"coordinates":[-1.241347,53.098454],"type":"Point"}
}