{
  "type": "Feature",
  "properties": {
    "iso:country":"GB",
    "sg:address":"170 Ebury St",
    "sg:city":"London",
    "sg:classifiers":[
        {
            "category":"Building & Trades",
            "subcategory":"Construction",
            "type":"Services"
        }
    ],
    "sg:postcode":"SW1W 8UP",
    "sg:province":"Greater London",
    "sg:tags":[
        "builder"
    ],
    "wof:name":"Pettit,A J,",
    "wof:placetype":"venue"
},
  "geometry": {"coordinates":[-0.152089,51.491631],"type":"Point"}
}