{
  "type": "Feature",
  "properties": {
    "iso:country":"GB",
    "sg:address":"Gardrum Moss",
    "sg:city":"Falkirk",
    "sg:classifiers":[
        {
            "category":"Building & Trades",
            "subcategory":"Landscaping Services",
            "type":"Services"
        }
    ],
    "sg:phone":"+44 1324 622940",
    "sg:postcode":"FK1 3AR",
    "sg:province":"Falkirk",
    "sg:tags":[
        "horticultural",
        "consultant"
    ],
    "wof:name":"Sinclair William Horticulture",
    "wof:placetype":"venue"
},
  "geometry": {"coordinates":[-3.834019,55.940128],"type":"Point"}
}