{
  "type": "Feature",
  "properties": {
    "iso:country":"GB",
    "sg:address":"150 Lytham Road, Warton",
    "sg:city":"Preston",
    "sg:classifiers":[
        {
            "category":"Fast Food",
            "type":"Food & Drink"
        }
    ],
    "sg:phone":"+44 1772 635254",
    "sg:postcode":"PR4 1XE",
    "sg:province":"Lancashire",
    "sg:tags":[
        "away",
        "meal",
        "outlet",
        "take"
    ],
    "sg:website":"http://www.sandwichbar.co.uk",
    "wof:name":"White Sandwich & Coffee Bar",
    "wof:placetype":"venue"
},
  "geometry": {"coordinates":[-2.876951,53.752506],"type":"Point"}
}