{
  "type": "Feature",
  "properties": {
    "iso:country":"GB",
    "sg:address":"37-41 Cranleigh Court Rd, Yate",
    "sg:city":"Bristol",
    "sg:classifiers":[
        {
            "category":"Food & Beverages",
            "subcategory":"Supermarket",
            "type":"Retail Goods"
        }
    ],
    "sg:postcode":"BS37 5DQ",
    "sg:province":"Gloucestershire",
    "wof:name":"H & D Food & Wines",
    "wof:placetype":"venue"
},
  "geometry": {"coordinates":[-2.424933,51.54192],"type":"Point"}
}