{
  "type": "Feature",
  "properties": {
    "iso:country":"GB",
    "sg:address":"50 Main St, Barton Under Needwood",
    "sg:city":"Burton-on-trent",
    "sg:classifiers":[
        {
            "category":"Retail",
            "subcategory":"Auto Repair",
            "type":"Services"
        }
    ],
    "sg:postcode":"DE13 8AA",
    "sg:province":"Derbyshire",
    "sg:tags":[
        "modification",
        "garage"
    ],
    "wof:name":"Passam,R J,",
    "wof:placetype":"venue"
},
  "geometry": {"coordinates":[-1.723889,52.765099],"type":"Point"}
}