{
  "type": "Feature",
  "properties": {
    "addr:full":"59 Hills Rd Cambridge Cambridgeshire CB2 1NT",
    "addr:housenumber":"59",
    "addr:postcode":"cb2 1nt",
    "addr:street":"Hills Rd",
    "iso:country":"GB",
    "sg:address":"59 Hills Rd",
    "sg:city":"Cambridge",
    "sg:classifiers":[
        {
            "category":"Fast Food",
            "type":"Food & Drink"
        }
    ],
    "sg:phone":"+44 1223 360444",
    "sg:postcode":"CB2 1NT",
    "sg:province":"Cambridgeshire",
    "sg:tags":[
        "delivery"
    ],
    "wof:name":"Pizza Wheels",
    "wof:placetype":"venue"
},
  "geometry": {"coordinates":[0.1296799928,52.1966247559],"type":"Point"}
}