{
  "type": "Feature",
  "properties": {
    "iso:country":"GB",
    "sg:address":"60 Market St",
    "sg:city":"Ashby De La Zouch",
    "sg:classifiers":[
        {
            "category":"Professional",
            "subcategory":"Business Services",
            "type":"Services"
        }
    ],
    "sg:phone":"+44 1530 413955",
    "sg:postcode":"LE65 1AN",
    "sg:province":"Derbyshire",
    "sg:tags":[
        "bookmaker"
    ],
    "wof:name":"Manny Bernstein Ltd",
    "wof:placetype":"venue"
},
  "geometry": {"coordinates":[-1.473344,52.746651],"type":"Point"}
}