{
  "type": "Feature",
  "properties": {
    "addr:full":"R W S Ho, 5 Renfield St Glasgow Glasgow City G2 5EZ",
    "addr:housenumber":"5",
    "addr:postcode":"g2 5ez",
    "addr:street":"W S Ho;Renfield St",
    "iso:country":"GB",
    "sg:address":"R W S Ho, 5 Renfield St",
    "sg:city":"Glasgow",
    "sg:classifiers":[
        {
            "category":"Banks & Credit Unions",
            "subcategory":"Financial Services",
            "type":"Services"
        }
    ],
    "sg:phone":"+44 141 204 4830",
    "sg:postcode":"G2 5EZ",
    "sg:province":"Glasgow City",
    "sg:tags":[
        "adviser"
    ],
    "wof:name":"Quay Financial Matters Ltd",
    "wof:placetype":"venue"
},
  "geometry": {"coordinates":[-4.2573800087,55.8608703613],"type":"Point"}
}