{
  "type": "Feature",
  "properties": {
    "addr:full":"Spatham La Hassocks East Sussex BN6 8XH",
    "addr:postcode":"bn6 8xh",
    "addr:street":"La Hassocks",
    "iso:country":"GB",
    "sg:address":"Spatham La",
    "sg:city":"Hassocks",
    "sg:classifiers":[
        {
            "category":"Landmark",
            "subcategory":"Tourist Attraction",
            "type":"Public Place"
        }
    ],
    "sg:phone":"+44 1273 843498",
    "sg:postcode":"BN6 8XH",
    "sg:province":"East Sussex",
    "sg:tags":[
        "interest"
    ],
    "wof:name":"Stoneywish Country Park",
    "wof:placetype":"venue"
},
  "geometry": {"coordinates":[-0.140269,50.923996],"type":"Point"}
}