{
  "type": "Feature",
  "properties": {
    "iso:country":"GB",
    "sg:address":"44-46 Cranbourn St",
    "sg:city":"Holborn",
    "sg:classifiers":[
        {
            "category":"Food & Beverages",
            "subcategory":"Meat & Fish",
            "type":"Retail Goods"
        }
    ],
    "sg:phone":"+44 20 7734 3607",
    "sg:postcode":"WC2H 7AN",
    "sg:province":"Greater London",
    "sg:tags":[
        "chip"
    ],
    "wof:name":"Fish & Chip The",
    "wof:placetype":"venue"
},
  "geometry": {"coordinates":[-0.1289249957,51.5111274719],"type":"Point"}
}