{
  "type": "Feature",
  "properties": {
    "addr:full":"3 Saintbury Clo Stratford Upon Avon Warwickshire CV37 7HD",
    "addr:housenumber":"3",
    "addr:postcode":"cv37 7hd",
    "addr:street":"Saintbury Clo",
    "iso:country":"GB",
    "sg:address":"3 Saintbury Clo",
    "sg:city":"Stratford Upon Avon",
    "sg:classifiers":[
        {
            "category":"Wholesale",
            "subcategory":"Sporting Goods",
            "type":"Manufacturing & Wholesale Goods"
        }
    ],
    "sg:phone":"+44 1789 269922",
    "sg:postcode":"CV37 7HD",
    "sg:province":"Warwickshire",
    "sg:tags":[
        "mnfr",
        "sport",
        "equipment"
    ],
    "wof:name":"M G Enterprises",
    "wof:placetype":"venue"
},
  "geometry": {"coordinates":[-1.6831309795,52.1874275208],"type":"Point"}
}