{
  "type": "Feature",
  "properties": {
    "addr:full":"20 Middleton Grange Shopping Centre Hartlepool Durham TS24 7RS",
    "addr:housenumber":"20",
    "addr:postcode":"ts24 7rs",
    "addr:street":"Middleton Grange Shopping",
    "iso:country":"GB",
    "sg:address":"20 Middleton Grange Shopping Centre",
    "sg:city":"Hartlepool",
    "sg:classifiers":[
        {
            "category":"Travel",
            "subcategory":"Travel Agent",
            "type":"Entertainment"
        }
    ],
    "sg:phone":"+44 1429 866100",
    "sg:postcode":"TS24 7RS",
    "sg:province":"Durham",
    "wof:name":"Travel World",
    "wof:placetype":"venue"
},
  "geometry": {"coordinates":[-1.2100989819,54.6844711304],"type":"Point"}
}