{
  "type": "Feature",
  "properties": {
    "iso:country":"GB",
    "sg:address":"The Barn, Radwell",
    "sg:city":"Baldock",
    "sg:classifiers":[
        {
            "category":"Shopping",
            "subcategory":"Pets & Pet Supplies",
            "type":"Retail Goods"
        }
    ],
    "sg:phone":"+44 1462 733844",
    "sg:postcode":"SG7 5EN",
    "sg:province":"Bedfordshire",
    "sg:tags":[
        "food"
    ],
    "wof:name":"Radwell Animal Feeds",
    "wof:placetype":"venue"
},
  "geometry": {"coordinates":[-0.205771,52.00729],"type":"Point"}
}