{
  "type": "Feature",
  "properties": {
    "addr:full":"24 Benedict Square Peterborough Cambridgeshire PE4 6GD",
    "addr:housenumber":"24",
    "addr:postcode":"pe4 6gd",
    "addr:street":"Benedict Square",
    "iso:country":"GB",
    "sg:address":"24 Benedict Square",
    "sg:city":"Peterborough",
    "sg:classifiers":[
        {
            "category":"Organizations",
            "subcategory":"Non-profit Organization",
            "type":"Services"
        }
    ],
    "sg:phone":"+44 1733 577506",
    "sg:postcode":"PE4 6GD",
    "sg:province":"Cambridgeshire",
    "sg:tags":[
        "organisation",
        "voluntary",
        "charity"
    ],
    "wof:name":"Sense-Manor House Crafts",
    "wof:placetype":"venue"
},
  "geometry": {"coordinates":[-0.282346,52.610355],"type":"Point"}
}