{
  "type": "Feature",
  "properties": {
    "iso:country":"GB",
    "sg:address":"25 Castle St Mall",
    "sg:city":"Macclesfield",
    "sg:classifiers":[
        {
            "category":"Shopping",
            "subcategory":"Gifts & Souvenirs",
            "type":"Retail Goods"
        },
        {
            "category":"Home & Garden",
            "subcategory":"Kitchen Supply",
            "type":"Retail Goods"
        }
    ],
    "sg:phone":"+44 1625 618194",
    "sg:postcode":"SK11 6AF",
    "sg:province":"Cheshire",
    "sg:tags":[
        "shop",
        "glassware",
        "china"
    ],
    "wof:name":"Chinacave",
    "wof:placetype":"venue"
},
  "geometry": {"coordinates":[-2.125756,53.255669],"type":"Point"}
}