{
  "type": "Feature",
  "properties": {
    "iso:country":"GB",
    "sg:address":"Clay Lanes Farm, Clay Lane, Haslington",
    "sg:city":"Crewe",
    "sg:classifiers":[
        {
            "category":"Farming",
            "subcategory":"Livestock Farm",
            "type":"Manufacturing & Wholesale Goods"
        }
    ],
    "sg:phone":"+44 1270 582715",
    "sg:postcode":"CW1 5SQ",
    "sg:province":"Cheshire",
    "sg:tags":[
        "others"
    ],
    "wof:name":"J J & J D Hughes",
    "wof:placetype":"venue"
},
  "geometry": {"coordinates":[-2.394339,53.097462],"type":"Point"}
}