{
  "type": "Feature",
  "properties": {
    "iso:country":"GB",
    "sg:address":"Morgans, White Gritt, Minsterley",
    "sg:city":"Shrewsbury",
    "sg:classifiers":[
        {
            "category":"Communications",
            "subcategory":"Film & Video Production",
            "type":"Services"
        }
    ],
    "sg:phone":"+44 1588 650456",
    "sg:postcode":"SY5 0JL",
    "sg:province":"Shropshire",
    "sg:tags":[
        "tv",
        "studio"
    ],
    "wof:name":"Cam 3 Video Productions",
    "wof:placetype":"venue"
},
  "geometry": {"coordinates":[-2.9253981113,52.6382255554],"type":"Point"}
}