{
  "type": "Feature",
  "properties": {
    "addr:full":"247 Chapeltown Rd Leeds West Yorkshire LS7 3EX",
    "addr:housenumber":"247",
    "addr:postcode":"ls7 3ex",
    "addr:street":"Chapeltown Rd",
    "iso:country":"GB",
    "sg:address":"247 Chapeltown Rd",
    "sg:city":"Leeds",
    "sg:classifiers":[
        {
            "category":"Fast Food",
            "type":"Food & Drink"
        }
    ],
    "sg:postcode":"LS7 3EX",
    "sg:province":"West Yorkshire",
    "sg:tags":[
        "away",
        "take"
    ],
    "wof:name":"Wright,Al Rick,",
    "wof:placetype":"venue"
},
  "geometry": {"coordinates":[-1.531467,53.817795],"type":"Point"}
}