{
  "type": "Feature",
  "properties": {
    "addr:full":"Cammrocks Farm, Straight Drove, Coveney Ely Cambridgeshire CB6 2DR",
    "addr:postcode":"cb6 2dr",
    "addr:street":"Straight Drove",
    "iso:country":"GB",
    "sg:address":"Cammrocks Farm, Straight Drove, Coveney",
    "sg:city":"Ely",
    "sg:classifiers":[
        {
            "category":"Farming",
            "subcategory":"Livestock Farm",
            "type":"Manufacturing & Wholesale Goods"
        },
        {
            "category":"Farming",
            "subcategory":"Farm",
            "type":"Manufacturing & Wholesale Goods"
        }
    ],
    "sg:postcode":"CB6 2DR",
    "sg:province":"Cambridgeshire",
    "sg:tags":[
        "mixed",
        "crop",
        "others"
    ],
    "wof:name":"B & L Lucas",
    "wof:placetype":"venue"
},
  "geometry": {"coordinates":[0.189535,52.418167],"type":"Point"}
}