{
  "type": "Feature",
  "properties": {
    "addr:full":"32-34 Cotham Hill Bristol City of Bristol BS6 6LA",
    "addr:housenumber":"32-34",
    "addr:postcode":"bs6 6la",
    "addr:street":"Cotham Hill",
    "iso:country":"GB",
    "sg:address":"32-34 Cotham Hill",
    "sg:city":"Bristol",
    "sg:classifiers":[
        {
            "category":"Restaurant",
            "type":"Food & Drink"
        }
    ],
    "sg:phone":"+44 117 974 1390",
    "sg:postcode":"BS6 6LA",
    "sg:province":"City of Bristol",
    "sg:tags":[
        "indian"
    ],
    "wof:name":"Cotham Tandoori",
    "wof:placetype":"venue"
},
  "geometry": {"coordinates":[-2.600589,51.462551],"type":"Point"}
}