{
  "type": "Feature",
  "properties": {
    "iso:country":"GB",
    "sg:address":"Pennington Flash Country Park, St. Helens Rd",
    "sg:city":"Leigh",
    "sg:classifiers":[
        {
            "category":"Sports & Exercise",
            "subcategory":"Golf",
            "type":"Entertainment"
        }
    ],
    "sg:phone":"+44 1942 682852",
    "sg:postcode":"WN7 3PA",
    "sg:province":"Lancashire",
    "sg:tags":[
        "club",
        "course"
    ],
    "wof:name":"4 Put Golf Shop",
    "wof:placetype":"venue"
},
  "geometry": {"coordinates":[-2.5189940929,53.4969711304],"type":"Point"}
}