{
  "type": "Feature",
  "properties": {
    "iso:country":"GB",
    "sg:address":"5 Moorside La",
    "sg:city":"Stockport",
    "sg:classifiers":[
        {
            "category":"Home & Garden",
            "subcategory":"Household Appliances",
            "type":"Retail Goods"
        }
    ],
    "sg:phone":"+44 161 432 3363",
    "sg:postcode":"SK4 4DT",
    "sg:province":"Cheshire",
    "sg:tags":[
        "domestic",
        "centre"
    ],
    "wof:name":"Stockport Appliance Centre",
    "wof:placetype":"venue"
},
  "geometry": {"coordinates":[-2.1895260811,53.4167633057],"type":"Point"}
}