{
  "type": "Feature",
  "properties": {
    "iso:country":"GB",
    "sg:address":"Police Station, 7 Tower View",
    "sg:city":"Newcastle Upon Tyne",
    "sg:classifiers":[
        {
            "category":"Shopping",
            "subcategory":"Department Store",
            "type":"Retail Goods"
        },
        {
            "category":"Food & Beverages",
            "subcategory":"Groceries & Convenience Stores",
            "type":"Retail Goods"
        }
    ],
    "sg:phone":"+44 191 241 0181",
    "sg:postcode":"NE15 6NY",
    "sg:province":"Northumberland",
    "wof:name":"Generals Dealers",
    "wof:placetype":"venue"
},
  "geometry": {"coordinates":[-1.67297,54.97541],"type":"Point"}
}