{
  "type": "Feature",
  "properties": {
    "addr:full":"49a Main St Burton On Trent Derbyshire DE13 8AA",
    "addr:housenumber":"49a",
    "addr:postcode":"de13 8aa",
    "addr:street":"Main St",
    "iso:country":"GB",
    "sg:address":"49a Main St",
    "sg:city":"Burton On Trent",
    "sg:classifiers":[
        {
            "category":"Deli",
            "type":"Food & Drink"
        }
    ],
    "sg:phone":"+44 1283 716129",
    "sg:postcode":"DE13 8AA",
    "sg:province":"Derbyshire",
    "sg:tags":[
        "delicatessen"
    ],
    "wof:name":"Country Kitchen",
    "wof:placetype":"venue"
},
  "geometry": {"coordinates":[-1.725554,52.765144],"type":"Point"}
}