{
  "type": "Feature",
  "properties": {
    "addr:full":"1 Rolleston Street Leicester Leicestershire LE5 3SB",
    "addr:housenumber":"1",
    "addr:postcode":"le5 3sb",
    "addr:street":"Rolleston Street",
    "iso:country":"GB",
    "sg:address":"1 Rolleston Street",
    "sg:city":"Leicester",
    "sg:classifiers":[
        {
            "category":"Retail",
            "subcategory":"Repair Shop",
            "type":"Services"
        }
    ],
    "sg:phone":"+44 116 251 6170",
    "sg:postcode":"LE5 3SB",
    "sg:province":"Leicestershire",
    "sg:tags":[
        "television",
        "good",
        "video",
        "servicing",
        "maintenance",
        "radio"
    ],
    "wof:name":"Profile Vision",
    "wof:placetype":"venue"
},
  "geometry": {"coordinates":[-1.103448987,52.6389160156],"type":"Point"}
}