{
  "type": "Feature",
  "properties": {
    "iso:country":"GB",
    "sg:address":"Studio 7 Deeside Enterprise Centre, Rowleys Dr",
    "sg:city":"Deeside",
    "sg:classifiers":[
        {
            "category":"Professional",
            "subcategory":"Printing & Photocopies",
            "type":"Services"
        }
    ],
    "sg:phone":"+44 1244 830996",
    "sg:postcode":"CH5 1PP",
    "sg:province":"Flintshire",
    "sg:tags":[
        "printer"
    ],
    "wof:name":"Future Promotions",
    "wof:placetype":"venue"
},
  "geometry": {"coordinates":[-3.024988,53.20248],"type":"Point"}
}