{
  "type": "Feature",
  "properties": {
    "addr:full":"Brookside Business Pk, Cold Meece Stone Staffordshire ST15 0RZ",
    "addr:postcode":"st15 0rz",
    "addr:street":"Pk Cold Meece",
    "iso:country":"GB",
    "sg:address":"Brookside Business Pk, Cold Meece",
    "sg:city":"Stone",
    "sg:classifiers":[
        {
            "category":"Professional",
            "subcategory":"Management & Consulting",
            "type":"Services"
        },
        {
            "category":"Professional",
            "subcategory":"Computer Services",
            "type":"Services"
        }
    ],
    "sg:postcode":"ST15 0RZ",
    "sg:province":"Staffordshire",
    "sg:tags":[
        "consultant",
        "training",
        "system",
        "software"
    ],
    "wof:name":"I T Training Direct Ltd",
    "wof:placetype":"venue"
},
  "geometry": {"coordinates":[-2.215289,52.892574],"type":"Point"}
}