{
  "type": "Feature",
  "properties": {
    "addr:full":"141a Oakway Woking Surrey GU21 1TR",
    "addr:housenumber":"141a",
    "addr:postcode":"gu21 1tr",
    "addr:street":"Oakway",
    "iso:country":"GB",
    "sg:address":"141a Oakway",
    "sg:city":"Woking",
    "sg:classifiers":[
        {
            "category":"Real Estate",
            "subcategory":"Architect",
            "type":"Services"
        }
    ],
    "sg:phone":"+44 1483 486808",
    "sg:postcode":"GU21 1TR",
    "sg:province":"Surrey",
    "sg:tags":[
        "architectural"
    ],
    "wof:name":"Trinder Architectural Consultant",
    "wof:placetype":"venue"
},
  "geometry": {"coordinates":[-0.608003,51.310947],"type":"Point"}
}