{
  "type": "Feature",
  "properties": {
    "iso:country":"GB",
    "sg:address":"The Old Rectory Farm, Waterside, Pear Tree Bridge",
    "sg:city":"Milton Keynes",
    "sg:classifiers":[
        {
            "category":"Sports & Exercise",
            "subcategory":"Stables",
            "type":"Entertainment"
        }
    ],
    "sg:phone":"+44 1908 230081",
    "sg:postcode":"MK6 3EJ",
    "sg:province":"Buckinghamshire",
    "sg:tags":[
        "education",
        "equestrian"
    ],
    "wof:name":"The Old Rectory Riding School Trust",
    "wof:placetype":"venue"
},
  "geometry": {"coordinates":[-0.73195,52.029621],"type":"Point"}
}