{
  "type": "Feature",
  "properties": {
    "iso:country":"GB",
    "sg:address":"Park Lane, Eddington Road, Nettlestone",
    "sg:city":"Seaview",
    "sg:classifiers":[
        {
            "category":"Home & Garden",
            "subcategory":"Building Materials",
            "type":"Retail Goods"
        }
    ],
    "sg:postcode":"PO34 5LT",
    "sg:province":"Isle of Wight",
    "sg:tags":[
        "fencing"
    ],
    "wof:name":"Malcolm  & Russell Page Vaughan",
    "wof:placetype":"venue"
},
  "geometry": {"coordinates":[-1.110274,50.719559],"type":"Point"}
}