{
  "type": "Feature",
  "properties": {
    "addr:full":"Unit 2 Midland Structures Indust Estate, Ampthill Road Bedford Bedfordshire MK42 9JJ",
    "addr:housenumber":"unit 2",
    "addr:postcode":"mk42 9jj",
    "addr:street":"Ampthill Road",
    "iso:country":"GB",
    "sg:address":"Unit 2 Midland Structures Indust Estate, Ampthill Road",
    "sg:city":"Bedford",
    "sg:classifiers":[
        {
            "category":"Professional",
            "subcategory":"Advertising",
            "type":"Services"
        }
    ],
    "sg:phone":"+44 1234 356744",
    "sg:postcode":"MK42 9JJ",
    "sg:province":"Bedfordshire",
    "wof:name":"Millanium",
    "wof:placetype":"venue"
},
  "geometry": {"coordinates":[-0.47295,52.12466],"type":"Point"}
}