{
  "type": "Feature",
  "properties": {
    "addr:full":"St Aldwyn Road Gloucester Gloucestershire GL1 4RB",
    "addr:postcode":"gl1 4rb",
    "addr:street":"St Aldwyn Road",
    "iso:country":"GB",
    "sg:address":"St Aldwyn Road",
    "sg:city":"Gloucester",
    "sg:classifiers":[
        {
            "category":"Retail",
            "subcategory":"Auto Repair",
            "type":"Services"
        }
    ],
    "sg:phone":"+44 1452 520846",
    "sg:postcode":"GL1 4RB",
    "sg:province":"Gloucestershire",
    "sg:tags":[
        "modification",
        "garage",
        "related"
    ],
    "wof:name":"St Aldwyn Garage",
    "wof:placetype":"venue"
},
  "geometry": {"coordinates":[-2.236374,51.850826],"type":"Point"}
}