{
  "type": "Feature",
  "properties": {
    "addr:full":"180 Albert Street Edinburgh City of Edinburgh EH7 5NA",
    "addr:housenumber":"180",
    "addr:postcode":"eh7 5na",
    "addr:street":"Albert Street",
    "iso:country":"GB",
    "sg:address":"180 Albert Street",
    "sg:city":"Edinburgh",
    "sg:classifiers":[
        {
            "category":"Bars & Pubs",
            "type":"Food & Drink"
        }
    ],
    "sg:phone":"+44 131 554 3828",
    "sg:postcode":"EH7 5NA",
    "sg:province":"City of Edinburgh",
    "sg:tags":[
        "pubs",
        "inn"
    ],
    "wof:name":"The Royal Nip",
    "wof:placetype":"venue"
},
  "geometry": {"coordinates":[-3.1778290272,55.9626693726],"type":"Point"}
}