{
  "type": "Feature",
  "properties": {
    "addr:full":"5a Tunnel Road Beaminster Dorset DT8 3BQ",
    "addr:housenumber":"5a",
    "addr:postcode":"dt8 3bq",
    "addr:street":"Tunnel Road",
    "iso:country":"GB",
    "sg:address":"5a Tunnel Road",
    "sg:city":"Beaminster",
    "sg:classifiers":[
        {
            "category":"Building & Trades",
            "subcategory":"Construction",
            "type":"Services"
        }
    ],
    "sg:postcode":"DT8 3BQ",
    "sg:province":"Dorset",
    "sg:tags":[
        "builder",
        "welder"
    ],
    "wof:name":"Elliott Engineering",
    "wof:placetype":"venue"
},
  "geometry": {"coordinates":[-2.743867,50.810661],"type":"Point"}
}