{
  "type": "Feature",
  "properties": {
    "addr:full":"Willow House, Ipswich Road, Long Stratton Norwich Norfolk NR15 2TA",
    "addr:postcode":"nr15 2ta",
    "addr:street":"Ipswich Road",
    "iso:country":"GB",
    "sg:address":"Willow House, Ipswich Road, Long Stratton",
    "sg:city":"Norwich",
    "sg:classifiers":[
        {
            "category":"Banks & Credit Unions",
            "subcategory":"Financial Services",
            "type":"Services"
        }
    ],
    "sg:phone":"+44 1508 530567",
    "sg:postcode":"NR15 2TA",
    "sg:province":"Norfolk",
    "sg:tags":[
        "adviser",
        "independent"
    ],
    "wof:name":"Moss & Roberts",
    "wof:placetype":"venue"
},
  "geometry": {"coordinates":[1.232493,52.481564],"type":"Point"}
}