{
  "type": "Feature",
  "properties": {
    "addr:full":"50 Hawthorne Spinney York North Yorkshire YO24 1JP",
    "addr:housenumber":"50",
    "addr:postcode":"yo24 1jp",
    "addr:street":"Hawthorne Spinney",
    "iso:country":"GB",
    "sg:address":"50 Hawthorne Spinney",
    "sg:city":"York",
    "sg:classifiers":[
        {
            "category":"Building & Trades",
            "subcategory":"Plumbing",
            "type":"Services"
        }
    ],
    "sg:postcode":"YO24 1JP",
    "sg:province":"North Yorkshire",
    "sg:tags":[
        "heating"
    ],
    "wof:name":"N Legge",
    "wof:placetype":"venue"
},
  "geometry": {"coordinates":[-1.106869,53.93988],"type":"Point"}
}