{
  "type": "Feature",
  "properties": {
    "iso:country":"GB",
    "sg:address":"Brewery La",
    "sg:city":"Dewsbury",
    "sg:classifiers":[
        {
            "category":"Home & Garden",
            "subcategory":"Kitchen Supply",
            "type":"Retail Goods"
        }
    ],
    "sg:phone":"+44 1924 462143",
    "sg:postcode":"WF12 9HU",
    "sg:province":"West Yorkshire",
    "sg:tags":[
        "measuring",
        "scale"
    ],
    "wof:name":"Salter Weigh-Tronix Ltd",
    "wof:placetype":"venue"
},
  "geometry": {"coordinates":[-1.635924,53.675404],"type":"Point"}
}