{
  "type": "Feature",
  "properties": {
    "addr:full":"320 Barking Road London Greater London E13 8HL",
    "addr:housenumber":"320",
    "addr:postcode":"e13 8hl",
    "addr:street":"Barking Road",
    "iso:country":"GB",
    "sg:address":"320 Barking Road",
    "sg:city":"London",
    "sg:classifiers":[
        {
            "category":"Restaurant",
            "type":"Food & Drink"
        }
    ],
    "sg:phone":"+44 20 7473 4333",
    "sg:postcode":"E13 8HL",
    "sg:province":"Greater London",
    "sg:tags":[
        "indian",
        "-"
    ],
    "wof:name":"Samrat Tandoori Restaurant",
    "wof:placetype":"venue"
},
  "geometry": {"coordinates":[0.0204980001,51.5211791992],"type":"Point"}
}