{
  "type": "Feature",
  "properties": {
    "iso:country":"GB",
    "sg:address":"11 Windsor Gardens",
    "sg:city":"Benfleet",
    "sg:classifiers":[
        {
            "category":"Building & Trades",
            "subcategory":"Cleaning & Sanitation",
            "type":"Services"
        }
    ],
    "sg:postcode":"SS7 3YF",
    "sg:province":"Essex",
    "sg:tags":[
        "commercial"
    ],
    "wof:name":"Guilder Cleaning Services",
    "wof:placetype":"venue"
},
  "geometry": {"coordinates":[0.59906,51.560234],"type":"Point"}
}