{
  "type": "Feature",
  "properties": {
    "addr:full":"Ansvar House, 31 St Leonards Road Eastbourne East Sussex BN21 3UU",
    "addr:housenumber":"31",
    "addr:postcode":"bn21 3uu",
    "addr:street":"St Leonards Road",
    "iso:country":"GB",
    "sg:address":"Ansvar House, 31 St Leonards Road",
    "sg:city":"Eastbourne",
    "sg:classifiers":[
        {
            "category":"Insurance",
            "subcategory":"Insurance Agent",
            "type":"Services"
        }
    ],
    "sg:postcode":"BN21 3UU",
    "sg:province":"East Sussex",
    "sg:tags":[
        "broker"
    ],
    "wof:name":"Crusade Services Ltd.",
    "wof:placetype":"venue"
},
  "geometry": {"coordinates":[0.283799,50.77282],"type":"Point"}
}