{
  "type": "Feature",
  "properties": {
    "addr:full":"285 Stockport Road Hyde Cheshire SK14 5RF",
    "addr:housenumber":"285",
    "addr:postcode":"sk14 5rf",
    "addr:street":"Stockport Road",
    "iso:country":"GB",
    "sg:address":"285 Stockport Road",
    "sg:city":"Hyde",
    "sg:classifiers":[
        {
            "category":"Deli",
            "type":"Food & Drink"
        }
    ],
    "sg:phone":"+44 161 366 6181",
    "sg:postcode":"SK14 5RF",
    "sg:province":"Cheshire",
    "sg:tags":[
        "delicatessen"
    ],
    "wof:name":"The Village Larder",
    "wof:placetype":"venue"
},
  "geometry": {"coordinates":[-2.0711150169,53.436882019],"type":"Point"}
}