{
  "type": "Feature",
  "properties": {
    "iso:country":"GB",
    "sg:address":"161 Fulham Rd",
    "sg:city":"Chelsea",
    "sg:classifiers":[
        {
            "category":"Conference Center",
            "type":"Public Place"
        }
    ],
    "sg:phone":"+44 20 7581 8946",
    "sg:postcode":"SW3 6SN",
    "sg:province":"Greater London",
    "wof:name":"Travel Design & Marketing",
    "wof:placetype":"venue"
},
  "geometry": {"coordinates":[-0.171173,51.491978],"type":"Point"}
}