{
  "type": "Feature",
  "properties": {
    "addr:full":"9a Glencryan Road, Cumbernauld Glasgow Falkirk G67 2UH",
    "addr:housenumber":"9a",
    "addr:postcode":"g67 2uh",
    "addr:street":"Glencryan Road",
    "iso:country":"GB",
    "sg:address":"9a Glencryan Road, Cumbernauld",
    "sg:city":"Glasgow",
    "sg:classifiers":[
        {
            "category":"Building & Trades",
            "subcategory":"Construction",
            "type":"Services"
        }
    ],
    "sg:phone":"+44 1236 781033",
    "sg:postcode":"G67 2UH",
    "sg:province":"Falkirk",
    "sg:tags":[
        "builder"
    ],
    "wof:name":"The Cumbernauld Trade & Supply Centre",
    "wof:placetype":"venue"
},
  "geometry": {"coordinates":[-3.978657,55.943451],"type":"Point"}
}