{
  "type": "Feature",
  "properties": {
    "addr:full":"Park Lane Aberdare Neath Port Talbot CF44 8HN",
    "addr:postcode":"cf44 8hn",
    "addr:street":"Park Lane",
    "iso:country":"GB",
    "sg:address":"Park Lane",
    "sg:city":"Aberdare",
    "sg:classifiers":[
        {
            "category":"Education",
            "subcategory":"Special Training",
            "type":"Public Place"
        },
        {
            "category":"Education",
            "subcategory":"School",
            "type":"Public Place"
        },
        {
            "category":"Government",
            "subcategory":"Office",
            "type":"Public Place"
        }
    ],
    "sg:phone":"+44 1685 874489",
    "sg:postcode":"CF44 8HN",
    "sg:province":"Neath Port Talbot",
    "sg:tags":[
        "local"
    ],
    "wof:name":"Park Lane Special School",
    "wof:placetype":"venue"
},
  "geometry": {"coordinates":[-3.461714,51.721062],"type":"Point"}
}