{
  "type": "Feature",
  "properties": {
    "iso:country":"GB",
    "sg:address":"66 Prospect Road, Minster",
    "sg:city":"Ramsgate",
    "sg:classifiers":[
        {
            "category":"Banks & Credit Unions",
            "subcategory":"Investment Brokerage",
            "type":"Services"
        }
    ],
    "sg:phone":"+44 1843 822278",
    "sg:postcode":"CT12 4EQ",
    "sg:province":"Kent",
    "sg:tags":[
        "contractor"
    ],
    "wof:name":"Roy Bailey",
    "wof:placetype":"venue"
},
  "geometry": {"coordinates":[1.308993,51.33765],"type":"Point"}
}