{
  "type": "Feature",
  "properties": {
    "addr:full":"28 Main Street, Barrowden Oakham Leicestershire LE15 8EQ",
    "addr:housenumber":"28",
    "addr:postcode":"le15 8eq",
    "addr:street":"Main Street",
    "iso:country":"GB",
    "sg:address":"28 Main Street, Barrowden",
    "sg:city":"Oakham",
    "sg:classifiers":[
        {
            "category":"Bars & Pubs",
            "type":"Food & Drink"
        },
        {
            "category":"Community Center",
            "subcategory":"Social",
            "type":"Public Place"
        }
    ],
    "sg:phone":"+44 1572 747247",
    "sg:postcode":"LE15 8EQ",
    "sg:province":"Leicestershire",
    "sg:tags":[
        "pubs",
        "house",
        "inn",
        "activity"
    ],
    "wof:name":"Exeter Arms",
    "wof:placetype":"venue"
},
  "geometry": {"coordinates":[-0.6041849852,52.5903816223],"type":"Point"}
}