{
  "type": "Feature",
  "properties": {
    "addr:full":"45 Trinity Gardens London Greater London SW9 8DR",
    "addr:housenumber":"45",
    "addr:postcode":"sw9 8dr",
    "addr:street":"Trinity Gardens",
    "iso:country":"GB",
    "sg:address":"45 Trinity Gardens",
    "sg:city":"London",
    "sg:classifiers":[
        {
            "category":"Bars & Pubs",
            "type":"Food & Drink"
        }
    ],
    "sg:phone":"+44 20 7274 4544",
    "sg:postcode":"SW9 8DR",
    "sg:province":"Greater London",
    "sg:tags":[
        "pubs",
        "house",
        "inn",
        "public",
        "activity"
    ],
    "wof:name":"Trinity Arms",
    "wof:placetype":"venue"
},
  "geometry": {"coordinates":[-0.1193009987,51.461769104],"type":"Point"}
}