{
  "type": "Feature",
  "properties": {
    "addr:full":"Broadshean Farm, Kirkoswald Maybole East Ayrshire KA19 8HP",
    "addr:housenumber":"kirkoswald",
    "addr:postcode":"ka19 8hp",
    "addr:street":"Maybole East",
    "iso:country":"GB",
    "sg:address":"Broadshean Farm, Kirkoswald",
    "sg:city":"Maybole",
    "sg:classifiers":[
        {
            "category":"Farming",
            "subcategory":"Farm",
            "type":"Manufacturing & Wholesale Goods"
        }
    ],
    "sg:postcode":"KA19 8HP",
    "sg:province":"East Ayrshire",
    "sg:tags":[
        "mixed",
        "crop"
    ],
    "wof:name":"McFadzean",
    "wof:placetype":"venue"
},
  "geometry": {"coordinates":[-4.769749,55.33091],"type":"Point"}
}