{
  "type": "Feature",
  "properties": {
    "iso:country":"GB",
    "sg:address":"Unit C, Decoy Road, Dominion Way",
    "sg:city":"Worthing",
    "sg:classifiers":[
        {
            "category":"Wholesale",
            "subcategory":"Machinery & Supplies",
            "type":"Manufacturing & Wholesale Goods"
        }
    ],
    "sg:phone":"+44 1903 206622",
    "sg:postcode":"BN14 8ND",
    "sg:province":"West Sussex",
    "sg:tags":[
        "pump"
    ],
    "wof:name":"Ram Pumps Ltd.",
    "wof:placetype":"venue"
},
  "geometry": {"coordinates":[-0.3579,50.824921],"type":"Point"}
}