{
  "type": "Feature",
  "properties": {
    "iso:country":"GB",
    "sg:address":"15 New Broadway",
    "sg:city":"Ealing",
    "sg:classifiers":[
        {
            "category":"Personal",
            "subcategory":"Psychics & Astrologers",
            "type":"Services"
        }
    ],
    "sg:phone":"+44 20 8579 8964",
    "sg:postcode":"W5 5AW",
    "sg:province":"Greater London",
    "sg:tags":[
        "clairvoyant",
        "palmist"
    ],
    "wof:name":"Angelina's Psychic Readings",
    "wof:placetype":"venue"
},
  "geometry": {"coordinates":[-0.305213,51.512959],"type":"Point"}
}