{
  "type": "Feature",
  "properties": {
    "addr:full":"93 Wrens Park House, Warwick Grove Clapton Greater London E5 9LW",
    "addr:housenumber":"93",
    "addr:postcode":"e5 9lw",
    "addr:street":"Wrens Park House Warwick Grove",
    "iso:country":"GB",
    "sg:address":"93 Wrens Park House, Warwick Grove",
    "sg:city":"Clapton",
    "sg:classifiers":[
        {
            "category":"Government",
            "subcategory":"City Hall",
            "type":"Public Place"
        }
    ],
    "sg:phone":"+44 20 8806 6269",
    "sg:postcode":"E5 9LW",
    "sg:province":"Greater London",
    "wof:name":"Raynes Park Tenants Association",
    "wof:placetype":"venue"
},
  "geometry": {"coordinates":[-0.0539060012,51.5587921143],"type":"Point"}
}