{
  "type": "Feature",
  "properties": {
    "addr:full":"64 Leicester Rd Wigston Leicestershire LE18 1DR",
    "addr:housenumber":"64",
    "addr:postcode":"le18 1dr",
    "addr:street":"Leicester Rd",
    "iso:country":"GB",
    "sg:address":"64 Leicester Rd",
    "sg:city":"Wigston",
    "sg:classifiers":[
        {
            "category":"Bars & Pubs",
            "type":"Food & Drink"
        }
    ],
    "sg:phone":"+44 116 281 0719",
    "sg:postcode":"LE18 1DR",
    "sg:province":"Leicestershire",
    "sg:tags":[
        "pubs",
        "inn"
    ],
    "wof:name":"Punch Retail Ltd",
    "wof:placetype":"venue"
},
  "geometry": {"coordinates":[-1.1058909893,52.5873336792],"type":"Point"}
}