{
  "type": "Feature",
  "properties": {
    "addr:full":"32 The Grove Ilkley North Yorkshire LS29 9EE",
    "addr:housenumber":"32",
    "addr:postcode":"ls29 9ee",
    "addr:street":"The Grove",
    "iso:country":"GB",
    "sg:address":"32 The Grove",
    "sg:city":"Ilkley",
    "sg:classifiers":[
        {
            "category":"Cafe",
            "type":"Food & Drink"
        }
    ],
    "sg:phone":"+44 1943 608029",
    "sg:postcode":"LS29 9EE",
    "sg:province":"North Yorkshire",
    "sg:tags":[
        "tea",
        "snack",
        "bar",
        "room"
    ],
    "wof:name":"Betty's Cafe",
    "wof:placetype":"venue"
},
  "geometry": {"coordinates":[-1.8259060383,53.9247207642],"type":"Point"}
}