{
  "type": "Feature",
  "properties": {
    "addr:full":"45 Whitehall Road Ramsgate Kent CT12 6DE",
    "addr:housenumber":"45",
    "addr:postcode":"ct12 6de",
    "addr:street":"Whitehall Road Ramsgate",
    "iso:country":"GB",
    "sg:address":"45 Whitehall Road",
    "sg:city":"Ramsgate",
    "sg:classifiers":[
        {
            "category":"Manufacturing",
            "subcategory":"Tools & Machinery",
            "type":"Manufacturing & Wholesale Goods"
        }
    ],
    "sg:phone":"+44 1843 853355",
    "sg:postcode":"CT12 6DE",
    "sg:province":"Kent",
    "sg:tags":[
        "design",
        "maker",
        "manufacturer"
    ],
    "wof:name":"S P S TOOLS",
    "wof:placetype":"venue"
},
  "geometry": {"coordinates":[1.4041399956,51.3439750671],"type":"Point"}
}