{
  "type": "Feature",
  "properties": {
    "addr:full":"8a Shawcross Walk, Port Street Evesham Gloucestershire WR11 1AW",
    "addr:housenumber":"8a",
    "addr:postcode":"wr11 1aw",
    "addr:street":"Shawcross Walk Port Street",
    "iso:country":"GB",
    "sg:address":"8a Shawcross Walk, Port Street",
    "sg:city":"Evesham",
    "sg:classifiers":[
        {
            "category":"Organizations",
            "subcategory":"Non-profit Organization",
            "type":"Services"
        }
    ],
    "sg:phone":"+44 1386 49110",
    "sg:postcode":"WR11 1AW",
    "sg:province":"Gloucestershire",
    "sg:tags":[
        "organisation",
        "voluntary",
        "charity"
    ],
    "wof:name":"National Schizophrenia Fellowship",
    "wof:placetype":"venue"
},
  "geometry": {"coordinates":[-1.9439690113,52.1063919067],"type":"Point"}
}