{
  "type": "Feature",
  "properties": {
    "addr:full":"2 Freight Cottages, Freight La Cranbrook Kent TN17 3BZ",
    "addr:housenumber":"2",
    "addr:postcode":"tn17 3bz",
    "iso:country":"GB",
    "sg:address":"2 Freight Cottages, Freight La",
    "sg:city":"Cranbrook",
    "sg:classifiers":[
        {
            "category":"Building & Trades",
            "subcategory":"Plumbing",
            "type":"Services"
        }
    ],
    "sg:phone":"+44 1580 714760",
    "sg:postcode":"TN17 3BZ",
    "sg:province":"Kent",
    "sg:tags":[
        "central",
        "heating"
    ],
    "wof:name":"Robertson S A",
    "wof:placetype":"venue"
},
  "geometry": {"coordinates":[0.535245,51.0965],"type":"Point"}
}