{
  "type": "Feature",
  "properties": {
    "addr:full":"Chettisham Garage, Lynn Road, Chettisham Ely Cambridgeshire CB6 1SA",
    "addr:postcode":"cb6 1sa",
    "addr:street":"Lynn Road",
    "iso:country":"GB",
    "sg:address":"Chettisham Garage, Lynn Road, Chettisham",
    "sg:city":"Ely",
    "sg:classifiers":[
        {
            "category":"Retail",
            "subcategory":"Auto Repair",
            "type":"Services"
        }
    ],
    "sg:postcode":"CB6 1SA",
    "sg:province":"Cambridgeshire",
    "sg:tags":[
        "body",
        "garage",
        "modification",
        "car"
    ],
    "wof:name":"David Lee",
    "wof:placetype":"venue"
},
  "geometry": {"coordinates":[0.275545001,52.422290802],"type":"Point"}
}