{
  "type": "Feature",
  "properties": {
    "addr:full":"85 Albert Street Edinburgh City of Edinburgh EH7 5LY",
    "addr:housenumber":"85",
    "addr:postcode":"eh7 5ly",
    "addr:street":"Albert Street",
    "iso:country":"GB",
    "sg:address":"85 Albert Street",
    "sg:city":"Edinburgh",
    "sg:classifiers":[
        {
            "category":"Fast Food",
            "type":"Food & Drink"
        }
    ],
    "sg:postcode":"EH7 5LY",
    "sg:province":"City of Edinburgh",
    "sg:tags":[
        "delivery"
    ],
    "wof:name":"Ian Wood",
    "wof:placetype":"venue"
},
  "geometry": {"coordinates":[-3.1748239994,55.9627418518],"type":"Point"}
}