{
  "type": "Feature",
  "properties": {
    "addr:full":"203 Argyle Street Glasgow Glasgow City G2 8BU",
    "addr:housenumber":"203",
    "addr:postcode":"g2 8bu",
    "addr:street":"Argyle Street",
    "iso:country":"GB",
    "sg:address":"203 Argyle Street",
    "sg:city":"Glasgow",
    "sg:classifiers":[
        {
            "category":"Food & Beverages",
            "subcategory":"Bakery",
            "type":"Retail Goods"
        }
    ],
    "sg:phone":"+44 141 221 0144",
    "sg:postcode":"G2 8BU",
    "sg:province":"Glasgow City",
    "sg:tags":[
        "pizza"
    ],
    "wof:name":"Pizza Hut",
    "wof:placetype":"venue"
},
  "geometry": {"coordinates":[-4.261059,55.858749],"type":"Point"}
}