{
  "type": "Feature",
  "properties": {
    "iso:country":"GB",
    "sg:address":"2 Sea View Road, Parkstone",
    "sg:city":"Poole",
    "sg:classifiers":[
        {
            "category":"Shopping",
            "subcategory":"News",
            "type":"Retail Goods"
        }
    ],
    "sg:phone":"+44 1202 742777",
    "sg:postcode":"BH12 3JU",
    "sg:province":"Dorset",
    "sg:tags":[
        "newsagent"
    ],
    "wof:name":"Viewpoint News",
    "wof:placetype":"venue"
},
  "geometry": {"coordinates":[-1.9529080391,50.7313346863],"type":"Point"}
}