{
  "type": "Feature",
  "properties": {
    "iso:country":"GB",
    "sg:address":"45 Collier Row Road",
    "sg:city":"Romford",
    "sg:classifiers":[
        {
            "category":"Education",
            "subcategory":"Library",
            "type":"Public Place"
        }
    ],
    "sg:phone":"+44 1708 760063",
    "sg:postcode":"RM5 3NR",
    "sg:province":"Essex",
    "sg:tags":[
        "book"
    ],
    "wof:name":"Collier Row Library",
    "wof:placetype":"venue"
},
  "geometry": {"coordinates":[0.168580994,51.5895271301],"type":"Point"}
}