{
  "type": "Feature",
  "properties": {
    "addr:full":"Columbus House, Allington Road, Eynesbury Huntingdon Bedfordshire PE19 2RD",
    "addr:postcode":"pe19 2rd",
    "addr:street":"Allington Road",
    "iso:country":"GB",
    "sg:address":"Columbus House, Allington Road, Eynesbury",
    "sg:city":"Huntingdon",
    "sg:classifiers":[
        {
            "category":"Shopping",
            "subcategory":"Mobile Phones",
            "type":"Retail Goods"
        }
    ],
    "sg:phone":"+44 1480 471600",
    "sg:postcode":"PE19 2RD",
    "sg:province":"Bedfordshire",
    "wof:name":"The Biz",
    "wof:placetype":"venue"
},
  "geometry": {"coordinates":[-0.2648940086,52.2170562744],"type":"Point"}
}