{
  "type": "Feature",
  "properties": {
    "iso:country":"GB",
    "sg:address":"121a High Street",
    "sg:city":"Waltham Cross",
    "sg:classifiers":[
        {
            "category":"Shopping",
            "subcategory":"Baby Store",
            "type":"Retail Goods"
        }
    ],
    "sg:phone":"+44 1992 627623",
    "sg:postcode":"EN8 7AN",
    "sg:province":"Essex",
    "sg:tags":[
        "babywear",
        "childrens"
    ],
    "wof:name":"Adams Childrenswear",
    "wof:placetype":"venue"
},
  "geometry": {"coordinates":[-0.032892,51.685253],"type":"Point"}
}