{
  "type": "Feature",
  "properties": {
    "iso:country":"GB",
    "sg:address":"111 Cleggs Lane, Little Hulton, Worlsey",
    "sg:city":"Manchester",
    "sg:classifiers":[
        {
            "category":"Retail",
            "subcategory":"Auto Repair",
            "type":"Services"
        }
    ],
    "sg:phone":"+44 161 799 6210",
    "sg:postcode":"M38 9RS",
    "sg:province":"Greater Manchester",
    "sg:tags":[
        "car",
        "servicing",
        "radiator"
    ],
    "wof:name":"B & J Radiators",
    "wof:placetype":"venue"
},
  "geometry": {"coordinates":[-2.419257,53.534889],"type":"Point"}
}