{
  "type": "Feature",
  "properties": {
    "iso:country":"GB",
    "sg:address":"68-70 Market Street",
    "sg:city":"Colne",
    "sg:classifiers":[
        {
            "category":"Community Center",
            "subcategory":"Social",
            "type":"Public Place"
        }
    ],
    "sg:phone":"+44 1282 859288",
    "sg:postcode":"BB8 0HS",
    "sg:province":"Lancashire",
    "sg:tags":[
        "frozen",
        "food",
        "freezer",
        "centre"
    ],
    "wof:name":"Jack Fulton",
    "wof:placetype":"venue"
},
  "geometry": {"coordinates":[-2.1653709412,53.8572692871],"type":"Point"}
}