{
  "type": "Feature",
  "properties": {
    "addr:full":"Connaught Plain Attleborough Norfolk NR17 2EJ",
    "addr:postcode":"nr17 2ej",
    "addr:street":"Connaught Plain",
    "iso:country":"GB",
    "sg:address":"Connaught Plain",
    "sg:city":"Attleborough",
    "sg:classifiers":[
        {
            "category":"Professional",
            "subcategory":"Employment Agencies",
            "type":"Services"
        }
    ],
    "sg:phone":"+44 1953 453644",
    "sg:postcode":"NR17 2EJ",
    "sg:province":"Norfolk",
    "sg:tags":[
        "consultant"
    ],
    "wof:name":"Breckland Employment Agency",
    "wof:placetype":"venue"
},
  "geometry": {"coordinates":[1.0146859884,52.5163993835],"type":"Point"}
}