{
  "type": "Feature",
  "properties": {
    "addr:full":"124 Duke St Birkenhead Merseyside L41 8BT",
    "addr:housenumber":"124",
    "addr:postcode":"l41 8bt",
    "addr:street":"Duke St",
    "iso:country":"GB",
    "sg:address":"124 Duke St",
    "sg:city":"Birkenhead",
    "sg:classifiers":[
        {
            "category":"Food & Beverages",
            "subcategory":"Meat & Fish",
            "type":"Retail Goods"
        }
    ],
    "sg:phone":"+44 151 652 7300",
    "sg:postcode":"L41 8BT",
    "sg:province":"Merseyside",
    "sg:tags":[
        "chip"
    ],
    "wof:name":"Choices",
    "wof:placetype":"venue"
},
  "geometry": {"coordinates":[-3.039543,53.396816],"type":"Point"}
}