{
  "type": "Feature",
  "properties": {
    "addr:full":"46 Clarges Street London Greater London W1J 7ER",
    "addr:housenumber":"46",
    "addr:postcode":"w1j 7er",
    "addr:street":"Clarges Street",
    "iso:country":"GB",
    "sg:address":"46 Clarges Street",
    "sg:city":"London",
    "sg:classifiers":[
        {
            "category":"Organizations",
            "subcategory":"Membership Organization",
            "type":"Services"
        }
    ],
    "sg:phone":"+44 20 7495 3656",
    "sg:postcode":"W1J 7ER",
    "sg:province":"Greater London",
    "sg:tags":[
        "club"
    ],
    "wof:name":"The Fox Club",
    "wof:placetype":"venue"
},
  "geometry": {"coordinates":[-0.1445309967,51.5062675476],"type":"Point"}
}