{
  "type": "Feature",
  "properties": {
    "iso:country":"GB",
    "sg:address":"Laird Forge Buildings, Gottries Road",
    "sg:city":"Irvine",
    "sg:classifiers":[
        {
            "category":"Museum",
            "subcategory":"Art Museum",
            "type":"Entertainment"
        },
        {
            "category":"Museum",
            "type":"Entertainment"
        }
    ],
    "sg:phone":"+44 1294 278283",
    "sg:postcode":"KA12 8QE",
    "sg:province":"North Ayrshire",
    "sg:tags":[
        "gallery"
    ],
    "wof:name":"Scottish Maritime Museum Trust",
    "wof:placetype":"venue"
},
  "geometry": {"coordinates":[-4.6732587814,55.6019744873],"type":"Point"}
}