{
  "type": "Feature",
  "properties": {
    "iso:country":"GB",
    "sg:address":"Unit 13 Osier Way, Park St Industrial Estate",
    "sg:city":"Aylesbury",
    "sg:classifiers":[
        {
            "category":"Freight",
            "type":"Transportation"
        }
    ],
    "sg:postcode":"HP20 1EB",
    "sg:province":"Buckinghamshire",
    "sg:tags":[
        "haulage",
        "road"
    ],
    "wof:name":"Derek Pell",
    "wof:placetype":"venue"
},
  "geometry": {"coordinates":[-0.7987769842,51.8178215027],"type":"Point"}
}