{
  "type": "Feature",
  "properties": {
    "addr:full":"Unit 19, Faraday Mill, Business Park, Faraday Rd Plymouth Devon PL4 0ST",
    "addr:housenumber":"unit 19",
    "addr:postcode":"pl4 0st",
    "addr:street":"Faraday Mill Business Park Faraday Rd",
    "iso:country":"GB",
    "sg:address":"Unit 19, Faraday Mill, Business Park, Faraday Rd",
    "sg:city":"Plymouth",
    "sg:classifiers":[
        {
            "category":"Personal",
            "type":"Services"
        }
    ],
    "sg:phone":"+44 1752 301449",
    "sg:postcode":"PL4 0ST",
    "sg:province":"Devon",
    "sg:tags":[
        "dressmaker"
    ],
    "wof:name":"The Sewing Factory",
    "wof:placetype":"venue"
},
  "geometry": {"coordinates":[-4.1134419441,50.3686485291],"type":"Point"}
}