{
  "type": "Feature",
  "properties": {
    "addr:full":"The Cottage, Green End, Pertenhall Bedford Bedfordshire MK44 2AX",
    "addr:postcode":"mk44 2ax",
    "addr:street":"Green End",
    "iso:country":"GB",
    "sg:address":"The Cottage, Green End, Pertenhall",
    "sg:city":"Bedford",
    "sg:classifiers":[
        {
            "category":"Building & Trades",
            "subcategory":"Landscaping Services",
            "type":"Services"
        }
    ],
    "sg:phone":"+44 1480 861653",
    "sg:postcode":"MK44 2AX",
    "sg:province":"Bedfordshire",
    "sg:tags":[
        "gardening"
    ],
    "wof:name":"Countrywide Grounds Maintenance",
    "wof:placetype":"venue"
},
  "geometry": {"coordinates":[-0.413934,52.279301],"type":"Point"}
}