{
  "type": "Feature",
  "properties": {
    "iso:country":"GB",
    "sg:address":"13 Oakleigh Drive, Croxley Grn",
    "sg:city":"Rickmansworth",
    "sg:classifiers":[
        {
            "category":"Building & Trades",
            "subcategory":"Construction",
            "type":"Services"
        }
    ],
    "sg:postcode":"WD3 3EE",
    "sg:province":"Hertfordshire",
    "sg:tags":[
        "tiling",
        "contractor"
    ],
    "wof:name":"Danny Brown",
    "wof:placetype":"venue"
},
  "geometry": {"coordinates":[-0.4379529953,51.6471672058],"type":"Point"}
}