{
  "type": "Feature",
  "properties": {
    "addr:full":"26 Woodrow Lane Bromsgrove Worcestershire B61 0PU",
    "addr:housenumber":"26",
    "addr:postcode":"b61 0pu",
    "addr:street":"Woodrow Lane",
    "iso:country":"GB",
    "sg:address":"26 Woodrow Lane",
    "sg:city":"Bromsgrove",
    "sg:classifiers":[
        {
            "category":"Autos & Motor Vehicles",
            "subcategory":"Recreational Vehicle Sales",
            "type":"Retail Goods"
        }
    ],
    "sg:phone":"+44 1527 833454",
    "sg:postcode":"B61 0PU",
    "sg:province":"Worcestershire",
    "sg:tags":[
        "caravans",
        "motorhomes",
        "trailer"
    ],
    "wof:name":"Sheila Haines",
    "wof:placetype":"venue"
},
  "geometry": {"coordinates":[-2.0552990437,52.3663215637],"type":"Point"}
}