{
  "type": "Feature",
  "properties": {
    "iso:country":"GB",
    "sg:address":"Trewilym Farm, Wolfs Castle, Hayes Castle",
    "sg:city":"Haverfordwest",
    "sg:classifiers":[
        {
            "category":"Farming",
            "subcategory":"Farm",
            "type":"Manufacturing & Wholesale Goods"
        }
    ],
    "sg:phone":"+44 1348 831381",
    "sg:postcode":"SA62 5AA",
    "sg:province":"Pembrokeshire",
    "sg:tags":[
        "mixed",
        "crop"
    ],
    "wof:name":"A W R Thomas & Son",
    "wof:placetype":"venue"
},
  "geometry": {"coordinates":[-5.07171,51.90453],"type":"Point"}
}