{
  "type": "Feature",
  "properties": {
    "iso:country":"GB",
    "sg:address":"19 Holder Road",
    "sg:city":"Aldershot",
    "sg:classifiers":[
        {
            "category":"Building & Trades",
            "subcategory":"Construction",
            "type":"Services"
        }
    ],
    "sg:phone":"+44 1252 333332",
    "sg:postcode":"GU12 4RH",
    "sg:province":"Hampshire",
    "sg:tags":[
        "restoration",
        "refurbishment"
    ],
    "wof:name":"Shenfield Associates Ltd.",
    "wof:placetype":"venue"
},
  "geometry": {"coordinates":[-0.738008,51.242855],"type":"Point"}
}