{
  "type": "Feature",
  "properties": {
    "addr:full":"5 Heath Gardens Halifax West Yorkshire HX3 0BD",
    "addr:housenumber":"5",
    "addr:postcode":"hx3 0bd",
    "addr:street":"Heath Gardens",
    "iso:country":"GB",
    "sg:address":"5 Heath Gardens",
    "sg:city":"Halifax",
    "sg:classifiers":[
        {
            "category":"Health Services",
            "subcategory":"Podiatrist",
            "type":"Services"
        }
    ],
    "sg:phone":"+44 1422 352926",
    "sg:postcode":"HX3 0BD",
    "sg:province":"West Yorkshire",
    "sg:tags":[
        "podiatrists",
        "chiropodist"
    ],
    "wof:name":"J Angela Sladdin",
    "wof:placetype":"venue"
},
  "geometry": {"coordinates":[-1.864446,53.710114],"type":"Point"}
}