{
  "type": "Feature",
  "properties": {
    "iso:country":"GB",
    "sg:address":"Wigwam Lane, Hucknall",
    "sg:city":"Nottingham",
    "sg:classifiers":[
        {
            "category":"Manufacturing",
            "subcategory":"Metals",
            "type":"Manufacturing & Wholesale Goods"
        },
        {
            "category":"Professional",
            "subcategory":"Engineering",
            "type":"Services"
        }
    ],
    "sg:phone":"+44 115 963 4020",
    "sg:postcode":"NG15 7TA",
    "sg:province":"Nottinghamshire",
    "sg:tags":[
        "steel",
        "fabricator",
        "precision",
        "engineer"
    ],
    "wof:name":"Triad Phoenix Engineering Ltd",
    "wof:placetype":"venue"
},
  "geometry": {"coordinates":[-1.209209,53.032398],"type":"Point"}
}