{
  "type": "Feature",
  "properties": {
    "iso:country":"GB",
    "sg:address":"Unit 1 Northfield Way, Aycliffe Indust Est",
    "sg:city":"Newton Aycliffe",
    "sg:classifiers":[
        {
            "category":"Government",
            "subcategory":"Post Office",
            "type":"Public Place"
        }
    ],
    "sg:phone":"+44 1325 301781",
    "sg:postcode":"DL5 6EJ",
    "sg:province":"Durham",
    "sg:tags":[
        "messenger",
        "courier"
    ],
    "wof:name":"Fastrack Parcels",
    "wof:placetype":"venue"
},
  "geometry": {"coordinates":[-1.579988,54.611778],"type":"Point"}
}