{
  "type": "Feature",
  "properties": {
    "iso:country":"GB",
    "sg:address":"Eardswick Lane, Minshull Vernon",
    "sg:city":"Crewe",
    "sg:classifiers":[
        {
            "category":"Building & Trades",
            "subcategory":"Landscaping Services",
            "type":"Services"
        },
        {
            "category":"Home & Garden",
            "subcategory":"Garden Supply",
            "type":"Retail Goods"
        }
    ],
    "sg:phone":"+44 1270 522482",
    "sg:postcode":"CW1 4RQ",
    "sg:province":"Cheshire",
    "sg:tags":[
        "planting",
        "nurseryman",
        "tree",
        "shrub"
    ],
    "wof:name":"Minshulls Nurserymen",
    "wof:placetype":"venue"
},
  "geometry": {"coordinates":[-2.484052,53.129093],"type":"Point"}
}