{
  "type": "Feature",
  "properties": {
    "addr:full":"85 Church Street Leigh Lancashire WN7 1AZ",
    "addr:housenumber":"85",
    "addr:postcode":"wn7 1az",
    "addr:street":"Church Street Leigh",
    "iso:country":"GB",
    "sg:address":"85 Church Street",
    "sg:city":"Leigh",
    "sg:classifiers":[
        {
            "category":"Professional",
            "subcategory":"Business Services",
            "type":"Services"
        }
    ],
    "sg:phone":"+44 1942 680065",
    "sg:postcode":"WN7 1AZ",
    "sg:province":"Lancashire",
    "sg:tags":[
        "trade"
    ],
    "wof:name":"Civil Engineering Contractors Association",
    "wof:placetype":"venue"
},
  "geometry": {"coordinates":[-2.5135779381,53.4976577759],"type":"Point"}
}