{
  "type": "Feature",
  "properties": {
    "addr:full":"Stallington Rd Stoke On Trent Staffordshire ST11 9QL",
    "addr:postcode":"st11 9ql",
    "addr:street":"Stallington Rd",
    "iso:country":"GB",
    "sg:address":"Stallington Rd",
    "sg:city":"Stoke On Trent",
    "sg:classifiers":[
        {
            "category":"Health Services",
            "subcategory":"Hospital",
            "type":"Services"
        }
    ],
    "sg:phone":"+44 1782 388222",
    "sg:postcode":"ST11 9QL",
    "sg:province":"Staffordshire",
    "wof:name":"Stallington Hall Combined Healthcare Learning Disabilities",
    "wof:placetype":"venue"
},
  "geometry": {"coordinates":[-2.064509,52.964775],"type":"Point"}
}