{
  "type": "Feature",
  "properties": {
    "iso:country":"GB",
    "sg:address":"3 The Triangle Shopping Centre",
    "sg:city":"Bridgend",
    "sg:classifiers":[
        {
            "category":"Fast Food",
            "type":"Food & Drink"
        }
    ],
    "sg:phone":"+44 1656 668556",
    "sg:postcode":"CF31 2LL",
    "sg:province":"Bridgend",
    "sg:tags":[
        "away",
        "meal",
        "outlet",
        "take"
    ],
    "wof:name":"Godfrey Takeaway",
    "wof:placetype":"venue"
},
  "geometry": {"coordinates":[-3.5462810993,51.506061554],"type":"Point"}
}