{
  "type": "Feature",
  "properties": {
    "iso:country":"GB",
    "sg:address":"170 Station Rd",
    "sg:city":"Addlestone",
    "sg:classifiers":[
        {
            "category":"Military Area",
            "subcategory":"Air Force Base",
            "type":"Public Place"
        }
    ],
    "sg:phone":"+44 1932 858858",
    "sg:postcode":"KT15 2BD",
    "sg:province":"Surrey",
    "sg:tags":[
        "taxi",
        "hire",
        "private"
    ],
    "wof:name":"Apollo Cars",
    "wof:placetype":"venue"
},
  "geometry": {"coordinates":[-0.485033,51.372314],"type":"Point"}
}