{
  "type": "Feature",
  "properties": {
    "iso:country":"GB",
    "sg:address":"Berries Rd, Cookham",
    "sg:city":"Maidenhead",
    "sg:classifiers":[
        {
            "category":"Health Services",
            "subcategory":"Nursing And Care Facility",
            "type":"Services"
        }
    ],
    "sg:phone":"+44 1628 810557",
    "sg:postcode":"SL6 9SD",
    "sg:province":"Berkshire",
    "sg:tags":[
        "home"
    ],
    "wof:name":"The Cookham Riverside",
    "wof:placetype":"venue"
},
  "geometry": {"coordinates":[-0.707164,51.557995],"type":"Point"}
}