{
  "type": "Feature",
  "properties": {
    "iso:country":"GB",
    "sg:address":"School Walk, Bestwood Village",
    "sg:city":"Nottingham",
    "sg:classifiers":[
        {
            "category":"Health Services",
            "subcategory":"Nursing And Care Facility",
            "type":"Services"
        }
    ],
    "sg:phone":"+44 115 977 0331",
    "sg:postcode":"NG6 8UU",
    "sg:province":"Nottinghamshire",
    "sg:tags":[
        "home"
    ],
    "wof:name":"Hawthorne Nursing Home For The Elderly",
    "wof:placetype":"venue"
},
  "geometry": {"coordinates":[-1.1785390377,53.0245018005],"type":"Point"}
}