{
  "type": "Feature",
  "properties": {
    "addr:full":"4 King Street Truro Cornwall TR1 2RA",
    "addr:housenumber":"4",
    "addr:postcode":"tr1 2ra",
    "addr:street":"King Street",
    "iso:country":"GB",
    "sg:address":"4 King Street",
    "sg:city":"Truro",
    "sg:classifiers":[
        {
            "category":"Food & Beverages",
            "subcategory":"Fruits & Vegetables",
            "type":"Retail Goods"
        }
    ],
    "sg:phone":"+44 1872 273672",
    "sg:postcode":"TR1 2RA",
    "sg:province":"Cornwall",
    "sg:tags":[
        "greengrocer"
    ],
    "wof:name":"Trim (Retail) Ltd.",
    "wof:placetype":"venue"
},
  "geometry": {"coordinates":[-5.052169,50.263882],"type":"Point"}
}