{
  "type": "Feature",
  "properties": {
    "addr:full":"186 Ferndale Rd Swindon Wiltshire SN2 1EY",
    "addr:housenumber":"186",
    "addr:postcode":"sn2 1ey",
    "addr:street":"Ferndale Rd",
    "iso:country":"GB",
    "sg:address":"186 Ferndale Rd",
    "sg:city":"Swindon",
    "sg:classifiers":[
        {
            "category":"Building & Trades",
            "subcategory":"Plumbing",
            "type":"Services"
        }
    ],
    "sg:phone":"+44 1793 436312",
    "sg:postcode":"SN2 1EY",
    "sg:province":"Wiltshire",
    "sg:tags":[
        "central",
        "heating"
    ],
    "wof:name":"Glen Benson",
    "wof:placetype":"venue"
},
  "geometry": {"coordinates":[-1.7853759527,51.5712013245],"type":"Point"}
}