{
  "type": "Feature",
  "properties": {
    "addr:full":"Dolau Gwyn, Bryncrug Tywyn Gwynedd LL36 9UL",
    "addr:postcode":"ll36 9ul",
    "iso:country":"GB",
    "sg:address":"Dolau Gwyn, Bryncrug",
    "sg:city":"Tywyn",
    "sg:classifiers":[
        {
            "category":"Retail",
            "subcategory":"Veterinary Services",
            "type":"Services"
        }
    ],
    "sg:phone":"+44 1654 710948",
    "sg:postcode":"LL36 9UL",
    "sg:province":"Gwynedd",
    "sg:tags":[
        "surgeon"
    ],
    "wof:name":"E Williams",
    "wof:placetype":"venue"
},
  "geometry": {"coordinates":[-4.0884189606,52.5865859985],"type":"Point"}
}