{
  "type": "Feature",
  "properties": {
    "iso:country":"GB",
    "sg:address":"140 English Street",
    "sg:city":"Hull",
    "sg:classifiers":[
        {
            "category":"Retail",
            "subcategory":"Auto Repair",
            "type":"Services"
        }
    ],
    "sg:phone":"+44 1482 225067",
    "sg:postcode":"HU3 2BT",
    "sg:province":"East Riding of Yorkshire",
    "sg:tags":[
        "engine",
        "car",
        "specialist"
    ],
    "wof:name":"Engine Gearbox Centres 1996",
    "wof:placetype":"venue"
},
  "geometry": {"coordinates":[-0.3505809903,53.7365074158],"type":"Point"}
}