{
  "type": "Feature",
  "properties": {
    "iso:country":"GB",
    "sg:address":"1, Norman Court, 11 Grape Lane",
    "sg:city":"York",
    "sg:classifiers":[
        {
            "category":"Shopping",
            "subcategory":"Clothing, Apparel, & Fashions",
            "type":"Retail Goods"
        },
        {
            "category":"Shopping",
            "subcategory":"Used Merchandise",
            "type":"Retail Goods"
        }
    ],
    "sg:phone":"+44 1904 631565",
    "sg:postcode":"YO1 7HU",
    "sg:province":"North Yorkshire",
    "sg:tags":[
        "shop",
        "second-hand"
    ],
    "wof:name":"Priestleys Vintage Clothing",
    "wof:placetype":"venue"
},
  "geometry": {"coordinates":[-1.082215,53.960804],"type":"Point"}
}