{
  "type": "Feature",
  "properties": {
    "addr:full":"1-3 Quicks Road London Greater London SW19 1EZ",
    "addr:housenumber":"1-3",
    "addr:postcode":"sw19 1ez",
    "addr:street":"Quicks Road",
    "iso:country":"GB",
    "sg:address":"1-3 Quicks Road",
    "sg:city":"London",
    "sg:classifiers":[
        {
            "category":"Professional",
            "subcategory":"Printing & Photocopies",
            "type":"Services"
        }
    ],
    "sg:phone":"+44 20 8544 1445",
    "sg:postcode":"SW19 1EZ",
    "sg:province":"Greater London",
    "sg:tags":[
        "printer"
    ],
    "wof:name":"Positive Images U K",
    "wof:placetype":"venue"
},
  "geometry": {"coordinates":[-0.18749,51.419121],"type":"Point"}
}