{
  "type": "Feature",
  "properties": {
    "addr:full":"47 Bear Street Barnstaple Devon EX32 7DB",
    "addr:housenumber":"47",
    "addr:postcode":"ex32 7db",
    "addr:street":"Bear Street",
    "iso:country":"GB",
    "sg:address":"47 Bear Street",
    "sg:city":"Barnstaple",
    "sg:classifiers":[
        {
            "category":"Food & Beverages",
            "subcategory":"Meat & Fish",
            "type":"Retail Goods"
        }
    ],
    "sg:phone":"+44 1271 342232",
    "sg:postcode":"EX32 7DB",
    "sg:province":"Devon",
    "sg:tags":[
        "chip"
    ],
    "wof:name":"The Silver Cod",
    "wof:placetype":"venue"
},
  "geometry": {"coordinates":[-4.0575819016,51.0809860229],"type":"Point"}
}