{
  "type": "Feature",
  "properties": {
    "addr:full":"35 Sutton Avenue Tamworth Staffordshire B78 3JZ",
    "addr:housenumber":"35",
    "addr:postcode":"b78 3jz",
    "addr:street":"Sutton Avenue",
    "iso:country":"GB",
    "sg:address":"35 Sutton Avenue",
    "sg:city":"Tamworth",
    "sg:classifiers":[
        {
            "category":"Home & Garden",
            "subcategory":"Household Appliances",
            "type":"Retail Goods"
        }
    ],
    "sg:phone":"+44 1827 66023",
    "sg:postcode":"B78 3JZ",
    "sg:province":"Staffordshire",
    "sg:tags":[
        "electrical"
    ],
    "wof:name":"Geoffrey Dolman",
    "wof:placetype":"venue"
},
  "geometry": {"coordinates":[-1.731935,52.618916],"type":"Point"}
}