{
  "type": "Feature",
  "properties": {
    "addr:full":"28 Wear Industrial Estate, Wear Washington Durham NE38 9BZ",
    "addr:housenumber":"28",
    "addr:postcode":"ne38 9bz",
    "addr:street":"Wear Industrial;Washington",
    "iso:country":"GB",
    "sg:address":"28 Wear Industrial Estate, Wear",
    "sg:city":"Washington",
    "sg:classifiers":[
        {
            "category":"Home & Garden",
            "subcategory":"Hardware",
            "type":"Retail Goods"
        }
    ],
    "sg:phone":"+44 191 416 4477",
    "sg:postcode":"NE38 9BZ",
    "sg:province":"Durham",
    "sg:tags":[
        "equipment",
        "central",
        "heating"
    ],
    "wof:name":"Gledhill (Water Storage) Ltd.",
    "wof:placetype":"venue"
},
  "geometry": {"coordinates":[-1.5387109518,54.8848876953],"type":"Point"}
}