{
  "type": "Feature",
  "properties": {
    "addr:full":"54 Sheppenhall Gro, Aston Nantwich Cheshire CW5 8DF",
    "addr:housenumber":"54",
    "addr:postcode":"cw5 8df",
    "addr:street":"Sheppenhall Gro Aston",
    "iso:country":"GB",
    "sg:address":"54 Sheppenhall Gro, Aston",
    "sg:city":"Nantwich",
    "sg:classifiers":[
        {
            "category":"Education",
            "subcategory":"Special Training",
            "type":"Public Place"
        }
    ],
    "sg:postcode":"CW5 8DF",
    "sg:province":"Cheshire",
    "sg:tags":[
        "school",
        "language"
    ],
    "wof:name":"The Scott Languages Bureau",
    "wof:placetype":"venue"
},
  "geometry": {"coordinates":[-2.5758199692,53.0143814087],"type":"Point"}
}