{
  "type": "Feature",
  "properties": {
    "addr:full":"Pike End Road, Rishworth Sowerby Bridge West Yorkshire HX6 4QS",
    "addr:postcode":"hx6 4qs",
    "addr:street":"Pike End Road;West",
    "iso:country":"GB",
    "sg:address":"Pike End Road, Rishworth",
    "sg:city":"Sowerby Bridge",
    "sg:classifiers":[
        {
            "category":"Farming",
            "subcategory":"Livestock Farm",
            "type":"Manufacturing & Wholesale Goods"
        },
        {
            "category":"Farming",
            "subcategory":"Farm",
            "type":"Manufacturing & Wholesale Goods"
        }
    ],
    "sg:postcode":"HX6 4QS",
    "sg:province":"West Yorkshire",
    "sg:tags":[
        "mixed",
        "crop",
        "others"
    ],
    "wof:name":"Daniel Stott",
    "wof:placetype":"venue"
},
  "geometry": {"coordinates":[-1.9575929642,53.6541252136],"type":"Point"}
}