{
  "type": "Feature",
  "properties": {
    "addr:full":"135 Wistaston Green Rd Crewe Cheshire CW2 8RW",
    "addr:housenumber":"135",
    "addr:postcode":"cw2 8rw",
    "addr:street":"Wistaston Green Rd",
    "iso:country":"GB",
    "sg:address":"135 Wistaston Green Rd",
    "sg:city":"Crewe",
    "sg:classifiers":[
        {
            "category":"Health Services",
            "subcategory":"Podiatrist",
            "type":"Services"
        }
    ],
    "sg:phone":"+44 1270 668851",
    "sg:postcode":"CW2 8RW",
    "sg:province":"Cheshire",
    "sg:tags":[
        "podiatrists",
        "chiropodist"
    ],
    "wof:name":"R W Wood",
    "wof:placetype":"venue"
},
  "geometry": {"coordinates":[-2.477529,53.089851],"type":"Point"}
}