{
  "type": "Feature",
  "properties": {
    "iso:country":"GB",
    "sg:address":"25 Donaldson Cres, Southbank Business Park",
    "sg:city":"Glasgow",
    "sg:classifiers":[
        {
            "category":"Professional",
            "subcategory":"Art Services",
            "type":"Services"
        }
    ],
    "sg:phone":"+44 141 777 7900",
    "sg:postcode":"G66 1XF",
    "sg:province":"East Dunbartonshire",
    "sg:tags":[
        "photographer"
    ],
    "wof:name":"McCandlish & Robson Photographers",
    "wof:placetype":"venue"
},
  "geometry": {"coordinates":[-4.158594,55.933929],"type":"Point"}
}