{
  "type": "Feature",
  "properties": {
    "iso:country":"GB",
    "sg:address":"27 Orchard Street",
    "sg:city":"Bristol",
    "sg:classifiers":[
        {
            "category":"Banks & Credit Unions",
            "subcategory":"Bank",
            "type":"Services"
        }
    ],
    "sg:phone":"+44 117 929 9881",
    "sg:postcode":"BS1 5EH",
    "sg:province":"City of Bristol",
    "sg:tags":[
        "broker",
        "mortgage"
    ],
    "wof:name":"The Hartwood Group",
    "wof:placetype":"venue"
},
  "geometry": {"coordinates":[-2.599657,51.453686],"type":"Point"}
}