{
  "type": "Feature",
  "properties": {
    "addr:full":"Marforge House, 73 High Street, Codicote Hitchin Hertfordshire SG4 8XE",
    "addr:housenumber":"73",
    "addr:postcode":"sg4 8xe",
    "addr:street":"High Street",
    "iso:country":"GB",
    "sg:address":"Marforge House, 73 High Street, Codicote",
    "sg:city":"Hitchin",
    "sg:classifiers":[
        {
            "category":"Professional",
            "subcategory":"Business Services",
            "type":"Services"
        }
    ],
    "sg:phone":"+44 1438 821500",
    "sg:postcode":"SG4 8XE",
    "sg:province":"Hertfordshire",
    "sg:tags":[
        "import",
        "export",
        "agent"
    ],
    "wof:name":"Streamline Foods Ltd.",
    "wof:placetype":"venue"
},
  "geometry": {"coordinates":[-0.236007,51.849602],"type":"Point"}
}