{
  "type": "Feature",
  "properties": {
    "addr:full":"University Of Leeds Union Buildings Leeds West Yorkshire LS1 1UH",
    "addr:postcode":"ls1 1uh",
    "addr:street":"Union Buildings Leeds West",
    "iso:country":"GB",
    "sg:address":"University Of Leeds Union Buildings",
    "sg:city":"Leeds",
    "sg:classifiers":[
        {
            "category":"Health Services",
            "subcategory":"Optometrist",
            "type":"Services"
        }
    ],
    "sg:phone":"+44 113 245 5618",
    "sg:postcode":"LS1 1UH",
    "sg:province":"West Yorkshire",
    "sg:tags":[
        "optician"
    ],
    "wof:name":"University Vision Ltd.",
    "wof:placetype":"venue"
},
  "geometry": {"coordinates":[-1.546587,53.794495],"type":"Point"}
}