{
  "type": "Feature",
  "properties": {
    "iso:country":"GB",
    "sg:address":"Millhouse Garage, High Lane West, West Hallam",
    "sg:city":"Ilkeston",
    "sg:classifiers":[
        {
            "category":"Autos & Motor Vehicles",
            "subcategory":"Automobile Sales",
            "type":"Retail Goods"
        }
    ],
    "sg:phone":"+44 115 930 2839",
    "sg:postcode":"DE7 6HQ",
    "sg:province":"Derbyshire",
    "sg:tags":[
        "car"
    ],
    "wof:name":"Millhouse of West Hallam Ltd.",
    "wof:placetype":"venue"
},
  "geometry": {"coordinates":[-1.3589890003,52.9667549133],"type":"Point"}
}