{
  "type": "Feature",
  "properties": {
    "addr:full":"7 Harborne Park Road, Harborne Birmingham West Midlands B17 0DE",
    "addr:housenumber":"7",
    "addr:postcode":"b17 0de",
    "addr:street":"Harborne Park Road",
    "iso:country":"GB",
    "sg:address":"7 Harborne Park Road, Harborne",
    "sg:city":"Birmingham",
    "sg:classifiers":[
        {
            "category":"Shopping",
            "subcategory":"Clothing, Apparel, & Fashions",
            "type":"Retail Goods"
        }
    ],
    "sg:phone":"+44 121 428 2689",
    "sg:postcode":"B17 0DE",
    "sg:province":"West Midlands",
    "sg:tags":[
        "menswear"
    ],
    "wof:name":"Republic Menswear",
    "wof:placetype":"venue"
},
  "geometry": {"coordinates":[-1.9570089579,52.4578437805],"type":"Point"}
}