{
  "type": "Feature",
  "properties": {
    "addr:full":"202 Mitcham Road London Greater London SW17 9NN",
    "addr:housenumber":"202",
    "addr:postcode":"sw17 9nn",
    "addr:street":"Mitcham Road",
    "iso:country":"GB",
    "sg:address":"202 Mitcham Road",
    "sg:city":"London",
    "sg:classifiers":[
        {
            "category":"Shopping",
            "subcategory":"Florist",
            "type":"Retail Goods"
        }
    ],
    "sg:phone":"+44 20 8672 3144",
    "sg:postcode":"SW17 9NN",
    "sg:province":"Greater London",
    "wof:name":"Matthews",
    "wof:placetype":"venue"
},
  "geometry": {"coordinates":[-0.160726,51.423035],"type":"Point"}
}