{
  "type": "Feature",
  "properties": {
    "addr:full":"163 Fleet Rd Fleet Dorset GU13 8PD",
    "addr:housenumber":"163",
    "addr:postcode":"gu13 8pd",
    "addr:street":"Fleet Rd",
    "iso:country":"GB",
    "sg:address":"163 Fleet Rd",
    "sg:city":"Fleet",
    "sg:classifiers":[
        {
            "category":"Real Estate",
            "subcategory":"Real Estate Agent",
            "type":"Services"
        }
    ],
    "sg:phone":"+44 1252 811352",
    "sg:postcode":"GU13 8PD",
    "sg:province":"Dorset",
    "wof:name":"Rogers Property Co.Ltd",
    "wof:placetype":"venue"
},
  "geometry": {"coordinates":[-0.839821,51.282887],"type":"Point"}
}