{
  "type": "Feature",
  "properties": {
    "addr:full":"64 Grafton Road Worcester Park Surrey KT4 7QP",
    "addr:housenumber":"64",
    "addr:postcode":"kt4 7qp",
    "addr:street":"Grafton Road",
    "iso:country":"GB",
    "sg:address":"64 Grafton Road",
    "sg:city":"Worcester Park",
    "sg:classifiers":[
        {
            "category":"Building & Trades",
            "subcategory":"Construction",
            "type":"Services"
        }
    ],
    "sg:phone":"+44 20 8330 1387",
    "sg:postcode":"KT4 7QP",
    "sg:province":"Surrey",
    "sg:tags":[
        "flooring"
    ],
    "wof:name":"G & A Carpets",
    "wof:placetype":"venue"
},
  "geometry": {"coordinates":[-0.2653050125,51.3725814819],"type":"Point"}
}