{
  "type": "Feature",
  "properties": {
    "iso:country":"GB",
    "sg:address":"Central Ho, 75-79 Park St",
    "sg:city":"Camberley",
    "sg:classifiers":[
        {
            "category":"Professional",
            "subcategory":"Management & Consulting",
            "type":"Services"
        }
    ],
    "sg:phone":"+44 1276 675777",
    "sg:postcode":"GU15 3PT",
    "sg:province":"Berkshire",
    "sg:tags":[
        "consultant",
        "business"
    ],
    "wof:name":"Aspect International Consulting",
    "wof:placetype":"venue"
},
  "geometry": {"coordinates":[-0.7342299819,51.3362159729],"type":"Point"}
}