{
  "type": "Feature",
  "properties": {
    "addr:full":"15a Market Street, Fordham Ely Cambridgeshire CB7 5LQ",
    "addr:housenumber":"15a",
    "addr:postcode":"cb7 5lq",
    "addr:street":"Market Street",
    "iso:country":"GB",
    "sg:address":"15a Market Street, Fordham",
    "sg:city":"Ely",
    "sg:classifiers":[
        {
            "category":"Personal",
            "subcategory":"Beauty Salon",
            "type":"Services"
        }
    ],
    "sg:phone":"+44 1638 720272",
    "sg:postcode":"CB7 5LQ",
    "sg:province":"Cambridgeshire",
    "sg:tags":[
        "lady",
        "hairdresser"
    ],
    "wof:name":"Dianne's Hairdressers",
    "wof:placetype":"venue"
},
  "geometry": {"coordinates":[0.384649,52.306461],"type":"Point"}
}