{
  "type": "Feature",
  "properties": {
    "addr:full":"2a Flowers Way Clacton On Sea Essex CO15 2EP",
    "addr:housenumber":"2a",
    "addr:postcode":"co15 2ep",
    "addr:street":"Flowers Way",
    "iso:country":"GB",
    "sg:address":"2a Flowers Way",
    "sg:city":"Clacton On Sea",
    "sg:classifiers":[
        {
            "category":"Arts & Performance",
            "subcategory":"Music",
            "type":"Entertainment"
        }
    ],
    "sg:phone":"+44 20 8556 5418",
    "sg:postcode":"CO15 2EP",
    "sg:province":"Essex",
    "sg:tags":[
        "mobile",
        "disco"
    ],
    "wof:name":"Steve's Country Disco",
    "wof:placetype":"venue"
},
  "geometry": {"coordinates":[1.118170023,51.7765769958],"type":"Point"}
}