{
  "type": "Feature",
  "properties": {
    "addr:full":"20 Pack Lane, Oakley Basingstoke Hampshire RG23 7BE",
    "addr:housenumber":"20",
    "addr:postcode":"rg23 7be",
    "addr:street":"Pack Lane",
    "iso:country":"GB",
    "sg:address":"20 Pack Lane, Oakley",
    "sg:city":"Basingstoke",
    "sg:classifiers":[
        {
            "category":"Building & Trades",
            "subcategory":"Landscaping Services",
            "type":"Services"
        }
    ],
    "sg:phone":"+44 1256 780658",
    "sg:postcode":"RG23 7BE",
    "sg:province":"Hampshire",
    "sg:tags":[
        "gardening"
    ],
    "wof:name":"Bob Gregory",
    "wof:placetype":"venue"
},
  "geometry": {"coordinates":[-1.1736619473,51.2554893494],"type":"Point"}
}