{
  "type": "Feature",
  "properties": {
    "iso:country":"GB",
    "sg:address":"Windsor Cottage, Pine Gro",
    "sg:city":"Weybridge",
    "sg:classifiers":[
        {
            "category":"Building & Trades",
            "subcategory":"Construction",
            "type":"Services"
        }
    ],
    "sg:phone":"+44 1932 846742",
    "sg:postcode":"KT13 9AS",
    "sg:province":"Surrey",
    "sg:tags":[
        "roofing"
    ],
    "wof:name":"Harvey Roofing",
    "wof:placetype":"venue"
},
  "geometry": {"coordinates":[-0.4510439932,51.3669166565],"type":"Point"}
}