{
  "type": "Feature",
  "properties": {
    "iso:country":"GB",
    "sg:address":"18 Oakland Ave",
    "sg:city":"Manchester",
    "sg:classifiers":[
        {
            "category":"Building & Trades",
            "subcategory":"Construction",
            "type":"Services"
        }
    ],
    "sg:phone":"+44 161 442 2212",
    "sg:postcode":"M19 1LB",
    "sg:province":"Greater Manchester",
    "sg:tags":[
        "contractor"
    ],
    "wof:name":"Fennelly & Sons Maintenance Gangs Ltd",
    "wof:placetype":"venue"
},
  "geometry": {"coordinates":[-2.210319,53.427361],"type":"Point"}
}