{
  "type": "Feature",
  "properties": {
    "iso:country":"GB",
    "sg:address":"Tower Cottage, The Street",
    "sg:city":"Canterbury",
    "sg:classifiers":[
        {
            "category":"Bus Charters",
            "type":"Transportation"
        }
    ],
    "sg:phone":"+44 1233 740440",
    "sg:postcode":"CT4 8HJ",
    "sg:province":"Kent",
    "sg:tags":[
        "hire",
        "coach"
    ],
    "wof:name":"J H & D Smith",
    "wof:placetype":"venue"
},
  "geometry": {"coordinates":[0.8964999914,51.2273712158],"type":"Point"}
}