{
  "type": "Feature",
  "properties": {
    "iso:country":"GB",
    "sg:address":"Monteviot Nurseries, Ancrum",
    "sg:city":"Jedburgh",
    "sg:classifiers":[
        {
            "category":"Organizations",
            "subcategory":"Non-profit Organization",
            "type":"Services"
        }
    ],
    "sg:phone":"+44 1835 830750",
    "sg:postcode":"TD8 6TU",
    "sg:province":"Scottish Borders",
    "sg:tags":[
        "organisation",
        "voluntary",
        "charity"
    ],
    "wof:name":"Borders Forest Trust (The)",
    "wof:placetype":"venue"
},
  "geometry": {"coordinates":[-2.554624,55.477718],"type":"Point"}
}