{
  "type": "Feature",
  "properties": {
    "addr:full":"3 Bexhill Centre, Thalia House, London Road Bexhill-on-sea East Sussex TN39 3JT",
    "addr:housenumber":"3",
    "addr:postcode":"tn39 3jt",
    "addr:street":"Bexhill Centre Thalia;London Road",
    "iso:country":"GB",
    "sg:address":"3 Bexhill Centre, Thalia House, London Road",
    "sg:city":"Bexhill-on-sea",
    "sg:classifiers":[
        {
            "category":"Organizations",
            "subcategory":"Non-profit Organization",
            "type":"Services"
        }
    ],
    "sg:phone":"+44 1424 213583",
    "sg:postcode":"TN39 3JT",
    "sg:province":"East Sussex",
    "sg:tags":[
        "organisation",
        "voluntary",
        "charity"
    ],
    "wof:name":"British Red Cross",
    "wof:placetype":"venue"
},
  "geometry": {"coordinates":[0.46999,50.841549],"type":"Point"}
}