{
  "type": "Feature",
  "properties": {
    "addr:full":"8 Mill Street Kidlington Buckinghamshire OX5 2EF",
    "addr:housenumber":"8",
    "addr:postcode":"ox5 2ef",
    "addr:street":"Mill Street",
    "iso:country":"GB",
    "sg:address":"8 Mill Street",
    "sg:city":"Kidlington",
    "sg:classifiers":[
        {
            "category":"Social Services",
            "subcategory":"Retirement Home",
            "type":"Services"
        }
    ],
    "sg:phone":"+44 1865 841859",
    "sg:postcode":"OX5 2EF",
    "sg:province":"Buckinghamshire",
    "sg:tags":[
        "residential",
        "care"
    ],
    "wof:name":"Glebe House",
    "wof:placetype":"venue"
},
  "geometry": {"coordinates":[-1.2819490433,51.8253097534],"type":"Point"}
}