{
  "type": "Feature",
  "properties": {
    "iso:country":"GB",
    "sg:address":"Crown Rd, Christchurch",
    "sg:city":"Wisbech",
    "sg:classifiers":[
        {
            "category":"Education",
            "subcategory":"School",
            "type":"Public Place"
        }
    ],
    "sg:phone":"+44 1354 638229",
    "sg:postcode":"PE14 9NA",
    "sg:province":"Cambridgeshire",
    "sg:tags":[
        "local",
        "authority"
    ],
    "wof:name":"Townley Primary School",
    "wof:placetype":"venue"
},
  "geometry": {"coordinates":[0.19907,52.549179],"type":"Point"}
}