{
  "type": "Feature",
  "properties": {
    "addr:full":"124/125 Princes St Edinburgh City of Edinburgh EH2 4AD",
    "addr:housenumber":"124 / 125",
    "addr:postcode":"eh2 4ad",
    "addr:street":"Princes St",
    "iso:country":"GB",
    "sg:address":"124/125 Princes St",
    "sg:city":"Edinburgh",
    "sg:classifiers":[
        {
            "category":"Professional",
            "subcategory":"Art Services",
            "type":"Services"
        }
    ],
    "sg:phone":"+44 131 220 3322",
    "sg:postcode":"EH2 4AD",
    "sg:province":"City of Edinburgh",
    "sg:tags":[
        "consultant",
        "design"
    ],
    "wof:name":"B D G McColl (Scotland) Ltd",
    "wof:placetype":"venue"
},
  "geometry": {"coordinates":[-3.204126,55.950912],"type":"Point"}
}