{
  "type": "Feature",
  "properties": {
    "iso:country":"GB",
    "sg:address":"47 Leopald Street, Orchard Square",
    "sg:city":"Sheffield",
    "sg:classifiers":[
        {
            "category":"Shopping",
            "subcategory":"Comic Books",
            "type":"Retail Goods"
        }
    ],
    "sg:phone":"+44 114 270 1588",
    "sg:postcode":"S1 2GY",
    "sg:province":"South Yorkshire",
    "sg:tags":[
        "jeweller"
    ],
    "wof:name":"Andino Jewellery Gallery",
    "wof:placetype":"venue"
},
  "geometry": {"coordinates":[-1.471085,53.381802],"type":"Point"}
}