{
  "type": "Feature",
  "properties": {
    "addr:full":"4th Floor South Point, South Accommodation Road Leeds West Yorkshire LS10 1PP",
    "addr:housenumber":"4th floor south",
    "addr:postcode":"ls10 1pp",
    "addr:street":"Point South Accommodation Road",
    "iso:country":"GB",
    "sg:address":"4th Floor South Point, South Accommodation Road",
    "sg:city":"Leeds",
    "sg:classifiers":[
        {
            "category":"Real Estate",
            "subcategory":"Surveying",
            "type":"Services"
        }
    ],
    "sg:postcode":"LS10 1PP",
    "sg:province":"West Yorkshire",
    "sg:tags":[
        "surveyor",
        "valuer"
    ],
    "wof:name":"Chris Baker Associates",
    "wof:placetype":"venue"
},
  "geometry": {"coordinates":[-1.5308400393,53.786239624],"type":"Point"}
}