{
  "type": "Feature",
  "properties": {
    "addr:full":"34 Hartington Place Edinburgh City of Edinburgh EH10 4LE",
    "addr:housenumber":"34",
    "addr:postcode":"eh10 4le",
    "addr:street":"Hartington Place Edinburgh",
    "iso:country":"GB",
    "sg:address":"34 Hartington Place",
    "sg:city":"Edinburgh",
    "sg:classifiers":[
        {
            "category":"Organizations",
            "subcategory":"Community Association",
            "type":"Services"
        }
    ],
    "sg:phone":"+44 131 229 7658",
    "sg:postcode":"EH10 4LE",
    "sg:province":"City of Edinburgh",
    "sg:tags":[
        "society",
        "housing"
    ],
    "wof:name":"Outlook",
    "wof:placetype":"venue"
},
  "geometry": {"coordinates":[-3.2115390301,55.9379234314],"type":"Point"}
}