{
  "type": "Feature",
  "properties": {
    "addr:full":"55 Durrants Lane Berkhamsted Bedfordshire HP4 3PL",
    "addr:housenumber":"55",
    "addr:postcode":"hp4 3pl",
    "addr:street":"Durrants Lane",
    "iso:country":"GB",
    "sg:address":"55 Durrants Lane",
    "sg:city":"Berkhamsted",
    "sg:classifiers":[
        {
            "category":"Manufacturing",
            "subcategory":"Signs",
            "type":"Manufacturing & Wholesale Goods"
        }
    ],
    "sg:phone":"+44 1442 871204",
    "sg:postcode":"HP4 3PL",
    "sg:province":"Bedfordshire",
    "sg:tags":[
        "writer"
    ],
    "wof:name":"David Woollacott",
    "wof:placetype":"venue"
},
  "geometry": {"coordinates":[-0.589276,51.762341],"type":"Point"}
}