{
  "type": "Feature",
  "properties": {
    "iso:country":"GB",
    "sg:address":"247 Kensington",
    "sg:city":"Liverpool",
    "sg:classifiers":[
        {
            "category":"Home & Garden",
            "subcategory":"Carpets & Floor Coverings",
            "type":"Retail Goods"
        }
    ],
    "sg:phone":"+44 151 283 2882",
    "sg:postcode":"L7 2RG",
    "sg:province":"Merseyside",
    "sg:tags":[
        "carpets",
        "retailer",
        "rug",
        "matting"
    ],
    "wof:name":"W E & J E Longstaffe",
    "wof:placetype":"venue"
},
  "geometry": {"coordinates":[-2.947037,53.412216],"type":"Point"}
}