{
  "type": "Feature",
  "properties": {
    "iso:country":"GB",
    "sg:address":"25 Georgina Close, Totton",
    "sg:city":"Southampton",
    "sg:classifiers":[
        {
            "category":"Military Area",
            "subcategory":"Air Force Base",
            "type":"Public Place"
        }
    ],
    "sg:postcode":"SO40 2BE",
    "sg:province":"Hampshire",
    "sg:tags":[
        "taxi",
        "hire",
        "private"
    ],
    "wof:name":"Inter Airport Cars",
    "wof:placetype":"venue"
},
  "geometry": {"coordinates":[-1.5238599777,50.9258003235],"type":"Point"}
}