{
  "type": "Feature",
  "properties": {
    "addr:full":"Castleton Farm Banff Aberdeenshire AB45 3PD",
    "addr:postcode":"ab45 3pd",
    "iso:country":"GB",
    "sg:address":"Castleton Farm",
    "sg:city":"Banff",
    "sg:classifiers":[
        {
            "category":"Farming",
            "subcategory":"Farm",
            "type":"Manufacturing & Wholesale Goods"
        }
    ],
    "sg:postcode":"AB45 3PD",
    "sg:province":"Aberdeenshire",
    "sg:tags":[
        "mixed",
        "crop"
    ],
    "wof:name":"William Sharp & Son",
    "wof:placetype":"venue"
},
  "geometry": {"coordinates":[-2.4760389328,57.6374092102],"type":"Point"}
}