{
  "type": "Feature",
  "properties": {
    "iso:country":"GB",
    "sg:address":"Southwold House, South Road, Tetford",
    "sg:city":"Horncastle",
    "sg:classifiers":[
        {
            "category":"Health Services",
            "subcategory":"Nursing And Care Facility",
            "type":"Services"
        }
    ],
    "sg:phone":"+44 1507 533393",
    "sg:postcode":"LN9 6QB",
    "sg:province":"Lincolnshire",
    "sg:tags":[
        "home"
    ],
    "wof:name":"South Wold Nursing Home",
    "wof:placetype":"venue"
},
  "geometry": {"coordinates":[-0.009216,53.252239],"type":"Point"}
}