{
  "type": "Feature",
  "properties": {
    "iso:country":"GB",
    "sg:address":"185 St Marys Lane",
    "sg:city":"Upminster",
    "sg:classifiers":[
        {
            "category":"Autos & Motor Vehicles",
            "subcategory":"Auto Supplies",
            "type":"Retail Goods"
        }
    ],
    "sg:phone":"+44 1708 227544",
    "sg:postcode":"RM14 3BU",
    "sg:province":"Essex",
    "sg:tags":[
        "exhaust",
        "absorber",
        "shock"
    ],
    "wof:name":"Kwik-Fit",
    "wof:placetype":"venue"
},
  "geometry": {"coordinates":[0.251702,51.556469],"type":"Point"}
}