{
  "type": "Feature",
  "properties": {
    "iso:country":"GB",
    "sg:address":"1d Tait St",
    "sg:city":"Dalkeith",
    "sg:classifiers":[
        {
            "category":"Shopping",
            "subcategory":"Bicycles & Sporting Goods",
            "type":"Retail Goods"
        }
    ],
    "sg:phone":"+44 131 654 1170",
    "sg:postcode":"EH22 1AZ",
    "sg:province":"City of Edinburgh",
    "sg:tags":[
        "cycle",
        "accessory"
    ],
    "wof:name":"Bike Shed The",
    "wof:placetype":"venue"
},
  "geometry": {"coordinates":[-3.096809,55.90435],"type":"Point"}
}