{
  "type": "Feature",
  "properties": {
    "addr:full":"Main St Alexandria Argyll and Bute G83 0UG",
    "addr:postcode":"g83 0ug",
    "addr:street":"Main St",
    "iso:country":"GB",
    "sg:address":"Main St",
    "sg:city":"Alexandria",
    "sg:classifiers":[
        {
            "category":"Real Estate",
            "subcategory":"Developer",
            "type":"Services"
        }
    ],
    "sg:phone":"+44 1389 710077",
    "sg:postcode":"G83 0UG",
    "sg:province":"Argyll and Bute",
    "sg:tags":[
        "property"
    ],
    "wof:name":"Pathfinder (Loch Lomand) Ltd",
    "wof:placetype":"venue"
},
  "geometry": {"coordinates":[-4.583704,55.990067],"type":"Point"}
}