{
  "type": "Feature",
  "properties": {
    "iso:country":"GB",
    "sg:address":"Unit 4a Clere Water Place, Lower Way",
    "sg:city":"Thatcham",
    "sg:classifiers":[
        {
            "category":"Communications",
            "subcategory":"Newspaper",
            "type":"Services"
        }
    ],
    "sg:phone":"+44 1635 864645",
    "sg:postcode":"RG19 3RF",
    "sg:province":"Berkshire",
    "sg:tags":[
        "magazine"
    ],
    "wof:name":"Auto Exchange",
    "wof:placetype":"venue"
},
  "geometry": {"coordinates":[-1.282647,51.402435],"type":"Point"}
}