{
  "type": "Feature",
  "properties": {
    "addr:full":"1530 London Road Glasgow Glasgow City G31 4QB",
    "addr:housenumber":"1530",
    "addr:postcode":"g31 4qb",
    "addr:street":"London Road",
    "iso:country":"GB",
    "sg:address":"1530 London Road",
    "sg:city":"Glasgow",
    "sg:classifiers":[
        {
            "category":"Retail",
            "subcategory":"Auto Rental",
            "type":"Services"
        }
    ],
    "sg:phone":"+44 141 556 7471",
    "sg:postcode":"G31 4QB",
    "sg:province":"Glasgow City",
    "sg:tags":[
        "car"
    ],
    "wof:name":"Kenning Car & Van Rental",
    "wof:placetype":"venue"
},
  "geometry": {"coordinates":[-4.193978,55.844509],"type":"Point"}
}