{
  "type": "Feature",
  "properties": {
    "addr:full":"150 Chelsworth Rd Felixstowe Suffolk IP11 2UJ",
    "addr:housenumber":"150",
    "addr:postcode":"ip11 2uj",
    "addr:street":"Chelsworth Rd",
    "iso:country":"GB",
    "sg:address":"150 Chelsworth Rd",
    "sg:city":"Felixstowe",
    "sg:classifiers":[
        {
            "category":"Shopping",
            "subcategory":"Computers & Home Electronics",
            "type":"Retail Goods"
        }
    ],
    "sg:phone":"+44 1394 210710",
    "sg:postcode":"IP11 2UJ",
    "sg:province":"Suffolk",
    "wof:name":"Computer Creations",
    "wof:placetype":"venue"
},
  "geometry": {"coordinates":[1.32713,51.962669],"type":"Point"}
}