{
  "type": "Feature",
  "properties": {
    "iso:country":"GB",
    "sg:address":"1-9 Stockport Rd",
    "sg:city":"Stockport",
    "sg:classifiers":[
        {
            "category":"Professional",
            "subcategory":"Computer Services",
            "type":"Services"
        }
    ],
    "sg:phone":"+44 161 406 6644",
    "sg:postcode":"SK6 4BN",
    "sg:province":"Cheshire",
    "sg:tags":[
        "system",
        "software"
    ],
    "wof:name":"Pennine Computers",
    "wof:placetype":"venue"
},
  "geometry": {"coordinates":[-2.089546,53.413731],"type":"Point"}
}