{
  "type": "Feature",
  "properties": {
    "iso:country":"GB",
    "sg:address":"17 Wren Close, Deeping St Nicholas",
    "sg:city":"Spalding",
    "sg:classifiers":[
        {
            "category":"Retail",
            "subcategory":"Driving School",
            "type":"Services"
        }
    ],
    "sg:postcode":"PE11 3DX",
    "sg:province":"Lincolnshire",
    "wof:name":"Patti's",
    "wof:placetype":"venue"
},
  "geometry": {"coordinates":[-0.211419,52.721169],"type":"Point"}
}