{
  "type": "Feature",
  "properties": {
    "addr:full":"Tytandderwen Farm Bala Gwynedd LL23 7EP",
    "addr:postcode":"ll23 7ep",
    "addr:street":"Bala",
    "iso:country":"GB",
    "sg:address":"Tytandderwen Farm",
    "sg:city":"Bala",
    "sg:classifiers":[
        {
            "category":"Recreation",
            "subcategory":"Campground",
            "type":"Entertainment"
        }
    ],
    "sg:postcode":"LL23 7EP",
    "sg:province":"Gwynedd",
    "sg:tags":[
        "site",
        "camping"
    ],
    "wof:name":"Robert Davies",
    "wof:placetype":"venue"
},
  "geometry": {"coordinates":[-3.595467,52.912148],"type":"Point"}
}