{
  "type": "Feature",
  "properties": {
    "addr:full":"44 Roehampton Clo London Greater London SW15 5LU",
    "addr:housenumber":"44",
    "addr:postcode":"sw15 5lu",
    "iso:country":"GB",
    "sg:address":"44 Roehampton Clo",
    "sg:city":"London",
    "sg:classifiers":[
        {
            "category":"Professional",
            "subcategory":"Management & Consulting",
            "type":"Services"
        }
    ],
    "sg:postcode":"SW15 5LU",
    "sg:province":"Greater London",
    "sg:tags":[
        "music"
    ],
    "wof:name":"Demac Managment",
    "wof:placetype":"venue"
},
  "geometry": {"coordinates":[-0.257208,51.454437],"type":"Point"}
}