{
  "type": "Feature",
  "properties": {
    "iso:country":"GB",
    "sg:address":"43 Head Street",
    "sg:city":"Colchester",
    "sg:classifiers":[
        {
            "category":"Home & Garden",
            "subcategory":"Household Appliances",
            "type":"Retail Goods"
        },
        {
            "category":"Retail",
            "subcategory":"Event Space",
            "type":"Services"
        },
        {
            "category":"Communications",
            "type":"Services"
        }
    ],
    "sg:phone":"+44 1206 765410",
    "sg:postcode":"CO1 1NH",
    "sg:province":"Essex",
    "sg:tags":[
        "product",
        "tv",
        "gas",
        "sales",
        "radio",
        "video",
        "electrical"
    ],
    "wof:name":"THE ENERGY CENTRE",
    "wof:placetype":"venue"
},
  "geometry": {"coordinates":[0.89609,51.888222],"type":"Point"}
}