{
  "type": "Feature",
  "properties": {
    "iso:country":"GB",
    "sg:address":"Weggis Farm, Higher Metcombe",
    "sg:city":"Ottery St Mary",
    "sg:classifiers":[
        {
            "category":"Farming",
            "subcategory":"Livestock Farm",
            "type":"Manufacturing & Wholesale Goods"
        }
    ],
    "sg:phone":"+44 1404 813527",
    "sg:postcode":"EX11 1SQ",
    "sg:province":"Devon",
    "sg:tags":[
        "others"
    ],
    "wof:name":"S E Lightfoot",
    "wof:placetype":"venue"
},
  "geometry": {"coordinates":[-3.283026,50.751137],"type":"Point"}
}