{
  "type": "Feature",
  "properties": {
    "addr:full":"27 Derby Lane Liverpool Merseyside L13 6QA",
    "addr:housenumber":"27",
    "addr:postcode":"l13 6qa",
    "addr:street":"Derby Lane",
    "iso:country":"GB",
    "sg:address":"27 Derby Lane",
    "sg:city":"Liverpool",
    "sg:classifiers":[
        {
            "category":"Education",
            "subcategory":"Dance Studio",
            "type":"Public Place"
        }
    ],
    "sg:phone":"+44 151 228 4586",
    "sg:postcode":"L13 6QA",
    "sg:province":"Merseyside",
    "sg:tags":[
        "school",
        "dancing"
    ],
    "wof:name":"Martin's Dance Centre",
    "wof:placetype":"venue"
},
  "geometry": {"coordinates":[-2.914738,53.415863],"type":"Point"}
}