{
  "type": "Feature",
  "properties": {
    "addr:full":"9-12 Wellington Centre Aldershot Hampshire GU11 1AP",
    "addr:housenumber":"9-12",
    "addr:postcode":"gu11 1ap",
    "addr:street":"Wellington",
    "iso:country":"GB",
    "sg:address":"9-12 Wellington Centre",
    "sg:city":"Aldershot",
    "sg:classifiers":[
        {
            "category":"Government",
            "subcategory":"Post Office",
            "type":"Public Place"
        }
    ],
    "sg:phone":"+44 1252 343144",
    "sg:postcode":"GU11 1AP",
    "sg:province":"Hampshire",
    "wof:name":"Aldershot Franchise Post Office",
    "wof:placetype":"venue"
},
  "geometry": {"coordinates":[-0.759346,51.249603],"type":"Point"}
}