{
  "type": "Feature",
  "properties": {
    "iso:country":"GB",
    "sg:address":"Mountdale Gardens",
    "sg:city":"Leigh-on-sea",
    "sg:classifiers":[
        {
            "category":"Education",
            "subcategory":"School",
            "type":"Public Place"
        }
    ],
    "sg:phone":"+44 1702 524193",
    "sg:postcode":"SS9 4AW",
    "sg:province":"Essex",
    "sg:tags":[
        "local",
        "authority"
    ],
    "wof:name":"St Christophers School",
    "wof:placetype":"venue"
},
  "geometry": {"coordinates":[0.658550024,51.5599098206],"type":"Point"}
}