{
  "type": "Feature",
  "properties": {
    "iso:country":"GB",
    "sg:address":"Meer End Road",
    "sg:city":"Kenilworth",
    "sg:classifiers":[
        {
            "category":"Bars & Pubs",
            "type":"Food & Drink"
        }
    ],
    "sg:phone":"+44 1676 533224",
    "sg:postcode":"CV8 1PW",
    "sg:province":"Warwickshire",
    "sg:tags":[
        "pubs",
        "inn"
    ],
    "wof:name":"The Tipperary Inn",
    "wof:placetype":"venue"
},
  "geometry": {"coordinates":[-1.646751,52.363293],"type":"Point"}
}