{
  "type": "Feature",
  "properties": {
    "addr:full":"9 Bircherley Grn Shopping Cent Hertford Hertfordshire SG14 1BH",
    "addr:housenumber":"9",
    "addr:postcode":"sg14 1bh",
    "addr:street":"Bircherley Grn;Hertford",
    "iso:country":"GB",
    "sg:address":"9 Bircherley Grn Shopping Cent",
    "sg:city":"Hertford",
    "sg:classifiers":[
        {
            "category":"Shopping",
            "subcategory":"Florist",
            "type":"Retail Goods"
        }
    ],
    "sg:phone":"+44 1992 589168",
    "sg:postcode":"SG14 1BH",
    "sg:province":"Hertfordshire",
    "wof:name":"Blossoms",
    "wof:placetype":"venue"
},
  "geometry": {"coordinates":[-0.07569,51.798195],"type":"Point"}
}