{
  "type": "Feature",
  "properties": {
    "iso:country":"GB",
    "sg:address":"Tonge Moor Health Centre, Thicketford Rd",
    "sg:city":"Bolton",
    "sg:classifiers":[
        {
            "category":"Health Services",
            "subcategory":"Doctor",
            "type":"Services"
        }
    ],
    "sg:phone":"+44 1204 521094",
    "sg:postcode":"BL2 2LW",
    "sg:province":"Lancashire",
    "sg:tags":[
        "practitioners"
    ],
    "wof:name":"Leather, D A",
    "wof:placetype":"venue"
},
  "geometry": {"coordinates":[-2.411739,53.594791],"type":"Point"}
}