{
  "type": "Feature",
  "properties": {
    "addr:full":"25 Bridge Industries Fareham Hampshire PO16 8SX",
    "addr:housenumber":"25",
    "addr:postcode":"po16 8sx",
    "iso:country":"GB",
    "sg:address":"25 Bridge Industries",
    "sg:city":"Fareham",
    "sg:classifiers":[
        {
            "category":"Professional",
            "subcategory":"Engineering",
            "type":"Services"
        },
        {
            "category":"Autos & Motor Vehicles",
            "subcategory":"Boat Sales",
            "type":"Retail Goods"
        }
    ],
    "sg:phone":"+44 1329 829200",
    "sg:postcode":"PO16 8SX",
    "sg:province":"Hampshire",
    "sg:tags":[
        "engine",
        "ge",
        "engineer",
        "rebuilders",
        "mechanical"
    ],
    "wof:name":"Cylinder Head Engineering",
    "wof:placetype":"venue"
},
  "geometry": {"coordinates":[-1.171249,50.861115],"type":"Point"}
}