{
  "type": "Feature",
  "properties": {
    "addr:full":"Alliance House, Library Road Chorley Lancashire PR6 7EN",
    "addr:postcode":"pr6 7en",
    "addr:street":"Library Road",
    "iso:country":"GB",
    "sg:address":"Alliance House, Library Road",
    "sg:city":"Chorley",
    "sg:classifiers":[
        {
            "category":"Professional",
            "subcategory":"Computer Services",
            "type":"Services"
        }
    ],
    "sg:phone":"+44 870 400 9524",
    "sg:postcode":"PR6 7EN",
    "sg:province":"Lancashire",
    "sg:tags":[
        "consultant"
    ],
    "wof:name":"C S C",
    "wof:placetype":"venue"
},
  "geometry": {"coordinates":[-2.640898,53.707237],"type":"Point"}
}