{
  "type": "Feature",
  "properties": {
    "addr:full":"Unit 6 Rear Of 168 New Rd Rainham Essex RM13 8RS",
    "addr:housenumber":"unit 6 rear of 168",
    "addr:postcode":"rm13 8rs",
    "addr:street":"New Rd",
    "iso:country":"GB",
    "sg:address":"Unit 6 Rear Of 168 New Rd",
    "sg:city":"Rainham",
    "sg:classifiers":[
        {
            "category":"Retail",
            "subcategory":"Auto Repair",
            "type":"Services"
        }
    ],
    "sg:postcode":"RM13 8RS",
    "sg:province":"Essex",
    "sg:tags":[
        "modification",
        "garage"
    ],
    "wof:name":"A New Road Service Centre",
    "wof:placetype":"venue"
},
  "geometry": {"coordinates":[0.190426,51.517914],"type":"Point"}
}