{
  "type": "Feature",
  "properties": {
    "addr:full":"72 Denton Street Carlisle Cumbria CA2 5EN",
    "addr:housenumber":"72",
    "addr:postcode":"ca2 5en",
    "addr:street":"Denton Street",
    "iso:country":"GB",
    "sg:address":"72 Denton Street",
    "sg:city":"Carlisle",
    "sg:classifiers":[
        {
            "category":"Organizations",
            "subcategory":"Community Association",
            "type":"Services"
        },
        {
            "category":"Organizations",
            "subcategory":"Membership Organization",
            "type":"Services"
        }
    ],
    "sg:phone":"+44 1228 526891",
    "sg:postcode":"CA2 5EN",
    "sg:province":"Cumbria",
    "sg:tags":[
        "club",
        "social"
    ],
    "wof:name":"Rex Bingo Club",
    "wof:placetype":"venue"
},
  "geometry": {"coordinates":[-2.9403669834,54.887096405],"type":"Point"}
}