{
  "type": "Feature",
  "properties": {
    "addr:full":"Unit 18, Newtown Road Ashford Kent TN24 0PN",
    "addr:housenumber":"unit 18",
    "addr:postcode":"tn24 0pn",
    "addr:street":"Newtown Road",
    "iso:country":"GB",
    "sg:address":"Unit 18, Newtown Road",
    "sg:city":"Ashford",
    "sg:classifiers":[
        {
            "category":"Food & Beverages",
            "subcategory":"Specialty",
            "type":"Retail Goods"
        }
    ],
    "sg:phone":"+44 1303 227199",
    "sg:postcode":"TN24 0PN",
    "sg:province":"Kent",
    "sg:tags":[
        "organic"
    ],
    "wof:name":"Occam Organic Foods",
    "wof:placetype":"venue"
},
  "geometry": {"coordinates":[0.882224977,51.1376342773],"type":"Point"}
}