{
  "type": "Feature",
  "properties": {
    "addr:full":"162 Church Road Hove East Sussex BN3 2DL",
    "addr:housenumber":"162",
    "addr:postcode":"bn3 2dl",
    "addr:street":"Church Road",
    "iso:country":"GB",
    "sg:address":"162 Church Road",
    "sg:city":"Hove",
    "sg:classifiers":[
        {
            "category":"Professional",
            "subcategory":"Lawyer & Legal Services",
            "type":"Services"
        }
    ],
    "sg:phone":"+44 1273 325434",
    "sg:postcode":"BN3 2DL",
    "sg:province":"East Sussex",
    "sg:tags":[
        "solicitor"
    ],
    "wof:name":"Stockmans Solicitors",
    "wof:placetype":"venue"
},
  "geometry": {"coordinates":[-0.1755110025,50.8281822205],"type":"Point"}
}