{
  "type": "Feature",
  "properties": {
    "addr:full":"24 High Street London Greater London N8 7PB",
    "addr:housenumber":"24",
    "addr:postcode":"n8 7pb",
    "addr:street":"High Street",
    "iso:country":"GB",
    "sg:address":"24 High Street",
    "sg:city":"London",
    "sg:classifiers":[
        {
            "category":"Government",
            "subcategory":"Post Office",
            "type":"Public Place"
        }
    ],
    "sg:phone":"+44 20 8340 2434",
    "sg:postcode":"N8 7PB",
    "sg:province":"Greater London",
    "wof:name":"Hornsey High Street Post Office",
    "wof:placetype":"venue"
},
  "geometry": {"coordinates":[-0.1205679998,51.5871734619],"type":"Point"}
}