{
  "type": "Feature",
  "properties": {
    "iso:country":"GB",
    "sg:address":"254 High Street",
    "sg:city":"Epping",
    "sg:classifiers":[
        {
            "category":"Shopping",
            "subcategory":"Department Store",
            "type":"Retail Goods"
        },
        {
            "category":"Home & Garden",
            "subcategory":"Carpets & Floor Coverings",
            "type":"Retail Goods"
        }
    ],
    "sg:phone":"+44 1992 570224",
    "sg:postcode":"CM16 4AP",
    "sg:province":"Essex",
    "sg:tags":[
        "retailer",
        "rug"
    ],
    "wof:name":"James Collop",
    "wof:placetype":"venue"
},
  "geometry": {"coordinates":[0.114097,51.700775],"type":"Point"}
}