{
  "type": "Feature",
  "properties": {
    "addr:full":"207 Lewisham High Street London Greater London SE13 6LY",
    "addr:housenumber":"207",
    "addr:postcode":"se13 6ly",
    "addr:street":"Lewisham High Street",
    "iso:country":"GB",
    "sg:address":"207 Lewisham High Street",
    "sg:city":"London",
    "sg:classifiers":[
        {
            "category":"Health Services",
            "subcategory":"Nursing And Care Facility",
            "type":"Services"
        }
    ],
    "sg:postcode":"SE13 6LY",
    "sg:province":"Greater London",
    "sg:tags":[
        "agency"
    ],
    "wof:name":"Darkwa Millicent Anpwi",
    "wof:placetype":"venue"
},
  "geometry": {"coordinates":[-0.0125299999,51.4584693909],"type":"Point"}
}