{
  "type": "Feature",
  "properties": {
    "addr:full":"5 The Square Ellon Aberdeenshire AB41 9JB",
    "addr:housenumber":"5",
    "addr:postcode":"ab41 9jb",
    "addr:street":"The Square",
    "iso:country":"GB",
    "sg:address":"5 The Square",
    "sg:city":"Ellon",
    "sg:classifiers":[
        {
            "category":"Professional",
            "subcategory":"Accounting & Tax Preparation",
            "type":"Services"
        }
    ],
    "sg:phone":"+44 1358 720414",
    "sg:postcode":"AB41 9JB",
    "sg:province":"Aberdeenshire",
    "sg:tags":[
        "accountant"
    ],
    "wof:name":"Atholl Scott",
    "wof:placetype":"venue"
},
  "geometry": {"coordinates":[-2.070702076,57.365146637],"type":"Point"}
}