{
  "type": "Feature",
  "properties": {
    "addr:full":"Hillview, Bosworth Road, Wellsborough Nuneaton Leicestershire CV13 6PA",
    "addr:postcode":"cv13 6pa",
    "addr:street":"Bosworth Road",
    "iso:country":"GB",
    "sg:address":"Hillview, Bosworth Road, Wellsborough",
    "sg:city":"Nuneaton",
    "sg:classifiers":[
        {
            "category":"Transit Center",
            "subcategory":"Passenger",
            "type":"Transportation"
        },
        {
            "category":"Retail",
            "subcategory":"Pet Boarding",
            "type":"Services"
        }
    ],
    "sg:phone":"+44 1455 291995",
    "sg:postcode":"CV13 6PA",
    "sg:province":"Leicestershire",
    "sg:tags":[
        "kennel",
        "catteries"
    ],
    "wof:name":"Cottage Cattery",
    "wof:placetype":"venue"
},
  "geometry": {"coordinates":[-1.4629570246,52.6194190979],"type":"Point"}
}