{
  "type": "Feature",
  "properties": {
    "iso:country":"GB",
    "sg:address":"Old Stone Trough Lane, Kelbrook",
    "sg:city":"Barnoldswick",
    "sg:classifiers":[
        {
            "category":"Farming",
            "subcategory":"Livestock Farm",
            "type":"Manufacturing & Wholesale Goods"
        }
    ],
    "sg:phone":"+44 1282 842205",
    "sg:postcode":"BB18 6LW",
    "sg:province":"Lancashire",
    "sg:tags":[
        "others"
    ],
    "wof:name":"E Simpson",
    "wof:placetype":"venue"
},
  "geometry": {"coordinates":[-2.15248,53.893402],"type":"Point"}
}