{
  "type": "Feature",
  "properties": {
    "addr:full":"Barn Cottage, Bownhill, Woodchester Stroud Gloucestershire GL5 5PW",
    "addr:postcode":"gl5 5pw",
    "addr:street":"Bownhill Woodchester",
    "iso:country":"GB",
    "sg:address":"Barn Cottage, Bownhill, Woodchester",
    "sg:city":"Stroud",
    "sg:classifiers":[
        {
            "category":"Professional",
            "subcategory":"Employment Agencies",
            "type":"Services"
        }
    ],
    "sg:postcode":"GL5 5PW",
    "sg:province":"Gloucestershire",
    "sg:tags":[
        "consultant"
    ],
    "wof:name":"Gallery Resources Ltd.",
    "wof:placetype":"venue"
},
  "geometry": {"coordinates":[-2.2311999798,51.7240791321],"type":"Point"}
}