{
  "type": "Feature",
  "properties": {
    "addr:full":"4 Westbury Avenue Bury St Edmunds Suffolk IP33 3PZ",
    "addr:housenumber":"4",
    "addr:postcode":"ip33 3pz",
    "addr:street":"Westbury Avenue",
    "iso:country":"GB",
    "sg:address":"4 Westbury Avenue",
    "sg:city":"Bury St Edmunds",
    "sg:classifiers":[
        {
            "category":"Building & Trades",
            "subcategory":"Construction",
            "type":"Services"
        }
    ],
    "sg:phone":"+44 1284 754466",
    "sg:postcode":"IP33 3PZ",
    "sg:province":"Suffolk",
    "sg:tags":[
        "builder"
    ],
    "wof:name":"Barbrooke Bros",
    "wof:placetype":"venue"
},
  "geometry": {"coordinates":[0.6961690187,52.244808197],"type":"Point"}
}