{
  "type": "Feature",
  "properties": {
    "iso:country":"GB",
    "sg:address":"5 Broomfield Close",
    "sg:city":"Nottingham",
    "sg:classifiers":[
        {
            "category":"Professional",
            "subcategory":"Engineering",
            "type":"Services"
        }
    ],
    "sg:phone":"+44 115 939 4289",
    "sg:postcode":"NG10 5GQ",
    "sg:province":"Derbyshire",
    "sg:tags":[
        "contractor",
        "electrical",
        "engineer"
    ],
    "wof:name":"A G Hardy Ltd.",
    "wof:placetype":"venue"
},
  "geometry": {"coordinates":[-1.295065,52.921032],"type":"Point"}
}