{
  "type": "Feature",
  "properties": {
    "iso:country":"GB",
    "sg:address":"28 Hammer Lane, Warborough",
    "sg:city":"Wallingford",
    "sg:classifiers":[
        {
            "category":"Wholesale",
            "subcategory":"Machinery & Supplies",
            "type":"Manufacturing & Wholesale Goods"
        },
        {
            "category":"Home & Garden",
            "subcategory":"Kitchen Supply",
            "type":"Retail Goods"
        }
    ],
    "sg:phone":"+44 1865 858565",
    "sg:postcode":"OX10 7DJ",
    "sg:province":"Oxfordshire",
    "sg:tags":[
        "measuring",
        "scale"
    ],
    "wof:name":"Parker Weighing Systems",
    "wof:placetype":"venue"
},
  "geometry": {"coordinates":[-1.1411950588,51.6415557861],"type":"Point"}
}