{
  "type": "Feature",
  "properties": {
    "addr:full":"169a Gladstone St Peterborough Cambridgeshire PE1 2BN",
    "addr:housenumber":"169a",
    "addr:postcode":"pe1 2bn",
    "addr:street":"Gladstone St",
    "iso:country":"GB",
    "sg:address":"169a Gladstone St",
    "sg:city":"Peterborough",
    "sg:classifiers":[
        {
            "category":"Retail",
            "subcategory":"Auto Repair",
            "type":"Services"
        }
    ],
    "sg:phone":"+44 1733 346464",
    "sg:postcode":"PE1 2BN",
    "sg:province":"Cambridgeshire",
    "sg:tags":[
        "modification",
        "garage"
    ],
    "wof:name":"Jamspeed",
    "wof:placetype":"venue"
},
  "geometry": {"coordinates":[-0.250112,52.581577],"type":"Point"}
}