{
  "type": "Feature",
  "properties": {
    "addr:full":"61-63 Cudworth Street London Greater London E1 5QU",
    "addr:housenumber":"61-63",
    "addr:postcode":"e1 5qu",
    "addr:street":"Cudworth Street",
    "iso:country":"GB",
    "sg:address":"61-63 Cudworth Street",
    "sg:city":"London",
    "sg:classifiers":[
        {
            "category":"Shopping",
            "subcategory":"Computers & Home Electronics",
            "type":"Retail Goods"
        }
    ],
    "sg:postcode":"E1 5QU",
    "sg:province":"Greater London",
    "sg:tags":[
        "equipment",
        "video",
        "cctv"
    ],
    "wof:name":"Crosspath Services Ltd.",
    "wof:placetype":"venue"
},
  "geometry": {"coordinates":[-0.0561,51.523964],"type":"Point"}
}