{
  "type": "Feature",
  "properties": {
    "iso:country":"GB",
    "sg:address":"Edward Road",
    "sg:city":"Bedford",
    "sg:classifiers":[
        {
            "category":"Education",
            "subcategory":"School",
            "type":"Public Place"
        }
    ],
    "sg:phone":"+44 1234 301400",
    "sg:postcode":"MK42 9DR",
    "sg:province":"Bedfordshire",
    "sg:tags":[
        "local",
        "authority"
    ],
    "wof:name":"Caudwell Lower School",
    "wof:placetype":"venue"
},
  "geometry": {"coordinates":[-0.4750620127,52.1269416809],"type":"Point"}
}