{
  "type": "Feature",
  "properties": {
    "addr:full":"20 Darwin Street London Greater London SE17 1HB",
    "addr:housenumber":"20",
    "addr:postcode":"se17 1hb",
    "addr:street":"Darwin Street",
    "iso:country":"GB",
    "sg:address":"20 Darwin Street",
    "sg:city":"London",
    "sg:classifiers":[
        {
            "category":"Bars & Pubs",
            "type":"Food & Drink"
        }
    ],
    "sg:postcode":"SE17 1HB",
    "sg:province":"Greater London",
    "sg:tags":[
        "pubs",
        "inn"
    ],
    "wof:name":"Leslie Elliot",
    "wof:placetype":"venue"
},
  "geometry": {"coordinates":[-0.086157,51.493103],"type":"Point"}
}