{
  "type": "Feature",
  "properties": {
    "addr:full":"210 Wellgate Rotherham South Yorkshire S60 2PD",
    "addr:housenumber":"210",
    "addr:postcode":"s60 2pd",
    "addr:street":"Wellgate Rotherham South",
    "iso:country":"GB",
    "sg:address":"210 Wellgate",
    "sg:city":"Rotherham",
    "sg:classifiers":[
        {
            "category":"Government",
            "subcategory":"Customs House",
            "type":"Public Place"
        }
    ],
    "sg:phone":"+44 1709 838301",
    "sg:postcode":"S60 2PD",
    "sg:province":"South Yorkshire",
    "sg:tags":[
        "clearance"
    ],
    "wof:name":"Wellgate Salesrooms",
    "wof:placetype":"venue"
},
  "geometry": {"coordinates":[-1.348747,53.427135],"type":"Point"}
}