{
  "type": "Feature",
  "properties": {
    "addr:full":"282 North End Rd Fulham Greater London SW6 1NH",
    "addr:housenumber":"282",
    "addr:postcode":"sw6 1nh",
    "addr:street":"North End Rd",
    "iso:country":"GB",
    "sg:address":"282 North End Rd",
    "sg:city":"Fulham",
    "sg:classifiers":[
        {
            "category":"Farming",
            "subcategory":"Aquatic Farm",
            "type":"Manufacturing & Wholesale Goods"
        }
    ],
    "sg:phone":"+44 20 7610 3296",
    "sg:postcode":"SW6 1NH",
    "sg:province":"Greater London",
    "sg:tags":[
        "hydroponics"
    ],
    "wof:name":"Roots & Shoots Hydroponics",
    "wof:placetype":"venue"
},
  "geometry": {"coordinates":[-0.201436,51.483692],"type":"Point"}
}