{
  "type": "Feature",
  "properties": {
    "iso:country":"GB",
    "sg:address":"Bircher Hall, Bircher",
    "sg:city":"Leominster",
    "sg:classifiers":[
        {
            "category":"Professional",
            "subcategory":"Computer Services",
            "type":"Services"
        }
    ],
    "sg:phone":"+44 1568 780310",
    "sg:postcode":"HR6 0AX",
    "sg:province":"Herefordshire",
    "sg:tags":[
        "system",
        "software"
    ],
    "wof:name":"W.F Cawley",
    "wof:placetype":"venue"
},
  "geometry": {"coordinates":[-2.7693860531,52.2869567871],"type":"Point"}
}