{
  "type": "Feature",
  "properties": {
    "addr:full":"Unit 3 Sutton Lane, Sutton Market Drayton Shropshire TF9 2HY",
    "addr:housenumber":"unit 3",
    "addr:postcode":"tf9 2hy",
    "addr:street":"Sutton Lane",
    "iso:country":"GB",
    "sg:address":"Unit 3 Sutton Lane, Sutton",
    "sg:city":"Market Drayton",
    "sg:classifiers":[
        {
            "category":"Manufacturing",
            "subcategory":"Glass & Minerals",
            "type":"Manufacturing & Wholesale Goods"
        }
    ],
    "sg:phone":"+44 1630 638383",
    "sg:postcode":"TF9 2HY",
    "sg:province":"Shropshire",
    "sg:tags":[
        "fibre",
        "moulding"
    ],
    "wof:name":"T & M Glass Fibre Mouldings",
    "wof:placetype":"venue"
},
  "geometry": {"coordinates":[-2.5114660263,52.8805122375],"type":"Point"}
}