{
  "type": "Feature",
  "properties": {
    "addr:full":"225 Duckworth Street Darwen Lancashire BB3 1AU",
    "addr:housenumber":"225",
    "addr:postcode":"bb3 1au",
    "addr:street":"Duckworth Street",
    "iso:country":"GB",
    "sg:address":"225 Duckworth Street",
    "sg:city":"Darwen",
    "sg:classifiers":[
        {
            "category":"Food & Beverages",
            "subcategory":"Liquor & Beverages",
            "type":"Retail Goods"
        }
    ],
    "sg:phone":"+44 1254 702898",
    "sg:postcode":"BB3 1AU",
    "sg:province":"Lancashire",
    "sg:tags":[
        "beer",
        "wine",
        "spirit",
        "wines"
    ],
    "wof:name":"W J Bland",
    "wof:placetype":"venue"
},
  "geometry": {"coordinates":[-2.4692089558,53.6973266602],"type":"Point"}
}