{
  "type": "Feature",
  "properties": {
    "iso:country":"GB",
    "sg:address":"34 Cae Brynton Road",
    "sg:city":"Newport",
    "sg:classifiers":[
        {
            "category":"Building & Trades",
            "subcategory":"Plumbing",
            "type":"Services"
        }
    ],
    "sg:phone":"+44 1633 840472",
    "sg:postcode":"NP20 3FY",
    "sg:province":"Newport",
    "sg:tags":[
        "central",
        "installation",
        "system",
        "servicing",
        "heating"
    ],
    "wof:name":"H G Carver",
    "wof:placetype":"venue"
},
  "geometry": {"coordinates":[-3.012809,51.575294],"type":"Point"}
}