{
  "type": "Feature",
  "properties": {
    "iso:country":"GB",
    "sg:address":"Loes House, 14b Market Square",
    "sg:city":"Alton",
    "sg:classifiers":[
        {
            "category":"Military Area",
            "subcategory":"Air Force Base",
            "type":"Public Place"
        }
    ],
    "sg:phone":"+44 1420 88888",
    "sg:postcode":"GU34 1HD",
    "sg:province":"Hampshire",
    "sg:tags":[
        "taxi",
        "hire",
        "private"
    ],
    "wof:name":"Wessex Cars",
    "wof:placetype":"venue"
},
  "geometry": {"coordinates":[-0.97644,51.148521],"type":"Point"}
}