{
  "type": "Feature",
  "properties": {
    "addr:full":"17 Brewery Lane Stansted Essex CM24 8LB",
    "addr:housenumber":"17",
    "addr:postcode":"cm24 8lb",
    "addr:street":"Brewery Lane",
    "iso:country":"GB",
    "sg:address":"17 Brewery Lane",
    "sg:city":"Stansted",
    "sg:classifiers":[
        {
            "category":"Professional",
            "subcategory":"Management & Consulting",
            "type":"Services"
        }
    ],
    "sg:phone":"+44 1279 814971",
    "sg:postcode":"CM24 8LB",
    "sg:province":"Essex",
    "sg:tags":[
        "consultant",
        "business"
    ],
    "wof:name":"Executive Elect Ltd.",
    "wof:placetype":"venue"
},
  "geometry": {"coordinates":[0.1997269988,51.905292511],"type":"Point"}
}