{
  "type": "Feature",
  "properties": {
    "addr:full":"The Rectory Buntingford Hertfordshire SG9 9LL",
    "addr:postcode":"sg9 9ll",
    "iso:country":"GB",
    "sg:address":"The Rectory",
    "sg:city":"Buntingford",
    "sg:classifiers":[
        {
            "category":"Wholesale",
            "subcategory":"Toys & Hobbies",
            "type":"Manufacturing & Wholesale Goods"
        }
    ],
    "sg:phone":"+44 1763 274120",
    "sg:postcode":"SG9 9LL",
    "sg:province":"Hertfordshire",
    "sg:tags":[
        "balloon",
        "novelty"
    ],
    "wof:name":"Kentex (Printers)",
    "wof:placetype":"venue"
},
  "geometry": {"coordinates":[-0.0172690004,51.9462890625],"type":"Point"}
}