{
  "type": "Feature",
  "properties": {
    "iso:country":"GB",
    "sg:address":"Hayfield Road, Chinley",
    "sg:city":"High Peak",
    "sg:classifiers":[
        {
            "category":"Bars & Pubs",
            "type":"Food & Drink"
        }
    ],
    "sg:phone":"+44 1663 750519",
    "sg:postcode":"SK23 6AL",
    "sg:province":"Cheshire",
    "sg:tags":[
        "pubs",
        "inn"
    ],
    "wof:name":"The Lamb Inn",
    "wof:placetype":"venue"
},
  "geometry": {"coordinates":[-1.92762,53.354836],"type":"Point"}
}