{
  "type": "Feature",
  "properties": {
    "iso:country":"GB",
    "sg:address":"Cross Garage, Queens Road",
    "sg:city":"Ashton-under-lyne",
    "sg:classifiers":[
        {
            "category":"Retail",
            "subcategory":"Auto Repair",
            "type":"Services"
        }
    ],
    "sg:phone":"+44 161 330 6206",
    "sg:postcode":"OL6 8HE",
    "sg:province":"Greater Manchester",
    "sg:tags":[
        "modification",
        "garage",
        "related"
    ],
    "wof:name":"Cross Garage",
    "wof:placetype":"venue"
},
  "geometry": {"coordinates":[-2.088242,53.489239],"type":"Point"}
}