{
  "type": "Feature",
  "properties": {
    "addr:full":"Unit 2 Edison Business Centre, 52 Edison Road Aylesbury Buckinghamshire HP19 8TE",
    "addr:housenumber":"unit 2;52",
    "addr:postcode":"hp19 8te",
    "addr:street":"Edison Business;Edison Road",
    "iso:country":"GB",
    "sg:address":"Unit 2 Edison Business Centre, 52 Edison Road",
    "sg:city":"Aylesbury",
    "sg:classifiers":[
        {
            "category":"Professional",
            "type":"Services"
        }
    ],
    "sg:phone":"+44 1296 429129",
    "sg:postcode":"HP19 8TE",
    "sg:province":"Buckinghamshire",
    "sg:tags":[
        "entertainer"
    ],
    "wof:name":"Primetime Events Ltd.",
    "wof:placetype":"venue"
},
  "geometry": {"coordinates":[-0.8507500291,51.8222312927],"type":"Point"}
}