{
  "type": "Feature",
  "properties": {
    "iso:country":"GB",
    "sg:address":"24 Barton Street",
    "sg:city":"Bath",
    "sg:classifiers":[
        {
            "category":"Real Estate",
            "subcategory":"Surveying",
            "type":"Services"
        }
    ],
    "sg:phone":"+44 1225 427000",
    "sg:postcode":"BA1 1HG",
    "sg:province":"Bath and North East Somerset",
    "sg:tags":[
        "surveyor",
        "valuer"
    ],
    "wof:name":"Smith-Woolley Partnership",
    "wof:placetype":"venue"
},
  "geometry": {"coordinates":[-2.362904,51.382626],"type":"Point"}
}