{
  "type": "Feature",
  "properties": {
    "addr:full":"Westgate Elland West Yorkshire HX5 0BB",
    "addr:postcode":"hx5 0bb",
    "addr:street":"Westgate Elland West",
    "iso:country":"GB",
    "sg:address":"Westgate",
    "sg:city":"Elland",
    "sg:classifiers":[
        {
            "category":"Deli",
            "type":"Food & Drink"
        }
    ],
    "sg:phone":"+44 1422 370589",
    "sg:postcode":"HX5 0BB",
    "sg:province":"West Yorkshire",
    "sg:tags":[
        "delicatessen"
    ],
    "wof:name":"Belicatessen The",
    "wof:placetype":"venue"
},
  "geometry": {"coordinates":[-1.8419719934,53.6857643127],"type":"Point"}
}