{
  "type": "Feature",
  "properties": {
    "addr:full":"Unit C8 The Premier Centre, Premier Way Romsey Hampshire SO51 9DG",
    "addr:housenumber":"c8 the;centre",
    "addr:postcode":"so51 9dg",
    "addr:street":"Premier Way",
    "iso:country":"GB",
    "sg:address":"Unit C8 The Premier Centre, Premier Way",
    "sg:city":"Romsey",
    "sg:classifiers":[
        {
            "category":"Autos & Motor Vehicles",
            "subcategory":"Automobile Sales",
            "type":"Retail Goods"
        }
    ],
    "sg:phone":"+44 1794 830373",
    "sg:postcode":"SO51 9DG",
    "sg:province":"Hampshire",
    "sg:tags":[
        "car"
    ],
    "wof:name":"Abbey Park Cars",
    "wof:placetype":"venue"
},
  "geometry": {"coordinates":[-1.463194,50.982567],"type":"Point"}
}