{
  "type": "Feature",
  "properties": {
    "addr:full":"The Willows, Llancarfan Barry The Vale of Glamorgan CF62 3AD",
    "addr:housenumber":"llancarfan",
    "addr:postcode":"cf62 3ad",
    "addr:street":"Barry The Vale",
    "iso:country":"GB",
    "sg:address":"The Willows, Llancarfan",
    "sg:city":"Barry",
    "sg:classifiers":[
        {
            "category":"Autos & Motor Vehicles",
            "subcategory":"Automobile Sales",
            "type":"Retail Goods"
        }
    ],
    "sg:phone":"+44 29 2081 3026",
    "sg:postcode":"CF62 3AD",
    "sg:province":"The Vale of Glamorgan",
    "sg:tags":[
        "car"
    ],
    "wof:name":"Cars Cardiff Ltd.",
    "wof:placetype":"venue"
},
  "geometry": {"coordinates":[-3.366697073,51.4232559204],"type":"Point"}
}