{
  "type": "Feature",
  "properties": {
    "iso:country":"GB",
    "sg:address":"27 Ridley Place",
    "sg:city":"Newcastle-upon-tyne",
    "sg:classifiers":[
        {
            "category":"Professional",
            "subcategory":"Lawyer & Legal Services",
            "type":"Services"
        }
    ],
    "sg:phone":"+44 191 232 8058",
    "sg:postcode":"NE1 8LE",
    "sg:province":"Tyne and Wear",
    "sg:tags":[
        "solicitor"
    ],
    "wof:name":"Davies Bell & Reed",
    "wof:placetype":"venue"
},
  "geometry": {"coordinates":[-1.61171,54.97736],"type":"Point"}
}