{
  "type": "Feature",
  "properties": {
    "addr:full":"2 Corfton Rd Ealing Greater London W5 2HS",
    "addr:housenumber":"2",
    "addr:postcode":"w5 2hs",
    "addr:street":"Corfton Rd",
    "iso:country":"GB",
    "sg:address":"2 Corfton Rd",
    "sg:city":"Ealing",
    "sg:classifiers":[
        {
            "category":"Government",
            "subcategory":"Office",
            "type":"Public Place"
        }
    ],
    "sg:phone":"+44 20 8997 7127",
    "sg:postcode":"W5 2HS",
    "sg:province":"Greater London",
    "sg:tags":[
        "central"
    ],
    "wof:name":"The Probation Service",
    "wof:placetype":"venue"
},
  "geometry": {"coordinates":[-0.2983630002,51.5186233521],"type":"Point"}
}