{
  "type": "Feature",
  "properties": {
    "addr:full":"Elm Street, Temple Normanton Chesterfield Derbyshire S42 5DW",
    "addr:postcode":"s42 5dw",
    "addr:street":"Elm Street",
    "iso:country":"GB",
    "sg:address":"Elm Street, Temple Normanton",
    "sg:city":"Chesterfield",
    "sg:classifiers":[
        {
            "category":"Recreation",
            "type":"Entertainment"
        }
    ],
    "sg:postcode":"S42 5DW",
    "sg:province":"Derbyshire",
    "sg:tags":[
        "snooker",
        "billiards",
        "pool"
    ],
    "wof:name":"Toms Snooker Club",
    "wof:placetype":"venue"
},
  "geometry": {"coordinates":[-1.3743710518,53.2037849426],"type":"Point"}
}