{
  "type": "Feature",
  "properties": {
    "iso:country":"GB",
    "sg:address":"68 Kirkland",
    "sg:city":"Kendal",
    "sg:classifiers":[
        {
            "category":"Shopping",
            "subcategory":"Books",
            "type":"Retail Goods"
        }
    ],
    "sg:phone":"+44 1539 740841",
    "sg:postcode":"LA9 5AP",
    "sg:province":"Cumbria",
    "sg:tags":[
        "second-hand"
    ],
    "wof:name":"Kirkland Books",
    "wof:placetype":"venue"
},
  "geometry": {"coordinates":[-2.745397,54.321491],"type":"Point"}
}