{
  "type": "Feature",
  "properties": {
    "addr:full":"11 St Thomas Square Newport Isle of Wight PO30 1SN",
    "addr:housenumber":"11",
    "addr:postcode":"po30 1sn",
    "addr:street":"St Thomas Square",
    "iso:country":"GB",
    "sg:address":"11 St Thomas Square",
    "sg:city":"Newport",
    "sg:classifiers":[
        {
            "category":"Real Estate",
            "subcategory":"Real Estate Agent",
            "type":"Services"
        }
    ],
    "sg:phone":"+44 1983 821020",
    "sg:postcode":"PO30 1SN",
    "sg:province":"Isle of Wight",
    "wof:name":"Keith Rogers",
    "wof:placetype":"venue"
},
  "geometry": {"coordinates":[-1.2955470085,50.6933860779],"type":"Point"}
}