{
  "type": "Feature",
  "properties": {
    "addr:full":"Station Road, Draycott Cheddar Somerset BS27 3TQ",
    "addr:postcode":"bs27 3tq",
    "addr:street":"Station Road",
    "iso:country":"GB",
    "sg:address":"Station Road, Draycott",
    "sg:city":"Cheddar",
    "sg:classifiers":[
        {
            "category":"Bars & Pubs",
            "type":"Food & Drink"
        }
    ],
    "sg:postcode":"BS27 3TQ",
    "sg:province":"Somerset",
    "sg:tags":[
        "pubs",
        "inn"
    ],
    "wof:name":"Strawberry Special Inn",
    "wof:placetype":"venue"
},
  "geometry": {"coordinates":[-2.7776589394,51.2796592712],"type":"Point"}
}