{
  "type": "Feature",
  "properties": {
    "iso:country":"GB",
    "sg:address":"Alford Road, Huttoft",
    "sg:city":"Alford",
    "sg:classifiers":[
        {
            "category":"Government",
            "subcategory":"Post Office",
            "type":"Public Place"
        }
    ],
    "sg:phone":"+44 1507 490581",
    "sg:postcode":"LN13 9RB",
    "sg:province":"Lincolnshire",
    "wof:name":"Huttoft Sub Post Office",
    "wof:placetype":"venue"
},
  "geometry": {"coordinates":[0.180093,53.261505],"type":"Point"}
}