{
  "type": "Feature",
  "properties": {
    "iso:country":"GB",
    "sg:address":"Bellway Industrial Estate, Whitley Road",
    "sg:city":"Newcastle-upon-tyne",
    "sg:classifiers":[
        {
            "category":"Autos & Motor Vehicles",
            "subcategory":"Automobile Sales",
            "type":"Retail Goods"
        }
    ],
    "sg:phone":"+44 191 266 1150",
    "sg:postcode":"NE12 8NE",
    "sg:province":"Tyne and Wear",
    "sg:tags":[
        "car"
    ],
    "wof:name":"Weston Saab",
    "wof:placetype":"venue"
},
  "geometry": {"coordinates":[-1.6123689413,54.9779167175],"type":"Point"}
}