{
  "type": "Feature",
  "properties": {
    "iso:country":"GB",
    "sg:address":"30 High Street",
    "sg:city":"Alcester",
    "sg:classifiers":[
        {
            "category":"Professional",
            "subcategory":"Detective & Security Services",
            "type":"Services"
        }
    ],
    "sg:phone":"+44 1789 762450",
    "sg:postcode":"B49 5AB",
    "sg:province":"Warwickshire",
    "sg:tags":[
        "locksmith"
    ],
    "wof:name":"Alcester Locks",
    "wof:placetype":"venue"
},
  "geometry": {"coordinates":[-1.870175,52.214195],"type":"Point"}
}