{
  "type": "Feature",
  "properties": {
    "addr:full":"47 Central Drive Dudley Staffordshire DY3 2QE",
    "addr:housenumber":"47",
    "addr:postcode":"dy3 2qe",
    "addr:street":"Central Drive",
    "iso:country":"GB",
    "sg:address":"47 Central Drive",
    "sg:city":"Dudley",
    "sg:classifiers":[
        {
            "category":"Personal",
            "subcategory":"Beauty Salon",
            "type":"Services"
        },
        {
            "category":"Personal",
            "subcategory":"Barber",
            "type":"Services"
        }
    ],
    "sg:phone":"+44 1384 233401",
    "sg:postcode":"DY3 2QE",
    "sg:province":"Staffordshire",
    "sg:tags":[
        "unisex",
        "hairdresser"
    ],
    "wof:name":"Hair & Beauty",
    "wof:placetype":"venue"
},
  "geometry": {"coordinates":[-2.126577,52.514584],"type":"Point"}
}