{
  "type": "Feature",
  "properties": {
    "iso:country":"GB",
    "sg:address":"Unit 16 Magnus, Tame Valley Business Centre",
    "sg:city":"Tamworth",
    "sg:classifiers":[
        {
            "category":"Professional",
            "type":"Services"
        }
    ],
    "sg:phone":"+44 1827 281600",
    "sg:postcode":"B77 5BY",
    "sg:province":"Staffordshire",
    "sg:tags":[
        "repair",
        "tech",
        "maintenance"
    ],
    "wof:name":"Avenue International Ltd.",
    "wof:placetype":"venue"
},
  "geometry": {"coordinates":[-1.673813,52.603996],"type":"Point"}
}