{
  "type": "Feature",
  "properties": {
    "addr:full":"Unit 19, Southern Way Harlow Essex CM18 7BH",
    "addr:housenumber":"unit 19",
    "addr:postcode":"cm18 7bh",
    "addr:street":"Southern Way",
    "iso:country":"GB",
    "sg:address":"Unit 19, Southern Way",
    "sg:city":"Harlow",
    "sg:classifiers":[
        {
            "category":"Government",
            "subcategory":"Post Office",
            "type":"Public Place"
        }
    ],
    "sg:phone":"+44 1279 838166",
    "sg:postcode":"CM18 7BH",
    "sg:province":"Essex",
    "sg:tags":[
        "messenger",
        "courier"
    ],
    "wof:name":"Pendragon Ltd",
    "wof:placetype":"venue"
},
  "geometry": {"coordinates":[0.120163,51.756622],"type":"Point"}
}