{
  "type": "Feature",
  "properties": {
    "addr:full":"Shepherds Cottage Buntingford Hertfordshire SG9 0LD",
    "addr:postcode":"sg9 0ld",
    "iso:country":"GB",
    "sg:address":"Shepherds Cottage",
    "sg:city":"Buntingford",
    "sg:classifiers":[
        {
            "category":"Professional",
            "subcategory":"Lawyer & Legal Services",
            "type":"Services"
        }
    ],
    "sg:postcode":"SG9 0LD",
    "sg:province":"Hertfordshire",
    "sg:tags":[
        "solicitor"
    ],
    "wof:name":"Brands Collective Ltd.",
    "wof:placetype":"venue"
},
  "geometry": {"coordinates":[-0.0186349992,51.9463005066],"type":"Point"}
}