{
  "type": "Feature",
  "properties": {
    "iso:country":"GB",
    "sg:address":"54a Trundleys Rd",
    "sg:city":"Deptford",
    "sg:classifiers":[
        {
            "category":"Recreation",
            "subcategory":"Dog Park",
            "type":"Entertainment"
        }
    ],
    "sg:phone":"+44 20 8694 1794",
    "sg:postcode":"SE8 5JG",
    "sg:province":"Greater London",
    "wof:name":"Mucky Pups (Deptford)",
    "wof:placetype":"venue"
},
  "geometry": {"coordinates":[-0.044147,51.48798],"type":"Point"}
}