{
  "type": "Feature",
  "properties": {
    "addr:full":"1-5 George St Aberdeen Aberdeen City AB25 1HZ",
    "addr:housenumber":"1-5",
    "addr:postcode":"ab25 1hz",
    "addr:street":"George St",
    "iso:country":"GB",
    "sg:address":"1-5 George St",
    "sg:city":"Aberdeen",
    "sg:classifiers":[
        {
            "category":"Shopping",
            "subcategory":"Mobile Phones",
            "type":"Retail Goods"
        }
    ],
    "sg:phone":"+44 1224 645000",
    "sg:postcode":"AB25 1HZ",
    "sg:province":"Aberdeen City",
    "wof:name":"DX Communications Ltd",
    "wof:placetype":"venue"
},
  "geometry": {"coordinates":[-2.1006391048,57.1494293213],"type":"Point"}
}