{
  "type": "Feature",
  "properties": {
    "iso:country":"GB",
    "sg:address":"27 Kemplay Rd",
    "sg:city":"London",
    "sg:classifiers":[
        {
            "category":"Professional",
            "type":"Services"
        }
    ],
    "sg:postcode":"NW3 1TA",
    "sg:province":"Greater London",
    "sg:tags":[
        "auctioneer"
    ],
    "wof:name":"Ketterer,R,",
    "wof:placetype":"venue"
},
  "geometry": {"coordinates":[-0.173417,51.556038],"type":"Point"}
}