{
  "type": "Feature",
  "properties": {
    "addr:full":"Coombe Cottage, Colway Cross Teignmouth Devon TQ14 9TJ",
    "addr:postcode":"tq14 9tj",
    "addr:street":"Colway Cross",
    "iso:country":"GB",
    "sg:address":"Coombe Cottage, Colway Cross",
    "sg:city":"Teignmouth",
    "sg:classifiers":[
        {
            "category":"Recreation",
            "subcategory":"Water Park",
            "type":"Entertainment"
        }
    ],
    "sg:postcode":"TQ14 9TJ",
    "sg:province":"Devon",
    "sg:tags":[
        "sport"
    ],
    "wof:name":"Devon Windsurf & Canoe Centre",
    "wof:placetype":"venue"
},
  "geometry": {"coordinates":[-3.5109,50.556652],"type":"Point"}
}