{
  "type": "Feature",
  "properties": {
    "iso:country":"GB",
    "sg:address":"121 Deyes Lane",
    "sg:city":"Liverpool",
    "sg:classifiers":[
        {
            "category":"Fast Food",
            "type":"Food & Drink"
        },
        {
            "category":"Food & Beverages",
            "subcategory":"Groceries & Convenience Stores",
            "type":"Retail Goods"
        }
    ],
    "sg:phone":"+44 151 526 7589",
    "sg:postcode":"L31 6DG",
    "sg:province":"Lancashire",
    "sg:tags":[
        "shop",
        "fish",
        "take",
        "chip",
        "away"
    ],
    "wof:name":"MAGHULL'S PREMIER FISH & CHIP SHOP",
    "wof:placetype":"venue"
},
  "geometry": {"coordinates":[-2.931581,53.515808],"type":"Point"}
}