{
  "type": "Feature",
  "properties": {
    "addr:full":"Wool Lane Midhurst West Sussex GU29 9BX",
    "addr:postcode":"gu29 9bx",
    "addr:street":"Wool Lane",
    "iso:country":"GB",
    "sg:address":"Wool Lane",
    "sg:city":"Midhurst",
    "sg:classifiers":[
        {
            "category":"Bars & Pubs",
            "type":"Food & Drink"
        },
        {
            "category":"Community Center",
            "subcategory":"Social",
            "type":"Public Place"
        }
    ],
    "sg:phone":"+44 1730 813450",
    "sg:postcode":"GU29 9BX",
    "sg:province":"West Sussex",
    "sg:tags":[
        "pubs",
        "house",
        "inn",
        "activity"
    ],
    "wof:name":"The Wheatsheaf Inn",
    "wof:placetype":"venue"
},
  "geometry": {"coordinates":[-0.7391790152,50.985824585],"type":"Point"}
}