{
  "type": "Feature",
  "properties": {
    "addr:full":"Hospital Rd, Pendlebury Manchester Greater Manchester M27 4HA",
    "addr:postcode":"m27 4ha",
    "addr:street":"Hospital Rd",
    "iso:country":"GB",
    "sg:address":"Hospital Rd, Pendlebury",
    "sg:city":"Manchester",
    "sg:classifiers":[
        {
            "category":"Health Services",
            "subcategory":"Hospital",
            "type":"Services"
        },
        {
            "category":"Education",
            "subcategory":"Special Training",
            "type":"Public Place"
        }
    ],
    "sg:postcode":"M27 4HA",
    "sg:province":"Greater Manchester",
    "sg:tags":[
        "school"
    ],
    "wof:name":"Royal Manchester Childrens Hospital",
    "wof:placetype":"venue"
},
  "geometry": {"coordinates":[-2.317914,53.509995],"type":"Point"}
}