{
  "type": "Feature",
  "properties": {
    "addr:full":"Unit B8,, Telford Rd Bicester Oxfordshire OX26 4LD",
    "addr:postcode":"ox26 4ld",
    "addr:street":"Telford Rd",
    "iso:country":"GB",
    "sg:address":"Unit B8,, Telford Rd",
    "sg:city":"Bicester",
    "sg:classifiers":[
        {
            "category":"Government",
            "subcategory":"Post Office",
            "type":"Public Place"
        }
    ],
    "sg:postcode":"OX26 4LD",
    "sg:province":"Oxfordshire",
    "sg:tags":[
        "messenger",
        "courier"
    ],
    "wof:name":"Bac Ii Bac Couriers",
    "wof:placetype":"venue"
},
  "geometry": {"coordinates":[-1.1315490007,51.9028968811],"type":"Point"}
}