{
  "type": "Feature",
  "properties": {
    "addr:full":"Station Road, Wiveliscombe Taunton Devon TA4 2LX",
    "addr:postcode":"ta4 2lx",
    "addr:street":"Station Road",
    "iso:country":"GB",
    "sg:address":"Station Road, Wiveliscombe",
    "sg:city":"Taunton",
    "sg:classifiers":[
        {
            "category":"Farming",
            "subcategory":"Farm",
            "type":"Manufacturing & Wholesale Goods"
        }
    ],
    "sg:phone":"+44 1984 623855",
    "sg:postcode":"TA4 2LX",
    "sg:province":"Devon",
    "sg:tags":[
        "agricultural"
    ],
    "wof:name":"Direct Plant Services",
    "wof:placetype":"venue"
},
  "geometry": {"coordinates":[-3.3088541031,51.0414581299],"type":"Point"}
}