{
  "type": "Feature",
  "properties": {
    "addr:full":"Trannack Mill, Coverack Bridges Helston Cornwall TR13 0LX",
    "addr:postcode":"tr13 0lx",
    "iso:country":"GB",
    "sg:address":"Trannack Mill, Coverack Bridges",
    "sg:city":"Helston",
    "sg:classifiers":[
        {
            "category":"Shopping",
            "subcategory":"Hobbies, Toys, & Games",
            "type":"Retail Goods"
        }
    ],
    "sg:postcode":"TR13 0LX",
    "sg:province":"Cornwall",
    "sg:tags":[
        "toy"
    ],
    "wof:name":"The Toy Workshop",
    "wof:placetype":"venue"
},
  "geometry": {"coordinates":[-5.263879,50.125324],"type":"Point"}
}