{
  "type": "Feature",
  "properties": {
    "addr:full":"Horton Depot, Stanwell Road, Horton Slough Berkshire SL3 9PE",
    "addr:postcode":"sl3 9pe",
    "addr:street":"Stanwell Road",
    "iso:country":"GB",
    "sg:address":"Horton Depot, Stanwell Road, Horton",
    "sg:city":"Slough",
    "sg:classifiers":[
        {
            "category":"Home & Garden",
            "subcategory":"Building Materials",
            "type":"Retail Goods"
        }
    ],
    "sg:phone":"+44 1753 686223",
    "sg:postcode":"SL3 9PE",
    "sg:province":"Berkshire",
    "sg:tags":[
        "fencing"
    ],
    "wof:name":"Fence Line",
    "wof:placetype":"venue"
},
  "geometry": {"coordinates":[-0.542158,51.47316],"type":"Point"}
}