{
  "type": "Feature",
  "properties": {
    "addr:full":"44 Hookstone Avenue Harrogate North Yorkshire HG2 8ER",
    "addr:housenumber":"44",
    "addr:postcode":"hg2 8er",
    "addr:street":"Hookstone Avenue",
    "iso:country":"GB",
    "sg:address":"44 Hookstone Avenue",
    "sg:city":"Harrogate",
    "sg:classifiers":[
        {
            "category":"Professional",
            "subcategory":"Engineering",
            "type":"Services"
        }
    ],
    "sg:phone":"+44 1423 867111",
    "sg:postcode":"HG2 8ER",
    "sg:province":"North Yorkshire",
    "sg:tags":[
        "contractor",
        "electrical",
        "engineer"
    ],
    "wof:name":"Glenn Bailey Electrician",
    "wof:placetype":"venue"
},
  "geometry": {"coordinates":[-1.5298089981,53.9773025513],"type":"Point"}
}