{
  "type": "Feature",
  "properties": {
    "iso:country":"GB",
    "sg:address":"Tregwindles, St Breock",
    "sg:city":"Wadebridge",
    "sg:classifiers":[
        {
            "category":"Farming",
            "subcategory":"Livestock Farm",
            "type":"Manufacturing & Wholesale Goods"
        }
    ],
    "sg:postcode":"PL27 7LF",
    "sg:province":"Cornwall",
    "sg:tags":[
        "others"
    ],
    "wof:name":"W H Pedlar",
    "wof:placetype":"venue"
},
  "geometry": {"coordinates":[-4.8380241394,50.5181884766],"type":"Point"}
}