{
  "type": "Feature",
  "properties": {
    "iso:country":"GB",
    "sg:address":"10 West Way",
    "sg:city":"Luton",
    "sg:classifiers":[
        {
            "category":"Fast Food",
            "type":"Food & Drink"
        },
        {
            "category":"Food & Beverages",
            "subcategory":"Meat & Fish",
            "type":"Retail Goods"
        }
    ],
    "sg:phone":"+44 1582 402464",
    "sg:postcode":"LU2 8DZ",
    "sg:province":"Bedfordshire",
    "sg:tags":[
        "shop",
        "chip"
    ],
    "wof:name":"West Way Fish 'N' Chips",
    "wof:placetype":"venue"
},
  "geometry": {"coordinates":[-0.3781690001,51.9273986816],"type":"Point"}
}