{
  "type": "Feature",
  "properties": {
    "iso:country":"GB",
    "sg:address":"19 Market Street",
    "sg:city":"Wotton-under-edge",
    "sg:classifiers":[
        {
            "category":"Building & Trades",
            "subcategory":"Plumbing",
            "type":"Services"
        }
    ],
    "sg:phone":"+44 1453 842764",
    "sg:postcode":"GL12 7AE",
    "sg:province":"Gloucestershire",
    "sg:tags":[
        "central",
        "heating"
    ],
    "wof:name":"G C Kitchen Ltd.",
    "wof:placetype":"venue"
},
  "geometry": {"coordinates":[-2.353909,51.63699],"type":"Point"}
}