{
  "type": "Feature",
  "properties": {
    "addr:full":"69 Windsor Road, Prestwich Manchester Greater Manchester M25 0DB",
    "addr:housenumber":"69",
    "addr:postcode":"m25 0db",
    "addr:street":"Windsor Road",
    "iso:country":"GB",
    "sg:address":"69 Windsor Road, Prestwich",
    "sg:city":"Manchester",
    "sg:classifiers":[
        {
            "category":"Professional",
            "subcategory":"Accounting & Tax Preparation",
            "type":"Services"
        }
    ],
    "sg:phone":"+44 161 795 3905",
    "sg:postcode":"M25 0DB",
    "sg:province":"Greater Manchester",
    "sg:tags":[
        "accountant",
        "activity"
    ],
    "wof:name":"Millers",
    "wof:placetype":"venue"
},
  "geometry": {"coordinates":[-2.253716,53.524769],"type":"Point"}
}