{
  "type": "Feature",
  "properties": {
    "iso:country":"GB",
    "sg:address":"1 Dyche Drive",
    "sg:city":"Sheffield",
    "sg:classifiers":[
        {
            "category":"Organizations",
            "subcategory":"Non-profit Organization",
            "type":"Services"
        }
    ],
    "sg:phone":"+44 114 237 5921",
    "sg:postcode":"S8 8DN",
    "sg:province":"Derbyshire",
    "sg:tags":[
        "organisation",
        "voluntary",
        "charity"
    ],
    "wof:name":"B & J Neighbourhood & Safety Forum",
    "wof:placetype":"venue"
},
  "geometry": {"coordinates":[-1.463157,53.322556],"type":"Point"}
}