{
  "type": "Feature",
  "properties": {
    "iso:country":"GB",
    "sg:address":"23 Goodmayes Rd, Goodmayes",
    "sg:city":"Ilford",
    "sg:classifiers":[
        {
            "category":"Professional",
            "subcategory":"Printing & Photocopies",
            "type":"Services"
        }
    ],
    "sg:phone":"+44 20 8983 8281",
    "sg:postcode":"IG3 9UH",
    "sg:province":"Essex",
    "sg:tags":[
        "plate",
        "lithographic",
        "maker"
    ],
    "wof:name":"The Bargain Box",
    "wof:placetype":"venue"
},
  "geometry": {"coordinates":[0.110718,51.566269],"type":"Point"}
}