{
  "type": "Feature",
  "properties": {
    "addr:full":"Suna Barony Road, Auchinleck Cumnock East Ayrshire KA18 2LL",
    "addr:postcode":"ka18 2ll",
    "addr:street":"Barony Road;Cumnock East",
    "iso:country":"GB",
    "sg:address":"Suna Barony Road, Auchinleck",
    "sg:city":"Cumnock",
    "sg:classifiers":[
        {
            "category":"Shopping",
            "subcategory":"Mobile Phones",
            "type":"Retail Goods"
        },
        {
            "category":"Communications",
            "type":"Services"
        }
    ],
    "sg:phone":"+44 1290 422135",
    "sg:postcode":"KA18 2LL",
    "sg:province":"East Ayrshire",
    "sg:tags":[
        "telecommunication"
    ],
    "wof:name":"Shield-Mor",
    "wof:placetype":"venue"
},
  "geometry": {"coordinates":[-4.2952737808,55.4740257263],"type":"Point"}
}