{
  "type": "Feature",
  "properties": {
    "iso:country":"GB",
    "sg:address":"16 High St",
    "sg:city":"Uxbridge",
    "sg:classifiers":[
        {
            "category":"Building & Trades",
            "subcategory":"Construction",
            "type":"Services"
        }
    ],
    "sg:postcode":"UB8 1JN",
    "sg:province":"Buckinghamshire",
    "sg:tags":[
        "builder"
    ],
    "wof:name":"Mallet Construction Ltd",
    "wof:placetype":"venue"
},
  "geometry": {"coordinates":[-0.476724,51.545052],"type":"Point"}
}