{
  "type": "Feature",
  "properties": {
    "iso:country":"GB",
    "sg:address":"6 East Park, Thursby",
    "sg:city":"Carlisle",
    "sg:classifiers":[
        {
            "category":"Professional",
            "subcategory":"Printing & Photocopies",
            "type":"Services"
        }
    ],
    "sg:phone":"+44 16973 42767",
    "sg:postcode":"CA5 6QE",
    "sg:province":"Cumbria",
    "sg:tags":[
        "printer"
    ],
    "wof:name":"Brett Mitton Printing",
    "wof:placetype":"venue"
},
  "geometry": {"coordinates":[-3.0546,54.841949],"type":"Point"}
}