{
  "type": "Feature",
  "properties": {
    "iso:country":"GB",
    "sg:address":"Unit 6a, Arrow Trading Est, Audenshaw",
    "sg:city":"Manchester",
    "sg:classifiers":[
        {
            "category":"Retail",
            "subcategory":"Auto Repair",
            "type":"Services"
        }
    ],
    "sg:phone":"+44 161 336 3284",
    "sg:postcode":"M34 5LR",
    "sg:province":"Greater Manchester",
    "sg:tags":[
        "modification",
        "garage"
    ],
    "wof:name":"B Galley Motors",
    "wof:placetype":"venue"
},
  "geometry": {"coordinates":[-2.1232039928,53.4637184143],"type":"Point"}
}