{
  "type": "Feature",
  "properties": {
    "addr:full":"2&3 Victory Park, Trident Close Rochester Kent ME2 4ER",
    "addr:housenumber":"2 & 3",
    "addr:postcode":"me2 4er",
    "addr:street":"Victory Park Trident Close",
    "iso:country":"GB",
    "sg:address":"2&3 Victory Park, Trident Close",
    "sg:city":"Rochester",
    "sg:classifiers":[
        {
            "category":"Manufacturing",
            "subcategory":"Tools & Machinery",
            "type":"Manufacturing & Wholesale Goods"
        }
    ],
    "sg:phone":"+44 1634 717766",
    "sg:postcode":"ME2 4ER",
    "sg:province":"Kent",
    "sg:tags":[
        "design",
        "maker"
    ],
    "wof:name":"Medway T & G Services Ltd.",
    "wof:placetype":"venue"
},
  "geometry": {"coordinates":[0.51451,51.39484],"type":"Point"}
}