{
  "type": "Feature",
  "properties": {
    "iso:country":"GB",
    "sg:address":"51 Sackville Road",
    "sg:city":"Bexhill-on-sea",
    "sg:classifiers":[
        {
            "category":"Recreation",
            "subcategory":"Dog Park",
            "type":"Entertainment"
        }
    ],
    "sg:phone":"+44 1424 733110",
    "sg:postcode":"TN39 3JD",
    "sg:province":"East Sussex",
    "wof:name":"Scruffs",
    "wof:placetype":"venue"
},
  "geometry": {"coordinates":[0.470266,50.838295],"type":"Point"}
}