{
  "type": "Feature",
  "properties": {
    "addr:full":"8 Stather Road, Burton Upon Stather Scunthorpe Lincolnshire DN15 9DH",
    "addr:housenumber":"8",
    "addr:postcode":"dn15 9dh",
    "addr:street":"Stather Road",
    "iso:country":"GB",
    "sg:address":"8 Stather Road, Burton Upon Stather",
    "sg:city":"Scunthorpe",
    "sg:classifiers":[
        {
            "category":"Professional",
            "subcategory":"Computer Services",
            "type":"Services"
        }
    ],
    "sg:postcode":"DN15 9DH",
    "sg:province":"Lincolnshire",
    "sg:tags":[
        "system",
        "software"
    ],
    "wof:name":"D L K Ltd.",
    "wof:placetype":"venue"
},
  "geometry": {"coordinates":[-0.6903079748,53.6538848877],"type":"Point"}
}