{
  "type": "Feature",
  "properties": {
    "iso:country":"GB",
    "sg:address":"117 Worcester Road",
    "sg:city":"Stourbridge",
    "sg:classifiers":[
        {
            "category":"Food & Beverages",
            "subcategory":"Groceries & Convenience Stores",
            "type":"Retail Goods"
        }
    ],
    "sg:phone":"+44 1562 882565",
    "sg:postcode":"DY9 0NG",
    "sg:province":"West Midlands",
    "wof:name":"Spar Hagley",
    "wof:placetype":"venue"
},
  "geometry": {"coordinates":[-2.14022,52.435974],"type":"Point"}
}