{
  "type": "Feature",
  "properties": {
    "addr:full":"45 Kavanaghs Rd Brentwood Essex CM14 4NE",
    "addr:housenumber":"45",
    "addr:postcode":"cm14 4ne",
    "addr:street":"Kavanaghs Rd",
    "iso:country":"GB",
    "sg:address":"45 Kavanaghs Rd",
    "sg:city":"Brentwood",
    "sg:classifiers":[
        {
            "category":"Building & Trades",
            "subcategory":"Construction",
            "type":"Services"
        }
    ],
    "sg:phone":"+44 1277 212076",
    "sg:postcode":"CM14 4NE",
    "sg:province":"Essex",
    "sg:tags":[
        "tiling",
        "contractor"
    ],
    "wof:name":"Port,Charles,",
    "wof:placetype":"venue"
},
  "geometry": {"coordinates":[0.2887069881,51.6139564514],"type":"Point"}
}