{
  "type": "Feature",
  "properties": {
    "addr:full":"17 Swansea Rd Llanelli Carmarthenshire SA15 3YT",
    "addr:housenumber":"17",
    "addr:postcode":"sa15 3yt",
    "addr:street":"Swansea Rd",
    "iso:country":"GB",
    "sg:address":"17 Swansea Rd",
    "sg:city":"Llanelli",
    "sg:classifiers":[
        {
            "category":"Taxi",
            "type":"Transportation"
        }
    ],
    "sg:phone":"+44 1554 757635",
    "sg:postcode":"SA15 3YT",
    "sg:province":"Carmarthenshire",
    "sg:tags":[
        "mini",
        "cab"
    ],
    "wof:name":"Amber Taxis",
    "wof:placetype":"venue"
},
  "geometry": {"coordinates":[-4.154822,51.684422],"type":"Point"}
}