{
  "type": "Feature",
  "properties": {
    "iso:country":"GB",
    "sg:address":"7 St James Place East, The Hoe",
    "sg:city":"Plymouth",
    "sg:classifiers":[
        {
            "category":"Travel",
            "subcategory":"Hotels & Motels",
            "type":"Entertainment"
        }
    ],
    "sg:phone":"+44 1752 261459",
    "sg:postcode":"PL1 3AS",
    "sg:province":"Devon",
    "sg:tags":[
        "house",
        "guest"
    ],
    "wof:name":"Peter & Lisa Tozer",
    "wof:placetype":"venue"
},
  "geometry": {"coordinates":[-4.146968,50.367199],"type":"Point"}
}