{
  "type": "Feature",
  "properties": {
    "addr:full":"Western House, Salt Works Lane, Weston Stafford Staffordshire ST18 0JE",
    "addr:postcode":"st18 0je",
    "addr:street":"Works Lane",
    "iso:country":"GB",
    "sg:address":"Western House, Salt Works Lane, Weston",
    "sg:city":"Stafford",
    "sg:classifiers":[
        {
            "category":"Retail",
            "subcategory":"Auto Rental",
            "type":"Services"
        }
    ],
    "sg:phone":"+44 1889 270700",
    "sg:postcode":"ST18 0JE",
    "sg:province":"Staffordshire",
    "sg:tags":[
        "truck",
        "hire",
        "van"
    ],
    "wof:name":"Stafford Car & Van Hire Co",
    "wof:placetype":"venue"
},
  "geometry": {"coordinates":[-2.036329,52.837608],"type":"Point"}
}