{
  "type": "Feature",
  "properties": {
    "addr:full":"349 The Grn, Eccleston Chorley Lancashire PR7 5PH",
    "addr:housenumber":"349",
    "addr:postcode":"pr7 5ph",
    "addr:street":"The Grn",
    "iso:country":"GB",
    "sg:address":"349 The Grn, Eccleston",
    "sg:city":"Chorley",
    "sg:classifiers":[
        {
            "category":"Professional",
            "subcategory":"Management & Consulting",
            "type":"Services"
        }
    ],
    "sg:phone":"+44 1257 450991",
    "sg:postcode":"PR7 5PH",
    "sg:province":"Lancashire",
    "sg:tags":[
        "sport"
    ],
    "sg:website":"http://www.essellesports.com",
    "wof:name":"Esselle Sports Management Ltd.",
    "wof:placetype":"venue"
},
  "geometry": {"coordinates":[-2.7317950726,53.6502914429],"type":"Point"}
}