{
  "type": "Feature",
  "properties": {
    "addr:full":"9 Loseby Lane Leicester Leicestershire LE1 5DR",
    "addr:housenumber":"9",
    "addr:postcode":"le1 5dr",
    "addr:street":"Loseby Lane",
    "iso:country":"GB",
    "sg:address":"9 Loseby Lane",
    "sg:city":"Leicester",
    "sg:classifiers":[
        {
            "category":"Shopping",
            "subcategory":"Clothing, Apparel, & Fashions",
            "type":"Retail Goods"
        }
    ],
    "sg:phone":"+44 116 291 1444",
    "sg:postcode":"LE1 5DR",
    "sg:province":"Leicestershire",
    "sg:tags":[
        "lingerie",
        "hosiery"
    ],
    "wof:name":"Harwayes Ltd.",
    "wof:placetype":"venue"
},
  "geometry": {"coordinates":[-1.135598,52.634712],"type":"Point"}
}