{
  "type": "Feature",
  "properties": {
    "addr:full":"Caretaker, 2 Millbrook House, Willow Walk Swindon Wiltshire SN4 0SD",
    "addr:housenumber":"2",
    "addr:postcode":"sn4 0sd",
    "addr:street":"Caretaker;Willow Walk",
    "iso:country":"GB",
    "sg:address":"Caretaker, 2 Millbrook House, Willow Walk",
    "sg:city":"Swindon",
    "sg:classifiers":[
        {
            "category":"Social Services",
            "subcategory":"Adult Care",
            "type":"Services"
        }
    ],
    "sg:phone":"+44 845 601 4232",
    "sg:postcode":"SN4 0SD",
    "sg:province":"Wiltshire",
    "sg:tags":[
        "housing",
        "sheltered"
    ],
    "wof:name":"S Bell",
    "wof:placetype":"venue"
},
  "geometry": {"coordinates":[-1.78948,51.523579],"type":"Point"}
}