{
  "type": "Feature",
  "properties": {
    "addr:full":"1-3 Church Road, Lawrence Hill Bristol City of Bristol BS5 9JJ",
    "addr:housenumber":"1-3",
    "addr:postcode":"bs5 9jj",
    "addr:street":"Church Road",
    "iso:country":"GB",
    "sg:address":"1-3 Church Road, Lawrence Hill",
    "sg:city":"Bristol",
    "sg:classifiers":[
        {
            "category":"Retail",
            "subcategory":"Auto Repair",
            "type":"Services"
        }
    ],
    "sg:phone":"+44 117 935 1060",
    "sg:postcode":"BS5 9JJ",
    "sg:province":"City of Bristol",
    "sg:tags":[
        "garage"
    ],
    "wof:name":"Machine Mart Ltd.",
    "wof:placetype":"venue"
},
  "geometry": {"coordinates":[-2.5590889454,51.4584083557],"type":"Point"}
}