{
  "type": "Feature",
  "properties": {
    "addr:full":"110 High Street Crediton Devon EX17 3LF",
    "addr:housenumber":"110",
    "addr:postcode":"ex17 3lf",
    "addr:street":"High Street",
    "iso:country":"GB",
    "sg:address":"110 High Street",
    "sg:city":"Crediton",
    "sg:classifiers":[
        {
            "category":"Health Services",
            "subcategory":"Dentist",
            "type":"Services"
        }
    ],
    "sg:phone":"+44 1363 772020",
    "sg:postcode":"EX17 3LF",
    "sg:province":"Devon",
    "wof:name":"James Hull & Associates",
    "wof:placetype":"venue"
},
  "geometry": {"coordinates":[-3.660659,50.790813],"type":"Point"}
}