{
  "type": "Feature",
  "properties": {
    "addr:full":"Haslingden Rd, Rawtenstall Rossendale Lancashire BB4 6QU",
    "addr:postcode":"bb4 6qu",
    "addr:street":"Haslingden Rd",
    "iso:country":"GB",
    "sg:address":"Haslingden Rd, Rawtenstall",
    "sg:city":"Rossendale",
    "sg:classifiers":[
        {
            "category":"Education",
            "subcategory":"Library",
            "type":"Public Place"
        }
    ],
    "sg:phone":"+44 1706 227911",
    "sg:postcode":"BB4 6QU",
    "sg:province":"Lancashire",
    "sg:tags":[
        "book"
    ],
    "wof:name":"Rawtenstall Library",
    "wof:placetype":"venue"
},
  "geometry": {"coordinates":[-2.309053,53.696751],"type":"Point"}
}