{
  "type": "Feature",
  "properties": {
    "iso:country":"GB",
    "sg:address":"4 Duke St",
    "sg:city":"London",
    "sg:classifiers":[
        {
            "category":"Professional",
            "subcategory":"Business Services",
            "type":"Services"
        }
    ],
    "sg:postcode":"W1U 3EH",
    "sg:province":"Greater London",
    "sg:tags":[
        "distributor",
        "film"
    ],
    "wof:name":"Edge Production",
    "wof:placetype":"venue"
},
  "geometry": {"coordinates":[-0.152539,51.516155],"type":"Point"}
}