{
  "type": "Feature",
  "properties": {
    "addr:full":"4 Duke St London Greater London W1U 3EH",
    "addr:housenumber":"4",
    "addr:postcode":"w1u 3eh",
    "addr:street":"Duke St",
    "iso:country":"GB",
    "sg:address":"4 Duke St",
    "sg:city":"London",
    "sg:classifiers":[
        {
            "category":"Professional",
            "subcategory":"Business Services",
            "type":"Services"
        }
    ],
    "sg:postcode":"W1U 3EH",
    "sg:province":"Greater London",
    "sg:tags":[
        "distributor",
        "film"
    ],
    "wof:name":"Edge Production",
    "wof:placetype":"venue"
},
  "geometry": {"coordinates":[-0.152539,51.516155],"type":"Point"}
}