{
  "type": "Feature",
  "properties": {
    "iso:country":"GB",
    "sg:address":"Unit 19-20 Aberafan Centre",
    "sg:city":"Port Talbot",
    "sg:classifiers":[
        {
            "category":"Shopping",
            "subcategory":"Gifts & Souvenirs",
            "type":"Retail Goods"
        }
    ],
    "sg:phone":"+44 1639 894430",
    "sg:postcode":"SA13 1PB",
    "sg:province":"Neath Port Talbot",
    "sg:tags":[
        "poster",
        "card"
    ],
    "wof:name":"Centre Cards",
    "wof:placetype":"venue"
},
  "geometry": {"coordinates":[-3.78549,51.59676],"type":"Point"}
}