{
  "type": "Feature",
  "properties": {
    "iso:country":"GB",
    "sg:address":"67 Elliott Drive, Inkersall",
    "sg:city":"Chesterfield",
    "sg:classifiers":[
        {
            "category":"Personal",
            "subcategory":"Beauty Salon",
            "type":"Services"
        }
    ],
    "sg:phone":"+44 1246 281129",
    "sg:postcode":"S43 3DZ",
    "sg:province":"Derbyshire",
    "sg:tags":[
        "unisex",
        "hairdresser"
    ],
    "wof:name":"Kwik Kutz",
    "wof:placetype":"venue"
},
  "geometry": {"coordinates":[-1.370199,53.248631],"type":"Point"}
}