{
  "type": "Feature",
  "properties": {
    "addr:full":"16 The Merry Hill Centre Brierley Hill West Midlands DY5 1SH",
    "addr:housenumber":"16",
    "addr:postcode":"dy5 1sh",
    "addr:street":"The;Hill;Brierley Hill",
    "iso:country":"GB",
    "sg:address":"16 The Merry Hill Centre",
    "sg:city":"Brierley Hill",
    "sg:classifiers":[
        {
            "category":"Professional",
            "subcategory":"Employment Agencies",
            "type":"Services"
        }
    ],
    "sg:phone":"+44 1384 554950",
    "sg:postcode":"DY5 1SH",
    "sg:province":"West Midlands",
    "sg:tags":[
        "consultant"
    ],
    "wof:name":"Merryhill Jobcentre",
    "wof:placetype":"venue"
},
  "geometry": {"coordinates":[-2.1213300228,52.4831504822],"type":"Point"}
}