{
  "type": "Feature",
  "properties": {
    "addr:full":"2 Presmere Road, Pettistree Woodbridge Suffolk IP13 0JA",
    "addr:housenumber":"2",
    "addr:postcode":"ip13 0ja",
    "addr:street":"Presmere Road",
    "iso:country":"GB",
    "sg:address":"2 Presmere Road, Pettistree",
    "sg:city":"Woodbridge",
    "sg:classifiers":[
        {
            "category":"Professional",
            "subcategory":"Engineering",
            "type":"Services"
        },
        {
            "category":"Building & Trades",
            "subcategory":"Electrical",
            "type":"Services"
        }
    ],
    "sg:phone":"+44 1394 382586",
    "sg:postcode":"IP13 0JA",
    "sg:province":"Suffolk",
    "sg:tags":[
        "engineer",
        "electrician",
        "contractor"
    ],
    "wof:name":"Addison Electrical",
    "wof:placetype":"venue"
},
  "geometry": {"coordinates":[1.35342,52.143959],"type":"Point"}
}