{
  "type": "Feature",
  "properties": {
    "addr:full":"4 Clatter Cottages Caersws Powys SY17 5NL",
    "addr:housenumber":"4",
    "addr:postcode":"sy17 5nl",
    "addr:street":"Clatter;Caersws",
    "iso:country":"GB",
    "sg:address":"4 Clatter Cottages",
    "sg:city":"Caersws",
    "sg:classifiers":[
        {
            "category":"Building & Trades",
            "subcategory":"Construction",
            "type":"Services"
        }
    ],
    "sg:phone":"+44 1686 420270",
    "sg:postcode":"SY17 5NL",
    "sg:province":"Powys",
    "sg:tags":[
        "decorator",
        "painter"
    ],
    "wof:name":"Grosvenor & Jones",
    "wof:placetype":"venue"
},
  "geometry": {"coordinates":[-3.4772670269,52.5154876709],"type":"Point"}
}