{
  "type": "Feature",
  "properties": {
    "addr:full":"44 Chancery Lane Beckenham Kent BR3 6NR",
    "addr:housenumber":"44",
    "addr:postcode":"br3 6nr",
    "addr:street":"Chancery Lane",
    "iso:country":"GB",
    "sg:address":"44 Chancery Lane",
    "sg:city":"Beckenham",
    "sg:classifiers":[
        {
            "category":"Shopping",
            "subcategory":"Computers & Home Electronics",
            "type":"Retail Goods"
        }
    ],
    "sg:phone":"+44 20 8658 9988",
    "sg:postcode":"BR3 6NR",
    "sg:province":"Kent",
    "wof:name":"Anglo European Computers",
    "wof:placetype":"venue"
},
  "geometry": {"coordinates":[-0.019422,51.406303],"type":"Point"}
}