{
  "type": "Feature",
  "properties": {
    "addr:full":"Bates Business Centre, Church Rd Romford Essex RM3 0JF",
    "addr:postcode":"rm3 0jf",
    "addr:street":"Church Rd",
    "iso:country":"GB",
    "sg:address":"Bates Business Centre, Church Rd",
    "sg:city":"Romford",
    "sg:classifiers":[
        {
            "category":"Building & Trades",
            "subcategory":"Construction",
            "type":"Services"
        }
    ],
    "sg:phone":"+44 1708 370333",
    "sg:postcode":"RM3 0JF",
    "sg:province":"Essex",
    "sg:tags":[
        "pipework",
        "contractor"
    ],
    "wof:name":"Spirit League Engineering Ltd",
    "wof:placetype":"venue"
},
  "geometry": {"coordinates":[0.24081,51.596779],"type":"Point"}
}