{
  "type": "Feature",
  "properties": {
    "addr:full":"Maypole Street, Wombourne Wolverhampton Shropshire WV5 9JB",
    "addr:postcode":"wv5 9jb",
    "addr:street":"Maypole Street",
    "iso:country":"GB",
    "sg:address":"Maypole Street, Wombourne",
    "sg:city":"Wolverhampton",
    "sg:classifiers":[
        {
            "category":"Health Services",
            "subcategory":"Optometrist",
            "type":"Services"
        }
    ],
    "sg:phone":"+44 1902 893732",
    "sg:postcode":"WV5 9JB",
    "sg:province":"Shropshire",
    "sg:tags":[
        "optician"
    ],
    "wof:name":"Perrigo Opticians",
    "wof:placetype":"venue"
},
  "geometry": {"coordinates":[-2.1873390675,52.5368499756],"type":"Point"}
}