{
  "type": "Feature",
  "properties": {
    "addr:full":"Gladeside Court, Succombs Hill Warlingham Kent CR6 9JG",
    "addr:postcode":"cr6 9jg",
    "addr:street":"Gladeside;Succombs Hill",
    "iso:country":"GB",
    "sg:address":"Gladeside Court, Succombs Hill",
    "sg:city":"Warlingham",
    "sg:classifiers":[
        {
            "category":"Shopping",
            "subcategory":"Pharmacy",
            "type":"Retail Goods"
        }
    ],
    "sg:postcode":"CR6 9JG",
    "sg:province":"Kent",
    "sg:tags":[
        "medicine",
        "therapy"
    ],
    "wof:name":"Alisa Marino",
    "wof:placetype":"venue"
},
  "geometry": {"coordinates":[-0.067107,51.300205],"type":"Point"}
}