{
  "type": "Feature",
  "properties": {
    "addr:full":"Unit 1, Fair Oak Court Exeter Devon EX5 2BB",
    "addr:housenumber":"unit 1",
    "addr:postcode":"ex5 2bb",
    "addr:street":"Fair Oak Court",
    "iso:country":"GB",
    "sg:address":"Unit 1, Fair Oak Court",
    "sg:city":"Exeter",
    "sg:classifiers":[
        {
            "category":"Government",
            "subcategory":"Police Station",
            "type":"Public Place"
        }
    ],
    "sg:phone":"+44 1392 444700",
    "sg:postcode":"EX5 2BB",
    "sg:province":"Devon",
    "sg:tags":[
        "support"
    ],
    "wof:name":"Police Resources International Ltd.",
    "wof:placetype":"venue"
},
  "geometry": {"coordinates":[-3.4096300602,50.7305412292],"type":"Point"}
}