{
  "type": "Feature",
  "properties": {
    "addr:full":"Long Reach House, Wardington Banbury Northamptonshire OX17 1RU",
    "addr:postcode":"ox17 1ru",
    "iso:country":"GB",
    "sg:address":"Long Reach House, Wardington",
    "sg:city":"Banbury",
    "sg:classifiers":[
        {
            "category":"Manufacturing",
            "subcategory":"Building Materials",
            "type":"Manufacturing & Wholesale Goods"
        }
    ],
    "sg:postcode":"OX17 1RU",
    "sg:province":"Northamptonshire",
    "sg:tags":[
        "shutter",
        "supp",
        "door"
    ],
    "wof:name":"Long Reach Marketing",
    "wof:placetype":"venue"
},
  "geometry": {"coordinates":[-1.284406,52.115826],"type":"Point"}
}