{
  "type": "Feature",
  "properties": {
    "addr:full":"4 Marine Parade Barmouth Gwynedd LL42 1NA",
    "addr:housenumber":"4",
    "addr:postcode":"ll42 1na",
    "addr:street":"Marine Parade",
    "iso:country":"GB",
    "sg:address":"4 Marine Parade",
    "sg:city":"Barmouth",
    "sg:classifiers":[
        {
            "category":"Travel",
            "subcategory":"Hotels & Motels",
            "type":"Entertainment"
        }
    ],
    "sg:postcode":"LL42 1NA",
    "sg:province":"Gwynedd",
    "sg:tags":[
        "house",
        "guest"
    ],
    "wof:name":"Leamington House Hotel",
    "wof:placetype":"venue"
},
  "geometry": {"coordinates":[-4.058031,52.722607],"type":"Point"}
}