{
  "type": "Feature",
  "properties": {
    "addr:full":"Unit 1, Papermill End Birmingham West Midlands B44 8NA",
    "addr:housenumber":"unit 1",
    "addr:postcode":"b44 8na",
    "addr:street":"Papermill End",
    "iso:country":"GB",
    "sg:address":"Unit 1, Papermill End",
    "sg:city":"Birmingham",
    "sg:classifiers":[
        {
            "category":"Professional",
            "subcategory":"Testing Lab",
            "type":"Services"
        },
        {
            "category":"Retail",
            "subcategory":"Auto Repair",
            "type":"Services"
        }
    ],
    "sg:phone":"+44 121 356 0124",
    "sg:postcode":"B44 8NA",
    "sg:province":"West Midlands",
    "sg:tags":[
        "modification",
        "garage",
        "mot"
    ],
    "wof:name":"M O T Testing Services",
    "wof:placetype":"venue"
},
  "geometry": {"coordinates":[-1.898301959,52.5337028503],"type":"Point"}
}