{
  "type": "Feature",
  "properties": {
    "addr:full":"158 Victoria Rise, Clapham London Greater London SW4 0NW",
    "addr:housenumber":"158",
    "addr:postcode":"sw4 0nw",
    "addr:street":"Victoria Rise",
    "iso:country":"GB",
    "sg:address":"158 Victoria Rise, Clapham",
    "sg:city":"London",
    "sg:classifiers":[
        {
            "category":"Professional",
            "subcategory":"Business Services",
            "type":"Services"
        }
    ],
    "sg:phone":"+44 20 7622 0688",
    "sg:postcode":"SW4 0NW",
    "sg:province":"Greater London",
    "sg:tags":[
        "planning",
        "design"
    ],
    "wof:name":"Ashwell Construction Co. Ltd.",
    "wof:placetype":"venue"
},
  "geometry": {"coordinates":[-0.1489800066,51.4663925171],"type":"Point"}
}