{
  "type": "Feature",
  "properties": {
    "addr:full":"Hope Chapel, Battle Lane, Chew Magna Bristol Somerset BS40 8PS",
    "addr:postcode":"bs40 8ps",
    "addr:street":"Battle Lane",
    "iso:country":"GB",
    "sg:address":"Hope Chapel, Battle Lane, Chew Magna",
    "sg:city":"Bristol",
    "sg:classifiers":[
        {
            "category":"Professional",
            "subcategory":"Advertising",
            "type":"Services"
        }
    ],
    "sg:phone":"+44 1275 333777",
    "sg:postcode":"BS40 8PS",
    "sg:province":"Somerset",
    "sg:tags":[
        "agency"
    ],
    "wof:name":"Village Design & Communications Ltd.",
    "wof:placetype":"venue"
},
  "geometry": {"coordinates":[-2.611749,51.3657],"type":"Point"}
}