{
  "type": "Feature",
  "properties": {
    "addr:full":"129 Poplars Avenue Warrington Cheshire WA2 9LW",
    "addr:housenumber":"129",
    "addr:postcode":"wa2 9lw",
    "addr:street":"Poplars Avenue",
    "iso:country":"GB",
    "sg:address":"129 Poplars Avenue",
    "sg:city":"Warrington",
    "sg:classifiers":[
        {
            "category":"Food & Beverages",
            "subcategory":"Meat & Fish",
            "type":"Retail Goods"
        }
    ],
    "sg:phone":"+44 1925 811886",
    "sg:postcode":"WA2 9LW",
    "sg:province":"Cheshire",
    "sg:tags":[
        "butcher"
    ],
    "wof:name":"Brian Ball",
    "wof:placetype":"venue"
},
  "geometry": {"coordinates":[-2.57562,53.410786],"type":"Point"}
}