{
  "type": "Feature",
  "properties": {
    "addr:full":"464 Edinburgh Rd Glasgow Glasgow City G33 3AL",
    "addr:housenumber":"464",
    "addr:postcode":"g33 3al",
    "addr:street":"Edinburgh Rd",
    "iso:country":"GB",
    "sg:address":"464 Edinburgh Rd",
    "sg:city":"Glasgow",
    "sg:classifiers":[
        {
            "category":"Food & Beverages",
            "subcategory":"Fruits & Vegetables",
            "type":"Retail Goods"
        }
    ],
    "sg:postcode":"G33 3AL",
    "sg:province":"Glasgow City",
    "sg:tags":[
        "greengrocer"
    ],
    "wof:name":"Tominey,W,",
    "wof:placetype":"venue"
},
  "geometry": {"coordinates":[-4.1814608574,55.8628158569],"type":"Point"}
}