{
  "type": "Feature",
  "properties": {
    "iso:country":"GB",
    "sg:address":"7 Lyons Cres",
    "sg:city":"Tonbridge",
    "sg:classifiers":[
        {
            "category":"Professional",
            "subcategory":"Lawyer & Legal Services",
            "type":"Services"
        }
    ],
    "sg:phone":"+44 1732 365831",
    "sg:postcode":"TN9 1EX",
    "sg:province":"Kent",
    "sg:tags":[
        "advice",
        "counselling"
    ],
    "wof:name":"Tonbridge Young Womens Project",
    "wof:placetype":"venue"
},
  "geometry": {"coordinates":[0.2760629952,51.1959342957],"type":"Point"}
}