{
  "type": "Feature",
  "properties": {
    "addr:full":"Meadowbrook Cottage, Green Lane Deeside Flintshire CH5 2LH",
    "addr:postcode":"ch5 2lh",
    "addr:street":"Green Lane",
    "iso:country":"GB",
    "sg:address":"Meadowbrook Cottage, Green Lane",
    "sg:city":"Deeside",
    "sg:classifiers":[
        {
            "category":"Retail",
            "subcategory":"Repair Shop",
            "type":"Services"
        }
    ],
    "sg:postcode":"CH5 2LH",
    "sg:province":"Flintshire",
    "sg:tags":[
        "plant",
        "machinery"
    ],
    "wof:name":"J R Plant Services",
    "wof:placetype":"venue"
},
  "geometry": {"coordinates":[-3.024987936,53.2024803162],"type":"Point"}
}