{
  "type": "Feature",
  "properties": {
    "addr:full":"Northwood Pk Rd, Bushbury Wolverhampton Staffordshire WV10 8ER",
    "addr:postcode":"wv10 8er",
    "addr:street":"Northwood Pk Rd",
    "iso:country":"GB",
    "sg:address":"Northwood Pk Rd, Bushbury",
    "sg:city":"Wolverhampton",
    "sg:classifiers":[
        {
            "category":"Community Center",
            "type":"Public Place"
        }
    ],
    "sg:phone":"+44 1902 397874",
    "sg:postcode":"WV10 8ER",
    "sg:province":"Staffordshire",
    "sg:tags":[
        "recreation",
        "leisure",
        "centre"
    ],
    "wof:name":"Metropolitan Borough Council",
    "wof:placetype":"venue"
},
  "geometry": {"coordinates":[-2.114917,52.627243],"type":"Point"}
}