{
  "type": "Feature",
  "properties": {
    "iso:country":"GB",
    "sg:address":"10 Abbey Road",
    "sg:city":"Malvern",
    "sg:classifiers":[
        {
            "category":"Communications",
            "type":"Services"
        }
    ],
    "sg:phone":"+44 1684 564558",
    "sg:postcode":"WR14 3HG",
    "sg:province":"Herefordshire",
    "sg:tags":[
        "data",
        "network"
    ],
    "wof:name":"C T P Information Management Ltd.",
    "wof:placetype":"venue"
},
  "geometry": {"coordinates":[-2.328989,52.109055],"type":"Point"}
}