{
  "type": "Feature",
  "properties": {
    "iso:country":"GB",
    "sg:address":"Cuckoo Hill Farm, Castlethorpe Road, Hanslope",
    "sg:city":"Milton Keynes",
    "sg:classifiers":[
        {
            "category":"Retail",
            "subcategory":"Laundry & Dry Cleaning",
            "type":"Services"
        }
    ],
    "sg:postcode":"MK19 7HQ",
    "sg:province":"Buckinghamshire",
    "sg:tags":[
        "alteration"
    ],
    "wof:name":"Quality Care Dry Cleaning",
    "wof:placetype":"venue"
},
  "geometry": {"coordinates":[-0.8391709924,52.0926818848],"type":"Point"}
}