{
  "type": "Feature",
  "properties": {
    "addr:full":"Foundation House, Hanbury Manor Ware Hertfordshire SG12 0UH",
    "addr:postcode":"sg12 0uh",
    "addr:street":"Hanbury;Ware",
    "iso:country":"GB",
    "sg:address":"Foundation House, Hanbury Manor",
    "sg:city":"Ware",
    "sg:classifiers":[
        {
            "category":"Organizations",
            "subcategory":"Non-profit Organization",
            "type":"Services"
        }
    ],
    "sg:postcode":"SG12 0UH",
    "sg:province":"Hertfordshire",
    "sg:tags":[
        "organisation",
        "voluntary",
        "charity"
    ],
    "wof:name":"The Golf Foundation Ltd.",
    "wof:placetype":"venue"
},
  "geometry": {"coordinates":[-0.035127,51.816338],"type":"Point"}
}