{
  "type": "Feature",
  "properties": {
    "iso:country":"GB",
    "sg:address":"9 Meeting House Lane",
    "sg:city":"Ringwood",
    "sg:classifiers":[
        {
            "category":"Restaurant",
            "type":"Food & Drink"
        }
    ],
    "sg:postcode":"BH24 1AY",
    "sg:province":"Dorset",
    "wof:name":"Peppercorn Bistro",
    "wof:placetype":"venue"
},
  "geometry": {"coordinates":[-1.7918570042,50.8469047546],"type":"Point"}
}