{
  "type": "Feature",
  "properties": {
    "addr:full":"Blenheim Road, Longmead Trading Estate Epsom Surrey KT19 9BE",
    "addr:housenumber":"estate",
    "addr:postcode":"kt19 9be",
    "addr:street":"Blenheim Road;Trading",
    "iso:country":"GB",
    "sg:address":"Blenheim Road, Longmead Trading Estate",
    "sg:city":"Epsom",
    "sg:classifiers":[
        {
            "category":"Professional",
            "subcategory":"Engineering",
            "type":"Services"
        }
    ],
    "sg:phone":"+44 1372 741633",
    "sg:postcode":"KT19 9BE",
    "sg:province":"Surrey",
    "sg:tags":[
        "precision",
        "engineer"
    ],
    "wof:name":"W E C S  Tools Ltd.",
    "wof:placetype":"venue"
},
  "geometry": {"coordinates":[-0.2622880042,51.3436927795],"type":"Point"}
}