{
  "type": "Feature",
  "properties": {
    "addr:full":"27 Caerphilly Road Cardiff Cardiff CF14 4AD",
    "addr:housenumber":"27",
    "addr:postcode":"cf14 4ad",
    "addr:street":"Caerphilly Road",
    "iso:country":"GB",
    "sg:address":"27 Caerphilly Road",
    "sg:city":"Cardiff",
    "sg:classifiers":[
        {
            "category":"Building & Trades",
            "subcategory":"Equipment Rental",
            "type":"Services"
        },
        {
            "category":"Building & Trades",
            "subcategory":"Construction",
            "type":"Services"
        }
    ],
    "sg:phone":"+44 29 2061 8223",
    "sg:postcode":"CF14 4AD",
    "sg:province":"Cardiff",
    "sg:tags":[
        "hire",
        "plant",
        "tool",
        "centre"
    ],
    "wof:name":"Brandon Hire Plc",
    "wof:placetype":"venue"
},
  "geometry": {"coordinates":[-3.199846,51.508579],"type":"Point"}
}