{
  "type": "Feature",
  "properties": {
    "iso:country":"GB",
    "sg:address":"3 Baileys Lane, Halewood",
    "sg:city":"Liverpool",
    "sg:classifiers":[
        {
            "category":"Food & Beverages",
            "subcategory":"Meat & Fish",
            "type":"Retail Goods"
        }
    ],
    "sg:phone":"+44 151 280 5176",
    "sg:postcode":"L26 2XB",
    "sg:province":"Merseyside",
    "sg:tags":[
        "butcher"
    ],
    "wof:name":"Michael Thomas",
    "wof:placetype":"venue"
},
  "geometry": {"coordinates":[-2.82235,53.367435],"type":"Point"}
}