{
  "type": "Feature",
  "properties": {
    "iso:country":"GB",
    "sg:address":"200 Pennygate",
    "sg:city":"Spalding",
    "sg:classifiers":[
        {
            "category":"Communications",
            "subcategory":"Film & Video Production",
            "type":"Services"
        }
    ],
    "sg:phone":"+44 1775 766230",
    "sg:postcode":"PE11 1LT",
    "sg:province":"Lincolnshire",
    "sg:tags":[
        "equipment",
        "cctv",
        "mnfr"
    ],
    "wof:name":"Direct Security Systems",
    "wof:placetype":"venue"
},
  "geometry": {"coordinates":[-0.169975996,52.7865600586],"type":"Point"}
}