{
  "type": "Feature",
  "properties": {
    "iso:country":"GB",
    "sg:address":"R/o P & P Seating Ltd, 429 The Meadway, Kitts Grn",
    "sg:city":"Birmingham",
    "sg:classifiers":[
        {
            "category":"Autos & Motor Vehicles",
            "subcategory":"Motorcycle Sales",
            "type":"Retail Goods"
        }
    ],
    "sg:phone":"+44 121 784 8266",
    "sg:postcode":"B33 0LQ",
    "sg:province":"West Midlands",
    "sg:tags":[
        "component"
    ],
    "wof:name":"Rustler Racing",
    "wof:placetype":"venue"
},
  "geometry": {"coordinates":[-1.77201,52.479771],"type":"Point"}
}