{
  "type": "Feature",
  "properties": {
    "addr:full":"200 Acklam Road Middlesbrough North Yorkshire TS5 4PS",
    "addr:housenumber":"200",
    "addr:postcode":"ts5 4ps",
    "addr:street":"Acklam Road",
    "iso:country":"GB",
    "sg:address":"200 Acklam Road",
    "sg:city":"Middlesbrough",
    "sg:classifiers":[
        {
            "category":"Organizations",
            "subcategory":"Membership Organization",
            "type":"Services"
        }
    ],
    "sg:phone":"+44 1642 815264",
    "sg:postcode":"TS5 4PS",
    "sg:province":"North Yorkshire",
    "sg:tags":[
        "club"
    ],
    "wof:name":"St.Francis Club",
    "wof:placetype":"venue"
},
  "geometry": {"coordinates":[-1.259879,54.559807],"type":"Point"}
}