{
  "type": "Feature",
  "properties": {
    "addr:full":"Unit 9 Cambrian Court, Ferry Boat Close, Swansea Enterprise Park Swansea Swansea SA6 8PZ",
    "addr:housenumber":"unit 9;enterprise",
    "addr:postcode":"sa6 8pz",
    "addr:street":"Cambrian Court Ferry Boat Close;Park",
    "iso:country":"GB",
    "sg:address":"Unit 9 Cambrian Court, Ferry Boat Close, Swansea Enterprise Park",
    "sg:city":"Swansea",
    "sg:classifiers":[
        {
            "category":"Retail",
            "subcategory":"Repair Shop",
            "type":"Services"
        }
    ],
    "sg:postcode":"SA6 8PZ",
    "sg:province":"Swansea",
    "sg:tags":[
        "plant",
        "machinery"
    ],
    "wof:name":"Equipment Services (Wales) Ltd.",
    "wof:placetype":"venue"
},
  "geometry": {"coordinates":[-3.9201879501,51.6592178345],"type":"Point"}
}