{
  "type": "Feature",
  "properties": {
    "iso:country":"GB",
    "sg:address":"West End, Herstmonceux",
    "sg:city":"Hailsham",
    "sg:classifiers":[
        {
            "category":"Social Services",
            "subcategory":"Retirement Home",
            "type":"Services"
        }
    ],
    "sg:phone":"+44 1323 832021",
    "sg:postcode":"BN27 4NX",
    "sg:province":"East Sussex",
    "sg:tags":[
        "residential",
        "care"
    ],
    "wof:name":"Dunsfold Specialist Care Home",
    "wof:placetype":"venue"
},
  "geometry": {"coordinates":[0.3215439916,50.8890800476],"type":"Point"}
}