{
  "type": "Feature",
  "properties": {
    "iso:country":"GB",
    "sg:address":"Church Road, Plymstock",
    "sg:city":"Plymouth",
    "sg:classifiers":[
        {
            "category":"Place Of Worship",
            "type":"Public Place"
        },
        {
            "category":"Education",
            "subcategory":"School",
            "type":"Public Place"
        }
    ],
    "sg:phone":"+44 1752 402679",
    "sg:postcode":"PL9 9AZ",
    "sg:province":"Devon",
    "sg:tags":[
        "local",
        "authority"
    ],
    "wof:name":"Plymstock Secondary School",
    "wof:placetype":"venue"
},
  "geometry": {"coordinates":[-4.086291,50.355801],"type":"Point"}
}