{
  "type": "Feature",
  "properties": {
    "addr:full":"Trimingham House, Beacon Road, Trimingham Norwich Norfolk NR11 8DX",
    "addr:housenumber":"trimingham",
    "addr:postcode":"nr11 8dx",
    "addr:street":"Beacon Road;Norwich",
    "iso:country":"GB",
    "sg:address":"Trimingham House, Beacon Road, Trimingham",
    "sg:city":"Norwich",
    "sg:classifiers":[
        {
            "category":"Recreation",
            "subcategory":"Campground",
            "type":"Entertainment"
        }
    ],
    "sg:phone":"+44 1263 720421",
    "sg:postcode":"NR11 8DX",
    "sg:province":"Norfolk",
    "sg:tags":[
        "caravan",
        "park"
    ],
    "wof:name":"Trimingham House Caravan Park",
    "wof:placetype":"venue"
},
  "geometry": {"coordinates":[1.406985,52.891319],"type":"Point"}
}