{
  "type": "Feature",
  "properties": {
    "iso:country":"GB",
    "sg:address":"12 Waveney Drive",
    "sg:city":"March",
    "sg:classifiers":[
        {
            "category":"Building & Trades",
            "subcategory":"Construction",
            "type":"Services"
        }
    ],
    "sg:phone":"+44 1354 653678",
    "sg:postcode":"PE15 8DY",
    "sg:province":"Cambridgeshire",
    "sg:tags":[
        "dry",
        "plastering",
        "plasterers",
        "lining",
        "related",
        "screeders"
    ],
    "wof:name":"A R Wales",
    "wof:placetype":"venue"
},
  "geometry": {"coordinates":[0.073279,52.553505],"type":"Point"}
}