{
  "type": "Feature",
  "properties": {
    "addr:full":"402-408 Leeds Road Bradford West Yorkshire BD3 9RE",
    "addr:housenumber":"402-408",
    "addr:postcode":"bd3 9re",
    "addr:street":"Leeds Road",
    "iso:country":"GB",
    "sg:address":"402-408 Leeds Road",
    "sg:city":"Bradford",
    "sg:classifiers":[
        {
            "category":"Bars & Pubs",
            "type":"Food & Drink"
        }
    ],
    "sg:postcode":"BD3 9RE",
    "sg:province":"West Yorkshire",
    "sg:tags":[
        "pubs",
        "inn"
    ],
    "wof:name":"The Adelphi",
    "wof:placetype":"venue"
},
  "geometry": {"coordinates":[-1.737577,53.792511],"type":"Point"}
}