{
  "type": "Feature",
  "properties": {
    "iso:country":"GB",
    "sg:address":"46 Europa Business Park, Bird Hall La",
    "sg:city":"Stockport",
    "sg:classifiers":[
        {
            "category":"Bus Stop",
            "subcategory":"None",
            "type":"Transportation"
        }
    ],
    "sg:phone":"+44 161 428 6558",
    "sg:postcode":"SK3 0XA",
    "sg:province":"Cheshire",
    "sg:tags":[
        "filter"
    ],
    "wof:name":"E C Stewart Filtration Ltd",
    "wof:placetype":"venue"
},
  "geometry": {"coordinates":[-2.184929,53.393959],"type":"Point"}
}