{
  "type": "Feature",
  "properties": {
    "iso:country":"GB",
    "sg:address":"7 Thornton Road",
    "sg:city":"Thornton Heath",
    "sg:classifiers":[
        {
            "category":"Shopping",
            "subcategory":"Department Store",
            "type":"Retail Goods"
        }
    ],
    "sg:postcode":"CR7 6BD",
    "sg:province":"Surrey",
    "wof:name":"B C Pitt & Sons",
    "wof:placetype":"venue"
},
  "geometry": {"coordinates":[-0.114619,51.393402],"type":"Point"}
}