{
  "type": "Feature",
  "properties": {
    "addr:full":"Coed Farm, Cilcennin Lampeter Carmarthenshire SA48 8DH",
    "addr:postcode":"sa48 8dh",
    "addr:street":"Carmarthenshire",
    "iso:country":"GB",
    "sg:address":"Coed Farm, Cilcennin",
    "sg:city":"Lampeter",
    "sg:classifiers":[
        {
            "category":"Farming",
            "subcategory":"Livestock Farm",
            "type":"Manufacturing & Wholesale Goods"
        }
    ],
    "sg:phone":"+44 1570 470408",
    "sg:postcode":"SA48 8DH",
    "sg:province":"Carmarthenshire",
    "sg:tags":[
        "others"
    ],
    "wof:name":"T G M & R C Thomas",
    "wof:placetype":"venue"
},
  "geometry": {"coordinates":[-4.166659832,52.2193946838],"type":"Point"}
}