{
  "type": "Feature",
  "properties": {
    "iso:country":"GB",
    "sg:address":"28 Pale Road",
    "sg:city":"Neath",
    "sg:classifiers":[
        {
            "category":"Banks & Credit Unions",
            "subcategory":"Financial Services",
            "type":"Services"
        }
    ],
    "sg:postcode":"SA10 6BW",
    "sg:province":"Neath Port Talbot",
    "sg:tags":[
        "claim",
        "assessor"
    ],
    "wof:name":"D L Combstock",
    "wof:placetype":"venue"
},
  "geometry": {"coordinates":[-3.841147,51.655758],"type":"Point"}
}