{
  "type": "Feature",
  "properties": {
    "iso:country":"GB",
    "sg:address":"8 Moorfield Indstl Est, Burnley Rd, Altham",
    "sg:city":"Accrington",
    "sg:classifiers":[
        {
            "category":"Wholesale",
            "subcategory":"Scrap",
            "type":"Manufacturing & Wholesale Goods"
        }
    ],
    "sg:postcode":"BB5 5TX",
    "sg:province":"Lancashire",
    "sg:tags":[
        "waste",
        "metal"
    ],
    "wof:name":"Spires,Peter,",
    "wof:placetype":"venue"
},
  "geometry": {"coordinates":[-2.3566360474,53.7898025513],"type":"Point"}
}