{
  "type": "Feature",
  "properties": {
    "iso:country":"GB",
    "sg:address":"Office, 69 Main Street, Douglas",
    "sg:city":"Lanark",
    "sg:classifiers":[
        {
            "category":"Freight",
            "type":"Transportation"
        }
    ],
    "sg:phone":"+44 1555 851282",
    "sg:postcode":"ML11 0QG",
    "sg:province":"South Lanarkshire",
    "sg:tags":[
        "haulage",
        "road"
    ],
    "wof:name":"J Bairner & Sons",
    "wof:placetype":"venue"
},
  "geometry": {"coordinates":[-3.845479,55.559464],"type":"Point"}
}