{
  "type": "Feature",
  "properties": {
    "iso:country":"GB",
    "sg:address":"7-8 Exchange Walk",
    "sg:city":"Nottingham",
    "sg:classifiers":[
        {
            "category":"Professional",
            "subcategory":"Art Services",
            "type":"Services"
        }
    ],
    "sg:phone":"+44 115 950 8458",
    "sg:postcode":"NG1 2NX",
    "sg:province":"Nottinghamshire",
    "sg:tags":[
        "photographer"
    ],
    "wof:name":"Foto Processing",
    "wof:placetype":"venue"
},
  "geometry": {"coordinates":[-1.14892,52.952862],"type":"Point"}
}