{
  "type": "Feature",
  "properties": {
    "addr:full":"Unit 1a Hoohill Industrial Estate, Bispham Road Blackpool Lancashire FY3 7HJ",
    "addr:housenumber":"unit 1a",
    "addr:postcode":"fy3 7hj",
    "addr:street":"Industrial Estate Bispham Road",
    "iso:country":"GB",
    "sg:address":"Unit 1a Hoohill Industrial Estate, Bispham Road",
    "sg:city":"Blackpool",
    "sg:classifiers":[
        {
            "category":"Professional",
            "type":"Services"
        },
        {
            "category":"Retail",
            "subcategory":"Auto Repair",
            "type":"Services"
        }
    ],
    "sg:postcode":"FY3 7HJ",
    "sg:province":"Lancashire",
    "sg:tags":[
        "modification",
        "garage",
        "transportation",
        "car"
    ],
    "wof:name":"T R B Motors",
    "wof:placetype":"venue"
},
  "geometry": {"coordinates":[-3.03255,53.832619],"type":"Point"}
}