{
  "type": "Feature",
  "properties": {
    "addr:full":"65 Hallidale Crescent, Deanpark Renfrew Renfrewshire PA4 0YA",
    "addr:housenumber":"65",
    "addr:postcode":"pa4 0ya",
    "addr:street":"Hallidale Crescent Deanpark",
    "iso:country":"GB",
    "sg:address":"65 Hallidale Crescent, Deanpark",
    "sg:city":"Renfrew",
    "sg:classifiers":[
        {
            "category":"Retail",
            "subcategory":"Driving School",
            "type":"Services"
        }
    ],
    "sg:phone":"+44 141 886 6283",
    "sg:postcode":"PA4 0YA",
    "sg:province":"Renfrewshire",
    "wof:name":"Renfrew Driving Centre",
    "wof:placetype":"venue"
},
  "geometry": {"coordinates":[-4.372429,55.871475],"type":"Point"}
}