{
  "type": "Feature",
  "properties": {
    "iso:country":"GB",
    "sg:address":"256 Heanor Road",
    "sg:city":"Ilkeston",
    "sg:classifiers":[
        {
            "category":"Professional",
            "subcategory":"Art Services",
            "type":"Services"
        },
        {
            "category":"Building & Trades",
            "subcategory":"Construction",
            "type":"Services"
        }
    ],
    "sg:phone":"+44 115 930 9189",
    "sg:postcode":"DE7 8TG",
    "sg:province":"Derbyshire",
    "sg:tags":[
        "decorator",
        "painter"
    ],
    "wof:name":"D  Kerry",
    "wof:placetype":"venue"
},
  "geometry": {"coordinates":[-1.318683,52.988415],"type":"Point"}
}