{
  "type": "Feature",
  "properties": {
    "addr:full":"Macmanniston, Dalrymple Ayr East Ayrshire KA6 6BT",
    "addr:postcode":"ka6 6bt",
    "addr:street":"Macmanniston Dalrymple",
    "iso:country":"GB",
    "sg:address":"Macmanniston, Dalrymple",
    "sg:city":"Ayr",
    "sg:classifiers":[
        {
            "category":"Professional",
            "subcategory":"Engineering",
            "type":"Services"
        }
    ],
    "sg:phone":"+44 1292 560369",
    "sg:postcode":"KA6 6BT",
    "sg:province":"East Ayrshire",
    "sg:tags":[
        "civil",
        "engineer"
    ],
    "wof:name":"Lymburn Contractors Ltd.",
    "wof:placetype":"venue"
},
  "geometry": {"coordinates":[-4.5891208649,55.3982467651],"type":"Point"}
}