{
  "type": "Feature",
  "properties": {
    "addr:full":"1145 Tollcross Road Glasgow Glasgow City G32 8HB",
    "addr:housenumber":"1145",
    "addr:postcode":"g32 8hb",
    "addr:street":"Tollcross Road",
    "iso:country":"GB",
    "sg:address":"1145 Tollcross Road",
    "sg:city":"Glasgow",
    "sg:classifiers":[
        {
            "category":"Fast Food",
            "type":"Food & Drink"
        }
    ],
    "sg:postcode":"G32 8HB",
    "sg:province":"Glasgow City",
    "sg:tags":[
        "away",
        "take"
    ],
    "wof:name":"Tollcross Express",
    "wof:placetype":"venue"
},
  "geometry": {"coordinates":[-4.170167923,55.8433837891],"type":"Point"}
}