{
  "type": "Feature",
  "properties": {
    "iso:country":"GB",
    "sg:address":"41-43 Streatham Hill",
    "sg:city":"London",
    "sg:classifiers":[
        {
            "category":"Health Services",
            "subcategory":"Health Practitioner",
            "type":"Services"
        }
    ],
    "sg:postcode":"SW2 4TP",
    "sg:province":"Greater London",
    "sg:tags":[
        "therapist",
        "speech"
    ],
    "wof:name":"West Lambeth Community Care (Nhs) Trust",
    "wof:placetype":"venue"
},
  "geometry": {"coordinates":[-0.124511,51.441338],"type":"Point"}
}