{
  "type": "Feature",
  "properties": {
    "addr:full":"69 Main St Nottingham Nottinghamshire NG14 5ED",
    "addr:housenumber":"69",
    "addr:postcode":"ng14 5ed",
    "addr:street":"Main St",
    "iso:country":"GB",
    "sg:address":"69 Main St",
    "sg:city":"Nottingham",
    "sg:classifiers":[
        {
            "category":"Food & Beverages",
            "subcategory":"Bakery",
            "type":"Retail Goods"
        }
    ],
    "sg:phone":"+44 115 931 2213",
    "sg:postcode":"NG14 5ED",
    "sg:province":"Nottinghamshire",
    "sg:tags":[
        "baker"
    ],
    "wof:name":"Catherines Bakery",
    "wof:placetype":"venue"
},
  "geometry": {"coordinates":[-1.0349689722,52.9890785217],"type":"Point"}
}