{
  "type": "Feature",
  "properties": {
    "iso:country":"GB",
    "sg:address":"Kings Lane, Englefield Green",
    "sg:city":"Egham",
    "sg:classifiers":[
        {
            "category":"Farming",
            "subcategory":"Nursery",
            "type":"Manufacturing & Wholesale Goods"
        },
        {
            "category":"Education",
            "subcategory":"Preschool",
            "type":"Public Place"
        }
    ],
    "sg:phone":"+44 1784 472668",
    "sg:postcode":"TW20 0UE",
    "sg:province":"Surrey",
    "sg:tags":[
        "school",
        "creche"
    ],
    "wof:name":"Englefield Green Montessori School",
    "wof:placetype":"venue"
},
  "geometry": {"coordinates":[-0.589652,51.430458],"type":"Point"}
}