{
  "type": "Feature",
  "properties": {
    "iso:country":"GB",
    "sg:address":"16 Victoria Way",
    "sg:city":"Burgess Hill",
    "sg:classifiers":[
        {
            "category":"Home & Garden",
            "subcategory":"Home Furnishings",
            "type":"Retail Goods"
        }
    ],
    "sg:phone":"+44 1444 258931",
    "sg:postcode":"RH15 9NF",
    "sg:province":"East Sussex",
    "sg:tags":[
        "patio",
        "furniture"
    ],
    "wof:name":"Alexander Rose Ltd.",
    "wof:placetype":"venue"
},
  "geometry": {"coordinates":[-0.141185,50.954964],"type":"Point"}
}