{
  "type": "Feature",
  "properties": {
    "addr:full":"12 Dean Terrace Ryton Tyne and Wear NE40 3HQ",
    "addr:housenumber":"12",
    "addr:postcode":"ne40 3hq",
    "addr:street":"Dean Terrace",
    "iso:country":"GB",
    "sg:address":"12 Dean Terrace",
    "sg:city":"Ryton",
    "sg:classifiers":[
        {
            "category":"Personal",
            "subcategory":"Beauty Salon",
            "type":"Services"
        },
        {
            "category":"Personal",
            "subcategory":"Barber",
            "type":"Services"
        }
    ],
    "sg:phone":"+44 191 413 7318",
    "sg:postcode":"NE40 3HQ",
    "sg:province":"Tyne and Wear",
    "sg:tags":[
        "unisex",
        "hairdresser"
    ],
    "wof:name":"Suki Hair Studio",
    "wof:placetype":"venue"
},
  "geometry": {"coordinates":[-1.7574440241,54.9735565186],"type":"Point"}
}