{
  "type": "Feature",
  "properties": {
    "addr:full":"56a Queens Way London Greater London W2 3RY",
    "addr:housenumber":"56a",
    "addr:postcode":"w2 3ry",
    "addr:street":"Queens Way",
    "iso:country":"GB",
    "sg:address":"56a Queens Way",
    "sg:city":"London",
    "sg:classifiers":[
        {
            "category":"Professional",
            "subcategory":"Detective & Security Services",
            "type":"Services"
        }
    ],
    "sg:phone":"+44 20 7243 0967",
    "sg:postcode":"W2 3RY",
    "sg:province":"Greater London",
    "sg:tags":[
        "equipment"
    ],
    "wof:name":"Spy Shop",
    "wof:placetype":"venue"
},
  "geometry": {"coordinates":[-0.187384,51.512081],"type":"Point"}
}