{
  "type": "Feature",
  "properties": {
    "addr:full":"18a Vivian Avenue Hendon Greater London NW4 3XP",
    "addr:housenumber":"18a",
    "addr:postcode":"nw4 3xp",
    "addr:street":"Vivian Avenue",
    "iso:country":"GB",
    "sg:address":"18a Vivian Avenue",
    "sg:city":"Hendon",
    "sg:classifiers":[
        {
            "category":"Communications",
            "type":"Services"
        }
    ],
    "sg:phone":"+44 20 8931 9314",
    "sg:postcode":"NW4 3XP",
    "sg:province":"Greater London",
    "sg:tags":[
        "telecommunication"
    ],
    "wof:name":"On Line Communications",
    "wof:placetype":"venue"
},
  "geometry": {"coordinates":[-0.2287829965,51.5826721191],"type":"Point"}
}