{
  "type": "Feature",
  "properties": {
    "addr:full":"48 Bramfield Road London Greater London SW11 6RB",
    "addr:housenumber":"48",
    "addr:postcode":"sw11 6rb",
    "addr:street":"Bramfield Road",
    "iso:country":"GB",
    "sg:address":"48 Bramfield Road",
    "sg:city":"London",
    "sg:classifiers":[
        {
            "category":"Communications",
            "subcategory":"Film & Video Production",
            "type":"Services"
        }
    ],
    "sg:phone":"+44 20 7223 5868",
    "sg:postcode":"SW11 6RB",
    "sg:province":"Greater London",
    "sg:tags":[
        "tv",
        "studio"
    ],
    "wof:name":"Triangle Productions",
    "wof:placetype":"venue"
},
  "geometry": {"coordinates":[-0.165836,51.455231],"type":"Point"}
}