{
  "type": "Feature",
  "properties": {
    "addr:full":"The Warren, Holmeswood Road, Rufford Ormskirk Lancashire L40 1TX",
    "addr:postcode":"l40 1tx",
    "addr:street":"Holmeswood Road",
    "iso:country":"GB",
    "sg:address":"The Warren, Holmeswood Road, Rufford",
    "sg:city":"Ormskirk",
    "sg:classifiers":[
        {
            "category":"Freight",
            "type":"Transportation"
        }
    ],
    "sg:phone":"+44 1704 821722",
    "sg:postcode":"L40 1TX",
    "sg:province":"Lancashire",
    "sg:tags":[
        "haulage",
        "transport",
        "road"
    ],
    "wof:name":"W & M Thompson Haulage Contractors",
    "wof:placetype":"venue"
},
  "geometry": {"coordinates":[-2.8555679321,53.6440162659],"type":"Point"}
}