{
  "type": "Feature",
  "properties": {
    "addr:full":"22 Elsham Crescent Lincoln Lincolnshire LN6 3YT",
    "addr:housenumber":"22",
    "addr:postcode":"ln6 3yt",
    "addr:street":"Elsham Crescent",
    "iso:country":"GB",
    "sg:address":"22 Elsham Crescent",
    "sg:city":"Lincoln",
    "sg:classifiers":[
        {
            "category":"Building & Trades",
            "subcategory":"Construction",
            "type":"Services"
        }
    ],
    "sg:phone":"+44 1522 690874",
    "sg:postcode":"LN6 3YT",
    "sg:province":"Lincolnshire",
    "sg:tags":[
        "flooring"
    ],
    "wof:name":"G.P Construction",
    "wof:placetype":"venue"
},
  "geometry": {"coordinates":[-0.5976039767,53.215259552],"type":"Point"}
}