{
  "type": "Feature",
  "properties": {
    "addr:full":"Unit 56 Stratford Workshops, Burford Road, Stratford London Greater London E15 2SP",
    "addr:housenumber":"unit 56",
    "addr:postcode":"e15 2sp",
    "addr:street":"Burford Road",
    "iso:country":"GB",
    "sg:address":"Unit 56 Stratford Workshops, Burford Road, Stratford",
    "sg:city":"London",
    "sg:classifiers":[
        {
            "category":"Home & Garden",
            "subcategory":"Carpets & Floor Coverings",
            "type":"Retail Goods"
        }
    ],
    "sg:phone":"+44 1277 824174",
    "sg:postcode":"E15 2SP",
    "sg:province":"Greater London",
    "sg:tags":[
        "carpets",
        "rug",
        "matting"
    ],
    "wof:name":"Garrard Interiors",
    "wof:placetype":"venue"
},
  "geometry": {"coordinates":[-0.0004,51.537121],"type":"Point"}
}