{
  "type": "Feature",
  "properties": {
    "iso:country":"GB",
    "sg:address":"Finistere House, Chapel Street",
    "sg:city":"Ripley",
    "sg:classifiers":[
        {
            "category":"Banks & Credit Unions",
            "subcategory":"Financial Services",
            "type":"Services"
        }
    ],
    "sg:postcode":"DE5 3DL",
    "sg:province":"Derbyshire",
    "sg:tags":[
        "consultant"
    ],
    "wof:name":"Froggett Financial",
    "wof:placetype":"venue"
},
  "geometry": {"coordinates":[-1.405124,53.052555],"type":"Point"}
}