{
  "type": "Feature",
  "properties": {
    "iso:country":"GB",
    "sg:address":"Woodland House, Woodland Park, Bradford Road",
    "sg:city":"Bradford",
    "sg:classifiers":[
        {
            "category":"Building & Trades",
            "subcategory":"Construction",
            "type":"Services"
        }
    ],
    "sg:phone":"+44 1274 866700",
    "sg:postcode":"BD19 6AR",
    "sg:province":"West Yorkshire",
    "sg:tags":[
        "builder"
    ],
    "wof:name":"Totty Building Services Ltd.",
    "wof:placetype":"venue"
},
  "geometry": {"coordinates":[-1.7583060265,53.7957382202],"type":"Point"}
}