{
  "type": "Feature",
  "properties": {
    "addr:full":"289a Prince Avenue Westcliff-on-sea Essex SS0 0JP",
    "addr:housenumber":"289a",
    "addr:postcode":"ss0 0jp",
    "addr:street":"Prince Avenue",
    "iso:country":"GB",
    "sg:address":"289a Prince Avenue",
    "sg:city":"Westcliff-on-sea",
    "sg:classifiers":[
        {
            "category":"Health Services",
            "subcategory":"Health Practitioner",
            "type":"Services"
        }
    ],
    "sg:phone":"+44 1702 432432",
    "sg:postcode":"SS0 0JP",
    "sg:province":"Essex",
    "sg:tags":[
        "hypnotherapists"
    ],
    "wof:name":"G F Bird",
    "wof:placetype":"venue"
},
  "geometry": {"coordinates":[0.6855639815,51.5597572327],"type":"Point"}
}