{
  "type": "Feature",
  "properties": {
    "iso:country":"GB",
    "sg:address":"Pivington Mill, Pluckley",
    "sg:city":"Ashford",
    "sg:classifiers":[
        {
            "category":"Shopping",
            "subcategory":"Computers & Home Electronics",
            "type":"Retail Goods"
        }
    ],
    "sg:postcode":"TN27 0PG",
    "sg:province":"Kent",
    "wof:name":"Christopher I Ellsworth",
    "wof:placetype":"venue"
},
  "geometry": {"coordinates":[0.755068,51.176594],"type":"Point"}
}