{
  "type": "Feature",
  "properties": {
    "iso:country":"GB",
    "sg:address":"Suite 2, Empire House, Regina Road",
    "sg:city":"Chelmsford",
    "sg:classifiers":[
        {
            "category":"Social Services",
            "type":"Services"
        },
        {
            "category":"Government",
            "subcategory":"Office",
            "type":"Public Place"
        }
    ],
    "sg:phone":"+44 1245 358092",
    "sg:postcode":"CM1 1PE",
    "sg:province":"Essex",
    "sg:tags":[
        "local"
    ],
    "wof:name":"Mid Essex Youth Justice Centre",
    "wof:placetype":"venue"
},
  "geometry": {"coordinates":[0.4769499898,51.7376937866],"type":"Point"}
}