{
  "type": "Feature",
  "properties": {
    "addr:full":"Herringham Rd Charlton Greater London SE7 8NN",
    "addr:postcode":"se7 8nn",
    "addr:street":"Herringham Rd",
    "iso:country":"GB",
    "sg:address":"Herringham Rd",
    "sg:city":"Charlton",
    "sg:classifiers":[
        {
            "category":"Home & Garden",
            "subcategory":"Kitchen Supply",
            "type":"Retail Goods"
        }
    ],
    "sg:phone":"+44 20 8853 1333",
    "sg:postcode":"SE7 8NN",
    "sg:province":"Greater London",
    "sg:tags":[
        "equipment",
        "catering"
    ],
    "wof:name":"Stangard Ltd",
    "wof:placetype":"venue"
},
  "geometry": {"coordinates":[0.0356910005,51.4940109253],"type":"Point"}
}