{
  "type": "Feature",
  "properties": {
    "addr:full":"49 High St Edgware Greater London HA8 7DD",
    "addr:housenumber":"49",
    "addr:postcode":"ha8 7dd",
    "addr:street":"High St",
    "iso:country":"GB",
    "sg:address":"49 High St",
    "sg:city":"Edgware",
    "sg:classifiers":[
        {
            "category":"Retail",
            "subcategory":"Photofinishing",
            "type":"Services"
        }
    ],
    "sg:phone":"+44 20 8951 5177",
    "sg:postcode":"HA8 7DD",
    "sg:province":"Greater London",
    "sg:tags":[
        "photographic",
        "processor"
    ],
    "wof:name":"Complete Group",
    "wof:placetype":"venue"
},
  "geometry": {"coordinates":[-0.2789900005,51.6099891663],"type":"Point"}
}