{
  "type": "Feature",
  "properties": {
    "addr:full":"Unit 18, Wrexham Road Business Village Slough Berkshire SL2 5HF",
    "addr:housenumber":"unit",
    "addr:postcode":"sl2 5hf",
    "addr:street":"Wrexham Road",
    "iso:country":"GB",
    "sg:address":"Unit 18, Wrexham Road Business Village",
    "sg:city":"Slough",
    "sg:classifiers":[
        {
            "category":"Wholesale",
            "subcategory":"Electrical",
            "type":"Manufacturing & Wholesale Goods"
        }
    ],
    "sg:postcode":"SL2 5HF",
    "sg:province":"Berkshire",
    "sg:tags":[
        "equipment",
        "refrigeration"
    ],
    "wof:name":"Bie Refrigerating Machinery Ltd.",
    "wof:placetype":"venue"
},
  "geometry": {"coordinates":[-0.5797299743,51.513999939],"type":"Point"}
}