{
  "type": "Feature",
  "properties": {
    "addr:full":"3.1 Lower Trostre Rd Llanelli Carmarthenshire SA14 9UU",
    "addr:housenumber":"3.1",
    "addr:postcode":"sa14 9uu",
    "addr:street":"Lower Trostre Rd",
    "iso:country":"GB",
    "sg:address":"3.1 Lower Trostre Rd",
    "sg:city":"Llanelli",
    "sg:classifiers":[
        {
            "category":"Home & Garden",
            "subcategory":"Carpets & Floor Coverings",
            "type":"Retail Goods"
        }
    ],
    "sg:phone":"+44 1554 770778",
    "sg:postcode":"SA14 9UU",
    "sg:province":"Carmarthenshire",
    "sg:tags":[
        "rubber",
        "plastic"
    ],
    "wof:name":"Capital T",
    "wof:placetype":"venue"
},
  "geometry": {"coordinates":[-4.144869,51.669331],"type":"Point"}
}