{
  "type": "Feature",
  "properties": {
    "addr:full":"Todburn Steel, Slaley Hexham Northumberland NE47 0DH",
    "addr:postcode":"ne47 0dh",
    "addr:street":"Northumberland",
    "iso:country":"GB",
    "sg:address":"Todburn Steel, Slaley",
    "sg:city":"Hexham",
    "sg:classifiers":[
        {
            "category":"Farming",
            "subcategory":"Livestock Farm",
            "type":"Manufacturing & Wholesale Goods"
        },
        {
            "category":"Farming",
            "subcategory":"Farm",
            "type":"Manufacturing & Wholesale Goods"
        }
    ],
    "sg:phone":"+44 1434 673230",
    "sg:postcode":"NE47 0DH",
    "sg:province":"Northumberland",
    "sg:tags":[
        "mixed",
        "crop",
        "others"
    ],
    "wof:name":"Thomas Johnston",
    "wof:placetype":"venue"
},
  "geometry": {"coordinates":[-2.0399401188,54.9144248962],"type":"Point"}
}