{
  "type": "Feature",
  "properties": {
    "addr:full":"Henry Tudor House, 72 Wyle Cop Shrewsbury Shropshire SY1 1UX",
    "addr:housenumber":"72",
    "addr:postcode":"sy1 1ux",
    "addr:street":"Wyle Cop",
    "iso:country":"GB",
    "sg:address":"Henry Tudor House, 72 Wyle Cop",
    "sg:city":"Shrewsbury",
    "sg:classifiers":[
        {
            "category":"Shopping",
            "subcategory":"Gifts & Souvenirs",
            "type":"Retail Goods"
        }
    ],
    "sg:postcode":"SY1 1UX",
    "sg:province":"Shropshire",
    "sg:tags":[
        "shop"
    ],
    "wof:name":"Christmas Dreams",
    "wof:placetype":"venue"
},
  "geometry": {"coordinates":[-2.7502820492,52.7061347961],"type":"Point"}
}