{
  "type": "Feature",
  "properties": {
    "iso:country":"GB",
    "sg:address":"4 Tavistock Rd",
    "sg:city":"London",
    "sg:classifiers":[
        {
            "category":"Social Services",
            "subcategory":"Retirement Home",
            "type":"Services"
        }
    ],
    "sg:postcode":"W11 1BA",
    "sg:province":"Greater London",
    "sg:tags":[
        "residential",
        "care"
    ],
    "wof:name":"Westminster City Council",
    "wof:placetype":"venue"
},
  "geometry": {"coordinates":[-0.2019740045,51.5201263428],"type":"Point"}
}