{
  "type": "Feature",
  "properties": {
    "addr:full":"Luke Lane, Innsworth Gloucester Gloucestershire GL3 1HJ",
    "addr:postcode":"gl3 1hj",
    "addr:street":"Luke Lane",
    "iso:country":"GB",
    "sg:address":"Luke Lane, Innsworth",
    "sg:city":"Gloucester",
    "sg:classifiers":[
        {
            "category":"Education",
            "subcategory":"School",
            "type":"Public Place"
        }
    ],
    "sg:phone":"+44 1452 730780",
    "sg:postcode":"GL3 1HJ",
    "sg:province":"Gloucestershire",
    "sg:tags":[
        "local",
        "authority"
    ],
    "wof:name":"Larkfield County Infants",
    "wof:placetype":"venue"
},
  "geometry": {"coordinates":[-2.2029190063,51.8883857727],"type":"Point"}
}