{
  "type": "Feature",
  "properties": {
    "iso:country":"GB",
    "sg:address":"Court Lane, Shipham",
    "sg:city":"Winscombe",
    "sg:classifiers":[
        {
            "category":"Shopping",
            "subcategory":"Department Store",
            "type":"Retail Goods"
        }
    ],
    "sg:postcode":"BS25 1TF",
    "sg:province":"Somerset",
    "wof:name":"Mendip Store",
    "wof:placetype":"venue"
},
  "geometry": {"coordinates":[-2.796354,51.314201],"type":"Point"}
}