{
  "type": "Feature",
  "properties": {
    "addr:full":"11-15 Aitken St Largs North Ayrshire KA30 8AT",
    "addr:housenumber":"11-15",
    "addr:postcode":"ka30 8at",
    "addr:street":"Aitken St",
    "iso:country":"GB",
    "sg:address":"11-15 Aitken St",
    "sg:city":"Largs",
    "sg:classifiers":[
        {
            "category":"Government",
            "subcategory":"Post Office",
            "type":"Public Place"
        }
    ],
    "sg:phone":"+44 1475 673137",
    "sg:postcode":"KA30 8AT",
    "sg:province":"North Ayrshire",
    "wof:name":"Post Office Counters Ltd",
    "wof:placetype":"venue"
},
  "geometry": {"coordinates":[-4.8672862053,55.7941017151],"type":"Point"}
}