{
  "type": "Feature",
  "properties": {
    "iso:country":"GB",
    "sg:address":"4 The Village, Holne",
    "sg:city":"Newton Abbot",
    "sg:classifiers":[
        {
            "category":"Building & Trades",
            "subcategory":"Construction",
            "type":"Services"
        }
    ],
    "sg:postcode":"TQ13 7SL",
    "sg:province":"Devon",
    "sg:tags":[
        "builder"
    ],
    "wof:name":"Robert Garth Grose",
    "wof:placetype":"venue"
},
  "geometry": {"coordinates":[-3.8264729977,50.5114936829],"type":"Point"}
}