{
  "type": "Feature",
  "properties": {
    "addr:full":"19 Earlsfield Maidenhead Berkshire SL6 2LZ",
    "addr:housenumber":"19",
    "addr:postcode":"sl6 2lz",
    "addr:street":"Earlsfield",
    "iso:country":"GB",
    "sg:address":"19 Earlsfield",
    "sg:city":"Maidenhead",
    "sg:classifiers":[
        {
            "category":"Professional",
            "subcategory":"Computer Services",
            "type":"Services"
        }
    ],
    "sg:phone":"+44 1628 776793",
    "sg:postcode":"SL6 2LZ",
    "sg:province":"Berkshire",
    "sg:tags":[
        "system",
        "software"
    ],
    "wof:name":"Consultancy Services Ltd",
    "wof:placetype":"venue"
},
  "geometry": {"coordinates":[-0.703302,51.498146],"type":"Point"}
}