{
  "type": "Feature",
  "properties": {
    "iso:country":"GB",
    "sg:address":"Wellington House, Pollard St East",
    "sg:city":"Manchester",
    "sg:classifiers":[
        {
            "category":"Real Estate",
            "subcategory":"Real Estate Agent",
            "type":"Services"
        }
    ],
    "sg:phone":"+44 161 273 5596",
    "sg:postcode":"M40 7FS",
    "sg:province":"Greater Manchester",
    "wof:name":"Purbridge",
    "wof:placetype":"venue"
},
  "geometry": {"coordinates":[-2.21403,53.484241],"type":"Point"}
}