{
  "type": "Feature",
  "properties": {
    "addr:full":"3 High Street West Sunderland Tyne and Wear SR1 3EY",
    "addr:housenumber":"3",
    "addr:postcode":"sr1 3ey",
    "addr:street":"High Street West",
    "iso:country":"GB",
    "sg:address":"3 High Street West",
    "sg:city":"Sunderland",
    "sg:classifiers":[
        {
            "category":"Home & Garden",
            "subcategory":"Hardware",
            "type":"Retail Goods"
        }
    ],
    "sg:phone":"+44 191 514 2906",
    "sg:postcode":"SR1 3EY",
    "sg:province":"Tyne and Wear",
    "sg:tags":[
        "retailer",
        "diy"
    ],
    "wof:name":"Strother (Ironmonger) Ltd.",
    "wof:placetype":"venue"
},
  "geometry": {"coordinates":[-1.389367,54.90633],"type":"Point"}
}