{
  "type": "Feature",
  "properties": {
    "iso:country":"GB",
    "sg:address":"The Old School, 17 Meeting House Lane",
    "sg:city":"Penrith",
    "sg:classifiers":[
        {
            "category":"Education",
            "subcategory":"Preschool",
            "type":"Public Place"
        }
    ],
    "sg:phone":"+44 1768 890272",
    "sg:postcode":"CA11 7TR",
    "sg:province":"Cumbria",
    "sg:tags":[
        "pre",
        "school",
        "playgroups",
        "pre-school"
    ],
    "wof:name":"Penrith Preschool Playgroup",
    "wof:placetype":"venue"
},
  "geometry": {"coordinates":[-2.750049,54.666119],"type":"Point"}
}