{
  "type": "Feature",
  "properties": {
    "iso:country":"GB",
    "sg:address":"111-113 Upper Tooting Road",
    "sg:city":"London",
    "sg:classifiers":[
        {
            "category":"Shopping",
            "subcategory":"Clothing, Apparel, & Fashions",
            "type":"Retail Goods"
        }
    ],
    "sg:phone":"+44 20 8682 9990",
    "sg:postcode":"SW17 7TJ",
    "sg:province":"Greater London",
    "sg:tags":[
        "shop"
    ],
    "wof:name":"Nasar Collections",
    "wof:placetype":"venue"
},
  "geometry": {"coordinates":[-0.163275,51.433128],"type":"Point"}
}