{
  "type": "Feature",
  "properties": {
    "addr:full":"53 Mwrog Street Ruthin Denbighshire LL15 1LB",
    "addr:housenumber":"53",
    "addr:postcode":"ll15 1lb",
    "addr:street":"Mwrog Street",
    "iso:country":"GB",
    "sg:address":"53 Mwrog Street",
    "sg:city":"Ruthin",
    "sg:classifiers":[
        {
            "category":"Retail",
            "subcategory":"Auto Repair",
            "type":"Services"
        }
    ],
    "sg:phone":"+44 1824 705565",
    "sg:postcode":"LL15 1LB",
    "sg:province":"Denbighshire",
    "sg:tags":[
        "modification",
        "garage",
        "related"
    ],
    "wof:name":"Glan Clwyd Garage",
    "wof:placetype":"venue"
},
  "geometry": {"coordinates":[-3.317624,53.112091],"type":"Point"}
}