{
  "type": "Feature",
  "properties": {
    "iso:country":"GB",
    "sg:address":"Padside Grn, Summerbridge",
    "sg:city":"Harrogate",
    "sg:classifiers":[
        {
            "category":"Shopping",
            "subcategory":"Photographic Equipment",
            "type":"Retail Goods"
        }
    ],
    "sg:postcode":"HG3 4AL",
    "sg:province":"North Yorkshire",
    "wof:name":"Brent Communications",
    "wof:placetype":"venue"
},
  "geometry": {"coordinates":[-1.693886,54.057629],"type":"Point"}
}