{
  "type": "Feature",
  "properties": {
    "addr:full":"102 High Street Gloucester Gloucestershire GL1 4TA",
    "addr:housenumber":"102",
    "addr:postcode":"gl1 4ta",
    "addr:street":"High Street",
    "iso:country":"GB",
    "sg:address":"102 High Street",
    "sg:city":"Gloucester",
    "sg:classifiers":[
        {
            "category":"Shopping",
            "type":"Retail Goods"
        }
    ],
    "sg:postcode":"GL1 4TA",
    "sg:province":"Gloucestershire",
    "sg:tags":[
        "part",
        "accessory"
    ],
    "wof:name":"Verns Autoparts",
    "wof:placetype":"venue"
},
  "geometry": {"coordinates":[-2.236923,51.854282],"type":"Point"}
}