{
  "type": "Feature",
  "properties": {
    "addr:full":"139 Middleton Blvd Nottingham Nottinghamshire NG8 1FW",
    "addr:housenumber":"139",
    "addr:postcode":"ng8 1fw",
    "addr:street":"Middleton Blvd",
    "iso:country":"GB",
    "sg:address":"139 Middleton Blvd",
    "sg:city":"Nottingham",
    "sg:classifiers":[
        {
            "category":"Building & Trades",
            "subcategory":"Plumbing",
            "type":"Services"
        }
    ],
    "sg:phone":"+44 115 928 6000",
    "sg:postcode":"NG8 1FW",
    "sg:province":"Nottinghamshire",
    "sg:tags":[
        "consultant",
        "heating"
    ],
    "wof:name":"Geoffrey Leathard Associates",
    "wof:placetype":"venue"
},
  "geometry": {"coordinates":[-1.1933890581,52.9547386169],"type":"Point"}
}