{
  "type": "Feature",
  "properties": {
    "iso:country":"GB",
    "sg:address":"1 Glenfield Road",
    "sg:city":"Glasgow",
    "sg:classifiers":[
        {
            "category":"Farming",
            "subcategory":"Dairy Farm",
            "type":"Manufacturing & Wholesale Goods"
        }
    ],
    "sg:phone":"+44 1355 226556",
    "sg:postcode":"G75 0RA",
    "sg:province":"South Lanarkshire",
    "sg:tags":[
        "furnishers"
    ],
    "wof:name":"The Furnishing Service Ltd.",
    "wof:placetype":"venue"
},
  "geometry": {"coordinates":[-4.1609101295,55.7507705688],"type":"Point"}
}