{
  "type": "Feature",
  "properties": {
    "addr:full":"Jonswood Farm, Watchfield Highbridge Somerset TA9 4RD",
    "addr:housenumber":"watchfield highbridge",
    "addr:postcode":"ta9 4rd",
    "addr:street":"Somerset",
    "iso:country":"GB",
    "sg:address":"Jonswood Farm, Watchfield",
    "sg:city":"Highbridge",
    "sg:classifiers":[
        {
            "category":"Building & Trades",
            "subcategory":"Construction",
            "type":"Services"
        }
    ],
    "sg:phone":"+44 1278 793017",
    "sg:postcode":"TA9 4RD",
    "sg:province":"Somerset",
    "sg:tags":[
        "builder"
    ],
    "wof:name":"J & M Cornish & Son",
    "wof:placetype":"venue"
},
  "geometry": {"coordinates":[-2.935894,51.218704],"type":"Point"}
}