{
  "type": "Feature",
  "properties": {
    "addr:full":"34 Bankhead Terrace Lanark South Lanarkshire ML11 9BW",
    "addr:housenumber":"34",
    "addr:postcode":"ml11 9bw",
    "addr:street":"Bankhead Terrace",
    "iso:country":"GB",
    "sg:address":"34 Bankhead Terrace",
    "sg:city":"Lanark",
    "sg:classifiers":[
        {
            "category":"Military Area",
            "subcategory":"Air Force Base",
            "type":"Public Place"
        }
    ],
    "sg:phone":"+44 1555 664780",
    "sg:postcode":"ML11 9BW",
    "sg:province":"South Lanarkshire",
    "sg:tags":[
        "taxi",
        "hire",
        "private"
    ],
    "wof:name":"Carol's Taxis",
    "wof:placetype":"venue"
},
  "geometry": {"coordinates":[-3.7734940052,55.6665802002],"type":"Point"}
}