{
  "type": "Feature",
  "properties": {
    "addr:full":"14 The Delph Peterborough Cambridgeshire PE7 1QH",
    "addr:housenumber":"14",
    "addr:postcode":"pe7 1qh",
    "addr:street":"The Delph",
    "iso:country":"GB",
    "sg:address":"14 The Delph",
    "sg:city":"Peterborough",
    "sg:classifiers":[
        {
            "category":"Food & Beverages",
            "subcategory":"Meat & Fish",
            "type":"Retail Goods"
        }
    ],
    "sg:postcode":"PE7 1QH",
    "sg:province":"Cambridgeshire",
    "sg:tags":[
        "chip"
    ],
    "wof:name":"Delph Fish Shop Paulines Plaice",
    "wof:placetype":"venue"
},
  "geometry": {"coordinates":[-0.125979,52.55772],"type":"Point"}
}