{
  "type": "Feature",
  "properties": {
    "iso:country":"GB",
    "sg:address":"2 The Tythings Commercial Centre",
    "sg:city":"Wincanton",
    "sg:classifiers":[
        {
            "category":"Professional",
            "subcategory":"Art Services",
            "type":"Services"
        }
    ],
    "sg:phone":"+44 1963 32970",
    "sg:postcode":"BA9 9RZ",
    "sg:province":"Somerset",
    "sg:tags":[
        "picture",
        "framing"
    ],
    "wof:name":"M & J Pictures Ltd.",
    "wof:placetype":"venue"
},
  "geometry": {"coordinates":[-2.413179,51.0578],"type":"Point"}
}