{
  "type": "Feature",
  "properties": {
    "iso:country":"GB",
    "sg:address":"132-140 Idle Road",
    "sg:city":"Bradford",
    "sg:classifiers":[
        {
            "category":"Shopping",
            "type":"Retail Goods"
        }
    ],
    "sg:phone":"+44 1274 632911",
    "sg:postcode":"BD2 4NE",
    "sg:province":"West Yorkshire",
    "sg:tags":[
        "bag"
    ],
    "wof:name":"R S Crooke & Co. (Paper Sales) Ltd.",
    "wof:placetype":"venue"
},
  "geometry": {"coordinates":[-1.7327840328,53.812046051],"type":"Point"}
}