{
  "type": "Feature",
  "properties": {
    "iso:country":"GB",
    "sg:address":"West One Ho, 23 St Georges Rd",
    "sg:city":"Cheltenham",
    "sg:classifiers":[
        {
            "category":"Professional",
            "subcategory":"Lawyer & Legal Services",
            "type":"Services"
        }
    ],
    "sg:phone":"+44 1242 228585",
    "sg:postcode":"GL50 3DT",
    "sg:province":"Gloucestershire",
    "sg:tags":[
        "solicitor"
    ],
    "wof:name":"Sheppard's Solicitors",
    "wof:placetype":"venue"
},
  "geometry": {"coordinates":[-2.078459,51.898048],"type":"Point"}
}