{
  "type": "Feature",
  "properties": {
    "addr:full":"23 Richmond Way London Greater London W14 0AS",
    "addr:housenumber":"23",
    "addr:postcode":"w14 0as",
    "addr:street":"Richmond Way",
    "iso:country":"GB",
    "sg:address":"23 Richmond Way",
    "sg:city":"London",
    "sg:classifiers":[
        {
            "category":"Restaurant",
            "type":"Food & Drink"
        }
    ],
    "sg:phone":"+44 20 7603 9461",
    "sg:postcode":"W14 0AS",
    "sg:province":"Greater London",
    "wof:name":"Chinon Restaurant",
    "wof:placetype":"venue"
},
  "geometry": {"coordinates":[-0.2173079997,51.5021286011],"type":"Point"}
}