{
  "type": "Feature",
  "properties": {
    "addr:full":"3 King Edward Drive Grays Essex RM16 2GG",
    "addr:housenumber":"3",
    "addr:postcode":"rm16 2gg",
    "addr:street":"King Edward Drive",
    "iso:country":"GB",
    "sg:address":"3 King Edward Drive",
    "sg:city":"Grays",
    "sg:classifiers":[
        {
            "category":"Building & Trades",
            "subcategory":"Construction",
            "type":"Services"
        }
    ],
    "sg:postcode":"RM16 2GG",
    "sg:province":"Essex",
    "sg:tags":[
        "builder"
    ],
    "wof:name":"Gowler Decorators",
    "wof:placetype":"venue"
},
  "geometry": {"coordinates":[0.3496550024,51.4864654541],"type":"Point"}
}