{
  "type": "Feature",
  "properties": {
    "iso:country":"GB",
    "sg:address":"60 Yelland Road, Fremington",
    "sg:city":"Barnstaple",
    "sg:classifiers":[
        {
            "category":"Building & Trades",
            "subcategory":"Construction",
            "type":"Services"
        }
    ],
    "sg:phone":"+44 1271 860082",
    "sg:postcode":"EX31 3DU",
    "sg:province":"Devon",
    "sg:tags":[
        "builder"
    ],
    "wof:name":"G R H Building Contractors",
    "wof:placetype":"venue"
},
  "geometry": {"coordinates":[-4.1358590126,51.0694198608],"type":"Point"}
}