{
  "type": "Feature",
  "properties": {
    "addr:full":"5 Castlemore Road, Baildon Shipley West Yorkshire BD17 6QN",
    "addr:housenumber":"5",
    "addr:postcode":"bd17 6qn",
    "addr:street":"Castlemore Road",
    "iso:country":"GB",
    "sg:address":"5 Castlemore Road, Baildon",
    "sg:city":"Shipley",
    "sg:classifiers":[
        {
            "category":"Communications",
            "type":"Services"
        }
    ],
    "sg:postcode":"BD17 6QN",
    "sg:province":"West Yorkshire",
    "sg:tags":[
        "audio-visual"
    ],
    "wof:name":"Moorpark Video Productions",
    "wof:placetype":"venue"
},
  "geometry": {"coordinates":[-1.762766,53.847019],"type":"Point"}
}