{
  "type": "Feature",
  "properties": {
    "iso:country":"GB",
    "sg:address":"68 Relugas Rd",
    "sg:city":"Edinburgh",
    "sg:classifiers":[
        {
            "category":"Professional",
            "subcategory":"Employment Agencies",
            "type":"Services"
        }
    ],
    "sg:phone":"+44 131 662 9616",
    "sg:postcode":"EH9 2LZ",
    "sg:province":"City of Edinburgh",
    "sg:tags":[
        "consultant"
    ],
    "wof:name":"Robert Barton Associates",
    "wof:placetype":"venue"
},
  "geometry": {"coordinates":[-3.182536,55.929569],"type":"Point"}
}