{
  "type": "Feature",
  "properties": {
    "addr:full":"Norlie House, Donington Road Boston Lincolnshire PE20 3HL",
    "addr:postcode":"pe20 3hl",
    "addr:street":"Donington Road",
    "iso:country":"GB",
    "sg:address":"Norlie House, Donington Road",
    "sg:city":"Boston",
    "sg:classifiers":[
        {
            "category":"Banks & Credit Unions",
            "subcategory":"Investment Brokerage",
            "type":"Services"
        }
    ],
    "sg:postcode":"PE20 3HL",
    "sg:province":"Lincolnshire",
    "sg:tags":[
        "contractor"
    ],
    "wof:name":"Richard Foster (Contracting) Ltd.",
    "wof:placetype":"venue"
},
  "geometry": {"coordinates":[-0.1790439934,52.919128418],"type":"Point"}
}