{
  "type": "Feature",
  "properties": {
    "addr:full":"57 Burtons Road, Hunton Hill Hampton Greater London TW12 1DE",
    "addr:housenumber":"57",
    "addr:postcode":"tw12 1de",
    "addr:street":"Burtons Road",
    "iso:country":"GB",
    "sg:address":"57 Burtons Road, Hunton Hill",
    "sg:city":"Hampton",
    "sg:classifiers":[
        {
            "category":"Communications",
            "subcategory":"Film & Video Production",
            "type":"Services"
        }
    ],
    "sg:phone":"+44 20 8979 3529",
    "sg:postcode":"TW12 1DE",
    "sg:province":"Greater London",
    "sg:tags":[
        "illustrator",
        "artist"
    ],
    "wof:name":"King & King Associates",
    "wof:placetype":"venue"
},
  "geometry": {"coordinates":[-0.358296,51.431114],"type":"Point"}
}