{
  "type": "Feature",
  "properties": {
    "iso:country":"GB",
    "sg:address":"The Wharf, Carlton-on-trent",
    "sg:city":"Newark",
    "sg:classifiers":[
        {
            "category":"Home & Garden",
            "subcategory":"Garden Supply",
            "type":"Retail Goods"
        },
        {
            "category":"Home & Garden",
            "subcategory":"Hardware",
            "type":"Retail Goods"
        },
        {
            "category":"Manufacturing",
            "subcategory":"Glass & Minerals",
            "type":"Manufacturing & Wholesale Goods"
        }
    ],
    "sg:phone":"+44 1636 821209",
    "sg:postcode":"NG23 6NR",
    "sg:province":"Lincolnshire",
    "sg:tags":[
        "stone",
        "gear",
        "slate",
        "chalk",
        "sand",
        "gravel",
        "cutter"
    ],
    "wof:name":"Robert Teal Ltd.",
    "wof:placetype":"venue"
},
  "geometry": {"coordinates":[-0.808054,53.168705],"type":"Point"}
}