{
  "type": "Feature",
  "properties": {
    "addr:full":"Creaton Road, Brixworth Northampton Northamptonshire NN6 9BW",
    "addr:postcode":"nn6 9bw",
    "addr:street":"Creaton Road",
    "iso:country":"GB",
    "sg:address":"Creaton Road, Brixworth",
    "sg:city":"Northampton",
    "sg:classifiers":[
        {
            "category":"Autos & Motor Vehicles",
            "subcategory":"Fuel & Gas Station",
            "type":"Retail Goods"
        }
    ],
    "sg:phone":"+44 1604 880444",
    "sg:postcode":"NN6 9BW",
    "sg:province":"Northamptonshire",
    "sg:tags":[
        "petrol",
        "filling"
    ],
    "wof:name":"Nene Fuels",
    "wof:placetype":"venue"
},
  "geometry": {"coordinates":[-0.903534,52.329048],"type":"Point"}
}