{
  "type": "Feature",
  "properties": {
    "addr:full":"Bagstone Wotton-under-edge Gloucestershire GL12 8BD",
    "addr:postcode":"gl12 8bd",
    "iso:country":"GB",
    "sg:address":"Bagstone",
    "sg:city":"Wotton-under-edge",
    "sg:classifiers":[
        {
            "category":"Building & Trades",
            "subcategory":"Locksmith",
            "type":"Services"
        }
    ],
    "sg:phone":"+44 1454 228077",
    "sg:postcode":"GL12 8BD",
    "sg:province":"Gloucestershire",
    "wof:name":"Bagstone Truck Services (Car & Commercial Recovery & Repair) Ltd.",
    "wof:placetype":"venue"
},
  "geometry": {"coordinates":[-2.4495270252,51.5768547058],"type":"Point"}
}