{
  "type": "Feature",
  "properties": {
    "iso:country":"GB",
    "sg:address":"Rockliffe Works, Paterson Street",
    "sg:city":"Blackburn",
    "sg:classifiers":[
        {
            "category":"Utilities",
            "subcategory":"Recycling",
            "type":"Services"
        }
    ],
    "sg:phone":"+44 1254 680384",
    "sg:postcode":"BB2 3SP",
    "sg:province":"Lancashire",
    "sg:tags":[
        "raw",
        "material"
    ],
    "wof:name":"Holt & Macintosh Waste Plastics Ltd",
    "wof:placetype":"venue"
},
  "geometry": {"coordinates":[-2.4829199314,53.7392692566],"type":"Point"}
}