{
  "type": "Feature",
  "properties": {
    "addr:full":"127 Greenway Road Runcorn Cheshire WA7 4NT",
    "addr:housenumber":"127",
    "addr:postcode":"wa7 4nt",
    "addr:street":"Greenway Road",
    "iso:country":"GB",
    "sg:address":"127 Greenway Road",
    "sg:city":"Runcorn",
    "sg:classifiers":[
        {
            "category":"Building & Trades",
            "subcategory":"Construction",
            "type":"Services"
        }
    ],
    "sg:phone":"+44 1928 564098",
    "sg:postcode":"WA7 4NT",
    "sg:province":"Cheshire",
    "sg:tags":[
        "fork",
        "lift",
        "truck"
    ],
    "wof:name":"Runcorn Fork Truck Services",
    "wof:placetype":"venue"
},
  "geometry": {"coordinates":[-2.7369229794,53.3347053528],"type":"Point"}
}