{
  "type": "Feature",
  "properties": {
    "iso:country":"GB",
    "sg:address":"53 Coalville Road",
    "sg:city":"St Helens",
    "sg:classifiers":[
        {
            "category":"Building & Trades",
            "subcategory":"Construction",
            "type":"Services"
        }
    ],
    "sg:phone":"+44 1744 756990",
    "sg:postcode":"WA11 9JS",
    "sg:province":"Lancashire",
    "sg:tags":[
        "tiling",
        "contractor"
    ],
    "wof:name":"Paul Waring",
    "wof:placetype":"venue"
},
  "geometry": {"coordinates":[-2.712658,53.466198],"type":"Point"}
}