{
  "type": "Feature",
  "properties": {
    "iso:country":"GB",
    "sg:address":"White House Farm, Reading Road",
    "sg:city":"Hook",
    "sg:classifiers":[
        {
            "category":"Recreation",
            "subcategory":"Fishing",
            "type":"Entertainment"
        }
    ],
    "sg:phone":"+44 1256 767300",
    "sg:postcode":"RG27 9BZ",
    "sg:province":"Berkshire",
    "sg:tags":[
        "equipment",
        "angling"
    ],
    "wof:name":"Nix Angling Supplies",
    "wof:placetype":"venue"
},
  "geometry": {"coordinates":[-0.9575870037,51.2944831848],"type":"Point"}
}