{
  "type": "Feature",
  "properties": {
    "iso:country":"GB",
    "sg:address":"Schoolhouse, Finzean",
    "sg:city":"Banchory",
    "sg:classifiers":[
        {
            "category":"Shopping",
            "subcategory":"Books",
            "type":"Retail Goods"
        }
    ],
    "sg:phone":"+44 1330 850722",
    "sg:postcode":"AB31 6NY",
    "sg:province":"Aberdeen City",
    "wof:name":"Sounding Strings",
    "wof:placetype":"venue"
},
  "geometry": {"coordinates":[-2.651751,57.021698],"type":"Point"}
}