{
  "type": "Feature",
  "properties": {
    "iso:country":"GB",
    "sg:address":"300 Nelson Road",
    "sg:city":"Twickenham",
    "sg:classifiers":[
        {
            "category":"Shopping",
            "subcategory":"News",
            "type":"Retail Goods"
        }
    ],
    "sg:phone":"+44 20 8894 7868",
    "sg:postcode":"TW2 7AJ",
    "sg:province":"Greater London",
    "sg:tags":[
        "newsagent"
    ],
    "wof:name":"Teens",
    "wof:placetype":"venue"
},
  "geometry": {"coordinates":[-0.3678179979,51.4530792236],"type":"Point"}
}