{
  "type": "Feature",
  "properties": {
    "addr:full":"Industrial Estate Rd Llangefni Gwynedd LL77 7JA",
    "addr:postcode":"ll77 7ja",
    "addr:street":"Industrial Estate Rd",
    "iso:country":"GB",
    "sg:address":"Industrial Estate Rd",
    "sg:city":"Llangefni",
    "sg:classifiers":[
        {
            "category":"Retail",
            "subcategory":"Auto Repair",
            "type":"Services"
        }
    ],
    "sg:phone":"+44 1248 724430",
    "sg:postcode":"LL77 7JA",
    "sg:province":"Gwynedd",
    "sg:tags":[
        "modification",
        "garage"
    ],
    "wof:name":"Tyn Lon Garage Paint & Body Centre Ltd",
    "wof:placetype":"venue"
},
  "geometry": {"coordinates":[-4.307204,53.25526],"type":"Point"}
}