{
  "type": "Feature",
  "properties": {
    "addr:full":"22a Long Street Wigston Leicestershire LE18 2AH",
    "addr:housenumber":"22a",
    "addr:postcode":"le18 2ah",
    "addr:street":"Long Street",
    "iso:country":"GB",
    "sg:address":"22a Long Street",
    "sg:city":"Wigston",
    "sg:classifiers":[
        {
            "category":"Home & Garden",
            "subcategory":"Household Appliances",
            "type":"Retail Goods"
        },
        {
            "category":"Building & Trades",
            "subcategory":"Cleaning & Sanitation",
            "type":"Services"
        }
    ],
    "sg:phone":"+44 116 288 3163",
    "sg:postcode":"LE18 2AH",
    "sg:province":"Leicestershire",
    "sg:tags":[
        "cleaner",
        "repairer",
        "domestic",
        "sale",
        "vacuum"
    ],
    "wof:name":"A C Maintenance",
    "wof:placetype":"venue"
},
  "geometry": {"coordinates":[-1.108273983,52.5839271545],"type":"Point"}
}