{
  "type": "Feature",
  "properties": {
    "addr:full":"15 Salkeld Street Glasgow Glasgow City G5 8HE",
    "addr:housenumber":"15",
    "addr:postcode":"g5 8he",
    "addr:street":"Salkeld Street",
    "iso:country":"GB",
    "sg:address":"15 Salkeld Street",
    "sg:city":"Glasgow",
    "sg:classifiers":[
        {
            "category":"Retail",
            "subcategory":"Auto Repair",
            "type":"Services"
        }
    ],
    "sg:phone":"+44 141 429 7262",
    "sg:postcode":"G5 8HE",
    "sg:province":"Glasgow City",
    "sg:tags":[
        "body",
        "car"
    ],
    "wof:name":"Allan's Motor Repairs",
    "wof:placetype":"venue"
},
  "geometry": {"coordinates":[-4.260641,55.849442],"type":"Point"}
}