{
  "type": "Feature",
  "properties": {
    "addr:full":"29 Bar Lane, Stapleford Cambridge Cambridgeshire CB2 5BJ",
    "addr:housenumber":"29",
    "addr:postcode":"cb2 5bj",
    "addr:street":"Bar Lane",
    "iso:country":"GB",
    "sg:address":"29 Bar Lane, Stapleford",
    "sg:city":"Cambridge",
    "sg:classifiers":[
        {
            "category":"Social Services",
            "subcategory":"Child Care",
            "type":"Services"
        }
    ],
    "sg:phone":"+44 1223 843063",
    "sg:postcode":"CB2 5BJ",
    "sg:province":"Cambridgeshire",
    "sg:tags":[
        "children's",
        "home"
    ],
    "wof:name":"The School House",
    "wof:placetype":"venue"
},
  "geometry": {"coordinates":[0.1527229995,52.1455345154],"type":"Point"}
}