{
  "type": "Feature",
  "properties": {
    "addr:full":"29 Champion Hill London Greater London SE5 8AL",
    "addr:housenumber":"29",
    "addr:postcode":"se5 8al",
    "addr:street":"Champion Hill",
    "iso:country":"GB",
    "sg:address":"29 Champion Hill",
    "sg:city":"London",
    "sg:classifiers":[
        {
            "category":"Professional",
            "subcategory":"Management & Consulting",
            "type":"Services"
        }
    ],
    "sg:phone":"+44 20 7738 7712",
    "sg:postcode":"SE5 8AL",
    "sg:province":"Greater London",
    "sg:tags":[
        "consultant",
        "business"
    ],
    "wof:name":"Hughes McCormack Ltd",
    "wof:placetype":"venue"
},
  "geometry": {"coordinates":[-0.0869299993,51.4637184143],"type":"Point"}
}