{
  "type": "Feature",
  "properties": {
    "addr:full":"Dormer House, 1 Shirley Road Rushden Bedfordshire NN10 6BY",
    "addr:housenumber":"1",
    "addr:postcode":"nn10 6by",
    "addr:street":"Shirley Road",
    "iso:country":"GB",
    "sg:address":"Dormer House, 1 Shirley Road",
    "sg:city":"Rushden",
    "sg:classifiers":[
        {
            "category":"Professional",
            "subcategory":"Accounting & Tax Preparation",
            "type":"Services"
        },
        {
            "category":"Banks & Credit Unions",
            "subcategory":"Bank",
            "type":"Services"
        }
    ],
    "sg:postcode":"NN10 6BY",
    "sg:province":"Bedfordshire",
    "sg:tags":[
        "stocktaking",
        "accountant",
        "inventory"
    ],
    "wof:name":"D J Dormer & Son Ltd.",
    "wof:placetype":"venue"
},
  "geometry": {"coordinates":[-0.598025,52.295345],"type":"Point"}
}