{
  "type": "Feature",
  "properties": {
    "addr:full":"Lennox Rd Finsbury Park Greater London N4 3NW",
    "addr:postcode":"n4 3nw",
    "addr:street":"Lennox Rd",
    "iso:country":"GB",
    "sg:address":"Lennox Rd",
    "sg:city":"Finsbury Park",
    "sg:classifiers":[
        {
            "category":"Community Center",
            "subcategory":"Youth",
            "type":"Public Place"
        }
    ],
    "sg:phone":"+44 20 7263 1601",
    "sg:postcode":"N4 3NW",
    "sg:province":"Greater London",
    "sg:tags":[
        "organisation",
        "centre"
    ],
    "wof:name":"Islington YMCA Youth Arts Project",
    "wof:placetype":"venue"
},
  "geometry": {"coordinates":[-0.1083789989,51.5667457581],"type":"Point"}
}