{
  "type": "Feature",
  "properties": {
    "addr:full":"39 Church Street Guisborough North Yorkshire TS14 6HG",
    "addr:housenumber":"39",
    "addr:postcode":"ts14 6hg",
    "addr:street":"Church Street",
    "iso:country":"GB",
    "sg:address":"39 Church Street",
    "sg:city":"Guisborough",
    "sg:classifiers":[
        {
            "category":"Restaurant",
            "type":"Food & Drink"
        }
    ],
    "sg:postcode":"TS14 6HG",
    "sg:province":"North Yorkshire",
    "wof:name":"Cilantro Restaurant",
    "wof:placetype":"venue"
},
  "geometry": {"coordinates":[-1.0494660139,54.5368461609],"type":"Point"}
}