{
  "type": "Feature",
  "properties": {
    "addr:full":"21 Stanley Rd Manchester Lancashire M45 8GT",
    "addr:housenumber":"21",
    "addr:postcode":"m45 8gt",
    "addr:street":"Stanley Rd",
    "iso:country":"GB",
    "sg:address":"21 Stanley Rd",
    "sg:city":"Manchester",
    "sg:classifiers":[
        {
            "category":"Retail",
            "subcategory":"Driving School",
            "type":"Services"
        }
    ],
    "sg:phone":"+44 161 796 2107",
    "sg:postcode":"M45 8GT",
    "sg:province":"Lancashire",
    "wof:name":"A1 Quickpass School Of Motoring",
    "wof:placetype":"venue"
},
  "geometry": {"coordinates":[-2.2931399345,53.5522270203],"type":"Point"}
}