{
  "type": "Feature",
  "properties": {
    "iso:country":"GB",
    "sg:address":"63 Cadmore Lane, Cheshunt",
    "sg:city":"Waltham Cross",
    "sg:classifiers":[
        {
            "category":"Communications",
            "type":"Services"
        }
    ],
    "sg:phone":"+44 1992 632080",
    "sg:postcode":"EN8 9JG",
    "sg:province":"Essex",
    "sg:tags":[
        "telecommunication"
    ],
    "wof:name":"Call Associates Ltd.",
    "wof:placetype":"venue"
},
  "geometry": {"coordinates":[-0.031334,51.709377],"type":"Point"}
}