{
  "type": "Feature",
  "properties": {
    "addr:full":"Unit 21, One Stop Retail Park, Walsall Road Birmingham West Midlands B42 1AA",
    "addr:housenumber":"unit 21",
    "addr:postcode":"b42 1aa",
    "addr:street":"Retail Park Walsall Road",
    "iso:country":"GB",
    "sg:address":"Unit 21, One Stop Retail Park, Walsall Road",
    "sg:city":"Birmingham",
    "sg:classifiers":[
        {
            "category":"Personal",
            "subcategory":"Beauty Salon",
            "type":"Services"
        }
    ],
    "sg:phone":"+44 121 344 4118",
    "sg:postcode":"B42 1AA",
    "sg:province":"West Midlands",
    "sg:tags":[
        "unisex",
        "hairdresser"
    ],
    "wof:name":"Onestop Hair Salon",
    "wof:placetype":"venue"
},
  "geometry": {"coordinates":[-1.903069973,52.5173187256],"type":"Point"}
}