{
  "type": "Feature",
  "properties": {
    "addr:full":"Sterne Street London Greater London W12 8AD",
    "addr:postcode":"w12 8ad",
    "addr:street":"Sterne Street",
    "iso:country":"GB",
    "sg:address":"Sterne Street",
    "sg:city":"London",
    "sg:classifiers":[
        {
            "category":"Retail",
            "subcategory":"Auto Repair",
            "type":"Services"
        }
    ],
    "sg:phone":"+44 20 8740 4380",
    "sg:postcode":"W12 8AD",
    "sg:province":"Greater London",
    "sg:tags":[
        "body",
        "car"
    ],
    "wof:name":"Sheapards Bush Auto Services",
    "wof:placetype":"venue"
},
  "geometry": {"coordinates":[-0.22127,51.505089],"type":"Point"}
}