{
  "type": "Feature",
  "properties": {
    "iso:country":"GB",
    "sg:address":"35 Bunyan Road, Kempston",
    "sg:city":"Bedford",
    "sg:classifiers":[
        {
            "category":"Education",
            "subcategory":"Music School",
            "type":"Public Place"
        }
    ],
    "sg:phone":"+44 1234 853933",
    "sg:postcode":"MK42 8HL",
    "sg:province":"Bedfordshire",
    "sg:tags":[
        "conservatory"
    ],
    "wof:name":"Addison Buildings",
    "wof:placetype":"venue"
},
  "geometry": {"coordinates":[-0.494668,52.117867],"type":"Point"}
}