{
  "type": "Feature",
  "properties": {
    "iso:country":"GB",
    "sg:address":"Granhams Farm, Granhams Road, Grt Shelford",
    "sg:city":"Cambridge",
    "sg:classifiers":[
        {
            "category":"Farming",
            "subcategory":"Livestock Farm",
            "type":"Manufacturing & Wholesale Goods"
        }
    ],
    "sg:phone":"+44 1223 840642",
    "sg:postcode":"CB2 5JX",
    "sg:province":"Cambridgeshire",
    "sg:tags":[
        "others"
    ],
    "wof:name":"L Webster & Sons",
    "wof:placetype":"venue"
},
  "geometry": {"coordinates":[0.134937,52.15308],"type":"Point"}
}