{
  "type": "Feature",
  "properties": {
    "iso:country":"GB",
    "sg:address":"12 Golf Links Road",
    "sg:city":"Burnham-on-sea",
    "sg:classifiers":[
        {
            "category":"Building & Trades",
            "subcategory":"Construction",
            "type":"Services"
        }
    ],
    "sg:phone":"+44 1278 789492",
    "sg:postcode":"TA8 2PW",
    "sg:province":"Somerset",
    "sg:tags":[
        "joinery",
        "joiner",
        "carpenter",
        "carpentry"
    ],
    "wof:name":"Colin Rufus Joinery Service",
    "wof:placetype":"venue"
},
  "geometry": {"coordinates":[-2.999924,51.252911],"type":"Point"}
}