{
  "type": "Feature",
  "properties": {
    "addr:full":"6 Albany Street Edinburgh City of Edinburgh EH1 3QB",
    "addr:housenumber":"6",
    "addr:postcode":"eh1 3qb",
    "addr:street":"Albany Street",
    "iso:country":"GB",
    "sg:address":"6 Albany Street",
    "sg:city":"Edinburgh",
    "sg:classifiers":[
        {
            "category":"Communications",
            "type":"Services"
        }
    ],
    "sg:postcode":"EH1 3QB",
    "sg:province":"City of Edinburgh",
    "sg:tags":[
        "data",
        "network"
    ],
    "wof:name":"Codata Limited",
    "wof:placetype":"venue"
},
  "geometry": {"coordinates":[-3.18625,55.95805],"type":"Point"}
}