{
  "type": "Feature",
  "properties": {
    "addr:full":"Unit 18 Almondvale South Livingston West Lothian EH54 6NG",
    "addr:housenumber":"unit 18",
    "addr:postcode":"eh54 6ng",
    "addr:street":"Almondvale South",
    "iso:country":"GB",
    "sg:address":"Unit 18 Almondvale South",
    "sg:city":"Livingston",
    "sg:classifiers":[
        {
            "category":"Organizations",
            "subcategory":"Non-profit Organization",
            "type":"Services"
        }
    ],
    "sg:phone":"+44 1506 435746",
    "sg:postcode":"EH54 6NG",
    "sg:province":"West Lothian",
    "sg:tags":[
        "organisation",
        "voluntary",
        "charity"
    ],
    "wof:name":"British Heart Foundation",
    "wof:placetype":"venue"
},
  "geometry": {"coordinates":[-3.5088050365,55.8842964172],"type":"Point"}
}