{
  "type": "Feature",
  "properties": {
    "addr:full":"82 Dumbreck Rd Glasgow Glasgow City G41 4SN",
    "addr:housenumber":"82",
    "addr:postcode":"g41 4sn",
    "addr:street":"Dumbreck Rd",
    "iso:country":"GB",
    "sg:address":"82 Dumbreck Rd",
    "sg:city":"Glasgow",
    "sg:classifiers":[
        {
            "category":"Sports & Exercise",
            "subcategory":"Stables",
            "type":"Entertainment"
        }
    ],
    "sg:phone":"+44 141 427 0660",
    "sg:postcode":"G41 4SN",
    "sg:province":"Glasgow City",
    "sg:tags":[
        "education",
        "equestrian"
    ],
    "wof:name":"Dumbreck Riding School",
    "wof:placetype":"venue"
},
  "geometry": {"coordinates":[-4.308084,55.838688],"type":"Point"}
}