{
  "type": "Feature",
  "properties": {
    "iso:country":"GB",
    "sg:address":"Regency House, Bonville Road, Brislington",
    "sg:city":"Bristol",
    "sg:classifiers":[
        {
            "category":"Professional",
            "subcategory":"Business Services",
            "type":"Services"
        }
    ],
    "sg:phone":"+44 117 977 0252",
    "sg:postcode":"BS4 5QH",
    "sg:province":"City of Bristol",
    "sg:tags":[
        "accomodation"
    ],
    "wof:name":"Kirkcave Business Centre",
    "wof:placetype":"venue"
},
  "geometry": {"coordinates":[-2.5358119011,51.4370498657],"type":"Point"}
}