{
  "type": "Feature",
  "properties": {
    "addr:full":"Thirstin Mills, Thirstin Road, Hunley Huddersfield South Yorkshire HD9 6JH",
    "addr:postcode":"hd9 6jh",
    "addr:street":"Thirstin Road",
    "iso:country":"GB",
    "sg:address":"Thirstin Mills, Thirstin Road, Hunley",
    "sg:city":"Huddersfield",
    "sg:classifiers":[
        {
            "category":"Building & Trades",
            "subcategory":"Construction",
            "type":"Services"
        }
    ],
    "sg:postcode":"HD9 6JH",
    "sg:province":"South Yorkshire",
    "sg:tags":[
        "builder"
    ],
    "wof:name":"Jack Brook (Builders) Ltd.",
    "wof:placetype":"venue"
},
  "geometry": {"coordinates":[-1.79835,53.604771],"type":"Point"}
}