{
  "type": "Feature",
  "properties": {
    "iso:country":"GB",
    "sg:address":"45 Maldon Road, Danbury",
    "sg:city":"Chelmsford",
    "sg:classifiers":[
        {
            "category":"Manufacturing",
            "subcategory":"Tools & Machinery",
            "type":"Manufacturing & Wholesale Goods"
        },
        {
            "category":"Home & Garden",
            "subcategory":"Hardware",
            "type":"Retail Goods"
        }
    ],
    "sg:phone":"+44 1245 226565",
    "sg:postcode":"CM3 4QL",
    "sg:province":"Essex",
    "sg:tags":[
        "machine",
        "equipment",
        "welding",
        "manufacturer"
    ],
    "wof:name":"Arc Services",
    "wof:placetype":"venue"
},
  "geometry": {"coordinates":[0.587013,51.716457],"type":"Point"}
}