{
  "type": "Feature",
  "properties": {
    "addr:full":"59 Thoresby Close Bridlington East Riding of Yorkshire YO16 7EN",
    "addr:housenumber":"59",
    "addr:postcode":"yo16 7en",
    "addr:street":"Thoresby Close",
    "iso:country":"GB",
    "sg:address":"59 Thoresby Close",
    "sg:city":"Bridlington",
    "sg:classifiers":[
        {
            "category":"Professional",
            "type":"Services"
        },
        {
            "category":"Professional",
            "subcategory":"Employment Agencies",
            "type":"Services"
        }
    ],
    "sg:phone":"+44 1262 671492",
    "sg:postcode":"YO16 7EN",
    "sg:province":"East Riding of Yorkshire",
    "sg:tags":[
        "entertainer",
        "entertainment"
    ],
    "wof:name":"Safehaven Entertainments Agency",
    "wof:placetype":"venue"
},
  "geometry": {"coordinates":[-0.197552,54.099781],"type":"Point"}
}