{
  "type": "Feature",
  "properties": {
    "addr:full":"High Clays Farm, Stockton Road, Stockton Southam Warwickshire CV47 8LD",
    "addr:postcode":"cv47 8ld",
    "addr:street":"Stockton Road",
    "iso:country":"GB",
    "sg:address":"High Clays Farm, Stockton Road, Stockton",
    "sg:city":"Southam",
    "sg:classifiers":[
        {
            "category":"Building & Trades",
            "subcategory":"Construction",
            "type":"Services"
        }
    ],
    "sg:phone":"+44 1926 815037",
    "sg:postcode":"CV47 8LD",
    "sg:province":"Warwickshire",
    "sg:tags":[
        "welder"
    ],
    "wof:name":"Custom Engineering",
    "wof:placetype":"venue"
},
  "geometry": {"coordinates":[-1.361049,52.271946],"type":"Point"}
}