{
  "type": "Feature",
  "properties": {
    "addr:full":"139-141 Dominion Rd, Glenfield Leicester Leicestershire LE3 8JB",
    "addr:housenumber":"139-141",
    "addr:postcode":"le3 8jb",
    "addr:street":"Dominion Rd",
    "iso:country":"GB",
    "sg:address":"139-141 Dominion Rd, Glenfield",
    "sg:city":"Leicester",
    "sg:classifiers":[
        {
            "category":"Manufacturing",
            "subcategory":"Lumber",
            "type":"Manufacturing & Wholesale Goods"
        }
    ],
    "sg:postcode":"LE3 8JB",
    "sg:province":"Leicestershire",
    "sg:tags":[
        "importer",
        "merchants",
        "agent",
        "timber"
    ],
    "wof:name":"Eyre,William,",
    "wof:placetype":"venue"
},
  "geometry": {"coordinates":[-1.1920429468,52.6449432373],"type":"Point"}
}