{
  "type": "Feature",
  "properties": {
    "iso:country":"GB",
    "sg:address":"20 Bettws Shopping Centre, Bettws",
    "sg:city":"Newport",
    "sg:classifiers":[
        {
            "category":"Cafe",
            "type":"Food & Drink"
        }
    ],
    "sg:postcode":"NP20 7TN",
    "sg:province":"Newport",
    "sg:tags":[
        "tea",
        "room"
    ],
    "wof:name":"Malcolm Arscott",
    "wof:placetype":"venue"
},
  "geometry": {"coordinates":[-3.0181450844,51.6088943481],"type":"Point"}
}