{
  "type": "Feature",
  "properties": {
    "addr:full":"197 Dumbarton Road Clydebank East Dunbartonshire G81 4XJ",
    "addr:housenumber":"197",
    "addr:postcode":"g81 4xj",
    "addr:street":"Dumbarton Road",
    "iso:country":"GB",
    "sg:address":"197 Dumbarton Road",
    "sg:city":"Clydebank",
    "sg:classifiers":[
        {
            "category":"Home & Garden",
            "subcategory":"Household Appliances",
            "type":"Retail Goods"
        },
        {
            "category":"Banks & Credit Unions",
            "subcategory":"Investment Brokerage",
            "type":"Services"
        }
    ],
    "sg:phone":"+44 141 941 3909",
    "sg:postcode":"G81 4XJ",
    "sg:province":"East Dunbartonshire",
    "sg:tags":[
        "equipment",
        "electrical",
        "laundry",
        "sales"
    ],
    "wof:name":"Ron Struthers Laundry Spares & Service",
    "wof:placetype":"venue"
},
  "geometry": {"coordinates":[-4.435649,55.913601],"type":"Point"}
}