{
  "type": "Feature",
  "properties": {
    "iso:country":"GB",
    "sg:address":"15a West End",
    "sg:city":"West Calder",
    "sg:classifiers":[
        {
            "category":"Professional",
            "subcategory":"Accounting & Tax Preparation",
            "type":"Services"
        }
    ],
    "sg:phone":"+44 1506 871796",
    "sg:postcode":"EH55 8EH",
    "sg:province":"South Lanarkshire",
    "sg:tags":[
        "accountant"
    ],
    "wof:name":"B Maloney & Co",
    "wof:placetype":"venue"
},
  "geometry": {"coordinates":[-3.575547,55.850147],"type":"Point"}
}