{
  "type": "Feature",
  "properties": {
    "iso:country":"GB",
    "sg:address":"43 Meneage Street",
    "sg:city":"Helston",
    "sg:classifiers":[
        {
            "category":"Professional",
            "subcategory":"Lawyer & Legal Services",
            "type":"Services"
        }
    ],
    "sg:phone":"+44 1326 573767",
    "sg:postcode":"TR13 8RB",
    "sg:province":"Cornwall",
    "sg:tags":[
        "solicitor"
    ],
    "wof:name":"Davies Partnership",
    "wof:placetype":"venue"
},
  "geometry": {"coordinates":[-5.2730140686,50.1000595093],"type":"Point"}
}