{
  "type": "Feature",
  "properties": {
    "addr:full":"7 Bushell Business Park, Lester Way Wallingford Oxfordshire OX10 9DD",
    "addr:housenumber":"7",
    "addr:postcode":"ox10 9dd",
    "addr:street":"Bushell Business Park Lester Way",
    "iso:country":"GB",
    "sg:address":"7 Bushell Business Park, Lester Way",
    "sg:city":"Wallingford",
    "sg:classifiers":[
        {
            "category":"Shopping",
            "subcategory":"Clothing, Apparel, & Fashions",
            "type":"Retail Goods"
        },
        {
            "category":"Manufacturing",
            "subcategory":"Apparel",
            "type":"Manufacturing & Wholesale Goods"
        }
    ],
    "sg:phone":"+44 70 0045 6700",
    "sg:postcode":"OX10 9DD",
    "sg:province":"Oxfordshire",
    "sg:tags":[
        "clothing",
        "shirt",
        "maker"
    ],
    "wof:name":"L R C Collections Ltd.",
    "wof:placetype":"venue"
},
  "geometry": {"coordinates":[-1.1256229877,51.6009101868],"type":"Point"}
}