{
  "type": "Feature",
  "properties": {
    "iso:country":"GB",
    "sg:address":"4 Parkland Business Centre, Chartwell Road",
    "sg:city":"Lancing",
    "sg:classifiers":[
        {
            "category":"Utilities",
            "subcategory":"Mobile Phone",
            "type":"Services"
        }
    ],
    "sg:phone":"+44 1903 750800",
    "sg:postcode":"BN15 8UE",
    "sg:province":"West Sussex",
    "sg:tags":[
        "mnfr",
        "good",
        "electrical"
    ],
    "wof:name":"Tactical Controls Ltd.",
    "wof:placetype":"venue"
},
  "geometry": {"coordinates":[-0.318039,50.821899],"type":"Point"}
}