{
  "type": "Feature",
  "properties": {
    "iso:country":"GB",
    "sg:address":"Park Manor Farm, Mill End, Audley",
    "sg:city":"Stoke-on-trent",
    "sg:classifiers":[
        {
            "category":"Professional",
            "subcategory":"Business Services",
            "type":"Services"
        },
        {
            "category":"Personal",
            "subcategory":"Adult",
            "type":"Services"
        }
    ],
    "sg:postcode":"ST7 8JH",
    "sg:province":"Cheshire",
    "sg:tags":[
        "bookmaker",
        "equestrian"
    ],
    "wof:name":"Baugh,Brian P J,",
    "wof:placetype":"venue"
},
  "geometry": {"coordinates":[-2.2909638882,53.0545539856],"type":"Point"}
}