{
  "type": "Feature",
  "properties": {
    "addr:full":"4 Station Road, Rainhill Prescot Cheshire L35 0LL",
    "addr:housenumber":"4",
    "addr:postcode":"l35 0ll",
    "addr:street":"Station Road",
    "iso:country":"GB",
    "sg:address":"4 Station Road, Rainhill",
    "sg:city":"Prescot",
    "sg:classifiers":[
        {
            "category":"Home & Garden",
            "subcategory":"Home Furnishings",
            "type":"Retail Goods"
        },
        {
            "category":"Home & Garden",
            "subcategory":"Furniture",
            "type":"Retail Goods"
        }
    ],
    "sg:phone":"+44 151 431 0054",
    "sg:postcode":"L35 0LL",
    "sg:province":"Cheshire",
    "sg:tags":[
        "pine"
    ],
    "wof:name":"Christies",
    "wof:placetype":"venue"
},
  "geometry": {"coordinates":[-2.7667460442,53.4167251587],"type":"Point"}
}