{
  "type": "Feature",
  "properties": {
    "iso:country":"GB",
    "sg:address":"Unit 16, Sandybridge Lane Industrial Estate, Shafton",
    "sg:city":"Barnsley",
    "sg:classifiers":[
        {
            "category":"Retail",
            "subcategory":"Auto Repair",
            "type":"Services"
        }
    ],
    "sg:phone":"+44 1226 781800",
    "sg:postcode":"S72 8PH",
    "sg:province":"South Yorkshire",
    "sg:tags":[
        "truck",
        "repairer",
        "van",
        "bodybuilder"
    ],
    "wof:name":"Unity Coach Painters",
    "wof:placetype":"venue"
},
  "geometry": {"coordinates":[-1.417268,53.601524],"type":"Point"}
}