{
  "type": "Feature",
  "properties": {
    "addr:full":"94 Edgbaston Road Birmingham West Midlands B12 9QA",
    "addr:housenumber":"94",
    "addr:postcode":"b12 9qa",
    "addr:street":"Edgbaston Road",
    "iso:country":"GB",
    "sg:address":"94 Edgbaston Road",
    "sg:city":"Birmingham",
    "sg:classifiers":[
        {
            "category":"Organizations",
            "subcategory":"Non-profit Organization",
            "type":"Services"
        }
    ],
    "sg:phone":"+44 121 440 5890",
    "sg:postcode":"B12 9QA",
    "sg:province":"West Midlands",
    "sg:tags":[
        "charitable",
        "organisation",
        "voluntary",
        "charity"
    ],
    "wof:name":"Action Force Volunteers",
    "wof:placetype":"venue"
},
  "geometry": {"coordinates":[-1.8976089954,52.4542808533],"type":"Point"}
}