{
  "type": "Feature",
  "properties": {
    "iso:country":"GB",
    "sg:address":"Unit 8c, Kayley Industrial Estate",
    "sg:city":"Ashton-under-lyne",
    "sg:classifiers":[
        {
            "category":"Farming",
            "subcategory":"Dairy Farm",
            "type":"Manufacturing & Wholesale Goods"
        }
    ],
    "sg:phone":"+44 161 343 2959",
    "sg:postcode":"OL7 0AU",
    "sg:province":"Greater Manchester",
    "wof:name":"A & I Holmes & Co. Ltd.",
    "wof:placetype":"venue"
},
  "geometry": {"coordinates":[-2.108483,53.487389],"type":"Point"}
}