{
  "type": "Feature",
  "properties": {
    "addr:full":"1-4 Caroline Place Plymouth Devon PL1 3PP",
    "addr:housenumber":"1-4",
    "addr:postcode":"pl1 3pp",
    "addr:street":"Caroline Place",
    "iso:country":"GB",
    "sg:address":"1-4 Caroline Place",
    "sg:city":"Plymouth",
    "sg:classifiers":[
        {
            "category":"Shopping",
            "subcategory":"Computers & Home Electronics",
            "type":"Retail Goods"
        }
    ],
    "sg:phone":"+44 1752 668585",
    "sg:postcode":"PL1 3PP",
    "sg:province":"Devon",
    "sg:tags":[
        "electrical"
    ],
    "wof:name":"Edmundson Electrical Ltd.",
    "wof:placetype":"venue"
},
  "geometry": {"coordinates":[-4.1588439941,50.3670883179],"type":"Point"}
}