{
  "type": "Feature",
  "properties": {
    "addr:full":"Sterling House, Farnham Road Slough Berkshire SL1 4XP",
    "addr:postcode":"sl1 4xp",
    "addr:street":"Farnham Road",
    "iso:country":"GB",
    "sg:address":"Sterling House, Farnham Road",
    "sg:city":"Slough",
    "sg:classifiers":[
        {
            "category":"Organizations",
            "subcategory":"Membership Organization",
            "type":"Services"
        }
    ],
    "sg:postcode":"SL1 4XP",
    "sg:province":"Berkshire",
    "sg:tags":[
        "club"
    ],
    "wof:name":"The Inmarsat Manufacturers' Association",
    "wof:placetype":"venue"
},
  "geometry": {"coordinates":[-0.615949,51.525856],"type":"Point"}
}