{
  "type": "Feature",
  "properties": {
    "addr:full":"22 Royds Lane, Rothwell Leeds West Yorkshire LS26 0BE",
    "addr:housenumber":"22",
    "addr:postcode":"ls26 0be",
    "addr:street":"Royds Lane",
    "iso:country":"GB",
    "sg:address":"22 Royds Lane, Rothwell",
    "sg:city":"Leeds",
    "sg:classifiers":[
        {
            "category":"Health Services",
            "subcategory":"Dentist",
            "type":"Services"
        }
    ],
    "sg:phone":"+44 113 282 2233",
    "sg:postcode":"LS26 0BE",
    "sg:province":"West Yorkshire",
    "wof:name":"Dental Surgery",
    "wof:placetype":"venue"
},
  "geometry": {"coordinates":[-1.476478,53.747776],"type":"Point"}
}