{
  "type": "Feature",
  "properties": {
    "addr:full":"102 Cherwell Dr Walsall Staffordshire WS8 7LL",
    "addr:housenumber":"102",
    "addr:postcode":"ws8 7ll",
    "addr:street":"Cherwell Dr",
    "iso:country":"GB",
    "sg:address":"102 Cherwell Dr",
    "sg:city":"Walsall",
    "sg:classifiers":[
        {
            "category":"Organizations",
            "subcategory":"Community Association",
            "type":"Services"
        }
    ],
    "sg:phone":"+44 1543 453255",
    "sg:postcode":"WS8 7LL",
    "sg:province":"Staffordshire",
    "sg:tags":[
        "relation",
        "public"
    ],
    "wof:name":"Wings Image Consultancy",
    "wof:placetype":"venue"
},
  "geometry": {"coordinates":[-1.957172,52.65942],"type":"Point"}
}