{
  "type": "Feature",
  "properties": {
    "addr:full":"Unit 3, 57 Barclay Street, Monkwearmouth Sunderland Tyne and Wear SR2 8HS",
    "addr:housenumber":"unit;57",
    "addr:postcode":"sr2 8hs",
    "addr:street":"Barclay Street",
    "iso:country":"GB",
    "sg:address":"Unit 3, 57 Barclay Street, Monkwearmouth",
    "sg:city":"Sunderland",
    "sg:classifiers":[
        {
            "category":"Retail",
            "subcategory":"Auto Repair",
            "type":"Services"
        }
    ],
    "sg:phone":"+44 191 514 2115",
    "sg:postcode":"SR2 8HS",
    "sg:province":"Tyne and Wear",
    "sg:tags":[
        "modification",
        "garage"
    ],
    "wof:name":"T A Motors",
    "wof:placetype":"venue"
},
  "geometry": {"coordinates":[-1.37971,54.899281],"type":"Point"}
}