{
  "type": "Feature",
  "properties": {
    "addr:full":"Chaucer House, Wheatley Road Whitstable Kent CT5 1LS",
    "addr:postcode":"ct5 1ls",
    "addr:street":"Wheatley Road",
    "iso:country":"GB",
    "sg:address":"Chaucer House, Wheatley Road",
    "sg:city":"Whitstable",
    "sg:classifiers":[
        {
            "category":"Shopping",
            "subcategory":"Stationery & Office Supplies",
            "type":"Retail Goods"
        },
        {
            "category":"Professional",
            "subcategory":"Business Services",
            "type":"Services"
        }
    ],
    "sg:phone":"+44 1227 280028",
    "sg:postcode":"CT5 1LS",
    "sg:province":"Kent",
    "sg:tags":[
        "interior",
        "planning",
        "design"
    ],
    "wof:name":"Workplace By Design Ltd",
    "wof:placetype":"venue"
},
  "geometry": {"coordinates":[1.0264060497,51.362247467],"type":"Point"}
}