{
  "type": "Feature",
  "properties": {
    "addr:full":"74 Portland Place Hamilton South Lanarkshire ML3 7LA",
    "addr:housenumber":"74",
    "addr:postcode":"ml3 7la",
    "addr:street":"Portland Place",
    "iso:country":"GB",
    "sg:address":"74 Portland Place",
    "sg:city":"Hamilton",
    "sg:classifiers":[
        {
            "category":"Professional",
            "subcategory":"Printing & Photocopies",
            "type":"Services"
        },
        {
            "category":"Organizations",
            "subcategory":"Non-profit Organization",
            "type":"Services"
        }
    ],
    "sg:phone":"+44 1698 891402",
    "sg:postcode":"ML3 7LA",
    "sg:province":"South Lanarkshire",
    "sg:tags":[
        "charitable",
        "organisation",
        "printer",
        "charity"
    ],
    "wof:name":"Voice",
    "wof:placetype":"venue"
},
  "geometry": {"coordinates":[-4.0401701927,55.7686309814],"type":"Point"}
}