{
  "type": "Feature",
  "properties": {
    "addr:full":"52 Back Frederick St Sunderland Tyne and Wear SR1 1NF",
    "addr:housenumber":"52",
    "addr:postcode":"sr1 1nf",
    "addr:street":"Back Frederick St",
    "iso:country":"GB",
    "sg:address":"52 Back Frederick St",
    "sg:city":"Sunderland",
    "sg:classifiers":[
        {
            "category":"Manufacturing",
            "subcategory":"Glass & Minerals",
            "type":"Manufacturing & Wholesale Goods"
        }
    ],
    "sg:postcode":"SR1 1NF",
    "sg:province":"Tyne and Wear",
    "sg:tags":[
        "glassworker"
    ],
    "wof:name":"Ackroyd,Stuart,",
    "wof:placetype":"venue"
},
  "geometry": {"coordinates":[-1.3791069984,54.9062080383],"type":"Point"}
}