{
  "type": "Feature",
  "properties": {
    "addr:full":"123 High Street Rushden Bedfordshire NN10 0NZ",
    "addr:housenumber":"123",
    "addr:postcode":"nn10 0nz",
    "addr:street":"High Street",
    "iso:country":"GB",
    "sg:address":"123 High Street",
    "sg:city":"Rushden",
    "sg:classifiers":[
        {
            "category":"Banks & Credit Unions",
            "subcategory":"Bank",
            "type":"Services"
        },
        {
            "category":"Real Estate",
            "subcategory":"Real Estate Agent",
            "type":"Services"
        }
    ],
    "sg:phone":"+44 1933 316131",
    "sg:postcode":"NN10 0NZ",
    "sg:province":"Bedfordshire",
    "sg:tags":[
        "broker",
        "mortgage"
    ],
    "wof:name":"Prime Choice Ltd.",
    "wof:placetype":"venue"
},
  "geometry": {"coordinates":[-0.5987169743,52.2919120789],"type":"Point"}
}