{
  "type": "Feature",
  "properties": {
    "addr:full":"134 Kings Ash Road Paignton Devon TQ3 3TU",
    "addr:housenumber":"134",
    "addr:postcode":"tq3 3tu",
    "addr:street":"Kings Ash Road",
    "iso:country":"GB",
    "sg:address":"134 Kings Ash Road",
    "sg:city":"Paignton",
    "sg:classifiers":[
        {
            "category":"Building & Trades",
            "subcategory":"Construction",
            "type":"Services"
        }
    ],
    "sg:postcode":"TQ3 3TU",
    "sg:province":"Devon",
    "sg:tags":[
        "builder"
    ],
    "wof:name":"Raymond Dowell",
    "wof:placetype":"venue"
},
  "geometry": {"coordinates":[-3.5887300968,50.4337081909],"type":"Point"}
}