{
  "type": "Feature",
  "properties": {
    "addr:full":"389 Aspley Lane Nottingham Nottinghamshire NG8 5RR",
    "addr:housenumber":"389",
    "addr:postcode":"ng8 5rr",
    "addr:street":"Aspley Lane",
    "iso:country":"GB",
    "sg:address":"389 Aspley Lane",
    "sg:city":"Nottingham",
    "sg:classifiers":[
        {
            "category":"Communications",
            "subcategory":"Film & Video Production",
            "type":"Services"
        }
    ],
    "sg:phone":"+44 115 929 2126",
    "sg:postcode":"NG8 5RR",
    "sg:province":"Nottinghamshire",
    "sg:tags":[
        "tv",
        "studio"
    ],
    "wof:name":"Crestbeam Ltd.",
    "wof:placetype":"venue"
},
  "geometry": {"coordinates":[-1.200756,52.971687],"type":"Point"}
}