{
  "type": "Feature",
  "properties": {
    "iso:country":"GB",
    "sg:address":"2 Craiglinn Yard",
    "sg:city":"Glasgow",
    "sg:classifiers":[
        {
            "category":"Building & Trades",
            "subcategory":"Construction",
            "type":"Services"
        }
    ],
    "sg:phone":"+44 1236 456613",
    "sg:postcode":"G68 9AA",
    "sg:province":"East Dunbartonshire",
    "sg:tags":[
        "builder"
    ],
    "wof:name":"Morris & Bulloch",
    "wof:placetype":"venue"
},
  "geometry": {"coordinates":[-4.033705,55.947563],"type":"Point"}
}