{
  "type": "Feature",
  "properties": {
    "addr:full":"63 Orchard Fld, Bethersden Ashford Kent TN26 3AW",
    "addr:housenumber":"63",
    "addr:postcode":"tn26 3aw",
    "addr:street":"Orchard Fld",
    "iso:country":"GB",
    "sg:address":"63 Orchard Fld, Bethersden",
    "sg:city":"Ashford",
    "sg:classifiers":[
        {
            "category":"Real Estate",
            "subcategory":"Surveying",
            "type":"Services"
        }
    ],
    "sg:phone":"+44 1233 820464",
    "sg:postcode":"TN26 3AW",
    "sg:province":"Kent",
    "sg:tags":[
        "building",
        "surveyor"
    ],
    "wof:name":"Bethersden Surveying Service",
    "wof:placetype":"venue"
},
  "geometry": {"coordinates":[0.75083,51.126762],"type":"Point"}
}