{
  "type": "Feature",
  "properties": {
    "addr:full":"6 Wilford Road, Ruddington Nottingham Nottinghamshire NG11 6EN",
    "addr:housenumber":"6",
    "addr:postcode":"ng11 6en",
    "addr:street":"Wilford Road",
    "iso:country":"GB",
    "sg:address":"6 Wilford Road, Ruddington",
    "sg:city":"Nottingham",
    "sg:classifiers":[
        {
            "category":"Retail",
            "subcategory":"Laundry & Dry Cleaning",
            "type":"Services"
        }
    ],
    "sg:phone":"+44 115 914 8844",
    "sg:postcode":"NG11 6EN",
    "sg:province":"Nottinghamshire",
    "sg:tags":[
        "alteration"
    ],
    "wof:name":"Speedyclean",
    "wof:placetype":"venue"
},
  "geometry": {"coordinates":[-1.149436,52.89304],"type":"Point"}
}