{
  "type": "Feature",
  "properties": {
    "addr:full":"Church Lane, Hampton Bishop Hereford Herefordshire HR1 4JZ",
    "addr:postcode":"hr1 4jz",
    "addr:street":"Church Lane",
    "iso:country":"GB",
    "sg:address":"Church Lane, Hampton Bishop",
    "sg:city":"Hereford",
    "sg:classifiers":[
        {
            "category":"Health Services",
            "subcategory":"Nursing And Care Facility",
            "type":"Services"
        },
        {
            "category":"Social Services",
            "subcategory":"Retirement Home",
            "type":"Services"
        }
    ],
    "sg:phone":"+44 1432 870287",
    "sg:postcode":"HR1 4JZ",
    "sg:province":"Herefordshire",
    "sg:tags":[
        "residential"
    ],
    "wof:name":"Hampton House",
    "wof:placetype":"venue"
},
  "geometry": {"coordinates":[-2.6439790726,52.0380897522],"type":"Point"}
}