{
  "type": "Feature",
  "properties": {
    "addr:full":"2a Workshop Askew Crescent London Greater London W12 9DP",
    "addr:housenumber":"2a workshop",
    "addr:postcode":"w12 9dp",
    "addr:street":"Askew Crescent",
    "iso:country":"GB",
    "sg:address":"2a Workshop Askew Crescent",
    "sg:city":"London",
    "sg:classifiers":[
        {
            "category":"Communications",
            "subcategory":"Film & Video Production",
            "type":"Services"
        }
    ],
    "sg:phone":"+44 20 8743 7597",
    "sg:postcode":"W12 9DP",
    "sg:province":"Greater London",
    "sg:tags":[
        "tv",
        "studio"
    ],
    "wof:name":"Prima Vestor Production",
    "wof:placetype":"venue"
},
  "geometry": {"coordinates":[-0.24336,51.505932],"type":"Point"}
}