{
  "type": "Feature",
  "properties": {
    "addr:full":"245 Hammersmith Rd Hammersmith Greater London W6 8DP",
    "addr:housenumber":"245",
    "addr:postcode":"w6 8dp",
    "addr:street":"Hammersmith Rd",
    "iso:country":"GB",
    "sg:address":"245 Hammersmith Rd",
    "sg:city":"Hammersmith",
    "sg:classifiers":[
        {
            "category":"Professional",
            "subcategory":"Business Services",
            "type":"Services"
        }
    ],
    "sg:phone":"+44 20 8563 1343",
    "sg:postcode":"W6 8DP",
    "sg:province":"Greater London",
    "sg:tags":[
        "import",
        "export",
        "agent"
    ],
    "wof:name":"Kinstreet Ltd",
    "wof:placetype":"venue"
},
  "geometry": {"coordinates":[-0.222604,51.491291],"type":"Point"}
}