{
  "type": "Feature",
  "properties": {
    "addr:full":"1588a Longdon Ho, High St Solihull Warwickshire B93 0LF",
    "addr:housenumber":"1588a",
    "addr:postcode":"b93 0lf",
    "addr:street":"Longdon Ho High St",
    "iso:country":"GB",
    "sg:address":"1588a Longdon Ho, High St",
    "sg:city":"Solihull",
    "sg:classifiers":[
        {
            "category":"Professional",
            "subcategory":"Employment Agencies",
            "type":"Services"
        }
    ],
    "sg:phone":"+44 1564 777702",
    "sg:postcode":"B93 0LF",
    "sg:province":"Warwickshire",
    "sg:tags":[
        "consultant"
    ],
    "wof:name":"Datapol Group Plc",
    "wof:placetype":"venue"
},
  "geometry": {"coordinates":[-1.7363599539,52.3900184631],"type":"Point"}
}