{
  "type": "Feature",
  "properties": {
    "iso:country":"GB",
    "sg:address":"49 Harpenden Rd",
    "sg:city":"St Albans",
    "sg:classifiers":[
        {
            "category":"Utilities",
            "type":"Services"
        }
    ],
    "sg:postcode":"AL3 6BJ",
    "sg:province":"Hertfordshire",
    "sg:tags":[
        "internet"
    ],
    "wof:name":"Winweb International Ltd",
    "wof:placetype":"venue"
},
  "geometry": {"coordinates":[-0.335357,51.766781],"type":"Point"}
}