{
  "type": "Feature",
  "properties": {
    "addr:full":"6 Hedderwickhill Cotts Dunbar East Lothian EH42 1XF",
    "addr:housenumber":"6;cotts",
    "addr:postcode":"eh42 1xf",
    "addr:street":"Hedderwickhill",
    "iso:country":"GB",
    "sg:address":"6 Hedderwickhill Cotts",
    "sg:city":"Dunbar",
    "sg:classifiers":[
        {
            "category":"Building & Trades",
            "subcategory":"Construction",
            "type":"Services"
        }
    ],
    "sg:phone":"+44 1368 863607",
    "sg:postcode":"EH42 1XF",
    "sg:province":"East Lothian",
    "sg:tags":[
        "joiner",
        "carpenter"
    ],
    "wof:name":"Bell Grant Joiners & Building Contractors",
    "wof:placetype":"venue"
},
  "geometry": {"coordinates":[-2.5317790508,55.9884567261],"type":"Point"}
}