{
  "type": "Feature",
  "properties": {
    "iso:country":"GB",
    "sg:address":"High Ridge Farm, Hospital Road, Shirrell Heath",
    "sg:city":"Southampton",
    "sg:classifiers":[
        {
            "category":"Shopping",
            "subcategory":"Pets & Pet Supplies",
            "type":"Retail Goods"
        }
    ],
    "sg:postcode":"SO32 2JR",
    "sg:province":"Hampshire",
    "sg:tags":[
        "equestrian"
    ],
    "wof:name":"Equestrian Services",
    "wof:placetype":"venue"
},
  "geometry": {"coordinates":[-1.188309,50.923725],"type":"Point"}
}