{
  "type": "Feature",
  "properties": {
    "addr:full":"92 Cambridge Street London Greater London SW1V 4QG",
    "addr:housenumber":"92",
    "addr:postcode":"sw1v 4qg",
    "addr:street":"Cambridge Street",
    "iso:country":"GB",
    "sg:address":"92 Cambridge Street",
    "sg:city":"London",
    "sg:classifiers":[
        {
            "category":"Travel",
            "subcategory":"Hotels & Motels",
            "type":"Entertainment"
        }
    ],
    "sg:phone":"+44 20 7834 6467",
    "sg:postcode":"SW1V 4QG",
    "sg:province":"Greater London",
    "wof:name":"Oxford House",
    "wof:placetype":"venue"
},
  "geometry": {"coordinates":[-0.1434680074,51.4898834229],"type":"Point"}
}