{
  "type": "Feature",
  "properties": {
    "iso:country":"GB",
    "sg:address":"92 Cambridge Street",
    "sg:city":"London",
    "sg:classifiers":[
        {
            "category":"Travel",
            "subcategory":"Hotels & Motels",
            "type":"Entertainment"
        }
    ],
    "sg:phone":"+44 20 7834 6467",
    "sg:postcode":"SW1V 4QG",
    "sg:province":"Greater London",
    "wof:name":"Oxford House",
    "wof:placetype":"venue"
},
  "geometry": {"coordinates":[-0.1434680074,51.4898834229],"type":"Point"}
}