{
  "type": "Feature",
  "properties": {
    "addr:full":"Lion Hill, Tadworth St Tadworth Surrey KT20 5RP",
    "addr:postcode":"kt20 5rp",
    "addr:street":"Lion Hill Tadworth St",
    "iso:country":"GB",
    "sg:address":"Lion Hill, Tadworth St",
    "sg:city":"Tadworth",
    "sg:classifiers":[
        {
            "category":"Health Services",
            "subcategory":"Dentist",
            "type":"Services"
        }
    ],
    "sg:phone":"+44 1737 350397",
    "sg:postcode":"KT20 5RP",
    "sg:province":"Surrey",
    "wof:name":"D Orme-smith",
    "wof:placetype":"venue"
},
  "geometry": {"coordinates":[-0.2351489961,51.2915382385],"type":"Point"}
}