{
  "type": "Feature",
  "properties": {
    "iso:country":"GB",
    "sg:address":"7 Green Street",
    "sg:city":"Strathaven",
    "sg:classifiers":[
        {
            "category":"Banks & Credit Unions",
            "subcategory":"Bank",
            "type":"Services"
        }
    ],
    "sg:phone":"+44 135752911127",
    "sg:postcode":"ML10 6LT",
    "sg:province":"South Lanarkshire",
    "sg:tags":[
        "broker",
        "mortgage"
    ],
    "wof:name":"Mortgage Options",
    "wof:placetype":"venue"
},
  "geometry": {"coordinates":[-4.0666770935,55.6774520874],"type":"Point"}
}