{
  "type": "Feature",
  "properties": {
    "addr:full":"Smythen Farm, Sterridge Valley, Berrynarbor Ilfracombe Devon EX34 9TB",
    "addr:housenumber":"berrynarbor ilfracombe",
    "addr:postcode":"ex34 9tb",
    "addr:street":"Sterridge",
    "iso:country":"GB",
    "sg:address":"Smythen Farm, Sterridge Valley, Berrynarbor",
    "sg:city":"Ilfracombe",
    "sg:classifiers":[
        {
            "category":"Travel",
            "subcategory":"Hotels & Motels",
            "type":"Entertainment"
        },
        {
            "category":"Bars & Pubs",
            "subcategory":"Hookah Bar",
            "type":"Food & Drink"
        }
    ],
    "sg:phone":"+44 1271 882875",
    "sg:postcode":"EX34 9TB",
    "sg:province":"Devon",
    "sg:tags":[
        "self",
        "holiday",
        "catering"
    ],
    "wof:name":"Smythen Farm Coastal Holiday Cottages",
    "wof:placetype":"venue"
},
  "geometry": {"coordinates":[-4.123554,51.20816],"type":"Point"}
}