{
  "type": "Feature",
  "properties": {
    "iso:country":"GB",
    "sg:address":"7 Alexandra Rd",
    "sg:city":"Colchester",
    "sg:classifiers":[
        {
            "category":"Professional",
            "subcategory":"Management & Consulting",
            "type":"Services"
        }
    ],
    "sg:postcode":"CO3 3DB",
    "sg:province":"Essex",
    "sg:tags":[
        "consultant",
        "business"
    ],
    "wof:name":"Thomas,Kim,",
    "wof:placetype":"venue"
},
  "geometry": {"coordinates":[0.893658,51.885666],"type":"Point"}
}