{
  "type": "Feature",
  "properties": {
    "iso:country":"GB",
    "sg:address":"89 Portland Rd",
    "sg:city":"Worthing",
    "sg:classifiers":[
        {
            "category":"Building & Trades",
            "subcategory":"Plumbing",
            "type":"Services"
        }
    ],
    "sg:phone":"+44 70 0062 9329",
    "sg:postcode":"BN11 1QG",
    "sg:province":"West Sussex",
    "sg:tags":[
        "heating"
    ],
    "wof:name":"A J Gladman",
    "wof:placetype":"venue"
},
  "geometry": {"coordinates":[-0.3731969893,50.8122558594],"type":"Point"}
}