{
  "type": "Feature",
  "properties": {
    "addr:full":"69a Richardshaw Lane, Stanningley Pudsey West Yorkshire LS28 7EL",
    "addr:housenumber":"69a",
    "addr:postcode":"ls28 7el",
    "addr:street":"Richardshaw Lane;West",
    "iso:country":"GB",
    "sg:address":"69a Richardshaw Lane, Stanningley",
    "sg:city":"Pudsey",
    "sg:classifiers":[
        {
            "category":"Organizations",
            "subcategory":"Labor Organization",
            "type":"Services"
        }
    ],
    "sg:phone":"+44 113 257 7920",
    "sg:postcode":"LS28 7EL",
    "sg:province":"West Yorkshire",
    "sg:tags":[
        "attendance",
        "system",
        "time"
    ],
    "wof:name":"Time Recorder Services",
    "wof:placetype":"venue"
},
  "geometry": {"coordinates":[-1.6643470526,53.8003959656],"type":"Point"}
}