{
  "type": "Feature",
  "properties": {
    "iso:country":"GB",
    "sg:address":"West Dilston Ho, Aldbrough St John",
    "sg:city":"Richmond",
    "sg:classifiers":[
        {
            "category":"Professional",
            "subcategory":"Management & Consulting",
            "type":"Services"
        }
    ],
    "sg:postcode":"DL11 7SZ",
    "sg:province":"Durham",
    "sg:tags":[
        "consultant",
        "business"
    ],
    "wof:name":"O'Connor International",
    "wof:placetype":"venue"
},
  "geometry": {"coordinates":[-1.68857,54.498711],"type":"Point"}
}