{
  "type": "Feature",
  "properties": {
    "addr:full":"3 Burn Road Inverness Highland IV2 4NG",
    "addr:housenumber":"3",
    "addr:postcode":"iv2 4ng",
    "addr:street":"Burn Road",
    "iso:country":"GB",
    "sg:address":"3 Burn Road",
    "sg:city":"Inverness",
    "sg:classifiers":[
        {
            "category":"Building & Trades",
            "subcategory":"Plumbing",
            "type":"Services"
        }
    ],
    "sg:phone":"+44 1463 225343",
    "sg:postcode":"IV2 4NG",
    "sg:province":"Highland",
    "sg:tags":[
        "heating"
    ],
    "wof:name":"Iain A Macrae",
    "wof:placetype":"venue"
},
  "geometry": {"coordinates":[-4.21991,57.463646],"type":"Point"}
}