{
  "type": "Feature",
  "properties": {
    "iso:country":"GB",
    "sg:address":"3 Burn Road",
    "sg:city":"Inverness",
    "sg:classifiers":[
        {
            "category":"Building & Trades",
            "subcategory":"Plumbing",
            "type":"Services"
        }
    ],
    "sg:phone":"+44 1463 225343",
    "sg:postcode":"IV2 4NG",
    "sg:province":"Highland",
    "sg:tags":[
        "heating"
    ],
    "wof:name":"Iain A Macrae",
    "wof:placetype":"venue"
},
  "geometry": {"coordinates":[-4.21991,57.463646],"type":"Point"}
}