{
  "type": "Feature",
  "properties": {
    "addr:full":"Thayers Farm, 6 Thayers Farm Road Beckenham Kent BR3 4LZ",
    "addr:housenumber":"6",
    "addr:postcode":"br3 4lz",
    "addr:street":"Thayers Farm Road",
    "iso:country":"GB",
    "sg:address":"Thayers Farm, 6 Thayers Farm Road",
    "sg:city":"Beckenham",
    "sg:classifiers":[
        {
            "category":"Manufacturing",
            "subcategory":"Signs",
            "type":"Manufacturing & Wholesale Goods"
        }
    ],
    "sg:phone":"+44 20 8402 4240",
    "sg:postcode":"BR3 4LZ",
    "sg:province":"Kent",
    "sg:tags":[
        "commercial",
        "maker"
    ],
    "wof:name":"Signs Sealed & Delivered",
    "wof:placetype":"venue"
},
  "geometry": {"coordinates":[-0.041218,51.409763],"type":"Point"}
}