{
  "type": "Feature",
  "properties": {
    "iso:country":"GB",
    "sg:address":"Robtec House, High Street, Cleobury Mortimer",
    "sg:city":"Kidderminster",
    "sg:classifiers":[
        {
            "category":"Organizations",
            "subcategory":"Labor Organization",
            "type":"Services"
        },
        {
            "category":"Organizations",
            "subcategory":"Professional Association",
            "type":"Services"
        }
    ],
    "sg:phone":"+44 1299 271122",
    "sg:postcode":"DY14 8DP",
    "sg:province":"Shropshire",
    "sg:tags":[
        "control",
        "tech",
        "system",
        "automation"
    ],
    "sg:website":"http://www.robtec-cnc.co.uk",
    "wof:name":"Robtec Automation Ltd.",
    "wof:placetype":"venue"
},
  "geometry": {"coordinates":[-2.484409,52.378506],"type":"Point"}
}