{
  "type": "Feature",
  "properties": {
    "addr:full":"Church Lane, Church End, Sarratt Rickmansworth Hertfordshire WD3 6HH",
    "addr:postcode":"wd3 6hh",
    "addr:street":"Church Lane",
    "iso:country":"GB",
    "sg:address":"Church Lane, Church End, Sarratt",
    "sg:city":"Rickmansworth",
    "sg:classifiers":[
        {
            "category":"Bars & Pubs",
            "type":"Food & Drink"
        }
    ],
    "sg:phone":"+44 1923 282908",
    "sg:postcode":"WD3 6HH",
    "sg:province":"Hertfordshire",
    "sg:tags":[
        "pubs",
        "inn"
    ],
    "wof:name":"The Cock Inn",
    "wof:placetype":"venue"
},
  "geometry": {"coordinates":[-0.4898790121,51.6821517944],"type":"Point"}
}