{
  "type": "Feature",
  "properties": {
    "iso:country":"GB",
    "sg:address":"212-218 Grange Road",
    "sg:city":"Birkenhead",
    "sg:classifiers":[
        {
            "category":"Shopping",
            "subcategory":"Music",
            "type":"Retail Goods"
        }
    ],
    "sg:phone":"+44 151 647 7701",
    "sg:postcode":"CH41 6EA",
    "sg:province":"Merseyside",
    "sg:tags":[
        "record",
        "tape",
        "cd"
    ],
    "wof:name":"Virgin Retail",
    "wof:placetype":"venue"
},
  "geometry": {"coordinates":[-3.027448,53.389652],"type":"Point"}
}