{
  "type": "Feature",
  "properties": {
    "iso:country":"GB",
    "sg:address":"The Palm Ho, Swannery Car Park, Radipole Park Dr",
    "sg:city":"Weymouth",
    "sg:classifiers":[
        {
            "category":"Home & Garden",
            "subcategory":"Garden Supply",
            "type":"Retail Goods"
        }
    ],
    "sg:phone":"+44 1305 784100",
    "sg:postcode":"DT4 7TZ",
    "sg:province":"Dorset",
    "sg:tags":[
        "nursery",
        "centre"
    ],
    "wof:name":"Days Gardening World",
    "wof:placetype":"venue"
},
  "geometry": {"coordinates":[-2.459206,50.609901],"type":"Point"}
}