{
  "type": "Feature",
  "properties": {
    "addr:full":"Unit 10 College Business Centre, Prince Georges Rd Wimbledon Greater London SW19 2PX",
    "addr:housenumber":"unit 10",
    "addr:postcode":"sw19 2px",
    "addr:street":"College Business Centre;Georges Rd",
    "iso:country":"GB",
    "sg:address":"Unit 10 College Business Centre, Prince Georges Rd",
    "sg:city":"Wimbledon",
    "sg:classifiers":[
        {
            "category":"Food & Beverages",
            "subcategory":"Liquor & Beverages",
            "type":"Retail Goods"
        }
    ],
    "sg:phone":"+44 20 8648 9194",
    "sg:postcode":"SW19 2PX",
    "sg:province":"Greater London",
    "sg:tags":[
        "drink",
        "soft"
    ],
    "wof:name":"Edgehill Drinks Ltd",
    "wof:placetype":"venue"
},
  "geometry": {"coordinates":[-0.207024,51.420998],"type":"Point"}
}