{
  "type": "Feature",
  "properties": {
    "addr:full":"76 Henry Road Gloucester Gloucestershire GL1 3DY",
    "addr:housenumber":"76",
    "addr:postcode":"gl1 3dy",
    "addr:street":"Henry Road",
    "iso:country":"GB",
    "sg:address":"76 Henry Road",
    "sg:city":"Gloucester",
    "sg:classifiers":[
        {
            "category":"Building & Trades",
            "subcategory":"Landscaping Services",
            "type":"Services"
        }
    ],
    "sg:phone":"+44 1452 413918",
    "sg:postcode":"GL1 3DY",
    "sg:province":"Gloucestershire",
    "sg:tags":[
        "design",
        "garden",
        "landscape",
        "contractor"
    ],
    "wof:name":"Martin Haward",
    "wof:placetype":"venue"
},
  "geometry": {"coordinates":[-2.235757,51.870049],"type":"Point"}
}