{
  "type": "Feature",
  "properties": {
    "addr:full":"Sea View Road Skegness Lincolnshire PE25 1BT",
    "addr:postcode":"pe25 1bt",
    "addr:street":"Sea View Road",
    "iso:country":"GB",
    "sg:address":"Sea View Road",
    "sg:city":"Skegness",
    "sg:classifiers":[
        {
            "category":"Professional",
            "subcategory":"Testing Lab",
            "type":"Services"
        }
    ],
    "sg:postcode":"PE25 1BT",
    "sg:province":"Lincolnshire",
    "sg:tags":[
        "mot"
    ],
    "wof:name":"A E & C A Pullon",
    "wof:placetype":"venue"
},
  "geometry": {"coordinates":[0.341265,53.151436],"type":"Point"}
}