{
  "type": "Feature",
  "properties": {
    "addr:full":"60 Brooke Street Glasgow Glasgow City G40 2AB",
    "addr:housenumber":"60",
    "addr:postcode":"g40 2ab",
    "addr:street":"Brooke Street",
    "iso:country":"GB",
    "sg:address":"60 Brooke Street",
    "sg:city":"Glasgow",
    "sg:classifiers":[
        {
            "category":"Organizations",
            "subcategory":"Non-profit Organization",
            "type":"Services"
        }
    ],
    "sg:phone":"+44 141 551 0595",
    "sg:postcode":"G40 2AB",
    "sg:province":"Glasgow City",
    "sg:tags":[
        "organisation",
        "voluntary",
        "charity"
    ],
    "wof:name":"West of Scotland Seniors Forum",
    "wof:placetype":"venue"
},
  "geometry": {"coordinates":[-4.2237482071,55.851978302],"type":"Point"}
}