{
  "type": "Feature",
  "properties": {
    "addr:full":"6 Rowtown Addlestone Surrey KT15 1EN",
    "addr:housenumber":"6",
    "addr:postcode":"kt15 1en",
    "addr:street":"Rowtown Addlestone",
    "iso:country":"GB",
    "sg:address":"6 Rowtown",
    "sg:city":"Addlestone",
    "sg:classifiers":[
        {
            "category":"Building & Trades",
            "subcategory":"Construction",
            "type":"Services"
        }
    ],
    "sg:phone":"+44 1932 845357",
    "sg:postcode":"KT15 1EN",
    "sg:province":"Surrey",
    "sg:tags":[
        "contractor"
    ],
    "wof:name":"Choice Southern Contracting",
    "wof:placetype":"venue"
},
  "geometry": {"coordinates":[-0.508184,51.362385],"type":"Point"}
}