{
  "type": "Feature",
  "properties": {
    "addr:full":"30 Causton Street London Greater London SW1P 4AU",
    "addr:housenumber":"30",
    "addr:postcode":"sw1p 4au",
    "addr:street":"Causton Street",
    "iso:country":"GB",
    "sg:address":"30 Causton Street",
    "sg:city":"London",
    "sg:classifiers":[
        {
            "category":"Education",
            "subcategory":"Special Training",
            "type":"Public Place"
        }
    ],
    "sg:phone":"+44 20 7976 5456",
    "sg:postcode":"SW1P 4AU",
    "sg:province":"Greater London",
    "sg:tags":[
        "school"
    ],
    "wof:name":"Assessment Learning London Ltd.",
    "wof:placetype":"venue"
},
  "geometry": {"coordinates":[-0.13121,51.490223],"type":"Point"}
}