{
  "type": "Feature",
  "properties": {
    "addr:full":"50 Tamworth Street Lichfield Staffordshire WS13 6JJ",
    "addr:housenumber":"50",
    "addr:postcode":"ws13 6jj",
    "addr:street":"Tamworth Street",
    "iso:country":"GB",
    "sg:address":"50 Tamworth Street",
    "sg:city":"Lichfield",
    "sg:classifiers":[
        {
            "category":"Restaurant",
            "type":"Food & Drink"
        }
    ],
    "sg:phone":"+44 1543 418515",
    "sg:postcode":"WS13 6JJ",
    "sg:province":"Staffordshire",
    "wof:name":"Lee Garden Cantonese Restaurant",
    "wof:placetype":"venue"
},
  "geometry": {"coordinates":[-1.8249980211,52.6838531494],"type":"Point"}
}