{
  "type": "Feature",
  "properties": {
    "addr:full":"107 London Rd, Hadleigh Benfleet Essex SS7 2QL",
    "addr:housenumber":"107",
    "addr:postcode":"ss7 2ql",
    "addr:street":"London Rd",
    "iso:country":"GB",
    "sg:address":"107 London Rd, Hadleigh",
    "sg:city":"Benfleet",
    "sg:classifiers":[
        {
            "category":"Professional",
            "subcategory":"Business Services",
            "type":"Services"
        }
    ],
    "sg:postcode":"SS7 2QL",
    "sg:province":"Essex",
    "sg:tags":[
        "accomodation"
    ],
    "wof:name":"Memory House (Leigh) Ltd",
    "wof:placetype":"venue"
},
  "geometry": {"coordinates":[0.60384,51.55508],"type":"Point"}
}