{
  "type": "Feature",
  "properties": {
    "addr:full":"223 Stanley Road Bootle Merseyside L20 3DY",
    "addr:housenumber":"223",
    "addr:postcode":"l20 3dy",
    "addr:street":"Stanley Road",
    "iso:country":"GB",
    "sg:address":"223 Stanley Road",
    "sg:city":"Bootle",
    "sg:classifiers":[
        {
            "category":"Shopping",
            "subcategory":"Pharmacy",
            "type":"Retail Goods"
        }
    ],
    "sg:phone":"+44 151 922 5761",
    "sg:postcode":"L20 3DY",
    "sg:province":"Merseyside",
    "sg:tags":[
        "pharmacist",
        "dispensing",
        "chemist"
    ],
    "wof:name":"Merton Dispensing Chemist",
    "wof:placetype":"venue"
},
  "geometry": {"coordinates":[-2.990453,53.449844],"type":"Point"}
}