{
  "type": "Feature",
  "properties": {
    "addr:full":"Lower Farm, High Street Royston Bedfordshire SG8 8HT",
    "addr:postcode":"sg8 8ht",
    "addr:street":"High Street",
    "iso:country":"GB",
    "sg:address":"Lower Farm, High Street",
    "sg:city":"Royston",
    "sg:classifiers":[
        {
            "category":"Farming",
            "subcategory":"Livestock Farm",
            "type":"Manufacturing & Wholesale Goods"
        }
    ],
    "sg:postcode":"SG8 8HT",
    "sg:province":"Bedfordshire",
    "sg:tags":[
        "others"
    ],
    "wof:name":"Manor Farms",
    "wof:placetype":"venue"
},
  "geometry": {"coordinates":[-0.021984,52.04821],"type":"Point"}
}