{
  "type": "Feature",
  "properties": {
    "addr:full":"48 Back Sneddon Street Paisley Renfrewshire PA3 2DD",
    "addr:housenumber":"48",
    "addr:postcode":"pa3 2dd",
    "addr:street":"Back Sneddon Street",
    "iso:country":"GB",
    "sg:address":"48 Back Sneddon Street",
    "sg:city":"Paisley",
    "sg:classifiers":[
        {
            "category":"Food & Beverages",
            "subcategory":"Supermarket",
            "type":"Retail Goods"
        }
    ],
    "sg:phone":"+44 141 889 3286",
    "sg:postcode":"PA3 2DD",
    "sg:province":"Renfrewshire",
    "wof:name":"Safeway Stores Ltd.",
    "wof:placetype":"venue"
},
  "geometry": {"coordinates":[-4.424604,55.850136],"type":"Point"}
}