{
  "type": "Feature",
  "properties": {
    "addr:full":"12 South Park Sevenoaks Kent TN13 1AN",
    "addr:housenumber":"12",
    "addr:postcode":"tn13 1an",
    "addr:street":"South Park",
    "iso:country":"GB",
    "sg:address":"12 South Park",
    "sg:city":"Sevenoaks",
    "sg:classifiers":[
        {
            "category":"Professional",
            "subcategory":"Printing & Photocopies",
            "type":"Services"
        }
    ],
    "sg:phone":"+44 1732 740252",
    "sg:postcode":"TN13 1AN",
    "sg:province":"Kent",
    "sg:tags":[
        "trophy"
    ],
    "wof:name":"Cobbles",
    "wof:placetype":"venue"
},
  "geometry": {"coordinates":[0.1912740022,51.2705421448],"type":"Point"}
}