{
  "type": "Feature",
  "properties": {
    "iso:country":"GB",
    "sg:address":"Manor Ct",
    "sg:city":"Hunstanton",
    "sg:classifiers":[
        {
            "category":"Professional",
            "subcategory":"Lawyer & Legal Services",
            "type":"Services"
        }
    ],
    "sg:phone":"+44 1485 525100",
    "sg:postcode":"PE36 6LN",
    "sg:province":"Norfolk",
    "sg:tags":[
        "solicitor"
    ],
    "wof:name":"Jane Wearing & Co",
    "wof:placetype":"venue"
},
  "geometry": {"coordinates":[0.5417349935,52.9582099915],"type":"Point"}
}