{
  "type": "Feature",
  "properties": {
    "addr:full":"A63 Westbound Brough East Riding of Yorkshire HU15 1RZ",
    "addr:postcode":"hu15 1rz",
    "iso:country":"GB",
    "sg:address":"A63 Westbound",
    "sg:city":"Brough",
    "sg:classifiers":[
        {
            "category":"Autos & Motor Vehicles",
            "subcategory":"Fuel & Gas Station",
            "type":"Retail Goods"
        }
    ],
    "sg:phone":"+44 1430 422127",
    "sg:postcode":"HU15 1RZ",
    "sg:province":"East Riding of Yorkshire",
    "sg:tags":[
        "hr",
        "petrol"
    ],
    "wof:name":"Westcave Services",
    "wof:placetype":"venue"
},
  "geometry": {"coordinates":[-0.558175,53.734268],"type":"Point"}
}