{
  "type": "Feature",
  "properties": {
    "iso:country":"GB",
    "sg:address":"18 Ryelands Clo",
    "sg:city":"Rochdale",
    "sg:classifiers":[
        {
            "category":"Education",
            "subcategory":"Dance Studio",
            "type":"Public Place"
        }
    ],
    "sg:postcode":"OL16 4UE",
    "sg:province":"Lancashire",
    "sg:tags":[
        "school",
        "dancing"
    ],
    "wof:name":"Williamson Dancing School",
    "wof:placetype":"venue"
},
  "geometry": {"coordinates":[-2.143719,53.602631],"type":"Point"}
}