{
  "type": "Feature",
  "properties": {
    "addr:full":"Ingliston Market, Ingliston Newbridge City of Edinburgh EH28 8NB",
    "addr:postcode":"eh28 8nb",
    "addr:street":"Ingliston",
    "iso:country":"GB",
    "sg:address":"Ingliston Market, Ingliston",
    "sg:city":"Newbridge",
    "sg:classifiers":[
        {
            "category":"Professional",
            "subcategory":"Business Services",
            "type":"Services"
        }
    ],
    "sg:phone":"+44 131 333 3801",
    "sg:postcode":"EH28 8NB",
    "sg:province":"City of Edinburgh",
    "sg:tags":[
        "operator",
        "market"
    ],
    "wof:name":"Spook Erections",
    "wof:placetype":"venue"
},
  "geometry": {"coordinates":[-3.409335,55.940845],"type":"Point"}
}