{
  "type": "Feature",
  "properties": {
    "addr:full":"493 Sunderland Road Gateshead Tyne and Wear NE8 3QQ",
    "addr:housenumber":"493",
    "addr:postcode":"ne8 3qq",
    "addr:street":"Sunderland Road",
    "iso:country":"GB",
    "sg:address":"493 Sunderland Road",
    "sg:city":"Gateshead",
    "sg:classifiers":[
        {
            "category":"Food & Beverages",
            "subcategory":"Liquor & Beverages",
            "type":"Retail Goods"
        }
    ],
    "sg:postcode":"NE8 3QQ",
    "sg:province":"Tyne and Wear",
    "sg:tags":[
        "beer",
        "spirit",
        "wines"
    ],
    "wof:name":"Top Shop",
    "wof:placetype":"venue"
},
  "geometry": {"coordinates":[-1.582618,54.954636],"type":"Point"}
}