{
  "type": "Feature",
  "properties": {
    "iso:country":"GB",
    "sg:address":"70-76 St Georges Street",
    "sg:city":"Norwich",
    "sg:classifiers":[
        {
            "category":"Restaurant",
            "type":"Food & Drink"
        }
    ],
    "sg:phone":"+44 1603 626626",
    "sg:postcode":"NR3 1AB",
    "sg:province":"Norfolk",
    "wof:name":"Last Wine Bars Ltd.",
    "wof:placetype":"venue"
},
  "geometry": {"coordinates":[1.294695,52.632797],"type":"Point"}
}