{
  "type": "Feature",
  "properties": {
    "iso:country":"GB",
    "sg:address":"12 Wild Ridings Square",
    "sg:city":"Bracknell",
    "sg:classifiers":[
        {
            "category":"Real Estate",
            "subcategory":"Real Estate Agent",
            "type":"Services"
        }
    ],
    "sg:phone":"+44 1344 868634",
    "sg:postcode":"RG12 7SJ",
    "sg:province":"Berkshire",
    "wof:name":"Andrew Lampkin",
    "wof:placetype":"venue"
},
  "geometry": {"coordinates":[-0.762474,51.407711],"type":"Point"}
}