{
  "type": "Feature",
  "properties": {
    "addr:full":"Sportsview, Bryn Estyn Rd Wrexham Wrexham LL13 9TY",
    "addr:postcode":"ll13 9ty",
    "addr:street":"Estyn Rd",
    "iso:country":"GB",
    "sg:address":"Sportsview, Bryn Estyn Rd",
    "sg:city":"Wrexham",
    "sg:classifiers":[
        {
            "category":"Arena",
            "subcategory":"Sports Club",
            "type":"Entertainment"
        }
    ],
    "sg:phone":"+44 1978 311553",
    "sg:postcode":"LL13 9TY",
    "sg:province":"Wrexham",
    "wof:name":"Welsh Rugby Union",
    "wof:placetype":"venue"
},
  "geometry": {"coordinates":[-2.968279,53.054596],"type":"Point"}
}