{
  "type": "Feature",
  "properties": {
    "iso:country":"GB",
    "sg:address":"10 Old Mill Crescent",
    "sg:city":"Newark",
    "sg:classifiers":[
        {
            "category":"Health Services",
            "subcategory":"Podiatrist",
            "type":"Services"
        }
    ],
    "sg:postcode":"NG24 2HY",
    "sg:province":"Nottinghamshire",
    "sg:tags":[
        "podiatrists",
        "chiropodist"
    ],
    "wof:name":"J M M Jackson",
    "wof:placetype":"venue"
},
  "geometry": {"coordinates":[-0.793173,53.074692],"type":"Point"}
}