{
  "type": "Feature",
  "properties": {
    "iso:country":"GB",
    "sg:address":"Pendre Farm",
    "sg:city":"Caersws",
    "sg:classifiers":[
        {
            "category":"Farming",
            "subcategory":"Livestock Farm",
            "type":"Manufacturing & Wholesale Goods"
        }
    ],
    "sg:phone":"+44 1686 688288",
    "sg:postcode":"SY17 5EF",
    "sg:province":"Powys",
    "sg:tags":[
        "others"
    ],
    "wof:name":"Brian Brown",
    "wof:placetype":"venue"
},
  "geometry": {"coordinates":[-3.430329,52.516735],"type":"Point"}
}