{
  "type": "Feature",
  "properties": {
    "iso:country":"GB",
    "sg:address":"Ewenny Road, St Brides Major",
    "sg:city":"Bridgend",
    "sg:classifiers":[
        {
            "category":"Retail",
            "subcategory":"Funeral Services",
            "type":"Services"
        }
    ],
    "sg:phone":"+44 1656 880308",
    "sg:postcode":"CF32 0SB",
    "sg:province":"Bridgend",
    "wof:name":"J R David",
    "wof:placetype":"venue"
},
  "geometry": {"coordinates":[-3.558979,51.459396],"type":"Point"}
}