{
  "type": "Feature",
  "properties": {
    "addr:full":"Merryvale Road Okehampton Devon EX20 1UB",
    "addr:postcode":"ex20 1ub",
    "addr:street":"Merryvale Road",
    "iso:country":"GB",
    "sg:address":"Merryvale Road",
    "sg:city":"Okehampton",
    "sg:classifiers":[
        {
            "category":"Personal",
            "type":"Services"
        }
    ],
    "sg:phone":"+44 1837 54451",
    "sg:postcode":"EX20 1UB",
    "sg:province":"Devon",
    "sg:tags":[
        "delivery"
    ],
    "wof:name":"Target Worldwide Express",
    "wof:placetype":"venue"
},
  "geometry": {"coordinates":[-4.0025148392,50.7392234802],"type":"Point"}
}