{
  "type": "Feature",
  "properties": {
    "addr:full":"8-10 Dixons Fold, North Walsham Road Norwich Norfolk NR6 7QD",
    "addr:housenumber":"8-10",
    "addr:postcode":"nr6 7qd",
    "addr:street":"Dixons Fold North Walsham Road Norwich Norfolk",
    "iso:country":"GB",
    "sg:address":"8-10 Dixons Fold, North Walsham Road",
    "sg:city":"Norwich",
    "sg:classifiers":[
        {
            "category":"Food & Beverages",
            "subcategory":"Liquor & Beverages",
            "type":"Retail Goods"
        }
    ],
    "sg:phone":"+44 1603 429043",
    "sg:postcode":"NR6 7QD",
    "sg:province":"Norfolk",
    "sg:tags":[
        "beer",
        "spirit",
        "wines"
    ],
    "wof:name":"Unwins Wine Merchants",
    "wof:placetype":"venue"
},
  "geometry": {"coordinates":[1.320735,52.667995],"type":"Point"}
}