{
  "type": "Feature",
  "properties": {
    "addr:full":"9 Penlan Street Pwllheli Gwynedd LL53 5DH",
    "addr:housenumber":"9",
    "addr:postcode":"ll53 5dh",
    "addr:street":"Penlan Street",
    "iso:country":"GB",
    "sg:address":"9 Penlan Street",
    "sg:city":"Pwllheli",
    "sg:classifiers":[
        {
            "category":"Personal",
            "subcategory":"Beauty Salon",
            "type":"Services"
        },
        {
            "category":"Personal",
            "subcategory":"Barber",
            "type":"Services"
        }
    ],
    "sg:phone":"+44 1758 612566",
    "sg:postcode":"LL53 5DH",
    "sg:province":"Gwynedd",
    "sg:tags":[
        "unisex",
        "hairdresser"
    ],
    "wof:name":"Patricia'S Hairdressers",
    "wof:placetype":"venue"
},
  "geometry": {"coordinates":[-4.4165511131,52.8895568848],"type":"Point"}
}