{
  "type": "Feature",
  "properties": {
    "addr:full":"Hir Waun, Tylwch Llanidloes Powys SY18 6JS",
    "addr:postcode":"sy18 6js",
    "addr:street":"Hir",
    "iso:country":"GB",
    "sg:address":"Hir Waun, Tylwch",
    "sg:city":"Llanidloes",
    "sg:classifiers":[
        {
            "category":"Farming",
            "subcategory":"Livestock Farm",
            "type":"Manufacturing & Wholesale Goods"
        },
        {
            "category":"Farming",
            "subcategory":"Farm",
            "type":"Manufacturing & Wholesale Goods"
        }
    ],
    "sg:postcode":"SY18 6JS",
    "sg:province":"Powys",
    "sg:tags":[
        "mixed",
        "crop",
        "others"
    ],
    "wof:name":"Cemlyn J Sheen",
    "wof:placetype":"venue"
},
  "geometry": {"coordinates":[-3.5401659012,52.4459152222],"type":"Point"}
}