{
  "type": "Feature",
  "properties": {
    "addr:full":"Torrington Health Centre, New Rd Torrington Devon EX38 8EL",
    "addr:postcode":"ex38 8el",
    "addr:street":"New Rd",
    "iso:country":"GB",
    "sg:address":"Torrington Health Centre, New Rd",
    "sg:city":"Torrington",
    "sg:classifiers":[
        {
            "category":"Health Services",
            "subcategory":"Doctor",
            "type":"Services"
        }
    ],
    "sg:phone":"+44 1805 622247",
    "sg:postcode":"EX38 8EL",
    "sg:province":"Devon",
    "sg:tags":[
        "practitioners"
    ],
    "wof:name":"Armstrong, B",
    "wof:placetype":"venue"
},
  "geometry": {"coordinates":[-4.1422548294,50.9531517029],"type":"Point"}
}