{
  "type": "Feature",
  "properties": {
    "addr:full":"20 Harbour Street Nairn Highland IV12 4NU",
    "addr:housenumber":"20",
    "addr:postcode":"iv12 4nu",
    "addr:street":"Harbour Street",
    "iso:country":"GB",
    "sg:address":"20 Harbour Street",
    "sg:city":"Nairn",
    "sg:classifiers":[
        {
            "category":"Shopping",
            "subcategory":"Department Store",
            "type":"Retail Goods"
        },
        {
            "category":"Food & Beverages",
            "subcategory":"Supermarket",
            "type":"Retail Goods"
        },
        {
            "category":"Food & Beverages",
            "subcategory":"Groceries & Convenience Stores",
            "type":"Retail Goods"
        }
    ],
    "sg:phone":"+44 1667 453280",
    "sg:postcode":"IV12 4NU",
    "sg:province":"Highland",
    "wof:name":"Harbour Street Stores",
    "wof:placetype":"venue"
},
  "geometry": {"coordinates":[-3.8650789261,57.5865440369],"type":"Point"}
}