{
  "type": "Feature",
  "properties": {
    "addr:full":"The Street Bury St Edmunds Cambridgeshire IP28 8AE",
    "addr:postcode":"ip28 8ae",
    "addr:street":"The Street",
    "iso:country":"GB",
    "sg:address":"The Street",
    "sg:city":"Bury St Edmunds",
    "sg:classifiers":[
        {
            "category":"Place Of Worship",
            "type":"Public Place"
        }
    ],
    "sg:phone":"+44 1638 713145",
    "sg:postcode":"IP28 8AE",
    "sg:province":"Cambridgeshire",
    "wof:name":"Beck Row Methodist Church",
    "wof:placetype":"venue"
},
  "geometry": {"coordinates":[0.483793,52.371155],"type":"Point"}
}