{
  "type": "Feature",
  "properties": {
    "addr:full":"The Old Bakery High Wych Rd, High Wych Sawbridgeworth Essex CM21 0HZ",
    "addr:postcode":"cm21 0hz",
    "addr:street":"High Wych Rd",
    "iso:country":"GB",
    "sg:address":"The Old Bakery High Wych Rd, High Wych",
    "sg:city":"Sawbridgeworth",
    "sg:classifiers":[
        {
            "category":"Farming",
            "subcategory":"Nursery",
            "type":"Manufacturing & Wholesale Goods"
        }
    ],
    "sg:phone":"+44 1279 725275",
    "sg:postcode":"CM21 0HZ",
    "sg:province":"Essex",
    "sg:tags":[
        "creche"
    ],
    "wof:name":"Cherish Private Day Nursery",
    "wof:placetype":"venue"
},
  "geometry": {"coordinates":[0.12242,51.808052],"type":"Point"}
}