{
  "type": "Feature",
  "properties": {
    "addr:full":"2 Fishermans Way Bourne End Berkshire SL8 5LY",
    "addr:housenumber":"2",
    "addr:postcode":"sl8 5ly",
    "addr:street":"Fishermans Way",
    "iso:country":"GB",
    "sg:address":"2 Fishermans Way",
    "sg:city":"Bourne End",
    "sg:classifiers":[
        {
            "category":"Professional",
            "subcategory":"Art Services",
            "type":"Services"
        },
        {
            "category":"Building & Trades",
            "subcategory":"Construction",
            "type":"Services"
        }
    ],
    "sg:phone":"+44 1628 528921",
    "sg:postcode":"SL8 5LY",
    "sg:province":"Berkshire",
    "sg:tags":[
        "decorator",
        "painter"
    ],
    "wof:name":"N W Upward",
    "wof:placetype":"venue"
},
  "geometry": {"coordinates":[-0.7095270157,51.5806427002],"type":"Point"}
}