{
  "type": "Feature",
  "properties": {
    "addr:full":"Unit 13.5 Wealden Forest Park, Herne Common Herne Bay Kent CT6 7LQ",
    "addr:postcode":"ct6 7lq",
    "addr:street":"Herne",
    "iso:country":"GB",
    "sg:address":"Unit 13.5 Wealden Forest Park, Herne Common",
    "sg:city":"Herne Bay",
    "sg:classifiers":[
        {
            "category":"Building & Trades",
            "subcategory":"Construction",
            "type":"Services"
        }
    ],
    "sg:phone":"+44 1227 711090",
    "sg:postcode":"CT6 7LQ",
    "sg:province":"Kent",
    "sg:tags":[
        "surfacing",
        "road"
    ],
    "wof:name":"Kent Roadmarking Co",
    "wof:placetype":"venue"
},
  "geometry": {"coordinates":[1.1251,51.371216],"type":"Point"}
}