{
  "type": "Feature",
  "properties": {
    "addr:full":"Ysgubor Wen, Tan-y-bwlch Blaenau Ffestiniog Gwynedd LL41 3YU",
    "addr:postcode":"ll41 3yu",
    "addr:street":"Ysgubor;Tan-Y-Bwlch",
    "iso:country":"GB",
    "sg:address":"Ysgubor Wen, Tan-y-bwlch",
    "sg:city":"Blaenau Ffestiniog",
    "sg:classifiers":[
        {
            "category":"Restaurant",
            "type":"Food & Drink"
        }
    ],
    "sg:phone":"+44 1766 590391",
    "sg:postcode":"LL41 3YU",
    "sg:province":"Gwynedd",
    "wof:name":"The White Barn",
    "wof:placetype":"venue"
},
  "geometry": {"coordinates":[-3.9405050278,52.9953422546],"type":"Point"}
}