{
  "type": "Feature",
  "properties": {
    "iso:country":"GB",
    "sg:address":"P O Box 52, High Street, Kippax",
    "sg:city":"Leeds",
    "sg:classifiers":[
        {
            "category":"Building & Trades",
            "subcategory":"Pest Control",
            "type":"Services"
        },
        {
            "category":"Building & Trades",
            "subcategory":"Construction",
            "type":"Services"
        }
    ],
    "sg:phone":"+44 113 286 5056",
    "sg:postcode":"LS25 7AJ",
    "sg:province":"North Yorkshire",
    "sg:tags":[
        "painting",
        "decorator",
        "painter",
        "contractor"
    ],
    "wof:name":"Steven Parker Painting Contractors Ltd.",
    "wof:placetype":"venue"
},
  "geometry": {"coordinates":[-1.371276021,53.7708320618],"type":"Point"}
}