{
  "type": "Feature",
  "properties": {
    "iso:country":"GB",
    "sg:address":"Pendon View House, Eastside Lane, Bawdrip",
    "sg:city":"Bridgwater",
    "sg:classifiers":[
        {
            "category":"Home & Garden",
            "subcategory":"Carpets & Floor Coverings",
            "type":"Retail Goods"
        }
    ],
    "sg:phone":"+44 1278 685333",
    "sg:postcode":"TA7 8QB",
    "sg:province":"Somerset",
    "sg:tags":[
        "cleaner",
        "upholstery"
    ],
    "wof:name":"A B C Cleaning",
    "wof:placetype":"venue"
},
  "geometry": {"coordinates":[-2.942987,51.15078],"type":"Point"}
}