{
  "type": "Feature",
  "properties": {
    "addr:full":"Milburn Hall Haugh Head Wooler Northumberland NE71 6QU",
    "addr:postcode":"ne71 6qu",
    "addr:street":"Haugh Head",
    "iso:country":"GB",
    "sg:address":"Milburn Hall Haugh Head",
    "sg:city":"Wooler",
    "sg:classifiers":[
        {
            "category":"Professional",
            "subcategory":"Engineering",
            "type":"Services"
        }
    ],
    "sg:postcode":"NE71 6QU",
    "sg:province":"Northumberland",
    "wof:name":"D S U Ltd",
    "wof:placetype":"venue"
},
  "geometry": {"coordinates":[-2.011584,55.547771],"type":"Point"}
}