{
  "type": "Feature",
  "properties": {
    "addr:full":"Claremont St Newcastle Upon Tyne Tyne and Wear NE2 4AH",
    "addr:postcode":"ne2 4ah",
    "addr:street":"Claremont St",
    "iso:country":"GB",
    "sg:address":"Claremont St",
    "sg:city":"Newcastle Upon Tyne",
    "sg:classifiers":[
        {
            "category":"Place Of Worship",
            "type":"Public Place"
        }
    ],
    "sg:phone":"+44 191 232 3341",
    "sg:postcode":"NE2 4AH",
    "sg:province":"Tyne and Wear",
    "wof:name":"St Luke's Church",
    "wof:placetype":"venue"
},
  "geometry": {"coordinates":[-1.6241500378,54.9832992554],"type":"Point"}
}