{
  "type": "Feature",
  "properties": {
    "iso:country":"GB",
    "sg:address":"3 Brindley Place",
    "sg:city":"Birmingham",
    "sg:classifiers":[
        {
            "category":"Real Estate",
            "subcategory":"Surveying",
            "type":"Services"
        }
    ],
    "sg:phone":"+44 870 900 8990",
    "sg:postcode":"B1 2JB",
    "sg:province":"West Midlands",
    "sg:tags":[
        "surveyor",
        "valuer"
    ],
    "wof:name":"G V A Grimley",
    "wof:placetype":"venue"
},
  "geometry": {"coordinates":[-1.909594,52.480797],"type":"Point"}
}