{
  "type": "Feature",
  "properties": {
    "addr:full":"3 The Oaklands, Etchinghill Rugeley Staffordshire WS15 2SD",
    "addr:housenumber":"3",
    "addr:postcode":"ws15 2sd",
    "addr:street":"The;Etchinghill",
    "iso:country":"GB",
    "sg:address":"3 The Oaklands, Etchinghill",
    "sg:city":"Rugeley",
    "sg:classifiers":[
        {
            "category":"Retail",
            "subcategory":"Repair Shop",
            "type":"Services"
        }
    ],
    "sg:phone":"+44 1889 570056",
    "sg:postcode":"WS15 2SD",
    "sg:province":"Staffordshire",
    "sg:tags":[
        "maintenance"
    ],
    "wof:name":"D N T Property Maintenance",
    "wof:placetype":"venue"
},
  "geometry": {"coordinates":[-1.9555319548,52.7608566284],"type":"Point"}
}