{
  "type": "Feature",
  "properties": {
    "iso:country":"GB",
    "sg:address":"14 West Mackenzie Park",
    "sg:city":"Inverness",
    "sg:classifiers":[
        {
            "category":"Transit Center",
            "subcategory":"Freight",
            "type":"Transportation"
        }
    ],
    "sg:phone":"+44 1463 239313",
    "sg:postcode":"IV2 3ST",
    "sg:province":"Highland",
    "sg:tags":[
        "piano",
        "accessory"
    ],
    "wof:name":"Graham Muir Piano Tuning & Servicing H.N.D. M.I.T",
    "wof:placetype":"venue"
},
  "geometry": {"coordinates":[-4.2004380226,57.4668617249],"type":"Point"}
}