{
  "type": "Feature",
  "properties": {
    "addr:full":"415 Strand London Greater London WC2R 0NS",
    "addr:housenumber":"415",
    "addr:postcode":"wc2r 0ns",
    "addr:street":"Strand",
    "iso:country":"GB",
    "sg:address":"415 Strand",
    "sg:city":"London",
    "sg:classifiers":[
        {
            "category":"Banks & Credit Unions",
            "subcategory":"Financial Services",
            "type":"Services"
        }
    ],
    "sg:phone":"+44 20 7599 0600",
    "sg:postcode":"WC2R 0NS",
    "sg:province":"Greater London",
    "sg:tags":[
        "building",
        "society"
    ],
    "wof:name":"Nationwide Building Society",
    "wof:placetype":"venue"
},
  "geometry": {"coordinates":[-0.1191890016,51.5112800598],"type":"Point"}
}