{
  "type": "Feature",
  "properties": {
    "addr:full":"Worthy Road, Chittening Trading Estate Bristol City of Bristol BS11 0YB",
    "addr:postcode":"bs11 0yb",
    "addr:street":"Worthy Road Chittening Trading Estate",
    "iso:country":"GB",
    "sg:address":"Worthy Road, Chittening Trading Estate",
    "sg:city":"Bristol",
    "sg:classifiers":[
        {
            "category":"Home & Garden",
            "subcategory":"Carpets & Floor Coverings",
            "type":"Retail Goods"
        }
    ],
    "sg:phone":"+44 117 938 2100",
    "sg:postcode":"BS11 0YB",
    "sg:province":"City of Bristol",
    "sg:tags":[
        "crane"
    ],
    "wof:name":"Lifting Equipment Ltd.",
    "wof:placetype":"venue"
},
  "geometry": {"coordinates":[-2.680619,51.527954],"type":"Point"}
}