{
  "type": "Feature",
  "properties": {
    "addr:full":"Unit5, Island Carr Industrial Estate, Island Carr Road Brigg Lincolnshire DN20 8PD",
    "addr:postcode":"dn20 8pd",
    "addr:street":"Unit5 Island Carr Industrial Estate Island Carr Road",
    "iso:country":"GB",
    "sg:address":"Unit5, Island Carr Industrial Estate, Island Carr Road",
    "sg:city":"Brigg",
    "sg:classifiers":[
        {
            "category":"Wholesale",
            "subcategory":"Medical Equipment & Supplies",
            "type":"Manufacturing & Wholesale Goods"
        },
        {
            "category":"Health Services",
            "subcategory":"Clinic",
            "type":"Services"
        }
    ],
    "sg:phone":"+44 1652 657200",
    "sg:postcode":"DN20 8PD",
    "sg:province":"Lincolnshire",
    "sg:tags":[
        "manufacture"
    ],
    "wof:name":"Oak Medical Services Ltd.",
    "wof:placetype":"venue"
},
  "geometry": {"coordinates":[-0.484879,53.552986],"type":"Point"}
}