{
  "type": "Feature",
  "properties": {
    "iso:country":"GB",
    "sg:address":"The Upper Drive",
    "sg:city":"Hove",
    "sg:classifiers":[
        {
            "category":"Education",
            "subcategory":"School",
            "type":"Public Place"
        },
        {
            "category":"Government",
            "subcategory":"Office",
            "type":"Public Place"
        }
    ],
    "sg:phone":"+44 1273 555811",
    "sg:postcode":"BN3 6NB",
    "sg:province":"East Sussex",
    "sg:tags":[
        "local",
        "authority"
    ],
    "wof:name":"Cottesmore St Mary's R C Primary School",
    "wof:placetype":"venue"
},
  "geometry": {"coordinates":[-0.1560160071,50.8384819031],"type":"Point"}
}