{
  "type": "Feature",
  "properties": {
    "iso:country":"GB",
    "sg:address":"119 Chadwell Heath Lane",
    "sg:city":"Romford",
    "sg:classifiers":[
        {
            "category":"Farming",
            "subcategory":"Aquatic Farm",
            "type":"Manufacturing & Wholesale Goods"
        }
    ],
    "sg:phone":"+44 20 8599 8282",
    "sg:postcode":"RM6 4YX",
    "sg:province":"Essex",
    "sg:tags":[
        "installers",
        "draughtproofing"
    ],
    "wof:name":"Draughtbusters Draughtproofing",
    "wof:placetype":"venue"
},
  "geometry": {"coordinates":[0.12277,51.575172],"type":"Point"}
}