{
  "type": "Feature",
  "properties": {
    "iso:country":"GB",
    "sg:address":"Po Box 7159",
    "sg:city":"Redditch",
    "sg:classifiers":[
        {
            "category":"Professional",
            "type":"Services"
        }
    ],
    "sg:phone":"+44 1527 585333",
    "sg:postcode":"B97 4ER",
    "sg:province":"Warwickshire",
    "sg:tags":[
        "repair",
        "tech",
        "maintenance"
    ],
    "wof:name":"X-Tant Ltd.",
    "wof:placetype":"venue"
},
  "geometry": {"coordinates":[-1.948039,52.301151],"type":"Point"}
}