{
  "type": "Feature",
  "properties": {
    "addr:full":"Granite House, 97-101 Cannon Street London Greater London EC4N 5AE",
    "addr:housenumber":"97-101",
    "addr:postcode":"ec4n 5ae",
    "addr:street":"Granite;Cannon Street",
    "iso:country":"GB",
    "sg:address":"Granite House, 97-101 Cannon Street",
    "sg:city":"London",
    "sg:classifiers":[
        {
            "category":"Banks & Credit Unions",
            "subcategory":"Bank",
            "type":"Services"
        }
    ],
    "sg:phone":"+44 20 7621 9876",
    "sg:postcode":"EC4N 5AE",
    "sg:province":"Greater London",
    "wof:name":"Habib Bank Ltd.",
    "wof:placetype":"venue"
},
  "geometry": {"coordinates":[-0.092659,51.51215],"type":"Point"}
}