{
  "type": "Feature",
  "properties": {
    "addr:full":"47 St Albans Road East Hatfield Hertfordshire AL10 0EJ",
    "addr:housenumber":"47",
    "addr:postcode":"al10 0ej",
    "addr:street":"St Albans Road East",
    "iso:country":"GB",
    "sg:address":"47 St Albans Road East",
    "sg:city":"Hatfield",
    "sg:classifiers":[
        {
            "category":"Communications",
            "type":"Services"
        }
    ],
    "sg:postcode":"AL10 0EJ",
    "sg:province":"Hertfordshire",
    "sg:tags":[
        "telecommunication"
    ],
    "wof:name":"Microline (U K) Ltd",
    "wof:placetype":"venue"
},
  "geometry": {"coordinates":[-0.2217999995,51.7644958496],"type":"Point"}
}