{
  "type": "Feature",
  "properties": {
    "addr:full":"12 Kings Lea Ossett West Yorkshire WF5 8RY",
    "addr:housenumber":"12",
    "addr:postcode":"wf5 8ry",
    "addr:street":"Kings Lea",
    "iso:country":"GB",
    "sg:address":"12 Kings Lea",
    "sg:city":"Ossett",
    "sg:classifiers":[
        {
            "category":"Building & Trades",
            "subcategory":"Construction",
            "type":"Services"
        }
    ],
    "sg:phone":"+44 1924 278603",
    "sg:postcode":"WF5 8RY",
    "sg:province":"West Yorkshire",
    "sg:tags":[
        "decorator",
        "painter"
    ],
    "wof:name":"A Andrews Painting & Decorating Services",
    "wof:placetype":"venue"
},
  "geometry": {"coordinates":[-1.589948,53.690582],"type":"Point"}
}