{
  "type": "Feature",
  "properties": {
    "addr:full":"227 Manchester Road Warrington Cheshire WA1 3RQ",
    "addr:housenumber":"227",
    "addr:postcode":"wa1 3rq",
    "addr:street":"Manchester Road",
    "iso:country":"GB",
    "sg:address":"227 Manchester Road",
    "sg:city":"Warrington",
    "sg:classifiers":[
        {
            "category":"Building & Trades",
            "subcategory":"Construction",
            "type":"Services"
        }
    ],
    "sg:postcode":"WA1 3RQ",
    "sg:province":"Cheshire",
    "sg:tags":[
        "joiner",
        "carpenter"
    ],
    "wof:name":"D J Anrews Joiner & Builder",
    "wof:placetype":"venue"
},
  "geometry": {"coordinates":[-2.5689549446,53.3962554932],"type":"Point"}
}