{
  "type": "Feature",
  "properties": {
    "iso:country":"GB",
    "sg:address":"6c Ullswater Rd",
    "sg:city":"Hartlepool",
    "sg:classifiers":[
        {
            "category":"Manufacturing",
            "subcategory":"Rubber & Plastics",
            "type":"Manufacturing & Wholesale Goods"
        }
    ],
    "sg:phone":"+44 1429 424801",
    "sg:postcode":"TS25 1UE",
    "sg:province":"Durham",
    "sg:tags":[
        "supplier",
        "stockist"
    ],
    "wof:name":"Advanced Polycarbonates Ltd",
    "wof:placetype":"venue"
},
  "geometry": {"coordinates":[-1.210454,54.676193],"type":"Point"}
}