{
  "type": "Feature",
  "properties": {
    "addr:full":"Hither House, Ipswich Road Ipswich Suffolk IP9 2QT",
    "addr:postcode":"ip9 2qt",
    "addr:street":"Ipswich Road",
    "iso:country":"GB",
    "sg:address":"Hither House, Ipswich Road",
    "sg:city":"Ipswich",
    "sg:classifiers":[
        {
            "category":"Food & Beverages",
            "subcategory":"Meat & Fish",
            "type":"Retail Goods"
        }
    ],
    "sg:phone":"+44 1473 328329",
    "sg:postcode":"IP9 2QT",
    "sg:province":"Suffolk",
    "sg:tags":[
        "butcher"
    ],
    "wof:name":"C J Arnold Family Butcher",
    "wof:placetype":"venue"
},
  "geometry": {"coordinates":[1.158276,51.991028],"type":"Point"}
}