{
  "type": "Feature",
  "properties": {
    "addr:full":"Unit 3, Sunset Brunell Rd, Totton Southampton Hampshire SO40 3WX",
    "addr:housenumber":"unit 3",
    "addr:postcode":"so40 3wx",
    "addr:street":"Sunset Brunell Rd",
    "iso:country":"GB",
    "sg:address":"Unit 3, Sunset Brunell Rd, Totton",
    "sg:city":"Southampton",
    "sg:classifiers":[
        {
            "category":"Autos & Motor Vehicles",
            "subcategory":"Boat Sales",
            "type":"Retail Goods"
        }
    ],
    "sg:phone":"+44 23 8066 0755",
    "sg:postcode":"SO40 3WX",
    "sg:province":"Hampshire",
    "sg:tags":[
        "repair",
        "builder"
    ],
    "wof:name":"Harris Pye Outfitting",
    "wof:placetype":"venue"
},
  "geometry": {"coordinates":[-1.491189,50.91991],"type":"Point"}
}