{
  "type": "Feature",
  "properties": {
    "addr:full":"Unit 5, Bay Works, Pevensey Bay Pevensey East Sussex BN24 6EG",
    "addr:housenumber":"unit 5",
    "addr:postcode":"bn24 6eg",
    "addr:street":"Bay Works Pevensey Bay",
    "iso:country":"GB",
    "sg:address":"Unit 5, Bay Works, Pevensey Bay",
    "sg:city":"Pevensey",
    "sg:classifiers":[
        {
            "category":"Building & Trades",
            "subcategory":"Electrical",
            "type":"Services"
        }
    ],
    "sg:phone":"+44 1323 767904",
    "sg:postcode":"BN24 6EG",
    "sg:province":"East Sussex",
    "sg:tags":[
        "lighting"
    ],
    "wof:name":"Assemlec",
    "wof:placetype":"venue"
},
  "geometry": {"coordinates":[0.3562349975,50.8140296936],"type":"Point"}
}