{
  "type": "Feature",
  "properties": {
    "addr:full":"Fort Royal House, 1 London Rd Worcester Worcestershire WR5 2DJ",
    "addr:housenumber":"1",
    "addr:postcode":"wr5 2dj",
    "addr:street":"London Rd",
    "iso:country":"GB",
    "sg:address":"Fort Royal House, 1 London Rd",
    "sg:city":"Worcester",
    "sg:classifiers":[
        {
            "category":"Sports & Exercise",
            "subcategory":"Playing Field",
            "type":"Entertainment"
        }
    ],
    "sg:phone":"+44 1905 769734",
    "sg:postcode":"WR5 2DJ",
    "sg:province":"Worcestershire",
    "sg:tags":[
        "sanitary",
        "hygiene",
        "appliance"
    ],
    "wof:name":"Simply Showers",
    "wof:placetype":"venue"
},
  "geometry": {"coordinates":[-2.215496,52.186577],"type":"Point"}
}