{
  "type": "Feature",
  "properties": {
    "iso:country":"GB",
    "sg:address":"266 Chester Rd North",
    "sg:city":"Kidderminster",
    "sg:classifiers":[
        {
            "category":"Shopping",
            "subcategory":"Department Store",
            "type":"Retail Goods"
        }
    ],
    "sg:postcode":"DY10 2RR",
    "sg:province":"Staffordshire",
    "wof:name":"Coley,Susan,",
    "wof:placetype":"venue"
},
  "geometry": {"coordinates":[-2.2342319489,52.3929290771],"type":"Point"}
}