{
  "type": "Feature",
  "properties": {
    "iso:country":"GB",
    "sg:address":"Unit 21 Coalville Road Works, Colville Road",
    "sg:city":"Lowestoft",
    "sg:classifiers":[
        {
            "category":"Organizations",
            "subcategory":"Labor Organization",
            "type":"Services"
        },
        {
            "category":"Wholesale",
            "subcategory":"Machinery & Supplies",
            "type":"Manufacturing & Wholesale Goods"
        },
        {
            "category":"Professional",
            "subcategory":"Business Services",
            "type":"Services"
        }
    ],
    "sg:phone":"+44 1502 508888",
    "sg:postcode":"NR33 9QS",
    "sg:province":"Suffolk",
    "sg:tags":[
        "control",
        "industrial",
        "-",
        "agent",
        "instrument",
        "export",
        "import"
    ],
    "wof:name":"Eagle Exports Ltd",
    "wof:placetype":"venue"
},
  "geometry": {"coordinates":[1.720248,52.469444],"type":"Point"}
}