{
  "type": "Feature",
  "properties": {
    "addr:full":"662-664 Holloway Road London Greater London N19 3NY",
    "addr:housenumber":"662-664",
    "addr:postcode":"n19 3ny",
    "addr:street":"Holloway Road",
    "iso:country":"GB",
    "sg:address":"662-664 Holloway Road",
    "sg:city":"London",
    "sg:classifiers":[
        {
            "category":"Insurance",
            "subcategory":"Insurance Agent",
            "type":"Services"
        },
        {
            "category":"Banks & Credit Unions",
            "subcategory":"Financial Services",
            "type":"Services"
        }
    ],
    "sg:phone":"+44 20 7272 0559",
    "sg:postcode":"N19 3NY",
    "sg:province":"Greater London",
    "sg:tags":[
        "adviser"
    ],
    "wof:name":"Archway Investment & Mortgage Centre",
    "wof:placetype":"venue"
},
  "geometry": {"coordinates":[-0.1292289943,51.5638389587],"type":"Point"}
}