{
  "type": "Feature",
  "properties": {
    "iso:country":"GB",
    "sg:address":"94 Winchester Road",
    "sg:city":"Basingstoke",
    "sg:classifiers":[
        {
            "category":"Health Services",
            "subcategory":"Dentist",
            "type":"Services"
        }
    ],
    "sg:phone":"+44 1256 329007",
    "sg:postcode":"RG21 8UJ",
    "sg:province":"Hampshire",
    "sg:tags":[
        "technician",
        "dental"
    ],
    "wof:name":"Devonshire Lodge Dental Laboratory",
    "wof:placetype":"venue"
},
  "geometry": {"coordinates":[-1.094962,51.259712],"type":"Point"}
}