{
  "type": "Feature",
  "properties": {
    "addr:full":"Little London House, North Kelsey Market Rasen Lincolnshire LN7 6JP",
    "addr:housenumber":"north",
    "addr:postcode":"ln7 6jp",
    "addr:street":"Kelsey Market",
    "iso:country":"GB",
    "sg:address":"Little London House, North Kelsey",
    "sg:city":"Market Rasen",
    "sg:classifiers":[
        {
            "category":"Professional",
            "subcategory":"Engineering",
            "type":"Services"
        }
    ],
    "sg:phone":"+44 1652 678116",
    "sg:postcode":"LN7 6JP",
    "sg:province":"Lincolnshire",
    "wof:name":"R.W.H East",
    "wof:placetype":"venue"
},
  "geometry": {"coordinates":[-0.31672,53.498398],"type":"Point"}
}