{
  "type": "Feature",
  "properties": {
    "addr:full":"22 Cannon Hill, Southgate London Greater London N14 6LY",
    "addr:housenumber":"22",
    "addr:postcode":"n14 6ly",
    "addr:street":"Cannon Hill",
    "iso:country":"GB",
    "sg:address":"22 Cannon Hill, Southgate",
    "sg:city":"London",
    "sg:classifiers":[
        {
            "category":"Organizations",
            "subcategory":"Membership Organization",
            "type":"Services"
        }
    ],
    "sg:postcode":"N14 6LY",
    "sg:province":"Greater London",
    "sg:tags":[
        "club"
    ],
    "wof:name":"St. James Management Co. Limited",
    "wof:placetype":"venue"
},
  "geometry": {"coordinates":[-0.122576,51.623577],"type":"Point"}
}