{
  "type": "Feature",
  "properties": {
    "addr:full":"Causeway Street Kidwelly Carmarthenshire SA17 4SL",
    "addr:postcode":"sa17 4sl",
    "addr:street":"Causeway Street",
    "iso:country":"GB",
    "sg:address":"Causeway Street",
    "sg:city":"Kidwelly",
    "sg:classifiers":[
        {
            "category":"Food & Beverages",
            "subcategory":"Bakery",
            "type":"Retail Goods"
        }
    ],
    "sg:phone":"+44 1554 890305",
    "sg:postcode":"SA17 4SL",
    "sg:province":"Carmarthenshire",
    "sg:tags":[
        "baker"
    ],
    "wof:name":"Stephens Bakehouse",
    "wof:placetype":"venue"
},
  "geometry": {"coordinates":[-4.307479,51.736488],"type":"Point"}
}