{
  "type": "Feature",
  "properties": {
    "addr:full":"Kirkstead Road, Cheadle Hulme Cheadle Cheshire SK8 7PZ",
    "addr:postcode":"sk8 7pz",
    "addr:street":"Kirkstead Road",
    "iso:country":"GB",
    "sg:address":"Kirkstead Road, Cheadle Hulme",
    "sg:city":"Cheadle",
    "sg:classifiers":[
        {
            "category":"Education",
            "subcategory":"School",
            "type":"Public Place"
        }
    ],
    "sg:phone":"+44 161 439 6961",
    "sg:postcode":"SK8 7PZ",
    "sg:province":"Cheshire",
    "sg:tags":[
        "local",
        "authority"
    ],
    "wof:name":"Hursthead Junior School",
    "wof:placetype":"venue"
},
  "geometry": {"coordinates":[-2.180884,53.361244],"type":"Point"}
}