{
  "type": "Feature",
  "properties": {
    "iso:country":"GB",
    "sg:address":"166 Newport Road",
    "sg:city":"Cardiff",
    "sg:classifiers":[
        {
            "category":"Professional",
            "subcategory":"Engineering",
            "type":"Services"
        }
    ],
    "sg:postcode":"CF24 1YQ",
    "sg:province":"Cardiff",
    "sg:tags":[
        "consulting",
        "engineer"
    ],
    "wof:name":"Gareth Tucker",
    "wof:placetype":"venue"
},
  "geometry": {"coordinates":[-3.156343,51.490742],"type":"Point"}
}