{
  "type": "Feature",
  "properties": {
    "iso:country":"GB",
    "sg:address":"25 Norfolk Square",
    "sg:city":"London",
    "sg:classifiers":[
        {
            "category":"Travel",
            "subcategory":"Hotels & Motels",
            "type":"Entertainment"
        }
    ],
    "sg:phone":"+44 20 7262 2417",
    "sg:postcode":"W2 1RX",
    "sg:province":"Greater London",
    "wof:name":"Chrysos Hotel",
    "wof:placetype":"venue"
},
  "geometry": {"coordinates":[-0.172737,51.515915],"type":"Point"}
}