{
  "type": "Feature",
  "properties": {
    "addr:full":"6 Peaslake Ct, Egmont Rd Sutton Surrey SM2 5JS",
    "addr:housenumber":"6",
    "addr:postcode":"sm2 5js",
    "addr:street":"Peaslake Ct Egmont Rd",
    "iso:country":"GB",
    "sg:address":"6 Peaslake Ct, Egmont Rd",
    "sg:city":"Sutton",
    "sg:classifiers":[
        {
            "category":"Building & Trades",
            "subcategory":"Construction",
            "type":"Services"
        }
    ],
    "sg:postcode":"SM2 5JS",
    "sg:province":"Surrey",
    "sg:tags":[
        "builder"
    ],
    "wof:name":"Young,N,",
    "wof:placetype":"venue"
},
  "geometry": {"coordinates":[-0.1861799955,51.3530807495],"type":"Point"}
}