{
  "type": "Feature",
  "properties": {
    "iso:country":"GB",
    "sg:address":"990 Thornton Road",
    "sg:city":"Bradford",
    "sg:classifiers":[
        {
            "category":"Utilities",
            "subcategory":"Fuel Oil & Lpg",
            "type":"Services"
        }
    ],
    "sg:phone":"+44 1274 41813",
    "sg:postcode":"BD8 0PB",
    "sg:province":"West Yorkshire",
    "sg:tags":[
        "coal",
        "smokeless"
    ],
    "wof:name":"James Crompton",
    "wof:placetype":"venue"
},
  "geometry": {"coordinates":[-1.8104690313,53.7950706482],"type":"Point"}
}