{
  "type": "Feature",
  "properties": {
    "iso:country":"GB",
    "sg:address":"Coed Mawr Hall, Mostyn Road",
    "sg:city":"Holywell",
    "sg:classifiers":[
        {
            "category":"Shopping",
            "type":"Retail Goods"
        }
    ],
    "sg:phone":"+44 1352 716255",
    "sg:postcode":"CH8 9DN",
    "sg:province":"Denbighshire",
    "sg:tags":[
        "part",
        "accessory"
    ],
    "wof:name":"Karen Waring & Glen Farvett",
    "wof:placetype":"venue"
},
  "geometry": {"coordinates":[-3.258082,53.312134],"type":"Point"}
}