{
  "type": "Feature",
  "properties": {
    "iso:country":"GB",
    "sg:address":"Canyards Hills Farm, Bolsterstone",
    "sg:city":"Sheffield",
    "sg:classifiers":[
        {
            "category":"Farming",
            "subcategory":"Livestock Farm",
            "type":"Manufacturing & Wholesale Goods"
        }
    ],
    "sg:postcode":"S36 4ZA",
    "sg:province":"South Yorkshire",
    "sg:tags":[
        "others"
    ],
    "wof:name":"E & M Wainwright",
    "wof:placetype":"venue"
},
  "geometry": {"coordinates":[-1.612325,53.451012],"type":"Point"}
}