{
  "type": "Feature",
  "properties": {
    "addr:full":"15 Shelsley Drive Birmingham West Midlands B13 9JU",
    "addr:housenumber":"15",
    "addr:postcode":"b13 9ju",
    "addr:street":"Shelsley Drive",
    "iso:country":"GB",
    "sg:address":"15 Shelsley Drive",
    "sg:city":"Birmingham",
    "sg:classifiers":[
        {
            "category":"Building & Trades",
            "subcategory":"Construction",
            "type":"Services"
        }
    ],
    "sg:phone":"+44 121 449 7327",
    "sg:postcode":"B13 9JU",
    "sg:province":"West Midlands",
    "sg:tags":[
        "builder"
    ],
    "wof:name":"McDermott Contractors",
    "wof:placetype":"venue"
},
  "geometry": {"coordinates":[-1.872559,52.440571],"type":"Point"}
}