{
  "type": "Feature",
  "properties": {
    "addr:full":"Great Plummers Farm, Peters Grn Luton Bedfordshire LU2 9PP",
    "addr:postcode":"lu2 9pp",
    "addr:street":"Peters Grn",
    "iso:country":"GB",
    "sg:address":"Great Plummers Farm, Peters Grn",
    "sg:city":"Luton",
    "sg:classifiers":[
        {
            "category":"Farming",
            "subcategory":"Livestock Farm",
            "type":"Manufacturing & Wholesale Goods"
        }
    ],
    "sg:phone":"+44 1438 832262",
    "sg:postcode":"LU2 9PP",
    "sg:province":"Bedfordshire",
    "sg:tags":[
        "others"
    ],
    "wof:name":"W J Abraham & Son",
    "wof:placetype":"venue"
},
  "geometry": {"coordinates":[-0.375695,51.877029],"type":"Point"}
}