{
  "type": "Feature",
  "properties": {
    "addr:full":"Unit 15b Raleigh Hall Industrial Estate, Eccleshall Stafford Staffordshire ST21 6JL",
    "addr:housenumber":"unit 15b raleigh hall",
    "addr:postcode":"st21 6jl",
    "addr:street":"Industrial Estate",
    "iso:country":"GB",
    "sg:address":"Unit 15b Raleigh Hall Industrial Estate, Eccleshall",
    "sg:city":"Stafford",
    "sg:classifiers":[
        {
            "category":"Building & Trades",
            "subcategory":"Electrical",
            "type":"Services"
        }
    ],
    "sg:phone":"+44 1785 851077",
    "sg:postcode":"ST21 6JL",
    "sg:province":"Staffordshire",
    "sg:tags":[
        "consultant",
        "lighting"
    ],
    "wof:name":"Parkersell (Lighting & Electrical) Services",
    "wof:placetype":"venue"
},
  "geometry": {"coordinates":[-2.246274,52.873497],"type":"Point"}
}