{
  "type": "Feature",
  "properties": {
    "addr:full":"27 Raleigh Close Eaton Socon St Neots Bedfordshire PE19 8NN",
    "addr:housenumber":"27",
    "addr:postcode":"pe19 8nn",
    "addr:street":"Raleigh Close;Socon",
    "iso:country":"GB",
    "sg:address":"27 Raleigh Close Eaton Socon",
    "sg:city":"St Neots",
    "sg:classifiers":[
        {
            "category":"Shopping",
            "subcategory":"Pets & Pet Supplies",
            "type":"Retail Goods"
        },
        {
            "category":"Recreation",
            "subcategory":"Go Karts",
            "type":"Entertainment"
        }
    ],
    "sg:phone":"+44 1480 393223",
    "sg:postcode":"PE19 8NN",
    "sg:province":"Bedfordshire",
    "sg:tags":[
        "shop",
        "karting"
    ],
    "wof:name":"MARK WIMBLETON",
    "wof:placetype":"venue"
},
  "geometry": {"coordinates":[-0.2968299985,52.2169418335],"type":"Point"}
}