{
  "type": "Feature",
  "properties": {
    "addr:full":"East Kingsway Business Centre, Mid Craigie Trading Estate, Mid Craigie Road Dundee Dundee City DD4 7RH",
    "addr:housenumber":"business centre",
    "addr:postcode":"dd4 7rh",
    "addr:street":"East Kingsway;Mid Craigie Trading Estate Mid Craigie Road",
    "iso:country":"GB",
    "sg:address":"East Kingsway Business Centre, Mid Craigie Trading Estate, Mid Craigie Road",
    "sg:city":"Dundee",
    "sg:classifiers":[
        {
            "category":"Real Estate",
            "subcategory":"Real Estate Agent",
            "type":"Services"
        }
    ],
    "sg:phone":"+44 1382 456783",
    "sg:postcode":"DD4 7RH",
    "sg:province":"Dundee City",
    "wof:name":"Keiller Estates (Water) Ltd.",
    "wof:placetype":"venue"
},
  "geometry": {"coordinates":[-2.93557,56.475498],"type":"Point"}
}