{
  "type": "Feature",
  "properties": {
    "iso:country":"GB",
    "sg:address":"4 Wetherby Gardens",
    "sg:city":"Earl's Court",
    "sg:classifiers":[
        {
            "category":"Education",
            "subcategory":"Special Training",
            "type":"Public Place"
        }
    ],
    "sg:phone":"+44 20 7373 3852",
    "sg:postcode":"SW5 0JN",
    "sg:province":"Greater London",
    "sg:tags":[
        "product",
        "centre"
    ],
    "wof:name":"St James's Secretarial College",
    "wof:placetype":"venue"
},
  "geometry": {"coordinates":[-0.1860789955,51.4916343689],"type":"Point"}
}