{
  "type": "Feature",
  "properties": {
    "iso:country":"GB",
    "sg:address":"Springfield Way",
    "sg:city":"Brackley",
    "sg:classifiers":[
        {
            "category":"Arena",
            "subcategory":"Stadium",
            "type":"Entertainment"
        },
        {
            "category":"Community Center",
            "type":"Public Place"
        }
    ],
    "sg:phone":"+44 1280 705584",
    "sg:postcode":"NN13 6JJ",
    "sg:province":"Buckinghamshire",
    "sg:tags":[
        "ground",
        "recreation",
        "sport",
        "leisure",
        "centre"
    ],
    "wof:name":"Brackley Recreation Centre Ltd",
    "wof:placetype":"venue"
},
  "geometry": {"coordinates":[-1.154487,52.036671],"type":"Point"}
}