{
  "type": "Feature",
  "properties": {
    "iso:country":"GB",
    "sg:address":"Burgoyne Rd, Thornhill",
    "sg:city":"Southampton",
    "sg:classifiers":[
        {
            "category":"Organizations",
            "subcategory":"Non-profit Organization",
            "type":"Services"
        }
    ],
    "sg:phone":"+44 23 8040 4048",
    "sg:postcode":"SO19 6PB",
    "sg:province":"Hampshire",
    "sg:tags":[
        "organisation",
        "voluntary",
        "charity"
    ],
    "wof:name":"Youth At Risk",
    "wof:placetype":"venue"
},
  "geometry": {"coordinates":[-1.330813,50.903042],"type":"Point"}
}