{
  "type": "Feature",
  "properties": {
    "addr:full":"22 Wulfric Square, Bretton Peterborough Cambridgeshire PE3 8RF",
    "addr:housenumber":"22",
    "addr:postcode":"pe3 8rf",
    "addr:street":"Wulfric Square Bretton",
    "iso:country":"GB",
    "sg:address":"22 Wulfric Square, Bretton",
    "sg:city":"Peterborough",
    "sg:classifiers":[
        {
            "category":"Organizations",
            "subcategory":"Non-profit Organization",
            "type":"Services"
        }
    ],
    "sg:phone":"+44 1733 266311",
    "sg:postcode":"PE3 8RF",
    "sg:province":"Cambridgeshire",
    "sg:tags":[
        "organisation",
        "voluntary",
        "charity"
    ],
    "wof:name":"Re-Store",
    "wof:placetype":"venue"
},
  "geometry": {"coordinates":[-0.26832,52.598873],"type":"Point"}
}