{
  "type": "Feature",
  "properties": {
    "addr:full":"Units 39-40 Great Western Road Martock Somerset TA12 6HB",
    "addr:housenumber":"units 39-40",
    "addr:postcode":"ta12 6hb",
    "addr:street":"Great Western Road",
    "iso:country":"GB",
    "sg:address":"Units 39-40 Great Western Road",
    "sg:city":"Martock",
    "sg:classifiers":[
        {
            "category":"Freight",
            "type":"Transportation"
        }
    ],
    "sg:phone":"+44 1935 826348",
    "sg:postcode":"TA12 6HB",
    "sg:province":"Somerset",
    "sg:tags":[
        "forwarders"
    ],
    "wof:name":"Alternative Transport Services",
    "wof:placetype":"venue"
},
  "geometry": {"coordinates":[-2.770669,50.967247],"type":"Point"}
}