{
  "type": "Feature",
  "properties": {
    "addr:full":"Lawrence House, Church Lane, Stoak Chester Cheshire CH2 4HP",
    "addr:postcode":"ch2 4hp",
    "addr:street":"Church Lane",
    "iso:country":"GB",
    "sg:address":"Lawrence House, Church Lane, Stoak",
    "sg:city":"Chester",
    "sg:classifiers":[
        {
            "category":"Professional",
            "subcategory":"Computer Services",
            "type":"Services"
        }
    ],
    "sg:postcode":"CH2 4HP",
    "sg:province":"Cheshire",
    "sg:tags":[
        "system",
        "software"
    ],
    "wof:name":"S D M Consultants Ltd.",
    "wof:placetype":"venue"
},
  "geometry": {"coordinates":[-2.901564,53.239594],"type":"Point"}
}