{
  "type": "Feature",
  "properties": {
    "iso:country":"GB",
    "sg:address":"1 Plumtree The Cottage, Wass Lane",
    "sg:city":"Louth",
    "sg:classifiers":[
        {
            "category":"Shopping",
            "subcategory":"Pharmacy",
            "type":"Retail Goods"
        }
    ],
    "sg:phone":"+44 1507 343091",
    "sg:postcode":"LN8 5NH",
    "sg:province":"Lincolnshire",
    "sg:tags":[
        "pharmaceutical"
    ],
    "wof:name":"Epiderm Ltd.",
    "wof:placetype":"venue"
},
  "geometry": {"coordinates":[-0.3273099959,53.3154792786],"type":"Point"}
}