{
  "type": "Feature",
  "properties": {
    "addr:full":"33 Kingsmead Road, Loudwater High Wycombe Buckinghamshire HP11 1HX",
    "addr:housenumber":"33",
    "addr:postcode":"hp11 1hx",
    "addr:street":"Kingsmead Road",
    "iso:country":"GB",
    "sg:address":"33 Kingsmead Road, Loudwater",
    "sg:city":"High Wycombe",
    "sg:classifiers":[
        {
            "category":"Professional",
            "subcategory":"Printing & Photocopies",
            "type":"Services"
        }
    ],
    "sg:phone":"+44 1494 462781",
    "sg:postcode":"HP11 1HX",
    "sg:province":"Buckinghamshire",
    "sg:tags":[
        "printer"
    ],
    "wof:name":"Print Innovations",
    "wof:placetype":"venue"
},
  "geometry": {"coordinates":[-0.7217059731,51.6168708801],"type":"Point"}
}