{
  "type": "Feature",
  "properties": {
    "addr:full":"Po Box 102 Farnham Hampshire GU10 3YS",
    "addr:housenumber":"po",
    "addr:postcode":"gu10 3ys",
    "addr:street":"Box 102",
    "iso:country":"GB",
    "sg:address":"Po Box 102",
    "sg:city":"Farnham",
    "sg:classifiers":[
        {
            "category":"Personal",
            "type":"Services"
        }
    ],
    "sg:postcode":"GU10 3YS",
    "sg:province":"Hampshire",
    "sg:tags":[
        "supplier",
        "perfume"
    ],
    "wof:name":"Embassy Promotions",
    "wof:placetype":"venue"
},
  "geometry": {"coordinates":[-0.7901390195,51.1859016418],"type":"Point"}
}