{
  "type": "Feature",
  "properties": {
    "iso:country":"GB",
    "sg:address":"4 Teal House, The Millstream, London Road",
    "sg:city":"High Wycombe",
    "sg:classifiers":[
        {
            "category":"Health Services",
            "subcategory":"Doctor",
            "type":"Services"
        }
    ],
    "sg:phone":"+44 1494 539939",
    "sg:postcode":"HP11 1AE",
    "sg:province":"Buckinghamshire",
    "sg:tags":[
        "practitioners"
    ],
    "wof:name":"W R Tingey",
    "wof:placetype":"venue"
},
  "geometry": {"coordinates":[-0.7382900119,51.6254615784],"type":"Point"}
}