{
  "type": "Feature",
  "properties": {
    "iso:country":"GB",
    "sg:address":"50 High Street",
    "sg:city":"Northwood",
    "sg:classifiers":[
        {
            "category":"Shopping",
            "subcategory":"Shoes",
            "type":"Retail Goods"
        }
    ],
    "sg:phone":"+44 1923 840050",
    "sg:postcode":"HA6 1BL",
    "sg:province":"Greater London",
    "sg:tags":[
        "shop"
    ],
    "wof:name":"Pullens",
    "wof:placetype":"venue"
},
  "geometry": {"coordinates":[-0.4162679911,51.6067466736],"type":"Point"}
}