{
  "type": "Feature",
  "properties": {
    "addr:full":"Salisbury Road, Pimperne Blandford Forum Dorset DT11 8TX",
    "addr:postcode":"dt11 8tx",
    "addr:street":"Salisbury Road",
    "iso:country":"GB",
    "sg:address":"Salisbury Road, Pimperne",
    "sg:city":"Blandford Forum",
    "sg:classifiers":[
        {
            "category":"Bars & Pubs",
            "type":"Food & Drink"
        },
        {
            "category":"Community Center",
            "subcategory":"Social",
            "type":"Public Place"
        }
    ],
    "sg:phone":"+44 1258 453115",
    "sg:postcode":"DT11 8TX",
    "sg:province":"Dorset",
    "sg:tags":[
        "pubs",
        "house",
        "inn",
        "activity"
    ],
    "wof:name":"Farquharson Arms",
    "wof:placetype":"venue"
},
  "geometry": {"coordinates":[-2.1345388889,50.8820304871],"type":"Point"}
}