{
  "type": "Feature",
  "properties": {
    "addr:full":"13 Pingle Drive Bicester Oxfordshire OX26 6WD",
    "addr:housenumber":"13",
    "addr:postcode":"ox26 6wd",
    "addr:street":"Pingle Drive",
    "iso:country":"GB",
    "sg:address":"13 Pingle Drive",
    "sg:city":"Bicester",
    "sg:classifiers":[
        {
            "category":"Shopping",
            "subcategory":"Luggage & Leather Goods",
            "type":"Retail Goods"
        }
    ],
    "sg:phone":"+44 1869 240444",
    "sg:postcode":"OX26 6WD",
    "sg:province":"Oxfordshire",
    "wof:name":"Equator Luggage",
    "wof:placetype":"venue"
},
  "geometry": {"coordinates":[-1.1563600302,51.893081665],"type":"Point"}
}