{
  "type": "Feature",
  "properties": {
    "iso:country":"GB",
    "sg:address":"Nelson Street",
    "sg:city":"Liverpool",
    "sg:classifiers":[
        {
            "category":"Community Center",
            "type":"Public Place"
        }
    ],
    "sg:phone":"+44 151 709 7909",
    "sg:postcode":"L1 5DW",
    "sg:province":"Merseyside",
    "sg:tags":[
        "centre"
    ],
    "wof:name":"St Jame's Health & Community Centre",
    "wof:placetype":"venue"
},
  "geometry": {"coordinates":[-2.9779639244,53.3988647461],"type":"Point"}
}