{
  "type": "Feature",
  "properties": {
    "iso:country":"GB",
    "sg:address":"9a Chester Road",
    "sg:city":"Newquay",
    "sg:classifiers":[
        {
            "category":"Food & Beverages",
            "subcategory":"Meat & Fish",
            "type":"Retail Goods"
        }
    ],
    "sg:phone":"+44 1637 873571",
    "sg:postcode":"TR7 2RT",
    "sg:province":"Cornwall",
    "sg:tags":[
        "butcher"
    ],
    "wof:name":"J H & R Veall",
    "wof:placetype":"venue"
},
  "geometry": {"coordinates":[-5.064738,50.417233],"type":"Point"}
}