{
  "type": "Feature",
  "properties": {
    "addr:full":"Ferrymount Home, North Street Ferryhill Durham DL17 8HX",
    "addr:postcode":"dl17 8hx",
    "addr:street":"North Street",
    "iso:country":"GB",
    "sg:address":"Ferrymount Home, North Street",
    "sg:city":"Ferryhill",
    "sg:classifiers":[
        {
            "category":"Health Services",
            "subcategory":"Nursing And Care Facility",
            "type":"Services"
        },
        {
            "category":"Government",
            "subcategory":"Office",
            "type":"Public Place"
        }
    ],
    "sg:phone":"+44 1740 651667",
    "sg:postcode":"DL17 8HX",
    "sg:province":"Durham",
    "sg:tags":[
        "residential",
        "local"
    ],
    "wof:name":"DURHAM COUNTY COUNCIL",
    "wof:placetype":"venue"
},
  "geometry": {"coordinates":[-1.557652,54.688812],"type":"Point"}
}