{
  "type": "Feature",
  "properties": {
    "addr:full":"32 Somerville Close, Waddington Lincoln Lincolnshire LN5 9QR",
    "addr:housenumber":"32",
    "addr:postcode":"ln5 9qr",
    "addr:street":"Somerville Close",
    "iso:country":"GB",
    "sg:address":"32 Somerville Close, Waddington",
    "sg:city":"Lincoln",
    "sg:classifiers":[
        {
            "category":"Manufacturing",
            "subcategory":"Wood Products",
            "type":"Manufacturing & Wholesale Goods"
        },
        {
            "category":"Manufacturing",
            "subcategory":"Jewelry",
            "type":"Manufacturing & Wholesale Goods"
        },
        {
            "category":"Building & Trades",
            "subcategory":"Construction",
            "type":"Services"
        }
    ],
    "sg:phone":"+44 1522 751988",
    "sg:postcode":"LN5 9QR",
    "sg:province":"Lincolnshire",
    "sg:tags":[
        "joinery",
        "manufacturer",
        "jewellery",
        "repair"
    ],
    "wof:name":"Clarman Joinery Ltd",
    "wof:placetype":"venue"
},
  "geometry": {"coordinates":[-0.5525839925,53.1743736267],"type":"Point"}
}