{
  "type": "Feature",
  "properties": {
    "iso:country":"GB",
    "sg:address":"315 Horn La",
    "sg:city":"Acton",
    "sg:classifiers":[
        {
            "category":"Restaurant",
            "type":"Food & Drink"
        }
    ],
    "sg:phone":"+44 20 8992 6478",
    "sg:postcode":"W3 0BU",
    "sg:province":"Greater London",
    "wof:name":"Lee's Garden",
    "wof:placetype":"venue"
},
  "geometry": {"coordinates":[-0.26597,51.51889],"type":"Point"}
}