{
  "type": "Feature",
  "properties": {
    "iso:country":"GB",
    "sg:address":"1 New Road, Southbourne",
    "sg:city":"Emsworth",
    "sg:classifiers":[
        {
            "category":"Personal",
            "subcategory":"Beauty Salon",
            "type":"Services"
        }
    ],
    "sg:phone":"+44 1243 377541",
    "sg:postcode":"PO10 8JX",
    "sg:province":"Hampshire",
    "sg:tags":[
        "lady",
        "hairdresser"
    ],
    "wof:name":"J C's",
    "wof:placetype":"venue"
},
  "geometry": {"coordinates":[-0.905416,50.845158],"type":"Point"}
}