{
  "type": "Feature",
  "properties": {
    "addr:full":"Unit 17/18, Victoria Industrial Estate Leigh Lancashire WN7 5SE",
    "addr:housenumber":"unit 17 / 18",
    "addr:postcode":"wn7 5se",
    "addr:street":"Victoria Industrial Estate",
    "iso:country":"GB",
    "sg:address":"Unit 17/18, Victoria Industrial Estate",
    "sg:city":"Leigh",
    "sg:classifiers":[
        {
            "category":"Food & Beverages",
            "subcategory":"Specialty",
            "type":"Retail Goods"
        }
    ],
    "sg:phone":"+44 1942 269677",
    "sg:postcode":"WN7 5SE",
    "sg:province":"Lancashire",
    "sg:tags":[
        "product",
        "health"
    ],
    "wof:name":"Powerbeck Sports Ltd.",
    "wof:placetype":"venue"
},
  "geometry": {"coordinates":[-2.5248599052,53.5044517517],"type":"Point"}
}