{
  "type": "Feature",
  "properties": {
    "addr:full":"181 Ditchling Road Brighton East Sussex BN1 6JB",
    "addr:housenumber":"181",
    "addr:postcode":"bn1 6jb",
    "addr:street":"Ditchling Road",
    "iso:country":"GB",
    "sg:address":"181 Ditchling Road",
    "sg:city":"Brighton",
    "sg:classifiers":[
        {
            "category":"Farming",
            "subcategory":"Nursery",
            "type":"Manufacturing & Wholesale Goods"
        }
    ],
    "sg:postcode":"BN1 6JB",
    "sg:province":"East Sussex",
    "sg:tags":[
        "creche"
    ],
    "wof:name":"Hopscotch",
    "wof:placetype":"venue"
},
  "geometry": {"coordinates":[-0.134112,50.840481],"type":"Point"}
}