{
  "type": "Feature",
  "properties": {
    "addr:full":"22 Wapping Lane Whitechapel Devon E1W2RL",
    "addr:housenumber":"22",
    "addr:postcode":"e1w2rl",
    "addr:street":"Wapping Lane",
    "iso:country":"GB",
    "sg:address":"22 Wapping Lane",
    "sg:city":"Whitechapel",
    "sg:classifiers":[
        {
            "category":"Health Services",
            "subcategory":"Doctor",
            "type":"Services"
        }
    ],
    "sg:phone":"+44 20 7481 9376",
    "sg:postcode":"E1W2RL",
    "sg:province":"Devon",
    "sg:tags":[
        "practitioners"
    ],
    "wof:name":"Drs Stern Thaya Mooney Leigh & Wright",
    "wof:placetype":"venue"
},
  "geometry": {"coordinates":[-0.058499,51.505749],"type":"Point"}
}