{
  "type": "Feature",
  "properties": {
    "iso:country":"GB",
    "sg:address":"2236 London Road",
    "sg:city":"Glasgow",
    "sg:classifiers":[
        {
            "category":"Building & Trades",
            "subcategory":"Construction",
            "type":"Services"
        }
    ],
    "sg:postcode":"G32 8YF",
    "sg:province":"Glasgow City",
    "sg:tags":[
        "roofing"
    ],
    "wof:name":"Thomas Gaughan",
    "wof:placetype":"venue"
},
  "geometry": {"coordinates":[-4.1555199623,55.8367424011],"type":"Point"}
}