{
  "type": "Feature",
  "properties": {
    "addr:full":"Unit F, Western Trading Est, Trading Estate Rd Willesden Greater London NW10 7LU",
    "addr:postcode":"nw10 7lu",
    "addr:street":"Estate Rd",
    "iso:country":"GB",
    "sg:address":"Unit F, Western Trading Est, Trading Estate Rd",
    "sg:city":"Willesden",
    "sg:classifiers":[
        {
            "category":"Professional",
            "subcategory":"Computer Services",
            "type":"Services"
        }
    ],
    "sg:phone":"+44 20 8838 2691",
    "sg:postcode":"NW10 7LU",
    "sg:province":"Greater London",
    "sg:tags":[
        "system",
        "software"
    ],
    "wof:name":"Mint Computers",
    "wof:placetype":"venue"
},
  "geometry": {"coordinates":[-0.26856,51.526428],"type":"Point"}
}