{
  "type": "Feature",
  "properties": {
    "addr:full":"Langurroc Road, Crantock Newquay Cornwall TR8 5RB",
    "addr:postcode":"tr8 5rb",
    "addr:street":"Langurroc Road",
    "iso:country":"GB",
    "sg:address":"Langurroc Road, Crantock",
    "sg:city":"Newquay",
    "sg:classifiers":[
        {
            "category":"Bars & Pubs",
            "type":"Food & Drink"
        }
    ],
    "sg:phone":"+44 1637 830243",
    "sg:postcode":"TR8 5RB",
    "sg:province":"Cornwall",
    "sg:tags":[
        "pubs",
        "house",
        "inn",
        "public",
        "activity"
    ],
    "wof:name":"Old Albion Inn",
    "wof:placetype":"venue"
},
  "geometry": {"coordinates":[-5.1105189323,50.4002990723],"type":"Point"}
}