{
  "type": "Feature",
  "properties": {
    "iso:country":"GB",
    "sg:address":"9 Montrose Way",
    "sg:city":"Dunblane",
    "sg:classifiers":[
        {
            "category":"Professional",
            "subcategory":"Management & Consulting",
            "type":"Services"
        }
    ],
    "sg:postcode":"FK15 9JL",
    "sg:province":"Perth and Kinross",
    "sg:tags":[
        "consultant",
        "transport"
    ],
    "wof:name":"Alan Howes Associates",
    "wof:placetype":"venue"
},
  "geometry": {"coordinates":[-3.9796080589,56.1922798157],"type":"Point"}
}