{
  "type": "Feature",
  "properties": {
    "iso:country":"GB",
    "sg:address":"123 High St",
    "sg:city":"Broadstairs",
    "sg:classifiers":[
        {
            "category":"Real Estate",
            "subcategory":"Real Estate Agent",
            "type":"Services"
        }
    ],
    "sg:phone":"+44 1843 866606",
    "sg:postcode":"CT10 1NQ",
    "sg:province":"Kent",
    "wof:name":"Belmonte Commercial & Bowmanor Property",
    "wof:placetype":"venue"
},
  "geometry": {"coordinates":[1.435001,51.359829],"type":"Point"}
}