{
  "type": "Feature",
  "properties": {
    "addr:full":"East Chinnock Yeovil Dorset BA22 9DR",
    "addr:postcode":"ba22 9dr",
    "addr:street":"East Chinnock",
    "iso:country":"GB",
    "sg:address":"East Chinnock",
    "sg:city":"Yeovil",
    "sg:classifiers":[
        {
            "category":"Travel",
            "subcategory":"Hotels & Motels",
            "type":"Entertainment"
        }
    ],
    "sg:phone":"+44 1935 862237",
    "sg:postcode":"BA22 9DR",
    "sg:province":"Dorset",
    "sg:tags":[
        "house",
        "guest"
    ],
    "wof:name":"The Gables Guest House",
    "wof:placetype":"venue"
},
  "geometry": {"coordinates":[-2.71594,50.91597],"type":"Point"}
}