{
  "type": "Feature",
  "properties": {
    "iso:country":"GB",
    "sg:address":"137 Stafford Road",
    "sg:city":"Wallington",
    "sg:classifiers":[
        {
            "category":"Shopping",
            "subcategory":"Clothing, Apparel, & Fashions",
            "type":"Retail Goods"
        }
    ],
    "sg:phone":"+44 20 8669 2530",
    "sg:postcode":"SM6 9BN",
    "sg:province":"Surrey",
    "sg:tags":[
        "dresswear"
    ],
    "wof:name":"Second Connection",
    "wof:placetype":"venue"
},
  "geometry": {"coordinates":[-0.1406950057,51.3591308594],"type":"Point"}
}