{
  "type": "Feature",
  "properties": {
    "iso:country":"GB",
    "sg:address":"Off Commercial Street, Aberbargoed",
    "sg:city":"Bargoed",
    "sg:classifiers":[
        {
            "category":"Organizations",
            "subcategory":"Membership Organization",
            "type":"Services"
        }
    ],
    "sg:phone":"+44 1443 830218",
    "sg:postcode":"CF81 9EX",
    "sg:province":"Caerphilly",
    "sg:tags":[
        "club"
    ],
    "wof:name":"Arthur Balfour Conservative Working Men's Club Ltd.",
    "wof:placetype":"venue"
},
  "geometry": {"coordinates":[-3.221308,51.690517],"type":"Point"}
}