{
  "type": "Feature",
  "properties": {
    "addr:full":"Church Lane, Govilon Abergavenny Herefordshire NP7 9RP",
    "addr:postcode":"np7 9rp",
    "addr:street":"Church Lane",
    "iso:country":"GB",
    "sg:address":"Church Lane, Govilon",
    "sg:city":"Abergavenny",
    "sg:classifiers":[
        {
            "category":"Bars & Pubs",
            "type":"Food & Drink"
        },
        {
            "category":"Community Center",
            "subcategory":"Social",
            "type":"Public Place"
        }
    ],
    "sg:phone":"+44 1873 830177",
    "sg:postcode":"NP7 9RP",
    "sg:province":"Herefordshire",
    "sg:tags":[
        "pubs",
        "house",
        "inn",
        "activity"
    ],
    "wof:name":"The Bridgend Inn",
    "wof:placetype":"venue"
},
  "geometry": {"coordinates":[-3.0616090298,51.8191337585],"type":"Point"}
}