{
  "type": "Feature",
  "properties": {
    "addr:full":"Unit 16c, Samson House, Arterial Rd, Laindon Basildon Essex SS15 6DR",
    "addr:housenumber":"unit 16c samson house",
    "addr:postcode":"ss15 6dr",
    "addr:street":"Arterial Rd",
    "iso:country":"GB",
    "sg:address":"Unit 16c, Samson House, Arterial Rd, Laindon",
    "sg:city":"Basildon",
    "sg:classifiers":[
        {
            "category":"Building & Trades",
            "subcategory":"Cleaning & Sanitation",
            "type":"Services"
        }
    ],
    "sg:phone":"+44 1268 541668",
    "sg:postcode":"SS15 6DR",
    "sg:province":"Essex",
    "sg:tags":[
        "polishing",
        "floor"
    ],
    "wof:name":"Goldarrow Impex UK Ltd",
    "wof:placetype":"venue"
},
  "geometry": {"coordinates":[0.4103490114,51.5749893188],"type":"Point"}
}