{
  "type": "Feature",
  "properties": {
    "addr:full":"10 Watermill Croft, North Stainley Ripon North Yorkshire HG4 3LB",
    "addr:housenumber":"10",
    "addr:postcode":"hg4 3lb",
    "addr:street":"Watermill Croft North Stainley",
    "iso:country":"GB",
    "sg:address":"10 Watermill Croft, North Stainley",
    "sg:city":"Ripon",
    "sg:classifiers":[
        {
            "category":"Professional",
            "subcategory":"Computer Services",
            "type":"Services"
        }
    ],
    "sg:phone":"+44 1765 635528",
    "sg:postcode":"HG4 3LB",
    "sg:province":"North Yorkshire",
    "sg:tags":[
        "system",
        "software"
    ],
    "wof:name":"Tuley Associates Ltd.",
    "wof:placetype":"venue"
},
  "geometry": {"coordinates":[-1.561995,54.186558],"type":"Point"}
}