{
  "type": "Feature",
  "properties": {
    "iso:country":"GB",
    "sg:address":"Hampton House, Summerheath Road",
    "sg:city":"Hailsham",
    "sg:classifiers":[
        {
            "category":"Government",
            "subcategory":"Office",
            "type":"Public Place"
        }
    ],
    "sg:phone":"+44 1323 843168",
    "sg:postcode":"BN27 3DP",
    "sg:province":"East Sussex",
    "sg:tags":[
        "central"
    ],
    "wof:name":"Wealden District Council",
    "wof:placetype":"venue"
},
  "geometry": {"coordinates":[0.25411,50.866192],"type":"Point"}
}