{
  "type": "Feature",
  "properties": {
    "addr:full":"12 Holly Road Liverpool Merseyside L7 0LH",
    "addr:housenumber":"12",
    "addr:postcode":"l7 0lh",
    "addr:street":"Holly Road",
    "iso:country":"GB",
    "sg:address":"12 Holly Road",
    "sg:city":"Liverpool",
    "sg:classifiers":[
        {
            "category":"Social Services",
            "subcategory":"Retirement Home",
            "type":"Services"
        }
    ],
    "sg:phone":"+44 151 263 2412",
    "sg:postcode":"L7 0LH",
    "sg:province":"Merseyside",
    "sg:tags":[
        "residential",
        "care"
    ],
    "wof:name":"Holly Road Residential Home",
    "wof:placetype":"venue"
},
  "geometry": {"coordinates":[-2.9392719269,53.4102745056],"type":"Point"}
}