{
  "type": "Feature",
  "properties": {
    "addr:full":"84 Alexandra Rd Farnborough Hampshire GU14 6DD",
    "addr:housenumber":"84",
    "addr:postcode":"gu14 6dd",
    "addr:street":"Alexandra Rd",
    "iso:country":"GB",
    "sg:address":"84 Alexandra Rd",
    "sg:city":"Farnborough",
    "sg:classifiers":[
        {
            "category":"Home & Garden",
            "subcategory":"Household Appliances",
            "type":"Retail Goods"
        }
    ],
    "sg:phone":"+44 1252 545709",
    "sg:postcode":"GU14 6DD",
    "sg:province":"Hampshire",
    "sg:tags":[
        "electrical",
        "domestic"
    ],
    "wof:name":"Capel Control",
    "wof:placetype":"venue"
},
  "geometry": {"coordinates":[-0.7502869964,51.2776870728],"type":"Point"}
}