{
  "type": "Feature",
  "properties": {
    "addr:full":"27 Albion Industrial Estate, Endermere Road Coventry Warwickshire CV6 5PY",
    "addr:housenumber":"27",
    "addr:postcode":"cv6 5py",
    "addr:street":"Albion Industrial;Endermere Road",
    "iso:country":"GB",
    "sg:address":"27 Albion Industrial Estate, Endermere Road",
    "sg:city":"Coventry",
    "sg:classifiers":[
        {
            "category":"Manufacturing",
            "subcategory":"Tools & Machinery",
            "type":"Manufacturing & Wholesale Goods"
        }
    ],
    "sg:phone":"+44 24 7666 4614",
    "sg:postcode":"CV6 5PY",
    "sg:province":"Warwickshire",
    "wof:name":"Cromwell Tools (Coventry)",
    "wof:placetype":"venue"
},
  "geometry": {"coordinates":[-1.5052989721,52.4309005737],"type":"Point"}
}