{
  "type": "Feature",
  "properties": {
    "iso:country":"GB",
    "sg:address":"9 Farleigh Wick",
    "sg:city":"Bradford-on-avon",
    "sg:classifiers":[
        {
            "category":"Bars & Pubs",
            "type":"Food & Drink"
        },
        {
            "category":"Community Center",
            "subcategory":"Social",
            "type":"Public Place"
        }
    ],
    "sg:phone":"+44 1225 863122",
    "sg:postcode":"BA15 2PU",
    "sg:province":"Wiltshire",
    "sg:tags":[
        "pubs",
        "house",
        "inn",
        "activity"
    ],
    "wof:name":"The Fox & Hounds",
    "wof:placetype":"venue"
},
  "geometry": {"coordinates":[-2.288904,51.395596],"type":"Point"}
}