{
  "type": "Feature",
  "properties": {
    "iso:country":"GB",
    "sg:address":"41 Elm Road",
    "sg:city":"Kettering",
    "sg:classifiers":[
        {
            "category":"Professional",
            "subcategory":"Computer Services",
            "type":"Services"
        }
    ],
    "sg:phone":"+44 1536 310246",
    "sg:postcode":"NN15 7AY",
    "sg:province":"Northamptonshire",
    "sg:tags":[
        "development",
        "system",
        "software"
    ],
    "sg:website":"http://www.pr-soft.com",
    "wof:name":"P R Soft Ltd.",
    "wof:placetype":"venue"
},
  "geometry": {"coordinates":[-0.712778,52.395439],"type":"Point"}
}