{
  "type": "Feature",
  "properties": {
    "addr:full":"14 Bensted Clo Maidstone Kent ME15 0SD",
    "addr:housenumber":"14",
    "addr:postcode":"me15 0sd",
    "addr:street":"Bensted Clo",
    "iso:country":"GB",
    "sg:address":"14 Bensted Clo",
    "sg:city":"Maidstone",
    "sg:classifiers":[
        {
            "category":"Professional",
            "type":"Services"
        }
    ],
    "sg:phone":"+44 1622 820524",
    "sg:postcode":"ME15 0SD",
    "sg:province":"Kent",
    "sg:tags":[
        "caterer"
    ],
    "wof:name":"Secret Service Catering",
    "wof:placetype":"venue"
},
  "geometry": {"coordinates":[0.460471,51.219036],"type":"Point"}
}