{
  "type": "Feature",
  "properties": {
    "iso:country":"GB",
    "sg:address":"17 Dechmont Road",
    "sg:city":"Edinburgh",
    "sg:classifiers":[
        {
            "category":"Building & Trades",
            "subcategory":"Construction",
            "type":"Services"
        }
    ],
    "sg:postcode":"EH12 8JF",
    "sg:province":"City of Edinburgh",
    "sg:tags":[
        "decorator",
        "painter"
    ],
    "wof:name":"Allen Decorating Brian",
    "wof:placetype":"venue"
},
  "geometry": {"coordinates":[-3.3073539734,55.9428787231],"type":"Point"}
}