{
  "type": "Feature",
  "properties": {
    "addr:full":"134 Leeds Rd Shipley West Yorkshire BD18 1BX",
    "addr:housenumber":"134",
    "addr:postcode":"bd18 1bx",
    "addr:street":"Leeds Rd",
    "iso:country":"GB",
    "sg:address":"134 Leeds Rd",
    "sg:city":"Shipley",
    "sg:classifiers":[
        {
            "category":"Bars & Pubs",
            "type":"Food & Drink"
        }
    ],
    "sg:phone":"+44 1274 595722",
    "sg:postcode":"BD18 1BX",
    "sg:province":"West Yorkshire",
    "sg:tags":[
        "pubs",
        "inn"
    ],
    "wof:name":"The Blue Bell Hotel",
    "wof:placetype":"venue"
},
  "geometry": {"coordinates":[-1.7678300142,53.8342132568],"type":"Point"}
}