{
  "type": "Feature",
  "properties": {
    "addr:full":"62 Wallasey Rd Wallasey Merseyside L44 2AE",
    "addr:housenumber":"62",
    "addr:postcode":"l44 2ae",
    "addr:street":"Wallasey Rd",
    "iso:country":"GB",
    "sg:address":"62 Wallasey Rd",
    "sg:city":"Wallasey",
    "sg:classifiers":[
        {
            "category":"Sports & Exercise",
            "subcategory":"Sports Center",
            "type":"Entertainment"
        }
    ],
    "sg:phone":"+44 151 639 4304",
    "sg:postcode":"L44 2AE",
    "sg:province":"Merseyside",
    "sg:tags":[
        "shop",
        "good"
    ],
    "wof:name":"Blacks",
    "wof:placetype":"venue"
},
  "geometry": {"coordinates":[-3.0478689671,53.4194488525],"type":"Point"}
}