{
  "type": "Feature",
  "properties": {
    "iso:country":"GB",
    "sg:address":"177 High Street",
    "sg:city":"Hornchurch",
    "sg:classifiers":[
        {
            "category":"Fast Food",
            "type":"Food & Drink"
        }
    ],
    "sg:postcode":"RM11 3XS",
    "sg:province":"Essex",
    "sg:tags":[
        "away",
        "take"
    ],
    "wof:name":"The Sandwich Shop",
    "wof:placetype":"venue"
},
  "geometry": {"coordinates":[0.2214670032,51.5616455078],"type":"Point"}
}