{
  "type": "Feature",
  "properties": {
    "addr:full":"Westend Mills, Watergate Road Dewsbury West Yorkshire WF12 9QB",
    "addr:postcode":"wf12 9qb",
    "addr:street":"Westend;Watergate Road",
    "iso:country":"GB",
    "sg:address":"Westend Mills, Watergate Road",
    "sg:city":"Dewsbury",
    "sg:classifiers":[
        {
            "category":"Wholesale",
            "subcategory":"Auto Parts",
            "type":"Manufacturing & Wholesale Goods"
        },
        {
            "category":"Manufacturing",
            "subcategory":"Paper Products",
            "type":"Manufacturing & Wholesale Goods"
        }
    ],
    "sg:phone":"+44 1924 465958",
    "sg:postcode":"WF12 9QB",
    "sg:province":"West Yorkshire",
    "sg:tags":[
        "merchant",
        "car",
        "waste",
        "breaker"
    ],
    "wof:name":"Blackburns Waste Disposal Ltd",
    "wof:placetype":"venue"
},
  "geometry": {"coordinates":[-1.63839,53.687908],"type":"Point"}
}