{
  "type": "Feature",
  "properties": {
    "addr:full":"Carreg Y Big, Selattyn Oswestry Shropshire SY10 7HX",
    "addr:postcode":"sy10 7hx",
    "iso:country":"GB",
    "sg:address":"Carreg Y Big, Selattyn",
    "sg:city":"Oswestry",
    "sg:classifiers":[
        {
            "category":"Sports & Exercise",
            "subcategory":"Stables",
            "type":"Entertainment"
        }
    ],
    "sg:phone":"+44 1691 654754",
    "sg:postcode":"SY10 7HX",
    "sg:province":"Shropshire",
    "sg:tags":[
        "education",
        "equestrian"
    ],
    "wof:name":"Oswestry Equestrian Centre",
    "wof:placetype":"venue"
},
  "geometry": {"coordinates":[-3.0903339386,52.8983345032],"type":"Point"}
}