{
  "type": "Feature",
  "properties": {
    "addr:full":"86 London Rd, Blackwater Camberley Hampshire GU17 0AE",
    "addr:housenumber":"86",
    "addr:postcode":"gu17 0ae",
    "addr:street":"London Rd",
    "iso:country":"GB",
    "sg:address":"86 London Rd, Blackwater",
    "sg:city":"Camberley",
    "sg:classifiers":[
        {
            "category":"Autos & Motor Vehicles",
            "subcategory":"Fuel & Gas Station",
            "type":"Retail Goods"
        }
    ],
    "sg:phone":"+44 1276 606910",
    "sg:postcode":"GU17 0AE",
    "sg:province":"Hampshire",
    "sg:tags":[
        "petrol",
        "filling"
    ],
    "wof:name":"Total Convenience Stores",
    "wof:placetype":"venue"
},
  "geometry": {"coordinates":[-0.7813590169,51.3305091858],"type":"Point"}
}