{
  "type": "Feature",
  "properties": {
    "addr:full":"8 Dunster Gardens London Greater London NW6 7NH",
    "addr:housenumber":"8",
    "addr:postcode":"nw6 7nh",
    "addr:street":"Dunster Gardens",
    "iso:country":"GB",
    "sg:address":"8 Dunster Gardens",
    "sg:city":"London",
    "sg:classifiers":[
        {
            "category":"Arts & Performance",
            "subcategory":"Theater",
            "type":"Entertainment"
        }
    ],
    "sg:postcode":"NW6 7NH",
    "sg:province":"Greater London",
    "sg:tags":[
        "theatrical",
        "agency"
    ],
    "wof:name":"Daily Domestics Cleaning Agency",
    "wof:placetype":"venue"
},
  "geometry": {"coordinates":[-0.200764,51.542919],"type":"Point"}
}