{
  "type": "Feature",
  "properties": {
    "addr:full":"Helland Barton, Ladock Truro Cornwall TR2 4QE",
    "addr:housenumber":"ladock",
    "addr:postcode":"tr2 4qe",
    "addr:street":"Helland",
    "iso:country":"GB",
    "sg:address":"Helland Barton, Ladock",
    "sg:city":"Truro",
    "sg:classifiers":[
        {
            "category":"Home & Garden",
            "subcategory":"Garden Supply",
            "type":"Retail Goods"
        },
        {
            "category":"Farming",
            "subcategory":"Farm",
            "type":"Manufacturing & Wholesale Goods"
        }
    ],
    "sg:postcode":"TR2 4QE",
    "sg:province":"Cornwall",
    "sg:tags":[
        "mixed",
        "bulb",
        "crop",
        "grower"
    ],
    "wof:name":"R B & J M Harvey & Sons",
    "wof:placetype":"venue"
},
  "geometry": {"coordinates":[-4.9572138786,50.3191604614],"type":"Point"}
}