{
  "type": "Feature",
  "properties": {
    "addr:full":"16 Cader Road London Greater London SW18 2RN",
    "addr:housenumber":"16",
    "addr:postcode":"sw18 2rn",
    "addr:street":"Cader Road",
    "iso:country":"GB",
    "sg:address":"16 Cader Road",
    "sg:city":"London",
    "sg:classifiers":[
        {
            "category":"Professional",
            "subcategory":"Art Services",
            "type":"Services"
        }
    ],
    "sg:phone":"+44 20 8870 5105",
    "sg:postcode":"SW18 2RN",
    "sg:province":"Greater London",
    "sg:tags":[
        "consultant",
        "design"
    ],
    "wof:name":"Grease Lightening",
    "wof:placetype":"venue"
},
  "geometry": {"coordinates":[-0.1845899969,51.4518966675],"type":"Point"}
}