{
  "type": "Feature",
  "properties": {
    "addr:full":"18 Coquet Street, Amble Morpeth Northumberland NE65 0DJ",
    "addr:housenumber":"18",
    "addr:postcode":"ne65 0dj",
    "addr:street":"Coquet Street",
    "iso:country":"GB",
    "sg:address":"18 Coquet Street, Amble",
    "sg:city":"Morpeth",
    "sg:classifiers":[
        {
            "category":"Recreation",
            "subcategory":"Water Park",
            "type":"Entertainment"
        },
        {
            "category":"Sports & Exercise",
            "subcategory":"Sports Center",
            "type":"Entertainment"
        }
    ],
    "sg:phone":"+44 1665 710367",
    "sg:postcode":"NE65 0DJ",
    "sg:province":"Northumberland",
    "sg:tags":[
        "activity",
        "watersport"
    ],
    "wof:name":"Coquet Shorebase Trust",
    "wof:placetype":"venue"
},
  "geometry": {"coordinates":[-1.5871239901,55.3311882019],"type":"Point"}
}