{
  "type": "Feature",
  "properties": {
    "addr:full":"9 Tollerdown Road Weymouth Dorset DT4 0SQ",
    "addr:housenumber":"9",
    "addr:postcode":"dt4 0sq",
    "addr:street":"Tollerdown Road",
    "iso:country":"GB",
    "sg:address":"9 Tollerdown Road",
    "sg:city":"Weymouth",
    "sg:classifiers":[
        {
            "category":"Utilities",
            "subcategory":"Refuse",
            "type":"Services"
        }
    ],
    "sg:phone":"+44 1305 775230",
    "sg:postcode":"DT4 0SQ",
    "sg:province":"Dorset",
    "sg:tags":[
        "disposal",
        "waste"
    ],
    "wof:name":"Fastbone Ltd.",
    "wof:placetype":"venue"
},
  "geometry": {"coordinates":[-2.482640028,50.6081161499],"type":"Point"}
}