{
  "type": "Feature",
  "properties": {
    "addr:full":"17 Blind Lane, New Silksworth Sunderland Tyne and Wear SR3 1AT",
    "addr:housenumber":"17",
    "addr:postcode":"sr3 1at",
    "addr:street":"Blind Lane",
    "iso:country":"GB",
    "sg:address":"17 Blind Lane, New Silksworth",
    "sg:city":"Sunderland",
    "sg:classifiers":[
        {
            "category":"Shopping",
            "type":"Retail Goods"
        }
    ],
    "sg:postcode":"SR3 1AT",
    "sg:province":"Tyne and Wear",
    "sg:tags":[
        "part",
        "accessory"
    ],
    "wof:name":"Save & Drive",
    "wof:placetype":"venue"
},
  "geometry": {"coordinates":[-1.40116,54.874828],"type":"Point"}
}