{
  "type": "Feature",
  "properties": {
    "addr:full":"Flat 8 Southside Quarter, 38 Southside Quarter, Burns Rd Battersea Greater London SW11 5GY",
    "addr:housenumber":"8;38",
    "addr:postcode":"sw11 5gy",
    "addr:street":"Burns Rd",
    "iso:country":"GB",
    "sg:address":"Flat 8 Southside Quarter, 38 Southside Quarter, Burns Rd",
    "sg:city":"Battersea",
    "sg:classifiers":[
        {
            "category":"Professional",
            "subcategory":"Management & Consulting",
            "type":"Services"
        }
    ],
    "sg:phone":"+44 20 7228 5500",
    "sg:postcode":"SW11 5GY",
    "sg:province":"Greater London",
    "sg:tags":[
        "consultant",
        "promotion",
        "direct",
        "sale"
    ],
    "wof:name":"Zebra Consultancy",
    "wof:placetype":"venue"
},
  "geometry": {"coordinates":[-0.162839,51.467464],"type":"Point"}
}