{
  "type": "Feature",
  "properties": {
    "iso:country":"GB",
    "sg:address":"44 Lynton Avenue",
    "sg:city":"Orpington",
    "sg:classifiers":[
        {
            "category":"Social Services",
            "subcategory":"Adult Care",
            "type":"Services"
        }
    ],
    "sg:phone":"+44 1322 625700",
    "sg:postcode":"BR5 2EH",
    "sg:province":"Kent",
    "sg:tags":[
        "day",
        "centre"
    ],
    "wof:name":"Oxlea N H S Trust",
    "wof:placetype":"venue"
},
  "geometry": {"coordinates":[0.1057389975,51.3930130005],"type":"Point"}
}