{
  "type": "Feature",
  "properties": {
    "addr:full":"Lower Rd, Barnacle Coventry Warwickshire CV7 9LD",
    "addr:postcode":"cv7 9ld",
    "addr:street":"Lower Rd",
    "iso:country":"GB",
    "sg:address":"Lower Rd, Barnacle",
    "sg:city":"Coventry",
    "sg:classifiers":[
        {
            "category":"Retail",
            "subcategory":"Auto Repair",
            "type":"Services"
        }
    ],
    "sg:postcode":"CV7 9LD",
    "sg:province":"Warwickshire",
    "sg:tags":[
        "modification",
        "garage"
    ],
    "wof:name":"Ward,Thomas Victor,",
    "wof:placetype":"venue"
},
  "geometry": {"coordinates":[-1.432371974,52.4598312378],"type":"Point"}
}