{
  "type": "Feature",
  "properties": {
    "iso:country":"GB",
    "sg:address":"Dallam Avenue",
    "sg:city":"Morecambe",
    "sg:classifiers":[
        {
            "category":"Education",
            "subcategory":"School",
            "type":"Public Place"
        }
    ],
    "sg:phone":"+44 1524 410207",
    "sg:postcode":"LA4 5BG",
    "sg:province":"Lancashire",
    "sg:tags":[
        "local",
        "authority"
    ],
    "wof:name":"Morecambe High School",
    "wof:placetype":"venue"
},
  "geometry": {"coordinates":[-2.854519,54.076542],"type":"Point"}
}