{
  "type": "Feature",
  "properties": {
    "addr:full":"44 Colwith Road, Hammersmith London Greater London W6 9EY",
    "addr:housenumber":"44",
    "addr:postcode":"w6 9ey",
    "addr:street":"Colwith Road",
    "iso:country":"GB",
    "sg:address":"44 Colwith Road, Hammersmith",
    "sg:city":"London",
    "sg:classifiers":[
        {
            "category":"Home & Garden",
            "subcategory":"Carpets & Floor Coverings",
            "type":"Retail Goods"
        }
    ],
    "sg:phone":"+44 20 8746 3220",
    "sg:postcode":"W6 9EY",
    "sg:province":"Greater London",
    "sg:tags":[
        "cleaner",
        "upholstery"
    ],
    "wof:name":"Norse Carpet Cleaning",
    "wof:placetype":"venue"
},
  "geometry": {"coordinates":[-0.222181,51.485878],"type":"Point"}
}