{
  "type": "Feature",
  "properties": {
    "iso:country":"GB",
    "sg:address":"Babell",
    "sg:city":"Holywell",
    "sg:classifiers":[
        {
            "category":"Farming",
            "subcategory":"Livestock Farm",
            "type":"Manufacturing & Wholesale Goods"
        }
    ],
    "sg:postcode":"CH8 8PR",
    "sg:province":"Denbighshire",
    "sg:tags":[
        "others"
    ],
    "wof:name":"E E Jones",
    "wof:placetype":"venue"
},
  "geometry": {"coordinates":[-3.2506570816,53.2511062622],"type":"Point"}
}