{
  "type": "Feature",
  "properties": {
    "iso:country":"GB",
    "sg:address":"6 Riverside Court, Castle Street",
    "sg:city":"Barnstaple",
    "sg:classifiers":[
        {
            "category":"Professional",
            "subcategory":"Advertising",
            "type":"Services"
        }
    ],
    "sg:phone":"+44 1271 328002",
    "sg:postcode":"EX31 1EP",
    "sg:province":"Devon",
    "sg:tags":[
        "agency"
    ],
    "wof:name":"The Entire Works Ltd.",
    "wof:placetype":"venue"
},
  "geometry": {"coordinates":[-4.062565,51.079506],"type":"Point"}
}