{
  "type": "Feature",
  "properties": {
    "addr:full":"Edward Hyde Building Watford Hertfordshire WD17 1SX",
    "addr:postcode":"wd17 1sx",
    "iso:country":"GB",
    "sg:address":"Edward Hyde Building",
    "sg:city":"Watford",
    "sg:classifiers":[
        {
            "category":"Autos & Motor Vehicles",
            "subcategory":"Auto Supplies",
            "type":"Retail Goods"
        }
    ],
    "sg:postcode":"WD17 1SX",
    "sg:province":"Hertfordshire",
    "sg:tags":[
        "rubber",
        "tyre"
    ],
    "wof:name":"Kleber",
    "wof:placetype":"venue"
},
  "geometry": {"coordinates":[-0.390719,51.652119],"type":"Point"}
}