{
  "type": "Feature",
  "properties": {
    "addr:full":"New Valley, Cowbrow, Lupton Carnforth Cumbria LA6 1PF",
    "addr:postcode":"la6 1pf",
    "iso:country":"GB",
    "sg:address":"New Valley, Cowbrow, Lupton",
    "sg:city":"Carnforth",
    "sg:classifiers":[
        {
            "category":"Freight",
            "type":"Transportation"
        }
    ],
    "sg:phone":"+44 15395 67232",
    "sg:postcode":"LA6 1PF",
    "sg:province":"Cumbria",
    "sg:tags":[
        "haulage",
        "transport",
        "road"
    ],
    "wof:name":"E Redmayne & Son",
    "wof:placetype":"venue"
},
  "geometry": {"coordinates":[-2.7250630856,54.1822395325],"type":"Point"}
}