{
  "type": "Feature",
  "properties": {
    "iso:country":"GB",
    "sg:address":"70 Brick Kiln Lane",
    "sg:city":"Loughborough",
    "sg:classifiers":[
        {
            "category":"Building & Trades",
            "subcategory":"Plumbing",
            "type":"Services"
        }
    ],
    "sg:postcode":"LE12 9EL",
    "sg:province":"Leicestershire",
    "sg:tags":[
        "heating"
    ],
    "wof:name":"Ralph Colin Partridge",
    "wof:placetype":"venue"
},
  "geometry": {"coordinates":[-1.3041729927,52.7542114258],"type":"Point"}
}