{
  "type": "Feature",
  "properties": {
    "addr:full":"Stewart Street Bury Lancashire BL8 1SU",
    "addr:postcode":"bl8 1su",
    "addr:street":"Stewart Street",
    "iso:country":"GB",
    "sg:address":"Stewart Street",
    "sg:city":"Bury",
    "sg:classifiers":[
        {
            "category":"Farming",
            "subcategory":"Nursery",
            "type":"Manufacturing & Wholesale Goods"
        }
    ],
    "sg:phone":"+44 161 797 3788",
    "sg:postcode":"BL8 1SU",
    "sg:province":"Lancashire",
    "sg:tags":[
        "creche"
    ],
    "wof:name":"Brightsparks Kindergarten",
    "wof:placetype":"venue"
},
  "geometry": {"coordinates":[-2.320229,53.599491],"type":"Point"}
}