{
  "type": "Feature",
  "properties": {
    "addr:full":"Unit 7 Springvale Mill, Flip Rd, Haslingden Rossendale Lancashire BB4 5EJ",
    "addr:housenumber":"unit 7",
    "addr:postcode":"bb4 5ej",
    "addr:street":"Springvale Mill Flip Rd",
    "iso:country":"GB",
    "sg:address":"Unit 7 Springvale Mill, Flip Rd, Haslingden",
    "sg:city":"Rossendale",
    "sg:classifiers":[
        {
            "category":"Professional",
            "type":"Services"
        }
    ],
    "sg:postcode":"BB4 5EJ",
    "sg:province":"Lancashire",
    "sg:tags":[
        "interior",
        "furnishers",
        "designer"
    ],
    "wof:name":"Bownes,Maria,",
    "wof:placetype":"venue"
},
  "geometry": {"coordinates":[-2.3253939152,53.7046394348],"type":"Point"}
}