{
  "type": "Feature",
  "properties": {
    "iso:country":"GB",
    "sg:address":"Normanton Lane, Bottesford",
    "sg:city":"Nottingham",
    "sg:classifiers":[
        {
            "category":"Farming",
            "subcategory":"Dairy Farm",
            "type":"Manufacturing & Wholesale Goods"
        }
    ],
    "sg:phone":"+44 1949 842661",
    "sg:postcode":"NG13 0EL",
    "sg:province":"Leicestershire",
    "wof:name":"Long Clawson Dairy Ltd",
    "wof:placetype":"venue"
},
  "geometry": {"coordinates":[-0.799514,52.941921],"type":"Point"}
}