{
  "type": "Feature",
  "properties": {
    "addr:full":"Met Station Arcade, Hammersmith Bdwy, Hammersmith London Greater London W6 7AA",
    "addr:postcode":"w6 7aa",
    "addr:street":"Bdwy",
    "iso:country":"GB",
    "sg:address":"Met Station Arcade, Hammersmith Bdwy, Hammersmith",
    "sg:city":"London",
    "sg:classifiers":[
        {
            "category":"Bars & Pubs",
            "subcategory":"Wine Bar",
            "type":"Food & Drink"
        }
    ],
    "sg:postcode":"W6 7AA",
    "sg:province":"Greater London",
    "wof:name":"El Metro Tapas Bar & Cafe Brasserie",
    "wof:placetype":"venue"
},
  "geometry": {"coordinates":[-0.2252299935,51.493221283],"type":"Point"}
}