{
  "type": "Feature",
  "properties": {
    "iso:country":"GB",
    "sg:address":"307 St Annes Road",
    "sg:city":"Blackpool",
    "sg:classifiers":[
        {
            "category":"Building & Trades",
            "subcategory":"Construction",
            "type":"Services"
        }
    ],
    "sg:phone":"+44 1253 343345",
    "sg:postcode":"FY4 2EE",
    "sg:province":"Lancashire",
    "sg:tags":[
        "roofing"
    ],
    "wof:name":"K W S  Improvements Ltd.",
    "wof:placetype":"venue"
},
  "geometry": {"coordinates":[-3.038145,53.788902],"type":"Point"}
}