{
  "type": "Feature",
  "properties": {
    "iso:country":"GB",
    "sg:address":"8 Marlborough Park, East Kilbride",
    "sg:city":"Glasgow",
    "sg:classifiers":[
        {
            "category":"Home & Garden",
            "subcategory":"Household Appliances",
            "type":"Retail Goods"
        }
    ],
    "sg:phone":"+44 1355 247109",
    "sg:postcode":"G75 8PS",
    "sg:province":"South Lanarkshire",
    "sg:tags":[
        "electrical"
    ],
    "wof:name":"Fletcher Domestic Appliance Repairs",
    "wof:placetype":"venue"
},
  "geometry": {"coordinates":[-4.211791,55.752102],"type":"Point"}
}