{
  "type": "Feature",
  "properties": {
    "addr:full":"Unit 21 Bramley Centre Leeds West Yorkshire LS13 2ET",
    "addr:housenumber":"unit 21",
    "addr:postcode":"ls13 2et",
    "addr:street":"Bramley Centre Leeds West",
    "iso:country":"GB",
    "sg:address":"Unit 21 Bramley Centre",
    "sg:city":"Leeds",
    "sg:classifiers":[
        {
            "category":"Retail",
            "subcategory":"Photofinishing",
            "type":"Services"
        }
    ],
    "sg:phone":"+44 113 236 0806",
    "sg:postcode":"LS13 2ET",
    "sg:province":"West Yorkshire",
    "sg:tags":[
        "photographic",
        "processor"
    ],
    "wof:name":"Klick Photopoint",
    "wof:placetype":"venue"
},
  "geometry": {"coordinates":[-1.6271140575,53.8120346069],"type":"Point"}
}