{
  "type": "Feature",
  "properties": {
    "iso:country":"GB",
    "sg:address":"1 Cambusnethan Street",
    "sg:city":"Edinburgh",
    "sg:classifiers":[
        {
            "category":"Shopping",
            "subcategory":"Computers & Home Electronics",
            "type":"Retail Goods"
        }
    ],
    "sg:phone":"+44 131 661 3334",
    "sg:postcode":"EH7 5TZ",
    "sg:province":"City of Edinburgh",
    "sg:tags":[
        "aerial",
        "television",
        "radio"
    ],
    "wof:name":"Aerial-Rite",
    "wof:placetype":"venue"
},
  "geometry": {"coordinates":[-3.162189,55.956635],"type":"Point"}
}