{
  "type": "Feature",
  "properties": {
    "iso:country":"GB",
    "sg:address":"86 Loughborough Road, Mountsorrel",
    "sg:city":"Loughborough",
    "sg:classifiers":[
        {
            "category":"Health Services",
            "subcategory":"Nursing And Care Facility",
            "type":"Services"
        },
        {
            "category":"Social Services",
            "subcategory":"Retirement Home",
            "type":"Services"
        }
    ],
    "sg:phone":"+44 1509 413667",
    "sg:postcode":"LE12 7AU",
    "sg:province":"Leicestershire",
    "sg:tags":[
        "residential"
    ],
    "wof:name":"David Leslie Residential Home",
    "wof:placetype":"venue"
},
  "geometry": {"coordinates":[-1.1465610266,52.7336235046],"type":"Point"}
}