{
  "type": "Feature",
  "properties": {
    "iso:country":"GB",
    "sg:address":"Ardgowan Road",
    "sg:city":"Wemyss Bay",
    "sg:classifiers":[
        {
            "category":"Education",
            "subcategory":"School",
            "type":"Public Place"
        },
        {
            "category":"Government",
            "subcategory":"Office",
            "type":"Public Place"
        }
    ],
    "sg:phone":"+44 1475 521792",
    "sg:postcode":"PA18 6AT",
    "sg:province":"Inverclyde",
    "sg:tags":[
        "local",
        "authority"
    ],
    "wof:name":"Wemyss Bay Primary School",
    "wof:placetype":"venue"
},
  "geometry": {"coordinates":[-4.88717,55.888275],"type":"Point"}
}