{
  "type": "Feature",
  "properties": {
    "addr:full":"Northlake, Stockley Okehampton Devon EX20 1QH",
    "addr:postcode":"ex20 1qh",
    "addr:street":"Stockley",
    "iso:country":"GB",
    "sg:address":"Northlake, Stockley",
    "sg:city":"Okehampton",
    "sg:classifiers":[
        {
            "category":"Transit Center",
            "subcategory":"Passenger",
            "type":"Transportation"
        }
    ],
    "sg:postcode":"EX20 1QH",
    "sg:province":"Devon",
    "sg:tags":[
        "boarding",
        "kennel",
        "catteries"
    ],
    "wof:name":"Northlake Boarding Kennels",
    "wof:placetype":"venue"
},
  "geometry": {"coordinates":[-4.0025148392,50.7392234802],"type":"Point"}
}