{
  "type": "Feature",
  "properties": {
    "addr:full":"28 High Street Manningtree Essex CO11 1AJ",
    "addr:housenumber":"28",
    "addr:postcode":"co11 1aj",
    "addr:street":"High Street",
    "iso:country":"GB",
    "sg:address":"28 High Street",
    "sg:city":"Manningtree",
    "sg:classifiers":[
        {
            "category":"Shopping",
            "subcategory":"Books",
            "type":"Retail Goods"
        }
    ],
    "sg:postcode":"CO11 1AJ",
    "sg:province":"Essex",
    "sg:tags":[
        "bookseller"
    ],
    "wof:name":"Mustard Seed",
    "wof:placetype":"venue"
},
  "geometry": {"coordinates":[1.064177,51.945274],"type":"Point"}
}