{
  "type": "Feature",
  "properties": {
    "addr:full":"57 Newton Street Manchester Greater Manchester M1 1ET",
    "addr:housenumber":"57",
    "addr:postcode":"m1 1et",
    "addr:street":"Newton Street",
    "iso:country":"GB",
    "sg:address":"57 Newton Street",
    "sg:city":"Manchester",
    "sg:classifiers":[
        {
            "category":"Place Of Worship",
            "type":"Public Place"
        },
        {
            "category":"Museum",
            "subcategory":"Art Museum",
            "type":"Entertainment"
        },
        {
            "category":"Museum",
            "type":"Entertainment"
        }
    ],
    "sg:phone":"+44 161 856 3287",
    "sg:postcode":"M1 1ET",
    "sg:province":"Greater Manchester",
    "sg:tags":[
        "gallery"
    ],
    "wof:name":"MUSEUM OF THE GREATER MANCHESTER POLICE",
    "wof:placetype":"venue"
},
  "geometry": {"coordinates":[-2.2324380875,53.4823722839],"type":"Point"}
}