{
  "type": "Feature",
  "properties": {
    "addr:full":"Sterling House, 10g Buntsford Park Road Bromsgrove Worcestershire B60 3DX",
    "addr:housenumber":"10g",
    "addr:postcode":"b60 3dx",
    "addr:street":"Buntsford Park Road",
    "iso:country":"GB",
    "sg:address":"Sterling House, 10g Buntsford Park Road",
    "sg:city":"Bromsgrove",
    "sg:classifiers":[
        {
            "category":"Education",
            "subcategory":"Special Training",
            "type":"Public Place"
        }
    ],
    "sg:postcode":"B60 3DX",
    "sg:province":"Worcestershire",
    "sg:tags":[
        "product",
        "centre"
    ],
    "wof:name":"Crystal Training Ltd",
    "wof:placetype":"venue"
},
  "geometry": {"coordinates":[-2.064099,52.316307],"type":"Point"}
}