{
  "type": "Feature",
  "properties": {
    "iso:country":"GB",
    "sg:address":"310 Edgware Rd",
    "sg:city":"Bayswater",
    "sg:classifiers":[
        {
            "category":"Banks & Credit Unions",
            "subcategory":"Financial Services",
            "type":"Services"
        }
    ],
    "sg:phone":"+44 20 7723 7371",
    "sg:postcode":"W2 1DY",
    "sg:province":"Greater London",
    "sg:tags":[
        "adviser"
    ],
    "wof:name":"Finance Commercial & Corporate",
    "wof:placetype":"venue"
},
  "geometry": {"coordinates":[-0.172207,51.52137],"type":"Point"}
}