{
  "type": "Feature",
  "properties": {
    "addr:full":"45-47 High Street Cobham Surrey KT11 3DP",
    "addr:housenumber":"45-47",
    "addr:postcode":"kt11 3dp",
    "addr:street":"High Street",
    "iso:country":"GB",
    "sg:address":"45-47 High Street",
    "sg:city":"Cobham",
    "sg:classifiers":[
        {
            "category":"Utilities",
            "subcategory":"Sewage",
            "type":"Services"
        }
    ],
    "sg:phone":"+44 1932 868440",
    "sg:postcode":"KT11 3DP",
    "sg:province":"Surrey",
    "sg:tags":[
        "acoustic",
        "consultant"
    ],
    "wof:name":"Vernon Cole Associates",
    "wof:placetype":"venue"
},
  "geometry": {"coordinates":[-0.4102860093,51.327419281],"type":"Point"}
}