{
  "type": "Feature",
  "properties": {
    "iso:country":"GB",
    "sg:address":"69 Main Street, North Frodingham",
    "sg:city":"Driffield",
    "sg:classifiers":[
        {
            "category":"Farming",
            "subcategory":"Livestock Farm",
            "type":"Manufacturing & Wholesale Goods"
        }
    ],
    "sg:phone":"+44 1262 488202",
    "sg:postcode":"YO25 8LG",
    "sg:province":"East Riding of Yorkshire",
    "sg:tags":[
        "others"
    ],
    "wof:name":"C C Connor & Sons",
    "wof:placetype":"venue"
},
  "geometry": {"coordinates":[-0.2920629978,53.9698524475],"type":"Point"}
}