{
  "type": "Feature",
  "properties": {
    "iso:country":"GB",
    "sg:address":"Stephenson Ho, Stephenson Way",
    "sg:city":"Crawley",
    "sg:classifiers":[
        {
            "category":"Freight",
            "type":"Transportation"
        }
    ],
    "sg:phone":"+44 1293 543344",
    "sg:postcode":"RH10 2UZ",
    "sg:province":"Surrey",
    "sg:tags":[
        "forwarders"
    ],
    "wof:name":"Overall International Air Cargo Ltd",
    "wof:placetype":"venue"
},
  "geometry": {"coordinates":[-0.184753,51.118458],"type":"Point"}
}