{
  "type": "Feature",
  "properties": {
    "addr:full":"Grove Road Stoke-on-trent Staffordshire ST4 4LE",
    "addr:postcode":"st4 4le",
    "addr:street":"Grove Road",
    "iso:country":"GB",
    "sg:address":"Grove Road",
    "sg:city":"Stoke-on-trent",
    "sg:classifiers":[
        {
            "category":"Autos & Motor Vehicles",
            "subcategory":"Auto Supplies",
            "type":"Retail Goods"
        }
    ],
    "sg:postcode":"ST4 4LE",
    "sg:province":"Staffordshire",
    "sg:tags":[
        "car",
        "towing",
        "trailer",
        "eqpt",
        "accessory"
    ],
    "wof:name":"Indespension Ltd.",
    "wof:placetype":"venue"
},
  "geometry": {"coordinates":[-2.1728870869,52.9937553406],"type":"Point"}
}