{
  "type": "Feature",
  "properties": {
    "iso:country":"GB",
    "sg:address":"317 Chester Road, Aldridge",
    "sg:city":"Walsall",
    "sg:classifiers":[
        {
            "category":"Government",
            "subcategory":"Post Office",
            "type":"Public Place"
        }
    ],
    "sg:phone":"+44 121 353 7069",
    "sg:postcode":"WS9 0PH",
    "sg:province":"Staffordshire",
    "wof:name":"Chester Road Post Office",
    "wof:placetype":"venue"
},
  "geometry": {"coordinates":[-1.8886170387,52.5897712708],"type":"Point"}
}