{
  "type": "Feature",
  "properties": {
    "iso:country":"GB",
    "sg:address":"57 High St, Wavertree",
    "sg:city":"Liverpool",
    "sg:classifiers":[
        {
            "category":"Shopping",
            "subcategory":"Gifts & Souvenirs",
            "type":"Retail Goods"
        }
    ],
    "sg:postcode":"L15 8HE",
    "sg:province":"Merseyside",
    "sg:tags":[
        "shop"
    ],
    "wof:name":"Fahey,J,",
    "wof:placetype":"venue"
},
  "geometry": {"coordinates":[-2.919438,53.398819],"type":"Point"}
}