{
  "type": "Feature",
  "properties": {
    "iso:country":"GB",
    "sg:address":"Main Street, Plains",
    "sg:city":"Airdrie",
    "sg:classifiers":[
        {
            "category":"Autos & Motor Vehicles",
            "subcategory":"Fuel & Gas Station",
            "type":"Retail Goods"
        }
    ],
    "sg:phone":"+44 1236 769994",
    "sg:postcode":"ML6 7JE",
    "sg:province":"North Lanarkshire",
    "sg:tags":[
        "petrol",
        "filling"
    ],
    "wof:name":"West End Garage",
    "wof:placetype":"venue"
},
  "geometry": {"coordinates":[-3.919979,55.881142],"type":"Point"}
}