{
  "type": "Feature",
  "properties": {
    "addr:full":"Rowanlea, Garlogie, Skene Westhill Aberdeen City AB32 6RX",
    "addr:postcode":"ab32 6rx",
    "iso:country":"GB",
    "sg:address":"Rowanlea, Garlogie, Skene",
    "sg:city":"Westhill",
    "sg:classifiers":[
        {
            "category":"Farming",
            "subcategory":"Livestock Farm",
            "type":"Manufacturing & Wholesale Goods"
        }
    ],
    "sg:postcode":"AB32 6RX",
    "sg:province":"Aberdeen City",
    "sg:tags":[
        "others"
    ],
    "wof:name":"Ovaflo Ltd",
    "wof:placetype":"venue"
},
  "geometry": {"coordinates":[-2.2926840782,57.1494445801],"type":"Point"}
}