{
  "type": "Feature",
  "properties": {
    "addr:full":"Whaplode Lodge, Jekils Bank, Holbeach St Johns Spalding Cambridgeshire PE12 8RQ",
    "addr:postcode":"pe12 8rq",
    "addr:street":"Holbeach St;Spalding",
    "iso:country":"GB",
    "sg:address":"Whaplode Lodge, Jekils Bank, Holbeach St Johns",
    "sg:city":"Spalding",
    "sg:classifiers":[
        {
            "category":"Manufacturing",
            "subcategory":"Metals",
            "type":"Manufacturing & Wholesale Goods"
        }
    ],
    "sg:phone":"+44 1406 540631",
    "sg:postcode":"PE12 8RQ",
    "sg:province":"Cambridgeshire",
    "sg:tags":[
        "steel",
        "fabricator",
        "erectors"
    ],
    "wof:name":"R F Welding & Fabrication Services Ltd",
    "wof:placetype":"venue"
},
  "geometry": {"coordinates":[-0.02881,52.7419204712],"type":"Point"}
}