{
  "type": "Feature",
  "properties": {
    "addr:full":"96 Cooks Close, Bradley Stoke Bristol Gloucestershire BS32 0BB",
    "addr:housenumber":"96",
    "addr:postcode":"bs32 0bb",
    "addr:street":"Cooks Close",
    "iso:country":"GB",
    "sg:address":"96 Cooks Close, Bradley Stoke",
    "sg:city":"Bristol",
    "sg:classifiers":[
        {
            "category":"Organizations",
            "subcategory":"Non-profit Organization",
            "type":"Services"
        }
    ],
    "sg:postcode":"BS32 0BB",
    "sg:province":"Gloucestershire",
    "sg:tags":[
        "organisation",
        "voluntary",
        "charity"
    ],
    "wof:name":"Save the Children Fund",
    "wof:placetype":"venue"
},
  "geometry": {"coordinates":[-2.55496,51.54475],"type":"Point"}
}