{
  "type": "Feature",
  "properties": {
    "addr:full":"232 Carter St Ely Cambridgeshire CB7 5JU",
    "addr:housenumber":"232",
    "addr:postcode":"cb7 5ju",
    "addr:street":"Carter St",
    "iso:country":"GB",
    "sg:address":"232 Carter St",
    "sg:city":"Ely",
    "sg:classifiers":[
        {
            "category":"Sports & Exercise",
            "subcategory":"Skate Park",
            "type":"Entertainment"
        }
    ],
    "sg:phone":"+44 1638 721886",
    "sg:postcode":"CB7 5JU",
    "sg:province":"Cambridgeshire",
    "sg:tags":[
        "mnfrs",
        "brake",
        "clutch"
    ],
    "wof:name":"Brake & Clutch Components",
    "wof:placetype":"venue"
},
  "geometry": {"coordinates":[0.3840810061,52.3128814697],"type":"Point"}
}