{
  "type": "Feature",
  "properties": {
    "iso:country":"GB",
    "sg:address":"P O Box 116",
    "sg:city":"Wilmslow",
    "sg:classifiers":[
        {
            "category":"Professional",
            "subcategory":"Credit Reporting & Collection",
            "type":"Services"
        }
    ],
    "sg:postcode":"SK9 2UA",
    "sg:province":"Cheshire",
    "sg:tags":[
        "collecting",
        "agency"
    ],
    "wof:name":"Accounting Services",
    "wof:placetype":"venue"
},
  "geometry": {"coordinates":[-2.227897,53.326797],"type":"Point"}
}