{
  "type": "Feature",
  "properties": {
    "addr:full":"81 Polefield Circle, Prestwich Manchester Greater Manchester M25 2NQ",
    "addr:housenumber":"81",
    "addr:postcode":"m25 2nq",
    "addr:street":"Polefield Circle",
    "iso:country":"GB",
    "sg:address":"81 Polefield Circle, Prestwich",
    "sg:city":"Manchester",
    "sg:classifiers":[
        {
            "category":"Professional",
            "subcategory":"Art Services",
            "type":"Services"
        },
        {
            "category":"Building & Trades",
            "subcategory":"Construction",
            "type":"Services"
        }
    ],
    "sg:postcode":"M25 2NQ",
    "sg:province":"Greater Manchester",
    "sg:tags":[
        "decorator",
        "painter"
    ],
    "wof:name":"DAVID THORNTON",
    "wof:placetype":"venue"
},
  "geometry": {"coordinates":[-2.2748279572,53.5397644043],"type":"Point"}
}