{
  "type": "Feature",
  "properties": {
    "iso:country":"GB",
    "sg:address":"1 Crawley Grange, Pound Lane, North Crawley",
    "sg:city":"Newport Pagnell",
    "sg:classifiers":[
        {
            "category":"Professional",
            "subcategory":"Accounting & Tax Preparation",
            "type":"Services"
        }
    ],
    "sg:phone":"+44 1234 391319",
    "sg:postcode":"MK16 9HL",
    "sg:province":"Buckinghamshire",
    "sg:tags":[
        "accountant"
    ],
    "wof:name":"Vrs-V A T  Refund Services Ltd.",
    "wof:placetype":"venue"
},
  "geometry": {"coordinates":[-0.648625,52.093136],"type":"Point"}
}