{
  "type": "Feature",
  "properties": {
    "addr:full":"Hilton Lane, Prestwich Manchester Greater Manchester M25 9XJ",
    "addr:postcode":"m25 9xj",
    "addr:street":"Hilton Lane",
    "iso:country":"GB",
    "sg:address":"Hilton Lane, Prestwich",
    "sg:city":"Manchester",
    "sg:classifiers":[
        {
            "category":"Retail",
            "subcategory":"Auto Repair",
            "type":"Services"
        }
    ],
    "sg:phone":"+44 161 773 2510",
    "sg:postcode":"M25 9XJ",
    "sg:province":"Greater Manchester",
    "sg:tags":[
        "modification",
        "garage",
        "related"
    ],
    "wof:name":"Rainsough Filling Station Ltd",
    "wof:placetype":"venue"
},
  "geometry": {"coordinates":[-2.277846,53.521996],"type":"Point"}
}