{
  "type": "Feature",
  "properties": {
    "iso:country":"GB",
    "sg:address":"Gloucester Park Swimming Pool, Broadmayne",
    "sg:city":"Basildon",
    "sg:classifiers":[
        {
            "category":"Health Services",
            "subcategory":"Clinic",
            "type":"Services"
        }
    ],
    "sg:phone":"+44 1268 767727",
    "sg:postcode":"SS14 2EB",
    "sg:province":"Essex",
    "sg:tags":[
        "aromatherapy"
    ],
    "wof:name":"Lesley Croft",
    "wof:placetype":"venue"
},
  "geometry": {"coordinates":[0.4538,51.57386],"type":"Point"}
}