{
  "type": "Feature",
  "properties": {
    "iso:country":"GB",
    "sg:address":"101 High Street",
    "sg:city":"Broadway",
    "sg:classifiers":[
        {
            "category":"Travel",
            "subcategory":"Hotels & Motels",
            "type":"Entertainment"
        }
    ],
    "sg:postcode":"WR12 7AL",
    "sg:province":"Gloucestershire",
    "sg:tags":[
        "house",
        "guest"
    ],
    "wof:name":"Christie's",
    "wof:placetype":"venue"
},
  "geometry": {"coordinates":[-1.854393,52.036373],"type":"Point"}
}