{
  "type": "Feature",
  "properties": {
    "addr:full":"2 Rectory Lane, Wolverton Tadley Berkshire RG26 5RS",
    "addr:housenumber":"2",
    "addr:postcode":"rg26 5rs",
    "addr:street":"Rectory Lane",
    "iso:country":"GB",
    "sg:address":"2 Rectory Lane, Wolverton",
    "sg:city":"Tadley",
    "sg:classifiers":[
        {
            "category":"Travel",
            "subcategory":"Travel Agent",
            "type":"Entertainment"
        }
    ],
    "sg:phone":"+44 1635 297209",
    "sg:postcode":"RG26 5RS",
    "sg:province":"Berkshire",
    "wof:name":"Pyrenean Mountain Tours",
    "wof:placetype":"venue"
},
  "geometry": {"coordinates":[-1.2217370272,51.3154945374],"type":"Point"}
}