{
  "type": "Feature",
  "properties": {
    "iso:country":"GB",
    "sg:address":"19 Wimpole Street",
    "sg:city":"London",
    "sg:classifiers":[
        {
            "category":"Health Services",
            "subcategory":"Dentist",
            "type":"Services"
        }
    ],
    "sg:phone":"+44 20 7580 7988",
    "sg:postcode":"W1W 8LR",
    "sg:province":"Greater London",
    "wof:name":"Martin Gough Practice",
    "wof:placetype":"venue"
},
  "geometry": {"coordinates":[-0.148044,51.518234],"type":"Point"}
}