{
  "type": "Feature",
  "properties": {
    "addr:full":"15 Carmyle Avenue Glasgow Glasgow City G32 8HL",
    "addr:housenumber":"15",
    "addr:postcode":"g32 8hl",
    "addr:street":"Carmyle Avenue",
    "iso:country":"GB",
    "sg:address":"15 Carmyle Avenue",
    "sg:city":"Glasgow",
    "sg:classifiers":[
        {
            "category":"Professional",
            "subcategory":"Detective & Security Services",
            "type":"Services"
        },
        {
            "category":"Building & Trades",
            "subcategory":"Locksmith",
            "type":"Services"
        }
    ],
    "sg:phone":"+44 141 763 1599",
    "sg:postcode":"G32 8HL",
    "sg:province":"Glasgow City",
    "wof:name":"G & E Lock & Safe Co",
    "wof:placetype":"venue"
},
  "geometry": {"coordinates":[-4.1612401009,55.8406028748],"type":"Point"}
}