{
  "type": "Feature",
  "properties": {
    "addr:full":"Calmore Industrial Estate Southampton Hampshire SO40 3SS",
    "addr:postcode":"so40 3ss",
    "addr:street":"Calmore Industrial Estate",
    "iso:country":"GB",
    "sg:address":"Calmore Industrial Estate",
    "sg:city":"Southampton",
    "sg:classifiers":[
        {
            "category":"Manufacturing",
            "subcategory":"Metals",
            "type":"Manufacturing & Wholesale Goods"
        }
    ],
    "sg:postcode":"SO40 3SS",
    "sg:province":"Hampshire",
    "sg:tags":[
        "steel",
        "stockholder"
    ],
    "wof:name":"Beaumont Stainless Steels Ltd.",
    "wof:placetype":"venue"
},
  "geometry": {"coordinates":[-1.503587,50.934181],"type":"Point"}
}