{
  "type": "Feature",
  "properties": {
    "addr:full":"39 Back Sneddon Street Paisley Renfrewshire PA3 2DE",
    "addr:housenumber":"39",
    "addr:postcode":"pa3 2de",
    "addr:street":"Back Sneddon Street",
    "iso:country":"GB",
    "sg:address":"39 Back Sneddon Street",
    "sg:city":"Paisley",
    "sg:classifiers":[
        {
            "category":"Professional",
            "subcategory":"Testing Lab",
            "type":"Services"
        }
    ],
    "sg:phone":"+44 141 887 3531",
    "sg:postcode":"PA3 2DE",
    "sg:province":"Renfrewshire",
    "sg:tags":[
        "laboratory"
    ],
    "wof:name":"H & J Stainfast Ltd.",
    "wof:placetype":"venue"
},
  "geometry": {"coordinates":[-4.4251289368,55.8495521545],"type":"Point"}
}