{
  "type": "Feature",
  "properties": {
    "addr:full":"1a West St Helen Street Abingdon Oxfordshire OX14 5BL",
    "addr:housenumber":"1a",
    "addr:postcode":"ox14 5bl",
    "addr:street":"West St Helen Street",
    "iso:country":"GB",
    "sg:address":"1a West St Helen Street",
    "sg:city":"Abingdon",
    "sg:classifiers":[
        {
            "category":"Shopping",
            "subcategory":"Shoes",
            "type":"Retail Goods"
        }
    ],
    "sg:phone":"+44 1235 521506",
    "sg:postcode":"OX14 5BL",
    "sg:province":"Oxfordshire",
    "sg:tags":[
        "shop"
    ],
    "wof:name":"Lady McBeth Shoe Co. Ltd.",
    "wof:placetype":"venue"
},
  "geometry": {"coordinates":[-1.283039,51.669899],"type":"Point"}
}