{
  "type": "Feature",
  "properties": {
    "addr:full":"Unit 1, Roseville Business Park, Roseville Road Leeds West Yorkshire LS8 5DR",
    "addr:housenumber":"unit 1",
    "addr:postcode":"ls8 5dr",
    "addr:street":"Roseville Business Park Roseville Road",
    "iso:country":"GB",
    "sg:address":"Unit 1, Roseville Business Park, Roseville Road",
    "sg:city":"Leeds",
    "sg:classifiers":[
        {
            "category":"Wholesale",
            "subcategory":"Groceries",
            "type":"Manufacturing & Wholesale Goods"
        }
    ],
    "sg:phone":"+44 113 235 1830",
    "sg:postcode":"LS8 5DR",
    "sg:province":"West Yorkshire",
    "sg:tags":[
        "food",
        "supplier",
        "drink"
    ],
    "wof:name":"C C F S Roseville Ltd.",
    "wof:placetype":"venue"
},
  "geometry": {"coordinates":[-1.52847,53.807621],"type":"Point"}
}