{
  "type": "Feature",
  "properties": {
    "addr:full":"White House Farm, Newcastle Monmouth Gloucestershire NP25 5NF",
    "addr:postcode":"np25 5nf",
    "addr:street":"Newcastle",
    "iso:country":"GB",
    "sg:address":"White House Farm, Newcastle",
    "sg:city":"Monmouth",
    "sg:classifiers":[
        {
            "category":"Farming",
            "subcategory":"Farm",
            "type":"Manufacturing & Wholesale Goods"
        }
    ],
    "sg:phone":"+44 1600 750287",
    "sg:postcode":"NP25 5NF",
    "sg:province":"Gloucestershire",
    "sg:tags":[
        "mixed",
        "crop"
    ],
    "wof:name":"J F W McConnel",
    "wof:placetype":"venue"
},
  "geometry": {"coordinates":[-2.8024799824,51.8515625],"type":"Point"}
}