{
  "type": "Feature",
  "properties": {
    "addr:full":"142 High Road London Greater London E18 2QS",
    "addr:housenumber":"142",
    "addr:postcode":"e18 2qs",
    "addr:street":"High Road",
    "iso:country":"GB",
    "sg:address":"142 High Road",
    "sg:city":"London",
    "sg:classifiers":[
        {
            "category":"Home & Garden",
            "subcategory":"Building Materials",
            "type":"Retail Goods"
        }
    ],
    "sg:phone":"+44 20 8506 1355",
    "sg:postcode":"E18 2QS",
    "sg:province":"Greater London",
    "sg:tags":[
        "fencing"
    ],
    "wof:name":"Waltham Forest Fencing",
    "wof:placetype":"venue"
},
  "geometry": {"coordinates":[0.0212459993,51.596824646],"type":"Point"}
}