{
  "type": "Feature",
  "properties": {
    "iso:country":"GB",
    "sg:address":"Pauls Road",
    "sg:city":"Ipswich",
    "sg:classifiers":[
        {
            "category":"Professional",
            "subcategory":"Printing & Photocopies",
            "type":"Services"
        }
    ],
    "sg:phone":"+44 1473 254817",
    "sg:postcode":"IP2 0AN",
    "sg:province":"Suffolk",
    "sg:tags":[
        "printer"
    ],
    "wof:name":"Winsor Clarke Ltd.",
    "wof:placetype":"venue"
},
  "geometry": {"coordinates":[1.131916,52.055706],"type":"Point"}
}