{
  "type": "Feature",
  "properties": {
    "iso:country":"GB",
    "sg:address":"238 Fulford Rd",
    "sg:city":"York",
    "sg:classifiers":[
        {
            "category":"Organizations",
            "subcategory":"Non-profit Organization",
            "type":"Services"
        }
    ],
    "sg:phone":"+44 1904 625288",
    "sg:postcode":"YO1 4EQ",
    "sg:province":"North Yorkshire",
    "sg:tags":[
        "organisation",
        "voluntary",
        "charity"
    ],
    "wof:name":"S S A F A Forces Help",
    "wof:placetype":"venue"
},
  "geometry": {"coordinates":[-1.074056983,53.9448051453],"type":"Point"}
}