{
  "type": "Feature",
  "properties": {
    "addr:full":"Lloyd's 1 Lime Street London Greater London EC3M 7HA",
    "addr:housenumber":"1",
    "addr:postcode":"ec3m 7ha",
    "addr:street":"Lloyd'S;Lime Street",
    "iso:country":"GB",
    "sg:address":"Lloyd's 1 Lime Street",
    "sg:city":"London",
    "sg:classifiers":[
        {
            "category":"Professional",
            "subcategory":"Detective & Security Services",
            "type":"Services"
        }
    ],
    "sg:phone":"+44 20 7617 5925",
    "sg:postcode":"EC3M 7HA",
    "sg:province":"Greater London",
    "sg:tags":[
        "underwriter"
    ],
    "wof:name":"Jago Managing Agency Ltd.",
    "wof:placetype":"venue"
},
  "geometry": {"coordinates":[-0.08214,51.512539],"type":"Point"}
}