{
  "type": "Feature",
  "properties": {
    "addr:full":"214 Fulwood Road, Broomhill Sheffield South Yorkshire S10 3BB",
    "addr:housenumber":"214",
    "addr:postcode":"s10 3bb",
    "addr:street":"Fulwood Road",
    "iso:country":"GB",
    "sg:address":"214 Fulwood Road, Broomhill",
    "sg:city":"Sheffield",
    "sg:classifiers":[
        {
            "category":"Shopping",
            "subcategory":"Pharmacy",
            "type":"Retail Goods"
        }
    ],
    "sg:phone":"+44 114 266 0637",
    "sg:postcode":"S10 3BB",
    "sg:province":"South Yorkshire",
    "sg:tags":[
        "pharmacist",
        "chemist"
    ],
    "wof:name":"Boots the Chemists",
    "wof:placetype":"venue"
},
  "geometry": {"coordinates":[-1.500914,53.377689],"type":"Point"}
}