{
  "type": "Feature",
  "properties": {
    "addr:full":"Gresty Road Crewe Cheshire CW2 6EB",
    "addr:postcode":"cw2 6eb",
    "addr:street":"Gresty Road",
    "iso:country":"GB",
    "sg:address":"Gresty Road",
    "sg:city":"Crewe",
    "sg:classifiers":[
        {
            "category":"Retail",
            "subcategory":"Auto Repair",
            "type":"Services"
        }
    ],
    "sg:phone":"+44 1270 258670",
    "sg:postcode":"CW2 6EB",
    "sg:province":"Cheshire",
    "sg:tags":[
        "modification",
        "garage"
    ],
    "wof:name":"Roy Moore's Motor Repairs",
    "wof:placetype":"venue"
},
  "geometry": {"coordinates":[-2.436699,53.087975],"type":"Point"}
}