{
  "type": "Feature",
  "properties": {
    "iso:country":"GB",
    "sg:address":"Manor Farm, The Street, Tongham",
    "sg:city":"Farnham",
    "sg:classifiers":[
        {
            "category":"Shopping",
            "subcategory":"Jewelry",
            "type":"Retail Goods"
        }
    ],
    "sg:phone":"+44 1252 783900",
    "sg:postcode":"GU10 1DE",
    "sg:province":"Hampshire",
    "sg:tags":[
        "gold",
        "silversmith"
    ],
    "wof:name":"Morgan Unconventional Silver",
    "wof:placetype":"venue"
},
  "geometry": {"coordinates":[-0.7297899723,51.2333030701],"type":"Point"}
}