{
  "type": "Feature",
  "properties": {
    "iso:country":"GB",
    "sg:address":"74 Midsummer Arcade, Central Milton Keynes",
    "sg:city":"Milton Keynes",
    "sg:classifiers":[
        {
            "category":"Government",
            "subcategory":"Post Office",
            "type":"Public Place"
        }
    ],
    "sg:phone":"+44 845 722 3344",
    "sg:postcode":"MK9 3AA",
    "sg:province":"Buckinghamshire",
    "wof:name":"Post Office Ltd.",
    "wof:placetype":"venue"
},
  "geometry": {"coordinates":[-0.754559,52.041355],"type":"Point"}
}