{
  "type": "Feature",
  "properties": {
    "addr:full":"Plumpton Road Farm, Plumpton Road, Weston Towcester Buckinghamshire NN12 8PT",
    "addr:postcode":"nn12 8pt",
    "addr:street":"Plumpton Road;Plumpton Road",
    "iso:country":"GB",
    "sg:address":"Plumpton Road Farm, Plumpton Road, Weston",
    "sg:city":"Towcester",
    "sg:classifiers":[
        {
            "category":"Farming",
            "subcategory":"Livestock Farm",
            "type":"Manufacturing & Wholesale Goods"
        }
    ],
    "sg:postcode":"NN12 8PT",
    "sg:province":"Buckinghamshire",
    "sg:tags":[
        "others"
    ],
    "wof:name":"D J & S T Webb",
    "wof:placetype":"venue"
},
  "geometry": {"coordinates":[-1.135828,52.117546],"type":"Point"}
}