{
  "type": "Feature",
  "properties": {
    "addr:full":"1-3 Windsor Court Rugby Warwickshire CV21 3BH",
    "addr:housenumber":"1-3",
    "addr:postcode":"cv21 3bh",
    "addr:street":"Windsor Court",
    "iso:country":"GB",
    "sg:address":"1-3 Windsor Court",
    "sg:city":"Rugby",
    "sg:classifiers":[
        {
            "category":"Shopping",
            "subcategory":"Stationery & Office Supplies",
            "type":"Retail Goods"
        },
        {
            "category":"Shopping",
            "subcategory":"News",
            "type":"Retail Goods"
        }
    ],
    "sg:phone":"+44 1788 543935",
    "sg:postcode":"CV21 3BH",
    "sg:province":"Warwickshire",
    "sg:tags":[
        "newsagent"
    ],
    "wof:name":"The Odd Spot",
    "wof:placetype":"venue"
},
  "geometry": {"coordinates":[-1.2469029427,52.372844696],"type":"Point"}
}