{
  "type": "Feature",
  "properties": {
    "iso:country":"GB",
    "sg:address":"21 St Modwens Walk",
    "sg:city":"Burton-on-trent",
    "sg:classifiers":[
        {
            "category":"Shopping",
            "subcategory":"Florist",
            "type":"Retail Goods"
        }
    ],
    "sg:phone":"+44 1283 545340",
    "sg:postcode":"DE14 1HL",
    "sg:province":"Derbyshire",
    "wof:name":"Flower Stop",
    "wof:placetype":"venue"
},
  "geometry": {"coordinates":[-1.63164,52.801868],"type":"Point"}
}