{
  "type": "Feature",
  "properties": {
    "iso:country":"GB",
    "sg:address":"26 Westminster Terrace",
    "sg:city":"Glasgow",
    "sg:classifiers":[
        {
            "category":"Fast Food",
            "type":"Food & Drink"
        }
    ],
    "sg:phone":"+44 141 204 3651",
    "sg:postcode":"G3 7RU",
    "sg:province":"Glasgow City",
    "sg:tags":[
        "away",
        "take"
    ],
    "wof:name":"Starvine Marvine",
    "wof:placetype":"venue"
},
  "geometry": {"coordinates":[-4.2841191292,55.8655204773],"type":"Point"}
}