{
  "type": "Feature",
  "properties": {
    "addr:full":"149-155 Ashley Road Poole Dorset BH14 9DN",
    "addr:housenumber":"149-155",
    "addr:postcode":"bh14 9dn",
    "addr:street":"Ashley Road",
    "iso:country":"GB",
    "sg:address":"149-155 Ashley Road",
    "sg:city":"Poole",
    "sg:classifiers":[
        {
            "category":"Autos & Motor Vehicles",
            "subcategory":"Motorcycle Sales",
            "type":"Retail Goods"
        }
    ],
    "sg:postcode":"BH14 9DN",
    "sg:province":"Dorset",
    "wof:name":"Roger Barretts Parkstone",
    "wof:placetype":"venue"
},
  "geometry": {"coordinates":[-1.9318059683,50.728263855],"type":"Point"}
}