{
  "type": "Feature",
  "properties": {
    "addr:full":"Owls Hall Farm, Blackmore End Braintree Essex CM7 4DF",
    "addr:housenumber":"farm blackmore",
    "addr:postcode":"cm7 4df",
    "addr:street":"Hall;End",
    "iso:country":"GB",
    "sg:address":"Owls Hall Farm, Blackmore End",
    "sg:city":"Braintree",
    "sg:classifiers":[
        {
            "category":"Professional",
            "subcategory":"Employment Agencies",
            "type":"Services"
        }
    ],
    "sg:phone":"+44 1371 850537",
    "sg:postcode":"CM7 4DF",
    "sg:province":"Essex",
    "sg:tags":[
        "agricultural",
        "advice"
    ],
    "wof:name":"H A Finbow",
    "wof:placetype":"venue"
},
  "geometry": {"coordinates":[0.553242,51.877758],"type":"Point"}
}