{
  "type": "Feature",
  "properties": {
    "addr:full":"57 The Ridgeway, Golders Grn London Greater London NW11 8QL",
    "addr:housenumber":"57",
    "addr:postcode":"nw11 8ql",
    "addr:street":"The Ridgeway Golders Grn",
    "iso:country":"GB",
    "sg:address":"57 The Ridgeway, Golders Grn",
    "sg:city":"London",
    "sg:classifiers":[
        {
            "category":"Health Services",
            "subcategory":"Doctor",
            "type":"Services"
        }
    ],
    "sg:phone":"+44 20 8458 8153",
    "sg:postcode":"NW11 8QL",
    "sg:province":"Greater London",
    "sg:tags":[
        "practitioners"
    ],
    "wof:name":"Dr J A Goldin",
    "wof:placetype":"venue"
},
  "geometry": {"coordinates":[-0.2021970004,51.572353363],"type":"Point"}
}