{
  "type": "Feature",
  "properties": {
    "iso:country":"GB",
    "sg:address":"127 Helme Lane, Meltham",
    "sg:city":"Huddersfield",
    "sg:classifiers":[
        {
            "category":"Professional",
            "subcategory":"Engineering",
            "type":"Services"
        }
    ],
    "sg:postcode":"HD9 5RJ",
    "sg:province":"South Yorkshire",
    "sg:tags":[
        "contractor",
        "electrical",
        "engineer"
    ],
    "wof:name":"M J Haigh Electrician",
    "wof:placetype":"venue"
},
  "geometry": {"coordinates":[-1.8501080275,53.5989151001],"type":"Point"}
}