{
  "type": "Feature",
  "properties": {
    "addr:full":"84 Station Rd Shrewsbury Shropshire SY4 5BL",
    "addr:housenumber":"84",
    "addr:postcode":"sy4 5bl",
    "addr:street":"Station Rd",
    "iso:country":"GB",
    "sg:address":"84 Station Rd",
    "sg:city":"Shrewsbury",
    "sg:classifiers":[
        {
            "category":"Place Of Worship",
            "type":"Public Place"
        }
    ],
    "sg:phone":"+44 1939 232404",
    "sg:postcode":"SY4 5BL",
    "sg:province":"Shropshire",
    "wof:name":"Bettisfield Methodist United Reformed Church",
    "wof:placetype":"venue"
},
  "geometry": {"coordinates":[-2.7200210094,52.8601570129],"type":"Point"}
}