{
  "type": "Feature",
  "properties": {
    "iso:country":"GB",
    "sg:address":"25 Victoria St",
    "sg:city":"Bristol",
    "sg:classifiers":[
        {
            "category":"Communications",
            "type":"Services"
        }
    ],
    "sg:phone":"+44 117 930 0606",
    "sg:postcode":"BS1 6AA",
    "sg:province":"City of Bristol",
    "sg:tags":[
        "audio-visual"
    ],
    "wof:name":"Sardis International PLC",
    "wof:placetype":"venue"
},
  "geometry": {"coordinates":[-2.5927920341,51.449508667],"type":"Point"}
}