{
  "type": "Feature",
  "properties": {
    "addr:full":"Glasshampton Monastery, Shrawley Worcester Herefordshire WR6 6TQ",
    "addr:postcode":"wr6 6tq",
    "iso:country":"GB",
    "sg:address":"Glasshampton Monastery, Shrawley",
    "sg:city":"Worcester",
    "sg:classifiers":[
        {
            "category":"Organizations",
            "subcategory":"Religious Organization",
            "type":"Services"
        }
    ],
    "sg:phone":"+44 1299 896345",
    "sg:postcode":"WR6 6TQ",
    "sg:province":"Herefordshire",
    "sg:tags":[
        "organisation"
    ],
    "wof:name":"Society of St. Francis",
    "wof:placetype":"venue"
},
  "geometry": {"coordinates":[-2.285599,52.282345],"type":"Point"}
}