{
  "type": "Feature",
  "properties": {
    "iso:country":"GB",
    "sg:address":"P O Box 51",
    "sg:city":"Middlesbrough",
    "sg:classifiers":[
        {
            "category":"Professional",
            "subcategory":"Employment Agencies",
            "type":"Services"
        }
    ],
    "sg:phone":"+44 1642 464877",
    "sg:postcode":"TS6 6YD",
    "sg:province":"North Yorkshire",
    "sg:tags":[
        "consultant"
    ],
    "wof:name":"Friday (UK) Ltd",
    "wof:placetype":"venue"
},
  "geometry": {"coordinates":[-1.175989,54.578442],"type":"Point"}
}