{
  "type": "Feature",
  "properties": {
    "addr:full":"4 East Cliff Road Tunbridge Wells Kent TN4 9AD",
    "addr:housenumber":"4",
    "addr:postcode":"tn4 9ad",
    "addr:street":"East Cliff Road",
    "iso:country":"GB",
    "sg:address":"4 East Cliff Road",
    "sg:city":"Tunbridge Wells",
    "sg:classifiers":[
        {
            "category":"Professional",
            "subcategory":"Computer Services",
            "type":"Services"
        }
    ],
    "sg:postcode":"TN4 9AD",
    "sg:province":"Kent",
    "sg:tags":[
        "system",
        "software"
    ],
    "wof:name":"Brackendale Technology Ltd.",
    "wof:placetype":"venue"
},
  "geometry": {"coordinates":[0.261279,51.144958],"type":"Point"}
}