{
  "type": "Feature",
  "properties": {
    "iso:country":"GB",
    "sg:address":"12 Silver Street",
    "sg:city":"Dursley",
    "sg:classifiers":[
        {
            "category":"Shopping",
            "subcategory":"Thrift Store",
            "type":"Retail Goods"
        }
    ],
    "sg:phone":"+44 1453 544160",
    "sg:postcode":"GL11 4ND",
    "sg:province":"Gloucestershire",
    "sg:tags":[
        "shop",
        "charity"
    ],
    "wof:name":"Break Charity Shop",
    "wof:placetype":"venue"
},
  "geometry": {"coordinates":[-2.353663,51.681011],"type":"Point"}
}