{
  "type": "Feature",
  "properties": {
    "addr:full":"The Old Fire Station, Portland Road Hythe Kent CT21 6EG",
    "addr:postcode":"ct21 6eg",
    "addr:street":"Portland Road",
    "iso:country":"GB",
    "sg:address":"The Old Fire Station, Portland Road",
    "sg:city":"Hythe",
    "sg:classifiers":[
        {
            "category":"Retail",
            "subcategory":"Auto Repair",
            "type":"Services"
        }
    ],
    "sg:phone":"+44 1303 263732",
    "sg:postcode":"CT21 6EG",
    "sg:province":"Kent",
    "sg:tags":[
        "modification",
        "garage"
    ],
    "wof:name":"Hythe Garage",
    "wof:placetype":"venue"
},
  "geometry": {"coordinates":[1.0804810524,51.0708274841],"type":"Point"}
}