{
  "type": "Feature",
  "properties": {
    "iso:country":"GB",
    "sg:address":"Brookmans Park",
    "sg:city":"Hatfield",
    "sg:classifiers":[
        {
            "category":"Professional",
            "subcategory":"Employment Agencies",
            "type":"Services"
        }
    ],
    "sg:phone":"+44 1707 644551",
    "sg:postcode":"AL9 7UW",
    "sg:province":"Hertfordshire",
    "sg:tags":[
        "consultant"
    ],
    "wof:name":"O & G Personnel",
    "wof:placetype":"venue"
},
  "geometry": {"coordinates":[-0.20015,51.719238],"type":"Point"}
}