{
  "type": "Feature",
  "properties": {
    "addr:full":"Unit 57 Bellwin Drive, Flixborough Industrial Estate, Flixborough Scunthorpe Lincolnshire DN15 8SN",
    "addr:housenumber":"unit 57",
    "addr:postcode":"dn15 8sn",
    "addr:street":"Bellwin Drive Flixborough Industrial Estate",
    "iso:country":"GB",
    "sg:address":"Unit 57 Bellwin Drive, Flixborough Industrial Estate, Flixborough",
    "sg:city":"Scunthorpe",
    "sg:classifiers":[
        {
            "category":"Communications",
            "type":"Services"
        }
    ],
    "sg:phone":"+44 1724 275500",
    "sg:postcode":"DN15 8SN",
    "sg:province":"Lincolnshire",
    "sg:tags":[
        "telecommunication"
    ],
    "wof:name":"EXi telecoms",
    "wof:placetype":"venue"
},
  "geometry": {"coordinates":[-0.697859,53.620209],"type":"Point"}
}