{
  "type": "Feature",
  "properties": {
    "addr:full":"112 The Stow Shopping Centre Harlow Essex CM20 3AS",
    "addr:housenumber":"112",
    "addr:postcode":"cm20 3as",
    "addr:street":"The;Shopping Centre",
    "iso:country":"GB",
    "sg:address":"112 The Stow Shopping Centre",
    "sg:city":"Harlow",
    "sg:classifiers":[
        {
            "category":"Shopping",
            "subcategory":"Bicycles & Sporting Goods",
            "type":"Retail Goods"
        }
    ],
    "sg:postcode":"CM20 3AS",
    "sg:province":"Essex",
    "sg:tags":[
        "cycle",
        "accessory"
    ],
    "wof:name":"Bush Bikes",
    "wof:placetype":"venue"
},
  "geometry": {"coordinates":[0.1140239984,51.7759666443],"type":"Point"}
}