{
  "type": "Feature",
  "properties": {
    "iso:country":"GB",
    "sg:address":"Frogend, Bishops Frome",
    "sg:city":"Worcester",
    "sg:classifiers":[
        {
            "category":"Farming",
            "subcategory":"Livestock Farm",
            "type":"Manufacturing & Wholesale Goods"
        }
    ],
    "sg:postcode":"WR6 5BT",
    "sg:province":"Herefordshire",
    "sg:tags":[
        "others"
    ],
    "wof:name":"Charles J Pudge",
    "wof:placetype":"venue"
},
  "geometry": {"coordinates":[-2.494824,52.133301],"type":"Point"}
}