{
  "type": "Feature",
  "properties": {
    "addr:full":"Unit 2 The Airfield, Little Staughton Bedford Bedfordshire MK44 2BN",
    "addr:housenumber":"unit 2;staughton",
    "addr:postcode":"mk44 2bn",
    "addr:street":"The;Bedfordshire",
    "iso:country":"GB",
    "sg:address":"Unit 2 The Airfield, Little Staughton",
    "sg:city":"Bedford",
    "sg:classifiers":[
        {
            "category":"Wholesale",
            "subcategory":"Motor Vehicles",
            "type":"Manufacturing & Wholesale Goods"
        }
    ],
    "sg:phone":"+44 1234 378109",
    "sg:postcode":"MK44 2BN",
    "sg:province":"Bedfordshire",
    "sg:tags":[
        "aircraft",
        "spare"
    ],
    "wof:name":"Regale Ltd",
    "wof:placetype":"venue"
},
  "geometry": {"coordinates":[-0.377565,52.21822],"type":"Point"}
}