{
  "type": "Feature",
  "properties": {
    "addr:full":"Manor Farm Road Birmingham West Midlands B11 2HX",
    "addr:postcode":"b11 2hx",
    "addr:street":"Manor Farm Road",
    "iso:country":"GB",
    "sg:address":"Manor Farm Road",
    "sg:city":"Birmingham",
    "sg:classifiers":[
        {
            "category":"Autos & Motor Vehicles",
            "subcategory":"Automobile Sales",
            "type":"Retail Goods"
        }
    ],
    "sg:phone":"+44 121 708 1522",
    "sg:postcode":"B11 2HX",
    "sg:province":"West Midlands",
    "sg:tags":[
        "car"
    ],
    "wof:name":"G V S",
    "wof:placetype":"venue"
},
  "geometry": {"coordinates":[-1.848239,52.454075],"type":"Point"}
}