{
  "type": "Feature",
  "properties": {
    "addr:full":"2 Hill Rise, Hinchley Wood Esher Surrey KT10 0AL",
    "addr:housenumber":"2",
    "addr:postcode":"kt10 0al",
    "addr:street":"Hill Rise",
    "iso:country":"GB",
    "sg:address":"2 Hill Rise, Hinchley Wood",
    "sg:city":"Esher",
    "sg:classifiers":[
        {
            "category":"Professional",
            "subcategory":"Business Services",
            "type":"Services"
        }
    ],
    "sg:phone":"+44 1932 223692",
    "sg:postcode":"KT10 0AL",
    "sg:province":"Surrey",
    "sg:tags":[
        "import",
        "export",
        "agent"
    ],
    "wof:name":"Pamleen Trading",
    "wof:placetype":"venue"
},
  "geometry": {"coordinates":[-0.3264960051,51.3774757385],"type":"Point"}
}