{
  "type": "Feature",
  "properties": {
    "addr:full":"43 Walton Avenue Blyth Northumberland NE24 5HB",
    "addr:housenumber":"43",
    "addr:postcode":"ne24 5hb",
    "addr:street":"Walton Avenue;Northumberland",
    "iso:country":"GB",
    "sg:address":"43 Walton Avenue",
    "sg:city":"Blyth",
    "sg:classifiers":[
        {
            "category":"Professional",
            "subcategory":"Art Services",
            "type":"Services"
        },
        {
            "category":"Building & Trades",
            "subcategory":"Construction",
            "type":"Services"
        }
    ],
    "sg:phone":"+44 1670 544115",
    "sg:postcode":"NE24 5HB",
    "sg:province":"Northumberland",
    "sg:tags":[
        "decorator",
        "painter"
    ],
    "wof:name":"Bill Morris",
    "wof:placetype":"venue"
},
  "geometry": {"coordinates":[-1.524251,55.128887],"type":"Point"}
}