{
  "type": "Feature",
  "properties": {
    "addr:full":"69 The Broadway Loughton Essex IG10 3SP",
    "addr:housenumber":"69",
    "addr:postcode":"ig10 3sp",
    "addr:street":"The Broadway",
    "iso:country":"GB",
    "sg:address":"69 The Broadway",
    "sg:city":"Loughton",
    "sg:classifiers":[
        {
            "category":"Cinema",
            "subcategory":"Movie Rental",
            "type":"Entertainment"
        }
    ],
    "sg:phone":"+44 20 8508 3348",
    "sg:postcode":"IG10 3SP",
    "sg:province":"Essex",
    "sg:tags":[
        "video",
        "library"
    ],
    "wof:name":"Pinewood Video",
    "wof:placetype":"venue"
},
  "geometry": {"coordinates":[0.083944,51.64806],"type":"Point"}
}