{
  "type": "Feature",
  "properties": {
    "addr:full":"12-14 Oxford St Ripley Derbyshire DE5 3AG",
    "addr:housenumber":"12-14",
    "addr:postcode":"de5 3ag",
    "addr:street":"Oxford St",
    "iso:country":"GB",
    "sg:address":"12-14 Oxford St",
    "sg:city":"Ripley",
    "sg:classifiers":[
        {
            "category":"Shopping",
            "subcategory":"Pharmacy",
            "type":"Retail Goods"
        }
    ],
    "sg:phone":"+44 1773 570076",
    "sg:postcode":"DE5 3AG",
    "sg:province":"Derbyshire",
    "sg:tags":[
        "store",
        "drug"
    ],
    "wof:name":"Lloyds Supersave Drugstore",
    "wof:placetype":"venue"
},
  "geometry": {"coordinates":[-1.4058660269,53.0498199463],"type":"Point"}
}