{
  "type": "Feature",
  "properties": {
    "addr:full":"St John's House, 12-18 Queen Street Manchester Greater Manchester M2 5HR",
    "addr:housenumber":"12-18",
    "addr:postcode":"m2 5hr",
    "addr:street":"Queen Street",
    "iso:country":"GB",
    "sg:address":"St John's House, 12-18 Queen Street",
    "sg:city":"Manchester",
    "sg:classifiers":[
        {
            "category":"Professional",
            "subcategory":"Management & Consulting",
            "type":"Services"
        }
    ],
    "sg:phone":"+44 161 831 9722",
    "sg:postcode":"M2 5HR",
    "sg:province":"Greater Manchester",
    "sg:tags":[
        "consultant",
        "business"
    ],
    "wof:name":"North Consulting",
    "wof:placetype":"venue"
},
  "geometry": {"coordinates":[-2.163895,53.507397],"type":"Point"}
}