{
  "type": "Feature",
  "properties": {
    "addr:full":"26 Lexton Gardns London Greater London SW12 0AY",
    "addr:housenumber":"26",
    "addr:postcode":"sw12 0ay",
    "addr:street":"Lexton Gardns",
    "iso:country":"GB",
    "sg:address":"26 Lexton Gardns",
    "sg:city":"London",
    "sg:classifiers":[
        {
            "category":"Professional",
            "subcategory":"Accounting & Tax Preparation",
            "type":"Services"
        }
    ],
    "sg:phone":"+44 20 8678 1287",
    "sg:postcode":"SW12 0AY",
    "sg:province":"Greater London",
    "sg:tags":[
        "accountant"
    ],
    "wof:name":"E A Wong & Co",
    "wof:placetype":"venue"
},
  "geometry": {"coordinates":[-0.131131,51.4445],"type":"Point"}
}