{
  "type": "Feature",
  "properties": {
    "addr:full":"139 Well St Hackney Greater London E9 7LJ",
    "addr:housenumber":"139",
    "addr:postcode":"e9 7lj",
    "addr:street":"Well St",
    "iso:country":"GB",
    "sg:address":"139 Well St",
    "sg:city":"Hackney",
    "sg:classifiers":[
        {
            "category":"Health Services",
            "subcategory":"Dentist",
            "type":"Services"
        }
    ],
    "sg:phone":"+44 20 8985 9828",
    "sg:postcode":"E9 7LJ",
    "sg:province":"Greater London",
    "wof:name":"C.T.J Donnelly",
    "wof:placetype":"venue"
},
  "geometry": {"coordinates":[-0.0491,51.54216],"type":"Point"}
}