{
  "type": "Feature",
  "properties": {
    "addr:full":"Fourth Avenue, Garston Watford Hertfordshire WD25 9QB",
    "addr:postcode":"wd25 9qb",
    "addr:street":"Fourth Avenue",
    "iso:country":"GB",
    "sg:address":"Fourth Avenue, Garston",
    "sg:city":"Watford",
    "sg:classifiers":[
        {
            "category":"Arts & Performance",
            "subcategory":"Music",
            "type":"Entertainment"
        }
    ],
    "sg:phone":"+44 1923 677358",
    "sg:postcode":"WD25 9QB",
    "sg:province":"Hertfordshire",
    "sg:tags":[
        "mobile",
        "disco"
    ],
    "wof:name":"A A Rhythm Masters Entertainment",
    "wof:placetype":"venue"
},
  "geometry": {"coordinates":[-0.382659,51.687321],"type":"Point"}
}