{
  "type": "Feature",
  "properties": {
    "addr:full":"Albion Road Scarborough North Yorkshire YO11 2BT",
    "addr:postcode":"yo11 2bt",
    "addr:street":"Albion Road",
    "iso:country":"GB",
    "sg:address":"Albion Road",
    "sg:city":"Scarborough",
    "sg:classifiers":[
        {
            "category":"Retail",
            "subcategory":"Auto Repair",
            "type":"Services"
        }
    ],
    "sg:phone":"+44 1723 501539",
    "sg:postcode":"YO11 2BT",
    "sg:province":"North Yorkshire",
    "sg:tags":[
        "modification",
        "garage",
        "related"
    ],
    "wof:name":"T & S Motors",
    "wof:placetype":"venue"
},
  "geometry": {"coordinates":[-0.402097,54.27499],"type":"Point"}
}