{
  "type": "Feature",
  "properties": {
    "addr:full":"New St Chambers, 67a New Street Birmingham West Midlands B2 4DU",
    "addr:housenumber":"67a",
    "addr:postcode":"4du",
    "addr:street":"New St;New Street",
    "iso:country":"GB",
    "sg:address":"New St Chambers, 67a New Street",
    "sg:city":"Birmingham",
    "sg:classifiers":[
        {
            "category":"Professional",
            "subcategory":"Employment Agencies",
            "type":"Services"
        }
    ],
    "sg:phone":"+44 121 632 4743",
    "sg:postcode":"B2 4DU",
    "sg:province":"West Midlands",
    "sg:tags":[
        "consultant"
    ],
    "wof:name":"First Personnel Group Services",
    "wof:placetype":"venue"
},
  "geometry": {"coordinates":[-1.90084,52.479328],"type":"Point"}
}