{
  "type": "Feature",
  "properties": {
    "addr:full":"Oxhey Dr Health Centre, Oxhey Dr Watford Hertfordshire WD19 7SF",
    "addr:postcode":"wd19 7sf",
    "addr:street":"Oxhey;Oxhey Dr",
    "iso:country":"GB",
    "sg:address":"Oxhey Dr Health Centre, Oxhey Dr",
    "sg:city":"Watford",
    "sg:classifiers":[
        {
            "category":"Health Services",
            "subcategory":"Doctor",
            "type":"Services"
        }
    ],
    "sg:phone":"+44 20 8421 5224",
    "sg:postcode":"WD19 7SF",
    "sg:province":"Hertfordshire",
    "sg:tags":[
        "practitioners"
    ],
    "wof:name":"North West Herts Health Authority",
    "wof:placetype":"venue"
},
  "geometry": {"coordinates":[-0.387454,51.626324],"type":"Point"}
}