{
  "type": "Feature",
  "properties": {
    "iso:country":"GB",
    "sg:address":"83 Stafford Street",
    "sg:city":"Willenhall",
    "sg:classifiers":[
        {
            "category":"Food & Beverages",
            "subcategory":"Bakery",
            "type":"Retail Goods"
        }
    ],
    "sg:phone":"+44 1902 603299",
    "sg:postcode":"WV13 1RT",
    "sg:province":"West Midlands",
    "sg:tags":[
        "baker"
    ],
    "wof:name":"Greggs Plc",
    "wof:placetype":"venue"
},
  "geometry": {"coordinates":[-2.056374,52.585178],"type":"Point"}
}