{
  "type": "Feature",
  "properties": {
    "addr:full":"The New Depot Workshop, Llanwhog Caersws Powys SY17 5JG",
    "addr:postcode":"sy17 5jg",
    "addr:street":"Caersws",
    "iso:country":"GB",
    "sg:address":"The New Depot Workshop, Llanwhog",
    "sg:city":"Caersws",
    "sg:classifiers":[
        {
            "category":"Manufacturing",
            "subcategory":"Metals",
            "type":"Manufacturing & Wholesale Goods"
        }
    ],
    "sg:phone":"+44 1686 688567",
    "sg:postcode":"SY17 5JG",
    "sg:province":"Powys",
    "sg:tags":[
        "steel",
        "fabricator",
        "erectors"
    ],
    "wof:name":"Griffiths & Evans",
    "wof:placetype":"venue"
},
  "geometry": {"coordinates":[-3.430329,52.516735],"type":"Point"}
}