{
  "type": "Feature",
  "properties": {
    "iso:country":"GB",
    "sg:address":"141 North End",
    "sg:city":"Croydon",
    "sg:classifiers":[
        {
            "category":"Shopping",
            "subcategory":"Gifts & Souvenirs",
            "type":"Retail Goods"
        }
    ],
    "sg:phone":"+44 20 8686 2777",
    "sg:postcode":"CR0 1TN",
    "sg:province":"Surrey",
    "sg:tags":[
        "poster",
        "card"
    ],
    "wof:name":"Celebration Cards Ltd.",
    "wof:placetype":"venue"
},
  "geometry": {"coordinates":[-0.1023269966,51.3771820068],"type":"Point"}
}