{
  "type": "Feature",
  "properties": {
    "addr:full":"30-36 Peverill St, Radford Nottingham Nottinghamshire NG7 4AL",
    "addr:housenumber":"30-36",
    "addr:postcode":"ng7 4al",
    "addr:street":"Peverill St",
    "iso:country":"GB",
    "sg:address":"30-36 Peverill St, Radford",
    "sg:city":"Nottingham",
    "sg:classifiers":[
        {
            "category":"Recreation",
            "subcategory":"Arcade",
            "type":"Entertainment"
        }
    ],
    "sg:phone":"+44 115 942 1420",
    "sg:postcode":"NG7 4AL",
    "sg:province":"Nottinghamshire",
    "sg:tags":[
        "machine",
        "amusement"
    ],
    "wof:name":"G & S Leisure",
    "wof:placetype":"venue"
},
  "geometry": {"coordinates":[-1.16832,52.960255],"type":"Point"}
}