{
  "type": "Feature",
  "properties": {
    "iso:country":"GB",
    "sg:address":"2 Atholl Place",
    "sg:city":"Perth",
    "sg:classifiers":[
        {
            "category":"Professional",
            "subcategory":"Accounting & Tax Preparation",
            "type":"Services"
        }
    ],
    "sg:phone":"+44 1738 633944",
    "sg:postcode":"PH1 5ND",
    "sg:province":"Perth and Kinross",
    "sg:tags":[
        "accountant"
    ],
    "wof:name":"J Steele",
    "wof:placetype":"venue"
},
  "geometry": {"coordinates":[-3.4293489456,56.3989105225],"type":"Point"}
}