{
  "type": "Feature",
  "properties": {
    "iso:country":"GB",
    "sg:address":"Unit 7 Valley Mills, Whitehall Road, Drighlington",
    "sg:city":"Bradford",
    "sg:classifiers":[
        {
            "category":"Cafe",
            "type":"Food & Drink"
        }
    ],
    "sg:phone":"+44 113 285 2052",
    "sg:postcode":"BD11 1NQ",
    "sg:province":"West Yorkshire",
    "sg:tags":[
        "tea",
        "room"
    ],
    "wof:name":"Snack Factory",
    "wof:placetype":"venue"
},
  "geometry": {"coordinates":[-1.662250042,53.7565917969],"type":"Point"}
}