{
  "type": "Feature",
  "properties": {
    "iso:country":"GB",
    "sg:address":"64 High Street",
    "sg:city":"Johnstone",
    "sg:classifiers":[
        {
            "category":"Building & Trades",
            "subcategory":"Landscaping Services",
            "type":"Services"
        }
    ],
    "sg:phone":"+44 1505 336813",
    "sg:postcode":"PA5 8SG",
    "sg:province":"Renfrewshire",
    "sg:tags":[
        "gardening"
    ],
    "wof:name":"Flower Pot Garden Maintenance",
    "wof:placetype":"venue"
},
  "geometry": {"coordinates":[-4.513985157,55.8372840881],"type":"Point"}
}