{
  "type": "Feature",
  "properties": {
    "iso:country":"GB",
    "sg:address":"2 Ferry Road, Hythe",
    "sg:city":"Southampton",
    "sg:classifiers":[
        {
            "category":"Personal",
            "subcategory":"Beauty Salon",
            "type":"Services"
        },
        {
            "category":"Personal",
            "subcategory":"Barber",
            "type":"Services"
        }
    ],
    "sg:phone":"+44 23 8020 7720",
    "sg:postcode":"SO45 5GD",
    "sg:province":"Hampshire",
    "sg:tags":[
        "unisex",
        "hairdresser"
    ],
    "wof:name":"Head Quarters Hair Design",
    "wof:placetype":"venue"
},
  "geometry": {"coordinates":[-1.405189,50.86536],"type":"Point"}
}