{
  "type": "Feature",
  "properties": {
    "iso:country":"GB",
    "sg:address":"Brook Lane, Radcliffe Road, Gamston",
    "sg:city":"Nottingham",
    "sg:classifiers":[
        {
            "category":"Fast Food",
            "type":"Food & Drink"
        }
    ],
    "sg:phone":"+44 115 982 0638",
    "sg:postcode":"NG2 6NR",
    "sg:province":"Nottinghamshire",
    "sg:tags":[
        "away",
        "take"
    ],
    "wof:name":"H Broadhead",
    "wof:placetype":"venue"
},
  "geometry": {"coordinates":[-1.103499,52.927338],"type":"Point"}
}