{
  "type": "Feature",
  "properties": {
    "iso:country":"GB",
    "sg:address":"Lazy Acre, The Orchard, Stanton Drew",
    "sg:city":"Bristol",
    "sg:classifiers":[
        {
            "category":"Professional",
            "subcategory":"Business Services",
            "type":"Services"
        }
    ],
    "sg:phone":"+44 1275 333115",
    "sg:postcode":"BS39 4DS",
    "sg:province":"Somerset",
    "sg:tags":[
        "agent",
        "manufacturers'"
    ],
    "wof:name":"T M & J Shattock (Marketing & Manufacturers Agents)",
    "wof:placetype":"venue"
},
  "geometry": {"coordinates":[-2.580069,51.366444],"type":"Point"}
}