{
  "type": "Feature",
  "properties": {
    "addr:full":"65a Laighstonehall Road Hamilton South Lanarkshire ML3 8PD",
    "addr:housenumber":"65a",
    "addr:postcode":"ml3 8pd",
    "addr:street":"Laighstonehall Road",
    "iso:country":"GB",
    "sg:address":"65a Laighstonehall Road",
    "sg:city":"Hamilton",
    "sg:classifiers":[
        {
            "category":"Fast Food",
            "type":"Food & Drink"
        }
    ],
    "sg:phone":"+44 1698 281705",
    "sg:postcode":"ML3 8PD",
    "sg:province":"South Lanarkshire",
    "sg:tags":[
        "away",
        "take"
    ],
    "wof:name":"Tandoori Mania",
    "wof:placetype":"venue"
},
  "geometry": {"coordinates":[-4.062589,55.76725],"type":"Point"}
}