{
  "type": "Feature",
  "properties": {
    "addr:full":"Q E 2 Law Courts, 1 Newton St Birmingham West Midlands B4 7NA",
    "addr:housenumber":"2;1",
    "addr:postcode":"b4 7na",
    "addr:street":"E;Courts;St",
    "iso:country":"GB",
    "sg:address":"Q E 2 Law Courts, 1 Newton St",
    "sg:city":"Birmingham",
    "sg:classifiers":[
        {
            "category":"Government",
            "subcategory":"Court House",
            "type":"Public Place"
        }
    ],
    "sg:phone":"+44 121 681 3300",
    "sg:postcode":"B4 7NA",
    "sg:province":"West Midlands",
    "wof:name":"Birmingham Crown Court",
    "wof:placetype":"venue"
},
  "geometry": {"coordinates":[-1.8941700459,52.4830589294],"type":"Point"}
}