{
  "type": "Feature",
  "properties": {
    "iso:country":"GB",
    "sg:address":"68 Canterbury Road",
    "sg:city":"Herne Bay",
    "sg:classifiers":[
        {
            "category":"Shopping",
            "subcategory":"Shoes",
            "type":"Retail Goods"
        }
    ],
    "sg:phone":"+44 1227 361507",
    "sg:postcode":"CT6 5SB",
    "sg:province":"Kent",
    "sg:tags":[
        "shop"
    ],
    "wof:name":"Colemans Industrial Ltd.",
    "wof:placetype":"venue"
},
  "geometry": {"coordinates":[1.13293,51.368221],"type":"Point"}
}