{
  "type": "Feature",
  "properties": {
    "addr:full":"28 Thirsk Road Northallerton North Yorkshire DL6 1PH",
    "addr:housenumber":"28",
    "addr:postcode":"dl6 1ph",
    "addr:street":"Thirsk Road",
    "iso:country":"GB",
    "sg:address":"28 Thirsk Road",
    "sg:city":"Northallerton",
    "sg:classifiers":[
        {
            "category":"Health Services",
            "subcategory":"Nursing And Care Facility",
            "type":"Services"
        }
    ],
    "sg:phone":"+44 1609 780362",
    "sg:postcode":"DL6 1PH",
    "sg:province":"North Yorkshire",
    "sg:tags":[
        "home"
    ],
    "wof:name":"Wellhall Ltd.",
    "wof:placetype":"venue"
},
  "geometry": {"coordinates":[-1.434083,54.334633],"type":"Point"}
}