{
  "type": "Feature",
  "properties": {
    "addr:full":"11 Earp Avenue Newark Nottinghamshire NG24 4DD",
    "addr:housenumber":"11",
    "addr:postcode":"ng24 4dd",
    "addr:street":"Earp Avenue",
    "iso:country":"GB",
    "sg:address":"11 Earp Avenue",
    "sg:city":"Newark",
    "sg:classifiers":[
        {
            "category":"Building & Trades",
            "subcategory":"Construction",
            "type":"Services"
        }
    ],
    "sg:postcode":"NG24 4DD",
    "sg:province":"Nottinghamshire",
    "sg:tags":[
        "glazier"
    ],
    "wof:name":"Riverside Glass & Glazing",
    "wof:placetype":"venue"
},
  "geometry": {"coordinates":[-0.8051589727,53.0683097839],"type":"Point"}
}