{
  "type": "Feature",
  "properties": {
    "iso:country":"GB",
    "sg:address":"Ensbury Avenue",
    "sg:city":"Bournemouth",
    "sg:classifiers":[
        {
            "category":"Education",
            "subcategory":"Special Training",
            "type":"Public Place"
        }
    ],
    "sg:phone":"+44 1202 518189",
    "sg:postcode":"BH10 4EP",
    "sg:province":"Dorset",
    "sg:tags":[
        "school"
    ],
    "wof:name":"Slades Farm Mixed Special School",
    "wof:placetype":"venue"
},
  "geometry": {"coordinates":[-1.890119,50.751431],"type":"Point"}
}