{
  "type": "Feature",
  "properties": {
    "addr:full":"Oxford Way Jarrow Tyne and Wear NE32 4XA",
    "addr:postcode":"ne32 4xa",
    "addr:street":"Oxford Way",
    "iso:country":"GB",
    "sg:address":"Oxford Way",
    "sg:city":"Jarrow",
    "sg:classifiers":[
        {
            "category":"Education",
            "subcategory":"School",
            "type":"Public Place"
        },
        {
            "category":"Government",
            "subcategory":"Office",
            "type":"Public Place"
        }
    ],
    "sg:phone":"+44 191 483 7879",
    "sg:postcode":"NE32 4XA",
    "sg:province":"Tyne and Wear",
    "sg:tags":[
        "local",
        "authority"
    ],
    "wof:name":"Fellgate Autistic Unit",
    "wof:placetype":"venue"
},
  "geometry": {"coordinates":[-1.4899840355,54.9523696899],"type":"Point"}
}