{
  "type": "Feature",
  "properties": {
    "iso:country":"GB",
    "sg:address":"2a High Street, Gwersyllt",
    "sg:city":"Wrexham",
    "sg:classifiers":[
        {
            "category":"Taxi",
            "type":"Transportation"
        },
        {
            "category":"Military Area",
            "subcategory":"Air Force Base",
            "type":"Public Place"
        }
    ],
    "sg:phone":"+44 1978 751444",
    "sg:postcode":"LL11 4LA",
    "sg:province":"Wrexham",
    "sg:tags":[
        "mini",
        "hire",
        "private",
        "cab"
    ],
    "wof:name":"ACE TAXIS",
    "wof:placetype":"venue"
},
  "geometry": {"coordinates":[-3.016053,53.072987],"type":"Point"}
}