{
  "type": "Feature",
  "properties": {
    "addr:full":"57-59 Great Darkgate Street Aberystwyth Ceredigion SY23 1DW",
    "addr:housenumber":"57-59",
    "addr:postcode":"sy23 1dw",
    "addr:street":"Great Darkgate Street",
    "iso:country":"GB",
    "sg:address":"57-59 Great Darkgate Street",
    "sg:city":"Aberystwyth",
    "sg:classifiers":[
        {
            "category":"Bars & Pubs",
            "type":"Food & Drink"
        }
    ],
    "sg:phone":"+44 1970 617878",
    "sg:postcode":"SY23 1DW",
    "sg:province":"Ceredigion",
    "sg:tags":[
        "pubs",
        "inn"
    ],
    "wof:name":"Angel Inn",
    "wof:placetype":"venue"
},
  "geometry": {"coordinates":[-4.0844941139,52.4147186279],"type":"Point"}
}