{
  "type": "Feature",
  "properties": {
    "iso:country":"GB",
    "sg:address":"Maurys Lane, West Wellow",
    "sg:city":"Romsey",
    "sg:classifiers":[
        {
            "category":"Professional",
            "subcategory":"Engineering",
            "type":"Services"
        }
    ],
    "sg:phone":"+44 1794 322261",
    "sg:postcode":"SO51 6DB",
    "sg:province":"Hampshire",
    "sg:tags":[
        "contractor",
        "electrical",
        "engineer"
    ],
    "wof:name":"T Windess Ltd.",
    "wof:placetype":"venue"
},
  "geometry": {"coordinates":[-1.587326,50.974628],"type":"Point"}
}