{
  "type": "Feature",
  "properties": {
    "addr:full":"341 Muswell Hill, Broadway London Greater London N10 1BX",
    "addr:housenumber":"341",
    "addr:postcode":"n10 1bx",
    "addr:street":"Muswell Hill Broadway",
    "iso:country":"GB",
    "sg:address":"341 Muswell Hill, Broadway",
    "sg:city":"London",
    "sg:classifiers":[
        {
            "category":"Building & Trades",
            "subcategory":"Construction",
            "type":"Services"
        }
    ],
    "sg:postcode":"N10 1BX",
    "sg:province":"Greater London",
    "sg:tags":[
        "builder"
    ],
    "wof:name":"Molloy & Lynskey Ltd.",
    "wof:placetype":"venue"
},
  "geometry": {"coordinates":[-0.1435859948,51.5926361084],"type":"Point"}
}