{
  "type": "Feature",
  "properties": {
    "iso:country":"GB",
    "sg:address":"Derby Works, Shrivenham Road, Highworth",
    "sg:city":"Swindon",
    "sg:classifiers":[
        {
            "category":"Autos & Motor Vehicles",
            "subcategory":"Auto Supplies",
            "type":"Retail Goods"
        }
    ],
    "sg:phone":"+44 1793 764901",
    "sg:postcode":"SN6 7BZ",
    "sg:province":"Gloucestershire",
    "sg:tags":[
        "tyre"
    ],
    "wof:name":"Manor Tyres",
    "wof:placetype":"venue"
},
  "geometry": {"coordinates":[-1.7119389772,51.6308441162],"type":"Point"}
}