{
  "type": "Feature",
  "properties": {
    "iso:country":"GB",
    "sg:address":"St Albans Road",
    "sg:city":"Darwen",
    "sg:classifiers":[
        {
            "category":"Education",
            "subcategory":"School",
            "type":"Public Place"
        }
    ],
    "sg:phone":"+44 1254 701336",
    "sg:postcode":"BB3 0HY",
    "sg:province":"Lancashire",
    "sg:tags":[
        "local",
        "authority"
    ],
    "wof:name":"St Cuthberts C Of E Primary School",
    "wof:placetype":"venue"
},
  "geometry": {"coordinates":[-2.480404,53.707985],"type":"Point"}
}