{
  "type": "Feature",
  "properties": {
    "iso:country":"GB",
    "sg:address":"Tyburn Rd",
    "sg:city":"Birmingham",
    "sg:classifiers":[
        {
            "category":"Military Area",
            "subcategory":"Air Force Base",
            "type":"Public Place"
        }
    ],
    "sg:phone":"+44 121 350 4444",
    "sg:postcode":"B24 8NN",
    "sg:province":"West Midlands",
    "sg:tags":[
        "taxi",
        "hire",
        "private"
    ],
    "wof:name":"Warmley Cars",
    "wof:placetype":"venue"
},
  "geometry": {"coordinates":[-1.835584,52.509811],"type":"Point"}
}