{
  "type": "Feature",
  "properties": {
    "addr:full":"1 Hobart Rd Hayes Greater London UB4 9LY",
    "addr:housenumber":"1",
    "addr:postcode":"ub4 9ly",
    "addr:street":"Hobart Rd",
    "iso:country":"GB",
    "sg:address":"1 Hobart Rd",
    "sg:city":"Hayes",
    "sg:classifiers":[
        {
            "category":"Professional",
            "subcategory":"Engineering",
            "type":"Services"
        }
    ],
    "sg:phone":"+44 20 8845 9573",
    "sg:postcode":"UB4 9LY",
    "sg:province":"Greater London",
    "sg:tags":[
        "contractor",
        "electrical",
        "engineer"
    ],
    "wof:name":"V Petford",
    "wof:placetype":"venue"
},
  "geometry": {"coordinates":[-0.391005,51.528004],"type":"Point"}
}