{
  "type": "Feature",
  "properties": {
    "addr:full":"74 Clifton York East Riding of Yorkshire YO3 6AW",
    "addr:housenumber":"74",
    "addr:postcode":"yo3 6aw",
    "addr:street":"Clifton York",
    "iso:country":"GB",
    "sg:address":"74 Clifton",
    "sg:city":"York",
    "sg:classifiers":[
        {
            "category":"Health Services",
            "subcategory":"Optometrist",
            "type":"Services"
        }
    ],
    "sg:phone":"+44 1904 641922",
    "sg:postcode":"YO3 6AW",
    "sg:province":"East Riding of Yorkshire",
    "sg:tags":[
        "optician"
    ],
    "wof:name":"I S Anderson",
    "wof:placetype":"venue"
},
  "geometry": {"coordinates":[-1.0978300571,53.9706192017],"type":"Point"}
}