{
  "type": "Feature",
  "properties": {
    "addr:full":"220 Norwood Rd Tulse Hill Greater London SE27 9BU",
    "addr:housenumber":"220",
    "addr:postcode":"se27 9bu",
    "addr:street":"Norwood Rd Tulse Hill",
    "iso:country":"GB",
    "sg:address":"220 Norwood Rd",
    "sg:city":"Tulse Hill",
    "sg:classifiers":[
        {
            "category":"Personal",
            "subcategory":"Beauty Salon",
            "type":"Services"
        }
    ],
    "sg:phone":"+44 20 8766 6036",
    "sg:postcode":"SE27 9BU",
    "sg:province":"Greater London",
    "sg:tags":[
        "unisex",
        "hairdresser"
    ],
    "wof:name":"City Shapers Hair Salon",
    "wof:placetype":"venue"
},
  "geometry": {"coordinates":[-0.106119,51.438534],"type":"Point"}
}