{
  "type": "Feature",
  "properties": {
    "iso:country":"GB",
    "sg:address":"Lodgeworthy Farm, Bridgerule",
    "sg:city":"Holsworthy",
    "sg:classifiers":[
        {
            "category":"Farming",
            "subcategory":"Farm",
            "type":"Manufacturing & Wholesale Goods"
        }
    ],
    "sg:phone":"+44 1288 381351",
    "sg:postcode":"EX22 7EH",
    "sg:province":"Cornwall",
    "sg:tags":[
        "mixed",
        "crop"
    ],
    "wof:name":"G M & J B Hale & Son",
    "wof:placetype":"venue"
},
  "geometry": {"coordinates":[-4.455791,50.799919],"type":"Point"}
}