{
  "type": "Feature",
  "properties": {
    "addr:full":"246-248 Rooley Lane Bradford West Yorkshire BD5 8LB",
    "addr:housenumber":"246-248",
    "addr:postcode":"bd5 8lb",
    "addr:street":"Rooley Lane",
    "iso:country":"GB",
    "sg:address":"246-248 Rooley Lane",
    "sg:city":"Bradford",
    "sg:classifiers":[
        {
            "category":"Sports & Exercise",
            "subcategory":"Golf",
            "type":"Entertainment"
        }
    ],
    "sg:phone":"+44 1274 724449",
    "sg:postcode":"BD5 8LB",
    "sg:province":"West Yorkshire",
    "sg:tags":[
        "club",
        "course"
    ],
    "wof:name":"The West Bowling Golf Club Ltd.",
    "wof:placetype":"venue"
},
  "geometry": {"coordinates":[-1.748089,53.768478],"type":"Point"}
}