{
  "type": "Feature",
  "properties": {
    "addr:full":"1a Harwoods Road Watford Hertfordshire WD18 7RB",
    "addr:housenumber":"1a",
    "addr:postcode":"wd18 7rb",
    "addr:street":"Harwoods Road",
    "iso:country":"GB",
    "sg:address":"1a Harwoods Road",
    "sg:city":"Watford",
    "sg:classifiers":[
        {
            "category":"Professional",
            "subcategory":"Engineering",
            "type":"Services"
        }
    ],
    "sg:phone":"+44 1923 31112",
    "sg:postcode":"WD18 7RB",
    "sg:province":"Hertfordshire",
    "wof:name":"Harbour Jig & Tool Co. Ltd.",
    "wof:placetype":"venue"
},
  "geometry": {"coordinates":[-0.4044660032,51.6498527527],"type":"Point"}
}