{
  "type": "Feature",
  "properties": {
    "addr:full":"Foxhall Fields, East Bergholt Colchester Essex CO7 6QZ",
    "addr:postcode":"co7 6qz",
    "addr:street":"Foxhall Fields",
    "iso:country":"GB",
    "sg:address":"Foxhall Fields, East Bergholt",
    "sg:city":"Colchester",
    "sg:classifiers":[
        {
            "category":"Bars & Pubs",
            "type":"Food & Drink"
        }
    ],
    "sg:phone":"+44 1206 298298",
    "sg:postcode":"CO7 6QZ",
    "sg:province":"Essex",
    "sg:tags":[
        "pubs",
        "inn"
    ],
    "wof:name":"The Beehive Inn",
    "wof:placetype":"venue"
},
  "geometry": {"coordinates":[1.0205390453,51.9783401489],"type":"Point"}
}