{
  "type": "Feature",
  "properties": {
    "addr:full":"Four Paws, 112 Rylands Road Ashford Kent TN24 9LR",
    "addr:housenumber":"112",
    "addr:postcode":"tn24 9lr",
    "addr:street":"Rylands Road",
    "iso:country":"GB",
    "sg:address":"Four Paws, 112 Rylands Road",
    "sg:city":"Ashford",
    "sg:classifiers":[
        {
            "category":"Professional",
            "subcategory":"Art Services",
            "type":"Services"
        }
    ],
    "sg:postcode":"TN24 9LR",
    "sg:province":"Kent",
    "sg:tags":[
        "photographer"
    ],
    "wof:name":"Lintons Photographics",
    "wof:placetype":"venue"
},
  "geometry": {"coordinates":[0.88276,51.164391],"type":"Point"}
}