{
  "type": "Feature",
  "properties": {
    "addr:full":"Trevigue, Crackington Haven Bude Cornwall EX23 0LQ",
    "addr:postcode":"ex23 0lq",
    "iso:country":"GB",
    "sg:address":"Trevigue, Crackington Haven",
    "sg:city":"Bude",
    "sg:classifiers":[
        {
            "category":"Farming",
            "subcategory":"Dairy Farm",
            "type":"Manufacturing & Wholesale Goods"
        }
    ],
    "sg:postcode":"EX23 0LQ",
    "sg:province":"Cornwall",
    "wof:name":"K A Crocker & Sons",
    "wof:placetype":"venue"
},
  "geometry": {"coordinates":[-4.632869,50.741505],"type":"Point"}
}