{
  "type": "Feature",
  "properties": {
    "addr:full":"Station Rd Huddersfield West Yorkshire HD7 1AE",
    "addr:postcode":"hd7 1ae",
    "addr:street":"Station Rd",
    "iso:country":"GB",
    "sg:address":"Station Rd",
    "sg:city":"Huddersfield",
    "sg:classifiers":[
        {
            "category":"Retail",
            "subcategory":"Auto Repair",
            "type":"Services"
        }
    ],
    "sg:phone":"+44 1484 684854",
    "sg:postcode":"HD7 1AE",
    "sg:province":"West Yorkshire",
    "sg:tags":[
        "modification",
        "garage"
    ],
    "wof:name":"M Littlewood",
    "wof:placetype":"venue"
},
  "geometry": {"coordinates":[-1.783583,53.647945],"type":"Point"}
}