{
  "type": "Feature",
  "properties": {
    "addr:full":"Shaw Rd Dudley West Midlands DY2 8TS",
    "addr:postcode":"dy2 8ts",
    "addr:street":"Shaw Rd",
    "iso:country":"GB",
    "sg:address":"Shaw Rd",
    "sg:city":"Dudley",
    "sg:classifiers":[
        {
            "category":"Taxi",
            "type":"Transportation"
        }
    ],
    "sg:phone":"+44 1384 239494",
    "sg:postcode":"DY2 8TS",
    "sg:province":"West Midlands",
    "sg:tags":[
        "mini",
        "cab"
    ],
    "wof:name":"A K Taxis",
    "wof:placetype":"venue"
},
  "geometry": {"coordinates":[-2.085009,52.505436],"type":"Point"}
}