{
  "type": "Feature",
  "properties": {
    "addr:full":"30 Southwark St, Baseford Nottingham Nottinghamshire NG6 0DA",
    "addr:housenumber":"30",
    "addr:postcode":"ng6 0da",
    "addr:street":"Southwark St",
    "iso:country":"GB",
    "sg:address":"30 Southwark St, Baseford",
    "sg:city":"Nottingham",
    "sg:classifiers":[
        {
            "category":"Shopping",
            "subcategory":"Florist",
            "type":"Retail Goods"
        }
    ],
    "sg:postcode":"NG6 0DA",
    "sg:province":"Nottinghamshire",
    "wof:name":"Nichols,Gaynor,",
    "wof:placetype":"venue"
},
  "geometry": {"coordinates":[-1.180511,52.986279],"type":"Point"}
}