{
  "type": "Feature",
  "properties": {
    "addr:full":"Unit 61 Kyle Road Industrial Estate Irvine North Ayrshire KA12 8JN",
    "addr:housenumber":"unit 61",
    "addr:postcode":"ka12 8jn",
    "addr:street":"Kyle Road Industrial Estate",
    "iso:country":"GB",
    "sg:address":"Unit 61 Kyle Road Industrial Estate",
    "sg:city":"Irvine",
    "sg:classifiers":[
        {
            "category":"Professional",
            "subcategory":"Engineering",
            "type":"Services"
        }
    ],
    "sg:phone":"+44 1294 274296",
    "sg:postcode":"KA12 8JN",
    "sg:province":"North Ayrshire",
    "wof:name":"Hugh K Gillies (Construction Engineering Services) Ltd.",
    "wof:placetype":"venue"
},
  "geometry": {"coordinates":[-4.673259,55.601974],"type":"Point"}
}