{
  "type": "Feature",
  "properties": {
    "addr:full":"Coed Helen, Coed Helen Road Caernarfon Gwynedd LL54 5RS",
    "addr:postcode":"ll54 5rs",
    "addr:street":"Helen Road",
    "iso:country":"GB",
    "sg:address":"Coed Helen, Coed Helen Road",
    "sg:city":"Caernarfon",
    "sg:classifiers":[
        {
            "category":"Organizations",
            "subcategory":"Membership Organization",
            "type":"Services"
        }
    ],
    "sg:phone":"+44 1286 676770",
    "sg:postcode":"LL54 5RS",
    "sg:province":"Gwynedd",
    "sg:tags":[
        "club"
    ],
    "wof:name":"The Caravan Club Ltd.",
    "wof:placetype":"venue"
},
  "geometry": {"coordinates":[-4.277438,53.136555],"type":"Point"}
}