{
  "type": "Feature",
  "properties": {
    "addr:full":"12 Trafalgar Way, Erskine Industrial Estate Liverpool Merseyside L6 1NA",
    "addr:housenumber":"12",
    "addr:postcode":"l6 1na",
    "addr:street":"Trafalgar Way;Industrial Estate",
    "iso:country":"GB",
    "sg:address":"12 Trafalgar Way, Erskine Industrial Estate",
    "sg:city":"Liverpool",
    "sg:classifiers":[
        {
            "category":"Building & Trades",
            "subcategory":"Construction",
            "type":"Services"
        }
    ],
    "sg:phone":"+44 151 260 5545",
    "sg:postcode":"L6 1NA",
    "sg:province":"Merseyside",
    "sg:tags":[
        "paint",
        "household",
        "spraying"
    ],
    "wof:name":"Bodyshop Services Ltd.",
    "wof:placetype":"venue"
},
  "geometry": {"coordinates":[-2.9646039009,53.4125404358],"type":"Point"}
}