{
  "type": "Feature",
  "properties": {
    "iso:country":"GB",
    "sg:address":"324 Ropery Road",
    "sg:city":"Gainsborough",
    "sg:classifiers":[
        {
            "category":"Personal",
            "subcategory":"Beauty Salon",
            "type":"Services"
        }
    ],
    "sg:postcode":"DN21 2PD",
    "sg:province":"Lincolnshire",
    "sg:tags":[
        "unisex",
        "hairdresser"
    ],
    "wof:name":"The Trim Inn",
    "wof:placetype":"venue"
},
  "geometry": {"coordinates":[-0.7826009989,53.4071769714],"type":"Point"}
}