{
  "type": "Feature",
  "properties": {
    "addr:full":"200 St Albans Road Watford Hertfordshire WD24 5BH",
    "addr:housenumber":"200",
    "addr:postcode":"wd24 5bh",
    "addr:street":"St Albans Road",
    "iso:country":"GB",
    "sg:address":"200 St Albans Road",
    "sg:city":"Watford",
    "sg:classifiers":[
        {
            "category":"Shopping",
            "subcategory":"Gifts & Souvenirs",
            "type":"Retail Goods"
        }
    ],
    "sg:postcode":"WD24 5BH",
    "sg:province":"Hertfordshire",
    "sg:tags":[
        "poster",
        "card"
    ],
    "wof:name":"Regency Cards",
    "wof:placetype":"venue"
},
  "geometry": {"coordinates":[-0.396279,51.672371],"type":"Point"}
}