{
  "type": "Feature",
  "properties": {
    "addr:full":"Sontec House, Concorde Road Norwich Norfolk NR6 6BE",
    "addr:postcode":"nr6 6be",
    "addr:street":"Concorde Road Norwich Norfolk",
    "iso:country":"GB",
    "sg:address":"Sontec House, Concorde Road",
    "sg:city":"Norwich",
    "sg:classifiers":[
        {
            "category":"Retail",
            "subcategory":"Repair Shop",
            "type":"Services"
        }
    ],
    "sg:phone":"+44 1603 483675",
    "sg:postcode":"NR6 6BE",
    "sg:province":"Norfolk",
    "sg:tags":[
        "radio",
        "television",
        "video"
    ],
    "wof:name":"Sontec (Electronics) Ltd.",
    "wof:placetype":"venue"
},
  "geometry": {"coordinates":[1.287538,52.659866],"type":"Point"}
}