{
  "type": "Feature",
  "properties": {
    "addr:full":"7 Greville Street London Greater London EC1N 8PQ",
    "addr:housenumber":"7",
    "addr:postcode":"ec1n 8pq",
    "addr:street":"Greville Street",
    "iso:country":"GB",
    "sg:address":"7 Greville Street",
    "sg:city":"London",
    "sg:classifiers":[
        {
            "category":"Building & Trades",
            "subcategory":"Equipment Rental",
            "type":"Services"
        }
    ],
    "sg:phone":"+44 20 7831 6170",
    "sg:postcode":"EC1N 8PQ",
    "sg:province":"Greater London",
    "sg:tags":[
        "supply"
    ],
    "wof:name":"Hanron Jewellery",
    "wof:placetype":"venue"
},
  "geometry": {"coordinates":[-0.107119,51.519489],"type":"Point"}
}