{
  "type": "Feature",
  "properties": {
    "iso:country":"GB",
    "sg:address":"6th Floor 94 Hope St",
    "sg:city":"Glasgow",
    "sg:classifiers":[
        {
            "category":"Social Services",
            "type":"Services"
        }
    ],
    "sg:phone":"+44 141 248 4537",
    "sg:postcode":"G2 6PH",
    "sg:province":"Glasgow City",
    "wof:name":"Apex Trust Scotland",
    "wof:placetype":"venue"
},
  "geometry": {"coordinates":[-4.258401,55.861187],"type":"Point"}
}