{
  "type": "Feature",
  "properties": {
    "addr:full":"51 Paxton Crescent Lochgelly Fife KY5 9ET",
    "addr:housenumber":"51",
    "addr:postcode":"ky5 9et",
    "addr:street":"Paxton Crescent",
    "iso:country":"GB",
    "sg:address":"51 Paxton Crescent",
    "sg:city":"Lochgelly",
    "sg:classifiers":[
        {
            "category":"Building & Trades",
            "subcategory":"Construction",
            "type":"Services"
        }
    ],
    "sg:phone":"+44 1592 781687",
    "sg:postcode":"KY5 9ET",
    "sg:province":"Fife",
    "sg:tags":[
        "builder"
    ],
    "wof:name":"David J Black Construction",
    "wof:placetype":"venue"
},
  "geometry": {"coordinates":[-3.3143639565,56.1312561035],"type":"Point"}
}