{
  "type": "Feature",
  "properties": {
    "addr:full":"1 Frank Place, Durham Road, Birtley Chester-le-street Durham DH3 2QF",
    "addr:housenumber":"1",
    "addr:postcode":"dh3 2qf",
    "addr:street":"Frank Place Durham Road",
    "iso:country":"GB",
    "sg:address":"1 Frank Place, Durham Road, Birtley",
    "sg:city":"Chester-le-street",
    "sg:classifiers":[
        {
            "category":"Professional",
            "subcategory":"Art Services",
            "type":"Services"
        }
    ],
    "sg:phone":"+44 191 410 8066",
    "sg:postcode":"DH3 2QF",
    "sg:province":"Durham",
    "sg:tags":[
        "framing"
    ],
    "wof:name":"Decorframes",
    "wof:placetype":"venue"
},
  "geometry": {"coordinates":[-1.57757,54.892872],"type":"Point"}
}