{
  "type": "Feature",
  "properties": {
    "iso:country":"GB",
    "sg:address":"206 Merton Road",
    "sg:city":"London",
    "sg:classifiers":[
        {
            "category":"Fast Food",
            "type":"Food & Drink"
        }
    ],
    "sg:postcode":"SW18 5SW",
    "sg:province":"Greater London",
    "sg:tags":[
        "away",
        "take"
    ],
    "wof:name":"The Golden Carp",
    "wof:placetype":"venue"
},
  "geometry": {"coordinates":[-0.199279,51.450577],"type":"Point"}
}