{
  "type": "Feature",
  "properties": {
    "iso:country":"GB",
    "sg:address":"Ham Villa Farm Ham Road, Charlton Kings",
    "sg:city":"Cheltenham",
    "sg:classifiers":[
        {
            "category":"Utilities",
            "subcategory":"Refuse",
            "type":"Services"
        }
    ],
    "sg:phone":"+44 1242 529397",
    "sg:postcode":"GL52 6NB",
    "sg:province":"Gloucestershire",
    "sg:tags":[
        "skip",
        "hire"
    ],
    "wof:name":"P S R Waste Disposal Ltd.",
    "wof:placetype":"venue"
},
  "geometry": {"coordinates":[-2.044046,51.883915],"type":"Point"}
}