{
  "type": "Feature",
  "properties": {
    "addr:full":"Warden, 21 Hillfield, South Zeal Okehampton Devon EX20 2NY",
    "addr:housenumber":"21",
    "addr:postcode":"ex20 2ny",
    "addr:street":"Warden;Hillfield South Zeal",
    "iso:country":"GB",
    "sg:address":"Warden, 21 Hillfield, South Zeal",
    "sg:city":"Okehampton",
    "sg:classifiers":[
        {
            "category":"Social Services",
            "subcategory":"Adult Care",
            "type":"Services"
        },
        {
            "category":"Government",
            "subcategory":"Office",
            "type":"Public Place"
        }
    ],
    "sg:postcode":"EX20 2NY",
    "sg:province":"Devon",
    "sg:tags":[
        "housing",
        "local",
        "sheltered"
    ],
    "wof:name":"Hillfield & the Croft Sheltered Housing",
    "wof:placetype":"venue"
},
  "geometry": {"coordinates":[-3.9121370316,50.7222480774],"type":"Point"}
}