{
  "type": "Feature",
  "properties": {
    "iso:country":"GB",
    "sg:address":"Brent Farm, Cockerhurst Rd, Shoreham",
    "sg:city":"Sevenoaks",
    "sg:classifiers":[
        {
            "category":"Home & Garden",
            "subcategory":"Home Furnishings",
            "type":"Retail Goods"
        }
    ],
    "sg:phone":"+44 1959 522358",
    "sg:postcode":"TN14 7UA",
    "sg:province":"Kent",
    "sg:tags":[
        "patio",
        "furniture"
    ],
    "wof:name":"The Olde Curiosity Garden",
    "wof:placetype":"venue"
},
  "geometry": {"coordinates":[0.1782850027,51.3378639221],"type":"Point"}
}