{
  "type": "Feature",
  "properties": {
    "iso:country":"GB",
    "sg:address":"Main Street, Farnsfield",
    "sg:city":"Newark",
    "sg:classifiers":[
        {
            "category":"Food & Beverages",
            "subcategory":"Bakery",
            "type":"Retail Goods"
        }
    ],
    "sg:phone":"+44 1623 882283",
    "sg:postcode":"NG22 8EF",
    "sg:province":"Nottinghamshire",
    "sg:tags":[
        "baker"
    ],
    "wof:name":"G Atherley & Son",
    "wof:placetype":"venue"
},
  "geometry": {"coordinates":[-1.0334939957,53.1023101807],"type":"Point"}
}