{
  "type": "Feature",
  "properties": {
    "addr:full":"14 Castlehill Road Dumbarton Argyll and Bute G82 5BL",
    "addr:housenumber":"14",
    "addr:postcode":"g82 5bl",
    "addr:street":"Castlehill Road",
    "iso:country":"GB",
    "sg:address":"14 Castlehill Road",
    "sg:city":"Dumbarton",
    "sg:classifiers":[
        {
            "category":"Fast Food",
            "type":"Food & Drink"
        }
    ],
    "sg:phone":"+44 1389 767666",
    "sg:postcode":"G82 5BL",
    "sg:province":"Argyll and Bute",
    "sg:tags":[
        "away",
        "meal",
        "outlet",
        "take"
    ],
    "wof:name":"The New Dragon Inn",
    "wof:placetype":"venue"
},
  "geometry": {"coordinates":[-4.5869789124,55.9495315552],"type":"Point"}
}