{
  "type": "Feature",
  "properties": {
    "iso:country":"GB",
    "sg:address":"18 Oakfield Street",
    "sg:city":"Cardiff",
    "sg:classifiers":[
        {
            "category":"Farming",
            "subcategory":"Nursery",
            "type":"Manufacturing & Wholesale Goods"
        },
        {
            "category":"Social Services",
            "subcategory":"Child Care",
            "type":"Services"
        }
    ],
    "sg:postcode":"CF24 3RD",
    "sg:province":"Cardiff",
    "sg:tags":[
        "creche"
    ],
    "wof:name":"POPPETS NURSERY",
    "wof:placetype":"venue"
},
  "geometry": {"coordinates":[-3.1596369743,51.489780426],"type":"Point"}
}