{
  "type": "Feature",
  "properties": {
    "iso:country":"GB",
    "sg:address":"41-43 The Esplanade",
    "sg:city":"Fleetwood",
    "sg:classifiers":[
        {
            "category":"Travel",
            "subcategory":"Hotels & Motels",
            "type":"Entertainment"
        }
    ],
    "sg:phone":"+44 1253 874796",
    "sg:postcode":"FY7 6QE",
    "sg:province":"Lancashire",
    "wof:name":"The New Boston Hotel",
    "wof:placetype":"venue"
},
  "geometry": {"coordinates":[-3.0190711021,53.9252929688],"type":"Point"}
}