{
  "type": "Feature",
  "properties": {
    "addr:full":"46 Carlyon Rd Wembley Greater London HA0 1JE",
    "addr:housenumber":"46",
    "addr:postcode":"ha0 1je",
    "addr:street":"Carlyon Rd",
    "iso:country":"GB",
    "sg:address":"46 Carlyon Rd",
    "sg:city":"Wembley",
    "sg:classifiers":[
        {
            "category":"Retail",
            "subcategory":"Auto Rental",
            "type":"Services"
        }
    ],
    "sg:phone":"+44 20 8997 9050",
    "sg:postcode":"HA0 1JE",
    "sg:province":"Greater London",
    "sg:tags":[
        "car"
    ],
    "wof:name":"Jack's",
    "wof:placetype":"venue"
},
  "geometry": {"coordinates":[-0.293946,51.537884],"type":"Point"}
}