{
  "type": "Feature",
  "properties": {
    "iso:country":"GB",
    "sg:address":"7 St. John St",
    "sg:city":"Clerkenwell",
    "sg:classifiers":[
        {
            "category":"Wholesale",
            "subcategory":"Books, Periodicals, & Newspapers",
            "type":"Manufacturing & Wholesale Goods"
        }
    ],
    "sg:phone":"+44 20 7251 2477",
    "sg:postcode":"EC1M 4AA",
    "sg:province":"Greater London",
    "sg:tags":[
        "publishing"
    ],
    "wof:name":"Production Consultancy Ltd",
    "wof:placetype":"venue"
},
  "geometry": {"coordinates":[-0.1019359976,51.5203132629],"type":"Point"}
}