{
  "type": "Feature",
  "properties": {
    "iso:country":"GB",
    "sg:address":"Suite 210, 164/180 Union Street",
    "sg:city":"London",
    "sg:classifiers":[
        {
            "category":"Professional",
            "subcategory":"Printing & Photocopies",
            "type":"Services"
        }
    ],
    "sg:phone":"+44 20 7620 2774",
    "sg:postcode":"SE1 0LH",
    "sg:province":"Greater London",
    "sg:tags":[
        "printer"
    ],
    "wof:name":"Canadian Bank Note International Ltd.",
    "wof:placetype":"venue"
},
  "geometry": {"coordinates":[-0.099219,51.503857],"type":"Point"}
}