{
  "type": "Feature",
  "properties": {
    "iso:country":"GB",
    "sg:address":"19 Wharton Rd, Headington",
    "sg:city":"Oxford",
    "sg:classifiers":[
        {
            "category":"Bars & Pubs",
            "type":"Food & Drink"
        }
    ],
    "sg:postcode":"OX3 8AL",
    "sg:province":"Oxfordshire",
    "sg:tags":[
        "pubs",
        "inn"
    ],
    "wof:name":"Courage Ltd",
    "wof:placetype":"venue"
},
  "geometry": {"coordinates":[-1.2050499916,51.7591285706],"type":"Point"}
}