{
  "type": "Feature",
  "properties": {
    "iso:country":"GB",
    "sg:address":"89 Kettering Road",
    "sg:city":"Northampton",
    "sg:classifiers":[
        {
            "category":"Organizations",
            "subcategory":"Non-profit Organization",
            "type":"Services"
        }
    ],
    "sg:phone":"+44 1604 636404",
    "sg:postcode":"NN1 4AW",
    "sg:province":"Northamptonshire",
    "sg:tags":[
        "organisation",
        "voluntary",
        "charity"
    ],
    "wof:name":"British Red Cross",
    "wof:placetype":"venue"
},
  "geometry": {"coordinates":[-0.88583,52.242298],"type":"Point"}
}