{
  "type": "Feature",
  "properties": {
    "iso:country":"GB",
    "sg:address":"Unit 25 Harper Centre",
    "sg:city":"Bedford",
    "sg:classifiers":[
        {
            "category":"Shopping",
            "subcategory":"Discount & Variety Stores",
            "type":"Retail Goods"
        }
    ],
    "sg:phone":"+44 1234 349710",
    "sg:postcode":"MK40 1TG",
    "sg:province":"Bedfordshire",
    "sg:tags":[
        "centre"
    ],
    "wof:name":"Superspot Ltd.",
    "wof:placetype":"venue"
},
  "geometry": {"coordinates":[-0.464958,52.138973],"type":"Point"}
}