{
  "type": "Feature",
  "properties": {
    "iso:country":"GB",
    "sg:address":"Anderson House, 389 Argyle Street",
    "sg:city":"Glasgow",
    "sg:classifiers":[
        {
            "category":"Building & Trades",
            "subcategory":"Plumbing",
            "type":"Services"
        }
    ],
    "sg:postcode":"G2 8LR",
    "sg:province":"Glasgow City",
    "sg:tags":[
        "filtration",
        "system"
    ],
    "wof:name":"Pall Europe Ltd.",
    "wof:placetype":"venue"
},
  "geometry": {"coordinates":[-4.264793,55.85902],"type":"Point"}
}