{
  "type": "Feature",
  "properties": {
    "addr:full":"South Gro Garages, Moorgate Rotherham South Yorkshire S60 2EN",
    "addr:postcode":"s60 2en",
    "addr:street":"South Gro Garages Moorgate",
    "iso:country":"GB",
    "sg:address":"South Gro Garages, Moorgate",
    "sg:city":"Rotherham",
    "sg:classifiers":[
        {
            "category":"Manufacturing",
            "subcategory":"Signs",
            "type":"Manufacturing & Wholesale Goods"
        }
    ],
    "sg:postcode":"S60 2EN",
    "sg:province":"South Yorkshire",
    "sg:tags":[
        "writer"
    ],
    "wof:name":"Gary Oxley Signs Plus",
    "wof:placetype":"venue"
},
  "geometry": {"coordinates":[-1.354243,53.429874],"type":"Point"}
}