{
  "type": "Feature",
  "properties": {
    "iso:country":"GB",
    "sg:address":"3 Somerford Place",
    "sg:city":"Willenhall",
    "sg:classifiers":[
        {
            "category":"Shopping",
            "subcategory":"Florist",
            "type":"Retail Goods"
        }
    ],
    "sg:phone":"+44 1902 604176",
    "sg:postcode":"WV13 3DZ",
    "sg:province":"West Midlands",
    "wof:name":"Conroys Florist",
    "wof:placetype":"venue"
},
  "geometry": {"coordinates":[-2.062819,52.583191],"type":"Point"}
}