{
  "type": "Feature",
  "properties": {
    "addr:full":"11 Glover Street Stoke-on-trent Staffordshire ST1 2LU",
    "addr:housenumber":"11",
    "addr:postcode":"st1 2lu",
    "addr:street":"Glover Street",
    "iso:country":"GB",
    "sg:address":"11 Glover Street",
    "sg:city":"Stoke-on-trent",
    "sg:classifiers":[
        {
            "category":"Ice Cream",
            "type":"Food & Drink"
        }
    ],
    "sg:postcode":"ST1 2LU",
    "sg:province":"Staffordshire",
    "sg:tags":[
        "mnfr"
    ],
    "wof:name":"Lewis's Ice Cream",
    "wof:placetype":"venue"
},
  "geometry": {"coordinates":[-2.16768,53.033432],"type":"Point"}
}