{
  "type": "Feature",
  "properties": {
    "addr:full":"Image House, Newbridge, Cadnam Southampton Hampshire SO40 2NW",
    "addr:postcode":"so40 2nw",
    "addr:street":"Cadnam",
    "iso:country":"GB",
    "sg:address":"Image House, Newbridge, Cadnam",
    "sg:city":"Southampton",
    "sg:classifiers":[
        {
            "category":"Manufacturing",
            "subcategory":"Signs",
            "type":"Manufacturing & Wholesale Goods"
        }
    ],
    "sg:phone":"+44 23 8081 3989",
    "sg:postcode":"SO40 2NW",
    "sg:province":"Hampshire",
    "sg:tags":[
        "writer"
    ],
    "wof:name":"Freestyle Signs",
    "wof:placetype":"venue"
},
  "geometry": {"coordinates":[-1.574074,50.919258],"type":"Point"}
}