{
  "type": "Feature",
  "properties": {
    "iso:country":"GB",
    "sg:address":"47 Grosvenor Road",
    "sg:city":"Tunbridge Wells",
    "sg:classifiers":[
        {
            "category":"Bars & Pubs",
            "type":"Food & Drink"
        }
    ],
    "sg:phone":"+44 1892 522427",
    "sg:postcode":"TN1 2AY",
    "sg:province":"Kent",
    "sg:tags":[
        "pubs",
        "inn"
    ],
    "wof:name":"The Rose & Crown",
    "wof:placetype":"venue"
},
  "geometry": {"coordinates":[0.262334,51.136208],"type":"Point"}
}