{
  "type": "Feature",
  "properties": {
    "addr:full":"1 Black Swan Court, 69 Westgate Road Newcastle-upon-tyne Tyne and Wear NE1 1SG",
    "addr:housenumber":"1;69",
    "addr:postcode":"ne1 1sg",
    "addr:street":"Black Swan;Westgate Road",
    "iso:country":"GB",
    "sg:address":"1 Black Swan Court, 69 Westgate Road",
    "sg:city":"Newcastle-upon-tyne",
    "sg:classifiers":[
        {
            "category":"Utilities",
            "type":"Services"
        }
    ],
    "sg:phone":"+44 191 261 2115",
    "sg:postcode":"NE1 1SG",
    "sg:province":"Tyne and Wear",
    "sg:tags":[
        "internet"
    ],
    "wof:name":"The Cavendish Press",
    "wof:placetype":"venue"
},
  "geometry": {"coordinates":[-1.6123689413,54.9779167175],"type":"Point"}
}