{
  "type": "Feature",
  "properties": {
    "iso:country":"GB",
    "sg:address":"534 Scott Hall Road",
    "sg:city":"Leeds",
    "sg:classifiers":[
        {
            "category":"Personal",
            "subcategory":"Beauty Salon",
            "type":"Services"
        }
    ],
    "sg:postcode":"LS7 3RA",
    "sg:province":"West Yorkshire",
    "sg:tags":[
        "unisex",
        "hairdresser"
    ],
    "wof:name":"Clipso Hair Salon",
    "wof:placetype":"venue"
},
  "geometry": {"coordinates":[-1.546924,53.827347],"type":"Point"}
}