{
  "type": "Feature",
  "properties": {
    "addr:full":"92-94 Manchester Rd, Denton Manchester Greater Manchester M34 3PR",
    "addr:housenumber":"92-94",
    "addr:postcode":"m34 3pr",
    "addr:street":"Manchester Rd",
    "iso:country":"GB",
    "sg:address":"92-94 Manchester Rd, Denton",
    "sg:city":"Manchester",
    "sg:classifiers":[
        {
            "category":"Retail",
            "subcategory":"Auto Repair",
            "type":"Services"
        }
    ],
    "sg:phone":"+44 161 337 8800",
    "sg:postcode":"M34 3PR",
    "sg:province":"Greater Manchester",
    "sg:tags":[
        "car",
        "upholsterer"
    ],
    "wof:name":"Uncle Sam's Carwash Ltd",
    "wof:placetype":"venue"
},
  "geometry": {"coordinates":[-2.118439,53.456188],"type":"Point"}
}