{
  "type": "Feature",
  "properties": {
    "addr:full":"33 Midhurst Av Westcliff On Sea Essex SS0 0NP",
    "addr:housenumber":"33",
    "addr:postcode":"ss0 0np",
    "addr:street":"Midhurst Av",
    "iso:country":"GB",
    "sg:address":"33 Midhurst Av",
    "sg:city":"Westcliff On Sea",
    "sg:classifiers":[
        {
            "category":"Building & Trades",
            "subcategory":"Construction",
            "type":"Services"
        }
    ],
    "sg:phone":"+44 1702 333679",
    "sg:postcode":"SS0 0NP",
    "sg:province":"Essex",
    "sg:tags":[
        "flooring"
    ],
    "wof:name":"Savill Parquet Floors",
    "wof:placetype":"venue"
},
  "geometry": {"coordinates":[0.693259,51.558205],"type":"Point"}
}