{
  "type": "Feature",
  "properties": {
    "addr:full":"68-70 London Road Croydon Surrey CR0 2TB",
    "addr:housenumber":"68-70",
    "addr:postcode":"cr0 2tb",
    "addr:street":"London Road",
    "iso:country":"GB",
    "sg:address":"68-70 London Road",
    "sg:city":"Croydon",
    "sg:classifiers":[
        {
            "category":"Shopping",
            "subcategory":"Musical Instruments",
            "type":"Retail Goods"
        }
    ],
    "sg:phone":"+44 20 8680 1042",
    "sg:postcode":"CR0 2TB",
    "sg:province":"Surrey",
    "sg:tags":[
        "music",
        "sheet"
    ],
    "wof:name":"Rockbottom",
    "wof:placetype":"venue"
},
  "geometry": {"coordinates":[-0.1046430022,51.3804206848],"type":"Point"}
}