{
  "type": "Feature",
  "properties": {
    "addr:full":"Unit 4, Esland Place Cirencester Gloucestershire GL7 1YG",
    "addr:housenumber":"unit 4",
    "addr:postcode":"gl7 1yg",
    "addr:street":"Esland Place",
    "iso:country":"GB",
    "sg:address":"Unit 4, Esland Place",
    "sg:city":"Cirencester",
    "sg:classifiers":[
        {
            "category":"Shopping",
            "subcategory":"Stationery & Office Supplies",
            "type":"Retail Goods"
        },
        {
            "category":"Manufacturing",
            "subcategory":"Paper Products",
            "type":"Manufacturing & Wholesale Goods"
        }
    ],
    "sg:phone":"+44 1285 650888",
    "sg:postcode":"GL7 1YG",
    "sg:province":"Gloucestershire",
    "sg:tags":[
        "manufacture",
        "adhesive",
        "tape",
        "domestic"
    ],
    "wof:name":"South Western Specialised Tape Ltd.",
    "wof:placetype":"venue"
},
  "geometry": {"coordinates":[-1.960164,51.705181],"type":"Point"}
}