{
  "type": "Feature",
  "properties": {
    "addr:full":"131 Sydney Road London Greater London N10 2ND",
    "addr:housenumber":"131",
    "addr:postcode":"n10 2nd",
    "addr:street":"Sydney Road",
    "iso:country":"GB",
    "sg:address":"131 Sydney Road",
    "sg:city":"London",
    "sg:classifiers":[
        {
            "category":"Professional",
            "subcategory":"Art Services",
            "type":"Services"
        }
    ],
    "sg:phone":"+44 20 8444 9046",
    "sg:postcode":"N10 2ND",
    "sg:province":"Greater London",
    "sg:tags":[
        "photographer"
    ],
    "wof:name":"Patrick Gorman Photography",
    "wof:placetype":"venue"
},
  "geometry": {"coordinates":[-0.144115,51.603138],"type":"Point"}
}