{
  "type": "Feature",
  "properties": {
    "iso:country":"GB",
    "sg:address":"170 Bower Street",
    "sg:city":"Bedford",
    "sg:classifiers":[
        {
            "category":"Organizations",
            "subcategory":"Membership Organization",
            "type":"Services"
        }
    ],
    "sg:phone":"+44 1234 351928",
    "sg:postcode":"MK40 3QZ",
    "sg:province":"Bedfordshire",
    "sg:tags":[
        "club"
    ],
    "wof:name":"Association of Ukranians in Great Britain",
    "wof:placetype":"venue"
},
  "geometry": {"coordinates":[-0.454777,52.139702],"type":"Point"}
}