{
  "type": "Feature",
  "properties": {
    "iso:country":"GB",
    "sg:address":"94 Hamlets Way",
    "sg:city":"London",
    "sg:classifiers":[
        {
            "category":"Personal",
            "subcategory":"Barber",
            "type":"Services"
        }
    ],
    "sg:phone":"+44 20 8980 1333",
    "sg:postcode":"E3 4SY",
    "sg:province":"Greater London",
    "sg:tags":[
        "men's",
        "hairdresser"
    ],
    "wof:name":"Micks",
    "wof:placetype":"venue"
},
  "geometry": {"coordinates":[-0.0334560014,51.5232086182],"type":"Point"}
}