{
  "type": "Feature",
  "properties": {
    "iso:country":"GB",
    "sg:address":"38 Park Avenue, Allerton Bywater",
    "sg:city":"Castleford",
    "sg:classifiers":[
        {
            "category":"Military Area",
            "subcategory":"Air Force Base",
            "type":"Public Place"
        }
    ],
    "sg:phone":"+44 1977 555576",
    "sg:postcode":"WF10 2AS",
    "sg:province":"West Yorkshire",
    "sg:tags":[
        "taxi",
        "hire",
        "private"
    ],
    "wof:name":"E & C Goodall",
    "wof:placetype":"venue"
},
  "geometry": {"coordinates":[-1.358318,53.745621],"type":"Point"}
}