{
  "type": "Feature",
  "properties": {
    "addr:full":"Norman Hall, Cromwell Road Grays Essex RM17 5HF",
    "addr:postcode":"rm17 5hf",
    "addr:street":"Cromwell Road",
    "iso:country":"GB",
    "sg:address":"Norman Hall, Cromwell Road",
    "sg:city":"Grays",
    "sg:classifiers":[
        {
            "category":"Education",
            "subcategory":"Special Training",
            "type":"Public Place"
        }
    ],
    "sg:postcode":"RM17 5HF",
    "sg:province":"Essex",
    "sg:tags":[
        "martial art",
        "instruction"
    ],
    "wof:name":"Loke Martial Arts Studios",
    "wof:placetype":"venue"
},
  "geometry": {"coordinates":[0.326975,51.479614],"type":"Point"}
}