{
  "type": "Feature",
  "properties": {
    "iso:country":"GB",
    "sg:address":"1 Park Road, Hampton",
    "sg:city":"Kingston-upon-thames",
    "sg:classifiers":[
        {
            "category":"Utilities",
            "type":"Services"
        }
    ],
    "sg:postcode":"KT1 4AS",
    "sg:province":"Greater London",
    "sg:tags":[
        "internet"
    ],
    "wof:name":"Website Workshop Ltd",
    "wof:placetype":"venue"
},
  "geometry": {"coordinates":[-0.311677,51.412811],"type":"Point"}
}