{
  "type": "Feature",
  "properties": {
    "addr:full":"38 High Street, Wickwar Wotton-under-edge Gloucestershire GL12 8NP",
    "addr:housenumber":"38",
    "addr:postcode":"gl12 8np",
    "addr:street":"High Street",
    "iso:country":"GB",
    "sg:address":"38 High Street, Wickwar",
    "sg:city":"Wotton-under-edge",
    "sg:classifiers":[
        {
            "category":"Shopping",
            "subcategory":"Antiques",
            "type":"Retail Goods"
        },
        {
            "category":"Shopping",
            "subcategory":"Used Merchandise",
            "type":"Retail Goods"
        }
    ],
    "sg:postcode":"GL12 8NP",
    "sg:province":"Gloucestershire",
    "sg:tags":[
        "shop",
        "second-hand"
    ],
    "wof:name":"Bell Passage Antiques",
    "wof:placetype":"venue"
},
  "geometry": {"coordinates":[-2.3999741077,51.5945854187],"type":"Point"}
}