{
  "type": "Feature",
  "properties": {
    "iso:country":"GB",
    "sg:address":"26 West High Street",
    "sg:city":"Crieff",
    "sg:classifiers":[
        {
            "category":"Deli",
            "type":"Food & Drink"
        },
        {
            "category":"Food & Beverages",
            "subcategory":"Supermarket",
            "type":"Retail Goods"
        }
    ],
    "sg:phone":"+44 1764 653011",
    "sg:postcode":"PH7 4DL",
    "sg:province":"Perth and Kinross",
    "sg:tags":[
        "delicatessen"
    ],
    "wof:name":"Corn Exchange",
    "wof:placetype":"venue"
},
  "geometry": {"coordinates":[-3.842585,56.373356],"type":"Point"}
}