{
  "type": "Feature",
  "properties": {
    "addr:full":"Kent County Show Ground, Detling Hill Maidstone Kent ME14 3JF",
    "addr:postcode":"me14 3jf",
    "iso:country":"GB",
    "sg:address":"Kent County Show Ground, Detling Hill",
    "sg:city":"Maidstone",
    "sg:classifiers":[
        {
            "category":"Education",
            "subcategory":"Special Training",
            "type":"Public Place"
        }
    ],
    "sg:postcode":"ME14 3JF",
    "sg:province":"Kent",
    "sg:tags":[
        "product",
        "centre"
    ],
    "wof:name":"Springate Gordon Transport Training Services",
    "wof:placetype":"venue"
},
  "geometry": {"coordinates":[0.5693740249,51.293384552],"type":"Point"}
}