{
  "type": "Feature",
  "properties": {
    "addr:full":"145 Northfield Avenue, Ealing London Greater London W13 9QT",
    "addr:housenumber":"145",
    "addr:postcode":"w13 9qt",
    "addr:street":"Northfield Avenue",
    "iso:country":"GB",
    "sg:address":"145 Northfield Avenue, Ealing",
    "sg:city":"London",
    "sg:classifiers":[
        {
            "category":"Building & Trades",
            "subcategory":"Construction",
            "type":"Services"
        }
    ],
    "sg:postcode":"W13 9QT",
    "sg:province":"Greater London",
    "sg:tags":[
        "flooring"
    ],
    "wof:name":"Northfield Flooring Co.",
    "wof:placetype":"venue"
},
  "geometry": {"coordinates":[-0.3162739873,51.5026435852],"type":"Point"}
}