{
  "type": "Feature",
  "properties": {
    "addr:full":"B2-B4 Rowood Estate, 25-27 Murdock Road Bicester Oxfordshire OX26 4PP",
    "addr:housenumber":"25-27",
    "addr:postcode":"ox26 4pp",
    "addr:street":"Rowood;Murdock Road",
    "iso:country":"GB",
    "sg:address":"B2-B4 Rowood Estate, 25-27 Murdock Road",
    "sg:city":"Bicester",
    "sg:classifiers":[
        {
            "category":"Organizations",
            "subcategory":"Labor Organization",
            "type":"Services"
        },
        {
            "category":"Wholesale",
            "subcategory":"Machinery & Supplies",
            "type":"Manufacturing & Wholesale Goods"
        }
    ],
    "sg:phone":"+44 1869 244943",
    "sg:postcode":"OX26 4PP",
    "sg:province":"Oxfordshire",
    "sg:tags":[
        "woodworking",
        "supplier",
        "industrial",
        "manufacturer"
    ],
    "wof:name":"R W Machines Ltd",
    "wof:placetype":"venue"
},
  "geometry": {"coordinates":[-1.143772006,51.9021873474],"type":"Point"}
}