{
  "type": "Feature",
  "properties": {
    "addr:full":"Bearwalden Business Park, Royston Road, Wendens Ambo Saffron Walden Essex CB11 4JX",
    "addr:postcode":"cb11 4jx",
    "addr:street":"Business Park Royston Road",
    "iso:country":"GB",
    "sg:address":"Bearwalden Business Park, Royston Road, Wendens Ambo",
    "sg:city":"Saffron Walden",
    "sg:classifiers":[
        {
            "category":"Bus Stop",
            "subcategory":"None",
            "type":"Transportation"
        },
        {
            "category":"Military Area",
            "subcategory":"Air Force Base",
            "type":"Public Place"
        }
    ],
    "sg:phone":"+44 1799 540983",
    "sg:postcode":"CB11 4JX",
    "sg:province":"Essex",
    "sg:tags":[
        "filter",
        "water",
        "treatment"
    ],
    "wof:name":"Ward (Saffron Walden) Ltd.",
    "wof:placetype":"venue"
},
  "geometry": {"coordinates":[0.205205,52.005974],"type":"Point"}
}