{
  "type": "Feature",
  "properties": {
    "iso:country":"GB",
    "sg:address":"12 Church St",
    "sg:city":"Lochwinnoch",
    "sg:classifiers":[
        {
            "category":"Cinema",
            "subcategory":"Movie Rental",
            "type":"Entertainment"
        }
    ],
    "sg:postcode":"PA12 4AD",
    "sg:province":"Renfrewshire",
    "sg:tags":[
        "video",
        "library"
    ],
    "wof:name":"Law,Hugh,",
    "wof:placetype":"venue"
},
  "geometry": {"coordinates":[-4.622879,55.797619],"type":"Point"}
}