{
  "type": "Feature",
  "properties": {
    "iso:country":"GB",
    "sg:address":"23 Cranford Drive, Holybourne",
    "sg:city":"Alton",
    "sg:classifiers":[
        {
            "category":"Utilities",
            "subcategory":"Sewage",
            "type":"Services"
        }
    ],
    "sg:phone":"+44 1420 85478",
    "sg:postcode":"GU34 4HJ",
    "sg:province":"Hampshire",
    "sg:tags":[
        "acoustic",
        "consultant"
    ],
    "wof:name":"Acoustic & Environmental Technology",
    "wof:placetype":"venue"
},
  "geometry": {"coordinates":[-0.951921,51.161301],"type":"Point"}
}