{
  "type": "Feature",
  "properties": {
    "addr:full":"Russell Ho, 47 Wilkinson St Sheffield South Yorkshire S10 2GB",
    "addr:housenumber":"47",
    "addr:postcode":"s10 2gb",
    "addr:street":"Wilkinson St",
    "iso:country":"GB",
    "sg:address":"Russell Ho, 47 Wilkinson St",
    "sg:city":"Sheffield",
    "sg:classifiers":[
        {
            "category":"Professional",
            "subcategory":"Management & Consulting",
            "type":"Services"
        }
    ],
    "sg:postcode":"S10 2GB",
    "sg:province":"South Yorkshire",
    "sg:tags":[
        "consultant",
        "business"
    ],
    "wof:name":"Blagg,Wilfred,",
    "wof:placetype":"venue"
},
  "geometry": {"coordinates":[-1.4645440578,53.3831100464],"type":"Point"}
}