{
  "type": "Feature",
  "properties": {
    "addr:full":"637 Fulham Road London Greater London SW6 5UQ",
    "addr:housenumber":"637",
    "addr:postcode":"sw6 5uq",
    "addr:street":"Fulham Road",
    "iso:country":"GB",
    "sg:address":"637 Fulham Road",
    "sg:city":"London",
    "sg:classifiers":[
        {
            "category":"Home & Garden",
            "subcategory":"Carpets & Floor Coverings",
            "type":"Retail Goods"
        }
    ],
    "sg:phone":"+44 20 7610 9800",
    "sg:postcode":"SW6 5UQ",
    "sg:province":"Greater London",
    "sg:tags":[
        "carpets",
        "rug",
        "matting"
    ],
    "wof:name":"Rugstore",
    "wof:placetype":"venue"
},
  "geometry": {"coordinates":[-0.1988860071,51.4795265198],"type":"Point"}
}