{
  "type": "Feature",
  "properties": {
    "addr:full":"425 High Road London Greater London NW10 2JN",
    "addr:housenumber":"425",
    "addr:postcode":"nw10 2jn",
    "addr:street":"High Road",
    "iso:country":"GB",
    "sg:address":"425 High Road",
    "sg:city":"London",
    "sg:classifiers":[
        {
            "category":"Fast Food",
            "type":"Food & Drink"
        }
    ],
    "sg:postcode":"NW10 2JN",
    "sg:province":"Greater London",
    "sg:tags":[
        "away",
        "take"
    ],
    "wof:name":"Happy Garden",
    "wof:placetype":"venue"
},
  "geometry": {"coordinates":[-0.2427670062,51.5490684509],"type":"Point"}
}