{
  "type": "Feature",
  "properties": {
    "addr:full":"8 Corrigan Clo Milton Keynes Buckinghamshire MK3 6BP",
    "addr:housenumber":"8",
    "addr:postcode":"mk3 6bp",
    "addr:street":"Corrigan Clo",
    "iso:country":"GB",
    "sg:address":"8 Corrigan Clo",
    "sg:city":"Milton Keynes",
    "sg:classifiers":[
        {
            "category":"Building & Trades",
            "subcategory":"Plumbing",
            "type":"Services"
        }
    ],
    "sg:phone":"+44 1908 368556",
    "sg:postcode":"MK3 6BP",
    "sg:province":"Buckinghamshire",
    "sg:tags":[
        "central",
        "heating"
    ],
    "wof:name":"D A C Services",
    "wof:placetype":"venue"
},
  "geometry": {"coordinates":[-0.7475960255,51.9952507019],"type":"Point"}
}