{
  "type": "Feature",
  "properties": {
    "addr:full":"21-25 Sanders Road, Finedon Road Industrial Estate Wellingborough Northamptonshire NN8 4NL",
    "addr:housenumber":"21-25",
    "addr:postcode":"nn8 4nl",
    "addr:street":"Sanders Road Finedon Road Industrial Estate",
    "iso:country":"GB",
    "sg:address":"21-25 Sanders Road, Finedon Road Industrial Estate",
    "sg:city":"Wellingborough",
    "sg:classifiers":[
        {
            "category":"Professional",
            "subcategory":"Printing & Photocopies",
            "type":"Services"
        }
    ],
    "sg:phone":"+44 1933 229194",
    "sg:postcode":"NN8 4NL",
    "sg:province":"Northamptonshire",
    "sg:tags":[
        "printer"
    ],
    "wof:name":"General Printers",
    "wof:placetype":"venue"
},
  "geometry": {"coordinates":[-0.683631,52.319309],"type":"Point"}
}