{
  "type": "Feature",
  "properties": {
    "addr:full":"The Chapel, Northampton Rd Market Harborough Leicestershire LE16 9HE",
    "addr:postcode":"le16 9he",
    "addr:street":"Northampton Rd",
    "iso:country":"GB",
    "sg:address":"The Chapel, Northampton Rd",
    "sg:city":"Market Harborough",
    "sg:classifiers":[
        {
            "category":"Retail",
            "subcategory":"Funeral Services",
            "type":"Services"
        }
    ],
    "sg:postcode":"LE16 9HE",
    "sg:province":"Leicestershire",
    "sg:tags":[
        "cemetery",
        "crematorium"
    ],
    "wof:name":"Leicestershire County Council",
    "wof:placetype":"venue"
},
  "geometry": {"coordinates":[-0.9186859727,52.4757461548],"type":"Point"}
}