{
  "type": "Feature",
  "properties": {
    "iso:country":"GB",
    "sg:address":"14c Duffryn Road, Rhydyfelin",
    "sg:city":"Pontypridd",
    "sg:classifiers":[
        {
            "category":"Food & Beverages",
            "subcategory":"Bakery",
            "type":"Retail Goods"
        }
    ],
    "sg:postcode":"CF37 5RW",
    "sg:province":"Caerphilly",
    "sg:tags":[
        "baker"
    ],
    "wof:name":"Loafers",
    "wof:placetype":"venue"
},
  "geometry": {"coordinates":[-3.305607,51.586254],"type":"Point"}
}