{
  "type": "Feature",
  "properties": {
    "iso:country":"GB",
    "sg:address":"Forebank Care Home, 26 Forebank Road",
    "sg:city":"Dundee",
    "sg:classifiers":[
        {
            "category":"Health Services",
            "subcategory":"Nursing And Care Facility",
            "type":"Services"
        }
    ],
    "sg:phone":"+44 1382 206161",
    "sg:postcode":"DD1 2PB",
    "sg:province":"Dundee City",
    "sg:tags":[
        "home"
    ],
    "sg:website":"http://www.fshc.co.uk",
    "wof:name":"Forebank Nursing Home",
    "wof:placetype":"venue"
},
  "geometry": {"coordinates":[-2.968763,56.466251],"type":"Point"}
}