{
  "type": "Feature",
  "properties": {
    "addr:full":"29 Eldred Rd Liverpool Merseyside L16 8NZ",
    "addr:housenumber":"29",
    "addr:postcode":"l16 8nz",
    "addr:street":"Eldred Rd",
    "iso:country":"GB",
    "sg:address":"29 Eldred Rd",
    "sg:city":"Liverpool",
    "sg:classifiers":[
        {
            "category":"Home & Garden",
            "subcategory":"Home Furnishings",
            "type":"Retail Goods"
        }
    ],
    "sg:phone":"+44 151 722 4569",
    "sg:postcode":"L16 8NZ",
    "sg:province":"Merseyside",
    "sg:tags":[
        "awning",
        "canopy",
        "blinds"
    ],
    "wof:name":"S S & L Rosen Ltd",
    "wof:placetype":"venue"
},
  "geometry": {"coordinates":[-2.898847,53.391872],"type":"Point"}
}