{
  "type": "Feature",
  "properties": {
    "addr:full":"Unit 10 Sandy Lane Industrial Estate Stourport-on-severn Worcestershire DY13 9QB",
    "addr:housenumber":"unit 10",
    "addr:postcode":"dy13 9qb",
    "addr:street":"Sandy Lane Industrial Estate",
    "iso:country":"GB",
    "sg:address":"Unit 10 Sandy Lane Industrial Estate",
    "sg:city":"Stourport-on-severn",
    "sg:classifiers":[
        {
            "category":"Wholesale",
            "subcategory":"Toys & Hobbies",
            "type":"Manufacturing & Wholesale Goods"
        }
    ],
    "sg:phone":"+44 1299 877876",
    "sg:postcode":"DY13 9QB",
    "sg:province":"Worcestershire",
    "sg:tags":[
        "game"
    ],
    "wof:name":"Lookrite",
    "wof:placetype":"venue"
},
  "geometry": {"coordinates":[-2.2669990063,52.329246521],"type":"Point"}
}