{
  "type": "Feature",
  "properties": {
    "iso:country":"GB",
    "sg:address":"Shay Gate Farm, Skipton Old Road",
    "sg:city":"Colne",
    "sg:classifiers":[
        {
            "category":"Freight",
            "type":"Transportation"
        }
    ],
    "sg:phone":"+44 1282 868238",
    "sg:postcode":"BB8 7EW",
    "sg:province":"Lancashire",
    "sg:tags":[
        "haulage",
        "transport",
        "road"
    ],
    "wof:name":"C & G A Guy",
    "wof:placetype":"venue"
},
  "geometry": {"coordinates":[-2.1703650951,53.8568572998],"type":"Point"}
}