{
  "type": "Feature",
  "properties": {
    "addr:full":"10 Beadles Lane Oxted Surrey RH8 9JJ",
    "addr:housenumber":"10",
    "addr:postcode":"rh8 9jj",
    "addr:street":"Beadles Lane",
    "iso:country":"GB",
    "sg:address":"10 Beadles Lane",
    "sg:city":"Oxted",
    "sg:classifiers":[
        {
            "category":"Military Area",
            "subcategory":"Air Force Base",
            "type":"Public Place"
        }
    ],
    "sg:phone":"+44 1883 713101",
    "sg:postcode":"RH8 9JJ",
    "sg:province":"Surrey",
    "sg:tags":[
        "decorative",
        "glass",
        "mirror",
        "mnfr"
    ],
    "wof:name":"Limes Glass Ltd.",
    "wof:placetype":"venue"
},
  "geometry": {"coordinates":[-0.0163129997,51.251701355],"type":"Point"}
}