{
  "type": "Feature",
  "properties": {
    "addr:full":"10a High Church Street Nottingham Nottinghamshire NG7 7JP",
    "addr:housenumber":"10a",
    "addr:postcode":"ng7 7jp",
    "addr:street":"High Church Street",
    "iso:country":"GB",
    "sg:address":"10a High Church Street",
    "sg:city":"Nottingham",
    "sg:classifiers":[
        {
            "category":"Retail",
            "subcategory":"Auto Repair",
            "type":"Services"
        }
    ],
    "sg:phone":"+44 115 978 0734",
    "sg:postcode":"NG7 7JP",
    "sg:province":"Nottinghamshire",
    "sg:tags":[
        "modification",
        "garage"
    ],
    "wof:name":"Terry Robinson Motor Body Repairs",
    "wof:placetype":"venue"
},
  "geometry": {"coordinates":[-1.168097,52.974503],"type":"Point"}
}