{
  "type": "Feature",
  "properties": {
    "addr:full":"74 Cambridge Street Sheffield South Yorkshire S1 4HP",
    "addr:housenumber":"74",
    "addr:postcode":"s1 4hp",
    "addr:street":"Cambridge Street",
    "iso:country":"GB",
    "sg:address":"74 Cambridge Street",
    "sg:city":"Sheffield",
    "sg:classifiers":[
        {
            "category":"Professional",
            "subcategory":"Art Services",
            "type":"Services"
        }
    ],
    "sg:phone":"+44 114 279 6363",
    "sg:postcode":"S1 4HP",
    "sg:province":"South Yorkshire",
    "sg:tags":[
        "framing"
    ],
    "wof:name":"Fastframe",
    "wof:placetype":"venue"
},
  "geometry": {"coordinates":[-1.471642971,53.3783378601],"type":"Point"}
}