{
  "type": "Feature",
  "properties": {
    "addr:full":"14 Pine Road, Gleenfield Leicester Leicestershire LE3 8DH",
    "addr:housenumber":"14",
    "addr:postcode":"le3 8dh",
    "addr:street":"Pine Road Gleenfield",
    "iso:country":"GB",
    "sg:address":"14 Pine Road, Gleenfield",
    "sg:city":"Leicester",
    "sg:classifiers":[
        {
            "category":"Home & Garden",
            "subcategory":"Household Appliances",
            "type":"Retail Goods"
        }
    ],
    "sg:phone":"+44 116 287 2006",
    "sg:postcode":"LE3 8DH",
    "sg:province":"Leicestershire",
    "sg:tags":[
        "electrical"
    ],
    "wof:name":"Glenfield Domestic's",
    "wof:placetype":"venue"
},
  "geometry": {"coordinates":[-1.201733,52.647259],"type":"Point"}
}