{
  "type": "Feature",
  "properties": {
    "iso:country":"GB",
    "sg:address":"Chelford Road, Henbury",
    "sg:city":"Macclesfield",
    "sg:classifiers":[
        {
            "category":"Fast Food",
            "type":"Food & Drink"
        }
    ],
    "sg:phone":"+44 1625 424312",
    "sg:postcode":"SK11 9PG",
    "sg:province":"Cheshire",
    "sg:tags":[
        "away",
        "take"
    ],
    "wof:name":"Greenhall Witley Hotels",
    "wof:placetype":"venue"
},
  "geometry": {"coordinates":[-2.2840850353,53.271270752],"type":"Point"}
}