{
  "type": "Feature",
  "properties": {
    "iso:country":"GB",
    "sg:address":"Hillhaven, Belmont Avenue, Hucclecote",
    "sg:city":"Gloucester",
    "sg:classifiers":[
        {
            "category":"Building & Trades",
            "subcategory":"Construction",
            "type":"Services"
        }
    ],
    "sg:phone":"+44 1452 612010",
    "sg:postcode":"GL3 3SF",
    "sg:province":"Gloucestershire",
    "sg:tags":[
        "builder"
    ],
    "wof:name":"Charles Hill",
    "wof:placetype":"venue"
},
  "geometry": {"coordinates":[-2.188129,51.855614],"type":"Point"}
}