{
  "type": "Feature",
  "properties": {
    "iso:country":"GB",
    "sg:address":"Auldtown Of Carnousie, Forglen",
    "sg:city":"Turriff",
    "sg:classifiers":[
        {
            "category":"Farming",
            "subcategory":"Farm",
            "type":"Manufacturing & Wholesale Goods"
        }
    ],
    "sg:phone":"+44 1466 780303",
    "sg:postcode":"AB53 4LL",
    "sg:province":"Aberdeenshire",
    "sg:tags":[
        "mixed",
        "crop"
    ],
    "wof:name":"Maxwell Farms Ltd.",
    "wof:placetype":"venue"
},
  "geometry": {"coordinates":[-2.455229,57.539902],"type":"Point"}
}