{
  "type": "Feature",
  "properties": {
    "addr:full":"Insight Ho, 256 Radford Rd Coventry Warwickshire CV6 3BU",
    "addr:housenumber":"256",
    "addr:postcode":"cv6 3bu",
    "addr:street":"Radford Rd",
    "iso:country":"GB",
    "sg:address":"Insight Ho, 256 Radford Rd",
    "sg:city":"Coventry",
    "sg:classifiers":[
        {
            "category":"Professional",
            "subcategory":"Printing & Photocopies",
            "type":"Services"
        }
    ],
    "sg:phone":"+44 24 7660 1616",
    "sg:postcode":"CV6 3BU",
    "sg:province":"Warwickshire",
    "sg:tags":[
        "printer"
    ],
    "wof:name":"Printrite Co",
    "wof:placetype":"venue"
},
  "geometry": {"coordinates":[-1.52273,52.423759],"type":"Point"}
}