{
  "type": "Feature",
  "properties": {
    "addr:full":"Planet Wks, Arrow Trad Est, Corporation Rd, Audenshaw Manchester Greater Manchester M34 5LR",
    "addr:postcode":"m34 5lr",
    "addr:street":"Arrow Trad Est Corporation Rd",
    "iso:country":"GB",
    "sg:address":"Planet Wks, Arrow Trad Est, Corporation Rd, Audenshaw",
    "sg:city":"Manchester",
    "sg:classifiers":[
        {
            "category":"Professional",
            "subcategory":"Management & Consulting",
            "type":"Services"
        }
    ],
    "sg:phone":"+44 161 320 6699",
    "sg:postcode":"M34 5LR",
    "sg:province":"Greater Manchester",
    "sg:tags":[
        "fire",
        "consultant",
        "protection"
    ],
    "wof:name":"J T M Electrical Co Ltd",
    "wof:placetype":"venue"
},
  "geometry": {"coordinates":[-2.1291790009,53.4712753296],"type":"Point"}
}