{
  "type": "Feature",
  "properties": {
    "iso:country":"GB",
    "sg:address":"Unit 47 Barking Industrial Park, Alfreds Way",
    "sg:city":"Barking",
    "sg:classifiers":[
        {
            "category":"Home & Garden",
            "subcategory":"Home Furnishings",
            "type":"Retail Goods"
        },
        {
            "category":"Manufacturing",
            "subcategory":"Glass & Minerals",
            "type":"Manufacturing & Wholesale Goods"
        },
        {
            "category":"Wholesale",
            "subcategory":"Home Furnishings",
            "type":"Manufacturing & Wholesale Goods"
        }
    ],
    "sg:phone":"+44 20 8507 9301",
    "sg:postcode":"IG11 0TJ",
    "sg:province":"Essex",
    "sg:tags":[
        "shop",
        "household",
        "china",
        "crystalware",
        "wholesaler",
        "glassware"
    ],
    "wof:name":"MANNY'S WHOLESALE",
    "wof:placetype":"venue"
},
  "geometry": {"coordinates":[0.104205,51.516819],"type":"Point"}
}