{
  "type": "Feature",
  "properties": {
    "iso:country":"GB",
    "sg:address":"Dobshill Joinery Works, Dobshill",
    "sg:city":"Deeside",
    "sg:classifiers":[
        {
            "category":"Shopping",
            "subcategory":"Computers & Home Electronics",
            "type":"Retail Goods"
        }
    ],
    "sg:phone":"+44 1244 550997",
    "sg:postcode":"CH5 3LZ",
    "sg:province":"Flintshire",
    "wof:name":"Graham Shone & Son (Dobshill) Ltd.",
    "wof:placetype":"venue"
},
  "geometry": {"coordinates":[-3.024987936,53.2024803162],"type":"Point"}
}