{
  "type": "Feature",
  "properties": {
    "addr:full":"53 Rosebank Holyport Rd Fulham Greater London SW6 6LH",
    "addr:housenumber":"53",
    "addr:postcode":"sw6 6lh",
    "addr:street":"Rosebank Holyport Rd",
    "iso:country":"GB",
    "sg:address":"53 Rosebank Holyport Rd",
    "sg:city":"Fulham",
    "sg:classifiers":[
        {
            "category":"Professional",
            "subcategory":"Management & Consulting",
            "type":"Services"
        }
    ],
    "sg:phone":"+44 20 7385 2881",
    "sg:postcode":"SW6 6LH",
    "sg:province":"Greater London",
    "sg:tags":[
        "environmental",
        "consultant"
    ],
    "wof:name":"Environmental Context",
    "wof:placetype":"venue"
},
  "geometry": {"coordinates":[-0.222909,51.481609],"type":"Point"}
}