{
  "type": "Feature",
  "properties": {
    "addr:full":"13 Milford Road London Greater London W13 9HZ",
    "addr:housenumber":"13",
    "addr:postcode":"w13 9hz",
    "addr:street":"Milford Road",
    "iso:country":"GB",
    "sg:address":"13 Milford Road",
    "sg:city":"London",
    "sg:classifiers":[
        {
            "category":"Home & Garden",
            "subcategory":"Carpets & Floor Coverings",
            "type":"Retail Goods"
        }
    ],
    "sg:phone":"+44 20 7701 7028",
    "sg:postcode":"W13 9HZ",
    "sg:province":"Greater London",
    "sg:tags":[
        "carpets",
        "rug",
        "matting"
    ],
    "wof:name":"Gini (U K) Ltd.",
    "wof:placetype":"venue"
},
  "geometry": {"coordinates":[-0.3223359883,51.5078353882],"type":"Point"}
}