{
  "type": "Feature",
  "properties": {
    "iso:country":"GB",
    "sg:address":"5 Wilson Rd",
    "sg:city":"Chessington",
    "sg:classifiers":[
        {
            "category":"Professional",
            "type":"Services"
        }
    ],
    "sg:phone":"+44 20 8287 6201",
    "sg:postcode":"KT9 2HE",
    "sg:province":"Surrey",
    "sg:tags":[
        "interior",
        "furnishers",
        "designer"
    ],
    "wof:name":"Tina Ayling",
    "wof:placetype":"venue"
},
  "geometry": {"coordinates":[-0.29801,51.362465],"type":"Point"}
}