{
  "type": "Feature",
  "properties": {
    "iso:country":"GB",
    "sg:address":"7-9 Alexandra Road",
    "sg:city":"Grimsby",
    "sg:classifiers":[
        {
            "category":"Professional",
            "subcategory":"Computer Services",
            "type":"Services"
        }
    ],
    "sg:phone":"+44 1472 501234",
    "sg:postcode":"DN31 1RD",
    "sg:province":"Lincolnshire",
    "sg:tags":[
        "consultant"
    ],
    "wof:name":"L C S Group Ltd.",
    "wof:placetype":"venue"
},
  "geometry": {"coordinates":[-0.087825,53.566704],"type":"Point"}
}