{
  "type": "Feature",
  "properties": {
    "iso:country":"GB",
    "sg:address":"Yeadon Airport Industrial Estate, Gate 1 Harrogate Road, Yeadon",
    "sg:city":"Leeds",
    "sg:classifiers":[
        {
            "category":"Freight",
            "type":"Transportation"
        }
    ],
    "sg:phone":"+44 113 250 0222",
    "sg:postcode":"LS19 7WP",
    "sg:province":"West Yorkshire",
    "sg:tags":[
        "airfreight"
    ],
    "wof:name":"Wyng Roadflight Ltd.",
    "wof:placetype":"venue"
},
  "geometry": {"coordinates":[-1.65866,53.87619],"type":"Point"}
}