{
  "type": "Feature",
  "properties": {
    "iso:country":"GB",
    "sg:address":"Mill Lane",
    "sg:city":"Welshpool",
    "sg:classifiers":[
        {
            "category":"Manufacturing",
            "subcategory":"Building Materials",
            "type":"Manufacturing & Wholesale Goods"
        }
    ],
    "sg:phone":"+44 1938 556677",
    "sg:postcode":"SY21 7BL",
    "sg:province":"Shropshire",
    "sg:tags":[
        "merchant",
        "builder"
    ],
    "wof:name":"Boys & Boden Ltd.",
    "wof:placetype":"venue"
},
  "geometry": {"coordinates":[-3.1441500187,52.6607627869],"type":"Point"}
}