{
  "type": "Feature",
  "properties": {
    "addr:full":"Croft Road Industrial Estate Newcastle Staffordshire ST5 0TW",
    "addr:postcode":"st5 0tw",
    "addr:street":"Croft Road Industrial Estate",
    "iso:country":"GB",
    "sg:address":"Croft Road Industrial Estate",
    "sg:city":"Newcastle",
    "sg:classifiers":[
        {
            "category":"Home & Garden",
            "subcategory":"Hardware",
            "type":"Retail Goods"
        }
    ],
    "sg:phone":"+44 1782 753200",
    "sg:postcode":"ST5 0TW",
    "sg:province":"Staffordshire",
    "sg:tags":[
        "component",
        "electronic"
    ],
    "wof:name":"Aws Electronics Ltd.",
    "wof:placetype":"venue"
},
  "geometry": {"coordinates":[-2.2266139984,53.0176048279],"type":"Point"}
}