{
  "type": "Feature",
  "properties": {
    "iso:country":"GB",
    "sg:address":"96 Main Street",
    "sg:city":"Ayr",
    "sg:classifiers":[
        {
            "category":"Fast Food",
            "type":"Food & Drink"
        }
    ],
    "sg:phone":"+44 1292 288338",
    "sg:postcode":"KA8 8EF",
    "sg:province":"South Ayrshire",
    "sg:tags":[
        "away",
        "meal",
        "outlet",
        "take"
    ],
    "wof:name":"Hughes & Wallace",
    "wof:placetype":"venue"
},
  "geometry": {"coordinates":[-4.629684,55.468117],"type":"Point"}
}