{
  "type": "Feature",
  "properties": {
    "iso:country":"GB",
    "sg:address":"170 South Parade, Matlock Bath",
    "sg:city":"Matlock",
    "sg:classifiers":[
        {
            "category":"Travel",
            "subcategory":"Hotels & Motels",
            "type":"Entertainment"
        }
    ],
    "sg:postcode":"DE4 3NR",
    "sg:province":"Derbyshire",
    "sg:tags":[
        "house",
        "guest"
    ],
    "wof:name":"Old Museum Restaurant & Guest House",
    "wof:placetype":"venue"
},
  "geometry": {"coordinates":[-1.56361,53.119736],"type":"Point"}
}