{
  "type": "Feature",
  "properties": {
    "iso:country":"GB",
    "sg:address":"36 Collingwood Street",
    "sg:city":"Newcastle-upon-tyne",
    "sg:classifiers":[
        {
            "category":"Shopping",
            "subcategory":"News",
            "type":"Retail Goods"
        }
    ],
    "sg:phone":"+44 191 232 5179",
    "sg:postcode":"NE1 1JF",
    "sg:province":"Tyne and Wear",
    "sg:tags":[
        "newsagent"
    ],
    "wof:name":"City News",
    "wof:placetype":"venue"
},
  "geometry": {"coordinates":[-1.6137260199,54.9698753357],"type":"Point"}
}