{
  "type": "Feature",
  "properties": {
    "addr:full":"Unit 25 Croydon House, 1 Peall Road Croydon Surrey CR0 3EX",
    "addr:housenumber":"unit 25 croydon house 1",
    "addr:postcode":"cr0 3ex",
    "addr:street":"Peall Road",
    "iso:country":"GB",
    "sg:address":"Unit 25 Croydon House, 1 Peall Road",
    "sg:city":"Croydon",
    "sg:classifiers":[
        {
            "category":"Professional",
            "subcategory":"Detective & Security Services",
            "type":"Services"
        }
    ],
    "sg:phone":"+44 20 8288 0181",
    "sg:postcode":"CR0 3EX",
    "sg:province":"Surrey",
    "sg:tags":[
        "car"
    ],
    "wof:name":"Safe N Sound Communications",
    "wof:placetype":"venue"
},
  "geometry": {"coordinates":[-0.1229929999,51.3888931274],"type":"Point"}
}