{
  "type": "Feature",
  "properties": {
    "addr:full":"Roseland, The Causeway Arundel West Sussex BN18 9JL",
    "addr:postcode":"bn18 9jl",
    "addr:street":"The Causeway",
    "iso:country":"GB",
    "sg:address":"Roseland, The Causeway",
    "sg:city":"Arundel",
    "sg:classifiers":[
        {
            "category":"Shopping",
            "subcategory":"Antiques",
            "type":"Retail Goods"
        }
    ],
    "sg:phone":"+44 1903 883672",
    "sg:postcode":"BN18 9JL",
    "sg:province":"West Sussex",
    "wof:name":"Allcocks Roseland Restoration",
    "wof:placetype":"venue"
},
  "geometry": {"coordinates":[-0.5545889735,50.8548355103],"type":"Point"}
}