{
  "type": "Feature",
  "properties": {
    "addr:full":"Manor House, 40 Moat Lane Birmingham West Midlands B5 5BD",
    "addr:housenumber":"40",
    "addr:postcode":"b5 5bd",
    "addr:street":"Manor;Moat Lane",
    "iso:country":"GB",
    "sg:address":"Manor House, 40 Moat Lane",
    "sg:city":"Birmingham",
    "sg:classifiers":[
        {
            "category":"Wholesale",
            "subcategory":"Meat",
            "type":"Manufacturing & Wholesale Goods"
        }
    ],
    "sg:phone":"+44 121 622 4511",
    "sg:postcode":"B5 5BD",
    "sg:province":"West Midlands",
    "sg:tags":[
        "product"
    ],
    "wof:name":"Southdown Foods Ltd.",
    "wof:placetype":"venue"
},
  "geometry": {"coordinates":[-1.891422,52.475731],"type":"Point"}
}