{
  "type": "Feature",
  "properties": {
    "addr:full":"Selby Centre, Selby Rd Tottenham Greater London N17 8JL",
    "addr:postcode":"n17 8jl",
    "addr:street":"Selby Rd",
    "iso:country":"GB",
    "sg:address":"Selby Centre, Selby Rd",
    "sg:city":"Tottenham",
    "sg:classifiers":[
        {
            "category":"Arena",
            "subcategory":"Sports Club",
            "type":"Entertainment"
        }
    ],
    "sg:phone":"+44 20 8885 1407",
    "sg:postcode":"N17 8JL",
    "sg:province":"Greater London",
    "wof:name":"Wood Green Weight Lifting Club",
    "wof:placetype":"venue"
},
  "geometry": {"coordinates":[-0.0790100023,51.6073989868],"type":"Point"}
}