{
  "type": "Feature",
  "properties": {
    "addr:full":"Dorrington Farm, Rye Hill Road Harlow Essex CM18 7JF",
    "addr:postcode":"cm18 7jf",
    "addr:street":"Rye Hill Road",
    "iso:country":"GB",
    "sg:address":"Dorrington Farm, Rye Hill Road",
    "sg:city":"Harlow",
    "sg:classifiers":[
        {
            "category":"Manufacturing",
            "subcategory":"Tools & Machinery",
            "type":"Manufacturing & Wholesale Goods"
        },
        {
            "category":"Professional",
            "subcategory":"Business Services",
            "type":"Services"
        }
    ],
    "sg:phone":"+44 1279 422220",
    "sg:postcode":"CM18 7JF",
    "sg:province":"Essex",
    "sg:tags":[
        "industrial",
        "cleaners",
        "-",
        "commercial",
        "cleaning",
        "vacuum",
        "distributor",
        "mnfrs"
    ],
    "sg:website":"http://www.wcsuk.com",
    "wof:name":"Woodbridge Commercial Ltd.",
    "wof:placetype":"venue"
},
  "geometry": {"coordinates":[0.0975600034,51.7429199219],"type":"Point"}
}