{
  "type": "Feature",
  "properties": {
    "iso:country":"GB",
    "sg:address":"106 High Street",
    "sg:city":"Tewkesbury",
    "sg:classifiers":[
        {
            "category":"Shopping",
            "subcategory":"Florist",
            "type":"Retail Goods"
        }
    ],
    "sg:postcode":"GL20 5JZ",
    "sg:province":"Gloucestershire",
    "wof:name":"Hazel Andrew",
    "wof:placetype":"venue"
},
  "geometry": {"coordinates":[-2.156364,51.994965],"type":"Point"}
}