{
  "type": "Feature",
  "properties": {
    "iso:country":"GB",
    "sg:address":"Technology House, March Place",
    "sg:city":"Aylesbury",
    "sg:classifiers":[
        {
            "category":"Professional",
            "type":"Services"
        }
    ],
    "sg:postcode":"HP19 3UG",
    "sg:province":"Buckinghamshire",
    "sg:tags":[
        "repair",
        "tech",
        "maintenance"
    ],
    "wof:name":"Microtek Support Services",
    "wof:placetype":"venue"
},
  "geometry": {"coordinates":[-0.82727,51.818077],"type":"Point"}
}