{
  "type": "Feature",
  "properties": {
    "addr:full":"37 The Green Market Newcastle-upon-tyne Tyne and Wear NE1 7YA",
    "addr:housenumber":"37",
    "addr:postcode":"ne1 7ya",
    "addr:street":"The Green Market",
    "iso:country":"GB",
    "sg:address":"37 The Green Market",
    "sg:city":"Newcastle-upon-tyne",
    "sg:classifiers":[
        {
            "category":"Personal",
            "subcategory":"Shoe Repair & Shine",
            "type":"Services"
        },
        {
            "category":"Shopping",
            "subcategory":"Shoes",
            "type":"Retail Goods"
        }
    ],
    "sg:phone":"+44 191 232 7205",
    "sg:postcode":"NE1 7YA",
    "sg:province":"Tyne and Wear",
    "wof:name":"The Greenmarket Cobbler Ltd.",
    "wof:placetype":"venue"
},
  "geometry": {"coordinates":[-1.6123689413,54.9779167175],"type":"Point"}
}