{
  "type": "Feature",
  "properties": {
    "addr:full":"131 Carlton St Castleford West Yorkshire WF10 1EF",
    "addr:housenumber":"131",
    "addr:postcode":"wf10 1ef",
    "addr:street":"Carlton St",
    "iso:country":"GB",
    "sg:address":"131 Carlton St",
    "sg:city":"Castleford",
    "sg:classifiers":[
        {
            "category":"Home & Garden",
            "subcategory":"Furniture",
            "type":"Retail Goods"
        }
    ],
    "sg:phone":"+44 1977 513499",
    "sg:postcode":"WF10 1EF",
    "sg:province":"West Yorkshire",
    "wof:name":"Carlton Street Bed Centre",
    "wof:placetype":"venue"
},
  "geometry": {"coordinates":[-1.3558419943,53.7255897522],"type":"Point"}
}