{
  "type": "Feature",
  "properties": {
    "iso:country":"GB",
    "sg:address":"Alice Street",
    "sg:city":"Keighley",
    "sg:classifiers":[
        {
            "category":"Home & Garden",
            "subcategory":"Hardware",
            "type":"Retail Goods"
        }
    ],
    "sg:phone":"+44 1535 602532",
    "sg:postcode":"BD21 3JD",
    "sg:province":"West Yorkshire",
    "sg:tags":[
        "product",
        "wire",
        "electrical"
    ],
    "wof:name":"Bethel Rhodes & Sons (Wireworkers) Ltd.",
    "wof:placetype":"venue"
},
  "geometry": {"coordinates":[-1.909179,53.86935],"type":"Point"}
}