{
  "type": "Feature",
  "properties": {
    "iso:country":"GB",
    "sg:address":"153c Harrow Road",
    "sg:city":"Wembley",
    "sg:classifiers":[
        {
            "category":"Food & Beverages",
            "subcategory":"Meat & Fish",
            "type":"Retail Goods"
        }
    ],
    "sg:postcode":"HA9 6DN",
    "sg:province":"Greater London",
    "sg:tags":[
        "butcher"
    ],
    "wof:name":"M Balla",
    "wof:placetype":"venue"
},
  "geometry": {"coordinates":[-0.2794530094,51.5485877991],"type":"Point"}
}