{
  "type": "Feature",
  "properties": {
    "addr:full":"5 College Street York North Yorkshire YO1 7JF",
    "addr:housenumber":"5",
    "addr:postcode":"yo1 7jf",
    "addr:street":"College Street",
    "iso:country":"GB",
    "sg:address":"5 College Street",
    "sg:city":"York",
    "sg:classifiers":[
        {
            "category":"Organizations",
            "subcategory":"Non-profit Organization",
            "type":"Services"
        }
    ],
    "sg:phone":"+44 1904 557235",
    "sg:postcode":"YO1 7JF",
    "sg:province":"North Yorkshire",
    "sg:tags":[
        "charitable",
        "organisation",
        "voluntary",
        "charity"
    ],
    "wof:name":"ST WILLIAMS FOUNDATION",
    "wof:placetype":"venue"
},
  "geometry": {"coordinates":[-1.080246,53.962395],"type":"Point"}
}