{
  "type": "Feature",
  "properties": {
    "iso:country":"GB",
    "sg:address":"7 Dartford Road",
    "sg:city":"March",
    "sg:classifiers":[
        {
            "category":"Shopping",
            "subcategory":"Clothing, Apparel, & Fashions",
            "type":"Retail Goods"
        },
        {
            "category":"Shopping",
            "subcategory":"Baby Store",
            "type":"Retail Goods"
        }
    ],
    "sg:phone":"+44 1354 651414",
    "sg:postcode":"PE15 8LA",
    "sg:province":"Cambridgeshire",
    "sg:tags":[
        "child",
        "childrens",
        "babywear"
    ],
    "wof:name":"Kids Corner",
    "wof:placetype":"venue"
},
  "geometry": {"coordinates":[0.088059999,52.5513725281],"type":"Point"}
}