{
  "type": "Feature",
  "properties": {
    "iso:country":"GB",
    "sg:address":"1 College Rd",
    "sg:city":"Immingham",
    "sg:classifiers":[
        {
            "category":"Freight",
            "type":"Transportation"
        }
    ],
    "sg:phone":"+44 1469 540781",
    "sg:postcode":"DN40 3PL",
    "sg:province":"Lincolnshire",
    "sg:tags":[
        "haulage",
        "road"
    ],
    "wof:name":"P & A Deliveries",
    "wof:placetype":"venue"
},
  "geometry": {"coordinates":[-0.2825939953,53.6603813171],"type":"Point"}
}