{
  "type": "Feature",
  "properties": {
    "addr:full":"Dundas Place, The Village Glasgow South Lanarkshire G74 4JQ",
    "addr:postcode":"g74 4jq",
    "addr:street":"Dundas Place The Village",
    "iso:country":"GB",
    "sg:address":"Dundas Place, The Village",
    "sg:city":"Glasgow",
    "sg:classifiers":[
        {
            "category":"Retail",
            "subcategory":"Auto Rental",
            "type":"Services"
        }
    ],
    "sg:phone":"+44 1355 233111",
    "sg:postcode":"G74 4JQ",
    "sg:province":"South Lanarkshire",
    "sg:tags":[
        "car"
    ],
    "wof:name":"Central Garage Car Rental Ltd.",
    "wof:placetype":"venue"
},
  "geometry": {"coordinates":[-4.17903,55.766739],"type":"Point"}
}