{
  "type": "Feature",
  "properties": {
    "addr:full":"Crest House, 7 Highfield Road Birmingham West Midlands B15 3ED",
    "addr:housenumber":"7",
    "addr:postcode":"b15 3ed",
    "addr:street":"Highfield Road",
    "iso:country":"GB",
    "sg:address":"Crest House, 7 Highfield Road",
    "sg:city":"Birmingham",
    "sg:classifiers":[
        {
            "category":"Professional",
            "subcategory":"Advertising",
            "type":"Services"
        }
    ],
    "sg:phone":"+44 121 455 0188",
    "sg:postcode":"B15 3ED",
    "sg:province":"West Midlands",
    "wof:name":"Innervision Ltd.",
    "wof:placetype":"venue"
},
  "geometry": {"coordinates":[-1.924799,52.470482],"type":"Point"}
}