{
  "type": "Feature",
  "properties": {
    "iso:country":"GB",
    "sg:address":"160 Charnwood Road, Shepshed",
    "sg:city":"Loughborough",
    "sg:classifiers":[
        {
            "category":"Bars & Pubs",
            "type":"Food & Drink"
        },
        {
            "category":"Community Center",
            "subcategory":"Social",
            "type":"Public Place"
        }
    ],
    "sg:phone":"+44 1509 503283",
    "sg:postcode":"LE12 9NR",
    "sg:province":"Leicestershire",
    "sg:tags":[
        "pubs",
        "house",
        "inn",
        "activity"
    ],
    "wof:name":"THE RAILWAY",
    "wof:placetype":"venue"
},
  "geometry": {"coordinates":[-1.295202,52.76609],"type":"Point"}
}