{
  "type": "Feature",
  "properties": {
    "iso:country":"GB",
    "sg:address":"65 Garfield Road, Wimbledon",
    "sg:city":"London",
    "sg:classifiers":[
        {
            "category":"Professional",
            "subcategory":"Engineering",
            "type":"Services"
        }
    ],
    "sg:phone":"+44 20 8542 9290",
    "sg:postcode":"SW19 8RZ",
    "sg:province":"Greater London",
    "sg:tags":[
        "contractor",
        "electrical",
        "engineer"
    ],
    "wof:name":"Avg Electrical Services",
    "wof:placetype":"venue"
},
  "geometry": {"coordinates":[-0.185817,51.423103],"type":"Point"}
}