{
  "type": "Feature",
  "properties": {
    "addr:full":"1 Market Hill Buckingham Buckinghamshire MK18 1JX",
    "addr:housenumber":"1",
    "addr:postcode":"mk18 1jx",
    "addr:street":"Market Hill",
    "iso:country":"GB",
    "sg:address":"1 Market Hill",
    "sg:city":"Buckingham",
    "sg:classifiers":[
        {
            "category":"Retail",
            "subcategory":"Laundry & Dry Cleaning",
            "type":"Services"
        }
    ],
    "sg:phone":"+44 1280 824484",
    "sg:postcode":"MK18 1JX",
    "sg:province":"Buckinghamshire",
    "sg:tags":[
        "alteration"
    ],
    "wof:name":"Quality Cleaners",
    "wof:placetype":"venue"
},
  "geometry": {"coordinates":[-0.987308,52.000439],"type":"Point"}
}