{
  "type": "Feature",
  "properties": {
    "addr:full":"28 Weathercock Close, Woburn Sands Milton Keynes Bedfordshire MK17 8SS",
    "addr:housenumber":"28",
    "addr:postcode":"mk17 8ss",
    "addr:street":"Weathercock Close",
    "iso:country":"GB",
    "sg:address":"28 Weathercock Close, Woburn Sands",
    "sg:city":"Milton Keynes",
    "sg:classifiers":[
        {
            "category":"Building & Trades",
            "subcategory":"Landscaping Services",
            "type":"Services"
        }
    ],
    "sg:phone":"+44 1908 585339",
    "sg:postcode":"MK17 8SS",
    "sg:province":"Bedfordshire",
    "sg:tags":[
        "landscape",
        "contractor"
    ],
    "wof:name":"The Property Maintenance Group",
    "wof:placetype":"venue"
},
  "geometry": {"coordinates":[-0.6480770111,52.0180282593],"type":"Point"}
}