{
  "type": "Feature",
  "properties": {
    "addr:full":"117 St Albans Rd Watford Hertfordshire WD24 6QU",
    "addr:housenumber":"117",
    "addr:postcode":"wd24 6qu",
    "addr:street":"St Albans Rd",
    "iso:country":"GB",
    "sg:address":"117 St Albans Rd",
    "sg:city":"Watford",
    "sg:classifiers":[
        {
            "category":"Shopping",
            "subcategory":"Computers & Home Electronics",
            "type":"Retail Goods"
        }
    ],
    "sg:postcode":"WD24 6QU",
    "sg:province":"Hertfordshire",
    "sg:tags":[
        "consumables"
    ],
    "wof:name":"Norcil Ltd",
    "wof:placetype":"venue"
},
  "geometry": {"coordinates":[-0.3996849954,51.6648178101],"type":"Point"}
}