{
  "type": "Feature",
  "properties": {
    "addr:full":"154 Leigh Road Leigh Lancashire WN7 1SJ",
    "addr:housenumber":"154",
    "addr:postcode":"wn7 1sj",
    "addr:street":"Leigh Road Leigh",
    "iso:country":"GB",
    "sg:address":"154 Leigh Road",
    "sg:city":"Leigh",
    "sg:classifiers":[
        {
            "category":"Professional",
            "subcategory":"Computer Services",
            "type":"Services"
        }
    ],
    "sg:postcode":"WN7 1SJ",
    "sg:province":"Lancashire",
    "sg:tags":[
        "system",
        "software"
    ],
    "wof:name":"T H Information Systems Ltd.",
    "wof:placetype":"venue"
},
  "geometry": {"coordinates":[-2.518036,53.504185],"type":"Point"}
}