{
  "type": "Feature",
  "properties": {
    "iso:country":"GB",
    "sg:address":"6 Rutherfield Avenue",
    "sg:city":"Bexhill-on-sea",
    "sg:classifiers":[
        {
            "category":"Banks & Credit Unions",
            "subcategory":"Financial Services",
            "type":"Services"
        }
    ],
    "sg:postcode":"TN40 1SY",
    "sg:province":"East Sussex",
    "sg:tags":[
        "claim",
        "assessor"
    ],
    "wof:name":"B W Locke & Co",
    "wof:placetype":"venue"
},
  "geometry": {"coordinates":[0.479654,50.842163],"type":"Point"}
}