{
  "type": "Feature",
  "properties": {
    "addr:full":"The Docks, Portishead Bristol Somerset BS20 7DG",
    "addr:postcode":"bs20 7dg",
    "iso:country":"GB",
    "sg:address":"The Docks, Portishead",
    "sg:city":"Bristol",
    "sg:classifiers":[
        {
            "category":"Professional",
            "subcategory":"Engineering",
            "type":"Services"
        }
    ],
    "sg:phone":"+44 1275 842111",
    "sg:postcode":"BS20 7DG",
    "sg:province":"Somerset",
    "sg:tags":[
        "civil",
        "engineer"
    ],
    "wof:name":"Pearce Project Management",
    "wof:placetype":"venue"
},
  "geometry": {"coordinates":[-2.7681400776,51.4915084839],"type":"Point"}
}