{
  "type": "Feature",
  "properties": {
    "addr:full":"Seafield Rd, Leith Edinburgh Edinburgh City of Edinburgh EH6 7LD",
    "addr:postcode":"eh6 7ld",
    "addr:street":"Seafield Rd",
    "iso:country":"GB",
    "sg:address":"Seafield Rd, Leith Edinburgh",
    "sg:city":"Edinburgh",
    "sg:classifiers":[
        {
            "category":"Autos & Motor Vehicles",
            "subcategory":"Automobile Sales",
            "type":"Retail Goods"
        }
    ],
    "sg:phone":"+44 131 553 4940",
    "sg:postcode":"EH6 7LD",
    "sg:province":"City of Edinburgh",
    "sg:tags":[
        "commercial"
    ],
    "wof:name":"Daewoo Support Centre",
    "wof:placetype":"venue"
},
  "geometry": {"coordinates":[-3.164114,55.977493],"type":"Point"}
}