{
  "type": "Feature",
  "properties": {
    "iso:country":"GB",
    "sg:address":"65 Victoria Road West, Cleveleys",
    "sg:city":"Blackpool",
    "sg:classifiers":[
        {
            "category":"Shopping",
            "subcategory":"Department Store",
            "type":"Retail Goods"
        }
    ],
    "sg:phone":"+44 1253 853617",
    "sg:postcode":"FY5 1AJ",
    "sg:province":"Lancashire",
    "wof:name":"Levick & Hewitson",
    "wof:placetype":"venue"
},
  "geometry": {"coordinates":[-3.0420870781,53.8773765564],"type":"Point"}
}