{
  "type": "Feature",
  "properties": {
    "addr:full":"42 Dalsetter Avenue Glasgow Glasgow City G15 8TE",
    "addr:housenumber":"42",
    "addr:postcode":"g15 8te",
    "addr:street":"Dalsetter Avenue",
    "iso:country":"GB",
    "sg:address":"42 Dalsetter Avenue",
    "sg:city":"Glasgow",
    "sg:classifiers":[
        {
            "category":"Professional",
            "subcategory":"Business Services",
            "type":"Services"
        }
    ],
    "sg:postcode":"G15 8TE",
    "sg:province":"Glasgow City",
    "sg:tags":[
        "accomodation"
    ],
    "wof:name":"Drumchapel Community Business Ltd.",
    "wof:placetype":"venue"
},
  "geometry": {"coordinates":[-4.366254,55.906151],"type":"Point"}
}