{
  "type": "Feature",
  "properties": {
    "addr:full":"92 High Street Northallerton North Yorkshire DL7 8PT",
    "addr:housenumber":"92",
    "addr:postcode":"dl7 8pt",
    "addr:street":"High Street",
    "iso:country":"GB",
    "sg:address":"92 High Street",
    "sg:city":"Northallerton",
    "sg:classifiers":[
        {
            "category":"Professional",
            "subcategory":"Advertising",
            "type":"Services"
        },
        {
            "category":"Deli",
            "type":"Food & Drink"
        }
    ],
    "sg:phone":"+44 1609 772880",
    "sg:postcode":"DL7 8PT",
    "sg:province":"North Yorkshire",
    "sg:tags":[
        "delicatessen",
        "agency"
    ],
    "wof:name":"Lewis & Cooper Ltd.",
    "wof:placetype":"venue"
},
  "geometry": {"coordinates":[-1.434185,54.339981],"type":"Point"}
}