{
  "type": "Feature",
  "properties": {
    "addr:full":"152 Church Hill Loughton Essex IG10 1LJ",
    "addr:housenumber":"152",
    "addr:postcode":"ig10 1lj",
    "addr:street":"Church Hill",
    "iso:country":"GB",
    "sg:address":"152 Church Hill",
    "sg:city":"Loughton",
    "sg:classifiers":[
        {
            "category":"Shopping",
            "subcategory":"News",
            "type":"Retail Goods"
        }
    ],
    "sg:phone":"+44 20 8508 1994",
    "sg:postcode":"IG10 1LJ",
    "sg:province":"Essex",
    "sg:tags":[
        "newsagent"
    ],
    "wof:name":"Newsbox",
    "wof:placetype":"venue"
},
  "geometry": {"coordinates":[0.0664409995,51.6559028625],"type":"Point"}
}