{
  "type": "Feature",
  "properties": {
    "addr:full":"Mold Road Wrexham Wrexham LL11 2AH",
    "addr:postcode":"ll11 2ah",
    "addr:street":"Mold Road",
    "iso:country":"GB",
    "sg:address":"Mold Road",
    "sg:city":"Wrexham",
    "sg:classifiers":[
        {
            "category":"Arena",
            "subcategory":"Sports Club",
            "type":"Entertainment"
        }
    ],
    "sg:phone":"+44 1978 262129",
    "sg:postcode":"LL11 2AH",
    "sg:province":"Wrexham",
    "wof:name":"The Wrexham Association Football Club Ltd.",
    "wof:placetype":"venue"
},
  "geometry": {"coordinates":[-3.0063359737,53.0520896912],"type":"Point"}
}