{
  "type": "Feature",
  "properties": {
    "iso:country":"GB",
    "sg:address":"276 Hillmorton Road",
    "sg:city":"Rugby",
    "sg:classifiers":[
        {
            "category":"Shopping",
            "type":"Retail Goods"
        }
    ],
    "sg:phone":"+44 1788 576659",
    "sg:postcode":"CV22 5BW",
    "sg:province":"Warwickshire",
    "sg:tags":[
        "part",
        "accessory"
    ],
    "wof:name":"Paddox Cycles & Auto Spares",
    "wof:placetype":"venue"
},
  "geometry": {"coordinates":[-1.231306,52.361256],"type":"Point"}
}