{
  "type": "Feature",
  "properties": {
    "addr:full":"9 Rectory Road Stourbridge Staffordshire DY8 2HA",
    "addr:housenumber":"9",
    "addr:postcode":"dy8 2ha",
    "addr:street":"Rectory Road",
    "iso:country":"GB",
    "sg:address":"9 Rectory Road",
    "sg:city":"Stourbridge",
    "sg:classifiers":[
        {
            "category":"Social Services",
            "subcategory":"Retirement Home",
            "type":"Services"
        }
    ],
    "sg:phone":"+44 1384 373306",
    "sg:postcode":"DY8 2HA",
    "sg:province":"Staffordshire",
    "sg:tags":[
        "rest"
    ],
    "wof:name":"Holly Lodge",
    "wof:placetype":"venue"
},
  "geometry": {"coordinates":[-2.1388199329,52.4464035034],"type":"Point"}
}