{
  "type": "Feature",
  "properties": {
    "addr:full":"144 High Street Montrose Aberdeenshire DD10 8JB",
    "addr:housenumber":"144",
    "addr:postcode":"dd10 8jb",
    "addr:street":"High Street",
    "iso:country":"GB",
    "sg:address":"144 High Street",
    "sg:city":"Montrose",
    "sg:classifiers":[
        {
            "category":"Shopping",
            "subcategory":"Clothing, Apparel, & Fashions",
            "type":"Retail Goods"
        }
    ],
    "sg:postcode":"DD10 8JB",
    "sg:province":"Aberdeenshire",
    "sg:tags":[
        "ladieswear"
    ],
    "wof:name":"Larouge",
    "wof:placetype":"venue"
},
  "geometry": {"coordinates":[-2.4685590267,56.7111358643],"type":"Point"}
}