{
  "type": "Feature",
  "properties": {
    "addr:full":"2 The Parade, Market Street, Claycross Chesterfield Derbyshire S45 9JE",
    "addr:housenumber":"2",
    "addr:postcode":"s45 9je",
    "addr:street":"The Parade Market Street",
    "iso:country":"GB",
    "sg:address":"2 The Parade, Market Street, Claycross",
    "sg:city":"Chesterfield",
    "sg:classifiers":[
        {
            "category":"Cafe",
            "type":"Food & Drink"
        }
    ],
    "sg:phone":"+44 1246 250737",
    "sg:postcode":"S45 9JE",
    "sg:province":"Derbyshire",
    "sg:tags":[
        "tea",
        "room"
    ],
    "wof:name":"Aristocrat",
    "wof:placetype":"venue"
},
  "geometry": {"coordinates":[-1.4021869898,53.1644325256],"type":"Point"}
}