{
  "type": "Feature",
  "properties": {
    "addr:full":"35 Hartfield Avenue, Elstree Borehamwood Hertfordshire WD6 3JB",
    "addr:housenumber":"35",
    "addr:postcode":"wd6 3jb",
    "addr:street":"Hartfield Avenue",
    "iso:country":"GB",
    "sg:address":"35 Hartfield Avenue, Elstree",
    "sg:city":"Borehamwood",
    "sg:classifiers":[
        {
            "category":"Professional",
            "subcategory":"Management & Consulting",
            "type":"Services"
        }
    ],
    "sg:postcode":"WD6 3JB",
    "sg:province":"Hertfordshire",
    "sg:tags":[
        "consultant",
        "business"
    ],
    "wof:name":"Essakay Consulting Ltd",
    "wof:placetype":"venue"
},
  "geometry": {"coordinates":[-0.2790749967,51.6474571228],"type":"Point"}
}