{
  "type": "Feature",
  "properties": {
    "addr:full":"Lowestoft Rd Watford Hertfordshire WD2 5AX",
    "addr:postcode":"wd2 5ax",
    "addr:street":"Lowestoft Rd",
    "iso:country":"GB",
    "sg:address":"Lowestoft Rd",
    "sg:city":"Watford",
    "sg:classifiers":[
        {
            "category":"Retail",
            "subcategory":"Auto Repair",
            "type":"Services"
        }
    ],
    "sg:phone":"+44 1923 225237",
    "sg:postcode":"WD2 5AX",
    "sg:province":"Hertfordshire",
    "sg:tags":[
        "modification",
        "garage"
    ],
    "wof:name":"Mini & Metro Specialists",
    "wof:placetype":"venue"
},
  "geometry": {"coordinates":[-0.3996190131,51.6695556641],"type":"Point"}
}