{
  "type": "Feature",
  "properties": {
    "addr:full":"61 High St Harlow Essex CM19 5EA",
    "addr:housenumber":"61",
    "addr:postcode":"cm19 5ea",
    "addr:street":"High St",
    "iso:country":"GB",
    "sg:address":"61 High St",
    "sg:city":"Harlow",
    "sg:classifiers":[
        {
            "category":"Government",
            "subcategory":"Police Station",
            "type":"Public Place"
        }
    ],
    "sg:phone":"+44 1279 793124",
    "sg:postcode":"CM19 5EA",
    "sg:province":"Essex",
    "sg:tags":[
        "support"
    ],
    "wof:name":"Roydon Police Station",
    "wof:placetype":"venue"
},
  "geometry": {"coordinates":[0.0402720012,51.7714614868],"type":"Point"}
}