{
  "type": "Feature",
  "properties": {
    "addr:full":"3-4 Blackheath Gro London Greater London SE3 0DD",
    "addr:housenumber":"3-4",
    "addr:postcode":"se3 0dd",
    "addr:street":"Blackheath Gro",
    "iso:country":"GB",
    "sg:address":"3-4 Blackheath Gro",
    "sg:city":"London",
    "sg:classifiers":[
        {
            "category":"Education",
            "subcategory":"Library",
            "type":"Public Place"
        }
    ],
    "sg:phone":"+44 20 8852 5309",
    "sg:postcode":"SE3 0DD",
    "sg:province":"Greater London",
    "sg:tags":[
        "book"
    ],
    "wof:name":"Blackheath Village Library",
    "wof:placetype":"venue"
},
  "geometry": {"coordinates":[0.0093369996,51.4660682678],"type":"Point"}
}