{
  "type": "Feature",
  "properties": {
    "addr:full":"27 Lydiate Lane, Eccleston Chorley Lancashire PR7 6LX",
    "addr:housenumber":"27",
    "addr:postcode":"pr7 6lx",
    "addr:street":"Lydiate Lane",
    "iso:country":"GB",
    "sg:address":"27 Lydiate Lane, Eccleston",
    "sg:city":"Chorley",
    "sg:classifiers":[
        {
            "category":"Building & Trades",
            "subcategory":"Construction",
            "type":"Services"
        }
    ],
    "sg:phone":"+44 1257 451239",
    "sg:postcode":"PR7 6LX",
    "sg:province":"Lancashire",
    "sg:tags":[
        "decorator",
        "painter"
    ],
    "wof:name":"S J Holmes",
    "wof:placetype":"venue"
},
  "geometry": {"coordinates":[-2.7309861183,53.6596717834],"type":"Point"}
}