{
  "type": "Feature",
  "properties": {
    "iso:country":"GB",
    "sg:address":"14 Pentwyn Deintyr",
    "sg:city":"Treharris",
    "sg:classifiers":[
        {
            "category":"Building & Trades",
            "subcategory":"Construction",
            "type":"Services"
        }
    ],
    "sg:phone":"+44 1443 410555",
    "sg:postcode":"CF46 5EA",
    "sg:province":"Caerphilly",
    "sg:tags":[
        "demolition",
        "contractor"
    ],
    "wof:name":"Step-Up",
    "wof:placetype":"venue"
},
  "geometry": {"coordinates":[-3.3112080097,51.6563796997],"type":"Point"}
}