{
  "type": "Feature",
  "properties": {
    "addr:full":"Honiton Community College, School La Honiton Devon EX14 8QW",
    "addr:postcode":"ex14 8qw",
    "addr:street":"La",
    "iso:country":"GB",
    "sg:address":"Honiton Community College, School La",
    "sg:city":"Honiton",
    "sg:classifiers":[
        {
            "category":"Community Center",
            "subcategory":"Youth",
            "type":"Public Place"
        }
    ],
    "sg:phone":"+44 1404 42102",
    "sg:postcode":"EX14 8QW",
    "sg:province":"Devon",
    "sg:tags":[
        "organisation",
        "centre"
    ],
    "wof:name":"Honiton Youth Centre",
    "wof:placetype":"venue"
},
  "geometry": {"coordinates":[-3.196906,50.797386],"type":"Point"}
}