{
  "type": "Feature",
  "properties": {
    "addr:full":"3 Croft Road Ware Hertfordshire SG12 0BD",
    "addr:housenumber":"3",
    "addr:postcode":"sg12 0bd",
    "addr:street":"Croft Road Ware",
    "iso:country":"GB",
    "sg:address":"3 Croft Road",
    "sg:city":"Ware",
    "sg:classifiers":[
        {
            "category":"Retail",
            "subcategory":"Driving School",
            "type":"Services"
        }
    ],
    "sg:phone":"+44 1920 464591",
    "sg:postcode":"SG12 0BD",
    "sg:province":"Hertfordshire",
    "wof:name":"Brian Robert Stevens",
    "wof:placetype":"venue"
},
  "geometry": {"coordinates":[-0.0389849991,51.8155441284],"type":"Point"}
}