{
  "type": "Feature",
  "properties": {
    "addr:full":"Riverside Business Centre, New Rd Crickhowell Monmouthshire NP8 1AY",
    "addr:postcode":"np8 1ay",
    "addr:street":"New Rd",
    "iso:country":"GB",
    "sg:address":"Riverside Business Centre, New Rd",
    "sg:city":"Crickhowell",
    "sg:classifiers":[
        {
            "category":"Recreation",
            "subcategory":"Fishing",
            "type":"Entertainment"
        }
    ],
    "sg:phone":"+44 1873 811877",
    "sg:postcode":"NP8 1AY",
    "sg:province":"Monmouthshire",
    "sg:tags":[
        "angling"
    ],
    "wof:name":"Pont Crug-Y-Hywel",
    "wof:placetype":"venue"
},
  "geometry": {"coordinates":[-3.1674540043,51.8719558716],"type":"Point"}
}