{
  "type": "Feature",
  "properties": {
    "addr:full":"112a-116 Tarleton House Bolton Lancashire BL1 4DH",
    "addr:housenumber":"112a-116",
    "addr:postcode":"bl1 4dh",
    "addr:street":"Tarleton House",
    "iso:country":"GB",
    "sg:address":"112a-116 Tarleton House",
    "sg:city":"Bolton",
    "sg:classifiers":[
        {
            "category":"Professional",
            "subcategory":"Lawyer & Legal Services",
            "type":"Services"
        }
    ],
    "sg:phone":"+44 1204 845700",
    "sg:postcode":"BL1 4DH",
    "sg:province":"Lancashire",
    "sg:tags":[
        "practitioner",
        "insolvency"
    ],
    "wof:name":"Ratcliffe & Co.",
    "wof:placetype":"venue"
},
  "geometry": {"coordinates":[-2.4265940189,53.578289032],"type":"Point"}
}