{
  "type": "Feature",
  "properties": {
    "iso:country":"GB",
    "sg:address":"85 Myddleton Road",
    "sg:city":"London",
    "sg:classifiers":[
        {
            "category":"Fast Food",
            "type":"Food & Drink"
        }
    ],
    "sg:phone":"+44 20 8889 4290",
    "sg:postcode":"N22 8NE",
    "sg:province":"Greater London",
    "sg:tags":[
        "away",
        "meal",
        "outlet",
        "take"
    ],
    "wof:name":"Win-Lok Chinese",
    "wof:placetype":"venue"
},
  "geometry": {"coordinates":[-0.1174490005,51.6062927246],"type":"Point"}
}