{
  "type": "Feature",
  "properties": {
    "iso:country":"GB",
    "sg:address":"1 Grange Road",
    "sg:city":"Edinburgh",
    "sg:classifiers":[
        {
            "category":"Bars & Pubs",
            "type":"Food & Drink"
        }
    ],
    "sg:phone":"+44 131 667 2335",
    "sg:postcode":"EH9 1UH",
    "sg:province":"City of Edinburgh",
    "sg:tags":[
        "pubs",
        "inn"
    ],
    "wof:name":"Bierex",
    "wof:placetype":"venue"
},
  "geometry": {"coordinates":[-3.1822190285,55.9366912842],"type":"Point"}
}