{
  "type": "Feature",
  "properties": {
    "iso:country":"GB",
    "sg:address":"16 Holmfirth Road, Meltham",
    "sg:city":"Huddersfield",
    "sg:classifiers":[
        {
            "category":"Shopping",
            "subcategory":"Pets & Pet Supplies",
            "type":"Retail Goods"
        }
    ],
    "sg:phone":"+44 1484 851172",
    "sg:postcode":"HD9 4ES",
    "sg:province":"South Yorkshire",
    "sg:tags":[
        "shop"
    ],
    "wof:name":"Meltham Pets & Garden Supplies",
    "wof:placetype":"venue"
},
  "geometry": {"coordinates":[-1.850077,53.591122],"type":"Point"}
}