{
  "type": "Feature",
  "properties": {
    "addr:full":"29 Waverley Road, Drayton Portsmouth Hampshire PO6 1RA",
    "addr:housenumber":"29",
    "addr:postcode":"hampshire po6 1ra",
    "addr:street":"Waverley Road",
    "iso:country":"GB",
    "sg:address":"29 Waverley Road, Drayton",
    "sg:city":"Portsmouth",
    "sg:classifiers":[
        {
            "category":"Building & Trades",
            "subcategory":"Plumbing",
            "type":"Services"
        }
    ],
    "sg:postcode":"PO6 1RA",
    "sg:province":"Hampshire",
    "sg:tags":[
        "drain",
        "clearance",
        "sewer"
    ],
    "wof:name":"Freeflow",
    "wof:placetype":"venue"
},
  "geometry": {"coordinates":[-1.046699,50.845448],"type":"Point"}
}