{
  "type": "Feature",
  "properties": {
    "addr:full":"5 Grosvenor Ave, Breaston Derby Derbyshire DE72 3AB",
    "addr:housenumber":"5",
    "addr:postcode":"de72 3ab",
    "addr:street":"Grosvenor Ave",
    "iso:country":"GB",
    "sg:address":"5 Grosvenor Ave, Breaston",
    "sg:city":"Derby",
    "sg:classifiers":[
        {
            "category":"Home & Garden",
            "subcategory":"Building Materials",
            "type":"Retail Goods"
        }
    ],
    "sg:postcode":"DE72 3AB",
    "sg:province":"Derbyshire",
    "sg:tags":[
        "insulation",
        "installers"
    ],
    "wof:name":"Miller,Clive,",
    "wof:placetype":"venue"
},
  "geometry": {"coordinates":[-1.309057,52.899822],"type":"Point"}
}