{
  "type": "Feature",
  "properties": {
    "addr:full":"22 Bondgate Without Alnwick Northumberland NE66 1PN",
    "addr:housenumber":"22",
    "addr:postcode":"ne66 1pn",
    "addr:street":"Bondgate Without",
    "iso:country":"GB",
    "sg:address":"22 Bondgate Without",
    "sg:city":"Alnwick",
    "sg:classifiers":[
        {
            "category":"Personal",
            "type":"Services"
        },
        {
            "category":"Professional",
            "subcategory":"Lawyer & Legal Services",
            "type":"Services"
        }
    ],
    "sg:phone":"+44 1665 604135",
    "sg:postcode":"NE66 1PN",
    "sg:province":"Northumberland",
    "sg:tags":[
        "advice",
        "counselling"
    ],
    "wof:name":"Citizens Advice Bureau",
    "wof:placetype":"venue"
},
  "geometry": {"coordinates":[-1.7022000551,55.4121704102],"type":"Point"}
}