{
  "type": "Feature",
  "properties": {
    "iso:country":"GB",
    "sg:address":"The Mill, Boden Street",
    "sg:city":"Chard",
    "sg:classifiers":[
        {
            "category":"Professional",
            "subcategory":"Printing & Photocopies",
            "type":"Services"
        }
    ],
    "sg:phone":"+44 1460 61297",
    "sg:postcode":"TA20 2AX",
    "sg:province":"Devon",
    "sg:tags":[
        "plate",
        "lithographic",
        "maker"
    ],
    "wof:name":"Rapid Print & Design",
    "wof:placetype":"venue"
},
  "geometry": {"coordinates":[-2.9550440311,50.8406715393],"type":"Point"}
}