{
  "type": "Feature",
  "properties": {
    "addr:full":"91 Front St Nottingham Nottinghamshire NG5 7EB",
    "addr:housenumber":"91",
    "addr:postcode":"ng5 7eb",
    "addr:street":"Front St",
    "iso:country":"GB",
    "sg:address":"91 Front St",
    "sg:city":"Nottingham",
    "sg:classifiers":[
        {
            "category":"Bars & Pubs",
            "type":"Food & Drink"
        }
    ],
    "sg:phone":"+44 115 967 1022",
    "sg:postcode":"NG5 7EB",
    "sg:province":"Nottinghamshire",
    "sg:tags":[
        "pubs",
        "inn"
    ],
    "wof:name":"Horse & Jockey",
    "wof:placetype":"venue"
},
  "geometry": {"coordinates":[-1.1276390553,53.0039520264],"type":"Point"}
}