{
  "type": "Feature",
  "properties": {
    "iso:country":"GB",
    "sg:address":"213-217 Bethnal Green Rd",
    "sg:city":"Bethnal Green",
    "sg:classifiers":[
        {
            "category":"Insurance",
            "subcategory":"Insurance Agent",
            "type":"Services"
        }
    ],
    "sg:phone":"+44 20 7739 3511",
    "sg:postcode":"E2 6AB",
    "sg:province":"Greater London",
    "wof:name":"Century Insurance Centre",
    "wof:placetype":"venue"
},
  "geometry": {"coordinates":[-0.0677990019,51.5261955261],"type":"Point"}
}