{
  "type": "Feature",
  "properties": {
    "addr:full":"17 Woodside Grn London Greater London SE25 5EY",
    "addr:housenumber":"17",
    "addr:postcode":"se25 5ey",
    "addr:street":"Woodside Grn",
    "iso:country":"GB",
    "sg:address":"17 Woodside Grn",
    "sg:city":"London",
    "sg:classifiers":[
        {
            "category":"Farming",
            "subcategory":"Livestock Farm",
            "type":"Manufacturing & Wholesale Goods"
        }
    ],
    "sg:postcode":"SE25 5EY",
    "sg:province":"Greater London",
    "sg:tags":[
        "breeder"
    ],
    "wof:name":"Flowers of Woodside",
    "wof:placetype":"venue"
},
  "geometry": {"coordinates":[-0.071771,51.385944],"type":"Point"}
}