{
  "type": "Feature",
  "properties": {
    "addr:full":"Lawrence Avenue New Malden Surrey KT3 5NB",
    "addr:postcode":"kt3 5nb",
    "addr:street":"Lawrence Avenue",
    "iso:country":"GB",
    "sg:address":"Lawrence Avenue",
    "sg:city":"New Malden",
    "sg:classifiers":[
        {
            "category":"Education",
            "subcategory":"School",
            "type":"Public Place"
        }
    ],
    "sg:phone":"+44 20 8337 9620",
    "sg:postcode":"KT3 5NB",
    "sg:province":"Surrey",
    "sg:tags":[
        "local",
        "authority"
    ],
    "wof:name":"Malden Manor Primary School",
    "wof:placetype":"venue"
},
  "geometry": {"coordinates":[-0.2643589973,51.3903961182],"type":"Point"}
}