{
  "type": "Feature",
  "properties": {
    "addr:full":"209 Cricklewood Broadway London Greater London NW2 3HS",
    "addr:housenumber":"209",
    "addr:postcode":"nw2 3hs",
    "addr:street":"Cricklewood Broadway",
    "iso:country":"GB",
    "sg:address":"209 Cricklewood Broadway",
    "sg:city":"London",
    "sg:classifiers":[
        {
            "category":"Professional",
            "subcategory":"Computer Services",
            "type":"Services"
        }
    ],
    "sg:phone":"+44 20 8208 1770",
    "sg:postcode":"NW2 3HS",
    "sg:province":"Greater London",
    "sg:tags":[
        "information"
    ],
    "wof:name":"Islamic Information Centre",
    "wof:placetype":"venue"
},
  "geometry": {"coordinates":[-0.216548,51.557507],"type":"Point"}
}