{
  "type": "Feature",
  "properties": {
    "addr:full":"17 Culbard Street Elgin Moray IV30 1JT",
    "addr:housenumber":"17",
    "addr:postcode":"iv30 1jt",
    "addr:street":"Culbard Street",
    "iso:country":"GB",
    "sg:address":"17 Culbard Street",
    "sg:city":"Elgin",
    "sg:classifiers":[
        {
            "category":"Personal",
            "subcategory":"Beauty Salon",
            "type":"Services"
        }
    ],
    "sg:phone":"+44 1343 547958",
    "sg:postcode":"IV30 1JT",
    "sg:province":"Moray",
    "sg:tags":[
        "unisex",
        "hairdresser"
    ],
    "wof:name":"Kenneth's Hair Stylists",
    "wof:placetype":"venue"
},
  "geometry": {"coordinates":[-3.3150119781,57.6471366882],"type":"Point"}
}