{
  "type": "Feature",
  "properties": {
    "addr:full":"2 Stockton Road Coventry West Midlands CV1 5HY",
    "addr:housenumber":"2",
    "addr:postcode":"cv1 5hy",
    "addr:street":"Stockton Road",
    "iso:country":"GB",
    "sg:address":"2 Stockton Road",
    "sg:city":"Coventry",
    "sg:classifiers":[
        {
            "category":"Food & Beverages",
            "subcategory":"Meat & Fish",
            "type":"Retail Goods"
        }
    ],
    "sg:phone":"+44 24 7622 8963",
    "sg:postcode":"CV1 5HY",
    "sg:province":"West Midlands",
    "sg:tags":[
        "butcher"
    ],
    "wof:name":"Irfan Khan Butchers",
    "wof:placetype":"venue"
},
  "geometry": {"coordinates":[-1.499089,52.415867],"type":"Point"}
}