{
  "type": "Feature",
  "properties": {
    "iso:country":"GB",
    "sg:address":"Centenary House, Gilberd Court, Newcomen Way",
    "sg:city":"Colchester",
    "sg:classifiers":[
        {
            "category":"Professional",
            "subcategory":"Printing & Photocopies",
            "type":"Services"
        }
    ],
    "sg:phone":"+44 1206 755206",
    "sg:postcode":"CO4 9WN",
    "sg:province":"Essex",
    "sg:tags":[
        "computer",
        "tag",
        "label"
    ],
    "wof:name":"Pago Ltd.",
    "wof:placetype":"venue"
},
  "geometry": {"coordinates":[0.924455,51.921791],"type":"Point"}
}