{
  "type": "Feature",
  "properties": {
    "addr:full":"Unit E Weaverthorpe Park Bradford West Yorkshire BD4 9RQ",
    "addr:postcode":"bd4 9rq",
    "addr:street":"Bradford West",
    "iso:country":"GB",
    "sg:address":"Unit E Weaverthorpe Park",
    "sg:city":"Bradford",
    "sg:classifiers":[
        {
            "category":"Shopping",
            "subcategory":"Discount & Variety Stores",
            "type":"Retail Goods"
        }
    ],
    "sg:phone":"+44 1274 653977",
    "sg:postcode":"BD4 9RQ",
    "sg:province":"West Yorkshire",
    "sg:tags":[
        "centre"
    ],
    "wof:name":"Poundstretcher Ltd",
    "wof:placetype":"venue"
},
  "geometry": {"coordinates":[-1.709419,53.766884],"type":"Point"}
}