{
  "type": "Feature",
  "properties": {
    "iso:country":"GB",
    "sg:address":"21 Northgate Street",
    "sg:city":"Bury St Edmunds",
    "sg:classifiers":[
        {
            "category":"Health Services",
            "subcategory":"Podiatrist",
            "type":"Services"
        },
        {
            "category":"Health Services",
            "subcategory":"Chiropractor",
            "type":"Services"
        }
    ],
    "sg:phone":"+44 1284 702796",
    "sg:postcode":"IP33 1HP",
    "sg:province":"Suffolk",
    "sg:tags":[
        "podiatrists",
        "chiropodist"
    ],
    "wof:name":"James Waters & Penelope",
    "wof:placetype":"venue"
},
  "geometry": {"coordinates":[0.716047,52.248936],"type":"Point"}
}