{
  "type": "Feature",
  "properties": {
    "iso:country":"GB",
    "sg:address":"10 Rothesay Place",
    "sg:city":"Edinburgh",
    "sg:classifiers":[
        {
            "category":"Professional",
            "subcategory":"Management & Consulting",
            "type":"Services"
        }
    ],
    "sg:phone":"+44 131 226 5731",
    "sg:postcode":"EH3 7SL",
    "sg:province":"City of Edinburgh",
    "sg:tags":[
        "consultant",
        "business"
    ],
    "wof:name":"Osprey Pmi Ltd.",
    "wof:placetype":"venue"
},
  "geometry": {"coordinates":[-3.2173950672,55.9504470825],"type":"Point"}
}