{
  "type": "Feature",
  "properties": {
    "iso:country":"GB",
    "sg:address":"8 Market Street",
    "sg:city":"Margate",
    "sg:classifiers":[
        {
            "category":"Restaurant",
            "type":"Food & Drink"
        }
    ],
    "sg:phone":"+44 1843 223750",
    "sg:postcode":"CT9 1EU",
    "sg:province":"Kent",
    "sg:tags":[
        "-",
        "chinese"
    ],
    "wof:name":"Rice Bowl",
    "wof:placetype":"venue"
},
  "geometry": {"coordinates":[1.380875,51.389301],"type":"Point"}
}