{
  "type": "Feature",
  "properties": {
    "iso:country":"GB",
    "sg:address":"26 Cove Road",
    "sg:city":"Farnborough",
    "sg:classifiers":[
        {
            "category":"Personal",
            "subcategory":"Barber",
            "type":"Services"
        }
    ],
    "sg:phone":"+44 1252 515603",
    "sg:postcode":"GU14 0EN",
    "sg:province":"Hampshire",
    "sg:tags":[
        "men's",
        "hairdresser"
    ],
    "wof:name":"Mandy 'K' Barbers Shop",
    "wof:placetype":"venue"
},
  "geometry": {"coordinates":[-0.766481,51.292641],"type":"Point"}
}