{
  "type": "Feature",
  "properties": {
    "addr:full":"4 William Street Herne Bay Kent CT6 5EJ",
    "addr:housenumber":"4",
    "addr:postcode":"ct6 5ej",
    "addr:street":"William Street",
    "iso:country":"GB",
    "sg:address":"4 William Street",
    "sg:city":"Herne Bay",
    "sg:classifiers":[
        {
            "category":"Shopping",
            "subcategory":"Clothing, Apparel, & Fashions",
            "type":"Retail Goods"
        }
    ],
    "sg:phone":"+44 1227 372489",
    "sg:postcode":"CT6 5EJ",
    "sg:province":"Kent",
    "sg:tags":[
        "shop"
    ],
    "wof:name":"Margot Gowns",
    "wof:placetype":"venue"
},
  "geometry": {"coordinates":[1.128461957,51.3724212646],"type":"Point"}
}