{
  "type": "Feature",
  "properties": {
    "addr:full":"21 Stockbridge Road Winchester Hampshire SO22 6RN",
    "addr:housenumber":"21",
    "addr:postcode":"so22 6rn",
    "addr:street":"Stockbridge Road",
    "iso:country":"GB",
    "sg:address":"21 Stockbridge Road",
    "sg:city":"Winchester",
    "sg:classifiers":[
        {
            "category":"Shopping",
            "subcategory":"Bicycles & Sporting Goods",
            "type":"Retail Goods"
        }
    ],
    "sg:phone":"+44 1962 868066",
    "sg:postcode":"SO22 6RN",
    "sg:province":"Hampshire",
    "sg:tags":[
        "equipment",
        "gym",
        "sport"
    ],
    "wof:name":"Chic Physique Health & Fitness",
    "wof:placetype":"venue"
},
  "geometry": {"coordinates":[-1.324707,51.067379],"type":"Point"}
}