{
  "type": "Feature",
  "properties": {
    "iso:country":"GB",
    "sg:address":"Longridge",
    "sg:city":"Knutsford",
    "sg:classifiers":[
        {
            "category":"Government",
            "subcategory":"Office",
            "type":"Public Place"
        }
    ],
    "sg:phone":"+44 1565 634578",
    "sg:postcode":"WA16 8PA",
    "sg:province":"Cheshire",
    "sg:tags":[
        "local"
    ],
    "wof:name":"Cheshire County Council",
    "wof:placetype":"venue"
},
  "geometry": {"coordinates":[-2.34864,53.307858],"type":"Point"}
}