{
  "type": "Feature",
  "properties": {
    "addr:full":"63 College Road Liverpool Merseyside L23 0RL",
    "addr:housenumber":"63",
    "addr:postcode":"l23 0rl",
    "addr:street":"College Road",
    "iso:country":"GB",
    "sg:address":"63 College Road",
    "sg:city":"Liverpool",
    "sg:classifiers":[
        {
            "category":"Personal",
            "subcategory":"Beauty Salon",
            "type":"Services"
        }
    ],
    "sg:phone":"+44 151 949 0949",
    "sg:postcode":"L23 0RL",
    "sg:province":"Merseyside",
    "sg:tags":[
        "unisex",
        "hairdresser"
    ],
    "wof:name":"John-Paul Hairdressing",
    "wof:placetype":"venue"
},
  "geometry": {"coordinates":[-3.029481,53.483505],"type":"Point"}
}