{
  "type": "Feature",
  "properties": {
    "addr:full":"Portrack Lane Stockton-on-tees Durham TS18 2HQ",
    "addr:postcode":"ts18 2hq",
    "addr:street":"Portrack Lane",
    "iso:country":"GB",
    "sg:address":"Portrack Lane",
    "sg:city":"Stockton-on-tees",
    "sg:classifiers":[
        {
            "category":"Food & Beverages",
            "subcategory":"Liquor & Beverages",
            "type":"Retail Goods"
        }
    ],
    "sg:postcode":"TS18 2HQ",
    "sg:province":"Durham",
    "sg:tags":[
        "drink",
        "soft"
    ],
    "wof:name":"Wright & Co. Ltd.",
    "wof:placetype":"venue"
},
  "geometry": {"coordinates":[-1.2987190485,54.5704345703],"type":"Point"}
}