{
  "type": "Feature",
  "properties": {
    "addr:full":"3 Northwood Drive Sittingbourne Kent ME10 4QN",
    "addr:housenumber":"3",
    "addr:postcode":"me10 4qn",
    "addr:street":"Northwood Drive",
    "iso:country":"GB",
    "sg:address":"3 Northwood Drive",
    "sg:city":"Sittingbourne",
    "sg:classifiers":[
        {
            "category":"Fast Food",
            "type":"Food & Drink"
        }
    ],
    "sg:phone":"+44 1795 428118",
    "sg:postcode":"ME10 4QN",
    "sg:province":"Kent",
    "sg:tags":[
        "away",
        "meal",
        "outlet",
        "take"
    ],
    "wof:name":"Hot Wok's",
    "wof:placetype":"venue"
},
  "geometry": {"coordinates":[0.7347030044,51.3310012817],"type":"Point"}
}