{
  "type": "Feature",
  "properties": {
    "addr:full":"Main St, Greenodd Ulverston Cumbria LA12 7QZ",
    "addr:postcode":"la12 7qz",
    "addr:street":"Main St",
    "iso:country":"GB",
    "sg:address":"Main St, Greenodd",
    "sg:city":"Ulverston",
    "sg:classifiers":[
        {
            "category":"Travel",
            "subcategory":"Hotels & Motels",
            "type":"Entertainment"
        }
    ],
    "sg:phone":"+44 1229 861246",
    "sg:postcode":"LA12 7QZ",
    "sg:province":"Cumbria",
    "wof:name":"Machells Arms Hotel",
    "wof:placetype":"venue"
},
  "geometry": {"coordinates":[-3.0923540592,54.1967315674],"type":"Point"}
}