{
  "type": "Feature",
  "properties": {
    "addr:full":"Wapseys Wood, Oxford Road Gerrards Cross Buckinghamshire SL9 8TE",
    "addr:postcode":"sl9 8te",
    "addr:street":"Oxford Road",
    "iso:country":"GB",
    "sg:address":"Wapseys Wood, Oxford Road",
    "sg:city":"Gerrards Cross",
    "sg:classifiers":[
        {
            "category":"Utilities",
            "subcategory":"Refuse",
            "type":"Services"
        }
    ],
    "sg:phone":"+44 1753 880579",
    "sg:postcode":"SL9 8TE",
    "sg:province":"Buckinghamshire",
    "sg:tags":[
        "disposal",
        "waste"
    ],
    "wof:name":"Onyx Leigh Environmental Ltd.",
    "wof:placetype":"venue"
},
  "geometry": {"coordinates":[-0.5625789762,51.5789756775],"type":"Point"}
}