{
  "type": "Feature",
  "properties": {
    "iso:country":"GB",
    "sg:address":"26 Monyash Close",
    "sg:city":"Ilkeston",
    "sg:classifiers":[
        {
            "category":"Building & Trades",
            "subcategory":"Construction",
            "type":"Services"
        }
    ],
    "sg:phone":"+44 115 932 9219",
    "sg:postcode":"DE7 8PR",
    "sg:province":"Derbyshire",
    "sg:tags":[
        "builder"
    ],
    "wof:name":"R A Toms",
    "wof:placetype":"venue"
},
  "geometry": {"coordinates":[-1.3137710094,52.9863204956],"type":"Point"}
}