{
  "type": "Feature",
  "properties": {
    "addr:full":"Village Way, Trafford Park Manchester Cheshire M17 1RL",
    "addr:postcode":"m17 1rl",
    "addr:street":"Village Way",
    "iso:country":"GB",
    "sg:address":"Village Way, Trafford Park",
    "sg:city":"Manchester",
    "sg:classifiers":[
        {
            "category":"Shopping",
            "subcategory":"Computers & Home Electronics",
            "type":"Retail Goods"
        }
    ],
    "sg:phone":"+44 161 872 0100",
    "sg:postcode":"M17 1RL",
    "sg:province":"Cheshire",
    "wof:name":"Just Printers",
    "wof:placetype":"venue"
},
  "geometry": {"coordinates":[-2.3069410324,53.4671363831],"type":"Point"}
}