{
  "type": "Feature",
  "properties": {
    "iso:country":"GB",
    "sg:address":"Wallgrove Farm, Low Lane, Tushingham",
    "sg:city":"Whitchurch",
    "sg:classifiers":[
        {
            "category":"Manufacturing",
            "subcategory":"Metals",
            "type":"Manufacturing & Wholesale Goods"
        }
    ],
    "sg:postcode":"SY13 4QL",
    "sg:province":"Cheshire",
    "sg:tags":[
        "steel",
        "fabricator",
        "erectors"
    ],
    "wof:name":"Wallgrove Fabrications",
    "wof:placetype":"venue"
},
  "geometry": {"coordinates":[-2.685209,52.970558],"type":"Point"}
}