{
  "type": "Feature",
  "properties": {
    "addr:full":"St Georges House, Dragons Wharf, Dragons Lane Sandbach Cheshire CW11 3PA",
    "addr:postcode":"cw11 3pa",
    "addr:street":"Dragons Wharf Dragons Lane",
    "iso:country":"GB",
    "sg:address":"St Georges House, Dragons Wharf, Dragons Lane",
    "sg:city":"Sandbach",
    "sg:classifiers":[
        {
            "category":"Professional",
            "subcategory":"Engineering",
            "type":"Services"
        }
    ],
    "sg:phone":"+44 1270 750323",
    "sg:postcode":"CW11 3PA",
    "sg:province":"Cheshire",
    "wof:name":"Rainer U K Ltd.",
    "wof:placetype":"venue"
},
  "geometry": {"coordinates":[-2.405911,53.157433],"type":"Point"}
}