{
  "type": "Feature",
  "properties": {
    "iso:country":"GB",
    "sg:address":"65 Petty France",
    "sg:city":"London",
    "sg:classifiers":[
        {
            "category":"Professional",
            "subcategory":"Business Services",
            "type":"Services"
        }
    ],
    "sg:phone":"+44 20 7654 5800",
    "sg:postcode":"SW1H 9EU",
    "sg:province":"Greater London",
    "sg:tags":[
        "trade"
    ],
    "wof:name":"British Chambers of Commerce",
    "wof:placetype":"venue"
},
  "geometry": {"coordinates":[-0.13743,51.499119],"type":"Point"}
}