{
  "type": "Feature",
  "properties": {
    "addr:full":"18 Middle Road Southampton Hampshire SO31 7GH",
    "addr:housenumber":"18",
    "addr:postcode":"so31 7gh",
    "addr:street":"Middle Road",
    "iso:country":"GB",
    "sg:address":"18 Middle Road",
    "sg:city":"Southampton",
    "sg:classifiers":[
        {
            "category":"Food & Beverages",
            "subcategory":"Fruits & Vegetables",
            "type":"Retail Goods"
        }
    ],
    "sg:phone":"+44 1489 575193",
    "sg:postcode":"SO31 7GH",
    "sg:province":"Hampshire",
    "sg:tags":[
        "greengrocer"
    ],
    "wof:name":"A G Axton",
    "wof:placetype":"venue"
},
  "geometry": {"coordinates":[-1.268358,50.87244],"type":"Point"}
}