{
  "type": "Feature",
  "properties": {
    "iso:country":"GB",
    "sg:address":"20 Green Lanes",
    "sg:city":"London",
    "sg:classifiers":[
        {
            "category":"Food & Beverages",
            "subcategory":"Supermarket",
            "type":"Retail Goods"
        }
    ],
    "sg:phone":"+44 20 8881 6239",
    "sg:postcode":"N13 6HT",
    "sg:province":"Greater London",
    "wof:name":"Oz Tum Greenlane Supermarket",
    "wof:placetype":"venue"
},
  "geometry": {"coordinates":[-0.109514,51.610481],"type":"Point"}
}