{
  "type": "Feature",
  "properties": {
    "iso:country":"GB",
    "sg:address":"Branbridges Rd",
    "sg:city":"Tonbridge",
    "sg:classifiers":[
        {
            "category":"Professional",
            "subcategory":"Engineering",
            "type":"Services"
        }
    ],
    "sg:phone":"+44 1622 871325",
    "sg:postcode":"TN12 5HE",
    "sg:province":"Kent",
    "sg:tags":[
        "civil",
        "engineer"
    ],
    "wof:name":"Arnold & Nathan Try Build Ltd",
    "wof:placetype":"venue"
},
  "geometry": {"coordinates":[0.396807,51.208538],"type":"Point"}
}