{
  "type": "Feature",
  "properties": {
    "iso:country":"GB",
    "sg:address":"Unit 4, Roman Way, Godmanchester",
    "sg:city":"Huntingdon",
    "sg:classifiers":[
        {
            "category":"Building & Trades",
            "subcategory":"Construction",
            "type":"Services"
        }
    ],
    "sg:postcode":"PE18 8HN",
    "sg:province":"Cambridgeshire",
    "sg:tags":[
        "glazier"
    ],
    "wof:name":"A D Plumb (Glass & Glazing)",
    "wof:placetype":"venue"
},
  "geometry": {"coordinates":[-0.1699499935,52.3188209534],"type":"Point"}
}