{
  "type": "Feature",
  "properties": {
    "iso:country":"GB",
    "sg:address":"32 Laceys Lane, Exning",
    "sg:city":"Newmarket",
    "sg:classifiers":[
        {
            "category":"Home & Garden",
            "subcategory":"Carpets & Floor Coverings",
            "type":"Retail Goods"
        }
    ],
    "sg:phone":"+44 7860 141232",
    "sg:postcode":"CB8 7HL",
    "sg:province":"Cambridgeshire",
    "sg:tags":[
        "carpets",
        "rug",
        "matting"
    ],
    "wof:name":"Carpet Magic",
    "wof:placetype":"venue"
},
  "geometry": {"coordinates":[0.3679400086,52.2612113953],"type":"Point"}
}