{
  "type": "Feature",
  "properties": {
    "iso:country":"GB",
    "sg:address":"Gatley Hill House, Church Rd, Gatley",
    "sg:city":"Cheadle",
    "sg:classifiers":[
        {
            "category":"Education",
            "subcategory":"Library",
            "type":"Public Place"
        }
    ],
    "sg:phone":"+44 161 491 3340",
    "sg:postcode":"SK8 4EY",
    "sg:province":"Cheshire",
    "sg:tags":[
        "book"
    ],
    "wof:name":"Gatley Library",
    "wof:placetype":"venue"
},
  "geometry": {"coordinates":[-2.235073,53.392639],"type":"Point"}
}