{
  "type": "Feature",
  "properties": {
    "addr:full":"Icknield House, East Cheap Letchworth Hertfordshire SG6 3DF",
    "addr:postcode":"sg6 3df",
    "addr:street":"East Cheap Letchworth",
    "iso:country":"GB",
    "sg:address":"Icknield House, East Cheap",
    "sg:city":"Letchworth",
    "sg:classifiers":[
        {
            "category":"Insurance",
            "subcategory":"Insurance Agent",
            "type":"Services"
        }
    ],
    "sg:phone":"+44 1462 480367",
    "sg:postcode":"SG6 3DF",
    "sg:province":"Hertfordshire",
    "sg:tags":[
        "broker"
    ],
    "wof:name":"Aegis Insurance Brokers Ltd.",
    "wof:placetype":"venue"
},
  "geometry": {"coordinates":[-0.2279500067,51.9790496826],"type":"Point"}
}