{
  "type": "Feature",
  "properties": {
    "addr:full":"Rectory Lane, Middleton Cheney Banbury Northamptonshire OX17 2NZ",
    "addr:postcode":"ox17 2nz",
    "addr:street":"Rectory Lane",
    "iso:country":"GB",
    "sg:address":"Rectory Lane, Middleton Cheney",
    "sg:city":"Banbury",
    "sg:classifiers":[
        {
            "category":"Health Services",
            "subcategory":"Nursing And Care Facility",
            "type":"Services"
        }
    ],
    "sg:phone":"+44 1295 710494",
    "sg:postcode":"OX17 2NZ",
    "sg:province":"Northamptonshire",
    "sg:tags":[
        "home"
    ],
    "wof:name":"Cheney House Nursing Home",
    "wof:placetype":"venue"
},
  "geometry": {"coordinates":[-1.2612240314,52.068145752],"type":"Point"}
}