{
  "type": "Feature",
  "properties": {
    "addr:full":"26 Upr Poole Rd Dursley Gloucestershire GL11 4LE",
    "addr:housenumber":"26",
    "addr:postcode":"gl11 4le",
    "addr:street":"Upr Poole Rd",
    "iso:country":"GB",
    "sg:address":"26 Upr Poole Rd",
    "sg:city":"Dursley",
    "sg:classifiers":[
        {
            "category":"Farming",
            "subcategory":"Dairy Farm",
            "type":"Manufacturing & Wholesale Goods"
        }
    ],
    "sg:postcode":"GL11 4LE",
    "sg:province":"Gloucestershire",
    "wof:name":"Westaway,P W,",
    "wof:placetype":"venue"
},
  "geometry": {"coordinates":[-2.353004,51.678925],"type":"Point"}
}