{
  "type": "Feature",
  "properties": {
    "iso:country":"GB",
    "sg:address":"73 Ness Road, Shoeburyness",
    "sg:city":"Southend-on-sea",
    "sg:classifiers":[
        {
            "category":"Farming",
            "subcategory":"Poultry Farm",
            "type":"Manufacturing & Wholesale Goods"
        }
    ],
    "sg:phone":"+44 1702 292034",
    "sg:postcode":"SS3 9DB",
    "sg:province":"Essex",
    "wof:name":"Southend Poultry",
    "wof:placetype":"venue"
},
  "geometry": {"coordinates":[0.782896,51.531445],"type":"Point"}
}