{
  "type": "Feature",
  "properties": {
    "addr:full":"1 Shire Lane, Heath Chesterfield Derbyshire S44 5SQ",
    "addr:housenumber":"1",
    "addr:postcode":"s44 5sq",
    "addr:street":"Shire Lane",
    "iso:country":"GB",
    "sg:address":"1 Shire Lane, Heath",
    "sg:city":"Chesterfield",
    "sg:classifiers":[
        {
            "category":"Building & Trades",
            "subcategory":"Construction",
            "type":"Services"
        }
    ],
    "sg:postcode":"S44 5SQ",
    "sg:province":"Derbyshire",
    "sg:tags":[
        "glazier",
        "decorator",
        "painter"
    ],
    "wof:name":"John Stephen Morris",
    "wof:placetype":"venue"
},
  "geometry": {"coordinates":[-1.3434430361,53.2001190186],"type":"Point"}
}