{
  "type": "Feature",
  "properties": {
    "addr:full":"26a Short Heath Rd, Erdington Birmingham West Midlands B23 6JX",
    "addr:housenumber":"26a",
    "addr:postcode":"b23 6jx",
    "addr:street":"Short Heath Rd",
    "iso:country":"GB",
    "sg:address":"26a Short Heath Rd, Erdington",
    "sg:city":"Birmingham",
    "sg:classifiers":[
        {
            "category":"Autos & Motor Vehicles",
            "subcategory":"Automobile Sales",
            "type":"Retail Goods"
        }
    ],
    "sg:postcode":"B23 6JX",
    "sg:province":"West Midlands",
    "sg:tags":[
        "car"
    ],
    "wof:name":"Franklin,Chris,",
    "wof:placetype":"venue"
},
  "geometry": {"coordinates":[-1.8449480534,52.5289268494],"type":"Point"}
}