{
  "type": "Feature",
  "properties": {
    "iso:country":"GB",
    "sg:address":"202 Mansfield Rd",
    "sg:city":"Nottingham",
    "sg:classifiers":[
        {
            "category":"Fast Food",
            "type":"Food & Drink"
        }
    ],
    "sg:postcode":"NG1 3HX",
    "sg:province":"Nottinghamshire",
    "sg:tags":[
        "away",
        "take"
    ],
    "wof:name":"Mallmange Ltd",
    "wof:placetype":"venue"
},
  "geometry": {"coordinates":[-1.1523790359,52.9646873474],"type":"Point"}
}