{
  "type": "Feature",
  "properties": {
    "iso:country":"GB",
    "sg:address":"115 Alexandra Parade",
    "sg:city":"Dunoon",
    "sg:classifiers":[
        {
            "category":"Taxi",
            "type":"Transportation"
        },
        {
            "category":"Military Area",
            "subcategory":"Air Force Base",
            "type":"Public Place"
        }
    ],
    "sg:phone":"+44 1369 706444",
    "sg:postcode":"PA23 8AW",
    "sg:province":"Argyll and Bute",
    "sg:tags":[
        "hire",
        "private"
    ],
    "wof:name":"Clyde Independent Taxis",
    "wof:placetype":"venue"
},
  "geometry": {"coordinates":[-4.9188451767,55.9542350769],"type":"Point"}
}