{
  "type": "Feature",
  "properties": {
    "iso:country":"GB",
    "sg:address":"207 Soho Road, Handsworth",
    "sg:city":"Birmingham",
    "sg:classifiers":[
        {
            "category":"Food & Beverages",
            "subcategory":"Bakery",
            "type":"Retail Goods"
        }
    ],
    "sg:phone":"+44 121 554 0869",
    "sg:postcode":"B21 9SX",
    "sg:province":"West Midlands",
    "sg:tags":[
        "baker"
    ],
    "wof:name":"H V Smith (Caterers)",
    "wof:placetype":"venue"
},
  "geometry": {"coordinates":[-1.93342,52.503014],"type":"Point"}
}