{
  "type": "Feature",
  "properties": {
    "addr:full":"21 Spey Drive Oakham Leicestershire LE15 6JP",
    "addr:housenumber":"21",
    "addr:postcode":"le15 6jp",
    "addr:street":"Spey Drive",
    "iso:country":"GB",
    "sg:address":"21 Spey Drive",
    "sg:city":"Oakham",
    "sg:classifiers":[
        {
            "category":"Professional",
            "subcategory":"Engineering",
            "type":"Services"
        }
    ],
    "sg:postcode":"LE15 6JP",
    "sg:province":"Leicestershire",
    "sg:tags":[
        "contractor",
        "electrical",
        "engineer"
    ],
    "wof:name":"T S Lee",
    "wof:placetype":"venue"
},
  "geometry": {"coordinates":[-0.7370839715,52.661693573],"type":"Point"}
}