{
  "type": "Feature",
  "properties": {
    "iso:country":"GB",
    "sg:address":"28-32 Salisbury Road, Amesbury",
    "sg:city":"Salisbury",
    "sg:classifiers":[
        {
            "category":"Retail",
            "subcategory":"Auto Repair",
            "type":"Services"
        }
    ],
    "sg:phone":"+44 1980 622633",
    "sg:postcode":"SP4 7HL",
    "sg:province":"Hampshire",
    "sg:tags":[
        "modification",
        "garage"
    ],
    "wof:name":"Auto Central Service Centre",
    "wof:placetype":"venue"
},
  "geometry": {"coordinates":[-1.7779380083,51.169757843],"type":"Point"}
}