{
  "type": "Feature",
  "properties": {
    "iso:country":"GB",
    "sg:address":"15 Beech House Road",
    "sg:city":"Croydon",
    "sg:classifiers":[
        {
            "category":"Building & Trades",
            "subcategory":"Construction",
            "type":"Services"
        }
    ],
    "sg:phone":"+44 20 8656 0857",
    "sg:postcode":"CR0 1JQ",
    "sg:province":"Surrey",
    "sg:tags":[
        "decorator",
        "painter"
    ],
    "wof:name":"Croydon Maintenance",
    "wof:placetype":"venue"
},
  "geometry": {"coordinates":[-0.094508,51.370323],"type":"Point"}
}