{
  "type": "Feature",
  "properties": {
    "addr:full":"1 Heritage House, North Street Glenrothes Fife KY7 5NA",
    "addr:housenumber":"1",
    "addr:postcode":"ky7 5na",
    "addr:street":"Heritage;North Street",
    "iso:country":"GB",
    "sg:address":"1 Heritage House, North Street",
    "sg:city":"Glenrothes",
    "sg:classifiers":[
        {
            "category":"Banks & Credit Unions",
            "subcategory":"Financial Services",
            "type":"Services"
        }
    ],
    "sg:phone":"+44 1592 755689",
    "sg:postcode":"KY7 5NA",
    "sg:province":"Fife",
    "sg:tags":[
        "adviser"
    ],
    "wof:name":"Slater Hogg Mortgages",
    "wof:placetype":"venue"
},
  "geometry": {"coordinates":[-3.173744,56.197208],"type":"Point"}
}