{
  "type": "Feature",
  "properties": {
    "iso:country":"GB",
    "sg:address":"330 Ledbury Road",
    "sg:city":"Hereford",
    "sg:classifiers":[
        {
            "category":"Coffee & Tea",
            "type":"Food & Drink"
        }
    ],
    "sg:phone":"+44 1432 274643",
    "sg:postcode":"HR1 1QN",
    "sg:province":"Herefordshire",
    "wof:name":"Bewley's Coffee",
    "wof:placetype":"venue"
},
  "geometry": {"coordinates":[-2.684628,52.058422],"type":"Point"}
}