{
  "type": "Feature",
  "properties": {
    "addr:full":"104 Hornby Street Bury Lancashire BL9 5BB",
    "addr:housenumber":"104",
    "addr:postcode":"bl9 5bb",
    "addr:street":"Hornby Street",
    "iso:country":"GB",
    "sg:address":"104 Hornby Street",
    "sg:city":"Bury",
    "sg:classifiers":[
        {
            "category":"Home & Garden",
            "subcategory":"Home Furnishings",
            "type":"Retail Goods"
        }
    ],
    "sg:postcode":"BL9 5BB",
    "sg:province":"Lancashire",
    "sg:tags":[
        "blind",
        "curtain",
        "fitting"
    ],
    "wof:name":"A & D Curtain Textiles",
    "wof:placetype":"venue"
},
  "geometry": {"coordinates":[-2.2928960323,53.5990257263],"type":"Point"}
}