{
  "type": "Feature",
  "properties": {
    "iso:country":"GB",
    "sg:address":"37-39 Grainger St, Newcastle",
    "sg:city":"Newcastle Upon Tyne",
    "sg:classifiers":[
        {
            "category":"Education",
            "subcategory":"College",
            "type":"Public Place"
        }
    ],
    "sg:phone":"+44 191 232 3880",
    "sg:postcode":"NE1 5JE",
    "sg:province":"Tyne and Wear",
    "sg:tags":[
        "school"
    ],
    "wof:name":"National Schoolwear Centres",
    "wof:placetype":"venue"
},
  "geometry": {"coordinates":[-1.6158590317,54.970539093],"type":"Point"}
}