{
  "type": "Feature",
  "properties": {
    "addr:full":"91 Heath Street London Greater London NW3 6SS",
    "addr:housenumber":"91",
    "addr:postcode":"nw3 6ss",
    "addr:street":"Heath Street",
    "iso:country":"GB",
    "sg:address":"91 Heath Street",
    "sg:city":"London",
    "sg:classifiers":[
        {
            "category":"Real Estate",
            "subcategory":"Real Estate Agent",
            "type":"Services"
        }
    ],
    "sg:phone":"+44 20 7794 8088",
    "sg:postcode":"NW3 6SS",
    "sg:province":"Greater London",
    "wof:name":"Spyer & Dove Estate Agents",
    "wof:placetype":"venue"
},
  "geometry": {"coordinates":[-0.178727,51.558876],"type":"Point"}
}