{
  "type": "Feature",
  "properties": {
    "iso:country":"GB",
    "sg:address":"9 Wallace Street",
    "sg:city":"Paisley",
    "sg:classifiers":[
        {
            "category":"Freight",
            "type":"Transportation"
        }
    ],
    "sg:phone":"+44 141 889 3513",
    "sg:postcode":"PA3 2BU",
    "sg:province":"Renfrewshire",
    "sg:tags":[
        "haulage",
        "road"
    ],
    "wof:name":"J & M Taylor (Holdings) Ltd.",
    "wof:placetype":"venue"
},
  "geometry": {"coordinates":[-4.42549,55.85136],"type":"Point"}
}