{
  "type": "Feature",
  "properties": {
    "iso:country":"GB",
    "sg:address":"Meridian West, Meridian Business Park",
    "sg:city":"Leicester",
    "sg:classifiers":[
        {
            "category":"Professional",
            "subcategory":"Engineering",
            "type":"Services"
        }
    ],
    "sg:phone":"+44 116 263 0670",
    "sg:postcode":"LE3 2XS",
    "sg:province":"Leicestershire",
    "sg:tags":[
        "contractor",
        "electrical",
        "engineer"
    ],
    "wof:name":"East Midlands Electricity Contracting",
    "wof:placetype":"venue"
},
  "geometry": {"coordinates":[-1.18027,52.605171],"type":"Point"}
}