{
  "type": "Feature",
  "properties": {
    "addr:full":"21a Woburn Street, Ampthill Bedford Bedfordshire MK45 2HP",
    "addr:housenumber":"21a",
    "addr:postcode":"mk45 2hp",
    "addr:street":"Woburn Street",
    "iso:country":"GB",
    "sg:address":"21a Woburn Street, Ampthill",
    "sg:city":"Bedford",
    "sg:classifiers":[
        {
            "category":"Social Services",
            "subcategory":"Retirement Home",
            "type":"Services"
        }
    ],
    "sg:phone":"+44 1525 840555",
    "sg:postcode":"MK45 2HP",
    "sg:province":"Bedfordshire",
    "sg:tags":[
        "care"
    ],
    "wof:name":"Home From Hospital (Bedfordshire) Ltd.",
    "wof:placetype":"venue"
},
  "geometry": {"coordinates":[-0.494531,52.031864],"type":"Point"}
}