{
  "type": "Feature",
  "properties": {
    "addr:full":"Halifax Rd Dewsbury West Yorkshire WF13 4JD",
    "addr:postcode":"wf13 4jd",
    "addr:street":"Halifax Rd",
    "iso:country":"GB",
    "sg:address":"Halifax Rd",
    "sg:city":"Dewsbury",
    "sg:classifiers":[
        {
            "category":"Place Of Worship",
            "type":"Public Place"
        }
    ],
    "sg:phone":"+44 1924 465961",
    "sg:postcode":"WF13 4JD",
    "sg:province":"West Yorkshire",
    "wof:name":"Church Of Jesus Christ Of Latter Day Saints",
    "wof:placetype":"venue"
},
  "geometry": {"coordinates":[-1.641982,53.700821],"type":"Point"}
}