{
  "type": "Feature",
  "properties": {
    "iso:country":"GB",
    "sg:address":"22 Guys Farm Road, South Woodham Ferrers",
    "sg:city":"Chelmsford",
    "sg:classifiers":[
        {
            "category":"Education",
            "subcategory":"School",
            "type":"Public Place"
        }
    ],
    "sg:phone":"+44 1245 321301",
    "sg:postcode":"CM3 5NB",
    "sg:province":"Essex",
    "sg:tags":[
        "foundation",
        "college"
    ],
    "wof:name":"Elmwood County Primary School",
    "wof:placetype":"venue"
},
  "geometry": {"coordinates":[0.613571,51.646584],"type":"Point"}
}