{
  "type": "Feature",
  "properties": {
    "iso:country":"GB",
    "sg:address":"5 Park Heights, Fiennes Cres",
    "sg:city":"Nottingham",
    "sg:classifiers":[
        {
            "category":"Professional",
            "subcategory":"Management & Consulting",
            "type":"Services"
        }
    ],
    "sg:phone":"+44 115 924 0882",
    "sg:postcode":"NG7 1ER",
    "sg:province":"Nottinghamshire",
    "sg:tags":[
        "consultant",
        "business"
    ],
    "wof:name":"Simpson Parker & Associates",
    "wof:placetype":"venue"
},
  "geometry": {"coordinates":[-1.16431,52.948502],"type":"Point"}
}