{
  "type": "Feature",
  "properties": {
    "addr:full":"54 Broad Street Alresford Hampshire SO24 9AN",
    "addr:housenumber":"54",
    "addr:postcode":"so24 9an",
    "addr:street":"Broad Street",
    "iso:country":"GB",
    "sg:address":"54 Broad Street",
    "sg:city":"Alresford",
    "sg:classifiers":[
        {
            "category":"Professional",
            "subcategory":"Art Services",
            "type":"Services"
        }
    ],
    "sg:phone":"+44 1962 734179",
    "sg:postcode":"SO24 9AN",
    "sg:province":"Hampshire",
    "sg:tags":[
        "framing"
    ],
    "wof:name":"J G & B Watson",
    "wof:placetype":"venue"
},
  "geometry": {"coordinates":[-1.1616289616,51.092212677],"type":"Point"}
}