{
  "type": "Feature",
  "properties": {
    "addr:full":"7 Wharf Lane, Cliffe Rochester Kent ME3 7UE",
    "addr:housenumber":"7",
    "addr:postcode":"me3 7ue",
    "addr:street":"Wharf Lane",
    "iso:country":"GB",
    "sg:address":"7 Wharf Lane, Cliffe",
    "sg:city":"Rochester",
    "sg:classifiers":[
        {
            "category":"Building & Trades",
            "subcategory":"Landscaping Services",
            "type":"Services"
        }
    ],
    "sg:phone":"+44 1634 220457",
    "sg:postcode":"ME3 7UE",
    "sg:province":"Kent",
    "sg:tags":[
        "forestry",
        "tree"
    ],
    "wof:name":"Baker & Sons",
    "wof:placetype":"venue"
},
  "geometry": {"coordinates":[0.502933979,51.4624938965],"type":"Point"}
}