{
  "type": "Feature",
  "properties": {
    "iso:country":"GB",
    "sg:address":"Pen Y Fernel Farm, Culfor Road",
    "sg:city":"Swansea",
    "sg:classifiers":[
        {
            "category":"Manufacturing",
            "subcategory":"Metals",
            "type":"Manufacturing & Wholesale Goods"
        }
    ],
    "sg:phone":"+44 1792 899667",
    "sg:postcode":"SA4 6UB",
    "sg:province":"Carmarthenshire",
    "sg:tags":[
        "steel",
        "fabricator",
        "erectors"
    ],
    "wof:name":"Farmers Fabrication & Sheet Metal Works Ltd.",
    "wof:placetype":"venue"
},
  "geometry": {"coordinates":[-4.062706,51.667789],"type":"Point"}
}