{
  "type": "Feature",
  "properties": {
    "iso:country":"GB",
    "sg:address":"8 Crofters Brook, Radcliffe",
    "sg:city":"Manchester",
    "sg:classifiers":[
        {
            "category":"Professional",
            "subcategory":"Business Services",
            "type":"Services"
        }
    ],
    "sg:postcode":"M26 2RL",
    "sg:province":"Greater Manchester",
    "sg:tags":[
        "import",
        "export",
        "agent"
    ],
    "wof:name":"Stilmet International Ltd",
    "wof:placetype":"venue"
},
  "geometry": {"coordinates":[-2.317434,53.56675],"type":"Point"}
}