{
  "type": "Feature",
  "properties": {
    "addr:full":"Weedon Road Industrial Estate Northampton Northamptonshire NN5 5AF",
    "addr:postcode":"nn5 5af",
    "addr:street":"Weedon Road Industrial Estate",
    "iso:country":"GB",
    "sg:address":"Weedon Road Industrial Estate",
    "sg:city":"Northampton",
    "sg:classifiers":[
        {
            "category":"Shopping",
            "type":"Retail Goods"
        }
    ],
    "sg:phone":"+44 1604 587444",
    "sg:postcode":"NN5 5AF",
    "sg:province":"Northamptonshire",
    "sg:tags":[
        "part",
        "accessory"
    ],
    "wof:name":"Halfords Superstore",
    "wof:placetype":"venue"
},
  "geometry": {"coordinates":[-0.920679,52.240883],"type":"Point"}
}