{
  "type": "Feature",
  "properties": {
    "iso:country":"GB",
    "sg:address":"Community Education Centre, Barnsley Rd",
    "sg:city":"Barnsley",
    "sg:classifiers":[
        {
            "category":"Professional",
            "subcategory":"Employment Agencies",
            "type":"Services"
        }
    ],
    "sg:phone":"+44 1226 270030",
    "sg:postcode":"S73 8HT",
    "sg:province":"South Yorkshire",
    "sg:tags":[
        "career",
        "guidance"
    ],
    "wof:name":"Wombwell Jobclub",
    "wof:placetype":"venue"
},
  "geometry": {"coordinates":[-1.40229,53.52459],"type":"Point"}
}