{
  "type": "Feature",
  "properties": {
    "addr:full":"2-4 Longbutts Lane, Gawsworth Macclesfield Cheshire SK11 9QU",
    "addr:housenumber":"2-4",
    "addr:postcode":"sk11 9qu",
    "addr:street":"Longbutts Lane",
    "iso:country":"GB",
    "sg:address":"2-4 Longbutts Lane, Gawsworth",
    "sg:city":"Macclesfield",
    "sg:classifiers":[
        {
            "category":"Shopping",
            "subcategory":"Department Store",
            "type":"Retail Goods"
        }
    ],
    "sg:postcode":"SK11 9QU",
    "sg:province":"Cheshire",
    "wof:name":"J B & J Longson",
    "wof:placetype":"venue"
},
  "geometry": {"coordinates":[-2.166274,53.230888],"type":"Point"}
}