{
  "type": "Feature",
  "properties": {
    "iso:country":"GB",
    "sg:address":"South Staffs Freight Terminal, Lynn Lane, Shenstone",
    "sg:city":"Lichfield",
    "sg:classifiers":[
        {
            "category":"Retail",
            "subcategory":"Auto Repair",
            "type":"Services"
        }
    ],
    "sg:phone":"+44 1543 481808",
    "sg:postcode":"WS14 0EN",
    "sg:province":"Staffordshire",
    "sg:tags":[
        "body",
        "car"
    ],
    "wof:name":"M-Tec",
    "wof:placetype":"venue"
},
  "geometry": {"coordinates":[-1.880594,52.636978],"type":"Point"}
}