{
  "type": "Feature",
  "properties": {
    "addr:full":"111 Park Lane Oldbury West Midlands B69 4PX",
    "addr:housenumber":"111",
    "addr:postcode":"b69 4px",
    "addr:street":"Park Lane",
    "iso:country":"GB",
    "sg:address":"111 Park Lane",
    "sg:city":"Oldbury",
    "sg:classifiers":[
        {
            "category":"Retail",
            "subcategory":"Auto Repair",
            "type":"Services"
        }
    ],
    "sg:phone":"+44 121 541 2278",
    "sg:postcode":"B69 4PX",
    "sg:province":"West Midlands",
    "sg:tags":[
        "modification",
        "garage"
    ],
    "wof:name":"Volks Magic",
    "wof:placetype":"venue"
},
  "geometry": {"coordinates":[-2.0151159763,52.4942550659],"type":"Point"}
}