{
  "type": "Feature",
  "properties": {
    "addr:full":"Unit 29 Trench Lock 2 Telford Shropshire TF1 5SW",
    "addr:housenumber":"unit 29;2",
    "addr:postcode":"tf1 5sw",
    "addr:street":"Trench Lock",
    "iso:country":"GB",
    "sg:address":"Unit 29 Trench Lock 2",
    "sg:city":"Telford",
    "sg:classifiers":[
        {
            "category":"Cafe",
            "type":"Food & Drink"
        }
    ],
    "sg:phone":"+44 1952 240168",
    "sg:postcode":"TF1 5SW",
    "sg:province":"Shropshire",
    "sg:tags":[
        "tea",
        "room"
    ],
    "wof:name":"W Mapp",
    "wof:placetype":"venue"
},
  "geometry": {"coordinates":[-2.4719130993,52.707824707],"type":"Point"}
}