{
  "type": "Feature",
  "properties": {
    "iso:country":"GB",
    "sg:address":"Unit 76 33 The Mall",
    "sg:city":"Bexleyheath",
    "sg:classifiers":[
        {
            "category":"Shopping",
            "subcategory":"Shoes",
            "type":"Retail Goods"
        }
    ],
    "sg:phone":"+44 20 8303 4985",
    "sg:postcode":"DA6 7JJ",
    "sg:province":"Kent",
    "sg:tags":[
        "shop"
    ],
    "wof:name":"Saxone",
    "wof:placetype":"venue"
},
  "geometry": {"coordinates":[0.150461,51.451031],"type":"Point"}
}