{
  "type": "Feature",
  "properties": {
    "iso:country":"GB",
    "sg:address":"29 Studland Road, Alum Chine",
    "sg:city":"Bournemouth",
    "sg:classifiers":[
        {
            "category":"Travel",
            "subcategory":"Hotels & Motels",
            "type":"Entertainment"
        }
    ],
    "sg:phone":"+44 1202 765307",
    "sg:postcode":"BH4 8HZ",
    "sg:province":"Dorset",
    "wof:name":"Fircliff Private Hotel",
    "wof:placetype":"venue"
},
  "geometry": {"coordinates":[-1.9010590315,50.7137756348],"type":"Point"}
}