{
  "type": "Feature",
  "properties": {
    "iso:country":"GB",
    "sg:address":"50 Shaftesbury Avenue",
    "sg:city":"London",
    "sg:classifiers":[
        {
            "category":"Restaurant",
            "type":"Food & Drink"
        }
    ],
    "sg:postcode":"W1D 6LP",
    "sg:province":"Greater London",
    "wof:name":"Schlotzskys",
    "wof:placetype":"venue"
},
  "geometry": {"coordinates":[-0.132818,51.51149],"type":"Point"}
}