{
  "type": "Feature",
  "properties": {
    "iso:country":"GB",
    "sg:address":"Garden House, The Warren",
    "sg:city":"Cromer",
    "sg:classifiers":[
        {
            "category":"Real Estate",
            "subcategory":"Architect",
            "type":"Services"
        }
    ],
    "sg:phone":"+44 1263 514515",
    "sg:postcode":"NR27 0AR",
    "sg:province":"Norfolk",
    "wof:name":"JAMES BOND",
    "wof:placetype":"venue"
},
  "geometry": {"coordinates":[1.31029,52.928322],"type":"Point"}
}