{
  "type": "Feature",
  "properties": {
    "addr:full":"Brideswells, Cushnie Alford Aberdeenshire AB33 8LD",
    "addr:postcode":"ab33 8ld",
    "iso:country":"GB",
    "sg:address":"Brideswells, Cushnie",
    "sg:city":"Alford",
    "sg:classifiers":[
        {
            "category":"Sports & Exercise",
            "subcategory":"Stables",
            "type":"Entertainment"
        }
    ],
    "sg:phone":"+44 1975 581266",
    "sg:postcode":"AB33 8LD",
    "sg:province":"Aberdeenshire",
    "sg:tags":[
        "equestrian",
        "centre",
        "livery",
        "schools",
        "riding",
        "education"
    ],
    "wof:name":"BRIDESWELL RIDING STABLES",
    "wof:placetype":"venue"
},
  "geometry": {"coordinates":[-2.7054889202,57.2341384888],"type":"Point"}
}