{
  "type": "Feature",
  "properties": {
    "iso:country":"GB",
    "sg:address":"51a Dymock St",
    "sg:city":"Fulham",
    "sg:classifiers":[
        {
            "category":"Building & Trades",
            "subcategory":"Construction",
            "type":"Services"
        }
    ],
    "sg:phone":"+44 20 7731 2534",
    "sg:postcode":"SW6 3ET",
    "sg:province":"Greater London",
    "sg:tags":[
        "builder"
    ],
    "wof:name":"B L Walker",
    "wof:placetype":"venue"
},
  "geometry": {"coordinates":[-0.1922239959,51.4673271179],"type":"Point"}
}