{
  "type": "Feature",
  "properties": {
    "addr:full":"3 Bay View Manor, 163 Sea Road Westgate On Sea Kent CT8 8QA",
    "addr:housenumber":"3;163",
    "addr:postcode":"ct8 8qa",
    "addr:street":"Bay View;Sea Road Westgate",
    "iso:country":"GB",
    "sg:address":"3 Bay View Manor, 163 Sea Road",
    "sg:city":"Westgate On Sea",
    "sg:classifiers":[
        {
            "category":"Building & Trades",
            "subcategory":"Construction",
            "type":"Services"
        }
    ],
    "sg:phone":"+44 1843 835700",
    "sg:postcode":"CT8 8QA",
    "sg:province":"Kent",
    "sg:tags":[
        "builder"
    ],
    "wof:name":"David C Manyweathers",
    "wof:placetype":"venue"
},
  "geometry": {"coordinates":[1.3270950317,51.381729126],"type":"Point"}
}