{
  "type": "Feature",
  "properties": {
    "iso:country":"GB",
    "sg:address":"76 Sussex Avenue",
    "sg:city":"Isleworth",
    "sg:classifiers":[
        {
            "category":"Banks & Credit Unions",
            "subcategory":"Financial Services",
            "type":"Services"
        }
    ],
    "sg:phone":"+44 20 8230 7167",
    "sg:postcode":"TW7 6LB",
    "sg:province":"Greater London",
    "sg:tags":[
        "adviser"
    ],
    "wof:name":"Mirage Investments",
    "wof:placetype":"venue"
},
  "geometry": {"coordinates":[-0.343091011,51.4682769775],"type":"Point"}
}