{
  "type": "Feature",
  "properties": {
    "addr:full":"16 Bowring Close, Whipton Exeter Devon EX1 3TU",
    "addr:housenumber":"16",
    "addr:postcode":"ex1 3tu",
    "addr:street":"Bowring Close",
    "iso:country":"GB",
    "sg:address":"16 Bowring Close, Whipton",
    "sg:city":"Exeter",
    "sg:classifiers":[
        {
            "category":"Building & Trades",
            "subcategory":"Construction",
            "type":"Services"
        },
        {
            "category":"Retail",
            "subcategory":"Storage",
            "type":"Services"
        }
    ],
    "sg:phone":"+44 1392 438808",
    "sg:postcode":"EX1 3TU",
    "sg:province":"Devon",
    "sg:tags":[
        "builder",
        "household",
        "removal"
    ],
    "wof:name":"A1 Removals & Storage",
    "wof:placetype":"venue"
},
  "geometry": {"coordinates":[-3.4922680855,50.7275314331],"type":"Point"}
}