{
  "type": "Feature",
  "properties": {
    "iso:country":"GB",
    "sg:address":"19 Redwick Road, Pilning",
    "sg:city":"Bristol",
    "sg:classifiers":[
        {
            "category":"Professional",
            "subcategory":"Advertising",
            "type":"Services"
        },
        {
            "category":"Manufacturing",
            "subcategory":"Signs",
            "type":"Manufacturing & Wholesale Goods"
        }
    ],
    "sg:postcode":"BS35 4LG",
    "sg:province":"Gloucestershire",
    "sg:tags":[
        "agency",
        "nameplate"
    ],
    "wof:name":"Avon Displays",
    "wof:placetype":"venue"
},
  "geometry": {"coordinates":[-2.64452,51.563377],"type":"Point"}
}