{
  "type": "Feature",
  "properties": {
    "addr:full":"Gormans Yard, Grace Road Exeter Devon EX2 8QE",
    "addr:postcode":"ex2 8qe",
    "addr:street":"Grace Road",
    "iso:country":"GB",
    "sg:address":"Gormans Yard, Grace Road",
    "sg:city":"Exeter",
    "sg:classifiers":[
        {
            "category":"Food & Beverages",
            "subcategory":"Bakery",
            "type":"Retail Goods"
        }
    ],
    "sg:postcode":"EX2 8QE",
    "sg:province":"Devon",
    "sg:tags":[
        "confectionery"
    ],
    "wof:name":"Granny Pascoe",
    "wof:placetype":"venue"
},
  "geometry": {"coordinates":[-3.522840023,50.7030792236],"type":"Point"}
}