{
  "type": "Feature",
  "properties": {
    "addr:full":"Brettenham House, 9 Savoy Street London Greater London WC2E 7EG",
    "addr:housenumber":"brettenham;9",
    "addr:postcode":"wc2e 7eg",
    "addr:street":"Savoy Street",
    "iso:country":"GB",
    "sg:address":"Brettenham House, 9 Savoy Street",
    "sg:city":"London",
    "sg:classifiers":[
        {
            "category":"Banks & Credit Unions",
            "subcategory":"Investment Brokerage",
            "type":"Services"
        }
    ],
    "sg:phone":"+44 20 7379 1000",
    "sg:postcode":"WC2E 7EG",
    "sg:province":"Greater London",
    "wof:name":"Greycoat Ltd.",
    "wof:placetype":"venue"
},
  "geometry": {"coordinates":[-0.1194749996,51.510269165],"type":"Point"}
}