{
  "type": "Feature",
  "properties": {
    "iso:country":"GB",
    "sg:address":"8 Cuckoo Hill",
    "sg:city":"Bures",
    "sg:classifiers":[
        {
            "category":"Manufacturing",
            "subcategory":"Metals",
            "type":"Manufacturing & Wholesale Goods"
        },
        {
            "category":"Wholesale",
            "subcategory":"Scrap",
            "type":"Manufacturing & Wholesale Goods"
        }
    ],
    "sg:phone":"+44 1787 227602",
    "sg:postcode":"CO8 5JH",
    "sg:province":"Essex",
    "sg:tags":[
        "waste"
    ],
    "wof:name":"Dennis John Partridge",
    "wof:placetype":"venue"
},
  "geometry": {"coordinates":[0.780238,51.974422],"type":"Point"}
}