{
  "type": "Feature",
  "properties": {
    "addr:full":"Vale View, North Rd Whitland Carmarthenshire SA34 0BB",
    "addr:postcode":"sa34 0bb",
    "addr:street":"North Rd",
    "iso:country":"GB",
    "sg:address":"Vale View, North Rd",
    "sg:city":"Whitland",
    "sg:classifiers":[
        {
            "category":"Retail",
            "subcategory":"Driving School",
            "type":"Services"
        }
    ],
    "sg:phone":"+44 1994 240465",
    "sg:postcode":"SA34 0BB",
    "sg:province":"Carmarthenshire",
    "wof:name":"Millfield School of Motoring",
    "wof:placetype":"venue"
},
  "geometry": {"coordinates":[-4.612054,51.819256],"type":"Point"}
}