{
  "type": "Feature",
  "properties": {
    "addr:full":"49 Cameron Crescent, Windygates Leven Fife KY8 5EA",
    "addr:housenumber":"49",
    "addr:postcode":"ky8 5ea",
    "addr:street":"Cameron Crescent;Leven",
    "iso:country":"GB",
    "sg:address":"49 Cameron Crescent, Windygates",
    "sg:city":"Leven",
    "sg:classifiers":[
        {
            "category":"Professional",
            "subcategory":"Business Services",
            "type":"Services"
        }
    ],
    "sg:phone":"+44 1333 353373",
    "sg:postcode":"KY8 5EA",
    "sg:province":"Fife",
    "sg:tags":[
        "shop",
        "cleaning"
    ],
    "wof:name":"Ecocleen",
    "wof:placetype":"venue"
},
  "geometry": {"coordinates":[-3.0620648861,56.1955604553],"type":"Point"}
}