{
  "type": "Feature",
  "properties": {
    "addr:full":"Newmills Rd Dalkeith City of Edinburgh EH22 2ET",
    "addr:postcode":"eh22 2et",
    "addr:street":"Newmills Rd",
    "iso:country":"GB",
    "sg:address":"Newmills Rd",
    "sg:city":"Dalkeith",
    "sg:classifiers":[
        {
            "category":"Bars & Pubs",
            "type":"Food & Drink"
        }
    ],
    "sg:phone":"+44 131 663 3198",
    "sg:postcode":"EH22 2ET",
    "sg:province":"City of Edinburgh",
    "sg:tags":[
        "pubs",
        "inn"
    ],
    "wof:name":"Unicorn Roadhouse The",
    "wof:placetype":"venue"
},
  "geometry": {"coordinates":[-3.0404889584,55.8894615173],"type":"Point"}
}