{
  "type": "Feature",
  "properties": {
    "addr:full":"White Cottage Fawley Court, Fawley Henley On Thames Berkshire RG9 3AG",
    "addr:postcode":"rg9 3ag",
    "addr:street":"Fawley Court",
    "iso:country":"GB",
    "sg:address":"White Cottage Fawley Court, Fawley",
    "sg:city":"Henley On Thames",
    "sg:classifiers":[
        {
            "category":"Professional",
            "subcategory":"Printing & Photocopies",
            "type":"Services"
        }
    ],
    "sg:postcode":"RG9 3AG",
    "sg:province":"Berkshire",
    "sg:tags":[
        "printer"
    ],
    "wof:name":"Carousel Press Ltd",
    "wof:placetype":"venue"
},
  "geometry": {"coordinates":[-0.90137,51.556114],"type":"Point"}
}