{
  "type": "Feature",
  "properties": {
    "addr:full":"5 Hawks Green Lane Cannock Staffordshire WS11 2LL",
    "addr:housenumber":"5",
    "addr:postcode":"ws11 2ll",
    "addr:street":"Hawks Green Lane",
    "iso:country":"GB",
    "sg:address":"5 Hawks Green Lane",
    "sg:city":"Cannock",
    "sg:classifiers":[
        {
            "category":"Recreation",
            "type":"Entertainment"
        }
    ],
    "sg:phone":"+44 1543 505755",
    "sg:postcode":"WS11 2LL",
    "sg:province":"Staffordshire",
    "sg:tags":[
        "hot",
        "balloon",
        "air"
    ],
    "wof:name":"Aerial Promotions Ltd.",
    "wof:placetype":"venue"
},
  "geometry": {"coordinates":[-2.0111870766,52.6953887939],"type":"Point"}
}