{
  "type": "Feature",
  "properties": {
    "addr:full":"176 Melrose Avenue London Greater London NW2 4JY",
    "addr:housenumber":"176",
    "addr:postcode":"nw2 4jy",
    "addr:street":"Melrose Avenue",
    "iso:country":"GB",
    "sg:address":"176 Melrose Avenue",
    "sg:city":"London",
    "sg:classifiers":[
        {
            "category":"Shopping",
            "subcategory":"Pharmacy",
            "type":"Retail Goods"
        }
    ],
    "sg:phone":"+44 20 8450 3366",
    "sg:postcode":"NW2 4JY",
    "sg:province":"Greater London",
    "sg:tags":[
        "medicine",
        "therapy"
    ],
    "wof:name":"Touchpro U K Chair Massage School",
    "wof:placetype":"venue"
},
  "geometry": {"coordinates":[-0.228497,51.55405],"type":"Point"}
}