{
  "type": "Feature",
  "properties": {
    "addr:full":"49 Harris Rd, Beeston Nottingham Nottinghamshire NG9 4FD",
    "addr:housenumber":"49",
    "addr:postcode":"ng9 4fd",
    "addr:street":"Harris Rd",
    "iso:country":"GB",
    "sg:address":"49 Harris Rd, Beeston",
    "sg:city":"Nottingham",
    "sg:classifiers":[
        {
            "category":"Communications",
            "subcategory":"Film & Video Production",
            "type":"Services"
        }
    ],
    "sg:phone":"+44 115 919 6760",
    "sg:postcode":"NG9 4FD",
    "sg:province":"Nottinghamshire",
    "sg:tags":[
        "illustrator",
        "artist"
    ],
    "wof:name":"Richard Sanders",
    "wof:placetype":"venue"
},
  "geometry": {"coordinates":[-1.2346680164,52.9232177734],"type":"Point"}
}