{
  "type": "Feature",
  "properties": {
    "addr:full":"5 Queen Street, Seaton Carew Hartlepool Durham TS25 1AH",
    "addr:housenumber":"5",
    "addr:postcode":"ts25 1ah",
    "addr:street":"Queen Street",
    "iso:country":"GB",
    "sg:address":"5 Queen Street, Seaton Carew",
    "sg:city":"Hartlepool",
    "sg:classifiers":[
        {
            "category":"Recreation",
            "subcategory":"Water Park",
            "type":"Entertainment"
        }
    ],
    "sg:phone":"+44 1429 277278",
    "sg:postcode":"TS25 1AH",
    "sg:province":"Durham",
    "sg:tags":[
        "sport"
    ],
    "wof:name":"Longscar Powerboating",
    "wof:placetype":"venue"
},
  "geometry": {"coordinates":[-1.1925729513,54.6645278931],"type":"Point"}
}