{
  "type": "Feature",
  "properties": {
    "addr:full":"Unit 27 Lyon Road, Hersham Trading Estate Walton-on-thames Surrey KT12 3PU",
    "addr:housenumber":"unit 27",
    "addr:postcode":"kt12 3pu",
    "addr:street":"Lyon Road;Trading",
    "iso:country":"GB",
    "sg:address":"Unit 27 Lyon Road, Hersham Trading Estate",
    "sg:city":"Walton-on-thames",
    "sg:classifiers":[
        {
            "category":"Shopping",
            "subcategory":"Gifts & Souvenirs",
            "type":"Retail Goods"
        }
    ],
    "sg:postcode":"KT12 3PU",
    "sg:province":"Surrey",
    "sg:tags":[
        "giftware"
    ],
    "wof:name":"Ashleigh & Burwood Ltd.",
    "wof:placetype":"venue"
},
  "geometry": {"coordinates":[-0.386587,51.378899],"type":"Point"}
}