{
  "type": "Feature",
  "properties": {
    "iso:country":"GB",
    "sg:address":"Fore Street, Bugle",
    "sg:city":"St Austell",
    "sg:classifiers":[
        {
            "category":"Education",
            "subcategory":"School",
            "type":"Public Place"
        }
    ],
    "sg:phone":"+44 1726 850420",
    "sg:postcode":"PL26 8PD",
    "sg:province":"Cornwall",
    "sg:tags":[
        "local",
        "authority"
    ],
    "wof:name":"Bugle County Primary School",
    "wof:placetype":"venue"
},
  "geometry": {"coordinates":[-4.793348,50.397259],"type":"Point"}
}