{
  "type": "Feature",
  "properties": {
    "iso:country":"GB",
    "sg:address":"Studio 5, The Chimneys, Dauntsey Lock",
    "sg:city":"Chippenham",
    "sg:classifiers":[
        {
            "category":"Farming",
            "subcategory":"Farm & Veterinary Services",
            "type":"Manufacturing & Wholesale Goods"
        }
    ],
    "sg:phone":"+44 1249 892266",
    "sg:postcode":"SN15 4HD",
    "sg:province":"Wiltshire",
    "sg:tags":[
        "lampshade",
        "mnfs",
        "distributor"
    ],
    "wof:name":"Shells Shades",
    "wof:placetype":"venue"
},
  "geometry": {"coordinates":[-2.01679,51.53754],"type":"Point"}
}