{
  "type": "Feature",
  "properties": {
    "addr:full":"The Old Bakery, 11 High Street, Milborne Port Sherborne Dorset DT9 5AG",
    "addr:housenumber":"11",
    "addr:postcode":"dt9 5ag",
    "addr:street":"High Street",
    "iso:country":"GB",
    "sg:address":"The Old Bakery, 11 High Street, Milborne Port",
    "sg:city":"Sherborne",
    "sg:classifiers":[
        {
            "category":"Home & Garden",
            "subcategory":"Household Appliances",
            "type":"Retail Goods"
        }
    ],
    "sg:phone":"+44 1963 250313",
    "sg:postcode":"DT9 5AG",
    "sg:province":"Dorset",
    "sg:tags":[
        "repairs",
        "electrical",
        "domestic",
        "servicing"
    ],
    "wof:name":"Taylors Domestic Appliances Ltd",
    "wof:placetype":"venue"
},
  "geometry": {"coordinates":[-2.5215740204,50.9491653442],"type":"Point"}
}