{
  "type": "Feature",
  "properties": {
    "addr:full":"Broadclyst Gardens Southend-on-sea Essex SS1 3QT",
    "addr:postcode":"ss1 3qt",
    "addr:street":"Broadclyst Gardens",
    "iso:country":"GB",
    "sg:address":"Broadclyst Gardens",
    "sg:city":"Southend-on-sea",
    "sg:classifiers":[
        {
            "category":"Sports & Exercise",
            "subcategory":"Tennis Court",
            "type":"Entertainment"
        }
    ],
    "sg:phone":"+44 1702 589144",
    "sg:postcode":"SS1 3QT",
    "sg:province":"Essex",
    "wof:name":"Southend Lawn Tennis Club",
    "wof:placetype":"venue"
},
  "geometry": {"coordinates":[0.764303,51.542503],"type":"Point"}
}