{
  "type": "Feature",
  "properties": {
    "addr:full":"258 Westborough Rd Westcliff On Sea Essex SS0 9PT",
    "addr:housenumber":"258",
    "addr:postcode":"ss0 9pt",
    "addr:street":"Westborough Rd",
    "iso:country":"GB",
    "sg:address":"258 Westborough Rd",
    "sg:city":"Westcliff On Sea",
    "sg:classifiers":[
        {
            "category":"Health Services",
            "subcategory":"Doctor",
            "type":"Services"
        }
    ],
    "sg:phone":"+44 1702 348800",
    "sg:postcode":"SS0 9PT",
    "sg:province":"Essex",
    "sg:tags":[
        "practitioners"
    ],
    "wof:name":"Mukherjee, S K",
    "wof:placetype":"venue"
},
  "geometry": {"coordinates":[0.685973,51.547024],"type":"Point"}
}