{
  "type": "Feature",
  "properties": {
    "iso:country":"GB",
    "sg:address":"Unit 17, Llandygai Ind Est, Llandygai",
    "sg:city":"Bangor",
    "sg:classifiers":[
        {
            "category":"Wholesale",
            "subcategory":"Construction Materials",
            "type":"Manufacturing & Wholesale Goods"
        }
    ],
    "sg:phone":"+44 1248 371700",
    "sg:postcode":"LL57 4YH",
    "sg:province":"Gwynedd",
    "sg:tags":[
        "cladding"
    ],
    "wof:name":"Cybi Plastics",
    "wof:placetype":"venue"
},
  "geometry": {"coordinates":[-4.1009140015,53.2166366577],"type":"Point"}
}