{
  "type": "Feature",
  "properties": {
    "addr:full":"65 Bath Street Glasgow Glasgow City G2 2BX",
    "addr:housenumber":"65",
    "addr:postcode":"g2 2bx",
    "addr:street":"Bath Street",
    "iso:country":"GB",
    "sg:address":"65 Bath Street",
    "sg:city":"Glasgow",
    "sg:classifiers":[
        {
            "category":"Banks & Credit Unions",
            "subcategory":"Financial Services",
            "type":"Services"
        }
    ],
    "sg:postcode":"G2 2BX",
    "sg:province":"Glasgow City",
    "sg:tags":[
        "adviser"
    ],
    "wof:name":"Capital Management",
    "wof:placetype":"venue"
},
  "geometry": {"coordinates":[-4.256839,55.86375],"type":"Point"}
}