{
  "type": "Feature",
  "properties": {
    "addr:full":"Stocks Lane, Over Peover Knutsford Cheshire WA16 9EX",
    "addr:postcode":"wa16 9ex",
    "addr:street":"Stocks Lane",
    "iso:country":"GB",
    "sg:address":"Stocks Lane, Over Peover",
    "sg:city":"Knutsford",
    "sg:classifiers":[
        {
            "category":"Bars & Pubs",
            "type":"Food & Drink"
        }
    ],
    "sg:phone":"+44 1565 722332",
    "sg:postcode":"WA16 9EX",
    "sg:province":"Cheshire",
    "sg:tags":[
        "pubs",
        "inn"
    ],
    "wof:name":"The Whipping Stocks",
    "wof:placetype":"venue"
},
  "geometry": {"coordinates":[-2.3404250145,53.2665061951],"type":"Point"}
}