{
  "type": "Feature",
  "properties": {
    "iso:country":"GB",
    "sg:address":"137-143 High Street",
    "sg:city":"Sutton",
    "sg:classifiers":[
        {
            "category":"Professional",
            "subcategory":"Accounting & Tax Preparation",
            "type":"Services"
        }
    ],
    "sg:phone":"+44 20 7022 0050",
    "sg:postcode":"SM1 1JH",
    "sg:province":"Surrey",
    "sg:tags":[
        "accountant"
    ],
    "wof:name":"Clarkson Hyde Ltd.",
    "wof:placetype":"venue"
},
  "geometry": {"coordinates":[-0.193366006,51.3635787964],"type":"Point"}
}