{
  "type": "Feature",
  "properties": {
    "iso:country":"GB",
    "sg:address":"32 Dendridge Clo",
    "sg:city":"Enfield",
    "sg:classifiers":[
        {
            "category":"Building & Trades",
            "subcategory":"Construction",
            "type":"Services"
        }
    ],
    "sg:postcode":"EN1 4PW",
    "sg:province":"Greater London",
    "sg:tags":[
        "tiling",
        "contractor"
    ],
    "wof:name":"Cotton,E J,",
    "wof:placetype":"venue"
},
  "geometry": {"coordinates":[-0.051731,51.671932],"type":"Point"}
}