{
  "type": "Feature",
  "properties": {
    "iso:country":"GB",
    "sg:address":"12-14 Friar St",
    "sg:city":"Reading",
    "sg:classifiers":[
        {
            "category":"Bars & Pubs",
            "type":"Food & Drink"
        }
    ],
    "sg:phone":"+44 118 958 1457",
    "sg:postcode":"RG1 1DB",
    "sg:province":"Berkshire",
    "sg:tags":[
        "pubs",
        "inn"
    ],
    "wof:name":"Newt & Cucumber",
    "wof:placetype":"venue"
},
  "geometry": {"coordinates":[-0.971405983,51.4567642212],"type":"Point"}
}