{
  "type": "Feature",
  "properties": {
    "addr:full":"46 Stoke Road Cobham Surrey KT11 3BQ",
    "addr:housenumber":"46",
    "addr:postcode":"kt11 3bq",
    "addr:street":"Stoke Road",
    "iso:country":"GB",
    "sg:address":"46 Stoke Road",
    "sg:city":"Cobham",
    "sg:classifiers":[
        {
            "category":"Professional",
            "subcategory":"Secretarial Services",
            "type":"Services"
        },
        {
            "category":"Professional",
            "subcategory":"Art Services",
            "type":"Services"
        }
    ],
    "sg:phone":"+44 1932 864898",
    "sg:postcode":"KT11 3BQ",
    "sg:province":"Surrey",
    "sg:tags":[
        "photographer"
    ],
    "wof:name":"DI MOND, NICOLA",
    "wof:placetype":"venue"
},
  "geometry": {"coordinates":[-0.3899419904,51.3228797913],"type":"Point"}
}