{
  "type": "Feature",
  "properties": {
    "iso:country":"GB",
    "sg:address":"Ts Brave Fen Lane",
    "sg:city":"Beccles",
    "sg:classifiers":[
        {
            "category":"Organizations",
            "subcategory":"Non-profit Organization",
            "type":"Services"
        }
    ],
    "sg:phone":"+44 1502 711858",
    "sg:postcode":"NR34 9BB",
    "sg:province":"Norfolk",
    "sg:tags":[
        "organisation",
        "voluntary",
        "charity"
    ],
    "wof:name":"Beccles Sea Cadets",
    "wof:placetype":"venue"
},
  "geometry": {"coordinates":[1.567245,52.453667],"type":"Point"}
}