{
  "type": "Feature",
  "properties": {
    "addr:full":"843 London Road Thornton Heath Surrey CR7 6JH",
    "addr:housenumber":"843",
    "addr:postcode":"cr7 6jh",
    "addr:street":"London Road",
    "iso:country":"GB",
    "sg:address":"843 London Road",
    "sg:city":"Thornton Heath",
    "sg:classifiers":[
        {
            "category":"Social Services",
            "subcategory":"Adult Care",
            "type":"Services"
        }
    ],
    "sg:phone":"+44 20 8700 8600",
    "sg:postcode":"CR7 6JH",
    "sg:province":"Surrey",
    "sg:tags":[
        "day",
        "centre"
    ],
    "wof:name":"Oaks Resource Centre",
    "wof:placetype":"venue"
},
  "geometry": {"coordinates":[-0.114619,51.394772],"type":"Point"}
}