{
  "type": "Feature",
  "properties": {
    "addr:full":"1a Hythe Street Dartford Kent DA1 1BE",
    "addr:housenumber":"1a",
    "addr:postcode":"da1 1be",
    "addr:street":"Hythe Street",
    "iso:country":"GB",
    "sg:address":"1a Hythe Street",
    "sg:city":"Dartford",
    "sg:classifiers":[
        {
            "category":"Shopping",
            "subcategory":"Discount & Variety Stores",
            "type":"Retail Goods"
        }
    ],
    "sg:postcode":"DA1 1BE",
    "sg:province":"Kent",
    "sg:tags":[
        "surplus"
    ],
    "wof:name":"Kentons Army Surplus",
    "wof:placetype":"venue"
},
  "geometry": {"coordinates":[0.217027,51.444649],"type":"Point"}
}