{
  "type": "Feature",
  "properties": {
    "addr:full":"Bromyard Industrial Estate Bromyard Herefordshire HR7 4NP",
    "addr:postcode":"hr7 4np",
    "addr:street":"Industrial Estate",
    "iso:country":"GB",
    "sg:address":"Bromyard Industrial Estate",
    "sg:city":"Bromyard",
    "sg:classifiers":[
        {
            "category":"Shopping",
            "subcategory":"Pets & Pet Supplies",
            "type":"Retail Goods"
        }
    ],
    "sg:phone":"+44 1885 483601",
    "sg:postcode":"HR7 4NP",
    "sg:province":"Herefordshire",
    "sg:tags":[
        "equestrian"
    ],
    "wof:name":"M J Ainge & Co",
    "wof:placetype":"venue"
},
  "geometry": {"coordinates":[-2.510399,52.189098],"type":"Point"}
}