{
  "type": "Feature",
  "properties": {
    "addr:full":"Woodvale Centre, Woodvale Office Park, Woodvale Road Brighouse West Yorkshire HD6 4AB",
    "addr:postcode":"hd6 4ab",
    "addr:street":"Woodvale Road",
    "iso:country":"GB",
    "sg:address":"Woodvale Centre, Woodvale Office Park, Woodvale Road",
    "sg:city":"Brighouse",
    "sg:classifiers":[
        {
            "category":"Professional",
            "type":"Services"
        }
    ],
    "sg:phone":"+44 1484 710233",
    "sg:postcode":"HD6 4AB",
    "sg:province":"West Yorkshire",
    "sg:tags":[
        "exhibition"
    ],
    "wof:name":"OEC Designs Ltd",
    "wof:placetype":"venue"
},
  "geometry": {"coordinates":[-1.7737369537,53.7021942139],"type":"Point"}
}