{
  "type": "Feature",
  "properties": {
    "iso:country":"GB",
    "sg:address":"542 Scott Hall Rd",
    "sg:city":"Leeds",
    "sg:classifiers":[
        {
            "category":"Fast Food",
            "type":"Food & Drink"
        }
    ],
    "sg:phone":"+44 113 288 8900",
    "sg:postcode":"LS7 3RA",
    "sg:province":"West Yorkshire",
    "sg:tags":[
        "away",
        "take"
    ],
    "wof:name":"Subras Tandoori",
    "wof:placetype":"venue"
},
  "geometry": {"coordinates":[-1.546732,53.827946],"type":"Point"}
}