{
  "type": "Feature",
  "properties": {
    "addr:full":"11 Heath Close, Great Boughton Chester Cheshire CH3 5RZ",
    "addr:housenumber":"11",
    "addr:postcode":"ch3 5rz",
    "addr:street":"Heath Close",
    "iso:country":"GB",
    "sg:address":"11 Heath Close, Great Boughton",
    "sg:city":"Chester",
    "sg:classifiers":[
        {
            "category":"Professional",
            "subcategory":"Engineering",
            "type":"Services"
        }
    ],
    "sg:postcode":"CH3 5RZ",
    "sg:province":"Cheshire",
    "sg:tags":[
        "civil",
        "engineer"
    ],
    "wof:name":"Keith Paul Roberts",
    "wof:placetype":"venue"
},
  "geometry": {"coordinates":[-2.858936,53.187439],"type":"Point"}
}