{
  "type": "Feature",
  "properties": {
    "iso:country":"GB",
    "sg:address":"Vale House, Stainswick Lane, Shrivenham",
    "sg:city":"Swindon",
    "sg:classifiers":[
        {
            "category":"Building & Trades",
            "subcategory":"Construction",
            "type":"Services"
        }
    ],
    "sg:phone":"+44 1793 782968",
    "sg:postcode":"SN6 8LB",
    "sg:province":"Gloucestershire",
    "sg:tags":[
        "joiner",
        "carpenter"
    ],
    "wof:name":"Robert David Bourton",
    "wof:placetype":"venue"
},
  "geometry": {"coordinates":[-1.6439089775,51.5808563232],"type":"Point"}
}