{
  "type": "Feature",
  "properties": {
    "iso:country":"GB",
    "sg:address":"13 Newman Road",
    "sg:city":"Birmingham",
    "sg:classifiers":[
        {
            "category":"Professional",
            "subcategory":"Management & Consulting",
            "type":"Services"
        }
    ],
    "sg:postcode":"B24 9AG",
    "sg:province":"West Midlands",
    "sg:tags":[
        "consultant",
        "training"
    ],
    "wof:name":"I J E D",
    "wof:placetype":"venue"
},
  "geometry": {"coordinates":[-1.841969,52.521873],"type":"Point"}
}