{
  "type": "Feature",
  "properties": {
    "addr:full":"10 The Arcade, Station Road Redhill Surrey RH1 1PA",
    "addr:housenumber":"10;arcade",
    "addr:postcode":"rh1 1pa",
    "addr:street":"The;Station Road",
    "iso:country":"GB",
    "sg:address":"10 The Arcade, Station Road",
    "sg:city":"Redhill",
    "sg:classifiers":[
        {
            "category":"Shopping",
            "subcategory":"Music",
            "type":"Retail Goods"
        }
    ],
    "sg:postcode":"RH1 1PA",
    "sg:province":"Surrey",
    "sg:tags":[
        "record",
        "tape",
        "cd"
    ],
    "wof:name":"Hits",
    "wof:placetype":"venue"
},
  "geometry": {"coordinates":[-0.1688790023,51.2381782532],"type":"Point"}
}