{
  "type": "Feature",
  "properties": {
    "iso:country":"GB",
    "sg:address":"15-16 St Georges Terrace",
    "sg:city":"Millom",
    "sg:classifiers":[
        {
            "category":"Shopping",
            "subcategory":"Shoes",
            "type":"Retail Goods"
        }
    ],
    "sg:phone":"+44 1229 770370",
    "sg:postcode":"LA18 4DB",
    "sg:province":"Cumbria",
    "sg:tags":[
        "shop",
        "retailer",
        "footwear"
    ],
    "wof:name":"Discount Footwear",
    "wof:placetype":"venue"
},
  "geometry": {"coordinates":[-3.26904,54.209732],"type":"Point"}
}