{
  "type": "Feature",
  "properties": {
    "iso:country":"GB",
    "sg:address":"3 Western Hill",
    "sg:city":"Consett",
    "sg:classifiers":[
        {
            "category":"Retail",
            "subcategory":"Driving School",
            "type":"Services"
        }
    ],
    "sg:phone":"+44 1207 500580",
    "sg:postcode":"DH8 0LJ",
    "sg:province":"Durham",
    "wof:name":"Owen's Driving School",
    "wof:placetype":"venue"
},
  "geometry": {"coordinates":[-1.8550219536,54.8650779724],"type":"Point"}
}