{
  "type": "Feature",
  "properties": {
    "iso:country":"GB",
    "sg:address":"The Green, Bailey Street",
    "sg:city":"Stafford",
    "sg:classifiers":[
        {
            "category":"Place Of Worship",
            "type":"Public Place"
        }
    ],
    "sg:phone":"+44 1785 256714",
    "sg:postcode":"ST17 4BG",
    "sg:province":"Staffordshire",
    "wof:name":"Stafford baptist Church",
    "wof:placetype":"venue"
},
  "geometry": {"coordinates":[-2.11528,52.803558],"type":"Point"}
}