{
  "type": "Feature",
  "properties": {
    "iso:country":"GB",
    "sg:address":"Newham Grange Leisure Farm, Wykeham Way, Coulby Newham",
    "sg:city":"Middlesbrough",
    "sg:classifiers":[
        {
            "category":"Shopping",
            "subcategory":"Pets & Pet Supplies",
            "type":"Retail Goods"
        },
        {
            "category":"Farming",
            "subcategory":"Livestock Farm",
            "type":"Manufacturing & Wholesale Goods"
        },
        {
            "category":"Landmark",
            "subcategory":"Tourist Attraction",
            "type":"Public Place"
        }
    ],
    "sg:phone":"+44 1642 300202",
    "sg:postcode":"TS8 0TG",
    "sg:province":"North Yorkshire",
    "sg:tags":[
        "zoo",
        "others",
        "interest",
        "activity"
    ],
    "wof:name":"Newham Grange Leisure Farm",
    "wof:placetype":"venue"
},
  "geometry": {"coordinates":[-1.220444,54.530396],"type":"Point"}
}