{
  "type": "Feature",
  "properties": {
    "iso:country":"GB",
    "sg:address":"Hippenscombe Farm, Fosbury",
    "sg:city":"Marlborough",
    "sg:classifiers":[
        {
            "category":"Farming",
            "subcategory":"Poultry Farm",
            "type":"Manufacturing & Wholesale Goods"
        }
    ],
    "sg:phone":"+44 1264 730249",
    "sg:postcode":"SN8 3NW",
    "sg:province":"Berkshire",
    "sg:tags":[
        "game"
    ],
    "wof:name":"Thames Valley Egg (Production)",
    "wof:placetype":"venue"
},
  "geometry": {"coordinates":[-1.5436639786,51.3208847046],"type":"Point"}
}