{
  "type": "Feature",
  "properties": {
    "iso:country":"GB",
    "sg:address":"Madeley St",
    "sg:city":"Derby",
    "sg:classifiers":[
        {
            "category":"Organizations",
            "subcategory":"Community Association",
            "type":"Services"
        }
    ],
    "sg:phone":"+44 1332 363847",
    "sg:postcode":"DE23 8HW",
    "sg:province":"Derbyshire",
    "sg:tags":[
        "society",
        "housing"
    ],
    "wof:name":"Anchor Housing Trust",
    "wof:placetype":"venue"
},
  "geometry": {"coordinates":[-1.474011,52.911343],"type":"Point"}
}