{
  "type": "Feature",
  "properties": {
    "iso:country":"GB",
    "sg:address":"183 Buckley Lane, Farnworth",
    "sg:city":"Bolton",
    "sg:classifiers":[
        {
            "category":"Food & Beverages",
            "subcategory":"Groceries & Convenience Stores",
            "type":"Retail Goods"
        }
    ],
    "sg:postcode":"BL4 9SH",
    "sg:province":"Lancashire",
    "wof:name":"Buckley Stores",
    "wof:placetype":"venue"
},
  "geometry": {"coordinates":[-2.4066989422,53.5413284302],"type":"Point"}
}