{
  "type": "Feature",
  "properties": {
    "addr:full":"Bedford Road Northampton Northamptonshire NN1 5NW",
    "addr:postcode":"nn1 5nw",
    "addr:street":"Bedford Road",
    "iso:country":"GB",
    "sg:address":"Bedford Road",
    "sg:city":"Northampton",
    "sg:classifiers":[
        {
            "category":"Autos & Motor Vehicles",
            "subcategory":"Auto Supplies",
            "type":"Retail Goods"
        }
    ],
    "sg:postcode":"NN1 5NW",
    "sg:province":"Northamptonshire",
    "sg:tags":[
        "towbars"
    ],
    "wof:name":"J King",
    "wof:placetype":"venue"
},
  "geometry": {"coordinates":[-0.887171,52.234615],"type":"Point"}
}