{
  "type": "Feature",
  "properties": {
    "iso:country":"GB",
    "sg:address":"Flat 2 Carlton House, 73 Clyde Road",
    "sg:city":"Croydon",
    "sg:classifiers":[
        {
            "category":"Organizations",
            "subcategory":"Membership Organization",
            "type":"Services"
        }
    ],
    "sg:postcode":"CR0 6SZ",
    "sg:province":"Surrey",
    "sg:tags":[
        "club"
    ],
    "wof:name":"Carlton (Clyde) Management Company Limit",
    "wof:placetype":"venue"
},
  "geometry": {"coordinates":[-0.0808599964,51.377368927],"type":"Point"}
}