{
  "type": "Feature",
  "properties": {
    "iso:country":"GB",
    "sg:address":"Suite 5 04, New Loom House, 101 Back Church Lane",
    "sg:city":"London",
    "sg:classifiers":[
        {
            "category":"Professional",
            "subcategory":"Employment Agencies",
            "type":"Services"
        }
    ],
    "sg:phone":"+44 20 7680 4011",
    "sg:postcode":"E1 1LU",
    "sg:province":"Greater London",
    "sg:tags":[
        "consultant"
    ],
    "wof:name":"Excel Resources International Ltd.",
    "wof:placetype":"venue"
},
  "geometry": {"coordinates":[-0.067264,51.512653],"type":"Point"}
}