{
  "type": "Feature",
  "properties": {
    "addr:full":"477 London Road, Davenham Northwich Cheshire CW9 8NA",
    "addr:housenumber":"477",
    "addr:postcode":"cw9 8na",
    "addr:street":"London Road",
    "iso:country":"GB",
    "sg:address":"477 London Road, Davenham",
    "sg:city":"Northwich",
    "sg:classifiers":[
        {
            "category":"Government",
            "subcategory":"Post Office",
            "type":"Public Place"
        }
    ],
    "sg:phone":"+44 1606 43150",
    "sg:postcode":"CW9 8NA",
    "sg:province":"Cheshire",
    "wof:name":"Davenham Post Office",
    "wof:placetype":"venue"
},
  "geometry": {"coordinates":[-2.5095388889,53.2294311523],"type":"Point"}
}