{
  "type": "Feature",
  "properties": {
    "addr:full":"Library, Ditton Street Ilminster Somerset TA19 0BW",
    "addr:postcode":"ta19 0bw",
    "addr:street":"Ditton Street",
    "iso:country":"GB",
    "sg:address":"Library, Ditton Street",
    "sg:city":"Ilminster",
    "sg:classifiers":[
        {
            "category":"Education",
            "subcategory":"Library",
            "type":"Public Place"
        }
    ],
    "sg:phone":"+44 1460 52695",
    "sg:postcode":"TA19 0BW",
    "sg:province":"Somerset",
    "sg:tags":[
        "book"
    ],
    "wof:name":"Ilminster Library",
    "wof:placetype":"venue"
},
  "geometry": {"coordinates":[-2.910258,50.92609],"type":"Point"}
}