{
  "type": "Feature",
  "properties": {
    "addr:full":"Loanhead Farm, Aiket Road, Dunlop Kilmarnock East Ayrshire KA3 4BP",
    "addr:postcode":"ka3 4bp",
    "addr:street":"Aiket Road Dunlop",
    "iso:country":"GB",
    "sg:address":"Loanhead Farm, Aiket Road, Dunlop",
    "sg:city":"Kilmarnock",
    "sg:classifiers":[
        {
            "category":"Farming",
            "subcategory":"Dairy Farm",
            "type":"Manufacturing & Wholesale Goods"
        }
    ],
    "sg:phone":"+44 1560 484929",
    "sg:postcode":"KA3 4BP",
    "sg:province":"East Ayrshire",
    "sg:tags":[
        "farmer"
    ],
    "wof:name":"David Hamilton & Co",
    "wof:placetype":"venue"
},
  "geometry": {"coordinates":[-4.534,55.712536],"type":"Point"}
}