{
  "type": "Feature",
  "properties": {
    "addr:full":"3rd Floor, Equipoint, Coventry Road Birmingham West Midlands B25 8AT",
    "addr:housenumber":"3rd floor",
    "addr:postcode":"b25 8at",
    "addr:street":"Equipoint Coventry Road",
    "iso:country":"GB",
    "sg:address":"3rd Floor, Equipoint, Coventry Road",
    "sg:city":"Birmingham",
    "sg:classifiers":[
        {
            "category":"Professional",
            "subcategory":"Advertising",
            "type":"Services"
        },
        {
            "category":"Communications",
            "subcategory":"Newspaper",
            "type":"Services"
        }
    ],
    "sg:phone":"+44 121 606 1607",
    "sg:postcode":"B25 8AT",
    "sg:province":"West Midlands",
    "sg:tags":[
        "magazine"
    ],
    "wof:name":"Bargain Pages Ltd.",
    "wof:placetype":"venue"
},
  "geometry": {"coordinates":[-1.8208700418,52.4668998718],"type":"Point"}
}