{
  "type": "Feature",
  "properties": {
    "addr:full":"209 Mill Road Cambridge Cambridgeshire CB1 3AN",
    "addr:housenumber":"209",
    "addr:postcode":"cb1 3an",
    "addr:street":"Mill Road",
    "iso:country":"GB",
    "sg:address":"209 Mill Road",
    "sg:city":"Cambridge",
    "sg:classifiers":[
        {
            "category":"Professional",
            "subcategory":"Engineering",
            "type":"Services"
        }
    ],
    "sg:postcode":"CB1 3AN",
    "sg:province":"Cambridgeshire",
    "sg:tags":[
        "electronic",
        "engineer"
    ],
    "wof:name":"Nanophon Ltd.",
    "wof:placetype":"venue"
},
  "geometry": {"coordinates":[0.1467850059,52.1972961426],"type":"Point"}
}