{
  "type": "Feature",
  "properties": {
    "addr:full":"179-181 Lewisham Way London Greater London SE4 1XA",
    "addr:housenumber":"179-181",
    "addr:postcode":"se4 1xa",
    "addr:street":"Lewisham Way",
    "iso:country":"GB",
    "sg:address":"179-181 Lewisham Way",
    "sg:city":"London",
    "sg:classifiers":[
        {
            "category":"Banks & Credit Unions",
            "subcategory":"Financial Services",
            "type":"Services"
        }
    ],
    "sg:phone":"+44 121 705 7777",
    "sg:postcode":"SE4 1XA",
    "sg:province":"Greater London",
    "sg:tags":[
        "consultant"
    ],
    "wof:name":"S & U Plc",
    "wof:placetype":"venue"
},
  "geometry": {"coordinates":[-0.029479,51.471039],"type":"Point"}
}