{
  "type": "Feature",
  "properties": {
    "addr:full":"Beacon Hill Ind Est, Botany Way Purfleet Essex RM19 1SR",
    "addr:postcode":"rm19 1sr",
    "addr:street":"Hill Ind Est Botany Way",
    "iso:country":"GB",
    "sg:address":"Beacon Hill Ind Est, Botany Way",
    "sg:city":"Purfleet",
    "sg:classifiers":[
        {
            "category":"Professional",
            "subcategory":"Business Services",
            "type":"Services"
        }
    ],
    "sg:phone":"+44 1708 681300",
    "sg:postcode":"RM19 1SR",
    "sg:province":"Essex",
    "sg:tags":[
        "distribution"
    ],
    "wof:name":"Wincanton Logistics",
    "wof:placetype":"venue"
},
  "geometry": {"coordinates":[0.2414930016,51.4803390503],"type":"Point"}
}