{
  "type": "Feature",
  "properties": {
    "iso:country":"GB",
    "sg:address":"50 West St",
    "sg:city":"Axbridge",
    "sg:classifiers":[
        {
            "category":"Professional",
            "subcategory":"Management & Consulting",
            "type":"Services"
        }
    ],
    "sg:phone":"+44 1934 732669",
    "sg:postcode":"BS26 2AD",
    "sg:province":"Somerset",
    "sg:tags":[
        "consultant",
        "business"
    ],
    "wof:name":"Paradigm",
    "wof:placetype":"venue"
},
  "geometry": {"coordinates":[-2.8230500221,51.2878952026],"type":"Point"}
}