{
  "type": "Feature",
  "properties": {
    "addr:full":"Unit G5 Butlers Wharf Business Centre, 45 Curlew St London Greater London SE1 2ND",
    "addr:housenumber":"45",
    "addr:postcode":"se1 2nd",
    "addr:street":"Curlew St",
    "iso:country":"GB",
    "sg:address":"Unit G5 Butlers Wharf Business Centre, 45 Curlew St",
    "sg:city":"London",
    "sg:classifiers":[
        {
            "category":"Building & Trades",
            "subcategory":"Construction",
            "type":"Services"
        }
    ],
    "sg:postcode":"SE1 2ND",
    "sg:province":"Greater London",
    "sg:tags":[
        "builder"
    ],
    "wof:name":"Oak Carpenter Building Contractors Ltd",
    "wof:placetype":"venue"
},
  "geometry": {"coordinates":[-0.07437,51.50227],"type":"Point"}
}