{
  "type": "Feature",
  "properties": {
    "iso:country":"GB",
    "sg:address":"Nursery Park Rd",
    "sg:city":"Ashington",
    "sg:classifiers":[
        {
            "category":"Health Services",
            "subcategory":"Doctor",
            "type":"Services"
        },
        {
            "category":"Health Services",
            "subcategory":"Clinic",
            "type":"Services"
        }
    ],
    "sg:phone":"+44 1670 528100",
    "sg:postcode":"NE63 0HP",
    "sg:province":"Northumberland",
    "sg:tags":[
        "nh",
        "practitioners"
    ],
    "wof:name":"Nursery Park Medical Group",
    "wof:placetype":"venue"
},
  "geometry": {"coordinates":[-1.560984,55.167702],"type":"Point"}
}