{
  "type": "Feature",
  "properties": {
    "addr:full":"77 Oak Avenue Todmorden Lancashire OL14 5PD",
    "addr:housenumber":"77",
    "addr:postcode":"ol14 5pd",
    "addr:street":"Oak Avenue",
    "iso:country":"GB",
    "sg:address":"77 Oak Avenue",
    "sg:city":"Todmorden",
    "sg:classifiers":[
        {
            "category":"Shopping",
            "subcategory":"Musical Instruments",
            "type":"Retail Goods"
        }
    ],
    "sg:postcode":"OL14 5PD",
    "sg:province":"Lancashire",
    "wof:name":"Colin Sutcliffe Instrument Repairs",
    "wof:placetype":"venue"
},
  "geometry": {"coordinates":[-2.10221,53.721848],"type":"Point"}
}