{
  "type": "Feature",
  "properties": {
    "addr:full":"27-29 Benhall Avenue Cheltenham Gloucestershire GL51 6AF",
    "addr:housenumber":"27-29",
    "addr:postcode":"gl51 6af",
    "addr:street":"Benhall Avenue",
    "iso:country":"GB",
    "sg:address":"27-29 Benhall Avenue",
    "sg:city":"Cheltenham",
    "sg:classifiers":[
        {
            "category":"Shopping",
            "subcategory":"News",
            "type":"Retail Goods"
        }
    ],
    "sg:phone":"+44 1242 523123",
    "sg:postcode":"GL51 6AF",
    "sg:province":"Gloucestershire",
    "sg:tags":[
        "newsagent"
    ],
    "wof:name":"Stars News Shops Ltd",
    "wof:placetype":"venue"
},
  "geometry": {"coordinates":[-2.118241,51.894753],"type":"Point"}
}