{
  "type": "Feature",
  "properties": {
    "addr:full":"26 Apollo Way Blackwood Caerphilly NP2 1WA",
    "addr:housenumber":"26",
    "addr:postcode":"np2 1wa",
    "addr:street":"Apollo Way",
    "iso:country":"GB",
    "sg:address":"26 Apollo Way",
    "sg:city":"Blackwood",
    "sg:classifiers":[
        {
            "category":"Food & Beverages",
            "subcategory":"Groceries & Convenience Stores",
            "type":"Retail Goods"
        }
    ],
    "sg:phone":"+44 1495 225926",
    "sg:postcode":"NP2 1WA",
    "sg:province":"Caerphilly",
    "wof:name":"W Willet",
    "wof:placetype":"venue"
},
  "geometry": {"coordinates":[-3.203896,51.667294],"type":"Point"}
}