{
  "type": "Feature",
  "properties": {
    "addr:full":"Unit 1 Sidings Indust Est, Hound Rd Southampton Hampshire SO31 5QA",
    "addr:housenumber":"unit 1",
    "addr:postcode":"so31 5qa",
    "addr:street":"Sidings Indust Est Hound Rd",
    "iso:country":"GB",
    "sg:address":"Unit 1 Sidings Indust Est, Hound Rd",
    "sg:city":"Southampton",
    "sg:classifiers":[
        {
            "category":"Wholesale",
            "subcategory":"Office Equipment",
            "type":"Manufacturing & Wholesale Goods"
        }
    ],
    "sg:phone":"+44 23 8045 7036",
    "sg:postcode":"SO31 5QA",
    "sg:province":"Hampshire",
    "sg:tags":[
        "partition",
        "cubicle"
    ],
    "wof:name":"Aztec Interiors",
    "wof:placetype":"venue"
},
  "geometry": {"coordinates":[-1.33921,50.872391],"type":"Point"}
}