{
  "type": "Feature",
  "properties": {
    "addr:full":"Victoria Road Mexborough South Yorkshire S64 9BX",
    "addr:postcode":"s64 9bx",
    "addr:street":"Victoria Road",
    "iso:country":"GB",
    "sg:address":"Victoria Road",
    "sg:city":"Mexborough",
    "sg:classifiers":[
        {
            "category":"Retail",
            "subcategory":"Auto Repair",
            "type":"Services"
        }
    ],
    "sg:phone":"+44 1709 583160",
    "sg:postcode":"S64 9BX",
    "sg:province":"South Yorkshire",
    "sg:tags":[
        "modification",
        "garage"
    ],
    "wof:name":"Tony Goddard & Son",
    "wof:placetype":"venue"
},
  "geometry": {"coordinates":[-1.2843589783,53.4981460571],"type":"Point"}
}