{
  "type": "Feature",
  "properties": {
    "addr:full":"4 Trafalgar Terrace Redcar North Yorkshire TS10 1QQ",
    "addr:housenumber":"4",
    "addr:postcode":"ts10 1qq",
    "addr:street":"Trafalgar Terrace",
    "iso:country":"GB",
    "sg:address":"4 Trafalgar Terrace",
    "sg:city":"Redcar",
    "sg:classifiers":[
        {
            "category":"Health Services",
            "subcategory":"Nursing And Care Facility",
            "type":"Services"
        }
    ],
    "sg:phone":"+44 1642 483673",
    "sg:postcode":"TS10 1QQ",
    "sg:province":"North Yorkshire",
    "sg:tags":[
        "home"
    ],
    "wof:name":"Lyngarth Residential Home",
    "wof:placetype":"venue"
},
  "geometry": {"coordinates":[-1.0770360231,54.6166038513],"type":"Point"}
}