{
  "type": "Feature",
  "properties": {
    "iso:country":"GB",
    "sg:address":"Newport Pagnell Road, Hardingstone",
    "sg:city":"Northampton",
    "sg:classifiers":[
        {
            "category":"Autos & Motor Vehicles",
            "subcategory":"Automobile Sales",
            "type":"Retail Goods"
        },
        {
            "category":"Retail",
            "subcategory":"Auto Repair",
            "type":"Services"
        }
    ],
    "sg:postcode":"NN4 6ER",
    "sg:province":"Northamptonshire",
    "sg:tags":[
        "modification",
        "garage",
        "car"
    ],
    "wof:name":"Autohaus Paint & Body",
    "wof:placetype":"venue"
},
  "geometry": {"coordinates":[-0.885216,52.213619],"type":"Point"}
}