{
  "type": "Feature",
  "properties": {
    "addr:full":"52 Hutton Close, Crowther Washington Durham NE38 0AH",
    "addr:housenumber":"52",
    "addr:postcode":"ne38 0ah",
    "addr:street":"Hutton Close",
    "iso:country":"GB",
    "sg:address":"52 Hutton Close, Crowther",
    "sg:city":"Washington",
    "sg:classifiers":[
        {
            "category":"Professional",
            "subcategory":"Engineering",
            "type":"Services"
        }
    ],
    "sg:phone":"+44 191 417 9916",
    "sg:postcode":"NE38 0AH",
    "sg:province":"Durham",
    "sg:tags":[
        "engineer"
    ],
    "wof:name":"Crowther Engineering Ltd.",
    "wof:placetype":"venue"
},
  "geometry": {"coordinates":[-1.5547729731,54.9019432068],"type":"Point"}
}