{
  "type": "Feature",
  "properties": {
    "iso:country":"GB",
    "sg:address":"5 Windsor Street",
    "sg:city":"Chertsey",
    "sg:classifiers":[
        {
            "category":"Food & Beverages",
            "subcategory":"Groceries & Convenience Stores",
            "type":"Retail Goods"
        }
    ],
    "sg:phone":"+44 1932 566557",
    "sg:postcode":"KT16 8AY",
    "sg:province":"Surrey",
    "wof:name":"One Stop Community Stores Ltd.",
    "wof:placetype":"venue"
},
  "geometry": {"coordinates":[-0.5040739775,51.3921546936],"type":"Point"}
}