{
  "type": "Feature",
  "properties": {
    "addr:full":"125a Willerby Road Harrogate North Yorkshire HG3 3BN",
    "addr:housenumber":"125a",
    "addr:postcode":"hg3 3bn",
    "addr:street":"Willerby Road",
    "iso:country":"GB",
    "sg:address":"125a Willerby Road",
    "sg:city":"Harrogate",
    "sg:classifiers":[
        {
            "category":"Building & Trades",
            "subcategory":"Construction",
            "type":"Services"
        }
    ],
    "sg:phone":"+44 1423 884450",
    "sg:postcode":"HG3 3BN",
    "sg:province":"North Yorkshire",
    "sg:tags":[
        "roofing"
    ],
    "wof:name":"Luty Roofing Contractors",
    "wof:placetype":"venue"
},
  "geometry": {"coordinates":[-1.54039,54.04211],"type":"Point"}
}