{
  "type": "Feature",
  "properties": {
    "addr:full":"62 Woods Lane, Cheadle Hulme Cheadle Cheshire SK8 7JX",
    "addr:housenumber":"62",
    "addr:postcode":"sk8 7jx",
    "addr:street":"Woods Lane",
    "iso:country":"GB",
    "sg:address":"62 Woods Lane, Cheadle Hulme",
    "sg:city":"Cheadle",
    "sg:classifiers":[
        {
            "category":"Recreation",
            "subcategory":"Dog Park",
            "type":"Entertainment"
        }
    ],
    "sg:postcode":"SK8 7JX",
    "sg:province":"Cheshire",
    "wof:name":"Mrs Bumbles Grooming Salon",
    "wof:placetype":"venue"
},
  "geometry": {"coordinates":[-2.187204,53.363628],"type":"Point"}
}