{
  "type": "Feature",
  "properties": {
    "iso:country":"GB",
    "sg:address":"55 Nigel Road",
    "sg:city":"London",
    "sg:classifiers":[
        {
            "category":"Place Of Worship",
            "type":"Public Place"
        }
    ],
    "sg:phone":"+44 20 7639 8459",
    "sg:postcode":"SE15 4NP",
    "sg:province":"Greater London",
    "wof:name":"Peckham Rye baptist Tabernacle",
    "wof:placetype":"venue"
},
  "geometry": {"coordinates":[-0.066739,51.46611],"type":"Point"}
}