{
  "type": "Feature",
  "properties": {
    "addr:full":"81 The Parade Leamington Spa Warwickshire CV32 4AY",
    "addr:housenumber":"81",
    "addr:postcode":"cv32 4ay",
    "addr:street":"The Parade",
    "iso:country":"GB",
    "sg:address":"81 The Parade",
    "sg:city":"Leamington Spa",
    "sg:classifiers":[
        {
            "category":"Travel",
            "subcategory":"Travel Agent",
            "type":"Entertainment"
        }
    ],
    "sg:phone":"+44 1926 307100",
    "sg:postcode":"CV32 4AY",
    "sg:province":"Warwickshire",
    "wof:name":"Thomas Cook",
    "wof:placetype":"venue"
},
  "geometry": {"coordinates":[-1.53524,52.289909],"type":"Point"}
}