{
  "type": "Feature",
  "properties": {
    "addr:full":"46-48 Red Lion Yard, Fore Street Okehampton Devon EX20 1AW",
    "addr:housenumber":"46-48",
    "addr:postcode":"ex20 1aw",
    "addr:street":"Red Lion Yard Fore Street",
    "iso:country":"GB",
    "sg:address":"46-48 Red Lion Yard, Fore Street",
    "sg:city":"Okehampton",
    "sg:classifiers":[
        {
            "category":"Shopping",
            "subcategory":"Pets & Pet Supplies",
            "type":"Retail Goods"
        }
    ],
    "sg:phone":"+44 1837 55403",
    "sg:postcode":"EX20 1AW",
    "sg:province":"Devon",
    "sg:tags":[
        "food"
    ],
    "wof:name":"Okehampton Pet & Equine Supplies",
    "wof:placetype":"venue"
},
  "geometry": {"coordinates":[-4.002515,50.739223],"type":"Point"}
}