{
  "type": "Feature",
  "properties": {
    "addr:full":"13 Mathews Way Abingdon Oxfordshire OX13 6JX",
    "addr:housenumber":"13",
    "addr:postcode":"ox13 6jx",
    "addr:street":"Mathews Way",
    "iso:country":"GB",
    "sg:address":"13 Mathews Way",
    "sg:city":"Abingdon",
    "sg:classifiers":[
        {
            "category":"Retail",
            "subcategory":"Repair Shop",
            "type":"Services"
        }
    ],
    "sg:postcode":"OX13 6JX",
    "sg:province":"Oxfordshire",
    "sg:tags":[
        "maintenance"
    ],
    "wof:name":"Vale Builders",
    "wof:placetype":"venue"
},
  "geometry": {"coordinates":[-1.3125139475,51.7041435242],"type":"Point"}
}