{
  "type": "Feature",
  "properties": {
    "addr:full":"1 Hornecourt Manor Farm Cottages, Hornecourt Hill Horley Surrey RH6 9LB",
    "addr:housenumber":"1",
    "addr:postcode":"rh6 9lb",
    "addr:street":"Hornecourt Manor Farm Cottages Hornecourt Hill",
    "iso:country":"GB",
    "sg:address":"1 Hornecourt Manor Farm Cottages, Hornecourt Hill",
    "sg:city":"Horley",
    "sg:classifiers":[
        {
            "category":"Home & Garden",
            "subcategory":"Building Materials",
            "type":"Retail Goods"
        }
    ],
    "sg:phone":"+44 1342 842546",
    "sg:postcode":"RH6 9LB",
    "sg:province":"Surrey",
    "sg:tags":[
        "dust",
        "extraction",
        "system"
    ],
    "wof:name":"Southern Filters",
    "wof:placetype":"venue"
},
  "geometry": {"coordinates":[-0.169289,51.175365],"type":"Point"}
}