{
  "type": "Feature",
  "properties": {
    "iso:country":"GB",
    "sg:address":"Po Box 236",
    "sg:city":"Chatham",
    "sg:classifiers":[
        {
            "category":"Recreation",
            "subcategory":"Fishing",
            "type":"Entertainment"
        }
    ],
    "sg:phone":"+44 1634 316374",
    "sg:postcode":"ME4 6LF",
    "sg:province":"Kent",
    "sg:tags":[
        "angling"
    ],
    "wof:name":"Trace Ace Tackle Ltd",
    "wof:placetype":"venue"
},
  "geometry": {"coordinates":[0.52244,51.381889],"type":"Point"}
}