{
  "type": "Feature",
  "properties": {
    "addr:full":"Ainderby Hall, Ainderby Quernhow Thirsk North Yorkshire YO7 4HZ",
    "addr:postcode":"yo7 4hz",
    "iso:country":"GB",
    "sg:address":"Ainderby Hall, Ainderby Quernhow",
    "sg:city":"Thirsk",
    "sg:classifiers":[
        {
            "category":"Home & Garden",
            "subcategory":"Garden Supply",
            "type":"Retail Goods"
        },
        {
            "category":"Farming",
            "subcategory":"Farm",
            "type":"Manufacturing & Wholesale Goods"
        }
    ],
    "sg:phone":"+44 1845 567224",
    "sg:postcode":"YO7 4HZ",
    "sg:province":"North Yorkshire",
    "sg:tags":[
        "mixed",
        "bulb",
        "crop",
        "grower"
    ],
    "wof:name":"Thomas M Jopling",
    "wof:placetype":"venue"
},
  "geometry": {"coordinates":[-1.4631140232,54.2222709656],"type":"Point"}
}