{
  "type": "Feature",
  "properties": {
    "iso:country":"GB",
    "sg:address":"Central Marches Business Development Cen, Long Lane Indstl Est",
    "sg:city":"Craven Arms",
    "sg:classifiers":[
        {
            "category":"Wholesale",
            "subcategory":"Office Equipment",
            "type":"Manufacturing & Wholesale Goods"
        },
        {
            "category":"Community Center",
            "type":"Public Place"
        }
    ],
    "sg:postcode":"SY7 8DU",
    "sg:province":"Herefordshire",
    "sg:tags":[
        "conference",
        "room",
        "business",
        "centre",
        "agency",
        "enterprise"
    ],
    "wof:name":"Business Link Shropshire Ltd",
    "wof:placetype":"venue"
},
  "geometry": {"coordinates":[-2.836239,52.439388],"type":"Point"}
}