{
  "type": "Feature",
  "properties": {
    "addr:full":"107a Reddal Hill Road Cradley Heath West Midlands B64 5JG",
    "addr:housenumber":"107a",
    "addr:postcode":"b64 5jg",
    "addr:street":"Reddal Hill Road",
    "iso:country":"GB",
    "sg:address":"107a Reddal Hill Road",
    "sg:city":"Cradley Heath",
    "sg:classifiers":[
        {
            "category":"Manufacturing",
            "subcategory":"Glass & Minerals",
            "type":"Manufacturing & Wholesale Goods"
        }
    ],
    "sg:postcode":"B64 5JG",
    "sg:province":"West Midlands",
    "sg:tags":[
        "glassworker"
    ],
    "wof:name":"The Glass Shop (Cradley) Ltd.",
    "wof:placetype":"venue"
},
  "geometry": {"coordinates":[-2.073771,52.476505],"type":"Point"}
}