{
  "type": "Feature",
  "properties": {
    "addr:full":"Crawleyside, Stanhope Bishop Auckland Durham DL13 2HA",
    "addr:postcode":"dl13 2ha",
    "addr:street":"Crawleyside;Auckland",
    "iso:country":"GB",
    "sg:address":"Crawleyside, Stanhope",
    "sg:city":"Bishop Auckland",
    "sg:classifiers":[
        {
            "category":"Recreation",
            "subcategory":"Campground",
            "type":"Entertainment"
        }
    ],
    "sg:phone":"+44 191 548 3506",
    "sg:postcode":"DL13 2HA",
    "sg:province":"Durham",
    "sg:tags":[
        "caravan",
        "park"
    ],
    "wof:name":"Stanhope Burn Caravan Park",
    "wof:placetype":"venue"
},
  "geometry": {"coordinates":[-2.0055539608,54.746925354],"type":"Point"}
}