{
  "type": "Feature",
  "properties": {
    "addr:full":"The Old Bake House, Owl End Lane, Lower Boddington Daventry Northamptonshire NN11 6XZ",
    "addr:postcode":"nn11 6xz",
    "addr:street":"Owl End Lane",
    "iso:country":"GB",
    "sg:address":"The Old Bake House, Owl End Lane, Lower Boddington",
    "sg:city":"Daventry",
    "sg:classifiers":[
        {
            "category":"Organizations",
            "subcategory":"Community Association",
            "type":"Services"
        }
    ],
    "sg:postcode":"NN11 6XZ",
    "sg:province":"Northamptonshire",
    "sg:tags":[
        "relation",
        "public"
    ],
    "wof:name":"The Ceres Partnership Ltd.",
    "wof:placetype":"venue"
},
  "geometry": {"coordinates":[-1.29849,52.164791],"type":"Point"}
}