{
  "type": "Feature",
  "properties": {
    "addr:full":"The White House, 1 Hook Lane Welling Kent DA16 2DJ",
    "addr:housenumber":"1",
    "addr:postcode":"da16 2dj",
    "addr:street":"Hook Lane",
    "iso:country":"GB",
    "sg:address":"The White House, 1 Hook Lane",
    "sg:city":"Welling",
    "sg:classifiers":[
        {
            "category":"Professional",
            "subcategory":"Lawyer & Legal Services",
            "type":"Services"
        }
    ],
    "sg:phone":"+44 20 8850 9291",
    "sg:postcode":"DA16 2DJ",
    "sg:province":"Kent",
    "sg:tags":[
        "solicitor"
    ],
    "wof:name":"Cattermole Solicitors",
    "wof:placetype":"venue"
},
  "geometry": {"coordinates":[0.10739,51.462158],"type":"Point"}
}