{
  "type": "Feature",
  "properties": {
    "iso:country":"GB",
    "sg:address":"17 Abbots Gro",
    "sg:city":"Stevenage",
    "sg:classifiers":[
        {
            "category":"Home & Garden",
            "subcategory":"Building Materials",
            "type":"Retail Goods"
        }
    ],
    "sg:phone":"+44 1438 369503",
    "sg:postcode":"SG1 1NS",
    "sg:province":"Hertfordshire",
    "sg:tags":[
        "ironwork",
        "diy",
        "wrought"
    ],
    "wof:name":"Fancy Fabrication",
    "wof:placetype":"venue"
},
  "geometry": {"coordinates":[-0.190566,51.900963],"type":"Point"}
}