{
  "type": "Feature",
  "properties": {
    "iso:country":"GB",
    "sg:address":"17 High Street",
    "sg:city":"Lutterworth",
    "sg:classifiers":[
        {
            "category":"Fast Food",
            "type":"Food & Drink"
        }
    ],
    "sg:phone":"+44 1455 552222",
    "sg:postcode":"LE17 4AT",
    "sg:province":"Leicestershire",
    "sg:tags":[
        "away",
        "meal",
        "outlet",
        "take"
    ],
    "wof:name":"China Cottage",
    "wof:placetype":"venue"
},
  "geometry": {"coordinates":[-1.199895,52.455006],"type":"Point"}
}