{
  "type": "Feature",
  "properties": {
    "iso:country":"GB",
    "sg:address":"77 Rodney Ct, 6-8 Maida Vale",
    "sg:city":"Maida Vale",
    "sg:classifiers":[
        {
            "category":"Professional",
            "subcategory":"Lawyer & Legal Services",
            "type":"Services"
        }
    ],
    "sg:phone":"+44 20 7266 0909",
    "sg:postcode":"W9 1TJ",
    "sg:province":"Greater London",
    "wof:name":"W P Kosmas",
    "wof:placetype":"venue"
},
  "geometry": {"coordinates":[-0.17896,51.526901],"type":"Point"}
}