{
  "type": "Feature",
  "properties": {
    "iso:country":"GB",
    "sg:address":"50 George Street",
    "sg:city":"Walsall",
    "sg:classifiers":[
        {
            "category":"Real Estate",
            "subcategory":"Surveying",
            "type":"Services"
        }
    ],
    "sg:phone":"+44 1922 621088",
    "sg:postcode":"WS1 1RS",
    "sg:province":"West Midlands",
    "sg:tags":[
        "surveyor",
        "quantity"
    ],
    "wof:name":"Desmond Ball Crump & Willis",
    "wof:placetype":"venue"
},
  "geometry": {"coordinates":[-1.980981,52.582294],"type":"Point"}
}