{
  "type": "Feature",
  "properties": {
    "addr:full":"1 Tait Street Dalkeith City of Edinburgh EH22 1AT",
    "addr:housenumber":"1",
    "addr:postcode":"eh22 1at",
    "addr:street":"Tait Street",
    "iso:country":"GB",
    "sg:address":"1 Tait Street",
    "sg:city":"Dalkeith",
    "sg:classifiers":[
        {
            "category":"Banks & Credit Unions",
            "subcategory":"Atm",
            "type":"Services"
        },
        {
            "category":"Home & Garden",
            "subcategory":"Building Materials",
            "type":"Retail Goods"
        }
    ],
    "sg:phone":"+44 131 660 2188",
    "sg:postcode":"EH22 1AT",
    "sg:province":"City of Edinburgh",
    "sg:tags":[
        "hinge",
        "cutting",
        "key"
    ],
    "wof:name":"Apache Services",
    "wof:placetype":"venue"
},
  "geometry": {"coordinates":[-3.0685179234,55.8949928284],"type":"Point"}
}