{
  "type": "Feature",
  "properties": {
    "addr:full":"1 Northumberland Terrace Plymouth Devon PL1 3DD",
    "addr:housenumber":"1",
    "addr:postcode":"pl1 3dd",
    "addr:street":"Northumberland Terrace",
    "iso:country":"GB",
    "sg:address":"1 Northumberland Terrace",
    "sg:city":"Plymouth",
    "sg:classifiers":[
        {
            "category":"Retail",
            "subcategory":"Auto Repair",
            "type":"Services"
        }
    ],
    "sg:postcode":"PL1 3DD",
    "sg:province":"Devon",
    "sg:tags":[
        "modification",
        "garage"
    ],
    "wof:name":"The Volkswagen Clinic",
    "wof:placetype":"venue"
},
  "geometry": {"coordinates":[-4.1489090919,50.363609314],"type":"Point"}
}