{
  "type": "Feature",
  "properties": {
    "addr:full":"55a Gorsey La Warrington Cheshire WA1 3PR",
    "addr:housenumber":"55a",
    "addr:postcode":"wa1 3pr",
    "addr:street":"Gorsey La Warrington Cheshire",
    "iso:country":"GB",
    "sg:address":"55a Gorsey La",
    "sg:city":"Warrington",
    "sg:classifiers":[
        {
            "category":"Retail",
            "subcategory":"Auto Repair",
            "type":"Services"
        }
    ],
    "sg:phone":"+44 1925 491302",
    "sg:postcode":"WA1 3PR",
    "sg:province":"Cheshire",
    "sg:tags":[
        "modification",
        "garage"
    ],
    "wof:name":"LRC Autos",
    "wof:placetype":"venue"
},
  "geometry": {"coordinates":[-2.5755600929,53.3995857239],"type":"Point"}
}