{
  "type": "Feature",
  "properties": {
    "iso:country":"GB",
    "sg:address":"Verity House, 40 Holmesdale Road",
    "sg:city":"Reigate",
    "sg:classifiers":[
        {
            "category":"Real Estate",
            "subcategory":"Surveying",
            "type":"Services"
        }
    ],
    "sg:phone":"+44 1737 222060",
    "sg:postcode":"RH2 0BQ",
    "sg:province":"Surrey",
    "sg:tags":[
        "surveyor",
        "quantity"
    ],
    "wof:name":"Chaseway Project Support",
    "wof:placetype":"venue"
},
  "geometry": {"coordinates":[-0.200319007,51.2415390015],"type":"Point"}
}