{
  "type": "Feature",
  "properties": {
    "iso:country":"GB",
    "sg:address":"42 Hartington Rd",
    "sg:city":"Southampton",
    "sg:classifiers":[
        {
            "category":"Professional",
            "type":"Services"
        }
    ],
    "sg:phone":"+44 23 8049 2983",
    "sg:postcode":"SO14 0EW",
    "sg:province":"Hampshire",
    "sg:tags":[
        "entertainer"
    ],
    "wof:name":"The Parr 3's Musical Entertainers",
    "wof:placetype":"venue"
},
  "geometry": {"coordinates":[-1.3924039602,50.9105186462],"type":"Point"}
}