{
  "type": "Feature",
  "properties": {
    "addr:full":"Unit 12-18 Piccadilly Trading Es Manchester Greater Manchester M1 2PL",
    "addr:housenumber":"unit 12-18",
    "addr:postcode":"m1 2pl",
    "addr:street":"Piccadilly Trading",
    "iso:country":"GB",
    "sg:address":"Unit 12-18 Piccadilly Trading Es",
    "sg:city":"Manchester",
    "sg:classifiers":[
        {
            "category":"Personal",
            "type":"Services"
        }
    ],
    "sg:phone":"+44 870 850 1150",
    "sg:postcode":"M1 2PL",
    "sg:province":"Greater Manchester",
    "sg:tags":[
        "delivery"
    ],
    "wof:name":"Parcelforce",
    "wof:placetype":"venue"
},
  "geometry": {"coordinates":[-2.219715,53.477425],"type":"Point"}
}