{
  "type": "Feature",
  "properties": {
    "addr:full":"13 Woodgavil Banstead Surrey SM7 1AA",
    "addr:housenumber":"13",
    "addr:postcode":"sm7 1aa",
    "addr:street":"Woodgavil Banstead",
    "iso:country":"GB",
    "sg:address":"13 Woodgavil",
    "sg:city":"Banstead",
    "sg:classifiers":[
        {
            "category":"Communications",
            "subcategory":"Film & Video Production",
            "type":"Services"
        },
        {
            "category":"Professional",
            "subcategory":"Printing & Photocopies",
            "type":"Services"
        }
    ],
    "sg:phone":"+44 1737 358034",
    "sg:postcode":"SM7 1AA",
    "sg:province":"Surrey",
    "sg:tags":[
        "supplier",
        "duplicating",
        "copying",
        "photocopier"
    ],
    "wof:name":"B M Copiers",
    "wof:placetype":"venue"
},
  "geometry": {"coordinates":[-0.2137659937,51.3194618225],"type":"Point"}
}