{
  "type": "Feature",
  "properties": {
    "addr:full":"Bateman Ho, Otto St Elephant And Castle Greater London SE17 3PF",
    "addr:postcode":"se17 3pf",
    "addr:street":"Otto St",
    "iso:country":"GB",
    "sg:address":"Bateman Ho, Otto St",
    "sg:city":"Elephant And Castle",
    "sg:classifiers":[
        {
            "category":"Professional",
            "subcategory":"Computer Services",
            "type":"Services"
        }
    ],
    "sg:phone":"+44 20 7820 8686",
    "sg:postcode":"SE17 3PF",
    "sg:province":"Greater London",
    "sg:tags":[
        "system",
        "software"
    ],
    "wof:name":"Micro Night System Services",
    "wof:placetype":"venue"
},
  "geometry": {"coordinates":[-0.1054399982,51.4826011658],"type":"Point"}
}