{
  "type": "Feature",
  "properties": {
    "addr:full":"North Carr Farm, West Stockwith Doncaster Lincolnshire DN10 4BD",
    "addr:housenumber":"stockwith",
    "addr:postcode":"dn10 4bd",
    "addr:street":"North Carr Farm West",
    "iso:country":"GB",
    "sg:address":"North Carr Farm, West Stockwith",
    "sg:city":"Doncaster",
    "sg:classifiers":[
        {
            "category":"Home & Garden",
            "subcategory":"Garden Supply",
            "type":"Retail Goods"
        }
    ],
    "sg:postcode":"DN10 4BD",
    "sg:province":"Lincolnshire",
    "sg:tags":[
        "turfing"
    ],
    "wof:name":"W S Harris & Sons Ltd.",
    "wof:placetype":"venue"
},
  "geometry": {"coordinates":[-0.809586,53.444824],"type":"Point"}
}