{
  "type": "Feature",
  "properties": {
    "addr:full":"14 Victoria Rd Bournemouth Dorset BH1 4RR",
    "addr:housenumber":"14",
    "addr:postcode":"bh1 4rr",
    "addr:street":"Victoria Rd",
    "iso:country":"GB",
    "sg:address":"14 Victoria Rd",
    "sg:city":"Bournemouth",
    "sg:classifiers":[
        {
            "category":"Professional",
            "subcategory":"Printing & Photocopies",
            "type":"Services"
        }
    ],
    "sg:phone":"+44 1202 558822",
    "sg:postcode":"BH1 4RR",
    "sg:province":"Dorset",
    "sg:tags":[
        "printer"
    ],
    "wof:name":"R W Mace",
    "wof:placetype":"venue"
},
  "geometry": {"coordinates":[-1.8559989929,50.7286376953],"type":"Point"}
}