{
  "type": "Feature",
  "properties": {
    "iso:country":"GB",
    "sg:address":"14-15 Brunswick St, Stockton",
    "sg:city":"Middlesbrough",
    "sg:classifiers":[
        {
            "category":"Retail",
            "subcategory":"Auto Rental",
            "type":"Services"
        }
    ],
    "sg:phone":"+44 1642 603606",
    "sg:postcode":"TS4 2UR",
    "sg:province":"North Yorkshire",
    "sg:tags":[
        "car"
    ],
    "wof:name":"Budget Rent-A-Car International Inc",
    "wof:placetype":"venue"
},
  "geometry": {"coordinates":[-1.23145,54.555988],"type":"Point"}
}