{
  "type": "Feature",
  "properties": {
    "iso:country":"GB",
    "sg:address":"58 Galley Lane, Arkley",
    "sg:city":"Barnet",
    "sg:classifiers":[
        {
            "category":"Building & Trades",
            "subcategory":"Construction",
            "type":"Services"
        }
    ],
    "sg:postcode":"EN5 4AL",
    "sg:province":"Hertfordshire",
    "sg:tags":[
        "builder"
    ],
    "wof:name":"Arkley Developments Ltd.",
    "wof:placetype":"venue"
},
  "geometry": {"coordinates":[-0.2304439992,51.6632423401],"type":"Point"}
}