{
  "type": "Feature",
  "properties": {
    "iso:country":"GB",
    "sg:address":"13 Forrest Road",
    "sg:city":"Edinburgh",
    "sg:classifiers":[
        {
            "category":"Professional",
            "subcategory":"Printing & Photocopies",
            "type":"Services"
        }
    ],
    "sg:phone":"+44 131 226 4353",
    "sg:postcode":"EH1 2QH",
    "sg:province":"City of Edinburgh",
    "sg:tags":[
        "duplicating",
        "copying"
    ],
    "wof:name":"Colour Copy Centre",
    "wof:placetype":"venue"
},
  "geometry": {"coordinates":[-3.191142,55.946262],"type":"Point"}
}