{
  "type": "Feature",
  "properties": {
    "addr:full":"2c High Street Dumbarton Argyll and Bute G82 1LL",
    "addr:housenumber":"2c",
    "addr:postcode":"g82 1ll",
    "addr:street":"High Street",
    "iso:country":"GB",
    "sg:address":"2c High Street",
    "sg:city":"Dumbarton",
    "sg:classifiers":[
        {
            "category":"Bars & Pubs",
            "type":"Food & Drink"
        }
    ],
    "sg:phone":"+44 1389 732703",
    "sg:postcode":"G82 1LL",
    "sg:province":"Argyll and Bute",
    "sg:tags":[
        "pubs",
        "inn"
    ],
    "wof:name":"Court House Bar",
    "wof:placetype":"venue"
},
  "geometry": {"coordinates":[-4.567876,55.943443],"type":"Point"}
}