{
  "type": "Feature",
  "properties": {
    "addr:full":"1154 Stratford Road Birmingham West Midlands B28 8AF",
    "addr:housenumber":"1154",
    "addr:postcode":"b28 8af",
    "addr:street":"Stratford Road",
    "iso:country":"GB",
    "sg:address":"1154 Stratford Road",
    "sg:city":"Birmingham",
    "sg:classifiers":[
        {
            "category":"Fast Food",
            "type":"Food & Drink"
        }
    ],
    "sg:phone":"+44 121 778 3332",
    "sg:postcode":"B28 8AF",
    "sg:province":"West Midlands",
    "sg:tags":[
        "away",
        "take"
    ],
    "wof:name":"Noshin Tandoori",
    "wof:placetype":"venue"
},
  "geometry": {"coordinates":[-1.8472679853,52.4379806519],"type":"Point"}
}