{
  "type": "Feature",
  "properties": {
    "iso:country":"GB",
    "sg:address":"1 Rowner Road",
    "sg:city":"Gosport",
    "sg:classifiers":[
        {
            "category":"Health Services",
            "subcategory":"Doctor",
            "type":"Services"
        }
    ],
    "sg:phone":"+44 23 9258 0093",
    "sg:postcode":"PO13 9UA",
    "sg:province":"Hampshire",
    "sg:tags":[
        "practitioners"
    ],
    "wof:name":"J H Grocock & S R E Morgan",
    "wof:placetype":"venue"
},
  "geometry": {"coordinates":[-1.172929,50.813141],"type":"Point"}
}