{
  "type": "Feature",
  "properties": {
    "iso:country":"GB",
    "sg:address":"Morbec Farm Arterial Rd",
    "sg:city":"Wickford",
    "sg:classifiers":[
        {
            "category":"Retail",
            "subcategory":"Auto Repair",
            "type":"Services"
        }
    ],
    "sg:postcode":"SS12 9JF",
    "sg:province":"Essex",
    "sg:tags":[
        "modification",
        "garage"
    ],
    "wof:name":"Titan Road Services Limited",
    "wof:placetype":"venue"
},
  "geometry": {"coordinates":[0.5189149976,51.6114349365],"type":"Point"}
}