{
  "type": "Feature",
  "properties": {
    "addr:full":"Goitre Farm, Garth Llangammarch Wells Powys LD4 4BN",
    "addr:postcode":"ld4 4bn",
    "addr:street":"Garth Llangammarch Wells",
    "iso:country":"GB",
    "sg:address":"Goitre Farm, Garth",
    "sg:city":"Llangammarch Wells",
    "sg:classifiers":[
        {
            "category":"Farming",
            "subcategory":"Farm",
            "type":"Manufacturing & Wholesale Goods"
        }
    ],
    "sg:phone":"+44 1591 620658",
    "sg:postcode":"LD4 4BN",
    "sg:province":"Powys",
    "sg:tags":[
        "mixed",
        "crop"
    ],
    "wof:name":"C J Davies",
    "wof:placetype":"venue"
},
  "geometry": {"coordinates":[-3.5557758808,52.1129798889],"type":"Point"}
}