{
  "type": "Feature",
  "properties": {
    "addr:full":"320 Mansel Rd Birmingham West Midlands B10 9NN",
    "addr:housenumber":"320",
    "addr:postcode":"b10 9nn",
    "addr:street":"Mansel Rd",
    "iso:country":"GB",
    "sg:address":"320 Mansel Rd",
    "sg:city":"Birmingham",
    "sg:classifiers":[
        {
            "category":"Travel",
            "subcategory":"Hotels & Motels",
            "type":"Entertainment"
        }
    ],
    "sg:postcode":"B10 9NN",
    "sg:province":"West Midlands",
    "sg:tags":[
        "house",
        "guest"
    ],
    "wof:name":"Ruhan,John,",
    "wof:placetype":"venue"
},
  "geometry": {"coordinates":[-1.848353982,52.4670944214],"type":"Point"}
}