{
  "type": "Feature",
  "properties": {
    "addr:full":"1 Grosvenor Terrace, Bowness On Windermere Windermere Cumbria LA23 3BS",
    "addr:housenumber":"1",
    "addr:postcode":"la23 3bs",
    "addr:street":"Grosvenor Terrace",
    "iso:country":"GB",
    "sg:address":"1 Grosvenor Terrace, Bowness On Windermere",
    "sg:city":"Windermere",
    "sg:classifiers":[
        {
            "category":"Fast Food",
            "type":"Food & Drink"
        },
        {
            "category":"Restaurant",
            "type":"Food & Drink"
        }
    ],
    "sg:phone":"+44 15394 42884",
    "sg:postcode":"LA23 3BS",
    "sg:province":"Cumbria",
    "sg:tags":[
        "away",
        "take"
    ],
    "wof:name":"The Alpine Restaurant",
    "wof:placetype":"venue"
},
  "geometry": {"coordinates":[-2.922436,54.362869],"type":"Point"}
}