{
  "type": "Feature",
  "properties": {
    "addr:full":"32-36 Harvey Lane Norwich Norfolk NR7 0DH",
    "addr:housenumber":"32-36",
    "addr:postcode":"nr7 0dh",
    "addr:street":"Harvey Lane",
    "iso:country":"GB",
    "sg:address":"32-36 Harvey Lane",
    "sg:city":"Norwich",
    "sg:classifiers":[
        {
            "category":"Autos & Motor Vehicles",
            "subcategory":"Motorcycle Sales",
            "type":"Retail Goods"
        }
    ],
    "sg:postcode":"NR7 0DH",
    "sg:province":"Norfolk",
    "wof:name":"P & H Motorcycles",
    "wof:placetype":"venue"
},
  "geometry": {"coordinates":[1.3289899826,52.6324501038],"type":"Point"}
}