{
  "type": "Feature",
  "properties": {
    "addr:full":"Rowans Red Lane, Churchinford Taunton Devon TA3 7QY",
    "addr:postcode":"ta3 7qy",
    "addr:street":"Red Lane Churchinford",
    "iso:country":"GB",
    "sg:address":"Rowans Red Lane, Churchinford",
    "sg:city":"Taunton",
    "sg:classifiers":[
        {
            "category":"Real Estate",
            "subcategory":"Surveying",
            "type":"Services"
        }
    ],
    "sg:phone":"+44 1823 601160",
    "sg:postcode":"TA3 7QY",
    "sg:province":"Devon",
    "sg:tags":[
        "surveyor",
        "valuer"
    ],
    "wof:name":"D Neil Atkinson & Co",
    "wof:placetype":"venue"
},
  "geometry": {"coordinates":[-3.121392,50.908089],"type":"Point"}
}