{
  "type": "Feature",
  "properties": {
    "iso:country":"GB",
    "sg:address":"Business Station Complex",
    "sg:city":"Rochdale",
    "sg:classifiers":[
        {
            "category":"Cafe",
            "type":"Food & Drink"
        }
    ],
    "sg:phone":"+44 1706 522014",
    "sg:postcode":"OL16 1YG",
    "sg:province":"Lancashire",
    "sg:tags":[
        "tea",
        "snack",
        "bar",
        "room"
    ],
    "wof:name":"The Bus Stop Cafe",
    "wof:placetype":"venue"
},
  "geometry": {"coordinates":[-2.1546299458,53.6177101135],"type":"Point"}
}