{
  "type": "Feature",
  "properties": {
    "addr:full":"Church Street, Hargrave Wellingborough Northamptonshire NN9 6BW",
    "addr:postcode":"nn9 6bw",
    "addr:street":"Church Street",
    "iso:country":"GB",
    "sg:address":"Church Street, Hargrave",
    "sg:city":"Wellingborough",
    "sg:classifiers":[
        {
            "category":"Bars & Pubs",
            "type":"Food & Drink"
        },
        {
            "category":"Community Center",
            "subcategory":"Social",
            "type":"Public Place"
        }
    ],
    "sg:postcode":"NN9 6BW",
    "sg:province":"Northamptonshire",
    "sg:tags":[
        "pubs",
        "house",
        "inn",
        "activity"
    ],
    "wof:name":"The Old Nags Head",
    "wof:placetype":"venue"
},
  "geometry": {"coordinates":[-0.4800589979,52.324016571],"type":"Point"}
}