{
  "type": "Feature",
  "properties": {
    "addr:full":"Moorhouse Farm Thirsk North Yorkshire YO7 2EF",
    "addr:housenumber":"thirsk",
    "addr:postcode":"yo7 2ef",
    "iso:country":"GB",
    "sg:address":"Moorhouse Farm",
    "sg:city":"Thirsk",
    "sg:classifiers":[
        {
            "category":"Farming",
            "subcategory":"Farm",
            "type":"Manufacturing & Wholesale Goods"
        }
    ],
    "sg:phone":"+44 1845 522334",
    "sg:postcode":"YO7 2EF",
    "sg:province":"North Yorkshire",
    "sg:tags":[
        "mixed",
        "crop"
    ],
    "wof:name":"B Bosomworth & Sons",
    "wof:placetype":"venue"
},
  "geometry": {"coordinates":[-1.342253,54.232689],"type":"Point"}
}