{
  "type": "Feature",
  "properties": {
    "iso:country":"GB",
    "sg:address":"72 Harley Street",
    "sg:city":"London",
    "sg:classifiers":[
        {
            "category":"Health Services",
            "subcategory":"Dentist",
            "type":"Services"
        }
    ],
    "sg:phone":"+44 20 7580 3168",
    "sg:postcode":"W1G 7HG",
    "sg:province":"Greater London",
    "wof:name":"A C Newbury",
    "wof:placetype":"venue"
},
  "geometry": {"coordinates":[-0.1471540034,51.5199012756],"type":"Point"}
}