{
  "type": "Feature",
  "properties": {
    "addr:full":"Riddrievale Court Glasgow Glasgow City G33 2RN",
    "addr:postcode":"g33 2rn",
    "addr:street":"Riddrievale Court",
    "iso:country":"GB",
    "sg:address":"Riddrievale Court",
    "sg:city":"Glasgow",
    "sg:classifiers":[
        {
            "category":"Travel",
            "subcategory":"Hostel",
            "type":"Entertainment"
        }
    ],
    "sg:phone":"+44 141 770 4635",
    "sg:postcode":"G33 2RN",
    "sg:province":"Glasgow City",
    "wof:name":"Riddrie Hostel",
    "wof:placetype":"venue"
},
  "geometry": {"coordinates":[-4.1858329773,55.8698310852],"type":"Point"}
}