{
  "type": "Feature",
  "properties": {
    "iso:country":"GB",
    "sg:address":"6 Hillbudge Terrace Park St",
    "sg:city":"Crediton",
    "sg:classifiers":[
        {
            "category":"Arts & Performance",
            "subcategory":"Theater",
            "type":"Entertainment"
        }
    ],
    "sg:phone":"+44 1363 775251",
    "sg:postcode":"EX17 3ED",
    "sg:province":"Devon",
    "sg:tags":[
        "theatre"
    ],
    "wof:name":"Imule Theatre Co",
    "wof:placetype":"venue"
},
  "geometry": {"coordinates":[-3.6551089287,50.7894515991],"type":"Point"}
}