{
  "type": "Feature",
  "properties": {
    "iso:country":"GB",
    "sg:address":"107 Netherton Lane, Netherton",
    "sg:city":"Wakefield",
    "sg:classifiers":[
        {
            "category":"Shopping",
            "subcategory":"Department Store",
            "type":"Retail Goods"
        },
        {
            "category":"Place Of Worship",
            "type":"Public Place"
        },
        {
            "category":"Food & Beverages",
            "subcategory":"Groceries & Convenience Stores",
            "type":"Retail Goods"
        }
    ],
    "sg:phone":"+44 1924 277961",
    "sg:postcode":"WF4 4HQ",
    "sg:province":"West Yorkshire",
    "wof:name":"Netherton Stores",
    "wof:placetype":"venue"
},
  "geometry": {"coordinates":[-1.5749720335,53.6489105225],"type":"Point"}
}