{
  "type": "Feature",
  "properties": {
    "iso:country":"GB",
    "sg:address":"188-190 Kingfield Road",
    "sg:city":"Coventry",
    "sg:classifiers":[
        {
            "category":"Retail",
            "subcategory":"Auto Rental",
            "type":"Services"
        }
    ],
    "sg:phone":"+44 24 7668 5676",
    "sg:postcode":"CV6 5PL",
    "sg:province":"Warwickshire",
    "sg:tags":[
        "car",
        "vehicle"
    ],
    "wof:name":"Kingfield Vehicle Services",
    "wof:placetype":"venue"
},
  "geometry": {"coordinates":[-1.5075069666,52.4266433716],"type":"Point"}
}