{
  "type": "Feature",
  "properties": {
    "iso:country":"GB",
    "sg:address":"Unit 50, Percy Business Park, Rounds Green Rd",
    "sg:city":"Oldbury",
    "sg:classifiers":[
        {
            "category":"Manufacturing",
            "subcategory":"Metals",
            "type":"Manufacturing & Wholesale Goods"
        }
    ],
    "sg:phone":"+44 121 544 5748",
    "sg:postcode":"B69 2RD",
    "sg:province":"West Midlands",
    "sg:tags":[
        "steel",
        "fabricator",
        "erectors"
    ],
    "wof:name":"Crompton Fabrication",
    "wof:placetype":"venue"
},
  "geometry": {"coordinates":[-2.015845,52.503777],"type":"Point"}
}