{
  "type": "Feature",
  "properties": {
    "iso:country":"GB",
    "sg:address":"17 The Observatory, High St",
    "sg:city":"Slough",
    "sg:classifiers":[
        {
            "category":"Shopping",
            "subcategory":"Clothing, Apparel, & Fashions",
            "type":"Retail Goods"
        }
    ],
    "sg:phone":"+44 1753 539094",
    "sg:postcode":"SL1 1LE",
    "sg:province":"Berkshire",
    "sg:tags":[
        "shop"
    ],
    "wof:name":"Double Bubble",
    "wof:placetype":"venue"
},
  "geometry": {"coordinates":[-0.596417,51.507874],"type":"Point"}
}