{
  "type": "Feature",
  "properties": {
    "addr:full":"Walbrook House, 23 Walbrook London Greater London EC4N 8BT",
    "addr:housenumber":"23",
    "addr:postcode":"ec4n 8bt",
    "iso:country":"GB",
    "sg:address":"Walbrook House, 23 Walbrook",
    "sg:city":"London",
    "sg:classifiers":[
        {
            "category":"Professional",
            "subcategory":"Business Services",
            "type":"Services"
        }
    ],
    "sg:postcode":"EC4N 8BT",
    "sg:province":"Greater London",
    "sg:tags":[
        "holding"
    ],
    "wof:name":"Essexkent Ltd",
    "wof:placetype":"venue"
},
  "geometry": {"coordinates":[-0.09029,51.51265],"type":"Point"}
}