{
  "type": "Feature",
  "properties": {
    "iso:country":"GB",
    "sg:address":"493-493a London Road",
    "sg:city":"Westcliff-on-sea",
    "sg:classifiers":[
        {
            "category":"Shopping",
            "subcategory":"Pets & Pet Supplies",
            "type":"Retail Goods"
        }
    ],
    "sg:phone":"+44 1702 343488",
    "sg:postcode":"SS0 9LG",
    "sg:province":"Essex",
    "wof:name":"Chalkwell Pets",
    "wof:placetype":"venue"
},
  "geometry": {"coordinates":[0.690227,51.544445],"type":"Point"}
}