{
  "type": "Feature",
  "properties": {
    "addr:full":"20 Victoria Road Stanford-le-hope Essex SS17 0HS",
    "addr:housenumber":"20",
    "addr:postcode":"ss17 0hs",
    "addr:street":"Victoria Road",
    "iso:country":"GB",
    "sg:address":"20 Victoria Road",
    "sg:city":"Stanford-le-hope",
    "sg:classifiers":[
        {
            "category":"Health Services",
            "subcategory":"Health Practitioner",
            "type":"Services"
        }
    ],
    "sg:phone":"+44 1375 361011",
    "sg:postcode":"SS17 0HS",
    "sg:province":"Essex",
    "sg:tags":[
        "acupuncture",
        "physiotherapist",
        "osteopath"
    ],
    "sg:website":"http://www.lingwoodclinic.co.uk",
    "wof:name":"Lingwood Clinic",
    "wof:placetype":"venue"
},
  "geometry": {"coordinates":[0.4246549904,51.515789032],"type":"Point"}
}