{
  "type": "Feature",
  "properties": {
    "addr:full":"23 The Promenade Bridlington East Riding of Yorkshire YO15 2QA",
    "addr:housenumber":"23",
    "addr:postcode":"yo15 2qa",
    "addr:street":"The Promenade Bridlington",
    "iso:country":"GB",
    "sg:address":"23 The Promenade",
    "sg:city":"Bridlington",
    "sg:classifiers":[
        {
            "category":"Shopping",
            "subcategory":"Books",
            "type":"Retail Goods"
        }
    ],
    "sg:postcode":"YO15 2QA",
    "sg:province":"East Riding of Yorkshire",
    "sg:tags":[
        "bookseller"
    ],
    "wof:name":"Garlands of Bridlington",
    "wof:placetype":"venue"
},
  "geometry": {"coordinates":[-0.189232,54.082851],"type":"Point"}
}