{
  "type": "Feature",
  "properties": {
    "addr:full":"3 Crescent Terrace Whitby North Yorkshire YO21 3EL",
    "addr:housenumber":"3",
    "addr:postcode":"yo21 3el",
    "addr:street":"Crescent Terrace",
    "iso:country":"GB",
    "sg:address":"3 Crescent Terrace",
    "sg:city":"Whitby",
    "sg:classifiers":[
        {
            "category":"Travel",
            "subcategory":"Hotels & Motels",
            "type":"Entertainment"
        }
    ],
    "sg:phone":"+44 1947 821888",
    "sg:postcode":"YO21 3EL",
    "sg:province":"North Yorkshire",
    "wof:name":"The Anchorage Hotel",
    "wof:placetype":"venue"
},
  "geometry": {"coordinates":[-0.619854,54.488811],"type":"Point"}
}