{
  "type": "Feature",
  "properties": {
    "iso:country":"GB",
    "sg:address":"51 Rose Avenue, Darfield",
    "sg:city":"Barnsley",
    "sg:classifiers":[
        {
            "category":"Building & Trades",
            "subcategory":"Construction",
            "type":"Services"
        }
    ],
    "sg:phone":"+44 1226 755557",
    "sg:postcode":"S73 9BW",
    "sg:province":"South Yorkshire",
    "sg:tags":[
        "roofing"
    ],
    "wof:name":"William Wright Roofing Services",
    "wof:placetype":"venue"
},
  "geometry": {"coordinates":[-1.379601,53.542202],"type":"Point"}
}