{
  "type": "Feature",
  "properties": {
    "iso:country":"GB",
    "sg:address":"39 Roseburn Terrace",
    "sg:city":"Edinburgh",
    "sg:classifiers":[
        {
            "category":"Home & Garden",
            "subcategory":"Household Appliances",
            "type":"Retail Goods"
        },
        {
            "category":"Retail",
            "subcategory":"Repair Shop",
            "type":"Services"
        }
    ],
    "sg:phone":"+44 131 337 0038",
    "sg:postcode":"EH12 5NQ",
    "sg:province":"City of Edinburgh",
    "sg:tags":[
        "machine",
        "electrical",
        "washing"
    ],
    "wof:name":"Capital Domestic Repairs",
    "wof:placetype":"venue"
},
  "geometry": {"coordinates":[-3.2376270294,55.9422988892],"type":"Point"}
}