{
  "type": "Feature",
  "properties": {
    "iso:country":"GB",
    "sg:address":"2 Union Terrace",
    "sg:city":"Dundee",
    "sg:classifiers":[
        {
            "category":"Travel",
            "subcategory":"Hotels & Motels",
            "type":"Entertainment"
        }
    ],
    "sg:phone":"+44 1382 223521",
    "sg:postcode":"DD3 6JD",
    "sg:province":"Dundee City",
    "wof:name":"Barton House Hotel",
    "wof:placetype":"venue"
},
  "geometry": {"coordinates":[-2.9780030251,56.4659881592],"type":"Point"}
}