{
  "type": "Feature",
  "properties": {
    "iso:country":"GB",
    "sg:address":"20 Gardner Street",
    "sg:city":"Brighton",
    "sg:classifiers":[
        {
            "category":"Personal",
            "subcategory":"Beauty Salon",
            "type":"Services"
        }
    ],
    "sg:phone":"+44 1273 677385",
    "sg:postcode":"BN1 1UP",
    "sg:province":"East Sussex",
    "sg:tags":[
        "unisex",
        "hairdresser"
    ],
    "wof:name":"Janet Loraine Hair & Beauty",
    "wof:placetype":"venue"
},
  "geometry": {"coordinates":[-0.139631,50.825233],"type":"Point"}
}