{
  "type": "Feature",
  "properties": {
    "iso:country":"GB",
    "sg:address":"4th Floor, 12-13 Greville Street",
    "sg:city":"London",
    "sg:classifiers":[
        {
            "category":"Organizations",
            "subcategory":"Non-profit Organization",
            "type":"Services"
        }
    ],
    "sg:postcode":"EC1N 8SB",
    "sg:province":"Greater London",
    "sg:tags":[
        "organisation",
        "voluntary",
        "charity"
    ],
    "wof:name":"Camden  &  Westminster Refugee Training",
    "wof:placetype":"venue"
},
  "geometry": {"coordinates":[-0.107575,51.519295],"type":"Point"}
}