{
  "type": "Feature",
  "properties": {
    "addr:full":"Kirkmay Crossing, Crail Anstruther Fife KY10 3XA",
    "addr:postcode":"ky10 3xa",
    "addr:street":"Kirkmay Crossing",
    "iso:country":"GB",
    "sg:address":"Kirkmay Crossing, Crail",
    "sg:city":"Anstruther",
    "sg:classifiers":[
        {
            "category":"Shopping",
            "subcategory":"Hobbies, Toys, & Games",
            "type":"Retail Goods"
        }
    ],
    "sg:postcode":"KY10 3XA",
    "sg:province":"Fife",
    "sg:tags":[
        "house",
        "dolls'",
        "doll"
    ],
    "wof:name":"Bermades Original Paper Doll Co.",
    "wof:placetype":"venue"
},
  "geometry": {"coordinates":[-2.7009840012,56.2228851318],"type":"Point"}
}