{
  "type": "Feature",
  "properties": {
    "addr:full":"22 Great James Street Bloomsbury Greater London WC1N 3ES",
    "addr:housenumber":"22",
    "addr:postcode":"wc1n 3es",
    "addr:street":"Great James Street",
    "iso:country":"GB",
    "sg:address":"22 Great James Street",
    "sg:city":"Bloomsbury",
    "sg:classifiers":[
        {
            "category":"Professional",
            "subcategory":"Business Services",
            "type":"Services"
        }
    ],
    "sg:postcode":"WC1N 3ES",
    "sg:province":"Greater London",
    "sg:tags":[
        "holding"
    ],
    "wof:name":"Whitcombe Holdings Ltd",
    "wof:placetype":"venue"
},
  "geometry": {"coordinates":[-0.117242001,51.521648407],"type":"Point"}
}