{
  "type": "Feature",
  "properties": {
    "addr:full":"9 Chapel Row, Middleton-in-teesdale Barnard Castle Cumbria DL12 0SN",
    "addr:housenumber":"9",
    "addr:postcode":"dl12 0sn",
    "addr:street":"Chapel Row",
    "iso:country":"GB",
    "sg:address":"9 Chapel Row, Middleton-in-teesdale",
    "sg:city":"Barnard Castle",
    "sg:classifiers":[
        {
            "category":"Fast Food",
            "type":"Food & Drink"
        },
        {
            "category":"Restaurant",
            "type":"Food & Drink"
        }
    ],
    "sg:postcode":"DL12 0SN",
    "sg:province":"Cumbria",
    "sg:tags":[
        "away",
        "take"
    ],
    "wof:name":"Watson,Nicola,",
    "wof:placetype":"venue"
},
  "geometry": {"coordinates":[-2.0811500549,54.6239089966],"type":"Point"}
}