{
  "type": "Feature",
  "properties": {
    "addr:full":"30 Halford Rd Stratford Upon Avon Warwickshire CV37 9BD",
    "addr:housenumber":"30",
    "addr:postcode":"cv37 9bd",
    "addr:street":"Halford Rd",
    "iso:country":"GB",
    "sg:address":"30 Halford Rd",
    "sg:city":"Stratford Upon Avon",
    "sg:classifiers":[
        {
            "category":"Building & Trades",
            "subcategory":"Landscaping Services",
            "type":"Services"
        }
    ],
    "sg:phone":"+44 1789 292233",
    "sg:postcode":"CV37 9BD",
    "sg:province":"Warwickshire",
    "sg:tags":[
        "contractor"
    ],
    "wof:name":"Garden Draft & Design",
    "wof:placetype":"venue"
},
  "geometry": {"coordinates":[-1.723508,52.186089],"type":"Point"}
}