{
  "type": "Feature",
  "properties": {
    "addr:full":"8 George Street Croydon Surrey CR0 1PA",
    "addr:housenumber":"8",
    "addr:postcode":"cr0 1pa",
    "addr:street":"George Street",
    "iso:country":"GB",
    "sg:address":"8 George Street",
    "sg:city":"Croydon",
    "sg:classifiers":[
        {
            "category":"Shopping",
            "subcategory":"Pharmacy",
            "type":"Retail Goods"
        }
    ],
    "sg:phone":"+44 20 8680 7761",
    "sg:postcode":"CR0 1PA",
    "sg:province":"Surrey",
    "sg:tags":[
        "medicine",
        "therapy"
    ],
    "wof:name":"Essential Care Training Ltd.",
    "wof:placetype":"venue"
},
  "geometry": {"coordinates":[-0.0996029973,51.3736076355],"type":"Point"}
}