{
  "type": "Feature",
  "properties": {
    "iso:country":"GB",
    "sg:address":"Camden Square",
    "sg:city":"Seaham",
    "sg:classifiers":[
        {
            "category":"Education",
            "subcategory":"School",
            "type":"Public Place"
        },
        {
            "category":"Government",
            "subcategory":"Office",
            "type":"Public Place"
        }
    ],
    "sg:phone":"+44 191 581 3020",
    "sg:postcode":"SR7 7SY",
    "sg:province":"Durham",
    "sg:tags":[
        "local",
        "authority"
    ],
    "wof:name":"Camden Square Infant School",
    "wof:placetype":"venue"
},
  "geometry": {"coordinates":[-1.342804,54.833641],"type":"Point"}
}