{
  "type": "Feature",
  "properties": {
    "iso:country":"GB",
    "sg:address":"Oversley Cottage, Shrewsbury Rd, Edgmond",
    "sg:city":"Newport",
    "sg:classifiers":[
        {
            "category":"Banks & Credit Unions",
            "subcategory":"Bank",
            "type":"Services"
        }
    ],
    "sg:phone":"+44 1952 813144",
    "sg:postcode":"TF10 8HT",
    "sg:province":"Shropshire",
    "sg:tags":[
        "broker",
        "mortgage"
    ],
    "wof:name":"K.W Mortgage Consultants",
    "wof:placetype":"venue"
},
  "geometry": {"coordinates":[-2.410849,52.773045],"type":"Point"}
}