{
  "type": "Feature",
  "properties": {
    "addr:full":"31 Robert Wynd Bilston West Midlands WV14 9SE",
    "addr:housenumber":"31",
    "addr:postcode":"wv14 9se",
    "addr:street":"Robert Wynd",
    "iso:country":"GB",
    "sg:address":"31 Robert Wynd",
    "sg:city":"Bilston",
    "sg:classifiers":[
        {
            "category":"Building & Trades",
            "subcategory":"Construction",
            "type":"Services"
        }
    ],
    "sg:phone":"+44 1902 676139",
    "sg:postcode":"WV14 9SE",
    "sg:province":"West Midlands",
    "sg:tags":[
        "roofing"
    ],
    "wof:name":"B M N Roofing",
    "wof:placetype":"venue"
},
  "geometry": {"coordinates":[-2.1042010784,52.5478668213],"type":"Point"}
}