{
  "type": "Feature",
  "properties": {
    "addr:full":"54 Kilmarnock Road Glasgow Glasgow City G41 3NH",
    "addr:housenumber":"54",
    "addr:postcode":"g41 3nh",
    "addr:street":"Kilmarnock Road",
    "iso:country":"GB",
    "sg:address":"54 Kilmarnock Road",
    "sg:city":"Glasgow",
    "sg:classifiers":[
        {
            "category":"Bars & Pubs",
            "subcategory":"Nightclub",
            "type":"Food & Drink"
        }
    ],
    "sg:phone":"+44 141 649 2050",
    "sg:postcode":"G41 3NH",
    "sg:province":"Glasgow City",
    "sg:tags":[
        "club",
        "night"
    ],
    "wof:name":"Rosco's Nightclub",
    "wof:placetype":"venue"
},
  "geometry": {"coordinates":[-4.2828879356,55.8293228149],"type":"Point"}
}