{
  "type": "Feature",
  "properties": {
    "addr:full":"Eland Grn, North Road, Ponteland Newcastle-upon-tyne Northumberland NE20 9UR",
    "addr:postcode":"ne20 9ur",
    "addr:street":"Eland Grn North Road",
    "iso:country":"GB",
    "sg:address":"Eland Grn, North Road, Ponteland",
    "sg:city":"Newcastle-upon-tyne",
    "sg:classifiers":[
        {
            "category":"Farming",
            "subcategory":"Livestock Farm",
            "type":"Manufacturing & Wholesale Goods"
        }
    ],
    "sg:postcode":"NE20 9UR",
    "sg:province":"Northumberland",
    "sg:tags":[
        "others"
    ],
    "wof:name":"Frank Stephenson",
    "wof:placetype":"venue"
},
  "geometry": {"coordinates":[-1.7427150011,55.0497398376],"type":"Point"}
}