{
  "type": "Feature",
  "properties": {
    "addr:full":"33 Woodlands Road London Greater London N9 8RP",
    "addr:housenumber":"33",
    "addr:postcode":"n9 8rp",
    "addr:street":"Woodlands Road",
    "iso:country":"GB",
    "sg:address":"33 Woodlands Road",
    "sg:city":"London",
    "sg:classifiers":[
        {
            "category":"Building & Trades",
            "subcategory":"Construction",
            "type":"Services"
        }
    ],
    "sg:phone":"+44 20 8805 4161",
    "sg:postcode":"N9 8RP",
    "sg:province":"Greater London",
    "sg:tags":[
        "joinery",
        "joiner",
        "carpenter",
        "carpentry"
    ],
    "wof:name":"L G Carpentry & Joinery",
    "wof:placetype":"venue"
},
  "geometry": {"coordinates":[-0.048794,51.631397],"type":"Point"}
}