{
  "type": "Feature",
  "properties": {
    "addr:full":"21 Burley Way, Blackwater Camberley Hampshire GU17 0HQ",
    "addr:housenumber":"21",
    "addr:postcode":"gu17 0hq",
    "addr:street":"Burley Way",
    "iso:country":"GB",
    "sg:address":"21 Burley Way, Blackwater",
    "sg:city":"Camberley",
    "sg:classifiers":[
        {
            "category":"Retail",
            "subcategory":"Driving School",
            "type":"Services"
        }
    ],
    "sg:phone":"+44 1252 878409",
    "sg:postcode":"GU17 0HQ",
    "sg:province":"Hampshire",
    "wof:name":"Theresa's School Of Motoring",
    "wof:placetype":"venue"
},
  "geometry": {"coordinates":[-0.788549006,51.3373908997],"type":"Point"}
}