{
  "type": "Feature",
  "properties": {
    "iso:country":"GB",
    "sg:address":"Boycot Farm, Yockleton",
    "sg:city":"Shrewsbury",
    "sg:classifiers":[
        {
            "category":"Farming",
            "subcategory":"Farm",
            "type":"Manufacturing & Wholesale Goods"
        }
    ],
    "sg:phone":"+44 1743 790281",
    "sg:postcode":"SY5 9QA",
    "sg:province":"Shropshire",
    "sg:tags":[
        "mixed",
        "crop"
    ],
    "wof:name":"D J Evans",
    "wof:placetype":"venue"
},
  "geometry": {"coordinates":[-2.886779,52.68578],"type":"Point"}
}