{
  "type": "Feature",
  "properties": {
    "addr:full":"120 Beckett St Leeds West Yorkshire LS9 7JX",
    "addr:housenumber":"120",
    "addr:postcode":"ls9 7jx",
    "addr:street":"Beckett St",
    "iso:country":"GB",
    "sg:address":"120 Beckett St",
    "sg:city":"Leeds",
    "sg:classifiers":[
        {
            "category":"Bars & Pubs",
            "type":"Food & Drink"
        }
    ],
    "sg:postcode":"LS9 7JX",
    "sg:province":"West Yorkshire",
    "sg:tags":[
        "pubs",
        "inn"
    ],
    "wof:name":"Batley,Jannine,",
    "wof:placetype":"venue"
},
  "geometry": {"coordinates":[-1.5208599567,53.8055953979],"type":"Point"}
}