{
  "type": "Feature",
  "properties": {
    "addr:full":"Liberty Road Bellshill North Lanarkshire ML4 2EY",
    "addr:postcode":"ml4 2ey",
    "addr:street":"Liberty Road",
    "iso:country":"GB",
    "sg:address":"Liberty Road",
    "sg:city":"Bellshill",
    "sg:classifiers":[
        {
            "category":"Arena",
            "subcategory":"Sports Club",
            "type":"Entertainment"
        }
    ],
    "sg:phone":"+44 1698 745114",
    "sg:postcode":"ML4 2EY",
    "sg:province":"North Lanarkshire",
    "wof:name":"Orbiston Bowling Club",
    "wof:placetype":"venue"
},
  "geometry": {"coordinates":[-4.0235590935,55.8122291565],"type":"Point"}
}