{
  "type": "Feature",
  "properties": {
    "addr:full":"42 North View, Westbury Park Bristol City of Bristol BS6 7QA",
    "addr:housenumber":"42",
    "addr:postcode":"bs6 7qa",
    "addr:street":"North View;Park",
    "iso:country":"GB",
    "sg:address":"42 North View, Westbury Park",
    "sg:city":"Bristol",
    "sg:classifiers":[
        {
            "category":"Shopping",
            "subcategory":"News",
            "type":"Retail Goods"
        }
    ],
    "sg:phone":"+44 117 907 6665",
    "sg:postcode":"BS6 7QA",
    "sg:province":"City of Bristol",
    "sg:tags":[
        "newsagent"
    ],
    "wof:name":"Westbury Park News",
    "wof:placetype":"venue"
},
  "geometry": {"coordinates":[-2.6125900745,51.4795303345],"type":"Point"}
}