{
  "type": "Feature",
  "properties": {
    "iso:country":"GB",
    "sg:address":"4 Clare Cres",
    "sg:city":"Towcester",
    "sg:classifiers":[
        {
            "category":"Personal",
            "type":"Services"
        }
    ],
    "sg:phone":"+44 1327 351746",
    "sg:postcode":"NN12 7QQ",
    "sg:province":"Buckinghamshire",
    "sg:tags":[
        "delivery"
    ],
    "wof:name":"L & G Collection & Delivery Services",
    "wof:placetype":"venue"
},
  "geometry": {"coordinates":[-0.995357,52.129471],"type":"Point"}
}