{
  "type": "Feature",
  "properties": {
    "iso:country":"GB",
    "sg:address":"Swilletts Farm",
    "sg:city":"Beaminster",
    "sg:classifiers":[
        {
            "category":"Farming",
            "subcategory":"Livestock Farm",
            "type":"Manufacturing & Wholesale Goods"
        }
    ],
    "sg:phone":"+44 1308 868297",
    "sg:postcode":"DT8 3LB",
    "sg:province":"Dorset",
    "sg:tags":[
        "others"
    ],
    "wof:name":"W T Ewins",
    "wof:placetype":"venue"
},
  "geometry": {"coordinates":[-2.7388939857,50.8090057373],"type":"Point"}
}