{
  "type": "Feature",
  "properties": {
    "iso:country":"GB",
    "sg:address":"151-155 Radford Road",
    "sg:city":"Coventry",
    "sg:classifiers":[
        {
            "category":"Home & Garden",
            "subcategory":"Home Furnishings",
            "type":"Retail Goods"
        }
    ],
    "sg:postcode":"CV6 3BT",
    "sg:province":"Warwickshire",
    "sg:tags":[
        "wall",
        "wallpaper",
        "covering"
    ],
    "wof:name":"Bargain Warehouse",
    "wof:placetype":"venue"
},
  "geometry": {"coordinates":[-1.521303,52.422405],"type":"Point"}
}