{
  "type": "Feature",
  "properties": {
    "iso:country":"GB",
    "sg:address":"31-33 Silver Birch Road, Erdington",
    "sg:city":"Birmingham",
    "sg:classifiers":[
        {
            "category":"Social Services",
            "subcategory":"Retirement Home",
            "type":"Services"
        }
    ],
    "sg:phone":"+44 121 350 4212",
    "sg:postcode":"B24 0AR",
    "sg:province":"West Midlands",
    "sg:tags":[
        "residential",
        "rest",
        "care"
    ],
    "wof:name":"St Agnes Residential Care For The Elderly",
    "wof:placetype":"venue"
},
  "geometry": {"coordinates":[-1.827975,52.530876],"type":"Point"}
}