{
  "type": "Feature",
  "properties": {
    "addr:full":"46 Macdonald Cres, Twechar Glasgow East Dunbartonshire G65 9SH",
    "addr:housenumber":"46",
    "addr:postcode":"g65 9sh",
    "addr:street":"Macdonald Cres Twechar",
    "iso:country":"GB",
    "sg:address":"46 Macdonald Cres, Twechar",
    "sg:city":"Glasgow",
    "sg:classifiers":[
        {
            "category":"Professional",
            "type":"Services"
        }
    ],
    "sg:phone":"+44 1236 823794",
    "sg:postcode":"G65 9SH",
    "sg:province":"East Dunbartonshire",
    "sg:tags":[
        "caterer"
    ],
    "wof:name":"Chelles Catering",
    "wof:placetype":"venue"
},
  "geometry": {"coordinates":[-4.0848379135,55.9510040283],"type":"Point"}
}