{
  "type": "Feature",
  "properties": {
    "addr:full":"100 Fonthill Road London Greater London N4 3AT",
    "addr:housenumber":"100",
    "addr:postcode":"n4 3at",
    "addr:street":"Fonthill Road",
    "iso:country":"GB",
    "sg:address":"100 Fonthill Road",
    "sg:city":"London",
    "sg:classifiers":[
        {
            "category":"Shopping",
            "subcategory":"Clothing, Apparel, & Fashions",
            "type":"Retail Goods"
        }
    ],
    "sg:phone":"+44 20 7272 2065",
    "sg:postcode":"N4 3AT",
    "sg:province":"Greater London",
    "sg:tags":[
        "clothing"
    ],
    "wof:name":"Magic",
    "wof:placetype":"venue"
},
  "geometry": {"coordinates":[-0.109499,51.56488],"type":"Point"}
}