{
  "type": "Feature",
  "properties": {
    "iso:country":"GB",
    "sg:address":"Cattle Farm, Cattle Carr, Misterton",
    "sg:city":"Doncaster",
    "sg:classifiers":[
        {
            "category":"Farming",
            "subcategory":"Farm",
            "type":"Manufacturing & Wholesale Goods"
        }
    ],
    "sg:phone":"+44 1427 890224",
    "sg:postcode":"DN10 4AX",
    "sg:province":"Lincolnshire",
    "sg:tags":[
        "mixed",
        "crop"
    ],
    "wof:name":"Stan White Farms",
    "wof:placetype":"venue"
},
  "geometry": {"coordinates":[-0.850294,53.444641],"type":"Point"}
}