{
  "type": "Feature",
  "properties": {
    "addr:full":"Suite1 Hayling Island Hampshire PO11 0NT",
    "addr:postcode":"po11 0nt",
    "iso:country":"GB",
    "sg:address":"Suite1",
    "sg:city":"Hayling Island",
    "sg:classifiers":[
        {
            "category":"Health Services",
            "subcategory":"Chiropractor",
            "type":"Services"
        }
    ],
    "sg:phone":"+44 23 9246 7645",
    "sg:postcode":"PO11 0NT",
    "sg:province":"Hampshire",
    "wof:name":"Hayling Island Chiropractic Clinic",
    "wof:placetype":"venue"
},
  "geometry": {"coordinates":[-0.979659,50.80069],"type":"Point"}
}