{
  "type": "Feature",
  "properties": {
    "addr:full":"55 Glasgow Road, Rutherglen Glasgow Glasgow City G73 1LJ",
    "addr:housenumber":"55",
    "addr:postcode":"g73 1lj",
    "addr:street":"Glasgow Road",
    "iso:country":"GB",
    "sg:address":"55 Glasgow Road, Rutherglen",
    "sg:city":"Glasgow",
    "sg:classifiers":[
        {
            "category":"Bars & Pubs",
            "type":"Food & Drink"
        }
    ],
    "sg:phone":"+44 131 557 5121",
    "sg:postcode":"G73 1LJ",
    "sg:province":"Glasgow City",
    "sg:tags":[
        "pubs",
        "inn"
    ],
    "wof:name":"The Black Bull",
    "wof:placetype":"venue"
},
  "geometry": {"coordinates":[-4.227869,55.838997],"type":"Point"}
}