{
  "type": "Feature",
  "properties": {
    "iso:country":"GB",
    "sg:address":"St John Street, Wainfleet",
    "sg:city":"Skegness",
    "sg:classifiers":[
        {
            "category":"Education",
            "subcategory":"Library",
            "type":"Public Place"
        },
        {
            "category":"Government",
            "subcategory":"Office",
            "type":"Public Place"
        }
    ],
    "sg:phone":"+44 1754 880418",
    "sg:postcode":"PE24 4DL",
    "sg:province":"Lincolnshire",
    "sg:tags":[
        "book",
        "local"
    ],
    "wof:name":"Wainfleet Library",
    "wof:placetype":"venue"
},
  "geometry": {"coordinates":[0.2377350032,53.1079063416],"type":"Point"}
}