{
  "type": "Feature",
  "properties": {
    "addr:full":"Coventry Rd Birmingham Warwickshire B46 3EE",
    "addr:postcode":"b46 3ee",
    "addr:street":"Coventry Rd",
    "iso:country":"GB",
    "sg:address":"Coventry Rd",
    "sg:city":"Birmingham",
    "sg:classifiers":[
        {
            "category":"Place Of Worship",
            "type":"Public Place"
        }
    ],
    "sg:phone":"+44 1675 463939",
    "sg:postcode":"B46 3EE",
    "sg:province":"Warwickshire",
    "wof:name":"Sacred Heart & St Teresa Coleshill Catholic Church",
    "wof:placetype":"venue"
},
  "geometry": {"coordinates":[-1.704989,52.49556],"type":"Point"}
}