{
  "type": "Feature",
  "properties": {
    "addr:full":"Club House, Virginia Park Caerphilly Caerphilly CF83 3JA",
    "addr:postcode":"cf83 3ja",
    "addr:street":"Club",
    "iso:country":"GB",
    "sg:address":"Club House, Virginia Park",
    "sg:city":"Caerphilly",
    "sg:classifiers":[
        {
            "category":"Arena",
            "subcategory":"Sports Club",
            "type":"Entertainment"
        }
    ],
    "sg:phone":"+44 29 2086 5077",
    "sg:postcode":"CF83 3JA",
    "sg:province":"Caerphilly",
    "wof:name":"Caerphilly Rugby Football Club",
    "wof:placetype":"venue"
},
  "geometry": {"coordinates":[-3.2188138962,51.582698822],"type":"Point"}
}