{
  "type": "Feature",
  "properties": {
    "iso:country":"GB",
    "sg:address":"43 The Uplands",
    "sg:city":"Smethwick",
    "sg:classifiers":[
        {
            "category":"Autos & Motor Vehicles",
            "subcategory":"Auto Supplies",
            "type":"Retail Goods"
        },
        {
            "category":"Shopping",
            "type":"Retail Goods"
        }
    ],
    "sg:postcode":"B67 6BY",
    "sg:province":"West Midlands",
    "sg:tags":[
        "car",
        "part",
        "accessory"
    ],
    "wof:name":"Autofit Car Spares & Accessories",
    "wof:placetype":"venue"
},
  "geometry": {"coordinates":[-1.9748409986,52.4885826111],"type":"Point"}
}