{
  "type": "Feature",
  "properties": {
    "addr:full":"39 High Street Bridgwater Somerset TA6 3BG",
    "addr:housenumber":"39",
    "addr:postcode":"ta6 3bg",
    "addr:street":"High Street",
    "iso:country":"GB",
    "sg:address":"39 High Street",
    "sg:city":"Bridgwater",
    "sg:classifiers":[
        {
            "category":"Arena",
            "subcategory":"Sports Club",
            "type":"Entertainment"
        }
    ],
    "sg:phone":"+44 1278 446922",
    "sg:postcode":"TA6 3BG",
    "sg:province":"Somerset",
    "wof:name":"BRIDGWATER TOWN FC LOTTERY",
    "wof:placetype":"venue"
},
  "geometry": {"coordinates":[-3.0054769516,51.1279449463],"type":"Point"}
}