{
  "type": "Feature",
  "properties": {
    "addr:full":"153 High Street, Gorleston Great Yarmouth Norfolk NR31 6RB",
    "addr:housenumber":"153",
    "addr:postcode":"nr31 6rb",
    "addr:street":"High Street",
    "iso:country":"GB",
    "sg:address":"153 High Street, Gorleston",
    "sg:city":"Great Yarmouth",
    "sg:classifiers":[
        {
            "category":"Real Estate",
            "subcategory":"Surveying",
            "type":"Services"
        },
        {
            "category":"Real Estate",
            "subcategory":"Real Estate Agent",
            "type":"Services"
        }
    ],
    "sg:phone":"+44 1493 441440",
    "sg:postcode":"NR31 6RB",
    "sg:province":"Norfolk",
    "sg:tags":[
        "surveyor",
        "valuer"
    ],
    "wof:name":"Ian Sinclair",
    "wof:placetype":"venue"
},
  "geometry": {"coordinates":[1.7279,52.579147],"type":"Point"}
}