{
  "type": "Feature",
  "properties": {
    "addr:full":"3 Woodseats Road Sheffield Derbyshire S8 0PD",
    "addr:housenumber":"3",
    "addr:postcode":"s8 0pd",
    "addr:street":"Woodseats Road",
    "iso:country":"GB",
    "sg:address":"3 Woodseats Road",
    "sg:city":"Sheffield",
    "sg:classifiers":[
        {
            "category":"Shopping",
            "subcategory":"Jewelry",
            "type":"Retail Goods"
        }
    ],
    "sg:phone":"+44 114 258 1777",
    "sg:postcode":"S8 0PD",
    "sg:province":"Derbyshire",
    "sg:tags":[
        "gold",
        "silversmith"
    ],
    "wof:name":"G P S Repair Services",
    "wof:placetype":"venue"
},
  "geometry": {"coordinates":[-1.4858939648,53.3526191711],"type":"Point"}
}