{
  "type": "Feature",
  "properties": {
    "addr:full":"32 Church Lane, West Parley Ferndown Dorset BH22 8TS",
    "addr:housenumber":"32",
    "addr:postcode":"bh22 8ts",
    "addr:street":"Church Lane West",
    "iso:country":"GB",
    "sg:address":"32 Church Lane, West Parley",
    "sg:city":"Ferndown",
    "sg:classifiers":[
        {
            "category":"Utilities",
            "type":"Services"
        }
    ],
    "sg:postcode":"BH22 8TS",
    "sg:province":"Dorset",
    "sg:tags":[
        "internet"
    ],
    "wof:name":"Harry's Computers",
    "wof:placetype":"venue"
},
  "geometry": {"coordinates":[-1.878439,50.776093],"type":"Point"}
}