{
  "type": "Feature",
  "properties": {
    "iso:country":"GB",
    "sg:address":"28 Oxford Place, Western Approach",
    "sg:city":"Plymouth",
    "sg:classifiers":[
        {
            "category":"Health Services",
            "subcategory":"Doctor",
            "type":"Services"
        }
    ],
    "sg:phone":"+44 1752 665805",
    "sg:postcode":"PL1 5AJ",
    "sg:province":"Devon",
    "sg:tags":[
        "practitioners"
    ],
    "wof:name":"Drs Walsh & Protheroe",
    "wof:placetype":"venue"
},
  "geometry": {"coordinates":[-4.144376,50.374458],"type":"Point"}
}