{
  "type": "Feature",
  "properties": {
    "iso:country":"GB",
    "sg:address":"166 Main Street, Barrhead",
    "sg:city":"Glasgow",
    "sg:classifiers":[
        {
            "category":"Shopping",
            "subcategory":"Florist",
            "type":"Retail Goods"
        }
    ],
    "sg:phone":"+44 141 881 2214",
    "sg:postcode":"G78 1SL",
    "sg:province":"East Ayrshire",
    "wof:name":"Arena",
    "wof:placetype":"venue"
},
  "geometry": {"coordinates":[-4.38908,55.800961],"type":"Point"}
}