{
  "type": "Feature",
  "properties": {
    "addr:full":"George Moore Court, Hedgecroft, Thornton Liverpool Merseyside L23 1ZD",
    "addr:postcode":"l23 1zd",
    "addr:street":"George Moore Court",
    "iso:country":"GB",
    "sg:address":"George Moore Court, Hedgecroft, Thornton",
    "sg:city":"Liverpool",
    "sg:classifiers":[
        {
            "category":"Social Services",
            "subcategory":"Adult Care",
            "type":"Services"
        },
        {
            "category":"Social Services",
            "subcategory":"Retirement Home",
            "type":"Services"
        }
    ],
    "sg:phone":"+44 151 924 4890",
    "sg:postcode":"L23 1ZD",
    "sg:province":"Merseyside",
    "sg:tags":[
        "accomodation",
        "housing",
        "sheltered"
    ],
    "wof:name":"LIVER HOUSING ASSOCIATION",
    "wof:placetype":"venue"
},
  "geometry": {"coordinates":[-2.9968540668,53.5002250671],"type":"Point"}
}