{
  "type": "Feature",
  "properties": {
    "addr:full":"281 Northolt Rd Harrow Greater London HA2 8HX",
    "addr:housenumber":"281",
    "addr:postcode":"ha2 8hx",
    "addr:street":"Northolt Rd",
    "iso:country":"GB",
    "sg:address":"281 Northolt Rd",
    "sg:city":"Harrow",
    "sg:classifiers":[
        {
            "category":"Shopping",
            "subcategory":"Thrift Store",
            "type":"Retail Goods"
        }
    ],
    "sg:phone":"+44 20 8426 4940",
    "sg:postcode":"HA2 8HX",
    "sg:province":"Greater London",
    "sg:tags":[
        "shop",
        "charity"
    ],
    "wof:name":"St. Lukes Hospice Charity Shop Area Office",
    "wof:placetype":"venue"
},
  "geometry": {"coordinates":[-0.3548409939,51.5633773804],"type":"Point"}
}