{
  "type": "Feature",
  "properties": {
    "iso:country":"GB",
    "sg:address":"6 Cobham Parade, Leeds Road",
    "sg:city":"Wakefield",
    "sg:classifiers":[
        {
            "category":"Retail",
            "subcategory":"Laundry & Dry Cleaning",
            "type":"Services"
        }
    ],
    "sg:phone":"+44 1924 826108",
    "sg:postcode":"WF1 2DY",
    "sg:province":"West Yorkshire",
    "sg:tags":[
        "launderette"
    ],
    "wof:name":"Bubbles Launderette",
    "wof:placetype":"venue"
},
  "geometry": {"coordinates":[-1.5016579628,53.7098846436],"type":"Point"}
}