{
  "type": "Feature",
  "properties": {
    "addr:full":"The Square, 1 Fife Street Turriff Aberdeenshire AB53 4DN",
    "addr:housenumber":"1",
    "addr:postcode":"ab53 4dn",
    "addr:street":"The;Fife Street",
    "iso:country":"GB",
    "sg:address":"The Square, 1 Fife Street",
    "sg:city":"Turriff",
    "sg:classifiers":[
        {
            "category":"Home & Garden",
            "subcategory":"Carpets & Floor Coverings",
            "type":"Retail Goods"
        }
    ],
    "sg:phone":"+44 1888 562383",
    "sg:postcode":"AB53 4DN",
    "sg:province":"Aberdeenshire",
    "sg:tags":[
        "carpets",
        "rug",
        "matting"
    ],
    "wof:name":"McDonalds",
    "wof:placetype":"venue"
},
  "geometry": {"coordinates":[-2.455229044,57.5399017334],"type":"Point"}
}