{
  "type": "Feature",
  "properties": {
    "addr:full":"Suite 9 2nd Floor, 73 Robertson Street Glasgow Glasgow City G2 8QD",
    "addr:housenumber":"suite 9 2nd floor 73",
    "addr:postcode":"g2 8qd",
    "addr:street":"Robertson Street",
    "iso:country":"GB",
    "sg:address":"Suite 9 2nd Floor, 73 Robertson Street",
    "sg:city":"Glasgow",
    "sg:classifiers":[
        {
            "category":"Professional",
            "subcategory":"Research",
            "type":"Services"
        }
    ],
    "sg:postcode":"G2 8QD",
    "sg:province":"Glasgow City",
    "sg:tags":[
        "analytical",
        "consulting",
        "chemist"
    ],
    "wof:name":"Nicolet Analytical",
    "wof:placetype":"venue"
},
  "geometry": {"coordinates":[-4.2613039017,55.8579330444],"type":"Point"}
}