{
  "type": "Feature",
  "properties": {
    "iso:country":"GB",
    "sg:address":"10 Market Place, Wolsingham",
    "sg:city":"Bishop Auckland",
    "sg:classifiers":[
        {
            "category":"Shopping",
            "subcategory":"Clothing, Apparel, & Fashions",
            "type":"Retail Goods"
        },
        {
            "category":"Shopping",
            "subcategory":"Comic Books",
            "type":"Retail Goods"
        }
    ],
    "sg:postcode":"DL13 3AF",
    "sg:province":"Durham",
    "sg:tags":[
        "jeweller",
        "dresswear"
    ],
    "wof:name":"Silver With Elegance",
    "wof:placetype":"venue"
},
  "geometry": {"coordinates":[-1.884623,54.730106],"type":"Point"}
}