{
  "type": "Feature",
  "properties": {
    "addr:full":"Tawney Street Boston Lincolnshire PE21 6RS",
    "addr:postcode":"pe21 6rs",
    "addr:street":"Tawney Street",
    "iso:country":"GB",
    "sg:address":"Tawney Street",
    "sg:city":"Boston",
    "sg:classifiers":[
        {
            "category":"Retail",
            "subcategory":"Auto Rental",
            "type":"Services"
        }
    ],
    "sg:phone":"+44 1205 354400",
    "sg:postcode":"PE21 6RS",
    "sg:province":"Lincolnshire",
    "sg:tags":[
        "car"
    ],
    "wof:name":"Hampsons (Self Drive Hire) Ltd.",
    "wof:placetype":"venue"
},
  "geometry": {"coordinates":[-0.022854,52.983082],"type":"Point"}
}