{
  "type": "Feature",
  "properties": {
    "iso:country":"GB",
    "sg:address":"1 Wellfield Road, Offerton",
    "sg:city":"Stockport",
    "sg:classifiers":[
        {
            "category":"Retail",
            "subcategory":"Laundry & Dry Cleaning",
            "type":"Services"
        }
    ],
    "sg:phone":"+44 161 483 4655",
    "sg:postcode":"SK2 6AS",
    "sg:province":"Cheshire",
    "sg:tags":[
        "alteration"
    ],
    "wof:name":"The Guild of Cleaners & Launderers",
    "wof:placetype":"venue"
},
  "geometry": {"coordinates":[-2.13302,53.395687],"type":"Point"}
}