{
  "type": "Feature",
  "properties": {
    "iso:country":"GB",
    "sg:address":"23 Croft Road",
    "sg:city":"Torquay",
    "sg:classifiers":[
        {
            "category":"Travel",
            "subcategory":"Hotels & Motels",
            "type":"Entertainment"
        }
    ],
    "sg:phone":"+44 1803 294844",
    "sg:postcode":"TQ2 5UD",
    "sg:province":"Devon",
    "wof:name":"Howden Court Hotel",
    "wof:placetype":"venue"
},
  "geometry": {"coordinates":[-3.5348260403,50.4661026001],"type":"Point"}
}