{
  "type": "Feature",
  "properties": {
    "iso:country":"GB",
    "sg:address":"334 Upper Parliament St",
    "sg:city":"Liverpool",
    "sg:classifiers":[
        {
            "category":"Health Services",
            "subcategory":"Doctor",
            "type":"Services"
        }
    ],
    "sg:phone":"+44 151 709 1263",
    "sg:postcode":"L8 7QL",
    "sg:province":"Merseyside",
    "sg:tags":[
        "practitioners"
    ],
    "wof:name":"Rao, V K",
    "wof:placetype":"venue"
},
  "geometry": {"coordinates":[-2.9501099586,53.398525238],"type":"Point"}
}