{
  "type": "Feature",
  "properties": {
    "iso:country":"GB",
    "sg:address":"727 London Road, West Thurrock",
    "sg:city":"Grays",
    "sg:classifiers":[
        {
            "category":"Food & Beverages",
            "subcategory":"Liquor & Beverages",
            "type":"Retail Goods"
        }
    ],
    "sg:postcode":"RM20 3HX",
    "sg:province":"Essex",
    "sg:tags":[
        "beer",
        "spirit",
        "wines"
    ],
    "wof:name":"Joginder Hundal",
    "wof:placetype":"venue"
},
  "geometry": {"coordinates":[0.2865499854,51.4804496765],"type":"Point"}
}