{
  "type": "Feature",
  "properties": {
    "addr:full":"Craiglands, Bryncethin Bridgend Bridgend CF32 9YT",
    "addr:postcode":"cf32 9yt",
    "addr:street":"Bridgend",
    "iso:country":"GB",
    "sg:address":"Craiglands, Bryncethin",
    "sg:city":"Bridgend",
    "sg:classifiers":[
        {
            "category":"Building & Trades",
            "subcategory":"Construction",
            "type":"Services"
        }
    ],
    "sg:phone":"+44 1656 729989",
    "sg:postcode":"CF32 9YT",
    "sg:province":"Bridgend",
    "sg:tags":[
        "equipment"
    ],
    "wof:name":"Kingfisher Hire & Sales Ltd.",
    "wof:placetype":"venue"
},
  "geometry": {"coordinates":[-3.5661160946,51.5472259521],"type":"Point"}
}