{
  "type": "Feature",
  "properties": {
    "iso:country":"GB",
    "sg:address":"Main Street, Upper Poppleton",
    "sg:city":"York",
    "sg:classifiers":[
        {
            "category":"Education",
            "subcategory":"School",
            "type":"Public Place"
        },
        {
            "category":"Government",
            "subcategory":"Office",
            "type":"Public Place"
        }
    ],
    "sg:phone":"+44 1904 794649",
    "sg:postcode":"YO26 6JT",
    "sg:province":"North Yorkshire",
    "sg:tags":[
        "local",
        "authority"
    ],
    "wof:name":"Upper Poppleton County Junior School",
    "wof:placetype":"venue"
},
  "geometry": {"coordinates":[-1.1477940083,53.9632110596],"type":"Point"}
}