{
  "type": "Feature",
  "properties": {
    "addr:full":"Dover Terrace Bath Bath and North East Somerset BA1 6PF",
    "addr:postcode":"ba1 6pf",
    "addr:street":"Dover Terrace",
    "iso:country":"GB",
    "sg:address":"Dover Terrace",
    "sg:city":"Bath",
    "sg:classifiers":[
        {
            "category":"Autos & Motor Vehicles",
            "subcategory":"Fuel & Gas Station",
            "type":"Retail Goods"
        }
    ],
    "sg:phone":"+44 1225 310013",
    "sg:postcode":"BA1 6PF",
    "sg:province":"Bath and North East Somerset",
    "sg:tags":[
        "hr",
        "petrol"
    ],
    "wof:name":"Walcot Service Station",
    "wof:placetype":"venue"
},
  "geometry": {"coordinates":[-2.354479,51.392757],"type":"Point"}
}