{
  "type": "Feature",
  "properties": {
    "addr:full":"Unit 1 Saxon Way, Battledown Industrial Estate Cheltenham Gloucestershire GL52 6QX",
    "addr:housenumber":"unit 1",
    "addr:postcode":"gl52 6qx",
    "addr:street":"Saxon Way;Industrial Estate",
    "iso:country":"GB",
    "sg:address":"Unit 1 Saxon Way, Battledown Industrial Estate",
    "sg:city":"Cheltenham",
    "sg:classifiers":[
        {
            "category":"Retail",
            "subcategory":"Auto Repair",
            "type":"Services"
        }
    ],
    "sg:phone":"+44 1242 545800",
    "sg:postcode":"GL52 6QX",
    "sg:province":"Gloucestershire",
    "sg:tags":[
        "body",
        "car"
    ],
    "wof:name":"Exclusive Repair Services",
    "wof:placetype":"venue"
},
  "geometry": {"coordinates":[-2.05866,51.895302],"type":"Point"}
}