{
  "type": "Feature",
  "properties": {
    "addr:full":"81 Portobello Rd Notting Hill Greater London W11 2QB",
    "addr:housenumber":"81",
    "addr:postcode":"w11 2qb",
    "addr:street":"Portobello Rd",
    "iso:country":"GB",
    "sg:address":"81 Portobello Rd",
    "sg:city":"Notting Hill",
    "sg:classifiers":[
        {
            "category":"Shopping",
            "subcategory":"Antiques",
            "type":"Retail Goods"
        }
    ],
    "sg:phone":"+44 20 7229 8130",
    "sg:postcode":"W11 2QB",
    "sg:province":"Greater London",
    "wof:name":"Judy Fox",
    "wof:placetype":"venue"
},
  "geometry": {"coordinates":[-0.2022739947,51.5126914978],"type":"Point"}
}