{
  "type": "Feature",
  "properties": {
    "iso:country":"GB",
    "sg:address":"216 Trinity Road",
    "sg:city":"London",
    "sg:classifiers":[
        {
            "category":"Restaurant",
            "type":"Food & Drink"
        }
    ],
    "sg:phone":"+44 20 8672 7740",
    "sg:postcode":"SW17 7HP",
    "sg:province":"Greater London",
    "sg:tags":[
        "indian"
    ],
    "wof:name":"Indian Ocean Restaurant",
    "wof:placetype":"venue"
},
  "geometry": {"coordinates":[-0.167374,51.443462],"type":"Point"}
}