{
  "type": "Feature",
  "properties": {
    "addr:full":"51 Marple Road, Ofreton Stockport Cheshire SK2 5EL",
    "addr:housenumber":"51",
    "addr:postcode":"sk2 5el",
    "addr:street":"Marple Road Ofreton",
    "iso:country":"GB",
    "sg:address":"51 Marple Road, Ofreton",
    "sg:city":"Stockport",
    "sg:classifiers":[
        {
            "category":"Retail",
            "subcategory":"Storage",
            "type":"Services"
        }
    ],
    "sg:postcode":"SK2 5EL",
    "sg:province":"Cheshire",
    "sg:tags":[
        "household",
        "removal"
    ],
    "wof:name":"A Houghton",
    "wof:placetype":"venue"
},
  "geometry": {"coordinates":[-2.126113,53.399982],"type":"Point"}
}