{
  "type": "Feature",
  "properties": {
    "iso:country":"GB",
    "sg:address":"1 Cemetery Road, Wombwell",
    "sg:city":"Barnsley",
    "sg:classifiers":[
        {
            "category":"Bus Charters",
            "type":"Transportation"
        }
    ],
    "sg:phone":"+44 1226 753903",
    "sg:postcode":"S73 8HZ",
    "sg:province":"South Yorkshire",
    "sg:tags":[
        "hire",
        "coach"
    ],
    "sg:website":"http://www.wombwellcoaches.com",
    "wof:name":"Wombwell Coaches Ltd",
    "wof:placetype":"venue"
},
  "geometry": {"coordinates":[-1.401398,53.524147],"type":"Point"}
}