{
  "type": "Feature",
  "properties": {
    "iso:country":"GB",
    "sg:address":"71 Clarendon Gardens",
    "sg:city":"Ilford",
    "sg:classifiers":[
        {
            "category":"Wholesale",
            "subcategory":"Meat",
            "type":"Manufacturing & Wholesale Goods"
        }
    ],
    "sg:phone":"+44 20 8518 5886",
    "sg:postcode":"IG1 3JW",
    "sg:province":"Essex",
    "sg:tags":[
        "-"
    ],
    "wof:name":"Kashmir Halal Meats",
    "wof:placetype":"venue"
},
  "geometry": {"coordinates":[0.059548,51.567917],"type":"Point"}
}