{
  "type": "Feature",
  "properties": {
    "addr:full":"Coate Water, Coate Swindon Wiltshire SN3 6AA",
    "addr:postcode":"sn3 6aa",
    "addr:street":"Swindon",
    "iso:country":"GB",
    "sg:address":"Coate Water, Coate",
    "sg:city":"Swindon",
    "sg:classifiers":[
        {
            "category":"Government",
            "subcategory":"Office",
            "type":"Public Place"
        },
        {
            "category":"Park",
            "type":"Public Place"
        },
        {
            "category":"Landmark",
            "subcategory":"Tourist Attraction",
            "type":"Public Place"
        }
    ],
    "sg:phone":"+44 1793 490150",
    "sg:postcode":"SN3 6AA",
    "sg:province":"Wiltshire",
    "sg:tags":[
        "local",
        "garden",
        "interest"
    ],
    "wof:name":"Coate Water Country Park",
    "wof:placetype":"venue"
},
  "geometry": {"coordinates":[-1.7373939753,51.5434761047],"type":"Point"}
}