{
  "type": "Feature",
  "properties": {
    "iso:country":"GB",
    "sg:address":"3 Culver St East",
    "sg:city":"Colchester",
    "sg:classifiers":[
        {
            "category":"Cafe",
            "type":"Food & Drink"
        }
    ],
    "sg:postcode":"CO1 1LD",
    "sg:province":"Essex",
    "sg:tags":[
        "tea",
        "room"
    ],
    "wof:name":"D'Arcy's",
    "wof:placetype":"venue"
},
  "geometry": {"coordinates":[0.90254,51.889107],"type":"Point"}
}