{
  "type": "Feature",
  "properties": {
    "iso:country":"GB",
    "sg:address":"28, Naworth Drive",
    "sg:city":"Carlisle",
    "sg:classifiers":[
        {
            "category":"Home & Garden",
            "subcategory":"Home Furnishings",
            "type":"Retail Goods"
        }
    ],
    "sg:phone":"+44 1228 598646",
    "sg:postcode":"CA3 0DD",
    "sg:province":"Cumbria",
    "sg:tags":[
        "blind",
        "curtain",
        "fitting"
    ],
    "wof:name":"C.S Blinds",
    "wof:placetype":"venue"
},
  "geometry": {"coordinates":[-2.948366,54.917828],"type":"Point"}
}