{
  "type": "Feature",
  "properties": {
    "addr:full":"26 King Street Hereford Herefordshire HR4 9BX",
    "addr:housenumber":"26",
    "addr:postcode":"hr4 9bx",
    "addr:street":"King Street",
    "iso:country":"GB",
    "sg:address":"26 King Street",
    "sg:city":"Hereford",
    "sg:classifiers":[
        {
            "category":"Real Estate",
            "subcategory":"Real Estate Agent",
            "type":"Services"
        }
    ],
    "sg:phone":"+44 1432 343777",
    "sg:postcode":"HR4 9BX",
    "sg:province":"Herefordshire",
    "wof:name":"Cross & James",
    "wof:placetype":"venue"
},
  "geometry": {"coordinates":[-2.717709,52.054577],"type":"Point"}
}