{
  "type": "Feature",
  "properties": {
    "iso:country":"GB",
    "sg:address":"Bobbins Mill, Tansley",
    "sg:city":"Matlock",
    "sg:classifiers":[
        {
            "category":"Manufacturing",
            "subcategory":"Metals",
            "type":"Manufacturing & Wholesale Goods"
        },
        {
            "category":"Wholesale",
            "subcategory":"Scrap",
            "type":"Manufacturing & Wholesale Goods"
        }
    ],
    "sg:phone":"+44 1629 55704",
    "sg:postcode":"DE4 5FQ",
    "sg:province":"Derbyshire",
    "sg:tags":[
        "waste"
    ],
    "wof:name":"Adrian Howard",
    "wof:placetype":"venue"
},
  "geometry": {"coordinates":[-1.518149,53.131901],"type":"Point"}
}