{
  "type": "Feature",
  "properties": {
    "iso:country":"GB",
    "sg:address":"Unit 3, Cherry Park Farm Industrial Estate, Cambridge Road",
    "sg:city":"Royston",
    "sg:classifiers":[
        {
            "category":"Manufacturing",
            "subcategory":"Signs",
            "type":"Manufacturing & Wholesale Goods"
        }
    ],
    "sg:phone":"+44 1763 262909",
    "sg:postcode":"SG8 6EY",
    "sg:province":"Bedfordshire",
    "sg:tags":[
        "writer"
    ],
    "wof:name":"Unlimited Logos",
    "wof:placetype":"venue"
},
  "geometry": {"coordinates":[-0.021984,52.04821],"type":"Point"}
}