{
  "type": "Feature",
  "properties": {
    "iso:country":"GB",
    "sg:address":"2 East End Lane, Wilden",
    "sg:city":"Bedford",
    "sg:classifiers":[
        {
            "category":"Professional",
            "subcategory":"Detective & Security Services",
            "type":"Services"
        }
    ],
    "sg:postcode":"MK44 2QN",
    "sg:province":"Bedfordshire",
    "sg:tags":[
        "alarm",
        "burglar",
        "system"
    ],
    "wof:name":"Argus Ltd.",
    "wof:placetype":"venue"
},
  "geometry": {"coordinates":[-0.3959189951,52.182598114],"type":"Point"}
}