{
  "type": "Feature",
  "properties": {
    "addr:full":"3 Riflemans Way Chepstow Gloucestershire NP16 5EJ",
    "addr:housenumber":"3",
    "addr:postcode":"np16 5ej",
    "addr:street":"Riflemans Way",
    "iso:country":"GB",
    "sg:address":"3 Riflemans Way",
    "sg:city":"Chepstow",
    "sg:classifiers":[
        {
            "category":"Recreation",
            "subcategory":"Dog Park",
            "type":"Entertainment"
        },
        {
            "category":"Retail",
            "subcategory":"Animal Services",
            "type":"Services"
        }
    ],
    "sg:phone":"+44 1291 629564",
    "sg:postcode":"NP16 5EJ",
    "sg:province":"Gloucestershire",
    "sg:tags":[
        "grooming",
        "clipping"
    ],
    "wof:name":"Clippets Canine Beauty Salon",
    "wof:placetype":"venue"
},
  "geometry": {"coordinates":[-2.6798119545,51.637878418],"type":"Point"}
}