{
  "type": "Feature",
  "properties": {
    "iso:country":"GB",
    "sg:address":"Clachan Cottage Hotel",
    "sg:city":"Lochearnhead",
    "sg:classifiers":[
        {
            "category":"Recreation",
            "subcategory":"Water Park",
            "type":"Entertainment"
        }
    ],
    "sg:phone":"+44 1567 830321",
    "sg:postcode":"FK19 8PU",
    "sg:province":"Stirling",
    "sg:tags":[
        "sport"
    ],
    "wof:name":"Z A K S Waterskiing",
    "wof:placetype":"venue"
},
  "geometry": {"coordinates":[-4.287324,56.385239],"type":"Point"}
}