{
  "type": "Feature",
  "properties": {
    "iso:country":"GB",
    "sg:address":"8 Albyn Terrace",
    "sg:city":"Aberdeen",
    "sg:classifiers":[
        {
            "category":"Professional",
            "subcategory":"Lawyer & Legal Services",
            "type":"Services"
        }
    ],
    "sg:phone":"+44 1224 622101",
    "sg:postcode":"AB10 1YP",
    "sg:province":"Aberdeen City",
    "sg:tags":[
        "solicitor"
    ],
    "wof:name":"Davies Wood Summers",
    "wof:placetype":"venue"
},
  "geometry": {"coordinates":[-2.1228,57.143307],"type":"Point"}
}