{
  "type": "Feature",
  "properties": {
    "iso:country":"GB",
    "sg:address":"3 Camden Place",
    "sg:city":"Preston",
    "sg:classifiers":[
        {
            "category":"Professional",
            "subcategory":"Art Services",
            "type":"Services"
        }
    ],
    "sg:phone":"+44 1772 822221",
    "sg:postcode":"PR1 3JL",
    "sg:province":"Lancashire",
    "sg:tags":[
        "graphic",
        "designer"
    ],
    "wof:name":"Rush of Blue Ltd.",
    "wof:placetype":"venue"
},
  "geometry": {"coordinates":[-2.701432,53.754864],"type":"Point"}
}