{
  "type": "Feature",
  "properties": {
    "iso:country":"GB",
    "sg:address":"Unit 26, Littlewood Lane, Hoveton",
    "sg:city":"Norwich",
    "sg:classifiers":[
        {
            "category":"Manufacturing",
            "subcategory":"Metals",
            "type":"Manufacturing & Wholesale Goods"
        },
        {
            "category":"Home & Garden",
            "subcategory":"Building Materials",
            "type":"Retail Goods"
        }
    ],
    "sg:phone":"+44 1603 781219",
    "sg:postcode":"NR12 8DZ",
    "sg:province":"Norfolk",
    "sg:tags":[
        "steel",
        "product",
        "production",
        "design",
        "iron",
        "erectors",
        "fabricator",
        "wrought"
    ],
    "wof:name":"Anvil Wrought Ironwork",
    "wof:placetype":"venue"
},
  "geometry": {"coordinates":[1.421127,52.71571],"type":"Point"}
}