{
  "type": "Feature",
  "properties": {
    "addr:full":"Normandy Ho, Nether St Alton Hampshire GU34 1EA",
    "addr:postcode":"gu34 1ea",
    "addr:street":"Nether St",
    "iso:country":"GB",
    "sg:address":"Normandy Ho, Nether St",
    "sg:city":"Alton",
    "sg:classifiers":[
        {
            "category":"Professional",
            "subcategory":"Computer Services",
            "type":"Services"
        }
    ],
    "sg:phone":"+44 1420 83811",
    "sg:postcode":"GU34 1EA",
    "sg:province":"Hampshire",
    "sg:tags":[
        "system",
        "software"
    ],
    "wof:name":"Bit (U K) Ltd",
    "wof:placetype":"venue"
},
  "geometry": {"coordinates":[-0.9703490138,51.1520690918],"type":"Point"}
}