{
  "type": "Feature",
  "properties": {
    "addr:full":"Brackendale, Furzehill Wimborne Dorset BH21 4HD",
    "addr:postcode":"bh21 4hd",
    "iso:country":"GB",
    "sg:address":"Brackendale, Furzehill",
    "sg:city":"Wimborne",
    "sg:classifiers":[
        {
            "category":"Utilities",
            "subcategory":"Fuel Oil & Lpg",
            "type":"Services"
        }
    ],
    "sg:phone":"+44 1202 887301",
    "sg:postcode":"BH21 4HD",
    "sg:province":"Dorset",
    "sg:tags":[
        "supplier",
        "peat",
        "firewood",
        "logs"
    ],
    "wof:name":"Furzehill Loggery",
    "wof:placetype":"venue"
},
  "geometry": {"coordinates":[-1.979794,50.818729],"type":"Point"}
}