{
  "type": "Feature",
  "properties": {
    "iso:country":"GB",
    "sg:address":"398 Ashton Road",
    "sg:city":"Oldham",
    "sg:classifiers":[
        {
            "category":"Shopping",
            "subcategory":"News",
            "type":"Retail Goods"
        }
    ],
    "sg:phone":"+44 161 624 2612",
    "sg:postcode":"OL8 3HF",
    "sg:province":"Lancashire",
    "sg:tags":[
        "newsagent"
    ],
    "wof:name":"A B C News",
    "wof:placetype":"venue"
},
  "geometry": {"coordinates":[-2.111247,53.525433],"type":"Point"}
}