{
  "type": "Feature",
  "properties": {
    "iso:country":"GB",
    "sg:address":"Roughwood Dr",
    "sg:city":"Liverpool",
    "sg:classifiers":[
        {
            "category":"Education",
            "subcategory":"University",
            "type":"Public Place"
        }
    ],
    "sg:phone":"+44 151 546 4394",
    "sg:postcode":"L33 8XF",
    "sg:province":"Lancashire",
    "sg:tags":[
        "adult"
    ],
    "wof:name":"Ruffwood Adult Education Centre",
    "wof:placetype":"venue"
},
  "geometry": {"coordinates":[-2.881306,53.486374],"type":"Point"}
}