{
  "type": "Feature",
  "properties": {
    "addr:full":"Ratho Hall, 51 Baird Road, Ratho Newbridge City of Edinburgh EH28 8QY",
    "addr:housenumber":"51",
    "addr:postcode":"eh28 8qy",
    "addr:street":"Baird Road",
    "iso:country":"GB",
    "sg:address":"Ratho Hall, 51 Baird Road, Ratho",
    "sg:city":"Newbridge",
    "sg:classifiers":[
        {
            "category":"Professional",
            "subcategory":"Accounting & Tax Preparation",
            "type":"Services"
        }
    ],
    "sg:phone":"+44 131 335 3333",
    "sg:postcode":"EH28 8QY",
    "sg:province":"City of Edinburgh",
    "sg:tags":[
        "accountant"
    ],
    "wof:name":"J & F Small",
    "wof:placetype":"venue"
},
  "geometry": {"coordinates":[-3.409335,55.940845],"type":"Point"}
}