{
  "type": "Feature",
  "properties": {
    "iso:country":"GB",
    "sg:address":"Danesmoor Drive",
    "sg:city":"Bury",
    "sg:classifiers":[
        {
            "category":"Education",
            "subcategory":"School",
            "type":"Public Place"
        },
        {
            "category":"Government",
            "subcategory":"Office",
            "type":"Public Place"
        }
    ],
    "sg:phone":"+44 161 764 3781",
    "sg:postcode":"BL9 6ER",
    "sg:province":"Lancashire",
    "sg:tags":[
        "local",
        "authority"
    ],
    "wof:name":"St Joseph's & St Bede's R C Primary School",
    "wof:placetype":"venue"
},
  "geometry": {"coordinates":[-2.281177,53.604103],"type":"Point"}
}