{
  "type": "Feature",
  "properties": {
    "iso:country":"GB",
    "sg:address":"37 Cranmer Avenue",
    "sg:city":"Hove",
    "sg:classifiers":[
        {
            "category":"Retail",
            "subcategory":"Repair Shop",
            "type":"Services"
        }
    ],
    "sg:phone":"+44 1273 773826",
    "sg:postcode":"BN3 7JP",
    "sg:province":"East Sussex",
    "sg:tags":[
        "upholsterer"
    ],
    "wof:name":"John Menzies",
    "wof:placetype":"venue"
},
  "geometry": {"coordinates":[-0.186165,50.839802],"type":"Point"}
}