{
  "type": "Feature",
  "properties": {
    "addr:full":"22a Mill Street Congleton Cheshire CW12 1AB",
    "addr:housenumber":"22a",
    "addr:postcode":"cw12 1ab",
    "addr:street":"Mill Street",
    "iso:country":"GB",
    "sg:address":"22a Mill Street",
    "sg:city":"Congleton",
    "sg:classifiers":[
        {
            "category":"Personal",
            "subcategory":"Beauty Salon",
            "type":"Services"
        }
    ],
    "sg:phone":"+44 1260 279082",
    "sg:postcode":"CW12 1AB",
    "sg:province":"Cheshire",
    "sg:tags":[
        "ladies",
        "lady",
        "hairdresser"
    ],
    "wof:name":"Margarets Hair Design",
    "wof:placetype":"venue"
},
  "geometry": {"coordinates":[-2.214346,53.164474],"type":"Point"}
}