{
  "type": "Feature",
  "properties": {
    "addr:full":"Torcoed Quarry, Porthyrhyd Carmarthen Carmarthenshire SA32 8PY",
    "addr:postcode":"sa32 8py",
    "addr:street":"Torcoed;Porthyrhyd;Carmarthenshire",
    "iso:country":"GB",
    "sg:address":"Torcoed Quarry, Porthyrhyd",
    "sg:city":"Carmarthen",
    "sg:classifiers":[
        {
            "category":"Manufacturing",
            "subcategory":"Glass & Minerals",
            "type":"Manufacturing & Wholesale Goods"
        }
    ],
    "sg:phone":"+44 1267 275261",
    "sg:postcode":"SA32 8PY",
    "sg:province":"Carmarthenshire",
    "sg:tags":[
        "chalk",
        "stone",
        "slate"
    ],
    "wof:name":"Tarmac Quarry Products Ltd",
    "wof:placetype":"venue"
},
  "geometry": {"coordinates":[-4.1488690376,51.821811676],"type":"Point"}
}