{
  "type": "Feature",
  "properties": {
    "iso:country":"GB",
    "sg:address":"89 Rosemary St",
    "sg:city":"Mansfield",
    "sg:classifiers":[
        {
            "category":"Shopping",
            "subcategory":"News",
            "type":"Retail Goods"
        }
    ],
    "sg:postcode":"NG18 1QY",
    "sg:province":"Nottinghamshire",
    "sg:tags":[
        "newsagent"
    ],
    "wof:name":"Maguires,T,",
    "wof:placetype":"venue"
},
  "geometry": {"coordinates":[-1.206393,53.147823],"type":"Point"}
}