{
  "type": "Feature",
  "properties": {
    "iso:country":"GB",
    "sg:address":"3 Three Tuns Court, King Street",
    "sg:city":"Norwich",
    "sg:classifiers":[
        {
            "category":"Professional",
            "subcategory":"Computer Services",
            "type":"Services"
        }
    ],
    "sg:postcode":"NR1 1XD",
    "sg:province":"Norfolk",
    "sg:tags":[
        "system",
        "software"
    ],
    "wof:name":"Replylast Ltd",
    "wof:placetype":"venue"
},
  "geometry": {"coordinates":[1.2948999405,52.6224937439],"type":"Point"}
}