{
  "type": "Feature",
  "properties": {
    "addr:full":"69 Glebe Gardens New Malden Surrey KT3 5RU",
    "addr:housenumber":"69",
    "addr:postcode":"kt3 5ru",
    "addr:street":"Glebe Gardens",
    "iso:country":"GB",
    "sg:address":"69 Glebe Gardens",
    "sg:city":"New Malden",
    "sg:classifiers":[
        {
            "category":"Building & Trades",
            "subcategory":"Construction",
            "type":"Services"
        }
    ],
    "sg:phone":"+44 20 8942 3931",
    "sg:postcode":"KT3 5RU",
    "sg:province":"Surrey",
    "sg:tags":[
        "dry",
        "plastering",
        "plasterers",
        "lining",
        "related",
        "screeders"
    ],
    "wof:name":"Joe Staff",
    "wof:placetype":"venue"
},
  "geometry": {"coordinates":[-0.2574769855,51.3885955811],"type":"Point"}
}