{
  "type": "Feature",
  "properties": {
    "addr:full":"24 Meaford Road, Barlaston Stoke-on-trent Staffordshire ST12 9EB",
    "addr:postcode":"st12 9eb",
    "addr:street":"24 Meaford Road",
    "iso:country":"GB",
    "sg:address":"24 Meaford Road, Barlaston",
    "sg:city":"Stoke-on-trent",
    "sg:classifiers":[
        {
            "category":"Retail",
            "subcategory":"Driving School",
            "type":"Services"
        }
    ],
    "sg:postcode":"ST12 9EB",
    "sg:province":"Staffordshire",
    "wof:name":"A T N Driver Training",
    "wof:placetype":"venue"
},
  "geometry": {"coordinates":[-2.171088,52.9403],"type":"Point"}
}