{
  "type": "Feature",
  "properties": {
    "iso:country":"GB",
    "sg:address":"Grosvenor Road",
    "sg:city":"Llandrindod Wells",
    "sg:classifiers":[
        {
            "category":"Government",
            "subcategory":"Post Office",
            "type":"Public Place"
        }
    ],
    "sg:phone":"+44 1597 822626",
    "sg:postcode":"LD1 5NA",
    "sg:province":"Powys",
    "wof:name":"M W & S M Yeo",
    "wof:placetype":"venue"
},
  "geometry": {"coordinates":[-3.380114,52.234509],"type":"Point"}
}