{
  "type": "Feature",
  "properties": {
    "addr:full":"105 Chevening Road, Chipstead Sevenoaks Kent TN13 2SA",
    "addr:housenumber":"105",
    "addr:postcode":"tn13 2sa",
    "addr:street":"Chevening Road",
    "iso:country":"GB",
    "sg:address":"105 Chevening Road, Chipstead",
    "sg:city":"Sevenoaks",
    "sg:classifiers":[
        {
            "category":"Education",
            "subcategory":"Special Training",
            "type":"Public Place"
        }
    ],
    "sg:postcode":"TN13 2SA",
    "sg:province":"Kent",
    "sg:tags":[
        "product",
        "centre"
    ],
    "wof:name":"C A T S International",
    "wof:placetype":"venue"
},
  "geometry": {"coordinates":[0.142718,51.290638],"type":"Point"}
}