{
  "type": "Feature",
  "properties": {
    "addr:full":"63 Whitehall Rd Halesowen West Midlands B63 3JS",
    "addr:housenumber":"63",
    "addr:postcode":"b63 3js",
    "addr:street":"Whitehall Rd",
    "iso:country":"GB",
    "sg:address":"63 Whitehall Rd",
    "sg:city":"Halesowen",
    "sg:classifiers":[
        {
            "category":"Government",
            "subcategory":"Post Office",
            "type":"Public Place"
        }
    ],
    "sg:phone":"+44 121 602 6771",
    "sg:postcode":"B63 3JS",
    "sg:province":"West Midlands",
    "sg:tags":[
        "messenger",
        "courier"
    ],
    "wof:name":"Mundon Light Freight",
    "wof:placetype":"venue"
},
  "geometry": {"coordinates":[-2.047319,52.452225],"type":"Point"}
}