{
  "type": "Feature",
  "properties": {
    "addr:full":"34 Buck Street Bradford West Yorkshire BD3 9QP",
    "addr:housenumber":"34",
    "addr:postcode":"bd3 9qp",
    "addr:street":"Buck Street",
    "iso:country":"GB",
    "sg:address":"34 Buck Street",
    "sg:city":"Bradford",
    "sg:classifiers":[
        {
            "category":"Autos & Motor Vehicles",
            "subcategory":"Fuel & Gas Station",
            "type":"Retail Goods"
        },
        {
            "category":"Wholesale",
            "subcategory":"Machinery & Supplies",
            "type":"Manufacturing & Wholesale Goods"
        }
    ],
    "sg:phone":"+44 1274 740200",
    "sg:postcode":"BD3 9QP",
    "sg:province":"West Yorkshire",
    "sg:tags":[
        "pump",
        "sale",
        "servicing"
    ],
    "wof:name":"A K Pumps",
    "wof:placetype":"venue"
},
  "geometry": {"coordinates":[-1.739705,53.791325],"type":"Point"}
}