{
  "type": "Feature",
  "properties": {
    "iso:country":"GB",
    "sg:address":"Keeston Hill",
    "sg:city":"Haverfordwest",
    "sg:classifiers":[
        {
            "category":"Restaurant",
            "type":"Food & Drink"
        }
    ],
    "sg:postcode":"SA62 6EJ",
    "sg:province":"Pembrokeshire",
    "wof:name":"Keeston Kitchen",
    "wof:placetype":"venue"
},
  "geometry": {"coordinates":[-5.056918,51.8311],"type":"Point"}
}