{
  "type": "Feature",
  "properties": {
    "addr:full":"345 Upper Street London Greater London N1 0PD",
    "addr:housenumber":"345",
    "addr:postcode":"n1 0pd",
    "addr:street":"Upper Street",
    "iso:country":"GB",
    "sg:address":"345 Upper Street",
    "sg:city":"London",
    "sg:classifiers":[
        {
            "category":"Home & Garden",
            "subcategory":"Furniture",
            "type":"Retail Goods"
        }
    ],
    "sg:phone":"+44 20 7226 4345",
    "sg:postcode":"N1 0PD",
    "sg:province":"Greater London",
    "sg:tags":[
        "outlet"
    ],
    "wof:name":"Artichoke",
    "wof:placetype":"venue"
},
  "geometry": {"coordinates":[-0.10448,51.534622],"type":"Point"}
}