{
  "type": "Feature",
  "properties": {
    "addr:full":"Homeleigh, Parsons Drove, Billinghay Lincoln Lincolnshire LN4 4BB",
    "addr:postcode":"ln4 4bb",
    "addr:street":"Drove",
    "iso:country":"GB",
    "sg:address":"Homeleigh, Parsons Drove, Billinghay",
    "sg:city":"Lincoln",
    "sg:classifiers":[
        {
            "category":"Banks & Credit Unions",
            "subcategory":"Investment Brokerage",
            "type":"Services"
        }
    ],
    "sg:phone":"+44 1526 860560",
    "sg:postcode":"LN4 4BB",
    "sg:province":"Lincolnshire",
    "sg:tags":[
        "contractor"
    ],
    "wof:name":"J E Stevenson",
    "wof:placetype":"venue"
},
  "geometry": {"coordinates":[-0.28111,53.079254],"type":"Point"}
}