{
  "type": "Feature",
  "properties": {
    "iso:country":"GB",
    "sg:address":"125 Huddersfield Road",
    "sg:city":"Barnsley",
    "sg:classifiers":[
        {
            "category":"Manufacturing",
            "subcategory":"Petroleum Products",
            "type":"Manufacturing & Wholesale Goods"
        }
    ],
    "sg:phone":"+44 1226 770333",
    "sg:postcode":"S75 1AH",
    "sg:province":"South Yorkshire",
    "sg:tags":[
        "double",
        "glazing"
    ],
    "wof:name":"Yorkshire Window Co. Ltd.",
    "wof:placetype":"venue"
},
  "geometry": {"coordinates":[-1.495619,53.564068],"type":"Point"}
}