{
  "type": "Feature",
  "properties": {
    "iso:country":"GB",
    "sg:address":"Kent Cottage Bridge Lane",
    "sg:city":"Kendal",
    "sg:classifiers":[
        {
            "category":"Real Estate",
            "subcategory":"Architect",
            "type":"Services"
        }
    ],
    "sg:phone":"+44 1539 727477",
    "sg:postcode":"LA9 7BX",
    "sg:province":"Cumbria",
    "wof:name":"Vis Williams Prichard Partnership",
    "wof:placetype":"venue"
},
  "geometry": {"coordinates":[-2.748084,54.324001],"type":"Point"}
}