{
  "type": "Feature",
  "properties": {
    "addr:full":"22-23 Queens Square Crawley Surrey RH10 1HA",
    "addr:housenumber":"22-23",
    "addr:postcode":"rh10 1ha",
    "addr:street":"Queens Square",
    "iso:country":"GB",
    "sg:address":"22-23 Queens Square",
    "sg:city":"Crawley",
    "sg:classifiers":[
        {
            "category":"Home & Garden",
            "subcategory":"Household Appliances",
            "type":"Retail Goods"
        }
    ],
    "sg:phone":"+44 1293 611414",
    "sg:postcode":"RH10 1HA",
    "sg:province":"Surrey",
    "sg:tags":[
        "electrical",
        "domestic"
    ],
    "wof:name":"Dixons",
    "wof:placetype":"venue"
},
  "geometry": {"coordinates":[-0.1868879944,51.1153907776],"type":"Point"}
}