{
  "type": "Feature",
  "properties": {
    "addr:full":"78 Linden Rd Bognor Regis West Sussex PO21 2AZ",
    "addr:housenumber":"78",
    "addr:postcode":"po21 2az",
    "addr:street":"Linden Rd",
    "iso:country":"GB",
    "sg:address":"78 Linden Rd",
    "sg:city":"Bognor Regis",
    "sg:classifiers":[
        {
            "category":"Autos & Motor Vehicles",
            "subcategory":"Motorcycle Sales",
            "type":"Retail Goods"
        }
    ],
    "sg:phone":"+44 1243 869184",
    "sg:postcode":"PO21 2AZ",
    "sg:province":"West Sussex",
    "sg:tags":[
        "chauffeur",
        "driven",
        "car"
    ],
    "wof:name":"Occasions",
    "wof:placetype":"venue"
},
  "geometry": {"coordinates":[-0.681479,50.789272],"type":"Point"}
}