{
  "type": "Feature",
  "properties": {
    "addr:full":"4 Elwyn Road Exmouth Devon EX8 2EL",
    "addr:housenumber":"4",
    "addr:postcode":"ex8 2el",
    "addr:street":"Elwyn Road",
    "iso:country":"GB",
    "sg:address":"4 Elwyn Road",
    "sg:city":"Exmouth",
    "sg:classifiers":[
        {
            "category":"Home & Garden",
            "subcategory":"Household Appliances",
            "type":"Retail Goods"
        }
    ],
    "sg:postcode":"EX8 2EL",
    "sg:province":"Devon",
    "sg:tags":[
        "electrical"
    ],
    "wof:name":"A T T Services",
    "wof:placetype":"venue"
},
  "geometry": {"coordinates":[-3.39498,50.620323],"type":"Point"}
}