{
  "type": "Feature",
  "properties": {
    "iso:country":"GB",
    "sg:address":"2 Ray Avenue",
    "sg:city":"Nantwich",
    "sg:classifiers":[
        {
            "category":"Professional",
            "subcategory":"Art Services",
            "type":"Services"
        }
    ],
    "sg:phone":"+44 1270 623984",
    "sg:postcode":"CW5 6HJ",
    "sg:province":"Cheshire",
    "sg:tags":[
        "graphic",
        "designer"
    ],
    "wof:name":"Designright",
    "wof:placetype":"venue"
},
  "geometry": {"coordinates":[-2.511881,53.076683],"type":"Point"}
}