{
  "type": "Feature",
  "properties": {
    "addr:full":"307 (snh) Bty Royal Artillery, Hucknall Lane, Bulwell Nottingham Nottinghamshire NG6 8AQ",
    "addr:housenumber":"307",
    "addr:postcode":"ng6 8aq",
    "addr:street":"Snh Bty Royal Artillery Hucknall Lane",
    "iso:country":"GB",
    "sg:address":"307 (snh) Bty Royal Artillery, Hucknall Lane, Bulwell",
    "sg:city":"Nottingham",
    "sg:classifiers":[
        {
            "category":"Government",
            "subcategory":"Office",
            "type":"Public Place"
        }
    ],
    "sg:phone":"+44 115 927 2251",
    "sg:postcode":"NG6 8AQ",
    "sg:province":"Nottinghamshire",
    "sg:tags":[
        "armed",
        "reserve"
    ],
    "wof:name":"Territorial Army",
    "wof:placetype":"venue"
},
  "geometry": {"coordinates":[-1.1981639862,53.0011940002],"type":"Point"}
}