{
  "type": "Feature",
  "properties": {
    "addr:full":"112 Albany Road Cardiff Cardiff CF24 3RU",
    "addr:housenumber":"112",
    "addr:postcode":"cf24 3ru",
    "addr:street":"Albany Road",
    "iso:country":"GB",
    "sg:address":"112 Albany Road",
    "sg:city":"Cardiff",
    "sg:classifiers":[
        {
            "category":"Real Estate",
            "subcategory":"Real Estate Operator",
            "type":"Services"
        }
    ],
    "sg:phone":"+44 29 2025 5370",
    "sg:postcode":"CF24 3RU",
    "sg:province":"Cardiff",
    "sg:tags":[
        "letting",
        "agent"
    ],
    "wof:name":"Globe Property Management",
    "wof:placetype":"venue"
},
  "geometry": {"coordinates":[-3.1648190022,51.494052887],"type":"Point"}
}