{
  "type": "Feature",
  "properties": {
    "addr:full":"Market Avenue Wickford Essex SS11 8TG",
    "addr:postcode":"ss11 8tg",
    "addr:street":"Market Avenue Wickford",
    "iso:country":"GB",
    "sg:address":"Market Avenue",
    "sg:city":"Wickford",
    "sg:classifiers":[
        {
            "category":"Social Services",
            "subcategory":"Adult Care",
            "type":"Services"
        },
        {
            "category":"Government",
            "subcategory":"Office",
            "type":"Public Place"
        }
    ],
    "sg:phone":"+44 1268 766570",
    "sg:postcode":"SS11 8TG",
    "sg:province":"Essex",
    "sg:tags":[
        "housing",
        "local",
        "sheltered"
    ],
    "wof:name":"Willow Court Sheltered Housing",
    "wof:placetype":"venue"
},
  "geometry": {"coordinates":[0.518050015,51.6151199341],"type":"Point"}
}