{
  "type": "Feature",
  "properties": {
    "iso:country":"GB",
    "sg:address":"19 Belle Vue Road",
    "sg:city":"Wakefield",
    "sg:classifiers":[
        {
            "category":"Professional",
            "subcategory":"Art Services",
            "type":"Services"
        }
    ],
    "sg:phone":"+44 1924 210140",
    "sg:postcode":"WF1 5NF",
    "sg:province":"West Yorkshire",
    "sg:tags":[
        "graphic",
        "designer"
    ],
    "wof:name":"The Communication Practice",
    "wof:placetype":"venue"
},
  "geometry": {"coordinates":[-1.481972,53.666069],"type":"Point"}
}