{
  "type": "Feature",
  "properties": {
    "addr:full":"The Old Bakery, Watling St,, Hockliffe, Leighton Buzzard Bedfordshire LU7 9LP",
    "addr:postcode":"lu7 9lp",
    "addr:street":"Watling St",
    "iso:country":"GB",
    "sg:address":"The Old Bakery, Watling St,, Hockliffe,",
    "sg:city":"Leighton Buzzard",
    "sg:classifiers":[
        {
            "category":"Shopping",
            "subcategory":"Department Store",
            "type":"Retail Goods"
        }
    ],
    "sg:postcode":"LU7 9LP",
    "sg:province":"Bedfordshire",
    "wof:name":"Pullums Sports",
    "wof:placetype":"venue"
},
  "geometry": {"coordinates":[-0.585949,51.932377],"type":"Point"}
}