{
  "type": "Feature",
  "properties": {
    "addr:full":"Westwaters Oakmere Durham Durham DH1 1TW",
    "addr:postcode":"dh1 1tw",
    "iso:country":"GB",
    "sg:address":"Westwaters Oakmere",
    "sg:city":"Durham",
    "sg:classifiers":[
        {
            "category":"Bars & Pubs",
            "type":"Food & Drink"
        }
    ],
    "sg:postcode":"DH1 1TW",
    "sg:province":"Durham",
    "sg:tags":[
        "pubs",
        "inn"
    ],
    "wof:name":"Norfolk Hotel Ltd.",
    "wof:placetype":"venue"
},
  "geometry": {"coordinates":[-1.5746079683,54.7775344849],"type":"Point"}
}