{
  "type": "Feature",
  "properties": {
    "iso:country":"GB",
    "sg:address":"1 Links Avenue, Little Sutton",
    "sg:city":"Ellesmere Port",
    "sg:classifiers":[
        {
            "category":"Professional",
            "subcategory":"Testing Lab",
            "type":"Services"
        },
        {
            "category":"Professional",
            "subcategory":"Engineering",
            "type":"Services"
        }
    ],
    "sg:postcode":"CH66 1QS",
    "sg:province":"Cheshire",
    "sg:tags":[
        "engineer",
        "inspection",
        "calibration"
    ],
    "wof:name":"Ultrascan Non - Destructive Testing Ltd.",
    "wof:placetype":"venue"
},
  "geometry": {"coordinates":[-2.9452240467,53.2891616821],"type":"Point"}
}