{
  "type": "Feature",
  "properties": {
    "iso:country":"GB",
    "sg:address":"41 Church Street, Gamlingay",
    "sg:city":"Sandy",
    "sg:classifiers":[
        {
            "category":"Building & Trades",
            "subcategory":"Construction",
            "type":"Services"
        }
    ],
    "sg:postcode":"SG19 3JJ",
    "sg:province":"Bedfordshire",
    "sg:tags":[
        "joiner",
        "carpenter"
    ],
    "wof:name":"R G Carpenter Joinery Contractors",
    "wof:placetype":"venue"
},
  "geometry": {"coordinates":[-0.189469,52.15538],"type":"Point"}
}