{
  "type": "Feature",
  "properties": {
    "addr:full":"5 Coopers Yard 7 Curran Rd Cardiff Cardiff CF1 5DF",
    "addr:housenumber":"5;7",
    "addr:postcode":"cf1 5df",
    "addr:street":"Coopers Yard;Curran Rd",
    "iso:country":"GB",
    "sg:address":"5 Coopers Yard 7 Curran Rd",
    "sg:city":"Cardiff",
    "sg:classifiers":[
        {
            "category":"Organizations",
            "subcategory":"Non-profit Organization",
            "type":"Services"
        }
    ],
    "sg:phone":"+44 29 2022 2282",
    "sg:postcode":"CF1 5DF",
    "sg:province":"Cardiff",
    "sg:tags":[
        "organisation",
        "voluntary",
        "charity"
    ],
    "wof:name":"Crossroads",
    "wof:placetype":"venue"
},
  "geometry": {"coordinates":[-3.180670023,51.4812583923],"type":"Point"}
}