{
  "type": "Feature",
  "properties": {
    "iso:country":"GB",
    "sg:address":"312 Seven Sisters Road, Finsbury Park",
    "sg:city":"London",
    "sg:classifiers":[
        {
            "category":"Banks & Credit Unions",
            "subcategory":"Bank",
            "type":"Services"
        }
    ],
    "sg:phone":"+44 845 604 0626",
    "sg:postcode":"N4 2AW",
    "sg:province":"Greater London",
    "wof:name":"Hsbc Bank Plc",
    "wof:placetype":"venue"
},
  "geometry": {"coordinates":[-0.103103,51.565517],"type":"Point"}
}