{
  "type": "Feature",
  "properties": {
    "iso:country":"GB",
    "sg:address":"Westmere Drive, Crewe Business Park",
    "sg:city":"Crewe",
    "sg:classifiers":[
        {
            "category":"Building & Trades",
            "subcategory":"Construction",
            "type":"Services"
        }
    ],
    "sg:postcode":"CW1 6ZD",
    "sg:province":"Cheshire",
    "sg:tags":[
        "valve"
    ],
    "wof:name":"Swagelok (U K )",
    "wof:placetype":"venue"
},
  "geometry": {"coordinates":[-2.421008,53.090652],"type":"Point"}
}