{
  "type": "Feature",
  "properties": {
    "iso:country":"GB",
    "sg:address":"13 Progress Business Centre, Whittle Park Way",
    "sg:city":"Slough",
    "sg:classifiers":[
        {
            "category":"Organizations",
            "subcategory":"Community Association",
            "type":"Services"
        }
    ],
    "sg:phone":"+44 1628 686918",
    "sg:postcode":"SL1 6DQ",
    "sg:province":"Berkshire",
    "sg:tags":[
        "relation",
        "public"
    ],
    "wof:name":"J B Pr",
    "wof:placetype":"venue"
},
  "geometry": {"coordinates":[-0.650409,51.522224],"type":"Point"}
}