{
  "type": "Feature",
  "properties": {
    "addr:full":"Unit 20-21 Warwick St Industrial Estate, Storforth Lane Chesterfield Derbyshire S40 2TT",
    "addr:housenumber":"unit 20-21;estate",
    "addr:postcode":"s40 2tt",
    "addr:street":"Warwick St Industrial;Storforth Lane",
    "iso:country":"GB",
    "sg:address":"Unit 20-21 Warwick St Industrial Estate, Storforth Lane",
    "sg:city":"Chesterfield",
    "sg:classifiers":[
        {
            "category":"Professional",
            "subcategory":"Art Services",
            "type":"Services"
        }
    ],
    "sg:phone":"+44 1246 209690",
    "sg:postcode":"S40 2TT",
    "sg:province":"Derbyshire",
    "sg:tags":[
        "framing"
    ],
    "wof:name":"The Real McCoy Picture Co",
    "wof:placetype":"venue"
},
  "geometry": {"coordinates":[-1.4244990349,53.2204055786],"type":"Point"}
}