{
  "type": "Feature",
  "properties": {
    "addr:full":"2 Barking Road London Greater London E6 3BP",
    "addr:housenumber":"2",
    "addr:postcode":"e6 3bp",
    "addr:street":"Barking Road",
    "iso:country":"GB",
    "sg:address":"2 Barking Road",
    "sg:city":"London",
    "sg:classifiers":[
        {
            "category":"Shopping",
            "subcategory":"Thrift Store",
            "type":"Retail Goods"
        }
    ],
    "sg:phone":"+44 20 8503 5035",
    "sg:postcode":"E6 3BP",
    "sg:province":"Greater London",
    "sg:tags":[
        "shop",
        "charity"
    ],
    "wof:name":"Family Welfare Association",
    "wof:placetype":"venue"
},
  "geometry": {"coordinates":[0.038262,51.530159],"type":"Point"}
}