{
  "type": "Feature",
  "properties": {
    "addr:full":"70 Priors Hill Swindon Wiltshire SN4 0RW",
    "addr:housenumber":"70",
    "addr:postcode":"sn4 0rw",
    "addr:street":"Priors Hill",
    "iso:country":"GB",
    "sg:address":"70 Priors Hill",
    "sg:city":"Swindon",
    "sg:classifiers":[
        {
            "category":"Retail",
            "subcategory":"Auto Repair",
            "type":"Services"
        }
    ],
    "sg:postcode":"SN4 0RW",
    "sg:province":"Wiltshire",
    "sg:tags":[
        "car",
        "upholsterer"
    ],
    "wof:name":"Covercraft",
    "wof:placetype":"venue"
},
  "geometry": {"coordinates":[-1.788528,51.519596],"type":"Point"}
}