{
  "type": "Feature",
  "properties": {
    "addr:full":"196 Napier Road Gillingham Kent ME7 4HJ",
    "addr:housenumber":"196",
    "addr:postcode":"me7 4hj",
    "addr:street":"Napier Road",
    "iso:country":"GB",
    "sg:address":"196 Napier Road",
    "sg:city":"Gillingham",
    "sg:classifiers":[
        {
            "category":"Cinema",
            "subcategory":"Movie Rental",
            "type":"Entertainment"
        }
    ],
    "sg:phone":"+44 1634 280053",
    "sg:postcode":"ME7 4HJ",
    "sg:province":"Kent",
    "sg:tags":[
        "video",
        "library"
    ],
    "wof:name":"Napier Videos & Off Licence",
    "wof:placetype":"venue"
},
  "geometry": {"coordinates":[0.552799,51.379833],"type":"Point"}
}