{
  "type": "Feature",
  "properties": {
    "iso:country":"GB",
    "sg:address":"Rose Cottage, Crackenthorpe",
    "sg:city":"Appleby-in-westmorland",
    "sg:classifiers":[
        {
            "category":"Building & Trades",
            "subcategory":"Construction",
            "type":"Services"
        }
    ],
    "sg:phone":"+44 17683 51954",
    "sg:postcode":"CA16 6AF",
    "sg:province":"Cumbria",
    "sg:tags":[
        "builder"
    ],
    "wof:name":"Douglas Hall",
    "wof:placetype":"venue"
},
  "geometry": {"coordinates":[-2.48743,54.577309],"type":"Point"}
}