{
  "type": "Feature",
  "properties": {
    "addr:full":"19 Bassett Terrace Llanelli Carmarthenshire SA15 4DU",
    "addr:housenumber":"19",
    "addr:postcode":"sa15 4du",
    "addr:street":"Bassett Terrace",
    "iso:country":"GB",
    "sg:address":"19 Bassett Terrace",
    "sg:city":"Llanelli",
    "sg:classifiers":[
        {
            "category":"Food & Beverages",
            "subcategory":"Groceries & Convenience Stores",
            "type":"Retail Goods"
        }
    ],
    "sg:phone":"+44 1554 757133",
    "sg:postcode":"SA15 4DU",
    "sg:province":"Carmarthenshire",
    "sg:website":"http://www.spar.co.uk",
    "wof:name":"Spar",
    "wof:placetype":"venue"
},
  "geometry": {"coordinates":[-4.1926870346,51.6861572266],"type":"Point"}
}