{
  "type": "Feature",
  "properties": {
    "addr:full":"3 Fitzmaurice Court, Rackheath Industrial Estate, Rackheath Norwich Norfolk NR13 6PY",
    "addr:housenumber":"3",
    "addr:postcode":"nr13 6py",
    "addr:street":"Fitzmaurice Court;Industrial",
    "iso:country":"GB",
    "sg:address":"3 Fitzmaurice Court, Rackheath Industrial Estate, Rackheath",
    "sg:city":"Norwich",
    "sg:classifiers":[
        {
            "category":"Building & Trades",
            "subcategory":"Construction",
            "type":"Services"
        }
    ],
    "sg:phone":"+44 1603 722222",
    "sg:postcode":"NR13 6PY",
    "sg:province":"Norfolk",
    "sg:tags":[
        "flooring"
    ],
    "wof:name":"Aston Home & Commercial",
    "wof:placetype":"venue"
},
  "geometry": {"coordinates":[1.3718730211,52.6734542847],"type":"Point"}
}