{
  "type": "Feature",
  "properties": {
    "iso:country":"GB",
    "sg:address":"32 Chaplet Avenue",
    "sg:city":"Glasgow",
    "sg:classifiers":[
        {
            "category":"Health Services",
            "subcategory":"Health Practitioner",
            "type":"Services"
        }
    ],
    "sg:postcode":"G13 3LX",
    "sg:province":"Glasgow City",
    "sg:tags":[
        "hypnotherapists"
    ],
    "wof:name":"L Buchan",
    "wof:placetype":"venue"
},
  "geometry": {"coordinates":[-4.347651,55.89571],"type":"Point"}
}