{
  "type": "Feature",
  "properties": {
    "addr:full":"The Elms, Whitstone Holsworthy Cornwall EX22 6TB",
    "addr:postcode":"ex22 6tb",
    "iso:country":"GB",
    "sg:address":"The Elms, Whitstone",
    "sg:city":"Holsworthy",
    "sg:classifiers":[
        {
            "category":"Retail",
            "subcategory":"Animal Services",
            "type":"Services"
        }
    ],
    "sg:phone":"+44 1409 261457",
    "sg:postcode":"EX22 6TB",
    "sg:province":"Cornwall",
    "sg:tags":[
        "carrier",
        "transportation"
    ],
    "wof:name":"STEVEN J SLUGGETT",
    "wof:placetype":"venue"
},
  "geometry": {"coordinates":[-4.3527340889,50.8100128174],"type":"Point"}
}