{
  "type": "Feature",
  "properties": {
    "addr:full":"38 Balham High Road London Greater London SW12 9AH",
    "addr:housenumber":"38",
    "addr:postcode":"sw12 9ah",
    "addr:street":"Balham High Road",
    "iso:country":"GB",
    "sg:address":"38 Balham High Road",
    "sg:city":"London",
    "sg:classifiers":[
        {
            "category":"Place Of Worship",
            "type":"Public Place"
        }
    ],
    "sg:phone":"+44 20 8767 7546",
    "sg:postcode":"SW12 9AH",
    "sg:province":"Greater London",
    "wof:name":"The Salvation Army",
    "wof:placetype":"venue"
},
  "geometry": {"coordinates":[-0.1488769948,51.4478340149],"type":"Point"}
}