{
  "type": "Feature",
  "properties": {
    "addr:full":"38a High Street, Long Eaton Nottingham Derbyshire NG10 1LN",
    "addr:housenumber":"38a",
    "addr:postcode":"ng10 1ln",
    "addr:street":"High Street",
    "iso:country":"GB",
    "sg:address":"38a High Street, Long Eaton",
    "sg:city":"Nottingham",
    "sg:classifiers":[
        {
            "category":"Shopping",
            "subcategory":"Clothing, Apparel, & Fashions",
            "type":"Retail Goods"
        }
    ],
    "sg:phone":"+44 115 946 2637",
    "sg:postcode":"NG10 1LN",
    "sg:province":"Derbyshire",
    "sg:tags":[
        "shop"
    ],
    "wof:name":"Peacocks Stores",
    "wof:placetype":"venue"
},
  "geometry": {"coordinates":[-1.269091,52.89687],"type":"Point"}
}