{
  "type": "Feature",
  "properties": {
    "addr:full":"Middlewich Road Crewe Cheshire CW4 7ES",
    "addr:postcode":"cw4 7es",
    "addr:street":"Middlewich Road",
    "iso:country":"GB",
    "sg:address":"Middlewich Road",
    "sg:city":"Crewe",
    "sg:classifiers":[
        {
            "category":"Autos & Motor Vehicles",
            "subcategory":"Fuel & Gas Station",
            "type":"Retail Goods"
        }
    ],
    "sg:phone":"+44 1477 536910",
    "sg:postcode":"CW4 7ES",
    "sg:province":"Cheshire",
    "sg:tags":[
        "petrol",
        "filling"
    ],
    "wof:name":"Croco Filling Station",
    "wof:placetype":"venue"
},
  "geometry": {"coordinates":[-2.3858520985,53.2007331848],"type":"Point"}
}