{
  "type": "Feature",
  "properties": {
    "addr:full":"Norwich Road Norwich Norfolk NR9 3DD",
    "addr:postcode":"nr9 3dd",
    "addr:street":"Norwich Road Norwich Norfolk",
    "iso:country":"GB",
    "sg:address":"Norwich Road",
    "sg:city":"Norwich",
    "sg:classifiers":[
        {
            "category":"Autos & Motor Vehicles",
            "subcategory":"Automobile Sales",
            "type":"Retail Goods"
        }
    ],
    "sg:phone":"+44 1603 810583",
    "sg:postcode":"NR9 3DD",
    "sg:province":"Norfolk",
    "sg:tags":[
        "car"
    ],
    "wof:name":"Hethersett Car Centre",
    "wof:placetype":"venue"
},
  "geometry": {"coordinates":[1.18457,52.598469],"type":"Point"}
}