{
  "type": "Feature",
  "properties": {
    "addr:full":"110 Uxbridge Road London Greater London W7 3SU",
    "addr:housenumber":"110",
    "addr:postcode":"w7 3su",
    "addr:street":"Uxbridge Road",
    "iso:country":"GB",
    "sg:address":"110 Uxbridge Road",
    "sg:city":"London",
    "sg:classifiers":[
        {
            "category":"Bars & Pubs",
            "type":"Food & Drink"
        }
    ],
    "sg:phone":"+44 20 8567 2370",
    "sg:postcode":"W7 3SU",
    "sg:province":"Greater London",
    "sg:tags":[
        "pubs",
        "inn"
    ],
    "wof:name":"The Kings Arms",
    "wof:placetype":"venue"
},
  "geometry": {"coordinates":[-0.337437,51.508575],"type":"Point"}
}