{
  "type": "Feature",
  "properties": {
    "addr:full":"Tamar View Industrial Estate Saltash Cornwall PL12 6LD",
    "addr:postcode":"pl12 6ld",
    "addr:street":"Tamar View Industrial Estate",
    "iso:country":"GB",
    "sg:address":"Tamar View Industrial Estate",
    "sg:city":"Saltash",
    "sg:classifiers":[
        {
            "category":"Professional",
            "type":"Services"
        }
    ],
    "sg:phone":"+44 1752 843423",
    "sg:postcode":"PL12 6LD",
    "sg:province":"Cornwall",
    "sg:tags":[
        "shopfitters"
    ],
    "wof:name":"John Richards (Shopfitters)",
    "wof:placetype":"venue"
},
  "geometry": {"coordinates":[-4.212884,50.408749],"type":"Point"}
}