{
  "type": "Feature",
  "properties": {
    "iso:country":"GB",
    "sg:address":"65 Bank Road",
    "sg:city":"Matlock",
    "sg:classifiers":[
        {
            "category":"Food & Beverages",
            "subcategory":"Bakery",
            "type":"Retail Goods"
        }
    ],
    "sg:phone":"+44 1629 580998",
    "sg:postcode":"DE4 3GL",
    "sg:province":"Derbyshire",
    "sg:tags":[
        "baker"
    ],
    "wof:name":"Cobs 'N' Cakes",
    "wof:placetype":"venue"
},
  "geometry": {"coordinates":[-1.55198,53.141247],"type":"Point"}
}