{
  "type": "Feature",
  "properties": {
    "addr:full":"The Pitts, Bonchurch Ventnor Isle of Wight PO38 1NT",
    "addr:postcode":"po38 1nt",
    "iso:country":"GB",
    "sg:address":"The Pitts, Bonchurch",
    "sg:city":"Ventnor",
    "sg:classifiers":[
        {
            "category":"Travel",
            "subcategory":"Hotels & Motels",
            "type":"Entertainment"
        }
    ],
    "sg:postcode":"PO38 1NT",
    "sg:province":"Isle of Wight",
    "sg:tags":[
        "self",
        "catering"
    ],
    "wof:name":"Ashcliff Holiday Apartments",
    "wof:placetype":"venue"
},
  "geometry": {"coordinates":[-1.200489,50.596527],"type":"Point"}
}