{
  "type": "Feature",
  "properties": {
    "iso:country":"GB",
    "sg:address":"The Leaside, Leverstock Grn",
    "sg:city":"Hemel Hempstead",
    "sg:classifiers":[
        {
            "category":"Retail",
            "subcategory":"Auto Repair",
            "type":"Services"
        }
    ],
    "sg:phone":"+44 1442 252413",
    "sg:postcode":"HP2 4PZ",
    "sg:province":"Hertfordshire",
    "sg:tags":[
        "modification",
        "garage"
    ],
    "wof:name":"Bestplan Services Ltd.",
    "wof:placetype":"venue"
},
  "geometry": {"coordinates":[-0.4316799939,51.7487792969],"type":"Point"}
}