{
  "type": "Feature",
  "properties": {
    "addr:full":"14 East Street Fareham Hampshire PO16 0BN",
    "addr:housenumber":"14",
    "addr:postcode":"po16 0bn",
    "addr:street":"East Street",
    "iso:country":"GB",
    "sg:address":"14 East Street",
    "sg:city":"Fareham",
    "sg:classifiers":[
        {
            "category":"Organizations",
            "subcategory":"Political Organization",
            "type":"Services"
        }
    ],
    "sg:phone":"+44 1329 822646",
    "sg:postcode":"PO16 0BN",
    "sg:province":"Hampshire",
    "sg:tags":[
        "party"
    ],
    "wof:name":"Fareham Conservative Association",
    "wof:placetype":"venue"
},
  "geometry": {"coordinates":[-1.1732369661,50.8521385193],"type":"Point"}
}