{
  "type": "Feature",
  "properties": {
    "addr:full":"Riverside Walks, Riverside Rd, Gorleston Great Yarmouth Norfolk NR31 6PX",
    "addr:postcode":"nr31 6px",
    "addr:street":"Walks Riverside Rd Gorleston Great Yarmouth",
    "iso:country":"GB",
    "sg:address":"Riverside Walks, Riverside Rd, Gorleston",
    "sg:city":"Great Yarmouth",
    "sg:classifiers":[
        {
            "category":"Wholesale",
            "subcategory":"Construction Materials",
            "type":"Manufacturing & Wholesale Goods"
        }
    ],
    "sg:postcode":"NR31 6PX",
    "sg:province":"Norfolk",
    "sg:tags":[
        "coating",
        "powder"
    ],
    "wof:name":"Shepherd,Lee,",
    "wof:placetype":"venue"
},
  "geometry": {"coordinates":[1.726515,52.569031],"type":"Point"}
}