{
  "type": "Feature",
  "properties": {
    "iso:country":"GB",
    "sg:address":"42 Long Street",
    "sg:city":"Tetbury",
    "sg:classifiers":[
        {
            "category":"Shopping",
            "subcategory":"Antiques",
            "type":"Retail Goods"
        }
    ],
    "sg:phone":"+44 1666 502687",
    "sg:postcode":"GL8 8AQ",
    "sg:province":"Gloucestershire",
    "wof:name":"Porch House Antiques",
    "wof:placetype":"venue"
},
  "geometry": {"coordinates":[-2.161561,51.638168],"type":"Point"}
}