{
  "type": "Feature",
  "properties": {
    "addr:full":"Brentwood Centre, Crescent Drive, Shenfield Brentwood Essex CM15 8DP",
    "addr:postcode":"cm15 8dp",
    "addr:street":"Centre Crescent Drive",
    "iso:country":"GB",
    "sg:address":"Brentwood Centre, Crescent Drive, Shenfield",
    "sg:city":"Brentwood",
    "sg:classifiers":[
        {
            "category":"Health Services",
            "subcategory":"Doctor",
            "type":"Services"
        },
        {
            "category":"Social Services",
            "subcategory":"Child Care",
            "type":"Services"
        }
    ],
    "sg:phone":"+44 1277 306000",
    "sg:postcode":"CM15 8DP",
    "sg:province":"Essex",
    "sg:tags":[
        "donor",
        "blood"
    ],
    "wof:name":"National Blood Service",
    "wof:placetype":"venue"
},
  "geometry": {"coordinates":[0.314372,51.623672],"type":"Point"}
}