{
  "type": "Feature",
  "properties": {
    "addr:full":"4-6 Halfway Street Sidcup Kent DA15 8LL",
    "addr:housenumber":"4-6",
    "addr:postcode":"da15 8ll",
    "addr:street":"Halfway Street",
    "iso:country":"GB",
    "sg:address":"4-6 Halfway Street",
    "sg:city":"Sidcup",
    "sg:classifiers":[
        {
            "category":"Retail",
            "subcategory":"Auto Repair",
            "type":"Services"
        }
    ],
    "sg:phone":"+44 20 8308 0579",
    "sg:postcode":"DA15 8LL",
    "sg:province":"Kent",
    "sg:tags":[
        "modification",
        "garage"
    ],
    "wof:name":"The Metro Centre",
    "wof:placetype":"venue"
},
  "geometry": {"coordinates":[0.1006309986,51.4366493225],"type":"Point"}
}