{
  "type": "Feature",
  "properties": {
    "addr:full":"10 Tentercroft St Ind Est Lincoln Lincolnshire LN5 7ED",
    "addr:housenumber":"10",
    "addr:postcode":"ln5 7ed",
    "addr:street":"Tentercroft St",
    "iso:country":"GB",
    "sg:address":"10 Tentercroft St Ind Est",
    "sg:city":"Lincoln",
    "sg:classifiers":[
        {
            "category":"Taxi",
            "type":"Transportation"
        }
    ],
    "sg:phone":"+44 1522 539222",
    "sg:postcode":"LN5 7ED",
    "sg:province":"Lincolnshire",
    "sg:tags":[
        "mini",
        "cab"
    ],
    "wof:name":"Swan Private Hire",
    "wof:placetype":"venue"
},
  "geometry": {"coordinates":[-0.541468,53.225494],"type":"Point"}
}