{
  "type": "Feature",
  "properties": {
    "addr:full":"13 Woodbridge Street London Greater London EC1R 0LL",
    "addr:housenumber":"13",
    "addr:postcode":"ec1r 0ll",
    "addr:street":"Woodbridge Street",
    "iso:country":"GB",
    "sg:address":"13 Woodbridge Street",
    "sg:city":"London",
    "sg:classifiers":[
        {
            "category":"Professional",
            "subcategory":"Lawyer & Legal Services",
            "type":"Services"
        }
    ],
    "sg:postcode":"EC1R 0LL",
    "sg:province":"Greater London",
    "sg:tags":[
        "solicitor"
    ],
    "wof:name":"Civis Project Management Plc",
    "wof:placetype":"venue"
},
  "geometry": {"coordinates":[-0.104721,51.524673],"type":"Point"}
}