{
  "type": "Feature",
  "properties": {
    "iso:country":"GB",
    "sg:address":"4 Fairfax View, Horsforth",
    "sg:city":"Leeds",
    "sg:classifiers":[
        {
            "category":"Banks & Credit Unions",
            "subcategory":"Financial Services",
            "type":"Services"
        }
    ],
    "sg:postcode":"LS18 5SZ",
    "sg:province":"West Yorkshire",
    "sg:tags":[
        "consultant"
    ],
    "wof:name":"Legrams Meeting Room Trust",
    "wof:placetype":"venue"
},
  "geometry": {"coordinates":[-1.6411019564,53.8540611267],"type":"Point"}
}