{
  "type": "Feature",
  "properties": {
    "addr:full":"202 Bishopsgate London Greater London EC2M 4NR",
    "addr:housenumber":"202",
    "addr:postcode":"ec2m 4nr",
    "addr:street":"Bishopsgate",
    "iso:country":"GB",
    "sg:address":"202 Bishopsgate",
    "sg:city":"London",
    "sg:classifiers":[
        {
            "category":"Food & Beverages",
            "subcategory":"Meat & Fish",
            "type":"Retail Goods"
        }
    ],
    "sg:phone":"+44 20 7283 1763",
    "sg:postcode":"EC2M 4NR",
    "sg:province":"Greater London",
    "sg:tags":[
        "seafood"
    ],
    "wof:name":"Bill Bentleys (Bishopsgate) Ltd.",
    "wof:placetype":"venue"
},
  "geometry": {"coordinates":[-0.0797810033,51.5181007385],"type":"Point"}
}