{
  "type": "Feature",
  "properties": {
    "iso:country":"GB",
    "sg:address":"420 Ashley Road, Parkstone",
    "sg:city":"Poole",
    "sg:classifiers":[
        {
            "category":"Shopping",
            "subcategory":"Books",
            "type":"Retail Goods"
        }
    ],
    "sg:postcode":"BH14 0AA",
    "sg:province":"Dorset",
    "sg:tags":[
        "bookseller"
    ],
    "wof:name":"D J Brooking",
    "wof:placetype":"venue"
},
  "geometry": {"coordinates":[-1.941069,50.729008],"type":"Point"}
}