{
  "type": "Feature",
  "properties": {
    "iso:country":"GB",
    "sg:address":"Green Sykes Road, Oakworth",
    "sg:city":"Keighley",
    "sg:classifiers":[
        {
            "category":"Farming",
            "subcategory":"Livestock Farm",
            "type":"Manufacturing & Wholesale Goods"
        }
    ],
    "sg:phone":"+44 1535 604332",
    "sg:postcode":"BD22 0PY",
    "sg:province":"North Yorkshire",
    "sg:tags":[
        "others"
    ],
    "wof:name":"George A Pickles",
    "wof:placetype":"venue"
},
  "geometry": {"coordinates":[-1.973307,53.873039],"type":"Point"}
}