{
  "type": "Feature",
  "properties": {
    "addr:full":"Brook Street Macclesfield Cheshire SK11 7AW",
    "addr:postcode":"sk11 7aw",
    "addr:street":"Brook Street",
    "iso:country":"GB",
    "sg:address":"Brook Street",
    "sg:city":"Macclesfield",
    "sg:classifiers":[
        {
            "category":"Recreation",
            "subcategory":"Boat Charter",
            "type":"Entertainment"
        }
    ],
    "sg:phone":"+44 1625 420042",
    "sg:postcode":"SK11 7AW",
    "sg:province":"Cheshire",
    "sg:tags":[
        "excursion"
    ],
    "wof:name":"Macclesfield Canal Centre Ltd.",
    "wof:placetype":"venue"
},
  "geometry": {"coordinates":[-2.1159451008,53.2572174072],"type":"Point"}
}