{
  "type": "Feature",
  "properties": {
    "iso:country":"GB",
    "sg:address":"90 Runwell Road",
    "sg:city":"Wickford",
    "sg:classifiers":[
        {
            "category":"Utilities",
            "subcategory":"Telephone",
            "type":"Services"
        }
    ],
    "sg:phone":"+44 1268 571123",
    "sg:postcode":"SS11 7HR",
    "sg:province":"Essex",
    "sg:tags":[
        "telecommunication"
    ],
    "wof:name":"Gemstone Communications",
    "wof:placetype":"venue"
},
  "geometry": {"coordinates":[0.529785,51.619129],"type":"Point"}
}