{
  "type": "Feature",
  "properties": {
    "addr:full":"6 Hampton Close Torquay Devon TQ1 4PS",
    "addr:housenumber":"6",
    "addr:postcode":"tq1 4ps",
    "addr:street":"Hampton Close",
    "iso:country":"GB",
    "sg:address":"6 Hampton Close",
    "sg:city":"Torquay",
    "sg:classifiers":[
        {
            "category":"Professional",
            "subcategory":"Art Services",
            "type":"Services"
        }
    ],
    "sg:phone":"+44 1803 326162",
    "sg:postcode":"TQ1 4PS",
    "sg:province":"Devon",
    "sg:tags":[
        "photographer"
    ],
    "wof:name":"Hot Shots",
    "wof:placetype":"venue"
},
  "geometry": {"coordinates":[-3.5226590633,50.4823951721],"type":"Point"}
}