{
  "type": "Feature",
  "properties": {
    "iso:country":"GB",
    "sg:address":"Bradford Road",
    "sg:city":"Huddersfield",
    "sg:classifiers":[
        {
            "category":"Bars & Pubs",
            "type":"Food & Drink"
        }
    ],
    "sg:phone":"+44 1484 420700",
    "sg:postcode":"HD2 2LL",
    "sg:province":"West Yorkshire",
    "sg:tags":[
        "pubs",
        "inn"
    ],
    "wof:name":"The Ashbrow",
    "wof:placetype":"venue"
},
  "geometry": {"coordinates":[-1.780182,53.667728],"type":"Point"}
}