{
  "type": "Feature",
  "properties": {
    "addr:full":"43 New St Plymouth Devon PL1 2ND",
    "addr:housenumber":"43",
    "addr:postcode":"pl1 2nd",
    "addr:street":"New St",
    "iso:country":"GB",
    "sg:address":"43 New St",
    "sg:city":"Plymouth",
    "sg:classifiers":[
        {
            "category":"Arts & Performance",
            "subcategory":"Art Gallery",
            "type":"Entertainment"
        }
    ],
    "sg:phone":"+44 1752 224692",
    "sg:postcode":"PL1 2ND",
    "sg:province":"Devon",
    "wof:name":"West Devon Gallery",
    "wof:placetype":"venue"
},
  "geometry": {"coordinates":[-4.143839,50.368351],"type":"Point"}
}