{
  "type": "Feature",
  "properties": {
    "addr:full":"49 Main Street, Cambuslang Glasgow South Lanarkshire G72 7HB",
    "addr:housenumber":"49",
    "addr:postcode":"g72 7hb",
    "addr:street":"Main Street",
    "iso:country":"GB",
    "sg:address":"49 Main Street, Cambuslang",
    "sg:city":"Glasgow",
    "sg:classifiers":[
        {
            "category":"Shopping",
            "subcategory":"Crafts & Fabrics",
            "type":"Retail Goods"
        }
    ],
    "sg:postcode":"G72 7HB",
    "sg:province":"South Lanarkshire",
    "sg:tags":[
        "shop",
        "needlecraft",
        "wool"
    ],
    "wof:name":"Cable Stitch Wool Shop",
    "wof:placetype":"venue"
},
  "geometry": {"coordinates":[-4.168525219,55.8194122314],"type":"Point"}
}