{
  "type": "Feature",
  "properties": {
    "addr:full":"120 High Street Herne Bay Kent CT6 5JY",
    "addr:housenumber":"120",
    "addr:postcode":"ct6 5jy",
    "addr:street":"High Street",
    "iso:country":"GB",
    "sg:address":"120 High Street",
    "sg:city":"Herne Bay",
    "sg:classifiers":[
        {
            "category":"Health Services",
            "subcategory":"Dentist",
            "type":"Services"
        }
    ],
    "sg:phone":"+44 1227 366984",
    "sg:postcode":"CT6 5JY",
    "sg:province":"Kent",
    "wof:name":"GEORGE D KEATING",
    "wof:placetype":"venue"
},
  "geometry": {"coordinates":[1.1272159815,51.3711509705],"type":"Point"}
}