{
  "type": "Feature",
  "properties": {
    "addr:full":"1-3 High Park Pl Southport Lancashire PR9 7QP",
    "addr:housenumber":"1-3",
    "addr:postcode":"pr9 7qp",
    "addr:street":"High Park Pl",
    "iso:country":"GB",
    "sg:address":"1-3 High Park Pl",
    "sg:city":"Southport",
    "sg:classifiers":[
        {
            "category":"Food & Beverages",
            "subcategory":"Groceries & Convenience Stores",
            "type":"Retail Goods"
        }
    ],
    "sg:postcode":"PR9 7QP",
    "sg:province":"Lancashire",
    "wof:name":"Hall,James,& Co (Southport) Ltd",
    "wof:placetype":"venue"
},
  "geometry": {"coordinates":[-2.96537,53.654129],"type":"Point"}
}