{
  "type": "Feature",
  "properties": {
    "iso:country":"GB",
    "sg:address":"12 Market Square",
    "sg:city":"Lytham St Annes",
    "sg:classifiers":[
        {
            "category":"Real Estate",
            "subcategory":"Surveying",
            "type":"Services"
        }
    ],
    "sg:phone":"+44 1253 795619",
    "sg:postcode":"FY8 5LW",
    "sg:province":"Lancashire",
    "sg:tags":[
        "surveyor",
        "valuer"
    ],
    "wof:name":"McDonald Surveyors & Valuers Ltd.",
    "wof:placetype":"venue"
},
  "geometry": {"coordinates":[-2.964763,53.737],"type":"Point"}
}