{
  "type": "Feature",
  "properties": {
    "iso:country":"GB",
    "sg:address":"99-101 Highcross Street",
    "sg:city":"Leicester",
    "sg:classifiers":[
        {
            "category":"Professional",
            "subcategory":"Employment Agencies",
            "type":"Services"
        }
    ],
    "sg:phone":"+44 116 262 2540",
    "sg:postcode":"LE1 4PH",
    "sg:province":"Leicestershire",
    "sg:tags":[
        "modelling"
    ],
    "wof:name":"Pat Keeling Model Agency",
    "wof:placetype":"venue"
},
  "geometry": {"coordinates":[-1.139896,52.637466],"type":"Point"}
}