{
  "type": "Feature",
  "properties": {
    "iso:country":"GB",
    "sg:address":"90 Main St, Fulford",
    "sg:city":"York",
    "sg:classifiers":[
        {
            "category":"Professional",
            "type":"Services"
        }
    ],
    "sg:postcode":"YO10 4PS",
    "sg:province":"North Yorkshire",
    "sg:tags":[
        "notary",
        "public"
    ],
    "wof:name":"Hey,Julian,",
    "wof:placetype":"venue"
},
  "geometry": {"coordinates":[-1.071421,53.934093],"type":"Point"}
}