{
  "type": "Feature",
  "properties": {
    "addr:full":"Danecourt, 14 St Peters Road Poole Dorset BH14 0PA",
    "addr:housenumber":"14",
    "addr:postcode":"bh14 0pa",
    "addr:street":"Danecourt;St Peters Road",
    "iso:country":"GB",
    "sg:address":"Danecourt, 14 St Peters Road",
    "sg:city":"Poole",
    "sg:classifiers":[
        {
            "category":"Health Services",
            "subcategory":"Nursing And Care Facility",
            "type":"Services"
        },
        {
            "category":"Organizations",
            "subcategory":"Community Association",
            "type":"Services"
        }
    ],
    "sg:phone":"+44 1202 722775",
    "sg:postcode":"BH14 0PA",
    "sg:province":"Dorset",
    "sg:tags":[
        "residential",
        "housing",
        "society"
    ],
    "wof:name":"ANCHOR TRUST",
    "wof:placetype":"venue"
},
  "geometry": {"coordinates":[-1.9545300007,50.7262382507],"type":"Point"}
}