{
  "type": "Feature",
  "properties": {
    "addr:full":"67 Victoria Ave Manchester Greater Manchester M9 0RD",
    "addr:housenumber":"67",
    "addr:postcode":"m9 0rd",
    "addr:street":"Victoria Ave",
    "iso:country":"GB",
    "sg:address":"67 Victoria Ave",
    "sg:city":"Manchester",
    "sg:classifiers":[
        {
            "category":"Shopping",
            "subcategory":"Antiques",
            "type":"Retail Goods"
        }
    ],
    "sg:postcode":"M9 0RD",
    "sg:province":"Greater Manchester",
    "wof:name":"B 2 Old",
    "wof:placetype":"venue"
},
  "geometry": {"coordinates":[-2.212916,53.533401],"type":"Point"}
}