{
  "type": "Feature",
  "properties": {
    "iso:country":"GB",
    "sg:address":"9 Star Lane",
    "sg:city":"Lymm",
    "sg:classifiers":[
        {
            "category":"Shopping",
            "subcategory":"Musical Instruments",
            "type":"Retail Goods"
        }
    ],
    "sg:phone":"+44 1925 755350",
    "sg:postcode":"WA13 9LE",
    "sg:province":"Cheshire",
    "wof:name":"Cheshire Pianos",
    "wof:placetype":"venue"
},
  "geometry": {"coordinates":[-2.494595,53.384579],"type":"Point"}
}