{
  "type": "Feature",
  "properties": {
    "iso:country":"GB",
    "sg:address":"29/30 Fitzroy Square",
    "sg:city":"London",
    "sg:classifiers":[
        {
            "category":"Building & Trades",
            "subcategory":"Construction",
            "type":"Services"
        }
    ],
    "sg:postcode":"W1T 6LQ",
    "sg:province":"Greater London",
    "sg:tags":[
        "builder"
    ],
    "wof:name":"Building Construction & Management (Uk)",
    "wof:placetype":"venue"
},
  "geometry": {"coordinates":[-0.1404519975,51.5226097107],"type":"Point"}
}