{
  "type": "Feature",
  "properties": {
    "iso:country":"GB",
    "sg:address":"Twin Mill, George Street",
    "sg:city":"Heywood",
    "sg:classifiers":[
        {
            "category":"Manufacturing",
            "subcategory":"Textiles",
            "type":"Manufacturing & Wholesale Goods"
        }
    ],
    "sg:phone":"+44 1706 360085",
    "sg:postcode":"OL10 2ED",
    "sg:province":"Lancashire",
    "sg:tags":[
        "made-up"
    ],
    "wof:name":"Collins Brothers (Heywood) Ltd.",
    "wof:placetype":"venue"
},
  "geometry": {"coordinates":[-2.21833,53.593521],"type":"Point"}
}