{
  "type": "Feature",
  "properties": {
    "addr:full":"914-916 Foleshill Road Coventry Warwickshire CV6 6GS",
    "addr:postcode":"914-916;cv6 6gs",
    "addr:street":"Foleshill Road",
    "iso:country":"GB",
    "sg:address":"914-916 Foleshill Road",
    "sg:city":"Coventry",
    "sg:classifiers":[
        {
            "category":"Shopping",
            "subcategory":"Computers & Home Electronics",
            "type":"Retail Goods"
        },
        {
            "category":"Communications",
            "type":"Services"
        }
    ],
    "sg:phone":"+44 24 7668 9208",
    "sg:postcode":"CV6 6GS",
    "sg:province":"Warwickshire",
    "sg:tags":[
        "tv",
        "radio",
        "television",
        "video",
        "sale"
    ],
    "wof:name":"T S R Television Sales & Rental",
    "wof:placetype":"venue"
},
  "geometry": {"coordinates":[-1.490802,52.44072],"type":"Point"}
}