{
  "type": "Feature",
  "properties": {
    "addr:full":"Unit 6a Strathspey Industrial Estate Grantown-on-spey Highland PH26 3JY",
    "addr:housenumber":"unit 6a",
    "addr:postcode":"ph26 3jy",
    "addr:street":"Strathspey Industrial Estate Grantown-On-Spey",
    "iso:country":"GB",
    "sg:address":"Unit 6a Strathspey Industrial Estate",
    "sg:city":"Grantown-on-spey",
    "sg:classifiers":[
        {
            "category":"Wholesale",
            "subcategory":"Meat",
            "type":"Manufacturing & Wholesale Goods"
        }
    ],
    "sg:phone":"+44 1479 873900",
    "sg:postcode":"PH26 3JY",
    "sg:province":"Highland",
    "sg:tags":[
        "product"
    ],
    "wof:name":"Quality Meats",
    "wof:placetype":"venue"
},
  "geometry": {"coordinates":[-3.606779,57.332001],"type":"Point"}
}