{
  "type": "Feature",
  "properties": {
    "addr:full":"21 Panton St London Greater London SW1Y 4DR",
    "addr:housenumber":"21",
    "addr:postcode":"sw1y 4dr",
    "addr:street":"Panton St",
    "iso:country":"GB",
    "sg:address":"21 Panton St",
    "sg:city":"London",
    "sg:classifiers":[
        {
            "category":"Travel",
            "subcategory":"Travel Agent",
            "type":"Entertainment"
        }
    ],
    "sg:postcode":"SW1Y 4DR",
    "sg:province":"Greater London",
    "wof:name":"Winge Travel Ltd",
    "wof:placetype":"venue"
},
  "geometry": {"coordinates":[-0.132034,51.509396],"type":"Point"}
}