{
  "type": "Feature",
  "properties": {
    "iso:country":"GB",
    "sg:address":"128 Drake St",
    "sg:city":"Rochdale",
    "sg:classifiers":[
        {
            "category":"Insurance",
            "subcategory":"Insurance Agent",
            "type":"Services"
        }
    ],
    "sg:phone":"+44 1706 648797",
    "sg:postcode":"OL16 1PN",
    "sg:province":"Lancashire",
    "wof:name":"Douglas Cronshaw",
    "wof:placetype":"venue"
},
  "geometry": {"coordinates":[-2.1544520855,53.6137313843],"type":"Point"}
}