{
  "type": "Feature",
  "properties": {
    "addr:full":"327a Cowbridge Road East Cardiff Cardiff CF5 1JD",
    "addr:housenumber":"327a",
    "addr:postcode":"cf5 1jd",
    "addr:street":"Cowbridge Road East",
    "iso:country":"GB",
    "sg:address":"327a Cowbridge Road East",
    "sg:city":"Cardiff",
    "sg:classifiers":[
        {
            "category":"Fast Food",
            "type":"Food & Drink"
        }
    ],
    "sg:phone":"+44 29 2022 8906",
    "sg:postcode":"CF5 1JD",
    "sg:province":"Cardiff",
    "sg:tags":[
        "away",
        "take"
    ],
    "wof:name":"Emma Joe's",
    "wof:placetype":"venue"
},
  "geometry": {"coordinates":[-3.2049911022,51.4818229675],"type":"Point"}
}