{
  "type": "Feature",
  "properties": {
    "iso:country":"GB",
    "sg:address":"Norvic Ho, 1-7 Hilton St",
    "sg:city":"Manchester",
    "sg:classifiers":[
        {
            "category":"Manufacturing",
            "subcategory":"Apparel",
            "type":"Manufacturing & Wholesale Goods"
        }
    ],
    "sg:phone":"+44 161 839 0333",
    "sg:postcode":"M4 1LP",
    "sg:province":"Greater Manchester",
    "sg:tags":[
        "shirt",
        "maker"
    ],
    "wof:name":"Intaglio Ltd",
    "wof:placetype":"venue"
},
  "geometry": {"coordinates":[-2.2349500656,53.4832611084],"type":"Point"}
}