{
  "type": "Feature",
  "properties": {
    "iso:country":"GB",
    "sg:address":"Wentworth House, Wentworth Street",
    "sg:city":"Peterborough",
    "sg:classifiers":[
        {
            "category":"Communications",
            "subcategory":"Newspaper",
            "type":"Services"
        }
    ],
    "sg:phone":"+44 1733 213960",
    "sg:postcode":"PE1 1DS",
    "sg:province":"Cambridgeshire",
    "sg:tags":[
        "magazine"
    ],
    "wof:name":"E M A P Plc",
    "wof:placetype":"venue"
},
  "geometry": {"coordinates":[-0.243574,52.57148],"type":"Point"}
}