{
  "type": "Feature",
  "properties": {
    "addr:full":"299 Greenford Road Greenford Greater London UB6 8RE",
    "addr:housenumber":"299",
    "addr:postcode":"ub6 8re",
    "addr:street":"Greenford Road",
    "iso:country":"GB",
    "sg:address":"299 Greenford Road",
    "sg:city":"Greenford",
    "sg:classifiers":[
        {
            "category":"Professional",
            "subcategory":"Lawyer & Legal Services",
            "type":"Services"
        }
    ],
    "sg:phone":"+44 20 8575 2191",
    "sg:postcode":"UB6 8RE",
    "sg:province":"Greater London",
    "sg:tags":[
        "conveyancing"
    ],
    "wof:name":"Conway & Co.",
    "wof:placetype":"venue"
},
  "geometry": {"coordinates":[-0.350397,51.531048],"type":"Point"}
}