{
  "type": "Feature",
  "properties": {
    "iso:country":"GB",
    "sg:address":"Unit 3oakwood Industrial Park",
    "sg:city":"Crawley",
    "sg:classifiers":[
        {
            "category":"Home & Garden",
            "subcategory":"Building Materials",
            "type":"Retail Goods"
        },
        {
            "category":"Home & Garden",
            "subcategory":"Hardware",
            "type":"Retail Goods"
        }
    ],
    "sg:phone":"+44 20 8302 4023",
    "sg:postcode":"RH10 9AZ",
    "sg:province":"Surrey",
    "sg:tags":[
        "shower",
        "equipment",
        "bathroom",
        "fitting",
        "unit"
    ],
    "wof:name":"The London Shower Co. Ltd.",
    "wof:placetype":"venue"
},
  "geometry": {"coordinates":[-0.184753,51.118458],"type":"Point"}
}