{
  "type": "Feature",
  "properties": {
    "addr:full":"Milton Farm, Milton, East Knoyle Salisbury Wiltshire SP3 6BG",
    "addr:housenumber":"milton;knoyle",
    "addr:postcode":"sp3 6bg",
    "addr:street":"East",
    "iso:country":"GB",
    "sg:address":"Milton Farm, Milton, East Knoyle",
    "sg:city":"Salisbury",
    "sg:classifiers":[
        {
            "category":"Farming",
            "subcategory":"Farm",
            "type":"Manufacturing & Wholesale Goods"
        }
    ],
    "sg:phone":"+44 1747 830247",
    "sg:postcode":"SP3 6BG",
    "sg:province":"Wiltshire",
    "sg:tags":[
        "mixed",
        "crop"
    ],
    "wof:name":"Hyde & Son",
    "wof:placetype":"venue"
},
  "geometry": {"coordinates":[-2.167996,51.077801],"type":"Point"}
}