{
  "type": "Feature",
  "properties": {
    "iso:country":"GB",
    "sg:address":"P O Box 920",
    "sg:city":"Oxford",
    "sg:classifiers":[
        {
            "category":"Professional",
            "type":"Services"
        }
    ],
    "sg:phone":"+44 1865 311914",
    "sg:postcode":"OX2 7YH",
    "sg:province":"Oxfordshire",
    "sg:tags":[
        "archaeologist"
    ],
    "wof:name":"Phoenix Consulting",
    "wof:placetype":"venue"
},
  "geometry": {"coordinates":[-1.2659,51.78056],"type":"Point"}
}