{
  "type": "Feature",
  "properties": {
    "iso:country":"GB",
    "sg:address":"13 The Chestnuts, Eaton Grange, Long Eaton",
    "sg:city":"Nottingham",
    "sg:classifiers":[
        {
            "category":"Real Estate",
            "subcategory":"Architect",
            "type":"Services"
        }
    ],
    "sg:phone":"+44 115 946 3041",
    "sg:postcode":"NG10 3QB",
    "sg:province":"Derbyshire",
    "wof:name":"Mining Technology Consultants & Associates",
    "wof:placetype":"venue"
},
  "geometry": {"coordinates":[-1.296231,52.897285],"type":"Point"}
}