{
  "type": "Feature",
  "properties": {
    "addr:full":"2nd Floor, 402 Holloway Road London Greater London N7 6PZ",
    "addr:housenumber":"2nd floor 402",
    "addr:postcode":"n7 6pz",
    "addr:street":"Holloway Road",
    "iso:country":"GB",
    "sg:address":"2nd Floor, 402 Holloway Road",
    "sg:city":"London",
    "sg:classifiers":[
        {
            "category":"Professional",
            "subcategory":"Lawyer & Legal Services",
            "type":"Services"
        }
    ],
    "sg:phone":"+44 20 7700 0265",
    "sg:postcode":"N7 6PZ",
    "sg:province":"Greater London",
    "sg:tags":[
        "solicitor"
    ],
    "wof:name":"Percy Short & Cuthbert",
    "wof:placetype":"venue"
},
  "geometry": {"coordinates":[-0.117791,51.556835],"type":"Point"}
}