{
  "type": "Feature",
  "properties": {
    "addr:full":"6 Seax Way Basildon Essex SS15 6SW",
    "addr:housenumber":"6",
    "addr:postcode":"ss15 6sw",
    "addr:street":"Seax Way",
    "iso:country":"GB",
    "sg:address":"6 Seax Way",
    "sg:city":"Basildon",
    "sg:classifiers":[
        {
            "category":"Professional",
            "subcategory":"Printing & Photocopies",
            "type":"Services"
        }
    ],
    "sg:phone":"+44 1268 413611",
    "sg:postcode":"SS15 6SW",
    "sg:province":"Essex",
    "sg:tags":[
        "printer"
    ],
    "wof:name":"Falder Matthews Ltd.",
    "wof:placetype":"venue"
},
  "geometry": {"coordinates":[0.4030520022,51.5782775879],"type":"Point"}
}