{
  "type": "Feature",
  "properties": {
    "addr:full":"P O Box 24 Monmouth Gloucestershire NP25 5YA",
    "addr:housenumber":"box 24",
    "addr:postcode":"np25 5ya",
    "addr:street":"P O",
    "iso:country":"GB",
    "sg:address":"P O Box 24",
    "sg:city":"Monmouth",
    "sg:classifiers":[
        {
            "category":"Recreation",
            "subcategory":"Fishing",
            "type":"Entertainment"
        }
    ],
    "sg:phone":"+44 1600 715457",
    "sg:postcode":"NP25 5YA",
    "sg:province":"Gloucestershire",
    "sg:tags":[
        "equipment",
        "angling"
    ],
    "wof:name":"Time Flies",
    "wof:placetype":"venue"
},
  "geometry": {"coordinates":[-2.7455921173,51.8249359131],"type":"Point"}
}