{
  "type": "Feature",
  "properties": {
    "addr:full":"Heatherdene, Newtown Common Newbury Berkshire RG20 9BE",
    "addr:postcode":"rg20 9be",
    "addr:street":"Heatherdene",
    "iso:country":"GB",
    "sg:address":"Heatherdene, Newtown Common",
    "sg:city":"Newbury",
    "sg:classifiers":[
        {
            "category":"Building & Trades",
            "subcategory":"Construction",
            "type":"Services"
        }
    ],
    "sg:phone":"+44 1635 30318",
    "sg:postcode":"RG20 9BE",
    "sg:province":"Berkshire",
    "sg:tags":[
        "joiner",
        "carpenter"
    ],
    "wof:name":"Bob Miles",
    "wof:placetype":"venue"
},
  "geometry": {"coordinates":[-1.326341033,51.3658828735],"type":"Point"}
}