{
  "type": "Feature",
  "properties": {
    "iso:country":"GB",
    "sg:address":"Oaktree Cottage, Hound Grn, Hook",
    "sg:city":"Basingstoke",
    "sg:classifiers":[
        {
            "category":"Professional",
            "subcategory":"Management & Consulting",
            "type":"Services"
        }
    ],
    "sg:postcode":"RG27 8LQ",
    "sg:province":"Berkshire",
    "sg:tags":[
        "consultant",
        "training"
    ],
    "wof:name":"Ei-Line Image Services",
    "wof:placetype":"venue"
},
  "geometry": {"coordinates":[-0.95441,51.327888],"type":"Point"}
}