{
  "type": "Feature",
  "properties": {
    "addr:full":"27 Paul Street London Greater London EC2A 4JU",
    "addr:housenumber":"27",
    "addr:postcode":"ec2a 4ju",
    "addr:street":"Paul Street",
    "iso:country":"GB",
    "sg:address":"27 Paul Street",
    "sg:city":"London",
    "sg:classifiers":[
        {
            "category":"Shopping",
            "subcategory":"Books",
            "type":"Retail Goods"
        }
    ],
    "sg:phone":"+44 20 7330 9000",
    "sg:postcode":"EC2A 4JU",
    "sg:province":"Greater London",
    "wof:name":"Cahners Travel Group",
    "wof:placetype":"venue"
},
  "geometry": {"coordinates":[-0.084582001,51.5228004456],"type":"Point"}
}