{
  "type": "Feature",
  "properties": {
    "iso:country":"GB",
    "sg:address":"North Road, South Kilworth",
    "sg:city":"Lutterworth",
    "sg:classifiers":[
        {
            "category":"Building & Trades",
            "subcategory":"Construction",
            "type":"Services"
        }
    ],
    "sg:postcode":"LE17 6DU",
    "sg:province":"Leicestershire",
    "sg:tags":[
        "builder"
    ],
    "wof:name":"Byrne Building Co. (Leicester) Ltd.",
    "wof:placetype":"venue"
},
  "geometry": {"coordinates":[-1.110774,52.432037],"type":"Point"}
}