{
  "type": "Feature",
  "properties": {
    "addr:full":"73 Claylands Road London Greater London SW8 1PJ",
    "addr:housenumber":"73",
    "addr:postcode":"sw8 1pj",
    "addr:street":"Claylands Road",
    "iso:country":"GB",
    "sg:address":"73 Claylands Road",
    "sg:city":"London",
    "sg:classifiers":[
        {
            "category":"Shopping",
            "subcategory":"Department Store",
            "type":"Retail Goods"
        },
        {
            "category":"Food & Beverages",
            "subcategory":"Groceries & Convenience Stores",
            "type":"Retail Goods"
        }
    ],
    "sg:phone":"+44 20 7582 2462",
    "sg:postcode":"SW8 1PJ",
    "sg:province":"Greater London",
    "wof:name":"Ashmole Stores",
    "wof:placetype":"venue"
},
  "geometry": {"coordinates":[-0.117101,51.481819],"type":"Point"}
}