{
  "type": "Feature",
  "properties": {
    "iso:country":"GB",
    "sg:address":"2-4 Bridge Street",
    "sg:city":"Driffield",
    "sg:classifiers":[
        {
            "category":"Retail",
            "subcategory":"Auto Repair",
            "type":"Services"
        }
    ],
    "sg:phone":"+44 1377 252526",
    "sg:postcode":"YO25 6DA",
    "sg:province":"East Riding of Yorkshire",
    "sg:tags":[
        "modification",
        "garage"
    ],
    "wof:name":"Brian Kitt (Motor Engineer)",
    "wof:placetype":"venue"
},
  "geometry": {"coordinates":[-0.4347499907,54.0046043396],"type":"Point"}
}