{
  "type": "Feature",
  "properties": {
    "addr:full":"Hallew Road St Austell Cornwall PL26 7YA",
    "addr:postcode":"pl26 7ya",
    "addr:street":"Hallew Road",
    "iso:country":"GB",
    "sg:address":"Hallew Road",
    "sg:city":"St Austell",
    "sg:classifiers":[
        {
            "category":"Retail",
            "subcategory":"Auto Repair",
            "type":"Services"
        }
    ],
    "sg:phone":"+44 1726 822326",
    "sg:postcode":"PL26 7YA",
    "sg:province":"Cornwall",
    "sg:tags":[
        "modification",
        "garage"
    ],
    "wof:name":"Nanpean Garage",
    "wof:placetype":"venue"
},
  "geometry": {"coordinates":[-4.871899128,50.3695487976],"type":"Point"}
}