{
  "type": "Feature",
  "properties": {
    "addr:full":"Fountain Ho, Broomgrove Rd Sheffield South Yorkshire S10 2LS",
    "addr:postcode":"s10 2ls",
    "addr:street":"Broomgrove Rd",
    "iso:country":"GB",
    "sg:address":"Fountain Ho, Broomgrove Rd",
    "sg:city":"Sheffield",
    "sg:classifiers":[
        {
            "category":"Professional",
            "subcategory":"Accounting & Tax Preparation",
            "type":"Services"
        }
    ],
    "sg:phone":"+44 114 266 4491",
    "sg:postcode":"S10 2LS",
    "sg:province":"South Yorkshire",
    "sg:tags":[
        "accountant"
    ],
    "wof:name":"John N Board",
    "wof:placetype":"venue"
},
  "geometry": {"coordinates":[-1.4949640036,53.3749961853],"type":"Point"}
}