{
  "type": "Feature",
  "properties": {
    "iso:country":"GB",
    "sg:address":"Unit 14 Lea Instl Park, Lea Road",
    "sg:city":"Ipswich",
    "sg:classifiers":[
        {
            "category":"Retail",
            "subcategory":"Storage",
            "type":"Services"
        }
    ],
    "sg:postcode":"IP5 1BU",
    "sg:province":"Suffolk",
    "sg:tags":[
        "household",
        "removal"
    ],
    "wof:name":"Dexion",
    "wof:placetype":"venue"
},
  "geometry": {"coordinates":[1.23231,52.0662],"type":"Point"}
}