{
  "type": "Feature",
  "properties": {
    "iso:country":"GB",
    "sg:address":"Rospeath Industrial Estate, Crowlas",
    "sg:city":"Penzance",
    "sg:classifiers":[
        {
            "category":"Freight",
            "type":"Transportation"
        }
    ],
    "sg:phone":"+44 1736 741100",
    "sg:postcode":"TR20 8DU",
    "sg:province":"Cornwall",
    "sg:tags":[
        "haulage",
        "road"
    ],
    "wof:name":"Newport Transport",
    "wof:placetype":"venue"
},
  "geometry": {"coordinates":[-5.479339,50.146053],"type":"Point"}
}