{
  "type": "Feature",
  "properties": {
    "addr:full":"22 Somerleyton Rd Brixton Greater London SW9 8ND",
    "addr:housenumber":"22",
    "addr:postcode":"sw9 8nd",
    "addr:street":"Somerleyton Rd",
    "iso:country":"GB",
    "sg:address":"22 Somerleyton Rd",
    "sg:city":"Brixton",
    "sg:classifiers":[
        {
            "category":"Wholesale",
            "subcategory":"Machinery & Supplies",
            "type":"Manufacturing & Wholesale Goods"
        }
    ],
    "sg:phone":"+44 20 7738 7372",
    "sg:postcode":"SW9 8ND",
    "sg:province":"Greater London",
    "sg:tags":[
        "theatrical"
    ],
    "wof:name":"M D M",
    "wof:placetype":"venue"
},
  "geometry": {"coordinates":[-0.1075399965,51.459072113],"type":"Point"}
}