{
  "type": "Feature",
  "properties": {
    "addr:full":"Unit 8, Water Line Estate, Malbis York North Yorkshire YO23 2UY",
    "addr:housenumber":"unit 8",
    "addr:postcode":"yo23 2uy",
    "addr:street":"Water Line Estate",
    "iso:country":"GB",
    "sg:address":"Unit 8, Water Line Estate, Malbis",
    "sg:city":"York",
    "sg:classifiers":[
        {
            "category":"Manufacturing",
            "subcategory":"Paper Products",
            "type":"Manufacturing & Wholesale Goods"
        }
    ],
    "sg:phone":"+44 1904 700500",
    "sg:postcode":"YO23 2UY",
    "sg:province":"North Yorkshire",
    "sg:tags":[
        "filter",
        "mnfrs",
        "supplier"
    ],
    "wof:name":"Tml International Ltd.",
    "wof:placetype":"venue"
},
  "geometry": {"coordinates":[-1.0834269524,53.953338623],"type":"Point"}
}