{
  "type": "Feature",
  "properties": {
    "iso:country":"GB",
    "sg:address":"Central Trading Estate, Gatehouse Road",
    "sg:city":"Aylesbury",
    "sg:classifiers":[
        {
            "category":"Home & Garden",
            "subcategory":"Home Furnishings",
            "type":"Retail Goods"
        },
        {
            "category":"Home & Garden",
            "subcategory":"Furniture",
            "type":"Retail Goods"
        }
    ],
    "sg:phone":"+44 1296 710200",
    "sg:postcode":"HP19 8EB",
    "sg:province":"Buckinghamshire",
    "sg:tags":[
        "homefurnishings"
    ],
    "wof:name":"Marco Manufacturing Ltd.",
    "wof:placetype":"venue"
},
  "geometry": {"coordinates":[-0.8245300055,51.8199996948],"type":"Point"}
}