{
  "type": "Feature",
  "properties": {
    "iso:country":"GB",
    "sg:address":"Cowdown Farm House, Cowdown Lane",
    "sg:city":"Andover",
    "sg:classifiers":[
        {
            "category":"Farming",
            "subcategory":"Nursery",
            "type":"Manufacturing & Wholesale Goods"
        }
    ],
    "sg:phone":"+44 1264 363098",
    "sg:postcode":"SP11 6LE",
    "sg:province":"Hampshire",
    "sg:tags":[
        "creche"
    ],
    "wof:name":"Cowdown Nursery Ltd.",
    "wof:placetype":"venue"
},
  "geometry": {"coordinates":[-1.448329,51.199181],"type":"Point"}
}