{
  "type": "Feature",
  "properties": {
    "iso:country":"GB",
    "sg:address":"Higher Menadew Farm, Bugle",
    "sg:city":"St Austell",
    "sg:classifiers":[
        {
            "category":"Farming",
            "subcategory":"Livestock Farm",
            "type":"Manufacturing & Wholesale Goods"
        }
    ],
    "sg:postcode":"PL26 8QW",
    "sg:province":"Cornwall",
    "sg:tags":[
        "others"
    ],
    "wof:name":"Andrew W J Higman",
    "wof:placetype":"venue"
},
  "geometry": {"coordinates":[-4.7929677963,50.3958358765],"type":"Point"}
}