{
  "type": "Feature",
  "properties": {
    "addr:full":"Saunders Close Kettering Northamptonshire NN16 0AP",
    "addr:postcode":"nn16 0ap",
    "addr:street":"Saunders Close",
    "iso:country":"GB",
    "sg:address":"Saunders Close",
    "sg:city":"Kettering",
    "sg:classifiers":[
        {
            "category":"Social Services",
            "subcategory":"Child Care",
            "type":"Services"
        },
        {
            "category":"Social Services",
            "subcategory":"Adult Care",
            "type":"Services"
        }
    ],
    "sg:phone":"+44 1536 410339",
    "sg:postcode":"NN16 0AP",
    "sg:province":"Northamptonshire",
    "sg:tags":[
        "day",
        "centre"
    ],
    "wof:name":"Henley Day Centre",
    "wof:placetype":"venue"
},
  "geometry": {"coordinates":[-0.730088,52.397053],"type":"Point"}
}