{
  "type": "Feature",
  "properties": {
    "addr:full":"17 Atherton Road, Hindley Wigan Lancashire WN2 3EA",
    "addr:housenumber":"17",
    "addr:postcode":"wn2 3ea",
    "addr:street":"Atherton Road",
    "iso:country":"GB",
    "sg:address":"17 Atherton Road, Hindley",
    "sg:city":"Wigan",
    "sg:classifiers":[
        {
            "category":"Personal",
            "subcategory":"Beauty Salon",
            "type":"Services"
        }
    ],
    "sg:phone":"+44 1942 257333",
    "sg:postcode":"WN2 3EA",
    "sg:province":"Lancashire",
    "sg:tags":[
        "unisex",
        "hairdresser"
    ],
    "wof:name":"Hair 17 by Sheila Lannon",
    "wof:placetype":"venue"
},
  "geometry": {"coordinates":[-2.580113,53.533257],"type":"Point"}
}