{
  "type": "Feature",
  "properties": {
    "iso:country":"GB",
    "sg:address":"14 Swain Street",
    "sg:city":"Watchet",
    "sg:classifiers":[
        {
            "category":"Health Services",
            "subcategory":"Dentist",
            "type":"Services"
        }
    ],
    "sg:phone":"+44 1984 631201",
    "sg:postcode":"TA23 0AB",
    "sg:province":"Somerset",
    "sg:tags":[
        "technician",
        "dental"
    ],
    "wof:name":"Dave & Mike Champion",
    "wof:placetype":"venue"
},
  "geometry": {"coordinates":[-3.330166,51.180557],"type":"Point"}
}