{
  "type": "Feature",
  "properties": {
    "iso:country":"GB",
    "sg:address":"57 Victoria Road",
    "sg:city":"Fleet",
    "sg:classifiers":[
        {
            "category":"Professional",
            "subcategory":"Printing & Photocopies",
            "type":"Services"
        }
    ],
    "sg:phone":"+44 1252 615949",
    "sg:postcode":"GU51 4DW",
    "sg:province":"Hampshire",
    "sg:tags":[
        "engraving"
    ],
    "wof:name":"Adabe Services",
    "wof:placetype":"venue"
},
  "geometry": {"coordinates":[-0.8469150066,51.2821273804],"type":"Point"}
}