{
  "type": "Feature",
  "properties": {
    "iso:country":"GB",
    "sg:address":"Sheridan Boathouse, Willow Court Lane",
    "sg:city":"Wallingford",
    "sg:classifiers":[
        {
            "category":"Wholesale",
            "subcategory":"Motor Vehicles",
            "type":"Manufacturing & Wholesale Goods"
        },
        {
            "category":"Autos & Motor Vehicles",
            "subcategory":"Boat Sales",
            "type":"Retail Goods"
        }
    ],
    "sg:phone":"+44 1491 652755",
    "sg:postcode":"OX10 9HU",
    "sg:province":"Oxfordshire",
    "sg:tags":[
        "repair",
        "builder",
        "turbine"
    ],
    "wof:name":"John Freeman (Sales) Ltd.",
    "wof:placetype":"venue"
},
  "geometry": {"coordinates":[-1.153429,51.57531],"type":"Point"}
}