{
  "type": "Feature",
  "properties": {
    "iso:country":"GB",
    "sg:address":"Beacon House, South Mimms Service Station",
    "sg:city":"Potters Bar",
    "sg:classifiers":[
        {
            "category":"Wholesale",
            "subcategory":"Scrap",
            "type":"Manufacturing & Wholesale Goods"
        }
    ],
    "sg:phone":"+44 1707 661321",
    "sg:postcode":"EN6 3NE",
    "sg:province":"Greater London",
    "sg:tags":[
        "salvage"
    ],
    "wof:name":"Cotman Auto Salvage",
    "wof:placetype":"venue"
},
  "geometry": {"coordinates":[-0.233206,51.696964],"type":"Point"}
}