{
  "type": "Feature",
  "properties": {
    "addr:full":"88a Stamford Hill Stoke Newington Greater London N16 6XS",
    "addr:housenumber":"88a",
    "addr:postcode":"n16 6xs",
    "addr:street":"Stamford Hill",
    "iso:country":"GB",
    "sg:address":"88a Stamford Hill",
    "sg:city":"Stoke Newington",
    "sg:classifiers":[
        {
            "category":"Utilities",
            "type":"Services"
        }
    ],
    "sg:phone":"+44 20 8806 5727",
    "sg:postcode":"N16 6XS",
    "sg:province":"Greater London",
    "sg:tags":[
        "internet"
    ],
    "wof:name":"Syntagram",
    "wof:placetype":"venue"
},
  "geometry": {"coordinates":[-0.072847,51.56683],"type":"Point"}
}