{
  "type": "Feature",
  "properties": {
    "addr:full":"Briars Lane Doncaster South Yorkshire DN7 5AZ",
    "addr:postcode":"dn7 5az",
    "addr:street":"Briars Lane",
    "iso:country":"GB",
    "sg:address":"Briars Lane",
    "sg:city":"Doncaster",
    "sg:classifiers":[
        {
            "category":"Retail",
            "subcategory":"Auto Repair",
            "type":"Services"
        }
    ],
    "sg:postcode":"DN7 5AZ",
    "sg:province":"South Yorkshire",
    "sg:tags":[
        "modification",
        "garage"
    ],
    "wof:name":"Doncaster Engineering Services",
    "wof:placetype":"venue"
},
  "geometry": {"coordinates":[-1.0262900591,53.6011734009],"type":"Point"}
}