{
  "type": "Feature",
  "properties": {
    "iso:country":"GB",
    "sg:address":"Bristol End, Portishead",
    "sg:city":"Bristol",
    "sg:classifiers":[
        {
            "category":"Arena",
            "subcategory":"Sports Club",
            "type":"Entertainment"
        }
    ],
    "sg:phone":"+44 1275 847136",
    "sg:postcode":"BS20 9PZ",
    "sg:province":"Somerset",
    "wof:name":"Portishead Football Club",
    "wof:placetype":"venue"
},
  "geometry": {"coordinates":[-2.76995,51.47366],"type":"Point"}
}