{
  "type": "Feature",
  "properties": {
    "addr:full":"57 Primrose Avenue Larkhall South Lanarkshire ML9 1JX",
    "addr:housenumber":"57",
    "addr:postcode":"ml9 1jx",
    "addr:street":"Primrose Avenue",
    "iso:country":"GB",
    "sg:address":"57 Primrose Avenue",
    "sg:city":"Larkhall",
    "sg:classifiers":[
        {
            "category":"Building & Trades",
            "subcategory":"Plumbing",
            "type":"Services"
        }
    ],
    "sg:postcode":"ML9 1JX",
    "sg:province":"South Lanarkshire",
    "sg:tags":[
        "heating"
    ],
    "wof:name":"Grainger,John B,",
    "wof:placetype":"venue"
},
  "geometry": {"coordinates":[-3.9746100903,55.7265167236],"type":"Point"}
}