{
  "type": "Feature",
  "properties": {
    "iso:country":"GB",
    "sg:address":"Van Hage Garden Company, Great Amwell",
    "sg:city":"Ware",
    "sg:classifiers":[
        {
            "category":"Building & Trades",
            "subcategory":"Construction",
            "type":"Services"
        }
    ],
    "sg:phone":"+44 1920 870191",
    "sg:postcode":"SG12 9RP",
    "sg:province":"Hertfordshire",
    "sg:tags":[
        "window",
        "replacement"
    ],
    "wof:name":"Anglian Home Improvements",
    "wof:placetype":"venue"
},
  "geometry": {"coordinates":[-0.017809,51.794022],"type":"Point"}
}