{
  "type": "Feature",
  "properties": {
    "iso:country":"GB",
    "sg:address":"Unit 5 Stour Road",
    "sg:city":"London",
    "sg:classifiers":[
        {
            "category":"Wholesale",
            "subcategory":"Scrap",
            "type":"Manufacturing & Wholesale Goods"
        }
    ],
    "sg:phone":"+44 20 7249 7273",
    "sg:postcode":"E3 2NT",
    "sg:province":"Greater London",
    "sg:tags":[
        "waste",
        "metal"
    ],
    "wof:name":"Silver Lining Industries Ltd.",
    "wof:placetype":"venue"
},
  "geometry": {"coordinates":[-0.0216589998,51.5395355225],"type":"Point"}
}