{
  "type": "Feature",
  "properties": {
    "iso:country":"GB",
    "sg:address":"Hedgerows, Orchard Road",
    "sg:city":"Orpington",
    "sg:classifiers":[
        {
            "category":"Building & Trades",
            "subcategory":"Construction",
            "type":"Services"
        }
    ],
    "sg:phone":"+44 1689 852020",
    "sg:postcode":"BR6 7NT",
    "sg:province":"Kent",
    "sg:tags":[
        "contractor",
        "pool",
        "swimming"
    ],
    "wof:name":"J S A Leisure Ltd.",
    "wof:placetype":"venue"
},
  "geometry": {"coordinates":[0.1010800004,51.3780403137],"type":"Point"}
}