{
  "type": "Feature",
  "properties": {
    "addr:full":"28 Babbacombe Drive Ferryhill Durham DL17 8DA",
    "addr:housenumber":"28",
    "addr:postcode":"dl17 8da",
    "addr:street":"Babbacombe Drive",
    "iso:country":"GB",
    "sg:address":"28 Babbacombe Drive",
    "sg:city":"Ferryhill",
    "sg:classifiers":[
        {
            "category":"Health Services",
            "subcategory":"Podiatrist",
            "type":"Services"
        }
    ],
    "sg:phone":"+44 1740 656855",
    "sg:postcode":"DL17 8DA",
    "sg:province":"Durham",
    "sg:tags":[
        "podiatrists",
        "chiropodist"
    ],
    "wof:name":"Paul Mountford",
    "wof:placetype":"venue"
},
  "geometry": {"coordinates":[-1.534783,54.68338],"type":"Point"}
}