{
  "type": "Feature",
  "properties": {
    "addr:full":"35 Milnes Avenue Leigh Lancashire WN7 3JU",
    "addr:housenumber":"35",
    "addr:postcode":"wn7 3ju",
    "addr:street":"Milnes Avenue",
    "iso:country":"GB",
    "sg:address":"35 Milnes Avenue",
    "sg:city":"Leigh",
    "sg:classifiers":[
        {
            "category":"Personal",
            "subcategory":"Hair Removal",
            "type":"Services"
        }
    ],
    "sg:postcode":"WN7 3JU",
    "sg:province":"Lancashire",
    "sg:tags":[
        "electrolysis"
    ],
    "wof:name":"Pennington Electroylsis & Beauty Clinic",
    "wof:placetype":"venue"
},
  "geometry": {"coordinates":[-2.518752,53.482742],"type":"Point"}
}