{
  "type": "Feature",
  "properties": {
    "addr:full":"302 Park Road, Toxteth Liverpool Merseyside L8 4QY",
    "addr:housenumber":"302",
    "addr:postcode":"l8 4qy",
    "addr:street":"Park Road",
    "iso:country":"GB",
    "sg:address":"302 Park Road, Toxteth",
    "sg:city":"Liverpool",
    "sg:classifiers":[
        {
            "category":"Cafe",
            "type":"Food & Drink"
        }
    ],
    "sg:postcode":"L8 4QY",
    "sg:province":"Merseyside",
    "sg:tags":[
        "tea",
        "room"
    ],
    "wof:name":"The Dingle Cafe",
    "wof:placetype":"venue"
},
  "geometry": {"coordinates":[-2.9624500275,53.3835105896],"type":"Point"}
}