{
  "type": "Feature",
  "properties": {
    "addr:full":"53 Queen Street Edinburgh City of Edinburgh EH2 3NS",
    "addr:housenumber":"53",
    "addr:postcode":"eh2 3ns",
    "addr:street":"Queen Street",
    "iso:country":"GB",
    "sg:address":"53 Queen Street",
    "sg:city":"Edinburgh",
    "sg:classifiers":[
        {
            "category":"Insurance",
            "subcategory":"Insurance Agent",
            "type":"Services"
        }
    ],
    "sg:phone":"+44 845 606 0708",
    "sg:postcode":"EH2 3NS",
    "sg:province":"City of Edinburgh",
    "wof:name":"Albany Life Assurance Co. Ltd.",
    "wof:placetype":"venue"
},
  "geometry": {"coordinates":[-3.203166,55.953953],"type":"Point"}
}