{
  "type": "Feature",
  "properties": {
    "addr:full":"26 Alexandra Rd Clevedon Somerset BS21 7QH",
    "addr:housenumber":"26",
    "addr:postcode":"bs21 7qh",
    "addr:street":"Alexandra Rd",
    "iso:country":"GB",
    "sg:address":"26 Alexandra Rd",
    "sg:city":"Clevedon",
    "sg:classifiers":[
        {
            "category":"Health Services",
            "subcategory":"Dentist",
            "type":"Services"
        }
    ],
    "sg:phone":"+44 1275 872001",
    "sg:postcode":"BS21 7QH",
    "sg:province":"Somerset",
    "sg:tags":[
        "technician",
        "dental"
    ],
    "wof:name":"L & D A Norris",
    "wof:placetype":"venue"
},
  "geometry": {"coordinates":[-2.858635,51.44186],"type":"Point"}
}