{
  "type": "Feature",
  "properties": {
    "iso:country":"GB",
    "sg:address":"Meadow Lane, Hartley Wintney",
    "sg:city":"Hook",
    "sg:classifiers":[
        {
            "category":"Personal",
            "subcategory":"Psychics & Astrologers",
            "type":"Services"
        }
    ],
    "sg:phone":"+44 1252 842982",
    "sg:postcode":"RG27 8RF",
    "sg:province":"Berkshire",
    "sg:tags":[
        "clairvoyant",
        "palmist"
    ],
    "wof:name":"S Thomas",
    "wof:placetype":"venue"
},
  "geometry": {"coordinates":[-0.9071000218,51.3052978516],"type":"Point"}
}