{
  "type": "Feature",
  "properties": {
    "iso:country":"GB",
    "sg:address":"63 Queen Elizabeth Avenue",
    "sg:city":"Walsall",
    "sg:classifiers":[
        {
            "category":"Shopping",
            "subcategory":"Florist",
            "type":"Retail Goods"
        }
    ],
    "sg:postcode":"WS2 0BD",
    "sg:province":"West Midlands",
    "wof:name":"The Flower Shop",
    "wof:placetype":"venue"
},
  "geometry": {"coordinates":[-2.02298,52.589149],"type":"Point"}
}