{
  "type": "Feature",
  "properties": {
    "addr:full":"1 Ash Farm, Alder Lane Widnes Cheshire WA8 5PY",
    "addr:housenumber":"1",
    "addr:postcode":"wa8 5py",
    "addr:street":"Ash Farm Alder Lane",
    "iso:country":"GB",
    "sg:address":"1 Ash Farm, Alder Lane",
    "sg:city":"Widnes",
    "sg:classifiers":[
        {
            "category":"Wholesale",
            "subcategory":"Machinery & Supplies",
            "type":"Manufacturing & Wholesale Goods"
        }
    ],
    "sg:phone":"+44 151 424 0044",
    "sg:postcode":"WA8 5PY",
    "sg:province":"Cheshire",
    "wof:name":"H L Tractors Ltd.",
    "wof:placetype":"venue"
},
  "geometry": {"coordinates":[-2.7332439423,53.3740310669],"type":"Point"}
}