{
  "type": "Feature",
  "properties": {
    "addr:full":"207 Park Road Blackpool Lancashire FY1 5LN",
    "addr:housenumber":"207",
    "addr:postcode":"fy1 5ln",
    "addr:street":"Park Road",
    "iso:country":"GB",
    "sg:address":"207 Park Road",
    "sg:city":"Blackpool",
    "sg:classifiers":[
        {
            "category":"Food & Beverages",
            "subcategory":"Meat & Fish",
            "type":"Retail Goods"
        },
        {
            "category":"Food & Beverages",
            "subcategory":"Groceries & Convenience Stores",
            "type":"Retail Goods"
        }
    ],
    "sg:phone":"+44 1253 761959",
    "sg:postcode":"FY1 5LN",
    "sg:province":"Lancashire",
    "sg:tags":[
        "shop",
        "chip"
    ],
    "wof:name":"The Pelican",
    "wof:placetype":"venue"
},
  "geometry": {"coordinates":[-3.0390479565,53.810005188],"type":"Point"}
}