{
  "type": "Feature",
  "properties": {
    "iso:country":"GB",
    "sg:address":"1 Shearer St Springfield Quay",
    "sg:city":"Glasgow",
    "sg:classifiers":[
        {
            "category":"Building & Trades",
            "subcategory":"Equipment Rental",
            "type":"Services"
        }
    ],
    "sg:phone":"+44 141 418 0800",
    "sg:postcode":"G5 8TA",
    "sg:province":"Glasgow City",
    "sg:tags":[
        "diver"
    ],
    "wof:name":"Dive Atlantis",
    "wof:placetype":"venue"
},
  "geometry": {"coordinates":[-4.2708702087,55.8547096252],"type":"Point"}
}