{
  "type": "Feature",
  "properties": {
    "addr:full":"43 Lune St Preston Lancashire PR1 2NN",
    "addr:housenumber":"43",
    "addr:postcode":"pr1 2nn",
    "addr:street":"Lune St",
    "iso:country":"GB",
    "sg:address":"43 Lune St",
    "sg:city":"Preston",
    "sg:classifiers":[
        {
            "category":"Organizations",
            "subcategory":"Community Association",
            "type":"Services"
        }
    ],
    "sg:phone":"+44 1772 253205",
    "sg:postcode":"PR1 2NN",
    "sg:province":"Lancashire",
    "sg:tags":[
        "relation",
        "public"
    ],
    "wof:name":"P.R One Communications",
    "wof:placetype":"venue"
},
  "geometry": {"coordinates":[-2.702808,53.758545],"type":"Point"}
}