{
  "type": "Feature",
  "properties": {
    "iso:country":"GB",
    "sg:address":"47 Cambridge Gardens",
    "sg:city":"Hastings",
    "sg:classifiers":[
        {
            "category":"Travel",
            "subcategory":"Hotels & Motels",
            "type":"Entertainment"
        }
    ],
    "sg:phone":"+44 1424 430080",
    "sg:postcode":"TN34 1EN",
    "sg:province":"East Sussex",
    "sg:tags":[
        "house",
        "guest"
    ],
    "wof:name":"Senlac Guest House",
    "wof:placetype":"venue"
},
  "geometry": {"coordinates":[0.576506,50.855778],"type":"Point"}
}