{
  "type": "Feature",
  "properties": {
    "iso:country":"GB",
    "sg:address":"53 York Road",
    "sg:city":"Tadcaster",
    "sg:classifiers":[
        {
            "category":"Health Services",
            "subcategory":"Podiatrist",
            "type":"Services"
        }
    ],
    "sg:postcode":"LS24 8AE",
    "sg:province":"North Yorkshire",
    "sg:tags":[
        "podiatrists",
        "chiropodist"
    ],
    "wof:name":"E S Helsdon",
    "wof:placetype":"venue"
},
  "geometry": {"coordinates":[-1.254279,53.887993],"type":"Point"}
}