{
  "type": "Feature",
  "properties": {
    "iso:country":"GB",
    "sg:address":"143 Roe La",
    "sg:city":"Southport",
    "sg:classifiers":[
        {
            "category":"Food & Beverages",
            "subcategory":"Fruits & Vegetables",
            "type":"Retail Goods"
        }
    ],
    "sg:postcode":"PR9 7PW",
    "sg:province":"Lancashire",
    "sg:tags":[
        "greengrocer"
    ],
    "wof:name":"Piles of Fruit",
    "wof:placetype":"venue"
},
  "geometry": {"coordinates":[-2.9658648968,53.6542739868],"type":"Point"}
}