{
  "type": "Feature",
  "properties": {
    "addr:full":"25 Back St Kyle Highland IV20 1XB",
    "addr:housenumber":"25",
    "addr:postcode":"iv20 1xb",
    "addr:street":"Back St",
    "iso:country":"GB",
    "sg:address":"25 Back St",
    "sg:city":"Kyle",
    "sg:classifiers":[
        {
            "category":"Building & Trades",
            "subcategory":"Construction",
            "type":"Services"
        }
    ],
    "sg:phone":"+44 7831 226762",
    "sg:postcode":"IV20 1XB",
    "sg:province":"Highland",
    "sg:tags":[
        "joiner",
        "carpenter"
    ],
    "wof:name":"Hugh Munro Services",
    "wof:placetype":"venue"
},
  "geometry": {"coordinates":[-3.901845932,57.7865104675],"type":"Point"}
}