{
  "type": "Feature",
  "properties": {
    "iso:country":"GB",
    "sg:address":"Unit 6 Steed Court Business Park, Waggon Lane, Upton",
    "sg:city":"Pontefract",
    "sg:classifiers":[
        {
            "category":"Sports & Exercise",
            "subcategory":"Gym",
            "type":"Entertainment"
        }
    ],
    "sg:phone":"+44 1977 642525",
    "sg:postcode":"WF9 1JJ",
    "sg:province":"West Yorkshire",
    "sg:tags":[
        "club",
        "fitness",
        "health",
        "centre"
    ],
    "wof:name":"Superflex Ultimate Fitness",
    "wof:placetype":"venue"
},
  "geometry": {"coordinates":[-1.285309,53.615166],"type":"Point"}
}