{
  "type": "Feature",
  "properties": {
    "addr:full":"68 Bassleton La Stockton On Tees Durham TS17 0LA",
    "addr:housenumber":"68",
    "addr:postcode":"ts17 0la",
    "addr:street":"Bassleton La Stockton On Tees",
    "iso:country":"GB",
    "sg:address":"68 Bassleton La",
    "sg:city":"Stockton On Tees",
    "sg:classifiers":[
        {
            "category":"Retail",
            "subcategory":"Driving School",
            "type":"Services"
        }
    ],
    "sg:phone":"+44 1642 761978",
    "sg:postcode":"TS17 0LA",
    "sg:province":"Durham",
    "wof:name":"Jack Elliott",
    "wof:placetype":"venue"
},
  "geometry": {"coordinates":[-1.309455,54.533936],"type":"Point"}
}