{
  "type": "Feature",
  "properties": {
    "iso:country":"GB",
    "sg:address":"Reading Road, Upton",
    "sg:city":"Didcot",
    "sg:classifiers":[
        {
            "category":"Bars & Pubs",
            "type":"Food & Drink"
        },
        {
            "category":"Community Center",
            "subcategory":"Social",
            "type":"Public Place"
        }
    ],
    "sg:phone":"+44 1235 850723",
    "sg:postcode":"OX11 9JJ",
    "sg:province":"Oxfordshire",
    "sg:tags":[
        "pubs",
        "house",
        "inn",
        "activity"
    ],
    "wof:name":"George & Dragon",
    "wof:placetype":"venue"
},
  "geometry": {"coordinates":[-1.263628,51.577641],"type":"Point"}
}