{
  "type": "Feature",
  "properties": {
    "addr:full":"169-173 Promenade Blackpool Lancashire FY1 5BQ",
    "addr:housenumber":"169-173",
    "addr:postcode":"fy1 5bq",
    "addr:street":"Promenade",
    "iso:country":"GB",
    "sg:address":"169-173 Promenade",
    "sg:city":"Blackpool",
    "sg:classifiers":[
        {
            "category":"Bars & Pubs",
            "type":"Food & Drink"
        }
    ],
    "sg:phone":"+44 1253 627090",
    "sg:postcode":"FY1 5BQ",
    "sg:province":"Lancashire",
    "sg:tags":[
        "pubs",
        "inn"
    ],
    "wof:name":"Gaietys",
    "wof:placetype":"venue"
},
  "geometry": {"coordinates":[-3.055438,53.809643],"type":"Point"}
}