{
  "type": "Feature",
  "properties": {
    "addr:full":"2 Wharncliffe Drive Bradford West Yorkshire BD2 3SX",
    "addr:housenumber":"2",
    "addr:postcode":"bd2 3sx",
    "addr:street":"Wharncliffe Drive",
    "iso:country":"GB",
    "sg:address":"2 Wharncliffe Drive",
    "sg:city":"Bradford",
    "sg:classifiers":[
        {
            "category":"Government",
            "subcategory":"Post Office",
            "type":"Public Place"
        }
    ],
    "sg:phone":"+44 1274 639926",
    "sg:postcode":"BD2 3SX",
    "sg:province":"West Yorkshire",
    "wof:name":"Wharncliffe Drive Post Office",
    "wof:placetype":"venue"
},
  "geometry": {"coordinates":[-1.715076,53.816689],"type":"Point"}
}