{
  "type": "Feature",
  "properties": {
    "iso:country":"GB",
    "sg:address":"High Street, Abersychan",
    "sg:city":"Pontypool",
    "sg:classifiers":[
        {
            "category":"Bars & Pubs",
            "type":"Food & Drink"
        }
    ],
    "sg:phone":"+44 1495 772649",
    "sg:postcode":"NP4 7AB",
    "sg:province":"Monmouthshire",
    "sg:tags":[
        "pubs",
        "inn"
    ],
    "wof:name":"The Old Castle Inn",
    "wof:placetype":"venue"
},
  "geometry": {"coordinates":[-3.060703,51.723824],"type":"Point"}
}