{
  "type": "Feature",
  "properties": {
    "iso:country":"GB",
    "sg:address":"71 Guntons Close, Soham",
    "sg:city":"Ely",
    "sg:classifiers":[
        {
            "category":"Autos & Motor Vehicles",
            "subcategory":"Motorcycle Sales",
            "type":"Retail Goods"
        }
    ],
    "sg:phone":"+44 1353 721516",
    "sg:postcode":"CB7 5DJ",
    "sg:province":"Cambridgeshire",
    "sg:tags":[
        "chauffeur",
        "driven",
        "car"
    ],
    "wof:name":"Elysian Chauffeur Services",
    "wof:placetype":"venue"
},
  "geometry": {"coordinates":[0.334683001,52.3368644714],"type":"Point"}
}