{
  "type": "Feature",
  "properties": {
    "addr:full":"Tanyard Lane Steyning West Sussex BN44 3RJ",
    "addr:postcode":"bn44 3rj",
    "addr:street":"Tanyard Lane",
    "iso:country":"GB",
    "sg:address":"Tanyard Lane",
    "sg:city":"Steyning",
    "sg:classifiers":[
        {
            "category":"Social Services",
            "subcategory":"Retirement Home",
            "type":"Services"
        }
    ],
    "sg:postcode":"BN44 3RJ",
    "sg:province":"West Sussex",
    "sg:tags":[
        "residential",
        "care"
    ],
    "wof:name":"Croft Meadow",
    "wof:placetype":"venue"
},
  "geometry": {"coordinates":[-0.3304559886,50.8905296326],"type":"Point"}
}