{
  "type": "Feature",
  "properties": {
    "addr:full":"617a Forest Road, Wlathamstow London Greater London E17 4NE",
    "addr:housenumber":"617a",
    "addr:postcode":"e17 4ne",
    "addr:street":"Forest Road",
    "iso:country":"GB",
    "sg:address":"617a Forest Road, Wlathamstow",
    "sg:city":"London",
    "sg:classifiers":[
        {
            "category":"Real Estate",
            "subcategory":"Real Estate Agent",
            "type":"Services"
        }
    ],
    "sg:phone":"+44 20 8523 1371",
    "sg:postcode":"E17 4NE",
    "sg:province":"Greater London",
    "wof:name":"Halifax Property Services",
    "wof:placetype":"venue"
},
  "geometry": {"coordinates":[-0.0165710002,51.5901603699],"type":"Point"}
}