{
  "type": "Feature",
  "properties": {
    "iso:country":"GB",
    "sg:address":"23 Chapple Drive",
    "sg:city":"Haverhill",
    "sg:classifiers":[
        {
            "category":"Professional",
            "type":"Services"
        }
    ],
    "sg:postcode":"CB9 0DJ",
    "sg:province":"Essex",
    "sg:tags":[
        "entertainer"
    ],
    "wof:name":"Circuit Entertainments",
    "wof:placetype":"venue"
},
  "geometry": {"coordinates":[0.4384630024,52.0893440247],"type":"Point"}
}