{
  "type": "Feature",
  "properties": {
    "iso:country":"GB",
    "sg:address":"Thorndon Grove, Windmill Hill",
    "sg:city":"Worcester",
    "sg:classifiers":[
        {
            "category":"Food & Beverages",
            "subcategory":"Farmers Market",
            "type":"Retail Goods"
        }
    ],
    "sg:postcode":"WR7 4RP",
    "sg:province":"Worcestershire",
    "sg:tags":[
        "gardener"
    ],
    "wof:name":"L R & A H Proctor",
    "wof:placetype":"venue"
},
  "geometry": {"coordinates":[-2.1198399067,52.1427688599],"type":"Point"}
}