{
  "type": "Feature",
  "properties": {
    "iso:country":"GB",
    "sg:address":"19 Cartmel Close",
    "sg:city":"Cheadle",
    "sg:classifiers":[
        {
            "category":"Home & Garden",
            "subcategory":"Home Furnishings",
            "type":"Retail Goods"
        }
    ],
    "sg:postcode":"SK8 4QP",
    "sg:province":"Cheshire",
    "sg:tags":[
        "blind",
        "curtain",
        "fitting"
    ],
    "wof:name":"Heather Ross Curtains",
    "wof:placetype":"venue"
},
  "geometry": {"coordinates":[-2.223158,53.383057],"type":"Point"}
}