{
  "type": "Feature",
  "properties": {
    "addr:full":"38 Elizabeth St Corby Northamptonshire NN17 1PN",
    "addr:housenumber":"38",
    "addr:postcode":"nn17 1pn",
    "addr:street":"Elizabeth St",
    "iso:country":"GB",
    "sg:address":"38 Elizabeth St",
    "sg:city":"Corby",
    "sg:classifiers":[
        {
            "category":"Communications",
            "subcategory":"Newspaper",
            "type":"Services"
        }
    ],
    "sg:phone":"+44 1536 393911",
    "sg:postcode":"NN17 1PN",
    "sg:province":"Northamptonshire",
    "sg:tags":[
        "magazine"
    ],
    "wof:name":"Corby Evening Telegraph",
    "wof:placetype":"venue"
},
  "geometry": {"coordinates":[-0.6996039748,52.488948822],"type":"Point"}
}