{
  "type": "Feature",
  "properties": {
    "iso:country":"GB",
    "sg:address":"The Coach House",
    "sg:city":"Cambridge",
    "sg:classifiers":[
        {
            "category":"Real Estate",
            "subcategory":"Surveying",
            "type":"Services"
        }
    ],
    "sg:phone":"+44 1223 845000",
    "sg:postcode":"CB2 2LG",
    "sg:province":"Cambridgeshire",
    "sg:tags":[
        "surveyor",
        "quantity"
    ],
    "wof:name":"Henry Riley (Cambridge) Cdm Ltd.",
    "wof:placetype":"venue"
},
  "geometry": {"coordinates":[0.11673,52.180618],"type":"Point"}
}