{
  "type": "Feature",
  "properties": {
    "addr:full":"5-7 Downs Road London Greater London E5 8QJ",
    "addr:housenumber":"5-7",
    "addr:postcode":"e5 8qj",
    "addr:street":"Downs Road",
    "iso:country":"GB",
    "sg:address":"5-7 Downs Road",
    "sg:city":"London",
    "sg:classifiers":[
        {
            "category":"Retail",
            "subcategory":"Repair Shop",
            "type":"Services"
        }
    ],
    "sg:phone":"+44 20 8986 9823",
    "sg:postcode":"E5 8QJ",
    "sg:province":"Greater London",
    "sg:tags":[
        "sharpening",
        "tool"
    ],
    "wof:name":"Henrys Saw Service",
    "wof:placetype":"venue"
},
  "geometry": {"coordinates":[-0.0589740016,51.5557861328],"type":"Point"}
}