{
  "type": "Feature",
  "properties": {
    "addr:full":"Church Way, Ecton Northampton Northamptonshire NN6 0QE",
    "addr:postcode":"nn6 0qe",
    "addr:street":"Church Way",
    "iso:country":"GB",
    "sg:address":"Church Way, Ecton",
    "sg:city":"Northampton",
    "sg:classifiers":[
        {
            "category":"Community Center",
            "type":"Public Place"
        }
    ],
    "sg:postcode":"NN6 0QE",
    "sg:province":"Northamptonshire",
    "sg:tags":[
        "conference",
        "room",
        "centre"
    ],
    "wof:name":"Ecton House Retreat & Conference Centre",
    "wof:placetype":"venue"
},
  "geometry": {"coordinates":[-0.7905179858,52.2665100098],"type":"Point"}
}