{
  "type": "Feature",
  "properties": {
    "iso:country":"GB",
    "sg:address":"York Road",
    "sg:city":"Doncaster",
    "sg:classifiers":[
        {
            "category":"Autos & Motor Vehicles",
            "subcategory":"Fuel & Gas Station",
            "type":"Retail Goods"
        }
    ],
    "sg:phone":"+44 1302 788720",
    "sg:postcode":"DN5 8RW",
    "sg:province":"South Yorkshire",
    "sg:tags":[
        "hr",
        "petrol"
    ],
    "wof:name":"Sun Service Station & Convenience Shop",
    "wof:placetype":"venue"
},
  "geometry": {"coordinates":[-1.167279,53.539474],"type":"Point"}
}