{
  "type": "Feature",
  "properties": {
    "iso:country":"GB",
    "sg:address":"Sandgate House",
    "sg:city":"Penrith",
    "sg:classifiers":[
        {
            "category":"Shopping",
            "subcategory":"Clothing, Apparel, & Fashions",
            "type":"Retail Goods"
        }
    ],
    "sg:postcode":"CA11 7TJ",
    "sg:province":"Cumbria",
    "sg:tags":[
        "ladieswear"
    ],
    "wof:name":"Maureen Armstrong",
    "wof:placetype":"venue"
},
  "geometry": {"coordinates":[-2.757469,54.664303],"type":"Point"}
}