{
  "type": "Feature",
  "properties": {
    "addr:full":"Unit 4 Block 1 Kirkcaldy Fife KY1 3PB",
    "addr:housenumber":"unit 4 block 1",
    "addr:postcode":"ky1 3pb",
    "iso:country":"GB",
    "sg:address":"Unit 4 Block 1",
    "sg:city":"Kirkcaldy",
    "sg:classifiers":[
        {
            "category":"Professional",
            "subcategory":"Printing & Photocopies",
            "type":"Services"
        }
    ],
    "sg:phone":"+44 1592 653866",
    "sg:postcode":"KY1 3PB",
    "sg:province":"Fife",
    "sg:tags":[
        "process",
        "screen",
        "printer"
    ],
    "wof:name":"Belisle",
    "wof:placetype":"venue"
},
  "geometry": {"coordinates":[-3.1459190845,56.1341896057],"type":"Point"}
}