{
  "type": "Feature",
  "properties": {
    "addr:full":"380 Northenden Road Sale Cheshire M33 2PZ",
    "addr:housenumber":"380",
    "addr:postcode":"m33 2pz",
    "addr:street":"Northenden Road",
    "iso:country":"GB",
    "sg:address":"380 Northenden Road",
    "sg:city":"Sale",
    "sg:classifiers":[
        {
            "category":"Shopping",
            "subcategory":"News",
            "type":"Retail Goods"
        }
    ],
    "sg:phone":"+44 161 973 4773",
    "sg:postcode":"M33 2PZ",
    "sg:province":"Cheshire",
    "sg:tags":[
        "newsagent"
    ],
    "wof:name":"Mo-News",
    "wof:placetype":"venue"
},
  "geometry": {"coordinates":[-2.291492939,53.418926239],"type":"Point"}
}