{
  "type": "Feature",
  "properties": {
    "iso:country":"GB",
    "sg:address":"34 Pinions Road",
    "sg:city":"High Wycombe",
    "sg:classifiers":[
        {
            "category":"Professional",
            "subcategory":"Management & Consulting",
            "type":"Services"
        }
    ],
    "sg:phone":"+44 1494 511344",
    "sg:postcode":"HP13 7AS",
    "sg:province":"Buckinghamshire",
    "sg:tags":[
        "sport"
    ],
    "wof:name":"The Soccer Mad Merchandising Co.",
    "wof:placetype":"venue"
},
  "geometry": {"coordinates":[-0.726097,51.62289],"type":"Point"}
}