{
  "type": "Feature",
  "properties": {
    "iso:country":"GB",
    "sg:address":"39-41 Regent Street",
    "sg:city":"Shanklin",
    "sg:classifiers":[
        {
            "category":"Shopping",
            "subcategory":"Thrift Store",
            "type":"Retail Goods"
        }
    ],
    "sg:phone":"+44 1983 868550",
    "sg:postcode":"PO37 7AF",
    "sg:province":"Isle of Wight",
    "sg:tags":[
        "shop",
        "charity"
    ],
    "wof:name":"Osel Charity Shop",
    "wof:placetype":"venue"
},
  "geometry": {"coordinates":[-1.178149,50.630833],"type":"Point"}
}