{
  "type": "Feature",
  "properties": {
    "addr:full":"113 River Road Barking Essex IG11 0EG",
    "addr:housenumber":"113",
    "addr:postcode":"ig11 0eg",
    "addr:street":"River Road",
    "iso:country":"GB",
    "sg:address":"113 River Road",
    "sg:city":"Barking",
    "sg:classifiers":[
        {
            "category":"Food & Beverages",
            "subcategory":"Liquor & Beverages",
            "type":"Retail Goods"
        }
    ],
    "sg:phone":"+44 20 8594 3001",
    "sg:postcode":"IG11 0EG",
    "sg:province":"Essex",
    "sg:tags":[
        "drink",
        "soft"
    ],
    "wof:name":"Bestline Enterprises Ltd.",
    "wof:placetype":"venue"
},
  "geometry": {"coordinates":[0.0995630026,51.5166664124],"type":"Point"}
}