{
  "type": "Feature",
  "properties": {
    "iso:country":"GB",
    "sg:address":"P O Box 49",
    "sg:city":"Ashtead",
    "sg:classifiers":[
        {
            "category":"Government",
            "subcategory":"Office",
            "type":"Public Place"
        }
    ],
    "sg:phone":"+44 1372 279083",
    "sg:postcode":"KT21 1YG",
    "sg:province":"Surrey",
    "sg:tags":[
        "local"
    ],
    "wof:name":"Corporation of London",
    "wof:placetype":"venue"
},
  "geometry": {"coordinates":[-0.300948,51.308899],"type":"Point"}
}