{
  "type": "Feature",
  "properties": {
    "iso:country":"GB",
    "sg:address":"Station Road, Erdington",
    "sg:city":"Birmingham",
    "sg:classifiers":[
        {
            "category":"Farming",
            "subcategory":"Nursery",
            "type":"Manufacturing & Wholesale Goods"
        },
        {
            "category":"Government",
            "subcategory":"Office",
            "type":"Public Place"
        }
    ],
    "sg:phone":"+44 121 373 1123",
    "sg:postcode":"B23 6UB",
    "sg:province":"West Midlands",
    "sg:tags":[
        "local",
        "creche"
    ],
    "wof:name":"Osborne Nursery School",
    "wof:placetype":"venue"
},
  "geometry": {"coordinates":[-1.846459,52.519863],"type":"Point"}
}