{
  "type": "Feature",
  "properties": {
    "addr:full":"Gladstone St, Rothwell Kettering Northamptonshire NN14 6ER",
    "addr:postcode":"nn14 6er",
    "addr:street":"Gladstone St",
    "iso:country":"GB",
    "sg:address":"Gladstone St, Rothwell",
    "sg:city":"Kettering",
    "sg:classifiers":[
        {
            "category":"Organizations",
            "subcategory":"Membership Organization",
            "type":"Services"
        }
    ],
    "sg:postcode":"NN14 6ER",
    "sg:province":"Northamptonshire",
    "sg:tags":[
        "club"
    ],
    "wof:name":"Rothwell Rifle Band Club",
    "wof:placetype":"venue"
},
  "geometry": {"coordinates":[-0.80109,52.424404],"type":"Point"}
}