{
  "type": "Feature",
  "properties": {
    "addr:full":"21 Wellesley Park Wellington Devon TA21 8PZ",
    "addr:housenumber":"21",
    "addr:postcode":"ta21 8pz",
    "addr:street":"Wellesley Park Wellington",
    "iso:country":"GB",
    "sg:address":"21 Wellesley Park",
    "sg:city":"Wellington",
    "sg:classifiers":[
        {
            "category":"Building & Trades",
            "subcategory":"Construction",
            "type":"Services"
        }
    ],
    "sg:phone":"+44 1823 666344",
    "sg:postcode":"TA21 8PZ",
    "sg:province":"Devon",
    "sg:tags":[
        "decorator",
        "painter"
    ],
    "wof:name":"M F Gaines",
    "wof:placetype":"venue"
},
  "geometry": {"coordinates":[-3.224108,50.97377],"type":"Point"}
}