{
  "type": "Feature",
  "properties": {
    "addr:full":"Tredinnick Barn, St Mabyn Bodmin Cornwall PL30 3BX",
    "addr:postcode":"pl30 3bx",
    "addr:street":"St",
    "iso:country":"GB",
    "sg:address":"Tredinnick Barn, St Mabyn",
    "sg:city":"Bodmin",
    "sg:classifiers":[
        {
            "category":"Shopping",
            "subcategory":"Florist",
            "type":"Retail Goods"
        }
    ],
    "sg:postcode":"PL30 3BX",
    "sg:province":"Cornwall",
    "wof:name":"Phoenix Flower Importers",
    "wof:placetype":"venue"
},
  "geometry": {"coordinates":[-4.75834,50.524658],"type":"Point"}
}