{
  "type": "Feature",
  "properties": {
    "addr:full":"Solaire House Lucas Close, Yateley Camberley Hampshire GU46 6JD",
    "addr:postcode":"gu46 6jd",
    "addr:street":"Lucas Close",
    "iso:country":"GB",
    "sg:address":"Solaire House Lucas Close, Yateley",
    "sg:city":"Camberley",
    "sg:classifiers":[
        {
            "category":"Professional",
            "subcategory":"Management & Consulting",
            "type":"Services"
        }
    ],
    "sg:postcode":"GU46 6JD",
    "sg:province":"Hampshire",
    "sg:tags":[
        "consultant",
        "specialist"
    ],
    "wof:name":"Coral Hatto Solaire Beauty & Health",
    "wof:placetype":"venue"
},
  "geometry": {"coordinates":[-0.8294590116,51.3353843689],"type":"Point"}
}