{
  "type": "Feature",
  "properties": {
    "iso:country":"GB",
    "sg:address":"Summerhill Farm, Hanbury",
    "sg:city":"Droitwich",
    "sg:classifiers":[
        {
            "category":"Banks & Credit Unions",
            "subcategory":"Investment Brokerage",
            "type":"Services"
        },
        {
            "category":"Farming",
            "subcategory":"Dairy Farm",
            "type":"Manufacturing & Wholesale Goods"
        },
        {
            "category":"Farming",
            "subcategory":"Livestock Farm",
            "type":"Manufacturing & Wholesale Goods"
        }
    ],
    "sg:phone":"+44 1905 773231",
    "sg:postcode":"WR9 7DY",
    "sg:province":"Worcestershire",
    "sg:tags":[
        "contractor",
        "others"
    ],
    "wof:name":"R Fowler & Sons Ltd.",
    "wof:placetype":"venue"
},
  "geometry": {"coordinates":[-2.156488,52.268078],"type":"Point"}
}