{
  "type": "Feature",
  "properties": {
    "addr:full":"Greenacres House, Kersewell Estate, Carnwath Lanark South Lanarkshire ML11 8LF",
    "addr:postcode":"ml11 8lf",
    "addr:street":"Kersewell;Carnwath",
    "iso:country":"GB",
    "sg:address":"Greenacres House, Kersewell Estate, Carnwath",
    "sg:city":"Lanark",
    "sg:classifiers":[
        {
            "category":"Professional",
            "subcategory":"Business Services",
            "type":"Services"
        }
    ],
    "sg:phone":"+44 1555 840961",
    "sg:postcode":"ML11 8LF",
    "sg:province":"South Lanarkshire",
    "sg:tags":[
        "import",
        "export",
        "agent"
    ],
    "wof:name":"David Walkinshaw Tractor Exports",
    "wof:placetype":"venue"
},
  "geometry": {"coordinates":[-3.624613,55.700565],"type":"Point"}
}