{
  "type": "Feature",
  "properties": {
    "addr:full":"Quay Street Yarmouth Isle of Wight PO41 0PB",
    "addr:postcode":"po41 0pb",
    "addr:street":"Quay Street",
    "iso:country":"GB",
    "sg:address":"Quay Street",
    "sg:city":"Yarmouth",
    "sg:classifiers":[
        {
            "category":"Cafe",
            "type":"Food & Drink"
        }
    ],
    "sg:postcode":"PO41 0PB",
    "sg:province":"Isle of Wight",
    "sg:tags":[
        "tea",
        "room"
    ],
    "wof:name":"The Coffee House",
    "wof:placetype":"venue"
},
  "geometry": {"coordinates":[-1.4998240471,50.7062110901],"type":"Point"}
}