{
  "type": "Feature",
  "properties": {
    "iso:country":"GB",
    "sg:address":"Trem Y Cyll",
    "sg:city":"Llanerchymedd",
    "sg:classifiers":[
        {
            "category":"Utilities",
            "subcategory":"Refuse",
            "type":"Services"
        }
    ],
    "sg:phone":"+44 1248 470566",
    "sg:postcode":"LL71 7DL",
    "sg:province":"Isle of Anglesey",
    "sg:tags":[
        "skip",
        "hire"
    ],
    "wof:name":"Anglesey Waste Disposal",
    "wof:placetype":"venue"
},
  "geometry": {"coordinates":[-4.3763628006,53.3303527832],"type":"Point"}
}