{
  "type": "Feature",
  "properties": {
    "addr:full":"22 Bond Street Dewsbury West Yorkshire WF13 1AU",
    "addr:housenumber":"22",
    "addr:postcode":"wf13 1au",
    "addr:street":"Bond Street",
    "iso:country":"GB",
    "sg:address":"22 Bond Street",
    "sg:city":"Dewsbury",
    "sg:classifiers":[
        {
            "category":"Real Estate",
            "subcategory":"Architect",
            "type":"Services"
        }
    ],
    "sg:phone":"+44 1924 456696",
    "sg:postcode":"WF13 1AU",
    "sg:province":"West Yorkshire",
    "wof:name":"Rod Briggs Design Group",
    "wof:placetype":"venue"
},
  "geometry": {"coordinates":[-1.6311030388,53.6921844482],"type":"Point"}
}