{
  "type": "Feature",
  "properties": {
    "addr:full":"C/o Cmr Partnership 1210 Parkvie, Arlington Business Park Theale Reading Berkshire RG7 4TY",
    "addr:housenumber":"1210",
    "addr:postcode":"rg7 4ty",
    "addr:street":"C / O;Parkvie Arlington Business Park",
    "iso:country":"GB",
    "sg:address":"C/o Cmr Partnership 1210 Parkvie, Arlington Business Park Theale",
    "sg:city":"Reading",
    "sg:classifiers":[
        {
            "category":"Professional",
            "subcategory":"Management & Consulting",
            "type":"Services"
        }
    ],
    "sg:postcode":"RG7 4TY",
    "sg:province":"Berkshire",
    "sg:tags":[
        "marketing",
        "consultant"
    ],
    "wof:name":"Resolution Marketing Associates Ltd",
    "wof:placetype":"venue"
},
  "geometry": {"coordinates":[-1.0667,51.437069],"type":"Point"}
}