{
  "type": "Feature",
  "properties": {
    "addr:full":"137b Mostyn St Llandudno Conwy LL30 2PE",
    "addr:housenumber":"137b",
    "addr:postcode":"ll30 2pe",
    "addr:street":"Mostyn St",
    "iso:country":"GB",
    "sg:address":"137b Mostyn St",
    "sg:city":"Llandudno",
    "sg:classifiers":[
        {
            "category":"Shopping",
            "subcategory":"Department Store",
            "type":"Retail Goods"
        }
    ],
    "sg:postcode":"LL30 2PE",
    "sg:province":"Conwy",
    "wof:name":"The Musician Centre",
    "wof:placetype":"venue"
},
  "geometry": {"coordinates":[-3.83233,53.326385],"type":"Point"}
}