{
  "type": "Feature",
  "properties": {
    "iso:country":"GB",
    "sg:address":"Grange Farm, Church Road, Flimby",
    "sg:city":"Maryport",
    "sg:classifiers":[
        {
            "category":"Farming",
            "subcategory":"Farm",
            "type":"Manufacturing & Wholesale Goods"
        }
    ],
    "sg:phone":"+44 1900 813433",
    "sg:postcode":"CA15 8TJ",
    "sg:province":"Cumbria",
    "sg:tags":[
        "mixed",
        "crop"
    ],
    "wof:name":"MATTHEW PALMER",
    "wof:placetype":"venue"
},
  "geometry": {"coordinates":[-3.5183010101,54.6921768188],"type":"Point"}
}