{
  "type": "Feature",
  "properties": {
    "addr:full":"29-30 Dolphin Centre Poole Dorset BH15 1SS",
    "addr:housenumber":"29-30",
    "addr:postcode":"bh15 1ss",
    "addr:street":"Dolphin Centre",
    "iso:country":"GB",
    "sg:address":"29-30 Dolphin Centre",
    "sg:city":"Poole",
    "sg:classifiers":[
        {
            "category":"Shopping",
            "subcategory":"Shoes",
            "type":"Retail Goods"
        }
    ],
    "sg:phone":"+44 1202 676338",
    "sg:postcode":"BH15 1SS",
    "sg:province":"Dorset",
    "sg:tags":[
        "shop",
        "retailer",
        "footwear"
    ],
    "wof:name":"Clarks Shoes Ltd",
    "wof:placetype":"venue"
},
  "geometry": {"coordinates":[-1.9867390394,50.7144851685],"type":"Point"}
}