{
  "type": "Feature",
  "properties": {
    "iso:country":"GB",
    "sg:address":"34 Cromwell Street",
    "sg:city":"Burnley",
    "sg:classifiers":[
        {
            "category":"Food & Beverages",
            "subcategory":"Fruits & Vegetables",
            "type":"Retail Goods"
        },
        {
            "category":"Food & Beverages",
            "subcategory":"Groceries & Convenience Stores",
            "type":"Retail Goods"
        }
    ],
    "sg:phone":"+44 1282 422236",
    "sg:postcode":"BB12 0DB",
    "sg:province":"Lancashire",
    "sg:tags":[
        "grocer",
        "greengrocer"
    ],
    "wof:name":"Shakeel Grocers",
    "wof:placetype":"venue"
},
  "geometry": {"coordinates":[-2.247017,53.797737],"type":"Point"}
}