{
  "type": "Feature",
  "properties": {
    "addr:full":"Brodick Castle, Isle Of Arran Brodick North Ayrshire KA27 8HY",
    "addr:postcode":"ka27 8hy",
    "iso:country":"GB",
    "sg:address":"Brodick Castle, Isle Of Arran",
    "sg:city":"Brodick",
    "sg:classifiers":[
        {
            "category":"Community Center",
            "type":"Public Place"
        }
    ],
    "sg:phone":"+44 1770 302202",
    "sg:postcode":"KA27 8HY",
    "sg:province":"North Ayrshire",
    "sg:tags":[
        "nursery",
        "centre"
    ],
    "wof:name":"The National Trust",
    "wof:placetype":"venue"
},
  "geometry": {"coordinates":[-5.152319,55.577576],"type":"Point"}
}