{
  "type": "Feature",
  "properties": {
    "iso:country":"GB",
    "sg:address":"The Square",
    "sg:city":"Exeter",
    "sg:classifiers":[
        {
            "category":"Retail",
            "subcategory":"Funeral Services",
            "type":"Services"
        }
    ],
    "sg:phone":"+44 1404 822020",
    "sg:postcode":"EX5 2SN",
    "sg:province":"Devon",
    "wof:name":"E Hansford & Son (devon) Ltd",
    "wof:placetype":"venue"
},
  "geometry": {"coordinates":[-3.389004,50.745495],"type":"Point"}
}