{
  "type": "Feature",
  "properties": {
    "addr:full":"92 Fonthill Road Aberdeen Aberdeen City AB11 6UL",
    "addr:housenumber":"92",
    "addr:postcode":"ab11 6ul",
    "addr:street":"Fonthill Road",
    "iso:country":"GB",
    "sg:address":"92 Fonthill Road",
    "sg:city":"Aberdeen",
    "sg:classifiers":[
        {
            "category":"Professional",
            "subcategory":"Art Services",
            "type":"Services"
        }
    ],
    "sg:postcode":"AB11 6UL",
    "sg:province":"Aberdeen City",
    "sg:tags":[
        "photographer"
    ],
    "wof:name":"Maggie Miller Photography",
    "wof:placetype":"venue"
},
  "geometry": {"coordinates":[-2.1107809544,57.1373138428],"type":"Point"}
}