{
  "type": "Feature",
  "properties": {
    "iso:country":"GB",
    "sg:address":"1 Russell Ho, King St",
    "sg:city":"Ayr",
    "sg:classifiers":[
        {
            "category":"Government",
            "subcategory":"Office",
            "type":"Public Place"
        }
    ],
    "sg:phone":"+44 1292 615000",
    "sg:postcode":"KA8 0BD",
    "sg:province":"South Ayrshire",
    "sg:tags":[
        "central"
    ],
    "wof:name":"H M Inspector of Taxes",
    "wof:placetype":"venue"
},
  "geometry": {"coordinates":[-4.62497,55.466492],"type":"Point"}
}