{
  "type": "Feature",
  "properties": {
    "addr:full":"120-122 Roundhay Rd Leeds West Yorkshire LS8 5NA",
    "addr:postcode":"120-122;ls8 5na",
    "addr:street":"Roundhay Rd",
    "iso:country":"GB",
    "sg:address":"120-122 Roundhay Rd",
    "sg:city":"Leeds",
    "sg:classifiers":[
        {
            "category":"Home & Garden",
            "subcategory":"Hardware",
            "type":"Retail Goods"
        }
    ],
    "sg:postcode":"LS8 5NA",
    "sg:province":"West Yorkshire",
    "sg:tags":[
        "retailer",
        "diy"
    ],
    "wof:name":"World of Decor",
    "wof:placetype":"venue"
},
  "geometry": {"coordinates":[-1.52526,53.810883],"type":"Point"}
}