{
  "type": "Feature",
  "properties": {
    "addr:full":"332 Mare Street London Greater London E8 1HA",
    "addr:housenumber":"332",
    "addr:postcode":"e8 1ha",
    "addr:street":"Mare Street",
    "iso:country":"GB",
    "sg:address":"332 Mare Street",
    "sg:city":"London",
    "sg:classifiers":[
        {
            "category":"Shopping",
            "subcategory":"Crafts & Fabrics",
            "type":"Retail Goods"
        }
    ],
    "sg:phone":"+44 20 8986 8452",
    "sg:postcode":"E8 1HA",
    "sg:province":"Greater London",
    "sg:tags":[
        "shop"
    ],
    "wof:name":"Hackney Fabrics",
    "wof:placetype":"venue"
},
  "geometry": {"coordinates":[-0.054892,51.546803],"type":"Point"}
}