{
  "type": "Feature",
  "properties": {
    "addr:full":"Friarscroft Car Park, Friarscroft Way Aylesbury Buckinghamshire HP20 2JB",
    "addr:postcode":"hp20 2jb",
    "addr:street":"Friarscroft Way",
    "iso:country":"GB",
    "sg:address":"Friarscroft Car Park, Friarscroft Way",
    "sg:city":"Aylesbury",
    "sg:classifiers":[
        {
            "category":"Retail",
            "subcategory":"Auto Rental",
            "type":"Services"
        }
    ],
    "sg:phone":"+44 1296 434540",
    "sg:postcode":"HP20 2JB",
    "sg:province":"Buckinghamshire",
    "sg:tags":[
        "car"
    ],
    "wof:name":"Avis Rent A Car Ltd.",
    "wof:placetype":"venue"
},
  "geometry": {"coordinates":[-0.811864,51.818779],"type":"Point"}
}