{
  "type": "Feature",
  "properties": {
    "iso:country":"GB",
    "sg:address":"Unit 1 Gannow Business Park, Gannow Lane",
    "sg:city":"Burnley",
    "sg:classifiers":[
        {
            "category":"Home & Garden",
            "subcategory":"Garden Supply",
            "type":"Retail Goods"
        }
    ],
    "sg:phone":"+44 1282 433846",
    "sg:postcode":"BB12 6JJ",
    "sg:province":"Lancashire",
    "sg:tags":[
        "ornament"
    ],
    "wof:name":"Art Line (U K) Ltd.",
    "wof:placetype":"venue"
},
  "geometry": {"coordinates":[-2.27534,53.78941],"type":"Point"}
}