{
  "type": "Feature",
  "properties": {
    "addr:full":"80 Compton Road Southport Lancashire PR8 4HA",
    "addr:housenumber":"80",
    "addr:postcode":"pr8 4ha",
    "addr:street":"Compton Road",
    "iso:country":"GB",
    "sg:address":"80 Compton Road",
    "sg:city":"Southport",
    "sg:classifiers":[
        {
            "category":"Personal",
            "subcategory":"Beauty Salon",
            "type":"Services"
        },
        {
            "category":"Personal",
            "subcategory":"Barber",
            "type":"Services"
        }
    ],
    "sg:phone":"+44 1704 569944",
    "sg:postcode":"PR8 4HA",
    "sg:province":"Lancashire",
    "sg:tags":[
        "unisex",
        "hairdresser"
    ],
    "wof:name":"Lynn's Hairstylists",
    "wof:placetype":"venue"
},
  "geometry": {"coordinates":[-3.0059249401,53.6300125122],"type":"Point"}
}