{
  "type": "Feature",
  "properties": {
    "addr:full":"Upbury Manor, Marlborough Road Gillingham Kent ME7 5HR",
    "addr:postcode":"me7 5hr",
    "addr:street":"Marlborough Road",
    "iso:country":"GB",
    "sg:address":"Upbury Manor, Marlborough Road",
    "sg:city":"Gillingham",
    "sg:classifiers":[
        {
            "category":"Professional",
            "subcategory":"Computer Services",
            "type":"Services"
        }
    ],
    "sg:phone":"+44 1634 264040",
    "sg:postcode":"ME7 5HR",
    "sg:province":"Kent",
    "sg:tags":[
        "development",
        "system",
        "software"
    ],
    "wof:name":"REDWOOD SYSTEMS",
    "wof:placetype":"venue"
},
  "geometry": {"coordinates":[0.5417299867,51.3882408142],"type":"Point"}
}