{
  "type": "Feature",
  "properties": {
    "iso:country":"GB",
    "sg:address":"12 Isleham Rd, Fordham",
    "sg:city":"Ely",
    "sg:classifiers":[
        {
            "category":"Retail",
            "subcategory":"Auto Repair",
            "type":"Services"
        }
    ],
    "sg:phone":"+44 1638 720381",
    "sg:postcode":"CB7 5NL",
    "sg:province":"Cambridgeshire",
    "sg:tags":[
        "modification",
        "garage"
    ],
    "wof:name":"Butler,Peter,",
    "wof:placetype":"venue"
},
  "geometry": {"coordinates":[0.395817,52.311535],"type":"Point"}
}