{
  "type": "Feature",
  "properties": {
    "addr:full":"1a Willow Street Oswestry Shropshire SY11 1AF",
    "addr:housenumber":"1a",
    "addr:postcode":"sy11 1af",
    "addr:street":"Willow Street",
    "iso:country":"GB",
    "sg:address":"1a Willow Street",
    "sg:city":"Oswestry",
    "sg:classifiers":[
        {
            "category":"Personal",
            "subcategory":"Beauty Salon",
            "type":"Services"
        }
    ],
    "sg:postcode":"SY11 1AF",
    "sg:province":"Shropshire",
    "sg:tags":[
        "unisex",
        "hairdresser"
    ],
    "wof:name":"Madame Pompadour",
    "wof:placetype":"venue"
},
  "geometry": {"coordinates":[-3.055745,52.859085],"type":"Point"}
}