{
  "type": "Feature",
  "properties": {
    "iso:country":"GB",
    "sg:address":"71 Runcorn Rd",
    "sg:city":"Northwich",
    "sg:classifiers":[
        {
            "category":"Professional",
            "subcategory":"Lawyer & Legal Services",
            "type":"Services"
        }
    ],
    "sg:phone":"+44 1606 76606",
    "sg:postcode":"CW8 4ES",
    "sg:province":"Cheshire",
    "sg:tags":[
        "advice",
        "counselling"
    ],
    "wof:name":"Christian Careline",
    "wof:placetype":"venue"
},
  "geometry": {"coordinates":[-2.547489,53.269348],"type":"Point"}
}