{
  "type": "Feature",
  "properties": {
    "addr:full":"Tipples Farm, Dereham Road, Swanton Novers Melton Constable Norfolk NR24 2NN",
    "addr:postcode":"nr24 2nn",
    "addr:street":"Dereham Road",
    "iso:country":"GB",
    "sg:address":"Tipples Farm, Dereham Road, Swanton Novers",
    "sg:city":"Melton Constable",
    "sg:classifiers":[
        {
            "category":"Farming",
            "subcategory":"Farm",
            "type":"Manufacturing & Wholesale Goods"
        }
    ],
    "sg:phone":"+44 1263 860434",
    "sg:postcode":"NR24 2NN",
    "sg:province":"Norfolk",
    "sg:tags":[
        "mixed",
        "crop"
    ],
    "wof:name":"M J Plumb",
    "wof:placetype":"venue"
},
  "geometry": {"coordinates":[1.0384149551,52.8566246033],"type":"Point"}
}