{
  "type": "Feature",
  "properties": {
    "iso:country":"GB",
    "sg:address":"71 Bridge Street",
    "sg:city":"Belper",
    "sg:classifiers":[
        {
            "category":"Bars & Pubs",
            "type":"Food & Drink"
        }
    ],
    "sg:phone":"+44 1773 822324",
    "sg:postcode":"DE56 1BA",
    "sg:province":"Derbyshire",
    "sg:tags":[
        "pubs",
        "inn"
    ],
    "wof:name":"The Duke of Devonshire",
    "wof:placetype":"venue"
},
  "geometry": {"coordinates":[-1.485342,53.025417],"type":"Point"}
}