{
  "type": "Feature",
  "properties": {
    "addr:full":"34 Melbourne Avenue, Westwood, East Kilbride Glasgow South Lanarkshire G75 8DT",
    "addr:housenumber":"34",
    "addr:postcode":"g75 8dt",
    "addr:street":"Melbourne Avenue",
    "iso:country":"GB",
    "sg:address":"34 Melbourne Avenue, Westwood, East Kilbride",
    "sg:city":"Glasgow",
    "sg:classifiers":[
        {
            "category":"Personal",
            "type":"Services"
        }
    ],
    "sg:postcode":"G75 8DT",
    "sg:province":"South Lanarkshire",
    "sg:tags":[
        "wedding"
    ],
    "wof:name":"E K Video Production",
    "wof:placetype":"venue"
},
  "geometry": {"coordinates":[-4.1972341537,55.7559204102],"type":"Point"}
}