{
  "type": "Feature",
  "properties": {
    "iso:country":"GB",
    "sg:address":"St Stephens House, Dogflud Way",
    "sg:city":"Farnham",
    "sg:classifiers":[
        {
            "category":"Professional",
            "subcategory":"Computer Services",
            "type":"Services"
        }
    ],
    "sg:postcode":"GU9 7UD",
    "sg:province":"Surrey",
    "sg:tags":[
        "system",
        "software"
    ],
    "wof:name":"Sitestream Software Ltd.",
    "wof:placetype":"venue"
},
  "geometry": {"coordinates":[-0.793219,51.217564],"type":"Point"}
}