{
  "type": "Feature",
  "properties": {
    "iso:country":"GB",
    "sg:address":"Beacon View Farm Industrial Estate, Barrow Road",
    "sg:city":"Loughborough",
    "sg:classifiers":[
        {
            "category":"Wholesale",
            "subcategory":"Scrap",
            "type":"Manufacturing & Wholesale Goods"
        }
    ],
    "sg:postcode":"LE12 8EN",
    "sg:province":"Leicestershire",
    "sg:tags":[
        "salvage"
    ],
    "wof:name":"A 6 Repairables",
    "wof:placetype":"venue"
},
  "geometry": {"coordinates":[-1.1576700211,52.7511291504],"type":"Point"}
}