{
  "type": "Feature",
  "properties": {
    "iso:country":"GB",
    "sg:address":"East Street",
    "sg:city":"Chulmleigh",
    "sg:classifiers":[
        {
            "category":"Food & Beverages",
            "subcategory":"Bakery",
            "type":"Retail Goods"
        }
    ],
    "sg:phone":"+44 1769 580228",
    "sg:postcode":"EX18 7DD",
    "sg:province":"Devon",
    "sg:tags":[
        "shop",
        "baker"
    ],
    "wof:name":"Chulmleigh Bakery",
    "wof:placetype":"venue"
},
  "geometry": {"coordinates":[-3.8655939102,50.9131813049],"type":"Point"}
}