{
  "type": "Feature",
  "properties": {
    "iso:country":"GB",
    "sg:address":"64 King St",
    "sg:city":"Broseley",
    "sg:classifiers":[
        {
            "category":"Professional",
            "subcategory":"Management & Consulting",
            "type":"Services"
        }
    ],
    "sg:phone":"+44 1952 883271",
    "sg:postcode":"TF12 5PR",
    "sg:province":"Shropshire",
    "sg:tags":[
        "marketing",
        "consultant"
    ],
    "wof:name":"R J S Sales & Marketing",
    "wof:placetype":"venue"
},
  "geometry": {"coordinates":[-2.486663,52.618847],"type":"Point"}
}