{
  "type": "Feature",
  "properties": {
    "addr:full":"7 George Street West Luton Bedfordshire LU1 2BJ",
    "addr:housenumber":"7",
    "addr:postcode":"lu1 2bj",
    "addr:street":"George Street West",
    "iso:country":"GB",
    "sg:address":"7 George Street West",
    "sg:city":"Luton",
    "sg:classifiers":[
        {
            "category":"Professional",
            "subcategory":"Lawyer & Legal Services",
            "type":"Services"
        }
    ],
    "sg:phone":"+44 1582 749100",
    "sg:postcode":"LU1 2BJ",
    "sg:province":"Bedfordshire",
    "sg:tags":[
        "solicitor"
    ],
    "wof:name":"Churchman Thaker Solicitors",
    "wof:placetype":"venue"
},
  "geometry": {"coordinates":[-0.41663,51.878147],"type":"Point"}
}