{
  "type": "Feature",
  "properties": {
    "iso:country":"GB",
    "sg:address":"67 Bridge Street",
    "sg:city":"Usk",
    "sg:classifiers":[
        {
            "category":"Building & Trades",
            "subcategory":"Construction",
            "type":"Services"
        }
    ],
    "sg:phone":"+44 1291 671167",
    "sg:postcode":"NP15 1BQ",
    "sg:province":"Monmouthshire",
    "sg:tags":[
        "builder"
    ],
    "wof:name":"S & M C",
    "wof:placetype":"venue"
},
  "geometry": {"coordinates":[-2.906147,51.701939],"type":"Point"}
}