{
  "type": "Feature",
  "properties": {
    "iso:country":"GB",
    "sg:address":"Rackery Lane",
    "sg:city":"Wrexham",
    "sg:classifiers":[
        {
            "category":"Professional",
            "subcategory":"Art Services",
            "type":"Services"
        }
    ],
    "sg:phone":"+44 1767 601280",
    "sg:postcode":"LL12 0PB",
    "sg:province":"Wrexham",
    "sg:tags":[
        "consultant",
        "design"
    ],
    "wof:name":"Mayflower Aerospace (Hansford) Ltd.",
    "wof:placetype":"venue"
},
  "geometry": {"coordinates":[-3.003467,53.102177],"type":"Point"}
}