{
  "type": "Feature",
  "properties": {
    "iso:country":"GB",
    "sg:address":"16 Theberton Street",
    "sg:city":"London",
    "sg:classifiers":[
        {
            "category":"Professional",
            "subcategory":"Lawyer & Legal Services",
            "type":"Services"
        }
    ],
    "sg:phone":"+44 20 7288 4700",
    "sg:postcode":"N1 0QX",
    "sg:province":"Greater London",
    "sg:tags":[
        "conveyancing"
    ],
    "wof:name":"Bolt Burdon",
    "wof:placetype":"venue"
},
  "geometry": {"coordinates":[-0.1035099998,51.5376663208],"type":"Point"}
}