{
  "type": "Feature",
  "properties": {
    "addr:full":"315 Tyburn Road, Erdington Birmingham West Midlands B24 8NB",
    "addr:housenumber":"315",
    "addr:postcode":"b24 8nb",
    "addr:street":"Tyburn Road",
    "iso:country":"GB",
    "sg:address":"315 Tyburn Road, Erdington",
    "sg:city":"Birmingham",
    "sg:classifiers":[
        {
            "category":"Retail",
            "subcategory":"Auto Repair",
            "type":"Services"
        }
    ],
    "sg:phone":"+44 121 322 5620",
    "sg:postcode":"B24 8NB",
    "sg:province":"West Midlands",
    "sg:tags":[
        "bodybuilder",
        "repairer"
    ],
    "wof:name":"Summerdale Truck Bodies Ltd.",
    "wof:placetype":"venue"
},
  "geometry": {"coordinates":[-1.847275,52.50893],"type":"Point"}
}