{
  "type": "Feature",
  "properties": {
    "iso:country":"GB",
    "sg:address":"Coventry Road, Broughton Astley",
    "sg:city":"Leicester",
    "sg:classifiers":[
        {
            "category":"Manufacturing",
            "subcategory":"Building Materials",
            "type":"Manufacturing & Wholesale Goods"
        }
    ],
    "sg:phone":"+44 1455 282287",
    "sg:postcode":"LE9 6QD",
    "sg:province":"Leicestershire",
    "sg:tags":[
        "concrete",
        "product"
    ],
    "wof:name":"Foxon Bros (Concrete Products) Ltd.",
    "wof:placetype":"venue"
},
  "geometry": {"coordinates":[-1.225593,52.531677],"type":"Point"}
}