{
  "type": "Feature",
  "properties": {
    "iso:country":"GB",
    "sg:address":"95 Neath Road, Briton Ferry",
    "sg:city":"Neath",
    "sg:classifiers":[
        {
            "category":"Shopping",
            "subcategory":"Clothing, Apparel, & Fashions",
            "type":"Retail Goods"
        }
    ],
    "sg:phone":"+44 1639 822690",
    "sg:postcode":"SA11 2DQ",
    "sg:province":"Neath Port Talbot",
    "sg:tags":[
        "shop"
    ],
    "wof:name":"Canasta",
    "wof:placetype":"venue"
},
  "geometry": {"coordinates":[-3.818346,51.632034],"type":"Point"}
}