{
  "type": "Feature",
  "properties": {
    "addr:full":"Netherton Farm, Mattys Lane, Frodsham Warrington Cheshire WA6 6UT",
    "addr:postcode":"wa6 6ut",
    "addr:street":"Netherton;Mattys Lane",
    "iso:country":"GB",
    "sg:address":"Netherton Farm, Mattys Lane, Frodsham",
    "sg:city":"Warrington",
    "sg:classifiers":[
        {
            "category":"Farming",
            "subcategory":"Livestock Farm",
            "type":"Manufacturing & Wholesale Goods"
        }
    ],
    "sg:postcode":"WA6 6UT",
    "sg:province":"Cheshire",
    "sg:tags":[
        "others"
    ],
    "wof:name":"S Williams & Son",
    "wof:placetype":"venue"
},
  "geometry": {"coordinates":[-2.73383,53.288288],"type":"Point"}
}