{
  "type": "Feature",
  "properties": {
    "addr:full":"3 Cotton Dupplin Est Perth Perth and Kinross PH2 0PW",
    "addr:housenumber":"3",
    "addr:postcode":"ph2 0pw",
    "addr:street":"Cotton Dupplin Est",
    "iso:country":"GB",
    "sg:address":"3 Cotton Dupplin Est",
    "sg:city":"Perth",
    "sg:classifiers":[
        {
            "category":"Real Estate",
            "subcategory":"Surveying",
            "type":"Services"
        }
    ],
    "sg:phone":"+44 1738 443454",
    "sg:postcode":"PH2 0PW",
    "sg:province":"Perth and Kinross",
    "sg:tags":[
        "surveyor",
        "quantity"
    ],
    "wof:name":"Quantitech",
    "wof:placetype":"venue"
},
  "geometry": {"coordinates":[-3.4860200882,56.3649940491],"type":"Point"}
}