{
  "type": "Feature",
  "properties": {
    "iso:country":"GB",
    "sg:address":"Station Studio, Cooksbridge",
    "sg:city":"Lewes",
    "sg:classifiers":[
        {
            "category":"Building & Trades",
            "subcategory":"Landscaping Services",
            "type":"Services"
        }
    ],
    "sg:phone":"+44 1273 400983",
    "sg:postcode":"BN8 4SW",
    "sg:province":"East Sussex",
    "sg:tags":[
        "contractor"
    ],
    "wof:name":"Station Studio",
    "wof:placetype":"venue"
},
  "geometry": {"coordinates":[-0.0082040001,50.9044265747],"type":"Point"}
}