{
  "type": "Feature",
  "properties": {
    "iso:country":"GB",
    "sg:address":"Unit 1c, Eden Street",
    "sg:city":"Coventry",
    "sg:classifiers":[
        {
            "category":"Professional",
            "subcategory":"Engineering",
            "type":"Services"
        }
    ],
    "sg:phone":"+44 24 7666 8585",
    "sg:postcode":"CV6 5HE",
    "sg:province":"Warwickshire",
    "sg:tags":[
        "engineer"
    ],
    "wof:name":"Shan Engineering",
    "wof:placetype":"venue"
},
  "geometry": {"coordinates":[-1.487507,52.428135],"type":"Point"}
}