{
  "type": "Feature",
  "properties": {
    "addr:full":"21 Stone Street Cranbrook Kent TN17 3HF",
    "addr:housenumber":"21",
    "addr:postcode":"tn17 3hf",
    "addr:street":"Stone Street",
    "iso:country":"GB",
    "sg:address":"21 Stone Street",
    "sg:city":"Cranbrook",
    "sg:classifiers":[
        {
            "category":"Shopping",
            "subcategory":"Department Store",
            "type":"Retail Goods"
        }
    ],
    "sg:phone":"+44 1580 714687",
    "sg:postcode":"TN17 3HF",
    "sg:province":"Kent",
    "wof:name":"Daisychain",
    "wof:placetype":"venue"
},
  "geometry": {"coordinates":[0.5365700126,51.0962562561],"type":"Point"}
}