{
  "type": "Feature",
  "properties": {
    "iso:country":"GB",
    "sg:address":"Registration & Inspection Unit, Cassaton Ho, 43-49 Fawcett St",
    "sg:city":"Sunderland",
    "sg:classifiers":[
        {
            "category":"Social Services",
            "type":"Services"
        }
    ],
    "sg:phone":"+44 191 553 7266",
    "sg:postcode":"SR1 1RR",
    "sg:province":"Tyne and Wear",
    "wof:name":"Social Services",
    "wof:placetype":"venue"
},
  "geometry": {"coordinates":[-1.3815740347,54.9052772522],"type":"Point"}
}