{
  "type": "Feature",
  "properties": {
    "iso:country":"GB",
    "sg:address":"Woodside Garage, Woodhead Road",
    "sg:city":"Huddersfield",
    "sg:classifiers":[
        {
            "category":"Retail",
            "subcategory":"Auto Repair",
            "type":"Services"
        }
    ],
    "sg:phone":"+44 1484 682474",
    "sg:postcode":"HD9 2PR",
    "sg:province":"South Yorkshire",
    "sg:tags":[
        "modification",
        "garage"
    ],
    "wof:name":"Holmfirth Coachworks",
    "wof:placetype":"venue"
},
  "geometry": {"coordinates":[-1.80013,53.56591],"type":"Point"}
}