{
  "type": "Feature",
  "properties": {
    "addr:full":"41b High St South, Langley Moor Durham Durham DH7 8JW",
    "addr:housenumber":"41b",
    "addr:postcode":"dh7 8jw",
    "addr:street":"High St South",
    "iso:country":"GB",
    "sg:address":"41b High St South, Langley Moor",
    "sg:city":"Durham",
    "sg:classifiers":[
        {
            "category":"Real Estate",
            "subcategory":"Real Estate Operator",
            "type":"Services"
        },
        {
            "category":"Building & Trades",
            "subcategory":"Construction",
            "type":"Services"
        }
    ],
    "sg:phone":"+44 191 378 9352",
    "sg:postcode":"DH7 8JW",
    "sg:province":"Durham",
    "sg:tags":[
        "letting",
        "roofing",
        "agent"
    ],
    "wof:name":"Brett Bros Developments Ltd.",
    "wof:placetype":"venue"
},
  "geometry": {"coordinates":[-1.610124,54.758076],"type":"Point"}
}