{
  "type": "Feature",
  "properties": {
    "addr:full":"Blythe Road Southwold Suffolk IP18 6AZ",
    "addr:postcode":"ip18 6az",
    "addr:street":"Blythe Road",
    "iso:country":"GB",
    "sg:address":"Blythe Road",
    "sg:city":"Southwold",
    "sg:classifiers":[
        {
            "category":"Wholesale",
            "subcategory":"Scrap",
            "type":"Manufacturing & Wholesale Goods"
        },
        {
            "category":"Wholesale",
            "subcategory":"Auto Parts",
            "type":"Manufacturing & Wholesale Goods"
        }
    ],
    "sg:phone":"+44 1502 722756",
    "sg:postcode":"IP18 6AZ",
    "sg:province":"Suffolk",
    "sg:tags":[
        "car",
        "breaker",
        "dismantlers"
    ],
    "wof:name":"Sole Bay Car Spares",
    "wof:placetype":"venue"
},
  "geometry": {"coordinates":[1.6762,52.328163],"type":"Point"}
}