{
  "type": "Feature",
  "properties": {
    "addr:full":"8 Oxford Road Dewsbury West Yorkshire WF13 4LN",
    "addr:housenumber":"8",
    "addr:postcode":"wf13 4ln",
    "addr:street":"Oxford Road",
    "iso:country":"GB",
    "sg:address":"8 Oxford Road",
    "sg:city":"Dewsbury",
    "sg:classifiers":[
        {
            "category":"Health Services",
            "subcategory":"Nursing And Care Facility",
            "type":"Services"
        }
    ],
    "sg:phone":"+44 1924 462951",
    "sg:postcode":"WF13 4LN",
    "sg:province":"West Yorkshire",
    "sg:tags":[
        "home"
    ],
    "wof:name":"Sunnyside Nursing & Residential Home",
    "wof:placetype":"venue"
},
  "geometry": {"coordinates":[-1.640362,53.696262],"type":"Point"}
}