{
  "type": "Feature",
  "properties": {
    "addr:full":"758-760 Great Cambridge Road Enfield Greater London EN1 3RN",
    "addr:housenumber":"758-760",
    "addr:postcode":"en1 3rn",
    "addr:street":"Great Cambridge Road",
    "iso:country":"GB",
    "sg:address":"758-760 Great Cambridge Road",
    "sg:city":"Enfield",
    "sg:classifiers":[
        {
            "category":"Manufacturing",
            "subcategory":"Food",
            "type":"Manufacturing & Wholesale Goods"
        }
    ],
    "sg:postcode":"EN1 3RN",
    "sg:province":"Greater London",
    "sg:tags":[
        "mnfr",
        "drink",
        "soft"
    ],
    "wof:name":"Sport Specific Beverages",
    "wof:placetype":"venue"
},
  "geometry": {"coordinates":[-0.0589979999,51.658290863],"type":"Point"}
}