{
  "type": "Feature",
  "properties": {
    "iso:country":"GB",
    "sg:address":"20 Victoria Street",
    "sg:city":"Egham",
    "sg:classifiers":[
        {
            "category":"Professional",
            "type":"Services"
        }
    ],
    "sg:phone":"+44 1784 433139",
    "sg:postcode":"TW20 0QY",
    "sg:province":"Surrey",
    "sg:tags":[
        "caterer"
    ],
    "wof:name":"Deli-on-the-Green",
    "wof:placetype":"venue"
},
  "geometry": {"coordinates":[-0.570412,51.428947],"type":"Point"}
}