{
  "type": "Feature",
  "properties": {
    "addr:full":"15 West Park London Greater London SE9 4RZ",
    "addr:housenumber":"15",
    "addr:postcode":"se9 4rz",
    "addr:street":"West Park",
    "iso:country":"GB",
    "sg:address":"15 West Park",
    "sg:city":"London",
    "sg:classifiers":[
        {
            "category":"Shopping",
            "subcategory":"Books",
            "type":"Retail Goods"
        },
        {
            "category":"Shopping",
            "subcategory":"Used Merchandise",
            "type":"Retail Goods"
        }
    ],
    "sg:phone":"+44 20 8851 8487",
    "sg:postcode":"SE9 4RZ",
    "sg:province":"Greater London",
    "sg:tags":[
        "second-hand",
        "secondhand"
    ],
    "wof:name":"Collectable Books",
    "wof:placetype":"venue"
},
  "geometry": {"coordinates":[0.0463100001,51.4386901855],"type":"Point"}
}