{
  "type": "Feature",
  "properties": {
    "addr:full":"12-14 Nursery Road Montrose Aberdeenshire DD10 9AW",
    "addr:housenumber":"12-14",
    "addr:postcode":"dd10 9aw",
    "addr:street":"Nursery Road",
    "iso:country":"GB",
    "sg:address":"12-14 Nursery Road",
    "sg:city":"Montrose",
    "sg:classifiers":[
        {
            "category":"Shopping",
            "subcategory":"Tobacco",
            "type":"Retail Goods"
        }
    ],
    "sg:phone":"+44 1674 672778",
    "sg:postcode":"DD10 9AW",
    "sg:province":"Aberdeenshire",
    "sg:tags":[
        "confectioner",
        "tobacconist"
    ],
    "wof:name":"Stanley Henderson",
    "wof:placetype":"venue"
},
  "geometry": {"coordinates":[-2.467316,56.71962],"type":"Point"}
}