{
  "type": "Feature",
  "properties": {
    "addr:full":"Thurleston Lodge Cottages Ipswich Suffolk IP1 6TF",
    "addr:postcode":"ip1 6tf",
    "iso:country":"GB",
    "sg:address":"Thurleston Lodge Cottages",
    "sg:city":"Ipswich",
    "sg:classifiers":[
        {
            "category":"Professional",
            "type":"Services"
        }
    ],
    "sg:phone":"+44 1473 226650",
    "sg:postcode":"IP1 6TF",
    "sg:province":"Suffolk",
    "sg:tags":[
        "reflexologists"
    ],
    "wof:name":"W Seal & H Borth",
    "wof:placetype":"venue"
},
  "geometry": {"coordinates":[1.135415,52.086685],"type":"Point"}
}