{
  "type": "Feature",
  "properties": {
    "iso:country":"GB",
    "sg:address":"Unit 7 Anker Court, Alliance Close, Attleborough Fields Industrial E",
    "sg:city":"Nuneaton",
    "sg:classifiers":[
        {
            "category":"Manufacturing",
            "subcategory":"Rubber & Plastics",
            "type":"Manufacturing & Wholesale Goods"
        },
        {
            "category":"Retail",
            "subcategory":"Auto Repair",
            "type":"Services"
        }
    ],
    "sg:phone":"+44 24 7635 0575",
    "sg:postcode":"CV11 6SD",
    "sg:province":"Leicestershire",
    "sg:tags":[
        "supplier",
        "rebuilding",
        "retreading",
        "stockist",
        "tyre"
    ],
    "sg:website":"http://www.amcast.co.uk",
    "wof:name":"Amcast Ltd",
    "wof:placetype":"venue"
},
  "geometry": {"coordinates":[-1.446089,52.518456],"type":"Point"}
}