{
  "type": "Feature",
  "properties": {
    "iso:country":"GB",
    "sg:address":"Tees Ho, School Aycliffe La",
    "sg:city":"Newton Aycliffe",
    "sg:classifiers":[
        {
            "category":"Social Services",
            "subcategory":"Retirement Home",
            "type":"Services"
        }
    ],
    "sg:phone":"+44 1325 301354",
    "sg:postcode":"DL5 6QA",
    "sg:province":"Durham",
    "sg:tags":[
        "residential",
        "care"
    ],
    "wof:name":"South Durham Health Care",
    "wof:placetype":"venue"
},
  "geometry": {"coordinates":[-1.563024044,54.5962715149],"type":"Point"}
}