{
  "type": "Feature",
  "properties": {
    "iso:country":"GB",
    "sg:address":"4 Harpton Parade",
    "sg:city":"Yateley",
    "sg:classifiers":[
        {
            "category":"Personal",
            "subcategory":"Beauty Salon",
            "type":"Services"
        },
        {
            "category":"Personal",
            "subcategory":"Barber",
            "type":"Services"
        }
    ],
    "sg:phone":"+44 1252 879259",
    "sg:postcode":"GU46 7SB",
    "sg:province":"Hampshire",
    "sg:tags":[
        "unisex",
        "hairdresser"
    ],
    "wof:name":"Perfection",
    "wof:placetype":"venue"
},
  "geometry": {"coordinates":[-0.829934001,51.3441734314],"type":"Point"}
}