{
  "type": "Feature",
  "properties": {
    "addr:full":"16 Commercial St Cinderford Gloucestershire GL14 2RR",
    "addr:housenumber":"16",
    "addr:postcode":"gl14 2rr",
    "addr:street":"Commercial St",
    "iso:country":"GB",
    "sg:address":"16 Commercial St",
    "sg:city":"Cinderford",
    "sg:classifiers":[
        {
            "category":"Food & Beverages",
            "subcategory":"Supermarket",
            "type":"Retail Goods"
        }
    ],
    "sg:postcode":"GL14 2RR",
    "sg:province":"Gloucestershire",
    "wof:name":"Dean Off Licence",
    "wof:placetype":"venue"
},
  "geometry": {"coordinates":[-2.499863,51.822998],"type":"Point"}
}