{
  "type": "Feature",
  "properties": {
    "iso:country":"GB",
    "sg:address":"8 Brus House, Mitchell Avenue, Thornaby",
    "sg:city":"Stockton-on-tees",
    "sg:classifiers":[
        {
            "category":"Real Estate",
            "subcategory":"Real Estate Agent",
            "type":"Services"
        }
    ],
    "sg:phone":"+44 1642 760255",
    "sg:postcode":"TS17 9ES",
    "sg:province":"Durham",
    "wof:name":"B B G Estate Agencies",
    "wof:placetype":"venue"
},
  "geometry": {"coordinates":[-1.292764,54.51828],"type":"Point"}
}