{
  "type": "Feature",
  "properties": {
    "addr:full":"16 George Street Bathgate West Lothian EH48 1PW",
    "addr:housenumber":"16",
    "addr:postcode":"eh48 1pw",
    "addr:street":"George Street Bathgate",
    "iso:country":"GB",
    "sg:address":"16 George Street",
    "sg:city":"Bathgate",
    "sg:classifiers":[
        {
            "category":"Real Estate",
            "subcategory":"Surveying",
            "type":"Services"
        }
    ],
    "sg:phone":"+44 1506 634525",
    "sg:postcode":"EH48 1PW",
    "sg:province":"West Lothian",
    "sg:tags":[
        "surveyor",
        "valuer"
    ],
    "wof:name":"Allied Surveyors Scotland Plc",
    "wof:placetype":"venue"
},
  "geometry": {"coordinates":[-3.641754,55.900986],"type":"Point"}
}