{
  "type": "Feature",
  "properties": {
    "addr:full":"Unit 9 St Peters Walk Northampton Northamptonshire NN1 1PT",
    "addr:housenumber":"unit 9",
    "addr:postcode":"nn1 1pt",
    "addr:street":"St Peters Walk",
    "iso:country":"GB",
    "sg:address":"Unit 9 St Peters Walk",
    "sg:city":"Northampton",
    "sg:classifiers":[
        {
            "category":"Personal",
            "subcategory":"Beauty Salon",
            "type":"Services"
        }
    ],
    "sg:phone":"+44 1604 630325",
    "sg:postcode":"NN1 1PT",
    "sg:province":"Northamptonshire",
    "sg:tags":[
        "unisex",
        "hairdresser"
    ],
    "wof:name":"Shine Hairdressing",
    "wof:placetype":"venue"
},
  "geometry": {"coordinates":[-0.8988580108,52.2340202332],"type":"Point"}
}