{
  "type": "Feature",
  "properties": {
    "addr:full":"158 Manchester Road, Chorlton Manchester Cheshire M16 0DZ",
    "addr:housenumber":"158",
    "addr:postcode":"m16 0dz",
    "addr:street":"Manchester Road",
    "iso:country":"GB",
    "sg:address":"158 Manchester Road, Chorlton",
    "sg:city":"Manchester",
    "sg:classifiers":[
        {
            "category":"Health Services",
            "subcategory":"Nursing And Care Facility",
            "type":"Services"
        }
    ],
    "sg:phone":"+44 161 881 2514",
    "sg:postcode":"M16 0DZ",
    "sg:province":"Cheshire",
    "sg:tags":[
        "home"
    ],
    "wof:name":"The Conifers Care Group",
    "wof:placetype":"venue"
},
  "geometry": {"coordinates":[-2.274185,53.449554],"type":"Point"}
}