{
  "type": "Feature",
  "properties": {
    "addr:full":"58 Spencer St Birmingham West Midlands B18 6DS",
    "addr:housenumber":"58",
    "addr:postcode":"b18 6ds",
    "addr:street":"Spencer St",
    "iso:country":"GB",
    "sg:address":"58 Spencer St",
    "sg:city":"Birmingham",
    "sg:classifiers":[
        {
            "category":"Professional",
            "subcategory":"Art Services",
            "type":"Services"
        }
    ],
    "sg:phone":"+44 121 236 8469",
    "sg:postcode":"B18 6DS",
    "sg:province":"West Midlands",
    "sg:tags":[
        "model",
        "maker"
    ],
    "wof:name":"C Haddock Model Maker",
    "wof:placetype":"venue"
},
  "geometry": {"coordinates":[-1.9109059572,52.4888648987],"type":"Point"}
}