{
  "type": "Feature",
  "properties": {
    "addr:full":"37 South Street North Chesterfield Derbyshire S43 2AA",
    "addr:housenumber":"37",
    "addr:postcode":"s43 2aa",
    "addr:street":"South Street",
    "iso:country":"GB",
    "sg:address":"37 South Street North",
    "sg:city":"Chesterfield",
    "sg:classifiers":[
        {
            "category":"Personal",
            "type":"Services"
        }
    ],
    "sg:phone":"+44 1246 261409",
    "sg:postcode":"S43 2AA",
    "sg:province":"Derbyshire",
    "sg:tags":[
        "wedding"
    ],
    "wof:name":"Knight's Photographic",
    "wof:placetype":"venue"
},
  "geometry": {"coordinates":[-1.4044549465,53.2743682861],"type":"Point"}
}