{
  "type": "Feature",
  "properties": {
    "iso:country":"GB",
    "sg:address":"172 Darlaston Road",
    "sg:city":"Wednesbury",
    "sg:classifiers":[
        {
            "category":"Retail",
            "subcategory":"Auto Repair",
            "type":"Services"
        }
    ],
    "sg:postcode":"WS10 7TA",
    "sg:province":"West Midlands",
    "sg:tags":[
        "modification",
        "garage"
    ],
    "wof:name":"Unique Motor Services",
    "wof:placetype":"venue"
},
  "geometry": {"coordinates":[-2.0330889225,52.5646095276],"type":"Point"}
}