{
  "type": "Feature",
  "properties": {
    "addr:full":"Minnis Lane, Stelling Minnis Canterbury Kent CT4 6AS",
    "addr:postcode":"ct4 6as",
    "addr:street":"Minnis Lane",
    "iso:country":"GB",
    "sg:address":"Minnis Lane, Stelling Minnis",
    "sg:city":"Canterbury",
    "sg:classifiers":[
        {
            "category":"Bars & Pubs",
            "type":"Food & Drink"
        }
    ],
    "sg:phone":"+44 1227 709265",
    "sg:postcode":"CT4 6AS",
    "sg:province":"Kent",
    "sg:tags":[
        "pubs",
        "inn"
    ],
    "wof:name":"The Rose & Crown",
    "wof:placetype":"venue"
},
  "geometry": {"coordinates":[1.0686600208,51.1792640686],"type":"Point"}
}