{
  "type": "Feature",
  "properties": {
    "addr:full":"29 Newick Drive, Newick Lewes East Sussex BN8 4NY",
    "addr:housenumber":"29",
    "addr:postcode":"bn8 4ny",
    "addr:street":"Newick Drive Newick",
    "iso:country":"GB",
    "sg:address":"29 Newick Drive, Newick",
    "sg:city":"Lewes",
    "sg:classifiers":[
        {
            "category":"Food & Beverages",
            "subcategory":"Liquor & Beverages",
            "type":"Retail Goods"
        }
    ],
    "sg:postcode":"BN8 4NY",
    "sg:province":"East Sussex",
    "sg:tags":[
        "beer",
        "spirit",
        "wines"
    ],
    "wof:name":"Corkers",
    "wof:placetype":"venue"
},
  "geometry": {"coordinates":[0.0105410004,50.9730567932],"type":"Point"}
}