{
  "type": "Feature",
  "properties": {
    "iso:country":"GB",
    "sg:address":"3 West Street, Comberton",
    "sg:city":"Cambridge",
    "sg:classifiers":[
        {
            "category":"Shopping",
            "subcategory":"News",
            "type":"Retail Goods"
        }
    ],
    "sg:postcode":"CB3 7DS",
    "sg:province":"Cambridgeshire",
    "sg:tags":[
        "newsagent"
    ],
    "wof:name":"United News Shops Ltd.",
    "wof:placetype":"venue"
},
  "geometry": {"coordinates":[0.0188159999,52.1868438721],"type":"Point"}
}