{
  "type": "Feature",
  "properties": {
    "iso:country":"GB",
    "sg:address":"Stable Yard, Brcks Farm",
    "sg:city":"Ingatestone",
    "sg:classifiers":[
        {
            "category":"Shopping",
            "subcategory":"Computers & Home Electronics",
            "type":"Retail Goods"
        }
    ],
    "sg:phone":"+44 1277 829127",
    "sg:postcode":"CM4 9PD",
    "sg:province":"Essex",
    "sg:tags":[
        "consumables"
    ],
    "wof:name":"Welrole Ltd.",
    "wof:placetype":"venue"
},
  "geometry": {"coordinates":[0.383585,51.669922],"type":"Point"}
}