{
  "type": "Feature",
  "properties": {
    "iso:country":"GB",
    "sg:address":"51 Newstead Avenue, Burbage",
    "sg:city":"Hinckley",
    "sg:classifiers":[
        {
            "category":"Home & Garden",
            "subcategory":"Garden Supply",
            "type":"Retail Goods"
        }
    ],
    "sg:postcode":"LE10 2JA",
    "sg:province":"Leicestershire",
    "sg:tags":[
        "nursery",
        "centre"
    ],
    "wof:name":"Three Pots Conifer & Heather Nursery",
    "wof:placetype":"venue"
},
  "geometry": {"coordinates":[-1.3684029579,52.5208587646],"type":"Point"}
}