{
  "type": "Feature",
  "properties": {
    "iso:country":"GB",
    "sg:address":"Times House, 50 Claremont Road",
    "sg:city":"London",
    "sg:classifiers":[
        {
            "category":"Shopping",
            "subcategory":"Stationery & Office Supplies",
            "type":"Retail Goods"
        }
    ],
    "sg:postcode":"W9 3DZ",
    "sg:province":"Greater London",
    "wof:name":"Eastkale & Co.",
    "wof:placetype":"venue"
},
  "geometry": {"coordinates":[-0.204899,51.532959],"type":"Point"}
}