{
  "type": "Feature",
  "properties": {
    "iso:country":"GB",
    "sg:address":"Homefield Rd",
    "sg:city":"Worthing",
    "sg:classifiers":[
        {
            "category":"Health Services",
            "subcategory":"Clinic",
            "type":"Services"
        }
    ],
    "sg:phone":"+44 1903 212206",
    "sg:postcode":"BN11 2HS",
    "sg:province":"West Sussex",
    "sg:tags":[
        "nh"
    ],
    "wof:name":"Greenacres Community Mental Health Centre",
    "wof:placetype":"venue"
},
  "geometry": {"coordinates":[-0.363146,50.818657],"type":"Point"}
}