{
  "type": "Feature",
  "properties": {
    "addr:full":"Tonmawr 2000 Sports Centre, Heol Hamdden, Tonmawr Port Talbot Neath Port Talbot SA12 9UU",
    "addr:postcode":"sa12 9uu",
    "addr:street":"Heol Hamdden Tonmawr Port Talbot",
    "iso:country":"GB",
    "sg:address":"Tonmawr 2000 Sports Centre, Heol Hamdden, Tonmawr",
    "sg:city":"Port Talbot",
    "sg:classifiers":[
        {
            "category":"Community Center",
            "type":"Public Place"
        }
    ],
    "sg:phone":"+44 1639 639457",
    "sg:postcode":"SA12 9UU",
    "sg:province":"Neath Port Talbot",
    "sg:tags":[
        "recreation",
        "leisure",
        "centre"
    ],
    "wof:name":"Tonmawr 2000",
    "wof:placetype":"venue"
},
  "geometry": {"coordinates":[-3.7310910225,51.6528205872],"type":"Point"}
}