{
  "type": "Feature",
  "properties": {
    "addr:full":"Salisbury Road, St Judes Plymouth Devon PL4 8QP",
    "addr:postcode":"pl4 8qp",
    "addr:street":"Salisbury Road",
    "iso:country":"GB",
    "sg:address":"Salisbury Road, St Judes",
    "sg:city":"Plymouth",
    "sg:classifiers":[
        {
            "category":"Place Of Worship",
            "type":"Public Place"
        }
    ],
    "sg:phone":"+44 1752 268925",
    "sg:postcode":"PL4 8QP",
    "sg:province":"Devon",
    "wof:name":"Salisbury Road baptist Church",
    "wof:placetype":"venue"
},
  "geometry": {"coordinates":[-4.1168241501,50.3773765564],"type":"Point"}
}