{
  "type": "Feature",
  "properties": {
    "addr:full":"6 Beech Mount Skipton North Yorkshire BD20 8NS",
    "addr:housenumber":"6",
    "addr:postcode":"bd20 8ns",
    "addr:street":"Beech Mount",
    "iso:country":"GB",
    "sg:address":"6 Beech Mount",
    "sg:city":"Skipton",
    "sg:classifiers":[
        {
            "category":"Sports & Exercise",
            "subcategory":"Golf",
            "type":"Entertainment"
        }
    ],
    "sg:phone":"+44 1535 637859",
    "sg:postcode":"BD20 8NS",
    "sg:province":"North Yorkshire",
    "sg:tags":[
        "greeting",
        "card"
    ],
    "wof:name":"Aspects Cards & Prints",
    "wof:placetype":"venue"
},
  "geometry": {"coordinates":[-2.01866,53.917809],"type":"Point"}
}