{
  "type": "Feature",
  "properties": {
    "iso:country":"GB",
    "sg:address":"Chadderton Drive",
    "sg:city":"Newcastle-upon-tyne",
    "sg:classifiers":[
        {
            "category":"Education",
            "subcategory":"School",
            "type":"Public Place"
        }
    ],
    "sg:phone":"+44 191 267 8367",
    "sg:postcode":"NE5 1EL",
    "sg:province":"Tyne and Wear",
    "sg:tags":[
        "local",
        "authority"
    ],
    "wof:name":"Chapel House Middle School",
    "wof:placetype":"venue"
},
  "geometry": {"coordinates":[-1.7200930119,55.000579834],"type":"Point"}
}