{
  "type": "Feature",
  "properties": {
    "addr:full":"Coach Drive Cambridge Cambridgeshire CB3 7EN",
    "addr:postcode":"cb3 7en",
    "addr:street":"Coach Drive",
    "iso:country":"GB",
    "sg:address":"Coach Drive",
    "sg:city":"Cambridge",
    "sg:classifiers":[
        {
            "category":"Government",
            "subcategory":"City Hall",
            "type":"Public Place"
        }
    ],
    "sg:phone":"+44 1223 264814",
    "sg:postcode":"CB3 7EN",
    "sg:province":"Cambridgeshire",
    "wof:name":"Cambridge City Council",
    "wof:placetype":"venue"
},
  "geometry": {"coordinates":[0.0253309999,52.1530990601],"type":"Point"}
}