{
  "type": "Feature",
  "properties": {
    "iso:country":"GB",
    "sg:address":"Mill Lane, Rainford",
    "sg:city":"St Helens",
    "sg:classifiers":[
        {
            "category":"Government",
            "subcategory":"Post Office",
            "type":"Public Place"
        }
    ],
    "sg:phone":"+44 1744 884008",
    "sg:postcode":"WA11 8NB",
    "sg:province":"Lancashire",
    "sg:tags":[
        "print",
        "typesetter"
    ],
    "wof:name":"N P S Phototypesetting Ltd.",
    "wof:placetype":"venue"
},
  "geometry": {"coordinates":[-2.7669639587,53.4906616211],"type":"Point"}
}