{
  "type": "Feature",
  "properties": {
    "iso:country":"GB",
    "sg:address":"Harrogate Road, Harewood",
    "sg:city":"Leeds",
    "sg:classifiers":[
        {
            "category":"Autos & Motor Vehicles",
            "subcategory":"Fuel & Gas Station",
            "type":"Retail Goods"
        }
    ],
    "sg:postcode":"LS17 9LN",
    "sg:province":"North Yorkshire",
    "sg:tags":[
        "petrol",
        "filling"
    ],
    "wof:name":"Harewood Filling Station",
    "wof:placetype":"venue"
},
  "geometry": {"coordinates":[-1.529416,53.9193],"type":"Point"}
}