{
  "type": "Feature",
  "properties": {
    "addr:full":"27 Hoxton Street London Greater London N1 6NH",
    "addr:housenumber":"27",
    "addr:postcode":"n1 6nh",
    "addr:street":"Hoxton Street",
    "iso:country":"GB",
    "sg:address":"27 Hoxton Street",
    "sg:city":"London",
    "sg:classifiers":[
        {
            "category":"Professional",
            "subcategory":"Art Services",
            "type":"Services"
        }
    ],
    "sg:phone":"+44 20 7729 5480",
    "sg:postcode":"N1 6NH",
    "sg:province":"Greater London",
    "sg:tags":[
        "graphic",
        "designer"
    ],
    "wof:name":"Gary Rowland Associates",
    "wof:placetype":"venue"
},
  "geometry": {"coordinates":[-0.080392,51.52776],"type":"Point"}
}