{
  "type": "Feature",
  "properties": {
    "addr:full":"Unit 32 Enterprise Way Newport Newport NP20 2AQ",
    "addr:housenumber":"unit 32",
    "addr:postcode":"np20 2aq",
    "addr:street":"Enterprise Way",
    "iso:country":"GB",
    "sg:address":"Unit 32 Enterprise Way",
    "sg:city":"Newport",
    "sg:classifiers":[
        {
            "category":"Professional",
            "subcategory":"Printing & Photocopies",
            "type":"Services"
        }
    ],
    "sg:phone":"+44 1633 283477",
    "sg:postcode":"NP20 2AQ",
    "sg:province":"Newport",
    "sg:tags":[
        "image",
        "processing",
        "system"
    ],
    "wof:name":"Eltham Lewis Associates",
    "wof:placetype":"venue"
},
  "geometry": {"coordinates":[-2.9862670898,51.5794487],"type":"Point"}
}