{
  "type": "Feature",
  "properties": {
    "addr:full":"11 Selborne Walk London Greater London E17 7JR",
    "addr:housenumber":"11",
    "addr:postcode":"e17 7jr",
    "addr:street":"Selborne Walk",
    "iso:country":"GB",
    "sg:address":"11 Selborne Walk",
    "sg:city":"London",
    "sg:classifiers":[
        {
            "category":"Shopping",
            "subcategory":"Clothing, Apparel, & Fashions",
            "type":"Retail Goods"
        }
    ],
    "sg:phone":"+44 20 8223 0889",
    "sg:postcode":"E17 7JR",
    "sg:province":"Greater London",
    "sg:tags":[
        "shop"
    ],
    "wof:name":"New Look Retailers Ltd.",
    "wof:placetype":"venue"
},
  "geometry": {"coordinates":[-0.024795,51.582401],"type":"Point"}
}