{
  "type": "Feature",
  "properties": {
    "iso:country":"GB",
    "sg:address":"Granville House, 49 The Mall",
    "sg:city":"Faversham",
    "sg:classifiers":[
        {
            "category":"Banks & Credit Unions",
            "subcategory":"Bank",
            "type":"Services"
        },
        {
            "category":"Banks & Credit Unions",
            "subcategory":"Financial Services",
            "type":"Services"
        }
    ],
    "sg:phone":"+44 1795 537641",
    "sg:postcode":"ME13 8JW",
    "sg:province":"Kent",
    "sg:tags":[
        "consultant",
        "institution"
    ],
    "wof:name":"M Closton",
    "wof:placetype":"venue"
},
  "geometry": {"coordinates":[0.8879470229,51.3092956543],"type":"Point"}
}