{
  "type": "Feature",
  "properties": {
    "iso:country":"GB",
    "sg:address":"53 Dartmouth Road, Willesden Green",
    "sg:city":"London",
    "sg:classifiers":[
        {
            "category":"Health Services",
            "subcategory":"Dentist",
            "type":"Services"
        }
    ],
    "sg:postcode":"NW2 4EP",
    "sg:province":"Greater London",
    "wof:name":"The Dental Practice",
    "wof:placetype":"venue"
},
  "geometry": {"coordinates":[-0.2115460038,51.5483818054],"type":"Point"}
}