{
  "type": "Feature",
  "properties": {
    "iso:country":"GB",
    "sg:address":"5 Avenue Road",
    "sg:city":"Wymondham",
    "sg:classifiers":[
        {
            "category":"Building & Trades",
            "subcategory":"Cleaning & Sanitation",
            "type":"Services"
        },
        {
            "category":"Social Services",
            "subcategory":"Adult Care",
            "type":"Services"
        }
    ],
    "sg:phone":"+44 1953 606286",
    "sg:postcode":"NR18 0QF",
    "sg:province":"Norfolk",
    "sg:tags":[
        "cleaner",
        "upholstery",
        "domestic",
        "carpet"
    ],
    "wof:name":"ACADEMY CLEANING SERVICES",
    "wof:placetype":"venue"
},
  "geometry": {"coordinates":[1.116561,52.569778],"type":"Point"}
}