{
  "type": "Feature",
  "properties": {
    "addr:full":"Farm Buildings, Hillhouse La Horsham West Sussex RH12 3BD",
    "addr:postcode":"rh12 3bd",
    "addr:street":"La Horsham",
    "iso:country":"GB",
    "sg:address":"Farm Buildings, Hillhouse La",
    "sg:city":"Horsham",
    "sg:classifiers":[
        {
            "category":"Home & Garden",
            "subcategory":"Building Materials",
            "type":"Retail Goods"
        }
    ],
    "sg:phone":"+44 1403 823653",
    "sg:postcode":"RH12 3BD",
    "sg:province":"West Sussex",
    "sg:tags":[
        "fencing"
    ],
    "wof:name":"A Covey",
    "wof:placetype":"venue"
},
  "geometry": {"coordinates":[-0.348785013,51.0887756348],"type":"Point"}
}