{
  "type": "Feature",
  "properties": {
    "addr:full":"139 Goldhawk Road London Greater London W12 8EW",
    "addr:housenumber":"139",
    "addr:postcode":"w12 8ew",
    "addr:street":"Goldhawk Road",
    "iso:country":"GB",
    "sg:address":"139 Goldhawk Road",
    "sg:city":"London",
    "sg:classifiers":[
        {
            "category":"Autos & Motor Vehicles",
            "subcategory":"Auto Supplies",
            "type":"Retail Goods"
        }
    ],
    "sg:postcode":"W12 8EW",
    "sg:province":"Greater London",
    "sg:tags":[
        "component"
    ],
    "wof:name":"Pal Auto Factors",
    "wof:placetype":"venue"
},
  "geometry": {"coordinates":[-0.2312400043,51.5013656616],"type":"Point"}
}