{
  "type": "Feature",
  "properties": {
    "addr:full":"Market House, 109 Guildford Street Chertsey Surrey KT16 9AS",
    "addr:housenumber":"109",
    "addr:postcode":"kt16 9as",
    "addr:street":"Guildford Street",
    "iso:country":"GB",
    "sg:address":"Market House, 109 Guildford Street",
    "sg:city":"Chertsey",
    "sg:classifiers":[
        {
            "category":"Professional",
            "subcategory":"Accounting & Tax Preparation",
            "type":"Services"
        }
    ],
    "sg:phone":"+44 1932 570044",
    "sg:postcode":"KT16 9AS",
    "sg:province":"Surrey",
    "sg:tags":[
        "accountant"
    ],
    "wof:name":"N S Associates",
    "wof:placetype":"venue"
},
  "geometry": {"coordinates":[-0.5047219992,51.3912467957],"type":"Point"}
}