{
  "type": "Feature",
  "properties": {
    "iso:country":"GB",
    "sg:address":"Station Road, Purton",
    "sg:city":"Swindon",
    "sg:classifiers":[
        {
            "category":"Shopping",
            "subcategory":"Bicycles & Sporting Goods",
            "type":"Retail Goods"
        },
        {
            "category":"Shopping",
            "subcategory":"Pets & Pet Supplies",
            "type":"Retail Goods"
        }
    ],
    "sg:phone":"+44 1793 770613",
    "sg:postcode":"SN5 4AH",
    "sg:province":"Wiltshire",
    "sg:tags":[
        "riding",
        "saddlery",
        "equestrian",
        "wear"
    ],
    "wof:name":"Elmgrove Saddlery",
    "wof:placetype":"venue"
},
  "geometry": {"coordinates":[-1.866154,51.588913],"type":"Point"}
}