{
  "type": "Feature",
  "properties": {
    "addr:full":"5 Sandhurst Market, Catford London Greater London SE6 2BG",
    "addr:housenumber":"5",
    "addr:postcode":"se6 2bg",
    "addr:street":"Sandhurst Market Catford",
    "iso:country":"GB",
    "sg:address":"5 Sandhurst Market, Catford",
    "sg:city":"London",
    "sg:classifiers":[
        {
            "category":"Fast Food",
            "type":"Food & Drink"
        }
    ],
    "sg:postcode":"SE6 2BG",
    "sg:province":"Greater London",
    "sg:tags":[
        "away",
        "take"
    ],
    "wof:name":"S Ratnayake",
    "wof:placetype":"venue"
},
  "geometry": {"coordinates":[-0.0096819997,51.442237854],"type":"Point"}
}