{
  "type": "Feature",
  "properties": {
    "iso:country":"GB",
    "sg:address":"4 Moorfields Highwalk",
    "sg:city":"London",
    "sg:classifiers":[
        {
            "category":"Personal",
            "subcategory":"Beauty Salon",
            "type":"Services"
        }
    ],
    "sg:postcode":"EC2Y 5EE",
    "sg:province":"Greater London",
    "sg:tags":[
        "unisex",
        "hairdresser"
    ],
    "wof:name":"Changes",
    "wof:placetype":"venue"
},
  "geometry": {"coordinates":[-0.089354,51.51804],"type":"Point"}
}