{
  "type": "Feature",
  "properties": {
    "addr:full":"2-4 New Quay Street Campbeltown Argyll and Bute PA28 6BD",
    "addr:housenumber":"2-4",
    "addr:postcode":"pa28 6bd",
    "addr:street":"New Quay Street",
    "iso:country":"GB",
    "sg:address":"2-4 New Quay Street",
    "sg:city":"Campbeltown",
    "sg:classifiers":[
        {
            "category":"Professional",
            "subcategory":"Employment Agencies",
            "type":"Services"
        }
    ],
    "sg:phone":"+44 1586 559220",
    "sg:postcode":"PA28 6BD",
    "sg:province":"Argyll and Bute",
    "sg:tags":[
        "consultant"
    ],
    "wof:name":"Jobcentre Plus",
    "wof:placetype":"venue"
},
  "geometry": {"coordinates":[-5.601169,55.423164],"type":"Point"}
}