{
  "type": "Feature",
  "properties": {
    "iso:country":"GB",
    "sg:address":"95 Church La, Sholden",
    "sg:city":"Deal",
    "sg:classifiers":[
        {
            "category":"Home & Garden",
            "subcategory":"Carpets & Floor Coverings",
            "type":"Retail Goods"
        }
    ],
    "sg:postcode":"CT14 9QL",
    "sg:province":"Kent",
    "sg:tags":[
        "carpets",
        "rug",
        "matting"
    ],
    "wof:name":"Lawson,Karl,",
    "wof:placetype":"venue"
},
  "geometry": {"coordinates":[1.383222,51.221485],"type":"Point"}
}