{
  "type": "Feature",
  "properties": {
    "iso:country":"GB",
    "sg:address":"St Olaves, Hampers Lane, Storrington",
    "sg:city":"Pulborough",
    "sg:classifiers":[
        {
            "category":"Shopping",
            "subcategory":"Crafts & Fabrics",
            "type":"Retail Goods"
        }
    ],
    "sg:postcode":"RH20 3HZ",
    "sg:province":"West Sussex",
    "sg:tags":[
        "machine",
        "sewing",
        "knitting"
    ],
    "wof:name":"Brian Stow",
    "wof:placetype":"venue"
},
  "geometry": {"coordinates":[-0.5118790269,50.9570770264],"type":"Point"}
}