{
  "type": "Feature",
  "properties": {
    "addr:full":"54 Croydon Rd Caterham Surrey CR3 6QB",
    "addr:housenumber":"54",
    "addr:postcode":"cr3 6qb",
    "addr:street":"Croydon Rd",
    "iso:country":"GB",
    "sg:address":"54 Croydon Rd",
    "sg:city":"Caterham",
    "sg:classifiers":[
        {
            "category":"Manufacturing",
            "subcategory":"Paper Products",
            "type":"Manufacturing & Wholesale Goods"
        }
    ],
    "sg:phone":"+44 1883 349456",
    "sg:postcode":"CR3 6QB",
    "sg:province":"Surrey",
    "sg:tags":[
        "build",
        "plastic"
    ],
    "wof:name":"Surrey Foam",
    "wof:placetype":"venue"
},
  "geometry": {"coordinates":[-0.07847,51.283966],"type":"Point"}
}