{
  "type": "Feature",
  "properties": {
    "addr:full":"83 Derby Road Salford Greater Manchester M5 2LE",
    "addr:housenumber":"83",
    "addr:postcode":"m5 2le",
    "addr:street":"Derby Road",
    "iso:country":"GB",
    "sg:address":"83 Derby Road",
    "sg:city":"Salford",
    "sg:classifiers":[
        {
            "category":"Professional",
            "subcategory":"Engineering",
            "type":"Services"
        }
    ],
    "sg:phone":"+44 161 737 7026",
    "sg:postcode":"M5 2LE",
    "sg:province":"Greater Manchester",
    "sg:tags":[
        "contractor",
        "electrical",
        "engineer"
    ],
    "wof:name":"Thomas William Hicks",
    "wof:placetype":"venue"
},
  "geometry": {"coordinates":[-2.301166,53.485985],"type":"Point"}
}