{
  "type": "Feature",
  "properties": {
    "addr:full":"Unit 58, Rowfant Business Centre, Wallage Lane Crawley Surrey RH10 4NG",
    "addr:housenumber":"unit 58",
    "addr:postcode":"rh10 4ng",
    "addr:street":"Rowfant Business;Wallage Lane",
    "iso:country":"GB",
    "sg:address":"Unit 58, Rowfant Business Centre, Wallage Lane",
    "sg:city":"Crawley",
    "sg:classifiers":[
        {
            "category":"Building & Trades",
            "subcategory":"Construction",
            "type":"Services"
        }
    ],
    "sg:phone":"+44 1342 717776",
    "sg:postcode":"RH10 4NG",
    "sg:province":"Surrey",
    "sg:tags":[
        "platform",
        "work",
        "scaffolding"
    ],
    "wof:name":"Worth Scaffolding Co.",
    "wof:placetype":"venue"
},
  "geometry": {"coordinates":[-0.0860290006,51.12292099],"type":"Point"}
}