{
  "type": "Feature",
  "properties": {
    "iso:country":"GB",
    "sg:address":"Queens Chambers, 2 North Street",
    "sg:city":"Newport",
    "sg:classifiers":[
        {
            "category":"Building & Trades",
            "subcategory":"Landscaping Services",
            "type":"Services"
        }
    ],
    "sg:phone":"+44 1633 212322",
    "sg:postcode":"NP20 1JZ",
    "sg:province":"Newport",
    "sg:tags":[
        "contractor",
        "drainage"
    ],
    "wof:name":"Caldicot & Wentloog Level Drainage Board",
    "wof:placetype":"venue"
},
  "geometry": {"coordinates":[-2.99794,51.586979],"type":"Point"}
}