{
  "type": "Feature",
  "properties": {
    "addr:full":"20 Southover Street Brighton East Sussex BN2 9UD",
    "addr:postcode":"bn2 9ud",
    "addr:street":"Southover Street",
    "iso:country":"GB",
    "sg:address":"20 Southover Street",
    "sg:city":"Brighton",
    "sg:classifiers":[
        {
            "category":"Fast Food",
            "type":"Food & Drink"
        }
    ],
    "sg:phone":"+44 1273 676867",
    "sg:postcode":"BN2 9UD",
    "sg:province":"East Sussex",
    "sg:tags":[
        "away",
        "take"
    ],
    "wof:name":"Famous Moe's Food Service Ltd.",
    "wof:placetype":"venue"
},
  "geometry": {"coordinates":[-0.1299960017,50.8290557861],"type":"Point"}
}