{
  "type": "Feature",
  "properties": {
    "addr:full":"Unit 2 Guardian Park, Station Estate Tadcaster North Yorkshire LS24 9SG",
    "addr:housenumber":"unit 2",
    "addr:postcode":"ls24 9sg",
    "addr:street":"Guardian Park;Estate",
    "iso:country":"GB",
    "sg:address":"Unit 2 Guardian Park, Station Estate",
    "sg:city":"Tadcaster",
    "sg:classifiers":[
        {
            "category":"Shopping",
            "subcategory":"Clothing, Apparel, & Fashions",
            "type":"Retail Goods"
        }
    ],
    "sg:phone":"+44 1937 531611",
    "sg:postcode":"LS24 9SG",
    "sg:province":"North Yorkshire",
    "sg:tags":[
        "mnfr",
        "staff",
        "wear",
        "uniform"
    ],
    "wof:name":"M D Staffwear",
    "wof:placetype":"venue"
},
  "geometry": {"coordinates":[-1.266114,53.882275],"type":"Point"}
}