{
  "type": "Feature",
  "properties": {
    "addr:full":"363a Lytham Road Blackpool Lancashire FY4 1EA",
    "addr:housenumber":"363a",
    "addr:postcode":"fy4 1ea",
    "addr:street":"Lytham Road",
    "iso:country":"GB",
    "sg:address":"363a Lytham Road",
    "sg:city":"Blackpool",
    "sg:classifiers":[
        {
            "category":"Autos & Motor Vehicles",
            "subcategory":"Motorcycle Sales",
            "type":"Retail Goods"
        }
    ],
    "sg:phone":"+44 1253 408288",
    "sg:postcode":"FY4 1EA",
    "sg:province":"Lancashire",
    "wof:name":"Esoteric Motor Cycle Paint Work",
    "wof:placetype":"venue"
},
  "geometry": {"coordinates":[-3.0497150421,53.794128418],"type":"Point"}
}