{
  "type": "Feature",
  "properties": {
    "addr:full":"21 Osborne Rd, Formby Liverpool Lancashire L37 6AR",
    "addr:housenumber":"21",
    "addr:postcode":"l37 6ar",
    "addr:street":"Osborne Rd",
    "iso:country":"GB",
    "sg:address":"21 Osborne Rd, Formby",
    "sg:city":"Liverpool",
    "sg:classifiers":[
        {
            "category":"Professional",
            "subcategory":"Business Services",
            "type":"Services"
        }
    ],
    "sg:postcode":"L37 6AR",
    "sg:province":"Lancashire",
    "sg:tags":[
        "import",
        "export",
        "agent"
    ],
    "wof:name":"Conroy,Dennis,",
    "wof:placetype":"venue"
},
  "geometry": {"coordinates":[-3.0664858818,53.5471763611],"type":"Point"}
}