{
  "type": "Feature",
  "properties": {
    "addr:full":"Grove Road Lymington Hampshire SO41 3RF",
    "addr:postcode":"so41 3rf",
    "addr:street":"Grove Road",
    "iso:country":"GB",
    "sg:address":"Grove Road",
    "sg:city":"Lymington",
    "sg:classifiers":[
        {
            "category":"Manufacturing",
            "subcategory":"Building Materials",
            "type":"Manufacturing & Wholesale Goods"
        }
    ],
    "sg:phone":"+44 1590 672277",
    "sg:postcode":"SO41 3RF",
    "sg:province":"Hampshire",
    "sg:tags":[
        "merchant",
        "builder"
    ],
    "wof:name":"Travis Perkins Trading Co.  Ltd.",
    "wof:placetype":"venue"
},
  "geometry": {"coordinates":[-1.5395020247,50.7562026978],"type":"Point"}
}