{
  "type": "Feature",
  "properties": {
    "iso:country":"GB",
    "sg:address":"48 High St",
    "sg:city":"Harpenden",
    "sg:classifiers":[
        {
            "category":"Shopping",
            "subcategory":"Clothing, Apparel, & Fashions",
            "type":"Retail Goods"
        }
    ],
    "sg:postcode":"AL5 2SX",
    "sg:province":"Hertfordshire",
    "sg:tags":[
        "dresswear"
    ],
    "wof:name":"Moss Bros Group Plc",
    "wof:placetype":"venue"
},
  "geometry": {"coordinates":[-0.35682,51.816219],"type":"Point"}
}