{
  "type": "Feature",
  "properties": {
    "addr:full":"5 Wellington Road Blackpool Lancashire FY1 6AR",
    "addr:housenumber":"5",
    "addr:postcode":"fy1 6ar",
    "addr:street":"Wellington Road",
    "iso:country":"GB",
    "sg:address":"5 Wellington Road",
    "sg:city":"Blackpool",
    "sg:classifiers":[
        {
            "category":"Travel",
            "subcategory":"Hotels & Motels",
            "type":"Entertainment"
        }
    ],
    "sg:postcode":"FY1 6AR",
    "sg:province":"Lancashire",
    "wof:name":"Chesterfield Hotel",
    "wof:placetype":"venue"
},
  "geometry": {"coordinates":[-3.054143,53.80389],"type":"Point"}
}