{
  "type": "Feature",
  "properties": {
    "iso:country":"GB",
    "sg:address":"Fish Shop",
    "sg:city":"Snodland",
    "sg:classifiers":[
        {
            "category":"Food & Beverages",
            "subcategory":"Meat & Fish",
            "type":"Retail Goods"
        }
    ],
    "sg:phone":"+44 1634 240308",
    "sg:postcode":"ME6 5EE",
    "sg:province":"Kent",
    "sg:tags":[
        "chip"
    ],
    "wof:name":"Pete's Place",
    "wof:placetype":"venue"
},
  "geometry": {"coordinates":[0.446165,51.327026],"type":"Point"}
}