{
  "type": "Feature",
  "properties": {
    "addr:full":"14a Wesley Street, Rodley Leeds West Yorkshire LS13 1JH",
    "addr:housenumber":"14a",
    "addr:postcode":"ls13 1jh",
    "addr:street":"Wesley Street",
    "iso:country":"GB",
    "sg:address":"14a Wesley Street, Rodley",
    "sg:city":"Leeds",
    "sg:classifiers":[
        {
            "category":"Shopping",
            "subcategory":"Baby Store",
            "type":"Retail Goods"
        },
        {
            "category":"Home & Garden",
            "subcategory":"Building Materials",
            "type":"Retail Goods"
        }
    ],
    "sg:phone":"+44 113 236 2241",
    "sg:postcode":"LS13 1JH",
    "sg:province":"West Yorkshire",
    "sg:tags":[
        "fencing",
        "nursery",
        "accessory"
    ],
    "wof:name":"Outdoor Maintenance",
    "wof:placetype":"venue"
},
  "geometry": {"coordinates":[-1.6594049931,53.8221626282],"type":"Point"}
}