{
  "type": "Feature",
  "properties": {
    "addr:full":"Rockcliffe Dalbeattie Dumfries and Galloway DG5 4QF",
    "addr:postcode":"dg5 4qf",
    "iso:country":"GB",
    "sg:address":"Rockcliffe",
    "sg:city":"Dalbeattie",
    "sg:classifiers":[
        {
            "category":"Travel",
            "subcategory":"Hotels & Motels",
            "type":"Entertainment"
        }
    ],
    "sg:phone":"+44 1556 630225",
    "sg:postcode":"DG5 4QF",
    "sg:province":"Dumfries and Galloway",
    "wof:name":"Barons Craig Hotel",
    "wof:placetype":"venue"
},
  "geometry": {"coordinates":[-3.8178989887,54.9140014648],"type":"Point"}
}