{
  "type": "Feature",
  "properties": {
    "addr:full":"20 High Street, Little Paxton St Neots Bedfordshire PE19 6HA",
    "addr:housenumber":"20",
    "addr:postcode":"pe19 6ha",
    "addr:street":"High Street",
    "iso:country":"GB",
    "sg:address":"20 High Street, Little Paxton",
    "sg:city":"St Neots",
    "sg:classifiers":[
        {
            "category":"Farming",
            "subcategory":"Nursery",
            "type":"Manufacturing & Wholesale Goods"
        }
    ],
    "sg:phone":"+44 1480 212171",
    "sg:postcode":"PE19 6HA",
    "sg:province":"Bedfordshire",
    "sg:tags":[
        "creche"
    ],
    "wof:name":"Cherubs Kindergarten",
    "wof:placetype":"venue"
},
  "geometry": {"coordinates":[-0.173599,52.260639],"type":"Point"}
}