{
  "type": "Feature",
  "properties": {
    "iso:country":"GB",
    "sg:address":"151 Charing Cross Road",
    "sg:city":"London",
    "sg:classifiers":[
        {
            "category":"Shopping",
            "subcategory":"Shoes",
            "type":"Retail Goods"
        }
    ],
    "sg:phone":"+44 20 7437 5275",
    "sg:postcode":"WC2H 0EE",
    "sg:province":"Greater London",
    "sg:tags":[
        "shop"
    ],
    "wof:name":"Office London",
    "wof:placetype":"venue"
},
  "geometry": {"coordinates":[-0.130496,51.515911],"type":"Point"}
}