{
  "type": "Feature",
  "properties": {
    "iso:country":"GB",
    "sg:address":"2a Curzon Road, Ealing",
    "sg:city":"London",
    "sg:classifiers":[
        {
            "category":"Retail",
            "subcategory":"Auto Repair",
            "type":"Services"
        }
    ],
    "sg:phone":"+44 20 8997 5044",
    "sg:postcode":"W5 1NF",
    "sg:province":"Greater London",
    "sg:tags":[
        "modification",
        "garage"
    ],
    "wof:name":"Curzon Road Garage Ltd.",
    "wof:placetype":"venue"
},
  "geometry": {"coordinates":[-0.31626001,51.5258216858],"type":"Point"}
}