{
  "type": "Feature",
  "properties": {
    "iso:country":"GB",
    "sg:address":"Pentrefoelas",
    "sg:city":"Betws-y-coed",
    "sg:classifiers":[
        {
            "category":"Travel",
            "subcategory":"Hotels & Motels",
            "type":"Entertainment"
        }
    ],
    "sg:phone":"+44 1690 770213",
    "sg:postcode":"LL24 0HT",
    "sg:province":"Conwy",
    "wof:name":"Foelas Arms Hotel",
    "wof:placetype":"venue"
},
  "geometry": {"coordinates":[-3.8045489788,53.0942611694],"type":"Point"}
}