{
  "type": "Feature",
  "properties": {
    "addr:full":"Great North Road, Brookmans Park Hatfield Hertfordshire AL9 6ND",
    "addr:postcode":"al9 6nd",
    "addr:street":"Great North Road",
    "iso:country":"GB",
    "sg:address":"Great North Road, Brookmans Park",
    "sg:city":"Hatfield",
    "sg:classifiers":[
        {
            "category":"Building & Trades",
            "subcategory":"Landscaping Services",
            "type":"Services"
        },
        {
            "category":"Home & Garden",
            "subcategory":"Garden Supply",
            "type":"Retail Goods"
        }
    ],
    "sg:phone":"+44 1707 653372",
    "sg:postcode":"AL9 6ND",
    "sg:province":"Hertfordshire",
    "sg:tags":[
        "nursery",
        "designer",
        "architect",
        "landscape",
        "centre"
    ],
    "wof:name":"The Dutch Nursery Ltd.",
    "wof:placetype":"venue"
},
  "geometry": {"coordinates":[-0.177275,51.725746],"type":"Point"}
}