{
  "type": "Feature",
  "properties": {
    "iso:country":"GB",
    "sg:address":"62 Hamilton Place",
    "sg:city":"Edinburgh",
    "sg:classifiers":[
        {
            "category":"Shopping",
            "subcategory":"Books",
            "type":"Retail Goods"
        }
    ],
    "sg:postcode":"EH3 5AZ",
    "sg:province":"City of Edinburgh",
    "sg:tags":[
        "bookseller",
        "retailer"
    ],
    "wof:name":"Rhodawn Ltd.",
    "wof:placetype":"venue"
},
  "geometry": {"coordinates":[-3.2074739933,55.9589576721],"type":"Point"}
}