{
  "type": "Feature",
  "properties": {
    "addr:full":"26 Barbot Close, Edmonton Lower Edmonton Greater London N9 9XW",
    "addr:housenumber":"26",
    "addr:postcode":"n9 9xw",
    "addr:street":"Barbot Close",
    "iso:country":"GB",
    "sg:address":"26 Barbot Close, Edmonton",
    "sg:city":"Lower Edmonton",
    "sg:classifiers":[
        {
            "category":"Building & Trades",
            "subcategory":"Construction",
            "type":"Services"
        }
    ],
    "sg:phone":"+44 20 8887 0723",
    "sg:postcode":"N9 9XW",
    "sg:province":"Greater London",
    "sg:tags":[
        "builder"
    ],
    "wof:name":"A.Lltight",
    "wof:placetype":"venue"
},
  "geometry": {"coordinates":[-0.0638799965,51.6210861206],"type":"Point"}
}