{
  "type": "Feature",
  "properties": {
    "addr:full":"Leighton Industrial Park, Billington Road Leighton Buzzard Bedfordshire LU7 4AJ",
    "addr:postcode":"lu7 4aj",
    "addr:street":"Industrial Park Billington Road",
    "iso:country":"GB",
    "sg:address":"Leighton Industrial Park, Billington Road",
    "sg:city":"Leighton Buzzard",
    "sg:classifiers":[
        {
            "category":"Social Services",
            "type":"Services"
        }
    ],
    "sg:phone":"+44 1525 218146",
    "sg:postcode":"LU7 4AJ",
    "sg:province":"Bedfordshire",
    "sg:tags":[
        "disability"
    ],
    "wof:name":"Med-I-Pant (U K) Ltd.",
    "wof:placetype":"venue"
},
  "geometry": {"coordinates":[-0.6376489997,51.9142990112],"type":"Point"}
}