{
  "type": "Feature",
  "properties": {
    "addr:full":"5 Hustlergate Bradford West Yorkshire BD1 1RE",
    "addr:housenumber":"5",
    "addr:postcode":"bd1 1re",
    "addr:street":"Hustlergate Bradford West",
    "iso:country":"GB",
    "sg:address":"5 Hustlergate",
    "sg:city":"Bradford",
    "sg:classifiers":[
        {
            "category":"Personal",
            "subcategory":"Beauty Salon",
            "type":"Services"
        }
    ],
    "sg:phone":"+44 1274 723250",
    "sg:postcode":"BD1 1RE",
    "sg:province":"West Yorkshire",
    "sg:tags":[
        "unisex",
        "hairdresser"
    ],
    "wof:name":"Excellent",
    "wof:placetype":"venue"
},
  "geometry": {"coordinates":[-1.7528820038,53.7943611145],"type":"Point"}
}