{
  "type": "Feature",
  "properties": {
    "iso:country":"GB",
    "sg:address":"Kilrea Close",
    "sg:city":"Liverpool",
    "sg:classifiers":[
        {
            "category":"Social Services",
            "subcategory":"Adult Care",
            "type":"Services"
        },
        {
            "category":"Social Services",
            "subcategory":"Retirement Home",
            "type":"Services"
        }
    ],
    "sg:phone":"+44 151 256 6277",
    "sg:postcode":"L11 8NX",
    "sg:province":"Merseyside",
    "sg:tags":[
        "housing",
        "sheltered",
        "accommodation"
    ],
    "wof:name":"Kilrea Lodge",
    "wof:placetype":"venue"
},
  "geometry": {"coordinates":[-2.9256470203,53.436832428],"type":"Point"}
}