{
  "type": "Feature",
  "properties": {
    "iso:country":"GB",
    "sg:address":"Neville Road, Gargrave",
    "sg:city":"Skipton",
    "sg:classifiers":[
        {
            "category":"Education",
            "subcategory":"School",
            "type":"Public Place"
        },
        {
            "category":"Government",
            "subcategory":"Office",
            "type":"Public Place"
        }
    ],
    "sg:phone":"+44 1756 749433",
    "sg:postcode":"BD23 3RE",
    "sg:province":"Lancashire",
    "sg:tags":[
        "local",
        "authority"
    ],
    "wof:name":"Gargrave C of E Primary School",
    "wof:placetype":"venue"
},
  "geometry": {"coordinates":[-2.106344,53.983109],"type":"Point"}
}