{
  "type": "Feature",
  "properties": {
    "addr:full":"25a Fashion St Whitechapel Greater London E1 6PX",
    "addr:housenumber":"25a",
    "addr:postcode":"e1 6px",
    "addr:street":"Fashion St",
    "iso:country":"GB",
    "sg:address":"25a Fashion St",
    "sg:city":"Whitechapel",
    "sg:classifiers":[
        {
            "category":"Shopping",
            "subcategory":"Clothing, Apparel, & Fashions",
            "type":"Retail Goods"
        }
    ],
    "sg:phone":"+44 20 7247 0602",
    "sg:postcode":"E1 6PX",
    "sg:province":"Greater London",
    "sg:tags":[
        "clothing"
    ],
    "wof:name":"Fashion Street Warehouse Ltd",
    "wof:placetype":"venue"
},
  "geometry": {"coordinates":[-0.0734340027,51.5185432434],"type":"Point"}
}