{
  "type": "Feature",
  "properties": {
    "addr:full":"107 The Highway Pontypool Monmouthshire NP4 0PJ",
    "addr:housenumber":"107",
    "addr:postcode":"np4 0pj",
    "addr:street":"The Highway",
    "iso:country":"GB",
    "sg:address":"107 The Highway",
    "sg:city":"Pontypool",
    "sg:classifiers":[
        {
            "category":"Retail",
            "subcategory":"Funeral Services",
            "type":"Services"
        }
    ],
    "sg:postcode":"NP4 0PJ",
    "sg:province":"Monmouthshire",
    "wof:name":"Davies,H M J,",
    "wof:placetype":"venue"
},
  "geometry": {"coordinates":[-2.9907650948,51.6981315613],"type":"Point"}
}