{
  "type": "Feature",
  "properties": {
    "addr:full":"266 Oystermouth Road Swansea Neath Port Talbot SA1 3UH",
    "addr:housenumber":"266",
    "addr:postcode":"sa1 3uh",
    "addr:street":"Oystermouth Road",
    "iso:country":"GB",
    "sg:address":"266 Oystermouth Road",
    "sg:city":"Swansea",
    "sg:classifiers":[
        {
            "category":"Travel",
            "subcategory":"Hotels & Motels",
            "type":"Entertainment"
        }
    ],
    "sg:phone":"+44 1792 653859",
    "sg:postcode":"SA1 3UH",
    "sg:province":"Neath Port Talbot",
    "sg:tags":[
        "house",
        "guest"
    ],
    "wof:name":"Sandpiper Guest House",
    "wof:placetype":"venue"
},
  "geometry": {"coordinates":[-3.9529030323,51.613899231],"type":"Point"}
}