{
  "type": "Feature",
  "properties": {
    "iso:country":"GB",
    "sg:address":"137a George Street",
    "sg:city":"Edinburgh",
    "sg:classifiers":[
        {
            "category":"Real Estate",
            "subcategory":"Surveying",
            "type":"Services"
        }
    ],
    "sg:phone":"+44 131 220 3220",
    "sg:postcode":"EH2 4JY",
    "sg:province":"City of Edinburgh",
    "sg:tags":[
        "surveyor",
        "valuer"
    ],
    "wof:name":"Fisher Wilson (Scotland) Ltd.",
    "wof:placetype":"venue"
},
  "geometry": {"coordinates":[-3.2065289021,55.9520454407],"type":"Point"}
}