{
  "type": "Feature",
  "properties": {
    "addr:full":"Handley House, 7 North Gate Newark Nottinghamshire NG24 1EH",
    "addr:housenumber":"handley;7",
    "addr:postcode":"ng24 1eh",
    "addr:street":"North Gate",
    "iso:country":"GB",
    "sg:address":"Handley House, 7 North Gate",
    "sg:city":"Newark",
    "sg:classifiers":[
        {
            "category":"Real Estate",
            "subcategory":"Architect",
            "type":"Services"
        }
    ],
    "sg:phone":"+44 1636 672356",
    "sg:postcode":"NG24 1EH",
    "sg:province":"Nottinghamshire",
    "sg:tags":[
        "architectural"
    ],
    "wof:name":"GORDON BENOY & PARTNERS (SERVICES) COMPANY LTD",
    "wof:placetype":"venue"
},
  "geometry": {"coordinates":[-0.808701,53.07959],"type":"Point"}
}