{
  "type": "Feature",
  "properties": {
    "iso:country":"GB",
    "sg:address":"New House, Cheltenham Road, Bisley",
    "sg:city":"Stroud",
    "sg:classifiers":[
        {
            "category":"Professional",
            "subcategory":"Art Services",
            "type":"Services"
        }
    ],
    "sg:postcode":"GL6 7BL",
    "sg:province":"Gloucestershire",
    "sg:tags":[
        "consultant",
        "design"
    ],
    "wof:name":"T C D B Design Consultants",
    "wof:placetype":"venue"
},
  "geometry": {"coordinates":[-2.1404619217,51.7529220581],"type":"Point"}
}