{
  "type": "Feature",
  "properties": {
    "addr:full":"286 Acklam Rd Ladbroke Grove Greater London W10 5QZ",
    "addr:housenumber":"286",
    "addr:postcode":"w10 5qz",
    "addr:street":"Acklam Rd",
    "iso:country":"GB",
    "sg:address":"286 Acklam Rd",
    "sg:city":"Ladbroke Grove",
    "sg:classifiers":[
        {
            "category":"Shopping",
            "subcategory":"Gifts & Souvenirs",
            "type":"Retail Goods"
        }
    ],
    "sg:phone":"+44 20 8964 1956",
    "sg:postcode":"W10 5QZ",
    "sg:province":"Greater London",
    "sg:tags":[
        "giftware"
    ],
    "wof:name":"B & N London",
    "wof:placetype":"venue"
},
  "geometry": {"coordinates":[-0.213459,51.523285],"type":"Point"}
}