{
  "type": "Feature",
  "properties": {
    "iso:country":"GB",
    "sg:address":"59 Barnwood Road",
    "sg:city":"Gloucester",
    "sg:classifiers":[
        {
            "category":"Building & Trades",
            "subcategory":"Construction",
            "type":"Services"
        }
    ],
    "sg:phone":"+44 1452 331850",
    "sg:postcode":"GL2 0SF",
    "sg:province":"Gloucestershire",
    "sg:tags":[
        "decorator",
        "painter"
    ],
    "wof:name":"Help Painter & Decorator",
    "wof:placetype":"venue"
},
  "geometry": {"coordinates":[-2.216731,51.865494],"type":"Point"}
}