{
  "type": "Feature",
  "properties": {
    "iso:country":"GB",
    "sg:address":"20 Chart Downs",
    "sg:city":"Dorking",
    "sg:classifiers":[
        {
            "category":"Building & Trades",
            "subcategory":"Construction",
            "type":"Services"
        }
    ],
    "sg:phone":"+44 1306 876747",
    "sg:postcode":"RH5 4DH",
    "sg:province":"Surrey",
    "sg:tags":[
        "builder"
    ],
    "wof:name":"J.J Quinn",
    "wof:placetype":"venue"
},
  "geometry": {"coordinates":[-0.316901,51.218197],"type":"Point"}
}