{
  "type": "Feature",
  "properties": {
    "addr:full":"90 Tavistock Street Bedford Bedfordshire MK40 2RX",
    "addr:housenumber":"90",
    "addr:postcode":"mk40 2rx",
    "addr:street":"Tavistock Street",
    "iso:country":"GB",
    "sg:address":"90 Tavistock Street",
    "sg:city":"Bedford",
    "sg:classifiers":[
        {
            "category":"Fast Food",
            "type":"Food & Drink"
        }
    ],
    "sg:phone":"+44 1234 217866",
    "sg:postcode":"MK40 2RX",
    "sg:province":"Bedfordshire",
    "sg:tags":[
        "away",
        "take"
    ],
    "wof:name":"Vijays Tandoori",
    "wof:placetype":"venue"
},
  "geometry": {"coordinates":[-0.4729090035,52.1413993835],"type":"Point"}
}