{
  "type": "Feature",
  "properties": {
    "addr:full":"16 Ryefields, Scholes Huddersfield South Yorkshire HD9 1XF",
    "addr:housenumber":"16",
    "addr:postcode":"hd9 1xf",
    "addr:street":"Ryefields Scholes",
    "iso:country":"GB",
    "sg:address":"16 Ryefields, Scholes",
    "sg:city":"Huddersfield",
    "sg:classifiers":[
        {
            "category":"Arts & Performance",
            "subcategory":"Music",
            "type":"Entertainment"
        }
    ],
    "sg:phone":"+44 1484 685513",
    "sg:postcode":"HD9 1XF",
    "sg:province":"South Yorkshire",
    "sg:tags":[
        "mobile",
        "disco"
    ],
    "wof:name":"Simms Discotheque",
    "wof:placetype":"venue"
},
  "geometry": {"coordinates":[-1.7635339499,53.5634460449],"type":"Point"}
}