{
  "type": "Feature",
  "properties": {
    "addr:full":"2 Palace Buildings, Grand Parade North Shields Tyne and Wear NE30 4JS",
    "addr:housenumber":"2",
    "addr:postcode":"ne30 4js",
    "addr:street":"Palace Buildings Grand Parade",
    "iso:country":"GB",
    "sg:address":"2 Palace Buildings, Grand Parade",
    "sg:city":"North Shields",
    "sg:classifiers":[
        {
            "category":"Shopping",
            "subcategory":"Gifts & Souvenirs",
            "type":"Retail Goods"
        }
    ],
    "sg:postcode":"NE30 4JS",
    "sg:province":"Tyne and Wear",
    "sg:tags":[
        "shop"
    ],
    "wof:name":"Which-Craft",
    "wof:placetype":"venue"
},
  "geometry": {"coordinates":[-1.447969,55.010895],"type":"Point"}
}