{
  "type": "Feature",
  "properties": {
    "addr:full":"50 Copley Rd Doncaster South Yorkshire DN1 2QW",
    "addr:housenumber":"50",
    "addr:postcode":"dn1 2qw",
    "addr:street":"Copley Rd",
    "iso:country":"GB",
    "sg:address":"50 Copley Rd",
    "sg:city":"Doncaster",
    "sg:classifiers":[
        {
            "category":"Shopping",
            "subcategory":"Musical Instruments",
            "type":"Retail Goods"
        }
    ],
    "sg:phone":"+44 1302 769890",
    "sg:postcode":"DN1 2QW",
    "sg:province":"South Yorkshire",
    "sg:tags":[
        "music",
        "sheet"
    ],
    "wof:name":"Wizard Guitars Ltd",
    "wof:placetype":"venue"
},
  "geometry": {"coordinates":[-1.129015,53.526283],"type":"Point"}
}