{
  "type": "Feature",
  "properties": {
    "iso:country":"GB",
    "sg:address":"22 Belvedere Rd",
    "sg:city":"Bournemouth",
    "sg:classifiers":[
        {
            "category":"Building & Trades",
            "subcategory":"Construction",
            "type":"Services"
        }
    ],
    "sg:phone":"+44 1202 297601",
    "sg:postcode":"BH3 7LB",
    "sg:province":"Dorset",
    "sg:tags":[
        "roofing"
    ],
    "wof:name":"Durham Felt Roofing",
    "wof:placetype":"venue"
},
  "geometry": {"coordinates":[-1.8677070141,50.7358207703],"type":"Point"}
}