{
  "type": "Feature",
  "properties": {
    "addr:full":"6 Market Place Corbridge Northumberland NE45 5AW",
    "addr:housenumber":"6",
    "addr:postcode":"ne45 5aw",
    "addr:street":"Market Place;Northumberland",
    "iso:country":"GB",
    "sg:address":"6 Market Place",
    "sg:city":"Corbridge",
    "sg:classifiers":[
        {
            "category":"Banks & Credit Unions",
            "subcategory":"Financial Services",
            "type":"Services"
        }
    ],
    "sg:phone":"+44 1434 632111",
    "sg:postcode":"NE45 5AW",
    "sg:province":"Northumberland",
    "sg:tags":[
        "adviser"
    ],
    "wof:name":"Halcyon Financial Management",
    "wof:placetype":"venue"
},
  "geometry": {"coordinates":[-2.0200080872,54.9739074707],"type":"Point"}
}