{
  "type": "Feature",
  "properties": {
    "iso:country":"GB",
    "sg:address":"32 High Street",
    "sg:city":"Battle",
    "sg:classifiers":[
        {
            "category":"Bus Charters",
            "type":"Transportation"
        }
    ],
    "sg:phone":"+44 1424 772181",
    "sg:postcode":"TN33 0EH",
    "sg:province":"East Sussex",
    "sg:tags":[
        "hire",
        "coach"
    ],
    "wof:name":"Vicarys Coaches Ltd.",
    "wof:placetype":"venue"
},
  "geometry": {"coordinates":[0.48554,50.915791],"type":"Point"}
}