{
  "type": "Feature",
  "properties": {
    "addr:full":"Sandy Flatts Lane, Off Ladgate Lane Middlesbrough North Yorkshire TS5 7YN",
    "addr:postcode":"ts5 7yn",
    "addr:street":"Flatts Lane Off Ladgate Lane",
    "iso:country":"GB",
    "sg:address":"Sandy Flatts Lane, Off Ladgate Lane",
    "sg:city":"Middlesbrough",
    "sg:classifiers":[
        {
            "category":"Home & Garden",
            "subcategory":"Garden Supply",
            "type":"Retail Goods"
        }
    ],
    "sg:phone":"+44 1642 320514",
    "sg:postcode":"TS5 7YN",
    "sg:province":"North Yorkshire",
    "sg:tags":[
        "nursery",
        "centre"
    ],
    "wof:name":"Plantarama",
    "wof:placetype":"venue"
},
  "geometry": {"coordinates":[-1.240332,54.53511],"type":"Point"}
}