{
  "type": "Feature",
  "properties": {
    "iso:country":"GB",
    "sg:address":"D'urton Lane, Broughton",
    "sg:city":"Preston",
    "sg:classifiers":[
        {
            "category":"Shopping",
            "subcategory":"Bicycles & Sporting Goods",
            "type":"Retail Goods"
        }
    ],
    "sg:phone":"+44 1772 863130",
    "sg:postcode":"PR3 5LE",
    "sg:province":"Lancashire",
    "sg:tags":[
        "riding",
        "saddlery",
        "sport",
        "sale",
        "wear"
    ],
    "wof:name":"Preston Saddlery",
    "wof:placetype":"venue"
},
  "geometry": {"coordinates":[-2.7011799812,53.8018608093],"type":"Point"}
}