{
  "type": "Feature",
  "properties": {
    "iso:country":"GB",
    "sg:address":"13 Lowesmoor Wharf, Lowesmoor",
    "sg:city":"Worcester",
    "sg:classifiers":[
        {
            "category":"Wholesale",
            "subcategory":"Machinery & Supplies",
            "type":"Manufacturing & Wholesale Goods"
        }
    ],
    "sg:phone":"+44 1905 723457",
    "sg:postcode":"WR1 2RR",
    "sg:province":"Worcestershire",
    "sg:tags":[
        "pump"
    ],
    "wof:name":"West Midland Pump Services Ltd.",
    "wof:placetype":"venue"
},
  "geometry": {"coordinates":[-2.2187769413,52.194355011],"type":"Point"}
}