{
  "type": "Feature",
  "properties": {
    "iso:country":"GB",
    "sg:address":"Unit 4 Culreoch Way, Blackparks Industrial Estate",
    "sg:city":"Stranraer",
    "sg:classifiers":[
        {
            "category":"Professional",
            "subcategory":"Employment Agencies",
            "type":"Services"
        },
        {
            "category":"Shopping",
            "subcategory":"Pets & Pet Supplies",
            "type":"Retail Goods"
        }
    ],
    "sg:phone":"+44 1776 702272",
    "sg:postcode":"DG9 7UA",
    "sg:province":"Dumfries and Galloway",
    "sg:tags":[
        "feed",
        "agricultural",
        "advice",
        "animal"
    ],
    "wof:name":"Wcf Country Centres",
    "wof:placetype":"venue"
},
  "geometry": {"coordinates":[-5.0164442062,54.9056358337],"type":"Point"}
}