{
  "type": "Feature",
  "properties": {
    "iso:country":"GB",
    "sg:address":"3 Barlby Gro",
    "sg:city":"Sheffield",
    "sg:classifiers":[
        {
            "category":"Building & Trades",
            "subcategory":"Construction",
            "type":"Services"
        }
    ],
    "sg:phone":"+44 114 247 3210",
    "sg:postcode":"S12 4NB",
    "sg:province":"Derbyshire",
    "sg:tags":[
        "roofing"
    ],
    "wof:name":"Robert Green",
    "wof:placetype":"venue"
},
  "geometry": {"coordinates":[-1.366009,53.343933],"type":"Point"}
}