{
  "type": "Feature",
  "properties": {
    "iso:country":"GB",
    "sg:address":"7 Oak Tree Lane, Selly Oak",
    "sg:city":"Birmingham",
    "sg:classifiers":[
        {
            "category":"Shopping",
            "subcategory":"Jewelry",
            "type":"Retail Goods"
        },
        {
            "category":"Shopping",
            "subcategory":"Comic Books",
            "type":"Retail Goods"
        }
    ],
    "sg:phone":"+44 121 471 4100",
    "sg:postcode":"B29 6JE",
    "sg:province":"West Midlands",
    "sg:tags":[
        "jeweller",
        "sale",
        "jewellery"
    ],
    "wof:name":"Nightingale Jewellery",
    "wof:placetype":"venue"
},
  "geometry": {"coordinates":[-1.939699,52.439278],"type":"Point"}
}