{
  "type": "Feature",
  "properties": {
    "addr:full":"7 Little Charles St Herne Bay Kent CT6 5ET",
    "addr:housenumber":"7",
    "addr:postcode":"ct6 5et",
    "addr:street":"Little Charles St",
    "iso:country":"GB",
    "sg:address":"7 Little Charles St",
    "sg:city":"Herne Bay",
    "sg:classifiers":[
        {
            "category":"Retail",
            "subcategory":"Auto Repair",
            "type":"Services"
        }
    ],
    "sg:postcode":"CT6 5ET",
    "sg:province":"Kent",
    "sg:tags":[
        "modification",
        "garage"
    ],
    "wof:name":"West,Justin,",
    "wof:placetype":"venue"
},
  "geometry": {"coordinates":[1.1294339895,51.3722496033],"type":"Point"}
}