{
  "type": "Feature",
  "properties": {
    "addr:full":"27 Newburgh Place, Highworth Swindon Gloucestershire SN6 7DN",
    "addr:housenumber":"27",
    "addr:postcode":"sn6 7dn",
    "addr:street":"Newburgh Place",
    "iso:country":"GB",
    "sg:address":"27 Newburgh Place, Highworth",
    "sg:city":"Swindon",
    "sg:classifiers":[
        {
            "category":"Professional",
            "subcategory":"Computer Services",
            "type":"Services"
        }
    ],
    "sg:phone":"+44 1793 766866",
    "sg:postcode":"SN6 7DN",
    "sg:province":"Gloucestershire",
    "sg:tags":[
        "system",
        "software"
    ],
    "wof:name":"Highworth Computers Ltd.",
    "wof:placetype":"venue"
},
  "geometry": {"coordinates":[-1.7150950432,51.6330337524],"type":"Point"}
}