{
  "type": "Feature",
  "properties": {
    "iso:country":"GB",
    "sg:address":"3 Newtown Avenue, North Bersted",
    "sg:city":"Bognor Regis",
    "sg:classifiers":[
        {
            "category":"Home & Garden",
            "subcategory":"Building Materials",
            "type":"Retail Goods"
        }
    ],
    "sg:phone":"+44 7971 296651",
    "sg:postcode":"PO21 5HS",
    "sg:province":"West Sussex",
    "sg:tags":[
        "insulation",
        "installers"
    ],
    "wof:name":"K C Dobbs & Son",
    "wof:placetype":"venue"
},
  "geometry": {"coordinates":[-0.691182971,50.7977638245],"type":"Point"}
}