{
  "type": "Feature",
  "properties": {
    "addr:full":"53 Padgbury La Congleton Cheshire CW12 4LP",
    "addr:housenumber":"53",
    "addr:postcode":"cw12 4lp",
    "addr:street":"Padgbury La Congleton",
    "iso:country":"GB",
    "sg:address":"53 Padgbury La",
    "sg:city":"Congleton",
    "sg:classifiers":[
        {
            "category":"Professional",
            "subcategory":"Engineering",
            "type":"Services"
        }
    ],
    "sg:phone":"+44 1260 270928",
    "sg:postcode":"CW12 4LP",
    "sg:province":"Cheshire",
    "sg:tags":[
        "contractor",
        "electrical",
        "engineer"
    ],
    "wof:name":"G Byrne",
    "wof:placetype":"venue"
},
  "geometry": {"coordinates":[-2.2432150841,53.1619873047],"type":"Point"}
}