{
  "type": "Feature",
  "properties": {
    "addr:full":"100 Hollins Road Oldham Lancashire OL8 3DU",
    "addr:housenumber":"100",
    "addr:postcode":"ol8 3du",
    "addr:street":"Hollins Road",
    "iso:country":"GB",
    "sg:address":"100 Hollins Road",
    "sg:city":"Oldham",
    "sg:classifiers":[
        {
            "category":"Personal",
            "subcategory":"Beauty Salon",
            "type":"Services"
        }
    ],
    "sg:phone":"+44 161 624 8401",
    "sg:postcode":"OL8 3DU",
    "sg:province":"Lancashire",
    "sg:tags":[
        "ladies",
        "lady",
        "hairdresser"
    ],
    "wof:name":"SHORT & CURLY'S",
    "wof:placetype":"venue"
},
  "geometry": {"coordinates":[-2.1142780781,53.5250320435],"type":"Point"}
}