{
  "type": "Feature",
  "properties": {
    "addr:full":"54 Ridgeway, Plympton Plymouth Devon PL7 2BE",
    "addr:housenumber":"54",
    "addr:postcode":"pl7 2be",
    "addr:street":"Ridgeway",
    "iso:country":"GB",
    "sg:address":"54 Ridgeway, Plympton",
    "sg:city":"Plymouth",
    "sg:classifiers":[
        {
            "category":"Government",
            "subcategory":"Post Office",
            "type":"Public Place"
        }
    ],
    "sg:phone":"+44 845 722 3344",
    "sg:postcode":"PL7 2BE",
    "sg:province":"Devon",
    "wof:name":"Post Office Ltd.",
    "wof:placetype":"venue"
},
  "geometry": {"coordinates":[-4.0521988869,50.3876876831],"type":"Point"}
}