{
  "type": "Feature",
  "properties": {
    "iso:country":"GB",
    "sg:address":"Church Street",
    "sg:city":"Basingstoke",
    "sg:classifiers":[
        {
            "category":"Social Services",
            "type":"Services"
        }
    ],
    "sg:postcode":"RG21 7QQ",
    "sg:province":"Hampshire",
    "sg:tags":[
        "disability"
    ],
    "wof:name":"Shopmobility Basingstoke",
    "wof:placetype":"venue"
},
  "geometry": {"coordinates":[-1.088735,51.265869],"type":"Point"}
}