{
  "type": "Feature",
  "properties": {
    "iso:country":"GB",
    "sg:address":"Rosevean House, Rosemundy",
    "sg:city":"St Agnes",
    "sg:classifiers":[
        {
            "category":"Health Services",
            "subcategory":"Nursing And Care Facility",
            "type":"Services"
        }
    ],
    "sg:postcode":"TR5 0UD",
    "sg:province":"Cornwall",
    "sg:tags":[
        "home"
    ],
    "wof:name":"Abbeyfield St. Agnes Society Ltd.",
    "wof:placetype":"venue"
},
  "geometry": {"coordinates":[-5.1986088753,50.3120155334],"type":"Point"}
}