{
  "type": "Feature",
  "properties": {
    "addr:full":"47 Hounslow Road, Hanworth Feltham Greater London TW13 6QA",
    "addr:housenumber":"47",
    "addr:postcode":"tw13 6qa",
    "addr:street":"Hounslow Road",
    "iso:country":"GB",
    "sg:address":"47 Hounslow Road, Hanworth",
    "sg:city":"Feltham",
    "sg:classifiers":[
        {
            "category":"Autos & Motor Vehicles",
            "subcategory":"Fuel & Gas Station",
            "type":"Retail Goods"
        }
    ],
    "sg:phone":"+44 20 8894 2454",
    "sg:postcode":"TW13 6QA",
    "sg:province":"Greater London",
    "sg:tags":[
        "petrol",
        "filling"
    ],
    "wof:name":"NEM PETROLEUM CO LTD",
    "wof:placetype":"venue"
},
  "geometry": {"coordinates":[-0.390237,51.430511],"type":"Point"}
}