{
  "type": "Feature",
  "properties": {
    "addr:full":"74a Knott Lane Hyde Cheshire SK14 5BS",
    "addr:housenumber":"74a",
    "addr:postcode":"sk14 5bs",
    "addr:street":"Knott Lane",
    "iso:country":"GB",
    "sg:address":"74a Knott Lane",
    "sg:city":"Hyde",
    "sg:classifiers":[
        {
            "category":"Food & Beverages",
            "subcategory":"Groceries & Convenience Stores",
            "type":"Retail Goods"
        }
    ],
    "sg:phone":"+44 161 368 4192",
    "sg:postcode":"SK14 5BS",
    "sg:province":"Cheshire",
    "wof:name":"A & B Sutcliffe",
    "wof:placetype":"venue"
},
  "geometry": {"coordinates":[-2.0795691013,53.4404754639],"type":"Point"}
}