{
  "type": "Feature",
  "properties": {
    "addr:full":"246-247 Waterloo Street Burton-on-trent Derbyshire DE14 2NJ",
    "addr:housenumber":"246-247",
    "addr:postcode":"de14 2nj",
    "addr:street":"Waterloo Street",
    "iso:country":"GB",
    "sg:address":"246-247 Waterloo Street",
    "sg:city":"Burton-on-trent",
    "sg:classifiers":[
        {
            "category":"Shopping",
            "subcategory":"Baby Store",
            "type":"Retail Goods"
        }
    ],
    "sg:postcode":"DE14 2NJ",
    "sg:province":"Derbyshire",
    "sg:tags":[
        "nursery",
        "accessory"
    ],
    "wof:name":"Second to None",
    "wof:placetype":"venue"
},
  "geometry": {"coordinates":[-1.64349,52.808983],"type":"Point"}
}