{
  "type": "Feature",
  "properties": {
    "iso:country":"GB",
    "sg:address":"12 High Street, Edwinstowe",
    "sg:city":"Mansfield",
    "sg:classifiers":[
        {
            "category":"Shopping",
            "subcategory":"Clothing, Apparel, & Fashions",
            "type":"Retail Goods"
        }
    ],
    "sg:phone":"+44 1623 822432",
    "sg:postcode":"NG21 9QS",
    "sg:province":"Nottinghamshire",
    "sg:tags":[
        "menswear"
    ],
    "wof:name":"J F Roe & Sons",
    "wof:placetype":"venue"
},
  "geometry": {"coordinates":[-1.064639,53.194733],"type":"Point"}
}