{
  "type": "Feature",
  "properties": {
    "iso:country":"GB",
    "sg:address":"78 Church Rd",
    "sg:city":"Watford",
    "sg:classifiers":[
        {
            "category":"Professional",
            "subcategory":"Computer Services",
            "type":"Services"
        }
    ],
    "sg:phone":"+44 1923 219915",
    "sg:postcode":"WD1 3PU",
    "sg:province":"Hertfordshire",
    "sg:tags":[
        "system",
        "software"
    ],
    "wof:name":"Clear Sites",
    "wof:placetype":"venue"
},
  "geometry": {"coordinates":[-0.401823,51.66758],"type":"Point"}
}