{
  "type": "Feature",
  "properties": {
    "addr:full":"Birmingham Road, Shenstone Lichfield Staffordshire WS14 0JR",
    "addr:postcode":"ws14 0jr",
    "addr:street":"Birmingham Road",
    "iso:country":"GB",
    "sg:address":"Birmingham Road, Shenstone",
    "sg:city":"Lichfield",
    "sg:classifiers":[
        {
            "category":"Farming",
            "subcategory":"Livestock Farm",
            "type":"Manufacturing & Wholesale Goods"
        }
    ],
    "sg:postcode":"WS14 0JR",
    "sg:province":"Staffordshire",
    "sg:tags":[
        "others"
    ],
    "wof:name":"Foden & Abel",
    "wof:placetype":"venue"
},
  "geometry": {"coordinates":[-1.8403099775,52.6407814026],"type":"Point"}
}