{
  "type": "Feature",
  "properties": {
    "addr:full":"22 Ryecroft Street Gloucester Gloucestershire GL1 4LY",
    "addr:housenumber":"22",
    "addr:postcode":"gl1 4ly",
    "addr:street":"Ryecroft Street",
    "iso:country":"GB",
    "sg:address":"22 Ryecroft Street",
    "sg:city":"Gloucester",
    "sg:classifiers":[
        {
            "category":"Shopping",
            "subcategory":"Department Store",
            "type":"Retail Goods"
        },
        {
            "category":"Food & Beverages",
            "subcategory":"Supermarket",
            "type":"Retail Goods"
        }
    ],
    "sg:phone":"+44 1452 521168",
    "sg:postcode":"GL1 4LY",
    "sg:province":"Gloucestershire",
    "wof:name":"Mohmedi Stores",
    "wof:placetype":"venue"
},
  "geometry": {"coordinates":[-2.2382850647,51.8579177856],"type":"Point"}
}