{
  "type": "Feature",
  "properties": {
    "iso:country":"GB",
    "sg:address":"3 Park Road, Narborough",
    "sg:city":"Leicester",
    "sg:classifiers":[
        {
            "category":"Professional",
            "subcategory":"Computer Services",
            "type":"Services"
        }
    ],
    "sg:postcode":"LE9 5GQ",
    "sg:province":"Leicestershire",
    "sg:tags":[
        "system",
        "software"
    ],
    "wof:name":"Michael J Breen Ltd",
    "wof:placetype":"venue"
},
  "geometry": {"coordinates":[-1.21197,52.571739],"type":"Point"}
}