{
  "type": "Feature",
  "properties": {
    "addr:full":"87a Bordesley Green Rd Birmingham West Midlands B9 4TW",
    "addr:housenumber":"87a",
    "addr:postcode":"b9 4tw",
    "addr:street":"Bordesley Green Rd",
    "iso:country":"GB",
    "sg:address":"87a Bordesley Green Rd",
    "sg:city":"Birmingham",
    "sg:classifiers":[
        {
            "category":"Manufacturing",
            "subcategory":"Metals",
            "type":"Manufacturing & Wholesale Goods"
        }
    ],
    "sg:phone":"+44 121 772 5571",
    "sg:postcode":"B9 4TW",
    "sg:province":"West Midlands",
    "sg:tags":[
        "steel",
        "fabricator",
        "erectors"
    ],
    "wof:name":"T Morley",
    "wof:placetype":"venue"
},
  "geometry": {"coordinates":[-1.856671,52.478947],"type":"Point"}
}