{
  "type": "Feature",
  "properties": {
    "iso:country":"GB",
    "sg:address":"3 Beach Rd",
    "sg:city":"Weston-super-mare",
    "sg:classifiers":[
        {
            "category":"Shopping",
            "subcategory":"Department Store",
            "type":"Retail Goods"
        }
    ],
    "sg:postcode":"BS23 1AS",
    "sg:province":"Somerset",
    "wof:name":"Pier View Indoor Market",
    "wof:placetype":"venue"
},
  "geometry": {"coordinates":[-2.980514,51.347279],"type":"Point"}
}