{
  "type": "Feature",
  "properties": {
    "iso:country":"GB",
    "sg:address":"Upleadon Farm, Munsley",
    "sg:city":"Ledbury",
    "sg:classifiers":[
        {
            "category":"Farming",
            "subcategory":"Livestock Farm",
            "type":"Manufacturing & Wholesale Goods"
        }
    ],
    "sg:phone":"+44 1531 670291",
    "sg:postcode":"HR8 2SL",
    "sg:province":"Gloucestershire",
    "sg:tags":[
        "others"
    ],
    "wof:name":"John H Fearis",
    "wof:placetype":"venue"
},
  "geometry": {"coordinates":[-2.4911339283,52.0647697449],"type":"Point"}
}