{
  "type": "Feature",
  "properties": {
    "addr:full":"62 Queen Elizabeth Drive Normanton West Yorkshire WF6 1JG",
    "addr:housenumber":"62",
    "addr:postcode":"wf6 1jg",
    "addr:street":"Queen Elizabeth Drive Normanton West",
    "iso:country":"GB",
    "sg:address":"62 Queen Elizabeth Drive",
    "sg:city":"Normanton",
    "sg:classifiers":[
        {
            "category":"Shopping",
            "subcategory":"News",
            "type":"Retail Goods"
        }
    ],
    "sg:phone":"+44 1924 893057",
    "sg:postcode":"WF6 1JG",
    "sg:province":"West Yorkshire",
    "sg:tags":[
        "newsagent"
    ],
    "wof:name":"Normanton News",
    "wof:placetype":"venue"
},
  "geometry": {"coordinates":[-1.415959,53.689186],"type":"Point"}
}