{
  "type": "Feature",
  "properties": {
    "addr:full":"10 Dover Street London Greater London W1S 4LW",
    "addr:housenumber":"10",
    "addr:postcode":"w1s 4lw",
    "addr:street":"Dover Street",
    "iso:country":"GB",
    "sg:address":"10 Dover Street",
    "sg:city":"London",
    "sg:classifiers":[
        {
            "category":"Organizations",
            "subcategory":"Membership Organization",
            "type":"Services"
        }
    ],
    "sg:phone":"+44 20 7493 3166",
    "sg:postcode":"W1S 4LW",
    "sg:province":"Greater London",
    "sg:tags":[
        "club"
    ],
    "wof:name":"Club Choice Ltd.",
    "wof:placetype":"venue"
},
  "geometry": {"coordinates":[-0.141668,51.508121],"type":"Point"}
}