{
  "type": "Feature",
  "properties": {
    "iso:country":"GB",
    "sg:address":"Highwood Hospital Grounds, Ongar Rd",
    "sg:city":"Brentwood",
    "sg:classifiers":[
        {
            "category":"Organizations",
            "subcategory":"Community Association",
            "type":"Services"
        }
    ],
    "sg:phone":"+44 1277 200994",
    "sg:postcode":"CM15 9DY",
    "sg:province":"Essex",
    "sg:tags":[
        "society",
        "housing"
    ],
    "wof:name":"Barking Havering & Brentwood Housing Consortium",
    "wof:placetype":"venue"
},
  "geometry": {"coordinates":[0.29634,51.626019],"type":"Point"}
}