{
  "type": "Feature",
  "properties": {
    "addr:full":"10 Bridge St, Blaydon Blaydon On Tyne Tyne and Wear NE21 4NR",
    "addr:housenumber":"10",
    "addr:postcode":"ne21 4nr",
    "addr:street":"Bridge St",
    "iso:country":"GB",
    "sg:address":"10 Bridge St, Blaydon",
    "sg:city":"Blaydon On Tyne",
    "sg:classifiers":[
        {
            "category":"Shopping",
            "subcategory":"Antiques",
            "type":"Retail Goods"
        }
    ],
    "sg:phone":"+44 191 414 3535",
    "sg:postcode":"NE21 4NR",
    "sg:province":"Tyne and Wear",
    "wof:name":"Blaydon Antiques Centre",
    "wof:placetype":"venue"
},
  "geometry": {"coordinates":[-1.717817,54.966255],"type":"Point"}
}