{
  "type": "Feature",
  "properties": {
    "iso:country":"GB",
    "sg:address":"200 Bedford Rd",
    "sg:city":"Birkenhead",
    "sg:classifiers":[
        {
            "category":"Professional",
            "subcategory":"Lawyer & Legal Services",
            "type":"Services"
        }
    ],
    "sg:phone":"+44 151 645 9276",
    "sg:postcode":"CH42 2AT",
    "sg:province":"Merseyside",
    "sg:tags":[
        "advice",
        "counselling"
    ],
    "wof:name":"Rockferry Community Care Association",
    "wof:placetype":"venue"
},
  "geometry": {"coordinates":[-3.0120449066,53.3720092773],"type":"Point"}
}