{
  "type": "Feature",
  "properties": {
    "addr:full":"74 Pall Mall Chorley Lancashire PR7 2LE",
    "addr:housenumber":"74",
    "addr:postcode":"pr7 2le",
    "addr:street":"Pall Mall",
    "iso:country":"GB",
    "sg:address":"74 Pall Mall",
    "sg:city":"Chorley",
    "sg:classifiers":[
        {
            "category":"Shopping",
            "subcategory":"Pets & Pet Supplies",
            "type":"Retail Goods"
        }
    ],
    "sg:postcode":"PR7 2LE",
    "sg:province":"Lancashire",
    "wof:name":"Chorley Pets",
    "wof:placetype":"venue"
},
  "geometry": {"coordinates":[-2.63329,53.648472],"type":"Point"}
}