{
  "type": "Feature",
  "properties": {
    "iso:country":"GB",
    "sg:address":"162-166 High St",
    "sg:city":"Berkhamsted",
    "sg:classifiers":[
        {
            "category":"Retail",
            "subcategory":"Photofinishing",
            "type":"Services"
        }
    ],
    "sg:phone":"+44 1442 864191",
    "sg:postcode":"HP4 3AP",
    "sg:province":"Bedfordshire",
    "sg:tags":[
        "photographic",
        "processor"
    ],
    "wof:name":"SupaSnaps",
    "wof:placetype":"venue"
},
  "geometry": {"coordinates":[-0.5739840269,51.7636604309],"type":"Point"}
}