{
  "type": "Feature",
  "properties": {
    "addr:full":"Unit 3, Timberlaine Industrial Estate, Quarry Lane Chichester West Sussex PO19 8PQ",
    "addr:housenumber":"unit 3",
    "addr:postcode":"po19 8pq",
    "addr:street":"Timberlaine Industrial Estate Quarry Lane",
    "iso:country":"GB",
    "sg:address":"Unit 3, Timberlaine Industrial Estate, Quarry Lane",
    "sg:city":"Chichester",
    "sg:classifiers":[
        {
            "category":"Building & Trades",
            "subcategory":"Plumbing",
            "type":"Services"
        }
    ],
    "sg:postcode":"PO19 8PQ",
    "sg:province":"West Sussex",
    "sg:tags":[
        "merchant",
        "plumbers'"
    ],
    "wof:name":"Scotts Heating & Plumbing Supplies",
    "wof:placetype":"venue"
},
  "geometry": {"coordinates":[-0.7754290104,50.8361663818],"type":"Point"}
}