{
  "type": "Feature",
  "properties": {
    "iso:country":"GB",
    "sg:address":"Station Yard, Main Road",
    "sg:city":"Stocksfield",
    "sg:classifiers":[
        {
            "category":"Retail",
            "subcategory":"Veterinary Services",
            "type":"Services"
        }
    ],
    "sg:postcode":"NE43 7NJ",
    "sg:province":"Northumberland",
    "sg:tags":[
        "surgeon"
    ],
    "wof:name":"Station Veterinary Clinic",
    "wof:placetype":"venue"
},
  "geometry": {"coordinates":[-1.915894,54.946686],"type":"Point"}
}