{
  "type": "Feature",
  "properties": {
    "addr:full":"Engleside, Lane End Rd Bembridge Isle of Wight PO35 5UE",
    "addr:postcode":"po35 5ue",
    "addr:street":"Engleside Lane End Rd",
    "iso:country":"GB",
    "sg:address":"Engleside, Lane End Rd",
    "sg:city":"Bembridge",
    "sg:classifiers":[
        {
            "category":"Professional",
            "subcategory":"Engineering",
            "type":"Services"
        }
    ],
    "sg:phone":"+44 1983 872613",
    "sg:postcode":"PO35 5UE",
    "sg:province":"Isle of Wight",
    "sg:tags":[
        "contractor",
        "electrical",
        "engineer"
    ],
    "wof:name":"RFJ Wood",
    "wof:placetype":"venue"
},
  "geometry": {"coordinates":[-1.0879570246,50.6896095276],"type":"Point"}
}