{
  "type": "Feature",
  "properties": {
    "iso:country":"GB",
    "sg:address":"24 Main St, Sprotbrough",
    "sg:city":"Doncaster",
    "sg:classifiers":[
        {
            "category":"Recreation",
            "type":"Entertainment"
        }
    ],
    "sg:phone":"+44 1302 311113",
    "sg:postcode":"DN5 7RF",
    "sg:province":"South Yorkshire",
    "sg:tags":[
        "hot",
        "balloon",
        "air"
    ],
    "wof:name":"Balloon Rides",
    "wof:placetype":"venue"
},
  "geometry": {"coordinates":[-1.1891310215,53.5122299194],"type":"Point"}
}