{
  "type": "Feature",
  "properties": {
    "iso:country":"GB",
    "sg:address":"Pulloxhill Road, Greenfield",
    "sg:city":"Bedford",
    "sg:classifiers":[
        {
            "category":"Education",
            "subcategory":"School",
            "type":"Public Place"
        }
    ],
    "sg:phone":"+44 1525 712426",
    "sg:postcode":"MK45 5ES",
    "sg:province":"Bedfordshire",
    "sg:tags":[
        "local",
        "authority"
    ],
    "wof:name":"Greenfield Lower School",
    "wof:placetype":"venue"
},
  "geometry": {"coordinates":[-0.466089,52.002762],"type":"Point"}
}