{
  "type": "Feature",
  "properties": {
    "iso:country":"GB",
    "sg:address":"Visitor Centre, Needle Mill Lane",
    "sg:city":"Redditch",
    "sg:classifiers":[
        {
            "category":"Museum",
            "subcategory":"Art Museum",
            "type":"Entertainment"
        },
        {
            "category":"Government",
            "subcategory":"Office",
            "type":"Public Place"
        }
    ],
    "sg:phone":"+44 1527 62509",
    "sg:postcode":"B98 8HY",
    "sg:province":"Warwickshire",
    "sg:tags":[
        "local",
        "gallery"
    ],
    "wof:name":"Forge Mill Needle Museum & Bordesley Abbey",
    "wof:placetype":"venue"
},
  "geometry": {"coordinates":[-1.93485,52.314861],"type":"Point"}
}