{
  "type": "Feature",
  "properties": {
    "iso:country":"GB",
    "sg:address":"15/17/19 Tarleton Street",
    "sg:city":"Liverpool",
    "sg:classifiers":[
        {
            "category":"Banks & Credit Unions",
            "subcategory":"Bank",
            "type":"Services"
        }
    ],
    "sg:postcode":"L1 1QS",
    "sg:province":"Merseyside",
    "wof:name":"Halifax Plc",
    "wof:placetype":"venue"
},
  "geometry": {"coordinates":[-2.978481,53.409775],"type":"Point"}
}