{
  "type": "Feature",
  "properties": {
    "addr:full":"771 London Road Hounslow Greater London TW3 1RS",
    "addr:housenumber":"771",
    "addr:postcode":"tw3 1rs",
    "addr:street":"London Road",
    "iso:country":"GB",
    "sg:address":"771 London Road",
    "sg:city":"Hounslow",
    "sg:classifiers":[
        {
            "category":"Retail",
            "subcategory":"Laundry & Dry Cleaning",
            "type":"Services"
        }
    ],
    "sg:phone":"+44 20 8570 5042",
    "sg:postcode":"TW3 1RS",
    "sg:province":"Greater London",
    "sg:tags":[
        "alteration"
    ],
    "wof:name":"Tryus Cleaners",
    "wof:placetype":"venue"
},
  "geometry": {"coordinates":[-0.3525139987,51.4710426331],"type":"Point"}
}