{
  "type": "Feature",
  "properties": {
    "addr:full":"31 Coatbank Street Coatbridge North Lanarkshire ML5 3SP",
    "addr:housenumber":"31",
    "addr:postcode":"ml5 3sp",
    "addr:street":"Coatbank Street",
    "iso:country":"GB",
    "sg:address":"31 Coatbank Street",
    "sg:city":"Coatbridge",
    "sg:classifiers":[
        {
            "category":"Shopping",
            "subcategory":"Beauty & Cosmetics",
            "type":"Retail Goods"
        }
    ],
    "sg:phone":"+44 1236 437080",
    "sg:postcode":"ML5 3SP",
    "sg:province":"North Lanarkshire",
    "sg:tags":[
        "equipment",
        "supply",
        "hairdressing"
    ],
    "wof:name":"Salon Services",
    "wof:placetype":"venue"
},
  "geometry": {"coordinates":[-4.0200009346,55.8571357727],"type":"Point"}
}