{
  "type": "Feature",
  "properties": {
    "addr:full":"42 Harley Street London Greater London W1G 9PR",
    "addr:housenumber":"42",
    "addr:postcode":"w1g 9pr",
    "addr:street":"Harley Street",
    "iso:country":"GB",
    "sg:address":"42 Harley Street",
    "sg:city":"London",
    "sg:classifiers":[
        {
            "category":"Health Services",
            "subcategory":"Doctor",
            "type":"Services"
        }
    ],
    "sg:phone":"+44 20 7580 1354",
    "sg:postcode":"W1G 9PR",
    "sg:province":"Greater London",
    "sg:tags":[
        "practitioners"
    ],
    "wof:name":"Irving Luke",
    "wof:placetype":"venue"
},
  "geometry": {"coordinates":[-0.146558,51.518593],"type":"Point"}
}