{
  "type": "Feature",
  "properties": {
    "addr:full":"75 Clay Lane, Clay Cross Chesterfield Derbyshire S45 9AW",
    "addr:housenumber":"75",
    "addr:postcode":"s45 9aw",
    "addr:street":"Clay Lane",
    "iso:country":"GB",
    "sg:address":"75 Clay Lane, Clay Cross",
    "sg:city":"Chesterfield",
    "sg:classifiers":[
        {
            "category":"Health Services",
            "subcategory":"Podiatrist",
            "type":"Services"
        }
    ],
    "sg:postcode":"S45 9AW",
    "sg:province":"Derbyshire",
    "sg:tags":[
        "podiatrists",
        "chiropodist"
    ],
    "wof:name":"Diane Mason",
    "wof:placetype":"venue"
},
  "geometry": {"coordinates":[-1.4211770296,53.161655426],"type":"Point"}
}