{
  "type": "Feature",
  "properties": {
    "iso:country":"GB",
    "sg:address":"60 Barrowgate Rd",
    "sg:city":"Chiswick",
    "sg:classifiers":[
        {
            "category":"Autos & Motor Vehicles",
            "subcategory":"Motorcycle Sales",
            "type":"Retail Goods"
        }
    ],
    "sg:phone":"+44 20 8742 8414",
    "sg:postcode":"W4 4QU",
    "sg:province":"Greater London",
    "sg:tags":[
        "chauffeur",
        "driven",
        "car"
    ],
    "wof:name":"R I M Chauffeur Drive",
    "wof:placetype":"venue"
},
  "geometry": {"coordinates":[-0.265924,51.488434],"type":"Point"}
}