{
  "type": "Feature",
  "properties": {
    "addr:full":"55 Hurst St Birmingham West Midlands B5 4TE",
    "addr:housenumber":"55",
    "addr:postcode":"b5 4te",
    "addr:street":"Hurst St",
    "iso:country":"GB",
    "sg:address":"55 Hurst St",
    "sg:city":"Birmingham",
    "sg:classifiers":[
        {
            "category":"Fast Food",
            "type":"Food & Drink"
        }
    ],
    "sg:postcode":"B5 4TE",
    "sg:province":"West Midlands",
    "sg:tags":[
        "away",
        "take"
    ],
    "wof:name":"Oscars Catering",
    "wof:placetype":"venue"
},
  "geometry": {"coordinates":[-1.897207,52.474281],"type":"Point"}
}