{
  "type": "Feature",
  "properties": {
    "addr:full":"Heath House Mill, Heath House La Huddersfield West Yorkshire HD7 4JW",
    "addr:housenumber":"mill",
    "addr:postcode":"hd7 4jw",
    "addr:street":"Heath;Heath House La Huddersfield West",
    "iso:country":"GB",
    "sg:address":"Heath House Mill, Heath House La",
    "sg:city":"Huddersfield",
    "sg:classifiers":[
        {
            "category":"Professional",
            "subcategory":"Credit Reporting & Collection",
            "type":"Services"
        }
    ],
    "sg:phone":"+44 1484 460660",
    "sg:postcode":"HD7 4JW",
    "sg:province":"West Yorkshire",
    "sg:tags":[
        "merchant",
        "rag"
    ],
    "wof:name":"J M R Ltd",
    "wof:placetype":"venue"
},
  "geometry": {"coordinates":[-1.8687649965,53.6429634094],"type":"Point"}
}