{
  "type": "Feature",
  "properties": {
    "addr:full":"101 Reddal Hill Rd Cradley Heath West Midlands B64 5JR",
    "addr:housenumber":"101",
    "addr:postcode":"b64 5jr",
    "addr:street":"Reddal Hill Rd",
    "iso:country":"GB",
    "sg:address":"101 Reddal Hill Rd",
    "sg:city":"Cradley Heath",
    "sg:classifiers":[
        {
            "category":"Autos & Motor Vehicles",
            "subcategory":"Automobile Sales",
            "type":"Retail Goods"
        }
    ],
    "sg:phone":"+44 1384 637245",
    "sg:postcode":"B64 5JR",
    "sg:province":"West Midlands",
    "sg:tags":[
        "car"
    ],
    "wof:name":"Horse Shoe Garage",
    "wof:placetype":"venue"
},
  "geometry": {"coordinates":[-2.0732910633,52.4764175415],"type":"Point"}
}