{
  "type": "Feature",
  "properties": {
    "addr:full":"8 Northgate Heckmondwike West Yorkshire WF16 0HW",
    "addr:housenumber":"8;heckmondwike",
    "addr:postcode":"wf16 0hw",
    "addr:street":"Northgate",
    "iso:country":"GB",
    "sg:address":"8 Northgate",
    "sg:city":"Heckmondwike",
    "sg:classifiers":[
        {
            "category":"Health Services",
            "subcategory":"Optometrist",
            "type":"Services"
        }
    ],
    "sg:phone":"+44 1924 409334",
    "sg:postcode":"WF16 0HW",
    "sg:province":"West Yorkshire",
    "sg:tags":[
        "optician"
    ],
    "wof:name":"Phipps Opticians",
    "wof:placetype":"venue"
},
  "geometry": {"coordinates":[-1.6758970022,53.7077217102],"type":"Point"}
}