{
  "type": "Feature",
  "properties": {
    "addr:full":"29 Ivanhoe Road, Hogwood Industrial Estate, Finchhamsptead Wokingham Berkshire RG40 4QQ",
    "addr:housenumber":"29",
    "addr:postcode":"rg40 4qq",
    "addr:street":"Ivanhoe Road Hogwood Industrial Estate Finchhamsptead",
    "iso:country":"GB",
    "sg:address":"29 Ivanhoe Road, Hogwood Industrial Estate, Finchhamsptead",
    "sg:city":"Wokingham",
    "sg:classifiers":[
        {
            "category":"Professional",
            "subcategory":"Computer Services",
            "type":"Services"
        }
    ],
    "sg:phone":"+44 118 973 2977",
    "sg:postcode":"RG40 4QQ",
    "sg:province":"Berkshire",
    "sg:tags":[
        "consultant"
    ],
    "wof:name":"Eurorealm Consultants Ltd.",
    "wof:placetype":"venue"
},
  "geometry": {"coordinates":[-0.8345940113,51.4108009338],"type":"Point"}
}