{
  "type": "Feature",
  "properties": {
    "iso:country":"GB",
    "sg:address":"30 Parkstone Lane, Worsley",
    "sg:city":"Manchester",
    "sg:classifiers":[
        {
            "category":"Building & Trades",
            "subcategory":"Construction",
            "type":"Services"
        }
    ],
    "sg:postcode":"M28 2PW",
    "sg:province":"Greater Manchester",
    "sg:tags":[
        "contractor",
        "paving",
        "driveway"
    ],
    "wof:name":"Parkstone Landscapes",
    "wof:placetype":"venue"
},
  "geometry": {"coordinates":[-2.3807,53.496246],"type":"Point"}
}