{
  "type": "Feature",
  "properties": {
    "iso:country":"GB",
    "sg:address":"Euston Station",
    "sg:city":"London",
    "sg:classifiers":[
        {
            "category":"Banks & Credit Unions",
            "subcategory":"Bureau De Change",
            "type":"Services"
        }
    ],
    "sg:phone":"+44 20 7387 0916",
    "sg:postcode":"NW1 2DU",
    "sg:province":"Greater London",
    "wof:name":"Exchange International",
    "wof:placetype":"venue"
},
  "geometry": {"coordinates":[-0.13391,51.527939],"type":"Point"}
}