{
  "type": "Feature",
  "properties": {
    "addr:full":"Victory Retail Park, Flathouse Rd Portsmouth Hampshire PO1 4QP",
    "addr:postcode":"hampshire po1 4qp",
    "addr:street":"Flathouse Rd",
    "iso:country":"GB",
    "sg:address":"Victory Retail Park, Flathouse Rd",
    "sg:city":"Portsmouth",
    "sg:classifiers":[
        {
            "category":"Professional",
            "subcategory":"Detective & Security Services",
            "type":"Services"
        }
    ],
    "sg:phone":"+44 23 9281 1112",
    "sg:postcode":"PO1 4QP",
    "sg:province":"Hampshire",
    "wof:name":"Valga",
    "wof:placetype":"venue"
},
  "geometry": {"coordinates":[-1.0872839689,50.8040084839],"type":"Point"}
}