{
  "type": "Feature",
  "properties": {
    "iso:country":"GB",
    "sg:address":"2-4 Hardwicke Road",
    "sg:city":"Reigate",
    "sg:classifiers":[
        {
            "category":"Health Services",
            "subcategory":"Health Practitioner",
            "type":"Services"
        }
    ],
    "sg:postcode":"RH2 9HJ",
    "sg:province":"Surrey",
    "sg:tags":[
        "psychotherapist",
        "hypnotherapists"
    ],
    "wof:name":"Ray Twine",
    "wof:placetype":"venue"
},
  "geometry": {"coordinates":[-0.209581,51.240154],"type":"Point"}
}