{
  "type": "Feature",
  "properties": {
    "addr:full":"5 Meadow View Kidlington Buckinghamshire OX5 2XY",
    "addr:housenumber":"5",
    "addr:postcode":"ox5 2xy",
    "addr:street":"Meadow View",
    "iso:country":"GB",
    "sg:address":"5 Meadow View",
    "sg:city":"Kidlington",
    "sg:classifiers":[
        {
            "category":"Building & Trades",
            "subcategory":"Construction",
            "type":"Services"
        }
    ],
    "sg:postcode":"OX5 2XY",
    "sg:province":"Buckinghamshire",
    "sg:tags":[
        "decorator",
        "painter"
    ],
    "wof:name":"Mullard,Trevor,",
    "wof:placetype":"venue"
},
  "geometry": {"coordinates":[-1.2874759436,51.8281555176],"type":"Point"}
}