{
  "type": "Feature",
  "properties": {
    "iso:country":"GB",
    "sg:address":"99 Kensington, Kensington",
    "sg:city":"Liverpool",
    "sg:classifiers":[
        {
            "category":"Bars & Pubs",
            "type":"Food & Drink"
        }
    ],
    "sg:postcode":"L7 8XA",
    "sg:province":"Merseyside",
    "sg:tags":[
        "pubs",
        "inn"
    ],
    "wof:name":"Lord Seldon (The)",
    "wof:placetype":"venue"
},
  "geometry": {"coordinates":[-2.961739,53.410919],"type":"Point"}
}