{
  "type": "Feature",
  "properties": {
    "addr:full":"London Road, Allostock Knutsford Cheshire WA16 9LU",
    "addr:postcode":"wa16 9lu",
    "addr:street":"London Road",
    "iso:country":"GB",
    "sg:address":"London Road, Allostock",
    "sg:city":"Knutsford",
    "sg:classifiers":[
        {
            "category":"Travel",
            "subcategory":"Hotels & Motels",
            "type":"Entertainment"
        }
    ],
    "sg:postcode":"WA16 9LU",
    "sg:province":"Cheshire",
    "wof:name":"Cottage Restaurant & Lodge",
    "wof:placetype":"venue"
},
  "geometry": {"coordinates":[-2.383348,53.235809],"type":"Point"}
}