{
  "type": "Feature",
  "properties": {
    "addr:full":"2 Court Street Whitechapel Greater London E1 1DG",
    "addr:housenumber":"2",
    "addr:postcode":"e1 1dg",
    "addr:street":"Court Street",
    "iso:country":"GB",
    "sg:address":"2 Court Street",
    "sg:city":"Whitechapel",
    "sg:classifiers":[
        {
            "category":"Travel",
            "subcategory":"Travel Agent",
            "type":"Entertainment"
        }
    ],
    "sg:phone":"+44 20 7247 8466",
    "sg:postcode":"E1 1DG",
    "sg:province":"Greater London",
    "wof:name":"G A Travel Centre",
    "wof:placetype":"venue"
},
  "geometry": {"coordinates":[-0.061187,51.518993],"type":"Point"}
}