{
  "type": "Feature",
  "properties": {
    "iso:country":"GB",
    "sg:address":"The First Floor Offices, Midlands House, 194 Torrington Avenue",
    "sg:city":"Coventry",
    "sg:classifiers":[
        {
            "category":"Professional",
            "subcategory":"Advertising",
            "type":"Services"
        }
    ],
    "sg:phone":"+44 24 7647 4310",
    "sg:postcode":"CV4 9BL",
    "sg:province":"Warwickshire",
    "sg:tags":[
        "agency"
    ],
    "wof:name":"Adetch Marketing",
    "wof:placetype":"venue"
},
  "geometry": {"coordinates":[-1.577009,52.397991],"type":"Point"}
}