{
  "type": "Feature",
  "properties": {
    "addr:full":"23 White Sq, Clapham Common Clapham Greater London SW4 7JL",
    "addr:housenumber":"23",
    "addr:postcode":"sw4 7jl",
    "addr:street":"White Sq Clapham Common",
    "iso:country":"GB",
    "sg:address":"23 White Sq, Clapham Common",
    "sg:city":"Clapham",
    "sg:classifiers":[
        {
            "category":"Retail",
            "subcategory":"Driving School",
            "type":"Services"
        }
    ],
    "sg:phone":"+44 20 7928 6838",
    "sg:postcode":"SW4 7JL",
    "sg:province":"Greater London",
    "wof:name":"Clapham & Streatham Driving School",
    "wof:placetype":"venue"
},
  "geometry": {"coordinates":[-0.1323750019,51.4611473083],"type":"Point"}
}