{
  "type": "Feature",
  "properties": {
    "addr:full":"Eden Cottage, Rodridge Lane, Station Town Wingate Durham TS28 5EZ",
    "addr:postcode":"ts28 5ez",
    "addr:street":"Rodridge Lane Station;Wingate",
    "iso:country":"GB",
    "sg:address":"Eden Cottage, Rodridge Lane, Station Town",
    "sg:city":"Wingate",
    "sg:classifiers":[
        {
            "category":"Arts & Performance",
            "subcategory":"Music",
            "type":"Entertainment"
        },
        {
            "category":"Arts & Performance",
            "subcategory":"Theater",
            "type":"Entertainment"
        }
    ],
    "sg:phone":"+44 1429 838686",
    "sg:postcode":"TS28 5EZ",
    "sg:province":"Durham",
    "sg:tags":[
        "musician",
        "orchestra",
        "composer"
    ],
    "wof:name":"A Solo Highland Piper",
    "wof:placetype":"venue"
},
  "geometry": {"coordinates":[-1.379784,54.734425],"type":"Point"}
}