{
  "type": "Feature",
  "properties": {
    "addr:full":"18 Ledbury, Great Linford Milton Keynes Buckinghamshire MK14 5DS",
    "addr:housenumber":"18",
    "addr:postcode":"mk14 5ds",
    "addr:street":"Ledbury",
    "iso:country":"GB",
    "sg:address":"18 Ledbury, Great Linford",
    "sg:city":"Milton Keynes",
    "sg:classifiers":[
        {
            "category":"Professional",
            "subcategory":"Accounting & Tax Preparation",
            "type":"Services"
        }
    ],
    "sg:phone":"+44 1908 690066",
    "sg:postcode":"MK14 5DS",
    "sg:province":"Buckinghamshire",
    "sg:tags":[
        "accountant"
    ],
    "wof:name":"Smith Pearman & Co",
    "wof:placetype":"venue"
},
  "geometry": {"coordinates":[-0.7611560225,52.0695915222],"type":"Point"}
}