{
  "type": "Feature",
  "properties": {
    "addr:full":"Unit 2 Dunlop Rd, Hunt End Indust Est Redditch Warwickshire B97 5XP",
    "addr:housenumber":"unit 2",
    "addr:postcode":"b97 5xp",
    "addr:street":"Dunlop Rd;End Indust Est",
    "iso:country":"GB",
    "sg:address":"Unit 2 Dunlop Rd, Hunt End Indust Est",
    "sg:city":"Redditch",
    "sg:classifiers":[
        {
            "category":"Professional",
            "subcategory":"Art Services",
            "type":"Services"
        }
    ],
    "sg:phone":"+44 1527 402424",
    "sg:postcode":"B97 5XP",
    "sg:province":"Warwickshire",
    "sg:tags":[
        "decorating",
        "painting"
    ],
    "wof:name":"Crown Frances Decorator Trade Centre",
    "wof:placetype":"venue"
},
  "geometry": {"coordinates":[-1.9497900009,52.2760276794],"type":"Point"}
}