{
  "type": "Feature",
  "properties": {
    "addr:full":"7 Bow Ct, Fletchworth Gate Coventry West Midlands CV5 6SP",
    "addr:housenumber":"7",
    "addr:postcode":"cv5 6sp",
    "addr:street":"Bow Ct Fletchworth Gate",
    "iso:country":"GB",
    "sg:address":"7 Bow Ct, Fletchworth Gate",
    "sg:city":"Coventry",
    "sg:classifiers":[
        {
            "category":"Professional",
            "subcategory":"Management & Consulting",
            "type":"Services"
        }
    ],
    "sg:phone":"+44 24 7667 0181",
    "sg:postcode":"CV5 6SP",
    "sg:province":"West Midlands",
    "sg:tags":[
        "marketing",
        "consultant"
    ],
    "wof:name":"International Research Consultants Ltd",
    "wof:placetype":"venue"
},
  "geometry": {"coordinates":[-1.551253,52.396263],"type":"Point"}
}