{
  "type": "Feature",
  "properties": {
    "addr:full":"90 Ouseley Road, Wraysbury Staines Berkshire TW19 5JH",
    "addr:housenumber":"90",
    "addr:postcode":"tw19 5jh",
    "addr:street":"Ouseley Road",
    "iso:country":"GB",
    "sg:address":"90 Ouseley Road, Wraysbury",
    "sg:city":"Staines",
    "sg:classifiers":[
        {
            "category":"Professional",
            "subcategory":"Management & Consulting",
            "type":"Services"
        }
    ],
    "sg:postcode":"TW19 5JH",
    "sg:province":"Berkshire",
    "sg:tags":[
        "consultant",
        "business"
    ],
    "wof:name":"Abbco Consultancy Ltd.",
    "wof:placetype":"venue"
},
  "geometry": {"coordinates":[-0.5711600184,51.4532470703],"type":"Point"}
}