{
  "type": "Feature",
  "properties": {
    "iso:country":"GB",
    "sg:address":"30 Eldred Road",
    "sg:city":"Barking",
    "sg:classifiers":[
        {
            "category":"Building & Trades",
            "subcategory":"Cleaning & Sanitation",
            "type":"Services"
        }
    ],
    "sg:postcode":"IG11 7YH",
    "sg:province":"Essex",
    "sg:tags":[
        "contracting",
        "commercial"
    ],
    "wof:name":"Advanced Cleaning Services",
    "wof:placetype":"venue"
},
  "geometry": {"coordinates":[0.089538,51.534496],"type":"Point"}
}