{
  "type": "Feature",
  "properties": {
    "addr:full":"Unit 1, Martin Court, Bulwell Nottingham Nottinghamshire NG6 8US",
    "addr:housenumber":"unit 1",
    "addr:postcode":"ng6 8us",
    "addr:street":"Martin Court",
    "iso:country":"GB",
    "sg:address":"Unit 1, Martin Court, Bulwell",
    "sg:city":"Nottingham",
    "sg:classifiers":[
        {
            "category":"Professional",
            "subcategory":"Printing & Photocopies",
            "type":"Services"
        }
    ],
    "sg:phone":"+44 115 977 0771",
    "sg:postcode":"NG6 8US",
    "sg:province":"Nottinghamshire",
    "sg:tags":[
        "printer"
    ],
    "wof:name":"Central Colour Ltd.",
    "wof:placetype":"venue"
},
  "geometry": {"coordinates":[-1.194679,53.003891],"type":"Point"}
}