{
  "type": "Feature",
  "properties": {
    "addr:full":"11 Albert Street Peterhead Aberdeenshire AB42 1ZW",
    "addr:housenumber":"11",
    "addr:postcode":"ab42 1zw",
    "addr:street":"Albert Street",
    "iso:country":"GB",
    "sg:address":"11 Albert Street",
    "sg:city":"Peterhead",
    "sg:classifiers":[
        {
            "category":"Wholesale",
            "subcategory":"Seafood",
            "type":"Manufacturing & Wholesale Goods"
        },
        {
            "category":"Food & Beverages",
            "subcategory":"Meat & Fish",
            "type":"Retail Goods"
        }
    ],
    "sg:phone":"+44 1779 479672",
    "sg:postcode":"AB42 1ZW",
    "sg:province":"Aberdeenshire",
    "sg:tags":[
        "merchant"
    ],
    "wof:name":"Quayside Quality Fish Supplies",
    "wof:placetype":"venue"
},
  "geometry": {"coordinates":[-1.7720669508,57.5073356628],"type":"Point"}
}