{
  "type": "Feature",
  "properties": {
    "addr:full":"St. Johns Lane Barnstaple Devon EX32 9DD",
    "addr:postcode":"ex32 9dd",
    "addr:street":"St. Johns Lane",
    "iso:country":"GB",
    "sg:address":"St. Johns Lane",
    "sg:city":"Barnstaple",
    "sg:classifiers":[
        {
            "category":"Education",
            "subcategory":"Music School",
            "type":"Public Place"
        }
    ],
    "sg:phone":"+44 1271 342456",
    "sg:postcode":"EX32 9DD",
    "sg:province":"Devon",
    "sg:tags":[
        "conservatory"
    ],
    "wof:name":"West Country Conservatories",
    "wof:placetype":"venue"
},
  "geometry": {"coordinates":[-4.039589,51.071945],"type":"Point"}
}