{
  "type": "Feature",
  "properties": {
    "addr:full":"414 Newark Road Lincoln Lincolnshire LN6 8RX",
    "addr:housenumber":"414",
    "addr:postcode":"ln6 8rx",
    "addr:street":"Newark Road",
    "iso:country":"GB",
    "sg:address":"414 Newark Road",
    "sg:city":"Lincoln",
    "sg:classifiers":[
        {
            "category":"Professional",
            "subcategory":"Accounting & Tax Preparation",
            "type":"Services"
        }
    ],
    "sg:phone":"+44 1522 520338",
    "sg:postcode":"LN6 8RX",
    "sg:province":"Lincolnshire",
    "sg:tags":[
        "accountant",
        "activity"
    ],
    "wof:name":"R P Ellis",
    "wof:placetype":"venue"
},
  "geometry": {"coordinates":[-0.567311,53.200134],"type":"Point"}
}