{
  "type": "Feature",
  "properties": {
    "addr:full":"20 Rosemary Ave,, Lwr Earley, Reading Berkshire RG6 5YQ",
    "addr:housenumber":"20",
    "addr:postcode":"rg6 5yq",
    "addr:street":"Rosemary Ave",
    "iso:country":"GB",
    "sg:address":"20 Rosemary Ave,, Lwr Earley,",
    "sg:city":"Reading",
    "sg:classifiers":[
        {
            "category":"Wholesale",
            "subcategory":"Office Equipment",
            "type":"Manufacturing & Wholesale Goods"
        }
    ],
    "sg:postcode":"RG6 5YQ",
    "sg:province":"Berkshire",
    "sg:tags":[
        "partition",
        "cubicle"
    ],
    "wof:name":"Effective Partitioning Etc Ltd",
    "wof:placetype":"venue"
},
  "geometry": {"coordinates":[-0.9383140206,51.4248962402],"type":"Point"}
}