{
  "type": "Feature",
  "properties": {
    "addr:full":"55 Broomlands St Paisley Renfrewshire PA1 2NQ",
    "addr:housenumber":"55",
    "addr:postcode":"pa1 2nq",
    "addr:street":"Broomlands St",
    "iso:country":"GB",
    "sg:address":"55 Broomlands St",
    "sg:city":"Paisley",
    "sg:classifiers":[
        {
            "category":"Professional",
            "subcategory":"Engineering",
            "type":"Services"
        }
    ],
    "sg:phone":"+44 141 889 7911",
    "sg:postcode":"PA1 2NQ",
    "sg:province":"Renfrewshire",
    "sg:tags":[
        "contractor",
        "electrical",
        "engineer"
    ],
    "wof:name":"G Mullen (Electrical Contractor) Ltd",
    "wof:placetype":"venue"
},
  "geometry": {"coordinates":[-4.4437,55.842213],"type":"Point"}
}