{
  "type": "Feature",
  "properties": {
    "addr:full":"Whipps Cross University Hospital, Leytonstone London Greater London E11 1NR",
    "addr:postcode":"e11 1nr",
    "addr:street":"Whipps",
    "iso:country":"GB",
    "sg:address":"Whipps Cross University Hospital, Leytonstone",
    "sg:city":"London",
    "sg:classifiers":[
        {
            "category":"Health Services",
            "subcategory":"Hospital",
            "type":"Services"
        }
    ],
    "sg:phone":"+44 20 8539 5522",
    "sg:postcode":"E11 1NR",
    "sg:province":"Greater London",
    "wof:name":"Whipps Cross University Hospital NHS Trust",
    "wof:placetype":"venue"
},
  "geometry": {"coordinates":[0.0123819998,51.5763626099],"type":"Point"}
}