{
  "type": "Feature",
  "properties": {
    "iso:country":"GB",
    "sg:address":"81 Waldon Street",
    "sg:city":"Hartlepool",
    "sg:classifiers":[
        {
            "category":"Organizations",
            "subcategory":"Membership Organization",
            "type":"Services"
        },
        {
            "category":"Arena",
            "subcategory":"Sports Club",
            "type":"Entertainment"
        }
    ],
    "sg:phone":"+44 1429 260204",
    "sg:postcode":"TS24 7QJ",
    "sg:province":"Durham",
    "wof:name":"Cameron Sports & Social Club",
    "wof:placetype":"venue"
},
  "geometry": {"coordinates":[-1.2142989635,54.6811714172],"type":"Point"}
}