{
  "type": "Feature",
  "properties": {
    "addr:full":"Protea House, Marine Parade Dover Kent CT17 9AW",
    "addr:postcode":"ct17 9aw",
    "addr:street":"Marine Parade Dover",
    "iso:country":"GB",
    "sg:address":"Protea House, Marine Parade",
    "sg:city":"Dover",
    "sg:classifiers":[
        {
            "category":"Freight",
            "type":"Transportation"
        }
    ],
    "sg:phone":"+44 1304 202701",
    "sg:postcode":"CT17 9AW",
    "sg:province":"Kent",
    "sg:tags":[
        "forwarders"
    ],
    "wof:name":"Gibbons Freight",
    "wof:placetype":"venue"
},
  "geometry": {"coordinates":[1.322014,51.125141],"type":"Point"}
}