{
  "type": "Feature",
  "properties": {
    "addr:full":"4 Cocoa Yard, Pillory Street Nantwich Cheshire CW5 5BQ",
    "addr:housenumber":"4",
    "addr:postcode":"cw5 5bq",
    "addr:street":"Cocoa Yard Pillory Street",
    "iso:country":"GB",
    "sg:address":"4 Cocoa Yard, Pillory Street",
    "sg:city":"Nantwich",
    "sg:classifiers":[
        {
            "category":"Personal",
            "subcategory":"Beauty Salon",
            "type":"Services"
        }
    ],
    "sg:postcode":"CW5 5BQ",
    "sg:province":"Cheshire",
    "sg:tags":[
        "lady",
        "hairdresser"
    ],
    "wof:name":"Sas's Hair Design",
    "wof:placetype":"venue"
},
  "geometry": {"coordinates":[-2.5165019035,53.0658912659],"type":"Point"}
}