{
  "type": "Feature",
  "properties": {
    "addr:full":"102 Station Parade Harrogate North Yorkshire HG1 1HQ",
    "addr:housenumber":"102",
    "addr:postcode":"hg1 1hq",
    "addr:street":"Station Parade",
    "iso:country":"GB",
    "sg:address":"102 Station Parade",
    "sg:city":"Harrogate",
    "sg:classifiers":[
        {
            "category":"Professional",
            "subcategory":"Engineering",
            "type":"Services"
        }
    ],
    "sg:phone":"+44 1423 530999",
    "sg:postcode":"HG1 1HQ",
    "sg:province":"North Yorkshire",
    "sg:tags":[
        "consulting",
        "engineer"
    ],
    "wof:name":"Stevenson Calam Associates",
    "wof:placetype":"venue"
},
  "geometry": {"coordinates":[-1.5365159512,53.9892311096],"type":"Point"}
}