{
  "type": "Feature",
  "properties": {
    "iso:country":"GB",
    "sg:address":"34 Victoria Street",
    "sg:city":"Morecambe",
    "sg:classifiers":[
        {
            "category":"Personal",
            "subcategory":"Barber",
            "type":"Services"
        }
    ],
    "sg:phone":"+44 1524 426452",
    "sg:postcode":"LA4 4AJ",
    "sg:province":"Lancashire",
    "sg:tags":[
        "unisex",
        "men's",
        "hairdresser"
    ],
    "wof:name":"COLIN BROWN",
    "wof:placetype":"venue"
},
  "geometry": {"coordinates":[-2.868408,54.071774],"type":"Point"}
}