{
  "type": "Feature",
  "properties": {
    "iso:country":"GB",
    "sg:address":"Moorlands Farm, Drayton",
    "sg:city":"Langport",
    "sg:classifiers":[
        {
            "category":"Professional",
            "subcategory":"Computer Services",
            "type":"Services"
        }
    ],
    "sg:phone":"+44 20 8400 1652",
    "sg:postcode":"TA10 0LT",
    "sg:province":"Somerset",
    "sg:tags":[
        "consultant"
    ],
    "wof:name":"Hans Ltd.",
    "wof:placetype":"venue"
},
  "geometry": {"coordinates":[-2.847615,51.019234],"type":"Point"}
}