{
  "type": "Feature",
  "properties": {
    "iso:country":"GB",
    "sg:address":"380 South Road",
    "sg:city":"Sheffield",
    "sg:classifiers":[
        {
            "category":"Personal",
            "subcategory":"Beauty Salon",
            "type":"Services"
        }
    ],
    "sg:postcode":"S6 3TF",
    "sg:province":"South Yorkshire",
    "wof:name":"Pretty Woman",
    "wof:placetype":"venue"
},
  "geometry": {"coordinates":[-1.502002,53.394505],"type":"Point"}
}