{
  "type": "Feature",
  "properties": {
    "addr:full":"H T V Studios, Bath Road, Arnos Vale Bristol City of Bristol BS4 3HG",
    "addr:postcode":"bs4 3hg",
    "addr:street":"Bath Road",
    "iso:country":"GB",
    "sg:address":"H T V Studios, Bath Road, Arnos Vale",
    "sg:city":"Bristol",
    "sg:classifiers":[
        {
            "category":"Communications",
            "type":"Services"
        }
    ],
    "sg:phone":"+44 117 972 2451",
    "sg:postcode":"BS4 3HG",
    "sg:province":"City of Bristol",
    "sg:tags":[
        "audio-visual"
    ],
    "wof:name":"Chatford Group Video & Sound Rental",
    "wof:placetype":"venue"
},
  "geometry": {"coordinates":[-2.5593988895,51.440410614],"type":"Point"}
}