{
  "type": "Feature",
  "properties": {
    "iso:country":"GB",
    "sg:address":"153 Milton Ave, Broadgreen",
    "sg:city":"Liverpool",
    "sg:classifiers":[
        {
            "category":"Professional",
            "subcategory":"Computer Services",
            "type":"Services"
        }
    ],
    "sg:phone":"+44 151 480 6103",
    "sg:postcode":"L14 6TF",
    "sg:province":"Merseyside",
    "sg:tags":[
        "aided",
        "design"
    ],
    "wof:name":"A K B Cad Services Ltd",
    "wof:placetype":"venue"
},
  "geometry": {"coordinates":[-2.880803,53.411934],"type":"Point"}
}