{
  "type": "Feature",
  "properties": {
    "addr:full":"197 St Marys Road, Garston Liverpool Merseyside L19 0NE",
    "addr:housenumber":"197",
    "addr:postcode":"l19 0ne",
    "addr:street":"St Marys Road",
    "iso:country":"GB",
    "sg:address":"197 St Marys Road, Garston",
    "sg:city":"Liverpool",
    "sg:classifiers":[
        {
            "category":"Personal",
            "subcategory":"Beauty Salon",
            "type":"Services"
        },
        {
            "category":"Personal",
            "subcategory":"Barber",
            "type":"Services"
        }
    ],
    "sg:phone":"+44 151 427 4981",
    "sg:postcode":"L19 0NE",
    "sg:province":"Merseyside",
    "sg:tags":[
        "unisex",
        "hairdresser"
    ],
    "wof:name":"Caprice",
    "wof:placetype":"venue"
},
  "geometry": {"coordinates":[-2.9074110985,53.3580627441],"type":"Point"}
}