{
  "type": "Feature",
  "properties": {
    "iso:country":"GB",
    "sg:address":"Stanley Av",
    "sg:city":"Romford",
    "sg:classifiers":[
        {
            "category":"Professional",
            "subcategory":"Secretarial Services",
            "type":"Services"
        }
    ],
    "sg:phone":"+44 1708 746384",
    "sg:postcode":"RM2 5BX",
    "sg:province":"Essex",
    "wof:name":"Type-Rite",
    "wof:placetype":"venue"
},
  "geometry": {"coordinates":[0.200683,51.58284],"type":"Point"}
}