{
  "type": "Feature",
  "properties": {
    "iso:country":"GB",
    "sg:address":"13 Rosebank, Hensingham",
    "sg:city":"Whitehaven",
    "sg:classifiers":[
        {
            "category":"Building & Trades",
            "subcategory":"Plumbing",
            "type":"Services"
        }
    ],
    "sg:phone":"+44 1946 692960",
    "sg:postcode":"CA28 8QJ",
    "sg:province":"Cumbria",
    "sg:tags":[
        "heating"
    ],
    "wof:name":"W H Holloway",
    "wof:placetype":"venue"
},
  "geometry": {"coordinates":[-3.57082,54.538307],"type":"Point"}
}