{
  "type": "Feature",
  "properties": {
    "iso:country":"GB",
    "sg:address":"Unit 101",
    "sg:city":"Livingston",
    "sg:classifiers":[
        {
            "category":"Food & Beverages",
            "subcategory":"Liquor & Beverages",
            "type":"Retail Goods"
        }
    ],
    "sg:phone":"+44 1506 442092",
    "sg:postcode":"EH54 6NB",
    "sg:province":"West Lothian",
    "sg:tags":[
        "beer",
        "spirit",
        "wines"
    ],
    "wof:name":"Victoria Wine Co",
    "wof:placetype":"venue"
},
  "geometry": {"coordinates":[-3.5204091072,55.8912200928],"type":"Point"}
}