{
  "type": "Feature",
  "properties": {
    "addr:full":"182 Oldfield Lane South Greenford Greater London UB6 9JS",
    "addr:housenumber":"182",
    "addr:postcode":"ub6 9js",
    "addr:street":"Oldfield Lane South",
    "iso:country":"GB",
    "sg:address":"182 Oldfield Lane South",
    "sg:city":"Greenford",
    "sg:classifiers":[
        {
            "category":"Organizations",
            "subcategory":"Membership Organization",
            "type":"Services"
        }
    ],
    "sg:phone":"+44 20 8578 5733",
    "sg:postcode":"UB6 9JS",
    "sg:province":"Greater London",
    "sg:tags":[
        "club"
    ],
    "wof:name":"The Royal British Legion",
    "wof:placetype":"venue"
},
  "geometry": {"coordinates":[-0.349126,51.535648],"type":"Point"}
}