{
  "type": "Feature",
  "properties": {
    "iso:country":"GB",
    "sg:address":"Bolam Landfill Site, Bolam",
    "sg:city":"Darlington",
    "sg:classifiers":[
        {
            "category":"Utilities",
            "subcategory":"Refuse",
            "type":"Services"
        }
    ],
    "sg:phone":"+44 1388 833323",
    "sg:postcode":"DL2 2UP",
    "sg:province":"Durham",
    "sg:tags":[
        "disposal",
        "waste"
    ],
    "wof:name":"Bolom",
    "wof:placetype":"venue"
},
  "geometry": {"coordinates":[-1.6924500465,54.5990142822],"type":"Point"}
}