{
  "type": "Feature",
  "properties": {
    "iso:country":"GB",
    "sg:address":"27 Peascod Street",
    "sg:city":"Windsor",
    "sg:classifiers":[
        {
            "category":"Professional",
            "subcategory":"Employment Agencies",
            "type":"Services"
        }
    ],
    "sg:phone":"+44 1753 830141",
    "sg:postcode":"SL4 1DU",
    "sg:province":"Berkshire",
    "sg:tags":[
        "consultant"
    ],
    "wof:name":"Masterclass Recruitment & Training",
    "wof:placetype":"venue"
},
  "geometry": {"coordinates":[-0.609493,51.481594],"type":"Point"}
}