{
  "type": "Feature",
  "properties": {
    "addr:full":"Turnham Road London Greater London SE4 2HH",
    "addr:postcode":"se4 2hh",
    "addr:street":"Turnham Road",
    "iso:country":"GB",
    "sg:address":"Turnham Road",
    "sg:city":"London",
    "sg:classifiers":[
        {
            "category":"Education",
            "subcategory":"School",
            "type":"Public Place"
        }
    ],
    "sg:phone":"+44 20 7639 0440",
    "sg:postcode":"SE4 2HH",
    "sg:province":"Greater London",
    "sg:tags":[
        "local",
        "authority"
    ],
    "wof:name":"Turnham Primary School",
    "wof:placetype":"venue"
},
  "geometry": {"coordinates":[-0.0418739989,51.4590568542],"type":"Point"}
}