{
  "type": "Feature",
  "properties": {
    "iso:country":"GB",
    "sg:address":"Perry St Works, Factory Lane",
    "sg:city":"Chard",
    "sg:classifiers":[
        {
            "category":"Shopping",
            "subcategory":"Crafts & Fabrics",
            "type":"Retail Goods"
        }
    ],
    "sg:phone":"+44 1460 220312",
    "sg:postcode":"TA20 2NR",
    "sg:province":"Devon",
    "sg:tags":[
        "netting"
    ],
    "wof:name":"Swiss Net Uk",
    "wof:placetype":"venue"
},
  "geometry": {"coordinates":[-2.94348,50.845173],"type":"Point"}
}