{
  "type": "Feature",
  "properties": {
    "addr:full":"Suite 203 Mill Studio Business C, Entre Crane Mead Ware Hertfordshire SG12 9PY",
    "addr:housenumber":"suite 203 mill studio business c entre",
    "addr:postcode":"sg12 9py",
    "addr:street":"Crane Mead Ware",
    "iso:country":"GB",
    "sg:address":"Suite 203 Mill Studio Business C, Entre Crane Mead",
    "sg:city":"Ware",
    "sg:classifiers":[
        {
            "category":"Shopping",
            "subcategory":"Stationery & Office Supplies",
            "type":"Retail Goods"
        }
    ],
    "sg:phone":"+44 1920 444275",
    "sg:postcode":"SG12 9PY",
    "sg:province":"Hertfordshire",
    "sg:tags":[
        "item",
        "promotional"
    ],
    "wof:name":"Ulterior Motifs Ltd.",
    "wof:placetype":"venue"
},
  "geometry": {"coordinates":[-0.035127,51.816338],"type":"Point"}
}