{
  "type": "Feature",
  "properties": {
    "iso:country":"GB",
    "sg:address":"6 Ploughlands, Dundonald",
    "sg:city":"Kilmarnock",
    "sg:classifiers":[
        {
            "category":"Shopping",
            "subcategory":"Department Store",
            "type":"Retail Goods"
        },
        {
            "category":"Home & Garden",
            "subcategory":"Garden Supply",
            "type":"Retail Goods"
        }
    ],
    "sg:phone":"+44 1563 850215",
    "sg:postcode":"KA2 9BT",
    "sg:province":"East Ayrshire",
    "sg:tags":[
        "centre"
    ],
    "wof:name":"FRASER'S GARDEN CENTRE",
    "wof:placetype":"venue"
},
  "geometry": {"coordinates":[-4.586279,55.579632],"type":"Point"}
}