{
  "type": "Feature",
  "properties": {
    "addr:full":"17 Harley Street London Greater London W1G 9QH",
    "addr:housenumber":"17",
    "addr:postcode":"w1g 9qh",
    "addr:street":"Harley Street",
    "iso:country":"GB",
    "sg:address":"17 Harley Street",
    "sg:city":"London",
    "sg:classifiers":[
        {
            "category":"Health Services",
            "subcategory":"Doctor",
            "type":"Services"
        }
    ],
    "sg:phone":"+44 20 7580 6283",
    "sg:postcode":"W1G 9QH",
    "sg:province":"Greater London",
    "sg:tags":[
        "surgeon"
    ],
    "wof:name":"Patrick J Whitfield",
    "wof:placetype":"venue"
},
  "geometry": {"coordinates":[-0.1464630067,51.5174674988],"type":"Point"}
}