{
  "type": "Feature",
  "properties": {
    "addr:full":"32 Gables Avenue Borehamwood Hertfordshire WD6 4SP",
    "addr:housenumber":"32",
    "addr:postcode":"wd6 4sp",
    "addr:street":"Gables Avenue Borehamwood",
    "iso:country":"GB",
    "sg:address":"32 Gables Avenue",
    "sg:city":"Borehamwood",
    "sg:classifiers":[
        {
            "category":"Professional",
            "subcategory":"Accounting & Tax Preparation",
            "type":"Services"
        }
    ],
    "sg:phone":"+44 20 8953 9885",
    "sg:postcode":"WD6 4SP",
    "sg:province":"Hertfordshire",
    "sg:tags":[
        "accountant"
    ],
    "wof:name":"Sherman Bass Trent & Co.",
    "wof:placetype":"venue"
},
  "geometry": {"coordinates":[-0.282365,51.656895],"type":"Point"}
}