{
  "type": "Feature",
  "properties": {
    "iso:country":"GB",
    "sg:address":"4 Barron Street",
    "sg:city":"Aberdeen",
    "sg:classifiers":[
        {
            "category":"Fast Food",
            "type":"Food & Drink"
        }
    ],
    "sg:phone":"+44 1224 276976",
    "sg:postcode":"AB24 2QF",
    "sg:province":"Aberdeen City",
    "sg:tags":[
        "away",
        "meal",
        "outlet",
        "take"
    ],
    "wof:name":"Snappy Tomato Pizza",
    "wof:placetype":"venue"
},
  "geometry": {"coordinates":[-2.119332,57.167747],"type":"Point"}
}