{
  "type": "Feature",
  "properties": {
    "iso:country":"GB",
    "sg:address":"4 St Marys St",
    "sg:city":"Carmarthen",
    "sg:classifiers":[
        {
            "category":"Professional",
            "subcategory":"Lawyer & Legal Services",
            "type":"Services"
        }
    ],
    "sg:phone":"+44 1267 236426",
    "sg:postcode":"SA31 1TN",
    "sg:province":"Carmarthenshire",
    "sg:tags":[
        "solicitor"
    ],
    "wof:name":"Trant & Richards",
    "wof:placetype":"venue"
},
  "geometry": {"coordinates":[-4.3067789078,51.856086731],"type":"Point"}
}