{
  "type": "Feature",
  "properties": {
    "addr:full":"22 Ashwell Road Oakham Leicestershire LE15 6QG",
    "addr:housenumber":"22",
    "addr:postcode":"le15 6qg",
    "addr:street":"Ashwell Road",
    "iso:country":"GB",
    "sg:address":"22 Ashwell Road",
    "sg:city":"Oakham",
    "sg:classifiers":[
        {
            "category":"Food & Beverages",
            "subcategory":"Groceries & Convenience Stores",
            "type":"Retail Goods"
        }
    ],
    "sg:phone":"+44 1572 722214",
    "sg:postcode":"LE15 6QG",
    "sg:province":"Leicestershire",
    "wof:name":"MACE CONVENIENCE EXPRESS",
    "wof:placetype":"venue"
},
  "geometry": {"coordinates":[-0.725771,52.673717],"type":"Point"}
}