{
  "type": "Feature",
  "properties": {
    "iso:country":"GB",
    "sg:address":"Gainsborough Lodge, South Farm Road",
    "sg:city":"Worthing",
    "sg:classifiers":[
        {
            "category":"Organizations",
            "subcategory":"Community Association",
            "type":"Services"
        }
    ],
    "sg:phone":"+44 1903 207968",
    "sg:postcode":"BN14 7ED",
    "sg:province":"West Sussex",
    "sg:tags":[
        "society",
        "housing"
    ],
    "wof:name":"Anchor Trust",
    "wof:placetype":"venue"
},
  "geometry": {"coordinates":[-0.3783999979,50.8230209351],"type":"Point"}
}