{
  "type": "Feature",
  "properties": {
    "addr:full":"Ghyll House, Wreay Carlisle Cumbria CA4 0SA",
    "addr:postcode":"ca4 0sa",
    "addr:street":"Wreay",
    "iso:country":"GB",
    "sg:address":"Ghyll House, Wreay",
    "sg:city":"Carlisle",
    "sg:classifiers":[
        {
            "category":"Farming",
            "subcategory":"Farm",
            "type":"Manufacturing & Wholesale Goods"
        }
    ],
    "sg:phone":"+44 16974 73297",
    "sg:postcode":"CA4 0SA",
    "sg:province":"Cumbria",
    "sg:tags":[
        "mixed",
        "crop"
    ],
    "wof:name":"Thomas W Bird",
    "wof:placetype":"venue"
},
  "geometry": {"coordinates":[-2.8563189507,54.7977600098],"type":"Point"}
}