{
  "type": "Feature",
  "properties": {
    "iso:country":"GB",
    "sg:address":"4 Victoria Ho, Dapps Hill, Keynsham",
    "sg:city":"Bristol",
    "sg:classifiers":[
        {
            "category":"Real Estate",
            "subcategory":"Surveying",
            "type":"Services"
        }
    ],
    "sg:postcode":"BS31 1UL",
    "sg:province":"City of Bristol",
    "sg:tags":[
        "building",
        "surveyor"
    ],
    "wof:name":"Isherwood,M J,",
    "wof:placetype":"venue"
},
  "geometry": {"coordinates":[-2.4964289665,51.4144706726],"type":"Point"}
}