{
  "type": "Feature",
  "properties": {
    "iso:country":"GB",
    "sg:address":"Macadam Road, Earlstrees Industrial Estate",
    "sg:city":"Corby",
    "sg:classifiers":[
        {
            "category":"Autos & Motor Vehicles",
            "subcategory":"Auto Supplies",
            "type":"Retail Goods"
        }
    ],
    "sg:postcode":"NN17 4JN",
    "sg:province":"Northamptonshire",
    "sg:tags":[
        "transmission",
        "equipment",
        "power"
    ],
    "wof:name":"Dulmison (U K) Ltd.",
    "wof:placetype":"venue"
},
  "geometry": {"coordinates":[-0.685729,52.504768],"type":"Point"}
}