{
  "type": "Feature",
  "properties": {
    "iso:country":"GB",
    "sg:address":"62 Hillfoot Street",
    "sg:city":"Dunoon",
    "sg:classifiers":[
        {
            "category":"Professional",
            "subcategory":"Art Services",
            "type":"Services"
        }
    ],
    "sg:phone":"+44 1369 703300",
    "sg:postcode":"PA23 7DT",
    "sg:province":"Argyll and Bute",
    "sg:tags":[
        "framing"
    ],
    "wof:name":"James O'Boyd",
    "wof:placetype":"venue"
},
  "geometry": {"coordinates":[-4.928156,55.947109],"type":"Point"}
}