{
  "type": "Feature",
  "properties": {
    "iso:country":"GB",
    "sg:address":"121 Redworth Road",
    "sg:city":"Shildon",
    "sg:classifiers":[
        {
            "category":"Food & Beverages",
            "subcategory":"Meat & Fish",
            "type":"Retail Goods"
        },
        {
            "category":"Food & Beverages",
            "subcategory":"Groceries & Convenience Stores",
            "type":"Retail Goods"
        }
    ],
    "sg:phone":"+44 1388 773932",
    "sg:postcode":"DL4 2JL",
    "sg:province":"Durham",
    "sg:tags":[
        "shop",
        "chip"
    ],
    "wof:name":"Betty's Fish Shop",
    "wof:placetype":"venue"
},
  "geometry": {"coordinates":[-1.641207,54.623814],"type":"Point"}
}