{
  "type": "Feature",
  "properties": {
    "addr:full":"Unit 2c, Dalston Cross Shopping Centre London Greater London E8 2LX",
    "addr:housenumber":"unit 2c",
    "addr:postcode":"e8 2lx",
    "addr:street":"Cross Shopping Centre",
    "iso:country":"GB",
    "sg:address":"Unit 2c, Dalston Cross Shopping Centre",
    "sg:city":"London",
    "sg:classifiers":[
        {
            "category":"Shopping",
            "subcategory":"Shoes",
            "type":"Retail Goods"
        }
    ],
    "sg:phone":"+44 20 7254 7104",
    "sg:postcode":"E8 2LX",
    "sg:province":"Greater London",
    "sg:tags":[
        "shop"
    ],
    "wof:name":"Oliver Timpson",
    "wof:placetype":"venue"
},
  "geometry": {"coordinates":[-0.0716240034,51.5462532043],"type":"Point"}
}