{
  "type": "Feature",
  "properties": {
    "iso:country":"GB",
    "sg:address":"1240b Evesham Rd",
    "sg:city":"Redditch",
    "sg:classifiers":[
        {
            "category":"Shopping",
            "subcategory":"Florist",
            "type":"Retail Goods"
        }
    ],
    "sg:phone":"+44 1527 893377",
    "sg:postcode":"B96 6AA",
    "sg:province":"Warwickshire",
    "wof:name":"Forget Me Nots",
    "wof:placetype":"venue"
},
  "geometry": {"coordinates":[-1.9375020266,52.2580337524],"type":"Point"}
}