{
  "type": "Feature",
  "properties": {
    "iso:country":"GB",
    "sg:address":"43 Ripon Way",
    "sg:city":"Borehamwood",
    "sg:classifiers":[
        {
            "category":"Professional",
            "subcategory":"Management & Consulting",
            "type":"Services"
        }
    ],
    "sg:phone":"+44 20 8386 9559",
    "sg:postcode":"WD6 2HY",
    "sg:province":"Hertfordshire",
    "sg:tags":[
        "consultant",
        "safety"
    ],
    "wof:name":"Personnel Safety Ltd.",
    "wof:placetype":"venue"
},
  "geometry": {"coordinates":[-0.253253,51.648335],"type":"Point"}
}