{
  "type": "Feature",
  "properties": {
    "addr:full":"86-90 Front Street, Monkseaton Whitley Bay Northumberland NE25 8DN",
    "addr:housenumber":"86-90",
    "addr:postcode":"ne25 8dn",
    "addr:street":"Front Street",
    "iso:country":"GB",
    "sg:address":"86-90 Front Street, Monkseaton",
    "sg:city":"Whitley Bay",
    "sg:classifiers":[
        {
            "category":"Professional",
            "type":"Services"
        }
    ],
    "sg:phone":"+44 191 251 3180",
    "sg:postcode":"NE25 8DN",
    "sg:province":"Northumberland",
    "sg:tags":[
        "marine"
    ],
    "wof:name":"Marine Cargo Access Design Ltd.",
    "wof:placetype":"venue"
},
  "geometry": {"coordinates":[-1.46492,55.040966],"type":"Point"}
}