{
  "type": "Feature",
  "properties": {
    "iso:country":"GB",
    "sg:address":"240 Bawtry Road, Tanyard Shopping Centre",
    "sg:city":"Rotherham",
    "sg:classifiers":[
        {
            "category":"Shopping",
            "subcategory":"Clothing, Apparel, & Fashions",
            "type":"Retail Goods"
        }
    ],
    "sg:phone":"+44 1709 700866",
    "sg:postcode":"S66 1AA",
    "sg:province":"South Yorkshire",
    "sg:tags":[
        "shop"
    ],
    "wof:name":"Java Boutique",
    "wof:placetype":"venue"
},
  "geometry": {"coordinates":[-1.283687,53.42104],"type":"Point"}
}