{
  "type": "Feature",
  "properties": {
    "iso:country":"GB",
    "sg:address":"Wadgate Rd",
    "sg:city":"Felixstowe",
    "sg:classifiers":[
        {
            "category":"Place Of Worship",
            "type":"Public Place"
        }
    ],
    "sg:phone":"+44 1394 271962",
    "sg:postcode":"IP11 8LP",
    "sg:province":"Suffolk",
    "wof:name":"Cavendish Community Church",
    "wof:placetype":"venue"
},
  "geometry": {"coordinates":[1.3330149651,51.9651107788],"type":"Point"}
}