{
  "type": "Feature",
  "properties": {
    "addr:full":"45 Buxton Road, High Lane Stockport Cheshire SK6 8DR",
    "addr:housenumber":"45",
    "addr:postcode":"sk6 8dr",
    "addr:street":"Buxton Road High Lane",
    "iso:country":"GB",
    "sg:address":"45 Buxton Road, High Lane",
    "sg:city":"Stockport",
    "sg:classifiers":[
        {
            "category":"Personal",
            "subcategory":"Beauty Salon",
            "type":"Services"
        }
    ],
    "sg:phone":"+44 1663 764868",
    "sg:postcode":"SK6 8DR",
    "sg:province":"Cheshire",
    "sg:tags":[
        "unisex",
        "hairdresser"
    ],
    "wof:name":"Kutz Hair Studio",
    "wof:placetype":"venue"
},
  "geometry": {"coordinates":[-2.074401,53.364727],"type":"Point"}
}