{
  "type": "Feature",
  "properties": {
    "addr:full":"7 Gordonbrock Road London Greater London SE4 1JA",
    "addr:housenumber":"7",
    "addr:postcode":"se4 1ja",
    "addr:street":"Gordonbrock Road",
    "iso:country":"GB",
    "sg:address":"7 Gordonbrock Road",
    "sg:city":"London",
    "sg:classifiers":[
        {
            "category":"Professional",
            "subcategory":"Detective & Security Services",
            "type":"Services"
        }
    ],
    "sg:postcode":"SE4 1JA",
    "sg:province":"Greater London",
    "sg:tags":[
        "equipment",
        "installers"
    ],
    "wof:name":"Adassa Security & Communication",
    "wof:placetype":"venue"
},
  "geometry": {"coordinates":[-0.0270709991,51.4559173584],"type":"Point"}
}