{
  "type": "Feature",
  "properties": {
    "addr:full":"15a Kings Rd Cardiff Cardiff CF11 9BZ",
    "addr:housenumber":"15a",
    "addr:postcode":"cf11 9bz",
    "addr:street":"Kings Rd",
    "iso:country":"GB",
    "sg:address":"15a Kings Rd",
    "sg:city":"Cardiff",
    "sg:classifiers":[
        {
            "category":"Professional",
            "subcategory":"Business Services",
            "type":"Services"
        }
    ],
    "sg:postcode":"CF11 9BZ",
    "sg:province":"Cardiff",
    "sg:tags":[
        "import",
        "export",
        "agent"
    ],
    "wof:name":"Powell,Mark,",
    "wof:placetype":"venue"
},
  "geometry": {"coordinates":[-3.1966109276,51.4819717407],"type":"Point"}
}