{
  "type": "Feature",
  "properties": {
    "addr:full":"42 Annesley Road Newport Pagnell Buckinghamshire MK16 0BG",
    "addr:housenumber":"42",
    "addr:postcode":"mk16 0bg",
    "addr:street":"Annesley Road",
    "iso:country":"GB",
    "sg:address":"42 Annesley Road",
    "sg:city":"Newport Pagnell",
    "sg:classifiers":[
        {
            "category":"Shopping",
            "subcategory":"Department Store",
            "type":"Retail Goods"
        }
    ],
    "sg:phone":"+44 1908 217884",
    "sg:postcode":"MK16 0BG",
    "sg:province":"Buckinghamshire",
    "wof:name":"Londis",
    "wof:placetype":"venue"
},
  "geometry": {"coordinates":[-0.7354689837,52.0811500549],"type":"Point"}
}