{
  "type": "Feature",
  "properties": {
    "addr:full":"28b Main Street Motherwell North Lanarkshire ML1 4TA",
    "addr:housenumber":"28b",
    "addr:postcode":"ml1 4ta",
    "addr:street":"Main Street",
    "iso:country":"GB",
    "sg:address":"28b Main Street",
    "sg:city":"Motherwell",
    "sg:classifiers":[
        {
            "category":"Banks & Credit Unions",
            "subcategory":"Financial Services",
            "type":"Services"
        }
    ],
    "sg:phone":"+44 1698 833300",
    "sg:postcode":"ML1 4TA",
    "sg:province":"North Lanarkshire",
    "sg:tags":[
        "adviser"
    ],
    "wof:name":"Independent Financial Matters Ltd.",
    "wof:placetype":"venue"
},
  "geometry": {"coordinates":[-3.9780929089,55.821018219],"type":"Point"}
}