{
  "type": "Feature",
  "properties": {
    "addr:full":"St Michaels Road, Wittering Peterborough Cambridgeshire PE8 6DW",
    "addr:postcode":"pe8 6dw",
    "addr:street":"St Michaels Road",
    "iso:country":"GB",
    "sg:address":"St Michaels Road, Wittering",
    "sg:city":"Peterborough",
    "sg:classifiers":[
        {
            "category":"Farming",
            "subcategory":"Nursery",
            "type":"Manufacturing & Wholesale Goods"
        },
        {
            "category":"Education",
            "subcategory":"Preschool",
            "type":"Public Place"
        }
    ],
    "sg:phone":"+44 1780 783150",
    "sg:postcode":"PE8 6DW",
    "sg:province":"Cambridgeshire",
    "sg:tags":[
        "school",
        "creche"
    ],
    "wof:name":"Flying Start Pre School & Daycare Centre",
    "wof:placetype":"venue"
},
  "geometry": {"coordinates":[-0.4384100139,52.6091461182],"type":"Point"}
}