{
  "type": "Feature",
  "properties": {
    "iso:country":"GB",
    "sg:address":"18 Tyersal Garth",
    "sg:city":"Bradford",
    "sg:classifiers":[
        {
            "category":"Building & Trades",
            "subcategory":"Construction",
            "type":"Services"
        }
    ],
    "sg:phone":"+44 1274 661013",
    "sg:postcode":"BD4 8HB",
    "sg:province":"West Yorkshire",
    "sg:tags":[
        "builder"
    ],
    "wof:name":"J T Building Drawing Services",
    "wof:placetype":"venue"
},
  "geometry": {"coordinates":[-1.6981929541,53.7920303345],"type":"Point"}
}