{
  "type": "Feature",
  "properties": {
    "iso:country":"GB",
    "sg:address":"163 Crayford Road",
    "sg:city":"Dartford",
    "sg:classifiers":[
        {
            "category":"Shopping",
            "subcategory":"Used Merchandise",
            "type":"Retail Goods"
        }
    ],
    "sg:phone":"+44 1322 528250",
    "sg:postcode":"DA1 4HA",
    "sg:province":"Kent",
    "sg:tags":[
        "shop",
        "second-hand"
    ],
    "wof:name":"Next To Nothing",
    "wof:placetype":"venue"
},
  "geometry": {"coordinates":[0.179945,51.45092],"type":"Point"}
}