{
  "type": "Feature",
  "properties": {
    "iso:country":"GB",
    "sg:address":"Beauchamp Buildings, Atherstone Industrial Estate",
    "sg:city":"Stratford-upon-avon",
    "sg:classifiers":[
        {
            "category":"Home & Garden",
            "subcategory":"Home Furnishings",
            "type":"Retail Goods"
        }
    ],
    "sg:postcode":"CV37 8DX",
    "sg:province":"Warwickshire",
    "sg:tags":[
        "furnishers",
        "planner",
        "kitchen"
    ],
    "wof:name":"J P Handy",
    "wof:placetype":"venue"
},
  "geometry": {"coordinates":[-1.689294,52.15871],"type":"Point"}
}