{
  "type": "Feature",
  "properties": {
    "addr:full":"2 The Garth Cobham Surrey KT11 2DZ",
    "addr:housenumber":"2",
    "addr:postcode":"kt11 2dz",
    "addr:street":"The Garth Cobham",
    "iso:country":"GB",
    "sg:address":"2 The Garth",
    "sg:city":"Cobham",
    "sg:classifiers":[
        {
            "category":"Professional",
            "subcategory":"Management & Consulting",
            "type":"Services"
        },
        {
            "category":"Professional",
            "subcategory":"Computer Services",
            "type":"Services"
        }
    ],
    "sg:phone":"+44 1932 865794",
    "sg:postcode":"KT11 2DZ",
    "sg:province":"Surrey",
    "sg:tags":[
        "consultant",
        "business",
        "information"
    ],
    "wof:name":"NEMAKAST LTD",
    "wof:placetype":"venue"
},
  "geometry": {"coordinates":[-0.4011349976,51.3378562927],"type":"Point"}
}