{
  "type": "Feature",
  "properties": {
    "iso:country":"GB",
    "sg:address":"Upgang Lane",
    "sg:city":"Whitby",
    "sg:classifiers":[
        {
            "category":"Organizations",
            "subcategory":"Community Association",
            "type":"Services"
        },
        {
            "category":"Organizations",
            "subcategory":"Membership Organization",
            "type":"Services"
        }
    ],
    "sg:phone":"+44 1947 602930",
    "sg:postcode":"YO21 3DT",
    "sg:province":"North Yorkshire",
    "sg:tags":[
        "club",
        "social"
    ],
    "wof:name":"Whitby Conservative Club",
    "wof:placetype":"venue"
},
  "geometry": {"coordinates":[-0.63678,54.493195],"type":"Point"}
}