{
  "type": "Feature",
  "properties": {
    "iso:country":"GB",
    "sg:address":"Unit 4, Block 6",
    "sg:city":"Lanark",
    "sg:classifiers":[
        {
            "category":"Manufacturing",
            "subcategory":"Rubber & Plastics",
            "type":"Manufacturing & Wholesale Goods"
        }
    ],
    "sg:postcode":"ML11 7SR",
    "sg:province":"South Lanarkshire",
    "sg:tags":[
        "supplier",
        "stockist"
    ],
    "wof:name":"Tinto Plastics (Scotland) Ltd.",
    "wof:placetype":"venue"
},
  "geometry": {"coordinates":[-3.804829,55.695557],"type":"Point"}
}