{
  "type": "Feature",
  "properties": {
    "addr:full":"Ash Road South Wrexham Wrexham LL13 9UG",
    "addr:postcode":"ll13 9ug",
    "addr:street":"Ash Road South",
    "iso:country":"GB",
    "sg:address":"Ash Road South",
    "sg:city":"Wrexham",
    "sg:classifiers":[
        {
            "category":"Building & Trades",
            "subcategory":"Plumbing",
            "type":"Services"
        },
        {
            "category":"Building & Trades",
            "subcategory":"Construction",
            "type":"Services"
        }
    ],
    "sg:phone":"+44 1978 661162",
    "sg:postcode":"LL13 9UG",
    "sg:province":"Wrexham",
    "sg:tags":[
        "heating",
        "contractor"
    ],
    "wof:name":"A D Fisher & Co. Ltd.",
    "wof:placetype":"venue"
},
  "geometry": {"coordinates":[-2.971489,53.051975],"type":"Point"}
}