{
  "type": "Feature",
  "properties": {
    "iso:country":"GB",
    "sg:address":"127 Tofts Road",
    "sg:city":"Barton-upon-humber",
    "sg:classifiers":[
        {
            "category":"Freight",
            "type":"Transportation"
        }
    ],
    "sg:phone":"+44 1652 632383",
    "sg:postcode":"DN18 5ND",
    "sg:province":"Lincolnshire",
    "sg:tags":[
        "haulage",
        "transport",
        "road"
    ],
    "wof:name":"J P Borrill Transport",
    "wof:placetype":"venue"
},
  "geometry": {"coordinates":[-0.448753,53.677711],"type":"Point"}
}