{
  "type": "Feature",
  "properties": {
    "addr:full":"Yorkshire House, 9 Stratford Road, Sherley Solihull West Midlands B90 3LU",
    "addr:housenumber":"9",
    "addr:postcode":"b90 3lu",
    "addr:street":"Stratford Road Sherley",
    "iso:country":"GB",
    "sg:address":"Yorkshire House, 9 Stratford Road, Sherley",
    "sg:city":"Solihull",
    "sg:classifiers":[
        {
            "category":"Banks & Credit Unions",
            "subcategory":"Financial Services",
            "type":"Services"
        }
    ],
    "sg:phone":"+44 121 745 3211",
    "sg:postcode":"B90 3LU",
    "sg:province":"West Midlands",
    "sg:tags":[
        "consultant"
    ],
    "wof:name":"J S P Financial Services Ltd.",
    "wof:placetype":"venue"
},
  "geometry": {"coordinates":[-1.8323069811,52.4193077087],"type":"Point"}
}