{
  "type": "Feature",
  "properties": {
    "iso:country":"GB",
    "sg:address":"20-24 High Street",
    "sg:city":"Rayleigh",
    "sg:classifiers":[
        {
            "category":"Professional",
            "subcategory":"Accounting & Tax Preparation",
            "type":"Services"
        }
    ],
    "sg:phone":"+44 1268 747028",
    "sg:postcode":"SS6 7EF",
    "sg:province":"Essex",
    "sg:tags":[
        "accountant"
    ],
    "wof:name":"Masons",
    "wof:placetype":"venue"
},
  "geometry": {"coordinates":[0.6071439981,51.5874023438],"type":"Point"}
}