{
  "type": "Feature",
  "properties": {
    "addr:full":"The Field House, Johns Lane Tipton West Midlands DY4 7PT",
    "addr:postcode":"dy4 7pt",
    "addr:street":"Johns Lane",
    "iso:country":"GB",
    "sg:address":"The Field House, Johns Lane",
    "sg:city":"Tipton",
    "sg:classifiers":[
        {
            "category":"Manufacturing",
            "subcategory":"Building Materials",
            "type":"Manufacturing & Wholesale Goods"
        }
    ],
    "sg:postcode":"DY4 7PT",
    "sg:province":"West Midlands",
    "sg:tags":[
        "concrete",
        "product"
    ],
    "wof:name":"Midland Concrete Products Ltd.",
    "wof:placetype":"venue"
},
  "geometry": {"coordinates":[-2.0456390381,52.5238113403],"type":"Point"}
}