{
  "type": "Feature",
  "properties": {
    "addr:full":"55 George St Oldham Lancashire OL1 1LT",
    "addr:housenumber":"55",
    "addr:postcode":"ol1 1lt",
    "addr:street":"George St",
    "iso:country":"GB",
    "sg:address":"55 George St",
    "sg:city":"Oldham",
    "sg:classifiers":[
        {
            "category":"Shopping",
            "subcategory":"Thrift Store",
            "type":"Retail Goods"
        }
    ],
    "sg:phone":"+44 161 624 9008",
    "sg:postcode":"OL1 1LT",
    "sg:province":"Lancashire",
    "sg:tags":[
        "shop",
        "charity"
    ],
    "wof:name":"Age Concern",
    "wof:placetype":"venue"
},
  "geometry": {"coordinates":[-2.115834,53.540401],"type":"Point"}
}