{
  "type": "Feature",
  "properties": {
    "addr:full":"Charles Clore Macmillan Day Unit, 214 Newtown Road Newbury Berkshire RG14 7ED",
    "addr:housenumber":"unit 214",
    "addr:postcode":"rg14 7ed",
    "addr:street":"Newtown Road",
    "iso:country":"GB",
    "sg:address":"Charles Clore Macmillan Day Unit, 214 Newtown Road",
    "sg:city":"Newbury",
    "sg:classifiers":[
        {
            "category":"Organizations",
            "subcategory":"Non-profit Organization",
            "type":"Services"
        }
    ],
    "sg:phone":"+44 1635 31542",
    "sg:postcode":"RG14 7ED",
    "sg:province":"Berkshire",
    "sg:tags":[
        "organisation",
        "voluntary",
        "charity"
    ],
    "wof:name":"Newbury & District Cancer Care Trust",
    "wof:placetype":"venue"
},
  "geometry": {"coordinates":[-1.3258719444,51.405872345],"type":"Point"}
}