{
  "type": "Feature",
  "properties": {
    "addr:full":"140 Old Oak Road, Acton London Greater London W3 7HS",
    "addr:housenumber":"140",
    "addr:postcode":"w3 7hs",
    "addr:street":"Old Oak Road",
    "iso:country":"GB",
    "sg:address":"140 Old Oak Road, Acton",
    "sg:city":"London",
    "sg:classifiers":[
        {
            "category":"Building & Trades",
            "subcategory":"Plumbing",
            "type":"Services"
        }
    ],
    "sg:postcode":"W3 7HS",
    "sg:province":"Greater London",
    "sg:tags":[
        "central",
        "heating"
    ],
    "wof:name":"Sampsons Electrical Contractors",
    "wof:placetype":"venue"
},
  "geometry": {"coordinates":[-0.2470719963,51.5119819641],"type":"Point"}
}