{
  "type": "Feature",
  "properties": {
    "addr:full":"Allander, Bathley Lane, Little Carlton Newark Lincolnshire NG23 6BY",
    "addr:postcode":"ng23 6by",
    "addr:street":"Bathley Lane",
    "iso:country":"GB",
    "sg:address":"Allander, Bathley Lane, Little Carlton",
    "sg:city":"Newark",
    "sg:classifiers":[
        {
            "category":"Professional",
            "subcategory":"Engineering",
            "type":"Services"
        },
        {
            "category":"Building & Trades",
            "subcategory":"Construction",
            "type":"Services"
        }
    ],
    "sg:phone":"+44 1636 702797",
    "sg:postcode":"NG23 6BY",
    "sg:province":"Lincolnshire",
    "sg:tags":[
        "civil",
        "builder",
        "engineer"
    ],
    "wof:name":"Mykon Construction Co.",
    "wof:placetype":"venue"
},
  "geometry": {"coordinates":[-0.8386639953,53.1228904724],"type":"Point"}
}