{
  "type": "Feature",
  "properties": {
    "addr:full":"11 Forfar Avenue Glasgow Glasgow City G52 3JQ",
    "addr:housenumber":"11",
    "addr:postcode":"g52 3jq",
    "addr:street":"Forfar Avenue",
    "iso:country":"GB",
    "sg:address":"11 Forfar Avenue",
    "sg:city":"Glasgow",
    "sg:classifiers":[
        {
            "category":"Shopping",
            "subcategory":"Jewelry",
            "type":"Retail Goods"
        },
        {
            "category":"Shopping",
            "subcategory":"Comic Books",
            "type":"Retail Goods"
        }
    ],
    "sg:phone":"+44 141 883 8777",
    "sg:postcode":"G52 3JQ",
    "sg:province":"Glasgow City",
    "sg:tags":[
        "jeweller",
        "sale",
        "jewellery"
    ],
    "wof:name":"Craigs Of Cardonald Jewellers",
    "wof:placetype":"venue"
},
  "geometry": {"coordinates":[-4.354452,55.845573],"type":"Point"}
}