{
  "type": "Feature",
  "properties": {
    "iso:country":"GB",
    "sg:address":"Eastern Avenue",
    "sg:city":"Gloucester",
    "sg:classifiers":[
        {
            "category":"Building & Trades",
            "subcategory":"Construction",
            "type":"Services"
        }
    ],
    "sg:phone":"+44 1452 381000",
    "sg:postcode":"GL4 3BY",
    "sg:province":"Gloucestershire",
    "sg:tags":[
        "valve"
    ],
    "wof:name":"Hytork International Ltd.",
    "wof:placetype":"venue"
},
  "geometry": {"coordinates":[-2.213558,51.86356],"type":"Point"}
}