{
  "type": "Feature",
  "properties": {
    "addr:full":"60 Goding Street London Greater London SE11 5AW",
    "addr:housenumber":"60",
    "addr:postcode":"se11 5aw",
    "addr:street":"Goding Street",
    "iso:country":"GB",
    "sg:address":"60 Goding Street",
    "sg:city":"London",
    "sg:classifiers":[
        {
            "category":"Autos & Motor Vehicles",
            "subcategory":"Automobile Sales",
            "type":"Retail Goods"
        }
    ],
    "sg:phone":"+44 20 7582 1233",
    "sg:postcode":"SE11 5AW",
    "sg:province":"Greater London",
    "sg:tags":[
        "car"
    ],
    "wof:name":"Algarve Motors",
    "wof:placetype":"venue"
},
  "geometry": {"coordinates":[-0.1221819967,51.4864425659],"type":"Point"}
}