{
  "type": "Feature",
  "properties": {
    "addr:full":"36 Wheatfield Road, Stanway Colchester Essex CO3 0YJ",
    "addr:housenumber":"36",
    "addr:postcode":"co3 0yj",
    "addr:street":"Wheatfield Road",
    "iso:country":"GB",
    "sg:address":"36 Wheatfield Road, Stanway",
    "sg:city":"Colchester",
    "sg:classifiers":[
        {
            "category":"Building & Trades",
            "subcategory":"Construction",
            "type":"Services"
        }
    ],
    "sg:postcode":"CO3 0YJ",
    "sg:province":"Essex",
    "sg:tags":[
        "joiner",
        "carpenter"
    ],
    "wof:name":"Anthony Ronald Humm",
    "wof:placetype":"venue"
},
  "geometry": {"coordinates":[0.8458619714,51.8822898865],"type":"Point"}
}