{
  "type": "Feature",
  "properties": {
    "addr:full":"Eternite Wharf, Stevenage Rd Fulham Greater London SW6 6PF",
    "addr:postcode":"sw6 6pf",
    "addr:street":"Stevenage Rd",
    "iso:country":"GB",
    "sg:address":"Eternite Wharf, Stevenage Rd",
    "sg:city":"Fulham",
    "sg:classifiers":[
        {
            "category":"Personal",
            "type":"Services"
        }
    ],
    "sg:phone":"+44 20 8395 6498",
    "sg:postcode":"SW6 6PF",
    "sg:province":"Greater London",
    "sg:tags":[
        "slimming",
        "product"
    ],
    "wof:name":"Slimming World",
    "wof:placetype":"venue"
},
  "geometry": {"coordinates":[-0.222401,51.477196],"type":"Point"}
}