{
  "type": "Feature",
  "properties": {
    "iso:country":"GB",
    "sg:address":"Vale Mill Lodge, Huddersfield Road, Mossley",
    "sg:city":"Ashton-under-lyne",
    "sg:classifiers":[
        {
            "category":"Shopping",
            "subcategory":"Gifts & Souvenirs",
            "type":"Retail Goods"
        }
    ],
    "sg:phone":"+44 1457 834782",
    "sg:postcode":"OL5 9LL",
    "sg:province":"Greater Manchester",
    "sg:tags":[
        "giftware"
    ],
    "wof:name":"Morrison Marketing Ltd.",
    "wof:placetype":"venue"
},
  "geometry": {"coordinates":[-2.04125,53.517082],"type":"Point"}
}