{
  "type": "Feature",
  "properties": {
    "addr:full":"80 Islington High St Islington Greater London N1 8EQ",
    "addr:housenumber":"80",
    "addr:postcode":"n1 8eq",
    "addr:street":"Islington High St",
    "iso:country":"GB",
    "sg:address":"80 Islington High St",
    "sg:city":"Islington",
    "sg:classifiers":[
        {
            "category":"Professional",
            "subcategory":"Lawyer & Legal Services",
            "type":"Services"
        }
    ],
    "sg:phone":"+44 20 7833 1066",
    "sg:postcode":"N1 8EQ",
    "sg:province":"Greater London",
    "wof:name":"Search Matters",
    "wof:placetype":"venue"
},
  "geometry": {"coordinates":[-0.1050290018,51.5339012146],"type":"Point"}
}