{
  "type": "Feature",
  "properties": {
    "addr:full":"Unit 3 Exeter Devon EX2 8LN",
    "addr:housenumber":"unit 3",
    "addr:postcode":"ex2 8ln",
    "iso:country":"GB",
    "sg:address":"Unit 3",
    "sg:city":"Exeter",
    "sg:classifiers":[
        {
            "category":"Shopping",
            "subcategory":"Beauty & Cosmetics",
            "type":"Retail Goods"
        }
    ],
    "sg:phone":"+44 1392 250470",
    "sg:postcode":"EX2 8LN",
    "sg:province":"Devon",
    "sg:tags":[
        "equipment",
        "supply",
        "hairdressing"
    ],
    "wof:name":"K B Salon Supplies Ltd.",
    "wof:placetype":"venue"
},
  "geometry": {"coordinates":[-3.5328390598,50.7024803162],"type":"Point"}
}