{
  "type": "Feature",
  "properties": {
    "addr:full":"Witherston Way London Greater London SE9 3JN",
    "addr:postcode":"se9 3jn",
    "addr:street":"Witherston Way",
    "iso:country":"GB",
    "sg:address":"Witherston Way",
    "sg:city":"London",
    "sg:classifiers":[
        {
            "category":"Education",
            "subcategory":"School",
            "type":"Public Place"
        },
        {
            "category":"Government",
            "subcategory":"Office",
            "type":"Public Place"
        }
    ],
    "sg:phone":"+44 20 8857 4965",
    "sg:postcode":"SE9 3JN",
    "sg:province":"Greater London",
    "sg:tags":[
        "local",
        "authority"
    ],
    "wof:name":"Greenacres Primary School",
    "wof:placetype":"venue"
},
  "geometry": {"coordinates":[0.0580880009,51.433719635],"type":"Point"}
}