{
  "type": "Feature",
  "properties": {
    "iso:country":"GB",
    "sg:address":"20 Upper Kirkgate",
    "sg:city":"Wakefield",
    "sg:classifiers":[
        {
            "category":"Communications",
            "subcategory":"Film & Video Production",
            "type":"Services"
        }
    ],
    "sg:phone":"+44 1924 377951",
    "sg:postcode":"WF1 1SP",
    "sg:province":"West Yorkshire",
    "sg:tags":[
        "tv"
    ],
    "wof:name":"Granada Home Technology",
    "wof:placetype":"venue"
},
  "geometry": {"coordinates":[-1.4943939447,53.6824455261],"type":"Point"}
}