{
  "type": "Feature",
  "properties": {
    "iso:country":"GB",
    "sg:address":"14 Maple Close, Oldland Common",
    "sg:city":"Bristol",
    "sg:classifiers":[
        {
            "category":"Manufacturing",
            "subcategory":"Lumber",
            "type":"Manufacturing & Wholesale Goods"
        }
    ],
    "sg:phone":"+44 117 956 2266",
    "sg:postcode":"BS30 9PX",
    "sg:province":"Gloucestershire",
    "sg:tags":[
        "importer",
        "merchants",
        "agent",
        "timber"
    ],
    "wof:name":"Woodstock Timber Co. (U K) Ltd.",
    "wof:placetype":"venue"
},
  "geometry": {"coordinates":[-2.481347084,51.4432067871],"type":"Point"}
}