{
  "type": "Feature",
  "properties": {
    "iso:country":"GB",
    "sg:address":"852 Melton Road, Thurmaston",
    "sg:city":"Leicester",
    "sg:classifiers":[
        {
            "category":"Retail",
            "subcategory":"Auto Repair",
            "type":"Services"
        }
    ],
    "sg:phone":"+44 116 269 6111",
    "sg:postcode":"LE4 8BT",
    "sg:province":"Leicestershire",
    "sg:tags":[
        "bodybuilder",
        "repairer"
    ],
    "wof:name":"Pickerings Transport Services Ltd.",
    "wof:placetype":"venue"
},
  "geometry": {"coordinates":[-1.098999,52.679089],"type":"Point"}
}