{
  "type": "Feature",
  "properties": {
    "addr:full":"101 Lancaster Rd Enfield Greater London EN2 0JN",
    "addr:housenumber":"101",
    "addr:postcode":"en2 0jn",
    "addr:street":"Lancaster Rd",
    "iso:country":"GB",
    "sg:address":"101 Lancaster Rd",
    "sg:city":"Enfield",
    "sg:classifiers":[
        {
            "category":"Shopping",
            "subcategory":"Florist",
            "type":"Retail Goods"
        }
    ],
    "sg:phone":"+44 20 8363 5702",
    "sg:postcode":"EN2 0JN",
    "sg:province":"Greater London",
    "wof:name":"Lancaster Florist",
    "wof:placetype":"venue"
},
  "geometry": {"coordinates":[-0.0825759992,51.6640815735],"type":"Point"}
}