{
  "type": "Feature",
  "properties": {
    "addr:full":"17 Newtimber Gdns Shoreham-by-sea West Sussex BN43 5GQ",
    "addr:housenumber":"17",
    "addr:postcode":"bn43 5gq",
    "addr:street":"Newtimber Gdns Shoreham-By-Sea",
    "iso:country":"GB",
    "sg:address":"17 Newtimber Gdns",
    "sg:city":"Shoreham-by-sea",
    "sg:classifiers":[
        {
            "category":"Home & Garden",
            "subcategory":"Household Appliances",
            "type":"Retail Goods"
        },
        {
            "category":"Wholesale",
            "subcategory":"Vending Machines",
            "type":"Manufacturing & Wholesale Goods"
        }
    ],
    "sg:phone":"+44 1273 701618",
    "sg:postcode":"BN43 5GQ",
    "sg:province":"West Sussex",
    "sg:tags":[
        "electrical",
        "domestic",
        "sale"
    ],
    "wof:name":"Edgar's Vending Ltd",
    "wof:placetype":"venue"
},
  "geometry": {"coordinates":[-0.2719439864,50.8418693542],"type":"Point"}
}