{
  "type": "Feature",
  "properties": {
    "addr:full":"58 New Street Dalry North Ayrshire KA24 5AF",
    "addr:housenumber":"58",
    "addr:postcode":"ka24 5af",
    "addr:street":"New Street",
    "iso:country":"GB",
    "sg:address":"58 New Street",
    "sg:city":"Dalry",
    "sg:classifiers":[
        {
            "category":"Banks & Credit Unions",
            "subcategory":"Bank",
            "type":"Services"
        }
    ],
    "sg:phone":"+44 1294 832270",
    "sg:postcode":"KA24 5AF",
    "sg:province":"North Ayrshire",
    "sg:tags":[
        "financial",
        "institution"
    ],
    "sg:website":"http://www.lloydstsb.com",
    "wof:name":"Lloyds T S B Bank Plc",
    "wof:placetype":"venue"
},
  "geometry": {"coordinates":[-4.7180271149,55.7076263428],"type":"Point"}
}