{
  "type": "Feature",
  "properties": {
    "addr:full":"Barn Park Road Plymouth Devon PL3 4LP",
    "addr:postcode":"pl3 4lp",
    "addr:street":"Park Road",
    "iso:country":"GB",
    "sg:address":"Barn Park Road",
    "sg:city":"Plymouth",
    "sg:classifiers":[
        {
            "category":"Personal",
            "subcategory":"Beauty Salon",
            "type":"Services"
        },
        {
            "category":"Personal",
            "subcategory":"Barber",
            "type":"Services"
        }
    ],
    "sg:phone":"+44 1752 667684",
    "sg:postcode":"PL3 4LP",
    "sg:province":"Devon",
    "sg:tags":[
        "unisex",
        "hairdresser"
    ],
    "wof:name":"CLIVE H LITTLEJOHNS & P F BUCKLEY",
    "wof:placetype":"venue"
},
  "geometry": {"coordinates":[-4.142599,50.388775],"type":"Point"}
}