{
  "type": "Feature",
  "properties": {
    "addr:full":"27 North Rd, Ravensthorpe Dewsbury West Yorkshire WF13 3AA",
    "addr:housenumber":"27",
    "addr:postcode":"wf13 3aa",
    "addr:street":"North Rd",
    "iso:country":"GB",
    "sg:address":"27 North Rd, Ravensthorpe",
    "sg:city":"Dewsbury",
    "sg:classifiers":[
        {
            "category":"Health Services",
            "subcategory":"Podiatrist",
            "type":"Services"
        }
    ],
    "sg:phone":"+44 1924 464492",
    "sg:postcode":"WF13 3AA",
    "sg:province":"West Yorkshire",
    "sg:tags":[
        "podiatrists",
        "chiropodist"
    ],
    "wof:name":"Drs MacKay Balasunderam & Chandra",
    "wof:placetype":"venue"
},
  "geometry": {"coordinates":[-1.664517045,53.6795158386],"type":"Point"}
}