{
  "type": "Feature",
  "properties": {
    "iso:country":"GB",
    "sg:address":"17 Ash Street",
    "sg:city":"Dundee",
    "sg:classifiers":[
        {
            "category":"Manufacturing",
            "subcategory":"Furniture",
            "type":"Manufacturing & Wholesale Goods"
        }
    ],
    "sg:phone":"+44 1382 223797",
    "sg:postcode":"DD1 5AR",
    "sg:province":"Dundee City",
    "sg:tags":[
        "polishing",
        "french"
    ],
    "wof:name":"John Stewart & Son",
    "wof:placetype":"venue"
},
  "geometry": {"coordinates":[-2.985658884,56.4633483887],"type":"Point"}
}