{
  "type": "Feature",
  "properties": {
    "addr:full":"8 Ashmount Road London Greater London N19 3BH",
    "addr:housenumber":"8",
    "addr:postcode":"n19 3bh",
    "addr:street":"Ashmount Road",
    "iso:country":"GB",
    "sg:address":"8 Ashmount Road",
    "sg:city":"London",
    "sg:classifiers":[
        {
            "category":"Professional",
            "subcategory":"Management & Consulting",
            "type":"Services"
        }
    ],
    "sg:phone":"+44 20 7561 9876",
    "sg:postcode":"N19 3BH",
    "sg:province":"Greater London",
    "sg:tags":[
        "marketing",
        "consultant"
    ],
    "wof:name":"Yellow Hat Consulting Ltd",
    "wof:placetype":"venue"
},
  "geometry": {"coordinates":[-0.1322190017,51.5716819763],"type":"Point"}
}