{
  "type": "Feature",
  "properties": {
    "addr:full":"1st Floor, St James House, St James Row Burnley Lancashire BB11 1DR",
    "addr:postcode":"bb11 1dr",
    "addr:street":"Floor St;St James Row",
    "iso:country":"GB",
    "sg:address":"1st Floor, St James House, St James Row",
    "sg:city":"Burnley",
    "sg:classifiers":[
        {
            "category":"Organizations",
            "subcategory":"Community Association",
            "type":"Services"
        }
    ],
    "sg:phone":"+44 1282 455990",
    "sg:postcode":"BB11 1DR",
    "sg:province":"Lancashire",
    "sg:tags":[
        "society",
        "housing"
    ],
    "wof:name":"Stonham Housing Association Ltd.",
    "wof:placetype":"venue"
},
  "geometry": {"coordinates":[-2.244164,53.78904],"type":"Point"}
}