{
  "type": "Feature",
  "properties": {
    "iso:country":"GB",
    "sg:address":"Corskellie, Rothiemay",
    "sg:city":"Huntly",
    "sg:classifiers":[
        {
            "category":"Home & Garden",
            "subcategory":"Garden Supply",
            "type":"Retail Goods"
        }
    ],
    "sg:postcode":"AB54 5NA",
    "sg:province":"Aberdeenshire",
    "sg:tags":[
        "bulb",
        "grower"
    ],
    "wof:name":"Robertson,R,& Sons",
    "wof:placetype":"venue"
},
  "geometry": {"coordinates":[-2.793409,57.442581],"type":"Point"}
}