{
  "type": "Feature",
  "properties": {
    "addr:full":"74 Broad Street Chesham Buckinghamshire HP5 3DX",
    "addr:housenumber":"74",
    "addr:postcode":"hp5 3dx",
    "addr:street":"Broad Street",
    "iso:country":"GB",
    "sg:address":"74 Broad Street",
    "sg:city":"Chesham",
    "sg:classifiers":[
        {
            "category":"Shopping",
            "subcategory":"News",
            "type":"Retail Goods"
        }
    ],
    "sg:phone":"+44 1494 783268",
    "sg:postcode":"HP5 3DX",
    "sg:province":"Buckinghamshire",
    "sg:tags":[
        "newsagent"
    ],
    "wof:name":"E Brackley & Son Ltd.",
    "wof:placetype":"venue"
},
  "geometry": {"coordinates":[-0.610089,51.709553],"type":"Point"}
}