{
  "type": "Feature",
  "properties": {
    "iso:country":"GB",
    "sg:address":"Greyfriars Chambers",
    "sg:city":"Bedford",
    "sg:classifiers":[
        {
            "category":"Professional",
            "subcategory":"Employment Agencies",
            "type":"Services"
        }
    ],
    "sg:phone":"+44 1234 214614",
    "sg:postcode":"MK40 1HJ",
    "sg:province":"Bedfordshire",
    "sg:tags":[
        "consultant"
    ],
    "wof:name":"Hays Specialist Recruitment Ltd.",
    "wof:placetype":"venue"
},
  "geometry": {"coordinates":[-0.471824,52.136463],"type":"Point"}
}