{
  "type": "Feature",
  "properties": {
    "addr:full":"138 Elm Tree Avenue Frinton-on-sea Essex CO14 8TF",
    "addr:housenumber":"138",
    "addr:postcode":"co14 8tf",
    "addr:street":"Elm Tree Avenue",
    "iso:country":"GB",
    "sg:address":"138 Elm Tree Avenue",
    "sg:city":"Frinton-on-sea",
    "sg:classifiers":[
        {
            "category":"Retail",
            "subcategory":"Veterinary Services",
            "type":"Services"
        }
    ],
    "sg:phone":"+44 1255 850456",
    "sg:postcode":"CO14 8TF",
    "sg:province":"Essex",
    "sg:tags":[
        "surgeon",
        "activity"
    ],
    "wof:name":"Haven Veterinary Practice",
    "wof:placetype":"venue"
},
  "geometry": {"coordinates":[1.2478400469,51.8437690735],"type":"Point"}
}