{
  "type": "Feature",
  "properties": {
    "iso:country":"GB",
    "sg:address":"15, High St",
    "sg:city":"Swindon",
    "sg:classifiers":[
        {
            "category":"Recreation",
            "subcategory":"Dog Park",
            "type":"Entertainment"
        }
    ],
    "sg:phone":"+44 1793 727529",
    "sg:postcode":"SN4 0NG",
    "sg:province":"Wiltshire",
    "wof:name":"Spear Lesley",
    "wof:placetype":"venue"
},
  "geometry": {"coordinates":[-1.73077,51.516441],"type":"Point"}
}