{
  "type": "Feature",
  "properties": {
    "addr:full":"25-26 Market Place Loughborough Leicestershire LE11 3EB",
    "addr:housenumber":"25-26",
    "addr:postcode":"le11 3eb",
    "addr:street":"Market Place",
    "iso:country":"GB",
    "sg:address":"25-26 Market Place",
    "sg:city":"Loughborough",
    "sg:classifiers":[
        {
            "category":"Sports & Exercise",
            "subcategory":"Sports Center",
            "type":"Entertainment"
        }
    ],
    "sg:phone":"+44 1509 261911",
    "sg:postcode":"LE11 3EB",
    "sg:province":"Leicestershire",
    "sg:tags":[
        "shop",
        "good"
    ],
    "wof:name":"Fox Leisure",
    "wof:placetype":"venue"
},
  "geometry": {"coordinates":[-1.206087,52.77174],"type":"Point"}
}