{
  "type": "Feature",
  "properties": {
    "iso:country":"GB",
    "sg:address":"15 Stoneleigh Road",
    "sg:city":"Kenilworth",
    "sg:classifiers":[
        {
            "category":"Building & Trades",
            "subcategory":"Construction",
            "type":"Services"
        }
    ],
    "sg:phone":"+44 1926 856287",
    "sg:postcode":"CV8 2GB",
    "sg:province":"Warwickshire",
    "sg:tags":[
        "builder"
    ],
    "wof:name":"Woodcote Builders",
    "wof:placetype":"venue"
},
  "geometry": {"coordinates":[-1.5714230537,52.3506698608],"type":"Point"}
}