{
  "type": "Feature",
  "properties": {
    "addr:full":"264 Tottenham Court Road London Greater London W1T 7RJ",
    "addr:housenumber":"264",
    "addr:postcode":"w1t 7rj",
    "addr:street":"Tottenham Court Road",
    "iso:country":"GB",
    "sg:address":"264 Tottenham Court Road",
    "sg:city":"London",
    "sg:classifiers":[
        {
            "category":"Fast Food",
            "type":"Food & Drink"
        }
    ],
    "sg:phone":"+44 20 7436 4416",
    "sg:postcode":"W1T 7RJ",
    "sg:province":"Greater London",
    "sg:tags":[
        "away",
        "take"
    ],
    "wof:name":"Burger King",
    "wof:placetype":"venue"
},
  "geometry": {"coordinates":[-0.130516,51.517044],"type":"Point"}
}