{
  "type": "Feature",
  "properties": {
    "iso:country":"GB",
    "sg:address":"7 Mornington Terr",
    "sg:city":"London",
    "sg:classifiers":[
        {
            "category":"Professional",
            "subcategory":"Art Services",
            "type":"Services"
        }
    ],
    "sg:postcode":"NW1 7RR",
    "sg:province":"Greater London",
    "sg:tags":[
        "photographer"
    ],
    "wof:name":"Damn Fine Design",
    "wof:placetype":"venue"
},
  "geometry": {"coordinates":[-0.142229,51.534119],"type":"Point"}
}