{
  "type": "Feature",
  "properties": {
    "addr:full":"24-28 High Street New Malden Surrey KT3 4HE",
    "addr:housenumber":"24-28",
    "addr:postcode":"kt3 4he",
    "addr:street":"High Street",
    "iso:country":"GB",
    "sg:address":"24-28 High Street",
    "sg:city":"New Malden",
    "sg:classifiers":[
        {
            "category":"Food & Beverages",
            "subcategory":"Supermarket",
            "type":"Retail Goods"
        }
    ],
    "sg:phone":"+44 20 8942 8988",
    "sg:postcode":"KT3 4HE",
    "sg:province":"Surrey",
    "wof:name":"Waitrose Supermarkets",
    "wof:placetype":"venue"
},
  "geometry": {"coordinates":[-0.256233,51.402515],"type":"Point"}
}