{
  "type": "Feature",
  "properties": {
    "addr:full":"219-221 Salisbury Road Southampton Hampshire SO40 3LL",
    "addr:housenumber":"219-221",
    "addr:postcode":"so40 3ll",
    "addr:street":"Salisbury Road",
    "iso:country":"GB",
    "sg:address":"219-221 Salisbury Road",
    "sg:city":"Southampton",
    "sg:classifiers":[
        {
            "category":"Food & Beverages",
            "subcategory":"Groceries & Convenience Stores",
            "type":"Retail Goods"
        }
    ],
    "sg:phone":"+44 23 8086 5965",
    "sg:postcode":"SO40 3LL",
    "sg:province":"Hampshire",
    "wof:name":"Alldays",
    "wof:placetype":"venue"
},
  "geometry": {"coordinates":[-1.500428,50.926865],"type":"Point"}
}