{
  "type": "Feature",
  "properties": {
    "addr:full":"Savoy Hill, Welbeck College Welbeck Worksop Nottinghamshire S80 3LN",
    "addr:postcode":"s80 3ln",
    "addr:street":"Savoy Hill",
    "iso:country":"GB",
    "sg:address":"Savoy Hill, Welbeck College Welbeck",
    "sg:city":"Worksop",
    "sg:classifiers":[
        {
            "category":"Building & Trades",
            "subcategory":"Construction",
            "type":"Services"
        }
    ],
    "sg:phone":"+44 1909 483330",
    "sg:postcode":"S80 3LN",
    "sg:province":"Nottinghamshire",
    "sg:tags":[
        "builder"
    ],
    "wof:name":"Willows Building & Maintenance",
    "wof:placetype":"venue"
},
  "geometry": {"coordinates":[-1.1704349518,53.2624931335],"type":"Point"}
}