{
  "type": "Feature",
  "properties": {
    "addr:full":"24 Strathmore Avenue, Alvaston Derby Derbyshire DE24 0FX",
    "addr:housenumber":"24",
    "addr:postcode":"de24 0fx",
    "addr:street":"Strathmore Avenue",
    "iso:country":"GB",
    "sg:address":"24 Strathmore Avenue, Alvaston",
    "sg:city":"Derby",
    "sg:classifiers":[
        {
            "category":"Bus Charters",
            "type":"Transportation"
        }
    ],
    "sg:phone":"+44 1332 755803",
    "sg:postcode":"DE24 0FX",
    "sg:province":"Derbyshire",
    "sg:tags":[
        "mini",
        "hire",
        "coach",
        "leasing"
    ],
    "wof:name":"Round Robin Coaches",
    "wof:placetype":"venue"
},
  "geometry": {"coordinates":[-1.4363390207,52.8901443481],"type":"Point"}
}