{
  "type": "Feature",
  "properties": {
    "addr:full":"Bank House, 8 Cherry Street Birmingham West Midlands B2 5AL",
    "addr:housenumber":"8",
    "addr:postcode":"b2 5al",
    "addr:street":"Cherry Street",
    "iso:country":"GB",
    "sg:address":"Bank House, 8 Cherry Street",
    "sg:city":"Birmingham",
    "sg:classifiers":[
        {
            "category":"Travel",
            "subcategory":"Travel Agent",
            "type":"Entertainment"
        }
    ],
    "sg:phone":"+44 121 644 5544",
    "sg:postcode":"B2 5AL",
    "sg:province":"West Midlands",
    "wof:name":"American Express Travel Service",
    "wof:placetype":"venue"
},
  "geometry": {"coordinates":[-1.89778,52.480701],"type":"Point"}
}