{
  "type": "Feature",
  "properties": {
    "addr:full":"442 Marton Road Middlesbrough North Yorkshire TS4 3AA",
    "addr:housenumber":"442",
    "addr:postcode":"ts4 3aa",
    "addr:street":"Marton Road",
    "iso:country":"GB",
    "sg:address":"442 Marton Road",
    "sg:city":"Middlesbrough",
    "sg:classifiers":[
        {
            "category":"Food & Beverages",
            "subcategory":"Meat & Fish",
            "type":"Retail Goods"
        },
        {
            "category":"Food & Beverages",
            "subcategory":"Groceries & Convenience Stores",
            "type":"Retail Goods"
        }
    ],
    "sg:phone":"+44 1642 816815",
    "sg:postcode":"TS4 3AA",
    "sg:province":"North Yorkshire",
    "sg:tags":[
        "shop",
        "chip"
    ],
    "wof:name":"Belle Vue Fisheries",
    "wof:placetype":"venue"
},
  "geometry": {"coordinates":[-1.2220020294,54.5565643311],"type":"Point"}
}