{
  "type": "Feature",
  "properties": {
    "addr:full":"Woodbury Lane, Norton Evesham Worcestershire WR5 2PT",
    "addr:postcode":"wr5 2pt",
    "addr:street":"Woodbury Lane",
    "iso:country":"GB",
    "sg:address":"Woodbury Lane, Norton",
    "sg:city":"Evesham",
    "sg:classifiers":[
        {
            "category":"Professional",
            "subcategory":"Printing & Photocopies",
            "type":"Services"
        }
    ],
    "sg:phone":"+44 1905 358823",
    "sg:postcode":"WR5 2PT",
    "sg:province":"Worcestershire",
    "sg:tags":[
        "printer"
    ],
    "wof:name":"Sandwell Printing Co",
    "wof:placetype":"venue"
},
  "geometry": {"coordinates":[-2.179164,52.158844],"type":"Point"}
}