{
  "type": "Feature",
  "properties": {
    "addr:full":"13 The Avenue London Greater London W13 8JR",
    "addr:housenumber":"13",
    "addr:postcode":"w13 8jr",
    "addr:street":"The Avenue",
    "iso:country":"GB",
    "sg:address":"13 The Avenue",
    "sg:city":"London",
    "sg:classifiers":[
        {
            "category":"Food & Beverages",
            "subcategory":"Supermarket",
            "type":"Retail Goods"
        }
    ],
    "sg:postcode":"W13 8JR",
    "sg:province":"Greater London",
    "wof:name":"Alliance Food Store",
    "wof:placetype":"venue"
},
  "geometry": {"coordinates":[-0.3193730116,51.5143432617],"type":"Point"}
}