{
  "type": "Feature",
  "properties": {
    "addr:full":"217 Broadway Lane Bournemouth Dorset BH8 0AE",
    "addr:housenumber":"217",
    "addr:postcode":"bh8 0ae",
    "addr:street":"Broadway Lane",
    "iso:country":"GB",
    "sg:address":"217 Broadway Lane",
    "sg:city":"Bournemouth",
    "sg:classifiers":[
        {
            "category":"Real Estate",
            "subcategory":"Surveying",
            "type":"Services"
        }
    ],
    "sg:postcode":"BH8 0AE",
    "sg:province":"Dorset",
    "sg:tags":[
        "surveyor",
        "land"
    ],
    "wof:name":"Fox Surveys",
    "wof:placetype":"venue"
},
  "geometry": {"coordinates":[-1.848521,50.763481],"type":"Point"}
}