{
  "type": "Feature",
  "properties": {
    "iso:country":"GB",
    "sg:address":"Chaseley Care Home, 404 Promenade",
    "sg:city":"Blackpool",
    "sg:classifiers":[
        {
            "category":"Social Services",
            "subcategory":"Retirement Home",
            "type":"Services"
        }
    ],
    "sg:phone":"+44 1253 352622",
    "sg:postcode":"FY1 2LB",
    "sg:province":"Lancashire",
    "sg:tags":[
        "rest"
    ],
    "wof:name":"Chaseley Rest Home",
    "wof:placetype":"venue"
},
  "geometry": {"coordinates":[-3.0555200577,53.8320617676],"type":"Point"}
}