{
  "type": "Feature",
  "properties": {
    "iso:country":"GB",
    "sg:address":"12 Ripon Rd",
    "sg:city":"Harrogate",
    "sg:classifiers":[
        {
            "category":"Health Services",
            "subcategory":"Dentist",
            "type":"Services"
        }
    ],
    "sg:phone":"+44 1423 566481",
    "sg:postcode":"HG1 2JB",
    "sg:province":"North Yorkshire",
    "wof:name":"B S Palmer",
    "wof:placetype":"venue"
},
  "geometry": {"coordinates":[-1.546377,53.998173],"type":"Point"}
}