{
  "type": "Feature",
  "properties": {
    "addr:full":"Hawthorn Farm, Coskills Barnetby Lincolnshire DN38 6DL",
    "addr:postcode":"dn38 6dl",
    "iso:country":"GB",
    "sg:address":"Hawthorn Farm, Coskills",
    "sg:city":"Barnetby",
    "sg:classifiers":[
        {
            "category":"Farming",
            "subcategory":"Livestock Farm",
            "type":"Manufacturing & Wholesale Goods"
        }
    ],
    "sg:phone":"+44 1652 688272",
    "sg:postcode":"DN38 6DL",
    "sg:province":"Lincolnshire",
    "sg:tags":[
        "others"
    ],
    "wof:name":"C F Neave",
    "wof:placetype":"venue"
},
  "geometry": {"coordinates":[-0.404298991,53.5746192932],"type":"Point"}
}