{
  "type": "Feature",
  "properties": {
    "iso:country":"GB",
    "sg:address":"83 Old Milton Rd",
    "sg:city":"New Milton",
    "sg:classifiers":[
        {
            "category":"Food & Beverages",
            "subcategory":"Candy",
            "type":"Retail Goods"
        }
    ],
    "sg:phone":"+44 1425 611508",
    "sg:postcode":"BH25 6DN",
    "sg:province":"Hampshire",
    "sg:tags":[
        "confectionery"
    ],
    "wof:name":"Speciality Cakes & Supplies",
    "wof:placetype":"venue"
},
  "geometry": {"coordinates":[-1.658831,50.751427],"type":"Point"}
}