{
  "type": "Feature",
  "properties": {
    "iso:country":"GB",
    "sg:address":"27 Churchill Parade",
    "sg:city":"Sutton Coldfield",
    "sg:classifiers":[
        {
            "category":"Home & Garden",
            "subcategory":"Household Appliances",
            "type":"Retail Goods"
        }
    ],
    "sg:phone":"+44 121 378 0900",
    "sg:postcode":"B75 7LD",
    "sg:province":"Staffordshire",
    "sg:tags":[
        "domestic",
        "electrical",
        "sales"
    ],
    "wof:name":"Gardner Services Centre",
    "wof:placetype":"venue"
},
  "geometry": {"coordinates":[-1.785716,52.563164],"type":"Point"}
}