{
  "type": "Feature",
  "properties": {
    "addr:full":"Mere Lane, Armthorpe Doncaster South Yorkshire DN3 2DB",
    "addr:postcode":"dn3 2db",
    "addr:street":"Mere Lane",
    "iso:country":"GB",
    "sg:address":"Mere Lane, Armthorpe",
    "sg:city":"Doncaster",
    "sg:classifiers":[
        {
            "category":"Health Services",
            "subcategory":"Doctor",
            "type":"Services"
        },
        {
            "category":"Health Services",
            "subcategory":"Clinic",
            "type":"Services"
        }
    ],
    "sg:phone":"+44 1302 300322",
    "sg:postcode":"DN3 2DB",
    "sg:province":"South Yorkshire",
    "sg:tags":[
        "nh",
        "practitioners"
    ],
    "wof:name":"The Village Practice",
    "wof:placetype":"venue"
},
  "geometry": {"coordinates":[-1.0607249737,53.5437583923],"type":"Point"}
}