{
  "type": "Feature",
  "properties": {
    "iso:country":"GB",
    "sg:address":"59 Green La",
    "sg:city":"Ilford",
    "sg:classifiers":[
        {
            "category":"Shopping",
            "subcategory":"Clothing, Apparel, & Fashions",
            "type":"Retail Goods"
        }
    ],
    "sg:phone":"+44 20 8514 8175",
    "sg:postcode":"IG1 1XG",
    "sg:province":"Essex",
    "sg:tags":[
        "clothing"
    ],
    "wof:name":"Dressco Act",
    "wof:placetype":"venue"
},
  "geometry": {"coordinates":[0.084438,51.558929],"type":"Point"}
}