{
  "type": "Feature",
  "properties": {
    "addr:full":"46 Second Avenue Stafford Staffordshire ST16 1PR",
    "addr:housenumber":"46",
    "addr:postcode":"st16 1pr",
    "addr:street":"Second Avenue",
    "iso:country":"GB",
    "sg:address":"46 Second Avenue",
    "sg:city":"Stafford",
    "sg:classifiers":[
        {
            "category":"Building & Trades",
            "subcategory":"Plumbing",
            "type":"Services"
        }
    ],
    "sg:phone":"+44 1785 212106",
    "sg:postcode":"ST16 1PR",
    "sg:province":"Staffordshire",
    "sg:tags":[
        "central",
        "heating"
    ],
    "wof:name":"J K Murray Plumbing & Heating",
    "wof:placetype":"venue"
},
  "geometry": {"coordinates":[-2.133532,52.824215],"type":"Point"}
}