{
  "type": "Feature",
  "properties": {
    "iso:country":"GB",
    "sg:address":"Unit 3",
    "sg:city":"Corby",
    "sg:classifiers":[
        {
            "category":"Autos & Motor Vehicles",
            "subcategory":"Auto Supplies",
            "type":"Retail Goods"
        }
    ],
    "sg:postcode":"NN18 8EW",
    "sg:province":"Northamptonshire",
    "sg:tags":[
        "component"
    ],
    "wof:name":"Premier Mota Parts",
    "wof:placetype":"venue"
},
  "geometry": {"coordinates":[-0.706299,52.474468],"type":"Point"}
}