{
  "type": "Feature",
  "properties": {
    "addr:full":"46 Newbrook Road, Over Hulton Bolton Lancashire BL5 1ER",
    "addr:housenumber":"46",
    "addr:postcode":"bl5 1er",
    "addr:street":"Newbrook Road",
    "iso:country":"GB",
    "sg:address":"46 Newbrook Road, Over Hulton",
    "sg:city":"Bolton",
    "sg:classifiers":[
        {
            "category":"Fast Food",
            "type":"Food & Drink"
        }
    ],
    "sg:phone":"+44 1204 63091",
    "sg:postcode":"BL5 1ER",
    "sg:province":"Lancashire",
    "sg:tags":[
        "away",
        "meal",
        "outlet",
        "take"
    ],
    "wof:name":"Pit Stop",
    "wof:placetype":"venue"
},
  "geometry": {"coordinates":[-2.4704511166,53.5454826355],"type":"Point"}
}