{
  "type": "Feature",
  "properties": {
    "iso:country":"GB",
    "sg:address":"45 Castle Arcade",
    "sg:city":"Cardiff",
    "sg:classifiers":[
        {
            "category":"Transit Center",
            "subcategory":"Freight",
            "type":"Transportation"
        }
    ],
    "sg:postcode":"CF10 1BW",
    "sg:province":"Cardiff",
    "sg:tags":[
        "shop",
        "craft",
        "centre"
    ],
    "wof:name":"Claire Grove Buttons",
    "wof:placetype":"venue"
},
  "geometry": {"coordinates":[-3.180717,51.481022],"type":"Point"}
}