{
  "type": "Feature",
  "properties": {
    "iso:country":"GB",
    "sg:address":"23 Dunkeld Road",
    "sg:city":"Sheffield",
    "sg:classifiers":[
        {
            "category":"Health Services",
            "subcategory":"Health Practitioner",
            "type":"Services"
        }
    ],
    "sg:postcode":"S11 9HN",
    "sg:province":"Derbyshire",
    "sg:tags":[
        "psychologist"
    ],
    "wof:name":"C I M Test Publishers",
    "wof:placetype":"venue"
},
  "geometry": {"coordinates":[-1.508943,53.354591],"type":"Point"}
}