{
  "type": "Feature",
  "properties": {
    "addr:full":"High Street, Seend Melksham Wiltshire SN12 6NR",
    "addr:postcode":"sn12 6nr",
    "addr:street":"High Street",
    "iso:country":"GB",
    "sg:address":"High Street, Seend",
    "sg:city":"Melksham",
    "sg:classifiers":[
        {
            "category":"Government",
            "subcategory":"Post Office",
            "type":"Public Place"
        }
    ],
    "sg:phone":"+44 1380 828250",
    "sg:postcode":"SN12 6NR",
    "sg:province":"Wiltshire",
    "wof:name":"Seend Post Office Stores",
    "wof:placetype":"venue"
},
  "geometry": {"coordinates":[-2.1381690502,51.3728065491],"type":"Point"}
}