{
  "type": "Feature",
  "properties": {
    "iso:country":"GB",
    "sg:address":"59 Forrester Street",
    "sg:city":"Walsall",
    "sg:classifiers":[
        {
            "category":"Cinema",
            "subcategory":"Movie Rental",
            "type":"Entertainment"
        }
    ],
    "sg:phone":"+44 1922 646283",
    "sg:postcode":"WS2 9PL",
    "sg:province":"West Midlands",
    "sg:tags":[
        "video",
        "library"
    ],
    "wof:name":"Takhar Video",
    "wof:placetype":"venue"
},
  "geometry": {"coordinates":[-1.995387,52.584827],"type":"Point"}
}