{
  "type": "Feature",
  "properties": {
    "addr:full":"Grove Rd Hitchin Bedfordshire SG5 1JX",
    "addr:postcode":"sg5 1jx",
    "addr:street":"Grove Rd",
    "iso:country":"GB",
    "sg:address":"Grove Rd",
    "sg:city":"Hitchin",
    "sg:classifiers":[
        {
            "category":"Government",
            "subcategory":"Police Station",
            "type":"Public Place"
        }
    ],
    "sg:phone":"+44 1462 425000",
    "sg:postcode":"SG5 1JX",
    "sg:province":"Bedfordshire",
    "sg:tags":[
        "support"
    ],
    "wof:name":"Hitchin Police Station",
    "wof:placetype":"venue"
},
  "geometry": {"coordinates":[-0.2697890103,51.9580116272],"type":"Point"}
}