{
  "type": "Feature",
  "properties": {
    "iso:country":"GB",
    "sg:address":"6 South Wolfe Street",
    "sg:city":"Stoke-on-trent",
    "sg:classifiers":[
        {
            "category":"Health Services",
            "subcategory":"Optometrist",
            "type":"Services"
        }
    ],
    "sg:phone":"+44 1782 848070",
    "sg:postcode":"ST4 4AA",
    "sg:province":"Staffordshire",
    "sg:tags":[
        "optician"
    ],
    "wof:name":"Edwards Opticians",
    "wof:placetype":"venue"
},
  "geometry": {"coordinates":[-2.185228,53.003273],"type":"Point"}
}