{
  "type": "Feature",
  "properties": {
    "addr:full":"32 Bromley Hill Bromley Kent BR1 4JX",
    "addr:housenumber":"32",
    "addr:postcode":"br1 4jx",
    "addr:street":"Bromley Hill",
    "iso:country":"GB",
    "sg:address":"32 Bromley Hill",
    "sg:city":"Bromley",
    "sg:classifiers":[
        {
            "category":"Fast Food",
            "type":"Food & Drink"
        }
    ],
    "sg:phone":"+44 20 8290 1524",
    "sg:postcode":"BR1 4JX",
    "sg:province":"Kent",
    "sg:tags":[
        "away",
        "take"
    ],
    "wof:name":"Fortune House",
    "wof:placetype":"venue"
},
  "geometry": {"coordinates":[-0.001098,51.420528],"type":"Point"}
}