{
  "type": "Feature",
  "properties": {
    "addr:full":"Calverley Lane, Rodley Leeds West Yorkshire LS13 1NP",
    "addr:postcode":"ls13 1np",
    "addr:street":"Calverley Lane",
    "iso:country":"GB",
    "sg:address":"Calverley Lane, Rodley",
    "sg:city":"Leeds",
    "sg:classifiers":[
        {
            "category":"Wholesale",
            "subcategory":"Meat",
            "type":"Manufacturing & Wholesale Goods"
        },
        {
            "category":"Travel",
            "subcategory":"Hotels & Motels",
            "type":"Entertainment"
        }
    ],
    "sg:postcode":"LS13 1NP",
    "sg:province":"West Yorkshire",
    "sg:tags":[
        "abattoir"
    ],
    "wof:name":"P O'Brien",
    "wof:placetype":"venue"
},
  "geometry": {"coordinates":[-1.661319,53.823101],"type":"Point"}
}