{
  "type": "Feature",
  "properties": {
    "iso:country":"GB",
    "sg:address":"Fordbrook Farm, Brixton",
    "sg:city":"Plymouth",
    "sg:classifiers":[
        {
            "category":"Community Center",
            "type":"Public Place"
        }
    ],
    "sg:postcode":"PL8 2BQ",
    "sg:province":"Devon",
    "sg:tags":[
        "nursery",
        "centre"
    ],
    "wof:name":"Fordbrook Nursery",
    "wof:placetype":"venue"
},
  "geometry": {"coordinates":[-4.034559,50.35146],"type":"Point"}
}