{
  "type": "Feature",
  "properties": {
    "addr:full":"Fitzherbert Road, Farlington Portsmouth Hampshire PO6 1RT",
    "addr:postcode":"hampshire po6 1rt",
    "addr:street":"Fitzherbert Road",
    "iso:country":"GB",
    "sg:address":"Fitzherbert Road, Farlington",
    "sg:city":"Portsmouth",
    "sg:classifiers":[
        {
            "category":"Manufacturing",
            "subcategory":"Electronics",
            "type":"Manufacturing & Wholesale Goods"
        }
    ],
    "sg:phone":"+44 23 9231 4545",
    "sg:postcode":"PO6 1RT",
    "sg:province":"Hampshire",
    "sg:tags":[
        "control",
        "manufacture",
        "-",
        "component",
        "distribution",
        "electronic"
    ],
    "wof:name":"Harwin Plc",
    "wof:placetype":"venue"
},
  "geometry": {"coordinates":[-1.030622,50.843586],"type":"Point"}
}