{
  "type": "Feature",
  "properties": {
    "addr:full":"Rodwell Farm, Baylham Ipswich Suffolk IP6 8JW",
    "addr:postcode":"ip6 8jw",
    "iso:country":"GB",
    "sg:address":"Rodwell Farm, Baylham",
    "sg:city":"Ipswich",
    "sg:classifiers":[
        {
            "category":"Farming",
            "subcategory":"Dairy Farm",
            "type":"Manufacturing & Wholesale Goods"
        }
    ],
    "sg:phone":"+44 1473 830192",
    "sg:postcode":"IP6 8JW",
    "sg:province":"Suffolk",
    "wof:name":"R Richards",
    "wof:placetype":"venue"
},
  "geometry": {"coordinates":[1.072237,52.122375],"type":"Point"}
}