{
  "type": "Feature",
  "properties": {
    "addr:full":"107 The Broadway Southall Greater London UB1 1LN",
    "addr:housenumber":"107",
    "addr:postcode":"ub1 1ln",
    "addr:street":"The Broadway",
    "iso:country":"GB",
    "sg:address":"107 The Broadway",
    "sg:city":"Southall",
    "sg:classifiers":[
        {
            "category":"Food & Beverages",
            "subcategory":"Candy",
            "type":"Retail Goods"
        }
    ],
    "sg:phone":"+44 20 8843 9049",
    "sg:postcode":"UB1 1LN",
    "sg:province":"Greater London",
    "sg:tags":[
        "confectioner"
    ],
    "wof:name":"Ambala Sweet Centre",
    "wof:placetype":"venue"
},
  "geometry": {"coordinates":[-0.390344,51.51318],"type":"Point"}
}