{
  "type": "Feature",
  "properties": {
    "addr:full":"Church Square Inveraray Argyll and Bute PA32 8TX",
    "addr:postcode":"pa32 8tx",
    "addr:street":"Church Square Inveraray",
    "iso:country":"GB",
    "sg:address":"Church Square",
    "sg:city":"Inveraray",
    "sg:classifiers":[
        {
            "category":"Museum",
            "subcategory":"Art Museum",
            "type":"Entertainment"
        },
        {
            "category":"Landmark",
            "subcategory":"Tourist Attraction",
            "type":"Public Place"
        }
    ],
    "sg:phone":"+44 1499 302381",
    "sg:postcode":"PA32 8TX",
    "sg:province":"Argyll and Bute",
    "sg:tags":[
        "gallery",
        "interest"
    ],
    "wof:name":"Inveraray Jail",
    "wof:placetype":"venue"
},
  "geometry": {"coordinates":[-5.07249403,56.2314453125],"type":"Point"}
}