{
  "type": "Feature",
  "properties": {
    "iso:country":"GB",
    "sg:address":"Rosemary Cottage, High Street, Staplehurst",
    "sg:city":"Tonbridge",
    "sg:classifiers":[
        {
            "category":"Professional",
            "subcategory":"Engineering",
            "type":"Services"
        }
    ],
    "sg:postcode":"TN12 0AY",
    "sg:province":"Kent",
    "sg:tags":[
        "consultant",
        "structural"
    ],
    "wof:name":"Alan Baxter",
    "wof:placetype":"venue"
},
  "geometry": {"coordinates":[0.552592,51.167049],"type":"Point"}
}