{
  "type": "Feature",
  "properties": {
    "addr:full":"2 Lezayre Road Orpington Kent BR6 6BP",
    "addr:housenumber":"2",
    "addr:postcode":"br6 6bp",
    "addr:street":"Lezayre Road",
    "iso:country":"GB",
    "sg:address":"2 Lezayre Road",
    "sg:city":"Orpington",
    "sg:classifiers":[
        {
            "category":"Retail",
            "subcategory":"Auto Repair",
            "type":"Services"
        }
    ],
    "sg:phone":"+44 1689 857536",
    "sg:postcode":"BR6 6BP",
    "sg:province":"Kent",
    "sg:tags":[
        "modification",
        "garage"
    ],
    "wof:name":"S D Motors",
    "wof:placetype":"venue"
},
  "geometry": {"coordinates":[0.0906189978,51.3532714844],"type":"Point"}
}