{
  "type": "Feature",
  "properties": {
    "iso:country":"GB",
    "sg:address":"Burton Rd, Streethay",
    "sg:city":"Lichfield",
    "sg:classifiers":[
        {
            "category":"Autos & Motor Vehicles",
            "subcategory":"Automobile Sales",
            "type":"Retail Goods"
        }
    ],
    "sg:phone":"+44 1543 416212",
    "sg:postcode":"WS13 8LT",
    "sg:province":"Staffordshire",
    "sg:tags":[
        "commercial"
    ],
    "wof:name":"G & G Car Sales",
    "wof:placetype":"venue"
},
  "geometry": {"coordinates":[-1.753314,52.688854],"type":"Point"}
}