{
  "type": "Feature",
  "properties": {
    "addr:full":"10 Hanway St West End Hampshire W1P 9DD",
    "addr:housenumber":"10",
    "addr:postcode":"w1p 9dd",
    "addr:street":"Hanway St",
    "iso:country":"GB",
    "sg:address":"10 Hanway St",
    "sg:city":"West End",
    "sg:classifiers":[
        {
            "category":"Shopping",
            "subcategory":"Mobile Phones",
            "type":"Retail Goods"
        }
    ],
    "sg:phone":"+44 20 7436 2626",
    "sg:postcode":"W1P 9DD",
    "sg:province":"Hampshire",
    "wof:name":"Moving Connections",
    "wof:placetype":"venue"
},
  "geometry": {"coordinates":[-0.1321910024,51.5166282654],"type":"Point"}
}