{
  "type": "Feature",
  "properties": {
    "addr:full":"The Forge, Emmerson Close, Swainby Northallerton North Yorkshire DL6 3EL",
    "addr:postcode":"dl6 3el",
    "addr:street":"Emmerson Close",
    "iso:country":"GB",
    "sg:address":"The Forge, Emmerson Close, Swainby",
    "sg:city":"Northallerton",
    "sg:classifiers":[
        {
            "category":"Autos & Motor Vehicles",
            "subcategory":"Automobile Sales",
            "type":"Retail Goods"
        }
    ],
    "sg:phone":"+44 1642 701177",
    "sg:postcode":"DL6 3EL",
    "sg:province":"North Yorkshire",
    "sg:tags":[
        "car"
    ],
    "wof:name":"C McAdams Ltd.",
    "wof:placetype":"venue"
},
  "geometry": {"coordinates":[-1.269127,54.414082],"type":"Point"}
}