{
  "type": "Feature",
  "properties": {
    "addr:full":"3 Main Street Prestwick South Ayrshire KA9 1AA",
    "addr:housenumber":"3",
    "addr:postcode":"ka9 1aa",
    "addr:street":"Main Street",
    "iso:country":"GB",
    "sg:address":"3 Main Street",
    "sg:city":"Prestwick",
    "sg:classifiers":[
        {
            "category":"Food & Beverages",
            "subcategory":"Bakery",
            "type":"Retail Goods"
        }
    ],
    "sg:phone":"+44 1292 474282",
    "sg:postcode":"KA9 1AA",
    "sg:province":"South Ayrshire",
    "sg:tags":[
        "baker"
    ],
    "wof:name":"Daily Bake",
    "wof:placetype":"venue"
},
  "geometry": {"coordinates":[-4.610735,55.501514],"type":"Point"}
}