{
  "type": "Feature",
  "properties": {
    "addr:full":"32 Aleyn Way Baldock Bedfordshire SG7 6SU",
    "addr:housenumber":"32",
    "addr:postcode":"sg7 6su",
    "addr:street":"Aleyn Way",
    "iso:country":"GB",
    "sg:address":"32 Aleyn Way",
    "sg:city":"Baldock",
    "sg:classifiers":[
        {
            "category":"Building & Trades",
            "subcategory":"Construction",
            "type":"Services"
        }
    ],
    "sg:phone":"+44 1462 894997",
    "sg:postcode":"SG7 6SU",
    "sg:province":"Bedfordshire",
    "sg:tags":[
        "decorator",
        "painter"
    ],
    "wof:name":"Richardson Decorators",
    "wof:placetype":"venue"
},
  "geometry": {"coordinates":[-0.169174,51.991734],"type":"Point"}
}