{
  "type": "Feature",
  "properties": {
    "addr:full":"17 Ormerod Rd Burnley Lancashire BB11 2RU",
    "addr:housenumber":"17",
    "addr:postcode":"bb11 2ru",
    "addr:street":"Ormerod Rd",
    "iso:country":"GB",
    "sg:address":"17 Ormerod Rd",
    "sg:city":"Burnley",
    "sg:classifiers":[
        {
            "category":"Health Services",
            "subcategory":"Dentist",
            "type":"Services"
        }
    ],
    "sg:phone":"+44 1282 427404",
    "sg:postcode":"BB11 2RU",
    "sg:province":"Lancashire",
    "wof:name":"M.C Allan",
    "wof:placetype":"venue"
},
  "geometry": {"coordinates":[-2.2382650375,53.792514801],"type":"Point"}
}