{
  "type": "Feature",
  "properties": {
    "iso:country":"GB",
    "sg:address":"5-7 Elphinstone Road",
    "sg:city":"Tranent",
    "sg:classifiers":[
        {
            "category":"Home & Garden",
            "subcategory":"Hardware",
            "type":"Retail Goods"
        },
        {
            "category":"Personal",
            "subcategory":"Skin Care",
            "type":"Services"
        }
    ],
    "sg:phone":"+44 1875 611400",
    "sg:postcode":"EH33 2LG",
    "sg:province":"East Lothian",
    "sg:tags":[
        "part",
        "motorcycle",
        "manufacturer",
        "accessory"
    ],
    "wof:name":"Eclipse Motor Cycles",
    "wof:placetype":"venue"
},
  "geometry": {"coordinates":[-2.961264,55.943363],"type":"Point"}
}