{
  "type": "Feature",
  "properties": {
    "addr:full":"Yeovil Labour Party, Central Road Yeovil Somerset BA20 1JL",
    "addr:postcode":"ba20 1jl",
    "addr:street":"Central Road",
    "iso:country":"GB",
    "sg:address":"Yeovil Labour Party, Central Road",
    "sg:city":"Yeovil",
    "sg:classifiers":[
        {
            "category":"Organizations",
            "subcategory":"Membership Organization",
            "type":"Services"
        }
    ],
    "sg:phone":"+44 1935 423450",
    "sg:postcode":"BA20 1JL",
    "sg:province":"Somerset",
    "sg:tags":[
        "club"
    ],
    "wof:name":"Yeovil Labour Club Ltd.",
    "wof:placetype":"venue"
},
  "geometry": {"coordinates":[-2.6267900467,50.9421806335],"type":"Point"}
}