{
  "type": "Feature",
  "properties": {
    "addr:full":"Vine Rd, Barnes Barnes Greater London SW13 0NE",
    "addr:postcode":"sw13 0ne",
    "addr:street":"Vine Rd",
    "iso:country":"GB",
    "sg:address":"Vine Rd, Barnes",
    "sg:city":"Barnes",
    "sg:classifiers":[
        {
            "category":"Farming",
            "subcategory":"Nursery",
            "type":"Manufacturing & Wholesale Goods"
        }
    ],
    "sg:phone":"+44 20 8878 9695",
    "sg:postcode":"SW13 0NE",
    "sg:province":"Greater London",
    "sg:tags":[
        "creche"
    ],
    "wof:name":"The Montessori Pavilion",
    "wof:placetype":"venue"
},
  "geometry": {"coordinates":[-0.2478239983,51.4666252136],"type":"Point"}
}