{
  "type": "Feature",
  "properties": {
    "iso:country":"GB",
    "sg:address":"133 Grimsby Road",
    "sg:city":"Cleethorpes",
    "sg:classifiers":[
        {
            "category":"Building & Trades",
            "subcategory":"Construction",
            "type":"Services"
        }
    ],
    "sg:phone":"+44 1472 269696",
    "sg:postcode":"DN35 7DG",
    "sg:province":"Lincolnshire",
    "sg:tags":[
        "monumental",
        "mason"
    ],
    "wof:name":"Serenity Memorials",
    "wof:placetype":"venue"
},
  "geometry": {"coordinates":[-0.050256,53.569794],"type":"Point"}
}