{
  "type": "Feature",
  "properties": {
    "addr:full":"1 Railway Street Bishop Auckland Durham DL14 7LR",
    "addr:housenumber":"1",
    "addr:postcode":"dl14 7lr",
    "addr:street":"Railway Street",
    "iso:country":"GB",
    "sg:address":"1 Railway Street",
    "sg:city":"Bishop Auckland",
    "sg:classifiers":[
        {
            "category":"Shopping",
            "subcategory":"Pets & Pet Supplies",
            "type":"Retail Goods"
        }
    ],
    "sg:phone":"+44 1388 609980",
    "sg:postcode":"DL14 7LR",
    "sg:province":"Durham",
    "wof:name":"T & C Kennels & Stable Supplies",
    "wof:placetype":"venue"
},
  "geometry": {"coordinates":[-1.6723970175,54.6592903137],"type":"Point"}
}