{
  "type": "Feature",
  "properties": {
    "iso:country":"GB",
    "sg:address":"298 Whippendell Rd",
    "sg:city":"Watford",
    "sg:classifiers":[
        {
            "category":"Professional",
            "subcategory":"Management & Consulting",
            "type":"Services"
        }
    ],
    "sg:phone":"+44 1923 202072",
    "sg:postcode":"WD1 7PD",
    "sg:province":"Hertfordshire",
    "sg:tags":[
        "consultant",
        "business"
    ],
    "wof:name":"Link Business Services",
    "wof:placetype":"venue"
},
  "geometry": {"coordinates":[-0.411507,51.650848],"type":"Point"}
}