{
  "type": "Feature",
  "properties": {
    "addr:full":"202 Blythe Road London Greater London W14 0HH",
    "addr:housenumber":"202",
    "addr:postcode":"w14 0hh",
    "addr:street":"Blythe Road",
    "iso:country":"GB",
    "sg:address":"202 Blythe Road",
    "sg:city":"London",
    "sg:classifiers":[
        {
            "category":"Retail",
            "subcategory":"Storage",
            "type":"Services"
        }
    ],
    "sg:phone":"+44 20 7602 1181",
    "sg:postcode":"W14 0HH",
    "sg:province":"Greater London",
    "sg:tags":[
        "household",
        "removal"
    ],
    "wof:name":"Aztec Removals Kensington",
    "wof:placetype":"venue"
},
  "geometry": {"coordinates":[-0.220049,51.499454],"type":"Point"}
}