{
  "type": "Feature",
  "properties": {
    "addr:full":"The Granary, Haggs Road Harrogate North Yorkshire HG3 1EQ",
    "addr:postcode":"hg3 1eq",
    "addr:street":"Haggs Road",
    "iso:country":"GB",
    "sg:address":"The Granary, Haggs Road",
    "sg:city":"Harrogate",
    "sg:classifiers":[
        {
            "category":"Organizations",
            "subcategory":"Non-profit Organization",
            "type":"Services"
        }
    ],
    "sg:phone":"+44 1423 879510",
    "sg:postcode":"HG3 1EQ",
    "sg:province":"North Yorkshire",
    "sg:tags":[
        "organisation",
        "voluntary",
        "charity"
    ],
    "wof:name":"The Anthony Nolan Trust",
    "wof:placetype":"venue"
},
  "geometry": {"coordinates":[-1.48723,53.956451],"type":"Point"}
}