{
  "type": "Feature",
  "properties": {
    "addr:full":"Saunders Yard, Trout Road West Drayton Greater London UB7 7SN",
    "addr:postcode":"ub7 7sn",
    "addr:street":"Trout Road",
    "iso:country":"GB",
    "sg:address":"Saunders Yard, Trout Road",
    "sg:city":"West Drayton",
    "sg:classifiers":[
        {
            "category":"Retail",
            "subcategory":"Auto Repair",
            "type":"Services"
        }
    ],
    "sg:phone":"+44 1895 445465",
    "sg:postcode":"UB7 7SN",
    "sg:province":"Greater London",
    "sg:tags":[
        "body",
        "car"
    ],
    "wof:name":"J & J Autos",
    "wof:placetype":"venue"
},
  "geometry": {"coordinates":[-0.4739899933,51.5091171265],"type":"Point"}
}