{
  "type": "Feature",
  "properties": {
    "addr:full":"101 Academy Street Inverness Highland IV1 1LX",
    "addr:housenumber":"101",
    "addr:postcode":"iv1 1lx",
    "addr:street":"Academy Street",
    "iso:country":"GB",
    "sg:address":"101 Academy Street",
    "sg:city":"Inverness",
    "sg:classifiers":[
        {
            "category":"Personal",
            "subcategory":"Barber",
            "type":"Services"
        }
    ],
    "sg:phone":"+44 1463 710111",
    "sg:postcode":"IV1 1LX",
    "sg:province":"Highland",
    "sg:tags":[
        "men's",
        "hairdresser"
    ],
    "wof:name":"Leonard J Cameron",
    "wof:placetype":"venue"
},
  "geometry": {"coordinates":[-4.227809906,57.4805335999],"type":"Point"}
}