{
  "type": "Feature",
  "properties": {
    "addr:full":"51 Winchester Avenue London Greater London NW6 7TT",
    "addr:housenumber":"51",
    "addr:postcode":"nw6 7tt",
    "addr:street":"Winchester Avenue",
    "iso:country":"GB",
    "sg:address":"51 Winchester Avenue",
    "sg:city":"London",
    "sg:classifiers":[
        {
            "category":"Community Center",
            "subcategory":"Youth",
            "type":"Public Place"
        }
    ],
    "sg:postcode":"NW6 7TT",
    "sg:province":"Greater London",
    "sg:tags":[
        "organisation",
        "centre"
    ],
    "wof:name":"Brent Adolescent Centre",
    "wof:placetype":"venue"
},
  "geometry": {"coordinates":[-0.209123,51.540638],"type":"Point"}
}