{
  "type": "Feature",
  "properties": {
    "addr:full":"Bishop Centre, Bath Road, Taplow Maidenhead Berkshire SL6 0NY",
    "addr:postcode":"sl6 0ny",
    "addr:street":"Bath Road",
    "iso:country":"GB",
    "sg:address":"Bishop Centre, Bath Road, Taplow",
    "sg:city":"Maidenhead",
    "sg:classifiers":[
        {
            "category":"Home & Garden",
            "subcategory":"Hardware",
            "type":"Retail Goods"
        }
    ],
    "sg:phone":"+44 1628 604309",
    "sg:postcode":"SL6 0NY",
    "sg:province":"Berkshire",
    "sg:tags":[
        "equipment",
        "bathroom",
        "fitting"
    ],
    "wof:name":"European Bathrooms Ltd.",
    "wof:placetype":"venue"
},
  "geometry": {"coordinates":[-0.687149,51.532169],"type":"Point"}
}