{
  "type": "Feature",
  "properties": {
    "iso:country":"GB",
    "sg:address":"14 Worsley Road North, Walkden, Worsley",
    "sg:city":"Manchester",
    "sg:classifiers":[
        {
            "category":"Professional",
            "subcategory":"Detective & Security Services",
            "type":"Services"
        }
    ],
    "sg:postcode":"M28 3GW",
    "sg:province":"Greater Manchester",
    "sg:tags":[
        "car"
    ],
    "wof:name":"W T Alarms",
    "wof:placetype":"venue"
},
  "geometry": {"coordinates":[-2.400397,53.532791],"type":"Point"}
}