{
  "type": "Feature",
  "properties": {
    "addr:full":"1 Glebe Farm View, Gedling Nottingham Nottinghamshire NG4 4NZ",
    "addr:housenumber":"1",
    "addr:postcode":"ng4 4nz",
    "addr:street":"Glebe Farm View",
    "iso:country":"GB",
    "sg:address":"1 Glebe Farm View, Gedling",
    "sg:city":"Nottingham",
    "sg:classifiers":[
        {
            "category":"Building & Trades",
            "subcategory":"Construction",
            "type":"Services"
        }
    ],
    "sg:postcode":"NG4 4NZ",
    "sg:province":"Nottinghamshire",
    "sg:tags":[
        "builder"
    ],
    "wof:name":"Fox Donald Building Maintenance",
    "wof:placetype":"venue"
},
  "geometry": {"coordinates":[-1.079479,52.984093],"type":"Point"}
}