{
  "type": "Feature",
  "properties": {
    "addr:full":"36 Gedling Rd, Carlton Nottingham Nottinghamshire NG4 3FH",
    "addr:housenumber":"36",
    "addr:postcode":"ng4 3fh",
    "addr:street":"Gedling Rd",
    "iso:country":"GB",
    "sg:address":"36 Gedling Rd, Carlton",
    "sg:city":"Nottingham",
    "sg:classifiers":[
        {
            "category":"Professional",
            "subcategory":"Art Services",
            "type":"Services"
        }
    ],
    "sg:postcode":"NG4 3FH",
    "sg:province":"Nottinghamshire",
    "sg:tags":[
        "photographer"
    ],
    "wof:name":"Colourcraft",
    "wof:placetype":"venue"
},
  "geometry": {"coordinates":[-1.082129,52.970928],"type":"Point"}
}