{
  "type": "Feature",
  "properties": {
    "addr:full":"Jistcourt House, Rutherglen Centre, Seaway Parade Port Talbot Neath Port Talbot SA12 7BR",
    "addr:postcode":"sa12 7br",
    "addr:street":"Rutherglen;Seaway Parade",
    "iso:country":"GB",
    "sg:address":"Jistcourt House, Rutherglen Centre, Seaway Parade",
    "sg:city":"Port Talbot",
    "sg:classifiers":[
        {
            "category":"Building & Trades",
            "subcategory":"Construction",
            "type":"Services"
        }
    ],
    "sg:phone":"+44 1639 823830",
    "sg:postcode":"SA12 7BR",
    "sg:province":"Neath Port Talbot",
    "sg:tags":[
        "builder"
    ],
    "wof:name":"Evans & Norman",
    "wof:placetype":"venue"
},
  "geometry": {"coordinates":[-3.802369,51.591385],"type":"Point"}
}