{
  "type": "Feature",
  "properties": {
    "iso:country":"GB",
    "sg:address":"Canal Street",
    "sg:city":"Huddersfield",
    "sg:classifiers":[
        {
            "category":"Building & Trades",
            "subcategory":"Cleaning & Sanitation",
            "type":"Services"
        }
    ],
    "sg:phone":"+44 1484 518696",
    "sg:postcode":"HD1 6NY",
    "sg:province":"West Yorkshire",
    "sg:tags":[
        "steam"
    ],
    "wof:name":"Acorn Pressure Wash",
    "wof:placetype":"venue"
},
  "geometry": {"coordinates":[-1.771833,53.657242],"type":"Point"}
}