{
  "type": "Feature",
  "properties": {
    "addr:full":"29 Old Barn Rd Wareham Dorset BH20 7HF",
    "addr:housenumber":"29",
    "addr:postcode":"bh20 7hf",
    "addr:street":"Old Barn Rd",
    "iso:country":"GB",
    "sg:address":"29 Old Barn Rd",
    "sg:city":"Wareham",
    "sg:classifiers":[
        {
            "category":"Building & Trades",
            "subcategory":"Equipment Rental",
            "type":"Services"
        }
    ],
    "sg:phone":"+44 1929 471707",
    "sg:postcode":"BH20 7HF",
    "sg:province":"Dorset",
    "sg:tags":[
        "plant",
        "machinery"
    ],
    "wof:name":"Kingsbere Contractors",
    "wof:placetype":"venue"
},
  "geometry": {"coordinates":[-2.221005,50.752789],"type":"Point"}
}