{
  "type": "Feature",
  "properties": {
    "iso:country":"GB",
    "sg:address":"5a Ravensdale Rd, Ravensdale",
    "sg:city":"Mansfield",
    "sg:classifiers":[
        {
            "category":"Food & Beverages",
            "subcategory":"Meat & Fish",
            "type":"Retail Goods"
        }
    ],
    "sg:postcode":"NG18 2DD",
    "sg:province":"Nottinghamshire",
    "sg:tags":[
        "chip"
    ],
    "wof:name":"Chalos,K,",
    "wof:placetype":"venue"
},
  "geometry": {"coordinates":[-1.1796239614,53.1489944458],"type":"Point"}
}