{
  "type": "Feature",
  "properties": {
    "addr:full":"14 Chancery Lane Huddersfield West Yorkshire HD1 2DT",
    "addr:housenumber":"14",
    "addr:postcode":"hd1 2dt",
    "addr:street":"Chancery Lane",
    "iso:country":"GB",
    "sg:address":"14 Chancery Lane",
    "sg:city":"Huddersfield",
    "sg:classifiers":[
        {
            "category":"Shopping",
            "subcategory":"Musical Instruments",
            "type":"Retail Goods"
        }
    ],
    "sg:phone":"+44 1484 542139",
    "sg:postcode":"HD1 2DT",
    "sg:province":"West Yorkshire",
    "wof:name":"Paulman Instruments",
    "wof:placetype":"venue"
},
  "geometry": {"coordinates":[-1.78279,53.646809],"type":"Point"}
}