{
  "type": "Feature",
  "properties": {
    "iso:country":"GB",
    "sg:address":"116 Broadwater Gardens",
    "sg:city":"Orpington",
    "sg:classifiers":[
        {
            "category":"Building & Trades",
            "subcategory":"Plumbing",
            "type":"Services"
        }
    ],
    "sg:phone":"+44 1689 862848",
    "sg:postcode":"BR6 7UA",
    "sg:province":"Kent",
    "sg:tags":[
        "heating"
    ],
    "wof:name":"R & T Plumbing Services",
    "wof:placetype":"venue"
},
  "geometry": {"coordinates":[0.068336,51.364578],"type":"Point"}
}