{
  "type": "Feature",
  "properties": {
    "addr:full":"Peveril Court, West Bridgford Nottingham Nottinghamshire NG2 7PB",
    "addr:postcode":"ng2 7pb",
    "addr:street":"Peveril Court",
    "iso:country":"GB",
    "sg:address":"Peveril Court, West Bridgford",
    "sg:city":"Nottingham",
    "sg:classifiers":[
        {
            "category":"Health Services",
            "subcategory":"Nursing And Care Facility",
            "type":"Services"
        }
    ],
    "sg:phone":"+44 115 981 0370",
    "sg:postcode":"NG2 7PB",
    "sg:province":"Nottinghamshire",
    "sg:tags":[
        "home"
    ],
    "wof:name":"Anchor Housing Trust",
    "wof:placetype":"venue"
},
  "geometry": {"coordinates":[-1.133128,52.928822],"type":"Point"}
}