{
  "type": "Feature",
  "properties": {
    "addr:full":"The New Warehouse, Wood Lane, Bushbury Wolverhampton Staffordshire WV10 8HN",
    "addr:postcode":"wv10 8hn",
    "addr:street":"Wood Lane",
    "iso:country":"GB",
    "sg:address":"The New Warehouse, Wood Lane, Bushbury",
    "sg:city":"Wolverhampton",
    "sg:classifiers":[
        {
            "category":"Food & Beverages",
            "subcategory":"Groceries & Convenience Stores",
            "type":"Retail Goods"
        }
    ],
    "sg:phone":"+44 1902 789715",
    "sg:postcode":"WV10 8HN",
    "sg:province":"Staffordshire",
    "sg:tags":[
        "merchant",
        "potato"
    ],
    "wof:name":"J Newton & Sons",
    "wof:placetype":"venue"
},
  "geometry": {"coordinates":[-2.1168320179,52.6227378845],"type":"Point"}
}