{
  "type": "Feature",
  "properties": {
    "addr:full":"23 Barton Road Maidstone Kent ME15 7DU",
    "addr:housenumber":"23",
    "addr:postcode":"me15 7du",
    "addr:street":"Barton Road",
    "iso:country":"GB",
    "sg:address":"23 Barton Road",
    "sg:city":"Maidstone",
    "sg:classifiers":[
        {
            "category":"Professional",
            "type":"Services"
        }
    ],
    "sg:postcode":"ME15 7DU",
    "sg:province":"Kent",
    "sg:tags":[
        "entertainer"
    ],
    "wof:name":"Mungo the Clown",
    "wof:placetype":"venue"
},
  "geometry": {"coordinates":[0.5288059711,51.2658195496],"type":"Point"}
}