{
  "type": "Feature",
  "properties": {
    "addr:full":"Faringdon Road, Shippon Abingdon Oxfordshire OX13 6NA",
    "addr:postcode":"ox13 6na",
    "addr:street":"Faringdon Road Shippon",
    "iso:country":"GB",
    "sg:address":"Faringdon Road, Shippon",
    "sg:city":"Abingdon",
    "sg:classifiers":[
        {
            "category":"Social Services",
            "subcategory":"Retirement Home",
            "type":"Services"
        }
    ],
    "sg:phone":"+44 1235 524933",
    "sg:postcode":"OX13 6NA",
    "sg:province":"Oxfordshire",
    "sg:tags":[
        "residential",
        "care"
    ],
    "wof:name":"Stowford House",
    "wof:placetype":"venue"
},
  "geometry": {"coordinates":[-1.3213939667,51.6834411621],"type":"Point"}
}