{
  "type": "Feature",
  "properties": {
    "addr:full":"Marina House, Front Street, Old South Moor Stanley Durham DH9 7EY",
    "addr:postcode":"dh9 7ey",
    "addr:street":"Front Street",
    "iso:country":"GB",
    "sg:address":"Marina House, Front Street, Old South Moor",
    "sg:city":"Stanley",
    "sg:classifiers":[
        {
            "category":"Building & Trades",
            "subcategory":"Cleaning & Sanitation",
            "type":"Services"
        }
    ],
    "sg:phone":"+44 1207 231897",
    "sg:postcode":"DH9 7EY",
    "sg:province":"Durham",
    "sg:tags":[
        "sweep",
        "chimney"
    ],
    "wof:name":"George Roberts",
    "wof:placetype":"venue"
},
  "geometry": {"coordinates":[-1.703894,54.867142],"type":"Point"}
}