{
  "type": "Feature",
  "properties": {
    "addr:full":"2 Watling Avenue Edgware Greater London HA8 0LL",
    "addr:housenumber":"2",
    "addr:postcode":"ha8 0ll",
    "addr:street":"Watling Avenue",
    "iso:country":"GB",
    "sg:address":"2 Watling Avenue",
    "sg:city":"Edgware",
    "sg:classifiers":[
        {
            "category":"Shopping",
            "subcategory":"Pharmacy",
            "type":"Retail Goods"
        }
    ],
    "sg:phone":"+44 20 8952 9887",
    "sg:postcode":"HA8 0LL",
    "sg:province":"Greater London",
    "sg:tags":[
        "store",
        "drug",
        "outlet"
    ],
    "wof:name":"Anthony's",
    "wof:placetype":"venue"
},
  "geometry": {"coordinates":[-0.266918987,51.6008987427],"type":"Point"}
}