{
  "type": "Feature",
  "properties": {
    "addr:full":"Unit 2 Brymau Four Trading Est, River La Chester Cheshire CH4 8RF",
    "addr:housenumber":"unit 2",
    "addr:postcode":"ch4 8rf",
    "addr:street":"Brymau",
    "iso:country":"GB",
    "sg:address":"Unit 2 Brymau Four Trading Est, River La",
    "sg:city":"Chester",
    "sg:classifiers":[
        {
            "category":"Food & Beverages",
            "subcategory":"Supermarket",
            "type":"Retail Goods"
        }
    ],
    "sg:phone":"+44 1244 680127",
    "sg:postcode":"CH4 8RF",
    "sg:province":"Cheshire",
    "sg:tags":[
        "frozen"
    ],
    "wof:name":"Borculo Whey Products",
    "wof:placetype":"venue"
},
  "geometry": {"coordinates":[-2.93335,53.180923],"type":"Point"}
}