{
  "type": "Feature",
  "properties": {
    "iso:country":"GB",
    "sg:address":"43 Kilburn Lane",
    "sg:city":"Belper",
    "sg:classifiers":[
        {
            "category":"Utilities",
            "subcategory":"Refuse",
            "type":"Services"
        }
    ],
    "sg:phone":"+44 1773 820700",
    "sg:postcode":"DE56 0SF",
    "sg:province":"Derbyshire",
    "sg:tags":[
        "skip",
        "hire"
    ],
    "wof:name":"D B Skips",
    "wof:placetype":"venue"
},
  "geometry": {"coordinates":[-1.448908,53.020954],"type":"Point"}
}