{
  "type": "Feature",
  "properties": {
    "addr:full":"541 Lincoln Road Peterborough Cambridgeshire PE1 2PB",
    "addr:housenumber":"541",
    "addr:postcode":"pe1 2pb",
    "addr:street":"Lincoln Road",
    "iso:country":"GB",
    "sg:address":"541 Lincoln Road",
    "sg:city":"Peterborough",
    "sg:classifiers":[
        {
            "category":"Shopping",
            "subcategory":"Bicycles & Sporting Goods",
            "type":"Retail Goods"
        }
    ],
    "sg:phone":"+44 1733 561550",
    "sg:postcode":"PE1 2PB",
    "sg:province":"Cambridgeshire",
    "sg:tags":[
        "cycle",
        "accessory"
    ],
    "wof:name":"On Yer Bike",
    "wof:placetype":"venue"
},
  "geometry": {"coordinates":[-0.253378,52.591393],"type":"Point"}
}