{
  "type": "Feature",
  "properties": {
    "iso:country":"GB",
    "sg:address":"17 Castle Street",
    "sg:city":"Cirencester",
    "sg:classifiers":[
        {
            "category":"Bars & Pubs",
            "type":"Food & Drink"
        }
    ],
    "sg:phone":"+44 1285 653187",
    "sg:postcode":"GL7 1QD",
    "sg:province":"Gloucestershire",
    "sg:tags":[
        "pubs",
        "inn"
    ],
    "wof:name":"The Black Horse",
    "wof:placetype":"venue"
},
  "geometry": {"coordinates":[-1.969288,51.716656],"type":"Point"}
}