{
  "type": "Feature",
  "properties": {
    "addr:full":"Dte House, Hollins Lane Bury Lancashire BL9 8AT",
    "addr:postcode":"bl9 8at",
    "addr:street":"Hollins Lane",
    "iso:country":"GB",
    "sg:address":"Dte House, Hollins Lane",
    "sg:city":"Bury",
    "sg:classifiers":[
        {
            "category":"Professional",
            "subcategory":"Accounting & Tax Preparation",
            "type":"Services"
        }
    ],
    "sg:phone":"+44 161 767 1200",
    "sg:postcode":"BL9 8AT",
    "sg:province":"Lancashire",
    "sg:tags":[
        "accountant"
    ],
    "wof:name":"Downham Train Epstein Plc",
    "wof:placetype":"venue"
},
  "geometry": {"coordinates":[-2.2766389847,53.5679397583],"type":"Point"}
}