{
  "type": "Feature",
  "properties": {
    "iso:country":"GB",
    "sg:address":"75a Great George Street",
    "sg:city":"Leeds",
    "sg:classifiers":[
        {
            "category":"Shopping",
            "subcategory":"Florist",
            "type":"Retail Goods"
        }
    ],
    "sg:phone":"+44 113 242 1771",
    "sg:postcode":"LS1 3BR",
    "sg:province":"West Yorkshire",
    "wof:name":"The Flower Court",
    "wof:placetype":"venue"
},
  "geometry": {"coordinates":[-1.5537769794,53.8012199402],"type":"Point"}
}