{
  "type": "Feature",
  "properties": {
    "addr:full":"3 Mid Street Bathgate West Lothian EH48 1PR",
    "addr:housenumber":"3",
    "addr:postcode":"eh48 1pr",
    "addr:street":"Mid Street Bathgate",
    "iso:country":"GB",
    "sg:address":"3 Mid Street",
    "sg:city":"Bathgate",
    "sg:classifiers":[
        {
            "category":"Sports & Exercise",
            "subcategory":"Swimming Pool",
            "type":"Entertainment"
        }
    ],
    "sg:phone":"+44 1506 652783",
    "sg:postcode":"EH48 1PR",
    "sg:province":"West Lothian",
    "wof:name":"Bathgate Swimming Pool",
    "wof:placetype":"venue"
},
  "geometry": {"coordinates":[-3.63968,55.903126],"type":"Point"}
}