{
  "type": "Feature",
  "properties": {
    "addr:full":"20 Brixton Road London Greater London SW9 6BU",
    "addr:housenumber":"20",
    "addr:postcode":"sw9 6bu",
    "addr:street":"Brixton Road",
    "iso:country":"GB",
    "sg:address":"20 Brixton Road",
    "sg:city":"London",
    "sg:classifiers":[
        {
            "category":"Communications",
            "subcategory":"Newspaper",
            "type":"Services"
        },
        {
            "category":"Wholesale",
            "subcategory":"Books, Periodicals, & Newspapers",
            "type":"Manufacturing & Wholesale Goods"
        }
    ],
    "sg:phone":"+44 20 7735 5164",
    "sg:postcode":"SW9 6BU",
    "sg:province":"Greater London",
    "sg:tags":[
        "magazine",
        "publishing"
    ],
    "wof:name":"La Voce Degli Italiani",
    "wof:placetype":"venue"
},
  "geometry": {"coordinates":[-0.111415,51.480339],"type":"Point"}
}