{
  "type": "Feature",
  "properties": {
    "addr:full":"The Smokery, Greenhill Rents, Cowcross St Clerkenwell Greater London EC1M 6BN",
    "addr:postcode":"ec1m 6bn",
    "addr:street":"Greenhill Rents Cowcross St",
    "iso:country":"GB",
    "sg:address":"The Smokery, Greenhill Rents, Cowcross St",
    "sg:city":"Clerkenwell",
    "sg:classifiers":[
        {
            "category":"Professional",
            "subcategory":"Lawyer & Legal Services",
            "type":"Services"
        }
    ],
    "sg:phone":"+44 20 7845 7400",
    "sg:postcode":"EC1M 6BN",
    "sg:province":"Greater London",
    "sg:tags":[
        "solicitor"
    ],
    "wof:name":"Ingram Winter Green",
    "wof:placetype":"venue"
},
  "geometry": {"coordinates":[-0.10246,51.51981],"type":"Point"}
}