{
  "type": "Feature",
  "properties": {
    "iso:country":"GB",
    "sg:address":"Moss Farm, Ellerdine",
    "sg:city":"Telford",
    "sg:classifiers":[
        {
            "category":"Utilities",
            "subcategory":"Refuse",
            "type":"Services"
        }
    ],
    "sg:postcode":"TF6 6RL",
    "sg:province":"Shropshire",
    "sg:tags":[
        "disposal",
        "waste"
    ],
    "wof:name":"Cartwright Waste Disposal Services",
    "wof:placetype":"venue"
},
  "geometry": {"coordinates":[-2.564407,52.78653],"type":"Point"}
}