{
  "type": "Feature",
  "properties": {
    "addr:full":"The Coach House, Caerwent Gardens, Caerwent Caldicot Monmouthshire NP26 5FN",
    "addr:postcode":"np26 5fn",
    "addr:street":"Caerwent",
    "iso:country":"GB",
    "sg:address":"The Coach House, Caerwent Gardens, Caerwent",
    "sg:city":"Caldicot",
    "sg:classifiers":[
        {
            "category":"Building & Trades",
            "subcategory":"Construction",
            "type":"Services"
        }
    ],
    "sg:postcode":"NP26 5FN",
    "sg:province":"Monmouthshire",
    "sg:tags":[
        "builder"
    ],
    "wof:name":"R E Hicks Building Contractors",
    "wof:placetype":"venue"
},
  "geometry": {"coordinates":[-2.766163,51.613064],"type":"Point"}
}