{
  "type": "Feature",
  "properties": {
    "addr:full":"11 Station Terr Caerphilly Caerphilly CF83 1HD",
    "addr:housenumber":"11",
    "addr:postcode":"cf83 1hd",
    "addr:street":"Station Terr",
    "iso:country":"GB",
    "sg:address":"11 Station Terr",
    "sg:city":"Caerphilly",
    "sg:classifiers":[
        {
            "category":"Health Services",
            "subcategory":"Dentist",
            "type":"Services"
        }
    ],
    "sg:phone":"+44 29 2088 2034",
    "sg:postcode":"CF83 1HD",
    "sg:province":"Caerphilly",
    "wof:name":"S McHugh",
    "wof:placetype":"venue"
},
  "geometry": {"coordinates":[-3.218161,51.571987],"type":"Point"}
}