{
  "type": "Feature",
  "properties": {
    "addr:full":"York House, 41 Sheet Street Windsor Berkshire SL4 1DD",
    "addr:housenumber":"41",
    "addr:postcode":"sl4 1dd",
    "addr:street":"Sheet Street",
    "iso:country":"GB",
    "sg:address":"York House, 41 Sheet Street",
    "sg:city":"Windsor",
    "sg:classifiers":[
        {
            "category":"Government",
            "subcategory":"Office",
            "type":"Public Place"
        }
    ],
    "sg:phone":"+44 1753 868111",
    "sg:postcode":"SL4 1DD",
    "sg:province":"Berkshire",
    "sg:tags":[
        "local"
    ],
    "wof:name":"Royal Borough of Windsor & Maidenhead",
    "wof:placetype":"venue"
},
  "geometry": {"coordinates":[-0.606162,51.479111],"type":"Point"}
}