{
  "type": "Feature",
  "properties": {
    "iso:country":"GB",
    "sg:address":"Toc H, Portland Road",
    "sg:city":"Rushden",
    "sg:classifiers":[
        {
            "category":"Insurance",
            "subcategory":"Health Insurance",
            "type":"Services"
        }
    ],
    "sg:phone":"+44 1933 355100",
    "sg:postcode":"NN10 0DJ",
    "sg:province":"Bedfordshire",
    "wof:name":"Northamptonshire & District Hospitals Guild",
    "wof:placetype":"venue"
},
  "geometry": {"coordinates":[-0.5980240107,52.2876243591],"type":"Point"}
}