{
  "type": "Feature",
  "properties": {
    "addr:full":"29 Drumby Crescent Glasgow East Renfrewshire G76 7HN",
    "addr:housenumber":"29",
    "addr:postcode":"g76 7hn",
    "addr:street":"Drumby Crescent",
    "iso:country":"GB",
    "sg:address":"29 Drumby Crescent",
    "sg:city":"Glasgow",
    "sg:classifiers":[
        {
            "category":"Building & Trades",
            "subcategory":"Plumbing",
            "type":"Services"
        }
    ],
    "sg:phone":"+44 141 638 5253",
    "sg:postcode":"G76 7HN",
    "sg:province":"East Renfrewshire",
    "sg:tags":[
        "heating"
    ],
    "wof:name":"Anthony McParland Plumbing Services",
    "wof:placetype":"venue"
},
  "geometry": {"coordinates":[-4.2835302353,55.7938423157],"type":"Point"}
}