{
  "type": "Feature",
  "properties": {
    "iso:country":"GB",
    "sg:address":"4-5 Angel Row",
    "sg:city":"Nottingham",
    "sg:classifiers":[
        {
            "category":"Restaurant",
            "type":"Food & Drink"
        }
    ],
    "sg:phone":"+44 115 941 0108",
    "sg:postcode":"NG1 6HL",
    "sg:province":"Nottinghamshire",
    "sg:tags":[
        "italian"
    ],
    "wof:name":"Bella Pasta",
    "wof:placetype":"venue"
},
  "geometry": {"coordinates":[-1.153290987,52.9538764954],"type":"Point"}
}