{
  "type": "Feature",
  "properties": {
    "addr:full":"35 Long Ley Welwyn Garden City Hertfordshire AL7 2HE",
    "addr:housenumber":"35",
    "addr:postcode":"al7 2he",
    "addr:street":"Long Ley;Garden",
    "iso:country":"GB",
    "sg:address":"35 Long Ley",
    "sg:city":"Welwyn Garden City",
    "sg:classifiers":[
        {
            "category":"Personal",
            "type":"Services"
        }
    ],
    "sg:phone":"+44 1707 330765",
    "sg:postcode":"AL7 2HE",
    "sg:province":"Hertfordshire",
    "sg:tags":[
        "dressmaker",
        "wedding"
    ],
    "wof:name":"Sewing Services",
    "wof:placetype":"venue"
},
  "geometry": {"coordinates":[-0.170451,51.800285],"type":"Point"}
}