{
  "type": "Feature",
  "properties": {
    "addr:full":"Langdon Mill, Begelly Kilgetty Pembrokeshire SA68 0NJ",
    "addr:postcode":"sa68 0nj",
    "addr:street":"Langdon",
    "iso:country":"GB",
    "sg:address":"Langdon Mill, Begelly",
    "sg:city":"Kilgetty",
    "sg:classifiers":[
        {
            "category":"Farming",
            "subcategory":"Farm",
            "type":"Manufacturing & Wholesale Goods"
        }
    ],
    "sg:phone":"+44 1834 891201",
    "sg:postcode":"SA68 0NJ",
    "sg:province":"Pembrokeshire",
    "sg:tags":[
        "mixed",
        "crop"
    ],
    "wof:name":"M D James & Sons",
    "wof:placetype":"venue"
},
  "geometry": {"coordinates":[-4.7145628929,51.7328338623],"type":"Point"}
}