{
  "type": "Feature",
  "properties": {
    "addr:full":"98 High St Olney Buckinghamshire MK46 4BE",
    "addr:housenumber":"98",
    "addr:postcode":"mk46 4be",
    "addr:street":"High St",
    "iso:country":"GB",
    "sg:address":"98 High St",
    "sg:city":"Olney",
    "sg:classifiers":[
        {
            "category":"Shopping",
            "subcategory":"Bicycles & Sporting Goods",
            "type":"Retail Goods"
        }
    ],
    "sg:phone":"+44 1234 711466",
    "sg:postcode":"MK46 4BE",
    "sg:province":"Buckinghamshire",
    "sg:tags":[
        "cycle",
        "accessory"
    ],
    "wof:name":"Minney Bros",
    "wof:placetype":"venue"
},
  "geometry": {"coordinates":[-0.7013300061,52.1567344666],"type":"Point"}
}