{
  "type": "Feature",
  "properties": {
    "addr:full":"8 Ellens Glen Road Edinburgh City of Edinburgh EH17 7QP",
    "addr:housenumber":"8",
    "addr:postcode":"eh17 7qp",
    "addr:street":"Ellens Glen Road",
    "iso:country":"GB",
    "sg:address":"8 Ellens Glen Road",
    "sg:city":"Edinburgh",
    "sg:classifiers":[
        {
            "category":"Building & Trades",
            "subcategory":"Construction",
            "type":"Services"
        }
    ],
    "sg:postcode":"EH17 7QP",
    "sg:province":"City of Edinburgh",
    "sg:tags":[
        "roofing"
    ],
    "wof:name":"John Dixon",
    "wof:placetype":"venue"
},
  "geometry": {"coordinates":[-3.1496720314,55.9110221863],"type":"Point"}
}