{
  "type": "Feature",
  "properties": {
    "iso:country":"GB",
    "sg:address":"334 Cotmanhay Road",
    "sg:city":"Ilkeston",
    "sg:classifiers":[
        {
            "category":"Home & Garden",
            "subcategory":"Home Furnishings",
            "type":"Retail Goods"
        },
        {
            "category":"Home & Garden",
            "subcategory":"Furniture",
            "type":"Retail Goods"
        }
    ],
    "sg:phone":"+44 115 930 7954",
    "sg:postcode":"DE7 8JW",
    "sg:province":"Derbyshire",
    "sg:tags":[
        "fitted"
    ],
    "wof:name":"Oatenvale Ltd.",
    "wof:placetype":"venue"
},
  "geometry": {"coordinates":[-1.308307,52.984535],"type":"Point"}
}