{
  "type": "Feature",
  "properties": {
    "addr:full":"Unit 1 Highlands Ave Wokingham Berkshire RG11 4SP",
    "addr:housenumber":"unit 1",
    "addr:postcode":"rg11 4sp",
    "addr:street":"Highlands Ave",
    "iso:country":"GB",
    "sg:address":"Unit 1 Highlands Ave",
    "sg:city":"Wokingham",
    "sg:classifiers":[
        {
            "category":"Retail",
            "subcategory":"Auto Repair",
            "type":"Services"
        }
    ],
    "sg:postcode":"RG11 4SP",
    "sg:province":"Berkshire",
    "sg:tags":[
        "modification",
        "garage"
    ],
    "wof:name":"Collier,Paul,",
    "wof:placetype":"venue"
},
  "geometry": {"coordinates":[-0.872714,51.406086],"type":"Point"}
}