{
  "type": "Feature",
  "properties": {
    "addr:full":"Unit 3-6 Abergelly Road, Swansea West Industrial Estate Swansea Swansea SA5 4DY",
    "addr:housenumber":"unit 3-6",
    "addr:postcode":"sa5 4dy",
    "addr:street":"Abergelly Road;Industrial Estate",
    "iso:country":"GB",
    "sg:address":"Unit 3-6 Abergelly Road, Swansea West Industrial Estate",
    "sg:city":"Swansea",
    "sg:classifiers":[
        {
            "category":"Food & Beverages",
            "subcategory":"Bakery",
            "type":"Retail Goods"
        }
    ],
    "sg:phone":"+44 1792 585333",
    "sg:postcode":"SA5 4DY",
    "sg:province":"Swansea",
    "sg:tags":[
        "baker",
        "confectionery"
    ],
    "wof:name":"Wendy's Bakery",
    "wof:placetype":"venue"
},
  "geometry": {"coordinates":[-3.9937839508,51.6472740173],"type":"Point"}
}