{
  "type": "Feature",
  "properties": {
    "addr:full":"525 Dunstable Road Luton Bedfordshire LU4 8QN",
    "addr:housenumber":"525",
    "addr:postcode":"lu4 8qn",
    "addr:street":"Dunstable Road",
    "iso:country":"GB",
    "sg:address":"525 Dunstable Road",
    "sg:city":"Luton",
    "sg:classifiers":[
        {
            "category":"Travel",
            "subcategory":"Hotels & Motels",
            "type":"Entertainment"
        }
    ],
    "sg:phone":"+44 1582 491870",
    "sg:postcode":"LU4 8QN",
    "sg:province":"Bedfordshire",
    "sg:tags":[
        "house",
        "guest"
    ],
    "wof:name":"Sunview Guest House",
    "wof:placetype":"venue"
},
  "geometry": {"coordinates":[-0.458233,51.892033],"type":"Point"}
}