{
  "type": "Feature",
  "properties": {
    "addr:full":"7 Station Pde, Kenton La, Off Belmont Circle Harrow Greater London HA3 8SB",
    "addr:housenumber":"7",
    "addr:postcode":"ha3 8sb",
    "addr:street":"Station Pde;La Off Belmont Circle",
    "iso:country":"GB",
    "sg:address":"7 Station Pde, Kenton La, Off Belmont Circle",
    "sg:city":"Harrow",
    "sg:classifiers":[
        {
            "category":"Health Services",
            "subcategory":"Dentist",
            "type":"Services"
        }
    ],
    "sg:phone":"+44 20 8909 3260",
    "sg:postcode":"HA3 8SB",
    "sg:province":"Greater London",
    "wof:name":"Belmont Dental Centre",
    "wof:placetype":"venue"
},
  "geometry": {"coordinates":[-0.319991,51.600891],"type":"Point"}
}