{
  "type": "Feature",
  "properties": {
    "addr:full":"11 Oakley Street Northampton Northamptonshire NN1 3EP",
    "addr:housenumber":"11",
    "addr:postcode":"nn1 3ep",
    "addr:street":"Oakley Street",
    "iso:country":"GB",
    "sg:address":"11 Oakley Street",
    "sg:city":"Northampton",
    "sg:classifiers":[
        {
            "category":"Professional",
            "subcategory":"Printing & Photocopies",
            "type":"Services"
        }
    ],
    "sg:postcode":"NN1 3EP",
    "sg:province":"Northamptonshire",
    "sg:tags":[
        "duplicating",
        "copying"
    ],
    "wof:name":"1ST Copiers",
    "wof:placetype":"venue"
},
  "geometry": {"coordinates":[-0.89337,52.244705],"type":"Point"}
}