{
  "type": "Feature",
  "properties": {
    "addr:full":"Liverpool Road, Great Sankey Warrington Cheshire WA5 3LG",
    "addr:postcode":"wa5 3lg",
    "addr:street":"Liverpool Road",
    "iso:country":"GB",
    "sg:address":"Liverpool Road, Great Sankey",
    "sg:city":"Warrington",
    "sg:classifiers":[
        {
            "category":"Autos & Motor Vehicles",
            "subcategory":"Automobile Sales",
            "type":"Retail Goods"
        },
        {
            "category":"Autos & Motor Vehicles",
            "subcategory":"Auto Supplies",
            "type":"Retail Goods"
        }
    ],
    "sg:phone":"+44 1925 727002",
    "sg:postcode":"WA5 3LG",
    "sg:province":"Cheshire",
    "sg:tags":[
        "exhaust",
        "absorber",
        "shock",
        "car"
    ],
    "wof:name":"Broadoaks Service Station",
    "wof:placetype":"venue"
},
  "geometry": {"coordinates":[-2.66644907,53.3930664062],"type":"Point"}
}