{
  "type": "Feature",
  "properties": {
    "addr:full":"Westfield Lane, Wyke Bradford West Yorkshire BD12 9BT",
    "addr:postcode":"bd12 9bt",
    "addr:street":"Westfield Lane",
    "iso:country":"GB",
    "sg:address":"Westfield Lane, Wyke",
    "sg:city":"Bradford",
    "sg:classifiers":[
        {
            "category":"Retail",
            "subcategory":"Auto Repair",
            "type":"Services"
        }
    ],
    "sg:phone":"+44 1274 603603",
    "sg:postcode":"BD12 9BT",
    "sg:province":"West Yorkshire",
    "sg:tags":[
        "modification",
        "garage"
    ],
    "wof:name":"Wyke Car Centre",
    "wof:placetype":"venue"
},
  "geometry": {"coordinates":[-1.7683000565,53.7368812561],"type":"Point"}
}