{
  "type": "Feature",
  "properties": {
    "addr:full":"Unit 1f, Ravenstor Road, Wirksworth Matlock Derbyshire DE4 4FY",
    "addr:housenumber":"unit 1f",
    "addr:postcode":"de4 4fy",
    "addr:street":"Ravenstor Road",
    "iso:country":"GB",
    "sg:address":"Unit 1f, Ravenstor Road, Wirksworth",
    "sg:city":"Matlock",
    "sg:classifiers":[
        {
            "category":"Professional",
            "subcategory":"Printing & Photocopies",
            "type":"Services"
        }
    ],
    "sg:phone":"+44 1629 826383",
    "sg:postcode":"DE4 4FY",
    "sg:province":"Derbyshire",
    "sg:tags":[
        "printer"
    ],
    "wof:name":"Solar Press Ltd",
    "wof:placetype":"venue"
},
  "geometry": {"coordinates":[-1.5722039938,53.0909538269],"type":"Point"}
}