{
  "type": "Feature",
  "properties": {
    "iso:country":"GB",
    "sg:address":"65 Knightsbridge",
    "sg:city":"London",
    "sg:classifiers":[
        {
            "category":"Mining & Drilling",
            "type":"Manufacturing & Wholesale Goods"
        }
    ],
    "sg:phone":"+44 20 7224 9700",
    "sg:postcode":"SW1X 7RA",
    "sg:province":"Greater London",
    "sg:tags":[
        "oil",
        "petroleum"
    ],
    "wof:name":"Swanshire International Ltd.",
    "wof:placetype":"venue"
},
  "geometry": {"coordinates":[-0.157184,51.502178],"type":"Point"}
}