{
  "type": "Feature",
  "properties": {
    "iso:country":"GB",
    "sg:address":"1a Kinders Lane, Greenfield",
    "sg:city":"Oldham",
    "sg:classifiers":[
        {
            "category":"Cafe",
            "type":"Food & Drink"
        }
    ],
    "sg:phone":"+44 1457 875133",
    "sg:postcode":"OL3 7BW",
    "sg:province":"Lancashire",
    "sg:tags":[
        "tea",
        "snack",
        "bar",
        "room"
    ],
    "wof:name":"Country Kitchen",
    "wof:placetype":"venue"
},
  "geometry": {"coordinates":[-2.0047390461,53.53565979],"type":"Point"}
}