{
  "type": "Feature",
  "properties": {
    "addr:full":"Wheelers Lane Birmingham West Midlands B13 0ST",
    "addr:postcode":"b13 0st",
    "addr:street":"Wheelers Lane",
    "iso:country":"GB",
    "sg:address":"Wheelers Lane",
    "sg:city":"Birmingham",
    "sg:classifiers":[
        {
            "category":"Community Center",
            "type":"Public Place"
        },
        {
            "category":"Government",
            "subcategory":"Office",
            "type":"Public Place"
        }
    ],
    "sg:phone":"+44 121 464 4222",
    "sg:postcode":"B13 0ST",
    "sg:province":"West Midlands",
    "sg:tags":[
        "recreation",
        "local",
        "leisure",
        "centre"
    ],
    "wof:name":"Billesley Indoor Tennis Centre",
    "wof:placetype":"venue"
},
  "geometry": {"coordinates":[-1.8770589828,52.4311447144],"type":"Point"}
}