{
  "type": "Feature",
  "properties": {
    "addr:full":"200 Brunswick Road London Greater London N15 5DB",
    "addr:housenumber":"200",
    "addr:postcode":"n15 5db",
    "addr:street":"Brunswick Road",
    "iso:country":"GB",
    "sg:address":"200 Brunswick Road",
    "sg:city":"London",
    "sg:classifiers":[
        {
            "category":"Organizations",
            "subcategory":"Community Association",
            "type":"Services"
        }
    ],
    "sg:phone":"+44 20 8802 6093",
    "sg:postcode":"N15 5DB",
    "sg:province":"Greater London",
    "sg:tags":[
        "society",
        "housing"
    ],
    "wof:name":"Holly Court",
    "wof:placetype":"venue"
},
  "geometry": {"coordinates":[-0.076219,51.583431],"type":"Point"}
}