{
  "type": "Feature",
  "properties": {
    "addr:full":"Upper Brow Top Farm, Quernmore Lancaster Lancashire LA2 0QW",
    "addr:postcode":"la2 0qw",
    "addr:street":"Upper Brow Top;Quernmore",
    "iso:country":"GB",
    "sg:address":"Upper Brow Top Farm, Quernmore",
    "sg:city":"Lancaster",
    "sg:classifiers":[
        {
            "category":"Transit Center",
            "subcategory":"Freight",
            "type":"Transportation"
        }
    ],
    "sg:postcode":"LA2 0QW",
    "sg:province":"Lancashire",
    "sg:tags":[
        "shop",
        "craft",
        "centre"
    ],
    "wof:name":"R Woodhouse",
    "wof:placetype":"venue"
},
  "geometry": {"coordinates":[-2.72761,54.018822],"type":"Point"}
}