{
  "type": "Feature",
  "properties": {
    "iso:country":"GB",
    "sg:address":"Coppid Hall Farm, Main Road, Havenstreet",
    "sg:city":"Ryde",
    "sg:classifiers":[
        {
            "category":"Farming",
            "subcategory":"Dairy Farm",
            "type":"Manufacturing & Wholesale Goods"
        }
    ],
    "sg:phone":"+44 1983 882489",
    "sg:postcode":"PO33 4DH",
    "sg:province":"Isle of Wight",
    "wof:name":"Coppid Hall Farm",
    "wof:placetype":"venue"
},
  "geometry": {"coordinates":[-1.197274,50.714378],"type":"Point"}
}