{
  "type": "Feature",
  "properties": {
    "addr:full":"58 Buckstones Road, Shaw Oldham Lancashire OL2 8DN",
    "addr:housenumber":"58",
    "addr:postcode":"ol2 8dn",
    "addr:street":"Buckstones Road",
    "iso:country":"GB",
    "sg:address":"58 Buckstones Road, Shaw",
    "sg:city":"Oldham",
    "sg:classifiers":[
        {
            "category":"Personal",
            "subcategory":"Beauty Salon",
            "type":"Services"
        }
    ],
    "sg:postcode":"OL2 8DN",
    "sg:province":"Lancashire",
    "sg:tags":[
        "unisex",
        "hairdresser"
    ],
    "wof:name":"Sylvia's Hair Stylist",
    "wof:placetype":"venue"
},
  "geometry": {"coordinates":[-2.0854279995,53.5873565674],"type":"Point"}
}