{
  "type": "Feature",
  "properties": {
    "addr:full":"Aldborough Road South Ilford Essex IG3 8EU",
    "addr:postcode":"ig3 8eu",
    "addr:street":"Aldborough Road South",
    "iso:country":"GB",
    "sg:address":"Aldborough Road South",
    "sg:city":"Ilford",
    "sg:classifiers":[
        {
            "category":"Education",
            "subcategory":"School",
            "type":"Public Place"
        },
        {
            "category":"Government",
            "subcategory":"Office",
            "type":"Public Place"
        }
    ],
    "sg:phone":"+44 20 8590 3808",
    "sg:postcode":"IG3 8EU",
    "sg:province":"Essex",
    "sg:tags":[
        "local",
        "authority"
    ],
    "wof:name":"Canon Palmer Catholic School",
    "wof:placetype":"venue"
},
  "geometry": {"coordinates":[0.1000249982,51.5775756836],"type":"Point"}
}