{
  "type": "Feature",
  "properties": {
    "addr:full":"15-17 Cook Lane Keighley West Yorkshire BD21 3PY",
    "addr:housenumber":"15-17",
    "addr:postcode":"bd21 3py",
    "addr:street":"Cook Lane",
    "iso:country":"GB",
    "sg:address":"15-17 Cook Lane",
    "sg:city":"Keighley",
    "sg:classifiers":[
        {
            "category":"Home & Garden",
            "subcategory":"Household Appliances",
            "type":"Retail Goods"
        }
    ],
    "sg:phone":"+44 1535 662844",
    "sg:postcode":"BD21 3PY",
    "sg:province":"West Yorkshire",
    "sg:tags":[
        "electrical",
        "domestic"
    ],
    "wof:name":"Dixons",
    "wof:placetype":"venue"
},
  "geometry": {"coordinates":[-1.9084310532,53.8671531677],"type":"Point"}
}