{
  "type": "Feature",
  "properties": {
    "addr:full":"Royal Portbury Dock Bristol Somerset BS20 7XL",
    "addr:postcode":"bs20 7xl",
    "addr:street":"Dock",
    "iso:country":"GB",
    "sg:address":"Royal Portbury Dock",
    "sg:city":"Bristol",
    "sg:classifiers":[
        {
            "category":"Manufacturing",
            "subcategory":"Lumber",
            "type":"Manufacturing & Wholesale Goods"
        }
    ],
    "sg:phone":"+44 1275 375577",
    "sg:postcode":"BS20 7XL",
    "sg:province":"Somerset",
    "sg:tags":[
        "importer",
        "merchants",
        "agent",
        "timber"
    ],
    "wof:name":"Baltic Direct",
    "wof:placetype":"venue"
},
  "geometry": {"coordinates":[-2.7173190117,51.4746360779],"type":"Point"}
}