{
  "type": "Feature",
  "properties": {
    "iso:country":"GB",
    "sg:address":"11 Woosehill Lane",
    "sg:city":"Wokingham",
    "sg:classifiers":[
        {
            "category":"Shopping",
            "subcategory":"Mobile Phones",
            "type":"Retail Goods"
        }
    ],
    "sg:postcode":"RG41 2TT",
    "sg:province":"Berkshire",
    "wof:name":"Thames Cellular",
    "wof:placetype":"venue"
},
  "geometry": {"coordinates":[-0.8503609896,51.4084358215],"type":"Point"}
}