{
  "type": "Feature",
  "properties": {
    "addr:full":"Rear Of 14 Upper Yoden Way Peterlee Durham SR8 1AX",
    "addr:housenumber":"rear of 14",
    "addr:postcode":"sr8 1ax",
    "addr:street":"Upper Yoden Way",
    "iso:country":"GB",
    "sg:address":"Rear Of 14 Upper Yoden Way",
    "sg:city":"Peterlee",
    "sg:classifiers":[
        {
            "category":"Professional",
            "subcategory":"Lawyer & Legal Services",
            "type":"Services"
        }
    ],
    "sg:phone":"+44 191 586 2639",
    "sg:postcode":"SR8 1AX",
    "sg:province":"Durham",
    "sg:tags":[
        "advice",
        "counselling"
    ],
    "wof:name":"Citizens Advice Bureau",
    "wof:placetype":"venue"
},
  "geometry": {"coordinates":[-1.3330550194,54.7609939575],"type":"Point"}
}