{
  "type": "Feature",
  "properties": {
    "addr:full":"133 Commercial Street, Senghenydd Caerphilly Caerphilly CF83 4FZ",
    "addr:housenumber":"133",
    "addr:postcode":"cf83 4fz",
    "addr:street":"Commercial Street",
    "iso:country":"GB",
    "sg:address":"133 Commercial Street, Senghenydd",
    "sg:city":"Caerphilly",
    "sg:classifiers":[
        {
            "category":"Retail",
            "subcategory":"Auto Repair",
            "type":"Services"
        }
    ],
    "sg:phone":"+44 29 2083 0141",
    "sg:postcode":"CF83 4FZ",
    "sg:province":"Caerphilly",
    "sg:tags":[
        "modification",
        "garage"
    ],
    "wof:name":"Windsor Motor Repairs",
    "wof:placetype":"venue"
},
  "geometry": {"coordinates":[-3.2759869099,51.6067237854],"type":"Point"}
}