{
  "type": "Feature",
  "properties": {
    "addr:full":"70 St Nicolas Park Drive Nuneaton Leicestershire CV11 6DJ",
    "addr:housenumber":"70",
    "addr:postcode":"cv11 6dj",
    "addr:street":"St Nicolas Park Drive",
    "iso:country":"GB",
    "sg:address":"70 St Nicolas Park Drive",
    "sg:city":"Nuneaton",
    "sg:classifiers":[
        {
            "category":"Shopping",
            "subcategory":"Florist",
            "type":"Retail Goods"
        }
    ],
    "sg:phone":"+44 24 7635 1120",
    "sg:postcode":"CV11 6DJ",
    "sg:province":"Leicestershire",
    "wof:name":"Anns Florist",
    "wof:placetype":"venue"
},
  "geometry": {"coordinates":[-1.446618,52.536114],"type":"Point"}
}