{
  "type": "Feature",
  "properties": {
    "addr:full":"7 St Johns Place, Whitchurch Cardiff Cardiff CF14 7AJ",
    "addr:housenumber":"7",
    "addr:postcode":"cf14 7aj",
    "addr:street":"St Johns Place",
    "iso:country":"GB",
    "sg:address":"7 St Johns Place, Whitchurch",
    "sg:city":"Cardiff",
    "sg:classifiers":[
        {
            "category":"Professional",
            "subcategory":"Engineering",
            "type":"Services"
        }
    ],
    "sg:postcode":"CF14 7AJ",
    "sg:province":"Cardiff",
    "wof:name":"Allied Technologies Ltd.",
    "wof:placetype":"venue"
},
  "geometry": {"coordinates":[-3.2241,51.519901],"type":"Point"}
}