{
  "type": "Feature",
  "properties": {
    "addr:full":"The Manor House, Gosfield Halstead Essex CO9 1SE",
    "addr:postcode":"co9 1se",
    "addr:street":"Gosfield",
    "iso:country":"GB",
    "sg:address":"The Manor House, Gosfield",
    "sg:city":"Halstead",
    "sg:classifiers":[
        {
            "category":"Sports & Exercise",
            "subcategory":"Golf",
            "type":"Entertainment"
        }
    ],
    "sg:phone":"+44 1787 474747",
    "sg:postcode":"CO9 1SE",
    "sg:province":"Essex",
    "sg:tags":[
        "club",
        "course"
    ],
    "wof:name":"Gosfield Lake Golf Club Ltd.",
    "wof:placetype":"venue"
},
  "geometry": {"coordinates":[0.6537200212,51.9103851318],"type":"Point"}
}