{
  "type": "Feature",
  "properties": {
    "addr:full":"49 Bluestone Lane Immingham Lincolnshire DN40 2DU",
    "addr:housenumber":"49",
    "addr:postcode":"dn40 2du",
    "addr:street":"Bluestone Lane",
    "iso:country":"GB",
    "sg:address":"49 Bluestone Lane",
    "sg:city":"Immingham",
    "sg:classifiers":[
        {
            "category":"Personal",
            "subcategory":"Beauty Salon",
            "type":"Services"
        },
        {
            "category":"Personal",
            "subcategory":"Barber",
            "type":"Services"
        }
    ],
    "sg:phone":"+44 1469 572933",
    "sg:postcode":"DN40 2DU",
    "sg:province":"Lincolnshire",
    "sg:tags":[
        "unisex",
        "hairdresser"
    ],
    "wof:name":"Fay Elizabeth",
    "wof:placetype":"venue"
},
  "geometry": {"coordinates":[-0.224579,53.614311],"type":"Point"}
}