{
  "type": "Feature",
  "properties": {
    "iso:country":"GB",
    "sg:address":"15 Upton Close",
    "sg:city":"Ipswich",
    "sg:classifiers":[
        {
            "category":"Retail",
            "subcategory":"Driving School",
            "type":"Services"
        },
        {
            "category":"Health Services",
            "subcategory":"Podiatrist",
            "type":"Services"
        }
    ],
    "sg:phone":"+44 1473 225319",
    "sg:postcode":"IP4 2QQ",
    "sg:province":"Suffolk",
    "sg:tags":[
        "podiatrists",
        "chiropodist"
    ],
    "wof:name":"Maria Gordon",
    "wof:placetype":"venue"
},
  "geometry": {"coordinates":[1.1677540541,52.0581626892],"type":"Point"}
}