{
  "type": "Feature",
  "properties": {
    "iso:country":"GB",
    "sg:address":"6 St Johns Close",
    "sg:city":"Norwich",
    "sg:classifiers":[
        {
            "category":"Recreation",
            "subcategory":"Fishing",
            "type":"Entertainment"
        }
    ],
    "sg:phone":"+44 1603 626770",
    "sg:postcode":"NR1 2AD",
    "sg:province":"Norfolk",
    "sg:tags":[
        "angling"
    ],
    "wof:name":"Tom Boulton Fishing Tackle",
    "wof:placetype":"venue"
},
  "geometry": {"coordinates":[1.294437,52.614452],"type":"Point"}
}