{
  "type": "Feature",
  "properties": {
    "addr:full":"32 Victoria Road Southampton Hampshire SO19 9DX",
    "addr:housenumber":"32",
    "addr:postcode":"so19 9dx",
    "addr:street":"Victoria Road",
    "iso:country":"GB",
    "sg:address":"32 Victoria Road",
    "sg:city":"Southampton",
    "sg:classifiers":[
        {
            "category":"Organizations",
            "subcategory":"Membership Organization",
            "type":"Services"
        }
    ],
    "sg:postcode":"SO19 9DX",
    "sg:province":"Hampshire",
    "sg:tags":[
        "club"
    ],
    "wof:name":"Woolston Social Club",
    "wof:placetype":"venue"
},
  "geometry": {"coordinates":[-1.379986,50.897179],"type":"Point"}
}