{
  "type": "Feature",
  "properties": {
    "addr:full":"Unit 16 The Ashley Centre Epsom Surrey KT18 5DA",
    "addr:housenumber":"unit 16;ashley centre",
    "addr:postcode":"kt18 5da",
    "addr:street":"The",
    "iso:country":"GB",
    "sg:address":"Unit 16 The Ashley Centre",
    "sg:city":"Epsom",
    "sg:classifiers":[
        {
            "category":"Food & Beverages",
            "subcategory":"Candy",
            "type":"Retail Goods"
        }
    ],
    "sg:phone":"+44 1372 742980",
    "sg:postcode":"KT18 5DA",
    "sg:province":"Surrey",
    "sg:tags":[
        "confectioner"
    ],
    "wof:name":"Thorntons plc",
    "wof:placetype":"venue"
},
  "geometry": {"coordinates":[-0.257354,51.326801],"type":"Point"}
}