{
  "type": "Feature",
  "properties": {
    "addr:full":"Whitecote, Gestingthorpe Road, Little Maplestead Halstead Essex CO9 2SN",
    "addr:postcode":"co9 2sn",
    "addr:street":"Gestingthorpe Road",
    "iso:country":"GB",
    "sg:address":"Whitecote, Gestingthorpe Road, Little Maplestead",
    "sg:city":"Halstead",
    "sg:classifiers":[
        {
            "category":"Professional",
            "subcategory":"Engineering",
            "type":"Services"
        }
    ],
    "sg:phone":"+44 1223 271820",
    "sg:postcode":"CO9 2SN",
    "sg:province":"Essex",
    "sg:tags":[
        "consultant",
        "structural"
    ],
    "wof:name":"Wright Consulting Engineers Ltd.",
    "wof:placetype":"venue"
},
  "geometry": {"coordinates":[0.635825,51.943996],"type":"Point"}
}