{
  "type": "Feature",
  "properties": {
    "addr:full":"36 Pandora Rd Kilburn Greater London NW6 1TT",
    "addr:housenumber":"36",
    "addr:postcode":"nw6 1tt",
    "addr:street":"Pandora Rd",
    "iso:country":"GB",
    "sg:address":"36 Pandora Rd",
    "sg:city":"Kilburn",
    "sg:classifiers":[
        {
            "category":"Retail",
            "subcategory":"Storage",
            "type":"Services"
        }
    ],
    "sg:phone":"+44 7973 671954",
    "sg:postcode":"NW6 1TT",
    "sg:province":"Greater London",
    "sg:tags":[
        "household",
        "removal"
    ],
    "wof:name":"A Simple Move",
    "wof:placetype":"venue"
},
  "geometry": {"coordinates":[-0.195507,51.549706],"type":"Point"}
}