{
  "type": "Feature",
  "properties": {
    "iso:country":"GB",
    "sg:address":"Raf Linton-on-ouse",
    "sg:city":"York",
    "sg:classifiers":[
        {
            "category":"Real Estate",
            "subcategory":"Real Estate Services",
            "type":"Services"
        },
        {
            "category":"Building & Trades",
            "subcategory":"Cleaning & Sanitation",
            "type":"Services"
        }
    ],
    "sg:phone":"+44 1347 848355",
    "sg:postcode":"YO6 2AJ",
    "sg:province":"East Riding of Yorkshire",
    "sg:tags":[
        "management",
        "facility"
    ],
    "wof:name":"Mowlem Aqumen Managed Services Ltd.",
    "wof:placetype":"venue"
},
  "geometry": {"coordinates":[-1.2483,54.04055],"type":"Point"}
}