{
  "type": "Feature",
  "properties": {
    "iso:country":"GB",
    "sg:address":"The Old Greyhound, Church End",
    "sg:city":"Dunstable",
    "sg:classifiers":[
        {
            "category":"Retail",
            "subcategory":"Repair Shop",
            "type":"Services"
        }
    ],
    "sg:postcode":"LU6 2EP",
    "sg:province":"Bedfordshire",
    "sg:tags":[
        "maintenance"
    ],
    "wof:name":"R Bennett",
    "wof:placetype":"venue"
},
  "geometry": {"coordinates":[-0.520663,51.885803],"type":"Point"}
}