{
  "type": "Feature",
  "properties": {
    "iso:country":"GB",
    "sg:address":"Lord Lister Health Centre, 121 Woodgrange Rd",
    "sg:city":"Forest Gate",
    "sg:classifiers":[
        {
            "category":"Health Services",
            "subcategory":"Doctor",
            "type":"Services"
        }
    ],
    "sg:phone":"+44 20 8250 7585",
    "sg:postcode":"E7 0EP",
    "sg:province":"Greater London",
    "sg:tags":[
        "practitioners"
    ],
    "wof:name":"Patel, Y I",
    "wof:placetype":"venue"
},
  "geometry": {"coordinates":[0.02496,51.550671],"type":"Point"}
}