{
  "type": "Feature",
  "properties": {
    "addr:full":"70-71 Wells Street London Greater London W1T 3QE",
    "addr:housenumber":"70-71",
    "addr:postcode":"w1t 3qe",
    "addr:street":"Wells Street",
    "iso:country":"GB",
    "sg:address":"70-71 Wells Street",
    "sg:city":"London",
    "sg:classifiers":[
        {
            "category":"Shopping",
            "subcategory":"Clothing, Apparel, & Fashions",
            "type":"Retail Goods"
        }
    ],
    "sg:phone":"+44 20 7580 3395",
    "sg:postcode":"W1T 3QE",
    "sg:province":"Greater London",
    "sg:tags":[
        "clothing",
        "fabric"
    ],
    "wof:name":"Jonathan Simon Ltd.",
    "wof:placetype":"venue"
},
  "geometry": {"coordinates":[-0.1398359984,51.5185775757],"type":"Point"}
}