{
  "type": "Feature",
  "properties": {
    "iso:country":"GB",
    "sg:address":"Care Of Hanham Methodist Church, Chapel Rd",
    "sg:city":"Bristol",
    "sg:classifiers":[
        {
            "category":"Place Of Worship",
            "type":"Public Place"
        }
    ],
    "sg:phone":"+44 117 935 3308",
    "sg:postcode":"BS30 8SD",
    "sg:province":"Gloucestershire",
    "wof:name":"Kingswood Methodist Circuit",
    "wof:placetype":"venue"
},
  "geometry": {"coordinates":[-2.51604,51.449402],"type":"Point"}
}