{
  "type": "Feature",
  "properties": {
    "addr:full":"209 Churchill Avenue Aylesbury Buckinghamshire HP21 8BA",
    "addr:housenumber":"209",
    "addr:postcode":"hp21 8ba",
    "addr:street":"Churchill Avenue",
    "iso:country":"GB",
    "sg:address":"209 Churchill Avenue",
    "sg:city":"Aylesbury",
    "sg:classifiers":[
        {
            "category":"Building & Trades",
            "subcategory":"Cleaning & Sanitation",
            "type":"Services"
        }
    ],
    "sg:phone":"+44 1296 484370",
    "sg:postcode":"HP21 8BA",
    "sg:province":"Buckinghamshire",
    "sg:tags":[
        "steam"
    ],
    "wof:name":"J.S.B Mobile Cleaning",
    "wof:placetype":"venue"
},
  "geometry": {"coordinates":[-0.8073580265,51.7989807129],"type":"Point"}
}