{
  "type": "Feature",
  "properties": {
    "addr:full":"382 Grace Way Stevenage Hertfordshire SG1 5AR",
    "addr:housenumber":"382",
    "addr:postcode":"sg1 5ar",
    "addr:street":"Grace Way",
    "iso:country":"GB",
    "sg:address":"382 Grace Way",
    "sg:city":"Stevenage",
    "sg:classifiers":[
        {
            "category":"Building & Trades",
            "subcategory":"Construction",
            "type":"Services"
        }
    ],
    "sg:phone":"+44 1438 359166",
    "sg:postcode":"SG1 5AR",
    "sg:province":"Hertfordshire",
    "sg:tags":[
        "roofing"
    ],
    "wof:name":"Empire Roofing",
    "wof:placetype":"venue"
},
  "geometry": {"coordinates":[-0.1920119971,51.9112625122],"type":"Point"}
}