{
  "type": "Feature",
  "properties": {
    "addr:full":"Suffolk House, 3 Sorrel House, Grimwade Street Ipswich Suffolk IP4 1LN",
    "addr:housenumber":"3",
    "addr:postcode":"ip4 1ln",
    "addr:street":"Grimwade Street",
    "iso:country":"GB",
    "sg:address":"Suffolk House, 3 Sorrel House, Grimwade Street",
    "sg:city":"Ipswich",
    "sg:classifiers":[
        {
            "category":"Insurance",
            "subcategory":"Insurance Agent",
            "type":"Services"
        }
    ],
    "sg:postcode":"IP4 1LN",
    "sg:province":"Suffolk",
    "sg:tags":[
        "broker"
    ],
    "wof:name":"M R M I B Ltd.",
    "wof:placetype":"venue"
},
  "geometry": {"coordinates":[1.1627800465,52.0536613464],"type":"Point"}
}