{
  "type": "Feature",
  "properties": {
    "iso:country":"GB",
    "sg:address":"315 High Rd",
    "sg:city":"Ilford",
    "sg:classifiers":[
        {
            "category":"Taxi",
            "type":"Transportation"
        }
    ],
    "sg:phone":"+44 20 8553 4114",
    "sg:postcode":"IG1 1NR",
    "sg:province":"Essex",
    "sg:tags":[
        "mini",
        "cab"
    ],
    "wof:name":"Barking Radio Cars",
    "wof:placetype":"venue"
},
  "geometry": {"coordinates":[0.088881,51.562363],"type":"Point"}
}