{
  "type": "Feature",
  "properties": {
    "addr:full":"315 High Rd Ilford Essex IG1 1NR",
    "addr:housenumber":"315",
    "addr:postcode":"ig1 1nr",
    "addr:street":"High Rd",
    "iso:country":"GB",
    "sg:address":"315 High Rd",
    "sg:city":"Ilford",
    "sg:classifiers":[
        {
            "category":"Taxi",
            "type":"Transportation"
        }
    ],
    "sg:phone":"+44 20 8553 4114",
    "sg:postcode":"IG1 1NR",
    "sg:province":"Essex",
    "sg:tags":[
        "mini",
        "cab"
    ],
    "wof:name":"Barking Radio Cars",
    "wof:placetype":"venue"
},
  "geometry": {"coordinates":[0.088881,51.562363],"type":"Point"}
}