{
  "type": "Feature",
  "properties": {
    "addr:full":"2 Linton St Leicester Leicestershire LE5 5JA",
    "addr:housenumber":"2",
    "addr:postcode":"le5 5ja",
    "addr:street":"Linton St",
    "iso:country":"GB",
    "sg:address":"2 Linton St",
    "sg:city":"Leicester",
    "sg:classifiers":[
        {
            "category":"Education",
            "subcategory":"Special Training",
            "type":"Public Place"
        }
    ],
    "sg:postcode":"LE5 5JA",
    "sg:province":"Leicestershire",
    "sg:tags":[
        "product",
        "centre"
    ],
    "wof:name":"Geer,Nigel,",
    "wof:placetype":"venue"
},
  "geometry": {"coordinates":[-1.1090769768,52.625869751],"type":"Point"}
}