{
  "type": "Feature",
  "properties": {
    "addr:full":"6 Anson Street Liverpool Merseyside L3 5NY",
    "addr:housenumber":"6",
    "addr:postcode":"l3 5ny",
    "addr:street":"Anson Street",
    "iso:country":"GB",
    "sg:address":"6 Anson Street",
    "sg:city":"Liverpool",
    "sg:classifiers":[
        {
            "category":"Organizations",
            "subcategory":"Professional Association",
            "type":"Services"
        }
    ],
    "sg:phone":"+44 151 707 0572",
    "sg:postcode":"L3 5NY",
    "sg:province":"Merseyside",
    "sg:tags":[
        "union",
        "trade"
    ],
    "wof:name":"Prospect",
    "wof:placetype":"venue"
},
  "geometry": {"coordinates":[-2.9707329273,53.4093551636],"type":"Point"}
}