{
  "type": "Feature",
  "properties": {
    "addr:full":"33 Foxholes Lane, Calverley Pudsey West Yorkshire LS28 5NS",
    "addr:housenumber":"33",
    "addr:postcode":"ls28 5ns",
    "addr:street":"Foxholes Lane;West",
    "iso:country":"GB",
    "sg:address":"33 Foxholes Lane, Calverley",
    "sg:city":"Pudsey",
    "sg:classifiers":[
        {
            "category":"Building & Trades",
            "subcategory":"Construction",
            "type":"Services"
        }
    ],
    "sg:phone":"+44 113 256 8595",
    "sg:postcode":"LS28 5NS",
    "sg:province":"West Yorkshire",
    "sg:tags":[
        "roofing"
    ],
    "wof:name":"J R Sowery Cladding",
    "wof:placetype":"venue"
},
  "geometry": {"coordinates":[-1.6857440472,53.8259162903],"type":"Point"}
}