{
  "type": "Feature",
  "properties": {
    "iso:country":"GB",
    "sg:address":"11 Coronation Buildings, Wallasey Rd, Liscard",
    "sg:city":"Wallasey",
    "sg:classifiers":[
        {
            "category":"Organizations",
            "subcategory":"Non-profit Organization",
            "type":"Services"
        }
    ],
    "sg:phone":"+44 151 630 5356",
    "sg:postcode":"L45 4NE",
    "sg:province":"Merseyside",
    "sg:tags":[
        "organisation",
        "voluntary",
        "charity"
    ],
    "wof:name":"Y.M.C.A Charity Shop",
    "wof:placetype":"venue"
},
  "geometry": {"coordinates":[-3.05002,53.42144],"type":"Point"}
}