{
  "type": "Feature",
  "properties": {
    "addr:full":"Tempest Tower, Little Orton Carlisle Cumbria CA5 6EP",
    "addr:postcode":"ca5 6ep",
    "addr:street":"Little",
    "iso:country":"GB",
    "sg:address":"Tempest Tower, Little Orton",
    "sg:city":"Carlisle",
    "sg:classifiers":[
        {
            "category":"Farming",
            "subcategory":"Dairy Farm",
            "type":"Manufacturing & Wholesale Goods"
        }
    ],
    "sg:phone":"+44 1228 576322",
    "sg:postcode":"CA5 6EP",
    "sg:province":"Cumbria",
    "sg:tags":[
        "farmer"
    ],
    "wof:name":"T W Martin",
    "wof:placetype":"venue"
},
  "geometry": {"coordinates":[-3.0132300854,54.8868942261],"type":"Point"}
}