{
  "type": "Feature",
  "properties": {
    "addr:full":"21 Station Road, Helmdon Brackley Buckinghamshire NN13 5QT",
    "addr:housenumber":"21",
    "addr:postcode":"nn13 5qt",
    "addr:street":"Station Road",
    "iso:country":"GB",
    "sg:address":"21 Station Road, Helmdon",
    "sg:city":"Brackley",
    "sg:classifiers":[
        {
            "category":"Education",
            "subcategory":"School",
            "type":"Public Place"
        }
    ],
    "sg:phone":"+44 1295 768126",
    "sg:postcode":"NN13 5QT",
    "sg:province":"Buckinghamshire",
    "sg:tags":[
        "local",
        "authority"
    ],
    "wof:name":"Helmdon County Primary School",
    "wof:placetype":"venue"
},
  "geometry": {"coordinates":[-1.1460050344,52.0873451233],"type":"Point"}
}