{
  "type": "Feature",
  "properties": {
    "addr:full":"851-853 Holderness Road Hull East Riding of Yorkshire HU8 9BA",
    "addr:housenumber":"851-853",
    "addr:postcode":"hu8 9ba",
    "addr:street":"Holderness Road",
    "iso:country":"GB",
    "sg:address":"851-853 Holderness Road",
    "sg:city":"Hull",
    "sg:classifiers":[
        {
            "category":"Social Services",
            "subcategory":"Retirement Home",
            "type":"Services"
        }
    ],
    "sg:phone":"+44 1482 794270",
    "sg:postcode":"HU8 9BA",
    "sg:province":"East Riding of Yorkshire",
    "sg:tags":[
        "residential",
        "care"
    ],
    "wof:name":"Homestead Residential Home for the Elderly",
    "wof:placetype":"venue"
},
  "geometry": {"coordinates":[-0.2853569984,53.7676010132],"type":"Point"}
}