{
  "type": "Feature",
  "properties": {
    "iso:country":"GB",
    "sg:address":"43 Albany Park Drive, Winnersh",
    "sg:city":"Wokingham",
    "sg:classifiers":[
        {
            "category":"Professional",
            "subcategory":"Management & Consulting",
            "type":"Services"
        }
    ],
    "sg:postcode":"RG41 5HZ",
    "sg:province":"Berkshire",
    "sg:tags":[
        "environmental",
        "consultant"
    ],
    "wof:name":"Envex Co. Ltd.",
    "wof:placetype":"venue"
},
  "geometry": {"coordinates":[-0.8876109719,51.4350013733],"type":"Point"}
}