{
  "type": "Feature",
  "properties": {
    "iso:country":"GB",
    "sg:address":"Swindon Road, Kington Langley",
    "sg:city":"Chippenham",
    "sg:classifiers":[
        {
            "category":"Professional",
            "subcategory":"Computer Services",
            "type":"Services"
        }
    ],
    "sg:phone":"+44 1249 751000",
    "sg:postcode":"SN15 5SE",
    "sg:province":"Wiltshire",
    "sg:tags":[
        "consultant"
    ],
    "wof:name":"A S E Group",
    "wof:placetype":"venue"
},
  "geometry": {"coordinates":[-2.114341,51.489937],"type":"Point"}
}