{
  "type": "Feature",
  "properties": {
    "addr:full":"Birmingham Road, Hagley Stourbridge West Midlands DY9 9JS",
    "addr:postcode":"dy9 9js",
    "addr:street":"Birmingham Road",
    "iso:country":"GB",
    "sg:address":"Birmingham Road, Hagley",
    "sg:city":"Stourbridge",
    "sg:classifiers":[
        {
            "category":"Travel",
            "subcategory":"Hotels & Motels",
            "type":"Entertainment"
        },
        {
            "category":"Restaurant",
            "type":"Food & Drink"
        }
    ],
    "sg:phone":"+44 1562 883120",
    "sg:postcode":"DY9 9JS",
    "sg:province":"West Midlands",
    "sg:tags":[
        "-",
        "english"
    ],
    "wof:name":"Badgers Sett",
    "wof:placetype":"venue"
},
  "geometry": {"coordinates":[-2.123934,52.427727],"type":"Point"}
}