{
  "type": "Feature",
  "properties": {
    "iso:country":"GB",
    "sg:address":"The Old Orchard, Woodside Lane, Wroot",
    "sg:city":"Doncaster",
    "sg:classifiers":[
        {
            "category":"Building & Trades",
            "subcategory":"Construction",
            "type":"Services"
        }
    ],
    "sg:phone":"+44 1302 771526",
    "sg:postcode":"DN9 2BP",
    "sg:province":"Lincolnshire",
    "sg:tags":[
        "tile",
        "fitting",
        "tiling",
        "laying",
        "contractor"
    ],
    "wof:name":"A D Tiling",
    "wof:placetype":"venue"
},
  "geometry": {"coordinates":[-0.832111001,53.4867401123],"type":"Point"}
}