{
  "type": "Feature",
  "properties": {
    "addr:full":"Unit 1, Finch Close Nottingham Nottinghamshire NG7 2NN",
    "addr:housenumber":"unit 1",
    "addr:postcode":"ng7 2nn",
    "addr:street":"Finch Close",
    "iso:country":"GB",
    "sg:address":"Unit 1, Finch Close",
    "sg:city":"Nottingham",
    "sg:classifiers":[
        {
            "category":"Autos & Motor Vehicles",
            "subcategory":"Auto Supplies",
            "type":"Retail Goods"
        }
    ],
    "sg:phone":"+44 115 986 5114",
    "sg:postcode":"NG7 2NN",
    "sg:province":"Nottinghamshire",
    "sg:tags":[
        "tyre"
    ],
    "wof:name":"Central Tyre",
    "wof:placetype":"venue"
},
  "geometry": {"coordinates":[-1.171151042,52.9372177124],"type":"Point"}
}