{
  "type": "Feature",
  "properties": {
    "iso:country":"GB",
    "sg:address":"119 Cambuslang Road",
    "sg:city":"Glasgow",
    "sg:classifiers":[
        {
            "category":"Autos & Motor Vehicles",
            "subcategory":"Auto Supplies",
            "type":"Retail Goods"
        },
        {
            "category":"Retail",
            "subcategory":"Auto Repair",
            "type":"Services"
        }
    ],
    "sg:phone":"+44 141 647 5399",
    "sg:postcode":"G72 7TS",
    "sg:province":"South Lanarkshire",
    "sg:tags":[
        "modification",
        "garage",
        "related",
        "towbars"
    ],
    "wof:name":"Towbar Centre",
    "wof:placetype":"venue"
},
  "geometry": {"coordinates":[-4.194215,55.827354],"type":"Point"}
}