{
  "type": "Feature",
  "properties": {
    "iso:country":"GB",
    "sg:address":"Barncoose Lane, Illogan Highway",
    "sg:city":"Redruth",
    "sg:classifiers":[
        {
            "category":"Autos & Motor Vehicles",
            "subcategory":"Auto Supplies",
            "type":"Retail Goods"
        }
    ],
    "sg:phone":"+44 1209 215397",
    "sg:postcode":"TR15 3EW",
    "sg:province":"Cornwall",
    "sg:tags":[
        "tyre"
    ],
    "wof:name":"Associated Tyre Specialists Ltd.",
    "wof:placetype":"venue"
},
  "geometry": {"coordinates":[-5.2511582375,50.2287864685],"type":"Point"}
}