{
  "type": "Feature",
  "properties": {
    "iso:country":"GB",
    "sg:address":"125 Bridge Street",
    "sg:city":"Birkenhead",
    "sg:classifiers":[
        {
            "category":"Professional",
            "subcategory":"Engineering",
            "type":"Services"
        }
    ],
    "sg:phone":"+44 151 647 4641",
    "sg:postcode":"CH41 1BD",
    "sg:province":"Merseyside",
    "wof:name":"Micro Metallic Ltd.",
    "wof:placetype":"venue"
},
  "geometry": {"coordinates":[-3.0180621147,53.3963623047],"type":"Point"}
}