{
  "type": "Feature",
  "properties": {
    "iso:country":"GB",
    "sg:address":"Horn House Lane, Briton Wood Industrial Estate",
    "sg:city":"Liverpool",
    "sg:classifiers":[
        {
            "category":"Wholesale",
            "subcategory":"Non-durable Goods",
            "type":"Manufacturing & Wholesale Goods"
        }
    ],
    "sg:phone":"+44 151 546 9211",
    "sg:postcode":"L33 7YQ",
    "sg:province":"Lancashire",
    "sg:tags":[
        "carry",
        "cash"
    ],
    "wof:name":"Makro Self Service Wholesalers Ltd.",
    "wof:placetype":"venue"
},
  "geometry": {"coordinates":[-2.8543999195,53.4698295593],"type":"Point"}
}