{
  "type": "Feature",
  "properties": {
    "iso:country":"GB",
    "sg:address":"119 Devons Rd",
    "sg:city":"Bow",
    "sg:classifiers":[
        {
            "category":"Retail",
            "subcategory":"Auto Repair",
            "type":"Services"
        }
    ],
    "sg:phone":"+44 20 7987 5680",
    "sg:postcode":"E3 3QX",
    "sg:province":"Greater London",
    "sg:tags":[
        "car",
        "specialist",
        "customizing"
    ],
    "wof:name":"J.P. Tyres",
    "wof:placetype":"venue"
},
  "geometry": {"coordinates":[-0.018929,51.521168],"type":"Point"}
}