{
  "type": "Feature",
  "properties": {
    "iso:country":"GB",
    "sg:address":"Bumpers Lane, Higher Ferry",
    "sg:city":"Chester",
    "sg:classifiers":[
        {
            "category":"Farming",
            "subcategory":"Dairy Farm",
            "type":"Manufacturing & Wholesale Goods"
        }
    ],
    "sg:phone":"+44 1244 377571",
    "sg:postcode":"CH1 6QE",
    "sg:province":"Cheshire",
    "sg:tags":[
        "farmer"
    ],
    "wof:name":"R W Littler",
    "wof:placetype":"venue"
},
  "geometry": {"coordinates":[-2.926359,53.185776],"type":"Point"}
}