{
  "type": "Feature",
  "properties": {
    "iso:country":"GB",
    "sg:address":"Tesco Distribution Centre, Southmead Industrial Park",
    "sg:city":"Didcot",
    "sg:classifiers":[
        {
            "category":"Retail",
            "subcategory":"Auto Repair",
            "type":"Services"
        }
    ],
    "sg:phone":"+44 1235 512202",
    "sg:postcode":"OX11 7HP",
    "sg:province":"Oxfordshire",
    "sg:tags":[
        "bodybuilder",
        "repairer"
    ],
    "wof:name":"City Transport Ltd.",
    "wof:placetype":"venue"
},
  "geometry": {"coordinates":[-1.232115,51.602383],"type":"Point"}
}