{
  "type": "Feature",
  "properties": {
    "iso:country":"GB",
    "sg:address":"Carnfield Hall Garden Centre, Carnfield Hill, South  Normanton",
    "sg:city":"Alfreton",
    "sg:classifiers":[
        {
            "category":"Home & Garden",
            "subcategory":"Furniture",
            "type":"Retail Goods"
        }
    ],
    "sg:phone":"+44 1773 520748",
    "sg:postcode":"DE55 2BE",
    "sg:province":"Derbyshire",
    "wof:name":"Carnfield Workshops",
    "wof:placetype":"venue"
},
  "geometry": {"coordinates":[-1.3367140293,53.1006698608],"type":"Point"}
}