{
  "type": "Feature",
  "properties": {
    "iso:country":"GB",
    "sg:address":"88 Elvet Bridge",
    "sg:city":"Durham",
    "sg:classifiers":[
        {
            "category":"Real Estate",
            "subcategory":"Real Estate Agent",
            "type":"Services"
        }
    ],
    "sg:phone":"+44 191 386 2777",
    "sg:postcode":"DH1 3AG",
    "sg:province":"Durham",
    "wof:name":"Robinson Clough & Kearns",
    "wof:placetype":"venue"
},
  "geometry": {"coordinates":[-1.572298,54.775673],"type":"Point"}
}