{
  "type": "Feature",
  "properties": {
    "iso:country":"GB",
    "sg:address":"Matchless Works, Foundry Lane",
    "sg:city":"Horsham",
    "sg:classifiers":[
        {
            "category":"Professional",
            "subcategory":"Accounting & Tax Preparation",
            "type":"Services"
        },
        {
            "category":"Professional",
            "subcategory":"Engineering",
            "type":"Services"
        }
    ],
    "sg:phone":"+44 1403 260271",
    "sg:postcode":"RH13 5PX",
    "sg:province":"West Sussex",
    "sg:tags":[
        "payroll",
        "engineer"
    ],
    "wof:name":"Vaultland Engineering",
    "wof:placetype":"venue"
},
  "geometry": {"coordinates":[-0.31544,51.071388],"type":"Point"}
}