{
  "type": "Feature",
  "properties": {
    "iso:country":"GB",
    "sg:address":"Kirkby Lonsdale Casterton",
    "sg:city":"Carnforth",
    "sg:classifiers":[
        {
            "category":"Education",
            "subcategory":"School",
            "type":"Public Place"
        }
    ],
    "sg:postcode":"LA6 2SG",
    "sg:province":"Cumbria",
    "sg:tags":[
        "independent",
        "preparatory"
    ],
    "wof:name":"Casterton School",
    "wof:placetype":"venue"
},
  "geometry": {"coordinates":[-2.578715086,54.2107772827],"type":"Point"}
}