{
  "type": "Feature",
  "properties": {
    "iso:country":"GB",
    "sg:address":"Unit C Albion Yard, Balfe Street",
    "sg:city":"London",
    "sg:classifiers":[
        {
            "category":"Manufacturing",
            "subcategory":"Signs",
            "type":"Manufacturing & Wholesale Goods"
        }
    ],
    "sg:phone":"+44 20 7278 1414",
    "sg:postcode":"N1 9ED",
    "sg:province":"Greater London",
    "sg:tags":[
        "nameplate"
    ],
    "wof:name":"6666 Designer Services",
    "wof:placetype":"venue"
},
  "geometry": {"coordinates":[-0.1211740002,51.5324211121],"type":"Point"}
}