{
  "type": "Feature",
  "properties": {
    "addr:full":"108 Fetter Lane London Greater London EC4A 1ES",
    "addr:housenumber":"108",
    "addr:postcode":"ec4a 1es",
    "addr:street":"Fetter Lane",
    "iso:country":"GB",
    "sg:address":"108 Fetter Lane",
    "sg:city":"London",
    "sg:classifiers":[
        {
            "category":"Bars & Pubs",
            "type":"Food & Drink"
        }
    ],
    "sg:postcode":"EC4A 1ES",
    "sg:province":"Greater London",
    "sg:tags":[
        "pubs",
        "inn"
    ],
    "wof:name":"The Mucky Duck",
    "wof:placetype":"venue"
},
  "geometry": {"coordinates":[-0.1091089994,51.5168304443],"type":"Point"}
}