{
  "type": "Feature",
  "properties": {
    "iso:country":"GB",
    "sg:address":"31 Victoria Lane",
    "sg:city":"Hayes",
    "sg:classifiers":[
        {
            "category":"Retail",
            "subcategory":"Driving School",
            "type":"Services"
        }
    ],
    "sg:phone":"+44 20 8897 1743",
    "sg:postcode":"UB3 5EW",
    "sg:province":"Greater London",
    "wof:name":"Hudson School of Motoring",
    "wof:placetype":"venue"
},
  "geometry": {"coordinates":[-0.438098,51.490784],"type":"Point"}
}