{
  "type": "Feature",
  "properties": {
    "iso:country":"GB",
    "sg:address":"167-170 Abbey Foregate",
    "sg:city":"Shrewsbury",
    "sg:classifiers":[
        {
            "category":"Autos & Motor Vehicles",
            "subcategory":"Auto Supplies",
            "type":"Retail Goods"
        }
    ],
    "sg:phone":"+44 1743 352626",
    "sg:postcode":"SY2 6AH",
    "sg:province":"Shropshire",
    "sg:tags":[
        "exhaust",
        "absorber",
        "shock"
    ],
    "wof:name":"Kwik-Fit",
    "wof:placetype":"venue"
},
  "geometry": {"coordinates":[-2.7406458855,52.7067146301],"type":"Point"}
}