{
  "type": "Feature",
  "properties": {
    "iso:country":"GB",
    "sg:address":"32 Main St",
    "sg:city":"Egremont",
    "sg:classifiers":[
        {
            "category":"Food & Beverages",
            "subcategory":"Fruits & Vegetables",
            "type":"Retail Goods"
        }
    ],
    "sg:postcode":"CA22 2DR",
    "sg:province":"Cumbria",
    "sg:tags":[
        "greengrocer"
    ],
    "wof:name":"R & S Pascoe",
    "wof:placetype":"venue"
},
  "geometry": {"coordinates":[-3.5281219482,54.4826316833],"type":"Point"}
}