{
  "type": "Feature",
  "properties": {
    "addr:full":"2 Carment Drive Glasgow Glasgow City G41 3PP",
    "addr:housenumber":"2",
    "addr:postcode":"g41 3pp",
    "addr:street":"Carment Drive",
    "iso:country":"GB",
    "sg:address":"2 Carment Drive",
    "sg:city":"Glasgow",
    "sg:classifiers":[
        {
            "category":"Professional",
            "subcategory":"Lawyer & Legal Services",
            "type":"Services"
        }
    ],
    "sg:phone":"+44 141 649 5682",
    "sg:postcode":"G41 3PP",
    "sg:province":"Glasgow City",
    "sg:tags":[
        "solicitor"
    ],
    "wof:name":"Furst Cyril & Co",
    "wof:placetype":"venue"
},
  "geometry": {"coordinates":[-4.2860841751,55.8266487122],"type":"Point"}
}