{
  "type": "Feature",
  "properties": {
    "addr:full":"Lidsey Rd, Woodgate Chichester West Sussex PO20 6ST",
    "addr:postcode":"po20 6st",
    "addr:street":"Lidsey Rd Woodgate",
    "iso:country":"GB",
    "sg:address":"Lidsey Rd, Woodgate",
    "sg:city":"Chichester",
    "sg:classifiers":[
        {
            "category":"Retail",
            "subcategory":"Auto Repair",
            "type":"Services"
        }
    ],
    "sg:postcode":"PO20 6ST",
    "sg:province":"West Sussex",
    "sg:tags":[
        "car",
        "upholsterer"
    ],
    "wof:name":"Merrimans Vintage & Classic Car Trimmers",
    "wof:placetype":"venue"
},
  "geometry": {"coordinates":[-0.66947,50.828209],"type":"Point"}
}