{
  "type": "Feature",
  "properties": {
    "iso:country":"GB",
    "sg:address":"2 Laurels Clo, Eynesbury",
    "sg:city":"Huntingdon",
    "sg:classifiers":[
        {
            "category":"Professional",
            "subcategory":"Lawyer & Legal Services",
            "type":"Services"
        }
    ],
    "sg:phone":"+44 1480 219400",
    "sg:postcode":"PE19 2HZ",
    "sg:province":"Bedfordshire",
    "sg:tags":[
        "advice",
        "counselling"
    ],
    "wof:name":"Huntingdon Counselling Consultancy",
    "wof:placetype":"venue"
},
  "geometry": {"coordinates":[-0.263569,52.2216],"type":"Point"}
}