{
  "type": "Feature",
  "properties": {
    "iso:country":"GB",
    "sg:address":"Unit 14 Colliery Lane, Exhall",
    "sg:city":"Coventry",
    "sg:classifiers":[
        {
            "category":"Wholesale",
            "subcategory":"Photographic Equipment",
            "type":"Manufacturing & Wholesale Goods"
        }
    ],
    "sg:postcode":"CV7 9NW",
    "sg:province":"Warwickshire",
    "sg:tags":[
        "w'sale"
    ],
    "wof:name":"Manni Batterjee",
    "wof:placetype":"venue"
},
  "geometry": {"coordinates":[-1.4750939608,52.4722709656],"type":"Point"}
}