{
  "type": "Feature",
  "properties": {
    "addr:full":"Middlebarrow Quarry Carnforth Cumbria LA5 0UH",
    "addr:postcode":"la5 0uh",
    "addr:street":"Middlebarrow Quarry",
    "iso:country":"GB",
    "sg:address":"Middlebarrow Quarry",
    "sg:city":"Carnforth",
    "sg:classifiers":[
        {
            "category":"Manufacturing",
            "subcategory":"Glass & Minerals",
            "type":"Manufacturing & Wholesale Goods"
        }
    ],
    "sg:phone":"+44 1524 701375",
    "sg:postcode":"LA5 0UH",
    "sg:province":"Cumbria",
    "sg:tags":[
        "chalk",
        "stone",
        "slate"
    ],
    "wof:name":"ARC Northern",
    "wof:placetype":"venue"
},
  "geometry": {"coordinates":[-2.7680590153,54.1284790039],"type":"Point"}
}