{
  "type": "Feature",
  "properties": {
    "addr:full":"15-15a Breck Road Poulton-le-fylde Lancashire FY6 7AA",
    "addr:housenumber":"15-15a",
    "addr:postcode":"fy6 7aa",
    "addr:street":"Breck Road Poulton-Le-Fylde",
    "iso:country":"GB",
    "sg:address":"15-15a Breck Road",
    "sg:city":"Poulton-le-fylde",
    "sg:classifiers":[
        {
            "category":"Real Estate",
            "subcategory":"Real Estate Agent",
            "type":"Services"
        }
    ],
    "sg:phone":"+44 1253 894445",
    "sg:postcode":"FY6 7AA",
    "sg:province":"Lancashire",
    "wof:name":"Halifax Property Services",
    "wof:placetype":"venue"
},
  "geometry": {"coordinates":[-2.991568,53.848015],"type":"Point"}
}