{
  "type": "Feature",
  "properties": {
    "addr:full":"Suite 11 Chester Park, Alfreton Rd Derby Derbyshire DE21 4AS",
    "addr:housenumber":"11",
    "addr:postcode":"de21 4as",
    "addr:street":"Suite;Chester Park Alfreton Rd",
    "iso:country":"GB",
    "sg:address":"Suite 11 Chester Park, Alfreton Rd",
    "sg:city":"Derby",
    "sg:classifiers":[
        {
            "category":"Professional",
            "subcategory":"Engineering",
            "type":"Services"
        }
    ],
    "sg:phone":"+44 1332 344084",
    "sg:postcode":"DE21 4AS",
    "sg:province":"Derbyshire",
    "sg:tags":[
        "contractor",
        "electrical",
        "engineer"
    ],
    "wof:name":"C & M Engineering",
    "wof:placetype":"venue"
},
  "geometry": {"coordinates":[-1.47088,52.934811],"type":"Point"}
}