{
  "type": "Feature",
  "properties": {
    "addr:full":"Community Transport Building, Erskine Rd Rotherham South Yorkshire S65 1RF",
    "addr:postcode":"s65 1rf",
    "addr:street":"Erskine Rd",
    "iso:country":"GB",
    "sg:address":"Community Transport Building, Erskine Rd",
    "sg:city":"Rotherham",
    "sg:classifiers":[
        {
            "category":"Organizations",
            "subcategory":"Non-profit Organization",
            "type":"Services"
        }
    ],
    "sg:phone":"+44 1709 835525",
    "sg:postcode":"S65 1RF",
    "sg:province":"South Yorkshire",
    "sg:tags":[
        "organisation",
        "voluntary",
        "charity"
    ],
    "wof:name":"Rotherham Crime Reduction Programme",
    "wof:placetype":"venue"
},
  "geometry": {"coordinates":[-1.35055,53.438358],"type":"Point"}
}