{
  "type": "Feature",
  "properties": {
    "addr:full":"2 Brynawel, Coed Y Felin Road, Brymbo Wrexham Wrexham LL11 5DP",
    "addr:housenumber":"2",
    "addr:postcode":"ll11 5dp",
    "addr:street":"Brynawel Coed Y Felin Road",
    "iso:country":"GB",
    "sg:address":"2 Brynawel, Coed Y Felin Road, Brymbo",
    "sg:city":"Wrexham",
    "sg:classifiers":[
        {
            "category":"Utilities",
            "subcategory":"Fuel Oil & Lpg",
            "type":"Services"
        }
    ],
    "sg:postcode":"LL11 5DP",
    "sg:province":"Wrexham",
    "sg:tags":[
        "coal",
        "smokeless"
    ],
    "wof:name":"A Green Coal Merchants",
    "wof:placetype":"venue"
},
  "geometry": {"coordinates":[-3.0516140461,53.0783615112],"type":"Point"}
}