{
  "type": "Feature",
  "properties": {
    "addr:full":"271 Willesden Lane London Greater London NW2 5JG",
    "addr:housenumber":"271",
    "addr:postcode":"nw2 5jg",
    "addr:street":"Willesden Lane",
    "iso:country":"GB",
    "sg:address":"271 Willesden Lane",
    "sg:city":"London",
    "sg:classifiers":[
        {
            "category":"Real Estate",
            "subcategory":"Developer",
            "type":"Services"
        }
    ],
    "sg:phone":"+44 20 8459 3826",
    "sg:postcode":"NW2 5JG",
    "sg:province":"Greater London",
    "sg:tags":[
        "property"
    ],
    "wof:name":"Rosscourt Group of Companies",
    "wof:placetype":"venue"
},
  "geometry": {"coordinates":[-0.221592,51.546841],"type":"Point"}
}