{
  "type": "Feature",
  "properties": {
    "addr:full":"2 Mitchell Road Poole Dorset BH17 8US",
    "addr:housenumber":"2",
    "addr:postcode":"bh17 8us",
    "addr:street":"Mitchell Road",
    "iso:country":"GB",
    "sg:address":"2 Mitchell Road",
    "sg:city":"Poole",
    "sg:classifiers":[
        {
            "category":"Organizations",
            "subcategory":"Non-profit Organization",
            "type":"Services"
        }
    ],
    "sg:phone":"+44 1202 667183",
    "sg:postcode":"BH17 8US",
    "sg:province":"Dorset",
    "sg:tags":[
        "organisation",
        "voluntary",
        "charity"
    ],
    "wof:name":"Day Centres for Older People",
    "wof:placetype":"venue"
},
  "geometry": {"coordinates":[-1.962473,50.741955],"type":"Point"}
}