{
  "type": "Feature",
  "properties": {
    "iso:country":"GB",
    "sg:address":"49 Well Street",
    "sg:city":"Exeter",
    "sg:classifiers":[
        {
            "category":"Food & Beverages",
            "subcategory":"Liquor & Beverages",
            "type":"Retail Goods"
        }
    ],
    "sg:postcode":"EX4 6QA",
    "sg:province":"Devon",
    "sg:tags":[
        "beer",
        "wine",
        "spirit",
        "wines"
    ],
    "wof:name":"THE LIONS HOLT OFF LICENCE",
    "wof:placetype":"venue"
},
  "geometry": {"coordinates":[-3.52206,50.731537],"type":"Point"}
}