{
  "type": "Feature",
  "properties": {
    "addr:full":"27 Covert Road, Sharston, Wythenshawe Manchester Greater Manchester M22 4QS",
    "addr:housenumber":"27",
    "addr:postcode":"m22 4qs",
    "addr:street":"Covert Road Sharston",
    "iso:country":"GB",
    "sg:address":"27 Covert Road, Sharston, Wythenshawe",
    "sg:city":"Manchester",
    "sg:classifiers":[
        {
            "category":"Building & Trades",
            "subcategory":"Cleaning & Sanitation",
            "type":"Services"
        }
    ],
    "sg:postcode":"M22 4QS",
    "sg:province":"Greater Manchester",
    "sg:tags":[
        "cleaner",
        "window"
    ],
    "wof:name":"Immediate Window Cleaning",
    "wof:placetype":"venue"
},
  "geometry": {"coordinates":[-2.2500879765,53.3884239197],"type":"Point"}
}