{
  "type": "Feature",
  "properties": {
    "iso:country":"GB",
    "sg:address":", Bentworth",
    "sg:city":"Alton",
    "sg:classifiers":[
        {
            "category":"Bars & Pubs",
            "type":"Food & Drink"
        }
    ],
    "sg:phone":"+44 1420 562338",
    "sg:postcode":"GU34 5JT",
    "sg:province":"Hampshire",
    "sg:tags":[
        "pubs",
        "inn"
    ],
    "wof:name":"The Sun Inn",
    "wof:placetype":"venue"
},
  "geometry": {"coordinates":[-1.046129,51.117802],"type":"Point"}
}