{
  "type": "Feature",
  "properties": {
    "addr:full":", Bentworth Alton Hampshire GU34 5JT",
    "addr:housenumber":"bentworth",
    "addr:postcode":"gu34 5jt",
    "addr:street":"Alton Hampshire",
    "iso:country":"GB",
    "sg:address":", Bentworth",
    "sg:city":"Alton",
    "sg:classifiers":[
        {
            "category":"Bars & Pubs",
            "type":"Food & Drink"
        }
    ],
    "sg:phone":"+44 1420 562338",
    "sg:postcode":"GU34 5JT",
    "sg:province":"Hampshire",
    "sg:tags":[
        "pubs",
        "inn"
    ],
    "wof:name":"The Sun Inn",
    "wof:placetype":"venue"
},
  "geometry": {"coordinates":[-1.046129,51.117802],"type":"Point"}
}