{
  "type": "Feature",
  "properties": {
    "addr:full":"Unit 16 Crondal Road, Bayton Road Industrial Estate, Exhall Coventry Warwickshire CV7 9EL",
    "addr:housenumber":"unit 16",
    "addr:postcode":"cv7 9el",
    "addr:street":"Crondal Road Bayton Road Industrial Estate",
    "iso:country":"GB",
    "sg:address":"Unit 16 Crondal Road, Bayton Road Industrial Estate, Exhall",
    "sg:city":"Coventry",
    "sg:classifiers":[
        {
            "category":"Wholesale",
            "subcategory":"Auto Parts",
            "type":"Manufacturing & Wholesale Goods"
        }
    ],
    "sg:phone":"+44 24 7664 4311",
    "sg:postcode":"CV7 9EL",
    "sg:province":"Warwickshire",
    "sg:tags":[
        "wholesaler",
        "tyre"
    ],
    "wof:name":"Summit Tyres (U K) Ltd.",
    "wof:placetype":"venue"
},
  "geometry": {"coordinates":[-1.476188,52.465916],"type":"Point"}
}