{
  "type": "Feature",
  "properties": {
    "iso:country":"GB",
    "sg:address":"Green Lane, Aston",
    "sg:city":"Sheffield",
    "sg:classifiers":[
        {
            "category":"Arena",
            "subcategory":"Sports Club",
            "type":"Entertainment"
        }
    ],
    "sg:phone":"+44 114 287 3000",
    "sg:postcode":"S26 2BD",
    "sg:province":"South Yorkshire",
    "wof:name":"Aston Hall Cricket Club",
    "wof:placetype":"venue"
},
  "geometry": {"coordinates":[-1.293974,53.363045],"type":"Point"}
}