{
  "type": "Feature",
  "properties": {
    "addr:full":"41 Commercial Street Camborne Cornwall TR14 8JX",
    "addr:housenumber":"41",
    "addr:postcode":"tr14 8jx",
    "addr:street":"Commercial Street",
    "iso:country":"GB",
    "sg:address":"41 Commercial Street",
    "sg:city":"Camborne",
    "sg:classifiers":[
        {
            "category":"Shopping",
            "subcategory":"Photographic Equipment",
            "type":"Retail Goods"
        }
    ],
    "sg:phone":"+44 1209 716261",
    "sg:postcode":"TR14 8JX",
    "sg:province":"Cornwall",
    "sg:tags":[
        "supply"
    ],
    "wof:name":"Bowie-Castlebank Ltd.",
    "wof:placetype":"venue"
},
  "geometry": {"coordinates":[-5.3004260063,50.213924408],"type":"Point"}
}