{
  "type": "Feature",
  "properties": {
    "addr:full":"126 Strathayr Place Ayr South Ayrshire KA8 0AY",
    "addr:housenumber":"126",
    "addr:postcode":"ka8 0ay",
    "addr:street":"Strathayr Place",
    "iso:country":"GB",
    "sg:address":"126 Strathayr Place",
    "sg:city":"Ayr",
    "sg:classifiers":[
        {
            "category":"Building & Trades",
            "subcategory":"Construction",
            "type":"Services"
        }
    ],
    "sg:phone":"+44 1292 268306",
    "sg:postcode":"KA8 0AY",
    "sg:province":"South Ayrshire",
    "sg:tags":[
        "roofing",
        "contracting"
    ],
    "wof:name":"J G L Roofing Ltd.",
    "wof:placetype":"venue"
},
  "geometry": {"coordinates":[-4.6258649826,55.4632072449],"type":"Point"}
}