{
  "type": "Feature",
  "properties": {
    "iso:country":"GB",
    "sg:address":"31 Rowan Drive, Ponteland",
    "sg:city":"Newcastle-upon-tyne",
    "sg:classifiers":[
        {
            "category":"Building & Trades",
            "subcategory":"Construction",
            "type":"Services"
        }
    ],
    "sg:postcode":"NE20 9QJ",
    "sg:province":"Northumberland",
    "sg:tags":[
        "builder"
    ],
    "wof:name":"J S & J Renton",
    "wof:placetype":"venue"
},
  "geometry": {"coordinates":[-1.744083,55.055088],"type":"Point"}
}