{
  "type": "Feature",
  "properties": {
    "addr:full":"Dumballs Road Cardiff Cardiff CF10 5FE",
    "addr:postcode":"cf10 5fe",
    "addr:street":"Dumballs Road",
    "iso:country":"GB",
    "sg:address":"Dumballs Road",
    "sg:city":"Cardiff",
    "sg:classifiers":[
        {
            "category":"Wholesale",
            "subcategory":"Machinery & Supplies",
            "type":"Manufacturing & Wholesale Goods"
        }
    ],
    "sg:phone":"+44 29 2048 1616",
    "sg:postcode":"CF10 5FE",
    "sg:province":"Cardiff",
    "sg:tags":[
        "hydraulic"
    ],
    "wof:name":"Transport Hydraulics Ltd.",
    "wof:placetype":"venue"
},
  "geometry": {"coordinates":[-3.176189,51.472481],"type":"Point"}
}