{
  "type": "Feature",
  "properties": {
    "iso:country":"GB",
    "sg:address":"16 Ellesmere Road, Ashton In Makerfield",
    "sg:city":"Wigan",
    "sg:classifiers":[
        {
            "category":"Professional",
            "subcategory":"Engineering",
            "type":"Services"
        }
    ],
    "sg:phone":"+44 1942 201167",
    "sg:postcode":"WN4 9RR",
    "sg:province":"Lancashire",
    "sg:tags":[
        "contractor",
        "electrical",
        "engineer"
    ],
    "wof:name":"Eric Hardman Electrical Contractor",
    "wof:placetype":"venue"
},
  "geometry": {"coordinates":[-2.652508,53.49411],"type":"Point"}
}