{
  "type": "Feature",
  "properties": {
    "iso:country":"GB",
    "sg:address":"3 Raymond Rd",
    "sg:city":"Maidenhead",
    "sg:classifiers":[
        {
            "category":"Mining & Drilling",
            "type":"Manufacturing & Wholesale Goods"
        }
    ],
    "sg:phone":"+44 1628 777147",
    "sg:postcode":"SL6 6DF",
    "sg:province":"Berkshire",
    "sg:tags":[
        "contractor"
    ],
    "wof:name":"Advanced Concrete Drilling Services",
    "wof:placetype":"venue"
},
  "geometry": {"coordinates":[-0.735008,51.52301],"type":"Point"}
}