{
  "type": "Feature",
  "properties": {
    "iso:country":"GB",
    "sg:address":"25 St Georges Terrace",
    "sg:city":"Plymouth",
    "sg:classifiers":[
        {
            "category":"Food & Beverages",
            "subcategory":"Liquor & Beverages",
            "type":"Retail Goods"
        }
    ],
    "sg:postcode":"PL2 1HS",
    "sg:province":"Devon",
    "sg:tags":[
        "beer",
        "spirit",
        "wines"
    ],
    "wof:name":"Londis Cheers",
    "wof:placetype":"venue"
},
  "geometry": {"coordinates":[-4.168755,50.383339],"type":"Point"}
}