{
  "type": "Feature",
  "properties": {
    "addr:full":"621 Halifax Road, Hurstead Rochdale Lancashire OL12 9PY",
    "addr:housenumber":"621",
    "addr:postcode":"ol12 9py",
    "addr:street":"Halifax Road",
    "iso:country":"GB",
    "sg:address":"621 Halifax Road, Hurstead",
    "sg:city":"Rochdale",
    "sg:classifiers":[
        {
            "category":"Fast Food",
            "type":"Food & Drink"
        }
    ],
    "sg:phone":"+44 1706 379007",
    "sg:postcode":"OL12 9PY",
    "sg:province":"Lancashire",
    "sg:tags":[
        "away",
        "take"
    ],
    "wof:name":"Chop Suey House",
    "wof:placetype":"venue"
},
  "geometry": {"coordinates":[-2.125246048,53.6365890503],"type":"Point"}
}