{
  "type": "Feature",
  "properties": {
    "addr:full":"1 Paper Buildings, Temple London Greater London EC4Y 7EP",
    "addr:housenumber":"1",
    "addr:postcode":"ec4y 7ep",
    "iso:country":"GB",
    "sg:address":"1 Paper Buildings, Temple",
    "sg:city":"London",
    "sg:classifiers":[
        {
            "category":"Professional",
            "subcategory":"Lawyer & Legal Services",
            "type":"Services"
        }
    ],
    "sg:phone":"+44 20 7353 3728",
    "sg:postcode":"EC4Y 7EP",
    "sg:province":"Greater London",
    "sg:tags":[
        "barrister"
    ],
    "wof:name":"Anthony Davies",
    "wof:placetype":"venue"
},
  "geometry": {"coordinates":[-0.109089002,51.5120391846],"type":"Point"}
}