{
  "type": "Feature",
  "properties": {
    "iso:country":"GB",
    "sg:address":"38 Greenham Drive",
    "sg:city":"Seaview",
    "sg:classifiers":[
        {
            "category":"Wholesale",
            "subcategory":"Toys & Hobbies",
            "type":"Manufacturing & Wholesale Goods"
        }
    ],
    "sg:phone":"+44 1983 612704",
    "sg:postcode":"PO34 5LD",
    "sg:province":"Isle of Wight",
    "sg:tags":[
        "balloon",
        "novelty"
    ],
    "wof:name":"Helie Balloons",
    "wof:placetype":"venue"
},
  "geometry": {"coordinates":[-1.112566,50.711666],"type":"Point"}
}