{
  "type": "Feature",
  "properties": {
    "addr:full":"Flat 81 Osprey Court, Osprey Close Manchester Cheshire M15 5QB",
    "addr:housenumber":"flat 81",
    "addr:postcode":"m15 5qb",
    "addr:street":"Osprey Court Osprey Close",
    "iso:country":"GB",
    "sg:address":"Flat 81 Osprey Court, Osprey Close",
    "sg:city":"Manchester",
    "sg:classifiers":[
        {
            "category":"Building & Trades",
            "subcategory":"Construction",
            "type":"Services"
        }
    ],
    "sg:postcode":"M15 5QB",
    "sg:province":"Cheshire",
    "sg:tags":[
        "builder"
    ],
    "wof:name":"Kenmure Ltd",
    "wof:placetype":"venue"
},
  "geometry": {"coordinates":[-2.250549,53.467106],"type":"Point"}
}