{
  "type": "Feature",
  "properties": {
    "addr:full":"7 Kings Court, Pateley Bridge Harrogate North Yorkshire HG3 5JW",
    "addr:housenumber":"7",
    "addr:postcode":"hg3 5jw",
    "addr:street":"Kings Court",
    "iso:country":"GB",
    "sg:address":"7 Kings Court, Pateley Bridge",
    "sg:city":"Harrogate",
    "sg:classifiers":[
        {
            "category":"Social Services",
            "subcategory":"Job Training",
            "type":"Services"
        },
        {
            "category":"Recreation",
            "type":"Entertainment"
        }
    ],
    "sg:phone":"+44 1423 711044",
    "sg:postcode":"HG3 5JW",
    "sg:province":"North Yorkshire",
    "sg:tags":[
        "corporate",
        "leisure",
        "provider"
    ],
    "wof:name":"Log Heights Ltd.",
    "wof:placetype":"venue"
},
  "geometry": {"coordinates":[-1.7610789537,54.0868759155],"type":"Point"}
}