{
  "type": "Feature",
  "properties": {
    "addr:full":"Station Rd, Boldon Boldon Colliery Tyne and Wear NE35 9HP",
    "addr:postcode":"ne35 9hp",
    "addr:street":"Station Rd",
    "iso:country":"GB",
    "sg:address":"Station Rd, Boldon",
    "sg:city":"Boldon Colliery",
    "sg:classifiers":[
        {
            "category":"Government",
            "subcategory":"Post Office",
            "type":"Public Place"
        }
    ],
    "sg:phone":"+44 191 536 7343",
    "sg:postcode":"NE35 9HP",
    "sg:province":"Tyne and Wear",
    "wof:name":"Station Road P.O",
    "wof:placetype":"venue"
},
  "geometry": {"coordinates":[-1.4671299458,54.9573898315],"type":"Point"}
}