{
  "type": "Feature",
  "properties": {
    "iso:country":"GB",
    "sg:address":"Churchill House, Church St, Wellington",
    "sg:city":"Telford",
    "sg:classifiers":[
        {
            "category":"Travel",
            "subcategory":"Travel Agent",
            "type":"Entertainment"
        }
    ],
    "sg:phone":"+44 1952 254841",
    "sg:postcode":"TF1 1DU",
    "sg:province":"Shropshire",
    "wof:name":"Worldchoice Carlson",
    "wof:placetype":"venue"
},
  "geometry": {"coordinates":[-2.518519,52.703156],"type":"Point"}
}