{
  "type": "Feature",
  "properties": {
    "iso:country":"GB",
    "sg:address":"102 High St",
    "sg:city":"Wakefield",
    "sg:classifiers":[
        {
            "category":"Health Services",
            "subcategory":"Dentist",
            "type":"Services"
        }
    ],
    "sg:phone":"+44 1924 255437",
    "sg:postcode":"WF4 3EF",
    "sg:province":"West Yorkshire",
    "wof:name":"A Petersons",
    "wof:placetype":"venue"
},
  "geometry": {"coordinates":[-1.5285,53.641842],"type":"Point"}
}