{
  "type": "Feature",
  "properties": {
    "addr:full":"Lea Croft Wrexham Rd, Brindley Nantwich Cheshire CW5 8HY",
    "addr:postcode":"cw5 8hy",
    "addr:street":"Lea Croft Wrexham Rd",
    "iso:country":"GB",
    "sg:address":"Lea Croft Wrexham Rd, Brindley",
    "sg:city":"Nantwich",
    "sg:classifiers":[
        {
            "category":"Building & Trades",
            "subcategory":"Construction",
            "type":"Services"
        }
    ],
    "sg:phone":"+44 1270 524345",
    "sg:postcode":"CW5 8HY",
    "sg:province":"Cheshire",
    "sg:tags":[
        "joiner",
        "carpenter"
    ],
    "wof:name":"T.G Griffiths",
    "wof:placetype":"venue"
},
  "geometry": {"coordinates":[-2.6083099842,53.0759353638],"type":"Point"}
}