{
  "type": "Feature",
  "properties": {
    "iso:country":"GB",
    "sg:address":"31 Victoria Gdn(s), St Columb Road",
    "sg:city":"St Columb",
    "sg:classifiers":[
        {
            "category":"Retail",
            "subcategory":"Repair Shop",
            "type":"Services"
        }
    ],
    "sg:phone":"+44 1726 860505",
    "sg:postcode":"TR9 6QR",
    "sg:province":"Cornwall",
    "sg:tags":[
        "upholsterer"
    ],
    "wof:name":"T Birchall Upholstery",
    "wof:placetype":"venue"
},
  "geometry": {"coordinates":[-4.936884,50.43256],"type":"Point"}
}