{
  "type": "Feature",
  "properties": {
    "iso:country":"GB",
    "sg:address":"Crown Street",
    "sg:city":"Wolverhampton",
    "sg:classifiers":[
        {
            "category":"Cafe",
            "type":"Food & Drink"
        }
    ],
    "sg:postcode":"WV1 1PX",
    "sg:province":"West Midlands",
    "sg:tags":[
        "tea",
        "room"
    ],
    "wof:name":"Crown Cafe",
    "wof:placetype":"venue"
},
  "geometry": {"coordinates":[-2.124234,52.596725],"type":"Point"}
}