{
  "type": "Feature",
  "properties": {
    "addr:full":"Neville House, Marsh Road, Leagrave Luton Bedfordshire LU3 2RZ",
    "addr:postcode":"lu3 2rz",
    "addr:street":"Marsh Road",
    "iso:country":"GB",
    "sg:address":"Neville House, Marsh Road, Leagrave",
    "sg:city":"Luton",
    "sg:classifiers":[
        {
            "category":"Retail",
            "subcategory":"Funeral Services",
            "type":"Services"
        }
    ],
    "sg:phone":"+44 1582 490005",
    "sg:postcode":"LU3 2RZ",
    "sg:province":"Bedfordshire",
    "wof:name":"Neville Funeral Service Ltd.",
    "wof:placetype":"venue"
},
  "geometry": {"coordinates":[-0.457908988,51.9066925049],"type":"Point"}
}