{
  "type": "Feature",
  "properties": {
    "addr:full":"96 Belgrave Gate Leicester Leicestershire LE1 3GR",
    "addr:housenumber":"96",
    "addr:postcode":"le1 3gr",
    "addr:street":"Belgrave Gate",
    "iso:country":"GB",
    "sg:address":"96 Belgrave Gate",
    "sg:city":"Leicester",
    "sg:classifiers":[
        {
            "category":"Restaurant",
            "type":"Food & Drink"
        }
    ],
    "sg:phone":"+44 116 253 8559",
    "sg:postcode":"LE1 3GR",
    "sg:province":"Leicestershire",
    "wof:name":"Athletic Bar Cafe The",
    "wof:placetype":"venue"
},
  "geometry": {"coordinates":[-1.131147027,52.6393241882],"type":"Point"}
}