{
  "type": "Feature",
  "properties": {
    "iso:country":"GB",
    "sg:address":"69 Rocky Lane, Anfield",
    "sg:city":"Liverpool",
    "sg:classifiers":[
        {
            "category":"Shopping",
            "subcategory":"News",
            "type":"Retail Goods"
        }
    ],
    "sg:phone":"+44 151 260 0215",
    "sg:postcode":"L6 4BB",
    "sg:province":"Merseyside",
    "sg:tags":[
        "newsagent"
    ],
    "wof:name":"News General Store",
    "wof:placetype":"venue"
},
  "geometry": {"coordinates":[-2.943027,53.422447],"type":"Point"}
}