{
  "type": "Feature",
  "properties": {
    "iso:country":"GB",
    "sg:address":"Pant Y Llwydrew",
    "sg:city":"Kidwelly",
    "sg:classifiers":[
        {
            "category":"Farming",
            "subcategory":"Livestock Farm",
            "type":"Manufacturing & Wholesale Goods"
        }
    ],
    "sg:phone":"+44 1267 267336",
    "sg:postcode":"SA17 5AU",
    "sg:province":"Carmarthenshire",
    "sg:tags":[
        "others"
    ],
    "wof:name":"William A N Jones",
    "wof:placetype":"venue"
},
  "geometry": {"coordinates":[-4.303438,51.736519],"type":"Point"}
}