{
  "type": "Feature",
  "properties": {
    "addr:full":"10 Broadcroft Gro, Tingley Wakefield West Yorkshire WF3 1TU",
    "addr:housenumber":"10",
    "addr:postcode":"wf3 1tu",
    "addr:street":"Broadcroft Gro Tingley",
    "iso:country":"GB",
    "sg:address":"10 Broadcroft Gro, Tingley",
    "sg:city":"Wakefield",
    "sg:classifiers":[
        {
            "category":"Professional",
            "subcategory":"Accounting & Tax Preparation",
            "type":"Services"
        }
    ],
    "sg:postcode":"WF3 1TU",
    "sg:province":"West Yorkshire",
    "sg:tags":[
        "accountant"
    ],
    "wof:name":"Holder Chartered Accountant",
    "wof:placetype":"venue"
},
  "geometry": {"coordinates":[-1.5704590082,53.7248001099],"type":"Point"}
}