{
  "type": "Feature",
  "properties": {
    "iso:country":"GB",
    "sg:address":"Berryhill Farm",
    "sg:city":"Kelso",
    "sg:classifiers":[
        {
            "category":"Home & Garden",
            "subcategory":"Garden Supply",
            "type":"Retail Goods"
        },
        {
            "category":"Farming",
            "subcategory":"Farm",
            "type":"Manufacturing & Wholesale Goods"
        }
    ],
    "sg:phone":"+44 1573 224118",
    "sg:postcode":"TD5 7SX",
    "sg:province":"Scottish Borders",
    "sg:tags":[
        "mixed",
        "bulb",
        "crop",
        "grower"
    ],
    "wof:name":"W & A Rennie",
    "wof:placetype":"venue"
},
  "geometry": {"coordinates":[-2.433349,55.597576],"type":"Point"}
}