{
  "type": "Feature",
  "properties": {
    "iso:country":"GB",
    "sg:address":"Holden House, Chester Business Park",
    "sg:city":"Chester",
    "sg:classifiers":[
        {
            "category":"Professional",
            "type":"Services"
        }
    ],
    "sg:postcode":"CH4 9QU",
    "sg:province":"Cheshire",
    "sg:tags":[
        "leasing"
    ],
    "wof:name":"Primeday Ltd",
    "wof:placetype":"venue"
},
  "geometry": {"coordinates":[-2.906947,53.161064],"type":"Point"}
}