{
  "type": "Feature",
  "properties": {
    "addr:full":"Redstone House, Redstone Road Narberth Carmarthenshire SA67 7EX",
    "addr:postcode":"sa67 7ex",
    "addr:street":"Redstone Road",
    "iso:country":"GB",
    "sg:address":"Redstone House, Redstone Road",
    "sg:city":"Narberth",
    "sg:classifiers":[
        {
            "category":"Shopping",
            "subcategory":"Bicycles & Sporting Goods",
            "type":"Retail Goods"
        }
    ],
    "sg:phone":"+44 1834 861898",
    "sg:postcode":"SA67 7EX",
    "sg:province":"Carmarthenshire",
    "sg:tags":[
        "riding",
        "saddlery",
        "wear"
    ],
    "wof:name":"James the Saddler",
    "wof:placetype":"venue"
},
  "geometry": {"coordinates":[-4.7443089485,51.8111190796],"type":"Point"}
}