{
  "type": "Feature",
  "properties": {
    "addr:full":"9 Chapter Road, Kennington London Greater London SE17 3ES",
    "addr:housenumber":"9",
    "addr:postcode":"se17 3es",
    "addr:street":"Chapter Road",
    "iso:country":"GB",
    "sg:address":"9 Chapter Road, Kennington",
    "sg:city":"London",
    "sg:classifiers":[
        {
            "category":"Professional",
            "subcategory":"Business Services",
            "type":"Services"
        }
    ],
    "sg:postcode":"SE17 3ES",
    "sg:province":"Greater London",
    "sg:tags":[
        "hospitality",
        "corporate"
    ],
    "wof:name":"The House of Magic",
    "wof:placetype":"venue"
},
  "geometry": {"coordinates":[-0.1020390019,51.486492157],"type":"Point"}
}