{
  "type": "Feature",
  "properties": {
    "addr:full":"107 Humber Av South Ockendon Essex RM15 5JT",
    "addr:housenumber":"107",
    "addr:postcode":"rm15 5jt",
    "addr:street":"Humber Av South Ockendon",
    "iso:country":"GB",
    "sg:address":"107 Humber Av",
    "sg:city":"South Ockendon",
    "sg:classifiers":[
        {
            "category":"Health Services",
            "subcategory":"Dentist",
            "type":"Services"
        }
    ],
    "sg:phone":"+44 1708 853107",
    "sg:postcode":"RM15 5JT",
    "sg:province":"Essex",
    "wof:name":"Miss T J Steeples",
    "wof:placetype":"venue"
},
  "geometry": {"coordinates":[0.2723580003,51.50730896],"type":"Point"}
}