{
  "type": "Feature",
  "properties": {
    "addr:full":"12b Hampton Road Ilford Essex IG1 1PS",
    "addr:housenumber":"12b",
    "addr:postcode":"ig1 1ps",
    "addr:street":"Hampton Road",
    "iso:country":"GB",
    "sg:address":"12b Hampton Road",
    "sg:city":"Ilford",
    "sg:classifiers":[
        {
            "category":"Building & Trades",
            "subcategory":"Construction",
            "type":"Services"
        }
    ],
    "sg:phone":"+44 20 8478 9983",
    "sg:postcode":"IG1 1PS",
    "sg:province":"Essex",
    "sg:tags":[
        "erectors",
        "platform",
        "scaffold",
        "work",
        "scaffolding"
    ],
    "wof:name":"Hi-Line Scaffolding",
    "wof:placetype":"venue"
},
  "geometry": {"coordinates":[0.075275,51.551277],"type":"Point"}
}