{
  "type": "Feature",
  "properties": {
    "addr:full":"114 Colby Drive, Thurmaston Leicester Leicestershire LE4 8LA",
    "addr:housenumber":"114",
    "addr:postcode":"le4 8la",
    "addr:street":"Colby Drive",
    "iso:country":"GB",
    "sg:address":"114 Colby Drive, Thurmaston",
    "sg:city":"Leicester",
    "sg:classifiers":[
        {
            "category":"Building & Trades",
            "subcategory":"Construction",
            "type":"Services"
        }
    ],
    "sg:postcode":"LE4 8LA",
    "sg:province":"Leicestershire",
    "sg:tags":[
        "roofing"
    ],
    "wof:name":"Soar Valley Roofing",
    "wof:placetype":"venue"
},
  "geometry": {"coordinates":[-1.0835579634,52.6753807068],"type":"Point"}
}