{
  "type": "Feature",
  "properties": {
    "addr:full":"The Fruit Shop, Drummond Street, Comrie Crieff Perth and Kinross PH6 2DW",
    "addr:postcode":"ph6 2dw",
    "addr:street":"Drummond Street",
    "iso:country":"GB",
    "sg:address":"The Fruit Shop, Drummond Street, Comrie",
    "sg:city":"Crieff",
    "sg:classifiers":[
        {
            "category":"Food & Beverages",
            "subcategory":"Fruits & Vegetables",
            "type":"Retail Goods"
        }
    ],
    "sg:phone":"+44 1764 670224",
    "sg:postcode":"PH6 2DW",
    "sg:province":"Perth and Kinross",
    "sg:tags":[
        "greengrocer"
    ],
    "wof:name":"Arthur Payne Ltd.",
    "wof:placetype":"venue"
},
  "geometry": {"coordinates":[-3.985064,56.370964],"type":"Point"}
}