{
  "type": "Feature",
  "properties": {
    "addr:full":"Latherford Close, Four Ashes Industrial Estate Wolverhampton Staffordshire WV10 7DY",
    "addr:postcode":"wv10 7dy",
    "addr:street":"Latherford Close;Industrial Estate",
    "iso:country":"GB",
    "sg:address":"Latherford Close, Four Ashes Industrial Estate",
    "sg:city":"Wolverhampton",
    "sg:classifiers":[
        {
            "category":"Manufacturing",
            "subcategory":"Electronics",
            "type":"Manufacturing & Wholesale Goods"
        }
    ],
    "sg:phone":"+44 1902 791878",
    "sg:postcode":"WV10 7DY",
    "sg:province":"Staffordshire",
    "sg:tags":[
        "control",
        "component",
        "-",
        "electronic"
    ],
    "wof:name":"Pat Cti Services Ltd",
    "wof:placetype":"venue"
},
  "geometry": {"coordinates":[-2.1174991131,52.673084259],"type":"Point"}
}