{
  "type": "Feature",
  "properties": {
    "iso:country":"GB",
    "sg:address":"Haldon Pilch La",
    "sg:city":"Liverpool",
    "sg:classifiers":[
        {
            "category":"Health Services",
            "subcategory":"Doctor",
            "type":"Services"
        }
    ],
    "sg:postcode":"L14 0JE",
    "sg:province":"Merseyside",
    "sg:tags":[
        "practitioners"
    ],
    "wof:name":"Duckenfield,Dr F M,",
    "wof:placetype":"venue"
},
  "geometry": {"coordinates":[-2.978481,53.409775],"type":"Point"}
}