{
  "type": "Feature",
  "properties": {
    "addr:full":"5 High Street Crowborough East Sussex TN6 2QA",
    "addr:housenumber":"5",
    "addr:postcode":"tn6 2qa",
    "addr:street":"High Street",
    "iso:country":"GB",
    "sg:address":"5 High Street",
    "sg:city":"Crowborough",
    "sg:classifiers":[
        {
            "category":"Personal",
            "subcategory":"Shoe Repair & Shine",
            "type":"Services"
        },
        {
            "category":"Shopping",
            "subcategory":"Shoes",
            "type":"Retail Goods"
        }
    ],
    "sg:phone":"+44 1892 654984",
    "sg:postcode":"TN6 2QA",
    "sg:province":"East Sussex",
    "wof:name":"Guests Shoe Service Ltd.",
    "wof:placetype":"venue"
},
  "geometry": {"coordinates":[0.162103,51.060081],"type":"Point"}
}