{
  "type": "Feature",
  "properties": {
    "addr:full":"18 Park Rd Teddington Greater London TW11 0AQ",
    "addr:housenumber":"18",
    "addr:postcode":"tw11 0aq",
    "addr:street":"Park Rd",
    "iso:country":"GB",
    "sg:address":"18 Park Rd",
    "sg:city":"Teddington",
    "sg:classifiers":[
        {
            "category":"Government",
            "subcategory":"Police Station",
            "type":"Public Place"
        }
    ],
    "sg:phone":"+44 20 8943 9299",
    "sg:postcode":"TW11 0AQ",
    "sg:province":"Greater London",
    "sg:tags":[
        "support"
    ],
    "wof:name":"Metropolitan Police Service",
    "wof:placetype":"venue"
},
  "geometry": {"coordinates":[-0.334971,51.424763],"type":"Point"}
}