{
  "type": "Feature",
  "properties": {
    "addr:full":"147 Charlotte Way Liverpool Merseyside L1 1NA",
    "addr:housenumber":"147",
    "addr:postcode":"l1 1na",
    "addr:street":"Charlotte Way",
    "iso:country":"GB",
    "sg:address":"147 Charlotte Way",
    "sg:city":"Liverpool",
    "sg:classifiers":[
        {
            "category":"Sports & Exercise",
            "subcategory":"Sports Center",
            "type":"Entertainment"
        }
    ],
    "sg:phone":"+44 151 707 1800",
    "sg:postcode":"L1 1NA",
    "sg:province":"Merseyside",
    "sg:tags":[
        "shop",
        "good"
    ],
    "wof:name":"City Trainers",
    "wof:placetype":"venue"
},
  "geometry": {"coordinates":[-2.9805140495,53.4063911438],"type":"Point"}
}