{
  "type": "Feature",
  "properties": {
    "iso:country":"GB",
    "sg:address":"27 High Street",
    "sg:city":"Poole",
    "sg:classifiers":[
        {
            "category":"Shopping",
            "subcategory":"Music",
            "type":"Retail Goods"
        }
    ],
    "sg:phone":"+44 1202 660618",
    "sg:postcode":"BH15 1AB",
    "sg:province":"Dorset",
    "sg:tags":[
        "dvd",
        "record",
        "tape",
        "vinyl",
        "cd"
    ],
    "wof:name":"Boiler Room Records",
    "wof:placetype":"venue"
},
  "geometry": {"coordinates":[-1.987526,50.71312],"type":"Point"}
}