{
  "type": "Feature",
  "properties": {
    "addr:full":"New Hall, Landermere, Salt-le-soken Clacton On Sea Essex CO16 0NH",
    "addr:postcode":"co16 0nh",
    "addr:street":"Clacton;Sea",
    "iso:country":"GB",
    "sg:address":"New Hall, Landermere, Salt-le-soken",
    "sg:city":"Clacton On Sea",
    "sg:classifiers":[
        {
            "category":"Banks & Credit Unions",
            "subcategory":"Financial Services",
            "type":"Services"
        }
    ],
    "sg:phone":"+44 1255 862403",
    "sg:postcode":"CO16 0NH",
    "sg:province":"Essex",
    "sg:tags":[
        "consultant"
    ],
    "wof:name":"Trinity Research & Management",
    "wof:placetype":"venue"
},
  "geometry": {"coordinates":[1.1838200092,51.8646202087],"type":"Point"}
}