{
  "type": "Feature",
  "properties": {
    "iso:country":"GB",
    "sg:address":"Manor Farm, Thursford Road",
    "sg:city":"Fakenham",
    "sg:classifiers":[
        {
            "category":"Farming",
            "subcategory":"Livestock Farm",
            "type":"Manufacturing & Wholesale Goods"
        }
    ],
    "sg:postcode":"NR21 0JW",
    "sg:province":"Norfolk",
    "sg:tags":[
        "others"
    ],
    "wof:name":"W J F Ross Ltd.",
    "wof:placetype":"venue"
},
  "geometry": {"coordinates":[0.9387300014,52.8708343506],"type":"Point"}
}