{
  "type": "Feature",
  "properties": {
    "addr:full":"167 Waidshouse Road Nelson Lancashire BB9 0RR",
    "addr:housenumber":"167",
    "addr:postcode":"bb9 0rr",
    "addr:street":"Waidshouse Road",
    "iso:country":"GB",
    "sg:address":"167 Waidshouse Road",
    "sg:city":"Nelson",
    "sg:classifiers":[
        {
            "category":"Personal",
            "type":"Services"
        },
        {
            "category":"Professional",
            "subcategory":"Employment Agencies",
            "type":"Services"
        }
    ],
    "sg:phone":"+44 1282 694815",
    "sg:postcode":"BB9 0RR",
    "sg:province":"Lancashire",
    "sg:tags":[
        "introduction",
        "dating",
        "friendship"
    ],
    "wof:name":"Connect Singles Directory",
    "wof:placetype":"venue"
},
  "geometry": {"coordinates":[-2.2124409676,53.8265075684],"type":"Point"}
}