{
  "type": "Feature",
  "properties": {
    "iso:country":"GB",
    "sg:address":"The Workshop, Crossways Farm",
    "sg:city":"Yeovil",
    "sg:classifiers":[
        {
            "category":"Retail",
            "subcategory":"Auto Repair",
            "type":"Services"
        }
    ],
    "sg:postcode":"BA22 8AP",
    "sg:province":"Dorset",
    "sg:tags":[
        "modification",
        "garage"
    ],
    "wof:name":"N D Stevens Auto Repairs",
    "wof:placetype":"venue"
},
  "geometry": {"coordinates":[-2.649929,51.00452],"type":"Point"}
}