{
  "type": "Feature",
  "properties": {
    "addr:full":"Cheney Manor Road Swindon Wiltshire SN2 2PF",
    "addr:postcode":"sn2 2pf",
    "addr:street":"Manor Road",
    "iso:country":"GB",
    "sg:address":"Cheney Manor Road",
    "sg:city":"Swindon",
    "sg:classifiers":[
        {
            "category":"Bars & Pubs",
            "type":"Food & Drink"
        },
        {
            "category":"Community Center",
            "subcategory":"Social",
            "type":"Public Place"
        }
    ],
    "sg:phone":"+44 1793 522988",
    "sg:postcode":"SN2 2PF",
    "sg:province":"Wiltshire",
    "sg:tags":[
        "pubs",
        "house",
        "inn",
        "activity"
    ],
    "wof:name":"Rodbourne Arms",
    "wof:placetype":"venue"
},
  "geometry": {"coordinates":[-1.798893,51.581696],"type":"Point"}
}