{
  "type": "Feature",
  "properties": {
    "addr:full":"Back Dragon Avenue Harrogate North Yorkshire HG1 5DW",
    "addr:postcode":"hg1 5dw",
    "addr:street":"Avenue",
    "iso:country":"GB",
    "sg:address":"Back Dragon Avenue",
    "sg:city":"Harrogate",
    "sg:classifiers":[
        {
            "category":"Manufacturing",
            "subcategory":"Building Materials",
            "type":"Manufacturing & Wholesale Goods"
        }
    ],
    "sg:phone":"+44 1423 561416",
    "sg:postcode":"HG1 5DW",
    "sg:province":"North Yorkshire",
    "sg:tags":[
        "merchant",
        "builder"
    ],
    "wof:name":"INDEPENDENT BUILDERS & PLUMBERS MERCHANTS LTD",
    "wof:placetype":"venue"
},
  "geometry": {"coordinates":[-1.5354340076,53.995967865],"type":"Point"}
}