{
  "type": "Feature",
  "properties": {
    "addr:full":"Welford Road, Long Marston Stratford-upon-avon Warwickshire CV37 8RH",
    "addr:postcode":"cv37 8rh",
    "addr:street":"Welford Road",
    "iso:country":"GB",
    "sg:address":"Welford Road, Long Marston",
    "sg:city":"Stratford-upon-avon",
    "sg:classifiers":[
        {
            "category":"Travel",
            "subcategory":"Hotels & Motels",
            "type":"Entertainment"
        }
    ],
    "sg:phone":"+44 1789 721800",
    "sg:postcode":"CV37 8RH",
    "sg:province":"Warwickshire",
    "sg:tags":[
        "house",
        "guest"
    ],
    "wof:name":"The Grange",
    "wof:placetype":"venue"
},
  "geometry": {"coordinates":[-1.7763390541,52.139289856],"type":"Point"}
}