{
  "type": "Feature",
  "properties": {
    "addr:full":"40 Sturmer Close, Yate Bristol Gloucestershire BS37 5UR",
    "addr:housenumber":"40",
    "addr:postcode":"bs37 5ur",
    "addr:street":"Sturmer Close",
    "iso:country":"GB",
    "sg:address":"40 Sturmer Close, Yate",
    "sg:city":"Bristol",
    "sg:classifiers":[
        {
            "category":"Shopping",
            "subcategory":"Mobile Phones",
            "type":"Retail Goods"
        }
    ],
    "sg:postcode":"BS37 5UR",
    "sg:province":"Gloucestershire",
    "wof:name":"Telecoms Plus Ltd",
    "wof:placetype":"venue"
},
  "geometry": {"coordinates":[-2.416601,51.550194],"type":"Point"}
}