{
  "type": "Feature",
  "properties": {
    "addr:full":"7 Blair Parade, Moredon Road Swindon Wiltshire SN25 3DE",
    "addr:housenumber":"7",
    "addr:postcode":"sn25 3de",
    "addr:street":"Blair Parade Moredon Road",
    "iso:country":"GB",
    "sg:address":"7 Blair Parade, Moredon Road",
    "sg:city":"Swindon",
    "sg:classifiers":[
        {
            "category":"Food & Beverages",
            "subcategory":"Bakery",
            "type":"Retail Goods"
        }
    ],
    "sg:postcode":"SN25 3DE",
    "sg:province":"Wiltshire",
    "sg:tags":[
        "baker"
    ],
    "wof:name":"The Cakehole",
    "wof:placetype":"venue"
},
  "geometry": {"coordinates":[-1.7998930216,51.5830497742],"type":"Point"}
}