{
  "type": "Feature",
  "properties": {
    "iso:country":"GB",
    "sg:address":"Torside Cottage, Torside Level Crossing, Hadfield",
    "sg:city":"Glossop",
    "sg:classifiers":[
        {
            "category":"Transit Center",
            "subcategory":"Passenger",
            "type":"Transportation"
        }
    ],
    "sg:postcode":"SK13 1HY",
    "sg:province":"Derbyshire",
    "sg:tags":[
        "boarding",
        "kennel",
        "catteries"
    ],
    "wof:name":"Torside Boarding Kennels & Cattery",
    "wof:placetype":"venue"
},
  "geometry": {"coordinates":[-1.9803819656,53.4604301453],"type":"Point"}
}