{
  "type": "Feature",
  "properties": {
    "iso:country":"GB",
    "sg:address":"83-85 Wardour St",
    "sg:city":"West End",
    "sg:classifiers":[
        {
            "category":"Bars & Pubs",
            "type":"Food & Drink"
        }
    ],
    "sg:phone":"+44 20 7437 3490",
    "sg:postcode":"W1V 3TG",
    "sg:province":"Hampshire",
    "sg:tags":[
        "pubs",
        "inn"
    ],
    "wof:name":"The Bar",
    "wof:placetype":"venue"
},
  "geometry": {"coordinates":[-0.133395,51.512432],"type":"Point"}
}