{
  "type": "Feature",
  "properties": {
    "addr:full":"24 Sawyers Close Winchester Hampshire SO22 5JX",
    "addr:housenumber":"24",
    "addr:postcode":"so22 5jx",
    "addr:street":"Sawyers Close",
    "iso:country":"GB",
    "sg:address":"24 Sawyers Close",
    "sg:city":"Winchester",
    "sg:classifiers":[
        {
            "category":"Shopping",
            "subcategory":"Antiques",
            "type":"Retail Goods"
        }
    ],
    "sg:phone":"+44 1962 854748",
    "sg:postcode":"SO22 5JX",
    "sg:province":"Hampshire",
    "wof:name":"G T C Eyles",
    "wof:placetype":"venue"
},
  "geometry": {"coordinates":[-1.347269,51.071377],"type":"Point"}
}