{
  "type": "Feature",
  "properties": {
    "addr:full":"34 Prospect Road, Minster Ramsgate Kent CT12 4EG",
    "addr:housenumber":"34",
    "addr:postcode":"ct12 4eg",
    "addr:street":"Prospect Road;Ramsgate",
    "iso:country":"GB",
    "sg:address":"34 Prospect Road, Minster",
    "sg:city":"Ramsgate",
    "sg:classifiers":[
        {
            "category":"Banks & Credit Unions",
            "subcategory":"Bureau De Change",
            "type":"Services"
        }
    ],
    "sg:phone":"+44 1843 821499",
    "sg:postcode":"CT12 4EG",
    "sg:province":"Kent",
    "sg:tags":[
        "town",
        "consultant",
        "planning"
    ],
    "wof:name":"Town Planning Practice Ltd.",
    "wof:placetype":"venue"
},
  "geometry": {"coordinates":[1.308756,51.336651],"type":"Point"}
}