{
  "type": "Feature",
  "properties": {
    "iso:country":"GB",
    "sg:address":"2 Ross Close",
    "sg:city":"Exeter",
    "sg:classifiers":[
        {
            "category":"Banks & Credit Unions",
            "subcategory":"Financial Services",
            "type":"Services"
        }
    ],
    "sg:phone":"+44 1392 466450",
    "sg:postcode":"EX1 3UE",
    "sg:province":"Devon",
    "sg:tags":[
        "adviser"
    ],
    "wof:name":"S J Allcock & Co.",
    "wof:placetype":"venue"
},
  "geometry": {"coordinates":[-3.4624969959,50.7402534485],"type":"Point"}
}