{
  "type": "Feature",
  "properties": {
    "iso:country":"GB",
    "sg:address":"185 Bordesley Green East, Bordesley Green",
    "sg:city":"Birmingham",
    "sg:classifiers":[
        {
            "category":"Home & Garden",
            "subcategory":"Home Furnishings",
            "type":"Retail Goods"
        },
        {
            "category":"Home & Garden",
            "subcategory":"Furniture",
            "type":"Retail Goods"
        }
    ],
    "sg:postcode":"B9 5SR",
    "sg:province":"West Midlands",
    "sg:tags":[
        "soft",
        "sale"
    ],
    "wof:name":"D HASMI",
    "wof:placetype":"venue"
},
  "geometry": {"coordinates":[-1.824233,52.479733],"type":"Point"}
}