{
  "type": "Feature",
  "properties": {
    "addr:full":"9 Front Street, Acomb York North Yorkshire YO24 3BW",
    "addr:housenumber":"9",
    "addr:postcode":"yo24 3bw",
    "addr:street":"Front Street",
    "iso:country":"GB",
    "sg:address":"9 Front Street, Acomb",
    "sg:city":"York",
    "sg:classifiers":[
        {
            "category":"Food & Beverages",
            "subcategory":"Cheese",
            "type":"Retail Goods"
        },
        {
            "category":"Wholesale",
            "subcategory":"Groceries",
            "type":"Manufacturing & Wholesale Goods"
        }
    ],
    "sg:phone":"+44 1904 781986",
    "sg:postcode":"YO24 3BW",
    "sg:province":"North Yorkshire",
    "sg:tags":[
        "supplier",
        "drink",
        "catering"
    ],
    "wof:name":"Scoop Value",
    "wof:placetype":"venue"
},
  "geometry": {"coordinates":[-1.125922,53.955143],"type":"Point"}
}