{
  "type": "Feature",
  "properties": {
    "addr:full":"31 Durngate Street Dorchester Dorset DT1 1JP",
    "addr:housenumber":"31",
    "addr:postcode":"dt1 1jp",
    "addr:street":"Durngate Street",
    "iso:country":"GB",
    "sg:address":"31 Durngate Street",
    "sg:city":"Dorchester",
    "sg:classifiers":[
        {
            "category":"Professional",
            "subcategory":"Engineering",
            "type":"Services"
        }
    ],
    "sg:phone":"+44 1305 260191",
    "sg:postcode":"DT1 1JP",
    "sg:province":"Dorset",
    "sg:tags":[
        "consulting",
        "design",
        "engineer"
    ],
    "wof:name":"Malcolm Wright Partnership",
    "wof:placetype":"venue"
},
  "geometry": {"coordinates":[-2.433518,50.71476],"type":"Point"}
}