{
  "type": "Feature",
  "properties": {
    "addr:full":"21a Shuna Terrace, Soroba Oban Argyll and Bute PA34 4YE",
    "addr:housenumber":"21a",
    "addr:postcode":"pa34 4ye",
    "addr:street":"Shuna Terrace",
    "iso:country":"GB",
    "sg:address":"21a Shuna Terrace, Soroba",
    "sg:city":"Oban",
    "sg:classifiers":[
        {
            "category":"Health Services",
            "subcategory":"Health Practitioner",
            "type":"Services"
        }
    ],
    "sg:phone":"+44 1631 567419",
    "sg:postcode":"PA34 4YE",
    "sg:province":"Argyll and Bute",
    "sg:tags":[
        "hypnotherapists"
    ],
    "wof:name":"Kenneth Kaid Ahmed F.INST.HT",
    "wof:placetype":"venue"
},
  "geometry": {"coordinates":[-5.4636158943,56.4052391052],"type":"Point"}
}