{
  "type": "Feature",
  "properties": {
    "addr:full":"538 Kingsbury Road, Kingsbury London Greater London NW9 9HH",
    "addr:housenumber":"538",
    "addr:postcode":"nw9 9hh",
    "addr:street":"Kingsbury Road",
    "iso:country":"GB",
    "sg:address":"538 Kingsbury Road, Kingsbury",
    "sg:city":"London",
    "sg:classifiers":[
        {
            "category":"Food & Beverages",
            "subcategory":"Liquor & Beverages",
            "type":"Retail Goods"
        }
    ],
    "sg:phone":"+44 20 8206 1082",
    "sg:postcode":"NW9 9HH",
    "sg:province":"Greater London",
    "sg:tags":[
        "beer",
        "spirit",
        "wines"
    ],
    "wof:name":"Alpine Wines",
    "wof:placetype":"venue"
},
  "geometry": {"coordinates":[-0.277259,51.585735],"type":"Point"}
}