{
  "type": "Feature",
  "properties": {
    "addr:full":"62 Rosslyn Road, Bearsden Glasgow East Dunbartonshire G61 4DW",
    "addr:housenumber":"62",
    "addr:postcode":"g61 4dw",
    "addr:street":"Rosslyn Road",
    "iso:country":"GB",
    "sg:address":"62 Rosslyn Road, Bearsden",
    "sg:city":"Glasgow",
    "sg:classifiers":[
        {
            "category":"Retail",
            "subcategory":"Repair Shop",
            "type":"Services"
        }
    ],
    "sg:phone":"+44 141 942 4465",
    "sg:postcode":"G61 4DW",
    "sg:province":"East Dunbartonshire",
    "sg:tags":[
        "upholsterer"
    ],
    "wof:name":"Sinclair Upholstery",
    "wof:placetype":"venue"
},
  "geometry": {"coordinates":[-4.355238,55.923489],"type":"Point"}
}