{
  "type": "Feature",
  "properties": {
    "addr:full":"77 Chepstow Rd Bayswater Greater London W2 5QR",
    "addr:housenumber":"77",
    "addr:postcode":"w2 5qr",
    "addr:street":"Chepstow Rd",
    "iso:country":"GB",
    "sg:address":"77 Chepstow Rd",
    "sg:city":"Bayswater",
    "sg:classifiers":[
        {
            "category":"Freight",
            "type":"Transportation"
        }
    ],
    "sg:phone":"+44 20 7727 9462",
    "sg:postcode":"W2 5QR",
    "sg:province":"Greater London",
    "sg:tags":[
        "haulage",
        "road"
    ],
    "wof:name":"Roger W Pliszka Ltd",
    "wof:placetype":"venue"
},
  "geometry": {"coordinates":[-0.1943089962,51.5126991272],"type":"Point"}
}