{
  "type": "Feature",
  "properties": {
    "iso:country":"GB",
    "sg:address":"32 Drift Road, Clanfield",
    "sg:city":"Waterlooville",
    "sg:classifiers":[
        {
            "category":"Manufacturing",
            "subcategory":"Petroleum Products",
            "type":"Manufacturing & Wholesale Goods"
        }
    ],
    "sg:phone":"+44 23 9259 7575",
    "sg:postcode":"PO8 0UL",
    "sg:province":"Hampshire",
    "sg:tags":[
        "double",
        "glazing"
    ],
    "wof:name":"Profix Windows Ltd.",
    "wof:placetype":"venue"
},
  "geometry": {"coordinates":[-0.998992,50.935265],"type":"Point"}
}