{
  "type": "Feature",
  "properties": {
    "iso:country":"GB",
    "sg:address":"North Terminal Air Side, London Gatwick Airport",
    "sg:city":"Gatwick",
    "sg:classifiers":[
        {
            "category":"Shopping",
            "subcategory":"Comic Books",
            "type":"Retail Goods"
        }
    ],
    "sg:phone":"+44 1293 579404",
    "sg:postcode":"RH6 0NN",
    "sg:province":"Surrey",
    "sg:tags":[
        "jeweller"
    ],
    "wof:name":"Watch Station",
    "wof:placetype":"venue"
},
  "geometry": {"coordinates":[-0.1723539978,51.1617736816],"type":"Point"}
}