{
  "type": "Feature",
  "properties": {
    "addr:full":"734 London Road, West Thurrock Grays Essex RM20 3NL",
    "addr:housenumber":"734",
    "addr:postcode":"rm20 3nl",
    "addr:street":"London Road",
    "iso:country":"GB",
    "sg:address":"734 London Road, West Thurrock",
    "sg:city":"Grays",
    "sg:classifiers":[
        {
            "category":"Professional",
            "subcategory":"Testing Lab",
            "type":"Services"
        }
    ],
    "sg:phone":"+44 1708 680200",
    "sg:postcode":"RM20 3NL",
    "sg:province":"Essex",
    "sg:tags":[
        "inspection",
        "calibration"
    ],
    "wof:name":"Caleb Brett Division",
    "wof:placetype":"venue"
},
  "geometry": {"coordinates":[0.28655,51.48045],"type":"Point"}
}