{
  "type": "Feature",
  "properties": {
    "addr:full":"Loscoe Road Heanor Derbyshire DE75 7JT",
    "addr:postcode":"de75 7jt",
    "addr:street":"Loscoe Road",
    "iso:country":"GB",
    "sg:address":"Loscoe Road",
    "sg:city":"Heanor",
    "sg:classifiers":[
        {
            "category":"Autos & Motor Vehicles",
            "subcategory":"Fuel & Gas Station",
            "type":"Retail Goods"
        }
    ],
    "sg:phone":"+44 1773 530351",
    "sg:postcode":"DE75 7JT",
    "sg:province":"Derbyshire",
    "sg:tags":[
        "petrol",
        "filling"
    ],
    "wof:name":"Loscoe Petrol Station",
    "wof:placetype":"venue"
},
  "geometry": {"coordinates":[-1.363019,53.019951],"type":"Point"}
}