{
  "type": "Feature",
  "properties": {
    "iso:country":"GB",
    "sg:address":"33 Buckland Close",
    "sg:city":"Waterlooville",
    "sg:classifiers":[
        {
            "category":"Home & Garden",
            "subcategory":"Hardware",
            "type":"Retail Goods"
        }
    ],
    "sg:phone":"+44 23 9242 8643",
    "sg:postcode":"PO7 6ED",
    "sg:province":"Hampshire",
    "sg:tags":[
        "compressor",
        "air"
    ],
    "wof:name":"J.B Compressor Services",
    "wof:placetype":"venue"
},
  "geometry": {"coordinates":[-1.0366040468,50.8944854736],"type":"Point"}
}