{
  "type": "Feature",
  "properties": {
    "addr:full":"Unit 1 Green Lanes Shopping Cent Barnstaple Devon EX31 1UL",
    "addr:housenumber":"unit 1",
    "addr:postcode":"ex31 1ul",
    "addr:street":"Green Lanes",
    "iso:country":"GB",
    "sg:address":"Unit 1 Green Lanes Shopping Cent",
    "sg:city":"Barnstaple",
    "sg:classifiers":[
        {
            "category":"Shopping",
            "subcategory":"Clothing, Apparel, & Fashions",
            "type":"Retail Goods"
        }
    ],
    "sg:phone":"+44 1271 372841",
    "sg:postcode":"EX31 1UL",
    "sg:province":"Devon",
    "sg:tags":[
        "shop"
    ],
    "wof:name":"Big Star Ltd.",
    "wof:placetype":"venue"
},
  "geometry": {"coordinates":[-4.0605401993,51.0820617676],"type":"Point"}
}