{
  "type": "Feature",
  "properties": {
    "addr:full":"42 West Street Horsham West Sussex RH12 1PP",
    "addr:housenumber":"42",
    "addr:postcode":"rh12 1pp",
    "addr:street":"West Street",
    "iso:country":"GB",
    "sg:address":"42 West Street",
    "sg:city":"Horsham",
    "sg:classifiers":[
        {
            "category":"Shopping",
            "subcategory":"Shoes",
            "type":"Retail Goods"
        }
    ],
    "sg:phone":"+44 1403 217745",
    "sg:postcode":"RH12 1PP",
    "sg:province":"West Sussex",
    "wof:name":"Almeys",
    "wof:placetype":"venue"
},
  "geometry": {"coordinates":[-0.3312009871,51.0631599426],"type":"Point"}
}