{
  "type": "Feature",
  "properties": {
    "addr:full":"The Harrow Way Basingstoke Hampshire RG22 6HP",
    "addr:postcode":"rg22 6hp",
    "addr:street":"The Harrow Way",
    "iso:country":"GB",
    "sg:address":"The Harrow Way",
    "sg:city":"Basingstoke",
    "sg:classifiers":[
        {
            "category":"Retail",
            "subcategory":"Auto Repair",
            "type":"Services"
        }
    ],
    "sg:phone":"+44 1256 843193",
    "sg:postcode":"RG22 6HP",
    "sg:province":"Hampshire",
    "sg:tags":[
        "engine"
    ],
    "wof:name":"E A P Smiths Industries",
    "wof:placetype":"venue"
},
  "geometry": {"coordinates":[-1.1068810225,51.2500114441],"type":"Point"}
}