{
  "type": "Feature",
  "properties": {
    "iso:country":"GB",
    "sg:address":"12b Hargreaves Street",
    "sg:city":"Burnley",
    "sg:classifiers":[
        {
            "category":"Insurance",
            "subcategory":"Insurance Agent",
            "type":"Services"
        }
    ],
    "sg:phone":"+44 1282 426027",
    "sg:postcode":"BB11 1DZ",
    "sg:province":"Lancashire",
    "wof:name":"West Pennine Insurance Group",
    "wof:placetype":"venue"
},
  "geometry": {"coordinates":[-2.245115,53.788822],"type":"Point"}
}