{
  "type": "Feature",
  "properties": {
    "addr:full":"Graphico House, 69-71 London Road Croydon Surrey CR0 2RF",
    "addr:housenumber":"69-71",
    "addr:postcode":"cr0 2rf",
    "addr:street":"London Road",
    "iso:country":"GB",
    "sg:address":"Graphico House, 69-71 London Road",
    "sg:city":"Croydon",
    "sg:classifiers":[
        {
            "category":"Professional",
            "subcategory":"Printing & Photocopies",
            "type":"Services"
        }
    ],
    "sg:phone":"+44 20 8681 1101",
    "sg:postcode":"CR0 2RF",
    "sg:province":"Surrey",
    "sg:tags":[
        "printer"
    ],
    "wof:name":"Graphico (Printing) Ltd.",
    "wof:placetype":"venue"
},
  "geometry": {"coordinates":[-0.105117999,51.3804092407],"type":"Point"}
}