{
  "type": "Feature",
  "properties": {
    "addr:full":"Richmond Drive Skegness Lincolnshire PE25 3TH",
    "addr:postcode":"pe25 3th",
    "addr:street":"Richmond Drive",
    "iso:country":"GB",
    "sg:address":"Richmond Drive",
    "sg:city":"Skegness",
    "sg:classifiers":[
        {
            "category":"Professional",
            "subcategory":"Engineering",
            "type":"Services"
        }
    ],
    "sg:phone":"+44 1754 760594",
    "sg:postcode":"PE25 3TH",
    "sg:province":"Lincolnshire",
    "sg:tags":[
        "design",
        "engineer"
    ],
    "wof:name":"I C B Design & Engineering Ltd.",
    "wof:placetype":"venue"
},
  "geometry": {"coordinates":[0.3326500058,53.1374015808],"type":"Point"}
}