{
  "type": "Feature",
  "properties": {
    "addr:full":"17-19 Market Street Leigh Lancashire WN7 1DT",
    "addr:housenumber":"17-19",
    "addr:postcode":"wn7 1dt",
    "addr:street":"Market Street Leigh",
    "iso:country":"GB",
    "sg:address":"17-19 Market Street",
    "sg:city":"Leigh",
    "sg:classifiers":[
        {
            "category":"Professional",
            "subcategory":"Engineering",
            "type":"Services"
        }
    ],
    "sg:phone":"+44 1942 678686",
    "sg:postcode":"WN7 1DT",
    "sg:province":"Lancashire",
    "sg:tags":[
        "civil",
        "engineer"
    ],
    "wof:name":"The European Paving Corporation",
    "wof:placetype":"venue"
},
  "geometry": {"coordinates":[-2.518715,53.497124],"type":"Point"}
}