{
  "type": "Feature",
  "properties": {
    "iso:country":"GB",
    "sg:address":"Clovelly Road, Southbourne Industrial Estate, Southbourne",
    "sg:city":"Emsworth",
    "sg:classifiers":[
        {
            "category":"Professional",
            "subcategory":"Engineering",
            "type":"Services"
        }
    ],
    "sg:phone":"+44 1243 373712",
    "sg:postcode":"PO10 8PF",
    "sg:province":"Hampshire",
    "wof:name":"Metspin Ltd.",
    "wof:placetype":"venue"
},
  "geometry": {"coordinates":[-0.91072,50.852188],"type":"Point"}
}