{
  "type": "Feature",
  "properties": {
    "iso:country":"GB",
    "sg:address":"Second Avenue, Gwersyllt",
    "sg:city":"Wrexham",
    "sg:classifiers":[
        {
            "category":"Community Center",
            "type":"Public Place"
        }
    ],
    "sg:phone":"+44 1978 755857",
    "sg:postcode":"LL11 4ED",
    "sg:province":"Wrexham",
    "sg:tags":[
        "centre"
    ],
    "wof:name":"Gwersyllt Community Centre",
    "wof:placetype":"venue"
},
  "geometry": {"coordinates":[-3.0192840099,53.0723838806],"type":"Point"}
}