{
  "type": "Feature",
  "properties": {
    "addr:full":"81 Pinchbeck Road Spalding Lincolnshire PE11 1QF",
    "addr:housenumber":"81",
    "addr:postcode":"pe11 1qf",
    "addr:street":"Pinchbeck Road",
    "iso:country":"GB",
    "sg:address":"81 Pinchbeck Road",
    "sg:city":"Spalding",
    "sg:classifiers":[
        {
            "category":"Building & Trades",
            "subcategory":"Cleaning & Sanitation",
            "type":"Services"
        },
        {
            "category":"Education",
            "subcategory":"School",
            "type":"Public Place"
        }
    ],
    "sg:phone":"+44 1775 711800",
    "sg:postcode":"PE11 1QF",
    "sg:province":"Lincolnshire",
    "sg:tags":[
        "contracting",
        "commercial",
        "authority",
        "local"
    ],
    "wof:name":"University Consultant Services Ltd.",
    "wof:placetype":"venue"
},
  "geometry": {"coordinates":[-0.151992,52.793537],"type":"Point"}
}