{
  "type": "Feature",
  "properties": {
    "addr:full":"Unit 13 Astra Business Park, Guinness Road Manchester Cheshire M17 1SU",
    "addr:housenumber":"unit 13",
    "addr:postcode":"m17 1su",
    "addr:street":"Business Park Guinness Road",
    "iso:country":"GB",
    "sg:address":"Unit 13 Astra Business Park, Guinness Road",
    "sg:city":"Manchester",
    "sg:classifiers":[
        {
            "category":"Shopping",
            "subcategory":"Jewelry",
            "type":"Retail Goods"
        }
    ],
    "sg:phone":"+44 161 877 2777",
    "sg:postcode":"M17 1SU",
    "sg:province":"Cheshire",
    "sg:tags":[
        "diamond"
    ],
    "wof:name":"P S Building Supplies Ltd.",
    "wof:placetype":"venue"
},
  "geometry": {"coordinates":[-2.3339989185,53.4741096497],"type":"Point"}
}