{
  "type": "Feature",
  "properties": {
    "addr:full":"123 Devonshire Street Keighley West Yorkshire BD21 2QL",
    "addr:housenumber":"123",
    "addr:postcode":"bd21 2ql",
    "addr:street":"Devonshire Street",
    "iso:country":"GB",
    "sg:address":"123 Devonshire Street",
    "sg:city":"Keighley",
    "sg:classifiers":[
        {
            "category":"Food & Beverages",
            "subcategory":"Supermarket",
            "type":"Retail Goods"
        }
    ],
    "sg:phone":"+44 1535 663141",
    "sg:postcode":"BD21 2QL",
    "sg:province":"West Yorkshire",
    "wof:name":"Food Fair",
    "wof:placetype":"venue"
},
  "geometry": {"coordinates":[-1.9184039831,53.8674278259],"type":"Point"}
}