{
  "type": "Feature",
  "properties": {
    "addr:full":"151 Ridgeway, Plympton Plymouth Devon PL7 2HJ",
    "addr:housenumber":"151",
    "addr:postcode":"pl7 2hj",
    "addr:street":"Ridgeway",
    "iso:country":"GB",
    "sg:address":"151 Ridgeway, Plympton",
    "sg:city":"Plymouth",
    "sg:classifiers":[
        {
            "category":"Real Estate",
            "subcategory":"Real Estate Agent",
            "type":"Services"
        }
    ],
    "sg:phone":"+44 1752 336675",
    "sg:postcode":"PL7 2HJ",
    "sg:province":"Devon",
    "wof:name":"Miller Countrywide",
    "wof:placetype":"venue"
},
  "geometry": {"coordinates":[-4.0492801666,50.3874511719],"type":"Point"}
}