{
  "type": "Feature",
  "properties": {
    "iso:country":"GB",
    "sg:address":"Swanmead Park, Church Rd",
    "sg:city":"Basildon",
    "sg:classifiers":[
        {
            "category":"Landmark",
            "subcategory":"Tourist Attraction",
            "type":"Public Place"
        }
    ],
    "sg:phone":"+44 1268 523778",
    "sg:postcode":"SS14 2EU",
    "sg:province":"Essex",
    "sg:tags":[
        "interest"
    ],
    "wof:name":"Swanmead Park",
    "wof:placetype":"venue"
},
  "geometry": {"coordinates":[0.47225,51.57822],"type":"Point"}
}