{
  "type": "Feature",
  "properties": {
    "addr:full":"Stratford Road, Hockley Heath Solihull Warwickshire B94 6EA",
    "addr:postcode":"b94 6ea",
    "addr:street":"Stratford Road",
    "iso:country":"GB",
    "sg:address":"Stratford Road, Hockley Heath",
    "sg:city":"Solihull",
    "sg:classifiers":[
        {
            "category":"Manufacturing",
            "subcategory":"Petroleum Products",
            "type":"Manufacturing & Wholesale Goods"
        },
        {
            "category":"Home & Garden",
            "subcategory":"Home Furnishings",
            "type":"Retail Goods"
        }
    ],
    "sg:phone":"+44 1564 785224",
    "sg:postcode":"B94 6EA",
    "sg:province":"Warwickshire",
    "sg:tags":[
        "supplier",
        "candle",
        "manufacturer"
    ],
    "wof:name":"U Me Us",
    "wof:placetype":"venue"
},
  "geometry": {"coordinates":[-1.784994,52.372974],"type":"Point"}
}