{
  "type": "Feature",
  "properties": {
    "addr:full":"30 Bridge Street Kelso Scottish Borders TD5 7JD",
    "addr:housenumber":"30",
    "addr:postcode":"td5 7jd",
    "addr:street":"Bridge Street",
    "iso:country":"GB",
    "sg:address":"30 Bridge Street",
    "sg:city":"Kelso",
    "sg:classifiers":[
        {
            "category":"Shopping",
            "subcategory":"Bicycles & Sporting Goods",
            "type":"Retail Goods"
        }
    ],
    "sg:postcode":"TD5 7JD",
    "sg:province":"Scottish Borders",
    "sg:tags":[
        "cycle",
        "accessory"
    ],
    "wof:name":"Simon Porteous",
    "wof:placetype":"venue"
},
  "geometry": {"coordinates":[-2.4337100983,55.5980758667],"type":"Point"}
}