{
  "type": "Feature",
  "properties": {
    "addr:full":"Fernec Works, Stephenson Street Oldham Lancashire OL4 2HH",
    "addr:postcode":"ol4 2hh",
    "addr:street":"Stephenson Street",
    "iso:country":"GB",
    "sg:address":"Fernec Works, Stephenson Street",
    "sg:city":"Oldham",
    "sg:classifiers":[
        {
            "category":"Manufacturing",
            "subcategory":"Metals",
            "type":"Manufacturing & Wholesale Goods"
        }
    ],
    "sg:phone":"+44 161 628 2996",
    "sg:postcode":"OL4 2HH",
    "sg:province":"Lancashire",
    "sg:tags":[
        "steel",
        "fabricator",
        "erectors"
    ],
    "wof:name":"Marton Engineering Services Ltd.",
    "wof:placetype":"venue"
},
  "geometry": {"coordinates":[-2.0788400173,53.5490989685],"type":"Point"}
}