{
  "type": "Feature",
  "properties": {
    "iso:country":"GB",
    "sg:address":"Room 9 49 Coplaw St",
    "sg:city":"Glasgow",
    "sg:classifiers":[
        {
            "category":"Retail",
            "subcategory":"Funeral Services",
            "type":"Services"
        }
    ],
    "sg:phone":"+44 141 423 4420",
    "sg:postcode":"G42 7JE",
    "sg:province":"Glasgow City",
    "wof:name":"Hebrew Burial Society",
    "wof:placetype":"venue"
},
  "geometry": {"coordinates":[-4.265739,55.840458],"type":"Point"}
}