{
  "type": "Feature",
  "properties": {
    "iso:country":"GB",
    "sg:address":"28 Downham St",
    "sg:city":"Bradford",
    "sg:classifiers":[
        {
            "category":"Shopping",
            "subcategory":"Stationery & Office Supplies",
            "type":"Retail Goods"
        }
    ],
    "sg:phone":"+44 1274 731547",
    "sg:postcode":"BD3 9QY",
    "sg:province":"West Yorkshire",
    "sg:tags":[
        "item",
        "promotional"
    ],
    "wof:name":"Biff Promotions",
    "wof:placetype":"venue"
},
  "geometry": {"coordinates":[-1.738784,53.792301],"type":"Point"}
}