{
  "type": "Feature",
  "properties": {
    "addr:full":"Talbot Rd Birkenhead Merseyside L43 2HJ",
    "addr:postcode":"l43 2hj",
    "addr:street":"Talbot Rd",
    "iso:country":"GB",
    "sg:address":"Talbot Rd",
    "sg:city":"Birkenhead",
    "sg:classifiers":[
        {
            "category":"Restaurant",
            "type":"Food & Drink"
        }
    ],
    "sg:phone":"+44 151 653 3773",
    "sg:postcode":"L43 2HJ",
    "sg:province":"Merseyside",
    "wof:name":"Furlani's Restaurant",
    "wof:placetype":"venue"
},
  "geometry": {"coordinates":[-3.0509200096,53.3805084229],"type":"Point"}
}