{
  "type": "Feature",
  "properties": {
    "addr:full":"53 Telford Way Leicester Leicestershire LE5 2LX",
    "addr:housenumber":"53",
    "addr:postcode":"le5 2lx",
    "addr:street":"Telford Way",
    "iso:country":"GB",
    "sg:address":"53 Telford Way",
    "sg:city":"Leicester",
    "sg:classifiers":[
        {
            "category":"Professional",
            "subcategory":"Art Services",
            "type":"Services"
        },
        {
            "category":"Building & Trades",
            "subcategory":"Construction",
            "type":"Services"
        }
    ],
    "sg:phone":"+44 116 243 2822",
    "sg:postcode":"LE5 2LX",
    "sg:province":"Leicestershire",
    "sg:tags":[
        "decorator",
        "painter"
    ],
    "wof:name":"JULIAN JOHN BLAKEMAN",
    "wof:placetype":"venue"
},
  "geometry": {"coordinates":[-1.050464,52.634274],"type":"Point"}
}