{
  "type": "Feature",
  "properties": {
    "iso:country":"GB",
    "sg:address":"96 Colne Road, Brierfield",
    "sg:city":"Nelson",
    "sg:classifiers":[
        {
            "category":"Home & Garden",
            "subcategory":"Household Appliances",
            "type":"Retail Goods"
        }
    ],
    "sg:phone":"+44 1282 601801",
    "sg:postcode":"BB9 5NN",
    "sg:province":"Lancashire",
    "sg:tags":[
        "electrical"
    ],
    "wof:name":"Pendle Domestics",
    "wof:placetype":"venue"
},
  "geometry": {"coordinates":[-2.23389,53.826874],"type":"Point"}
}