{
  "type": "Feature",
  "properties": {
    "addr:full":"Charity Farm, Smithy Brow, Wrightington Wigan Lancashire WN6 9PP",
    "addr:postcode":"wn6 9pp",
    "addr:street":"Smithy Brow",
    "iso:country":"GB",
    "sg:address":"Charity Farm, Smithy Brow, Wrightington",
    "sg:city":"Wigan",
    "sg:classifiers":[
        {
            "category":"Farming",
            "subcategory":"Livestock Farm",
            "type":"Manufacturing & Wholesale Goods"
        }
    ],
    "sg:postcode":"WN6 9PP",
    "sg:province":"Lancashire",
    "sg:tags":[
        "others"
    ],
    "wof:name":"F J & P Waring",
    "wof:placetype":"venue"
},
  "geometry": {"coordinates":[-2.701154,53.606846],"type":"Point"}
}