{
  "type": "Feature",
  "properties": {
    "addr:full":"55 Broadway London Greater London SW1H 0BD",
    "addr:housenumber":"55",
    "addr:postcode":"sw1h 0bd",
    "addr:street":"Broadway",
    "iso:country":"GB",
    "sg:address":"55 Broadway",
    "sg:city":"London",
    "sg:classifiers":[
        {
            "category":"Professional",
            "subcategory":"Management & Consulting",
            "type":"Services"
        },
        {
            "category":"Museum",
            "subcategory":"History Museum",
            "type":"Entertainment"
        }
    ],
    "sg:phone":"+44 20 7222 5600",
    "sg:postcode":"SW1H 0BD",
    "sg:province":"Greater London",
    "sg:tags":[
        "information",
        "transport",
        "consultant"
    ],
    "wof:name":"London Underground Ltd.",
    "wof:placetype":"venue"
},
  "geometry": {"coordinates":[-0.1333809942,51.4994773865],"type":"Point"}
}