{
  "type": "Feature",
  "properties": {
    "addr:full":"71 High Street Stevenage Hertfordshire SG1 3AG",
    "addr:housenumber":"71",
    "addr:postcode":"sg1 3ag",
    "addr:street":"High Street",
    "iso:country":"GB",
    "sg:address":"71 High Street",
    "sg:city":"Stevenage",
    "sg:classifiers":[
        {
            "category":"Cafe",
            "type":"Food & Drink"
        }
    ],
    "sg:phone":"+44 1438 720519",
    "sg:postcode":"SG1 3AG",
    "sg:province":"Hertfordshire",
    "sg:tags":[
        "tea",
        "snack",
        "bar",
        "room"
    ],
    "wof:name":"T J's Cafe",
    "wof:placetype":"venue"
},
  "geometry": {"coordinates":[-0.2077360004,51.9107322693],"type":"Point"}
}