{
  "type": "Feature",
  "properties": {
    "iso:country":"GB",
    "sg:address":"465 Salisbury House, London Wall",
    "sg:city":"London",
    "sg:classifiers":[
        {
            "category":"Real Estate",
            "subcategory":"Real Estate Agent",
            "type":"Services"
        }
    ],
    "sg:postcode":"EC2M 5RQ",
    "sg:province":"Greater London",
    "wof:name":"Salisbury House Offices Ltd.",
    "wof:placetype":"venue"
},
  "geometry": {"coordinates":[-0.08667,51.516869],"type":"Point"}
}