{
  "type": "Feature",
  "properties": {
    "iso:country":"GB",
    "sg:address":"Unit 42, Kingfisher Court",
    "sg:city":"Newbury",
    "sg:classifiers":[
        {
            "category":"Shopping",
            "subcategory":"Pharmacy",
            "type":"Retail Goods"
        }
    ],
    "sg:phone":"+44 1635 550100",
    "sg:postcode":"RG14 5SJ",
    "sg:province":"Berkshire",
    "sg:tags":[
        "medical"
    ],
    "wof:name":"Forth Medical Ltd.",
    "wof:placetype":"venue"
},
  "geometry": {"coordinates":[-1.3021990061,51.4002456665],"type":"Point"}
}