{
  "type": "Feature",
  "properties": {
    "addr:full":"68 Derngate Northampton Northamptonshire NN1 1UH",
    "addr:housenumber":"68",
    "addr:postcode":"nn1 1uh",
    "addr:street":"Derngate Northampton",
    "iso:country":"GB",
    "sg:address":"68 Derngate",
    "sg:city":"Northampton",
    "sg:classifiers":[
        {
            "category":"Real Estate",
            "subcategory":"Architect",
            "type":"Services"
        }
    ],
    "sg:phone":"+44 1604 233363",
    "sg:postcode":"NN1 1UH",
    "sg:province":"Northamptonshire",
    "wof:name":"Hobden Projects Ltd",
    "wof:placetype":"venue"
},
  "geometry": {"coordinates":[-0.8903890252,52.235748291],"type":"Point"}
}