{
  "type": "Feature",
  "properties": {
    "iso:country":"GB",
    "sg:address":"7 Ewhurst Road",
    "sg:city":"Cranleigh",
    "sg:classifiers":[
        {
            "category":"Communications",
            "subcategory":"Newspaper",
            "type":"Services"
        }
    ],
    "sg:phone":"+44 1483 275251",
    "sg:postcode":"GU6 7AA",
    "sg:province":"Surrey",
    "sg:tags":[
        "magazine"
    ],
    "wof:name":"Cranleigh Times",
    "wof:placetype":"venue"
},
  "geometry": {"coordinates":[-0.483529,51.141312],"type":"Point"}
}