{
  "type": "Feature",
  "properties": {
    "addr:full":"Artichoke Pl, Camberwell Church St London Greater London SE5 8TS",
    "addr:postcode":"se5 8ts",
    "addr:street":"Artichoke Pl Camberwell Church St",
    "iso:country":"GB",
    "sg:address":"Artichoke Pl, Camberwell Church St",
    "sg:city":"London",
    "sg:classifiers":[
        {
            "category":"Community Center",
            "type":"Public Place"
        },
        {
            "category":"Government",
            "subcategory":"Office",
            "type":"Public Place"
        }
    ],
    "sg:postcode":"SE5 8TS",
    "sg:province":"Greater London",
    "sg:tags":[
        "recreation",
        "local",
        "leisure",
        "centre"
    ],
    "wof:name":"London Borough of Southwark",
    "wof:placetype":"venue"
},
  "geometry": {"coordinates":[-0.0920889974,51.4741592407],"type":"Point"}
}