{
  "type": "Feature",
  "properties": {
    "addr:full":"84 Hagley Road Stourbridge Staffordshire DY8 1QU",
    "addr:housenumber":"84",
    "addr:postcode":"dy8 1qu",
    "addr:street":"Hagley Road",
    "iso:country":"GB",
    "sg:address":"84 Hagley Road",
    "sg:city":"Stourbridge",
    "sg:classifiers":[
        {
            "category":"Fast Food",
            "type":"Food & Drink"
        }
    ],
    "sg:phone":"+44 1384 375552",
    "sg:postcode":"DY8 1QU",
    "sg:province":"Staffordshire",
    "sg:tags":[
        "away",
        "meal",
        "outlet",
        "take"
    ],
    "wof:name":"Herbs & Spices",
    "wof:placetype":"venue"
},
  "geometry": {"coordinates":[-2.1413700581,52.4498558044],"type":"Point"}
}