{
  "type": "Feature",
  "properties": {
    "addr:full":"14 Newbiggin Musselburgh City of Edinburgh EH21 7EH",
    "addr:housenumber":"14",
    "addr:postcode":"eh21 7eh",
    "addr:street":"Newbiggin Musselburgh",
    "iso:country":"GB",
    "sg:address":"14 Newbiggin",
    "sg:city":"Musselburgh",
    "sg:classifiers":[
        {
            "category":"Personal",
            "subcategory":"Beauty Salon",
            "type":"Services"
        }
    ],
    "sg:phone":"+44 131 665 4531",
    "sg:postcode":"EH21 7EH",
    "sg:province":"City of Edinburgh",
    "sg:tags":[
        "lady",
        "hairdresser"
    ],
    "wof:name":"Mister Michael's Hair Fashions",
    "wof:placetype":"venue"
},
  "geometry": {"coordinates":[-3.0474379063,55.9422492981],"type":"Point"}
}