{
  "type": "Feature",
  "properties": {
    "iso:country":"GB",
    "sg:address":"24 Stafford Street",
    "sg:city":"Edinburgh",
    "sg:classifiers":[
        {
            "category":"Professional",
            "subcategory":"Engineering",
            "type":"Services"
        }
    ],
    "sg:postcode":"EH3 7BD",
    "sg:province":"City of Edinburgh",
    "sg:tags":[
        "consulting",
        "design",
        "engineer"
    ],
    "wof:name":"Brand Leonard Ltd.",
    "wof:placetype":"venue"
},
  "geometry": {"coordinates":[-3.211788,55.949905],"type":"Point"}
}