{
  "type": "Feature",
  "properties": {
    "addr:full":"115 Commercial St Whitechapel Greater London E1 6BG",
    "addr:housenumber":"115",
    "addr:postcode":"e1 6bg",
    "addr:street":"Commercial St",
    "iso:country":"GB",
    "sg:address":"115 Commercial St",
    "sg:city":"Whitechapel",
    "sg:classifiers":[
        {
            "category":"Professional",
            "subcategory":"Printing & Photocopies",
            "type":"Services"
        }
    ],
    "sg:phone":"+44 20 7377 5037",
    "sg:postcode":"E1 6BG",
    "sg:province":"Greater London",
    "sg:tags":[
        "process",
        "screen",
        "printer"
    ],
    "wof:name":"Sintrex Ltd",
    "wof:placetype":"venue"
},
  "geometry": {"coordinates":[-0.0746600032,51.5200195312],"type":"Point"}
}