{
  "type": "Feature",
  "properties": {
    "addr:full":"12 Dickens Road Barnard Castle Cumbria DL12 8HJ",
    "addr:housenumber":"12",
    "addr:postcode":"dl12 8hj",
    "addr:street":"Dickens Road",
    "iso:country":"GB",
    "sg:address":"12 Dickens Road",
    "sg:city":"Barnard Castle",
    "sg:classifiers":[
        {
            "category":"Retail",
            "subcategory":"Driving School",
            "type":"Services"
        }
    ],
    "sg:postcode":"DL12 8HJ",
    "sg:province":"Cumbria",
    "wof:name":"John Moore Driving School",
    "wof:placetype":"venue"
},
  "geometry": {"coordinates":[-1.9107249975,54.5494384766],"type":"Point"}
}