{
  "type": "Feature",
  "properties": {
    "addr:full":"Staunton Court Business Park, Ledbury Park, Staunton Gloucester Gloucestershire GL19 3QS",
    "addr:postcode":"gl19 3qs",
    "addr:street":"Staunton;Business Park Ledbury Park",
    "iso:country":"GB",
    "sg:address":"Staunton Court Business Park, Ledbury Park, Staunton",
    "sg:city":"Gloucester",
    "sg:classifiers":[
        {
            "category":"Building & Trades",
            "subcategory":"Landscaping Services",
            "type":"Services"
        }
    ],
    "sg:phone":"+44 1452 840042",
    "sg:postcode":"GL19 3QS",
    "sg:province":"Gloucestershire",
    "sg:tags":[
        "horticultural",
        "consultant"
    ],
    "wof:name":"P B G Services",
    "wof:placetype":"venue"
},
  "geometry": {"coordinates":[-2.3209838867,51.9611091614],"type":"Point"}
}