{
  "type": "Feature",
  "properties": {
    "addr:full":"123 Keswick Close, Siddal Halifax West Yorkshire HX3 9BP",
    "addr:housenumber":"123",
    "addr:postcode":"hx3 9bp",
    "addr:street":"Keswick Close",
    "iso:country":"GB",
    "sg:address":"123 Keswick Close, Siddal",
    "sg:city":"Halifax",
    "sg:classifiers":[
        {
            "category":"Sports & Exercise",
            "subcategory":"Sports Center",
            "type":"Entertainment"
        }
    ],
    "sg:phone":"+44 1422 349957",
    "sg:postcode":"HX3 9BP",
    "sg:province":"West Yorkshire",
    "sg:tags":[
        "game",
        "combat"
    ],
    "wof:name":"Paint Ball Adventure Sports",
    "wof:placetype":"venue"
},
  "geometry": {"coordinates":[-1.8476220369,53.7075538635],"type":"Point"}
}