{
  "type": "Feature",
  "properties": {
    "addr:full":"Rosebery House, 70 Rosebery Avenue London Greater London EC1R 4RR",
    "addr:housenumber":"70",
    "addr:postcode":"ec1r 4rr",
    "addr:street":"Rosebery Avenue",
    "iso:country":"GB",
    "sg:address":"Rosebery House, 70 Rosebery Avenue",
    "sg:city":"London",
    "sg:classifiers":[
        {
            "category":"Social Services",
            "subcategory":"Job Training",
            "type":"Services"
        }
    ],
    "sg:phone":"+44 20 7278 3218",
    "sg:postcode":"EC1R 4RR",
    "sg:province":"Greater London",
    "sg:tags":[
        "draughtsman",
        "drawing"
    ],
    "wof:name":"Cadgraphics",
    "wof:placetype":"venue"
},
  "geometry": {"coordinates":[-0.10924,51.526146],"type":"Point"}
}