{
  "type": "Feature",
  "properties": {
    "addr:full":"7 King William Iv Gardens London Greater London SE20 7EG",
    "addr:housenumber":"7",
    "addr:postcode":"se20 7eg",
    "addr:street":"Gardens",
    "iso:country":"GB",
    "sg:address":"7 King William Iv Gardens",
    "sg:city":"London",
    "sg:classifiers":[
        {
            "category":"Professional",
            "subcategory":"Art Services",
            "type":"Services"
        }
    ],
    "sg:phone":"+44 20 8776 8101",
    "sg:postcode":"SE20 7EG",
    "sg:province":"Greater London",
    "sg:tags":[
        "graphic",
        "designer"
    ],
    "wof:name":"Sutton Cooper",
    "wof:placetype":"venue"
},
  "geometry": {"coordinates":[-0.055484,51.417931],"type":"Point"}
}