{
  "type": "Feature",
  "properties": {
    "addr:full":"2 Melbourne Rd East Ham Greater London E6 2RX",
    "addr:housenumber":"2",
    "addr:postcode":"e6 2rx",
    "addr:street":"Melbourne Rd",
    "iso:country":"GB",
    "sg:address":"2 Melbourne Rd",
    "sg:city":"East Ham",
    "sg:classifiers":[
        {
            "category":"Social Services",
            "subcategory":"Adult Care",
            "type":"Services"
        }
    ],
    "sg:phone":"+44 20 8552 8948",
    "sg:postcode":"E6 2RX",
    "sg:province":"Greater London",
    "sg:tags":[
        "day",
        "centre"
    ],
    "wof:name":"Brian Didsbury Centre",
    "wof:placetype":"venue"
},
  "geometry": {"coordinates":[0.0589830019,51.5324440002],"type":"Point"}
}