{
  "type": "Feature",
  "properties": {
    "addr:full":"Unit 6 The Old Laundrey, Haydon Way London Greater London SW11 1YF",
    "addr:housenumber":"unit 6",
    "addr:postcode":"sw11 1yf",
    "addr:street":"The;Haydon Way",
    "iso:country":"GB",
    "sg:address":"Unit 6 The Old Laundrey, Haydon Way",
    "sg:city":"London",
    "sg:classifiers":[
        {
            "category":"Professional",
            "subcategory":"Art Services",
            "type":"Services"
        }
    ],
    "sg:postcode":"SW11 1YF",
    "sg:province":"Greater London",
    "sg:tags":[
        "photographer"
    ],
    "wof:name":"Nick Moyler Photography",
    "wof:placetype":"venue"
},
  "geometry": {"coordinates":[-0.18006,51.461021],"type":"Point"}
}