{
  "type": "Feature",
  "properties": {
    "addr:full":"283 Blackmoorfoot Rd, Crosland Moor Huddersfield West Yorkshire HD4 5RL",
    "addr:housenumber":"283",
    "addr:postcode":"hd4 5rl",
    "addr:street":"Blackmoorfoot Rd;West",
    "iso:country":"GB",
    "sg:address":"283 Blackmoorfoot Rd, Crosland Moor",
    "sg:city":"Huddersfield",
    "sg:classifiers":[
        {
            "category":"Fast Food",
            "type":"Food & Drink"
        }
    ],
    "sg:phone":"+44 1484 645074",
    "sg:postcode":"HD4 5RL",
    "sg:province":"West Yorkshire",
    "sg:tags":[
        "away",
        "take"
    ],
    "wof:name":"Eastern Tandoori Take-away",
    "wof:placetype":"venue"
},
  "geometry": {"coordinates":[-1.810597,53.637154],"type":"Point"}
}