{
  "type": "Feature",
  "properties": {
    "iso:country":"GB",
    "sg:address":"1 Kilmaurs Main Cottages, Irvine Rd, Kilmaurs",
    "sg:city":"Kilmarnock",
    "sg:classifiers":[
        {
            "category":"Professional",
            "subcategory":"Accounting & Tax Preparation",
            "type":"Services"
        }
    ],
    "sg:phone":"+44 1563 550948",
    "sg:postcode":"KA3 2NX",
    "sg:province":"East Ayrshire",
    "sg:tags":[
        "accountant"
    ],
    "wof:name":"A1 Book Keeping Services",
    "wof:placetype":"venue"
},
  "geometry": {"coordinates":[-4.526824,55.638844],"type":"Point"}
}