{
  "type": "Feature",
  "properties": {
    "iso:country":"GB",
    "sg:address":"39 Main Street",
    "sg:city":"Alford",
    "sg:classifiers":[
        {
            "category":"Professional",
            "subcategory":"Lawyer & Legal Services",
            "type":"Services"
        }
    ],
    "sg:phone":"+44 1975 562939",
    "sg:postcode":"AB33 8PX",
    "sg:province":"Aberdeenshire",
    "sg:tags":[
        "solicitor"
    ],
    "wof:name":"Stuart Wilson Dickson & Co.",
    "wof:placetype":"venue"
},
  "geometry": {"coordinates":[-2.699374,57.231487],"type":"Point"}
}