{
  "type": "Feature",
  "properties": {
    "addr:full":"Stoken Hollow Farm London Road, Bozeat Wellingborough Bedfordshire NN29 7NP",
    "addr:postcode":"nn29 7np",
    "addr:street":"Stoken;London Road",
    "iso:country":"GB",
    "sg:address":"Stoken Hollow Farm London Road, Bozeat",
    "sg:city":"Wellingborough",
    "sg:classifiers":[
        {
            "category":"Building & Trades",
            "subcategory":"Construction",
            "type":"Services"
        }
    ],
    "sg:phone":"+44 1933 665995",
    "sg:postcode":"NN29 7NP",
    "sg:province":"Bedfordshire",
    "sg:tags":[
        "contractor",
        "pool",
        "swimming"
    ],
    "wof:name":"Kingfisher Pools & Leisure",
    "wof:placetype":"venue"
},
  "geometry": {"coordinates":[-0.6760280132,52.2217483521],"type":"Point"}
}