{
  "type": "Feature",
  "properties": {
    "iso:country":"GB",
    "sg:address":"Flat 1, 5 Alton Road",
    "sg:city":"Poole",
    "sg:classifiers":[
        {
            "category":"Personal",
            "subcategory":"Psychics & Astrologers",
            "type":"Services"
        }
    ],
    "sg:postcode":"BH14 8SJ",
    "sg:province":"Dorset",
    "wof:name":"Vivienne Baker Astrologer",
    "wof:placetype":"venue"
},
  "geometry": {"coordinates":[-1.94697,50.721611],"type":"Point"}
}