{
  "type": "Feature",
  "properties": {
    "iso:country":"GB",
    "sg:address":"107 Westland Drive",
    "sg:city":"Glasgow",
    "sg:classifiers":[
        {
            "category":"Professional",
            "subcategory":"Research",
            "type":"Services"
        }
    ],
    "sg:phone":"+44 1369 860027",
    "sg:postcode":"G14 9PF",
    "sg:province":"Glasgow City",
    "sg:tags":[
        "organisation",
        "market"
    ],
    "wof:name":"Management Information",
    "wof:placetype":"venue"
},
  "geometry": {"coordinates":[-4.3359909058,55.8815460205],"type":"Point"}
}