{
  "type": "Feature",
  "properties": {
    "addr:full":"Buteland Terrace Newbiggin-by-the-sea Northumberland NE64 6NS",
    "addr:postcode":"ne64 6ns",
    "addr:street":"Buteland;Northumberland",
    "iso:country":"GB",
    "sg:address":"Buteland Terrace",
    "sg:city":"Newbiggin-by-the-sea",
    "sg:classifiers":[
        {
            "category":"Health Services",
            "subcategory":"Doctor",
            "type":"Services"
        },
        {
            "category":"Health Services",
            "subcategory":"Clinic",
            "type":"Services"
        }
    ],
    "sg:phone":"+44 1670 816996",
    "sg:postcode":"NE64 6NS",
    "sg:province":"Northumberland",
    "sg:tags":[
        "nh",
        "practitioners"
    ],
    "wof:name":"The Health Centre",
    "wof:placetype":"venue"
},
  "geometry": {"coordinates":[-1.5175490379,55.1830749512],"type":"Point"}
}