{
  "type": "Feature",
  "properties": {
    "addr:full":"37 Stricklandgate Kendal Cumbria LA9 4LR",
    "addr:housenumber":"37",
    "addr:postcode":"la9 4lr",
    "addr:street":"Stricklandgate",
    "iso:country":"GB",
    "sg:address":"37 Stricklandgate",
    "sg:city":"Kendal",
    "sg:classifiers":[
        {
            "category":"Health Services",
            "subcategory":"Optometrist",
            "type":"Services"
        }
    ],
    "sg:phone":"+44 1539 734777",
    "sg:postcode":"LA9 4LR",
    "sg:province":"Cumbria",
    "sg:tags":[
        "optician"
    ],
    "wof:name":"Kendal Specsavers Ltd.",
    "wof:placetype":"venue"
},
  "geometry": {"coordinates":[-2.7471449375,54.3292694092],"type":"Point"}
}