{
  "type": "Feature",
  "properties": {
    "iso:country":"GB",
    "sg:address":"45 Stevenson Road",
    "sg:city":"Edinburgh",
    "sg:classifiers":[
        {
            "category":"Home & Garden",
            "subcategory":"Hardware",
            "type":"Retail Goods"
        }
    ],
    "sg:phone":"+44 131 346 1563",
    "sg:postcode":"EH11 2SL",
    "sg:province":"City of Edinburgh",
    "sg:tags":[
        "shop",
        "retailer",
        "diy"
    ],
    "wof:name":"B & Q plc",
    "wof:placetype":"venue"
},
  "geometry": {"coordinates":[-3.2427220345,55.9380607605],"type":"Point"}
}