{
  "type": "Feature",
  "properties": {
    "iso:country":"GB",
    "sg:address":"Flat 3 38 Dyke Road",
    "sg:city":"Brighton",
    "sg:classifiers":[
        {
            "category":"Organizations",
            "subcategory":"Membership Organization",
            "type":"Services"
        }
    ],
    "sg:postcode":"BN1 3JB",
    "sg:province":"East Sussex",
    "sg:tags":[
        "club"
    ],
    "wof:name":"The Association Resources Co  Ltd",
    "wof:placetype":"venue"
},
  "geometry": {"coordinates":[-0.14667,50.829121],"type":"Point"}
}