{
  "type": "Feature",
  "properties": {
    "iso:country":"GB",
    "sg:address":"13 Kirkham Road",
    "sg:city":"Harrogate",
    "sg:classifiers":[
        {
            "category":"Building & Trades",
            "subcategory":"Construction",
            "type":"Services"
        }
    ],
    "sg:phone":"+44 1423 562283",
    "sg:postcode":"HG1 4EL",
    "sg:province":"North Yorkshire",
    "sg:tags":[
        "tile",
        "fitting",
        "tiling",
        "laying",
        "contractor"
    ],
    "wof:name":"PAUL ROMAN",
    "wof:placetype":"venue"
},
  "geometry": {"coordinates":[-1.527431,54.010429],"type":"Point"}
}