{
  "type": "Feature",
  "properties": {
    "addr:full":"176 Bitterne Road Southampton Hampshire SO18 1BY",
    "addr:housenumber":"176",
    "addr:postcode":"so18 1by",
    "addr:street":"Bitterne Road",
    "iso:country":"GB",
    "sg:address":"176 Bitterne Road",
    "sg:city":"Southampton",
    "sg:classifiers":[
        {
            "category":"Shopping",
            "subcategory":"News",
            "type":"Retail Goods"
        }
    ],
    "sg:phone":"+44 23 8022 5942",
    "sg:postcode":"SO18 1BY",
    "sg:province":"Hampshire",
    "sg:tags":[
        "newsagent"
    ],
    "wof:name":"Edward Oliver",
    "wof:placetype":"venue"
},
  "geometry": {"coordinates":[-1.369258,50.916714],"type":"Point"}
}