{
  "type": "Feature",
  "properties": {
    "iso:country":"GB",
    "sg:address":"Poplar Road",
    "sg:city":"Birmingham",
    "sg:classifiers":[
        {
            "category":"Government",
            "subcategory":"Office",
            "type":"Public Place"
        }
    ],
    "sg:phone":"+44 121 444 0857",
    "sg:postcode":"B14 7AA",
    "sg:province":"West Midlands",
    "sg:tags":[
        "local"
    ],
    "wof:name":"Kings Heath Infant and Nursery School",
    "wof:placetype":"venue"
},
  "geometry": {"coordinates":[-1.889594,52.436668],"type":"Point"}
}