{
  "type": "Feature",
  "properties": {
    "addr:full":"324 West Derby Rd, Tuebrook Liverpool Merseyside L13 8AJ",
    "addr:housenumber":"324",
    "addr:postcode":"l13 8aj",
    "addr:street":"West Derby Rd",
    "iso:country":"GB",
    "sg:address":"324 West Derby Rd, Tuebrook",
    "sg:city":"Liverpool",
    "sg:classifiers":[
        {
            "category":"Retail",
            "subcategory":"Funeral Services",
            "type":"Services"
        }
    ],
    "sg:phone":"+44 151 228 3885",
    "sg:postcode":"L13 8AJ",
    "sg:province":"Merseyside",
    "wof:name":"Thompsons Funeral Services",
    "wof:placetype":"venue"
},
  "geometry": {"coordinates":[-2.9312369823,53.4247970581],"type":"Point"}
}