{
  "type": "Feature",
  "properties": {
    "iso:country":"GB",
    "sg:address":"4 Auckland Rd",
    "sg:city":"Lambeth",
    "sg:classifiers":[
        {
            "category":"Recreation",
            "type":"Entertainment"
        }
    ],
    "sg:phone":"+44 20 7587 1111",
    "sg:postcode":"SE11 5HF",
    "sg:province":"Greater London",
    "sg:tags":[
        "hot",
        "balloon",
        "air"
    ],
    "wof:name":"London Balloon The",
    "wof:placetype":"venue"
},
  "geometry": {"coordinates":[-0.121028997,51.4866409302],"type":"Point"}
}