{
  "type": "Feature",
  "properties": {
    "addr:full":"Unit 5 Hockley Court, Stratford Road, Hockley Heath Solihull Warwickshire B94 6NW",
    "addr:housenumber":"unit 5",
    "addr:postcode":"b94 6nw",
    "addr:street":"Hockley Court Stratford Road",
    "iso:country":"GB",
    "sg:address":"Unit 5 Hockley Court, Stratford Road, Hockley Heath",
    "sg:city":"Solihull",
    "sg:classifiers":[
        {
            "category":"Autos & Motor Vehicles",
            "subcategory":"Fuel & Gas Station",
            "type":"Retail Goods"
        }
    ],
    "sg:phone":"+44 1564 784030",
    "sg:postcode":"B94 6NW",
    "sg:province":"Warwickshire",
    "sg:tags":[
        "engine",
        "sale"
    ],
    "wof:name":"Peugeot Citroen Engines",
    "wof:placetype":"venue"
},
  "geometry": {"coordinates":[-1.7849940062,52.3729743958],"type":"Point"}
}