{
  "type": "Feature",
  "properties": {
    "addr:full":"Oddfellow Street Cleckheaton West Yorkshire BD19 6NX",
    "addr:postcode":"bd19 6nx",
    "addr:street":"Oddfellow Street",
    "iso:country":"GB",
    "sg:address":"Oddfellow Street",
    "sg:city":"Cleckheaton",
    "sg:classifiers":[
        {
            "category":"Retail",
            "subcategory":"Auto Repair",
            "type":"Services"
        }
    ],
    "sg:postcode":"BD19 6NX",
    "sg:province":"West Yorkshire",
    "sg:tags":[
        "modification",
        "garage"
    ],
    "wof:name":"C G Firth",
    "wof:placetype":"venue"
},
  "geometry": {"coordinates":[-1.7487089634,53.7283554077],"type":"Point"}
}