{
  "type": "Feature",
  "properties": {
    "iso:country":"GB",
    "sg:address":"111 Rotherhithe Street",
    "sg:city":"London",
    "sg:classifiers":[
        {
            "category":"Retail",
            "subcategory":"Event Space",
            "type":"Services"
        }
    ],
    "sg:phone":"+44 20 7252 0807",
    "sg:postcode":"SE16 4NF",
    "sg:province":"Greater London",
    "sg:tags":[
        "exhibition",
        "organiser"
    ],
    "wof:name":"D J C Associates",
    "wof:placetype":"venue"
},
  "geometry": {"coordinates":[-0.054016,51.501728],"type":"Point"}
}