{
  "type": "Feature",
  "properties": {
    "iso:country":"GB",
    "sg:address":"18 Western Road",
    "sg:city":"Tring",
    "sg:classifiers":[
        {
            "category":"Real Estate",
            "subcategory":"Real Estate Operator",
            "type":"Services"
        },
        {
            "category":"Building & Trades",
            "subcategory":"Construction",
            "type":"Services"
        }
    ],
    "sg:phone":"+44 1442 824362",
    "sg:postcode":"HP23 4BB",
    "sg:province":"Buckinghamshire",
    "sg:tags":[
        "builder",
        "property",
        "leasing"
    ],
    "wof:name":"Stephen Paul Byrne Ltd.",
    "wof:placetype":"venue"
},
  "geometry": {"coordinates":[-0.6666010022,51.792591095],"type":"Point"}
}