{
  "type": "Feature",
  "properties": {
    "addr:full":"Unit 4d Berrite Est, Ironbridgerial Road South West Drayton Greater London UB7 8JT",
    "addr:housenumber":"unit;berrite",
    "addr:postcode":"ub7 8jt",
    "addr:street":"Ironbridgerial Road South",
    "iso:country":"GB",
    "sg:address":"Unit 4d Berrite Est, Ironbridgerial Road South",
    "sg:city":"West Drayton",
    "sg:classifiers":[
        {
            "category":"Government",
            "subcategory":"Post Office",
            "type":"Public Place"
        }
    ],
    "sg:phone":"+44 1895 421010",
    "sg:postcode":"UB7 8JT",
    "sg:province":"Greater London",
    "sg:tags":[
        "messenger",
        "courier"
    ],
    "wof:name":"Edge Couriers The",
    "wof:placetype":"venue"
},
  "geometry": {"coordinates":[-0.46145,51.515202],"type":"Point"}
}