{
  "type": "Feature",
  "properties": {
    "iso:country":"GB",
    "sg:address":"63 Sheep Street",
    "sg:city":"Bicester",
    "sg:classifiers":[
        {
            "category":"Restaurant",
            "type":"Food & Drink"
        }
    ],
    "sg:phone":"+44 1869 320383",
    "sg:postcode":"OX26 6JW",
    "sg:province":"Oxfordshire",
    "sg:tags":[
        "-",
        "chinese"
    ],
    "wof:name":"Yin Hong Chinese Restaurant",
    "wof:placetype":"venue"
},
  "geometry": {"coordinates":[-1.1523959637,51.8990974426],"type":"Point"}
}