{
  "type": "Feature",
  "properties": {
    "iso:country":"GB",
    "sg:address":"57/59 Glantawe Street, Morriston",
    "sg:city":"Swansea",
    "sg:classifiers":[
        {
            "category":"Home & Garden",
            "subcategory":"Kitchen Supply",
            "type":"Retail Goods"
        }
    ],
    "sg:phone":"+44 1792 543520",
    "sg:postcode":"SA6 8DQ",
    "sg:province":"Swansea",
    "sg:tags":[
        "catering"
    ],
    "wof:name":"Cyril Cooke Ltd.",
    "wof:placetype":"venue"
},
  "geometry": {"coordinates":[-3.9241418839,51.6657485962],"type":"Point"}
}