{
  "type": "Feature",
  "properties": {
    "addr:full":"34 Westmorland Avenue Blackpool Lancashire FY1 5PG",
    "addr:housenumber":"34",
    "addr:postcode":"fy1 5pg",
    "addr:street":"Westmorland Avenue",
    "iso:country":"GB",
    "sg:address":"34 Westmorland Avenue",
    "sg:city":"Blackpool",
    "sg:classifiers":[
        {
            "category":"Travel",
            "subcategory":"Hotels & Motels",
            "type":"Entertainment"
        }
    ],
    "sg:postcode":"FY1 5PG",
    "sg:province":"Lancashire",
    "sg:tags":[
        "house",
        "guest"
    ],
    "wof:name":"The New Penny",
    "wof:placetype":"venue"
},
  "geometry": {"coordinates":[-3.0436,53.808769],"type":"Point"}
}