{
  "type": "Feature",
  "properties": {
    "addr:full":"23 Coalbrook Road, Pontyberem Llanelli Carmarthenshire SA15 5HU",
    "addr:housenumber":"23",
    "addr:postcode":"sa15 5hu",
    "addr:street":"Coalbrook Road",
    "iso:country":"GB",
    "sg:address":"23 Coalbrook Road, Pontyberem",
    "sg:city":"Llanelli",
    "sg:classifiers":[
        {
            "category":"Organizations",
            "subcategory":"Membership Organization",
            "type":"Services"
        }
    ],
    "sg:postcode":"SA15 5HU",
    "sg:province":"Carmarthenshire",
    "sg:tags":[
        "club"
    ],
    "wof:name":"Pontyberem Ex-Servicemans Club",
    "wof:placetype":"venue"
},
  "geometry": {"coordinates":[-4.1667261124,51.7789840698],"type":"Point"}
}