{
  "type": "Feature",
  "properties": {
    "addr:full":"156 Union Street Aberdeen Aberdeen City AB10 1QS",
    "addr:housenumber":"156",
    "addr:postcode":"ab10 1qs",
    "addr:street":"Union Street",
    "iso:country":"GB",
    "sg:address":"156 Union Street",
    "sg:city":"Aberdeen",
    "sg:classifiers":[
        {
            "category":"Home & Garden",
            "subcategory":"Household Appliances",
            "type":"Retail Goods"
        }
    ],
    "sg:phone":"+44 1224 287426",
    "sg:postcode":"AB10 1QS",
    "sg:province":"Aberdeen City",
    "sg:tags":[
        "electrical",
        "domestic"
    ],
    "wof:name":"Scottish Hydro Electric",
    "wof:placetype":"venue"
},
  "geometry": {"coordinates":[-2.100589,57.146069],"type":"Point"}
}