{
  "type": "Feature",
  "properties": {
    "iso:country":"GB",
    "sg:address":"30 Pinewood Grn, Iver Heath",
    "sg:city":"Iver",
    "sg:classifiers":[
        {
            "category":"Professional",
            "subcategory":"Engineering",
            "type":"Services"
        }
    ],
    "sg:phone":"+44 1753 794334",
    "sg:postcode":"SL0 0QP",
    "sg:province":"Berkshire",
    "sg:tags":[
        "contractor",
        "electrical",
        "engineer"
    ],
    "wof:name":"Hall Electrical",
    "wof:placetype":"venue"
},
  "geometry": {"coordinates":[-0.5268160105,51.5463485718],"type":"Point"}
}