{
  "type": "Feature",
  "properties": {
    "iso:country":"GB",
    "sg:address":"Penvale Road",
    "sg:city":"Northampton",
    "sg:classifiers":[
        {
            "category":"Education",
            "subcategory":"School",
            "type":"Public Place"
        }
    ],
    "sg:phone":"+44 1604 677970",
    "sg:postcode":"NN4 0QW",
    "sg:province":"Northamptonshire",
    "sg:tags":[
        "local",
        "authority"
    ],
    "wof:name":"East Hunsbury Primary School",
    "wof:placetype":"venue"
},
  "geometry": {"coordinates":[-0.9039790034,52.2128944397],"type":"Point"}
}