{
  "type": "Feature",
  "properties": {
    "addr:full":"9 Blue Boar Street Oxford Oxfordshire OX1 4EZ",
    "addr:housenumber":"9",
    "addr:postcode":"ox1 4ez",
    "addr:street":"Blue Boar Street",
    "iso:country":"GB",
    "sg:address":"9 Blue Boar Street",
    "sg:city":"Oxford",
    "sg:classifiers":[
        {
            "category":"Education",
            "subcategory":"Special Training",
            "type":"Public Place"
        }
    ],
    "sg:postcode":"OX1 4EZ",
    "sg:province":"Oxfordshire",
    "sg:tags":[
        "school",
        "language"
    ],
    "wof:name":"Oxford Language Training",
    "wof:placetype":"venue"
},
  "geometry": {"coordinates":[-1.256095,51.751534],"type":"Point"}
}