{
  "type": "Feature",
  "properties": {
    "iso:country":"GB",
    "sg:address":"25 Garrard Close, Salford Priors",
    "sg:city":"Evesham",
    "sg:classifiers":[
        {
            "category":"Professional",
            "subcategory":"Computer Services",
            "type":"Services"
        }
    ],
    "sg:postcode":"WR11 8XG",
    "sg:province":"Gloucestershire",
    "sg:tags":[
        "consultant"
    ],
    "wof:name":"Neil King Partnership",
    "wof:placetype":"venue"
},
  "geometry": {"coordinates":[-1.888537,52.159134],"type":"Point"}
}