{
  "type": "Feature",
  "properties": {
    "addr:full":"7 West Wynd Dundee Dundee City DD1 4JQ",
    "addr:housenumber":"7",
    "addr:postcode":"dd1 4jq",
    "addr:street":"West Wynd",
    "iso:country":"GB",
    "sg:address":"7 West Wynd",
    "sg:city":"Dundee",
    "sg:classifiers":[
        {
            "category":"Building & Trades",
            "subcategory":"Construction",
            "type":"Services"
        }
    ],
    "sg:phone":"+44 1250 876676",
    "sg:postcode":"DD1 4JQ",
    "sg:province":"Dundee City",
    "sg:tags":[
        "builder"
    ],
    "wof:name":"Alba Building Sciences Ltd.",
    "wof:placetype":"venue"
},
  "geometry": {"coordinates":[-2.9896709919,56.4569473267],"type":"Point"}
}