{
  "type": "Feature",
  "properties": {
    "addr:full":"Melincourt Neath Neath Port Talbot SA11 4BD",
    "addr:housenumber":"melincourt",
    "addr:postcode":"sa11 4bd",
    "addr:street":"Neath Neath Port Talbot",
    "iso:country":"GB",
    "sg:address":"Melincourt",
    "sg:city":"Neath",
    "sg:classifiers":[
        {
            "category":"Bars & Pubs",
            "type":"Food & Drink"
        }
    ],
    "sg:phone":"+44 1639 710155",
    "sg:postcode":"SA11 4BD",
    "sg:province":"Neath Port Talbot",
    "sg:tags":[
        "pubs",
        "inn"
    ],
    "wof:name":"Gored Arms The",
    "wof:placetype":"venue"
},
  "geometry": {"coordinates":[-3.7128999233,51.7015419006],"type":"Point"}
}