{
  "type": "Feature",
  "properties": {
    "addr:full":"Holmfield Farm, Holmsley Field Lane, Oulton Leeds West Yorkshire LS26 8TD",
    "addr:postcode":"ls26 8td",
    "addr:street":"Field Lane",
    "iso:country":"GB",
    "sg:address":"Holmfield Farm, Holmsley Field Lane, Oulton",
    "sg:city":"Leeds",
    "sg:classifiers":[
        {
            "category":"Food & Beverages",
            "subcategory":"Meat & Fish",
            "type":"Retail Goods"
        }
    ],
    "sg:phone":"+44 113 282 3275",
    "sg:postcode":"LS26 8TD",
    "sg:province":"West Yorkshire",
    "sg:tags":[
        "butcher"
    ],
    "wof:name":"David Sadler",
    "wof:placetype":"venue"
},
  "geometry": {"coordinates":[-1.4516090155,53.7498817444],"type":"Point"}
}