{
  "type": "Feature",
  "properties": {
    "iso:country":"GB",
    "sg:address":"Central Court, Gas Street",
    "sg:city":"Birmingham",
    "sg:classifiers":[
        {
            "category":"Communications",
            "type":"Services"
        }
    ],
    "sg:phone":"+44 870 600 6766",
    "sg:postcode":"B1 2JP",
    "sg:province":"West Midlands",
    "sg:tags":[
        "broadcasting"
    ],
    "wof:name":"Central Broadcasting",
    "wof:placetype":"venue"
},
  "geometry": {"coordinates":[-1.908531,52.475834],"type":"Point"}
}