{
  "type": "Feature",
  "properties": {
    "addr:full":"Craythorne Rd Burton On Trent Derbyshire DE13 0AZ",
    "addr:postcode":"trent derbyshire de13 0az",
    "addr:street":"Craythorne Rd",
    "iso:country":"GB",
    "sg:address":"Craythorne Rd",
    "sg:city":"Burton On Trent",
    "sg:classifiers":[
        {
            "category":"Restaurant",
            "type":"Food & Drink"
        }
    ],
    "sg:phone":"+44 1283 564329",
    "sg:postcode":"DE13 0AZ",
    "sg:province":"Derbyshire",
    "wof:name":"Craythorne The",
    "wof:placetype":"venue"
},
  "geometry": {"coordinates":[-1.629739,52.835018],"type":"Point"}
}