{
  "type": "Feature",
  "properties": {
    "iso:country":"GB",
    "sg:address":"Oxford St",
    "sg:city":"Wellingborough",
    "sg:classifiers":[
        {
            "category":"Bars & Pubs",
            "type":"Food & Drink"
        }
    ],
    "sg:postcode":"NN8 4HY",
    "sg:province":"Northamptonshire",
    "sg:tags":[
        "pubs",
        "inn"
    ],
    "wof:name":"Smout,A,",
    "wof:placetype":"venue"
},
  "geometry": {"coordinates":[-0.696296,52.302422],"type":"Point"}
}