{
  "type": "Feature",
  "properties": {
    "addr:full":"108 Above Bar St Southampton Hampshire SO14 7DT",
    "addr:housenumber":"108",
    "addr:postcode":"so14 7dt",
    "addr:street":"Above Bar St",
    "iso:country":"GB",
    "sg:address":"108 Above Bar St",
    "sg:city":"Southampton",
    "sg:classifiers":[
        {
            "category":"Shopping",
            "subcategory":"Clothing, Apparel, & Fashions",
            "type":"Retail Goods"
        }
    ],
    "sg:phone":"+44 23 8033 4153",
    "sg:postcode":"SO14 7DT",
    "sg:province":"Hampshire",
    "sg:tags":[
        "shop"
    ],
    "wof:name":"Principles",
    "wof:placetype":"venue"
},
  "geometry": {"coordinates":[-1.4043259621,50.9066963196],"type":"Point"}
}