{
  "type": "Feature",
  "properties": {
    "addr:full":"6a Sunbury Road, Longbridge Birmingham West Midlands B31 4LJ",
    "addr:housenumber":"6a",
    "addr:postcode":"b31 4lj",
    "addr:street":"Sunbury Road",
    "iso:country":"GB",
    "sg:address":"6a Sunbury Road, Longbridge",
    "sg:city":"Birmingham",
    "sg:classifiers":[
        {
            "category":"Personal",
            "subcategory":"Beauty Salon",
            "type":"Services"
        }
    ],
    "sg:postcode":"B31 4LJ",
    "sg:province":"West Midlands",
    "sg:tags":[
        "unisex",
        "hairdresser"
    ],
    "wof:name":"Ahead of Style",
    "wof:placetype":"venue"
},
  "geometry": {"coordinates":[-1.9794199467,52.3954048157],"type":"Point"}
}