{
  "type": "Feature",
  "properties": {
    "addr:full":"742 Llangyfelach Road, Treboeth Swansea Swansea SA5 9EH",
    "addr:housenumber":"742",
    "addr:postcode":"sa5 9eh",
    "addr:street":"Llangyfelach Road Treboeth",
    "iso:country":"GB",
    "sg:address":"742 Llangyfelach Road, Treboeth",
    "sg:city":"Swansea",
    "sg:classifiers":[
        {
            "category":"Shopping",
            "subcategory":"News",
            "type":"Retail Goods"
        }
    ],
    "sg:phone":"+44 1792 771204",
    "sg:postcode":"SA5 9EH",
    "sg:province":"Swansea",
    "sg:tags":[
        "newsagent"
    ],
    "wof:name":"H J Thomas & Son",
    "wof:placetype":"venue"
},
  "geometry": {"coordinates":[-3.9489979744,51.6533851624],"type":"Point"}
}