{
  "type": "Feature",
  "properties": {
    "iso:country":"GB",
    "sg:address":"8a Brindley Road, Reginald Road Industrial Estate",
    "sg:city":"St. Helens",
    "sg:classifiers":[
        {
            "category":"Manufacturing",
            "subcategory":"Paper Products",
            "type":"Manufacturing & Wholesale Goods"
        }
    ],
    "sg:phone":"+44 1744 820716",
    "sg:postcode":"WA9 4HY",
    "sg:province":"Cheshire",
    "sg:tags":[
        "merchant",
        "waste"
    ],
    "wof:name":"Central Haydock Waste Paper Co Ltd",
    "wof:placetype":"venue"
},
  "geometry": {"coordinates":[-2.703046,53.429977],"type":"Point"}
}