{
  "type": "Feature",
  "properties": {
    "addr:full":"237 Wexham Road Slough Berkshire SL2 5JT",
    "addr:housenumber":"237",
    "addr:postcode":"sl2 5jt",
    "addr:street":"Wexham Road",
    "iso:country":"GB",
    "sg:address":"237 Wexham Road",
    "sg:city":"Slough",
    "sg:classifiers":[
        {
            "category":"Food & Beverages",
            "subcategory":"Meat & Fish",
            "type":"Retail Goods"
        }
    ],
    "sg:phone":"+44 1753 523360",
    "sg:postcode":"SL2 5JT",
    "sg:province":"Berkshire",
    "sg:tags":[
        "butcher"
    ],
    "wof:name":"Takhar Meat Market",
    "wof:placetype":"venue"
},
  "geometry": {"coordinates":[-0.5787510276,51.5171966553],"type":"Point"}
}