{
  "type": "Feature",
  "properties": {
    "addr:full":"19 Cockspur Street London Greater London SW1Y 5BL",
    "addr:housenumber":"19",
    "addr:postcode":"sw1y 5bl",
    "addr:street":"Cockspur Street",
    "iso:country":"GB",
    "sg:address":"19 Cockspur Street",
    "sg:city":"London",
    "sg:classifiers":[
        {
            "category":"Landmark",
            "subcategory":"Tourist Information",
            "type":"Public Place"
        }
    ],
    "sg:phone":"+44 20 7930 2812",
    "sg:postcode":"SW1Y 5BL",
    "sg:province":"Greater London",
    "wof:name":"Scottish Tourist Board",
    "wof:placetype":"venue"
},
  "geometry": {"coordinates":[-0.130543,51.507519],"type":"Point"}
}