{
  "type": "Feature",
  "properties": {
    "addr:full":"23 Lyndhurst Road Lowestoft Suffolk NR32 4PD",
    "addr:housenumber":"23",
    "addr:postcode":"nr32 4pd",
    "addr:street":"Lyndhurst Road",
    "iso:country":"GB",
    "sg:address":"23 Lyndhurst Road",
    "sg:city":"Lowestoft",
    "sg:classifiers":[
        {
            "category":"Health Services",
            "subcategory":"Nursing And Care Facility",
            "type":"Services"
        },
        {
            "category":"Social Services",
            "subcategory":"Retirement Home",
            "type":"Services"
        }
    ],
    "sg:phone":"+44 1502 560165",
    "sg:postcode":"NR32 4PD",
    "sg:province":"Suffolk",
    "sg:tags":[
        "residential"
    ],
    "wof:name":"Cherry Lodge",
    "wof:placetype":"venue"
},
  "geometry": {"coordinates":[1.754482,52.490089],"type":"Point"}
}