{
  "type": "Feature",
  "properties": {
    "addr:full":"5 Point Hill London Greater London SE10 8QL",
    "addr:housenumber":"5",
    "addr:postcode":"se10 8ql",
    "iso:country":"GB",
    "sg:address":"5 Point Hill",
    "sg:city":"London",
    "sg:classifiers":[
        {
            "category":"Retail",
            "subcategory":"Auto Repair",
            "type":"Services"
        }
    ],
    "sg:phone":"+44 20 8692 5073",
    "sg:postcode":"SE10 8QL",
    "sg:province":"Greater London",
    "sg:tags":[
        "modification",
        "garage"
    ],
    "wof:name":"Blackheath Motor Craft",
    "wof:placetype":"venue"
},
  "geometry": {"coordinates":[-0.01005,51.475025],"type":"Point"}
}