{
  "type": "Feature",
  "properties": {
    "iso:country":"GB",
    "sg:address":"Station Road, North Thoresby",
    "sg:city":"Grimsby",
    "sg:classifiers":[
        {
            "category":"Organizations",
            "subcategory":"Non-profit Organization",
            "type":"Services"
        }
    ],
    "sg:phone":"+44 1472 840209",
    "sg:postcode":"DN36 5QU",
    "sg:province":"Lincolnshire",
    "sg:tags":[
        "organisation",
        "animal",
        "welfare"
    ],
    "wof:name":"Eastfield Veterinary Clinic",
    "wof:placetype":"venue"
},
  "geometry": {"coordinates":[-0.0606070012,53.4941177368],"type":"Point"}
}