{
  "type": "Feature",
  "properties": {
    "addr:full":"Station App Radlett Hertfordshire WD7 7AP",
    "addr:postcode":"wd7 7ap",
    "iso:country":"GB",
    "sg:address":"Station App",
    "sg:city":"Radlett",
    "sg:classifiers":[
        {
            "category":"Real Estate",
            "subcategory":"Surveying",
            "type":"Services"
        }
    ],
    "sg:postcode":"WD7 7AP",
    "sg:province":"Hertfordshire",
    "sg:tags":[
        "surveyor",
        "valuer"
    ],
    "wof:name":"Robertson & Co",
    "wof:placetype":"venue"
},
  "geometry": {"coordinates":[-0.317209,51.683575],"type":"Point"}
}