{
  "type": "Feature",
  "properties": {
    "iso:country":"GB",
    "sg:address":"128 Fortess Road",
    "sg:city":"London",
    "sg:classifiers":[
        {
            "category":"Travel",
            "subcategory":"Travel Agent",
            "type":"Entertainment"
        }
    ],
    "sg:postcode":"NW5 2HP",
    "sg:province":"Greater London",
    "wof:name":"Anthony Clifford",
    "wof:placetype":"venue"
},
  "geometry": {"coordinates":[-0.139181003,51.5554580688],"type":"Point"}
}