{
  "type": "Feature",
  "properties": {
    "iso:country":"GB",
    "sg:address":"83 Clifton Street",
    "sg:city":"Lytham St Annes",
    "sg:classifiers":[
        {
            "category":"Shopping",
            "subcategory":"Gifts & Souvenirs",
            "type":"Retail Goods"
        }
    ],
    "sg:phone":"+44 1253 794657",
    "sg:postcode":"FY8 5ER",
    "sg:province":"Lancashire",
    "sg:tags":[
        "shop"
    ],
    "wof:name":"Something Special",
    "wof:placetype":"venue"
},
  "geometry": {"coordinates":[-2.9617800713,53.7372779846],"type":"Point"}
}