{
  "type": "Feature",
  "properties": {
    "addr:full":"Boveridge Farm, Cranbourne Wimborne Dorset BH21 5RU",
    "addr:housenumber":"cranbourne",
    "addr:postcode":"bh21 5ru",
    "iso:country":"GB",
    "sg:address":"Boveridge Farm, Cranbourne",
    "sg:city":"Wimborne",
    "sg:classifiers":[
        {
            "category":"Farming",
            "subcategory":"Livestock Farm",
            "type":"Manufacturing & Wholesale Goods"
        }
    ],
    "sg:phone":"+44 1725 517241",
    "sg:postcode":"BH21 5RU",
    "sg:province":"Dorset",
    "sg:tags":[
        "others"
    ],
    "wof:name":"D J Dampney (Cranborne) Ltd.",
    "wof:placetype":"venue"
},
  "geometry": {"coordinates":[-1.9564490318,50.9075813293],"type":"Point"}
}