{
  "type": "Feature",
  "properties": {
    "addr:full":"40 George Street Ryde Isle of Wight PO33 2EN",
    "addr:housenumber":"40",
    "addr:postcode":"po33 2en",
    "addr:street":"George Street",
    "iso:country":"GB",
    "sg:address":"40 George Street",
    "sg:city":"Ryde",
    "sg:classifiers":[
        {
            "category":"Travel",
            "subcategory":"Hotels & Motels",
            "type":"Entertainment"
        }
    ],
    "sg:phone":"+44 1983 562719",
    "sg:postcode":"PO33 2EN",
    "sg:province":"Isle of Wight",
    "wof:name":"Newlands Hotel",
    "wof:placetype":"venue"
},
  "geometry": {"coordinates":[-1.160799,50.730759],"type":"Point"}
}