{
  "type": "Feature",
  "properties": {
    "iso:country":"GB",
    "sg:address":"15 Hamilton Clo",
    "sg:city":"Brighton",
    "sg:classifiers":[
        {
            "category":"Autos & Motor Vehicles",
            "subcategory":"Motorcycle Sales",
            "type":"Retail Goods"
        }
    ],
    "sg:phone":"+44 1273 419891",
    "sg:postcode":"BN41 2WY",
    "sg:province":"East Sussex",
    "sg:tags":[
        "chauffeur",
        "driven",
        "car"
    ],
    "wof:name":"Presidential Limousines",
    "wof:placetype":"venue"
},
  "geometry": {"coordinates":[-0.221691,50.851398],"type":"Point"}
}