{
  "type": "Feature",
  "properties": {
    "iso:country":"GB",
    "sg:address":"Leek Old Rd",
    "sg:city":"Macclesfield",
    "sg:classifiers":[
        {
            "category":"Building & Trades",
            "subcategory":"Landscaping Services",
            "type":"Services"
        }
    ],
    "sg:phone":"+44 1260 252345",
    "sg:postcode":"SK11 0HZ",
    "sg:province":"Cheshire",
    "sg:tags":[
        "forestry",
        "tree"
    ],
    "wof:name":"Andrew R Perry",
    "wof:placetype":"venue"
},
  "geometry": {"coordinates":[-2.119731,53.232983],"type":"Point"}
}