{
  "type": "Feature",
  "properties": {
    "iso:country":"GB",
    "sg:address":"33 Highbury Way",
    "sg:city":"Sudbury",
    "sg:classifiers":[
        {
            "category":"Shopping",
            "subcategory":"Department Store",
            "type":"Retail Goods"
        },
        {
            "category":"Home & Garden",
            "subcategory":"Carpets & Floor Coverings",
            "type":"Retail Goods"
        }
    ],
    "sg:phone":"+44 1787 374275",
    "sg:postcode":"CO10 0HD",
    "sg:province":"Essex",
    "sg:tags":[
        "carpets",
        "rug",
        "matting"
    ],
    "wof:name":"Agency Carpets",
    "wof:placetype":"venue"
},
  "geometry": {"coordinates":[0.752734,52.029812],"type":"Point"}
}