{
  "type": "Feature",
  "properties": {
    "iso:country":"GB",
    "sg:address":"Owen Street",
    "sg:city":"Tipton",
    "sg:classifiers":[
        {
            "category":"Retail",
            "subcategory":"Funeral Services",
            "type":"Services"
        }
    ],
    "sg:phone":"+44 121 557 2215",
    "sg:postcode":"DY4 8ET",
    "sg:province":"West Midlands",
    "wof:name":"Co-Operative Funeral Service",
    "wof:placetype":"venue"
},
  "geometry": {"coordinates":[-2.067279,52.529678],"type":"Point"}
}