{
  "type": "Feature",
  "properties": {
    "addr:full":"112 Besley Street London Greater London SW16 6BD",
    "addr:housenumber":"112",
    "addr:postcode":"sw16 6bd",
    "addr:street":"Besley Street",
    "iso:country":"GB",
    "sg:address":"112 Besley Street",
    "sg:city":"London",
    "sg:classifiers":[
        {
            "category":"Home & Garden",
            "subcategory":"Carpets & Floor Coverings",
            "type":"Retail Goods"
        }
    ],
    "sg:postcode":"SW16 6BD",
    "sg:province":"Greater London",
    "sg:tags":[
        "cleaner",
        "upholstery"
    ],
    "wof:name":"Dryfoam Carpet Cleaners",
    "wof:placetype":"venue"
},
  "geometry": {"coordinates":[-0.142278,51.418713],"type":"Point"}
}