{
  "type": "Feature",
  "properties": {
    "addr:full":"Tregarthenen Ho Bodmin Cornwall PL30 5LJ",
    "addr:postcode":"pl30 5lj",
    "iso:country":"GB",
    "sg:address":"Tregarthenen Ho",
    "sg:city":"Bodmin",
    "sg:classifiers":[
        {
            "category":"Building & Trades",
            "subcategory":"Construction",
            "type":"Services"
        }
    ],
    "sg:phone":"+44 1208 831321",
    "sg:postcode":"PL30 5LJ",
    "sg:province":"Cornwall",
    "sg:tags":[
        "builder"
    ],
    "wof:name":"Bealing Construction",
    "wof:placetype":"venue"
},
  "geometry": {"coordinates":[-4.7787799835,50.4603385925],"type":"Point"}
}