{
  "type": "Feature",
  "properties": {
    "addr:full":"7 Arden Road, Furnace Grn Crawley Surrey RH10 6HL",
    "addr:housenumber":"7",
    "addr:postcode":"rh10 6hl",
    "addr:street":"Arden Road Furnace Grn",
    "iso:country":"GB",
    "sg:address":"7 Arden Road, Furnace Grn",
    "sg:city":"Crawley",
    "sg:classifiers":[
        {
            "category":"Social Services",
            "subcategory":"Job Training",
            "type":"Services"
        }
    ],
    "sg:postcode":"RH10 6HL",
    "sg:province":"Surrey",
    "sg:tags":[
        "translator",
        "interpreter"
    ],
    "wof:name":"Abdank Polish Translator",
    "wof:placetype":"venue"
},
  "geometry": {"coordinates":[-0.1779759973,51.107219696],"type":"Point"}
}