{
  "type": "Feature",
  "properties": {
    "iso:country":"GB",
    "sg:address":"11 Foxmoor Lane, Ebley",
    "sg:city":"Stroud",
    "sg:classifiers":[
        {
            "category":"Freight",
            "type":"Transportation"
        }
    ],
    "sg:phone":"+44 1453 826383",
    "sg:postcode":"GL5 4PW",
    "sg:province":"Gloucestershire",
    "sg:tags":[
        "haulage",
        "road"
    ],
    "wof:name":"Fourways Delivery & Collection Service",
    "wof:placetype":"venue"
},
  "geometry": {"coordinates":[-2.257049,51.745937],"type":"Point"}
}