{
  "type": "Feature",
  "properties": {
    "addr:full":"Homerton Terrace Off Morning La Hackney Greater London E9 7AL",
    "addr:postcode":"e9 7al",
    "addr:street":"Homerton Terrace Off Morning",
    "iso:country":"GB",
    "sg:address":"Homerton Terrace Off Morning La",
    "sg:city":"Hackney",
    "sg:classifiers":[
        {
            "category":"Place Of Worship",
            "type":"Public Place"
        }
    ],
    "sg:phone":"+44 20 8985 2263",
    "sg:postcode":"E9 7AL",
    "sg:province":"Greater London",
    "wof:name":"St. Lukes Church Hackney",
    "wof:placetype":"venue"
},
  "geometry": {"coordinates":[-0.04604,51.542721],"type":"Point"}
}