{
  "type": "Feature",
  "properties": {
    "iso:country":"GB",
    "sg:address":"29 Strathmore Walk",
    "sg:city":"Luton",
    "sg:classifiers":[
        {
            "category":"Organizations",
            "subcategory":"Membership Organization",
            "type":"Services"
        }
    ],
    "sg:phone":"+44 1582 756334",
    "sg:postcode":"LU1 3PD",
    "sg:province":"Bedfordshire",
    "sg:tags":[
        "club"
    ],
    "wof:name":"Science Fiction Fan Club",
    "wof:placetype":"venue"
},
  "geometry": {"coordinates":[-0.408137,51.873932],"type":"Point"}
}