{
  "type": "Feature",
  "properties": {
    "addr:full":"14-16 Glencathara Rd Bognor Regis West Sussex PO21 2SF",
    "addr:housenumber":"14-16",
    "addr:postcode":"po21 2sf",
    "addr:street":"Glencathara Rd",
    "iso:country":"GB",
    "sg:address":"14-16 Glencathara Rd",
    "sg:city":"Bognor Regis",
    "sg:classifiers":[
        {
            "category":"Health Services",
            "subcategory":"Nursing And Care Facility",
            "type":"Services"
        }
    ],
    "sg:phone":"+44 1243 827222",
    "sg:postcode":"PO21 2SF",
    "sg:province":"West Sussex",
    "sg:tags":[
        "home"
    ],
    "wof:name":"Knightswood Nursing Home",
    "wof:placetype":"venue"
},
  "geometry": {"coordinates":[-0.686093,50.783836],"type":"Point"}
}