{
  "type": "Feature",
  "properties": {
    "iso:country":"GB",
    "sg:address":"368 Halliwell Road",
    "sg:city":"Bolton",
    "sg:classifiers":[
        {
            "category":"Personal",
            "subcategory":"Beauty Salon",
            "type":"Services"
        },
        {
            "category":"Building & Trades",
            "subcategory":"Construction",
            "type":"Services"
        }
    ],
    "sg:postcode":"BL1 8AP",
    "sg:province":"Lancashire",
    "sg:tags":[
        "unisex",
        "fork",
        "lift",
        "truck",
        "hairdresser"
    ],
    "wof:name":"John Corlett Training",
    "wof:placetype":"venue"
},
  "geometry": {"coordinates":[-2.4411439896,53.593662262],"type":"Point"}
}