{
  "type": "Feature",
  "properties": {
    "iso:country":"GB",
    "sg:address":"10 Corinthian Close",
    "sg:city":"Basingstoke",
    "sg:classifiers":[
        {
            "category":"Professional",
            "subcategory":"Management & Consulting",
            "type":"Services"
        }
    ],
    "sg:postcode":"RG22 4TN",
    "sg:province":"Hampshire",
    "sg:tags":[
        "consultant",
        "business"
    ],
    "wof:name":"Turnstar Consultancy Ltd",
    "wof:placetype":"venue"
},
  "geometry": {"coordinates":[-1.126776,51.238632],"type":"Point"}
}