{
  "type": "Feature",
  "properties": {
    "iso:country":"GB",
    "sg:address":"Halton House, 20-23 Holborn",
    "sg:city":"London",
    "sg:classifiers":[
        {
            "category":"Professional",
            "subcategory":"Lawyer & Legal Services",
            "type":"Services"
        }
    ],
    "sg:phone":"+44 20 7242 8508",
    "sg:postcode":"EC1N 2JD",
    "sg:province":"Greater London",
    "sg:tags":[
        "barrister"
    ],
    "wof:name":"Jill Martin",
    "wof:placetype":"venue"
},
  "geometry": {"coordinates":[-0.1096070036,51.5179252625],"type":"Point"}
}