{
  "type": "Feature",
  "properties": {
    "addr:full":"93 Oxford Road Calne Wiltshire SN11 8AQ",
    "addr:housenumber":"93",
    "addr:postcode":"sn11 8aq",
    "addr:street":"Oxford Road",
    "iso:country":"GB",
    "sg:address":"93 Oxford Road",
    "sg:city":"Calne",
    "sg:classifiers":[
        {
            "category":"Utilities",
            "subcategory":"Refuse",
            "type":"Services"
        }
    ],
    "sg:phone":"+44 1249 815982",
    "sg:postcode":"SN11 8AQ",
    "sg:province":"Wiltshire",
    "sg:tags":[
        "retail",
        "skip",
        "hire",
        "waste",
        "disposal"
    ],
    "wof:name":"D G Hudd",
    "wof:placetype":"venue"
},
  "geometry": {"coordinates":[-1.999891,51.4422],"type":"Point"}
}