{
  "type": "Feature",
  "properties": {
    "addr:full":"3 West Road, Ponteland Newcastle-upon-tyne Northumberland NE20 9SU",
    "addr:housenumber":"3",
    "addr:postcode":"ne20 9su",
    "addr:street":"West Road",
    "iso:country":"GB",
    "sg:address":"3 West Road, Ponteland",
    "sg:city":"Newcastle-upon-tyne",
    "sg:classifiers":[
        {
            "category":"Shopping",
            "subcategory":"Clothing, Apparel, & Fashions",
            "type":"Retail Goods"
        }
    ],
    "sg:phone":"+44 1661 872959",
    "sg:postcode":"NE20 9SU",
    "sg:province":"Northumberland",
    "sg:tags":[
        "shop"
    ],
    "wof:name":"Look Twice",
    "wof:placetype":"venue"
},
  "geometry": {"coordinates":[-1.7456179857,55.0492248535],"type":"Point"}
}