{
  "type": "Feature",
  "properties": {
    "iso:country":"GB",
    "sg:address":"3 Rutland Square",
    "sg:city":"Edinburgh",
    "sg:classifiers":[
        {
            "category":"Personal",
            "type":"Services"
        },
        {
            "category":"Professional",
            "subcategory":"Lawyer & Legal Services",
            "type":"Services"
        }
    ],
    "sg:phone":"+44 131 229 6275",
    "sg:postcode":"EH1 2AS",
    "sg:province":"City of Edinburgh",
    "sg:tags":[
        "advice",
        "counselling"
    ],
    "wof:name":"CRUSE Bereavement Care",
    "wof:placetype":"venue"
},
  "geometry": {"coordinates":[-3.2083799839,55.9487190247],"type":"Point"}
}