{
  "type": "Feature",
  "properties": {
    "addr:full":"36 Newhouse Drive Kilbirnie North Ayrshire KA25 6EP",
    "addr:housenumber":"36",
    "addr:postcode":"ka25 6ep",
    "addr:street":"Newhouse Drive",
    "iso:country":"GB",
    "sg:address":"36 Newhouse Drive",
    "sg:city":"Kilbirnie",
    "sg:classifiers":[
        {
            "category":"Building & Trades",
            "subcategory":"Cleaning & Sanitation",
            "type":"Services"
        },
        {
            "category":"Home & Garden",
            "subcategory":"Carpets & Floor Coverings",
            "type":"Retail Goods"
        }
    ],
    "sg:phone":"+44 1505 682519",
    "sg:postcode":"KA25 6EP",
    "sg:province":"North Ayrshire",
    "sg:tags":[
        "cleaner",
        "upholstery",
        "commercial"
    ],
    "wof:name":"Techniclean Services",
    "wof:placetype":"venue"
},
  "geometry": {"coordinates":[-4.695285,55.748466],"type":"Point"}
}