{
  "type": "Feature",
  "properties": {
    "addr:full":"Station Road Instl Est, Stokesley Middlesbrough North Yorkshire TS9 7AE",
    "addr:postcode":"ts9 7ae",
    "addr:street":"Station Road Instl Est",
    "iso:country":"GB",
    "sg:address":"Station Road Instl Est, Stokesley",
    "sg:city":"Middlesbrough",
    "sg:classifiers":[
        {
            "category":"Retail",
            "subcategory":"Auto Repair",
            "type":"Services"
        }
    ],
    "sg:phone":"+44 1642 711970",
    "sg:postcode":"TS9 7AE",
    "sg:province":"North Yorkshire",
    "sg:tags":[
        "body",
        "car",
        "commercial",
        "vehicle"
    ],
    "wof:name":"Stokesley Motors Ltd",
    "wof:placetype":"venue"
},
  "geometry": {"coordinates":[-1.181219,54.460896],"type":"Point"}
}