{
  "type": "Feature",
  "properties": {
    "iso:country":"GB",
    "sg:address":"30 Harmer Street",
    "sg:city":"Gravesend",
    "sg:classifiers":[
        {
            "category":"Building & Trades",
            "subcategory":"Construction",
            "type":"Services"
        }
    ],
    "sg:postcode":"DA12 2AX",
    "sg:province":"Kent",
    "sg:tags":[
        "builder"
    ],
    "wof:name":"Steele John Building/Decorating Contractors",
    "wof:placetype":"venue"
},
  "geometry": {"coordinates":[0.373678,51.442314],"type":"Point"}
}