{
  "type": "Feature",
  "properties": {
    "addr:full":"58 Albemarle Gate Cheltenham Gloucestershire GL50 4PJ",
    "addr:housenumber":"58",
    "addr:postcode":"gl50 4pj",
    "addr:street":"Albemarle Gate",
    "iso:country":"GB",
    "sg:address":"58 Albemarle Gate",
    "sg:city":"Cheltenham",
    "sg:classifiers":[
        {
            "category":"Real Estate",
            "subcategory":"Architect",
            "type":"Services"
        }
    ],
    "sg:phone":"+44 1242 234351",
    "sg:postcode":"GL50 4PJ",
    "sg:province":"Gloucestershire",
    "sg:tags":[
        "architectural"
    ],
    "wof:name":"Architecnics",
    "wof:placetype":"venue"
},
  "geometry": {"coordinates":[-2.0738270283,51.9118728638],"type":"Point"}
}