{
  "type": "Feature",
  "properties": {
    "addr:full":"12-16 Yarm Lane Stockton-on-tees Durham TS18 1ET",
    "addr:housenumber":"12-16",
    "addr:postcode":"ts18 1et",
    "addr:street":"Yarm Lane",
    "iso:country":"GB",
    "sg:address":"12-16 Yarm Lane",
    "sg:city":"Stockton-on-tees",
    "sg:classifiers":[
        {
            "category":"Fast Food",
            "type":"Food & Drink"
        }
    ],
    "sg:phone":"+44 1642 804355",
    "sg:postcode":"TS18 1ET",
    "sg:province":"Durham",
    "sg:tags":[
        "away",
        "take"
    ],
    "wof:name":"Porky's",
    "wof:placetype":"venue"
},
  "geometry": {"coordinates":[-1.313403964,54.5618095398],"type":"Point"}
}