{
  "type": "Feature",
  "properties": {
    "addr:full":"35 Aylesford Street London Greater London SW1V 3RY",
    "addr:housenumber":"35",
    "addr:postcode":"sw1v 3ry",
    "addr:street":"Aylesford Street",
    "iso:country":"GB",
    "sg:address":"35 Aylesford Street",
    "sg:city":"London",
    "sg:classifiers":[
        {
            "category":"Organizations",
            "subcategory":"Membership Organization",
            "type":"Services"
        }
    ],
    "sg:postcode":"SW1V 3RY",
    "sg:province":"Greater London",
    "sg:tags":[
        "club"
    ],
    "wof:name":"Aylesford Street (Management) Ltd",
    "wof:placetype":"venue"
},
  "geometry": {"coordinates":[-0.13377,51.487614],"type":"Point"}
}