{
  "type": "Feature",
  "properties": {
    "addr:full":"248 Regents Park Road London Greater London N3 3HN",
    "addr:housenumber":"248",
    "addr:postcode":"n3 3hn",
    "addr:street":"Regents Park Road",
    "iso:country":"GB",
    "sg:address":"248 Regents Park Road",
    "sg:city":"London",
    "sg:classifiers":[
        {
            "category":"Bars & Pubs",
            "type":"Food & Drink"
        },
        {
            "category":"Community Center",
            "subcategory":"Social",
            "type":"Public Place"
        }
    ],
    "sg:phone":"+44 20 8346 1012",
    "sg:postcode":"N3 3HN",
    "sg:province":"Greater London",
    "sg:tags":[
        "pubs",
        "house",
        "inn",
        "activity"
    ],
    "wof:name":"Queens Head",
    "wof:placetype":"venue"
},
  "geometry": {"coordinates":[-0.197721,51.597111],"type":"Point"}
}