{
  "type": "Feature",
  "properties": {
    "iso:country":"GB",
    "sg:address":"16 Wykeham Road",
    "sg:city":"Hendon",
    "sg:classifiers":[
        {
            "category":"Real Estate",
            "subcategory":"Developer",
            "type":"Services"
        }
    ],
    "sg:phone":"+44 20 8343 0841",
    "sg:postcode":"NW4 2SU",
    "sg:province":"Greater London",
    "sg:tags":[
        "property"
    ],
    "wof:name":"Treo Properties",
    "wof:placetype":"venue"
},
  "geometry": {"coordinates":[-0.225446,51.583279],"type":"Point"}
}