{
  "type": "Feature",
  "properties": {
    "addr:full":"Old Mill Farm, Longhope Gloucester Gloucestershire GL17 0PF",
    "addr:housenumber":"longhope",
    "addr:postcode":"gl17 0pf",
    "iso:country":"GB",
    "sg:address":"Old Mill Farm, Longhope",
    "sg:city":"Gloucester",
    "sg:classifiers":[
        {
            "category":"Building & Trades",
            "subcategory":"Construction",
            "type":"Services"
        }
    ],
    "sg:phone":"+44 1452 830804",
    "sg:postcode":"GL17 0PF",
    "sg:province":"Gloucestershire",
    "sg:tags":[
        "roofing"
    ],
    "wof:name":"HOUSECRAFT BUILDERS",
    "wof:placetype":"venue"
},
  "geometry": {"coordinates":[-2.4516489506,51.8657951355],"type":"Point"}
}