{
  "type": "Feature",
  "properties": {
    "iso:country":"GB",
    "sg:address":"11 Hilland Rise",
    "sg:city":"Bordon",
    "sg:classifiers":[
        {
            "category":"Professional",
            "subcategory":"Engineering",
            "type":"Services"
        }
    ],
    "sg:phone":"+44 1428 712350",
    "sg:postcode":"GU35 8LX",
    "sg:province":"Hampshire",
    "sg:tags":[
        "consulting",
        "engineer"
    ],
    "wof:name":"Enviromental & Oceanographic Ltd",
    "wof:placetype":"venue"
},
  "geometry": {"coordinates":[-0.82001,51.11705],"type":"Point"}
}