{
  "type": "Feature",
  "properties": {
    "iso:country":"GB",
    "sg:address":"Lynn Road Garage, Lynn Road, Grimston",
    "sg:city":"King's Lynn",
    "sg:classifiers":[
        {
            "category":"Autos & Motor Vehicles",
            "subcategory":"Automobile Sales",
            "type":"Retail Goods"
        }
    ],
    "sg:phone":"+44 1485 601212",
    "sg:postcode":"PE32 1AG",
    "sg:province":"Norfolk",
    "sg:tags":[
        "car"
    ],
    "wof:name":"John Wicks Cars",
    "wof:placetype":"venue"
},
  "geometry": {"coordinates":[0.5345399976,52.7751197815],"type":"Point"}
}