{
  "type": "Feature",
  "properties": {
    "iso:country":"GB",
    "sg:address":"2 Teviot Square, Cumbernauld",
    "sg:city":"Glasgow",
    "sg:classifiers":[
        {
            "category":"Organizations",
            "subcategory":"Non-profit Organization",
            "type":"Services"
        }
    ],
    "sg:phone":"+44 1236 453051",
    "sg:postcode":"G67 1NB",
    "sg:province":"Falkirk",
    "sg:tags":[
        "charitable",
        "organisation",
        "voluntary",
        "charity"
    ],
    "wof:name":"British Heart Foundation",
    "wof:placetype":"venue"
},
  "geometry": {"coordinates":[-3.99002,55.947571],"type":"Point"}
}