{
  "type": "Feature",
  "properties": {
    "addr:full":"2b Branch Road, Lower Wortley Leeds West Yorkshire LS12 4RN",
    "addr:housenumber":"2b",
    "addr:postcode":"ls12 4rn",
    "addr:street":"Branch Road",
    "iso:country":"GB",
    "sg:address":"2b Branch Road, Lower Wortley",
    "sg:city":"Leeds",
    "sg:classifiers":[
        {
            "category":"Military Area",
            "subcategory":"Naval Base",
            "type":"Public Place"
        },
        {
            "category":"Retail",
            "subcategory":"Auto Repair",
            "type":"Services"
        }
    ],
    "sg:phone":"+44 113 231 1226",
    "sg:postcode":"LS12 4RN",
    "sg:province":"West Yorkshire",
    "sg:tags":[
        "truck",
        "electrical",
        "van",
        "car",
        "centre"
    ],
    "wof:name":"Wortley Car Electrics",
    "wof:placetype":"venue"
},
  "geometry": {"coordinates":[-1.6029169559,53.7836875916],"type":"Point"}
}