{
  "type": "Feature",
  "properties": {
    "iso:country":"GB",
    "sg:address":"176 Halle Mall, Arndale Centre",
    "sg:city":"Manchester",
    "sg:classifiers":[
        {
            "category":"Shopping",
            "subcategory":"Clothing, Apparel, & Fashions",
            "type":"Retail Goods"
        }
    ],
    "sg:phone":"+44 161 835 1215",
    "sg:postcode":"M4 2EB",
    "sg:province":"Greater Manchester",
    "sg:tags":[
        "lingerie",
        "hosiery"
    ],
    "wof:name":"Swami's Nightwear",
    "wof:placetype":"venue"
},
  "geometry": {"coordinates":[-2.24037,53.485359],"type":"Point"}
}