{
  "type": "Feature",
  "properties": {
    "iso:country":"GB",
    "sg:address":"64 Ashkirk, Dudley",
    "sg:city":"Cramlington",
    "sg:classifiers":[
        {
            "category":"Building & Trades",
            "subcategory":"Construction",
            "type":"Services"
        }
    ],
    "sg:phone":"+44 191 250 0535",
    "sg:postcode":"NE23 7DG",
    "sg:province":"Northumberland",
    "sg:tags":[
        "builder"
    ],
    "wof:name":"George Bush",
    "wof:placetype":"venue"
},
  "geometry": {"coordinates":[-1.589829,55.056244],"type":"Point"}
}