{
  "type": "Feature",
  "properties": {
    "addr:full":"16 Bayford Road Littlehampton West Sussex BN17 5HL",
    "addr:housenumber":"16",
    "addr:postcode":"bn17 5hl",
    "addr:street":"Bayford Road",
    "iso:country":"GB",
    "sg:address":"16 Bayford Road",
    "sg:city":"Littlehampton",
    "sg:classifiers":[
        {
            "category":"Home & Garden",
            "subcategory":"Kitchen Supply",
            "type":"Retail Goods"
        }
    ],
    "sg:phone":"+44 1903 733199",
    "sg:postcode":"BN17 5HL",
    "sg:province":"West Sussex",
    "sg:tags":[
        "glassware",
        "china"
    ],
    "wof:name":"Collectables Ltd.",
    "wof:placetype":"venue"
},
  "geometry": {"coordinates":[-0.541015,50.808151],"type":"Point"}
}