{
  "type": "Feature",
  "properties": {
    "iso:country":"GB",
    "sg:address":"5 Henry Street",
    "sg:city":"Keighley",
    "sg:classifiers":[
        {
            "category":"Health Services",
            "subcategory":"Podiatrist",
            "type":"Services"
        }
    ],
    "sg:phone":"+44 1535 604164",
    "sg:postcode":"BD21 3DR",
    "sg:province":"West Yorkshire",
    "sg:tags":[
        "podiatrists",
        "chiropodist"
    ],
    "wof:name":"J Woollard",
    "wof:placetype":"venue"
},
  "geometry": {"coordinates":[-1.908089,53.868366],"type":"Point"}
}