{
  "type": "Feature",
  "properties": {
    "addr:full":"83 Mill Street Macclesfield Cheshire SK11 6NN",
    "addr:housenumber":"83",
    "addr:postcode":"sk11 6nn",
    "addr:street":"Mill Street",
    "iso:country":"GB",
    "sg:address":"83 Mill Street",
    "sg:city":"Macclesfield",
    "sg:classifiers":[
        {
            "category":"Home & Garden",
            "subcategory":"Carpets & Floor Coverings",
            "type":"Retail Goods"
        }
    ],
    "sg:postcode":"SK11 6NN",
    "sg:province":"Cheshire",
    "sg:tags":[
        "carpets",
        "rug",
        "matting"
    ],
    "wof:name":"Carpet Design",
    "wof:placetype":"venue"
},
  "geometry": {"coordinates":[-2.125894,53.257729],"type":"Point"}
}