{
  "type": "Feature",
  "properties": {
    "addr:full":"4 Cannon Street, Bedminster Bristol City of Bristol BS3 1BN",
    "addr:housenumber":"4",
    "addr:postcode":"bs3 1bn",
    "addr:street":"Cannon Street",
    "iso:country":"GB",
    "sg:address":"4 Cannon Street, Bedminster",
    "sg:city":"Bristol",
    "sg:classifiers":[
        {
            "category":"Shopping",
            "subcategory":"Pharmacy",
            "type":"Retail Goods"
        }
    ],
    "sg:phone":"+44 117 985 3388",
    "sg:postcode":"BS3 1BN",
    "sg:province":"City of Bristol",
    "sg:tags":[
        "pharmacist",
        "chemist"
    ],
    "wof:name":"Pharmacy Plus",
    "wof:placetype":"venue"
},
  "geometry": {"coordinates":[-2.600749,51.441013],"type":"Point"}
}