{
  "type": "Feature",
  "properties": {
    "iso:country":"GB",
    "sg:address":"Innovation Centre, Warwick Technology Park, Gallows Hill",
    "sg:city":"Warwick",
    "sg:classifiers":[
        {
            "category":"Professional",
            "subcategory":"Computer Services",
            "type":"Services"
        }
    ],
    "sg:phone":"+44 1926 623090",
    "sg:postcode":"CV34 6UW",
    "sg:province":"Warwickshire",
    "sg:tags":[
        "system",
        "software"
    ],
    "wof:name":"Focus Business Solution",
    "wof:placetype":"venue"
},
  "geometry": {"coordinates":[-1.566074,52.272785],"type":"Point"}
}