{
  "type": "Feature",
  "properties": {
    "addr:full":"Westoe Rd South Shields Tyne and Wear NE33 4LU",
    "addr:postcode":"ne33 4lu",
    "addr:street":"Westoe Rd",
    "iso:country":"GB",
    "sg:address":"Westoe Rd",
    "sg:city":"South Shields",
    "sg:classifiers":[
        {
            "category":"Place Of Worship",
            "type":"Public Place"
        }
    ],
    "sg:phone":"+44 191 427 9359",
    "sg:postcode":"NE33 4LU",
    "sg:province":"Tyne and Wear",
    "wof:name":"Westoe Road Baptist Church",
    "wof:placetype":"venue"
},
  "geometry": {"coordinates":[-1.42826,54.9925],"type":"Point"}
}