{
  "type": "Feature",
  "properties": {
    "addr:full":"26 Grove Place Bedford Bedfordshire MK40 3JJ",
    "addr:housenumber":"26",
    "addr:postcode":"mk40 3jj",
    "addr:street":"Grove Place",
    "iso:country":"GB",
    "sg:address":"26 Grove Place",
    "sg:city":"Bedford",
    "sg:classifiers":[
        {
            "category":"Professional",
            "subcategory":"Accounting & Tax Preparation",
            "type":"Services"
        }
    ],
    "sg:phone":"+44 1234 352668",
    "sg:postcode":"MK40 3JJ",
    "sg:province":"Bedfordshire",
    "sg:tags":[
        "accountant"
    ],
    "wof:name":"Peter J Monahan & Co",
    "wof:placetype":"venue"
},
  "geometry": {"coordinates":[-0.4612059891,52.1383781433],"type":"Point"}
}