{
  "type": "Feature",
  "properties": {
    "addr:full":"641 Southchurch Road Southend-on-sea Essex SS1 2PN",
    "addr:housenumber":"641",
    "addr:postcode":"ss1 2pn",
    "addr:street":"Southchurch Road",
    "iso:country":"GB",
    "sg:address":"641 Southchurch Road",
    "sg:city":"Southend-on-sea",
    "sg:classifiers":[
        {
            "category":"Retail",
            "subcategory":"Funeral Services",
            "type":"Services"
        }
    ],
    "sg:phone":"+44 1702 467426",
    "sg:postcode":"SS1 2PN",
    "sg:province":"Essex",
    "wof:name":"F P Guiver & Sons Ltd.",
    "wof:placetype":"venue"
},
  "geometry": {"coordinates":[0.7327839732,51.5408287048],"type":"Point"}
}