{
  "type": "Feature",
  "properties": {
    "addr:full":"Barrockstown, Westlinton Carlisle Cumbria CA6 6AE",
    "addr:postcode":"ca6 6ae",
    "iso:country":"GB",
    "sg:address":"Barrockstown, Westlinton",
    "sg:city":"Carlisle",
    "sg:classifiers":[
        {
            "category":"Shopping",
            "subcategory":"Party Supplies",
            "type":"Retail Goods"
        }
    ],
    "sg:phone":"+44 1228 791546",
    "sg:postcode":"CA6 6AE",
    "sg:province":"Cumbria",
    "sg:tags":[
        "inflatables",
        "bouncy",
        "castle"
    ],
    "wof:name":"Barrockstown Castles",
    "wof:placetype":"venue"
},
  "geometry": {"coordinates":[-2.949878931,54.971786499],"type":"Point"}
}