{
  "type": "Feature",
  "properties": {
    "addr:full":"2a Sycamore Walk, Blackburn Bathgate North Lanarkshire EH47 7LQ",
    "addr:housenumber":"2a",
    "addr:postcode":"eh47 7lq",
    "addr:street":"Sycamore Walk;Bathgate",
    "iso:country":"GB",
    "sg:address":"2a Sycamore Walk, Blackburn",
    "sg:city":"Bathgate",
    "sg:classifiers":[
        {
            "category":"Food & Beverages",
            "subcategory":"Supermarket",
            "type":"Retail Goods"
        }
    ],
    "sg:phone":"+44 1506 653748",
    "sg:postcode":"EH47 7LQ",
    "sg:province":"North Lanarkshire",
    "wof:name":"Scotmid Co-Operative Society",
    "wof:placetype":"venue"
},
  "geometry": {"coordinates":[-3.624277,55.875298],"type":"Point"}
}