{
  "type": "Feature",
  "properties": {
    "iso:country":"GB",
    "sg:address":"35 Monmouth Street",
    "sg:city":"London",
    "sg:classifiers":[
        {
            "category":"Shopping",
            "subcategory":"Clothing, Apparel, & Fashions",
            "type":"Retail Goods"
        }
    ],
    "sg:phone":"+44 20 7240 3807",
    "sg:postcode":"WC2H 9DD",
    "sg:province":"Greater London",
    "sg:tags":[
        "dresswear"
    ],
    "wof:name":"The Loft",
    "wof:placetype":"venue"
},
  "geometry": {"coordinates":[-0.1267610043,51.5140724182],"type":"Point"}
}