{
  "type": "Feature",
  "properties": {
    "addr:full":"37 Ropergate Pontefract North Yorkshire WF8 1LG",
    "addr:housenumber":"37",
    "addr:postcode":"wf8 1lg",
    "addr:street":"Ropergate Pontefract",
    "iso:country":"GB",
    "sg:address":"37 Ropergate",
    "sg:city":"Pontefract",
    "sg:classifiers":[
        {
            "category":"Home & Garden",
            "subcategory":"Home Furnishings",
            "type":"Retail Goods"
        },
        {
            "category":"Building & Trades",
            "subcategory":"Construction",
            "type":"Services"
        }
    ],
    "sg:phone":"+44 1977 600296",
    "sg:postcode":"WF8 1LG",
    "sg:province":"North Yorkshire",
    "sg:tags":[
        "installers",
        "planner",
        "kitchen",
        "furnishers"
    ],
    "wof:name":"M S Kitchens & Bedrooms Ltd",
    "wof:placetype":"venue"
},
  "geometry": {"coordinates":[-1.3132740259,53.6898765564],"type":"Point"}
}