{
  "type": "Feature",
  "properties": {
    "addr:full":"Unit 8, 1 2 The Leathermarket, 31 Weston Street London Greater London SE1 3ER",
    "addr:housenumber":"unit;1 2;31",
    "addr:postcode":"se1 3er",
    "addr:street":"The Leathermarket;Weston Street",
    "iso:country":"GB",
    "sg:address":"Unit 8, 1 2 The Leathermarket, 31 Weston Street",
    "sg:city":"London",
    "sg:classifiers":[
        {
            "category":"Arts & Performance",
            "subcategory":"Theater",
            "type":"Entertainment"
        }
    ],
    "sg:phone":"+44 20 7357 7154",
    "sg:postcode":"SE1 3ER",
    "sg:province":"Greater London",
    "sg:tags":[
        "theatre"
    ],
    "wof:name":"Martin Sutherland Productions Ltd.",
    "wof:placetype":"venue"
},
  "geometry": {"coordinates":[-0.08446,51.500389],"type":"Point"}
}