{
  "type": "Feature",
  "properties": {
    "iso:country":"GB",
    "sg:address":"97 Queen Street",
    "sg:city":"Newton Abbot",
    "sg:classifiers":[
        {
            "category":"Personal",
            "subcategory":"Beauty Salon",
            "type":"Services"
        }
    ],
    "sg:phone":"+44 1626 202112",
    "sg:postcode":"TQ12 2BG",
    "sg:province":"Devon",
    "sg:tags":[
        "unisex",
        "hairdresser"
    ],
    "wof:name":"Gershwins Hairdressers",
    "wof:placetype":"venue"
},
  "geometry": {"coordinates":[-3.604583,50.530964],"type":"Point"}
}