{
  "type": "Feature",
  "properties": {
    "addr:full":"Victoria Gardens, China Street Sunderland Tyne and Wear SR2 8RT",
    "addr:postcode":"sr2 8rt",
    "addr:street":"Victoria Gardens China Street",
    "iso:country":"GB",
    "sg:address":"Victoria Gardens, China Street",
    "sg:city":"Sunderland",
    "sg:classifiers":[
        {
            "category":"Bars & Pubs",
            "type":"Food & Drink"
        }
    ],
    "sg:phone":"+44 191 567 5539",
    "sg:postcode":"SR2 8RT",
    "sg:province":"Tyne and Wear",
    "sg:tags":[
        "pubs",
        "inn"
    ],
    "wof:name":"Victoria Gardens",
    "wof:placetype":"venue"
},
  "geometry": {"coordinates":[-1.3745499849,54.8931388855],"type":"Point"}
}