{
  "type": "Feature",
  "properties": {
    "addr:full":"14 Massetts Road Horley Surrey RH6 7DE",
    "addr:housenumber":"14",
    "addr:postcode":"rh6 7de",
    "addr:street":"Massetts Road",
    "iso:country":"GB",
    "sg:address":"14 Massetts Road",
    "sg:city":"Horley",
    "sg:classifiers":[
        {
            "category":"Military Area",
            "subcategory":"Air Force Base",
            "type":"Public Place"
        }
    ],
    "sg:phone":"+44 1293 824466",
    "sg:postcode":"RH6 7DE",
    "sg:province":"Surrey",
    "sg:tags":[
        "taxi",
        "hire",
        "private"
    ],
    "wof:name":"Dna & A 2 B",
    "wof:placetype":"venue"
},
  "geometry": {"coordinates":[-0.1646050066,51.1713371277],"type":"Point"}
}