{
  "type": "Feature",
  "properties": {
    "iso:country":"GB",
    "sg:address":"3 Little Common",
    "sg:city":"Stanmore",
    "sg:classifiers":[
        {
            "category":"Professional",
            "subcategory":"Engineering",
            "type":"Services"
        },
        {
            "category":"Wholesale",
            "subcategory":"Machinery & Supplies",
            "type":"Manufacturing & Wholesale Goods"
        }
    ],
    "sg:phone":"+44 20 8954 7302",
    "sg:postcode":"HA7 3BZ",
    "sg:province":"Greater London",
    "sg:tags":[
        "-",
        "sale",
        "hydraulic",
        "accessory",
        "equipment",
        "electrical",
        "engineer"
    ],
    "wof:name":"Switchgear Maintenance Distribution Ltd",
    "wof:placetype":"venue"
},
  "geometry": {"coordinates":[-0.319068,51.625015],"type":"Point"}
}