{
  "type": "Feature",
  "properties": {
    "iso:country":"GB",
    "sg:address":"7-11 Minerva Rd",
    "sg:city":"Willesden",
    "sg:classifiers":[
        {
            "category":"Organizations",
            "subcategory":"Non-profit Organization",
            "type":"Services"
        }
    ],
    "sg:phone":"+44 20 8357 2529",
    "sg:postcode":"NW10 6HJ",
    "sg:province":"Greater London",
    "sg:tags":[
        "alarm",
        "system"
    ],
    "wof:name":"Total Home Security",
    "wof:placetype":"venue"
},
  "geometry": {"coordinates":[-0.2610409856,51.530002594],"type":"Point"}
}