{
  "type": "Feature",
  "properties": {
    "addr:full":"Unit 3, Netherton Road Wishaw North Lanarkshire ML2 0EQ",
    "addr:housenumber":"unit 3",
    "addr:postcode":"ml2 0eq",
    "addr:street":"Netherton Road",
    "iso:country":"GB",
    "sg:address":"Unit 3, Netherton Road",
    "sg:city":"Wishaw",
    "sg:classifiers":[
        {
            "category":"Wholesale",
            "subcategory":"Machinery & Supplies",
            "type":"Manufacturing & Wholesale Goods"
        }
    ],
    "sg:phone":"+44 1698 381661",
    "sg:postcode":"ML2 0EQ",
    "sg:province":"North Lanarkshire",
    "sg:tags":[
        "industrial",
        "commercial"
    ],
    "wof:name":"Asset Equipment Ltd.",
    "wof:placetype":"venue"
},
  "geometry": {"coordinates":[-3.945189,55.768581],"type":"Point"}
}