{
  "type": "Feature",
  "properties": {
    "addr:full":"Westgate Common Mills, Alderthorpe Rd Wakefield West Yorkshire WF2 9NR",
    "addr:postcode":"wf2 9nr",
    "addr:street":"Westgate Common;Alderthorpe Rd",
    "iso:country":"GB",
    "sg:address":"Westgate Common Mills, Alderthorpe Rd",
    "sg:city":"Wakefield",
    "sg:classifiers":[
        {
            "category":"Shopping",
            "subcategory":"Crafts & Fabrics",
            "type":"Retail Goods"
        }
    ],
    "sg:phone":"+44 1924 362382",
    "sg:postcode":"WF2 9NR",
    "sg:province":"West Yorkshire",
    "sg:tags":[
        "knitwear",
        "yarn"
    ],
    "wof:name":"Thomas Ramsden & Co Ltd",
    "wof:placetype":"venue"
},
  "geometry": {"coordinates":[-1.505359,53.68121],"type":"Point"}
}