{
  "type": "Feature",
  "properties": {
    "addr:full":"Damhead Bridge Of Weir Inverclyde PA11 3BD",
    "addr:postcode":"pa11 3bd",
    "iso:country":"GB",
    "sg:address":"Damhead",
    "sg:city":"Bridge Of Weir",
    "sg:classifiers":[
        {
            "category":"Building & Trades",
            "subcategory":"Construction",
            "type":"Services"
        }
    ],
    "sg:phone":"+44 1505 612784",
    "sg:postcode":"PA11 3BD",
    "sg:province":"Inverclyde",
    "sg:tags":[
        "joiner",
        "carpenter"
    ],
    "wof:name":"James Kerr",
    "wof:placetype":"venue"
},
  "geometry": {"coordinates":[-4.577569,55.856491],"type":"Point"}
}