{
  "type": "Feature",
  "properties": {
    "addr:full":"6 Acorn Business Park, Keighley Road Skipton Lancashire BD23 2UE",
    "addr:housenumber":"6",
    "addr:postcode":"bd23 2ue",
    "addr:street":"Acorn Business Park Keighley Road",
    "iso:country":"GB",
    "sg:address":"6 Acorn Business Park, Keighley Road",
    "sg:city":"Skipton",
    "sg:classifiers":[
        {
            "category":"Education",
            "subcategory":"Special Training",
            "type":"Public Place"
        }
    ],
    "sg:phone":"+44 1535 630101",
    "sg:postcode":"BD23 2UE",
    "sg:province":"Lancashire",
    "sg:tags":[
        "product",
        "centre"
    ],
    "wof:name":"Craven Training Services Ltd.",
    "wof:placetype":"venue"
},
  "geometry": {"coordinates":[-2.0185139179,53.9602012634],"type":"Point"}
}