{
  "type": "Feature",
  "properties": {
    "iso:country":"GB",
    "sg:address":"31 Weston Rd, Long Ashton",
    "sg:city":"Bristol",
    "sg:classifiers":[
        {
            "category":"Fast Food",
            "type":"Food & Drink"
        }
    ],
    "sg:postcode":"BS41 9AA",
    "sg:province":"Somerset",
    "sg:tags":[
        "away",
        "take"
    ],
    "wof:name":"Restaurant Thirty-One",
    "wof:placetype":"venue"
},
  "geometry": {"coordinates":[-2.664405,51.429062],"type":"Point"}
}