{
  "type": "Feature",
  "properties": {
    "addr:full":"Lane End Farm, Upper Littleton Bristol Somerset BS40 8HG",
    "addr:postcode":"bs40 8hg",
    "addr:street":"Upper",
    "iso:country":"GB",
    "sg:address":"Lane End Farm, Upper Littleton",
    "sg:city":"Bristol",
    "sg:classifiers":[
        {
            "category":"Government",
            "subcategory":"Fire Station",
            "type":"Public Place"
        }
    ],
    "sg:postcode":"BS40 8HG",
    "sg:province":"Somerset",
    "sg:tags":[
        "security"
    ],
    "wof:name":"Abrahams Stollard (Bristol) Ltd.",
    "wof:placetype":"venue"
},
  "geometry": {"coordinates":[-2.6431999207,51.3767204285],"type":"Point"}
}