{
  "type": "Feature",
  "properties": {
    "addr:full":"47 Kings Street Oldham Lancashire OL1 3ST",
    "addr:housenumber":"47",
    "addr:postcode":"ol1 3st",
    "addr:street":"Kings Street",
    "iso:country":"GB",
    "sg:address":"47 Kings Street",
    "sg:city":"Oldham",
    "sg:classifiers":[
        {
            "category":"Personal",
            "subcategory":"Beauty Salon",
            "type":"Services"
        }
    ],
    "sg:phone":"+44 161 628 9303",
    "sg:postcode":"OL1 3ST",
    "sg:province":"Lancashire",
    "sg:tags":[
        "unisex",
        "hairdresser"
    ],
    "wof:name":"Chioma by Joe Petrillo",
    "wof:placetype":"venue"
},
  "geometry": {"coordinates":[-2.1165430546,53.5397987366],"type":"Point"}
}