{
  "type": "Feature",
  "properties": {
    "addr:full":"39 Durham Rd Edinburgh City of Edinburgh EH15 1PE",
    "addr:housenumber":"39",
    "addr:postcode":"eh15 1pe",
    "addr:street":"Durham Rd",
    "iso:country":"GB",
    "sg:address":"39 Durham Rd",
    "sg:city":"Edinburgh",
    "sg:classifiers":[
        {
            "category":"Retail",
            "subcategory":"Auto Repair",
            "type":"Services"
        }
    ],
    "sg:phone":"+44 131 669 3465",
    "sg:postcode":"EH15 1PE",
    "sg:province":"City of Edinburgh",
    "sg:tags":[
        "modification",
        "garage"
    ],
    "wof:name":"R Reilly Autos",
    "wof:placetype":"venue"
},
  "geometry": {"coordinates":[-3.1149950027,55.9532737732],"type":"Point"}
}