{
  "type": "Feature",
  "properties": {
    "addr:full":"236 Dunearn Drive Kirkcaldy Fife KY2 6LE",
    "addr:housenumber":"236",
    "addr:postcode":"ky2 6le",
    "addr:street":"Dunearn Drive",
    "iso:country":"GB",
    "sg:address":"236 Dunearn Drive",
    "sg:city":"Kirkcaldy",
    "sg:classifiers":[
        {
            "category":"Cinema",
            "subcategory":"Movie Rental",
            "type":"Entertainment"
        }
    ],
    "sg:phone":"+44 1592 264919",
    "sg:postcode":"KY2 6LE",
    "sg:province":"Fife",
    "sg:tags":[
        "video",
        "library"
    ],
    "wof:name":"Blockbuster Video",
    "wof:placetype":"venue"
},
  "geometry": {"coordinates":[-3.1840291023,56.1254997253],"type":"Point"}
}