{
  "type": "Feature",
  "properties": {
    "iso:country":"GB",
    "sg:address":"Queen St",
    "sg:city":"Louth",
    "sg:classifiers":[
        {
            "category":"Organizations",
            "subcategory":"Membership Organization",
            "type":"Services"
        }
    ],
    "sg:phone":"+44 1507 604504",
    "sg:postcode":"LN11 9AU",
    "sg:province":"Lincolnshire",
    "sg:tags":[
        "club"
    ],
    "wof:name":"Masonic Hall",
    "wof:placetype":"venue"
},
  "geometry": {"coordinates":[-0.002839,53.366634],"type":"Point"}
}