{
  "type": "Feature",
  "properties": {
    "addr:full":"Stowupland Service Station, Thorney Grn Stowmarket Suffolk IP14 4BJ",
    "addr:postcode":"ip14 4bj",
    "addr:street":"Thorney Grn",
    "iso:country":"GB",
    "sg:address":"Stowupland Service Station, Thorney Grn",
    "sg:city":"Stowmarket",
    "sg:classifiers":[
        {
            "category":"Autos & Motor Vehicles",
            "subcategory":"Fuel & Gas Station",
            "type":"Retail Goods"
        }
    ],
    "sg:phone":"+44 1449 612326",
    "sg:postcode":"IP14 4BJ",
    "sg:province":"Suffolk",
    "sg:tags":[
        "petrol",
        "filling"
    ],
    "wof:name":"G C A Leeks & Sons Ltd.",
    "wof:placetype":"venue"
},
  "geometry": {"coordinates":[0.996769011,52.1886253357],"type":"Point"}
}