{
  "type": "Feature",
  "properties": {
    "addr:full":"Reservoir Street Wigan Lancashire WN2 1QN",
    "addr:postcode":"wn2 1qn",
    "addr:street":"Reservoir Street",
    "iso:country":"GB",
    "sg:address":"Reservoir Street",
    "sg:city":"Wigan",
    "sg:classifiers":[
        {
            "category":"Retail",
            "subcategory":"Auto Repair",
            "type":"Services"
        }
    ],
    "sg:phone":"+44 1942 833509",
    "sg:postcode":"WN2 1QN",
    "sg:province":"Lancashire",
    "sg:tags":[
        "modification",
        "garage"
    ],
    "wof:name":"Auto Craft",
    "wof:placetype":"venue"
},
  "geometry": {"coordinates":[-2.5659639835,53.5618438721],"type":"Point"}
}