{
  "type": "Feature",
  "properties": {
    "iso:country":"GB",
    "sg:address":"Windsor Road",
    "sg:city":"Bexhill-on-sea",
    "sg:classifiers":[
        {
            "category":"Shopping",
            "subcategory":"Stationery & Office Supplies",
            "type":"Retail Goods"
        }
    ],
    "sg:phone":"+44 1424 218178",
    "sg:postcode":"TN39 3PB",
    "sg:province":"East Sussex",
    "sg:tags":[
        "printers'"
    ],
    "wof:name":"K W die-Cutting",
    "wof:placetype":"venue"
},
  "geometry": {"coordinates":[0.46782,50.843224],"type":"Point"}
}