{
  "type": "Feature",
  "properties": {
    "iso:country":"GB",
    "sg:address":"Priory Terr, 24 Bromham Rd",
    "sg:city":"Bedford",
    "sg:classifiers":[
        {
            "category":"Professional",
            "subcategory":"Secretarial Services",
            "type":"Services"
        }
    ],
    "sg:postcode":"MK40 2QD",
    "sg:province":"Bedfordshire",
    "wof:name":"Medisecs Limited",
    "wof:placetype":"venue"
},
  "geometry": {"coordinates":[-0.464958,52.138973],"type":"Point"}
}