{
  "type": "Feature",
  "properties": {
    "iso:country":"GB",
    "sg:address":"Bouchers Farm, Waterrow",
    "sg:city":"Taunton",
    "sg:classifiers":[
        {
            "category":"Professional",
            "subcategory":"Management & Consulting",
            "type":"Services"
        }
    ],
    "sg:postcode":"TA4 2AZ",
    "sg:province":"Devon",
    "sg:tags":[
        "consultant",
        "business"
    ],
    "wof:name":"Maitland",
    "wof:placetype":"venue"
},
  "geometry": {"coordinates":[-3.353798,51.020866],"type":"Point"}
}