{
  "type": "Feature",
  "properties": {
    "addr:full":"Wenlock Road South Shields Tyne and Wear NE34 9BA",
    "addr:postcode":"ne34 9ba",
    "addr:street":"Wenlock Road",
    "iso:country":"GB",
    "sg:address":"Wenlock Road",
    "sg:city":"South Shields",
    "sg:classifiers":[
        {
            "category":"Bars & Pubs",
            "type":"Food & Drink"
        }
    ],
    "sg:postcode":"NE34 9BA",
    "sg:province":"Tyne and Wear",
    "sg:tags":[
        "pubs",
        "inn"
    ],
    "wof:name":"The Iron Horse",
    "wof:placetype":"venue"
},
  "geometry": {"coordinates":[-1.455854,54.973137],"type":"Point"}
}