{
  "type": "Feature",
  "properties": {
    "iso:country":"GB",
    "sg:address":"Fore Street",
    "sg:city":"Ipswich",
    "sg:classifiers":[
        {
            "category":"Government",
            "subcategory":"Office",
            "type":"Public Place"
        },
        {
            "category":"Sports & Exercise",
            "subcategory":"Swimming Pool",
            "type":"Entertainment"
        }
    ],
    "sg:phone":"+44 1473 433668",
    "sg:postcode":"IP4 1JZ",
    "sg:province":"Suffolk",
    "sg:tags":[
        "local"
    ],
    "wof:name":"Fore Street Swimming Bath",
    "wof:placetype":"venue"
},
  "geometry": {"coordinates":[1.159343,52.054535],"type":"Point"}
}