{
  "type": "Feature",
  "properties": {
    "iso:country":"GB",
    "sg:address":"4 Clifford Gro",
    "sg:city":"Ashford",
    "sg:classifiers":[
        {
            "category":"Professional",
            "subcategory":"Business Services",
            "type":"Services"
        }
    ],
    "sg:postcode":"TW15 2JT",
    "sg:province":"Greater London",
    "sg:tags":[
        "import",
        "export",
        "agent"
    ],
    "wof:name":"Irvington Enterprises Ltd",
    "wof:placetype":"venue"
},
  "geometry": {"coordinates":[-0.4581089914,51.4344520569],"type":"Point"}
}