{
  "type": "Feature",
  "properties": {
    "addr:full":"19 Market St Loughborough Leicestershire LE11 3EP",
    "addr:housenumber":"19",
    "addr:postcode":"le11 3ep",
    "addr:street":"Market St",
    "iso:country":"GB",
    "sg:address":"19 Market St",
    "sg:city":"Loughborough",
    "sg:classifiers":[
        {
            "category":"Shopping",
            "subcategory":"Comic Books",
            "type":"Retail Goods"
        }
    ],
    "sg:postcode":"LE11 3EP",
    "sg:province":"Leicestershire",
    "sg:tags":[
        "jeweller"
    ],
    "wof:name":"White,E C,",
    "wof:placetype":"venue"
},
  "geometry": {"coordinates":[-1.20893,52.771557],"type":"Point"}
}