{
  "type": "Feature",
  "properties": {
    "iso:country":"GB",
    "sg:address":"Alchris Grange, Home Court Wellingore",
    "sg:city":"Lincoln",
    "sg:classifiers":[
        {
            "category":"Building & Trades",
            "subcategory":"Construction",
            "type":"Services"
        }
    ],
    "sg:postcode":"LN5 0DB",
    "sg:province":"Lincolnshire",
    "sg:tags":[
        "builder"
    ],
    "wof:name":"Chrysalis Homes Ltd.",
    "wof:placetype":"venue"
},
  "geometry": {"coordinates":[-0.5333020091,53.0988540649],"type":"Point"}
}