{
  "type": "Feature",
  "properties": {
    "iso:country":"GB",
    "sg:address":"19 Choyce Close",
    "sg:city":"Atherstone",
    "sg:classifiers":[
        {
            "category":"Professional",
            "type":"Services"
        }
    ],
    "sg:phone":"+44 1827 711511",
    "sg:postcode":"CV9 3AY",
    "sg:province":"Leicestershire",
    "sg:tags":[
        "entertainer"
    ],
    "wof:name":"The Mobile Disco Co",
    "wof:placetype":"venue"
},
  "geometry": {"coordinates":[-1.5458589792,52.5857467651],"type":"Point"}
}