{
  "type": "Feature",
  "properties": {
    "addr:full":"9 Cambridge Dr Ipswich Suffolk IP2 9UY",
    "addr:housenumber":"9",
    "addr:postcode":"ip2 9uy",
    "addr:street":"Cambridge Dr",
    "iso:country":"GB",
    "sg:address":"9 Cambridge Dr",
    "sg:city":"Ipswich",
    "sg:classifiers":[
        {
            "category":"Personal",
            "subcategory":"Barber",
            "type":"Services"
        }
    ],
    "sg:postcode":"IP2 9UY",
    "sg:province":"Suffolk",
    "sg:tags":[
        "men's",
        "hairdresser"
    ],
    "wof:name":"Frank & Lee",
    "wof:placetype":"venue"
},
  "geometry": {"coordinates":[1.1282299757,52.0419502258],"type":"Point"}
}