{
  "type": "Feature",
  "properties": {
    "addr:full":"9 Orchard Close Ruislip Greater London HA4 7LR",
    "addr:housenumber":"9",
    "addr:postcode":"ha4 7lr",
    "addr:street":"Orchard Close",
    "iso:country":"GB",
    "sg:address":"9 Orchard Close",
    "sg:city":"Ruislip",
    "sg:classifiers":[
        {
            "category":"Building & Trades",
            "subcategory":"Construction",
            "type":"Services"
        }
    ],
    "sg:phone":"+44 20 8451 7790",
    "sg:postcode":"HA4 7LR",
    "sg:province":"Greater London",
    "sg:tags":[
        "builder"
    ],
    "wof:name":"Vescon Developments Ltd.",
    "wof:placetype":"venue"
},
  "geometry": {"coordinates":[-0.4362680018,51.5759773254],"type":"Point"}
}