{
  "type": "Feature",
  "properties": {
    "addr:full":"Castle House, Dawson Road Milton Keynes Buckinghamshire MK1 1QT",
    "addr:postcode":"mk1 1qt",
    "addr:street":"Dawson Road",
    "iso:country":"GB",
    "sg:address":"Castle House, Dawson Road",
    "sg:city":"Milton Keynes",
    "sg:classifiers":[
        {
            "category":"Education",
            "subcategory":"Special Training",
            "type":"Public Place"
        }
    ],
    "sg:phone":"+44 1908 362670",
    "sg:postcode":"MK1 1QT",
    "sg:province":"Buckinghamshire",
    "sg:tags":[
        "product",
        "centre"
    ],
    "wof:name":"C I Rathbone",
    "wof:placetype":"venue"
},
  "geometry": {"coordinates":[-0.7227640152,52.0104103088],"type":"Point"}
}