{
  "type": "Feature",
  "properties": {
    "addr:full":"64 Central Drive Blackpool Lancashire FY1 5QB",
    "addr:housenumber":"64",
    "addr:postcode":"fy1 5qb",
    "addr:street":"Central Drive",
    "iso:country":"GB",
    "sg:address":"64 Central Drive",
    "sg:city":"Blackpool",
    "sg:classifiers":[
        {
            "category":"Food & Beverages",
            "subcategory":"Meat & Fish",
            "type":"Retail Goods"
        }
    ],
    "sg:phone":"+44 1253 625079",
    "sg:postcode":"FY1 5QB",
    "sg:province":"Lancashire",
    "sg:tags":[
        "chip"
    ],
    "wof:name":"Stevonia",
    "wof:placetype":"venue"
},
  "geometry": {"coordinates":[-3.051502943,53.813293457],"type":"Point"}
}