{
  "type": "Feature",
  "properties": {
    "iso:country":"GB",
    "sg:address":"21 Clydebank Road, North End",
    "sg:city":"Portsmouth",
    "sg:classifiers":[
        {
            "category":"Home & Garden",
            "subcategory":"Home Furnishings",
            "type":"Retail Goods"
        },
        {
            "category":"Home & Garden",
            "subcategory":"Carpets & Floor Coverings",
            "type":"Retail Goods"
        }
    ],
    "sg:phone":"+44 23 9269 5407",
    "sg:postcode":"PO2 7QG",
    "sg:province":"Hampshire",
    "sg:tags":[
        "fitting",
        "rug",
        "matting",
        "carpets"
    ],
    "wof:name":"S M S Carpet Fittings Specialists",
    "wof:placetype":"venue"
},
  "geometry": {"coordinates":[-1.081026,50.81171],"type":"Point"}
}