{
  "type": "Feature",
  "properties": {
    "addr:full":"37 Larchside Close, Spencers Wood Reading Berkshire RG7 1DS",
    "addr:housenumber":"37",
    "addr:postcode":"rg7 1ds",
    "addr:street":"Larchside Close Spencers Wood",
    "iso:country":"GB",
    "sg:address":"37 Larchside Close, Spencers Wood",
    "sg:city":"Reading",
    "sg:classifiers":[
        {
            "category":"Taxi",
            "type":"Transportation"
        }
    ],
    "sg:phone":"+44 118 988 3935",
    "sg:postcode":"RG7 1DS",
    "sg:province":"Berkshire",
    "sg:tags":[
        "mini",
        "cab"
    ],
    "wof:name":"Gold Wing Executive Cars",
    "wof:placetype":"venue"
},
  "geometry": {"coordinates":[-0.97117,51.393166],"type":"Point"}
}