{
  "type": "Feature",
  "properties": {
    "iso:country":"GB",
    "sg:address":"Fisher Industrial Estate, Wiggenhall Road",
    "sg:city":"Watford",
    "sg:classifiers":[
        {
            "category":"Wholesale",
            "subcategory":"Meat",
            "type":"Manufacturing & Wholesale Goods"
        }
    ],
    "sg:phone":"+44 1923 242338",
    "sg:postcode":"WD18 0FN",
    "sg:province":"Hertfordshire",
    "sg:tags":[
        "-"
    ],
    "wof:name":"Weddel Swift Distribution Ltd.",
    "wof:placetype":"venue"
},
  "geometry": {"coordinates":[-0.39544,51.648548],"type":"Point"}
}