{
  "type": "Feature",
  "properties": {
    "addr:full":"Kimberley Cott, Kirklington Bedale North Yorkshire DL8 2NG",
    "addr:postcode":"dl8 2ng",
    "iso:country":"GB",
    "sg:address":"Kimberley Cott, Kirklington",
    "sg:city":"Bedale",
    "sg:classifiers":[
        {
            "category":"Building & Trades",
            "subcategory":"Construction",
            "type":"Services"
        }
    ],
    "sg:postcode":"DL8 2NG",
    "sg:province":"North Yorkshire",
    "sg:tags":[
        "joinery"
    ],
    "wof:name":"Falshaw H & Y Joinery & Building",
    "wof:placetype":"venue"
},
  "geometry": {"coordinates":[-1.5120830536,54.2241210938],"type":"Point"}
}