{
  "type": "Feature",
  "properties": {
    "addr:full":"9 Kemelstowe Crescent, Hayley Grn Halesowen West Midlands B63 1ES",
    "addr:housenumber":"9",
    "addr:postcode":"b63 1es",
    "addr:street":"Kemelstowe Crescent Hayley Grn",
    "iso:country":"GB",
    "sg:address":"9 Kemelstowe Crescent, Hayley Grn",
    "sg:city":"Halesowen",
    "sg:classifiers":[
        {
            "category":"Professional",
            "subcategory":"Engineering",
            "type":"Services"
        }
    ],
    "sg:postcode":"B63 1ES",
    "sg:province":"West Midlands",
    "sg:tags":[
        "gas",
        "engineer"
    ],
    "wof:name":"P F Margetts & Sons",
    "wof:placetype":"venue"
},
  "geometry": {"coordinates":[-2.083586,52.432163],"type":"Point"}
}