{
  "type": "Feature",
  "properties": {
    "addr:full":"14 Kennet Rd Dartford Kent DA1 4SD",
    "addr:housenumber":"14",
    "addr:postcode":"da1 4sd",
    "addr:street":"Kennet Rd",
    "iso:country":"GB",
    "sg:address":"14 Kennet Rd",
    "sg:city":"Dartford",
    "sg:classifiers":[
        {
            "category":"Building & Trades",
            "subcategory":"Electrical",
            "type":"Services"
        }
    ],
    "sg:phone":"+44 1322 523298",
    "sg:postcode":"DA1 4SD",
    "sg:province":"Kent",
    "sg:tags":[
        "heating"
    ],
    "wof:name":"R & B Star",
    "wof:placetype":"venue"
},
  "geometry": {"coordinates":[0.19472,51.461586],"type":"Point"}
}