{
  "type": "Feature",
  "properties": {
    "iso:country":"GB",
    "sg:address":"Abbey Grove Farm, Randles La",
    "sg:city":"Stoke On Trent",
    "sg:classifiers":[
        {
            "category":"Shopping",
            "subcategory":"Discount & Variety Stores",
            "type":"Retail Goods"
        }
    ],
    "sg:phone":"+44 1782 550982",
    "sg:postcode":"ST9 0AT",
    "sg:province":"Staffordshire",
    "sg:tags":[
        "cleaning",
        "supply"
    ],
    "wof:name":"James Dodd",
    "wof:placetype":"venue"
},
  "geometry": {"coordinates":[-2.0528199673,53.0363616943],"type":"Point"}
}