{
  "type": "Feature",
  "properties": {
    "addr:full":"73 High St Billericay Essex CM12 9AS",
    "addr:housenumber":"73",
    "addr:postcode":"cm12 9as",
    "addr:street":"High St",
    "iso:country":"GB",
    "sg:address":"73 High St",
    "sg:city":"Billericay",
    "sg:classifiers":[
        {
            "category":"Place Of Worship",
            "type":"Public Place"
        }
    ],
    "sg:phone":"+44 1277 211353",
    "sg:postcode":"CM12 9AS",
    "sg:province":"Essex",
    "wof:name":"Billericay Spiritual Centre",
    "wof:placetype":"venue"
},
  "geometry": {"coordinates":[0.417629987,51.6257896423],"type":"Point"}
}