{
  "type": "Feature",
  "properties": {
    "addr:full":"26 Kingsmead Avenue Cheltenham Gloucestershire GL51 0AZ",
    "addr:housenumber":"26",
    "addr:postcode":"gl51 0az",
    "addr:street":"Kingsmead Avenue",
    "iso:country":"GB",
    "sg:address":"26 Kingsmead Avenue",
    "sg:city":"Cheltenham",
    "sg:classifiers":[
        {
            "category":"Wholesale",
            "subcategory":"Scrap",
            "type":"Manufacturing & Wholesale Goods"
        }
    ],
    "sg:phone":"+44 1242 702674",
    "sg:postcode":"GL51 0AZ",
    "sg:province":"Gloucestershire",
    "sg:tags":[
        "car",
        "breaker",
        "dismantlers"
    ],
    "wof:name":"Only Opels",
    "wof:placetype":"venue"
},
  "geometry": {"coordinates":[-2.1083779335,51.9105224609],"type":"Point"}
}