{
  "type": "Feature",
  "properties": {
    "addr:full":"185 Broad Street Glasgow Glasgow City G40 2QR",
    "addr:housenumber":"185",
    "addr:postcode":"g40 2qr",
    "addr:street":"Broad Street",
    "iso:country":"GB",
    "sg:address":"185 Broad Street",
    "sg:city":"Glasgow",
    "sg:classifiers":[
        {
            "category":"Travel",
            "subcategory":"Bed & Breakfast",
            "type":"Entertainment"
        }
    ],
    "sg:phone":"+44 141 554 6272",
    "sg:postcode":"G40 2QR",
    "sg:province":"Glasgow City",
    "sg:tags":[
        "ladder"
    ],
    "wof:name":"Clow Group Ltd.",
    "wof:placetype":"venue"
},
  "geometry": {"coordinates":[-4.221109,55.851402],"type":"Point"}
}