{
  "type": "Feature",
  "properties": {
    "addr:full":"Grange La, Kimberworth Rotherham South Yorkshire S61 2SQ",
    "addr:postcode":"s61 2sq",
    "addr:street":"Grange;South",
    "iso:country":"GB",
    "sg:address":"Grange La, Kimberworth",
    "sg:city":"Rotherham",
    "sg:classifiers":[
        {
            "category":"Insurance",
            "subcategory":"Insurance Agent",
            "type":"Services"
        },
        {
            "category":"Transit Center",
            "subcategory":"Passenger",
            "type":"Transportation"
        }
    ],
    "sg:phone":"+44 114 246 8898",
    "sg:postcode":"S61 2SQ",
    "sg:province":"South Yorkshire",
    "sg:tags":[
        "boarding",
        "kennel",
        "catteries"
    ],
    "wof:name":"Deansgate",
    "wof:placetype":"venue"
},
  "geometry": {"coordinates":[-1.396691,53.434784],"type":"Point"}
}