{
  "type": "Feature",
  "properties": {
    "iso:country":"GB",
    "sg:address":"Spalding Road, Pinchbeck",
    "sg:city":"Spalding",
    "sg:classifiers":[
        {
            "category":"Professional",
            "subcategory":"Advertising",
            "type":"Services"
        },
        {
            "category":"Wholesale",
            "subcategory":"Machinery & Supplies",
            "type":"Manufacturing & Wholesale Goods"
        }
    ],
    "sg:phone":"+44 1775 723764",
    "sg:postcode":"PE11 3UE",
    "sg:province":"Lincolnshire",
    "sg:tags":[
        "pump",
        "agency"
    ],
    "wof:name":"Glen Farrow (U K) Ltd.",
    "wof:placetype":"venue"
},
  "geometry": {"coordinates":[-0.161251,52.816528],"type":"Point"}
}