{
  "type": "Feature",
  "properties": {
    "iso:country":"GB",
    "sg:address":"5 School Lane, Quedgeley",
    "sg:city":"Gloucester",
    "sg:classifiers":[
        {
            "category":"Real Estate",
            "subcategory":"Real Estate Agent",
            "type":"Services"
        }
    ],
    "sg:phone":"+44 1452 722025",
    "sg:postcode":"GL2 4PJ",
    "sg:province":"Gloucestershire",
    "wof:name":"Taylors Estate Agents Ltd",
    "wof:placetype":"venue"
},
  "geometry": {"coordinates":[-2.27812,51.82568],"type":"Point"}
}