{
  "type": "Feature",
  "properties": {
    "addr:full":"Unit 2 Birmingham West Midlands B8 2HQ",
    "addr:housenumber":"unit 2",
    "addr:postcode":"b8 2hq",
    "iso:country":"GB",
    "sg:address":"Unit 2",
    "sg:city":"Birmingham",
    "sg:classifiers":[
        {
            "category":"Sports & Exercise",
            "subcategory":"Tennis Court",
            "type":"Entertainment"
        }
    ],
    "sg:phone":"+44 121 328 3026",
    "sg:postcode":"B8 2HQ",
    "sg:province":"West Midlands",
    "sg:tags":[
        "breakdown",
        "recovery"
    ],
    "wof:name":"H D Recovery",
    "wof:placetype":"venue"
},
  "geometry": {"coordinates":[-1.8333790302,52.4952201843],"type":"Point"}
}