{
  "type": "Feature",
  "properties": {
    "addr:full":"66 Friar St Droitwich Worcestershire WR9 8EF",
    "addr:housenumber":"66",
    "addr:postcode":"wr9 8ef",
    "addr:street":"Friar St",
    "iso:country":"GB",
    "sg:address":"66 Friar St",
    "sg:city":"Droitwich",
    "sg:classifiers":[
        {
            "category":"Real Estate",
            "subcategory":"Real Estate Agent",
            "type":"Services"
        }
    ],
    "sg:phone":"+44 1905 771785",
    "sg:postcode":"WR9 8EF",
    "sg:province":"Worcestershire",
    "wof:name":"Lumsdons Estate Agents",
    "wof:placetype":"venue"
},
  "geometry": {"coordinates":[-2.1488530636,52.268573761],"type":"Point"}
}