{
  "type": "Feature",
  "properties": {
    "iso:country":"GB",
    "sg:address":"Unit 4, Midlands Distribution Centre, Markfield Road",
    "sg:city":"Leicester",
    "sg:classifiers":[
        {
            "category":"Government",
            "subcategory":"Post Office",
            "type":"Public Place"
        }
    ],
    "sg:phone":"+44 1530 249999",
    "sg:postcode":"LE6 0SL",
    "sg:province":"Leicestershire",
    "sg:tags":[
        "messenger",
        "courier"
    ],
    "wof:name":"Hardings Transport Ltd.",
    "wof:placetype":"venue"
},
  "geometry": {"coordinates":[-1.2432899475,52.67578125],"type":"Point"}
}