{
  "type": "Feature",
  "properties": {
    "addr:full":"59 Creek Road, Greenwich London Greater London SE8 3BU",
    "addr:housenumber":"59",
    "addr:postcode":"se8 3bu",
    "addr:street":"Creek Road",
    "iso:country":"GB",
    "sg:address":"59 Creek Road, Greenwich",
    "sg:city":"London",
    "sg:classifiers":[
        {
            "category":"Bus Charters",
            "type":"Transportation"
        }
    ],
    "sg:postcode":"SE8 3BU",
    "sg:province":"Greater London",
    "sg:tags":[
        "coach"
    ],
    "wof:name":"Leke Salis & Co  Ltd",
    "wof:placetype":"venue"
},
  "geometry": {"coordinates":[-0.0233360007,51.4808807373],"type":"Point"}
}