{
  "type": "Feature",
  "properties": {
    "addr:full":"Crest Mills Huddersfield West Yorkshire HD3 4EA",
    "addr:postcode":"hd3 4ea",
    "addr:street":"Crest;West",
    "iso:country":"GB",
    "sg:address":"Crest Mills",
    "sg:city":"Huddersfield",
    "sg:classifiers":[
        {
            "category":"Home & Garden",
            "subcategory":"Home Furnishings",
            "type":"Retail Goods"
        }
    ],
    "sg:phone":"+44 1484 654080",
    "sg:postcode":"HD3 4EA",
    "sg:province":"West Yorkshire",
    "sg:tags":[
        "pipe",
        "fitting"
    ],
    "wof:name":"Premier Pipeline Supplies Ltd.",
    "wof:placetype":"venue"
},
  "geometry": {"coordinates":[-1.82413,53.645321],"type":"Point"}
}