{
  "type": "Feature",
  "properties": {
    "iso:country":"GB",
    "sg:address":"50 Cheap St",
    "sg:city":"Sherborne",
    "sg:classifiers":[
        {
            "category":"Banks & Credit Unions",
            "subcategory":"Bank",
            "type":"Services"
        }
    ],
    "sg:phone":"+44 1935 424671",
    "sg:postcode":"DT9 3BH",
    "sg:province":"Dorset",
    "wof:name":"NatWest",
    "wof:placetype":"venue"
},
  "geometry": {"coordinates":[-2.516093,50.948174],"type":"Point"}
}