{
  "type": "Feature",
  "properties": {
    "addr:full":"51 Cambridge Place Cambridge Cambridgeshire CB2 1NS",
    "addr:housenumber":"51",
    "addr:postcode":"cb2 1ns",
    "addr:street":"Cambridge Place",
    "iso:country":"GB",
    "sg:address":"51 Cambridge Place",
    "sg:city":"Cambridge",
    "sg:classifiers":[
        {
            "category":"Professional",
            "subcategory":"Computer Services",
            "type":"Services"
        }
    ],
    "sg:phone":"+44 1223 505062",
    "sg:postcode":"CB2 1NS",
    "sg:province":"Cambridgeshire",
    "sg:tags":[
        "system",
        "software"
    ],
    "wof:name":"Retec",
    "wof:placetype":"venue"
},
  "geometry": {"coordinates":[0.1299200058,52.1969146729],"type":"Point"}
}