{
  "type": "Feature",
  "properties": {
    "iso:country":"GB",
    "sg:address":"27 Rossall Lane",
    "sg:city":"Fleetwood",
    "sg:classifiers":[
        {
            "category":"Building & Trades",
            "subcategory":"Plumbing",
            "type":"Services"
        }
    ],
    "sg:phone":"+44 1253 873589",
    "sg:postcode":"FY7 8JP",
    "sg:province":"Lancashire",
    "sg:tags":[
        "plumber",
        "heating"
    ],
    "wof:name":"M A Edwards",
    "wof:placetype":"venue"
},
  "geometry": {"coordinates":[-3.03666,53.897781],"type":"Point"}
}