{
  "type": "Feature",
  "properties": {
    "iso:country":"GB",
    "sg:address":"63 Imperial Road, Beeston",
    "sg:city":"Nottingham",
    "sg:classifiers":[
        {
            "category":"Professional",
            "subcategory":"Art Services",
            "type":"Services"
        }
    ],
    "sg:postcode":"NG9 1FB",
    "sg:province":"Nottinghamshire",
    "sg:tags":[
        "model",
        "maker"
    ],
    "wof:name":"Tinderbox Fine Modelmaking",
    "wof:placetype":"venue"
},
  "geometry": {"coordinates":[-1.2223240137,52.9252662659],"type":"Point"}
}