{
  "type": "Feature",
  "properties": {
    "addr:full":"Unit 36b Crayford Indstl Est, Swaisland, Crayford Dartford Kent DA1 4HS",
    "addr:housenumber":"unit 36b",
    "addr:postcode":"da1 4hs",
    "addr:street":"Crayford Indstl Est Swaisland Crayford",
    "iso:country":"GB",
    "sg:address":"Unit 36b Crayford Indstl Est, Swaisland, Crayford",
    "sg:city":"Dartford",
    "sg:classifiers":[
        {
            "category":"Retail",
            "subcategory":"Auto Repair",
            "type":"Services"
        }
    ],
    "sg:postcode":"DA1 4HS",
    "sg:province":"Kent",
    "sg:tags":[
        "modification",
        "garage"
    ],
    "wof:name":"Weskin,Andy,",
    "wof:placetype":"venue"
},
  "geometry": {"coordinates":[0.177534,51.452374],"type":"Point"}
}