{
  "type": "Feature",
  "properties": {
    "addr:full":"51 Church St Peterborough Cambridgeshire PE2 8HF",
    "addr:housenumber":"51",
    "addr:postcode":"pe2 8hf",
    "addr:street":"Church St",
    "iso:country":"GB",
    "sg:address":"51 Church St",
    "sg:city":"Peterborough",
    "sg:classifiers":[
        {
            "category":"Building & Trades",
            "subcategory":"Equipment Rental",
            "type":"Services"
        }
    ],
    "sg:phone":"+44 1733 343931",
    "sg:postcode":"PE2 8HF",
    "sg:province":"Cambridgeshire",
    "sg:tags":[
        "hire",
        "centre"
    ],
    "wof:name":"Speedy Hire Centres",
    "wof:placetype":"venue"
},
  "geometry": {"coordinates":[-0.230623,52.5602],"type":"Point"}
}