{
  "type": "Feature",
  "properties": {
    "addr:full":"593 Davidson Rd Croydon Surrey CR0 6DU",
    "addr:housenumber":"593",
    "addr:postcode":"cr0 6du",
    "addr:street":"Davidson Rd",
    "iso:country":"GB",
    "sg:address":"593 Davidson Rd",
    "sg:city":"Croydon",
    "sg:classifiers":[
        {
            "category":"Organizations",
            "subcategory":"Non-profit Organization",
            "type":"Services"
        }
    ],
    "sg:phone":"+44 20 8656 8898",
    "sg:postcode":"CR0 6DU",
    "sg:province":"Surrey",
    "sg:tags":[
        "alarm",
        "system"
    ],
    "wof:name":"Knight Installations",
    "wof:placetype":"venue"
},
  "geometry": {"coordinates":[-0.076793,51.39122],"type":"Point"}
}