{
  "type": "Feature",
  "properties": {
    "iso:country":"GB",
    "sg:address":"54a Station Road, Chadwell Heath",
    "sg:city":"Romford",
    "sg:classifiers":[
        {
            "category":"Real Estate",
            "subcategory":"Real Estate Operator",
            "type":"Services"
        }
    ],
    "sg:phone":"+44 20 8599 2000",
    "sg:postcode":"RM6 4BU",
    "sg:province":"Essex",
    "sg:tags":[
        "letting",
        "agent"
    ],
    "wof:name":"Woodhouse St. John",
    "wof:placetype":"venue"
},
  "geometry": {"coordinates":[0.129675,51.567909],"type":"Point"}
}