{
  "type": "Feature",
  "properties": {
    "addr:full":"23 Garrick Street London Greater London WC2E 9BN",
    "addr:housenumber":"23",
    "addr:postcode":"wc2e 9bn",
    "addr:street":"Garrick Street",
    "iso:country":"GB",
    "sg:address":"23 Garrick Street",
    "sg:city":"London",
    "sg:classifiers":[
        {
            "category":"Organizations",
            "subcategory":"Non-profit Organization",
            "type":"Services"
        }
    ],
    "sg:phone":"+44 20 7379 8477",
    "sg:postcode":"WC2E 9BN",
    "sg:province":"Greater London",
    "sg:tags":[
        "organisation",
        "voluntary",
        "charity"
    ],
    "wof:name":"Young Concert Artists Trust",
    "wof:placetype":"venue"
},
  "geometry": {"coordinates":[-0.1267309934,51.5118484497],"type":"Point"}
}