{
  "type": "Feature",
  "properties": {
    "addr:full":"21b Eastcheap Letchworth Hertfordshire SG6 3DA",
    "addr:housenumber":"21b",
    "addr:postcode":"sg6 3da",
    "addr:street":"Eastcheap Letchworth",
    "iso:country":"GB",
    "sg:address":"21b Eastcheap",
    "sg:city":"Letchworth",
    "sg:classifiers":[
        {
            "category":"Food & Beverages",
            "subcategory":"Bakery",
            "type":"Retail Goods"
        }
    ],
    "sg:phone":"+44 1462 482224",
    "sg:postcode":"SG6 3DA",
    "sg:province":"Hertfordshire",
    "sg:tags":[
        "pizza"
    ],
    "wof:name":"Pizza Hut",
    "wof:placetype":"venue"
},
  "geometry": {"coordinates":[-0.2286480069,51.9782867432],"type":"Point"}
}