{
  "type": "Feature",
  "properties": {
    "addr:full":"Unit 1 Link Business Pk, St. James Rd Brackley Buckinghamshire NN13 7XY",
    "addr:housenumber":"unit 1",
    "addr:postcode":"nn13 7xy",
    "addr:street":"Link Business Pk St. James Rd",
    "iso:country":"GB",
    "sg:address":"Unit 1 Link Business Pk, St. James Rd",
    "sg:city":"Brackley",
    "sg:classifiers":[
        {
            "category":"Utilities",
            "subcategory":"Mobile Phone",
            "type":"Services"
        }
    ],
    "sg:phone":"+44 1280 700010",
    "sg:postcode":"NN13 7XY",
    "sg:province":"Buckinghamshire",
    "sg:tags":[
        "battery",
        "supplier"
    ],
    "wof:name":"Power Providers (U K) Ltd",
    "wof:placetype":"venue"
},
  "geometry": {"coordinates":[-1.1492660046,52.0273208618],"type":"Point"}
}