{
  "type": "Feature",
  "properties": {
    "iso:country":"GB",
    "sg:address":"Hubie St Warehouse",
    "sg:city":"Burnley",
    "sg:classifiers":[
        {
            "category":"Professional",
            "subcategory":"Business Services",
            "type":"Services"
        },
        {
            "category":"Manufacturing",
            "subcategory":"Lumber",
            "type":"Manufacturing & Wholesale Goods"
        }
    ],
    "sg:postcode":"BB12 0BD",
    "sg:province":"Lancashire",
    "sg:tags":[
        "merchants",
        "stockist",
        "importer",
        "agent",
        "tile",
        "timber"
    ],
    "wof:name":"Strictly Tiles",
    "wof:placetype":"venue"
},
  "geometry": {"coordinates":[-2.2496190071,53.7971191406],"type":"Point"}
}