{
  "type": "Feature",
  "properties": {
    "iso:country":"GB",
    "sg:address":"7c Merkins Avenue",
    "sg:city":"Dumbarton",
    "sg:classifiers":[
        {
            "category":"Professional",
            "subcategory":"Business Services",
            "type":"Services"
        }
    ],
    "sg:phone":"+44 1389 767858",
    "sg:postcode":"G82 3EB",
    "sg:province":"Argyll and Bute",
    "sg:tags":[
        "bookmaker"
    ],
    "wof:name":"Robertson Bookmakers",
    "wof:placetype":"venue"
},
  "geometry": {"coordinates":[-4.5533308983,55.9577407837],"type":"Point"}
}