{
  "type": "Feature",
  "properties": {
    "addr:full":"Unit 11 The Mall, High Street, Kensington London Greater London W8 5SF",
    "addr:housenumber":"unit 11",
    "addr:postcode":"w8 5sf",
    "addr:street":"The Mall High Street",
    "iso:country":"GB",
    "sg:address":"Unit 11 The Mall, High Street, Kensington",
    "sg:city":"London",
    "sg:classifiers":[
        {
            "category":"Shopping",
            "subcategory":"Clothing, Apparel, & Fashions",
            "type":"Retail Goods"
        }
    ],
    "sg:phone":"+44 20 7937 5168",
    "sg:postcode":"W8 5SF",
    "sg:province":"Greater London",
    "sg:tags":[
        "tie",
        "neckwear"
    ],
    "wof:name":"Tie Rack",
    "wof:placetype":"venue"
},
  "geometry": {"coordinates":[-0.2712039948,51.459197998],"type":"Point"}
}