{
  "type": "Feature",
  "properties": {
    "addr:full":"14 Ludford Drive, Stirchley Park Telford Shropshire TF3 1RD",
    "addr:housenumber":"14",
    "addr:postcode":"tf3 1rd",
    "addr:street":"Ludford Drive",
    "iso:country":"GB",
    "sg:address":"14 Ludford Drive, Stirchley Park",
    "sg:city":"Telford",
    "sg:classifiers":[
        {
            "category":"Professional",
            "subcategory":"Accounting & Tax Preparation",
            "type":"Services"
        }
    ],
    "sg:postcode":"TF3 1RD",
    "sg:province":"Shropshire",
    "sg:tags":[
        "accountant"
    ],
    "wof:name":"C F Bayliss",
    "wof:placetype":"venue"
},
  "geometry": {"coordinates":[-2.442526,52.655231],"type":"Point"}
}