{
  "type": "Feature",
  "properties": {
    "addr:full":"36 George Street Luton Bedfordshire LU1 2AE",
    "addr:housenumber":"36",
    "addr:postcode":"lu1 2ae",
    "addr:street":"George Street",
    "iso:country":"GB",
    "sg:address":"36 George Street",
    "sg:city":"Luton",
    "sg:classifiers":[
        {
            "category":"Shopping",
            "subcategory":"Books",
            "type":"Retail Goods"
        }
    ],
    "sg:phone":"+44 1582 486999",
    "sg:postcode":"LU1 2AE",
    "sg:province":"Bedfordshire",
    "sg:tags":[
        "bookseller"
    ],
    "wof:name":"Hammicks Bookshop",
    "wof:placetype":"venue"
},
  "geometry": {"coordinates":[-0.4153229892,51.8787078857],"type":"Point"}
}