{
  "type": "Feature",
  "properties": {
    "addr:full":"Glade Works Potters Bar Greater London EN6 4RY",
    "addr:postcode":"en6 4ry",
    "iso:country":"GB",
    "sg:address":"Glade Works",
    "sg:city":"Potters Bar",
    "sg:classifiers":[
        {
            "category":"Shopping",
            "subcategory":"Stationery & Office Supplies",
            "type":"Retail Goods"
        }
    ],
    "sg:phone":"+44 1707 876762",
    "sg:postcode":"EN6 4RY",
    "sg:province":"Greater London",
    "sg:tags":[
        "printers'"
    ],
    "wof:name":"Cuffley Cutters Ltd.",
    "wof:placetype":"venue"
},
  "geometry": {"coordinates":[-0.1784240007,51.6930122375],"type":"Point"}
}