{
  "type": "Feature",
  "properties": {
    "iso:country":"GB",
    "sg:address":"189 Brunsfield Way",
    "sg:city":"Edinburgh",
    "sg:classifiers":[
        {
            "category":"Health Services",
            "subcategory":"Podiatrist",
            "type":"Services"
        }
    ],
    "sg:postcode":"EH10 4AY",
    "sg:province":"City of Edinburgh",
    "sg:tags":[
        "podiatrists",
        "chiropodist"
    ],
    "wof:name":"Eric J Parker",
    "wof:placetype":"venue"
},
  "geometry": {"coordinates":[-3.209862,55.936008],"type":"Point"}
}