{
  "type": "Feature",
  "properties": {
    "addr:full":"42 Parsons Heath Colchester Essex CO4 3HY",
    "addr:housenumber":"42",
    "addr:postcode":"co4 3hy",
    "addr:street":"Parsons Heath Colchester",
    "iso:country":"GB",
    "sg:address":"42 Parsons Heath",
    "sg:city":"Colchester",
    "sg:classifiers":[
        {
            "category":"Professional",
            "subcategory":"Printing & Photocopies",
            "type":"Services"
        }
    ],
    "sg:postcode":"CO4 3HY",
    "sg:province":"Essex",
    "sg:tags":[
        "top",
        "publishing",
        "desk"
    ],
    "wof:name":"K M L Systems",
    "wof:placetype":"venue"
},
  "geometry": {"coordinates":[0.939316988,51.9020423889],"type":"Point"}
}