{
  "type": "Feature",
  "properties": {
    "addr:full":"Springwater Farm, Hammer Lane, Vines Cross Heathfield East Sussex TN21 9HE",
    "addr:postcode":"tn21 9he",
    "addr:street":"Springwater;Hammer Lane Vines",
    "iso:country":"GB",
    "sg:address":"Springwater Farm, Hammer Lane, Vines Cross",
    "sg:city":"Heathfield",
    "sg:classifiers":[
        {
            "category":"Farming",
            "subcategory":"Livestock Farm",
            "type":"Manufacturing & Wholesale Goods"
        }
    ],
    "sg:postcode":"TN21 9HE",
    "sg:province":"East Sussex",
    "sg:tags":[
        "others"
    ],
    "wof:name":"E & G M Moss",
    "wof:placetype":"venue"
},
  "geometry": {"coordinates":[0.26643,50.937366],"type":"Point"}
}