{
  "type": "Feature",
  "properties": {
    "iso:country":"GB",
    "sg:address":"21 Victoria Road, Draycott",
    "sg:city":"Derby",
    "sg:classifiers":[
        {
            "category":"Shopping",
            "subcategory":"News",
            "type":"Retail Goods"
        }
    ],
    "sg:phone":"+44 1332 872356",
    "sg:postcode":"DE72 3PS",
    "sg:province":"Derbyshire",
    "sg:tags":[
        "newsagent"
    ],
    "wof:name":"Draycott News",
    "wof:placetype":"venue"
},
  "geometry": {"coordinates":[-1.341389,52.894489],"type":"Point"}
}