{
  "type": "Feature",
  "properties": {
    "addr:full":"Victoria Road Aldeburgh Suffolk IP15 5EJ",
    "addr:postcode":"ip15 5ej",
    "addr:street":"Victoria Road",
    "iso:country":"GB",
    "sg:address":"Victoria Road",
    "sg:city":"Aldeburgh",
    "sg:classifiers":[
        {
            "category":"Recreation",
            "subcategory":"Dog Park",
            "type":"Entertainment"
        }
    ],
    "sg:postcode":"IP15 5EJ",
    "sg:province":"Suffolk",
    "wof:name":"Pet Perfection",
    "wof:placetype":"venue"
},
  "geometry": {"coordinates":[1.5936009884,52.1566581726],"type":"Point"}
}