{
  "type": "Feature",
  "properties": {
    "addr:full":"57 Victoria Street, Dyce Aberdeen Aberdeen City AB21 7DX",
    "addr:housenumber":"57",
    "addr:postcode":"ab21 7dx",
    "addr:street":"Victoria Street",
    "iso:country":"GB",
    "sg:address":"57 Victoria Street, Dyce",
    "sg:city":"Aberdeen",
    "sg:classifiers":[
        {
            "category":"Building & Trades",
            "subcategory":"Construction",
            "type":"Services"
        }
    ],
    "sg:phone":"+44 1224 772277",
    "sg:postcode":"AB21 7DX",
    "sg:province":"Aberdeen City",
    "sg:tags":[
        "heating",
        "contractor"
    ],
    "wof:name":"Acorn Heating & Ventilation",
    "wof:placetype":"venue"
},
  "geometry": {"coordinates":[-2.1886489391,57.2084732056],"type":"Point"}
}