{
  "type": "Feature",
  "properties": {
    "addr:full":"High St, Wherwell Andover Hampshire SP11 7JG",
    "addr:postcode":"sp11 7jg",
    "addr:street":"High St",
    "iso:country":"GB",
    "sg:address":"High St, Wherwell",
    "sg:city":"Andover",
    "sg:classifiers":[
        {
            "category":"Shopping",
            "subcategory":"Department Store",
            "type":"Retail Goods"
        }
    ],
    "sg:postcode":"SP11 7JG",
    "sg:province":"Hampshire",
    "wof:name":"20TH Century Stores",
    "wof:placetype":"venue"
},
  "geometry": {"coordinates":[-1.4447779655,51.1662864685],"type":"Point"}
}