{
  "type": "Feature",
  "properties": {
    "iso:country":"GB",
    "sg:address":"Parkhead Hall, 349 Ecclesall Road South",
    "sg:city":"Sheffield",
    "sg:classifiers":[
        {
            "category":"Shopping",
            "subcategory":"Pharmacy",
            "type":"Retail Goods"
        }
    ],
    "sg:postcode":"S11 9PX",
    "sg:province":"Derbyshire",
    "sg:tags":[
        "toiletry"
    ],
    "wof:name":"French & Scott Ltd",
    "wof:placetype":"venue"
},
  "geometry": {"coordinates":[-1.464544,53.38311],"type":"Point"}
}