{
  "type": "Feature",
  "properties": {
    "iso:country":"GB",
    "sg:address":"17-21 High Street, Ruddington",
    "sg:city":"Nottingham",
    "sg:classifiers":[
        {
            "category":"Health Services",
            "subcategory":"Medical Lab",
            "type":"Services"
        },
        {
            "category":"Shopping",
            "subcategory":"Pharmacy",
            "type":"Retail Goods"
        }
    ],
    "sg:phone":"+44 115 940 5565",
    "sg:postcode":"NG11 6DT",
    "sg:province":"Nottinghamshire",
    "sg:tags":[
        "medicine",
        "alternative",
        "therapy",
        "treatment"
    ],
    "wof:name":"FOUNDATION NATURAL THERAPY CENTRE",
    "wof:placetype":"venue"
},
  "geometry": {"coordinates":[-1.1491030455,52.8919754028],"type":"Point"}
}