{
  "type": "Feature",
  "properties": {
    "iso:country":"GB",
    "sg:address":"82 Stockport Road",
    "sg:city":"Ashton-under-lyne",
    "sg:classifiers":[
        {
            "category":"Home & Garden",
            "subcategory":"Home Furnishings",
            "type":"Retail Goods"
        },
        {
            "category":"Home & Garden",
            "subcategory":"Carpets & Floor Coverings",
            "type":"Retail Goods"
        }
    ],
    "sg:phone":"+44 161 343 4828",
    "sg:postcode":"OL7 0LH",
    "sg:province":"Greater Manchester",
    "sg:tags":[
        "furnishers",
        "planner",
        "bedroom"
    ],
    "wof:name":"Peter Gregory Bedrooms",
    "wof:placetype":"venue"
},
  "geometry": {"coordinates":[-2.107351,53.481091],"type":"Point"}
}