{
  "type": "Feature",
  "properties": {
    "addr:full":"341b Ordnance Road Enfield Greater London EN3 6HE",
    "addr:housenumber":"341b",
    "addr:postcode":"en3 6he",
    "addr:street":"Ordnance Road",
    "iso:country":"GB",
    "sg:address":"341b Ordnance Road",
    "sg:city":"Enfield",
    "sg:classifiers":[
        {
            "category":"Professional",
            "subcategory":"Management & Consulting",
            "type":"Services"
        }
    ],
    "sg:phone":"+44 1992 711142",
    "sg:postcode":"EN3 6HE",
    "sg:province":"Greater London",
    "sg:tags":[
        "fire",
        "consultant",
        "protection"
    ],
    "wof:name":"Bush Fire",
    "wof:placetype":"venue"
},
  "geometry": {"coordinates":[-0.023672,51.670795],"type":"Point"}
}