{
  "type": "Feature",
  "properties": {
    "addr:full":"High Greenside, Ravenstone Dale Kirkby Stephen Cumbria CA17 4LT",
    "addr:postcode":"ca17 4lt",
    "addr:street":"High;Ravenstone Dale",
    "iso:country":"GB",
    "sg:address":"High Greenside, Ravenstone Dale",
    "sg:city":"Kirkby Stephen",
    "sg:classifiers":[
        {
            "category":"Farming",
            "subcategory":"Livestock Farm",
            "type":"Manufacturing & Wholesale Goods"
        }
    ],
    "sg:postcode":"CA17 4LT",
    "sg:province":"Cumbria",
    "sg:tags":[
        "others"
    ],
    "wof:name":"John R Metcalfe",
    "wof:placetype":"venue"
},
  "geometry": {"coordinates":[-2.3486230373,54.4727172852],"type":"Point"}
}