{
  "type": "Feature",
  "properties": {
    "addr:full":"9 Felthambrook Industrial Estate, Felthambrook Way Feltham Greater London TW13 7DU",
    "addr:housenumber":"9",
    "addr:postcode":"tw13 7du",
    "addr:street":"Felthambrook Industrial Estate Felthambrook Way",
    "iso:country":"GB",
    "sg:address":"9 Felthambrook Industrial Estate, Felthambrook Way",
    "sg:city":"Feltham",
    "sg:classifiers":[
        {
            "category":"Freight",
            "type":"Transportation"
        }
    ],
    "sg:phone":"+44 20 8751 2109",
    "sg:postcode":"TW13 7DU",
    "sg:province":"Greater London",
    "sg:tags":[
        "forwarders"
    ],
    "wof:name":"Independent Cargo Consolidators Ltd",
    "wof:placetype":"venue"
},
  "geometry": {"coordinates":[-0.409204,51.447075],"type":"Point"}
}