{
  "type": "Feature",
  "properties": {
    "iso:country":"GB",
    "sg:address":"174a Shelbourne Road",
    "sg:city":"Bournemouth",
    "sg:classifiers":[
        {
            "category":"Health Services",
            "subcategory":"Podiatrist",
            "type":"Services"
        }
    ],
    "sg:phone":"+44 1202 524685",
    "sg:postcode":"BH8 8RA",
    "sg:province":"Dorset",
    "sg:tags":[
        "podiatrists",
        "chiropodist"
    ],
    "wof:name":"Inga Watts",
    "wof:placetype":"venue"
},
  "geometry": {"coordinates":[-1.861479,50.734917],"type":"Point"}
}