{
  "type": "Feature",
  "properties": {
    "addr:full":"244 Merton Road London Greater London SW19 1EQ",
    "addr:housenumber":"244",
    "addr:postcode":"sw19 1eq",
    "addr:street":"Merton Road",
    "iso:country":"GB",
    "sg:address":"244 Merton Road",
    "sg:city":"London",
    "sg:classifiers":[
        {
            "category":"Real Estate",
            "subcategory":"Surveying",
            "type":"Services"
        }
    ],
    "sg:phone":"+44 20 8542 3130",
    "sg:postcode":"SW19 1EQ",
    "sg:province":"Greater London",
    "sg:tags":[
        "surveyor",
        "valuer"
    ],
    "wof:name":"South East Surveys",
    "wof:placetype":"venue"
},
  "geometry": {"coordinates":[-0.192351,51.415836],"type":"Point"}
}