{
  "type": "Feature",
  "properties": {
    "addr:full":"Maghull Business Centre 1, Liverpool Road North, Liverpool Lancashire L31 2HB",
    "addr:housenumber":"1",
    "addr:postcode":"l31 2hb",
    "addr:street":"Liverpool Road North",
    "iso:country":"GB",
    "sg:address":"Maghull Business Centre 1, Liverpool Road North,",
    "sg:city":"Liverpool",
    "sg:classifiers":[
        {
            "category":"Shopping",
            "subcategory":"Beauty & Cosmetics",
            "type":"Retail Goods"
        }
    ],
    "sg:postcode":"L31 2HB",
    "sg:province":"Lancashire",
    "sg:tags":[
        "equipment",
        "supply",
        "hairdressing"
    ],
    "wof:name":"Body Profile Ltd",
    "wof:placetype":"venue"
},
  "geometry": {"coordinates":[-2.94491,53.51302],"type":"Point"}
}