{
  "type": "Feature",
  "properties": {
    "iso:country":"GB",
    "sg:address":"4 St. James Rd",
    "sg:city":"Blackpool",
    "sg:classifiers":[
        {
            "category":"Building & Trades",
            "subcategory":"Plumbing",
            "type":"Services"
        }
    ],
    "sg:phone":"+44 1253 402763",
    "sg:postcode":"FY4 2HZ",
    "sg:province":"Lancashire",
    "sg:tags":[
        "central",
        "heating"
    ],
    "wof:name":"Peter Lea",
    "wof:placetype":"venue"
},
  "geometry": {"coordinates":[-3.046309,53.78595],"type":"Point"}
}