{
  "type": "Feature",
  "properties": {
    "iso:country":"GB",
    "sg:address":"Critchill Manor, Critchill",
    "sg:city":"Frome",
    "sg:classifiers":[
        {
            "category":"Sports & Exercise",
            "subcategory":"Golf",
            "type":"Entertainment"
        }
    ],
    "sg:phone":"+44 1373 453410",
    "sg:postcode":"BA11 4LJ",
    "sg:province":"Somerset",
    "sg:tags":[
        "club",
        "course"
    ],
    "wof:name":"CRITCHILL MANOR (GOLF) LTD",
    "wof:placetype":"venue"
},
  "geometry": {"coordinates":[-2.334525,51.224842],"type":"Point"}
}