{
  "type": "Feature",
  "properties": {
    "iso:country":"GB",
    "sg:address":"158 Broadway, West Ealing",
    "sg:city":"London",
    "sg:classifiers":[
        {
            "category":"Professional",
            "subcategory":"Lawyer & Legal Services",
            "type":"Services"
        }
    ],
    "sg:phone":"+44 20 8840 2572",
    "sg:postcode":"W13 0TL",
    "sg:province":"Greater London",
    "wof:name":"Sweetman Burke & Sinker",
    "wof:placetype":"venue"
},
  "geometry": {"coordinates":[-0.328483,51.509701],"type":"Point"}
}