{
  "type": "Feature",
  "properties": {
    "iso:country":"GB",
    "sg:address":"19 Bath Street",
    "sg:city":"Frome",
    "sg:classifiers":[
        {
            "category":"Food & Beverages",
            "subcategory":"Meat & Fish",
            "type":"Retail Goods"
        }
    ],
    "sg:phone":"+44 1373 462697",
    "sg:postcode":"BA11 1DJ",
    "sg:province":"Somerset",
    "sg:tags":[
        "butcher"
    ],
    "wof:name":"G S Williams",
    "wof:placetype":"venue"
},
  "geometry": {"coordinates":[-2.3217020035,51.2302703857],"type":"Point"}
}