{
  "type": "Feature",
  "properties": {
    "addr:full":"Units 9 Colomendy Indstl Est, Rhyl Rd Denbigh Conwy LL16 5TA",
    "addr:housenumber":"units 9",
    "addr:postcode":"ll16 5ta",
    "addr:street":"Indstl;Rhyl Rd",
    "iso:country":"GB",
    "sg:address":"Units 9 Colomendy Indstl Est, Rhyl Rd",
    "sg:city":"Denbigh",
    "sg:classifiers":[
        {
            "category":"Building & Trades",
            "subcategory":"Construction",
            "type":"Services"
        }
    ],
    "sg:postcode":"LL16 5TA",
    "sg:province":"Conwy",
    "sg:tags":[
        "window",
        "glazier",
        "replacement"
    ],
    "wof:name":"Davies,Alan,",
    "wof:placetype":"venue"
},
  "geometry": {"coordinates":[-3.4211490154,53.1834106445],"type":"Point"}
}