{
  "type": "Feature",
  "properties": {
    "addr:full":"Woburn Close, Blackwell Alfreton Derbyshire DE55 5HH",
    "addr:postcode":"de55 5hh",
    "addr:street":"Woburn Close",
    "iso:country":"GB",
    "sg:address":"Woburn Close, Blackwell",
    "sg:city":"Alfreton",
    "sg:classifiers":[
        {
            "category":"Government",
            "subcategory":"City Hall",
            "type":"Public Place"
        }
    ],
    "sg:phone":"+44 1773 810181",
    "sg:postcode":"DE55 5HH",
    "sg:province":"Derbyshire",
    "wof:name":"Blackwell Community Centre",
    "wof:placetype":"venue"
},
  "geometry": {"coordinates":[-1.35387,53.121258],"type":"Point"}
}