{
  "type": "Feature",
  "properties": {
    "iso:country":"GB",
    "sg:address":"1 Ley Road, Felpham",
    "sg:city":"Bognor Regis",
    "sg:classifiers":[
        {
            "category":"Building & Trades",
            "subcategory":"Cleaning & Sanitation",
            "type":"Services"
        }
    ],
    "sg:phone":"+44 1243 585316",
    "sg:postcode":"PO22 7HS",
    "sg:province":"West Sussex",
    "sg:tags":[
        "sweep",
        "chimney"
    ],
    "wof:name":"Bognor & Chichester District Chimney Sweeps",
    "wof:placetype":"venue"
},
  "geometry": {"coordinates":[-0.6426699758,50.7913665771],"type":"Point"}
}