{
  "type": "Feature",
  "properties": {
    "addr:full":"9 Roman Rd Warrington Cheshire WA4 2EL",
    "addr:housenumber":"9",
    "addr:postcode":"wa4 2el",
    "addr:street":"Roman Rd",
    "iso:country":"GB",
    "sg:address":"9 Roman Rd",
    "sg:city":"Warrington",
    "sg:classifiers":[
        {
            "category":"Personal",
            "type":"Services"
        }
    ],
    "sg:phone":"+44 1925 261200",
    "sg:postcode":"WA4 2EL",
    "sg:province":"Cheshire",
    "sg:tags":[
        "wedding"
    ],
    "wof:name":"President Limousine Hire",
    "wof:placetype":"venue"
},
  "geometry": {"coordinates":[-2.5850439072,53.3718452454],"type":"Point"}
}