{
  "type": "Feature",
  "properties": {
    "iso:country":"GB",
    "sg:address":"Brentnall St",
    "sg:city":"Middlesbrough",
    "sg:classifiers":[
        {
            "category":"Parking",
            "type":"Transportation"
        }
    ],
    "sg:phone":"+44 1642 225330",
    "sg:postcode":"TS1 5AP",
    "sg:province":"North Yorkshire",
    "sg:tags":[
        "car",
        "park"
    ],
    "wof:name":"Brentnall Street Car Park",
    "wof:placetype":"venue"
},
  "geometry": {"coordinates":[-1.2412140369,54.5754737854],"type":"Point"}
}