{
  "type": "Feature",
  "properties": {
    "addr:full":"267 King St Glasgow Glasgow City G73 1DE",
    "addr:housenumber":"267",
    "addr:postcode":"g73 1de",
    "addr:street":"King St",
    "iso:country":"GB",
    "sg:address":"267 King St",
    "sg:city":"Glasgow",
    "sg:classifiers":[
        {
            "category":"Government",
            "subcategory":"Office",
            "type":"Public Place"
        }
    ],
    "sg:phone":"+44 141 647 0273",
    "sg:postcode":"G73 1DE",
    "sg:province":"Glasgow City",
    "sg:tags":[
        "central"
    ],
    "wof:name":"Scottish Childrens Reporter Administration",
    "wof:placetype":"venue"
},
  "geometry": {"coordinates":[-4.209309,55.829258],"type":"Point"}
}