{
  "type": "Feature",
  "properties": {
    "addr:full":"Chelwood House, Perrymount Road Haywards Heath East Sussex RH16 1DW",
    "addr:postcode":"rh16 1dw",
    "addr:street":"Perrymount Road",
    "iso:country":"GB",
    "sg:address":"Chelwood House, Perrymount Road",
    "sg:city":"Haywards Heath",
    "sg:classifiers":[
        {
            "category":"Professional",
            "subcategory":"Employment Agencies",
            "type":"Services"
        }
    ],
    "sg:phone":"+44 1444 443948",
    "sg:postcode":"RH16 1DW",
    "sg:province":"East Sussex",
    "sg:tags":[
        "consultant"
    ],
    "wof:name":"Heritage Construction Services Ltd.",
    "wof:placetype":"venue"
},
  "geometry": {"coordinates":[-0.103469,51.005371],"type":"Point"}
}