{
  "type": "Feature",
  "properties": {
    "iso:country":"GB",
    "sg:address":"39 North Hermitage Street",
    "sg:city":"Newcastleton",
    "sg:classifiers":[
        {
            "category":"Retail",
            "subcategory":"Auto Repair",
            "type":"Services"
        }
    ],
    "sg:phone":"+44 13873 75226",
    "sg:postcode":"TD9 0RA",
    "sg:province":"Cumbria",
    "sg:tags":[
        "modification",
        "garage"
    ],
    "wof:name":"W D Elliot",
    "wof:placetype":"venue"
},
  "geometry": {"coordinates":[-2.811791,55.181229],"type":"Point"}
}