{
  "type": "Feature",
  "properties": {
    "iso:country":"GB",
    "sg:address":"15 Union Street",
    "sg:city":"Reading",
    "sg:classifiers":[
        {
            "category":"Shopping",
            "subcategory":"Shoes",
            "type":"Retail Goods"
        }
    ],
    "sg:postcode":"RG1 1EU",
    "sg:province":"Berkshire",
    "wof:name":"Kobblers & Keys",
    "wof:placetype":"venue"
},
  "geometry": {"coordinates":[-0.972859,51.456631],"type":"Point"}
}