{
  "type": "Feature",
  "properties": {
    "iso:country":"GB",
    "sg:address":"Kingston Farm, Beatrice Avenue",
    "sg:city":"East Cowes",
    "sg:classifiers":[
        {
            "category":"Utilities",
            "subcategory":"Refuse",
            "type":"Services"
        }
    ],
    "sg:postcode":"PO32 6LL",
    "sg:province":"Isle of Wight",
    "sg:tags":[
        "disposal",
        "waste"
    ],
    "wof:name":"Tony Bacon",
    "wof:placetype":"venue"
},
  "geometry": {"coordinates":[-1.2840679884,50.7557792664],"type":"Point"}
}