{
  "type": "Feature",
  "properties": {
    "addr:full":"Caley Fisheries Ltd, 1 Dalrymple Street Fraserburgh Aberdeenshire AB43 9BH",
    "addr:housenumber":"1",
    "addr:postcode":"ab43 9bh",
    "addr:street":"Dalrymple Street",
    "iso:country":"GB",
    "sg:address":"Caley Fisheries Ltd, 1 Dalrymple Street",
    "sg:city":"Fraserburgh",
    "sg:classifiers":[
        {
            "category":"Professional",
            "type":"Services"
        }
    ],
    "sg:phone":"+44 1346 517049",
    "sg:postcode":"AB43 9BH",
    "sg:province":"Aberdeenshire",
    "sg:tags":[
        "entertainer"
    ],
    "wof:name":"T & W Enterprises Ltd.",
    "wof:placetype":"venue"
},
  "geometry": {"coordinates":[-2.015844,57.69442],"type":"Point"}
}