{
  "type": "Feature",
  "properties": {
    "iso:country":"GB",
    "sg:address":"The Mowhay, Trebetherick",
    "sg:city":"Wadebridge",
    "sg:classifiers":[
        {
            "category":"Shopping",
            "subcategory":"Hobbies, Toys, & Games",
            "type":"Retail Goods"
        }
    ],
    "sg:postcode":"PL27 6SE",
    "sg:province":"Cornwall",
    "sg:tags":[
        "kite"
    ],
    "wof:name":"Just Kites",
    "wof:placetype":"venue"
},
  "geometry": {"coordinates":[-4.919145,50.5658],"type":"Point"}
}