{
  "type": "Feature",
  "properties": {
    "iso:country":"GB",
    "sg:address":"154 Fulham Road",
    "sg:city":"London",
    "sg:classifiers":[
        {
            "category":"Cafe",
            "type":"Food & Drink"
        }
    ],
    "sg:phone":"+44 20 7244 8316",
    "sg:postcode":"SW10 9PR",
    "sg:province":"Greater London",
    "sg:tags":[
        "tea",
        "snack",
        "bar",
        "room"
    ],
    "wof:name":"Cafe De Lice",
    "wof:placetype":"venue"
},
  "geometry": {"coordinates":[-0.179963,51.486607],"type":"Point"}
}