{
  "type": "Feature",
  "properties": {
    "iso:country":"GB",
    "sg:address":"350 Millfield Hill",
    "sg:city":"Erskine",
    "sg:classifiers":[
        {
            "category":"Utilities",
            "subcategory":"Natural Gas",
            "type":"Services"
        }
    ],
    "sg:phone":"+44 141 812 5769",
    "sg:postcode":"PA8 6JN",
    "sg:province":"Renfrewshire",
    "sg:tags":[
        "supplier",
        "industrial"
    ],
    "wof:name":"Med-A-Gas",
    "wof:placetype":"venue"
},
  "geometry": {"coordinates":[-4.464135,55.900684],"type":"Point"}
}