{
  "type": "Feature",
  "properties": {
    "addr:full":"26-27 Cornelia Terrace Seaham Durham SR7 7RZ",
    "addr:housenumber":"26-27",
    "addr:postcode":"sr7 7rz",
    "addr:street":"Cornelia Terrace",
    "iso:country":"GB",
    "sg:address":"26-27 Cornelia Terrace",
    "sg:city":"Seaham",
    "sg:classifiers":[
        {
            "category":"Arena",
            "subcategory":"Sports Club",
            "type":"Entertainment"
        }
    ],
    "sg:phone":"+44 191 581 2331",
    "sg:postcode":"SR7 7RZ",
    "sg:province":"Durham",
    "wof:name":"Seaham Rugby Club",
    "wof:placetype":"venue"
},
  "geometry": {"coordinates":[-1.3402680159,54.8379402161],"type":"Point"}
}