{
  "type": "Feature",
  "properties": {
    "iso:country":"GB",
    "sg:address":"18 Temple Street",
    "sg:city":"Aylesbury",
    "sg:classifiers":[
        {
            "category":"Professional",
            "subcategory":"Lawyer & Legal Services",
            "type":"Services"
        }
    ],
    "sg:phone":"+44 1296 393877",
    "sg:postcode":"HP20 2RQ",
    "sg:province":"Buckinghamshire",
    "sg:tags":[
        "advice",
        "counselling"
    ],
    "wof:name":"J M P S Ltd.",
    "wof:placetype":"venue"
},
  "geometry": {"coordinates":[-0.814185,51.816345],"type":"Point"}
}