{
  "type": "Feature",
  "properties": {
    "iso:country":"GB",
    "sg:address":"84-86 Victoria Road West",
    "sg:city":"Thornton Cleveleys",
    "sg:classifiers":[
        {
            "category":"Food & Beverages",
            "subcategory":"Meat & Fish",
            "type":"Retail Goods"
        }
    ],
    "sg:phone":"+44 1253 853065",
    "sg:postcode":"FY5 1AG",
    "sg:province":"Lancashire",
    "sg:tags":[
        "butcher"
    ],
    "wof:name":"H Hargreaves & Sons",
    "wof:placetype":"venue"
},
  "geometry": {"coordinates":[-3.0417490005,53.8771095276],"type":"Point"}
}