{
  "type": "Feature",
  "properties": {
    "addr:full":"Saling House, Woods Road, Sturmer Haverhill Essex CB9 7ZH",
    "addr:postcode":"cb9 7zh",
    "addr:street":"House Woods Road",
    "iso:country":"GB",
    "sg:address":"Saling House, Woods Road, Sturmer",
    "sg:city":"Haverhill",
    "sg:classifiers":[
        {
            "category":"Real Estate",
            "subcategory":"Architect",
            "type":"Services"
        }
    ],
    "sg:phone":"+44 1440 709355",
    "sg:postcode":"CB9 7ZH",
    "sg:province":"Essex",
    "wof:name":"Paul Mitchell & Co",
    "wof:placetype":"venue"
},
  "geometry": {"coordinates":[0.470994,52.069279],"type":"Point"}
}