{
  "type": "Feature",
  "properties": {
    "iso:country":"GB",
    "sg:address":"9 Queensferry Pde",
    "sg:city":"Leicester",
    "sg:classifiers":[
        {
            "category":"Shopping",
            "subcategory":"News",
            "type":"Retail Goods"
        }
    ],
    "sg:phone":"+44 116 278 5383",
    "sg:postcode":"LE2 9LW",
    "sg:province":"Leicestershire",
    "sg:tags":[
        "newsagent"
    ],
    "wof:name":"R C News",
    "wof:placetype":"venue"
},
  "geometry": {"coordinates":[-1.1531579494,52.5882034302],"type":"Point"}
}