{
  "type": "Feature",
  "properties": {
    "iso:country":"GB",
    "sg:address":"4 Upland Cres",
    "sg:city":"Truro",
    "sg:classifiers":[
        {
            "category":"Place Of Worship",
            "type":"Public Place"
        }
    ],
    "sg:phone":"+44 1872 272514",
    "sg:postcode":"TR1 1LU",
    "sg:province":"Cornwall",
    "wof:name":"Methodist Church Cornwall District",
    "wof:placetype":"venue"
},
  "geometry": {"coordinates":[-5.036965,50.270538],"type":"Point"}
}