{
  "type": "Feature",
  "properties": {
    "iso:country":"GB",
    "sg:address":"10 Longfield Ave, Urmston",
    "sg:city":"Manchester",
    "sg:classifiers":[
        {
            "category":"Professional",
            "subcategory":"Management & Consulting",
            "type":"Services"
        }
    ],
    "sg:postcode":"M41 9DP",
    "sg:province":"Cheshire",
    "sg:tags":[
        "consultant",
        "business"
    ],
    "wof:name":"Vas-Q Management Services Ltd",
    "wof:placetype":"venue"
},
  "geometry": {"coordinates":[-2.3625760078,53.4457893372],"type":"Point"}
}