{
  "type": "Feature",
  "properties": {
    "addr:full":"Vulcan Works, Canal Street, Longport Stoke-on-trent Staffordshire ST6 4LU",
    "addr:postcode":"staffordshire st6 4lu",
    "addr:street":"Canal Street",
    "iso:country":"GB",
    "sg:address":"Vulcan Works, Canal Street, Longport",
    "sg:city":"Stoke-on-trent",
    "sg:classifiers":[
        {
            "category":"Professional",
            "subcategory":"Engineering",
            "type":"Services"
        }
    ],
    "sg:postcode":"ST6 4LU",
    "sg:province":"Staffordshire",
    "wof:name":"Westport Tool & Die",
    "wof:placetype":"venue"
},
  "geometry": {"coordinates":[-2.21597,53.044079],"type":"Point"}
}