{
  "type": "Feature",
  "properties": {
    "iso:country":"GB",
    "sg:address":"Blackstope La",
    "sg:city":"Retford",
    "sg:classifiers":[
        {
            "category":"Building & Trades",
            "subcategory":"Cleaning & Sanitation",
            "type":"Services"
        }
    ],
    "sg:phone":"+44 1777 860610",
    "sg:postcode":"DN22 6NE",
    "sg:province":"Nottinghamshire",
    "sg:tags":[
        "blast"
    ],
    "wof:name":"North Notts Coatings Ltd",
    "wof:placetype":"venue"
},
  "geometry": {"coordinates":[-0.932084024,53.321849823],"type":"Point"}
}