{
  "type": "Feature",
  "properties": {
    "addr:full":"11 Metro Ho, Second Way Wembley Greater London HA9 0YS",
    "addr:housenumber":"11;ho",
    "addr:postcode":"ha9 0ys",
    "addr:street":"Metro;Second Way",
    "iso:country":"GB",
    "sg:address":"11 Metro Ho, Second Way",
    "sg:city":"Wembley",
    "sg:classifiers":[
        {
            "category":"Manufacturing",
            "subcategory":"Petroleum Products",
            "type":"Manufacturing & Wholesale Goods"
        }
    ],
    "sg:phone":"+44 20 8812 2444",
    "sg:postcode":"HA9 0YS",
    "sg:province":"Greater London",
    "sg:tags":[
        "double",
        "glazing"
    ],
    "wof:name":"Secure Window Systems",
    "wof:placetype":"venue"
},
  "geometry": {"coordinates":[-0.273104,51.55751],"type":"Point"}
}