{
  "type": "Feature",
  "properties": {
    "addr:full":"Unit 12 Ketland Court, River Lane, Saltney Chester Cheshire CH4 8SB",
    "addr:housenumber":"unit 12",
    "addr:postcode":"ch4 8sb",
    "addr:street":"Ketland Court River Lane",
    "iso:country":"GB",
    "sg:address":"Unit 12 Ketland Court, River Lane, Saltney",
    "sg:city":"Chester",
    "sg:classifiers":[
        {
            "category":"Wholesale",
            "subcategory":"Fruits & Vegetables",
            "type":"Manufacturing & Wholesale Goods"
        }
    ],
    "sg:phone":"+44 1244 390721",
    "sg:postcode":"CH4 8SB",
    "sg:province":"Cheshire",
    "wof:name":"North Wales Fruiterers",
    "wof:placetype":"venue"
},
  "geometry": {"coordinates":[-2.9257199764,53.1805114746],"type":"Point"}
}