{
  "type": "Feature",
  "properties": {
    "addr:full":"Griffiths Road, Lostock Gralam Northwich Cheshire CW9 7NU",
    "addr:postcode":"cw9 7nu",
    "addr:street":"Griffiths Road",
    "iso:country":"GB",
    "sg:address":"Griffiths Road, Lostock Gralam",
    "sg:city":"Northwich",
    "sg:classifiers":[
        {
            "category":"Freight",
            "type":"Transportation"
        }
    ],
    "sg:phone":"+44 1606 44907",
    "sg:postcode":"CW9 7NU",
    "sg:province":"Cheshire",
    "sg:tags":[
        "haulage",
        "transport",
        "road"
    ],
    "wof:name":"Francis Transport",
    "wof:placetype":"venue"
},
  "geometry": {"coordinates":[-2.4605491161,53.2719917297],"type":"Point"}
}