{
  "type": "Feature",
  "properties": {
    "addr:full":"16-20 Hockley Nottingham Nottinghamshire NG1 1FP",
    "addr:housenumber":"16-20",
    "addr:postcode":"ng1 1fp",
    "addr:street":"Hockley",
    "iso:country":"GB",
    "sg:address":"16-20 Hockley",
    "sg:city":"Nottingham",
    "sg:classifiers":[
        {
            "category":"Shopping",
            "subcategory":"Clothing, Apparel, & Fashions",
            "type":"Retail Goods"
        }
    ],
    "sg:phone":"+44 115 911 9200",
    "sg:postcode":"NG1 1FP",
    "sg:province":"Nottinghamshire",
    "sg:tags":[
        "t-shirt"
    ],
    "wof:name":"Flying Colours",
    "wof:placetype":"venue"
},
  "geometry": {"coordinates":[-1.1405,52.953617],"type":"Point"}
}