{
  "type": "Feature",
  "properties": {
    "addr:full":"256 Doncaster Road Barnsley South Yorkshire S70 1XE",
    "addr:housenumber":"256",
    "addr:postcode":"s70 1xe",
    "addr:street":"Doncaster Road;Yorkshire",
    "iso:country":"GB",
    "sg:address":"256 Doncaster Road",
    "sg:city":"Barnsley",
    "sg:classifiers":[
        {
            "category":"Building & Trades",
            "subcategory":"Construction",
            "type":"Services"
        }
    ],
    "sg:postcode":"S70 1XE",
    "sg:province":"South Yorkshire",
    "sg:tags":[
        "builder"
    ],
    "wof:name":"P Shaw",
    "wof:placetype":"venue"
},
  "geometry": {"coordinates":[-1.464982,53.547195],"type":"Point"}
}