{
  "type": "Feature",
  "properties": {
    "iso:country":"GB",
    "sg:address":"252 Union St",
    "sg:city":"Aberdeen",
    "sg:classifiers":[
        {
            "category":"Real Estate",
            "subcategory":"Real Estate Agent",
            "type":"Services"
        }
    ],
    "sg:phone":"+44 1224 639779",
    "sg:postcode":"AB10 1TN",
    "sg:province":"Aberdeen City",
    "wof:name":"Alastair Gibb & Co",
    "wof:placetype":"venue"
},
  "geometry": {"coordinates":[-2.108174,57.144108],"type":"Point"}
}