{
  "type": "Feature",
  "properties": {
    "addr:full":"11 Clifford Rd North Berwick East Lothian EH39 4PW",
    "addr:housenumber":"11",
    "addr:postcode":"eh39 4pw",
    "addr:street":"Clifford Rd",
    "iso:country":"GB",
    "sg:address":"11 Clifford Rd",
    "sg:city":"North Berwick",
    "sg:classifiers":[
        {
            "category":"Retail",
            "subcategory":"Driving School",
            "type":"Services"
        }
    ],
    "sg:phone":"+44 1620 893397",
    "sg:postcode":"EH39 4PW",
    "sg:province":"East Lothian",
    "wof:name":"Wheelnutts Driving School",
    "wof:placetype":"venue"
},
  "geometry": {"coordinates":[-2.7170538902,56.058555603],"type":"Point"}
}