{
  "type": "Feature",
  "properties": {
    "addr:full":"254-256 King St Hammersmith Greater London W6 0SP",
    "addr:housenumber":"254-256",
    "addr:postcode":"w6 0sp",
    "addr:street":"King St",
    "iso:country":"GB",
    "sg:address":"254-256 King St",
    "sg:city":"Hammersmith",
    "sg:classifiers":[
        {
            "category":"Home & Garden",
            "subcategory":"Building Materials",
            "type":"Retail Goods"
        }
    ],
    "sg:phone":"+44 20 8748 6656",
    "sg:postcode":"W6 0SP",
    "sg:province":"Greater London",
    "sg:tags":[
        "furnishers",
        "bathroom",
        "planner"
    ],
    "wof:name":"Classic Bathrooms & Kitchens",
    "wof:placetype":"venue"
},
  "geometry": {"coordinates":[-0.2446389943,51.4934082031],"type":"Point"}
}