{
  "type": "Feature",
  "properties": {
    "addr:full":"6 Fairhope Avenue Morecambe Lancashire LA4 6JZ",
    "addr:housenumber":"6",
    "addr:postcode":"la4 6jz",
    "addr:street":"Fairhope Avenue",
    "iso:country":"GB",
    "sg:address":"6 Fairhope Avenue",
    "sg:city":"Morecambe",
    "sg:classifiers":[
        {
            "category":"Wholesale",
            "subcategory":"Meat",
            "type":"Manufacturing & Wholesale Goods"
        },
        {
            "category":"Manufacturing",
            "subcategory":"Food",
            "type":"Manufacturing & Wholesale Goods"
        }
    ],
    "sg:phone":"+44 1524 411308",
    "sg:postcode":"LA4 6JZ",
    "sg:province":"Lancashire",
    "sg:tags":[
        "product",
        "production"
    ],
    "wof:name":"Barton Cooked Meats",
    "wof:placetype":"venue"
},
  "geometry": {"coordinates":[-2.8348329067,54.0743751526],"type":"Point"}
}