{
  "type": "Feature",
  "properties": {
    "addr:full":"Wanstead Crescent, Allerton Bradford West Yorkshire BD15 7PA",
    "addr:postcode":"bd15 7pa",
    "addr:street":"Wanstead Crescent",
    "iso:country":"GB",
    "sg:address":"Wanstead Crescent, Allerton",
    "sg:city":"Bradford",
    "sg:classifiers":[
        {
            "category":"Health Services",
            "subcategory":"Doctor",
            "type":"Services"
        },
        {
            "category":"Health Services",
            "subcategory":"Clinic",
            "type":"Services"
        }
    ],
    "sg:phone":"+44 1274 542280",
    "sg:postcode":"BD15 7PA",
    "sg:province":"West Yorkshire",
    "sg:tags":[
        "nh",
        "practitioners"
    ],
    "wof:name":"Allerton Health Centre",
    "wof:placetype":"venue"
},
  "geometry": {"coordinates":[-1.821614027,53.8007392883],"type":"Point"}
}