{
  "type": "Feature",
  "properties": {
    "addr:full":"Enterprise House, 133 Blyth Road Hayes Greater London UB3 1DD",
    "addr:housenumber":"133",
    "addr:postcode":"ub3 1dd",
    "addr:street":"Blyth Road",
    "iso:country":"GB",
    "sg:address":"Enterprise House, 133 Blyth Road",
    "sg:city":"Hayes",
    "sg:classifiers":[
        {
            "category":"Government",
            "subcategory":"Post Office",
            "type":"Public Place"
        }
    ],
    "sg:phone":"+44 7973 925665",
    "sg:postcode":"UB3 1DD",
    "sg:province":"Greater London",
    "sg:tags":[
        "messenger",
        "courier"
    ],
    "wof:name":"Andrew Pedley Partnership",
    "wof:placetype":"venue"
},
  "geometry": {"coordinates":[-0.427091,51.50518],"type":"Point"}
}