{
  "type": "Feature",
  "properties": {
    "addr:full":"Dergoals Farm, Glenluce Newton Stewart Dumfries and Galloway DG8 0LG",
    "addr:postcode":"dg8 0lg",
    "addr:street":"Stewart",
    "iso:country":"GB",
    "sg:address":"Dergoals Farm, Glenluce",
    "sg:city":"Newton Stewart",
    "sg:classifiers":[
        {
            "category":"Home & Garden",
            "subcategory":"Hardware",
            "type":"Retail Goods"
        },
        {
            "category":"Farming",
            "subcategory":"Livestock Farm",
            "type":"Manufacturing & Wholesale Goods"
        }
    ],
    "sg:postcode":"DG8 0LG",
    "sg:province":"Dumfries and Galloway",
    "sg:tags":[
        "tarpaulin",
        "others"
    ],
    "wof:name":"Andy Mitchell",
    "wof:placetype":"venue"
},
  "geometry": {"coordinates":[-4.8121027946,54.8781166077],"type":"Point"}
}