{
  "type": "Feature",
  "properties": {
    "iso:country":"GB",
    "sg:address":"New House, Suite 24",
    "sg:city":"London",
    "sg:classifiers":[
        {
            "category":"Shopping",
            "subcategory":"Computers & Home Electronics",
            "type":"Retail Goods"
        }
    ],
    "sg:phone":"+44 1992 769000",
    "sg:postcode":"EC1N 8JY",
    "sg:province":"Greater London",
    "wof:name":"G T O  Distribution Ltd.",
    "wof:placetype":"venue"
},
  "geometry": {"coordinates":[-0.1021390036,51.4964561462],"type":"Point"}
}