{
  "type": "Feature",
  "properties": {
    "iso:country":"GB",
    "sg:address":"2 Clifton Crescent",
    "sg:city":"Folkestone",
    "sg:classifiers":[
        {
            "category":"Travel",
            "subcategory":"Hotels & Motels",
            "type":"Entertainment"
        }
    ],
    "sg:phone":"+44 1303 253712",
    "sg:postcode":"CT20 2EW",
    "sg:province":"Kent",
    "wof:name":"The Rhodesia Hotel",
    "wof:placetype":"venue"
},
  "geometry": {"coordinates":[1.169055,51.076126],"type":"Point"}
}