{
  "type": "Feature",
  "properties": {
    "addr:full":"Longbridge Meadow Est, Station Rd Cullompton Devon EX15 1BT",
    "addr:postcode":"ex15 1bt",
    "addr:street":"Longbridge Meadow Est Station Rd",
    "iso:country":"GB",
    "sg:address":"Longbridge Meadow Est, Station Rd",
    "sg:city":"Cullompton",
    "sg:classifiers":[
        {
            "category":"Wholesale",
            "subcategory":"Non-durable Goods",
            "type":"Manufacturing & Wholesale Goods"
        }
    ],
    "sg:phone":"+44 1884 34910",
    "sg:postcode":"EX15 1BT",
    "sg:province":"Devon",
    "sg:tags":[
        "carry",
        "cash"
    ],
    "wof:name":"Pricefighters Cash & Carry Ltd",
    "wof:placetype":"venue"
},
  "geometry": {"coordinates":[-3.3861789703,50.8594169617],"type":"Point"}
}