{
  "type": "Feature",
  "properties": {
    "addr:full":"36 Treville Close Redditch Warwickshire B98 0NN",
    "addr:housenumber":"36",
    "addr:postcode":"b98 0nn",
    "addr:street":"Treville Close",
    "iso:country":"GB",
    "sg:address":"36 Treville Close",
    "sg:city":"Redditch",
    "sg:classifiers":[
        {
            "category":"Autos & Motor Vehicles",
            "subcategory":"Motorcycle Sales",
            "type":"Retail Goods"
        }
    ],
    "sg:phone":"+44 1527 522330",
    "sg:postcode":"B98 0NN",
    "sg:province":"Warwickshire",
    "sg:tags":[
        "chauffeur",
        "driven",
        "car"
    ],
    "wof:name":"Mainline Limousines",
    "wof:placetype":"venue"
},
  "geometry": {"coordinates":[-1.8937239647,52.3024749756],"type":"Point"}
}