{
  "type": "Feature",
  "properties": {
    "addr:full":"23 Lucius Street Torquay Devon TQ2 5UW",
    "addr:housenumber":"23",
    "addr:postcode":"tq2 5uw",
    "addr:street":"Lucius Street",
    "iso:country":"GB",
    "sg:address":"23 Lucius Street",
    "sg:city":"Torquay",
    "sg:classifiers":[
        {
            "category":"Shopping",
            "subcategory":"Shoes",
            "type":"Retail Goods"
        }
    ],
    "sg:phone":"+44 1803 201956",
    "sg:postcode":"TQ2 5UW",
    "sg:province":"Devon",
    "sg:tags":[
        "shop"
    ],
    "wof:name":"Tarantella",
    "wof:placetype":"venue"
},
  "geometry": {"coordinates":[-3.5390200615,50.4676208496],"type":"Point"}
}