{
  "type": "Feature",
  "properties": {
    "addr:full":"173 High Road Loughton Essex IG10 4LF",
    "addr:housenumber":"173",
    "addr:postcode":"ig10 4lf",
    "addr:street":"High Road",
    "iso:country":"GB",
    "sg:address":"173 High Road",
    "sg:city":"Loughton",
    "sg:classifiers":[
        {
            "category":"Shopping",
            "subcategory":"Clothing, Apparel, & Fashions",
            "type":"Retail Goods"
        }
    ],
    "sg:phone":"+44 20 8508 9102",
    "sg:postcode":"IG10 4LF",
    "sg:province":"Essex",
    "sg:tags":[
        "shop"
    ],
    "wof:name":"Evergreen",
    "wof:placetype":"venue"
},
  "geometry": {"coordinates":[0.052943,51.645016],"type":"Point"}
}