{
  "type": "Feature",
  "properties": {
    "addr:full":"Wholesale Market, Red Doles Lane Huddersfield West Yorkshire HD2 1UL",
    "addr:postcode":"hd2 1ul",
    "addr:street":"Doles Lane",
    "iso:country":"GB",
    "sg:address":"Wholesale Market, Red Doles Lane",
    "sg:city":"Huddersfield",
    "sg:classifiers":[
        {
            "category":"Shopping",
            "subcategory":"Florist",
            "type":"Retail Goods"
        }
    ],
    "sg:phone":"+44 1484 353012",
    "sg:postcode":"HD2 1UL",
    "sg:province":"West Yorkshire",
    "wof:name":"Bletchers (Flowers) Ltd.",
    "wof:placetype":"venue"
},
  "geometry": {"coordinates":[-1.74552,53.674332],"type":"Point"}
}