{
  "type": "Feature",
  "properties": {
    "addr:full":"17 Briarfield Gardens Shipley West Yorkshire BD18 2BE",
    "addr:housenumber":"17",
    "addr:postcode":"bd18 2be",
    "addr:street":"Briarfield Gardens",
    "iso:country":"GB",
    "sg:address":"17 Briarfield Gardens",
    "sg:city":"Shipley",
    "sg:classifiers":[
        {
            "category":"Government",
            "subcategory":"Post Office",
            "type":"Public Place"
        }
    ],
    "sg:phone":"+44 1274 585321",
    "sg:postcode":"BD18 2BE",
    "sg:province":"West Yorkshire",
    "sg:tags":[
        "messenger",
        "courier"
    ],
    "wof:name":"Exsample Courier Services",
    "wof:placetype":"venue"
},
  "geometry": {"coordinates":[-1.7732709646,53.8252105713],"type":"Point"}
}