{
  "type": "Feature",
  "properties": {
    "addr:full":"13 Thames Drive Ruislip Greater London HA4 7AY",
    "addr:housenumber":"13",
    "addr:postcode":"ha4 7ay",
    "addr:street":"Thames Drive",
    "iso:country":"GB",
    "sg:address":"13 Thames Drive",
    "sg:city":"Ruislip",
    "sg:classifiers":[
        {
            "category":"Airport",
            "subcategory":"General Aviation",
            "type":"Transportation"
        }
    ],
    "sg:phone":"+44 1895 631220",
    "sg:postcode":"HA4 7AY",
    "sg:province":"Greater London",
    "sg:tags":[
        "consultant"
    ],
    "wof:name":"Lundkvist Aviation Research",
    "wof:placetype":"venue"
},
  "geometry": {"coordinates":[-0.438805,51.582325],"type":"Point"}
}