{
  "type": "Feature",
  "properties": {
    "addr:full":"Drummond Road, Aston Field Stafford Staffordshire ST16 3HJ",
    "addr:postcode":"st16 3hj",
    "addr:street":"Drummond Road Aston",
    "iso:country":"GB",
    "sg:address":"Drummond Road, Aston Field",
    "sg:city":"Stafford",
    "sg:classifiers":[
        {
            "category":"Wholesale",
            "subcategory":"Scrap",
            "type":"Manufacturing & Wholesale Goods"
        }
    ],
    "sg:phone":"+44 1785 242058",
    "sg:postcode":"ST16 3HJ",
    "sg:province":"Staffordshire",
    "sg:tags":[
        "waste",
        "metal"
    ],
    "wof:name":"J & S Metals",
    "wof:placetype":"venue"
},
  "geometry": {"coordinates":[-2.1142230034,52.8214836121],"type":"Point"}
}