{
  "type": "Feature",
  "properties": {
    "addr:full":"192a Alum Rock Rd Birmingham West Midlands B8 3DH",
    "addr:housenumber":"192a",
    "addr:postcode":"b8 3dh",
    "addr:street":"Alum Rock Rd",
    "iso:country":"GB",
    "sg:address":"192a Alum Rock Rd",
    "sg:city":"Birmingham",
    "sg:classifiers":[
        {
            "category":"Personal",
            "subcategory":"Beauty Salon",
            "type":"Services"
        }
    ],
    "sg:postcode":"B8 3DH",
    "sg:province":"West Midlands",
    "sg:tags":[
        "unisex",
        "hairdresser"
    ],
    "wof:name":"Fairey,Linda,",
    "wof:placetype":"venue"
},
  "geometry": {"coordinates":[-1.8508249521,52.488948822],"type":"Point"}
}