{
  "type": "Feature",
  "properties": {
    "addr:full":"Unit 7a Leyton Avenue Sutton-in-ashfield Nottinghamshire NG17 3BD",
    "addr:housenumber":"unit 7a",
    "addr:postcode":"ng17 3bd",
    "addr:street":"Leyton Avenue",
    "iso:country":"GB",
    "sg:address":"Unit 7a Leyton Avenue",
    "sg:city":"Sutton-in-ashfield",
    "sg:classifiers":[
        {
            "category":"Professional",
            "subcategory":"Engineering",
            "type":"Services"
        }
    ],
    "sg:postcode":"NG17 3BD",
    "sg:province":"Nottinghamshire",
    "sg:tags":[
        "precision",
        "engineer"
    ],
    "wof:name":"Dimension Precision Engineering",
    "wof:placetype":"venue"
},
  "geometry": {"coordinates":[-1.253666997,53.1353530884],"type":"Point"}
}