{
  "type": "Feature",
  "properties": {
    "addr:full":"6-7 Lower Parliament Street Nottingham Nottinghamshire NG1 3DB",
    "addr:housenumber":"6-7",
    "addr:postcode":"ng1 3db",
    "addr:street":"Lower Parliament Street",
    "iso:country":"GB",
    "sg:address":"6-7 Lower Parliament Street",
    "sg:city":"Nottingham",
    "sg:classifiers":[
        {
            "category":"Shopping",
            "subcategory":"Stationery & Office Supplies",
            "type":"Retail Goods"
        }
    ],
    "sg:phone":"+44 115 948 3786",
    "sg:postcode":"NG1 3DB",
    "sg:province":"Nottinghamshire",
    "wof:name":"Stationery Box Ltd.",
    "wof:placetype":"venue"
},
  "geometry": {"coordinates":[-1.147352,52.955158],"type":"Point"}
}