{
  "type": "Feature",
  "properties": {
    "iso:country":"GB",
    "sg:address":"19 The Spires Shopping Centre, High St",
    "sg:city":"Barnet",
    "sg:classifiers":[
        {
            "category":"Home & Garden",
            "subcategory":"Kitchen Supply",
            "type":"Retail Goods"
        }
    ],
    "sg:phone":"+44 20 8447 0783",
    "sg:postcode":"EN5 5XY",
    "sg:province":"Hertfordshire",
    "sg:tags":[
        "table"
    ],
    "wof:name":"Collanders",
    "wof:placetype":"venue"
},
  "geometry": {"coordinates":[-0.1982599944,51.6521186829],"type":"Point"}
}