{
  "type": "Feature",
  "properties": {
    "addr:full":"Craigholme, 16 Roman Rd, Bearsden Glasgow East Dunbartonshire G61 2SL",
    "addr:housenumber":"16",
    "addr:postcode":"g61 2sl",
    "addr:street":"Craigholme;Roman Rd",
    "iso:country":"GB",
    "sg:address":"Craigholme, 16 Roman Rd, Bearsden",
    "sg:city":"Glasgow",
    "sg:classifiers":[
        {
            "category":"Social Services",
            "subcategory":"Retirement Home",
            "type":"Services"
        }
    ],
    "sg:phone":"+44 141 942 3962",
    "sg:postcode":"G61 2SL",
    "sg:province":"East Dunbartonshire",
    "sg:tags":[
        "residential",
        "care"
    ],
    "wof:name":"The Glasgow and West of Scotland Society",
    "wof:placetype":"venue"
},
  "geometry": {"coordinates":[-4.32681,55.919529],"type":"Point"}
}