{
  "type": "Feature",
  "properties": {
    "iso:country":"GB",
    "sg:address":"North Bank",
    "sg:city":"Hassocks",
    "sg:classifiers":[
        {
            "category":"Social Services",
            "subcategory":"Retirement Home",
            "type":"Services"
        }
    ],
    "sg:phone":"+44 1273 846193",
    "sg:postcode":"BN6 8JG",
    "sg:province":"East Sussex",
    "sg:tags":[
        "residential",
        "care"
    ],
    "wof:name":"Stone Pound House",
    "wof:placetype":"venue"
},
  "geometry": {"coordinates":[-0.148244,50.924294],"type":"Point"}
}