{
  "type": "Feature",
  "properties": {
    "addr:full":"West Stockwell St Colchester Essex CO1 1BA",
    "addr:postcode":"co1 1ba",
    "addr:street":"West Stockwell St",
    "iso:country":"GB",
    "sg:address":"West Stockwell St",
    "sg:city":"Colchester",
    "sg:classifiers":[
        {
            "category":"Manufacturing",
            "subcategory":"Buildings",
            "type":"Manufacturing & Wholesale Goods"
        }
    ],
    "sg:phone":"+44 1206 760376",
    "sg:postcode":"CO1 1BA",
    "sg:province":"Essex",
    "sg:tags":[
        "portable"
    ],
    "wof:name":"Eastern Plant Service Ltd",
    "wof:placetype":"venue"
},
  "geometry": {"coordinates":[0.8992599845,51.8900108337],"type":"Point"}
}