{
  "type": "Feature",
  "properties": {
    "iso:country":"GB",
    "sg:address":"Heath Lane House, Heath Lane",
    "sg:city":"Godalming",
    "sg:classifiers":[
        {
            "category":"Professional",
            "subcategory":"Secretarial Services",
            "type":"Services"
        },
        {
            "category":"Professional",
            "subcategory":"Art Services",
            "type":"Services"
        }
    ],
    "sg:phone":"+44 1483 414050",
    "sg:postcode":"GU7 1UN",
    "sg:province":"Surrey",
    "sg:tags":[
        "photographer"
    ],
    "wof:name":"Abbot Secretarial & Print Services",
    "wof:placetype":"venue"
},
  "geometry": {"coordinates":[-0.6183840036,51.1839561462],"type":"Point"}
}