{
  "type": "Feature",
  "properties": {
    "iso:country":"GB",
    "sg:address":"Unit 22 Crelake Industrial Estate, Pixon Lane",
    "sg:city":"Tavistock",
    "sg:classifiers":[
        {
            "category":"Home & Garden",
            "subcategory":"Hardware",
            "type":"Retail Goods"
        }
    ],
    "sg:postcode":"PL19 8DH",
    "sg:province":"Devon",
    "sg:tags":[
        "lawnmowers",
        "machinery"
    ],
    "wof:name":"Abbey Garden Machinery",
    "wof:placetype":"venue"
},
  "geometry": {"coordinates":[-4.147309,50.545021],"type":"Point"}
}