{
  "type": "Feature",
  "properties": {
    "iso:country":"GB",
    "sg:address":"3 Queen Street",
    "sg:city":"Nottingham",
    "sg:classifiers":[
        {
            "category":"Bars & Pubs",
            "type":"Food & Drink"
        }
    ],
    "sg:phone":"+44 115 953 1531",
    "sg:postcode":"NG1 2BT",
    "sg:province":"Nottinghamshire",
    "sg:tags":[
        "pubs",
        "inn"
    ],
    "wof:name":"Redback Bar",
    "wof:placetype":"venue"
},
  "geometry": {"coordinates":[-1.150409,52.955029],"type":"Point"}
}