{
  "type": "Feature",
  "properties": {
    "addr:full":"Poplar Tree Farm, Parson Drove Wisbech Cambridgeshire PE13 4JT",
    "addr:housenumber":"parson",
    "addr:postcode":"pe13 4jt",
    "addr:street":"Poplar;Drove Wisbech",
    "iso:country":"GB",
    "sg:address":"Poplar Tree Farm, Parson Drove",
    "sg:city":"Wisbech",
    "sg:classifiers":[
        {
            "category":"Farming",
            "subcategory":"Livestock Farm",
            "type":"Manufacturing & Wholesale Goods"
        }
    ],
    "sg:postcode":"PE13 4JT",
    "sg:province":"Cambridgeshire",
    "sg:tags":[
        "others"
    ],
    "wof:name":"A Rowell & Sons",
    "wof:placetype":"venue"
},
  "geometry": {"coordinates":[0.102086,52.652725],"type":"Point"}
}