{
  "type": "Feature",
  "properties": {
    "iso:country":"GB",
    "sg:address":"382 Midsummer Boulevard",
    "sg:city":"Milton Keynes",
    "sg:classifiers":[
        {
            "category":"Professional",
            "subcategory":"Computer Services",
            "type":"Services"
        }
    ],
    "sg:phone":"+44 1908 847464",
    "sg:postcode":"MK9 2RG",
    "sg:province":"Buckinghamshire",
    "sg:tags":[
        "system",
        "software"
    ],
    "wof:name":"Intersoft Corporation UK",
    "wof:placetype":"venue"
},
  "geometry": {"coordinates":[-0.763119,52.038952],"type":"Point"}
}