{
  "type": "Feature",
  "properties": {
    "iso:country":"GB",
    "sg:address":"St Andrews Dock",
    "sg:city":"Hull",
    "sg:classifiers":[
        {
            "category":"Professional",
            "subcategory":"Engineering",
            "type":"Services"
        }
    ],
    "sg:phone":"+44 1482 327873",
    "sg:postcode":"HU3 4PN",
    "sg:province":"East Riding of Yorkshire",
    "sg:tags":[
        "engineer",
        "mechanical"
    ],
    "wof:name":"Marr Vessel Management Ltd.",
    "wof:placetype":"venue"
},
  "geometry": {"coordinates":[-0.371064,53.727547],"type":"Point"}
}