{
  "type": "Feature",
  "properties": {
    "addr:full":"1037 Bolton Rd Bradford West Yorkshire BD2 4LN",
    "addr:housenumber":"1037",
    "addr:postcode":"bd2 4ln",
    "addr:street":"Bolton Rd",
    "iso:country":"GB",
    "sg:address":"1037 Bolton Rd",
    "sg:city":"Bradford",
    "sg:classifiers":[
        {
            "category":"Real Estate",
            "subcategory":"Real Estate Agent",
            "type":"Services"
        }
    ],
    "sg:phone":"+44 1274 631821",
    "sg:postcode":"BD2 4LN",
    "sg:province":"West Yorkshire",
    "wof:name":"ROBERT WATTS",
    "wof:placetype":"venue"
},
  "geometry": {"coordinates":[-1.7447140217,53.8112792969],"type":"Point"}
}