{
  "type": "Feature",
  "properties": {
    "addr:full":"Stockpit Road Liverpool Lancashire L33 7TQ",
    "addr:postcode":"l33 7tq",
    "addr:street":"Stockpit Road",
    "iso:country":"GB",
    "sg:address":"Stockpit Road",
    "sg:city":"Liverpool",
    "sg:classifiers":[
        {
            "category":"Farming",
            "subcategory":"Dairy Farm",
            "type":"Manufacturing & Wholesale Goods"
        }
    ],
    "sg:phone":"+44 151 546 2621",
    "sg:postcode":"L33 7TQ",
    "sg:province":"Lancashire",
    "wof:name":"Dale Farm",
    "wof:placetype":"venue"
},
  "geometry": {"coordinates":[-2.8526139259,53.4831504822],"type":"Point"}
}