{
  "type": "Feature",
  "properties": {
    "addr:full":"75 Jarrett Av Rochester Kent ME2 4NB",
    "addr:housenumber":"75",
    "addr:postcode":"me2 4nb",
    "addr:street":"Jarrett Av Rochester",
    "iso:country":"GB",
    "sg:address":"75 Jarrett Av",
    "sg:city":"Rochester",
    "sg:classifiers":[
        {
            "category":"Cinema",
            "subcategory":"Movie Rental",
            "type":"Entertainment"
        }
    ],
    "sg:phone":"+44 1634 712755",
    "sg:postcode":"ME2 4NB",
    "sg:province":"Kent",
    "sg:tags":[
        "video",
        "library"
    ],
    "wof:name":"City Video",
    "wof:placetype":"venue"
},
  "geometry": {"coordinates":[0.5057740211,51.4095573425],"type":"Point"}
}