{
  "type": "Feature",
  "properties": {
    "addr:full":"33 Cornwall Close Warwick Warwickshire CV34 5HX",
    "addr:housenumber":"33",
    "addr:postcode":"cv34 5hx",
    "addr:street":"Cornwall Close",
    "iso:country":"GB",
    "sg:address":"33 Cornwall Close",
    "sg:city":"Warwick",
    "sg:classifiers":[
        {
            "category":"Building & Trades",
            "subcategory":"Plumbing",
            "type":"Services"
        }
    ],
    "sg:phone":"+44 1926 402056",
    "sg:postcode":"CV34 5HX",
    "sg:province":"Warwickshire",
    "sg:tags":[
        "heating"
    ],
    "wof:name":"R Goodman Plumbing & Heating",
    "wof:placetype":"venue"
},
  "geometry": {"coordinates":[-1.5799950361,52.2914619446],"type":"Point"}
}