{
  "type": "Feature",
  "properties": {
    "iso:country":"GB",
    "sg:address":"35 Reynolds Rd",
    "sg:city":"Hove",
    "sg:classifiers":[
        {
            "category":"Building & Trades",
            "subcategory":"Construction",
            "type":"Services"
        }
    ],
    "sg:postcode":"BN3 5RJ",
    "sg:province":"East Sussex",
    "sg:tags":[
        "builder"
    ],
    "wof:name":"Pocock Bricklaying Contractors",
    "wof:placetype":"venue"
},
  "geometry": {"coordinates":[-0.187921,50.833256],"type":"Point"}
}