{
  "type": "Feature",
  "properties": {
    "addr:full":"Harrow Club W10, 189 Freston Rd Ladbroke Grove Greater London W10 6TH",
    "addr:housenumber":"189",
    "addr:postcode":"w10 6th",
    "addr:street":"Freston Rd",
    "iso:country":"GB",
    "sg:address":"Harrow Club W10, 189 Freston Rd",
    "sg:city":"Ladbroke Grove",
    "sg:classifiers":[
        {
            "category":"Government",
            "subcategory":"Office",
            "type":"Public Place"
        }
    ],
    "sg:phone":"+44 20 8969 2528",
    "sg:postcode":"W10 6TH",
    "sg:province":"Greater London",
    "sg:tags":[
        "local"
    ],
    "wof:name":"London Borough Of Kensington & Chelsea",
    "wof:placetype":"venue"
},
  "geometry": {"coordinates":[-0.2194900066,51.5129318237],"type":"Point"}
}