{
  "type": "Feature",
  "properties": {
    "addr:full":"Edwinstowe House, High Street Edwinstowe Nottinghamshire NG21 9PR",
    "addr:postcode":"ng21 9pr",
    "addr:street":"High Street",
    "iso:country":"GB",
    "sg:address":"Edwinstowe House, High Street",
    "sg:city":"Edwinstowe",
    "sg:classifiers":[
        {
            "category":"Professional",
            "subcategory":"Art Services",
            "type":"Services"
        }
    ],
    "sg:phone":"+44 1623 821567",
    "sg:postcode":"NG21 9PR",
    "sg:province":"Nottinghamshire",
    "sg:tags":[
        "graphic",
        "designer"
    ],
    "wof:name":"Mousetrap Advertising & Design",
    "wof:placetype":"venue"
},
  "geometry": {"coordinates":[-1.064164,53.194229],"type":"Point"}
}