{
  "type": "Feature",
  "properties": {
    "addr:full":"Garamond House, 181-189 Grove Road London Greater London E17 9BZ",
    "addr:housenumber":"181-189",
    "addr:postcode":"e17 9bz",
    "addr:street":"Grove Road",
    "iso:country":"GB",
    "sg:address":"Garamond House, 181-189 Grove Road",
    "sg:city":"London",
    "sg:classifiers":[
        {
            "category":"Professional",
            "subcategory":"Printing & Photocopies",
            "type":"Services"
        }
    ],
    "sg:phone":"+44 20 8520 5249",
    "sg:postcode":"E17 9BZ",
    "sg:province":"Greater London",
    "sg:tags":[
        "printer"
    ],
    "wof:name":"INTERCITY PRINT FINANCIAL LTD",
    "wof:placetype":"venue"
},
  "geometry": {"coordinates":[-0.006795,51.579163],"type":"Point"}
}