{
  "type": "Feature",
  "properties": {
    "addr:full":"6 Sheep Walk, Caversham Reading Berkshire RG4 8NE",
    "addr:housenumber":"6",
    "addr:postcode":"rg4 8ne",
    "addr:street":"Sheep Walk",
    "iso:country":"GB",
    "sg:address":"6 Sheep Walk, Caversham",
    "sg:city":"Reading",
    "sg:classifiers":[
        {
            "category":"Real Estate",
            "subcategory":"Surveying",
            "type":"Services"
        }
    ],
    "sg:postcode":"RG4 8NE",
    "sg:province":"Berkshire",
    "sg:tags":[
        "surveyor",
        "valuer"
    ],
    "wof:name":"Heaven & Sadler",
    "wof:placetype":"venue"
},
  "geometry": {"coordinates":[-0.9699770212,51.4777297974],"type":"Point"}
}