{
  "type": "Feature",
  "properties": {
    "addr:full":"Builders Yard, Cefn Cross, Cefn Cribwr Bridgend Bridgend CF32 0DB",
    "addr:postcode":"cf32 0db",
    "addr:street":"Cefn Cross",
    "iso:country":"GB",
    "sg:address":"Builders Yard, Cefn Cross, Cefn Cribwr",
    "sg:city":"Bridgend",
    "sg:classifiers":[
        {
            "category":"Building & Trades",
            "subcategory":"Construction",
            "type":"Services"
        },
        {
            "category":"Manufacturing",
            "subcategory":"Building Materials",
            "type":"Manufacturing & Wholesale Goods"
        }
    ],
    "sg:phone":"+44 1656 744942",
    "sg:postcode":"CF32 0DB",
    "sg:province":"Bridgend",
    "sg:tags":[
        "merchant",
        "builder"
    ],
    "wof:name":"H&T Stanton",
    "wof:placetype":"venue"
},
  "geometry": {"coordinates":[-3.650289,51.531715],"type":"Point"}
}