{
  "type": "Feature",
  "properties": {
    "iso:country":"GB",
    "sg:address":"Pitt St",
    "sg:city":"Liverpool",
    "sg:classifiers":[
        {
            "category":"Education",
            "subcategory":"School",
            "type":"Public Place"
        }
    ],
    "sg:phone":"+44 151 709 2572",
    "sg:postcode":"L1 5BY",
    "sg:province":"Merseyside",
    "sg:tags":[
        "local",
        "authority"
    ],
    "wof:name":"St. Vincent's R.C Junior Mixed Infants",
    "wof:placetype":"venue"
},
  "geometry": {"coordinates":[-2.979534,53.398193],"type":"Point"}
}