{
  "type": "Feature",
  "properties": {
    "addr:full":"Carlisle Rd Airdrie North Lanarkshire ML6 8RH",
    "addr:postcode":"ml6 8rh",
    "addr:street":"Carlisle Rd",
    "iso:country":"GB",
    "sg:address":"Carlisle Rd",
    "sg:city":"Airdrie",
    "sg:classifiers":[
        {
            "category":"Home & Garden",
            "subcategory":"Home Furnishings",
            "type":"Retail Goods"
        }
    ],
    "sg:phone":"+44 1236 755000",
    "sg:postcode":"ML6 8RH",
    "sg:province":"North Lanarkshire",
    "sg:tags":[
        "awning",
        "canopy",
        "blinds"
    ],
    "wof:name":"IC Blinds",
    "wof:placetype":"venue"
},
  "geometry": {"coordinates":[-3.9643290043,55.8608207703],"type":"Point"}
}