{
  "type": "Feature",
  "properties": {
    "addr:full":"25 East Street Newquay Cornwall TR7 1DN",
    "addr:housenumber":"25",
    "addr:postcode":"tr7 1dn",
    "addr:street":"East Street",
    "iso:country":"GB",
    "sg:address":"25 East Street",
    "sg:city":"Newquay",
    "sg:classifiers":[
        {
            "category":"Banks & Credit Unions",
            "subcategory":"Financial Services",
            "type":"Services"
        }
    ],
    "sg:phone":"+44 1637 878787",
    "sg:postcode":"TR7 1DN",
    "sg:province":"Cornwall",
    "sg:tags":[
        "adviser"
    ],
    "wof:name":"John Eaves Associates",
    "wof:placetype":"venue"
},
  "geometry": {"coordinates":[-5.080912,50.414146],"type":"Point"}
}