{
  "type": "Feature",
  "properties": {
    "addr:full":"29 Cross Grn Basildon Essex SS16 5QW",
    "addr:housenumber":"29",
    "addr:postcode":"ss16 5qw",
    "addr:street":"Cross Grn",
    "iso:country":"GB",
    "sg:address":"29 Cross Grn",
    "sg:city":"Basildon",
    "sg:classifiers":[
        {
            "category":"Professional",
            "subcategory":"Detective & Security Services",
            "type":"Services"
        }
    ],
    "sg:phone":"+44 1268 545853",
    "sg:postcode":"SS16 5QW",
    "sg:province":"Essex",
    "sg:tags":[
        "alarm",
        "burglar",
        "system"
    ],
    "wof:name":"Belltronics Security Systems",
    "wof:placetype":"venue"
},
  "geometry": {"coordinates":[0.449925,51.566841],"type":"Point"}
}