{
  "type": "Feature",
  "properties": {
    "iso:country":"GB",
    "sg:address":"Rosegill, Hillside",
    "sg:city":"Morpeth",
    "sg:classifiers":[
        {
            "category":"Building & Trades",
            "subcategory":"Construction",
            "type":"Services"
        }
    ],
    "sg:phone":"+44 1669 620690",
    "sg:postcode":"NE65 7PT",
    "sg:province":"Northumberland",
    "sg:tags":[
        "builder"
    ],
    "wof:name":"Scott & Robson",
    "wof:placetype":"venue"
},
  "geometry": {"coordinates":[-1.931498,55.331196],"type":"Point"}
}