{
  "type": "Feature",
  "properties": {
    "addr:full":"7a Armstrong Road Benfleet Essex SS7 4PS",
    "addr:housenumber":"7a",
    "addr:postcode":"ss7 4ps",
    "addr:street":"Armstrong Road",
    "iso:country":"GB",
    "sg:address":"7a Armstrong Road",
    "sg:city":"Benfleet",
    "sg:classifiers":[
        {
            "category":"Home & Garden",
            "subcategory":"Furniture",
            "type":"Retail Goods"
        }
    ],
    "sg:phone":"+44 1268 752233",
    "sg:postcode":"SS7 4PS",
    "sg:province":"Essex",
    "wof:name":"Nostalgic Pine Ltd.",
    "wof:placetype":"venue"
},
  "geometry": {"coordinates":[0.5626050234,51.5735054016],"type":"Point"}
}