{
  "type": "Feature",
  "properties": {
    "addr:full":"19 Brookside Thame Buckinghamshire OX9 3DE",
    "addr:housenumber":"19",
    "addr:postcode":"ox9 3de",
    "addr:street":"Brookside",
    "iso:country":"GB",
    "sg:address":"19 Brookside",
    "sg:city":"Thame",
    "sg:classifiers":[
        {
            "category":"Banks & Credit Unions",
            "subcategory":"Bureau De Change",
            "type":"Services"
        },
        {
            "category":"Building & Trades",
            "subcategory":"Construction",
            "type":"Services"
        }
    ],
    "sg:phone":"+44 1844 215349",
    "sg:postcode":"OX9 3DE",
    "sg:province":"Buckinghamshire",
    "sg:tags":[
        "hygiene",
        "decorator",
        "cleaning",
        "painter"
    ],
    "wof:name":"Clean Coat Services Ltd.",
    "wof:placetype":"venue"
},
  "geometry": {"coordinates":[-0.977485,51.752052],"type":"Point"}
}