{
  "type": "Feature",
  "properties": {
    "iso:country":"GB",
    "sg:address":"Talfan Farm, Meidrim Road, St Clears",
    "sg:city":"Carmarthen",
    "sg:classifiers":[
        {
            "category":"Farming",
            "subcategory":"Livestock Farm",
            "type":"Manufacturing & Wholesale Goods"
        }
    ],
    "sg:phone":"+44 1994 230678",
    "sg:postcode":"SA33 4LJ",
    "sg:province":"Carmarthenshire",
    "sg:tags":[
        "others"
    ],
    "wof:name":"Lynn A Jones",
    "wof:placetype":"venue"
},
  "geometry": {"coordinates":[-4.49613,51.835979],"type":"Point"}
}