{
  "type": "Feature",
  "properties": {
    "iso:country":"GB",
    "sg:address":"1 Aberdovey Street",
    "sg:city":"Cardiff",
    "sg:classifiers":[
        {
            "category":"Organizations",
            "subcategory":"Community Association",
            "type":"Services"
        },
        {
            "category":"Organizations",
            "subcategory":"Membership Organization",
            "type":"Services"
        }
    ],
    "sg:phone":"+44 29 2025 1029",
    "sg:postcode":"CF24 2ER",
    "sg:province":"Cardiff",
    "sg:tags":[
        "club",
        "social"
    ],
    "wof:name":"Splotts Sports & Social Club",
    "wof:placetype":"venue"
},
  "geometry": {"coordinates":[-3.1507499218,51.4802017212],"type":"Point"}
}