{
  "type": "Feature",
  "properties": {
    "addr:full":"25 Lonsdale Road Blackpool Lancashire FY1 6EE",
    "addr:housenumber":"25",
    "addr:postcode":"fy1 6ee",
    "addr:street":"Lonsdale Road",
    "iso:country":"GB",
    "sg:address":"25 Lonsdale Road",
    "sg:city":"Blackpool",
    "sg:classifiers":[
        {
            "category":"Travel",
            "subcategory":"Hotels & Motels",
            "type":"Entertainment"
        }
    ],
    "sg:phone":"+44 1253 341327",
    "sg:postcode":"FY1 6EE",
    "sg:province":"Lancashire",
    "wof:name":"Oakfield Private Hotel",
    "wof:placetype":"venue"
},
  "geometry": {"coordinates":[-3.0515639782,53.8052253723],"type":"Point"}
}