{
  "type": "Feature",
  "properties": {
    "addr:full":"65 Aspin Lane Knaresborough North Yorkshire HG5 8EX",
    "addr:housenumber":"65",
    "addr:postcode":"hg5 8ex",
    "addr:street":"Aspin Lane",
    "iso:country":"GB",
    "sg:address":"65 Aspin Lane",
    "sg:city":"Knaresborough",
    "sg:classifiers":[
        {
            "category":"Communications",
            "subcategory":"Film & Video Production",
            "type":"Services"
        }
    ],
    "sg:postcode":"HG5 8EX",
    "sg:province":"North Yorkshire",
    "sg:tags":[
        "illustrator",
        "artist"
    ],
    "wof:name":"Peter Nelson",
    "wof:placetype":"venue"
},
  "geometry": {"coordinates":[-1.4581320286,53.9999237061],"type":"Point"}
}