{
  "type": "Feature",
  "properties": {
    "iso:country":"GB",
    "sg:address":"Whenby Lodge Farm, Whenby",
    "sg:city":"York",
    "sg:classifiers":[
        {
            "category":"Farming",
            "subcategory":"Livestock Farm",
            "type":"Manufacturing & Wholesale Goods"
        }
    ],
    "sg:phone":"+44 1347 878404",
    "sg:postcode":"YO61 4SF",
    "sg:province":"North Yorkshire",
    "sg:tags":[
        "others"
    ],
    "wof:name":"Genus",
    "wof:placetype":"venue"
},
  "geometry": {"coordinates":[-1.0385839939,54.1211013794],"type":"Point"}
}