{
  "type": "Feature",
  "properties": {
    "addr:full":"Unit 3, Hill Farm Lane Chalfont St. Giles Buckinghamshire HP8 4NT",
    "addr:housenumber":"unit 3",
    "addr:postcode":"hp8 4nt",
    "addr:street":"Hill Farm Lane",
    "iso:country":"GB",
    "sg:address":"Unit 3, Hill Farm Lane",
    "sg:city":"Chalfont St. Giles",
    "sg:classifiers":[
        {
            "category":"Retail",
            "subcategory":"Auto Repair",
            "type":"Services"
        }
    ],
    "sg:phone":"+44 1494 871965",
    "sg:postcode":"HP8 4NT",
    "sg:province":"Buckinghamshire",
    "sg:tags":[
        "modification",
        "garage"
    ],
    "wof:name":"B.R Howard",
    "wof:placetype":"venue"
},
  "geometry": {"coordinates":[-0.5852959752,51.6380577087],"type":"Point"}
}