{
  "type": "Feature",
  "properties": {
    "addr:full":"2 North View Close Bath Somerset BA2 1EH",
    "addr:housenumber":"2",
    "addr:postcode":"ba2 1eh",
    "addr:street":"North View Close",
    "iso:country":"GB",
    "sg:address":"2 North View Close",
    "sg:city":"Bath",
    "sg:classifiers":[
        {
            "category":"Professional",
            "subcategory":"Employment Agencies",
            "type":"Services"
        }
    ],
    "sg:phone":"+44 1225 401777",
    "sg:postcode":"BA2 1EH",
    "sg:province":"Somerset",
    "sg:tags":[
        "recr",
        "hire",
        "driver"
    ],
    "wof:name":"A B C Drivers",
    "wof:placetype":"venue"
},
  "geometry": {"coordinates":[-2.400569,51.376041],"type":"Point"}
}