{
  "type": "Feature",
  "properties": {
    "iso:country":"GB",
    "sg:address":"Home Farm, Bondend Road, Upton St Leonards",
    "sg:city":"Gloucester",
    "sg:classifiers":[
        {
            "category":"Freight",
            "type":"Transportation"
        },
        {
            "category":"Farming",
            "subcategory":"Livestock Farm",
            "type":"Manufacturing & Wholesale Goods"
        }
    ],
    "sg:phone":"+44 1452 618656",
    "sg:postcode":"GL4 8ED",
    "sg:province":"Gloucestershire",
    "sg:tags":[
        "haulage",
        "road"
    ],
    "wof:name":"D H G Cannon",
    "wof:placetype":"venue"
},
  "geometry": {"coordinates":[-2.19306,51.832939],"type":"Point"}
}