{
  "type": "Feature",
  "properties": {
    "addr:full":"Brewery Street Keighley West Yorkshire BD21 4JQ",
    "addr:postcode":"bd21 4jq",
    "addr:street":"Brewery Street",
    "iso:country":"GB",
    "sg:address":"Brewery Street",
    "sg:city":"Keighley",
    "sg:classifiers":[
        {
            "category":"Wholesale",
            "subcategory":"Scrap",
            "type":"Manufacturing & Wholesale Goods"
        }
    ],
    "sg:phone":"+44 1535 607870",
    "sg:postcode":"BD21 4JQ",
    "sg:province":"West Yorkshire",
    "sg:tags":[
        "waste",
        "metal"
    ],
    "wof:name":"Hengbays (1984) Ltd.",
    "wof:placetype":"venue"
},
  "geometry": {"coordinates":[-1.897814,53.867954],"type":"Point"}
}