{
  "type": "Feature",
  "properties": {
    "addr:full":"Draycott Moreton-in-marsh Gloucestershire GL56 9JU",
    "addr:postcode":"gl56 9ju",
    "iso:country":"GB",
    "sg:address":"Draycott",
    "sg:city":"Moreton-in-marsh",
    "sg:classifiers":[
        {
            "category":"Professional",
            "type":"Services"
        },
        {
            "category":"Organizations",
            "subcategory":"Community Association",
            "type":"Services"
        }
    ],
    "sg:phone":"+44 1386 700488",
    "sg:postcode":"GL56 9JU",
    "sg:province":"Gloucestershire",
    "sg:tags":[
        "specialist",
        "coating"
    ],
    "sg:website":"http://www.cotek.co.uk",
    "wof:name":"Cotek Papers Ltd",
    "wof:placetype":"venue"
},
  "geometry": {"coordinates":[-1.703281045,51.9897270203],"type":"Point"}
}