{
  "type": "Feature",
  "properties": {
    "addr:full":"Tan House Farm Melksham Wiltshire SN12 6RF",
    "addr:postcode":"sn12 6rf",
    "iso:country":"GB",
    "sg:address":"Tan House Farm",
    "sg:city":"Melksham",
    "sg:classifiers":[
        {
            "category":"Professional",
            "subcategory":"Engineering",
            "type":"Services"
        }
    ],
    "sg:postcode":"SN12 6RF",
    "sg:province":"Wiltshire",
    "wof:name":"N Player Engineers",
    "wof:placetype":"venue"
},
  "geometry": {"coordinates":[-2.124364,51.369354],"type":"Point"}
}