{
  "type": "Feature",
  "properties": {
    "addr:full":"19 Upfield Horley Surrey RH6 7JY",
    "addr:housenumber":"19",
    "addr:postcode":"rh6 7jy",
    "addr:street":"Upfield",
    "iso:country":"GB",
    "sg:address":"19 Upfield",
    "sg:city":"Horley",
    "sg:classifiers":[
        {
            "category":"Retail",
            "subcategory":"Driving School",
            "type":"Services"
        }
    ],
    "sg:postcode":"RH6 7JY",
    "sg:province":"Surrey",
    "wof:name":"Autolearn School of Motoring",
    "wof:placetype":"venue"
},
  "geometry": {"coordinates":[-0.167775,51.168701],"type":"Point"}
}