{
  "type": "Feature",
  "properties": {
    "iso:country":"GB",
    "sg:address":"19 Upfield",
    "sg:city":"Horley",
    "sg:classifiers":[
        {
            "category":"Retail",
            "subcategory":"Driving School",
            "type":"Services"
        }
    ],
    "sg:postcode":"RH6 7JY",
    "sg:province":"Surrey",
    "wof:name":"Autolearn School of Motoring",
    "wof:placetype":"venue"
},
  "geometry": {"coordinates":[-0.167775,51.168701],"type":"Point"}
}