{
  "type": "Feature",
  "properties": {
    "iso:country":"GB",
    "sg:address":"Mill Street",
    "sg:city":"Macduff",
    "sg:classifiers":[
        {
            "category":"Organizations",
            "subcategory":"Membership Organization",
            "type":"Services"
        }
    ],
    "sg:phone":"+44 1261 832619",
    "sg:postcode":"AB44 1RS",
    "sg:province":"Aberdeenshire",
    "sg:tags":[
        "club"
    ],
    "wof:name":"The Royal British Legion Scotland",
    "wof:placetype":"venue"
},
  "geometry": {"coordinates":[-2.489004,57.670422],"type":"Point"}
}