{
  "type": "Feature",
  "properties": {
    "addr:full":"248 George Street Aberdeen Aberdeen City AB25 1ES",
    "addr:housenumber":"248",
    "addr:postcode":"ab25 1es",
    "addr:street":"George Street",
    "iso:country":"GB",
    "sg:address":"248 George Street",
    "sg:city":"Aberdeen",
    "sg:classifiers":[
        {
            "category":"Manufacturing",
            "subcategory":"Textiles",
            "type":"Manufacturing & Wholesale Goods"
        }
    ],
    "sg:phone":"+44 1224 624625",
    "sg:postcode":"AB25 1ES",
    "sg:province":"Aberdeen City",
    "sg:tags":[
        "made-up"
    ],
    "wof:name":"The Bed Shed",
    "wof:placetype":"venue"
},
  "geometry": {"coordinates":[-2.104125,57.1525],"type":"Point"}
}