{
  "type": "Feature",
  "properties": {
    "addr:full":"27 Evans Avenue Sutton In Ashfield Nottinghamshire NG17 2GF",
    "addr:housenumber":"27",
    "addr:postcode":"ng17 2gf",
    "addr:street":"Evans Avenue",
    "iso:country":"GB",
    "sg:address":"27 Evans Avenue",
    "sg:city":"Sutton In Ashfield",
    "sg:classifiers":[
        {
            "category":"Building & Trades",
            "subcategory":"Landscaping Services",
            "type":"Services"
        }
    ],
    "sg:phone":"+44 1623 553023",
    "sg:postcode":"NG17 2GF",
    "sg:province":"Nottinghamshire",
    "sg:tags":[
        "forestry",
        "surgeon",
        "tree"
    ],
    "wof:name":"Ashfield Tree Services",
    "wof:placetype":"venue"
},
  "geometry": {"coordinates":[-1.283249,53.12936],"type":"Point"}
}