{
  "type": "Feature",
  "properties": {
    "addr:full":"79 Mount Park Road, Eastcote Pinner Greater London HA5 2JS",
    "addr:housenumber":"79",
    "addr:postcode":"ha5 2js",
    "addr:street":"Mount Park Road",
    "iso:country":"GB",
    "sg:address":"79 Mount Park Road, Eastcote",
    "sg:city":"Pinner",
    "sg:classifiers":[
        {
            "category":"Professional",
            "subcategory":"Engineering",
            "type":"Services"
        },
        {
            "category":"Building & Trades",
            "subcategory":"Electrical",
            "type":"Services"
        }
    ],
    "sg:phone":"+44 1895 471950",
    "sg:postcode":"HA5 2JS",
    "sg:province":"Greater London",
    "sg:tags":[
        "engineer",
        "electrician",
        "contractor"
    ],
    "wof:name":"L & S Electrical",
    "wof:placetype":"venue"
},
  "geometry": {"coordinates":[-0.4081459939,51.5852622986],"type":"Point"}
}