{
  "type": "Feature",
  "properties": {
    "iso:country":"GB",
    "sg:address":"Unit 4, Bracknell Enterprise Centre",
    "sg:city":"Bracknell",
    "sg:classifiers":[
        {
            "category":"Utilities",
            "subcategory":"Telephone",
            "type":"Services"
        }
    ],
    "sg:phone":"+44 1344 380280",
    "sg:postcode":"RG12 1NF",
    "sg:province":"Berkshire",
    "sg:tags":[
        "telecommunication"
    ],
    "wof:name":"Brooktrout Technology (Europe) Ltd.",
    "wof:placetype":"venue"
},
  "geometry": {"coordinates":[-0.76144,51.415138],"type":"Point"}
}