{
  "type": "Feature",
  "properties": {
    "iso:country":"GB",
    "sg:address":"178 Gloucester Road, Bishopston",
    "sg:city":"Bristol",
    "sg:classifiers":[
        {
            "category":"Health Services",
            "subcategory":"Medical Lab",
            "type":"Services"
        },
        {
            "category":"Health Services",
            "subcategory":"Dentist",
            "type":"Services"
        }
    ],
    "sg:phone":"+44 117 942 6379",
    "sg:postcode":"BS7 8NU",
    "sg:province":"City of Bristol",
    "sg:tags":[
        "technician",
        "instrument",
        "dental"
    ],
    "wof:name":"Gloucester Road Dental Laboratories",
    "wof:placetype":"venue"
},
  "geometry": {"coordinates":[-2.589952,51.478321],"type":"Point"}
}