{
  "type": "Feature",
  "properties": {
    "addr:full":"53 Old Woking Road West Byfleet Surrey KT14 6LF",
    "addr:housenumber":"53",
    "addr:postcode":"kt14 6lf",
    "addr:street":"Old Woking Road West",
    "iso:country":"GB",
    "sg:address":"53 Old Woking Road",
    "sg:city":"West Byfleet",
    "sg:classifiers":[
        {
            "category":"Real Estate",
            "subcategory":"Real Estate Agent",
            "type":"Services"
        },
        {
            "category":"Organizations",
            "subcategory":"Membership Organization",
            "type":"Services"
        }
    ],
    "sg:phone":"+44 1932 340371",
    "sg:postcode":"KT14 6LF",
    "sg:province":"Surrey",
    "sg:tags":[
        "club"
    ],
    "wof:name":"THE RESIDENTS OF CANAL BANK LTD",
    "wof:placetype":"venue"
},
  "geometry": {"coordinates":[-0.505519,51.336811],"type":"Point"}
}