{
  "type": "Feature",
  "properties": {
    "addr:full":"107 Chiswick High Road London Greater London W4 2ED",
    "addr:housenumber":"107",
    "addr:postcode":"w4 2ed",
    "addr:street":"Chiswick High Road",
    "iso:country":"GB",
    "sg:address":"107 Chiswick High Road",
    "sg:city":"London",
    "sg:classifiers":[
        {
            "category":"Retail",
            "subcategory":"Laundry & Dry Cleaning",
            "type":"Services"
        }
    ],
    "sg:phone":"+44 20 8994 0534",
    "sg:postcode":"W4 2ED",
    "sg:province":"Greater London",
    "sg:tags":[
        "alteration"
    ],
    "wof:name":"Four Star",
    "wof:placetype":"venue"
},
  "geometry": {"coordinates":[-0.2530469894,51.49269104],"type":"Point"}
}