{
  "type": "Feature",
  "properties": {
    "iso:country":"GB",
    "sg:address":"5 Shooters Hill",
    "sg:city":"Cowes",
    "sg:classifiers":[
        {
            "category":"Shopping",
            "subcategory":"News",
            "type":"Retail Goods"
        }
    ],
    "sg:phone":"+44 1983 292013",
    "sg:postcode":"PO31 7BE",
    "sg:province":"Isle of Wight",
    "sg:tags":[
        "newsagent"
    ],
    "sg:website":"http://www.cowesholidays.co.uk",
    "wof:name":"Chivertons of Cowes",
    "wof:placetype":"venue"
},
  "geometry": {"coordinates":[-1.297488,50.760944],"type":"Point"}
}