{
  "type": "Feature",
  "properties": {
    "iso:country":"GB",
    "sg:address":"50 St James Street",
    "sg:city":"Newport",
    "sg:classifiers":[
        {
            "category":"Personal",
            "subcategory":"Beauty Salon",
            "type":"Services"
        },
        {
            "category":"Personal",
            "subcategory":"Barber",
            "type":"Services"
        }
    ],
    "sg:phone":"+44 1983 521215",
    "sg:postcode":"PO30 1LQ",
    "sg:province":"Isle of Wight",
    "sg:tags":[
        "unisex",
        "hairdresser"
    ],
    "wof:name":"Hairlines International",
    "wof:placetype":"venue"
},
  "geometry": {"coordinates":[-1.2953979969,50.6968345642],"type":"Point"}
}