{
  "type": "Feature",
  "properties": {
    "iso:country":"GB",
    "sg:address":"The Pavilion, Recreation Ground Road",
    "sg:city":"Newport",
    "sg:classifiers":[
        {
            "category":"Arena",
            "subcategory":"Sports Club",
            "type":"Entertainment"
        }
    ],
    "sg:phone":"+44 1983 522499",
    "sg:postcode":"PO30 5AH",
    "sg:province":"Isle of Wight",
    "wof:name":"Newport Victoria Sports & Social Club",
    "wof:placetype":"venue"
},
  "geometry": {"coordinates":[-1.304667,50.695614],"type":"Point"}
}