{
  "type": "Feature",
  "properties": {
    "iso:country":"GB",
    "sg:address":"30 Woodlands Rd",
    "sg:city":"Hertford",
    "sg:classifiers":[
        {
            "category":"Building & Trades",
            "subcategory":"Construction",
            "type":"Services"
        }
    ],
    "sg:postcode":"SG13 7JF",
    "sg:province":"Hertfordshire",
    "sg:tags":[
        "bricklaying"
    ],
    "wof:name":"Wells,R B,",
    "wof:placetype":"venue"
},
  "geometry": {"coordinates":[-0.060048,51.797977],"type":"Point"}
}