{
  "type": "Feature",
  "properties": {
    "addr:full":"31 High Street Saffron Walden Cambridgeshire CB10 1AT",
    "addr:housenumber":"31",
    "addr:postcode":"cb10 1at",
    "addr:street":"High Street",
    "iso:country":"GB",
    "sg:address":"31 High Street",
    "sg:city":"Saffron Walden",
    "sg:classifiers":[
        {
            "category":"Building & Trades",
            "subcategory":"Landscaping Services",
            "type":"Services"
        }
    ],
    "sg:phone":"+44 1799 506042",
    "sg:postcode":"CB10 1AT",
    "sg:province":"Cambridgeshire",
    "sg:tags":[
        "landscape",
        "contractor"
    ],
    "wof:name":"Countrywide Ground Maintenance Services",
    "wof:placetype":"venue"
},
  "geometry": {"coordinates":[0.2386559993,52.023147583],"type":"Point"}
}