{
  "type": "Feature",
  "properties": {
    "addr:full":"9 Market Street Haverfordwest Pembrokeshire SA61 1NF",
    "addr:housenumber":"9",
    "addr:postcode":"sa61 1nf",
    "addr:street":"Market Street",
    "iso:country":"GB",
    "sg:address":"9 Market Street",
    "sg:city":"Haverfordwest",
    "sg:classifiers":[
        {
            "category":"Shopping",
            "subcategory":"Gifts & Souvenirs",
            "type":"Retail Goods"
        }
    ],
    "sg:postcode":"SA61 1NF",
    "sg:province":"Pembrokeshire",
    "sg:tags":[
        "shop"
    ],
    "wof:name":"Uptown Trading Co.",
    "wof:placetype":"venue"
},
  "geometry": {"coordinates":[-4.9714,51.80061],"type":"Point"}
}