{
  "type": "Feature",
  "properties": {
    "addr:full":"10 Market Square, Royton Oldham Lancashire OL2 5QD",
    "addr:housenumber":"10",
    "addr:postcode":"ol2 5qd",
    "addr:street":"Market Square",
    "iso:country":"GB",
    "sg:address":"10 Market Square, Royton",
    "sg:city":"Oldham",
    "sg:classifiers":[
        {
            "category":"Shopping",
            "subcategory":"Florist",
            "type":"Retail Goods"
        }
    ],
    "sg:phone":"+44 161 633 5863",
    "sg:postcode":"OL2 5QD",
    "sg:province":"Lancashire",
    "wof:name":"ROYTON FLOWER SHOP",
    "wof:placetype":"venue"
},
  "geometry": {"coordinates":[-2.1228621006,53.56615448],"type":"Point"}
}