{
  "type": "Feature",
  "properties": {
    "addr:full":"16 Hall Street, Rhosllanerchrugog Wrexham Wrexham LL14 2LE",
    "addr:housenumber":"16",
    "addr:postcode":"ll14 2le",
    "addr:street":"Hall Street",
    "iso:country":"GB",
    "sg:address":"16 Hall Street, Rhosllanerchrugog",
    "sg:city":"Wrexham",
    "sg:classifiers":[
        {
            "category":"Professional",
            "subcategory":"Printing & Photocopies",
            "type":"Services"
        }
    ],
    "sg:phone":"+44 1978 840555",
    "sg:postcode":"LL14 2LE",
    "sg:province":"Wrexham",
    "sg:tags":[
        "process",
        "screen",
        "printer"
    ],
    "wof:name":"Prime Signs",
    "wof:placetype":"venue"
},
  "geometry": {"coordinates":[-3.070754,52.99947],"type":"Point"}
}