{
  "type": "Feature",
  "properties": {
    "addr:full":"27 Nelson Rd Bognor Regis West Sussex PO21 2RY",
    "addr:housenumber":"27",
    "addr:postcode":"po21 2ry",
    "addr:street":"Nelson Rd",
    "iso:country":"GB",
    "sg:address":"27 Nelson Rd",
    "sg:city":"Bognor Regis",
    "sg:classifiers":[
        {
            "category":"Travel",
            "subcategory":"Hotels & Motels",
            "type":"Entertainment"
        }
    ],
    "sg:postcode":"PO21 2RY",
    "sg:province":"West Sussex",
    "sg:tags":[
        "self",
        "catering"
    ],
    "wof:name":"Farrell Holiday Trust",
    "wof:placetype":"venue"
},
  "geometry": {"coordinates":[-0.689882,50.785076],"type":"Point"}
}