{
  "type": "Feature",
  "properties": {
    "addr:full":"Petton Grange, Petton, Burlton Shrewsbury Shropshire SY4 5TH",
    "addr:housenumber":"petton",
    "addr:postcode":"sy4 5th",
    "addr:street":"Burlton",
    "iso:country":"GB",
    "sg:address":"Petton Grange, Petton, Burlton",
    "sg:city":"Shrewsbury",
    "sg:classifiers":[
        {
            "category":"Farming",
            "subcategory":"Farm",
            "type":"Manufacturing & Wholesale Goods"
        }
    ],
    "sg:phone":"+44 1939 270627",
    "sg:postcode":"SY4 5TH",
    "sg:province":"Shropshire",
    "sg:tags":[
        "mixed",
        "crop"
    ],
    "wof:name":"E R Pickering",
    "wof:placetype":"venue"
},
  "geometry": {"coordinates":[-2.806684,52.828964],"type":"Point"}
}