{
  "type": "Feature",
  "properties": {
    "addr:full":"8 Smithies Cl Halifax West Yorkshire HX4 0HB",
    "addr:housenumber":"8",
    "addr:postcode":"hx4 0hb",
    "addr:street":"Smithies Cl Halifax West",
    "iso:country":"GB",
    "sg:address":"8 Smithies Cl",
    "sg:city":"Halifax",
    "sg:classifiers":[
        {
            "category":"Retail",
            "subcategory":"Driving School",
            "type":"Services"
        }
    ],
    "sg:phone":"+44 1422 823541",
    "sg:postcode":"HX4 0HB",
    "sg:province":"West Yorkshire",
    "wof:name":"Pelikan School Of Motoring",
    "wof:placetype":"venue"
},
  "geometry": {"coordinates":[-1.9181330204,53.6764793396],"type":"Point"}
}