{
  "type": "Feature",
  "properties": {
    "addr:full":"24 Connaught Street, Marble Arch London Greater London W2 2AF",
    "addr:housenumber":"24",
    "addr:postcode":"w2 2af",
    "addr:street":"Connaught Street",
    "iso:country":"GB",
    "sg:address":"24 Connaught Street, Marble Arch",
    "sg:city":"London",
    "sg:classifiers":[
        {
            "category":"Shopping",
            "subcategory":"Stationery & Office Supplies",
            "type":"Retail Goods"
        },
        {
            "category":"Shopping",
            "subcategory":"Comic Books",
            "type":"Retail Goods"
        }
    ],
    "sg:phone":"+44 20 7723 4154",
    "sg:postcode":"W2 2AF",
    "sg:province":"Greater London",
    "sg:tags":[
        "recording",
        "machine",
        "jeweller",
        "time"
    ],
    "wof:name":"Ancient & Modern",
    "wof:placetype":"venue"
},
  "geometry": {"coordinates":[-0.165726,51.514671],"type":"Point"}
}