{
  "type": "Feature",
  "properties": {
    "iso:country":"GB",
    "sg:address":"42 Lennox Road",
    "sg:city":"Gravesend",
    "sg:classifiers":[
        {
            "category":"Home & Garden",
            "subcategory":"Carpets & Floor Coverings",
            "type":"Retail Goods"
        }
    ],
    "sg:phone":"+44 1474 569376",
    "sg:postcode":"DA11 0ER",
    "sg:province":"Kent",
    "sg:tags":[
        "cleaner",
        "upholstery"
    ],
    "wof:name":"Kleanteam",
    "wof:placetype":"venue"
},
  "geometry": {"coordinates":[0.357704,51.439198],"type":"Point"}
}