{
  "type": "Feature",
  "properties": {
    "addr:full":"Sheldon Lane Halesowen West Midlands B62 9DR",
    "addr:postcode":"b62 9dr",
    "addr:street":"Sheldon Lane",
    "iso:country":"GB",
    "sg:address":"Sheldon Lane",
    "sg:city":"Halesowen",
    "sg:classifiers":[
        {
            "category":"Health Services",
            "subcategory":"Doctor",
            "type":"Services"
        }
    ],
    "sg:phone":"+44 121 550 2207",
    "sg:postcode":"B62 9DR",
    "sg:province":"West Midlands",
    "sg:tags":[
        "practitioners"
    ],
    "wof:name":"T B Horsburgh",
    "wof:placetype":"venue"
},
  "geometry": {"coordinates":[-2.0283501148,52.4673500061],"type":"Point"}
}