{
  "type": "Feature",
  "properties": {
    "iso:country":"GB",
    "sg:address":"Main Street, Addingham",
    "sg:city":"Ilkley",
    "sg:classifiers":[
        {
            "category":"Fast Food",
            "type":"Food & Drink"
        },
        {
            "category":"Food & Beverages",
            "subcategory":"Meat & Fish",
            "type":"Retail Goods"
        }
    ],
    "sg:phone":"+44 1943 830610",
    "sg:postcode":"LS29 0PD",
    "sg:province":"North Yorkshire",
    "sg:tags":[
        "shop",
        "chip"
    ],
    "wof:name":"Old Station Fisheries",
    "wof:placetype":"venue"
},
  "geometry": {"coordinates":[-1.883444,53.944263],"type":"Point"}
}