{
  "type": "Feature",
  "properties": {
    "addr:full":"9 High Street, Wendover Aylesbury Buckinghamshire HP22 6DU",
    "addr:housenumber":"9",
    "addr:postcode":"hp22 6du",
    "addr:street":"High Street",
    "iso:country":"GB",
    "sg:address":"9 High Street, Wendover",
    "sg:city":"Aylesbury",
    "sg:classifiers":[
        {
            "category":"Travel",
            "subcategory":"Hotels & Motels",
            "type":"Entertainment"
        }
    ],
    "sg:phone":"+44 1296 622266",
    "sg:postcode":"HP22 6DU",
    "sg:province":"Buckinghamshire",
    "wof:name":"The Red Lion",
    "wof:placetype":"venue"
},
  "geometry": {"coordinates":[-0.7424640059,51.7640914917],"type":"Point"}
}