{
  "type": "Feature",
  "properties": {
    "iso:country":"GB",
    "sg:address":"55 Mossway, Croxteth",
    "sg:city":"Liverpool",
    "sg:classifiers":[
        {
            "category":"Taxi",
            "type":"Transportation"
        }
    ],
    "sg:phone":"+44 151 546 3030",
    "sg:postcode":"L11 0BL",
    "sg:province":"Merseyside",
    "sg:tags":[
        "mini",
        "cab"
    ],
    "wof:name":"Capital Taxis Ltd.",
    "wof:placetype":"venue"
},
  "geometry": {"coordinates":[-2.978481,53.409775],"type":"Point"}
}