{
  "type": "Feature",
  "properties": {
    "addr:full":"368 Christchurch Rd, West Parley Ferndown Dorset BH22 8SN",
    "addr:housenumber":"368",
    "addr:postcode":"bh22 8sn",
    "addr:street":"Christchurch Rd",
    "iso:country":"GB",
    "sg:address":"368 Christchurch Rd, West Parley",
    "sg:city":"Ferndown",
    "sg:classifiers":[
        {
            "category":"Building & Trades",
            "subcategory":"Plumbing",
            "type":"Services"
        }
    ],
    "sg:postcode":"BH22 8SN",
    "sg:province":"Dorset",
    "sg:tags":[
        "central",
        "heating"
    ],
    "wof:name":"Heatek (Pre Heat & Post Weld Heat Treatm",
    "wof:placetype":"venue"
},
  "geometry": {"coordinates":[-1.871595,50.780361],"type":"Point"}
}