{
  "type": "Feature",
  "properties": {
    "addr:full":"St Paul's Avenue Bradford West Yorkshire BD6 1SR",
    "addr:postcode":"bd6 1sr",
    "addr:street":"St Paul'S Avenue",
    "iso:country":"GB",
    "sg:address":"St Paul's Avenue",
    "sg:city":"Bradford",
    "sg:classifiers":[
        {
            "category":"Education",
            "subcategory":"School",
            "type":"Public Place"
        },
        {
            "category":"Government",
            "subcategory":"Office",
            "type":"Public Place"
        }
    ],
    "sg:phone":"+44 1274 677705",
    "sg:postcode":"BD6 1SR",
    "sg:province":"West Yorkshire",
    "sg:tags":[
        "local",
        "authority"
    ],
    "wof:name":"St Winefride's R C Primary School",
    "wof:placetype":"venue"
},
  "geometry": {"coordinates":[-1.704783,53.758213],"type":"Point"}
}