{
  "type": "Feature",
  "properties": {
    "addr:full":"Llandegveth Newport Monmouthshire NP18 1HX",
    "addr:postcode":"np18 1hx",
    "addr:street":"Llandegveth",
    "iso:country":"GB",
    "sg:address":"Llandegveth",
    "sg:city":"Newport",
    "sg:classifiers":[
        {
            "category":"Bars & Pubs",
            "type":"Food & Drink"
        },
        {
            "category":"Restaurant",
            "type":"Food & Drink"
        }
    ],
    "sg:phone":"+44 1633 450244",
    "sg:postcode":"NP18 1HX",
    "sg:province":"Monmouthshire",
    "sg:tags":[
        "-"
    ],
    "wof:name":"The Farmers Arms",
    "wof:placetype":"venue"
},
  "geometry": {"coordinates":[-2.910132,51.612434],"type":"Point"}
}