{
  "type": "Feature",
  "properties": {
    "addr:full":"10 Balmoral Close, Littleover Derby Derbyshire DE23 6DY",
    "addr:housenumber":"10",
    "addr:postcode":"de23 6dy",
    "addr:street":"Balmoral Close",
    "iso:country":"GB",
    "sg:address":"10 Balmoral Close, Littleover",
    "sg:city":"Derby",
    "sg:classifiers":[
        {
            "category":"Professional",
            "subcategory":"Engineering",
            "type":"Services"
        }
    ],
    "sg:phone":"+44 1332 372361",
    "sg:postcode":"DE23 6DY",
    "sg:province":"Derbyshire",
    "sg:tags":[
        "contractor",
        "electrical",
        "engineer"
    ],
    "wof:name":"Phillip Gregory",
    "wof:placetype":"venue"
},
  "geometry": {"coordinates":[-1.5125479698,52.9084129333],"type":"Point"}
}