{
  "type": "Feature",
  "properties": {
    "iso:country":"GB",
    "sg:address":"24 Binns Way, Binns Road Industrial Estate",
    "sg:city":"Liverpool",
    "sg:classifiers":[
        {
            "category":"Shopping",
            "subcategory":"Computers & Home Electronics",
            "type":"Retail Goods"
        }
    ],
    "sg:phone":"+44 151 228 5544",
    "sg:postcode":"L13 1EF",
    "sg:province":"Merseyside",
    "sg:tags":[
        "electrical"
    ],
    "wof:name":"Wavertree Electrical Supplies Ltd.",
    "wof:placetype":"venue"
},
  "geometry": {"coordinates":[-2.9224290848,53.4078559875],"type":"Point"}
}