{
  "type": "Feature",
  "properties": {
    "iso:country":"GB",
    "sg:address":"13 Deans Furlong",
    "sg:city":"Tring",
    "sg:classifiers":[
        {
            "category":"Real Estate",
            "subcategory":"Surveying",
            "type":"Services"
        },
        {
            "category":"Building & Trades",
            "subcategory":"Construction",
            "type":"Services"
        }
    ],
    "sg:phone":"+44 1442 824310",
    "sg:postcode":"HP23 4AR",
    "sg:province":"Buckinghamshire",
    "sg:tags":[
        "surveyor",
        "builder"
    ],
    "wof:name":"BARRY JOHNSON",
    "wof:placetype":"venue"
},
  "geometry": {"coordinates":[-0.666154,51.796501],"type":"Point"}
}