{
  "type": "Feature",
  "properties": {
    "iso:country":"GB",
    "sg:address":"245a St Vincent Street",
    "sg:city":"Glasgow",
    "sg:classifiers":[
        {
            "category":"Fast Food",
            "type":"Food & Drink"
        }
    ],
    "sg:postcode":"G2 5QY",
    "sg:province":"Glasgow City",
    "sg:tags":[
        "away",
        "take"
    ],
    "wof:name":"Piglets Sandwich Bar",
    "wof:placetype":"venue"
},
  "geometry": {"coordinates":[-4.2641720772,55.8622512817],"type":"Point"}
}