{
  "type": "Feature",
  "properties": {
    "addr:full":"Unit 2, 222 London Road St Albans Hertfordshire AL1 2NP",
    "addr:housenumber":"unit 2 222",
    "addr:postcode":"al1 2np",
    "addr:street":"London Road",
    "iso:country":"GB",
    "sg:address":"Unit 2, 222 London Road",
    "sg:city":"St Albans",
    "sg:classifiers":[
        {
            "category":"Professional",
            "subcategory":"Computer Services",
            "type":"Services"
        }
    ],
    "sg:phone":"+44 1727 845077",
    "sg:postcode":"AL1 2NP",
    "sg:province":"Hertfordshire",
    "sg:tags":[
        "system",
        "software"
    ],
    "wof:name":"Merlin Forms Ltd.",
    "wof:placetype":"venue"
},
  "geometry": {"coordinates":[-0.3396840096,51.7507667542],"type":"Point"}
}