{
  "type": "Feature",
  "properties": {
    "iso:country":"GB",
    "sg:address":"5 Sharps Rd",
    "sg:city":"Havant",
    "sg:classifiers":[
        {
            "category":"Building & Trades",
            "subcategory":"Construction",
            "type":"Services"
        }
    ],
    "sg:postcode":"PO9 5QH",
    "sg:province":"Hampshire",
    "sg:tags":[
        "builder"
    ],
    "wof:name":"Forster,Paul,",
    "wof:placetype":"venue"
},
  "geometry": {"coordinates":[-0.968963027,50.8687400818],"type":"Point"}
}