{
  "type": "Feature",
  "properties": {
    "iso:country":"GB",
    "sg:address":"The Boars Head, Church Street, Hampton Lucy",
    "sg:city":"Warwick",
    "sg:classifiers":[
        {
            "category":"Bars & Pubs",
            "type":"Food & Drink"
        }
    ],
    "sg:phone":"+44 1789 840533",
    "sg:postcode":"CV35 8BE",
    "sg:province":"Warwickshire",
    "sg:tags":[
        "pubs",
        "house",
        "inn",
        "public",
        "activity"
    ],
    "wof:name":"Boars Head",
    "wof:placetype":"venue"
},
  "geometry": {"coordinates":[-1.60283,52.246067],"type":"Point"}
}