{
  "type": "Feature",
  "properties": {
    "iso:country":"GB",
    "sg:address":"1 Turnberry Quay, Docklands",
    "sg:city":"Poplar",
    "sg:classifiers":[
        {
            "category":"Banks & Credit Unions",
            "subcategory":"Financial Services",
            "type":"Services"
        }
    ],
    "sg:phone":"+44 20 7987 4040",
    "sg:postcode":"E14 9RD",
    "sg:province":"Greater London",
    "sg:tags":[
        "consultant"
    ],
    "wof:name":"Corporate Finance",
    "wof:placetype":"venue"
},
  "geometry": {"coordinates":[-0.016139,51.495991],"type":"Point"}
}