{
  "type": "Feature",
  "properties": {
    "iso:country":"GB",
    "sg:address":"48 High Street, Gretton",
    "sg:city":"Corby",
    "sg:classifiers":[
        {
            "category":"Government",
            "subcategory":"Post Office",
            "type":"Public Place"
        }
    ],
    "sg:phone":"+44 1536 770243",
    "sg:postcode":"NN17 3DE",
    "sg:province":"Northamptonshire",
    "wof:name":"Gretton Sub Post Office",
    "wof:placetype":"venue"
},
  "geometry": {"coordinates":[-0.675515,52.539078],"type":"Point"}
}