{
  "type": "Feature",
  "properties": {
    "iso:country":"GB",
    "sg:address":"63 Middletune Avenue",
    "sg:city":"Sittingbourne",
    "sg:classifiers":[
        {
            "category":"Shopping",
            "subcategory":"Musical Instruments",
            "type":"Retail Goods"
        }
    ],
    "sg:postcode":"ME10 2JB",
    "sg:province":"Kent",
    "wof:name":"Phillip George Bleazey",
    "wof:placetype":"venue"
},
  "geometry": {"coordinates":[0.7273229957,51.3530769348],"type":"Point"}
}