{
  "type": "Feature",
  "properties": {
    "iso:country":"GB",
    "sg:address":"Unit 7, Gatwick Metro Centre",
    "sg:city":"Horley",
    "sg:classifiers":[
        {
            "category":"Manufacturing",
            "subcategory":"Wood Products",
            "type":"Manufacturing & Wholesale Goods"
        }
    ],
    "sg:phone":"+44 1293 772473",
    "sg:postcode":"RH6 9GA",
    "sg:province":"Surrey",
    "sg:tags":[
        "packaging",
        "crate",
        "pallets"
    ],
    "wof:name":"Newick Packers Ltd.",
    "wof:placetype":"venue"
},
  "geometry": {"coordinates":[-0.1692889929,51.175365448],"type":"Point"}
}