{
  "type": "Feature",
  "properties": {
    "iso:country":"GB",
    "sg:address":"Maurice House, Southmill Rd",
    "sg:city":"Bishops Stortford",
    "sg:classifiers":[
        {
            "category":"Communications",
            "subcategory":"Newspaper",
            "type":"Services"
        }
    ],
    "sg:phone":"+44 1279 771954",
    "sg:postcode":"CM23 3DH",
    "sg:province":"Essex",
    "sg:tags":[
        "magazine"
    ],
    "wof:name":"Speedway Star",
    "wof:placetype":"venue"
},
  "geometry": {"coordinates":[0.16552,51.861736],"type":"Point"}
}