{
  "type": "Feature",
  "properties": {
    "iso:country":"GB",
    "sg:address":"247 Queenborough Rd",
    "sg:city":"Sheerness",
    "sg:classifiers":[
        {
            "category":"Travel",
            "subcategory":"Hotels & Motels",
            "type":"Entertainment"
        }
    ],
    "sg:phone":"+44 1795 663606",
    "sg:postcode":"ME12 3EW",
    "sg:province":"Kent",
    "sg:tags":[
        "house",
        "guest"
    ],
    "wof:name":"Kingsferry Guest House",
    "wof:placetype":"venue"
},
  "geometry": {"coordinates":[0.7629389763,51.4102745056],"type":"Point"}
}