{
  "type": "Feature",
  "properties": {
    "addr:full":"Waterloo Road Clitheroe Lancashire BB7 1NS",
    "addr:postcode":"bb7 1ns",
    "addr:street":"Waterloo Road",
    "iso:country":"GB",
    "sg:address":"Waterloo Road",
    "sg:city":"Clitheroe",
    "sg:classifiers":[
        {
            "category":"Professional",
            "subcategory":"Engineering",
            "type":"Services"
        }
    ],
    "sg:phone":"+44 1200 425757",
    "sg:postcode":"BB7 1NS",
    "sg:province":"Lancashire",
    "sg:tags":[
        "precision",
        "engineer"
    ],
    "wof:name":"Elan Precision",
    "wof:placetype":"venue"
},
  "geometry": {"coordinates":[-2.3868720531,53.8746376038],"type":"Point"}
}