{
  "type": "Feature",
  "properties": {
    "addr:full":"159a High Road Loughton Essex IG10 4LF",
    "addr:housenumber":"159a",
    "addr:postcode":"ig10 4lf",
    "addr:street":"High Road",
    "iso:country":"GB",
    "sg:address":"159a High Road",
    "sg:city":"Loughton",
    "sg:classifiers":[
        {
            "category":"Restaurant",
            "type":"Food & Drink"
        }
    ],
    "sg:phone":"+44 20 8508 3119",
    "sg:postcode":"IG10 4LF",
    "sg:province":"Essex",
    "sg:tags":[
        "indian"
    ],
    "wof:name":"Eastern Eye",
    "wof:placetype":"venue"
},
  "geometry": {"coordinates":[0.053087,51.645218],"type":"Point"}
}