{
  "type": "Feature",
  "properties": {
    "iso:country":"GB",
    "sg:address":"59 Glenfields, Shepshed",
    "sg:city":"Loughborough",
    "sg:classifiers":[
        {
            "category":"Building & Trades",
            "subcategory":"Construction",
            "type":"Services"
        }
    ],
    "sg:phone":"+44 1509 650028",
    "sg:postcode":"LE12 9LF",
    "sg:province":"Leicestershire",
    "sg:tags":[
        "roofing"
    ],
    "wof:name":"R J E Roofing & Building Ltd.",
    "wof:placetype":"venue"
},
  "geometry": {"coordinates":[-1.301566,52.768867],"type":"Point"}
}