{
  "type": "Feature",
  "properties": {
    "iso:country":"GB",
    "sg:address":"1120 Warwick Road, Acocks Grn",
    "sg:city":"Birmingham",
    "sg:classifiers":[
        {
            "category":"Food & Beverages",
            "subcategory":"Fruits & Vegetables",
            "type":"Retail Goods"
        }
    ],
    "sg:phone":"+44 121 693 2224",
    "sg:postcode":"B27 6BL",
    "sg:province":"West Midlands",
    "sg:tags":[
        "greengrocer"
    ],
    "wof:name":"The Big Apple",
    "wof:placetype":"venue"
},
  "geometry": {"coordinates":[-1.821271,52.446747],"type":"Point"}
}