{
  "type": "Feature",
  "properties": {
    "addr:full":"The Mound, War Coppice Road Caterham Surrey CR3 6AS",
    "addr:postcode":"cr3 6as",
    "addr:street":"Coppice Road",
    "iso:country":"GB",
    "sg:address":"The Mound, War Coppice Road",
    "sg:city":"Caterham",
    "sg:classifiers":[
        {
            "category":"Building & Trades",
            "subcategory":"Plumbing",
            "type":"Services"
        }
    ],
    "sg:phone":"+44 1883 346112",
    "sg:postcode":"CR3 6AS",
    "sg:province":"Surrey",
    "sg:tags":[
        "central",
        "heating"
    ],
    "wof:name":"S E Johnson & Sons",
    "wof:placetype":"venue"
},
  "geometry": {"coordinates":[-0.0769359991,51.281578064],"type":"Point"}
}