{
  "type": "Feature",
  "properties": {
    "addr:full":"Sandford Orcas Sherborne Dorset DT9 4SE",
    "addr:postcode":"dt9 4se",
    "addr:street":"Orcas",
    "iso:country":"GB",
    "sg:address":"Sandford Orcas",
    "sg:city":"Sherborne",
    "sg:classifiers":[
        {
            "category":"Shopping",
            "subcategory":"Florist",
            "type":"Retail Goods"
        }
    ],
    "sg:postcode":"DT9 4SE",
    "sg:province":"Dorset",
    "wof:name":"Glenholme Nursery",
    "wof:placetype":"venue"
},
  "geometry": {"coordinates":[-2.529036,50.960888],"type":"Point"}
}