{
  "type": "Feature",
  "properties": {
    "addr:full":"The Farmhouse, Beechmere Rise, Mochdre Colwyn Bay Conwy LL28 5BG",
    "addr:postcode":"ll28 5bg",
    "addr:street":"Beechmere Rise",
    "iso:country":"GB",
    "sg:address":"The Farmhouse, Beechmere Rise, Mochdre",
    "sg:city":"Colwyn Bay",
    "sg:classifiers":[
        {
            "category":"Building & Trades",
            "subcategory":"Plumbing",
            "type":"Services"
        }
    ],
    "sg:phone":"+44 1492 547199",
    "sg:postcode":"LL28 5BG",
    "sg:province":"Conwy",
    "sg:tags":[
        "heating"
    ],
    "wof:name":"Paul A Roberts",
    "wof:placetype":"venue"
},
  "geometry": {"coordinates":[-3.762324,53.291809],"type":"Point"}
}