{
  "type": "Feature",
  "properties": {
    "iso:country":"GB",
    "sg:address":"Tinker Lane, Hoyland",
    "sg:city":"Barnsley",
    "sg:classifiers":[
        {
            "category":"Banks & Credit Unions",
            "subcategory":"Bureau De Change",
            "type":"Services"
        }
    ],
    "sg:phone":"+44 1226 351155",
    "sg:postcode":"S74 0PR",
    "sg:province":"South Yorkshire",
    "sg:tags":[
        "town",
        "consultant",
        "planning"
    ],
    "wof:name":"Simon Elliott Associates",
    "wof:placetype":"venue"
},
  "geometry": {"coordinates":[-1.444969,53.505569],"type":"Point"}
}