{
  "type": "Feature",
  "properties": {
    "iso:country":"GB",
    "sg:address":"C1-c3 Stafford Park 15",
    "sg:city":"Telford",
    "sg:classifiers":[
        {
            "category":"Manufacturing",
            "subcategory":"Metals",
            "type":"Manufacturing & Wholesale Goods"
        }
    ],
    "sg:postcode":"TF3 3BB",
    "sg:province":"Shropshire",
    "sg:tags":[
        "fabricator",
        "aluminium",
        "mnfrs"
    ],
    "wof:name":"George G Boliver",
    "wof:placetype":"venue"
},
  "geometry": {"coordinates":[-2.437082,52.679028],"type":"Point"}
}