{
  "type": "Feature",
  "properties": {
    "addr:full":"C/o Co-op New Barclay House, 234 Botley Road Oxford Oxfordshire OX2 0HP",
    "addr:housenumber":"234",
    "addr:postcode":"ox2 0hp",
    "addr:street":"C;Botley Road",
    "iso:country":"GB",
    "sg:address":"C/o Co-op New Barclay House, 234 Botley Road",
    "sg:city":"Oxford",
    "sg:classifiers":[
        {
            "category":"Retail",
            "subcategory":"Funeral Services",
            "type":"Services"
        }
    ],
    "sg:postcode":"OX2 0HP",
    "sg:province":"Oxfordshire",
    "sg:tags":[
        "cemetery",
        "crematorium"
    ],
    "wof:name":"Arthur W  Bruce Ltd.",
    "wof:placetype":"venue"
},
  "geometry": {"coordinates":[-1.288629055,51.7532196045],"type":"Point"}
}