{
  "type": "Feature",
  "properties": {
    "addr:full":"79 Hinckley Road Leicester Leicestershire LE3 0TD",
    "addr:housenumber":"79",
    "addr:postcode":"le3 0td",
    "addr:street":"Hinckley Road",
    "iso:country":"GB",
    "sg:address":"79 Hinckley Road",
    "sg:city":"Leicester",
    "sg:classifiers":[
        {
            "category":"Food & Beverages",
            "subcategory":"Meat & Fish",
            "type":"Retail Goods"
        }
    ],
    "sg:phone":"+44 116 233 6111",
    "sg:postcode":"LE3 0TD",
    "sg:province":"Leicestershire",
    "sg:tags":[
        "chip"
    ],
    "wof:name":"Sun Sing",
    "wof:placetype":"venue"
},
  "geometry": {"coordinates":[-1.15177,52.631767],"type":"Point"}
}