{
  "type": "Feature",
  "properties": {
    "iso:country":"GB",
    "sg:address":"49 Bridge St",
    "sg:city":"Morpeth",
    "sg:classifiers":[
        {
            "category":"Shopping",
            "subcategory":"Thrift Store",
            "type":"Retail Goods"
        }
    ],
    "sg:phone":"+44 1670 511804",
    "sg:postcode":"NE61 1PQ",
    "sg:province":"Northumberland",
    "sg:tags":[
        "shop",
        "charity"
    ],
    "wof:name":"British Heart Foundation Shops",
    "wof:placetype":"venue"
},
  "geometry": {"coordinates":[-1.687638,55.167397],"type":"Point"}
}