{
  "type": "Feature",
  "properties": {
    "iso:country":"GB",
    "sg:address":"121 Wennington Road",
    "sg:city":"Rainham",
    "sg:classifiers":[
        {
            "category":"Autos & Motor Vehicles",
            "subcategory":"Auto Supplies",
            "type":"Retail Goods"
        }
    ],
    "sg:phone":"+44 1708 554702",
    "sg:postcode":"RM13 9TH",
    "sg:province":"Essex",
    "sg:tags":[
        "component"
    ],
    "wof:name":"S & S Spares",
    "wof:placetype":"venue"
},
  "geometry": {"coordinates":[0.195255,51.516853],"type":"Point"}
}