{
  "type": "Feature",
  "properties": {
    "addr:full":"27 Liverpool Road, Penwortham Preston Lancashire PR1 9XD",
    "addr:housenumber":"27",
    "addr:postcode":"pr1 9xd",
    "addr:street":"Liverpool Road",
    "iso:country":"GB",
    "sg:address":"27 Liverpool Road, Penwortham",
    "sg:city":"Preston",
    "sg:classifiers":[
        {
            "category":"Real Estate",
            "subcategory":"Real Estate Agent",
            "type":"Services"
        }
    ],
    "sg:phone":"+44 1772 749266",
    "sg:postcode":"PR1 9XD",
    "sg:province":"Lancashire",
    "wof:name":"Reeds Rains",
    "wof:placetype":"venue"
},
  "geometry": {"coordinates":[-2.728219,53.750092],"type":"Point"}
}