{
  "type": "Feature",
  "properties": {
    "addr:full":"8 Cathcart Pl, Rutherglen Glasgow Glasgow City G73 2RB",
    "addr:housenumber":"8",
    "addr:postcode":"g73 2rb",
    "addr:street":"Cathcart Pl",
    "iso:country":"GB",
    "sg:address":"8 Cathcart Pl, Rutherglen",
    "sg:city":"Glasgow",
    "sg:classifiers":[
        {
            "category":"Home & Garden",
            "subcategory":"Building Materials",
            "type":"Retail Goods"
        }
    ],
    "sg:phone":"+44 141 647 4101",
    "sg:postcode":"G73 2RB",
    "sg:province":"Glasgow City",
    "sg:tags":[
        "fencing"
    ],
    "wof:name":"Tweedie Fencing Ltd",
    "wof:placetype":"venue"
},
  "geometry": {"coordinates":[-4.2222061157,55.8258934021],"type":"Point"}
}