{
  "type": "Feature",
  "properties": {
    "addr:full":"Unit 10 Fosse Park Industrial Estate, Everard W Leicester Leicestershire LE19 1BY",
    "addr:housenumber":"unit 10",
    "addr:postcode":"le19 1by",
    "addr:street":"Fosse Park Industrial;Everard W",
    "iso:country":"GB",
    "sg:address":"Unit 10 Fosse Park Industrial Estate, Everard W",
    "sg:city":"Leicester",
    "sg:classifiers":[
        {
            "category":"Shopping",
            "subcategory":"Clothing, Apparel, & Fashions",
            "type":"Retail Goods"
        }
    ],
    "sg:phone":"+44 116 282 5762",
    "sg:postcode":"LE19 1BY",
    "sg:province":"Leicestershire",
    "sg:tags":[
        "shop"
    ],
    "wof:name":"Dorsub (Prl) Ltd.",
    "wof:placetype":"venue"
},
  "geometry": {"coordinates":[-1.1825230122,52.5972061157],"type":"Point"}
}