{
  "type": "Feature",
  "properties": {
    "addr:full":"12 Burn Road Blaydon-on-tyne Tyne and Wear NE21 6EA",
    "addr:housenumber":"12",
    "addr:postcode":"ne21 6ea",
    "addr:street":"Burn Road",
    "iso:country":"GB",
    "sg:address":"12 Burn Road",
    "sg:city":"Blaydon-on-tyne",
    "sg:classifiers":[
        {
            "category":"Retail",
            "subcategory":"Driving School",
            "type":"Services"
        }
    ],
    "sg:postcode":"NE21 6EA",
    "sg:province":"Tyne and Wear",
    "wof:name":"Top Gear",
    "wof:placetype":"venue"
},
  "geometry": {"coordinates":[-1.735854,54.955475],"type":"Point"}
}