{
  "type": "Feature",
  "properties": {
    "addr:full":"10 Saltoun Street Wick Highland KW1 5ET",
    "addr:housenumber":"10",
    "addr:postcode":"kw1 5et",
    "addr:street":"Saltoun Street",
    "iso:country":"GB",
    "sg:address":"10 Saltoun Street",
    "sg:city":"Wick",
    "sg:classifiers":[
        {
            "category":"Professional",
            "subcategory":"Engineering",
            "type":"Services"
        }
    ],
    "sg:phone":"+44 1955 606308",
    "sg:postcode":"KW1 5ET",
    "sg:province":"Highland",
    "sg:tags":[
        "contractor",
        "electrical",
        "engineer"
    ],
    "wof:name":"R Begg Electrical",
    "wof:placetype":"venue"
},
  "geometry": {"coordinates":[-3.088023,58.440315],"type":"Point"}
}