{
  "type": "Feature",
  "properties": {
    "addr:full":"Corner Garage, High St Rotherham South Yorkshire S63 9DE",
    "addr:postcode":"s63 9de",
    "addr:street":"High St",
    "iso:country":"GB",
    "sg:address":"Corner Garage, High St",
    "sg:city":"Rotherham",
    "sg:classifiers":[
        {
            "category":"Autos & Motor Vehicles",
            "subcategory":"Auto Supplies",
            "type":"Retail Goods"
        }
    ],
    "sg:phone":"+44 1709 897391",
    "sg:postcode":"S63 9DE",
    "sg:province":"South Yorkshire",
    "sg:tags":[
        "tyre"
    ],
    "wof:name":"Goldthorpe Tyres",
    "wof:placetype":"venue"
},
  "geometry": {"coordinates":[-1.3048499823,53.5309486389],"type":"Point"}
}