{
  "type": "Feature",
  "properties": {
    "iso:country":"GB",
    "sg:address":"52 Mucklow Hill, Halesowen",
    "sg:city":"Birmingham",
    "sg:classifiers":[
        {
            "category":"Professional",
            "subcategory":"Engineering",
            "type":"Services"
        }
    ],
    "sg:postcode":"B62 8BL",
    "sg:province":"West Midlands",
    "sg:tags":[
        "civil",
        "engineer"
    ],
    "wof:name":"Colard Ltd",
    "wof:placetype":"venue"
},
  "geometry": {"coordinates":[-2.032181,52.461082],"type":"Point"}
}