{
  "type": "Feature",
  "properties": {
    "addr:full":"180 Sandgate Rd Folkestone Kent CT20 2LQ",
    "addr:housenumber":"180",
    "addr:postcode":"ct20 2lq",
    "addr:street":"Sandgate Rd",
    "iso:country":"GB",
    "sg:address":"180 Sandgate Rd",
    "sg:city":"Folkestone",
    "sg:classifiers":[
        {
            "category":"Shopping",
            "subcategory":"Pharmacy",
            "type":"Retail Goods"
        }
    ],
    "sg:phone":"+44 1303 220790",
    "sg:postcode":"CT20 2LQ",
    "sg:province":"Kent",
    "sg:tags":[
        "pharmacist",
        "chemist"
    ],
    "wof:name":"Lloyds Pharmacy",
    "wof:placetype":"venue"
},
  "geometry": {"coordinates":[1.1590739489,51.0764427185],"type":"Point"}
}