{
  "type": "Feature",
  "properties": {
    "addr:full":"2 Courtt Gardens, Stoodleigh Tiverton Devon EX16 9PL",
    "addr:housenumber":"2",
    "addr:postcode":"ex16 9pl",
    "addr:street":"Courtt Gardens",
    "iso:country":"GB",
    "sg:address":"2 Courtt Gardens, Stoodleigh",
    "sg:city":"Tiverton",
    "sg:classifiers":[
        {
            "category":"Professional",
            "subcategory":"Management & Consulting",
            "type":"Services"
        }
    ],
    "sg:phone":"+44 1398 351515",
    "sg:postcode":"EX16 9PL",
    "sg:province":"Devon",
    "sg:tags":[
        "consultant",
        "training"
    ],
    "wof:name":"James Brice Associates",
    "wof:placetype":"venue"
},
  "geometry": {"coordinates":[-3.536477,50.960098],"type":"Point"}
}