{
  "type": "Feature",
  "properties": {
    "iso:country":"GB",
    "sg:address":"39 St. Johns Hill",
    "sg:city":"Sevenoaks",
    "sg:classifiers":[
        {
            "category":"Health Services",
            "subcategory":"Doctor",
            "type":"Services"
        }
    ],
    "sg:phone":"+44 1732 747200",
    "sg:postcode":"TN13 3NT",
    "sg:province":"Kent",
    "sg:tags":[
        "practitioners"
    ],
    "wof:name":"Bakker, R D",
    "wof:placetype":"venue"
},
  "geometry": {"coordinates":[0.195298,51.284943],"type":"Point"}
}