{
  "type": "Feature",
  "properties": {
    "iso:country":"GB",
    "sg:address":"Aura House, 77 Dane Road",
    "sg:city":"Sale",
    "sg:classifiers":[
        {
            "category":"Wholesale",
            "subcategory":"Electrical",
            "type":"Manufacturing & Wholesale Goods"
        }
    ],
    "sg:phone":"+44 161 969 4714",
    "sg:postcode":"M33 7BP",
    "sg:province":"Cheshire",
    "sg:tags":[
        "equipment",
        "refrigeration"
    ],
    "wof:name":"Cooling Systems Ltd.",
    "wof:placetype":"venue"
},
  "geometry": {"coordinates":[-2.314469,53.431053],"type":"Point"}
}