{
  "type": "Feature",
  "properties": {
    "addr:full":"50 Carholme Road Lincoln Lincolnshire LN1 1ST",
    "addr:housenumber":"50",
    "addr:postcode":"ln1 1st",
    "addr:street":"Carholme Road",
    "iso:country":"GB",
    "sg:address":"50 Carholme Road",
    "sg:city":"Lincoln",
    "sg:classifiers":[
        {
            "category":"Wholesale",
            "subcategory":"Office Equipment",
            "type":"Manufacturing & Wholesale Goods"
        },
        {
            "category":"Banks & Credit Unions",
            "subcategory":"Bureau De Change",
            "type":"Services"
        },
        {
            "category":"Manufacturing",
            "subcategory":"Tools & Machinery",
            "type":"Manufacturing & Wholesale Goods"
        }
    ],
    "sg:phone":"+44 1522 824555",
    "sg:postcode":"LN1 1ST",
    "sg:province":"Lincolnshire",
    "sg:tags":[
        "merchant",
        "epos",
        "register",
        "cash",
        "accessory"
    ],
    "sg:website":"http://www.crs-epos.co.uk",
    "wof:name":"C R S Business Systems",
    "wof:placetype":"venue"
},
  "geometry": {"coordinates":[-0.552105,53.231724],"type":"Point"}
}