{
  "type": "Feature",
  "properties": {
    "addr:full":"Crown Bridge, Penkridge Stafford Shropshire ST19 5AA",
    "addr:postcode":"st19 5aa",
    "addr:street":"Crown",
    "iso:country":"GB",
    "sg:address":"Crown Bridge, Penkridge",
    "sg:city":"Stafford",
    "sg:classifiers":[
        {
            "category":"Professional",
            "subcategory":"Lawyer & Legal Services",
            "type":"Services"
        }
    ],
    "sg:phone":"+44 1785 712243",
    "sg:postcode":"ST19 5AA",
    "sg:province":"Shropshire",
    "sg:tags":[
        "solicitor"
    ],
    "wof:name":"Tedstone George & Tedstone",
    "wof:placetype":"venue"
},
  "geometry": {"coordinates":[-2.116339922,52.7226066589],"type":"Point"}
}