{
  "type": "Feature",
  "properties": {
    "iso:country":"GB",
    "sg:address":"165 South St",
    "sg:city":"St Andrews",
    "sg:classifiers":[
        {
            "category":"Shopping",
            "subcategory":"Department Store",
            "type":"Retail Goods"
        }
    ],
    "sg:postcode":"KY16 9EE",
    "sg:province":"Fife",
    "wof:name":"Geddes,J C,",
    "wof:placetype":"venue"
},
  "geometry": {"coordinates":[-2.791969,56.339588],"type":"Point"}
}