{
  "type": "Feature",
  "properties": {
    "iso:country":"GB",
    "sg:address":"Unit 11-12 Phoenix Centre",
    "sg:city":"Manchester",
    "sg:classifiers":[
        {
            "category":"Personal",
            "subcategory":"Beauty Salon",
            "type":"Services"
        }
    ],
    "sg:postcode":"M1 6DD",
    "sg:province":"Greater Manchester",
    "wof:name":"Oz Beauty Clinic",
    "wof:placetype":"venue"
},
  "geometry": {"coordinates":[-2.23934,53.476929],"type":"Point"}
}