{
  "type": "Feature",
  "properties": {
    "iso:country":"GB",
    "sg:address":"Easter Buchat, Glenbuchat",
    "sg:city":"Strathdon",
    "sg:classifiers":[
        {
            "category":"Farming",
            "subcategory":"Farm",
            "type":"Manufacturing & Wholesale Goods"
        }
    ],
    "sg:phone":"+44 1975 641277",
    "sg:postcode":"AB36 8TQ",
    "sg:province":"Aberdeenshire",
    "sg:tags":[
        "mixed",
        "crop"
    ],
    "wof:name":"W Thomson & Son",
    "wof:placetype":"venue"
},
  "geometry": {"coordinates":[-3.072829,57.203426],"type":"Point"}
}