{
  "type": "Feature",
  "properties": {
    "iso:country":"GB",
    "sg:address":"4 Dorian Rd",
    "sg:city":"Hornchurch",
    "sg:classifiers":[
        {
            "category":"Building & Trades",
            "subcategory":"Construction",
            "type":"Services"
        }
    ],
    "sg:phone":"+44 1708 456316",
    "sg:postcode":"RM12 4AW",
    "sg:province":"Essex",
    "sg:tags":[
        "builder"
    ],
    "wof:name":"G Embling",
    "wof:placetype":"venue"
},
  "geometry": {"coordinates":[0.2011550069,51.5626335144],"type":"Point"}
}