{
  "type": "Feature",
  "properties": {
    "addr:full":"742 Uxbridge Rd Hayes Greater London UB4 0RU",
    "addr:housenumber":"742",
    "addr:postcode":"ub4 0ru",
    "addr:street":"Uxbridge Rd",
    "iso:country":"GB",
    "sg:address":"742 Uxbridge Rd",
    "sg:city":"Hayes",
    "sg:classifiers":[
        {
            "category":"Food & Beverages",
            "subcategory":"Bakery",
            "type":"Retail Goods"
        }
    ],
    "sg:phone":"+44 20 8573 6882",
    "sg:postcode":"UB4 0RU",
    "sg:province":"Greater London",
    "sg:tags":[
        "baker"
    ],
    "wof:name":"Bakers Oven The",
    "wof:placetype":"venue"
},
  "geometry": {"coordinates":[-0.414435,51.520386],"type":"Point"}
}