{
  "type": "Feature",
  "properties": {
    "iso:country":"GB",
    "sg:address":"Team Valley Trading Estate",
    "sg:city":"Gateshead",
    "sg:classifiers":[
        {
            "category":"Manufacturing",
            "subcategory":"Wood Products",
            "type":"Manufacturing & Wholesale Goods"
        }
    ],
    "sg:phone":"+44 191 491 0988",
    "sg:postcode":"NE11 0RF",
    "sg:province":"Tyne and Wear",
    "sg:tags":[
        "packaging",
        "crate",
        "pallets"
    ],
    "wof:name":"Osmond Hartley",
    "wof:placetype":"venue"
},
  "geometry": {"coordinates":[-1.6201889515,54.9237213135],"type":"Point"}
}