{
  "type": "Feature",
  "properties": {
    "iso:country":"GB",
    "sg:address":"46a Swansea Market",
    "sg:city":"Swansea",
    "sg:classifiers":[
        {
            "category":"Food & Beverages",
            "subcategory":"Meat & Fish",
            "type":"Retail Goods"
        }
    ],
    "sg:phone":"+44 1792 467373",
    "sg:postcode":"SA1 3PQ",
    "sg:province":"Neath Port Talbot",
    "sg:tags":[
        "butcher"
    ],
    "wof:name":"Billy Upton Butchers",
    "wof:placetype":"venue"
},
  "geometry": {"coordinates":[-4.02618,51.658707],"type":"Point"}
}