{
  "type": "Feature",
  "properties": {
    "addr:full":"500-506 Caledonian Road London Greater London N7 9RP",
    "addr:housenumber":"500-506",
    "addr:postcode":"n7 9rp",
    "addr:street":"Caledonian Road",
    "iso:country":"GB",
    "sg:address":"500-506 Caledonian Road",
    "sg:city":"London",
    "sg:classifiers":[
        {
            "category":"Autos & Motor Vehicles",
            "subcategory":"Automobile Sales",
            "type":"Retail Goods"
        }
    ],
    "sg:postcode":"N7 9RP",
    "sg:province":"Greater London",
    "sg:tags":[
        "car"
    ],
    "wof:name":"Chris Jenkins Cars Ltd.",
    "wof:placetype":"venue"
},
  "geometry": {"coordinates":[-0.117837,51.551498],"type":"Point"}
}