{
  "type": "Feature",
  "properties": {
    "addr:full":"108 Argyle St Birkenhead Merseyside L41 6AG",
    "addr:housenumber":"108",
    "addr:postcode":"l41 6ag",
    "addr:street":"Argyle St",
    "iso:country":"GB",
    "sg:address":"108 Argyle St",
    "sg:city":"Birkenhead",
    "sg:classifiers":[
        {
            "category":"Shopping",
            "subcategory":"Tobacco",
            "type":"Retail Goods"
        }
    ],
    "sg:phone":"+44 151 647 3103",
    "sg:postcode":"L41 6AG",
    "sg:province":"Merseyside",
    "sg:tags":[
        "tobacconist"
    ],
    "wof:name":"Friars Newsagents",
    "wof:placetype":"venue"
},
  "geometry": {"coordinates":[-3.020042,53.390045],"type":"Point"}
}