{
  "type": "Feature",
  "properties": {
    "iso:country":"GB",
    "sg:address":"129 Radford Road",
    "sg:city":"Nottingham",
    "sg:classifiers":[
        {
            "category":"Professional",
            "subcategory":"Printing & Photocopies",
            "type":"Services"
        }
    ],
    "sg:phone":"+44 115 942 2522",
    "sg:postcode":"NG7 5DU",
    "sg:province":"Nottinghamshire",
    "sg:tags":[
        "printer"
    ],
    "wof:name":"Thakur Press",
    "wof:placetype":"venue"
},
  "geometry": {"coordinates":[-1.1712130308,52.9663887024],"type":"Point"}
}