{
  "type": "Feature",
  "properties": {
    "addr:full":"Sale Road Manchester Cheshire M23 0JX",
    "addr:postcode":"m23 0jx",
    "addr:street":"Sale Road",
    "iso:country":"GB",
    "sg:address":"Sale Road",
    "sg:city":"Manchester",
    "sg:classifiers":[
        {
            "category":"Farming",
            "subcategory":"Nursery",
            "type":"Manufacturing & Wholesale Goods"
        }
    ],
    "sg:phone":"+44 161 998 5545",
    "sg:postcode":"M23 0JX",
    "sg:province":"Cheshire",
    "sg:tags":[
        "creche"
    ],
    "wof:name":"The Childrens Centre",
    "wof:placetype":"venue"
},
  "geometry": {"coordinates":[-2.2772190571,53.4109687805],"type":"Point"}
}