{
  "type": "Feature",
  "properties": {
    "iso:country":"GB",
    "sg:address":"3 Jubilee Buildings, Outram St",
    "sg:city":"Sutton In Ashfield",
    "sg:classifiers":[
        {
            "category":"Restaurant",
            "type":"Food & Drink"
        }
    ],
    "sg:phone":"+44 1623 552249",
    "sg:postcode":"NG17 1DE",
    "sg:province":"Nottinghamshire",
    "sg:tags":[
        "indian"
    ],
    "wof:name":"SAF'S Balti House",
    "wof:placetype":"venue"
},
  "geometry": {"coordinates":[-1.277089,53.121841],"type":"Point"}
}