{
  "type": "Feature",
  "properties": {
    "addr:full":"60 Western Road Hove East Sussex BN3 1JD",
    "addr:housenumber":"60",
    "addr:postcode":"bn3 1jd",
    "addr:street":"Western Road",
    "iso:country":"GB",
    "sg:address":"60 Western Road",
    "sg:city":"Hove",
    "sg:classifiers":[
        {
            "category":"Restaurant",
            "type":"Food & Drink"
        }
    ],
    "sg:phone":"+44 1273 773922",
    "sg:postcode":"BN3 1JD",
    "sg:province":"East Sussex",
    "sg:tags":[
        "thai"
    ],
    "wof:name":"Aumthong Thai Restaurant",
    "wof:placetype":"venue"
},
  "geometry": {"coordinates":[-0.161628,50.826069],"type":"Point"}
}