{
  "type": "Feature",
  "properties": {
    "addr:full":"Duddon Mill Farm, Duddon Tarporley Cheshire CW6 0HA",
    "addr:postcode":"cw6 0ha",
    "addr:street":"Duddon;Tarporley",
    "iso:country":"GB",
    "sg:address":"Duddon Mill Farm, Duddon",
    "sg:city":"Tarporley",
    "sg:classifiers":[
        {
            "category":"Farming",
            "subcategory":"Livestock Farm",
            "type":"Manufacturing & Wholesale Goods"
        }
    ],
    "sg:phone":"+44 1829 740586",
    "sg:postcode":"CW6 0HA",
    "sg:province":"Cheshire",
    "sg:tags":[
        "others"
    ],
    "wof:name":"D J Roberts",
    "wof:placetype":"venue"
},
  "geometry": {"coordinates":[-2.6687550545,53.1593551636],"type":"Point"}
}