{
  "type": "Feature",
  "properties": {
    "addr:full":"28 Newmarket Louth Lincolnshire LN11 9EQ",
    "addr:housenumber":"28",
    "addr:postcode":"ln11 9eq",
    "addr:street":"Newmarket Louth",
    "iso:country":"GB",
    "sg:address":"28 Newmarket",
    "sg:city":"Louth",
    "sg:classifiers":[
        {
            "category":"Home & Garden",
            "subcategory":"Carpets & Floor Coverings",
            "type":"Retail Goods"
        }
    ],
    "sg:phone":"+44 1507 607149",
    "sg:postcode":"LN11 9EQ",
    "sg:province":"Lincolnshire",
    "sg:tags":[
        "carpets",
        "rug",
        "matting"
    ],
    "wof:name":"Ashton of Louth Carpet Warehouse",
    "wof:placetype":"venue"
},
  "geometry": {"coordinates":[-0.000962,53.363247],"type":"Point"}
}