{
  "type": "Feature",
  "properties": {
    "iso:country":"GB",
    "sg:address":"55a Chapel Road, Garston",
    "sg:city":"Liverpool",
    "sg:classifiers":[
        {
            "category":"Professional",
            "subcategory":"Detective & Security Services",
            "type":"Services"
        }
    ],
    "sg:postcode":"L19 1QX",
    "sg:province":"Merseyside",
    "sg:tags":[
        "car"
    ],
    "wof:name":"Auto Electronic Services (Liverpool)",
    "wof:placetype":"venue"
},
  "geometry": {"coordinates":[-2.898149,53.35746],"type":"Point"}
}