{
  "type": "Feature",
  "properties": {
    "iso:country":"GB",
    "sg:address":"41 High St, Wombwell",
    "sg:city":"Barnsley",
    "sg:classifiers":[
        {
            "category":"Insurance",
            "subcategory":"Insurance Agent",
            "type":"Services"
        }
    ],
    "sg:postcode":"S73 8HB",
    "sg:province":"South Yorkshire",
    "wof:name":"Neil,Andrew,",
    "wof:placetype":"venue"
},
  "geometry": {"coordinates":[-1.39912,53.522617],"type":"Point"}
}