{
  "type": "Feature",
  "properties": {
    "addr:full":"Territorial Army Centre, 198 Dyke Road Brighton East Sussex BN1 5AS",
    "addr:housenumber":"198",
    "addr:postcode":"bn1 5as",
    "addr:street":"Dyke Road",
    "iso:country":"GB",
    "sg:address":"Territorial Army Centre, 198 Dyke Road",
    "sg:city":"Brighton",
    "sg:classifiers":[
        {
            "category":"Community Center",
            "subcategory":"Youth",
            "type":"Public Place"
        },
        {
            "category":"Government",
            "subcategory":"Office",
            "type":"Public Place"
        }
    ],
    "sg:phone":"+44 1273 556041",
    "sg:postcode":"BN1 5AS",
    "sg:province":"East Sussex",
    "sg:tags":[
        "organisation",
        "reserve",
        "armed",
        "centre"
    ],
    "wof:name":"Ministry of Defence",
    "wof:placetype":"venue"
},
  "geometry": {"coordinates":[-0.1537899971,50.8376808167],"type":"Point"}
}