{
  "type": "Feature",
  "properties": {
    "iso:country":"GB",
    "sg:address":"Park Road Trianing Centre, Park Road",
    "sg:city":"Barnsley",
    "sg:classifiers":[
        {
            "category":"Education",
            "subcategory":"Special Training",
            "type":"Public Place"
        }
    ],
    "sg:phone":"+44 1226 295471",
    "sg:postcode":"S70 1YD",
    "sg:province":"South Yorkshire",
    "sg:tags":[
        "product",
        "centre"
    ],
    "wof:name":"Barnsley Youth Development Association",
    "wof:placetype":"venue"
},
  "geometry": {"coordinates":[-1.4754120111,53.5465698242],"type":"Point"}
}