{
  "type": "Feature",
  "properties": {
    "iso:country":"GB",
    "sg:address":"102 Ealing Rd",
    "sg:city":"Wembley",
    "sg:classifiers":[
        {
            "category":"Health Services",
            "subcategory":"Dentist",
            "type":"Services"
        }
    ],
    "sg:phone":"+44 20 8902 5082",
    "sg:postcode":"HA0 4TH",
    "sg:province":"Greater London",
    "wof:name":"K H Dusara",
    "wof:placetype":"venue"
},
  "geometry": {"coordinates":[-0.2979309857,51.548160553],"type":"Point"}
}