{
  "type": "Feature",
  "properties": {
    "addr:full":"14 London Road Spalding Lincolnshire PE11 2TA",
    "addr:housenumber":"14",
    "addr:postcode":"pe11 2ta",
    "addr:street":"London Road",
    "iso:country":"GB",
    "sg:address":"14 London Road",
    "sg:city":"Spalding",
    "sg:classifiers":[
        {
            "category":"Travel",
            "subcategory":"Hotels & Motels",
            "type":"Entertainment"
        }
    ],
    "sg:phone":"+44 1775 723983",
    "sg:postcode":"PE11 2TA",
    "sg:province":"Lincolnshire",
    "sg:tags":[
        "house",
        "guest"
    ],
    "wof:name":"The Mallard",
    "wof:placetype":"venue"
},
  "geometry": {"coordinates":[-0.150449,52.784969],"type":"Point"}
}