{
  "type": "Feature",
  "properties": {
    "addr:full":"52 Leighfield Clo Bedford Bedfordshire MK41 0AG",
    "addr:housenumber":"52",
    "addr:postcode":"mk41 0ag",
    "addr:street":"Leighfield Clo",
    "iso:country":"GB",
    "sg:address":"52 Leighfield Clo",
    "sg:city":"Bedford",
    "sg:classifiers":[
        {
            "category":"Building & Trades",
            "subcategory":"Cleaning & Sanitation",
            "type":"Services"
        }
    ],
    "sg:postcode":"MK41 0AG",
    "sg:province":"Bedfordshire",
    "sg:tags":[
        "cleaner",
        "window"
    ],
    "wof:name":"Brown,Leonard,",
    "wof:placetype":"venue"
},
  "geometry": {"coordinates":[-0.4208790064,52.1483535767],"type":"Point"}
}