{
  "type": "Feature",
  "properties": {
    "addr:full":"Oldbury On The Hill, Didmarton Badminton Gloucestershire GL9 1EA",
    "addr:postcode":"gl9 1ea",
    "iso:country":"GB",
    "sg:address":"Oldbury On The Hill, Didmarton",
    "sg:city":"Badminton",
    "sg:classifiers":[
        {
            "category":"Professional",
            "subcategory":"Engineering",
            "type":"Services"
        }
    ],
    "sg:phone":"+44 1454 238355",
    "sg:postcode":"GL9 1EA",
    "sg:province":"Gloucestershire",
    "sg:tags":[
        "contractor",
        "electrical",
        "engineer"
    ],
    "wof:name":"Bee-Jay Electrical",
    "wof:placetype":"venue"
},
  "geometry": {"coordinates":[-2.2861380577,51.5426445007],"type":"Point"}
}