{
  "type": "Feature",
  "properties": {
    "addr:full":"2 New Kings Road London Greater London SW6 4SA",
    "addr:housenumber":"2",
    "addr:postcode":"sw6 4sa",
    "addr:street":"New Kings Road",
    "iso:country":"GB",
    "sg:address":"2 New Kings Road",
    "sg:city":"London",
    "sg:classifiers":[
        {
            "category":"Professional",
            "type":"Services"
        }
    ],
    "sg:phone":"+44 20 7736 7828",
    "sg:postcode":"SW6 4SA",
    "sg:province":"Greater London",
    "sg:tags":[
        "entertainer"
    ],
    "wof:name":"J Gurnett Personal Management Ltd.",
    "wof:placetype":"venue"
},
  "geometry": {"coordinates":[-0.190802,51.477634],"type":"Point"}
}