{
  "type": "Feature",
  "properties": {
    "iso:country":"GB",
    "sg:address":"Essex Road",
    "sg:city":"Church Stretton",
    "sg:classifiers":[
        {
            "category":"Organizations",
            "subcategory":"Membership Organization",
            "type":"Services"
        }
    ],
    "sg:phone":"+44 1694 723193",
    "sg:postcode":"SY6 6EX",
    "sg:province":"Shropshire",
    "sg:tags":[
        "club"
    ],
    "wof:name":"Church Stretton & District Club",
    "wof:placetype":"venue"
},
  "geometry": {"coordinates":[-2.802894,52.539688],"type":"Point"}
}