{
  "type": "Feature",
  "properties": {
    "addr:full":"Grange Farm, Newark Lane Newark Nottinghamshire NG24 2SL",
    "addr:postcode":"ng24 2sl",
    "addr:street":"Newark Lane",
    "iso:country":"GB",
    "sg:address":"Grange Farm, Newark Lane",
    "sg:city":"Newark",
    "sg:classifiers":[
        {
            "category":"Farming",
            "subcategory":"Livestock Farm",
            "type":"Manufacturing & Wholesale Goods"
        }
    ],
    "sg:phone":"+44 1636 626269",
    "sg:postcode":"NG24 2SL",
    "sg:province":"Nottinghamshire",
    "sg:tags":[
        "others"
    ],
    "wof:name":"F J Bett & Sons",
    "wof:placetype":"venue"
},
  "geometry": {"coordinates":[-0.809347,53.073895],"type":"Point"}
}