{
  "type": "Feature",
  "properties": {
    "iso:country":"GB",
    "sg:address":"Armstrong House, The Finningley Estate, Hayfield Lane",
    "sg:city":"Doncaster",
    "sg:classifiers":[
        {
            "category":"Wholesale",
            "subcategory":"Machinery & Supplies",
            "type":"Manufacturing & Wholesale Goods"
        }
    ],
    "sg:phone":"+44 1302 772929",
    "sg:postcode":"DN9 3GA",
    "sg:province":"Lincolnshire",
    "sg:tags":[
        "industrial",
        "commercial"
    ],
    "wof:name":"Kiremko Food Processing Equipment (U K) Ltd.",
    "wof:placetype":"venue"
},
  "geometry": {"coordinates":[-1.01205,53.48753],"type":"Point"}
}