{
  "type": "Feature",
  "properties": {
    "iso:country":"GB",
    "sg:address":"220 Citadel Road",
    "sg:city":"Plymouth",
    "sg:classifiers":[
        {
            "category":"Travel",
            "subcategory":"Hotels & Motels",
            "type":"Entertainment"
        }
    ],
    "sg:phone":"+44 1752 254760",
    "sg:postcode":"PL1 3BB",
    "sg:province":"Devon",
    "wof:name":"Jewell in Plymouth Hotel",
    "wof:placetype":"venue"
},
  "geometry": {"coordinates":[-4.145993,50.366795],"type":"Point"}
}