{
  "type": "Feature",
  "properties": {
    "addr:full":"228 High Road Ilford Essex IG1 1QF",
    "addr:housenumber":"228",
    "addr:postcode":"ig1 1qf",
    "addr:street":"High Road",
    "iso:country":"GB",
    "sg:address":"228 High Road",
    "sg:city":"Ilford",
    "sg:classifiers":[
        {
            "category":"Home & Garden",
            "subcategory":"Home Furnishings",
            "type":"Retail Goods"
        },
        {
            "category":"Home & Garden",
            "subcategory":"Carpets & Floor Coverings",
            "type":"Retail Goods"
        }
    ],
    "sg:phone":"+44 20 8508 5028",
    "sg:postcode":"IG1 1QF",
    "sg:province":"Essex",
    "sg:tags":[
        "furnishers",
        "planner",
        "bedroom"
    ],
    "wof:name":"Kilbridge Ltd.",
    "wof:placetype":"venue"
},
  "geometry": {"coordinates":[0.077731,51.559799],"type":"Point"}
}