{
  "type": "Feature",
  "properties": {
    "addr:full":"482-490 Edgware Road London Greater London W2 1EL",
    "addr:housenumber":"482-490",
    "addr:postcode":"w2 1el",
    "addr:street":"Edgware Road",
    "iso:country":"GB",
    "sg:address":"482-490 Edgware Road",
    "sg:city":"London",
    "sg:classifiers":[
        {
            "category":"Autos & Motor Vehicles",
            "subcategory":"Fuel & Gas Station",
            "type":"Retail Goods"
        }
    ],
    "sg:phone":"+44 20 7724 2015",
    "sg:postcode":"W2 1EL",
    "sg:province":"Greater London",
    "sg:tags":[
        "hr",
        "petrol"
    ],
    "wof:name":"Capital Service Station",
    "wof:placetype":"venue"
},
  "geometry": {"coordinates":[-0.1757809967,51.5240821838],"type":"Point"}
}