{
  "type": "Feature",
  "properties": {
    "iso:country":"GB",
    "sg:address":"3 Whetstone Magna, Lutterworth Road, Whetstone",
    "sg:city":"Leicester",
    "sg:classifiers":[
        {
            "category":"Professional",
            "subcategory":"Art Services",
            "type":"Services"
        }
    ],
    "sg:postcode":"LE8 6NB",
    "sg:province":"Leicestershire",
    "sg:tags":[
        "consultant",
        "design"
    ],
    "wof:name":"Axiom Design Resource Ltd.",
    "wof:placetype":"venue"
},
  "geometry": {"coordinates":[-1.1804939508,52.5642852783],"type":"Point"}
}