{
  "type": "Feature",
  "properties": {
    "addr:full":"Elton Head Road St Helens Cheshire WA9 5BW",
    "addr:postcode":"wa9 5bw",
    "addr:street":"Elton Head Road",
    "iso:country":"GB",
    "sg:address":"Elton Head Road",
    "sg:city":"St Helens",
    "sg:classifiers":[
        {
            "category":"Professional",
            "type":"Services"
        }
    ],
    "sg:postcode":"WA9 5BW",
    "sg:province":"Cheshire",
    "sg:tags":[
        "interior",
        "furnishers",
        "designer"
    ],
    "wof:name":"Sarah Burtess",
    "wof:placetype":"venue"
},
  "geometry": {"coordinates":[-2.7405860424,53.4284629822],"type":"Point"}
}