{
  "type": "Feature",
  "properties": {
    "iso:country":"GB",
    "sg:address":"84 Main Street, Burton Joyce",
    "sg:city":"Nottingham",
    "sg:classifiers":[
        {
            "category":"Retail",
            "subcategory":"Auto Repair",
            "type":"Services"
        }
    ],
    "sg:phone":"+44 115 931 2110",
    "sg:postcode":"NG14 5EP",
    "sg:province":"Nottinghamshire",
    "sg:tags":[
        "modification",
        "garage",
        "related"
    ],
    "wof:name":"Woodview Garage",
    "wof:placetype":"venue"
},
  "geometry": {"coordinates":[-1.0319479704,52.9916381836],"type":"Point"}
}