{
  "type": "Feature",
  "properties": {
    "addr:full":"313 Field End Road, Eastcote Ruislip Greater London HA4 9NT",
    "addr:housenumber":"313",
    "addr:postcode":"ha4 9nt",
    "addr:street":"Field End Road",
    "iso:country":"GB",
    "sg:address":"313 Field End Road, Eastcote",
    "sg:city":"Ruislip",
    "sg:classifiers":[
        {
            "category":"Autos & Motor Vehicles",
            "subcategory":"Automobile Sales",
            "type":"Retail Goods"
        }
    ],
    "sg:phone":"+44 20 8429 2727",
    "sg:postcode":"HA4 9NT",
    "sg:province":"Greater London",
    "sg:tags":[
        "car"
    ],
    "wof:name":"Dan Perkins (G B) Ltd.",
    "wof:placetype":"venue"
},
  "geometry": {"coordinates":[-0.395681,51.574409],"type":"Point"}
}