{
  "type": "Feature",
  "properties": {
    "addr:full":"Barons Keep, The Mount, Highclere Newbury Berkshire RG20 9PS",
    "addr:postcode":"rg20 9ps",
    "addr:street":"Barons Keep The",
    "iso:country":"GB",
    "sg:address":"Barons Keep, The Mount, Highclere",
    "sg:city":"Newbury",
    "sg:classifiers":[
        {
            "category":"Building & Trades",
            "subcategory":"Construction",
            "type":"Services"
        }
    ],
    "sg:postcode":"RG20 9PS",
    "sg:province":"Berkshire",
    "sg:tags":[
        "contractor"
    ],
    "wof:name":"Redwing Structures",
    "wof:placetype":"venue"
},
  "geometry": {"coordinates":[-1.371954,51.344936],"type":"Point"}
}