{
  "type": "Feature",
  "properties": {
    "addr:full":"1238 Melton Road, Syston Leicester Leicestershire LE7 2HB",
    "addr:housenumber":"1238",
    "addr:postcode":"le7 2hb",
    "addr:street":"Melton Road",
    "iso:country":"GB",
    "sg:address":"1238 Melton Road, Syston",
    "sg:city":"Leicester",
    "sg:classifiers":[
        {
            "category":"Home & Garden",
            "subcategory":"Kitchen Supply",
            "type":"Retail Goods"
        }
    ],
    "sg:phone":"+44 116 260 8635",
    "sg:postcode":"LE7 2HB",
    "sg:province":"Leicestershire",
    "sg:tags":[
        "glassware",
        "china"
    ],
    "wof:name":"Peggy's China Shop",
    "wof:placetype":"venue"
},
  "geometry": {"coordinates":[-1.0754100084,52.6974830627],"type":"Point"}
}