{
  "type": "Feature",
  "properties": {
    "iso:country":"GB",
    "sg:address":"314 Bradford Rd, Fartown Bar",
    "sg:city":"Huddersfield",
    "sg:classifiers":[
        {
            "category":"Health Services",
            "subcategory":"Health Practitioner",
            "type":"Services"
        }
    ],
    "sg:phone":"+44 1484 480222",
    "sg:postcode":"HD1 6LQ",
    "sg:province":"West Yorkshire",
    "sg:tags":[
        "acupuncture"
    ],
    "wof:name":"Renji Chinese Medicine Centre",
    "wof:placetype":"venue"
},
  "geometry": {"coordinates":[-1.780497,53.661175],"type":"Point"}
}