{
  "type": "Feature",
  "properties": {
    "addr:full":"11 Cannon Street, Bedminster Bristol City of Bristol BS3 1BH",
    "addr:housenumber":"11",
    "addr:postcode":"bs3 1bh",
    "addr:street":"Cannon Street",
    "iso:country":"GB",
    "sg:address":"11 Cannon Street, Bedminster",
    "sg:city":"Bristol",
    "sg:classifiers":[
        {
            "category":"Personal",
            "subcategory":"Beauty Salon",
            "type":"Services"
        }
    ],
    "sg:phone":"+44 117 966 1066",
    "sg:postcode":"BS3 1BH",
    "sg:province":"City of Bristol",
    "sg:tags":[
        "unisex",
        "hairdresser"
    ],
    "wof:name":"Bauhaus Hair Design",
    "wof:placetype":"venue"
},
  "geometry": {"coordinates":[-2.601216,51.440979],"type":"Point"}
}