{
  "type": "Feature",
  "properties": {
    "addr:full":"29 Bolton St Brixham Devon TQ5 9BZ",
    "addr:housenumber":"29",
    "addr:postcode":"tq5 9bz",
    "addr:street":"Bolton St",
    "iso:country":"GB",
    "sg:address":"29 Bolton St",
    "sg:city":"Brixham",
    "sg:classifiers":[
        {
            "category":"Shopping",
            "subcategory":"Florist",
            "type":"Retail Goods"
        }
    ],
    "sg:phone":"+44 1803 852787",
    "sg:postcode":"TQ5 9BZ",
    "sg:province":"Devon",
    "wof:name":"Flower Shop",
    "wof:placetype":"venue"
},
  "geometry": {"coordinates":[-3.51576,50.39304],"type":"Point"}
}