{
  "type": "Feature",
  "properties": {
    "iso:country":"GB",
    "sg:address":"Rainford House, Wentworth St, Birdwell",
    "sg:city":"Barnsley",
    "sg:classifiers":[
        {
            "category":"Building & Trades",
            "subcategory":"Construction",
            "type":"Services"
        }
    ],
    "sg:phone":"+44 1226 350360",
    "sg:postcode":"S70 5UN",
    "sg:province":"South Yorkshire",
    "sg:tags":[
        "decorator",
        "painter"
    ],
    "wof:name":"Rainford House of Elegance Ltd",
    "wof:placetype":"venue"
},
  "geometry": {"coordinates":[-1.481529,53.505638],"type":"Point"}
}