{
  "type": "Feature",
  "properties": {
    "iso:country":"GB",
    "sg:address":"469 Wimborne Road",
    "sg:city":"Bournemouth",
    "sg:classifiers":[
        {
            "category":"Shopping",
            "subcategory":"Bicycles & Sporting Goods",
            "type":"Retail Goods"
        },
        {
            "category":"Sports & Exercise",
            "subcategory":"Sports Center",
            "type":"Entertainment"
        }
    ],
    "sg:phone":"+44 1202 530615",
    "sg:postcode":"BH9 2AN",
    "sg:province":"Dorset",
    "sg:tags":[
        "shop",
        "sale"
    ],
    "wof:name":"S & J Sports",
    "wof:placetype":"venue"
},
  "geometry": {"coordinates":[-1.87842,50.744263],"type":"Point"}
}