{
  "type": "Feature",
  "properties": {
    "iso:country":"GB",
    "sg:address":"Queens Av",
    "sg:city":"Macclesfield",
    "sg:classifiers":[
        {
            "category":"Professional",
            "subcategory":"Engineering",
            "type":"Services"
        }
    ],
    "sg:phone":"+44 1625 420674",
    "sg:postcode":"SK10 2BN",
    "sg:province":"Cheshire",
    "wof:name":"Spectus Refurbishment",
    "wof:placetype":"venue"
},
  "geometry": {"coordinates":[-2.117979,53.269821],"type":"Point"}
}