{
  "type": "Feature",
  "properties": {
    "addr:full":"6 Totnes Close Bedford Bedfordshire MK40 3AX",
    "addr:housenumber":"6",
    "addr:postcode":"mk40 3ax",
    "addr:street":"Totnes Close",
    "iso:country":"GB",
    "sg:address":"6 Totnes Close",
    "sg:city":"Bedford",
    "sg:classifiers":[
        {
            "category":"Retail",
            "subcategory":"Storage",
            "type":"Services"
        }
    ],
    "sg:postcode":"MK40 3AX",
    "sg:province":"Bedfordshire",
    "sg:tags":[
        "household",
        "removal"
    ],
    "wof:name":"Merlin Removals",
    "wof:placetype":"venue"
},
  "geometry": {"coordinates":[-0.4456250072,52.1412887573],"type":"Point"}
}