{
  "type": "Feature",
  "properties": {
    "addr:full":"Park View, Kingfield Rd Woking Surrey GU22 9AA",
    "addr:postcode":"gu22 9aa",
    "addr:street":"Park View Kingfield Rd",
    "iso:country":"GB",
    "sg:address":"Park View, Kingfield Rd",
    "sg:city":"Woking",
    "sg:classifiers":[
        {
            "category":"Professional",
            "subcategory":"Accounting & Tax Preparation",
            "type":"Services"
        }
    ],
    "sg:phone":"+44 1483 769252",
    "sg:postcode":"GU22 9AA",
    "sg:province":"Surrey",
    "sg:tags":[
        "accountant"
    ],
    "wof:name":"Denise Nolan Book-keeping Services",
    "wof:placetype":"venue"
},
  "geometry": {"coordinates":[-0.539729,51.301659],"type":"Point"}
}