{
  "type": "Feature",
  "properties": {
    "iso:country":"GB",
    "sg:address":"Alexander Road",
    "sg:city":"Greenhithe",
    "sg:classifiers":[
        {
            "category":"Community Center",
            "type":"Public Place"
        }
    ],
    "sg:postcode":"DA9 9HH",
    "sg:province":"Kent",
    "sg:tags":[
        "centre"
    ],
    "wof:name":"GREENHITHE COMMUNITY CENTRE",
    "wof:placetype":"venue"
},
  "geometry": {"coordinates":[0.291467,51.449696],"type":"Point"}
}