{
  "type": "Feature",
  "properties": {
    "iso:country":"GB",
    "sg:address":"10 Horsewell Court, Moulton",
    "sg:city":"Northampton",
    "sg:classifiers":[
        {
            "category":"Home & Garden",
            "subcategory":"Carpets & Floor Coverings",
            "type":"Retail Goods"
        }
    ],
    "sg:postcode":"NN3 7XB",
    "sg:province":"Northamptonshire",
    "sg:tags":[
        "carpets",
        "rug",
        "matting"
    ],
    "wof:name":"Nick Ayris Carpet Fitting",
    "wof:placetype":"venue"
},
  "geometry": {"coordinates":[-0.8552830219,52.2814292908],"type":"Point"}
}