{
  "type": "Feature",
  "properties": {
    "iso:country":"GB",
    "sg:address":"Bards Park",
    "sg:city":"Stonehaven",
    "sg:classifiers":[
        {
            "category":"Farming",
            "subcategory":"Livestock Farm",
            "type":"Manufacturing & Wholesale Goods"
        }
    ],
    "sg:phone":"+44 1569 762333",
    "sg:postcode":"AB39 2XH",
    "sg:province":"Aberdeenshire",
    "sg:tags":[
        "others"
    ],
    "wof:name":"J T M Innes",
    "wof:placetype":"venue"
},
  "geometry": {"coordinates":[-2.213839,56.968201],"type":"Point"}
}