{
  "type": "Feature",
  "properties": {
    "iso:country":"GB",
    "sg:address":"Eden Way, Pages Industrial Park",
    "sg:city":"Leighton Buzzard",
    "sg:classifiers":[
        {
            "category":"Autos & Motor Vehicles",
            "subcategory":"Fuel & Gas Station",
            "type":"Retail Goods"
        },
        {
            "category":"Autos & Motor Vehicles",
            "subcategory":"Auto Supplies",
            "type":"Retail Goods"
        }
    ],
    "sg:phone":"+44 1525 850800",
    "sg:postcode":"LU7 4TZ",
    "sg:province":"Bedfordshire",
    "sg:tags":[
        "car",
        "manufacturer",
        "accessory"
    ],
    "wof:name":"Mont Blanc Industri Uk Ltd",
    "wof:placetype":"venue"
},
  "geometry": {"coordinates":[-0.6540139914,51.9089851379],"type":"Point"}
}