{
  "type": "Feature",
  "properties": {
    "addr:full":"Edward Street Rugby Warwickshire CV21 3EZ",
    "addr:postcode":"cv21 3ez",
    "addr:street":"Edward Street",
    "iso:country":"GB",
    "sg:address":"Edward Street",
    "sg:city":"Rugby",
    "sg:classifiers":[
        {
            "category":"Organizations",
            "subcategory":"Membership Organization",
            "type":"Services"
        }
    ],
    "sg:phone":"+44 1788 544527",
    "sg:postcode":"CV21 3EZ",
    "sg:province":"Warwickshire",
    "sg:tags":[
        "club"
    ],
    "wof:name":"Rugby Indian Association",
    "wof:placetype":"venue"
},
  "geometry": {"coordinates":[-1.256725,52.374714],"type":"Point"}
}