{
  "type": "Feature",
  "properties": {
    "addr:full":"The Old Rectory, The Street, Lidgate Newmarket Cambridgeshire CB8 9PP",
    "addr:postcode":"cb8 9pp",
    "addr:street":"The Street",
    "iso:country":"GB",
    "sg:address":"The Old Rectory, The Street, Lidgate",
    "sg:city":"Newmarket",
    "sg:classifiers":[
        {
            "category":"Organizations",
            "subcategory":"Non-profit Organization",
            "type":"Services"
        }
    ],
    "sg:phone":"+44 1638 552674",
    "sg:postcode":"CB8 9PP",
    "sg:province":"Cambridgeshire",
    "sg:tags":[
        "organisation",
        "voluntary",
        "charity"
    ],
    "wof:name":"Gazeley Bible Fellowship",
    "wof:placetype":"venue"
},
  "geometry": {"coordinates":[0.518247,52.191364],"type":"Point"}
}