{
  "type": "Feature",
  "properties": {
    "addr:full":"Spring Vale Street Bury Lancashire BL8 3LR",
    "addr:postcode":"bl8 3lr",
    "addr:street":"Spring Vale Street",
    "iso:country":"GB",
    "sg:address":"Spring Vale Street",
    "sg:city":"Bury",
    "sg:classifiers":[
        {
            "category":"Shopping",
            "subcategory":"Department Store",
            "type":"Retail Goods"
        }
    ],
    "sg:postcode":"BL8 3LR",
    "sg:province":"Lancashire",
    "wof:name":"F Dewar & Son Flooring",
    "wof:placetype":"venue"
},
  "geometry": {"coordinates":[-2.341189,53.612335],"type":"Point"}
}