{
  "type": "Feature",
  "properties": {
    "addr:full":"111a Felixstowe Road Ipswich Suffolk IP3 8EA",
    "addr:housenumber":"111a",
    "addr:postcode":"ip3 8ea",
    "addr:street":"Felixstowe Road",
    "iso:country":"GB",
    "sg:address":"111a Felixstowe Road",
    "sg:city":"Ipswich",
    "sg:classifiers":[
        {
            "category":"Home & Garden",
            "subcategory":"Home Furnishings",
            "type":"Retail Goods"
        }
    ],
    "sg:phone":"+44 1473 711119",
    "sg:postcode":"IP3 8EA",
    "sg:province":"Suffolk",
    "sg:tags":[
        "awning",
        "canopy",
        "blinds"
    ],
    "wof:name":"Samantha Interiors Day",
    "wof:placetype":"venue"
},
  "geometry": {"coordinates":[1.178545,52.048553],"type":"Point"}
}