{
  "type": "Feature",
  "properties": {
    "iso:country":"GB",
    "sg:address":"37 Cuckoo Lane, Whitefield",
    "sg:city":"Manchester",
    "sg:classifiers":[
        {
            "category":"Shopping",
            "subcategory":"Pharmacy",
            "type":"Retail Goods"
        }
    ],
    "sg:phone":"+44 161 725 9726",
    "sg:postcode":"M45 6TE",
    "sg:province":"Lancashire",
    "sg:tags":[
        "pharmacist",
        "chemist"
    ],
    "wof:name":"Aluminium Factors Ltd.",
    "wof:placetype":"venue"
},
  "geometry": {"coordinates":[-2.273589,53.541531],"type":"Point"}
}