{
  "type": "Feature",
  "properties": {
    "iso:country":"GB",
    "sg:address":"Lodge Farm, Station Road, Melbourne",
    "sg:city":"Derby",
    "sg:classifiers":[
        {
            "category":"Farming",
            "subcategory":"Livestock Farm",
            "type":"Manufacturing & Wholesale Goods"
        }
    ],
    "sg:phone":"+44 1332 862619",
    "sg:postcode":"DE73 1BR",
    "sg:province":"Derbyshire",
    "sg:tags":[
        "others"
    ],
    "wof:name":"A T Hames & Son",
    "wof:placetype":"venue"
},
  "geometry": {"coordinates":[-1.427308,52.826107],"type":"Point"}
}