{
  "type": "Feature",
  "properties": {
    "iso:country":"GB",
    "sg:address":"29 Downe Avenue, Cudham",
    "sg:city":"Sevenoaks",
    "sg:classifiers":[
        {
            "category":"Building & Trades",
            "subcategory":"Landscaping Services",
            "type":"Services"
        }
    ],
    "sg:phone":"+44 1689 860829",
    "sg:postcode":"TN14 7QX",
    "sg:province":"Kent",
    "sg:tags":[
        "gardening"
    ],
    "wof:name":"Fred Gee Landscapes",
    "wof:placetype":"venue"
},
  "geometry": {"coordinates":[0.073902,51.334702],"type":"Point"}
}