{
  "type": "Feature",
  "properties": {
    "addr:full":"339-341 West Green Rd Seven Sisters Greater London N15 3PB",
    "addr:housenumber":"339-341",
    "addr:postcode":"n15 3pb",
    "addr:street":"West Green Rd",
    "iso:country":"GB",
    "sg:address":"339-341 West Green Rd",
    "sg:city":"Seven Sisters",
    "sg:classifiers":[
        {
            "category":"Health Services",
            "subcategory":"Doctor",
            "type":"Services"
        }
    ],
    "sg:phone":"+44 20 8881 9606",
    "sg:postcode":"N15 3PB",
    "sg:province":"Greater London",
    "sg:tags":[
        "practitioners"
    ],
    "wof:name":"Dr M.S.A Akunjee",
    "wof:placetype":"venue"
},
  "geometry": {"coordinates":[-0.09218,51.585991],"type":"Point"}
}