{
  "type": "Feature",
  "properties": {
    "iso:country":"GB",
    "sg:address":"66 High Street",
    "sg:city":"Stockton-on-tees",
    "sg:classifiers":[
        {
            "category":"Shopping",
            "subcategory":"Clothing, Apparel, & Fashions",
            "type":"Retail Goods"
        }
    ],
    "sg:postcode":"TS18 1AF",
    "sg:province":"Durham",
    "sg:tags":[
        "shop"
    ],
    "wof:name":"Janette Andrew",
    "wof:placetype":"venue"
},
  "geometry": {"coordinates":[-1.312597,54.562992],"type":"Point"}
}