{
  "type": "Feature",
  "properties": {
    "addr:full":"Prior Lodge, Prior Lane Lincoln Lincolnshire LN4 2SP",
    "addr:postcode":"ln4 2sp",
    "addr:street":"Prior Lane",
    "iso:country":"GB",
    "sg:address":"Prior Lodge, Prior Lane",
    "sg:city":"Lincoln",
    "sg:classifiers":[
        {
            "category":"Freight",
            "type":"Transportation"
        }
    ],
    "sg:phone":"+44 1526 320929",
    "sg:postcode":"LN4 2SP",
    "sg:province":"Lincolnshire",
    "sg:tags":[
        "haulage",
        "road"
    ],
    "wof:name":"W K Tonge Transport",
    "wof:placetype":"venue"
},
  "geometry": {"coordinates":[-0.3864299953,53.1534385681],"type":"Point"}
}