{
  "type": "Feature",
  "properties": {
    "addr:full":"Meadow Rd South Lambeth Greater London SW8 1AA",
    "addr:postcode":"sw8 1aa",
    "addr:street":"Meadow Rd",
    "iso:country":"GB",
    "sg:address":"Meadow Rd",
    "sg:city":"South Lambeth",
    "sg:classifiers":[
        {
            "category":"Government",
            "subcategory":"City Hall",
            "type":"Public Place"
        }
    ],
    "sg:phone":"+44 20 7582 5521",
    "sg:postcode":"SW8 1AA",
    "sg:province":"Greater London",
    "wof:name":"Ashmole Tenants Hall",
    "wof:placetype":"venue"
},
  "geometry": {"coordinates":[-0.117743,51.482643],"type":"Point"}
}