{
  "type": "Feature",
  "properties": {
    "iso:country":"GB",
    "sg:address":"34 King St",
    "sg:city":"Clitheroe",
    "sg:classifiers":[
        {
            "category":"Food & Beverages",
            "subcategory":"Liquor & Beverages",
            "type":"Retail Goods"
        }
    ],
    "sg:phone":"+44 1200 425068",
    "sg:postcode":"BB7 2EU",
    "sg:province":"Lancashire",
    "sg:tags":[
        "beer",
        "spirit",
        "wines"
    ],
    "wof:name":"Thresher Wine Shop",
    "wof:placetype":"venue"
},
  "geometry": {"coordinates":[-2.39273,53.873386],"type":"Point"}
}