{
  "type": "Feature",
  "properties": {
    "addr:full":"174 High Road West Byfleet Surrey KT14 7RG",
    "addr:housenumber":"174",
    "addr:postcode":"kt14 7rg",
    "addr:street":"High Road West",
    "iso:country":"GB",
    "sg:address":"174 High Road",
    "sg:city":"West Byfleet",
    "sg:classifiers":[
        {
            "category":"Fast Food",
            "type":"Food & Drink"
        }
    ],
    "sg:phone":"+44 1932 355888",
    "sg:postcode":"KT14 7RG",
    "sg:province":"Surrey",
    "sg:tags":[
        "away",
        "take"
    ],
    "wof:name":"Runa Takeaway",
    "wof:placetype":"venue"
},
  "geometry": {"coordinates":[-0.4698860049,51.3378334045],"type":"Point"}
}