{
  "type": "Feature",
  "properties": {
    "addr:full":"22 The Red Lion Yard, Greenleaze Bristol City of Bristol BS4 2TL",
    "addr:housenumber":"22",
    "addr:postcode":"bs4 2tl",
    "addr:street":"The",
    "iso:country":"GB",
    "sg:address":"22 The Red Lion Yard, Greenleaze",
    "sg:city":"Bristol",
    "sg:classifiers":[
        {
            "category":"Wholesale",
            "subcategory":"Scrap",
            "type":"Manufacturing & Wholesale Goods"
        }
    ],
    "sg:phone":"+44 117 972 4272",
    "sg:postcode":"BS4 2TL",
    "sg:province":"City of Bristol",
    "sg:tags":[
        "breaker",
        "dismantlers"
    ],
    "wof:name":"Mofo Car Breakers & Dismantlers",
    "wof:placetype":"venue"
},
  "geometry": {"coordinates":[-2.56518,51.43063],"type":"Point"}
}