{
  "type": "Feature",
  "properties": {
    "addr:full":"25 Moor Lane, Padiham Burnley Lancashire BB12 8LZ",
    "addr:housenumber":"25",
    "addr:postcode":"bb12 8lz",
    "addr:street":"Moor Lane",
    "iso:country":"GB",
    "sg:address":"25 Moor Lane, Padiham",
    "sg:city":"Burnley",
    "sg:classifiers":[
        {
            "category":"Wholesale",
            "subcategory":"Machinery & Supplies",
            "type":"Manufacturing & Wholesale Goods"
        },
        {
            "category":"Retail",
            "subcategory":"Auto Repair",
            "type":"Services"
        }
    ],
    "sg:phone":"+44 1282 777566",
    "sg:postcode":"BB12 8LZ",
    "sg:province":"Lancashire",
    "sg:tags":[
        "agricultural",
        "industrial",
        "commercial",
        "sales"
    ],
    "wof:name":"TRANTEC (SOLIDS HANDLING) LTD",
    "wof:placetype":"venue"
},
  "geometry": {"coordinates":[-2.3158071041,53.8027534485],"type":"Point"}
}