{
  "type": "Feature",
  "properties": {
    "addr:full":"Linley Lodge, Westgate, Aldridge Walsall Staffordshire WS9 8DD",
    "addr:postcode":"ws9 8dd",
    "addr:street":"Westgate",
    "iso:country":"GB",
    "sg:address":"Linley Lodge, Westgate, Aldridge",
    "sg:city":"Walsall",
    "sg:classifiers":[
        {
            "category":"Manufacturing",
            "subcategory":"Metals",
            "type":"Manufacturing & Wholesale Goods"
        }
    ],
    "sg:phone":"+44 1922 451212",
    "sg:postcode":"WS9 8DD",
    "sg:province":"Staffordshire",
    "sg:tags":[
        "die-casting"
    ],
    "wof:name":"A & D Diecasters Ltd.",
    "wof:placetype":"venue"
},
  "geometry": {"coordinates":[-1.915706,52.603863],"type":"Point"}
}