{
  "type": "Feature",
  "properties": {
    "iso:country":"GB",
    "sg:address":"124 Ferry Road",
    "sg:city":"Edinburgh",
    "sg:classifiers":[
        {
            "category":"Fast Food",
            "type":"Food & Drink"
        }
    ],
    "sg:phone":"+44 131 553 7755",
    "sg:postcode":"EH6 4PG",
    "sg:province":"City of Edinburgh",
    "sg:tags":[
        "away",
        "meal",
        "outlet",
        "take"
    ],
    "wof:name":"Hung Fung",
    "wof:placetype":"venue"
},
  "geometry": {"coordinates":[-3.184826,55.974617],"type":"Point"}
}