{
  "type": "Feature",
  "properties": {
    "addr:full":"Community Centre, St Michaels Road Hitchin Hertfordshire SG4 0QY",
    "addr:postcode":"sg4 0qy",
    "addr:street":"St Michaels Road",
    "iso:country":"GB",
    "sg:address":"Community Centre, St Michaels Road",
    "sg:city":"Hitchin",
    "sg:classifiers":[
        {
            "category":"Community Center",
            "type":"Public Place"
        }
    ],
    "sg:phone":"+44 1462 432635",
    "sg:postcode":"SG4 0QY",
    "sg:province":"Hertfordshire",
    "sg:tags":[
        "centre"
    ],
    "wof:name":"St.Michaels Mount Community Association",
    "wof:placetype":"venue"
},
  "geometry": {"coordinates":[-0.2574,51.951309],"type":"Point"}
}