{
  "type": "Feature",
  "properties": {
    "addr:full":"Ashes Lane, Fenny Bentley Ashbourne Derbyshire DE6 1LD",
    "addr:postcode":"de6 1ld",
    "addr:street":"Ashes Lane",
    "iso:country":"GB",
    "sg:address":"Ashes Lane, Fenny Bentley",
    "sg:city":"Ashbourne",
    "sg:classifiers":[
        {
            "category":"Education",
            "subcategory":"School",
            "type":"Public Place"
        }
    ],
    "sg:phone":"+44 1335 350362",
    "sg:postcode":"DE6 1LD",
    "sg:province":"Derbyshire",
    "sg:tags":[
        "local",
        "authority"
    ],
    "wof:name":"Fitz Herbert C of E Primary School",
    "wof:placetype":"venue"
},
  "geometry": {"coordinates":[-1.7325639725,53.0182800293],"type":"Point"}
}