{
  "type": "Feature",
  "properties": {
    "addr:full":"13 Liverpool Gardens Worthing West Sussex BN11 1RY",
    "addr:housenumber":"13",
    "addr:postcode":"bn11 1ry",
    "addr:street":"Liverpool Gardens",
    "iso:country":"GB",
    "sg:address":"13 Liverpool Gardens",
    "sg:city":"Worthing",
    "sg:classifiers":[
        {
            "category":"Professional",
            "subcategory":"Accounting & Tax Preparation",
            "type":"Services"
        }
    ],
    "sg:phone":"+44 1903 231869",
    "sg:postcode":"BN11 1RY",
    "sg:province":"West Sussex",
    "sg:tags":[
        "accountant"
    ],
    "wof:name":"Allan White & Co",
    "wof:placetype":"venue"
},
  "geometry": {"coordinates":[-0.3719039857,50.8131103516],"type":"Point"}
}