{
  "type": "Feature",
  "properties": {
    "addr:full":"11 Sandon Gro, Erdington Birmingham West Midlands B24 9DQ",
    "addr:housenumber":"11",
    "addr:postcode":"b24 9dq",
    "addr:street":"Sandon Gro",
    "iso:country":"GB",
    "sg:address":"11 Sandon Gro, Erdington",
    "sg:city":"Birmingham",
    "sg:classifiers":[
        {
            "category":"Home & Garden",
            "subcategory":"Building Materials",
            "type":"Retail Goods"
        }
    ],
    "sg:phone":"+44 121 350 2367",
    "sg:postcode":"B24 9DQ",
    "sg:province":"West Midlands",
    "sg:tags":[
        "ironwork",
        "product",
        "production",
        "design",
        "diy",
        "iron",
        "wrought"
    ],
    "wof:name":"Jackson Green",
    "wof:placetype":"venue"
},
  "geometry": {"coordinates":[-1.831895,52.521919],"type":"Point"}
}