{
  "type": "Feature",
  "properties": {
    "addr:full":"The Instrument Workshop, Wallsend Research Stn, Davy Bank Wallsend Tyne and Wear NE28 6UZ",
    "addr:postcode":"ne28 6uz",
    "iso:country":"GB",
    "sg:address":"The Instrument Workshop, Wallsend Research Stn, Davy Bank",
    "sg:city":"Wallsend",
    "sg:classifiers":[
        {
            "category":"Professional",
            "subcategory":"Engineering",
            "type":"Services"
        }
    ],
    "sg:postcode":"NE28 6UZ",
    "sg:province":"Tyne and Wear",
    "sg:tags":[
        "engineer"
    ],
    "wof:name":"Kestrel Services 2000 Ltd",
    "wof:placetype":"venue"
},
  "geometry": {"coordinates":[-1.5233800411,54.9888191223],"type":"Point"}
}