{
  "type": "Feature",
  "properties": {
    "addr:full":"Po Box 8 Barry The Vale of Glamorgan CF63 4XU",
    "addr:housenumber":"po;8",
    "addr:postcode":"cf63 4xu",
    "addr:street":"Box;Barry The Vale",
    "iso:country":"GB",
    "sg:address":"Po Box 8",
    "sg:city":"Barry",
    "sg:classifiers":[
        {
            "category":"Home & Garden",
            "subcategory":"Hardware",
            "type":"Retail Goods"
        }
    ],
    "sg:phone":"+44 1446 736403",
    "sg:postcode":"CF63 4XU",
    "sg:province":"The Vale of Glamorgan",
    "sg:tags":[
        "tarpaulin"
    ],
    "wof:name":"Dixons (Tarpaulins) Ltd.",
    "wof:placetype":"venue"
},
  "geometry": {"coordinates":[-3.26368,51.4062],"type":"Point"}
}