{
  "type": "Feature",
  "properties": {
    "addr:full":"31 Fountain Place Loanhead Midlothian EH20 9DT",
    "addr:housenumber":"31",
    "addr:postcode":"eh20 9dt",
    "addr:street":"Fountain Place",
    "iso:country":"GB",
    "sg:address":"31 Fountain Place",
    "sg:city":"Loanhead",
    "sg:classifiers":[
        {
            "category":"Building & Trades",
            "subcategory":"Construction",
            "type":"Services"
        }
    ],
    "sg:phone":"+44 131 440 1301",
    "sg:postcode":"EH20 9DT",
    "sg:province":"Midlothian",
    "sg:tags":[
        "decorator",
        "painter"
    ],
    "wof:name":"Hamilton C B Painting & Decorating Services",
    "wof:placetype":"venue"
},
  "geometry": {"coordinates":[-3.152781,55.880882],"type":"Point"}
}