{
  "type": "Feature",
  "properties": {
    "iso:country":"GB",
    "sg:address":"7 Dale Road",
    "sg:city":"Lewes",
    "sg:classifiers":[
        {
            "category":"Communications",
            "subcategory":"Film & Video Production",
            "type":"Services"
        }
    ],
    "sg:postcode":"BN7 1LH",
    "sg:province":"East Sussex",
    "sg:tags":[
        "illustrator",
        "artist"
    ],
    "wof:name":"G Wood",
    "wof:placetype":"venue"
},
  "geometry": {"coordinates":[-0.0045699999,50.8698692322],"type":"Point"}
}