{
  "type": "Feature",
  "properties": {
    "iso:country":"GB",
    "sg:address":"High Street, Waltham",
    "sg:city":"Grimsby",
    "sg:classifiers":[
        {
            "category":"Education",
            "subcategory":"Library",
            "type":"Public Place"
        },
        {
            "category":"Government",
            "subcategory":"Office",
            "type":"Public Place"
        }
    ],
    "sg:phone":"+44 1472 323656",
    "sg:postcode":"DN37 0LL",
    "sg:province":"Lincolnshire",
    "sg:tags":[
        "book",
        "local"
    ],
    "wof:name":"Waltham Library",
    "wof:placetype":"venue"
},
  "geometry": {"coordinates":[-0.094283998,53.5180931091],"type":"Point"}
}