{
  "type": "Feature",
  "properties": {
    "addr:full":"Inchkeith Place Falkirk Falkirk FK1 2PG",
    "addr:postcode":"fk1 2pg",
    "addr:street":"Inchkeith Place",
    "iso:country":"GB",
    "sg:address":"Inchkeith Place",
    "sg:city":"Falkirk",
    "sg:classifiers":[
        {
            "category":"Place Of Worship",
            "type":"Public Place"
        }
    ],
    "sg:phone":"+44 1324 613586",
    "sg:postcode":"FK1 2PG",
    "sg:province":"Falkirk",
    "wof:name":"Church Of Jesus Christ Of Latter Day Saints",
    "wof:placetype":"venue"
},
  "geometry": {"coordinates":[-3.786791,55.987171],"type":"Point"}
}