{
  "type": "Feature",
  "properties": {
    "iso:country":"GB",
    "sg:address":"Southam Rd",
    "sg:city":"Banbury",
    "sg:classifiers":[
        {
            "category":"Education",
            "subcategory":"School",
            "type":"Public Place"
        }
    ],
    "sg:phone":"+44 1295 263026",
    "sg:postcode":"OX16 2EG",
    "sg:province":"Oxfordshire",
    "sg:tags":[
        "local",
        "authority"
    ],
    "wof:name":"St.Mary's C.E Primary School",
    "wof:placetype":"venue"
},
  "geometry": {"coordinates":[-1.340217,52.066418],"type":"Point"}
}