{
  "type": "Feature",
  "properties": {
    "iso:country":"GB",
    "sg:address":"18 Hereford Rd",
    "sg:city":"Abergavenny",
    "sg:classifiers":[
        {
            "category":"Health Services",
            "subcategory":"Podiatrist",
            "type":"Services"
        }
    ],
    "sg:phone":"+44 1873 854058",
    "sg:postcode":"NP7 5PY",
    "sg:province":"Herefordshire",
    "sg:tags":[
        "podiatrists",
        "chiropodist"
    ],
    "wof:name":"Hester E O'Leary M.Ch.S S.R.Vh M.Pod.A",
    "wof:placetype":"venue"
},
  "geometry": {"coordinates":[-3.013449,51.8256],"type":"Point"}
}