{
  "type": "Feature",
  "properties": {
    "iso:country":"GB",
    "sg:address":"Pcs House 2 Winchester Drive, South West Industrial Estate",
    "sg:city":"Peterlee",
    "sg:classifiers":[
        {
            "category":"Shopping",
            "subcategory":"Computers & Home Electronics",
            "type":"Retail Goods"
        }
    ],
    "sg:phone":"+44 191 587 3430",
    "sg:postcode":"SR8 2RJ",
    "sg:province":"Durham",
    "wof:name":"Peterlee Computer Systems Ltd.",
    "wof:placetype":"venue"
},
  "geometry": {"coordinates":[-1.3652689457,54.755405426],"type":"Point"}
}