{
  "type": "Feature",
  "properties": {
    "addr:full":"74 Tycoch Road, Sketty Swansea Swansea SA2 9EQ",
    "addr:housenumber":"74",
    "addr:postcode":"sa2 9eq",
    "addr:street":"Tycoch Road",
    "iso:country":"GB",
    "sg:address":"74 Tycoch Road, Sketty",
    "sg:city":"Swansea",
    "sg:classifiers":[
        {
            "category":"Shopping",
            "subcategory":"Pets & Pet Supplies",
            "type":"Retail Goods"
        }
    ],
    "sg:phone":"+44 1792 206658",
    "sg:postcode":"SA2 9EQ",
    "sg:province":"Swansea",
    "wof:name":"J & S Products",
    "wof:placetype":"venue"
},
  "geometry": {"coordinates":[-3.9886670113,51.6221122742],"type":"Point"}
}