{
  "type": "Feature",
  "properties": {
    "addr:full":"P O Box 974 Lewes East Sussex BN7 1GA",
    "addr:housenumber":"974",
    "addr:postcode":"bn7 1ga",
    "addr:street":"P O Box",
    "iso:country":"GB",
    "sg:address":"P O Box 974",
    "sg:city":"Lewes",
    "sg:classifiers":[
        {
            "category":"Professional",
            "subcategory":"Management & Consulting",
            "type":"Services"
        }
    ],
    "sg:phone":"+44 1273 486346",
    "sg:postcode":"BN7 1GA",
    "sg:province":"East Sussex",
    "sg:tags":[
        "consultant",
        "transport"
    ],
    "wof:name":"The Martlet Consultancy Ltd.",
    "wof:placetype":"venue"
},
  "geometry": {"coordinates":[0.01062,50.873203],"type":"Point"}
}