{
  "type": "Feature",
  "properties": {
    "iso:country":"GB",
    "sg:address":"183 High Street",
    "sg:city":"Hounslow",
    "sg:classifiers":[
        {
            "category":"Shopping",
            "subcategory":"Clothing, Apparel, & Fashions",
            "type":"Retail Goods"
        }
    ],
    "sg:phone":"+44 20 8577 8525",
    "sg:postcode":"TW3 1BL",
    "sg:province":"Greater London",
    "sg:tags":[
        "shop"
    ],
    "wof:name":"Barnton Design Trading",
    "wof:placetype":"venue"
},
  "geometry": {"coordinates":[-0.360802,51.468998],"type":"Point"}
}