{
  "type": "Feature",
  "properties": {
    "iso:country":"GB",
    "sg:address":"Hill Farm",
    "sg:city":"Petersfield",
    "sg:classifiers":[
        {
            "category":"Farming",
            "subcategory":"Farm",
            "type":"Manufacturing & Wholesale Goods"
        }
    ],
    "sg:phone":"+44 1730 827366",
    "sg:postcode":"GU32 1BQ",
    "sg:province":"Hampshire",
    "sg:tags":[
        "mixed",
        "crop"
    ],
    "wof:name":"D W Reed",
    "wof:placetype":"venue"
},
  "geometry": {"coordinates":[-1.0157389641,51.0175590515],"type":"Point"}
}