{
  "type": "Feature",
  "properties": {
    "iso:country":"GB",
    "sg:address":"98 Whitton Close",
    "sg:city":"Doncaster",
    "sg:classifiers":[
        {
            "category":"Building & Trades",
            "subcategory":"Plumbing",
            "type":"Services"
        }
    ],
    "sg:phone":"+44 1302 531246",
    "sg:postcode":"DN4 7RD",
    "sg:province":"South Yorkshire",
    "sg:tags":[
        "heating"
    ],
    "wof:name":"Stuart Bates",
    "wof:placetype":"venue"
},
  "geometry": {"coordinates":[-1.092909,53.501217],"type":"Point"}
}