{
  "type": "Feature",
  "properties": {
    "addr:full":"31 Nursery Road, Knaphill Woking Surrey GU21 2NN",
    "addr:housenumber":"31",
    "addr:postcode":"gu21 2nn",
    "addr:street":"Nursery Road",
    "iso:country":"GB",
    "sg:address":"31 Nursery Road, Knaphill",
    "sg:city":"Woking",
    "sg:classifiers":[
        {
            "category":"Social Services",
            "subcategory":"Retirement Home",
            "type":"Services"
        }
    ],
    "sg:phone":"+44 1483 480764",
    "sg:postcode":"GU21 2NN",
    "sg:province":"Surrey",
    "sg:tags":[
        "residential",
        "care"
    ],
    "wof:name":"Woking Group Home",
    "wof:placetype":"venue"
},
  "geometry": {"coordinates":[-0.6118519902,51.318901062],"type":"Point"}
}