{
  "type": "Feature",
  "properties": {
    "addr:full":"11 Main Street, Carlton Nuneaton Leicestershire CV13 0BZ",
    "addr:housenumber":"11",
    "addr:postcode":"cv13 0bz",
    "addr:street":"Main Street",
    "iso:country":"GB",
    "sg:address":"11 Main Street, Carlton",
    "sg:city":"Nuneaton",
    "sg:classifiers":[
        {
            "category":"Banks & Credit Unions",
            "subcategory":"Financial Services",
            "type":"Services"
        }
    ],
    "sg:phone":"+44 1455 292650",
    "sg:postcode":"CV13 0BZ",
    "sg:province":"Leicestershire",
    "sg:tags":[
        "adviser"
    ],
    "wof:name":"Hawksworth Financial Services Ltd.",
    "wof:placetype":"venue"
},
  "geometry": {"coordinates":[-1.368512,52.647854],"type":"Point"}
}