{
  "type": "Feature",
  "properties": {
    "addr:full":"Unit 3 Lion Wks Old Mkt St Manchester Greater Manchester M9 8DU",
    "addr:housenumber":"unit 3",
    "addr:postcode":"m9 8du",
    "addr:street":"Lion Wks Old Mkt St",
    "iso:country":"GB",
    "sg:address":"Unit 3 Lion Wks Old Mkt St",
    "sg:city":"Manchester",
    "sg:classifiers":[
        {
            "category":"Professional",
            "subcategory":"Art Services",
            "type":"Services"
        }
    ],
    "sg:phone":"+44 161 795 6139",
    "sg:postcode":"M9 8DU",
    "sg:province":"Greater Manchester",
    "sg:tags":[
        "stone",
        "restoration",
        "cleaning"
    ],
    "wof:name":"Pennine Pointing Contractors",
    "wof:placetype":"venue"
},
  "geometry": {"coordinates":[-2.2268300056,53.5248985291],"type":"Point"}
}