{
  "type": "Feature",
  "properties": {
    "iso:country":"GB",
    "sg:address":"Technical Services Business Unit, Caldwellside Indust Est",
    "sg:city":"Lanark",
    "sg:classifiers":[
        {
            "category":"Government",
            "subcategory":"Office",
            "type":"Public Place"
        }
    ],
    "sg:phone":"+44 1555 661555",
    "sg:postcode":"ML11 7SR",
    "sg:province":"South Lanarkshire",
    "sg:tags":[
        "local"
    ],
    "wof:name":"South Lanarkshire Council",
    "wof:placetype":"venue"
},
  "geometry": {"coordinates":[-3.804829,55.695557],"type":"Point"}
}