{
  "type": "Feature",
  "properties": {
    "addr:full":"1st Floor, 146 Commercial Rd, Totton Southampton Hampshire SO40 3AA",
    "addr:housenumber":"146",
    "addr:postcode":"so40 3aa",
    "addr:street":"Commercial Rd",
    "iso:country":"GB",
    "sg:address":"1st Floor, 146 Commercial Rd, Totton",
    "sg:city":"Southampton",
    "sg:classifiers":[
        {
            "category":"Banks & Credit Unions",
            "subcategory":"Financial Services",
            "type":"Services"
        }
    ],
    "sg:postcode":"SO40 3AA",
    "sg:province":"Hampshire",
    "sg:tags":[
        "adviser"
    ],
    "wof:name":"Loveday-Lovell,Simon,",
    "wof:placetype":"venue"
},
  "geometry": {"coordinates":[-1.4812619686,50.9190101624],"type":"Point"}
}