{
  "type": "Feature",
  "properties": {
    "iso:country":"GB",
    "sg:address":"Green Lane",
    "sg:city":"Blackburn",
    "sg:classifiers":[
        {
            "category":"Community Center",
            "type":"Public Place"
        },
        {
            "category":"Government",
            "subcategory":"Office",
            "type":"Public Place"
        }
    ],
    "sg:phone":"+44 1254 201027",
    "sg:postcode":"BB2 4SR",
    "sg:province":"Lancashire",
    "sg:tags":[
        "local",
        "centre"
    ],
    "wof:name":"Green Lane Community Centre",
    "wof:placetype":"venue"
},
  "geometry": {"coordinates":[-2.515439,53.731106],"type":"Point"}
}