{
  "type": "Feature",
  "properties": {
    "iso:country":"GB",
    "sg:address":"P O Box 13482",
    "sg:city":"London",
    "sg:classifiers":[
        {
            "category":"Professional",
            "subcategory":"Management & Consulting",
            "type":"Services"
        },
        {
            "category":"Personal",
            "type":"Services"
        }
    ],
    "sg:postcode":"E17 4PS",
    "sg:province":"Greater London",
    "sg:tags":[
        "marketing",
        "agency",
        "friendship",
        "dating",
        "consultant"
    ],
    "wof:name":"Swans",
    "wof:placetype":"venue"
},
  "geometry": {"coordinates":[-0.0182,51.590881],"type":"Point"}
}