{
  "type": "Feature",
  "properties": {
    "iso:country":"GB",
    "sg:address":"Unit 6 Mansfield House, Upper Bond Street",
    "sg:city":"Hinckley",
    "sg:classifiers":[
        {
            "category":"Shopping",
            "subcategory":"Clothing, Apparel, & Fashions",
            "type":"Retail Goods"
        },
        {
            "category":"Manufacturing",
            "subcategory":"Apparel",
            "type":"Manufacturing & Wholesale Goods"
        }
    ],
    "sg:postcode":"LE10 1RJ",
    "sg:province":"Leicestershire",
    "sg:tags":[
        "mnfr",
        "lingerie",
        "hosiery"
    ],
    "wof:name":"Saxon Hosiery",
    "wof:placetype":"venue"
},
  "geometry": {"coordinates":[-1.373289,52.544762],"type":"Point"}
}