{
  "type": "Feature",
  "properties": {
    "addr:full":"1 Boston Road, Gorse Hill Industrial Estate, Beaumont Leys Leicester Leicestershire LE4 1BB",
    "addr:housenumber":"1",
    "addr:postcode":"leys;le4 1bb",
    "addr:street":"Boston Road;Estate",
    "iso:country":"GB",
    "sg:address":"1 Boston Road, Gorse Hill Industrial Estate, Beaumont Leys",
    "sg:city":"Leicester",
    "sg:classifiers":[
        {
            "category":"Professional",
            "subcategory":"Printing & Photocopies",
            "type":"Services"
        }
    ],
    "sg:phone":"+44 11622340505",
    "sg:postcode":"LE4 1BB",
    "sg:province":"Leicestershire",
    "sg:tags":[
        "plate",
        "lithographic",
        "maker"
    ],
    "wof:name":"Creative Products",
    "wof:placetype":"venue"
},
  "geometry": {"coordinates":[-1.1705629826,52.6636962891],"type":"Point"}
}