{
  "type": "Feature",
  "properties": {
    "iso:country":"GB",
    "sg:address":"Black Dyke Mills, Brighouse Road",
    "sg:city":"Bradford",
    "sg:classifiers":[
        {
            "category":"Manufacturing",
            "subcategory":"Textiles",
            "type":"Manufacturing & Wholesale Goods"
        }
    ],
    "sg:postcode":"BD13 1QA",
    "sg:province":"West Yorkshire",
    "sg:tags":[
        "made-up"
    ],
    "wof:name":"Sandra Halmanroyd",
    "wof:placetype":"venue"
},
  "geometry": {"coordinates":[-1.758306,53.795738],"type":"Point"}
}