{
  "type": "Feature",
  "properties": {
    "iso:country":"GB",
    "sg:address":"115-119 New Hall Lane",
    "sg:city":"Preston",
    "sg:classifiers":[
        {
            "category":"Home & Garden",
            "subcategory":"Furniture",
            "type":"Retail Goods"
        }
    ],
    "sg:phone":"+44 1772 796896",
    "sg:postcode":"PR1 5PB",
    "sg:province":"Lancashire",
    "wof:name":"V F M Furnishings",
    "wof:placetype":"venue"
},
  "geometry": {"coordinates":[-2.680159,53.762192],"type":"Point"}
}