{
  "type": "Feature",
  "properties": {
    "addr:full":"Valleyside Industrial Estate, Station Road Wymondham Norfolk NR18 0NN",
    "addr:postcode":"nr18 0nn",
    "addr:street":"Valleyside Industrial;Station Road",
    "iso:country":"GB",
    "sg:address":"Valleyside Industrial Estate, Station Road",
    "sg:city":"Wymondham",
    "sg:classifiers":[
        {
            "category":"Manufacturing",
            "subcategory":"Buildings",
            "type":"Manufacturing & Wholesale Goods"
        }
    ],
    "sg:phone":"+44 1953 606202",
    "sg:postcode":"NR18 0NN",
    "sg:province":"Norfolk",
    "sg:tags":[
        "mobile",
        "home"
    ],
    "wof:name":"Masterman Caravans",
    "wof:placetype":"venue"
},
  "geometry": {"coordinates":[1.116064,52.570229],"type":"Point"}
}