{
  "type": "Feature",
  "properties": {
    "addr:full":"2 Southwell Rd Benfleet Essex SS7 1JB",
    "addr:housenumber":"2",
    "addr:postcode":"ss7 1jb",
    "addr:street":"Southwell Rd",
    "iso:country":"GB",
    "sg:address":"2 Southwell Rd",
    "sg:city":"Benfleet",
    "sg:classifiers":[
        {
            "category":"Professional",
            "subcategory":"Computer Services",
            "type":"Services"
        }
    ],
    "sg:phone":"+44 1268 756499",
    "sg:postcode":"SS7 1JB",
    "sg:province":"Essex",
    "sg:tags":[
        "system",
        "software"
    ],
    "wof:name":"Systems & Office Support Ltd",
    "wof:placetype":"venue"
},
  "geometry": {"coordinates":[0.5716180205,51.5588340759],"type":"Point"}
}