{
  "type": "Feature",
  "properties": {
    "addr:full":"38 Commerce Street Insch Aberdeenshire AB52 6JB",
    "addr:housenumber":"38",
    "addr:postcode":"ab52 6jb",
    "addr:street":"Commerce Street",
    "iso:country":"GB",
    "sg:address":"38 Commerce Street",
    "sg:city":"Insch",
    "sg:classifiers":[
        {
            "category":"Professional",
            "subcategory":"Engineering",
            "type":"Services"
        }
    ],
    "sg:phone":"+44 1464 820337",
    "sg:postcode":"AB52 6JB",
    "sg:province":"Aberdeenshire",
    "sg:tags":[
        "agricultural",
        "engineer"
    ],
    "wof:name":"A L Simpson & Co",
    "wof:placetype":"venue"
},
  "geometry": {"coordinates":[-2.6141929626,57.3423805237],"type":"Point"}
}