{
  "type": "Feature",
  "properties": {
    "addr:full":"Hackworth Industrial Park Shildon Durham DL4 1LH",
    "addr:postcode":"dl4 1lh",
    "addr:street":"Hackworth Industrial Park",
    "iso:country":"GB",
    "sg:address":"Hackworth Industrial Park",
    "sg:city":"Shildon",
    "sg:classifiers":[
        {
            "category":"Home & Garden",
            "subcategory":"Kitchen Supply",
            "type":"Retail Goods"
        }
    ],
    "sg:phone":"+44 1388 773065",
    "sg:postcode":"DL4 1LH",
    "sg:province":"Durham",
    "sg:tags":[
        "measuring",
        "scale"
    ],
    "wof:name":"I S A Controls Ltd.",
    "wof:placetype":"venue"
},
  "geometry": {"coordinates":[-1.6517089605,54.6285705566],"type":"Point"}
}