{
  "type": "Feature",
  "properties": {
    "addr:full":"58 Clarendon Road Watford Hertfordshire WD1 1DE",
    "addr:housenumber":"58",
    "addr:postcode":"wd1 1de",
    "addr:street":"Clarendon Road",
    "iso:country":"GB",
    "sg:address":"58 Clarendon Road",
    "sg:city":"Watford",
    "sg:classifiers":[
        {
            "category":"Insurance",
            "subcategory":"Insurance Agent",
            "type":"Services"
        }
    ],
    "sg:postcode":"WD1 1DE",
    "sg:province":"Hertfordshire",
    "wof:name":"Eagle Star Insurance Co. Ltd.",
    "wof:placetype":"venue"
},
  "geometry": {"coordinates":[-0.396797,51.662457],"type":"Point"}
}