{
  "type": "Feature",
  "properties": {
    "addr:full":"118 Philadelphia Lane Norwich Norfolk NR3 3JJ",
    "addr:housenumber":"118",
    "addr:postcode":"nr3 3jj",
    "addr:street":"Philadelphia Lane",
    "iso:country":"GB",
    "sg:address":"118 Philadelphia Lane",
    "sg:city":"Norwich",
    "sg:classifiers":[
        {
            "category":"Bars & Pubs",
            "type":"Food & Drink"
        },
        {
            "category":"Community Center",
            "subcategory":"Social",
            "type":"Public Place"
        }
    ],
    "sg:phone":"+44 1603 415924",
    "sg:postcode":"NR3 3JJ",
    "sg:province":"Norfolk",
    "sg:tags":[
        "pubs",
        "house",
        "inn",
        "activity"
    ],
    "wof:name":"The Forge Freehouse",
    "wof:placetype":"venue"
},
  "geometry": {"coordinates":[1.28918,52.647743],"type":"Point"}
}