{
  "type": "Feature",
  "properties": {
    "addr:full":"Po Box 110 Bridgwater Somerset TA6 7NG",
    "addr:housenumber":"po",
    "addr:postcode":"ta6 7ng",
    "addr:street":"Box 110",
    "iso:country":"GB",
    "sg:address":"Po Box 110",
    "sg:city":"Bridgwater",
    "sg:classifiers":[
        {
            "category":"Shopping",
            "type":"Retail Goods"
        }
    ],
    "sg:postcode":"TA6 7NG",
    "sg:province":"Somerset",
    "sg:tags":[
        "product",
        "disposable"
    ],
    "wof:name":"Procare",
    "wof:placetype":"venue"
},
  "geometry": {"coordinates":[-3.024163,51.128391],"type":"Point"}
}