{
  "type": "Feature",
  "properties": {
    "addr:full":"Black Lion Court, High Street Congleton Cheshire CW12 1WL",
    "addr:postcode":"cw12 1wl",
    "addr:street":"High Street",
    "iso:country":"GB",
    "sg:address":"Black Lion Court, High Street",
    "sg:city":"Congleton",
    "sg:classifiers":[
        {
            "category":"Professional",
            "subcategory":"Engineering",
            "type":"Services"
        }
    ],
    "sg:phone":"+44 1260 299495",
    "sg:postcode":"CW12 1WL",
    "sg:province":"Cheshire",
    "sg:tags":[
        "consulting",
        "engineer"
    ],
    "wof:name":"D G Environmental Ltd.",
    "wof:placetype":"venue"
},
  "geometry": {"coordinates":[-2.2110390663,53.162853241],"type":"Point"}
}