{
  "type": "Feature",
  "properties": {
    "addr:full":"Cross Gates Llandrindod Wells Powys LD1 6RP",
    "addr:postcode":"ld1 6rp",
    "addr:street":"Llandrindod Wells",
    "iso:country":"GB",
    "sg:address":"Cross Gates",
    "sg:city":"Llandrindod Wells",
    "sg:classifiers":[
        {
            "category":"Retail",
            "subcategory":"Auto Repair",
            "type":"Services"
        }
    ],
    "sg:phone":"+44 1597 851332",
    "sg:postcode":"LD1 6RP",
    "sg:province":"Powys",
    "sg:tags":[
        "modification",
        "garage",
        "related"
    ],
    "wof:name":"B Stephens & Sons",
    "wof:placetype":"venue"
},
  "geometry": {"coordinates":[-3.3770289421,52.2457504272],"type":"Point"}
}