{
  "type": "Feature",
  "properties": {
    "addr:full":"576 Kingston Road, Raynes Park London Greater London SW20 8DR",
    "addr:housenumber":"576",
    "addr:postcode":"sw20 8dr",
    "addr:street":"Kingston Road",
    "iso:country":"GB",
    "sg:address":"576 Kingston Road, Raynes Park",
    "sg:city":"London",
    "sg:classifiers":[
        {
            "category":"Professional",
            "subcategory":"Computer Services",
            "type":"Services"
        }
    ],
    "sg:phone":"+44 20 8540 5655",
    "sg:postcode":"SW20 8DR",
    "sg:province":"Greater London",
    "sg:tags":[
        "system",
        "software"
    ],
    "wof:name":"Network Interlinks Ltd.",
    "wof:placetype":"venue"
},
  "geometry": {"coordinates":[-0.2247419953,51.4097824097],"type":"Point"}
}