{
  "type": "Feature",
  "properties": {
    "iso:country":"GB",
    "sg:address":"6 Holly Place",
    "sg:city":"Eastbourne",
    "sg:classifiers":[
        {
            "category":"Building & Trades",
            "subcategory":"Construction",
            "type":"Services"
        }
    ],
    "sg:postcode":"BN22 0UT",
    "sg:province":"East Sussex",
    "sg:tags":[
        "decorator",
        "painter"
    ],
    "wof:name":"Kenneth Moore",
    "wof:placetype":"venue"
},
  "geometry": {"coordinates":[0.2710979879,50.8050956726],"type":"Point"}
}