{
  "type": "Feature",
  "properties": {
    "iso:country":"GB",
    "sg:address":"7 Peacock Yard, Off Ilisse Street",
    "sg:city":"London",
    "sg:classifiers":[
        {
            "category":"Shopping",
            "subcategory":"Clothing, Apparel, & Fashions",
            "type":"Retail Goods"
        }
    ],
    "sg:phone":"+44 20 7252 4802",
    "sg:postcode":"SE17 3LH",
    "sg:province":"Greater London",
    "sg:tags":[
        "clothing"
    ],
    "wof:name":"Conscious Earthwear",
    "wof:placetype":"venue"
},
  "geometry": {"coordinates":[-0.1013600007,51.4893302917],"type":"Point"}
}