{
  "type": "Feature",
  "properties": {
    "addr:full":"39 Barfield Road, West Mersea Colchester Essex CO5 8QX",
    "addr:housenumber":"39",
    "addr:postcode":"co5 8qx",
    "addr:street":"Barfield Road West;Colchester",
    "iso:country":"GB",
    "sg:address":"39 Barfield Road, West Mersea",
    "sg:city":"Colchester",
    "sg:classifiers":[
        {
            "category":"Organizations",
            "subcategory":"Membership Organization",
            "type":"Services"
        }
    ],
    "sg:phone":"+44 1206 382765",
    "sg:postcode":"CO5 8QX",
    "sg:province":"Essex",
    "sg:tags":[
        "club"
    ],
    "wof:name":"Mersea Island Royal British Legion Club Ltd.",
    "wof:placetype":"venue"
},
  "geometry": {"coordinates":[0.9174960256,51.7783126831],"type":"Point"}
}