{
  "type": "Feature",
  "properties": {
    "iso:country":"GB",
    "sg:address":"10a Barley Road, Thelwall",
    "sg:city":"Warrington",
    "sg:classifiers":[
        {
            "category":"Personal",
            "subcategory":"Beauty Salon",
            "type":"Services"
        }
    ],
    "sg:phone":"+44 1925 261543",
    "sg:postcode":"WA4 2EZ",
    "sg:province":"Cheshire",
    "sg:tags":[
        "lady",
        "hairdresser"
    ],
    "wof:name":"Vienna Hair Fashions",
    "wof:placetype":"venue"
},
  "geometry": {"coordinates":[-2.5330209732,53.381187439],"type":"Point"}
}