{
  "type": "Feature",
  "properties": {
    "addr:full":"Manor Farm, Gate Helmsley York East Riding of Yorkshire YO41 1NB",
    "addr:postcode":"yo41 1nb",
    "addr:street":"Manor Farm Gate",
    "iso:country":"GB",
    "sg:address":"Manor Farm, Gate Helmsley",
    "sg:city":"York",
    "sg:classifiers":[
        {
            "category":"Travel",
            "subcategory":"Hotels & Motels",
            "type":"Entertainment"
        }
    ],
    "sg:phone":"+44 1759 371230",
    "sg:postcode":"YO41 1NB",
    "sg:province":"East Riding of Yorkshire",
    "sg:tags":[
        "house",
        "guest"
    ],
    "wof:name":"P H Wray",
    "wof:placetype":"venue"
},
  "geometry": {"coordinates":[-0.9444540143,53.9896087646],"type":"Point"}
}