{
  "type": "Feature",
  "properties": {
    "iso:country":"GB",
    "sg:address":"814 Melton Road, Thurmaston",
    "sg:city":"Leicester",
    "sg:classifiers":[
        {
            "category":"Personal",
            "type":"Services"
        }
    ],
    "sg:phone":"+44 116 269 5327",
    "sg:postcode":"LE4 8BE",
    "sg:province":"Leicestershire",
    "sg:tags":[
        "wedding"
    ],
    "wof:name":"Thurmaston Print Shop",
    "wof:placetype":"venue"
},
  "geometry": {"coordinates":[-1.097555,52.681129],"type":"Point"}
}