{
  "type": "Feature",
  "properties": {
    "iso:country":"GB",
    "sg:address":"75 St Johns Gro",
    "sg:city":"Harrogate",
    "sg:classifiers":[
        {
            "category":"Organizations",
            "subcategory":"Non-profit Organization",
            "type":"Services"
        }
    ],
    "sg:phone":"+44 1423 508083",
    "sg:postcode":"HG1 3AH",
    "sg:province":"North Yorkshire",
    "sg:tags":[
        "organisation",
        "voluntary",
        "charity"
    ],
    "wof:name":"Leukaemia Research Fund",
    "wof:placetype":"venue"
},
  "geometry": {"coordinates":[-1.543133,54.007538],"type":"Point"}
}