{
  "type": "Feature",
  "properties": {
    "iso:country":"GB",
    "sg:address":"76 Royal Parade",
    "sg:city":"Eastbourne",
    "sg:classifiers":[
        {
            "category":"Professional",
            "subcategory":"Printing & Photocopies",
            "type":"Services"
        }
    ],
    "sg:postcode":"BN22 7AE",
    "sg:province":"East Sussex",
    "sg:tags":[
        "plate",
        "lithographic",
        "maker"
    ],
    "wof:name":"Mjh Foil Block Printing",
    "wof:placetype":"venue"
},
  "geometry": {"coordinates":[0.299917,50.775036],"type":"Point"}
}