{
  "type": "Feature",
  "properties": {
    "addr:full":"Unit 1 Penhill Park, Beaumont Road Banbury Oxfordshire OX16 1RW",
    "addr:housenumber":"unit 1",
    "addr:postcode":"ox16 1rw",
    "addr:street":"Penhill Park Beaumont Road",
    "iso:country":"GB",
    "sg:address":"Unit 1 Penhill Park, Beaumont Road",
    "sg:city":"Banbury",
    "sg:classifiers":[
        {
            "category":"Shopping",
            "subcategory":"Beauty & Cosmetics",
            "type":"Retail Goods"
        }
    ],
    "sg:phone":"+44 1295 277720",
    "sg:postcode":"OX16 1RW",
    "sg:province":"Oxfordshire",
    "sg:tags":[
        "equipment",
        "supply",
        "hairdressing"
    ],
    "wof:name":"Salon Services (Hair & Beauty Supplies) Ltd.",
    "wof:placetype":"venue"
},
  "geometry": {"coordinates":[-1.3400280476,52.0611114502],"type":"Point"}
}