{
  "type": "Feature",
  "properties": {
    "addr:full":"Oakridge, Sutton St Nicholas Hereford Herefordshire HR1 3DF",
    "addr:postcode":"hr1 3df",
    "addr:street":"Sutton",
    "iso:country":"GB",
    "sg:address":"Oakridge, Sutton St Nicholas",
    "sg:city":"Hereford",
    "sg:classifiers":[
        {
            "category":"Manufacturing",
            "subcategory":"Signs",
            "type":"Manufacturing & Wholesale Goods"
        }
    ],
    "sg:phone":"+44 1568 797253",
    "sg:postcode":"HR1 3DF",
    "sg:province":"Herefordshire",
    "sg:tags":[
        "writer"
    ],
    "wof:name":"Signsystems",
    "wof:placetype":"venue"
},
  "geometry": {"coordinates":[-2.65957,52.13472],"type":"Point"}
}