{
  "type": "Feature",
  "properties": {
    "iso:country":"GB",
    "sg:address":"3 The Close",
    "sg:city":"Norwich",
    "sg:classifiers":[
        {
            "category":"Real Estate",
            "subcategory":"Surveying",
            "type":"Services"
        }
    ],
    "sg:phone":"+44 1603 629992",
    "sg:postcode":"NR1 4DL",
    "sg:province":"Norfolk",
    "sg:tags":[
        "surveyor",
        "valuer"
    ],
    "wof:name":"PERCY HOWES & CO",
    "wof:placetype":"venue"
},
  "geometry": {"coordinates":[1.430333972,52.6250457764],"type":"Point"}
}