{
  "type": "Feature",
  "properties": {
    "addr:full":"R/o Unit 5, Imperial Works, Fountayne Rd London Greater London N15 4QL",
    "addr:housenumber":"unit 5",
    "addr:postcode":"n15 4ql",
    "addr:street":"Imperial Works Fountayne Rd",
    "iso:country":"GB",
    "sg:address":"R/o Unit 5, Imperial Works, Fountayne Rd",
    "sg:city":"London",
    "sg:classifiers":[
        {
            "category":"Professional",
            "subcategory":"Business Services",
            "type":"Services"
        }
    ],
    "sg:postcode":"N15 4QL",
    "sg:province":"Greater London",
    "sg:tags":[
        "trade"
    ],
    "wof:name":"Igas Ltd",
    "wof:placetype":"venue"
},
  "geometry": {"coordinates":[-0.0630600005,51.5848503113],"type":"Point"}
}