{
  "type": "Feature",
  "properties": {
    "addr:full":"49 St. Clements St Oxford Oxfordshire OX4 1AG",
    "addr:housenumber":"49",
    "addr:postcode":"ox4 1ag",
    "addr:street":"St. Clements St",
    "iso:country":"GB",
    "sg:address":"49 St. Clements St",
    "sg:city":"Oxford",
    "sg:classifiers":[
        {
            "category":"Fast Food",
            "type":"Food & Drink"
        }
    ],
    "sg:postcode":"OX4 1AG",
    "sg:province":"Oxfordshire",
    "sg:tags":[
        "away",
        "take"
    ],
    "wof:name":"Verma,S & S,",
    "wof:placetype":"venue"
},
  "geometry": {"coordinates":[-1.241534,51.750454],"type":"Point"}
}