{
  "type": "Feature",
  "properties": {
    "addr:full":"105 Keymer Road Hassocks East Sussex BN6 8QL",
    "addr:housenumber":"105",
    "addr:postcode":"bn6 8ql",
    "addr:street":"Keymer Road",
    "iso:country":"GB",
    "sg:address":"105 Keymer Road",
    "sg:city":"Hassocks",
    "sg:classifiers":[
        {
            "category":"Autos & Motor Vehicles",
            "subcategory":"Automobile Sales",
            "type":"Retail Goods"
        }
    ],
    "sg:postcode":"BN6 8QL",
    "sg:province":"East Sussex",
    "sg:tags":[
        "car"
    ],
    "wof:name":"Keymer Car Sales",
    "wof:placetype":"venue"
},
  "geometry": {"coordinates":[-0.1318359971,50.9221801758],"type":"Point"}
}