{
  "type": "Feature",
  "properties": {
    "iso:country":"GB",
    "sg:address":"The Timbers Industrial Unit, Vale Rd",
    "sg:city":"Brighton",
    "sg:classifiers":[
        {
            "category":"Building & Trades",
            "subcategory":"Construction",
            "type":"Services"
        }
    ],
    "sg:phone":"+44 1273 430110",
    "sg:postcode":"BN41 1GG",
    "sg:province":"East Sussex",
    "sg:tags":[
        "flooring"
    ],
    "wof:name":"Regency Wooden Floors Of Brighton",
    "wof:placetype":"venue"
},
  "geometry": {"coordinates":[-0.2085800022,50.8348083496],"type":"Point"}
}