{
  "type": "Feature",
  "properties": {
    "iso:country":"GB",
    "sg:address":"Crawfield Lane, Bo'mains Industrial Estate",
    "sg:city":"Bo'ness",
    "sg:classifiers":[
        {
            "category":"Retail",
            "subcategory":"Auto Repair",
            "type":"Services"
        }
    ],
    "sg:phone":"+44 1506 671571",
    "sg:postcode":"EH51 9QG",
    "sg:province":"Falkirk",
    "sg:tags":[
        "bodybuilder",
        "repairer"
    ],
    "wof:name":"Fisher Estates (Scotland) Ltd.",
    "wof:placetype":"venue"
},
  "geometry": {"coordinates":[-3.59349,56.011669],"type":"Point"}
}