{
  "type": "Feature",
  "properties": {
    "addr:full":"45 Virginia Gardens, Off Twenty Acre Road Warrington Cheshire WA5 5WN",
    "addr:housenumber":"45",
    "addr:postcode":"wa5 5wn",
    "addr:street":"Virginia Gardens Off Twenty Acre Road",
    "iso:country":"GB",
    "sg:address":"45 Virginia Gardens, Off Twenty Acre Road",
    "sg:city":"Warrington",
    "sg:classifiers":[
        {
            "category":"Organizations",
            "subcategory":"Membership Organization",
            "type":"Services"
        }
    ],
    "sg:postcode":"WA5 5WN",
    "sg:province":"Cheshire",
    "sg:tags":[
        "club"
    ],
    "wof:name":"Ok Mum Ltd.",
    "wof:placetype":"venue"
},
  "geometry": {"coordinates":[-2.6486001015,53.4059906006],"type":"Point"}
}