{
  "type": "Feature",
  "properties": {
    "addr:full":"Harbour Road, Newlyn Penzance Cornwall TR18 5HA",
    "addr:postcode":"tr18 5ha",
    "addr:street":"Harbour Road",
    "iso:country":"GB",
    "sg:address":"Harbour Road, Newlyn",
    "sg:city":"Penzance",
    "sg:classifiers":[
        {
            "category":"Manufacturing",
            "subcategory":"Retail Goods",
            "type":"Manufacturing & Wholesale Goods"
        }
    ],
    "sg:phone":"+44 1736 363094",
    "sg:postcode":"TR18 5HA",
    "sg:province":"Cornwall",
    "sg:tags":[
        "chandler"
    ],
    "wof:name":"Cosalt International Ltd.",
    "wof:placetype":"venue"
},
  "geometry": {"coordinates":[-5.5524082184,50.1017608643],"type":"Point"}
}