{
  "type": "Feature",
  "properties": {
    "addr:full":"Beccles Road, Bradwell Great Yarmouth Norfolk NR31 8DH",
    "addr:postcode":"nr31 8dh",
    "addr:street":"Beccles Road;Yarmouth",
    "iso:country":"GB",
    "sg:address":"Beccles Road, Bradwell",
    "sg:city":"Great Yarmouth",
    "sg:classifiers":[
        {
            "category":"Bars & Pubs",
            "type":"Food & Drink"
        },
        {
            "category":"Community Center",
            "subcategory":"Social",
            "type":"Public Place"
        }
    ],
    "sg:phone":"+44 1493 651772",
    "sg:postcode":"NR31 8DH",
    "sg:province":"Norfolk",
    "sg:tags":[
        "pubs",
        "house",
        "inn",
        "activity"
    ],
    "wof:name":"The Arches",
    "wof:placetype":"venue"
},
  "geometry": {"coordinates":[1.697534,52.572739],"type":"Point"}
}