{
  "type": "Feature",
  "properties": {
    "addr:full":"1 Linden Terrace Whitley Bay Northumberland NE26 2AA",
    "addr:housenumber":"1",
    "addr:postcode":"ne26 2aa",
    "addr:street":"Linden Terrace",
    "iso:country":"GB",
    "sg:address":"1 Linden Terrace",
    "sg:city":"Whitley Bay",
    "sg:classifiers":[
        {
            "category":"Travel",
            "subcategory":"Hotels & Motels",
            "type":"Entertainment"
        }
    ],
    "sg:phone":"+44 191 251 7557",
    "sg:postcode":"NE26 2AA",
    "sg:province":"Northumberland",
    "sg:tags":[
        "house",
        "guest"
    ],
    "wof:name":"Esplanade Lodge",
    "wof:placetype":"venue"
},
  "geometry": {"coordinates":[-1.4424690008,55.0426216125],"type":"Point"}
}