{
  "type": "Feature",
  "properties": {
    "addr:full":"73 Lache Park Avenue Chester Cheshire CH4 8HT",
    "addr:housenumber":"73",
    "addr:postcode":"ch4 8ht",
    "addr:street":"Lache Park Avenue",
    "iso:country":"GB",
    "sg:address":"73 Lache Park Avenue",
    "sg:city":"Chester",
    "sg:classifiers":[
        {
            "category":"Building & Trades",
            "subcategory":"Plumbing",
            "type":"Services"
        }
    ],
    "sg:phone":"+44 1244 676968",
    "sg:postcode":"CH4 8HT",
    "sg:province":"Cheshire",
    "sg:tags":[
        "plumber",
        "heating"
    ],
    "wof:name":"A E Williams",
    "wof:placetype":"venue"
},
  "geometry": {"coordinates":[-2.909021,53.174427],"type":"Point"}
}