{
  "type": "Feature",
  "properties": {
    "iso:country":"GB",
    "sg:address":"15 Montrose Walk",
    "sg:city":"Weybridge",
    "sg:classifiers":[
        {
            "category":"Education",
            "subcategory":"Music School",
            "type":"Public Place"
        }
    ],
    "sg:phone":"+44 1932 888885",
    "sg:postcode":"KT13 8JN",
    "sg:province":"Surrey",
    "wof:name":"Re:Actors Ltd.",
    "wof:placetype":"venue"
},
  "geometry": {"coordinates":[-0.455549,51.376373],"type":"Point"}
}