{
  "type": "Feature",
  "properties": {
    "iso:country":"GB",
    "sg:address":"Grangewood Avenue",
    "sg:city":"Grays",
    "sg:classifiers":[
        {
            "category":"Education",
            "subcategory":"School",
            "type":"Public Place"
        }
    ],
    "sg:phone":"+44 1375 372513",
    "sg:postcode":"RM16 2GJ",
    "sg:province":"Essex",
    "sg:tags":[
        "local",
        "authority"
    ],
    "wof:name":"Woodside County Primary School",
    "wof:placetype":"venue"
},
  "geometry": {"coordinates":[0.3514800072,51.4884757996],"type":"Point"}
}