{
  "type": "Feature",
  "properties": {
    "iso:country":"GB",
    "sg:address":"Mimet Ho, 5a Praed St",
    "sg:city":"London",
    "sg:classifiers":[
        {
            "category":"Professional",
            "subcategory":"Business Services",
            "type":"Services"
        }
    ],
    "sg:postcode":"W2 1NJ",
    "sg:province":"Greater London",
    "sg:tags":[
        "import",
        "export",
        "agent"
    ],
    "wof:name":"A-Z Corp Services & Supply International",
    "wof:placetype":"venue"
},
  "geometry": {"coordinates":[-0.16949,51.51889],"type":"Point"}
}