{
  "type": "Feature",
  "properties": {
    "iso:country":"GB",
    "sg:address":"Unit 11, Gaza Trading Estate, Scabharbour Road",
    "sg:city":"Tonbridge",
    "sg:classifiers":[
        {
            "category":"Home & Garden",
            "subcategory":"Home Furnishings",
            "type":"Retail Goods"
        }
    ],
    "sg:phone":"+44 1732 460047",
    "sg:postcode":"TN11 8PL",
    "sg:province":"Kent",
    "sg:tags":[
        "furnishers",
        "planner",
        "kitchen"
    ],
    "wof:name":"R I Sheridan",
    "wof:placetype":"venue"
},
  "geometry": {"coordinates":[0.19601,51.219761],"type":"Point"}
}