{
  "type": "Feature",
  "properties": {
    "iso:country":"GB",
    "sg:address":"Rosemount, Church Rd, Trench",
    "sg:city":"Telford",
    "sg:classifiers":[
        {
            "category":"Military Area",
            "subcategory":"Air Force Base",
            "type":"Public Place"
        }
    ],
    "sg:postcode":"TF2 7HJ",
    "sg:province":"Shropshire",
    "sg:tags":[
        "taxi",
        "hire",
        "private"
    ],
    "wof:name":"Black,Ashley,",
    "wof:placetype":"venue"
},
  "geometry": {"coordinates":[-2.44852,52.711151],"type":"Point"}
}