{
  "type": "Feature",
  "properties": {
    "addr:full":"Wilson House, 105 Chesterfield Road Dronfield Derbyshire S18 2XE",
    "addr:housenumber":"105",
    "addr:postcode":"s18 2xe",
    "addr:street":"Chesterfield Road",
    "iso:country":"GB",
    "sg:address":"Wilson House, 105 Chesterfield Road",
    "sg:city":"Dronfield",
    "sg:classifiers":[
        {
            "category":"Real Estate",
            "subcategory":"Architect",
            "type":"Services"
        }
    ],
    "sg:phone":"+44 1246 290813",
    "sg:postcode":"S18 2XE",
    "sg:province":"Derbyshire",
    "wof:name":"John Rochford & Partners",
    "wof:placetype":"venue"
},
  "geometry": {"coordinates":[-1.465659,53.300011],"type":"Point"}
}