{
  "type": "Feature",
  "properties": {
    "addr:full":"Cuckoo Lodge Green Lane, Raymonds Hill Axminster Devon EX13 5TD",
    "addr:postcode":"ex13 5td",
    "addr:street":"Green Lane Raymonds Hill",
    "iso:country":"GB",
    "sg:address":"Cuckoo Lodge Green Lane, Raymonds Hill",
    "sg:city":"Axminster",
    "sg:classifiers":[
        {
            "category":"Building & Trades",
            "subcategory":"Construction",
            "type":"Services"
        }
    ],
    "sg:postcode":"EX13 5TD",
    "sg:province":"Devon",
    "sg:tags":[
        "builder"
    ],
    "wof:name":"G J Wellman Ltd.",
    "wof:placetype":"venue"
},
  "geometry": {"coordinates":[-3.0005619526,50.7812767029],"type":"Point"}
}