{
  "type": "Feature",
  "properties": {
    "addr:full":"75 Dartmouth Park Hill Kentish Town Greater London NW5 1JD",
    "addr:housenumber":"75",
    "addr:postcode":"nw5 1jd",
    "addr:street":"Dartmouth Park",
    "iso:country":"GB",
    "sg:address":"75 Dartmouth Park Hill",
    "sg:city":"Kentish Town",
    "sg:classifiers":[
        {
            "category":"Real Estate",
            "subcategory":"Architect",
            "type":"Services"
        }
    ],
    "sg:phone":"+44 20 7482 5953",
    "sg:postcode":"NW5 1JD",
    "sg:province":"Greater London",
    "wof:name":"Boaz Yariv",
    "wof:placetype":"venue"
},
  "geometry": {"coordinates":[-0.141182,51.561523],"type":"Point"}
}