{
  "type": "Feature",
  "properties": {
    "iso:country":"GB",
    "sg:address":"Vron Park Avenue",
    "sg:city":"Llanfairpwllgwyngyll",
    "sg:classifiers":[
        {
            "category":"Building & Trades",
            "subcategory":"Cleaning & Sanitation",
            "type":"Services"
        }
    ],
    "sg:phone":"+44 1978 716382",
    "sg:postcode":"LL61 5JW",
    "sg:province":"Isle of Anglesey",
    "sg:tags":[
        "commercial"
    ],
    "wof:name":"Ocs Wales Ltd.",
    "wof:placetype":"venue"
},
  "geometry": {"coordinates":[-4.2097492218,53.2214431763],"type":"Point"}
}