{
  "type": "Feature",
  "properties": {
    "addr:full":"Dickens Hypermarket, Pk La, Shiremoor Newcastle-upon-tyne Northumberland NE27 0ST",
    "addr:postcode":"ne27 0st",
    "addr:street":"Pk La Shiremoor",
    "iso:country":"GB",
    "sg:address":"Dickens Hypermarket, Pk La, Shiremoor",
    "sg:city":"Newcastle-upon-tyne",
    "sg:classifiers":[
        {
            "category":"Home & Garden",
            "subcategory":"Home Furnishings",
            "type":"Retail Goods"
        }
    ],
    "sg:postcode":"NE27 0ST",
    "sg:province":"Northumberland",
    "sg:tags":[
        "awning",
        "canopy",
        "blinds"
    ],
    "wof:name":"Blakey,Fred,",
    "wof:placetype":"venue"
},
  "geometry": {"coordinates":[-1.5043050051,55.0360641479],"type":"Point"}
}