{
  "type": "Feature",
  "properties": {
    "addr:full":"Catterick Golf Club, Leyburn Road Catterick Garrison North Yorkshire DL9 3QE",
    "addr:postcode":"dl9 3qe",
    "addr:street":"Leyburn Road",
    "iso:country":"GB",
    "sg:address":"Catterick Golf Club, Leyburn Road",
    "sg:city":"Catterick Garrison",
    "sg:classifiers":[
        {
            "category":"Sports & Exercise",
            "subcategory":"Golf",
            "type":"Entertainment"
        }
    ],
    "sg:phone":"+44 1748 833671",
    "sg:postcode":"DL9 3QE",
    "sg:province":"North Yorkshire",
    "sg:tags":[
        "club",
        "course"
    ],
    "wof:name":"Andy Marshal Golf Professional",
    "wof:placetype":"venue"
},
  "geometry": {"coordinates":[-1.7223119736,54.3766021729],"type":"Point"}
}