{
  "type": "Feature",
  "properties": {
    "iso:country":"GB",
    "sg:address":"12 Norwich Street",
    "sg:city":"London",
    "sg:classifiers":[
        {
            "category":"Banks & Credit Unions",
            "subcategory":"Financial Services",
            "type":"Services"
        }
    ],
    "sg:phone":"+44 20 7832 9802",
    "sg:postcode":"EC4A 1BP",
    "sg:province":"Greater London",
    "sg:tags":[
        "consultant"
    ],
    "wof:name":"Dow Jones Telerate",
    "wof:placetype":"venue"
},
  "geometry": {"coordinates":[-0.1101970002,51.5165939331],"type":"Point"}
}