{
  "type": "Feature",
  "properties": {
    "addr:full":"Unit 7, Pinefield Business Centre, Pinefield Industrial Estate Elgin Moray IV30 6AN",
    "addr:housenumber":"unit 7;business centre",
    "addr:postcode":"iv30 6an",
    "addr:street":"Industrial Estate",
    "iso:country":"GB",
    "sg:address":"Unit 7, Pinefield Business Centre, Pinefield Industrial Estate",
    "sg:city":"Elgin",
    "sg:classifiers":[
        {
            "category":"Retail",
            "subcategory":"Repair Shop",
            "type":"Services"
        }
    ],
    "sg:phone":"+44 1343 540003",
    "sg:postcode":"IV30 6AN",
    "sg:province":"Moray",
    "sg:tags":[
        "upholsterer"
    ],
    "wof:name":"Ronald Dunbar",
    "wof:placetype":"venue"
},
  "geometry": {"coordinates":[-3.304643,57.636486],"type":"Point"}
}