{
  "type": "Feature",
  "properties": {
    "addr:full":"114 Tooting High Street London Greater London SW17 0RR",
    "addr:housenumber":"114",
    "addr:postcode":"sw17 0rr",
    "addr:street":"Tooting High Street",
    "iso:country":"GB",
    "sg:address":"114 Tooting High Street",
    "sg:city":"London",
    "sg:classifiers":[
        {
            "category":"Shopping",
            "subcategory":"News",
            "type":"Retail Goods"
        }
    ],
    "sg:phone":"+44 20 8682 1677",
    "sg:postcode":"SW17 0RR",
    "sg:province":"Greater London",
    "sg:tags":[
        "newsagent"
    ],
    "wof:name":"Hannahs",
    "wof:placetype":"venue"
},
  "geometry": {"coordinates":[-0.1699880064,51.4262161255],"type":"Point"}
}