{
  "type": "Feature",
  "properties": {
    "addr:full":"67 Summer Lane Barnsley South Yorkshire S70 2PD",
    "addr:housenumber":"67",
    "addr:postcode":"s70 2pd",
    "addr:street":"Summer Lane;Yorkshire",
    "iso:country":"GB",
    "sg:address":"67 Summer Lane",
    "sg:city":"Barnsley",
    "sg:classifiers":[
        {
            "category":"Fast Food",
            "type":"Food & Drink"
        },
        {
            "category":"Food & Beverages",
            "subcategory":"Meat & Fish",
            "type":"Retail Goods"
        }
    ],
    "sg:phone":"+44 1226 205584",
    "sg:postcode":"S70 2PD",
    "sg:province":"South Yorkshire",
    "sg:tags":[
        "shop",
        "chip"
    ],
    "wof:name":"Darn's Fish & Chips",
    "wof:placetype":"venue"
},
  "geometry": {"coordinates":[-1.4905079603,53.5550231934],"type":"Point"}
}