{
  "type": "Feature",
  "properties": {
    "addr:full":"88 Sandy Lane Skelmersdale Lancashire WN8 8LQ",
    "addr:housenumber":"88",
    "addr:postcode":"wn8 8lq",
    "addr:street":"Sandy Lane",
    "iso:country":"GB",
    "sg:address":"88 Sandy Lane",
    "sg:city":"Skelmersdale",
    "sg:classifiers":[
        {
            "category":"Personal",
            "type":"Services"
        }
    ],
    "sg:postcode":"WN8 8LQ",
    "sg:province":"Lancashire",
    "sg:tags":[
        "delivery"
    ],
    "wof:name":"Foster Light Haulage",
    "wof:placetype":"venue"
},
  "geometry": {"coordinates":[-2.8060629368,53.5490608215],"type":"Point"}
}