{
  "type": "Feature",
  "properties": {
    "iso:country":"GB",
    "sg:address":"364 Whitworth Rd",
    "sg:city":"Rochdale",
    "sg:classifiers":[
        {
            "category":"Home & Garden",
            "subcategory":"Hardware",
            "type":"Retail Goods"
        }
    ],
    "sg:postcode":"OL12 0SF",
    "sg:province":"Lancashire",
    "sg:tags":[
        "retailer",
        "diy"
    ],
    "wof:name":"Nook Home Store",
    "wof:placetype":"venue"
},
  "geometry": {"coordinates":[-2.1608080864,53.6316070557],"type":"Point"}
}