{
  "type": "Feature",
  "properties": {
    "addr:full":"Auch Farm Bridge Of Orchy Argyll and Bute PA36 4AF",
    "addr:postcode":"pa36 4af",
    "addr:street":"Bridge;Orchy",
    "iso:country":"GB",
    "sg:address":"Auch Farm",
    "sg:city":"Bridge Of Orchy",
    "sg:classifiers":[
        {
            "category":"Farming",
            "subcategory":"Livestock Farm",
            "type":"Manufacturing & Wholesale Goods"
        }
    ],
    "sg:phone":"+44 1691 774159",
    "sg:postcode":"PA36 4AF",
    "sg:province":"Argyll and Bute",
    "sg:tags":[
        "others"
    ],
    "wof:name":"Auch Estates (Bridge of Orchy) Ltd.",
    "wof:placetype":"venue"
},
  "geometry": {"coordinates":[-4.7684340477,56.5182762146],"type":"Point"}
}