{
  "type": "Feature",
  "properties": {
    "addr:full":"4 East Walk, Yate Shopping Ctr Bristol Gloucestershire BS37 4AX",
    "addr:housenumber":"4",
    "addr:postcode":"bs37 4ax",
    "addr:street":"East Walk;Shopping Ctr",
    "iso:country":"GB",
    "sg:address":"4 East Walk, Yate Shopping Ctr",
    "sg:city":"Bristol",
    "sg:classifiers":[
        {
            "category":"Shopping",
            "subcategory":"Shoes",
            "type":"Retail Goods"
        }
    ],
    "sg:phone":"+44 1454 313638",
    "sg:postcode":"BS37 4AX",
    "sg:province":"Gloucestershire",
    "sg:tags":[
        "shop"
    ],
    "wof:name":"Clarks Shoes",
    "wof:placetype":"venue"
},
  "geometry": {"coordinates":[-2.4096150398,51.5391998291],"type":"Point"}
}