{
  "type": "Feature",
  "properties": {
    "addr:full":"Newton Wood Lane, Newton Alfreton Derbyshire DE55 5SG",
    "addr:postcode":"de55 5sg",
    "addr:street":"Newton Wood Lane",
    "iso:country":"GB",
    "sg:address":"Newton Wood Lane, Newton",
    "sg:city":"Alfreton",
    "sg:classifiers":[
        {
            "category":"Building & Trades",
            "subcategory":"Landscaping Services",
            "type":"Services"
        }
    ],
    "sg:phone":"+44 1773 591700",
    "sg:postcode":"DE55 5SG",
    "sg:province":"Derbyshire",
    "sg:tags":[
        "landscape",
        "contractor"
    ],
    "wof:name":"Key Services",
    "wof:placetype":"venue"
},
  "geometry": {"coordinates":[-1.331902,53.133797],"type":"Point"}
}