{
  "type": "Feature",
  "properties": {
    "iso:country":"GB",
    "sg:address":"16 Tudor Road, Wheathampstead",
    "sg:city":"St Albans",
    "sg:classifiers":[
        {
            "category":"Building & Trades",
            "subcategory":"Construction",
            "type":"Services"
        }
    ],
    "sg:phone":"+44 1582 832579",
    "sg:postcode":"AL4 8NW",
    "sg:province":"Hertfordshire",
    "sg:tags":[
        "builder"
    ],
    "wof:name":"Anthony Richard Clark",
    "wof:placetype":"venue"
},
  "geometry": {"coordinates":[-0.2856970131,51.8090591431],"type":"Point"}
}