{
  "type": "Feature",
  "properties": {
    "addr:full":"Po Box 3 Pontefract West Yorkshire WF7 6EQ",
    "addr:housenumber":"po;3",
    "addr:postcode":"wf7 6eq",
    "addr:street":"Box;Pontefract West",
    "iso:country":"GB",
    "sg:address":"Po Box 3",
    "sg:city":"Pontefract",
    "sg:classifiers":[
        {
            "category":"Shopping",
            "subcategory":"Stationery & Office Supplies",
            "type":"Retail Goods"
        }
    ],
    "sg:postcode":"WF7 6EQ",
    "sg:province":"West Yorkshire",
    "wof:name":"P & B Office Supplies",
    "wof:placetype":"venue"
},
  "geometry": {"coordinates":[-1.3764189482,53.6817512512],"type":"Point"}
}