{
  "type": "Feature",
  "properties": {
    "iso:country":"GB",
    "sg:address":"248 Shawfield Road",
    "sg:city":"Aldershot",
    "sg:classifiers":[
        {
            "category":"Fast Food",
            "type":"Food & Drink"
        }
    ],
    "sg:phone":"+44 1252 342859",
    "sg:postcode":"GU12 5DJ",
    "sg:province":"Hampshire",
    "sg:tags":[
        "away",
        "take"
    ],
    "wof:name":"The Chandni Takeaway",
    "wof:placetype":"venue"
},
  "geometry": {"coordinates":[-0.720609,51.256721],"type":"Point"}
}