{
  "type": "Feature",
  "properties": {
    "iso:country":"GB",
    "sg:address":"17 Palace Avenue",
    "sg:city":"Rhyl",
    "sg:classifiers":[
        {
            "category":"Social Services",
            "subcategory":"Retirement Home",
            "type":"Services"
        }
    ],
    "sg:phone":"+44 1745 354209",
    "sg:postcode":"LL18 1HS",
    "sg:province":"Conwy",
    "sg:tags":[
        "residential",
        "care"
    ],
    "wof:name":"Norcot",
    "wof:placetype":"venue"
},
  "geometry": {"coordinates":[-3.4997029305,53.316570282],"type":"Point"}
}