{
  "type": "Feature",
  "properties": {
    "iso:country":"GB",
    "sg:address":"Bridge Field, Banbury Road",
    "sg:city":"Warwick",
    "sg:classifiers":[
        {
            "category":"Education",
            "subcategory":"School",
            "type":"Public Place"
        }
    ],
    "sg:phone":"+44 1926 491545",
    "sg:postcode":"CV34 6PL",
    "sg:province":"Warwickshire",
    "sg:tags":[
        "independent",
        "preparatory"
    ],
    "wof:name":"Warwick Preparatory School",
    "wof:placetype":"venue"
},
  "geometry": {"coordinates":[-1.581327,52.278687],"type":"Point"}
}