{
  "type": "Feature",
  "properties": {
    "addr:full":"13 Hill Street Redcar North Yorkshire TS10 1BU",
    "addr:housenumber":"13",
    "addr:postcode":"ts10 1bu",
    "addr:street":"Hill Street",
    "iso:country":"GB",
    "sg:address":"13 Hill Street",
    "sg:city":"Redcar",
    "sg:classifiers":[
        {
            "category":"Retail",
            "subcategory":"Repair Shop",
            "type":"Services"
        }
    ],
    "sg:postcode":"TS10 1BU",
    "sg:province":"North Yorkshire",
    "sg:tags":[
        "radio",
        "television",
        "video"
    ],
    "wof:name":"Alan's T V & Video Repairs",
    "wof:placetype":"venue"
},
  "geometry": {"coordinates":[-1.077309,54.61853],"type":"Point"}
}