{
  "type": "Feature",
  "properties": {
    "iso:country":"GB",
    "sg:address":"Thames House, Molly Millars Lane",
    "sg:city":"Wokingham",
    "sg:classifiers":[
        {
            "category":"Autos & Motor Vehicles",
            "subcategory":"Automobile Sales",
            "type":"Retail Goods"
        }
    ],
    "sg:phone":"+44 118 978 0380",
    "sg:postcode":"RG41 2QR",
    "sg:province":"Berkshire",
    "sg:tags":[
        "car"
    ],
    "sg:website":"http://www.womo.co.uk",
    "wof:name":"Wokingham Motors Ltd.",
    "wof:placetype":"venue"
},
  "geometry": {"coordinates":[-0.847958982,51.4071044922],"type":"Point"}
}