{
  "type": "Feature",
  "properties": {
    "iso:country":"GB",
    "sg:address":"8 Arnside Close, Clayton-le-moors",
    "sg:city":"Accrington",
    "sg:classifiers":[
        {
            "category":"Shopping",
            "subcategory":"Party Supplies",
            "type":"Retail Goods"
        }
    ],
    "sg:postcode":"BB5 5GG",
    "sg:province":"Lancashire",
    "sg:tags":[
        "inflatables",
        "bouncy",
        "castle"
    ],
    "wof:name":"Abbey Leisure",
    "wof:placetype":"venue"
},
  "geometry": {"coordinates":[-2.392768,53.773121],"type":"Point"}
}