{
  "type": "Feature",
  "properties": {
    "addr:full":"Silures, Shelsley Drive, Colwall Malvern Gloucestershire WR13 6PS",
    "addr:postcode":"wr13 6ps",
    "addr:street":"Shelsley Drive",
    "iso:country":"GB",
    "sg:address":"Silures, Shelsley Drive, Colwall",
    "sg:city":"Malvern",
    "sg:classifiers":[
        {
            "category":"Professional",
            "type":"Services"
        }
    ],
    "sg:postcode":"WR13 6PS",
    "sg:province":"Gloucestershire",
    "sg:tags":[
        "caterer"
    ],
    "wof:name":"E & M Catering",
    "wof:placetype":"venue"
},
  "geometry": {"coordinates":[-2.3813939095,52.0789260864],"type":"Point"}
}