{
  "type": "Feature",
  "properties": {
    "addr:full":"Tresham Crescent, Yateley Camberley Hampshire GU46 6FR",
    "addr:postcode":"gu46 6fr",
    "addr:street":"Tresham Crescent",
    "iso:country":"GB",
    "sg:address":"Tresham Crescent, Yateley",
    "sg:city":"Camberley",
    "sg:classifiers":[
        {
            "category":"Shopping",
            "subcategory":"Pharmacy",
            "type":"Retail Goods"
        }
    ],
    "sg:phone":"+44 1252 860508",
    "sg:postcode":"GU46 6FR",
    "sg:province":"Hampshire",
    "sg:tags":[
        "pharmacist",
        "chemist"
    ],
    "wof:name":"Moss Chemists",
    "wof:placetype":"venue"
},
  "geometry": {"coordinates":[-0.8467239738,51.3382987976],"type":"Point"}
}