{
  "type": "Feature",
  "properties": {
    "iso:country":"GB",
    "sg:address":"20 Rosebury Avenue",
    "sg:city":"Bristol",
    "sg:classifiers":[
        {
            "category":"Building & Trades",
            "subcategory":"Construction",
            "type":"Services"
        }
    ],
    "sg:phone":"+44 117 955 8774",
    "sg:postcode":"BS2 9TN",
    "sg:province":"City of Bristol",
    "sg:tags":[
        "builder"
    ],
    "wof:name":"Leypale Ltd.",
    "wof:placetype":"venue"
},
  "geometry": {"coordinates":[-2.5745909214,51.4672622681],"type":"Point"}
}