{
  "type": "Feature",
  "properties": {
    "addr:full":"16 High Street, Tettenhall Wolverhampton Shropshire WV6 8QT",
    "addr:housenumber":"16",
    "addr:postcode":"wv6 8qt",
    "addr:street":"High Street",
    "iso:country":"GB",
    "sg:address":"16 High Street, Tettenhall",
    "sg:city":"Wolverhampton",
    "sg:classifiers":[
        {
            "category":"Government",
            "subcategory":"Police Station",
            "type":"Public Place"
        },
        {
            "category":"Banks & Credit Unions",
            "subcategory":"Investment Brokerage",
            "type":"Services"
        }
    ],
    "sg:postcode":"WV6 8QT",
    "sg:province":"Shropshire",
    "sg:tags":[
        "support"
    ],
    "wof:name":"Midland Investment Agency",
    "wof:placetype":"venue"
},
  "geometry": {"coordinates":[-2.1682999134,52.5980033875],"type":"Point"}
}