{
  "type": "Feature",
  "properties": {
    "addr:full":"43 Charles Road Solihull West Midlands B91 1TT",
    "addr:housenumber":"43",
    "addr:postcode":"b91 1tt",
    "addr:street":"Charles Road",
    "iso:country":"GB",
    "sg:address":"43 Charles Road",
    "sg:city":"Solihull",
    "sg:classifiers":[
        {
            "category":"Professional",
            "subcategory":"Management & Consulting",
            "type":"Services"
        },
        {
            "category":"Personal",
            "type":"Services"
        }
    ],
    "sg:phone":"+44 121 705 1937",
    "sg:postcode":"B91 1TT",
    "sg:province":"West Midlands",
    "sg:tags":[
        "consultant",
        "beauty",
        "specialist"
    ],
    "wof:name":"Colour For Life",
    "wof:placetype":"venue"
},
  "geometry": {"coordinates":[-1.8094710112,52.4063949585],"type":"Point"}
}