{
  "type": "Feature",
  "properties": {
    "addr:full":"Low Grn, Staveley Kendal Cumbria LA8 8LA",
    "addr:postcode":"la8 8la",
    "addr:street":"Low Grn",
    "iso:country":"GB",
    "sg:address":"Low Grn, Staveley",
    "sg:city":"Kendal",
    "sg:classifiers":[
        {
            "category":"Building & Trades",
            "subcategory":"Construction",
            "type":"Services"
        }
    ],
    "sg:phone":"+44 1539 822092",
    "sg:postcode":"LA8 8LA",
    "sg:province":"Cumbria",
    "sg:tags":[
        "glazier"
    ],
    "wof:name":"David Carrie",
    "wof:placetype":"venue"
},
  "geometry": {"coordinates":[-2.8014440536,54.298915863],"type":"Point"}
}