{
  "type": "Feature",
  "properties": {
    "addr:full":"509 Hackney Road London Greater London E2 9ED",
    "addr:housenumber":"509",
    "addr:postcode":"e2 9ed",
    "addr:street":"Hackney Road",
    "iso:country":"GB",
    "sg:address":"509 Hackney Road",
    "sg:city":"London",
    "sg:classifiers":[
        {
            "category":"Fast Food",
            "type":"Food & Drink"
        }
    ],
    "sg:phone":"+44 20 7631 1667",
    "sg:postcode":"E2 9ED",
    "sg:province":"Greater London",
    "sg:tags":[
        "away",
        "take"
    ],
    "wof:name":"Perfect Fried Chicken",
    "wof:placetype":"venue"
},
  "geometry": {"coordinates":[-0.0581640005,51.5325584412],"type":"Point"}
}