{
  "type": "Feature",
  "properties": {
    "iso:country":"GB",
    "sg:address":"53 Falmouth Av",
    "sg:city":"Stafford",
    "sg:classifiers":[
        {
            "category":"Building & Trades",
            "subcategory":"Cleaning & Sanitation",
            "type":"Services"
        }
    ],
    "sg:phone":"+44 1785 665395",
    "sg:postcode":"ST17 0JQ",
    "sg:province":"Staffordshire",
    "sg:tags":[
        "commercial"
    ],
    "wof:name":"Central Cleaning Contractors",
    "wof:placetype":"venue"
},
  "geometry": {"coordinates":[-2.071307,52.793892],"type":"Point"}
}