{
  "type": "Feature",
  "properties": {
    "addr:full":"36 Bedford Rd Liverpool Merseyside L4 5PU",
    "addr:housenumber":"36",
    "addr:postcode":"l4 5pu",
    "addr:street":"Bedford Rd",
    "iso:country":"GB",
    "sg:address":"36 Bedford Rd",
    "sg:city":"Liverpool",
    "sg:classifiers":[
        {
            "category":"Retail",
            "subcategory":"Auto Repair",
            "type":"Services"
        }
    ],
    "sg:phone":"+44 151 525 3098",
    "sg:postcode":"L4 5PU",
    "sg:province":"Merseyside",
    "sg:tags":[
        "modification",
        "garage"
    ],
    "wof:name":"Sam Leach",
    "wof:placetype":"venue"
},
  "geometry": {"coordinates":[-2.970328,53.4459],"type":"Point"}
}