{
  "type": "Feature",
  "properties": {
    "iso:country":"GB",
    "sg:address":"46 Victoria Rd",
    "sg:city":"Hartlepool",
    "sg:classifiers":[
        {
            "category":"Health Services",
            "subcategory":"Doctor",
            "type":"Services"
        }
    ],
    "sg:phone":"+44 1429 297290",
    "sg:postcode":"TS26 8DD",
    "sg:province":"Durham",
    "sg:tags":[
        "practitioners"
    ],
    "wof:name":"Gladstone House Surgery",
    "wof:placetype":"venue"
},
  "geometry": {"coordinates":[-1.219588,54.685703],"type":"Point"}
}