{
  "type": "Feature",
  "properties": {
    "iso:country":"GB",
    "sg:address":"115 Century Buildings, Summers Rd, Brunswick Business Park",
    "sg:city":"Liverpool",
    "sg:classifiers":[
        {
            "category":"Shopping",
            "subcategory":"Catalog Store",
            "type":"Retail Goods"
        }
    ],
    "sg:phone":"+44 151 707 9988",
    "sg:postcode":"L3 4BL",
    "sg:province":"Merseyside",
    "sg:tags":[
        "mail",
        "order"
    ],
    "wof:name":"Osmosis (Flora) Ltd",
    "wof:placetype":"venue"
},
  "geometry": {"coordinates":[-2.9796700478,53.3837203979],"type":"Point"}
}