{
  "type": "Feature",
  "properties": {
    "iso:country":"GB",
    "sg:address":"Lower Pertwood Farm, Hindon",
    "sg:city":"Salisbury",
    "sg:classifiers":[
        {
            "category":"Food & Beverages",
            "subcategory":"Specialty",
            "type":"Retail Goods"
        },
        {
            "category":"Farming",
            "subcategory":"Farm",
            "type":"Manufacturing & Wholesale Goods"
        }
    ],
    "sg:phone":"+44 1747 820499",
    "sg:postcode":"SP3 6TA",
    "sg:province":"Wiltshire",
    "sg:tags":[
        "mixed",
        "organic",
        "crop"
    ],
    "wof:name":"Pertwood Partners",
    "wof:placetype":"venue"
},
  "geometry": {"coordinates":[-2.1287,51.095421],"type":"Point"}
}