{
  "type": "Feature",
  "properties": {
    "iso:country":"GB",
    "sg:address":"2 Mays Grn, Harpsden",
    "sg:city":"Henley-on-thames",
    "sg:classifiers":[
        {
            "category":"Education",
            "subcategory":"Music School",
            "type":"Public Place"
        }
    ],
    "sg:postcode":"RG9 4AL",
    "sg:province":"Berkshire",
    "sg:tags":[
        "conservatory"
    ],
    "wof:name":"David Mott",
    "wof:placetype":"venue"
},
  "geometry": {"coordinates":[-0.9033110142,51.5211143494],"type":"Point"}
}