{
  "type": "Feature",
  "properties": {
    "addr:full":"3 Flixton Road, Urmston Manchester Cheshire M41 5AW",
    "addr:housenumber":"3",
    "addr:postcode":"m41 5aw",
    "addr:street":"Flixton Road",
    "iso:country":"GB",
    "sg:address":"3 Flixton Road, Urmston",
    "sg:city":"Manchester",
    "sg:classifiers":[
        {
            "category":"Real Estate",
            "subcategory":"Real Estate Agent",
            "type":"Services"
        }
    ],
    "sg:phone":"+44 161 747 9095",
    "sg:postcode":"M41 5AW",
    "sg:province":"Cheshire",
    "wof:name":"Paul Birtles & Co. Ltd.",
    "wof:placetype":"venue"
},
  "geometry": {"coordinates":[-2.353592,53.448429],"type":"Point"}
}