{
  "type": "Feature",
  "properties": {
    "iso:country":"GB",
    "sg:address":"Hoylake Rd",
    "sg:city":"Wirral",
    "sg:classifiers":[
        {
            "category":"Autos & Motor Vehicles",
            "subcategory":"Automobile Sales",
            "type":"Retail Goods"
        }
    ],
    "sg:postcode":"CH46 6DG",
    "sg:province":"Merseyside",
    "sg:tags":[
        "car"
    ],
    "wof:name":"Grange Car Centre",
    "wof:placetype":"venue"
},
  "geometry": {"coordinates":[-3.1283490658,53.3960952759],"type":"Point"}
}