{
  "type": "Feature",
  "properties": {
    "addr:full":"Ashburnham Road, Pembrey Burry Port Carmarthenshire SA16 0TP",
    "addr:postcode":"sa16 0tp",
    "addr:street":"Ashburnham Road",
    "iso:country":"GB",
    "sg:address":"Ashburnham Road, Pembrey",
    "sg:city":"Burry Port",
    "sg:classifiers":[
        {
            "category":"Education",
            "subcategory":"School",
            "type":"Public Place"
        }
    ],
    "sg:phone":"+44 1554 832207",
    "sg:postcode":"SA16 0TP",
    "sg:province":"Carmarthenshire",
    "sg:tags":[
        "local",
        "authority"
    ],
    "wof:name":"Pembrey Village Primary School",
    "wof:placetype":"venue"
},
  "geometry": {"coordinates":[-4.251719,51.6908],"type":"Point"}
}