{
  "type": "Feature",
  "properties": {
    "iso:country":"GB",
    "sg:address":"157 Clapton Common",
    "sg:city":"London",
    "sg:classifiers":[
        {
            "category":"Shopping",
            "subcategory":"Pawn Shop",
            "type":"Retail Goods"
        }
    ],
    "sg:phone":"+44 20 8809 1488",
    "sg:postcode":"E5 9AE",
    "sg:province":"Greater London",
    "sg:tags":[
        "pawnbroker"
    ],
    "wof:name":"Harvey & Thompson Ltd.",
    "wof:placetype":"venue"
},
  "geometry": {"coordinates":[-0.071618,51.572968],"type":"Point"}
}