{
  "type": "Feature",
  "properties": {
    "addr:full":"11 Galloway Drive Teignmouth Devon TQ14 9UX",
    "addr:housenumber":"11",
    "addr:postcode":"tq14 9ux",
    "addr:street":"Galloway Drive",
    "iso:country":"GB",
    "sg:address":"11 Galloway Drive",
    "sg:city":"Teignmouth",
    "sg:classifiers":[
        {
            "category":"Banks & Credit Unions",
            "subcategory":"Bank",
            "type":"Services"
        }
    ],
    "sg:phone":"+44 1626 776597",
    "sg:postcode":"TQ14 9UX",
    "sg:province":"Devon",
    "sg:tags":[
        "stocktaking",
        "inventory"
    ],
    "wof:name":"Stocktake UK",
    "wof:placetype":"venue"
},
  "geometry": {"coordinates":[-3.5128400326,50.5575752258],"type":"Point"}
}