{
  "type": "Feature",
  "properties": {
    "iso:country":"GB",
    "sg:address":"116 Micklegate",
    "sg:city":"York",
    "sg:classifiers":[
        {
            "category":"Education",
            "subcategory":"Special Training",
            "type":"Public Place"
        }
    ],
    "sg:phone":"+44 1904 624246",
    "sg:postcode":"YO1 6JX",
    "sg:province":"North Yorkshire",
    "sg:tags":[
        "school",
        "language"
    ],
    "wof:name":"York Associates",
    "wof:placetype":"venue"
},
  "geometry": {"coordinates":[-1.0902249813,53.9565429688],"type":"Point"}
}