{
  "type": "Feature",
  "properties": {
    "addr:full":"Springwood Mill, Pudsey Road Todmorden Lancashire OL14 8NJ",
    "addr:postcode":"ol14 8nj",
    "addr:street":"Pudsey Road",
    "iso:country":"GB",
    "sg:address":"Springwood Mill, Pudsey Road",
    "sg:city":"Todmorden",
    "sg:classifiers":[
        {
            "category":"Wholesale",
            "subcategory":"Scrap",
            "type":"Manufacturing & Wholesale Goods"
        }
    ],
    "sg:phone":"+44 1706 819969",
    "sg:postcode":"OL14 8NJ",
    "sg:province":"Lancashire",
    "sg:tags":[
        "waste",
        "metal"
    ],
    "wof:name":"Springwood Trading",
    "wof:placetype":"venue"
},
  "geometry": {"coordinates":[-2.097308,53.71431],"type":"Point"}
}