{
  "type": "Feature",
  "properties": {
    "addr:full":"116 Highfield Road South Shields Tyne and Wear NE34 6JL",
    "addr:housenumber":"116",
    "addr:postcode":"ne34 6jl",
    "addr:street":"Highfield Road",
    "iso:country":"GB",
    "sg:address":"116 Highfield Road",
    "sg:city":"South Shields",
    "sg:classifiers":[
        {
            "category":"Bars & Pubs",
            "type":"Food & Drink"
        }
    ],
    "sg:phone":"+44 191 455 4901",
    "sg:postcode":"NE34 6JL",
    "sg:province":"Tyne and Wear",
    "sg:tags":[
        "pubs",
        "inn"
    ],
    "wof:name":"The Fountain",
    "wof:placetype":"venue"
},
  "geometry": {"coordinates":[-1.409114,54.985191],"type":"Point"}
}