{
  "type": "Feature",
  "properties": {
    "addr:full":"51 Westwood Hill London Greater London SE26 6NS",
    "addr:housenumber":"51",
    "addr:postcode":"se26 6ns",
    "addr:street":"Westwood Hill",
    "iso:country":"GB",
    "sg:address":"51 Westwood Hill",
    "sg:city":"London",
    "sg:classifiers":[
        {
            "category":"Professional",
            "subcategory":"Secretarial Services",
            "type":"Services"
        },
        {
            "category":"Wholesale",
            "subcategory":"Books, Periodicals, & Newspapers",
            "type":"Manufacturing & Wholesale Goods"
        }
    ],
    "sg:phone":"+44 20 8676 9631",
    "sg:postcode":"SE26 6NS",
    "sg:province":"Greater London",
    "sg:tags":[
        "publishing"
    ],
    "wof:name":"Wordservice",
    "wof:placetype":"venue"
},
  "geometry": {"coordinates":[-0.067949,51.426346],"type":"Point"}
}