{
  "type": "Feature",
  "properties": {
    "addr:full":"11 Vallance Road London Greater London N22 7UD",
    "addr:housenumber":"11",
    "addr:postcode":"n22 7ud",
    "addr:street":"Vallance Road",
    "iso:country":"GB",
    "sg:address":"11 Vallance Road",
    "sg:city":"London",
    "sg:classifiers":[
        {
            "category":"Professional",
            "subcategory":"Accounting & Tax Preparation",
            "type":"Services"
        }
    ],
    "sg:phone":"+44 20 8888 1688",
    "sg:postcode":"N22 7UD",
    "sg:province":"Greater London",
    "sg:tags":[
        "accountant",
        "activity"
    ],
    "wof:name":"J J Dolan & Co",
    "wof:placetype":"venue"
},
  "geometry": {"coordinates":[-0.132756,51.597256],"type":"Point"}
}