{
  "type": "Feature",
  "properties": {
    "addr:full":"31-32 Victoria Arcade Great Yarmouth Norfolk NR30 2NU",
    "addr:housenumber":"31-32",
    "addr:postcode":"nr30 2nu",
    "addr:street":"Victoria Arcade;Yarmouth",
    "iso:country":"GB",
    "sg:address":"31-32 Victoria Arcade",
    "sg:city":"Great Yarmouth",
    "sg:classifiers":[
        {
            "category":"Home & Garden",
            "subcategory":"Home Furnishings",
            "type":"Retail Goods"
        }
    ],
    "sg:phone":"+44 1493 330407",
    "sg:postcode":"NR30 2NU",
    "sg:province":"Norfolk",
    "sg:tags":[
        "blind",
        "curtain",
        "fitting"
    ],
    "wof:name":"Arcade Interiors",
    "wof:placetype":"venue"
},
  "geometry": {"coordinates":[1.7260550261,52.606426239],"type":"Point"}
}