{
  "type": "Feature",
  "properties": {
    "iso:country":"GB",
    "sg:address":"8 West Street",
    "sg:city":"Warwick",
    "sg:classifiers":[
        {
            "category":"Fast Food",
            "type":"Food & Drink"
        }
    ],
    "sg:phone":"+44 1926 496802",
    "sg:postcode":"CV34 6AN",
    "sg:province":"Warwickshire",
    "sg:tags":[
        "away",
        "meal",
        "outlet",
        "take"
    ],
    "wof:name":"New Happy Garden",
    "wof:placetype":"venue"
},
  "geometry": {"coordinates":[-1.591459,52.27935],"type":"Point"}
}