{
  "type": "Feature",
  "properties": {
    "addr:full":"Churchill Road, Naunton Park Cheltenham Gloucestershire GL53 7EH",
    "addr:postcode":"gl53 7eh",
    "addr:street":"Churchill Road",
    "iso:country":"GB",
    "sg:address":"Churchill Road, Naunton Park",
    "sg:city":"Cheltenham",
    "sg:classifiers":[
        {
            "category":"Retail",
            "subcategory":"Auto Repair",
            "type":"Services"
        }
    ],
    "sg:phone":"+44 1242 523637",
    "sg:postcode":"GL53 7EH",
    "sg:province":"Gloucestershire",
    "sg:tags":[
        "body",
        "car"
    ],
    "wof:name":"D Reed & Son",
    "wof:placetype":"venue"
},
  "geometry": {"coordinates":[-2.0738298893,51.884727478],"type":"Point"}
}