{
  "type": "Feature",
  "properties": {
    "iso:country":"GB",
    "sg:address":"30-32 Portland Drive",
    "sg:city":"Redhill",
    "sg:classifiers":[
        {
            "category":"Food & Beverages",
            "subcategory":"Groceries & Convenience Stores",
            "type":"Retail Goods"
        }
    ],
    "sg:phone":"+44 1737 643343",
    "sg:postcode":"RH1 3HY",
    "sg:province":"Surrey",
    "wof:name":"J S Food & Wine",
    "wof:placetype":"venue"
},
  "geometry": {"coordinates":[-0.1447239965,51.260433197],"type":"Point"}
}