{
  "type": "Feature",
  "properties": {
    "iso:country":"GB",
    "sg:address":"417 Stourbridge Road, Catshill",
    "sg:city":"Bromsgrove",
    "sg:classifiers":[
        {
            "category":"Bars & Pubs",
            "type":"Food & Drink"
        },
        {
            "category":"Community Center",
            "subcategory":"Social",
            "type":"Public Place"
        }
    ],
    "sg:phone":"+44 1527 877355",
    "sg:postcode":"B61 9LG",
    "sg:province":"Worcestershire",
    "sg:tags":[
        "pubs",
        "house",
        "inn",
        "activity"
    ],
    "wof:name":"The Plough & Harrow",
    "wof:placetype":"venue"
},
  "geometry": {"coordinates":[-2.064715,52.363747],"type":"Point"}
}