{
  "type": "Feature",
  "properties": {
    "iso:country":"GB",
    "sg:address":"1 Grantley St",
    "sg:city":"Glasgow",
    "sg:classifiers":[
        {
            "category":"Health Services",
            "subcategory":"Doctor",
            "type":"Services"
        }
    ],
    "sg:phone":"+44 141 632 4698",
    "sg:postcode":"G41 3PT",
    "sg:province":"Glasgow City",
    "sg:tags":[
        "practitioners"
    ],
    "wof:name":"Fitchett, A A",
    "wof:placetype":"venue"
},
  "geometry": {"coordinates":[-4.2883558273,55.8260803223],"type":"Point"}
}