{
  "type": "Feature",
  "properties": {
    "addr:full":"Edward House, Edwards Street Blackburn Lancashire BB6 7GB",
    "addr:postcode":"bb6 7gb",
    "addr:street":"Edwards Street",
    "iso:country":"GB",
    "sg:address":"Edward House, Edwards Street",
    "sg:city":"Blackburn",
    "sg:classifiers":[
        {
            "category":"Education",
            "subcategory":"Library",
            "type":"Public Place"
        }
    ],
    "sg:phone":"+44 1254 877258",
    "sg:postcode":"BB6 7GB",
    "sg:province":"Lancashire",
    "sg:tags":[
        "book"
    ],
    "wof:name":"Schools Library Service",
    "wof:placetype":"venue"
},
  "geometry": {"coordinates":[-2.409194,53.785645],"type":"Point"}
}