{
  "type": "Feature",
  "properties": {
    "iso:country":"GB",
    "sg:address":"Millhouse, Millfields",
    "sg:city":"Nantwich",
    "sg:classifiers":[
        {
            "category":"Social Services",
            "subcategory":"Retirement Home",
            "type":"Services"
        }
    ],
    "sg:phone":"+44 1270 625061",
    "sg:postcode":"CW5 5HS",
    "sg:province":"Cheshire",
    "sg:tags":[
        "residential",
        "care"
    ],
    "wof:name":"C L S Care Services",
    "wof:placetype":"venue"
},
  "geometry": {"coordinates":[-2.5165019035,53.0658912659],"type":"Point"}
}