{
  "type": "Feature",
  "properties": {
    "addr:full":"Oak Tree Farm, Inglewhite Road, Goosnargh Preston Lancashire PR3 2EB",
    "addr:postcode":"pr3 2eb",
    "addr:street":"Inglewhite Road",
    "iso:country":"GB",
    "sg:address":"Oak Tree Farm, Inglewhite Road, Goosnargh",
    "sg:city":"Preston",
    "sg:classifiers":[
        {
            "category":"Farming",
            "subcategory":"Livestock Farm",
            "type":"Manufacturing & Wholesale Goods"
        }
    ],
    "sg:phone":"+44 1772 783691",
    "sg:postcode":"PR3 2EB",
    "sg:province":"Lancashire",
    "sg:tags":[
        "others"
    ],
    "wof:name":"R J Cornall & Partners",
    "wof:placetype":"venue"
},
  "geometry": {"coordinates":[-2.671284,53.822075],"type":"Point"}
}