{
  "type": "Feature",
  "properties": {
    "iso:country":"GB",
    "sg:address":"Banbury Railway Station",
    "sg:city":"Banbury",
    "sg:classifiers":[
        {
            "category":"Taxi",
            "type":"Transportation"
        }
    ],
    "sg:phone":"+44 1295 253838",
    "sg:postcode":"OX16 5AB",
    "sg:province":"Oxfordshire",
    "sg:tags":[
        "mini",
        "cab"
    ],
    "wof:name":"Union Taxis",
    "wof:placetype":"venue"
},
  "geometry": {"coordinates":[-1.32825,52.06068],"type":"Point"}
}