{
  "type": "Feature",
  "properties": {
    "addr:full":"6 Westfield Close, Kinsbury London Greater London NW9 0LX",
    "addr:housenumber":"6",
    "addr:postcode":"nw9 0lx",
    "addr:street":"Westfield Close",
    "iso:country":"GB",
    "sg:address":"6 Westfield Close, Kinsbury",
    "sg:city":"London",
    "sg:classifiers":[
        {
            "category":"Building & Trades",
            "subcategory":"Construction",
            "type":"Services"
        }
    ],
    "sg:postcode":"NW9 0LX",
    "sg:province":"Greater London",
    "sg:tags":[
        "builder"
    ],
    "wof:name":"Patrick Reid",
    "wof:placetype":"venue"
},
  "geometry": {"coordinates":[-0.2641409934,51.5920295715],"type":"Point"}
}