{
  "type": "Feature",
  "properties": {
    "addr:full":"588 Bolton Road, Pendlebury, Swinton Manchester Greater Manchester M27 4ET",
    "addr:housenumber":"588",
    "addr:postcode":"m27 4et",
    "addr:street":"Bolton Road",
    "iso:country":"GB",
    "sg:address":"588 Bolton Road, Pendlebury, Swinton",
    "sg:city":"Manchester",
    "sg:classifiers":[
        {
            "category":"Personal",
            "subcategory":"Nail Salon",
            "type":"Services"
        }
    ],
    "sg:phone":"+44 161 793 9091",
    "sg:postcode":"M27 4ET",
    "sg:province":"Greater Manchester",
    "sg:tags":[
        "solarium",
        "tanning"
    ],
    "wof:name":"Swinton Tanning Centre",
    "wof:placetype":"venue"
},
  "geometry": {"coordinates":[-2.3301000595,53.5171852112],"type":"Point"}
}