{
  "type": "Feature",
  "properties": {
    "addr:full":"75 Osmaston Road Derby Derbyshire DE1 2JH",
    "addr:housenumber":"75",
    "addr:postcode":"de1 2jh",
    "addr:street":"Osmaston Road",
    "iso:country":"GB",
    "sg:address":"75 Osmaston Road",
    "sg:city":"Derby",
    "sg:classifiers":[
        {
            "category":"Personal",
            "type":"Services"
        },
        {
            "category":"Professional",
            "subcategory":"Lawyer & Legal Services",
            "type":"Services"
        }
    ],
    "sg:phone":"+44 1332 366863",
    "sg:postcode":"DE1 2JH",
    "sg:province":"Derbyshire",
    "sg:tags":[
        "advice",
        "counselling"
    ],
    "wof:name":"Derby Counselling & Therapy Centre",
    "wof:placetype":"venue"
},
  "geometry": {"coordinates":[-1.474279,52.91745],"type":"Point"}
}