{
  "type": "Feature",
  "properties": {
    "iso:country":"GB",
    "sg:address":"2 Shelduck Close",
    "sg:city":"Aylesbury",
    "sg:classifiers":[
        {
            "category":"Building & Trades",
            "subcategory":"Plumbing",
            "type":"Services"
        }
    ],
    "sg:phone":"+44 1296 434445",
    "sg:postcode":"HP19 0WS",
    "sg:province":"Buckinghamshire",
    "sg:tags":[
        "plumber",
        "heating"
    ],
    "wof:name":"STEVE PITCHER LTD",
    "wof:placetype":"venue"
},
  "geometry": {"coordinates":[-0.806385,51.82962],"type":"Point"}
}