{
  "type": "Feature",
  "properties": {
    "iso:country":"GB",
    "sg:address":"9 Red Bank Road",
    "sg:city":"Blackpool",
    "sg:classifiers":[
        {
            "category":"Personal",
            "subcategory":"Beauty Salon",
            "type":"Services"
        }
    ],
    "sg:phone":"+44 1253 500137",
    "sg:postcode":"FY2 9HN",
    "sg:province":"Lancashire",
    "sg:tags":[
        "unisex",
        "hairdresser"
    ],
    "wof:name":"Hair by Peter Nicholas",
    "wof:placetype":"venue"
},
  "geometry": {"coordinates":[-3.0524981022,53.8498001099],"type":"Point"}
}