{
  "type": "Feature",
  "properties": {
    "addr:full":"Sherndon Manor Edenbridge East Sussex TN8 5PS",
    "addr:postcode":"tn8 5ps",
    "iso:country":"GB",
    "sg:address":"Sherndon Manor",
    "sg:city":"Edenbridge",
    "sg:classifiers":[
        {
            "category":"Professional",
            "subcategory":"Business Services",
            "type":"Services"
        }
    ],
    "sg:postcode":"TN8 5PS",
    "sg:province":"East Sussex",
    "sg:tags":[
        "holding"
    ],
    "wof:name":"Hugh Smallwood Holdings Ltd.",
    "wof:placetype":"venue"
},
  "geometry": {"coordinates":[0.0647469983,51.1973876953],"type":"Point"}
}