{
  "type": "Feature",
  "properties": {
    "addr:full":"8 Cob Meadow, Hatherleigh Okehampton Devon EX20 3JZ",
    "addr:housenumber":"8",
    "addr:postcode":"ex20 3jz",
    "addr:street":"Cob Meadow Hatherleigh",
    "iso:country":"GB",
    "sg:address":"8 Cob Meadow, Hatherleigh",
    "sg:city":"Okehampton",
    "sg:classifiers":[
        {
            "category":"Professional",
            "subcategory":"Engineering",
            "type":"Services"
        }
    ],
    "sg:phone":"+44 1837 810611",
    "sg:postcode":"EX20 3JZ",
    "sg:province":"Devon",
    "sg:tags":[
        "contractor",
        "electrical",
        "engineer"
    ],
    "wof:name":"A & E Bater Electrical",
    "wof:placetype":"venue"
},
  "geometry": {"coordinates":[-4.070534,50.819462],"type":"Point"}
}