{
  "type": "Feature",
  "properties": {
    "iso:country":"GB",
    "sg:address":"23 Church St, Wavertree",
    "sg:city":"Liverpool",
    "sg:classifiers":[
        {
            "category":"Real Estate",
            "subcategory":"Real Estate Agent",
            "type":"Services"
        }
    ],
    "sg:postcode":"L15 9EA",
    "sg:province":"Merseyside",
    "wof:name":"London & Cheshire Properties Ltd",
    "wof:placetype":"venue"
},
  "geometry": {"coordinates":[-2.914724,53.390224],"type":"Point"}
}