{
  "type": "Feature",
  "properties": {
    "iso:country":"GB",
    "sg:address":"82 Victoria Road",
    "sg:city":"Darlington",
    "sg:classifiers":[
        {
            "category":"Building & Trades",
            "subcategory":"Construction",
            "type":"Services"
        }
    ],
    "sg:phone":"+44 1325 464013",
    "sg:postcode":"DL1 5JG",
    "sg:province":"Durham",
    "sg:tags":[
        "monumental",
        "mason"
    ],
    "wof:name":"Nelsons Sculptors",
    "wof:placetype":"venue"
},
  "geometry": {"coordinates":[-1.553409,54.521759],"type":"Point"}
}