{
  "type": "Feature",
  "properties": {
    "iso:country":"GB",
    "sg:address":"90 High Street, Henley In Arden",
    "sg:city":"Solihull",
    "sg:classifiers":[
        {
            "category":"Professional",
            "subcategory":"Accounting & Tax Preparation",
            "type":"Services"
        }
    ],
    "sg:phone":"+44 1564 795755",
    "sg:postcode":"B95 5BY",
    "sg:province":"Warwickshire",
    "sg:tags":[
        "accountant",
        "activity"
    ],
    "wof:name":"Cullingworth & Co",
    "wof:placetype":"venue"
},
  "geometry": {"coordinates":[-1.780051,52.29287],"type":"Point"}
}