{
  "type": "Feature",
  "properties": {
    "addr:full":"17 Norwich Rd Leicester Leicestershire LE4 0LR",
    "addr:housenumber":"17",
    "addr:postcode":"le4 0lr",
    "addr:street":"Norwich Rd",
    "iso:country":"GB",
    "sg:address":"17 Norwich Rd",
    "sg:city":"Leicester",
    "sg:classifiers":[
        {
            "category":"Fast Food",
            "type":"Food & Drink"
        }
    ],
    "sg:phone":"+44 116 236 5556",
    "sg:postcode":"LE4 0LR",
    "sg:province":"Leicestershire",
    "sg:tags":[
        "away",
        "take"
    ],
    "wof:name":"Cob Shop The",
    "wof:placetype":"venue"
},
  "geometry": {"coordinates":[-1.142541,52.657829],"type":"Point"}
}