{
  "type": "Feature",
  "properties": {
    "iso:country":"GB",
    "sg:address":"34 Pollok Township Centre",
    "sg:city":"Glasgow",
    "sg:classifiers":[
        {
            "category":"Health Services",
            "subcategory":"Optometrist",
            "type":"Services"
        }
    ],
    "sg:phone":"+44 141 876 0876",
    "sg:postcode":"G53 6QR",
    "sg:province":"East Renfrewshire",
    "sg:tags":[
        "optician"
    ],
    "wof:name":"Visions Opticians",
    "wof:placetype":"venue"
},
  "geometry": {"coordinates":[-4.3421001434,55.8229484558],"type":"Point"}
}