{
  "type": "Feature",
  "properties": {
    "addr:full":"Frogwell Rd Callington Cornwall PL17 7JX",
    "addr:postcode":"pl17 7jx",
    "addr:street":"Frogwell Rd",
    "iso:country":"GB",
    "sg:address":"Frogwell Rd",
    "sg:city":"Callington",
    "sg:classifiers":[
        {
            "category":"Wholesale",
            "subcategory":"Machinery & Supplies",
            "type":"Manufacturing & Wholesale Goods"
        }
    ],
    "sg:phone":"+44 1579 383588",
    "sg:postcode":"PL17 7JX",
    "sg:province":"Cornwall",
    "wof:name":"C Penfold",
    "wof:placetype":"venue"
},
  "geometry": {"coordinates":[-4.3224477768,50.5019798279],"type":"Point"}
}