{
  "type": "Feature",
  "properties": {
    "addr:full":"77 St Pauls Avenue London Greater London NW2 5TG",
    "addr:housenumber":"77",
    "addr:postcode":"nw2 5tg",
    "addr:street":"St Pauls Avenue",
    "iso:country":"GB",
    "sg:address":"77 St Pauls Avenue",
    "sg:city":"London",
    "sg:classifiers":[
        {
            "category":"Autos & Motor Vehicles",
            "subcategory":"Fuel & Gas Station",
            "type":"Retail Goods"
        }
    ],
    "sg:phone":"+44 20 8451 2368",
    "sg:postcode":"NW2 5TG",
    "sg:province":"Greater London",
    "sg:tags":[
        "hr",
        "petrol"
    ],
    "wof:name":"Elf Oil U K Ltd.",
    "wof:placetype":"venue"
},
  "geometry": {"coordinates":[-0.227306,51.549603],"type":"Point"}
}