{
  "type": "Feature",
  "properties": {
    "addr:full":"Adjacent To Sutton Arms Hotel, Sherdley Road St Helens Cheshire WA9 5DF",
    "addr:postcode":"wa9 5df",
    "addr:street":"Sherdley Road",
    "iso:country":"GB",
    "sg:address":"Adjacent To Sutton Arms Hotel, Sherdley Road",
    "sg:city":"St Helens",
    "sg:classifiers":[
        {
            "category":"Professional",
            "subcategory":"Business Services",
            "type":"Services"
        }
    ],
    "sg:phone":"+44 1744 811919",
    "sg:postcode":"WA9 5DF",
    "sg:province":"Cheshire",
    "sg:tags":[
        "bookmaker"
    ],
    "wof:name":"Cheshire Racing",
    "wof:placetype":"venue"
},
  "geometry": {"coordinates":[-2.748470068,53.433391571],"type":"Point"}
}