{
  "type": "Feature",
  "properties": {
    "addr:full":"212 Havant Road Portsmouth Hampshire PO6 2EH",
    "addr:housenumber":"212",
    "addr:postcode":"hampshire po6 2eh",
    "addr:street":"Havant Road",
    "iso:country":"GB",
    "sg:address":"212 Havant Road",
    "sg:city":"Portsmouth",
    "sg:classifiers":[
        {
            "category":"Personal",
            "subcategory":"Beauty Salon",
            "type":"Services"
        }
    ],
    "sg:postcode":"PO6 2EH",
    "sg:province":"Hampshire",
    "sg:tags":[
        "lady",
        "hairdresser"
    ],
    "wof:name":"Maison Drayton Ltd.",
    "wof:placetype":"venue"
},
  "geometry": {"coordinates":[-1.0491169691,50.8464546204],"type":"Point"}
}