{
  "type": "Feature",
  "properties": {
    "addr:full":"Llyntro Farm, Rosemary Lane, Rossett Wrexham Wrexham LL12 0LA",
    "addr:postcode":"ll12 0la",
    "addr:street":"Rosemary Lane",
    "iso:country":"GB",
    "sg:address":"Llyntro Farm, Rosemary Lane, Rossett",
    "sg:city":"Wrexham",
    "sg:classifiers":[
        {
            "category":"Farming",
            "subcategory":"Dairy Farm",
            "type":"Manufacturing & Wholesale Goods"
        }
    ],
    "sg:phone":"+44 1244 570422",
    "sg:postcode":"LL12 0LA",
    "sg:province":"Wrexham",
    "sg:tags":[
        "farmer"
    ],
    "wof:name":"G J Walton",
    "wof:placetype":"venue"
},
  "geometry": {"coordinates":[-2.943889,53.109631],"type":"Point"}
}