{
  "type": "Feature",
  "properties": {
    "iso:country":"GB",
    "sg:address":"5 Barnetts Way",
    "sg:city":"Tunbridge Wells",
    "sg:classifiers":[
        {
            "category":"Personal",
            "type":"Services"
        }
    ],
    "sg:phone":"+44 1892 532254",
    "sg:postcode":"TN4 9DW",
    "sg:province":"Kent",
    "sg:tags":[
        "wedding"
    ],
    "wof:name":"Southborough Video Services",
    "wof:placetype":"venue"
},
  "geometry": {"coordinates":[0.2758310139,51.1547775269],"type":"Point"}
}