{
  "type": "Feature",
  "properties": {
    "iso:country":"GB",
    "sg:address":"Ash Service Station, London Road, Wendover",
    "sg:city":"Aylesbury",
    "sg:classifiers":[
        {
            "category":"Retail",
            "subcategory":"Auto Repair",
            "type":"Services"
        }
    ],
    "sg:phone":"+44 1296 624349",
    "sg:postcode":"HP22 6PN",
    "sg:province":"Buckinghamshire",
    "sg:tags":[
        "modification",
        "garage",
        "related"
    ],
    "wof:name":"Wendover Motor Services",
    "wof:placetype":"venue"
},
  "geometry": {"coordinates":[-0.742464,51.764091],"type":"Point"}
}