{
  "type": "Feature",
  "properties": {
    "iso:country":"GB",
    "sg:address":"Eye Hill Farm, Eye Hill Drove, Soham",
    "sg:city":"Ely",
    "sg:classifiers":[
        {
            "category":"Farming",
            "subcategory":"Farm",
            "type":"Manufacturing & Wholesale Goods"
        }
    ],
    "sg:phone":"+44 1353 720424",
    "sg:postcode":"CB7 5XF",
    "sg:province":"Cambridgeshire",
    "sg:tags":[
        "mixed",
        "crop"
    ],
    "wof:name":"Roger C Stevens",
    "wof:placetype":"venue"
},
  "geometry": {"coordinates":[0.35694,52.317989],"type":"Point"}
}