{
  "type": "Feature",
  "properties": {
    "iso:country":"GB",
    "sg:address":"75 Lakeside, Earley",
    "sg:city":"Reading",
    "sg:classifiers":[
        {
            "category":"Building & Trades",
            "subcategory":"Cleaning & Sanitation",
            "type":"Services"
        }
    ],
    "sg:postcode":"RG6 7PH",
    "sg:province":"Berkshire",
    "sg:tags":[
        "commercial"
    ],
    "wof:name":"Town & Country Cleaning Services",
    "wof:placetype":"venue"
},
  "geometry": {"coordinates":[-0.927533,51.434273],"type":"Point"}
}