{
  "type": "Feature",
  "properties": {
    "iso:country":"GB",
    "sg:address":"181 Garratt Lane",
    "sg:city":"London",
    "sg:classifiers":[
        {
            "category":"Retail",
            "subcategory":"Laundry & Dry Cleaning",
            "type":"Services"
        }
    ],
    "sg:phone":"+44 20 8488 8737",
    "sg:postcode":"SW18 4DP",
    "sg:province":"Greater London",
    "sg:tags":[
        "launderette"
    ],
    "wof:name":"Horizon",
    "wof:placetype":"venue"
},
  "geometry": {"coordinates":[-0.189867,51.450699],"type":"Point"}
}