{
  "type": "Feature",
  "properties": {
    "addr:full":"Tennyson Terrace, Morley Leeds West Yorkshire LS27 8QP",
    "addr:postcode":"ls27 8qp",
    "addr:street":"Tennyson Terrace",
    "iso:country":"GB",
    "sg:address":"Tennyson Terrace, Morley",
    "sg:city":"Leeds",
    "sg:classifiers":[
        {
            "category":"Health Services",
            "subcategory":"Nursing And Care Facility",
            "type":"Services"
        },
        {
            "category":"Social Services",
            "subcategory":"Retirement Home",
            "type":"Services"
        }
    ],
    "sg:phone":"+44 113 253 4740",
    "sg:postcode":"LS27 8QP",
    "sg:province":"West Yorkshire",
    "sg:tags":[
        "residential"
    ],
    "wof:name":"Knowle Manor",
    "wof:placetype":"venue"
},
  "geometry": {"coordinates":[-1.594494,53.745739],"type":"Point"}
}