{
  "type": "Feature",
  "properties": {
    "iso:country":"GB",
    "sg:address":"24 Victoria St",
    "sg:city":"Dundee",
    "sg:classifiers":[
        {
            "category":"Retail",
            "subcategory":"Funeral Services",
            "type":"Services"
        }
    ],
    "sg:phone":"+44 1382 461320",
    "sg:postcode":"DD4 6EB",
    "sg:province":"Dundee City",
    "wof:name":"Gray,J & J,",
    "wof:placetype":"venue"
},
  "geometry": {"coordinates":[-2.9602210522,56.4677429199],"type":"Point"}
}