{
  "type": "Feature",
  "properties": {
    "iso:country":"GB",
    "sg:address":"Pennyhooks Farm, Shrivenham",
    "sg:city":"Swindon",
    "sg:classifiers":[
        {
            "category":"Farming",
            "subcategory":"Livestock Farm",
            "type":"Manufacturing & Wholesale Goods"
        }
    ],
    "sg:postcode":"SN6 8EX",
    "sg:province":"Gloucestershire",
    "sg:tags":[
        "others"
    ],
    "wof:name":"E F & G Otter",
    "wof:placetype":"venue"
},
  "geometry": {"coordinates":[-1.659094,51.598389],"type":"Point"}
}