{
  "type": "Feature",
  "properties": {
    "iso:country":"GB",
    "sg:address":"31 Friars Stile Road",
    "sg:city":"Richmond",
    "sg:classifiers":[
        {
            "category":"Real Estate",
            "subcategory":"Architect",
            "type":"Services"
        }
    ],
    "sg:postcode":"TW10 6NH",
    "sg:province":"Greater London",
    "wof:name":"Maurice Broughton Associates",
    "wof:placetype":"venue"
},
  "geometry": {"coordinates":[-0.2961809933,51.4561157227],"type":"Point"}
}