{
  "type": "Feature",
  "properties": {
    "addr:full":"Narborough Road North Leicester Leicestershire LE3 5NF",
    "addr:postcode":"le3 5nf",
    "addr:street":"Narborough Road North",
    "iso:country":"GB",
    "sg:address":"Narborough Road North",
    "sg:city":"Leicester",
    "sg:classifiers":[
        {
            "category":"Home & Garden",
            "subcategory":"Carpets & Floor Coverings",
            "type":"Retail Goods"
        }
    ],
    "sg:phone":"+44 116 255 4401",
    "sg:postcode":"LE3 5NF",
    "sg:province":"Leicestershire",
    "sg:tags":[
        "carpets",
        "rug",
        "matting"
    ],
    "wof:name":"Allied Carpet Stores",
    "wof:placetype":"venue"
},
  "geometry": {"coordinates":[-1.146349,52.633598],"type":"Point"}
}