{
  "type": "Feature",
  "properties": {
    "addr:full":"39 Chatterton Road Bromley Kent BR2 9QQ",
    "addr:housenumber":"39",
    "addr:postcode":"br2 9qq",
    "addr:street":"Chatterton Road",
    "iso:country":"GB",
    "sg:address":"39 Chatterton Road",
    "sg:city":"Bromley",
    "sg:classifiers":[
        {
            "category":"Personal",
            "subcategory":"Beauty Salon",
            "type":"Services"
        }
    ],
    "sg:phone":"+44 20 8464 4727",
    "sg:postcode":"BR2 9QQ",
    "sg:province":"Kent",
    "sg:tags":[
        "lady",
        "hairdresser"
    ],
    "wof:name":"Pauline's",
    "wof:placetype":"venue"
},
  "geometry": {"coordinates":[0.0356430002,51.3924369812],"type":"Point"}
}