{
  "type": "Feature",
  "properties": {
    "addr:full":"Oak Farm, Marton Shrewsbury Shropshire SY4 3SA",
    "addr:postcode":"sy4 3sa",
    "addr:street":"Oak",
    "iso:country":"GB",
    "sg:address":"Oak Farm, Marton",
    "sg:city":"Shrewsbury",
    "sg:classifiers":[
        {
            "category":"Farming",
            "subcategory":"Livestock Farm",
            "type":"Manufacturing & Wholesale Goods"
        }
    ],
    "sg:postcode":"SY4 3SA",
    "sg:province":"Shropshire",
    "sg:tags":[
        "others"
    ],
    "wof:name":"Frederick J Hall",
    "wof:placetype":"venue"
},
  "geometry": {"coordinates":[-2.82036,52.81435],"type":"Point"}
}