{
  "type": "Feature",
  "properties": {
    "iso:country":"GB",
    "sg:address":"136 Gisburn Road, Barrowford",
    "sg:city":"Nelson",
    "sg:classifiers":[
        {
            "category":"Shopping",
            "subcategory":"News",
            "type":"Retail Goods"
        }
    ],
    "sg:phone":"+44 1282 692603",
    "sg:postcode":"BB9 6HQ",
    "sg:province":"Lancashire",
    "sg:tags":[
        "newsagent"
    ],
    "wof:name":"Park News",
    "wof:placetype":"venue"
},
  "geometry": {"coordinates":[-2.2143609524,53.8533439636],"type":"Point"}
}