{
  "type": "Feature",
  "properties": {
    "addr:full":"Unit 6, The Vivars Industrial Centre Selby East Riding of Yorkshire YO8 8BE",
    "addr:housenumber":"unit 6",
    "addr:postcode":"yo8 8be",
    "addr:street":"The Vivars Industrial Centre",
    "iso:country":"GB",
    "sg:address":"Unit 6, The Vivars Industrial Centre",
    "sg:city":"Selby",
    "sg:classifiers":[
        {
            "category":"Banks & Credit Unions",
            "subcategory":"Investment Brokerage",
            "type":"Services"
        }
    ],
    "sg:postcode":"YO8 8BE",
    "sg:province":"East Riding of Yorkshire",
    "sg:tags":[
        "agent"
    ],
    "wof:name":"Gerald W Child U K Agents",
    "wof:placetype":"venue"
},
  "geometry": {"coordinates":[-1.040264,53.765995],"type":"Point"}
}