{
  "type": "Feature",
  "properties": {
    "iso:country":"GB",
    "sg:address":"1 Hogarth Walk",
    "sg:city":"Plymouth",
    "sg:classifiers":[
        {
            "category":"Building & Trades",
            "subcategory":"Cleaning & Sanitation",
            "type":"Services"
        },
        {
            "category":"Home & Garden",
            "subcategory":"Carpets & Floor Coverings",
            "type":"Retail Goods"
        }
    ],
    "sg:phone":"+44 1752 406210",
    "sg:postcode":"PL9 8ET",
    "sg:province":"Devon",
    "sg:tags":[
        "cleaner",
        "upholstery"
    ],
    "wof:name":"Executive Cleaning Services South West Ltd",
    "wof:placetype":"venue"
},
  "geometry": {"coordinates":[-4.074587,50.354263],"type":"Point"}
}