{
  "type": "Feature",
  "properties": {
    "iso:country":"GB",
    "sg:address":"14 Vergam Terrace",
    "sg:city":"Fishguard",
    "sg:classifiers":[
        {
            "category":"Personal",
            "subcategory":"Beauty Salon",
            "type":"Services"
        }
    ],
    "sg:phone":"+44 1348 874651",
    "sg:postcode":"SA65 9DD",
    "sg:province":"Pembrokeshire",
    "sg:tags":[
        "unisex",
        "hairdresser"
    ],
    "wof:name":"Beehive",
    "wof:placetype":"venue"
},
  "geometry": {"coordinates":[-4.981119,51.996426],"type":"Point"}
}