{
  "type": "Feature",
  "properties": {
    "addr:full":"2 The White House, Church Road, Tylers Green High Wycombe Buckinghamshire HP10 8EG",
    "addr:housenumber":"2",
    "addr:postcode":"hp10 8eg",
    "addr:street":"The;Church Road Tylers Green",
    "iso:country":"GB",
    "sg:address":"2 The White House, Church Road, Tylers Green",
    "sg:city":"High Wycombe",
    "sg:classifiers":[
        {
            "category":"Shopping",
            "subcategory":"Beauty & Cosmetics",
            "type":"Retail Goods"
        }
    ],
    "sg:phone":"+44 1494 816297",
    "sg:postcode":"HP10 8EG",
    "sg:province":"Buckinghamshire",
    "wof:name":"Eaden",
    "wof:placetype":"venue"
},
  "geometry": {"coordinates":[-0.69673,51.635342],"type":"Point"}
}