{
  "type": "Feature",
  "properties": {
    "addr:full":"Graigend Drive Coatbridge North Lanarkshire ML5 5TJ",
    "addr:postcode":"ml5 5tj",
    "addr:street":"Graigend Drive",
    "iso:country":"GB",
    "sg:address":"Graigend Drive",
    "sg:city":"Coatbridge",
    "sg:classifiers":[
        {
            "category":"Education",
            "subcategory":"School",
            "type":"Public Place"
        }
    ],
    "sg:phone":"+44 1236 424733",
    "sg:postcode":"ML5 5TJ",
    "sg:province":"North Lanarkshire",
    "sg:tags":[
        "local",
        "authority"
    ],
    "wof:name":"St. Monica's Primary School",
    "wof:placetype":"venue"
},
  "geometry": {"coordinates":[-4.0358390808,55.8587532043],"type":"Point"}
}