{
  "type": "Feature",
  "properties": {
    "addr:full":"114 Station Road Addlestone Surrey KT15 2BQ",
    "addr:housenumber":"114",
    "addr:postcode":"kt15 2bq",
    "addr:street":"Station Road",
    "iso:country":"GB",
    "sg:address":"114 Station Road",
    "sg:city":"Addlestone",
    "sg:classifiers":[
        {
            "category":"Real Estate",
            "subcategory":"Real Estate Agent",
            "type":"Services"
        }
    ],
    "sg:phone":"+44 1932 846767",
    "sg:postcode":"KT15 2BQ",
    "sg:province":"Surrey",
    "wof:name":"Mann & Co",
    "wof:placetype":"venue"
},
  "geometry": {"coordinates":[-0.487447,51.371429],"type":"Point"}
}