{
  "type": "Feature",
  "properties": {
    "iso:country":"GB",
    "sg:address":"28 Granary Street, Burghead",
    "sg:city":"Elgin",
    "sg:classifiers":[
        {
            "category":"Cafe",
            "type":"Food & Drink"
        }
    ],
    "sg:phone":"+44 1343 835885",
    "sg:postcode":"IV30 5UJ",
    "sg:province":"Moray",
    "sg:tags":[
        "tea",
        "room"
    ],
    "wof:name":"The Beach Cafe",
    "wof:placetype":"venue"
},
  "geometry": {"coordinates":[-3.4908180237,57.7008972168],"type":"Point"}
}