{
  "type": "Feature",
  "properties": {
    "iso:country":"GB",
    "sg:address":"Unit 11-12 Newington Enterprise, Centre Wardwell Lane",
    "sg:city":"Sittingbourne",
    "sg:classifiers":[
        {
            "category":"Cemetery",
            "type":"Public Place"
        }
    ],
    "sg:postcode":"ME9 7BP",
    "sg:province":"Kent",
    "sg:tags":[
        "coffin"
    ],
    "wof:name":"Assured Deliverance",
    "wof:placetype":"venue"
},
  "geometry": {"coordinates":[0.67226,51.358391],"type":"Point"}
}