{
  "type": "Feature",
  "properties": {
    "iso:country":"GB",
    "sg:address":"15 Poplar Road, Great Cornard",
    "sg:city":"Sudbury",
    "sg:classifiers":[
        {
            "category":"Personal",
            "subcategory":"Beauty Salon",
            "type":"Services"
        }
    ],
    "sg:phone":"+44 1787 375919",
    "sg:postcode":"CO10 0LH",
    "sg:province":"Essex",
    "sg:tags":[
        "unisex",
        "hairdresser"
    ],
    "wof:name":"Fresh Hair",
    "wof:placetype":"venue"
},
  "geometry": {"coordinates":[0.748278,52.034763],"type":"Point"}
}