{
  "type": "Feature",
  "properties": {
    "addr:full":"2 Copse Close Liss Hampshire GU33 7EW",
    "addr:housenumber":"2",
    "addr:postcode":"gu33 7ew",
    "addr:street":"Copse Close",
    "iso:country":"GB",
    "sg:address":"2 Copse Close",
    "sg:city":"Liss",
    "sg:classifiers":[
        {
            "category":"Professional",
            "subcategory":"Computer Services",
            "type":"Services"
        }
    ],
    "sg:phone":"+44 7798 903812",
    "sg:postcode":"GU33 7EW",
    "sg:province":"Hampshire",
    "sg:tags":[
        "system",
        "software"
    ],
    "wof:name":"Hampshire 508 Ltd.",
    "wof:placetype":"venue"
},
  "geometry": {"coordinates":[-0.8852310181,51.0435943604],"type":"Point"}
}