{
  "type": "Feature",
  "properties": {
    "iso:country":"GB",
    "sg:address":"25 Polworth Road",
    "sg:city":"London",
    "sg:classifiers":[
        {
            "category":"Retail",
            "subcategory":"Storage",
            "type":"Services"
        }
    ],
    "sg:phone":"+44 1306 712144",
    "sg:postcode":"SW16 2ET",
    "sg:province":"Greater London",
    "sg:tags":[
        "household",
        "removal"
    ],
    "wof:name":"S L T Removals",
    "wof:placetype":"venue"
},
  "geometry": {"coordinates":[-0.1273889989,51.424823761],"type":"Point"}
}