{
  "type": "Feature",
  "properties": {
    "iso:country":"GB",
    "sg:address":"Pardovan Works, Philpstoun",
    "sg:city":"Linlithgow",
    "sg:classifiers":[
        {
            "category":"Retail",
            "subcategory":"Auto Repair",
            "type":"Services"
        }
    ],
    "sg:phone":"+44 1506 834067",
    "sg:postcode":"EH49 7TT",
    "sg:province":"Falkirk",
    "sg:tags":[
        "bodybuilder",
        "repairer"
    ],
    "wof:name":"McPhie Coachbuilders",
    "wof:placetype":"venue"
},
  "geometry": {"coordinates":[-3.602564,55.97657],"type":"Point"}
}