{
  "type": "Feature",
  "properties": {
    "addr:full":"Kirkcaldy East Area Office, 2 Park Rd Kirkcaldy Fife KY1 3EL",
    "addr:housenumber":"2",
    "addr:postcode":"ky1 3el",
    "addr:street":"East;Park Rd",
    "iso:country":"GB",
    "sg:address":"Kirkcaldy East Area Office, 2 Park Rd",
    "sg:city":"Kirkcaldy",
    "sg:classifiers":[
        {
            "category":"Government",
            "subcategory":"Office",
            "type":"Public Place"
        }
    ],
    "sg:phone":"+44 1592 418338",
    "sg:postcode":"KY1 3EL",
    "sg:province":"Fife",
    "sg:tags":[
        "local"
    ],
    "wof:name":"Fife Council",
    "wof:placetype":"venue"
},
  "geometry": {"coordinates":[-3.163029,56.109596],"type":"Point"}
}