{
  "type": "Feature",
  "properties": {
    "addr:full":"Long Crendon Manor, Frogmore Lane Aylesbury Buckinghamshire HP18 9DZ",
    "addr:postcode":"hp18 9dz",
    "addr:street":"Frogmore Lane",
    "iso:country":"GB",
    "sg:address":"Long Crendon Manor, Frogmore Lane",
    "sg:city":"Aylesbury",
    "sg:classifiers":[
        {
            "category":"Sports & Exercise",
            "subcategory":"Stables",
            "type":"Entertainment"
        }
    ],
    "sg:postcode":"HP18 9DZ",
    "sg:province":"Buckinghamshire",
    "sg:tags":[
        "education",
        "equestrian"
    ],
    "wof:name":"Crendon Manor Stables",
    "wof:placetype":"venue"
},
  "geometry": {"coordinates":[-0.995376,51.773502],"type":"Point"}
}