{
  "type": "Feature",
  "properties": {
    "addr:full":"9 Chapel Hill Wellingborough Bedfordshire NN29 7AS",
    "addr:housenumber":"9",
    "addr:postcode":"nn29 7as",
    "addr:street":"Chapel Hill",
    "iso:country":"GB",
    "sg:address":"9 Chapel Hill",
    "sg:city":"Wellingborough",
    "sg:classifiers":[
        {
            "category":"Building & Trades",
            "subcategory":"Construction",
            "type":"Services"
        }
    ],
    "sg:phone":"+44 1933 318109",
    "sg:postcode":"NN29 7AS",
    "sg:province":"Bedfordshire",
    "sg:tags":[
        "contractor",
        "paving",
        "driveway"
    ],
    "wof:name":"Steve Parkin Blockpaving",
    "wof:placetype":"venue"
},
  "geometry": {"coordinates":[-0.709649,52.273842],"type":"Point"}
}