{
  "type": "Feature",
  "properties": {
    "addr:full":"9 Hyde Park Crescent London Greater London W2 2PY",
    "addr:housenumber":"9",
    "addr:postcode":"w2 2py",
    "addr:street":"Hyde Park Crescent",
    "iso:country":"GB",
    "sg:address":"9 Hyde Park Crescent",
    "sg:city":"London",
    "sg:classifiers":[
        {
            "category":"Taxi",
            "type":"Transportation"
        }
    ],
    "sg:phone":"+44 20 7262 7788",
    "sg:postcode":"W2 2PY",
    "sg:province":"Greater London",
    "sg:tags":[
        "toastmaster"
    ],
    "wof:name":"Sheila Davies",
    "wof:placetype":"venue"
},
  "geometry": {"coordinates":[-0.169077,51.515133],"type":"Point"}
}