{
  "type": "Feature",
  "properties": {
    "iso:country":"GB",
    "sg:address":"Coronation House, The Borough",
    "sg:city":"Wedmore",
    "sg:classifiers":[
        {
            "category":"Health Services",
            "subcategory":"Dentist",
            "type":"Services"
        }
    ],
    "sg:phone":"+44 1934 713013",
    "sg:postcode":"BS28 4EG",
    "sg:province":"Somerset",
    "wof:name":"Wedmore Dental Practice",
    "wof:placetype":"venue"
},
  "geometry": {"coordinates":[-2.8088340759,51.2278938293],"type":"Point"}
}