{
  "type": "Feature",
  "properties": {
    "addr:full":"30 North Street Wetherby North Yorkshire LS22 6NN",
    "addr:housenumber":"30",
    "addr:postcode":"ls22 6nn",
    "addr:street":"North Street",
    "iso:country":"GB",
    "sg:address":"30 North Street",
    "sg:city":"Wetherby",
    "sg:classifiers":[
        {
            "category":"Shopping",
            "type":"Retail Goods"
        },
        {
            "category":"Sports & Exercise",
            "subcategory":"Playing Field",
            "type":"Entertainment"
        }
    ],
    "sg:phone":"+44 1937 581365",
    "sg:postcode":"LS22 6NN",
    "sg:province":"North Yorkshire",
    "sg:tags":[
        "merchant",
        "lift",
        "handling",
        "engineer",
        "mechanical"
    ],
    "wof:name":"Westrup (U K) Ltd.",
    "wof:placetype":"venue"
},
  "geometry": {"coordinates":[-1.385562,53.928555],"type":"Point"}
}