{
  "type": "Feature",
  "properties": {
    "iso:country":"GB",
    "sg:address":"60 Manor Drive, Upton",
    "sg:city":"Wirral",
    "sg:classifiers":[
        {
            "category":"Professional",
            "subcategory":"Management & Consulting",
            "type":"Services"
        }
    ],
    "sg:phone":"+44 151 678 2369",
    "sg:postcode":"CH49 6LQ",
    "sg:province":"Merseyside",
    "sg:tags":[
        "consultant",
        "business"
    ],
    "wof:name":"Txi Consulting Ltd.",
    "wof:placetype":"venue"
},
  "geometry": {"coordinates":[-3.094208,53.390678],"type":"Point"}
}