{
  "type": "Feature",
  "properties": {
    "addr:full":"285 Rochdale Road Oldham Lancashire OL1 2HG",
    "addr:housenumber":"285",
    "addr:postcode":"ol1 2hg",
    "addr:street":"Rochdale Road",
    "iso:country":"GB",
    "sg:address":"285 Rochdale Road",
    "sg:city":"Oldham",
    "sg:classifiers":[
        {
            "category":"Shopping",
            "subcategory":"Pharmacy",
            "type":"Retail Goods"
        }
    ],
    "sg:phone":"+44 161 633 1950",
    "sg:postcode":"OL1 2HG",
    "sg:province":"Lancashire",
    "sg:tags":[
        "pharmacist",
        "dispensing",
        "chemist"
    ],
    "wof:name":"Gardeners Chemist",
    "wof:placetype":"venue"
},
  "geometry": {"coordinates":[-2.1203570366,53.5497665405],"type":"Point"}
}