{
  "type": "Feature",
  "properties": {
    "addr:full":"24 Blackfriars Street Salford Greater Manchester M3 5BQ",
    "addr:housenumber":"24",
    "addr:postcode":"m3 5bq",
    "addr:street":"Blackfriars Street",
    "iso:country":"GB",
    "sg:address":"24 Blackfriars Street",
    "sg:city":"Salford",
    "sg:classifiers":[
        {
            "category":"Bars & Pubs",
            "type":"Food & Drink"
        }
    ],
    "sg:phone":"+44 161 832 7981",
    "sg:postcode":"M3 5BQ",
    "sg:province":"Greater Manchester",
    "sg:tags":[
        "pubs",
        "inn"
    ],
    "wof:name":"Whitbread Group Plc",
    "wof:placetype":"venue"
},
  "geometry": {"coordinates":[-2.248649,53.484329],"type":"Point"}
}