{
  "type": "Feature",
  "properties": {
    "addr:full":"5 Thunderton Place Elgin Moray IV30 1BQ",
    "addr:housenumber":"5",
    "addr:postcode":"iv30 1bq",
    "addr:street":"Thunderton Place",
    "iso:country":"GB",
    "sg:address":"5 Thunderton Place",
    "sg:city":"Elgin",
    "sg:classifiers":[
        {
            "category":"Health Services",
            "subcategory":"Podiatrist",
            "type":"Services"
        }
    ],
    "sg:phone":"+44 1343 549177",
    "sg:postcode":"IV30 1BQ",
    "sg:province":"Moray",
    "sg:tags":[
        "podiatrists",
        "chiropodist"
    ],
    "wof:name":"G W Macpherson",
    "wof:placetype":"venue"
},
  "geometry": {"coordinates":[-3.317525,57.648067],"type":"Point"}
}