{
  "type": "Feature",
  "properties": {
    "iso:country":"GB",
    "sg:address":"Top Floor Dolphin House, 21 Hendford",
    "sg:city":"Yeovil",
    "sg:classifiers":[
        {
            "category":"Social Services",
            "subcategory":"Job Training",
            "type":"Services"
        },
        {
            "category":"Education",
            "subcategory":"Special Training",
            "type":"Public Place"
        },
        {
            "category":"Government",
            "subcategory":"Office",
            "type":"Public Place"
        }
    ],
    "sg:phone":"+44 1935 420067",
    "sg:postcode":"BA20 1TQ",
    "sg:province":"Somerset",
    "sg:tags":[
        "product",
        "local",
        "centre"
    ],
    "sg:website":"http://www.sct.ac",
    "wof:name":"Somerset County Training",
    "wof:placetype":"venue"
},
  "geometry": {"coordinates":[-2.63495,50.940228],"type":"Point"}
}