{
  "type": "Feature",
  "properties": {
    "addr:full":"10 Blenheim Avenue, Stony Stratford Milton Keynes Buckinghamshire MK11 1EX",
    "addr:housenumber":"10",
    "addr:postcode":"mk11 1ex",
    "addr:street":"Blenheim Avenue",
    "iso:country":"GB",
    "sg:address":"10 Blenheim Avenue, Stony Stratford",
    "sg:city":"Milton Keynes",
    "sg:classifiers":[
        {
            "category":"Building & Trades",
            "subcategory":"Construction",
            "type":"Services"
        }
    ],
    "sg:postcode":"MK11 1EX",
    "sg:province":"Buckinghamshire",
    "sg:tags":[
        "bricklayer",
        "bricklaying"
    ],
    "wof:name":"Malcolm Vaughan Haynes",
    "wof:placetype":"venue"
},
  "geometry": {"coordinates":[-0.847098,52.052029],"type":"Point"}
}