{
  "type": "Feature",
  "properties": {
    "addr:full":"116 Old Lane Leeds West Yorkshire LS11 8AG",
    "addr:housenumber":"116",
    "addr:postcode":"ls11 8ag",
    "addr:street":"Old Lane",
    "iso:country":"GB",
    "sg:address":"116 Old Lane",
    "sg:city":"Leeds",
    "sg:classifiers":[
        {
            "category":"Retail",
            "subcategory":"Auto Repair",
            "type":"Services"
        }
    ],
    "sg:phone":"+44 113 280 0515",
    "sg:postcode":"LS11 8AG",
    "sg:province":"West Yorkshire",
    "sg:tags":[
        "body",
        "car"
    ],
    "wof:name":"Accident & Repair Centre",
    "wof:placetype":"venue"
},
  "geometry": {"coordinates":[-1.563349,53.765591],"type":"Point"}
}