{
  "type": "Feature",
  "properties": {
    "iso:country":"GB",
    "sg:address":"Isle Farm, Isle Of Whithorn",
    "sg:city":"Newton Stewart",
    "sg:classifiers":[
        {
            "category":"Home & Garden",
            "subcategory":"Garden Supply",
            "type":"Retail Goods"
        },
        {
            "category":"Farming",
            "subcategory":"Farm",
            "type":"Manufacturing & Wholesale Goods"
        }
    ],
    "sg:postcode":"DG8 8JF",
    "sg:province":"Dumfries and Galloway",
    "sg:tags":[
        "mixed",
        "bulb",
        "crop",
        "grower"
    ],
    "wof:name":"Thomas Forsyth",
    "wof:placetype":"venue"
},
  "geometry": {"coordinates":[-4.366126,54.700771],"type":"Point"}
}