{
  "type": "Feature",
  "properties": {
    "addr:full":"81 High Rd West Felixstowe Suffolk IP11 9AB",
    "addr:housenumber":"81",
    "addr:postcode":"ip11 9ab",
    "addr:street":"High Rd West",
    "iso:country":"GB",
    "sg:address":"81 High Rd West",
    "sg:city":"Felixstowe",
    "sg:classifiers":[
        {
            "category":"Shopping",
            "subcategory":"Pets & Pet Supplies",
            "type":"Retail Goods"
        }
    ],
    "sg:phone":"+44 1394 270129",
    "sg:postcode":"IP11 9AB",
    "sg:province":"Suffolk",
    "wof:name":"C.O.F. Ltd",
    "wof:placetype":"venue"
},
  "geometry": {"coordinates":[1.3459999561,51.9679450989],"type":"Point"}
}