{
  "type": "Feature",
  "properties": {
    "addr:full":"Preston Chapel, 164 Preston Rd Yeovil Somerset BA20 2EQ",
    "addr:housenumber":"164",
    "addr:postcode":"ba20 2eq",
    "addr:street":"Preston Rd",
    "iso:country":"GB",
    "sg:address":"Preston Chapel, 164 Preston Rd",
    "sg:city":"Yeovil",
    "sg:classifiers":[
        {
            "category":"Place Of Worship",
            "type":"Public Place"
        }
    ],
    "sg:phone":"+44 1935 433146",
    "sg:postcode":"BA20 2EQ",
    "sg:province":"Somerset",
    "wof:name":"Yeovil Community Church",
    "wof:placetype":"venue"
},
  "geometry": {"coordinates":[-2.6581299305,50.9435195923],"type":"Point"}
}