{
  "type": "Feature",
  "properties": {
    "addr:full":"4 Oak View, Brecon Road Crickhowell Monmouthshire NP8 1DG",
    "addr:housenumber":"4",
    "addr:postcode":"np8 1dg",
    "addr:street":"Oak;Brecon Road",
    "iso:country":"GB",
    "sg:address":"4 Oak View, Brecon Road",
    "sg:city":"Crickhowell",
    "sg:classifiers":[
        {
            "category":"Building & Trades",
            "subcategory":"Construction",
            "type":"Services"
        }
    ],
    "sg:phone":"+44 1873 812194",
    "sg:postcode":"NP8 1DG",
    "sg:province":"Monmouthshire",
    "sg:tags":[
        "builder"
    ],
    "wof:name":"David Isaac",
    "wof:placetype":"venue"
},
  "geometry": {"coordinates":[-3.1381220818,51.8616256714],"type":"Point"}
}