{
  "type": "Feature",
  "properties": {
    "addr:full":"Edgbury Court, 12 Goldsmith Lane London Greater London NW9 9AL",
    "addr:housenumber":"12",
    "addr:postcode":"nw9 9al",
    "addr:street":"Goldsmith Lane",
    "iso:country":"GB",
    "sg:address":"Edgbury Court, 12 Goldsmith Lane",
    "sg:city":"London",
    "sg:classifiers":[
        {
            "category":"Professional",
            "subcategory":"Engineering",
            "type":"Services"
        }
    ],
    "sg:postcode":"NW9 9AL",
    "sg:province":"Greater London",
    "sg:tags":[
        "contractor",
        "electrical",
        "engineer"
    ],
    "wof:name":"Fenn Electrics",
    "wof:placetype":"venue"
},
  "geometry": {"coordinates":[-0.2674880028,51.5897712708],"type":"Point"}
}