{
  "type": "Feature",
  "properties": {
    "addr:full":"Bedford Road, Milton Ernest Bedford Bedfordshire MK44 1RR",
    "addr:postcode":"mk44 1rr",
    "addr:street":"Bedford Road",
    "iso:country":"GB",
    "sg:address":"Bedford Road, Milton Ernest",
    "sg:city":"Bedford",
    "sg:classifiers":[
        {
            "category":"Health Services",
            "subcategory":"Nursing And Care Facility",
            "type":"Services"
        }
    ],
    "sg:postcode":"MK44 1RR",
    "sg:province":"Bedfordshire",
    "sg:tags":[
        "home"
    ],
    "wof:name":"The Grange",
    "wof:placetype":"venue"
},
  "geometry": {"coordinates":[-0.5102850199,52.1920852661],"type":"Point"}
}