{
  "type": "Feature",
  "properties": {
    "iso:country":"GB",
    "sg:address":"9 Barrack Street",
    "sg:city":"Bridport",
    "sg:classifiers":[
        {
            "category":"Education",
            "subcategory":"Dance Studio",
            "type":"Public Place"
        }
    ],
    "sg:phone":"+44 1308 427769",
    "sg:postcode":"DT6 3LX",
    "sg:province":"Dorset",
    "sg:tags":[
        "school",
        "dancing"
    ],
    "wof:name":"BRIDGEPORT SCHOOL OF DANCING",
    "wof:placetype":"venue"
},
  "geometry": {"coordinates":[-2.75487,50.733692],"type":"Point"}
}