{
  "type": "Feature",
  "properties": {
    "addr:full":"52 Peach Street Wokingham Berkshire RG40 1XG",
    "addr:housenumber":"52",
    "addr:postcode":"rg40 1xg",
    "addr:street":"Peach Street",
    "iso:country":"GB",
    "sg:address":"52 Peach Street",
    "sg:city":"Wokingham",
    "sg:classifiers":[
        {
            "category":"Shopping",
            "subcategory":"Pets & Pet Supplies",
            "type":"Retail Goods"
        }
    ],
    "sg:postcode":"RG40 1XG",
    "sg:province":"Berkshire",
    "wof:name":"Wokingham Pet Shop",
    "wof:placetype":"venue"
},
  "geometry": {"coordinates":[-0.830722,51.410904],"type":"Point"}
}