{
  "type": "Feature",
  "properties": {
    "addr:full":"Northbrook College, Broadwater Rd Worthing West Sussex BN14 8HJ",
    "addr:postcode":"bn14 8hj",
    "addr:street":"Broadwater Rd",
    "iso:country":"GB",
    "sg:address":"Northbrook College, Broadwater Rd",
    "sg:city":"Worthing",
    "sg:classifiers":[
        {
            "category":"Education",
            "subcategory":"University",
            "type":"Public Place"
        }
    ],
    "sg:phone":"+44 1903 206632",
    "sg:postcode":"BN14 8HJ",
    "sg:province":"West Sussex",
    "sg:tags":[
        "adult"
    ],
    "wof:name":"Open Learning Centre",
    "wof:placetype":"venue"
},
  "geometry": {"coordinates":[-0.3661839962,50.8302688599],"type":"Point"}
}