{
  "type": "Feature",
  "properties": {
    "addr:full":"44 Westparkside Goole East Riding of Yorkshire DN14 6XN",
    "addr:housenumber":"44",
    "addr:postcode":"dn14 6xn",
    "addr:street":"Westparkside Goole",
    "iso:country":"GB",
    "sg:address":"44 Westparkside",
    "sg:city":"Goole",
    "sg:classifiers":[
        {
            "category":"Building & Trades",
            "subcategory":"Construction",
            "type":"Services"
        }
    ],
    "sg:phone":"+44 1405 761229",
    "sg:postcode":"DN14 6XN",
    "sg:province":"East Riding of Yorkshire",
    "sg:tags":[
        "concrete",
        "contractor"
    ],
    "wof:name":"Sykes Concreting Services Ltd",
    "wof:placetype":"venue"
},
  "geometry": {"coordinates":[-0.889179,53.713432],"type":"Point"}
}