{
  "type": "Feature",
  "properties": {
    "iso:country":"GB",
    "sg:address":"Villas Rd, Bolsover",
    "sg:city":"Chesterfield",
    "sg:classifiers":[
        {
            "category":"Community Center",
            "type":"Public Place"
        }
    ],
    "sg:phone":"+44 1246 828054",
    "sg:postcode":"S44 6QE",
    "sg:province":"Derbyshire",
    "sg:tags":[
        "recreation",
        "leisure",
        "centre"
    ],
    "wof:name":"Castle Lesiure Park",
    "wof:placetype":"venue"
},
  "geometry": {"coordinates":[-1.2900710106,53.2290916443],"type":"Point"}
}