{
  "type": "Feature",
  "properties": {
    "addr:full":"13 The Avenue, Kew Richmond Greater London TW9 2AL",
    "addr:housenumber":"13",
    "addr:postcode":"tw9 2al",
    "addr:street":"The Avenue",
    "iso:country":"GB",
    "sg:address":"13 The Avenue, Kew",
    "sg:city":"Richmond",
    "sg:classifiers":[
        {
            "category":"Recreation",
            "subcategory":"Gun Range",
            "type":"Entertainment"
        }
    ],
    "sg:phone":"+44 20 8940 4114",
    "sg:postcode":"TW9 2AL",
    "sg:province":"Greater London",
    "sg:tags":[
        "operator",
        "tour"
    ],
    "wof:name":"Templeworld Ltd.",
    "wof:placetype":"venue"
},
  "geometry": {"coordinates":[-0.287702,51.473354],"type":"Point"}
}