{
  "type": "Feature",
  "properties": {
    "addr:full":"Duck Street, Tisbury Salisbury Wiltshire SP3 6LJ",
    "addr:postcode":"sp3 6lj",
    "addr:street":"Duck Street",
    "iso:country":"GB",
    "sg:address":"Duck Street, Tisbury",
    "sg:city":"Salisbury",
    "sg:classifiers":[
        {
            "category":"Professional",
            "subcategory":"Engineering",
            "type":"Services"
        }
    ],
    "sg:phone":"+44 1747 870822",
    "sg:postcode":"SP3 6LJ",
    "sg:province":"Wiltshire",
    "sg:tags":[
        "electronic",
        "engineer"
    ],
    "wof:name":"Ian Harris",
    "wof:placetype":"venue"
},
  "geometry": {"coordinates":[-2.07389,51.066547],"type":"Point"}
}