{
  "type": "Feature",
  "properties": {
    "iso:country":"GB",
    "sg:address":"12 Market St",
    "sg:city":"Highbridge",
    "sg:classifiers":[
        {
            "category":"Professional",
            "subcategory":"Printing & Photocopies",
            "type":"Services"
        }
    ],
    "sg:phone":"+44 1278 780953",
    "sg:postcode":"TA9 3BW",
    "sg:province":"Somerset",
    "sg:tags":[
        "duplicating",
        "copying"
    ],
    "wof:name":"Clarity Copiers Avon & Co",
    "wof:placetype":"venue"
},
  "geometry": {"coordinates":[-2.975102,51.219238],"type":"Point"}
}