{
  "type": "Feature",
  "properties": {
    "addr:full":"65 Johnson Street Laurencekirk Aberdeenshire AB30 1AN",
    "addr:housenumber":"65",
    "addr:postcode":"ab30 1an",
    "addr:street":"Johnson Street",
    "iso:country":"GB",
    "sg:address":"65 Johnson Street",
    "sg:city":"Laurencekirk",
    "sg:classifiers":[
        {
            "category":"Professional",
            "type":"Services"
        }
    ],
    "sg:phone":"+44 1561 377420",
    "sg:postcode":"AB30 1AN",
    "sg:province":"Aberdeenshire",
    "sg:tags":[
        "auctioneer"
    ],
    "wof:name":"James S T Liddle",
    "wof:placetype":"venue"
},
  "geometry": {"coordinates":[-2.466624,56.830967],"type":"Point"}
}