{
  "type": "Feature",
  "properties": {
    "addr:full":"24 Plumley Road, Handforth Wilmslow Cheshire SK9 3RR",
    "addr:housenumber":"24",
    "addr:postcode":"sk9 3rr",
    "addr:street":"Plumley Road",
    "iso:country":"GB",
    "sg:address":"24 Plumley Road, Handforth",
    "sg:city":"Wilmslow",
    "sg:classifiers":[
        {
            "category":"Shopping",
            "subcategory":"Pets & Pet Supplies",
            "type":"Retail Goods"
        }
    ],
    "sg:phone":"+44 1625 548044",
    "sg:postcode":"SK9 3RR",
    "sg:province":"Cheshire",
    "wof:name":"Handforth Pets Groomers",
    "wof:placetype":"venue"
},
  "geometry": {"coordinates":[-2.215852,53.354565],"type":"Point"}
}