{
  "type": "Feature",
  "properties": {
    "addr:full":"Regional Office 5 College Street St Albans Hertfordshire AL3 4PW",
    "addr:housenumber":"5",
    "addr:postcode":"al3 4pw",
    "addr:street":"College Street",
    "iso:country":"GB",
    "sg:address":"Regional Office 5 College Street",
    "sg:city":"St Albans",
    "sg:classifiers":[
        {
            "category":"Building & Trades",
            "subcategory":"Construction",
            "type":"Services"
        }
    ],
    "sg:phone":"+44 1344 426826",
    "sg:postcode":"AL3 4PW",
    "sg:province":"Hertfordshire",
    "sg:tags":[
        "contractor"
    ],
    "wof:name":"John Mowlem Construction Eastern Region",
    "wof:placetype":"venue"
},
  "geometry": {"coordinates":[-0.34218,51.7533],"type":"Point"}
}