{
  "type": "Feature",
  "properties": {
    "addr:full":"Unit B Chandler Centre, Hythe Quay Colchester Essex CO2 8JL",
    "addr:postcode":"co2 8jl",
    "addr:street":"Hythe Quay Colchester",
    "iso:country":"GB",
    "sg:address":"Unit B Chandler Centre, Hythe Quay",
    "sg:city":"Colchester",
    "sg:classifiers":[
        {
            "category":"Autos & Motor Vehicles",
            "subcategory":"Automobile Sales",
            "type":"Retail Goods"
        }
    ],
    "sg:phone":"+44 1206 864268",
    "sg:postcode":"CO2 8JL",
    "sg:province":"Essex",
    "sg:tags":[
        "car"
    ],
    "wof:name":"S M King",
    "wof:placetype":"venue"
},
  "geometry": {"coordinates":[0.9172899723,51.8753700256],"type":"Point"}
}