{
  "type": "Feature",
  "properties": {
    "addr:full":"31 Tennyson Ho, Browning St Elephant And Castle Greater London SE17 1DB",
    "addr:housenumber":"31",
    "addr:postcode":"se17 1db",
    "addr:street":"Tennyson Ho Browning St",
    "iso:country":"GB",
    "sg:address":"31 Tennyson Ho, Browning St",
    "sg:city":"Elephant And Castle",
    "sg:classifiers":[
        {
            "category":"Government",
            "subcategory":"Office",
            "type":"Public Place"
        }
    ],
    "sg:phone":"+44 20 7708 0708",
    "sg:postcode":"SE17 1DB",
    "sg:province":"Greater London",
    "sg:tags":[
        "local"
    ],
    "wof:name":"Browning Estate Management Board",
    "wof:placetype":"venue"
},
  "geometry": {"coordinates":[-0.0943899974,51.4896507263],"type":"Point"}
}