{
  "type": "Feature",
  "properties": {
    "addr:full":"2 Pellon Lane Halifax West Yorkshire HX1 5SP",
    "addr:housenumber":"2",
    "addr:postcode":"hx1 5sp",
    "addr:street":"Pellon Lane",
    "iso:country":"GB",
    "sg:address":"2 Pellon Lane",
    "sg:city":"Halifax",
    "sg:classifiers":[
        {
            "category":"Cafe",
            "type":"Food & Drink"
        }
    ],
    "sg:phone":"+44 1422 364314",
    "sg:postcode":"HX1 5SP",
    "sg:province":"West Yorkshire",
    "sg:tags":[
        "tea",
        "room"
    ],
    "wof:name":"Breakfast Bar",
    "wof:placetype":"venue"
},
  "geometry": {"coordinates":[-1.863461,53.723736],"type":"Point"}
}