{
  "type": "Feature",
  "properties": {
    "addr:full":"High Street, Clapham Bedford Bedfordshire MK41 6EG",
    "addr:postcode":"mk41 6eg",
    "addr:street":"High Street",
    "iso:country":"GB",
    "sg:address":"High Street, Clapham",
    "sg:city":"Bedford",
    "sg:classifiers":[
        {
            "category":"Education",
            "subcategory":"School",
            "type":"Public Place"
        }
    ],
    "sg:phone":"+44 1234 359128",
    "sg:postcode":"MK41 6EG",
    "sg:province":"Bedfordshire",
    "sg:tags":[
        "local",
        "authority"
    ],
    "wof:name":"Ursula Taylor Lower School",
    "wof:placetype":"venue"
},
  "geometry": {"coordinates":[-0.5020890236,52.1637954712],"type":"Point"}
}