{
  "type": "Feature",
  "properties": {
    "addr:full":"62 Burnhead Road Glasgow Glasgow City G43 2SU",
    "addr:housenumber":"62",
    "addr:postcode":"g43 2su",
    "addr:street":"Burnhead Road",
    "iso:country":"GB",
    "sg:address":"62 Burnhead Road",
    "sg:city":"Glasgow",
    "sg:classifiers":[
        {
            "category":"Organizations",
            "subcategory":"Community Association",
            "type":"Services"
        }
    ],
    "sg:postcode":"G43 2SU",
    "sg:province":"Glasgow City",
    "sg:tags":[
        "relation",
        "public"
    ],
    "wof:name":"Robert Joyner Associates",
    "wof:placetype":"venue"
},
  "geometry": {"coordinates":[-4.2816390991,55.8136672974],"type":"Point"}
}