{
  "type": "Feature",
  "properties": {
    "iso:country":"GB",
    "sg:address":"Perth Road",
    "sg:city":"Blairgowrie",
    "sg:classifiers":[
        {
            "category":"Travel",
            "subcategory":"Hotels & Motels",
            "type":"Entertainment"
        }
    ],
    "sg:postcode":"PH10 6EQ",
    "sg:province":"Perth and Kinross",
    "sg:tags":[
        "house",
        "guest"
    ],
    "wof:name":"Duan Villa Guesthouse",
    "wof:placetype":"venue"
},
  "geometry": {"coordinates":[-3.343914,56.588066],"type":"Point"}
}