{
  "type": "Feature",
  "properties": {
    "iso:country":"GB",
    "sg:address":"Raymond Close, Rodney Way",
    "sg:city":"Slough",
    "sg:classifiers":[
        {
            "category":"Education",
            "subcategory":"School",
            "type":"Public Place"
        }
    ],
    "sg:phone":"+44 1753 682937",
    "sg:postcode":"SL3 0PR",
    "sg:province":"Berkshire",
    "sg:tags":[
        "college"
    ],
    "wof:name":"Pippins School",
    "wof:placetype":"venue"
},
  "geometry": {"coordinates":[-0.511089,51.48111],"type":"Point"}
}