{
  "type": "Feature",
  "properties": {
    "addr:full":"P O Box 34 Bangor Isle of Anglesey LL60 6WD",
    "addr:housenumber":"box 34",
    "addr:postcode":"ll60 6wd",
    "addr:street":"P O",
    "iso:country":"GB",
    "sg:address":"P O Box 34",
    "sg:city":"Bangor",
    "sg:classifiers":[
        {
            "category":"Home & Garden",
            "subcategory":"Home Furnishings",
            "type":"Retail Goods"
        }
    ],
    "sg:postcode":"LL60 6WD",
    "sg:province":"Isle of Anglesey",
    "sg:tags":[
        "furnishers",
        "planner",
        "kitchen"
    ],
    "wof:name":"The Design House 2000 Ltd.",
    "wof:placetype":"venue"
},
  "geometry": {"coordinates":[-4.277279,53.219921],"type":"Point"}
}