{
  "type": "Feature",
  "properties": {
    "addr:full":"179 Findon Rd Worthing West Sussex BN14 0EP",
    "addr:housenumber":"179",
    "addr:postcode":"bn14 0ep",
    "addr:street":"Findon Rd",
    "iso:country":"GB",
    "sg:address":"179 Findon Rd",
    "sg:city":"Worthing",
    "sg:classifiers":[
        {
            "category":"Retail",
            "subcategory":"Veterinary Services",
            "type":"Services"
        }
    ],
    "sg:phone":"+44 1903 877325",
    "sg:postcode":"BN14 0EP",
    "sg:province":"West Sussex",
    "sg:tags":[
        "surgeon"
    ],
    "wof:name":"Lyons Richard",
    "wof:placetype":"venue"
},
  "geometry": {"coordinates":[-0.3989279866,50.8500061035],"type":"Point"}
}