{
  "type": "Feature",
  "properties": {
    "addr:full":"117a Long Acre London Greater London WC2E 9TA",
    "addr:housenumber":"117a",
    "addr:postcode":"wc2e 9ta",
    "addr:street":"Long Acre",
    "iso:country":"GB",
    "sg:address":"117a Long Acre",
    "sg:city":"London",
    "sg:classifiers":[
        {
            "category":"Shopping",
            "subcategory":"Clothing, Apparel, & Fashions",
            "type":"Retail Goods"
        }
    ],
    "sg:phone":"+44 20 7497 1255",
    "sg:postcode":"WC2E 9TA",
    "sg:province":"Greater London",
    "sg:tags":[
        "shop"
    ],
    "wof:name":"The Original Levi's Store",
    "wof:placetype":"venue"
},
  "geometry": {"coordinates":[-0.1250669956,51.5128860474],"type":"Point"}
}