{
  "type": "Feature",
  "properties": {
    "addr:full":"5 Bridge Street Pickering North Yorkshire YO18 8DT",
    "addr:housenumber":"5",
    "addr:postcode":"yo18 8dt",
    "addr:street":"Bridge Street",
    "iso:country":"GB",
    "sg:address":"5 Bridge Street",
    "sg:city":"Pickering",
    "sg:classifiers":[
        {
            "category":"Personal",
            "subcategory":"Beauty Salon",
            "type":"Services"
        },
        {
            "category":"Personal",
            "subcategory":"Barber",
            "type":"Services"
        }
    ],
    "sg:phone":"+44 1751 475117",
    "sg:postcode":"YO18 8DT",
    "sg:province":"North Yorkshire",
    "sg:tags":[
        "unisex",
        "hairdresser"
    ],
    "wof:name":"Mister Paul",
    "wof:placetype":"venue"
},
  "geometry": {"coordinates":[-0.778793,54.246468],"type":"Point"}
}