{
  "type": "Feature",
  "properties": {
    "iso:country":"GB",
    "sg:address":"17 Allestree Rd",
    "sg:city":"London",
    "sg:classifiers":[
        {
            "category":"Communications",
            "subcategory":"Film & Video Production",
            "type":"Services"
        }
    ],
    "sg:postcode":"SW6 6AD",
    "sg:province":"Greater London",
    "sg:tags":[
        "tv",
        "studio"
    ],
    "wof:name":"Clay,Barnaby,",
    "wof:placetype":"venue"
},
  "geometry": {"coordinates":[-0.2126,51.47945],"type":"Point"}
}