{
  "type": "Feature",
  "properties": {
    "iso:country":"GB",
    "sg:address":"83 Whitecraig Rd",
    "sg:city":"Musselburgh",
    "sg:classifiers":[
        {
            "category":"Retail",
            "subcategory":"Auto Repair",
            "type":"Services"
        }
    ],
    "sg:phone":"+44 131 665 9301",
    "sg:postcode":"EH21 8NF",
    "sg:province":"City of Edinburgh",
    "sg:tags":[
        "modification",
        "garage"
    ],
    "wof:name":"A1 Recovery & Garage Services",
    "wof:placetype":"venue"
},
  "geometry": {"coordinates":[-3.090819,55.935131],"type":"Point"}
}