{
  "type": "Feature",
  "properties": {
    "iso:country":"GB",
    "sg:address":"42 The Street, Beck Row",
    "sg:city":"Bury St Edmunds",
    "sg:classifiers":[
        {
            "category":"Autos & Motor Vehicles",
            "subcategory":"Automobile Sales",
            "type":"Retail Goods"
        }
    ],
    "sg:phone":"+44 1638 712752",
    "sg:postcode":"IP28 8AE",
    "sg:province":"Cambridgeshire",
    "sg:tags":[
        "car"
    ],
    "wof:name":"Mildenhall Car Sales",
    "wof:placetype":"venue"
},
  "geometry": {"coordinates":[0.509333,52.365288],"type":"Point"}
}