{
  "type": "Feature",
  "properties": {
    "addr:full":"Unit 1, Salisbury Rd, Rye Park Hoddesdon Essex EN11 0HY",
    "addr:housenumber":"unit 1",
    "addr:postcode":"en11 0hy",
    "addr:street":"Salisbury Rd",
    "iso:country":"GB",
    "sg:address":"Unit 1, Salisbury Rd, Rye Park",
    "sg:city":"Hoddesdon",
    "sg:classifiers":[
        {
            "category":"Retail",
            "subcategory":"Auto Repair",
            "type":"Services"
        }
    ],
    "sg:phone":"+44 1992 462775",
    "sg:postcode":"EN11 0HY",
    "sg:province":"Essex",
    "sg:tags":[
        "modification",
        "garage"
    ],
    "wof:name":"Salisbury Motors",
    "wof:placetype":"venue"
},
  "geometry": {"coordinates":[0.004857,51.7681922913],"type":"Point"}
}