{
  "type": "Feature",
  "properties": {
    "iso:country":"GB",
    "sg:address":"Bridge Road East",
    "sg:city":"Welwyn Garden City",
    "sg:classifiers":[
        {
            "category":"Autos & Motor Vehicles",
            "subcategory":"Fuel & Gas Station",
            "type":"Retail Goods"
        }
    ],
    "sg:phone":"+44 1707 338176",
    "sg:postcode":"AL7 1LE",
    "sg:province":"Hertfordshire",
    "sg:tags":[
        "hr",
        "petrol"
    ],
    "wof:name":"Eastbridge Service Station",
    "wof:placetype":"venue"
},
  "geometry": {"coordinates":[-0.198204,51.801987],"type":"Point"}
}