{
  "type": "Feature",
  "properties": {
    "iso:country":"GB",
    "sg:address":"57 High Street, Cleobury Mortimer",
    "sg:city":"Kidderminster",
    "sg:classifiers":[
        {
            "category":"Professional",
            "subcategory":"Business Services",
            "type":"Services"
        }
    ],
    "sg:phone":"+44 1299 271573",
    "sg:postcode":"DY14 8DN",
    "sg:province":"Shropshire",
    "sg:tags":[
        "bookmaker"
    ],
    "wof:name":"D Flowers",
    "wof:placetype":"venue"
},
  "geometry": {"coordinates":[-2.48496,52.378613],"type":"Point"}
}