{
  "type": "Feature",
  "properties": {
    "addr:full":"Unit 9, Diplocks Way Hailsham East Sussex BN27 3JF",
    "addr:housenumber":"unit 9",
    "addr:postcode":"bn27 3jf",
    "addr:street":"Diplocks Way",
    "iso:country":"GB",
    "sg:address":"Unit 9, Diplocks Way",
    "sg:city":"Hailsham",
    "sg:classifiers":[
        {
            "category":"Home & Garden",
            "subcategory":"Hardware",
            "type":"Retail Goods"
        }
    ],
    "sg:phone":"+44 1323 840377",
    "sg:postcode":"BN27 3JF",
    "sg:province":"East Sussex",
    "sg:tags":[
        "generator"
    ],
    "wof:name":"Gen Power Ltd.",
    "wof:placetype":"venue"
},
  "geometry": {"coordinates":[0.244859,50.861858],"type":"Point"}
}