{
  "type": "Feature",
  "properties": {
    "iso:country":"GB",
    "sg:address":"17c High Street",
    "sg:city":"Biggleswade",
    "sg:classifiers":[
        {
            "category":"Professional",
            "subcategory":"Accounting & Tax Preparation",
            "type":"Services"
        }
    ],
    "sg:phone":"+44 1462 487081",
    "sg:postcode":"SG18 0JE",
    "sg:province":"Bedfordshire",
    "sg:tags":[
        "accountant"
    ],
    "wof:name":"Graham T Viles & Co",
    "wof:placetype":"venue"
},
  "geometry": {"coordinates":[-0.265382,52.087021],"type":"Point"}
}