{
  "type": "Feature",
  "properties": {
    "iso:country":"GB",
    "sg:address":"Railway St, Ramsbottom",
    "sg:city":"Bury",
    "sg:classifiers":[
        {
            "category":"Personal",
            "type":"Services"
        }
    ],
    "sg:phone":"+44 1282 415526",
    "sg:postcode":"BL0 9AR",
    "sg:province":"Lancashire",
    "sg:tags":[
        "delivery"
    ],
    "wof:name":"T.N.T Sameday",
    "wof:placetype":"venue"
},
  "geometry": {"coordinates":[-2.3185989857,53.648475647],"type":"Point"}
}