{
  "type": "Feature",
  "properties": {
    "addr:full":"132 High Street Billericay Essex CM12 9DF",
    "addr:housenumber":"132",
    "addr:postcode":"cm12 9df",
    "addr:street":"High Street",
    "iso:country":"GB",
    "sg:address":"132 High Street",
    "sg:city":"Billericay",
    "sg:classifiers":[
        {
            "category":"Health Services",
            "subcategory":"Optometrist",
            "type":"Services"
        }
    ],
    "sg:phone":"+44 1277 631873",
    "sg:postcode":"CM12 9DF",
    "sg:province":"Essex",
    "sg:tags":[
        "optician"
    ],
    "wof:name":"Revelln J & Ptnrs",
    "wof:placetype":"venue"
},
  "geometry": {"coordinates":[0.4164220095,51.6229743958],"type":"Point"}
}