{
  "type": "Feature",
  "properties": {
    "addr:full":"107 Overbrook Road, Hardwicke Gloucester Gloucestershire GL2 4RZ",
    "addr:housenumber":"107",
    "addr:postcode":"gl2 4rz",
    "addr:street":"Overbrook Road",
    "iso:country":"GB",
    "sg:address":"107 Overbrook Road, Hardwicke",
    "sg:city":"Gloucester",
    "sg:classifiers":[
        {
            "category":"Professional",
            "subcategory":"Computer Services",
            "type":"Services"
        }
    ],
    "sg:phone":"+44 1452 728525",
    "sg:postcode":"GL2 4RZ",
    "sg:province":"Gloucestershire",
    "sg:tags":[
        "system",
        "software"
    ],
    "wof:name":"Meason Enterprises Ltd.",
    "wof:placetype":"venue"
},
  "geometry": {"coordinates":[-2.289984,51.819626],"type":"Point"}
}