{
  "type": "Feature",
  "properties": {
    "addr:full":"Unit 1/4 Tanyard Industrial Estate, Tanyard Road, Milnsbridge Huddersfield West Yorkshire HD3 4NB",
    "addr:housenumber":"unit 1 / 4;estate",
    "addr:postcode":"hd3 4nb",
    "addr:street":"Tanyard Industrial;Tanyard Road;West",
    "iso:country":"GB",
    "sg:address":"Unit 1/4 Tanyard Industrial Estate, Tanyard Road, Milnsbridge",
    "sg:city":"Huddersfield",
    "sg:classifiers":[
        {
            "category":"Shopping",
            "subcategory":"Stationery & Office Supplies",
            "type":"Retail Goods"
        }
    ],
    "sg:phone":"+44 1484 461060",
    "sg:postcode":"HD3 4NB",
    "sg:province":"West Yorkshire",
    "sg:tags":[
        "commercial"
    ],
    "wof:name":"Cleartask Ltd.",
    "wof:placetype":"venue"
},
  "geometry": {"coordinates":[-1.827694,53.637772],"type":"Point"}
}