{
  "type": "Feature",
  "properties": {
    "iso:country":"GB",
    "sg:address":"Nevilles Farm, Maynards Gn",
    "sg:city":"Heathfield",
    "sg:classifiers":[
        {
            "category":"Farming",
            "subcategory":"Livestock Farm",
            "type":"Manufacturing & Wholesale Goods"
        }
    ],
    "sg:phone":"+44 1435 862817",
    "sg:postcode":"TN21 0DJ",
    "sg:province":"East Sussex",
    "sg:tags":[
        "others"
    ],
    "wof:name":"Henry C Jarvis",
    "wof:placetype":"venue"
},
  "geometry": {"coordinates":[0.252349,50.971859],"type":"Point"}
}