{
  "type": "Feature",
  "properties": {
    "iso:country":"GB",
    "sg:address":"116 Hulme Hall Road, Cheadle Hulme",
    "sg:city":"Cheadle",
    "sg:classifiers":[
        {
            "category":"Building & Trades",
            "subcategory":"Construction",
            "type":"Services"
        }
    ],
    "sg:phone":"+44 161 486 0492",
    "sg:postcode":"SK8 6LQ",
    "sg:province":"Cheshire",
    "sg:tags":[
        "decorator",
        "painter"
    ],
    "wof:name":"Richard N Mathers",
    "wof:placetype":"venue"
},
  "geometry": {"coordinates":[-2.190362,53.366707],"type":"Point"}
}