{
  "type": "Feature",
  "properties": {
    "addr:full":"81 Kettering Road Northampton Northamptonshire NN1 4AW",
    "addr:housenumber":"81",
    "addr:postcode":"nn1 4aw",
    "addr:street":"Kettering Road",
    "iso:country":"GB",
    "sg:address":"81 Kettering Road",
    "sg:city":"Northampton",
    "sg:classifiers":[
        {
            "category":"Personal",
            "subcategory":"Tattoo Parlor",
            "type":"Services"
        }
    ],
    "sg:phone":"+44 1604 472929",
    "sg:postcode":"NN1 4AW",
    "sg:province":"Northamptonshire",
    "sg:tags":[
        "tattooing",
        "piercing"
    ],
    "wof:name":"Alternative Arts Tattoo & Piercing",
    "wof:placetype":"venue"
},
  "geometry": {"coordinates":[-0.886071,52.242191],"type":"Point"}
}