{
  "type": "Feature",
  "properties": {
    "addr:full":"The Stables, 53 Church Street, Theale Reading Berkshire RG7 4AW",
    "addr:housenumber":"53",
    "addr:postcode":"rg7 4aw",
    "addr:street":"Church Street",
    "iso:country":"GB",
    "sg:address":"The Stables, 53 Church Street, Theale",
    "sg:city":"Reading",
    "sg:classifiers":[
        {
            "category":"Shopping",
            "subcategory":"Stationery & Office Supplies",
            "type":"Retail Goods"
        }
    ],
    "sg:phone":"+44 118 930 5303",
    "sg:postcode":"RG7 4AW",
    "sg:province":"Berkshire",
    "sg:tags":[
        "printers'"
    ],
    "wof:name":"Computaform Thames Valley",
    "wof:placetype":"venue"
},
  "geometry": {"coordinates":[-1.07356,51.43557],"type":"Point"}
}