{
  "type": "Feature",
  "properties": {
    "addr:full":"Pentlepoir Saundersfoot Pembrokeshire SA69 9BJ",
    "addr:postcode":"sa69 9bj",
    "iso:country":"GB",
    "sg:address":"Pentlepoir",
    "sg:city":"Saundersfoot",
    "sg:classifiers":[
        {
            "category":"Government",
            "subcategory":"Post Office",
            "type":"Public Place"
        }
    ],
    "sg:phone":"+44 1834 812359",
    "sg:postcode":"SA69 9BJ",
    "sg:province":"Pembrokeshire",
    "wof:name":"Pentlepoir Post Office",
    "wof:placetype":"venue"
},
  "geometry": {"coordinates":[-4.6995558739,51.7102050781],"type":"Point"}
}