{
  "type": "Feature",
  "properties": {
    "iso:country":"GB",
    "sg:address":"14 Mannicotts",
    "sg:city":"Welwyn Garden City",
    "sg:classifiers":[
        {
            "category":"Banks & Credit Unions",
            "subcategory":"Investment Brokerage",
            "type":"Services"
        },
        {
            "category":"Professional",
            "subcategory":"Credit Reporting & Collection",
            "type":"Services"
        }
    ],
    "sg:phone":"+44 1438 712345",
    "sg:postcode":"AL8 7BW",
    "sg:province":"Hertfordshire",
    "sg:tags":[
        "adviser",
        "pension",
        "consultant"
    ],
    "wof:name":"Specialist Pension Services Ltd.",
    "wof:placetype":"venue"
},
  "geometry": {"coordinates":[-0.220158,51.801605],"type":"Point"}
}