{
  "type": "Feature",
  "properties": {
    "addr:full":"37 Molyneux St London Greater London W1H 5HW",
    "addr:housenumber":"37",
    "addr:postcode":"w1h 5hw",
    "addr:street":"Molyneux St",
    "iso:country":"GB",
    "sg:address":"37 Molyneux St",
    "sg:city":"London",
    "sg:classifiers":[
        {
            "category":"Train Station",
            "subcategory":"Light Rail",
            "type":"Transportation"
        }
    ],
    "sg:postcode":"W1H 5HW",
    "sg:province":"Greater London",
    "sg:tags":[
        "arbitrator"
    ],
    "wof:name":"Goodall,Francis Cruice,",
    "wof:placetype":"venue"
},
  "geometry": {"coordinates":[-0.1643709987,51.5181541443],"type":"Point"}
}