{
  "type": "Feature",
  "properties": {
    "iso:country":"GB",
    "sg:address":"42 King Edward Road, Walthamstow",
    "sg:city":"London",
    "sg:classifiers":[
        {
            "category":"Health Services",
            "subcategory":"Health Practitioner",
            "type":"Services"
        }
    ],
    "sg:postcode":"E17 6HZ",
    "sg:province":"Greater London",
    "sg:tags":[
        "homoeopathic"
    ],
    "wof:name":"Anita Wicks",
    "wof:placetype":"venue"
},
  "geometry": {"coordinates":[-0.035464,51.588779],"type":"Point"}
}