{
  "type": "Feature",
  "properties": {
    "iso:country":"GB",
    "sg:address":"68 Bridge Street",
    "sg:city":"Banbury",
    "sg:classifiers":[
        {
            "category":"Fast Food",
            "type":"Food & Drink"
        }
    ],
    "sg:phone":"+44 1295 250857",
    "sg:postcode":"OX16 5QF",
    "sg:province":"Oxfordshire",
    "sg:tags":[
        "away",
        "meal",
        "outlet",
        "take"
    ],
    "wof:name":"Welcome",
    "wof:placetype":"venue"
},
  "geometry": {"coordinates":[-1.330552,52.061634],"type":"Point"}
}