{
  "type": "Feature",
  "properties": {
    "addr:full":"135 Bdwy Didcot Oxfordshire OX11 8RQ",
    "addr:housenumber":"135",
    "addr:postcode":"ox11 8rq",
    "addr:street":"Bdwy Didcot",
    "iso:country":"GB",
    "sg:address":"135 Bdwy",
    "sg:city":"Didcot",
    "sg:classifiers":[
        {
            "category":"Real Estate",
            "subcategory":"Real Estate Agent",
            "type":"Services"
        }
    ],
    "sg:phone":"+44 1235 812333",
    "sg:postcode":"OX11 8RQ",
    "sg:province":"Oxfordshire",
    "wof:name":"Allen & Harris",
    "wof:placetype":"venue"
},
  "geometry": {"coordinates":[-1.2406580448,51.6060943604],"type":"Point"}
}