{
  "type": "Feature",
  "properties": {
    "addr:full":"Northfield Industrial Estate, North Drive Rotherham South Yorkshire S60 1QF",
    "addr:postcode":"s60 1qf",
    "addr:street":"Northfield Industrial Estate North Drive",
    "iso:country":"GB",
    "sg:address":"Northfield Industrial Estate, North Drive",
    "sg:city":"Rotherham",
    "sg:classifiers":[
        {
            "category":"Professional",
            "subcategory":"Business Services",
            "type":"Services"
        }
    ],
    "sg:phone":"+44 1709 836713",
    "sg:postcode":"S60 1QF",
    "sg:province":"South Yorkshire",
    "sg:tags":[
        "distribution"
    ],
    "wof:name":"Murison Distribution (Holdings) Ltd.",
    "wof:placetype":"venue"
},
  "geometry": {"coordinates":[-1.3542430401,53.4298744202],"type":"Point"}
}