{
  "type": "Feature",
  "properties": {
    "addr:full":"Strathlene Surgery, Black Isle Road Muir Of Ord Highland IV6 7RR",
    "addr:postcode":"iv6 7rr",
    "addr:street":"Black Isle Road",
    "iso:country":"GB",
    "sg:address":"Strathlene Surgery, Black Isle Road",
    "sg:city":"Muir Of Ord",
    "sg:classifiers":[
        {
            "category":"Health Services",
            "subcategory":"Doctor",
            "type":"Services"
        },
        {
            "category":"Health Services",
            "subcategory":"Clinic",
            "type":"Services"
        }
    ],
    "sg:postcode":"IV6 7RR",
    "sg:province":"Highland",
    "sg:tags":[
        "nh",
        "practitioners"
    ],
    "wof:name":"Strathlene Surgery",
    "wof:placetype":"venue"
},
  "geometry": {"coordinates":[-4.4585990906,57.5176887512],"type":"Point"}
}