{
  "type": "Feature",
  "properties": {
    "iso:country":"GB",
    "sg:address":"32 Raylor Centre, James Street",
    "sg:city":"York",
    "sg:classifiers":[
        {
            "category":"Retail",
            "subcategory":"Auto Repair",
            "type":"Services"
        }
    ],
    "sg:phone":"+44 1904 431101",
    "sg:postcode":"YO10 3DW",
    "sg:province":"North Yorkshire",
    "sg:tags":[
        "modification",
        "garage"
    ],
    "wof:name":"Garage Services",
    "wof:placetype":"venue"
},
  "geometry": {"coordinates":[-1.0661400557,53.9567108154],"type":"Point"}
}