{
  "type": "Feature",
  "properties": {
    "iso:country":"GB",
    "sg:address":"20 Borthyn",
    "sg:city":"Ruthin",
    "sg:classifiers":[
        {
            "category":"Food & Beverages",
            "subcategory":"Meat & Fish",
            "type":"Retail Goods"
        },
        {
            "category":"Food & Beverages",
            "subcategory":"Groceries & Convenience Stores",
            "type":"Retail Goods"
        }
    ],
    "sg:phone":"+44 1824 702039",
    "sg:postcode":"LL15 1NU",
    "sg:province":"Denbighshire",
    "sg:tags":[
        "shop",
        "chip"
    ],
    "wof:name":"I MACNAB",
    "wof:placetype":"venue"
},
  "geometry": {"coordinates":[-3.316637,53.113564],"type":"Point"}
}