{
  "type": "Feature",
  "properties": {
    "addr:full":"20 Quarry Road Irvine North Ayrshire KA12 0TH",
    "addr:housenumber":"20",
    "addr:postcode":"ka12 0th",
    "addr:street":"Quarry Road",
    "iso:country":"GB",
    "sg:address":"20 Quarry Road",
    "sg:city":"Irvine",
    "sg:classifiers":[
        {
            "category":"Fast Food",
            "type":"Food & Drink"
        }
    ],
    "sg:phone":"+44 1294 311261",
    "sg:postcode":"KA12 0TH",
    "sg:province":"North Ayrshire",
    "sg:tags":[
        "away",
        "take"
    ],
    "wof:name":"Alexander Dunlop",
    "wof:placetype":"venue"
},
  "geometry": {"coordinates":[-4.666368,55.619087],"type":"Point"}
}