{
  "type": "Feature",
  "properties": {
    "addr:full":"2 Blything Court, Highley Bridgnorth Shropshire WV16 6JQ",
    "addr:housenumber":"2",
    "addr:postcode":"wv16 6jq",
    "addr:street":"Blything Court",
    "iso:country":"GB",
    "sg:address":"2 Blything Court, Highley",
    "sg:city":"Bridgnorth",
    "sg:classifiers":[
        {
            "category":"Building & Trades",
            "subcategory":"Landscaping Services",
            "type":"Services"
        }
    ],
    "sg:phone":"+44 1746 861246",
    "sg:postcode":"WV16 6JQ",
    "sg:province":"Shropshire",
    "sg:tags":[
        "forestry",
        "tree"
    ],
    "wof:name":"P J Hughes",
    "wof:placetype":"venue"
},
  "geometry": {"coordinates":[-2.384393,52.449841],"type":"Point"}
}