{
  "type": "Feature",
  "properties": {
    "addr:full":"Ashington Manor Farm Yeovil Dorset BA22 8ED",
    "addr:postcode":"ba22 8ed",
    "addr:street":"Dorset",
    "iso:country":"GB",
    "sg:address":"Ashington Manor Farm",
    "sg:city":"Yeovil",
    "sg:classifiers":[
        {
            "category":"Farming",
            "subcategory":"Livestock Farm",
            "type":"Manufacturing & Wholesale Goods"
        }
    ],
    "sg:postcode":"BA22 8ED",
    "sg:province":"Dorset",
    "sg:tags":[
        "others"
    ],
    "wof:name":"C & M Hawkins",
    "wof:placetype":"venue"
},
  "geometry": {"coordinates":[-2.6250329018,50.9871101379],"type":"Point"}
}