{
  "type": "Feature",
  "properties": {
    "addr:full":"2 Madison Vean Hayle Cornwall TR27 4ES",
    "addr:housenumber":"2",
    "addr:postcode":"tr27 4es",
    "iso:country":"GB",
    "sg:address":"2 Madison Vean",
    "sg:city":"Hayle",
    "sg:classifiers":[
        {
            "category":"Shopping",
            "subcategory":"Catalog Store",
            "type":"Retail Goods"
        }
    ],
    "sg:phone":"+44 1736 754437",
    "sg:postcode":"TR27 4ES",
    "sg:province":"Cornwall",
    "sg:tags":[
        "mail",
        "order"
    ],
    "wof:name":"Canvex",
    "wof:placetype":"venue"
},
  "geometry": {"coordinates":[-5.404407,50.193836],"type":"Point"}
}