{
  "type": "Feature",
  "properties": {
    "addr:full":"Riverside, Bourton-on-the-watermitcham Cheltenham Gloucestershire GL54 2BP",
    "addr:postcode":"gl54 2bp",
    "iso:country":"GB",
    "sg:address":"Riverside, Bourton-on-the-watermitcham",
    "sg:city":"Cheltenham",
    "sg:classifiers":[
        {
            "category":"Cafe",
            "type":"Food & Drink"
        }
    ],
    "sg:phone":"+44 1451 820803",
    "sg:postcode":"GL54 2BP",
    "sg:province":"Gloucestershire",
    "sg:tags":[
        "tea",
        "room"
    ],
    "wof:name":"Riverside Coffee House",
    "wof:placetype":"venue"
},
  "geometry": {"coordinates":[-1.760916,51.88678],"type":"Point"}
}