{
  "type": "Feature",
  "properties": {
    "addr:full":"5 Montgomery Square, Wath Upon Dearne Rotherham South Yorkshire S63 7RZ",
    "addr:housenumber":"5",
    "addr:postcode":"s63 7rz",
    "addr:street":"Montgomery Square Wath",
    "iso:country":"GB",
    "sg:address":"5 Montgomery Square, Wath Upon Dearne",
    "sg:city":"Rotherham",
    "sg:classifiers":[
        {
            "category":"Education",
            "subcategory":"Dance Studio",
            "type":"Public Place"
        }
    ],
    "sg:phone":"+44 1709 879235",
    "sg:postcode":"S63 7RZ",
    "sg:province":"South Yorkshire",
    "sg:tags":[
        "toning"
    ],
    "wof:name":"Harleys",
    "wof:placetype":"venue"
},
  "geometry": {"coordinates":[-1.3463619947,53.5032234192],"type":"Point"}
}