{
  "type": "Feature",
  "properties": {
    "addr:full":"42 Hockerill Street Bishops Stortford Essex CM23 2DW",
    "addr:housenumber":"42",
    "addr:postcode":"cm23 2dw",
    "addr:street":"Hockerill Street",
    "iso:country":"GB",
    "sg:address":"42 Hockerill Street",
    "sg:city":"Bishops Stortford",
    "sg:classifiers":[
        {
            "category":"Building & Trades",
            "subcategory":"Landscaping Services",
            "type":"Services"
        }
    ],
    "sg:phone":"+44 1279 504024",
    "sg:postcode":"CM23 2DW",
    "sg:province":"Essex",
    "sg:tags":[
        "pond",
        "aquarium"
    ],
    "wof:name":"Aquatic Fanatics",
    "wof:placetype":"venue"
},
  "geometry": {"coordinates":[0.1659359932,51.8696975708],"type":"Point"}
}