{
  "type": "Feature",
  "properties": {
    "iso:country":"GB",
    "sg:address":"112/114 London Road",
    "sg:city":"Southend-on-sea",
    "sg:classifiers":[
        {
            "category":"Home & Garden",
            "subcategory":"Furniture",
            "type":"Retail Goods"
        }
    ],
    "sg:phone":"+44 1702 331000",
    "sg:postcode":"SS1 1PQ",
    "sg:province":"Essex",
    "wof:name":"H West Furnishers Ltd.",
    "wof:placetype":"venue"
},
  "geometry": {"coordinates":[0.7056829929,51.5402412415],"type":"Point"}
}