{
  "type": "Feature",
  "properties": {
    "addr:full":"Unit 2, O.p.m. House Nottingham Nottinghamshire NG5 2LB",
    "addr:housenumber":"unit 2 o.p.m. house",
    "addr:postcode":"ng5 2lb",
    "iso:country":"GB",
    "sg:address":"Unit 2, O.p.m. House",
    "sg:city":"Nottingham",
    "sg:classifiers":[
        {
            "category":"Health Services",
            "subcategory":"Dentist",
            "type":"Services"
        }
    ],
    "sg:phone":"+44 115 969 2808",
    "sg:postcode":"NG5 2LB",
    "sg:province":"Nottinghamshire",
    "sg:tags":[
        "technician",
        "instrument",
        "dental"
    ],
    "wof:name":"Bloomfield Dental Laboratories Limited",
    "wof:placetype":"venue"
},
  "geometry": {"coordinates":[-1.15099895,52.9743347168],"type":"Point"}
}