{
  "type": "Feature",
  "properties": {
    "addr:full":"10 Dolphin Lodge, Grand Avenue Worthing West Sussex BN11 5AL",
    "addr:housenumber":"10",
    "addr:postcode":"bn11 5al",
    "addr:street":"Grand Avenue",
    "iso:country":"GB",
    "sg:address":"10 Dolphin Lodge, Grand Avenue",
    "sg:city":"Worthing",
    "sg:classifiers":[
        {
            "category":"Shopping",
            "subcategory":"Hobbies, Toys, & Games",
            "type":"Retail Goods"
        }
    ],
    "sg:postcode":"BN11 5AL",
    "sg:province":"West Sussex",
    "sg:tags":[
        "collectors'",
        "item"
    ],
    "wof:name":"Yeomanry Miniatures",
    "wof:placetype":"venue"
},
  "geometry": {"coordinates":[-0.3754239976,50.8136253357],"type":"Point"}
}