{
  "type": "Feature",
  "properties": {
    "addr:full":"Colebrook London Road, Watersfield Pulborough West Sussex RH20 1ND",
    "addr:postcode":"rh20 1nd",
    "addr:street":"Colebrook London Road Watersfield",
    "iso:country":"GB",
    "sg:address":"Colebrook London Road, Watersfield",
    "sg:city":"Pulborough",
    "sg:classifiers":[
        {
            "category":"Professional",
            "subcategory":"Computer Services",
            "type":"Services"
        }
    ],
    "sg:phone":"+44 1798 831020",
    "sg:postcode":"RH20 1ND",
    "sg:province":"West Sussex",
    "sg:tags":[
        "development",
        "system",
        "software"
    ],
    "wof:name":"Wessex Software Systems",
    "wof:placetype":"venue"
},
  "geometry": {"coordinates":[-0.5555850267,50.9344787598],"type":"Point"}
}