{
  "type": "Feature",
  "properties": {
    "iso:country":"GB",
    "sg:address":"Church Street, Golcar",
    "sg:city":"Huddersfield",
    "sg:classifiers":[
        {
            "category":"Place Of Worship",
            "type":"Public Place"
        }
    ],
    "sg:phone":"+44 1484 654647",
    "sg:postcode":"HD7 4PX",
    "sg:province":"West Yorkshire",
    "wof:name":"John The Evangelist C Of E St",
    "wof:placetype":"venue"
},
  "geometry": {"coordinates":[-1.8399139643,53.6400985718],"type":"Point"}
}