{
  "type": "Feature",
  "properties": {
    "addr:full":"Burk Road Industrial Estate Totnes Devon TQ9 5XL",
    "addr:postcode":"tq9 5xl",
    "addr:street":"Burk Road Industrial Estate",
    "iso:country":"GB",
    "sg:address":"Burk Road Industrial Estate",
    "sg:city":"Totnes",
    "sg:classifiers":[
        {
            "category":"Home & Garden",
            "subcategory":"Hardware",
            "type":"Retail Goods"
        }
    ],
    "sg:phone":"+44 1803 866464",
    "sg:postcode":"TQ9 5XL",
    "sg:province":"Devon",
    "sg:tags":[
        "tubing",
        "fitting",
        "hose",
        "diy"
    ],
    "wof:name":"Exact Engineering (Hose & Fittings) Co. Ltd.",
    "wof:placetype":"venue"
},
  "geometry": {"coordinates":[-3.6823899746,50.4349937439],"type":"Point"}
}