{
  "type": "Feature",
  "properties": {
    "addr:full":"101 Castle St Bolton Lancashire BL2 1JP",
    "addr:housenumber":"101",
    "addr:postcode":"bl2 1jp",
    "addr:street":"Castle St",
    "iso:country":"GB",
    "sg:address":"101 Castle St",
    "sg:city":"Bolton",
    "sg:classifiers":[
        {
            "category":"Social Services",
            "subcategory":"Adult Care",
            "type":"Services"
        }
    ],
    "sg:phone":"+44 1204 396626",
    "sg:postcode":"BL2 1JP",
    "sg:province":"Lancashire",
    "sg:tags":[
        "day",
        "centre"
    ],
    "wof:name":"Castle Street Day Centre",
    "wof:placetype":"venue"
},
  "geometry": {"coordinates":[-2.415398,53.577354],"type":"Point"}
}