{
  "type": "Feature",
  "properties": {
    "addr:full":"Unit B8 Hrs Ho, Hrs Business Park, Garretts Green La Birmingham West Midlands B33 0UE",
    "addr:postcode":"b33 0ue",
    "addr:street":"Business Park Garretts Green La Birmingham",
    "iso:country":"GB",
    "sg:address":"Unit B8 Hrs Ho, Hrs Business Park, Garretts Green La",
    "sg:city":"Birmingham",
    "sg:classifiers":[
        {
            "category":"Sports & Exercise",
            "subcategory":"Skate Park",
            "type":"Entertainment"
        }
    ],
    "sg:phone":"+44 121 785 2454",
    "sg:postcode":"B33 0UE",
    "sg:province":"West Midlands",
    "sg:tags":[
        "equipment",
        "grinding"
    ],
    "wof:name":"Ghiringhelli Grinding Ltd",
    "wof:placetype":"venue"
},
  "geometry": {"coordinates":[-1.769896,52.475517],"type":"Point"}
}