{
  "type": "Feature",
  "properties": {
    "addr:full":"64 Fowler Street South Shields Tyne and Wear NE33 1PG",
    "addr:housenumber":"64",
    "addr:postcode":"ne33 1pg",
    "addr:street":"Fowler Street",
    "iso:country":"GB",
    "sg:address":"64 Fowler Street",
    "sg:city":"South Shields",
    "sg:classifiers":[
        {
            "category":"Retail",
            "subcategory":"Photofinishing",
            "type":"Services"
        }
    ],
    "sg:postcode":"NE33 1PG",
    "sg:province":"Tyne and Wear",
    "sg:tags":[
        "photographic",
        "processor"
    ],
    "wof:name":"Photo-Fast",
    "wof:placetype":"venue"
},
  "geometry": {"coordinates":[-1.431056,54.997215],"type":"Point"}
}