{
  "type": "Feature",
  "properties": {
    "iso:country":"GB",
    "sg:address":"Bedbury Lane",
    "sg:city":"Freshwater",
    "sg:classifiers":[
        {
            "category":"Farming",
            "subcategory":"Livestock Farm",
            "type":"Manufacturing & Wholesale Goods"
        },
        {
            "category":"Farming",
            "subcategory":"Farm",
            "type":"Manufacturing & Wholesale Goods"
        }
    ],
    "sg:phone":"+44 1983 752566",
    "sg:postcode":"PO40 9PB",
    "sg:province":"Isle of Wight",
    "sg:tags":[
        "mixed",
        "crop",
        "others"
    ],
    "wof:name":"S J & A W Fidler",
    "wof:placetype":"venue"
},
  "geometry": {"coordinates":[-1.521918,50.675709],"type":"Point"}
}