{
  "type": "Feature",
  "properties": {
    "addr:full":"Apsley House, 35 Waterloo Street Birmingham West Midlands B2 5TJ",
    "addr:housenumber":"35",
    "addr:postcode":"5tj",
    "addr:street":"Waterloo Street",
    "iso:country":"GB",
    "sg:address":"Apsley House, 35 Waterloo Street",
    "sg:city":"Birmingham",
    "sg:classifiers":[
        {
            "category":"Professional",
            "subcategory":"Research",
            "type":"Services"
        }
    ],
    "sg:phone":"+44 121 233 3991",
    "sg:postcode":"B2 5TJ",
    "sg:province":"West Midlands",
    "sg:tags":[
        "actuary"
    ],
    "wof:name":"Watson Wyatt Partners",
    "wof:placetype":"venue"
},
  "geometry": {"coordinates":[-1.901061058,52.4802131653],"type":"Point"}
}