{
  "type": "Feature",
  "properties": {
    "iso:country":"GB",
    "sg:address":"Edgebourough House, Upper Edgeborough Road",
    "sg:city":"Guildford",
    "sg:classifiers":[
        {
            "category":"Health Services",
            "subcategory":"Nursing And Care Facility",
            "type":"Services"
        }
    ],
    "sg:phone":"+44 1483 442800",
    "sg:postcode":"GU1 2BJ",
    "sg:province":"Surrey",
    "sg:tags":[
        "home"
    ],
    "wof:name":"B U P A Care Homes",
    "wof:placetype":"venue"
},
  "geometry": {"coordinates":[-0.5556139946,51.2365684509],"type":"Point"}
}