{
  "type": "Feature",
  "properties": {
    "addr:full":"534a Loughborough Road, Birstall Leicester Leicestershire LE4 3EG",
    "addr:housenumber":"534a",
    "addr:postcode":"le4 3eg",
    "addr:street":"Loughborough Road",
    "iso:country":"GB",
    "sg:address":"534a Loughborough Road, Birstall",
    "sg:city":"Leicester",
    "sg:classifiers":[
        {
            "category":"Health Services",
            "subcategory":"Dentist",
            "type":"Services"
        }
    ],
    "sg:phone":"+44 116 267 4254",
    "sg:postcode":"LE4 3EG",
    "sg:province":"Leicestershire",
    "wof:name":"THE FIRST DENTAL PRACTICE",
    "wof:placetype":"venue"
},
  "geometry": {"coordinates":[-1.125764966,52.6801452637],"type":"Point"}
}