{
  "type": "Feature",
  "properties": {
    "addr:full":"23 Basildon Road Basildon Essex SS15 5SF",
    "addr:housenumber":"23",
    "addr:postcode":"ss15 5sf",
    "addr:street":"Basildon Road",
    "iso:country":"GB",
    "sg:address":"23 Basildon Road",
    "sg:city":"Basildon",
    "sg:classifiers":[
        {
            "category":"Building & Trades",
            "subcategory":"Construction",
            "type":"Services"
        }
    ],
    "sg:phone":"+44 1268 526208",
    "sg:postcode":"SS15 5SF",
    "sg:province":"Essex",
    "sg:tags":[
        "builder"
    ],
    "wof:name":"Right Way Plastering Ltd.",
    "wof:placetype":"venue"
},
  "geometry": {"coordinates":[0.427171,51.578983],"type":"Point"}
}