{
  "type": "Feature",
  "properties": {
    "addr:full":"Unit 5 Concord House, Lime Street Liverpool Merseyside L1 1NY",
    "addr:housenumber":"unit 5",
    "addr:postcode":"l1 1ny",
    "addr:street":"Concord;Lime Street",
    "iso:country":"GB",
    "sg:address":"Unit 5 Concord House, Lime Street",
    "sg:city":"Liverpool",
    "sg:classifiers":[
        {
            "category":"Shopping",
            "subcategory":"Luggage & Leather Goods",
            "type":"Retail Goods"
        }
    ],
    "sg:phone":"+44 151 709 3543",
    "sg:postcode":"L1 1NY",
    "sg:province":"Merseyside",
    "sg:tags":[
        "shop",
        "leathergoods"
    ],
    "wof:name":"International Leather Store",
    "wof:placetype":"venue"
},
  "geometry": {"coordinates":[-2.9788379669,53.4060592651],"type":"Point"}
}