{
  "type": "Feature",
  "properties": {
    "addr:full":"Bede House, St Cuthberts Way Newton Aycliffe Durham DL5 6DJ",
    "addr:postcode":"dl5 6dj",
    "addr:street":"St Cuthberts Way",
    "iso:country":"GB",
    "sg:address":"Bede House, St Cuthberts Way",
    "sg:city":"Newton Aycliffe",
    "sg:classifiers":[
        {
            "category":"Education",
            "subcategory":"Special Training",
            "type":"Public Place"
        }
    ],
    "sg:phone":"+44 1325 320022",
    "sg:postcode":"DL5 6DJ",
    "sg:province":"Durham",
    "sg:tags":[
        "product",
        "centre"
    ],
    "wof:name":"R H Associates",
    "wof:placetype":"venue"
},
  "geometry": {"coordinates":[-1.569329,54.610458],"type":"Point"}
}