{
  "type": "Feature",
  "properties": {
    "addr:full":"100 Vauxhall Walk Lambeth Greater London SE11 5EL",
    "addr:housenumber":"100",
    "addr:postcode":"se11 5el",
    "addr:street":"Vauxhall Walk",
    "iso:country":"GB",
    "sg:address":"100 Vauxhall Walk",
    "sg:city":"Lambeth",
    "sg:classifiers":[
        {
            "category":"Professional",
            "subcategory":"Art Services",
            "type":"Services"
        }
    ],
    "sg:phone":"+44 20 7735 5063",
    "sg:postcode":"SE11 5EL",
    "sg:province":"Greater London",
    "sg:tags":[
        "framing"
    ],
    "wof:name":"Fox & Sharples",
    "wof:placetype":"venue"
},
  "geometry": {"coordinates":[-0.120692,51.489052],"type":"Point"}
}