{
  "type": "Feature",
  "properties": {
    "iso:country":"GB",
    "sg:address":"Futures House, Clayton Road",
    "sg:city":"Hayes",
    "sg:classifiers":[
        {
            "category":"Education",
            "subcategory":"Special Training",
            "type":"Public Place"
        }
    ],
    "sg:phone":"+44 20 8756 1516",
    "sg:postcode":"UB3 1BQ",
    "sg:province":"Greater London",
    "sg:tags":[
        "product",
        "centre"
    ],
    "wof:name":"Middlesex Training Consortium",
    "wof:placetype":"venue"
},
  "geometry": {"coordinates":[-0.424821,51.505325],"type":"Point"}
}