{
  "type": "Feature",
  "properties": {
    "addr:full":"Canal Street Barnsley South Yorkshire S71 1LJ",
    "addr:postcode":"s71 1lj",
    "addr:street":"Canal Street;Yorkshire",
    "iso:country":"GB",
    "sg:address":"Canal Street",
    "sg:city":"Barnsley",
    "sg:classifiers":[
        {
            "category":"Bars & Pubs",
            "type":"Food & Drink"
        },
        {
            "category":"Travel",
            "subcategory":"Hotels & Motels",
            "type":"Entertainment"
        }
    ],
    "sg:phone":"+44 1226 289813",
    "sg:postcode":"S71 1LJ",
    "sg:province":"South Yorkshire",
    "sg:tags":[
        "pubs",
        "house",
        "inn",
        "guest"
    ],
    "wof:name":"Keel Inn Motel",
    "wof:placetype":"venue"
},
  "geometry": {"coordinates":[-1.474998,53.559479],"type":"Point"}
}