{
  "type": "Feature",
  "properties": {
    "addr:full":"5a Brackley Street, Farnworth Bolton Lancashire BL4 9DS",
    "addr:housenumber":"5a",
    "addr:postcode":"bl4 9ds",
    "addr:street":"Brackley Street",
    "iso:country":"GB",
    "sg:address":"5a Brackley Street, Farnworth",
    "sg:city":"Bolton",
    "sg:classifiers":[
        {
            "category":"Shopping",
            "subcategory":"Department Store",
            "type":"Retail Goods"
        },
        {
            "category":"Shopping",
            "subcategory":"Gifts & Souvenirs",
            "type":"Retail Goods"
        }
    ],
    "sg:phone":"+44 1204 701955",
    "sg:postcode":"BL4 9DS",
    "sg:province":"Lancashire",
    "sg:tags":[
        "poster",
        "card"
    ],
    "wof:name":"Susan O'Connell",
    "wof:placetype":"venue"
},
  "geometry": {"coordinates":[-2.3932180405,53.5481948853],"type":"Point"}
}