{
  "type": "Feature",
  "properties": {
    "addr:full":"Barley House, Oakfield Grove Bristol City of Bristol BS8 2BN",
    "addr:postcode":"bs8 2bn",
    "addr:street":"Oakfield Grove",
    "iso:country":"GB",
    "sg:address":"Barley House, Oakfield Grove",
    "sg:city":"Bristol",
    "sg:classifiers":[
        {
            "category":"Shopping",
            "type":"Retail Goods"
        }
    ],
    "sg:phone":"+44 1327 857733",
    "sg:postcode":"BS8 2BN",
    "sg:province":"City of Bristol",
    "sg:tags":[
        "part",
        "accessory"
    ],
    "wof:name":"Silverstone Proparts Ltd",
    "wof:placetype":"venue"
},
  "geometry": {"coordinates":[-2.6123600006,51.4597015381],"type":"Point"}
}