{
  "type": "Feature",
  "properties": {
    "addr:full":"Penygroes Industrial Estate, Penygroes Caernarfon Gwynedd LL54 6DB",
    "addr:postcode":"ll54 6db",
    "addr:street":"Estate Penygroes",
    "iso:country":"GB",
    "sg:address":"Penygroes Industrial Estate, Penygroes",
    "sg:city":"Caernarfon",
    "sg:classifiers":[
        {
            "category":"Utilities",
            "subcategory":"Refuse",
            "type":"Services"
        }
    ],
    "sg:phone":"+44 1286 881185",
    "sg:postcode":"LL54 6DB",
    "sg:province":"Gwynedd",
    "sg:tags":[
        "skip",
        "hire"
    ],
    "wof:name":"Arfon Skips Ltd",
    "wof:placetype":"venue"
},
  "geometry": {"coordinates":[-4.285762,53.048351],"type":"Point"}
}