{
  "type": "Feature",
  "properties": {
    "addr:full":"1 The Pound Field Llantwit Major The Vale of Glamorgan CF61 1DL",
    "addr:housenumber":"1",
    "addr:postcode":"cf61 1dl",
    "addr:street":"The Pound Field;The",
    "iso:country":"GB",
    "sg:address":"1 The Pound Field",
    "sg:city":"Llantwit Major",
    "sg:classifiers":[
        {
            "category":"Home & Garden",
            "subcategory":"Furniture",
            "type":"Retail Goods"
        }
    ],
    "sg:postcode":"CF61 1DL",
    "sg:province":"The Vale of Glamorgan",
    "wof:name":"Mavin,Pamela,",
    "wof:placetype":"venue"
},
  "geometry": {"coordinates":[-3.488492,51.41016],"type":"Point"}
}