{
  "type": "Feature",
  "properties": {
    "addr:full":"Glutton Bridge Cottage, Glutton Bridge Buxton Derbyshire SK17 0EN",
    "addr:postcode":"sk17 0en",
    "addr:street":"Glutton Bridge",
    "iso:country":"GB",
    "sg:address":"Glutton Bridge Cottage, Glutton Bridge",
    "sg:city":"Buxton",
    "sg:classifiers":[
        {
            "category":"Retail",
            "subcategory":"Auto Repair",
            "type":"Services"
        }
    ],
    "sg:phone":"+44 1298 83519",
    "sg:postcode":"SK17 0EN",
    "sg:province":"Derbyshire",
    "sg:tags":[
        "modification",
        "garage"
    ],
    "wof:name":"George Garage Ltd.",
    "wof:placetype":"venue"
},
  "geometry": {"coordinates":[-1.8763619661,53.1956138611],"type":"Point"}
}