{
  "type": "Feature",
  "properties": {
    "iso:country":"GB",
    "sg:address":"136 Bolton Road, Darwin",
    "sg:city":"Blackburn",
    "sg:classifiers":[
        {
            "category":"Sports & Exercise",
            "subcategory":"Gym",
            "type":"Entertainment"
        }
    ],
    "sg:phone":"+44 1254 708838",
    "sg:postcode":"BB3 1BZ",
    "sg:province":"Lancashire",
    "sg:tags":[
        "fitness",
        "health",
        "centre"
    ],
    "wof:name":"Power Zone Gym",
    "wof:placetype":"venue"
},
  "geometry": {"coordinates":[-2.46664,53.691368],"type":"Point"}
}