{
  "type": "Feature",
  "properties": {
    "iso:country":"GB",
    "sg:address":"315 Heeley Road",
    "sg:city":"Birmingham",
    "sg:classifiers":[
        {
            "category":"Shopping",
            "subcategory":"Thrift Store",
            "type":"Retail Goods"
        }
    ],
    "sg:phone":"+44 121 472 1500",
    "sg:postcode":"B29 7DA",
    "sg:province":"West Midlands",
    "sg:tags":[
        "shop",
        "charity"
    ],
    "wof:name":"St Mary's Hospice Charity Shop",
    "wof:placetype":"venue"
},
  "geometry": {"coordinates":[-1.929353,52.437119],"type":"Point"}
}