{
  "type": "Feature",
  "properties": {
    "addr:full":"Sinderland Road, Broadheath Altrincham Cheshire WA14 5HQ",
    "addr:postcode":"wa14 5hq",
    "addr:street":"Sinderland Road",
    "iso:country":"GB",
    "sg:address":"Sinderland Road, Broadheath",
    "sg:city":"Altrincham",
    "sg:classifiers":[
        {
            "category":"Wholesale",
            "subcategory":"Scrap",
            "type":"Manufacturing & Wholesale Goods"
        }
    ],
    "sg:phone":"+44 161 941 4238",
    "sg:postcode":"WA14 5HQ",
    "sg:province":"Cheshire",
    "sg:tags":[
        "waste",
        "metal"
    ],
    "wof:name":"Altrincham Civic Amenities Compound",
    "wof:placetype":"venue"
},
  "geometry": {"coordinates":[-2.3525509834,53.400390625],"type":"Point"}
}