{
  "type": "Feature",
  "properties": {
    "iso:country":"GB",
    "sg:address":"Hollow Lane, Cheddleton",
    "sg:city":"Leek",
    "sg:classifiers":[
        {
            "category":"Education",
            "subcategory":"School",
            "type":"Public Place"
        }
    ],
    "sg:phone":"+44 1538 360435",
    "sg:postcode":"ST13 7HP",
    "sg:province":"Staffordshire",
    "sg:tags":[
        "local",
        "authority"
    ],
    "wof:name":"St Edwards First School",
    "wof:placetype":"venue"
},
  "geometry": {"coordinates":[-2.043203,53.064342],"type":"Point"}
}