{
  "type": "Feature",
  "properties": {
    "addr:full":"1 Stormont Rd Hitchin Bedfordshire SG5 1SJ",
    "addr:housenumber":"1",
    "addr:postcode":"sg5 1sj",
    "addr:street":"Stormont Rd",
    "iso:country":"GB",
    "sg:address":"1 Stormont Rd",
    "sg:city":"Hitchin",
    "sg:classifiers":[
        {
            "category":"Building & Trades",
            "subcategory":"Plumbing",
            "type":"Services"
        }
    ],
    "sg:phone":"+44 1462 435680",
    "sg:postcode":"SG5 1SJ",
    "sg:province":"Bedfordshire",
    "sg:tags":[
        "heating"
    ],
    "wof:name":"B J Foster",
    "wof:placetype":"venue"
},
  "geometry": {"coordinates":[-0.2740530074,51.957824707],"type":"Point"}
}