{
  "type": "Feature",
  "properties": {
    "iso:country":"GB",
    "sg:address":"New Road",
    "sg:city":"Calne",
    "sg:classifiers":[
        {
            "category":"Education",
            "subcategory":"Library",
            "type":"Public Place"
        },
        {
            "category":"Government",
            "subcategory":"Office",
            "type":"Public Place"
        }
    ],
    "sg:phone":"+44 1249 813128",
    "sg:postcode":"SN11 0JJ",
    "sg:province":"Wiltshire",
    "sg:tags":[
        "book",
        "local"
    ],
    "wof:name":"Calne Library",
    "wof:placetype":"venue"
},
  "geometry": {"coordinates":[-2.004104,51.436131],"type":"Point"}
}