{
  "type": "Feature",
  "properties": {
    "addr:full":"Wrights Seadale Caravan Camp Filey North Yorkshire YO14 0BB",
    "addr:postcode":"yo14 0bb",
    "iso:country":"GB",
    "sg:address":"Wrights Seadale Caravan Camp",
    "sg:city":"Filey",
    "sg:classifiers":[
        {
            "category":"Food & Beverages",
            "subcategory":"Groceries & Convenience Stores",
            "type":"Retail Goods"
        },
        {
            "category":"Recreation",
            "subcategory":"Campground",
            "type":"Entertainment"
        }
    ],
    "sg:postcode":"YO14 0BB",
    "sg:province":"North Yorkshire",
    "sg:tags":[
        "caravan",
        "park"
    ],
    "wof:name":"Wright's Seadale Caravan Camp Ltd.",
    "wof:placetype":"venue"
},
  "geometry": {"coordinates":[-0.290749,54.211845],"type":"Point"}
}