{
  "type": "Feature",
  "properties": {
    "iso:country":"GB",
    "sg:address":"71 Bingley Road, Saltaire",
    "sg:city":"Shipley",
    "sg:classifiers":[
        {
            "category":"Health Services",
            "subcategory":"Optometrist",
            "type":"Services"
        }
    ],
    "sg:phone":"+44 1274 533898",
    "sg:postcode":"BD18 4SB",
    "sg:province":"West Yorkshire",
    "sg:tags":[
        "optician"
    ],
    "wof:name":"Opula",
    "wof:placetype":"venue"
},
  "geometry": {"coordinates":[-1.7924989462,53.8352012634],"type":"Point"}
}