{
  "type": "Feature",
  "properties": {
    "iso:country":"GB",
    "sg:address":"Carse Grange Poultry Farm, Errol",
    "sg:city":"Perth",
    "sg:classifiers":[
        {
            "category":"Farming",
            "subcategory":"Livestock Farm",
            "type":"Manufacturing & Wholesale Goods"
        }
    ],
    "sg:phone":"+44 1821 642453",
    "sg:postcode":"PH2 7SY",
    "sg:province":"Perth and Kinross",
    "sg:tags":[
        "others"
    ],
    "wof:name":"M G Sheret",
    "wof:placetype":"venue"
},
  "geometry": {"coordinates":[-3.209753,56.393379],"type":"Point"}
}