{
  "type": "Feature",
  "properties": {
    "iso:country":"GB",
    "sg:address":"80 Stanley Avenue",
    "sg:city":"Dagenham",
    "sg:classifiers":[
        {
            "category":"Professional",
            "subcategory":"Art Services",
            "type":"Services"
        }
    ],
    "sg:phone":"+44 20 8517 4501",
    "sg:postcode":"RM8 1JJ",
    "sg:province":"Essex",
    "sg:tags":[
        "stone",
        "restoration",
        "cleaning"
    ],
    "wof:name":"D Maggs Stone Cleaning & Restoration",
    "wof:placetype":"venue"
},
  "geometry": {"coordinates":[0.150269,51.567566],"type":"Point"}
}