{
  "type": "Feature",
  "properties": {
    "addr:full":"161a Wellgate Rotherham South Yorkshire S60 2NN",
    "addr:housenumber":"161a",
    "addr:postcode":"s60 2nn",
    "addr:street":"Wellgate Rotherham South",
    "iso:country":"GB",
    "sg:address":"161a Wellgate",
    "sg:city":"Rotherham",
    "sg:classifiers":[
        {
            "category":"Banks & Credit Unions",
            "subcategory":"Financial Services",
            "type":"Services"
        }
    ],
    "sg:phone":"+44 1246 418940",
    "sg:postcode":"S60 2NN",
    "sg:province":"South Yorkshire",
    "sg:tags":[
        "consultant"
    ],
    "wof:name":"Vy-Tel Services Ltd.",
    "wof:placetype":"venue"
},
  "geometry": {"coordinates":[-1.3502880335,53.4277763367],"type":"Point"}
}