{
  "type": "Feature",
  "properties": {
    "addr:full":"Stondon Massey, Ongar Road Brentwood Essex CM15 0EQ",
    "addr:postcode":"cm15 0eq",
    "addr:street":"Ongar Road",
    "iso:country":"GB",
    "sg:address":"Stondon Massey, Ongar Road",
    "sg:city":"Brentwood",
    "sg:classifiers":[
        {
            "category":"Shopping",
            "subcategory":"Department Store",
            "type":"Retail Goods"
        },
        {
            "category":"Food & Beverages",
            "subcategory":"Supermarket",
            "type":"Retail Goods"
        }
    ],
    "sg:phone":"+44 1277 823333",
    "sg:postcode":"CM15 0EQ",
    "sg:province":"Essex",
    "wof:name":"Stondon Village Stores",
    "wof:placetype":"venue"
},
  "geometry": {"coordinates":[0.2881669998,51.681968689],"type":"Point"}
}