{
  "type": "Feature",
  "properties": {
    "addr:full":"Market Pl, High St Glastonbury Somerset BA6 9HW",
    "addr:postcode":"ba6 9hw",
    "addr:street":"Market Pl High St",
    "iso:country":"GB",
    "sg:address":"Market Pl, High St",
    "sg:city":"Glastonbury",
    "sg:classifiers":[
        {
            "category":"Shopping",
            "subcategory":"Pharmacy",
            "type":"Retail Goods"
        }
    ],
    "sg:phone":"+44 1458 833317",
    "sg:postcode":"BA6 9HW",
    "sg:province":"Somerset",
    "sg:tags":[
        "medicine",
        "therapy"
    ],
    "wof:name":"K McNulty",
    "wof:placetype":"venue"
},
  "geometry": {"coordinates":[-2.717859,51.147339],"type":"Point"}
}