{
  "type": "Feature",
  "properties": {
    "addr:full":"Corner House Farm, Hawton Lane, Farndon Newark Nottinghamshire NG24 3SD",
    "addr:postcode":"ng24 3sd",
    "addr:street":"Hawton Lane",
    "iso:country":"GB",
    "sg:address":"Corner House Farm, Hawton Lane, Farndon",
    "sg:city":"Newark",
    "sg:classifiers":[
        {
            "category":"Professional",
            "subcategory":"Engineering",
            "type":"Services"
        }
    ],
    "sg:phone":"+44 1636 685454",
    "sg:postcode":"NG24 3SD",
    "sg:province":"Nottinghamshire",
    "wof:name":"Combine Fabrications Ltd.",
    "wof:placetype":"venue"
},
  "geometry": {"coordinates":[-0.8466200233,53.0580978394],"type":"Point"}
}