{
  "type": "Feature",
  "properties": {
    "addr:full":"Dukes Stud Newmarket Road, Ashley Newmarket Cambridgeshire CB8 9DR",
    "addr:postcode":"cb8 9dr",
    "addr:street":"Newmarket Road",
    "iso:country":"GB",
    "sg:address":"Dukes Stud Newmarket Road, Ashley",
    "sg:city":"Newmarket",
    "sg:classifiers":[
        {
            "category":"Farming",
            "subcategory":"Livestock Farm",
            "type":"Manufacturing & Wholesale Goods"
        }
    ],
    "sg:phone":"+44 1638 730214",
    "sg:postcode":"CB8 9DR",
    "sg:province":"Cambridgeshire",
    "sg:tags":[
        "stud"
    ],
    "wof:name":"Michael G Wyatt",
    "wof:placetype":"venue"
},
  "geometry": {"coordinates":[0.4841380119,52.2257804871],"type":"Point"}
}