{
  "type": "Feature",
  "properties": {
    "addr:full":"Civic Centre Uxbridge Buckinghamshire UB8 1UW",
    "addr:postcode":"ub8 1uw",
    "iso:country":"GB",
    "sg:address":"Civic Centre",
    "sg:city":"Uxbridge",
    "sg:classifiers":[
        {
            "category":"Government",
            "subcategory":"Office",
            "type":"Public Place"
        },
        {
            "category":"Sports & Exercise",
            "subcategory":"Swimming Pool",
            "type":"Entertainment"
        }
    ],
    "sg:phone":"+44 1895 250111",
    "sg:postcode":"UB8 1UW",
    "sg:province":"Buckinghamshire",
    "sg:tags":[
        "marriage",
        "death",
        "births",
        "local"
    ],
    "wof:name":"London Borough of Hillingdon",
    "wof:placetype":"venue"
},
  "geometry": {"coordinates":[-0.474536,51.544071],"type":"Point"}
}