{
  "type": "Feature",
  "properties": {
    "iso:country":"GB",
    "sg:address":"196 Bromford Lane, Erdington",
    "sg:city":"Birmingham",
    "sg:classifiers":[
        {
            "category":"Autos & Motor Vehicles",
            "subcategory":"Auto Supplies",
            "type":"Retail Goods"
        }
    ],
    "sg:phone":"+44 121 328 1564",
    "sg:postcode":"B24 8DL",
    "sg:province":"West Midlands",
    "sg:tags":[
        "tyre"
    ],
    "wof:name":"Hi-Q Tyre Services",
    "wof:placetype":"venue"
},
  "geometry": {"coordinates":[-1.833089,52.508411],"type":"Point"}
}