{
  "type": "Feature",
  "properties": {
    "addr:full":"25 Dalry Rd Edinburgh City of Edinburgh EH11 2BQ",
    "addr:housenumber":"25",
    "addr:postcode":"eh11 2bq",
    "addr:street":"Dalry Rd",
    "iso:country":"GB",
    "sg:address":"25 Dalry Rd",
    "sg:city":"Edinburgh",
    "sg:classifiers":[
        {
            "category":"Food & Beverages",
            "subcategory":"Groceries & Convenience Stores",
            "type":"Retail Goods"
        }
    ],
    "sg:phone":"+44 131 467 7175",
    "sg:postcode":"EH11 2BQ",
    "sg:province":"City of Edinburgh",
    "wof:name":"Buchanan,Neil",
    "wof:placetype":"venue"
},
  "geometry": {"coordinates":[-3.217259,55.945244],"type":"Point"}
}