{
  "type": "Feature",
  "properties": {
    "addr:full":"Church View, Pillerton Hersey Warwick Warwickshire CV35 0QJ",
    "addr:postcode":"cv35 0qj",
    "iso:country":"GB",
    "sg:address":"Church View, Pillerton Hersey",
    "sg:city":"Warwick",
    "sg:classifiers":[
        {
            "category":"Building & Trades",
            "subcategory":"Construction",
            "type":"Services"
        }
    ],
    "sg:phone":"+44 1789 740136",
    "sg:postcode":"CV35 0QJ",
    "sg:province":"Warwickshire",
    "sg:tags":[
        "builder"
    ],
    "wof:name":"T Hitchman",
    "wof:placetype":"venue"
},
  "geometry": {"coordinates":[-1.511815,52.156887],"type":"Point"}
}