{
  "type": "Feature",
  "properties": {
    "addr:full":"1 North Street Alexandria Argyll and Bute G83 0EA",
    "addr:housenumber":"1",
    "addr:postcode":"g83 0ea",
    "addr:street":"North Street",
    "iso:country":"GB",
    "sg:address":"1 North Street",
    "sg:city":"Alexandria",
    "sg:classifiers":[
        {
            "category":"Building & Trades",
            "subcategory":"Construction",
            "type":"Services"
        }
    ],
    "sg:postcode":"G83 0EA",
    "sg:province":"Argyll and Bute",
    "sg:tags":[
        "builder"
    ],
    "wof:name":"James Law",
    "wof:placetype":"venue"
},
  "geometry": {"coordinates":[-4.58248,55.989082],"type":"Point"}
}