{
  "type": "Feature",
  "properties": {
    "addr:full":"The Old Forge, Estate Yard Tunbridge Wells East Sussex TN3 9JR",
    "addr:postcode":"tn3 9jr",
    "iso:country":"GB",
    "sg:address":"The Old Forge, Estate Yard",
    "sg:city":"Tunbridge Wells",
    "sg:classifiers":[
        {
            "category":"Professional",
            "subcategory":"Management & Consulting",
            "type":"Services"
        }
    ],
    "sg:phone":"+44 1892 511128",
    "sg:postcode":"TN3 9JR",
    "sg:province":"East Sussex",
    "sg:tags":[
        "consultant"
    ],
    "wof:name":"The Charles Douglas Organisation Ltd.",
    "wof:placetype":"venue"
},
  "geometry": {"coordinates":[0.22602,51.101742],"type":"Point"}
}