{
  "type": "Feature",
  "properties": {
    "addr:full":"28 Chestnut Rise London Greater London SE18 1RL",
    "addr:housenumber":"28",
    "addr:postcode":"se18 1rl",
    "addr:street":"Chestnut Rise",
    "iso:country":"GB",
    "sg:address":"28 Chestnut Rise",
    "sg:city":"London",
    "sg:classifiers":[
        {
            "category":"Retail",
            "subcategory":"Auto Repair",
            "type":"Services"
        }
    ],
    "sg:phone":"+44 20 8854 1319",
    "sg:postcode":"SE18 1RL",
    "sg:province":"Greater London",
    "sg:tags":[
        "modification",
        "garage"
    ],
    "wof:name":"Alexander Commercials",
    "wof:placetype":"venue"
},
  "geometry": {"coordinates":[0.0875430033,51.484161377],"type":"Point"}
}