{
  "type": "Feature",
  "properties": {
    "addr:full":"21 Beaumont Rd Middlesbrough North Yorkshire TS3 6NN",
    "addr:housenumber":"21",
    "addr:postcode":"ts3 6nn",
    "addr:street":"Beaumont Rd",
    "iso:country":"GB",
    "sg:address":"21 Beaumont Rd",
    "sg:city":"Middlesbrough",
    "sg:classifiers":[
        {
            "category":"Professional",
            "subcategory":"Engineering",
            "type":"Services"
        }
    ],
    "sg:phone":"+44 1642 245352",
    "sg:postcode":"TS3 6NN",
    "sg:province":"North Yorkshire",
    "sg:tags":[
        "contractor",
        "electrical",
        "engineer"
    ],
    "wof:name":"Brian Gull Electrics",
    "wof:placetype":"venue"
},
  "geometry": {"coordinates":[-1.2097539902,54.5702934265],"type":"Point"}
}