{
  "type": "Feature",
  "properties": {
    "addr:full":"Syles Orchard Taunton Devon TA4 1AJ",
    "addr:postcode":"ta4 1aj",
    "addr:street":"Orchard",
    "iso:country":"GB",
    "sg:address":"Syles Orchard",
    "sg:city":"Taunton",
    "sg:classifiers":[
        {
            "category":"Banks & Credit Unions",
            "subcategory":"Investment Brokerage",
            "type":"Services"
        }
    ],
    "sg:phone":"+44 1823 461405",
    "sg:postcode":"TA4 1AJ",
    "sg:province":"Devon",
    "sg:tags":[
        "contractor"
    ],
    "wof:name":"Peter Thomas",
    "wof:placetype":"venue"
},
  "geometry": {"coordinates":[-3.180754,50.998356],"type":"Point"}
}