{
  "type": "Feature",
  "properties": {
    "iso:country":"GB",
    "sg:address":"1 Kempson Rd",
    "sg:city":"London",
    "sg:classifiers":[
        {
            "category":"Professional",
            "subcategory":"Engineering",
            "type":"Services"
        }
    ],
    "sg:postcode":"SW6 4PX",
    "sg:province":"Greater London",
    "wof:name":"Tomlinson,M G,",
    "wof:placetype":"venue"
},
  "geometry": {"coordinates":[-0.193825,51.478329],"type":"Point"}
}