{
  "type": "Feature",
  "properties": {
    "addr:full":"94-95 Bath Street Birmingham West Midlands B4 6HG",
    "addr:housenumber":"94-95",
    "addr:postcode":"b4 6hg",
    "addr:street":"Bath Street",
    "iso:country":"GB",
    "sg:address":"94-95 Bath Street",
    "sg:city":"Birmingham",
    "sg:classifiers":[
        {
            "category":"Building & Trades",
            "subcategory":"Construction",
            "type":"Services"
        }
    ],
    "sg:postcode":"B4 6HG",
    "sg:province":"West Midlands",
    "sg:tags":[
        "dry",
        "lining",
        "plasterers",
        "screeders"
    ],
    "wof:name":"Period Plasterwear",
    "wof:placetype":"venue"
},
  "geometry": {"coordinates":[-1.896658,52.486561],"type":"Point"}
}