{
  "type": "Feature",
  "properties": {
    "addr:full":"273 Penn Road, Penn Wolverhampton Staffordshire WV4 5QP",
    "addr:housenumber":"273",
    "addr:postcode":"wv4 5qp",
    "addr:street":"Penn Road",
    "iso:country":"GB",
    "sg:address":"273 Penn Road, Penn",
    "sg:city":"Wolverhampton",
    "sg:classifiers":[
        {
            "category":"Building & Trades",
            "subcategory":"Construction",
            "type":"Services"
        }
    ],
    "sg:phone":"+44 1902 332525",
    "sg:postcode":"WV4 5QP",
    "sg:province":"Staffordshire",
    "sg:tags":[
        "decorator",
        "painter"
    ],
    "wof:name":"Localrun (Decorating) Ltd.",
    "wof:placetype":"venue"
},
  "geometry": {"coordinates":[-2.1535,52.560532],"type":"Point"}
}