{
  "type": "Feature",
  "properties": {
    "addr:full":"The Folly Ind Est, Gaymers Way North Walsham Norfolk NR28 0AN",
    "addr:postcode":"nr28 0an",
    "addr:street":"Gaymers Way",
    "iso:country":"GB",
    "sg:address":"The Folly Ind Est, Gaymers Way",
    "sg:city":"North Walsham",
    "sg:classifiers":[
        {
            "category":"Building & Trades",
            "subcategory":"Construction",
            "type":"Services"
        }
    ],
    "sg:phone":"+44 1692 409955",
    "sg:postcode":"NR28 0AN",
    "sg:province":"Norfolk",
    "sg:tags":[
        "joinery"
    ],
    "wof:name":"Go Direkt",
    "wof:placetype":"venue"
},
  "geometry": {"coordinates":[1.3847600222,52.8183135986],"type":"Point"}
}