{
  "type": "Feature",
  "properties": {
    "addr:full":"Bearwood Collage, Bearwood Rd Wokingham Berkshire RG41 5BG",
    "addr:postcode":"rg41 5bg",
    "addr:street":"Bearwood Rd",
    "iso:country":"GB",
    "sg:address":"Bearwood Collage, Bearwood Rd",
    "sg:city":"Wokingham",
    "sg:classifiers":[
        {
            "category":"Farming",
            "subcategory":"Nursery",
            "type":"Manufacturing & Wholesale Goods"
        }
    ],
    "sg:phone":"+44 118 977 4417",
    "sg:postcode":"RG41 5BG",
    "sg:province":"Berkshire",
    "sg:tags":[
        "creche"
    ],
    "wof:name":"Claremont Kindergarten",
    "wof:placetype":"venue"
},
  "geometry": {"coordinates":[-0.884496,51.418339],"type":"Point"}
}