{
  "type": "Feature",
  "properties": {
    "iso:country":"GB",
    "sg:address":"82 Newton Road",
    "sg:city":"Rushden",
    "sg:classifiers":[
        {
            "category":"Government",
            "subcategory":"Fire Station",
            "type":"Public Place"
        }
    ],
    "sg:phone":"+44 1933 411338",
    "sg:postcode":"NN10 0HQ",
    "sg:province":"Bedfordshire",
    "sg:tags":[
        "w'sale",
        "lighting"
    ],
    "wof:name":"Eco Lamps Ltd.",
    "wof:placetype":"venue"
},
  "geometry": {"coordinates":[-0.59146,52.289364],"type":"Point"}
}