{
  "type": "Feature",
  "properties": {
    "addr:full":"389 Upper Richmond Road West, East Sheen London Greater London SW14 7NX",
    "addr:housenumber":"389",
    "addr:postcode":"sw14 7nx",
    "addr:street":"Upper Richmond Road West",
    "iso:country":"GB",
    "sg:address":"389 Upper Richmond Road West, East Sheen",
    "sg:city":"London",
    "sg:classifiers":[
        {
            "category":"Travel",
            "subcategory":"Travel Agent",
            "type":"Entertainment"
        }
    ],
    "sg:phone":"+44 20 8876 9739",
    "sg:postcode":"SW14 7NX",
    "sg:province":"Greater London",
    "wof:name":"Lunn Poly Ltd.",
    "wof:placetype":"venue"
},
  "geometry": {"coordinates":[-0.2679179907,51.4643554688],"type":"Point"}
}