{
  "type": "Feature",
  "properties": {
    "iso:country":"GB",
    "sg:address":"Forsythe Court, The Headrow",
    "sg:city":"Leeds",
    "sg:classifiers":[
        {
            "category":"Communications",
            "type":"Services"
        }
    ],
    "sg:postcode":"LS27 9LJ",
    "sg:province":"West Yorkshire",
    "sg:tags":[
        "telecommunication"
    ],
    "wof:name":"Sensar International Ltd.",
    "wof:placetype":"venue"
},
  "geometry": {"coordinates":[-1.546626,53.799618],"type":"Point"}
}