{
  "type": "Feature",
  "properties": {
    "iso:country":"GB",
    "sg:address":"2 Leighton Drive",
    "sg:city":"Sheffield",
    "sg:classifiers":[
        {
            "category":"Social Services",
            "subcategory":"Retirement Home",
            "type":"Services"
        }
    ],
    "sg:phone":"+44 114 239 8429",
    "sg:postcode":"S14 1ST",
    "sg:province":"South Yorkshire",
    "sg:tags":[
        "rest"
    ],
    "wof:name":"Castalayn",
    "wof:placetype":"venue"
},
  "geometry": {"coordinates":[-1.432754,53.34341],"type":"Point"}
}