{
  "type": "Feature",
  "properties": {
    "iso:country":"GB",
    "sg:address":"West Bank Dock Estate, Widnes",
    "sg:city":"Widnes",
    "sg:classifiers":[
        {
            "category":"Wholesale",
            "subcategory":"Chemicals & Plastics",
            "type":"Manufacturing & Wholesale Goods"
        }
    ],
    "sg:phone":"+44 151 424 4281",
    "sg:postcode":"WA8 0NY",
    "sg:province":"Cheshire",
    "sg:tags":[
        "product",
        "allied"
    ],
    "wof:name":"Elf Atochem Ltd",
    "wof:placetype":"venue"
},
  "geometry": {"coordinates":[-2.7409229279,53.3541984558],"type":"Point"}
}