{
  "type": "Feature",
  "properties": {
    "addr:full":"Pennine Divn 16a Hart Street Southport Lancashire PR8 6BT",
    "addr:housenumber":"16a",
    "addr:postcode":"pr8 6bt",
    "addr:street":"Hart Street",
    "iso:country":"GB",
    "sg:address":"Pennine Divn 16a Hart Street",
    "sg:city":"Southport",
    "sg:classifiers":[
        {
            "category":"Shopping",
            "subcategory":"Computers & Home Electronics",
            "type":"Retail Goods"
        }
    ],
    "sg:postcode":"PR8 6BT",
    "sg:province":"Lancashire",
    "sg:tags":[
        "electrical"
    ],
    "wof:name":"City Electrical Factors Ltd",
    "wof:placetype":"venue"
},
  "geometry": {"coordinates":[-3.0063040257,53.6479148865],"type":"Point"}
}