{
  "type": "Feature",
  "properties": {
    "iso:country":"GB",
    "sg:address":"Woodley Green, Woodley",
    "sg:city":"Reading",
    "sg:classifiers":[
        {
            "category":"Bars & Pubs",
            "type":"Food & Drink"
        },
        {
            "category":"Community Center",
            "subcategory":"Social",
            "type":"Public Place"
        }
    ],
    "sg:phone":"+44 118 969 9756",
    "sg:postcode":"RG5 4QP",
    "sg:province":"Berkshire",
    "sg:tags":[
        "pubs",
        "house",
        "inn",
        "activity"
    ],
    "wof:name":"Bull & Chequers",
    "wof:placetype":"venue"
},
  "geometry": {"coordinates":[-0.8955090046,51.4556503296],"type":"Point"}
}