{
  "type": "Feature",
  "properties": {
    "addr:full":"52 Hight Street, Carisbrooke Newport Isle of Wight PO30 1NR",
    "addr:housenumber":"52",
    "addr:postcode":"po30 1nr",
    "addr:street":"Hight Street",
    "iso:country":"GB",
    "sg:address":"52 Hight Street, Carisbrooke",
    "sg:city":"Newport",
    "sg:classifiers":[
        {
            "category":"Government",
            "subcategory":"Post Office",
            "type":"Public Place"
        }
    ],
    "sg:phone":"+44 1983 533156",
    "sg:postcode":"PO30 1NR",
    "sg:province":"Isle of Wight",
    "wof:name":"D Mattin",
    "wof:placetype":"venue"
},
  "geometry": {"coordinates":[-1.3000279665,50.6978797913],"type":"Point"}
}