{
  "type": "Feature",
  "properties": {
    "addr:full":"7 Bramblewood Broseley Shropshire TF12 5NY",
    "addr:housenumber":"7",
    "addr:postcode":"tf12 5ny",
    "addr:street":"Bramblewood Broseley Shropshire",
    "iso:country":"GB",
    "sg:address":"7 Bramblewood",
    "sg:city":"Broseley",
    "sg:classifiers":[
        {
            "category":"Retail",
            "subcategory":"Driving School",
            "type":"Services"
        }
    ],
    "sg:phone":"+44 1952 882881",
    "sg:postcode":"TF12 5NY",
    "sg:province":"Shropshire",
    "wof:name":"Midland Driving School",
    "wof:placetype":"venue"
},
  "geometry": {"coordinates":[-2.4786729813,52.617565155],"type":"Point"}
}