{
  "type": "Feature",
  "properties": {
    "addr:full":"2 Giles Cross, Bradford Peverell Dorchester Dorset DT2 9SJ",
    "addr:housenumber":"2",
    "addr:postcode":"dt2 9sj",
    "addr:street":"Giles Cross;Dorset",
    "iso:country":"GB",
    "sg:address":"2 Giles Cross, Bradford Peverell",
    "sg:city":"Dorchester",
    "sg:classifiers":[
        {
            "category":"Shopping",
            "type":"Retail Goods"
        }
    ],
    "sg:phone":"+44 1305 267763",
    "sg:postcode":"DT2 9SJ",
    "sg:province":"Dorset",
    "sg:tags":[
        "merchant"
    ],
    "wof:name":"KW Alternative Feeds",
    "wof:placetype":"venue"
},
  "geometry": {"coordinates":[-2.4766390324,50.7302818298],"type":"Point"}
}