{
  "type": "Feature",
  "properties": {
    "addr:full":"Suite 20, 10 - 20 Castle Street Luton Bedfordshire LU1 3AJ",
    "addr:housenumber":"10 20",
    "addr:postcode":"lu1 3aj",
    "addr:street":"Suite 20;Castle Street",
    "iso:country":"GB",
    "sg:address":"Suite 20, 10 - 20 Castle Street",
    "sg:city":"Luton",
    "sg:classifiers":[
        {
            "category":"Professional",
            "subcategory":"Art Services",
            "type":"Services"
        }
    ],
    "sg:postcode":"LU1 3AJ",
    "sg:province":"Bedfordshire",
    "sg:tags":[
        "photographer"
    ],
    "wof:name":"Infocus Wedding & Portrait Photography",
    "wof:placetype":"venue"
},
  "geometry": {"coordinates":[-0.4151780009,51.877040863],"type":"Point"}
}