{
  "type": "Feature",
  "properties": {
    "iso:country":"GB",
    "sg:address":"Harpur Hill Industrial Estate, Harpur Hill",
    "sg:city":"Buxton",
    "sg:classifiers":[
        {
            "category":"Manufacturing",
            "subcategory":"Lumber",
            "type":"Manufacturing & Wholesale Goods"
        }
    ],
    "sg:phone":"+44 1298 27600",
    "sg:postcode":"SK17 9JL",
    "sg:province":"Derbyshire",
    "sg:tags":[
        "importer",
        "merchants",
        "agent",
        "timber"
    ],
    "wof:name":"Bernard's Reclaim Timber",
    "wof:placetype":"venue"
},
  "geometry": {"coordinates":[-1.9057199955,53.2368431091],"type":"Point"}
}