{
  "type": "Feature",
  "properties": {
    "addr:full":"Maerdy Court, Maerdy Road Ferndale Rhondda, Cynon, Taff CF43 4BT",
    "addr:postcode":"cf43 4bt",
    "addr:street":"Maerdy;Maerdy Road",
    "iso:country":"GB",
    "sg:address":"Maerdy Court, Maerdy Road",
    "sg:city":"Ferndale",
    "sg:classifiers":[
        {
            "category":"Social Services",
            "subcategory":"Adult Care",
            "type":"Services"
        }
    ],
    "sg:phone":"+44 1443 733220",
    "sg:postcode":"CF43 4BT",
    "sg:province":"Rhondda, Cynon, Taff",
    "sg:tags":[
        "housing",
        "sheltered"
    ],
    "wof:name":"Maerdy Court Sheltered Accommodation Complex",
    "wof:placetype":"venue"
},
  "geometry": {"coordinates":[-3.4837789536,51.6733283997],"type":"Point"}
}