{
  "type": "Feature",
  "properties": {
    "iso:country":"GB",
    "sg:address":"1 Sheddocksley Rd",
    "sg:city":"Aberdeen",
    "sg:classifiers":[
        {
            "category":"Retail",
            "subcategory":"Driving School",
            "type":"Services"
        }
    ],
    "sg:phone":"+44 1224 694902",
    "sg:postcode":"AB16 6NW",
    "sg:province":"Aberdeen City",
    "wof:name":"Pegasus Driving School",
    "wof:placetype":"venue"
},
  "geometry": {"coordinates":[-2.17236,57.15205],"type":"Point"}
}