{
  "type": "Feature",
  "properties": {
    "addr:full":"Common Marsh Lane, Lords Meadow Industrial Estate Crediton Devon EX17 1HJ",
    "addr:postcode":"ex17 1hj",
    "addr:street":"Common Marsh Lane Lords Meadow Industrial Estate",
    "iso:country":"GB",
    "sg:address":"Common Marsh Lane, Lords Meadow Industrial Estate",
    "sg:city":"Crediton",
    "sg:classifiers":[
        {
            "category":"Wholesale",
            "subcategory":"Scrap",
            "type":"Manufacturing & Wholesale Goods"
        }
    ],
    "sg:postcode":"EX17 1HJ",
    "sg:province":"Devon",
    "sg:tags":[
        "waste",
        "metal"
    ],
    "wof:name":"S C & G C Wood",
    "wof:placetype":"venue"
},
  "geometry": {"coordinates":[-3.644402,50.788692],"type":"Point"}
}