{
  "type": "Feature",
  "properties": {
    "addr:full":"213 York Road Southend-on-sea Essex SS1 2RU",
    "addr:housenumber":"213",
    "addr:postcode":"ss1 2ru",
    "addr:street":"York Road",
    "iso:country":"GB",
    "sg:address":"213 York Road",
    "sg:city":"Southend-on-sea",
    "sg:classifiers":[
        {
            "category":"Health Services",
            "subcategory":"Health Practitioner",
            "type":"Services"
        }
    ],
    "sg:postcode":"SS1 2RU",
    "sg:province":"Essex",
    "sg:tags":[
        "hypnotherapists"
    ],
    "wof:name":"J T Penn",
    "wof:placetype":"venue"
},
  "geometry": {"coordinates":[0.7273870111,51.5367279053],"type":"Point"}
}