{
  "type": "Feature",
  "properties": {
    "addr:full":"47 Scotland Road Nelson Lancashire BB9 7UT",
    "addr:housenumber":"47",
    "addr:postcode":"bb9 7ut",
    "addr:street":"Scotland Road",
    "iso:country":"GB",
    "sg:address":"47 Scotland Road",
    "sg:city":"Nelson",
    "sg:classifiers":[
        {
            "category":"Organizations",
            "subcategory":"Non-profit Organization",
            "type":"Services"
        }
    ],
    "sg:phone":"+44 1282 695876",
    "sg:postcode":"BB9 7UT",
    "sg:province":"Lancashire",
    "sg:tags":[
        "organisation",
        "voluntary",
        "charity"
    ],
    "wof:name":"Age Concern England (National Council of",
    "wof:placetype":"venue"
},
  "geometry": {"coordinates":[-2.214273,53.838051],"type":"Point"}
}