{
  "type": "Feature",
  "properties": {
    "iso:country":"GB",
    "sg:address":"4 Treeside Av",
    "sg:city":"Southampton",
    "sg:classifiers":[
        {
            "category":"Parking",
            "type":"Transportation"
        }
    ],
    "sg:phone":"+44 23 8066 0386",
    "sg:postcode":"SO40 9HJ",
    "sg:province":"Hampshire",
    "sg:tags":[
        "car",
        "valet"
    ],
    "wof:name":"Totton Cars",
    "wof:placetype":"venue"
},
  "geometry": {"coordinates":[-1.485384,50.916847],"type":"Point"}
}