{
  "type": "Feature",
  "properties": {
    "addr:full":"1-3 Market Place Sheffield South Yorkshire S1 2GH",
    "addr:housenumber":"1-3",
    "addr:postcode":"s1 2gh",
    "addr:street":"Market Place",
    "iso:country":"GB",
    "sg:address":"1-3 Market Place",
    "sg:city":"Sheffield",
    "sg:classifiers":[
        {
            "category":"Bars & Pubs",
            "type":"Food & Drink"
        },
        {
            "category":"Community Center",
            "subcategory":"Social",
            "type":"Public Place"
        }
    ],
    "sg:phone":"+44 114 275 6609",
    "sg:postcode":"S1 2GH",
    "sg:province":"South Yorkshire",
    "sg:tags":[
        "pubs",
        "house",
        "inn",
        "activity"
    ],
    "wof:name":"The Bankers Draft",
    "wof:placetype":"venue"
},
  "geometry": {"coordinates":[-1.464544,53.38311],"type":"Point"}
}