{
  "type": "Feature",
  "properties": {
    "addr:full":"57 Downland Ave, Southwick Brighton West Sussex BN42 4RL",
    "addr:housenumber":"57",
    "addr:postcode":"bn42 4rl",
    "addr:street":"Downland Ave",
    "iso:country":"GB",
    "sg:address":"57 Downland Ave, Southwick",
    "sg:city":"Brighton",
    "sg:classifiers":[
        {
            "category":"Banks & Credit Unions",
            "subcategory":"Bank",
            "type":"Services"
        }
    ],
    "sg:postcode":"BN42 4RL",
    "sg:province":"West Sussex",
    "sg:tags":[
        "stocktaking",
        "inventory"
    ],
    "wof:name":"Ashley-Denman & Co",
    "wof:placetype":"venue"
},
  "geometry": {"coordinates":[-0.238481,50.841686],"type":"Point"}
}