{
  "type": "Feature",
  "properties": {
    "iso:country":"GB",
    "sg:address":"The Vicarage Cottage, High St, Wadworth",
    "sg:city":"Doncaster",
    "sg:classifiers":[
        {
            "category":"Utilities",
            "subcategory":"Sewage",
            "type":"Services"
        }
    ],
    "sg:phone":"+44 1302 854303",
    "sg:postcode":"DN11 9BG",
    "sg:province":"South Yorkshire",
    "sg:tags":[
        "acoustic",
        "consultant"
    ],
    "wof:name":"S F Garritt Limited",
    "wof:placetype":"venue"
},
  "geometry": {"coordinates":[-1.1305650473,53.5243911743],"type":"Point"}
}