{
  "type": "Feature",
  "properties": {
    "iso:country":"GB",
    "sg:address":"241 Hesketh Lane, Tarleton",
    "sg:city":"Preston",
    "sg:classifiers":[
        {
            "category":"Professional",
            "subcategory":"Art Services",
            "type":"Services"
        }
    ],
    "sg:postcode":"PR4 6AT",
    "sg:province":"Lancashire",
    "sg:tags":[
        "photographer"
    ],
    "wof:name":"Michelle Lund Photography",
    "wof:placetype":"venue"
},
  "geometry": {"coordinates":[-2.837019,53.694172],"type":"Point"}
}