{
  "type": "Feature",
  "properties": {
    "iso:country":"GB",
    "sg:address":"18 Daniels Lane",
    "sg:city":"Skelmersdale",
    "sg:classifiers":[
        {
            "category":"Building & Trades",
            "subcategory":"Cleaning & Sanitation",
            "type":"Services"
        }
    ],
    "sg:phone":"+44 1695 724866",
    "sg:postcode":"WN8 9NH",
    "sg:province":"Lancashire",
    "sg:tags":[
        "cleaner",
        "window"
    ],
    "wof:name":"Bankfield Window Cleaning Co.",
    "wof:placetype":"venue"
},
  "geometry": {"coordinates":[-2.769379,53.542461],"type":"Point"}
}