{
  "type": "Feature",
  "properties": {
    "addr:full":"688 Christchurch Rd Bournemouth Dorset BH7 6BY",
    "addr:housenumber":"688",
    "addr:postcode":"bh7 6by",
    "addr:street":"Christchurch Rd",
    "iso:country":"GB",
    "sg:address":"688 Christchurch Rd",
    "sg:city":"Bournemouth",
    "sg:classifiers":[
        {
            "category":"Recreation",
            "subcategory":"Amusement Park",
            "type":"Entertainment"
        }
    ],
    "sg:phone":"+44 1202 391234",
    "sg:postcode":"BH7 6BY",
    "sg:province":"Dorset",
    "sg:tags":[
        "arcade"
    ],
    "wof:name":"J.R's Place Amusement Arcade",
    "wof:placetype":"venue"
},
  "geometry": {"coordinates":[-1.835234046,50.7278518677],"type":"Point"}
}