{
  "type": "Feature",
  "properties": {
    "addr:full":"4 Hammanor Cotts Littlehampton West Sussex BN16 4JF",
    "addr:housenumber":"4",
    "addr:postcode":"bn16 4jf",
    "addr:street":"Hammanor Cotts",
    "iso:country":"GB",
    "sg:address":"4 Hammanor Cotts",
    "sg:city":"Littlehampton",
    "sg:classifiers":[
        {
            "category":"Retail",
            "subcategory":"Storage",
            "type":"Services"
        }
    ],
    "sg:phone":"+44 1903 775743",
    "sg:postcode":"BN16 4JF",
    "sg:province":"West Sussex",
    "sg:tags":[
        "household",
        "removal"
    ],
    "wof:name":"Mark Reed",
    "wof:placetype":"venue"
},
  "geometry": {"coordinates":[-0.484079,50.828972],"type":"Point"}
}