{
  "type": "Feature",
  "properties": {
    "iso:country":"GB",
    "sg:address":"Esplanade",
    "sg:city":"Ryde",
    "sg:classifiers":[
        {
            "category":"Recreation",
            "subcategory":"Amusement Park",
            "type":"Entertainment"
        }
    ],
    "sg:postcode":"PO33 1JA",
    "sg:province":"Isle of Wight",
    "sg:tags":[
        "arcade"
    ],
    "wof:name":"Peter Pan Playground",
    "wof:placetype":"venue"
},
  "geometry": {"coordinates":[-1.1557739973,50.731426239],"type":"Point"}
}