{
  "type": "Feature",
  "properties": {
    "addr:full":"52 Northumberland Street, Alnmouth Alnwick Northumberland NE66 2RJ",
    "addr:housenumber":"52",
    "addr:postcode":"ne66 2rj",
    "addr:street":"Northumberland Street",
    "iso:country":"GB",
    "sg:address":"52 Northumberland Street, Alnmouth",
    "sg:city":"Alnwick",
    "sg:classifiers":[
        {
            "category":"Government",
            "subcategory":"Post Office",
            "type":"Public Place"
        }
    ],
    "sg:postcode":"NE66 2RJ",
    "sg:province":"Northumberland",
    "wof:name":"Alnmouth Post Office & Newsagent",
    "wof:placetype":"venue"
},
  "geometry": {"coordinates":[-1.7035139799,55.4126014709],"type":"Point"}
}