{
  "type": "Feature",
  "properties": {
    "addr:full":"1 High Court Leeds West Yorkshire LS2 7PJ",
    "addr:housenumber":"1",
    "addr:postcode":"ls2 7pj",
    "addr:street":"High Court",
    "iso:country":"GB",
    "sg:address":"1 High Court",
    "sg:city":"Leeds",
    "sg:classifiers":[
        {
            "category":"Professional",
            "subcategory":"Credit Reporting & Collection",
            "type":"Services"
        }
    ],
    "sg:postcode":"LS2 7PJ",
    "sg:province":"West Yorkshire",
    "sg:tags":[
        "collecting",
        "agency"
    ],
    "wof:name":"Credit Default Register Ltd.",
    "wof:placetype":"venue"
},
  "geometry": {"coordinates":[-1.538105011,53.7950706482],"type":"Point"}
}