{
  "type": "Feature",
  "properties": {
    "addr:full":"The Mill, Maryland Wells-next-the-sea Norfolk NR23 1LY",
    "addr:postcode":"nr23 1ly",
    "iso:country":"GB",
    "sg:address":"The Mill, Maryland",
    "sg:city":"Wells-next-the-sea",
    "sg:classifiers":[
        {
            "category":"Retail",
            "subcategory":"Veterinary Services",
            "type":"Services"
        }
    ],
    "sg:phone":"+44 1328 711022",
    "sg:postcode":"NR23 1LY",
    "sg:province":"Norfolk",
    "sg:tags":[
        "surgeon",
        "activity"
    ],
    "wof:name":"Glaven Veterinary Practice",
    "wof:placetype":"venue"
},
  "geometry": {"coordinates":[0.8563680053,52.9533081055],"type":"Point"}
}