{
  "type": "Feature",
  "properties": {
    "iso:country":"GB",
    "sg:address":"207 Hope Carr Road",
    "sg:city":"Leigh",
    "sg:classifiers":[
        {
            "category":"Retail",
            "subcategory":"Repair Shop",
            "type":"Services"
        }
    ],
    "sg:postcode":"WN7 3AL",
    "sg:province":"Lancashire",
    "sg:tags":[
        "maintenance"
    ],
    "wof:name":"N Wall Decorators",
    "wof:placetype":"venue"
},
  "geometry": {"coordinates":[-2.503428,53.488758],"type":"Point"}
}