{
  "type": "Feature",
  "properties": {
    "iso:country":"GB",
    "sg:address":"Ground Floor 220a",
    "sg:city":"London",
    "sg:classifiers":[
        {
            "category":"Personal",
            "type":"Services"
        },
        {
            "category":"Retail",
            "subcategory":"Repair Shop",
            "type":"Services"
        }
    ],
    "sg:phone":"+44 20 7498 4360",
    "sg:postcode":"SW8 4LP",
    "sg:province":"Greater London",
    "sg:tags":[
        "tailor",
        "clothing"
    ],
    "sg:website":"http://www.designeralterations.com",
    "wof:name":"Designer Alterations Management Services Ltd",
    "wof:placetype":"venue"
},
  "geometry": {"coordinates":[-0.1478,51.475941],"type":"Point"}
}