{
  "type": "Feature",
  "properties": {
    "addr:full":"The Old Drill Hall House, 72 Manchester Road, Mossley Ashton-under-lyne Greater Manchester OL5 9AY",
    "addr:housenumber":"72",
    "addr:postcode":"ol5 9ay",
    "addr:street":"Manchester Road",
    "iso:country":"GB",
    "sg:address":"The Old Drill Hall House, 72 Manchester Road, Mossley",
    "sg:city":"Ashton-under-lyne",
    "sg:classifiers":[
        {
            "category":"Building & Trades",
            "subcategory":"Landscaping Services",
            "type":"Services"
        }
    ],
    "sg:phone":"+44 1457 834970",
    "sg:postcode":"OL5 9AY",
    "sg:province":"Greater Manchester",
    "sg:tags":[
        "gardening"
    ],
    "wof:name":"Earthworm Services",
    "wof:placetype":"venue"
},
  "geometry": {"coordinates":[-2.02712,53.529434],"type":"Point"}
}