{
  "type": "Feature",
  "properties": {
    "iso:country":"GB",
    "sg:address":"Buckland St Mary, Birchwood",
    "sg:city":"Chard",
    "sg:classifiers":[
        {
            "category":"Farming",
            "subcategory":"Livestock Farm",
            "type":"Manufacturing & Wholesale Goods"
        }
    ],
    "sg:phone":"+44 1460 234304",
    "sg:postcode":"TA20 3QQ",
    "sg:province":"Devon",
    "sg:tags":[
        "others"
    ],
    "wof:name":"F D Aplin & Son",
    "wof:placetype":"venue"
},
  "geometry": {"coordinates":[-3.072369,50.921196],"type":"Point"}
}