{
  "type": "Feature",
  "properties": {
    "addr:full":"P O Box 40 March Cambridgeshire PE15 9UB",
    "addr:housenumber":"box 40",
    "addr:postcode":"pe15 9ub",
    "addr:street":"P O",
    "iso:country":"GB",
    "sg:address":"P O Box 40",
    "sg:city":"March",
    "sg:classifiers":[
        {
            "category":"Professional",
            "subcategory":"Accounting & Tax Preparation",
            "type":"Services"
        }
    ],
    "sg:postcode":"PE15 9UB",
    "sg:province":"Cambridgeshire",
    "sg:tags":[
        "accountant"
    ],
    "wof:name":"Evergreen Accountancy Services",
    "wof:placetype":"venue"
},
  "geometry": {"coordinates":[0.0889049992,52.5512542725],"type":"Point"}
}