{
  "type": "Feature",
  "properties": {
    "addr:full":"Taunton Road Brighton East Sussex BN2 4JN",
    "addr:postcode":"bn2 4jn",
    "addr:street":"Taunton Road",
    "iso:country":"GB",
    "sg:address":"Taunton Road",
    "sg:city":"Brighton",
    "sg:classifiers":[
        {
            "category":"Bars & Pubs",
            "type":"Food & Drink"
        }
    ],
    "sg:phone":"+44 1273 703366",
    "sg:postcode":"BN2 4JN",
    "sg:province":"East Sussex",
    "sg:tags":[
        "pubs",
        "inn"
    ],
    "wof:name":"Punch Pub Co. (Ib) Ltd.",
    "wof:placetype":"venue"
},
  "geometry": {"coordinates":[-0.099316,50.841003],"type":"Point"}
}