{
  "type": "Feature",
  "properties": {
    "addr:full":"Kinghorn Health Centre, Rossland Pl Burntisland Fife KY3 9RT",
    "addr:postcode":"ky3 9rt",
    "addr:street":"Rossland Pl",
    "iso:country":"GB",
    "sg:address":"Kinghorn Health Centre, Rossland Pl",
    "sg:city":"Burntisland",
    "sg:classifiers":[
        {
            "category":"Health Services",
            "subcategory":"Doctor",
            "type":"Services"
        }
    ],
    "sg:phone":"+44 1592 890217",
    "sg:postcode":"KY3 9RT",
    "sg:province":"Fife",
    "sg:tags":[
        "practitioners"
    ],
    "wof:name":"Chishti, M K",
    "wof:placetype":"venue"
},
  "geometry": {"coordinates":[-3.234709,56.059174],"type":"Point"}
}