{
  "type": "Feature",
  "properties": {
    "addr:full":"398 Hythe Road Ashford Kent TN24 0QL",
    "addr:housenumber":"398",
    "addr:postcode":"tn24 0ql",
    "addr:street":"Hythe Road",
    "iso:country":"GB",
    "sg:address":"398 Hythe Road",
    "sg:city":"Ashford",
    "sg:classifiers":[
        {
            "category":"Cafe",
            "type":"Food & Drink"
        }
    ],
    "sg:postcode":"TN24 0QL",
    "sg:province":"Kent",
    "sg:tags":[
        "tea",
        "room"
    ],
    "wof:name":"Terrence Dickinson",
    "wof:placetype":"venue"
},
  "geometry": {"coordinates":[0.8911700249,51.1453285217],"type":"Point"}
}