{
  "type": "Feature",
  "properties": {
    "addr:full":"49a Rugby Road, Cubbington Leamington Spa Warwickshire CV32 7HZ",
    "addr:housenumber":"49a",
    "addr:postcode":"cv32 7hz",
    "addr:street":"Rugby Road",
    "iso:country":"GB",
    "sg:address":"49a Rugby Road, Cubbington",
    "sg:city":"Leamington Spa",
    "sg:classifiers":[
        {
            "category":"Building & Trades",
            "subcategory":"Construction",
            "type":"Services"
        }
    ],
    "sg:postcode":"CV32 7HZ",
    "sg:province":"Warwickshire",
    "sg:tags":[
        "bricklaying"
    ],
    "wof:name":"R G Price",
    "wof:placetype":"venue"
},
  "geometry": {"coordinates":[-1.5110110044,52.3108291626],"type":"Point"}
}