{
  "type": "Feature",
  "properties": {
    "addr:full":"139 High Street Aldershot Hampshire GU11 1TT",
    "addr:housenumber":"139",
    "addr:postcode":"gu11 1tt",
    "addr:street":"High Street",
    "iso:country":"GB",
    "sg:address":"139 High Street",
    "sg:city":"Aldershot",
    "sg:classifiers":[
        {
            "category":"Shopping",
            "subcategory":"Clothing, Apparel, & Fashions",
            "type":"Retail Goods"
        }
    ],
    "sg:phone":"+44 1252 313460",
    "sg:postcode":"GU11 1TT",
    "sg:province":"Hampshire",
    "sg:tags":[
        "shop",
        "dress",
        "outlet",
        "fancy"
    ],
    "wof:name":"The Dressing Up Shop",
    "wof:placetype":"venue"
},
  "geometry": {"coordinates":[-0.7593690157,51.2494659424],"type":"Point"}
}