{
  "type": "Feature",
  "properties": {
    "iso:country":"GB",
    "sg:address":"14 Manor Close",
    "sg:city":"Droitwich",
    "sg:classifiers":[
        {
            "category":"Health Services",
            "subcategory":"Health Practitioner",
            "type":"Services"
        }
    ],
    "sg:postcode":"WR9 8HG",
    "sg:province":"Worcestershire",
    "sg:tags":[
        "physiotherapist"
    ],
    "wof:name":"Health Care Services",
    "wof:placetype":"venue"
},
  "geometry": {"coordinates":[-2.1436960697,52.2655258179],"type":"Point"}
}