{
  "type": "Feature",
  "properties": {
    "addr:full":"Unit 2 Galley Hill Yd, Galley Hill Waltham Abbey Essex EN9 2AG",
    "addr:housenumber":"unit 2",
    "addr:postcode":"en9 2ag",
    "addr:street":"Galley Hill Yd Galley Hill",
    "iso:country":"GB",
    "sg:address":"Unit 2 Galley Hill Yd, Galley Hill",
    "sg:city":"Waltham Abbey",
    "sg:classifiers":[
        {
            "category":"Retail",
            "subcategory":"Auto Repair",
            "type":"Services"
        }
    ],
    "sg:postcode":"EN9 2AG",
    "sg:province":"Essex",
    "sg:tags":[
        "body",
        "car"
    ],
    "wof:name":"Fine Art Custom",
    "wof:placetype":"venue"
},
  "geometry": {"coordinates":[0.0177829992,51.6925544739],"type":"Point"}
}