{
  "type": "Feature",
  "properties": {
    "iso:country":"GB",
    "sg:address":"162 Liverpool Road North",
    "sg:city":"Liverpool",
    "sg:classifiers":[
        {
            "category":"Professional",
            "subcategory":"Lawyer & Legal Services",
            "type":"Services"
        }
    ],
    "sg:postcode":"L31 2HP",
    "sg:province":"Lancashire",
    "wof:name":"Costings Ltd.",
    "wof:placetype":"venue"
},
  "geometry": {"coordinates":[-2.937237,53.527061],"type":"Point"}
}