{
  "type": "Feature",
  "properties": {
    "iso:country":"GB",
    "sg:address":"25 Hawes Avenue, Quarnby",
    "sg:city":"Huddersfield",
    "sg:classifiers":[
        {
            "category":"Autos & Motor Vehicles",
            "subcategory":"Automobile Sales",
            "type":"Retail Goods"
        }
    ],
    "sg:phone":"+44 1484 314177",
    "sg:postcode":"HD3 4DT",
    "sg:province":"West Yorkshire",
    "sg:tags":[
        "car",
        "truck"
    ],
    "wof:name":"Planet Auto Electrics",
    "wof:placetype":"venue"
},
  "geometry": {"coordinates":[-1.8243160248,53.6488075256],"type":"Point"}
}