{
  "type": "Feature",
  "properties": {
    "addr:full":"38 Hallroyd Crescent Todmorden Lancashire OL14 5DA",
    "addr:housenumber":"38",
    "addr:postcode":"ol14 5da",
    "addr:street":"Hallroyd Crescent",
    "iso:country":"GB",
    "sg:address":"38 Hallroyd Crescent",
    "sg:city":"Todmorden",
    "sg:classifiers":[
        {
            "category":"Retail",
            "subcategory":"Driving School",
            "type":"Services"
        }
    ],
    "sg:phone":"+44 1706 813274",
    "sg:postcode":"OL14 5DA",
    "sg:province":"Lancashire",
    "wof:name":"Driven By You School Of Motoring",
    "wof:placetype":"venue"
},
  "geometry": {"coordinates":[-2.0894169807,53.7157936096],"type":"Point"}
}