{
  "type": "Feature",
  "properties": {
    "iso:country":"GB",
    "sg:address":"Wychwood, Northbrook Road, Coundon",
    "sg:city":"Coventry",
    "sg:classifiers":[
        {
            "category":"Shopping",
            "subcategory":"Baby Store",
            "type":"Retail Goods"
        },
        {
            "category":"Shopping",
            "subcategory":"Hobbies, Toys, & Games",
            "type":"Retail Goods"
        }
    ],
    "sg:phone":"+44 24 7633 4787",
    "sg:postcode":"CV6 2AJ",
    "sg:province":"Warwickshire",
    "sg:tags":[
        "shop",
        "nursery",
        "toy",
        "accessory"
    ],
    "wof:name":"Coventry Activity Toys Centre",
    "wof:placetype":"venue"
},
  "geometry": {"coordinates":[-1.541958,52.430592],"type":"Point"}
}