{
  "type": "Feature",
  "properties": {
    "addr:full":"St Georges Centre, Bolton Street Chorley Lancashire PR7 3QY",
    "addr:postcode":"pr7 3qy",
    "addr:street":"Bolton Street",
    "iso:country":"GB",
    "sg:address":"St Georges Centre, Bolton Street",
    "sg:city":"Chorley",
    "sg:classifiers":[
        {
            "category":"Manufacturing",
            "subcategory":"Tools & Machinery",
            "type":"Manufacturing & Wholesale Goods"
        },
        {
            "category":"Insurance",
            "subcategory":"Insurance Agent",
            "type":"Services"
        }
    ],
    "sg:phone":"+44 1257 269641",
    "sg:postcode":"PR7 3QY",
    "sg:province":"Lancashire",
    "sg:tags":[
        "society",
        "friendly"
    ],
    "wof:name":"Co-Operative Insurance Society Ltd.",
    "wof:placetype":"venue"
},
  "geometry": {"coordinates":[-2.6344759464,53.6406478882],"type":"Point"}
}