{
  "type": "Feature",
  "properties": {
    "iso:country":"GB",
    "sg:address":"2 Little Aston Lane",
    "sg:city":"Sutton Coldfield",
    "sg:classifiers":[
        {
            "category":"Shopping",
            "subcategory":"Department Store",
            "type":"Retail Goods"
        }
    ],
    "sg:phone":"+44 121 353 7205",
    "sg:postcode":"B74 3UF",
    "sg:province":"Staffordshire",
    "wof:name":"Blake Street New Stores",
    "wof:placetype":"venue"
},
  "geometry": {"coordinates":[-1.852942,52.602589],"type":"Point"}
}