{
  "type": "Feature",
  "properties": {
    "addr:full":"Easter Jackston, Longmanhill Banff Aberdeenshire AB45 3RS",
    "addr:postcode":"ab45 3rs",
    "iso:country":"GB",
    "sg:address":"Easter Jackston, Longmanhill",
    "sg:city":"Banff",
    "sg:classifiers":[
        {
            "category":"Farming",
            "subcategory":"Dairy Farm",
            "type":"Manufacturing & Wholesale Goods"
        }
    ],
    "sg:postcode":"AB45 3RS",
    "sg:province":"Aberdeenshire",
    "wof:name":"William J Morrison",
    "wof:placetype":"venue"
},
  "geometry": {"coordinates":[-2.4384860992,57.6516532898],"type":"Point"}
}