{
  "type": "Feature",
  "properties": {
    "addr:full":"302 Gloucester Road, Horfield Bristol City of Bristol BS7 8PD",
    "addr:housenumber":"302",
    "addr:postcode":"bs7 8pd",
    "addr:street":"Gloucester Road",
    "iso:country":"GB",
    "sg:address":"302 Gloucester Road, Horfield",
    "sg:city":"Bristol",
    "sg:classifiers":[
        {
            "category":"Cinema",
            "subcategory":"Movie Rental",
            "type":"Entertainment"
        }
    ],
    "sg:phone":"+44 117 923 2065",
    "sg:postcode":"BS7 8PD",
    "sg:province":"City of Bristol",
    "sg:tags":[
        "video",
        "library"
    ],
    "wof:name":"Blockbuster Video",
    "wof:placetype":"venue"
},
  "geometry": {"coordinates":[-2.5880990028,51.4817466736],"type":"Point"}
}