{
  "type": "Feature",
  "properties": {
    "addr:full":"8 Elm Drive East Grinstead East Sussex RH19 3UH",
    "addr:housenumber":"8",
    "addr:postcode":"rh19 3uh",
    "addr:street":"Elm Drive",
    "iso:country":"GB",
    "sg:address":"8 Elm Drive",
    "sg:city":"East Grinstead",
    "sg:classifiers":[
        {
            "category":"Professional",
            "subcategory":"Engineering",
            "type":"Services"
        }
    ],
    "sg:postcode":"RH19 3UH",
    "sg:province":"East Sussex",
    "sg:tags":[
        "contractor",
        "electrical",
        "engineer"
    ],
    "wof:name":"I Andrews Electrical & Security Contract",
    "wof:placetype":"venue"
},
  "geometry": {"coordinates":[0.002415,51.126804],"type":"Point"}
}