{
  "type": "Feature",
  "properties": {
    "addr:full":"25 Station Road, Wombwell Barnsley South Yorkshire S73 0BJ",
    "addr:housenumber":"25",
    "addr:postcode":"s73 0bj",
    "addr:street":"Station Road;Yorkshire",
    "iso:country":"GB",
    "sg:address":"25 Station Road, Wombwell",
    "sg:city":"Barnsley",
    "sg:classifiers":[
        {
            "category":"Organizations",
            "subcategory":"Membership Organization",
            "type":"Services"
        }
    ],
    "sg:phone":"+44 1226 752181",
    "sg:postcode":"S73 0BJ",
    "sg:province":"South Yorkshire",
    "sg:tags":[
        "club",
        "social"
    ],
    "wof:name":"Wombwell Working Mens Club",
    "wof:placetype":"venue"
},
  "geometry": {"coordinates":[-1.394712,53.523964],"type":"Point"}
}