{
  "type": "Feature",
  "properties": {
    "iso:country":"GB",
    "sg:address":"The Old School, The Green",
    "sg:city":"Thetford",
    "sg:classifiers":[
        {
            "category":"Professional",
            "subcategory":"Printing & Photocopies",
            "type":"Services"
        }
    ],
    "sg:postcode":"IP25 7LA",
    "sg:province":"Norfolk",
    "sg:tags":[
        "printer"
    ],
    "wof:name":"Shipdham Press",
    "wof:placetype":"venue"
},
  "geometry": {"coordinates":[0.80163,52.58601],"type":"Point"}
}