{
  "type": "Feature",
  "properties": {
    "addr:full":"4 Bartholomews Brighton East Sussex BN1 1HG",
    "addr:housenumber":"4",
    "addr:postcode":"bn1 1hg",
    "addr:street":"Bartholomews",
    "iso:country":"GB",
    "sg:address":"4 Bartholomews",
    "sg:city":"Brighton",
    "sg:classifiers":[
        {
            "category":"Shopping",
            "subcategory":"Clothing, Apparel, & Fashions",
            "type":"Retail Goods"
        }
    ],
    "sg:phone":"+44 1273 727699",
    "sg:postcode":"BN1 1HG",
    "sg:province":"East Sussex",
    "sg:tags":[
        "clothing",
        "accessory"
    ],
    "wof:name":"Chrome Mechanics Ltd",
    "wof:placetype":"venue"
},
  "geometry": {"coordinates":[-0.1398199946,50.8206214905],"type":"Point"}
}