{
  "type": "Feature",
  "properties": {
    "addr:full":"17 Lawford Rd Rugby Warwickshire CV21 2EB",
    "addr:housenumber":"17",
    "addr:postcode":"cv21 2eb",
    "addr:street":"Lawford Rd",
    "iso:country":"GB",
    "sg:address":"17 Lawford Rd",
    "sg:city":"Rugby",
    "sg:classifiers":[
        {
            "category":"Health Services",
            "subcategory":"Clinic",
            "type":"Services"
        }
    ],
    "sg:phone":"+44 1788 330444",
    "sg:postcode":"CV21 2EB",
    "sg:province":"Warwickshire",
    "sg:tags":[
        "planning",
        "family",
        "centre"
    ],
    "wof:name":"Pregnancy Counselling Centre",
    "wof:placetype":"venue"
},
  "geometry": {"coordinates":[-1.2867389917,52.3756561279],"type":"Point"}
}