{
  "type": "Feature",
  "properties": {
    "iso:country":"GB",
    "sg:address":"Mushroom Farm",
    "sg:city":"Penzance",
    "sg:classifiers":[
        {
            "category":"Sports & Exercise",
            "subcategory":"Skate Park",
            "type":"Entertainment"
        }
    ],
    "sg:phone":"+44 1736 368721",
    "sg:postcode":"TR20 8YF",
    "sg:province":"Cornwall",
    "sg:tags":[
        "mushroom"
    ],
    "wof:name":"Phillips Growers",
    "wof:placetype":"venue"
},
  "geometry": {"coordinates":[-5.508409977,50.1342506409],"type":"Point"}
}