{
  "type": "Feature",
  "properties": {
    "iso:country":"GB",
    "sg:address":"5 Ormond Yard",
    "sg:city":"London",
    "sg:classifiers":[
        {
            "category":"Personal",
            "subcategory":"Barber",
            "type":"Services"
        }
    ],
    "sg:phone":"+44 20 7930 2070",
    "sg:postcode":"SW1Y 6JT",
    "sg:province":"Greater London",
    "sg:tags":[
        "men's",
        "hairdresser"
    ],
    "wof:name":"Briggs",
    "wof:placetype":"venue"
},
  "geometry": {"coordinates":[-0.1367029995,51.5079460144],"type":"Point"}
}