{
  "type": "Feature",
  "properties": {
    "addr:full":"10 Rothay Drive, Meadowbank, Reddish Stockport Cheshire SK5 6TQ",
    "addr:housenumber":"10",
    "addr:postcode":"sk5 6tq",
    "addr:street":"Rothay Drive",
    "iso:country":"GB",
    "sg:address":"10 Rothay Drive, Meadowbank, Reddish",
    "sg:city":"Stockport",
    "sg:classifiers":[
        {
            "category":"Building & Trades",
            "subcategory":"Construction",
            "type":"Services"
        }
    ],
    "sg:phone":"+44 161 432 7007",
    "sg:postcode":"SK5 6TQ",
    "sg:province":"Cheshire",
    "sg:tags":[
        "decorator",
        "painter"
    ],
    "wof:name":"George Golborn",
    "wof:placetype":"venue"
},
  "geometry": {"coordinates":[-2.1527400017,53.4417076111],"type":"Point"}
}