{
  "type": "Feature",
  "properties": {
    "iso:country":"GB",
    "sg:address":"The Community Centre, Scott Rd",
    "sg:city":"Selby",
    "sg:classifiers":[
        {
            "category":"Community Center",
            "type":"Public Place"
        }
    ],
    "sg:phone":"+44 1757 708450",
    "sg:postcode":"YO8 0BL",
    "sg:province":"East Riding of Yorkshire",
    "sg:tags":[
        "centre"
    ],
    "wof:name":"Selby Community Association The",
    "wof:placetype":"venue"
},
  "geometry": {"coordinates":[-1.0703459978,53.783908844],"type":"Point"}
}