{
  "type": "Feature",
  "properties": {
    "iso:country":"GB",
    "sg:address":"Unit 7, White Horse Business Park, Ware Road",
    "sg:city":"Faringdon",
    "sg:classifiers":[
        {
            "category":"Retail",
            "subcategory":"Storage",
            "type":"Services"
        }
    ],
    "sg:phone":"+44 1367 718710",
    "sg:postcode":"SN7 8NY",
    "sg:province":"Oxfordshire",
    "sg:tags":[
        "household",
        "removal"
    ],
    "wof:name":"Ardington Archives",
    "wof:placetype":"venue"
},
  "geometry": {"coordinates":[-1.586654,51.65617],"type":"Point"}
}