{
  "type": "Feature",
  "properties": {
    "addr:full":"110 Warwick Road Carlisle Cumbria CA1 1JU",
    "addr:housenumber":"110",
    "addr:postcode":"ca1 1ju",
    "addr:street":"Warwick Road",
    "iso:country":"GB",
    "sg:address":"110 Warwick Road",
    "sg:city":"Carlisle",
    "sg:classifiers":[
        {
            "category":"Travel",
            "subcategory":"Hotels & Motels",
            "type":"Entertainment"
        }
    ],
    "sg:phone":"+44 1228 522112",
    "sg:postcode":"CA1 1JU",
    "sg:province":"Cumbria",
    "sg:tags":[
        "house",
        "guest"
    ],
    "wof:name":"East View Guest House",
    "wof:placetype":"venue"
},
  "geometry": {"coordinates":[-2.924314,54.894306],"type":"Point"}
}