{
  "type": "Feature",
  "properties": {
    "addr:full":"22 Edinburgh Road Dalkeith City of Edinburgh EH22 1JR",
    "addr:housenumber":"22",
    "addr:postcode":"eh22 1jr",
    "addr:street":"Edinburgh Road",
    "iso:country":"GB",
    "sg:address":"22 Edinburgh Road",
    "sg:city":"Dalkeith",
    "sg:classifiers":[
        {
            "category":"Professional",
            "subcategory":"Printing & Photocopies",
            "type":"Services"
        }
    ],
    "sg:phone":"+44 131 663 4455",
    "sg:postcode":"EH22 1JR",
    "sg:province":"City of Edinburgh",
    "sg:tags":[
        "process",
        "screen",
        "printer"
    ],
    "wof:name":"McGregor's Signs Ltd.",
    "wof:placetype":"venue"
},
  "geometry": {"coordinates":[-3.0728580952,55.8960037231],"type":"Point"}
}