{
  "type": "Feature",
  "properties": {
    "iso:country":"GB",
    "sg:address":"Cane Lane, Grove",
    "sg:city":"Wantage",
    "sg:classifiers":[
        {
            "category":"Building & Trades",
            "subcategory":"Construction",
            "type":"Services"
        }
    ],
    "sg:phone":"+44 1235 772772",
    "sg:postcode":"OX12 0AB",
    "sg:province":"Berkshire",
    "sg:tags":[
        "builder"
    ],
    "wof:name":"Stepnell",
    "wof:placetype":"venue"
},
  "geometry": {"coordinates":[-1.429296,51.604271],"type":"Point"}
}