{
  "type": "Feature",
  "properties": {
    "addr:full":"High St Saxmundham Suffolk IP17 3EP",
    "addr:postcode":"ip17 3ep",
    "addr:street":"High St",
    "iso:country":"GB",
    "sg:address":"High St",
    "sg:city":"Saxmundham",
    "sg:classifiers":[
        {
            "category":"Professional",
            "type":"Services"
        }
    ],
    "sg:phone":"+44 7850 764532",
    "sg:postcode":"IP17 3EP",
    "sg:province":"Suffolk",
    "sg:tags":[
        "caterer"
    ],
    "wof:name":"Dinner Service The",
    "wof:placetype":"venue"
},
  "geometry": {"coordinates":[1.627243,52.273453],"type":"Point"}
}