{
  "type": "Feature",
  "properties": {
    "iso:country":"GB",
    "sg:address":"76 Low Hills Lane, Oakes",
    "sg:city":"Huddersfield",
    "sg:classifiers":[
        {
            "category":"Building & Trades",
            "subcategory":"Plumbing",
            "type":"Services"
        }
    ],
    "sg:phone":"+44 1484 650848",
    "sg:postcode":"HD3 3PQ",
    "sg:province":"West Yorkshire",
    "sg:tags":[
        "heating"
    ],
    "wof:name":"T Doyle Plumbing & Heating Services",
    "wof:placetype":"venue"
},
  "geometry": {"coordinates":[-1.834431,53.659855],"type":"Point"}
}