{
  "type": "Feature",
  "properties": {
    "iso:country":"GB",
    "sg:address":"Salop Rd",
    "sg:city":"Welshpool",
    "sg:classifiers":[
        {
            "category":"Bars & Pubs",
            "type":"Food & Drink"
        }
    ],
    "sg:postcode":"SY21 7EE",
    "sg:province":"Shropshire",
    "sg:tags":[
        "pubs",
        "inn"
    ],
    "wof:name":"Platt,Richard S,",
    "wof:placetype":"venue"
},
  "geometry": {"coordinates":[-3.142277,52.661537],"type":"Point"}
}