{
  "type": "Feature",
  "properties": {
    "iso:country":"GB",
    "sg:address":"South Lawn Farm, Swinbrook",
    "sg:city":"Burford",
    "sg:classifiers":[
        {
            "category":"Shopping",
            "subcategory":"Party Supplies",
            "type":"Retail Goods"
        }
    ],
    "sg:postcode":"OX18 4EN",
    "sg:province":"Gloucestershire",
    "sg:tags":[
        "marquees",
        "floor",
        "tent"
    ],
    "wof:name":"Prestige Marquees Ltd.",
    "wof:placetype":"venue"
},
  "geometry": {"coordinates":[-1.635023,51.802338],"type":"Point"}
}