{
  "type": "Feature",
  "properties": {
    "addr:full":"172 & 173 Boughton Industrial Estate, Boughton Newark Nottinghamshire NG22 9LD",
    "addr:housenumber":"172 & 173",
    "addr:postcode":"ng22 9ld",
    "addr:street":"Boughton Industrial Estate",
    "iso:country":"GB",
    "sg:address":"172 & 173 Boughton Industrial Estate, Boughton",
    "sg:city":"Newark",
    "sg:classifiers":[
        {
            "category":"Retail",
            "subcategory":"Auto Repair",
            "type":"Services"
        }
    ],
    "sg:phone":"+44 1623 861880",
    "sg:postcode":"NG22 9LD",
    "sg:province":"Nottinghamshire",
    "sg:tags":[
        "modification",
        "garage"
    ],
    "wof:name":"D & P Transport",
    "wof:placetype":"venue"
},
  "geometry": {"coordinates":[-0.97566998,53.2073707581],"type":"Point"}
}