{
  "type": "Feature",
  "properties": {
    "addr:full":"158 Devonshire Street Sheffield South Yorkshire S3 7SG",
    "addr:housenumber":"158",
    "addr:postcode":"s3 7sg",
    "addr:street":"Devonshire Street",
    "iso:country":"GB",
    "sg:address":"158 Devonshire Street",
    "sg:city":"Sheffield",
    "sg:classifiers":[
        {
            "category":"Shopping",
            "subcategory":"Antiques",
            "type":"Retail Goods"
        }
    ],
    "sg:phone":"+44 114 275 2311",
    "sg:postcode":"S3 7SG",
    "sg:province":"South Yorkshire",
    "wof:name":"Filibuster & Booth",
    "wof:placetype":"venue"
},
  "geometry": {"coordinates":[-1.479033,53.379688],"type":"Point"}
}