{
  "type": "Feature",
  "properties": {
    "addr:full":"Mayfield, Ricketts Hill Road, Tatsfield Westerham Kent TN16 2NG",
    "addr:postcode":"tn16 2ng",
    "addr:street":"Ricketts Hill Road",
    "iso:country":"GB",
    "sg:address":"Mayfield, Ricketts Hill Road, Tatsfield",
    "sg:city":"Westerham",
    "sg:classifiers":[
        {
            "category":"Professional",
            "type":"Services"
        }
    ],
    "sg:phone":"+44 1959 571059",
    "sg:postcode":"TN16 2NG",
    "sg:province":"Kent",
    "sg:tags":[
        "reflexologists"
    ],
    "wof:name":"Raymond Paul McLaren-Gibbs",
    "wof:placetype":"venue"
},
  "geometry": {"coordinates":[0.0239020009,51.2932090759],"type":"Point"}
}