{
  "type": "Feature",
  "properties": {
    "iso:country":"GB",
    "sg:address":"2 Hall Street",
    "sg:city":"Blackwood",
    "sg:classifiers":[
        {
            "category":"Home & Garden",
            "subcategory":"Kitchen Supply",
            "type":"Retail Goods"
        }
    ],
    "sg:postcode":"NP12 1NR",
    "sg:province":"Caerphilly",
    "sg:tags":[
        "glassware",
        "china"
    ],
    "wof:name":"Islwyn Crystal",
    "wof:placetype":"venue"
},
  "geometry": {"coordinates":[-3.1936290264,51.6671714783],"type":"Point"}
}