{
  "type": "Feature",
  "properties": {
    "addr:full":"Southampton House, Ring Street Sturminster Newton Dorset DT10 2LZ",
    "addr:postcode":"dt10 2lz",
    "addr:street":"Ring Street",
    "iso:country":"GB",
    "sg:address":"Southampton House, Ring Street",
    "sg:city":"Sturminster Newton",
    "sg:classifiers":[
        {
            "category":"Shopping",
            "subcategory":"Clothing, Apparel, & Fashions",
            "type":"Retail Goods"
        }
    ],
    "sg:postcode":"DT10 2LZ",
    "sg:province":"Dorset",
    "sg:tags":[
        "shop"
    ],
    "wof:name":"Inspirations",
    "wof:placetype":"venue"
},
  "geometry": {"coordinates":[-2.377724,50.958675],"type":"Point"}
}