{
  "type": "Feature",
  "properties": {
    "iso:country":"GB",
    "sg:address":"Clifton Moor, York Ring Road",
    "sg:city":"York",
    "sg:classifiers":[
        {
            "category":"Fast Food",
            "type":"Food & Drink"
        }
    ],
    "sg:phone":"+44 1904 693959",
    "sg:postcode":"YO30 4XZ",
    "sg:province":"North Yorkshire",
    "sg:tags":[
        "away",
        "take"
    ],
    "wof:name":"McDonalds Restaurants Ltd.",
    "wof:placetype":"venue"
},
  "geometry": {"coordinates":[-1.103076,53.98703],"type":"Point"}
}