{
  "type": "Feature",
  "properties": {
    "addr:full":"96a London Rd Marlborough Berkshire SN8 2AP",
    "addr:housenumber":"96a",
    "addr:postcode":"rd;sn8 2ap",
    "addr:street":"London",
    "iso:country":"GB",
    "sg:address":"96a London Rd",
    "sg:city":"Marlborough",
    "sg:classifiers":[
        {
            "category":"Building & Trades",
            "subcategory":"Construction",
            "type":"Services"
        }
    ],
    "sg:phone":"+44 1672 511818",
    "sg:postcode":"SN8 2AP",
    "sg:province":"Berkshire",
    "sg:tags":[
        "roofing"
    ],
    "wof:name":"Marlborough Roofing",
    "wof:placetype":"venue"
},
  "geometry": {"coordinates":[-1.7211560011,51.4198226929],"type":"Point"}
}