{
  "type": "Feature",
  "properties": {
    "addr:full":"42 Leighcliff Road Leigh-on-sea Essex SS9 1DJ",
    "addr:housenumber":"42",
    "addr:postcode":"ss9 1dj",
    "addr:street":"Leighcliff Road",
    "iso:country":"GB",
    "sg:address":"42 Leighcliff Road",
    "sg:city":"Leigh-on-sea",
    "sg:classifiers":[
        {
            "category":"Professional",
            "subcategory":"Art Services",
            "type":"Services"
        }
    ],
    "sg:phone":"+44 1702 475000",
    "sg:postcode":"SS9 1DJ",
    "sg:province":"Essex",
    "sg:tags":[
        "consultant",
        "design"
    ],
    "wof:name":"Roy Salmon Partnership",
    "wof:placetype":"venue"
},
  "geometry": {"coordinates":[0.663105011,51.5426101685],"type":"Point"}
}