{
  "type": "Feature",
  "properties": {
    "addr:full":"Stocks St Manchester Greater Manchester M8 8GG",
    "addr:postcode":"m8 8gg",
    "addr:street":"Stocks St",
    "iso:country":"GB",
    "sg:address":"Stocks St",
    "sg:city":"Manchester",
    "sg:classifiers":[
        {
            "category":"Shopping",
            "subcategory":"Baby Store",
            "type":"Retail Goods"
        }
    ],
    "sg:phone":"+44 161 834 1537",
    "sg:postcode":"M8 8GG",
    "sg:province":"Greater Manchester",
    "sg:tags":[
        "nursery",
        "accessory"
    ],
    "wof:name":"Kooltrade Wholesale Nursery Products",
    "wof:placetype":"venue"
},
  "geometry": {"coordinates":[-2.2378139496,53.4946937561],"type":"Point"}
}