{
  "type": "Feature",
  "properties": {
    "iso:country":"GB",
    "sg:address":"40 Hutton Road, Shenfield",
    "sg:city":"Brentwood",
    "sg:classifiers":[
        {
            "category":"Health Services",
            "subcategory":"Dentist",
            "type":"Services"
        }
    ],
    "sg:phone":"+44 1277 233912",
    "sg:postcode":"CM15 8LB",
    "sg:province":"Essex",
    "wof:name":"F Rossouw",
    "wof:placetype":"venue"
},
  "geometry": {"coordinates":[0.322352,51.629517],"type":"Point"}
}