{
  "type": "Feature",
  "properties": {
    "addr:full":"Unit 10 Nelson Trading Estate, The Path London Greater London SW19 3BL",
    "addr:housenumber":"unit 10",
    "addr:postcode":"sw19 3bl",
    "addr:street":"Nelson Trading Estate The Path",
    "iso:country":"GB",
    "sg:address":"Unit 10 Nelson Trading Estate, The Path",
    "sg:city":"London",
    "sg:classifiers":[
        {
            "category":"Shopping",
            "subcategory":"Computers & Home Electronics",
            "type":"Retail Goods"
        }
    ],
    "sg:phone":"+44 20 8543 2959",
    "sg:postcode":"SW19 3BL",
    "sg:province":"Greater London",
    "sg:tags":[
        "mnfr",
        "system",
        "intercom"
    ],
    "wof:name":"D S Technologies Ltd.",
    "wof:placetype":"venue"
},
  "geometry": {"coordinates":[-0.19381,51.41375],"type":"Point"}
}