{
  "type": "Feature",
  "properties": {
    "iso:country":"GB",
    "sg:address":"3 Waterside Court, Pocket Nook",
    "sg:city":"St Helens",
    "sg:classifiers":[
        {
            "category":"Banks & Credit Unions",
            "subcategory":"Bureau De Change",
            "type":"Services"
        }
    ],
    "sg:phone":"+44 1744 21515",
    "sg:postcode":"WA9 1UA",
    "sg:province":"Cheshire",
    "sg:tags":[
        "town",
        "consultant",
        "planning"
    ],
    "wof:name":"Ravenhead Renaissance Ltd.",
    "wof:placetype":"venue"
},
  "geometry": {"coordinates":[-2.7256441116,53.4586105347],"type":"Point"}
}