{
  "type": "Feature",
  "properties": {
    "iso:country":"GB",
    "sg:address":"The Business Centre, Bow Bridge Clo",
    "sg:city":"Rotherham",
    "sg:classifiers":[
        {
            "category":"Bus Stop",
            "subcategory":"None",
            "type":"Transportation"
        }
    ],
    "sg:phone":"+44 1709 515661",
    "sg:postcode":"S60 1BY",
    "sg:province":"South Yorkshire",
    "sg:tags":[
        "filter"
    ],
    "wof:name":"Cascade Water Systems",
    "wof:placetype":"venue"
},
  "geometry": {"coordinates":[-1.354491,53.437832],"type":"Point"}
}