{
  "type": "Feature",
  "properties": {
    "addr:full":"Hall Close Seaham Durham SR7 0PG",
    "addr:postcode":"sr7 0pg",
    "addr:street":"Hall Close",
    "iso:country":"GB",
    "sg:address":"Hall Close",
    "sg:city":"Seaham",
    "sg:classifiers":[
        {
            "category":"Building & Trades",
            "subcategory":"Construction",
            "type":"Services"
        }
    ],
    "sg:postcode":"SR7 0PG",
    "sg:province":"Durham",
    "sg:tags":[
        "joiner",
        "carpenter"
    ],
    "wof:name":"Melvin Cardy Joinery",
    "wof:placetype":"venue"
},
  "geometry": {"coordinates":[-1.3816920519,54.8435897827],"type":"Point"}
}