{
  "type": "Feature",
  "properties": {
    "addr:full":"112a Uxbridge Road London Greater London W12 8LR",
    "addr:housenumber":"112a",
    "addr:postcode":"w12 8lr",
    "addr:street":"Uxbridge Road",
    "iso:country":"GB",
    "sg:address":"112a Uxbridge Road",
    "sg:city":"London",
    "sg:classifiers":[
        {
            "category":"Communications",
            "subcategory":"Film & Video Production",
            "type":"Services"
        }
    ],
    "sg:phone":"+44 20 8723 7773",
    "sg:postcode":"W12 8LR",
    "sg:province":"Greater London",
    "sg:tags":[
        "recording",
        "studio"
    ],
    "wof:name":"Xofa Music",
    "wof:placetype":"venue"
},
  "geometry": {"coordinates":[-0.2215099931,51.5047149658],"type":"Point"}
}