{
  "type": "Feature",
  "properties": {
    "iso:country":"GB",
    "sg:address":"69 Toll Bar Road",
    "sg:city":"Warrington",
    "sg:classifiers":[
        {
            "category":"Professional",
            "subcategory":"Detective & Security Services",
            "type":"Services"
        }
    ],
    "sg:postcode":"WA2 9TD",
    "sg:province":"Cheshire",
    "sg:tags":[
        "car"
    ],
    "wof:name":"P C S Home Protection",
    "wof:placetype":"venue"
},
  "geometry": {"coordinates":[-2.5975730419,53.4186973572],"type":"Point"}
}