{
  "type": "Feature",
  "properties": {
    "iso:country":"GB",
    "sg:address":"Springfield, Brumstead Road, Stalham",
    "sg:city":"Norwich",
    "sg:classifiers":[
        {
            "category":"Building & Trades",
            "subcategory":"Cleaning & Sanitation",
            "type":"Services"
        },
        {
            "category":"Shopping",
            "subcategory":"Discount & Variety Stores",
            "type":"Retail Goods"
        }
    ],
    "sg:phone":"+44 1692 582238",
    "sg:postcode":"NR12 9DE",
    "sg:province":"Norfolk",
    "sg:tags":[
        "window",
        "supply"
    ],
    "wof:name":"R E L Contracts",
    "wof:placetype":"venue"
},
  "geometry": {"coordinates":[1.49907,52.788509],"type":"Point"}
}