{
  "type": "Feature",
  "properties": {
    "addr:full":"Badminton Road Bristol Gloucestershire BS37 5HX",
    "addr:postcode":"bs37 5hx",
    "addr:street":"Badminton Road",
    "iso:country":"GB",
    "sg:address":"Badminton Road",
    "sg:city":"Bristol",
    "sg:classifiers":[
        {
            "category":"Building & Trades",
            "subcategory":"Construction",
            "type":"Services"
        }
    ],
    "sg:phone":"+44 1454 314201",
    "sg:postcode":"BS37 5HX",
    "sg:province":"Gloucestershire",
    "sg:tags":[
        "builder"
    ],
    "wof:name":"Tubecon Ltd.",
    "wof:placetype":"venue"
},
  "geometry": {"coordinates":[-2.4426500797,51.5390853882],"type":"Point"}
}