{
  "type": "Feature",
  "properties": {
    "addr:full":"18 Newbry Wantage Berkshire OX12 8DA",
    "addr:housenumber":"18",
    "addr:postcode":"ox12 8da",
    "addr:street":"Newbry Wantage",
    "iso:country":"GB",
    "sg:address":"18 Newbry",
    "sg:city":"Wantage",
    "sg:classifiers":[
        {
            "category":"Professional",
            "subcategory":"Lawyer & Legal Services",
            "type":"Services"
        }
    ],
    "sg:phone":"+44 1235 772212",
    "sg:postcode":"OX12 8DA",
    "sg:province":"Berkshire",
    "sg:tags":[
        "solicitor"
    ],
    "wof:name":"Patrick Smith & Co.",
    "wof:placetype":"venue"
},
  "geometry": {"coordinates":[-1.4263269901,51.5873603821],"type":"Point"}
}