{
  "type": "Feature",
  "properties": {
    "addr:full":"Lincoln House, 7 Culmington Road London Greater London W13 9NB",
    "addr:housenumber":"7",
    "addr:postcode":"w13 9nb",
    "addr:street":"Culmington Road",
    "iso:country":"GB",
    "sg:address":"Lincoln House, 7 Culmington Road",
    "sg:city":"London",
    "sg:classifiers":[
        {
            "category":"Professional",
            "subcategory":"Accounting & Tax Preparation",
            "type":"Services"
        }
    ],
    "sg:phone":"+44 20 8579 3650",
    "sg:postcode":"W13 9NB",
    "sg:province":"Greater London",
    "sg:tags":[
        "accountant"
    ],
    "wof:name":"Gandhi & Co",
    "wof:placetype":"venue"
},
  "geometry": {"coordinates":[-0.3142040074,51.5106620789],"type":"Point"}
}