{
  "type": "Feature",
  "properties": {
    "iso:country":"GB",
    "sg:address":"Unit House, Speke Blvd",
    "sg:city":"Liverpool",
    "sg:classifiers":[
        {
            "category":"Freight",
            "type":"Transportation"
        }
    ],
    "sg:phone":"+44 151 448 1907",
    "sg:postcode":"L24 9JA",
    "sg:province":"Merseyside",
    "sg:tags":[
        "forwarders"
    ],
    "wof:name":"Phoenix Agencies",
    "wof:placetype":"venue"
},
  "geometry": {"coordinates":[-2.850134,53.348511],"type":"Point"}
}