{
  "type": "Feature",
  "properties": {
    "iso:country":"GB",
    "sg:address":"1 Tremadart Close, Duloe",
    "sg:city":"Liskeard",
    "sg:classifiers":[
        {
            "category":"Building & Trades",
            "subcategory":"Plumbing",
            "type":"Services"
        }
    ],
    "sg:phone":"+44 1579 344336",
    "sg:postcode":"PL14 4PX",
    "sg:province":"Cornwall",
    "sg:tags":[
        "heating"
    ],
    "wof:name":"Plumbing South West Ltd.",
    "wof:placetype":"venue"
},
  "geometry": {"coordinates":[-4.487874,50.400402],"type":"Point"}
}