{
  "type": "Feature",
  "properties": {
    "iso:country":"GB",
    "sg:address":"C/o Po Box 20",
    "sg:city":"Bromyard",
    "sg:classifiers":[
        {
            "category":"Social Services",
            "type":"Services"
        },
        {
            "category":"Social Services",
            "subcategory":"Retirement Home",
            "type":"Services"
        }
    ],
    "sg:phone":"+44 870 527 5274",
    "sg:postcode":"HR7 4YU",
    "sg:province":"Herefordshire",
    "sg:tags":[
        "equipment",
        "suppliers",
        "disability",
        "manufacturers"
    ],
    "wof:name":"Liftwell Products Ltd",
    "wof:placetype":"venue"
},
  "geometry": {"coordinates":[-2.514429,52.186939],"type":"Point"}
}