{
  "type": "Feature",
  "properties": {
    "addr:full":"164 Stockport Rd Cheadle Cheshire SK8 2DP",
    "addr:housenumber":"164",
    "addr:postcode":"sk8 2dp",
    "addr:street":"Stockport Rd Cheadle",
    "iso:country":"GB",
    "sg:address":"164 Stockport Rd",
    "sg:city":"Cheadle",
    "sg:classifiers":[
        {
            "category":"Retail",
            "subcategory":"Auto Repair",
            "type":"Services"
        }
    ],
    "sg:phone":"+44 161 428 1929",
    "sg:postcode":"SK8 2DP",
    "sg:province":"Cheshire",
    "sg:tags":[
        "modification",
        "garage"
    ],
    "wof:name":"National Tyres & Autocare",
    "wof:placetype":"venue"
},
  "geometry": {"coordinates":[-2.203284,53.395809],"type":"Point"}
}