{
  "type": "Feature",
  "properties": {
    "addr:full":"3 Chudleigh Clo Bedford Bedfordshire MK40 3AW",
    "addr:housenumber":"3",
    "addr:postcode":"mk40 3aw",
    "addr:street":"Chudleigh Clo",
    "iso:country":"GB",
    "sg:address":"3 Chudleigh Clo",
    "sg:city":"Bedford",
    "sg:classifiers":[
        {
            "category":"Professional",
            "subcategory":"Business Services",
            "type":"Services"
        }
    ],
    "sg:phone":"+44 1234 357964",
    "sg:postcode":"MK40 3AW",
    "sg:province":"Bedfordshire",
    "sg:tags":[
        "trade"
    ],
    "wof:name":"Federation Of Small Businesses",
    "wof:placetype":"venue"
},
  "geometry": {"coordinates":[-0.4464530051,52.1448135376],"type":"Point"}
}