{
  "type": "Feature",
  "properties": {
    "addr:full":"21 Albert Gro, Wimbledon London Greater London SW20 8PZ",
    "addr:housenumber":"21",
    "addr:postcode":"sw20 8pz",
    "addr:street":"Albert Gro;London",
    "iso:country":"GB",
    "sg:address":"21 Albert Gro, Wimbledon",
    "sg:city":"London",
    "sg:classifiers":[
        {
            "category":"Professional",
            "subcategory":"Art Services",
            "type":"Services"
        }
    ],
    "sg:phone":"+44 20 8944 7430",
    "sg:postcode":"SW20 8PZ",
    "sg:province":"Greater London",
    "sg:tags":[
        "photographer"
    ],
    "wof:name":"Don Chesser",
    "wof:placetype":"venue"
},
  "geometry": {"coordinates":[-0.2182500064,51.4141616821],"type":"Point"}
}