{
  "type": "Feature",
  "properties": {
    "addr:full":"Lincoln Hall, Swaton Rd Bow Greater London E3 4ET",
    "addr:postcode":"e3 4et",
    "addr:street":"Lincoln;Swaton Rd",
    "iso:country":"GB",
    "sg:address":"Lincoln Hall, Swaton Rd",
    "sg:city":"Bow",
    "sg:classifiers":[
        {
            "category":"Organizations",
            "subcategory":"Non-profit Organization",
            "type":"Services"
        }
    ],
    "sg:phone":"+44 20 7987 4375",
    "sg:postcode":"E3 4ET",
    "sg:province":"Greater London",
    "sg:tags":[
        "organisation",
        "voluntary",
        "charity"
    ],
    "wof:name":"Save The Children Fund",
    "wof:placetype":"venue"
},
  "geometry": {"coordinates":[-0.01865,51.523392],"type":"Point"}
}