{
  "type": "Feature",
  "properties": {
    "iso:country":"GB",
    "sg:address":"11 Market Square, St Juste",
    "sg:city":"Penzance",
    "sg:classifiers":[
        {
            "category":"Food & Beverages",
            "subcategory":"Meat & Fish",
            "type":"Retail Goods"
        }
    ],
    "sg:phone":"+44 1736 788136",
    "sg:postcode":"TR19 7HD",
    "sg:province":"Cornwall",
    "sg:tags":[
        "butcher"
    ],
    "wof:name":"K D McFadden",
    "wof:placetype":"venue"
},
  "geometry": {"coordinates":[-5.680251,50.12447],"type":"Point"}
}