{
  "type": "Feature",
  "properties": {
    "addr:full":"Featherstone High School, Pontefract Road Pontefract West Yorkshire WF7 5AJ",
    "addr:postcode":"wf7 5aj",
    "addr:street":"Pontefract Road",
    "iso:country":"GB",
    "sg:address":"Featherstone High School, Pontefract Road",
    "sg:city":"Pontefract",
    "sg:classifiers":[
        {
            "category":"Professional",
            "subcategory":"Computer Services",
            "type":"Services"
        }
    ],
    "sg:postcode":"WF7 5AJ",
    "sg:province":"West Yorkshire",
    "sg:tags":[
        "system",
        "software"
    ],
    "wof:name":"Spring General Services Ltd.",
    "wof:placetype":"venue"
},
  "geometry": {"coordinates":[-1.3408,53.676781],"type":"Point"}
}