{
  "type": "Feature",
  "properties": {
    "addr:full":"61 Wheatfield Rd, Bilton Rugby Warwickshire CV22 7LL",
    "addr:housenumber":"61",
    "addr:postcode":"cv22 7ll",
    "addr:street":"Wheatfield Rd",
    "iso:country":"GB",
    "sg:address":"61 Wheatfield Rd, Bilton",
    "sg:city":"Rugby",
    "sg:classifiers":[
        {
            "category":"Professional",
            "subcategory":"Employment Agencies",
            "type":"Services"
        }
    ],
    "sg:phone":"+44 1788 562497",
    "sg:postcode":"CV22 7LL",
    "sg:province":"Warwickshire",
    "sg:tags":[
        "consultant"
    ],
    "wof:name":"Butlers Recruitment",
    "wof:placetype":"venue"
},
  "geometry": {"coordinates":[-1.2897210121,52.3652992249],"type":"Point"}
}