{
  "type": "Feature",
  "properties": {
    "addr:full":"1 Kingsfield Road Herne Bay Kent CT6 7EA",
    "addr:housenumber":"1",
    "addr:postcode":"ct6 7ea",
    "addr:street":"Kingsfield Road",
    "iso:country":"GB",
    "sg:address":"1 Kingsfield Road",
    "sg:city":"Herne Bay",
    "sg:classifiers":[
        {
            "category":"Personal",
            "subcategory":"Beauty Salon",
            "type":"Services"
        }
    ],
    "sg:phone":"+44 1227 368958",
    "sg:postcode":"CT6 7EA",
    "sg:province":"Kent",
    "sg:tags":[
        "lady",
        "hairdresser"
    ],
    "wof:name":"Veronica Jons",
    "wof:placetype":"venue"
},
  "geometry": {"coordinates":[1.1417,51.359241],"type":"Point"}
}