{
  "type": "Feature",
  "properties": {
    "addr:full":"52 Cambridge Road, Stretham Ely Cambridgeshire CB6 3LW",
    "addr:housenumber":"52",
    "addr:postcode":"cb6 3lw",
    "addr:street":"Cambridge Road",
    "iso:country":"GB",
    "sg:address":"52 Cambridge Road, Stretham",
    "sg:city":"Ely",
    "sg:classifiers":[
        {
            "category":"Transit Center",
            "subcategory":"Passenger",
            "type":"Transportation"
        }
    ],
    "sg:phone":"+44 1353 649563",
    "sg:postcode":"CB6 3LW",
    "sg:province":"Cambridgeshire",
    "sg:tags":[
        "boarding",
        "kennel",
        "catteries"
    ],
    "wof:name":"Cosy Kennels",
    "wof:placetype":"venue"
},
  "geometry": {"coordinates":[0.2087769955,52.3409385681],"type":"Point"}
}