{
  "type": "Feature",
  "properties": {
    "addr:full":"Yawlingate Road, Friskney Boston Lincolnshire PE22 8QF",
    "addr:postcode":"pe22 8qf",
    "addr:street":"Yawlingate Road",
    "iso:country":"GB",
    "sg:address":"Yawlingate Road, Friskney",
    "sg:city":"Boston",
    "sg:classifiers":[
        {
            "category":"Wholesale",
            "subcategory":"Fruits & Vegetables",
            "type":"Manufacturing & Wholesale Goods"
        }
    ],
    "sg:phone":"+44 1754 820277",
    "sg:postcode":"PE22 8QF",
    "sg:province":"Lincolnshire",
    "wof:name":"Tuplin & Son (Farmers & Produce Merchants) Ltd.",
    "wof:placetype":"venue"
},
  "geometry": {"coordinates":[0.179487,53.077427],"type":"Point"}
}