{
  "type": "Feature",
  "properties": {
    "addr:full":"10a Cordwallis Road Maidenhead Berkshire SL6 7DG",
    "addr:housenumber":"10a",
    "addr:postcode":"sl6 7dg",
    "addr:street":"Cordwallis Road",
    "iso:country":"GB",
    "sg:address":"10a Cordwallis Road",
    "sg:city":"Maidenhead",
    "sg:classifiers":[
        {
            "category":"Home & Garden",
            "subcategory":"Home Furnishings",
            "type":"Retail Goods"
        }
    ],
    "sg:phone":"+44 1628 771212",
    "sg:postcode":"SL6 7DG",
    "sg:province":"Berkshire",
    "sg:tags":[
        "pipe",
        "fitting"
    ],
    "wof:name":"Steam Ancillaries Ltd.",
    "wof:placetype":"venue"
},
  "geometry": {"coordinates":[-0.7235059738,51.5284042358],"type":"Point"}
}