{
  "type": "Feature",
  "properties": {
    "addr:full":"1 Swift Close Poole Dorset BH17 7UT",
    "addr:housenumber":"1",
    "addr:postcode":"bh17 7ut",
    "addr:street":"Swift Close",
    "iso:country":"GB",
    "sg:address":"1 Swift Close",
    "sg:city":"Poole",
    "sg:classifiers":[
        {
            "category":"Autos & Motor Vehicles",
            "subcategory":"Auto Supplies",
            "type":"Retail Goods"
        },
        {
            "category":"Banks & Credit Unions",
            "subcategory":"Investment Brokerage",
            "type":"Services"
        }
    ],
    "sg:phone":"+44 1202 601365",
    "sg:postcode":"BH17 7UT",
    "sg:province":"Dorset",
    "sg:tags":[
        "shutter",
        "guard",
        "security",
        "grille"
    ],
    "wof:name":"Dorset Security Shutters",
    "wof:placetype":"venue"
},
  "geometry": {"coordinates":[-2.0067279339,50.7428627014],"type":"Point"}
}