{
  "type": "Feature",
  "properties": {
    "iso:country":"GB",
    "sg:address":"30 Upper High Street",
    "sg:city":"Thame",
    "sg:classifiers":[
        {
            "category":"Manufacturing",
            "subcategory":"Jewelry",
            "type":"Manufacturing & Wholesale Goods"
        }
    ],
    "sg:phone":"+44 1494 524124",
    "sg:postcode":"OX9 3EZ",
    "sg:province":"Buckinghamshire",
    "sg:tags":[
        "repair",
        "jewellery"
    ],
    "wof:name":"Mayanna Ltd",
    "wof:placetype":"venue"
},
  "geometry": {"coordinates":[-0.975197,51.745911],"type":"Point"}
}