{
  "type": "Feature",
  "properties": {
    "addr:full":"44 Clos Myddlyn, Beddau Pontypridd Rhondda, Cynon, Taff CF38 2JS",
    "addr:housenumber":"44",
    "addr:postcode":"cf38 2js",
    "addr:street":"Clos Myddlyn Beddau Pontypridd;Cynon Taff",
    "iso:country":"GB",
    "sg:address":"44 Clos Myddlyn, Beddau",
    "sg:city":"Pontypridd",
    "sg:classifiers":[
        {
            "category":"Recreation",
            "subcategory":"Dog Park",
            "type":"Entertainment"
        }
    ],
    "sg:postcode":"CF38 2JS",
    "sg:province":"Rhondda, Cynon, Taff",
    "wof:name":"Merry Mutts",
    "wof:placetype":"venue"
},
  "geometry": {"coordinates":[-3.3556489944,51.5558891296],"type":"Point"}
}