{
  "type": "Feature",
  "properties": {
    "addr:full":"Unit F, Consort Way Burgess Hill East Sussex RH15 9TJ",
    "addr:postcode":"rh15 9tj",
    "addr:street":"Consort Way",
    "iso:country":"GB",
    "sg:address":"Unit F, Consort Way",
    "sg:city":"Burgess Hill",
    "sg:classifiers":[
        {
            "category":"Manufacturing",
            "subcategory":"Food",
            "type":"Manufacturing & Wholesale Goods"
        },
        {
            "category":"Ice Cream",
            "type":"Food & Drink"
        }
    ],
    "sg:phone":"+44 1444 870111",
    "sg:postcode":"RH15 9TJ",
    "sg:province":"East Sussex",
    "sg:tags":[
        "distributor",
        "manufacturer"
    ],
    "wof:name":"Consort Frozen Foods Ltd",
    "wof:placetype":"venue"
},
  "geometry": {"coordinates":[-0.1459909976,50.9537963867],"type":"Point"}
}