{
  "type": "Feature",
  "properties": {
    "addr:full":"31-32 Jubilee Road Aberdare Neath Port Talbot CF44 6DD",
    "addr:housenumber":"31-32",
    "addr:postcode":"cf44 6dd",
    "addr:street":"Jubilee Road",
    "iso:country":"GB",
    "sg:address":"31-32 Jubilee Road",
    "sg:city":"Aberdare",
    "sg:classifiers":[
        {
            "category":"Shopping",
            "subcategory":"Department Store",
            "type":"Retail Goods"
        }
    ],
    "sg:phone":"+44 1685 883274",
    "sg:postcode":"CF44 6DD",
    "sg:province":"Neath Port Talbot",
    "wof:name":"Godreaman Discount Food Store",
    "wof:placetype":"venue"
},
  "geometry": {"coordinates":[-3.428929,51.696301],"type":"Point"}
}