{
  "type": "Feature",
  "properties": {
    "iso:country":"GB",
    "sg:address":"Hollow Lane",
    "sg:city":"Canterbury",
    "sg:classifiers":[
        {
            "category":"Education",
            "subcategory":"School",
            "type":"Public Place"
        }
    ],
    "sg:phone":"+44 1227 464134",
    "sg:postcode":"CT1 3SD",
    "sg:province":"Kent",
    "sg:tags":[
        "college",
        "local",
        "authority"
    ],
    "wof:name":"Wincheap Primary School",
    "wof:placetype":"venue"
},
  "geometry": {"coordinates":[1.069037,51.266239],"type":"Point"}
}