{
  "type": "Feature",
  "properties": {
    "iso:country":"GB",
    "sg:address":"10a Littlegate Street",
    "sg:city":"Oxford",
    "sg:classifiers":[
        {
            "category":"Real Estate",
            "subcategory":"Surveying",
            "type":"Services"
        }
    ],
    "sg:phone":"+44 1865 249117",
    "sg:postcode":"OX1 1QT",
    "sg:province":"Oxfordshire",
    "sg:tags":[
        "surveyor",
        "valuer"
    ],
    "wof:name":"Raybould Frudd",
    "wof:placetype":"venue"
},
  "geometry": {"coordinates":[-1.2595390081,51.7495079041],"type":"Point"}
}