{
  "type": "Feature",
  "properties": {
    "addr:full":"Haslar Road Gosport Hampshire PO12 1NU",
    "addr:postcode":"po12 1nu",
    "addr:street":"Haslar Road",
    "iso:country":"GB",
    "sg:address":"Haslar Road",
    "sg:city":"Gosport",
    "sg:classifiers":[
        {
            "category":"Manufacturing",
            "subcategory":"Retail Goods",
            "type":"Manufacturing & Wholesale Goods"
        }
    ],
    "sg:phone":"+44 23 9252 6522",
    "sg:postcode":"PO12 1NU",
    "sg:province":"Hampshire",
    "sg:tags":[
        "chandler"
    ],
    "wof:name":"R Arthur & Co",
    "wof:placetype":"venue"
},
  "geometry": {"coordinates":[-1.1209290028,50.793006897],"type":"Point"}
}