{
  "type": "Feature",
  "properties": {
    "addr:full":"216 Leeds Road, Kippax Leeds North Yorkshire LS25 7EH",
    "addr:housenumber":"216",
    "addr:postcode":"ls25 7eh",
    "addr:street":"Leeds Road",
    "iso:country":"GB",
    "sg:address":"216 Leeds Road, Kippax",
    "sg:city":"Leeds",
    "sg:classifiers":[
        {
            "category":"Farming",
            "subcategory":"Farm",
            "type":"Manufacturing & Wholesale Goods"
        },
        {
            "category":"Food & Beverages",
            "subcategory":"Groceries & Convenience Stores",
            "type":"Retail Goods"
        }
    ],
    "sg:phone":"+44 113 286 1970",
    "sg:postcode":"LS25 7EH",
    "sg:province":"North Yorkshire",
    "sg:tags":[
        "merchant",
        "egg",
        "producer"
    ],
    "wof:name":"David A Silkstone",
    "wof:placetype":"venue"
},
  "geometry": {"coordinates":[-1.3858109713,53.7826690674],"type":"Point"}
}