{
  "type": "Feature",
  "properties": {
    "iso:country":"GB",
    "sg:address":"Queen Street",
    "sg:city":"South Shields",
    "sg:classifiers":[
        {
            "category":"Building & Trades",
            "subcategory":"Construction",
            "type":"Services"
        }
    ],
    "sg:phone":"+44 191 455 5585",
    "sg:postcode":"NE33 1HW",
    "sg:province":"Tyne and Wear",
    "sg:tags":[
        "glazier"
    ],
    "wof:name":"Mills Glass Ltd",
    "wof:placetype":"venue"
},
  "geometry": {"coordinates":[-1.4349039793,54.9986114502],"type":"Point"}
}