{
  "type": "Feature",
  "properties": {
    "addr:full":"Unit A2, Cuba Industrial Estate, Bolton Road North Bury Lancashire BL0 0NE",
    "addr:housenumber":"a2",
    "addr:postcode":"bl0 0ne",
    "addr:street":"Cuba Industrial Estate Bolton Road North",
    "iso:country":"GB",
    "sg:address":"Unit A2, Cuba Industrial Estate, Bolton Road North",
    "sg:city":"Bury",
    "sg:classifiers":[
        {
            "category":"Retail",
            "subcategory":"Auto Repair",
            "type":"Services"
        }
    ],
    "sg:phone":"+44 1706 827975",
    "sg:postcode":"BL0 0NE",
    "sg:province":"Lancashire",
    "sg:tags":[
        "car",
        "upholsterer"
    ],
    "wof:name":"Michael Kenyon",
    "wof:placetype":"venue"
},
  "geometry": {"coordinates":[-2.3159799576,53.6566886902],"type":"Point"}
}