{
  "type": "Feature",
  "properties": {
    "addr:full":"Steel St Rotherham South Yorkshire S61 1DF",
    "addr:postcode":"s61 1df",
    "addr:street":"Steel St",
    "iso:country":"GB",
    "sg:address":"Steel St",
    "sg:city":"Rotherham",
    "sg:classifiers":[
        {
            "category":"Wholesale",
            "subcategory":"Scrap",
            "type":"Manufacturing & Wholesale Goods"
        }
    ],
    "sg:phone":"+44 1709 550218",
    "sg:postcode":"S61 1DF",
    "sg:province":"South Yorkshire",
    "sg:tags":[
        "waste",
        "metal"
    ],
    "wof:name":"M N Sargeson",
    "wof:placetype":"venue"
},
  "geometry": {"coordinates":[-1.37951,53.42738],"type":"Point"}
}