{
  "type": "Feature",
  "properties": {
    "addr:full":"Edinburgh Road St Leonards-on-sea East Sussex TN38 8HH",
    "addr:postcode":"leonards-on-sea;tn38 8hh",
    "addr:street":"Edinburgh Road St",
    "iso:country":"GB",
    "sg:address":"Edinburgh Road",
    "sg:city":"St Leonards-on-sea",
    "sg:classifiers":[
        {
            "category":"Social Services",
            "subcategory":"Child Care",
            "type":"Services"
        }
    ],
    "sg:postcode":"TN38 8HH",
    "sg:province":"East Sussex",
    "sg:tags":[
        "childminders"
    ],
    "wof:name":"Club 4 Kids",
    "wof:placetype":"venue"
},
  "geometry": {"coordinates":[0.5335770249,50.8579025269],"type":"Point"}
}