{
  "type": "Feature",
  "properties": {
    "addr:full":"Halstead Road, Eight Ash Grn Colchester Essex CO6 3QA",
    "addr:postcode":"co6 3qa",
    "addr:street":"Halstead Road Eight Ash Grn Colchester",
    "iso:country":"GB",
    "sg:address":"Halstead Road, Eight Ash Grn",
    "sg:city":"Colchester",
    "sg:classifiers":[
        {
            "category":"Bars & Pubs",
            "type":"Food & Drink"
        }
    ],
    "sg:postcode":"CO6 3QA",
    "sg:province":"Essex",
    "sg:tags":[
        "pubs",
        "inn"
    ],
    "wof:name":"The Brick & Tile",
    "wof:placetype":"venue"
},
  "geometry": {"coordinates":[0.7777950168,51.9148216248],"type":"Point"}
}