{
  "type": "Feature",
  "properties": {
    "iso:country":"GB",
    "sg:address":"52a West Street, Portchester",
    "sg:city":"Fareham",
    "sg:classifiers":[
        {
            "category":"Restaurant",
            "type":"Food & Drink"
        }
    ],
    "sg:phone":"+44 23 9237 2426",
    "sg:postcode":"PO16 9UN",
    "sg:province":"Hampshire",
    "wof:name":"Penny's Bistro",
    "wof:placetype":"venue"
},
  "geometry": {"coordinates":[-1.128485,50.845905],"type":"Point"}
}