{
  "type": "Feature",
  "properties": {
    "addr:full":"Sutton Mill Farm, Claverley Wolverhampton Shropshire WV5 7BL",
    "addr:postcode":"wv5 7bl",
    "addr:street":"Sutton",
    "iso:country":"GB",
    "sg:address":"Sutton Mill Farm, Claverley",
    "sg:city":"Wolverhampton",
    "sg:classifiers":[
        {
            "category":"Farming",
            "subcategory":"Farm",
            "type":"Manufacturing & Wholesale Goods"
        }
    ],
    "sg:postcode":"WV5 7BL",
    "sg:province":"Shropshire",
    "sg:tags":[
        "mixed",
        "crop"
    ],
    "wof:name":"J B & J A Cotham & Son",
    "wof:placetype":"venue"
},
  "geometry": {"coordinates":[-2.3031229973,52.5373039246],"type":"Point"}
}