{
  "type": "Feature",
  "properties": {
    "addr:full":"5 Beresford Square Woolwich Greater London SE18 6BB",
    "addr:housenumber":"5",
    "addr:postcode":"se18 6bb",
    "addr:street":"Beresford Square",
    "iso:country":"GB",
    "sg:address":"5 Beresford Square",
    "sg:city":"Woolwich",
    "sg:classifiers":[
        {
            "category":"Restaurant",
            "type":"Food & Drink"
        }
    ],
    "sg:phone":"+44 20 8854 9414",
    "sg:postcode":"SE18 6BB",
    "sg:province":"Greater London",
    "wof:name":"Golden Grill",
    "wof:placetype":"venue"
},
  "geometry": {"coordinates":[0.0687439963,51.4915428162],"type":"Point"}
}