{
  "type": "Feature",
  "properties": {
    "iso:country":"GB",
    "sg:address":"Clapton Road, Midsomer Norton",
    "sg:city":"Bath",
    "sg:classifiers":[
        {
            "category":"Education",
            "subcategory":"School",
            "type":"Public Place"
        },
        {
            "category":"Government",
            "subcategory":"Office",
            "type":"Public Place"
        }
    ],
    "sg:phone":"+44 1761 412777",
    "sg:postcode":"BA3 2LP",
    "sg:province":"Somerset",
    "sg:tags":[
        "local",
        "authority"
    ],
    "wof:name":"Longvernal Primary School",
    "wof:placetype":"venue"
},
  "geometry": {"coordinates":[-2.496334,51.284565],"type":"Point"}
}