{
  "type": "Feature",
  "properties": {
    "iso:country":"GB",
    "sg:address":"Unit 18, Stafford Park 12",
    "sg:city":"Telford",
    "sg:classifiers":[
        {
            "category":"Manufacturing",
            "subcategory":"Chemicals & Compounds",
            "type":"Manufacturing & Wholesale Goods"
        }
    ],
    "sg:phone":"+44 1952 200909",
    "sg:postcode":"TF3 3BJ",
    "sg:province":"Shropshire",
    "wof:name":"Premkem Ltd.",
    "wof:placetype":"venue"
},
  "geometry": {"coordinates":[-2.416149,52.672195],"type":"Point"}
}