{
  "type": "Feature",
  "properties": {
    "iso:country":"GB",
    "sg:address":"Simmondley Village",
    "sg:city":"Glossop",
    "sg:classifiers":[
        {
            "category":"Bars & Pubs",
            "type":"Food & Drink"
        }
    ],
    "sg:phone":"+44 1457 852028",
    "sg:postcode":"SK13 6LS",
    "sg:province":"Derbyshire",
    "sg:tags":[
        "pubs",
        "inn"
    ],
    "wof:name":"The Hare & Hounds",
    "wof:placetype":"venue"
},
  "geometry": {"coordinates":[-1.9631990194,53.4378967285],"type":"Point"}
}