{
  "type": "Feature",
  "properties": {
    "addr:full":"109 The Highway, Croesyceiliog Cwmbran Monmouthshire NP44 2HE",
    "addr:housenumber":"109",
    "addr:postcode":"np44 2he",
    "addr:street":"The Highway",
    "iso:country":"GB",
    "sg:address":"109 The Highway, Croesyceiliog",
    "sg:city":"Cwmbran",
    "sg:classifiers":[
        {
            "category":"Personal",
            "subcategory":"Beauty Salon",
            "type":"Services"
        },
        {
            "category":"Personal",
            "subcategory":"Barber",
            "type":"Services"
        }
    ],
    "sg:phone":"+44 1633 483654",
    "sg:postcode":"NP44 2HE",
    "sg:province":"Monmouthshire",
    "sg:tags":[
        "unisex",
        "hairdresser"
    ],
    "wof:name":"Salon 109",
    "wof:placetype":"venue"
},
  "geometry": {"coordinates":[-3.0038189888,51.6613616943],"type":"Point"}
}