{
  "type": "Feature",
  "properties": {
    "addr:full":"Unit 2 Hope Farm, Crouch Lane, Sandhurst Cranbrook East Sussex TN18 5PD",
    "addr:housenumber":"unit 2",
    "addr:postcode":"tn18 5pd",
    "addr:street":"Hope;Crouch Lane",
    "iso:country":"GB",
    "sg:address":"Unit 2 Hope Farm, Crouch Lane, Sandhurst",
    "sg:city":"Cranbrook",
    "sg:classifiers":[
        {
            "category":"Military Area",
            "subcategory":"Army Base",
            "type":"Public Place"
        },
        {
            "category":"Manufacturing",
            "subcategory":"Lumber",
            "type":"Manufacturing & Wholesale Goods"
        }
    ],
    "sg:phone":"+44 1580 850986",
    "sg:postcode":"TN18 5PD",
    "sg:province":"East Sussex",
    "sg:tags":[
        "merchants",
        "centre",
        "joinery",
        "agent",
        "importer",
        "timber"
    ],
    "wof:name":"Scalegold Joinery Ltd.",
    "wof:placetype":"venue"
},
  "geometry": {"coordinates":[0.5625450015,51.0272789001],"type":"Point"}
}