{
  "type": "Feature",
  "properties": {
    "addr:full":"115 City Rd Cardiff Cardiff CF24 3BP",
    "addr:housenumber":"115",
    "addr:postcode":"cf24 3bp",
    "addr:street":"City Rd",
    "iso:country":"GB",
    "sg:address":"115 City Rd",
    "sg:city":"Cardiff",
    "sg:classifiers":[
        {
            "category":"Home & Garden",
            "subcategory":"Home Furnishings",
            "type":"Retail Goods"
        }
    ],
    "sg:postcode":"CF24 3BP",
    "sg:province":"Cardiff",
    "sg:tags":[
        "merchant",
        "diy",
        "decorators'"
    ],
    "wof:name":"Master Decorators Supply Co",
    "wof:placetype":"venue"
},
  "geometry": {"coordinates":[-3.1684260368,51.4889717102],"type":"Point"}
}