{
  "type": "Feature",
  "properties": {
    "addr:full":"Old Art Room, Woodland Road Centre Newton Abbot Devon TQ13 7DR",
    "addr:postcode":"tq13 7dr",
    "addr:street":"Woodland Road",
    "iso:country":"GB",
    "sg:address":"Old Art Room, Woodland Road Centre",
    "sg:city":"Newton Abbot",
    "sg:classifiers":[
        {
            "category":"Organizations",
            "subcategory":"Non-profit Organization",
            "type":"Services"
        }
    ],
    "sg:postcode":"TQ13 7DR",
    "sg:province":"Devon",
    "sg:tags":[
        "organisation",
        "voluntary",
        "charity"
    ],
    "wof:name":"Ashburton Community Development Trust",
    "wof:placetype":"venue"
},
  "geometry": {"coordinates":[-3.7714490891,50.5209693909],"type":"Point"}
}