{
  "type": "Feature",
  "properties": {
    "iso:country":"GB",
    "sg:address":"206 Brook St",
    "sg:city":"Dundee",
    "sg:classifiers":[
        {
            "category":"Manufacturing",
            "subcategory":"Metals",
            "type":"Manufacturing & Wholesale Goods"
        }
    ],
    "sg:phone":"+44 1382 224340",
    "sg:postcode":"DD1 5BH",
    "sg:province":"Dundee City",
    "wof:name":"Starlite Electroplating (Dundee) Ltd",
    "wof:placetype":"venue"
},
  "geometry": {"coordinates":[-2.989616,56.461788],"type":"Point"}
}