{
  "type": "Feature",
  "properties": {
    "iso:country":"GB",
    "sg:address":"95 Manchester Road",
    "sg:city":"Altrincham",
    "sg:classifiers":[
        {
            "category":"Home & Garden",
            "subcategory":"Hardware",
            "type":"Retail Goods"
        }
    ],
    "sg:phone":"+44 161 928 1418",
    "sg:postcode":"WA14 4RJ",
    "sg:province":"Cheshire",
    "sg:tags":[
        "lawnmowers",
        "machinery"
    ],
    "wof:name":"Sale Mowers and Tropheys",
    "wof:placetype":"venue"
},
  "geometry": {"coordinates":[-2.352389,53.397091],"type":"Point"}
}