{
  "type": "Feature",
  "properties": {
    "addr:full":"Hill Bridge Garage, Campsea Ash Woodbridge Suffolk IP13 0PT",
    "addr:postcode":"ip13 0pt",
    "addr:street":"Hill;Ash",
    "iso:country":"GB",
    "sg:address":"Hill Bridge Garage, Campsea Ash",
    "sg:city":"Woodbridge",
    "sg:classifiers":[
        {
            "category":"Retail",
            "subcategory":"Auto Repair",
            "type":"Services"
        }
    ],
    "sg:phone":"+44 1728 746182",
    "sg:postcode":"IP13 0PT",
    "sg:province":"Suffolk",
    "sg:tags":[
        "modification",
        "garage"
    ],
    "wof:name":"F L & M J Taylor",
    "wof:placetype":"venue"
},
  "geometry": {"coordinates":[1.3987799883,52.1516685486],"type":"Point"}
}