{
  "type": "Feature",
  "properties": {
    "iso:country":"GB",
    "sg:address":"8/10 Regency Arcade, 23 Molesworth Street",
    "sg:city":"Wadebridge",
    "sg:classifiers":[
        {
            "category":"Professional",
            "subcategory":"Accounting & Tax Preparation",
            "type":"Services"
        }
    ],
    "sg:phone":"+44 1208 813661",
    "sg:postcode":"PL27 7DH",
    "sg:province":"Cornwall",
    "sg:tags":[
        "accountant",
        "bookkeeping",
        "primarily",
        "activity"
    ],
    "wof:name":"M J C Oliver & Co",
    "wof:placetype":"venue"
},
  "geometry": {"coordinates":[-4.838024,50.518188],"type":"Point"}
}