{
  "type": "Feature",
  "properties": {
    "iso:country":"GB",
    "sg:address":"6 Maiden Lane, Covent Garden",
    "sg:city":"London",
    "sg:classifiers":[
        {
            "category":"Real Estate",
            "subcategory":"Real Estate Agent",
            "type":"Services"
        }
    ],
    "sg:phone":"+44 20 7836 9013",
    "sg:postcode":"WC2E 7NW",
    "sg:province":"Greater London",
    "wof:name":"Grantham Court Properties (Mayfair) Ltd.",
    "wof:placetype":"venue"
},
  "geometry": {"coordinates":[-0.1259309947,51.5425224304],"type":"Point"}
}