{
  "type": "Feature",
  "properties": {
    "addr:full":"4 Shorland Oaks Bracknell Berkshire RG42 2JZ",
    "addr:housenumber":"4",
    "addr:postcode":"rg42 2jz",
    "addr:street":"Shorland Oaks",
    "iso:country":"GB",
    "sg:address":"4 Shorland Oaks",
    "sg:city":"Bracknell",
    "sg:classifiers":[
        {
            "category":"Real Estate",
            "subcategory":"Real Estate Services",
            "type":"Services"
        },
        {
            "category":"Building & Trades",
            "subcategory":"Construction",
            "type":"Services"
        }
    ],
    "sg:phone":"+44 1344 301456",
    "sg:postcode":"RG42 2JZ",
    "sg:province":"Berkshire",
    "sg:tags":[
        "builder"
    ],
    "wof:name":"Eskdale Construction Ltd.",
    "wof:placetype":"venue"
},
  "geometry": {"coordinates":[-0.74308,51.428059],"type":"Point"}
}