{
  "type": "Feature",
  "properties": {
    "iso:country":"GB",
    "sg:address":"4 Walesby Close",
    "sg:city":"Grimsby",
    "sg:classifiers":[
        {
            "category":"Organizations",
            "subcategory":"Non-profit Organization",
            "type":"Services"
        }
    ],
    "sg:postcode":"DN33 3HQ",
    "sg:province":"Lincolnshire",
    "sg:tags":[
        "organisation",
        "voluntary",
        "charity"
    ],
    "wof:name":"The Parkinsons Disease Society",
    "wof:placetype":"venue"
},
  "geometry": {"coordinates":[-0.1039529964,53.5315093994],"type":"Point"}
}