{
  "type": "Feature",
  "properties": {
    "iso:country":"GB",
    "sg:address":"39 Borden Lane",
    "sg:city":"Sittingbourne",
    "sg:classifiers":[
        {
            "category":"Building & Trades",
            "subcategory":"Plumbing",
            "type":"Services"
        }
    ],
    "sg:phone":"+44 1795 477266",
    "sg:postcode":"ME10 1BU",
    "sg:province":"Kent",
    "sg:tags":[
        "heating"
    ],
    "wof:name":"Gasflo Heating Services",
    "wof:placetype":"venue"
},
  "geometry": {"coordinates":[0.7217289805,51.341003418],"type":"Point"}
}