{
  "type": "Feature",
  "properties": {
    "addr:full":"Goldsmith Rd Wellingborough Northamptonshire NN8 3RU",
    "addr:postcode":"nn8 3ru",
    "addr:street":"Goldsmith Rd",
    "iso:country":"GB",
    "sg:address":"Goldsmith Rd",
    "sg:city":"Wellingborough",
    "sg:classifiers":[
        {
            "category":"Social Services",
            "subcategory":"Adult Care",
            "type":"Services"
        }
    ],
    "sg:phone":"+44 1933 677326",
    "sg:postcode":"NN8 3RU",
    "sg:province":"Northamptonshire",
    "sg:tags":[
        "day",
        "centre"
    ],
    "wof:name":"Glamis Hall Day Centre",
    "wof:placetype":"venue"
},
  "geometry": {"coordinates":[-0.7238789797,52.3026008606],"type":"Point"}
}