{
  "type": "Feature",
  "properties": {
    "addr:full":"5 The Parade, Bramhope Leeds West Yorkshire LS16 9AF",
    "addr:housenumber":"5",
    "addr:postcode":"ls16 9af",
    "addr:street":"The Parade",
    "iso:country":"GB",
    "sg:address":"5 The Parade, Bramhope",
    "sg:city":"Leeds",
    "sg:classifiers":[
        {
            "category":"Personal",
            "subcategory":"Beauty Salon",
            "type":"Services"
        },
        {
            "category":"Personal",
            "subcategory":"Barber",
            "type":"Services"
        }
    ],
    "sg:postcode":"LS16 9AF",
    "sg:province":"West Yorkshire",
    "sg:tags":[
        "unisex",
        "hairdresser"
    ],
    "wof:name":"Sara'S",
    "wof:placetype":"venue"
},
  "geometry": {"coordinates":[-1.615417,53.884586],"type":"Point"}
}