{
  "type": "Feature",
  "properties": {
    "iso:country":"GB",
    "sg:address":"Glendon Lodge Farm, Rushton Road",
    "sg:city":"Kettering",
    "sg:classifiers":[
        {
            "category":"Sports & Exercise",
            "subcategory":"Stables",
            "type":"Entertainment"
        }
    ],
    "sg:postcode":"NN14 1QF",
    "sg:province":"Northamptonshire",
    "sg:tags":[
        "education",
        "equestrian"
    ],
    "wof:name":"J N Hipwell & Sons",
    "wof:placetype":"venue"
},
  "geometry": {"coordinates":[-0.7613840103,52.4385948181],"type":"Point"}
}