{
  "type": "Feature",
  "properties": {
    "iso:country":"GB",
    "sg:address":"76 Brewers Street",
    "sg:city":"London",
    "sg:classifiers":[
        {
            "category":"Professional",
            "subcategory":"Advertising",
            "type":"Services"
        }
    ],
    "sg:phone":"+44 20 7734 0682",
    "sg:postcode":"W1F 9TU",
    "sg:province":"Greater London",
    "sg:tags":[
        "medium"
    ],
    "wof:name":"London International Advertising Awards Ltd.",
    "wof:placetype":"venue"
},
  "geometry": {"coordinates":[-0.1368139982,51.5109367371],"type":"Point"}
}