{
  "type": "Feature",
  "properties": {
    "addr:full":"P O Box 29, Pensnett Trading Estate Brierley Hill Staffordshire DY6 7NP",
    "addr:housenumber":"box 29",
    "addr:postcode":"dy6 7np",
    "addr:street":"P O;Trading Estate",
    "iso:country":"GB",
    "sg:address":"P O Box 29, Pensnett Trading Estate",
    "sg:city":"Brierley Hill",
    "sg:classifiers":[
        {
            "category":"Professional",
            "subcategory":"Engineering",
            "type":"Services"
        }
    ],
    "sg:phone":"+44 1384 401000",
    "sg:postcode":"DY6 7NP",
    "sg:province":"Staffordshire",
    "sg:tags":[
        "material"
    ],
    "sg:website":"http://www.kennametal.co.uk",
    "wof:name":"Kennametal Uk Ltd",
    "wof:placetype":"venue"
},
  "geometry": {"coordinates":[-2.1629400253,52.5050086975],"type":"Point"}
}