{
  "type": "Feature",
  "properties": {
    "iso:country":"GB",
    "sg:address":"8 James Square",
    "sg:city":"Crieff",
    "sg:classifiers":[
        {
            "category":"Food & Beverages",
            "subcategory":"Liquor & Beverages",
            "type":"Retail Goods"
        }
    ],
    "sg:phone":"+44 1764 652210",
    "sg:postcode":"PH7 3EY",
    "sg:province":"Perth and Kinross",
    "sg:tags":[
        "beer",
        "spirit",
        "wines"
    ],
    "wof:name":"Victoria Wine",
    "wof:placetype":"venue"
},
  "geometry": {"coordinates":[-3.84133,56.37307],"type":"Point"}
}