{
  "type": "Feature",
  "properties": {
    "iso:country":"GB",
    "sg:address":"52 Drury Lane",
    "sg:city":"Solihull",
    "sg:classifiers":[
        {
            "category":"Shopping",
            "subcategory":"Shoes",
            "type":"Retail Goods"
        }
    ],
    "sg:phone":"+44 121 704 2218",
    "sg:postcode":"B91 3BH",
    "sg:province":"West Midlands",
    "sg:tags":[
        "shop",
        "retailer",
        "footwear"
    ],
    "wof:name":"Le Scarpe Ltd",
    "wof:placetype":"venue"
},
  "geometry": {"coordinates":[-1.775241,52.413792],"type":"Point"}
}