{
  "type": "Feature",
  "properties": {
    "addr:full":"2 Crediton Avenue Stoke-on-trent Staffordshire ST6 7NE",
    "addr:housenumber":"2",
    "addr:postcode":"st6 7ne",
    "addr:street":"Crediton Avenue",
    "iso:country":"GB",
    "sg:address":"2 Crediton Avenue",
    "sg:city":"Stoke-on-trent",
    "sg:classifiers":[
        {
            "category":"Personal",
            "type":"Services"
        }
    ],
    "sg:phone":"+44 1782 822739",
    "sg:postcode":"ST6 7NE",
    "sg:province":"Staffordshire",
    "sg:tags":[
        "wedding"
    ],
    "wof:name":"Wedding Executive Hire",
    "wof:placetype":"venue"
},
  "geometry": {"coordinates":[-2.177072,53.06097],"type":"Point"}
}