{
  "type": "Feature",
  "properties": {
    "addr:full":"13 Queensland Avenue Redcar North Yorkshire TS10 2DT",
    "addr:housenumber":"13",
    "addr:postcode":"ts10 2dt",
    "addr:street":"Queensland Avenue",
    "iso:country":"GB",
    "sg:address":"13 Queensland Avenue",
    "sg:city":"Redcar",
    "sg:classifiers":[
        {
            "category":"Building & Trades",
            "subcategory":"Construction",
            "type":"Services"
        }
    ],
    "sg:postcode":"TS10 2DT",
    "sg:province":"North Yorkshire",
    "sg:tags":[
        "builder"
    ],
    "wof:name":"T Joyce Builder",
    "wof:placetype":"venue"
},
  "geometry": {"coordinates":[-1.0581610203,54.6101074219],"type":"Point"}
}