{
  "type": "Feature",
  "properties": {
    "iso:country":"GB",
    "sg:address":"Birchwood Road",
    "sg:city":"Swanley",
    "sg:classifiers":[
        {
            "category":"Bars & Pubs",
            "type":"Food & Drink"
        }
    ],
    "sg:phone":"+44 1322 662112",
    "sg:postcode":"BR8 7QA",
    "sg:province":"Kent",
    "sg:tags":[
        "pubs",
        "inn"
    ],
    "wof:name":"The Birchwood",
    "wof:placetype":"venue"
},
  "geometry": {"coordinates":[0.1607110053,51.4094047546],"type":"Point"}
}