{
  "type": "Feature",
  "properties": {
    "iso:country":"GB",
    "sg:address":"Lyndale, Waverbridge",
    "sg:city":"Wigton",
    "sg:classifiers":[
        {
            "category":"Building & Trades",
            "subcategory":"Construction",
            "type":"Services"
        }
    ],
    "sg:phone":"+44 16973 42675",
    "sg:postcode":"CA7 0DT",
    "sg:province":"Cumbria",
    "sg:tags":[
        "joiner",
        "carpenter"
    ],
    "wof:name":"Joseph Henry Fisher",
    "wof:placetype":"venue"
},
  "geometry": {"coordinates":[-3.2097249031,54.8303184509],"type":"Point"}
}