{
  "type": "Feature",
  "properties": {
    "addr:full":"Scalpay Ho, Isle Of Scalpay Isle Of Skye Highland IV49 9BS",
    "addr:postcode":"iv49 9bs",
    "addr:street":"Scalpay",
    "iso:country":"GB",
    "sg:address":"Scalpay Ho, Isle Of Scalpay",
    "sg:city":"Isle Of Skye",
    "sg:classifiers":[
        {
            "category":"Farming",
            "subcategory":"Livestock Farm",
            "type":"Manufacturing & Wholesale Goods"
        }
    ],
    "sg:phone":"+44 1471 822276",
    "sg:postcode":"IV49 9BS",
    "sg:province":"Highland",
    "sg:tags":[
        "others"
    ],
    "wof:name":"Scalpay Broadford",
    "wof:placetype":"venue"
},
  "geometry": {"coordinates":[-5.9710898399,57.2982215881],"type":"Point"}
}