{
  "type": "Feature",
  "properties": {
    "addr:full":"Market Street, Goldthorpe Rotherham South Yorkshire S63 9HB",
    "addr:postcode":"s63 9hb",
    "addr:street":"Market Street",
    "iso:country":"GB",
    "sg:address":"Market Street, Goldthorpe",
    "sg:city":"Rotherham",
    "sg:classifiers":[
        {
            "category":"Shopping",
            "subcategory":"Clothing, Apparel, & Fashions",
            "type":"Retail Goods"
        }
    ],
    "sg:phone":"+44 1709 894575",
    "sg:postcode":"S63 9HB",
    "sg:province":"South Yorkshire",
    "sg:tags":[
        "workwear",
        "protective"
    ],
    "wof:name":"Portwest Clothing Ltd.",
    "wof:placetype":"venue"
},
  "geometry": {"coordinates":[-1.304249,53.532574],"type":"Point"}
}