{
  "type": "Feature",
  "properties": {
    "addr:full":"Yardley Grange, 389 Church Rd, Yardley Birmingham West Midlands B33 8PA",
    "addr:housenumber":"389",
    "addr:postcode":"b33 8pa",
    "addr:street":"Church Rd",
    "iso:country":"GB",
    "sg:address":"Yardley Grange, 389 Church Rd, Yardley",
    "sg:city":"Birmingham",
    "sg:classifiers":[
        {
            "category":"Health Services",
            "subcategory":"Nursing And Care Facility",
            "type":"Services"
        }
    ],
    "sg:phone":"+44 121 789 7188",
    "sg:postcode":"B33 8PA",
    "sg:province":"West Midlands",
    "sg:tags":[
        "home"
    ],
    "wof:name":"Yardley Great Trust",
    "wof:placetype":"venue"
},
  "geometry": {"coordinates":[-1.8032599688,52.4742088318],"type":"Point"}
}