{
  "type": "Feature",
  "properties": {
    "addr:full":"Unit B8, Stuart House, Kemp Rd Dagenham Essex RM8 1SL",
    "addr:postcode":"rm8 1sl",
    "addr:street":"Kemp Rd",
    "iso:country":"GB",
    "sg:address":"Unit B8, Stuart House, Kemp Rd",
    "sg:city":"Dagenham",
    "sg:classifiers":[
        {
            "category":"Professional",
            "subcategory":"Management & Consulting",
            "type":"Services"
        }
    ],
    "sg:phone":"+44 20 8590 1885",
    "sg:postcode":"RM8 1SL",
    "sg:province":"Essex",
    "sg:tags":[
        "consultant",
        "promotion",
        "sale"
    ],
    "wof:name":"First Contact",
    "wof:placetype":"venue"
},
  "geometry": {"coordinates":[0.1314249933,51.5645713806],"type":"Point"}
}