{
  "type": "Feature",
  "properties": {
    "addr:full":"84 Gallowgate Street Largs North Ayrshire KA30 8LZ",
    "addr:housenumber":"84",
    "addr:postcode":"ka30 8lz",
    "addr:street":"Gallowgate Street",
    "iso:country":"GB",
    "sg:address":"84 Gallowgate Street",
    "sg:city":"Largs",
    "sg:classifiers":[
        {
            "category":"Restaurant",
            "type":"Food & Drink"
        }
    ],
    "sg:phone":"+44 1475 686051",
    "sg:postcode":"KA30 8LZ",
    "sg:province":"North Ayrshire",
    "sg:tags":[
        "indian"
    ],
    "wof:name":"Koh-I-Noor Restaurant",
    "wof:placetype":"venue"
},
  "geometry": {"coordinates":[-4.869037,55.796608],"type":"Point"}
}