{
  "type": "Feature",
  "properties": {
    "addr:full":"25 Highfield Drive, Gildersome, Morley Leeds West Yorkshire LS27 7DW",
    "addr:housenumber":"25",
    "addr:postcode":"ls27 7dw",
    "addr:street":"Highfield Drive",
    "iso:country":"GB",
    "sg:address":"25 Highfield Drive, Gildersome, Morley",
    "sg:city":"Leeds",
    "sg:classifiers":[
        {
            "category":"Professional",
            "type":"Services"
        },
        {
            "category":"Professional",
            "subcategory":"Employment Agencies",
            "type":"Services"
        }
    ],
    "sg:phone":"+44 113 253 0983",
    "sg:postcode":"LS27 7DW",
    "sg:province":"West Yorkshire",
    "sg:tags":[
        "entertainer",
        "entertainment"
    ],
    "wof:name":"John Wall Enterprises",
    "wof:placetype":"venue"
},
  "geometry": {"coordinates":[-1.6246659756,53.7595787048],"type":"Point"}
}