{
  "type": "Feature",
  "properties": {
    "addr:full":"85 Hathaway Road Swindon Wiltshire SN2 7TY",
    "addr:housenumber":"85",
    "addr:postcode":"sn2 7ty",
    "addr:street":"Hathaway Road",
    "iso:country":"GB",
    "sg:address":"85 Hathaway Road",
    "sg:city":"Swindon",
    "sg:classifiers":[
        {
            "category":"Parking",
            "type":"Transportation"
        }
    ],
    "sg:postcode":"SN2 7TY",
    "sg:province":"Wiltshire",
    "sg:tags":[
        "car",
        "valet"
    ],
    "wof:name":"Clean Wheels",
    "wof:placetype":"venue"
},
  "geometry": {"coordinates":[-1.7700300217,51.5909500122],"type":"Point"}
}