{
  "type": "Feature",
  "properties": {
    "addr:full":"2 The Avenue Leeds North Yorkshire LS17 7BE",
    "addr:housenumber":"2",
    "addr:postcode":"ls17 7be",
    "addr:street":"The Avenue",
    "iso:country":"GB",
    "sg:address":"2 The Avenue",
    "sg:city":"Leeds",
    "sg:classifiers":[
        {
            "category":"Shopping",
            "subcategory":"Pharmacy",
            "type":"Retail Goods"
        }
    ],
    "sg:phone":"+44 113 267 3470",
    "sg:postcode":"LS17 7BE",
    "sg:province":"North Yorkshire",
    "sg:tags":[
        "pharmacist",
        "chemist"
    ],
    "wof:name":"Hills Pharmacy",
    "wof:placetype":"venue"
},
  "geometry": {"coordinates":[-1.562948,53.856625],"type":"Point"}
}