{
  "type": "Feature",
  "properties": {
    "addr:full":"12 Nuffield Court, Bennett Crescent, Cowley Oxford Oxfordshire OX4 2UN",
    "addr:housenumber":"12",
    "addr:postcode":"ox4 2un",
    "addr:street":"Nuffield Court Bennett Crescent",
    "iso:country":"GB",
    "sg:address":"12 Nuffield Court, Bennett Crescent, Cowley",
    "sg:city":"Oxford",
    "sg:classifiers":[
        {
            "category":"Building & Trades",
            "subcategory":"Construction",
            "type":"Services"
        }
    ],
    "sg:phone":"+44 1865 749499",
    "sg:postcode":"OX4 2UN",
    "sg:province":"Oxfordshire",
    "sg:tags":[
        "decorator",
        "painter"
    ],
    "wof:name":"Redec Interiors Builders & Decorators",
    "wof:placetype":"venue"
},
  "geometry": {"coordinates":[-1.210014,51.733753],"type":"Point"}
}