{
  "type": "Feature",
  "properties": {
    "iso:country":"GB",
    "sg:address":"39 Knights Hill",
    "sg:city":"London",
    "sg:classifiers":[
        {
            "category":"Food & Beverages",
            "subcategory":"Meat & Fish",
            "type":"Retail Goods"
        }
    ],
    "sg:phone":"+44 20 8670 5111",
    "sg:postcode":"SE27 0HS",
    "sg:province":"Greater London",
    "sg:tags":[
        "chip"
    ],
    "wof:name":"Knights Fish Bar",
    "wof:placetype":"venue"
},
  "geometry": {"coordinates":[-0.104187,51.430496],"type":"Point"}
}