{
  "type": "Feature",
  "properties": {
    "addr:full":"20 Tadworth Parade Hornchurch Essex RM12 5AS",
    "addr:housenumber":"20",
    "addr:postcode":"rm12 5as",
    "addr:street":"Tadworth Parade",
    "iso:country":"GB",
    "sg:address":"20 Tadworth Parade",
    "sg:city":"Hornchurch",
    "sg:classifiers":[
        {
            "category":"Shopping",
            "subcategory":"Gifts & Souvenirs",
            "type":"Retail Goods"
        }
    ],
    "sg:postcode":"RM12 5AS",
    "sg:province":"Essex",
    "sg:tags":[
        "poster",
        "card"
    ],
    "wof:name":"Greetings",
    "wof:placetype":"venue"
},
  "geometry": {"coordinates":[0.199792996,51.5489120483],"type":"Point"}
}