{
  "type": "Feature",
  "properties": {
    "addr:full":"Marston Ferry Road Oxford Oxfordshire OX2 7EE",
    "addr:postcode":"ox2 7ee",
    "addr:street":"Marston Ferry Road",
    "iso:country":"GB",
    "sg:address":"Marston Ferry Road",
    "sg:city":"Oxford",
    "sg:classifiers":[
        {
            "category":"Arena",
            "subcategory":"Sports Club",
            "type":"Entertainment"
        }
    ],
    "sg:phone":"+44 1865 552813",
    "sg:postcode":"OX2 7EE",
    "sg:province":"Oxfordshire",
    "wof:name":"Oxford Harlequins",
    "wof:placetype":"venue"
},
  "geometry": {"coordinates":[-1.262619,51.774361],"type":"Point"}
}