{
  "type": "Feature",
  "properties": {
    "iso:country":"GB",
    "sg:address":"60 The Thoroughfare",
    "sg:city":"Halesworth",
    "sg:classifiers":[
        {
            "category":"Shopping",
            "subcategory":"Shoes",
            "type":"Retail Goods"
        }
    ],
    "sg:postcode":"IP19 8AR",
    "sg:province":"Suffolk",
    "sg:tags":[
        "shop"
    ],
    "wof:name":"Doris M Spall",
    "wof:placetype":"venue"
},
  "geometry": {"coordinates":[1.5017579794,52.344039917],"type":"Point"}
}