{
  "type": "Feature",
  "properties": {
    "iso:country":"GB",
    "sg:address":"105 High St",
    "sg:city":"Slough",
    "sg:classifiers":[
        {
            "category":"Restaurant",
            "type":"Food & Drink"
        }
    ],
    "sg:phone":"+44 1753 537887",
    "sg:postcode":"SL1 1DH",
    "sg:province":"Berkshire",
    "wof:name":"Harry's Bar & Restaurant",
    "wof:placetype":"venue"
},
  "geometry": {"coordinates":[-0.595073998,51.509513855],"type":"Point"}
}