{
  "type": "Feature",
  "properties": {
    "iso:country":"GB",
    "sg:address":"20-21 Far Gosford Street",
    "sg:city":"Coventry",
    "sg:classifiers":[
        {
            "category":"Fast Food",
            "type":"Food & Drink"
        }
    ],
    "sg:phone":"+44 24 7622 9651",
    "sg:postcode":"CV1 5DT",
    "sg:province":"West Midlands",
    "sg:tags":[
        "away",
        "take"
    ],
    "wof:name":"Monsoon Tandoori & Balti Restaurant",
    "wof:placetype":"venue"
},
  "geometry": {"coordinates":[-1.497934,52.407459],"type":"Point"}
}