{
  "type": "Feature",
  "properties": {
    "addr:full":"11 Henderson Road Sunderland Tyne and Wear SR4 7TG",
    "addr:housenumber":"11",
    "addr:postcode":"sr4 7tg",
    "addr:street":"Henderson Road",
    "iso:country":"GB",
    "sg:address":"11 Henderson Road",
    "sg:city":"Sunderland",
    "sg:classifiers":[
        {
            "category":"Banks & Credit Unions",
            "subcategory":"Financial Services",
            "type":"Services"
        }
    ],
    "sg:phone":"+44 191 565 2100",
    "sg:postcode":"SR4 7TG",
    "sg:province":"Tyne and Wear",
    "sg:tags":[
        "consultant",
        "pension"
    ],
    "wof:name":"Keyline Mortgage & Financial Services",
    "wof:placetype":"venue"
},
  "geometry": {"coordinates":[-1.4127379656,54.9025917053],"type":"Point"}
}