{
  "type": "Feature",
  "properties": {
    "addr:full":"48 Chaseside Avenue, Twyford Reading Berkshire RG10 9BT",
    "addr:housenumber":"48",
    "addr:postcode":"rg10 9bt",
    "addr:street":"Chaseside Avenue",
    "iso:country":"GB",
    "sg:address":"48 Chaseside Avenue, Twyford",
    "sg:city":"Reading",
    "sg:classifiers":[
        {
            "category":"Professional",
            "subcategory":"Computer Services",
            "type":"Services"
        }
    ],
    "sg:phone":"+44 7973 259143",
    "sg:postcode":"RG10 9BT",
    "sg:province":"Berkshire",
    "sg:tags":[
        "development",
        "system",
        "software"
    ],
    "wof:name":"Green Room Gb Ltd.",
    "wof:placetype":"venue"
},
  "geometry": {"coordinates":[-0.867977,51.486225],"type":"Point"}
}