{
  "type": "Feature",
  "properties": {
    "addr:full":"30 Eleanor Crescent Newcastle Staffordshire ST5 3SA",
    "addr:housenumber":"30",
    "addr:postcode":"st5 3sa",
    "addr:street":"Eleanor Crescent",
    "iso:country":"GB",
    "sg:address":"30 Eleanor Crescent",
    "sg:city":"Newcastle",
    "sg:classifiers":[
        {
            "category":"Home & Garden",
            "subcategory":"Household Appliances",
            "type":"Retail Goods"
        }
    ],
    "sg:postcode":"ST5 3SA",
    "sg:province":"Staffordshire",
    "sg:tags":[
        "electrical"
    ],
    "wof:name":"Refrigeration Service & Maintenance",
    "wof:placetype":"venue"
},
  "geometry": {"coordinates":[-2.231188,53.001022],"type":"Point"}
}