{
  "type": "Feature",
  "properties": {
    "addr:full":"30 Trinity Road Rayleigh Essex SS6 8QD",
    "addr:housenumber":"30",
    "addr:postcode":"ss6 8qd",
    "addr:street":"Trinity Road Rayleigh",
    "iso:country":"GB",
    "sg:address":"30 Trinity Road",
    "sg:city":"Rayleigh",
    "sg:classifiers":[
        {
            "category":"Shopping",
            "subcategory":"Musical Instruments",
            "type":"Retail Goods"
        }
    ],
    "sg:postcode":"SS6 8QD",
    "sg:province":"Essex",
    "wof:name":"Antony W Fisher",
    "wof:placetype":"venue"
},
  "geometry": {"coordinates":[0.614937,51.582714],"type":"Point"}
}