{
  "type": "Feature",
  "properties": {
    "iso:country":"GB",
    "sg:address":"Appledore, Coleshill Lane, Winchmore Hill",
    "sg:city":"Amersham",
    "sg:classifiers":[
        {
            "category":"Building & Trades",
            "subcategory":"Plumbing",
            "type":"Services"
        }
    ],
    "sg:postcode":"HP7 0NP",
    "sg:province":"Buckinghamshire",
    "sg:tags":[
        "central",
        "heating"
    ],
    "wof:name":"M S Wingrove",
    "wof:placetype":"venue"
},
  "geometry": {"coordinates":[-0.6545799971,51.6479034424],"type":"Point"}
}