{
  "type": "Feature",
  "properties": {
    "addr:full":"52 Upper St Islington Greater London N1 0QH",
    "addr:housenumber":"52",
    "addr:postcode":"n1 0qh",
    "addr:street":"Upper St",
    "iso:country":"GB",
    "sg:address":"52 Upper St",
    "sg:city":"Islington",
    "sg:classifiers":[
        {
            "category":"Arts & Performance",
            "subcategory":"Theater",
            "type":"Entertainment"
        }
    ],
    "sg:phone":"+44 20 7226 5256",
    "sg:postcode":"N1 0QH",
    "sg:province":"Greater London",
    "sg:tags":[
        "theatrical",
        "agency"
    ],
    "wof:name":"Manhattan Management & Marketing Ltd",
    "wof:placetype":"venue"
},
  "geometry": {"coordinates":[-0.1043369994,51.5353736877],"type":"Point"}
}