{
  "type": "Feature",
  "properties": {
    "addr:full":"Suite 4 Town House, The Parade Telford Shropshire TF1 1PY",
    "addr:housenumber":"suite 4",
    "addr:postcode":"tf1 1py",
    "addr:street":"Town;The Parade",
    "iso:country":"GB",
    "sg:address":"Suite 4 Town House, The Parade",
    "sg:city":"Telford",
    "sg:classifiers":[
        {
            "category":"Health Services",
            "subcategory":"Dentist",
            "type":"Services"
        }
    ],
    "sg:postcode":"TF1 1PY",
    "sg:province":"Shropshire",
    "wof:name":"Mark Davies",
    "wof:placetype":"venue"
},
  "geometry": {"coordinates":[-2.5163199902,52.7008895874],"type":"Point"}
}