{
  "type": "Feature",
  "properties": {
    "iso:country":"GB",
    "sg:address":"26 Pennine View, Upton",
    "sg:city":"Pontefract",
    "sg:classifiers":[
        {
            "category":"Retail",
            "subcategory":"Repair Shop",
            "type":"Services"
        }
    ],
    "sg:phone":"+44 1977 645353",
    "sg:postcode":"WF9 1LZ",
    "sg:province":"West Yorkshire",
    "sg:tags":[
        "maintenance"
    ],
    "wof:name":"Pearbax Builders",
    "wof:placetype":"venue"
},
  "geometry": {"coordinates":[-1.285626,53.617115],"type":"Point"}
}