{
  "type": "Feature",
  "properties": {
    "iso:country":"GB",
    "sg:address":"22 Ainslie Place",
    "sg:city":"Edinburgh",
    "sg:classifiers":[
        {
            "category":"Professional",
            "subcategory":"Lawyer & Legal Services",
            "type":"Services"
        }
    ],
    "sg:postcode":"EH3 6AJ",
    "sg:province":"City of Edinburgh",
    "sg:tags":[
        "solicitor"
    ],
    "wof:name":"Bishop & Robertson Chalmers",
    "wof:placetype":"venue"
},
  "geometry": {"coordinates":[-3.2093958855,55.9532775879],"type":"Point"}
}