{
  "type": "Feature",
  "properties": {
    "addr:full":"Northallerton Rd Northallerton North Yorkshire DL7 9AA",
    "addr:postcode":"dl7 9aa",
    "addr:street":"Northallerton Rd",
    "iso:country":"GB",
    "sg:address":"Northallerton Rd",
    "sg:city":"Northallerton",
    "sg:classifiers":[
        {
            "category":"Shopping",
            "subcategory":"Department Store",
            "type":"Retail Goods"
        }
    ],
    "sg:phone":"+44 1677 422413",
    "sg:postcode":"DL7 9AA",
    "sg:province":"North Yorkshire",
    "wof:name":"E & T Taylor",
    "wof:placetype":"venue"
},
  "geometry": {"coordinates":[-1.5530120134,54.3078041077],"type":"Point"}
}