{
  "type": "Feature",
  "properties": {
    "addr:full":"1 Stoneyfield Road Coulsdon Surrey CR5 2HP",
    "addr:housenumber":"1",
    "addr:postcode":"cr5 2hp",
    "addr:street":"Stoneyfield Road",
    "iso:country":"GB",
    "sg:address":"1 Stoneyfield Road",
    "sg:city":"Coulsdon",
    "sg:classifiers":[
        {
            "category":"Building & Trades",
            "subcategory":"Construction",
            "type":"Services"
        }
    ],
    "sg:postcode":"CR5 2HP",
    "sg:province":"Surrey",
    "sg:tags":[
        "builder"
    ],
    "wof:name":"J W C Builders",
    "wof:placetype":"venue"
},
  "geometry": {"coordinates":[-0.1235880032,51.3123321533],"type":"Point"}
}