{
  "type": "Feature",
  "properties": {
    "iso:country":"GB",
    "sg:address":"16 Parkstone Close",
    "sg:city":"Bedford",
    "sg:classifiers":[
        {
            "category":"Professional",
            "subcategory":"Accounting & Tax Preparation",
            "type":"Services"
        }
    ],
    "sg:phone":"+44 1234 300222",
    "sg:postcode":"MK41 8BD",
    "sg:province":"Bedfordshire",
    "sg:tags":[
        "accountant"
    ],
    "wof:name":"Ron Simmonds Associates",
    "wof:placetype":"venue"
},
  "geometry": {"coordinates":[-0.44891,52.160732],"type":"Point"}
}