{
  "type": "Feature",
  "properties": {
    "iso:country":"GB",
    "sg:address":"46 Park Rd, Low Moor",
    "sg:city":"Bradford",
    "sg:classifiers":[
        {
            "category":"Shopping",
            "subcategory":"Party Supplies",
            "type":"Retail Goods"
        }
    ],
    "sg:phone":"+44 1274 416710",
    "sg:postcode":"BD12 0DL",
    "sg:province":"West Yorkshire",
    "sg:tags":[
        "inflatables",
        "bouncy",
        "castle"
    ],
    "wof:name":"Jump Around",
    "wof:placetype":"venue"
},
  "geometry": {"coordinates":[-1.772039,53.756481],"type":"Point"}
}