{
  "type": "Feature",
  "properties": {
    "iso:country":"GB",
    "sg:address":"65 Penny Meadow",
    "sg:city":"Ashton-under-lyne",
    "sg:classifiers":[
        {
            "category":"Home & Garden",
            "subcategory":"Furniture",
            "type":"Retail Goods"
        }
    ],
    "sg:postcode":"OL6 6EL",
    "sg:province":"Greater Manchester",
    "wof:name":"Bunbury,Gary,",
    "wof:placetype":"venue"
},
  "geometry": {"coordinates":[-2.0895650387,53.4899215698],"type":"Point"}
}