{
  "type": "Feature",
  "properties": {
    "addr:full":"256 South Road Sheffield South Yorkshire S6 3TB",
    "addr:housenumber":"256",
    "addr:postcode":"s6 3tb",
    "addr:street":"South Road",
    "iso:country":"GB",
    "sg:address":"256 South Road",
    "sg:city":"Sheffield",
    "sg:classifiers":[
        {
            "category":"Personal",
            "subcategory":"Beauty Salon",
            "type":"Services"
        }
    ],
    "sg:phone":"+44 114 232 2400",
    "sg:postcode":"S6 3TB",
    "sg:province":"South Yorkshire",
    "sg:tags":[
        "unisex",
        "hairdresser"
    ],
    "wof:name":"Curl Up & Dye",
    "wof:placetype":"venue"
},
  "geometry": {"coordinates":[-1.49967,53.392296],"type":"Point"}
}