{
  "type": "Feature",
  "properties": {
    "iso:country":"GB",
    "sg:address":"14 Hillgrove Crescent",
    "sg:city":"Kidderminster",
    "sg:classifiers":[
        {
            "category":"Professional",
            "subcategory":"Management & Consulting",
            "type":"Services"
        }
    ],
    "sg:phone":"+44 1562 861096",
    "sg:postcode":"DY10 3AP",
    "sg:province":"Staffordshire",
    "sg:tags":[
        "consultant",
        "business"
    ],
    "wof:name":"Morton Hodson Management Consultants",
    "wof:placetype":"venue"
},
  "geometry": {"coordinates":[-2.230884,52.382584],"type":"Point"}
}