{
  "type": "Feature",
  "properties": {
    "iso:country":"GB",
    "sg:address":"The Forum Centre, Bridgegate",
    "sg:city":"Irvine",
    "sg:classifiers":[
        {
            "category":"Shopping",
            "subcategory":"Department Store",
            "type":"Retail Goods"
        }
    ],
    "sg:phone":"+44 1294 466241",
    "sg:postcode":"KA12 8BQ",
    "sg:province":"North Ayrshire",
    "wof:name":"Fairways",
    "wof:placetype":"venue"
},
  "geometry": {"coordinates":[-4.6732587814,55.6019744873],"type":"Point"}
}