{
  "type": "Feature",
  "properties": {
    "iso:country":"GB",
    "sg:address":"65 High Street",
    "sg:city":"Cowes",
    "sg:classifiers":[
        {
            "category":"Shopping",
            "subcategory":"Books",
            "type":"Retail Goods"
        }
    ],
    "sg:postcode":"PO31 7RL",
    "sg:province":"Isle of Wight",
    "sg:tags":[
        "second-hand"
    ],
    "wof:name":"Charles Dickens Bookshop",
    "wof:placetype":"venue"
},
  "geometry": {"coordinates":[-1.298898,50.764462],"type":"Point"}
}