{
  "type": "Feature",
  "properties": {
    "iso:country":"GB",
    "sg:address":"19 Hay Street, Coupar Angus",
    "sg:city":"Blairgowrie",
    "sg:classifiers":[
        {
            "category":"Professional",
            "subcategory":"Art Services",
            "type":"Services"
        },
        {
            "category":"Building & Trades",
            "subcategory":"Construction",
            "type":"Services"
        }
    ],
    "sg:phone":"+44 1828 628193",
    "sg:postcode":"PH13 9BE",
    "sg:province":"Angus",
    "sg:tags":[
        "decorator",
        "painter"
    ],
    "wof:name":"Dick Mckay",
    "wof:placetype":"venue"
},
  "geometry": {"coordinates":[-3.2686309814,56.5481491089],"type":"Point"}
}