{
  "type": "Feature",
  "properties": {
    "addr:full":"Top Town Market, Freshney Place Grimsby Lincolnshire DN31 1AA",
    "addr:postcode":"dn31 1aa",
    "addr:street":"Place Grimsby",
    "iso:country":"GB",
    "sg:address":"Top Town Market, Freshney Place",
    "sg:city":"Grimsby",
    "sg:classifiers":[
        {
            "category":"Shopping",
            "subcategory":"Comic Books",
            "type":"Retail Goods"
        }
    ],
    "sg:phone":"+44 1472 361692",
    "sg:postcode":"DN31 1AA",
    "sg:province":"Lincolnshire",
    "sg:tags":[
        "jeweller"
    ],
    "wof:name":"Ian Crawford Jewellery",
    "wof:placetype":"venue"
},
  "geometry": {"coordinates":[-0.0849,53.565231],"type":"Point"}
}