{
  "type": "Feature",
  "properties": {
    "iso:country":"GB",
    "sg:address":"Barn Cottage, Church Street, Hampstead Norreys",
    "sg:city":"Thatcham",
    "sg:classifiers":[
        {
            "category":"Building & Trades",
            "subcategory":"Construction",
            "type":"Services"
        }
    ],
    "sg:phone":"+44 1635 201089",
    "sg:postcode":"RG18 0TB",
    "sg:province":"Berkshire",
    "sg:tags":[
        "builder"
    ],
    "wof:name":"R H Caesar",
    "wof:placetype":"venue"
},
  "geometry": {"coordinates":[-1.238813,51.483204],"type":"Point"}
}