{
  "type": "Feature",
  "properties": {
    "iso:country":"GB",
    "sg:address":"134 Moss Gro, Kingswinford",
    "sg:city":"Brierley Hill",
    "sg:classifiers":[
        {
            "category":"Shopping",
            "subcategory":"Discount & Variety Stores",
            "type":"Retail Goods"
        }
    ],
    "sg:phone":"+44 1384 400085",
    "sg:postcode":"DY6 9ES",
    "sg:province":"Staffordshire",
    "sg:tags":[
        "shop",
        "model"
    ],
    "wof:name":"Penn Models",
    "wof:placetype":"venue"
},
  "geometry": {"coordinates":[-2.1703000069,52.5032691956],"type":"Point"}
}