{
  "type": "Feature",
  "properties": {
    "iso:country":"GB",
    "sg:address":"Duncan House, Dolphin Square",
    "sg:city":"London",
    "sg:classifiers":[
        {
            "category":"Professional",
            "subcategory":"Business Services",
            "type":"Services"
        }
    ],
    "sg:phone":"+44 20 7828 9465",
    "sg:postcode":"SW1V 3PW",
    "sg:province":"Greater London",
    "sg:tags":[
        "trade"
    ],
    "wof:name":"The Sugar Bureau",
    "wof:placetype":"venue"
},
  "geometry": {"coordinates":[-0.135411,51.486568],"type":"Point"}
}