{
  "type": "Feature",
  "properties": {
    "iso:country":"GB",
    "sg:address":"Phoenix House, 27 King Street",
    "sg:city":"North Shields",
    "sg:classifiers":[
        {
            "category":"Organizations",
            "subcategory":"Community Association",
            "type":"Services"
        },
        {
            "category":"Organizations",
            "subcategory":"Membership Organization",
            "type":"Services"
        }
    ],
    "sg:phone":"+44 191 290 0473",
    "sg:postcode":"NE30 1BZ",
    "sg:province":"Tyne and Wear",
    "sg:tags":[
        "club",
        "social"
    ],
    "wof:name":"KING STREET SOCIAL CLUB & INSTITUTE LTD",
    "wof:placetype":"venue"
},
  "geometry": {"coordinates":[-1.440503,55.011913],"type":"Point"}
}