{
  "type": "Feature",
  "properties": {
    "addr:full":"Dalmally Road Inveraray Argyll and Bute PA32 8XD",
    "addr:postcode":"pa32 8xd",
    "addr:street":"Dalmally Road",
    "iso:country":"GB",
    "sg:address":"Dalmally Road",
    "sg:city":"Inveraray",
    "sg:classifiers":[
        {
            "category":"Autos & Motor Vehicles",
            "subcategory":"Fuel & Gas Station",
            "type":"Retail Goods"
        }
    ],
    "sg:phone":"+44 1499 302289",
    "sg:postcode":"PA32 8XD",
    "sg:province":"Argyll and Bute",
    "sg:tags":[
        "petrol",
        "filling"
    ],
    "wof:name":"Arch Filling Station",
    "wof:placetype":"venue"
},
  "geometry": {"coordinates":[-5.07249403,56.2314453125],"type":"Point"}
}