{
  "type": "Feature",
  "properties": {
    "addr:full":"25 B Under Wood Street London Greater London N1 7LG",
    "addr:housenumber":"25 b",
    "addr:postcode":"n1 7lg",
    "addr:street":"Under Wood Street",
    "iso:country":"GB",
    "sg:address":"25 B Under Wood Street",
    "sg:city":"London",
    "sg:classifiers":[
        {
            "category":"Real Estate",
            "subcategory":"Architect",
            "type":"Services"
        }
    ],
    "sg:phone":"+44 20 7251 8888",
    "sg:postcode":"N1 7LG",
    "sg:province":"Greater London",
    "wof:name":"Zombory Moldovan Moore",
    "wof:placetype":"venue"
},
  "geometry": {"coordinates":[-0.091968,51.529922],"type":"Point"}
}