{
  "type": "Feature",
  "properties": {
    "addr:full":"18 Derby Square Loughborough Leicestershire LE11 5AL",
    "addr:housenumber":"18",
    "addr:postcode":"le11 5al",
    "addr:street":"Derby Square",
    "iso:country":"GB",
    "sg:address":"18 Derby Square",
    "sg:city":"Loughborough",
    "sg:classifiers":[
        {
            "category":"Communications",
            "subcategory":"Newspaper",
            "type":"Services"
        }
    ],
    "sg:phone":"+44 1509 618740",
    "sg:postcode":"LE11 5AL",
    "sg:province":"Leicestershire",
    "sg:tags":[
        "magazine"
    ],
    "wof:name":"Swimming Times Publications",
    "wof:placetype":"venue"
},
  "geometry": {"coordinates":[-1.207748,52.7724],"type":"Point"}
}