{
  "type": "Feature",
  "properties": {
    "iso:country":"GB",
    "sg:address":"Ley Farm",
    "sg:city":"Fordingbridge",
    "sg:classifiers":[
        {
            "category":"Shopping",
            "type":"Retail Goods"
        }
    ],
    "sg:phone":"+44 1725 517100",
    "sg:postcode":"SP6 3EB",
    "sg:province":"Dorset",
    "sg:tags":[
        "merchant"
    ],
    "wof:name":"One Stop Genetics",
    "wof:placetype":"venue"
},
  "geometry": {"coordinates":[-1.8471829891,50.9343109131],"type":"Point"}
}