{
  "type": "Feature",
  "properties": {
    "iso:country":"GB",
    "sg:address":"Unit 7, Skurrays Development, George Lane",
    "sg:city":"Marlborough",
    "sg:classifiers":[
        {
            "category":"Autos & Motor Vehicles",
            "subcategory":"Auto Supplies",
            "type":"Retail Goods"
        }
    ],
    "sg:phone":"+44 1672 513713",
    "sg:postcode":"SN8 4DA",
    "sg:province":"Berkshire",
    "sg:tags":[
        "exhaust",
        "absorber",
        "shock"
    ],
    "wof:name":"Checkpoint",
    "wof:placetype":"venue"
},
  "geometry": {"coordinates":[-1.7298890352,51.421333313],"type":"Point"}
}