{
  "type": "Feature",
  "properties": {
    "iso:country":"GB",
    "sg:address":"5 South East Circus Place",
    "sg:city":"Edinburgh",
    "sg:classifiers":[
        {
            "category":"Professional",
            "subcategory":"Engineering",
            "type":"Services"
        },
        {
            "category":"Social Services",
            "subcategory":"Job Training",
            "type":"Services"
        }
    ],
    "sg:postcode":"EH3 6TJ",
    "sg:province":"City of Edinburgh",
    "sg:tags":[
        "translator",
        "interpreter",
        "consulting",
        "engineer"
    ],
    "wof:name":"Italien Translations",
    "wof:placetype":"venue"
},
  "geometry": {"coordinates":[-3.203111,55.956776],"type":"Point"}
}