{
  "type": "Feature",
  "properties": {
    "iso:country":"GB",
    "sg:address":"501 Leeds & Bradford Rd",
    "sg:city":"Leeds",
    "sg:classifiers":[
        {
            "category":"Professional",
            "subcategory":"Detective & Security Services",
            "type":"Services"
        }
    ],
    "sg:phone":"+44 113 236 1600",
    "sg:postcode":"LS13 2AG",
    "sg:province":"West Yorkshire",
    "sg:tags":[
        "alarm",
        "burglar",
        "system"
    ],
    "wof:name":"Direct Alarms",
    "wof:placetype":"venue"
},
  "geometry": {"coordinates":[-1.639038,53.817272],"type":"Point"}
}