{
  "type": "Feature",
  "properties": {
    "iso:country":"GB",
    "sg:address":"106 High Road, South Tottenham",
    "sg:city":"London",
    "sg:classifiers":[
        {
            "category":"Health Services",
            "subcategory":"Doctor",
            "type":"Services"
        },
        {
            "category":"Health Services",
            "subcategory":"Dentist",
            "type":"Services"
        }
    ],
    "sg:phone":"+44 20 8800 1326",
    "sg:postcode":"N15 6JR",
    "sg:province":"Greater London",
    "wof:name":"P R & R K PATEL",
    "wof:placetype":"venue"
},
  "geometry": {"coordinates":[-0.0728629977,51.5784339905],"type":"Point"}
}