{
  "type": "Feature",
  "properties": {
    "addr:full":"Studford Gill Farm, Tosside Skipton Lancashire BD23 4SU",
    "addr:postcode":"bd23 4su",
    "addr:street":"Tosside",
    "iso:country":"GB",
    "sg:address":"Studford Gill Farm, Tosside",
    "sg:city":"Skipton",
    "sg:classifiers":[
        {
            "category":"Farming",
            "subcategory":"Livestock Farm",
            "type":"Manufacturing & Wholesale Goods"
        }
    ],
    "sg:postcode":"BD23 4SU",
    "sg:province":"Lancashire",
    "sg:tags":[
        "others"
    ],
    "wof:name":"S Taylor",
    "wof:placetype":"venue"
},
  "geometry": {"coordinates":[-2.353539,53.999981],"type":"Point"}
}