{
  "type": "Feature",
  "properties": {
    "iso:country":"GB",
    "sg:address":"158 Trafalgar Road",
    "sg:city":"London",
    "sg:classifiers":[
        {
            "category":"Shopping",
            "subcategory":"Pharmacy",
            "type":"Retail Goods"
        }
    ],
    "sg:phone":"+44 20 8858 1463",
    "sg:postcode":"SE10 9TZ",
    "sg:province":"Greater London",
    "sg:tags":[
        "pharmacist",
        "dispensing",
        "chemist"
    ],
    "wof:name":"Metex Pharmacy",
    "wof:placetype":"venue"
},
  "geometry": {"coordinates":[0.0036319999,51.4847068787],"type":"Point"}
}