{
  "type": "Feature",
  "properties": {
    "iso:country":"GB",
    "sg:address":"34 Ernest Road, Wivenhoe",
    "sg:city":"Colchester",
    "sg:classifiers":[
        {
            "category":"Health Services",
            "subcategory":"Health Practitioner",
            "type":"Services"
        }
    ],
    "sg:phone":"+44 1206 825333",
    "sg:postcode":"CO7 9LQ",
    "sg:province":"Essex",
    "sg:tags":[
        "hypnotherapists"
    ],
    "wof:name":"Aware Consultancy",
    "wof:placetype":"venue"
},
  "geometry": {"coordinates":[0.9614539742,51.8611602783],"type":"Point"}
}