{
  "type": "Feature",
  "properties": {
    "addr:full":"Chorlton Office, 102 Manchester Rd Manchester Cheshire M21 9SZ",
    "addr:housenumber":"102",
    "addr:postcode":"m21 9sz",
    "addr:street":"Manchester Rd",
    "iso:country":"GB",
    "sg:address":"Chorlton Office, 102 Manchester Rd",
    "sg:city":"Manchester",
    "sg:classifiers":[
        {
            "category":"Social Services",
            "type":"Services"
        }
    ],
    "sg:phone":"+44 161 881 0911",
    "sg:postcode":"M21 9SZ",
    "sg:province":"Cheshire",
    "wof:name":"Manchester Social Services",
    "wof:placetype":"venue"
},
  "geometry": {"coordinates":[-2.2826390266,53.4387893677],"type":"Point"}
}