{
  "type": "Feature",
  "properties": {
    "iso:country":"GB",
    "sg:address":"Sir John Lyon House, 5 High Timber Street",
    "sg:city":"London",
    "sg:classifiers":[
        {
            "category":"Personal",
            "type":"Services"
        }
    ],
    "sg:postcode":"EC4V 3LU",
    "sg:province":"Greater London",
    "sg:tags":[
        "delivery"
    ],
    "wof:name":"Thompson Lloyds & Ewart",
    "wof:placetype":"venue"
},
  "geometry": {"coordinates":[-0.096705,51.510921],"type":"Point"}
}