{
  "type": "Feature",
  "properties": {
    "addr:full":"Grant Thornton Ho, Melton St London Greater London NW1 2EP",
    "addr:postcode":"nw1 2ep",
    "addr:street":"Melton St",
    "iso:country":"GB",
    "sg:address":"Grant Thornton Ho, Melton St",
    "sg:city":"London",
    "sg:classifiers":[
        {
            "category":"Banks & Credit Unions",
            "subcategory":"Financial Services",
            "type":"Services"
        }
    ],
    "sg:postcode":"NW1 2EP",
    "sg:province":"Greater London",
    "sg:tags":[
        "consultant"
    ],
    "wof:name":"Mount Olympus Investments Ltd",
    "wof:placetype":"venue"
},
  "geometry": {"coordinates":[-0.13391,51.52692],"type":"Point"}
}