{
  "type": "Feature",
  "properties": {
    "addr:full":"Blackfriars Corner, Chapel Street Salford Greater Manchester M3 7AA",
    "addr:postcode":"m3 7aa",
    "addr:street":"Chapel Street",
    "iso:country":"GB",
    "sg:address":"Blackfriars Corner, Chapel Street",
    "sg:city":"Salford",
    "sg:classifiers":[
        {
            "category":"Retail",
            "subcategory":"Auto Repair",
            "type":"Services"
        }
    ],
    "sg:phone":"+44 161 832 3838",
    "sg:postcode":"M3 7AA",
    "sg:province":"Greater Manchester",
    "sg:tags":[
        "modification",
        "garage"
    ],
    "wof:name":"Leyden Brothers (Blackfriars) Limited",
    "wof:placetype":"venue"
},
  "geometry": {"coordinates":[-2.256298,53.488434],"type":"Point"}
}