{
  "type": "Feature",
  "properties": {
    "addr:full":"2 High Street Camberley Berkshire GU15 3SX",
    "addr:housenumber":"2",
    "addr:postcode":"gu15 3sx",
    "addr:street":"High Street",
    "iso:country":"GB",
    "sg:address":"2 High Street",
    "sg:city":"Camberley",
    "sg:classifiers":[
        {
            "category":"Shopping",
            "subcategory":"Comic Books",
            "type":"Retail Goods"
        }
    ],
    "sg:phone":"+44 1276 27474",
    "sg:postcode":"GU15 3SX",
    "sg:province":"Berkshire",
    "sg:tags":[
        "jeweller"
    ],
    "wof:name":"Capigi",
    "wof:placetype":"venue"
},
  "geometry": {"coordinates":[-0.7456340194,51.3396949768],"type":"Point"}
}