{
  "type": "Feature",
  "properties": {
    "iso:country":"GB",
    "sg:address":"Asby Farm, Asby",
    "sg:city":"Workington",
    "sg:classifiers":[
        {
            "category":"Farming",
            "subcategory":"Dairy Farm",
            "type":"Manufacturing & Wholesale Goods"
        },
        {
            "category":"Farming",
            "subcategory":"Farm",
            "type":"Manufacturing & Wholesale Goods"
        }
    ],
    "sg:phone":"+44 1946 862072",
    "sg:postcode":"CA14 4RP",
    "sg:province":"Cumbria",
    "sg:tags":[
        "mixed",
        "crop"
    ],
    "wof:name":"P Palmer",
    "wof:placetype":"venue"
},
  "geometry": {"coordinates":[-3.451944,54.570122],"type":"Point"}
}