{
  "type": "Feature",
  "properties": {
    "iso:country":"GB",
    "sg:address":"Shreding Green Garage, Langley Park Road",
    "sg:city":"Iver",
    "sg:classifiers":[
        {
            "category":"Autos & Motor Vehicles",
            "subcategory":"Auto Supplies",
            "type":"Retail Goods"
        }
    ],
    "sg:phone":"+44 1753 654939",
    "sg:postcode":"SL0 0JG",
    "sg:province":"Berkshire",
    "sg:tags":[
        "tyre"
    ],
    "wof:name":"Charlie Browns Autocentres Ltd",
    "wof:placetype":"venue"
},
  "geometry": {"coordinates":[-0.5206189752,51.5365447998],"type":"Point"}
}