{
  "type": "Feature",
  "properties": {
    "iso:country":"GB",
    "sg:address":"340 Grays Inn Road",
    "sg:city":"London",
    "sg:classifiers":[
        {
            "category":"Professional",
            "type":"Services"
        }
    ],
    "sg:phone":"+44 20 7833 5885",
    "sg:postcode":"WC1X 8BJ",
    "sg:province":"Greater London",
    "sg:tags":[
        "auctioneer"
    ],
    "wof:name":"Harman Healy Ltd.",
    "wof:placetype":"venue"
},
  "geometry": {"coordinates":[-0.119975999,51.5295410156],"type":"Point"}
}