{
  "type": "Feature",
  "properties": {
    "addr:full":"30 Southall St Manchester Greater Manchester M3 1WH",
    "addr:housenumber":"30",
    "addr:postcode":"m3 1wh",
    "addr:street":"Southall St",
    "iso:country":"GB",
    "sg:address":"30 Southall St",
    "sg:city":"Manchester",
    "sg:classifiers":[
        {
            "category":"Manufacturing",
            "subcategory":"Textiles",
            "type":"Manufacturing & Wholesale Goods"
        }
    ],
    "sg:phone":"+44 161 834 8914",
    "sg:postcode":"M3 1WH",
    "sg:province":"Greater Manchester",
    "sg:tags":[
        "merchant",
        "agent"
    ],
    "wof:name":"Viatex (Manchester) Ltd",
    "wof:placetype":"venue"
},
  "geometry": {"coordinates":[-2.2457249165,53.4918708801],"type":"Point"}
}