{
  "type": "Feature",
  "properties": {
    "addr:full":"Unit 2 Ashton Pk, Antler Ct, Ashton In Makerfield Wigan Lancashire WN4 8DU",
    "addr:housenumber":"unit 2",
    "addr:postcode":"wn4 8du",
    "addr:street":"Ashton Pk Antler Ct",
    "iso:country":"GB",
    "sg:address":"Unit 2 Ashton Pk, Antler Ct, Ashton In Makerfield",
    "sg:city":"Wigan",
    "sg:classifiers":[
        {
            "category":"Freight",
            "type":"Transportation"
        }
    ],
    "sg:phone":"+44 1942 722424",
    "sg:postcode":"WN4 8DU",
    "sg:province":"Lancashire",
    "sg:tags":[
        "haulage",
        "road"
    ],
    "wof:name":"Corsi F I T (U K) Ltd",
    "wof:placetype":"venue"
},
  "geometry": {"coordinates":[-2.6376299858,53.5018997192],"type":"Point"}
}