{
  "type": "Feature",
  "properties": {
    "addr:full":"6 Fairfields, Free Prae Road Chertsey Surrey KT16 8EA",
    "addr:housenumber":"6",
    "addr:postcode":"kt16 8ea",
    "addr:street":"Fairfields Free Prae Road",
    "iso:country":"GB",
    "sg:address":"6 Fairfields, Free Prae Road",
    "sg:city":"Chertsey",
    "sg:classifiers":[
        {
            "category":"Recreation",
            "subcategory":"Amusement Park",
            "type":"Entertainment"
        }
    ],
    "sg:postcode":"KT16 8EA",
    "sg:province":"Surrey",
    "sg:tags":[
        "arcade"
    ],
    "wof:name":"Edwards Amusements",
    "wof:placetype":"venue"
},
  "geometry": {"coordinates":[-0.498067,51.38541],"type":"Point"}
}