{
  "type": "Feature",
  "properties": {
    "iso:country":"GB",
    "sg:address":"The Weighbridge, Abermule",
    "sg:city":"Montgomery",
    "sg:classifiers":[
        {
            "category":"Building & Trades",
            "subcategory":"Cleaning & Sanitation",
            "type":"Services"
        }
    ],
    "sg:phone":"+44 1686 630691",
    "sg:postcode":"SY15 6HN",
    "sg:province":"Shropshire",
    "sg:tags":[
        "dry",
        "control",
        "damp",
        "rot"
    ],
    "wof:name":"Newtown Damproofing Co. Ltd.",
    "wof:placetype":"venue"
},
  "geometry": {"coordinates":[-3.1464788914,52.5635643005],"type":"Point"}
}