{
  "type": "Feature",
  "properties": {
    "addr:full":", Hemswell Cliff Gainsborough Lincolnshire DN21 5TX",
    "addr:postcode":"dn21 5tx",
    "iso:country":"GB",
    "sg:address":", Hemswell Cliff",
    "sg:city":"Gainsborough",
    "sg:classifiers":[
        {
            "category":"Government",
            "subcategory":"Post Office",
            "type":"Public Place"
        }
    ],
    "sg:phone":"+44 1427 668215",
    "sg:postcode":"DN21 5TX",
    "sg:province":"Lincolnshire",
    "wof:name":"Hemswell Cliff P.O",
    "wof:placetype":"venue"
},
  "geometry": {"coordinates":[-0.601888001,53.407169342],"type":"Point"}
}