{
  "type": "Feature",
  "properties": {
    "iso:country":"GB",
    "sg:address":"Unit 3, Baring St",
    "sg:city":"Manchester",
    "sg:classifiers":[
        {
            "category":"Freight",
            "type":"Transportation"
        }
    ],
    "sg:phone":"+44 161 274 3444",
    "sg:postcode":"M1 2PY",
    "sg:province":"Greater Manchester",
    "sg:tags":[
        "haulage",
        "road"
    ],
    "wof:name":"Anc Ltd",
    "wof:placetype":"venue"
},
  "geometry": {"coordinates":[-2.22769,53.474258],"type":"Point"}
}