{
  "type": "Feature",
  "properties": {
    "iso:country":"GB",
    "sg:address":"Seaclose Wharf, Town Quay",
    "sg:city":"Newport",
    "sg:classifiers":[
        {
            "category":"Landmark",
            "subcategory":"Tourist Attraction",
            "type":"Public Place"
        }
    ],
    "sg:phone":"+44 1983 533493",
    "sg:postcode":"PO30 2EF",
    "sg:province":"Isle of Wight",
    "sg:tags":[
        "interest"
    ],
    "wof:name":"The Classic Boat Centre Trust",
    "wof:placetype":"venue"
},
  "geometry": {"coordinates":[-1.295939,50.7001],"type":"Point"}
}