{
  "type": "Feature",
  "properties": {
    "iso:country":"GB",
    "sg:address":"Hill View, Balmoral Road",
    "sg:city":"Blairgowrie",
    "sg:classifiers":[
        {
            "category":"Building & Trades",
            "subcategory":"Construction",
            "type":"Services"
        }
    ],
    "sg:postcode":"PH10 7AE",
    "sg:province":"Perth and Kinross",
    "sg:tags":[
        "contractor",
        "paving",
        "driveway"
    ],
    "wof:name":"Roger Smith Paving Services",
    "wof:placetype":"venue"
},
  "geometry": {"coordinates":[-3.340659,56.601925],"type":"Point"}
}