{
  "type": "Feature",
  "properties": {
    "addr:full":"Birkdale Road, New Marske Redcar North Yorkshire TS11 8DP",
    "addr:postcode":"ts11 8dp",
    "addr:street":"Birkdale Road",
    "iso:country":"GB",
    "sg:address":"Birkdale Road, New Marske",
    "sg:city":"Redcar",
    "sg:classifiers":[
        {
            "category":"Arts & Performance",
            "subcategory":"Music",
            "type":"Entertainment"
        }
    ],
    "sg:postcode":"TS11 8DP",
    "sg:province":"North Yorkshire",
    "sg:tags":[
        "mobile",
        "disco"
    ],
    "wof:name":"Malc's Roadshow",
    "wof:placetype":"venue"
},
  "geometry": {"coordinates":[-1.0439740419,54.5804405212],"type":"Point"}
}