{
  "type": "Feature",
  "properties": {
    "addr:full":"24 Dealston Road, Barrhead Glasgow East Ayrshire G78 1NL",
    "addr:housenumber":"24",
    "addr:postcode":"g78 1nl",
    "addr:street":"Dealston Road",
    "iso:country":"GB",
    "sg:address":"24 Dealston Road, Barrhead",
    "sg:city":"Glasgow",
    "sg:classifiers":[
        {
            "category":"Building & Trades",
            "subcategory":"Cleaning & Sanitation",
            "type":"Services"
        }
    ],
    "sg:postcode":"G78 1NL",
    "sg:province":"East Ayrshire",
    "sg:tags":[
        "cleaner",
        "window"
    ],
    "wof:name":"Allbright Cleaning Services",
    "wof:placetype":"venue"
},
  "geometry": {"coordinates":[-4.3980550766,55.806552887],"type":"Point"}
}