{
  "type": "Feature",
  "properties": {
    "iso:country":"GB",
    "sg:address":"20 Boxgrove Rd",
    "sg:city":"Guildford",
    "sg:classifiers":[
        {
            "category":"Real Estate",
            "subcategory":"Surveying",
            "type":"Services"
        }
    ],
    "sg:postcode":"GU1 2NF",
    "sg:province":"Surrey",
    "sg:tags":[
        "surveyor",
        "quantity"
    ],
    "wof:name":"Slaven,E J,",
    "wof:placetype":"venue"
},
  "geometry": {"coordinates":[-0.548399,51.24445],"type":"Point"}
}