{
  "type": "Feature",
  "properties": {
    "iso:country":"GB",
    "sg:address":"Holland Park, Holland Drive",
    "sg:city":"Newcastle-upon-tyne",
    "sg:classifiers":[
        {
            "category":"Banks & Credit Unions",
            "subcategory":"Financial Services",
            "type":"Services"
        }
    ],
    "sg:phone":"+44 191 261 9661",
    "sg:postcode":"NE2 4LD",
    "sg:province":"Tyne and Wear",
    "sg:tags":[
        "adviser"
    ],
    "wof:name":"B M A Services",
    "wof:placetype":"venue"
},
  "geometry": {"coordinates":[-1.6326680183,54.9807510376],"type":"Point"}
}