{
  "type": "Feature",
  "properties": {
    "addr:full":"52 Station Road Rushden Bedfordshire NN10 9SG",
    "addr:housenumber":"52",
    "addr:postcode":"nn10 9sg",
    "addr:street":"Station Road",
    "iso:country":"GB",
    "sg:address":"52 Station Road",
    "sg:city":"Rushden",
    "sg:classifiers":[
        {
            "category":"Personal",
            "subcategory":"Shoe Repair & Shine",
            "type":"Services"
        },
        {
            "category":"Shopping",
            "subcategory":"Shoes",
            "type":"Retail Goods"
        }
    ],
    "sg:phone":"+44 1933 314053",
    "sg:postcode":"NN10 9SG",
    "sg:province":"Bedfordshire",
    "wof:name":"Leeding Shoe Repairing Services",
    "wof:placetype":"venue"
},
  "geometry": {"coordinates":[-0.602175,52.292835],"type":"Point"}
}