{
  "type": "Feature",
  "properties": {
    "iso:country":"GB",
    "sg:address":"3 Ableside Terrace",
    "sg:city":"Sunderland",
    "sg:classifiers":[
        {
            "category":"Building & Trades",
            "subcategory":"Construction",
            "type":"Services"
        }
    ],
    "sg:phone":"+44 191 516 0518",
    "sg:postcode":"SR6 8LP",
    "sg:province":"Tyne and Wear",
    "sg:tags":[
        "builder"
    ],
    "wof:name":"Varley Builders",
    "wof:placetype":"venue"
},
  "geometry": {"coordinates":[-1.3840110302,54.9326324463],"type":"Point"}
}