{
  "type": "Feature",
  "properties": {
    "iso:country":"GB",
    "sg:address":"6 Walcote Place",
    "sg:city":"Winchester",
    "sg:classifiers":[
        {
            "category":"Personal",
            "subcategory":"Beauty Salon",
            "type":"Services"
        }
    ],
    "sg:phone":"+44 1962 851551",
    "sg:postcode":"SO23 9AP",
    "sg:province":"Hampshire",
    "wof:name":"Wessex Health & Beauty",
    "wof:placetype":"venue"
},
  "geometry": {"coordinates":[-1.316809,51.063068],"type":"Point"}
}