{
  "type": "Feature",
  "properties": {
    "addr:full":"12 King St Dukinfield Greater Manchester SK16 4JQ",
    "addr:housenumber":"12",
    "addr:postcode":"sk16 4jq",
    "addr:street":"King St",
    "iso:country":"GB",
    "sg:address":"12 King St",
    "sg:city":"Dukinfield",
    "sg:classifiers":[
        {
            "category":"Professional",
            "subcategory":"Lawyer & Legal Services",
            "type":"Services"
        }
    ],
    "sg:phone":"+44 161 343 6225",
    "sg:postcode":"SK16 4JQ",
    "sg:province":"Greater Manchester",
    "wof:name":"Claims Direct",
    "wof:placetype":"venue"
},
  "geometry": {"coordinates":[-2.0930719376,53.4782867432],"type":"Point"}
}