{
  "type": "Feature",
  "properties": {
    "addr:full":"Diglis Dock Road Worcester Worcestershire WR5 3BS",
    "addr:postcode":"wr5 3bs",
    "addr:street":"Dock Road",
    "iso:country":"GB",
    "sg:address":"Diglis Dock Road",
    "sg:city":"Worcester",
    "sg:classifiers":[
        {
            "category":"Autos & Motor Vehicles",
            "subcategory":"Automobile Sales",
            "type":"Retail Goods"
        }
    ],
    "sg:phone":"+44 1905 350880",
    "sg:postcode":"WR5 3BS",
    "sg:province":"Worcestershire",
    "sg:tags":[
        "auction",
        "car"
    ],
    "wof:name":"Worcester Car Auctions",
    "wof:placetype":"venue"
},
  "geometry": {"coordinates":[-2.2195489407,52.1818885803],"type":"Point"}
}