{
  "type": "Feature",
  "properties": {
    "iso:country":"GB",
    "sg:address":"Salisbury House, Vernon Walk",
    "sg:city":"Southampton",
    "sg:classifiers":[
        {
            "category":"Insurance",
            "subcategory":"Insurance Agent",
            "type":"Services"
        }
    ],
    "sg:phone":"+44 23 8023 2555",
    "sg:postcode":"SO15 2SU",
    "sg:province":"Hampshire",
    "wof:name":"Claims Office",
    "wof:placetype":"venue"
},
  "geometry": {"coordinates":[-1.4073189497,50.9099388123],"type":"Point"}
}