{
  "type": "Feature",
  "properties": {
    "addr:full":"Croftswood, Blacksmiths Close, Sedgeberrow Evesham Gloucestershire WR11 7UP",
    "addr:postcode":"wr11 7up",
    "addr:street":"Blacksmiths Close",
    "iso:country":"GB",
    "sg:address":"Croftswood, Blacksmiths Close, Sedgeberrow",
    "sg:city":"Evesham",
    "sg:classifiers":[
        {
            "category":"Building & Trades",
            "subcategory":"Construction",
            "type":"Services"
        }
    ],
    "sg:phone":"+44 1386 882097",
    "sg:postcode":"WR11 7UP",
    "sg:province":"Gloucestershire",
    "sg:tags":[
        "joinery"
    ],
    "wof:name":"Bell Woodcraft",
    "wof:placetype":"venue"
},
  "geometry": {"coordinates":[-1.9648859501,52.0464096069],"type":"Point"}
}