{
  "type": "Feature",
  "properties": {
    "addr:full":"98a Howard Street North Shields Tyne and Wear NE30 1NA",
    "addr:housenumber":"98a",
    "addr:postcode":"ne30 1na",
    "addr:street":"Howard Street",
    "iso:country":"GB",
    "sg:address":"98a Howard Street",
    "sg:city":"North Shields",
    "sg:classifiers":[
        {
            "category":"Home & Garden",
            "subcategory":"Home Furnishings",
            "type":"Retail Goods"
        }
    ],
    "sg:phone":"+44 191 257 2118",
    "sg:postcode":"NE30 1NA",
    "sg:province":"Tyne and Wear",
    "sg:tags":[
        "mantelpiece",
        "fireplace"
    ],
    "wof:name":"Antique Fireplaces & Furniture",
    "wof:placetype":"venue"
},
  "geometry": {"coordinates":[-1.443242,55.008595],"type":"Point"}
}