{
  "type": "Feature",
  "properties": {
    "addr:full":"240a Portobello Rd Notting Hill Greater London W11 1LL",
    "addr:housenumber":"240a",
    "addr:postcode":"w11 1ll",
    "addr:street":"Portobello Rd",
    "iso:country":"GB",
    "sg:address":"240a Portobello Rd",
    "sg:city":"Notting Hill",
    "sg:classifiers":[
        {
            "category":"Bars & Pubs",
            "type":"Food & Drink"
        }
    ],
    "sg:phone":"+44 20 7229 6472",
    "sg:postcode":"W11 1LL",
    "sg:province":"Greater London",
    "sg:tags":[
        "pubs",
        "inn"
    ],
    "wof:name":"The Market Bar",
    "wof:placetype":"venue"
},
  "geometry": {"coordinates":[-0.206206,51.517704],"type":"Point"}
}