{
  "type": "Feature",
  "properties": {
    "addr:full":"116a Portswood Road Southampton Hampshire SO17 2FY",
    "addr:housenumber":"116a",
    "addr:postcode":"so17 2fy",
    "addr:street":"Portswood Road",
    "iso:country":"GB",
    "sg:address":"116a Portswood Road",
    "sg:city":"Southampton",
    "sg:classifiers":[
        {
            "category":"Fast Food",
            "type":"Food & Drink"
        }
    ],
    "sg:phone":"+44 23 8055 3558",
    "sg:postcode":"SO17 2FY",
    "sg:province":"Hampshire",
    "sg:tags":[
        "away",
        "take"
    ],
    "wof:name":"Happy Sandwich",
    "wof:placetype":"venue"
},
  "geometry": {"coordinates":[-1.394476,50.923824],"type":"Point"}
}