{
  "type": "Feature",
  "properties": {
    "iso:country":"GB",
    "sg:address":"1st Floor, Coventry St",
    "sg:city":"West End",
    "sg:classifiers":[
        {
            "category":"Utilities",
            "type":"Services"
        }
    ],
    "sg:phone":"+44 20 7437 3704",
    "sg:postcode":"W1V 8DH",
    "sg:province":"Hampshire",
    "sg:tags":[
        "internet"
    ],
    "wof:name":"Internet Exchange",
    "wof:placetype":"venue"
},
  "geometry": {"coordinates":[-0.13398,51.510033],"type":"Point"}
}