{
  "type": "Feature",
  "properties": {
    "iso:country":"GB",
    "sg:address":"70 Churchfield Lane, Glasshoughton",
    "sg:city":"Castleford",
    "sg:classifiers":[
        {
            "category":"Building & Trades",
            "subcategory":"Plumbing",
            "type":"Services"
        }
    ],
    "sg:phone":"+44 1977 512307",
    "sg:postcode":"WF10 4DD",
    "sg:province":"West Yorkshire",
    "sg:tags":[
        "heating"
    ],
    "wof:name":"John Grady",
    "wof:placetype":"venue"
},
  "geometry": {"coordinates":[-1.337593,53.719959],"type":"Point"}
}