{
  "type": "Feature",
  "properties": {
    "iso:country":"GB",
    "sg:address":"Torr View Avenue",
    "sg:city":"Plymouth",
    "sg:classifiers":[
        {
            "category":"Professional",
            "subcategory":"Computer Services",
            "type":"Services"
        }
    ],
    "sg:postcode":"PL3 4QN",
    "sg:province":"Devon",
    "sg:tags":[
        "system",
        "software"
    ],
    "wof:name":"Psion User Group",
    "wof:placetype":"venue"
},
  "geometry": {"coordinates":[-4.1438288689,50.3937683105],"type":"Point"}
}