{
  "type": "Feature",
  "properties": {
    "iso:country":"GB",
    "sg:address":"27 Hillfoot Green",
    "sg:city":"Liverpool",
    "sg:classifiers":[
        {
            "category":"Communications",
            "type":"Services"
        }
    ],
    "sg:postcode":"L25 7UH",
    "sg:province":"Merseyside",
    "sg:tags":[
        "telecommunication"
    ],
    "wof:name":"Westingway Ltd",
    "wof:placetype":"venue"
},
  "geometry": {"coordinates":[-2.86574,53.363102],"type":"Point"}
}