{
  "type": "Feature",
  "properties": {
    "addr:full":"Morghew Park Tenterden Kent TN30 7LR",
    "addr:postcode":"tn30 7lr",
    "iso:country":"GB",
    "sg:address":"Morghew Park",
    "sg:city":"Tenterden",
    "sg:classifiers":[
        {
            "category":"Wholesale",
            "subcategory":"Fruits & Vegetables",
            "type":"Manufacturing & Wholesale Goods"
        }
    ],
    "sg:phone":"+44 1580 763158",
    "sg:postcode":"TN30 7LR",
    "sg:province":"Kent",
    "wof:name":"Wadhurst Park Ltd.",
    "wof:placetype":"venue"
},
  "geometry": {"coordinates":[0.69406,51.075405],"type":"Point"}
}