{
  "type": "Feature",
  "properties": {
    "addr:full":"Pentwyn Farm, Llangua Abergavenny Herefordshire NP7 8HF",
    "addr:postcode":"np7 8hf",
    "addr:street":"Llangua",
    "iso:country":"GB",
    "sg:address":"Pentwyn Farm, Llangua",
    "sg:city":"Abergavenny",
    "sg:classifiers":[
        {
            "category":"Farming",
            "subcategory":"Livestock Farm",
            "type":"Manufacturing & Wholesale Goods"
        }
    ],
    "sg:phone":"+44 1981 240364",
    "sg:postcode":"NP7 8HF",
    "sg:province":"Herefordshire",
    "sg:tags":[
        "others"
    ],
    "wof:name":"W H Jones",
    "wof:placetype":"venue"
},
  "geometry": {"coordinates":[-2.884633,51.929012],"type":"Point"}
}