{
  "type": "Feature",
  "properties": {
    "iso:country":"GB",
    "sg:address":"37 Fairmile Lane",
    "sg:city":"Cobham",
    "sg:classifiers":[
        {
            "category":"Sports & Exercise",
            "subcategory":"Playing Field",
            "type":"Entertainment"
        }
    ],
    "sg:phone":"+44 1932 866492",
    "sg:postcode":"KT11 2DL",
    "sg:province":"Surrey",
    "sg:tags":[
        "sanitary",
        "hygiene",
        "appliance"
    ],
    "wof:name":"Barrys Home Improvement Services",
    "wof:placetype":"venue"
},
  "geometry": {"coordinates":[-0.3884339929,51.3264465332],"type":"Point"}
}