{
  "type": "Feature",
  "properties": {
    "addr:full":"The William Brooke Academy, Armitage Bridge Huddersfield West Yorkshire HD4 7NR",
    "addr:postcode":"hd4 7nr",
    "addr:street":"West",
    "iso:country":"GB",
    "sg:address":"The William Brooke Academy, Armitage Bridge",
    "sg:city":"Huddersfield",
    "sg:classifiers":[
        {
            "category":"Education",
            "subcategory":"Dance Studio",
            "type":"Public Place"
        }
    ],
    "sg:phone":"+44 1484 660884",
    "sg:postcode":"HD4 7NR",
    "sg:province":"West Yorkshire",
    "sg:tags":[
        "school",
        "ballet",
        "dancing"
    ],
    "wof:name":"Huddersfield School Of Theatre Dance",
    "wof:placetype":"venue"
},
  "geometry": {"coordinates":[-1.803988,53.619675],"type":"Point"}
}