{
  "type": "Feature",
  "properties": {
    "iso:country":"GB",
    "sg:address":"235 Botley Rd",
    "sg:city":"Southampton",
    "sg:classifiers":[
        {
            "category":"Home & Garden",
            "subcategory":"Garden Supply",
            "type":"Retail Goods"
        }
    ],
    "sg:phone":"+44 1489 573893",
    "sg:postcode":"SO31 1BJ",
    "sg:province":"Hampshire",
    "sg:tags":[
        "nursery",
        "centre"
    ],
    "wof:name":"Hilton Nurseries",
    "wof:placetype":"venue"
},
  "geometry": {"coordinates":[-1.2671339512,50.8869743347],"type":"Point"}
}