{
  "type": "Feature",
  "properties": {
    "iso:country":"GB",
    "sg:address":"The Mill, Glynde",
    "sg:city":"Lewes",
    "sg:classifiers":[
        {
            "category":"Home & Garden",
            "subcategory":"Building Materials",
            "type":"Retail Goods"
        }
    ],
    "sg:postcode":"BN8 6SS",
    "sg:province":"East Sussex",
    "sg:tags":[
        "system",
        "staircase"
    ],
    "wof:name":"Lewes Design Contracts Ltd.",
    "wof:placetype":"venue"
},
  "geometry": {"coordinates":[0.068225,50.861897],"type":"Point"}
}