{
  "type": "Feature",
  "properties": {
    "addr:full":"18 Boulevard Weston Super Mare Somerset BS23 1NA",
    "addr:housenumber":"18",
    "addr:postcode":"bs23 1na",
    "addr:street":"Boulevard Weston",
    "iso:country":"GB",
    "sg:address":"18 Boulevard",
    "sg:city":"Weston Super Mare",
    "sg:classifiers":[
        {
            "category":"Food & Beverages",
            "subcategory":"Supermarket",
            "type":"Retail Goods"
        }
    ],
    "sg:phone":"+44 1934 645858",
    "sg:postcode":"BS23 1NA",
    "sg:province":"Somerset",
    "wof:name":"Ioannides",
    "wof:placetype":"venue"
},
  "geometry": {"coordinates":[-2.975028,51.350147],"type":"Point"}
}