{
  "type": "Feature",
  "properties": {
    "addr:full":"44 Portholme Dr Selby East Riding of Yorkshire YO8 0QF",
    "addr:housenumber":"44",
    "addr:postcode":"yo8 0qf",
    "addr:street":"Portholme Dr",
    "iso:country":"GB",
    "sg:address":"44 Portholme Dr",
    "sg:city":"Selby",
    "sg:classifiers":[
        {
            "category":"Shopping",
            "subcategory":"Beauty & Cosmetics",
            "type":"Retail Goods"
        }
    ],
    "sg:phone":"+44 1757 704477",
    "sg:postcode":"YO8 0QF",
    "sg:province":"East Riding of Yorkshire",
    "sg:tags":[
        "equipment",
        "supply",
        "hairdressing"
    ],
    "wof:name":"Giltsharp York",
    "wof:placetype":"venue"
},
  "geometry": {"coordinates":[-1.072715044,53.780456543],"type":"Point"}
}