{
  "type": "Feature",
  "properties": {
    "addr:full":"150 Bedford Road, Kempston Bedford Bedfordshire MK42 8BH",
    "addr:housenumber":"150",
    "addr:postcode":"mk42 8bh",
    "addr:street":"Bedford Road",
    "iso:country":"GB",
    "sg:address":"150 Bedford Road, Kempston",
    "sg:city":"Bedford",
    "sg:classifiers":[
        {
            "category":"Retail",
            "subcategory":"Funeral Services",
            "type":"Services"
        }
    ],
    "sg:postcode":"MK42 8BH",
    "sg:province":"Bedfordshire",
    "wof:name":"Abbots",
    "wof:placetype":"venue"
},
  "geometry": {"coordinates":[-0.4918259978,52.120059967],"type":"Point"}
}