{
  "type": "Feature",
  "properties": {
    "addr:full":"Forge Garage, Callowend Worcester Worcestershire WR2 4TE",
    "addr:postcode":"wr2 4te",
    "iso:country":"GB",
    "sg:address":"Forge Garage, Callowend",
    "sg:city":"Worcester",
    "sg:classifiers":[
        {
            "category":"Retail",
            "subcategory":"Auto Repair",
            "type":"Services"
        }
    ],
    "sg:postcode":"WR2 4TE",
    "sg:province":"Worcestershire",
    "sg:tags":[
        "modification",
        "garage"
    ],
    "wof:name":"W J Davies",
    "wof:placetype":"venue"
},
  "geometry": {"coordinates":[-2.2432899475,52.1422691345],"type":"Point"}
}