{
  "type": "Feature",
  "properties": {
    "iso:country":"GB",
    "sg:address":"Lee Farm, Freckenham",
    "sg:city":"Bury St Edmunds",
    "sg:classifiers":[
        {
            "category":"Home & Garden",
            "subcategory":"Garden Supply",
            "type":"Retail Goods"
        },
        {
            "category":"Farming",
            "subcategory":"Livestock Farm",
            "type":"Manufacturing & Wholesale Goods"
        }
    ],
    "sg:postcode":"IP28 8HR",
    "sg:province":"Cambridgeshire",
    "sg:tags":[
        "bulb",
        "grower",
        "others"
    ],
    "wof:name":"G A Thornalley & Sons",
    "wof:placetype":"venue"
},
  "geometry": {"coordinates":[0.43994,52.337551],"type":"Point"}
}