{
  "type": "Feature",
  "properties": {
    "addr:full":"26 The Parade Walton-on-the-naze Essex CO14 8EA",
    "addr:housenumber":"26",
    "addr:postcode":"co14 8ea",
    "addr:street":"The Parade",
    "iso:country":"GB",
    "sg:address":"26 The Parade",
    "sg:city":"Walton-on-the-naze",
    "sg:classifiers":[
        {
            "category":"Home & Garden",
            "subcategory":"Household Appliances",
            "type":"Retail Goods"
        },
        {
            "category":"Building & Trades",
            "subcategory":"Construction",
            "type":"Services"
        },
        {
            "category":"Communications",
            "type":"Services"
        }
    ],
    "sg:phone":"+44 1255 676648",
    "sg:postcode":"CO14 8EA",
    "sg:province":"Essex",
    "sg:tags":[
        "tv",
        "video",
        "builder",
        "electrical",
        "radio"
    ],
    "wof:name":"Allied Ariels",
    "wof:placetype":"venue"
},
  "geometry": {"coordinates":[1.2715740204,51.8473205566],"type":"Point"}
}