{
  "type": "Feature",
  "properties": {
    "iso:country":"GB",
    "sg:address":"56 High Street",
    "sg:city":"Banchory",
    "sg:classifiers":[
        {
            "category":"Food & Beverages",
            "subcategory":"Bakery",
            "type":"Retail Goods"
        }
    ],
    "sg:phone":"+44 1330 823353",
    "sg:postcode":"AB31 5SS",
    "sg:province":"Aberdeen City",
    "sg:tags":[
        "shop",
        "baker"
    ],
    "wof:name":"Chalmers Bakery Ltd",
    "wof:placetype":"venue"
},
  "geometry": {"coordinates":[-2.503331,57.051254],"type":"Point"}
}