{
  "type": "Feature",
  "properties": {
    "addr:full":"Maryland Farm, Smiths Lane, Ditcheat Shepton Mallet Somerset BA4 6PR",
    "addr:postcode":"ba4 6pr",
    "addr:street":"Smiths Lane",
    "iso:country":"GB",
    "sg:address":"Maryland Farm, Smiths Lane, Ditcheat",
    "sg:city":"Shepton Mallet",
    "sg:classifiers":[
        {
            "category":"Farming",
            "subcategory":"Dairy Farm",
            "type":"Manufacturing & Wholesale Goods"
        },
        {
            "category":"Food & Beverages",
            "subcategory":"Dairy",
            "type":"Retail Goods"
        }
    ],
    "sg:phone":"+44 1749 860666",
    "sg:postcode":"BA4 6PR",
    "sg:province":"Somerset",
    "sg:tags":[
        "cheese",
        "maker"
    ],
    "wof:name":"A J & R G Barber Ltd",
    "wof:placetype":"venue"
},
  "geometry": {"coordinates":[-2.5356690884,51.1242408752],"type":"Point"}
}