{
  "type": "Feature",
  "properties": {
    "addr:full":"19 Hart Street Walsall West Midlands WS1 3PE",
    "addr:housenumber":"19",
    "addr:postcode":"ws1 3pe",
    "addr:street":"Hart Street",
    "iso:country":"GB",
    "sg:address":"19 Hart Street",
    "sg:city":"Walsall",
    "sg:classifiers":[
        {
            "category":"Wholesale",
            "subcategory":"Construction Materials",
            "type":"Manufacturing & Wholesale Goods"
        }
    ],
    "sg:postcode":"WS1 3PE",
    "sg:province":"West Midlands",
    "sg:tags":[
        "distributor",
        "spring"
    ],
    "wof:name":"Cobra Springs",
    "wof:placetype":"venue"
},
  "geometry": {"coordinates":[-1.982714,52.578732],"type":"Point"}
}