{
  "type": "Feature",
  "properties": {
    "iso:country":"GB",
    "sg:address":"Penistone Road North",
    "sg:city":"Sheffield",
    "sg:classifiers":[
        {
            "category":"Sports & Exercise",
            "subcategory":"Golf",
            "type":"Entertainment"
        }
    ],
    "sg:phone":"+44 114 285 5633",
    "sg:postcode":"S6 1LT",
    "sg:province":"South Yorkshire",
    "sg:tags":[
        "equipment"
    ],
    "wof:name":"American Golf Discount Centre",
    "wof:placetype":"venue"
},
  "geometry": {"coordinates":[-1.5003000498,53.4142608643],"type":"Point"}
}