{
  "type": "Feature",
  "properties": {
    "addr:full":"1 Sanderson Street, Coxhoe Durham Durham DH6 4DF",
    "addr:housenumber":"1",
    "addr:postcode":"dh6 4df",
    "addr:street":"Sanderson Street",
    "iso:country":"GB",
    "sg:address":"1 Sanderson Street, Coxhoe",
    "sg:city":"Durham",
    "sg:classifiers":[
        {
            "category":"Health Services",
            "subcategory":"Optometrist",
            "type":"Services"
        },
        {
            "category":"Shopping",
            "subcategory":"Optician",
            "type":"Retail Goods"
        }
    ],
    "sg:phone":"+44 191 377 0628",
    "sg:postcode":"DH6 4DF",
    "sg:province":"Durham",
    "sg:tags":[
        "ophthalmic"
    ],
    "wof:name":"J W Grundy",
    "wof:placetype":"venue"
},
  "geometry": {"coordinates":[-1.5034680367,54.714717865],"type":"Point"}
}