{
  "type": "Feature",
  "properties": {
    "addr:full":"23 Bridge Street Tadcaster North Yorkshire LS24 9AW",
    "addr:housenumber":"23",
    "addr:postcode":"ls24 9aw",
    "addr:street":"Bridge Street",
    "iso:country":"GB",
    "sg:address":"23 Bridge Street",
    "sg:city":"Tadcaster",
    "sg:classifiers":[
        {
            "category":"Bars & Pubs",
            "type":"Food & Drink"
        }
    ],
    "sg:phone":"+44 1937 835470",
    "sg:postcode":"LS24 9AW",
    "sg:province":"North Yorkshire",
    "sg:tags":[
        "pubs",
        "house",
        "inn",
        "public",
        "activity"
    ],
    "wof:name":"Angel & White Horse",
    "wof:placetype":"venue"
},
  "geometry": {"coordinates":[-1.260978,53.884266],"type":"Point"}
}