{
  "type": "Feature",
  "properties": {
    "addr:full":"12 High Street Gateshead Tyne and Wear NE8 2AQ",
    "addr:housenumber":"12",
    "addr:postcode":"ne8 2aq",
    "addr:street":"High Street",
    "iso:country":"GB",
    "sg:address":"12 High Street",
    "sg:city":"Gateshead",
    "sg:classifiers":[
        {
            "category":"Professional",
            "subcategory":"Detective & Security Services",
            "type":"Services"
        }
    ],
    "sg:postcode":"NE8 2AQ",
    "sg:province":"Tyne and Wear",
    "sg:tags":[
        "alarm",
        "burglar",
        "system"
    ],
    "wof:name":"D N W Protection",
    "wof:placetype":"venue"
},
  "geometry": {"coordinates":[-1.5696729422,54.9520301819],"type":"Point"}
}