{
  "type": "Feature",
  "properties": {
    "iso:country":"GB",
    "sg:address":"140-146 Dock Road",
    "sg:city":"Tilbury",
    "sg:classifiers":[
        {
            "category":"Government",
            "subcategory":"Post Office",
            "type":"Public Place"
        }
    ],
    "sg:phone":"+44 1375 843240",
    "sg:postcode":"RM18 7BS",
    "sg:province":"Essex",
    "wof:name":"Tilbury Post Office",
    "wof:placetype":"venue"
},
  "geometry": {"coordinates":[0.3553029895,51.4621734619],"type":"Point"}
}