{
  "type": "Feature",
  "properties": {
    "iso:country":"GB",
    "sg:address":"Moor Farm, Haisthorpe",
    "sg:city":"Driffield",
    "sg:classifiers":[
        {
            "category":"Farming",
            "subcategory":"Farm",
            "type":"Manufacturing & Wholesale Goods"
        }
    ],
    "sg:phone":"+44 1262 490296",
    "sg:postcode":"YO25 4NT",
    "sg:province":"East Riding of Yorkshire",
    "sg:tags":[
        "mixed",
        "crop"
    ],
    "wof:name":"Maurice Coultas",
    "wof:placetype":"venue"
},
  "geometry": {"coordinates":[-0.2778509855,54.0652809143],"type":"Point"}
}