{
  "type": "Feature",
  "properties": {
    "iso:country":"GB",
    "sg:address":"5 The Clock House, Carterton",
    "sg:city":"Carterton",
    "sg:classifiers":[
        {
            "category":"Professional",
            "subcategory":"Lawyer & Legal Services",
            "type":"Services"
        }
    ],
    "sg:phone":"+44 1993 850835",
    "sg:postcode":"OX18 3HN",
    "sg:province":"Gloucestershire",
    "sg:tags":[
        "solicitor"
    ],
    "wof:name":"Dunning, Nanderson And Parks",
    "wof:placetype":"venue"
},
  "geometry": {"coordinates":[-1.5903840065,51.7606239319],"type":"Point"}
}