{
  "type": "Feature",
  "properties": {
    "addr:full":"Lower Ground Floor, 31 Oval Road, Camden London Greater London NW1 7EA",
    "addr:housenumber":"31",
    "addr:postcode":"nw1 7ea",
    "addr:street":"Ground Floor;Oval Road",
    "iso:country":"GB",
    "sg:address":"Lower Ground Floor, 31 Oval Road, Camden",
    "sg:city":"London",
    "sg:classifiers":[
        {
            "category":"Professional",
            "subcategory":"Management & Consulting",
            "type":"Services"
        }
    ],
    "sg:phone":"+44 20 7482 2345",
    "sg:postcode":"NW1 7EA",
    "sg:province":"Greater London",
    "sg:tags":[
        "music"
    ],
    "wof:name":"H U M",
    "wof:placetype":"venue"
},
  "geometry": {"coordinates":[-0.147683993,51.5392189026],"type":"Point"}
}