{
  "type": "Feature",
  "properties": {
    "addr:full":"125-126 High Street Lincoln Lincolnshire LN5 7PP",
    "addr:housenumber":"125-126",
    "addr:postcode":"ln5 7pp",
    "addr:street":"High Street",
    "iso:country":"GB",
    "sg:address":"125-126 High Street",
    "sg:city":"Lincoln",
    "sg:classifiers":[
        {
            "category":"Home & Garden",
            "subcategory":"Furniture",
            "type":"Retail Goods"
        }
    ],
    "sg:phone":"+44 1522 521066",
    "sg:postcode":"LN5 7PP",
    "sg:province":"Lincolnshire",
    "wof:name":"G H Shaw Ltd.",
    "wof:placetype":"venue"
},
  "geometry": {"coordinates":[-0.543963,53.223145],"type":"Point"}
}