{
  "type": "Feature",
  "properties": {
    "addr:full":"Bixton Street, Thompson St Industrial Estate Blackburn Lancashire BB2 1TR",
    "addr:postcode":"bb2 1tr",
    "addr:street":"Bixton Street Thompson St Industrial Estate",
    "iso:country":"GB",
    "sg:address":"Bixton Street, Thompson St Industrial Estate",
    "sg:city":"Blackburn",
    "sg:classifiers":[
        {
            "category":"Manufacturing",
            "subcategory":"Petroleum Products",
            "type":"Manufacturing & Wholesale Goods"
        }
    ],
    "sg:phone":"+44 1254 260667",
    "sg:postcode":"BB2 1TR",
    "sg:province":"Lancashire",
    "sg:tags":[
        "double",
        "glazing"
    ],
    "wof:name":"Framemaker Ltd.",
    "wof:placetype":"venue"
},
  "geometry": {"coordinates":[-2.49905,53.74313],"type":"Point"}
}