{
  "type": "Feature",
  "properties": {
    "addr:full":"Holme Lane Doncaster South Yorkshire DN5 0LR",
    "addr:postcode":"dn5 0lr",
    "addr:street":"Holme Lane",
    "iso:country":"GB",
    "sg:address":"Holme Lane",
    "sg:city":"Doncaster",
    "sg:classifiers":[
        {
            "category":"Restaurant",
            "type":"Food & Drink"
        }
    ],
    "sg:postcode":"DN5 0LR",
    "sg:province":"South Yorkshire",
    "wof:name":"Thornhurst Manor",
    "wof:placetype":"venue"
},
  "geometry": {"coordinates":[-1.145188,53.592472],"type":"Point"}
}