{
  "type": "Feature",
  "properties": {
    "addr:full":"Spring Gardens Indust Est, Spring Gardens Whitland Carmarthenshire SA34 0HZ",
    "addr:postcode":"sa34 0hz",
    "addr:street":"Spring Gardens Indust Est Spring Gardens",
    "iso:country":"GB",
    "sg:address":"Spring Gardens Indust Est, Spring Gardens",
    "sg:city":"Whitland",
    "sg:classifiers":[
        {
            "category":"Personal",
            "type":"Services"
        }
    ],
    "sg:phone":"+44 1994 240856",
    "sg:postcode":"SA34 0HZ",
    "sg:province":"Carmarthenshire",
    "sg:tags":[
        "delivery"
    ],
    "wof:name":"Royal Mail",
    "wof:placetype":"venue"
},
  "geometry": {"coordinates":[-4.606442,51.81971],"type":"Point"}
}