{
  "type": "Feature",
  "properties": {
    "addr:full":"High St Bridlington East Riding of Yorkshire YO16 4QA",
    "addr:postcode":"yo16 4qa",
    "addr:street":"High St",
    "iso:country":"GB",
    "sg:address":"High St",
    "sg:city":"Bridlington",
    "sg:classifiers":[
        {
            "category":"Food & Beverages",
            "subcategory":"Bakery",
            "type":"Retail Goods"
        }
    ],
    "sg:phone":"+44 1262 400439",
    "sg:postcode":"YO16 4QA",
    "sg:province":"East Riding of Yorkshire",
    "sg:tags":[
        "baker"
    ],
    "wof:name":"Dunsters of Bridlington",
    "wof:placetype":"venue"
},
  "geometry": {"coordinates":[-0.2313989997,54.0765151978],"type":"Point"}
}