{
  "type": "Feature",
  "properties": {
    "addr:full":"Blackstone Road Huntingdon Cambridgeshire PE29 6EF",
    "addr:postcode":"pe29 6ef",
    "addr:street":"Blackstone Road",
    "iso:country":"GB",
    "sg:address":"Blackstone Road",
    "sg:city":"Huntingdon",
    "sg:classifiers":[
        {
            "category":"Professional",
            "subcategory":"Computer Services",
            "type":"Services"
        }
    ],
    "sg:phone":"+44 1480 414141",
    "sg:postcode":"PE29 6EF",
    "sg:province":"Cambridgeshire",
    "sg:tags":[
        "system",
        "software"
    ],
    "wof:name":"Tarragon Software Ltd.",
    "wof:placetype":"venue"
},
  "geometry": {"coordinates":[-0.189767,52.345627],"type":"Point"}
}