{
  "type": "Feature",
  "properties": {
    "addr:full":"78-80 Station Street, Kirkby In Ashfield Nottingham Nottinghamshire NG17 7AP",
    "addr:housenumber":"78-80",
    "addr:postcode":"ng17 7ap",
    "addr:street":"Station Street",
    "iso:country":"GB",
    "sg:address":"78-80 Station Street, Kirkby In Ashfield",
    "sg:city":"Nottingham",
    "sg:classifiers":[
        {
            "category":"Banks & Credit Unions",
            "subcategory":"Financial Services",
            "type":"Services"
        }
    ],
    "sg:phone":"+44 1623 756571",
    "sg:postcode":"NG17 7AP",
    "sg:province":"Nottinghamshire",
    "sg:tags":[
        "building",
        "society"
    ],
    "wof:name":"The Nottingham Building Society",
    "wof:placetype":"venue"
},
  "geometry": {"coordinates":[-1.2449560165,53.0987892151],"type":"Point"}
}