{
  "type": "Feature",
  "properties": {
    "iso:country":"GB",
    "sg:address":"South Road",
    "sg:city":"Skegness",
    "sg:classifiers":[
        {
            "category":"Food & Beverages",
            "subcategory":"Candy",
            "type":"Retail Goods"
        }
    ],
    "sg:postcode":"PE24 5TR",
    "sg:province":"Lincolnshire",
    "sg:tags":[
        "confectioner"
    ],
    "wof:name":"The Candy Store",
    "wof:placetype":"venue"
},
  "geometry": {"coordinates":[0.336813,53.223297],"type":"Point"}
}