{
  "type": "Feature",
  "properties": {
    "addr:full":"30 Parnassus Gardens, Fyvie Turriff Aberdeenshire AB53 8QD",
    "addr:housenumber":"30",
    "addr:postcode":"ab53 8qd",
    "addr:street":"Parnassus Gardens",
    "iso:country":"GB",
    "sg:address":"30 Parnassus Gardens, Fyvie",
    "sg:city":"Turriff",
    "sg:classifiers":[
        {
            "category":"Farming",
            "subcategory":"Poultry Farm",
            "type":"Manufacturing & Wholesale Goods"
        }
    ],
    "sg:phone":"+44 1651 891274",
    "sg:postcode":"AB53 8QD",
    "sg:province":"Aberdeenshire",
    "sg:tags":[
        "related"
    ],
    "wof:name":"Highland Cattle Handling Services",
    "wof:placetype":"venue"
},
  "geometry": {"coordinates":[-2.389741,57.431866],"type":"Point"}
}