{
  "type": "Feature",
  "properties": {
    "addr:full":"25 Gloucester Avenue Northampton Northamptonshire NN4 8QE",
    "addr:housenumber":"25",
    "addr:postcode":"nn4 8qe",
    "addr:street":"Gloucester Avenue",
    "iso:country":"GB",
    "sg:address":"25 Gloucester Avenue",
    "sg:city":"Northampton",
    "sg:classifiers":[
        {
            "category":"Building & Trades",
            "subcategory":"Cleaning & Sanitation",
            "type":"Services"
        }
    ],
    "sg:phone":"+44 1604 765447",
    "sg:postcode":"NN4 8QE",
    "sg:province":"Northamptonshire",
    "sg:tags":[
        "cleaner",
        "window"
    ],
    "wof:name":"M J Ford Cleaning Services",
    "wof:placetype":"venue"
},
  "geometry": {"coordinates":[-0.9004909992,52.2188606262],"type":"Point"}
}