{
  "type": "Feature",
  "properties": {
    "iso:country":"GB",
    "sg:address":"59 High Street",
    "sg:city":"Sittingbourne",
    "sg:classifiers":[
        {
            "category":"Banks & Credit Unions",
            "subcategory":"Financial Services",
            "type":"Services"
        }
    ],
    "sg:phone":"+44 1795 470100",
    "sg:postcode":"ME10 4AW",
    "sg:province":"Kent",
    "sg:tags":[
        "adviser",
        "independent"
    ],
    "wof:name":"Privatfinans Ltd.",
    "wof:placetype":"venue"
},
  "geometry": {"coordinates":[0.736785,51.339748],"type":"Point"}
}