{
  "type": "Feature",
  "properties": {
    "addr:full":"40a Morthen Rd, Wickersley Rotherham South Yorkshire S66 1EN",
    "addr:housenumber":"40a",
    "addr:postcode":"s66 1en",
    "addr:street":"Morthen Rd",
    "iso:country":"GB",
    "sg:address":"40a Morthen Rd, Wickersley",
    "sg:city":"Rotherham",
    "sg:classifiers":[
        {
            "category":"Freight",
            "type":"Transportation"
        }
    ],
    "sg:phone":"+44 1709 548977",
    "sg:postcode":"S66 1EN",
    "sg:province":"South Yorkshire",
    "sg:tags":[
        "haulage",
        "road"
    ],
    "wof:name":"L. Payling Limited",
    "wof:placetype":"venue"
},
  "geometry": {"coordinates":[-1.279997,53.418591],"type":"Point"}
}