{
  "type": "Feature",
  "properties": {
    "addr:full":"Ince Green Lane, Ince Wigan Lancashire WN2 2DG",
    "addr:postcode":"wn2 2dg",
    "addr:street":"Green Lane",
    "iso:country":"GB",
    "sg:address":"Ince Green Lane, Ince",
    "sg:city":"Wigan",
    "sg:classifiers":[
        {
            "category":"Bars & Pubs",
            "type":"Food & Drink"
        }
    ],
    "sg:phone":"+44 1942 201091",
    "sg:postcode":"WN2 2DG",
    "sg:province":"Lancashire",
    "sg:tags":[
        "pubs",
        "inn"
    ],
    "wof:name":"Anderton Arms",
    "wof:placetype":"venue"
},
  "geometry": {"coordinates":[-2.605579,53.54285],"type":"Point"}
}