{
  "type": "Feature",
  "properties": {
    "addr:full":"Brimscombe Hill, Brimscombe Stroud Gloucestershire GL5 2QP",
    "addr:postcode":"gl5 2qp",
    "addr:street":"Brimscombe;Brimscombe",
    "iso:country":"GB",
    "sg:address":"Brimscombe Hill, Brimscombe",
    "sg:city":"Stroud",
    "sg:classifiers":[
        {
            "category":"Organizations",
            "subcategory":"Non-profit Organization",
            "type":"Services"
        }
    ],
    "sg:phone":"+44 1453 883633",
    "sg:postcode":"GL5 2QP",
    "sg:province":"Gloucestershire",
    "sg:tags":[
        "organisation",
        "voluntary",
        "charity"
    ],
    "wof:name":"The Nelson Trust",
    "wof:placetype":"venue"
},
  "geometry": {"coordinates":[-2.1810429096,51.7192459106],"type":"Point"}
}