{
  "type": "Feature",
  "properties": {
    "iso:country":"GB",
    "sg:address":"P O Box 5109, Hampton In Arden",
    "sg:city":"Solihull",
    "sg:classifiers":[
        {
            "category":"Shopping",
            "subcategory":"Music",
            "type":"Retail Goods"
        }
    ],
    "sg:postcode":"B92 0HW",
    "sg:province":"West Midlands",
    "sg:tags":[
        "record",
        "tape",
        "cd"
    ],
    "wof:name":"Stephen Lee",
    "wof:placetype":"venue"
},
  "geometry": {"coordinates":[-1.70253,52.425159],"type":"Point"}
}