{
  "type": "Feature",
  "properties": {
    "addr:full":"36 Wickery Dene, Wootton Fills Northampton Northamptonshire NN4 6BE",
    "addr:housenumber":"36",
    "addr:postcode":"nn4 6be",
    "addr:street":"Wickery Dene Wootton Fills",
    "iso:country":"GB",
    "sg:address":"36 Wickery Dene, Wootton Fills",
    "sg:city":"Northampton",
    "sg:classifiers":[
        {
            "category":"Building & Trades",
            "subcategory":"Plumbing",
            "type":"Services"
        }
    ],
    "sg:postcode":"NN4 6BE",
    "sg:province":"Northamptonshire",
    "sg:tags":[
        "heating"
    ],
    "wof:name":"Austin,Malcom,",
    "wof:placetype":"venue"
},
  "geometry": {"coordinates":[-0.8693839908,52.2026557922],"type":"Point"}
}