{
  "type": "Feature",
  "properties": {
    "addr:full":"Engineers House The Promenade, Clifton Down Bristol City of Bristol BS8 3NB",
    "addr:postcode":"bs8 3nb",
    "addr:street":"The Promenade Clifton Down",
    "iso:country":"GB",
    "sg:address":"Engineers House The Promenade, Clifton Down",
    "sg:city":"Bristol",
    "sg:classifiers":[
        {
            "category":"Education",
            "subcategory":"Special Training",
            "type":"Public Place"
        }
    ],
    "sg:phone":"+44 117 973 7447",
    "sg:postcode":"BS8 3NB",
    "sg:province":"City of Bristol",
    "sg:tags":[
        "product",
        "centre"
    ],
    "wof:name":"The Learning Combination Ltd.",
    "wof:placetype":"venue"
},
  "geometry": {"coordinates":[-2.615904,51.46077],"type":"Point"}
}