{
  "type": "Feature",
  "properties": {
    "iso:country":"GB",
    "sg:address":"29 Parsonage Street",
    "sg:city":"Dursley",
    "sg:classifiers":[
        {
            "category":"Food & Beverages",
            "subcategory":"Fruits & Vegetables",
            "type":"Retail Goods"
        }
    ],
    "sg:phone":"+44 1453 542088",
    "sg:postcode":"GL11 4BW",
    "sg:province":"Gloucestershire",
    "sg:tags":[
        "greengrocer"
    ],
    "wof:name":"Bramleys",
    "wof:placetype":"venue"
},
  "geometry": {"coordinates":[-2.356863,51.682087],"type":"Point"}
}