{
  "type": "Feature",
  "properties": {
    "addr:full":"Flat 2 41a Cromwell Avenue, Highgate London Greater London N6 5HN",
    "addr:housenumber":"41a",
    "addr:postcode":"n6 5hn",
    "addr:street":"Cromwell Avenue Highgate",
    "iso:country":"GB",
    "sg:address":"Flat 2 41a Cromwell Avenue, Highgate",
    "sg:city":"London",
    "sg:classifiers":[
        {
            "category":"Building & Trades",
            "subcategory":"Landscaping Services",
            "type":"Services"
        }
    ],
    "sg:phone":"+44 20 8341 3808",
    "sg:postcode":"N6 5HN",
    "sg:province":"Greater London",
    "sg:tags":[
        "gardening"
    ],
    "wof:name":"Rob Knaap",
    "wof:placetype":"venue"
},
  "geometry": {"coordinates":[-0.14102,51.571369],"type":"Point"}
}