{
  "type": "Feature",
  "properties": {
    "addr:full":"27 Dudley Street, Sedgley Dudley Staffordshire DY3 1SG",
    "addr:housenumber":"27",
    "addr:postcode":"dy3 1sg",
    "addr:street":"Dudley Street",
    "iso:country":"GB",
    "sg:address":"27 Dudley Street, Sedgley",
    "sg:city":"Dudley",
    "sg:classifiers":[
        {
            "category":"Real Estate",
            "subcategory":"Surveying",
            "type":"Services"
        },
        {
            "category":"Real Estate",
            "subcategory":"Architect",
            "type":"Services"
        }
    ],
    "sg:postcode":"DY3 1SG",
    "sg:province":"Staffordshire",
    "sg:tags":[
        "surveyor",
        "valuer"
    ],
    "wof:name":"Wakeman Associates",
    "wof:placetype":"venue"
},
  "geometry": {"coordinates":[-2.120524,52.540123],"type":"Point"}
}