{
  "type": "Feature",
  "properties": {
    "iso:country":"GB",
    "sg:address":"20 Clifton Rd",
    "sg:city":"Tunbridge Wells",
    "sg:classifiers":[
        {
            "category":"Health Services",
            "subcategory":"Dentist",
            "type":"Services"
        }
    ],
    "sg:phone":"+44 1892 540990",
    "sg:postcode":"TN2 3AR",
    "sg:province":"East Sussex",
    "wof:name":"Sinclair M J",
    "wof:placetype":"venue"
},
  "geometry": {"coordinates":[0.278142,51.148643],"type":"Point"}
}