{
  "type": "Feature",
  "properties": {
    "iso:country":"GB",
    "sg:address":"8 White Hart Mews, Southgate",
    "sg:city":"Sleaford",
    "sg:classifiers":[
        {
            "category":"Building & Trades",
            "subcategory":"Construction",
            "type":"Services"
        }
    ],
    "sg:phone":"+44 1529 305704",
    "sg:postcode":"NG34 7RY",
    "sg:province":"Lincolnshire",
    "sg:tags":[
        "ceiling",
        "suspended",
        "contractor"
    ],
    "wof:name":"Carratt Suspended Ceilings Ltd.",
    "wof:placetype":"venue"
},
  "geometry": {"coordinates":[-0.411869,52.994587],"type":"Point"}
}