{
  "type": "Feature",
  "properties": {
    "addr:full":"Meridian Vale House, Meridian Vale Bristol City of Bristol BS8 1BZ",
    "addr:postcode":"bs8 1bz",
    "addr:street":"Meridian Vale",
    "iso:country":"GB",
    "sg:address":"Meridian Vale House, Meridian Vale",
    "sg:city":"Bristol",
    "sg:classifiers":[
        {
            "category":"Building & Trades",
            "subcategory":"Construction",
            "type":"Services"
        }
    ],
    "sg:phone":"+44 117 926 2432",
    "sg:postcode":"BS8 1BZ",
    "sg:province":"City of Bristol",
    "sg:tags":[
        "builder"
    ],
    "wof:name":"Fisher W G & Sons (bristol) Ltd",
    "wof:placetype":"venue"
},
  "geometry": {"coordinates":[-2.6079590321,51.4567108154],"type":"Point"}
}