{
  "type": "Feature",
  "properties": {
    "addr:full":"Bristol & West House, 82 Union Street Glasgow Glasgow City G1 3QS",
    "addr:housenumber":"82",
    "addr:postcode":"g1 3qs",
    "addr:street":"Bristol & West;Union Street",
    "iso:country":"GB",
    "sg:address":"Bristol & West House, 82 Union Street",
    "sg:city":"Glasgow",
    "sg:classifiers":[
        {
            "category":"Professional",
            "type":"Services"
        },
        {
            "category":"Education",
            "subcategory":"Special Training",
            "type":"Public Place"
        }
    ],
    "sg:phone":"+44 141 221 5051",
    "sg:postcode":"G1 3QS",
    "sg:province":"Glasgow City",
    "sg:tags":[
        "repair",
        "product",
        "tech",
        "maintenance",
        "centre"
    ],
    "wof:name":"C Tec",
    "wof:placetype":"venue"
},
  "geometry": {"coordinates":[-4.2566580772,55.8597946167],"type":"Point"}
}