{
  "type": "Feature",
  "properties": {
    "addr:full":"Paignton Road, Stoke Gabriel Totnes Devon TQ9 6SE",
    "addr:postcode":"tq9 6se",
    "addr:street":"Paignton Road",
    "iso:country":"GB",
    "sg:address":"Paignton Road, Stoke Gabriel",
    "sg:city":"Totnes",
    "sg:classifiers":[
        {
            "category":"Cafe",
            "type":"Food & Drink"
        }
    ],
    "sg:postcode":"TQ9 6SE",
    "sg:province":"Devon",
    "sg:tags":[
        "tea",
        "room"
    ],
    "wof:name":"Mrs G's Teashop & Dining Room",
    "wof:placetype":"venue"
},
  "geometry": {"coordinates":[-3.622959,50.407505],"type":"Point"}
}