{
  "type": "Feature",
  "properties": {
    "iso:country":"GB",
    "sg:address":"Cliff Road",
    "sg:city":"Hornsea",
    "sg:classifiers":[
        {
            "category":"Recreation",
            "subcategory":"Campground",
            "type":"Entertainment"
        }
    ],
    "sg:phone":"+44 1964 532331",
    "sg:postcode":"HU18 1JY",
    "sg:province":"East Riding of Yorkshire",
    "sg:tags":[
        "caravan",
        "park"
    ],
    "wof:name":"North Cliff",
    "wof:placetype":"venue"
},
  "geometry": {"coordinates":[-0.171839,53.908234],"type":"Point"}
}