{
  "type": "Feature",
  "properties": {
    "iso:country":"GB",
    "sg:address":"39-41 High Street",
    "sg:city":"Dumbarton",
    "sg:classifiers":[
        {
            "category":"Shopping",
            "subcategory":"Clothing, Apparel, & Fashions",
            "type":"Retail Goods"
        }
    ],
    "sg:phone":"+44 1389 761787",
    "sg:postcode":"G82 1LS",
    "sg:province":"Argyll and Bute",
    "sg:tags":[
        "shop"
    ],
    "wof:name":"Kirkwood & Co. Ltd.",
    "wof:placetype":"venue"
},
  "geometry": {"coordinates":[-4.569929,55.943085],"type":"Point"}
}