{
  "type": "Feature",
  "properties": {
    "iso:country":"GB",
    "sg:address":"25 Eastcheap",
    "sg:city":"London",
    "sg:classifiers":[
        {
            "category":"Insurance",
            "subcategory":"Insurance Agent",
            "type":"Services"
        }
    ],
    "sg:postcode":"EC3M 1LE",
    "sg:province":"Greater London",
    "sg:tags":[
        "broker"
    ],
    "wof:name":"Alfred Blackmore & Co. Ltd.",
    "wof:placetype":"venue"
},
  "geometry": {"coordinates":[-0.084184,51.510765],"type":"Point"}
}