{
  "type": "Feature",
  "properties": {
    "iso:country":"GB",
    "sg:address":"27 Park Farm Road, Great Barr",
    "sg:city":"Birmingham",
    "sg:classifiers":[
        {
            "category":"Real Estate",
            "subcategory":"Surveying",
            "type":"Services"
        }
    ],
    "sg:postcode":"B43 7QQ",
    "sg:province":"West Midlands",
    "sg:tags":[
        "surveyor",
        "valuer"
    ],
    "wof:name":"Patrick J Cluxton",
    "wof:placetype":"venue"
},
  "geometry": {"coordinates":[-1.915083,52.556881],"type":"Point"}
}