{
  "type": "Feature",
  "properties": {
    "addr:full":"Burwell Village College, The Causeway, Burwell Cambridge Cambridgeshire CB5 0DX",
    "addr:postcode":"cb5 0dx",
    "addr:street":"The Causeway Burwell",
    "iso:country":"GB",
    "sg:address":"Burwell Village College, The Causeway, Burwell",
    "sg:city":"Cambridge",
    "sg:classifiers":[
        {
            "category":"Professional",
            "subcategory":"Printing & Photocopies",
            "type":"Services"
        }
    ],
    "sg:phone":"+44 1638 613102",
    "sg:postcode":"CB5 0DX",
    "sg:province":"Cambridgeshire",
    "sg:tags":[
        "plate",
        "lithographic",
        "maker"
    ],
    "wof:name":"Burwell Community Print Centre Ltd.",
    "wof:placetype":"venue"
},
  "geometry": {"coordinates":[0.328955,52.277561],"type":"Point"}
}