{
  "type": "Feature",
  "properties": {
    "addr:full":"Grasmere Top Road, North Killingholme Immingham Lincolnshire DN40 3JU",
    "addr:postcode":"dn40 3ju",
    "addr:street":"Top Road North",
    "iso:country":"GB",
    "sg:address":"Grasmere Top Road, North Killingholme",
    "sg:city":"Immingham",
    "sg:classifiers":[
        {
            "category":"Manufacturing",
            "subcategory":"Metals",
            "type":"Manufacturing & Wholesale Goods"
        }
    ],
    "sg:postcode":"DN40 3JU",
    "sg:province":"Lincolnshire",
    "sg:tags":[
        "steel",
        "fabricator",
        "erectors"
    ],
    "wof:name":"Pilgrim Fabrication",
    "wof:placetype":"venue"
},
  "geometry": {"coordinates":[-0.2752439976,53.6421661377],"type":"Point"}
}