{
  "type": "Feature",
  "properties": {
    "addr:full":"Unit 4 Swan Business Park, Sandpit Road Dartford Kent DA1 5ED",
    "addr:housenumber":"unit 4",
    "addr:postcode":"da1 5ed",
    "addr:street":"Swan Business Park Sandpit Road",
    "iso:country":"GB",
    "sg:address":"Unit 4 Swan Business Park, Sandpit Road",
    "sg:city":"Dartford",
    "sg:classifiers":[
        {
            "category":"Shopping",
            "subcategory":"Crafts & Fabrics",
            "type":"Retail Goods"
        }
    ],
    "sg:phone":"+44 1322 279210",
    "sg:postcode":"DA1 5ED",
    "sg:province":"Kent",
    "sg:tags":[
        "machine",
        "sewing",
        "knitting"
    ],
    "wof:name":"Aisin (U K) Ltd.",
    "wof:placetype":"venue"
},
  "geometry": {"coordinates":[0.220555,51.444633],"type":"Point"}
}