{
  "type": "Feature",
  "properties": {
    "iso:country":"GB",
    "sg:address":"Unit 2 Greaves Way, Stanbridge Road",
    "sg:city":"Leighton Buzzard",
    "sg:classifiers":[
        {
            "category":"Professional",
            "subcategory":"Engineering",
            "type":"Services"
        }
    ],
    "sg:phone":"+44 1525 373310",
    "sg:postcode":"LU7 4QB",
    "sg:province":"Bedfordshire",
    "sg:tags":[
        "precision",
        "engineer"
    ],
    "wof:name":"Littler Co. Ltd.",
    "wof:placetype":"venue"
},
  "geometry": {"coordinates":[-0.651574,51.913673],"type":"Point"}
}