{
  "type": "Feature",
  "properties": {
    "addr:full":"Sir Frank Whittle Road Derby Derbyshire DE21 4SX",
    "addr:postcode":"de21 4sx",
    "addr:street":"Sir Frank Whittle Road",
    "iso:country":"GB",
    "sg:address":"Sir Frank Whittle Road",
    "sg:city":"Derby",
    "sg:classifiers":[
        {
            "category":"Autos & Motor Vehicles",
            "subcategory":"Automobile Sales",
            "type":"Retail Goods"
        }
    ],
    "sg:postcode":"DE21 4SX",
    "sg:province":"Derbyshire",
    "sg:tags":[
        "car"
    ],
    "wof:name":"Derwent Securities Ltd.",
    "wof:placetype":"venue"
},
  "geometry": {"coordinates":[-1.459504,52.947895],"type":"Point"}
}