{
  "type": "Feature",
  "properties": {
    "iso:country":"GB",
    "sg:address":"5 Clarkston Road",
    "sg:city":"Glasgow",
    "sg:classifiers":[
        {
            "category":"Home & Garden",
            "subcategory":"Furniture",
            "type":"Retail Goods"
        }
    ],
    "sg:postcode":"G44 4EF",
    "sg:province":"East Renfrewshire",
    "wof:name":"Ian Wright",
    "wof:placetype":"venue"
},
  "geometry": {"coordinates":[-4.2618870735,55.8176651001],"type":"Point"}
}