{
  "type": "Feature",
  "properties": {
    "iso:country":"GB",
    "sg:address":"18 The George Shopping Centre",
    "sg:city":"Grantham",
    "sg:classifiers":[
        {
            "category":"Shopping",
            "subcategory":"Clothing, Apparel, & Fashions",
            "type":"Retail Goods"
        }
    ],
    "sg:phone":"+44 1476 578899",
    "sg:postcode":"NG31 6LH",
    "sg:province":"Lincolnshire",
    "sg:tags":[
        "shop"
    ],
    "sg:website":"http://www.ewm.co.uk",
    "wof:name":"The Edinburgh Woollen Mill Ltd.",
    "wof:placetype":"venue"
},
  "geometry": {"coordinates":[-0.642859,52.913197],"type":"Point"}
}