{
  "type": "Feature",
  "properties": {
    "iso:country":"GB",
    "sg:address":"Unit 15 Clifton Road",
    "sg:city":"Huntingdon",
    "sg:classifiers":[
        {
            "category":"Professional",
            "subcategory":"Engineering",
            "type":"Services"
        }
    ],
    "sg:phone":"+44 1480 436663",
    "sg:postcode":"PE29 7EJ",
    "sg:province":"Cambridgeshire",
    "sg:tags":[
        "engineer",
        "mechanical"
    ],
    "wof:name":"Lecol Engineering Ltd.",
    "wof:placetype":"venue"
},
  "geometry": {"coordinates":[-0.184599,52.343876],"type":"Point"}
}