{
  "type": "Feature",
  "properties": {
    "addr:full":"85-99 Montague Street Rothesay Argyll and Bute PA20 0HP",
    "addr:housenumber":"85-99",
    "addr:postcode":"pa20 0hp",
    "addr:street":"Montague Street",
    "iso:country":"GB",
    "sg:address":"85-99 Montague Street",
    "sg:city":"Rothesay",
    "sg:classifiers":[
        {
            "category":"Shopping",
            "subcategory":"Department Store",
            "type":"Retail Goods"
        }
    ],
    "sg:phone":"+44 1700 503414",
    "sg:postcode":"PA20 0HP",
    "sg:province":"Argyll and Bute",
    "wof:name":"Woolworths Plc",
    "wof:placetype":"venue"
},
  "geometry": {"coordinates":[-5.0695209503,55.8588943481],"type":"Point"}
}