{
  "type": "Feature",
  "properties": {
    "addr:full":"Newhall Farm, Newhall Lane, Edingley Newark Nottinghamshire NG22 8BS",
    "addr:postcode":"ng22 8bs",
    "addr:street":"Newhall;Newhall Lane",
    "iso:country":"GB",
    "sg:address":"Newhall Farm, Newhall Lane, Edingley",
    "sg:city":"Newark",
    "sg:classifiers":[
        {
            "category":"Farming",
            "subcategory":"Livestock Farm",
            "type":"Manufacturing & Wholesale Goods"
        }
    ],
    "sg:phone":"+44 1623 883041",
    "sg:postcode":"NG22 8BS",
    "sg:province":"Nottinghamshire",
    "sg:tags":[
        "others"
    ],
    "wof:name":"D W H Brown",
    "wof:placetype":"venue"
},
  "geometry": {"coordinates":[-1.006759,53.095505],"type":"Point"}
}