{
  "type": "Feature",
  "properties": {
    "iso:country":"GB",
    "sg:address":"Hobbs House, Bessborough Road",
    "sg:city":"Harrow",
    "sg:classifiers":[
        {
            "category":"Professional",
            "subcategory":"Management & Consulting",
            "type":"Services"
        }
    ],
    "sg:phone":"+44 20 8423 2400",
    "sg:postcode":"HA1 3EX",
    "sg:province":"Greater London",
    "sg:tags":[
        "consultant",
        "business"
    ],
    "sg:website":"http://www.altonwood.com",
    "wof:name":"Altonwood Project Services Ltd.",
    "wof:placetype":"venue"
},
  "geometry": {"coordinates":[-0.3427650034,51.5777816772],"type":"Point"}
}