{
  "type": "Feature",
  "properties": {
    "addr:full":"15-17 Church Road, Barnes London Greater London SW13 9HG",
    "addr:housenumber":"15-17",
    "addr:postcode":"sw13 9hg",
    "addr:street":"Church Road",
    "iso:country":"GB",
    "sg:address":"15-17 Church Road, Barnes",
    "sg:city":"London",
    "sg:classifiers":[
        {
            "category":"Professional",
            "subcategory":"Lawyer & Legal Services",
            "type":"Services"
        }
    ],
    "sg:phone":"+44 20 8939 6300",
    "sg:postcode":"SW13 9HG",
    "sg:province":"Greater London",
    "sg:tags":[
        "solicitor"
    ],
    "wof:name":"Rodgers & Burton",
    "wof:placetype":"venue"
},
  "geometry": {"coordinates":[-0.246824,51.473709],"type":"Point"}
}