{
  "type": "Feature",
  "properties": {
    "addr:full":"111 High Street Marlborough Berkshire SN8 1LT",
    "addr:housenumber":"111",
    "addr:postcode":"sn8 1lt",
    "addr:street":"High Street",
    "iso:country":"GB",
    "sg:address":"111 High Street",
    "sg:city":"Marlborough",
    "sg:classifiers":[
        {
            "category":"Bars & Pubs",
            "type":"Food & Drink"
        }
    ],
    "sg:phone":"+44 1672 512064",
    "sg:postcode":"SN8 1LT",
    "sg:province":"Berkshire",
    "sg:tags":[
        "pubs",
        "inn"
    ],
    "wof:name":"The Royal Oak",
    "wof:placetype":"venue"
},
  "geometry": {"coordinates":[-1.7314809561,51.4206542969],"type":"Point"}
}