{
  "type": "Feature",
  "properties": {
    "iso:country":"GB",
    "sg:address":"48 Victoria Road",
    "sg:city":"Exmouth",
    "sg:classifiers":[
        {
            "category":"Social Services",
            "subcategory":"Retirement Home",
            "type":"Services"
        }
    ],
    "sg:postcode":"EX8 1DW",
    "sg:province":"Devon",
    "sg:tags":[
        "residential",
        "care"
    ],
    "wof:name":"Trevena",
    "wof:placetype":"venue"
},
  "geometry": {"coordinates":[-3.418379,50.618542],"type":"Point"}
}