{
  "type": "Feature",
  "properties": {
    "iso:country":"GB",
    "sg:address":"Launday Cottage, Bedfield Lane, Headbourne Worthy",
    "sg:city":"Winchester",
    "sg:classifiers":[
        {
            "category":"Professional",
            "subcategory":"Management & Consulting",
            "type":"Services"
        }
    ],
    "sg:phone":"+44 1962 883305",
    "sg:postcode":"SO23 7UA",
    "sg:province":"Hampshire",
    "sg:tags":[
        "consultant",
        "business"
    ],
    "wof:name":"Bibs-Industry",
    "wof:placetype":"venue"
},
  "geometry": {"coordinates":[-1.3062980175,51.0892791748],"type":"Point"}
}