{
  "type": "Feature",
  "properties": {
    "addr:full":"Kingsway Lyme Regis Devon DT7 3DY",
    "addr:postcode":"dt7 3dy",
    "addr:street":"Kingsway",
    "iso:country":"GB",
    "sg:address":"Kingsway",
    "sg:city":"Lyme Regis",
    "sg:classifiers":[
        {
            "category":"Education",
            "subcategory":"School",
            "type":"Public Place"
        }
    ],
    "sg:phone":"+44 1297 442623",
    "sg:postcode":"DT7 3DY",
    "sg:province":"Devon",
    "sg:tags":[
        "local",
        "authority"
    ],
    "wof:name":"St. Michael's Primary School",
    "wof:placetype":"venue"
},
  "geometry": {"coordinates":[-2.9355940819,50.7298583984],"type":"Point"}
}