{
  "type": "Feature",
  "properties": {
    "addr:full":"2 Edward Street Bridgwater Somerset TA6 5ET",
    "addr:housenumber":"2",
    "addr:postcode":"ta6 5et",
    "addr:street":"Edward Street",
    "iso:country":"GB",
    "sg:address":"2 Edward Street",
    "sg:city":"Bridgwater",
    "sg:classifiers":[
        {
            "category":"Shopping",
            "subcategory":"News",
            "type":"Retail Goods"
        }
    ],
    "sg:phone":"+44 1278 422137",
    "sg:postcode":"TA6 5ET",
    "sg:province":"Somerset",
    "sg:tags":[
        "newsagent"
    ],
    "wof:name":"Watts News",
    "wof:placetype":"venue"
},
  "geometry": {"coordinates":[-2.993079,51.127766],"type":"Point"}
}