{
  "type": "Feature",
  "properties": {
    "addr:full":"76 Elfrida Crescent Catford Greater London SE6 3EN",
    "addr:housenumber":"76",
    "addr:postcode":"se6 3en",
    "addr:street":"Elfrida Crescent",
    "iso:country":"GB",
    "sg:address":"76 Elfrida Crescent",
    "sg:city":"Catford",
    "sg:classifiers":[
        {
            "category":"Retail",
            "subcategory":"Driving School",
            "type":"Services"
        }
    ],
    "sg:phone":"+44 20 8697 7894",
    "sg:postcode":"SE6 3EN",
    "sg:province":"Greater London",
    "wof:name":"Turning Point School of Motoring",
    "wof:placetype":"venue"
},
  "geometry": {"coordinates":[-0.0239100009,51.4286193848],"type":"Point"}
}