{
  "type": "Feature",
  "properties": {
    "addr:full":"Southfield La Driffield East Riding of Yorkshire YO25 8TU",
    "addr:postcode":"yo25 8tu",
    "addr:street":"Southfield La",
    "iso:country":"GB",
    "sg:address":"Southfield La",
    "sg:city":"Driffield",
    "sg:classifiers":[
        {
            "category":"Recreation",
            "subcategory":"Campground",
            "type":"Entertainment"
        }
    ],
    "sg:phone":"+44 1262 468491",
    "sg:postcode":"YO25 8TU",
    "sg:province":"East Riding of Yorkshire",
    "sg:tags":[
        "holiday",
        "centre",
        "camp"
    ],
    "wof:name":"Beach Bank Caravan Park",
    "wof:placetype":"venue"
},
  "geometry": {"coordinates":[-0.278829,53.973469],"type":"Point"}
}