{
  "type": "Feature",
  "properties": {
    "addr:full":"14 Grand Union Centre West Row Ladbroke Grove Greater London W10 5AS",
    "addr:housenumber":"14",
    "addr:postcode":"w10 5as",
    "addr:street":"Grand Union;West Row",
    "iso:country":"GB",
    "sg:address":"14 Grand Union Centre West Row",
    "sg:city":"Ladbroke Grove",
    "sg:classifiers":[
        {
            "category":"Communications",
            "subcategory":"Newspaper",
            "type":"Services"
        }
    ],
    "sg:phone":"+44 20 8968 0234",
    "sg:postcode":"W10 5AS",
    "sg:province":"Greater London",
    "sg:tags":[
        "magazine"
    ],
    "wof:name":"Skin Two Magazine",
    "wof:placetype":"venue"
},
  "geometry": {"coordinates":[-0.213459,51.5232849121],"type":"Point"}
}