{
  "type": "Feature",
  "properties": {
    "addr:full":"Harold Road Centre, 170 Harold Road London Greater London E13 0SE",
    "addr:housenumber":"170",
    "addr:postcode":"e13 0se",
    "addr:street":"Harold Road;Harold Road",
    "iso:country":"GB",
    "sg:address":"Harold Road Centre, 170 Harold Road",
    "sg:city":"London",
    "sg:classifiers":[
        {
            "category":"Organizations",
            "subcategory":"Non-profit Organization",
            "type":"Services"
        }
    ],
    "sg:postcode":"E13 0SE",
    "sg:province":"Greater London",
    "sg:tags":[
        "organisation",
        "voluntary",
        "charity"
    ],
    "wof:name":"Newham Community Renewal Programme Ltd.",
    "wof:placetype":"venue"
},
  "geometry": {"coordinates":[0.02715,51.534019],"type":"Point"}
}