{
  "type": "Feature",
  "properties": {
    "addr:full":"Davy Bank, Hadrian Road Wallsend Tyne and Wear NE28 6UZ",
    "addr:postcode":"ne28 6uz",
    "addr:street":"Hadrian Road",
    "iso:country":"GB",
    "sg:address":"Davy Bank, Hadrian Road",
    "sg:city":"Wallsend",
    "sg:classifiers":[
        {
            "category":"Home & Garden",
            "subcategory":"Hardware",
            "type":"Retail Goods"
        },
        {
            "category":"Manufacturing",
            "subcategory":"Building Materials",
            "type":"Manufacturing & Wholesale Goods"
        }
    ],
    "sg:phone":"+44 191 262 8811",
    "sg:postcode":"NE28 6UZ",
    "sg:province":"Tyne and Wear",
    "sg:tags":[
        "merchant",
        "equipment",
        "bathroom",
        "builder",
        "fitting"
    ],
    "wof:name":"Jewson Ltd.",
    "wof:placetype":"venue"
},
  "geometry": {"coordinates":[-1.5181809664,54.99061203],"type":"Point"}
}