{
  "type": "Feature",
  "properties": {
    "addr:full":"6 Margaret Street Ammanford Carmarthenshire SA18 2NP",
    "addr:housenumber":"6",
    "addr:postcode":"sa18 2np",
    "addr:street":"Margaret Street",
    "iso:country":"GB",
    "sg:address":"6 Margaret Street",
    "sg:city":"Ammanford",
    "sg:classifiers":[
        {
            "category":"Shopping",
            "subcategory":"Pharmacy",
            "type":"Retail Goods"
        }
    ],
    "sg:phone":"+44 1269 594488",
    "sg:postcode":"SA18 2NP",
    "sg:province":"Carmarthenshire",
    "sg:tags":[
        "pharmacist",
        "store",
        "drug",
        "chemist"
    ],
    "wof:name":"H M Davies & A R Evans",
    "wof:placetype":"venue"
},
  "geometry": {"coordinates":[-3.9822199345,51.7955513],"type":"Point"}
}