{
  "type": "Feature",
  "properties": {
    "addr:full":"The Temple Montpelier Road Brighton East Sussex BN1 3AT",
    "addr:postcode":"bn1 3at",
    "addr:street":"Montpelier Road",
    "iso:country":"GB",
    "sg:address":"The Temple Montpelier Road",
    "sg:city":"Brighton",
    "sg:classifiers":[
        {
            "category":"Education",
            "subcategory":"School",
            "type":"Public Place"
        }
    ],
    "sg:phone":"+44 1273 734112",
    "sg:postcode":"BN1 3AT",
    "sg:province":"East Sussex",
    "sg:tags":[
        "independent",
        "preparatory"
    ],
    "wof:name":"Brighton & Hove High School",
    "wof:placetype":"venue"
},
  "geometry": {"coordinates":[-0.151579,50.82692],"type":"Point"}
}