{
  "type": "Feature",
  "properties": {
    "addr:full":"10 Montague Place Worthing West Sussex BN11 3BG",
    "addr:housenumber":"10",
    "addr:postcode":"bn11 3bg",
    "addr:street":"Montague Place",
    "iso:country":"GB",
    "sg:address":"10 Montague Place",
    "sg:city":"Worthing",
    "sg:classifiers":[
        {
            "category":"Restaurant",
            "type":"Food & Drink"
        }
    ],
    "sg:phone":"+44 1903 200388",
    "sg:postcode":"BN11 3BG",
    "sg:province":"West Sussex",
    "wof:name":"Oliver's Restaurant",
    "wof:placetype":"venue"
},
  "geometry": {"coordinates":[-0.371574,50.809978],"type":"Point"}
}