{
  "type": "Feature",
  "properties": {
    "iso:country":"GB",
    "sg:address":"School House, Thornham Magna",
    "sg:city":"Eye",
    "sg:classifiers":[
        {
            "category":"Building & Trades",
            "subcategory":"Construction",
            "type":"Services"
        }
    ],
    "sg:phone":"+44 1379 678459",
    "sg:postcode":"IP23 8HA",
    "sg:province":"Suffolk",
    "sg:tags":[
        "builder"
    ],
    "wof:name":"J H Vaudrey & Son Ltd",
    "wof:placetype":"venue"
},
  "geometry": {"coordinates":[1.0910910368,52.3040657043],"type":"Point"}
}