{
  "type": "Feature",
  "properties": {
    "addr:full":"Unit 0, St Marks Business Centre, St James Industrial Estate Corby Northamptonshire NN18 8AN",
    "addr:housenumber":"unit 0",
    "addr:postcode":"nn18 8an",
    "addr:street":"St;St;Industrial Estate",
    "iso:country":"GB",
    "sg:address":"Unit 0, St Marks Business Centre, St James Industrial Estate",
    "sg:city":"Corby",
    "sg:classifiers":[
        {
            "category":"Building & Trades",
            "subcategory":"Cleaning & Sanitation",
            "type":"Services"
        }
    ],
    "sg:postcode":"NN18 8AN",
    "sg:province":"Northamptonshire",
    "sg:tags":[
        "commercial"
    ],
    "wof:name":"Dawsons Cleaning Services",
    "wof:placetype":"venue"
},
  "geometry": {"coordinates":[-0.6848040223,52.4871711731],"type":"Point"}
}