{
  "type": "Feature",
  "properties": {
    "addr:full":"51 Long Meadow, Frimley Camberley Hampshire GU16 8RS",
    "addr:housenumber":"51",
    "addr:postcode":"gu16 8rs",
    "iso:country":"GB",
    "sg:address":"51 Long Meadow, Frimley",
    "sg:city":"Camberley",
    "sg:classifiers":[
        {
            "category":"Professional",
            "subcategory":"Art Services",
            "type":"Services"
        }
    ],
    "sg:phone":"+44 1276 23494",
    "sg:postcode":"GU16 8RS",
    "sg:province":"Hampshire",
    "sg:tags":[
        "photographer"
    ],
    "wof:name":"David Hart",
    "wof:placetype":"venue"
},
  "geometry": {"coordinates":[-0.7314789891,51.3258132935],"type":"Point"}
}