{
  "type": "Feature",
  "properties": {
    "iso:country":"GB",
    "sg:address":"The Green, Fringford",
    "sg:city":"Bicester",
    "sg:classifiers":[
        {
            "category":"Education",
            "subcategory":"School",
            "type":"Public Place"
        }
    ],
    "sg:phone":"+44 1869 277397",
    "sg:postcode":"OX27 8DY",
    "sg:province":"Buckinghamshire",
    "sg:tags":[
        "local",
        "authority"
    ],
    "wof:name":"Fringford C Of E Primary School",
    "wof:placetype":"venue"
},
  "geometry": {"coordinates":[-1.176709,51.948944],"type":"Point"}
}