{
  "type": "Feature",
  "properties": {
    "iso:country":"GB",
    "sg:address":"Waterloo Gardens",
    "sg:city":"London",
    "sg:classifiers":[
        {
            "category":"Education",
            "subcategory":"School",
            "type":"Public Place"
        }
    ],
    "sg:phone":"+44 20 8980 4920",
    "sg:postcode":"E2 9JY",
    "sg:province":"Greater London",
    "sg:tags":[
        "local",
        "authority"
    ],
    "wof:name":"St John the Baptist R C Junior School",
    "wof:placetype":"venue"
},
  "geometry": {"coordinates":[-0.052219,51.533291],"type":"Point"}
}