{
  "type": "Feature",
  "properties": {
    "addr:full":"Allostock Grange, Middlewich Road, Allostock Knutsford Cheshire WA16 9JX",
    "addr:postcode":"wa16 9jx",
    "addr:street":"Middlewich Road",
    "iso:country":"GB",
    "sg:address":"Allostock Grange, Middlewich Road, Allostock",
    "sg:city":"Knutsford",
    "sg:classifiers":[
        {
            "category":"Education",
            "subcategory":"Music School",
            "type":"Public Place"
        }
    ],
    "sg:phone":"+44 1565 723366",
    "sg:postcode":"WA16 9JX",
    "sg:province":"Cheshire",
    "sg:tags":[
        "teacher"
    ],
    "wof:name":"Cheshire School of Music",
    "wof:placetype":"venue"
},
  "geometry": {"coordinates":[-2.3833479881,53.2358093262],"type":"Point"}
}