{
  "type": "Feature",
  "properties": {
    "addr:full":"The Manor House, 260 Ecclesall Rd South Sheffield Derbyshire S11 9PS",
    "addr:housenumber":"260",
    "addr:postcode":"s11 9ps",
    "addr:street":"Ecclesall Rd",
    "iso:country":"GB",
    "sg:address":"The Manor House, 260 Ecclesall Rd South",
    "sg:city":"Sheffield",
    "sg:classifiers":[
        {
            "category":"Education",
            "subcategory":"Special Training",
            "type":"Public Place"
        }
    ],
    "sg:phone":"+44 114 226 3000",
    "sg:postcode":"S11 9PS",
    "sg:province":"Derbyshire",
    "sg:tags":[
        "product",
        "centre"
    ],
    "wof:name":"NHS Management Training Scheme & Mesol Programme",
    "wof:placetype":"venue"
},
  "geometry": {"coordinates":[-1.513951,53.354496],"type":"Point"}
}