{
  "type": "Feature",
  "properties": {
    "addr:full":"Rennies Lane Durham Durham DH1 2RQ",
    "addr:postcode":"dh1 2rq",
    "addr:street":"Rennies Lane",
    "iso:country":"GB",
    "sg:address":"Rennies Lane",
    "sg:city":"Durham",
    "sg:classifiers":[
        {
            "category":"Retail",
            "subcategory":"Auto Repair",
            "type":"Services"
        }
    ],
    "sg:phone":"+44 191 386 0295",
    "sg:postcode":"DH1 2RQ",
    "sg:province":"Durham",
    "sg:tags":[
        "modification",
        "garage"
    ],
    "wof:name":"James Tyson",
    "wof:placetype":"venue"
},
  "geometry": {"coordinates":[-1.543884,54.776375],"type":"Point"}
}