{
  "type": "Feature",
  "properties": {
    "addr:full":"Greenheys Business Centre, Pencroft Way Manchester Cheshire M15 6JJ",
    "addr:postcode":"m15 6jj",
    "addr:street":"Pencroft Way",
    "iso:country":"GB",
    "sg:address":"Greenheys Business Centre, Pencroft Way",
    "sg:city":"Manchester",
    "sg:classifiers":[
        {
            "category":"Professional",
            "subcategory":"Business Services",
            "type":"Services"
        }
    ],
    "sg:phone":"+44 161 232 7007",
    "sg:postcode":"M15 6JJ",
    "sg:province":"Cheshire",
    "sg:tags":[
        "agent",
        "manufacturers'"
    ],
    "wof:name":"Vanhuizen Agencies Ltd.",
    "wof:placetype":"venue"
},
  "geometry": {"coordinates":[-2.243369,53.46241],"type":"Point"}
}