{
  "type": "Feature",
  "properties": {
    "addr:full":"50 The Green, St Peters Way Northampton Northamptonshire NN1 1ST",
    "addr:housenumber":"50",
    "addr:postcode":"nn1 1st",
    "addr:street":"The Green St Peters Way",
    "iso:country":"GB",
    "sg:address":"50 The Green, St Peters Way",
    "sg:city":"Northampton",
    "sg:classifiers":[
        {
            "category":"Retail",
            "subcategory":"Auto Repair",
            "type":"Services"
        }
    ],
    "sg:phone":"+44 1604 20603",
    "sg:postcode":"NN1 1ST",
    "sg:province":"Northamptonshire",
    "sg:tags":[
        "body",
        "car"
    ],
    "wof:name":"Wonow Ltd.",
    "wof:placetype":"venue"
},
  "geometry": {"coordinates":[-0.9031509757,52.2356758118],"type":"Point"}
}