{
  "type": "Feature",
  "properties": {
    "iso:country":"GB",
    "sg:address":"630 Chiswick High Rd",
    "sg:city":"Borehamwood",
    "sg:classifiers":[
        {
            "category":"Communications",
            "subcategory":"Newspaper",
            "type":"Services"
        }
    ],
    "sg:phone":"+44 20 8207 5599",
    "sg:postcode":"W4 5BG",
    "sg:province":"Greater London",
    "sg:tags":[
        "magazine"
    ],
    "wof:name":"United Business Media",
    "wof:placetype":"venue"
},
  "geometry": {"coordinates":[-0.276369,51.49231],"type":"Point"}
}