{
  "type": "Feature",
  "properties": {
    "iso:country":"GB",
    "sg:address":"Unit 2 Lowland Road, Brandon",
    "sg:city":"Durham",
    "sg:classifiers":[
        {
            "category":"Food & Beverages",
            "subcategory":"Bakery",
            "type":"Retail Goods"
        }
    ],
    "sg:phone":"+44 191 378 0942",
    "sg:postcode":"DH7 8NN",
    "sg:province":"Durham",
    "sg:tags":[
        "baker"
    ],
    "wof:name":"Greggs",
    "wof:placetype":"venue"
},
  "geometry": {"coordinates":[-1.630369,54.75132],"type":"Point"}
}