{
  "type": "Feature",
  "properties": {
    "iso:country":"GB",
    "sg:address":"Accelerator, First Floor, Paragon Ho",
    "sg:city":"Manchester",
    "sg:classifiers":[
        {
            "category":"Professional",
            "subcategory":"Art Services",
            "type":"Services"
        }
    ],
    "sg:phone":"+44 161 877 9262",
    "sg:postcode":"M16 0LN",
    "sg:province":"Cheshire",
    "sg:tags":[
        "graphic",
        "designer"
    ],
    "wof:name":"Taplin Design",
    "wof:placetype":"venue"
},
  "geometry": {"coordinates":[-2.24881,53.479622],"type":"Point"}
}