{
  "type": "Feature",
  "properties": {
    "iso:country":"GB",
    "sg:address":"Unit 11 Troy Industrial Estate, Jill Lane",
    "sg:city":"Redditch",
    "sg:classifiers":[
        {
            "category":"Manufacturing",
            "subcategory":"Jewelry",
            "type":"Manufacturing & Wholesale Goods"
        },
        {
            "category":"Building & Trades",
            "subcategory":"Construction",
            "type":"Services"
        }
    ],
    "sg:postcode":"B96 6ES",
    "sg:province":"Warwickshire",
    "sg:tags":[
        "joinery",
        "jewellery",
        "repair"
    ],
    "wof:name":"L A Beard & Co",
    "wof:placetype":"venue"
},
  "geometry": {"coordinates":[-1.92194,52.264568],"type":"Point"}
}