{
  "type": "Feature",
  "properties": {
    "iso:country":"GB",
    "sg:address":"3-5 Silent Street",
    "sg:city":"Ipswich",
    "sg:classifiers":[
        {
            "category":"Shopping",
            "subcategory":"Books",
            "type":"Retail Goods"
        }
    ],
    "sg:phone":"+44 1473 254776",
    "sg:postcode":"IP1 1TF",
    "sg:province":"Suffolk",
    "sg:tags":[
        "retailer",
        "second-hand"
    ],
    "wof:name":"Claude Cox Books",
    "wof:placetype":"venue"
},
  "geometry": {"coordinates":[1.1529430151,52.0548973083],"type":"Point"}
}