{
  "type": "Feature",
  "properties": {
    "addr:full":"Drake House, Drake Avenue Staines Berkshire TW18 2AP",
    "addr:postcode":"tw18 2ap",
    "addr:street":"Drake Avenue",
    "iso:country":"GB",
    "sg:address":"Drake House, Drake Avenue",
    "sg:city":"Staines",
    "sg:classifiers":[
        {
            "category":"Manufacturing",
            "subcategory":"Metals",
            "type":"Manufacturing & Wholesale Goods"
        }
    ],
    "sg:phone":"+44 1784 452683",
    "sg:postcode":"TW18 2AP",
    "sg:province":"Berkshire",
    "sg:tags":[
        "work",
        "sheet"
    ],
    "wof:name":"Drake Manufacturing Ltd.",
    "wof:placetype":"venue"
},
  "geometry": {"coordinates":[-0.505894,51.431622],"type":"Point"}
}