{
  "type": "Feature",
  "properties": {
    "iso:country":"GB",
    "sg:address":"17 Willson Croft, Hall Grn",
    "sg:city":"Birmingham",
    "sg:classifiers":[
        {
            "category":"Professional",
            "subcategory":"Art Services",
            "type":"Services"
        }
    ],
    "sg:postcode":"B28 0SS",
    "sg:province":"West Midlands",
    "sg:tags":[
        "photographer"
    ],
    "wof:name":"A & J Photography",
    "wof:placetype":"venue"
},
  "geometry": {"coordinates":[-1.854746,52.411064],"type":"Point"}
}