{
  "type": "Feature",
  "properties": {
    "iso:country":"GB",
    "sg:address":"1a Casselbank Street, Leith",
    "sg:city":"Edinburgh",
    "sg:classifiers":[
        {
            "category":"Building & Trades",
            "subcategory":"Construction",
            "type":"Services"
        }
    ],
    "sg:phone":"+44 131 554 7338",
    "sg:postcode":"EH6 5HA",
    "sg:province":"City of Edinburgh",
    "sg:tags":[
        "dry",
        "plastering",
        "plasterers",
        "lining",
        "related",
        "screeders"
    ],
    "wof:name":"Scott & Davie",
    "wof:placetype":"venue"
},
  "geometry": {"coordinates":[-3.173363,55.970181],"type":"Point"}
}