{
  "type": "Feature",
  "properties": {
    "addr:full":"Ground Floor No 1, Magellan Terrace Crawley Surrey RH10 9PJ",
    "addr:housenumber":"ground floor no 1",
    "addr:postcode":"rh10 9pj",
    "addr:street":"Magellan Terrace",
    "iso:country":"GB",
    "sg:address":"Ground Floor No 1, Magellan Terrace",
    "sg:city":"Crawley",
    "sg:classifiers":[
        {
            "category":"Building & Trades",
            "subcategory":"Construction",
            "type":"Services"
        }
    ],
    "sg:phone":"+44 1293 436331",
    "sg:postcode":"RH10 9PJ",
    "sg:province":"Surrey",
    "sg:tags":[
        "restoration",
        "refurbishment"
    ],
    "wof:name":"Interior Design & Development Ltd.",
    "wof:placetype":"venue"
},
  "geometry": {"coordinates":[-0.184753,51.118458],"type":"Point"}
}