{
  "type": "Feature",
  "properties": {
    "addr:full":"131-139 Camberwell Road London Greater London SE5 0HF",
    "addr:housenumber":"131-139",
    "addr:postcode":"se5 0hf",
    "addr:street":"Camberwell Road",
    "iso:country":"GB",
    "sg:address":"131-139 Camberwell Road",
    "sg:city":"London",
    "sg:classifiers":[
        {
            "category":"Organizations",
            "subcategory":"Non-profit Organization",
            "type":"Services"
        }
    ],
    "sg:phone":"+44 20 7708 4497",
    "sg:postcode":"SE5 0HF",
    "sg:province":"Greater London",
    "sg:tags":[
        "organisation",
        "voluntary",
        "charity"
    ],
    "wof:name":"Southwark Carers",
    "wof:placetype":"venue"
},
  "geometry": {"coordinates":[-0.094084,51.480442],"type":"Point"}
}