{
  "type": "Feature",
  "properties": {
    "iso:country":"GB",
    "sg:address":"47 Lovat Road",
    "sg:city":"Preston",
    "sg:classifiers":[
        {
            "category":"Banks & Credit Unions",
            "subcategory":"Bureau De Change",
            "type":"Services"
        },
        {
            "category":"Shopping",
            "subcategory":"Clothing, Apparel, & Fashions",
            "type":"Retail Goods"
        },
        {
            "category":"Food & Beverages",
            "subcategory":"Liquor & Beverages",
            "type":"Retail Goods"
        }
    ],
    "sg:phone":"+44 1772 201591",
    "sg:postcode":"PR1 6DQ",
    "sg:province":"Lancashire",
    "sg:tags":[
        "shop",
        "wines",
        "fancy",
        "beer",
        "dress",
        "spirit",
        "wine"
    ],
    "wof:name":"The Real Ale Shop",
    "wof:placetype":"venue"
},
  "geometry": {"coordinates":[-2.701402,53.770096],"type":"Point"}
}