{
  "type": "Feature",
  "properties": {
    "iso:country":"GB",
    "sg:address":"Methuen Oval, Wyke",
    "sg:city":"Bradford",
    "sg:classifiers":[
        {
            "category":"Professional",
            "subcategory":"Detective & Security Services",
            "type":"Services"
        }
    ],
    "sg:postcode":"BD12 8SA",
    "sg:province":"West Yorkshire",
    "wof:name":"Reynolds,Julian,",
    "wof:placetype":"venue"
},
  "geometry": {"coordinates":[-1.758306,53.795738],"type":"Point"}
}