{
  "type": "Feature",
  "properties": {
    "addr:full":"15 Bonds Lane, Garstang Preston Lancashire PR3 1ZB",
    "addr:housenumber":"15",
    "addr:postcode":"pr3 1zb",
    "addr:street":"Bonds Lane",
    "iso:country":"GB",
    "sg:address":"15 Bonds Lane, Garstang",
    "sg:city":"Preston",
    "sg:classifiers":[
        {
            "category":"Education",
            "subcategory":"Preschool",
            "type":"Public Place"
        }
    ],
    "sg:phone":"+44 1995 602012",
    "sg:postcode":"PR3 1ZB",
    "sg:province":"Lancashire",
    "sg:tags":[
        "pre",
        "school",
        "playgroups",
        "pre-school"
    ],
    "wof:name":"Hummingbirds Pre School Education Group",
    "wof:placetype":"venue"
},
  "geometry": {"coordinates":[-2.7712869644,53.8973007202],"type":"Point"}
}