{
  "type": "Feature",
  "properties": {
    "addr:full":"184 Fitzwilliam Street Sheffield South Yorkshire S1 4JR",
    "addr:housenumber":"184",
    "addr:postcode":"s1 4jr",
    "addr:street":"Fitzwilliam Street",
    "iso:country":"GB",
    "sg:address":"184 Fitzwilliam Street",
    "sg:city":"Sheffield",
    "sg:classifiers":[
        {
            "category":"Shopping",
            "subcategory":"Computers & Home Electronics",
            "type":"Retail Goods"
        }
    ],
    "sg:phone":"+44 114 275 6048",
    "sg:postcode":"S1 4JR",
    "sg:province":"South Yorkshire",
    "sg:tags":[
        "hi-fi",
        "centre"
    ],
    "wof:name":"Moorgate Acoustics Ltd.",
    "wof:placetype":"venue"
},
  "geometry": {"coordinates":[-1.4777460098,53.377166748],"type":"Point"}
}