{
  "type": "Feature",
  "properties": {
    "addr:full":"12 Heath Road Petersfield Hampshire GU31 4DU",
    "addr:housenumber":"12",
    "addr:postcode":"gu31 4du",
    "addr:street":"Heath Road",
    "iso:country":"GB",
    "sg:address":"12 Heath Road",
    "sg:city":"Petersfield",
    "sg:classifiers":[
        {
            "category":"Professional",
            "subcategory":"Advertising",
            "type":"Services"
        }
    ],
    "sg:phone":"+44 1730 268631",
    "sg:postcode":"GU31 4DU",
    "sg:province":"Hampshire",
    "sg:tags":[
        "agency"
    ],
    "wof:name":"Hattons",
    "wof:placetype":"venue"
},
  "geometry": {"coordinates":[-0.9332919717,51.0036010742],"type":"Point"}
}