{
  "type": "Feature",
  "properties": {
    "addr:full":"6 Davenport Drive Bromsgrove Worcestershire B60 2DW",
    "addr:housenumber":"6",
    "addr:postcode":"b60 2dw",
    "addr:street":"Davenport Drive",
    "iso:country":"GB",
    "sg:address":"6 Davenport Drive",
    "sg:city":"Bromsgrove",
    "sg:classifiers":[
        {
            "category":"Real Estate",
            "subcategory":"Architect",
            "type":"Services"
        }
    ],
    "sg:phone":"+44 1527 871832",
    "sg:postcode":"B60 2DW",
    "sg:province":"Worcestershire",
    "wof:name":"GRINYER GRIFFITHS PARTNERSHIP ARCHITECT",
    "wof:placetype":"venue"
},
  "geometry": {"coordinates":[-2.050154,52.329678],"type":"Point"}
}