{
  "type": "Feature",
  "properties": {
    "addr:full":"23 Ferncombe Drive Rugeley Staffordshire WS15 2XB",
    "addr:housenumber":"23",
    "addr:postcode":"ws15 2xb",
    "addr:street":"Ferncombe Drive",
    "iso:country":"GB",
    "sg:address":"23 Ferncombe Drive",
    "sg:city":"Rugeley",
    "sg:classifiers":[
        {
            "category":"Building & Trades",
            "subcategory":"Construction",
            "type":"Services"
        }
    ],
    "sg:phone":"+44 1889 585491",
    "sg:postcode":"WS15 2XB",
    "sg:province":"Staffordshire",
    "sg:tags":[
        "glazier",
        "decorator",
        "painter"
    ],
    "wof:name":"Alistair Glyn Pountney",
    "wof:placetype":"venue"
},
  "geometry": {"coordinates":[-1.952533,52.76709],"type":"Point"}
}