{
  "type": "Feature",
  "properties": {
    "addr:full":"52 Upper Brook Street London Greater London W1K 2BX",
    "addr:housenumber":"52",
    "addr:postcode":"w1k 2bx",
    "addr:street":"Upper Brook Street",
    "iso:country":"GB",
    "sg:address":"52 Upper Brook Street",
    "sg:city":"London",
    "sg:classifiers":[
        {
            "category":"Professional",
            "subcategory":"Business Services",
            "type":"Services"
        }
    ],
    "sg:postcode":"W1K 2BX",
    "sg:province":"Greater London",
    "sg:tags":[
        "distribution"
    ],
    "wof:name":"Zmg Corporation",
    "wof:placetype":"venue"
},
  "geometry": {"coordinates":[-0.1542290002,51.5114135742],"type":"Point"}
}