{
  "type": "Feature",
  "properties": {
    "iso:country":"GB",
    "sg:address":"Higher Murchington Farm, Chagford",
    "sg:city":"Newton Abbot",
    "sg:classifiers":[
        {
            "category":"Ice Cream",
            "type":"Food & Drink"
        }
    ],
    "sg:phone":"+44 1647 433648",
    "sg:postcode":"TQ13 8HJ",
    "sg:province":"Devon",
    "sg:tags":[
        "mnfr"
    ],
    "wof:name":"Devonshire Farmhouse Ice-Cream",
    "wof:placetype":"venue"
},
  "geometry": {"coordinates":[-3.8342559338,50.6774177551],"type":"Point"}
}