{
  "type": "Feature",
  "properties": {
    "addr:full":"Swan Roundabout West Bromwich West Midlands B70 0YA",
    "addr:postcode":"b70 0ya",
    "addr:street":"Swan Roundabout",
    "iso:country":"GB",
    "sg:address":"Swan Roundabout",
    "sg:city":"West Bromwich",
    "sg:classifiers":[
        {
            "category":"Autos & Motor Vehicles",
            "subcategory":"Fuel & Gas Station",
            "type":"Retail Goods"
        }
    ],
    "sg:postcode":"B70 0YA",
    "sg:province":"West Midlands",
    "sg:tags":[
        "hr",
        "petrol"
    ],
    "wof:name":"Cygnus Service Station",
    "wof:placetype":"venue"
},
  "geometry": {"coordinates":[-2.016213,52.529072],"type":"Point"}
}