{
  "type": "Feature",
  "properties": {
    "addr:full":"Stn App, High St Ongar Essex CM5 9BN",
    "addr:postcode":"cm5 9bn",
    "addr:street":"High St",
    "iso:country":"GB",
    "sg:address":"Stn App, High St",
    "sg:city":"Ongar",
    "sg:classifiers":[
        {
            "category":"Shopping",
            "subcategory":"Department Store",
            "type":"Retail Goods"
        }
    ],
    "sg:postcode":"CM5 9BN",
    "sg:province":"Essex",
    "wof:name":"Ruston,M,",
    "wof:placetype":"venue"
},
  "geometry": {"coordinates":[0.24517,51.706131],"type":"Point"}
}