{
  "type": "Feature",
  "properties": {
    "iso:country":"GB",
    "sg:address":"46 Osprey Road, Manor Park",
    "sg:city":"Solihull",
    "sg:classifiers":[
        {
            "category":"Shopping",
            "subcategory":"Antiques",
            "type":"Retail Goods"
        }
    ],
    "sg:phone":"+44 121 707 0369",
    "sg:postcode":"B27 7BA",
    "sg:province":"West Midlands",
    "wof:name":"Tony Marcus",
    "wof:placetype":"venue"
},
  "geometry": {"coordinates":[-1.8128600121,52.4412994385],"type":"Point"}
}