{
  "type": "Feature",
  "properties": {
    "iso:country":"GB",
    "sg:address":"24 Gloversfield",
    "sg:city":"Winscombe",
    "sg:classifiers":[
        {
            "category":"Military Area",
            "subcategory":"Air Force Base",
            "type":"Public Place"
        }
    ],
    "sg:phone":"+44 1934 843922",
    "sg:postcode":"BS25 1ST",
    "sg:province":"Somerset",
    "sg:tags":[
        "taxi",
        "hire",
        "private"
    ],
    "wof:name":"J & S Cars Taxis",
    "wof:placetype":"venue"
},
  "geometry": {"coordinates":[-2.820949,51.314461],"type":"Point"}
}