{
  "type": "Feature",
  "properties": {
    "iso:country":"GB",
    "sg:address":"517 Eturia Road, Basford",
    "sg:city":"Stoke-on-trent",
    "sg:classifiers":[
        {
            "category":"Real Estate",
            "subcategory":"Real Estate Agent",
            "type":"Services"
        }
    ],
    "sg:postcode":"ST4 6HP",
    "sg:province":"Staffordshire",
    "wof:name":"Trentowns Estate Agents",
    "wof:placetype":"venue"
},
  "geometry": {"coordinates":[-2.210395,53.016319],"type":"Point"}
}