{
  "type": "Feature",
  "properties": {
    "iso:country":"GB",
    "sg:address":"11 Green Terrace",
    "sg:city":"Sunderland",
    "sg:classifiers":[
        {
            "category":"Education",
            "subcategory":"Special Training",
            "type":"Public Place"
        }
    ],
    "sg:phone":"+44 191 514 2183",
    "sg:postcode":"SR1 3PZ",
    "sg:province":"Tyne and Wear",
    "sg:tags":[
        "product",
        "centre"
    ],
    "wof:name":"Spring Skills",
    "wof:placetype":"venue"
},
  "geometry": {"coordinates":[-1.3887890577,54.9041748047],"type":"Point"}
}