{
  "type": "Feature",
  "properties": {
    "iso:country":"GB",
    "sg:address":"52-54 Marine Road West",
    "sg:city":"Morecambe",
    "sg:classifiers":[
        {
            "category":"Recreation",
            "subcategory":"Amusement Park",
            "type":"Entertainment"
        }
    ],
    "sg:phone":"+44 1524 412449",
    "sg:postcode":"LA4 4EU",
    "sg:province":"Lancashire",
    "sg:tags":[
        "arcade",
        "activity"
    ],
    "wof:name":"ALHAMBRA LEISURE CENTRE",
    "wof:placetype":"venue"
},
  "geometry": {"coordinates":[-2.880488,54.066437],"type":"Point"}
}