{
  "type": "Feature",
  "properties": {
    "iso:country":"GB",
    "sg:address":"Deepthwaite Farm, Woodhouse",
    "sg:city":"Milnthorpe",
    "sg:classifiers":[
        {
            "category":"Farming",
            "subcategory":"Farm",
            "type":"Manufacturing & Wholesale Goods"
        }
    ],
    "sg:postcode":"LA7 7NQ",
    "sg:province":"Cumbria",
    "sg:tags":[
        "mixed",
        "crop"
    ],
    "wof:name":"J Sowerby",
    "wof:placetype":"venue"
},
  "geometry": {"coordinates":[-2.772592,54.226864],"type":"Point"}
}