{
  "type": "Feature",
  "properties": {
    "addr:full":"Unit 84, 2 Russel Way Gateshead Tyne and Wear NE11 9YZ",
    "addr:housenumber":"unit 84 2",
    "addr:postcode":"ne11 9yz",
    "addr:street":"Russel Way",
    "iso:country":"GB",
    "sg:address":"Unit 84, 2 Russel Way",
    "sg:city":"Gateshead",
    "sg:classifiers":[
        {
            "category":"Shopping",
            "subcategory":"Clothing, Apparel, & Fashions",
            "type":"Retail Goods"
        }
    ],
    "sg:phone":"+44 191 460 9255",
    "sg:postcode":"NE11 9YZ",
    "sg:province":"Tyne and Wear",
    "sg:tags":[
        "accessory"
    ],
    "wof:name":"CLAIRE'S ACCESSORIES UK LTD",
    "wof:placetype":"venue"
},
  "geometry": {"coordinates":[-1.6685400009,54.957660675],"type":"Point"}
}