{
  "type": "Feature",
  "properties": {
    "addr:full":"56a Station Rd Cradley Heath West Midlands B64 6NU",
    "addr:housenumber":"56a",
    "addr:postcode":"b64 6nu",
    "addr:street":"Station Rd",
    "iso:country":"GB",
    "sg:address":"56a Station Rd",
    "sg:city":"Cradley Heath",
    "sg:classifiers":[
        {
            "category":"Home & Garden",
            "subcategory":"Home Furnishings",
            "type":"Retail Goods"
        }
    ],
    "sg:phone":"+44 1384 566958",
    "sg:postcode":"B64 6NU",
    "sg:province":"West Midlands",
    "sg:tags":[
        "mantelpiece",
        "fireplace"
    ],
    "wof:name":"Steve Ridley Feature Fireplaces",
    "wof:placetype":"venue"
},
  "geometry": {"coordinates":[-2.059979,52.471733],"type":"Point"}
}