{
  "type": "Feature",
  "properties": {
    "addr:full":"15 Sandy La Westerham Kent TN16 1EB",
    "addr:housenumber":"15",
    "addr:postcode":"tn16 1eb",
    "addr:street":"Sandy La Westerham",
    "iso:country":"GB",
    "sg:address":"15 Sandy La",
    "sg:city":"Westerham",
    "sg:classifiers":[
        {
            "category":"Retail",
            "subcategory":"Auto Repair",
            "type":"Services"
        }
    ],
    "sg:phone":"+44 1959 564068",
    "sg:postcode":"TN16 1EB",
    "sg:province":"Kent",
    "sg:tags":[
        "modification",
        "garage"
    ],
    "wof:name":"MCm Westerham",
    "wof:placetype":"venue"
},
  "geometry": {"coordinates":[0.077284,51.273369],"type":"Point"}
}