{
  "type": "Feature",
  "properties": {
    "iso:country":"GB",
    "sg:address":"92 Woodville Road, Cathays",
    "sg:city":"Cardiff",
    "sg:classifiers":[
        {
            "category":"Building & Trades",
            "subcategory":"Construction",
            "type":"Services"
        }
    ],
    "sg:postcode":"CF24 4ED",
    "sg:province":"Cardiff",
    "sg:tags":[
        "roofing"
    ],
    "wof:name":"Hector's House Ltd",
    "wof:placetype":"venue"
},
  "geometry": {"coordinates":[-3.177537,51.493061],"type":"Point"}
}