{
  "type": "Feature",
  "properties": {
    "addr:full":"Mount Bures Road Colchester Essex CO6 2AP",
    "addr:postcode":"co6 2ap",
    "addr:street":"Mount Bures Road Colchester",
    "iso:country":"GB",
    "sg:address":"Mount Bures Road",
    "sg:city":"Colchester",
    "sg:classifiers":[
        {
            "category":"Shopping",
            "subcategory":"Stationery & Office Supplies",
            "type":"Retail Goods"
        }
    ],
    "sg:postcode":"CO6 2AP",
    "sg:province":"Essex",
    "sg:tags":[
        "equipment"
    ],
    "wof:name":"R P Contracts",
    "wof:placetype":"venue"
},
  "geometry": {"coordinates":[0.7801100016,51.9326400757],"type":"Point"}
}