{
  "type": "Feature",
  "properties": {
    "addr:full":"8 Newquay Avenue Stockport Cheshire SK5 7BQ",
    "addr:housenumber":"8",
    "addr:postcode":"sk5 7bq",
    "addr:street":"Newquay Avenue",
    "iso:country":"GB",
    "sg:address":"8 Newquay Avenue",
    "sg:city":"Stockport",
    "sg:classifiers":[
        {
            "category":"Building & Trades",
            "subcategory":"Plumbing",
            "type":"Services"
        }
    ],
    "sg:phone":"+44 161 485 7412",
    "sg:postcode":"SK5 7BQ",
    "sg:province":"Cheshire",
    "sg:tags":[
        "central",
        "heating"
    ],
    "wof:name":"Heating Maintenance",
    "wof:placetype":"venue"
},
  "geometry": {"coordinates":[-2.162502,53.434296],"type":"Point"}
}