{
  "type": "Feature",
  "properties": {
    "iso:country":"GB",
    "sg:address":"19 Woodlands Rise, Downend",
    "sg:city":"Bristol",
    "sg:classifiers":[
        {
            "category":"Utilities",
            "subcategory":"Electric",
            "type":"Services"
        }
    ],
    "sg:phone":"+44 117 970 1364",
    "sg:postcode":"BS16 2RX",
    "sg:province":"City of Bristol",
    "sg:tags":[
        "electricity"
    ],
    "wof:name":"Team Analysis Energy Brokers",
    "wof:placetype":"venue"
},
  "geometry": {"coordinates":[-2.5112309456,51.4892349243],"type":"Point"}
}