{
  "type": "Feature",
  "properties": {
    "iso:country":"GB",
    "sg:address":"Unit 2, 40 Midland Road",
    "sg:city":"Bristol",
    "sg:classifiers":[
        {
            "category":"Professional",
            "subcategory":"Art Services",
            "type":"Services"
        }
    ],
    "sg:postcode":"BS16 4NW",
    "sg:province":"City of Bristol",
    "sg:tags":[
        "framing"
    ],
    "wof:name":"West & Wales Framing Supplies",
    "wof:placetype":"venue"
},
  "geometry": {"coordinates":[-2.510433,51.478649],"type":"Point"}
}