{
  "type": "Feature",
  "properties": {
    "iso:country":"GB",
    "sg:address":"West Lodge, Hill End Lane",
    "sg:city":"St Albans",
    "sg:classifiers":[
        {
            "category":"Organizations",
            "subcategory":"Non-profit Organization",
            "type":"Services"
        }
    ],
    "sg:phone":"+44 1727 847242",
    "sg:postcode":"AL4 0RB",
    "sg:province":"Hertfordshire",
    "sg:tags":[
        "organisation",
        "voluntary",
        "charity"
    ],
    "wof:name":"Highfield Park Trust",
    "wof:placetype":"venue"
},
  "geometry": {"coordinates":[-0.27177,51.742592],"type":"Point"}
}