{
  "type": "Feature",
  "properties": {
    "iso:country":"GB",
    "sg:address":"289 Mitcham Road",
    "sg:city":"London",
    "sg:classifiers":[
        {
            "category":"Wholesale",
            "subcategory":"Office Equipment",
            "type":"Manufacturing & Wholesale Goods"
        }
    ],
    "sg:phone":"+44 20 8767 8899",
    "sg:postcode":"SW17 9JQ",
    "sg:province":"Greater London",
    "sg:tags":[
        "register",
        "cash",
        "accessory"
    ],
    "wof:name":"Kar Cash Registers",
    "wof:placetype":"venue"
},
  "geometry": {"coordinates":[-0.160871,51.420826],"type":"Point"}
}