{
  "type": "Feature",
  "properties": {
    "iso:country":"GB",
    "sg:address":"4th Floor, Tolworth Tower, Tolworth",
    "sg:city":"Surbiton",
    "sg:classifiers":[
        {
            "category":"Professional",
            "subcategory":"Business Services",
            "type":"Services"
        }
    ],
    "sg:phone":"+44 20 8390 1444",
    "sg:postcode":"KT6 7EL",
    "sg:province":"Surrey",
    "sg:tags":[
        "food",
        "import",
        "export",
        "agent"
    ],
    "wof:name":"Francis Nicholls Ltd.",
    "wof:placetype":"venue"
},
  "geometry": {"coordinates":[-0.283073,51.381611],"type":"Point"}
}