{
  "type": "Feature",
  "properties": {
    "addr:full":"19 Deedes St Airdrie North Lanarkshire ML6 9AF",
    "addr:housenumber":"19",
    "addr:postcode":"ml6 9af",
    "addr:street":"Deedes St",
    "iso:country":"GB",
    "sg:address":"19 Deedes St",
    "sg:city":"Airdrie",
    "sg:classifiers":[
        {
            "category":"Home & Garden",
            "subcategory":"Household Appliances",
            "type":"Retail Goods"
        }
    ],
    "sg:phone":"+44 1236 767174",
    "sg:postcode":"ML6 9AF",
    "sg:province":"North Lanarkshire",
    "sg:tags":[
        "electrical"
    ],
    "wof:name":"A1 Washing Machine Repairs",
    "wof:placetype":"venue"
},
  "geometry": {"coordinates":[-4.002135,55.861946],"type":"Point"}
}