{
  "type": "Feature",
  "properties": {
    "iso:country":"GB",
    "sg:address":"41 Wendover Rd",
    "sg:city":"Aylesbury",
    "sg:classifiers":[
        {
            "category":"Home & Garden",
            "subcategory":"Building Materials",
            "type":"Retail Goods"
        }
    ],
    "sg:phone":"+44 1296 424121",
    "sg:postcode":"HP21 9TA",
    "sg:province":"Buckinghamshire",
    "sg:tags":[
        "ironwork",
        "wrought"
    ],
    "wof:name":"Structural Steel Services",
    "wof:placetype":"venue"
},
  "geometry": {"coordinates":[-0.80477,51.81023],"type":"Point"}
}