{
  "type": "Feature",
  "properties": {
    "iso:country":"GB",
    "sg:address":"Unit8, Warehouse Lane, Foulridge",
    "sg:city":"Colne",
    "sg:classifiers":[
        {
            "category":"Professional",
            "subcategory":"Engineering",
            "type":"Services"
        }
    ],
    "sg:phone":"+44 1282 869567",
    "sg:postcode":"BB8 7PP",
    "sg:province":"Lancashire",
    "sg:tags":[
        "engineer"
    ],
    "wof:name":"B B Engineering",
    "wof:placetype":"venue"
},
  "geometry": {"coordinates":[-2.170609,53.878059],"type":"Point"}
}