{
  "type": "Feature",
  "properties": {
    "addr:full":"954 Eastern Avenue Ilford Essex IG2 7JD",
    "addr:housenumber":"954",
    "addr:postcode":"ig2 7jd",
    "addr:street":"Eastern Avenue",
    "iso:country":"GB",
    "sg:address":"954 Eastern Avenue",
    "sg:city":"Ilford",
    "sg:classifiers":[
        {
            "category":"Fast Food",
            "type":"Food & Drink"
        }
    ],
    "sg:postcode":"IG2 7JD",
    "sg:province":"Essex",
    "sg:tags":[
        "away",
        "meal",
        "outlet",
        "take"
    ],
    "wof:name":"CHINESE EXPRESS",
    "wof:placetype":"venue"
},
  "geometry": {"coordinates":[0.09849,51.577255],"type":"Point"}
}