{
  "type": "Feature",
  "properties": {
    "addr:full":"12-16 New Rents Ashford Kent TN23 1JJ",
    "addr:housenumber":"12-16",
    "addr:postcode":"tn23 1jj",
    "addr:street":"New Rents",
    "iso:country":"GB",
    "sg:address":"12-16 New Rents",
    "sg:city":"Ashford",
    "sg:classifiers":[
        {
            "category":"Shopping",
            "subcategory":"Bicycles & Sporting Goods",
            "type":"Retail Goods"
        }
    ],
    "sg:phone":"+44 1233 662800",
    "sg:postcode":"TN23 1JJ",
    "sg:province":"Kent",
    "sg:tags":[
        "cycle",
        "accessory"
    ],
    "wof:name":"Canterbury Cycle Mart",
    "wof:placetype":"venue"
},
  "geometry": {"coordinates":[0.8703050017,51.1496315002],"type":"Point"}
}