{
  "type": "Feature",
  "properties": {
    "addr:full":"Little Loveney Hall, Wakes Colne Colchester Essex CO6 2BH",
    "addr:postcode":"co6 2bh",
    "addr:street":"Wakes;Colchester",
    "iso:country":"GB",
    "sg:address":"Little Loveney Hall, Wakes Colne",
    "sg:city":"Colchester",
    "sg:classifiers":[
        {
            "category":"Home & Garden",
            "subcategory":"Garden Supply",
            "type":"Retail Goods"
        }
    ],
    "sg:postcode":"CO6 2BH",
    "sg:province":"Essex",
    "sg:tags":[
        "bulb",
        "grower"
    ],
    "wof:name":"E H Ashby & Son",
    "wof:placetype":"venue"
},
  "geometry": {"coordinates":[0.755685,51.923264],"type":"Point"}
}