{
  "type": "Feature",
  "properties": {
    "iso:country":"GB",
    "sg:address":"The Orangery, Turners Hill Road, Worth",
    "sg:city":"Crawley",
    "sg:classifiers":[
        {
            "category":"Professional",
            "subcategory":"Computer Services",
            "type":"Services"
        }
    ],
    "sg:phone":"+44 1293 872000",
    "sg:postcode":"RH10 4SS",
    "sg:province":"Surrey",
    "sg:tags":[
        "system",
        "software"
    ],
    "wof:name":"Macro 4 Funding Ltd.",
    "wof:placetype":"venue"
},
  "geometry": {"coordinates":[-0.0923480019,51.1326560974],"type":"Point"}
}