{
  "type": "Feature",
  "properties": {
    "iso:country":"GB",
    "sg:address":"37 Union St",
    "sg:city":"Ryde",
    "sg:classifiers":[
        {
            "category":"Shopping",
            "subcategory":"Thrift Store",
            "type":"Retail Goods"
        }
    ],
    "sg:phone":"+44 1983 562121",
    "sg:postcode":"PO33 2LE",
    "sg:province":"Isle of Wight",
    "sg:tags":[
        "shop",
        "charity"
    ],
    "wof:name":"The Crypt Shop",
    "wof:placetype":"venue"
},
  "geometry": {"coordinates":[-1.162335,50.730366],"type":"Point"}
}