{
  "type": "Feature",
  "properties": {
    "addr:full":"16 Tower Square, Tunstall Stoke-on-trent Staffordshire ST6 5AB",
    "addr:housenumber":"16",
    "addr:postcode":"staffordshire st6 5ab",
    "addr:street":"Tower Square",
    "iso:country":"GB",
    "sg:address":"16 Tower Square, Tunstall",
    "sg:city":"Stoke-on-trent",
    "sg:classifiers":[
        {
            "category":"Food & Beverages",
            "subcategory":"Bakery",
            "type":"Retail Goods"
        }
    ],
    "sg:postcode":"ST6 5AB",
    "sg:province":"Staffordshire",
    "sg:tags":[
        "baker"
    ],
    "wof:name":"Arthur Chatwin Ltd.",
    "wof:placetype":"venue"
},
  "geometry": {"coordinates":[-2.21138,53.058086],"type":"Point"}
}