{
  "type": "Feature",
  "properties": {
    "iso:country":"GB",
    "sg:address":"Millmannoch Avenue, Drongan",
    "sg:city":"Ayr",
    "sg:classifiers":[
        {
            "category":"Arena",
            "subcategory":"Sports Club",
            "type":"Entertainment"
        }
    ],
    "sg:phone":"+44 1292 590937",
    "sg:postcode":"KA6 7BY",
    "sg:province":"East Ayrshire",
    "wof:name":"Drongan Miners Welfare Bowling Club",
    "wof:placetype":"venue"
},
  "geometry": {"coordinates":[-4.455979,55.435989],"type":"Point"}
}