{
  "type": "Feature",
  "properties": {
    "addr:full":"The Old Lifeboat House, Foryd Rhyl Conwy LL18 5BD",
    "addr:postcode":"ll18 5bd",
    "addr:street":"Foryd",
    "iso:country":"GB",
    "sg:address":"The Old Lifeboat House, Foryd",
    "sg:city":"Rhyl",
    "sg:classifiers":[
        {
            "category":"Building & Trades",
            "subcategory":"Construction",
            "type":"Services"
        }
    ],
    "sg:phone":"+44 1745 354579",
    "sg:postcode":"LL18 5BD",
    "sg:province":"Conwy",
    "sg:tags":[
        "builder",
        "joiner",
        "carpenter"
    ],
    "wof:name":"Graham Drury",
    "wof:placetype":"venue"
},
  "geometry": {"coordinates":[-3.520439,53.310452],"type":"Point"}
}