{
  "type": "Feature",
  "properties": {
    "addr:full":"Cox's Lane Smethwick West Midlands B64 5QT",
    "addr:postcode":"b64 5qt",
    "addr:street":"Cox'S Lane",
    "iso:country":"GB",
    "sg:address":"Cox's Lane",
    "sg:city":"Smethwick",
    "sg:classifiers":[
        {
            "category":"Cafe",
            "type":"Food & Drink"
        }
    ],
    "sg:phone":"+44 1384 413759",
    "sg:postcode":"B64 5QT",
    "sg:province":"West Midlands",
    "sg:tags":[
        "tea",
        "snack",
        "bar",
        "room"
    ],
    "wof:name":"White Lion Cafe & Corner Shop",
    "wof:placetype":"venue"
},
  "geometry": {"coordinates":[-1.9739379883,52.4928245544],"type":"Point"}
}