{
  "type": "Feature",
  "properties": {
    "addr:full":"Unit 8, 187 Fylde Road Ind Est, Fylde Rd Preston Lancashire PR1 2TY",
    "addr:housenumber":"unit 8",
    "addr:postcode":"187;pr1 2ty",
    "addr:street":"Fylde Road;Est;Rd",
    "iso:country":"GB",
    "sg:address":"Unit 8, 187 Fylde Road Ind Est, Fylde Rd",
    "sg:city":"Preston",
    "sg:classifiers":[
        {
            "category":"Professional",
            "subcategory":"Printing & Photocopies",
            "type":"Services"
        }
    ],
    "sg:phone":"+44 1772 887700",
    "sg:postcode":"PR1 2TY",
    "sg:province":"Lancashire",
    "sg:tags":[
        "plate",
        "lithographic",
        "maker"
    ],
    "wof:name":"ACORN GRAPHICS",
    "wof:placetype":"venue"
},
  "geometry": {"coordinates":[-2.71408391,53.7647209167],"type":"Point"}
}