{
  "type": "Feature",
  "properties": {
    "addr:full":", Alweston Sherborne Dorset DT9 5HR",
    "addr:postcode":"dt9 5hr",
    "addr:street":"Alweston",
    "iso:country":"GB",
    "sg:address":", Alweston",
    "sg:city":"Sherborne",
    "sg:classifiers":[
        {
            "category":"Sports & Exercise",
            "subcategory":"Golf",
            "type":"Entertainment"
        }
    ],
    "sg:phone":"+44 1963 23330",
    "sg:postcode":"DT9 5HR",
    "sg:province":"Dorset",
    "sg:tags":[
        "club",
        "course"
    ],
    "wof:name":"Folke Golf Centre",
    "wof:placetype":"venue"
},
  "geometry": {"coordinates":[-2.480749,50.925629],"type":"Point"}
}