{
  "type": "Feature",
  "properties": {
    "addr:full":"5-9 Laker Road Rochester Kent ME1 3QZ",
    "addr:housenumber":"5-9",
    "addr:postcode":"me1 3qz",
    "addr:street":"Laker Road Rochester",
    "iso:country":"GB",
    "sg:address":"5-9 Laker Road",
    "sg:city":"Rochester",
    "sg:classifiers":[
        {
            "category":"Wholesale",
            "subcategory":"Non-durable Goods",
            "type":"Manufacturing & Wholesale Goods"
        }
    ],
    "sg:postcode":"ME1 3QZ",
    "sg:province":"Kent",
    "sg:tags":[
        "carry",
        "cash"
    ],
    "wof:name":"Booker Cash & Carry",
    "wof:placetype":"venue"
},
  "geometry": {"coordinates":[0.501365,51.349937],"type":"Point"}
}