{
  "type": "Feature",
  "properties": {
    "addr:full":"Hillview Farm, Folley Rd Wolverhampton Shropshire WV6 7JL",
    "addr:postcode":"wv6 7jl",
    "addr:street":"Folley Rd",
    "iso:country":"GB",
    "sg:address":"Hillview Farm, Folley Rd",
    "sg:city":"Wolverhampton",
    "sg:classifiers":[
        {
            "category":"Education",
            "subcategory":"Special Training",
            "type":"Public Place"
        }
    ],
    "sg:phone":"+44 1746 783271",
    "sg:postcode":"WV6 7JL",
    "sg:province":"Shropshire",
    "sg:tags":[
        "product",
        "centre"
    ],
    "wof:name":"Training By Design",
    "wof:placetype":"venue"
},
  "geometry": {"coordinates":[-2.34077,52.583858],"type":"Point"}
}