{
  "type": "Feature",
  "properties": {
    "addr:full":"2 Stewkley Road, Cublington Leighton Buzzard Bedfordshire LU7 0LR",
    "addr:housenumber":"2",
    "addr:postcode":"lu7 0lr",
    "addr:street":"Stewkley Road",
    "iso:country":"GB",
    "sg:address":"2 Stewkley Road, Cublington",
    "sg:city":"Leighton Buzzard",
    "sg:classifiers":[
        {
            "category":"Shopping",
            "subcategory":"Bicycles & Sporting Goods",
            "type":"Retail Goods"
        }
    ],
    "sg:phone":"+44 1296 682281",
    "sg:postcode":"LU7 0LR",
    "sg:province":"Bedfordshire",
    "sg:tags":[
        "equipment",
        "gym",
        "sport"
    ],
    "wof:name":"U S Electronics Cardio Equipment",
    "wof:placetype":"venue"
},
  "geometry": {"coordinates":[-0.713895,51.897968],"type":"Point"}
}