{
  "type": "Feature",
  "properties": {
    "iso:country":"GB",
    "sg:address":"18 Queen Street",
    "sg:city":"West End",
    "sg:classifiers":[
        {
            "category":"Organizations",
            "subcategory":"Membership Organization",
            "type":"Services"
        }
    ],
    "sg:postcode":"W1X 7PJ",
    "sg:province":"Hampshire",
    "sg:tags":[
        "club"
    ],
    "wof:name":"Frontcourt Ltd",
    "wof:placetype":"venue"
},
  "geometry": {"coordinates":[-0.1473149955,51.5072174072],"type":"Point"}
}