{
  "type": "Feature",
  "properties": {
    "addr:full":"316d Brockley Road London Greater London SE4 2AZ",
    "addr:housenumber":"316d",
    "addr:postcode":"se4 2az",
    "addr:street":"Brockley Road",
    "iso:country":"GB",
    "sg:address":"316d Brockley Road",
    "sg:city":"London",
    "sg:classifiers":[
        {
            "category":"Building & Trades",
            "subcategory":"Construction",
            "type":"Services"
        }
    ],
    "sg:phone":"+44 20 8691 2647",
    "sg:postcode":"SE4 2AZ",
    "sg:province":"Greater London",
    "sg:tags":[
        "decorator",
        "painter"
    ],
    "wof:name":"Cluett'll Do It",
    "wof:placetype":"venue"
},
  "geometry": {"coordinates":[-0.0346149988,51.4579544067],"type":"Point"}
}