{
  "type": "Feature",
  "properties": {
    "addr:full":"Invergowrie Dundee Dundee City DD2 5DA",
    "addr:postcode":"dd2 5da",
    "iso:country":"GB",
    "sg:address":"Invergowrie",
    "sg:city":"Dundee",
    "sg:classifiers":[
        {
            "category":"Government",
            "subcategory":"Post Office",
            "type":"Public Place"
        }
    ],
    "sg:phone":"+44 1382 562731",
    "sg:postcode":"DD2 5DA",
    "sg:province":"Dundee City",
    "sg:tags":[
        "organisation",
        "soc",
        "research"
    ],
    "wof:name":"The Scottish Crop Research Institute",
    "wof:placetype":"venue"
},
  "geometry": {"coordinates":[-3.0694000721,56.4564590454],"type":"Point"}
}