{
  "type": "Feature",
  "properties": {
    "addr:full":"164-166 Holliday St Birmingham West Midlands B1 1TJ",
    "addr:housenumber":"164-166",
    "addr:postcode":"b1 1tj",
    "addr:street":"Holliday St",
    "iso:country":"GB",
    "sg:address":"164-166 Holliday St",
    "sg:city":"Birmingham",
    "sg:classifiers":[
        {
            "category":"Utilities",
            "type":"Services"
        }
    ],
    "sg:phone":"+44 121 628 5551",
    "sg:postcode":"B1 1TJ",
    "sg:province":"West Midlands",
    "sg:tags":[
        "internet"
    ],
    "wof:name":"Net Star Ltd",
    "wof:placetype":"venue"
},
  "geometry": {"coordinates":[-1.9103629589,52.4743309021],"type":"Point"}
}