{
  "type": "Feature",
  "properties": {
    "addr:full":"Flat 4 The Arcade, The Street, Charmouth Bridport Dorset DT6 6PU",
    "addr:postcode":"dt6 6pu",
    "addr:street":"The Arcade The Street",
    "iso:country":"GB",
    "sg:address":"Flat 4 The Arcade, The Street, Charmouth",
    "sg:city":"Bridport",
    "sg:classifiers":[
        {
            "category":"Shopping",
            "subcategory":"News",
            "type":"Retail Goods"
        }
    ],
    "sg:postcode":"DT6 6PU",
    "sg:province":"Dorset",
    "sg:tags":[
        "newsagent"
    ],
    "wof:name":"Morgans of Charmouth",
    "wof:placetype":"venue"
},
  "geometry": {"coordinates":[-2.90326,50.738621],"type":"Point"}
}