{
  "type": "Feature",
  "properties": {
    "iso:country":"GB",
    "sg:address":"63 Saltergate",
    "sg:city":"Chesterfield",
    "sg:classifiers":[
        {
            "category":"Banks & Credit Unions",
            "subcategory":"Investment Brokerage",
            "type":"Services"
        }
    ],
    "sg:phone":"+44 1246 200880",
    "sg:postcode":"S40 1UJ",
    "sg:province":"Derbyshire",
    "wof:name":"Elshaw Tempest Associates",
    "wof:placetype":"venue"
},
  "geometry": {"coordinates":[-1.429008,53.237568],"type":"Point"}
}