{
  "type": "Feature",
  "properties": {
    "iso:country":"GB",
    "sg:address":"12 Park St",
    "sg:city":"Luton",
    "sg:classifiers":[
        {
            "category":"Shopping",
            "subcategory":"Thrift Store",
            "type":"Retail Goods"
        }
    ],
    "sg:phone":"+44 1582 455441",
    "sg:postcode":"LU1 3EP",
    "sg:province":"Bedfordshire",
    "sg:tags":[
        "shop",
        "charity"
    ],
    "wof:name":"British Red Cross Shop",
    "wof:placetype":"venue"
},
  "geometry": {"coordinates":[-0.4093469977,51.8760643005],"type":"Point"}
}