{
  "type": "Feature",
  "properties": {
    "addr:full":"Castle View, Barn Woolsthorpe Lane Muston Nottingham Leicestershire NG13 0FE",
    "addr:postcode":"ng13 0fe",
    "addr:street":"Castle;Woolsthorpe Lane",
    "iso:country":"GB",
    "sg:address":"Castle View, Barn Woolsthorpe Lane Muston",
    "sg:city":"Nottingham",
    "sg:classifiers":[
        {
            "category":"Real Estate",
            "subcategory":"Surveying",
            "type":"Services"
        }
    ],
    "sg:phone":"+44 1949 844008",
    "sg:postcode":"NG13 0FE",
    "sg:province":"Leicestershire",
    "sg:tags":[
        "building",
        "surveyor"
    ],
    "wof:name":"Goodall Booth",
    "wof:placetype":"venue"
},
  "geometry": {"coordinates":[-0.790509,52.930832],"type":"Point"}
}