{
  "type": "Feature",
  "properties": {
    "addr:full":"56 North Main Street, Carronshore Falkirk Falkirk FK2 8HL",
    "addr:housenumber":"56",
    "addr:postcode":"fk2 8hl",
    "addr:street":"North Main Street",
    "iso:country":"GB",
    "sg:address":"56 North Main Street, Carronshore",
    "sg:city":"Falkirk",
    "sg:classifiers":[
        {
            "category":"Food & Beverages",
            "subcategory":"Meat & Fish",
            "type":"Retail Goods"
        }
    ],
    "sg:phone":"+44 1324 562285",
    "sg:postcode":"FK2 8HL",
    "sg:province":"Falkirk",
    "sg:tags":[
        "chip"
    ],
    "wof:name":"G Falcone Fish & Chip Bar",
    "wof:placetype":"venue"
},
  "geometry": {"coordinates":[-3.7755789757,56.0274238586],"type":"Point"}
}