{
  "type": "Feature",
  "properties": {
    "addr:full":"New House Farm, Cwms Lane Church Stretton Shropshire SY6 7AZ",
    "addr:housenumber":"new house farm",
    "addr:postcode":"sy6 7az",
    "addr:street":"Cwms Lane",
    "iso:country":"GB",
    "sg:address":"New House Farm, Cwms Lane",
    "sg:city":"Church Stretton",
    "sg:classifiers":[
        {
            "category":"Farming",
            "subcategory":"Livestock Farm",
            "type":"Manufacturing & Wholesale Goods"
        }
    ],
    "sg:phone":"+44 1694 722952",
    "sg:postcode":"SY6 7AZ",
    "sg:province":"Shropshire",
    "sg:tags":[
        "others"
    ],
    "wof:name":"P T Parkes & Sons",
    "wof:placetype":"venue"
},
  "geometry": {"coordinates":[-2.8003339767,52.5376548767],"type":"Point"}
}