{
  "type": "Feature",
  "properties": {
    "addr:full":"Garleigh Road, Rothbury Morpeth Northumberland NE65 7RG",
    "addr:postcode":"ne65 7rg",
    "addr:street":"Garleigh Road",
    "iso:country":"GB",
    "sg:address":"Garleigh Road, Rothbury",
    "sg:city":"Morpeth",
    "sg:classifiers":[
        {
            "category":"Professional",
            "subcategory":"Engineering",
            "type":"Services"
        }
    ],
    "sg:phone":"+44 1669 620755",
    "sg:postcode":"NE65 7RG",
    "sg:province":"Northumberland",
    "sg:tags":[
        "agricultural",
        "engineer"
    ],
    "wof:name":"Newtown Engineering Co",
    "wof:placetype":"venue"
},
  "geometry": {"coordinates":[-1.9139939547,55.3092536926],"type":"Point"}
}