{
  "type": "Feature",
  "properties": {
    "addr:full":"206 Turners Hill, Cheshunt Waltham Cross Essex EN8 9DE",
    "addr:housenumber":"206",
    "addr:postcode":"en8 9de",
    "addr:street":"Turners Hill Cheshunt;Cross",
    "iso:country":"GB",
    "sg:address":"206 Turners Hill, Cheshunt",
    "sg:city":"Waltham Cross",
    "sg:classifiers":[
        {
            "category":"Freight",
            "type":"Transportation"
        }
    ],
    "sg:phone":"+44 1992 642963",
    "sg:postcode":"EN8 9DE",
    "sg:province":"Essex",
    "sg:tags":[
        "weighbridge",
        "public"
    ],
    "wof:name":"Weighbridge Systems 2000 Ltd",
    "wof:placetype":"venue"
},
  "geometry": {"coordinates":[-0.034469001,51.7026100159],"type":"Point"}
}