{
  "type": "Feature",
  "properties": {
    "iso:country":"GB",
    "sg:address":"2 Bracken Hill",
    "sg:city":"Peterlee",
    "sg:classifiers":[
        {
            "category":"Professional",
            "subcategory":"Engineering",
            "type":"Services"
        }
    ],
    "sg:phone":"+44 191 518 0020",
    "sg:postcode":"SR8 2LY",
    "sg:province":"Durham",
    "sg:tags":[
        "engineer"
    ],
    "wof:name":"Emerson Process Management",
    "wof:placetype":"venue"
},
  "geometry": {"coordinates":[-1.366247,54.756947],"type":"Point"}
}