{
  "type": "Feature",
  "properties": {
    "iso:country":"GB",
    "sg:address":"Cvs House, 69 Division Street",
    "sg:city":"Sheffield",
    "sg:classifiers":[
        {
            "category":"Organizations",
            "subcategory":"Non-profit Organization",
            "type":"Services"
        }
    ],
    "sg:postcode":"S1 4GE",
    "sg:province":"South Yorkshire",
    "sg:tags":[
        "organisation",
        "voluntary",
        "charity"
    ],
    "wof:name":"The Home Learning Project",
    "wof:placetype":"venue"
},
  "geometry": {"coordinates":[-1.474967,53.379715],"type":"Point"}
}