{
  "type": "Feature",
  "properties": {
    "addr:full":"38 Dawson Road, Byfleet West Byfleet Surrey KT14 7JE",
    "addr:housenumber":"38",
    "addr:postcode":"kt14 7je",
    "addr:street":"Dawson Road;West Byfleet",
    "iso:country":"GB",
    "sg:address":"38 Dawson Road, Byfleet",
    "sg:city":"West Byfleet",
    "sg:classifiers":[
        {
            "category":"Social Services",
            "subcategory":"Adult Care",
            "type":"Services"
        }
    ],
    "sg:phone":"+44 1932 342197",
    "sg:postcode":"KT14 7JE",
    "sg:province":"Surrey",
    "sg:tags":[
        "domestic",
        "cleaning"
    ],
    "wof:name":"Profile Cleaning Services",
    "wof:placetype":"venue"
},
  "geometry": {"coordinates":[-0.479981,51.343479],"type":"Point"}
}