{
  "type": "Feature",
  "properties": {
    "iso:country":"GB",
    "sg:address":"2 Heworth Gro",
    "sg:city":"Washington",
    "sg:classifiers":[
        {
            "category":"Building & Trades",
            "subcategory":"Landscaping Services",
            "type":"Services"
        }
    ],
    "sg:postcode":"NE37 2PZ",
    "sg:province":"Tyne and Wear",
    "sg:tags":[
        "landscape",
        "contractor"
    ],
    "wof:name":"Bamling's Contracts",
    "wof:placetype":"venue"
},
  "geometry": {"coordinates":[-1.525251,54.91468],"type":"Point"}
}