{
  "type": "Feature",
  "properties": {
    "iso:country":"GB",
    "sg:address":"21 Avon Road",
    "sg:city":"Melksham",
    "sg:classifiers":[
        {
            "category":"Freight",
            "type":"Transportation"
        }
    ],
    "sg:phone":"+44 1225 704216",
    "sg:postcode":"SN12 8AY",
    "sg:province":"Wiltshire",
    "sg:tags":[
        "haulage",
        "road"
    ],
    "wof:name":"Johnson's Removals Ltd.",
    "wof:placetype":"venue"
},
  "geometry": {"coordinates":[-2.141609,51.384254],"type":"Point"}
}