{
  "type": "Feature",
  "properties": {
    "iso:country":"GB",
    "sg:address":"16-18 Fletcher Mall",
    "sg:city":"Leicester",
    "sg:classifiers":[
        {
            "category":"Communications",
            "type":"Services"
        }
    ],
    "sg:phone":"+44 116 236 6078",
    "sg:postcode":"LE4 1DF",
    "sg:province":"Leicestershire",
    "sg:tags":[
        "tv",
        "video",
        "radio"
    ],
    "wof:name":"The Energy Centre",
    "wof:placetype":"venue"
},
  "geometry": {"coordinates":[-1.1681799889,52.6657600403],"type":"Point"}
}