{
  "type": "Feature",
  "properties": {
    "addr:full":"New Downs, St Agnes St Marys Cornwall TR5 0ST",
    "addr:postcode":"tr5 0st",
    "addr:street":"St;St",
    "iso:country":"GB",
    "sg:address":"New Downs, St Agnes",
    "sg:city":"St Marys",
    "sg:classifiers":[
        {
            "category":"Wholesale",
            "subcategory":"Non-durable Goods",
            "type":"Manufacturing & Wholesale Goods"
        },
        {
            "category":"Coffee & Tea",
            "type":"Food & Drink"
        }
    ],
    "sg:phone":"+44 1872 552121",
    "sg:postcode":"TR5 0ST",
    "sg:province":"Cornwall",
    "sg:tags":[
        "carry",
        "cash"
    ],
    "wof:name":"L Doble Ltd.",
    "wof:placetype":"venue"
},
  "geometry": {"coordinates":[-5.1991991997,50.3120994568],"type":"Point"}
}