{
  "type": "Feature",
  "properties": {
    "addr:full":"Victoria Works, Ball Street Nottingham Nottinghamshire NG3 3AX",
    "addr:postcode":"ng3 3ax",
    "addr:street":"Ball Street",
    "iso:country":"GB",
    "sg:address":"Victoria Works, Ball Street",
    "sg:city":"Nottingham",
    "sg:classifiers":[
        {
            "category":"Home & Garden",
            "subcategory":"Kitchen Supply",
            "type":"Retail Goods"
        }
    ],
    "sg:phone":"+44 115 955 7878",
    "sg:postcode":"NG3 3AX",
    "sg:province":"Nottinghamshire",
    "sg:tags":[
        "catering"
    ],
    "wof:name":"1st Class Food",
    "wof:placetype":"venue"
},
  "geometry": {"coordinates":[-1.1277400255,52.9655990601],"type":"Point"}
}