{
  "type": "Feature",
  "properties": {
    "iso:country":"GB",
    "sg:address":"Station App, High Street",
    "sg:city":"Ongar",
    "sg:classifiers":[
        {
            "category":"Shopping",
            "subcategory":"Bicycles & Sporting Goods",
            "type":"Retail Goods"
        }
    ],
    "sg:postcode":"CM5 9BN",
    "sg:province":"Essex",
    "sg:tags":[
        "dance",
        "balletwear"
    ],
    "wof:name":"Dance World Outfitters",
    "wof:placetype":"venue"
},
  "geometry": {"coordinates":[0.24517,51.706131],"type":"Point"}
}