{
  "type": "Feature",
  "properties": {
    "addr:full":"2 Abbey Street Rugby Warwickshire CV21 3LH",
    "addr:housenumber":"2",
    "addr:postcode":"cv21 3lh",
    "addr:street":"Abbey Street",
    "iso:country":"GB",
    "sg:address":"2 Abbey Street",
    "sg:city":"Rugby",
    "sg:classifiers":[
        {
            "category":"Personal",
            "subcategory":"Barber",
            "type":"Services"
        }
    ],
    "sg:phone":"+44 1788 565309",
    "sg:postcode":"CV21 3LH",
    "sg:province":"Warwickshire",
    "sg:tags":[
        "men's",
        "hairdresser"
    ],
    "wof:name":"Fosters Hairdressers",
    "wof:placetype":"venue"
},
  "geometry": {"coordinates":[-1.2504839897,52.3778991699],"type":"Point"}
}