{
  "type": "Feature",
  "properties": {
    "addr:full":"124 Quebec Street Bolton Lancashire BL3 5LX",
    "addr:housenumber":"124",
    "addr:postcode":"bl3 5lx",
    "addr:street":"Quebec Street",
    "iso:country":"GB",
    "sg:address":"124 Quebec Street",
    "sg:city":"Bolton",
    "sg:classifiers":[
        {
            "category":"Food & Beverages",
            "subcategory":"Supermarket",
            "type":"Retail Goods"
        },
        {
            "category":"Food & Beverages",
            "subcategory":"Fruits & Vegetables",
            "type":"Retail Goods"
        }
    ],
    "sg:postcode":"BL3 5LX",
    "sg:province":"Lancashire",
    "sg:tags":[
        "greengrocer"
    ],
    "wof:name":"Wellfield Stores",
    "wof:placetype":"venue"
},
  "geometry": {"coordinates":[-2.4464390278,53.5692596436],"type":"Point"}
}