{
  "type": "Feature",
  "properties": {
    "addr:full":"Suite 15 Westmead Business Cntr, Cowper Avenue Sutton Surrey SM1 3RD",
    "addr:postcode":"sm1 3rd",
    "addr:street":"Suite 15 Westmead Business Cntr Cowper Avenue",
    "iso:country":"GB",
    "sg:address":"Suite 15 Westmead Business Cntr, Cowper Avenue",
    "sg:city":"Sutton",
    "sg:classifiers":[
        {
            "category":"Manufacturing",
            "subcategory":"Petroleum Products",
            "type":"Manufacturing & Wholesale Goods"
        }
    ],
    "sg:phone":"+44 20 8770 9414",
    "sg:postcode":"SM1 3RD",
    "sg:province":"Surrey",
    "sg:tags":[
        "double",
        "glazing"
    ],
    "wof:name":"Weatherseal Window Systems",
    "wof:placetype":"venue"
},
  "geometry": {"coordinates":[-0.197558,51.361191],"type":"Point"}
}