{
  "type": "Feature",
  "properties": {
    "addr:full":"35 Hythe St Dartford Kent DA1 1BE",
    "addr:housenumber":"35",
    "addr:postcode":"da1 1be",
    "addr:street":"Hythe St",
    "iso:country":"GB",
    "sg:address":"35 Hythe St",
    "sg:city":"Dartford",
    "sg:classifiers":[
        {
            "category":"Farming",
            "subcategory":"Livestock Farm",
            "type":"Manufacturing & Wholesale Goods"
        }
    ],
    "sg:postcode":"DA1 1BE",
    "sg:province":"Kent",
    "sg:tags":[
        "breeder"
    ],
    "wof:name":"Clement,G,",
    "wof:placetype":"venue"
},
  "geometry": {"coordinates":[0.216777,51.445187],"type":"Point"}
}