{
  "type": "Feature",
  "properties": {
    "addr:full":"Third Floor, 111 Baker Street London Greater London W1U 6RP",
    "addr:housenumber":"third;111",
    "addr:postcode":"w1u 6rp",
    "addr:street":"Baker Street",
    "iso:country":"GB",
    "sg:address":"Third Floor, 111 Baker Street",
    "sg:city":"London",
    "sg:classifiers":[
        {
            "category":"Travel",
            "subcategory":"Travel Agent",
            "type":"Entertainment"
        }
    ],
    "sg:phone":"+44 20 7299 9300",
    "sg:postcode":"W1U 6RP",
    "sg:province":"Greater London",
    "wof:name":"Perfect Travel Ltd.",
    "wof:placetype":"venue"
},
  "geometry": {"coordinates":[-0.157315,51.521206],"type":"Point"}
}