{
  "type": "Feature",
  "properties": {
    "iso:country":"GB",
    "sg:address":"9 Highfield Drive",
    "sg:city":"Bromley",
    "sg:classifiers":[
        {
            "category":"Shopping",
            "subcategory":"Computers & Home Electronics",
            "type":"Retail Goods"
        }
    ],
    "sg:phone":"+44 20 8464 2163",
    "sg:postcode":"BR2 0RX",
    "sg:province":"Kent",
    "wof:name":"S & H Computer Systems Ltd",
    "wof:placetype":"venue"
},
  "geometry": {"coordinates":[0.005277,51.397724],"type":"Point"}
}