{
  "type": "Feature",
  "properties": {
    "addr:full":"Chalk Farm Road, Camden London Greater London NW1 8AH",
    "addr:postcode":"nw1 8ah",
    "addr:street":"Chalk Farm Road",
    "iso:country":"GB",
    "sg:address":"Chalk Farm Road, Camden",
    "sg:city":"London",
    "sg:classifiers":[
        {
            "category":"Professional",
            "subcategory":"Business Services",
            "type":"Services"
        }
    ],
    "sg:phone":"+44 20 7485 5511",
    "sg:postcode":"NW1 8AH",
    "sg:province":"Greater London",
    "sg:tags":[
        "operator",
        "market"
    ],
    "wof:name":"Stables Market (Camden) Ltd.",
    "wof:placetype":"venue"
},
  "geometry": {"coordinates":[-0.1484870017,51.542804718],"type":"Point"}
}