{
  "type": "Feature",
  "properties": {
    "addr:full":"Lower Village, Bradworthy Holsworthy Cornwall EX22 7TQ",
    "addr:postcode":"ex22 7tq",
    "addr:street":"Lower",
    "iso:country":"GB",
    "sg:address":"Lower Village, Bradworthy",
    "sg:city":"Holsworthy",
    "sg:classifiers":[
        {
            "category":"Retail",
            "subcategory":"Repair Shop",
            "type":"Services"
        }
    ],
    "sg:phone":"+44 1409 241782",
    "sg:postcode":"EX22 7TQ",
    "sg:province":"Cornwall",
    "sg:tags":[
        "clocks",
        "watch",
        "sale",
        "clock"
    ],
    "wof:name":"Lavender Clockmakers & Jewellers",
    "wof:placetype":"venue"
},
  "geometry": {"coordinates":[-4.386544,50.898212],"type":"Point"}
}