{
  "type": "Feature",
  "properties": {
    "iso:country":"GB",
    "sg:address":"113 Wellhall Road",
    "sg:city":"Hamilton",
    "sg:classifiers":[
        {
            "category":"Food & Beverages",
            "subcategory":"Meat & Fish",
            "type":"Retail Goods"
        },
        {
            "category":"Food & Beverages",
            "subcategory":"Groceries & Convenience Stores",
            "type":"Retail Goods"
        }
    ],
    "sg:phone":"+44 1698 283025",
    "sg:postcode":"ML3 9XN",
    "sg:province":"South Lanarkshire",
    "sg:tags":[
        "shop",
        "chip"
    ],
    "wof:name":"Golden Fry",
    "wof:placetype":"venue"
},
  "geometry": {"coordinates":[-4.0733189583,55.7696304321],"type":"Point"}
}