{
  "type": "Feature",
  "properties": {
    "iso:country":"GB",
    "sg:address":"1 Shotesham Road",
    "sg:city":"Norwich",
    "sg:classifiers":[
        {
            "category":"Food & Beverages",
            "subcategory":"Groceries & Convenience Stores",
            "type":"Retail Goods"
        }
    ],
    "sg:phone":"+44 1508 492108",
    "sg:postcode":"NR14 7LE",
    "sg:province":"Norfolk",
    "wof:name":"Premier Express",
    "wof:placetype":"venue"
},
  "geometry": {"coordinates":[1.349681,52.565605],"type":"Point"}
}