{
  "type": "Feature",
  "properties": {
    "iso:country":"GB",
    "sg:address":"8 St Andrews Street",
    "sg:city":"Harrogate",
    "sg:classifiers":[
        {
            "category":"Building & Trades",
            "subcategory":"Cleaning & Sanitation",
            "type":"Services"
        }
    ],
    "sg:phone":"+44 1423 884435",
    "sg:postcode":"HG2 7RS",
    "sg:province":"North Yorkshire",
    "sg:tags":[
        "commercial"
    ],
    "wof:name":"Interior Cleaning Services",
    "wof:placetype":"venue"
},
  "geometry": {"coordinates":[-1.51413,53.994797],"type":"Point"}
}