{
  "type": "Feature",
  "properties": {
    "addr:full":"231 Hertford Rd Lower Edmonton Greater London N9 7ER",
    "addr:housenumber":"231",
    "addr:postcode":"n9 7er",
    "addr:street":"Hertford Rd",
    "iso:country":"GB",
    "sg:address":"231 Hertford Rd",
    "sg:city":"Lower Edmonton",
    "sg:classifiers":[
        {
            "category":"Food & Beverages",
            "subcategory":"Fruits & Vegetables",
            "type":"Retail Goods"
        }
    ],
    "sg:phone":"+44 20 8805 1042",
    "sg:postcode":"N9 7ER",
    "sg:province":"Greater London",
    "sg:tags":[
        "greengrocer"
    ],
    "wof:name":"B Chellar",
    "wof:placetype":"venue"
},
  "geometry": {"coordinates":[-0.054791,51.632233],"type":"Point"}
}