{
  "type": "Feature",
  "properties": {
    "addr:full":"289 London Road, Stone Greenhithe Kent DA9 9DA",
    "addr:housenumber":"289",
    "addr:postcode":"da9 9da",
    "addr:street":"London Road",
    "iso:country":"GB",
    "sg:address":"289 London Road, Stone",
    "sg:city":"Greenhithe",
    "sg:classifiers":[
        {
            "category":"Bars & Pubs",
            "type":"Food & Drink"
        }
    ],
    "sg:phone":"+44 1322 382005",
    "sg:postcode":"DA9 9DA",
    "sg:province":"Kent",
    "sg:tags":[
        "pubs",
        "inn"
    ],
    "wof:name":"The Welcome All",
    "wof:placetype":"venue"
},
  "geometry": {"coordinates":[0.2644009888,51.4462928772],"type":"Point"}
}