{
  "type": "Feature",
  "properties": {
    "iso:country":"GB",
    "sg:address":"360-364 City Road",
    "sg:city":"London",
    "sg:classifiers":[
        {
            "category":"Professional",
            "subcategory":"Management & Consulting",
            "type":"Services"
        }
    ],
    "sg:postcode":"EC1V 2PY",
    "sg:province":"Greater London",
    "sg:tags":[
        "consultant",
        "energy",
        "conservation"
    ],
    "wof:name":"Entech Energy Consultants Ltd.",
    "wof:placetype":"venue"
},
  "geometry": {"coordinates":[-0.095025,51.528973],"type":"Point"}
}