{
  "type": "Feature",
  "properties": {
    "addr:full":"20 High Street Bargoed Caerphilly CF81 8RA",
    "addr:housenumber":"20",
    "addr:postcode":"cf81 8ra",
    "addr:street":"High Street",
    "iso:country":"GB",
    "sg:address":"20 High Street",
    "sg:city":"Bargoed",
    "sg:classifiers":[
        {
            "category":"Travel",
            "subcategory":"Travel Agent",
            "type":"Entertainment"
        }
    ],
    "sg:phone":"+44 1443 820369",
    "sg:postcode":"CF81 8RA",
    "sg:province":"Caerphilly",
    "wof:name":"Holiday Express",
    "wof:placetype":"venue"
},
  "geometry": {"coordinates":[-3.229021,51.690861],"type":"Point"}
}