{
  "type": "Feature",
  "properties": {
    "addr:full":"147 Stagsden Road, Bromham Bedford Bedfordshire MK43 8QJ",
    "addr:housenumber":"147",
    "addr:postcode":"mk43 8qj",
    "addr:street":"Stagsden Road",
    "iso:country":"GB",
    "sg:address":"147 Stagsden Road, Bromham",
    "sg:city":"Bedford",
    "sg:classifiers":[
        {
            "category":"Building & Trades",
            "subcategory":"Landscaping Services",
            "type":"Services"
        }
    ],
    "sg:postcode":"MK43 8QJ",
    "sg:province":"Bedfordshire",
    "sg:tags":[
        "landscape",
        "contractor"
    ],
    "wof:name":"D J Goff",
    "wof:placetype":"venue"
},
  "geometry": {"coordinates":[-0.53906,52.1423],"type":"Point"}
}