{
  "type": "Feature",
  "properties": {
    "addr:full":"Unit 3 Merlin Park, Wood Lane Birmingham West Midlands B24 9LZ",
    "addr:housenumber":"unit 3",
    "addr:postcode":"b24 9lz",
    "addr:street":"Merlin Park Wood Lane",
    "iso:country":"GB",
    "sg:address":"Unit 3 Merlin Park, Wood Lane",
    "sg:city":"Birmingham",
    "sg:classifiers":[
        {
            "category":"Professional",
            "subcategory":"Business Services",
            "type":"Services"
        }
    ],
    "sg:postcode":"B24 9LZ",
    "sg:province":"West Midlands",
    "sg:tags":[
        "distribution"
    ],
    "wof:name":"Adam Jones Distribution Ltd.",
    "wof:placetype":"venue"
},
  "geometry": {"coordinates":[-1.82187,52.518581],"type":"Point"}
}