{
  "type": "Feature",
  "properties": {
    "addr:full":"2 Perimeter Road Elgin Moray IV30 6DF",
    "addr:housenumber":"2",
    "addr:postcode":"iv30 6df",
    "addr:street":"Perimeter Road",
    "iso:country":"GB",
    "sg:address":"2 Perimeter Road",
    "sg:city":"Elgin",
    "sg:classifiers":[
        {
            "category":"Manufacturing",
            "subcategory":"Tools & Machinery",
            "type":"Manufacturing & Wholesale Goods"
        },
        {
            "category":"Wholesale",
            "subcategory":"Machinery & Supplies",
            "type":"Manufacturing & Wholesale Goods"
        }
    ],
    "sg:phone":"+44 1343 545207",
    "sg:postcode":"IV30 6DF",
    "sg:province":"Moray",
    "sg:tags":[
        "equipment",
        "pump",
        "hydraulic",
        "manufacturer"
    ],
    "wof:name":"Hendry Hydraulics Ltd.",
    "wof:placetype":"venue"
},
  "geometry": {"coordinates":[-3.2920930386,57.6460952759],"type":"Point"}
}