{
  "type": "Feature",
  "properties": {
    "iso:country":"GB",
    "sg:address":"60 Charlotte Street",
    "sg:city":"London",
    "sg:classifiers":[
        {
            "category":"Professional",
            "subcategory":"Research",
            "type":"Services"
        }
    ],
    "sg:phone":"+44 20 7580 0277",
    "sg:postcode":"W1T 2NU",
    "sg:province":"Greater London",
    "sg:tags":[
        "market"
    ],
    "wof:name":"Conway Smith Rose",
    "wof:placetype":"venue"
},
  "geometry": {"coordinates":[-0.1361140013,51.5200386047],"type":"Point"}
}