{
  "type": "Feature",
  "properties": {
    "addr:full":"16-18 Chancellor Street, Partick Glasgow Glasgow City G11 5RQ",
    "addr:housenumber":"16-18",
    "addr:postcode":"g11 5rq",
    "addr:street":"Chancellor Street",
    "iso:country":"GB",
    "sg:address":"16-18 Chancellor Street, Partick",
    "sg:city":"Glasgow",
    "sg:classifiers":[
        {
            "category":"Shopping",
            "subcategory":"Bicycles & Sporting Goods",
            "type":"Retail Goods"
        }
    ],
    "sg:phone":"+44 141 357 1344",
    "sg:postcode":"G11 5RQ",
    "sg:province":"Glasgow City",
    "sg:tags":[
        "shop",
        "cycle",
        "accessory"
    ],
    "wof:name":"West End Cycles",
    "wof:placetype":"venue"
},
  "geometry": {"coordinates":[-4.298555851,55.8719863892],"type":"Point"}
}