{
  "type": "Feature",
  "properties": {
    "iso:country":"GB",
    "sg:address":"Odyssey House",
    "sg:city":"Cheltenham",
    "sg:classifiers":[
        {
            "category":"Recreation",
            "subcategory":"Gun Range",
            "type":"Entertainment"
        }
    ],
    "sg:phone":"+44 1242 224482",
    "sg:postcode":"GL50 3FB",
    "sg:province":"Gloucestershire",
    "sg:tags":[
        "operator",
        "tour"
    ],
    "wof:name":"The Odyssey Experience Ltd.",
    "wof:placetype":"venue"
},
  "geometry": {"coordinates":[-2.0784590244,51.8980484009],"type":"Point"}
}