{
  "type": "Feature",
  "properties": {
    "addr:full":"Truro Drive Plymouth Devon PL5 4LA",
    "addr:postcode":"pl5 4la",
    "addr:street":"Truro Drive",
    "iso:country":"GB",
    "sg:address":"Truro Drive",
    "sg:city":"Plymouth",
    "sg:classifiers":[
        {
            "category":"Home & Garden",
            "subcategory":"Garden Supply",
            "type":"Retail Goods"
        }
    ],
    "sg:phone":"+44 1752 701645",
    "sg:postcode":"PL5 4LA",
    "sg:province":"Devon",
    "sg:tags":[
        "nursery",
        "centre"
    ],
    "wof:name":"Woodvale Nurseries",
    "wof:placetype":"venue"
},
  "geometry": {"coordinates":[-4.167289,50.422256],"type":"Point"}
}