{
  "type": "Feature",
  "properties": {
    "iso:country":"GB",
    "sg:address":"20a Nazeingbury Parade, Nazeing Road, Nazeing",
    "sg:city":"Waltham Abbey",
    "sg:classifiers":[
        {
            "category":"Food & Beverages",
            "subcategory":"Bakery",
            "type":"Retail Goods"
        }
    ],
    "sg:phone":"+44 1992 892269",
    "sg:postcode":"EN9 2JL",
    "sg:province":"Essex",
    "sg:tags":[
        "baker"
    ],
    "wof:name":"Alan Braithwaite",
    "wof:placetype":"venue"
},
  "geometry": {"coordinates":[0.048448,51.738914],"type":"Point"}
}