{
  "type": "Feature",
  "properties": {
    "addr:full":"Unit, 2, Quay Rd Blyth Northumberland NE24 2AS",
    "addr:housenumber":"unit 2",
    "addr:postcode":"ne24 2as",
    "addr:street":"Quay Rd;Northumberland",
    "iso:country":"GB",
    "sg:address":"Unit, 2, Quay Rd",
    "sg:city":"Blyth",
    "sg:classifiers":[
        {
            "category":"Retail",
            "subcategory":"Auto Repair",
            "type":"Services"
        }
    ],
    "sg:phone":"+44 1670 352761",
    "sg:postcode":"NE24 2AS",
    "sg:province":"Northumberland",
    "sg:tags":[
        "modification",
        "garage"
    ],
    "wof:name":"A & A Charlton",
    "wof:placetype":"venue"
},
  "geometry": {"coordinates":[-1.5038590431,55.1287117004],"type":"Point"}
}