{
  "type": "Feature",
  "properties": {
    "addr:full":"Mary Stevens Centre, 221 Hagley Road Stourbridge Staffordshire DY8 2JP",
    "addr:housenumber":"221",
    "addr:postcode":"dy8 2jp",
    "addr:street":"Mary;Hagley Road",
    "iso:country":"GB",
    "sg:address":"Mary Stevens Centre, 221 Hagley Road",
    "sg:city":"Stourbridge",
    "sg:classifiers":[
        {
            "category":"Organizations",
            "subcategory":"Non-profit Organization",
            "type":"Services"
        }
    ],
    "sg:phone":"+44 1384 444053",
    "sg:postcode":"DY8 2JP",
    "sg:province":"Staffordshire",
    "sg:tags":[
        "organisation",
        "voluntary",
        "charity"
    ],
    "wof:name":"Partially Sighted Society",
    "wof:placetype":"venue"
},
  "geometry": {"coordinates":[-2.147854,52.453949],"type":"Point"}
}