{
  "type": "Feature",
  "properties": {
    "addr:full":"Unit 7a Gloucester Gloucestershire GL1 4JD",
    "addr:housenumber":"unit 7a",
    "addr:postcode":"gl1 4jd",
    "iso:country":"GB",
    "sg:address":"Unit 7a",
    "sg:city":"Gloucester",
    "sg:classifiers":[
        {
            "category":"Military Area",
            "subcategory":"Air Force Base",
            "type":"Public Place"
        }
    ],
    "sg:phone":"+44 1452 385050",
    "sg:postcode":"GL1 4JD",
    "sg:province":"Gloucestershire",
    "sg:tags":[
        "taxi",
        "hire",
        "private"
    ],
    "wof:name":"John's Private Hire",
    "wof:placetype":"venue"
},
  "geometry": {"coordinates":[-2.2496240139,51.8638114929],"type":"Point"}
}