{
  "type": "Feature",
  "properties": {
    "iso:country":"GB",
    "sg:address":"16 Furlong Cres",
    "sg:city":"Blackpool",
    "sg:classifiers":[
        {
            "category":"Banks & Credit Unions",
            "subcategory":"Bank",
            "type":"Services"
        }
    ],
    "sg:phone":"+44 1253 311848",
    "sg:postcode":"FY3 7LP",
    "sg:province":"Lancashire",
    "sg:tags":[
        "stocktaking",
        "inventory"
    ],
    "wof:name":"Hindle & Hargate",
    "wof:placetype":"venue"
},
  "geometry": {"coordinates":[-3.0158679485,53.8361282349],"type":"Point"}
}