{
  "type": "Feature",
  "properties": {
    "addr:full":"Manor Farm, Main St Goole East Riding of Yorkshire DN14 7YW",
    "addr:postcode":"dn14 7yw",
    "addr:street":"Manor;Main St",
    "iso:country":"GB",
    "sg:address":"Manor Farm, Main St",
    "sg:city":"Goole",
    "sg:classifiers":[
        {
            "category":"Farming",
            "subcategory":"Livestock Farm",
            "type":"Manufacturing & Wholesale Goods"
        }
    ],
    "sg:phone":"+44 1430 440347",
    "sg:postcode":"DN14 7YW",
    "sg:province":"East Riding of Yorkshire",
    "sg:tags":[
        "others"
    ],
    "wof:name":"F & B Thompson",
    "wof:placetype":"venue"
},
  "geometry": {"coordinates":[-0.7249500155,53.7074584961],"type":"Point"}
}