{
  "type": "Feature",
  "properties": {
    "addr:full":"69 Rhosddu Rusty Road Wrexham Wrexham LL11 2NW",
    "addr:housenumber":"69",
    "addr:postcode":"ll11 2nw",
    "addr:street":"Rhosddu Rusty Road",
    "iso:country":"GB",
    "sg:address":"69 Rhosddu Rusty Road",
    "sg:city":"Wrexham",
    "sg:classifiers":[
        {
            "category":"Professional",
            "subcategory":"Printing & Photocopies",
            "type":"Services"
        }
    ],
    "sg:phone":"+44 1978 265837",
    "sg:postcode":"LL11 2NW",
    "sg:province":"Wrexham",
    "sg:tags":[
        "printer"
    ],
    "wof:name":"Jones & Williams (Printers) Ltd.",
    "wof:placetype":"venue"
},
  "geometry": {"coordinates":[-2.9979300499,53.0536804199],"type":"Point"}
}