{
  "type": "Feature",
  "properties": {
    "addr:full":"94 High Street, Blainia Abertillery Blaenau Gwent NP13 3BN",
    "addr:housenumber":"94",
    "addr:postcode":"np13 3bn",
    "addr:street":"High Street;Abertillery Blaenau Gwent",
    "iso:country":"GB",
    "sg:address":"94 High Street, Blainia",
    "sg:city":"Abertillery",
    "sg:classifiers":[
        {
            "category":"Ice Cream",
            "type":"Food & Drink"
        }
    ],
    "sg:postcode":"NP13 3BN",
    "sg:province":"Blaenau Gwent",
    "sg:tags":[
        "shop",
        "mobile",
        "parlour"
    ],
    "wof:name":"G G F Zeraschi",
    "wof:placetype":"venue"
},
  "geometry": {"coordinates":[-3.1376230717,51.7301177979],"type":"Point"}
}