{
  "type": "Feature",
  "properties": {
    "iso:country":"GB",
    "sg:address":"201/206 Bloomfield Rd",
    "sg:city":"Tipton",
    "sg:classifiers":[
        {
            "category":"Manufacturing",
            "subcategory":"Building Materials",
            "type":"Manufacturing & Wholesale Goods"
        }
    ],
    "sg:postcode":"DY4 9AJ",
    "sg:province":"West Midlands",
    "sg:tags":[
        "concrete",
        "product"
    ],
    "wof:name":"Bloomfield Precast Concrete",
    "wof:placetype":"venue"
},
  "geometry": {"coordinates":[-2.074955,52.532452],"type":"Point"}
}