{
  "type": "Feature",
  "properties": {
    "addr:full":"Committee, 4 Thornwell Way Wincanton Somerset BA9 9EN",
    "addr:housenumber":"4",
    "addr:postcode":"ba9 9en",
    "addr:street":"Committee;Thornwell Way",
    "iso:country":"GB",
    "sg:address":"Committee, 4 Thornwell Way",
    "sg:city":"Wincanton",
    "sg:classifiers":[
        {
            "category":"Organizations",
            "subcategory":"Non-profit Organization",
            "type":"Services"
        }
    ],
    "sg:postcode":"BA9 9EN",
    "sg:province":"Somerset",
    "sg:tags":[
        "organisation",
        "voluntary",
        "charity"
    ],
    "wof:name":"The Cancer Research Campaign",
    "wof:placetype":"venue"
},
  "geometry": {"coordinates":[-2.4131789207,51.057800293],"type":"Point"}
}