{
  "type": "Feature",
  "properties": {
    "addr:full":"Woods Farm Wokingham Berkshire RG40 3AE",
    "addr:postcode":"rg40 3ae",
    "iso:country":"GB",
    "sg:address":"Woods Farm",
    "sg:city":"Wokingham",
    "sg:classifiers":[
        {
            "category":"Banks & Credit Unions",
            "subcategory":"Financial Services",
            "type":"Services"
        }
    ],
    "sg:phone":"+44 118 977 1961",
    "sg:postcode":"RG40 3AE",
    "sg:province":"Berkshire",
    "sg:tags":[
        "adviser"
    ],
    "wof:name":"Tamar",
    "wof:placetype":"venue"
},
  "geometry": {"coordinates":[-0.8345940113,51.4108009338],"type":"Point"}
}