{
  "type": "Feature",
  "properties": {
    "iso:country":"GB",
    "sg:address":"330 Mare Street",
    "sg:city":"London",
    "sg:classifiers":[
        {
            "category":"Personal",
            "subcategory":"Beauty Salon",
            "type":"Services"
        },
        {
            "category":"Personal",
            "subcategory":"Barber",
            "type":"Services"
        }
    ],
    "sg:phone":"+44 20 8985 3084",
    "sg:postcode":"E8 1HA",
    "sg:province":"Greater London",
    "sg:tags":[
        "unisex",
        "hairdresser"
    ],
    "wof:name":"Casanova",
    "wof:placetype":"venue"
},
  "geometry": {"coordinates":[-0.054974,51.546761],"type":"Point"}
}