{
  "type": "Feature",
  "properties": {
    "iso:country":"GB",
    "sg:address":"10 Commercial Square",
    "sg:city":"Camborne",
    "sg:classifiers":[
        {
            "category":"Shopping",
            "subcategory":"Shoes",
            "type":"Retail Goods"
        }
    ],
    "sg:phone":"+44 1209 717921",
    "sg:postcode":"TR14 8DZ",
    "sg:province":"Cornwall",
    "sg:tags":[
        "shop"
    ],
    "wof:name":"Shoe Express",
    "wof:placetype":"venue"
},
  "geometry": {"coordinates":[-5.300675,50.213306],"type":"Point"}
}