{
  "type": "Feature",
  "properties": {
    "addr:full":"27a Willesden Lane Kilburn Greater London NW6 7RD",
    "addr:housenumber":"27a",
    "addr:postcode":"nw6 7rd",
    "addr:street":"Willesden Lane",
    "iso:country":"GB",
    "sg:address":"27a Willesden Lane",
    "sg:city":"Kilburn",
    "sg:classifiers":[
        {
            "category":"Professional",
            "subcategory":"Printing & Photocopies",
            "type":"Services"
        }
    ],
    "sg:phone":"+44 20 7328 2415",
    "sg:postcode":"NW6 7RD",
    "sg:province":"Greater London",
    "sg:tags":[
        "plate",
        "lithographic",
        "maker"
    ],
    "wof:name":"Colour Printing",
    "wof:placetype":"venue"
},
  "geometry": {"coordinates":[-0.199333,51.541489],"type":"Point"}
}