{
  "type": "Feature",
  "properties": {
    "addr:full":"Thorpefields, Gunthorpe Road, Newborough Peterborough Cambridgeshire PE6 7SE",
    "addr:postcode":"pe6 7se",
    "addr:street":"Thorpefields Gunthorpe Road",
    "iso:country":"GB",
    "sg:address":"Thorpefields, Gunthorpe Road, Newborough",
    "sg:city":"Peterborough",
    "sg:classifiers":[
        {
            "category":"Home & Garden",
            "subcategory":"Garden Supply",
            "type":"Retail Goods"
        },
        {
            "category":"Farming",
            "subcategory":"Crops",
            "type":"Manufacturing & Wholesale Goods"
        }
    ],
    "sg:phone":"+44 1733 810254",
    "sg:postcode":"PE6 7SE",
    "sg:province":"Cambridgeshire",
    "sg:tags":[
        "bulb",
        "arable",
        "grower"
    ],
    "wof:name":"F E Godfrey",
    "wof:placetype":"venue"
},
  "geometry": {"coordinates":[-0.2212740034,52.6406211853],"type":"Point"}
}