{
  "type": "Feature",
  "properties": {
    "addr:full":"Abbey Road Motorist Centre, Belsize Road London Greater London NW6 4AD",
    "addr:postcode":"nw6 4ad",
    "addr:street":"Abbey Road Motorist;Belsize Road",
    "iso:country":"GB",
    "sg:address":"Abbey Road Motorist Centre, Belsize Road",
    "sg:city":"London",
    "sg:classifiers":[
        {
            "category":"Professional",
            "subcategory":"Art Services",
            "type":"Services"
        }
    ],
    "sg:postcode":"NW6 4AD",
    "sg:province":"Greater London",
    "sg:tags":[
        "framing"
    ],
    "wof:name":"The Picture Warehouse Ltd.",
    "wof:placetype":"venue"
},
  "geometry": {"coordinates":[-0.1858499944,51.5401191711],"type":"Point"}
}