{
  "type": "Feature",
  "properties": {
    "iso:country":"GB",
    "sg:address":"46 Morfydd Street, Morriston",
    "sg:city":"Swansea",
    "sg:classifiers":[
        {
            "category":"Health Services",
            "subcategory":"Dentist",
            "type":"Services"
        }
    ],
    "sg:phone":"+44 1792 774000",
    "sg:postcode":"SA6 8BU",
    "sg:province":"Swansea",
    "wof:name":"Family Dental Surgery",
    "wof:placetype":"venue"
},
  "geometry": {"coordinates":[-3.9247460365,51.6619224548],"type":"Point"}
}