{
  "type": "Feature",
  "properties": {
    "iso:country":"GB",
    "sg:address":"9 Holmesdale Road",
    "sg:city":"Reigate",
    "sg:classifiers":[
        {
            "category":"Personal",
            "subcategory":"Beauty Salon",
            "type":"Services"
        }
    ],
    "sg:phone":"+44 1737 221219",
    "sg:postcode":"RH2 0BA",
    "sg:province":"Surrey",
    "wof:name":"Sans Souci",
    "wof:placetype":"venue"
},
  "geometry": {"coordinates":[-0.2044859976,51.242351532],"type":"Point"}
}