{
  "type": "Feature",
  "properties": {
    "iso:country":"GB",
    "sg:address":"5 Goldbeaters House, 6-12 Manette Street",
    "sg:city":"London",
    "sg:classifiers":[
        {
            "category":"Travel",
            "subcategory":"Travel Agent",
            "type":"Entertainment"
        }
    ],
    "sg:postcode":"W1D 4AT",
    "sg:province":"Greater London",
    "wof:name":"Equinox Travel Ltd",
    "wof:placetype":"venue"
},
  "geometry": {"coordinates":[-0.1308880001,51.5147895813],"type":"Point"}
}