{
  "type": "Feature",
  "properties": {
    "iso:country":"GB",
    "sg:address":"Springvale Place",
    "sg:city":"Saltcoats",
    "sg:classifiers":[
        {
            "category":"Education",
            "subcategory":"Library",
            "type":"Public Place"
        }
    ],
    "sg:phone":"+44 1294 469546",
    "sg:postcode":"KA21 5LS",
    "sg:province":"North Ayrshire",
    "sg:tags":[
        "book"
    ],
    "wof:name":"Saltcoats Branch Library",
    "wof:placetype":"venue"
},
  "geometry": {"coordinates":[-4.787464,55.63549],"type":"Point"}
}