{
  "type": "Feature",
  "properties": {
    "addr:full":"Unit 28 Century St Industrial Estate Sheffield South Yorkshire S9 5DX",
    "addr:housenumber":"unit 28",
    "addr:postcode":"s9 5dx",
    "addr:street":"Century St Industrial Estate",
    "iso:country":"GB",
    "sg:address":"Unit 28 Century St Industrial Estate",
    "sg:city":"Sheffield",
    "sg:classifiers":[
        {
            "category":"Professional",
            "subcategory":"Advertising",
            "type":"Services"
        }
    ],
    "sg:phone":"+44 114 261 8035",
    "sg:postcode":"S9 5DX",
    "sg:province":"South Yorkshire",
    "sg:tags":[
        "outdoor"
    ],
    "wof:name":"J C Decaux Uk",
    "wof:placetype":"venue"
},
  "geometry": {"coordinates":[-1.419039011,53.3963394165],"type":"Point"}
}