{
  "type": "Feature",
  "properties": {
    "iso:country":"GB",
    "sg:address":"42 Market Place",
    "sg:city":"Leicester",
    "sg:classifiers":[
        {
            "category":"Food & Beverages",
            "subcategory":"Meat & Fish",
            "type":"Retail Goods"
        }
    ],
    "sg:phone":"+44 116 253 8669",
    "sg:postcode":"LE1 5GF",
    "sg:province":"Leicestershire",
    "sg:tags":[
        "butcher"
    ],
    "wof:name":"Dewhurst Butchers",
    "wof:placetype":"venue"
},
  "geometry": {"coordinates":[-1.1336970329,52.635219574],"type":"Point"}
}