{
  "type": "Feature",
  "properties": {
    "addr:full":"Spring Gardens Westminster Greater London SW1A 2BN",
    "addr:postcode":"sw1a 2bn",
    "addr:street":"Spring Gardens",
    "iso:country":"GB",
    "sg:address":"Spring Gardens",
    "sg:city":"Westminster",
    "sg:classifiers":[
        {
            "category":"Parking",
            "type":"Transportation"
        }
    ],
    "sg:phone":"+44 20 7930 1565",
    "sg:postcode":"SW1A 2BN",
    "sg:province":"Greater London",
    "sg:tags":[
        "car",
        "park"
    ],
    "wof:name":"Trafalgar Car Parking",
    "wof:placetype":"venue"
},
  "geometry": {"coordinates":[-0.128017,51.506737],"type":"Point"}
}