{
  "type": "Feature",
  "properties": {
    "addr:full":"93 Pimlico Road London Greater London SW1W 8PH",
    "addr:housenumber":"93",
    "addr:postcode":"sw1w 8ph",
    "addr:street":"Pimlico Road",
    "iso:country":"GB",
    "sg:address":"93 Pimlico Road",
    "sg:city":"London",
    "sg:classifiers":[
        {
            "category":"Shopping",
            "subcategory":"Antiques",
            "type":"Retail Goods"
        }
    ],
    "sg:phone":"+44 20 7730 7987",
    "sg:postcode":"SW1W 8PH",
    "sg:province":"Greater London",
    "wof:name":"Christopher Howe Antiques",
    "wof:placetype":"venue"
},
  "geometry": {"coordinates":[-0.1544069946,51.4900779724],"type":"Point"}
}