{
  "type": "Feature",
  "properties": {
    "addr:full":"39 Liverpool Road North, Burscough Ormskirk Lancashire L40 0SA",
    "addr:housenumber":"39",
    "addr:postcode":"l40 0sa",
    "addr:street":"Liverpool Road North",
    "iso:country":"GB",
    "sg:address":"39 Liverpool Road North, Burscough",
    "sg:city":"Ormskirk",
    "sg:classifiers":[
        {
            "category":"Military Area",
            "subcategory":"Air Force Base",
            "type":"Public Place"
        }
    ],
    "sg:phone":"+44 1695 572000",
    "sg:postcode":"L40 0SA",
    "sg:province":"Lancashire",
    "sg:tags":[
        "taxi",
        "hire",
        "private"
    ],
    "wof:name":"Premier Private Hire (Burscough) Ltd.",
    "wof:placetype":"venue"
},
  "geometry": {"coordinates":[-2.8423199654,53.6036148071],"type":"Point"}
}