{
  "type": "Feature",
  "properties": {
    "addr:full":"Beech Tree House, 16 The Strand Bromsgrove Worcestershire B61 8AB",
    "addr:housenumber":"16",
    "addr:postcode":"b61 8ab",
    "addr:street":"Beech;The Strand",
    "iso:country":"GB",
    "sg:address":"Beech Tree House, 16 The Strand",
    "sg:city":"Bromsgrove",
    "sg:classifiers":[
        {
            "category":"Shopping",
            "subcategory":"Jewelry",
            "type":"Retail Goods"
        },
        {
            "category":"Shopping",
            "subcategory":"Comic Books",
            "type":"Retail Goods"
        }
    ],
    "sg:phone":"+44 1527 873021",
    "sg:postcode":"B61 8AB",
    "sg:province":"Worcestershire",
    "sg:tags":[
        "jeweller",
        "sale",
        "jewellery"
    ],
    "wof:name":"Cupitt Jewellers",
    "wof:placetype":"venue"
},
  "geometry": {"coordinates":[-2.0573420525,52.33751297],"type":"Point"}
}