{
  "type": "Feature",
  "properties": {
    "iso:country":"GB",
    "sg:address":"14 Tyock Ind Est",
    "sg:city":"Elgin",
    "sg:classifiers":[
        {
            "category":"Autos & Motor Vehicles",
            "subcategory":"Automobile Sales",
            "type":"Retail Goods"
        }
    ],
    "sg:phone":"+44 1343 569100",
    "sg:postcode":"IV30 1XY",
    "sg:province":"Moray",
    "sg:tags":[
        "commercial"
    ],
    "wof:name":"Tyock Trade Car Sales Centre",
    "wof:placetype":"venue"
},
  "geometry": {"coordinates":[-3.317699,57.647419],"type":"Point"}
}