{
  "type": "Feature",
  "properties": {
    "addr:full":"25 Downsview Avenue, Woodingdean Brighton East Sussex BN2 6BP",
    "addr:housenumber":"25",
    "addr:postcode":"bn2 6bp",
    "addr:street":"Downsview Avenue",
    "iso:country":"GB",
    "sg:address":"25 Downsview Avenue, Woodingdean",
    "sg:city":"Brighton",
    "sg:classifiers":[
        {
            "category":"Building & Trades",
            "subcategory":"Plumbing",
            "type":"Services"
        }
    ],
    "sg:phone":"+44 1273 602171",
    "sg:postcode":"BN2 6BP",
    "sg:province":"East Sussex",
    "sg:tags":[
        "repair",
        "heating",
        "servicing",
        "boiler"
    ],
    "wof:name":"Steve Bennett Heating & Plumbing",
    "wof:placetype":"venue"
},
  "geometry": {"coordinates":[-0.0824540034,50.8374977112],"type":"Point"}
}