{
  "type": "Feature",
  "properties": {
    "addr:full":"Western Park Renfrew Renfrewshire PA4 8NG",
    "addr:postcode":"pa4 8ng",
    "addr:street":"Park",
    "iso:country":"GB",
    "sg:address":"Western Park",
    "sg:city":"Renfrew",
    "sg:classifiers":[
        {
            "category":"Organizations",
            "subcategory":"Membership Organization",
            "type":"Services"
        }
    ],
    "sg:phone":"+44 141 886 3400",
    "sg:postcode":"PA4 8NG",
    "sg:province":"Renfrewshire",
    "sg:tags":[
        "club"
    ],
    "wof:name":"Renfrew Football Club",
    "wof:placetype":"venue"
},
  "geometry": {"coordinates":[-4.3926200867,55.8784408569],"type":"Point"}
}