{
  "type": "Feature",
  "properties": {
    "addr:full":"47 St Quentin Drive Sheffield Derbyshire S17 4PN",
    "addr:housenumber":"47",
    "addr:postcode":"s17 4pn",
    "addr:street":"St Quentin Drive",
    "iso:country":"GB",
    "sg:address":"47 St Quentin Drive",
    "sg:city":"Sheffield",
    "sg:classifiers":[
        {
            "category":"Communications",
            "subcategory":"Film & Video Production",
            "type":"Services"
        },
        {
            "category":"Retail",
            "subcategory":"Portrait Studio",
            "type":"Services"
        }
    ],
    "sg:phone":"+44 114 236 4797",
    "sg:postcode":"S17 4PN",
    "sg:province":"Derbyshire",
    "sg:tags":[
        "photographer",
        "commercial",
        "illustrator",
        "artist"
    ],
    "wof:name":"BRENDON CLARK",
    "wof:placetype":"venue"
},
  "geometry": {"coordinates":[-1.512444973,53.3181915283],"type":"Point"}
}