{
  "type": "Feature",
  "properties": {
    "iso:country":"GB",
    "sg:address":"21 Southwick Square, Southwick",
    "sg:city":"Brighton",
    "sg:classifiers":[
        {
            "category":"Shopping",
            "subcategory":"News",
            "type":"Retail Goods"
        }
    ],
    "sg:phone":"+44 1273 593574",
    "sg:postcode":"BN42 4FP",
    "sg:province":"West Sussex",
    "sg:tags":[
        "newsagent"
    ],
    "wof:name":"Macfarlane's",
    "wof:placetype":"venue"
},
  "geometry": {"coordinates":[-0.2357,50.834068],"type":"Point"}
}