{
  "type": "Feature",
  "properties": {
    "addr:full":"109 Shields Road Newcastle-upon-tyne Tyne and Wear NE6 1DN",
    "addr:housenumber":"109",
    "addr:postcode":"ne6 1dn",
    "addr:street":"Shields Road",
    "iso:country":"GB",
    "sg:address":"109 Shields Road",
    "sg:city":"Newcastle-upon-tyne",
    "sg:classifiers":[
        {
            "category":"Cafe",
            "type":"Food & Drink"
        }
    ],
    "sg:phone":"+44 191 265 4467",
    "sg:postcode":"NE6 1DN",
    "sg:province":"Tyne and Wear",
    "sg:tags":[
        "tea",
        "room"
    ],
    "wof:name":"Rumbletums Cafe",
    "wof:placetype":"venue"
},
  "geometry": {"coordinates":[-1.58168,54.977146],"type":"Point"}
}