{
  "type": "Feature",
  "properties": {
    "iso:country":"GB",
    "sg:address":"Walhall, Bucknell Road",
    "sg:city":"Bicester",
    "sg:classifiers":[
        {
            "category":"Banks & Credit Unions",
            "subcategory":"Bank",
            "type":"Services"
        }
    ],
    "sg:phone":"+44 1869 248419",
    "sg:postcode":"OX26 2DG",
    "sg:province":"Oxfordshire",
    "sg:tags":[
        "stocktaking",
        "inventory"
    ],
    "wof:name":"Stockchek",
    "wof:placetype":"venue"
},
  "geometry": {"coordinates":[-1.1633629799,51.9065971375],"type":"Point"}
}