{
  "type": "Feature",
  "properties": {
    "addr:full":"New Street, Long Sutton Langport Somerset TA10 9JW",
    "addr:postcode":"ta10 9jw",
    "addr:street":"New Street",
    "iso:country":"GB",
    "sg:address":"New Street, Long Sutton",
    "sg:city":"Langport",
    "sg:classifiers":[
        {
            "category":"Farming",
            "subcategory":"Livestock Farm",
            "type":"Manufacturing & Wholesale Goods"
        }
    ],
    "sg:phone":"+44 1458 241056",
    "sg:postcode":"TA10 9JW",
    "sg:province":"Somerset",
    "sg:tags":[
        "others"
    ],
    "wof:name":"RICHARD CHARLES VAUX",
    "wof:placetype":"venue"
},
  "geometry": {"coordinates":[-2.7596929073,51.0242347717],"type":"Point"}
}