{
  "type": "Feature",
  "properties": {
    "addr:full":"217 Ilford Lane Ilford Essex IG1 2RZ",
    "addr:housenumber":"217",
    "addr:postcode":"ig1 2rz",
    "addr:street":"Ilford Lane",
    "iso:country":"GB",
    "sg:address":"217 Ilford Lane",
    "sg:city":"Ilford",
    "sg:classifiers":[
        {
            "category":"Health Services",
            "subcategory":"Dentist",
            "type":"Services"
        }
    ],
    "sg:phone":"+44 20 8514 4114",
    "sg:postcode":"IG1 2RZ",
    "sg:province":"Essex",
    "wof:name":"Y L Shah",
    "wof:placetype":"venue"
},
  "geometry": {"coordinates":[0.0741140023,51.5517272949],"type":"Point"}
}