{
  "type": "Feature",
  "properties": {
    "addr:full":"Ty'r Delyn, Mill Road Llanfairfechan Conwy LL33 0TS",
    "addr:postcode":"ll33 0ts",
    "addr:street":"Delyn Mill Road",
    "iso:country":"GB",
    "sg:address":"Ty'r Delyn, Mill Road",
    "sg:city":"Llanfairfechan",
    "sg:classifiers":[
        {
            "category":"Professional",
            "subcategory":"Accounting & Tax Preparation",
            "type":"Services"
        }
    ],
    "sg:phone":"+44 1248 681313",
    "sg:postcode":"LL33 0TS",
    "sg:province":"Conwy",
    "sg:tags":[
        "accountant"
    ],
    "wof:name":"Stoneycroft Business Services Ltd.",
    "wof:placetype":"venue"
},
  "geometry": {"coordinates":[-3.97337,53.25174],"type":"Point"}
}