{
  "type": "Feature",
  "properties": {
    "addr:full":"1 Winifreds Drive, Donnington Telford Shropshire TF2 8BB",
    "addr:housenumber":"1",
    "addr:postcode":"tf2 8bb",
    "addr:street":"Winifreds Drive",
    "iso:country":"GB",
    "sg:address":"1 Winifreds Drive, Donnington",
    "sg:city":"Telford",
    "sg:classifiers":[
        {
            "category":"Social Services",
            "subcategory":"Retirement Home",
            "type":"Services"
        }
    ],
    "sg:phone":"+44 1952 605758",
    "sg:postcode":"TF2 8BB",
    "sg:province":"Shropshire",
    "sg:tags":[
        "residential",
        "care"
    ],
    "wof:name":"Ivylands",
    "wof:placetype":"venue"
},
  "geometry": {"coordinates":[-2.4409399033,52.7161407471],"type":"Point"}
}