{
  "type": "Feature",
  "properties": {
    "addr:full":"1 Bolton Rd Luton Bedfordshire LU1 3HT",
    "addr:housenumber":"1",
    "addr:postcode":"lu1 3ht",
    "addr:street":"Bolton Rd",
    "iso:country":"GB",
    "sg:address":"1 Bolton Rd",
    "sg:city":"Luton",
    "sg:classifiers":[
        {
            "category":"Shopping",
            "subcategory":"Clothing, Apparel, & Fashions",
            "type":"Retail Goods"
        }
    ],
    "sg:phone":"+44 1582 436400",
    "sg:postcode":"LU1 3HT",
    "sg:province":"Bedfordshire",
    "sg:tags":[
        "cap",
        "hat"
    ],
    "wof:name":"Bermona Ltd",
    "wof:placetype":"venue"
},
  "geometry": {"coordinates":[-0.4072099924,51.8773155212],"type":"Point"}
}