{
  "type": "Feature",
  "properties": {
    "iso:country":"GB",
    "sg:address":"Unit E, Marsh Mills Park",
    "sg:city":"Plymouth",
    "sg:classifiers":[
        {
            "category":"Home & Garden",
            "subcategory":"Home Furnishings",
            "type":"Retail Goods"
        },
        {
            "category":"Home & Garden",
            "subcategory":"Furniture",
            "type":"Retail Goods"
        }
    ],
    "sg:phone":"+44 1752 264100",
    "sg:postcode":"PL6 8LX",
    "sg:province":"Devon",
    "sg:tags":[
        "beds",
        "bedding",
        "blanket"
    ],
    "wof:name":"Furniture Village Ltd.",
    "wof:placetype":"venue"
},
  "geometry": {"coordinates":[-4.089999,50.394039],"type":"Point"}
}