{
  "type": "Feature",
  "properties": {
    "addr:full":"128 Elm Gro Hayling Island Hampshire PO11 9EH",
    "addr:housenumber":"128",
    "addr:postcode":"po11 9eh",
    "addr:street":"Elm Gro",
    "iso:country":"GB",
    "sg:address":"128 Elm Gro",
    "sg:city":"Hayling Island",
    "sg:classifiers":[
        {
            "category":"Food & Beverages",
            "subcategory":"Fruits & Vegetables",
            "type":"Retail Goods"
        }
    ],
    "sg:phone":"+44 23 9246 5425",
    "sg:postcode":"PO11 9EH",
    "sg:province":"Hampshire",
    "sg:tags":[
        "greengrocer"
    ],
    "wof:name":"Hayling Fruiterers",
    "wof:placetype":"venue"
},
  "geometry": {"coordinates":[-0.9767950177,50.791885376],"type":"Point"}
}