{
  "type": "Feature",
  "properties": {
    "addr:full":"Unit 13 Wallingford Road, Off Abbey Lane Leicester Leicestershire LE4 5QJ",
    "addr:housenumber":"unit 13",
    "addr:postcode":"le4 5qj",
    "addr:street":"Wallingford Road Off Abbey Lane",
    "iso:country":"GB",
    "sg:address":"Unit 13 Wallingford Road, Off Abbey Lane",
    "sg:city":"Leicester",
    "sg:classifiers":[
        {
            "category":"Manufacturing",
            "subcategory":"Metals",
            "type":"Manufacturing & Wholesale Goods"
        }
    ],
    "sg:phone":"+44 116 268 1000",
    "sg:postcode":"LE4 5QJ",
    "sg:province":"Leicestershire",
    "sg:tags":[
        "work",
        "sheet"
    ],
    "wof:name":"A D L Sheet Metal",
    "wof:placetype":"venue"
},
  "geometry": {"coordinates":[-1.131544,52.655251],"type":"Point"}
}