{
  "type": "Feature",
  "properties": {
    "addr:full":"21 Old Hall Drive Manchester Greater Manchester M18 7FU",
    "addr:housenumber":"21",
    "addr:postcode":"m18 7fu",
    "addr:street":"Old Hall Drive",
    "iso:country":"GB",
    "sg:address":"21 Old Hall Drive",
    "sg:city":"Manchester",
    "sg:classifiers":[
        {
            "category":"Government",
            "subcategory":"Office",
            "type":"Public Place"
        }
    ],
    "sg:phone":"+44 161 220 7362",
    "sg:postcode":"M18 7FU",
    "sg:province":"Greater Manchester",
    "sg:tags":[
        "project",
        "gov",
        "community"
    ],
    "wof:name":"Gorton Community Forum",
    "wof:placetype":"venue"
},
  "geometry": {"coordinates":[-2.170442,53.457233],"type":"Point"}
}