{
  "type": "Feature",
  "properties": {
    "iso:country":"GB",
    "sg:address":"5 Beechmount Close, Baildon",
    "sg:city":"Shipley",
    "sg:classifiers":[
        {
            "category":"Retail",
            "subcategory":"Driving School",
            "type":"Services"
        }
    ],
    "sg:postcode":"BD17 6JG",
    "sg:province":"West Yorkshire",
    "wof:name":"Leeds-Bradford School of Motoring",
    "wof:placetype":"venue"
},
  "geometry": {"coordinates":[-1.766849,53.848671],"type":"Point"}
}