{
  "type": "Feature",
  "properties": {
    "addr:full":"16 Kenfig Road, Whitchurch Cardiff Cardiff CF14 1HX",
    "addr:housenumber":"16",
    "addr:postcode":"cf14 1hx",
    "addr:street":"Kenfig Road",
    "iso:country":"GB",
    "sg:address":"16 Kenfig Road, Whitchurch",
    "sg:city":"Cardiff",
    "sg:classifiers":[
        {
            "category":"Building & Trades",
            "subcategory":"Landscaping Services",
            "type":"Services"
        }
    ],
    "sg:postcode":"CF14 1HX",
    "sg:province":"Cardiff",
    "sg:tags":[
        "landscape",
        "contractor"
    ],
    "wof:name":"B Priddle",
    "wof:placetype":"venue"
},
  "geometry": {"coordinates":[-3.200828,51.506248],"type":"Point"}
}