{
  "type": "Feature",
  "properties": {
    "iso:country":"GB",
    "sg:address":"27 High Street",
    "sg:city":"Westbury",
    "sg:classifiers":[
        {
            "category":"Fast Food",
            "type":"Food & Drink"
        }
    ],
    "sg:postcode":"BA13 2GG",
    "sg:province":"Wiltshire",
    "sg:tags":[
        "away",
        "take"
    ],
    "wof:name":"Jambo Takeaway",
    "wof:placetype":"venue"
},
  "geometry": {"coordinates":[-2.184955,51.260471],"type":"Point"}
}