{
  "type": "Feature",
  "properties": {
    "addr:full":"St Johns Garage Wallingford Oxfordshire OX10 9AD",
    "addr:postcode":"ox10 9ad",
    "iso:country":"GB",
    "sg:address":"St Johns Garage",
    "sg:city":"Wallingford",
    "sg:classifiers":[
        {
            "category":"Retail",
            "subcategory":"Auto Repair",
            "type":"Services"
        }
    ],
    "sg:phone":"+44 1491 836017",
    "sg:postcode":"OX10 9AD",
    "sg:province":"Oxfordshire",
    "sg:tags":[
        "modification",
        "garage"
    ],
    "wof:name":"Jim Pink (Wallingford) Ltd.",
    "wof:placetype":"venue"
},
  "geometry": {"coordinates":[-1.1328890324,51.5977859497],"type":"Point"}
}