{
  "type": "Feature",
  "properties": {
    "addr:full":"The Resource Centre, 356 Holloway Road London Greater London N7 6PA",
    "addr:housenumber":"356",
    "addr:postcode":"n7 6pa",
    "addr:street":"Holloway Road",
    "iso:country":"GB",
    "sg:address":"The Resource Centre, 356 Holloway Road",
    "sg:city":"London",
    "sg:classifiers":[
        {
            "category":"Organizations",
            "subcategory":"Non-profit Organization",
            "type":"Services"
        }
    ],
    "sg:phone":"+44 20 7700 8171",
    "sg:postcode":"N7 6PA",
    "sg:province":"Greater London",
    "sg:tags":[
        "charitable",
        "organisation",
        "voluntary",
        "charity"
    ],
    "sg:website":"http://www.mhmedia.com",
    "wof:name":"Mental Health Media Ltd",
    "wof:placetype":"venue"
},
  "geometry": {"coordinates":[-0.1167600006,51.5561714172],"type":"Point"}
}