{
  "type": "Feature",
  "properties": {
    "iso:country":"GB",
    "sg:address":"Rye-hill Farm, Kirklinton",
    "sg:city":"Carlisle",
    "sg:classifiers":[
        {
            "category":"Shopping",
            "subcategory":"Pets & Pet Supplies",
            "type":"Retail Goods"
        }
    ],
    "sg:phone":"+44 1228 675356",
    "sg:postcode":"CA6 6AZ",
    "sg:province":"Cumbria",
    "sg:tags":[
        "food",
        "feed",
        "animal"
    ],
    "wof:name":"Eric's Pet Supplies",
    "wof:placetype":"venue"
},
  "geometry": {"coordinates":[-2.8865189552,54.9943199158],"type":"Point"}
}