{
  "type": "Feature",
  "properties": {
    "iso:country":"GB",
    "sg:address":"Unit 2 Cunliffe Ho, Manchester Rd",
    "sg:city":"Barnoldswick",
    "sg:classifiers":[
        {
            "category":"Manufacturing",
            "subcategory":"Wood Products",
            "type":"Manufacturing & Wholesale Goods"
        }
    ],
    "sg:postcode":"BB18 5PR",
    "sg:province":"Lancashire",
    "wof:name":"Quattan,J U,",
    "wof:placetype":"venue"
},
  "geometry": {"coordinates":[-2.186949,53.916],"type":"Point"}
}