{
  "type": "Feature",
  "properties": {
    "addr:full":"14a Margarets Buildings Bath Bath and North East Somerset BA1 2LP",
    "addr:housenumber":"14a",
    "addr:postcode":"ba1 2lp",
    "addr:street":"Margarets Buildings",
    "iso:country":"GB",
    "sg:address":"14a Margarets Buildings",
    "sg:city":"Bath",
    "sg:classifiers":[
        {
            "category":"Shopping",
            "subcategory":"Thrift Store",
            "type":"Retail Goods"
        }
    ],
    "sg:phone":"+44 1225 448793",
    "sg:postcode":"BA1 2LP",
    "sg:province":"Bath and North East Somerset",
    "sg:tags":[
        "shop",
        "charity"
    ],
    "wof:name":"Sue Ryder Foundation",
    "wof:placetype":"venue"
},
  "geometry": {"coordinates":[-2.361166954,51.3850708008],"type":"Point"}
}