{
  "type": "Feature",
  "properties": {
    "addr:full":"Plas Newton Lane Chester Cheshire CH2 1PR",
    "addr:postcode":"ch2 1pr",
    "addr:street":"Plas Newton Lane",
    "iso:country":"GB",
    "sg:address":"Plas Newton Lane",
    "sg:city":"Chester",
    "sg:classifiers":[
        {
            "category":"Arena",
            "subcategory":"Sports Club",
            "type":"Entertainment"
        }
    ],
    "sg:phone":"+44 1244 318167",
    "sg:postcode":"CH2 1PR",
    "sg:province":"Cheshire",
    "wof:name":"Cheshire County Council",
    "wof:placetype":"venue"
},
  "geometry": {"coordinates":[-2.8682639599,53.2122650146],"type":"Point"}
}