{
  "type": "Feature",
  "properties": {
    "iso:country":"GB",
    "sg:address":"7-9 Market Street",
    "sg:city":"Northwich",
    "sg:classifiers":[
        {
            "category":"Shopping",
            "subcategory":"Shoes",
            "type":"Retail Goods"
        }
    ],
    "sg:phone":"+44 1606 42577",
    "sg:postcode":"CW9 5BD",
    "sg:province":"Cheshire",
    "sg:tags":[
        "shop"
    ],
    "wof:name":"Gilroy H Wilson",
    "wof:placetype":"venue"
},
  "geometry": {"coordinates":[-2.514647,53.261124],"type":"Point"}
}