{
  "type": "Feature",
  "properties": {
    "iso:country":"GB",
    "sg:address":"Joseph Nickerson Research Cntr, Rothwell, Market Rasen",
    "sg:city":"Lincoln",
    "sg:classifiers":[
        {
            "category":"Home & Garden",
            "subcategory":"Garden Supply",
            "type":"Retail Goods"
        },
        {
            "category":"Government",
            "subcategory":"Post Office",
            "type":"Public Place"
        }
    ],
    "sg:phone":"+44 1472 371471",
    "sg:postcode":"LN7 6DT",
    "sg:province":"Lincolnshire",
    "sg:tags":[
        "merchant",
        "organisation",
        "seed",
        "soc",
        "research"
    ],
    "wof:name":"Nickerson Seeds Ltd.",
    "wof:placetype":"venue"
},
  "geometry": {"coordinates":[-0.2661080062,53.4805488586],"type":"Point"}
}