{
  "type": "Feature",
  "properties": {
    "iso:country":"GB",
    "sg:address":"4 Hollands Rd",
    "sg:city":"Haverhill",
    "sg:classifiers":[
        {
            "category":"Professional",
            "subcategory":"Computer Services",
            "type":"Services"
        }
    ],
    "sg:phone":"+44 1440 710070",
    "sg:postcode":"CB9 8PP",
    "sg:province":"Essex",
    "sg:tags":[
        "system",
        "software"
    ],
    "wof:name":"Intercomm Services Ltd",
    "wof:placetype":"venue"
},
  "geometry": {"coordinates":[0.446327,52.073608],"type":"Point"}
}