{
  "type": "Feature",
  "properties": {
    "iso:country":"GB",
    "sg:address":"Unit 8, Old Brickworks Workshops, Armadale",
    "sg:city":"Bathgate",
    "sg:classifiers":[
        {
            "category":"Professional",
            "subcategory":"Engineering",
            "type":"Services"
        }
    ],
    "sg:postcode":"EH48 2JU",
    "sg:province":"West Lothian",
    "wof:name":"Campbell Engineering",
    "wof:placetype":"venue"
},
  "geometry": {"coordinates":[-3.6967439651,55.8989295959],"type":"Point"}
}