{
  "type": "Feature",
  "properties": {
    "iso:country":"GB",
    "sg:address":"31 St Giles",
    "sg:city":"Oxford",
    "sg:classifiers":[
        {
            "category":"Deli",
            "type":"Food & Drink"
        }
    ],
    "sg:phone":"+44 1865 558853",
    "sg:postcode":"OX1 3LD",
    "sg:province":"Oxfordshire",
    "sg:tags":[
        "delicatessen"
    ],
    "wof:name":"Taylors",
    "wof:placetype":"venue"
},
  "geometry": {"coordinates":[-1.260922,51.758774],"type":"Point"}
}