{
  "type": "Feature",
  "properties": {
    "addr:full":"45 Bridge Street Llanelli Carmarthenshire SA14 8TW",
    "addr:housenumber":"45",
    "addr:postcode":"sa14 8tw",
    "addr:street":"Bridge Street",
    "iso:country":"GB",
    "sg:address":"45 Bridge Street",
    "sg:city":"Llanelli",
    "sg:classifiers":[
        {
            "category":"Personal",
            "subcategory":"Beauty Salon",
            "type":"Services"
        }
    ],
    "sg:phone":"+44 1554 821360",
    "sg:postcode":"SA14 8TW",
    "sg:province":"Carmarthenshire",
    "sg:tags":[
        "unisex",
        "hairdresser"
    ],
    "wof:name":"Tudor Style",
    "wof:placetype":"venue"
},
  "geometry": {"coordinates":[-4.084023,51.695484],"type":"Point"}
}