{
  "type": "Feature",
  "properties": {
    "addr:full":"13 Elm St Merthyr Tydfil Caerphilly CF48 4EA",
    "addr:housenumber":"13",
    "addr:postcode":"cf48 4ea",
    "addr:street":"Elm St",
    "iso:country":"GB",
    "sg:address":"13 Elm St",
    "sg:city":"Merthyr Tydfil",
    "sg:classifiers":[
        {
            "category":"Retail",
            "subcategory":"Driving School",
            "type":"Services"
        }
    ],
    "sg:phone":"+44 1443 690171",
    "sg:postcode":"CF48 4EA",
    "sg:province":"Caerphilly",
    "wof:name":"L Passo",
    "wof:placetype":"venue"
},
  "geometry": {"coordinates":[-3.347477,51.71167],"type":"Point"}
}