{
  "type": "Feature",
  "properties": {
    "iso:country":"GB",
    "sg:address":"Lansdowne Ho, 63 Balby Rd",
    "sg:city":"Doncaster",
    "sg:classifiers":[
        {
            "category":"Professional",
            "subcategory":"Lawyer & Legal Services",
            "type":"Services"
        }
    ],
    "sg:phone":"+44 1302 769442",
    "sg:postcode":"DN4 0RE",
    "sg:province":"South Yorkshire",
    "sg:tags":[
        "patent",
        "agent"
    ],
    "wof:name":"Loven & Co",
    "wof:placetype":"venue"
},
  "geometry": {"coordinates":[-1.14508,53.509998],"type":"Point"}
}