{
  "type": "Feature",
  "properties": {
    "addr:full":"2-4 Princes Street Stafford Staffordshire ST16 2BN",
    "addr:housenumber":"2-4",
    "addr:postcode":"st16 2bn",
    "addr:street":"Princes Street",
    "iso:country":"GB",
    "sg:address":"2-4 Princes Street",
    "sg:city":"Stafford",
    "sg:classifiers":[
        {
            "category":"Home & Garden",
            "subcategory":"Furniture",
            "type":"Retail Goods"
        }
    ],
    "sg:phone":"+44 1785 240744",
    "sg:postcode":"ST16 2BN",
    "sg:province":"Staffordshire",
    "wof:name":"Walmsley Furnishing Plc",
    "wof:placetype":"venue"
},
  "geometry": {"coordinates":[-2.1193239689,52.8082695007],"type":"Point"}
}