{
  "type": "Feature",
  "properties": {
    "addr:full":"38 Cranmer Drive, Nursling Southampton Hampshire SO16 0TD",
    "addr:housenumber":"38",
    "addr:postcode":"so16 0td",
    "addr:street":"Cranmer Drive",
    "iso:country":"GB",
    "sg:address":"38 Cranmer Drive, Nursling",
    "sg:city":"Southampton",
    "sg:classifiers":[
        {
            "category":"Communications",
            "type":"Services"
        }
    ],
    "sg:postcode":"SO16 0TD",
    "sg:province":"Hampshire",
    "sg:tags":[
        "data",
        "network"
    ],
    "wof:name":"Sovereign Data Ltd.",
    "wof:placetype":"venue"
},
  "geometry": {"coordinates":[-1.469531,50.944523],"type":"Point"}
}