{
  "type": "Feature",
  "properties": {
    "addr:full":"3 Victory Close, Three Legged Cross Wimborne Dorset BH21 6SX",
    "addr:housenumber":"3",
    "addr:postcode":"bh21 6sx",
    "addr:street":"Victory Close Three Legged Cross",
    "iso:country":"GB",
    "sg:address":"3 Victory Close, Three Legged Cross",
    "sg:city":"Wimborne",
    "sg:classifiers":[
        {
            "category":"Autos & Motor Vehicles",
            "subcategory":"Motorcycle Sales",
            "type":"Retail Goods"
        }
    ],
    "sg:postcode":"BH21 6SX",
    "sg:province":"Dorset",
    "wof:name":"Steve Bateman",
    "wof:placetype":"venue"
},
  "geometry": {"coordinates":[-1.8635469675,50.8434295654],"type":"Point"}
}