{
  "type": "Feature",
  "properties": {
    "addr:full":"Woodhorn Road, Hirst Ashington Northumberland NE63 9AS",
    "addr:postcode":"ne63 9as",
    "addr:street":"Woodhorn Road",
    "iso:country":"GB",
    "sg:address":"Woodhorn Road, Hirst",
    "sg:city":"Ashington",
    "sg:classifiers":[
        {
            "category":"Food & Beverages",
            "subcategory":"Supermarket",
            "type":"Retail Goods"
        }
    ],
    "sg:phone":"+44 1670 818778",
    "sg:postcode":"NE63 9AS",
    "sg:province":"Northumberland",
    "wof:name":"North Eastern & Cumbrian Co-Op Food Stores",
    "wof:placetype":"venue"
},
  "geometry": {"coordinates":[-1.554844,55.186363],"type":"Point"}
}