{
  "type": "Feature",
  "properties": {
    "addr:full":"Colonial House, 35 Church Road London Greater London SW13 9HQ",
    "addr:housenumber":"35",
    "addr:postcode":"sw13 9hq",
    "addr:street":"Church Road",
    "iso:country":"GB",
    "sg:address":"Colonial House, 35 Church Road",
    "sg:city":"London",
    "sg:classifiers":[
        {
            "category":"Professional",
            "type":"Services"
        }
    ],
    "sg:phone":"+44 20 8741 5100",
    "sg:postcode":"SW13 9HQ",
    "sg:province":"Greater London",
    "sg:tags":[
        "interior",
        "furnishers",
        "designer"
    ],
    "wof:name":"Bird Design Associates",
    "wof:placetype":"venue"
},
  "geometry": {"coordinates":[-0.24591,51.473995],"type":"Point"}
}