{
  "type": "Feature",
  "properties": {
    "addr:full":"47 Main Street, Bubwith Selby East Riding of Yorkshire YO8 6LX",
    "addr:housenumber":"47",
    "addr:postcode":"yo8 6lx",
    "addr:street":"Main Street",
    "iso:country":"GB",
    "sg:address":"47 Main Street, Bubwith",
    "sg:city":"Selby",
    "sg:classifiers":[
        {
            "category":"Shopping",
            "subcategory":"Department Store",
            "type":"Retail Goods"
        },
        {
            "category":"Government",
            "subcategory":"Post Office",
            "type":"Public Place"
        }
    ],
    "sg:phone":"+44 1757 288509",
    "sg:postcode":"YO8 6LX",
    "sg:province":"East Riding of Yorkshire",
    "wof:name":"B P & P A Windsor",
    "wof:placetype":"venue"
},
  "geometry": {"coordinates":[-0.915785,53.818424],"type":"Point"}
}