{
  "type": "Feature",
  "properties": {
    "iso:country":"GB",
    "sg:address":"1 Vine Street",
    "sg:city":"York",
    "sg:classifiers":[
        {
            "category":"Shopping",
            "subcategory":"Antiques",
            "type":"Retail Goods"
        }
    ],
    "sg:postcode":"YO23 1BB",
    "sg:province":"North Yorkshire",
    "wof:name":"Now & Then",
    "wof:placetype":"venue"
},
  "geometry": {"coordinates":[-1.0848749876,53.9512138367],"type":"Point"}
}