{
  "type": "Feature",
  "properties": {
    "iso:country":"GB",
    "sg:address":"44 Eccleshall Road",
    "sg:city":"Stone",
    "sg:classifiers":[
        {
            "category":"Food & Beverages",
            "subcategory":"Meat & Fish",
            "type":"Retail Goods"
        }
    ],
    "sg:phone":"+44 1785 812809",
    "sg:postcode":"ST15 0HN",
    "sg:province":"Staffordshire",
    "sg:tags":[
        "butcher"
    ],
    "wof:name":"R W Walker",
    "wof:placetype":"venue"
},
  "geometry": {"coordinates":[-2.1509308815,52.895362854],"type":"Point"}
}