{
  "type": "Feature",
  "properties": {
    "addr:full":"North View, Skitham Lane, Pilling Preston Lancashire PR3 6BD",
    "addr:postcode":"pr3 6bd",
    "addr:street":"North;Skitham Lane",
    "iso:country":"GB",
    "sg:address":"North View, Skitham Lane, Pilling",
    "sg:city":"Preston",
    "sg:classifiers":[
        {
            "category":"Transit Center",
            "subcategory":"Passenger",
            "type":"Transportation"
        },
        {
            "category":"Retail",
            "subcategory":"Pet Boarding",
            "type":"Services"
        }
    ],
    "sg:phone":"+44 1995 602141",
    "sg:postcode":"PR3 6BD",
    "sg:province":"Lancashire",
    "sg:tags":[
        "kennel",
        "catteries"
    ],
    "wof:name":"North View Boarding Kennels & Cats Hotel",
    "wof:placetype":"venue"
},
  "geometry": {"coordinates":[-2.9101560116,53.9309768677],"type":"Point"}
}