{
  "type": "Feature",
  "properties": {
    "iso:country":"GB",
    "sg:address":"37 Risborough Lane",
    "sg:city":"Folkestone",
    "sg:classifiers":[
        {
            "category":"Fast Food",
            "type":"Food & Drink"
        }
    ],
    "sg:phone":"+44 1303 273727",
    "sg:postcode":"CT19 4JH",
    "sg:province":"Kent",
    "sg:tags":[
        "away",
        "take"
    ],
    "wof:name":"Diamond Palace",
    "wof:placetype":"venue"
},
  "geometry": {"coordinates":[1.1414,51.087021],"type":"Point"}
}