{
  "type": "Feature",
  "properties": {
    "iso:country":"GB",
    "sg:address":"9 Market Place",
    "sg:city":"Alford",
    "sg:classifiers":[
        {
            "category":"Professional",
            "subcategory":"Lawyer & Legal Services",
            "type":"Services"
        }
    ],
    "sg:phone":"+44 1507 463431",
    "sg:postcode":"LN13 9EB",
    "sg:province":"Lincolnshire",
    "sg:tags":[
        "solicitor"
    ],
    "wof:name":"Walkers Owen & Craig",
    "wof:placetype":"venue"
},
  "geometry": {"coordinates":[0.179883,53.261063],"type":"Point"}
}