{
  "type": "Feature",
  "properties": {
    "iso:country":"GB",
    "sg:address":"Unit 2, Textilose Rd, Trafford Park",
    "sg:city":"Manchester",
    "sg:classifiers":[
        {
            "category":"Manufacturing",
            "subcategory":"Building Materials",
            "type":"Manufacturing & Wholesale Goods"
        }
    ],
    "sg:phone":"+44 161 872 5134",
    "sg:postcode":"M17 1PY",
    "sg:province":"Cheshire",
    "sg:tags":[
        "insulation"
    ],
    "wof:name":"Warren Bestobell",
    "wof:placetype":"venue"
},
  "geometry": {"coordinates":[-2.321525,53.462994],"type":"Point"}
}