{
  "type": "Feature",
  "properties": {
    "addr:full":"16 Walmer Crescent, Lower Bevendean Brighton East Sussex BN2 4LR",
    "addr:housenumber":"16",
    "addr:postcode":"bn2 4lr",
    "addr:street":"Walmer Crescent Lower Bevendean",
    "iso:country":"GB",
    "sg:address":"16 Walmer Crescent, Lower Bevendean",
    "sg:city":"Brighton",
    "sg:classifiers":[
        {
            "category":"Building & Trades",
            "subcategory":"Construction",
            "type":"Services"
        }
    ],
    "sg:postcode":"BN2 4LR",
    "sg:province":"East Sussex",
    "sg:tags":[
        "builder"
    ],
    "wof:name":"Peter Wenham",
    "wof:placetype":"venue"
},
  "geometry": {"coordinates":[-0.0899989977,50.8401260376],"type":"Point"}
}