{
  "type": "Feature",
  "properties": {
    "addr:full":"1 Thayer Street London Greater London W1U 3JA",
    "addr:housenumber":"1",
    "addr:postcode":"w1u 3ja",
    "addr:street":"Thayer Street",
    "iso:country":"GB",
    "sg:address":"1 Thayer Street",
    "sg:city":"London",
    "sg:classifiers":[
        {
            "category":"Travel",
            "subcategory":"Travel Agent",
            "type":"Entertainment"
        }
    ],
    "sg:postcode":"W1U 3JA",
    "sg:province":"Greater London",
    "wof:name":"Shalimar Travel",
    "wof:placetype":"venue"
},
  "geometry": {"coordinates":[-0.151627,51.518105],"type":"Point"}
}