{
  "type": "Feature",
  "properties": {
    "addr:full":"Boughton Industrial Estate, Boughton Newark Nottinghamshire NG22 9LD",
    "addr:housenumber":"boughton",
    "addr:postcode":"ng22 9ld",
    "addr:street":"Industrial Estate",
    "iso:country":"GB",
    "sg:address":"Boughton Industrial Estate, Boughton",
    "sg:city":"Newark",
    "sg:classifiers":[
        {
            "category":"Manufacturing",
            "subcategory":"Lumber",
            "type":"Manufacturing & Wholesale Goods"
        }
    ],
    "sg:postcode":"NG22 9LD",
    "sg:province":"Nottinghamshire",
    "sg:tags":[
        "importer",
        "merchants",
        "agent",
        "timber"
    ],
    "wof:name":"S & E Timber Supplies",
    "wof:placetype":"venue"
},
  "geometry": {"coordinates":[-0.9933720231,53.2082672119],"type":"Point"}
}