{
  "type": "Feature",
  "properties": {
    "addr:full":"Main Street, Scalloway Shetland Shetland Islands ZE1 0TR",
    "addr:postcode":"ze1 0tr",
    "addr:street":"Main Street",
    "iso:country":"GB",
    "sg:address":"Main Street, Scalloway",
    "sg:city":"Shetland",
    "sg:classifiers":[
        {
            "category":"Personal",
            "subcategory":"Beauty Salon",
            "type":"Services"
        },
        {
            "category":"Personal",
            "subcategory":"Barber",
            "type":"Services"
        }
    ],
    "sg:phone":"+44 1595 880483",
    "sg:postcode":"ZE1 0TR",
    "sg:province":"Shetland Islands",
    "sg:tags":[
        "unisex",
        "hairdresser"
    ],
    "wof:name":"The Shearing Shed",
    "wof:placetype":"venue"
},
  "geometry": {"coordinates":[-1.279884,60.137489],"type":"Point"}
}