{
  "type": "Feature",
  "properties": {
    "addr:full":"7 School St Wolverhampton West Midlands WV1 4LR",
    "addr:housenumber":"7",
    "addr:postcode":"wv1 4lr",
    "addr:street":"School St",
    "iso:country":"GB",
    "sg:address":"7 School St",
    "sg:city":"Wolverhampton",
    "sg:classifiers":[
        {
            "category":"Home & Garden",
            "subcategory":"Hardware",
            "type":"Retail Goods"
        }
    ],
    "sg:phone":"+44 1902 423082",
    "sg:postcode":"WV1 4LR",
    "sg:province":"West Midlands",
    "wof:name":"William Evans",
    "wof:placetype":"venue"
},
  "geometry": {"coordinates":[-2.1321980953,52.5839157104],"type":"Point"}
}