{
  "type": "Feature",
  "properties": {
    "addr:full":"100 Whyteleafe Hill Whyteleafe Surrey CR3 0AE",
    "addr:housenumber":"100",
    "addr:postcode":"cr3 0ae",
    "addr:street":"Whyteleafe Hill",
    "iso:country":"GB",
    "sg:address":"100 Whyteleafe Hill",
    "sg:city":"Whyteleafe",
    "sg:classifiers":[
        {
            "category":"Professional",
            "subcategory":"Detective & Security Services",
            "type":"Services"
        }
    ],
    "sg:phone":"+44 20 8660 0202",
    "sg:postcode":"CR3 0AE",
    "sg:province":"Surrey",
    "sg:tags":[
        "locksmith"
    ],
    "wof:name":"T M Wise Locksmiths",
    "wof:placetype":"venue"
},
  "geometry": {"coordinates":[-0.0865629986,51.3039474487],"type":"Point"}
}