{
  "type": "Feature",
  "properties": {
    "iso:country":"GB",
    "sg:address":"Unit 83 Carlton Industrial Estate, Albion Road, Carlton",
    "sg:city":"Barnsley",
    "sg:classifiers":[
        {
            "category":"Education",
            "subcategory":"Special Training",
            "type":"Public Place"
        }
    ],
    "sg:phone":"+44 1226 728529",
    "sg:postcode":"S71 3HW",
    "sg:province":"South Yorkshire",
    "sg:tags":[
        "product",
        "centre"
    ],
    "wof:name":"Hargreaves Training Services",
    "wof:placetype":"venue"
},
  "geometry": {"coordinates":[-1.4505389929,53.5831604004],"type":"Point"}
}