{
  "type": "Feature",
  "properties": {
    "addr:full":"156 Hale Rd Altrincham Cheshire WA15 8SQ",
    "addr:housenumber":"156",
    "addr:postcode":"wa15 8sq",
    "addr:street":"Hale Rd",
    "iso:country":"GB",
    "sg:address":"156 Hale Rd",
    "sg:city":"Altrincham",
    "sg:classifiers":[
        {
            "category":"Professional",
            "subcategory":"Employment Agencies",
            "type":"Services"
        }
    ],
    "sg:phone":"+44 161 929 6241",
    "sg:postcode":"WA15 8SQ",
    "sg:province":"Cheshire",
    "sg:tags":[
        "consultant"
    ],
    "wof:name":"Computer Applications People",
    "wof:placetype":"venue"
},
  "geometry": {"coordinates":[-2.337849,53.379524],"type":"Point"}
}