{
  "type": "Feature",
  "properties": {
    "addr:full":"49 Mill Street, Gamlingay Sandy Bedfordshire SG19 3JW",
    "addr:housenumber":"49",
    "addr:postcode":"sg19 3jw",
    "addr:street":"Mill Street",
    "iso:country":"GB",
    "sg:address":"49 Mill Street, Gamlingay",
    "sg:city":"Sandy",
    "sg:classifiers":[
        {
            "category":"Retail",
            "subcategory":"Veterinary Services",
            "type":"Services"
        }
    ],
    "sg:phone":"+44 1767 651569",
    "sg:postcode":"SG19 3JW",
    "sg:province":"Bedfordshire",
    "sg:tags":[
        "surgeon"
    ],
    "wof:name":"Adelaide Cottage Veterinary Centre",
    "wof:placetype":"venue"
},
  "geometry": {"coordinates":[-0.192407,52.152763],"type":"Point"}
}