{
  "type": "Feature",
  "properties": {
    "iso:country":"GB",
    "sg:address":"47b Hainton Avenue",
    "sg:city":"Grimsby",
    "sg:classifiers":[
        {
            "category":"Manufacturing",
            "subcategory":"Food",
            "type":"Manufacturing & Wholesale Goods"
        }
    ],
    "sg:phone":"+44 1472 241561",
    "sg:postcode":"DN32 9AS",
    "sg:province":"Lincolnshire",
    "sg:tags":[
        "equipment",
        "processing",
        "supply"
    ],
    "wof:name":"Jackstone Froster",
    "wof:placetype":"venue"
},
  "geometry": {"coordinates":[-0.074963,53.565632],"type":"Point"}
}