{
  "type": "Feature",
  "properties": {
    "iso:country":"GB",
    "sg:address":"22 Bramblefield Lane, Kemsley",
    "sg:city":"Sittingbourne",
    "sg:classifiers":[
        {
            "category":"Manufacturing",
            "subcategory":"Buildings",
            "type":"Manufacturing & Wholesale Goods"
        }
    ],
    "sg:phone":"+44 1795 427500",
    "sg:postcode":"ME10 2SX",
    "sg:province":"Kent",
    "sg:tags":[
        "system",
        "air conditioning"
    ],
    "wof:name":"Environmental Air Designs",
    "wof:placetype":"venue"
},
  "geometry": {"coordinates":[0.7321199775,51.3634719849],"type":"Point"}
}