{
  "type": "Feature",
  "properties": {
    "addr:full":"Lode Lane Solihull West Midlands B92 8NU",
    "addr:postcode":"b92 8nu",
    "addr:street":"Lode Lane",
    "iso:country":"GB",
    "sg:address":"Lode Lane",
    "sg:city":"Solihull",
    "sg:classifiers":[
        {
            "category":"Bars & Pubs",
            "type":"Food & Drink"
        }
    ],
    "sg:phone":"+44 121 742 0515",
    "sg:postcode":"B92 8NU",
    "sg:province":"West Midlands",
    "sg:tags":[
        "pubs",
        "inn"
    ],
    "wof:name":"Punch Retail Ltd.",
    "wof:placetype":"venue"
},
  "geometry": {"coordinates":[-1.7839939594,52.4395256042],"type":"Point"}
}