{
  "type": "Feature",
  "properties": {
    "iso:country":"GB",
    "sg:address":"22 Lion Street",
    "sg:city":"Rye",
    "sg:classifiers":[
        {
            "category":"Shopping",
            "subcategory":"Gifts & Souvenirs",
            "type":"Retail Goods"
        }
    ],
    "sg:phone":"+44 1797 224006",
    "sg:postcode":"TN31 7LB",
    "sg:province":"East Sussex",
    "sg:tags":[
        "shop"
    ],
    "wof:name":"Present Co.",
    "wof:placetype":"venue"
},
  "geometry": {"coordinates":[0.7341380119,50.950668335],"type":"Point"}
}