{
  "type": "Feature",
  "properties": {
    "addr:full":"Hazelwood Trading Est, Dominion Way Worthing West Sussex BN14 8LU",
    "addr:postcode":"bn14 8lu",
    "addr:street":"Dominion Way",
    "iso:country":"GB",
    "sg:address":"Hazelwood Trading Est, Dominion Way",
    "sg:city":"Worthing",
    "sg:classifiers":[
        {
            "category":"Manufacturing",
            "subcategory":"Wood Products",
            "type":"Manufacturing & Wholesale Goods"
        }
    ],
    "sg:phone":"+44 1903 205633",
    "sg:postcode":"BN14 8LU",
    "sg:province":"West Sussex",
    "sg:tags":[
        "packaging",
        "crate",
        "pallets"
    ],
    "wof:name":"Tee-Kay Packaging (Worthing) Ltd",
    "wof:placetype":"venue"
},
  "geometry": {"coordinates":[-0.3560200036,50.8235282898],"type":"Point"}
}