{
  "type": "Feature",
  "properties": {
    "addr:full":"70 Main Street, Wentworth Rotherham South Yorkshire S62 7TN",
    "addr:housenumber":"70",
    "addr:postcode":"s62 7tn",
    "addr:street":"Main Street",
    "iso:country":"GB",
    "sg:address":"70 Main Street, Wentworth",
    "sg:city":"Rotherham",
    "sg:classifiers":[
        {
            "category":"Shopping",
            "subcategory":"Crafts & Fabrics",
            "type":"Retail Goods"
        }
    ],
    "sg:phone":"+44 1226 742926",
    "sg:postcode":"S62 7TN",
    "sg:province":"South Yorkshire",
    "sg:tags":[
        "shop",
        "needlecraft",
        "wool",
        "retailer"
    ],
    "sg:website":"http://www.winghamwoolwork.co.uk",
    "wof:name":"Wingham Wool Work",
    "wof:placetype":"venue"
},
  "geometry": {"coordinates":[-1.4205540419,53.4794921875],"type":"Point"}
}