{
  "type": "Feature",
  "properties": {
    "iso:country":"GB",
    "sg:address":"43 Queen Street",
    "sg:city":"Chesterfield",
    "sg:classifiers":[
        {
            "category":"Utilities",
            "subcategory":"Telephone",
            "type":"Services"
        }
    ],
    "sg:phone":"+44 1246 557788",
    "sg:postcode":"S40 4SF",
    "sg:province":"Derbyshire",
    "sg:tags":[
        "telecommunication"
    ],
    "wof:name":"Telecom Plus",
    "wof:placetype":"venue"
},
  "geometry": {"coordinates":[-1.432035,53.241055],"type":"Point"}
}