{
  "type": "Feature",
  "properties": {
    "iso:country":"GB",
    "sg:address":"Cockpen",
    "sg:city":"Bonnyrigg",
    "sg:classifiers":[
        {
            "category":"Home & Garden",
            "subcategory":"Hardware",
            "type":"Retail Goods"
        }
    ],
    "sg:postcode":"EH19 3JA",
    "sg:province":"Midlothian",
    "sg:tags":[
        "device",
        "fixing",
        "fastener"
    ],
    "wof:name":"East Coast Engineering (Scotland) Ltd.",
    "wof:placetype":"venue"
},
  "geometry": {"coordinates":[-3.10407,55.874035],"type":"Point"}
}