{
  "type": "Feature",
  "properties": {
    "addr:full":"55 Cleveland Terrace Darlington Durham DL3 8HN",
    "addr:housenumber":"55",
    "addr:postcode":"dl3 8hn",
    "addr:street":"Cleveland Terrace",
    "iso:country":"GB",
    "sg:address":"55 Cleveland Terrace",
    "sg:city":"Darlington",
    "sg:classifiers":[
        {
            "category":"Sports & Exercise",
            "subcategory":"Gym",
            "type":"Entertainment"
        }
    ],
    "sg:postcode":"DL3 8HN",
    "sg:province":"Durham",
    "sg:tags":[
        "fitness",
        "health",
        "centre"
    ],
    "wof:name":"Bannatyne Fitness Ltd.",
    "wof:placetype":"venue"
},
  "geometry": {"coordinates":[-1.5680199862,54.5218658447],"type":"Point"}
}