{
  "type": "Feature",
  "properties": {
    "addr:full":"Sain Lenords House, North Street Horsham West Sussex RH12 1RJ",
    "addr:postcode":"rh12 1rj",
    "addr:street":"North Street",
    "iso:country":"GB",
    "sg:address":"Sain Lenords House, North Street",
    "sg:city":"Horsham",
    "sg:classifiers":[
        {
            "category":"Real Estate",
            "subcategory":"Real Estate Agent",
            "type":"Services"
        }
    ],
    "sg:phone":"+44 1403 272727",
    "sg:postcode":"RH12 1RJ",
    "sg:province":"West Sussex",
    "wof:name":"Arun Estate Agencies Ltd.",
    "wof:placetype":"venue"
},
  "geometry": {"coordinates":[-0.3214749992,51.0650749207],"type":"Point"}
}