{
  "type": "Feature",
  "properties": {
    "addr:full":"377 High Street West Bromwich West Midlands B70 9QW",
    "addr:housenumber":"377",
    "addr:postcode":"b70 9qw",
    "addr:street":"High Street",
    "iso:country":"GB",
    "sg:address":"377 High Street",
    "sg:city":"West Bromwich",
    "sg:classifiers":[
        {
            "category":"Organizations",
            "subcategory":"Membership Organization",
            "type":"Services"
        }
    ],
    "sg:phone":"+44 121 525 4744",
    "sg:postcode":"B70 9QW",
    "sg:province":"West Midlands",
    "sg:tags":[
        "club"
    ],
    "wof:name":"Clockfair Ltd.",
    "wof:placetype":"venue"
},
  "geometry": {"coordinates":[-2.0018880367,52.5232963562],"type":"Point"}
}