{
  "type": "Feature",
  "properties": {
    "iso:country":"GB",
    "sg:address":"73 Queens Road",
    "sg:city":"Nuneaton",
    "sg:classifiers":[
        {
            "category":"Professional",
            "subcategory":"Engineering",
            "type":"Services"
        }
    ],
    "sg:phone":"+44 24 7635 6222",
    "sg:postcode":"CV11 5LA",
    "sg:province":"Leicestershire",
    "sg:tags":[
        "gas",
        "engineer"
    ],
    "wof:name":"The Gas Show Rooms (Nuneaton)",
    "wof:placetype":"venue"
},
  "geometry": {"coordinates":[-1.473393,52.522533],"type":"Point"}
}