{
  "type": "Feature",
  "properties": {
    "iso:country":"GB",
    "sg:address":"Suite 4 The Old Bakery, Pontesbury",
    "sg:city":"Shrewsbury",
    "sg:classifiers":[
        {
            "category":"Building & Trades",
            "subcategory":"Landscaping Services",
            "type":"Services"
        }
    ],
    "sg:postcode":"SY5 0RR",
    "sg:province":"Shropshire",
    "sg:tags":[
        "designer",
        "architect",
        "landscape"
    ],
    "wof:name":"John Challoner Associates",
    "wof:placetype":"venue"
},
  "geometry": {"coordinates":[-2.892414093,52.6500511169],"type":"Point"}
}