{
  "type": "Feature",
  "properties": {
    "addr:full":"250 Kingshill Avenue Hayes Greater London UB4 8BZ",
    "addr:housenumber":"250",
    "addr:postcode":"ub4 8bz",
    "addr:street":"Kingshill Avenue",
    "iso:country":"GB",
    "sg:address":"250 Kingshill Avenue",
    "sg:city":"Hayes",
    "sg:classifiers":[
        {
            "category":"Retail",
            "subcategory":"Laundry & Dry Cleaning",
            "type":"Services"
        }
    ],
    "sg:postcode":"UB4 8BZ",
    "sg:province":"Greater London",
    "sg:tags":[
        "alteration"
    ],
    "wof:name":"Star Dry Cleaners",
    "wof:placetype":"venue"
},
  "geometry": {"coordinates":[-0.4200690091,51.5321617126],"type":"Point"}
}