{
  "type": "Feature",
  "properties": {
    "iso:country":"GB",
    "sg:address":"73a Blenheim St, Easton",
    "sg:city":"Bristol",
    "sg:classifiers":[
        {
            "category":"Retail",
            "subcategory":"Auto Repair",
            "type":"Services"
        }
    ],
    "sg:postcode":"BS5 0NS",
    "sg:province":"City of Bristol",
    "sg:tags":[
        "modification",
        "garage"
    ],
    "wof:name":"Blenheim Garage",
    "wof:placetype":"venue"
},
  "geometry": {"coordinates":[-2.6910049915,51.4783248901],"type":"Point"}
}