{
  "type": "Feature",
  "properties": {
    "iso:country":"GB",
    "sg:address":"313 Holloway Road",
    "sg:city":"London",
    "sg:classifiers":[
        {
            "category":"Arts & Performance",
            "subcategory":"Theater",
            "type":"Entertainment"
        }
    ],
    "sg:phone":"+44 20 7609 1313",
    "sg:postcode":"N7 9SU",
    "sg:province":"Greater London",
    "sg:tags":[
        "rehearsal",
        "studio",
        "facility"
    ],
    "wof:name":"BACKSTREET REHEARSAL STUDIOS",
    "wof:placetype":"venue"
},
  "geometry": {"coordinates":[-0.1150370017,51.554901123],"type":"Point"}
}