{
  "type": "Feature",
  "properties": {
    "addr:full":"49 Neal Street London Greater London WC2H 0PJ",
    "addr:housenumber":"49",
    "addr:postcode":"wc2h 0pj",
    "addr:street":"Neal Street",
    "iso:country":"GB",
    "sg:address":"49 Neal Street",
    "sg:city":"London",
    "sg:classifiers":[
        {
            "category":"Professional",
            "subcategory":"Art Services",
            "type":"Services"
        }
    ],
    "sg:postcode":"WC2H 0PJ",
    "sg:province":"Greater London",
    "sg:tags":[
        "consultant",
        "design"
    ],
    "wof:name":"Jeffrey J Dartnall",
    "wof:placetype":"venue"
},
  "geometry": {"coordinates":[-0.12626,51.514591],"type":"Point"}
}