{
  "type": "Feature",
  "properties": {
    "addr:full":"Kinneil Rd Bo'ness Falkirk EH51 0AY",
    "addr:postcode":"eh51 0ay",
    "addr:street":"Kinneil Rd",
    "iso:country":"GB",
    "sg:address":"Kinneil Rd",
    "sg:city":"Bo'ness",
    "sg:classifiers":[
        {
            "category":"Retail",
            "subcategory":"Auto Repair",
            "type":"Services"
        }
    ],
    "sg:phone":"+44 1506 826227",
    "sg:postcode":"EH51 0AY",
    "sg:province":"Falkirk",
    "sg:tags":[
        "modification",
        "garage"
    ],
    "wof:name":"Kinneil Autocentre",
    "wof:placetype":"venue"
},
  "geometry": {"coordinates":[-3.6240999699,56.0132904053],"type":"Point"}
}