{
  "type": "Feature",
  "properties": {
    "addr:full":"116 Balls Pond Road London Greater London N1 4AE",
    "addr:housenumber":"116",
    "addr:postcode":"n1 4ae",
    "addr:street":"Balls Pond Road",
    "iso:country":"GB",
    "sg:address":"116 Balls Pond Road",
    "sg:city":"London",
    "sg:classifiers":[
        {
            "category":"Communications",
            "type":"Services"
        }
    ],
    "sg:postcode":"N1 4AE",
    "sg:province":"Greater London",
    "sg:tags":[
        "tv",
        "video",
        "radio"
    ],
    "wof:name":"Insat International",
    "wof:placetype":"venue"
},
  "geometry": {"coordinates":[-0.083129,51.546787],"type":"Point"}
}