{
  "type": "Feature",
  "properties": {
    "addr:full":"15-17 Winding Road Halifax West Yorkshire HX1 1UZ",
    "addr:housenumber":"15-17",
    "addr:postcode":"hx1 1uz",
    "addr:street":"Winding Road",
    "iso:country":"GB",
    "sg:address":"15-17 Winding Road",
    "sg:city":"Halifax",
    "sg:classifiers":[
        {
            "category":"Restaurant",
            "type":"Food & Drink"
        }
    ],
    "sg:phone":"+44 1422 353434",
    "sg:postcode":"HX1 1UZ",
    "sg:province":"West Yorkshire",
    "wof:name":"Inn Cognito",
    "wof:placetype":"venue"
},
  "geometry": {"coordinates":[-1.8581540585,53.7255477905],"type":"Point"}
}