{
  "type": "Feature",
  "properties": {
    "addr:full":"27 Kingston Avenue, Stony Stratford Milton Keynes Buckinghamshire MK11 1DS",
    "addr:housenumber":"27",
    "addr:postcode":"mk11 1ds",
    "addr:street":"Kingston Avenue",
    "iso:country":"GB",
    "sg:address":"27 Kingston Avenue, Stony Stratford",
    "sg:city":"Milton Keynes",
    "sg:classifiers":[
        {
            "category":"Building & Trades",
            "subcategory":"Construction",
            "type":"Services"
        }
    ],
    "sg:phone":"+44 1908 563188",
    "sg:postcode":"MK11 1DS",
    "sg:province":"Buckinghamshire",
    "sg:tags":[
        "builder"
    ],
    "wof:name":"A B Construction",
    "wof:placetype":"venue"
},
  "geometry": {"coordinates":[-0.8466249704,52.0558891296],"type":"Point"}
}