{
  "type": "Feature",
  "properties": {
    "iso:country":"GB",
    "sg:address":"1 Redcliffe Gardens",
    "sg:city":"Ilford",
    "sg:classifiers":[
        {
            "category":"Shopping",
            "subcategory":"Party Supplies",
            "type":"Retail Goods"
        }
    ],
    "sg:phone":"+44 20 8554 1006",
    "sg:postcode":"IG1 3HQ",
    "sg:province":"Essex",
    "sg:tags":[
        "inflatables",
        "bouncy",
        "castle"
    ],
    "wof:name":"ABC Bouncy Castles",
    "wof:placetype":"venue"
},
  "geometry": {"coordinates":[0.065043,51.568096],"type":"Point"}
}