{
  "type": "Feature",
  "properties": {
    "addr:full":"169-171 High Street Tonbridge Kent TN9 1BX",
    "addr:housenumber":"169-171",
    "addr:postcode":"tn9 1bx",
    "addr:street":"High Street",
    "iso:country":"GB",
    "sg:address":"169-171 High Street",
    "sg:city":"Tonbridge",
    "sg:classifiers":[
        {
            "category":"Real Estate",
            "subcategory":"Real Estate Agent",
            "type":"Services"
        }
    ],
    "sg:phone":"+44 1732 351323",
    "sg:postcode":"TN9 1BX",
    "sg:province":"Kent",
    "wof:name":"Evans & Matta",
    "wof:placetype":"venue"
},
  "geometry": {"coordinates":[0.275849998,51.1982002258],"type":"Point"}
}