{
  "type": "Feature",
  "properties": {
    "addr:full":"341 Ladypool Road Birmingham West Midlands B12 8LA",
    "addr:housenumber":"341",
    "addr:postcode":"b12 8la",
    "addr:street":"Ladypool Road",
    "iso:country":"GB",
    "sg:address":"341 Ladypool Road",
    "sg:city":"Birmingham",
    "sg:classifiers":[
        {
            "category":"Retail",
            "subcategory":"Laundry & Dry Cleaning",
            "type":"Services"
        }
    ],
    "sg:phone":"+44 121 442 4667",
    "sg:postcode":"B12 8LA",
    "sg:province":"West Midlands",
    "sg:tags":[
        "alteration"
    ],
    "wof:name":"Metro Dry Cleaners",
    "wof:placetype":"venue"
},
  "geometry": {"coordinates":[-1.878285,52.452915],"type":"Point"}
}