{
  "type": "Feature",
  "properties": {
    "iso:country":"GB",
    "sg:address":"28 High Street",
    "sg:city":"Newport",
    "sg:classifiers":[
        {
            "category":"Home & Garden",
            "subcategory":"Household Appliances",
            "type":"Retail Goods"
        }
    ],
    "sg:phone":"+44 1983 523074",
    "sg:postcode":"PO30 1SS",
    "sg:province":"Isle of Wight",
    "sg:tags":[
        "electrical",
        "domestic"
    ],
    "wof:name":"Powerhouse Newport",
    "wof:placetype":"venue"
},
  "geometry": {"coordinates":[-1.292804,50.700184],"type":"Point"}
}