{
  "type": "Feature",
  "properties": {
    "addr:full":"Suite 4, Enterprise House, Kingsway North Gateshead Tyne and Wear NE11 0SR",
    "addr:housenumber":"suite 4 enterprise house",
    "addr:postcode":"ne11 0sr",
    "addr:street":"Kingsway North",
    "iso:country":"GB",
    "sg:address":"Suite 4, Enterprise House, Kingsway North",
    "sg:city":"Gateshead",
    "sg:classifiers":[
        {
            "category":"Social Services",
            "type":"Services"
        },
        {
            "category":"Building & Trades",
            "subcategory":"Cleaning & Sanitation",
            "type":"Services"
        }
    ],
    "sg:phone":"+44 191 482 0453",
    "sg:postcode":"NE11 0SR",
    "sg:province":"Tyne and Wear",
    "sg:tags":[
        "repair",
        "lift",
        "-",
        "disability"
    ],
    "wof:name":"OTIS INVESTMENTS LTD",
    "wof:placetype":"venue"
},
  "geometry": {"coordinates":[-1.6187399626,54.9330215454],"type":"Point"}
}