{
  "type": "Feature",
  "properties": {
    "addr:full":"Cliffantsy Farm, Clevancy Calne Wiltshire SN11 8ST",
    "addr:postcode":"sn11 8st",
    "addr:street":"Clevancy",
    "iso:country":"GB",
    "sg:address":"Cliffantsy Farm, Clevancy",
    "sg:city":"Calne",
    "sg:classifiers":[
        {
            "category":"Farming",
            "subcategory":"Farm",
            "type":"Manufacturing & Wholesale Goods"
        }
    ],
    "sg:postcode":"SN11 8ST",
    "sg:province":"Wiltshire",
    "sg:tags":[
        "mixed",
        "crop"
    ],
    "wof:name":"R & C Keevil",
    "wof:placetype":"venue"
},
  "geometry": {"coordinates":[-2.0049118996,51.4376716614],"type":"Point"}
}