{
  "type": "Feature",
  "properties": {
    "addr:full":"23 Rowner Road Gosport Hampshire PO13 9UE",
    "addr:housenumber":"23",
    "addr:postcode":"po13 9ue",
    "addr:street":"Rowner Road",
    "iso:country":"GB",
    "sg:address":"23 Rowner Road",
    "sg:city":"Gosport",
    "sg:classifiers":[
        {
            "category":"Fast Food",
            "type":"Food & Drink"
        }
    ],
    "sg:phone":"+44 23 9251 1560",
    "sg:postcode":"PO13 9UE",
    "sg:province":"Hampshire",
    "sg:tags":[
        "away",
        "take"
    ],
    "wof:name":"Masala Balti House",
    "wof:placetype":"venue"
},
  "geometry": {"coordinates":[-1.1720399857,50.8129386902],"type":"Point"}
}