{
  "type": "Feature",
  "properties": {
    "addr:full":"22a Church Street London Greater London N9 9DU",
    "addr:housenumber":"22a",
    "addr:postcode":"n9 9du",
    "addr:street":"Church Street",
    "iso:country":"GB",
    "sg:address":"22a Church Street",
    "sg:city":"London",
    "sg:classifiers":[
        {
            "category":"Real Estate",
            "subcategory":"Architect",
            "type":"Services"
        }
    ],
    "sg:phone":"+44 20 8807 0749",
    "sg:postcode":"N9 9DU",
    "sg:province":"Greater London",
    "wof:name":"Boreland Electronic Engineers Ltd.",
    "wof:placetype":"venue"
},
  "geometry": {"coordinates":[-0.0623809993,51.6251678467],"type":"Point"}
}