{
  "type": "Feature",
  "properties": {
    "iso:country":"GB",
    "sg:address":"Hinkley Point B Power Station, Hinkley Point",
    "sg:city":"Bridgwater",
    "sg:classifiers":[
        {
            "category":"Professional",
            "subcategory":"Engineering",
            "type":"Services"
        }
    ],
    "sg:phone":"+44 1278 652133",
    "sg:postcode":"TA5 1TD",
    "sg:province":"Somerset",
    "wof:name":"N N C Ltd.",
    "wof:placetype":"venue"
},
  "geometry": {"coordinates":[-3.14085,51.179699],"type":"Point"}
}