{
  "type": "Feature",
  "properties": {
    "iso:country":"GB",
    "sg:address":"Grove Terrace",
    "sg:city":"Taunton",
    "sg:classifiers":[
        {
            "category":"Education",
            "subcategory":"School",
            "type":"Public Place"
        },
        {
            "category":"Government",
            "subcategory":"Office",
            "type":"Public Place"
        }
    ],
    "sg:phone":"+44 1823 275906",
    "sg:postcode":"TA2 6HA",
    "sg:province":"Somerset",
    "sg:tags":[
        "local",
        "authority"
    ],
    "wof:name":"St. Andrew's C of E Primary School",
    "wof:placetype":"venue"
},
  "geometry": {"coordinates":[-3.104694,51.02475],"type":"Point"}
}