{
  "type": "Feature",
  "properties": {
    "addr:full":"Iver Ho, Middlegreen Est, Middlegreen Rd, Langley Slough Berkshire SL3 6DF",
    "addr:postcode":"sl3 6df",
    "addr:street":"Iver;Middlegreen Rd",
    "iso:country":"GB",
    "sg:address":"Iver Ho, Middlegreen Est, Middlegreen Rd, Langley",
    "sg:city":"Slough",
    "sg:classifiers":[
        {
            "category":"Professional",
            "subcategory":"Engineering",
            "type":"Services"
        }
    ],
    "sg:postcode":"SL3 6DF",
    "sg:province":"Berkshire",
    "wof:name":"Jaga Engineering Ltd",
    "wof:placetype":"venue"
},
  "geometry": {"coordinates":[-0.5572959781,51.5139427185],"type":"Point"}
}