{
  "type": "Feature",
  "properties": {
    "iso:country":"GB",
    "sg:address":"3-5 Canal Yard",
    "sg:city":"Welshpool",
    "sg:classifiers":[
        {
            "category":"Professional",
            "subcategory":"Printing & Photocopies",
            "type":"Services"
        }
    ],
    "sg:phone":"+44 1938 552260",
    "sg:postcode":"SY21 7AQ",
    "sg:province":"Shropshire",
    "sg:tags":[
        "printer"
    ],
    "wof:name":"Welshpool Printing Co Ltd",
    "wof:placetype":"venue"
},
  "geometry": {"coordinates":[-3.143909,52.661831],"type":"Point"}
}