{
  "type": "Feature",
  "properties": {
    "iso:country":"GB",
    "sg:address":"31 Clovelly Rd, Glenfield",
    "sg:city":"Leicester",
    "sg:classifiers":[
        {
            "category":"Building & Trades",
            "subcategory":"Plumbing",
            "type":"Services"
        }
    ],
    "sg:phone":"+44 116 287 2230",
    "sg:postcode":"LE3 8AD",
    "sg:province":"Leicestershire",
    "sg:tags":[
        "heating"
    ],
    "wof:name":"Rocar Installations",
    "wof:placetype":"venue"
},
  "geometry": {"coordinates":[-1.188583,52.648418],"type":"Point"}
}