{
  "type": "Feature",
  "properties": {
    "addr:full":"3 Dean Trench Street London Greater London SW1P 3HB",
    "addr:housenumber":"3",
    "addr:postcode":"sw1p 3hb",
    "addr:street":"Dean Trench Street",
    "iso:country":"GB",
    "sg:address":"3 Dean Trench Street",
    "sg:city":"London",
    "sg:classifiers":[
        {
            "category":"Utilities",
            "type":"Services"
        }
    ],
    "sg:phone":"+44 870 241 5091",
    "sg:postcode":"SW1P 3HB",
    "sg:province":"Greater London",
    "sg:tags":[
        "internet"
    ],
    "wof:name":"Hairnet Uk Ltd.",
    "wof:placetype":"venue"
},
  "geometry": {"coordinates":[-0.1279419959,51.4960403442],"type":"Point"}
}