{
  "type": "Feature",
  "properties": {
    "addr:full":"Carne Hill, St Dennis St Austell Cornwall PL26 8AY",
    "addr:postcode":"pl26 8ay",
    "addr:street":"Carne Hill St",
    "iso:country":"GB",
    "sg:address":"Carne Hill, St Dennis",
    "sg:city":"St Austell",
    "sg:classifiers":[
        {
            "category":"Education",
            "subcategory":"School",
            "type":"Public Place"
        }
    ],
    "sg:phone":"+44 1726 822546",
    "sg:postcode":"PL26 8AY",
    "sg:province":"Cornwall",
    "sg:tags":[
        "local",
        "authority"
    ],
    "wof:name":"St Dennis County Primary School",
    "wof:placetype":"venue"
},
  "geometry": {"coordinates":[-4.8828501701,50.386089325],"type":"Point"}
}