{
  "type": "Feature",
  "properties": {
    "iso:country":"GB",
    "sg:address":"Chestnut Rd",
    "sg:city":"Walsall",
    "sg:classifiers":[
        {
            "category":"Place Of Worship",
            "type":"Public Place"
        }
    ],
    "sg:phone":"+44 1922 407768",
    "sg:postcode":"WS3 1AP",
    "sg:province":"Staffordshire",
    "wof:name":"St Aidans Church",
    "wof:placetype":"venue"
},
  "geometry": {"coordinates":[-1.9846090078,52.6084213257],"type":"Point"}
}