{
  "type": "Feature",
  "properties": {
    "iso:country":"GB",
    "sg:address":"251 St John Road",
    "sg:city":"Edinburgh",
    "sg:classifiers":[
        {
            "category":"Shopping",
            "subcategory":"Florist",
            "type":"Retail Goods"
        }
    ],
    "sg:postcode":"EH12 7XD",
    "sg:province":"City of Edinburgh",
    "wof:name":"Steven Divine",
    "wof:placetype":"venue"
},
  "geometry": {"coordinates":[-3.28864,55.943089],"type":"Point"}
}