{
  "type": "Feature",
  "properties": {
    "addr:full":"14-16 Brunel Plaza Swindon Wiltshire SN1 1LF",
    "addr:housenumber":"14-16;plaza",
    "addr:postcode":"sn1 1lf",
    "addr:street":"Brunel",
    "iso:country":"GB",
    "sg:address":"14-16 Brunel Plaza",
    "sg:city":"Swindon",
    "sg:classifiers":[
        {
            "category":"Food & Beverages",
            "subcategory":"Specialty",
            "type":"Retail Goods"
        }
    ],
    "sg:phone":"+44 1793 520385",
    "sg:postcode":"SN1 1LF",
    "sg:province":"Wiltshire",
    "sg:tags":[
        "product",
        "health"
    ],
    "wof:name":"General Nutrition Centre",
    "wof:placetype":"venue"
},
  "geometry": {"coordinates":[-1.784979,51.563229],"type":"Point"}
}