{
  "type": "Feature",
  "properties": {
    "iso:country":"GB",
    "sg:address":"13 Queen Square",
    "sg:city":"Bath",
    "sg:classifiers":[
        {
            "category":"Professional",
            "subcategory":"Lawyer & Legal Services",
            "type":"Services"
        }
    ],
    "sg:phone":"+44 1225 337599",
    "sg:postcode":"BA1 2HJ",
    "sg:province":"Bath and North East Somerset",
    "sg:tags":[
        "solicitor"
    ],
    "wof:name":"S K Solicitors Ltd.",
    "wof:placetype":"venue"
},
  "geometry": {"coordinates":[-2.36377,51.382942],"type":"Point"}
}