{
  "type": "Feature",
  "properties": {
    "addr:full":"86 Abbey Road Torquay Devon TQ2 5NP",
    "addr:housenumber":"86",
    "addr:postcode":"tq2 5np",
    "addr:street":"Abbey Road",
    "iso:country":"GB",
    "sg:address":"86 Abbey Road",
    "sg:city":"Torquay",
    "sg:classifiers":[
        {
            "category":"Health Services",
            "subcategory":"Medical Lab",
            "type":"Services"
        }
    ],
    "sg:postcode":"TQ2 5NP",
    "sg:province":"Devon",
    "sg:tags":[
        "dental"
    ],
    "wof:name":"Paul S King",
    "wof:placetype":"venue"
},
  "geometry": {"coordinates":[-3.533804,50.466888],"type":"Point"}
}