{
  "type": "Feature",
  "properties": {
    "addr:full":"2 Church Street Barnoldswick Lancashire BB18 5UT",
    "addr:housenumber":"2",
    "addr:postcode":"bb18 5ut",
    "addr:street":"Church Street",
    "iso:country":"GB",
    "sg:address":"2 Church Street",
    "sg:city":"Barnoldswick",
    "sg:classifiers":[
        {
            "category":"Fast Food",
            "type":"Food & Drink"
        }
    ],
    "sg:phone":"+44 1282 850551",
    "sg:postcode":"BB18 5UT",
    "sg:province":"Lancashire",
    "sg:tags":[
        "away",
        "meal",
        "outlet",
        "take"
    ],
    "wof:name":"Peking House",
    "wof:placetype":"venue"
},
  "geometry": {"coordinates":[-2.188724041,53.9160766602],"type":"Point"}
}