{
  "type": "Feature",
  "properties": {
    "addr:full":"Newport Rd Cardiff Cardiff CF2 1SZ",
    "addr:postcode":"cf2 1sz",
    "addr:street":"Newport Rd",
    "iso:country":"GB",
    "sg:address":"Newport Rd",
    "sg:city":"Cardiff",
    "sg:classifiers":[
        {
            "category":"Professional",
            "subcategory":"Lawyer & Legal Services",
            "type":"Services"
        }
    ],
    "sg:phone":"+44 29 2047 2244",
    "sg:postcode":"CF2 1SZ",
    "sg:province":"Cardiff",
    "sg:tags":[
        "advice",
        "counselling"
    ],
    "wof:name":"Aids Counselling & Testing",
    "wof:placetype":"venue"
},
  "geometry": {"coordinates":[-3.1413290501,51.4984550476],"type":"Point"}
}