{
  "type": "Feature",
  "properties": {
    "addr:full":"11 Strutt Street Belper Derbyshire DE56 1UN",
    "addr:housenumber":"11",
    "addr:postcode":"de56 1un",
    "addr:street":"Strutt Street",
    "iso:country":"GB",
    "sg:address":"11 Strutt Street",
    "sg:city":"Belper",
    "sg:classifiers":[
        {
            "category":"Organizations",
            "subcategory":"Community Association",
            "type":"Services"
        },
        {
            "category":"Organizations",
            "subcategory":"Membership Organization",
            "type":"Services"
        }
    ],
    "sg:phone":"+44 1773 822151",
    "sg:postcode":"DE56 1UN",
    "sg:province":"Derbyshire",
    "sg:tags":[
        "club",
        "social"
    ],
    "wof:name":"The Royal British Legion",
    "wof:placetype":"venue"
},
  "geometry": {"coordinates":[-1.4807269573,53.0225753784],"type":"Point"}
}