{
  "type": "Feature",
  "properties": {
    "iso:country":"GB",
    "sg:address":"Oak Lea, Bonis Hall Lane",
    "sg:city":"Macclesfield",
    "sg:classifiers":[
        {
            "category":"Professional",
            "type":"Services"
        }
    ],
    "sg:phone":"+44 1625 829745",
    "sg:postcode":"SK10 4LR",
    "sg:province":"Cheshire",
    "sg:tags":[
        "entertainer"
    ],
    "wof:name":"Entertainment Artist Management",
    "wof:placetype":"venue"
},
  "geometry": {"coordinates":[-2.1594679356,53.3136711121],"type":"Point"}
}