{
  "type": "Feature",
  "properties": {
    "iso:country":"GB",
    "sg:address":"High Road, Roydon",
    "sg:city":"Diss",
    "sg:classifiers":[
        {
            "category":"Autos & Motor Vehicles",
            "subcategory":"Fuel & Gas Station",
            "type":"Retail Goods"
        }
    ],
    "sg:phone":"+44 1379 642055",
    "sg:postcode":"IP22 5RD",
    "sg:province":"Norfolk",
    "sg:tags":[
        "petrol",
        "filling"
    ],
    "wof:name":"Roydon Service Station",
    "wof:placetype":"venue"
},
  "geometry": {"coordinates":[1.0877759457,52.3796539307],"type":"Point"}
}