{
  "type": "Feature",
  "properties": {
    "iso:country":"GB",
    "sg:address":"1 Nelson Road",
    "sg:city":"Harwich",
    "sg:classifiers":[
        {
            "category":"Personal",
            "subcategory":"Beauty Salon",
            "type":"Services"
        }
    ],
    "sg:phone":"+44 1255 240340",
    "sg:postcode":"CO12 3AH",
    "sg:province":"Essex",
    "sg:tags":[
        "unisex",
        "hairdresser"
    ],
    "wof:name":"Crowning Glory",
    "wof:placetype":"venue"
},
  "geometry": {"coordinates":[1.27954,51.938187],"type":"Point"}
}