{
  "type": "Feature",
  "properties": {
    "addr:full":"Nun House Farm Northallerton North Yorkshire DL6 3TB",
    "addr:postcode":"dl6 3tb",
    "iso:country":"GB",
    "sg:address":"Nun House Farm",
    "sg:city":"Northallerton",
    "sg:classifiers":[
        {
            "category":"Farming",
            "subcategory":"Farm",
            "type":"Manufacturing & Wholesale Goods"
        }
    ],
    "sg:phone":"+44 1609 883376",
    "sg:postcode":"DL6 3TB",
    "sg:province":"North Yorkshire",
    "sg:tags":[
        "mixed",
        "crop"
    ],
    "wof:name":"W Raw & Son",
    "wof:placetype":"venue"
},
  "geometry": {"coordinates":[-1.4315240383,54.3383674622],"type":"Point"}
}