{
  "type": "Feature",
  "properties": {
    "addr:full":"15 Wickham Road Beckenham Kent BR3 5JS",
    "addr:housenumber":"15",
    "addr:postcode":"br3 5js",
    "addr:street":"Wickham Road",
    "iso:country":"GB",
    "sg:address":"15 Wickham Road",
    "sg:city":"Beckenham",
    "sg:classifiers":[
        {
            "category":"Professional",
            "type":"Services"
        }
    ],
    "sg:phone":"+44 20 8650 7745",
    "sg:postcode":"BR3 5JS",
    "sg:province":"Kent",
    "sg:tags":[
        "directory",
        "pub"
    ],
    "wof:name":"C B D Research Ltd.",
    "wof:placetype":"venue"
},
  "geometry": {"coordinates":[-0.019582,51.405678],"type":"Point"}
}