{
  "type": "Feature",
  "properties": {
    "addr:full":"Great Knighton Farm, Knighton Alcester Warwickshire B49 5LU",
    "addr:postcode":"b49 5lu",
    "iso:country":"GB",
    "sg:address":"Great Knighton Farm, Knighton",
    "sg:city":"Alcester",
    "sg:classifiers":[
        {
            "category":"Home & Garden",
            "subcategory":"Garden Supply",
            "type":"Retail Goods"
        },
        {
            "category":"Farming",
            "subcategory":"Livestock Farm",
            "type":"Manufacturing & Wholesale Goods"
        }
    ],
    "sg:postcode":"B49 5LU",
    "sg:province":"Warwickshire",
    "sg:tags":[
        "bulb",
        "grower",
        "others"
    ],
    "wof:name":"Robert J Leach",
    "wof:placetype":"venue"
},
  "geometry": {"coordinates":[-1.9453639984,52.210105896],"type":"Point"}
}