{
  "type": "Feature",
  "properties": {
    "iso:country":"GB",
    "sg:address":"42 Dickson Street",
    "sg:city":"Dunfermline",
    "sg:classifiers":[
        {
            "category":"Home & Garden",
            "subcategory":"Hardware",
            "type":"Retail Goods"
        },
        {
            "category":"Shopping",
            "subcategory":"Discount & Variety Stores",
            "type":"Retail Goods"
        }
    ],
    "sg:postcode":"KY12 7SN",
    "sg:province":"Fife",
    "sg:tags":[
        "equipment",
        "material",
        "cleaning",
        "supply"
    ],
    "wof:name":"PYEROY LTD",
    "wof:placetype":"venue"
},
  "geometry": {"coordinates":[-3.460363,56.062157],"type":"Point"}
}