{
  "type": "Feature",
  "properties": {
    "addr:full":"Flat 3 79-85 Bridge Rd Maidenhead Berkshire SL6 8LY",
    "addr:housenumber":"79-85",
    "addr:postcode":"sl6 8ly",
    "addr:street":"Bridge Rd",
    "iso:country":"GB",
    "sg:address":"Flat 3 79-85 Bridge Rd",
    "sg:city":"Maidenhead",
    "sg:classifiers":[
        {
            "category":"Building & Trades",
            "subcategory":"Construction",
            "type":"Services"
        }
    ],
    "sg:phone":"+44 1628 676682",
    "sg:postcode":"SL6 8LY",
    "sg:province":"Berkshire",
    "sg:tags":[
        "builder"
    ],
    "wof:name":"E J Harris",
    "wof:placetype":"venue"
},
  "geometry": {"coordinates":[-0.7272570133,51.5223731995],"type":"Point"}
}