{
  "type": "Feature",
  "properties": {
    "addr:full":"66 Empire Rd Torquay Devon TQ1 4LE",
    "addr:housenumber":"66",
    "addr:postcode":"tq1 4le",
    "addr:street":"Empire Rd",
    "iso:country":"GB",
    "sg:address":"66 Empire Rd",
    "sg:city":"Torquay",
    "sg:classifiers":[
        {
            "category":"Building & Trades",
            "subcategory":"Construction",
            "type":"Services"
        }
    ],
    "sg:phone":"+44 1803 326810",
    "sg:postcode":"TQ1 4LE",
    "sg:province":"Devon",
    "sg:tags":[
        "builder"
    ],
    "wof:name":"Higgs & Son",
    "wof:placetype":"venue"
},
  "geometry": {"coordinates":[-3.531163,50.478649],"type":"Point"}
}