{
  "type": "Feature",
  "properties": {
    "iso:country":"GB",
    "sg:address":"Unit 3 Somervell Street, Cambuslang",
    "sg:city":"Glasgow",
    "sg:classifiers":[
        {
            "category":"Retail",
            "subcategory":"Auto Repair",
            "type":"Services"
        }
    ],
    "sg:phone":"+44 141 641 1123",
    "sg:postcode":"G72 7EB",
    "sg:province":"South Lanarkshire",
    "sg:tags":[
        "body",
        "car"
    ],
    "wof:name":"A G L Vehicle Repairs Service",
    "wof:placetype":"venue"
},
  "geometry": {"coordinates":[-4.174338,55.820709],"type":"Point"}
}