{
  "type": "Feature",
  "properties": {
    "iso:country":"GB",
    "sg:address":"Eresby Avenue",
    "sg:city":"Spilsby",
    "sg:classifiers":[
        {
            "category":"Education",
            "subcategory":"Special Training",
            "type":"Public Place"
        },
        {
            "category":"Education",
            "subcategory":"School",
            "type":"Public Place"
        },
        {
            "category":"Government",
            "subcategory":"Office",
            "type":"Public Place"
        }
    ],
    "sg:phone":"+44 1790 752441",
    "sg:postcode":"PE23 5HU",
    "sg:province":"Lincolnshire",
    "sg:tags":[
        "local",
        "authority"
    ],
    "wof:name":"The Eresby School",
    "wof:placetype":"venue"
},
  "geometry": {"coordinates":[0.09033,53.173145],"type":"Point"}
}