{
  "type": "Feature",
  "properties": {
    "addr:full":"Knutsford Road, Chelford Macclesfield Cheshire SK11 9AS",
    "addr:postcode":"sk11 9as",
    "addr:street":"Knutsford Road",
    "iso:country":"GB",
    "sg:address":"Knutsford Road, Chelford",
    "sg:city":"Macclesfield",
    "sg:classifiers":[
        {
            "category":"Personal",
            "subcategory":"Beauty Salon",
            "type":"Services"
        }
    ],
    "sg:phone":"+44 1625 861332",
    "sg:postcode":"SK11 9AS",
    "sg:province":"Cheshire",
    "sg:tags":[
        "unisex",
        "hairdresser"
    ],
    "wof:name":"Hairline",
    "wof:placetype":"venue"
},
  "geometry": {"coordinates":[-2.281611,53.2705],"type":"Point"}
}