{
  "type": "Feature",
  "properties": {
    "addr:full":"Bardon Mill Hexham Northumberland NE47 7JN",
    "addr:postcode":"ne47 7jn",
    "addr:street":"Bardon Mill",
    "iso:country":"GB",
    "sg:address":"Bardon Mill",
    "sg:city":"Hexham",
    "sg:classifiers":[
        {
            "category":"Museum",
            "subcategory":"Art Museum",
            "type":"Entertainment"
        },
        {
            "category":"Museum",
            "type":"Entertainment"
        }
    ],
    "sg:phone":"+44 1434 344277",
    "sg:postcode":"NE47 7JN",
    "sg:province":"Northumberland",
    "sg:tags":[
        "gallery"
    ],
    "sg:website":"http://www.vindolanda.com",
    "wof:name":"Vindolanda Trust",
    "wof:placetype":"venue"
},
  "geometry": {"coordinates":[-2.3573300838,54.9914398193],"type":"Point"}
}