{
  "type": "Feature",
  "properties": {
    "iso:country":"GB",
    "sg:address":"Grass Royal",
    "sg:city":"Yeovil",
    "sg:classifiers":[
        {
            "category":"Education",
            "subcategory":"School",
            "type":"Public Place"
        },
        {
            "category":"Government",
            "subcategory":"Office",
            "type":"Public Place"
        }
    ],
    "sg:phone":"+44 1935 423863",
    "sg:postcode":"BA21 4JW",
    "sg:province":"Somerset",
    "sg:tags":[
        "local",
        "authority"
    ],
    "wof:name":"Grass Royal Junior School",
    "wof:placetype":"venue"
},
  "geometry": {"coordinates":[-2.6216681004,50.9480628967],"type":"Point"}
}