{
  "type": "Feature",
  "properties": {
    "addr:full":"79 De Freville Avenue Cambridge Cambridgeshire CB4 1HP",
    "addr:postcode":"cb4 1hp",
    "addr:street":"79 De Freville Avenue",
    "iso:country":"GB",
    "sg:address":"79 De Freville Avenue",
    "sg:city":"Cambridge",
    "sg:classifiers":[
        {
            "category":"Government",
            "subcategory":"Post Office",
            "type":"Public Place"
        }
    ],
    "sg:phone":"+44 1223 573104",
    "sg:postcode":"CB4 1HP",
    "sg:province":"Cambridgeshire",
    "sg:tags":[
        "organisation",
        "soc",
        "research"
    ],
    "wof:name":"Dr A Hooley",
    "wof:placetype":"venue"
},
  "geometry": {"coordinates":[0.1311729997,52.2124176025],"type":"Point"}
}