{
  "type": "Feature",
  "properties": {
    "addr:full":"Heron Road, Sowton Industrial Estate Exeter Devon EX2 7LX",
    "addr:postcode":"ex2 7lx",
    "addr:street":"Heron Road;Industrial Estate",
    "iso:country":"GB",
    "sg:address":"Heron Road, Sowton Industrial Estate",
    "sg:city":"Exeter",
    "sg:classifiers":[
        {
            "category":"Manufacturing",
            "subcategory":"Signs",
            "type":"Manufacturing & Wholesale Goods"
        }
    ],
    "sg:phone":"+44 1392 444501",
    "sg:postcode":"EX2 7LX",
    "sg:province":"Devon",
    "sg:tags":[
        "equipment",
        "nameplate"
    ],
    "sg:website":"http://www.wwdesign.com",
    "wof:name":"Wood & Wood International Signs Ltd",
    "wof:placetype":"venue"
},
  "geometry": {"coordinates":[-3.473614,50.722782],"type":"Point"}
}