{
  "type": "Feature",
  "properties": {
    "addr:full":"4 Ashfield Terrace Bingley West Yorkshire BD16 1EQ",
    "addr:housenumber":"4",
    "addr:postcode":"bd16 1eq",
    "addr:street":"Ashfield Terrace",
    "iso:country":"GB",
    "sg:address":"4 Ashfield Terrace",
    "sg:city":"Bingley",
    "sg:classifiers":[
        {
            "category":"Personal",
            "subcategory":"Beauty Salon",
            "type":"Services"
        }
    ],
    "sg:phone":"+44 1274 551038",
    "sg:postcode":"BD16 1EQ",
    "sg:province":"West Yorkshire",
    "sg:tags":[
        "unisex",
        "hairdresser"
    ],
    "wof:name":"Lee Skipsey",
    "wof:placetype":"venue"
},
  "geometry": {"coordinates":[-1.8320560455,53.8432197571],"type":"Point"}
}