{
  "type": "Feature",
  "properties": {
    "addr:full":"1 Rutherglen Road Glasgow Glasgow City G73 1SX",
    "addr:housenumber":"1",
    "addr:postcode":"g73 1sx",
    "addr:street":"Rutherglen Road",
    "iso:country":"GB",
    "sg:address":"1 Rutherglen Road",
    "sg:city":"Glasgow",
    "sg:classifiers":[
        {
            "category":"Retail",
            "subcategory":"Auto Repair",
            "type":"Services"
        }
    ],
    "sg:postcode":"G73 1SX",
    "sg:province":"Glasgow City",
    "sg:tags":[
        "modification",
        "garage"
    ],
    "wof:name":"William Curran",
    "wof:placetype":"venue"
},
  "geometry": {"coordinates":[-4.227687,55.836494],"type":"Point"}
}