{
  "type": "Feature",
  "properties": {
    "addr:full":"265 Strand London Greater London WC2R 1BH",
    "addr:housenumber":"265",
    "addr:postcode":"wc2r 1bh",
    "addr:street":"Strand",
    "iso:country":"GB",
    "sg:address":"265 Strand",
    "sg:city":"London",
    "sg:classifiers":[
        {
            "category":"Professional",
            "subcategory":"Lawyer & Legal Services",
            "type":"Services"
        }
    ],
    "sg:postcode":"WC2R 1BH",
    "sg:province":"Greater London",
    "wof:name":"Covington & Burling",
    "wof:placetype":"venue"
},
  "geometry": {"coordinates":[-0.1147089973,51.513217926],"type":"Point"}
}