{
  "type": "Feature",
  "properties": {
    "iso:country":"GB",
    "sg:address":"45 St. Helens Way",
    "sg:city":"Leeds",
    "sg:classifiers":[
        {
            "category":"Retail",
            "subcategory":"Auto Repair",
            "type":"Services"
        }
    ],
    "sg:phone":"+44 113 216 7534",
    "sg:postcode":"LS16 8LP",
    "sg:province":"West Yorkshire",
    "sg:tags":[
        "body",
        "car"
    ],
    "wof:name":"ChipsAway-bradford",
    "wof:placetype":"venue"
},
  "geometry": {"coordinates":[-1.582883,53.850174],"type":"Point"}
}