{
  "type": "Feature",
  "properties": {
    "iso:country":"GB",
    "sg:address":"King Edward Hall, High Street, Lindfield",
    "sg:city":"Haywards Heath",
    "sg:classifiers":[
        {
            "category":"Organizations",
            "subcategory":"Membership Organization",
            "type":"Services"
        }
    ],
    "sg:phone":"+44 1444 482369",
    "sg:postcode":"RH16 2HH",
    "sg:province":"East Sussex",
    "sg:tags":[
        "club",
        "social"
    ],
    "wof:name":"The Lindfield Club",
    "wof:placetype":"venue"
},
  "geometry": {"coordinates":[-0.0842870027,51.0106010437],"type":"Point"}
}