{
  "type": "Feature",
  "properties": {
    "iso:country":"GB",
    "sg:address":"Easter Dullatur Farm, Dullatur",
    "sg:city":"Glasgow",
    "sg:classifiers":[
        {
            "category":"Farming",
            "subcategory":"Livestock Farm",
            "type":"Manufacturing & Wholesale Goods"
        }
    ],
    "sg:phone":"+44 1236 724226",
    "sg:postcode":"G68 0AB",
    "sg:province":"East Dunbartonshire",
    "sg:tags":[
        "others"
    ],
    "wof:name":"Andrew M Duncan",
    "wof:placetype":"venue"
},
  "geometry": {"coordinates":[-4.008657,55.968307],"type":"Point"}
}