{
  "type": "Feature",
  "properties": {
    "iso:country":"GB",
    "sg:address":"12a Rozel, Middle Lincombe Rd",
    "sg:city":"Torquay",
    "sg:classifiers":[
        {
            "category":"Professional",
            "subcategory":"Management & Consulting",
            "type":"Services"
        }
    ],
    "sg:phone":"+44 1803 212220",
    "sg:postcode":"TQ1 2NF",
    "sg:province":"Devon",
    "sg:tags":[
        "consultant",
        "business"
    ],
    "wof:name":"The Marketing & Management Machine",
    "wof:placetype":"venue"
},
  "geometry": {"coordinates":[-3.514618,50.460873],"type":"Point"}
}