{
  "type": "Feature",
  "properties": {
    "iso:country":"GB",
    "sg:address":"40 Fore Street, Kings Kerswell",
    "sg:city":"Newton Abbot",
    "sg:classifiers":[
        {
            "category":"Food & Beverages",
            "subcategory":"Meat & Fish",
            "type":"Retail Goods"
        }
    ],
    "sg:phone":"+44 1803 874180",
    "sg:postcode":"TQ12 5HZ",
    "sg:province":"Devon",
    "sg:tags":[
        "butcher"
    ],
    "wof:name":"A 1 Catering Butcher",
    "wof:placetype":"venue"
},
  "geometry": {"coordinates":[-3.5792310238,50.4983520508],"type":"Point"}
}