{
  "type": "Feature",
  "properties": {
    "addr:full":"Gretna Terrace Gateshead Tyne and Wear NE10 0BS",
    "addr:postcode":"ne10 0bs",
    "addr:street":"Gretna Terrace",
    "iso:country":"GB",
    "sg:address":"Gretna Terrace",
    "sg:city":"Gateshead",
    "sg:classifiers":[
        {
            "category":"Organizations",
            "subcategory":"Community Association",
            "type":"Services"
        },
        {
            "category":"Organizations",
            "subcategory":"Membership Organization",
            "type":"Services"
        }
    ],
    "sg:phone":"+44 191 469 3162",
    "sg:postcode":"NE10 0BS",
    "sg:province":"Tyne and Wear",
    "sg:tags":[
        "club",
        "social"
    ],
    "wof:name":"FELLING WORKING MENS SOCIAL CLUB",
    "wof:placetype":"venue"
},
  "geometry": {"coordinates":[-1.57365,54.9496],"type":"Point"}
}