{
  "type": "Feature",
  "properties": {
    "iso:country":"GB",
    "sg:address":"The Street, Galleywood",
    "sg:city":"Chelmsford",
    "sg:classifiers":[
        {
            "category":"Food & Beverages",
            "subcategory":"Meat & Fish",
            "type":"Retail Goods"
        }
    ],
    "sg:phone":"+44 1245 250557",
    "sg:postcode":"CM2 8QL",
    "sg:province":"Essex",
    "sg:tags":[
        "chip"
    ],
    "wof:name":"Mr Fish",
    "wof:placetype":"venue"
},
  "geometry": {"coordinates":[0.4668749869,51.6977882385],"type":"Point"}
}