{
  "type": "Feature",
  "properties": {
    "addr:full":"9 New Station Road Bristol City of Bristol BS16 3RP",
    "addr:housenumber":"9",
    "addr:postcode":"bs16 3rp",
    "addr:street":"New Station Road",
    "iso:country":"GB",
    "sg:address":"9 New Station Road",
    "sg:city":"Bristol",
    "sg:classifiers":[
        {
            "category":"Shopping",
            "subcategory":"Music",
            "type":"Retail Goods"
        }
    ],
    "sg:phone":"+44 117 965 8608",
    "sg:postcode":"BS16 3RP",
    "sg:province":"City of Bristol",
    "sg:tags":[
        "record",
        "tape",
        "cd"
    ],
    "wof:name":"Kays Discs & Tapes",
    "wof:placetype":"venue"
},
  "geometry": {"coordinates":[-2.5292930603,51.479888916],"type":"Point"}
}