{
  "type": "Feature",
  "properties": {
    "addr:full":"59 High Street, Standlake Witney Oxfordshire OX29 7RH",
    "addr:housenumber":"59",
    "addr:postcode":"ox29 7rh",
    "addr:street":"High Street",
    "iso:country":"GB",
    "sg:address":"59 High Street, Standlake",
    "sg:city":"Witney",
    "sg:classifiers":[
        {
            "category":"Professional",
            "subcategory":"Engineering",
            "type":"Services"
        }
    ],
    "sg:phone":"+44 1865 300270",
    "sg:postcode":"OX29 7RH",
    "sg:province":"Oxfordshire",
    "wof:name":"Johnsons Engineering & Electrical Co",
    "wof:placetype":"venue"
},
  "geometry": {"coordinates":[-1.4283599854,51.7240066528],"type":"Point"}
}