{
  "type": "Feature",
  "properties": {
    "addr:full":"The Old Smithy, Hart St Henley-on-thames Berkshire RG9 2AR",
    "addr:postcode":"rg9 2ar",
    "addr:street":"Hart St",
    "iso:country":"GB",
    "sg:address":"The Old Smithy, Hart St",
    "sg:city":"Henley-on-thames",
    "sg:classifiers":[
        {
            "category":"Professional",
            "subcategory":"Art Services",
            "type":"Services"
        }
    ],
    "sg:postcode":"RG9 2AR",
    "sg:province":"Berkshire",
    "sg:tags":[
        "graphic",
        "designer"
    ],
    "wof:name":"Clark,Kate,",
    "wof:placetype":"venue"
},
  "geometry": {"coordinates":[-0.903189,51.535297],"type":"Point"}
}