{
  "type": "Feature",
  "properties": {
    "iso:country":"GB",
    "sg:address":"Hardwick",
    "sg:city":"Aylesbury",
    "sg:classifiers":[
        {
            "category":"Place Of Worship",
            "type":"Public Place"
        }
    ],
    "sg:phone":"+44 1296 641768",
    "sg:postcode":"HP21 7NS",
    "sg:province":"Buckinghamshire",
    "wof:name":"St Mary C of E Church",
    "wof:placetype":"venue"
},
  "geometry": {"coordinates":[-0.79801,51.803028],"type":"Point"}
}