{
  "type": "Feature",
  "properties": {
    "iso:country":"GB",
    "sg:address":"34 Commercial Street, Ystradgynlais",
    "sg:city":"Swansea",
    "sg:classifiers":[
        {
            "category":"Retail",
            "subcategory":"Repair Shop",
            "type":"Services"
        },
        {
            "category":"Communications",
            "type":"Services"
        }
    ],
    "sg:phone":"+44 1639 849200",
    "sg:postcode":"SA9 1JH",
    "sg:province":"Carmarthenshire",
    "sg:tags":[
        "tv",
        "radio",
        "television",
        "video"
    ],
    "wof:name":"Davies Tv & Video Repairs",
    "wof:placetype":"venue"
},
  "geometry": {"coordinates":[-3.759018,51.778202],"type":"Point"}
}