{
  "type": "Feature",
  "properties": {
    "addr:full":"113-115 Oatlands Dr Weybridge Surrey KT13 9LB",
    "addr:housenumber":"113-115",
    "addr:postcode":"kt13 9lb",
    "addr:street":"Oatlands Dr",
    "iso:country":"GB",
    "sg:address":"113-115 Oatlands Dr",
    "sg:city":"Weybridge",
    "sg:classifiers":[
        {
            "category":"Autos & Motor Vehicles",
            "subcategory":"Automobile Sales",
            "type":"Retail Goods"
        }
    ],
    "sg:phone":"+44 1932 820022",
    "sg:postcode":"KT13 9LB",
    "sg:province":"Surrey",
    "sg:tags":[
        "car"
    ],
    "wof:name":"Centre Group",
    "wof:placetype":"venue"
},
  "geometry": {"coordinates":[-0.439511,51.373154],"type":"Point"}
}