{
  "type": "Feature",
  "properties": {
    "addr:full":"36a Handsworth Avenue Chingford Greater London E4 9PJ",
    "addr:housenumber":"36a",
    "addr:postcode":"e4 9pj",
    "addr:street":"Handsworth Avenue",
    "iso:country":"GB",
    "sg:address":"36a Handsworth Avenue",
    "sg:city":"Chingford",
    "sg:classifiers":[
        {
            "category":"Place Of Worship",
            "type":"Public Place"
        }
    ],
    "sg:phone":"+44 20 8527 1182",
    "sg:postcode":"E4 9PJ",
    "sg:province":"Greater London",
    "wof:name":"Handsworth Avenue Methodist Church",
    "wof:placetype":"venue"
},
  "geometry": {"coordinates":[0.003889,51.609241],"type":"Point"}
}