{
  "type": "Feature",
  "properties": {
    "addr:full":"320 Drummond Road Skegness Lincolnshire PE25 3AY",
    "addr:housenumber":"320",
    "addr:postcode":"pe25 3ay",
    "addr:street":"Drummond Road",
    "iso:country":"GB",
    "sg:address":"320 Drummond Road",
    "sg:city":"Skegness",
    "sg:classifiers":[
        {
            "category":"Building & Trades",
            "subcategory":"Construction",
            "type":"Services"
        }
    ],
    "sg:phone":"+44 1754 764827",
    "sg:postcode":"PE25 3AY",
    "sg:province":"Lincolnshire",
    "sg:tags":[
        "builder"
    ],
    "wof:name":"G L Savage Ltd.",
    "wof:placetype":"venue"
},
  "geometry": {"coordinates":[0.336361,53.125893],"type":"Point"}
}