{
  "type": "Feature",
  "properties": {
    "iso:country":"GB",
    "sg:address":"3 Lancelyn Court Precinct, Bebington",
    "sg:city":"Wirral",
    "sg:classifiers":[
        {
            "category":"Shopping",
            "subcategory":"Pharmacy",
            "type":"Retail Goods"
        }
    ],
    "sg:phone":"+44 151 334 5486",
    "sg:postcode":"CH63 9JP",
    "sg:province":"Merseyside",
    "sg:tags":[
        "pharmacist",
        "store",
        "drug",
        "chemist"
    ],
    "wof:name":"W A Temple",
    "wof:placetype":"venue"
},
  "geometry": {"coordinates":[-3.004464,53.340343],"type":"Point"}
}