{
  "type": "Feature",
  "properties": {
    "addr:full":"48 Lowmoor Road, Kirkby-in-ashfield Nottingham Nottinghamshire NG17 7BG",
    "addr:housenumber":"48",
    "addr:postcode":"ng17 7bg",
    "addr:street":"Lowmoor Road",
    "iso:country":"GB",
    "sg:address":"48 Lowmoor Road, Kirkby-in-ashfield",
    "sg:city":"Nottingham",
    "sg:classifiers":[
        {
            "category":"Shopping",
            "subcategory":"Comic Books",
            "type":"Retail Goods"
        }
    ],
    "sg:postcode":"NG17 7BG",
    "sg:province":"Nottinghamshire",
    "sg:tags":[
        "jeweller"
    ],
    "wof:name":"Kingsway Jewellers",
    "wof:placetype":"venue"
},
  "geometry": {"coordinates":[-1.24442,53.111523],"type":"Point"}
}