{
  "type": "Feature",
  "properties": {
    "addr:full":"12 Mallaig Industrial Estate, The Pier Mallaig Highland PH41 4PX",
    "addr:housenumber":"12",
    "addr:postcode":"ph41 4px",
    "addr:street":"Mallaig Industrial Estate;Mallaig",
    "iso:country":"GB",
    "sg:address":"12 Mallaig Industrial Estate, The Pier",
    "sg:city":"Mallaig",
    "sg:classifiers":[
        {
            "category":"Farming",
            "subcategory":"Fish & Marine Products",
            "type":"Manufacturing & Wholesale Goods"
        }
    ],
    "sg:phone":"+44 1687 462234",
    "sg:postcode":"PH41 4PX",
    "sg:province":"Highland",
    "sg:tags":[
        "fisherman"
    ],
    "wof:name":"Kerrera Fisheries Ltd.",
    "wof:placetype":"venue"
},
  "geometry": {"coordinates":[-5.8291192055,57.0058250427],"type":"Point"}
}