{
  "type": "Feature",
  "properties": {
    "addr:full":"149 Richmond Park Road Bournemouth Dorset BH8 8UA",
    "addr:housenumber":"149",
    "addr:postcode":"bh8 8ua",
    "addr:street":"Richmond Park Road",
    "iso:country":"GB",
    "sg:address":"149 Richmond Park Road",
    "sg:city":"Bournemouth",
    "sg:classifiers":[
        {
            "category":"Travel",
            "subcategory":"Travel Agent",
            "type":"Entertainment"
        }
    ],
    "sg:phone":"+44 1202 538036",
    "sg:postcode":"BH8 8UA",
    "sg:province":"Dorset",
    "sg:tags":[
        "hotel",
        "agency",
        "booking"
    ],
    "wof:name":"Travellers B & B Uk",
    "wof:placetype":"venue"
},
  "geometry": {"coordinates":[-1.859777,50.736599],"type":"Point"}
}