{
  "type": "Feature",
  "properties": {
    "addr:full":"Second Floor, York House London Greater London SE1 7UT",
    "addr:housenumber":"second floor york",
    "addr:postcode":"se1 7ut",
    "iso:country":"GB",
    "sg:address":"Second Floor, York House",
    "sg:city":"London",
    "sg:classifiers":[
        {
            "category":"Organizations",
            "subcategory":"Non-profit Organization",
            "type":"Services"
        }
    ],
    "sg:phone":"+44 20 7928 7743",
    "sg:postcode":"SE1 7UT",
    "sg:province":"Greater London",
    "sg:tags":[
        "organisation",
        "voluntary",
        "charity"
    ],
    "wof:name":"British Eye Research Foundation",
    "wof:placetype":"venue"
},
  "geometry": {"coordinates":[-0.11594,51.500229],"type":"Point"}
}