{
  "type": "Feature",
  "properties": {
    "iso:country":"GB",
    "sg:address":"66 Main Street, Desford",
    "sg:city":"Leicester",
    "sg:classifiers":[
        {
            "category":"Shopping",
            "subcategory":"News",
            "type":"Retail Goods"
        }
    ],
    "sg:phone":"+44 1455 824411",
    "sg:postcode":"LE9 9NP",
    "sg:province":"Leicestershire",
    "sg:tags":[
        "newsagent"
    ],
    "wof:name":"Forbuoys",
    "wof:placetype":"venue"
},
  "geometry": {"coordinates":[-1.3414280415,52.6296920776],"type":"Point"}
}