{
  "type": "Feature",
  "properties": {
    "addr:full":"11 Pole Lane Darwen Lancashire BB3 3LD",
    "addr:housenumber":"11",
    "addr:postcode":"bb3 3ld",
    "addr:street":"Pole Lane",
    "iso:country":"GB",
    "sg:address":"11 Pole Lane",
    "sg:city":"Darwen",
    "sg:classifiers":[
        {
            "category":"Communications",
            "subcategory":"Newspaper",
            "type":"Services"
        }
    ],
    "sg:phone":"+44 1254 703389",
    "sg:postcode":"BB3 3LD",
    "sg:province":"Lancashire",
    "sg:tags":[
        "magazine"
    ],
    "wof:name":"Witch Ale",
    "wof:placetype":"venue"
},
  "geometry": {"coordinates":[-2.4484670162,53.6901664734],"type":"Point"}
}