{
  "type": "Feature",
  "properties": {
    "addr:full":"Naze Lane East, Flackleton Preston Lancashire PR4 1UN",
    "addr:postcode":"pr4 1un",
    "addr:street":"Naze Lane",
    "iso:country":"GB",
    "sg:address":"Naze Lane East, Flackleton",
    "sg:city":"Preston",
    "sg:classifiers":[
        {
            "category":"Autos & Motor Vehicles",
            "subcategory":"Boat Sales",
            "type":"Retail Goods"
        }
    ],
    "sg:phone":"+44 1772 633016",
    "sg:postcode":"PR4 1UN",
    "sg:province":"Lancashire",
    "sg:tags":[
        "repair",
        "builder"
    ],
    "wof:name":"Seahog Boats",
    "wof:placetype":"venue"
},
  "geometry": {"coordinates":[-2.8679409027,53.7524490356],"type":"Point"}
}