{
  "type": "Feature",
  "properties": {
    "iso:country":"GB",
    "sg:address":"134 Witton Street",
    "sg:city":"Northwich",
    "sg:classifiers":[
        {
            "category":"Personal",
            "subcategory":"Beauty Salon",
            "type":"Services"
        },
        {
            "category":"Personal",
            "subcategory":"Barber",
            "type":"Services"
        }
    ],
    "sg:phone":"+44 1606 43632",
    "sg:postcode":"CW9 5NP",
    "sg:province":"Cheshire",
    "sg:tags":[
        "unisex",
        "hairdresser"
    ],
    "wof:name":"Suttons",
    "wof:placetype":"venue"
},
  "geometry": {"coordinates":[-2.507042,53.262253],"type":"Point"}
}