{
  "type": "Feature",
  "properties": {
    "iso:country":"GB",
    "sg:address":"Eastbourne Street",
    "sg:city":"Walsall",
    "sg:classifiers":[
        {
            "category":"Wholesale",
            "subcategory":"Fruits & Vegetables",
            "type":"Manufacturing & Wholesale Goods"
        }
    ],
    "sg:phone":"+44 1922 626656",
    "sg:postcode":"WS4 2BN",
    "sg:province":"West Midlands",
    "wof:name":"F R Heydon",
    "wof:placetype":"venue"
},
  "geometry": {"coordinates":[-1.9743180275,52.5932388306],"type":"Point"}
}