{
  "type": "Feature",
  "properties": {
    "iso:country":"GB",
    "sg:address":"74 Milton Road",
    "sg:city":"Kirkcaldy",
    "sg:classifiers":[
        {
            "category":"Professional",
            "subcategory":"Lawyer & Legal Services",
            "type":"Services"
        }
    ],
    "sg:phone":"+44 1592 261345",
    "sg:postcode":"KY1 1TP",
    "sg:province":"Fife",
    "sg:tags":[
        "solicitor"
    ],
    "wof:name":"IAIN M BALFOUR",
    "wof:placetype":"venue"
},
  "geometry": {"coordinates":[-3.16701,56.103916],"type":"Point"}
}