{
  "type": "Feature",
  "properties": {
    "addr:full":"Wyburn House, New Street Torrington Devon EX38 8BN",
    "addr:postcode":"ex38 8bn",
    "addr:street":"New Street",
    "iso:country":"GB",
    "sg:address":"Wyburn House, New Street",
    "sg:city":"Torrington",
    "sg:classifiers":[
        {
            "category":"Personal",
            "type":"Services"
        }
    ],
    "sg:phone":"+44 1805 622554",
    "sg:postcode":"EX38 8BN",
    "sg:province":"Devon",
    "sg:tags":[
        "wedding"
    ],
    "wof:name":"Cheers",
    "wof:placetype":"venue"
},
  "geometry": {"coordinates":[-4.1529021263,50.9528694153],"type":"Point"}
}