{
  "type": "Feature",
  "properties": {
    "addr:full":"95 High Street, Eston Middlesbrough North Yorkshire TS6 9JD",
    "addr:housenumber":"95",
    "addr:postcode":"ts6 9jd",
    "addr:street":"High Street",
    "iso:country":"GB",
    "sg:address":"95 High Street, Eston",
    "sg:city":"Middlesbrough",
    "sg:classifiers":[
        {
            "category":"Health Services",
            "subcategory":"Optometrist",
            "type":"Services"
        }
    ],
    "sg:phone":"+44 1642 466155",
    "sg:postcode":"TS6 9JD",
    "sg:province":"North Yorkshire",
    "sg:tags":[
        "optician"
    ],
    "wof:name":"Evelyn Hall",
    "wof:placetype":"venue"
},
  "geometry": {"coordinates":[-1.143737,54.559689],"type":"Point"}
}