{
  "type": "Feature",
  "properties": {
    "addr:full":"69 Abergele Road Colwyn Bay Conwy LL29 7RU",
    "addr:housenumber":"69",
    "addr:postcode":"ll29 7ru",
    "addr:street":"Abergele Road",
    "iso:country":"GB",
    "sg:address":"69 Abergele Road",
    "sg:city":"Colwyn Bay",
    "sg:classifiers":[
        {
            "category":"Shopping",
            "subcategory":"Thrift Store",
            "type":"Retail Goods"
        },
        {
            "category":"Organizations",
            "subcategory":"Non-profit Organization",
            "type":"Services"
        }
    ],
    "sg:phone":"+44 1492 530857",
    "sg:postcode":"LL29 7RU",
    "sg:province":"Conwy",
    "sg:tags":[
        "shop",
        "organisation",
        "voluntary",
        "charity"
    ],
    "wof:name":"Scope",
    "wof:placetype":"venue"
},
  "geometry": {"coordinates":[-3.724542,53.293732],"type":"Point"}
}