{
  "type": "Feature",
  "properties": {
    "iso:country":"GB",
    "sg:address":"112 High Street",
    "sg:city":"Redcar",
    "sg:classifiers":[
        {
            "category":"Bars & Pubs",
            "subcategory":"Nightclub",
            "type":"Food & Drink"
        }
    ],
    "sg:postcode":"TS10 3DH",
    "sg:province":"North Yorkshire",
    "sg:tags":[
        "club",
        "night"
    ],
    "wof:name":"Georgies",
    "wof:placetype":"venue"
},
  "geometry": {"coordinates":[-1.062573,54.617573],"type":"Point"}
}