{
  "type": "Feature",
  "properties": {
    "iso:country":"GB",
    "sg:address":"Trinity Street",
    "sg:city":"Stalybridge",
    "sg:classifiers":[
        {
            "category":"Retail",
            "subcategory":"Auto Repair",
            "type":"Services"
        }
    ],
    "sg:phone":"+44 161 304 9393",
    "sg:postcode":"SK15 2BN",
    "sg:province":"Greater Manchester",
    "sg:tags":[
        "modification",
        "garage"
    ],
    "wof:name":"J Howarth Motors",
    "wof:placetype":"venue"
},
  "geometry": {"coordinates":[-2.056244,53.482937],"type":"Point"}
}