{
  "type": "Feature",
  "properties": {
    "iso:country":"GB",
    "sg:address":"Springfield Road",
    "sg:city":"Leek",
    "sg:classifiers":[
        {
            "category":"Home & Garden",
            "subcategory":"Furniture",
            "type":"Retail Goods"
        }
    ],
    "sg:phone":"+44 1538 382534",
    "sg:postcode":"ST13 6EN",
    "sg:province":"Staffordshire",
    "wof:name":"Creative Pine Trading",
    "wof:placetype":"venue"
},
  "geometry": {"coordinates":[-2.011817,53.107948],"type":"Point"}
}