{
  "type": "Feature",
  "properties": {
    "addr:full":"97 High Street Tipton West Midlands DY4 9JE",
    "addr:housenumber":"97",
    "addr:postcode":"dy4 9je",
    "addr:street":"High Street",
    "iso:country":"GB",
    "sg:address":"97 High Street",
    "sg:city":"Tipton",
    "sg:classifiers":[
        {
            "category":"Home & Garden",
            "subcategory":"Hardware",
            "type":"Retail Goods"
        }
    ],
    "sg:phone":"+44 121 557 8522",
    "sg:postcode":"DY4 9JE",
    "sg:province":"West Midlands",
    "sg:tags":[
        "retailer",
        "diy"
    ],
    "wof:name":"John the Handyman",
    "wof:placetype":"venue"
},
  "geometry": {"coordinates":[-2.063988924,52.5422286987],"type":"Point"}
}