{
  "type": "Feature",
  "properties": {
    "addr:full":"98 Fengate Peterborough Cambridgeshire PE1 5BB",
    "addr:housenumber":"98",
    "addr:postcode":"pe1 5bb",
    "addr:street":"Fengate Peterborough",
    "iso:country":"GB",
    "sg:address":"98 Fengate",
    "sg:city":"Peterborough",
    "sg:classifiers":[
        {
            "category":"Food & Beverages",
            "subcategory":"Supermarket",
            "type":"Retail Goods"
        },
        {
            "category":"Food & Beverages",
            "subcategory":"Groceries & Convenience Stores",
            "type":"Retail Goods"
        }
    ],
    "sg:phone":"+44 1733 566703",
    "sg:postcode":"PE1 5BB",
    "sg:province":"Cambridgeshire",
    "sg:tags":[
        "grocer"
    ],
    "wof:name":"P P Lodge",
    "wof:placetype":"venue"
},
  "geometry": {"coordinates":[-0.223950997,52.5708694458],"type":"Point"}
}