{
  "type": "Feature",
  "properties": {
    "iso:country":"GB",
    "sg:address":"66 Norman Road",
    "sg:city":"St Leonards-on-sea",
    "sg:classifiers":[
        {
            "category":"Professional",
            "subcategory":"Business Services",
            "type":"Services"
        }
    ],
    "sg:phone":"+44 1424 444726",
    "sg:postcode":"TN38 0EJ",
    "sg:province":"East Sussex",
    "wof:name":"la Maison Office Services Ltd.",
    "wof:placetype":"venue"
},
  "geometry": {"coordinates":[0.558152,50.851749],"type":"Point"}
}