{
  "type": "Feature",
  "properties": {
    "addr:full":"Sunway, Carters Corner Hailsham East Sussex BN27 4HT",
    "addr:housenumber":"sunway",
    "addr:postcode":"bn27 4ht",
    "addr:street":"Carters Corner",
    "iso:country":"GB",
    "sg:address":"Sunway, Carters Corner",
    "sg:city":"Hailsham",
    "sg:classifiers":[
        {
            "category":"Shopping",
            "subcategory":"Antiques",
            "type":"Retail Goods"
        }
    ],
    "sg:postcode":"BN27 4HT",
    "sg:province":"East Sussex",
    "wof:name":"Sunway Restorations",
    "wof:placetype":"venue"
},
  "geometry": {"coordinates":[0.2565200031,50.8653831482],"type":"Point"}
}