{
  "type": "Feature",
  "properties": {
    "iso:country":"GB",
    "sg:address":"Justin Close",
    "sg:city":"Brentford",
    "sg:classifiers":[
        {
            "category":"Real Estate",
            "subcategory":"Surveying",
            "type":"Services"
        },
        {
            "category":"Building & Trades",
            "subcategory":"Construction",
            "type":"Services"
        }
    ],
    "sg:postcode":"TW8 8QH",
    "sg:province":"Greater London",
    "sg:tags":[
        "surveyor",
        "builder",
        "valuer"
    ],
    "wof:name":"DAVID PARKINSON LTD",
    "wof:placetype":"venue"
},
  "geometry": {"coordinates":[-0.302817,51.482075],"type":"Point"}
}