{
  "type": "Feature",
  "properties": {
    "addr:full":"80-82 Stocksbank Road Mirfield West Yorkshire WF14 9QB",
    "addr:housenumber":"80-82",
    "addr:postcode":"wf14 9qb",
    "addr:street":"Stocksbank Road",
    "iso:country":"GB",
    "sg:address":"80-82 Stocksbank Road",
    "sg:city":"Mirfield",
    "sg:classifiers":[
        {
            "category":"Manufacturing",
            "subcategory":"Textiles",
            "type":"Manufacturing & Wholesale Goods"
        }
    ],
    "sg:phone":"+44 7885 280139",
    "sg:postcode":"WF14 9QB",
    "sg:province":"West Yorkshire",
    "sg:tags":[
        "merchant",
        "agent"
    ],
    "wof:name":"Kay & Roe Ltd.",
    "wof:placetype":"venue"
},
  "geometry": {"coordinates":[-1.7103550434,53.6803016663],"type":"Point"}
}