{
  "type": "Feature",
  "properties": {
    "addr:full":"10 Heol-y-fro Pontypridd Rhondda, Cynon, Taff CF38 1UD",
    "addr:housenumber":"10",
    "addr:postcode":"cf38 1ud",
    "addr:street":"Heol-Y-Fro Pontypridd;Cynon Taff",
    "iso:country":"GB",
    "sg:address":"10 Heol-y-fro",
    "sg:city":"Pontypridd",
    "sg:classifiers":[
        {
            "category":"Building & Trades",
            "subcategory":"Construction",
            "type":"Services"
        }
    ],
    "sg:phone":"+44 1443 206425",
    "sg:postcode":"CF38 1UD",
    "sg:province":"Rhondda, Cynon, Taff",
    "sg:tags":[
        "builder"
    ],
    "wof:name":"C J D Construction",
    "wof:placetype":"venue"
},
  "geometry": {"coordinates":[-3.326986,51.569321],"type":"Point"}
}