{
  "type": "Feature",
  "properties": {
    "addr:full":"88 Buxton Road, High Lane Stockport Cheshire SK6 8HJ",
    "addr:housenumber":"88",
    "addr:postcode":"sk6 8hj",
    "addr:street":"Buxton Road High Lane",
    "iso:country":"GB",
    "sg:address":"88 Buxton Road, High Lane",
    "sg:city":"Stockport",
    "sg:classifiers":[
        {
            "category":"Bars & Pubs",
            "type":"Food & Drink"
        },
        {
            "category":"Restaurant",
            "type":"Food & Drink"
        }
    ],
    "sg:phone":"+44 1663 762413",
    "sg:postcode":"SK6 8HJ",
    "sg:province":"Cheshire",
    "sg:tags":[
        "-"
    ],
    "wof:name":"Dog & Partridge",
    "wof:placetype":"venue"
},
  "geometry": {"coordinates":[-2.0722239017,53.3641700745],"type":"Point"}
}