{
  "type": "Feature",
  "properties": {
    "addr:full":"10 Castle Foregate Shrewsbury Shropshire SY1 2DJ",
    "addr:housenumber":"10",
    "addr:postcode":"sy1 2dj",
    "addr:street":"Castle Foregate",
    "iso:country":"GB",
    "sg:address":"10 Castle Foregate",
    "sg:city":"Shrewsbury",
    "sg:classifiers":[
        {
            "category":"Shopping",
            "subcategory":"News",
            "type":"Retail Goods"
        }
    ],
    "sg:phone":"+44 1743 351074",
    "sg:postcode":"SY1 2DJ",
    "sg:province":"Shropshire",
    "sg:tags":[
        "newsagent"
    ],
    "wof:name":"A P & J Thomas",
    "wof:placetype":"venue"
},
  "geometry": {"coordinates":[-2.750431,52.712391],"type":"Point"}
}