{
  "type": "Feature",
  "properties": {
    "iso:country":"GB",
    "sg:address":"2 Caslte Buildings, 147 Telegraph Road, Heswall",
    "sg:city":"Wirral",
    "sg:classifiers":[
        {
            "category":"Building & Trades",
            "subcategory":"Cleaning & Sanitation",
            "type":"Services"
        }
    ],
    "sg:phone":"+44 151 342 1999",
    "sg:postcode":"CH60 7SE",
    "sg:province":"Merseyside",
    "sg:tags":[
        "contracting",
        "commercial"
    ],
    "wof:name":"Cleaning Technology",
    "wof:placetype":"venue"
},
  "geometry": {"coordinates":[-3.098729,53.329056],"type":"Point"}
}