{
  "type": "Feature",
  "properties": {
    "addr:full":"Pengam Rd, Aberbargoed Bargoed Caerphilly CF81 9UA",
    "addr:postcode":"cf81 9ua",
    "addr:street":"Pengam Rd",
    "iso:country":"GB",
    "sg:address":"Pengam Rd, Aberbargoed",
    "sg:city":"Bargoed",
    "sg:classifiers":[
        {
            "category":"Education",
            "subcategory":"School",
            "type":"Public Place"
        }
    ],
    "sg:phone":"+44 1443 828900",
    "sg:postcode":"CF81 9UA",
    "sg:province":"Caerphilly",
    "sg:tags":[
        "local",
        "authority"
    ],
    "wof:name":"Bedwellty Comprehensive School",
    "wof:placetype":"venue"
},
  "geometry": {"coordinates":[-3.2196838856,51.6878204346],"type":"Point"}
}