{
  "type": "Feature",
  "properties": {
    "addr:full":"The Hoe Plymouth Devon PL1 2NZ",
    "addr:postcode":"pl1 2nz",
    "iso:country":"GB",
    "sg:address":"The Hoe",
    "sg:city":"Plymouth",
    "sg:classifiers":[
        {
            "category":"Government",
            "subcategory":"Office",
            "type":"Public Place"
        },
        {
            "category":"Landmark",
            "subcategory":"Tourist Attraction",
            "type":"Public Place"
        }
    ],
    "sg:phone":"+44 1752 603300",
    "sg:postcode":"PL1 2NZ",
    "sg:province":"Devon",
    "sg:tags":[
        "local",
        "interest"
    ],
    "wof:name":"The Plymouth Dome",
    "wof:placetype":"venue"
},
  "geometry": {"coordinates":[-4.13641,50.363041],"type":"Point"}
}