{
  "type": "Feature",
  "properties": {
    "addr:full":"31 South End Croydon Surrey CR0 1BE",
    "addr:housenumber":"31",
    "addr:postcode":"cr0 1be",
    "addr:street":"South End",
    "iso:country":"GB",
    "sg:address":"31 South End",
    "sg:city":"Croydon",
    "sg:classifiers":[
        {
            "category":"Restaurant",
            "type":"Food & Drink"
        }
    ],
    "sg:phone":"+44 20 8688 8422",
    "sg:postcode":"CR0 1BE",
    "sg:province":"Surrey",
    "wof:name":"Croydon Steak House",
    "wof:placetype":"venue"
},
  "geometry": {"coordinates":[-0.0989670008,51.3667106628],"type":"Point"}
}