{
  "type": "Feature",
  "properties": {
    "addr:full":"2a Queen St, Long Eaton Nottingham Derbyshire NG10 1BJ",
    "addr:housenumber":"2a",
    "addr:postcode":"ng10 1bj",
    "addr:street":"Queen St",
    "iso:country":"GB",
    "sg:address":"2a Queen St, Long Eaton",
    "sg:city":"Nottingham",
    "sg:classifiers":[
        {
            "category":"Building & Trades",
            "subcategory":"Construction",
            "type":"Services"
        }
    ],
    "sg:postcode":"NG10 1BJ",
    "sg:province":"Derbyshire",
    "sg:tags":[
        "builder"
    ],
    "wof:name":"Freeman Bros",
    "wof:placetype":"venue"
},
  "geometry": {"coordinates":[-1.273233,52.894764],"type":"Point"}
}