{
  "type": "Feature",
  "properties": {
    "addr:full":"2 South Hill Road, Boxmoor Hemel Hempstead Hertfordshire HP1 1JB",
    "addr:housenumber":"2",
    "addr:postcode":"hp1 1jb",
    "addr:street":"South Hill Road;Hempstead",
    "iso:country":"GB",
    "sg:address":"2 South Hill Road, Boxmoor",
    "sg:city":"Hemel Hempstead",
    "sg:classifiers":[
        {
            "category":"Building & Trades",
            "subcategory":"Landscaping Services",
            "type":"Services"
        }
    ],
    "sg:phone":"+44 1442 230319",
    "sg:postcode":"HP1 1JB",
    "sg:province":"Hertfordshire",
    "sg:tags":[
        "landscape",
        "contractor"
    ],
    "wof:name":"Utopia Landscapes",
    "wof:placetype":"venue"
},
  "geometry": {"coordinates":[-0.4769310057,51.7523422241],"type":"Point"}
}