{
  "type": "Feature",
  "properties": {
    "addr:full":"10 Replingham Road London Greater London SW18 5LS",
    "addr:housenumber":"10",
    "addr:postcode":"sw18 5ls",
    "addr:street":"Replingham Road",
    "iso:country":"GB",
    "sg:address":"10 Replingham Road",
    "sg:city":"London",
    "sg:classifiers":[
        {
            "category":"Professional",
            "type":"Services"
        },
        {
            "category":"Bakery",
            "type":"Food & Drink"
        }
    ],
    "sg:postcode":"SW18 5LS",
    "sg:province":"Greater London",
    "sg:tags":[
        "cake",
        "maker",
        "caterer"
    ],
    "wof:name":"Suzelle Cakes Ltd.",
    "wof:placetype":"venue"
},
  "geometry": {"coordinates":[-0.205531,51.444607],"type":"Point"}
}