{
  "type": "Feature",
  "properties": {
    "addr:full":"100 Lake Road Ambleside Cumbria LA22 0DB",
    "addr:housenumber":"100",
    "addr:postcode":"la22 0db",
    "addr:street":"Lake Road",
    "iso:country":"GB",
    "sg:address":"100 Lake Road",
    "sg:city":"Ambleside",
    "sg:classifiers":[
        {
            "category":"Arts & Performance",
            "subcategory":"Art Gallery",
            "type":"Entertainment"
        },
        {
            "category":"Shopping",
            "subcategory":"Books",
            "type":"Retail Goods"
        },
        {
            "category":"Arena",
            "subcategory":"Sports Club",
            "type":"Entertainment"
        }
    ],
    "sg:phone":"+44 15394 34440",
    "sg:postcode":"LA22 0DB",
    "sg:province":"Cumbria",
    "wof:name":"The Homes Of Football At Ambleside",
    "wof:placetype":"venue"
},
  "geometry": {"coordinates":[-2.9625959396,54.4291191101],"type":"Point"}
}