{
  "type": "Feature",
  "properties": {
    "addr:full":"Queensferry House, Carnegie Campus Dunfermline Fife KY11 8GR",
    "addr:postcode":"ky11 8gr",
    "iso:country":"GB",
    "sg:address":"Queensferry House, Carnegie Campus",
    "sg:city":"Dunfermline",
    "sg:classifiers":[
        {
            "category":"Health Services",
            "subcategory":"Clinic",
            "type":"Services"
        }
    ],
    "sg:phone":"+44 1383 843300",
    "sg:postcode":"KY11 8GR",
    "sg:province":"Fife",
    "sg:tags":[
        "medical"
    ],
    "wof:name":"Optos Plc",
    "wof:placetype":"venue"
},
  "geometry": {"coordinates":[-3.4271540642,56.0483856201],"type":"Point"}
}