{
  "type": "Feature",
  "properties": {
    "addr:full":"St Ninian Drive Inverness Highland IV3 5AU",
    "addr:postcode":"iv3 5au",
    "addr:street":"St Ninian Drive",
    "iso:country":"GB",
    "sg:address":"St Ninian Drive",
    "sg:city":"Inverness",
    "sg:classifiers":[
        {
            "category":"Education",
            "subcategory":"School",
            "type":"Public Place"
        },
        {
            "category":"Government",
            "subcategory":"Office",
            "type":"Public Place"
        }
    ],
    "sg:phone":"+44 1463 232636",
    "sg:postcode":"IV3 5AU",
    "sg:province":"Highland",
    "sg:tags":[
        "local",
        "authority"
    ],
    "wof:name":"Dalneigh Primary School",
    "wof:placetype":"venue"
},
  "geometry": {"coordinates":[-4.247794,57.474289],"type":"Point"}
}