{
  "type": "Feature",
  "properties": {
    "addr:full":"15 Orcheston Road Bournemouth Dorset BH8 8SP",
    "addr:housenumber":"15",
    "addr:postcode":"bh8 8sp",
    "addr:street":"Orcheston Road",
    "iso:country":"GB",
    "sg:address":"15 Orcheston Road",
    "sg:city":"Bournemouth",
    "sg:classifiers":[
        {
            "category":"Building & Trades",
            "subcategory":"Plumbing",
            "type":"Services"
        }
    ],
    "sg:phone":"+44 1202 398865",
    "sg:postcode":"BH8 8SP",
    "sg:province":"Dorset",
    "sg:tags":[
        "heating"
    ],
    "wof:name":"A J Way Plumbing & Heating",
    "wof:placetype":"venue"
},
  "geometry": {"coordinates":[-1.8582559824,50.7354927063],"type":"Point"}
}