{
  "type": "Feature",
  "properties": {
    "addr:full":"181 London Road, Temple Ewell Dover Kent CT16 3DF",
    "addr:housenumber":"181",
    "addr:postcode":"ct16 3df",
    "addr:street":"London Road",
    "iso:country":"GB",
    "sg:address":"181 London Road, Temple Ewell",
    "sg:city":"Dover",
    "sg:classifiers":[
        {
            "category":"Shopping",
            "subcategory":"Department Store",
            "type":"Retail Goods"
        },
        {
            "category":"Food & Beverages",
            "subcategory":"Supermarket",
            "type":"Retail Goods"
        }
    ],
    "sg:phone":"+44 1304 827100",
    "sg:postcode":"CT16 3DF",
    "sg:province":"Kent",
    "wof:name":"Southdown Stores",
    "wof:placetype":"venue"
},
  "geometry": {"coordinates":[1.2747000456,51.1487236023],"type":"Point"}
}