{
  "type": "Feature",
  "properties": {
    "iso:country":"GB",
    "sg:address":"143 William Street",
    "sg:city":"Grays",
    "sg:classifiers":[
        {
            "category":"Manufacturing",
            "subcategory":"Tools & Machinery",
            "type":"Manufacturing & Wholesale Goods"
        }
    ],
    "sg:phone":"+44 1375 376560",
    "sg:postcode":"RM17 6DZ",
    "sg:province":"Essex",
    "sg:tags":[
        "society",
        "friendly"
    ],
    "wof:name":"John Chapman",
    "wof:placetype":"venue"
},
  "geometry": {"coordinates":[0.3354099989,51.4754562378],"type":"Point"}
}