{
  "type": "Feature",
  "properties": {
    "iso:country":"GB",
    "sg:address":"36 Townshend Rd",
    "sg:city":"London",
    "sg:classifiers":[
        {
            "category":"Banks & Credit Unions",
            "subcategory":"Financial Services",
            "type":"Services"
        }
    ],
    "sg:postcode":"NW8 6LE",
    "sg:province":"Greater London",
    "sg:tags":[
        "claim",
        "assessor"
    ],
    "wof:name":"Balcombe,S H,& Co",
    "wof:placetype":"venue"
},
  "geometry": {"coordinates":[-0.166829,51.536079],"type":"Point"}
}