{
  "type": "Feature",
  "properties": {
    "addr:full":"High Street Slough Berkshire SL3 0JZ",
    "addr:postcode":"sl3 0jz",
    "addr:street":"High Street",
    "iso:country":"GB",
    "sg:address":"High Street",
    "sg:city":"Slough",
    "sg:classifiers":[
        {
            "category":"Restaurant",
            "type":"Food & Drink"
        }
    ],
    "sg:phone":"+44 1753 682628",
    "sg:postcode":"SL3 0JZ",
    "sg:province":"Berkshire",
    "wof:name":"The Ostrich Inn",
    "wof:placetype":"venue"
},
  "geometry": {"coordinates":[-0.528147,51.484451],"type":"Point"}
}