{
  "type": "Feature",
  "properties": {
    "addr:full":"Ashleigh, Helland, North Curry Taunton Devon TA3 6DU",
    "addr:postcode":"ta3 6du",
    "addr:street":"Helland North Curry",
    "iso:country":"GB",
    "sg:address":"Ashleigh, Helland, North Curry",
    "sg:city":"Taunton",
    "sg:classifiers":[
        {
            "category":"Building & Trades",
            "subcategory":"Landscaping Services",
            "type":"Services"
        }
    ],
    "sg:phone":"+44 1823 698198",
    "sg:postcode":"TA3 6DU",
    "sg:province":"Devon",
    "sg:tags":[
        "landscape",
        "contractor"
    ],
    "wof:name":"John Attwood",
    "wof:placetype":"venue"
},
  "geometry": {"coordinates":[-2.970339,51.022926],"type":"Point"}
}