{
  "type": "Feature",
  "properties": {
    "iso:country":"GB",
    "sg:address":"10 Baker St",
    "sg:city":"Northampton",
    "sg:classifiers":[
        {
            "category":"Professional",
            "subcategory":"Detective & Security Services",
            "type":"Services"
        }
    ],
    "sg:phone":"+44 1604 458310",
    "sg:postcode":"NN2 6DJ",
    "sg:province":"Northamptonshire",
    "sg:tags":[
        "agency"
    ],
    "wof:name":"Huntman Financial Services",
    "wof:placetype":"venue"
},
  "geometry": {"coordinates":[-0.9034069777,52.2483711243],"type":"Point"}
}