{
  "type": "Feature",
  "properties": {
    "iso:country":"GB",
    "sg:address":"5-6 Monument Buildings, Pembroke Pl",
    "sg:city":"Liverpool",
    "sg:classifiers":[
        {
            "category":"Shopping",
            "subcategory":"Bicycles & Sporting Goods",
            "type":"Retail Goods"
        }
    ],
    "sg:phone":"+44 151 709 0666",
    "sg:postcode":"L3 5PH",
    "sg:province":"Merseyside",
    "sg:tags":[
        "cycle",
        "accessory"
    ],
    "wof:name":"Action Bikes",
    "wof:placetype":"venue"
},
  "geometry": {"coordinates":[-2.9719688892,53.4092254639],"type":"Point"}
}