{
  "type": "Feature",
  "properties": {
    "addr:full":"Glebe Farm Cottage, Grovely Road Salisbury Wiltshire SP3 4AF",
    "addr:postcode":"sp3 4af",
    "addr:street":"Grovely Road",
    "iso:country":"GB",
    "sg:address":"Glebe Farm Cottage, Grovely Road",
    "sg:city":"Salisbury",
    "sg:classifiers":[
        {
            "category":"Professional",
            "type":"Services"
        }
    ],
    "sg:phone":"+44 1722 742312",
    "sg:postcode":"SP3 4AF",
    "sg:province":"Wiltshire",
    "sg:tags":[
        "caterer"
    ],
    "wof:name":"Lucy Turner",
    "wof:placetype":"venue"
},
  "geometry": {"coordinates":[-1.91893,51.083229],"type":"Point"}
}