{
  "type": "Feature",
  "properties": {
    "iso:country":"GB",
    "sg:address":"Dobroyd Castle, Pexwood Road",
    "sg:city":"Todmorden",
    "sg:classifiers":[
        {
            "category":"Shopping",
            "subcategory":"Pharmacy",
            "type":"Retail Goods"
        }
    ],
    "sg:phone":"+44 1706 812247",
    "sg:postcode":"OL14 7JJ",
    "sg:province":"Lancashire",
    "sg:tags":[
        "medicine",
        "therapy"
    ],
    "wof:name":"Losang Dragpa Centre",
    "wof:placetype":"venue"
},
  "geometry": {"coordinates":[-2.0973079205,53.7143096924],"type":"Point"}
}