{
  "type": "Feature",
  "properties": {
    "addr:full":"Montcrieff Business Centre, Friarton Road Perth Perth and Kinross PH2 8DG",
    "addr:postcode":"ph2 8dg",
    "addr:street":"Friarton Road",
    "iso:country":"GB",
    "sg:address":"Montcrieff Business Centre, Friarton Road",
    "sg:city":"Perth",
    "sg:classifiers":[
        {
            "category":"Professional",
            "subcategory":"Employment Agencies",
            "type":"Services"
        }
    ],
    "sg:postcode":"PH2 8DG",
    "sg:province":"Perth and Kinross",
    "sg:tags":[
        "consultant"
    ],
    "wof:name":"P H D Recruitment Ltd.",
    "wof:placetype":"venue"
},
  "geometry": {"coordinates":[-3.4324140549,56.3960533142],"type":"Point"}
}