{
  "type": "Feature",
  "properties": {
    "iso:country":"GB",
    "sg:address":"5 Shropshire Street, Audlem",
    "sg:city":"Crewe",
    "sg:classifiers":[
        {
            "category":"Food & Beverages",
            "subcategory":"Bakery",
            "type":"Retail Goods"
        }
    ],
    "sg:phone":"+44 1270 812226",
    "sg:postcode":"CW3 0AE",
    "sg:province":"Cheshire",
    "sg:tags":[
        "pizza"
    ],
    "wof:name":"The Pizza Parlour",
    "wof:placetype":"venue"
},
  "geometry": {"coordinates":[-2.508286,52.988514],"type":"Point"}
}