{
  "type": "Feature",
  "properties": {
    "iso:country":"GB",
    "sg:address":"529 Rayleigh Rd",
    "sg:city":"Leigh On Sea",
    "sg:classifiers":[
        {
            "category":"Autos & Motor Vehicles",
            "subcategory":"Fuel & Gas Station",
            "type":"Retail Goods"
        }
    ],
    "sg:phone":"+44 1702 512245",
    "sg:postcode":"SS9 5HJ",
    "sg:province":"Essex",
    "sg:tags":[
        "hr",
        "petrol"
    ],
    "wof:name":"Belgrave Filling Station",
    "wof:placetype":"venue"
},
  "geometry": {"coordinates":[0.639586,51.57251],"type":"Point"}
}