{
  "type": "Feature",
  "properties": {
    "iso:country":"GB",
    "sg:address":"Church Street, Rudgwick",
    "sg:city":"Horsham",
    "sg:classifiers":[
        {
            "category":"Farming",
            "subcategory":"Nursery",
            "type":"Manufacturing & Wholesale Goods"
        },
        {
            "category":"Education",
            "subcategory":"School",
            "type":"Public Place"
        }
    ],
    "sg:phone":"+44 1403 822391",
    "sg:postcode":"RH12 3HJ",
    "sg:province":"West Sussex",
    "sg:tags":[
        "independent",
        "preparatory",
        "creche"
    ],
    "sg:website":"http://www.pennthorpe.com",
    "wof:name":"Pennthorpe School Trust Ltd.",
    "wof:placetype":"venue"
},
  "geometry": {"coordinates":[-0.448429,51.090824],"type":"Point"}
}