{
  "type": "Feature",
  "properties": {
    "iso:country":"GB",
    "sg:address":"3 Chalkridge Road",
    "sg:city":"Portsmouth",
    "sg:classifiers":[
        {
            "category":"Professional",
            "subcategory":"Business Services",
            "type":"Services"
        }
    ],
    "sg:postcode":"PO6 2BE",
    "sg:province":"Hampshire",
    "sg:tags":[
        "assessment",
        "quality"
    ],
    "wof:name":"Garrett Associates",
    "wof:placetype":"venue"
},
  "geometry": {"coordinates":[-1.0603380203,50.8508338928],"type":"Point"}
}