{
  "type": "Feature",
  "properties": {
    "addr:full":"21 Hallstile Bank Hexham Northumberland NE46 3PG",
    "addr:housenumber":"21",
    "addr:postcode":"ne46 3pg",
    "addr:street":"Hallstile Bank",
    "iso:country":"GB",
    "sg:address":"21 Hallstile Bank",
    "sg:city":"Hexham",
    "sg:classifiers":[
        {
            "category":"Wholesale",
            "subcategory":"Toys & Hobbies",
            "type":"Manufacturing & Wholesale Goods"
        }
    ],
    "sg:postcode":"NE46 3PG",
    "sg:province":"Northumberland",
    "sg:tags":[
        "balloon",
        "novelty"
    ],
    "wof:name":"Harlequin",
    "wof:placetype":"venue"
},
  "geometry": {"coordinates":[-2.10004,54.972019],"type":"Point"}
}