{
  "type": "Feature",
  "properties": {
    "iso:country":"GB",
    "sg:address":"21 Hallstile Bank",
    "sg:city":"Hexham",
    "sg:classifiers":[
        {
            "category":"Wholesale",
            "subcategory":"Toys & Hobbies",
            "type":"Manufacturing & Wholesale Goods"
        }
    ],
    "sg:postcode":"NE46 3PG",
    "sg:province":"Northumberland",
    "sg:tags":[
        "balloon",
        "novelty"
    ],
    "wof:name":"Harlequin",
    "wof:placetype":"venue"
},
  "geometry": {"coordinates":[-2.10004,54.972019],"type":"Point"}
}