{
  "type": "Feature",
  "properties": {
    "iso:country":"GB",
    "sg:address":"136 High Street",
    "sg:city":"Tewkesbury",
    "sg:classifiers":[
        {
            "category":"Food & Beverages",
            "subcategory":"Fruits & Vegetables",
            "type":"Retail Goods"
        }
    ],
    "sg:phone":"+44 1684 292024",
    "sg:postcode":"GL20 5JR",
    "sg:province":"Gloucestershire",
    "sg:tags":[
        "greengrocer"
    ],
    "wof:name":"K H Brookes",
    "wof:placetype":"venue"
},
  "geometry": {"coordinates":[-2.157072,51.993427],"type":"Point"}
}