{
  "type": "Feature",
  "properties": {
    "addr:full":"110 Meadoway, Bishops Cleeve Cheltenham Gloucestershire GL52 8NB",
    "addr:housenumber":"110",
    "addr:postcode":"gl52 8nb",
    "addr:street":"Meadoway Bishops",
    "iso:country":"GB",
    "sg:address":"110 Meadoway, Bishops Cleeve",
    "sg:city":"Cheltenham",
    "sg:classifiers":[
        {
            "category":"Building & Trades",
            "subcategory":"Landscaping Services",
            "type":"Services"
        },
        {
            "category":"Professional",
            "subcategory":"Engineering",
            "type":"Services"
        }
    ],
    "sg:phone":"+44 1242 678103",
    "sg:postcode":"GL52 8NB",
    "sg:province":"Gloucestershire",
    "sg:tags":[
        "civil",
        "contractor",
        "landscape",
        "engineer"
    ],
    "wof:name":"B M C",
    "wof:placetype":"venue"
},
  "geometry": {"coordinates":[-2.0703499317,51.9394989014],"type":"Point"}
}