{
  "type": "Feature",
  "properties": {
    "addr:full":"9 Oriental Road Woking Surrey GU22 7AH",
    "addr:housenumber":"9",
    "addr:postcode":"gu22 7ah",
    "addr:street":"Oriental Road",
    "iso:country":"GB",
    "sg:address":"9 Oriental Road",
    "sg:city":"Woking",
    "sg:classifiers":[
        {
            "category":"Food & Beverages",
            "subcategory":"Meat & Fish",
            "type":"Retail Goods"
        }
    ],
    "sg:phone":"+44 1483 773415",
    "sg:postcode":"GU22 7AH",
    "sg:province":"Surrey",
    "sg:tags":[
        "butcher"
    ],
    "wof:name":"Vincent's Butchers",
    "wof:placetype":"venue"
},
  "geometry": {"coordinates":[-0.5535799861,51.3187026978],"type":"Point"}
}