{
  "type": "Feature",
  "properties": {
    "iso:country":"GB",
    "sg:address":"125 Woodfield Street, Morriston",
    "sg:city":"Swansea",
    "sg:classifiers":[
        {
            "category":"Shopping",
            "subcategory":"Shoes",
            "type":"Retail Goods"
        }
    ],
    "sg:phone":"+44 1792 774642",
    "sg:postcode":"SA6 8AL",
    "sg:province":"Swansea",
    "wof:name":"D & A Heel Bar",
    "wof:placetype":"venue"
},
  "geometry": {"coordinates":[-3.925453,51.66589],"type":"Point"}
}