{
  "type": "Feature",
  "properties": {
    "iso:country":"GB",
    "sg:address":"Boosbeck",
    "sg:city":"Saltburn By The Sea",
    "sg:classifiers":[
        {
            "category":"Education",
            "subcategory":"School",
            "type":"Public Place"
        }
    ],
    "sg:phone":"+44 1287 650238",
    "sg:postcode":"TS12 2BN",
    "sg:province":"North Yorkshire",
    "sg:tags":[
        "local",
        "authority"
    ],
    "wof:name":"Lockwood Primary School",
    "wof:placetype":"venue"
},
  "geometry": {"coordinates":[-0.984429,54.554482],"type":"Point"}
}