{
  "type": "Feature",
  "properties": {
    "addr:full":"39 Foyle Avenue, Chaddesden Derby Derbyshire DE21 6TZ",
    "addr:housenumber":"39",
    "addr:postcode":"de21 6tz",
    "addr:street":"Foyle Avenue",
    "iso:country":"GB",
    "sg:address":"39 Foyle Avenue, Chaddesden",
    "sg:city":"Derby",
    "sg:classifiers":[
        {
            "category":"Education",
            "subcategory":"Dance Studio",
            "type":"Public Place"
        }
    ],
    "sg:phone":"+44 1332 670578",
    "sg:postcode":"DE21 6TZ",
    "sg:province":"Derbyshire",
    "sg:tags":[
        "school",
        "dancing"
    ],
    "wof:name":"Dance One",
    "wof:placetype":"venue"
},
  "geometry": {"coordinates":[-1.4321030378,52.9188957214],"type":"Point"}
}