{
  "type": "Feature",
  "properties": {
    "addr:full":"Wheatfield Way, Hinckley Fields Industrial Estate Hinckley Leicestershire LE10 1YG",
    "addr:postcode":"le10 1yg",
    "addr:street":"Wheatfield Way;Fields Industrial Estate",
    "iso:country":"GB",
    "sg:address":"Wheatfield Way, Hinckley Fields Industrial Estate",
    "sg:city":"Hinckley",
    "sg:classifiers":[
        {
            "category":"Home & Garden",
            "subcategory":"Hardware",
            "type":"Retail Goods"
        }
    ],
    "sg:phone":"+44 1455 618666",
    "sg:postcode":"LE10 1YG",
    "sg:province":"Leicestershire",
    "sg:tags":[
        "component",
        "electronic"
    ],
    "wof:name":"I M V Invertomatic Victron U K Ltd.",
    "wof:placetype":"venue"
},
  "geometry": {"coordinates":[-1.376619,52.55611],"type":"Point"}
}