{
  "type": "Feature",
  "properties": {
    "iso:country":"GB",
    "sg:address":"Windhill Manor, Leeds Road",
    "sg:city":"Shipley",
    "sg:classifiers":[
        {
            "category":"Professional",
            "subcategory":"Management & Consulting",
            "type":"Services"
        },
        {
            "category":"Professional",
            "subcategory":"Advertising",
            "type":"Services"
        }
    ],
    "sg:phone":"+44 1274 538888",
    "sg:postcode":"BD18 1BP",
    "sg:province":"West Yorkshire",
    "sg:tags":[
        "marketing",
        "agency",
        "consultant"
    ],
    "wof:name":"Millennium A D M P Plc",
    "wof:placetype":"venue"
},
  "geometry": {"coordinates":[-1.7674399614,53.8345298767],"type":"Point"}
}