{
  "type": "Feature",
  "properties": {
    "addr:full":"35b St Georges Terrace, Jesmond Newcastle-upon-tyne Tyne and Wear NE2 2SU",
    "addr:housenumber":"35b",
    "addr:postcode":"ne2 2su",
    "addr:street":"St Georges Terrace",
    "iso:country":"GB",
    "sg:address":"35b St Georges Terrace, Jesmond",
    "sg:city":"Newcastle-upon-tyne",
    "sg:classifiers":[
        {
            "category":"Manufacturing",
            "subcategory":"Jewelry",
            "type":"Manufacturing & Wholesale Goods"
        }
    ],
    "sg:phone":"+44 191 281 8636",
    "sg:postcode":"NE2 2SU",
    "sg:province":"Tyne and Wear",
    "sg:tags":[
        "repair",
        "jewellery"
    ],
    "wof:name":"Kirkham & Turner",
    "wof:placetype":"venue"
},
  "geometry": {"coordinates":[-1.6067199707,54.9921722412],"type":"Point"}
}