{
  "type": "Feature",
  "properties": {
    "iso:country":"GB",
    "sg:address":"Gainsborough House, 33 Throgmorton St",
    "sg:city":"Moorgate",
    "sg:classifiers":[
        {
            "category":"Banks & Credit Unions",
            "subcategory":"Investment Brokerage",
            "type":"Services"
        }
    ],
    "sg:phone":"+44 20 7861 9600",
    "sg:postcode":"EC2N 2BR",
    "sg:province":"Greater London",
    "sg:tags":[
        "stockbroker"
    ],
    "wof:name":"Lynch, Jones & Ryan",
    "wof:placetype":"venue"
},
  "geometry": {"coordinates":[-0.087584,51.514755],"type":"Point"}
}