{
  "type": "Feature",
  "properties": {
    "addr:full":"3 Austhorpe Avenue Leeds West Yorkshire LS15 8QA",
    "addr:housenumber":"3",
    "addr:postcode":"ls15 8qa",
    "addr:street":"Austhorpe Avenue",
    "iso:country":"GB",
    "sg:address":"3 Austhorpe Avenue",
    "sg:city":"Leeds",
    "sg:classifiers":[
        {
            "category":"Professional",
            "subcategory":"Engineering",
            "type":"Services"
        }
    ],
    "sg:postcode":"LS15 8QA",
    "sg:province":"West Yorkshire",
    "sg:tags":[
        "civil",
        "engineer"
    ],
    "wof:name":"Duffy & Co",
    "wof:placetype":"venue"
},
  "geometry": {"coordinates":[-1.4349739552,53.7958297729],"type":"Point"}
}