{
  "type": "Feature",
  "properties": {
    "addr:full":"The Leas, Minster On Sea Sheerness Kent ME12 2DE",
    "addr:postcode":"me12 2de",
    "addr:street":"The",
    "iso:country":"GB",
    "sg:address":"The Leas, Minster On Sea",
    "sg:city":"Sheerness",
    "sg:classifiers":[
        {
            "category":"Restaurant",
            "type":"Food & Drink"
        }
    ],
    "sg:phone":"+44 1795 872266",
    "sg:postcode":"ME12 2DE",
    "sg:province":"Kent",
    "wof:name":"The Whitehouse Restaurant",
    "wof:placetype":"venue"
},
  "geometry": {"coordinates":[0.7646650076,51.4388504028],"type":"Point"}
}