{
  "type": "Feature",
  "properties": {
    "addr:full":"93 Whitestone Rd Nuneaton Leicestershire CV11 4SY",
    "addr:housenumber":"93",
    "addr:postcode":"cv11 4sy",
    "addr:street":"Whitestone Rd",
    "iso:country":"GB",
    "sg:address":"93 Whitestone Rd",
    "sg:city":"Nuneaton",
    "sg:classifiers":[
        {
            "category":"Professional",
            "subcategory":"Computer Services",
            "type":"Services"
        }
    ],
    "sg:phone":"+44 24 7634 9529",
    "sg:postcode":"CV11 4SY",
    "sg:province":"Leicestershire",
    "sg:tags":[
        "system",
        "software"
    ],
    "wof:name":"R M S Associates",
    "wof:placetype":"venue"
},
  "geometry": {"coordinates":[-1.4359209538,52.5021591187],"type":"Point"}
}