{
  "type": "Feature",
  "properties": {
    "addr:full":"8 Highfield Drive Ringwood Dorset BH24 1RL",
    "addr:housenumber":"8",
    "addr:postcode":"bh24 1rl",
    "addr:street":"Highfield Drive",
    "iso:country":"GB",
    "sg:address":"8 Highfield Drive",
    "sg:city":"Ringwood",
    "sg:classifiers":[
        {
            "category":"Shopping",
            "subcategory":"Discount & Variety Stores",
            "type":"Retail Goods"
        }
    ],
    "sg:postcode":"BH24 1RL",
    "sg:province":"Dorset",
    "sg:tags":[
        "cleaning",
        "supply"
    ],
    "wof:name":"Clean As A Whistle",
    "wof:placetype":"venue"
},
  "geometry": {"coordinates":[-1.782789,50.851955],"type":"Point"}
}