{
  "type": "Feature",
  "properties": {
    "iso:country":"GB",
    "sg:address":"12 The Ridgeway, Flitwick",
    "sg:city":"Bedford",
    "sg:classifiers":[
        {
            "category":"Military Area",
            "subcategory":"Air Force Base",
            "type":"Public Place"
        }
    ],
    "sg:phone":"+44 1525 717078",
    "sg:postcode":"MK45 1DH",
    "sg:province":"Bedfordshire",
    "sg:tags":[
        "taxi",
        "hire",
        "private"
    ],
    "wof:name":"4'A' Taxi Services",
    "wof:placetype":"venue"
},
  "geometry": {"coordinates":[-0.4965690076,52.0037384033],"type":"Point"}
}