{
  "type": "Feature",
  "properties": {
    "addr:full":"Tumblins Blandford Forum Dorset DT11 0ED",
    "addr:postcode":"dt11 0ed",
    "iso:country":"GB",
    "sg:address":"Tumblins",
    "sg:city":"Blandford Forum",
    "sg:classifiers":[
        {
            "category":"Professional",
            "subcategory":"Business Services",
            "type":"Services"
        }
    ],
    "sg:postcode":"DT11 0ED",
    "sg:province":"Dorset",
    "sg:tags":[
        "holding"
    ],
    "wof:name":"Acacia Holdings Ltd.",
    "wof:placetype":"venue"
},
  "geometry": {"coordinates":[-2.1588189602,50.8626441956],"type":"Point"}
}