{
  "type": "Feature",
  "properties": {
    "iso:country":"GB",
    "sg:address":"Prince St",
    "sg:city":"Blaenavon",
    "sg:classifiers":[
        {
            "category":"Travel",
            "subcategory":"Hotels & Motels",
            "type":"Entertainment"
        }
    ],
    "sg:phone":"+44 1495 790706",
    "sg:postcode":"NP4 9BD",
    "sg:province":"Monmouthshire",
    "wof:name":"Queen Victoria The",
    "wof:placetype":"venue"
},
  "geometry": {"coordinates":[-3.0855948925,51.7719078064],"type":"Point"}
}