{
  "type": "Feature",
  "properties": {
    "iso:country":"GB",
    "sg:address":"Rashiehill Mine, Woodmuir",
    "sg:city":"Lanark",
    "sg:classifiers":[
        {
            "category":"Mining & Drilling",
            "type":"Manufacturing & Wholesale Goods"
        }
    ],
    "sg:phone":"+44 1555 811170",
    "sg:postcode":"ML11 8BD",
    "sg:province":"South Lanarkshire",
    "sg:tags":[
        "coal"
    ],
    "wof:name":"Newcastle Mining (Collieries) Ltd",
    "wof:placetype":"venue"
},
  "geometry": {"coordinates":[-3.6311891079,55.7005386353],"type":"Point"}
}