{
  "type": "Feature",
  "properties": {
    "iso:country":"GB",
    "sg:address":"46 Molesey Close, Hersham",
    "sg:city":"Walton-on-thames",
    "sg:classifiers":[
        {
            "category":"Banks & Credit Unions",
            "subcategory":"Financial Services",
            "type":"Services"
        }
    ],
    "sg:phone":"+44 1932 228622",
    "sg:postcode":"KT12 4PX",
    "sg:province":"Surrey",
    "sg:tags":[
        "consultant"
    ],
    "wof:name":"The Uweso U K Trust",
    "wof:placetype":"venue"
},
  "geometry": {"coordinates":[-0.397853,51.366486],"type":"Point"}
}