{
  "type": "Feature",
  "properties": {
    "addr:full":"George Leigh Street School Buildings, Ancoats Manchester Greater Manchester M4 5WD",
    "addr:postcode":"m4 5wd",
    "addr:street":"George Leigh",
    "iso:country":"GB",
    "sg:address":"George Leigh Street School Buildings, Ancoats",
    "sg:city":"Manchester",
    "sg:classifiers":[
        {
            "category":"Professional",
            "subcategory":"Art Services",
            "type":"Services"
        }
    ],
    "sg:phone":"+44 161 236 2008",
    "sg:postcode":"M4 5WD",
    "sg:province":"Greater Manchester",
    "sg:tags":[
        "photographer"
    ],
    "wof:name":"Nomad Designs",
    "wof:placetype":"venue"
},
  "geometry": {"coordinates":[-2.2297239304,53.4850769043],"type":"Point"}
}