{
  "type": "Feature",
  "properties": {
    "addr:full":"101 Edgehill Rd Leicester Leicestershire LE4 9ED",
    "addr:housenumber":"101",
    "addr:postcode":"le4 9ed",
    "addr:street":"Edgehill Rd",
    "iso:country":"GB",
    "sg:address":"101 Edgehill Rd",
    "sg:city":"Leicester",
    "sg:classifiers":[
        {
            "category":"Sports & Exercise",
            "subcategory":"Tennis Court",
            "type":"Entertainment"
        }
    ],
    "sg:phone":"+44 116 246 1678",
    "sg:postcode":"LE4 9ED",
    "sg:province":"Leicestershire",
    "sg:tags":[
        "breakdown",
        "recovery"
    ],
    "wof:name":"Renault Leicester",
    "wof:placetype":"venue"
},
  "geometry": {"coordinates":[-1.0951219797,52.6556892395],"type":"Point"}
}