{
  "type": "Feature",
  "properties": {
    "addr:full":"30 Hillcrest Road Camberley Berkshire GU15 1LG",
    "addr:housenumber":"30",
    "addr:postcode":"gu15 1lg",
    "addr:street":"Hillcrest Road",
    "iso:country":"GB",
    "sg:address":"30 Hillcrest Road",
    "sg:city":"Camberley",
    "sg:classifiers":[
        {
            "category":"Professional",
            "subcategory":"Management & Consulting",
            "type":"Services"
        }
    ],
    "sg:postcode":"GU15 1LG",
    "sg:province":"Berkshire",
    "sg:tags":[
        "consultant",
        "business"
    ],
    "wof:name":"Ollier Associates",
    "wof:placetype":"venue"
},
  "geometry": {"coordinates":[-0.713786,51.343578],"type":"Point"}
}