{
  "type": "Feature",
  "properties": {
    "addr:full":"5-6 Beare Green Court, Beare Green Dorking Surrey RH5 4SL",
    "addr:housenumber":"5-6",
    "addr:postcode":"rh5 4sl",
    "addr:street":"Beare Green Court Beare Green",
    "iso:country":"GB",
    "sg:address":"5-6 Beare Green Court, Beare Green",
    "sg:city":"Dorking",
    "sg:classifiers":[
        {
            "category":"Sports & Exercise",
            "subcategory":"Gym",
            "type":"Entertainment"
        }
    ],
    "sg:phone":"+44 1306 713461",
    "sg:postcode":"RH5 4SL",
    "sg:province":"Surrey",
    "sg:tags":[
        "club",
        "fitness",
        "health",
        "centre"
    ],
    "wof:name":"Studio 56",
    "wof:placetype":"venue"
},
  "geometry": {"coordinates":[-0.3174270093,51.1798706055],"type":"Point"}
}