{
  "type": "Feature",
  "properties": {
    "addr:full":"112 Fleetwood Rd Thornton Cleveleys Lancashire FY5 1RD",
    "addr:housenumber":"112",
    "addr:postcode":"fy5 1rd",
    "addr:street":"Fleetwood Rd",
    "iso:country":"GB",
    "sg:address":"112 Fleetwood Rd",
    "sg:city":"Thornton Cleveleys",
    "sg:classifiers":[
        {
            "category":"Personal",
            "type":"Services"
        }
    ],
    "sg:phone":"+44 1253 853852",
    "sg:postcode":"FY5 1RD",
    "sg:province":"Lancashire",
    "sg:tags":[
        "wedding"
    ],
    "wof:name":"Classic Hire",
    "wof:placetype":"venue"
},
  "geometry": {"coordinates":[-3.038944006,53.8622093201],"type":"Point"}
}