{
  "type": "Feature",
  "properties": {
    "addr:full":"62 Springfield Road, Kings Heath Birmingham West Midlands B14 7DY",
    "addr:housenumber":"62",
    "addr:postcode":"b14 7dy",
    "addr:street":"Springfield Road",
    "iso:country":"GB",
    "sg:address":"62 Springfield Road, Kings Heath",
    "sg:city":"Birmingham",
    "sg:classifiers":[
        {
            "category":"Home & Garden",
            "subcategory":"Carpets & Floor Coverings",
            "type":"Retail Goods"
        }
    ],
    "sg:postcode":"B14 7DY",
    "sg:province":"West Midlands",
    "sg:tags":[
        "cleaner",
        "upholstery"
    ],
    "wof:name":"Super Bubbles",
    "wof:placetype":"venue"
},
  "geometry": {"coordinates":[-1.887596,52.434677],"type":"Point"}
}