{
  "type": "Feature",
  "properties": {
    "addr:full":"6 Berrylands Liss Hampshire GU33 7DB",
    "addr:housenumber":"6",
    "addr:postcode":"gu33 7db",
    "addr:street":"Berrylands",
    "iso:country":"GB",
    "sg:address":"6 Berrylands",
    "sg:city":"Liss",
    "sg:classifiers":[
        {
            "category":"Shopping",
            "subcategory":"Pharmacy",
            "type":"Retail Goods"
        }
    ],
    "sg:phone":"+44 1730 895505",
    "sg:postcode":"GU33 7DB",
    "sg:province":"Hampshire",
    "sg:tags":[
        "medicine",
        "therapy"
    ],
    "wof:name":"Phillipa Ashley",
    "wof:placetype":"venue"
},
  "geometry": {"coordinates":[-0.882599,51.056133],"type":"Point"}
}