{
  "type": "Feature",
  "properties": {
    "addr:full":"283 Linthorpe Road Middlesbrough North Yorkshire TS1 4AS",
    "addr:housenumber":"283",
    "addr:postcode":"ts1 4as",
    "addr:street":"Linthorpe Road",
    "iso:country":"GB",
    "sg:address":"283 Linthorpe Road",
    "sg:city":"Middlesbrough",
    "sg:classifiers":[
        {
            "category":"Professional",
            "subcategory":"Art Services",
            "type":"Services"
        }
    ],
    "sg:phone":"+44 1642 219766",
    "sg:postcode":"TS1 4AS",
    "sg:province":"North Yorkshire",
    "sg:tags":[
        "framing"
    ],
    "wof:name":"National Gallery",
    "wof:placetype":"venue"
},
  "geometry": {"coordinates":[-1.239664,54.568398],"type":"Point"}
}