{
  "type": "Feature",
  "properties": {
    "addr:full":"416-418 Holloway Rd London Greater London N7 6QA",
    "addr:housenumber":"416-418",
    "addr:postcode":"n7 6qa",
    "addr:street":"Holloway Rd",
    "iso:country":"GB",
    "sg:address":"416-418 Holloway Rd",
    "sg:city":"London",
    "sg:classifiers":[
        {
            "category":"Shopping",
            "subcategory":"Shoes",
            "type":"Retail Goods"
        }
    ],
    "sg:postcode":"N7 6QA",
    "sg:province":"Greater London",
    "sg:tags":[
        "shop"
    ],
    "wof:name":"Stead & Simpson Ltd",
    "wof:placetype":"venue"
},
  "geometry": {"coordinates":[-0.118118,51.557056],"type":"Point"}
}