{
  "type": "Feature",
  "properties": {
    "iso:country":"GB",
    "sg:address":"7 Town Gate Drive, Urmston",
    "sg:city":"Manchester",
    "sg:classifiers":[
        {
            "category":"Retail",
            "subcategory":"Auto Repair",
            "type":"Services"
        }
    ],
    "sg:phone":"+44 161 748 3202",
    "sg:postcode":"M41 6ER",
    "sg:province":"Cheshire",
    "sg:tags":[
        "modification",
        "garage"
    ],
    "wof:name":"Ian Dugdale Mobile Mechanic",
    "wof:placetype":"venue"
},
  "geometry": {"coordinates":[-2.405387,53.446651],"type":"Point"}
}