{
  "type": "Feature",
  "properties": {
    "iso:country":"GB",
    "sg:address":"10 The Birches Close, North Baddesley",
    "sg:city":"Southampton",
    "sg:classifiers":[
        {
            "category":"Retail",
            "subcategory":"Driving School",
            "type":"Services"
        }
    ],
    "sg:postcode":"SO52 9HL",
    "sg:province":"Hampshire",
    "wof:name":"Dave Webber",
    "wof:placetype":"venue"
},
  "geometry": {"coordinates":[-1.452369,50.978848],"type":"Point"}
}