{
  "type": "Feature",
  "properties": {
    "addr:full":"Unit 9, Claymore, Tame Valley Industrial Estate Tamworth Staffordshire B77 5DQ",
    "addr:housenumber":"unit 9;estate",
    "addr:postcode":"b77 5dq",
    "addr:street":"Valley Industrial",
    "iso:country":"GB",
    "sg:address":"Unit 9, Claymore, Tame Valley Industrial Estate",
    "sg:city":"Tamworth",
    "sg:classifiers":[
        {
            "category":"Home & Garden",
            "subcategory":"Home Furnishings",
            "type":"Retail Goods"
        }
    ],
    "sg:phone":"+44 1827 283630",
    "sg:postcode":"B77 5DQ",
    "sg:province":"Staffordshire",
    "sg:tags":[
        "mantelpiece",
        "fireplace"
    ],
    "wof:name":"Tamworth Fireplace Centre",
    "wof:placetype":"venue"
},
  "geometry": {"coordinates":[-1.6767539978,52.6083755493],"type":"Point"}
}