{
  "type": "Feature",
  "properties": {
    "addr:full":"Rodwell Ho, 100 Middlesex St Whitechapel Greater London E1 7HD",
    "addr:housenumber":"100",
    "addr:postcode":"e1 7hd",
    "addr:street":"Middlesex St",
    "iso:country":"GB",
    "sg:address":"Rodwell Ho, 100 Middlesex St",
    "sg:city":"Whitechapel",
    "sg:classifiers":[
        {
            "category":"Professional",
            "subcategory":"Computer Services",
            "type":"Services"
        }
    ],
    "sg:phone":"+44 20 7426 6400",
    "sg:postcode":"E1 7HD",
    "sg:province":"Greater London",
    "sg:tags":[
        "system",
        "software"
    ],
    "wof:name":"Compel",
    "wof:placetype":"venue"
},
  "geometry": {"coordinates":[-0.07662,51.517559],"type":"Point"}
}