{
  "type": "Feature",
  "properties": {
    "addr:full":"150 Main Street, East Calder Livingston City of Edinburgh EH53 0HD",
    "addr:housenumber":"150",
    "addr:postcode":"eh53 0hd",
    "addr:street":"Main Street East Calder Livingston",
    "iso:country":"GB",
    "sg:address":"150 Main Street, East Calder",
    "sg:city":"Livingston",
    "sg:classifiers":[
        {
            "category":"Building & Trades",
            "subcategory":"Construction",
            "type":"Services"
        }
    ],
    "sg:phone":"+44 1506 880487",
    "sg:postcode":"EH53 0HD",
    "sg:province":"City of Edinburgh",
    "sg:tags":[
        "joiner",
        "carpenter"
    ],
    "wof:name":"Dunbyus",
    "wof:placetype":"venue"
},
  "geometry": {"coordinates":[-3.4623949528,55.8961639404],"type":"Point"}
}