{
  "type": "Feature",
  "properties": {
    "addr:full":"8 Market Pde Barnsley South Yorkshire S70 1DE",
    "addr:housenumber":"8",
    "addr:postcode":"s70 1de",
    "addr:street":"Market Pde;Yorkshire",
    "iso:country":"GB",
    "sg:address":"8 Market Pde",
    "sg:city":"Barnsley",
    "sg:classifiers":[
        {
            "category":"Shopping",
            "subcategory":"Clothing, Apparel, & Fashions",
            "type":"Retail Goods"
        }
    ],
    "sg:phone":"+44 1226 730876",
    "sg:postcode":"S70 1DE",
    "sg:province":"South Yorkshire",
    "sg:tags":[
        "shop"
    ],
    "wof:name":"Kudos Clothing",
    "wof:placetype":"venue"
},
  "geometry": {"coordinates":[-1.4809889793,53.5522460938],"type":"Point"}
}