{
  "type": "Feature",
  "properties": {
    "iso:country":"GB",
    "sg:address":"41 Brampton Way, Portishead",
    "sg:city":"Bristol",
    "sg:classifiers":[
        {
            "category":"Social Services",
            "type":"Services"
        }
    ],
    "sg:postcode":"BS20 6YN",
    "sg:province":"Somerset",
    "sg:tags":[
        "disability"
    ],
    "wof:name":"Dolphin Lifts",
    "wof:placetype":"venue"
},
  "geometry": {"coordinates":[-2.7615818977,51.4777641296],"type":"Point"}
}