{
  "type": "Feature",
  "properties": {
    "iso:country":"GB",
    "sg:address":"Severn Bridge Industrial Estate",
    "sg:city":"Caldicot",
    "sg:classifiers":[
        {
            "category":"Military Area",
            "subcategory":"Air Force Base",
            "type":"Public Place"
        }
    ],
    "sg:phone":"+44 1291 430001",
    "sg:postcode":"NP26 5PW",
    "sg:province":"Monmouthshire",
    "sg:tags":[
        "water",
        "treatment"
    ],
    "wof:name":"Jesco P & S Ltd.",
    "wof:placetype":"venue"
},
  "geometry": {"coordinates":[-2.748045,51.585957],"type":"Point"}
}