{
  "type": "Feature",
  "properties": {
    "addr:full":"Riverside House Bridge End Hawes North Yorkshire DL8 3NH",
    "addr:postcode":"dl8 3nh",
    "addr:street":"Bridge End",
    "iso:country":"GB",
    "sg:address":"Riverside House Bridge End",
    "sg:city":"Hawes",
    "sg:classifiers":[
        {
            "category":"Sports & Exercise",
            "subcategory":"Sports Center",
            "type":"Entertainment"
        }
    ],
    "sg:postcode":"DL8 3NH",
    "sg:province":"North Yorkshire",
    "sg:tags":[
        "shop",
        "good"
    ],
    "wof:name":"Lowis's Countrywear",
    "wof:placetype":"venue"
},
  "geometry": {"coordinates":[-2.1994268894,54.3041763306],"type":"Point"}
}