{
  "type": "Feature",
  "properties": {
    "addr:full":"2 Argyll Rd Chelmsford Essex CM2 6PY",
    "addr:housenumber":"2",
    "addr:postcode":"cm2 6py",
    "addr:street":"Argyll Rd",
    "iso:country":"GB",
    "sg:address":"2 Argyll Rd",
    "sg:city":"Chelmsford",
    "sg:classifiers":[
        {
            "category":"Autos & Motor Vehicles",
            "subcategory":"Automobile Sales",
            "type":"Retail Goods"
        }
    ],
    "sg:phone":"+44 1245 462222",
    "sg:postcode":"CM2 6PY",
    "sg:province":"Essex",
    "sg:tags":[
        "car"
    ],
    "wof:name":"Markcass Ltd",
    "wof:placetype":"venue"
},
  "geometry": {"coordinates":[0.5057680011,51.7443695068],"type":"Point"}
}