{
  "type": "Feature",
  "properties": {
    "iso:country":"GB",
    "sg:address":"Unit 29 West Orchard Shopping Centre",
    "sg:city":"Coventry",
    "sg:classifiers":[
        {
            "category":"Sports & Exercise",
            "subcategory":"Sports Center",
            "type":"Entertainment"
        }
    ],
    "sg:phone":"+44 24 7655 9592",
    "sg:postcode":"CV1 1QT",
    "sg:province":"West Midlands",
    "sg:tags":[
        "shop",
        "good"
    ],
    "wof:name":"Intersport",
    "wof:placetype":"venue"
},
  "geometry": {"coordinates":[-1.5111839771,52.411075592],"type":"Point"}
}