{
  "type": "Feature",
  "properties": {
    "addr:full":"Station Road Holsworthy Cornwall EX22 6AZ",
    "addr:postcode":"ex22 6az",
    "addr:street":"Station Road",
    "iso:country":"GB",
    "sg:address":"Station Road",
    "sg:city":"Holsworthy",
    "sg:classifiers":[
        {
            "category":"Organizations",
            "subcategory":"Community Association",
            "type":"Services"
        },
        {
            "category":"Organizations",
            "subcategory":"Membership Organization",
            "type":"Services"
        }
    ],
    "sg:phone":"+44 1409 253162",
    "sg:postcode":"EX22 6AZ",
    "sg:province":"Cornwall",
    "sg:tags":[
        "club",
        "social"
    ],
    "wof:name":"Holsworthy Social Club",
    "wof:placetype":"venue"
},
  "geometry": {"coordinates":[-4.353085,50.80822],"type":"Point"}
}