{
  "type": "Feature",
  "properties": {
    "addr:full":"1 Mill Street Melton Mowbray Leicestershire LE13 1AY",
    "addr:housenumber":"1",
    "addr:postcode":"le13 1ay",
    "addr:street":"Mill Street",
    "iso:country":"GB",
    "sg:address":"1 Mill Street",
    "sg:city":"Melton Mowbray",
    "sg:classifiers":[
        {
            "category":"Personal",
            "subcategory":"Beauty Salon",
            "type":"Services"
        },
        {
            "category":"Personal",
            "subcategory":"Barber",
            "type":"Services"
        }
    ],
    "sg:phone":"+44 1664 410523",
    "sg:postcode":"LE13 1AY",
    "sg:province":"Leicestershire",
    "sg:tags":[
        "unisex",
        "hairdresser"
    ],
    "wof:name":"Michael Sorsky",
    "wof:placetype":"venue"
},
  "geometry": {"coordinates":[-0.8848099709,52.7632369995],"type":"Point"}
}