{
  "type": "Feature",
  "properties": {
    "iso:country":"GB",
    "sg:address":"37 Drayton La",
    "sg:city":"Portsmouth",
    "sg:classifiers":[
        {
            "category":"Building & Trades",
            "subcategory":"Plumbing",
            "type":"Services"
        }
    ],
    "sg:phone":"+44 23 9238 0045",
    "sg:postcode":"PO6 1HG",
    "sg:province":"Hampshire",
    "sg:tags":[
        "drain",
        "clearance",
        "sewer"
    ],
    "wof:name":"1st Dial-A-Rod",
    "wof:placetype":"venue"
},
  "geometry": {"coordinates":[-1.048672,50.849388],"type":"Point"}
}