{
  "type": "Feature",
  "properties": {
    "addr:full":"Unit 1 Leaside North, Aycliffe Industrial Estate Newton Aycliffe Durham DL5 6DU",
    "addr:housenumber":"unit 1",
    "addr:postcode":"dl5 6du",
    "addr:street":"Leaside North Aycliffe Industrial Estate;Aycliffe",
    "iso:country":"GB",
    "sg:address":"Unit 1 Leaside North, Aycliffe Industrial Estate",
    "sg:city":"Newton Aycliffe",
    "sg:classifiers":[
        {
            "category":"Wholesale",
            "subcategory":"Machinery & Supplies",
            "type":"Manufacturing & Wholesale Goods"
        }
    ],
    "sg:postcode":"DL5 6DU",
    "sg:province":"Durham",
    "sg:tags":[
        "hydraulic"
    ],
    "wof:name":"Linden Group Ltd.",
    "wof:placetype":"venue"
},
  "geometry": {"coordinates":[-1.563024,54.596272],"type":"Point"}
}