{
  "type": "Feature",
  "properties": {
    "iso:country":"GB",
    "sg:address":"104 Barnards Grn",
    "sg:city":"Malvern",
    "sg:classifiers":[
        {
            "category":"Professional",
            "subcategory":"Business Services",
            "type":"Services"
        }
    ],
    "sg:phone":"+44 845 850 4000",
    "sg:postcode":"WR14 3ND",
    "sg:province":"Herefordshire",
    "sg:tags":[
        "bookmaker"
    ],
    "wof:name":"Connell Racing",
    "wof:placetype":"venue"
},
  "geometry": {"coordinates":[-2.309259,52.105324],"type":"Point"}
}