{
  "type": "Feature",
  "properties": {
    "addr:full":"50 Station Road, Gomshall Guildford Surrey GU5 9LA",
    "addr:housenumber":"50",
    "addr:postcode":"gu5 9la",
    "addr:street":"Station Road",
    "iso:country":"GB",
    "sg:address":"50 Station Road, Gomshall",
    "sg:city":"Guildford",
    "sg:classifiers":[
        {
            "category":"Bars & Pubs",
            "type":"Food & Drink"
        },
        {
            "category":"Community Center",
            "subcategory":"Social",
            "type":"Public Place"
        }
    ],
    "sg:phone":"+44 1483 202506",
    "sg:postcode":"GU5 9LA",
    "sg:province":"Surrey",
    "sg:tags":[
        "pubs",
        "house",
        "inn",
        "activity"
    ],
    "wof:name":"The Compasses Inn",
    "wof:placetype":"venue"
},
  "geometry": {"coordinates":[-0.4478980005,51.2201919556],"type":"Point"}
}