{
  "type": "Feature",
  "properties": {
    "addr:full":"Day Green Farm, Day Green, Hassall Sandbach Cheshire CW11 4XU",
    "addr:postcode":"cw11 4xu",
    "addr:street":"Day",
    "iso:country":"GB",
    "sg:address":"Day Green Farm, Day Green, Hassall",
    "sg:city":"Sandbach",
    "sg:classifiers":[
        {
            "category":"Shopping",
            "subcategory":"Bicycles & Sporting Goods",
            "type":"Retail Goods"
        },
        {
            "category":"Home & Garden",
            "subcategory":"Carpets & Floor Coverings",
            "type":"Retail Goods"
        }
    ],
    "sg:phone":"+44 1270 872095",
    "sg:postcode":"CW11 4XU",
    "sg:province":"Cheshire",
    "sg:tags":[
        "riding",
        "saddlery",
        "retailer",
        "rug",
        "wear"
    ],
    "wof:name":"Alsager & Sandbach Saddlery",
    "wof:placetype":"venue"
},
  "geometry": {"coordinates":[-2.3636479378,53.1422080994],"type":"Point"}
}