{
  "type": "Feature",
  "properties": {
    "addr:full":"4 Gerrard Street London Greater London W1D 5PE",
    "addr:housenumber":"4",
    "addr:postcode":"w1d 5pe",
    "addr:street":"Gerrard Street",
    "iso:country":"GB",
    "sg:address":"4 Gerrard Street",
    "sg:city":"London",
    "sg:classifiers":[
        {
            "category":"Professional",
            "subcategory":"Accounting & Tax Preparation",
            "type":"Services"
        }
    ],
    "sg:phone":"+44 20 7437 1787",
    "sg:postcode":"W1D 5PE",
    "sg:province":"Greater London",
    "sg:tags":[
        "accountant"
    ],
    "wof:name":"Fong Baldwin & Co",
    "wof:placetype":"venue"
},
  "geometry": {"coordinates":[-0.1304170042,51.5121841431],"type":"Point"}
}