{
  "type": "Feature",
  "properties": {
    "iso:country":"GB",
    "sg:address":"33 Mill Road",
    "sg:city":"Worthing",
    "sg:classifiers":[
        {
            "category":"Health Services",
            "subcategory":"Dentist",
            "type":"Services"
        }
    ],
    "sg:phone":"+44 1903 238386",
    "sg:postcode":"BN11 5DS",
    "sg:province":"West Sussex",
    "wof:name":"Robert A Sale",
    "wof:placetype":"venue"
},
  "geometry": {"coordinates":[-0.395234,50.813889],"type":"Point"}
}