{
  "type": "Feature",
  "properties": {
    "addr:full":"21 Riverdale Drive, South Fields London Greater London SW18 4UR",
    "addr:housenumber":"21",
    "addr:postcode":"sw18 4ur",
    "addr:street":"Riverdale Drive South Fields",
    "iso:country":"GB",
    "sg:address":"21 Riverdale Drive, South Fields",
    "sg:city":"London",
    "sg:classifiers":[
        {
            "category":"Farming",
            "subcategory":"Nursery",
            "type":"Manufacturing & Wholesale Goods"
        }
    ],
    "sg:phone":"+44 20 8870 2009",
    "sg:postcode":"SW18 4UR",
    "sg:province":"Greater London",
    "sg:tags":[
        "creche"
    ],
    "wof:name":"Teddies Nurseries",
    "wof:placetype":"venue"
},
  "geometry": {"coordinates":[-0.1925349981,51.4431838989],"type":"Point"}
}