{
  "type": "Feature",
  "properties": {
    "iso:country":"GB",
    "sg:address":"18 Plock Court, Longford",
    "sg:city":"Gloucester",
    "sg:classifiers":[
        {
            "category":"Professional",
            "subcategory":"Computer Services",
            "type":"Services"
        }
    ],
    "sg:phone":"+44 1452 383206",
    "sg:postcode":"GL2 9DW",
    "sg:province":"Gloucestershire",
    "sg:tags":[
        "system",
        "software"
    ],
    "wof:name":"Weltech Computer Systems",
    "wof:placetype":"venue"
},
  "geometry": {"coordinates":[-2.238493,51.880169],"type":"Point"}
}