{
  "type": "Feature",
  "properties": {
    "iso:country":"GB",
    "sg:address":"9b-11c Caxton St North",
    "sg:city":"London",
    "sg:classifiers":[
        {
            "category":"Wholesale",
            "subcategory":"Scrap",
            "type":"Manufacturing & Wholesale Goods"
        }
    ],
    "sg:phone":"+44 20 7511 7294",
    "sg:postcode":"E16 1JR",
    "sg:province":"Greater London",
    "sg:tags":[
        "waste",
        "metal"
    ],
    "wof:name":"London City Metals (92) Ltd.",
    "wof:placetype":"venue"
},
  "geometry": {"coordinates":[0.0132299997,51.5102081299],"type":"Point"}
}