{
  "type": "Feature",
  "properties": {
    "iso:country":"GB",
    "sg:address":"P O Box 20",
    "sg:city":"Dumbarton",
    "sg:classifiers":[
        {
            "category":"Social Services",
            "type":"Services"
        }
    ],
    "sg:phone":"+44 141 951 3100",
    "sg:postcode":"G82 1SJ",
    "sg:province":"Argyll and Bute",
    "sg:tags":[
        "benefit",
        "agency"
    ],
    "wof:name":"Benefits Agency",
    "wof:placetype":"venue"
},
  "geometry": {"coordinates":[-4.561419,55.94352],"type":"Point"}
}