{
  "type": "Feature",
  "properties": {
    "iso:country":"GB",
    "sg:address":"77 Strathmartine Road",
    "sg:city":"Dundee",
    "sg:classifiers":[
        {
            "category":"Shopping",
            "subcategory":"Department Store",
            "type":"Retail Goods"
        },
        {
            "category":"Food & Beverages",
            "subcategory":"Groceries & Convenience Stores",
            "type":"Retail Goods"
        }
    ],
    "sg:phone":"+44 1382 832069",
    "sg:postcode":"DD3 7RY",
    "sg:province":"Dundee City",
    "wof:name":"Paterson's Stores",
    "wof:placetype":"venue"
},
  "geometry": {"coordinates":[-2.978281,56.47337],"type":"Point"}
}