{
  "type": "Feature",
  "properties": {
    "iso:country":"GB",
    "sg:address":"515 Slade Rd",
    "sg:city":"Birmingham",
    "sg:classifiers":[
        {
            "category":"Manufacturing",
            "subcategory":"Tools & Machinery",
            "type":"Manufacturing & Wholesale Goods"
        }
    ],
    "sg:postcode":"B23 7JG",
    "sg:province":"West Midlands",
    "sg:tags":[
        "society",
        "friendly"
    ],
    "wof:name":"Silvester,Roy Robert,",
    "wof:placetype":"venue"
},
  "geometry": {"coordinates":[-1.8589010239,52.5234565735],"type":"Point"}
}