{
  "type": "Feature",
  "properties": {
    "addr:full":"Orchid Way, Stony Lane Christchurch Dorset BH23 7LQ",
    "addr:postcode":"bh23 7lq",
    "addr:street":"Orchid Way Stony Lane",
    "iso:country":"GB",
    "sg:address":"Orchid Way, Stony Lane",
    "sg:city":"Christchurch",
    "sg:classifiers":[
        {
            "category":"Home & Garden",
            "subcategory":"Hardware",
            "type":"Retail Goods"
        }
    ],
    "sg:phone":"+44 1202 476748",
    "sg:postcode":"BH23 7LQ",
    "sg:province":"Dorset",
    "sg:tags":[
        "retailer",
        "diy"
    ],
    "wof:name":"B & Q Supercentre",
    "wof:placetype":"venue"
},
  "geometry": {"coordinates":[-1.776564,50.73407],"type":"Point"}
}