{
  "type": "Feature",
  "properties": {
    "iso:country":"GB",
    "sg:address":"Henybrook, Arscott Lane, Hooe",
    "sg:city":"Plymouth",
    "sg:classifiers":[
        {
            "category":"Shopping",
            "subcategory":"Antiques",
            "type":"Retail Goods"
        }
    ],
    "sg:phone":"+44 1752 482082",
    "sg:postcode":"PL9 9NP",
    "sg:province":"Devon",
    "wof:name":"Patrick & Valerie O'Donoghue",
    "wof:placetype":"venue"
},
  "geometry": {"coordinates":[-4.108622,50.352444],"type":"Point"}
}