{
  "type": "Feature",
  "properties": {
    "addr:full":"34 Marchbank Drive Balerno City of Edinburgh EH14 7ER",
    "addr:housenumber":"34",
    "addr:postcode":"eh14 7er",
    "addr:street":"Marchbank Drive",
    "iso:country":"GB",
    "sg:address":"34 Marchbank Drive",
    "sg:city":"Balerno",
    "sg:classifiers":[
        {
            "category":"Food & Beverages",
            "subcategory":"Liquor & Beverages",
            "type":"Retail Goods"
        }
    ],
    "sg:phone":"+44 131 451 5174",
    "sg:postcode":"EH14 7ER",
    "sg:province":"City of Edinburgh",
    "sg:tags":[
        "beer",
        "spirit",
        "wines"
    ],
    "wof:name":"Edinburgh Blenders",
    "wof:placetype":"venue"
},
  "geometry": {"coordinates":[-3.3413479328,55.8784751892],"type":"Point"}
}