{
  "type": "Feature",
  "properties": {
    "addr:full":"P O Box 25 Barry The Vale of Glamorgan CF62 6YE",
    "addr:housenumber":"box 25",
    "addr:postcode":"cf62 6ye",
    "addr:street":"P O;Barry The Vale",
    "iso:country":"GB",
    "sg:address":"P O Box 25",
    "sg:city":"Barry",
    "sg:classifiers":[
        {
            "category":"Retail",
            "subcategory":"Storage",
            "type":"Services"
        }
    ],
    "sg:phone":"+44 1446 738969",
    "sg:postcode":"CF62 6YE",
    "sg:province":"The Vale of Glamorgan",
    "sg:tags":[
        "household",
        "removal"
    ],
    "wof:name":"A To B Removals",
    "wof:placetype":"venue"
},
  "geometry": {"coordinates":[-3.29894,51.396832],"type":"Point"}
}