{
  "type": "Feature",
  "properties": {
    "addr:full":"26 Silver Street Whitby North Yorkshire YO21 3BU",
    "addr:housenumber":"26",
    "addr:postcode":"yo21 3bu",
    "addr:street":"Silver Street",
    "iso:country":"GB",
    "sg:address":"26 Silver Street",
    "sg:city":"Whitby",
    "sg:classifiers":[
        {
            "category":"Home & Garden",
            "subcategory":"Home Furnishings",
            "type":"Retail Goods"
        }
    ],
    "sg:phone":"+44 1947 605243",
    "sg:postcode":"YO21 3BU",
    "sg:province":"North Yorkshire",
    "sg:tags":[
        "furnishers",
        "planner",
        "kitchen"
    ],
    "wof:name":"Cottage Joinery Traditional Cabinet Co",
    "wof:placetype":"venue"
},
  "geometry": {"coordinates":[-0.616511,54.487072],"type":"Point"}
}