{
  "type": "Feature",
  "properties": {
    "addr:full":"165 Windmill Road Croydon Surrey CR0 2XT",
    "addr:housenumber":"165",
    "addr:postcode":"cr0 2xt",
    "addr:street":"Windmill Road",
    "iso:country":"GB",
    "sg:address":"165 Windmill Road",
    "sg:city":"Croydon",
    "sg:classifiers":[
        {
            "category":"Shopping",
            "type":"Retail Goods"
        }
    ],
    "sg:phone":"+44 20 8683 1871",
    "sg:postcode":"CR0 2XT",
    "sg:province":"Surrey",
    "sg:tags":[
        "part",
        "accessory"
    ],
    "wof:name":"Halfords",
    "wof:placetype":"venue"
},
  "geometry": {"coordinates":[-0.098071,51.386608],"type":"Point"}
}