{
  "type": "Feature",
  "properties": {
    "iso:country":"GB",
    "sg:address":"59a Causewayhead",
    "sg:city":"Penzance",
    "sg:classifiers":[
        {
            "category":"Shopping",
            "subcategory":"Discount & Variety Stores",
            "type":"Retail Goods"
        }
    ],
    "sg:phone":"+44 1736 360159",
    "sg:postcode":"TR18 2SS",
    "sg:province":"Cornwall",
    "sg:tags":[
        "centre"
    ],
    "wof:name":"Jims Cash & Carry",
    "wof:placetype":"venue"
},
  "geometry": {"coordinates":[-5.53836,50.119709],"type":"Point"}
}