{
  "type": "Feature",
  "properties": {
    "addr:full":"149 Rugby Rd Leamington Spa Warwickshire CV32 6DJ",
    "addr:housenumber":"149",
    "addr:postcode":"cv32 6dj",
    "addr:street":"Rugby Rd",
    "iso:country":"GB",
    "sg:address":"149 Rugby Rd",
    "sg:city":"Leamington Spa",
    "sg:classifiers":[
        {
            "category":"Personal",
            "type":"Services"
        }
    ],
    "sg:phone":"+44 1926 429884",
    "sg:postcode":"CV32 6DJ",
    "sg:province":"Warwickshire",
    "sg:tags":[
        "wedding"
    ],
    "wof:name":"Confetti Collection",
    "wof:placetype":"venue"
},
  "geometry": {"coordinates":[-1.5472550392,52.2928543091],"type":"Point"}
}