{
  "type": "Feature",
  "properties": {
    "addr:full":"Modern Ho, Summer La Barnsley South Yorkshire S70 2NP",
    "addr:postcode":"s70 2np",
    "addr:street":"Summer La Barnsley South",
    "iso:country":"GB",
    "sg:address":"Modern Ho, Summer La",
    "sg:city":"Barnsley",
    "sg:classifiers":[
        {
            "category":"Professional",
            "subcategory":"Employment Agencies",
            "type":"Services"
        }
    ],
    "sg:phone":"+44 1226 779900",
    "sg:postcode":"S70 2NP",
    "sg:province":"South Yorkshire",
    "sg:tags":[
        "recr",
        "hire",
        "driver"
    ],
    "wof:name":"Taskmaster (UK) Ltd",
    "wof:placetype":"venue"
},
  "geometry": {"coordinates":[-1.4847379923,53.5531921387],"type":"Point"}
}