{
  "type": "Feature",
  "properties": {
    "addr:full":"848 Leeds Road Bradford West Yorkshire BD3 9TU",
    "addr:housenumber":"848",
    "addr:postcode":"bd3 9tu",
    "addr:street":"Leeds Road",
    "iso:country":"GB",
    "sg:address":"848 Leeds Road",
    "sg:city":"Bradford",
    "sg:classifiers":[
        {
            "category":"Autos & Motor Vehicles",
            "subcategory":"Motorcycle Sales",
            "type":"Retail Goods"
        }
    ],
    "sg:postcode":"BD3 9TU",
    "sg:province":"West Yorkshire",
    "sg:tags":[
        "chauffeur",
        "driven",
        "car"
    ],
    "wof:name":"Autostyle Wedding Cars",
    "wof:placetype":"venue"
},
  "geometry": {"coordinates":[-1.727229,53.792278],"type":"Point"}
}