{
  "type": "Feature",
  "properties": {
    "addr:full":"Netherland House, Cargate Lane, Saxlingham Nethergate Norwich Norfolk NR15 1TS",
    "addr:postcode":"nr15 1ts",
    "addr:street":"Cargate Lane",
    "iso:country":"GB",
    "sg:address":"Netherland House, Cargate Lane, Saxlingham Nethergate",
    "sg:city":"Norwich",
    "sg:classifiers":[
        {
            "category":"Home & Garden",
            "subcategory":"Hardware",
            "type":"Retail Goods"
        }
    ],
    "sg:phone":"+44 1508 499587",
    "sg:postcode":"NR15 1TS",
    "sg:province":"Norfolk",
    "sg:tags":[
        "heat",
        "mech",
        "exchanger"
    ],
    "wof:name":"Secker & Son",
    "wof:placetype":"venue"
},
  "geometry": {"coordinates":[1.262622,52.534012],"type":"Point"}
}