{
  "type": "Feature",
  "properties": {
    "iso:country":"GB",
    "sg:address":"132 Grasmere Rd",
    "sg:city":"Ashford",
    "sg:classifiers":[
        {
            "category":"Social Services",
            "subcategory":"Job Training",
            "type":"Services"
        }
    ],
    "sg:phone":"+44 1233 626083",
    "sg:postcode":"TN24 9BQ",
    "sg:province":"Kent",
    "sg:tags":[
        "translator",
        "interpreter"
    ],
    "wof:name":"Business Translation Services",
    "wof:placetype":"venue"
},
  "geometry": {"coordinates":[0.879037,51.166134],"type":"Point"}
}