{
  "type": "Feature",
  "properties": {
    "iso:country":"GB",
    "sg:address":"6 Valley Bridge Parade",
    "sg:city":"Scarborough",
    "sg:classifiers":[
        {
            "category":"Personal",
            "subcategory":"Beauty Salon",
            "type":"Services"
        },
        {
            "category":"Personal",
            "subcategory":"Barber",
            "type":"Services"
        }
    ],
    "sg:phone":"+44 1723 366868",
    "sg:postcode":"YO11 2PF",
    "sg:province":"North Yorkshire",
    "sg:tags":[
        "unisex",
        "hairdresser"
    ],
    "wof:name":"Denise's",
    "wof:placetype":"venue"
},
  "geometry": {"coordinates":[-0.4038330019,54.2792243958],"type":"Point"}
}