{
  "type": "Feature",
  "properties": {
    "addr:full":"Mill Lane, Boroughbridge York North Yorkshire YO51 9LH",
    "addr:postcode":"yo51 9lh",
    "addr:street":"Mill Lane",
    "iso:country":"GB",
    "sg:address":"Mill Lane, Boroughbridge",
    "sg:city":"York",
    "sg:classifiers":[
        {
            "category":"Professional",
            "subcategory":"Engineering",
            "type":"Services"
        }
    ],
    "sg:postcode":"YO51 9LH",
    "sg:province":"North Yorkshire",
    "sg:tags":[
        "contractor",
        "electrical",
        "engineer"
    ],
    "wof:name":"Boroughbridge Electrical Co.",
    "wof:placetype":"venue"
},
  "geometry": {"coordinates":[-1.396873951,54.0972099304],"type":"Point"}
}