{
  "type": "Feature",
  "properties": {
    "addr:full":"15 Hitchin Street Biggleswade Bedfordshire SG18 8AX",
    "addr:housenumber":"15",
    "addr:postcode":"sg18 8ax",
    "addr:street":"Hitchin Street",
    "iso:country":"GB",
    "sg:address":"15 Hitchin Street",
    "sg:city":"Biggleswade",
    "sg:classifiers":[
        {
            "category":"Cafe",
            "type":"Food & Drink"
        }
    ],
    "sg:postcode":"SG18 8AX",
    "sg:province":"Bedfordshire",
    "sg:tags":[
        "tea",
        "room"
    ],
    "wof:name":"Cafe Sander's",
    "wof:placetype":"venue"
},
  "geometry": {"coordinates":[-0.2653029859,52.0857658386],"type":"Point"}
}