{
  "type": "Feature",
  "properties": {
    "iso:country":"GB",
    "sg:address":"1a Peveril Dr",
    "sg:city":"Nottingham",
    "sg:classifiers":[
        {
            "category":"Real Estate",
            "subcategory":"Architect",
            "type":"Services"
        }
    ],
    "sg:phone":"+44 115 941 3355",
    "sg:postcode":"NG7 1DE",
    "sg:province":"Nottinghamshire",
    "wof:name":"Nicholson Sir Charles Group",
    "wof:placetype":"venue"
},
  "geometry": {"coordinates":[-1.168982,52.960457],"type":"Point"}
}