{
  "type": "Feature",
  "properties": {
    "addr:full":"16 Brampton Court, Bowerhill Melksham Wiltshire SN12 6TH",
    "addr:housenumber":"16",
    "addr:postcode":"sn12 6th",
    "addr:street":"Brampton Court",
    "iso:country":"GB",
    "sg:address":"16 Brampton Court, Bowerhill",
    "sg:city":"Melksham",
    "sg:classifiers":[
        {
            "category":"Professional",
            "subcategory":"Computer Services",
            "type":"Services"
        }
    ],
    "sg:postcode":"SN12 6TH",
    "sg:province":"Wiltshire",
    "sg:tags":[
        "aided",
        "design"
    ],
    "wof:name":"Interface Systems Solutions Ltd",
    "wof:placetype":"venue"
},
  "geometry": {"coordinates":[-2.1251130104,51.3554344177],"type":"Point"}
}