{
  "type": "Feature",
  "properties": {
    "iso:country":"GB",
    "sg:address":"Blue Cedar Farm, Stoke St Michael",
    "sg:city":"Bath",
    "sg:classifiers":[
        {
            "category":"Farming",
            "subcategory":"Livestock Farm",
            "type":"Manufacturing & Wholesale Goods"
        }
    ],
    "sg:postcode":"BA3 5JY",
    "sg:province":"Somerset",
    "sg:tags":[
        "others"
    ],
    "wof:name":"Clive S Drew",
    "wof:placetype":"venue"
},
  "geometry": {"coordinates":[-2.47448,51.213181],"type":"Point"}
}