{
  "type": "Feature",
  "properties": {
    "addr:full":"50 Mansel Street Glasgow East Dunbartonshire G21 4JL",
    "addr:housenumber":"50",
    "addr:postcode":"g21 4jl",
    "addr:street":"Mansel Street",
    "iso:country":"GB",
    "sg:address":"50 Mansel Street",
    "sg:city":"Glasgow",
    "sg:classifiers":[
        {
            "category":"Education",
            "subcategory":"School",
            "type":"Public Place"
        },
        {
            "category":"Government",
            "subcategory":"Office",
            "type":"Public Place"
        }
    ],
    "sg:phone":"+44 141 558 1561",
    "sg:postcode":"G21 4JL",
    "sg:province":"East Dunbartonshire",
    "sg:tags":[
        "local",
        "authority"
    ],
    "wof:name":"Springburn Academy",
    "wof:placetype":"venue"
},
  "geometry": {"coordinates":[-4.225439,55.886787],"type":"Point"}
}