{
  "type": "Feature",
  "properties": {
    "iso:country":"GB",
    "sg:address":"234-236 London Road",
    "sg:city":"Portsmouth",
    "sg:classifiers":[
        {
            "category":"Food & Beverages",
            "subcategory":"Groceries & Convenience Stores",
            "type":"Retail Goods"
        }
    ],
    "sg:phone":"+44 23 9269 8332",
    "sg:postcode":"PO2 9JQ",
    "sg:province":"Hampshire",
    "wof:name":"Clements",
    "wof:placetype":"venue"
},
  "geometry": {"coordinates":[-1.075793,50.821281],"type":"Point"}
}