{
  "type": "Feature",
  "properties": {
    "iso:country":"GB",
    "sg:address":"37 Harbour Road",
    "sg:city":"Seaton",
    "sg:classifiers":[
        {
            "category":"Shopping",
            "subcategory":"Used Merchandise",
            "type":"Retail Goods"
        }
    ],
    "sg:phone":"+44 1297 23419",
    "sg:postcode":"EX12 2LX",
    "sg:province":"Devon",
    "sg:tags":[
        "shop",
        "second-hand"
    ],
    "wof:name":"This and That",
    "wof:placetype":"venue"
},
  "geometry": {"coordinates":[-3.068553,50.704239],"type":"Point"}
}