{
  "type": "Feature",
  "properties": {
    "addr:full":"Egginton Rd Derby Derbyshire DE65 5JD",
    "addr:postcode":"de65 5jd",
    "addr:street":"Egginton Rd",
    "iso:country":"GB",
    "sg:address":"Egginton Rd",
    "sg:city":"Derby",
    "sg:classifiers":[
        {
            "category":"Freight",
            "type":"Transportation"
        }
    ],
    "sg:phone":"+44 1283 734427",
    "sg:postcode":"DE65 5JD",
    "sg:province":"Derbyshire",
    "sg:tags":[
        "haulage",
        "road"
    ],
    "wof:name":"W F &",
    "wof:placetype":"venue"
},
  "geometry": {"coordinates":[-1.6294590235,52.8723182678],"type":"Point"}
}