{
  "type": "Feature",
  "properties": {
    "iso:country":"GB",
    "sg:address":"3 Duke Street",
    "sg:city":"Whitehaven",
    "sg:classifiers":[
        {
            "category":"Professional",
            "subcategory":"Lawyer & Legal Services",
            "type":"Services"
        }
    ],
    "sg:phone":"+44 1946 693321",
    "sg:postcode":"CA28 7EW",
    "sg:province":"Cumbria",
    "sg:tags":[
        "advice",
        "counselling"
    ],
    "wof:name":"Whitehaven Citizens Advice Bureau",
    "wof:placetype":"venue"
},
  "geometry": {"coordinates":[-3.588802,54.549938],"type":"Point"}
}