{
  "type": "Feature",
  "properties": {
    "iso:country":"GB",
    "sg:address":"123 Groveley Road",
    "sg:city":"Sunbury-on-thames",
    "sg:classifiers":[
        {
            "category":"Fast Food",
            "type":"Food & Drink"
        }
    ],
    "sg:phone":"+44 20 8890 2985",
    "sg:postcode":"TW16 7JZ",
    "sg:province":"Surrey",
    "sg:tags":[
        "away",
        "take"
    ],
    "wof:name":"Po-on Chinese",
    "wof:placetype":"venue"
},
  "geometry": {"coordinates":[-0.421312,51.429279],"type":"Point"}
}