{
  "type": "Feature",
  "properties": {
    "addr:full":"87 Cedric Rd Bath Bath and North East Somerset BA1 3PE",
    "addr:housenumber":"87",
    "addr:postcode":"ba1 3pe",
    "addr:street":"Cedric Rd",
    "iso:country":"GB",
    "sg:address":"87 Cedric Rd",
    "sg:city":"Bath",
    "sg:classifiers":[
        {
            "category":"Professional",
            "subcategory":"Engineering",
            "type":"Services"
        }
    ],
    "sg:phone":"+44 1225 336602",
    "sg:postcode":"BA1 3PE",
    "sg:province":"Bath and North East Somerset",
    "sg:tags":[
        "engineer"
    ],
    "wof:name":"D.J. Designs",
    "wof:placetype":"venue"
},
  "geometry": {"coordinates":[-2.387886,51.391483],"type":"Point"}
}