{
  "type": "Feature",
  "properties": {
    "addr:full":"289 Regents Park Road, Finchley London Greater London N3 3JY",
    "addr:housenumber":"289",
    "addr:postcode":"n3 3jy",
    "addr:street":"Regents Park Road",
    "iso:country":"GB",
    "sg:address":"289 Regents Park Road, Finchley",
    "sg:city":"London",
    "sg:classifiers":[
        {
            "category":"Building & Trades",
            "subcategory":"Cleaning & Sanitation",
            "type":"Services"
        }
    ],
    "sg:postcode":"N3 3JY",
    "sg:province":"Greater London",
    "sg:tags":[
        "dry",
        "control",
        "damp",
        "rot"
    ],
    "wof:name":"Olympic Preservation",
    "wof:placetype":"venue"
},
  "geometry": {"coordinates":[-0.19764,51.597958],"type":"Point"}
}