{
  "type": "Feature",
  "properties": {
    "iso:country":"GB",
    "sg:address":"78a Aylesbury Street, Wolverton",
    "sg:city":"Milton Keynes",
    "sg:classifiers":[
        {
            "category":"Home & Garden",
            "subcategory":"Household Appliances",
            "type":"Retail Goods"
        }
    ],
    "sg:phone":"+44 1908 223303",
    "sg:postcode":"MK12 5HU",
    "sg:province":"Buckinghamshire",
    "sg:tags":[
        "electrical"
    ],
    "wof:name":"Brampton Electrics",
    "wof:placetype":"venue"
},
  "geometry": {"coordinates":[-0.812835,52.060738],"type":"Point"}
}