{
  "type": "Feature",
  "properties": {
    "addr:full":"8 The Hordens, Barns Grn Horsham West Sussex RH13 0PJ",
    "addr:housenumber":"8",
    "addr:postcode":"rh13 0pj",
    "addr:street":"The Hordens Barns Grn",
    "iso:country":"GB",
    "sg:address":"8 The Hordens, Barns Grn",
    "sg:city":"Horsham",
    "sg:classifiers":[
        {
            "category":"Building & Trades",
            "subcategory":"Plumbing",
            "type":"Services"
        }
    ],
    "sg:postcode":"RH13 0PJ",
    "sg:province":"West Sussex",
    "sg:tags":[
        "heating"
    ],
    "wof:name":"Hall Engineering Services",
    "wof:placetype":"venue"
},
  "geometry": {"coordinates":[-0.3925470114,51.0314292908],"type":"Point"}
}