{
  "type": "Feature",
  "properties": {
    "addr:full":"2 Station Rd South Norwood Greater London SE25 5AJ",
    "addr:housenumber":"2",
    "addr:postcode":"se25 5aj",
    "addr:street":"Station Rd",
    "iso:country":"GB",
    "sg:address":"2 Station Rd",
    "sg:city":"South Norwood",
    "sg:classifiers":[
        {
            "category":"Food & Beverages",
            "subcategory":"Fruits & Vegetables",
            "type":"Retail Goods"
        }
    ],
    "sg:phone":"+44 20 8653 5834",
    "sg:postcode":"SE25 5AJ",
    "sg:province":"Greater London",
    "sg:tags":[
        "greengrocer"
    ],
    "wof:name":"John Stark & Sons",
    "wof:placetype":"venue"
},
  "geometry": {"coordinates":[-0.0767979994,51.3980178833],"type":"Point"}
}