{
  "type": "Feature",
  "properties": {
    "addr:full":"125 Hanbridge Avenue Newcastle Staffordshire ST5 8HX",
    "addr:housenumber":"125",
    "addr:postcode":"st5 8hx",
    "addr:street":"Hanbridge Avenue",
    "iso:country":"GB",
    "sg:address":"125 Hanbridge Avenue",
    "sg:city":"Newcastle",
    "sg:classifiers":[
        {
            "category":"Professional",
            "subcategory":"Business Services",
            "type":"Services"
        }
    ],
    "sg:phone":"+44 1782 613116",
    "sg:postcode":"ST5 8HX",
    "sg:province":"Staffordshire",
    "sg:tags":[
        "bookmaker"
    ],
    "wof:name":"Jack Cook Ltd.",
    "wof:placetype":"venue"
},
  "geometry": {"coordinates":[-2.2336189747,53.0411682129],"type":"Point"}
}