{
  "type": "Feature",
  "properties": {
    "iso:country":"GB",
    "sg:address":"Building 28a East Camp, R A F Sea Land",
    "sg:city":"Deeside",
    "sg:classifiers":[
        {
            "category":"Professional",
            "subcategory":"Engineering",
            "type":"Services"
        },
        {
            "category":"Building & Trades",
            "subcategory":"Construction",
            "type":"Services"
        },
        {
            "category":"Real Estate",
            "subcategory":"Architect",
            "type":"Services"
        }
    ],
    "sg:phone":"+44 1244 281532",
    "sg:postcode":"CH5 2LS",
    "sg:province":"Flintshire",
    "sg:tags":[
        "consulting",
        "builder",
        "engineer"
    ],
    "wof:name":"Atkins Decent",
    "wof:placetype":"venue"
},
  "geometry": {"coordinates":[-3.024987936,53.2024803162],"type":"Point"}
}