{
  "type": "Feature",
  "properties": {
    "iso:country":"GB",
    "sg:address":"Norland House, High Street",
    "sg:city":"Saundersfoot",
    "sg:classifiers":[
        {
            "category":"Recreation",
            "subcategory":"Fishing",
            "type":"Entertainment"
        }
    ],
    "sg:phone":"+44 1834 813115",
    "sg:postcode":"SA69 9EJ",
    "sg:province":"Pembrokeshire",
    "sg:tags":[
        "angling"
    ],
    "wof:name":"Bay Fishing Tackle",
    "wof:placetype":"venue"
},
  "geometry": {"coordinates":[-4.699805,51.711819],"type":"Point"}
}