{
  "type": "Feature",
  "properties": {
    "addr:full":"208 Well Street London Greater London E9 6QT",
    "addr:housenumber":"208",
    "addr:postcode":"e9 6qt",
    "addr:street":"Well Street",
    "iso:country":"GB",
    "sg:address":"208 Well Street",
    "sg:city":"London",
    "sg:classifiers":[
        {
            "category":"Personal",
            "subcategory":"Beauty Salon",
            "type":"Services"
        }
    ],
    "sg:phone":"+44 20 8985 1233",
    "sg:postcode":"E9 6QT",
    "sg:province":"Greater London",
    "sg:tags":[
        "unisex",
        "hairdresser"
    ],
    "wof:name":"Beauty Hi",
    "wof:placetype":"venue"
},
  "geometry": {"coordinates":[-0.0467110015,51.5442390442],"type":"Point"}
}