{
  "type": "Feature",
  "properties": {
    "iso:country":"GB",
    "sg:address":"West House, Redburn Road, Westerhope",
    "sg:city":"Newcastle-upon-tyne",
    "sg:classifiers":[
        {
            "category":"Professional",
            "subcategory":"Management & Consulting",
            "type":"Services"
        }
    ],
    "sg:phone":"+44 191 214 6621",
    "sg:postcode":"NE5 1NB",
    "sg:province":"Tyne and Wear",
    "sg:tags":[
        "consultant",
        "energy",
        "conservation"
    ],
    "wof:name":"Anthony E Grainger",
    "wof:placetype":"venue"
},
  "geometry": {"coordinates":[-1.69357,55.003262],"type":"Point"}
}