{
  "type": "Feature",
  "properties": {
    "addr:full":"1 Dubb Lane Bingley West Yorkshire BD16 2NW",
    "addr:housenumber":"1",
    "addr:postcode":"bd16 2nw",
    "addr:street":"Dubb Lane",
    "iso:country":"GB",
    "sg:address":"1 Dubb Lane",
    "sg:city":"Bingley",
    "sg:classifiers":[
        {
            "category":"Fast Food",
            "type":"Food & Drink"
        }
    ],
    "sg:phone":"+44 1274 510521",
    "sg:postcode":"BD16 2NW",
    "sg:province":"West Yorkshire",
    "sg:tags":[
        "away",
        "take"
    ],
    "wof:name":"The Spicey Hut",
    "wof:placetype":"venue"
},
  "geometry": {"coordinates":[-1.8348439932,53.8474960327],"type":"Point"}
}