{
  "type": "Feature",
  "properties": {
    "iso:country":"GB",
    "sg:address":"C/o Angstrom (fittings), Nettlehill Rd, Houstoun Indstl Est",
    "sg:city":"Livingston",
    "sg:postcode":"EH54 5DL",
    "sg:province":"West Lothian",
    "wof:name":"Heron Oil Tools Ltd",
    "wof:placetype":"venue"
},
  "geometry": {"coordinates":[-3.5098340511,55.8862457275],"type":"Point"}
}