{
  "type": "Feature",
  "properties": {
    "iso:country":"GB",
    "sg:address":"10 Arches Business Centre, Mill Road",
    "sg:city":"Rugby",
    "sg:classifiers":[
        {
            "category":"Manufacturing",
            "subcategory":"Signs",
            "type":"Manufacturing & Wholesale Goods"
        }
    ],
    "sg:postcode":"CV21 1QW",
    "sg:province":"Warwickshire",
    "sg:tags":[
        "commercial",
        "maker"
    ],
    "wof:name":"Allsign Rugby",
    "wof:placetype":"venue"
},
  "geometry": {"coordinates":[-1.24715,52.382889],"type":"Point"}
}