{
  "type": "Feature",
  "properties": {
    "iso:country":"GB",
    "sg:address":"Unit 7 Potters Lane, Kiln Farm",
    "sg:city":"Milton Keynes",
    "sg:classifiers":[
        {
            "category":"Food & Beverages",
            "subcategory":"Meat & Fish",
            "type":"Retail Goods"
        }
    ],
    "sg:postcode":"MK11 3HE",
    "sg:province":"Buckinghamshire",
    "sg:tags":[
        "merchant"
    ],
    "wof:name":"Atlantic Seafoods",
    "wof:placetype":"venue"
},
  "geometry": {"coordinates":[-0.819551,52.048046],"type":"Point"}
}