{
  "type": "Feature",
  "properties": {
    "addr:full":"Unit 7 Potters Lane, Kiln Farm Milton Keynes Buckinghamshire MK11 3HE",
    "addr:housenumber":"unit 7",
    "addr:postcode":"mk11 3he",
    "addr:street":"Potters Lane",
    "iso:country":"GB",
    "sg:address":"Unit 7 Potters Lane, Kiln Farm",
    "sg:city":"Milton Keynes",
    "sg:classifiers":[
        {
            "category":"Food & Beverages",
            "subcategory":"Meat & Fish",
            "type":"Retail Goods"
        }
    ],
    "sg:postcode":"MK11 3HE",
    "sg:province":"Buckinghamshire",
    "sg:tags":[
        "merchant"
    ],
    "wof:name":"Atlantic Seafoods",
    "wof:placetype":"venue"
},
  "geometry": {"coordinates":[-0.819551,52.048046],"type":"Point"}
}