{
  "type": "Feature",
  "properties": {
    "addr:full":"Ashbourne Road, Hurdlow Buxton Derbyshire SK17 9QQ",
    "addr:postcode":"sk17 9qq",
    "addr:street":"Ashbourne Road",
    "iso:country":"GB",
    "sg:address":"Ashbourne Road, Hurdlow",
    "sg:city":"Buxton",
    "sg:classifiers":[
        {
            "category":"Travel",
            "subcategory":"Hotels & Motels",
            "type":"Entertainment"
        }
    ],
    "sg:phone":"+44 1298 83348",
    "sg:postcode":"SK17 9QQ",
    "sg:province":"Derbyshire",
    "sg:tags":[
        "self",
        "catering"
    ],
    "wof:name":"The Bull I' Th' Thorn Inn",
    "wof:placetype":"venue"
},
  "geometry": {"coordinates":[-1.90412,53.246964],"type":"Point"}
}