{
  "type": "Feature",
  "properties": {
    "addr:full":"Unit A, Roften Ind Est, Hooton South Wirral Cheshire CH66 7NG",
    "addr:housenumber":"unit",
    "addr:postcode":"ch66 7ng",
    "addr:street":"South",
    "iso:country":"GB",
    "sg:address":"Unit A, Roften Ind Est, Hooton",
    "sg:city":"South Wirral",
    "sg:classifiers":[
        {
            "category":"Freight",
            "type":"Transportation"
        }
    ],
    "sg:phone":"+44 151 327 3515",
    "sg:postcode":"CH66 7NG",
    "sg:province":"Cheshire",
    "sg:tags":[
        "haulage",
        "road"
    ],
    "wof:name":"J.D Transport",
    "wof:placetype":"venue"
},
  "geometry": {"coordinates":[-2.9815900326,53.2954902649],"type":"Point"}
}