{
  "type": "Feature",
  "properties": {
    "addr:full":"481a High Road, Leytonstone London Greater London E11 4JU",
    "addr:housenumber":"481a",
    "addr:postcode":"e11 4ju",
    "addr:street":"High Road",
    "iso:country":"GB",
    "sg:address":"481a High Road, Leytonstone",
    "sg:city":"London",
    "sg:classifiers":[
        {
            "category":"Fast Food",
            "type":"Food & Drink"
        }
    ],
    "sg:postcode":"E11 4JU",
    "sg:province":"Greater London",
    "sg:tags":[
        "away",
        "take"
    ],
    "wof:name":"Eel Pie House",
    "wof:placetype":"venue"
},
  "geometry": {"coordinates":[0.0067500002,51.558139801],"type":"Point"}
}