{
  "type": "Feature",
  "properties": {
    "addr:full":"Unit 5, Cedar Park, Cobham Road Wimborne Dorset BH21 7SB",
    "addr:housenumber":"unit 5",
    "addr:postcode":"bh21 7sb",
    "addr:street":"Cobham Road",
    "iso:country":"GB",
    "sg:address":"Unit 5, Cedar Park, Cobham Road",
    "sg:city":"Wimborne",
    "sg:classifiers":[
        {
            "category":"Shopping",
            "subcategory":"Stationery & Office Supplies",
            "type":"Retail Goods"
        }
    ],
    "sg:phone":"+44 1202 896968",
    "sg:postcode":"BH21 7SB",
    "sg:province":"Dorset",
    "sg:tags":[
        "printers'"
    ],
    "wof:name":"Ultracoat",
    "wof:placetype":"venue"
},
  "geometry": {"coordinates":[-1.9887089729,50.8022346497],"type":"Point"}
}