{
  "type": "Feature",
  "properties": {
    "addr:full":"Unit, Centrovell Buildings, Centrovell Industrial Estate, Caldwell Road Nuneaton Leicestershire CV11 4NG",
    "addr:housenumber":"estate",
    "addr:postcode":"cv11 4ng",
    "addr:street":"Industrial;Caldwell Road",
    "iso:country":"GB",
    "sg:address":"Unit, Centrovell Buildings, Centrovell Industrial Estate, Caldwell Road",
    "sg:city":"Nuneaton",
    "sg:classifiers":[
        {
            "category":"Professional",
            "subcategory":"Accounting & Tax Preparation",
            "type":"Services"
        },
        {
            "category":"Communications",
            "subcategory":"News Services",
            "type":"Services"
        }
    ],
    "sg:phone":"+44 24 7634 6484",
    "sg:postcode":"CV11 4NG",
    "sg:province":"Leicestershire",
    "sg:tags":[
        "press",
        "pattern",
        "maker"
    ],
    "wof:name":"N P L Technologies Ltd.",
    "wof:placetype":"venue"
},
  "geometry": {"coordinates":[-1.4612109661,52.5090713501],"type":"Point"}
}