{
  "type": "Feature",
  "properties": {
    "iso:country":"GB",
    "sg:address":"Higher Garstang House Farm, Chapel Lane, Heapey",
    "sg:city":"Chorley",
    "sg:classifiers":[
        {
            "category":"Sports & Exercise",
            "subcategory":"Stables",
            "type":"Entertainment"
        }
    ],
    "sg:phone":"+44 1257 268801",
    "sg:postcode":"PR6 8TB",
    "sg:province":"Lancashire",
    "sg:tags":[
        "equestrian",
        "centre",
        "livery",
        "schools",
        "riding",
        "education"
    ],
    "wof:name":"Chorley Equestrian Centre",
    "wof:placetype":"venue"
},
  "geometry": {"coordinates":[-2.6062,53.680408],"type":"Point"}
}