{
  "type": "Feature",
  "properties": {
    "addr:full":"1 Butler Rd Halstead Essex CO9 1LL",
    "addr:housenumber":"1",
    "addr:postcode":"co9 1ll",
    "addr:street":"Butler Rd",
    "iso:country":"GB",
    "sg:address":"1 Butler Rd",
    "sg:city":"Halstead",
    "sg:classifiers":[
        {
            "category":"Building & Trades",
            "subcategory":"Construction",
            "type":"Services"
        }
    ],
    "sg:phone":"+44 1787 476953",
    "sg:postcode":"CO9 1LL",
    "sg:province":"Essex",
    "sg:tags":[
        "builder"
    ],
    "wof:name":"Avrabrook Ltd",
    "wof:placetype":"venue"
},
  "geometry": {"coordinates":[0.63324,51.943905],"type":"Point"}
}