{
  "type": "Feature",
  "properties": {
    "addr:full":"4 Liverpool Rd Newcastle Staffordshire ST5 2AT",
    "addr:housenumber":"4",
    "addr:postcode":"st5 2at",
    "addr:street":"Liverpool Rd",
    "iso:country":"GB",
    "sg:address":"4 Liverpool Rd",
    "sg:city":"Newcastle",
    "sg:classifiers":[
        {
            "category":"Shopping",
            "subcategory":"Music",
            "type":"Retail Goods"
        }
    ],
    "sg:phone":"+44 1782 712300",
    "sg:postcode":"ST5 2AT",
    "sg:province":"Staffordshire",
    "sg:tags":[
        "record",
        "tape",
        "cd"
    ],
    "wof:name":"Mike Lloyd Music",
    "wof:placetype":"venue"
},
  "geometry": {"coordinates":[-2.2293660641,53.012512207],"type":"Point"}
}