{
  "type": "Feature",
  "properties": {
    "iso:country":"GB",
    "sg:address":"10 Nicholas St",
    "sg:city":"Chester",
    "sg:classifiers":[
        {
            "category":"Banks & Credit Unions",
            "subcategory":"Financial Services",
            "type":"Services"
        }
    ],
    "sg:postcode":"CH1 2NX",
    "sg:province":"Cheshire",
    "sg:tags":[
        "consultant"
    ],
    "wof:name":"Mercator Finance Ltd",
    "wof:placetype":"venue"
},
  "geometry": {"coordinates":[-2.895164,53.189213],"type":"Point"}
}