{
  "type": "Feature",
  "properties": {
    "addr:full":"133 Hunts Pond Road, Park Gate Southampton Hampshire SO31 6RD",
    "addr:housenumber":"133",
    "addr:postcode":"so31 6rd",
    "addr:street":"Hunts Pond Road",
    "iso:country":"GB",
    "sg:address":"133 Hunts Pond Road, Park Gate",
    "sg:city":"Southampton",
    "sg:classifiers":[
        {
            "category":"Autos & Motor Vehicles",
            "subcategory":"Boat Sales",
            "type":"Retail Goods"
        }
    ],
    "sg:postcode":"SO31 6RD",
    "sg:province":"Hampshire",
    "sg:tags":[
        "repair",
        "builder"
    ],
    "wof:name":"Paint Systems (U K)",
    "wof:placetype":"venue"
},
  "geometry": {"coordinates":[-1.260905,50.863911],"type":"Point"}
}