{
  "type": "Feature",
  "properties": {
    "iso:country":"GB",
    "sg:address":"127 Percival Lane",
    "sg:city":"Runcorn",
    "sg:classifiers":[
        {
            "category":"Professional",
            "subcategory":"Detective & Security Services",
            "type":"Services"
        }
    ],
    "sg:phone":"+44 1928 561251",
    "sg:postcode":"WA7 4UY",
    "sg:province":"Cheshire",
    "wof:name":"Halton Security System",
    "wof:placetype":"venue"
},
  "geometry": {"coordinates":[-2.7447490692,53.3399391174],"type":"Point"}
}