{
  "type": "Feature",
  "properties": {
    "iso:country":"GB",
    "sg:address":"Canning Street, Cwm",
    "sg:city":"Ebbw Vale",
    "sg:classifiers":[
        {
            "category":"Community Center",
            "type":"Public Place"
        }
    ],
    "sg:phone":"+44 1495 371117",
    "sg:postcode":"NP3 6RH",
    "sg:province":"Blaenau Gwent",
    "sg:tags":[
        "centre"
    ],
    "wof:name":"Cwm Community Education Centre",
    "wof:placetype":"venue"
},
  "geometry": {"coordinates":[-3.2146799564,51.7970199585],"type":"Point"}
}