{
  "type": "Feature",
  "properties": {
    "addr:full":"22 Cooke Drive, Ipplepen Newton Abbot Devon TQ12 5QX",
    "addr:housenumber":"22",
    "addr:postcode":"tq12 5qx",
    "addr:street":"Cooke Drive",
    "iso:country":"GB",
    "sg:address":"22 Cooke Drive, Ipplepen",
    "sg:city":"Newton Abbot",
    "sg:classifiers":[
        {
            "category":"Building & Trades",
            "subcategory":"Construction",
            "type":"Services"
        }
    ],
    "sg:phone":"+44 1803 812638",
    "sg:postcode":"TQ12 5QX",
    "sg:province":"Devon",
    "sg:tags":[
        "roofing"
    ],
    "wof:name":"Abbey Roofing Company",
    "wof:placetype":"venue"
},
  "geometry": {"coordinates":[-3.6353309155,50.4880256653],"type":"Point"}
}