{
  "type": "Feature",
  "properties": {
    "iso:country":"GB",
    "sg:address":"729a Fishponds Road, Fishponds",
    "sg:city":"Bristol",
    "sg:classifiers":[
        {
            "category":"Professional",
            "subcategory":"Lawyer & Legal Services",
            "type":"Services"
        }
    ],
    "sg:phone":"+44 117 965 5366",
    "sg:postcode":"BS16 3UW",
    "sg:province":"City of Bristol",
    "sg:tags":[
        "solicitor"
    ],
    "wof:name":"Harnett & Co",
    "wof:placetype":"venue"
},
  "geometry": {"coordinates":[-2.529929,51.479996],"type":"Point"}
}