{
  "type": "Feature",
  "properties": {
    "addr:full":"6 Dryden Road Enfield Greater London EN1 2PP",
    "addr:housenumber":"6",
    "addr:postcode":"en1 2pp",
    "addr:street":"Dryden Road",
    "iso:country":"GB",
    "sg:address":"6 Dryden Road",
    "sg:city":"Enfield",
    "sg:classifiers":[
        {
            "category":"Social Services",
            "subcategory":"Retirement Home",
            "type":"Services"
        }
    ],
    "sg:phone":"+44 20 8360 3613",
    "sg:postcode":"EN1 2PP",
    "sg:province":"Greater London",
    "sg:tags":[
        "residential",
        "care"
    ],
    "wof:name":"Cedar House",
    "wof:placetype":"venue"
},
  "geometry": {"coordinates":[-0.0724190027,51.6408729553],"type":"Point"}
}