{
  "type": "Feature",
  "properties": {
    "addr:full":"Arcot Road, Tedworth Park Tidworth Hampshire SP9 7AH",
    "addr:postcode":"sp9 7ah",
    "addr:street":"Arcot Road Tedworth Park",
    "iso:country":"GB",
    "sg:address":"Arcot Road, Tedworth Park",
    "sg:city":"Tidworth",
    "sg:classifiers":[
        {
            "category":"Arena",
            "subcategory":"Sports Club",
            "type":"Entertainment"
        }
    ],
    "sg:phone":"+44 1980 846705",
    "sg:postcode":"SP9 7AH",
    "sg:province":"Hampshire",
    "wof:name":"Tidworth Polo Club",
    "wof:placetype":"venue"
},
  "geometry": {"coordinates":[-1.668089,51.225414],"type":"Point"}
}