{
  "type": "Feature",
  "properties": {
    "addr:full":"120 Darkes Lane Potters Bar Greater London EN6 1AE",
    "addr:housenumber":"120",
    "addr:postcode":"en6 1ae",
    "addr:street":"Darkes Lane",
    "iso:country":"GB",
    "sg:address":"120 Darkes Lane",
    "sg:city":"Potters Bar",
    "sg:classifiers":[
        {
            "category":"Personal",
            "subcategory":"Beauty Salon",
            "type":"Services"
        }
    ],
    "sg:phone":"+44 1707 662773",
    "sg:postcode":"EN6 1AE",
    "sg:province":"Greater London",
    "sg:tags":[
        "unisex",
        "hairdresser"
    ],
    "wof:name":"Kaos Hair Designers",
    "wof:placetype":"venue"
},
  "geometry": {"coordinates":[-0.1912399977,51.6981887817],"type":"Point"}
}