{
  "type": "Feature",
  "properties": {
    "addr:full":"1 Old Nichol Street London Greater London E2 7HR",
    "addr:housenumber":"1",
    "addr:postcode":"e2 7hr",
    "addr:street":"Old Nichol Street",
    "iso:country":"GB",
    "sg:address":"1 Old Nichol Street",
    "sg:city":"London",
    "sg:classifiers":[
        {
            "category":"Professional",
            "subcategory":"Computer Services",
            "type":"Services"
        }
    ],
    "sg:postcode":"E2 7HR",
    "sg:province":"Greater London",
    "sg:tags":[
        "system",
        "software"
    ],
    "wof:name":"Richardson Supply Co. Ltd.",
    "wof:placetype":"venue"
},
  "geometry": {"coordinates":[-0.073804,51.524796],"type":"Point"}
}