{
  "type": "Feature",
  "properties": {
    "addr:full":"Unit 5 Sharose Court, Hicks Road St Albans Hertfordshire AL3 8JH",
    "addr:housenumber":"unit 5",
    "addr:postcode":"al3 8jh",
    "addr:street":"Sharose Court Hicks Road",
    "iso:country":"GB",
    "sg:address":"Unit 5 Sharose Court, Hicks Road",
    "sg:city":"St Albans",
    "sg:classifiers":[
        {
            "category":"Home & Garden",
            "subcategory":"Household Appliances",
            "type":"Retail Goods"
        }
    ],
    "sg:postcode":"AL3 8JH",
    "sg:province":"Hertfordshire",
    "sg:tags":[
        "domestic",
        "electrical",
        "centre"
    ],
    "wof:name":"David Howgego",
    "wof:placetype":"venue"
},
  "geometry": {"coordinates":[-0.4536960125,51.837348938],"type":"Point"}
}