{
  "type": "Feature",
  "properties": {
    "addr:full":"Aston Fields Trading Estate Bromsgrove Worcestershire B60 3DN",
    "addr:postcode":"b60 3dn",
    "addr:street":"Aston;Trading Estate",
    "iso:country":"GB",
    "sg:address":"Aston Fields Trading Estate",
    "sg:city":"Bromsgrove",
    "sg:classifiers":[
        {
            "category":"Professional",
            "type":"Services"
        }
    ],
    "sg:phone":"+44 1633 871400",
    "sg:postcode":"B60 3DN",
    "sg:province":"Worcestershire",
    "sg:tags":[
        "shopfitters"
    ],
    "wof:name":"Creative Design & Management Ltd.",
    "wof:placetype":"venue"
},
  "geometry": {"coordinates":[-2.061869,52.317245],"type":"Point"}
}