{
  "type": "Feature",
  "properties": {
    "iso:country":"GB",
    "sg:address":"46 Park Rd",
    "sg:city":"Abingdon",
    "sg:classifiers":[
        {
            "category":"Health Services",
            "subcategory":"Health Practitioner",
            "type":"Services"
        }
    ],
    "sg:phone":"+44 1235 522386",
    "sg:postcode":"OX14 1DG",
    "sg:province":"Oxfordshire",
    "sg:tags":[
        "acupuncture"
    ],
    "wof:name":"S Tyack",
    "wof:placetype":"venue"
},
  "geometry": {"coordinates":[-1.2927930355,51.6712379456],"type":"Point"}
}