{
  "type": "Feature",
  "properties": {
    "addr:full":"7 Chadvil Rd, Gatley Cheadle Cheshire SK8 1NX",
    "addr:housenumber":"7",
    "addr:postcode":"sk8 1nx",
    "addr:street":"Chadvil Rd;Cheadle",
    "iso:country":"GB",
    "sg:address":"7 Chadvil Rd, Gatley",
    "sg:city":"Cheadle",
    "sg:classifiers":[
        {
            "category":"Building & Trades",
            "subcategory":"Construction",
            "type":"Services"
        }
    ],
    "sg:postcode":"SK8 1NX",
    "sg:province":"Cheshire",
    "sg:tags":[
        "builder"
    ],
    "wof:name":"Air-Conditioning Installations (U K) Ltd",
    "wof:placetype":"venue"
},
  "geometry": {"coordinates":[-2.22164011,53.3911552429],"type":"Point"}
}