{
  "type": "Feature",
  "properties": {
    "addr:full":"122 Queens Road East Grinstead East Sussex RH19 1BD",
    "addr:housenumber":"122",
    "addr:postcode":"rh19 1bd",
    "addr:street":"Queens Road",
    "iso:country":"GB",
    "sg:address":"122 Queens Road",
    "sg:city":"East Grinstead",
    "sg:classifiers":[
        {
            "category":"Shopping",
            "subcategory":"Bicycles & Sporting Goods",
            "type":"Retail Goods"
        }
    ],
    "sg:phone":"+44 1342 300162",
    "sg:postcode":"RH19 1BD",
    "sg:province":"East Sussex",
    "sg:tags":[
        "equipment",
        "leisure"
    ],
    "wof:name":"M & S Sub-Aqua Supplies Ltd.",
    "wof:placetype":"venue"
},
  "geometry": {"coordinates":[-0.013429,51.1236877441],"type":"Point"}
}