{
  "type": "Feature",
  "properties": {
    "addr:full":"Wilbraham Road Manchester Cheshire M21 0SA",
    "addr:postcode":"m21 0sa",
    "addr:street":"Wilbraham Road",
    "iso:country":"GB",
    "sg:address":"Wilbraham Road",
    "sg:city":"Manchester",
    "sg:classifiers":[
        {
            "category":"Autos & Motor Vehicles",
            "subcategory":"Fuel & Gas Station",
            "type":"Retail Goods"
        }
    ],
    "sg:phone":"+44 161 881 0714",
    "sg:postcode":"M21 0SA",
    "sg:province":"Cheshire",
    "sg:tags":[
        "hr",
        "petrol"
    ],
    "wof:name":"Aleef",
    "wof:placetype":"venue"
},
  "geometry": {"coordinates":[-2.276574,53.442524],"type":"Point"}
}