{
  "type": "Feature",
  "properties": {
    "iso:country":"GB",
    "sg:address":"62 Wavertree Road",
    "sg:city":"Liverpool",
    "sg:classifiers":[
        {
            "category":"Professional",
            "subcategory":"Art Services",
            "type":"Services"
        }
    ],
    "sg:phone":"+44 151 708 5121",
    "sg:postcode":"L7 1PH",
    "sg:province":"Merseyside",
    "sg:tags":[
        "picture",
        "framing"
    ],
    "wof:name":"Merseyside Framing & Arts Ltd",
    "wof:placetype":"venue"
},
  "geometry": {"coordinates":[-2.953425,53.404926],"type":"Point"}
}