{
  "type": "Feature",
  "properties": {
    "iso:country":"GB",
    "sg:address":"12 Woodside Rd, Simonstone",
    "sg:city":"Burnley",
    "sg:classifiers":[
        {
            "category":"Professional",
            "subcategory":"Computer Services",
            "type":"Services"
        }
    ],
    "sg:phone":"+44 1282 778771",
    "sg:postcode":"BB12 7JG",
    "sg:province":"Lancashire",
    "sg:tags":[
        "aided",
        "design"
    ],
    "wof:name":"3d Imaging",
    "wof:placetype":"venue"
},
  "geometry": {"coordinates":[-2.348265,53.808456],"type":"Point"}
}