{
  "type": "Feature",
  "properties": {
    "addr:full":"12 Forest Road Loughton Essex IG10 1DX",
    "addr:housenumber":"12",
    "addr:postcode":"ig10 1dx",
    "addr:street":"Forest Road",
    "iso:country":"GB",
    "sg:address":"12 Forest Road",
    "sg:city":"Loughton",
    "sg:classifiers":[
        {
            "category":"Restaurant",
            "type":"Food & Drink"
        }
    ],
    "sg:postcode":"IG10 1DX",
    "sg:province":"Essex",
    "sg:tags":[
        "indian"
    ],
    "wof:name":"Bengal Spice Ltd",
    "wof:placetype":"venue"
},
  "geometry": {"coordinates":[0.053526,51.64637],"type":"Point"}
}