{
  "type": "Feature",
  "properties": {
    "addr:full":"2 Nottingham Road Ilkeston Derbyshire DE7 5RE",
    "addr:housenumber":"2",
    "addr:postcode":"de7 5re",
    "addr:street":"Nottingham Road",
    "iso:country":"GB",
    "sg:address":"2 Nottingham Road",
    "sg:city":"Ilkeston",
    "sg:classifiers":[
        {
            "category":"Organizations",
            "subcategory":"Community Association",
            "type":"Services"
        },
        {
            "category":"Personal",
            "subcategory":"Nail Salon",
            "type":"Services"
        }
    ],
    "sg:phone":"+44 115 944 3710",
    "sg:postcode":"DE7 5RE",
    "sg:province":"Derbyshire",
    "sg:tags":[
        "solarium",
        "tanning",
        "related",
        "activity"
    ],
    "wof:name":"The Tanning Centre",
    "wof:placetype":"venue"
},
  "geometry": {"coordinates":[-1.3065199852,52.9675369263],"type":"Point"}
}