{
  "type": "Feature",
  "properties": {
    "addr:full":"59 Greengage Rise, Melbourn Royston Bedfordshire SG8 6DS",
    "addr:housenumber":"59",
    "addr:postcode":"sg8 6ds",
    "addr:street":"Greengage Rise",
    "iso:country":"GB",
    "sg:address":"59 Greengage Rise, Melbourn",
    "sg:city":"Royston",
    "sg:classifiers":[
        {
            "category":"Home & Garden",
            "subcategory":"Carpets & Floor Coverings",
            "type":"Retail Goods"
        }
    ],
    "sg:postcode":"SG8 6DS",
    "sg:province":"Bedfordshire",
    "sg:tags":[
        "cleaner",
        "upholstery"
    ],
    "wof:name":"Chris Thomas",
    "wof:placetype":"venue"
},
  "geometry": {"coordinates":[0.0184439998,52.0769767761],"type":"Point"}
}