{
  "type": "Feature",
  "properties": {
    "addr:full":"24 Muncaster Rd Ashford Greater London TW15 2HL",
    "addr:housenumber":"24",
    "addr:postcode":"tw15 2hl",
    "addr:street":"Muncaster Rd",
    "iso:country":"GB",
    "sg:address":"24 Muncaster Rd",
    "sg:city":"Ashford",
    "sg:classifiers":[
        {
            "category":"Building & Trades",
            "subcategory":"Construction",
            "type":"Services"
        }
    ],
    "sg:postcode":"TW15 2HL",
    "sg:province":"Greater London",
    "sg:tags":[
        "builder"
    ],
    "wof:name":"Winslade,B & E,",
    "wof:placetype":"venue"
},
  "geometry": {"coordinates":[-0.4519619942,51.4307594299],"type":"Point"}
}