{
  "type": "Feature",
  "properties": {
    "addr:full":"108 Green End Rd Bedford Bedfordshire MK44 3HD",
    "addr:housenumber":"108",
    "addr:postcode":"mk44 3hd",
    "addr:street":"Green End Rd",
    "iso:country":"GB",
    "sg:address":"108 Green End Rd",
    "sg:city":"Bedford",
    "sg:classifiers":[
        {
            "category":"Professional",
            "subcategory":"Business Services",
            "type":"Services"
        }
    ],
    "sg:phone":"+44 1234 870450",
    "sg:postcode":"MK44 3HD",
    "sg:province":"Bedfordshire",
    "sg:tags":[
        "broker",
        "commodity"
    ],
    "wof:name":"Atlas Market Strategies",
    "wof:placetype":"venue"
},
  "geometry": {"coordinates":[-0.3638620079,52.1603660583],"type":"Point"}
}