{
  "type": "Feature",
  "properties": {
    "addr:full":"The Cedars, 33 Windsor Street Chertsey Surrey KT16 8AT",
    "addr:housenumber":"33",
    "addr:postcode":"kt16 8at",
    "addr:street":"Windsor Street",
    "iso:country":"GB",
    "sg:address":"The Cedars, 33 Windsor Street",
    "sg:city":"Chertsey",
    "sg:classifiers":[
        {
            "category":"Museum",
            "subcategory":"Art Museum",
            "type":"Entertainment"
        },
        {
            "category":"Government",
            "subcategory":"Office",
            "type":"Public Place"
        }
    ],
    "sg:phone":"+44 1932 565764",
    "sg:postcode":"KT16 8AT",
    "sg:province":"Surrey",
    "sg:tags":[
        "local",
        "gallery"
    ],
    "wof:name":"Runnymede Borough Council",
    "wof:placetype":"venue"
},
  "geometry": {"coordinates":[-0.5082539916,51.3881988525],"type":"Point"}
}