{
  "type": "Feature",
  "properties": {
    "iso:country":"GB",
    "sg:address":"Willowbank",
    "sg:city":"Livingston",
    "sg:classifiers":[
        {
            "category":"Education",
            "subcategory":"School",
            "type":"Public Place"
        },
        {
            "category":"Government",
            "subcategory":"Office",
            "type":"Public Place"
        }
    ],
    "sg:phone":"+44 1506 434501",
    "sg:postcode":"EH54 6HN",
    "sg:province":"West Lothian",
    "sg:tags":[
        "local",
        "authority"
    ],
    "wof:name":"Harrysmuir Primary School",
    "wof:placetype":"venue"
},
  "geometry": {"coordinates":[-3.518662,55.901699],"type":"Point"}
}