{
  "type": "Feature",
  "properties": {
    "addr:full":"Teasdale Terrace Durham Durham DH1 2RN",
    "addr:postcode":"dh1 2rn",
    "addr:street":"Teasdale Terrace",
    "iso:country":"GB",
    "sg:address":"Teasdale Terrace",
    "sg:city":"Durham",
    "sg:classifiers":[
        {
            "category":"Travel",
            "subcategory":"Hotels & Motels",
            "type":"Entertainment"
        }
    ],
    "sg:phone":"+44 191 386 6453",
    "sg:postcode":"DH1 2RN",
    "sg:province":"Durham",
    "wof:name":"Gilesgate Moor Hotel",
    "wof:placetype":"venue"
},
  "geometry": {"coordinates":[-1.539904,54.778931],"type":"Point"}
}