{
  "type": "Feature",
  "properties": {
    "iso:country":"GB",
    "sg:address":"6 The Hart Centre, Fleet Road",
    "sg:city":"Fleet",
    "sg:classifiers":[
        {
            "category":"Shopping",
            "subcategory":"Catalog Store",
            "type":"Retail Goods"
        }
    ],
    "sg:phone":"+44 1252 812887",
    "sg:postcode":"GU51 3LA",
    "sg:province":"Hampshire",
    "sg:tags":[
        "catalogue",
        "showroom"
    ],
    "wof:name":"Argos Ltd.",
    "wof:placetype":"venue"
},
  "geometry": {"coordinates":[-0.830788,51.277771],"type":"Point"}
}