{
  "type": "Feature",
  "properties": {
    "iso:country":"GB",
    "sg:address":"Unit 3 Blackburn Industrial Estate, Enterprise Way",
    "sg:city":"Leeds",
    "sg:classifiers":[
        {
            "category":"Autos & Motor Vehicles",
            "subcategory":"Auto Supplies",
            "type":"Retail Goods"
        }
    ],
    "sg:phone":"+44 1977 681441",
    "sg:postcode":"LS25 6NF",
    "sg:province":"North Yorkshire",
    "sg:tags":[
        "car",
        "accessory"
    ],
    "wof:name":"Elmet Fascia & Design",
    "wof:placetype":"venue"
},
  "geometry": {"coordinates":[-1.22833,53.794849],"type":"Point"}
}