{
  "type": "Feature",
  "properties": {
    "iso:country":"GB",
    "sg:address":"Tompion House, Heaton Road",
    "sg:city":"Bradford",
    "sg:classifiers":[
        {
            "category":"Shopping",
            "subcategory":"Stationery & Office Supplies",
            "type":"Retail Goods"
        }
    ],
    "sg:phone":"+44 1274 497171",
    "sg:postcode":"BD8 8RB",
    "sg:province":"West Yorkshire",
    "sg:tags":[
        "recording",
        "machine",
        "time"
    ],
    "wof:name":"A G Thomas (Bradford) Ltd.",
    "wof:placetype":"venue"
},
  "geometry": {"coordinates":[-1.776834,53.80785],"type":"Point"}
}