{
  "type": "Feature",
  "properties": {
    "iso:country":"GB",
    "sg:address":"Eldon House, 12 Eldon Road",
    "sg:city":"Luton",
    "sg:classifiers":[
        {
            "category":"Professional",
            "subcategory":"Management & Consulting",
            "type":"Services"
        }
    ],
    "sg:phone":"+44 1582 492936",
    "sg:postcode":"LU4 0AU",
    "sg:province":"Bedfordshire",
    "sg:tags":[
        "consultant",
        "business"
    ],
    "wof:name":"Alexander Young Associates",
    "wof:placetype":"venue"
},
  "geometry": {"coordinates":[-0.472859,51.892395],"type":"Point"}
}