{
  "type": "Feature",
  "properties": {
    "iso:country":"GB",
    "sg:address":"71 Fernbank Ave, Huyton",
    "sg:city":"Liverpool",
    "sg:classifiers":[
        {
            "category":"Building & Trades",
            "subcategory":"Construction",
            "type":"Services"
        }
    ],
    "sg:postcode":"L36 9UD",
    "sg:province":"Merseyside",
    "sg:tags":[
        "decorator",
        "painter"
    ],
    "wof:name":"Faint,Chas,& Co",
    "wof:placetype":"venue"
},
  "geometry": {"coordinates":[-2.8477489948,53.4105911255],"type":"Point"}
}