{
  "type": "Feature",
  "properties": {
    "iso:country":"GB",
    "sg:address":"11 Long Acre",
    "sg:city":"London",
    "sg:classifiers":[
        {
            "category":"Professional",
            "subcategory":"Management & Consulting",
            "type":"Services"
        }
    ],
    "sg:phone":"+44 20 7240 6918",
    "sg:postcode":"WC2E 9LH",
    "sg:province":"Greater London",
    "sg:tags":[
        "consultant",
        "business"
    ],
    "wof:name":"Innova International Consultancy Ltd.",
    "wof:placetype":"venue"
},
  "geometry": {"coordinates":[-0.126266,51.512001],"type":"Point"}
}