{
  "type": "Feature",
  "properties": {
    "addr:full":"Green Lane, Horbury Junction Wakefield West Yorkshire WF4 5DY",
    "addr:postcode":"wf4 5dy",
    "addr:street":"Green Lane;West",
    "iso:country":"GB",
    "sg:address":"Green Lane, Horbury Junction",
    "sg:city":"Wakefield",
    "sg:classifiers":[
        {
            "category":"Wholesale",
            "subcategory":"Construction Materials",
            "type":"Manufacturing & Wholesale Goods"
        },
        {
            "category":"Building & Trades",
            "subcategory":"Construction",
            "type":"Services"
        }
    ],
    "sg:phone":"+44 1924 276064",
    "sg:postcode":"WF4 5DY",
    "sg:province":"West Yorkshire",
    "sg:tags":[
        "merchant",
        "stone",
        "demolition",
        "contractor"
    ],
    "wof:name":"Hirst Brothers (Properties) Ltd.",
    "wof:placetype":"venue"
},
  "geometry": {"coordinates":[-1.5447540283,53.6571159363],"type":"Point"}
}