{
  "type": "Feature",
  "properties": {
    "iso:country":"GB",
    "sg:address":"Suite 12 Ashford House, Beaufort Court",
    "sg:city":"Rochester",
    "sg:classifiers":[
        {
            "category":"Professional",
            "subcategory":"Management & Consulting",
            "type":"Services"
        }
    ],
    "sg:phone":"+44 1634 717771",
    "sg:postcode":"ME2 4FA",
    "sg:province":"Kent",
    "sg:tags":[
        "marketing",
        "consultant"
    ],
    "wof:name":"Clarrell International Ltd.",
    "wof:placetype":"venue"
},
  "geometry": {"coordinates":[0.51215,51.404209],"type":"Point"}
}