{
  "type": "Feature",
  "properties": {
    "addr:full":"Dolphin House, 3 North Street Guildford Surrey GU1 4AA",
    "addr:housenumber":"3",
    "addr:postcode":"gu1 4aa",
    "addr:street":"North Street",
    "iso:country":"GB",
    "sg:address":"Dolphin House, 3 North Street",
    "sg:city":"Guildford",
    "sg:classifiers":[
        {
            "category":"Communications",
            "type":"Services"
        }
    ],
    "sg:postcode":"GU1 4AA",
    "sg:province":"Surrey",
    "sg:tags":[
        "broadcasting"
    ],
    "wof:name":"County Sound Ltd.",
    "wof:placetype":"venue"
},
  "geometry": {"coordinates":[-0.574503,51.236408],"type":"Point"}
}