{
  "type": "Feature",
  "properties": {
    "iso:country":"GB",
    "sg:address":"Dolphin House, 3 North Street",
    "sg:city":"Guildford",
    "sg:classifiers":[
        {
            "category":"Communications",
            "type":"Services"
        }
    ],
    "sg:postcode":"GU1 4AA",
    "sg:province":"Surrey",
    "sg:tags":[
        "broadcasting"
    ],
    "wof:name":"County Sound Ltd.",
    "wof:placetype":"venue"
},
  "geometry": {"coordinates":[-0.574503,51.236408],"type":"Point"}
}