{
  "type": "Feature",
  "properties": {
    "addr:full":"Frog Lane, Great Bedwyn Marlborough Berkshire SN8 3LN",
    "addr:postcode":"sn8 3ln",
    "addr:street":"Frog Lane",
    "iso:country":"GB",
    "sg:address":"Frog Lane, Great Bedwyn",
    "sg:city":"Marlborough",
    "sg:classifiers":[
        {
            "category":"Social Services",
            "subcategory":"Adult Care",
            "type":"Services"
        }
    ],
    "sg:phone":"+44 1672 870179",
    "sg:postcode":"SN8 3LN",
    "sg:province":"Berkshire",
    "sg:tags":[
        "day",
        "centre"
    ],
    "wof:name":"Great Bedwyn Day Centre",
    "wof:placetype":"venue"
},
  "geometry": {"coordinates":[-1.5973039865,51.3793907166],"type":"Point"}
}