{
  "type": "Feature",
  "properties": {
    "iso:country":"GB",
    "sg:address":"Marlfields Hall, London Road",
    "sg:city":"Macclesfield",
    "sg:classifiers":[
        {
            "category":"Autos & Motor Vehicles",
            "subcategory":"Automobile Sales",
            "type":"Retail Goods"
        }
    ],
    "sg:postcode":"SK10 4NG",
    "sg:province":"Cheshire",
    "sg:tags":[
        "car"
    ],
    "wof:name":"Ashley Motor Co",
    "wof:placetype":"venue"
},
  "geometry": {"coordinates":[-2.1327700615,53.3310585022],"type":"Point"}
}