{
  "type": "Feature",
  "properties": {
    "iso:country":"GB",
    "sg:address":"Emesgate Lane, Silverdale",
    "sg:city":"Carnforth",
    "sg:classifiers":[
        {
            "category":"Cafe",
            "type":"Food & Drink"
        }
    ],
    "sg:postcode":"LA5 0RA",
    "sg:province":"Cumbria",
    "sg:tags":[
        "tea",
        "room"
    ],
    "wof:name":"Hedgerows Coffee House",
    "wof:placetype":"venue"
},
  "geometry": {"coordinates":[-2.826649,54.16748],"type":"Point"}
}