{
  "type": "Feature",
  "properties": {
    "iso:country":"GB",
    "sg:address":"24 Oakley Hill",
    "sg:city":"Wimborne",
    "sg:classifiers":[
        {
            "category":"Shopping",
            "subcategory":"Stationery & Office Supplies",
            "type":"Retail Goods"
        }
    ],
    "sg:phone":"+44 1202 883680",
    "sg:postcode":"BH21 1QH",
    "sg:province":"Dorset",
    "sg:tags":[
        "recording",
        "machine",
        "time"
    ],
    "wof:name":"Ole Olsen",
    "wof:placetype":"venue"
},
  "geometry": {"coordinates":[-1.9770519733,50.789226532],"type":"Point"}
}