{
  "type": "Feature",
  "properties": {
    "iso:country":"GB",
    "sg:address":"11 Walker Street, Hoylake",
    "sg:city":"Wirral",
    "sg:classifiers":[
        {
            "category":"Food & Beverages",
            "subcategory":"Bakery",
            "type":"Retail Goods"
        }
    ],
    "sg:postcode":"CH47 2DY",
    "sg:province":"Merseyside",
    "sg:tags":[
        "baker"
    ],
    "wof:name":"Malcolm's Bakery",
    "wof:placetype":"venue"
},
  "geometry": {"coordinates":[-3.1764500141,53.3945426941],"type":"Point"}
}