{
  "type": "Feature",
  "properties": {
    "addr:full":"Little Rough Park Close, Grayswood Haslemere Hampshire GU27 2DT",
    "addr:postcode":"hampshire gu27 2dt",
    "addr:street":"Park Close",
    "iso:country":"GB",
    "sg:address":"Little Rough Park Close, Grayswood",
    "sg:city":"Haslemere",
    "sg:classifiers":[
        {
            "category":"Professional",
            "subcategory":"Computer Services",
            "type":"Services"
        }
    ],
    "sg:phone":"+44 1428 656634",
    "sg:postcode":"GU27 2DT",
    "sg:province":"Hampshire",
    "sg:tags":[
        "system",
        "software"
    ],
    "wof:name":"Bishop Associates Ltd",
    "wof:placetype":"venue"
},
  "geometry": {"coordinates":[-0.7087240219,51.0887908936],"type":"Point"}
}