{
  "type": "Feature",
  "properties": {
    "addr:full":"692 Warwick Road Solihull West Midlands B91 3DX",
    "addr:housenumber":"692",
    "addr:postcode":"b91 3dx",
    "addr:street":"Warwick Road",
    "iso:country":"GB",
    "sg:address":"692 Warwick Road",
    "sg:city":"Solihull",
    "sg:classifiers":[
        {
            "category":"Professional",
            "subcategory":"Lawyer & Legal Services",
            "type":"Services"
        }
    ],
    "sg:phone":"+44 121 704 2525",
    "sg:postcode":"B91 3DX",
    "sg:province":"West Midlands",
    "sg:tags":[
        "solicitor"
    ],
    "wof:name":"Roland D W Evans",
    "wof:placetype":"venue"
},
  "geometry": {"coordinates":[-1.7761440277,52.4147338867],"type":"Point"}
}