{
  "type": "Feature",
  "properties": {
    "addr:full":"171 Roker Avenue Sunderland Tyne and Wear SR6 0HQ",
    "addr:housenumber":"171",
    "addr:postcode":"sr6 0hq",
    "addr:street":"Roker Avenue",
    "iso:country":"GB",
    "sg:address":"171 Roker Avenue",
    "sg:city":"Sunderland",
    "sg:classifiers":[
        {
            "category":"Personal",
            "subcategory":"Barber",
            "type":"Services"
        }
    ],
    "sg:phone":"+44 191 567 5800",
    "sg:postcode":"SR6 0HQ",
    "sg:province":"Tyne and Wear",
    "sg:tags":[
        "men's",
        "hairdresser"
    ],
    "wof:name":"P J's Barber Shop",
    "wof:placetype":"venue"
},
  "geometry": {"coordinates":[-1.3766599894,54.9159812927],"type":"Point"}
}