{
  "type": "Feature",
  "properties": {
    "addr:full":"119 Wainwright Street Birmingham West Midlands B6 5TG",
    "addr:housenumber":"119",
    "addr:postcode":"b6 5tg",
    "addr:street":"Wainwright Street",
    "iso:country":"GB",
    "sg:address":"119 Wainwright Street",
    "sg:city":"Birmingham",
    "sg:classifiers":[
        {
            "category":"Utilities",
            "subcategory":"Refuse",
            "type":"Services"
        }
    ],
    "sg:phone":"+44 121 327 1482",
    "sg:postcode":"B6 5TG",
    "sg:province":"West Midlands",
    "sg:tags":[
        "skip",
        "hire"
    ],
    "wof:name":"Michael Avery",
    "wof:placetype":"venue"
},
  "geometry": {"coordinates":[-1.8768520355,52.5001754761],"type":"Point"}
}