{
  "type": "Feature",
  "properties": {
    "addr:full":"Voscombe Farm, Lovacott, Newton Tracey Barnstaple Devon EX31 3QD",
    "addr:postcode":"ex31 3qd",
    "iso:country":"GB",
    "sg:address":"Voscombe Farm, Lovacott, Newton Tracey",
    "sg:city":"Barnstaple",
    "sg:classifiers":[
        {
            "category":"Farming",
            "subcategory":"Farm",
            "type":"Manufacturing & Wholesale Goods"
        }
    ],
    "sg:phone":"+44 1271 858207",
    "sg:postcode":"EX31 3QD",
    "sg:province":"Devon",
    "sg:tags":[
        "mixed",
        "crop"
    ],
    "wof:name":"S Johns",
    "wof:placetype":"venue"
},
  "geometry": {"coordinates":[-4.132459,51.069698],"type":"Point"}
}