{
  "type": "Feature",
  "properties": {
    "iso:country":"GB",
    "sg:address":"6 Valebrook Drive, Wybunbury",
    "sg:city":"Nantwich",
    "sg:classifiers":[
        {
            "category":"Retail",
            "subcategory":"Driving School",
            "type":"Services"
        }
    ],
    "sg:phone":"+44 1270 841682",
    "sg:postcode":"CW5 7LT",
    "sg:province":"Cheshire",
    "wof:name":"Alan's School of Motoring",
    "wof:placetype":"venue"
},
  "geometry": {"coordinates":[-2.460238,53.046131],"type":"Point"}
}