{
  "type": "Feature",
  "properties": {
    "iso:country":"GB",
    "sg:address":"Sancipher, Hillside",
    "sg:city":"Aberdeen",
    "sg:classifiers":[
        {
            "category":"Military Area",
            "subcategory":"Air Force Base",
            "type":"Public Place"
        }
    ],
    "sg:phone":"+44 1224 780158",
    "sg:postcode":"AB12 4RB",
    "sg:province":"Aberdeen City",
    "sg:tags":[
        "taxi",
        "hire",
        "private"
    ],
    "wof:name":"Leathan Taxis",
    "wof:placetype":"venue"
},
  "geometry": {"coordinates":[-2.12889,57.071419],"type":"Point"}
}