{
  "type": "Feature",
  "properties": {
    "iso:country":"GB",
    "sg:address":"13 Thorn Bank",
    "sg:city":"Guildford",
    "sg:classifiers":[
        {
            "category":"Personal",
            "type":"Services"
        }
    ],
    "sg:phone":"+44 1483 300303",
    "sg:postcode":"GU2 7PL",
    "sg:province":"Surrey",
    "sg:tags":[
        "wedding"
    ],
    "wof:name":"R L & J D Stockwell",
    "wof:placetype":"venue"
},
  "geometry": {"coordinates":[-0.593477,51.234047],"type":"Point"}
}