{
  "type": "Feature",
  "properties": {
    "addr:full":"24-26 Blacklands Way Abingdon Oxfordshire OX14 1DY",
    "addr:housenumber":"24-26",
    "addr:postcode":"ox14 1dy",
    "addr:street":"Blacklands Way",
    "iso:country":"GB",
    "sg:address":"24-26 Blacklands Way",
    "sg:city":"Abingdon",
    "sg:classifiers":[
        {
            "category":"Home & Garden",
            "subcategory":"Carpets & Floor Coverings",
            "type":"Retail Goods"
        },
        {
            "category":"Home & Garden",
            "subcategory":"Kitchen Supply",
            "type":"Retail Goods"
        }
    ],
    "sg:phone":"+44 1235 550420",
    "sg:postcode":"OX14 1DY",
    "sg:province":"Oxfordshire",
    "sg:tags":[
        "measuring",
        "scale",
        "manufacturer"
    ],
    "sg:website":"http://www.aandd-eu.net",
    "wof:name":"A & D Instruments Ltd",
    "wof:placetype":"venue"
},
  "geometry": {"coordinates":[-1.3026959896,51.6726760864],"type":"Point"}
}