{
  "type": "Feature",
  "properties": {
    "iso:country":"GB",
    "sg:address":"The Kings Centre, High St",
    "sg:city":"Aldershot",
    "sg:classifiers":[
        {
            "category":"Organizations",
            "subcategory":"Non-profit Organization",
            "type":"Services"
        }
    ],
    "sg:phone":"+44 1252 333233",
    "sg:postcode":"GU11 1DJ",
    "sg:province":"Hampshire",
    "sg:tags":[
        "organisation",
        "voluntary",
        "charity"
    ],
    "wof:name":"Kingscare",
    "wof:placetype":"venue"
},
  "geometry": {"coordinates":[-0.759346,51.249603],"type":"Point"}
}