{
  "type": "Feature",
  "properties": {
    "iso:country":"GB",
    "sg:address":"70 Church St",
    "sg:city":"Seaham",
    "sg:classifiers":[
        {
            "category":"Wholesale",
            "subcategory":"Toys & Hobbies",
            "type":"Manufacturing & Wholesale Goods"
        }
    ],
    "sg:phone":"+44 191 513 0203",
    "sg:postcode":"SR7 7HE",
    "sg:province":"Durham",
    "sg:tags":[
        "balloon",
        "novelty"
    ],
    "wof:name":"Dickie Dido's",
    "wof:placetype":"venue"
},
  "geometry": {"coordinates":[-1.331581,54.837151],"type":"Point"}
}