{
  "type": "Feature",
  "properties": {
    "addr:full":"4 Birdcage Walk Newmarket Cambridgeshire CB8 0NE",
    "addr:housenumber":"4",
    "addr:postcode":"cb8 0ne",
    "addr:street":"Birdcage Walk Newmarket",
    "iso:country":"GB",
    "sg:address":"4 Birdcage Walk",
    "sg:city":"Newmarket",
    "sg:classifiers":[
        {
            "category":"Building & Trades",
            "subcategory":"Construction",
            "type":"Services"
        }
    ],
    "sg:phone":"+44 1638 661955",
    "sg:postcode":"CB8 0NE",
    "sg:province":"Cambridgeshire",
    "sg:tags":[
        "builder"
    ],
    "wof:name":"Ken Hammond",
    "wof:placetype":"venue"
},
  "geometry": {"coordinates":[0.3969340026,52.2407951355],"type":"Point"}
}