{
  "type": "Feature",
  "properties": {
    "addr:full":"213 Bexley Road Erith Kent DA8 3EU",
    "addr:housenumber":"213",
    "addr:postcode":"da8 3eu",
    "addr:street":"Bexley Road",
    "iso:country":"GB",
    "sg:address":"213 Bexley Road",
    "sg:city":"Erith",
    "sg:classifiers":[
        {
            "category":"Personal",
            "subcategory":"Barber",
            "type":"Services"
        }
    ],
    "sg:phone":"+44 1322 332872",
    "sg:postcode":"DA8 3EU",
    "sg:province":"Kent",
    "sg:tags":[
        "men's",
        "hairdresser"
    ],
    "wof:name":"Peters",
    "wof:placetype":"venue"
},
  "geometry": {"coordinates":[0.1629099995,51.4752006531],"type":"Point"}
}