{
  "type": "Feature",
  "properties": {
    "addr:full":"5 High Street, Woodville Swadlincote Derbyshire DE11 7EH",
    "addr:housenumber":"5",
    "addr:postcode":"de11 7eh",
    "addr:street":"High Street",
    "iso:country":"GB",
    "sg:address":"5 High Street, Woodville",
    "sg:city":"Swadlincote",
    "sg:classifiers":[
        {
            "category":"Deli",
            "type":"Food & Drink"
        },
        {
            "category":"Food & Beverages",
            "subcategory":"Supermarket",
            "type":"Retail Goods"
        }
    ],
    "sg:phone":"+44 1283 217094",
    "sg:postcode":"DE11 7EH",
    "sg:province":"Derbyshire",
    "sg:tags":[
        "delicatessen"
    ],
    "wof:name":"Tollgate Provisions",
    "wof:placetype":"venue"
},
  "geometry": {"coordinates":[-1.533999,52.769146],"type":"Point"}
}