{
  "type": "Feature",
  "properties": {
    "addr:full":"17 Townsend, Wylye Warminster Somerset BA12 0RZ",
    "addr:housenumber":"17;wylye",
    "addr:postcode":"ba12 0rz",
    "addr:street":"Townsend",
    "iso:country":"GB",
    "sg:address":"17 Townsend, Wylye",
    "sg:city":"Warminster",
    "sg:classifiers":[
        {
            "category":"Building & Trades",
            "subcategory":"Construction",
            "type":"Services"
        }
    ],
    "sg:postcode":"BA12 0RZ",
    "sg:province":"Somerset",
    "sg:tags":[
        "roofing"
    ],
    "wof:name":"David Ford Felt Roofing Specialists",
    "wof:placetype":"venue"
},
  "geometry": {"coordinates":[-2.0870959759,51.1775474548],"type":"Point"}
}