{
  "type": "Feature",
  "properties": {
    "iso:country":"GB",
    "sg:address":"65 Henton Road",
    "sg:city":"Leicester",
    "sg:classifiers":[
        {
            "category":"Manufacturing",
            "subcategory":"Tools & Machinery",
            "type":"Manufacturing & Wholesale Goods"
        },
        {
            "category":"Home & Garden",
            "subcategory":"Hardware",
            "type":"Retail Goods"
        }
    ],
    "sg:phone":"+44 116 253 0346",
    "sg:postcode":"LE3 6AY",
    "sg:province":"Leicestershire",
    "sg:tags":[
        "merchant",
        "ironmonger"
    ],
    "wof:name":"H Roberts & Sons (Dial Indicators) Ltd.",
    "wof:placetype":"venue"
},
  "geometry": {"coordinates":[-1.157453,52.633938],"type":"Point"}
}