{
  "type": "Feature",
  "properties": {
    "addr:full":"Thorns Road, Quarry Bank Brierley Hill West Midlands DY5 2JY",
    "addr:postcode":"dy5 2jy",
    "addr:street":"Thorns Road;Brierley Hill",
    "iso:country":"GB",
    "sg:address":"Thorns Road, Quarry Bank",
    "sg:city":"Brierley Hill",
    "sg:classifiers":[
        {
            "category":"Bars & Pubs",
            "type":"Food & Drink"
        }
    ],
    "sg:phone":"+44 1384 423696",
    "sg:postcode":"DY5 2JY",
    "sg:province":"West Midlands",
    "sg:tags":[
        "pubs",
        "house",
        "inn",
        "public",
        "activity"
    ],
    "wof:name":"The Thorns Inn",
    "wof:placetype":"venue"
},
  "geometry": {"coordinates":[-2.110864,52.470692],"type":"Point"}
}