{
  "type": "Feature",
  "properties": {
    "iso:country":"GB",
    "sg:address":"7 The Thoroughfare",
    "sg:city":"Woodbridge",
    "sg:classifiers":[
        {
            "category":"Retail",
            "subcategory":"Portrait Studio",
            "type":"Services"
        },
        {
            "category":"Professional",
            "subcategory":"Art Services",
            "type":"Services"
        }
    ],
    "sg:phone":"+44 1394 384666",
    "sg:postcode":"IP12 1AA",
    "sg:province":"Suffolk",
    "sg:tags":[
        "photographer",
        "commercial"
    ],
    "wof:name":"Spike Powell Photographers",
    "wof:placetype":"venue"
},
  "geometry": {"coordinates":[1.329952,52.105267],"type":"Point"}
}