{
  "type": "Feature",
  "properties": {
    "addr:full":"3 Cromer Rd Tottenham Greater London N17 9RX",
    "addr:housenumber":"3",
    "addr:postcode":"n17 9rx",
    "addr:street":"Cromer Rd",
    "iso:country":"GB",
    "sg:address":"3 Cromer Rd",
    "sg:city":"Tottenham",
    "sg:classifiers":[
        {
            "category":"Shopping",
            "subcategory":"Mobile Phones",
            "type":"Retail Goods"
        }
    ],
    "sg:phone":"+44 20 8808 1102",
    "sg:postcode":"N17 9RX",
    "sg:province":"Greater London",
    "wof:name":"Well Connected",
    "wof:placetype":"venue"
},
  "geometry": {"coordinates":[-0.06445,51.596584],"type":"Point"}
}