{
  "type": "Feature",
  "properties": {
    "iso:country":"GB",
    "sg:address":"308 Linthorpe Road",
    "sg:city":"Middlesbrough",
    "sg:classifiers":[
        {
            "category":"Personal",
            "subcategory":"Beauty Salon",
            "type":"Services"
        }
    ],
    "sg:phone":"+44 1642 890111",
    "sg:postcode":"TS1 3QX",
    "sg:province":"North Yorkshire",
    "wof:name":"Phoenix Health & Beauty Clinic",
    "wof:placetype":"venue"
},
  "geometry": {"coordinates":[-1.239725,54.567368],"type":"Point"}
}