{
  "type": "Feature",
  "properties": {
    "iso:country":"GB",
    "sg:address":"Derby Road, Stapleford",
    "sg:city":"Nottingham",
    "sg:classifiers":[
        {
            "category":"Food & Beverages",
            "subcategory":"Liquor & Beverages",
            "type":"Retail Goods"
        }
    ],
    "sg:phone":"+44 115 949 9810",
    "sg:postcode":"NG9 7AN",
    "sg:province":"Nottinghamshire",
    "sg:tags":[
        "beer",
        "spirit",
        "wines"
    ],
    "wof:name":"Victoria Wine",
    "wof:placetype":"venue"
},
  "geometry": {"coordinates":[-1.275307,52.929298],"type":"Point"}
}