{
  "type": "Feature",
  "properties": {
    "addr:full":"22 Powis Terrace Notting Hill Greater London W11 1JH",
    "addr:housenumber":"22",
    "addr:postcode":"w11 1jh",
    "addr:street":"Powis Terrace",
    "iso:country":"GB",
    "sg:address":"22 Powis Terrace",
    "sg:city":"Notting Hill",
    "sg:classifiers":[
        {
            "category":"Manufacturing",
            "subcategory":"Apparel",
            "type":"Manufacturing & Wholesale Goods"
        }
    ],
    "sg:phone":"+44 20 7460 3216",
    "sg:postcode":"W11 1JH",
    "sg:province":"Greater London",
    "sg:tags":[
        "garment",
        "designer"
    ],
    "wof:name":"Sam De Trean",
    "wof:placetype":"venue"
},
  "geometry": {"coordinates":[-0.2013660073,51.5170021057],"type":"Point"}
}