{
  "type": "Feature",
  "properties": {
    "addr:full":"12a Lochend Rd South Edinburgh City of Edinburgh EH7 6BP",
    "addr:housenumber":"12a",
    "addr:postcode":"eh7 6bp",
    "addr:street":"Lochend Rd South Edinburgh",
    "iso:country":"GB",
    "sg:address":"12a Lochend Rd South",
    "sg:city":"Edinburgh",
    "sg:classifiers":[
        {
            "category":"Shopping",
            "subcategory":"Department Store",
            "type":"Retail Goods"
        },
        {
            "category":"Food & Beverages",
            "subcategory":"Supermarket",
            "type":"Retail Goods"
        }
    ],
    "sg:postcode":"EH7 6BP",
    "sg:province":"City of Edinburgh",
    "wof:name":"Sattar,A,",
    "wof:placetype":"venue"
},
  "geometry": {"coordinates":[-3.1584100723,55.9608421326],"type":"Point"}
}