{
  "type": "Feature",
  "properties": {
    "addr:full":"39 Eastbourne Rd Middlesbrough North Yorkshire TS5 6QN",
    "addr:housenumber":"39",
    "addr:postcode":"ts5 6qn",
    "addr:street":"Eastbourne Rd",
    "iso:country":"GB",
    "sg:address":"39 Eastbourne Rd",
    "sg:city":"Middlesbrough",
    "sg:classifiers":[
        {
            "category":"Health Services",
            "subcategory":"Dentist",
            "type":"Services"
        }
    ],
    "sg:phone":"+44 1642 850644",
    "sg:postcode":"TS5 6QN",
    "sg:province":"North Yorkshire",
    "wof:name":"A Clay",
    "wof:placetype":"venue"
},
  "geometry": {"coordinates":[-1.234747,54.557362],"type":"Point"}
}