{
  "type": "Feature",
  "properties": {
    "iso:country":"GB",
    "sg:address":"Rospeath La",
    "sg:city":"Penzance",
    "sg:classifiers":[
        {
            "category":"Wholesale",
            "subcategory":"Scrap",
            "type":"Manufacturing & Wholesale Goods"
        }
    ],
    "sg:phone":"+44 1736 741070",
    "sg:postcode":"TR20 8DU",
    "sg:province":"Cornwall",
    "sg:tags":[
        "waste",
        "metal"
    ],
    "wof:name":"Drews",
    "wof:placetype":"venue"
},
  "geometry": {"coordinates":[-5.479103,50.145187],"type":"Point"}
}