{
  "type": "Feature",
  "properties": {
    "addr:full":"Osbaldwick Link Road, Osbaldwick York North Yorkshire YO10 3WA",
    "addr:postcode":"yo10 3wa",
    "addr:street":"Osbaldwick Link Road",
    "iso:country":"GB",
    "sg:address":"Osbaldwick Link Road, Osbaldwick",
    "sg:city":"York",
    "sg:classifiers":[
        {
            "category":"Home & Garden",
            "subcategory":"Home Furnishings",
            "type":"Retail Goods"
        }
    ],
    "sg:phone":"+44 1904 415222",
    "sg:postcode":"YO10 3WA",
    "sg:province":"North Yorkshire",
    "sg:tags":[
        "furnishers",
        "planner",
        "kitchen"
    ],
    "wof:name":"Smith Brothers (York) Ltd.",
    "wof:placetype":"venue"
},
  "geometry": {"coordinates":[-1.0248889923,53.9545288086],"type":"Point"}
}