{
  "type": "Feature",
  "properties": {
    "iso:country":"GB",
    "sg:address":"13 High Street",
    "sg:city":"Windsor",
    "sg:classifiers":[
        {
            "category":"Professional",
            "subcategory":"Research",
            "type":"Services"
        }
    ],
    "sg:phone":"+44 1753 271400",
    "sg:postcode":"SL4 1LD",
    "sg:province":"Berkshire",
    "sg:tags":[
        "organisation",
        "market"
    ],
    "wof:name":"Leapfrog Research & Planning Ltd",
    "wof:placetype":"venue"
},
  "geometry": {"coordinates":[-0.6067939997,51.4815292358],"type":"Point"}
}