{
  "type": "Feature",
  "properties": {
    "addr:full":"Phoenix House, 1-3 Newhall St Birmingham West Midlands B3 3NH",
    "addr:housenumber":"1-3",
    "addr:postcode":"b3 3nh",
    "addr:street":"Newhall St",
    "iso:country":"GB",
    "sg:address":"Phoenix House, 1-3 Newhall St",
    "sg:city":"Birmingham",
    "sg:classifiers":[
        {
            "category":"Professional",
            "subcategory":"Employment Agencies",
            "type":"Services"
        }
    ],
    "sg:phone":"+44 121 607 5757",
    "sg:postcode":"B3 3NH",
    "sg:province":"West Midlands",
    "sg:tags":[
        "consultant"
    ],
    "wof:name":"Computer Futures",
    "wof:placetype":"venue"
},
  "geometry": {"coordinates":[-1.9009859562,52.4810295105],"type":"Point"}
}