{
  "type": "Feature",
  "properties": {
    "addr:full":"7-15 Wellington New Road Taunton Somerset TA1 5LU",
    "addr:housenumber":"7-15",
    "addr:postcode":"ta1 5lu",
    "addr:street":"Wellington New Road",
    "iso:country":"GB",
    "sg:address":"7-15 Wellington New Road",
    "sg:city":"Taunton",
    "sg:classifiers":[
        {
            "category":"Professional",
            "subcategory":"Detective & Security Services",
            "type":"Services"
        }
    ],
    "sg:postcode":"TA1 5LU",
    "sg:province":"Somerset",
    "sg:tags":[
        "car"
    ],
    "wof:name":"Carshop",
    "wof:placetype":"venue"
},
  "geometry": {"coordinates":[-3.1261689663,51.0130805969],"type":"Point"}
}