{
  "type": "Feature",
  "properties": {
    "addr:full":"Bradfield Road, Hillsborough Sheffield South Yorkshire S6 2BZ",
    "addr:postcode":"s6 2bz",
    "addr:street":"Bradfield Road",
    "iso:country":"GB",
    "sg:address":"Bradfield Road, Hillsborough",
    "sg:city":"Sheffield",
    "sg:classifiers":[
        {
            "category":"Retail",
            "subcategory":"Auto Repair",
            "type":"Services"
        }
    ],
    "sg:phone":"+44 114 232 5064",
    "sg:postcode":"S6 2BZ",
    "sg:province":"South Yorkshire",
    "sg:tags":[
        "modification",
        "garage"
    ],
    "wof:name":"Lex Autocentres",
    "wof:placetype":"venue"
},
  "geometry": {"coordinates":[-1.4986640215,53.4038696289],"type":"Point"}
}