{
  "type": "Feature",
  "properties": {
    "addr:full":"Rook Lane, Chaldon Caterham Surrey CR3 5AA",
    "addr:postcode":"cr3 5aa",
    "addr:street":"Rook Lane",
    "iso:country":"GB",
    "sg:address":"Rook Lane, Chaldon",
    "sg:city":"Caterham",
    "sg:classifiers":[
        {
            "category":"Sports & Exercise",
            "subcategory":"Golf",
            "type":"Entertainment"
        }
    ],
    "sg:phone":"+44 1883 344555",
    "sg:postcode":"CR3 5AA",
    "sg:province":"Surrey",
    "sg:tags":[
        "course",
        "club"
    ],
    "wof:name":"Surrey National Golf Club Ltd.",
    "wof:placetype":"venue"
},
  "geometry": {"coordinates":[-0.1022650003,51.2820167542],"type":"Point"}
}