{
  "type": "Feature",
  "properties": {
    "addr:full":"50 Kinmel Street Rhyl Conwy LL18 1AW",
    "addr:housenumber":"50",
    "addr:postcode":"ll18 1aw",
    "addr:street":"Kinmel Street",
    "iso:country":"GB",
    "sg:address":"50 Kinmel Street",
    "sg:city":"Rhyl",
    "sg:classifiers":[
        {
            "category":"Manufacturing",
            "subcategory":"Tools & Machinery",
            "type":"Manufacturing & Wholesale Goods"
        },
        {
            "category":"Insurance",
            "subcategory":"Insurance Agent",
            "type":"Services"
        }
    ],
    "sg:phone":"+44 1745 339009",
    "sg:postcode":"LL18 1AW",
    "sg:province":"Conwy",
    "sg:tags":[
        "society",
        "friendly"
    ],
    "wof:name":"Anchor Insurance Services",
    "wof:placetype":"venue"
},
  "geometry": {"coordinates":[-3.488784,53.319527],"type":"Point"}
}