{
  "type": "Feature",
  "properties": {
    "addr:full":"The Grange, The Street, Yatton Keynell Chippenham Gloucestershire SN14 7BA",
    "addr:postcode":"sn14 7ba",
    "addr:street":"The Street",
    "iso:country":"GB",
    "sg:address":"The Grange, The Street, Yatton Keynell",
    "sg:city":"Chippenham",
    "sg:classifiers":[
        {
            "category":"Professional",
            "subcategory":"Accounting & Tax Preparation",
            "type":"Services"
        }
    ],
    "sg:phone":"+44 1249 783555",
    "sg:postcode":"SN14 7BA",
    "sg:province":"Gloucestershire",
    "sg:tags":[
        "accountant",
        "activity"
    ],
    "wof:name":"J W Swales & Co Ltd",
    "wof:placetype":"venue"
},
  "geometry": {"coordinates":[-2.268149,51.514595],"type":"Point"}
}