{
  "type": "Feature",
  "properties": {
    "addr:full":"23 Winter Road Norwich Norfolk NR2 3RR",
    "addr:housenumber":"23",
    "addr:postcode":"nr2 3rr",
    "addr:street":"Winter Road Norwich Norfolk",
    "iso:country":"GB",
    "sg:address":"23 Winter Road",
    "sg:city":"Norwich",
    "sg:classifiers":[
        {
            "category":"Building & Trades",
            "subcategory":"Plumbing",
            "type":"Services"
        }
    ],
    "sg:phone":"+44 1603 664533",
    "sg:postcode":"NR2 3RR",
    "sg:province":"Norfolk",
    "sg:tags":[
        "plumber",
        "heating"
    ],
    "wof:name":"D R Turner Plumbing & Heating",
    "wof:placetype":"venue"
},
  "geometry": {"coordinates":[1.2707489729,52.631778717],"type":"Point"}
}