{
  "type": "Feature",
  "properties": {
    "iso:country":"GB",
    "sg:address":"East Road",
    "sg:city":"Harlow",
    "sg:classifiers":[
        {
            "category":"Professional",
            "subcategory":"Engineering",
            "type":"Services"
        }
    ],
    "sg:postcode":"CM20 2BJ",
    "sg:province":"Essex",
    "sg:tags":[
        "precision",
        "engineer"
    ],
    "wof:name":"Inflite Engineering Services Ltd.",
    "wof:placetype":"venue"
},
  "geometry": {"coordinates":[0.1242789999,51.7847442627],"type":"Point"}
}