{
  "type": "Feature",
  "properties": {
    "addr:full":"10-11 New Market Walk Merthyr Tydfil Merthyr Tydfil CF47 8EL",
    "addr:housenumber":"10-11",
    "addr:postcode":"cf47 8el",
    "addr:street":"New Market Walk",
    "iso:country":"GB",
    "sg:address":"10-11 New Market Walk",
    "sg:city":"Merthyr Tydfil",
    "sg:classifiers":[
        {
            "category":"Shopping",
            "subcategory":"Clothing, Apparel, & Fashions",
            "type":"Retail Goods"
        }
    ],
    "sg:phone":"+44 1685 370733",
    "sg:postcode":"CF47 8EL",
    "sg:province":"Merthyr Tydfil",
    "sg:tags":[
        "menswear"
    ],
    "wof:name":"Fosters Trading Co",
    "wof:placetype":"venue"
},
  "geometry": {"coordinates":[-3.379096,51.745785],"type":"Point"}
}