{
  "type": "Feature",
  "properties": {
    "addr:full":"55 Walcourt Road, Kempston Bedford Bedfordshire MK42 8ST",
    "addr:housenumber":"55",
    "addr:postcode":"mk42 8st",
    "addr:street":"Walcourt Road",
    "iso:country":"GB",
    "sg:address":"55 Walcourt Road, Kempston",
    "sg:city":"Bedford",
    "sg:classifiers":[
        {
            "category":"Building & Trades",
            "subcategory":"Construction",
            "type":"Services"
        }
    ],
    "sg:phone":"+44 1234 351310",
    "sg:postcode":"MK42 8ST",
    "sg:province":"Bedfordshire",
    "sg:tags":[
        "decorator",
        "painter"
    ],
    "wof:name":"A Palmer Builder & Decorator",
    "wof:placetype":"venue"
},
  "geometry": {"coordinates":[-0.4816380143,52.1218948364],"type":"Point"}
}