{
  "type": "Feature",
  "properties": {
    "iso:country":"GB",
    "sg:address":"586 Stoney Stanton Rd",
    "sg:city":"Coventry",
    "sg:classifiers":[
        {
            "category":"Retail",
            "subcategory":"Auto Repair",
            "type":"Services"
        }
    ],
    "sg:phone":"+44 24 7666 5511",
    "sg:postcode":"CV6 5FS",
    "sg:province":"Warwickshire",
    "sg:tags":[
        "modification",
        "garage"
    ],
    "wof:name":"Clutch & Gearbox Centre",
    "wof:placetype":"venue"
},
  "geometry": {"coordinates":[-1.490116,52.427998],"type":"Point"}
}