{
  "type": "Feature",
  "properties": {
    "addr:full":"2 Meard Street London Greater London W1F 0EF",
    "addr:housenumber":"2",
    "addr:postcode":"w1f 0ef",
    "addr:street":"Meard Street",
    "iso:country":"GB",
    "sg:address":"2 Meard Street",
    "sg:city":"London",
    "sg:classifiers":[
        {
            "category":"Professional",
            "subcategory":"Advertising",
            "type":"Services"
        }
    ],
    "sg:phone":"+44 20 7287 5667",
    "sg:postcode":"W1F 0EF",
    "sg:province":"Greater London",
    "wof:name":"The Creative Bull",
    "wof:placetype":"venue"
},
  "geometry": {"coordinates":[-0.132999,51.513279],"type":"Point"}
}