{
  "type": "Feature",
  "properties": {
    "iso:country":"GB",
    "sg:address":"Bowldish Farm, Sedgemoor Road, North Curry",
    "sg:city":"Taunton",
    "sg:classifiers":[
        {
            "category":"Banks & Credit Unions",
            "subcategory":"Investment Brokerage",
            "type":"Services"
        }
    ],
    "sg:postcode":"TA3 6DS",
    "sg:province":"Devon",
    "sg:tags":[
        "contractor"
    ],
    "wof:name":"Alan Denman",
    "wof:placetype":"venue"
},
  "geometry": {"coordinates":[-2.970339,51.022926],"type":"Point"}
}