{
  "type": "Feature",
  "properties": {
    "iso:country":"GB",
    "sg:address":"Unit 5 Station Farm Denton Road, Houton",
    "sg:city":"Northampton",
    "sg:classifiers":[
        {
            "category":"Retail",
            "subcategory":"Auto Repair",
            "type":"Services"
        }
    ],
    "sg:phone":"+44 1604 870244",
    "sg:postcode":"NN7 2BG",
    "sg:province":"Buckinghamshire",
    "sg:tags":[
        "modification",
        "garage"
    ],
    "wof:name":"Dan's Motor Repairs",
    "wof:placetype":"venue"
},
  "geometry": {"coordinates":[-0.79365,52.188141],"type":"Point"}
}