{
  "type": "Feature",
  "properties": {
    "iso:country":"GB",
    "sg:address":"Haweswater",
    "sg:city":"Brampton",
    "sg:classifiers":[
        {
            "category":"Travel",
            "subcategory":"Hotels & Motels",
            "type":"Entertainment"
        }
    ],
    "sg:phone":"+44 1931 713235",
    "sg:postcode":"CA10 2RP",
    "sg:province":"Cumbria",
    "wof:name":"Haweswater Hotel",
    "wof:placetype":"venue"
},
  "geometry": {"coordinates":[-2.79981,54.51754],"type":"Point"}
}