{
  "type": "Feature",
  "properties": {
    "iso:country":"GB",
    "sg:address":"24 Bridge Street",
    "sg:city":"Bradford-on-avon",
    "sg:classifiers":[
        {
            "category":"Restaurant",
            "type":"Food & Drink"
        }
    ],
    "sg:phone":"+44 1225 866443",
    "sg:postcode":"BA15 1BY",
    "sg:province":"Wiltshire",
    "sg:tags":[
        "thai",
        "-"
    ],
    "wof:name":"Thai Barn",
    "wof:placetype":"venue"
},
  "geometry": {"coordinates":[-2.2510530949,51.3464126587],"type":"Point"}
}