{
  "type": "Feature",
  "properties": {
    "iso:country":"GB",
    "sg:address":"Station Road",
    "sg:city":"Much Wenlock",
    "sg:classifiers":[
        {
            "category":"Bus Charters",
            "type":"Transportation"
        }
    ],
    "sg:phone":"+44 1952 727335",
    "sg:postcode":"TF13 6JE",
    "sg:province":"Shropshire",
    "sg:tags":[
        "hire",
        "coach"
    ],
    "wof:name":"Premier Coaches",
    "wof:placetype":"venue"
},
  "geometry": {"coordinates":[-2.557273,52.599594],"type":"Point"}
}