{
  "type": "Feature",
  "properties": {
    "addr:full":"Ivy Cottage, Ditton Park Rd, Datchet Slough Berkshire SL3 7JB",
    "addr:postcode":"sl3 7jb",
    "addr:street":"Ditton Park Rd",
    "iso:country":"GB",
    "sg:address":"Ivy Cottage, Ditton Park Rd, Datchet",
    "sg:city":"Slough",
    "sg:classifiers":[
        {
            "category":"Food & Beverages",
            "subcategory":"Liquor & Beverages",
            "type":"Retail Goods"
        }
    ],
    "sg:phone":"+44 1753 542022",
    "sg:postcode":"SL3 7JB",
    "sg:province":"Berkshire",
    "sg:tags":[
        "beer",
        "spirit",
        "wines"
    ],
    "wof:name":"Camden Wines",
    "wof:placetype":"venue"
},
  "geometry": {"coordinates":[-0.552269,51.495468],"type":"Point"}
}