{
  "type": "Feature",
  "properties": {
    "iso:country":"GB",
    "sg:address":"Tanhouse Farm, Newland",
    "sg:city":"Coleford",
    "sg:classifiers":[
        {
            "category":"Government",
            "subcategory":"Office",
            "type":"Public Place"
        }
    ],
    "sg:postcode":"GL16 8NQ",
    "sg:province":"Gloucestershire",
    "sg:tags":[
        "education",
        "agency",
        "authority"
    ],
    "wof:name":"Medieval Field of Study Centre",
    "wof:placetype":"venue"
},
  "geometry": {"coordinates":[-2.647718,51.782127],"type":"Point"}
}