{
  "type": "Feature",
  "properties": {
    "addr:full":"Beatrice Avenue East Cowes Isle of Wight PO32 6PA",
    "addr:postcode":"po32 6pa",
    "addr:street":"Beatrice Avenue",
    "iso:country":"GB",
    "sg:address":"Beatrice Avenue",
    "sg:city":"East Cowes",
    "sg:classifiers":[
        {
            "category":"Arena",
            "subcategory":"Sports Club",
            "type":"Entertainment"
        }
    ],
    "sg:phone":"+44 1983 297165",
    "sg:postcode":"PO32 6PA",
    "sg:province":"Isle of Wight",
    "wof:name":"East Cowes Victoria Sports & Social Club",
    "wof:placetype":"venue"
},
  "geometry": {"coordinates":[-1.2810189724,50.7495651245],"type":"Point"}
}