{
  "type": "Feature",
  "properties": {
    "addr:full":"53 Leys Avenue Letchworth Hertfordshire SG6 3EF",
    "addr:housenumber":"53",
    "addr:postcode":"sg6 3ef",
    "addr:street":"Leys Avenue Letchworth",
    "iso:country":"GB",
    "sg:address":"53 Leys Avenue",
    "sg:city":"Letchworth",
    "sg:classifiers":[
        {
            "category":"Travel",
            "subcategory":"Travel Agent",
            "type":"Entertainment"
        }
    ],
    "sg:phone":"+44 1462 685441",
    "sg:postcode":"SG6 3EF",
    "sg:province":"Hertfordshire",
    "wof:name":"Premier Worldchoice",
    "wof:placetype":"venue"
},
  "geometry": {"coordinates":[-0.225383,51.978416],"type":"Point"}
}