{
  "type": "Feature",
  "properties": {
    "addr:full":"The Entertainment Centre, Unit 11 & 25cranborne Road Potters Bar Greater London EN6 3DQ",
    "addr:housenumber":"unit 11 &",
    "addr:postcode":"en6 3dq",
    "addr:street":"25Cranborne Road",
    "iso:country":"GB",
    "sg:address":"The Entertainment Centre, Unit 11 & 25cranborne Road",
    "sg:city":"Potters Bar",
    "sg:classifiers":[
        {
            "category":"Utilities",
            "subcategory":"Natural Gas",
            "type":"Services"
        }
    ],
    "sg:phone":"+44 1707 650001",
    "sg:postcode":"EN6 3DQ",
    "sg:province":"Greater London",
    "sg:tags":[
        "control",
        "energy",
        "management",
        "system"
    ],
    "wof:name":"Suregas Ltd.",
    "wof:placetype":"venue"
},
  "geometry": {"coordinates":[-0.2040199935,51.700630188],"type":"Point"}
}