{
  "type": "Feature",
  "properties": {
    "iso:country":"GB",
    "sg:address":"43 Galloway St",
    "sg:city":"Dumfries",
    "sg:classifiers":[
        {
            "category":"Health Services",
            "subcategory":"Clinic",
            "type":"Services"
        }
    ],
    "sg:phone":"+44 1387 249998",
    "sg:postcode":"DG2 7TH",
    "sg:province":"Dumfries and Galloway",
    "sg:tags":[
        "private"
    ],
    "wof:name":"Stop Smoking Centre",
    "wof:placetype":"venue"
},
  "geometry": {"coordinates":[-3.6180970669,55.0690422058],"type":"Point"}
}