{
  "type": "Feature",
  "properties": {
    "addr:full":"34 Bank Street Braintree Essex CM7 1UG",
    "addr:housenumber":"34",
    "addr:postcode":"cm7 1ug",
    "addr:street":"Bank Street",
    "iso:country":"GB",
    "sg:address":"34 Bank Street",
    "sg:city":"Braintree",
    "sg:classifiers":[
        {
            "category":"Real Estate",
            "subcategory":"Real Estate Agent",
            "type":"Services"
        }
    ],
    "sg:phone":"+44 1376 327400",
    "sg:postcode":"CM7 1UG",
    "sg:province":"Essex",
    "wof:name":"Boydens Property Letting & Management",
    "wof:placetype":"venue"
},
  "geometry": {"coordinates":[0.5513859987,51.8794288635],"type":"Point"}
}