{
  "type": "Feature",
  "properties": {
    "iso:country":"GB",
    "sg:address":"692 Becontree Avenue",
    "sg:city":"Dagenham",
    "sg:classifiers":[
        {
            "category":"Personal",
            "subcategory":"Barber",
            "type":"Services"
        }
    ],
    "sg:phone":"+44 20 8984 7904",
    "sg:postcode":"RM8 3HD",
    "sg:province":"Essex",
    "sg:tags":[
        "men's",
        "hairdresser"
    ],
    "wof:name":"The Barber Shop",
    "wof:placetype":"venue"
},
  "geometry": {"coordinates":[0.147014,51.56023],"type":"Point"}
}