{
  "type": "Feature",
  "properties": {
    "iso:country":"GB",
    "sg:address":"Baulker Lane, Clipstone",
    "sg:city":"Mansfield",
    "sg:classifiers":[
        {
            "category":"Wholesale",
            "subcategory":"Electrical",
            "type":"Manufacturing & Wholesale Goods"
        }
    ],
    "sg:phone":"+44 1623 624146",
    "sg:postcode":"NG21 9BG",
    "sg:province":"Nottinghamshire",
    "sg:tags":[
        "equipment",
        "refrigeration"
    ],
    "wof:name":"Haskell & Co",
    "wof:placetype":"venue"
},
  "geometry": {"coordinates":[-1.1055699587,53.16563797],"type":"Point"}
}