{
  "type": "Feature",
  "properties": {
    "addr:full":"Dock Office, Trafford Rd Salford Greater Manchester M5 2XS",
    "addr:postcode":"m5 2xs",
    "addr:street":"Trafford Rd",
    "iso:country":"GB",
    "sg:address":"Dock Office, Trafford Rd",
    "sg:city":"Salford",
    "sg:classifiers":[
        {
            "category":"Freight",
            "type":"Transportation"
        }
    ],
    "sg:phone":"+44 161 877 4411",
    "sg:postcode":"M5 2XS",
    "sg:province":"Greater Manchester",
    "sg:tags":[
        "shipping"
    ],
    "wof:name":"N O L (United Kingdom) Ltd",
    "wof:placetype":"venue"
},
  "geometry": {"coordinates":[-2.32564,53.468399],"type":"Point"}
}