{
  "type": "Feature",
  "properties": {
    "addr:full":"Unit 1, 88-104 Powis Street London Greater London SE18 6LQ",
    "addr:housenumber":"unit 1",
    "addr:postcode":"88-104;se18 6lq",
    "addr:street":"Powis Street",
    "iso:country":"GB",
    "sg:address":"Unit 1, 88-104 Powis Street",
    "sg:city":"London",
    "sg:classifiers":[
        {
            "category":"Shopping",
            "subcategory":"Clothing, Apparel, & Fashions",
            "type":"Retail Goods"
        }
    ],
    "sg:phone":"+44 20 8316 1895",
    "sg:postcode":"SE18 6LQ",
    "sg:province":"Greater London",
    "sg:tags":[
        "ladieswear"
    ],
    "wof:name":"Bon Marche",
    "wof:placetype":"venue"
},
  "geometry": {"coordinates":[0.061705,51.492859],"type":"Point"}
}