{
  "type": "Feature",
  "properties": {
    "addr:full":"Chapel Street, Easingwold York North Yorkshire YO61 3AE",
    "addr:postcode":"yo61 3ae",
    "addr:street":"Chapel Street",
    "iso:country":"GB",
    "sg:address":"Chapel Street, Easingwold",
    "sg:city":"York",
    "sg:classifiers":[
        {
            "category":"Building & Trades",
            "subcategory":"Construction",
            "type":"Services"
        }
    ],
    "sg:phone":"+44 1347 822177",
    "sg:postcode":"YO61 3AE",
    "sg:province":"North Yorkshire",
    "sg:tags":[
        "builder"
    ],
    "wof:name":"National Conservsatory Advisory Service",
    "wof:placetype":"venue"
},
  "geometry": {"coordinates":[-1.1918330193,54.1214027405],"type":"Point"}
}