{
  "type": "Feature",
  "properties": {
    "addr:full":"Welland Road Knottingley North Yorkshire WF11 8AP",
    "addr:postcode":"wf11 8ap",
    "addr:street":"Welland Road",
    "iso:country":"GB",
    "sg:address":"Welland Road",
    "sg:city":"Knottingley",
    "sg:classifiers":[
        {
            "category":"Food & Beverages",
            "subcategory":"Farmers Market",
            "type":"Retail Goods"
        },
        {
            "category":"Manufacturing",
            "subcategory":"Glass & Minerals",
            "type":"Manufacturing & Wholesale Goods"
        }
    ],
    "sg:phone":"+44 1977 607124",
    "sg:postcode":"WF11 8AP",
    "sg:province":"North Yorkshire",
    "sg:tags":[
        "supplier",
        "mnfr",
        "bottle",
        "manufacturer"
    ],
    "sg:website":"http://www.stoelzle.com",
    "wof:name":"Stoelzle Flaconnage Ltd",
    "wof:placetype":"venue"
},
  "geometry": {"coordinates":[-1.2025909424,53.7104454041],"type":"Point"}
}