{
  "type": "Feature",
  "properties": {
    "addr:full":"108 Scrubs Lane, Willesdon London Greater London NW10 6QY",
    "addr:housenumber":"108",
    "addr:postcode":"nw10 6qy",
    "addr:street":"Scrubs Lane",
    "iso:country":"GB",
    "sg:address":"108 Scrubs Lane, Willesdon",
    "sg:city":"London",
    "sg:classifiers":[
        {
            "category":"Professional",
            "subcategory":"Business Services",
            "type":"Services"
        }
    ],
    "sg:phone":"+44 20 8969 7796",
    "sg:postcode":"NW10 6QY",
    "sg:province":"Greater London",
    "sg:tags":[
        "broker",
        "commodity"
    ],
    "wof:name":"Global Seeds & Trading Services (U K) Ltd.",
    "wof:placetype":"venue"
},
  "geometry": {"coordinates":[-0.2346870005,51.5259819031],"type":"Point"}
}