{
  "type": "Feature",
  "properties": {
    "addr:full":"12 Berkeley St London Greater London W1J 8DP",
    "addr:housenumber":"12",
    "addr:postcode":"w1j 8dp",
    "addr:street":"Berkeley St",
    "iso:country":"GB",
    "sg:address":"12 Berkeley St",
    "sg:city":"London",
    "sg:classifiers":[
        {
            "category":"Freight",
            "type":"Transportation"
        }
    ],
    "sg:phone":"+44 20 7493 7942",
    "sg:postcode":"W1J 8DP",
    "sg:province":"Greater London",
    "sg:tags":[
        "overseas",
        "shipping",
        "removal"
    ],
    "wof:name":"Daiichi Chuo Shipping (U K) Ltd",
    "wof:placetype":"venue"
},
  "geometry": {"coordinates":[-0.1431,51.508186],"type":"Point"}
}