{
  "type": "Feature",
  "properties": {
    "addr:full":"47 High Street, Chipping Sodbury Bristol Gloucestershire BS37 6BA",
    "addr:housenumber":"47",
    "addr:postcode":"bs37 6ba",
    "addr:street":"High Street Chipping;Bristol",
    "iso:country":"GB",
    "sg:address":"47 High Street, Chipping Sodbury",
    "sg:city":"Bristol",
    "sg:classifiers":[
        {
            "category":"Shopping",
            "subcategory":"Department Store",
            "type":"Retail Goods"
        },
        {
            "category":"Shopping",
            "subcategory":"Crafts & Fabrics",
            "type":"Retail Goods"
        }
    ],
    "sg:phone":"+44 1454 313216",
    "sg:postcode":"BS37 6BA",
    "sg:province":"Gloucestershire",
    "sg:tags":[
        "shop",
        "needlecraft",
        "wool"
    ],
    "wof:name":"The Ball of Wool",
    "wof:placetype":"venue"
},
  "geometry": {"coordinates":[-2.3941628933,51.5383872986],"type":"Point"}
}