{
  "type": "Feature",
  "properties": {
    "addr:full":"The Highway, Croesyceiliog Cwmbran Monmouthshire NP44 2HE",
    "addr:postcode":"np44 2he",
    "addr:street":"The Highway",
    "iso:country":"GB",
    "sg:address":"The Highway, Croesyceiliog",
    "sg:city":"Cwmbran",
    "sg:classifiers":[
        {
            "category":"Bars & Pubs",
            "type":"Food & Drink"
        }
    ],
    "sg:phone":"+44 1633 483218",
    "sg:postcode":"NP44 2HE",
    "sg:province":"Monmouthshire",
    "sg:tags":[
        "pubs",
        "inn"
    ],
    "wof:name":"Beerhouse Ltd",
    "wof:placetype":"venue"
},
  "geometry": {"coordinates":[-3.0074250698,51.6605682373],"type":"Point"}
}