{
  "type": "Feature",
  "properties": {
    "addr:full":"Kingsbridge, Dorsington Stratford-upon-avon Warwickshire CV37 8AR",
    "addr:postcode":"cv37 8ar",
    "iso:country":"GB",
    "sg:address":"Kingsbridge, Dorsington",
    "sg:city":"Stratford-upon-avon",
    "sg:classifiers":[
        {
            "category":"Professional",
            "subcategory":"Management & Consulting",
            "type":"Services"
        }
    ],
    "sg:postcode":"CV37 8AR",
    "sg:province":"Warwickshire",
    "sg:tags":[
        "consultant",
        "business"
    ],
    "wof:name":"Searchlight Utility Audits",
    "wof:placetype":"venue"
},
  "geometry": {"coordinates":[-1.8086899519,52.1454772949],"type":"Point"}
}