{
  "type": "Feature",
  "properties": {
    "addr:full":"Eign Street Hereford Herefordshire HR4 0AP",
    "addr:postcode":"hr4 0ap",
    "addr:street":"Eign Street",
    "iso:country":"GB",
    "sg:address":"Eign Street",
    "sg:city":"Hereford",
    "sg:classifiers":[
        {
            "category":"Bars & Pubs",
            "type":"Food & Drink"
        }
    ],
    "sg:phone":"+44 1432 355026",
    "sg:postcode":"HR4 0AP",
    "sg:province":"Herefordshire",
    "sg:tags":[
        "pubs",
        "inn"
    ],
    "wof:name":"Horse & Groom Inn",
    "wof:placetype":"venue"
},
  "geometry": {"coordinates":[-2.72246,52.056973],"type":"Point"}
}