{
  "type": "Feature",
  "properties": {
    "iso:country":"GB",
    "sg:address":"2 Briar Edge",
    "sg:city":"Newcastle-upon-tyne",
    "sg:classifiers":[
        {
            "category":"Professional",
            "subcategory":"Accounting & Tax Preparation",
            "type":"Services"
        }
    ],
    "sg:phone":"+44 191 266 9236",
    "sg:postcode":"NE12 7JN",
    "sg:province":"Tyne and Wear",
    "sg:tags":[
        "accountant",
        "activity"
    ],
    "wof:name":"Feeney Madden",
    "wof:placetype":"venue"
},
  "geometry": {"coordinates":[-1.567679,55.021969],"type":"Point"}
}