{
  "type": "Feature",
  "properties": {
    "addr:full":"22 Kings Place Glasgow Glasgow City G22 6LL",
    "addr:housenumber":"22",
    "addr:postcode":"g22 6ll",
    "addr:street":"Kings Place",
    "iso:country":"GB",
    "sg:address":"22 Kings Place",
    "sg:city":"Glasgow",
    "sg:classifiers":[
        {
            "category":"Taxi",
            "type":"Transportation"
        }
    ],
    "sg:phone":"+44 141 336 4422",
    "sg:postcode":"G22 6LL",
    "sg:province":"Glasgow City",
    "sg:tags":[
        "mini",
        "hire",
        "cab",
        "private",
        "vehicle"
    ],
    "wof:name":"Balmore Cars",
    "wof:placetype":"venue"
},
  "geometry": {"coordinates":[-4.2611408234,55.8926849365],"type":"Point"}
}