{
  "type": "Feature",
  "properties": {
    "iso:country":"GB",
    "sg:address":"Shop 88 Heath Rd",
    "sg:city":"Salisbury",
    "sg:classifiers":[
        {
            "category":"Retail",
            "subcategory":"Repair Shop",
            "type":"Services"
        }
    ],
    "sg:postcode":"SP2 9JX",
    "sg:province":"Wiltshire",
    "sg:tags":[
        "radio",
        "television",
        "video"
    ],
    "wof:name":"Churchill,David,",
    "wof:placetype":"venue"
},
  "geometry": {"coordinates":[-1.800284,51.069538],"type":"Point"}
}