{
  "type": "Feature",
  "properties": {
    "iso:country":"GB",
    "sg:address":"27 South Street",
    "sg:city":"Chichester",
    "sg:classifiers":[
        {
            "category":"Food & Beverages",
            "subcategory":"Bakery",
            "type":"Retail Goods"
        }
    ],
    "sg:phone":"+44 1243 786648",
    "sg:postcode":"PO19 1EL",
    "sg:province":"West Sussex",
    "sg:tags":[
        "pizza"
    ],
    "wof:name":"Pizzaexpress (Soho)",
    "wof:placetype":"venue"
},
  "geometry": {"coordinates":[-0.779905,50.834347],"type":"Point"}
}