{
  "type": "Feature",
  "properties": {
    "addr:full":"Kingsmoor House, Paringdon Road Harlow Essex CM19 4QT",
    "addr:postcode":"cm19 4qt",
    "addr:street":"Paringdon Road",
    "iso:country":"GB",
    "sg:address":"Kingsmoor House, Paringdon Road",
    "sg:city":"Harlow",
    "sg:classifiers":[
        {
            "category":"Social Services",
            "subcategory":"Adult Care",
            "type":"Services"
        }
    ],
    "sg:phone":"+44 1279 452783",
    "sg:postcode":"CM19 4QT",
    "sg:province":"Essex",
    "sg:tags":[
        "home",
        "help",
        "private"
    ],
    "wof:name":"Harlow Shared Care",
    "wof:placetype":"venue"
},
  "geometry": {"coordinates":[0.0803050026,51.7521896362],"type":"Point"}
}