{
  "type": "Feature",
  "properties": {
    "addr:full":"93-95 Knutsford Road, Grappenhall Warrington Cheshire WA4 2NS",
    "addr:housenumber":"93-95",
    "addr:postcode":"wa4 2ns",
    "addr:street":"Knutsford Road",
    "iso:country":"GB",
    "sg:address":"93-95 Knutsford Road, Grappenhall",
    "sg:city":"Warrington",
    "sg:classifiers":[
        {
            "category":"Personal",
            "subcategory":"Beauty Salon",
            "type":"Services"
        }
    ],
    "sg:phone":"+44 1925 262101",
    "sg:postcode":"WA4 2NS",
    "sg:province":"Cheshire",
    "sg:tags":[
        "unisex",
        "hairdresser"
    ],
    "wof:name":"Tintz Hairdressers & Beauticians",
    "wof:placetype":"venue"
},
  "geometry": {"coordinates":[-2.5491371155,53.3775939941],"type":"Point"}
}