{
  "type": "Feature",
  "properties": {
    "addr:full":"Resource Centre Wrexham Wrexham LL13 8TH",
    "addr:postcode":"ll13 8th",
    "iso:country":"GB",
    "sg:address":"Resource Centre",
    "sg:city":"Wrexham",
    "sg:classifiers":[
        {
            "category":"Organizations",
            "subcategory":"Non-profit Organization",
            "type":"Services"
        }
    ],
    "sg:phone":"+44 1978 361136",
    "sg:postcode":"LL13 8TH",
    "sg:province":"Wrexham",
    "sg:tags":[
        "organisation",
        "voluntary",
        "charity"
    ],
    "wof:name":"Wrexham Play Association",
    "wof:placetype":"venue"
},
  "geometry": {"coordinates":[-2.9971289635,53.0419540405],"type":"Point"}
}