{
  "type": "Feature",
  "properties": {
    "iso:country":"GB",
    "sg:address":"30 Pinkie Hill Crescent",
    "sg:city":"Musselburgh",
    "sg:classifiers":[
        {
            "category":"Building & Trades",
            "subcategory":"Construction",
            "type":"Services"
        }
    ],
    "sg:phone":"+44 131 665 5541",
    "sg:postcode":"EH21 7NJ",
    "sg:province":"City of Edinburgh",
    "sg:tags":[
        "roofing"
    ],
    "wof:name":"A Hutchison",
    "wof:placetype":"venue"
},
  "geometry": {"coordinates":[-3.035173893,55.9371795654],"type":"Point"}
}