{
  "type": "Feature",
  "properties": {
    "iso:country":"GB",
    "sg:address":"18 Middle Street, Newbridge",
    "sg:city":"Wrexham",
    "sg:classifiers":[
        {
            "category":"Building & Trades",
            "subcategory":"Cleaning & Sanitation",
            "type":"Services"
        }
    ],
    "sg:phone":"+44 1978 821570",
    "sg:postcode":"LL14 3JW",
    "sg:province":"Wrexham",
    "sg:tags":[
        "cleaner",
        "window"
    ],
    "wof:name":"P Edwards",
    "wof:placetype":"venue"
},
  "geometry": {"coordinates":[-3.066045,52.967396],"type":"Point"}
}