{
  "type": "Feature",
  "properties": {
    "addr:full":"Station Yard, Alrewas Burton-on-trent Derbyshire DE13 7BD",
    "addr:postcode":"de13 7bd",
    "iso:country":"GB",
    "sg:address":"Station Yard, Alrewas",
    "sg:city":"Burton-on-trent",
    "sg:classifiers":[
        {
            "category":"Professional",
            "subcategory":"Engineering",
            "type":"Services"
        }
    ],
    "sg:postcode":"DE13 7BD",
    "sg:province":"Derbyshire",
    "sg:tags":[
        "contractor",
        "electrical",
        "engineer"
    ],
    "wof:name":"Andrews Electrical",
    "wof:placetype":"venue"
},
  "geometry": {"coordinates":[-1.7537889481,52.7287445068],"type":"Point"}
}