{
  "type": "Feature",
  "properties": {
    "addr:full":"Wortley Moor Lane, Wortley Leeds West Yorkshire LS12 4HX",
    "addr:postcode":"ls12 4hx",
    "addr:street":"Moor Lane",
    "iso:country":"GB",
    "sg:address":"Wortley Moor Lane, Wortley",
    "sg:city":"Leeds",
    "sg:classifiers":[
        {
            "category":"Building & Trades",
            "subcategory":"Construction",
            "type":"Services"
        }
    ],
    "sg:phone":"+44 113 231 1454",
    "sg:postcode":"LS12 4HX",
    "sg:province":"West Yorkshire",
    "sg:tags":[
        "contractor"
    ],
    "wof:name":"McFadden Construction Ltd.",
    "wof:placetype":"venue"
},
  "geometry": {"coordinates":[-1.59716,53.792004],"type":"Point"}
}