{
  "type": "Feature",
  "properties": {
    "addr:full":"4 Rangers Road London Greater London E4 7QH",
    "addr:housenumber":"4",
    "addr:postcode":"e4 7qh",
    "addr:street":"Rangers Road",
    "iso:country":"GB",
    "sg:address":"4 Rangers Road",
    "sg:city":"London",
    "sg:classifiers":[
        {
            "category":"Restaurant",
            "type":"Food & Drink"
        }
    ],
    "sg:phone":"+44 20 8523 7246",
    "sg:postcode":"E4 7QH",
    "sg:province":"Greater London",
    "sg:tags":[
        "-",
        "english"
    ],
    "wof:name":"The Royal Forest",
    "wof:placetype":"venue"
},
  "geometry": {"coordinates":[0.0212670006,51.6341781616],"type":"Point"}
}