{
  "type": "Feature",
  "properties": {
    "addr:full":"18 Claremont Terrace York North Yorkshire YO31 7EJ",
    "addr:housenumber":"18",
    "addr:postcode":"yo31 7ej",
    "addr:street":"Claremont Terrace",
    "iso:country":"GB",
    "sg:address":"18 Claremont Terrace",
    "sg:city":"York",
    "sg:classifiers":[
        {
            "category":"Travel",
            "subcategory":"Hotels & Motels",
            "type":"Entertainment"
        }
    ],
    "sg:phone":"+44 1904 625158",
    "sg:postcode":"YO31 7EJ",
    "sg:province":"North Yorkshire",
    "sg:tags":[
        "house",
        "guest"
    ],
    "wof:name":"Claremont Guest House",
    "wof:placetype":"venue"
},
  "geometry": {"coordinates":[-1.0840400457,53.9652519226],"type":"Point"}
}