{
  "type": "Feature",
  "properties": {
    "addr:full":"Bellevue Road Banff Aberdeenshire AB45 1BY",
    "addr:postcode":"ab45 1by",
    "addr:street":"Bellevue Road",
    "iso:country":"GB",
    "sg:address":"Bellevue Road",
    "sg:city":"Banff",
    "sg:classifiers":[
        {
            "category":"Education",
            "subcategory":"School",
            "type":"Public Place"
        },
        {
            "category":"Government",
            "subcategory":"Office",
            "type":"Public Place"
        }
    ],
    "sg:phone":"+44 1261 812598",
    "sg:postcode":"AB45 1BY",
    "sg:province":"Aberdeenshire",
    "sg:tags":[
        "local",
        "authority"
    ],
    "wof:name":"Banff Academy",
    "wof:placetype":"venue"
},
  "geometry": {"coordinates":[-2.533231,57.662598],"type":"Point"}
}