{
  "type": "Feature",
  "properties": {
    "addr:full":"Gorsty Lea Garage, Wolverhampton Road, Codsall Wolverhampton Shropshire WV8 1PP",
    "addr:postcode":"wv8 1pp",
    "addr:street":"Wolverhampton Road",
    "iso:country":"GB",
    "sg:address":"Gorsty Lea Garage, Wolverhampton Road, Codsall",
    "sg:city":"Wolverhampton",
    "sg:classifiers":[
        {
            "category":"Autos & Motor Vehicles",
            "subcategory":"Automobile Sales",
            "type":"Retail Goods"
        }
    ],
    "sg:phone":"+44 1902 847024",
    "sg:postcode":"WV8 1PP",
    "sg:province":"Shropshire",
    "sg:tags":[
        "car"
    ],
    "wof:name":"Codsall Car Sales",
    "wof:placetype":"venue"
},
  "geometry": {"coordinates":[-2.1808929443,52.6263465881],"type":"Point"}
}