{
  "type": "Feature",
  "properties": {
    "iso:country":"GB",
    "sg:address":"Billingbear Lodge House, Carters Hill",
    "sg:city":"Wokingham",
    "sg:classifiers":[
        {
            "category":"Organizations",
            "subcategory":"Non-profit Organization",
            "type":"Services"
        }
    ],
    "sg:phone":"+44 1344 452922",
    "sg:postcode":"RG40 5RU",
    "sg:province":"Berkshire",
    "sg:tags":[
        "organisation",
        "voluntary",
        "charity"
    ],
    "wof:name":"Almshouse Association",
    "wof:placetype":"venue"
},
  "geometry": {"coordinates":[-0.797807,51.440121],"type":"Point"}
}