{
  "type": "Feature",
  "properties": {
    "iso:country":"GB",
    "sg:address":"Rivermead, Wilford Lane",
    "sg:city":"Nottingham",
    "sg:classifiers":[
        {
            "category":"Shopping",
            "subcategory":"Department Store",
            "type":"Retail Goods"
        }
    ],
    "sg:postcode":"NG2 7RB",
    "sg:province":"Nottinghamshire",
    "wof:name":"Rivermead Food & Wine",
    "wof:placetype":"venue"
},
  "geometry": {"coordinates":[-1.14132,52.931469],"type":"Point"}
}