{
  "type": "Feature",
  "properties": {
    "addr:full":"14 Turnbull Way Livingston West Lothian EH54 8RB",
    "addr:housenumber":"14",
    "addr:postcode":"eh54 8rb",
    "addr:street":"Turnbull Way",
    "iso:country":"GB",
    "sg:address":"14 Turnbull Way",
    "sg:city":"Livingston",
    "sg:classifiers":[
        {
            "category":"Banks & Credit Unions",
            "subcategory":"Financial Services",
            "type":"Services"
        }
    ],
    "sg:phone":"+44 1506 440222",
    "sg:postcode":"EH54 8RB",
    "sg:province":"West Lothian",
    "sg:tags":[
        "consultant"
    ],
    "wof:name":"Rutland Investment Managers",
    "wof:placetype":"venue"
},
  "geometry": {"coordinates":[-3.5272190571,55.9034538269],"type":"Point"}
}