{
  "type": "Feature",
  "properties": {
    "iso:country":"GB",
    "sg:address":"The Square, Castlebay, Isle Of Barra",
    "sg:city":"Castlebay",
    "sg:classifiers":[
        {
            "category":"Shopping",
            "subcategory":"Department Store",
            "type":"Retail Goods"
        },
        {
            "category":"Food & Beverages",
            "subcategory":"Groceries & Convenience Stores",
            "type":"Retail Goods"
        }
    ],
    "sg:phone":"+44 1871 810291",
    "sg:postcode":"HS9 5XD",
    "sg:province":"Eilean Siar",
    "wof:name":"A C Maclean",
    "wof:placetype":"venue"
},
  "geometry": {"coordinates":[-7.48737,56.955189],"type":"Point"}
}