{
  "type": "Feature",
  "properties": {
    "iso:country":"GB",
    "sg:address":"Sutherland Street",
    "sg:city":"Sheffield",
    "sg:classifiers":[
        {
            "category":"Cafe",
            "type":"Food & Drink"
        }
    ],
    "sg:phone":"+44 114 249 1010",
    "sg:postcode":"S4 7WG",
    "sg:province":"South Yorkshire",
    "sg:tags":[
        "tea",
        "room"
    ],
    "wof:name":"G G's Cafe",
    "wof:placetype":"venue"
},
  "geometry": {"coordinates":[-1.4487930536,53.3903121948],"type":"Point"}
}