{
  "type": "Feature",
  "properties": {
    "addr:full":"67-69 High St Godstone Surrey RH9 8DT",
    "addr:housenumber":"67-69",
    "addr:postcode":"rh9 8dt",
    "addr:street":"High St",
    "iso:country":"GB",
    "sg:address":"67-69 High St",
    "sg:city":"Godstone",
    "sg:classifiers":[
        {
            "category":"Banks & Credit Unions",
            "subcategory":"Financial Services",
            "type":"Services"
        }
    ],
    "sg:phone":"+44 1883 744525",
    "sg:postcode":"RH9 8DT",
    "sg:province":"Surrey",
    "sg:tags":[
        "adviser"
    ],
    "wof:name":"Denver Associates Ltd",
    "wof:placetype":"venue"
},
  "geometry": {"coordinates":[-0.0665939972,51.2474822998],"type":"Point"}
}