{
  "type": "Feature",
  "properties": {
    "addr:full":"High Street Salisbury Wiltshire SP3 6DR",
    "addr:postcode":"sp3 6dr",
    "addr:street":"High Street",
    "iso:country":"GB",
    "sg:address":"High Street",
    "sg:city":"Salisbury",
    "sg:classifiers":[
        {
            "category":"Professional",
            "type":"Services"
        }
    ],
    "sg:phone":"+44 1747 820511",
    "sg:postcode":"SP3 6DR",
    "sg:province":"Wiltshire",
    "sg:tags":[
        "interior",
        "furnishers",
        "designer"
    ],
    "wof:name":"The Splinter Group",
    "wof:placetype":"venue"
},
  "geometry": {"coordinates":[-2.1310219765,51.0957832336],"type":"Point"}
}