{
  "type": "Feature",
  "properties": {
    "addr:full":"485 Bradford Rd Batley West Yorkshire WF17 8LF",
    "addr:housenumber":"485",
    "addr:postcode":"wf17 8lf",
    "addr:street":"Bradford Rd",
    "iso:country":"GB",
    "sg:address":"485 Bradford Rd",
    "sg:city":"Batley",
    "sg:classifiers":[
        {
            "category":"Home & Garden",
            "subcategory":"Home Furnishings",
            "type":"Retail Goods"
        }
    ],
    "sg:phone":"+44 1924 503090",
    "sg:postcode":"WF17 8LF",
    "sg:province":"West Yorkshire",
    "sg:tags":[
        "homefurnishings"
    ],
    "wof:name":"Bowness Reproductions Ltd",
    "wof:placetype":"venue"
},
  "geometry": {"coordinates":[-1.63664,53.717709],"type":"Point"}
}