{
  "type": "Feature",
  "properties": {
    "addr:full":"57-59 Highstreet Bexley Kent DA5 1AB",
    "addr:housenumber":"57-59",
    "addr:postcode":"da5 1ab",
    "addr:street":"Highstreet",
    "iso:country":"GB",
    "sg:address":"57-59 Highstreet",
    "sg:city":"Bexley",
    "sg:classifiers":[
        {
            "category":"Real Estate",
            "subcategory":"Real Estate Agent",
            "type":"Services"
        }
    ],
    "sg:phone":"+44 1322 522381",
    "sg:postcode":"DA5 1AB",
    "sg:province":"Kent",
    "wof:name":"Your Move",
    "wof:placetype":"venue"
},
  "geometry": {"coordinates":[0.1407199949,51.4485206604],"type":"Point"}
}