{
  "type": "Feature",
  "properties": {
    "iso:country":"GB",
    "sg:address":"The Sussex Art Club, 7 Ship St",
    "sg:city":"Brighton",
    "sg:classifiers":[
        {
            "category":"Education",
            "subcategory":"Music School",
            "type":"Public Place"
        }
    ],
    "sg:phone":"+44 1273 673795",
    "sg:postcode":"BN2 2NA",
    "sg:province":"East Sussex",
    "wof:name":"North-Georgiou J",
    "wof:placetype":"venue"
},
  "geometry": {"coordinates":[-0.1344909966,50.8282165527],"type":"Point"}
}