{
  "type": "Feature",
  "properties": {
    "iso:country":"GB",
    "sg:address":"346 Abbey Street",
    "sg:city":"Derby",
    "sg:classifiers":[
        {
            "category":"Retail",
            "subcategory":"Auto Repair",
            "type":"Services"
        }
    ],
    "sg:phone":"+44 1332 342707",
    "sg:postcode":"DE22 3SZ",
    "sg:province":"Derbyshire",
    "sg:tags":[
        "modification",
        "garage",
        "related"
    ],
    "wof:name":"Abbey Street Garage",
    "wof:placetype":"venue"
},
  "geometry": {"coordinates":[-1.483618,52.913845],"type":"Point"}
}