{
  "type": "Feature",
  "properties": {
    "addr:full":"Springfield, Hillcrest Road Westerham Kent TN16 3TY",
    "addr:postcode":"tn16 3ty",
    "addr:street":"Hillcrest Road",
    "iso:country":"GB",
    "sg:address":"Springfield, Hillcrest Road",
    "sg:city":"Westerham",
    "sg:classifiers":[
        {
            "category":"Building & Trades",
            "subcategory":"Construction",
            "type":"Services"
        }
    ],
    "sg:phone":"+44 1959 572747",
    "sg:postcode":"TN16 3TY",
    "sg:province":"Kent",
    "sg:tags":[
        "window",
        "replacement"
    ],
    "wof:name":"Wood Lodge Glazing Co",
    "wof:placetype":"venue"
},
  "geometry": {"coordinates":[0.0712649971,51.267074585],"type":"Point"}
}