{
  "type": "Feature",
  "properties": {
    "iso:country":"GB",
    "sg:address":"Oak House Farm, Wycoller Road, Trawden",
    "sg:city":"Colne",
    "sg:classifiers":[
        {
            "category":"Retail",
            "subcategory":"Repair Shop",
            "type":"Services"
        },
        {
            "category":"Shopping",
            "subcategory":"Antiques",
            "type":"Retail Goods"
        }
    ],
    "sg:phone":"+44 1282 866853",
    "sg:postcode":"BB8 8SY",
    "sg:province":"Lancashire",
    "sg:tags":[
        "restoration"
    ],
    "wof:name":"K Bennett",
    "wof:placetype":"venue"
},
  "geometry": {"coordinates":[-2.1703650951,53.8568572998],"type":"Point"}
}