{
  "type": "Feature",
  "properties": {
    "addr:full":"3 Vidlevan Farm, Lymore Lane Keyhaven Lymington Hampshire SO41 0TS",
    "addr:housenumber":"3",
    "addr:postcode":"so41 0ts",
    "addr:street":"Vidlevan;Lymore Lane Keyhaven",
    "iso:country":"GB",
    "sg:address":"3 Vidlevan Farm, Lymore Lane Keyhaven",
    "sg:city":"Lymington",
    "sg:classifiers":[
        {
            "category":"Building & Trades",
            "subcategory":"Construction",
            "type":"Services"
        }
    ],
    "sg:phone":"+44 1590 688599",
    "sg:postcode":"SO41 0TS",
    "sg:province":"Hampshire",
    "sg:tags":[
        "builder"
    ],
    "wof:name":"Snuddens Ltd.",
    "wof:placetype":"venue"
},
  "geometry": {"coordinates":[-1.569347,50.722847],"type":"Point"}
}