{
  "type": "Feature",
  "properties": {
    "iso:country":"GB",
    "sg:address":"29 Barton Road, Haslingfield",
    "sg:city":"Cambridge",
    "sg:classifiers":[
        {
            "category":"Recreation",
            "subcategory":"Amusement Park",
            "type":"Entertainment"
        }
    ],
    "sg:phone":"+44 1223 871352",
    "sg:postcode":"CB3 7LL",
    "sg:province":"Cambridgeshire",
    "sg:tags":[
        "arcade"
    ],
    "wof:name":"Sound & Vision (Cambridge) Ltd.",
    "wof:placetype":"venue"
},
  "geometry": {"coordinates":[0.049631,52.154778],"type":"Point"}
}