{
  "type": "Feature",
  "properties": {
    "iso:country":"GB",
    "sg:address":"16 Church Road",
    "sg:city":"Kenley",
    "sg:classifiers":[
        {
            "category":"Organizations",
            "subcategory":"Non-profit Organization",
            "type":"Services"
        }
    ],
    "sg:phone":"+44 20 8660 1313",
    "sg:postcode":"CR8 5DU",
    "sg:province":"Surrey",
    "sg:tags":[
        "charitable",
        "organisation",
        "voluntary",
        "charity"
    ],
    "wof:name":"A S K",
    "wof:placetype":"venue"
},
  "geometry": {"coordinates":[-0.099729,51.322781],"type":"Point"}
}