{
  "type": "Feature",
  "properties": {
    "addr:full":"12 Misterton Peterborough Cambridgeshire PE2 5SZ",
    "addr:housenumber":"12",
    "addr:postcode":"pe2 5sz",
    "addr:street":"Misterton Peterborough",
    "iso:country":"GB",
    "sg:address":"12 Misterton",
    "sg:city":"Peterborough",
    "sg:classifiers":[
        {
            "category":"Food & Beverages",
            "subcategory":"Bakery",
            "type":"Retail Goods"
        }
    ],
    "sg:postcode":"PE2 5SZ",
    "sg:province":"Cambridgeshire",
    "sg:tags":[
        "baker"
    ],
    "wof:name":"Slice of Life",
    "wof:placetype":"venue"
},
  "geometry": {"coordinates":[-0.3036940098,52.5424461365],"type":"Point"}
}