{
  "type": "Feature",
  "properties": {
    "addr:full":"34 Beresford Terrace Ayr South Ayrshire KA7 2EN",
    "addr:housenumber":"34",
    "addr:postcode":"ka7 2en",
    "addr:street":"Beresford Terrace",
    "iso:country":"GB",
    "sg:address":"34 Beresford Terrace",
    "sg:city":"Ayr",
    "sg:classifiers":[
        {
            "category":"Manufacturing",
            "subcategory":"Tools & Machinery",
            "type":"Manufacturing & Wholesale Goods"
        }
    ],
    "sg:phone":"+44 1292 286333",
    "sg:postcode":"KA7 2EN",
    "sg:province":"South Ayrshire",
    "sg:tags":[
        "society",
        "friendly"
    ],
    "wof:name":"McLarens",
    "wof:placetype":"venue"
},
  "geometry": {"coordinates":[-4.6295099258,55.4569702148],"type":"Point"}
}