{
  "type": "Feature",
  "properties": {
    "addr:full":"24 Stonegate York North Yorkshire YO1 8AS",
    "addr:housenumber":"24",
    "addr:postcode":"yo1 8as",
    "addr:street":"Stonegate",
    "iso:country":"GB",
    "sg:address":"24 Stonegate",
    "sg:city":"York",
    "sg:classifiers":[
        {
            "category":"Shopping",
            "subcategory":"Clothing, Apparel, & Fashions",
            "type":"Retail Goods"
        },
        {
            "category":"Shopping",
            "subcategory":"Bicycles & Sporting Goods",
            "type":"Retail Goods"
        }
    ],
    "sg:phone":"+44 1904 674619",
    "sg:postcode":"YO1 8AS",
    "sg:province":"North Yorkshire",
    "sg:tags":[
        "equipment",
        "outdoor",
        "clothing",
        "camping"
    ],
    "wof:name":"Rohan Designs Ltd",
    "wof:placetype":"venue"
},
  "geometry": {"coordinates":[-1.084059,53.960735],"type":"Point"}
}