{
  "type": "Feature",
  "properties": {
    "addr:full":"5 Aizlewood Road Sheffield Derbyshire S8 0YX",
    "addr:housenumber":"5",
    "addr:postcode":"s8 0yx",
    "addr:street":"Aizlewood Road",
    "iso:country":"GB",
    "sg:address":"5 Aizlewood Road",
    "sg:city":"Sheffield",
    "sg:classifiers":[
        {
            "category":"Manufacturing",
            "subcategory":"Wood Products",
            "type":"Manufacturing & Wholesale Goods"
        }
    ],
    "sg:phone":"+44 114 255 5794",
    "sg:postcode":"S8 0YX",
    "sg:province":"Derbyshire",
    "sg:tags":[
        "maker",
        "cabinet"
    ],
    "wof:name":"Halbyrd Furniture Ltd.",
    "wof:placetype":"venue"
},
  "geometry": {"coordinates":[-1.4784229994,53.3606796265],"type":"Point"}
}