{
  "type": "Feature",
  "properties": {
    "iso:country":"GB",
    "sg:address":"37-57 Dorothy Road",
    "sg:city":"Leicester",
    "sg:classifiers":[
        {
            "category":"Wholesale",
            "subcategory":"Apparel",
            "type":"Manufacturing & Wholesale Goods"
        }
    ],
    "sg:phone":"+44 116 273 7932",
    "sg:postcode":"LE5 5DS",
    "sg:province":"Leicestershire",
    "sg:tags":[
        "babywear",
        "childrens"
    ],
    "wof:name":"Camden Fashion",
    "wof:placetype":"venue"
},
  "geometry": {"coordinates":[-1.100527,52.632946],"type":"Point"}
}