{
  "type": "Feature",
  "properties": {
    "addr:full":"37-38 Fore Street Taunton Somerset TA1 1HR",
    "addr:housenumber":"37-38",
    "addr:postcode":"ta1 1hr",
    "addr:street":"Fore Street",
    "iso:country":"GB",
    "sg:address":"37-38 Fore Street",
    "sg:city":"Taunton",
    "sg:classifiers":[
        {
            "category":"Shopping",
            "subcategory":"Baby Store",
            "type":"Retail Goods"
        }
    ],
    "sg:phone":"+44 1823 330095",
    "sg:postcode":"TA1 1HR",
    "sg:province":"Somerset",
    "sg:tags":[
        "babywear",
        "childrens"
    ],
    "wof:name":"Adams Childrenswear Ltd.",
    "wof:placetype":"venue"
},
  "geometry": {"coordinates":[-3.102422,51.014854],"type":"Point"}
}