{
  "type": "Feature",
  "properties": {
    "iso:country":"GB",
    "sg:address":"2 Abbots Ct, Stoke Rd",
    "sg:city":"Rochester",
    "sg:classifiers":[
        {
            "category":"Social Services",
            "subcategory":"Retirement Home",
            "type":"Services"
        }
    ],
    "sg:phone":"+44 1634 254822",
    "sg:postcode":"ME3 9LS",
    "sg:province":"Kent",
    "sg:tags":[
        "care"
    ],
    "wof:name":"Community Careline Services",
    "wof:placetype":"venue"
},
  "geometry": {"coordinates":[0.57827,51.41996],"type":"Point"}
}