{
  "type": "Feature",
  "properties": {
    "addr:full":"4 Mayfield Gardens Hendon Greater London NW4 2QA",
    "addr:housenumber":"4",
    "addr:postcode":"nw4 2qa",
    "addr:street":"Mayfield Gardens",
    "iso:country":"GB",
    "sg:address":"4 Mayfield Gardens",
    "sg:city":"Hendon",
    "sg:classifiers":[
        {
            "category":"Shopping",
            "subcategory":"Luggage & Leather Goods",
            "type":"Retail Goods"
        }
    ],
    "sg:phone":"+44 20 8202 8747",
    "sg:postcode":"NW4 2QA",
    "sg:province":"Greater London",
    "wof:name":"Novela Luggage & Shopping Trolleys",
    "wof:placetype":"venue"
},
  "geometry": {"coordinates":[-0.215308,51.579918],"type":"Point"}
}