{
  "type": "Feature",
  "properties": {
    "iso:country":"GB",
    "sg:address":"Dale Ho, Tiviot Dale",
    "sg:city":"Stockport",
    "sg:classifiers":[
        {
            "category":"Professional",
            "subcategory":"Engineering",
            "type":"Services"
        }
    ],
    "sg:postcode":"SK1 1TA",
    "sg:province":"Cheshire",
    "wof:name":"Anglian H & G Ltd",
    "wof:placetype":"venue"
},
  "geometry": {"coordinates":[-2.159070015,53.4129905701],"type":"Point"}
}