{
  "type": "Feature",
  "properties": {
    "iso:country":"GB",
    "sg:address":"15 Dover Street",
    "sg:city":"Canterbury",
    "sg:classifiers":[
        {
            "category":"Taxi",
            "type":"Transportation"
        }
    ],
    "sg:phone":"+44 1227 478338",
    "sg:postcode":"CT1 3HD",
    "sg:province":"Kent",
    "sg:tags":[
        "mini",
        "cab"
    ],
    "wof:name":"Pro-Cab",
    "wof:placetype":"venue"
},
  "geometry": {"coordinates":[1.083471,51.276211],"type":"Point"}
}