{
  "type": "Feature",
  "properties": {
    "addr:full":"9 David Road, Colnbrook Slough Berkshire SL3 0DB",
    "addr:housenumber":"9",
    "addr:postcode":"sl3 0db",
    "addr:street":"David Road",
    "iso:country":"GB",
    "sg:address":"9 David Road, Colnbrook",
    "sg:city":"Slough",
    "sg:classifiers":[
        {
            "category":"Professional",
            "subcategory":"Engineering",
            "type":"Services"
        }
    ],
    "sg:phone":"+44 1753 687060",
    "sg:postcode":"SL3 0DB",
    "sg:province":"Berkshire",
    "sg:tags":[
        "precision",
        "engineer"
    ],
    "wof:name":"Prizeglow Ltd.",
    "wof:placetype":"venue"
},
  "geometry": {"coordinates":[-0.5108039975,51.4753341675],"type":"Point"}
}