{
  "type": "Feature",
  "properties": {
    "addr:full":"Hoel Ffaldau, Brackla Industrial Estate Bridgend Bridgend CF31 2AG",
    "addr:postcode":"cf31 2ag",
    "addr:street":"Industrial Estate",
    "iso:country":"GB",
    "sg:address":"Hoel Ffaldau, Brackla Industrial Estate",
    "sg:city":"Bridgend",
    "sg:classifiers":[
        {
            "category":"Home & Garden",
            "subcategory":"Kitchen Supply",
            "type":"Retail Goods"
        }
    ],
    "sg:phone":"+44 1656 654003",
    "sg:postcode":"CF31 2AG",
    "sg:province":"Bridgend",
    "sg:tags":[
        "equipment",
        "catering"
    ],
    "wof:name":"Etchell Ltd.",
    "wof:placetype":"venue"
},
  "geometry": {"coordinates":[-3.5517749786,51.5041236877],"type":"Point"}
}