{
  "type": "Feature",
  "properties": {
    "addr:full":"161 Ware Road Hertford Hertfordshire SG13 7EQ",
    "addr:housenumber":"161",
    "addr:postcode":"sg13 7eq",
    "addr:street":"Ware Road",
    "iso:country":"GB",
    "sg:address":"161 Ware Road",
    "sg:city":"Hertford",
    "sg:classifiers":[
        {
            "category":"Retail",
            "subcategory":"Auto Repair",
            "type":"Services"
        }
    ],
    "sg:postcode":"SG13 7EQ",
    "sg:province":"Hertfordshire",
    "sg:tags":[
        "modification",
        "garage"
    ],
    "wof:name":"Meadside Garage",
    "wof:placetype":"venue"
},
  "geometry": {"coordinates":[-0.059126,51.800549],"type":"Point"}
}