{
  "type": "Feature",
  "properties": {
    "addr:full":"Barmston Centre Washington Durham NE38 8DQ",
    "addr:housenumber":"barmston",
    "addr:postcode":"ne38 8dq",
    "addr:street":"Centre Washington",
    "iso:country":"GB",
    "sg:address":"Barmston Centre",
    "sg:city":"Washington",
    "sg:classifiers":[
        {
            "category":"Home & Garden",
            "subcategory":"Carpets & Floor Coverings",
            "type":"Retail Goods"
        }
    ],
    "sg:phone":"+44 191 415 0528",
    "sg:postcode":"NE38 8DQ",
    "sg:province":"Durham",
    "sg:tags":[
        "carpets",
        "rug",
        "matting"
    ],
    "wof:name":"Carpetright Plc",
    "wof:placetype":"venue"
},
  "geometry": {"coordinates":[-1.5059740543,54.8952941895],"type":"Point"}
}