{
  "type": "Feature",
  "properties": {
    "addr:full":"Clarence Ho, 35 Clarence St Market Harborough Leicestershire LE16 7NE",
    "addr:housenumber":"35",
    "addr:postcode":"le16 7ne",
    "addr:street":"Clarence St",
    "iso:country":"GB",
    "sg:address":"Clarence Ho, 35 Clarence St",
    "sg:city":"Market Harborough",
    "sg:classifiers":[
        {
            "category":"Building & Trades",
            "subcategory":"Construction",
            "type":"Services"
        }
    ],
    "sg:postcode":"LE16 7NE",
    "sg:province":"Leicestershire",
    "sg:tags":[
        "builder"
    ],
    "wof:name":"P.M. Construction Services Ltd",
    "wof:placetype":"venue"
},
  "geometry": {"coordinates":[-0.922579,52.479397],"type":"Point"}
}