{
  "type": "Feature",
  "properties": {
    "iso:country":"GB",
    "sg:address":"Ainstable",
    "sg:city":"Carlisle",
    "sg:classifiers":[
        {
            "category":"Travel",
            "subcategory":"Hotels & Motels",
            "type":"Entertainment"
        }
    ],
    "sg:phone":"+44 1768 896219",
    "sg:postcode":"CA4 9QQ",
    "sg:province":"Cumbria",
    "wof:name":"Heather Glen Country Hotel",
    "wof:placetype":"venue"
},
  "geometry": {"coordinates":[-2.72914,54.808361],"type":"Point"}
}