{
  "type": "Feature",
  "properties": {
    "addr:full":"16 Brookside Court, Barb0t Hall Industrial Estate, Park Gate Rotherham South Yorkshire S62 6NX",
    "addr:housenumber":"16;barb0t hall",
    "addr:postcode":"s62 6nx",
    "addr:street":"Brookside Court;Industrial Estate Park Gate",
    "iso:country":"GB",
    "sg:address":"16 Brookside Court, Barb0t Hall Industrial Estate, Park Gate",
    "sg:city":"Rotherham",
    "sg:classifiers":[
        {
            "category":"Retail",
            "subcategory":"Auto Repair",
            "type":"Services"
        }
    ],
    "sg:phone":"+44 1709 362175",
    "sg:postcode":"S62 6NX",
    "sg:province":"South Yorkshire",
    "sg:tags":[
        "modification",
        "garage"
    ],
    "wof:name":"E B Hadfield Service & Repairs",
    "wof:placetype":"venue"
},
  "geometry": {"coordinates":[-1.353,53.44978],"type":"Point"}
}