{
  "type": "Feature",
  "properties": {
    "addr:full":"6 Arica Rd, Brockley London Greater London SE4 2PX",
    "addr:housenumber":"6",
    "addr:postcode":"se4 2px",
    "addr:street":"Arica Rd",
    "iso:country":"GB",
    "sg:address":"6 Arica Rd, Brockley",
    "sg:city":"London",
    "sg:classifiers":[
        {
            "category":"Freight",
            "type":"Transportation"
        }
    ],
    "sg:postcode":"SE4 2PX",
    "sg:province":"Greater London",
    "sg:tags":[
        "haulage",
        "road"
    ],
    "wof:name":"Eagle Express",
    "wof:placetype":"venue"
},
  "geometry": {"coordinates":[-0.0394250005,51.4633293152],"type":"Point"}
}