{
  "type": "Feature",
  "properties": {
    "addr:full":"80 Kings Avenue, Holland On Sea Clacton-on-sea Essex CO15 5EP",
    "addr:housenumber":"80",
    "addr:postcode":"co15 5ep",
    "addr:street":"Kings Avenue",
    "iso:country":"GB",
    "sg:address":"80 Kings Avenue, Holland On Sea",
    "sg:city":"Clacton-on-sea",
    "sg:classifiers":[
        {
            "category":"Fast Food",
            "type":"Food & Drink"
        }
    ],
    "sg:postcode":"CO15 5EP",
    "sg:province":"Essex",
    "sg:tags":[
        "away",
        "take"
    ],
    "wof:name":"The Friendly Fisherman",
    "wof:placetype":"venue"
},
  "geometry": {"coordinates":[1.1821559668,51.802280426],"type":"Point"}
}