{
  "type": "Feature",
  "properties": {
    "iso:country":"GB",
    "sg:address":"Woodland St",
    "sg:city":"Stoke On Trent",
    "sg:classifiers":[
        {
            "category":"Manufacturing",
            "subcategory":"Pottery",
            "type":"Manufacturing & Wholesale Goods"
        }
    ],
    "sg:phone":"+44 1782 811212",
    "sg:postcode":"ST6 6AP",
    "sg:province":"Staffordshire",
    "wof:name":"English Ironstone",
    "wof:placetype":"venue"
},
  "geometry": {"coordinates":[-2.206849,53.056789],"type":"Point"}
}