{
  "type": "Feature",
  "properties": {
    "iso:country":"GB",
    "sg:address":"63 Bath Road",
    "sg:city":"Reading",
    "sg:classifiers":[
        {
            "category":"Education",
            "subcategory":"School",
            "type":"Public Place"
        }
    ],
    "sg:postcode":"RG30 2BB",
    "sg:province":"Berkshire",
    "sg:tags":[
        "independent",
        "preparatory"
    ],
    "wof:name":"Presentation College",
    "wof:placetype":"venue"
},
  "geometry": {"coordinates":[-0.997644,51.447784],"type":"Point"}
}