{
  "type": "Feature",
  "properties": {
    "addr:full":"Holme Road, Yaxley Peterborough Cambridgeshire PE7 3NA",
    "addr:postcode":"pe7 3na",
    "addr:street":"Holme Road",
    "iso:country":"GB",
    "sg:address":"Holme Road, Yaxley",
    "sg:city":"Peterborough",
    "sg:classifiers":[
        {
            "category":"Building & Trades",
            "subcategory":"Landscaping Services",
            "type":"Services"
        }
    ],
    "sg:phone":"+44 1733 240699",
    "sg:postcode":"PE7 3NA",
    "sg:province":"Cambridgeshire",
    "sg:tags":[
        "horticultural"
    ],
    "wof:name":"Parwin Heaters Ltd.",
    "wof:placetype":"venue"
},
  "geometry": {"coordinates":[-0.252699,52.47403],"type":"Point"}
}