{
  "type": "Feature",
  "properties": {
    "addr:full":"Unit 12, Princes End Industrial Park, Nicholls Road Tipton West Midlands DY4 9LG",
    "addr:housenumber":"unit 12",
    "addr:postcode":"dy4 9lg",
    "addr:street":"Princes End Industrial Park Nicholls Road",
    "iso:country":"GB",
    "sg:address":"Unit 12, Princes End Industrial Park, Nicholls Road",
    "sg:city":"Tipton",
    "sg:classifiers":[
        {
            "category":"Building & Trades",
            "subcategory":"Construction",
            "type":"Services"
        }
    ],
    "sg:phone":"+44 121 557 1400",
    "sg:postcode":"DY4 9LG",
    "sg:province":"West Midlands",
    "sg:tags":[
        "window",
        "replacement"
    ],
    "wof:name":"Fairway Windows",
    "wof:placetype":"venue"
},
  "geometry": {"coordinates":[-2.070697,52.528137],"type":"Point"}
}