{
  "type": "Feature",
  "properties": {
    "addr:full":"Priory Rd, Ecclesfield Sheffield South Yorkshire S35 9XY",
    "addr:postcode":"s35 9xy",
    "addr:street":"Priory Rd",
    "iso:country":"GB",
    "sg:address":"Priory Rd, Ecclesfield",
    "sg:city":"Sheffield",
    "sg:classifiers":[
        {
            "category":"Retail",
            "subcategory":"Funeral Services",
            "type":"Services"
        }
    ],
    "sg:postcode":"S35 9XY",
    "sg:province":"South Yorkshire",
    "sg:tags":[
        "cemetery",
        "crematorium"
    ],
    "wof:name":"City Road Cemetery",
    "wof:placetype":"venue"
},
  "geometry": {"coordinates":[-1.470384,53.442139],"type":"Point"}
}