{
  "type": "Feature",
  "properties": {
    "addr:full":"20 Victoria Street Nottingham Nottinghamshire NG1 2EX",
    "addr:housenumber":"20",
    "addr:postcode":"ng1 2ex",
    "addr:street":"Victoria Street",
    "iso:country":"GB",
    "sg:address":"20 Victoria Street",
    "sg:city":"Nottingham",
    "sg:classifiers":[
        {
            "category":"Banks & Credit Unions",
            "subcategory":"Bureau De Change",
            "type":"Services"
        }
    ],
    "sg:phone":"+44 115 941 9800",
    "sg:postcode":"NG1 2EX",
    "sg:province":"Nottinghamshire",
    "sg:tags":[
        "town",
        "consultant",
        "planning"
    ],
    "wof:name":"A M K Planning",
    "wof:placetype":"venue"
},
  "geometry": {"coordinates":[-1.145648,52.953262],"type":"Point"}
}