{
  "type": "Feature",
  "properties": {
    "iso:country":"GB",
    "sg:address":"22 Church Street, Bentley",
    "sg:city":"Doncaster",
    "sg:classifiers":[
        {
            "category":"Manufacturing",
            "subcategory":"Electronics",
            "type":"Manufacturing & Wholesale Goods"
        }
    ],
    "sg:postcode":"DN5 0BB",
    "sg:province":"South Yorkshire",
    "sg:tags":[
        "computer",
        "-",
        "printed",
        "circuit"
    ],
    "wof:name":"Maxking Interfaces Ltd.",
    "wof:placetype":"venue"
},
  "geometry": {"coordinates":[-1.149775,53.544636],"type":"Point"}
}