{
  "type": "Feature",
  "properties": {
    "addr:full":"15 Poplar Court, Richmond Road Twickenham Greater London TW1 2DS",
    "addr:housenumber":"15",
    "addr:postcode":"tw1 2ds",
    "addr:street":"Poplar Court Richmond Road",
    "iso:country":"GB",
    "sg:address":"15 Poplar Court, Richmond Road",
    "sg:city":"Twickenham",
    "sg:classifiers":[
        {
            "category":"Retail",
            "subcategory":"Storage",
            "type":"Services"
        }
    ],
    "sg:postcode":"TW1 2DS",
    "sg:province":"Greater London",
    "sg:tags":[
        "household",
        "removal"
    ],
    "wof:name":"A A Richards Removals Est 1970",
    "wof:placetype":"venue"
},
  "geometry": {"coordinates":[-0.3282290101,51.4466362],"type":"Point"}
}