{
  "type": "Feature",
  "properties": {
    "iso:country":"GB",
    "sg:address":"3 Lower Road, Chorleywood",
    "sg:city":"Rickmansworth",
    "sg:classifiers":[
        {
            "category":"Professional",
            "subcategory":"Management & Consulting",
            "type":"Services"
        }
    ],
    "sg:phone":"+44 1923 284161",
    "sg:postcode":"WD3 5LH",
    "sg:province":"Hertfordshire",
    "sg:tags":[
        "consultant",
        "specialist"
    ],
    "wof:name":"The Elusive Butterfly",
    "wof:placetype":"venue"
},
  "geometry": {"coordinates":[-0.519998,51.654076],"type":"Point"}
}