{
  "type": "Feature",
  "properties": {
    "iso:country":"GB",
    "sg:address":"120 Hall Road",
    "sg:city":"Norwich",
    "sg:classifiers":[
        {
            "category":"Food & Beverages",
            "subcategory":"Meat & Fish",
            "type":"Retail Goods"
        }
    ],
    "sg:postcode":"NR1 3HP",
    "sg:province":"Norfolk",
    "sg:tags":[
        "butcher"
    ],
    "wof:name":"Prime Side Butchery",
    "wof:placetype":"venue"
},
  "geometry": {"coordinates":[1.2976709604,52.6184768677],"type":"Point"}
}