{
  "type": "Feature",
  "properties": {
    "addr:full":"1 Haverfordwest Business Centre, Merlins Court, Winch Lane Haverfordwest Pembrokeshire SA61 1SB",
    "addr:housenumber":"1",
    "addr:postcode":"sa61 1sb",
    "addr:street":"Winch Lane",
    "iso:country":"GB",
    "sg:address":"1 Haverfordwest Business Centre, Merlins Court, Winch Lane",
    "sg:city":"Haverfordwest",
    "sg:classifiers":[
        {
            "category":"Professional",
            "subcategory":"Engineering",
            "type":"Services"
        }
    ],
    "sg:phone":"+44 1437 766761",
    "sg:postcode":"SA61 1SB",
    "sg:province":"Pembrokeshire",
    "sg:tags":[
        "electronic",
        "engineer"
    ],
    "wof:name":"Honeywell Control Systems Ltd.",
    "wof:placetype":"venue"
},
  "geometry": {"coordinates":[-4.977350235,51.7987632751],"type":"Point"}
}