{
  "type": "Feature",
  "properties": {
    "addr:full":"Hunslett Delivery Office, 2 West Grange Drive Leeds West Yorkshire LS10 3AY",
    "addr:housenumber":"2",
    "addr:postcode":"ls10 3ay",
    "addr:street":"West Grange Drive",
    "iso:country":"GB",
    "sg:address":"Hunslett Delivery Office, 2 West Grange Drive",
    "sg:city":"Leeds",
    "sg:classifiers":[
        {
            "category":"Government",
            "subcategory":"Post Office",
            "type":"Public Place"
        }
    ],
    "sg:phone":"+44 113 271 7519",
    "sg:postcode":"LS10 3AY",
    "sg:province":"West Yorkshire",
    "wof:name":"Royal Mail",
    "wof:placetype":"venue"
},
  "geometry": {"coordinates":[-1.546587,53.794495],"type":"Point"}
}