{
  "type": "Feature",
  "properties": {
    "iso:country":"GB",
    "sg:address":"86 Magdalen Street",
    "sg:city":"Norwich",
    "sg:classifiers":[
        {
            "category":"Professional",
            "subcategory":"Art Services",
            "type":"Services"
        }
    ],
    "sg:phone":"+44 1603 616451",
    "sg:postcode":"NR3 1JF",
    "sg:province":"Norfolk",
    "sg:tags":[
        "photographer"
    ],
    "wof:name":"Studio Norwich",
    "wof:placetype":"venue"
},
  "geometry": {"coordinates":[1.296302,52.635834],"type":"Point"}
}