{
  "type": "Feature",
  "properties": {
    "addr:full":"High Raventhorpe, Malton Road, Cherry Burton Beverley East Riding of Yorkshire HU17 7RA",
    "addr:postcode":"hu17 7ra",
    "addr:street":"Malton Road",
    "iso:country":"GB",
    "sg:address":"High Raventhorpe, Malton Road, Cherry Burton",
    "sg:city":"Beverley",
    "sg:classifiers":[
        {
            "category":"Organizations",
            "subcategory":"Non-profit Organization",
            "type":"Services"
        }
    ],
    "sg:phone":"+44 1964 550555",
    "sg:postcode":"HU17 7RA",
    "sg:province":"East Riding of Yorkshire",
    "sg:tags":[
        "alarm",
        "system"
    ],
    "wof:name":"Adpro Securities",
    "wof:placetype":"venue"
},
  "geometry": {"coordinates":[-0.4981549978,53.8662223816],"type":"Point"}
}