{
  "type": "Feature",
  "properties": {
    "iso:country":"GB",
    "sg:address":"Lakeside, Old Mill La, Cowley",
    "sg:city":"Uxbridge",
    "sg:classifiers":[
        {
            "category":"Professional",
            "subcategory":"Management & Consulting",
            "type":"Services"
        }
    ],
    "sg:postcode":"UB8 2JH",
    "sg:province":"Buckinghamshire",
    "sg:tags":[
        "consultant",
        "business"
    ],
    "wof:name":"Clarke,Malcolm,",
    "wof:placetype":"venue"
},
  "geometry": {"coordinates":[-0.48227,51.531052],"type":"Point"}
}