{
  "type": "Feature",
  "properties": {
    "addr:full":"Frogmerry Green Farm, West St South Petherton Somerset TA13 5DJ",
    "addr:postcode":"ta13 5dj",
    "addr:street":"West St",
    "iso:country":"GB",
    "sg:address":"Frogmerry Green Farm, West St",
    "sg:city":"South Petherton",
    "sg:classifiers":[
        {
            "category":"Farming",
            "subcategory":"Farm",
            "type":"Manufacturing & Wholesale Goods"
        }
    ],
    "sg:phone":"+44 1460 242776",
    "sg:postcode":"TA13 5DJ",
    "sg:province":"Somerset",
    "sg:tags":[
        "mixed",
        "crop"
    ],
    "wof:name":"R & D Bragg & Son",
    "wof:placetype":"venue"
},
  "geometry": {"coordinates":[-2.8055388927,50.9495315552],"type":"Point"}
}