{
  "type": "Feature",
  "properties": {
    "iso:country":"GB",
    "sg:address":"142 Moss Road, Stretford",
    "sg:city":"Manchester",
    "sg:classifiers":[
        {
            "category":"Wholesale",
            "subcategory":"Scrap",
            "type":"Manufacturing & Wholesale Goods"
        },
        {
            "category":"Utilities",
            "subcategory":"Recycling",
            "type":"Services"
        }
    ],
    "sg:phone":"+44 161 865 8841",
    "sg:postcode":"M32 0AX",
    "sg:province":"Cheshire",
    "sg:tags":[
        "merchant",
        "dismantlers",
        "waste",
        "breaker"
    ],
    "wof:name":"Stretford Car Breakers",
    "wof:placetype":"venue"
},
  "geometry": {"coordinates":[-2.3101549149,53.4565200806],"type":"Point"}
}