{
  "type": "Feature",
  "properties": {
    "iso:country":"GB",
    "sg:address":"Manor Croft, Knoll Grn",
    "sg:city":"Preston",
    "sg:classifiers":[
        {
            "category":"Shopping",
            "subcategory":"Discount & Variety Stores",
            "type":"Retail Goods"
        }
    ],
    "sg:postcode":"PR3 2ZQ",
    "sg:province":"Lancashire",
    "sg:tags":[
        "cleaning",
        "supply"
    ],
    "wof:name":"Mercers (Longridge) Ltd.",
    "wof:placetype":"venue"
},
  "geometry": {"coordinates":[-2.553319931,53.8366317749],"type":"Point"}
}