{
  "type": "Feature",
  "properties": {
    "iso:country":"GB",
    "sg:address":"35 Westfield Lane",
    "sg:city":"St Leonards-on-sea",
    "sg:classifiers":[
        {
            "category":"Real Estate",
            "subcategory":"Surveying",
            "type":"Services"
        }
    ],
    "sg:phone":"+44 1424 753383",
    "sg:postcode":"TN37 7NE",
    "sg:province":"East Sussex",
    "sg:tags":[
        "building",
        "surveyor"
    ],
    "wof:name":"Hamson Partnership",
    "wof:placetype":"venue"
},
  "geometry": {"coordinates":[0.5603510141,50.8936843872],"type":"Point"}
}