{
  "type": "Feature",
  "properties": {
    "addr:full":"46 Claverhouse Drive Edinburgh City of Edinburgh EH16 6BU",
    "addr:housenumber":"46",
    "addr:postcode":"eh16 6bu",
    "addr:street":"Claverhouse Drive",
    "iso:country":"GB",
    "sg:address":"46 Claverhouse Drive",
    "sg:city":"Edinburgh",
    "sg:classifiers":[
        {
            "category":"Bus Charters",
            "type":"Transportation"
        }
    ],
    "sg:postcode":"EH16 6BU",
    "sg:province":"City of Edinburgh",
    "sg:tags":[
        "hire",
        "coach"
    ],
    "wof:name":"Bee-Line Mini Coaches",
    "wof:placetype":"venue"
},
  "geometry": {"coordinates":[-3.1580560207,55.9167556763],"type":"Point"}
}