{
  "type": "Feature",
  "properties": {
    "addr:full":"28 Blounts Drive Uttoxeter Derbyshire ST14 8TQ",
    "addr:housenumber":"28",
    "addr:postcode":"st14 8tq",
    "addr:street":"Blounts Drive",
    "iso:country":"GB",
    "sg:address":"28 Blounts Drive",
    "sg:city":"Uttoxeter",
    "sg:classifiers":[
        {
            "category":"Building & Trades",
            "subcategory":"Construction",
            "type":"Services"
        }
    ],
    "sg:phone":"+44 1889 564047",
    "sg:postcode":"ST14 8TQ",
    "sg:province":"Derbyshire",
    "sg:tags":[
        "decorator",
        "painter"
    ],
    "wof:name":"J & S Decorators",
    "wof:placetype":"venue"
},
  "geometry": {"coordinates":[-1.879604,52.89064],"type":"Point"}
}