{
  "type": "Feature",
  "properties": {
    "addr:full":"64 Marsh Wall Poplar Greater London E14 9TP",
    "addr:housenumber":"64",
    "addr:postcode":"e14 9tp",
    "addr:street":"Marsh Wall",
    "iso:country":"GB",
    "sg:address":"64 Marsh Wall",
    "sg:city":"Poplar",
    "sg:classifiers":[
        {
            "category":"Autos & Motor Vehicles",
            "subcategory":"Automobile Sales",
            "type":"Retail Goods"
        }
    ],
    "sg:phone":"+44 20 7536 0555",
    "sg:postcode":"E14 9TP",
    "sg:province":"Greater London",
    "sg:tags":[
        "car"
    ],
    "wof:name":"Docklands Audi",
    "wof:placetype":"venue"
},
  "geometry": {"coordinates":[-0.0224699993,51.5011100769],"type":"Point"}
}