{
  "type": "Feature",
  "properties": {
    "addr:full":"172 Front Street Chester Le Street Durham DH3 3AZ",
    "addr:housenumber":"172",
    "addr:postcode":"dh3 3az",
    "addr:street":"Front Street;Le Street",
    "iso:country":"GB",
    "sg:address":"172 Front Street",
    "sg:city":"Chester Le Street",
    "sg:classifiers":[
        {
            "category":"Shopping",
            "subcategory":"Thrift Store",
            "type":"Retail Goods"
        }
    ],
    "sg:phone":"+44 191 387 4314",
    "sg:postcode":"DH3 3AZ",
    "sg:province":"Durham",
    "sg:tags":[
        "shop",
        "charity"
    ],
    "wof:name":"St. Cuthberts Hospice Charity Shop",
    "wof:placetype":"venue"
},
  "geometry": {"coordinates":[-1.5731329918,54.8530044556],"type":"Point"}
}