{
  "type": "Feature",
  "properties": {
    "addr:full":"Within F.b Atkins & Sons Ltd, Complex, Burton Rd, Findern Derby Derbyshire DE65 6BG",
    "addr:postcode":"de65 6bg",
    "addr:street":"Burton Rd",
    "iso:country":"GB",
    "sg:address":"Within F.b Atkins & Sons Ltd, Complex, Burton Rd, Findern",
    "sg:city":"Derby",
    "sg:classifiers":[
        {
            "category":"Manufacturing",
            "subcategory":"Buildings",
            "type":"Manufacturing & Wholesale Goods"
        }
    ],
    "sg:phone":"+44 1332 521512",
    "sg:postcode":"DE65 6BG",
    "sg:province":"Derbyshire",
    "sg:tags":[
        "sectional"
    ],
    "wof:name":"Portable Offices Ltd",
    "wof:placetype":"venue"
},
  "geometry": {"coordinates":[-1.558,52.874432],"type":"Point"}
}