{
  "type": "Feature",
  "properties": {
    "addr:full":"Abbeyfield House, 1 George Street Llandeilo Carmarthenshire SA19 6AS",
    "addr:housenumber":"1",
    "addr:postcode":"sa19 6as",
    "addr:street":"George Street",
    "iso:country":"GB",
    "sg:address":"Abbeyfield House, 1 George Street",
    "sg:city":"Llandeilo",
    "sg:classifiers":[
        {
            "category":"Organizations",
            "subcategory":"Community Association",
            "type":"Services"
        }
    ],
    "sg:phone":"+44 1558 823222",
    "sg:postcode":"SA19 6AS",
    "sg:province":"Carmarthenshire",
    "sg:tags":[
        "society",
        "housing"
    ],
    "wof:name":"Abbeyfield Llandeilo Society Ltd.",
    "wof:placetype":"venue"
},
  "geometry": {"coordinates":[-3.995242,51.882332],"type":"Point"}
}