{
  "type": "Feature",
  "properties": {
    "addr:full":"41 Dace Road London Greater London E3 2NQ",
    "addr:housenumber":"41",
    "addr:postcode":"e3 2nq",
    "addr:street":"Dace Road",
    "iso:country":"GB",
    "sg:address":"41 Dace Road",
    "sg:city":"London",
    "sg:classifiers":[
        {
            "category":"Building & Trades",
            "subcategory":"Construction",
            "type":"Services"
        }
    ],
    "sg:phone":"+44 1268 691338",
    "sg:postcode":"E3 2NQ",
    "sg:province":"Greater London",
    "sg:tags":[
        "contractor"
    ],
    "wof:name":"Brooke-Hall Construction Ltd.",
    "wof:placetype":"venue"
},
  "geometry": {"coordinates":[-0.0231790002,51.5335006714],"type":"Point"}
}