{
  "type": "Feature",
  "properties": {
    "iso:country":"GB",
    "sg:address":"Units 10-11 Triplets Poldice, St Day",
    "sg:city":"Redruth",
    "sg:classifiers":[
        {
            "category":"Manufacturing",
            "subcategory":"Wood Products",
            "type":"Manufacturing & Wholesale Goods"
        }
    ],
    "sg:postcode":"TR16 5PZ",
    "sg:province":"Cornwall",
    "sg:tags":[
        "maker",
        "cabinet"
    ],
    "wof:name":"Elegant Interiors",
    "wof:placetype":"venue"
},
  "geometry": {"coordinates":[-5.1755199432,50.2437286377],"type":"Point"}
}