{
  "type": "Feature",
  "properties": {
    "addr:full":"17 Stafford Street, Eccleshall Stafford Staffordshire ST21 6BL",
    "addr:housenumber":"17",
    "addr:postcode":"st21 6bl",
    "addr:street":"Stafford Street",
    "iso:country":"GB",
    "sg:address":"17 Stafford Street, Eccleshall",
    "sg:city":"Stafford",
    "sg:classifiers":[
        {
            "category":"Travel",
            "subcategory":"Hotels & Motels",
            "type":"Entertainment"
        }
    ],
    "sg:phone":"+44 1785 850294",
    "sg:postcode":"ST21 6BL",
    "sg:province":"Staffordshire",
    "wof:name":"Kings Arms Hotel",
    "wof:placetype":"venue"
},
  "geometry": {"coordinates":[-2.251211,52.859077],"type":"Point"}
}