{
  "type": "Feature",
  "properties": {
    "iso:country":"GB",
    "sg:address":"109 Harp Road, Hanwell",
    "sg:city":"London",
    "sg:classifiers":[
        {
            "category":"Professional",
            "subcategory":"Engineering",
            "type":"Services"
        }
    ],
    "sg:postcode":"W7 1JQ",
    "sg:province":"Greater London",
    "sg:tags":[
        "contractor",
        "electrical",
        "engineer"
    ],
    "wof:name":"G Graham Electrical",
    "wof:placetype":"venue"
},
  "geometry": {"coordinates":[-0.3337309957,51.5248832703],"type":"Point"}
}