{
  "type": "Feature",
  "properties": {
    "addr:full":"26 Winsover Road Spalding Lincolnshire PE11 1EJ",
    "addr:housenumber":"26",
    "addr:postcode":"pe11 1ej",
    "addr:street":"Winsover Road",
    "iso:country":"GB",
    "sg:address":"26 Winsover Road",
    "sg:city":"Spalding",
    "sg:classifiers":[
        {
            "category":"Home & Garden",
            "subcategory":"Home Furnishings",
            "type":"Retail Goods"
        },
        {
            "category":"Building & Trades",
            "subcategory":"Landfill",
            "type":"Services"
        }
    ],
    "sg:phone":"+44 1775 760620",
    "sg:postcode":"PE11 1EJ",
    "sg:province":"Lincolnshire",
    "sg:tags":[
        "blind",
        "awning",
        "canopy",
        "blinds"
    ],
    "wof:name":"B T Blinds",
    "wof:placetype":"venue"
},
  "geometry": {"coordinates":[-0.1576360017,52.78698349],"type":"Point"}
}