{
  "type": "Feature",
  "properties": {
    "addr:full":"Bankside House, 107-112 Leadenhall Street London Greater London EC3A 4AQ",
    "addr:housenumber":"107-112",
    "addr:postcode":"ec3a 4aq",
    "addr:street":"Leadenhall Street",
    "iso:country":"GB",
    "sg:address":"Bankside House, 107-112 Leadenhall Street",
    "sg:city":"London",
    "sg:classifiers":[
        {
            "category":"Real Estate",
            "subcategory":"Real Estate Agent",
            "type":"Services"
        }
    ],
    "sg:phone":"+44 20 7891 2472",
    "sg:postcode":"EC3A 4AQ",
    "sg:province":"Greater London",
    "wof:name":"The Property Management Partnership",
    "wof:placetype":"venue"
},
  "geometry": {"coordinates":[-0.080713,51.513603],"type":"Point"}
}