{
  "type": "Feature",
  "properties": {
    "addr:full":"15 Boston Rd Boston Lincolnshire PE20 1DT",
    "addr:housenumber":"15",
    "addr:postcode":"pe20 1dt",
    "addr:street":"Boston Rd",
    "iso:country":"GB",
    "sg:address":"15 Boston Rd",
    "sg:city":"Boston",
    "sg:classifiers":[
        {
            "category":"Health Services",
            "subcategory":"Clinic",
            "type":"Services"
        }
    ],
    "sg:phone":"+44 1205 723101",
    "sg:postcode":"PE20 1DT",
    "sg:province":"Lincolnshire",
    "sg:tags":[
        "aromatherapy"
    ],
    "wof:name":"Holistic Aromatherapy Clinic",
    "wof:placetype":"venue"
},
  "geometry": {"coordinates":[-0.05782,52.930386],"type":"Point"}
}