{
  "type": "Feature",
  "properties": {
    "addr:full":"415 Rayners Lane Pinner Greater London HA5 5ER",
    "addr:housenumber":"415",
    "addr:postcode":"ha5 5er",
    "addr:street":"Rayners Lane",
    "iso:country":"GB",
    "sg:address":"415 Rayners Lane",
    "sg:city":"Pinner",
    "sg:classifiers":[
        {
            "category":"Food & Beverages",
            "subcategory":"Liquor & Beverages",
            "type":"Retail Goods"
        }
    ],
    "sg:postcode":"HA5 5ER",
    "sg:province":"Greater London",
    "sg:tags":[
        "beer",
        "wine",
        "spirit",
        "wines"
    ],
    "wof:name":"UNWINS WINE MERCHANTS",
    "wof:placetype":"venue"
},
  "geometry": {"coordinates":[-0.37132,51.576691],"type":"Point"}
}