{
  "type": "Feature",
  "properties": {
    "addr:full":"Beacon Park Road, Peverell Plymouth Devon PL2 3JP",
    "addr:postcode":"pl2 3jp",
    "addr:street":"Park Road Peverell",
    "iso:country":"GB",
    "sg:address":"Beacon Park Road, Peverell",
    "sg:city":"Plymouth",
    "sg:classifiers":[
        {
            "category":"Sports & Exercise",
            "subcategory":"Tennis Court",
            "type":"Entertainment"
        }
    ],
    "sg:phone":"+44 1752 777454",
    "sg:postcode":"PL2 3JP",
    "sg:province":"Devon",
    "sg:tags":[
        "squash"
    ],
    "wof:name":"Plymouth Albion R F C",
    "wof:placetype":"venue"
},
  "geometry": {"coordinates":[-4.1509289742,50.395488739],"type":"Point"}
}