{
  "type": "Feature",
  "properties": {
    "iso:country":"GB",
    "sg:address":"Northolt Rd",
    "sg:city":"Harrow",
    "sg:classifiers":[
        {
            "category":"Health Services",
            "subcategory":"Clinic",
            "type":"Services"
        }
    ],
    "sg:phone":"+44 20 8422 1113",
    "sg:postcode":"HA2 8EQ",
    "sg:province":"Greater London",
    "sg:tags":[
        "nh"
    ],
    "wof:name":"Northolt Road Clinic",
    "wof:placetype":"venue"
},
  "geometry": {"coordinates":[-0.353699,51.564404],"type":"Point"}
}