{
  "type": "Feature",
  "properties": {
    "addr:full":"28 High St Southampton Hampshire SO30 2EA",
    "addr:housenumber":"28",
    "addr:postcode":"so30 2ea",
    "addr:street":"High St",
    "iso:country":"GB",
    "sg:address":"28 High St",
    "sg:city":"Southampton",
    "sg:classifiers":[
        {
            "category":"Utilities",
            "subcategory":"Fuel Oil & Lpg",
            "type":"Services"
        }
    ],
    "sg:phone":"+44 1489 781516",
    "sg:postcode":"SO30 2EA",
    "sg:province":"Hampshire",
    "sg:tags":[
        "distributor"
    ],
    "wof:name":"Butler Fuels",
    "wof:placetype":"venue"
},
  "geometry": {"coordinates":[-1.272275,50.914436],"type":"Point"}
}