{
  "type": "Feature",
  "properties": {
    "iso:country":"GB",
    "sg:address":"9a Market Place",
    "sg:city":"Rugby",
    "sg:classifiers":[
        {
            "category":"Shopping",
            "subcategory":"Beauty & Cosmetics",
            "type":"Retail Goods"
        }
    ],
    "sg:phone":"+44 1788 536800",
    "sg:postcode":"CV21 3DU",
    "sg:province":"Warwickshire",
    "sg:tags":[
        "product"
    ],
    "wof:name":"The Body Shop International plc",
    "wof:placetype":"venue"
},
  "geometry": {"coordinates":[-1.262367,52.372032],"type":"Point"}
}