{
  "type": "Feature",
  "properties": {
    "addr:full":"21 Piel Street, Roa Island Barrow-in-furness Cumbria LA13 0QJ",
    "addr:housenumber":"21",
    "addr:postcode":"la13 0qj",
    "addr:street":"Piel Street Roa Island",
    "iso:country":"GB",
    "sg:address":"21 Piel Street, Roa Island",
    "sg:city":"Barrow-in-furness",
    "sg:classifiers":[
        {
            "category":"Building & Trades",
            "subcategory":"Construction",
            "type":"Services"
        }
    ],
    "sg:postcode":"LA13 0QJ",
    "sg:province":"Cumbria",
    "sg:tags":[
        "dry",
        "lining",
        "plasterers",
        "screeders"
    ],
    "wof:name":"Allen Plastering & Building Contractor",
    "wof:placetype":"venue"
},
  "geometry": {"coordinates":[-3.174613,54.074547],"type":"Point"}
}