{
  "type": "Feature",
  "properties": {
    "iso:country":"GB",
    "sg:address":"P O Box 21, Carr Lane",
    "sg:city":"Prescot",
    "sg:classifiers":[
        {
            "category":"Home & Garden",
            "subcategory":"Hardware",
            "type":"Retail Goods"
        }
    ],
    "sg:phone":"+44 151 430 4300",
    "sg:postcode":"L34 1PD",
    "sg:province":"Merseyside",
    "sg:tags":[
        "product",
        "wire",
        "electrical"
    ],
    "wof:name":"Bicc Rod Rollers Ltd",
    "wof:placetype":"venue"
},
  "geometry": {"coordinates":[-2.803034,53.430275],"type":"Point"}
}