{
  "type": "Feature",
  "properties": {
    "iso:country":"GB",
    "sg:address":"5 Bankfields Court, Bankfields Road",
    "sg:city":"Middlesbrough",
    "sg:classifiers":[
        {
            "category":"Health Services",
            "subcategory":"Clinic",
            "type":"Services"
        }
    ],
    "sg:postcode":"TS6 0TG",
    "sg:province":"North Yorkshire",
    "sg:tags":[
        "nh"
    ],
    "wof:name":"National Health Service Executive Headqu",
    "wof:placetype":"venue"
},
  "geometry": {"coordinates":[-1.152099,54.552921],"type":"Point"}
}