{
  "type": "Feature",
  "properties": {
    "iso:country":"GB",
    "sg:address":"6-8 Blackburn Road",
    "sg:city":"Accrington",
    "sg:classifiers":[
        {
            "category":"Home & Garden",
            "subcategory":"Hardware",
            "type":"Retail Goods"
        }
    ],
    "sg:postcode":"BB5 1HD",
    "sg:province":"Lancashire",
    "sg:tags":[
        "retailer",
        "lighting"
    ],
    "wof:name":"Lighthouse",
    "wof:placetype":"venue"
},
  "geometry": {"coordinates":[-2.36201,53.752804],"type":"Point"}
}