{
  "type": "Feature",
  "properties": {
    "addr:full":"Westhoughton Road, Adlington Chorley Lancashire PR7 4ET",
    "addr:postcode":"pr7 4et",
    "addr:street":"Westhoughton Road",
    "iso:country":"GB",
    "sg:address":"Westhoughton Road, Adlington",
    "sg:city":"Chorley",
    "sg:classifiers":[
        {
            "category":"Retail",
            "subcategory":"Auto Repair",
            "type":"Services"
        }
    ],
    "sg:postcode":"PR7 4ET",
    "sg:province":"Lancashire",
    "sg:tags":[
        "modification",
        "garage",
        "related"
    ],
    "wof:name":"Red Rose Garage",
    "wof:placetype":"venue"
},
  "geometry": {"coordinates":[-2.610103,53.618488],"type":"Point"}
}