{
  "type": "Feature",
  "properties": {
    "addr:full":"Hellier House, Shaw Hellier Business Centre, Two Woods Lane Brierley Hill West Midlands DY5 1TA",
    "addr:postcode":"dy5 1ta",
    "addr:street":"Woods Lane",
    "iso:country":"GB",
    "sg:address":"Hellier House, Shaw Hellier Business Centre, Two Woods Lane",
    "sg:city":"Brierley Hill",
    "sg:classifiers":[
        {
            "category":"Professional",
            "subcategory":"Computer Services",
            "type":"Services"
        }
    ],
    "sg:phone":"+44 1217 11646",
    "sg:postcode":"DY5 1TA",
    "sg:province":"West Midlands",
    "sg:tags":[
        "system",
        "software"
    ],
    "wof:name":"P R O Iv Ltd.",
    "wof:placetype":"venue"
},
  "geometry": {"coordinates":[-2.109609,52.476116],"type":"Point"}
}