{
  "type": "Feature",
  "properties": {
    "iso:country":"GB",
    "sg:address":"510 Liverpool Rd",
    "sg:city":"Manchester",
    "sg:classifiers":[
        {
            "category":"Retail",
            "subcategory":"Funeral Services",
            "type":"Services"
        }
    ],
    "sg:phone":"+44 161 777 9199",
    "sg:postcode":"M44 6AJ",
    "sg:province":"Greater Manchester",
    "wof:name":"Carriages",
    "wof:placetype":"venue"
},
  "geometry": {"coordinates":[-2.425596,53.440186],"type":"Point"}
}