{
  "type": "Feature",
  "properties": {
    "iso:country":"GB",
    "sg:address":"105 Mayals Road, Mayals",
    "sg:city":"Swansea",
    "sg:classifiers":[
        {
            "category":"Retail",
            "subcategory":"Veterinary Services",
            "type":"Services"
        }
    ],
    "sg:postcode":"SA3 5DH",
    "sg:province":"Swansea",
    "sg:tags":[
        "surgeon"
    ],
    "wof:name":"St.James Veterinary Group",
    "wof:placetype":"venue"
},
  "geometry": {"coordinates":[-4.0059790611,51.5936317444],"type":"Point"}
}