{
  "type": "Feature",
  "properties": {
    "addr:full":"13-14 Pydar Street Truro Cornwall TR1 2AX",
    "addr:housenumber":"13-14",
    "addr:postcode":"tr1 2ax",
    "addr:street":"Pydar Street",
    "iso:country":"GB",
    "sg:address":"13-14 Pydar Street",
    "sg:city":"Truro",
    "sg:classifiers":[
        {
            "category":"Home & Garden",
            "subcategory":"Household Appliances",
            "type":"Retail Goods"
        }
    ],
    "sg:phone":"+44 1872 240981",
    "sg:postcode":"TR1 2AX",
    "sg:province":"Cornwall",
    "sg:tags":[
        "electrical",
        "domestic"
    ],
    "wof:name":"Dixons",
    "wof:placetype":"venue"
},
  "geometry": {"coordinates":[-5.053623,50.264465],"type":"Point"}
}