{
  "type": "Feature",
  "properties": {
    "addr:full":"3 Cross, Oath Hill Malpas Cheshire SY14 8DQ",
    "addr:housenumber":"3",
    "addr:postcode":"sy14 8dq",
    "addr:street":"Cross Oath",
    "iso:country":"GB",
    "sg:address":"3 Cross, Oath Hill",
    "sg:city":"Malpas",
    "sg:classifiers":[
        {
            "category":"Building & Trades",
            "subcategory":"Cleaning & Sanitation",
            "type":"Services"
        }
    ],
    "sg:phone":"+44 1948 860103",
    "sg:postcode":"SY14 8DQ",
    "sg:province":"Cheshire",
    "sg:tags":[
        "sweep",
        "chimney"
    ],
    "wof:name":"S C Haycocks",
    "wof:placetype":"venue"
},
  "geometry": {"coordinates":[-2.766258955,53.020980835],"type":"Point"}
}