{
  "type": "Feature",
  "properties": {
    "addr:full":"Unit H2 Cowlairs Nottingham Nottinghamshire NG5 9RA",
    "addr:postcode":"ng5 9ra",
    "iso:country":"GB",
    "sg:address":"Unit H2 Cowlairs",
    "sg:city":"Nottingham",
    "sg:classifiers":[
        {
            "category":"Professional",
            "type":"Services"
        }
    ],
    "sg:phone":"+44 115 927 9323",
    "sg:postcode":"NG5 9RA",
    "sg:province":"Nottinghamshire",
    "sg:tags":[
        "services",
        "belt",
        "conveyor"
    ],
    "wof:name":"Aircotronic Ltd.",
    "wof:placetype":"venue"
},
  "geometry": {"coordinates":[-1.1789720058,53.0014343262],"type":"Point"}
}