{
  "type": "Feature",
  "properties": {
    "addr:full":"233 Frodingham Rd Scunthorpe Lincolnshire DN15 7NS",
    "addr:housenumber":"233",
    "addr:postcode":"dn15 7ns",
    "addr:street":"Frodingham Rd",
    "iso:country":"GB",
    "sg:address":"233 Frodingham Rd",
    "sg:city":"Scunthorpe",
    "sg:classifiers":[
        {
            "category":"Professional",
            "subcategory":"Printing & Photocopies",
            "type":"Services"
        }
    ],
    "sg:phone":"+44 1724 846937",
    "sg:postcode":"DN15 7NS",
    "sg:province":"Lincolnshire",
    "sg:tags":[
        "printer"
    ],
    "wof:name":"S G T Design",
    "wof:placetype":"venue"
},
  "geometry": {"coordinates":[-0.6559060216,53.5970077515],"type":"Point"}
}