{
  "type": "Feature",
  "properties": {
    "addr:full":"40 Lagland Street Poole Dorset BH15 1QG",
    "addr:housenumber":"40",
    "addr:postcode":"bh15 1qg",
    "addr:street":"Lagland Street",
    "iso:country":"GB",
    "sg:address":"40 Lagland Street",
    "sg:city":"Poole",
    "sg:classifiers":[
        {
            "category":"Communications",
            "type":"Services"
        }
    ],
    "sg:phone":"+44 1202 679671",
    "sg:postcode":"BH15 1QG",
    "sg:province":"Dorset",
    "sg:tags":[
        "audio-visual"
    ],
    "wof:name":"Common Heard Productions",
    "wof:placetype":"venue"
},
  "geometry": {"coordinates":[-1.982261,50.715687],"type":"Point"}
}