{
  "type": "Feature",
  "properties": {
    "iso:country":"GB",
    "sg:address":"566 London Road",
    "sg:city":"Isleworth",
    "sg:classifiers":[
        {
            "category":"Personal",
            "subcategory":"Tattoo Parlor",
            "type":"Services"
        }
    ],
    "sg:postcode":"TW7 4EP",
    "sg:province":"Greater London",
    "sg:tags":[
        "tattooing",
        "piercing"
    ],
    "wof:name":"Living Canvas",
    "wof:placetype":"venue"
},
  "geometry": {"coordinates":[-0.344682,51.474117],"type":"Point"}
}