{
  "type": "Feature",
  "properties": {
    "addr:full":"1 Newtown, Broad Chalke Salisbury Dorset SP5 5DS",
    "addr:housenumber":"1",
    "addr:postcode":"sp5 5ds",
    "addr:street":"Newtown",
    "iso:country":"GB",
    "sg:address":"1 Newtown, Broad Chalke",
    "sg:city":"Salisbury",
    "sg:classifiers":[
        {
            "category":"Home & Garden",
            "subcategory":"Building Materials",
            "type":"Retail Goods"
        },
        {
            "category":"Building & Trades",
            "subcategory":"Construction",
            "type":"Services"
        }
    ],
    "sg:postcode":"SP5 5DS",
    "sg:province":"Dorset",
    "sg:tags":[
        "fencing",
        "builder"
    ],
    "wof:name":"Ronald W Chalk",
    "wof:placetype":"venue"
},
  "geometry": {"coordinates":[-1.93981,51.026321],"type":"Point"}
}