{
  "type": "Feature",
  "properties": {
    "addr:full":"Creda Works, Blythe Bridge Stoke-on-trent Staffordshire ST11 9LN",
    "addr:postcode":"st11 9ln",
    "addr:street":"Bridge",
    "iso:country":"GB",
    "sg:address":"Creda Works, Blythe Bridge",
    "sg:city":"Stoke-on-trent",
    "sg:classifiers":[
        {
            "category":"Home & Garden",
            "subcategory":"Household Appliances",
            "type":"Retail Goods"
        }
    ],
    "sg:phone":"+44 1782 388300",
    "sg:postcode":"ST11 9LN",
    "sg:province":"Staffordshire",
    "sg:tags":[
        "electrical"
    ],
    "wof:name":"Hotpoint Creda Cannon",
    "wof:placetype":"venue"
},
  "geometry": {"coordinates":[-2.1750690937,53.0293693542],"type":"Point"}
}