{
  "type": "Feature",
  "properties": {
    "addr:full":"14 Upper Market Street Haverfordwest Pembrokeshire SA61 1QA",
    "addr:housenumber":"14",
    "addr:postcode":"sa61 1qa",
    "addr:street":"Upper Market Street",
    "iso:country":"GB",
    "sg:address":"14 Upper Market Street",
    "sg:city":"Haverfordwest",
    "sg:classifiers":[
        {
            "category":"Food & Beverages",
            "subcategory":"Meat & Fish",
            "type":"Retail Goods"
        }
    ],
    "sg:postcode":"SA61 1QA",
    "sg:province":"Pembrokeshire",
    "sg:tags":[
        "butcher"
    ],
    "wof:name":"John Hayes Family Butcher",
    "wof:placetype":"venue"
},
  "geometry": {"coordinates":[-4.9702830315,51.7998008728],"type":"Point"}
}