{
  "type": "Feature",
  "properties": {
    "addr:full":"Lab 503, 91 Western Rd Brighton East Sussex BN1 2NW",
    "addr:housenumber":"503 91",
    "addr:postcode":"bn1 2nw",
    "addr:street":"Western Rd",
    "iso:country":"GB",
    "sg:address":"Lab 503, 91 Western Rd",
    "sg:city":"Brighton",
    "sg:classifiers":[
        {
            "category":"Professional",
            "subcategory":"Testing Lab",
            "type":"Services"
        }
    ],
    "sg:phone":"+44 1273 241082",
    "sg:postcode":"BN1 2NW",
    "sg:province":"East Sussex",
    "sg:tags":[
        "inspection",
        "calibration"
    ],
    "wof:name":"EZ Test",
    "wof:placetype":"venue"
},
  "geometry": {"coordinates":[-0.15172,50.824471],"type":"Point"}
}