{
  "type": "Feature",
  "properties": {
    "iso:country":"GB",
    "sg:address":"Station Road, Taplow",
    "sg:city":"Maidenhead",
    "sg:classifiers":[
        {
            "category":"Autos & Motor Vehicles",
            "subcategory":"Automobile Sales",
            "type":"Retail Goods"
        }
    ],
    "sg:phone":"+44 1628 605353",
    "sg:postcode":"SL6 0NT",
    "sg:province":"Berkshire",
    "sg:tags":[
        "car"
    ],
    "wof:name":"S G T Ltd.",
    "wof:placetype":"venue"
},
  "geometry": {"coordinates":[-0.68019,51.523087],"type":"Point"}
}