{
  "type": "Feature",
  "properties": {
    "addr:full":"Old Barn Farm Road, Woolsbridge Industrial Estate, Three Legged Cross Wimborne Dorset BH21 6SP",
    "addr:housenumber":"estate",
    "addr:postcode":"bh21 6sp",
    "addr:street":"Old;Farm Road Woolsbridge Industrial",
    "iso:country":"GB",
    "sg:address":"Old Barn Farm Road, Woolsbridge Industrial Estate, Three Legged Cross",
    "sg:city":"Wimborne",
    "sg:classifiers":[
        {
            "category":"Home & Garden",
            "subcategory":"Building Materials",
            "type":"Retail Goods"
        },
        {
            "category":"Bars & Pubs",
            "subcategory":"Oxygen Bar",
            "type":"Food & Drink"
        }
    ],
    "sg:phone":"+44 1202 824181",
    "sg:postcode":"BH21 6SP",
    "sg:province":"Dorset",
    "sg:tags":[
        "ventilator",
        "ventilation",
        "system"
    ],
    "sg:website":"http://www.handc-ltd.co.uk",
    "wof:name":"Heating & Cooling Services Ltd",
    "wof:placetype":"venue"
},
  "geometry": {"coordinates":[-1.8644889593,50.8434753418],"type":"Point"}
}