{
  "type": "Feature",
  "properties": {
    "addr:full":"Fen Place Farm, East St Crawley Surrey RH10 4QA",
    "addr:postcode":"rh10 4qa",
    "addr:street":"Fen Place Farm East St",
    "iso:country":"GB",
    "sg:address":"Fen Place Farm, East St",
    "sg:city":"Crawley",
    "sg:classifiers":[
        {
            "category":"Wholesale",
            "subcategory":"Farm Supplies",
            "type":"Manufacturing & Wholesale Goods"
        }
    ],
    "sg:phone":"+44 1342 717238",
    "sg:postcode":"RH10 4QA",
    "sg:province":"Surrey",
    "sg:tags":[
        "straw",
        "hay",
        "merchant"
    ],
    "wof:name":"Abbott & Co",
    "wof:placetype":"venue"
},
  "geometry": {"coordinates":[-0.0860290006,51.12292099],"type":"Point"}
}