{
  "type": "Feature",
  "properties": {
    "iso:country":"GB",
    "sg:address":"Flat 2, 2 Wesley Villas",
    "sg:city":"Frome",
    "sg:classifiers":[
        {
            "category":"Place Of Worship",
            "type":"Public Place"
        }
    ],
    "sg:phone":"+44 1373 452383",
    "sg:postcode":"BA11 1HP",
    "sg:province":"Somerset",
    "wof:name":"Wesley Methodist Church",
    "wof:placetype":"venue"
},
  "geometry": {"coordinates":[-2.318807,51.228558],"type":"Point"}
}