{
  "type": "Feature",
  "properties": {
    "addr:full":"Fen Farm, Rush Grn, Barnham Broom Norwich Norfolk NR9 4EA",
    "addr:postcode":"nr9 4ea",
    "addr:street":"Rush Grn Barnham;Norwich Norfolk",
    "iso:country":"GB",
    "sg:address":"Fen Farm, Rush Grn, Barnham Broom",
    "sg:city":"Norwich",
    "sg:classifiers":[
        {
            "category":"Manufacturing",
            "subcategory":"Signs",
            "type":"Manufacturing & Wholesale Goods"
        }
    ],
    "sg:postcode":"NR9 4EA",
    "sg:province":"Norfolk",
    "sg:tags":[
        "writer"
    ],
    "wof:name":"U K Sports Graphics",
    "wof:placetype":"venue"
},
  "geometry": {"coordinates":[1.08055,52.624039],"type":"Point"}
}