{
  "type": "Feature",
  "properties": {
    "iso:country":"GB",
    "sg:address":"Old Wellington Road, Eccles",
    "sg:city":"Manchester",
    "sg:classifiers":[
        {
            "category":"Home & Garden",
            "subcategory":"Hardware",
            "type":"Retail Goods"
        }
    ],
    "sg:phone":"+44 161 707 7818",
    "sg:postcode":"M30 9QG",
    "sg:province":"Greater Manchester",
    "sg:tags":[
        "compressor",
        "air"
    ],
    "wof:name":"P S Pneumatic Services Ltd.",
    "wof:placetype":"venue"
},
  "geometry": {"coordinates":[-2.348869,53.486877],"type":"Point"}
}