{
  "type": "Feature",
  "properties": {
    "iso:country":"GB",
    "sg:address":"Mercer Street, Clayton-le-moors",
    "sg:city":"Accrington",
    "sg:classifiers":[
        {
            "category":"Education",
            "subcategory":"Dance Studio",
            "type":"Public Place"
        }
    ],
    "sg:phone":"+44 1254 872036",
    "sg:postcode":"BB5 5NZ",
    "sg:province":"Lancashire",
    "sg:tags":[
        "school",
        "dancing"
    ],
    "wof:name":"Royal Dance Club",
    "wof:placetype":"venue"
},
  "geometry": {"coordinates":[-2.383839,53.778107],"type":"Point"}
}