{
  "type": "Feature",
  "properties": {
    "addr:full":"1 Ecclesall Road South Sheffield Derbyshire S11 9PA",
    "addr:housenumber":"1",
    "addr:postcode":"s11 9pa",
    "addr:street":"Ecclesall Road South",
    "iso:country":"GB",
    "sg:address":"1 Ecclesall Road South",
    "sg:city":"Sheffield",
    "sg:classifiers":[
        {
            "category":"Autos & Motor Vehicles",
            "subcategory":"Automobile Sales",
            "type":"Retail Goods"
        },
        {
            "category":"Professional",
            "subcategory":"Management & Consulting",
            "type":"Services"
        }
    ],
    "sg:phone":"+44 114 267 0670",
    "sg:postcode":"S11 9PA",
    "sg:province":"Derbyshire",
    "sg:tags":[
        "car",
        "holding",
        "activity"
    ],
    "wof:name":"Briers Investment Leasing Ltd.",
    "wof:placetype":"venue"
},
  "geometry": {"coordinates":[-1.508174,53.35981],"type":"Point"}
}