{
  "type": "Feature",
  "properties": {
    "iso:country":"GB",
    "sg:address":"189c High Street, Harlesden",
    "sg:city":"London",
    "sg:classifiers":[
        {
            "category":"Retail",
            "subcategory":"Driving School",
            "type":"Services"
        }
    ],
    "sg:phone":"+44 20 8965 6596",
    "sg:postcode":"NW10 4TE",
    "sg:province":"Greater London",
    "wof:name":"N S M (Neasden) Ltd.",
    "wof:placetype":"venue"
},
  "geometry": {"coordinates":[-0.241517,51.534027],"type":"Point"}
}