{
  "type": "Feature",
  "properties": {
    "addr:full":"19b Fareham Enterprise Centre, Newgate Lane Fareham Hampshire PO14 1TH",
    "addr:housenumber":"19b;enterprise centre",
    "addr:postcode":"po14 1th",
    "addr:street":"Newgate Lane",
    "iso:country":"GB",
    "sg:address":"19b Fareham Enterprise Centre, Newgate Lane",
    "sg:city":"Fareham",
    "sg:classifiers":[
        {
            "category":"Professional",
            "subcategory":"Management & Consulting",
            "type":"Services"
        }
    ],
    "sg:phone":"+44 1329 515200",
    "sg:postcode":"PO14 1TH",
    "sg:province":"Hampshire",
    "sg:tags":[
        "marketing",
        "consultant"
    ],
    "wof:name":"Andy Tredgett Canvassing Services",
    "wof:placetype":"venue"
},
  "geometry": {"coordinates":[-1.184910059,50.8413391113],"type":"Point"}
}