{
  "type": "Feature",
  "properties": {
    "addr:full":"52-56 Camden High Street London Greater London NW1 0LT",
    "addr:housenumber":"52-56",
    "addr:postcode":"nw1 0lt",
    "addr:street":"Camden High Street",
    "iso:country":"GB",
    "sg:address":"52-56 Camden High Street",
    "sg:city":"London",
    "sg:classifiers":[
        {
            "category":"Home & Garden",
            "subcategory":"Hardware",
            "type":"Retail Goods"
        }
    ],
    "sg:phone":"+44 20 7387 2579",
    "sg:postcode":"NW1 0LT",
    "sg:province":"Greater London",
    "wof:name":"Romanys",
    "wof:placetype":"venue"
},
  "geometry": {"coordinates":[-0.13704,51.537567],"type":"Point"}
}