{
  "type": "Feature",
  "properties": {
    "addr:full":"Old Green Farm, Earthcott Grn, Alveston Bristol Gloucestershire BS35 3TD",
    "addr:postcode":"bs35 3td",
    "addr:street":"Green;Earthcott Grn",
    "iso:country":"GB",
    "sg:address":"Old Green Farm, Earthcott Grn, Alveston",
    "sg:city":"Bristol",
    "sg:classifiers":[
        {
            "category":"Farming",
            "subcategory":"Livestock Farm",
            "type":"Manufacturing & Wholesale Goods"
        },
        {
            "category":"Farming",
            "subcategory":"Farm",
            "type":"Manufacturing & Wholesale Goods"
        }
    ],
    "sg:postcode":"BS35 3TD",
    "sg:province":"Gloucestershire",
    "sg:tags":[
        "mixed",
        "crop",
        "others"
    ],
    "wof:name":"Richard J & Kathleen A King",
    "wof:placetype":"venue"
},
  "geometry": {"coordinates":[-2.532049,51.592155],"type":"Point"}
}