{
  "type": "Feature",
  "properties": {
    "addr:full":"37 West Paddock, Leyland Preston Lancashire PR5 1HR",
    "addr:housenumber":"37",
    "addr:postcode":"pr5 1hr",
    "addr:street":"West Paddock Leyland",
    "iso:country":"GB",
    "sg:address":"37 West Paddock, Leyland",
    "sg:city":"Preston",
    "sg:classifiers":[
        {
            "category":"Shopping",
            "subcategory":"Pharmacy",
            "type":"Retail Goods"
        }
    ],
    "sg:phone":"+44 1772 622288",
    "sg:postcode":"PR5 1HR",
    "sg:province":"Lancashire",
    "sg:tags":[
        "pharmacist",
        "chemist"
    ],
    "wof:name":"Worden Pharmacy",
    "wof:placetype":"venue"
},
  "geometry": {"coordinates":[-2.6934900284,53.6953392029],"type":"Point"}
}