{
  "type": "Feature",
  "properties": {
    "addr:full":"Rothay Road Ambleside Cumbria LA22 0EE",
    "addr:postcode":"la22 0ee",
    "addr:street":"Rothay Road",
    "iso:country":"GB",
    "sg:address":"Rothay Road",
    "sg:city":"Ambleside",
    "sg:classifiers":[
        {
            "category":"Autos & Motor Vehicles",
            "subcategory":"Automobile Sales",
            "type":"Retail Goods"
        },
        {
            "category":"Retail",
            "subcategory":"Auto Repair",
            "type":"Services"
        }
    ],
    "sg:phone":"+44 15394 31764",
    "sg:postcode":"LA22 0EE",
    "sg:province":"Cumbria",
    "sg:tags":[
        "modification",
        "specialist",
        "sales",
        "car",
        "classic"
    ],
    "wof:name":"Garner Restorations",
    "wof:placetype":"venue"
},
  "geometry": {"coordinates":[-2.964649,54.42989],"type":"Point"}
}