{
  "type": "Feature",
  "properties": {
    "addr:full":"Trevella Cottage, Crantock Newquay Cornwall TR8 5EW",
    "addr:postcode":"tr8 5ew",
    "iso:country":"GB",
    "sg:address":"Trevella Cottage, Crantock",
    "sg:city":"Newquay",
    "sg:classifiers":[
        {
            "category":"Recreation",
            "subcategory":"Campground",
            "type":"Entertainment"
        }
    ],
    "sg:phone":"+44 1637 830309",
    "sg:postcode":"TR8 5EW",
    "sg:province":"Cornwall",
    "sg:tags":[
        "holiday",
        "camp",
        "park",
        "centre"
    ],
    "wof:name":"A J Trevella",
    "wof:placetype":"venue"
},
  "geometry": {"coordinates":[-5.110519,50.400299],"type":"Point"}
}