{
  "type": "Feature",
  "properties": {
    "addr:full":"443a Carnation Lane, Bowerhill Melksham Wiltshire SN12 6RD",
    "addr:housenumber":"443a",
    "addr:postcode":"sn12 6rd",
    "addr:street":"Carnation Lane",
    "iso:country":"GB",
    "sg:address":"443a Carnation Lane, Bowerhill",
    "sg:city":"Melksham",
    "sg:classifiers":[
        {
            "category":"Banks & Credit Unions",
            "subcategory":"Financial Services",
            "type":"Services"
        }
    ],
    "sg:phone":"+44 1225 708522",
    "sg:postcode":"SN12 6RD",
    "sg:province":"Wiltshire",
    "sg:tags":[
        "consultant"
    ],
    "wof:name":"F M H Ltd.",
    "wof:placetype":"venue"
},
  "geometry": {"coordinates":[-2.106293,51.356873],"type":"Point"}
}