{
  "type": "Feature",
  "properties": {
    "iso:country":"GB",
    "sg:address":"Troed Y Rhiw, Llanddewi Brefi",
    "sg:city":"Shrewsbury",
    "sg:classifiers":[
        {
            "category":"Farming",
            "subcategory":"Livestock Farm",
            "type":"Manufacturing & Wholesale Goods"
        }
    ],
    "sg:phone":"+44 1974 298556",
    "sg:postcode":"SY25 6PE",
    "sg:province":"Ceredigion",
    "sg:tags":[
        "others"
    ],
    "wof:name":"J D Jones",
    "wof:placetype":"venue"
},
  "geometry": {"coordinates":[-3.96053,52.17033],"type":"Point"}
}