{
  "type": "Feature",
  "properties": {
    "iso:country":"GB",
    "sg:address":"174 Moorside Road, Swinton",
    "sg:city":"Manchester",
    "sg:classifiers":[
        {
            "category":"Shopping",
            "subcategory":"News",
            "type":"Retail Goods"
        }
    ],
    "sg:phone":"+44 161 794 4281",
    "sg:postcode":"M27 0LE",
    "sg:province":"Greater Manchester",
    "sg:tags":[
        "newsagent"
    ],
    "wof:name":"Moorside News",
    "wof:placetype":"venue"
},
  "geometry": {"coordinates":[-2.3546938896,53.50963974],"type":"Point"}
}