{
  "type": "Feature",
  "properties": {
    "addr:full":"Anton Buildings, Wessington Way Sunderland Tyne and Wear SR5 3NS",
    "addr:postcode":"sr5 3ns",
    "addr:street":"Anton Buildings Wessington Way",
    "iso:country":"GB",
    "sg:address":"Anton Buildings, Wessington Way",
    "sg:city":"Sunderland",
    "sg:classifiers":[
        {
            "category":"Professional",
            "subcategory":"Detective & Security Services",
            "type":"Services"
        }
    ],
    "sg:phone":"+44 191 549 2116",
    "sg:postcode":"SR5 3NS",
    "sg:province":"Tyne and Wear",
    "wof:name":"Asgard Security Services",
    "wof:placetype":"venue"
},
  "geometry": {"coordinates":[-1.46685,54.92065],"type":"Point"}
}