{
  "type": "Feature",
  "properties": {
    "addr:full":"Tea Rooms, 30 Goodramgate York North Yorkshire YO1 7LG",
    "addr:housenumber":"30",
    "addr:postcode":"yo1 7lg",
    "addr:street":"Goodramgate",
    "iso:country":"GB",
    "sg:address":"Tea Rooms, 30 Goodramgate",
    "sg:city":"York",
    "sg:classifiers":[
        {
            "category":"Cafe",
            "type":"Food & Drink"
        }
    ],
    "sg:phone":"+44 1904 659282",
    "sg:postcode":"YO1 7LG",
    "sg:province":"North Yorkshire",
    "sg:tags":[
        "tea",
        "room"
    ],
    "wof:name":"The National Trust",
    "wof:placetype":"venue"
},
  "geometry": {"coordinates":[-1.0792399645,53.9621696472],"type":"Point"}
}