{
  "type": "Feature",
  "properties": {
    "addr:full":"Lickey Road, Rednal Birmingham West Midlands B45 8TD",
    "addr:postcode":"b45 8td",
    "addr:street":"Lickey Road",
    "iso:country":"GB",
    "sg:address":"Lickey Road, Rednal",
    "sg:city":"Birmingham",
    "sg:classifiers":[
        {
            "category":"Education",
            "subcategory":"School",
            "type":"Public Place"
        },
        {
            "category":"Government",
            "subcategory":"Office",
            "type":"Public Place"
        }
    ],
    "sg:postcode":"B45 8TD",
    "sg:province":"West Midlands",
    "sg:tags":[
        "local",
        "authority"
    ],
    "wof:name":"St Columba's Roman Catholic Junior & Infant School",
    "wof:placetype":"venue"
},
  "geometry": {"coordinates":[-2.014059,52.37278],"type":"Point"}
}