{
  "type": "Feature",
  "properties": {
    "iso:country":"GB",
    "sg:address":"37 The Thoroughfare",
    "sg:city":"Harleston",
    "sg:classifiers":[
        {
            "category":"Food & Beverages",
            "subcategory":"Liquor & Beverages",
            "type":"Retail Goods"
        }
    ],
    "sg:phone":"+44 1379 854955",
    "sg:postcode":"IP20 9AS",
    "sg:province":"Norfolk",
    "sg:tags":[
        "beer",
        "spirit",
        "wines"
    ],
    "wof:name":"Corinium Ltd.",
    "wof:placetype":"venue"
},
  "geometry": {"coordinates":[1.300582,52.403435],"type":"Point"}
}