{
  "type": "Feature",
  "properties": {
    "addr:full":"Shama House, 22 Chalvey Road West Slough Berkshire SL1 2PJ",
    "addr:housenumber":"22",
    "addr:postcode":"sl1 2pj",
    "addr:street":"Chalvey Road West",
    "iso:country":"GB",
    "sg:address":"Shama House, 22 Chalvey Road West",
    "sg:city":"Slough",
    "sg:classifiers":[
        {
            "category":"Insurance",
            "subcategory":"Insurance Agent",
            "type":"Services"
        }
    ],
    "sg:phone":"+44 1753 534141",
    "sg:postcode":"SL1 2PJ",
    "sg:province":"Berkshire",
    "wof:name":"Royal Travel",
    "wof:placetype":"venue"
},
  "geometry": {"coordinates":[-0.602331,51.506069],"type":"Point"}
}