{
  "type": "Feature",
  "properties": {
    "iso:country":"GB",
    "sg:address":"Unit 3 Alexandra Road",
    "sg:city":"Sudbury",
    "sg:classifiers":[
        {
            "category":"Home & Garden",
            "subcategory":"Furniture",
            "type":"Retail Goods"
        }
    ],
    "sg:postcode":"CO10 2XH",
    "sg:province":"Essex",
    "wof:name":"Constable Pine & Design",
    "wof:placetype":"venue"
},
  "geometry": {"coordinates":[0.746455,52.041969],"type":"Point"}
}