{
  "type": "Feature",
  "properties": {
    "addr:full":"2 St Thomas Square Newport Isle of Wight PO30 1SN",
    "addr:housenumber":"2",
    "addr:postcode":"po30 1sn",
    "addr:street":"St Thomas Square",
    "iso:country":"GB",
    "sg:address":"2 St Thomas Square",
    "sg:city":"Newport",
    "sg:classifiers":[
        {
            "category":"Manufacturing",
            "subcategory":"Tools & Machinery",
            "type":"Manufacturing & Wholesale Goods"
        }
    ],
    "sg:phone":"+44 1983 520525",
    "sg:postcode":"PO30 1SN",
    "sg:province":"Isle of Wight",
    "sg:tags":[
        "society",
        "friendly"
    ],
    "wof:name":"Foster Insurance Services",
    "wof:placetype":"venue"
},
  "geometry": {"coordinates":[-1.2962019444,50.6922111511],"type":"Point"}
}