{
  "type": "Feature",
  "properties": {
    "addr:full":"Little Musgrove, Dunkeswell Abbey Honiton Devon EX14 4RP",
    "addr:housenumber":"dunkeswell",
    "addr:postcode":"ex14 4rp",
    "addr:street":"Abbey Honiton",
    "iso:country":"GB",
    "sg:address":"Little Musgrove, Dunkeswell Abbey",
    "sg:city":"Honiton",
    "sg:classifiers":[
        {
            "category":"Building & Trades",
            "subcategory":"Construction",
            "type":"Services"
        }
    ],
    "sg:postcode":"EX14 4RP",
    "sg:province":"Devon",
    "sg:tags":[
        "joiner",
        "carpenter"
    ],
    "wof:name":"C & C M Page",
    "wof:placetype":"venue"
},
  "geometry": {"coordinates":[-3.2232379913,50.8893890381],"type":"Point"}
}