{
  "type": "Feature",
  "properties": {
    "addr:full":"Ryton On Dunsmore Coventry Warwickshire CV8 3EN",
    "addr:postcode":"cv8 3en",
    "addr:street":"Ryton;Dunsmore",
    "iso:country":"GB",
    "sg:address":"Ryton On Dunsmore",
    "sg:city":"Coventry",
    "sg:classifiers":[
        {
            "category":"Government",
            "subcategory":"Police Station",
            "type":"Public Place"
        }
    ],
    "sg:phone":"+44 24 7663 9639",
    "sg:postcode":"CV8 3EN",
    "sg:province":"Warwickshire",
    "sg:tags":[
        "support"
    ],
    "wof:name":"Ryton Police Training Centre",
    "wof:placetype":"venue"
},
  "geometry": {"coordinates":[-1.4416300058,52.3553581238],"type":"Point"}
}