{
  "type": "Feature",
  "properties": {
    "addr:full":"18 Montague Avenue Leigh-on-sea Essex SS9 3SL",
    "addr:housenumber":"18",
    "addr:postcode":"ss9 3sl",
    "addr:street":"Montague Avenue",
    "iso:country":"GB",
    "sg:address":"18 Montague Avenue",
    "sg:city":"Leigh-on-sea",
    "sg:classifiers":[
        {
            "category":"Social Services",
            "subcategory":"Adult Care",
            "type":"Services"
        }
    ],
    "sg:postcode":"SS9 3SL",
    "sg:province":"Essex",
    "sg:tags":[
        "domestic",
        "cleaning"
    ],
    "wof:name":"Orbit Cleaning",
    "wof:placetype":"venue"
},
  "geometry": {"coordinates":[0.6356739998,51.5509796143],"type":"Point"}
}