{
  "type": "Feature",
  "properties": {
    "addr:full":"The Barn, Manor Green Easton Wells Somerset BA5 1ED",
    "addr:postcode":"ba5 1ed",
    "addr:street":"Manor Green",
    "iso:country":"GB",
    "sg:address":"The Barn, Manor Green Easton",
    "sg:city":"Wells",
    "sg:classifiers":[
        {
            "category":"Communications",
            "type":"Services"
        }
    ],
    "sg:phone":"+44 1749 870929",
    "sg:postcode":"BA5 1ED",
    "sg:province":"Somerset",
    "sg:tags":[
        "telecommunication"
    ],
    "wof:name":"Ward Industrial Products Ltd",
    "wof:placetype":"venue"
},
  "geometry": {"coordinates":[-2.698864,51.225925],"type":"Point"}
}