{
  "type": "Feature",
  "properties": {
    "addr:full":"6 Chell Grove Newcastle Staffordshire ST5 8HY",
    "addr:housenumber":"6",
    "addr:postcode":"st5 8hy",
    "addr:street":"Chell Grove",
    "iso:country":"GB",
    "sg:address":"6 Chell Grove",
    "sg:city":"Newcastle",
    "sg:classifiers":[
        {
            "category":"Transit Center",
            "subcategory":"Passenger",
            "type":"Transportation"
        }
    ],
    "sg:phone":"+44 1782 811725",
    "sg:postcode":"ST5 8HY",
    "sg:province":"Staffordshire",
    "sg:tags":[
        "airport"
    ],
    "wof:name":"Airlink UK",
    "wof:placetype":"venue"
},
  "geometry": {"coordinates":[-2.234926939,53.0412635803],"type":"Point"}
}