{
  "type": "Feature",
  "properties": {
    "addr:full":"432 Edgware Road London Greater London W2 1EA",
    "addr:housenumber":"432",
    "addr:postcode":"w2 1ea",
    "addr:street":"Edgware Road",
    "iso:country":"GB",
    "sg:address":"432 Edgware Road",
    "sg:city":"London",
    "sg:classifiers":[
        {
            "category":"Professional",
            "subcategory":"Business Services",
            "type":"Services"
        },
        {
            "category":"Communications",
            "type":"Services"
        }
    ],
    "sg:phone":"+44 20 7723 9616",
    "sg:postcode":"W2 1EA",
    "sg:province":"Greater London",
    "sg:tags":[
        "tv",
        "agent",
        "video",
        "import",
        "export",
        "radio"
    ],
    "wof:name":"A J Electronics Ltd.",
    "wof:placetype":"venue"
},
  "geometry": {"coordinates":[-0.1739680022,51.52293396],"type":"Point"}
}