{
  "type": "Feature",
  "properties": {
    "addr:full":"40 Carnation Road Liverpool Merseyside L9 1HX",
    "addr:housenumber":"40",
    "addr:postcode":"l9 1hx",
    "addr:street":"Carnation Road",
    "iso:country":"GB",
    "sg:address":"40 Carnation Road",
    "sg:city":"Liverpool",
    "sg:classifiers":[
        {
            "category":"Real Estate",
            "subcategory":"Real Estate Operator",
            "type":"Services"
        },
        {
            "category":"Building & Trades",
            "subcategory":"Construction",
            "type":"Services"
        }
    ],
    "sg:phone":"+44 151 523 8830",
    "sg:postcode":"L9 1HX",
    "sg:province":"Merseyside",
    "sg:tags":[
        "concrete",
        "pumping"
    ],
    "wof:name":"Mciver Concrete Pumping Ltd",
    "wof:placetype":"venue"
},
  "geometry": {"coordinates":[-2.951354,53.452747],"type":"Point"}
}