{
  "type": "Feature",
  "properties": {
    "addr:full":"The Lawn, Church La Chesterfield Derbyshire S44 5AG",
    "addr:postcode":"s44 5ag",
    "addr:street":"La Chesterfield",
    "iso:country":"GB",
    "sg:address":"The Lawn, Church La",
    "sg:city":"Chesterfield",
    "sg:classifiers":[
        {
            "category":"Building & Trades",
            "subcategory":"Construction",
            "type":"Services"
        }
    ],
    "sg:phone":"+44 1246 271927",
    "sg:postcode":"S44 5AG",
    "sg:province":"Derbyshire",
    "sg:tags":[
        "heating",
        "contractor"
    ],
    "wof:name":"Hasland Home Heating",
    "wof:placetype":"venue"
},
  "geometry": {"coordinates":[-1.385059,53.234322],"type":"Point"}
}