{
  "type": "Feature",
  "properties": {
    "addr:full":"33 St Crispin Road, Earls Barton Northampton Northamptonshire NN6 0PG",
    "addr:housenumber":"33",
    "addr:postcode":"nn6 0pg",
    "addr:street":"St Crispin Road",
    "iso:country":"GB",
    "sg:address":"33 St Crispin Road, Earls Barton",
    "sg:city":"Northampton",
    "sg:classifiers":[
        {
            "category":"Building & Trades",
            "subcategory":"Plumbing",
            "type":"Services"
        }
    ],
    "sg:phone":"+44 1604 811515",
    "sg:postcode":"NN6 0PG",
    "sg:province":"Northamptonshire",
    "sg:tags":[
        "heating"
    ],
    "wof:name":"Keith Barrow Heating & Plumbing Services Ltd.",
    "wof:placetype":"venue"
},
  "geometry": {"coordinates":[-0.7433279753,52.2668151855],"type":"Point"}
}