{
  "type": "Feature",
  "properties": {
    "iso:country":"GB",
    "sg:address":"26 Blackberry Lane",
    "sg:city":"Halesowen",
    "sg:classifiers":[
        {
            "category":"Professional",
            "subcategory":"Engineering",
            "type":"Services"
        }
    ],
    "sg:phone":"+44 121 602 0866",
    "sg:postcode":"B63 4NX",
    "sg:province":"West Midlands",
    "sg:tags":[
        "contractor",
        "electrical",
        "engineer"
    ],
    "wof:name":"Willetts Fire & Security",
    "wof:placetype":"venue"
},
  "geometry": {"coordinates":[-2.055768013,52.4443283081],"type":"Point"}
}