{
  "type": "Feature",
  "properties": {
    "addr:full":"4 Wordsworth Drive Sheffield South Yorkshire S5 8NP",
    "addr:housenumber":"4",
    "addr:postcode":"s5 8np",
    "addr:street":"Wordsworth Drive",
    "iso:country":"GB",
    "sg:address":"4 Wordsworth Drive",
    "sg:city":"Sheffield",
    "sg:classifiers":[
        {
            "category":"Government",
            "subcategory":"Customs House",
            "type":"Public Place"
        }
    ],
    "sg:postcode":"S5 8NP",
    "sg:province":"South Yorkshire",
    "sg:tags":[
        "clearance"
    ],
    "wof:name":"Second Chance",
    "wof:placetype":"venue"
},
  "geometry": {"coordinates":[-1.4871339798,53.4209022522],"type":"Point"}
}