{
  "type": "Feature",
  "properties": {
    "addr:full":"3 Happisburgh House, Priory Road Felixstowe Suffolk IP11 7NE",
    "addr:housenumber":"3;house",
    "addr:postcode":"ip11 7ne",
    "addr:street":"Priory Road",
    "iso:country":"GB",
    "sg:address":"3 Happisburgh House, Priory Road",
    "sg:city":"Felixstowe",
    "sg:classifiers":[
        {
            "category":"Professional",
            "subcategory":"Management & Consulting",
            "type":"Services"
        }
    ],
    "sg:phone":"+44 1394 286046",
    "sg:postcode":"IP11 7NE",
    "sg:province":"Suffolk",
    "sg:tags":[
        "consultant",
        "business"
    ],
    "wof:name":"Rideau Ltd.",
    "wof:placetype":"venue"
},
  "geometry": {"coordinates":[1.3424650431,51.9613685608],"type":"Point"}
}