{
  "type": "Feature",
  "properties": {
    "addr:full":"Sea Road, East Preston Littlehampton West Sussex BN16 1JP",
    "addr:postcode":"bn16 1jp",
    "addr:street":"Sea Road",
    "iso:country":"GB",
    "sg:address":"Sea Road, East Preston",
    "sg:city":"Littlehampton",
    "sg:classifiers":[
        {
            "category":"Social Services",
            "subcategory":"Retirement Home",
            "type":"Services"
        }
    ],
    "sg:phone":"+44 1903 784007",
    "sg:postcode":"BN16 1JP",
    "sg:province":"West Sussex",
    "sg:tags":[
        "residential",
        "care"
    ],
    "wof:name":"The Martlets",
    "wof:placetype":"venue"
},
  "geometry": {"coordinates":[-0.4810039997,50.8107910156],"type":"Point"}
}