{
  "type": "Feature",
  "properties": {
    "addr:full":"3 Longport Road Stoke-on-trent Staffordshire ST6 4NJ",
    "addr:housenumber":"3",
    "addr:postcode":"st6 4nj",
    "addr:street":"Longport Road",
    "iso:country":"GB",
    "sg:address":"3 Longport Road",
    "sg:city":"Stoke-on-trent",
    "sg:classifiers":[
        {
            "category":"Personal",
            "subcategory":"Beauty Salon",
            "type":"Services"
        }
    ],
    "sg:postcode":"ST6 4NJ",
    "sg:province":"Staffordshire",
    "sg:tags":[
        "unisex",
        "hairdresser"
    ],
    "wof:name":"Natalie's Hair Salon",
    "wof:placetype":"venue"
},
  "geometry": {"coordinates":[-2.2140259743,53.0425491333],"type":"Point"}
}