{
  "type": "Feature",
  "properties": {
    "iso:country":"GB",
    "sg:address":"1 Redbrick Cottage, Bakers Lane",
    "sg:city":"Colchester",
    "sg:classifiers":[
        {
            "category":"Freight",
            "type":"Transportation"
        }
    ],
    "sg:postcode":"CO3 4AU",
    "sg:province":"Essex",
    "sg:tags":[
        "haulage",
        "road"
    ],
    "wof:name":"S Eadie Transports",
    "wof:placetype":"venue"
},
  "geometry": {"coordinates":[0.86733,51.896118],"type":"Point"}
}