{
  "type": "Feature",
  "properties": {
    "addr:full":"30 Kings Road London Greater London E4 7JE",
    "addr:housenumber":"30",
    "addr:postcode":"e4 7je",
    "addr:street":"Kings Road",
    "iso:country":"GB",
    "sg:address":"30 Kings Road",
    "sg:city":"London",
    "sg:classifiers":[
        {
            "category":"Home & Garden",
            "subcategory":"Carpets & Floor Coverings",
            "type":"Retail Goods"
        }
    ],
    "sg:postcode":"E4 7JE",
    "sg:province":"Greater London",
    "sg:tags":[
        "cleaner",
        "upholstery"
    ],
    "wof:name":"Grosvenor Curtain Cleaning Services",
    "wof:placetype":"venue"
},
  "geometry": {"coordinates":[0.0028609999,51.6285896301],"type":"Point"}
}