{
  "type": "Feature",
  "properties": {
    "iso:country":"GB",
    "sg:address":"1 Battery Green Road",
    "sg:city":"Lowestoft",
    "sg:classifiers":[
        {
            "category":"Recreation",
            "subcategory":"Water Park",
            "type":"Entertainment"
        },
        {
            "category":"Manufacturing",
            "subcategory":"Retail Goods",
            "type":"Manufacturing & Wholesale Goods"
        }
    ],
    "sg:phone":"+44 1502 517992",
    "sg:postcode":"NR32 1DE",
    "sg:province":"Suffolk",
    "sg:tags":[
        "sport",
        "chandler"
    ],
    "wof:name":"Frithvale Ltd.",
    "wof:placetype":"venue"
},
  "geometry": {"coordinates":[1.7536200285,52.4747314453],"type":"Point"}
}