{
  "type": "Feature",
  "properties": {
    "addr:full":"25 Redhill Drive, Ensbury Park Bournemouth Dorset BH10 6AG",
    "addr:housenumber":"25",
    "addr:postcode":"bh10 6ag",
    "addr:street":"Redhill Drive",
    "iso:country":"GB",
    "sg:address":"25 Redhill Drive, Ensbury Park",
    "sg:city":"Bournemouth",
    "sg:classifiers":[
        {
            "category":"Building & Trades",
            "subcategory":"Construction",
            "type":"Services"
        }
    ],
    "sg:phone":"+44 1202 511604",
    "sg:postcode":"BH10 6AG",
    "sg:province":"Dorset",
    "sg:tags":[
        "joiner",
        "carpenter"
    ],
    "wof:name":"Ray G Dibben",
    "wof:placetype":"venue"
},
  "geometry": {"coordinates":[-1.8795080185,50.7607803345],"type":"Point"}
}