{
  "type": "Feature",
  "properties": {
    "iso:country":"GB",
    "sg:address":"Espford Farm, Crosthwaite",
    "sg:city":"Kendal",
    "sg:classifiers":[
        {
            "category":"Farming",
            "subcategory":"Livestock Farm",
            "type":"Manufacturing & Wholesale Goods"
        }
    ],
    "sg:phone":"+44 15395 68849",
    "sg:postcode":"LA8 8BS",
    "sg:province":"Cumbria",
    "sg:tags":[
        "others"
    ],
    "wof:name":"M L & S M Dobson",
    "wof:placetype":"venue"
},
  "geometry": {"coordinates":[-2.85748,54.314781],"type":"Point"}
}