{
  "type": "Feature",
  "properties": {
    "iso:country":"GB",
    "sg:address":"9a Southwick Mews",
    "sg:city":"Bayswater",
    "sg:classifiers":[
        {
            "category":"Building & Trades",
            "subcategory":"Construction",
            "type":"Services"
        }
    ],
    "sg:phone":"+44 20 7706 8107",
    "sg:postcode":"W2 1JG",
    "sg:province":"Greater London",
    "sg:tags":[
        "builder"
    ],
    "wof:name":"West End Refurbs",
    "wof:placetype":"venue"
},
  "geometry": {"coordinates":[-0.171451,51.516312],"type":"Point"}
}