{
  "type": "Feature",
  "properties": {
    "iso:country":"GB",
    "sg:address":"63 Aurelia Rd",
    "sg:city":"Croydon",
    "sg:classifiers":[
        {
            "category":"Building & Trades",
            "subcategory":"Construction",
            "type":"Services"
        }
    ],
    "sg:postcode":"CR0 3BE",
    "sg:province":"Surrey",
    "sg:tags":[
        "tiling",
        "contractor"
    ],
    "wof:name":"Allie,Taariq,",
    "wof:placetype":"venue"
},
  "geometry": {"coordinates":[-0.125802,51.389198],"type":"Point"}
}