{
  "type": "Feature",
  "properties": {
    "addr:full":"Lane Plata Works, Holme Lane Sheffield South Yorkshire S6 4JY",
    "addr:postcode":"s6 4jy",
    "addr:street":"Lane;Holme Lane",
    "iso:country":"GB",
    "sg:address":"Lane Plata Works, Holme Lane",
    "sg:city":"Sheffield",
    "sg:classifiers":[
        {
            "category":"Manufacturing",
            "subcategory":"Metals",
            "type":"Manufacturing & Wholesale Goods"
        }
    ],
    "sg:phone":"+44 114 233 8262",
    "sg:postcode":"S6 4JY",
    "sg:province":"South Yorkshire",
    "sg:tags":[
        "die-casting"
    ],
    "wof:name":"Burgon & Ball Ltd.",
    "wof:placetype":"venue"
},
  "geometry": {"coordinates":[-1.5096900463,53.4000091553],"type":"Point"}
}