{
  "type": "Feature",
  "properties": {
    "addr:full":"11 Theberton St Islington Greater London N1 0QY",
    "addr:housenumber":"11",
    "addr:postcode":"n1 0qy",
    "addr:street":"Theberton St",
    "iso:country":"GB",
    "sg:address":"11 Theberton St",
    "sg:city":"Islington",
    "sg:classifiers":[
        {
            "category":"Restaurant",
            "type":"Food & Drink"
        }
    ],
    "sg:phone":"+44 20 7226 3923",
    "sg:postcode":"N1 0QY",
    "sg:province":"Greater London",
    "sg:tags":[
        "italian"
    ],
    "wof:name":"Maremma",
    "wof:placetype":"venue"
},
  "geometry": {"coordinates":[-0.1034779996,51.5374336243],"type":"Point"}
}