{
  "type": "Feature",
  "properties": {
    "addr:full":"243a Victoria Park Rd London Greater London E9 7HD",
    "addr:housenumber":"243a",
    "addr:postcode":"e9 7hd",
    "addr:street":"Victoria Park Rd",
    "iso:country":"GB",
    "sg:address":"243a Victoria Park Rd",
    "sg:city":"London",
    "sg:classifiers":[
        {
            "category":"Building & Trades",
            "subcategory":"Construction",
            "type":"Services"
        }
    ],
    "sg:postcode":"E9 7HD",
    "sg:province":"Greater London",
    "sg:tags":[
        "builder"
    ],
    "wof:name":"Hackney Forge",
    "wof:placetype":"venue"
},
  "geometry": {"coordinates":[-0.04367,51.53849],"type":"Point"}
}