{
  "type": "Feature",
  "properties": {
    "iso:country":"GB",
    "sg:address":"3 St. Peters Court, Middleborough",
    "sg:city":"Colchester",
    "sg:classifiers":[
        {
            "category":"Education",
            "subcategory":"Special Training",
            "type":"Public Place"
        }
    ],
    "sg:phone":"+44 1206 764076",
    "sg:postcode":"CO1 1WD",
    "sg:province":"Essex",
    "sg:tags":[
        "product",
        "centre"
    ],
    "wof:name":"Spring Skills",
    "wof:placetype":"venue"
},
  "geometry": {"coordinates":[0.8975600004,51.8926506042],"type":"Point"}
}