{
  "type": "Feature",
  "properties": {
    "addr:full":"4 Healy Ct, Healy Pl Plymouth Devon PL2 1AZ",
    "addr:housenumber":"4",
    "addr:postcode":"pl2 1az",
    "addr:street":"Healy Ct Healy Pl",
    "iso:country":"GB",
    "sg:address":"4 Healy Ct, Healy Pl",
    "sg:city":"Plymouth",
    "sg:classifiers":[
        {
            "category":"Building & Trades",
            "subcategory":"Plumbing",
            "type":"Services"
        }
    ],
    "sg:phone":"+44 1752 605884",
    "sg:postcode":"PL2 1AZ",
    "sg:province":"Devon",
    "sg:tags":[
        "heating"
    ],
    "wof:name":"Devon Heating Services",
    "wof:placetype":"venue"
},
  "geometry": {"coordinates":[-4.170049,50.379688],"type":"Point"}
}