{
  "type": "Feature",
  "properties": {
    "addr:full":"1a Arbutus St Hackney Greater London E8 4DT",
    "addr:housenumber":"1a",
    "addr:postcode":"e8 4dt",
    "addr:street":"Arbutus St",
    "iso:country":"GB",
    "sg:address":"1a Arbutus St",
    "sg:city":"Hackney",
    "sg:classifiers":[
        {
            "category":"Building & Trades",
            "subcategory":"Construction",
            "type":"Services"
        }
    ],
    "sg:phone":"+44 20 7254 5666",
    "sg:postcode":"E8 4DT",
    "sg:province":"Greater London",
    "sg:tags":[
        "welder",
        "mechanical"
    ],
    "wof:name":"Sen Metal",
    "wof:placetype":"venue"
},
  "geometry": {"coordinates":[-0.076224,51.538864],"type":"Point"}
}