{
  "type": "Feature",
  "properties": {
    "iso:country":"GB",
    "sg:address":"23a York Road",
    "sg:city":"Ilford",
    "sg:classifiers":[
        {
            "category":"Professional",
            "subcategory":"Employment Agencies",
            "type":"Services"
        }
    ],
    "sg:phone":"+44 20 8514 1234",
    "sg:postcode":"IG1 3AD",
    "sg:province":"Essex",
    "sg:tags":[
        "consultant"
    ],
    "wof:name":"First Resort Employment Ltd.",
    "wof:placetype":"venue"
},
  "geometry": {"coordinates":[0.0683770031,51.5594482422],"type":"Point"}
}