{
  "type": "Feature",
  "properties": {
    "addr:full":"Richmond House, 15 Bloom Street Manchester Greater Manchester M1 3HZ",
    "addr:housenumber":"15",
    "addr:postcode":"m1 3hz",
    "addr:street":"Bloom Street",
    "iso:country":"GB",
    "sg:address":"Richmond House, 15 Bloom Street",
    "sg:city":"Manchester",
    "sg:classifiers":[
        {
            "category":"Health Services",
            "subcategory":"Clinic",
            "type":"Services"
        }
    ],
    "sg:phone":"+44 161 237 9020",
    "sg:postcode":"M1 3HZ",
    "sg:province":"Greater Manchester",
    "sg:tags":[
        "private"
    ],
    "wof:name":"The Papillon Centre Ltd.",
    "wof:placetype":"venue"
},
  "geometry": {"coordinates":[-2.236712,53.477806],"type":"Point"}
}