{
  "type": "Feature",
  "properties": {
    "iso:country":"GB",
    "sg:address":"Priory Cottage, Poling Street",
    "sg:city":"Arundel",
    "sg:classifiers":[
        {
            "category":"Home & Garden",
            "subcategory":"Home Furnishings",
            "type":"Retail Goods"
        }
    ],
    "sg:postcode":"BN18 9PS",
    "sg:province":"West Sussex",
    "sg:tags":[
        "furnishers",
        "planner",
        "kitchen"
    ],
    "wof:name":"Exquisite Kitchens",
    "wof:placetype":"venue"
},
  "geometry": {"coordinates":[-0.554589,50.854836],"type":"Point"}
}