{
  "type": "Feature",
  "properties": {
    "iso:country":"GB",
    "sg:address":"Essex House, Jutsums Lane",
    "sg:city":"Romford",
    "sg:classifiers":[
        {
            "category":"Manufacturing",
            "subcategory":"Wood Products",
            "type":"Manufacturing & Wholesale Goods"
        }
    ],
    "sg:phone":"+44 1708 725911",
    "sg:postcode":"RM7 0ER",
    "sg:province":"Essex",
    "sg:tags":[
        "packaging",
        "crate",
        "pallets"
    ],
    "wof:name":"Grangewood Plastic Packaging Ltd.",
    "wof:placetype":"venue"
},
  "geometry": {"coordinates":[0.1610870063,51.5699577332],"type":"Point"}
}