{
  "type": "Feature",
  "properties": {
    "iso:country":"GB",
    "sg:address":"12 The Grand Union Centre, West Row",
    "sg:city":"London",
    "sg:classifiers":[
        {
            "category":"Wholesale",
            "subcategory":"Music Publishers",
            "type":"Manufacturing & Wholesale Goods"
        }
    ],
    "sg:phone":"+44 20 8968 0988",
    "sg:postcode":"W10 5AS",
    "sg:province":"Greater London",
    "wof:name":"Year Zero Music Ltd.",
    "wof:placetype":"venue"
},
  "geometry": {"coordinates":[-0.2140000015,51.5255203247],"type":"Point"}
}