{
  "type": "Feature",
  "properties": {
    "addr:full":"373 High Road London Greater London N17 9HQ",
    "addr:housenumber":"373",
    "addr:postcode":"n17 9hq",
    "addr:street":"High Road",
    "iso:country":"GB",
    "sg:address":"373 High Road",
    "sg:city":"London",
    "sg:classifiers":[
        {
            "category":"Fast Food",
            "type":"Food & Drink"
        }
    ],
    "sg:postcode":"N17 9HQ",
    "sg:province":"Greater London",
    "sg:tags":[
        "away",
        "take"
    ],
    "wof:name":"Izmir Kebab House",
    "wof:placetype":"venue"
},
  "geometry": {"coordinates":[-0.070329,51.589352],"type":"Point"}
}