{
  "type": "Feature",
  "properties": {
    "iso:country":"GB",
    "sg:address":"Fenton Barns Retail Village, Fenton Barns",
    "sg:city":"North Berwick",
    "sg:classifiers":[
        {
            "category":"Recreation",
            "type":"Entertainment"
        }
    ],
    "sg:postcode":"EH39 5BW",
    "sg:province":"East Lothian",
    "sg:tags":[
        "corporate",
        "leisure"
    ],
    "wof:name":"Montgomery Golf Ltd.",
    "wof:placetype":"venue"
},
  "geometry": {"coordinates":[-2.782706,56.028156],"type":"Point"}
}