{
  "type": "Feature",
  "properties": {
    "addr:full":"328 Shields Road Newcastle-upon-tyne Tyne and Wear NE6 2UU",
    "addr:housenumber":"328",
    "addr:postcode":"ne6 2uu",
    "addr:street":"Shields Road",
    "iso:country":"GB",
    "sg:address":"328 Shields Road",
    "sg:city":"Newcastle-upon-tyne",
    "sg:classifiers":[
        {
            "category":"Autos & Motor Vehicles",
            "subcategory":"Auto Supplies",
            "type":"Retail Goods"
        }
    ],
    "sg:phone":"+44 191 224 0300",
    "sg:postcode":"NE6 2UU",
    "sg:province":"Tyne and Wear",
    "sg:tags":[
        "exhaust",
        "absorber",
        "shock"
    ],
    "wof:name":"Kwik-Fit",
    "wof:placetype":"venue"
},
  "geometry": {"coordinates":[-1.5746790171,54.9805412292],"type":"Point"}
}