{
  "type": "Feature",
  "properties": {
    "addr:full":", Church Knowle Wareham Dorset BH20 5NQ",
    "addr:postcode":"bh20 5nq",
    "addr:street":"Knowle",
    "iso:country":"GB",
    "sg:address":", Church Knowle",
    "sg:city":"Wareham",
    "sg:classifiers":[
        {
            "category":"Bars & Pubs",
            "type":"Food & Drink"
        }
    ],
    "sg:phone":"+44 1929 480357",
    "sg:postcode":"BH20 5NQ",
    "sg:province":"Dorset",
    "sg:tags":[
        "pubs",
        "inn"
    ],
    "wof:name":"The New Inn",
    "wof:placetype":"venue"
},
  "geometry": {"coordinates":[-2.1201078892,50.6409492493],"type":"Point"}
}