{
  "type": "Feature",
  "properties": {
    "iso:country":"GB",
    "sg:address":"Regency Court, Beeston",
    "sg:city":"Nottingham",
    "sg:classifiers":[
        {
            "category":"Social Services",
            "subcategory":"Adult Care",
            "type":"Services"
        }
    ],
    "sg:phone":"+44 115 922 5359",
    "sg:postcode":"NG9 2DS",
    "sg:province":"Nottinghamshire",
    "sg:tags":[
        "housing",
        "sheltered"
    ],
    "wof:name":"Regency Court Sheltered Housing",
    "wof:placetype":"venue"
},
  "geometry": {"coordinates":[-1.2109470367,52.9283714294],"type":"Point"}
}