{
  "type": "Feature",
  "properties": {
    "addr:full":"The Business Centre, Corporation Rd, Loughor Swansea Carmarthenshire SA4 2UQ",
    "addr:postcode":"sa4 2uq",
    "addr:street":"Corporation Rd",
    "iso:country":"GB",
    "sg:address":"The Business Centre, Corporation Rd, Loughor",
    "sg:city":"Swansea",
    "sg:classifiers":[
        {
            "category":"Professional",
            "subcategory":"Accounting & Tax Preparation",
            "type":"Services"
        }
    ],
    "sg:postcode":"SA4 2UQ",
    "sg:province":"Carmarthenshire",
    "sg:tags":[
        "accountant"
    ],
    "wof:name":"Coastline Accountancy Services",
    "wof:placetype":"venue"
},
  "geometry": {"coordinates":[-4.068570137,51.664188385],"type":"Point"}
}