{
  "type": "Feature",
  "properties": {
    "addr:full":"31 Great Smith Street London Greater London SW1P 3BN",
    "addr:housenumber":"31",
    "addr:postcode":"sw1p 3bn",
    "addr:street":"Great Smith Street",
    "iso:country":"GB",
    "sg:address":"31 Great Smith Street",
    "sg:city":"London",
    "sg:classifiers":[
        {
            "category":"Shopping",
            "subcategory":"Books",
            "type":"Retail Goods"
        }
    ],
    "sg:phone":"+44 20 7898 1301",
    "sg:postcode":"SW1P 3BN",
    "sg:province":"Greater London",
    "sg:tags":[
        "bookseller"
    ],
    "wof:name":"Church House Bookshop",
    "wof:placetype":"venue"
},
  "geometry": {"coordinates":[-0.129324,51.497669],"type":"Point"}
}