{
  "type": "Feature",
  "properties": {
    "iso:country":"GB",
    "sg:address":"3 New Cottage, Redbridge Lane, Nursling",
    "sg:city":"Southampton",
    "sg:classifiers":[
        {
            "category":"Home & Garden",
            "subcategory":"Carpets & Floor Coverings",
            "type":"Retail Goods"
        }
    ],
    "sg:phone":"+44 23 8089 9771",
    "sg:postcode":"SO16 0YH",
    "sg:province":"Hampshire",
    "sg:tags":[
        "cleaner",
        "upholstery"
    ],
    "wof:name":"Allied Sunshine",
    "wof:placetype":"venue"
},
  "geometry": {"coordinates":[-1.472689,50.944946],"type":"Point"}
}