{
  "type": "Feature",
  "properties": {
    "addr:full":"48 Sandringham Road Watford Hertfordshire WD24 7BB",
    "addr:housenumber":"48",
    "addr:postcode":"wd24 7bb",
    "addr:street":"Sandringham Road",
    "iso:country":"GB",
    "sg:address":"48 Sandringham Road",
    "sg:city":"Watford",
    "sg:classifiers":[
        {
            "category":"Building & Trades",
            "subcategory":"Construction",
            "type":"Services"
        }
    ],
    "sg:postcode":"WD24 7BB",
    "sg:province":"Hertfordshire",
    "sg:tags":[
        "decorator",
        "painter"
    ],
    "wof:name":"J A King",
    "wof:placetype":"venue"
},
  "geometry": {"coordinates":[-0.3952090144,51.6740379333],"type":"Point"}
}