{
  "type": "Feature",
  "properties": {
    "iso:country":"GB",
    "sg:address":"664 Bloxwich Road, Leamore",
    "sg:city":"Walsall",
    "sg:classifiers":[
        {
            "category":"Parking",
            "type":"Transportation"
        }
    ],
    "sg:phone":"+44 1922 494023",
    "sg:postcode":"WS3 2BB",
    "sg:province":"Staffordshire",
    "sg:tags":[
        "car",
        "valet"
    ],
    "wof:name":"Imo Car Wash",
    "wof:placetype":"venue"
},
  "geometry": {"coordinates":[-1.9964489937,52.6096076965],"type":"Point"}
}