{
  "type": "Feature",
  "properties": {
    "addr:full":"Georgian House Hotel, Manchester Road, Blackrod Bolton Lancashire BL6 5RU",
    "addr:postcode":"bl6 5ru",
    "addr:street":"Manchester Road",
    "iso:country":"GB",
    "sg:address":"Georgian House Hotel, Manchester Road, Blackrod",
    "sg:city":"Bolton",
    "sg:classifiers":[
        {
            "category":"Personal",
            "subcategory":"Beauty Salon",
            "type":"Services"
        }
    ],
    "sg:phone":"+44 1942 842303",
    "sg:postcode":"BL6 5RU",
    "sg:province":"Lancashire",
    "sg:tags":[
        "unisex",
        "hairdresser"
    ],
    "wof:name":"Lawsan Hair & Beauty Group",
    "wof:placetype":"venue"
},
  "geometry": {"coordinates":[-2.580204,53.592331],"type":"Point"}
}