{
  "type": "Feature",
  "properties": {
    "addr:full":"Moorview Business Park, 628/630 Leeds Road, Idle Bradford West Yorkshire BD10 8JH",
    "addr:housenumber":"628 / 630",
    "addr:postcode":"bd10 8jh",
    "addr:street":"Leeds Road",
    "iso:country":"GB",
    "sg:address":"Moorview Business Park, 628/630 Leeds Road, Idle",
    "sg:city":"Bradford",
    "sg:classifiers":[
        {
            "category":"Professional",
            "subcategory":"Computer Services",
            "type":"Services"
        }
    ],
    "sg:phone":"+44 1274 619975",
    "sg:postcode":"BD10 8JH",
    "sg:province":"West Yorkshire",
    "sg:tags":[
        "system",
        "software"
    ],
    "wof:name":"Concourse Computer Services Ltd.",
    "wof:placetype":"venue"
},
  "geometry": {"coordinates":[-1.7583060265,53.7957382202],"type":"Point"}
}