{
  "type": "Feature",
  "properties": {
    "addr:full":"Tenax Circle, Trafford Park Manchester Cheshire M17 1EZ",
    "addr:postcode":"m17 1ez",
    "addr:street":"Tenax Circle",
    "iso:country":"GB",
    "sg:address":"Tenax Circle, Trafford Park",
    "sg:city":"Manchester",
    "sg:classifiers":[
        {
            "category":"Shopping",
            "type":"Retail Goods"
        }
    ],
    "sg:phone":"+44 161 869 5800",
    "sg:postcode":"M17 1EZ",
    "sg:province":"Cheshire",
    "sg:tags":[
        "equipment",
        "clothing",
        "safety"
    ],
    "wof:name":"Arco Manchester",
    "wof:placetype":"venue"
},
  "geometry": {"coordinates":[-2.3226,53.475288],"type":"Point"}
}