{
  "type": "Feature",
  "properties": {
    "iso:country":"GB",
    "sg:address":"Riverview Farm, Perranwell Station",
    "sg:city":"Truro",
    "sg:classifiers":[
        {
            "category":"Manufacturing",
            "subcategory":"Textiles",
            "type":"Manufacturing & Wholesale Goods"
        }
    ],
    "sg:postcode":"TR3 7ND",
    "sg:province":"Cornwall",
    "sg:tags":[
        "printer"
    ],
    "wof:name":"Anita Foote Designs",
    "wof:placetype":"venue"
},
  "geometry": {"coordinates":[-5.114149,50.21579],"type":"Point"}
}