{
  "type": "Feature",
  "properties": {
    "addr:full":"100 High Road, Byfleet West Byfleet Surrey KT14 7QT",
    "addr:housenumber":"100",
    "addr:postcode":"kt14 7qt",
    "addr:street":"High Road;West Byfleet",
    "iso:country":"GB",
    "sg:address":"100 High Road, Byfleet",
    "sg:city":"West Byfleet",
    "sg:classifiers":[
        {
            "category":"Professional",
            "subcategory":"Accounting & Tax Preparation",
            "type":"Services"
        }
    ],
    "sg:phone":"+44 1932 353165",
    "sg:postcode":"KT14 7QT",
    "sg:province":"Surrey",
    "sg:tags":[
        "accountant",
        "activity"
    ],
    "wof:name":"Michael Welfare & Co Ltd",
    "wof:placetype":"venue"
},
  "geometry": {"coordinates":[-0.474472,51.338711],"type":"Point"}
}