{
  "type": "Feature",
  "properties": {
    "iso:country":"GB",
    "sg:address":"157 Cleethorpe Road",
    "sg:city":"Grimsby",
    "sg:classifiers":[
        {
            "category":"Manufacturing",
            "subcategory":"Wood Products",
            "type":"Manufacturing & Wholesale Goods"
        },
        {
            "category":"Building & Trades",
            "subcategory":"Construction",
            "type":"Services"
        }
    ],
    "sg:postcode":"DN31 3AX",
    "sg:province":"Lincolnshire",
    "sg:tags":[
        "joiner",
        "carpenter",
        "sawmill",
        "shaving"
    ],
    "wof:name":"The Door Store",
    "wof:placetype":"venue"
},
  "geometry": {"coordinates":[-0.069716,53.574821],"type":"Point"}
}