{
  "type": "Feature",
  "properties": {
    "addr:full":"1a Brompton Road, Sprotborough Doncaster South Yorkshire DN5 7LB",
    "addr:housenumber":"1a",
    "addr:postcode":"dn5 7lb",
    "addr:street":"Brompton Road",
    "iso:country":"GB",
    "sg:address":"1a Brompton Road, Sprotborough",
    "sg:city":"Doncaster",
    "sg:classifiers":[
        {
            "category":"Building & Trades",
            "subcategory":"Construction",
            "type":"Services"
        }
    ],
    "sg:phone":"+44 1302 854490",
    "sg:postcode":"DN5 7LB",
    "sg:province":"South Yorkshire",
    "sg:tags":[
        "joiner",
        "carpenter"
    ],
    "wof:name":"Marsh Construction Ltd.",
    "wof:placetype":"venue"
},
  "geometry": {"coordinates":[-1.182289,53.514935],"type":"Point"}
}