{
  "type": "Feature",
  "properties": {
    "addr:full":"59 Westoe Road South Shields Tyne and Wear NE33 4LU",
    "addr:housenumber":"59",
    "addr:postcode":"ne33 4lu",
    "addr:street":"Westoe Road",
    "iso:country":"GB",
    "sg:address":"59 Westoe Road",
    "sg:city":"South Shields",
    "sg:classifiers":[
        {
            "category":"Government",
            "subcategory":"Post Office",
            "type":"Public Place"
        }
    ],
    "sg:phone":"+44 191 455 5487",
    "sg:postcode":"NE33 4LU",
    "sg:province":"Tyne and Wear",
    "wof:name":"Westoe Road Post Office",
    "wof:placetype":"venue"
},
  "geometry": {"coordinates":[-1.428236,54.992672],"type":"Point"}
}