{
  "type": "Feature",
  "properties": {
    "addr:full":"Unit 30 Penraevon Indust Est, Meanwood Rd Leeds West Yorkshire LS7 2AW",
    "addr:housenumber":"unit 30",
    "addr:postcode":"ls7 2aw",
    "addr:street":"Indust;Meanwood Rd",
    "iso:country":"GB",
    "sg:address":"Unit 30 Penraevon Indust Est, Meanwood Rd",
    "sg:city":"Leeds",
    "sg:classifiers":[
        {
            "category":"Professional",
            "subcategory":"Engineering",
            "type":"Services"
        }
    ],
    "sg:phone":"+44 113 239 2652",
    "sg:postcode":"LS7 2AW",
    "sg:province":"West Yorkshire",
    "sg:tags":[
        "gas",
        "engineer"
    ],
    "wof:name":"S C S Plumbing & Heating Engineers",
    "wof:placetype":"venue"
},
  "geometry": {"coordinates":[-1.5428800583,53.8126792908],"type":"Point"}
}