{
  "type": "Feature",
  "properties": {
    "addr:full":"Tilbury Energy & Environment Cr, Fort Road, Tilbury Grays Essex RM18 8UJ",
    "addr:postcode":"rm18 8uj",
    "addr:street":"Cr Fort Road;Grays",
    "iso:country":"GB",
    "sg:address":"Tilbury Energy & Environment Cr, Fort Road, Tilbury",
    "sg:city":"Grays",
    "sg:classifiers":[
        {
            "category":"Landmark",
            "subcategory":"Tourist Attraction",
            "type":"Public Place"
        }
    ],
    "sg:phone":"+44 1375 857271",
    "sg:postcode":"RM18 8UJ",
    "sg:province":"Essex",
    "sg:tags":[
        "interest"
    ],
    "wof:name":"Energy Tours",
    "wof:placetype":"venue"
},
  "geometry": {"coordinates":[0.3902699947,51.4552497864],"type":"Point"}
}