{
  "type": "Feature",
  "properties": {
    "iso:country":"GB",
    "sg:address":"Wardington House, Wardington",
    "sg:city":"Banbury",
    "sg:classifiers":[
        {
            "category":"Health Services",
            "subcategory":"Nursing And Care Facility",
            "type":"Services"
        }
    ],
    "sg:phone":"+44 1295 750622",
    "sg:postcode":"OX17 1SD",
    "sg:province":"Northamptonshire",
    "sg:tags":[
        "home"
    ],
    "wof:name":"Redwave Management Ltd.",
    "wof:placetype":"venue"
},
  "geometry": {"coordinates":[-1.2844059467,52.1158256531],"type":"Point"}
}