{
  "type": "Feature",
  "properties": {
    "addr:full":"The King William Inn, Barn Street Crewkerne Dorset TA18 8BP",
    "addr:postcode":"ta18 8bp",
    "addr:street":"Street",
    "iso:country":"GB",
    "sg:address":"The King William Inn, Barn Street",
    "sg:city":"Crewkerne",
    "sg:classifiers":[
        {
            "category":"Bars & Pubs",
            "type":"Food & Drink"
        },
        {
            "category":"Community Center",
            "subcategory":"Social",
            "type":"Public Place"
        }
    ],
    "sg:phone":"+44 1460 74492",
    "sg:postcode":"TA18 8BP",
    "sg:province":"Dorset",
    "sg:tags":[
        "pubs",
        "house",
        "inn",
        "activity"
    ],
    "wof:name":"King William Inn",
    "wof:placetype":"venue"
},
  "geometry": {"coordinates":[-2.799715,50.882469],"type":"Point"}
}