{
  "type": "Feature",
  "properties": {
    "addr:full":"18 St Johns Road Slough Berkshire SL2 5EY",
    "addr:housenumber":"18",
    "addr:postcode":"sl2 5ey",
    "addr:street":"St Johns Road",
    "iso:country":"GB",
    "sg:address":"18 St Johns Road",
    "sg:city":"Slough",
    "sg:classifiers":[
        {
            "category":"Manufacturing",
            "subcategory":"Metals",
            "type":"Manufacturing & Wholesale Goods"
        }
    ],
    "sg:phone":"+44 1753 517322",
    "sg:postcode":"SL2 5EY",
    "sg:province":"Berkshire",
    "sg:tags":[
        "steel",
        "stockholder"
    ],
    "wof:name":"Forsteel Ltd.",
    "wof:placetype":"venue"
},
  "geometry": {"coordinates":[-0.585454,51.515415],"type":"Point"}
}