{
  "type": "Feature",
  "properties": {
    "iso:country":"GB",
    "sg:address":"241 Broomfield Road",
    "sg:city":"Chelmsford",
    "sg:classifiers":[
        {
            "category":"Fast Food",
            "type":"Food & Drink"
        }
    ],
    "sg:phone":"+44 1245 347529",
    "sg:postcode":"CM1 4DP",
    "sg:province":"Essex",
    "sg:tags":[
        "away",
        "meal",
        "outlet",
        "take"
    ],
    "wof:name":"China City",
    "wof:placetype":"venue"
},
  "geometry": {"coordinates":[0.468473,51.750893],"type":"Point"}
}