{
  "type": "Feature",
  "properties": {
    "iso:country":"GB",
    "sg:address":"51a George Street",
    "sg:city":"Richmond",
    "sg:classifiers":[
        {
            "category":"Professional",
            "subcategory":"Employment Agencies",
            "type":"Services"
        }
    ],
    "sg:phone":"+44 20 8948 1481",
    "sg:postcode":"TW9 1HJ",
    "sg:province":"Greater London",
    "sg:tags":[
        "consultant"
    ],
    "wof:name":"Brook Street Bureau Plc",
    "wof:placetype":"venue"
},
  "geometry": {"coordinates":[-0.304248,51.461002],"type":"Point"}
}