{
  "type": "Feature",
  "properties": {
    "iso:country":"GB",
    "sg:address":"Park House, 26 North End Road",
    "sg:city":"London",
    "sg:classifiers":[
        {
            "category":"Professional",
            "subcategory":"Management & Consulting",
            "type":"Services"
        }
    ],
    "sg:postcode":"NW11 7PT",
    "sg:province":"Greater London",
    "sg:tags":[
        "sport"
    ],
    "wof:name":"International Sports Travel Ltd",
    "wof:placetype":"venue"
},
  "geometry": {"coordinates":[-0.1917,51.571274],"type":"Point"}
}