{
  "type": "Feature",
  "properties": {
    "iso:country":"GB",
    "sg:address":"14 New Street",
    "sg:city":"Dudley",
    "sg:classifiers":[
        {
            "category":"Professional",
            "subcategory":"Lawyer & Legal Services",
            "type":"Services"
        }
    ],
    "sg:phone":"+44 1384 347800",
    "sg:postcode":"DY1 1LP",
    "sg:province":"West Midlands",
    "sg:tags":[
        "solicitor"
    ],
    "wof:name":"Rees Page",
    "wof:placetype":"venue"
},
  "geometry": {"coordinates":[-2.082188,52.511387],"type":"Point"}
}