{
  "type": "Feature",
  "properties": {
    "iso:country":"GB",
    "sg:address":"60 New King Street",
    "sg:city":"London",
    "sg:classifiers":[
        {
            "category":"Bars & Pubs",
            "type":"Food & Drink"
        }
    ],
    "sg:phone":"+44 20 8694 1224",
    "sg:postcode":"SE8 3JE",
    "sg:province":"Greater London",
    "sg:tags":[
        "pubs",
        "inn"
    ],
    "wof:name":"The Navy Arms",
    "wof:placetype":"venue"
},
  "geometry": {"coordinates":[-0.02678,51.483028],"type":"Point"}
}