{
  "type": "Feature",
  "properties": {
    "iso:country":"GB",
    "sg:address":"68-70 Brighton Rd",
    "sg:city":"Coulsdon",
    "sg:classifiers":[
        {
            "category":"Social Services",
            "subcategory":"Retirement Home",
            "type":"Services"
        }
    ],
    "sg:phone":"+44 20 8660 1990",
    "sg:postcode":"CR5 2BB",
    "sg:province":"Surrey",
    "sg:tags":[
        "residential",
        "care"
    ],
    "wof:name":"Willow Lodge",
    "wof:placetype":"venue"
},
  "geometry": {"coordinates":[-0.139179,51.318939],"type":"Point"}
}