{
  "type": "Feature",
  "properties": {
    "addr:full":"14a Park Street, Stratton St Margaret Swindon Wiltshire SN3 4LL",
    "addr:housenumber":"14a",
    "addr:postcode":"sn3 4ll",
    "addr:street":"Park Street",
    "iso:country":"GB",
    "sg:address":"14a Park Street, Stratton St Margaret",
    "sg:city":"Swindon",
    "sg:classifiers":[
        {
            "category":"Real Estate",
            "subcategory":"Architect",
            "type":"Services"
        }
    ],
    "sg:postcode":"SN3 4LL",
    "sg:province":"Wiltshire",
    "wof:name":"Camtrac (Engineering Designs) Ltd",
    "wof:placetype":"venue"
},
  "geometry": {"coordinates":[-1.7382349968,51.5787200928],"type":"Point"}
}