{
  "type": "Feature",
  "properties": {
    "addr:full":"Station Hill Farnham Surrey GU9 8AA",
    "addr:postcode":"gu9 8aa",
    "addr:street":"Station Hill Farnham",
    "iso:country":"GB",
    "sg:address":"Station Hill",
    "sg:city":"Farnham",
    "sg:classifiers":[
        {
            "category":"Autos & Motor Vehicles",
            "subcategory":"Automobile Sales",
            "type":"Retail Goods"
        }
    ],
    "sg:phone":"+44 1252 735274",
    "sg:postcode":"GU9 8AA",
    "sg:province":"Surrey",
    "sg:tags":[
        "car"
    ],
    "wof:name":"S H G Vehicle Consultants",
    "wof:placetype":"venue"
},
  "geometry": {"coordinates":[-0.792569,51.212231],"type":"Point"}
}