{
  "type": "Feature",
  "properties": {
    "addr:full":"97 Dukes Brow Blackburn Lancashire BB2 6DH",
    "addr:housenumber":"97",
    "addr:postcode":"bb2 6dh",
    "addr:street":"Dukes Brow",
    "iso:country":"GB",
    "sg:address":"97 Dukes Brow",
    "sg:city":"Blackburn",
    "sg:classifiers":[
        {
            "category":"Personal",
            "subcategory":"Beauty Salon",
            "type":"Services"
        }
    ],
    "sg:postcode":"BB2 6DH",
    "sg:province":"Lancashire",
    "sg:tags":[
        "unisex",
        "hairdresser"
    ],
    "wof:name":"Toni Begolo",
    "wof:placetype":"venue"
},
  "geometry": {"coordinates":[-2.502062,53.75412],"type":"Point"}
}