{
  "type": "Feature",
  "properties": {
    "addr:full":"31 Glebe Road, Cuckfield Haywards Heath East Sussex RH17 5BG",
    "addr:housenumber":"31",
    "addr:postcode":"rh17 5bg",
    "addr:street":"Glebe Road",
    "iso:country":"GB",
    "sg:address":"31 Glebe Road, Cuckfield",
    "sg:city":"Haywards Heath",
    "sg:classifiers":[
        {
            "category":"Building & Trades",
            "subcategory":"Landscaping Services",
            "type":"Services"
        }
    ],
    "sg:phone":"+44 1444 416783",
    "sg:postcode":"RH17 5BG",
    "sg:province":"East Sussex",
    "sg:tags":[
        "forestry",
        "surgeon",
        "tree"
    ],
    "wof:name":"Peter Tree Surgery Godbold",
    "wof:placetype":"venue"
},
  "geometry": {"coordinates":[-0.137823,51.009907],"type":"Point"}
}