{
  "type": "Feature",
  "properties": {
    "addr:full":"Castlecliff Workshops, 25 Johnston Terrace Edinburgh City of Edinburgh EH1 2NH",
    "addr:housenumber":"25",
    "addr:postcode":"eh1 2nh",
    "addr:street":"Johnston Terrace",
    "iso:country":"GB",
    "sg:address":"Castlecliff Workshops, 25 Johnston Terrace",
    "sg:city":"Edinburgh",
    "sg:classifiers":[
        {
            "category":"Communications",
            "subcategory":"Film & Video Production",
            "type":"Services"
        }
    ],
    "sg:phone":"+44 131 622 7370",
    "sg:postcode":"EH1 2NH",
    "sg:province":"City of Edinburgh",
    "sg:tags":[
        "tv",
        "studio"
    ],
    "wof:name":"Sharing Stories",
    "wof:placetype":"venue"
},
  "geometry": {"coordinates":[-3.2014501095,55.9474716187],"type":"Point"}
}