{
  "type": "Feature",
  "properties": {
    "addr:full":"57 South Milton Street, Cattedown Plymouth Devon PL4 0QE",
    "addr:housenumber":"57",
    "addr:postcode":"pl4 0qe",
    "addr:street":"South Milton Street",
    "iso:country":"GB",
    "sg:address":"57 South Milton Street, Cattedown",
    "sg:city":"Plymouth",
    "sg:classifiers":[
        {
            "category":"Building & Trades",
            "subcategory":"Construction",
            "type":"Services"
        }
    ],
    "sg:postcode":"PL4 0QE",
    "sg:province":"Devon",
    "sg:tags":[
        "platform",
        "work",
        "scaffolding"
    ],
    "wof:name":"J E M Scaffolding",
    "wof:placetype":"venue"
},
  "geometry": {"coordinates":[-4.118754,50.367306],"type":"Point"}
}