{
  "type": "Feature",
  "properties": {
    "addr:full":"4 Market Arcade Glossop Derbyshire SK13 8AP",
    "addr:housenumber":"4",
    "addr:postcode":"sk13 8ap",
    "addr:street":"Market Arcade",
    "iso:country":"GB",
    "sg:address":"4 Market Arcade",
    "sg:city":"Glossop",
    "sg:classifiers":[
        {
            "category":"Shopping",
            "subcategory":"Tobacco",
            "type":"Retail Goods"
        }
    ],
    "sg:phone":"+44 1457 861273",
    "sg:postcode":"SK13 8AP",
    "sg:province":"Derbyshire",
    "sg:tags":[
        "tobacconist"
    ],
    "wof:name":"Chris's",
    "wof:placetype":"venue"
},
  "geometry": {"coordinates":[-1.9508529902,53.4430580139],"type":"Point"}
}