{
  "type": "Feature",
  "properties": {
    "addr:full":"346 Meadow Lane Nottingham Nottinghamshire NG2 3GL",
    "addr:housenumber":"346",
    "addr:postcode":"ng2 3gl",
    "addr:street":"Meadow Lane",
    "iso:country":"GB",
    "sg:address":"346 Meadow Lane",
    "sg:city":"Nottingham",
    "sg:classifiers":[
        {
            "category":"Retail",
            "subcategory":"Repair Shop",
            "type":"Services"
        },
        {
            "category":"Manufacturing",
            "subcategory":"Furniture",
            "type":"Manufacturing & Wholesale Goods"
        }
    ],
    "sg:phone":"+44 115 986 4613",
    "sg:postcode":"NG2 3GL",
    "sg:province":"Nottinghamshire",
    "sg:tags":[
        "mnfr",
        "upholstering",
        "upholsterer"
    ],
    "wof:name":"M & K Flear Upholsters",
    "wof:placetype":"venue"
},
  "geometry": {"coordinates":[-1.1315829754,52.9451141357],"type":"Point"}
}