{
  "type": "Feature",
  "properties": {
    "addr:full":"16 Market Hall, New Market Huddersfield West Yorkshire HD1 2NN",
    "addr:housenumber":"16",
    "addr:postcode":"hd1 2nn",
    "addr:street":"Market Hall;Market",
    "iso:country":"GB",
    "sg:address":"16 Market Hall, New Market",
    "sg:city":"Huddersfield",
    "sg:classifiers":[
        {
            "category":"Food & Beverages",
            "subcategory":"Bakery",
            "type":"Retail Goods"
        }
    ],
    "sg:phone":"+44 1484 533955",
    "sg:postcode":"HD1 2NN",
    "sg:province":"West Yorkshire",
    "sg:tags":[
        "baker"
    ],
    "wof:name":"Watson's Bakeries",
    "wof:placetype":"venue"
},
  "geometry": {"coordinates":[-1.782684,53.646954],"type":"Point"}
}