{
  "type": "Feature",
  "properties": {
    "addr:full":"Unit 41 Hardwick Industrial Estate, Hardwick Lane Bury St Edmunds Suffolk IP33 2QH",
    "addr:housenumber":"unit 41;estate",
    "addr:postcode":"ip33 2qh",
    "addr:street":"Hardwick Industrial;Hardwick Lane",
    "iso:country":"GB",
    "sg:address":"Unit 41 Hardwick Industrial Estate, Hardwick Lane",
    "sg:city":"Bury St Edmunds",
    "sg:classifiers":[
        {
            "category":"Autos & Motor Vehicles",
            "subcategory":"Motorcycle Sales",
            "type":"Retail Goods"
        }
    ],
    "sg:phone":"+44 1284 756060",
    "sg:postcode":"IP33 2QH",
    "sg:province":"Suffolk",
    "sg:tags":[
        "component"
    ],
    "wof:name":"Saxon Performance Dyno Centre",
    "wof:placetype":"venue"
},
  "geometry": {"coordinates":[0.70932,52.249905],"type":"Point"}
}