{
  "type": "Feature",
  "properties": {
    "addr:full":"Unit G2 New Yatt Business Centre Witney Oxfordshire OX29 6TJ",
    "addr:housenumber":"g2;business",
    "addr:postcode":"ox29 6tj",
    "addr:street":"New Yatt",
    "iso:country":"GB",
    "sg:address":"Unit G2 New Yatt Business Centre",
    "sg:city":"Witney",
    "sg:classifiers":[
        {
            "category":"Retail",
            "subcategory":"Auto Repair",
            "type":"Services"
        }
    ],
    "sg:postcode":"OX29 6TJ",
    "sg:province":"Oxfordshire",
    "sg:tags":[
        "modification",
        "garage"
    ],
    "wof:name":"Hollis,Mark,",
    "wof:placetype":"venue"
},
  "geometry": {"coordinates":[-1.4626200199,51.8160438538],"type":"Point"}
}