{
  "type": "Feature",
  "properties": {
    "addr:full":"13 Ladeside Business Centre Perth Perth and Kinross PH1 5YA",
    "addr:housenumber":"13",
    "addr:postcode":"ph1 5ya",
    "addr:street":"Ladeside Business Centre",
    "iso:country":"GB",
    "sg:address":"13 Ladeside Business Centre",
    "sg:city":"Perth",
    "sg:classifiers":[
        {
            "category":"Building & Trades",
            "subcategory":"Construction",
            "type":"Services"
        }
    ],
    "sg:phone":"+44 1738 441399",
    "sg:postcode":"PH1 5YA",
    "sg:province":"Perth and Kinross",
    "sg:tags":[
        "glazier"
    ],
    "wof:name":"Balhousie Glazing Ltd.",
    "wof:placetype":"venue"
},
  "geometry": {"coordinates":[-3.439,56.39801],"type":"Point"}
}