{
  "type": "Feature",
  "properties": {
    "iso:country":"GB",
    "sg:address":"Unit 13 Harlequin Centre, Paul Street",
    "sg:city":"Exeter",
    "sg:classifiers":[
        {
            "category":"Home & Garden",
            "subcategory":"Kitchen Supply",
            "type":"Retail Goods"
        }
    ],
    "sg:phone":"+44 1392 258576",
    "sg:postcode":"EX4 3TT",
    "sg:province":"Devon",
    "sg:tags":[
        "ware"
    ],
    "wof:name":"The Cookshop",
    "wof:placetype":"venue"
},
  "geometry": {"coordinates":[-3.533344,50.72419],"type":"Point"}
}