{
  "type": "Feature",
  "properties": {
    "iso:country":"GB",
    "sg:address":"176 High Street",
    "sg:city":"Dudley",
    "sg:classifiers":[
        {
            "category":"Wholesale",
            "subcategory":"Medical Equipment & Supplies",
            "type":"Manufacturing & Wholesale Goods"
        }
    ],
    "sg:phone":"+44 1384 256002",
    "sg:postcode":"DY1 1QE",
    "sg:province":"West Midlands",
    "sg:tags":[
        "aid",
        "hearing"
    ],
    "wof:name":"The Dudley Hearing Centre",
    "wof:placetype":"venue"
},
  "geometry": {"coordinates":[-2.086616993,52.508934021],"type":"Point"}
}