{
  "type": "Feature",
  "properties": {
    "iso:country":"GB",
    "sg:address":"Scotland House",
    "sg:city":"Kidderminster",
    "sg:classifiers":[
        {
            "category":"Professional",
            "subcategory":"Accounting & Tax Preparation",
            "type":"Services"
        }
    ],
    "sg:postcode":"DY10 1QG",
    "sg:province":"Staffordshire",
    "sg:tags":[
        "accountant"
    ],
    "wof:name":"Laud Grice & Co",
    "wof:placetype":"venue"
},
  "geometry": {"coordinates":[-2.239409,52.382],"type":"Point"}
}