{
  "type": "Feature",
  "properties": {
    "addr:full":"283 St Helens Rd Leigh Lancashire WN7 3PA",
    "addr:housenumber":"283",
    "addr:postcode":"wn7 3pa",
    "addr:street":"St Helens Rd",
    "iso:country":"GB",
    "sg:address":"283 St Helens Rd",
    "sg:city":"Leigh",
    "sg:classifiers":[
        {
            "category":"Shopping",
            "subcategory":"Pets & Pet Supplies",
            "type":"Retail Goods"
        }
    ],
    "sg:postcode":"WN7 3PA",
    "sg:province":"Lancashire",
    "sg:tags":[
        "butcher"
    ],
    "wof:name":"Darbyshire,N,",
    "wof:placetype":"venue"
},
  "geometry": {"coordinates":[-2.5389831066,53.4800071716],"type":"Point"}
}