{
  "type": "Feature",
  "properties": {
    "iso:country":"GB",
    "sg:address":"Unit 2 Stennack Rd",
    "sg:city":"St Austell",
    "sg:classifiers":[
        {
            "category":"Home & Garden",
            "subcategory":"Hardware",
            "type":"Retail Goods"
        }
    ],
    "sg:phone":"+44 1726 67358",
    "sg:postcode":"PL25 3JQ",
    "sg:province":"Cornwall",
    "sg:tags":[
        "tubing",
        "fitting",
        "hose",
        "diy"
    ],
    "wof:name":"Western Hose & Fittings",
    "wof:placetype":"venue"
},
  "geometry": {"coordinates":[-4.761153,50.341839],"type":"Point"}
}