{
  "type": "Feature",
  "properties": {
    "iso:country":"GB",
    "sg:address":"2 Dock Street",
    "sg:city":"Bo'ness",
    "sg:classifiers":[
        {
            "category":"Retail",
            "subcategory":"Auto Repair",
            "type":"Services"
        }
    ],
    "sg:phone":"+44 1506 822523",
    "sg:postcode":"EH51 9AL",
    "sg:province":"Falkirk",
    "sg:tags":[
        "modification",
        "garage",
        "related"
    ],
    "wof:name":"Riddells Garage Bo'Ness Ltd",
    "wof:placetype":"venue"
},
  "geometry": {"coordinates":[-3.6026699543,56.0179405212],"type":"Point"}
}