{
  "type": "Feature",
  "properties": {
    "iso:country":"GB",
    "sg:address":"Old Mill (the), Earsham",
    "sg:city":"Bungay",
    "sg:classifiers":[
        {
            "category":"Manufacturing",
            "subcategory":"Lumber",
            "type":"Manufacturing & Wholesale Goods"
        }
    ],
    "sg:phone":"+44 1986 894745",
    "sg:postcode":"NR35 2TQ",
    "sg:province":"Norfolk",
    "sg:tags":[
        "importer",
        "merchants",
        "agent",
        "timber"
    ],
    "wof:name":"Country Superstores Ltd.",
    "wof:placetype":"venue"
},
  "geometry": {"coordinates":[1.4167950153,52.4525642395],"type":"Point"}
}