{
  "type": "Feature",
  "properties": {
    "iso:country":"GB",
    "sg:address":"Weststreet, Loxson",
    "sg:city":"Somerton",
    "sg:classifiers":[
        {
            "category":"Professional",
            "subcategory":"Engineering",
            "type":"Services"
        }
    ],
    "sg:postcode":"TA11 7PR",
    "sg:province":"Somerset",
    "wof:name":"Locke  F J & Son",
    "wof:placetype":"venue"
},
  "geometry": {"coordinates":[-2.734899044,51.0541648865],"type":"Point"}
}