{
  "type": "Feature",
  "properties": {
    "addr:full":"West View, Horden Peterlee Durham SR8 4DS",
    "addr:postcode":"sr8 4ds",
    "iso:country":"GB",
    "sg:address":"West View, Horden",
    "sg:city":"Peterlee",
    "sg:classifiers":[
        {
            "category":"Organizations",
            "subcategory":"Membership Organization",
            "type":"Services"
        }
    ],
    "sg:postcode":"SR8 4DS",
    "sg:province":"Durham",
    "sg:tags":[
        "club"
    ],
    "wof:name":"Horden Parkside Club",
    "wof:placetype":"venue"
},
  "geometry": {"coordinates":[-1.3111389875,54.7595596313],"type":"Point"}
}