{
  "type": "Feature",
  "properties": {
    "addr:full":"1a Pumpgate Street Inverness Highland IV3 8HX",
    "addr:housenumber":"1a",
    "addr:postcode":"iv3 8hx",
    "addr:street":"Pumpgate Street",
    "iso:country":"GB",
    "sg:address":"1a Pumpgate Street",
    "sg:city":"Inverness",
    "sg:classifiers":[
        {
            "category":"Bars & Pubs",
            "type":"Food & Drink"
        }
    ],
    "sg:postcode":"IV3 8HX",
    "sg:province":"Highland",
    "sg:tags":[
        "pubs",
        "inn"
    ],
    "wof:name":"Merkinch Arms",
    "wof:placetype":"venue"
},
  "geometry": {"coordinates":[-4.236955,57.485329],"type":"Point"}
}