{
  "type": "Feature",
  "properties": {
    "addr:full":"4 Brown Lennox Retail Park, Ynysangharad Road Pontypridd Caerphilly CF37 4DA",
    "addr:housenumber":"4",
    "addr:postcode":"cf37 4da",
    "addr:street":"Brown Lennox Retail Park Ynysangharad Road",
    "iso:country":"GB",
    "sg:address":"4 Brown Lennox Retail Park, Ynysangharad Road",
    "sg:city":"Pontypridd",
    "sg:classifiers":[
        {
            "category":"Shopping",
            "type":"Retail Goods"
        }
    ],
    "sg:phone":"+44 1443 485607",
    "sg:postcode":"CF37 4DA",
    "sg:province":"Caerphilly",
    "sg:tags":[
        "part",
        "accessory"
    ],
    "wof:name":"Halfords Superstore",
    "wof:placetype":"venue"
},
  "geometry": {"coordinates":[-3.3342740536,51.6021575928],"type":"Point"}
}