{
  "type": "Feature",
  "properties": {
    "addr:full":"Old Kirk Farm, Balloch Alexandria Argyll and Bute G83 8LY",
    "addr:postcode":"g83 8ly",
    "addr:street":"Old Kirk",
    "iso:country":"GB",
    "sg:address":"Old Kirk Farm, Balloch",
    "sg:city":"Alexandria",
    "sg:classifiers":[
        {
            "category":"Farming",
            "subcategory":"Farm",
            "type":"Manufacturing & Wholesale Goods"
        }
    ],
    "sg:phone":"+44 1389 752801",
    "sg:postcode":"G83 8LY",
    "sg:province":"Argyll and Bute",
    "sg:tags":[
        "mixed",
        "crop"
    ],
    "wof:name":"J A & A C McArthur",
    "wof:placetype":"venue"
},
  "geometry": {"coordinates":[-4.579449,56.004051],"type":"Point"}
}