{
  "type": "Feature",
  "properties": {
    "addr:full":"The Guildhall, Market Hill, Framlingham Woodbridge Suffolk IP13 9BD",
    "addr:postcode":"ip13 9bd",
    "addr:street":"Market Hill Framlingham",
    "iso:country":"GB",
    "sg:address":"The Guildhall, Market Hill, Framlingham",
    "sg:city":"Woodbridge",
    "sg:classifiers":[
        {
            "category":"Travel",
            "subcategory":"Travel Agent",
            "type":"Entertainment"
        }
    ],
    "sg:phone":"+44 1728 724446",
    "sg:postcode":"IP13 9BD",
    "sg:province":"Suffolk",
    "wof:name":"Galaxy Travel Ltd.",
    "wof:placetype":"venue"
},
  "geometry": {"coordinates":[1.3433320522,52.22108078],"type":"Point"}
}