{
  "type": "Feature",
  "properties": {
    "addr:full":"83 Pellatt Road, East Dulwich London Greater London SE22 9JD",
    "addr:housenumber":"83",
    "addr:postcode":"se22 9jd",
    "addr:street":"Pellatt Road",
    "iso:country":"GB",
    "sg:address":"83 Pellatt Road, East Dulwich",
    "sg:city":"London",
    "sg:classifiers":[
        {
            "category":"Real Estate",
            "subcategory":"Real Estate Agent",
            "type":"Services"
        }
    ],
    "sg:phone":"+44 20 8299 0533",
    "sg:postcode":"SE22 9JD",
    "sg:province":"Greater London",
    "wof:name":"St.Michael's Estate Agents Ltd.",
    "wof:placetype":"venue"
},
  "geometry": {"coordinates":[-0.0769340023,51.4543304443],"type":"Point"}
}