{
  "type": "Feature",
  "properties": {
    "addr:full":"18 Earsham Street Bungay Norfolk NR35 1AG",
    "addr:housenumber":"18",
    "addr:postcode":"nr35 1ag",
    "addr:street":"Earsham Street",
    "iso:country":"GB",
    "sg:address":"18 Earsham Street",
    "sg:city":"Bungay",
    "sg:classifiers":[
        {
            "category":"Real Estate",
            "subcategory":"Surveying",
            "type":"Services"
        }
    ],
    "sg:postcode":"NR35 1AG",
    "sg:province":"Norfolk",
    "sg:tags":[
        "building",
        "surveyor"
    ],
    "wof:name":"Patrick Bradley",
    "wof:placetype":"venue"
},
  "geometry": {"coordinates":[1.435995,52.456715],"type":"Point"}
}