{
  "type": "Feature",
  "properties": {
    "addr:full":"52 Frensham Road, Lower Bourne Farnham Hampshire GU10 3PX",
    "addr:housenumber":"52",
    "addr:postcode":"gu10 3px",
    "addr:street":"Frensham Road Lower",
    "iso:country":"GB",
    "sg:address":"52 Frensham Road, Lower Bourne",
    "sg:city":"Farnham",
    "sg:classifiers":[
        {
            "category":"Autos & Motor Vehicles",
            "subcategory":"Automobile Sales",
            "type":"Retail Goods"
        }
    ],
    "sg:postcode":"GU10 3PX",
    "sg:province":"Hampshire",
    "sg:tags":[
        "car"
    ],
    "wof:name":"John Morris",
    "wof:placetype":"venue"
},
  "geometry": {"coordinates":[-0.79009,51.196102],"type":"Point"}
}