{
  "type": "Feature",
  "properties": {
    "addr:full":"96 Mina Road Bristol City of Bristol BS2 9XW",
    "addr:housenumber":"96",
    "addr:postcode":"bs2 9xw",
    "addr:street":"Mina Road",
    "iso:country":"GB",
    "sg:address":"96 Mina Road",
    "sg:city":"Bristol",
    "sg:classifiers":[
        {
            "category":"Shopping",
            "subcategory":"News",
            "type":"Retail Goods"
        }
    ],
    "sg:phone":"+44 117 955 1246",
    "sg:postcode":"BS2 9XW",
    "sg:province":"City of Bristol",
    "sg:tags":[
        "newsagent"
    ],
    "wof:name":"Hussain News",
    "wof:placetype":"venue"
},
  "geometry": {"coordinates":[-2.575445,51.4697],"type":"Point"}
}