{
  "type": "Feature",
  "properties": {
    "addr:full":"Music Typesetters, New House, Albert Road Ballachulish Highland PH49 4JR",
    "addr:postcode":"ph49 4jr",
    "addr:street":"Albert Road",
    "iso:country":"GB",
    "sg:address":"Music Typesetters, New House, Albert Road",
    "sg:city":"Ballachulish",
    "sg:classifiers":[
        {
            "category":"Professional",
            "subcategory":"Printing & Photocopies",
            "type":"Services"
        }
    ],
    "sg:phone":"+44 1855 811507",
    "sg:postcode":"PH49 4JR",
    "sg:province":"Highland",
    "sg:tags":[
        "plate",
        "lithographic",
        "maker"
    ],
    "wof:name":"Music to Measure",
    "wof:placetype":"venue"
},
  "geometry": {"coordinates":[-5.1343002319,56.6772117615],"type":"Point"}
}