{
  "type": "Feature",
  "properties": {
    "iso:country":"GB",
    "sg:address":"Way Farm, North Tamerton",
    "sg:city":"Holsworthy",
    "sg:classifiers":[
        {
            "category":"Wholesale",
            "subcategory":"Non-durable Goods",
            "type":"Manufacturing & Wholesale Goods"
        },
        {
            "category":"Shopping",
            "subcategory":"Hobbies, Toys, & Games",
            "type":"Retail Goods"
        }
    ],
    "sg:postcode":"EX22 6RZ",
    "sg:province":"Cornwall",
    "sg:tags":[
        "carry",
        "toy",
        "sale",
        "cash"
    ],
    "wof:name":"K BERN WHOLESALE",
    "wof:placetype":"venue"
},
  "geometry": {"coordinates":[-4.3527340889,50.8100128174],"type":"Point"}
}