{
  "type": "Feature",
  "properties": {
    "iso:country":"GB",
    "sg:address":"40 Cannon Hill",
    "sg:city":"London",
    "sg:classifiers":[
        {
            "category":"Food & Beverages",
            "subcategory":"Liquor & Beverages",
            "type":"Retail Goods"
        }
    ],
    "sg:postcode":"N14 6LG",
    "sg:province":"Greater London",
    "sg:tags":[
        "beer",
        "spirit",
        "wines"
    ],
    "wof:name":"Noble Wine",
    "wof:placetype":"venue"
},
  "geometry": {"coordinates":[-0.123047,51.624043],"type":"Point"}
}