{
  "type": "Feature",
  "properties": {
    "iso:country":"GB",
    "sg:address":"1 Bow Street Chambers, Market Square",
    "sg:city":"Rugeley",
    "sg:classifiers":[
        {
            "category":"Farming",
            "subcategory":"Fish & Marine Products",
            "type":"Manufacturing & Wholesale Goods"
        },
        {
            "category":"Food & Beverages",
            "subcategory":"Meat & Fish",
            "type":"Retail Goods"
        }
    ],
    "sg:postcode":"WS15 2AZ",
    "sg:province":"Staffordshire",
    "sg:tags":[
        "fishmonger",
        "butcher"
    ],
    "wof:name":"R H Dean & Son",
    "wof:placetype":"venue"
},
  "geometry": {"coordinates":[-1.935352,52.757557],"type":"Point"}
}