{
  "type": "Feature",
  "properties": {
    "addr:full":"342 London Rd Grays Essex RM20 4AB",
    "addr:housenumber":"342",
    "addr:postcode":"rm20 4ab",
    "addr:street":"London Rd",
    "iso:country":"GB",
    "sg:address":"342 London Rd",
    "sg:city":"Grays",
    "sg:classifiers":[
        {
            "category":"Professional",
            "subcategory":"Engineering",
            "type":"Services"
        }
    ],
    "sg:phone":"+44 1375 372626",
    "sg:postcode":"RM20 4AB",
    "sg:province":"Essex",
    "sg:tags":[
        "contractor",
        "electrical",
        "engineer"
    ],
    "wof:name":"Wright Bros",
    "wof:placetype":"venue"
},
  "geometry": {"coordinates":[0.30181,51.477863],"type":"Point"}
}