{
  "type": "Feature",
  "properties": {
    "iso:country":"GB",
    "sg:address":"7 Cattlemarket",
    "sg:city":"Hexham",
    "sg:classifiers":[
        {
            "category":"Food & Beverages",
            "subcategory":"Meat & Fish",
            "type":"Retail Goods"
        }
    ],
    "sg:phone":"+44 1434 602271",
    "sg:postcode":"NE46 1NJ",
    "sg:province":"Northumberland",
    "sg:tags":[
        "butcher"
    ],
    "wof:name":"Thompson & Huddleston",
    "wof:placetype":"venue"
},
  "geometry": {"coordinates":[-2.0895791054,54.9650917053],"type":"Point"}
}