{
  "type": "Feature",
  "properties": {
    "addr:full":"4 Heather Drive, Lindford Bordon Hampshire GU35 0RN",
    "addr:housenumber":"4",
    "addr:postcode":"gu35 0rn",
    "addr:street":"Heather Drive",
    "iso:country":"GB",
    "sg:address":"4 Heather Drive, Lindford",
    "sg:city":"Bordon",
    "sg:classifiers":[
        {
            "category":"Building & Trades",
            "subcategory":"Construction",
            "type":"Services"
        }
    ],
    "sg:phone":"+44 1420 475074",
    "sg:postcode":"GU35 0RN",
    "sg:province":"Hampshire",
    "sg:tags":[
        "joinery",
        "joiner",
        "carpenter",
        "carpentry"
    ],
    "wof:name":"Nicholas Frank Powe",
    "wof:placetype":"venue"
},
  "geometry": {"coordinates":[-0.8484699726,51.1203956604],"type":"Point"}
}