{
  "type": "Feature",
  "properties": {
    "addr:full":"77 The Street, Warham Wells-next-the-sea Norfolk NR23 1NL",
    "addr:housenumber":"77",
    "addr:postcode":"nr23 1nl",
    "addr:street":"The Street",
    "iso:country":"GB",
    "sg:address":"77 The Street, Warham",
    "sg:city":"Wells-next-the-sea",
    "sg:classifiers":[
        {
            "category":"Professional",
            "subcategory":"Art Services",
            "type":"Services"
        }
    ],
    "sg:postcode":"NR23 1NL",
    "sg:province":"Norfolk",
    "sg:tags":[
        "graphic",
        "designer"
    ],
    "wof:name":"Lee,J,Graphic Design",
    "wof:placetype":"venue"
},
  "geometry": {"coordinates":[0.8975600004,52.9373512268],"type":"Point"}
}