{
  "type": "Feature",
  "properties": {
    "iso:country":"GB",
    "sg:address":"28 Telford Way",
    "sg:city":"Acton",
    "sg:classifiers":[
        {
            "category":"Conference Center",
            "type":"Public Place"
        }
    ],
    "sg:phone":"+44 20 8749 1019",
    "sg:postcode":"W3 7XS",
    "sg:province":"Greater London",
    "wof:name":"Stage Support",
    "wof:placetype":"venue"
},
  "geometry": {"coordinates":[-0.253848,51.520599],"type":"Point"}
}