{
  "type": "Feature",
  "properties": {
    "addr:full":"Winston Churchill House Ethel, Street, Birmingham West Midlands B2 4BG",
    "addr:postcode":"b2 4bg",
    "addr:street":"Winston;Ethel Street",
    "iso:country":"GB",
    "sg:address":"Winston Churchill House Ethel, Street,",
    "sg:city":"Birmingham",
    "sg:classifiers":[
        {
            "category":"Utilities",
            "type":"Services"
        }
    ],
    "sg:postcode":"B2 4BG",
    "sg:province":"West Midlands",
    "sg:tags":[
        "internet"
    ],
    "wof:name":"World-Wide-Foods Ltd",
    "wof:placetype":"venue"
},
  "geometry": {"coordinates":[-1.901079,52.478935],"type":"Point"}
}