{
  "type": "Feature",
  "properties": {
    "iso:country":"GB",
    "sg:address":"39 Balaam Street",
    "sg:city":"Plaistow",
    "sg:classifiers":[
        {
            "category":"Health Services",
            "subcategory":"Optometrist",
            "type":"Services"
        }
    ],
    "sg:phone":"+44 20 7476 9857",
    "sg:postcode":"E13 8EB",
    "sg:province":"Greater London",
    "sg:tags":[
        "optician"
    ],
    "wof:name":"W J Bowyer Ltd",
    "wof:placetype":"venue"
},
  "geometry": {"coordinates":[0.022414,51.523388],"type":"Point"}
}