{
  "type": "Feature",
  "properties": {
    "addr:full":"21 Moss Road, Kingswood Watford Hertfordshire WD25 0EW",
    "addr:housenumber":"21",
    "addr:postcode":"wd25 0ew",
    "addr:street":"Moss Road",
    "iso:country":"GB",
    "sg:address":"21 Moss Road, Kingswood",
    "sg:city":"Watford",
    "sg:classifiers":[
        {
            "category":"Retail",
            "subcategory":"Repair Shop",
            "type":"Services"
        }
    ],
    "sg:postcode":"WD25 0EW",
    "sg:province":"Hertfordshire",
    "sg:tags":[
        "maintenance"
    ],
    "wof:name":"John Lane Property Maintenance",
    "wof:placetype":"venue"
},
  "geometry": {"coordinates":[-0.3988130093,51.6903343201],"type":"Point"}
}