{
  "type": "Feature",
  "properties": {
    "iso:country":"GB",
    "sg:address":"Forge Ho, Tewkesbury Rd",
    "sg:city":"Cheltenham",
    "sg:classifiers":[
        {
            "category":"Home & Garden",
            "subcategory":"Home Furnishings",
            "type":"Retail Goods"
        }
    ],
    "sg:phone":"+44 1242 680453",
    "sg:postcode":"GL51 9SX",
    "sg:province":"Gloucestershire",
    "sg:tags":[
        "patio",
        "furniture"
    ],
    "wof:name":"Ewrose",
    "wof:placetype":"venue"
},
  "geometry": {"coordinates":[-2.092699,51.910004],"type":"Point"}
}