{
  "type": "Feature",
  "properties": {
    "addr:full":"7 Roger Beck Way, Sketty Swansea Swansea SA2 0JF",
    "addr:housenumber":"7",
    "addr:postcode":"sa2 0jf",
    "addr:street":"Roger Beck Way",
    "iso:country":"GB",
    "sg:address":"7 Roger Beck Way, Sketty",
    "sg:city":"Swansea",
    "sg:classifiers":[
        {
            "category":"Building & Trades",
            "subcategory":"Construction",
            "type":"Services"
        }
    ],
    "sg:phone":"+44 1792 206964",
    "sg:postcode":"SA2 0JF",
    "sg:province":"Swansea",
    "sg:tags":[
        "decorator",
        "painter"
    ],
    "wof:name":"G J & M Welch & Ian Atherton",
    "wof:placetype":"venue"
},
  "geometry": {"coordinates":[-3.976362,51.616787],"type":"Point"}
}