{
  "type": "Feature",
  "properties": {
    "addr:full":"Hylton Rd Sunderland Tyne and Wear SR4 7XF",
    "addr:postcode":"sr4 7xf",
    "addr:street":"Hylton Rd",
    "iso:country":"GB",
    "sg:address":"Hylton Rd",
    "sg:city":"Sunderland",
    "sg:classifiers":[
        {
            "category":"Health Services",
            "subcategory":"Doctor",
            "type":"Services"
        }
    ],
    "sg:phone":"+44 191 567 1319",
    "sg:postcode":"SR4 7XF",
    "sg:province":"Tyne and Wear",
    "sg:tags":[
        "practitioners"
    ],
    "wof:name":"Shetty, K",
    "wof:placetype":"venue"
},
  "geometry": {"coordinates":[-1.41057,54.903999],"type":"Point"}
}