{
  "type": "Feature",
  "properties": {
    "addr:full":"80 College Rd Liverpool Merseyside L23 0RP",
    "addr:housenumber":"80",
    "addr:postcode":"l23 0rp",
    "addr:street":"College Rd",
    "iso:country":"GB",
    "sg:address":"80 College Rd",
    "sg:city":"Liverpool",
    "sg:classifiers":[
        {
            "category":"Shopping",
            "subcategory":"Optical Goods",
            "type":"Retail Goods"
        }
    ],
    "sg:phone":"+44 151 931 5427",
    "sg:postcode":"L23 0RP",
    "sg:province":"Merseyside",
    "wof:name":"A & J Brown Optical Co",
    "wof:placetype":"venue"
},
  "geometry": {"coordinates":[-3.030662,53.484585],"type":"Point"}
}