{
  "type": "Feature",
  "properties": {
    "iso:country":"GB",
    "sg:address":"4 St. Georges, Wicklewood",
    "sg:city":"Wymondham",
    "sg:classifiers":[
        {
            "category":"Shopping",
            "subcategory":"Crafts & Fabrics",
            "type":"Retail Goods"
        },
        {
            "category":"Wholesale",
            "subcategory":"Plants",
            "type":"Manufacturing & Wholesale Goods"
        }
    ],
    "sg:phone":"+44 1953 603139",
    "sg:postcode":"NR18 9PD",
    "sg:province":"Norfolk",
    "sg:tags":[
        "machine",
        "sewing",
        "knitting"
    ],
    "wof:name":"Martin Land Sewing Machine Co Ltd",
    "wof:placetype":"venue"
},
  "geometry": {"coordinates":[1.0624300241,52.5835113525],"type":"Point"}
}