{
  "type": "Feature",
  "properties": {
    "addr:full":"Ravensleigh House, 1 Westmoreland Place Bromley Kent BR1 1DS",
    "addr:housenumber":"1",
    "addr:postcode":"br1 1ds",
    "addr:street":"Westmoreland Place",
    "iso:country":"GB",
    "sg:address":"Ravensleigh House, 1 Westmoreland Place",
    "sg:city":"Bromley",
    "sg:classifiers":[
        {
            "category":"Health Services",
            "subcategory":"Nursing And Care Facility",
            "type":"Services"
        }
    ],
    "sg:phone":"+44 20 8402 1010",
    "sg:postcode":"BR1 1DS",
    "sg:province":"Kent",
    "sg:tags":[
        "home"
    ],
    "wof:name":"Bromley Federation of Housing Associations",
    "wof:placetype":"venue"
},
  "geometry": {"coordinates":[0.01708,51.398827],"type":"Point"}
}