{
  "type": "Feature",
  "properties": {
    "addr:full":"Lawrence House, Goodwyn Avenue, Mill Hill London Greater London NW7 3RH",
    "addr:postcode":"nw7 3rh",
    "addr:street":"Goodwyn Avenue",
    "iso:country":"GB",
    "sg:address":"Lawrence House, Goodwyn Avenue, Mill Hill",
    "sg:city":"London",
    "sg:classifiers":[
        {
            "category":"Professional",
            "subcategory":"Business Services",
            "type":"Services"
        }
    ],
    "sg:phone":"+44 20 8906 8787",
    "sg:postcode":"NW7 3RH",
    "sg:province":"Greater London",
    "sg:tags":[
        "import",
        "export",
        "agent"
    ],
    "wof:name":"Mediterranean Growers Ltd.",
    "wof:placetype":"venue"
},
  "geometry": {"coordinates":[-0.2477740049,51.6155967712],"type":"Point"}
}