{
  "type": "Feature",
  "properties": {
    "iso:country":"GB",
    "sg:address":"Yeoman Lane",
    "sg:city":"Maidstone",
    "sg:classifiers":[
        {
            "category":"Health Services",
            "subcategory":"Doctor",
            "type":"Services"
        }
    ],
    "sg:phone":"+44 1622 737326",
    "sg:postcode":"ME14 4DS",
    "sg:province":"Kent",
    "sg:tags":[
        "practitioners"
    ],
    "wof:name":"The Surgery",
    "wof:placetype":"venue"
},
  "geometry": {"coordinates":[0.57465,51.270576],"type":"Point"}
}