{
  "type": "Feature",
  "properties": {
    "addr:full":"Longfield House, Aubourn Road, Bassingham Lincoln Lincolnshire LN5 9LE",
    "addr:postcode":"ln5 9le",
    "addr:street":"Aubourn Road",
    "iso:country":"GB",
    "sg:address":"Longfield House, Aubourn Road, Bassingham",
    "sg:city":"Lincoln",
    "sg:classifiers":[
        {
            "category":"Professional",
            "subcategory":"Engineering",
            "type":"Services"
        },
        {
            "category":"Building & Trades",
            "subcategory":"Electrical",
            "type":"Services"
        }
    ],
    "sg:phone":"+44 1522 788077",
    "sg:postcode":"LN5 9LE",
    "sg:province":"Lincolnshire",
    "sg:tags":[
        "engineer",
        "electrician",
        "contractor"
    ],
    "wof:name":"Mark Andrew Booker",
    "wof:placetype":"venue"
},
  "geometry": {"coordinates":[-0.6389759779,53.1281890869],"type":"Point"}
}