{
  "type": "Feature",
  "properties": {
    "addr:full":"Unit 9, 14 Bull Lane, Edmonton Upper Edmonton Greater London N18 1SX",
    "addr:housenumber":"unit;14",
    "addr:postcode":"n18 1sx",
    "addr:street":"Bull Lane",
    "iso:country":"GB",
    "sg:address":"Unit 9, 14 Bull Lane, Edmonton",
    "sg:city":"Upper Edmonton",
    "sg:classifiers":[
        {
            "category":"Shopping",
            "subcategory":"Clothing, Apparel, & Fashions",
            "type":"Retail Goods"
        }
    ],
    "sg:phone":"+44 20 8884 3868",
    "sg:postcode":"N18 1SX",
    "sg:province":"Greater London",
    "sg:tags":[
        "clothing",
        "fabric"
    ],
    "wof:name":"Circleace Ltd",
    "wof:placetype":"venue"
},
  "geometry": {"coordinates":[-0.075664,51.609882],"type":"Point"}
}