{
  "type": "Feature",
  "properties": {
    "iso:country":"GB",
    "sg:address":"15 Front Street, Arnold",
    "sg:city":"Nottingham",
    "sg:classifiers":[
        {
            "category":"Manufacturing",
            "subcategory":"Tools & Machinery",
            "type":"Manufacturing & Wholesale Goods"
        },
        {
            "category":"Insurance",
            "subcategory":"Insurance Agent",
            "type":"Services"
        }
    ],
    "sg:phone":"+44 115 920 3220",
    "sg:postcode":"NG5 7EA",
    "sg:province":"Nottinghamshire",
    "sg:tags":[
        "society",
        "friendly"
    ],
    "wof:name":"HILL HOUSE HAMMOND LTD",
    "wof:placetype":"venue"
},
  "geometry": {"coordinates":[-1.1281520128,53.0029182434],"type":"Point"}
}