{
  "type": "Feature",
  "properties": {
    "addr:full":"Hanover Place Sunderland Tyne and Wear SR4 6BY",
    "addr:postcode":"sr4 6by",
    "addr:street":"Hanover Place",
    "iso:country":"GB",
    "sg:address":"Hanover Place",
    "sg:city":"Sunderland",
    "sg:classifiers":[
        {
            "category":"Retail",
            "subcategory":"Auto Repair",
            "type":"Services"
        }
    ],
    "sg:phone":"+44 191 565 9123",
    "sg:postcode":"SR4 6BY",
    "sg:province":"Tyne and Wear",
    "sg:tags":[
        "modification",
        "garage"
    ],
    "wof:name":"Ayres Quay Motors",
    "wof:placetype":"venue"
},
  "geometry": {"coordinates":[-1.3944979906,54.9133071899],"type":"Point"}
}