{
  "type": "Feature",
  "properties": {
    "iso:country":"GB",
    "sg:address":"39 Dens Road",
    "sg:city":"Arbroath",
    "sg:classifiers":[
        {
            "category":"Manufacturing",
            "subcategory":"Metals",
            "type":"Manufacturing & Wholesale Goods"
        },
        {
            "category":"Wholesale",
            "subcategory":"Construction Materials",
            "type":"Manufacturing & Wholesale Goods"
        },
        {
            "category":"Home & Garden",
            "subcategory":"Hardware",
            "type":"Retail Goods"
        }
    ],
    "sg:phone":"+44 1241 872131",
    "sg:postcode":"DD11 1RU",
    "sg:province":"Angus",
    "sg:tags":[
        "spring",
        "distributor",
        "fastener",
        "fixing",
        "device",
        "manufacturer"
    ],
    "wof:name":"Precision Springs",
    "wof:placetype":"venue"
},
  "geometry": {"coordinates":[-2.5891590118,56.566860199],"type":"Point"}
}