{
  "type": "Feature",
  "properties": {
    "addr:full":"West Bargate, High Street Southampton Hampshire SO14 2FT",
    "addr:postcode":"so14 2ft",
    "addr:street":"West Bargate High Street",
    "iso:country":"GB",
    "sg:address":"West Bargate, High Street",
    "sg:city":"Southampton",
    "sg:classifiers":[
        {
            "category":"Home & Garden",
            "subcategory":"Furniture",
            "type":"Retail Goods"
        }
    ],
    "sg:phone":"+44 23 8023 0023",
    "sg:postcode":"SO14 2FT",
    "sg:province":"Hampshire",
    "wof:name":"The Linen Factory",
    "wof:placetype":"venue"
},
  "geometry": {"coordinates":[-1.4043669701,50.9026603699],"type":"Point"}
}