{
  "type": "Feature",
  "properties": {
    "iso:country":"GB",
    "sg:address":"151 New Road, West Parley",
    "sg:city":"Ferndown",
    "sg:classifiers":[
        {
            "category":"Home & Garden",
            "subcategory":"Furniture",
            "type":"Retail Goods"
        }
    ],
    "sg:postcode":"BH22 8EB",
    "sg:province":"Dorset",
    "wof:name":"Pinewood Studio",
    "wof:placetype":"venue"
},
  "geometry": {"coordinates":[-1.8822360039,50.7805595398],"type":"Point"}
}