{
  "type": "Feature",
  "properties": {
    "addr:full":"Burlington Lane London Greater London W4 3UN",
    "addr:postcode":"w4 3un",
    "addr:street":"Burlington Lane",
    "iso:country":"GB",
    "sg:address":"Burlington Lane",
    "sg:city":"London",
    "sg:classifiers":[
        {
            "category":"Education",
            "subcategory":"University",
            "type":"Public Place"
        }
    ],
    "sg:phone":"+44 20 8995 5934",
    "sg:postcode":"W4 3UN",
    "sg:province":"Greater London",
    "sg:tags":[
        "adult"
    ],
    "wof:name":"Chiswick Adult Education Centre",
    "wof:placetype":"venue"
},
  "geometry": {"coordinates":[-0.260259,51.48222],"type":"Point"}
}