{
  "type": "Feature",
  "properties": {
    "addr:full":"16 Regents Wharf, All Saints Street London Greater London N1 9RL",
    "addr:housenumber":"16",
    "addr:postcode":"n1 9rl",
    "addr:street":"Regents Wharf All Saints Street",
    "iso:country":"GB",
    "sg:address":"16 Regents Wharf, All Saints Street",
    "sg:city":"London",
    "sg:classifiers":[
        {
            "category":"Professional",
            "subcategory":"Art Services",
            "type":"Services"
        }
    ],
    "sg:phone":"+44 20 7837 5778",
    "sg:postcode":"N1 9RL",
    "sg:province":"Greater London",
    "sg:tags":[
        "consultant",
        "design"
    ],
    "wof:name":"Williams & Phoa Trustees Ltd.",
    "wof:placetype":"venue"
},
  "geometry": {"coordinates":[-0.1182700023,51.5347099304],"type":"Point"}
}