{
  "type": "Feature",
  "properties": {
    "addr:full":"35 Bancroft Hitchin Bedfordshire SG5 1LA",
    "addr:housenumber":"35",
    "addr:postcode":"sg5 1la",
    "addr:street":"Bancroft",
    "iso:country":"GB",
    "sg:address":"35 Bancroft",
    "sg:city":"Hitchin",
    "sg:classifiers":[
        {
            "category":"Professional",
            "subcategory":"Employment Agencies",
            "type":"Services"
        }
    ],
    "sg:phone":"+44 1462 441108",
    "sg:postcode":"SG5 1LA",
    "sg:province":"Bedfordshire",
    "sg:tags":[
        "consultant"
    ],
    "wof:name":"Justin Time Recruitment Ltd",
    "wof:placetype":"venue"
},
  "geometry": {"coordinates":[-0.2767429948,51.9510688782],"type":"Point"}
}