{
  "type": "Feature",
  "properties": {
    "addr:full":"13-23 North Square, Edmonton Green Shopping Centre London Greater London N9 0HW",
    "addr:housenumber":"13-23",
    "addr:postcode":"n9 0hw",
    "addr:street":"North Square Edmonton Green Shopping",
    "iso:country":"GB",
    "sg:address":"13-23 North Square, Edmonton Green Shopping Centre",
    "sg:city":"London",
    "sg:classifiers":[
        {
            "category":"Shopping",
            "subcategory":"Department Store",
            "type":"Retail Goods"
        },
        {
            "category":"Shopping",
            "subcategory":"Clothing, Apparel, & Fashions",
            "type":"Retail Goods"
        }
    ],
    "sg:phone":"+44 20 8884 1698",
    "sg:postcode":"N9 0HW",
    "sg:province":"Greater London",
    "sg:tags":[
        "shop",
        "departmental"
    ],
    "sg:website":"http://www.peacocks.co.uk",
    "wof:name":"Peacock's Stores Ltd.",
    "wof:placetype":"venue"
},
  "geometry": {"coordinates":[-0.0552739985,51.6258468628],"type":"Point"}
}