{
  "type": "Feature",
  "properties": {
    "iso:country":"GB",
    "sg:address":"34 Vicarage La",
    "sg:city":"Southampton",
    "sg:classifiers":[
        {
            "category":"Professional",
            "subcategory":"Art Services",
            "type":"Services"
        }
    ],
    "sg:phone":"+44 1489 781555",
    "sg:postcode":"SO32 2DP",
    "sg:province":"Hampshire",
    "sg:tags":[
        "graphic",
        "designer"
    ],
    "wof:name":"Maggsound Commercial",
    "wof:placetype":"venue"
},
  "geometry": {"coordinates":[-1.256423,50.918396],"type":"Point"}
}