{
  "type": "Feature",
  "properties": {
    "iso:country":"GB",
    "sg:address":"The Old Bakehouse, Lower Common, Aylburton",
    "sg:city":"Lydney",
    "sg:classifiers":[
        {
            "category":"Building & Trades",
            "subcategory":"Landscaping Services",
            "type":"Services"
        }
    ],
    "sg:phone":"+44 1594 841900",
    "sg:postcode":"GL15 6DR",
    "sg:province":"Gloucestershire",
    "sg:tags":[
        "designer",
        "architect",
        "landscape"
    ],
    "wof:name":"Jo Johnson Landscape Architects",
    "wof:placetype":"venue"
},
  "geometry": {"coordinates":[-2.5532560349,51.7147712708],"type":"Point"}
}