{
  "type": "Feature",
  "properties": {
    "iso:country":"GB",
    "sg:address":"Foxcote Farm, Foscot",
    "sg:city":"Chipping Norton",
    "sg:classifiers":[
        {
            "category":"Banks & Credit Unions",
            "subcategory":"Investment Brokerage",
            "type":"Services"
        }
    ],
    "sg:phone":"+44 1608 658881",
    "sg:postcode":"OX7 6RH",
    "sg:province":"Gloucestershire",
    "sg:tags":[
        "contractor"
    ],
    "wof:name":"Loudham Estates (Suffolk) Ltd.",
    "wof:placetype":"venue"
},
  "geometry": {"coordinates":[-1.6391340494,51.8946838379],"type":"Point"}
}