{
  "type": "Feature",
  "properties": {
    "addr:full":"11 Beechwood Drive Alexandria Argyll and Bute G83 9LR",
    "addr:housenumber":"11",
    "addr:postcode":"g83 9lr",
    "addr:street":"Beechwood Drive",
    "iso:country":"GB",
    "sg:address":"11 Beechwood Drive",
    "sg:city":"Alexandria",
    "sg:classifiers":[
        {
            "category":"Personal",
            "subcategory":"Beauty Salon",
            "type":"Services"
        }
    ],
    "sg:phone":"+44 1389 721336",
    "sg:postcode":"G83 9LR",
    "sg:province":"Argyll and Bute",
    "sg:tags":[
        "unisex",
        "ladies",
        "hairdresser"
    ],
    "wof:name":"Beechwood Hair Salon",
    "wof:placetype":"venue"
},
  "geometry": {"coordinates":[-4.5555357933,55.9765701294],"type":"Point"}
}