{
  "type": "Feature",
  "properties": {
    "addr:full":"8 Southgate Devizes Wiltshire SN10 5BY",
    "addr:housenumber":"8",
    "addr:postcode":"sn10 5by",
    "addr:street":"Southgate Devizes",
    "iso:country":"GB",
    "sg:address":"8 Southgate",
    "sg:city":"Devizes",
    "sg:classifiers":[
        {
            "category":"Retail",
            "subcategory":"Driving School",
            "type":"Services"
        }
    ],
    "sg:postcode":"SN10 5BY",
    "sg:province":"Wiltshire",
    "wof:name":"John Butler School of Motoring",
    "wof:placetype":"venue"
},
  "geometry": {"coordinates":[-1.991224,51.348145],"type":"Point"}
}