{
  "type": "Feature",
  "properties": {
    "iso:country":"GB",
    "sg:address":"8 Southgate",
    "sg:city":"Devizes",
    "sg:classifiers":[
        {
            "category":"Retail",
            "subcategory":"Driving School",
            "type":"Services"
        }
    ],
    "sg:postcode":"SN10 5BY",
    "sg:province":"Wiltshire",
    "wof:name":"John Butler School of Motoring",
    "wof:placetype":"venue"
},
  "geometry": {"coordinates":[-1.991224,51.348145],"type":"Point"}
}