{
  "type": "Feature",
  "properties": {
    "addr:full":"2 South Side, Shilbottle Alnwick Northumberland NE66 2XP",
    "addr:housenumber":"2",
    "addr:postcode":"ne66 2xp",
    "addr:street":"South",
    "iso:country":"GB",
    "sg:address":"2 South Side, Shilbottle",
    "sg:city":"Alnwick",
    "sg:classifiers":[
        {
            "category":"Organizations",
            "subcategory":"Non-profit Organization",
            "type":"Services"
        }
    ],
    "sg:phone":"+44 1665 575565",
    "sg:postcode":"NE66 2XP",
    "sg:province":"Northumberland",
    "sg:tags":[
        "organisation",
        "voluntary",
        "charity"
    ],
    "wof:name":"National Childbirth Trust",
    "wof:placetype":"venue"
},
  "geometry": {"coordinates":[-1.693514,55.40789],"type":"Point"}
}