{
  "type": "Feature",
  "properties": {
    "addr:full":"169 Pasture Road Nottingham Nottinghamshire NG9 8HZ",
    "addr:housenumber":"169",
    "addr:postcode":"ng9 8hz",
    "addr:street":"Pasture Road",
    "iso:country":"GB",
    "sg:address":"169 Pasture Road",
    "sg:city":"Nottingham",
    "sg:classifiers":[
        {
            "category":"Autos & Motor Vehicles",
            "subcategory":"Automobile Sales",
            "type":"Retail Goods"
        }
    ],
    "sg:postcode":"NG9 8HZ",
    "sg:province":"Nottinghamshire",
    "sg:tags":[
        "commercial"
    ],
    "wof:name":"M & M Cars",
    "wof:placetype":"venue"
},
  "geometry": {"coordinates":[-1.272207,52.940018],"type":"Point"}
}