{
  "type": "Feature",
  "properties": {
    "iso:country":"GB",
    "sg:address":"11 Knightsbridge Grn",
    "sg:city":"London",
    "sg:classifiers":[
        {
            "category":"Professional",
            "subcategory":"Printing & Photocopies",
            "type":"Services"
        }
    ],
    "sg:phone":"+44 20 7589 7203",
    "sg:postcode":"SW1X 7QL",
    "sg:province":"Greater London",
    "sg:tags":[
        "printer"
    ],
    "wof:name":"Kall-Kwik Printing",
    "wof:placetype":"venue"
},
  "geometry": {"coordinates":[-0.162378,51.501461],"type":"Point"}
}