{
  "type": "Feature",
  "properties": {
    "addr:full":"Plas Y Ward Farm, Rhewl Ruthin Denbighshire LL15 1TE",
    "addr:postcode":"ll15 1te",
    "addr:street":"Plas Y Ward",
    "iso:country":"GB",
    "sg:address":"Plas Y Ward Farm, Rhewl",
    "sg:city":"Ruthin",
    "sg:classifiers":[
        {
            "category":"Farming",
            "subcategory":"Livestock Farm",
            "type":"Manufacturing & Wholesale Goods"
        },
        {
            "category":"Farming",
            "subcategory":"Farm",
            "type":"Manufacturing & Wholesale Goods"
        }
    ],
    "sg:phone":"+44 1824 703822",
    "sg:postcode":"LL15 1TE",
    "sg:province":"Denbighshire",
    "sg:tags":[
        "mixed",
        "others"
    ],
    "wof:name":"H W Francis & Sons",
    "wof:placetype":"venue"
},
  "geometry": {"coordinates":[-3.3045220375,53.1140174866],"type":"Point"}
}