{
  "type": "Feature",
  "properties": {
    "addr:full":"Loanwath Road Annan Cumbria DG16 5ES",
    "addr:postcode":"dg16 5es",
    "addr:street":"Loanwath Road",
    "iso:country":"GB",
    "sg:address":"Loanwath Road",
    "sg:city":"Annan",
    "sg:classifiers":[
        {
            "category":"Manufacturing",
            "subcategory":"Chemicals & Compounds",
            "type":"Manufacturing & Wholesale Goods"
        }
    ],
    "sg:phone":"+44 1461 337572",
    "sg:postcode":"DG16 5ES",
    "sg:province":"Cumbria",
    "sg:tags":[
        "pesticide"
    ],
    "wof:name":"Ace Chemicals Ltd.",
    "wof:placetype":"venue"
},
  "geometry": {"coordinates":[-3.0762500763,54.9933586121],"type":"Point"}
}