{
  "type": "Feature",
  "properties": {
    "iso:country":"GB",
    "sg:address":"Blyth Valley Venture Workshops, Plessey Road",
    "sg:city":"Blyth",
    "sg:classifiers":[
        {
            "category":"Manufacturing",
            "subcategory":"Tools & Machinery",
            "type":"Manufacturing & Wholesale Goods"
        }
    ],
    "sg:postcode":"NE24 4BN",
    "sg:province":"Northumberland",
    "sg:tags":[
        "design",
        "maker"
    ],
    "wof:name":"Richard Kell",
    "wof:placetype":"venue"
},
  "geometry": {"coordinates":[-1.515669,55.123665],"type":"Point"}
}