{
  "type": "Feature",
  "properties": {
    "addr:full":"Stanford House, Princess Margaret Road, East Tilbury Grays Essex RM18 8YP",
    "addr:postcode":"rm18 8yp",
    "addr:street":"Princess Margaret Road East",
    "iso:country":"GB",
    "sg:address":"Stanford House, Princess Margaret Road, East Tilbury",
    "sg:city":"Grays",
    "sg:classifiers":[
        {
            "category":"Food & Beverages",
            "subcategory":"Supermarket",
            "type":"Retail Goods"
        }
    ],
    "sg:phone":"+44 1375 858600",
    "sg:postcode":"RM18 8YP",
    "sg:province":"Essex",
    "wof:name":"Tillberries",
    "wof:placetype":"venue"
},
  "geometry": {"coordinates":[0.4134550095,51.4847717285],"type":"Point"}
}