{
  "type": "Feature",
  "properties": {
    "iso:country":"GB",
    "sg:address":"36 Seymour Rd",
    "sg:city":"Newton Abbot",
    "sg:classifiers":[
        {
            "category":"Personal",
            "type":"Services"
        }
    ],
    "sg:postcode":"TQ12 2PU",
    "sg:province":"Devon",
    "sg:tags":[
        "dating",
        "friendship",
        "agency"
    ],
    "wof:name":"Alpha Connect",
    "wof:placetype":"venue"
},
  "geometry": {"coordinates":[-3.6101059914,50.535194397],"type":"Point"}
}