{
  "type": "Feature",
  "properties": {
    "addr:full":"Integration House, Alba Campus Livingston West Lothian EH54 7LL",
    "addr:postcode":"eh54 7ll",
    "iso:country":"GB",
    "sg:address":"Integration House, Alba Campus",
    "sg:city":"Livingston",
    "sg:classifiers":[
        {
            "category":"Professional",
            "subcategory":"Computer Services",
            "type":"Services"
        }
    ],
    "sg:phone":"+44 1506 460234",
    "sg:postcode":"EH54 7LL",
    "sg:province":"West Lothian",
    "sg:tags":[
        "system",
        "software"
    ],
    "wof:name":"Spektra Group Ltd.",
    "wof:placetype":"venue"
},
  "geometry": {"coordinates":[-3.5381588936,55.8858184814],"type":"Point"}
}