{
  "type": "Feature",
  "properties": {
    "iso:country":"GB",
    "sg:address":"464 Dudley Road",
    "sg:city":"Wolverhampton",
    "sg:classifiers":[
        {
            "category":"Food & Beverages",
            "subcategory":"Bakery",
            "type":"Retail Goods"
        }
    ],
    "sg:phone":"+44 1902 452072",
    "sg:postcode":"WV2 3AF",
    "sg:province":"West Midlands",
    "sg:tags":[
        "baker"
    ],
    "wof:name":"The Bread Basket",
    "wof:placetype":"venue"
},
  "geometry": {"coordinates":[-2.126407,52.575127],"type":"Point"}
}