{
  "type": "Feature",
  "properties": {
    "addr:full":"The Roses, Epping Road, Roydon Harlow Essex CM19 5DD",
    "addr:postcode":"cm19 5dd",
    "addr:street":"Epping Road",
    "iso:country":"GB",
    "sg:address":"The Roses, Epping Road, Roydon",
    "sg:city":"Harlow",
    "sg:classifiers":[
        {
            "category":"Freight",
            "type":"Transportation"
        }
    ],
    "sg:phone":"+44 1279 793105",
    "sg:postcode":"CM19 5DD",
    "sg:province":"Essex",
    "sg:tags":[
        "haulage",
        "transport",
        "road"
    ],
    "wof:name":"Kingsbury Transport",
    "wof:placetype":"venue"
},
  "geometry": {"coordinates":[0.038872,51.769241],"type":"Point"}
}