{
  "type": "Feature",
  "properties": {
    "addr:full":"9 Dellfield Parade, High Street, Cowley Uxbridge Buckinghamshire UB8 2EN",
    "addr:housenumber":"9",
    "addr:postcode":"ub8 2en",
    "addr:street":"Dellfield Parade High Street",
    "iso:country":"GB",
    "sg:address":"9 Dellfield Parade, High Street, Cowley",
    "sg:city":"Uxbridge",
    "sg:classifiers":[
        {
            "category":"Professional",
            "subcategory":"Accounting & Tax Preparation",
            "type":"Services"
        }
    ],
    "sg:phone":"+44 1895 256400",
    "sg:postcode":"UB8 2EN",
    "sg:province":"Buckinghamshire",
    "sg:tags":[
        "accountant"
    ],
    "wof:name":"Philippou & Co",
    "wof:placetype":"venue"
},
  "geometry": {"coordinates":[-0.480624,51.527771],"type":"Point"}
}