{
  "type": "Feature",
  "properties": {
    "iso:country":"GB",
    "sg:address":"2 White Hart Parade, London Road Blackwater",
    "sg:city":"Camberley",
    "sg:classifiers":[
        {
            "category":"Health Services",
            "subcategory":"Optometrist",
            "type":"Services"
        }
    ],
    "sg:phone":"+44 1276 33121",
    "sg:postcode":"GU17 9AA",
    "sg:province":"Hampshire",
    "sg:tags":[
        "optician"
    ],
    "wof:name":"Retina Medical Eye Centre",
    "wof:placetype":"venue"
},
  "geometry": {"coordinates":[-0.7793,51.331051],"type":"Point"}
}