{
  "type": "Feature",
  "properties": {
    "iso:country":"GB",
    "sg:address":"11 Piersland Place",
    "sg:city":"Irvine",
    "sg:classifiers":[
        {
            "category":"Professional",
            "subcategory":"Accounting & Tax Preparation",
            "type":"Services"
        },
        {
            "category":"Banks & Credit Unions",
            "subcategory":"Investment Brokerage",
            "type":"Services"
        }
    ],
    "sg:phone":"+44 1294 217129",
    "sg:postcode":"KA11 1QF",
    "sg:province":"East Ayrshire",
    "sg:tags":[
        "accountant",
        "auditor"
    ],
    "wof:name":"Andrew Howat & Co",
    "wof:placetype":"venue"
},
  "geometry": {"coordinates":[-4.6308307648,55.629825592],"type":"Point"}
}