{
  "type": "Feature",
  "properties": {
    "addr:full":"Shipman Joinery Yard, Station Rd, Rushton Kettering Northamptonshire NN14 1RL",
    "addr:postcode":"nn14 1rl",
    "addr:street":"Station Rd",
    "iso:country":"GB",
    "sg:address":"Shipman Joinery Yard, Station Rd, Rushton",
    "sg:city":"Kettering",
    "sg:classifiers":[
        {
            "category":"Shopping",
            "subcategory":"Pets & Pet Supplies",
            "type":"Retail Goods"
        }
    ],
    "sg:phone":"+44 1536 713405",
    "sg:postcode":"NN14 1RL",
    "sg:province":"Northamptonshire",
    "sg:tags":[
        "feed",
        "animal"
    ],
    "wof:name":"Countrywise Feeds & Needs",
    "wof:placetype":"venue"
},
  "geometry": {"coordinates":[-0.761384,52.438595],"type":"Point"}
}