{
  "type": "Feature",
  "properties": {
    "addr:full":"Vantage House, Great Lime Road Newcastle-upon-tyne Tyne and Wear NE12 9UD",
    "addr:postcode":"ne12 9ud",
    "addr:street":"Great Lime Road",
    "iso:country":"GB",
    "sg:address":"Vantage House, Great Lime Road",
    "sg:city":"Newcastle-upon-tyne",
    "sg:classifiers":[
        {
            "category":"Professional",
            "subcategory":"Management & Consulting",
            "type":"Services"
        }
    ],
    "sg:phone":"+44 191 280 2000",
    "sg:postcode":"NE12 9UD",
    "sg:province":"Tyne and Wear",
    "sg:tags":[
        "marketing",
        "consultant"
    ],
    "wof:name":"Vantagemax Plc",
    "wof:placetype":"venue"
},
  "geometry": {"coordinates":[-1.5357120037,55.0235710144],"type":"Point"}
}