{
  "type": "Feature",
  "properties": {
    "addr:full":"Snaygill Road Industrial Estate Skipton Lancashire BD23 2QR",
    "addr:postcode":"bd23 2qr",
    "addr:street":"Snaygill Road Industrial Estate",
    "iso:country":"GB",
    "sg:address":"Snaygill Road Industrial Estate",
    "sg:city":"Skipton",
    "sg:classifiers":[
        {
            "category":"Home & Garden",
            "subcategory":"Furniture",
            "type":"Retail Goods"
        }
    ],
    "sg:phone":"+44 870 746 7722",
    "sg:postcode":"BD23 2QR",
    "sg:province":"Lancashire",
    "sg:tags":[
        "bed",
        "mattress"
    ],
    "wof:name":"Pocket Spring Bed Company",
    "wof:placetype":"venue"
},
  "geometry": {"coordinates":[-2.0141789913,53.9458885193],"type":"Point"}
}