{
  "type": "Feature",
  "properties": {
    "iso:country":"GB",
    "sg:address":"St Aidans Road",
    "sg:city":"Carlisle",
    "sg:classifiers":[
        {
            "category":"Shopping",
            "subcategory":"Department Store",
            "type":"Retail Goods"
        },
        {
            "category":"Sports & Exercise",
            "subcategory":"Golf",
            "type":"Entertainment"
        }
    ],
    "sg:postcode":"CA1 1LS",
    "sg:province":"Cumbria",
    "sg:tags":[
        "equipment"
    ],
    "wof:name":"Stoneyholme Golf Shop",
    "wof:placetype":"venue"
},
  "geometry": {"coordinates":[-2.918774,54.89677],"type":"Point"}
}