{
  "type": "Feature",
  "properties": {
    "addr:full":"Mowbray Terrace Choppington Northumberland NE62 5QH",
    "addr:postcode":"ne62 5qh",
    "addr:street":"Mowbray Terrace;Northumberland",
    "iso:country":"GB",
    "sg:address":"Mowbray Terrace",
    "sg:city":"Choppington",
    "sg:classifiers":[
        {
            "category":"Retail",
            "subcategory":"Auto Repair",
            "type":"Services"
        }
    ],
    "sg:phone":"+44 1670 531571",
    "sg:postcode":"NE62 5QH",
    "sg:province":"Northumberland",
    "sg:tags":[
        "modification",
        "garage"
    ],
    "wof:name":"Tonys Auto Services",
    "wof:placetype":"venue"
},
  "geometry": {"coordinates":[-1.6000850201,55.1461753845],"type":"Point"}
}