{
  "type": "Feature",
  "properties": {
    "iso:country":"GB",
    "sg:address":"5 West View",
    "sg:city":"Mold",
    "sg:classifiers":[
        {
            "category":"Arts & Performance",
            "subcategory":"Music",
            "type":"Entertainment"
        }
    ],
    "sg:phone":"+44 1352 756073",
    "sg:postcode":"CH7 1DW",
    "sg:province":"Denbighshire",
    "sg:tags":[
        "mobile",
        "disco"
    ],
    "wof:name":"Hip Hop Disco",
    "wof:placetype":"venue"
},
  "geometry": {"coordinates":[-3.145042,53.167206],"type":"Point"}
}