{
  "type": "Feature",
  "properties": {
    "addr:full":"Unit 9 Shuttleworth Court, Shuttleworth Road, Elm Farm Industrial Estate Bedford Bedfordshire MK41 0EN",
    "addr:housenumber":"unit 9;estate",
    "addr:postcode":"mk41 0en",
    "addr:street":"Shuttleworth Court Shuttleworth Road Elm;Bedfordshire",
    "iso:country":"GB",
    "sg:address":"Unit 9 Shuttleworth Court, Shuttleworth Road, Elm Farm Industrial Estate",
    "sg:city":"Bedford",
    "sg:classifiers":[
        {
            "category":"Professional",
            "subcategory":"Engineering",
            "type":"Services"
        }
    ],
    "sg:phone":"+44 1234 273534",
    "sg:postcode":"MK41 0EN",
    "sg:province":"Bedfordshire",
    "wof:name":"Team Engineering (U K) Ltd.",
    "wof:placetype":"venue"
},
  "geometry": {"coordinates":[-0.422982,52.14632],"type":"Point"}
}