{
  "type": "Feature",
  "properties": {
    "addr:full":"610 Kings Road London Greater London SW6 2DX",
    "addr:housenumber":"610",
    "addr:postcode":"sw6 2dx",
    "addr:street":"Kings Road",
    "iso:country":"GB",
    "sg:address":"610 Kings Road",
    "sg:city":"London",
    "sg:classifiers":[
        {
            "category":"Shopping",
            "subcategory":"Antiques",
            "type":"Retail Goods"
        }
    ],
    "sg:phone":"+44 20 7731 7041",
    "sg:postcode":"SW6 2DX",
    "sg:province":"Greater London",
    "wof:name":"Rupert Cavendish",
    "wof:placetype":"venue"
},
  "geometry": {"coordinates":[-0.188686,51.478741],"type":"Point"}
}