{
  "type": "Feature",
  "properties": {
    "iso:country":"GB",
    "sg:address":"Northdown Road",
    "sg:city":"Margate",
    "sg:classifiers":[
        {
            "category":"Landmark",
            "subcategory":"Tourist Attraction",
            "type":"Public Place"
        }
    ],
    "sg:phone":"+44 1843 220139",
    "sg:postcode":"CT9 1QQ",
    "sg:province":"Kent",
    "sg:tags":[
        "interest"
    ],
    "wof:name":"Margate Caves",
    "wof:placetype":"venue"
},
  "geometry": {"coordinates":[1.38683,51.389938],"type":"Point"}
}