{
  "type": "Feature",
  "properties": {
    "iso:country":"GB",
    "sg:address":"Unit 1, Challenge Way, Hythe Hill",
    "sg:city":"Colchester",
    "sg:classifiers":[
        {
            "category":"Building & Trades",
            "subcategory":"Cleaning & Sanitation",
            "type":"Services"
        }
    ],
    "sg:phone":"+44 1206 795361",
    "sg:postcode":"CO1 2LY",
    "sg:province":"Essex",
    "sg:tags":[
        "boiler"
    ],
    "wof:name":"Ellis Tylin",
    "wof:placetype":"venue"
},
  "geometry": {"coordinates":[0.918525,51.88509],"type":"Point"}
}