{
  "type": "Feature",
  "properties": {
    "addr:full":"Queens Rd Oldham Lancashire OL9 9HU",
    "addr:postcode":"ol9 9hu",
    "addr:street":"Queens Rd",
    "iso:country":"GB",
    "sg:address":"Queens Rd",
    "sg:city":"Oldham",
    "sg:classifiers":[
        {
            "category":"Place Of Worship",
            "type":"Public Place"
        }
    ],
    "sg:phone":"+44 161 624 3562",
    "sg:postcode":"OL9 9HU",
    "sg:province":"Lancashire",
    "wof:name":"St Luke C of E Church",
    "wof:placetype":"venue"
},
  "geometry": {"coordinates":[-2.146834,53.542465],"type":"Point"}
}