{
  "type": "Feature",
  "properties": {
    "iso:country":"GB",
    "sg:address":"Evesham Road, Salford Priors",
    "sg:city":"Evesham",
    "sg:classifiers":[
        {
            "category":"Bars & Pubs",
            "type":"Food & Drink"
        }
    ],
    "sg:postcode":"WR11 8UU",
    "sg:province":"Gloucestershire",
    "sg:tags":[
        "pubs",
        "inn"
    ],
    "wof:name":"The Bell Inn",
    "wof:placetype":"venue"
},
  "geometry": {"coordinates":[-1.8893239498,52.1581192017],"type":"Point"}
}