{
  "type": "Feature",
  "properties": {
    "addr:full":"Hospital Farm, Burghill Hereford Herefordshire HR4 7RD",
    "addr:housenumber":"burghill",
    "addr:postcode":"hr4 7rd",
    "iso:country":"GB",
    "sg:address":"Hospital Farm, Burghill",
    "sg:city":"Hereford",
    "sg:classifiers":[
        {
            "category":"Farming",
            "subcategory":"Dairy Farm",
            "type":"Manufacturing & Wholesale Goods"
        },
        {
            "category":"Farming",
            "subcategory":"Farm",
            "type":"Manufacturing & Wholesale Goods"
        }
    ],
    "sg:postcode":"HR4 7RD",
    "sg:province":"Herefordshire",
    "sg:tags":[
        "mixed",
        "crop"
    ],
    "wof:name":"L G & S D Langford",
    "wof:placetype":"venue"
},
  "geometry": {"coordinates":[-2.7593309879,52.0964546204],"type":"Point"}
}