{
  "type": "Feature",
  "properties": {
    "iso:country":"GB",
    "sg:address":"117 St Peters Street",
    "sg:city":"St Albans",
    "sg:classifiers":[
        {
            "category":"Personal",
            "subcategory":"Beauty Salon",
            "type":"Services"
        },
        {
            "category":"Personal",
            "subcategory":"Barber",
            "type":"Services"
        }
    ],
    "sg:phone":"+44 1727 840393",
    "sg:postcode":"AL1 3ET",
    "sg:province":"Hertfordshire",
    "sg:tags":[
        "unisex",
        "hairdresser"
    ],
    "wof:name":"Hairscene",
    "wof:placetype":"venue"
},
  "geometry": {"coordinates":[-0.335137,51.756336],"type":"Point"}
}