{
  "type": "Feature",
  "properties": {
    "addr:full":"Day's Mill, Old Market, Nailsworth Stroud Gloucestershire GL6 0DU",
    "addr:postcode":"gl6 0du",
    "addr:street":"Day'S;Nailsworth",
    "iso:country":"GB",
    "sg:address":"Day's Mill, Old Market, Nailsworth",
    "sg:city":"Stroud",
    "sg:classifiers":[
        {
            "category":"Wholesale",
            "subcategory":"Machinery & Supplies",
            "type":"Manufacturing & Wholesale Goods"
        }
    ],
    "sg:phone":"+44 1453 833817",
    "sg:postcode":"GL6 0DU",
    "sg:province":"Gloucestershire",
    "sg:tags":[
        "theatrical"
    ],
    "wof:name":"Cotswold Costumes",
    "wof:placetype":"venue"
},
  "geometry": {"coordinates":[-2.2189,51.695381],"type":"Point"}
}