{
  "type": "Feature",
  "properties": {
    "iso:country":"GB",
    "sg:address":"Unit 8, Lealand Way",
    "sg:city":"Boston",
    "sg:classifiers":[
        {
            "category":"Home & Garden",
            "subcategory":"Home Furnishings",
            "type":"Retail Goods"
        }
    ],
    "sg:phone":"+44 1205 357963",
    "sg:postcode":"PE21 7SW",
    "sg:province":"Lincolnshire",
    "sg:tags":[
        "homefurnishings"
    ],
    "wof:name":"The Wood Shed",
    "wof:placetype":"venue"
},
  "geometry": {"coordinates":[-0.011703,52.965557],"type":"Point"}
}