{
  "type": "Feature",
  "properties": {
    "addr:full":"Ringmead Bracknell Berkshire RG12 8FS",
    "addr:postcode":"rg12 8fs",
    "addr:street":"Ringmead",
    "iso:country":"GB",
    "sg:address":"Ringmead",
    "sg:city":"Bracknell",
    "sg:classifiers":[
        {
            "category":"Education",
            "subcategory":"Music School",
            "type":"Public Place"
        }
    ],
    "sg:phone":"+44 1344 669712",
    "sg:postcode":"RG12 8FS",
    "sg:province":"Berkshire",
    "wof:name":"Stage Coach Bracknell",
    "wof:placetype":"venue"
},
  "geometry": {"coordinates":[-0.772084,51.403847],"type":"Point"}
}