{
  "type": "Feature",
  "properties": {
    "addr:full":"Queens Bank Postland, Crowland Peterborough Cambridgeshire PE6 0JR",
    "addr:postcode":"pe6 0jr",
    "addr:street":"Postland Crowland",
    "iso:country":"GB",
    "sg:address":"Queens Bank Postland, Crowland",
    "sg:city":"Peterborough",
    "sg:classifiers":[
        {
            "category":"Farming",
            "subcategory":"Livestock Farm",
            "type":"Manufacturing & Wholesale Goods"
        }
    ],
    "sg:postcode":"PE6 0JR",
    "sg:province":"Cambridgeshire",
    "sg:tags":[
        "others"
    ],
    "wof:name":"Drury Farms",
    "wof:placetype":"venue"
},
  "geometry": {"coordinates":[-0.1328790039,52.7170333862],"type":"Point"}
}