{
  "type": "Feature",
  "properties": {
    "addr:full":"Column Yard, Cambo Morpeth Northumberland NE61 4AY",
    "addr:postcode":"ne61 4ay",
    "addr:street":"Cambo",
    "iso:country":"GB",
    "sg:address":"Column Yard, Cambo",
    "sg:city":"Morpeth",
    "sg:classifiers":[
        {
            "category":"Real Estate",
            "subcategory":"Architect",
            "type":"Services"
        }
    ],
    "sg:phone":"+44 1670 774448",
    "sg:postcode":"NE61 4AY",
    "sg:province":"Northumberland",
    "wof:name":"Spence & Dower",
    "wof:placetype":"venue"
},
  "geometry": {"coordinates":[-1.961701,55.165302],"type":"Point"}
}