{
  "type": "Feature",
  "properties": {
    "addr:full":"29 Church Rd Bolton Lancashire BL1 6HE",
    "addr:housenumber":"29",
    "addr:postcode":"bl1 6he",
    "addr:street":"Church Rd",
    "iso:country":"GB",
    "sg:address":"29 Church Rd",
    "sg:city":"Bolton",
    "sg:classifiers":[
        {
            "category":"Retail",
            "subcategory":"Laundry & Dry Cleaning",
            "type":"Services"
        }
    ],
    "sg:phone":"+44 1204 848320",
    "sg:postcode":"BL1 6HE",
    "sg:province":"Lancashire",
    "sg:tags":[
        "alteration"
    ],
    "wof:name":"Press On",
    "wof:placetype":"venue"
},
  "geometry": {"coordinates":[-2.452986002,53.591999054],"type":"Point"}
}