{
  "type": "Feature",
  "properties": {
    "iso:country":"GB",
    "sg:address":"Unit 2 Berkeley House, 51 High Street",
    "sg:city":"Redhill",
    "sg:classifiers":[
        {
            "category":"Professional",
            "subcategory":"Art Services",
            "type":"Services"
        }
    ],
    "sg:postcode":"RH1 1RX",
    "sg:province":"Surrey",
    "sg:tags":[
        "framing"
    ],
    "wof:name":"Redhill Frame Shop",
    "wof:placetype":"venue"
},
  "geometry": {"coordinates":[-0.1689009964,51.238243103],"type":"Point"}
}