{
  "type": "Feature",
  "properties": {
    "iso:country":"GB",
    "sg:address":"32 Dryden Close, Hainault",
    "sg:city":"Ilford",
    "sg:classifiers":[
        {
            "category":"Home & Garden",
            "subcategory":"Household Appliances",
            "type":"Retail Goods"
        }
    ],
    "sg:postcode":"IG6 3EA",
    "sg:province":"Essex",
    "sg:tags":[
        "electrical"
    ],
    "wof:name":"P R C Domestic",
    "wof:placetype":"venue"
},
  "geometry": {"coordinates":[0.1060630009,51.6055450439],"type":"Point"}
}