{
  "type": "Feature",
  "properties": {
    "addr:full":"Unit 1, Haywood Estate, Pottery Road Newton Abbot Devon TQ12 3BN",
    "addr:housenumber":"unit 1;estate",
    "addr:postcode":"tq12 3bn",
    "addr:street":"Pottery Road",
    "iso:country":"GB",
    "sg:address":"Unit 1, Haywood Estate, Pottery Road",
    "sg:city":"Newton Abbot",
    "sg:classifiers":[
        {
            "category":"Retail",
            "subcategory":"Auto Repair",
            "type":"Services"
        }
    ],
    "sg:phone":"+44 1626 356403",
    "sg:postcode":"TQ12 3BN",
    "sg:province":"Devon",
    "sg:tags":[
        "modification",
        "garage"
    ],
    "wof:name":"Exeter Road Garage",
    "wof:placetype":"venue"
},
  "geometry": {"coordinates":[-3.607659,50.52887],"type":"Point"}
}