{
  "type": "Feature",
  "properties": {
    "addr:full":"Market Hall, Market Pl Burton On Trent Derbyshire DE14 1HE",
    "addr:postcode":"de14 1he",
    "addr:street":"Market Pl",
    "iso:country":"GB",
    "sg:address":"Market Hall, Market Pl",
    "sg:city":"Burton On Trent",
    "sg:classifiers":[
        {
            "category":"Shopping",
            "subcategory":"Gifts & Souvenirs",
            "type":"Retail Goods"
        }
    ],
    "sg:phone":"+44 1283 542428",
    "sg:postcode":"DE14 1HE",
    "sg:province":"Derbyshire",
    "sg:tags":[
        "poster",
        "card"
    ],
    "wof:name":"Paul Banbury",
    "wof:placetype":"venue"
},
  "geometry": {"coordinates":[-1.62971,52.801182],"type":"Point"}
}