{
  "type": "Feature",
  "properties": {
    "addr:full":"36 Bradford Street Walsall West Midlands WS1 3QA",
    "addr:housenumber":"36",
    "addr:postcode":"ws1 3qa",
    "addr:street":"Bradford Street",
    "iso:country":"GB",
    "sg:address":"36 Bradford Street",
    "sg:city":"Walsall",
    "sg:classifiers":[
        {
            "category":"Professional",
            "subcategory":"Lawyer & Legal Services",
            "type":"Services"
        }
    ],
    "sg:phone":"+44 1922 642018",
    "sg:postcode":"WS1 3QA",
    "sg:province":"West Midlands",
    "sg:tags":[
        "solicitor"
    ],
    "wof:name":"Mander & Henery",
    "wof:placetype":"venue"
},
  "geometry": {"coordinates":[-1.9842499495,52.5815887451],"type":"Point"}
}