{
  "type": "Feature",
  "properties": {
    "addr:full":"21 Montague St Worthing West Sussex BN11 3BE",
    "addr:housenumber":"21",
    "addr:postcode":"bn11 3be",
    "addr:street":"Montague St",
    "iso:country":"GB",
    "sg:address":"21 Montague St",
    "sg:city":"Worthing",
    "sg:classifiers":[
        {
            "category":"Shopping",
            "subcategory":"Clothing, Apparel, & Fashions",
            "type":"Retail Goods"
        }
    ],
    "sg:phone":"+44 1903 232803",
    "sg:postcode":"BN11 3BE",
    "sg:province":"West Sussex",
    "sg:tags":[
        "shop"
    ],
    "wof:name":"Top Shop",
    "wof:placetype":"venue"
},
  "geometry": {"coordinates":[-0.370456,50.810207],"type":"Point"}
}