{
  "type": "Feature",
  "properties": {
    "iso:country":"GB",
    "sg:address":"Unit 3, Egremont Close, Whitefield",
    "sg:city":"Manchester",
    "sg:classifiers":[
        {
            "category":"Manufacturing",
            "subcategory":"Wood Products",
            "type":"Manufacturing & Wholesale Goods"
        }
    ],
    "sg:phone":"+44 161 796 7379",
    "sg:postcode":"M45 8GU",
    "sg:province":"Lancashire",
    "sg:tags":[
        "packaging",
        "crate",
        "pallets"
    ],
    "wof:name":"Flowline Packaging Ltd.",
    "wof:placetype":"venue"
},
  "geometry": {"coordinates":[-2.2870891094,53.5530204773],"type":"Point"}
}