{
  "type": "Feature",
  "properties": {
    "iso:country":"GB",
    "sg:address":"15 Sherwood Street",
    "sg:city":"Mansfield",
    "sg:classifiers":[
        {
            "category":"Manufacturing",
            "subcategory":"Tools & Machinery",
            "type":"Manufacturing & Wholesale Goods"
        }
    ],
    "sg:phone":"+44 1623 429300",
    "sg:postcode":"NG18 1ER",
    "sg:province":"Nottinghamshire",
    "sg:tags":[
        "society",
        "friendly"
    ],
    "wof:name":"N F U Mutual Insurance Society",
    "wof:placetype":"venue"
},
  "geometry": {"coordinates":[-1.196709,53.139961],"type":"Point"}
}