{
  "type": "Feature",
  "properties": {
    "addr:full":"10 Bouverie St, Rutherglen Glasgow Glasgow City G73 2RX",
    "addr:housenumber":"10",
    "addr:postcode":"g73 2rx",
    "addr:street":"Bouverie St",
    "iso:country":"GB",
    "sg:address":"10 Bouverie St, Rutherglen",
    "sg:city":"Glasgow",
    "sg:classifiers":[
        {
            "category":"Professional",
            "type":"Services"
        }
    ],
    "sg:postcode":"G73 2RX",
    "sg:province":"Glasgow City",
    "sg:tags":[
        "interior",
        "furnishers",
        "designer"
    ],
    "wof:name":"Faram Ltd",
    "wof:placetype":"venue"
},
  "geometry": {"coordinates":[-4.221086,55.826359],"type":"Point"}
}