{
  "type": "Feature",
  "properties": {
    "iso:country":"GB",
    "sg:address":"Priorsleigh, Llangrove",
    "sg:city":"Ross-on-wye",
    "sg:classifiers":[
        {
            "category":"Professional",
            "subcategory":"Accounting & Tax Preparation",
            "type":"Services"
        }
    ],
    "sg:phone":"+44 1989 770496",
    "sg:postcode":"HR9 6EY",
    "sg:province":"Gloucestershire",
    "sg:tags":[
        "accountant"
    ],
    "wof:name":"D I & S R Thomas",
    "wof:placetype":"venue"
},
  "geometry": {"coordinates":[-2.689359,51.869781],"type":"Point"}
}