{
  "type": "Feature",
  "properties": {
    "addr:full":"1 Victoria Road Malvern Herefordshire WR14 2TD",
    "addr:housenumber":"1",
    "addr:postcode":"wr14 2td",
    "addr:street":"Victoria Road",
    "iso:country":"GB",
    "sg:address":"1 Victoria Road",
    "sg:city":"Malvern",
    "sg:classifiers":[
        {
            "category":"Manufacturing",
            "subcategory":"Jewelry",
            "type":"Manufacturing & Wholesale Goods"
        },
        {
            "category":"Building & Trades",
            "subcategory":"Construction",
            "type":"Services"
        }
    ],
    "sg:phone":"+44 1684 893883",
    "sg:postcode":"WR14 2TD",
    "sg:province":"Herefordshire",
    "sg:tags":[
        "joinery",
        "jewellery",
        "repair"
    ],
    "wof:name":"Homerose Joinery Products Ltd.",
    "wof:placetype":"venue"
},
  "geometry": {"coordinates":[-2.3247220516,52.1122055054],"type":"Point"}
}