{
  "type": "Feature",
  "properties": {
    "addr:full":"3 Fleet Place London Greater London EC4M 7RD",
    "addr:housenumber":"3",
    "addr:postcode":"ec4m 7rd",
    "addr:street":"Fleet Place",
    "iso:country":"GB",
    "sg:address":"3 Fleet Place",
    "sg:city":"London",
    "sg:classifiers":[
        {
            "category":"Bars & Pubs",
            "subcategory":"Wine Bar",
            "type":"Food & Drink"
        }
    ],
    "sg:phone":"+44 20 7329 3141",
    "sg:postcode":"EC4M 7RD",
    "sg:province":"Greater London",
    "wof:name":"Corney & Barrow",
    "wof:placetype":"venue"
},
  "geometry": {"coordinates":[-0.10348,51.516113],"type":"Point"}
}