{
  "type": "Feature",
  "properties": {
    "addr:full":"Spa Road Bolton Lancashire BL1 4AG",
    "addr:postcode":"bl1 4ag",
    "addr:street":"Spa Road",
    "iso:country":"GB",
    "sg:address":"Spa Road",
    "sg:city":"Bolton",
    "sg:classifiers":[
        {
            "category":"Bars & Pubs",
            "subcategory":"Nightclub",
            "type":"Food & Drink"
        }
    ],
    "sg:phone":"+44 1204 361427",
    "sg:postcode":"BL1 4AG",
    "sg:province":"Lancashire",
    "sg:tags":[
        "club",
        "night"
    ],
    "wof:name":"Hawthorns",
    "wof:placetype":"venue"
},
  "geometry": {"coordinates":[-2.436757,53.578472],"type":"Point"}
}