{
  "type": "Feature",
  "properties": {
    "addr:full":"35 Hamilton Rd St Albans Hertfordshire AL1 4PZ",
    "addr:housenumber":"35",
    "addr:postcode":"al1 4pz",
    "addr:street":"Hamilton Rd",
    "iso:country":"GB",
    "sg:address":"35 Hamilton Rd",
    "sg:city":"St Albans",
    "sg:classifiers":[
        {
            "category":"Professional",
            "subcategory":"Art Services",
            "type":"Services"
        }
    ],
    "sg:postcode":"AL1 4PZ",
    "sg:province":"Hertfordshire",
    "sg:tags":[
        "consultant",
        "design"
    ],
    "wof:name":"Orchard Mead Ltd",
    "wof:placetype":"venue"
},
  "geometry": {"coordinates":[-0.313714,51.756279],"type":"Point"}
}