{
  "type": "Feature",
  "properties": {
    "addr:full":"16 Queen Square Bristol City of Bristol BS1 4NT",
    "addr:housenumber":"16",
    "addr:postcode":"bs1 4nt",
    "addr:street":"Queen Square",
    "iso:country":"GB",
    "sg:address":"16 Queen Square",
    "sg:city":"Bristol",
    "sg:classifiers":[
        {
            "category":"Building & Trades",
            "subcategory":"Construction",
            "type":"Services"
        }
    ],
    "sg:phone":"+44 117 927 6844",
    "sg:postcode":"BS1 4NT",
    "sg:province":"City of Bristol",
    "sg:tags":[
        "builder"
    ],
    "wof:name":"J Jarvis & Son",
    "wof:placetype":"venue"
},
  "geometry": {"coordinates":[-2.593412,51.450516],"type":"Point"}
}