{
  "type": "Feature",
  "properties": {
    "addr:full":"52 Grantham Close, Plympton Plymouth Devon PL7 3UL",
    "addr:housenumber":"52",
    "addr:postcode":"pl7 3ul",
    "addr:street":"Grantham Close",
    "iso:country":"GB",
    "sg:address":"52 Grantham Close, Plympton",
    "sg:city":"Plymouth",
    "sg:classifiers":[
        {
            "category":"Retail",
            "subcategory":"Repair Shop",
            "type":"Services"
        },
        {
            "category":"Building & Trades",
            "subcategory":"Construction",
            "type":"Services"
        }
    ],
    "sg:phone":"+44 1752 345639",
    "sg:postcode":"PL7 3UL",
    "sg:province":"Devon",
    "sg:tags":[
        "builder",
        "maintenance"
    ],
    "wof:name":"F J White Developments",
    "wof:placetype":"venue"
},
  "geometry": {"coordinates":[-4.05039,50.387829],"type":"Point"}
}