{
  "type": "Feature",
  "properties": {
    "addr:full":"Union Road Oldbury West Midlands B69 3EX",
    "addr:postcode":"b69 3ex",
    "addr:street":"Union Road",
    "iso:country":"GB",
    "sg:address":"Union Road",
    "sg:city":"Oldbury",
    "sg:classifiers":[
        {
            "category":"Professional",
            "subcategory":"Engineering",
            "type":"Services"
        }
    ],
    "sg:phone":"+44 121 552 9988",
    "sg:postcode":"B69 3EX",
    "sg:province":"West Midlands",
    "wof:name":"Birmingham Hydraulic Services Ltd.",
    "wof:placetype":"venue"
},
  "geometry": {"coordinates":[-2.025362,52.513588],"type":"Point"}
}