{
  "type": "Feature",
  "properties": {
    "addr:full":"Cavendish House, Waterloo Street Birmingham West Midlands B2 5PP",
    "addr:postcode":"b2 5pp",
    "addr:street":"Waterloo Street",
    "iso:country":"GB",
    "sg:address":"Cavendish House, Waterloo Street",
    "sg:city":"Birmingham",
    "sg:classifiers":[
        {
            "category":"Professional",
            "subcategory":"Employment Agencies",
            "type":"Services"
        }
    ],
    "sg:phone":"+44 121 236 1200",
    "sg:postcode":"B2 5PP",
    "sg:province":"West Midlands",
    "sg:tags":[
        "consultant"
    ],
    "wof:name":"Ann Mills Taxation Recruitment",
    "wof:placetype":"venue"
},
  "geometry": {"coordinates":[-1.899891,52.480415],"type":"Point"}
}