{
  "type": "Feature",
  "properties": {
    "addr:full":"23 Wyndham Pk, Orton Wistow Peterborough Cambridgeshire PE2 6YD",
    "addr:housenumber":"23",
    "addr:postcode":"pe2 6yd",
    "addr:street":"Wyndham Pk",
    "iso:country":"GB",
    "sg:address":"23 Wyndham Pk, Orton Wistow",
    "sg:city":"Peterborough",
    "sg:classifiers":[
        {
            "category":"Building & Trades",
            "subcategory":"Construction",
            "type":"Services"
        }
    ],
    "sg:postcode":"PE2 6YD",
    "sg:province":"Cambridgeshire",
    "sg:tags":[
        "builder"
    ],
    "wof:name":"Ellington,Phillip,",
    "wof:placetype":"venue"
},
  "geometry": {"coordinates":[-0.3097299933,52.5585212708],"type":"Point"}
}