{
  "type": "Feature",
  "properties": {
    "addr:full":"5 Goodwin Dr Bristol City of Bristol BS14 0DR",
    "addr:housenumber":"5",
    "addr:postcode":"bs14 0dr",
    "addr:street":"Goodwin Dr",
    "iso:country":"GB",
    "sg:address":"5 Goodwin Dr",
    "sg:city":"Bristol",
    "sg:classifiers":[
        {
            "category":"Sports & Exercise",
            "subcategory":"Tennis Court",
            "type":"Entertainment"
        }
    ],
    "sg:phone":"+44 1275 541172",
    "sg:postcode":"BS14 0DR",
    "sg:province":"City of Bristol",
    "sg:tags":[
        "breakdown",
        "recovery"
    ],
    "wof:name":"New Station Recovery Services",
    "wof:placetype":"venue"
},
  "geometry": {"coordinates":[-2.5816459656,51.4061775208],"type":"Point"}
}