{
  "type": "Feature",
  "properties": {
    "addr:full":"Unit 3b Holywells Rd Ipswich Suffolk IP3 0DL",
    "addr:housenumber":"unit 3b",
    "addr:postcode":"ip3 0dl",
    "addr:street":"Holywells Rd",
    "iso:country":"GB",
    "sg:address":"Unit 3b Holywells Rd",
    "sg:city":"Ipswich",
    "sg:classifiers":[
        {
            "category":"Autos & Motor Vehicles",
            "subcategory":"Auto Supplies",
            "type":"Retail Goods"
        }
    ],
    "sg:phone":"+44 1473 211433",
    "sg:postcode":"IP3 0DL",
    "sg:province":"Suffolk",
    "sg:tags":[
        "tyre"
    ],
    "wof:name":"Supertread Tyres",
    "wof:placetype":"venue"
},
  "geometry": {"coordinates":[1.166569,52.046951],"type":"Point"}
}