{
  "type": "Feature",
  "properties": {
    "iso:country":"GB",
    "sg:address":"566 Kingsbury Road, Kingsbury",
    "sg:city":"London",
    "sg:classifiers":[
        {
            "category":"Real Estate",
            "subcategory":"Real Estate Agent",
            "type":"Services"
        }
    ],
    "sg:postcode":"NW9 9HJ",
    "sg:province":"Greater London",
    "wof:name":"Direct Estates",
    "wof:placetype":"venue"
},
  "geometry": {"coordinates":[-0.277785,51.585529],"type":"Point"}
}