{
  "type": "Feature",
  "properties": {
    "iso:country":"GB",
    "sg:address":"70 Aberafan Centre Mkt, Aberafan Centre",
    "sg:city":"Port Talbot",
    "sg:classifiers":[
        {
            "category":"Building & Trades",
            "subcategory":"Construction",
            "type":"Services"
        }
    ],
    "sg:postcode":"SA13 1PB",
    "sg:province":"Neath Port Talbot",
    "sg:tags":[
        "glazier"
    ],
    "wof:name":"Beautiful Decorating",
    "wof:placetype":"venue"
},
  "geometry": {"coordinates":[-3.78549,51.59676],"type":"Point"}
}