{
  "type": "Feature",
  "properties": {
    "addr:full":"14 Stoats Nest Village Coulsdon Surrey CR5 2JL",
    "addr:housenumber":"14",
    "addr:postcode":"cr5 2jl",
    "addr:street":"Stoats Nest Village",
    "iso:country":"GB",
    "sg:address":"14 Stoats Nest Village",
    "sg:city":"Coulsdon",
    "sg:classifiers":[
        {
            "category":"Building & Trades",
            "subcategory":"Construction",
            "type":"Services"
        }
    ],
    "sg:postcode":"CR5 2JL",
    "sg:province":"Surrey",
    "sg:tags":[
        "roofing"
    ],
    "wof:name":"Williams Electrical Ltd",
    "wof:placetype":"venue"
},
  "geometry": {"coordinates":[-0.129588,51.323376],"type":"Point"}
}