{
  "type": "Feature",
  "properties": {
    "iso:country":"GB",
    "sg:address":"Unit 1 Hayes Yard",
    "sg:city":"Bridgend",
    "sg:classifiers":[
        {
            "category":"Retail",
            "subcategory":"Auto Repair",
            "type":"Services"
        }
    ],
    "sg:postcode":"CF31 1NB",
    "sg:province":"Bridgend",
    "sg:tags":[
        "modification",
        "garage"
    ],
    "wof:name":"J Spray",
    "wof:placetype":"venue"
},
  "geometry": {"coordinates":[-3.579102,51.514584],"type":"Point"}
}