{
  "type": "Feature",
  "properties": {
    "addr:full":"Landchard House, Victoria Street West Bromwich West Midlands B70 8ER",
    "addr:postcode":"b70 8er",
    "addr:street":"Victoria Street",
    "iso:country":"GB",
    "sg:address":"Landchard House, Victoria Street",
    "sg:city":"West Bromwich",
    "sg:classifiers":[
        {
            "category":"Manufacturing",
            "subcategory":"Wood Products",
            "type":"Manufacturing & Wholesale Goods"
        }
    ],
    "sg:phone":"+44 121 525 8980",
    "sg:postcode":"B70 8ER",
    "sg:province":"West Midlands",
    "wof:name":"Partsmaster International",
    "wof:placetype":"venue"
},
  "geometry": {"coordinates":[-1.9964540005,52.5190238953],"type":"Point"}
}