{
  "type": "Feature",
  "properties": {
    "addr:full":"3 Strickland St Hull East Riding of Yorkshire HU3 4AD",
    "addr:housenumber":"3",
    "addr:postcode":"hu3 4ad",
    "addr:street":"Strickland St",
    "iso:country":"GB",
    "sg:address":"3 Strickland St",
    "sg:city":"Hull",
    "sg:classifiers":[
        {
            "category":"Autos & Motor Vehicles",
            "subcategory":"Auto Supplies",
            "type":"Retail Goods"
        }
    ],
    "sg:phone":"+44 1482 589666",
    "sg:postcode":"HU3 4AD",
    "sg:province":"East Riding of Yorkshire",
    "sg:tags":[
        "tyre"
    ],
    "wof:name":"Kut Kost Auto Car Center",
    "wof:placetype":"venue"
},
  "geometry": {"coordinates":[-0.358887,53.736122],"type":"Point"}
}