{
  "type": "Feature",
  "properties": {
    "addr:full":"Lloyds Court, 694 North Row Milton Keynes Buckinghamshire MK9 3AP",
    "addr:housenumber":"694",
    "addr:postcode":"mk9 3ap",
    "addr:street":"Lloyds;North Row",
    "iso:country":"GB",
    "sg:address":"Lloyds Court, 694 North Row",
    "sg:city":"Milton Keynes",
    "sg:classifiers":[
        {
            "category":"Travel",
            "subcategory":"Travel Agent",
            "type":"Entertainment"
        }
    ],
    "sg:phone":"+44 1908 207122",
    "sg:postcode":"MK9 3AP",
    "sg:province":"Buckinghamshire",
    "wof:name":"American Express Corporate Travel",
    "wof:placetype":"venue"
},
  "geometry": {"coordinates":[-0.757972,52.045815],"type":"Point"}
}