{
  "type": "Feature",
  "properties": {
    "iso:country":"GB",
    "sg:address":"30 Castle Street",
    "sg:city":"Clitheroe",
    "sg:classifiers":[
        {
            "category":"Shopping",
            "subcategory":"Department Store",
            "type":"Retail Goods"
        }
    ],
    "sg:phone":"+44 1200 422422",
    "sg:postcode":"BB7 2BX",
    "sg:province":"Lancashire",
    "wof:name":"Carsten Lemmermann",
    "wof:placetype":"venue"
},
  "geometry": {"coordinates":[-2.3914179802,53.8721733093],"type":"Point"}
}