{
  "type": "Feature",
  "properties": {
    "addr:full":"St Marys Lane, Hertingfordbury Hertford Hertfordshire SG14 2LX",
    "addr:postcode":"sg14 2lx",
    "addr:street":"St Marys Lane",
    "iso:country":"GB",
    "sg:address":"St Marys Lane, Hertingfordbury",
    "sg:city":"Hertford",
    "sg:classifiers":[
        {
            "category":"Education",
            "subcategory":"School",
            "type":"Public Place"
        }
    ],
    "sg:phone":"+44 1992 581378",
    "sg:postcode":"SG14 2LX",
    "sg:province":"Hertfordshire",
    "sg:tags":[
        "independent",
        "preparatory"
    ],
    "wof:name":"St.Joseph's in the Park Ltd.",
    "wof:placetype":"venue"
},
  "geometry": {"coordinates":[-0.1053619981,51.7910003662],"type":"Point"}
}