{
  "type": "Feature",
  "properties": {
    "addr:full":"61 Victoria Gro Bridport Dorset DT6 3AE",
    "addr:housenumber":"61",
    "addr:postcode":"dt6 3ae",
    "addr:street":"Victoria Gro",
    "iso:country":"GB",
    "sg:address":"61 Victoria Gro",
    "sg:city":"Bridport",
    "sg:classifiers":[
        {
            "category":"Real Estate",
            "subcategory":"Surveying",
            "type":"Services"
        }
    ],
    "sg:postcode":"DT6 3AE",
    "sg:province":"Dorset",
    "sg:tags":[
        "building",
        "surveyor"
    ],
    "wof:name":"Michael Fearn",
    "wof:placetype":"venue"
},
  "geometry": {"coordinates":[-2.7593109608,50.7359542847],"type":"Point"}
}