{
  "type": "Feature",
  "properties": {
    "addr:full":"8b North Parade Falmouth Cornwall TR11 2TD",
    "addr:housenumber":"8b",
    "addr:postcode":"tr11 2td",
    "addr:street":"North Parade",
    "iso:country":"GB",
    "sg:address":"8b North Parade",
    "sg:city":"Falmouth",
    "sg:classifiers":[
        {
            "category":"Professional",
            "subcategory":"Lawyer & Legal Services",
            "type":"Services"
        }
    ],
    "sg:phone":"+44 1326 313100",
    "sg:postcode":"TR11 2TD",
    "sg:province":"Cornwall",
    "sg:tags":[
        "solicitor"
    ],
    "wof:name":"Malcolm Ashdon",
    "wof:placetype":"venue"
},
  "geometry": {"coordinates":[-5.07728,50.162994],"type":"Point"}
}