{
  "type": "Feature",
  "properties": {
    "iso:country":"GB",
    "sg:address":"36 Bagworth Road, Barlestone",
    "sg:city":"Nuneaton",
    "sg:classifiers":[
        {
            "category":"Building & Trades",
            "subcategory":"Cleaning & Sanitation",
            "type":"Services"
        }
    ],
    "sg:phone":"+44 1455 292006",
    "sg:postcode":"CV13 0EG",
    "sg:province":"Leicestershire",
    "sg:tags":[
        "asbestos",
        "removal"
    ],
    "wof:name":"Phoenix (Leicester) Ltd.",
    "wof:placetype":"venue"
},
  "geometry": {"coordinates":[-1.366637,52.648212],"type":"Point"}
}