{
  "type": "Feature",
  "properties": {
    "addr:full":"22 Lansdown Rd Bude Cornwall EX23 8BH",
    "addr:housenumber":"22",
    "addr:postcode":"ex23 8bh",
    "addr:street":"Lansdown Rd",
    "iso:country":"GB",
    "sg:address":"22 Lansdown Rd",
    "sg:city":"Bude",
    "sg:classifiers":[
        {
            "category":"Food & Beverages",
            "subcategory":"Liquor & Beverages",
            "type":"Retail Goods"
        }
    ],
    "sg:postcode":"EX23 8BH",
    "sg:province":"Cornwall",
    "sg:tags":[
        "beer",
        "spirit",
        "wines"
    ],
    "wof:name":"Fry,Graham,",
    "wof:placetype":"venue"
},
  "geometry": {"coordinates":[-4.543759,50.829773],"type":"Point"}
}