{
  "type": "Feature",
  "properties": {
    "addr:full":"Meadowlea, Shutterton La Dawlish Devon EX7 0PD",
    "addr:postcode":"ex7 0pd",
    "addr:street":"La",
    "iso:country":"GB",
    "sg:address":"Meadowlea, Shutterton La",
    "sg:city":"Dawlish",
    "sg:classifiers":[
        {
            "category":"Manufacturing",
            "subcategory":"Pottery",
            "type":"Manufacturing & Wholesale Goods"
        }
    ],
    "sg:phone":"+44 1626 866165",
    "sg:postcode":"EX7 0PD",
    "sg:province":"Devon",
    "wof:name":"Peter E Barrett",
    "wof:placetype":"venue"
},
  "geometry": {"coordinates":[-3.444837,50.59795],"type":"Point"}
}