{
  "type": "Feature",
  "properties": {
    "iso:country":"GB",
    "sg:address":"Units 8-12 First Avenue, Westfield Industrial Estate",
    "sg:city":"Bath",
    "sg:classifiers":[
        {
            "category":"Professional",
            "subcategory":"Printing & Photocopies",
            "type":"Services"
        }
    ],
    "sg:phone":"+44 1761 416556",
    "sg:postcode":"BA3 4BS",
    "sg:province":"Somerset",
    "sg:tags":[
        "printer"
    ],
    "wof:name":"W F C Printing Solutions",
    "wof:placetype":"venue"
},
  "geometry": {"coordinates":[-2.4682900906,51.2801094055],"type":"Point"}
}