{
  "type": "Feature",
  "properties": {
    "iso:country":"GB",
    "sg:address":"6 Cardinal Close",
    "sg:city":"Nottingham",
    "sg:classifiers":[
        {
            "category":"Health Services",
            "subcategory":"Dentist",
            "type":"Services"
        }
    ],
    "sg:phone":"+44 115 979 9899",
    "sg:postcode":"NG3 3ND",
    "sg:province":"Nottinghamshire",
    "wof:name":"St.Annes Family Dental Centre",
    "wof:placetype":"venue"
},
  "geometry": {"coordinates":[-1.1330510378,52.9631767273],"type":"Point"}
}