{
  "type": "Feature",
  "properties": {
    "addr:full":"1 Laburnum Row Torquay Devon TQ2 5QX",
    "addr:housenumber":"1",
    "addr:postcode":"tq2 5qx",
    "addr:street":"Laburnum Row",
    "iso:country":"GB",
    "sg:address":"1 Laburnum Row",
    "sg:city":"Torquay",
    "sg:classifiers":[
        {
            "category":"Shopping",
            "subcategory":"Antiques",
            "type":"Retail Goods"
        }
    ],
    "sg:postcode":"TQ2 5QX",
    "sg:province":"Devon",
    "wof:name":"Sheraton House Antiques",
    "wof:placetype":"venue"
},
  "geometry": {"coordinates":[-3.538797,50.469692],"type":"Point"}
}