{
  "type": "Feature",
  "properties": {
    "addr:full":"47 Brownfield Gardens Maidenhead Berkshire SL6 2RL",
    "addr:housenumber":"47",
    "addr:postcode":"sl6 2rl",
    "addr:street":"Brownfield Gardens",
    "iso:country":"GB",
    "sg:address":"47 Brownfield Gardens",
    "sg:city":"Maidenhead",
    "sg:classifiers":[
        {
            "category":"Professional",
            "subcategory":"Detective & Security Services",
            "type":"Services"
        }
    ],
    "sg:phone":"+44 1628 789880",
    "sg:postcode":"SL6 2RL",
    "sg:province":"Berkshire",
    "sg:tags":[
        "activity"
    ],
    "wof:name":"J R T Security Services",
    "wof:placetype":"venue"
},
  "geometry": {"coordinates":[-0.7304909825,51.5151367188],"type":"Point"}
}