{
  "type": "Feature",
  "properties": {
    "addr:full":"94 Eastgate Louth Lincolnshire LN11 9AA",
    "addr:housenumber":"94",
    "addr:postcode":"ln11 9aa",
    "addr:street":"Eastgate Louth",
    "iso:country":"GB",
    "sg:address":"94 Eastgate",
    "sg:city":"Louth",
    "sg:classifiers":[
        {
            "category":"Shopping",
            "subcategory":"Clothing, Apparel, & Fashions",
            "type":"Retail Goods"
        },
        {
            "category":"Banks & Credit Unions",
            "subcategory":"Investment Brokerage",
            "type":"Services"
        }
    ],
    "sg:phone":"+44 1507 604233",
    "sg:postcode":"LN11 9AA",
    "sg:province":"Lincolnshire",
    "sg:tags":[
        "agency",
        "dress",
        "dresswear"
    ],
    "wof:name":"Vogue Clothing Agency",
    "wof:placetype":"venue"
},
  "geometry": {"coordinates":[-0.002562,53.367249],"type":"Point"}
}