{
  "type": "Feature",
  "properties": {
    "iso:country":"GB",
    "sg:address":"Glenure Road",
    "sg:city":"London",
    "sg:classifiers":[
        {
            "category":"Education",
            "subcategory":"School",
            "type":"Public Place"
        },
        {
            "category":"Government",
            "subcategory":"Office",
            "type":"Public Place"
        }
    ],
    "sg:phone":"+44 20 8850 7835",
    "sg:postcode":"SE9 1UF",
    "sg:province":"Greater London",
    "sg:tags":[
        "local",
        "authority"
    ],
    "sg:website":"http://www.lgfl.net",
    "wof:name":"St Marys R C Primary School",
    "wof:placetype":"venue"
},
  "geometry": {"coordinates":[0.06525,51.453541],"type":"Point"}
}