{
  "type": "Feature",
  "properties": {
    "addr:full":"7-9 Newport Place London Greater London WC2H 7JR",
    "addr:housenumber":"7-9",
    "addr:postcode":"wc2h 7jr",
    "addr:street":"Newport Place",
    "iso:country":"GB",
    "sg:address":"7-9 Newport Place",
    "sg:city":"London",
    "sg:classifiers":[
        {
            "category":"Shopping",
            "subcategory":"Books",
            "type":"Retail Goods"
        }
    ],
    "sg:phone":"+44 20 7437 3737",
    "sg:postcode":"WC2H 7JR",
    "sg:province":"Greater London",
    "sg:tags":[
        "bookseller"
    ],
    "wof:name":"Guanghwa Co.",
    "wof:placetype":"venue"
},
  "geometry": {"coordinates":[-0.129627,51.511929],"type":"Point"}
}