{
  "type": "Feature",
  "properties": {
    "iso:country":"GB",
    "sg:address":"The Old Bank, 2 Westbourne Gro",
    "sg:city":"Scarborough",
    "sg:classifiers":[
        {
            "category":"Social Services",
            "subcategory":"Retirement Home",
            "type":"Services"
        }
    ],
    "sg:phone":"+44 1723 503325",
    "sg:postcode":"YO11 2DJ",
    "sg:province":"North Yorkshire",
    "sg:tags":[
        "care"
    ],
    "wof:name":"Carewatch (North Yorkshire & East Riding of Yorksh",
    "wof:placetype":"venue"
},
  "geometry": {"coordinates":[-0.4038,54.272732],"type":"Point"}
}