{
  "type": "Feature",
  "properties": {
    "iso:country":"GB",
    "sg:address":"70 Bristol Road",
    "sg:city":"Gloucester",
    "sg:classifiers":[
        {
            "category":"Fast Food",
            "type":"Food & Drink"
        }
    ],
    "sg:phone":"+44 1452 303896",
    "sg:postcode":"GL1 5SD",
    "sg:province":"Gloucestershire",
    "sg:tags":[
        "away",
        "take"
    ],
    "wof:name":"Fhunxin Chinese Take Away",
    "wof:placetype":"venue"
},
  "geometry": {"coordinates":[-2.253091,51.855251],"type":"Point"}
}