{
  "type": "Feature",
  "properties": {
    "addr:full":"Unit 14 A Garth Estate Cardiff Caerphilly CF15 7RN",
    "addr:housenumber":"unit 14 a",
    "addr:postcode":"cf15 7rn",
    "addr:street":"Garth Estate",
    "iso:country":"GB",
    "sg:address":"Unit 14 A Garth Estate",
    "sg:city":"Cardiff",
    "sg:classifiers":[
        {
            "category":"Manufacturing",
            "subcategory":"Metals",
            "type":"Manufacturing & Wholesale Goods"
        }
    ],
    "sg:postcode":"CF15 7RN",
    "sg:province":"Caerphilly",
    "sg:tags":[
        "steel",
        "fabricator",
        "erectors"
    ],
    "wof:name":"T J Scarfe",
    "wof:placetype":"venue"
},
  "geometry": {"coordinates":[-3.26715,51.543541],"type":"Point"}
}