{
  "type": "Feature",
  "properties": {
    "addr:full":"Whiteladies Filling Station, 40a Whiteladies Road Bristol City of Bristol BS8 2NA",
    "addr:housenumber":"40a",
    "addr:postcode":"bs8 2na",
    "addr:street":"Whiteladies Road",
    "iso:country":"GB",
    "sg:address":"Whiteladies Filling Station, 40a Whiteladies Road",
    "sg:city":"Bristol",
    "sg:classifiers":[
        {
            "category":"Autos & Motor Vehicles",
            "subcategory":"Fuel & Gas Station",
            "type":"Retail Goods"
        }
    ],
    "sg:postcode":"BS8 2NA",
    "sg:province":"City of Bristol",
    "sg:tags":[
        "hr",
        "petrol"
    ],
    "wof:name":"B T Filling Stations",
    "wof:placetype":"venue"
},
  "geometry": {"coordinates":[-2.6087100506,51.4616889954],"type":"Point"}
}