{
  "type": "Feature",
  "properties": {
    "addr:full":"32-34 Clarendon Street Leamington Spa Warwickshire CV32 4PG",
    "addr:housenumber":"32-34",
    "addr:postcode":"cv32 4pg",
    "addr:street":"Clarendon Street",
    "iso:country":"GB",
    "sg:address":"32-34 Clarendon Street",
    "sg:city":"Leamington Spa",
    "sg:classifiers":[
        {
            "category":"Professional",
            "subcategory":"Accounting & Tax Preparation",
            "type":"Services"
        }
    ],
    "sg:phone":"+44 1926 330464",
    "sg:postcode":"CV32 4PG",
    "sg:province":"Warwickshire",
    "sg:tags":[
        "accountant"
    ],
    "wof:name":"Daffern & Co. Ltd.",
    "wof:placetype":"venue"
},
  "geometry": {"coordinates":[-1.531696,52.293026],"type":"Point"}
}