{
  "type": "Feature",
  "properties": {
    "addr:full":"24 Birmingham Road Walsall West Midlands WS1 2LZ",
    "addr:housenumber":"24",
    "addr:postcode":"ws1 2lz",
    "addr:street":"Birmingham Road",
    "iso:country":"GB",
    "sg:address":"24 Birmingham Road",
    "sg:city":"Walsall",
    "sg:classifiers":[
        {
            "category":"Manufacturing",
            "subcategory":"Rubber & Plastics",
            "type":"Manufacturing & Wholesale Goods"
        }
    ],
    "sg:phone":"+44 121 526 2962",
    "sg:postcode":"WS1 2LZ",
    "sg:province":"West Midlands",
    "sg:tags":[
        "product"
    ],
    "wof:name":"Malvern Plastics Ltd",
    "wof:placetype":"venue"
},
  "geometry": {"coordinates":[-1.974233,52.579842],"type":"Point"}
}