{
  "type": "Feature",
  "properties": {
    "addr:full":"4 Westbourne Grove Bayswater Greater London W2 5RA",
    "addr:housenumber":"4",
    "addr:postcode":"w2 5ra",
    "addr:street":"Westbourne Grove",
    "iso:country":"GB",
    "sg:address":"4 Westbourne Grove",
    "sg:city":"Bayswater",
    "sg:classifiers":[
        {
            "category":"Real Estate",
            "subcategory":"Real Estate Agent",
            "type":"Services"
        }
    ],
    "sg:phone":"+44 20 7792 2266",
    "sg:postcode":"W2 5RA",
    "sg:province":"Greater London",
    "wof:name":"Euro Fone",
    "wof:placetype":"venue"
},
  "geometry": {"coordinates":[-0.190167,51.515797],"type":"Point"}
}