{
  "type": "Feature",
  "properties": {
    "addr:full":"Unit 1-7 29 Station Rd Birmingham West Midlands B38 8SN",
    "addr:housenumber":"unit;29",
    "addr:postcode":"b38 8sn",
    "addr:street":"Station Rd",
    "iso:country":"GB",
    "sg:address":"Unit 1-7 29 Station Rd",
    "sg:city":"Birmingham",
    "sg:classifiers":[
        {
            "category":"Building & Trades",
            "subcategory":"Construction",
            "type":"Services"
        }
    ],
    "sg:phone":"+44 121 459 4507",
    "sg:postcode":"B38 8SN",
    "sg:province":"West Midlands",
    "sg:tags":[
        "builder"
    ],
    "wof:name":"K M H Plstering & Building Services",
    "wof:placetype":"venue"
},
  "geometry": {"coordinates":[-1.898162961,52.4767608643],"type":"Point"}
}