{
  "type": "Feature",
  "properties": {
    "iso:country":"GB",
    "sg:address":"301 Newcastle Street",
    "sg:city":"Stoke-on-trent",
    "sg:classifiers":[
        {
            "category":"Home & Garden",
            "subcategory":"Hardware",
            "type":"Retail Goods"
        }
    ],
    "sg:phone":"+44 1782 835420",
    "sg:postcode":"ST6 3RE",
    "sg:province":"Staffordshire",
    "wof:name":"James McGarry",
    "wof:placetype":"venue"
},
  "geometry": {"coordinates":[-2.211444,53.044899],"type":"Point"}
}