{
  "type": "Feature",
  "properties": {
    "iso:country":"GB",
    "sg:address":"59 Elder Road",
    "sg:city":"Leeds",
    "sg:classifiers":[
        {
            "category":"Professional",
            "subcategory":"Engineering",
            "type":"Services"
        },
        {
            "category":"Building & Trades",
            "subcategory":"Electrical",
            "type":"Services"
        }
    ],
    "sg:phone":"+44 113 239 4076",
    "sg:postcode":"LS13 4DB",
    "sg:province":"West Yorkshire",
    "sg:tags":[
        "engineer",
        "electrician",
        "contractor"
    ],
    "wof:name":"Steven Lawson",
    "wof:placetype":"venue"
},
  "geometry": {"coordinates":[-1.631231,53.805294],"type":"Point"}
}