{
  "type": "Feature",
  "properties": {
    "addr:full":"Manorhurst, Lewes Rd East Grinstead East Sussex RH19 3SY",
    "addr:postcode":"rh19 3sy",
    "addr:street":"Manorhurst Lewes Rd",
    "iso:country":"GB",
    "sg:address":"Manorhurst, Lewes Rd",
    "sg:city":"East Grinstead",
    "sg:classifiers":[
        {
            "category":"Building & Trades",
            "subcategory":"Pest Control",
            "type":"Services"
        }
    ],
    "sg:phone":"+44 1342 321280",
    "sg:postcode":"RH19 3SY",
    "sg:province":"East Sussex",
    "sg:tags":[
        "vermin"
    ],
    "wof:name":"Technic Services",
    "wof:placetype":"venue"
},
  "geometry": {"coordinates":[-0.007568,51.123981],"type":"Point"}
}