{
  "type": "Feature",
  "properties": {
    "addr:full":"20 Cemetery Rd Barnsley South Yorkshire S73 0PU",
    "addr:housenumber":"20",
    "addr:postcode":"s73 0pu",
    "addr:street":"Cemetery Rd;Yorkshire",
    "iso:country":"GB",
    "sg:address":"20 Cemetery Rd",
    "sg:city":"Barnsley",
    "sg:classifiers":[
        {
            "category":"Shopping",
            "subcategory":"Florist",
            "type":"Retail Goods"
        }
    ],
    "sg:phone":"+44 1226 754084",
    "sg:postcode":"S73 0PU",
    "sg:province":"South Yorkshire",
    "wof:name":"Walker's",
    "wof:placetype":"venue"
},
  "geometry": {"coordinates":[-1.411556,53.508266],"type":"Point"}
}