{
  "type": "Feature",
  "properties": {
    "addr:full":"113 Priory Wellington Devon TA21 9EW",
    "addr:housenumber":"113;wellington",
    "addr:postcode":"ta21 9ew",
    "addr:street":"Priory",
    "iso:country":"GB",
    "sg:address":"113 Priory",
    "sg:city":"Wellington",
    "sg:classifiers":[
        {
            "category":"Shopping",
            "subcategory":"Pets & Pet Supplies",
            "type":"Retail Goods"
        },
        {
            "category":"Shopping",
            "type":"Retail Goods"
        }
    ],
    "sg:postcode":"TA21 9EW",
    "sg:province":"Devon",
    "sg:tags":[
        "merchant",
        "feed",
        "animal"
    ],
    "wof:name":"Wellington Farm Supplies",
    "wof:placetype":"venue"
},
  "geometry": {"coordinates":[-3.2233319283,50.9808731079],"type":"Point"}
}