{
  "type": "Feature",
  "properties": {
    "addr:full":"Bath House, 8 Chapel Place, Rivington Street London Greater London EC2A 3DQ",
    "addr:housenumber":"8",
    "addr:postcode":"ec2a 3dq",
    "addr:street":"Chapel Place Rivington Street",
    "iso:country":"GB",
    "sg:address":"Bath House, 8 Chapel Place, Rivington Street",
    "sg:city":"London",
    "sg:classifiers":[
        {
            "category":"Shopping",
            "subcategory":"Books",
            "type":"Retail Goods"
        }
    ],
    "sg:phone":"+44 20 7739 5701",
    "sg:postcode":"EC2A 3DQ",
    "sg:province":"Greater London",
    "wof:name":"The Brown Reference Group Plc",
    "wof:placetype":"venue"
},
  "geometry": {"coordinates":[-0.08221,51.52631],"type":"Point"}
}