{
  "type": "Feature",
  "properties": {
    "addr:full":"Adept House, 64-66 Holderness Road Hull East Riding of Yorkshire HU9 1EQ",
    "addr:housenumber":"64-66",
    "addr:postcode":"hu9 1eq",
    "addr:street":"Holderness Road",
    "iso:country":"GB",
    "sg:address":"Adept House, 64-66 Holderness Road",
    "sg:city":"Hull",
    "sg:classifiers":[
        {
            "category":"Manufacturing",
            "subcategory":"Wood Products",
            "type":"Manufacturing & Wholesale Goods"
        }
    ],
    "sg:phone":"+44 1482 227400",
    "sg:postcode":"HU9 1EQ",
    "sg:province":"East Riding of Yorkshire",
    "sg:tags":[
        "packaging",
        "crate",
        "pallets"
    ],
    "wof:name":"Tony Britton Packaging Ltd.",
    "wof:placetype":"venue"
},
  "geometry": {"coordinates":[-0.319449,53.750019],"type":"Point"}
}