{
  "type": "Feature",
  "properties": {
    "iso:country":"GB",
    "sg:address":"High Legh Gardens, Ditchfield Lane, High Legh",
    "sg:city":"Knutsford",
    "sg:classifiers":[
        {
            "category":"Building & Trades",
            "subcategory":"Landscaping Services",
            "type":"Services"
        }
    ],
    "sg:phone":"+44 1925 756989",
    "sg:postcode":"WA16 0QW",
    "sg:province":"Cheshire",
    "sg:tags":[
        "pond",
        "aquarium"
    ],
    "wof:name":"High Legh Aquatics",
    "wof:placetype":"venue"
},
  "geometry": {"coordinates":[-2.376240015,53.3042030334],"type":"Point"}
}