{
  "type": "Feature",
  "properties": {
    "addr:full":"10 North Street Wareham Dorset BH20 4AF",
    "addr:housenumber":"10",
    "addr:postcode":"bh20 4af",
    "addr:street":"North Street",
    "iso:country":"GB",
    "sg:address":"10 North Street",
    "sg:city":"Wareham",
    "sg:classifiers":[
        {
            "category":"Real Estate",
            "subcategory":"Real Estate Agent",
            "type":"Services"
        }
    ],
    "sg:phone":"+44 1929 552632",
    "sg:postcode":"BH20 4AF",
    "sg:province":"Dorset",
    "wof:name":"Bullock & Lees Wareham",
    "wof:placetype":"venue"
},
  "geometry": {"coordinates":[-2.1099789143,50.6864738464],"type":"Point"}
}