{
  "type": "Feature",
  "properties": {
    "iso:country":"GB",
    "sg:address":"428b Victoria Rd",
    "sg:city":"Ruislip",
    "sg:classifiers":[
        {
            "category":"Home & Garden",
            "subcategory":"Home Furnishings",
            "type":"Retail Goods"
        }
    ],
    "sg:phone":"+44 20 8842 2382",
    "sg:postcode":"HA4 0EH",
    "sg:province":"Greater London",
    "sg:tags":[
        "beds",
        "bedding",
        "blanket"
    ],
    "wof:name":"Sleep Masters",
    "wof:placetype":"venue"
},
  "geometry": {"coordinates":[-0.399914,51.56028],"type":"Point"}
}