{
  "type": "Feature",
  "properties": {
    "addr:full":"21 Market Pl Wetherby North Yorkshire LS22 6LQ",
    "addr:housenumber":"21",
    "addr:postcode":"ls22 6lq",
    "addr:street":"Market Pl",
    "iso:country":"GB",
    "sg:address":"21 Market Pl",
    "sg:city":"Wetherby",
    "sg:classifiers":[
        {
            "category":"Banks & Credit Unions",
            "subcategory":"Bank",
            "type":"Services"
        }
    ],
    "sg:postcode":"LS22 6LQ",
    "sg:province":"North Yorkshire",
    "sg:tags":[
        "broker",
        "mortgage"
    ],
    "wof:name":"M C A Finance Ltd",
    "wof:placetype":"venue"
},
  "geometry": {"coordinates":[-1.386918,53.928062],"type":"Point"}
}