{
  "type": "Feature",
  "properties": {
    "addr:full":"31 Snowdrop Way, Widmerend High Wycombe Buckinghamshire HP15 6BL",
    "addr:housenumber":"31",
    "addr:postcode":"hp15 6bl",
    "addr:street":"Snowdrop Way",
    "iso:country":"GB",
    "sg:address":"31 Snowdrop Way, Widmerend",
    "sg:city":"High Wycombe",
    "sg:classifiers":[
        {
            "category":"Organizations",
            "subcategory":"Community Association",
            "type":"Services"
        },
        {
            "category":"Organizations",
            "subcategory":"Non-profit Organization",
            "type":"Services"
        }
    ],
    "sg:phone":"+44 1494 715345",
    "sg:postcode":"HP15 6BL",
    "sg:province":"Buckinghamshire",
    "sg:tags":[
        "organisation",
        "care",
        "animal",
        "welfare"
    ],
    "wof:name":"The Marjorie Nash Cat Rescue",
    "wof:placetype":"venue"
},
  "geometry": {"coordinates":[-0.718535,51.665546],"type":"Point"}
}