{
  "type": "Feature",
  "properties": {
    "iso:country":"GB",
    "sg:address":"40 West Market Building, London Central Markets",
    "sg:city":"London",
    "sg:classifiers":[
        {
            "category":"Wholesale",
            "subcategory":"Meat",
            "type":"Manufacturing & Wholesale Goods"
        }
    ],
    "sg:phone":"+44 20 7248 0121",
    "sg:postcode":"EC1A 9PS",
    "sg:province":"Greater London",
    "sg:tags":[
        "-"
    ],
    "wof:name":"James Burden Ltd.",
    "wof:placetype":"venue"
},
  "geometry": {"coordinates":[-0.1019399986,51.5190505981],"type":"Point"}
}