{
  "type": "Feature",
  "properties": {
    "iso:country":"GB",
    "sg:address":"87b Springbank Road, Hither Grn",
    "sg:city":"London",
    "sg:classifiers":[
        {
            "category":"Building & Trades",
            "subcategory":"Plumbing",
            "type":"Services"
        }
    ],
    "sg:postcode":"SE13 6SS",
    "sg:province":"Greater London",
    "sg:tags":[
        "central",
        "heating"
    ],
    "wof:name":"Aabacom Services",
    "wof:placetype":"venue"
},
  "geometry": {"coordinates":[0.000745,51.44949],"type":"Point"}
}