{
  "type": "Feature",
  "properties": {
    "addr:full":"255 Brownedge Road, Bamber Bridge Preston Lancashire PR5 6UT",
    "addr:housenumber":"255",
    "addr:postcode":"pr5 6ut",
    "addr:street":"Brownedge Road",
    "iso:country":"GB",
    "sg:address":"255 Brownedge Road, Bamber Bridge",
    "sg:city":"Preston",
    "sg:classifiers":[
        {
            "category":"Home & Garden",
            "subcategory":"Home Furnishings",
            "type":"Retail Goods"
        },
        {
            "category":"Wholesale",
            "subcategory":"Home Furnishings",
            "type":"Manufacturing & Wholesale Goods"
        }
    ],
    "sg:phone":"+44 1772 337929",
    "sg:postcode":"PR5 6UT",
    "sg:province":"Lancashire",
    "sg:tags":[
        "blind",
        "manufacture",
        "fitting",
        "curtain"
    ],
    "wof:name":"Jacqueline Riding",
    "wof:placetype":"venue"
},
  "geometry": {"coordinates":[-2.6730968952,53.7285346985],"type":"Point"}
}