{
  "type": "Feature",
  "properties": {
    "iso:country":"GB",
    "sg:address":"Tumble Down Barn, Chapel Hill, Woodton",
    "sg:city":"Bungay",
    "sg:classifiers":[
        {
            "category":"Building & Trades",
            "subcategory":"Construction",
            "type":"Services"
        }
    ],
    "sg:postcode":"NR35 2NX",
    "sg:province":"Norfolk",
    "sg:tags":[
        "builder"
    ],
    "wof:name":"Shreeve Builders",
    "wof:placetype":"venue"
},
  "geometry": {"coordinates":[1.37437,52.495434],"type":"Point"}
}