{
  "type": "Feature",
  "properties": {
    "iso:country":"GB",
    "sg:address":"Ensign Way, Hamble",
    "sg:city":"Southampton",
    "sg:classifiers":[
        {
            "category":"Arena",
            "subcategory":"Sports Club",
            "type":"Entertainment"
        }
    ],
    "sg:phone":"+44 23 8060 4100",
    "sg:postcode":"SO31 4RF",
    "sg:province":"Hampshire",
    "wof:name":"Royal Yachting Association",
    "wof:placetype":"venue"
},
  "geometry": {"coordinates":[-1.329304,50.85656],"type":"Point"}
}