{
  "type": "Feature",
  "properties": {
    "iso:country":"GB",
    "sg:address":"Unit 7 Lincoln Road, Pocklington Industrial Estate, Pocklington",
    "sg:city":"York",
    "sg:classifiers":[
        {
            "category":"Building & Trades",
            "subcategory":"Construction",
            "type":"Services"
        }
    ],
    "sg:postcode":"YO42 1NR",
    "sg:province":"East Riding of Yorkshire",
    "sg:tags":[
        "joiner",
        "carpenter"
    ],
    "wof:name":"James Pethullis",
    "wof:placetype":"venue"
},
  "geometry": {"coordinates":[-0.79929,53.92469],"type":"Point"}
}