{
  "type": "Feature",
  "properties": {
    "addr:full":"Highcroft, Dingle Lane, Kelsall Tarporley Cheshire CW6 0SG",
    "addr:postcode":"cw6 0sg",
    "addr:street":"Dingle Lane",
    "iso:country":"GB",
    "sg:address":"Highcroft, Dingle Lane, Kelsall",
    "sg:city":"Tarporley",
    "sg:classifiers":[
        {
            "category":"Building & Trades",
            "subcategory":"Landscaping Services",
            "type":"Services"
        }
    ],
    "sg:phone":"+44 1829 751616",
    "sg:postcode":"CW6 0SG",
    "sg:province":"Cheshire",
    "sg:tags":[
        "landscape",
        "contractor"
    ],
    "wof:name":"Gerald Sutton",
    "wof:placetype":"venue"
},
  "geometry": {"coordinates":[-2.668755,53.159355],"type":"Point"}
}