{
  "type": "Feature",
  "properties": {
    "iso:country":"GB",
    "sg:address":"Baildon Mills, Northgate, Baildon",
    "sg:city":"Shipley",
    "sg:classifiers":[
        {
            "category":"Manufacturing",
            "subcategory":"Textiles",
            "type":"Manufacturing & Wholesale Goods"
        }
    ],
    "sg:phone":"+44 1274 583276",
    "sg:postcode":"BD17 6JY",
    "sg:province":"West Yorkshire",
    "sg:tags":[
        "made-up"
    ],
    "wof:name":"John Peel & Son (Holdings) Ltd.",
    "wof:placetype":"venue"
},
  "geometry": {"coordinates":[-1.766849,53.848671],"type":"Point"}
}