{
  "type": "Feature",
  "properties": {
    "addr:full":"Topcliffe La, Tingley Wakefield West Yorkshire WF3 1SF",
    "addr:postcode":"wf3 1sf",
    "addr:street":"West",
    "iso:country":"GB",
    "sg:address":"Topcliffe La, Tingley",
    "sg:city":"Wakefield",
    "sg:classifiers":[
        {
            "category":"Utilities",
            "subcategory":"Natural Gas",
            "type":"Services"
        }
    ],
    "sg:phone":"+44 113 238 3702",
    "sg:postcode":"WF3 1SF",
    "sg:province":"West Yorkshire",
    "wof:name":"British Gas L P Gas",
    "wof:placetype":"venue"
},
  "geometry": {"coordinates":[-1.5860940218,53.7273483276],"type":"Point"}
}