{
  "type": "Feature",
  "properties": {
    "iso:country":"GB",
    "sg:address":"The Coach House, 2c Clark Road",
    "sg:city":"Wolverhampton",
    "sg:classifiers":[
        {
            "category":"Utilities",
            "subcategory":"Fuel Oil & Lpg",
            "type":"Services"
        }
    ],
    "sg:postcode":"WV3 9NW",
    "sg:province":"Staffordshire",
    "sg:tags":[
        "distributor"
    ],
    "wof:name":"Hallett Oils & Detergents",
    "wof:placetype":"venue"
},
  "geometry": {"coordinates":[-2.1478610039,52.58852005],"type":"Point"}
}