{
  "type": "Feature",
  "properties": {
    "iso:country":"GB",
    "sg:address":"Wood Street, Denton",
    "sg:city":"Manchester",
    "sg:classifiers":[
        {
            "category":"Food & Beverages",
            "subcategory":"Groceries & Convenience Stores",
            "type":"Retail Goods"
        }
    ],
    "sg:phone":"+44 161 336 6598",
    "sg:postcode":"M34 3DT",
    "sg:province":"Greater Manchester",
    "sg:tags":[
        "merchant",
        "potato"
    ],
    "wof:name":"DAVIES OF DENTON LTD",
    "wof:placetype":"venue"
},
  "geometry": {"coordinates":[-2.108184,53.45879],"type":"Point"}
}