{
  "type": "Feature",
  "properties": {
    "addr:full":"Plaish Park, Plaish Church Stretton Shropshire SY6 7HX",
    "addr:postcode":"sy6 7hx",
    "iso:country":"GB",
    "sg:address":"Plaish Park, Plaish",
    "sg:city":"Church Stretton",
    "sg:classifiers":[
        {
            "category":"Farming",
            "subcategory":"Livestock Farm",
            "type":"Manufacturing & Wholesale Goods"
        },
        {
            "category":"Building & Trades",
            "subcategory":"Construction",
            "type":"Services"
        }
    ],
    "sg:phone":"+44 1694 771262",
    "sg:postcode":"SY6 7HX",
    "sg:province":"Shropshire",
    "sg:tags":[
        "builder",
        "others"
    ],
    "wof:name":"Wh S K & M H Jones",
    "wof:placetype":"venue"
},
  "geometry": {"coordinates":[-2.8003339767,52.5376548767],"type":"Point"}
}