{
  "type": "Feature",
  "properties": {
    "addr:full":"47 Chalton St Camden Greater London NW1 1HY",
    "addr:housenumber":"47",
    "addr:postcode":"nw1 1hy",
    "addr:street":"Chalton St",
    "iso:country":"GB",
    "sg:address":"47 Chalton St",
    "sg:city":"Camden",
    "sg:classifiers":[
        {
            "category":"Organizations",
            "subcategory":"Non-profit Organization",
            "type":"Services"
        }
    ],
    "sg:phone":"+44 20 7388 9807",
    "sg:postcode":"NW1 1HY",
    "sg:province":"Greater London",
    "sg:tags":[
        "organisation",
        "voluntary",
        "charity"
    ],
    "wof:name":"National Pensioners Convention",
    "wof:placetype":"venue"
},
  "geometry": {"coordinates":[-0.130456,51.529758],"type":"Point"}
}