{
  "type": "Feature",
  "properties": {
    "addr:full":"46 High Street Cleator Moor Cumbria CA25 5LA",
    "addr:housenumber":"46",
    "addr:postcode":"ca25 5la",
    "addr:street":"High Street",
    "iso:country":"GB",
    "sg:address":"46 High Street",
    "sg:city":"Cleator Moor",
    "sg:classifiers":[
        {
            "category":"Sports & Exercise",
            "subcategory":"Sports Center",
            "type":"Entertainment"
        }
    ],
    "sg:phone":"+44 1946 815541",
    "sg:postcode":"CA25 5LA",
    "sg:province":"Cumbria",
    "sg:tags":[
        "shop",
        "good"
    ],
    "wof:name":"P Farrell",
    "wof:placetype":"venue"
},
  "geometry": {"coordinates":[-3.5152080059,54.5211257935],"type":"Point"}
}