{
  "type": "Feature",
  "properties": {
    "addr:full":"4 Clock House Parade, High Street, Wanstead London Greater London E11 2BB",
    "addr:housenumber":"4",
    "addr:postcode":"e11 2bb",
    "addr:street":"House Parade High Street",
    "iso:country":"GB",
    "sg:address":"4 Clock House Parade, High Street, Wanstead",
    "sg:city":"London",
    "sg:classifiers":[
        {
            "category":"Banks & Credit Unions",
            "subcategory":"Financial Services",
            "type":"Services"
        }
    ],
    "sg:phone":"+44 20 8530 2156",
    "sg:postcode":"E11 2BB",
    "sg:province":"Greater London",
    "sg:tags":[
        "building",
        "society"
    ],
    "wof:name":"Nationwide Building Society",
    "wof:placetype":"venue"
},
  "geometry": {"coordinates":[0.02658,51.577789],"type":"Point"}
}