{
  "type": "Feature",
  "properties": {
    "iso:country":"GB",
    "sg:address":"105 St Leonards Drive, Chapel St Leonards",
    "sg:city":"Skegness",
    "sg:classifiers":[
        {
            "category":"Food & Beverages",
            "subcategory":"Meat & Fish",
            "type":"Retail Goods"
        }
    ],
    "sg:postcode":"PE24 5RA",
    "sg:province":"Lincolnshire",
    "sg:tags":[
        "chip"
    ],
    "wof:name":"The Country Friar",
    "wof:placetype":"venue"
},
  "geometry": {"coordinates":[0.33597,53.231533],"type":"Point"}
}