{
  "type": "Feature",
  "properties": {
    "addr:full":"26-28 Stanthorpe Rd London Greater London SW16 2DY",
    "addr:housenumber":"26-28",
    "addr:postcode":"sw16 2dy",
    "addr:street":"Stanthorpe Rd",
    "iso:country":"GB",
    "sg:address":"26-28 Stanthorpe Rd",
    "sg:city":"London",
    "sg:classifiers":[
        {
            "category":"Travel",
            "subcategory":"Hotels & Motels",
            "type":"Entertainment"
        }
    ],
    "sg:postcode":"SW16 2DY",
    "sg:province":"Greater London",
    "wof:name":"Stanthorpe Hotel",
    "wof:placetype":"venue"
},
  "geometry": {"coordinates":[-0.128781,51.427666],"type":"Point"}
}