{
  "type": "Feature",
  "properties": {
    "iso:country":"GB",
    "sg:address":"54 Commercial Rd",
    "sg:city":"Whitechapel",
    "sg:classifiers":[
        {
            "category":"Shopping",
            "subcategory":"Mobile Phones",
            "type":"Retail Goods"
        }
    ],
    "sg:phone":"+44 20 7265 0303",
    "sg:postcode":"E1 1LP",
    "sg:province":"Greater London",
    "wof:name":"Station Communications",
    "wof:placetype":"venue"
},
  "geometry": {"coordinates":[-0.066829,51.514736],"type":"Point"}
}