{
  "type": "Feature",
  "properties": {
    "iso:country":"GB",
    "sg:address":"7 Sunnydale Avenue",
    "sg:city":"Brighouse",
    "sg:classifiers":[
        {
            "category":"Professional",
            "subcategory":"Engineering",
            "type":"Services"
        }
    ],
    "sg:postcode":"HD6 3ES",
    "sg:province":"West Yorkshire",
    "sg:tags":[
        "contractor",
        "electrical",
        "engineer"
    ],
    "wof:name":"Hartshorn,A P,",
    "wof:placetype":"venue"
},
  "geometry": {"coordinates":[-1.787068,53.692108],"type":"Point"}
}