{
  "type": "Feature",
  "properties": {
    "addr:full":"33 Longford Road Neath Neath Port Talbot SA10 7ET",
    "addr:housenumber":"33",
    "addr:postcode":"sa10 7et",
    "addr:street":"Longford Road",
    "iso:country":"GB",
    "sg:address":"33 Longford Road",
    "sg:city":"Neath",
    "sg:classifiers":[
        {
            "category":"Military Area",
            "subcategory":"Air Force Base",
            "type":"Public Place"
        }
    ],
    "sg:phone":"+44 1792 813587",
    "sg:postcode":"SA10 7ET",
    "sg:province":"Neath Port Talbot",
    "sg:tags":[
        "taxi",
        "hire",
        "private"
    ],
    "wof:name":"Abbey Cabs",
    "wof:placetype":"venue"
},
  "geometry": {"coordinates":[-3.8268918991,51.6658096313],"type":"Point"}
}