{
  "type": "Feature",
  "properties": {
    "iso:country":"GB",
    "sg:address":"69 Whitefriars",
    "sg:city":"Rushden",
    "sg:classifiers":[
        {
            "category":"Building & Trades",
            "subcategory":"Construction",
            "type":"Services"
        }
    ],
    "sg:phone":"+44 1933 318885",
    "sg:postcode":"NN10 9PE",
    "sg:province":"Bedfordshire",
    "sg:tags":[
        "builder"
    ],
    "wof:name":"Roy Neal",
    "wof:placetype":"venue"
},
  "geometry": {"coordinates":[-0.615716,52.28606],"type":"Point"}
}