{
  "type": "Feature",
  "properties": {
    "addr:full":"758 Oldham Road, Salesworth Manchester Lancashire M35 9XB",
    "addr:housenumber":"758",
    "addr:postcode":"m35 9xb",
    "addr:street":"Oldham Road",
    "iso:country":"GB",
    "sg:address":"758 Oldham Road, Salesworth",
    "sg:city":"Manchester",
    "sg:classifiers":[
        {
            "category":"Professional",
            "subcategory":"Lawyer & Legal Services",
            "type":"Services"
        }
    ],
    "sg:phone":"+44 161 834 0548",
    "sg:postcode":"M35 9XB",
    "sg:province":"Lancashire",
    "sg:tags":[
        "solicitor"
    ],
    "wof:name":"H L F Berry & Co.",
    "wof:placetype":"venue"
},
  "geometry": {"coordinates":[-2.147327,53.517033],"type":"Point"}
}