{
  "type": "Feature",
  "properties": {
    "addr:full":"Newbridge Quarry Kingsbridge Devon TQ7 2DH",
    "addr:postcode":"tq7 2dh",
    "addr:street":"Newbridge Quarry",
    "iso:country":"GB",
    "sg:address":"Newbridge Quarry",
    "sg:city":"Kingsbridge",
    "sg:classifiers":[
        {
            "category":"Home & Garden",
            "subcategory":"Garden Supply",
            "type":"Retail Goods"
        }
    ],
    "sg:phone":"+44 1548 852353",
    "sg:postcode":"TQ7 2DH",
    "sg:province":"Devon",
    "sg:tags":[
        "nursery",
        "centre"
    ],
    "wof:name":"E & B R Noyce Ltd.",
    "wof:placetype":"venue"
},
  "geometry": {"coordinates":[-3.6965789795,50.2690925598],"type":"Point"}
}