{
  "type": "Feature",
  "properties": {
    "addr:full":"40 Heol Llanelli, Trimsaran Kidwelly Carmarthenshire SA17 4AG",
    "addr:housenumber":"40",
    "addr:postcode":"sa17 4ag",
    "addr:street":"Heol Llanelli",
    "iso:country":"GB",
    "sg:address":"40 Heol Llanelli, Trimsaran",
    "sg:city":"Kidwelly",
    "sg:classifiers":[
        {
            "category":"Education",
            "subcategory":"School",
            "type":"Public Place"
        }
    ],
    "sg:phone":"+44 1554 810670",
    "sg:postcode":"SA17 4AG",
    "sg:province":"Carmarthenshire",
    "sg:tags":[
        "local",
        "authority"
    ],
    "wof:name":"Trimsaran Community Primary School",
    "wof:placetype":"venue"
},
  "geometry": {"coordinates":[-4.303438,51.736519],"type":"Point"}
}