{
  "type": "Feature",
  "properties": {
    "addr:full":"224 Dunvant Road, Dunvant Swansea Swansea SA2 7SR",
    "addr:housenumber":"224",
    "addr:postcode":"sa2 7sr",
    "addr:street":"Dunvant Road",
    "iso:country":"GB",
    "sg:address":"224 Dunvant Road, Dunvant",
    "sg:city":"Swansea",
    "sg:classifiers":[
        {
            "category":"Building & Trades",
            "subcategory":"Construction",
            "type":"Services"
        }
    ],
    "sg:postcode":"SA2 7SR",
    "sg:province":"Swansea",
    "sg:tags":[
        "decorator",
        "painter"
    ],
    "wof:name":"Brian Evans",
    "wof:placetype":"venue"
},
  "geometry": {"coordinates":[-4.0263,51.622627],"type":"Point"}
}