{
  "type": "Feature",
  "properties": {
    "addr:full":"1a Beethoven St Ladbroke Grove Greater London W10 4LG",
    "addr:housenumber":"1a",
    "addr:postcode":"w10 4lg",
    "addr:street":"Beethoven St",
    "iso:country":"GB",
    "sg:address":"1a Beethoven St",
    "sg:city":"Ladbroke Grove",
    "sg:classifiers":[
        {
            "category":"Professional",
            "subcategory":"Art Services",
            "type":"Services"
        }
    ],
    "sg:phone":"+44 20 8968 3062",
    "sg:postcode":"W10 4LG",
    "sg:province":"Greater London",
    "sg:tags":[
        "graphic",
        "designer"
    ],
    "wof:name":"Fuel Graphic Design",
    "wof:placetype":"venue"
},
  "geometry": {"coordinates":[-0.207221,51.530643],"type":"Point"}
}