{
  "type": "Feature",
  "properties": {
    "iso:country":"GB",
    "sg:address":"35 Horncliffe Road",
    "sg:city":"Blackpool",
    "sg:classifiers":[
        {
            "category":"Health Services",
            "subcategory":"Nursing And Care Facility",
            "type":"Services"
        },
        {
            "category":"Social Services",
            "subcategory":"Retirement Home",
            "type":"Services"
        }
    ],
    "sg:phone":"+44 1253 341576",
    "sg:postcode":"FY4 1LJ",
    "sg:province":"Lancashire",
    "sg:tags":[
        "residential",
        "rest"
    ],
    "wof:name":"Horncliffe House",
    "wof:placetype":"venue"
},
  "geometry": {"coordinates":[-3.050143,53.787262],"type":"Point"}
}