{
  "type": "Feature",
  "properties": {
    "iso:country":"GB",
    "sg:address":"51-57 (unit A) Effra Road, Brixton",
    "sg:city":"London",
    "sg:classifiers":[
        {
            "category":"Home & Garden",
            "subcategory":"Household Appliances",
            "type":"Retail Goods"
        }
    ],
    "sg:phone":"+44 20 7733 1886",
    "sg:postcode":"SW2 1BZ",
    "sg:province":"Greater London",
    "sg:tags":[
        "electrical",
        "domestic"
    ],
    "wof:name":"Currys",
    "wof:placetype":"venue"
},
  "geometry": {"coordinates":[-0.114365,51.457462],"type":"Point"}
}