{
  "type": "Feature",
  "properties": {
    "addr:full":"8 Brookside Cres, Cuffley Potters Bar Greater London EN6 4QN",
    "addr:housenumber":"8",
    "addr:postcode":"en6 4qn",
    "addr:street":"Brookside Cres",
    "iso:country":"GB",
    "sg:address":"8 Brookside Cres, Cuffley",
    "sg:city":"Potters Bar",
    "sg:classifiers":[
        {
            "category":"Manufacturing",
            "subcategory":"Tools & Machinery",
            "type":"Manufacturing & Wholesale Goods"
        }
    ],
    "sg:postcode":"EN6 4QN",
    "sg:province":"Greater London",
    "sg:tags":[
        "society",
        "friendly"
    ],
    "wof:name":"Pohl,David M,",
    "wof:placetype":"venue"
},
  "geometry": {"coordinates":[-0.1129100025,51.7157974243],"type":"Point"}
}