{
  "type": "Feature",
  "properties": {
    "addr:full":"Grosvenor Road, Langley Vale Epsom Surrey KT18 6JH",
    "addr:postcode":"kt18 6jh",
    "addr:street":"Grosvenor Road",
    "iso:country":"GB",
    "sg:address":"Grosvenor Road, Langley Vale",
    "sg:city":"Epsom",
    "sg:classifiers":[
        {
            "category":"Education",
            "subcategory":"School",
            "type":"Public Place"
        }
    ],
    "sg:phone":"+44 1372 273639",
    "sg:postcode":"KT18 6JH",
    "sg:province":"Surrey",
    "sg:tags":[
        "local",
        "authority"
    ],
    "wof:name":"Epsom Downs County Infant School",
    "wof:placetype":"venue"
},
  "geometry": {"coordinates":[-0.2698740065,51.3072013855],"type":"Point"}
}