{
  "type": "Feature",
  "properties": {
    "iso:country":"GB",
    "sg:address":"46 The Strand",
    "sg:city":"Exmouth",
    "sg:classifiers":[
        {
            "category":"Professional",
            "subcategory":"Art Services",
            "type":"Services"
        },
        {
            "category":"Shopping",
            "subcategory":"Crafts & Fabrics",
            "type":"Retail Goods"
        }
    ],
    "sg:phone":"+44 1395 227226",
    "sg:postcode":"EX8 1AL",
    "sg:province":"Devon",
    "sg:tags":[
        "material",
        "framing"
    ],
    "wof:name":"Fred Keetch",
    "wof:placetype":"venue"
},
  "geometry": {"coordinates":[-3.414576,50.619057],"type":"Point"}
}