{
  "type": "Feature",
  "properties": {
    "iso:country":"GB",
    "sg:address":"Unit 14, Crelake Ind Est, Pixon Lane",
    "sg:city":"Tavistock",
    "sg:classifiers":[
        {
            "category":"Building & Trades",
            "subcategory":"Plumbing",
            "type":"Services"
        }
    ],
    "sg:phone":"+44 1822 612299",
    "sg:postcode":"PL19 9AZ",
    "sg:province":"Devon",
    "sg:tags":[
        "merchant",
        "plumbers'"
    ],
    "wof:name":"Thompsons",
    "wof:placetype":"venue"
},
  "geometry": {"coordinates":[-4.144739,50.549934],"type":"Point"}
}