{
  "type": "Feature",
  "properties": {
    "iso:country":"GB",
    "sg:address":"The Old Warwick Road, Lapworth",
    "sg:city":"Solihull",
    "sg:classifiers":[
        {
            "category":"Bars & Pubs",
            "type":"Food & Drink"
        }
    ],
    "sg:phone":"+44 1564 782464",
    "sg:postcode":"B94 6JU",
    "sg:province":"Warwickshire",
    "sg:tags":[
        "pubs",
        "inn"
    ],
    "wof:name":"The Boot Inn",
    "wof:placetype":"venue"
},
  "geometry": {"coordinates":[-1.7702059746,52.3477554321],"type":"Point"}
}