{
  "type": "Feature",
  "properties": {
    "addr:full":"16 Ashtrees Road, Woodley Reading Berkshire RG5 4LP",
    "addr:housenumber":"16",
    "addr:postcode":"rg5 4lp",
    "addr:street":"Ashtrees Road",
    "iso:country":"GB",
    "sg:address":"16 Ashtrees Road, Woodley",
    "sg:city":"Reading",
    "sg:classifiers":[
        {
            "category":"Organizations",
            "subcategory":"Membership Organization",
            "type":"Services"
        }
    ],
    "sg:postcode":"RG5 4LP",
    "sg:province":"Berkshire",
    "sg:tags":[
        "club"
    ],
    "wof:name":"Stroke Club Earley & Woodley",
    "wof:placetype":"venue"
},
  "geometry": {"coordinates":[-0.899673,51.456306],"type":"Point"}
}