{
  "type": "Feature",
  "properties": {
    "addr:full":"94 Brook Street Erith Kent DA8 1JF",
    "addr:housenumber":"94",
    "addr:postcode":"da8 1jf",
    "addr:street":"Brook Street",
    "iso:country":"GB",
    "sg:address":"94 Brook Street",
    "sg:city":"Erith",
    "sg:classifiers":[
        {
            "category":"Building & Trades",
            "subcategory":"Construction",
            "type":"Services"
        }
    ],
    "sg:postcode":"DA8 1JF",
    "sg:province":"Kent",
    "sg:tags":[
        "joiner",
        "carpenter"
    ],
    "wof:name":"Codling Refurbishments Ltd",
    "wof:placetype":"venue"
},
  "geometry": {"coordinates":[0.158104,51.473953],"type":"Point"}
}