{
  "type": "Feature",
  "properties": {
    "iso:country":"GB",
    "sg:address":"Magpies, Idsworth",
    "sg:city":"Waterlooville",
    "sg:classifiers":[
        {
            "category":"Professional",
            "subcategory":"Advertising",
            "type":"Services"
        },
        {
            "category":"Professional",
            "subcategory":"Art Services",
            "type":"Services"
        }
    ],
    "sg:phone":"+44 23 9241 3777",
    "sg:postcode":"PO8 0AS",
    "sg:province":"Hampshire",
    "sg:tags":[
        "graphic",
        "agency",
        "designer"
    ],
    "wof:name":"Richard Pegg & Associates Ltd",
    "wof:placetype":"venue"
},
  "geometry": {"coordinates":[-0.96166,50.905033],"type":"Point"}
}