{
  "type": "Feature",
  "properties": {
    "iso:country":"GB",
    "sg:address":"Civic Way",
    "sg:city":"Swadlincote",
    "sg:classifiers":[
        {
            "category":"Government",
            "subcategory":"Court House",
            "type":"Public Place"
        }
    ],
    "sg:phone":"+44 1283 221467",
    "sg:postcode":"DE11 0AE",
    "sg:province":"Derbyshire",
    "wof:name":"South Derbyshire Magistrates Court",
    "wof:placetype":"venue"
},
  "geometry": {"coordinates":[-1.557774,52.774803],"type":"Point"}
}