{
  "type": "Feature",
  "properties": {
    "addr:full":"Suite 12, South West Centre, Archer Rd Sheffield Derbyshire S8 0JR",
    "addr:postcode":"s8 0jr",
    "addr:street":"Suite 12 South West;Archer Rd",
    "iso:country":"GB",
    "sg:address":"Suite 12, South West Centre, Archer Rd",
    "sg:city":"Sheffield",
    "sg:classifiers":[
        {
            "category":"Manufacturing",
            "subcategory":"Metals",
            "type":"Manufacturing & Wholesale Goods"
        }
    ],
    "sg:postcode":"S8 0JR",
    "sg:province":"Derbyshire",
    "sg:tags":[
        "steel",
        "stockholder"
    ],
    "wof:name":"Wright,Brian,Titanium Ltd",
    "wof:placetype":"venue"
},
  "geometry": {"coordinates":[-1.48806,53.349838],"type":"Point"}
}