{
  "type": "Feature",
  "properties": {
    "iso:country":"GB",
    "sg:address":"16 Pioneer Rd",
    "sg:city":"Faringdon",
    "sg:classifiers":[
        {
            "category":"Sports & Exercise",
            "subcategory":"Race Track",
            "type":"Entertainment"
        }
    ],
    "sg:phone":"+44 1367 244233",
    "sg:postcode":"SN7 7BU",
    "sg:province":"Oxfordshire",
    "sg:tags":[
        "motor"
    ],
    "wof:name":"Tarry Falcon Racing",
    "wof:placetype":"venue"
},
  "geometry": {"coordinates":[-1.583068,51.652908],"type":"Point"}
}