{
  "type": "Feature",
  "properties": {
    "addr:full":"Po Box 39 Croyde Braunton Devon EX33 1YP",
    "addr:housenumber":"po box 39;braunton",
    "addr:postcode":"ex33 1yp",
    "addr:street":"Croyde",
    "iso:country":"GB",
    "sg:address":"Po Box 39 Croyde",
    "sg:city":"Braunton",
    "sg:classifiers":[
        {
            "category":"Recreation",
            "subcategory":"Water Park",
            "type":"Entertainment"
        }
    ],
    "sg:phone":"+44 1271 890400",
    "sg:postcode":"EX33 1YP",
    "sg:province":"Devon",
    "sg:tags":[
        "sport"
    ],
    "wof:name":"Surf South West",
    "wof:placetype":"venue"
},
  "geometry": {"coordinates":[-4.1616492271,51.1098175049],"type":"Point"}
}