{
  "type": "Feature",
  "properties": {
    "addr:full":"83 Kings Rd, London Colney St. Albans Hertfordshire AL2 1ER",
    "addr:housenumber":"83",
    "addr:postcode":"al2 1er",
    "addr:street":"Kings Rd",
    "iso:country":"GB",
    "sg:address":"83 Kings Rd, London Colney",
    "sg:city":"St. Albans",
    "sg:classifiers":[
        {
            "category":"Government",
            "subcategory":"Post Office",
            "type":"Public Place"
        }
    ],
    "sg:phone":"+44 1727 823632",
    "sg:postcode":"AL2 1ER",
    "sg:province":"Hertfordshire",
    "sg:tags":[
        "messenger",
        "courier"
    ],
    "wof:name":"Direct Transport Services",
    "wof:placetype":"venue"
},
  "geometry": {"coordinates":[-0.3031240106,51.7245597839],"type":"Point"}
}