{
  "type": "Feature",
  "properties": {
    "addr:full":"114 Waterloo Rd Stoke On Trent Staffordshire ST6 3HB",
    "addr:housenumber":"114",
    "addr:postcode":"st6 3hb",
    "addr:street":"Waterloo Rd",
    "iso:country":"GB",
    "sg:address":"114 Waterloo Rd",
    "sg:city":"Stoke On Trent",
    "sg:classifiers":[
        {
            "category":"Bars & Pubs",
            "type":"Food & Drink"
        }
    ],
    "sg:phone":"+44 1782 836861",
    "sg:postcode":"ST6 3HB",
    "sg:province":"Staffordshire",
    "sg:tags":[
        "pubs",
        "inn"
    ],
    "wof:name":"Stag Inn",
    "wof:placetype":"venue"
},
  "geometry": {"coordinates":[-2.1928288937,53.0414505005],"type":"Point"}
}