{
  "type": "Feature",
  "properties": {
    "iso:country":"GB",
    "sg:address":"1 Piccadilly Circus",
    "sg:city":"London",
    "sg:classifiers":[
        {
            "category":"Commercial Area",
            "type":"Public Place"
        }
    ],
    "sg:postcode":"W1J 0DA",
    "sg:province":"Greater London",
    "sg:tags":[
        "shop",
        "centre"
    ],
    "wof:name":"The London Pavilion",
    "wof:placetype":"venue"
},
  "geometry": {"coordinates":[-0.135611,51.509464],"type":"Point"}
}