{
  "type": "Feature",
  "properties": {
    "iso:country":"GB",
    "sg:address":"Toynbee Road",
    "sg:city":"Eastleigh",
    "sg:classifiers":[
        {
            "category":"Education",
            "subcategory":"School",
            "type":"Public Place"
        }
    ],
    "sg:phone":"+44 23 8061 2536",
    "sg:postcode":"SO50 9DH",
    "sg:province":"Hampshire",
    "sg:tags":[
        "local",
        "authority"
    ],
    "wof:name":"The Crescent County Primary School",
    "wof:placetype":"venue"
},
  "geometry": {"coordinates":[-1.357279,50.972675],"type":"Point"}
}