{
  "type": "Feature",
  "properties": {
    "iso:country":"GB",
    "sg:address":"Downhouse Farm, Follygate",
    "sg:city":"Okehampton",
    "sg:classifiers":[
        {
            "category":"Farming",
            "subcategory":"Livestock Farm",
            "type":"Manufacturing & Wholesale Goods"
        }
    ],
    "sg:phone":"+44 1837 52297",
    "sg:postcode":"EX20 3AE",
    "sg:province":"Devon",
    "sg:tags":[
        "others"
    ],
    "wof:name":"Downhouse Farm",
    "wof:placetype":"venue"
},
  "geometry": {"coordinates":[-4.022429,50.762871],"type":"Point"}
}