{
  "type": "Feature",
  "properties": {
    "addr:full":"Coalburn Rd Glasgow Glasgow City G71 8DA",
    "addr:postcode":"g71 8da",
    "addr:street":"Coalburn Rd",
    "iso:country":"GB",
    "sg:address":"Coalburn Rd",
    "sg:city":"Glasgow",
    "sg:classifiers":[
        {
            "category":"Personal",
            "type":"Services"
        }
    ],
    "sg:phone":"+44 870 556 1013",
    "sg:postcode":"G71 8DA",
    "sg:province":"Glasgow City",
    "sg:tags":[
        "delivery"
    ],
    "wof:name":"Lynx Express Ltd",
    "wof:placetype":"venue"
},
  "geometry": {"coordinates":[-4.061021,55.817024],"type":"Point"}
}