{
  "type": "Feature",
  "properties": {
    "iso:country":"GB",
    "sg:address":"155 The Ryde",
    "sg:city":"Hatfield",
    "sg:classifiers":[
        {
            "category":"Shopping",
            "subcategory":"Pharmacy",
            "type":"Retail Goods"
        }
    ],
    "sg:phone":"+44 1707 251453",
    "sg:postcode":"AL9 5DP",
    "sg:province":"Hertfordshire",
    "sg:tags":[
        "medicine",
        "therapy"
    ],
    "wof:name":"Kerstin Schmidt",
    "wof:placetype":"venue"
},
  "geometry": {"coordinates":[-0.2144410014,51.7715606689],"type":"Point"}
}