{
  "type": "Feature",
  "properties": {
    "iso:country":"GB",
    "sg:address":"Maynes Farm, Gorhambury",
    "sg:city":"St Albans",
    "sg:classifiers":[
        {
            "category":"Farming",
            "subcategory":"Livestock Farm",
            "type":"Manufacturing & Wholesale Goods"
        }
    ],
    "sg:phone":"+44 1727 853323",
    "sg:postcode":"AL3 6AF",
    "sg:province":"Hertfordshire",
    "sg:tags":[
        "others"
    ],
    "wof:name":"G Woollatt",
    "wof:placetype":"venue"
},
  "geometry": {"coordinates":[-0.3738400042,51.7624588013],"type":"Point"}
}