{
  "type": "Feature",
  "properties": {
    "addr:full":"877 Christchurch Road, Boscombe Bournemouth Dorset BH7 6AT",
    "addr:housenumber":"877",
    "addr:postcode":"bh7 6at",
    "addr:street":"Christchurch Road",
    "iso:country":"GB",
    "sg:address":"877 Christchurch Road, Boscombe",
    "sg:city":"Bournemouth",
    "sg:classifiers":[
        {
            "category":"Home & Garden",
            "subcategory":"Building Materials",
            "type":"Retail Goods"
        }
    ],
    "sg:postcode":"BH7 6AT",
    "sg:province":"Dorset",
    "sg:tags":[
        "brick"
    ],
    "wof:name":"Focal Fires",
    "wof:placetype":"venue"
},
  "geometry": {"coordinates":[-1.8269809484,50.7300453186],"type":"Point"}
}