{
  "type": "Feature",
  "properties": {
    "addr:full":"578 Reading Road, Winnersh Wokingham Berkshire RG41 5HA",
    "addr:housenumber":"578",
    "addr:postcode":"rg41 5ha",
    "addr:street":"Reading Road",
    "iso:country":"GB",
    "sg:address":"578 Reading Road, Winnersh",
    "sg:city":"Wokingham",
    "sg:classifiers":[
        {
            "category":"Home & Garden",
            "subcategory":"Carpets & Floor Coverings",
            "type":"Retail Goods"
        }
    ],
    "sg:phone":"+44 118 979 4583",
    "sg:postcode":"RG41 5HA",
    "sg:province":"Berkshire",
    "sg:tags":[
        "carpets",
        "rug",
        "matting"
    ],
    "wof:name":"Cut Price Carpets",
    "wof:placetype":"venue"
},
  "geometry": {"coordinates":[-0.8914650083,51.4351615906],"type":"Point"}
}