{
  "type": "Feature",
  "properties": {
    "iso:country":"GB",
    "sg:address":"34 Galgate",
    "sg:city":"Barnard Castle",
    "sg:classifiers":[
        {
            "category":"Fast Food",
            "type":"Food & Drink"
        }
    ],
    "sg:phone":"+44 1833 638942",
    "sg:postcode":"DL12 8BH",
    "sg:province":"Cumbria",
    "sg:tags":[
        "away",
        "take"
    ],
    "wof:name":"The Golden Gate",
    "wof:placetype":"venue"
},
  "geometry": {"coordinates":[-1.923867,54.54541],"type":"Point"}
}