{
  "type": "Feature",
  "properties": {
    "iso:country":"GB",
    "sg:address":"Edgecombe House, Calne Road, Lyneham",
    "sg:city":"Chippenham",
    "sg:classifiers":[
        {
            "category":"Banks & Credit Unions",
            "subcategory":"Financial Services",
            "type":"Services"
        }
    ],
    "sg:phone":"+44 1249 890412",
    "sg:postcode":"SN15 4PT",
    "sg:province":"Wiltshire",
    "sg:tags":[
        "adviser"
    ],
    "wof:name":"Heather Moor Edgecomb",
    "wof:placetype":"venue"
},
  "geometry": {"coordinates":[-1.966094,51.508015],"type":"Point"}
}