{
  "type": "Feature",
  "properties": {
    "addr:full":"Warden, Springfield Court, Ravensbourne Place Milton Keynes Buckinghamshire MK6 3JJ",
    "addr:postcode":"mk6 3jj",
    "addr:street":"Ravensbourne Place",
    "iso:country":"GB",
    "sg:address":"Warden, Springfield Court, Ravensbourne Place",
    "sg:city":"Milton Keynes",
    "sg:classifiers":[
        {
            "category":"Social Services",
            "subcategory":"Adult Care",
            "type":"Services"
        },
        {
            "category":"Social Services",
            "subcategory":"Retirement Home",
            "type":"Services"
        }
    ],
    "sg:phone":"+44 1908 678411",
    "sg:postcode":"MK6 3JJ",
    "sg:province":"Buckinghamshire",
    "sg:tags":[
        "housing",
        "sheltered",
        "accommodation"
    ],
    "wof:name":"Springfield Court Sheltered Housing",
    "wof:placetype":"venue"
},
  "geometry": {"coordinates":[-0.738544,52.041393],"type":"Point"}
}