{
  "type": "Feature",
  "properties": {
    "addr:full":"66 High Road Nottingham Nottinghamshire NG9 2LF",
    "addr:housenumber":"66",
    "addr:postcode":"ng9 2lf",
    "addr:street":"High Road",
    "iso:country":"GB",
    "sg:address":"66 High Road",
    "sg:city":"Nottingham",
    "sg:classifiers":[
        {
            "category":"Restaurant",
            "type":"Food & Drink"
        }
    ],
    "sg:phone":"+44 115 922 9154",
    "sg:postcode":"NG9 2LF",
    "sg:province":"Nottinghamshire",
    "wof:name":"Choice Family Restaurant",
    "wof:placetype":"venue"
},
  "geometry": {"coordinates":[-1.2128590345,52.9284057617],"type":"Point"}
}