{
  "type": "Feature",
  "properties": {
    "iso:country":"GB",
    "sg:address":"16 Imperial Way",
    "sg:city":"Chislehurst",
    "sg:classifiers":[
        {
            "category":"Building & Trades",
            "subcategory":"Construction",
            "type":"Services"
        }
    ],
    "sg:phone":"+44 20 8325 6734",
    "sg:postcode":"BR7 6JP",
    "sg:province":"Kent",
    "sg:tags":[
        "joinery"
    ],
    "wof:name":"Chalmers Fencing",
    "wof:placetype":"venue"
},
  "geometry": {"coordinates":[0.075016,51.426361],"type":"Point"}
}