{
  "type": "Feature",
  "properties": {
    "addr:full":"408 London Road Sutton Surrey SM3 8JF",
    "addr:housenumber":"408",
    "addr:postcode":"sm3 8jf",
    "addr:street":"London Road",
    "iso:country":"GB",
    "sg:address":"408 London Road",
    "sg:city":"Sutton",
    "sg:classifiers":[
        {
            "category":"Communications",
            "subcategory":"Film & Video Production",
            "type":"Services"
        },
        {
            "category":"Professional",
            "subcategory":"Art Services",
            "type":"Services"
        }
    ],
    "sg:phone":"+44 20 8644 4271",
    "sg:postcode":"SM3 8JF",
    "sg:province":"Surrey",
    "sg:tags":[
        "illustrator",
        "artist"
    ],
    "wof:name":"Vincer Illustration",
    "wof:placetype":"venue"
},
  "geometry": {"coordinates":[-0.2307550013,51.3683357239],"type":"Point"}
}