{
  "type": "Feature",
  "properties": {
    "addr:full":"10 Colbourne Road Bath Somerset BA2 2SE",
    "addr:housenumber":"10",
    "addr:postcode":"ba2 2se",
    "addr:street":"Colbourne Road",
    "iso:country":"GB",
    "sg:address":"10 Colbourne Road",
    "sg:city":"Bath",
    "sg:classifiers":[
        {
            "category":"Building & Trades",
            "subcategory":"Construction",
            "type":"Services"
        }
    ],
    "sg:phone":"+44 1225 836051",
    "sg:postcode":"BA2 2SE",
    "sg:province":"Somerset",
    "sg:tags":[
        "roofing",
        "contracting"
    ],
    "wof:name":"Aquaseal Flat Roofing",
    "wof:placetype":"venue"
},
  "geometry": {"coordinates":[-2.3814489841,51.3565254211],"type":"Point"}
}