{
  "type": "Feature",
  "properties": {
    "iso:country":"GB",
    "sg:address":"122 London Road, Southborough",
    "sg:city":"Tunbridge Wells",
    "sg:classifiers":[
        {
            "category":"Professional",
            "subcategory":"Business Services",
            "type":"Services"
        }
    ],
    "sg:phone":"+44 1892 523171",
    "sg:postcode":"TN4 0PL",
    "sg:province":"Kent",
    "sg:tags":[
        "import",
        "export",
        "agent"
    ],
    "wof:name":"A Ronai (Eastern) Ltd.",
    "wof:placetype":"venue"
},
  "geometry": {"coordinates":[0.259961,51.155094],"type":"Point"}
}