{
  "type": "Feature",
  "properties": {
    "iso:country":"GB",
    "sg:address":"217 Barton Street",
    "sg:city":"Gloucester",
    "sg:classifiers":[
        {
            "category":"Home & Garden",
            "subcategory":"Hardware",
            "type":"Retail Goods"
        }
    ],
    "sg:postcode":"GL1 4HY",
    "sg:province":"Gloucestershire",
    "wof:name":"Barton Hardware & Garden Shop",
    "wof:placetype":"venue"
},
  "geometry": {"coordinates":[-2.233746,51.859226],"type":"Point"}
}