{
  "type": "Feature",
  "properties": {
    "addr:full":"Healey Road Garage Ossett West Yorkshire WF5 8LT",
    "addr:postcode":"wf5 8lt",
    "addr:street":"Healey;West",
    "iso:country":"GB",
    "sg:address":"Healey Road Garage",
    "sg:city":"Ossett",
    "sg:classifiers":[
        {
            "category":"Retail",
            "subcategory":"Auto Repair",
            "type":"Services"
        }
    ],
    "sg:phone":"+44 1924 260736",
    "sg:postcode":"WF5 8LT",
    "sg:province":"West Yorkshire",
    "sg:tags":[
        "modification",
        "garage"
    ],
    "wof:name":"Auto Service Centre",
    "wof:placetype":"venue"
},
  "geometry": {"coordinates":[-1.578064,53.674335],"type":"Point"}
}