{
  "type": "Feature",
  "properties": {
    "addr:full":"Four Lane Ends, Benton Newcastle-upon-tyne Tyne and Wear NE7 7UJ",
    "addr:postcode":"ne7 7uj",
    "addr:street":"Four Lane Ends",
    "iso:country":"GB",
    "sg:address":"Four Lane Ends, Benton",
    "sg:city":"Newcastle-upon-tyne",
    "sg:classifiers":[
        {
            "category":"Organizations",
            "subcategory":"Membership Organization",
            "type":"Services"
        }
    ],
    "sg:phone":"+44 191 292 2332",
    "sg:postcode":"NE7 7UJ",
    "sg:province":"Tyne and Wear",
    "sg:tags":[
        "club"
    ],
    "wof:name":"Benton Conservative Club Ltd.",
    "wof:placetype":"venue"
},
  "geometry": {"coordinates":[-1.5759199858,55.0096206665],"type":"Point"}
}