{
  "type": "Feature",
  "properties": {
    "addr:full":"2 Bridge Street Caernarfon Gwynedd LL55 1AB",
    "addr:housenumber":"2",
    "addr:postcode":"ll55 1ab",
    "addr:street":"Bridge Street",
    "iso:country":"GB",
    "sg:address":"2 Bridge Street",
    "sg:city":"Caernarfon",
    "sg:classifiers":[
        {
            "category":"Shopping",
            "subcategory":"Pharmacy",
            "type":"Retail Goods"
        }
    ],
    "sg:phone":"+44 1286 672352",
    "sg:postcode":"LL55 1AB",
    "sg:province":"Gwynedd",
    "sg:tags":[
        "pharmacist",
        "dispensing",
        "chemist"
    ],
    "wof:name":"Castle Pharmacy",
    "wof:placetype":"venue"
},
  "geometry": {"coordinates":[-4.2740287781,53.140750885],"type":"Point"}
}