{
  "type": "Feature",
  "properties": {
    "iso:country":"GB",
    "sg:address":"227-229 Belgrave Gate",
    "sg:city":"Leicester",
    "sg:classifiers":[
        {
            "category":"Shopping",
            "subcategory":"Crafts & Fabrics",
            "type":"Retail Goods"
        },
        {
            "category":"Manufacturing",
            "subcategory":"Textiles",
            "type":"Manufacturing & Wholesale Goods"
        }
    ],
    "sg:phone":"+44 116 253 7560",
    "sg:postcode":"LE1 3HT",
    "sg:province":"Leicestershire",
    "sg:tags":[
        "knitwear",
        "producer"
    ],
    "wof:name":"Dee Kay Knitwear Ltd.",
    "wof:placetype":"venue"
},
  "geometry": {"coordinates":[-1.128445,52.642296],"type":"Point"}
}