{
  "type": "Feature",
  "properties": {
    "iso:country":"GB",
    "sg:address":"Fairmile Road",
    "sg:city":"Christchurch",
    "sg:classifiers":[
        {
            "category":"Organizations",
            "subcategory":"Non-profit Organization",
            "type":"Services"
        }
    ],
    "sg:phone":"+44 1202 477628",
    "sg:postcode":"BH23 2JX",
    "sg:province":"Dorset",
    "sg:tags":[
        "charitable",
        "organisation",
        "voluntary",
        "charity"
    ],
    "wof:name":"The Macmillan Cancer Trust",
    "wof:placetype":"venue"
},
  "geometry": {"coordinates":[-1.796088,50.750881],"type":"Point"}
}