{
  "type": "Feature",
  "properties": {
    "iso:country":"GB",
    "sg:address":"Unit 15, Midlands Industrial Estate, Holt",
    "sg:city":"Trowbridge",
    "sg:classifiers":[
        {
            "category":"Home & Garden",
            "subcategory":"Home Furnishings",
            "type":"Retail Goods"
        }
    ],
    "sg:postcode":"BA14 6RU",
    "sg:province":"Wiltshire",
    "sg:tags":[
        "awning",
        "canopy",
        "blinds"
    ],
    "wof:name":"Abacus Blinds",
    "wof:placetype":"venue"
},
  "geometry": {"coordinates":[-2.208374,51.315342],"type":"Point"}
}