{
  "type": "Feature",
  "properties": {
    "iso:country":"GB",
    "sg:address":"P O Box 224, Buxton",
    "sg:city":"Norwich",
    "sg:classifiers":[
        {
            "category":"Professional",
            "subcategory":"Detective & Security Services",
            "type":"Services"
        }
    ],
    "sg:phone":"+44 1263 735865",
    "sg:postcode":"NR10 5RX",
    "sg:province":"Norfolk",
    "sg:tags":[
        "equipment"
    ],
    "wof:name":"Osprey Products Ltd.",
    "wof:placetype":"venue"
},
  "geometry": {"coordinates":[1.30815,52.757038],"type":"Point"}
}