{
  "type": "Feature",
  "properties": {
    "iso:country":"GB",
    "sg:address":"12 Longfellow Grn",
    "sg:city":"Kidderminster",
    "sg:classifiers":[
        {
            "category":"Fast Food",
            "type":"Food & Drink"
        }
    ],
    "sg:phone":"+44 1562 69118",
    "sg:postcode":"DY10 3XZ",
    "sg:province":"Staffordshire",
    "sg:tags":[
        "away",
        "meal",
        "outlet",
        "take"
    ],
    "wof:name":"HONG KONG KITCHEN",
    "wof:placetype":"venue"
},
  "geometry": {"coordinates":[-2.222383976,52.3865852356],"type":"Point"}
}