{
  "type": "Feature",
  "properties": {
    "iso:country":"GB",
    "sg:address":"56 Sparrow Hill",
    "sg:city":"Loughborough",
    "sg:classifiers":[
        {
            "category":"Shopping",
            "subcategory":"Florist",
            "type":"Retail Goods"
        }
    ],
    "sg:phone":"+44 1509 232448",
    "sg:postcode":"LE11 1BU",
    "sg:province":"Leicestershire",
    "wof:name":"The Happy Apple",
    "wof:placetype":"venue"
},
  "geometry": {"coordinates":[-1.202674,52.773418],"type":"Point"}
}