{
  "type": "Feature",
  "properties": {
    "iso:country":"GB",
    "sg:address":"Meadow Place, Wellmeadow",
    "sg:city":"Blairgowrie",
    "sg:classifiers":[
        {
            "category":"Shopping",
            "subcategory":"News",
            "type":"Retail Goods"
        }
    ],
    "sg:postcode":"PH10 6NQ",
    "sg:province":"Perth and Kinross",
    "sg:tags":[
        "newsagent"
    ],
    "wof:name":"Meadow Newsagents",
    "wof:placetype":"venue"
},
  "geometry": {"coordinates":[-3.336929,56.591431],"type":"Point"}
}