{
  "type": "Feature",
  "properties": {
    "addr:full":"Auchterderran Centre, Woodend Road, Cardenden Lochgelly Fife KY5 0NE",
    "addr:postcode":"ky5 0ne",
    "addr:street":"Woodend Road;Lochgelly",
    "iso:country":"GB",
    "sg:address":"Auchterderran Centre, Woodend Road, Cardenden",
    "sg:city":"Lochgelly",
    "sg:classifiers":[
        {
            "category":"Education",
            "subcategory":"University",
            "type":"Public Place"
        }
    ],
    "sg:phone":"+44 1592 414738",
    "sg:postcode":"KY5 0NE",
    "sg:province":"Fife",
    "sg:tags":[
        "adult"
    ],
    "wof:name":"Fife Adult Guidance & Education Services",
    "wof:placetype":"venue"
},
  "geometry": {"coordinates":[-3.2639119625,56.1473617554],"type":"Point"}
}