{
  "type": "Feature",
  "properties": {
    "iso:country":"GB",
    "sg:address":"42-44 The Avenue",
    "sg:city":"Middlesbrough",
    "sg:classifiers":[
        {
            "category":"Shopping",
            "subcategory":"Florist",
            "type":"Retail Goods"
        }
    ],
    "sg:phone":"+44 1642 652020",
    "sg:postcode":"TS5 6PD",
    "sg:province":"North Yorkshire",
    "wof:name":"Fred Humphreys Florist",
    "wof:placetype":"venue"
},
  "geometry": {"coordinates":[-1.241289,54.55835],"type":"Point"}
}