{
  "type": "Feature",
  "properties": {
    "addr:full":"465 Andre Street London Greater London E8 2AA",
    "addr:housenumber":"465",
    "addr:postcode":"e8 2aa",
    "addr:street":"Andre Street",
    "iso:country":"GB",
    "sg:address":"465 Andre Street",
    "sg:city":"London",
    "sg:classifiers":[
        {
            "category":"Manufacturing",
            "subcategory":"Metals",
            "type":"Manufacturing & Wholesale Goods"
        }
    ],
    "sg:phone":"+44 20 7254 8496",
    "sg:postcode":"E8 2AA",
    "sg:province":"Greater London",
    "sg:tags":[
        "work",
        "sheet"
    ],
    "wof:name":"Hamit Sheet Metal Works",
    "wof:placetype":"venue"
},
  "geometry": {"coordinates":[-0.0638440028,51.5517654419],"type":"Point"}
}