{
  "type": "Feature",
  "properties": {
    "iso:country":"GB",
    "sg:address":"49 Southlea Rd",
    "sg:city":"Manchester",
    "sg:classifiers":[
        {
            "category":"Government",
            "subcategory":"Post Office",
            "type":"Public Place"
        }
    ],
    "sg:phone":"+44 161 448 1145",
    "sg:postcode":"M20 4TH",
    "sg:province":"Greater Manchester",
    "sg:tags":[
        "messenger",
        "courier"
    ],
    "wof:name":"A Wilson & Son",
    "wof:placetype":"venue"
},
  "geometry": {"coordinates":[-2.2152938843,53.4272232056],"type":"Point"}
}