{
  "type": "Feature",
  "properties": {
    "iso:country":"GB",
    "sg:address":"40 New Rd, Skewen",
    "sg:city":"Neath",
    "sg:classifiers":[
        {
            "category":"Insurance",
            "subcategory":"Insurance Agent",
            "type":"Services"
        }
    ],
    "sg:phone":"+44 1792 812378",
    "sg:postcode":"SA10 6EP",
    "sg:province":"Neath Port Talbot",
    "wof:name":"Cornerstone Financial Services",
    "wof:placetype":"venue"
},
  "geometry": {"coordinates":[-3.842044,51.661167],"type":"Point"}
}