{
  "type": "Feature",
  "properties": {
    "iso:country":"GB",
    "sg:address":"83 Albert Road",
    "sg:city":"Blackpool",
    "sg:classifiers":[
        {
            "category":"Travel",
            "subcategory":"Hotels & Motels",
            "type":"Entertainment"
        }
    ],
    "sg:phone":"+44 1253 623071",
    "sg:postcode":"FY1 4PW",
    "sg:province":"Lancashire",
    "wof:name":"Oak Lea Hotel",
    "wof:placetype":"venue"
},
  "geometry": {"coordinates":[-3.049628,53.815708],"type":"Point"}
}