{
  "type": "Feature",
  "properties": {
    "addr:full":"Birmingham Road Alcester Warwickshire B49 5ED",
    "addr:postcode":"b49 5ed",
    "addr:street":"Birmingham Road",
    "iso:country":"GB",
    "sg:address":"Birmingham Road",
    "sg:city":"Alcester",
    "sg:classifiers":[
        {
            "category":"Education",
            "subcategory":"School",
            "type":"Public Place"
        }
    ],
    "sg:phone":"+44 1789 762494",
    "sg:postcode":"B49 5ED",
    "sg:province":"Warwickshire",
    "sg:tags":[
        "foundation",
        "college"
    ],
    "wof:name":"Alcester Grammar School",
    "wof:placetype":"venue"
},
  "geometry": {"coordinates":[-1.877557,52.220829],"type":"Point"}
}