{
  "type": "Feature",
  "properties": {
    "iso:country":"GB",
    "sg:address":"59 Coronation Ave",
    "sg:city":"Peterborough",
    "sg:classifiers":[
        {
            "category":"Building & Trades",
            "subcategory":"Construction",
            "type":"Services"
        }
    ],
    "sg:postcode":"PE7 1XD",
    "sg:province":"Cambridgeshire",
    "sg:tags":[
        "builder"
    ],
    "wof:name":"Butler,Brian,",
    "wof:placetype":"venue"
},
  "geometry": {"coordinates":[-0.116595,52.5591125488],"type":"Point"}
}