{
  "type": "Feature",
  "properties": {
    "addr:full":"Kelvin Gro, Marus Bridge Wigan Lancashire WN3 6SP",
    "addr:postcode":"wn3 6sp",
    "addr:street":"Marus Bridge",
    "iso:country":"GB",
    "sg:address":"Kelvin Gro, Marus Bridge",
    "sg:city":"Wigan",
    "sg:classifiers":[
        {
            "category":"Education",
            "subcategory":"Special Training",
            "type":"Public Place"
        }
    ],
    "sg:phone":"+44 1942 824150",
    "sg:postcode":"WN3 6SP",
    "sg:province":"Lancashire",
    "sg:tags":[
        "school"
    ],
    "wof:name":"Wigan Metropolitan Borough Council",
    "wof:placetype":"venue"
},
  "geometry": {"coordinates":[-2.6574299335,53.5211791992],"type":"Point"}
}