{
  "type": "Feature",
  "properties": {
    "addr:full":"The Square, Ryhall Stamford Cambridgeshire PE9 4HJ",
    "addr:postcode":"pe9 4hj",
    "addr:street":"The Square",
    "iso:country":"GB",
    "sg:address":"The Square, Ryhall",
    "sg:city":"Stamford",
    "sg:classifiers":[
        {
            "category":"Government",
            "subcategory":"Post Office",
            "type":"Public Place"
        }
    ],
    "sg:phone":"+44 1780 763572",
    "sg:postcode":"PE9 4HJ",
    "sg:province":"Cambridgeshire",
    "wof:name":"Ryhall Sub Post Office",
    "wof:placetype":"venue"
},
  "geometry": {"coordinates":[-0.4675599933,52.6855506897],"type":"Point"}
}