{
  "type": "Feature",
  "properties": {
    "iso:country":"GB",
    "sg:address":"121-23 High Street, Gosforth",
    "sg:city":"Newcastle-upon-tyne",
    "sg:classifiers":[
        {
            "category":"Restaurant",
            "type":"Food & Drink"
        }
    ],
    "sg:phone":"+44 191 213 0399",
    "sg:postcode":"NE3 1HA",
    "sg:province":"Tyne and Wear",
    "sg:tags":[
        "italian"
    ],
    "wof:name":"Made in Italy",
    "wof:placetype":"venue"
},
  "geometry": {"coordinates":[-1.6204659939,55.0042800903],"type":"Point"}
}