{
  "type": "Feature",
  "properties": {
    "iso:country":"GB",
    "sg:address":"394 Ashton Rd",
    "sg:city":"Oldham",
    "sg:classifiers":[
        {
            "category":"Shopping",
            "subcategory":"Department Store",
            "type":"Retail Goods"
        }
    ],
    "sg:phone":"+44 161 652 7891",
    "sg:postcode":"OL8 3HF",
    "sg:province":"Lancashire",
    "wof:name":"Roy Power",
    "wof:placetype":"venue"
},
  "geometry": {"coordinates":[-2.111179,53.525513],"type":"Point"}
}