{
  "type": "Feature",
  "properties": {
    "addr:full":"Meon Dental Practice, 27 High St Petersfield Hampshire GU32 3JR",
    "addr:housenumber":"27",
    "addr:postcode":"gu32 3jr",
    "addr:street":"High St",
    "iso:country":"GB",
    "sg:address":"Meon Dental Practice, 27 High St",
    "sg:city":"Petersfield",
    "sg:classifiers":[
        {
            "category":"Health Services",
            "subcategory":"Dentist",
            "type":"Services"
        }
    ],
    "sg:phone":"+44 1730 265555",
    "sg:postcode":"GU32 3JR",
    "sg:province":"Hampshire",
    "wof:name":"N May",
    "wof:placetype":"venue"
},
  "geometry": {"coordinates":[-0.935826,51.003796],"type":"Point"}
}