{
  "type": "Feature",
  "properties": {
    "iso:country":"GB",
    "sg:address":"Unit K4 Pride Hill Centre",
    "sg:city":"Shrewsbury",
    "sg:classifiers":[
        {
            "category":"Shopping",
            "subcategory":"Crafts & Fabrics",
            "type":"Retail Goods"
        }
    ],
    "sg:postcode":"SY1 1BU",
    "sg:province":"Shropshire",
    "sg:tags":[
        "material",
        "art"
    ],
    "wof:name":"The Crystal Man",
    "wof:placetype":"venue"
},
  "geometry": {"coordinates":[-2.752894,52.70882],"type":"Point"}
}