{
  "type": "Feature",
  "properties": {
    "iso:country":"GB",
    "sg:address":"Warmco Industrial Estate Manchester Road, Mossley",
    "sg:city":"Ashton-under-lyne",
    "sg:classifiers":[
        {
            "category":"Retail",
            "subcategory":"Auto Repair",
            "type":"Services"
        }
    ],
    "sg:phone":"+44 1457 834266",
    "sg:postcode":"OL5 9XA",
    "sg:province":"Greater Manchester",
    "sg:tags":[
        "modification",
        "garage"
    ],
    "wof:name":"Kg Myatt",
    "wof:placetype":"venue"
},
  "geometry": {"coordinates":[-2.04125,53.517082],"type":"Point"}
}