{
  "type": "Feature",
  "properties": {
    "iso:country":"GB",
    "sg:address":"Main Street",
    "sg:city":"Strathcarron",
    "sg:classifiers":[
        {
            "category":"Food & Beverages",
            "subcategory":"Meat & Fish",
            "type":"Retail Goods"
        }
    ],
    "sg:postcode":"IV54 8YD",
    "sg:province":"Highland",
    "sg:tags":[
        "butcher"
    ],
    "wof:name":"Rod Maclennan & Son",
    "wof:placetype":"venue"
},
  "geometry": {"coordinates":[-5.428674,57.423656],"type":"Point"}
}