{
  "type": "Feature",
  "properties": {
    "iso:country":"GB",
    "sg:address":"Unit S Springhead Enterprise Park, Northfleet",
    "sg:city":"Gravesend",
    "sg:classifiers":[
        {
            "category":"Manufacturing",
            "subcategory":"Building Materials",
            "type":"Manufacturing & Wholesale Goods"
        }
    ],
    "sg:phone":"+44 1474 369600",
    "sg:postcode":"DA11 8HJ",
    "sg:province":"Kent",
    "sg:tags":[
        "tile",
        "mnfrs"
    ],
    "wof:name":"Tile Magic Plc",
    "wof:placetype":"venue"
},
  "geometry": {"coordinates":[0.3326700032,51.4360084534],"type":"Point"}
}