{
  "type": "Feature",
  "properties": {
    "iso:country":"GB",
    "sg:address":"26 Stanley Road",
    "sg:city":"Newbury",
    "sg:classifiers":[
        {
            "category":"Professional",
            "subcategory":"Engineering",
            "type":"Services"
        }
    ],
    "sg:phone":"+44 1296 436778",
    "sg:postcode":"RG14 7PB",
    "sg:province":"Berkshire",
    "sg:tags":[
        "pneumatic",
        "engineer"
    ],
    "wof:name":"Activ-Air Automation Ltd.",
    "wof:placetype":"venue"
},
  "geometry": {"coordinates":[-1.314447999,51.3975868225],"type":"Point"}
}