{
  "type": "Feature",
  "properties": {
    "iso:country":"GB",
    "sg:address":"8 Fairway Dr",
    "sg:city":"Greenford",
    "sg:classifiers":[
        {
            "category":"Personal",
            "type":"Services"
        }
    ],
    "sg:phone":"+44 20 8813 0341",
    "sg:postcode":"UB6 8PW",
    "sg:province":"Greater London",
    "sg:tags":[
        "delivery"
    ],
    "wof:name":"TNT Contract Services",
    "wof:placetype":"venue"
},
  "geometry": {"coordinates":[-0.357932,51.54356],"type":"Point"}
}