{
  "type": "Feature",
  "properties": {
    "addr:full":"Broadlands House, Hazelwood Drive, St Mellons Cardiff Caerphilly CF3 0NS",
    "addr:postcode":"cf3 0ns",
    "addr:street":"Hazelwood Drive",
    "iso:country":"GB",
    "sg:address":"Broadlands House, Hazelwood Drive, St Mellons",
    "sg:city":"Cardiff",
    "sg:classifiers":[
        {
            "category":"Social Services",
            "subcategory":"Adult Care",
            "type":"Services"
        },
        {
            "category":"Government",
            "subcategory":"Office",
            "type":"Public Place"
        }
    ],
    "sg:phone":"+44 29 2077 7751",
    "sg:postcode":"CF3 0NS",
    "sg:province":"Caerphilly",
    "sg:tags":[
        "housing",
        "local",
        "sheltered"
    ],
    "wof:name":"Broadlands House Sheltered Housing",
    "wof:placetype":"venue"
},
  "geometry": {"coordinates":[-3.1064610481,51.5265007019],"type":"Point"}
}