{
  "type": "Feature",
  "properties": {
    "addr:full":"2 Queen Street Pontefract North Yorkshire WF8 4AF",
    "addr:housenumber":"2",
    "addr:postcode":"wf8 4af",
    "addr:street":"Queen Street",
    "iso:country":"GB",
    "sg:address":"2 Queen Street",
    "sg:city":"Pontefract",
    "sg:classifiers":[
        {
            "category":"Personal",
            "subcategory":"Beauty Salon",
            "type":"Services"
        }
    ],
    "sg:postcode":"WF8 4AF",
    "sg:province":"North Yorkshire",
    "sg:tags":[
        "unisex",
        "hairdresser"
    ],
    "wof:name":"Koronet",
    "wof:placetype":"venue"
},
  "geometry": {"coordinates":[-1.3189690113,53.6900634766],"type":"Point"}
}