{
  "type": "Feature",
  "properties": {
    "iso:country":"GB",
    "sg:address":"4 Medfield Street",
    "sg:city":"London",
    "sg:classifiers":[
        {
            "category":"Food & Beverages",
            "subcategory":"Liquor & Beverages",
            "type":"Retail Goods"
        }
    ],
    "sg:phone":"+44 20 8788 0361",
    "sg:postcode":"SW15 4JZ",
    "sg:province":"Greater London",
    "sg:tags":[
        "beer",
        "spirit",
        "wines"
    ],
    "wof:name":"Thresher Wine Merchants",
    "wof:placetype":"venue"
},
  "geometry": {"coordinates":[-0.239179,51.449631],"type":"Point"}
}