{
  "type": "Feature",
  "properties": {
    "iso:country":"GB",
    "sg:address":"34 Belmont Lane",
    "sg:city":"Chislehurst",
    "sg:classifiers":[
        {
            "category":"Building & Trades",
            "subcategory":"Construction",
            "type":"Services"
        }
    ],
    "sg:phone":"+44 20 8467 0551",
    "sg:postcode":"BR7 6BJ",
    "sg:province":"Kent",
    "sg:tags":[
        "surfacing",
        "road"
    ],
    "wof:name":"Orchman Contractors",
    "wof:placetype":"venue"
},
  "geometry": {"coordinates":[0.0702409968,51.4214897156],"type":"Point"}
}