{
  "type": "Feature",
  "properties": {
    "iso:country":"GB",
    "sg:address":"W.r.v.s Building, Crampton Tower",
    "sg:city":"Broadstairs",
    "sg:classifiers":[
        {
            "category":"Organizations",
            "subcategory":"Non-profit Organization",
            "type":"Services"
        }
    ],
    "sg:phone":"+44 1843 867470",
    "sg:postcode":"CT10 2AB",
    "sg:province":"Kent",
    "sg:tags":[
        "organisation",
        "voluntary",
        "charity"
    ],
    "wof:name":"Women's Royal Voluntary Service",
    "wof:placetype":"venue"
},
  "geometry": {"coordinates":[1.43331,51.359798],"type":"Point"}
}