{
  "type": "Feature",
  "properties": {
    "addr:full":"48 Navarino Road Worthing West Sussex BN11 2NF",
    "addr:housenumber":"48",
    "addr:postcode":"bn11 2nf",
    "addr:street":"Navarino Road",
    "iso:country":"GB",
    "sg:address":"48 Navarino Road",
    "sg:city":"Worthing",
    "sg:classifiers":[
        {
            "category":"Building & Trades",
            "subcategory":"Construction",
            "type":"Services"
        }
    ],
    "sg:postcode":"BN11 2NF",
    "sg:province":"West Sussex",
    "sg:tags":[
        "tiling",
        "contractor"
    ],
    "wof:name":"Clive B Innes",
    "wof:placetype":"venue"
},
  "geometry": {"coordinates":[-0.3527809978,50.8146247864],"type":"Point"}
}