{
  "type": "Feature",
  "properties": {
    "addr:full":"13 Heathfield, Stacey Bushes Milton Keynes Buckinghamshire MK12 6HP",
    "addr:housenumber":"13",
    "addr:postcode":"mk12 6hp",
    "addr:street":"Heathfield Stacey",
    "iso:country":"GB",
    "sg:address":"13 Heathfield, Stacey Bushes",
    "sg:city":"Milton Keynes",
    "sg:classifiers":[
        {
            "category":"Wholesale",
            "subcategory":"Construction Materials",
            "type":"Manufacturing & Wholesale Goods"
        }
    ],
    "sg:phone":"+44 1908 220347",
    "sg:postcode":"MK12 6HP",
    "sg:province":"Buckinghamshire",
    "sg:tags":[
        "coating",
        "powder"
    ],
    "wof:name":"Colourtone Stove Enamellers & Powder Coaters",
    "wof:placetype":"venue"
},
  "geometry": {"coordinates":[-0.803687,52.049587],"type":"Point"}
}