{
  "type": "Feature",
  "properties": {
    "addr:full":"53-54 Queens Road Hastings East Sussex TN34 1RE",
    "addr:housenumber":"53-54",
    "addr:postcode":"tn34 1re",
    "addr:street":"Queens Road",
    "iso:country":"GB",
    "sg:address":"53-54 Queens Road",
    "sg:city":"Hastings",
    "sg:classifiers":[
        {
            "category":"Shopping",
            "subcategory":"Crafts & Fabrics",
            "type":"Retail Goods"
        }
    ],
    "sg:phone":"+44 1424 423108",
    "sg:postcode":"TN34 1RE",
    "sg:province":"East Sussex",
    "sg:tags":[
        "machine",
        "sewing",
        "knitting"
    ],
    "wof:name":"Hastings Sewing Centre",
    "wof:placetype":"venue"
},
  "geometry": {"coordinates":[0.583211,50.858414],"type":"Point"}
}