{
  "type": "Feature",
  "properties": {
    "iso:country":"GB",
    "sg:address":"Unit 11 Leeholme Road",
    "sg:city":"Billingham",
    "sg:classifiers":[
        {
            "category":"Ice Cream",
            "type":"Food & Drink"
        }
    ],
    "sg:phone":"+44 1642 658010",
    "sg:postcode":"TS23 3TA",
    "sg:province":"Durham",
    "sg:tags":[
        "mnfr"
    ],
    "wof:name":"D Currie",
    "wof:placetype":"venue"
},
  "geometry": {"coordinates":[-1.2818000317,54.6068000793],"type":"Point"}
}