{
  "type": "Feature",
  "properties": {
    "addr:full":"67 Cubbington Road Leamington Spa Warwickshire CV32 7AQ",
    "addr:housenumber":"67",
    "addr:postcode":"cv32 7aq",
    "addr:street":"Cubbington Road",
    "iso:country":"GB",
    "sg:address":"67 Cubbington Road",
    "sg:city":"Leamington Spa",
    "sg:classifiers":[
        {
            "category":"Health Services",
            "subcategory":"Health Practitioner",
            "type":"Services"
        }
    ],
    "sg:phone":"+44 1926 421928",
    "sg:postcode":"CV32 7AQ",
    "sg:province":"Warwickshire",
    "sg:tags":[
        "psychotherapist"
    ],
    "wof:name":"Rosemary Clarke",
    "wof:placetype":"venue"
},
  "geometry": {"coordinates":[-1.52282,52.30294],"type":"Point"}
}