{
  "type": "Feature",
  "properties": {
    "addr:full":"38 Victoria Street Bristol City of Bristol BS1 6BY",
    "addr:housenumber":"38",
    "addr:postcode":"bs1 6by",
    "addr:street":"Victoria Street",
    "iso:country":"GB",
    "sg:address":"38 Victoria Street",
    "sg:city":"Bristol",
    "sg:classifiers":[
        {
            "category":"Organizations",
            "subcategory":"Non-profit Organization",
            "type":"Services"
        }
    ],
    "sg:phone":"+44 117 922 5353",
    "sg:postcode":"BS1 6BY",
    "sg:province":"City of Bristol",
    "sg:tags":[
        "organisation",
        "voluntary",
        "charity"
    ],
    "wof:name":"Age Concern Bristol",
    "wof:placetype":"venue"
},
  "geometry": {"coordinates":[-2.5883491039,51.4524230957],"type":"Point"}
}