{
  "type": "Feature",
  "properties": {
    "addr:full":"Clow Beck House, Monk End Farm Darlington Durham DL2 2SW",
    "addr:postcode":"dl2 2sw",
    "addr:street":"Darlington",
    "iso:country":"GB",
    "sg:address":"Clow Beck House, Monk End Farm",
    "sg:city":"Darlington",
    "sg:classifiers":[
        {
            "category":"Travel",
            "subcategory":"Hotels & Motels",
            "type":"Entertainment"
        }
    ],
    "sg:phone":"+44 1325 721075",
    "sg:postcode":"DL2 2SW",
    "sg:province":"Durham",
    "sg:tags":[
        "house",
        "guest"
    ],
    "wof:name":"D & H (Monk End) Ltd.",
    "wof:placetype":"venue"
},
  "geometry": {"coordinates":[-1.561282,54.484158],"type":"Point"}
}