{
  "type": "Feature",
  "properties": {
    "addr:full":"11 Winding Shott, Bramfield Hertford Hertfordshire SG14 2QP",
    "addr:housenumber":"11",
    "addr:postcode":"sg14 2qp",
    "addr:street":"Winding Shott",
    "iso:country":"GB",
    "sg:address":"11 Winding Shott, Bramfield",
    "sg:city":"Hertford",
    "sg:classifiers":[
        {
            "category":"Professional",
            "subcategory":"Advertising",
            "type":"Services"
        }
    ],
    "sg:phone":"+44 1992 503662",
    "sg:postcode":"SG14 2QP",
    "sg:province":"Hertfordshire",
    "sg:tags":[
        "agency"
    ],
    "wof:name":"Versaltile Wordsmith",
    "wof:placetype":"venue"
},
  "geometry": {"coordinates":[-0.126222,51.82383],"type":"Point"}
}