{
  "type": "Feature",
  "properties": {
    "addr:full":"32 Taff Vale Shopping Centre Pontypridd Caerphilly CF37 4TH",
    "addr:housenumber":"32",
    "addr:postcode":"cf37 4th",
    "addr:street":"Taff Vale Shopping Centre",
    "iso:country":"GB",
    "sg:address":"32 Taff Vale Shopping Centre",
    "sg:city":"Pontypridd",
    "sg:classifiers":[
        {
            "category":"Building & Trades",
            "subcategory":"Landscaping Services",
            "type":"Services"
        }
    ],
    "sg:phone":"+44 1443 403202",
    "sg:postcode":"CF37 4TH",
    "sg:province":"Caerphilly",
    "sg:tags":[
        "pond",
        "aquarium"
    ],
    "wof:name":"Tropical Fish Centre",
    "wof:placetype":"venue"
},
  "geometry": {"coordinates":[-3.3397760391,51.6047439575],"type":"Point"}
}