{
  "type": "Feature",
  "properties": {
    "iso:country":"GB",
    "sg:address":"Care Of Kings Centre, Raglan Rd",
    "sg:city":"Sale",
    "sg:classifiers":[
        {
            "category":"Professional",
            "subcategory":"Lawyer & Legal Services",
            "type":"Services"
        }
    ],
    "sg:phone":"+44 161 747 7880",
    "sg:postcode":"M33 4AQ",
    "sg:province":"Cheshire",
    "sg:tags":[
        "advice",
        "counselling"
    ],
    "wof:name":"Cross Roads Christian Counselling",
    "wof:placetype":"venue"
},
  "geometry": {"coordinates":[-2.3204169273,53.4259490967],"type":"Point"}
}