{
  "type": "Feature",
  "properties": {
    "addr:full":"6 The Betchworth, Reigate Road Betchworth Surrey RH3 7ET",
    "addr:housenumber":"6",
    "addr:postcode":"rh3 7et",
    "addr:street":"The Betchworth Reigate Road",
    "iso:country":"GB",
    "sg:address":"6 The Betchworth, Reigate Road",
    "sg:city":"Betchworth",
    "sg:classifiers":[
        {
            "category":"Building & Trades",
            "subcategory":"Landscaping Services",
            "type":"Services"
        }
    ],
    "sg:postcode":"RH3 7ET",
    "sg:province":"Surrey",
    "sg:tags":[
        "design",
        "gardening",
        "garden"
    ],
    "wof:name":"1 To One Garden Design",
    "wof:placetype":"venue"
},
  "geometry": {"coordinates":[-0.2677980065,51.235206604],"type":"Point"}
}