{
  "type": "Feature",
  "properties": {
    "addr:full":"Thirsk Junction Thirsk North Yorkshire YO7 4LT",
    "addr:postcode":"yo7 4lt",
    "iso:country":"GB",
    "sg:address":"Thirsk Junction",
    "sg:city":"Thirsk",
    "sg:classifiers":[
        {
            "category":"Travel",
            "subcategory":"Hotels & Motels",
            "type":"Entertainment"
        }
    ],
    "sg:phone":"+44 1845 524383",
    "sg:postcode":"YO7 4LT",
    "sg:province":"North Yorkshire",
    "wof:name":"The Old Red House Hotel",
    "wof:placetype":"venue"
},
  "geometry": {"coordinates":[-1.3422529697,54.2326889038],"type":"Point"}
}