{
  "type": "Feature",
  "properties": {
    "addr:full":"169 Brunshaw Avenue Burnley Lancashire BB10 4NQ",
    "addr:housenumber":"169",
    "addr:postcode":"bb10 4nq",
    "addr:street":"Brunshaw Avenue",
    "iso:country":"GB",
    "sg:address":"169 Brunshaw Avenue",
    "sg:city":"Burnley",
    "sg:classifiers":[
        {
            "category":"Building & Trades",
            "subcategory":"Construction",
            "type":"Services"
        }
    ],
    "sg:phone":"+44 1282 433893",
    "sg:postcode":"BB10 4NQ",
    "sg:province":"Lancashire",
    "sg:tags":[
        "builder"
    ],
    "wof:name":"P & C Pointing",
    "wof:placetype":"venue"
},
  "geometry": {"coordinates":[-2.2133510113,53.7845726013],"type":"Point"}
}