{
  "type": "Feature",
  "properties": {
    "iso:country":"GB",
    "sg:address":"30 Royal York Crescent",
    "sg:city":"Bristol",
    "sg:classifiers":[
        {
            "category":"Communications",
            "type":"Services"
        }
    ],
    "sg:postcode":"BS8 4JX",
    "sg:province":"City of Bristol",
    "sg:tags":[
        "broadcasting"
    ],
    "wof:name":"J P T Media Associates Ltd.",
    "wof:placetype":"venue"
},
  "geometry": {"coordinates":[-2.621126,51.453815],"type":"Point"}
}