{
  "type": "Feature",
  "properties": {
    "addr:full":"Beechlyn, Slade, Bucklebury Reading Berkshire RG7 6TE",
    "addr:postcode":"rg7 6te",
    "addr:street":"Beechlyn",
    "iso:country":"GB",
    "sg:address":"Beechlyn, Slade, Bucklebury",
    "sg:city":"Reading",
    "sg:classifiers":[
        {
            "category":"Freight",
            "type":"Transportation"
        }
    ],
    "sg:phone":"+44 1635 863437",
    "sg:postcode":"RG7 6TE",
    "sg:province":"Berkshire",
    "sg:tags":[
        "haulage",
        "road"
    ],
    "wof:name":"J.S Paulin",
    "wof:placetype":"venue"
},
  "geometry": {"coordinates":[-1.2064930201,51.4351654053],"type":"Point"}
}