{
  "type": "Feature",
  "properties": {
    "iso:country":"GB",
    "sg:address":"73 Pen Yr Alltwen, Alltwen, Pontardawe",
    "sg:city":"Swansea",
    "sg:classifiers":[
        {
            "category":"Building & Trades",
            "subcategory":"Construction",
            "type":"Services"
        }
    ],
    "sg:phone":"+44 1792 830582",
    "sg:postcode":"SA8 3EA",
    "sg:province":"Neath Port Talbot",
    "sg:tags":[
        "roofing"
    ],
    "wof:name":"Alltwen Building & Roofing Contractors Ltd.",
    "wof:placetype":"venue"
},
  "geometry": {"coordinates":[-3.837795,51.715309],"type":"Point"}
}