{
  "type": "Feature",
  "properties": {
    "addr:full":"Unit 111, 3rd Street, Newgreemham Park Newbury Berkshire RG14 6HN",
    "addr:housenumber":"111",
    "addr:postcode":"rg14 6hn",
    "addr:street":"3Rd Street;Newbury",
    "iso:country":"GB",
    "sg:address":"Unit 111, 3rd Street, Newgreemham Park",
    "sg:city":"Newbury",
    "sg:classifiers":[
        {
            "category":"Home & Garden",
            "subcategory":"Home Furnishings",
            "type":"Retail Goods"
        }
    ],
    "sg:phone":"+44 1635 44383",
    "sg:postcode":"RG14 6HN",
    "sg:province":"Berkshire",
    "sg:tags":[
        "beds",
        "bedding",
        "blanket"
    ],
    "wof:name":"Home Comforts",
    "wof:placetype":"venue"
},
  "geometry": {"coordinates":[-1.325872,51.405872],"type":"Point"}
}