{
  "type": "Feature",
  "properties": {
    "iso:country":"GB",
    "sg:address":"184 Bebington Road, Bebington",
    "sg:city":"Wirral",
    "sg:classifiers":[
        {
            "category":"Restaurant",
            "type":"Food & Drink"
        }
    ],
    "sg:phone":"+44 151 643 8600",
    "sg:postcode":"CH63 7NX",
    "sg:province":"Merseyside",
    "sg:tags":[
        "indian"
    ],
    "wof:name":"Alam Balti House",
    "wof:placetype":"venue"
},
  "geometry": {"coordinates":[-3.004098,53.355911],"type":"Point"}
}