{
  "type": "Feature",
  "properties": {
    "addr:full":"20 Edenfield Rd Knutsford Cheshire WA16 7HE",
    "addr:housenumber":"20",
    "addr:postcode":"wa16 7he",
    "addr:street":"Edenfield Rd",
    "iso:country":"GB",
    "sg:address":"20 Edenfield Rd",
    "sg:city":"Knutsford",
    "sg:classifiers":[
        {
            "category":"Professional",
            "subcategory":"Computer Services",
            "type":"Services"
        }
    ],
    "sg:phone":"+44 1565 873364",
    "sg:postcode":"WA16 7HE",
    "sg:province":"Cheshire",
    "sg:tags":[
        "system",
        "software"
    ],
    "wof:name":"C A B Computers",
    "wof:placetype":"venue"
},
  "geometry": {"coordinates":[-2.330477953,53.3128051758],"type":"Point"}
}