{
  "type": "Feature",
  "properties": {
    "addr:full":"58 Channings 215 Kingsway Hove East Sussex BN3 4FU",
    "addr:housenumber":"58;215",
    "addr:postcode":"bn3 4fu",
    "addr:street":"Channings;Kingsway Hove",
    "iso:country":"GB",
    "sg:address":"58 Channings 215 Kingsway",
    "sg:city":"Hove",
    "sg:classifiers":[
        {
            "category":"Professional",
            "subcategory":"Art Services",
            "type":"Services"
        }
    ],
    "sg:phone":"+44 1273 779422",
    "sg:postcode":"BN3 4FU",
    "sg:province":"East Sussex",
    "sg:tags":[
        "photographer"
    ],
    "wof:name":"Peter O'bryne",
    "wof:placetype":"venue"
},
  "geometry": {"coordinates":[-0.182449,50.838943],"type":"Point"}
}