{
  "type": "Feature",
  "properties": {
    "iso:country":"GB",
    "sg:address":"9 New Walk, Kingfisher Shopping Centre",
    "sg:city":"Redditch",
    "sg:classifiers":[
        {
            "category":"Shopping",
            "subcategory":"Shoes",
            "type":"Retail Goods"
        }
    ],
    "sg:phone":"+44 1527 69546",
    "sg:postcode":"B97 4YP",
    "sg:province":"Warwickshire",
    "wof:name":"Timpson Shoe Repairs",
    "wof:placetype":"venue"
},
  "geometry": {"coordinates":[-1.941267,52.30727],"type":"Point"}
}