{
  "type": "Feature",
  "properties": {
    "addr:full":"Qantel Ho, Anglia Way,, Moulton Pk, Northampton Northamptonshire NN3 6JA",
    "addr:postcode":"nn3 6ja",
    "addr:street":"Anglia Way",
    "iso:country":"GB",
    "sg:address":"Qantel Ho, Anglia Way,, Moulton Pk,",
    "sg:city":"Northampton",
    "sg:classifiers":[
        {
            "category":"Professional",
            "subcategory":"Computer Services",
            "type":"Services"
        }
    ],
    "sg:postcode":"NN3 6JA",
    "sg:province":"Northamptonshire",
    "sg:tags":[
        "system",
        "software"
    ],
    "wof:name":"Open Software Ltd",
    "wof:placetype":"venue"
},
  "geometry": {"coordinates":[-0.8733299971,52.2750091553],"type":"Point"}
}