{
  "type": "Feature",
  "properties": {
    "iso:country":"GB",
    "sg:address":"36a Victoria Rd, Netherfield",
    "sg:city":"Nottingham",
    "sg:classifiers":[
        {
            "category":"Recreation",
            "subcategory":"Amusement Park",
            "type":"Entertainment"
        }
    ],
    "sg:postcode":"NG4 2HE",
    "sg:province":"Nottinghamshire",
    "sg:tags":[
        "arcade"
    ],
    "wof:name":"Play One Amusements",
    "wof:placetype":"venue"
},
  "geometry": {"coordinates":[-1.0783319473,52.963722229],"type":"Point"}
}