{
  "type": "Feature",
  "properties": {
    "iso:country":"GB",
    "sg:address":"39 Fore St",
    "sg:city":"Fowey",
    "sg:classifiers":[
        {
            "category":"Food & Beverages",
            "subcategory":"Groceries & Convenience Stores",
            "type":"Retail Goods"
        }
    ],
    "sg:phone":"+44 1726 833356",
    "sg:postcode":"PL23 1AH",
    "sg:province":"Cornwall",
    "wof:name":"Spar Food Stores",
    "wof:placetype":"venue"
},
  "geometry": {"coordinates":[-4.634232,50.336308],"type":"Point"}
}