{
  "type": "Feature",
  "properties": {
    "addr:full":"72a Middle Street Brighton East Sussex BN1 1AL",
    "addr:housenumber":"72a",
    "addr:postcode":"bn1 1al",
    "addr:street":"Middle Street",
    "iso:country":"GB",
    "sg:address":"72a Middle Street",
    "sg:city":"Brighton",
    "sg:classifiers":[
        {
            "category":"Professional",
            "type":"Services"
        },
        {
            "category":"Professional",
            "subcategory":"Computer Services",
            "type":"Services"
        }
    ],
    "sg:phone":"+44 1273 773538",
    "sg:postcode":"BN1 1AL",
    "sg:province":"East Sussex",
    "sg:tags":[
        "repair",
        "tech",
        "system",
        "maintenance",
        "software"
    ],
    "wof:name":"C G Tech",
    "wof:placetype":"venue"
},
  "geometry": {"coordinates":[-0.143094,50.820808],"type":"Point"}
}