{
  "type": "Feature",
  "properties": {
    "iso:country":"GB",
    "sg:address":"Hammond Clo",
    "sg:city":"Newmarket",
    "sg:classifiers":[
        {
            "category":"Farming",
            "subcategory":"Dairy Farm",
            "type":"Manufacturing & Wholesale Goods"
        }
    ],
    "sg:phone":"+44 1638 662066",
    "sg:postcode":"CB8 0AZ",
    "sg:province":"Cambridgeshire",
    "wof:name":"MD Foods",
    "wof:placetype":"venue"
},
  "geometry": {"coordinates":[0.3885650039,52.2575187683],"type":"Point"}
}