{
  "type": "Feature",
  "properties": {
    "iso:country":"GB",
    "sg:address":"53 Well Hall Road",
    "sg:city":"London",
    "sg:classifiers":[
        {
            "category":"Shopping",
            "subcategory":"News",
            "type":"Retail Goods"
        }
    ],
    "sg:phone":"+44 20 8850 4310",
    "sg:postcode":"SE9 6SZ",
    "sg:province":"Greater London",
    "sg:tags":[
        "newsagent"
    ],
    "wof:name":"Raj News",
    "wof:placetype":"venue"
},
  "geometry": {"coordinates":[0.049934,51.457447],"type":"Point"}
}