{
  "type": "Feature",
  "properties": {
    "addr:full":"71 Oakfield Road Croydon Surrey CR0 2UX",
    "addr:housenumber":"71",
    "addr:postcode":"cr0 2ux",
    "addr:street":"Oakfield Road",
    "iso:country":"GB",
    "sg:address":"71 Oakfield Road",
    "sg:city":"Croydon",
    "sg:classifiers":[
        {
            "category":"Organizations",
            "subcategory":"Membership Organization",
            "type":"Services"
        }
    ],
    "sg:phone":"+44 20 8686 8388",
    "sg:postcode":"CR0 2UX",
    "sg:province":"Surrey",
    "sg:tags":[
        "club"
    ],
    "wof:name":"Provincial Grand Chapter of Surrey",
    "wof:placetype":"venue"
},
  "geometry": {"coordinates":[-0.100055,51.382847],"type":"Point"}
}