{
  "type": "Feature",
  "properties": {
    "addr:full":"First Avenue, Royal Portbury Dock, Portbury Bristol Somerset BS20 7XS",
    "addr:postcode":"bs20 7xs",
    "addr:street":"First Avenue Royal Portbury",
    "iso:country":"GB",
    "sg:address":"First Avenue, Royal Portbury Dock, Portbury",
    "sg:city":"Bristol",
    "sg:classifiers":[
        {
            "category":"Shopping",
            "type":"Retail Goods"
        }
    ],
    "sg:phone":"+44 1749 673271",
    "sg:postcode":"BS20 7XS",
    "sg:province":"Somerset",
    "sg:tags":[
        "merchant"
    ],
    "wof:name":"Sheldon Jones Agriculture",
    "wof:placetype":"venue"
},
  "geometry": {"coordinates":[-2.7170469761,51.484161377],"type":"Point"}
}