{
  "type": "Feature",
  "properties": {
    "iso:country":"GB",
    "sg:address":"95 Cow Lane",
    "sg:city":"Wakefield",
    "sg:classifiers":[
        {
            "category":"Food & Beverages",
            "subcategory":"Meat & Fish",
            "type":"Retail Goods"
        }
    ],
    "sg:phone":"+44 1226 700909",
    "sg:postcode":"WF4 2HF",
    "sg:province":"West Yorkshire",
    "sg:tags":[
        "chip"
    ],
    "wof:name":"T G F",
    "wof:placetype":"venue"
},
  "geometry": {"coordinates":[-1.4035220146,53.6245307922],"type":"Point"}
}