{
  "type": "Feature",
  "properties": {
    "addr:full":"Mileswood Farm, Old Wokingham Rd Crowthorne Berkshire RG45 6AU",
    "addr:postcode":"rg45 6au",
    "addr:street":"Old Wokingham Rd",
    "iso:country":"GB",
    "sg:address":"Mileswood Farm, Old Wokingham Rd",
    "sg:city":"Crowthorne",
    "sg:classifiers":[
        {
            "category":"Retail",
            "subcategory":"Auto Repair",
            "type":"Services"
        }
    ],
    "sg:phone":"+44 1344 780013",
    "sg:postcode":"RG45 6AU",
    "sg:province":"Berkshire",
    "sg:tags":[
        "body",
        "car"
    ],
    "wof:name":"A Mather",
    "wof:placetype":"venue"
},
  "geometry": {"coordinates":[-0.790444,51.376965],"type":"Point"}
}