{
  "type": "Feature",
  "properties": {
    "iso:country":"GB",
    "sg:address":"55 Milngavie Road, Bearsden",
    "sg:city":"Glasgow",
    "sg:classifiers":[
        {
            "category":"Government",
            "subcategory":"City Hall",
            "type":"Public Place"
        },
        {
            "category":"Shopping",
            "subcategory":"News",
            "type":"Retail Goods"
        },
        {
            "category":"Government",
            "subcategory":"Office",
            "type":"Public Place"
        }
    ],
    "sg:phone":"+44 141 942 5222",
    "sg:postcode":"G61 2DW",
    "sg:province":"East Dunbartonshire",
    "sg:tags":[
        "local",
        "newsagent"
    ],
    "wof:name":"Kessington Post Office",
    "wof:placetype":"venue"
},
  "geometry": {"coordinates":[-4.321564,55.915432],"type":"Point"}
}