{
  "type": "Feature",
  "properties": {
    "addr:full":"Unit 7 Langley Court, Burscough Industrial Estate, Burscough Ormskirk Lancashire L40 8JR",
    "addr:housenumber":"unit 7",
    "addr:postcode":"l40 8jr",
    "addr:street":"Langley Court;Industrial",
    "iso:country":"GB",
    "sg:address":"Unit 7 Langley Court, Burscough Industrial Estate, Burscough",
    "sg:city":"Ormskirk",
    "sg:classifiers":[
        {
            "category":"Professional",
            "subcategory":"Testing Lab",
            "type":"Services"
        }
    ],
    "sg:postcode":"L40 8JR",
    "sg:province":"Lancashire",
    "sg:tags":[
        "mot"
    ],
    "wof:name":"Swifts Garage",
    "wof:placetype":"venue"
},
  "geometry": {"coordinates":[-2.8657488823,53.6023254395],"type":"Point"}
}