{
  "type": "Feature",
  "properties": {
    "iso:country":"GB",
    "sg:address":"Golden Bough House, Stoke Bliss",
    "sg:city":"Tenbury Wells",
    "sg:classifiers":[
        {
            "category":"Professional",
            "subcategory":"Management & Consulting",
            "type":"Services"
        }
    ],
    "sg:phone":"+44 1885 410644",
    "sg:postcode":"WR15 8QH",
    "sg:province":"Herefordshire",
    "sg:tags":[
        "marketing",
        "consultant"
    ],
    "wof:name":"Cognito Bds Ltd.",
    "wof:placetype":"venue"
},
  "geometry": {"coordinates":[-2.594178915,52.3125839233],"type":"Point"}
}