{
  "type": "Feature",
  "properties": {
    "addr:full":"Spa Crt,spa La, Starbeck Harrogate North Yorkshire HG2 7JS",
    "addr:postcode":"hg2 7js",
    "addr:street":"La",
    "iso:country":"GB",
    "sg:address":"Spa Crt,spa La, Starbeck",
    "sg:city":"Harrogate",
    "sg:classifiers":[
        {
            "category":"Retail",
            "subcategory":"Laundry & Dry Cleaning",
            "type":"Services"
        },
        {
            "category":"Social Services",
            "subcategory":"Adult Care",
            "type":"Services"
        }
    ],
    "sg:postcode":"HG2 7JS",
    "sg:province":"North Yorkshire",
    "sg:tags":[
        "home",
        "domestic",
        "ironing"
    ],
    "wof:name":"Stewart,Mark,",
    "wof:placetype":"venue"
},
  "geometry": {"coordinates":[-1.49441,53.996868],"type":"Point"}
}