{
  "type": "Feature",
  "properties": {
    "iso:country":"GB",
    "sg:address":"123 Worcester Rd",
    "sg:city":"Stourbridge",
    "sg:classifiers":[
        {
            "category":"Real Estate",
            "subcategory":"Real Estate Agent",
            "type":"Services"
        }
    ],
    "sg:phone":"+44 1562 886633",
    "sg:postcode":"DY9 0NG",
    "sg:province":"West Midlands",
    "wof:name":"Shipways Royal & Sun Alliance Property Services",
    "wof:placetype":"venue"
},
  "geometry": {"coordinates":[-2.140223,52.435436],"type":"Point"}
}