{
  "type": "Feature",
  "properties": {
    "iso:country":"GB",
    "sg:address":"Frambury Lane, Newport",
    "sg:city":"Saffron Walden",
    "sg:classifiers":[
        {
            "category":"Education",
            "subcategory":"School",
            "type":"Public Place"
        }
    ],
    "sg:phone":"+44 1799 540055",
    "sg:postcode":"CB11 3PU",
    "sg:province":"Essex",
    "sg:tags":[
        "local",
        "authority"
    ],
    "wof:name":"Newport Primary School",
    "wof:placetype":"venue"
},
  "geometry": {"coordinates":[0.20865,51.982861],"type":"Point"}
}