{
  "type": "Feature",
  "properties": {
    "iso:country":"GB",
    "sg:address":"214 Innsworth Lane",
    "sg:city":"Gloucester",
    "sg:classifiers":[
        {
            "category":"Building & Trades",
            "subcategory":"Plumbing",
            "type":"Services"
        },
        {
            "category":"Government",
            "subcategory":"Post Office",
            "type":"Public Place"
        }
    ],
    "sg:phone":"+44 1452 731739",
    "sg:postcode":"GL3 1EA",
    "sg:province":"Gloucestershire",
    "sg:tags":[
        "clearance",
        "drain",
        "sewer",
        "sewar"
    ],
    "wof:name":"All Clear Drains",
    "wof:placetype":"venue"
},
  "geometry": {"coordinates":[-2.208495,51.888458],"type":"Point"}
}