{
  "type": "Feature",
  "properties": {
    "addr:full":"29 Worton Rd, Middle Barton Chipping Norton Chipping Norton Gloucestershire OX7 7EE",
    "addr:housenumber":"29;norton",
    "addr:postcode":"ox7 7ee",
    "addr:street":"Worton Rd Middle Barton",
    "iso:country":"GB",
    "sg:address":"29 Worton Rd, Middle Barton Chipping Norton",
    "sg:city":"Chipping Norton",
    "sg:classifiers":[
        {
            "category":"Utilities",
            "subcategory":"Fuel Oil & Lpg",
            "type":"Services"
        }
    ],
    "sg:phone":"+44 1865 200077",
    "sg:postcode":"OX7 7EE",
    "sg:province":"Gloucestershire",
    "wof:name":"Isis Oils",
    "wof:placetype":"venue"
},
  "geometry": {"coordinates":[-1.3700339794,51.9313697815],"type":"Point"}
}