{
  "type": "Feature",
  "properties": {
    "iso:country":"GB",
    "sg:address":"461 Ashley Road, Parkstone",
    "sg:city":"Poole",
    "sg:classifiers":[
        {
            "category":"Real Estate",
            "subcategory":"Real Estate Agent",
            "type":"Services"
        }
    ],
    "sg:phone":"+44 1202 721131",
    "sg:postcode":"BH14 0AX",
    "sg:province":"Dorset",
    "wof:name":"Thomas & Rawson",
    "wof:placetype":"venue"
},
  "geometry": {"coordinates":[-1.945418,50.729179],"type":"Point"}
}