{
  "type": "Feature",
  "properties": {
    "addr:full":"Unit 2 Churchfield Court, Top Valley Nottingham Nottinghamshire NG5 9JL",
    "addr:housenumber":"unit 2",
    "addr:postcode":"ng5 9jl",
    "addr:street":"Churchfield Court",
    "iso:country":"GB",
    "sg:address":"Unit 2 Churchfield Court, Top Valley",
    "sg:city":"Nottingham",
    "sg:classifiers":[
        {
            "category":"Wholesale",
            "subcategory":"Office Equipment",
            "type":"Manufacturing & Wholesale Goods"
        }
    ],
    "sg:phone":"+44 115 955 1733",
    "sg:postcode":"NG5 9JL",
    "sg:province":"Nottinghamshire",
    "sg:tags":[
        "partition",
        "cubicle"
    ],
    "wof:name":"B & M Installations",
    "wof:placetype":"venue"
},
  "geometry": {"coordinates":[-1.1680339575,53.0094299316],"type":"Point"}
}