{
  "type": "Feature",
  "properties": {
    "addr:full":"Fisher Street Off Gladstone St Nottingham Nottinghamshire NG7 6FJ",
    "addr:postcode":"ng7 6fj",
    "addr:street":"Fisher Street Off Gladstone St",
    "iso:country":"GB",
    "sg:address":"Fisher Street Off Gladstone St",
    "sg:city":"Nottingham",
    "sg:classifiers":[
        {
            "category":"Place Of Worship",
            "type":"Public Place"
        }
    ],
    "sg:phone":"+44 115 970 5390",
    "sg:postcode":"NG7 6FJ",
    "sg:province":"Nottinghamshire",
    "wof:name":"Hebron Church A O G",
    "wof:placetype":"venue"
},
  "geometry": {"coordinates":[-1.1710339785,52.9697494507],"type":"Point"}
}