{
  "type": "Feature",
  "properties": {
    "addr:full":"London Road, Reed Royston Bedfordshire SG8 8BB",
    "addr:postcode":"sg8 8bb",
    "addr:street":"London Road",
    "iso:country":"GB",
    "sg:address":"London Road, Reed",
    "sg:city":"Royston",
    "sg:classifiers":[
        {
            "category":"Retail",
            "subcategory":"Veterinary Services",
            "type":"Services"
        }
    ],
    "sg:phone":"+44 1763 848661",
    "sg:postcode":"SG8 8BB",
    "sg:province":"Bedfordshire",
    "sg:tags":[
        "surgeon"
    ],
    "wof:name":"Woolpack Veterinary Surgery",
    "wof:placetype":"venue"
},
  "geometry": {"coordinates":[0.0163310003,51.9895133972],"type":"Point"}
}