{
  "type": "Feature",
  "properties": {
    "iso:country":"GB",
    "sg:address":"8-10 Glebe",
    "sg:city":"Stevenage",
    "sg:classifiers":[
        {
            "category":"Wholesale",
            "subcategory":"Scrap",
            "type":"Manufacturing & Wholesale Goods"
        }
    ],
    "sg:phone":"+44 1438 74991",
    "sg:postcode":"SG2 0DL",
    "sg:province":"Hertfordshire",
    "sg:tags":[
        "waste",
        "metal"
    ],
    "wof:name":"Alchemy Metals Ltd.",
    "wof:placetype":"venue"
},
  "geometry": {"coordinates":[-0.171074,51.90955],"type":"Point"}
}