{
  "type": "Feature",
  "properties": {
    "addr:full":"Eden Ho, High St, Watton-le-stone Hertford Hertfordshire SG14 3RZ",
    "addr:postcode":"sg14 3rz",
    "addr:street":"High St",
    "iso:country":"GB",
    "sg:address":"Eden Ho, High St, Watton-le-stone",
    "sg:city":"Hertford",
    "sg:classifiers":[
        {
            "category":"Building & Trades",
            "subcategory":"Construction",
            "type":"Services"
        }
    ],
    "sg:postcode":"SG14 3RZ",
    "sg:province":"Hertfordshire",
    "sg:tags":[
        "builder"
    ],
    "wof:name":"Watts,Donald B,",
    "wof:placetype":"venue"
},
  "geometry": {"coordinates":[-0.108479999,51.8549880981],"type":"Point"}
}