{
  "type": "Feature",
  "properties": {
    "addr:full":"125 Low La, Horsforth Leeds West Yorkshire LS18 5PX",
    "addr:housenumber":"125",
    "addr:postcode":"ls18 5px",
    "addr:street":"Low La Horsforth Leeds West",
    "iso:country":"GB",
    "sg:address":"125 Low La, Horsforth",
    "sg:city":"Leeds",
    "sg:classifiers":[
        {
            "category":"Autos & Motor Vehicles",
            "subcategory":"Auto Supplies",
            "type":"Retail Goods"
        }
    ],
    "sg:phone":"+44 113 258 4668",
    "sg:postcode":"LS18 5PX",
    "sg:province":"West Yorkshire",
    "sg:tags":[
        "exhaust",
        "absorber",
        "shock"
    ],
    "wof:name":"Dixon Motor Group",
    "wof:placetype":"venue"
},
  "geometry": {"coordinates":[-1.6300640106,53.8434753418],"type":"Point"}
}