{
  "type": "Feature",
  "properties": {
    "iso:country":"GB",
    "sg:address":"Marler Yard, 9a Pinner Road",
    "sg:city":"Watford",
    "sg:classifiers":[
        {
            "category":"Professional",
            "subcategory":"Management & Consulting",
            "type":"Services"
        }
    ],
    "sg:phone":"+44 1923 210750",
    "sg:postcode":"WD19 4GF",
    "sg:province":"Hertfordshire",
    "sg:tags":[
        "consultant",
        "business"
    ],
    "wof:name":"Multiplicity Ltd.",
    "wof:placetype":"venue"
},
  "geometry": {"coordinates":[-0.38373,51.644539],"type":"Point"}
}