{
  "type": "Feature",
  "properties": {
    "addr:full":"Units 5 & 6, Ullenwood Court, Ullenwood Court Cheltenham Gloucestershire GL53 9QS",
    "addr:housenumber":"units 5 & 6",
    "addr:postcode":"gl53 9qs",
    "addr:street":"Ullenwood Court Ullenwood Court",
    "iso:country":"GB",
    "sg:address":"Units 5 & 6, Ullenwood Court, Ullenwood Court",
    "sg:city":"Cheltenham",
    "sg:classifiers":[
        {
            "category":"Manufacturing",
            "subcategory":"Petroleum Products",
            "type":"Manufacturing & Wholesale Goods"
        }
    ],
    "sg:phone":"+44 1242 575966",
    "sg:postcode":"GL53 9QS",
    "sg:province":"Gloucestershire",
    "sg:tags":[
        "double",
        "glazing"
    ],
    "wof:name":"Frames Windows Co. Ltd.",
    "wof:placetype":"venue"
},
  "geometry": {"coordinates":[-2.0902900696,51.8528213501],"type":"Point"}
}