{
  "type": "Feature",
  "properties": {
    "iso:country":"GB",
    "sg:address":"15 Norman Square, Cutpurse",
    "sg:city":"Richmond",
    "sg:classifiers":[
        {
            "category":"Building & Trades",
            "subcategory":"Construction",
            "type":"Services"
        }
    ],
    "sg:phone":"+44 1748 822682",
    "sg:postcode":"DL10 4PB",
    "sg:province":"North Yorkshire",
    "sg:tags":[
        "tiling",
        "contractor"
    ],
    "wof:name":"R & W Gibson & Son",
    "wof:placetype":"venue"
},
  "geometry": {"coordinates":[-1.731829,54.41309],"type":"Point"}
}