{
  "type": "Feature",
  "properties": {
    "iso:country":"GB",
    "sg:address":"Unit 5, Indslt Estate, Crabbe Street",
    "sg:city":"Stourbridge",
    "sg:classifiers":[
        {
            "category":"Home & Garden",
            "subcategory":"Hardware",
            "type":"Retail Goods"
        }
    ],
    "sg:phone":"+44 1384 892389",
    "sg:postcode":"DY9 8HX",
    "sg:province":"West Midlands",
    "sg:tags":[
        "fixing",
        "nuts",
        "bolt"
    ],
    "wof:name":"Cradley Forge & Engineering Ltd.",
    "wof:placetype":"venue"
},
  "geometry": {"coordinates":[-2.1061298847,52.4618606567],"type":"Point"}
}