{
  "type": "Feature",
  "properties": {
    "addr:full":"Unit 2, Chewton Street, Eastwood Nottingham Derbyshire NG16 3HB",
    "addr:housenumber":"unit 2",
    "addr:postcode":"ng16 3hb",
    "addr:street":"Chewton Street",
    "iso:country":"GB",
    "sg:address":"Unit 2, Chewton Street, Eastwood",
    "sg:city":"Nottingham",
    "sg:classifiers":[
        {
            "category":"Autos & Motor Vehicles",
            "subcategory":"Automobile Sales",
            "type":"Retail Goods"
        },
        {
            "category":"Autos & Motor Vehicles",
            "subcategory":"Auto Supplies",
            "type":"Retail Goods"
        }
    ],
    "sg:phone":"+44 1773 533355",
    "sg:postcode":"NG16 3HB",
    "sg:province":"Derbyshire",
    "sg:tags":[
        "component",
        "van",
        "truck"
    ],
    "sg:website":"http://www.digraph.co.uk",
    "wof:name":"Digraph Transport Supplies Ltd.",
    "wof:placetype":"venue"
},
  "geometry": {"coordinates":[-1.294994,53.0145],"type":"Point"}
}