{
  "type": "Feature",
  "properties": {
    "iso:country":"GB",
    "sg:address":"Low House Farm, Cowan Bridge",
    "sg:city":"Carnforth",
    "sg:classifiers":[
        {
            "category":"Farming",
            "subcategory":"Livestock Farm",
            "type":"Manufacturing & Wholesale Goods"
        }
    ],
    "sg:postcode":"LA6 2JJ",
    "sg:province":"Cumbria",
    "sg:tags":[
        "others"
    ],
    "wof:name":"Robin Caton",
    "wof:placetype":"venue"
},
  "geometry": {"coordinates":[-2.5482699871,54.1767196655],"type":"Point"}
}