{
  "type": "Feature",
  "properties": {
    "addr:full":"John Wilson Street, Woolwich London Greater London SE18 6QD",
    "addr:postcode":"se18 6qd",
    "addr:street":"John Wilson Street",
    "iso:country":"GB",
    "sg:address":"John Wilson Street, Woolwich",
    "sg:city":"London",
    "sg:classifiers":[
        {
            "category":"Cinema",
            "subcategory":"Movie Theater",
            "type":"Entertainment"
        }
    ],
    "sg:phone":"+44 20 7721 0123",
    "sg:postcode":"SE18 6QD",
    "sg:province":"Greater London",
    "wof:name":"Coronet Cinema",
    "wof:placetype":"venue"
},
  "geometry": {"coordinates":[0.0620700009,51.489730835],"type":"Point"}
}