{
  "type": "Feature",
  "properties": {
    "iso:country":"GB",
    "sg:address":"224 Bishopsgate",
    "sg:city":"London",
    "sg:classifiers":[
        {
            "category":"Banks & Credit Unions",
            "subcategory":"Bank",
            "type":"Services"
        }
    ],
    "sg:phone":"+44 20 7377 5422",
    "sg:postcode":"EC2M 4AN",
    "sg:province":"Greater London",
    "wof:name":"Abbey National Plc",
    "wof:placetype":"venue"
},
  "geometry": {"coordinates":[-0.0793349966,51.5184860229],"type":"Point"}
}