{
  "type": "Feature",
  "properties": {
    "addr:full":"Rear Of 10, 10 Splott Road Cardiff Cardiff CF24 2BZ",
    "addr:housenumber":"rear of 10 10",
    "addr:postcode":"cf24 2bz",
    "addr:street":"Splott Road",
    "iso:country":"GB",
    "sg:address":"Rear Of 10, 10 Splott Road",
    "sg:city":"Cardiff",
    "sg:classifiers":[
        {
            "category":"Autos & Motor Vehicles",
            "subcategory":"Auto Supplies",
            "type":"Retail Goods"
        }
    ],
    "sg:phone":"+44 29 2049 8773",
    "sg:postcode":"CF24 2BZ",
    "sg:province":"Cardiff",
    "sg:tags":[
        "tyre"
    ],
    "wof:name":"A1 Tyres",
    "wof:placetype":"venue"
},
  "geometry": {"coordinates":[-3.1530299187,51.4838409424],"type":"Point"}
}