{
  "type": "Feature",
  "properties": {
    "addr:full":"Queensbury Health Centre, Russell Rd Bradford West Yorkshire BD13 2AG",
    "addr:postcode":"bd13 2ag",
    "addr:street":"Russell Rd",
    "iso:country":"GB",
    "sg:address":"Queensbury Health Centre, Russell Rd",
    "sg:city":"Bradford",
    "sg:classifiers":[
        {
            "category":"Health Services",
            "subcategory":"Doctor",
            "type":"Services"
        }
    ],
    "sg:phone":"+44 1274 880507",
    "sg:postcode":"BD13 2AG",
    "sg:province":"West Yorkshire",
    "sg:tags":[
        "practitioners"
    ],
    "wof:name":"Wilson, A I",
    "wof:placetype":"venue"
},
  "geometry": {"coordinates":[-1.8459240198,53.7682495117],"type":"Point"}
}