{
  "type": "Feature",
  "properties": {
    "addr:full":"162 High Street Gillingham Kent ME7 1AJ",
    "addr:housenumber":"162",
    "addr:postcode":"me7 1aj",
    "addr:street":"High Street",
    "iso:country":"GB",
    "sg:address":"162 High Street",
    "sg:city":"Gillingham",
    "sg:classifiers":[
        {
            "category":"Food & Beverages",
            "subcategory":"Meat & Fish",
            "type":"Retail Goods"
        }
    ],
    "sg:phone":"+44 1634 851271",
    "sg:postcode":"ME7 1AJ",
    "sg:province":"Kent",
    "sg:tags":[
        "butcher"
    ],
    "wof:name":"MORE CUTS",
    "wof:placetype":"venue"
},
  "geometry": {"coordinates":[0.5490329862,51.3867874146],"type":"Point"}
}