{
  "type": "Feature",
  "properties": {
    "addr:full":"Shire Lane Keston Kent BR2 6AA",
    "addr:postcode":"br2 6aa",
    "addr:street":"Shire Lane",
    "iso:country":"GB",
    "sg:address":"Shire Lane",
    "sg:city":"Keston",
    "sg:classifiers":[
        {
            "category":"Shopping",
            "subcategory":"Pets & Pet Supplies",
            "type":"Retail Goods"
        }
    ],
    "sg:phone":"+44 1689 856618",
    "sg:postcode":"BR2 6AA",
    "sg:province":"Kent",
    "wof:name":"Jack Frost Animal Homes",
    "wof:placetype":"venue"
},
  "geometry": {"coordinates":[0.043251,51.347752],"type":"Point"}
}