{
  "type": "Feature",
  "properties": {
    "iso:country":"GB",
    "sg:address":"The Birches, Pinewood Hill",
    "sg:city":"Fleet",
    "sg:classifiers":[
        {
            "category":"Professional",
            "subcategory":"Business Services",
            "type":"Services"
        }
    ],
    "sg:postcode":"GU51 3AW",
    "sg:province":"Hampshire",
    "sg:tags":[
        "import",
        "export",
        "agent"
    ],
    "wof:name":"Play Safe Pet Pens",
    "wof:placetype":"venue"
},
  "geometry": {"coordinates":[-0.83444,51.28548],"type":"Point"}
}