{
  "type": "Feature",
  "properties": {
    "addr:full":"Bedford Road, Brogborough Bedford Bedfordshire MK43 0XY",
    "addr:postcode":"mk43 0xy",
    "addr:street":"Bedford Road",
    "iso:country":"GB",
    "sg:address":"Bedford Road, Brogborough",
    "sg:city":"Bedford",
    "sg:classifiers":[
        {
            "category":"Organizations",
            "subcategory":"Membership Organization",
            "type":"Services"
        }
    ],
    "sg:phone":"+44 1525 280319",
    "sg:postcode":"MK43 0XY",
    "sg:province":"Bedfordshire",
    "sg:tags":[
        "club"
    ],
    "wof:name":"Brogborough Sports & Social Club",
    "wof:placetype":"venue"
},
  "geometry": {"coordinates":[-0.596744,52.035137],"type":"Point"}
}