{
  "type": "Feature",
  "properties": {
    "iso:country":"GB",
    "sg:address":"39 Bothwell Street",
    "sg:city":"Glasgow",
    "sg:classifiers":[
        {
            "category":"Home & Garden",
            "subcategory":"Furniture",
            "type":"Retail Goods"
        }
    ],
    "sg:phone":"+44 141 226 5450",
    "sg:postcode":"G2 6NX",
    "sg:province":"Glasgow City",
    "wof:name":"Sofa Workshops",
    "wof:placetype":"venue"
},
  "geometry": {"coordinates":[-4.260523,55.86105],"type":"Point"}
}