{
  "type": "Feature",
  "properties": {
    "iso:country":"GB",
    "sg:address":"Eccleston Bridge Post Office, 106 Towngate",
    "sg:city":"Chorley",
    "sg:classifiers":[
        {
            "category":"Government",
            "subcategory":"Post Office",
            "type":"Public Place"
        }
    ],
    "sg:phone":"+44 1257 451260",
    "sg:postcode":"PR7 5QS",
    "sg:province":"Lancashire",
    "wof:name":"Eccleston Bridge Post Office",
    "wof:placetype":"venue"
},
  "geometry": {"coordinates":[-2.632134,53.652088],"type":"Point"}
}