{
  "type": "Feature",
  "properties": {
    "addr:full":"196 Lloyd St North Manchester Greater Manchester M14 4QB",
    "addr:housenumber":"196",
    "addr:postcode":"m14 4qb",
    "addr:street":"Lloyd St",
    "iso:country":"GB",
    "sg:address":"196 Lloyd St North",
    "sg:city":"Manchester",
    "sg:classifiers":[
        {
            "category":"Place Of Worship",
            "type":"Public Place"
        }
    ],
    "sg:phone":"+44 161 226 1588",
    "sg:postcode":"M14 4QB",
    "sg:province":"Greater Manchester",
    "wof:name":"Polish R C Church of Divine Mercy",
    "wof:placetype":"venue"
},
  "geometry": {"coordinates":[-2.23597,53.458324],"type":"Point"}
}