{
  "type": "Feature",
  "properties": {
    "iso:country":"GB",
    "sg:address":"20a Bedford Street, St Neots",
    "sg:city":"Huntingdon",
    "sg:classifiers":[
        {
            "category":"Building & Trades",
            "subcategory":"Construction",
            "type":"Services"
        }
    ],
    "sg:phone":"+44 1480 472024",
    "sg:postcode":"PE19 1AX",
    "sg:province":"Bedfordshire",
    "sg:tags":[
        "heating",
        "contractor"
    ],
    "wof:name":"Edden Heating Services",
    "wof:placetype":"venue"
},
  "geometry": {"coordinates":[-0.26671,52.230568],"type":"Point"}
}