{
  "type": "Feature",
  "properties": {
    "addr:full":"Red Gauntlet Road Helensburgh Argyll and Bute G84 7TZ",
    "addr:postcode":"g84 7tz",
    "addr:street":"Gauntlet Road",
    "iso:country":"GB",
    "sg:address":"Red Gauntlet Road",
    "sg:city":"Helensburgh",
    "sg:classifiers":[
        {
            "category":"Education",
            "subcategory":"School",
            "type":"Public Place"
        },
        {
            "category":"Government",
            "subcategory":"Office",
            "type":"Public Place"
        }
    ],
    "sg:phone":"+44 1436 673557",
    "sg:postcode":"G84 7TZ",
    "sg:province":"Argyll and Bute",
    "sg:tags":[
        "local",
        "authority"
    ],
    "wof:name":"Colgrain Primary School",
    "wof:placetype":"venue"
},
  "geometry": {"coordinates":[-4.7125291824,56.0003662109],"type":"Point"}
}