{
  "type": "Feature",
  "properties": {
    "addr:full":"10 Sheen Lane, Mortlake London Greater London SW14 8LL",
    "addr:housenumber":"10",
    "addr:postcode":"sw14 8ll",
    "addr:street":"Sheen Lane",
    "iso:country":"GB",
    "sg:address":"10 Sheen Lane, Mortlake",
    "sg:city":"London",
    "sg:classifiers":[
        {
            "category":"Manufacturing",
            "subcategory":"Building Materials",
            "type":"Manufacturing & Wholesale Goods"
        }
    ],
    "sg:phone":"+44 20 8876 9331",
    "sg:postcode":"SW14 8LL",
    "sg:province":"Greater London",
    "sg:tags":[
        "merchant",
        "builder"
    ],
    "wof:name":"Sheen Lane Builders Merchants",
    "wof:placetype":"venue"
},
  "geometry": {"coordinates":[-0.2668089867,51.4686813354],"type":"Point"}
}