{
  "type": "Feature",
  "properties": {
    "addr:full":"46 Edgehill Rd Northampton Northamptonshire NN5 6BZ",
    "addr:housenumber":"46",
    "addr:postcode":"nn5 6bz",
    "addr:street":"Edgehill Rd",
    "iso:country":"GB",
    "sg:address":"46 Edgehill Rd",
    "sg:city":"Northampton",
    "sg:classifiers":[
        {
            "category":"Autos & Motor Vehicles",
            "subcategory":"Motorcycle Sales",
            "type":"Retail Goods"
        }
    ],
    "sg:phone":"+44 1604 755878",
    "sg:postcode":"NN5 6BZ",
    "sg:province":"Northamptonshire",
    "sg:tags":[
        "chauffeur",
        "driven",
        "car"
    ],
    "wof:name":"Kruze Chauffer Drive",
    "wof:placetype":"venue"
},
  "geometry": {"coordinates":[-0.93604,52.252033],"type":"Point"}
}