{
  "type": "Feature",
  "properties": {
    "iso:country":"GB",
    "sg:address":"The High Farm, Arkholme",
    "sg:city":"Carnforth",
    "sg:classifiers":[
        {
            "category":"Farming",
            "subcategory":"Farm",
            "type":"Manufacturing & Wholesale Goods"
        }
    ],
    "sg:postcode":"LA6 1AR",
    "sg:province":"Cumbria",
    "sg:tags":[
        "mixed",
        "crop"
    ],
    "wof:name":"Hayhurst,G & D,",
    "wof:placetype":"venue"
},
  "geometry": {"coordinates":[-2.6379890442,54.1444168091],"type":"Point"}
}