{
  "type": "Feature",
  "properties": {
    "addr:full":"Raglan House, Raglan Street Harrogate North Yorkshire HG1 1LE",
    "addr:postcode":"hg1 1le",
    "addr:street":"Raglan Street",
    "iso:country":"GB",
    "sg:address":"Raglan House, Raglan Street",
    "sg:city":"Harrogate",
    "sg:classifiers":[
        {
            "category":"Professional",
            "subcategory":"Employment Agencies",
            "type":"Services"
        }
    ],
    "sg:phone":"+44 1423 531200",
    "sg:postcode":"HG1 1LE",
    "sg:province":"North Yorkshire",
    "sg:tags":[
        "consultant"
    ],
    "wof:name":"Liz Dargue Staffing (Harrogate) Ltd.",
    "wof:placetype":"venue"
},
  "geometry": {"coordinates":[-1.538399,53.991291],"type":"Point"}
}