{
  "type": "Feature",
  "properties": {
    "addr:full":"217 Upper Dale Road Derby Derbyshire DE23 8BS",
    "addr:housenumber":"217",
    "addr:postcode":"de23 8bs",
    "addr:street":"Upper Dale Road",
    "iso:country":"GB",
    "sg:address":"217 Upper Dale Road",
    "sg:city":"Derby",
    "sg:classifiers":[
        {
            "category":"Real Estate",
            "subcategory":"Real Estate Agent",
            "type":"Services"
        }
    ],
    "sg:phone":"+44 1332 730181",
    "sg:postcode":"DE23 8BS",
    "sg:province":"Derbyshire",
    "wof:name":"Homeletts",
    "wof:placetype":"venue"
},
  "geometry": {"coordinates":[-1.484434,52.902683],"type":"Point"}
}