{
  "type": "Feature",
  "properties": {
    "addr:full":"20 Manor Road Ruislip Greater London HA4 7LB",
    "addr:housenumber":"20",
    "addr:postcode":"ha4 7lb",
    "addr:street":"Manor Road",
    "iso:country":"GB",
    "sg:address":"20 Manor Road",
    "sg:city":"Ruislip",
    "sg:classifiers":[
        {
            "category":"Cinema",
            "subcategory":"Movie Rental",
            "type":"Entertainment"
        }
    ],
    "sg:phone":"+44 1895 624774",
    "sg:postcode":"HA4 7LB",
    "sg:province":"Greater London",
    "sg:tags":[
        "video",
        "library"
    ],
    "wof:name":"Look & Listen Ministries",
    "wof:placetype":"venue"
},
  "geometry": {"coordinates":[-0.4305379987,51.5758132935],"type":"Point"}
}