{
  "type": "Feature",
  "properties": {
    "iso:country":"GB",
    "sg:address":"521 Leeds Road, Thackley",
    "sg:city":"Bradford",
    "sg:classifiers":[
        {
            "category":"Government",
            "subcategory":"Post Office",
            "type":"Public Place"
        }
    ],
    "sg:phone":"+44 1274 611897",
    "sg:postcode":"BD10 8JZ",
    "sg:province":"West Yorkshire",
    "wof:name":"Thackley Post Office",
    "wof:placetype":"venue"
},
  "geometry": {"coordinates":[-1.735689044,53.842628479],"type":"Point"}
}