{
  "type": "Feature",
  "properties": {
    "addr:full":"41 Rookwood Avenue Wallington Surrey SM6 8HF",
    "addr:housenumber":"41",
    "addr:postcode":"sm6 8hf",
    "addr:street":"Rookwood Avenue",
    "iso:country":"GB",
    "sg:address":"41 Rookwood Avenue",
    "sg:city":"Wallington",
    "sg:classifiers":[
        {
            "category":"Organizations",
            "subcategory":"Non-profit Organization",
            "type":"Services"
        }
    ],
    "sg:postcode":"SM6 8HF",
    "sg:province":"Surrey",
    "sg:tags":[
        "organisation",
        "voluntary",
        "charity"
    ],
    "wof:name":"National Asthma Campaign",
    "wof:placetype":"venue"
},
  "geometry": {"coordinates":[-0.1374869943,51.3662376404],"type":"Point"}
}