{
  "type": "Feature",
  "properties": {
    "addr:full":"Eaglefield Rd Dornoch Highland IV25 3SU",
    "addr:postcode":"iv25 3su",
    "addr:street":"Eaglefield Rd",
    "iso:country":"GB",
    "sg:address":"Eaglefield Rd",
    "sg:city":"Dornoch",
    "sg:classifiers":[
        {
            "category":"Health Services",
            "subcategory":"Dentist",
            "type":"Services"
        }
    ],
    "sg:phone":"+44 1862 810267",
    "sg:postcode":"IV25 3SU",
    "sg:province":"Highland",
    "wof:name":"Alan Ramsey",
    "wof:placetype":"venue"
},
  "geometry": {"coordinates":[-4.0278692245,57.8816566467],"type":"Point"}
}