{
  "type": "Feature",
  "properties": {
    "iso:country":"GB",
    "sg:address":"Craiglae, Llangurig",
    "sg:city":"Llanidloes",
    "sg:classifiers":[
        {
            "category":"Building & Trades",
            "subcategory":"Plumbing",
            "type":"Services"
        }
    ],
    "sg:phone":"+44 1686 440245",
    "sg:postcode":"SY18 6SQ",
    "sg:province":"Powys",
    "sg:tags":[
        "heating"
    ],
    "wof:name":"Alan Addison",
    "wof:placetype":"venue"
},
  "geometry": {"coordinates":[-3.5401659012,52.4459152222],"type":"Point"}
}