{
  "type": "Feature",
  "properties": {
    "addr:full":"96 Stourbridge Road, Lye Stourbridge West Midlands DY9 7DD",
    "addr:housenumber":"96",
    "addr:postcode":"dy9 7dd",
    "addr:street":"Stourbridge Road",
    "iso:country":"GB",
    "sg:address":"96 Stourbridge Road, Lye",
    "sg:city":"Stourbridge",
    "sg:classifiers":[
        {
            "category":"Manufacturing",
            "subcategory":"Metals",
            "type":"Manufacturing & Wholesale Goods"
        }
    ],
    "sg:phone":"+44 1384 424151",
    "sg:postcode":"DY9 7DD",
    "sg:province":"West Midlands",
    "sg:tags":[
        "steel",
        "stockholder"
    ],
    "wof:name":"British Steel Service Centres Ltd.",
    "wof:placetype":"venue"
},
  "geometry": {"coordinates":[-2.121598,52.457844],"type":"Point"}
}