{
  "type": "Feature",
  "properties": {
    "addr:full":"Unit 17 Park Farm Business Centr, E Fornham Park, Fornham St Genevieve Bury St Edmunds Cambridgeshire IP28 6TS",
    "addr:housenumber":"unit 17",
    "addr:postcode":"ip28 6ts",
    "addr:street":"Park;Fornham St;St",
    "iso:country":"GB",
    "sg:address":"Unit 17 Park Farm Business Centr, E Fornham Park, Fornham St Genevieve",
    "sg:city":"Bury St Edmunds",
    "sg:classifiers":[
        {
            "category":"Professional",
            "subcategory":"Accounting & Tax Preparation",
            "type":"Services"
        }
    ],
    "sg:postcode":"IP28 6TS",
    "sg:province":"Cambridgeshire",
    "sg:tags":[
        "accountant"
    ],
    "wof:name":"Howard & Co",
    "wof:placetype":"venue"
},
  "geometry": {"coordinates":[0.7091500163,52.2790298462],"type":"Point"}
}