{
  "type": "Feature",
  "properties": {
    "addr:full":"Poplar Hall, Whatfield Road Ipswich Suffolk IP7 6LN",
    "addr:postcode":"ip7 6ln",
    "addr:street":"Whatfield Road",
    "iso:country":"GB",
    "sg:address":"Poplar Hall, Whatfield Road",
    "sg:city":"Ipswich",
    "sg:classifiers":[
        {
            "category":"Education",
            "subcategory":"Special Training",
            "type":"Public Place"
        }
    ],
    "sg:phone":"+44 1473 828400",
    "sg:postcode":"IP7 6LN",
    "sg:province":"Suffolk",
    "sg:tags":[
        "school",
        "flying"
    ],
    "wof:name":"Horizon Flying Club Ltd.",
    "wof:placetype":"venue"
},
  "geometry": {"coordinates":[0.951715,52.07896],"type":"Point"}
}