{
  "type": "Feature",
  "properties": {
    "iso:country":"GB",
    "sg:address":"56 South St",
    "sg:city":"Bridport",
    "sg:classifiers":[
        {
            "category":"Manufacturing",
            "subcategory":"Wood Products",
            "type":"Manufacturing & Wholesale Goods"
        }
    ],
    "sg:phone":"+44 1308 422408",
    "sg:postcode":"DT6 3NN",
    "sg:province":"Dorset",
    "sg:tags":[
        "woodturning"
    ],
    "wof:name":"Turning Point The",
    "wof:placetype":"venue"
},
  "geometry": {"coordinates":[-2.7582,50.731709],"type":"Point"}
}