{
  "type": "Feature",
  "properties": {
    "addr:full":"4 White Cottage Courtyard, 16 Magdalene Street Glastonbury Somerset BA6 9EH",
    "addr:housenumber":"4 white;courtyard 16",
    "addr:postcode":"ba6 9eh",
    "addr:street":"Magdalene Street",
    "iso:country":"GB",
    "sg:address":"4 White Cottage Courtyard, 16 Magdalene Street",
    "sg:city":"Glastonbury",
    "sg:classifiers":[
        {
            "category":"Professional",
            "subcategory":"Business Services",
            "type":"Services"
        }
    ],
    "sg:phone":"+44 1458 834741",
    "sg:postcode":"BA6 9EH",
    "sg:province":"Somerset",
    "sg:tags":[
        "agent",
        "manufacturers'"
    ],
    "wof:name":"Richard J T Amos",
    "wof:placetype":"venue"
},
  "geometry": {"coordinates":[-2.717009,51.147591],"type":"Point"}
}