{
  "type": "Feature",
  "properties": {
    "addr:full":"240-242 Greets Green Road West Bromwich West Midlands B70 9EP",
    "addr:housenumber":"240-242",
    "addr:postcode":"b70 9ep",
    "addr:street":"Greets Green Road",
    "iso:country":"GB",
    "sg:address":"240-242 Greets Green Road",
    "sg:city":"West Bromwich",
    "sg:classifiers":[
        {
            "category":"Retail",
            "subcategory":"Auto Rental",
            "type":"Services"
        }
    ],
    "sg:phone":"+44 121 557 1341",
    "sg:postcode":"B70 9EP",
    "sg:province":"West Midlands",
    "sg:tags":[
        "truck",
        "hire",
        "van"
    ],
    "wof:name":"Thompsons Hire & Haulage Ltd",
    "wof:placetype":"venue"
},
  "geometry": {"coordinates":[-2.0181789398,52.5203514099],"type":"Point"}
}