{
  "type": "Feature",
  "properties": {
    "addr:full":"14 King Sq Bristol City of Bristol BS2 8JH",
    "addr:housenumber":"14",
    "addr:postcode":"bs2 8jh",
    "addr:street":"King Sq",
    "iso:country":"GB",
    "sg:address":"14 King Sq",
    "sg:city":"Bristol",
    "sg:classifiers":[
        {
            "category":"Wholesale",
            "subcategory":"Music Publishers",
            "type":"Manufacturing & Wholesale Goods"
        }
    ],
    "sg:phone":"+44 117 924 8516",
    "sg:postcode":"BS2 8JH",
    "sg:province":"City of Bristol",
    "sg:tags":[
        "record"
    ],
    "wof:name":"Cup Of Tea Records",
    "wof:placetype":"venue"
},
  "geometry": {"coordinates":[-2.592484951,51.4614143372],"type":"Point"}
}