{
  "type": "Feature",
  "properties": {
    "iso:country":"GB",
    "sg:address":"Northgate Business Centre, Crown Road",
    "sg:city":"Enfield",
    "sg:classifiers":[
        {
            "category":"Insurance",
            "subcategory":"Insurance Agent",
            "type":"Services"
        }
    ],
    "sg:phone":"+44 20 8351 2400",
    "sg:postcode":"EN1 1FQ",
    "sg:province":"Greater London",
    "sg:tags":[
        "broker"
    ],
    "wof:name":"Victor C Knight Ltd.",
    "wof:placetype":"venue"
},
  "geometry": {"coordinates":[-0.054175,51.646591],"type":"Point"}
}