{
  "type": "Feature",
  "properties": {
    "iso:country":"GB",
    "sg:address":"51 Forge Close, Caerleon",
    "sg:city":"Newport",
    "sg:classifiers":[
        {
            "category":"Home & Garden",
            "subcategory":"Carpets & Floor Coverings",
            "type":"Retail Goods"
        }
    ],
    "sg:phone":"+44 1633 422600",
    "sg:postcode":"NP18 3PW",
    "sg:province":"Monmouthshire",
    "sg:tags":[
        "crane"
    ],
    "wof:name":"Morris Material Handling Ltd",
    "wof:placetype":"venue"
},
  "geometry": {"coordinates":[-2.9578950405,51.6187095642],"type":"Point"}
}