{
  "type": "Feature",
  "properties": {
    "iso:country":"GB",
    "sg:address":"Rock Channel",
    "sg:city":"Rye",
    "sg:classifiers":[
        {
            "category":"Shopping",
            "subcategory":"Computers & Home Electronics",
            "type":"Retail Goods"
        }
    ],
    "sg:phone":"+44 1797 225145",
    "sg:postcode":"TN31 7HJ",
    "sg:province":"East Sussex",
    "wof:name":"Woodhouse The",
    "wof:placetype":"venue"
},
  "geometry": {"coordinates":[0.7350429893,50.9480400085],"type":"Point"}
}