{
  "type": "Feature",
  "properties": {
    "iso:country":"GB",
    "sg:address":"13 Grove Street, Mansfield Woodhouse",
    "sg:city":"Mansfield",
    "sg:classifiers":[
        {
            "category":"Health Services",
            "subcategory":"Dentist",
            "type":"Services"
        }
    ],
    "sg:phone":"+44 1623 621305",
    "sg:postcode":"NG19 8BU",
    "sg:province":"Derbyshire",
    "wof:name":"J Whitbread",
    "wof:placetype":"venue"
},
  "geometry": {"coordinates":[-1.1973390579,53.1642112732],"type":"Point"}
}