{
  "type": "Feature",
  "properties": {
    "iso:country":"GB",
    "sg:address":"58-60 Berners St",
    "sg:city":"West End",
    "sg:classifiers":[
        {
            "category":"Professional",
            "subcategory":"Employment Agencies",
            "type":"Services"
        }
    ],
    "sg:phone":"+44 20 7580 3759",
    "sg:postcode":"W1P 3AE",
    "sg:province":"Hampshire",
    "sg:tags":[
        "consultant"
    ],
    "wof:name":"J H P Sumlock",
    "wof:placetype":"venue"
},
  "geometry": {"coordinates":[-0.136856,51.517097],"type":"Point"}
}