{
  "type": "Feature",
  "properties": {
    "addr:full":"Delfan, Felinfach Brecon Powys LD3 0UD",
    "addr:postcode":"ld3 0ud",
    "iso:country":"GB",
    "sg:address":"Delfan, Felinfach",
    "sg:city":"Brecon",
    "sg:classifiers":[
        {
            "category":"Retail",
            "subcategory":"Funeral Services",
            "type":"Services"
        }
    ],
    "sg:phone":"+44 1874 623477",
    "sg:postcode":"LD3 0UD",
    "sg:province":"Powys",
    "sg:tags":[
        "director"
    ],
    "wof:name":"A V Griffiths & Son",
    "wof:placetype":"venue"
},
  "geometry": {"coordinates":[-3.3220140934,51.9902458191],"type":"Point"}
}