{
  "type": "Feature",
  "properties": {
    "addr:full":"20a Victoria Road, Aberavon Port Talbot Neath Port Talbot SA12 6AB",
    "addr:housenumber":"20a",
    "addr:postcode":"sa12 6ab",
    "addr:street":"Victoria Road",
    "iso:country":"GB",
    "sg:address":"20a Victoria Road, Aberavon",
    "sg:city":"Port Talbot",
    "sg:classifiers":[
        {
            "category":"Shopping",
            "subcategory":"Pharmacy",
            "type":"Retail Goods"
        }
    ],
    "sg:phone":"+44 1639 883473",
    "sg:postcode":"SA12 6AB",
    "sg:province":"Neath Port Talbot",
    "sg:tags":[
        "pharmacist",
        "chemist"
    ],
    "wof:name":"Co-Op Pharmacy",
    "wof:placetype":"venue"
},
  "geometry": {"coordinates":[-3.801367,51.591782],"type":"Point"}
}