{
  "type": "Feature",
  "properties": {
    "addr:full":"14a Horndon Industrial Park, West Horndon Brentwood Essex CM13 3HW",
    "addr:housenumber":"14a",
    "addr:postcode":"cm13 3hw",
    "addr:street":"Horndon Industrial Park;Horndon",
    "iso:country":"GB",
    "sg:address":"14a Horndon Industrial Park, West Horndon",
    "sg:city":"Brentwood",
    "sg:classifiers":[
        {
            "category":"Shopping",
            "subcategory":"Stationery & Office Supplies",
            "type":"Retail Goods"
        },
        {
            "category":"Manufacturing",
            "subcategory":"Paper Products",
            "type":"Manufacturing & Wholesale Goods"
        }
    ],
    "sg:phone":"+44 1277 810846",
    "sg:postcode":"CM13 3HW",
    "sg:province":"Essex",
    "sg:tags":[
        "box",
        "packaging",
        "material",
        "carton",
        "manufacturer"
    ],
    "wof:name":"Turner Packaging Ltd.",
    "wof:placetype":"venue"
},
  "geometry": {"coordinates":[0.34282,51.568924],"type":"Point"}
}