{
  "type": "Feature",
  "properties": {
    "addr:full":"Marston Rd Spalding Cambridgeshire PE12 6EZ",
    "addr:postcode":"pe12 6ez",
    "addr:street":"Marston Rd",
    "iso:country":"GB",
    "sg:address":"Marston Rd",
    "sg:city":"Spalding",
    "sg:classifiers":[
        {
            "category":"Wholesale",
            "subcategory":"Meat",
            "type":"Manufacturing & Wholesale Goods"
        }
    ],
    "sg:phone":"+44 1775 766161",
    "sg:postcode":"PE12 6EZ",
    "sg:province":"Cambridgeshire",
    "sg:tags":[
        "product"
    ],
    "wof:name":"George Adams Group",
    "wof:placetype":"venue"
},
  "geometry": {"coordinates":[-0.1259499937,52.795589447],"type":"Point"}
}