{
  "type": "Feature",
  "properties": {
    "addr:full":"25 Stewarton Street Wishaw North Lanarkshire ML2 8AA",
    "addr:housenumber":"25",
    "addr:postcode":"ml2 8aa",
    "addr:street":"Stewarton Street",
    "iso:country":"GB",
    "sg:address":"25 Stewarton Street",
    "sg:city":"Wishaw",
    "sg:classifiers":[
        {
            "category":"Professional",
            "subcategory":"Accounting & Tax Preparation",
            "type":"Services"
        }
    ],
    "sg:phone":"+44 1698 361995",
    "sg:postcode":"ML2 8AA",
    "sg:province":"North Lanarkshire",
    "sg:tags":[
        "accountant",
        "activity"
    ],
    "wof:name":"Park Denholm & Co",
    "wof:placetype":"venue"
},
  "geometry": {"coordinates":[-3.9181120396,55.7729797363],"type":"Point"}
}