{
  "type": "Feature",
  "properties": {
    "iso:country":"GB",
    "sg:address":"Guildhall Cattle Market",
    "sg:city":"Sandwich",
    "sg:classifiers":[
        {
            "category":"Government",
            "subcategory":"Office",
            "type":"Public Place"
        }
    ],
    "sg:phone":"+44 1304 617197",
    "sg:postcode":"CT13 9AH",
    "sg:province":"Kent",
    "sg:tags":[
        "local"
    ],
    "wof:name":"Sandwich Town Council",
    "wof:placetype":"venue"
},
  "geometry": {"coordinates":[1.3423039913,51.2761688232],"type":"Point"}
}