{
  "type": "Feature",
  "properties": {
    "addr:full":"29 Henry Road Barnet Hertfordshire EN4 8BG",
    "addr:housenumber":"29",
    "addr:postcode":"en4 8bg",
    "addr:street":"Henry Road",
    "iso:country":"GB",
    "sg:address":"29 Henry Road",
    "sg:city":"Barnet",
    "sg:classifiers":[
        {
            "category":"Building & Trades",
            "subcategory":"Construction",
            "type":"Services"
        }
    ],
    "sg:phone":"+44 20 8440 4485",
    "sg:postcode":"EN4 8BG",
    "sg:province":"Hertfordshire",
    "sg:tags":[
        "joiner",
        "carpenter"
    ],
    "wof:name":"G F Barrett Ltd.",
    "wof:placetype":"venue"
},
  "geometry": {"coordinates":[-0.1693769991,51.6466026306],"type":"Point"}
}