{
  "type": "Feature",
  "properties": {
    "iso:country":"GB",
    "sg:address":"Stone Farm, Bere Ferrers",
    "sg:city":"Yelverton",
    "sg:classifiers":[
        {
            "category":"Manufacturing",
            "subcategory":"Tools & Machinery",
            "type":"Manufacturing & Wholesale Goods"
        }
    ],
    "sg:href":"http://api.simplegeo.com/1.0/features/SG_1I2JSbpjL15VZj9rthqrP1_50.451275_-4.170364@1300740015.json",
    "sg:postcode":"PL20 7JY",
    "sg:province":"Devon",
    "sg:tags":[
        "stone",
        "cutting"
    ],
    "wof:name":"Diamond Abrasive Technology Ltd",
    "wof:placetype":"venue"
},
  "geometry": {"coordinates":[-4.170364,50.451275],"type":"Point"}
}