{"geometry":{"type":"Point","coordinates":[-4.170364,50.451275]},"type":"Feature","id":102560945,"bbox":[-4.170364,50.451275,-4.170364,50.451275],"properties":{"sg:province":"Devon","sg:tags":["stone","cutting"],"geom:longitude":-4.170364,"wof:breaches":[],"sg:href":"http://api.simplegeo.com/1.0/features/SG_1I2JSbpjL15VZj9rthqrP1_50.451275_-4.170364@1300740015.json","sg:owner":"simplegeo","sg:postcode":"PL20 7JY","geom:latitude":50.451275,"sg:classifiers":[{"category":"Manufacturing","type":"Manufacturing & Wholesale Goods","subcategory":"Tools & Machinery"}],"sg:address":"Stone Farm, Bere Ferrers","wof:hierarchy":[{"venue_id":102560945,"country_id":85633159,"neighbourhood_id":85790877,"region_id":85683773}],"geom:area":0.000000,"sg:city":"Yelverton","wof:lastmodified":1438093415,"iso:country":"GB","wof:geomhash":"5d2112a046f532190b8f5917fb8de8b5","wof:name":"Diamond Abrasive Technology Ltd","wof:belongsto":[85633159,85790877,85683773],"src:geom":"simplegeo","wof:placetype":"venue","wof:supersedes":[],"wof:id":102560945,"wof:superseded_by":[],"wof:concordances":{"sg:id":"SG_1I2JSbpjL15VZj9rthqrP1_50.451275_-4.170364@1300740015"},"wof:parent_id":85790877}}