{
  "type": "Feature",
  "properties": {
    "iso:country":"GB",
    "sg:address":"13 Lossie Wynd",
    "sg:city":"Elgin",
    "sg:classifiers":[
        {
            "category":"Bars & Pubs",
            "type":"Food & Drink"
        }
    ],
    "sg:postcode":"IV30 1PU",
    "sg:province":"Moray",
    "sg:tags":[
        "pubs",
        "inn"
    ],
    "wof:name":"The Nags Head Tavern",
    "wof:placetype":"venue"
},
  "geometry": {"coordinates":[-3.317699,57.647419],"type":"Point"}
}