{
  "type": "Feature",
  "properties": {
    "addr:full":"Unit 24, Drome Rd, Zone Deeside Flintshire CH5 2NY",
    "addr:housenumber":"unit 24",
    "addr:postcode":"ch5 2ny",
    "addr:street":"Drome Rd",
    "iso:country":"GB",
    "sg:address":"Unit 24, Drome Rd, Zone",
    "sg:city":"Deeside",
    "sg:classifiers":[
        {
            "category":"Wholesale",
            "subcategory":"Machinery & Supplies",
            "type":"Manufacturing & Wholesale Goods"
        }
    ],
    "sg:phone":"+44 1244 289575",
    "sg:postcode":"CH5 2NY",
    "sg:province":"Flintshire",
    "sg:tags":[
        "equipment",
        "pneumatic",
        "system"
    ],
    "wof:name":"Donoflex Ltd",
    "wof:placetype":"venue"
},
  "geometry": {"coordinates":[-2.9981219769,53.2281036377],"type":"Point"}
}