{
  "type": "Feature",
  "properties": {
    "iso:country":"GB",
    "sg:address":"First Floor Office, 125 High St",
    "sg:city":"Uckfield",
    "sg:classifiers":[
        {
            "category":"Professional",
            "subcategory":"Accounting & Tax Preparation",
            "type":"Services"
        }
    ],
    "sg:postcode":"TN22 1RN",
    "sg:province":"East Sussex",
    "sg:tags":[
        "accountant"
    ],
    "wof:name":"Finn,Michael,",
    "wof:placetype":"venue"
},
  "geometry": {"coordinates":[0.09969,50.97654],"type":"Point"}
}