{
  "type": "Feature",
  "properties": {
    "iso:country":"GB",
    "sg:address":"Unit 416c, Thorpe Arch Industrial Park",
    "sg:city":"Wetherby",
    "sg:classifiers":[
        {
            "category":"Shopping",
            "subcategory":"Musical Instruments",
            "type":"Retail Goods"
        }
    ],
    "sg:postcode":"LS23 7BJ",
    "sg:province":"West Yorkshire",
    "wof:name":"3D Associates Ltd",
    "wof:placetype":"venue"
},
  "geometry": {"coordinates":[-1.343214,53.910599],"type":"Point"}
}