{
  "type": "Feature",
  "properties": {
    "addr:full":"15 Weensland Road Hawick Cumbria TD9 9NW",
    "addr:housenumber":"15",
    "addr:postcode":"td9 9nw",
    "addr:street":"Weensland Road",
    "iso:country":"GB",
    "sg:address":"15 Weensland Road",
    "sg:city":"Hawick",
    "sg:classifiers":[
        {
            "category":"Shopping",
            "subcategory":"News",
            "type":"Retail Goods"
        }
    ],
    "sg:phone":"+44 1450 373552",
    "sg:postcode":"TD9 9NW",
    "sg:province":"Cumbria",
    "sg:tags":[
        "newsagent"
    ],
    "wof:name":"The Little Shop",
    "wof:placetype":"venue"
},
  "geometry": {"coordinates":[-2.7810840607,55.4264297485],"type":"Point"}
}