{
  "type": "Feature",
  "properties": {
    "iso:country":"GB",
    "sg:address":"24a Sedley Taylor Road",
    "sg:city":"Cambridge",
    "sg:classifiers":[
        {
            "category":"Real Estate",
            "subcategory":"Architect",
            "type":"Services"
        }
    ],
    "sg:postcode":"CB2 2PN",
    "sg:province":"Cambridgeshire",
    "sg:tags":[
        "architectural"
    ],
    "wof:name":"Strategic Direction",
    "wof:placetype":"venue"
},
  "geometry": {"coordinates":[0.134295,52.179848],"type":"Point"}
}