{
  "type": "Feature",
  "properties": {
    "iso:country":"GB",
    "sg:address":"M A C A Hostel, 13 Charlotte Mews",
    "sg:city":"Swindon",
    "sg:classifiers":[
        {
            "category":"Travel",
            "subcategory":"Hostel",
            "type":"Entertainment"
        }
    ],
    "sg:phone":"+44 1793 497565",
    "sg:postcode":"SN1 3HT",
    "sg:province":"Wiltshire",
    "wof:name":"Redlands",
    "wof:placetype":"venue"
},
  "geometry": {"coordinates":[-1.7818139791,51.5617637634],"type":"Point"}
}