{
  "type": "Feature",
  "properties": {
    "addr:full":"Rose Tree Cottage, The Street, Coaley Dursley Gloucestershire GL11 5EB",
    "addr:postcode":"gl11 5eb",
    "addr:street":"The Street",
    "iso:country":"GB",
    "sg:address":"Rose Tree Cottage, The Street, Coaley",
    "sg:city":"Dursley",
    "sg:classifiers":[
        {
            "category":"Professional",
            "subcategory":"Art Services",
            "type":"Services"
        }
    ],
    "sg:phone":"+44 1453 890923",
    "sg:postcode":"GL11 5EB",
    "sg:province":"Gloucestershire",
    "sg:tags":[
        "carver",
        "sculptor"
    ],
    "wof:name":"Rafael Sorribas",
    "wof:placetype":"venue"
},
  "geometry": {"coordinates":[-2.365212,51.693291],"type":"Point"}
}