{
  "type": "Feature",
  "properties": {
    "addr:full":"Springwell Rd, Springwell Gateshead Tyne and Wear NE9 7SP",
    "addr:postcode":"ne9 7sp",
    "addr:street":"Springwell Rd",
    "iso:country":"GB",
    "sg:address":"Springwell Rd, Springwell",
    "sg:city":"Gateshead",
    "sg:classifiers":[
        {
            "category":"Professional",
            "subcategory":"Engineering",
            "type":"Services"
        }
    ],
    "sg:phone":"+44 191 417 3545",
    "sg:postcode":"NE9 7SP",
    "sg:province":"Tyne and Wear",
    "sg:tags":[
        "civil",
        "engineer"
    ],
    "wof:name":"Harbour & General Works Ltd",
    "wof:placetype":"venue"
},
  "geometry": {"coordinates":[-1.56773,54.926739],"type":"Point"}
}