{
  "type": "Feature",
  "properties": {
    "addr:full":"Unit 7, Chesterfield Trading Estate, Carrwood Road Chesterfield Derbyshire S41 9QB",
    "addr:housenumber":"unit 7",
    "addr:postcode":"s41 9qb",
    "addr:street":"Trading Estate Carrwood Road",
    "iso:country":"GB",
    "sg:address":"Unit 7, Chesterfield Trading Estate, Carrwood Road",
    "sg:city":"Chesterfield",
    "sg:classifiers":[
        {
            "category":"Professional",
            "subcategory":"Engineering",
            "type":"Services"
        }
    ],
    "sg:phone":"+44 1600 710100",
    "sg:postcode":"S41 9QB",
    "sg:province":"Derbyshire",
    "sg:tags":[
        "precision",
        "engineer"
    ],
    "wof:name":"Precision Engineering Services Ltd.",
    "wof:placetype":"venue"
},
  "geometry": {"coordinates":[-1.4353189468,53.2428817749],"type":"Point"}
}