{
  "type": "Feature",
  "properties": {
    "addr:full":"71 Thorpe Avenue Tonbridge Kent TN10 4PR",
    "addr:housenumber":"71",
    "addr:postcode":"tn10 4pr",
    "addr:street":"Thorpe Avenue",
    "iso:country":"GB",
    "sg:address":"71 Thorpe Avenue",
    "sg:city":"Tonbridge",
    "sg:classifiers":[
        {
            "category":"Building & Trades",
            "subcategory":"Construction",
            "type":"Services"
        }
    ],
    "sg:postcode":"TN10 4PR",
    "sg:province":"Kent",
    "sg:tags":[
        "excavation",
        "groundwork",
        "contractor"
    ],
    "wof:name":"Normans Fencing and Groundwork",
    "wof:placetype":"venue"
},
  "geometry": {"coordinates":[0.282033,51.213436],"type":"Point"}
}