{
  "type": "Feature",
  "properties": {
    "addr:full":"Uttoxeter Road, Draycott Stoke-on-trent Staffordshire ST11 9AQ",
    "addr:postcode":"st11 9aq",
    "addr:street":"Uttoxeter Road",
    "iso:country":"GB",
    "sg:address":"Uttoxeter Road, Draycott",
    "sg:city":"Stoke-on-trent",
    "sg:classifiers":[
        {
            "category":"Government",
            "subcategory":"Post Office",
            "type":"Public Place"
        }
    ],
    "sg:postcode":"ST11 9AQ",
    "sg:province":"Staffordshire",
    "wof:name":"Draycott Sub Post Office",
    "wof:placetype":"venue"
},
  "geometry": {"coordinates":[-2.0308640003,52.9588356018],"type":"Point"}
}