{
  "type": "Feature",
  "properties": {
    "addr:full":"Unit 2 Block 3, Threave Court, Castlehill Ind Est Carluke South Lanarkshire ML8 5UF",
    "addr:housenumber":"unit 2 block",
    "addr:postcode":"ml8 5uf",
    "addr:street":"Threave Court",
    "iso:country":"GB",
    "sg:address":"Unit 2 Block 3, Threave Court, Castlehill Ind Est",
    "sg:city":"Carluke",
    "sg:classifiers":[
        {
            "category":"Shopping",
            "subcategory":"Pets & Pet Supplies",
            "type":"Retail Goods"
        }
    ],
    "sg:phone":"+44 1555 750075",
    "sg:postcode":"ML8 5UF",
    "sg:province":"South Lanarkshire",
    "wof:name":"Evolution International Pet Products",
    "wof:placetype":"venue"
},
  "geometry": {"coordinates":[-3.84561,55.744888],"type":"Point"}
}