{
  "type": "Feature",
  "properties": {
    "iso:country":"GB",
    "sg:address":"10 Middleton Rd, Royton",
    "sg:city":"Oldham",
    "sg:classifiers":[
        {
            "category":"Personal",
            "subcategory":"Beauty Salon",
            "type":"Services"
        }
    ],
    "sg:phone":"+44 161 624 9922",
    "sg:postcode":"OL2 5PA",
    "sg:province":"Lancashire",
    "sg:tags":[
        "unisex",
        "hairdresser"
    ],
    "wof:name":"J.L James Hair Co",
    "wof:placetype":"venue"
},
  "geometry": {"coordinates":[-2.122065,53.565174],"type":"Point"}
}