{
  "type": "Feature",
  "properties": {
    "addr:full":"Mortimer Transport Yard, Featherbed Lane Hemel Hempstead Hertfordshire HP3 9DJ",
    "addr:postcode":"hp3 9dj",
    "addr:street":"Featherbed Lane",
    "iso:country":"GB",
    "sg:address":"Mortimer Transport Yard, Featherbed Lane",
    "sg:city":"Hemel Hempstead",
    "sg:classifiers":[
        {
            "category":"Shopping",
            "subcategory":"Discount & Variety Stores",
            "type":"Retail Goods"
        }
    ],
    "sg:phone":"+44 1442 235566",
    "sg:postcode":"HP3 9DJ",
    "sg:province":"Hertfordshire",
    "sg:tags":[
        "cleaning",
        "supply"
    ],
    "wof:name":"Black Bush Services",
    "wof:placetype":"venue"
},
  "geometry": {"coordinates":[-0.4727300107,51.7381782532],"type":"Point"}
}