{
  "type": "Feature",
  "properties": {
    "addr:full":"24 Milverton Road Glasgow East Renfrewshire G46 7JN",
    "addr:housenumber":"24",
    "addr:postcode":"g46 7jn",
    "addr:street":"Milverton Road",
    "iso:country":"GB",
    "sg:address":"24 Milverton Road",
    "sg:city":"Glasgow",
    "sg:classifiers":[
        {
            "category":"Building & Trades",
            "subcategory":"Construction",
            "type":"Services"
        },
        {
            "category":"Manufacturing",
            "subcategory":"Building Materials",
            "type":"Manufacturing & Wholesale Goods"
        }
    ],
    "sg:phone":"+44 141 638 4996",
    "sg:postcode":"G46 7JN",
    "sg:province":"East Renfrewshire",
    "sg:tags":[
        "tile",
        "mnfrs",
        "fitting",
        "laying",
        "contractor"
    ],
    "wof:name":"Thomson Tiling",
    "wof:placetype":"venue"
},
  "geometry": {"coordinates":[-4.3038611412,55.7951812744],"type":"Point"}
}