{
  "type": "Feature",
  "properties": {
    "addr:full":"Grove Street London Greater London N18 2TL",
    "addr:postcode":"n18 2tl",
    "addr:street":"Grove Street",
    "iso:country":"GB",
    "sg:address":"Grove Street",
    "sg:city":"London",
    "sg:classifiers":[
        {
            "category":"Education",
            "subcategory":"School",
            "type":"Public Place"
        },
        {
            "category":"Government",
            "subcategory":"Office",
            "type":"Public Place"
        }
    ],
    "sg:phone":"+44 20 8807 2578",
    "sg:postcode":"N18 2TL",
    "sg:province":"Greater London",
    "sg:tags":[
        "local",
        "authority"
    ],
    "wof:name":"St John & St James C Of E Primary School",
    "wof:placetype":"venue"
},
  "geometry": {"coordinates":[-0.0665000007,51.6110610962],"type":"Point"}
}