{
  "type": "Feature",
  "properties": {
    "iso:country":"GB",
    "sg:address":"50 Baker Street",
    "sg:city":"London",
    "sg:classifiers":[
        {
            "category":"Restaurant",
            "type":"Food & Drink"
        }
    ],
    "sg:phone":"+44 20 7224 4777",
    "sg:postcode":"W1U 7BT",
    "sg:province":"Greater London",
    "wof:name":"Al Fawar Restaurant",
    "wof:placetype":"venue"
},
  "geometry": {"coordinates":[-0.1557230055,51.5185890198],"type":"Point"}
}