{
  "type": "Feature",
  "properties": {
    "addr:full":"A61 167 Crossroads Busby Stoop Thirsk North Yorkshire YO7 4EQ",
    "addr:housenumber":"167",
    "addr:postcode":"yo7 4eq",
    "addr:street":"Crossroads Busby Stoop",
    "iso:country":"GB",
    "sg:address":"A61 167 Crossroads Busby Stoop",
    "sg:city":"Thirsk",
    "sg:classifiers":[
        {
            "category":"Retail",
            "subcategory":"Auto Repair",
            "type":"Services"
        }
    ],
    "sg:phone":"+44 1845 587232",
    "sg:postcode":"YO7 4EQ",
    "sg:province":"North Yorkshire",
    "sg:tags":[
        "modification",
        "garage"
    ],
    "wof:name":"A Earnshaw & Sons",
    "wof:placetype":"venue"
},
  "geometry": {"coordinates":[-1.3740240335,54.2279281616],"type":"Point"}
}