{
  "type": "Feature",
  "properties": {
    "addr:full":"Sornhill Cottage Galston East Ayrshire KA4 8NF",
    "addr:postcode":"ka4 8nf",
    "addr:street":"Galston East",
    "iso:country":"GB",
    "sg:address":"Sornhill Cottage",
    "sg:city":"Galston",
    "sg:classifiers":[
        {
            "category":"Professional",
            "subcategory":"Management & Consulting",
            "type":"Services"
        }
    ],
    "sg:phone":"+44 1563 822288",
    "sg:postcode":"KA4 8NF",
    "sg:province":"East Ayrshire",
    "sg:tags":[
        "consultant",
        "business"
    ],
    "wof:name":"P & H Ltd",
    "wof:placetype":"venue"
},
  "geometry": {"coordinates":[-4.3798441887,55.600025177],"type":"Point"}
}