{
  "type": "Feature",
  "properties": {
    "addr:full":"Unit 16, Monument Business Park, Warpsgrove Lane, Chalgrove Oxford Oxfordshire OX44 7RW",
    "addr:housenumber":"unit 16",
    "addr:postcode":"ox44 7rw",
    "addr:street":"Monument Business Park Warpsgrove Lane",
    "iso:country":"GB",
    "sg:address":"Unit 16, Monument Business Park, Warpsgrove Lane, Chalgrove",
    "sg:city":"Oxford",
    "sg:classifiers":[
        {
            "category":"Building & Trades",
            "subcategory":"Construction",
            "type":"Services"
        },
        {
            "category":"Retail",
            "subcategory":"Auto Repair",
            "type":"Services"
        }
    ],
    "sg:phone":"+44 1865 400011",
    "sg:postcode":"OX44 7RW",
    "sg:province":"Oxfordshire",
    "sg:tags":[
        "garage",
        "related",
        "concrete"
    ],
    "wof:name":"Pikehaven Ltd.",
    "wof:placetype":"venue"
},
  "geometry": {"coordinates":[-1.0649600029,51.6698188782],"type":"Point"}
}