{
  "type": "Feature",
  "properties": {
    "iso:country":"GB",
    "sg:address":"572 Cranbrook Road, Gants Hill",
    "sg:city":"Ilford",
    "sg:classifiers":[
        {
            "category":"Food & Beverages",
            "subcategory":"Liquor & Beverages",
            "type":"Retail Goods"
        }
    ],
    "sg:phone":"+44 20 8554 2470",
    "sg:postcode":"IG2 6RE",
    "sg:province":"Essex",
    "sg:tags":[
        "beer",
        "wine",
        "spirit",
        "wines"
    ],
    "wof:name":"Abis Off Licence",
    "wof:placetype":"venue"
},
  "geometry": {"coordinates":[0.0732240006,51.5795707703],"type":"Point"}
}