{
  "type": "Feature",
  "properties": {
    "iso:country":"GB",
    "sg:address":"Derby Ho, Lytham Rd, Fulwood",
    "sg:city":"Preston",
    "sg:classifiers":[
        {
            "category":"Manufacturing",
            "subcategory":"Rubber & Plastics",
            "type":"Manufacturing & Wholesale Goods"
        },
        {
            "category":"Professional",
            "subcategory":"Engineering",
            "type":"Services"
        },
        {
            "category":"Manufacturing",
            "subcategory":"Tools & Machinery",
            "type":"Manufacturing & Wholesale Goods"
        }
    ],
    "sg:postcode":"PR2 8JF",
    "sg:province":"Lancashire",
    "sg:tags":[
        "engineer",
        "design",
        "precision",
        "maker"
    ],
    "wof:name":"Canteen Smithy & Engineering Co Ltd",
    "wof:placetype":"venue"
},
  "geometry": {"coordinates":[-2.713888,53.77755],"type":"Point"}
}