{
  "type": "Feature",
  "properties": {
    "addr:full":"7 John Street Largs North Ayrshire KA30 8DT",
    "addr:housenumber":"7",
    "addr:postcode":"ka30 8dt",
    "addr:street":"John Street",
    "iso:country":"GB",
    "sg:address":"7 John Street",
    "sg:city":"Largs",
    "sg:classifiers":[
        {
            "category":"Arena",
            "subcategory":"Sports Club",
            "type":"Entertainment"
        }
    ],
    "sg:postcode":"KA30 8DT",
    "sg:province":"North Ayrshire",
    "wof:name":"Largs Sailing Club",
    "wof:placetype":"venue"
},
  "geometry": {"coordinates":[-4.8656787872,55.7885780334],"type":"Point"}
}