{
  "type": "Feature",
  "properties": {
    "addr:full":"Castle Gayer, Leys Lane Marazion Cornwall TR17 0AQ",
    "addr:postcode":"tr17 0aq",
    "addr:street":"Leys Lane",
    "iso:country":"GB",
    "sg:address":"Castle Gayer, Leys Lane",
    "sg:city":"Marazion",
    "sg:classifiers":[
        {
            "category":"Health Services",
            "subcategory":"Podiatrist",
            "type":"Services"
        }
    ],
    "sg:postcode":"TR17 0AQ",
    "sg:province":"Cornwall",
    "sg:tags":[
        "podiatrists",
        "chiropodist"
    ],
    "wof:name":"Ivory Brian S Chiropodist & Reflexologist",
    "wof:placetype":"venue"
},
  "geometry": {"coordinates":[-5.4598240852,50.1239891052],"type":"Point"}
}