{
  "type": "Feature",
  "properties": {
    "iso:country":"GB",
    "sg:address":"277 New North Road",
    "sg:city":"London",
    "sg:classifiers":[
        {
            "category":"Food & Beverages",
            "subcategory":"Liquor & Beverages",
            "type":"Retail Goods"
        }
    ],
    "sg:phone":"+44 20 7226 5173",
    "sg:postcode":"N1 7AA",
    "sg:province":"Greater London",
    "sg:tags":[
        "beer",
        "spirit",
        "wines"
    ],
    "wof:name":"The Wine Centre",
    "wof:placetype":"venue"
},
  "geometry": {"coordinates":[-0.0916009992,51.5376281738],"type":"Point"}
}