{
  "type": "Feature",
  "properties": {
    "addr:full":"Woodkirk International Freight T, Erminal Quarry Lane Dewsbury West Yorkshire WF12 7JJ",
    "addr:postcode":"wf12 7jj",
    "addr:street":"Quarry Lane",
    "iso:country":"GB",
    "sg:address":"Woodkirk International Freight T, Erminal Quarry Lane",
    "sg:city":"Dewsbury",
    "sg:classifiers":[
        {
            "category":"Freight",
            "type":"Transportation"
        }
    ],
    "sg:phone":"+44 1924 423655",
    "sg:postcode":"WF12 7JJ",
    "sg:province":"West Yorkshire",
    "sg:tags":[
        "haulage",
        "road"
    ],
    "wof:name":"S Bingham Transport Ltd.",
    "wof:placetype":"venue"
},
  "geometry": {"coordinates":[-1.5968799591,53.7189292908],"type":"Point"}
}