{
  "type": "Feature",
  "properties": {
    "iso:country":"GB",
    "sg:address":"30 Bournemouth Road, Lower Parkstone",
    "sg:city":"Poole",
    "sg:classifiers":[
        {
            "category":"Health Services",
            "subcategory":"Dentist",
            "type":"Services"
        }
    ],
    "sg:phone":"+44 1202 741622",
    "sg:postcode":"BH14 0ES",
    "sg:province":"Dorset",
    "wof:name":"JOHN F AHEARNE",
    "wof:placetype":"venue"
},
  "geometry": {"coordinates":[-1.9425990582,50.7249984741],"type":"Point"}
}