{
  "type": "Feature",
  "properties": {
    "addr:full":"Coventry & Warwickshire Hospital Coventry West Midlands CV1 4FH",
    "addr:postcode":"cv1 4fh",
    "iso:country":"GB",
    "sg:address":"Coventry & Warwickshire Hospital",
    "sg:city":"Coventry",
    "sg:classifiers":[
        {
            "category":"Health Services",
            "subcategory":"Clinic",
            "type":"Services"
        }
    ],
    "sg:phone":"+44 24 7684 4171",
    "sg:postcode":"CV1 4FH",
    "sg:province":"West Midlands",
    "sg:tags":[
        "nh",
        "private"
    ],
    "wof:name":"Women's Health & Information Centre",
    "wof:placetype":"venue"
},
  "geometry": {"coordinates":[-1.50786,52.413921],"type":"Point"}
}