{
  "type": "Feature",
  "properties": {
    "addr:full":"Unit 1, Zaim Trading Estate, Leaside Road London Greater London E5 9LU",
    "addr:housenumber":"unit 1",
    "addr:postcode":"e5 9lu",
    "addr:street":"Trading;Leaside Road",
    "iso:country":"GB",
    "sg:address":"Unit 1, Zaim Trading Estate, Leaside Road",
    "sg:city":"London",
    "sg:classifiers":[
        {
            "category":"Manufacturing",
            "subcategory":"Apparel",
            "type":"Manufacturing & Wholesale Goods"
        }
    ],
    "sg:phone":"+44 20 8806 6185",
    "sg:postcode":"E5 9LU",
    "sg:province":"Greater London",
    "sg:tags":[
        "shirt",
        "maker"
    ],
    "wof:name":"Tradepress (London) Ltd.",
    "wof:placetype":"venue"
},
  "geometry": {"coordinates":[-0.05225,51.566921],"type":"Point"}
}