{
  "type": "Feature",
  "properties": {
    "addr:full":"230 County Road, Walton Liverpool Merseyside L4 5TR",
    "addr:housenumber":"230",
    "addr:postcode":"l4 5tr",
    "addr:street":"County Road",
    "iso:country":"GB",
    "sg:address":"230 County Road, Walton",
    "sg:city":"Liverpool",
    "sg:classifiers":[
        {
            "category":"Wholesale",
            "subcategory":"Office Equipment",
            "type":"Manufacturing & Wholesale Goods"
        }
    ],
    "sg:phone":"+44 151 525 1712",
    "sg:postcode":"L4 5TR",
    "sg:province":"Merseyside",
    "sg:tags":[
        "register",
        "cash",
        "accessory"
    ],
    "wof:name":"F C R Cash Registers",
    "wof:placetype":"venue"
},
  "geometry": {"coordinates":[-2.96842,53.444786],"type":"Point"}
}