{
  "type": "Feature",
  "properties": {
    "iso:country":"GB",
    "sg:address":"21 Heavitree Road",
    "sg:city":"Exeter",
    "sg:classifiers":[
        {
            "category":"Restaurant",
            "type":"Food & Drink"
        }
    ],
    "sg:phone":"+44 1392 426600",
    "sg:postcode":"EX1 2LD",
    "sg:province":"Devon",
    "wof:name":"Harpoon Louie's Restaurant",
    "wof:placetype":"venue"
},
  "geometry": {"coordinates":[-3.520999,50.724815],"type":"Point"}
}