{
  "type": "Feature",
  "properties": {
    "addr:full":"Corporation Road Birkenhead Merseyside CH41 1LB",
    "addr:postcode":"ch41 1lb",
    "addr:street":"Corporation Road",
    "iso:country":"GB",
    "sg:address":"Corporation Road",
    "sg:city":"Birkenhead",
    "sg:classifiers":[
        {
            "category":"Building & Trades",
            "subcategory":"Construction",
            "type":"Services"
        }
    ],
    "sg:postcode":"CH41 1LB",
    "sg:province":"Merseyside",
    "sg:tags":[
        "decorator",
        "painter"
    ],
    "wof:name":"K J Mock Ltd.",
    "wof:placetype":"venue"
},
  "geometry": {"coordinates":[-3.033108,53.400837],"type":"Point"}
}