{
  "type": "Feature",
  "properties": {
    "addr:full":"Clock House One, Rookery Park, Yoxford Saxmundham Suffolk IP17 3HQ",
    "addr:housenumber":"saxmundham",
    "addr:postcode":"ip17 3hq",
    "iso:country":"GB",
    "sg:address":"Clock House One, Rookery Park, Yoxford",
    "sg:city":"Saxmundham",
    "sg:classifiers":[
        {
            "category":"Professional",
            "subcategory":"Advertising",
            "type":"Services"
        }
    ],
    "sg:phone":"+44 1728 668204",
    "sg:postcode":"IP17 3HQ",
    "sg:province":"Suffolk",
    "sg:tags":[
        "agency"
    ],
    "wof:name":"The Macalister Consultancy",
    "wof:placetype":"venue"
},
  "geometry": {"coordinates":[1.510412,52.265541],"type":"Point"}
}