{
  "type": "Feature",
  "properties": {
    "iso:country":"GB",
    "sg:address":"10 Blackpark Avenue",
    "sg:city":"Invergordon",
    "sg:classifiers":[
        {
            "category":"Home & Garden",
            "subcategory":"Household Appliances",
            "type":"Retail Goods"
        },
        {
            "category":"Retail",
            "subcategory":"Repair Shop",
            "type":"Services"
        }
    ],
    "sg:phone":"+44 1349 854128",
    "sg:postcode":"IV18 0HY",
    "sg:province":"Highland",
    "sg:tags":[
        "machine",
        "electrical",
        "washing"
    ],
    "wof:name":"Edward Mackay",
    "wof:placetype":"venue"
},
  "geometry": {"coordinates":[-4.154362,57.696495],"type":"Point"}
}