{
  "type": "Feature",
  "properties": {
    "iso:country":"GB",
    "sg:address":"Little Bovey Farm, Bovey Tracey",
    "sg:city":"Newton Abbot",
    "sg:classifiers":[
        {
            "category":"Farming",
            "subcategory":"Livestock Farm",
            "type":"Manufacturing & Wholesale Goods"
        },
        {
            "category":"Farming",
            "subcategory":"Farm",
            "type":"Manufacturing & Wholesale Goods"
        }
    ],
    "sg:phone":"+44 1626 833471",
    "sg:postcode":"TQ13 9PN",
    "sg:province":"Devon",
    "sg:tags":[
        "mixed",
        "crop",
        "others"
    ],
    "wof:name":"H & E Vooght",
    "wof:placetype":"venue"
},
  "geometry": {"coordinates":[-3.6750590801,50.593208313],"type":"Point"}
}