{
  "type": "Feature",
  "properties": {
    "addr:full":"1 The Laurels, Oatlands Drive Weybridge Surrey KT13 9LF",
    "addr:housenumber":"1",
    "addr:postcode":"kt13 9lf",
    "addr:street":"The Laurels Oatlands Drive",
    "iso:country":"GB",
    "sg:address":"1 The Laurels, Oatlands Drive",
    "sg:city":"Weybridge",
    "sg:classifiers":[
        {
            "category":"Health Services",
            "subcategory":"Health Practitioner",
            "type":"Services"
        }
    ],
    "sg:phone":"+44 1932 841399",
    "sg:postcode":"KT13 9LF",
    "sg:province":"Surrey",
    "sg:tags":[
        "hypnotherapists"
    ],
    "wof:name":"Oatlands Hypnotherapy",
    "wof:placetype":"venue"
},
  "geometry": {"coordinates":[-0.437761,51.373901],"type":"Point"}
}