{
  "type": "Feature",
  "properties": {
    "iso:country":"GB",
    "sg:address":"33 St Johns Way, Corringham",
    "sg:city":"Stanford-le-hope",
    "sg:classifiers":[
        {
            "category":"Home & Garden",
            "subcategory":"Hardware",
            "type":"Retail Goods"
        }
    ],
    "sg:phone":"+44 1375 673014",
    "sg:postcode":"SS17 7NA",
    "sg:province":"Essex",
    "sg:tags":[
        "shop",
        "retailer",
        "diy"
    ],
    "sg:website":"http://www.corringham-diy.freeserve.co.uk",
    "wof:name":"Corringham D I Y Centre",
    "wof:placetype":"venue"
},
  "geometry": {"coordinates":[0.448282,51.524773],"type":"Point"}
}