{
  "type": "Feature",
  "properties": {
    "iso:country":"GB",
    "sg:address":"6 Garden Street",
    "sg:city":"Cromer",
    "sg:classifiers":[
        {
            "category":"Professional",
            "subcategory":"Management & Consulting",
            "type":"Services"
        },
        {
            "category":"Professional",
            "subcategory":"Advertising",
            "type":"Services"
        }
    ],
    "sg:phone":"+44 1263 511864",
    "sg:postcode":"NR27 9HN",
    "sg:province":"Norfolk",
    "sg:tags":[
        "marketing",
        "mail",
        "direct",
        "consultant"
    ],
    "wof:name":"M & A SERVICES",
    "wof:placetype":"venue"
},
  "geometry": {"coordinates":[1.299262,52.93137],"type":"Point"}
}