{
  "type": "Feature",
  "properties": {
    "addr:full":"20 Dudley Road Southall Greater London UB2 5AR",
    "addr:housenumber":"20",
    "addr:postcode":"ub2 5ar",
    "addr:street":"Dudley Road",
    "iso:country":"GB",
    "sg:address":"20 Dudley Road",
    "sg:city":"Southall",
    "sg:classifiers":[
        {
            "category":"Fast Food",
            "type":"Food & Drink"
        }
    ],
    "sg:phone":"+44 20 8574 2019",
    "sg:postcode":"UB2 5AR",
    "sg:province":"Greater London",
    "sg:tags":[
        "away",
        "meal",
        "outlet",
        "take"
    ],
    "wof:name":"Punjab Sweet House",
    "wof:placetype":"venue"
},
  "geometry": {"coordinates":[-0.386341989,51.5026779175],"type":"Point"}
}