{
  "type": "Feature",
  "properties": {
    "iso:country":"GB",
    "sg:address":"59 Troughbrook Road, Hollingwood",
    "sg:city":"Chesterfield",
    "sg:classifiers":[
        {
            "category":"Arts & Performance",
            "subcategory":"Music",
            "type":"Entertainment"
        }
    ],
    "sg:postcode":"S43 2JW",
    "sg:province":"Derbyshire",
    "sg:tags":[
        "mobile",
        "disco"
    ],
    "wof:name":"Abbey Lane Disco Entertainment",
    "wof:placetype":"venue"
},
  "geometry": {"coordinates":[-1.377258,53.263565],"type":"Point"}
}