{
  "type": "Feature",
  "properties": {
    "addr:full":"Pyewipe Road Grimsby Lincolnshire DN31 2QN",
    "addr:postcode":"dn31 2qn",
    "addr:street":"Pyewipe Road",
    "iso:country":"GB",
    "sg:address":"Pyewipe Road",
    "sg:city":"Grimsby",
    "sg:classifiers":[
        {
            "category":"Manufacturing",
            "subcategory":"Building Materials",
            "type":"Manufacturing & Wholesale Goods"
        }
    ],
    "sg:phone":"+44 1472 350205",
    "sg:postcode":"DN31 2QN",
    "sg:province":"Lincolnshire",
    "sg:tags":[
        "merchant",
        "builder"
    ],
    "wof:name":"Jewson Ltd.",
    "wof:placetype":"venue"
},
  "geometry": {"coordinates":[-0.0975989997,53.5724983215],"type":"Point"}
}