{
  "type": "Feature",
  "properties": {
    "addr:full":"38a Fore St Ivybridge Devon PL21 9AE",
    "addr:housenumber":"38a",
    "addr:postcode":"pl21 9ae",
    "addr:street":"Fore St",
    "iso:country":"GB",
    "sg:address":"38a Fore St",
    "sg:city":"Ivybridge",
    "sg:classifiers":[
        {
            "category":"Shopping",
            "subcategory":"Gifts & Souvenirs",
            "type":"Retail Goods"
        }
    ],
    "sg:postcode":"PL21 9AE",
    "sg:province":"Devon",
    "sg:tags":[
        "shop"
    ],
    "wof:name":"Heaven Sent",
    "wof:placetype":"venue"
},
  "geometry": {"coordinates":[-3.9233191013,50.3885345459],"type":"Point"}
}