{
  "type": "Feature",
  "properties": {
    "addr:full":"67-71 Mian St Glasgow East Renfrewshire G46 7RX",
    "addr:housenumber":"67-71",
    "addr:postcode":"g46 7rx",
    "addr:street":"Mian St",
    "iso:country":"GB",
    "sg:address":"67-71 Mian St",
    "sg:city":"Glasgow",
    "sg:classifiers":[
        {
            "category":"Bars & Pubs",
            "type":"Food & Drink"
        }
    ],
    "sg:phone":"+44 141 621 2041",
    "sg:postcode":"G46 7RX",
    "sg:province":"East Renfrewshire",
    "sg:tags":[
        "pubs",
        "inn"
    ],
    "wof:name":"Rowallan Bar",
    "wof:placetype":"venue"
},
  "geometry": {"coordinates":[-4.3068590164,55.8012809753],"type":"Point"}
}