{
  "type": "Feature",
  "properties": {
    "addr:full":"358 Kilburn High Road London Greater London NW6 2QH",
    "addr:housenumber":"358",
    "addr:postcode":"nw6 2qh",
    "addr:street":"Kilburn High Road",
    "iso:country":"GB",
    "sg:address":"358 Kilburn High Road",
    "sg:city":"London",
    "sg:classifiers":[
        {
            "category":"Organizations",
            "subcategory":"Membership Organization",
            "type":"Services"
        }
    ],
    "sg:postcode":"NW6 2QH",
    "sg:province":"Greater London",
    "sg:tags":[
        "club"
    ],
    "wof:name":"3, Eaton Place Management Ltd",
    "wof:placetype":"venue"
},
  "geometry": {"coordinates":[-0.203343,51.546864],"type":"Point"}
}