{
  "type": "Feature",
  "properties": {
    "iso:country":"GB",
    "sg:address":"30 The Broadway, Wimbledon",
    "sg:city":"Wimbledon",
    "sg:classifiers":[
        {
            "category":"Food & Beverages",
            "subcategory":"Bakery",
            "type":"Retail Goods"
        }
    ],
    "sg:phone":"+44 20 8946 6976",
    "sg:postcode":"SW19 1RE",
    "sg:province":"Greater London",
    "sg:tags":[
        "baker"
    ],
    "wof:name":"Bakers Oven The",
    "wof:placetype":"venue"
},
  "geometry": {"coordinates":[-0.204456,51.419956],"type":"Point"}
}