{
  "type": "Feature",
  "properties": {
    "addr:full":"6 Quay Road Bridlington East Riding of Yorkshire YO15 2SB",
    "addr:housenumber":"6",
    "addr:postcode":"yo15 2sb",
    "addr:street":"Quay Road",
    "iso:country":"GB",
    "sg:address":"6 Quay Road",
    "sg:city":"Bridlington",
    "sg:classifiers":[
        {
            "category":"Insurance",
            "subcategory":"Insurance Agent",
            "type":"Services"
        }
    ],
    "sg:phone":"+44 1262 672236",
    "sg:postcode":"YO15 2SB",
    "sg:province":"East Riding of Yorkshire",
    "sg:tags":[
        "broker"
    ],
    "sg:website":"http://www.cpbennet.co.uk",
    "wof:name":"C P Bennet Ltd",
    "wof:placetype":"venue"
},
  "geometry": {"coordinates":[-0.1940290034,54.0849151611],"type":"Point"}
}