{
  "type": "Feature",
  "properties": {
    "iso:country":"GB",
    "sg:address":"Sunnyside, High Street, Yetminster",
    "sg:city":"Sherborne",
    "sg:classifiers":[
        {
            "category":"Personal",
            "subcategory":"Beauty Salon",
            "type":"Services"
        },
        {
            "category":"Personal",
            "subcategory":"Barber",
            "type":"Services"
        }
    ],
    "sg:phone":"+44 1935 873163",
    "sg:postcode":"DT9 6LF",
    "sg:province":"Dorset",
    "sg:tags":[
        "unisex",
        "hairdresser"
    ],
    "wof:name":"Georgies",
    "wof:placetype":"venue"
},
  "geometry": {"coordinates":[-2.581434,50.894821],"type":"Point"}
}