{
  "type": "Feature",
  "properties": {
    "addr:full":"57 Delapre Crescent Road Northampton Northamptonshire NN4 8NG",
    "addr:housenumber":"57",
    "addr:postcode":"nn4 8ng",
    "addr:street":"Delapre Crescent Road",
    "iso:country":"GB",
    "sg:address":"57 Delapre Crescent Road",
    "sg:city":"Northampton",
    "sg:classifiers":[
        {
            "category":"Taxi",
            "type":"Transportation"
        },
        {
            "category":"Military Area",
            "subcategory":"Air Force Base",
            "type":"Public Place"
        }
    ],
    "sg:phone":"+44 1604 764678",
    "sg:postcode":"NN4 8NG",
    "sg:province":"Northamptonshire",
    "sg:tags":[
        "hire",
        "private"
    ],
    "wof:name":"Take 6 Taxis",
    "wof:placetype":"venue"
},
  "geometry": {"coordinates":[-0.902278,52.225636],"type":"Point"}
}