{
  "type": "Feature",
  "properties": {
    "iso:country":"GB",
    "sg:address":"19 Cross St, Enderby",
    "sg:city":"Leicester",
    "sg:classifiers":[
        {
            "category":"Food & Beverages",
            "subcategory":"Supermarket",
            "type":"Retail Goods"
        }
    ],
    "sg:phone":"+44 116 286 7303",
    "sg:postcode":"LE9 5NJ",
    "sg:province":"Leicestershire",
    "wof:name":"Kwik Save Foodstores",
    "wof:placetype":"venue"
},
  "geometry": {"coordinates":[-1.20646,52.588631],"type":"Point"}
}