{
  "type": "Feature",
  "properties": {
    "iso:country":"GB",
    "sg:address":"Mill Lane, Fillongley",
    "sg:city":"Coventry",
    "sg:classifiers":[
        {
            "category":"Travel",
            "subcategory":"Hotels & Motels",
            "type":"Entertainment"
        }
    ],
    "sg:postcode":"CV7 8EE",
    "sg:province":"Warwickshire",
    "sg:tags":[
        "house",
        "guest"
    ],
    "wof:name":"Mill Farm House",
    "wof:placetype":"venue"
},
  "geometry": {"coordinates":[-1.60216,52.489841],"type":"Point"}
}