{
  "type": "Feature",
  "properties": {
    "addr:full":"The Poplars, Croxton Road, Fulmodestone Fakenham Norfolk NR21 0NJ",
    "addr:postcode":"nr21 0nj",
    "addr:street":"Croxton Road;Fakenham",
    "iso:country":"GB",
    "sg:address":"The Poplars, Croxton Road, Fulmodestone",
    "sg:city":"Fakenham",
    "sg:classifiers":[
        {
            "category":"Farming",
            "subcategory":"Livestock Farm",
            "type":"Manufacturing & Wholesale Goods"
        }
    ],
    "sg:phone":"+44 1328 878328",
    "sg:postcode":"NR21 0NJ",
    "sg:province":"Norfolk",
    "sg:tags":[
        "others"
    ],
    "wof:name":"Picken Holdings",
    "wof:placetype":"venue"
},
  "geometry": {"coordinates":[0.945159018,52.8409423828],"type":"Point"}
}