{
  "type": "Feature",
  "properties": {
    "addr:full":"81-82 Old Broad Street London Greater London EC2M 1PR",
    "addr:housenumber":"81-82",
    "addr:postcode":"ec2m 1pr",
    "addr:street":"Old Broad Street",
    "iso:country":"GB",
    "sg:address":"81-82 Old Broad Street",
    "sg:city":"London",
    "sg:classifiers":[
        {
            "category":"Bars & Pubs",
            "subcategory":"Wine Bar",
            "type":"Food & Drink"
        }
    ],
    "sg:phone":"+44 20 7920 9645",
    "sg:postcode":"EC2M 1PR",
    "sg:province":"Greater London",
    "wof:name":"Gows Restaurant",
    "wof:placetype":"venue"
},
  "geometry": {"coordinates":[-0.083123,51.516975],"type":"Point"}
}