{
  "type": "Feature",
  "properties": {
    "iso:country":"GB",
    "sg:address":"9 The Parade",
    "sg:city":"Leamington Spa",
    "sg:classifiers":[
        {
            "category":"Restaurant",
            "type":"Food & Drink"
        }
    ],
    "sg:phone":"+44 1926 887455",
    "sg:postcode":"CV32 4DW",
    "sg:province":"Warwickshire",
    "wof:name":"Oriental Star",
    "wof:placetype":"venue"
},
  "geometry": {"coordinates":[-1.5357849598,52.2931022644],"type":"Point"}
}