{
  "type": "Feature",
  "properties": {
    "iso:country":"GB",
    "sg:address":"Bishop Shopping Centre, Bath Road, Taplow",
    "sg:city":"Maidenhead",
    "sg:classifiers":[
        {
            "category":"Home & Garden",
            "subcategory":"Furniture",
            "type":"Retail Goods"
        }
    ],
    "sg:phone":"+44 1628 605444",
    "sg:postcode":"SL6 0NY",
    "sg:province":"Berkshire",
    "wof:name":"Sharps Bedrooms",
    "wof:placetype":"venue"
},
  "geometry": {"coordinates":[-0.687149,51.532169],"type":"Point"}
}