{
  "type": "Feature",
  "properties": {
    "iso:country":"GB",
    "sg:address":"Langley Avenue",
    "sg:city":"Felixstowe",
    "sg:classifiers":[
        {
            "category":"Community Center",
            "type":"Public Place"
        },
        {
            "category":"Government",
            "subcategory":"Office",
            "type":"Public Place"
        }
    ],
    "sg:phone":"+44 1394 279724",
    "sg:postcode":"IP11 2NA",
    "sg:province":"Suffolk",
    "sg:tags":[
        "local",
        "centre"
    ],
    "wof:name":"Layden Community Centre",
    "wof:placetype":"venue"
},
  "geometry": {"coordinates":[1.33446,51.966579],"type":"Point"}
}