{
  "type": "Feature",
  "properties": {
    "addr:full":"71 High Street Alness Highland IV17 0SH",
    "addr:housenumber":"71",
    "addr:postcode":"iv17 0sh",
    "addr:street":"High Street",
    "iso:country":"GB",
    "sg:address":"71 High Street",
    "sg:city":"Alness",
    "sg:classifiers":[
        {
            "category":"Personal",
            "subcategory":"Beauty Salon",
            "type":"Services"
        }
    ],
    "sg:postcode":"IV17 0SH",
    "sg:province":"Highland",
    "sg:tags":[
        "lady",
        "hairdresser"
    ],
    "wof:name":"Sylk Hair Fashion",
    "wof:placetype":"venue"
},
  "geometry": {"coordinates":[-4.2526931763,57.6958427429],"type":"Point"}
}