{
  "type": "Feature",
  "properties": {
    "iso:country":"GB",
    "sg:address":"Lyndale, Dyson La",
    "sg:city":"Sowerby Bridge",
    "sg:classifiers":[
        {
            "category":"Building & Trades",
            "subcategory":"Construction",
            "type":"Services"
        }
    ],
    "sg:phone":"+44 1422 822212",
    "sg:postcode":"HX6 4EN",
    "sg:province":"West Yorkshire",
    "sg:tags":[
        "joiner",
        "carpenter"
    ],
    "wof:name":"O & Kw Crawshaw Ltd",
    "wof:placetype":"venue"
},
  "geometry": {"coordinates":[-1.913934,53.706539],"type":"Point"}
}