{
  "type": "Feature",
  "properties": {
    "iso:country":"GB",
    "sg:address":"Olney Road, Yardley Hastings",
    "sg:city":"Northampton",
    "sg:classifiers":[
        {
            "category":"Farming",
            "subcategory":"Livestock Farm",
            "type":"Manufacturing & Wholesale Goods"
        }
    ],
    "sg:postcode":"NN7 1HL",
    "sg:province":"Buckinghamshire",
    "sg:tags":[
        "others"
    ],
    "wof:name":"Pasture Pigs",
    "wof:placetype":"venue"
},
  "geometry": {"coordinates":[-0.734026,52.20377],"type":"Point"}
}