{
  "type": "Feature",
  "properties": {
    "iso:country":"GB",
    "sg:address":"62-64 Market St",
    "sg:city":"Ashby-de-la-zouch",
    "sg:classifiers":[
        {
            "category":"Professional",
            "subcategory":"Engineering",
            "type":"Services"
        }
    ],
    "sg:phone":"+44 1530 563456",
    "sg:postcode":"LE65 1AN",
    "sg:province":"Derbyshire",
    "sg:tags":[
        "contractor",
        "electrical",
        "engineer"
    ],
    "wof:name":"Thomassen U K Ltd",
    "wof:placetype":"venue"
},
  "geometry": {"coordinates":[-1.473344,52.746651],"type":"Point"}
}