{
  "type": "Feature",
  "properties": {
    "iso:country":"GB",
    "sg:address":"131a-133 Dumbarton Avenue",
    "sg:city":"Stockton-on-tees",
    "sg:classifiers":[
        {
            "category":"Food & Beverages",
            "subcategory":"Groceries & Convenience Stores",
            "type":"Retail Goods"
        }
    ],
    "sg:phone":"+44 1642 608362",
    "sg:postcode":"TS19 0LN",
    "sg:province":"Durham",
    "wof:name":"Jones's",
    "wof:placetype":"venue"
},
  "geometry": {"coordinates":[-1.325482,54.581841],"type":"Point"}
}