{
  "type": "Feature",
  "properties": {
    "addr:full":"1 Clochranhill Road Ayr South Ayrshire KA7 4PZ",
    "addr:housenumber":"1",
    "addr:postcode":"ka7 4pz",
    "addr:street":"Clochranhill Road",
    "iso:country":"GB",
    "sg:address":"1 Clochranhill Road",
    "sg:city":"Ayr",
    "sg:classifiers":[
        {
            "category":"Retail",
            "subcategory":"Driving School",
            "type":"Services"
        }
    ],
    "sg:postcode":"KA7 4PZ",
    "sg:province":"South Ayrshire",
    "wof:name":"Alloway School of Motoring",
    "wof:placetype":"venue"
},
  "geometry": {"coordinates":[-4.632493,55.433407],"type":"Point"}
}