{
  "type": "Feature",
  "properties": {
    "addr:full":"Drumshoreland Cadet Centre Broxburn City of Edinburgh EH52 5PD",
    "addr:postcode":"eh52 5pd",
    "iso:country":"GB",
    "sg:address":"Drumshoreland Cadet Centre",
    "sg:city":"Broxburn",
    "sg:classifiers":[
        {
            "category":"Community Center",
            "subcategory":"Youth",
            "type":"Public Place"
        }
    ],
    "sg:phone":"+44 1506 858094",
    "sg:postcode":"EH52 5PD",
    "sg:province":"City of Edinburgh",
    "sg:tags":[
        "organisation",
        "centre"
    ],
    "wof:name":"D W Anderson",
    "wof:placetype":"venue"
},
  "geometry": {"coordinates":[-3.4718840122,55.9342346191],"type":"Point"}
}