{
  "type": "Feature",
  "properties": {
    "addr:full":"Unit 17, Victoria Works Burnley Lancashire BB11 5EF",
    "addr:housenumber":"unit 17",
    "addr:postcode":"bb11 5ef",
    "addr:street":"Victoria Works",
    "iso:country":"GB",
    "sg:address":"Unit 17, Victoria Works",
    "sg:city":"Burnley",
    "sg:classifiers":[
        {
            "category":"Retail",
            "subcategory":"Auto Repair",
            "type":"Services"
        }
    ],
    "sg:phone":"+44 1282 411686",
    "sg:postcode":"BB11 5EF",
    "sg:province":"Lancashire",
    "sg:tags":[
        "body",
        "car"
    ],
    "wof:name":"E & B Car Repairs",
    "wof:placetype":"venue"
},
  "geometry": {"coordinates":[-2.243809,53.78801],"type":"Point"}
}