{
  "type": "Feature",
  "properties": {
    "iso:country":"GB",
    "sg:address":"135-137 High St",
    "sg:city":"Ilford",
    "sg:classifiers":[
        {
            "category":"Home & Garden",
            "subcategory":"Furniture",
            "type":"Retail Goods"
        }
    ],
    "sg:phone":"+44 20 8550 0010",
    "sg:postcode":"IG6 2AJ",
    "sg:province":"Essex",
    "wof:name":"Davidsons",
    "wof:placetype":"venue"
},
  "geometry": {"coordinates":[0.083653,51.59235],"type":"Point"}
}