{
  "type": "Feature",
  "properties": {
    "addr:full":"54 Long Street Atherstone Leicestershire CV9 1AU",
    "addr:housenumber":"54",
    "addr:postcode":"cv9 1au",
    "addr:street":"Long Street",
    "iso:country":"GB",
    "sg:address":"54 Long Street",
    "sg:city":"Atherstone",
    "sg:classifiers":[
        {
            "category":"Travel",
            "subcategory":"Travel Agent",
            "type":"Entertainment"
        }
    ],
    "sg:phone":"+44 1827 720775",
    "sg:postcode":"CV9 1AU",
    "sg:province":"Leicestershire",
    "sg:tags":[
        "agency",
        "activity"
    ],
    "wof:name":"Bowen Travel Ltd",
    "wof:placetype":"venue"
},
  "geometry": {"coordinates":[-1.5481250286,52.5779418945],"type":"Point"}
}