{
  "type": "Feature",
  "properties": {
    "addr:full":"Unit 5 Highcliffe Corner, Lymington Road Christchurch Dorset BH23 5EL",
    "addr:housenumber":"unit 5",
    "addr:postcode":"bh23 5el",
    "addr:street":"Lymington Road",
    "iso:country":"GB",
    "sg:address":"Unit 5 Highcliffe Corner, Lymington Road",
    "sg:city":"Christchurch",
    "sg:classifiers":[
        {
            "category":"Retail",
            "subcategory":"Laundry & Dry Cleaning",
            "type":"Services"
        }
    ],
    "sg:postcode":"BH23 5EL",
    "sg:province":"Dorset",
    "sg:tags":[
        "launderette"
    ],
    "wof:name":"Highcliffe Laundrette",
    "wof:placetype":"venue"
},
  "geometry": {"coordinates":[-1.776564,50.73407],"type":"Point"}
}