{
  "type": "Feature",
  "properties": {
    "addr:full":"1 Ripple Villas, Ripple Road Barking Essex IG11 0SR",
    "addr:housenumber":"1",
    "addr:postcode":"ig11 0sr",
    "addr:street":"Ripple Villas Ripple Road",
    "iso:country":"GB",
    "sg:address":"1 Ripple Villas, Ripple Road",
    "sg:city":"Barking",
    "sg:classifiers":[
        {
            "category":"Manufacturing",
            "subcategory":"Metals",
            "type":"Manufacturing & Wholesale Goods"
        }
    ],
    "sg:phone":"+44 20 8592 4600",
    "sg:postcode":"IG11 0SR",
    "sg:province":"Essex",
    "sg:tags":[
        "work",
        "sheet"
    ],
    "wof:name":"Charndell Ltd.",
    "wof:placetype":"venue"
},
  "geometry": {"coordinates":[0.122105,51.531727],"type":"Point"}
}