{
  "type": "Feature",
  "properties": {
    "addr:full":"153 Portobello Road London Greater London W11 2DY",
    "addr:housenumber":"153",
    "addr:postcode":"w11 2dy",
    "addr:street":"Portobello Road",
    "iso:country":"GB",
    "sg:address":"153 Portobello Road",
    "sg:city":"London",
    "sg:classifiers":[
        {
            "category":"Communications",
            "subcategory":"Film & Video Production",
            "type":"Services"
        },
        {
            "category":"Professional",
            "subcategory":"Art Services",
            "type":"Services"
        }
    ],
    "sg:phone":"+44 20 7229 2248",
    "sg:postcode":"W11 2DY",
    "sg:province":"Greater London",
    "sg:tags":[
        "picture",
        "frame",
        "restoration",
        "cleaning"
    ],
    "wof:name":"Daggett Gallery",
    "wof:placetype":"venue"
},
  "geometry": {"coordinates":[-0.2044180036,51.5145072937],"type":"Point"}
}