{
  "type": "Feature",
  "properties": {
    "iso:country":"GB",
    "sg:address":"The Old Station, Exeter Road",
    "sg:city":"Ottery St Mary",
    "sg:classifiers":[
        {
            "category":"Organizations",
            "subcategory":"Non-profit Organization",
            "type":"Services"
        }
    ],
    "sg:phone":"+44 1404 815869",
    "sg:postcode":"EX11 1AH",
    "sg:province":"Devon",
    "sg:tags":[
        "organisation",
        "voluntary",
        "charity"
    ],
    "wof:name":"East Devon Volunteer Support Agency",
    "wof:placetype":"venue"
},
  "geometry": {"coordinates":[-3.283026,50.751137],"type":"Point"}
}