{
  "type": "Feature",
  "properties": {
    "addr:full":"31a High Street Rayleigh Essex SS6 7EW",
    "addr:housenumber":"31a",
    "addr:postcode":"ss6 7ew",
    "addr:street":"High Street Rayleigh",
    "iso:country":"GB",
    "sg:address":"31a High Street",
    "sg:city":"Rayleigh",
    "sg:classifiers":[
        {
            "category":"Retail",
            "subcategory":"Photofinishing",
            "type":"Services"
        }
    ],
    "sg:phone":"+44 1268 775040",
    "sg:postcode":"SS6 7EW",
    "sg:province":"Essex",
    "sg:tags":[
        "photographic",
        "processor"
    ],
    "wof:name":"Phoenix Photographic",
    "wof:placetype":"venue"
},
  "geometry": {"coordinates":[0.6071940064,51.5870742798],"type":"Point"}
}