{
  "type": "Feature",
  "properties": {
    "iso:country":"GB",
    "sg:address":"18 Walmer Crescent",
    "sg:city":"Glasgow",
    "sg:classifiers":[
        {
            "category":"Travel",
            "subcategory":"Hotels & Motels",
            "type":"Entertainment"
        }
    ],
    "sg:phone":"+44 141 427 5231",
    "sg:postcode":"G51 1AT",
    "sg:province":"Glasgow City",
    "sg:tags":[
        "house",
        "guest"
    ],
    "wof:name":"Amber Guest House",
    "wof:placetype":"venue"
},
  "geometry": {"coordinates":[-4.296714,55.852024],"type":"Point"}
}