{
  "type": "Feature",
  "properties": {
    "iso:country":"GB",
    "sg:address":"155 Gibraltar Street",
    "sg:city":"Sheffield",
    "sg:classifiers":[
        {
            "category":"Personal",
            "subcategory":"Tattoo Parlor",
            "type":"Services"
        }
    ],
    "sg:postcode":"S3 8UA",
    "sg:province":"South Yorkshire",
    "sg:tags":[
        "tattooing",
        "piercing"
    ],
    "wof:name":"Designer Skin Tattoo Studio",
    "wof:placetype":"venue"
},
  "geometry": {"coordinates":[-1.4715969563,53.3864974976],"type":"Point"}
}