{
  "type": "Feature",
  "properties": {
    "addr:full":"5 Castlegate York North Yorkshire YO1 9RN",
    "addr:housenumber":"5",
    "addr:postcode":"yo1 9rn",
    "addr:street":"Castlegate",
    "iso:country":"GB",
    "sg:address":"5 Castlegate",
    "sg:city":"York",
    "sg:classifiers":[
        {
            "category":"Bars & Pubs",
            "type":"Food & Drink"
        }
    ],
    "sg:phone":"+44 1904 659557",
    "sg:postcode":"YO1 9RN",
    "sg:province":"North Yorkshire",
    "sg:tags":[
        "pubs",
        "inn"
    ],
    "wof:name":"Little John Inn",
    "wof:placetype":"venue"
},
  "geometry": {"coordinates":[-1.0811760426,53.9575080872],"type":"Point"}
}