{
  "type": "Feature",
  "properties": {
    "addr:full":"12 Borovere Lane Alton Hampshire GU34 1PD",
    "addr:housenumber":"12",
    "addr:postcode":"gu34 1pd",
    "addr:street":"Borovere Lane",
    "iso:country":"GB",
    "sg:address":"12 Borovere Lane",
    "sg:city":"Alton",
    "sg:classifiers":[
        {
            "category":"Home & Garden",
            "subcategory":"Building Materials",
            "type":"Retail Goods"
        }
    ],
    "sg:phone":"+44 1420 88200",
    "sg:postcode":"GU34 1PD",
    "sg:province":"Hampshire",
    "sg:tags":[
        "fencing"
    ],
    "wof:name":"James Landscapes",
    "wof:placetype":"venue"
},
  "geometry": {"coordinates":[-0.980922,51.14323],"type":"Point"}
}