{
  "type": "Feature",
  "properties": {
    "addr:full":"30 Chapel Street, Cheadle Stoke-on-trent Staffordshire ST10 1DY",
    "addr:housenumber":"30",
    "addr:postcode":"st10 1dy",
    "addr:street":"Chapel Street Cheadle",
    "iso:country":"GB",
    "sg:address":"30 Chapel Street, Cheadle",
    "sg:city":"Stoke-on-trent",
    "sg:classifiers":[
        {
            "category":"Personal",
            "subcategory":"Beauty Salon",
            "type":"Services"
        }
    ],
    "sg:phone":"+44 1538 750678",
    "sg:postcode":"ST10 1DY",
    "sg:province":"Staffordshire",
    "sg:tags":[
        "unisex",
        "hairdresser"
    ],
    "wof:name":"Legends Hairdressing",
    "wof:placetype":"venue"
},
  "geometry": {"coordinates":[-1.987457037,52.9859580994],"type":"Point"}
}