{
  "type": "Feature",
  "properties": {
    "addr:full":"St Mawgan Newquay Cornwall TR8 4EP",
    "addr:postcode":"tr8 4ep",
    "addr:street":"St",
    "iso:country":"GB",
    "sg:address":"St Mawgan",
    "sg:city":"Newquay",
    "sg:classifiers":[
        {
            "category":"Bars & Pubs",
            "type":"Food & Drink"
        },
        {
            "category":"Brewery",
            "type":"Food & Drink"
        }
    ],
    "sg:phone":"+44 1637 860225",
    "sg:postcode":"TR8 4EP",
    "sg:province":"Cornwall",
    "sg:tags":[
        "house",
        "brewer",
        "public",
        "activity"
    ],
    "wof:name":"Falcon Inn",
    "wof:placetype":"venue"
},
  "geometry": {"coordinates":[-4.9972000122,50.4537582397],"type":"Point"}
}