{
  "type": "Feature",
  "properties": {
    "iso:country":"GB",
    "sg:address":"36 Pontmorlais",
    "sg:city":"Merthyr Tydfil",
    "sg:classifiers":[
        {
            "category":"Home & Garden",
            "subcategory":"Home Furnishings",
            "type":"Retail Goods"
        }
    ],
    "sg:postcode":"CF47 8UN",
    "sg:province":"Merthyr Tydfil",
    "sg:tags":[
        "awning",
        "canopy",
        "blinds"
    ],
    "wof:name":"Blinds Direct",
    "wof:placetype":"venue"
},
  "geometry": {"coordinates":[-3.380949,51.748718],"type":"Point"}
}