{
  "type": "Feature",
  "properties": {
    "addr:full":"The Old Glove Factory, Ladywell Barnstaple Devon EX31 1QT",
    "addr:postcode":"ex31 1qt",
    "addr:street":"Ladywell",
    "iso:country":"GB",
    "sg:address":"The Old Glove Factory, Ladywell",
    "sg:city":"Barnstaple",
    "sg:classifiers":[
        {
            "category":"Building & Trades",
            "subcategory":"Landscaping Services",
            "type":"Services"
        },
        {
            "category":"Real Estate",
            "subcategory":"Architect",
            "type":"Services"
        }
    ],
    "sg:phone":"+44 1271 374485",
    "sg:postcode":"EX31 1QT",
    "sg:province":"Devon",
    "sg:tags":[
        "contractor"
    ],
    "wof:name":"David Wilson Partnership",
    "wof:placetype":"venue"
},
  "geometry": {"coordinates":[-4.060794,51.088406],"type":"Point"}
}