{
  "type": "Feature",
  "properties": {
    "addr:full":"Unit 1 & 2, Lagos Farm Yard Billericay Essex CM11 2YL",
    "addr:housenumber":"unit 1 & 2",
    "addr:postcode":"cm11 2yl",
    "addr:street":"Lagos Farm Yard",
    "iso:country":"GB",
    "sg:address":"Unit 1 & 2, Lagos Farm Yard",
    "sg:city":"Billericay",
    "sg:classifiers":[
        {
            "category":"Retail",
            "subcategory":"Auto Repair",
            "type":"Services"
        }
    ],
    "sg:postcode":"CM11 2YL",
    "sg:province":"Essex",
    "sg:tags":[
        "body",
        "car"
    ],
    "wof:name":"Richard Beadle",
    "wof:placetype":"venue"
},
  "geometry": {"coordinates":[0.475789994,51.5975914001],"type":"Point"}
}