{
  "type": "Feature",
  "properties": {
    "addr:full":"21 Slattenham Close Aylesbury Buckinghamshire HP19 7SF",
    "addr:housenumber":"21",
    "addr:postcode":"hp19 7sf",
    "addr:street":"Slattenham Close",
    "iso:country":"GB",
    "sg:address":"21 Slattenham Close",
    "sg:city":"Aylesbury",
    "sg:classifiers":[
        {
            "category":"Professional",
            "subcategory":"Art Services",
            "type":"Services"
        },
        {
            "category":"Building & Trades",
            "subcategory":"Construction",
            "type":"Services"
        }
    ],
    "sg:phone":"+44 1296 429032",
    "sg:postcode":"HP19 7SF",
    "sg:province":"Buckinghamshire",
    "sg:tags":[
        "decorator",
        "painter"
    ],
    "wof:name":"Gary Benton",
    "wof:placetype":"venue"
},
  "geometry": {"coordinates":[-0.832179,51.811741],"type":"Point"}
}