{
  "type": "Feature",
  "properties": {
    "addr:full":"72 London Road, Newington Sittingbourne Kent ME9 7NR",
    "addr:housenumber":"72",
    "addr:postcode":"me9 7nr",
    "addr:street":"London Road",
    "iso:country":"GB",
    "sg:address":"72 London Road, Newington",
    "sg:city":"Sittingbourne",
    "sg:classifiers":[
        {
            "category":"Building & Trades",
            "subcategory":"Landscaping Services",
            "type":"Services"
        }
    ],
    "sg:phone":"+44 1795 843216",
    "sg:postcode":"ME9 7NR",
    "sg:province":"Kent",
    "sg:tags":[
        "landscape",
        "contractor"
    ],
    "wof:name":"A Watermill Gardens",
    "wof:placetype":"venue"
},
  "geometry": {"coordinates":[0.6544100046,51.3544387817],"type":"Point"}
}