{
  "type": "Feature",
  "properties": {
    "addr:full":"70 Coxford Road Southampton Hampshire SO16 5JT",
    "addr:housenumber":"70",
    "addr:postcode":"so16 5jt",
    "addr:street":"Coxford Road",
    "iso:country":"GB",
    "sg:address":"70 Coxford Road",
    "sg:city":"Southampton",
    "sg:classifiers":[
        {
            "category":"Bars & Pubs",
            "type":"Food & Drink"
        }
    ],
    "sg:postcode":"SO16 5JT",
    "sg:province":"Hampshire",
    "sg:tags":[
        "pubs",
        "inn"
    ],
    "wof:name":"Bridge Tavern",
    "wof:placetype":"venue"
},
  "geometry": {"coordinates":[-1.443457,50.933239],"type":"Point"}
}