{
  "type": "Feature",
  "properties": {
    "addr:full":"46 Walkerston Avenue Largs North Ayrshire KA30 8ER",
    "addr:housenumber":"46",
    "addr:postcode":"ka30 8er",
    "addr:street":"Walkerston Avenue",
    "iso:country":"GB",
    "sg:address":"46 Walkerston Avenue",
    "sg:city":"Largs",
    "sg:classifiers":[
        {
            "category":"Building & Trades",
            "subcategory":"Plumbing",
            "type":"Services"
        }
    ],
    "sg:phone":"+44 1475 686351",
    "sg:postcode":"KA30 8ER",
    "sg:province":"North Ayrshire",
    "sg:tags":[
        "central",
        "installation",
        "system",
        "servicing",
        "heating"
    ],
    "wof:name":"D M Crozier",
    "wof:placetype":"venue"
},
  "geometry": {"coordinates":[-4.8594579697,55.7833709717],"type":"Point"}
}