{
  "type": "Feature",
  "properties": {
    "iso:country":"GB",
    "sg:address":"Delta Close, Vulcan Road Estate",
    "sg:city":"Norwich",
    "sg:classifiers":[
        {
            "category":"Organizations",
            "subcategory":"Religious Organization",
            "type":"Services"
        }
    ],
    "sg:phone":"+44 1603 426159",
    "sg:postcode":"NR6 6BG",
    "sg:province":"Norfolk",
    "sg:tags":[
        "organisation"
    ],
    "wof:name":"Hughes & Coleman Ltd.",
    "wof:placetype":"venue"
},
  "geometry": {"coordinates":[1.287095,52.6586],"type":"Point"}
}