{
  "type": "Feature",
  "properties": {
    "addr:full":"71 Wrawby Street Brigg Lincolnshire DN20 8JE",
    "addr:housenumber":"71",
    "addr:postcode":"dn20 8je",
    "addr:street":"Wrawby Street",
    "iso:country":"GB",
    "sg:address":"71 Wrawby Street",
    "sg:city":"Brigg",
    "sg:classifiers":[
        {
            "category":"Real Estate",
            "subcategory":"Real Estate Agent",
            "type":"Services"
        }
    ],
    "sg:phone":"+44 1652 654001",
    "sg:postcode":"DN20 8JE",
    "sg:province":"Lincolnshire",
    "wof:name":"Halifax Property Services",
    "wof:placetype":"venue"
},
  "geometry": {"coordinates":[-0.491279,53.552025],"type":"Point"}
}