{
  "type": "Feature",
  "properties": {
    "iso:country":"GB",
    "sg:address":"7 Thornfield Parade, Holders Hill Road",
    "sg:city":"London",
    "sg:classifiers":[
        {
            "category":"Personal",
            "subcategory":"Beauty Salon",
            "type":"Services"
        }
    ],
    "sg:phone":"+44 20 8371 0306",
    "sg:postcode":"NW7 1LN",
    "sg:province":"Greater London",
    "sg:tags":[
        "lady",
        "hairdresser"
    ],
    "wof:name":"Aura Hair & Beauty Gallery",
    "wof:placetype":"venue"
},
  "geometry": {"coordinates":[-0.207093,51.603287],"type":"Point"}
}