{
  "type": "Feature",
  "properties": {
    "addr:full":"Medbourne Farm, Liddington Swindon Wiltshire SN4 0EY",
    "addr:housenumber":"medbourne;liddington",
    "addr:postcode":"sn4 0ey",
    "addr:street":"Swindon",
    "iso:country":"GB",
    "sg:address":"Medbourne Farm, Liddington",
    "sg:city":"Swindon",
    "sg:classifiers":[
        {
            "category":"Farming",
            "subcategory":"Farm",
            "type":"Manufacturing & Wholesale Goods"
        }
    ],
    "sg:phone":"+44 1793 790218",
    "sg:postcode":"SN4 0EY",
    "sg:province":"Wiltshire",
    "sg:tags":[
        "mixed",
        "crop"
    ],
    "wof:name":"J H P Farming Ltd",
    "wof:placetype":"venue"
},
  "geometry": {"coordinates":[-1.7046589851,51.530834198],"type":"Point"}
}