{
  "type": "Feature",
  "properties": {
    "iso:country":"GB",
    "sg:address":"Ridley Street",
    "sg:city":"Redcar",
    "sg:classifiers":[
        {
            "category":"Organizations",
            "subcategory":"Membership Organization",
            "type":"Services"
        }
    ],
    "sg:phone":"+44 1642 471747",
    "sg:postcode":"TS10 1RG",
    "sg:province":"North Yorkshire",
    "sg:tags":[
        "club"
    ],
    "wof:name":"The Grenfell Club",
    "wof:placetype":"venue"
},
  "geometry": {"coordinates":[-1.0714600086,54.6166496277],"type":"Point"}
}