{
  "type": "Feature",
  "properties": {
    "addr:full":"410a Osmaston Road Derby Derbyshire DE24 8AG",
    "addr:housenumber":"410a",
    "addr:postcode":"de24 8ag",
    "addr:street":"Osmaston Road",
    "iso:country":"GB",
    "sg:address":"410a Osmaston Road",
    "sg:city":"Derby",
    "sg:classifiers":[
        {
            "category":"Shopping",
            "subcategory":"Pharmacy",
            "type":"Retail Goods"
        }
    ],
    "sg:phone":"+44 1332 348946",
    "sg:postcode":"DE24 8AG",
    "sg:province":"Derbyshire",
    "sg:tags":[
        "pharmacist",
        "chemist"
    ],
    "wof:name":"Hedley Hewes Chemist",
    "wof:placetype":"venue"
},
  "geometry": {"coordinates":[-1.460432,52.902184],"type":"Point"}
}