{
  "type": "Feature",
  "properties": {
    "addr:full":"32 Lapstone Rd Millom Cumbria LA18 4BU",
    "addr:housenumber":"32",
    "addr:postcode":"la18 4bu",
    "addr:street":"Lapstone Rd",
    "iso:country":"GB",
    "sg:address":"32 Lapstone Rd",
    "sg:city":"Millom",
    "sg:classifiers":[
        {
            "category":"Real Estate",
            "subcategory":"Real Estate Agent",
            "type":"Services"
        }
    ],
    "sg:phone":"+44 1229 774809",
    "sg:postcode":"LA18 4BU",
    "sg:province":"Cumbria",
    "wof:name":"Bairstow Eves",
    "wof:placetype":"venue"
},
  "geometry": {"coordinates":[-3.269025,54.210068],"type":"Point"}
}