{
  "type": "Feature",
  "properties": {
    "iso:country":"GB",
    "sg:address":"North Mersey Business Centre, Unit 70, Knowsley Indstl Pk North",
    "sg:city":"Liverpool",
    "sg:classifiers":[
        {
            "category":"Freight",
            "type":"Transportation"
        }
    ],
    "sg:phone":"+44 151 477 1997",
    "sg:postcode":"L33 7UZ",
    "sg:province":"Lancashire",
    "sg:tags":[
        "forwarders"
    ],
    "wof:name":"Sovereign Freight Services Ltd",
    "wof:placetype":"venue"
},
  "geometry": {"coordinates":[-2.85515,53.489498],"type":"Point"}
}