{
  "type": "Feature",
  "properties": {
    "addr:full":"2 Prior Road Forfar Angus DD8 3DP",
    "addr:housenumber":"2",
    "addr:postcode":"dd8 3dp",
    "addr:street":"Prior Road",
    "iso:country":"GB",
    "sg:address":"2 Prior Road",
    "sg:city":"Forfar",
    "sg:classifiers":[
        {
            "category":"Autos & Motor Vehicles",
            "subcategory":"Motorcycle Sales",
            "type":"Retail Goods"
        }
    ],
    "sg:postcode":"DD8 3DP",
    "sg:province":"Angus",
    "sg:tags":[
        "chauffeur",
        "driven",
        "car"
    ],
    "wof:name":"Davidson Charter",
    "wof:placetype":"venue"
},
  "geometry": {"coordinates":[-2.879253,56.646286],"type":"Point"}
}