{
  "type": "Feature",
  "properties": {
    "iso:country":"GB",
    "sg:address":"141 Castle Rd",
    "sg:city":"Scarborough",
    "sg:classifiers":[
        {
            "category":"Travel",
            "subcategory":"Hotels & Motels",
            "type":"Entertainment"
        }
    ],
    "sg:phone":"+44 1723 377888",
    "sg:postcode":"YO11 1HX",
    "sg:province":"North Yorkshire",
    "sg:tags":[
        "self",
        "catering"
    ],
    "wof:name":"Castle Court",
    "wof:placetype":"venue"
},
  "geometry": {"coordinates":[-0.3934240043,54.2867431641],"type":"Point"}
}