{
  "type": "Feature",
  "properties": {
    "iso:country":"GB",
    "sg:address":"75 Dudley Road",
    "sg:city":"Rowley Regis",
    "sg:classifiers":[
        {
            "category":"Bars & Pubs",
            "type":"Food & Drink"
        }
    ],
    "sg:phone":"+44 121 561 4273",
    "sg:postcode":"B65 8JY",
    "sg:province":"West Midlands",
    "sg:tags":[
        "pubs",
        "inn"
    ],
    "wof:name":"The Cock Inn",
    "wof:placetype":"venue"
},
  "geometry": {"coordinates":[-2.0553898811,52.4890441895],"type":"Point"}
}