{
  "type": "Feature",
  "properties": {
    "addr:full":"58 Crooksbury Road Farnham Hampshire GU10 1QD",
    "addr:housenumber":"58",
    "addr:postcode":"gu10 1qd",
    "addr:street":"Crooksbury Road",
    "iso:country":"GB",
    "sg:address":"58 Crooksbury Road",
    "sg:city":"Farnham",
    "sg:classifiers":[
        {
            "category":"Building & Trades",
            "subcategory":"Construction",
            "type":"Services"
        }
    ],
    "sg:postcode":"GU10 1QD",
    "sg:province":"Hampshire",
    "sg:tags":[
        "heating",
        "contractor"
    ],
    "wof:name":"A W M Services Ltd.",
    "wof:placetype":"venue"
},
  "geometry": {"coordinates":[-0.750981,51.21294],"type":"Point"}
}