{
  "type": "Feature",
  "properties": {
    "addr:full":"163 George Street London Greater London W1H 5LA",
    "addr:housenumber":"163",
    "addr:postcode":"w1h 5la",
    "addr:street":"George Street",
    "iso:country":"GB",
    "sg:address":"163 George Street",
    "sg:city":"London",
    "sg:classifiers":[
        {
            "category":"Education",
            "subcategory":"Library",
            "type":"Public Place"
        }
    ],
    "sg:phone":"+44 20 7262 8428",
    "sg:postcode":"W1H 5LA",
    "sg:province":"Greater London",
    "sg:tags":[
        "book"
    ],
    "wof:name":"Shoaa Video",
    "wof:placetype":"venue"
},
  "geometry": {"coordinates":[-0.1639589965,51.5158424377],"type":"Point"}
}