{
  "type": "Feature",
  "properties": {
    "addr:full":"1st Floor 117 High Street Sutton Surrey SM1 1JF",
    "addr:housenumber":"117",
    "addr:postcode":"sm1 1jf",
    "addr:street":"High Street",
    "iso:country":"GB",
    "sg:address":"1st Floor 117 High Street",
    "sg:city":"Sutton",
    "sg:classifiers":[
        {
            "category":"Professional",
            "subcategory":"Employment Agencies",
            "type":"Services"
        }
    ],
    "sg:phone":"+44 20 8643 9422",
    "sg:postcode":"SM1 1JF",
    "sg:province":"Surrey",
    "sg:tags":[
        "consultant"
    ],
    "wof:name":"Reed Accountancy",
    "wof:placetype":"venue"
},
  "geometry": {"coordinates":[-0.1932200044,51.3632698059],"type":"Point"}
}