{
  "type": "Feature",
  "properties": {
    "iso:country":"GB",
    "sg:address":"363 Springfield Road",
    "sg:city":"Chelmsford",
    "sg:classifiers":[
        {
            "category":"Social Services",
            "subcategory":"Job Training",
            "type":"Services"
        }
    ],
    "sg:phone":"+44 1245 267363",
    "sg:postcode":"CM2 6AW",
    "sg:province":"Essex",
    "sg:tags":[
        "draughtsman",
        "drawing"
    ],
    "wof:name":"Design & Detail Partnership",
    "wof:placetype":"venue"
},
  "geometry": {"coordinates":[0.48806,51.73909],"type":"Point"}
}