{
  "type": "Feature",
  "properties": {
    "addr:full":"1 Storer Road Loughborough Leicestershire LE11 5EQ",
    "addr:housenumber":"1",
    "addr:postcode":"le11 5eq",
    "addr:street":"Storer Road",
    "iso:country":"GB",
    "sg:address":"1 Storer Road",
    "sg:city":"Loughborough",
    "sg:classifiers":[
        {
            "category":"Bars & Pubs",
            "subcategory":"Wine Bar",
            "type":"Food & Drink"
        }
    ],
    "sg:phone":"+44 1509 240280",
    "sg:postcode":"LE11 5EQ",
    "sg:province":"Leicestershire",
    "wof:name":"Biarrtz",
    "wof:placetype":"venue"
},
  "geometry": {"coordinates":[-1.2161940336,52.7724761963],"type":"Point"}
}