{
  "type": "Feature",
  "properties": {
    "addr:full":"Unit 13, Suprema Ind Est, Suprema Avenue, Edington Bridgwater Somerset TA7 9LF",
    "addr:housenumber":"unit 13",
    "addr:postcode":"ta7 9lf",
    "addr:street":"Suprema;Suprema Avenue",
    "iso:country":"GB",
    "sg:address":"Unit 13, Suprema Ind Est, Suprema Avenue, Edington",
    "sg:city":"Bridgwater",
    "sg:classifiers":[
        {
            "category":"Manufacturing",
            "subcategory":"Glass & Minerals",
            "type":"Manufacturing & Wholesale Goods"
        }
    ],
    "sg:phone":"+44 1278 723535",
    "sg:postcode":"TA7 9LF",
    "sg:province":"Somerset",
    "sg:tags":[
        "fibre",
        "moulding"
    ],
    "wof:name":"Acorn Pattern",
    "wof:placetype":"venue"
},
  "geometry": {"coordinates":[-2.8782849312,51.1540222168],"type":"Point"}
}