{
  "type": "Feature",
  "properties": {
    "iso:country":"GB",
    "sg:address":"High St",
    "sg:city":"Maesteg",
    "sg:classifiers":[
        {
            "category":"Health Services",
            "subcategory":"Doctor",
            "type":"Services"
        }
    ],
    "sg:phone":"+44 1656 732217",
    "sg:postcode":"CF34 0BT",
    "sg:province":"Bridgend",
    "sg:tags":[
        "practitioners"
    ],
    "wof:name":"Sharma, A K",
    "wof:placetype":"venue"
},
  "geometry": {"coordinates":[-3.662327,51.614727],"type":"Point"}
}