{
  "type": "Feature",
  "properties": {
    "addr:full":"50 Victoria Embankment London Greater London EC4Y 0LS",
    "addr:housenumber":"50",
    "addr:postcode":"ec4y 0ls",
    "addr:street":"Victoria Embankment",
    "iso:country":"GB",
    "sg:address":"50 Victoria Embankment",
    "sg:city":"London",
    "sg:classifiers":[
        {
            "category":"Professional",
            "subcategory":"Lawyer & Legal Services",
            "type":"Services"
        }
    ],
    "sg:phone":"+44 20 7842 8000",
    "sg:postcode":"EC4Y 0LS",
    "sg:province":"Greater London",
    "sg:tags":[
        "solicitor"
    ],
    "wof:name":"Laytons Ltd.",
    "wof:placetype":"venue"
},
  "geometry": {"coordinates":[-0.1078089997,51.5110855103],"type":"Point"}
}