{
  "type": "Feature",
  "properties": {
    "iso:country":"GB",
    "sg:address":"1000 The Quadrant, Ashridge Road, Almondsbury",
    "sg:city":"Bristol",
    "sg:classifiers":[
        {
            "category":"Professional",
            "subcategory":"Printing & Photocopies",
            "type":"Services"
        }
    ],
    "sg:phone":"+44 1454 613123",
    "sg:postcode":"BS32 4QA",
    "sg:province":"Gloucestershire",
    "sg:tags":[
        "mailing"
    ],
    "wof:name":"Ascom Uk Ltd.",
    "wof:placetype":"venue"
},
  "geometry": {"coordinates":[-2.564619,51.556526],"type":"Point"}
}