{
  "type": "Feature",
  "properties": {
    "iso:country":"GB",
    "sg:address":"Unit 2e Honeybourne Airfield, Western Road",
    "sg:city":"Evesham",
    "sg:classifiers":[
        {
            "category":"Manufacturing",
            "subcategory":"Wood Products",
            "type":"Manufacturing & Wholesale Goods"
        }
    ],
    "sg:phone":"+44 1386 833452",
    "sg:postcode":"WR11 7QF",
    "sg:province":"Gloucestershire",
    "sg:tags":[
        "maker",
        "cabinet"
    ],
    "wof:name":"Fine Furniture Design",
    "wof:placetype":"venue"
},
  "geometry": {"coordinates":[-1.828077,52.079624],"type":"Point"}
}