{
  "type": "Feature",
  "properties": {
    "addr:full":"Unit 5, Jesmond Buildings, Jesmond Rd Chester Cheshire CH1 4DQ",
    "addr:housenumber":"unit 5 jesmond buildings",
    "addr:postcode":"ch1 4dq",
    "addr:street":"Jesmond Rd",
    "iso:country":"GB",
    "sg:address":"Unit 5, Jesmond Buildings, Jesmond Rd",
    "sg:city":"Chester",
    "sg:classifiers":[
        {
            "category":"Autos & Motor Vehicles",
            "subcategory":"Auto Supplies",
            "type":"Retail Goods"
        }
    ],
    "sg:phone":"+44 1244 377855",
    "sg:postcode":"CH1 4DQ",
    "sg:province":"Cheshire",
    "sg:tags":[
        "car",
        "component"
    ],
    "wof:name":"Romoco",
    "wof:placetype":"venue"
},
  "geometry": {"coordinates":[-2.903889,53.196548],"type":"Point"}
}