{
  "type": "Feature",
  "properties": {
    "addr:full":"Pluckley Road, Bethersden Ashford Kent TN26 3DD",
    "addr:postcode":"tn26 3dd",
    "addr:street":"Pluckley Road",
    "iso:country":"GB",
    "sg:address":"Pluckley Road, Bethersden",
    "sg:city":"Ashford",
    "sg:classifiers":[
        {
            "category":"Home & Garden",
            "subcategory":"Garden Supply",
            "type":"Retail Goods"
        }
    ],
    "sg:phone":"+44 1233 820998",
    "sg:postcode":"TN26 3DD",
    "sg:province":"Kent",
    "sg:tags":[
        "nursery",
        "centre"
    ],
    "wof:name":"Stone Green Nurseries",
    "wof:placetype":"venue"
},
  "geometry": {"coordinates":[0.752973,51.126179],"type":"Point"}
}