{
  "type": "Feature",
  "properties": {
    "addr:full":"126 Purewell Christchurch Dorset BH23 1EU",
    "addr:housenumber":"126",
    "addr:postcode":"bh23 1eu",
    "addr:street":"Purewell",
    "iso:country":"GB",
    "sg:address":"126 Purewell",
    "sg:city":"Christchurch",
    "sg:classifiers":[
        {
            "category":"Building & Trades",
            "subcategory":"Construction",
            "type":"Services"
        }
    ],
    "sg:postcode":"BH23 1EU",
    "sg:province":"Dorset",
    "sg:tags":[
        "joiner",
        "carpenter"
    ],
    "wof:name":"Purewell Joinery",
    "wof:placetype":"venue"
},
  "geometry": {"coordinates":[-1.7606480122,50.7360572815],"type":"Point"}
}