{
  "type": "Feature",
  "properties": {
    "addr:full":"24 Chadkirk Cottages, Vale Road, Romiley Stockport Cheshire SK6 3LE",
    "addr:housenumber":"24",
    "addr:postcode":"sk6 3le",
    "addr:street":"Chadkirk Cottages Vale Road",
    "iso:country":"GB",
    "sg:address":"24 Chadkirk Cottages, Vale Road, Romiley",
    "sg:city":"Stockport",
    "sg:classifiers":[
        {
            "category":"Social Services",
            "type":"Services"
        }
    ],
    "sg:phone":"+44 161 426 0222",
    "sg:postcode":"SK6 3LE",
    "sg:province":"Cheshire",
    "sg:tags":[
        "disability"
    ],
    "wof:name":"Jeff Gosling Hand Controls Ltd.",
    "wof:placetype":"venue"
},
  "geometry": {"coordinates":[-2.0952010155,53.4031257629],"type":"Point"}
}