{
  "type": "Feature",
  "properties": {
    "iso:country":"GB",
    "sg:address":"Blakemere Craft Centre, Chester Road, Sandiway",
    "sg:city":"Northwich",
    "sg:classifiers":[
        {
            "category":"Shopping",
            "subcategory":"Computers & Home Electronics",
            "type":"Retail Goods"
        }
    ],
    "sg:phone":"+44 1606 882791",
    "sg:postcode":"CW8 2EB",
    "sg:province":"Cheshire",
    "wof:name":"Robert W Hayward",
    "wof:placetype":"venue"
},
  "geometry": {"coordinates":[-2.5922269821,53.2362136841],"type":"Point"}
}