{
  "type": "Feature",
  "properties": {
    "iso:country":"GB",
    "sg:address":"5 Nutter Road",
    "sg:city":"Thornton-cleveleys",
    "sg:classifiers":[
        {
            "category":"Cafe",
            "type":"Food & Drink"
        }
    ],
    "sg:phone":"+44 1253 853193",
    "sg:postcode":"FY5 1BG",
    "sg:province":"Lancashire",
    "sg:tags":[
        "tea",
        "room"
    ],
    "wof:name":"Mayfair Cafe",
    "wof:placetype":"venue"
},
  "geometry": {"coordinates":[-3.042141,53.877522],"type":"Point"}
}