{
  "type": "Feature",
  "properties": {
    "addr:full":"Plowright Surgery, 9-11 Plowright Pl Swaffham Norfolk PE37 7LQ",
    "addr:housenumber":"9-11",
    "addr:postcode":"pe37 7lq",
    "addr:street":"Plowright Pl",
    "iso:country":"GB",
    "sg:address":"Plowright Surgery, 9-11 Plowright Pl",
    "sg:city":"Swaffham",
    "sg:classifiers":[
        {
            "category":"Health Services",
            "subcategory":"Doctor",
            "type":"Services"
        }
    ],
    "sg:phone":"+44 1760 722797",
    "sg:postcode":"PE37 7LQ",
    "sg:province":"Norfolk",
    "sg:tags":[
        "practitioners"
    ],
    "wof:name":"Sorensen-Pound, D",
    "wof:placetype":"venue"
},
  "geometry": {"coordinates":[0.6897969842,52.6438446045],"type":"Point"}
}