{
  "type": "Feature",
  "properties": {
    "addr:full":"Warnford Court, 29 Throgmorton Street Moorgate Greater London EC2N 2AT",
    "addr:housenumber":"29",
    "addr:postcode":"ec2n 2at",
    "addr:street":"Warnford;Throgmorton Street",
    "iso:country":"GB",
    "sg:address":"Warnford Court, 29 Throgmorton Street",
    "sg:city":"Moorgate",
    "sg:classifiers":[
        {
            "category":"Organizations",
            "subcategory":"Membership Organization",
            "type":"Services"
        }
    ],
    "sg:postcode":"EC2N 2AT",
    "sg:province":"Greater London",
    "sg:tags":[
        "club"
    ],
    "wof:name":"Ifg Fund Management Ltd",
    "wof:placetype":"venue"
},
  "geometry": {"coordinates":[-0.086916998,51.5149002075],"type":"Point"}
}