{
  "type": "Feature",
  "properties": {
    "addr:full":"1a Cliff Gardens, Minster Sheerness Kent ME12 3QY",
    "addr:housenumber":"1a",
    "addr:postcode":"me12 3qy",
    "addr:street":"Cliff Gardens",
    "iso:country":"GB",
    "sg:address":"1a Cliff Gardens, Minster",
    "sg:city":"Sheerness",
    "sg:classifiers":[
        {
            "category":"Home & Garden",
            "subcategory":"Household Appliances",
            "type":"Retail Goods"
        }
    ],
    "sg:postcode":"ME12 3QY",
    "sg:province":"Kent",
    "sg:tags":[
        "electrical"
    ],
    "wof:name":"Domestic Xpress",
    "wof:placetype":"venue"
},
  "geometry": {"coordinates":[0.823661,51.421474],"type":"Point"}
}