{
  "type": "Feature",
  "properties": {
    "addr:full":"Great Square Braintree Essex CM7 1TX",
    "addr:postcode":"cm7 1tx",
    "addr:street":"Great Square",
    "iso:country":"GB",
    "sg:address":"Great Square",
    "sg:city":"Braintree",
    "sg:classifiers":[
        {
            "category":"Banks & Credit Unions",
            "subcategory":"Bank",
            "type":"Services"
        }
    ],
    "sg:phone":"+44 1206 812000",
    "sg:postcode":"CM7 1TX",
    "sg:province":"Essex",
    "wof:name":"Halifax Plc",
    "wof:placetype":"venue"
},
  "geometry": {"coordinates":[0.551105,51.878513],"type":"Point"}
}