{
  "type": "Feature",
  "properties": {
    "iso:country":"GB",
    "sg:address":"38 Penallta Road, Ystrad Mynach",
    "sg:city":"Hengoed",
    "sg:classifiers":[
        {
            "category":"Organizations",
            "subcategory":"Community Association",
            "type":"Services"
        },
        {
            "category":"Organizations",
            "subcategory":"Membership Organization",
            "type":"Services"
        }
    ],
    "sg:phone":"+44 1443 862584",
    "sg:postcode":"CF82 7AN",
    "sg:province":"Caerphilly",
    "sg:tags":[
        "club",
        "social"
    ],
    "wof:name":"YSTRAD MYNACH SPORTS & SOCIAL CLUB LTD",
    "wof:placetype":"venue"
},
  "geometry": {"coordinates":[-3.236782074,51.6435089111],"type":"Point"}
}