{
  "type": "Feature",
  "properties": {
    "addr:full":"4 Dragon Rd Harrogate North Yorkshire HG1 5DF",
    "addr:housenumber":"4",
    "addr:postcode":"hg1 5df",
    "addr:street":"Dragon Rd",
    "iso:country":"GB",
    "sg:address":"4 Dragon Rd",
    "sg:city":"Harrogate",
    "sg:classifiers":[
        {
            "category":"Building & Trades",
            "subcategory":"Construction",
            "type":"Services"
        }
    ],
    "sg:phone":"+44 1423 529277",
    "sg:postcode":"HG1 5DF",
    "sg:province":"North Yorkshire",
    "sg:tags":[
        "decorator",
        "painter"
    ],
    "wof:name":"J McCaffery",
    "wof:placetype":"venue"
},
  "geometry": {"coordinates":[-1.534144,53.996391],"type":"Point"}
}