{
  "type": "Feature",
  "properties": {
    "addr:full":"112 High Street Sittingbourne Kent ME10 4PL",
    "addr:housenumber":"112",
    "addr:postcode":"me10 4pl",
    "addr:street":"High Street",
    "iso:country":"GB",
    "sg:address":"112 High Street",
    "sg:city":"Sittingbourne",
    "sg:classifiers":[
        {
            "category":"Farming",
            "subcategory":"Fish & Marine Products",
            "type":"Manufacturing & Wholesale Goods"
        },
        {
            "category":"Food & Beverages",
            "subcategory":"Meat & Fish",
            "type":"Retail Goods"
        }
    ],
    "sg:phone":"+44 1795 423455",
    "sg:postcode":"ME10 4PL",
    "sg:province":"Kent",
    "sg:tags":[
        "fishmonger",
        "related"
    ],
    "wof:name":"A Thomsett",
    "wof:placetype":"venue"
},
  "geometry": {"coordinates":[0.7340649962,51.3404693604],"type":"Point"}
}