{
  "type": "Feature",
  "properties": {
    "addr:full":"1596 Coventry Rd Birmingham West Midlands B26 1AL",
    "addr:housenumber":"1596",
    "addr:postcode":"b26 1al",
    "addr:street":"Coventry Rd",
    "iso:country":"GB",
    "sg:address":"1596 Coventry Rd",
    "sg:city":"Birmingham",
    "sg:classifiers":[
        {
            "category":"Food & Beverages",
            "subcategory":"Meat & Fish",
            "type":"Retail Goods"
        }
    ],
    "sg:postcode":"B26 1AL",
    "sg:province":"West Midlands",
    "sg:tags":[
        "chip"
    ],
    "wof:name":"Hernandez,A,",
    "wof:placetype":"venue"
},
  "geometry": {"coordinates":[-1.8117220402,52.4619560242],"type":"Point"}
}