{
  "type": "Feature",
  "properties": {
    "addr:full":"87 Main Street, Walton Street Somerset BA16 9QH",
    "addr:housenumber":"87",
    "addr:postcode":"ba16 9qh",
    "addr:street":"Main Street Walton Street",
    "iso:country":"GB",
    "sg:address":"87 Main Street, Walton",
    "sg:city":"Street",
    "sg:classifiers":[
        {
            "category":"Building & Trades",
            "subcategory":"Construction",
            "type":"Services"
        }
    ],
    "sg:postcode":"BA16 9QH",
    "sg:province":"Somerset",
    "sg:tags":[
        "bricklaying"
    ],
    "wof:name":"Genesis Brickwork",
    "wof:placetype":"venue"
},
  "geometry": {"coordinates":[-2.7728428841,51.1236038208],"type":"Point"}
}