{
  "type": "Feature",
  "properties": {
    "addr:full":"9 Devonshire Road Middlesbrough North Yorkshire TS5 6DJ",
    "addr:housenumber":"9",
    "addr:postcode":"ts5 6dj",
    "addr:street":"Devonshire Road",
    "iso:country":"GB",
    "sg:address":"9 Devonshire Road",
    "sg:city":"Middlesbrough",
    "sg:classifiers":[
        {
            "category":"Personal",
            "subcategory":"Beauty Salon",
            "type":"Services"
        }
    ],
    "sg:phone":"+44 1642 818439",
    "sg:postcode":"TS5 6DJ",
    "sg:province":"North Yorkshire",
    "sg:tags":[
        "lady",
        "hairdresser"
    ],
    "wof:name":"Devonshire Salon",
    "wof:placetype":"venue"
},
  "geometry": {"coordinates":[-1.244315,54.56004],"type":"Point"}
}