{
  "type": "Feature",
  "properties": {
    "addr:full":"83 Oldfield Circus Northolt Greater London UB5 4RU",
    "addr:housenumber":"83",
    "addr:postcode":"ub5 4ru",
    "addr:street":"Oldfield Circus",
    "iso:country":"GB",
    "sg:address":"83 Oldfield Circus",
    "sg:city":"Northolt",
    "sg:classifiers":[
        {
            "category":"Shopping",
            "subcategory":"Florist",
            "type":"Retail Goods"
        }
    ],
    "sg:phone":"+44 20 8864 6856",
    "sg:postcode":"UB5 4RU",
    "sg:province":"Greater London",
    "wof:name":"Flowerland",
    "wof:placetype":"venue"
},
  "geometry": {"coordinates":[-0.3505240083,51.5524291992],"type":"Point"}
}