{
  "type": "Feature",
  "properties": {
    "addr:full":"Unit 1 Sapex Buildings, Spitalfield Lane Chichester West Sussex PO19 6SN",
    "addr:housenumber":"unit 1",
    "addr:postcode":"po19 6sn",
    "addr:street":"Sapex Buildings Spitalfield Lane",
    "iso:country":"GB",
    "sg:address":"Unit 1 Sapex Buildings, Spitalfield Lane",
    "sg:city":"Chichester",
    "sg:classifiers":[
        {
            "category":"Retail",
            "subcategory":"Repair Shop",
            "type":"Services"
        },
        {
            "category":"Building & Trades",
            "subcategory":"Construction",
            "type":"Services"
        }
    ],
    "sg:phone":"+44 1243 641642",
    "sg:postcode":"PO19 6SN",
    "sg:province":"West Sussex",
    "sg:tags":[
        "builder",
        "upholsterer"
    ],
    "wof:name":"Unique Upholsterers",
    "wof:placetype":"venue"
},
  "geometry": {"coordinates":[-0.7754290104,50.8361663818],"type":"Point"}
}