{
  "type": "Feature",
  "properties": {
    "iso:country":"GB",
    "sg:address":"Hillside House, Misterton",
    "sg:city":"Crewkerne",
    "sg:classifiers":[
        {
            "category":"Home & Garden",
            "subcategory":"Garden Supply",
            "type":"Retail Goods"
        }
    ],
    "sg:phone":"+44 1460 72432",
    "sg:postcode":"TA18 8LZ",
    "sg:province":"Dorset",
    "sg:tags":[
        "fertiliser"
    ],
    "wof:name":"Soil Fertility Dunns Ltd",
    "wof:placetype":"venue"
},
  "geometry": {"coordinates":[-2.7738559246,50.8702125549],"type":"Point"}
}