{
  "type": "Feature",
  "properties": {
    "addr:full":"Crosswall, Ramsgate Harbour Ramsgate Kent CT11 9RN",
    "addr:postcode":"ct11 9rn",
    "addr:street":"Crosswall Ramsgate Harbour",
    "iso:country":"GB",
    "sg:address":"Crosswall, Ramsgate Harbour",
    "sg:city":"Ramsgate",
    "sg:classifiers":[
        {
            "category":"Organizations",
            "subcategory":"Non-profit Organization",
            "type":"Services"
        }
    ],
    "sg:phone":"+44 1843 580580",
    "sg:postcode":"CT11 9RN",
    "sg:province":"Kent",
    "sg:tags":[
        "charitable",
        "organisation",
        "voluntary",
        "charity"
    ],
    "wof:name":"Royal National Lifeboat Institution",
    "wof:placetype":"venue"
},
  "geometry": {"coordinates":[1.421934,51.332584],"type":"Point"}
}