{
  "type": "Feature",
  "properties": {
    "addr:full":"4 Sedge Court, Thurrock Park Grays Essex RM17 6UR",
    "addr:housenumber":"4",
    "addr:postcode":"rm17 6ur",
    "addr:street":"Sedge Court;Park",
    "iso:country":"GB",
    "sg:address":"4 Sedge Court, Thurrock Park",
    "sg:city":"Grays",
    "sg:classifiers":[
        {
            "category":"Shopping",
            "subcategory":"Computers & Home Electronics",
            "type":"Retail Goods"
        }
    ],
    "sg:postcode":"RM17 6UR",
    "sg:province":"Essex",
    "wof:name":"Darmel Ltd",
    "wof:placetype":"venue"
},
  "geometry": {"coordinates":[0.34579,51.472679],"type":"Point"}
}