{
  "type": "Feature",
  "properties": {
    "addr:full":"Castle Wharf Canal St Nottingham Nottinghamshire NG1 4GA",
    "addr:postcode":"ng1 4ga",
    "addr:street":"Castle Wharf Canal St",
    "iso:country":"GB",
    "sg:address":"Castle Wharf Canal St",
    "sg:city":"Nottingham",
    "sg:classifiers":[
        {
            "category":"Bars & Pubs",
            "type":"Food & Drink"
        }
    ],
    "sg:phone":"+44 115 979 9111",
    "sg:postcode":"NG1 4GA",
    "sg:province":"Nottinghamshire",
    "sg:tags":[
        "pubs",
        "inn"
    ],
    "wof:name":"Waterfront The",
    "wof:placetype":"venue"
},
  "geometry": {"coordinates":[-1.143924,52.949226],"type":"Point"}
}