{
  "type": "Feature",
  "properties": {
    "iso:country":"GB",
    "sg:address":"Strand Street",
    "sg:city":"Padstow",
    "sg:classifiers":[
        {
            "category":"Bars & Pubs",
            "type":"Food & Drink"
        }
    ],
    "sg:postcode":"PL28 8BU",
    "sg:province":"Cornwall",
    "sg:tags":[
        "pubs",
        "inn"
    ],
    "wof:name":"The Harbour Inn",
    "wof:placetype":"venue"
},
  "geometry": {"coordinates":[-4.938001,50.540981],"type":"Point"}
}