{
  "type": "Feature",
  "properties": {
    "iso:country":"GB",
    "sg:address":"Bondleigh Moor House, Bondleigh",
    "sg:city":"North Tawton",
    "sg:classifiers":[
        {
            "category":"Shopping",
            "subcategory":"Jewelry",
            "type":"Retail Goods"
        }
    ],
    "sg:postcode":"EX20 2AQ",
    "sg:province":"Devon",
    "sg:tags":[
        "diamond"
    ],
    "wof:name":"London Industrial Diamond Co",
    "wof:placetype":"venue"
},
  "geometry": {"coordinates":[-3.8970689774,50.7989768982],"type":"Point"}
}