{
  "type": "Feature",
  "properties": {
    "iso:country":"GB",
    "sg:address":"Rivermede, Blackpool Road, St Michaels On Wyre",
    "sg:city":"Preston",
    "sg:classifiers":[
        {
            "category":"Social Services",
            "subcategory":"Retirement Home",
            "type":"Services"
        }
    ],
    "sg:postcode":"PR3 0UB",
    "sg:province":"Lancashire",
    "sg:tags":[
        "residential",
        "care"
    ],
    "wof:name":"Rivermede Residential Care Home",
    "wof:placetype":"venue"
},
  "geometry": {"coordinates":[-2.823564,53.861954],"type":"Point"}
}