{
  "type": "Feature",
  "properties": {
    "addr:full":"2a Heaven Green London Greater London W5 2UU",
    "addr:postcode":"w5 2uu",
    "addr:street":"Green",
    "iso:country":"GB",
    "sg:address":"2a Heaven Green",
    "sg:city":"London",
    "sg:classifiers":[
        {
            "category":"Professional",
            "subcategory":"Management & Consulting",
            "type":"Services"
        }
    ],
    "sg:phone":"+44 20 7224 9696",
    "sg:postcode":"W5 2UU",
    "sg:province":"Greater London",
    "sg:tags":[
        "marketing",
        "consultant"
    ],
    "wof:name":"Shams International Ltd.",
    "wof:placetype":"venue"
},
  "geometry": {"coordinates":[-0.3047800064,51.5153503418],"type":"Point"}
}