{
  "type": "Feature",
  "properties": {
    "addr:full":"The Old School House, The Green, Cassington Witney Oxfordshire OX29 4DN",
    "addr:postcode":"ox29 4dn",
    "addr:street":"The Green",
    "iso:country":"GB",
    "sg:address":"The Old School House, The Green, Cassington",
    "sg:city":"Witney",
    "sg:classifiers":[
        {
            "category":"Home & Garden",
            "subcategory":"Furniture",
            "type":"Retail Goods"
        }
    ],
    "sg:postcode":"OX29 4DN",
    "sg:province":"Oxfordshire",
    "wof:name":"Needle & Cotton",
    "wof:placetype":"venue"
},
  "geometry": {"coordinates":[-1.3432949781,51.7936935425],"type":"Point"}
}