{
  "type": "Feature",
  "properties": {
    "addr:full":"232 Station Rd Hayes Greater London UB3 4AN",
    "addr:housenumber":"232",
    "addr:postcode":"ub3 4an",
    "addr:street":"Station Rd",
    "iso:country":"GB",
    "sg:address":"232 Station Rd",
    "sg:city":"Hayes",
    "sg:classifiers":[
        {
            "category":"Building & Trades",
            "subcategory":"Construction",
            "type":"Services"
        }
    ],
    "sg:postcode":"UB3 4AN",
    "sg:province":"Greater London",
    "sg:tags":[
        "ceiling",
        "contractor"
    ],
    "wof:name":"Steadman,Rob,",
    "wof:placetype":"venue"
},
  "geometry": {"coordinates":[-0.4268400073,51.4977378845],"type":"Point"}
}