{
  "type": "Feature",
  "properties": {
    "addr:full":"East Wing, Blair House Dalry North Ayrshire KA24 4ER",
    "addr:postcode":"ka24 4er",
    "iso:country":"GB",
    "sg:address":"East Wing, Blair House",
    "sg:city":"Dalry",
    "sg:classifiers":[
        {
            "category":"Professional",
            "type":"Services"
        }
    ],
    "sg:phone":"+44 1294 832172",
    "sg:postcode":"KA24 4ER",
    "sg:province":"North Ayrshire",
    "sg:tags":[
        "interior",
        "furnishers",
        "designer"
    ],
    "wof:name":"Gabbi Interior Designs",
    "wof:placetype":"venue"
},
  "geometry": {"coordinates":[-4.720990181,55.7065963745],"type":"Point"}
}