{
  "type": "Feature",
  "properties": {
    "iso:country":"GB",
    "sg:address":"Klondyke Works, Sunnyside",
    "sg:city":"Swadlincote",
    "sg:classifiers":[
        {
            "category":"Retail",
            "subcategory":"Auto Repair",
            "type":"Services"
        }
    ],
    "sg:phone":"+44 1283 226400",
    "sg:postcode":"DE11 0TN",
    "sg:province":"Derbyshire",
    "sg:tags":[
        "modification",
        "garage"
    ],
    "wof:name":"Bretby Car Spares",
    "wof:placetype":"venue"
},
  "geometry": {"coordinates":[-1.5522090197,52.7740936279],"type":"Point"}
}