{
  "type": "Feature",
  "properties": {
    "iso:country":"GB",
    "sg:address":"85 Evelina Road",
    "sg:city":"London",
    "sg:classifiers":[
        {
            "category":"Professional",
            "subcategory":"Testing Lab",
            "type":"Services"
        },
        {
            "category":"Retail",
            "subcategory":"Auto Repair",
            "type":"Services"
        }
    ],
    "sg:phone":"+44 20 7639 9711",
    "sg:postcode":"SE15 3HL",
    "sg:province":"Greater London",
    "sg:tags":[
        "modification",
        "garage",
        "mot"
    ],
    "wof:name":"Prograde Ltd.",
    "wof:placetype":"venue"
},
  "geometry": {"coordinates":[-0.05443,51.467236],"type":"Point"}
}