{
  "type": "Feature",
  "properties": {
    "iso:country":"GB",
    "sg:address":"2a Dinas Lane, Huyton",
    "sg:city":"Liverpool",
    "sg:classifiers":[
        {
            "category":"Military Area",
            "subcategory":"Air Force Base",
            "type":"Public Place"
        }
    ],
    "sg:phone":"+44 151 220 7777",
    "sg:postcode":"L36 2NP",
    "sg:province":"Merseyside",
    "sg:tags":[
        "taxi",
        "hire",
        "private"
    ],
    "wof:name":"Relay Taxis",
    "wof:placetype":"venue"
},
  "geometry": {"coordinates":[-2.867559,53.420441],"type":"Point"}
}