{
  "type": "Feature",
  "properties": {
    "addr:full":"2 Beathwaite Drive, Bramhall Stockport Cheshire SK7 3NY",
    "addr:housenumber":"2",
    "addr:postcode":"sk7 3ny",
    "addr:street":"Beathwaite Drive",
    "iso:country":"GB",
    "sg:address":"2 Beathwaite Drive, Bramhall",
    "sg:city":"Stockport",
    "sg:classifiers":[
        {
            "category":"Professional",
            "subcategory":"Art Services",
            "type":"Services"
        }
    ],
    "sg:phone":"+44 1260 299299",
    "sg:postcode":"SK7 3NY",
    "sg:province":"Cheshire",
    "sg:tags":[
        "photographer"
    ],
    "wof:name":"David Lamb Photography",
    "wof:placetype":"venue"
},
  "geometry": {"coordinates":[-2.177026,53.372784],"type":"Point"}
}