{
  "type": "Feature",
  "properties": {
    "iso:country":"GB",
    "sg:address":"32 Worple Rd Mews",
    "sg:city":"Wimbledon",
    "sg:classifiers":[
        {
            "category":"Real Estate",
            "subcategory":"Architect",
            "type":"Services"
        }
    ],
    "sg:phone":"+44 20 8287 2808",
    "sg:postcode":"SW19 4DJ",
    "sg:province":"Greater London",
    "wof:name":"Alan Riley Associates",
    "wof:placetype":"venue"
},
  "geometry": {"coordinates":[-0.2104890049,51.4202690125],"type":"Point"}
}