{
  "type": "Feature",
  "properties": {
    "addr:full":"Yew Tree Farm, Pound Bank, Far Forest Kidderminster Shropshire DY14 9TH",
    "addr:postcode":"dy14 9th",
    "addr:street":"Yew;Far Forest",
    "iso:country":"GB",
    "sg:address":"Yew Tree Farm, Pound Bank, Far Forest",
    "sg:city":"Kidderminster",
    "sg:classifiers":[
        {
            "category":"Recreation",
            "subcategory":"Campground",
            "type":"Entertainment"
        }
    ],
    "sg:phone":"+44 1299 266300",
    "sg:postcode":"DY14 9TH",
    "sg:province":"Shropshire",
    "sg:tags":[
        "caravan",
        "park"
    ],
    "wof:name":"Michael Pound",
    "wof:placetype":"venue"
},
  "geometry": {"coordinates":[-2.3958899975,52.3652687073],"type":"Point"}
}