{
  "type": "Feature",
  "properties": {
    "iso:country":"GB",
    "sg:address":"64-70 Alma Road",
    "sg:city":"Bournemouth",
    "sg:classifiers":[
        {
            "category":"Autos & Motor Vehicles",
            "subcategory":"Automobile Sales",
            "type":"Retail Goods"
        }
    ],
    "sg:phone":"+44 1202 388488",
    "sg:postcode":"BH9 1AN",
    "sg:province":"Dorset",
    "sg:tags":[
        "car",
        "used"
    ],
    "sg:website":"http://www.silverladyservices.co.uk",
    "wof:name":"Silver Lady Services Ltd",
    "wof:placetype":"venue"
},
  "geometry": {"coordinates":[-1.8748749495,50.7389221191],"type":"Point"}
}