{
  "type": "Feature",
  "properties": {
    "addr:full":"66 Plasmawr Road Cardiff Cardiff CF5 3JX",
    "addr:housenumber":"66",
    "addr:postcode":"cf5 3jx",
    "addr:street":"Plasmawr Road",
    "iso:country":"GB",
    "sg:address":"66 Plasmawr Road",
    "sg:city":"Cardiff",
    "sg:classifiers":[
        {
            "category":"Government",
            "subcategory":"Post Office",
            "type":"Public Place"
        }
    ],
    "sg:phone":"+44 29 2055 5535",
    "sg:postcode":"CF5 3JX",
    "sg:province":"Cardiff",
    "wof:name":"Plasmawr Road Post Office",
    "wof:placetype":"venue"
},
  "geometry": {"coordinates":[-3.245374918,51.4959754944],"type":"Point"}
}