{
  "type": "Feature",
  "properties": {
    "addr:full":"568 Kingsland Road London Greater London E8 4AH",
    "addr:housenumber":"568",
    "addr:postcode":"e8 4ah",
    "addr:street":"Kingsland Road",
    "iso:country":"GB",
    "sg:address":"568 Kingsland Road",
    "sg:city":"London",
    "sg:classifiers":[
        {
            "category":"Home & Garden",
            "subcategory":"Carpets & Floor Coverings",
            "type":"Retail Goods"
        }
    ],
    "sg:phone":"+44 20 7254 8547",
    "sg:postcode":"E8 4AH",
    "sg:province":"Greater London",
    "sg:tags":[
        "carpets",
        "rug",
        "matting"
    ],
    "wof:name":"Surplus City",
    "wof:placetype":"venue"
},
  "geometry": {"coordinates":[-0.0756570026,51.5453338623],"type":"Point"}
}