{
  "type": "Feature",
  "properties": {
    "addr:full":"Unit 21, The Fort Industrial Park, Dunlop Way Birmingham West Midlands B35 7AR",
    "addr:housenumber":"unit 21",
    "addr:postcode":"b35 7ar",
    "addr:street":"Industrial Park Dunlop Way",
    "iso:country":"GB",
    "sg:address":"Unit 21, The Fort Industrial Park, Dunlop Way",
    "sg:city":"Birmingham",
    "sg:classifiers":[
        {
            "category":"Autos & Motor Vehicles",
            "subcategory":"Auto Supplies",
            "type":"Retail Goods"
        },
        {
            "category":"Shopping",
            "type":"Retail Goods"
        }
    ],
    "sg:phone":"+44 121 749 8800",
    "sg:postcode":"B35 7AR",
    "sg:province":"West Midlands",
    "sg:tags":[
        "part",
        "component",
        "accessory"
    ],
    "wof:name":"U R O Auto Spares Ltd.",
    "wof:placetype":"venue"
},
  "geometry": {"coordinates":[-1.804418,52.512028],"type":"Point"}
}