{
  "type": "Feature",
  "properties": {
    "addr:full":"Alexander House Walsall West Midlands WS1 3QD",
    "addr:postcode":"ws1 3qd",
    "addr:street":"Walsall",
    "iso:country":"GB",
    "sg:address":"Alexander House",
    "sg:city":"Walsall",
    "sg:classifiers":[
        {
            "category":"Professional",
            "subcategory":"Accounting & Tax Preparation",
            "type":"Services"
        }
    ],
    "sg:phone":"+44 1922 627178",
    "sg:postcode":"WS1 3QD",
    "sg:province":"West Midlands",
    "sg:tags":[
        "accountant"
    ],
    "wof:name":"Richard Maries & Co",
    "wof:placetype":"venue"
},
  "geometry": {"coordinates":[-1.9761040211,52.5852890015],"type":"Point"}
}