{
  "type": "Feature",
  "properties": {
    "addr:full":"12 Westminster Gardens Bedford Bedfordshire MK42 8TX",
    "addr:housenumber":"12",
    "addr:postcode":"mk42 8tx",
    "addr:street":"Westminster Gardens",
    "iso:country":"GB",
    "sg:address":"12 Westminster Gardens",
    "sg:city":"Bedford",
    "sg:classifiers":[
        {
            "category":"Freight",
            "type":"Transportation"
        }
    ],
    "sg:phone":"+44 1234 840675",
    "sg:postcode":"MK42 8TX",
    "sg:province":"Bedfordshire",
    "sg:tags":[
        "haulage",
        "road"
    ],
    "wof:name":"A C International Transport",
    "wof:placetype":"venue"
},
  "geometry": {"coordinates":[-0.493457,52.124714],"type":"Point"}
}