{
  "type": "Feature",
  "properties": {
    "addr:full":"18-20 Langney Road Eastbourne East Sussex BN21 3EU",
    "addr:housenumber":"18-20",
    "addr:postcode":"bn21 3eu",
    "addr:street":"Langney Road",
    "iso:country":"GB",
    "sg:address":"18-20 Langney Road",
    "sg:city":"Eastbourne",
    "sg:classifiers":[
        {
            "category":"Recreation",
            "type":"Entertainment"
        }
    ],
    "sg:phone":"+44 1323 722493",
    "sg:postcode":"BN21 3EU",
    "sg:province":"East Sussex",
    "sg:tags":[
        "snooker",
        "billiards",
        "pool"
    ],
    "wof:name":"Dolphin Snooker Club",
    "wof:placetype":"venue"
},
  "geometry": {"coordinates":[0.2880890071,50.7687301636],"type":"Point"}
}