{
  "type": "Feature",
  "properties": {
    "addr:full":"145 Lewes Road Brighton East Sussex BN2 3LG",
    "addr:housenumber":"145",
    "addr:postcode":"bn2 3lg",
    "addr:street":"Lewes Road",
    "iso:country":"GB",
    "sg:address":"145 Lewes Road",
    "sg:city":"Brighton",
    "sg:classifiers":[
        {
            "category":"Retail",
            "subcategory":"Funeral Services",
            "type":"Services"
        }
    ],
    "sg:postcode":"BN2 3LG",
    "sg:province":"East Sussex",
    "wof:name":"S E Skinner & Sons",
    "wof:placetype":"venue"
},
  "geometry": {"coordinates":[-0.1257490069,50.8355140686],"type":"Point"}
}