{
  "type": "Feature",
  "properties": {
    "addr:full":"Unit 6 Wyvern Industrial Estate, Lutterworth Leicester Leicestershire LE2 9TQ",
    "addr:housenumber":"unit 6",
    "addr:postcode":"le2 9tq",
    "addr:street":"Wyvern Industrial Estate",
    "iso:country":"GB",
    "sg:address":"Unit 6 Wyvern Industrial Estate, Lutterworth",
    "sg:city":"Leicester",
    "sg:classifiers":[
        {
            "category":"Building & Trades",
            "subcategory":"Construction",
            "type":"Services"
        }
    ],
    "sg:phone":"+44 116 247 7941",
    "sg:postcode":"LE2 9TQ",
    "sg:province":"Leicestershire",
    "sg:tags":[
        "glazier",
        "decorator",
        "painter"
    ],
    "wof:name":"P A Thurlow",
    "wof:placetype":"venue"
},
  "geometry": {"coordinates":[-1.1410200596,52.57862854],"type":"Point"}
}