{
  "type": "Feature",
  "properties": {
    "addr:full":"17 Old Market Place Warrington Cheshire WA1 1QB",
    "addr:housenumber":"17",
    "addr:postcode":"wa1 1qb",
    "addr:street":"Old Market Place",
    "iso:country":"GB",
    "sg:address":"17 Old Market Place",
    "sg:city":"Warrington",
    "sg:classifiers":[
        {
            "category":"Shopping",
            "subcategory":"Hobbies, Toys, & Games",
            "type":"Retail Goods"
        }
    ],
    "sg:phone":"+44 1925 573990",
    "sg:postcode":"WA1 1QB",
    "sg:province":"Cheshire",
    "sg:tags":[
        "shop",
        "toy",
        "sale"
    ],
    "sg:website":"http://www.elc.co.uk",
    "wof:name":"Early Learning Centre",
    "wof:placetype":"venue"
},
  "geometry": {"coordinates":[-2.5943639278,53.3899002075],"type":"Point"}
}