{
  "type": "Feature",
  "properties": {
    "addr:full":"36 West Main St Bathgate North Lanarkshire EH47 0QX",
    "addr:housenumber":"36",
    "addr:postcode":"eh47 0qx",
    "addr:street":"West Main St Bathgate",
    "iso:country":"GB",
    "sg:address":"36 West Main St",
    "sg:city":"Bathgate",
    "sg:classifiers":[
        {
            "category":"Shopping",
            "subcategory":"News",
            "type":"Retail Goods"
        }
    ],
    "sg:phone":"+44 1501 740256",
    "sg:postcode":"EH47 0QX",
    "sg:province":"North Lanarkshire",
    "sg:tags":[
        "newsagent"
    ],
    "wof:name":"Ali & Sons",
    "wof:placetype":"venue"
},
  "geometry": {"coordinates":[-3.6870279312,55.8665962219],"type":"Point"}
}