{
  "type": "Feature",
  "properties": {
    "addr:full":"Amersham Rd High Wycombe Buckinghamshire HP15 7PX",
    "addr:postcode":"hp15 7px",
    "addr:street":"Amersham Rd",
    "iso:country":"GB",
    "sg:address":"Amersham Rd",
    "sg:city":"High Wycombe",
    "sg:classifiers":[
        {
            "category":"Retail",
            "subcategory":"Repair Shop",
            "type":"Services"
        }
    ],
    "sg:phone":"+44 1494 711452",
    "sg:postcode":"HP15 7PX",
    "sg:province":"Buckinghamshire",
    "sg:tags":[
        "radio",
        "television",
        "video"
    ],
    "wof:name":"Eurotech",
    "wof:placetype":"venue"
},
  "geometry": {"coordinates":[-0.7148020267,51.6504707336],"type":"Point"}
}