{
  "type": "Feature",
  "properties": {
    "addr:full":"Calenick Street Truro Cornwall TR1 2SF",
    "addr:postcode":"tr1 2sf",
    "addr:street":"Calenick Street",
    "iso:country":"GB",
    "sg:address":"Calenick Street",
    "sg:city":"Truro",
    "sg:classifiers":[
        {
            "category":"Parking",
            "type":"Transportation"
        }
    ],
    "sg:phone":"+44 1872 276779",
    "sg:postcode":"TR1 2SF",
    "sg:province":"Cornwall",
    "sg:tags":[
        "car",
        "park"
    ],
    "wof:name":"Moorfield Car Park",
    "wof:placetype":"venue"
},
  "geometry": {"coordinates":[-5.054834,50.262104],"type":"Point"}
}