{
  "type": "Feature",
  "properties": {
    "addr:full":"594 Kingsbury Rd, Erdington Birmingham West Midlands B24 9PJ",
    "addr:housenumber":"594",
    "addr:postcode":"b24 9pj",
    "addr:street":"Kingsbury Rd",
    "iso:country":"GB",
    "sg:address":"594 Kingsbury Rd, Erdington",
    "sg:city":"Birmingham",
    "sg:classifiers":[
        {
            "category":"Shopping",
            "subcategory":"Florist",
            "type":"Retail Goods"
        }
    ],
    "sg:postcode":"B24 9PJ",
    "sg:province":"West Midlands",
    "wof:name":"Edwards,Angela,",
    "wof:placetype":"venue"
},
  "geometry": {"coordinates":[-1.822258,52.517479],"type":"Point"}
}