{
  "type": "Feature",
  "properties": {
    "addr:full":"Naburn Hill Farm, Crockey Hill York North Yorkshire YO19 4SR",
    "addr:postcode":"yo19 4sr",
    "addr:street":"Naburn Hill;Crockey Hill",
    "iso:country":"GB",
    "sg:address":"Naburn Hill Farm, Crockey Hill",
    "sg:city":"York",
    "sg:classifiers":[
        {
            "category":"Farming",
            "subcategory":"Farm",
            "type":"Manufacturing & Wholesale Goods"
        }
    ],
    "sg:postcode":"YO19 4SR",
    "sg:province":"North Yorkshire",
    "sg:tags":[
        "mixed",
        "crop"
    ],
    "wof:name":"T H Hobson Ltd.",
    "wof:placetype":"venue"
},
  "geometry": {"coordinates":[-1.0538539886,53.8905410767],"type":"Point"}
}