{
  "type": "Feature",
  "properties": {
    "iso:country":"GB",
    "sg:address":"Bank House, 2nd Floor, The Porter Gate",
    "sg:city":"Sheffield",
    "sg:classifiers":[
        {
            "category":"Insurance",
            "subcategory":"Insurance Agent",
            "type":"Services"
        }
    ],
    "sg:phone":"+44 114 272 3316",
    "sg:postcode":"S11 8NX",
    "sg:province":"Derbyshire",
    "wof:name":"Scottish Equitable Plc",
    "wof:placetype":"venue"
},
  "geometry": {"coordinates":[-1.4978539944,53.3682098389],"type":"Point"}
}