{
  "type": "Feature",
  "properties": {
    "addr:full":"23 Reevylands Dr Bradford West Yorkshire BD6 3QH",
    "addr:housenumber":"23",
    "addr:postcode":"bd6 3qh",
    "addr:street":"Reevylands Dr",
    "iso:country":"GB",
    "sg:address":"23 Reevylands Dr",
    "sg:city":"Bradford",
    "sg:classifiers":[
        {
            "category":"Building & Trades",
            "subcategory":"Plumbing",
            "type":"Services"
        }
    ],
    "sg:phone":"+44 1274 605306",
    "sg:postcode":"BD6 3QH",
    "sg:province":"West Yorkshire",
    "sg:tags":[
        "heating"
    ],
    "wof:name":"Dickinson T & Co",
    "wof:placetype":"venue"
},
  "geometry": {"coordinates":[-1.784308,53.764404],"type":"Point"}
}