{
  "type": "Feature",
  "properties": {
    "addr:full":"20 Northdown Rd Margate Kent CT9 2QU",
    "addr:housenumber":"20",
    "addr:postcode":"ct9 2qu",
    "addr:street":"Northdown Rd Margate",
    "iso:country":"GB",
    "sg:address":"20 Northdown Rd",
    "sg:city":"Margate",
    "sg:classifiers":[
        {
            "category":"Shopping",
            "subcategory":"Music",
            "type":"Retail Goods"
        }
    ],
    "sg:phone":"+44 1843 231359",
    "sg:postcode":"CT9 2QU",
    "sg:province":"Kent",
    "sg:tags":[
        "record",
        "tape",
        "cd"
    ],
    "wof:name":"Musical Box",
    "wof:placetype":"venue"
},
  "geometry": {"coordinates":[1.3878469467,51.3898773193],"type":"Point"}
}