{
  "type": "Feature",
  "properties": {
    "iso:country":"GB",
    "sg:address":"20 Milner Rd",
    "sg:city":"Whitstable",
    "sg:classifiers":[
        {
            "category":"Retail",
            "subcategory":"Driving School",
            "type":"Services"
        }
    ],
    "sg:phone":"+44 1227 276501",
    "sg:postcode":"CT5 4SH",
    "sg:province":"Kent",
    "wof:name":"Hill Brian",
    "wof:placetype":"venue"
},
  "geometry": {"coordinates":[1.000641,51.34573],"type":"Point"}
}