{
  "type": "Feature",
  "properties": {
    "addr:full":"Faccombe Andover Hampshire SP11 0AH",
    "addr:housenumber":"faccombe",
    "addr:postcode":"sp11 0ah",
    "addr:street":"Andover Hampshire",
    "iso:country":"GB",
    "sg:address":"Faccombe",
    "sg:city":"Andover",
    "sg:classifiers":[
        {
            "category":"Place Of Worship",
            "type":"Public Place"
        }
    ],
    "sg:phone":"+44 1264 736222",
    "sg:postcode":"SP11 0AH",
    "sg:province":"Hampshire",
    "wof:name":"St Barnabas C of E Church",
    "wof:placetype":"venue"
},
  "geometry": {"coordinates":[-1.4498100281,51.2785682678],"type":"Point"}
}