{
  "type": "Feature",
  "properties": {
    "addr:full":"Old Farm, Calves Hill, Chedworth Cheltenham Gloucestershire GL54 4AH",
    "addr:postcode":"gl54 4ah",
    "addr:street":"Calves Hill Chedworth",
    "iso:country":"GB",
    "sg:address":"Old Farm, Calves Hill, Chedworth",
    "sg:city":"Cheltenham",
    "sg:classifiers":[
        {
            "category":"Real Estate",
            "subcategory":"Surveying",
            "type":"Services"
        }
    ],
    "sg:phone":"+44 1285 720197",
    "sg:postcode":"GL54 4AH",
    "sg:province":"Gloucestershire",
    "sg:tags":[
        "surveyor",
        "valuer"
    ],
    "wof:name":"Harwood George",
    "wof:placetype":"venue"
},
  "geometry": {"coordinates":[-1.9252170324,51.8057937622],"type":"Point"}
}