{
  "type": "Feature",
  "properties": {
    "addr:full":"Llywn Celyn, Llanberis Caernarfon Gwynedd LL55 4SR",
    "addr:postcode":"ll55 4sr",
    "addr:street":"Llanberis",
    "iso:country":"GB",
    "sg:address":"Llywn Celyn, Llanberis",
    "sg:city":"Caernarfon",
    "sg:classifiers":[
        {
            "category":"Travel",
            "subcategory":"Hostel",
            "type":"Entertainment"
        }
    ],
    "sg:phone":"+44 1286 870280",
    "sg:postcode":"LL55 4SR",
    "sg:province":"Gwynedd",
    "sg:tags":[
        "youth"
    ],
    "wof:name":"Youth Hostels Association",
    "wof:placetype":"venue"
},
  "geometry": {"coordinates":[-4.120893,53.117477],"type":"Point"}
}