{
  "type": "Feature",
  "properties": {
    "addr:full":"Old School, Dodford Northampton Buckinghamshire NN7 4SX",
    "addr:postcode":"nn7 4sx",
    "addr:street":"Dodford",
    "iso:country":"GB",
    "sg:address":"Old School, Dodford",
    "sg:city":"Northampton",
    "sg:classifiers":[
        {
            "category":"Farming",
            "subcategory":"Nursery",
            "type":"Manufacturing & Wholesale Goods"
        }
    ],
    "sg:postcode":"NN7 4SX",
    "sg:province":"Buckinghamshire",
    "sg:tags":[
        "creche"
    ],
    "wof:name":"Holbourn House Day Nursery",
    "wof:placetype":"venue"
},
  "geometry": {"coordinates":[-1.101331,52.23951],"type":"Point"}
}