{
  "type": "Feature",
  "properties": {
    "addr:full":"357 Hedon Road Hull East Riding of Yorkshire HU9 1RA",
    "addr:housenumber":"357",
    "addr:postcode":"hu9 1ra",
    "addr:street":"Hedon Road",
    "iso:country":"GB",
    "sg:address":"357 Hedon Road",
    "sg:city":"Hull",
    "sg:classifiers":[
        {
            "category":"Manufacturing",
            "subcategory":"Signs",
            "type":"Manufacturing & Wholesale Goods"
        }
    ],
    "sg:phone":"+44 1482 227233",
    "sg:postcode":"HU9 1RA",
    "sg:province":"East Riding of Yorkshire",
    "sg:tags":[
        "nameplate"
    ],
    "wof:name":"Readwell Signs",
    "wof:placetype":"venue"
},
  "geometry": {"coordinates":[-0.30572,53.747684],"type":"Point"}
}