{
  "type": "Feature",
  "properties": {
    "addr:full":"23 Queens Road Llandudno Conwy LL30 1AZ",
    "addr:housenumber":"23",
    "addr:postcode":"ll30 1az",
    "addr:street":"Queens Road",
    "iso:country":"GB",
    "sg:address":"23 Queens Road",
    "sg:city":"Llandudno",
    "sg:classifiers":[
        {
            "category":"Professional",
            "subcategory":"Printing & Photocopies",
            "type":"Services"
        }
    ],
    "sg:phone":"+44 1492 877119",
    "sg:postcode":"LL30 1AZ",
    "sg:province":"Conwy",
    "sg:tags":[
        "printer"
    ],
    "wof:name":"Craig Y Don Printing Works Ltd",
    "wof:placetype":"venue"
},
  "geometry": {"coordinates":[-3.8112609386,53.3209953308],"type":"Point"}
}