{
  "type": "Feature",
  "properties": {
    "addr:full":"The Stables, Alderholt Park, Alderholt Fordingbridge Dorset SP6 3EH",
    "addr:postcode":"sp6 3eh",
    "addr:street":"Alderholt",
    "iso:country":"GB",
    "sg:address":"The Stables, Alderholt Park, Alderholt",
    "sg:city":"Fordingbridge",
    "sg:classifiers":[
        {
            "category":"Building & Trades",
            "subcategory":"Construction",
            "type":"Services"
        }
    ],
    "sg:phone":"+44 1425 656902",
    "sg:postcode":"SP6 3EH",
    "sg:province":"Dorset",
    "sg:tags":[
        "builder"
    ],
    "wof:name":"J.F Crouter & Son",
    "wof:placetype":"venue"
},
  "geometry": {"coordinates":[-1.8385089636,50.9115791321],"type":"Point"}
}