{
  "type": "Feature",
  "properties": {
    "addr:full":"34 Greenwich Park Street, Greenwich London Greater London SE10 9LT",
    "addr:housenumber":"34",
    "addr:postcode":"se10 9lt",
    "addr:street":"Greenwich Park Street",
    "iso:country":"GB",
    "sg:address":"34 Greenwich Park Street, Greenwich",
    "sg:city":"London",
    "sg:classifiers":[
        {
            "category":"Professional",
            "subcategory":"Management & Consulting",
            "type":"Services"
        }
    ],
    "sg:phone":"+44 20 8516 8355",
    "sg:postcode":"SE10 9LT",
    "sg:province":"Greater London",
    "sg:tags":[
        "consultant",
        "business"
    ],
    "wof:name":"Mayday Management Services Ltd",
    "wof:placetype":"venue"
},
  "geometry": {"coordinates":[0.000673,51.4824867249],"type":"Point"}
}