{
  "type": "Feature",
  "properties": {
    "addr:full":"Unit 8/9, Crosland Industrial Estate, Stockport Road West Stockport Cheshire SK6 2BR",
    "addr:housenumber":"unit 8 / 9",
    "addr:postcode":"sk6 2br",
    "addr:street":"Crosland Industrial Estate Stockport Road West",
    "iso:country":"GB",
    "sg:address":"Unit 8/9, Crosland Industrial Estate, Stockport Road West",
    "sg:city":"Stockport",
    "sg:classifiers":[
        {
            "category":"Home & Garden",
            "subcategory":"Hardware",
            "type":"Retail Goods"
        }
    ],
    "sg:phone":"+44 161 406 9800",
    "sg:postcode":"SK6 2BR",
    "sg:province":"Cheshire",
    "sg:tags":[
        "heat",
        "mech",
        "exchanger"
    ],
    "wof:name":"S W E P Ltd.",
    "wof:placetype":"venue"
},
  "geometry": {"coordinates":[-2.11529,53.421959],"type":"Point"}
}