{
  "type": "Feature",
  "properties": {
    "addr:full":"22 High Street, Kegworth Derby Leicestershire DE74 2DA",
    "addr:housenumber":"22",
    "addr:postcode":"de74 2da",
    "addr:street":"High Street",
    "iso:country":"GB",
    "sg:address":"22 High Street, Kegworth",
    "sg:city":"Derby",
    "sg:classifiers":[
        {
            "category":"Home & Garden",
            "subcategory":"Carpets & Floor Coverings",
            "type":"Retail Goods"
        }
    ],
    "sg:phone":"+44 1509 673974",
    "sg:postcode":"DE74 2DA",
    "sg:province":"Leicestershire",
    "sg:tags":[
        "material",
        "retailer",
        "rug",
        "flooring"
    ],
    "wof:name":"FLOORWISE GROUP LTD",
    "wof:placetype":"venue"
},
  "geometry": {"coordinates":[-1.3431500196,52.8394393921],"type":"Point"}
}