{
  "type": "Feature",
  "properties": {
    "addr:full":"69 High Street Porthmadog Gwynedd LL49 9LR",
    "addr:housenumber":"69",
    "addr:postcode":"ll49 9lr",
    "addr:street":"High Street",
    "iso:country":"GB",
    "sg:address":"69 High Street",
    "sg:city":"Porthmadog",
    "sg:classifiers":[
        {
            "category":"Shopping",
            "subcategory":"Clothing, Apparel, & Fashions",
            "type":"Retail Goods"
        }
    ],
    "sg:phone":"+44 1766 512105",
    "sg:postcode":"LL49 9LR",
    "sg:province":"Gwynedd",
    "sg:tags":[
        "menswear"
    ],
    "sg:website":"http://www.nigelhughesphoto.com",
    "wof:name":"Nigel'S",
    "wof:placetype":"venue"
},
  "geometry": {"coordinates":[-4.134255,52.932758],"type":"Point"}
}