{
  "type": "Feature",
  "properties": {
    "iso:country":"GB",
    "sg:address":"7 Porteous Pend, 25 Grassmarket",
    "sg:city":"Edinburgh",
    "sg:classifiers":[
        {
            "category":"Manufacturing",
            "subcategory":"Tools & Machinery",
            "type":"Manufacturing & Wholesale Goods"
        }
    ],
    "sg:phone":"+44 131 226 4124",
    "sg:postcode":"EH1 2HP",
    "sg:province":"City of Edinburgh",
    "sg:tags":[
        "society",
        "friendly"
    ],
    "wof:name":"Radiocabs Insurance Services",
    "wof:placetype":"venue"
},
  "geometry": {"coordinates":[-3.19681,55.947041],"type":"Point"}
}