{
  "type": "Feature",
  "properties": {
    "addr:full":"127 Town Road, Hanley Stoke-on-trent Staffordshire ST1 2JZ",
    "addr:housenumber":"127",
    "addr:postcode":"staffordshire st1 2jz",
    "addr:street":"Town Road",
    "iso:country":"GB",
    "sg:address":"127 Town Road, Hanley",
    "sg:city":"Stoke-on-trent",
    "sg:classifiers":[
        {
            "category":"Bars & Pubs",
            "type":"Food & Drink"
        }
    ],
    "sg:phone":"+44 1782 215364",
    "sg:postcode":"ST1 2JZ",
    "sg:province":"Staffordshire",
    "sg:tags":[
        "pubs",
        "inn"
    ],
    "wof:name":"Whitbread Hotel Co. Ltd.",
    "wof:placetype":"venue"
},
  "geometry": {"coordinates":[-2.175069,53.029369],"type":"Point"}
}