{
  "type": "Feature",
  "properties": {
    "iso:country":"GB",
    "sg:address":"35 St Cuthbert Street",
    "sg:city":"Wells",
    "sg:classifiers":[
        {
            "category":"Personal",
            "subcategory":"Beauty Salon",
            "type":"Services"
        }
    ],
    "sg:postcode":"BA5 2AW",
    "sg:province":"Somerset",
    "sg:tags":[
        "unisex",
        "hairdresser"
    ],
    "wof:name":"Ribbons Hair Studio",
    "wof:placetype":"venue"
},
  "geometry": {"coordinates":[-2.651184,51.20787],"type":"Point"}
}