{
  "type": "Feature",
  "properties": {
    "iso:country":"GB",
    "sg:address":"151 Byron Avenue",
    "sg:city":"Manor Park",
    "sg:classifiers":[
        {
            "category":"Health Services",
            "subcategory":"Doctor",
            "type":"Services"
        }
    ],
    "sg:phone":"+44 20 8471 5037",
    "sg:postcode":"E12 6NQ",
    "sg:province":"Greater London",
    "sg:tags":[
        "practitioners"
    ],
    "wof:name":"Dr P Alagaraja",
    "wof:placetype":"venue"
},
  "geometry": {"coordinates":[0.0544040017,51.5429267883],"type":"Point"}
}