{
  "type": "Feature",
  "properties": {
    "addr:full":"4 Hatherleigh Way Romford Essex RM3 8HE",
    "addr:housenumber":"4",
    "addr:postcode":"rm3 8he",
    "addr:street":"Hatherleigh Way",
    "iso:country":"GB",
    "sg:address":"4 Hatherleigh Way",
    "sg:city":"Romford",
    "sg:classifiers":[
        {
            "category":"Building & Trades",
            "subcategory":"Construction",
            "type":"Services"
        }
    ],
    "sg:phone":"+44 1708 373224",
    "sg:postcode":"RM3 8HE",
    "sg:province":"Essex",
    "sg:tags":[
        "tiling",
        "contractor"
    ],
    "wof:name":"A B C Tiling",
    "wof:placetype":"venue"
},
  "geometry": {"coordinates":[0.217418,51.596031],"type":"Point"}
}