{
  "type": "Feature",
  "properties": {
    "addr:full":"1 Gresham Street London Greater London EC2V 7BU",
    "addr:housenumber":"1",
    "addr:postcode":"ec2v 7bu",
    "addr:street":"Gresham Street",
    "iso:country":"GB",
    "sg:address":"1 Gresham Street",
    "sg:city":"London",
    "sg:classifiers":[
        {
            "category":"Organizations",
            "subcategory":"Membership Organization",
            "type":"Services"
        }
    ],
    "sg:postcode":"EC2V 7BU",
    "sg:province":"Greater London",
    "sg:tags":[
        "club"
    ],
    "wof:name":"Bickmore Management Limited",
    "wof:placetype":"venue"
},
  "geometry": {"coordinates":[-0.0967399999,51.5164070129],"type":"Point"}
}