{
  "type": "Feature",
  "properties": {
    "iso:country":"GB",
    "sg:address":"Lauder Rd",
    "sg:city":"Dalkeith",
    "sg:classifiers":[
        {
            "category":"Recreation",
            "subcategory":"Dog Park",
            "type":"Entertainment"
        }
    ],
    "sg:phone":"+44 131 660 4063",
    "sg:postcode":"EH22 2PX",
    "sg:province":"City of Edinburgh",
    "wof:name":"Dalkeith Breeding Kennels",
    "wof:placetype":"venue"
},
  "geometry": {"coordinates":[-3.040489,55.889462],"type":"Point"}
}