{
  "type": "Feature",
  "properties": {
    "iso:country":"GB",
    "sg:address":"1 The Green, Darnall",
    "sg:city":"Sheffield",
    "sg:classifiers":[
        {
            "category":"Organizations",
            "subcategory":"Membership Organization",
            "type":"Services"
        }
    ],
    "sg:phone":"+44 114 281 2017",
    "sg:postcode":"S9 5JN",
    "sg:province":"South Yorkshire",
    "sg:tags":[
        "club",
        "social"
    ],
    "wof:name":"The Green Social Club",
    "wof:placetype":"venue"
},
  "geometry": {"coordinates":[-1.410154,53.387859],"type":"Point"}
}