{
  "type": "Feature",
  "properties": {
    "iso:country":"GB",
    "sg:address":"10-12 Lorne Street",
    "sg:city":"Middlesbrough",
    "sg:classifiers":[
        {
            "category":"Building & Trades",
            "subcategory":"Construction",
            "type":"Services"
        }
    ],
    "sg:phone":"+44 1642 224193",
    "sg:postcode":"TS1 5QY",
    "sg:province":"North Yorkshire",
    "sg:tags":[
        "builder"
    ],
    "wof:name":"J E Nozedar Ltd.",
    "wof:placetype":"venue"
},
  "geometry": {"coordinates":[-1.250649,54.570728],"type":"Point"}
}