{
  "type": "Feature",
  "properties": {
    "iso:country":"GB",
    "sg:address":"London Road, Hook",
    "sg:city":"Basingstoke",
    "sg:classifiers":[
        {
            "category":"Manufacturing",
            "subcategory":"Building Materials",
            "type":"Manufacturing & Wholesale Goods"
        }
    ],
    "sg:phone":"+44 1256 763230",
    "sg:postcode":"RG27 9EE",
    "sg:province":"Berkshire",
    "sg:tags":[
        "merchant",
        "builder"
    ],
    "wof:name":"Wellworth Builders Supplies",
    "wof:placetype":"venue"
},
  "geometry": {"coordinates":[-0.9675289989,51.2805862427],"type":"Point"}
}