{
  "type": "Feature",
  "properties": {
    "addr:full":"Old R A F Camp, Brookland Romney Marsh Kent TN29 9TF",
    "addr:postcode":"tn29 9tf",
    "addr:street":"Old R A F Camp Brookland Romney",
    "iso:country":"GB",
    "sg:address":"Old R A F Camp, Brookland",
    "sg:city":"Romney Marsh",
    "sg:classifiers":[
        {
            "category":"Transit Center",
            "subcategory":"Freight",
            "type":"Transportation"
        }
    ],
    "sg:phone":"+44 1797 344616",
    "sg:postcode":"TN29 9TF",
    "sg:province":"Kent",
    "sg:tags":[
        "shop",
        "craft",
        "centre"
    ],
    "wof:name":"Phillippine Village",
    "wof:placetype":"venue"
},
  "geometry": {"coordinates":[0.8347110152,50.9978523254],"type":"Point"}
}