{
  "type": "Feature",
  "properties": {
    "iso:country":"GB",
    "sg:address":"Waterside Station Road, Woodmancote",
    "sg:city":"Cheltenham",
    "sg:classifiers":[
        {
            "category":"Home & Garden",
            "subcategory":"Carpets & Floor Coverings",
            "type":"Retail Goods"
        },
        {
            "category":"Personal",
            "subcategory":"Nail Salon",
            "type":"Services"
        }
    ],
    "sg:phone":"+44 1242 677229",
    "sg:postcode":"GL52 9HR",
    "sg:province":"Gloucestershire",
    "sg:tags":[
        "technician",
        "carpets",
        "rug",
        "matting"
    ],
    "wof:name":"Cheltenham Nail Studio",
    "wof:placetype":"venue"
},
  "geometry": {"coordinates":[-2.040493,51.946327],"type":"Point"}
}