{
  "type": "Feature",
  "properties": {
    "addr:full":"3 Limehurst Square Northampton Northamptonshire NN5 6LP",
    "addr:housenumber":"3",
    "addr:postcode":"nn5 6lp",
    "addr:street":"Limehurst Square",
    "iso:country":"GB",
    "sg:address":"3 Limehurst Square",
    "sg:city":"Northampton",
    "sg:classifiers":[
        {
            "category":"Professional",
            "subcategory":"Business Services",
            "type":"Services"
        },
        {
            "category":"Casinos & Gambling",
            "type":"Entertainment"
        }
    ],
    "sg:phone":"+44 1604 586332",
    "sg:postcode":"NN5 6LP",
    "sg:province":"Northamptonshire",
    "sg:tags":[
        "turf",
        "accountant",
        "bookmaker"
    ],
    "wof:name":"ALLAN JONES",
    "wof:placetype":"venue"
},
  "geometry": {"coordinates":[-0.945786,52.252071],"type":"Point"}
}