{
  "type": "Feature",
  "properties": {
    "iso:country":"GB",
    "sg:address":"Garstang By Pass Road, Churchtown",
    "sg:city":"Preston",
    "sg:classifiers":[
        {
            "category":"Autos & Motor Vehicles",
            "subcategory":"Fuel & Gas Station",
            "type":"Retail Goods"
        },
        {
            "category":"Utilities",
            "subcategory":"Fuel Oil & Lpg",
            "type":"Services"
        }
    ],
    "sg:phone":"+44 1995 606160",
    "sg:postcode":"PR3 0HQ",
    "sg:province":"Lancashire",
    "sg:tags":[
        "petrol",
        "distributor",
        "filling"
    ],
    "wof:name":"Churchtown Service Station",
    "wof:placetype":"venue"
},
  "geometry": {"coordinates":[-2.789922,53.881405],"type":"Point"}
}