{
  "type": "Feature",
  "properties": {
    "addr:full":"Laurence Ho, 1 Catford Rd Catford Greater London SE6 4RU",
    "addr:housenumber":"1",
    "addr:postcode":"se6 4ru",
    "addr:street":"Catford Rd",
    "iso:country":"GB",
    "sg:address":"Laurence Ho, 1 Catford Rd",
    "sg:city":"Catford",
    "sg:classifiers":[
        {
            "category":"Farming",
            "subcategory":"Nursery",
            "type":"Manufacturing & Wholesale Goods"
        }
    ],
    "sg:phone":"+44 20 8695 6000",
    "sg:postcode":"SE6 4RU",
    "sg:province":"Greater London",
    "sg:tags":[
        "creche"
    ],
    "wof:name":"Lewisham Early Years Service",
    "wof:placetype":"venue"
},
  "geometry": {"coordinates":[-0.02078,51.445019],"type":"Point"}
}