{
  "type": "Feature",
  "properties": {
    "addr:full":"St. Peters Community Hall, The Willows Stevenage Hertfordshire SG2 8AN",
    "addr:postcode":"sg2 8an",
    "iso:country":"GB",
    "sg:address":"St. Peters Community Hall, The Willows",
    "sg:city":"Stevenage",
    "sg:classifiers":[
        {
            "category":"Community Center",
            "type":"Public Place"
        }
    ],
    "sg:phone":"+44 1438 231134",
    "sg:postcode":"SG2 8AN",
    "sg:province":"Hertfordshire",
    "sg:tags":[
        "centre"
    ],
    "wof:name":"Broadwater Community Association",
    "wof:placetype":"venue"
},
  "geometry": {"coordinates":[-0.190548,51.888977],"type":"Point"}
}