{
  "type": "Feature",
  "properties": {
    "iso:country":"GB",
    "sg:address":"112 Mornington Road",
    "sg:city":"Bolton",
    "sg:classifiers":[
        {
            "category":"Personal",
            "subcategory":"Beauty Salon",
            "type":"Services"
        },
        {
            "category":"Personal",
            "subcategory":"Barber",
            "type":"Services"
        }
    ],
    "sg:phone":"+44 1204 840562",
    "sg:postcode":"BL1 4ED",
    "sg:province":"Lancashire",
    "sg:tags":[
        "unisex",
        "hairdresser"
    ],
    "wof:name":"Julie's",
    "wof:placetype":"venue"
},
  "geometry": {"coordinates":[-2.455181,53.583168],"type":"Point"}
}