{
  "type": "Feature",
  "properties": {
    "addr:full":"Ferry Lane, Brothertoft Boston Lincolnshire PE20 3SR",
    "addr:postcode":"pe20 3sr",
    "addr:street":"Ferry Lane",
    "iso:country":"GB",
    "sg:address":"Ferry Lane, Brothertoft",
    "sg:city":"Boston",
    "sg:classifiers":[
        {
            "category":"Farming",
            "subcategory":"Farm",
            "type":"Manufacturing & Wholesale Goods"
        }
    ],
    "sg:postcode":"PE20 3SR",
    "sg:province":"Lincolnshire",
    "sg:tags":[
        "mixed",
        "crop"
    ],
    "wof:name":"P & N Anderson & Son",
    "wof:placetype":"venue"
},
  "geometry": {"coordinates":[-0.1214490011,53.0094451904],"type":"Point"}
}