{
  "type": "Feature",
  "properties": {
    "addr:full":"Cefn-y-blaen Farn, Clyro Hereford Herefordshire HR3 5SH",
    "addr:postcode":"hr3 5sh",
    "addr:street":"Clyro",
    "iso:country":"GB",
    "sg:address":"Cefn-y-blaen Farn, Clyro",
    "sg:city":"Hereford",
    "sg:classifiers":[
        {
            "category":"Farming",
            "subcategory":"Livestock Farm",
            "type":"Manufacturing & Wholesale Goods"
        }
    ],
    "sg:postcode":"HR3 5SH",
    "sg:province":"Herefordshire",
    "sg:tags":[
        "others"
    ],
    "wof:name":"John R Lloyd",
    "wof:placetype":"venue"
},
  "geometry": {"coordinates":[-3.1479051113,52.0869102478],"type":"Point"}
}