{
  "type": "Feature",
  "properties": {
    "iso:country":"GB",
    "sg:address":"Care Of Kwiksave, Station Road, Ainsdale",
    "sg:city":"Southport",
    "sg:classifiers":[
        {
            "category":"Food & Beverages",
            "subcategory":"Bakery",
            "type":"Retail Goods"
        }
    ],
    "sg:phone":"+44 1704 570724",
    "sg:postcode":"PR8 3HR",
    "sg:province":"Lancashire",
    "sg:tags":[
        "baker"
    ],
    "wof:name":"Country Fayre",
    "wof:placetype":"venue"
},
  "geometry": {"coordinates":[-3.033525,53.602547],"type":"Point"}
}