{
  "type": "Feature",
  "properties": {
    "iso:country":"GB",
    "sg:address":"Southwell Minster, Church Street",
    "sg:city":"Southwell",
    "sg:classifiers":[
        {
            "category":"Cafe",
            "type":"Food & Drink"
        }
    ],
    "sg:phone":"+44 1636 815691",
    "sg:postcode":"NG25 0HD",
    "sg:province":"Nottinghamshire",
    "sg:tags":[
        "tea",
        "room"
    ],
    "wof:name":"J &G Griffin",
    "wof:placetype":"venue"
},
  "geometry": {"coordinates":[-0.955189,53.078121],"type":"Point"}
}