{
  "type": "Feature",
  "properties": {
    "addr:full":"7 Paddock Row, Grosvenor Precinct Chester Cheshire CH1 1ED",
    "addr:housenumber":"7",
    "addr:postcode":"ch1 1ed",
    "addr:street":"Paddock Row",
    "iso:country":"GB",
    "sg:address":"7 Paddock Row, Grosvenor Precinct",
    "sg:city":"Chester",
    "sg:classifiers":[
        {
            "category":"Food & Beverages",
            "subcategory":"Specialty",
            "type":"Retail Goods"
        }
    ],
    "sg:phone":"+44 1244 348153",
    "sg:postcode":"CH1 1ED",
    "sg:province":"Cheshire",
    "sg:tags":[
        "retailer",
        "product",
        "health"
    ],
    "wof:name":"Holland & Barrett Ltd",
    "wof:placetype":"venue"
},
  "geometry": {"coordinates":[-2.8943688869,53.188129425],"type":"Point"}
}