{
  "type": "Feature",
  "properties": {
    "iso:country":"GB",
    "sg:address":"Unit 7/8, Curran Road",
    "sg:city":"Cardiff",
    "sg:classifiers":[
        {
            "category":"Retail",
            "subcategory":"Storage",
            "type":"Services"
        }
    ],
    "sg:phone":"+44 29 2066 8915",
    "sg:postcode":"CF10 5DF",
    "sg:province":"Cardiff",
    "sg:tags":[
        "household",
        "removal"
    ],
    "wof:name":"Cardiff Archives",
    "wof:placetype":"venue"
},
  "geometry": {"coordinates":[-3.177016,51.471905],"type":"Point"}
}