{
  "type": "Feature",
  "properties": {
    "iso:country":"GB",
    "sg:address":"30b Elm Hill",
    "sg:city":"Norwich",
    "sg:classifiers":[
        {
            "category":"Personal",
            "subcategory":"Beauty Salon",
            "type":"Services"
        }
    ],
    "sg:phone":"+44 1603 621275",
    "sg:postcode":"NR3 1HG",
    "sg:province":"Norfolk",
    "sg:tags":[
        "unisex",
        "hairdresser"
    ],
    "wof:name":"John Oliver Haircutters",
    "wof:placetype":"venue"
},
  "geometry": {"coordinates":[1.297112,52.632042],"type":"Point"}
}