{
  "type": "Feature",
  "properties": {
    "iso:country":"GB",
    "sg:address":"24 Royal Arc",
    "sg:city":"Cardiff",
    "sg:classifiers":[
        {
            "category":"Shopping",
            "subcategory":"Clothing, Apparel, & Fashions",
            "type":"Retail Goods"
        }
    ],
    "sg:phone":"+44 29 2034 2229",
    "sg:postcode":"CF1 2AE",
    "sg:province":"Cardiff",
    "sg:tags":[
        "lingerie",
        "hosiery"
    ],
    "wof:name":"Rosies Of Cardiff",
    "wof:placetype":"venue"
},
  "geometry": {"coordinates":[-3.17673,51.478401],"type":"Point"}
}