{
  "type": "Feature",
  "properties": {
    "addr:full":"Atlanta Wks, Stamshaw Rd Portsmouth Hampshire PO2 8LP",
    "addr:postcode":"hampshire po2 8lp",
    "addr:street":"Stamshaw Rd",
    "iso:country":"GB",
    "sg:address":"Atlanta Wks, Stamshaw Rd",
    "sg:city":"Portsmouth",
    "sg:classifiers":[
        {
            "category":"Retail",
            "subcategory":"Auto Repair",
            "type":"Services"
        }
    ],
    "sg:postcode":"PO2 8LP",
    "sg:province":"Hampshire",
    "sg:tags":[
        "modification",
        "garage"
    ],
    "wof:name":"Lee,Tommy,",
    "wof:placetype":"venue"
},
  "geometry": {"coordinates":[-1.08397,50.819618],"type":"Point"}
}