{
  "type": "Feature",
  "properties": {
    "addr:full":"Town Hall, New Road Brixham Devon TQ5 8TA",
    "addr:postcode":"tq5 8ta",
    "addr:street":"New Road",
    "iso:country":"GB",
    "sg:address":"Town Hall, New Road",
    "sg:city":"Brixham",
    "sg:classifiers":[
        {
            "category":"Government",
            "subcategory":"Office",
            "type":"Public Place"
        }
    ],
    "sg:phone":"+44 1803 859782",
    "sg:postcode":"TQ5 8TA",
    "sg:province":"Devon",
    "sg:tags":[
        "local"
    ],
    "wof:name":"Torbay Council",
    "wof:placetype":"venue"
},
  "geometry": {"coordinates":[-3.517744,50.39407],"type":"Point"}
}