{
  "type": "Feature",
  "properties": {
    "iso:country":"GB",
    "sg:address":"Bush House, High Street",
    "sg:city":"Alton",
    "sg:classifiers":[
        {
            "category":"Cafe",
            "type":"Food & Drink"
        }
    ],
    "sg:postcode":"GU34 3JP",
    "sg:province":"Hampshire",
    "sg:tags":[
        "tea",
        "room"
    ],
    "wof:name":"Bush House Tea Room",
    "wof:placetype":"venue"
},
  "geometry": {"coordinates":[-0.975235,51.14912],"type":"Point"}
}