{
  "type": "Feature",
  "properties": {
    "addr:full":"Newhaven, Goose Lane Ilminster Somerset TA19 9QQ",
    "addr:postcode":"ta19 9qq",
    "addr:street":"Goose Lane",
    "iso:country":"GB",
    "sg:address":"Newhaven, Goose Lane",
    "sg:city":"Ilminster",
    "sg:classifiers":[
        {
            "category":"Retail",
            "subcategory":"Auto Rental",
            "type":"Services"
        }
    ],
    "sg:phone":"+44 1460 234690",
    "sg:postcode":"TA19 9QQ",
    "sg:province":"Somerset",
    "sg:tags":[
        "car"
    ],
    "wof:name":"Leisure Hire",
    "wof:placetype":"venue"
},
  "geometry": {"coordinates":[-2.9175300598,50.9286689758],"type":"Point"}
}