{
  "type": "Feature",
  "properties": {
    "iso:country":"GB",
    "sg:address":"458 Heysham Rd",
    "sg:city":"Morecambe",
    "sg:classifiers":[
        {
            "category":"Social Services",
            "subcategory":"Retirement Home",
            "type":"Services"
        }
    ],
    "sg:phone":"+44 1524 851288",
    "sg:postcode":"LA3 2BN",
    "sg:province":"Lancashire",
    "sg:tags":[
        "rest"
    ],
    "wof:name":"Old Hall Farm Retirement Home",
    "wof:placetype":"venue"
},
  "geometry": {"coordinates":[-2.89429,54.042934],"type":"Point"}
}