{
  "type": "Feature",
  "properties": {
    "addr:full":"8 Seaview Road Wallasey Merseyside CH45 4LA",
    "addr:housenumber":"8",
    "addr:postcode":"ch45 4la",
    "addr:street":"Seaview Road",
    "iso:country":"GB",
    "sg:address":"8 Seaview Road",
    "sg:city":"Wallasey",
    "sg:classifiers":[
        {
            "category":"Shopping",
            "subcategory":"Clothing, Apparel, & Fashions",
            "type":"Retail Goods"
        }
    ],
    "sg:phone":"+44 151 638 5767",
    "sg:postcode":"CH45 4LA",
    "sg:province":"Merseyside",
    "sg:tags":[
        "menswear"
    ],
    "wof:name":"Showman Ltd.",
    "wof:placetype":"venue"
},
  "geometry": {"coordinates":[-3.0454890728,53.4206008911],"type":"Point"}
}