{
  "type": "Feature",
  "properties": {
    "iso:country":"GB",
    "sg:address":"10 Lewis Rd",
    "sg:city":"Gravesend",
    "sg:classifiers":[
        {
            "category":"Government",
            "subcategory":"Post Office",
            "type":"Public Place"
        }
    ],
    "sg:phone":"+44 1474 834013",
    "sg:postcode":"DA13 9JG",
    "sg:province":"Kent",
    "wof:name":"Istead Rise Post Office",
    "wof:placetype":"venue"
},
  "geometry": {"coordinates":[0.350847,51.405117],"type":"Point"}
}