{
  "type": "Feature",
  "properties": {
    "addr:full":"Ashley House, Siemens Road Stafford Staffordshire ST17 4DT",
    "addr:postcode":"st17 4dt",
    "addr:street":"Siemens Road",
    "iso:country":"GB",
    "sg:address":"Ashley House, Siemens Road",
    "sg:city":"Stafford",
    "sg:classifiers":[
        {
            "category":"Professional",
            "subcategory":"Credit Reporting & Collection",
            "type":"Services"
        }
    ],
    "sg:postcode":"ST17 4DT",
    "sg:province":"Staffordshire",
    "sg:tags":[
        "bailiff"
    ],
    "wof:name":"Jefferies & Pennicott (Northern) Ltd.",
    "wof:placetype":"venue"
},
  "geometry": {"coordinates":[-2.1140639782,52.7974433899],"type":"Point"}
}