{
  "type": "Feature",
  "properties": {
    "iso:country":"GB",
    "sg:address":"East St North, Addington",
    "sg:city":"West Malling",
    "sg:classifiers":[
        {
            "category":"Sports & Exercise",
            "subcategory":"Tennis Court",
            "type":"Entertainment"
        }
    ],
    "sg:phone":"+44 1732 872275",
    "sg:postcode":"ME19 5DH",
    "sg:province":"Kent",
    "sg:tags":[
        "breakdown",
        "recovery"
    ],
    "wof:name":"Addington Recovery",
    "wof:placetype":"venue"
},
  "geometry": {"coordinates":[0.37986,51.306664],"type":"Point"}
}