{
  "type": "Feature",
  "properties": {
    "iso:country":"GB",
    "sg:address":", Llansilin",
    "sg:city":"Oswestry",
    "sg:classifiers":[
        {
            "category":"Bars & Pubs",
            "type":"Food & Drink"
        }
    ],
    "sg:phone":"+44 1691 791355",
    "sg:postcode":"SY10 7QB",
    "sg:province":"Shropshire",
    "sg:tags":[
        "pubs",
        "inn"
    ],
    "wof:name":"Wynnstay Inn",
    "wof:placetype":"venue"
},
  "geometry": {"coordinates":[-3.1755321026,52.8463363647],"type":"Point"}
}