{
  "type": "Feature",
  "properties": {
    "iso:country":"GB",
    "sg:address":"53 Cockpit Hill, Brompton",
    "sg:city":"Pickering",
    "sg:classifiers":[
        {
            "category":"Shopping",
            "subcategory":"Books",
            "type":"Retail Goods"
        }
    ],
    "sg:postcode":"DL6 2RQ",
    "sg:province":"North Yorkshire",
    "wof:name":"Whitehill Publishing",
    "wof:placetype":"venue"
},
  "geometry": {"coordinates":[-1.4216400385,54.362411499],"type":"Point"}
}