{
  "type": "Feature",
  "properties": {
    "addr:full":"180 Peelhouse Lane Widnes Cheshire WA8 9UJ",
    "addr:housenumber":"180",
    "addr:postcode":"wa8 9uj",
    "addr:street":"Peelhouse Lane",
    "iso:country":"GB",
    "sg:address":"180 Peelhouse Lane",
    "sg:city":"Widnes",
    "sg:classifiers":[
        {
            "category":"Organizations",
            "subcategory":"Membership Organization",
            "type":"Services"
        }
    ],
    "sg:phone":"+44 151 424 2213",
    "sg:postcode":"WA8 9UJ",
    "sg:province":"Cheshire",
    "sg:tags":[
        "club"
    ],
    "wof:name":"Farnworth Sports & Social Club",
    "wof:placetype":"venue"
},
  "geometry": {"coordinates":[-2.725128,53.380116],"type":"Point"}
}