{
  "type": "Feature",
  "properties": {
    "iso:country":"GB",
    "sg:address":"50 Binscombe Crescent, Binscombe",
    "sg:city":"Godalming",
    "sg:classifiers":[
        {
            "category":"Wholesale",
            "subcategory":"Office Equipment",
            "type":"Manufacturing & Wholesale Goods"
        },
        {
            "category":"Shopping",
            "subcategory":"Stationery & Office Supplies",
            "type":"Retail Goods"
        }
    ],
    "sg:phone":"+44 1483 419990",
    "sg:postcode":"GU7 3RB",
    "sg:province":"Surrey",
    "sg:tags":[
        "supplier",
        "furniture"
    ],
    "sg:website":"http://www.sitsmart.co.uk",
    "wof:name":"Sitsmart Ltd",
    "wof:placetype":"venue"
},
  "geometry": {"coordinates":[-0.612156,51.200138],"type":"Point"}
}