{
  "type": "Feature",
  "properties": {
    "addr:full":"53 Artesian Road London Greater London W2 5DB",
    "addr:housenumber":"53",
    "addr:postcode":"w2 5db",
    "addr:street":"Artesian Road",
    "iso:country":"GB",
    "sg:address":"53 Artesian Road",
    "sg:city":"London",
    "sg:classifiers":[
        {
            "category":"Real Estate",
            "subcategory":"Architect",
            "type":"Services"
        }
    ],
    "sg:phone":"+44 20 7221 0452",
    "sg:postcode":"W2 5DB",
    "sg:province":"Greater London",
    "wof:name":"Antony Lyons Architects",
    "wof:placetype":"venue"
},
  "geometry": {"coordinates":[-0.1981599927,51.515411377],"type":"Point"}
}