{
  "type": "Feature",
  "properties": {
    "iso:country":"GB",
    "sg:address":"Scotsburn Rd",
    "sg:city":"Tain",
    "sg:classifiers":[
        {
            "category":"Bus Charters",
            "type":"Transportation"
        }
    ],
    "sg:phone":"+44 1862 892683",
    "sg:postcode":"IV19 1PP",
    "sg:province":"Highland",
    "sg:tags":[
        "hire",
        "coach"
    ],
    "wof:name":"Inverness Traction",
    "wof:placetype":"venue"
},
  "geometry": {"coordinates":[-4.053245,57.811359],"type":"Point"}
}