{
  "type": "Feature",
  "properties": {
    "iso:country":"GB",
    "sg:address":"94 Warwick Street",
    "sg:city":"Leamington Spa",
    "sg:classifiers":[
        {
            "category":"Shopping",
            "subcategory":"News",
            "type":"Retail Goods"
        }
    ],
    "sg:phone":"+44 1926 833477",
    "sg:postcode":"CV32 4QG",
    "sg:province":"Warwickshire",
    "sg:tags":[
        "newsagent"
    ],
    "wof:name":"News Plus",
    "wof:placetype":"venue"
},
  "geometry": {"coordinates":[-1.5339889526,52.2919464111],"type":"Point"}
}