{
  "type": "Feature",
  "properties": {
    "iso:country":"GB",
    "sg:address":"Hyslop Street, Kelloholm",
    "sg:city":"Sanquhar",
    "sg:classifiers":[
        {
            "category":"Education",
            "subcategory":"School",
            "type":"Public Place"
        }
    ],
    "sg:phone":"+44 1659 67228",
    "sg:postcode":"DG4 6QJ",
    "sg:province":"Dumfries and Galloway",
    "sg:tags":[
        "local",
        "authority"
    ],
    "wof:name":"Kelloholm Primary School",
    "wof:placetype":"venue"
},
  "geometry": {"coordinates":[-3.920284,55.366493],"type":"Point"}
}