{
  "type": "Feature",
  "properties": {
    "addr:full":"Brook House Leominster Herefordshire HR6 0BB",
    "addr:postcode":"hr6 0bb",
    "addr:street":"Herefordshire",
    "iso:country":"GB",
    "sg:address":"Brook House",
    "sg:city":"Leominster",
    "sg:classifiers":[
        {
            "category":"Farming",
            "subcategory":"Livestock Farm",
            "type":"Manufacturing & Wholesale Goods"
        }
    ],
    "sg:phone":"+44 1568 780269",
    "sg:postcode":"HR6 0BB",
    "sg:province":"Herefordshire",
    "sg:tags":[
        "others"
    ],
    "wof:name":"Albert J S Niblett",
    "wof:placetype":"venue"
},
  "geometry": {"coordinates":[-2.7123188972,52.2772293091],"type":"Point"}
}