{
  "type": "Feature",
  "properties": {
    "addr:full":"49 Florence Street Newcastle Staffordshire ST5 2BH",
    "addr:housenumber":"49",
    "addr:postcode":"st5 2bh",
    "addr:street":"Florence Street",
    "iso:country":"GB",
    "sg:address":"49 Florence Street",
    "sg:city":"Newcastle",
    "sg:classifiers":[
        {
            "category":"Utilities",
            "subcategory":"Refuse",
            "type":"Services"
        }
    ],
    "sg:phone":"+44 1782 620592",
    "sg:postcode":"ST5 2BH",
    "sg:province":"Staffordshire",
    "sg:tags":[
        "disposal",
        "waste"
    ],
    "wof:name":"Owen Griffiths",
    "wof:placetype":"venue"
},
  "geometry": {"coordinates":[-2.2258059978,53.0146331787],"type":"Point"}
}