{
  "type": "Feature",
  "properties": {
    "iso:country":"GB",
    "sg:address":"8 Mill Lane, Padworth",
    "sg:city":"Reading",
    "sg:classifiers":[
        {
            "category":"Recreation",
            "type":"Entertainment"
        }
    ],
    "sg:phone":"+44 118 971 2781",
    "sg:postcode":"RG7 4JU",
    "sg:province":"Berkshire",
    "sg:tags":[
        "corporate",
        "leisure"
    ],
    "wof:name":"J.C Wildlife Hawk Talks",
    "wof:placetype":"venue"
},
  "geometry": {"coordinates":[-1.130311,51.396549],"type":"Point"}
}