{
  "type": "Feature",
  "properties": {
    "addr:full":"855a St Asaph Road, Caerwys Mold Denbighshire CH7 5BL",
    "addr:housenumber":"855a",
    "addr:postcode":"ch7 5bl",
    "addr:street":"St Asaph Road",
    "iso:country":"GB",
    "sg:address":"855a St Asaph Road, Caerwys",
    "sg:city":"Mold",
    "sg:classifiers":[
        {
            "category":"Home & Garden",
            "subcategory":"Garden Supply",
            "type":"Retail Goods"
        }
    ],
    "sg:phone":"+44 1352 720840",
    "sg:postcode":"CH7 5BL",
    "sg:province":"Denbighshire",
    "sg:tags":[
        "nursery",
        "centre"
    ],
    "wof:name":"L Brimble & Son",
    "wof:placetype":"venue"
},
  "geometry": {"coordinates":[-3.307498,53.246712],"type":"Point"}
}