{
  "type": "Feature",
  "properties": {
    "addr:full":"194 Lower Addiscombe Road Croydon Surrey CR0 7AA",
    "addr:housenumber":"194",
    "addr:postcode":"cr0 7aa",
    "addr:street":"Lower Addiscombe Road",
    "iso:country":"GB",
    "sg:address":"194 Lower Addiscombe Road",
    "sg:city":"Croydon",
    "sg:classifiers":[
        {
            "category":"Professional",
            "subcategory":"Lawyer & Legal Services",
            "type":"Services"
        }
    ],
    "sg:phone":"+44 20 8656 7116",
    "sg:postcode":"CR0 7AA",
    "sg:province":"Surrey",
    "sg:tags":[
        "conveyancing"
    ],
    "wof:name":"Redshaws",
    "wof:placetype":"venue"
},
  "geometry": {"coordinates":[-0.0653190017,51.383518219],"type":"Point"}
}