{
  "type": "Feature",
  "properties": {
    "iso:country":"GB",
    "sg:address":"2-6 Stockton Rd",
    "sg:city":"Hartlepool",
    "sg:classifiers":[
        {
            "category":"Bars & Pubs",
            "type":"Food & Drink"
        }
    ],
    "sg:phone":"+44 1429 221733",
    "sg:postcode":"TS24 7NU",
    "sg:province":"Durham",
    "sg:tags":[
        "pubs",
        "inn"
    ],
    "wof:name":"Venue The",
    "wof:placetype":"venue"
},
  "geometry": {"coordinates":[-1.210099,54.684471],"type":"Point"}
}