{
  "type": "Feature",
  "properties": {
    "iso:country":"GB",
    "sg:address":"19 Van Alloys Business Park, Stoke Row",
    "sg:city":"Henley-on-thames",
    "sg:classifiers":[
        {
            "category":"Autos & Motor Vehicles",
            "subcategory":"Automobile Sales",
            "type":"Retail Goods"
        }
    ],
    "sg:phone":"+44 1491 680911",
    "sg:postcode":"RG9 5QW",
    "sg:province":"Berkshire",
    "sg:tags":[
        "car"
    ],
    "wof:name":"Michael Ticehurst Specialist Cars",
    "wof:placetype":"venue"
},
  "geometry": {"coordinates":[-1.015119,51.55069],"type":"Point"}
}