{
  "type": "Feature",
  "properties": {
    "addr:full":"Farholme Mill, Farholme Lane Bacup Lancashire OL13 0EZ",
    "addr:postcode":"ol13 0ez",
    "addr:street":"Farholme Lane",
    "iso:country":"GB",
    "sg:address":"Farholme Mill, Farholme Lane",
    "sg:city":"Bacup",
    "sg:classifiers":[
        {
            "category":"Building & Trades",
            "subcategory":"Construction",
            "type":"Services"
        }
    ],
    "sg:phone":"+44 1706 879769",
    "sg:postcode":"OL13 0EZ",
    "sg:province":"Lancashire",
    "sg:tags":[
        "fork",
        "lift",
        "truck"
    ],
    "wof:name":"J & J Forktrucks",
    "wof:placetype":"venue"
},
  "geometry": {"coordinates":[-2.216749,53.692104],"type":"Point"}
}