{
  "type": "Feature",
  "properties": {
    "iso:country":"GB",
    "sg:address":"115 Madden Av",
    "sg:city":"Chatham",
    "sg:classifiers":[
        {
            "category":"Retail",
            "subcategory":"Driving School",
            "type":"Services"
        }
    ],
    "sg:phone":"+44 1634 305233",
    "sg:postcode":"ME5 9TQ",
    "sg:province":"Kent",
    "wof:name":"Drivewise School Of Motoring",
    "wof:placetype":"venue"
},
  "geometry": {"coordinates":[0.512618,51.349194],"type":"Point"}
}