{
  "type": "Feature",
  "properties": {
    "iso:country":"GB",
    "sg:address":"Old Glamis Road",
    "sg:city":"Dundee",
    "sg:classifiers":[
        {
            "category":"Community Center",
            "type":"Public Place"
        }
    ],
    "sg:phone":"+44 1382 432870",
    "sg:postcode":"DD3 0NR",
    "sg:province":"Dundee City",
    "sg:tags":[
        "recreation",
        "leisure",
        "centre"
    ],
    "wof:name":"Dick McTaggart Sports Centre",
    "wof:placetype":"venue"
},
  "geometry": {"coordinates":[-2.972552,56.490189],"type":"Point"}
}