{
  "type": "Feature",
  "properties": {
    "addr:full":"89 Mitcham Lane London Greater London SW16 6LY",
    "addr:housenumber":"89",
    "addr:postcode":"sw16 6ly",
    "addr:street":"Mitcham Lane",
    "iso:country":"GB",
    "sg:address":"89 Mitcham Lane",
    "sg:city":"London",
    "sg:classifiers":[
        {
            "category":"Personal",
            "subcategory":"Beauty Salon",
            "type":"Services"
        }
    ],
    "sg:phone":"+44 20 8769 3155",
    "sg:postcode":"SW16 6LY",
    "sg:province":"Greater London",
    "sg:tags":[
        "unisex",
        "hairdresser"
    ],
    "wof:name":"Afro Essentials",
    "wof:placetype":"venue"
},
  "geometry": {"coordinates":[-0.140645,51.424728],"type":"Point"}
}