{
  "type": "Feature",
  "properties": {
    "iso:country":"GB",
    "sg:address":"7 Dover Ho, Providence Clo",
    "sg:city":"Walsall",
    "sg:classifiers":[
        {
            "category":"Professional",
            "subcategory":"Secretarial Services",
            "type":"Services"
        }
    ],
    "sg:phone":"+44 1922 406837",
    "sg:postcode":"WS3 2AW",
    "sg:province":"Staffordshire",
    "sg:tags":[
        "processing",
        "word"
    ],
    "wof:name":"Denor Typewriters",
    "wof:placetype":"venue"
},
  "geometry": {"coordinates":[-1.99602,52.60648],"type":"Point"}
}