{
  "type": "Feature",
  "properties": {
    "iso:country":"GB",
    "sg:address":"Roman House, Grant Road",
    "sg:city":"Croydon",
    "sg:classifiers":[
        {
            "category":"Building & Trades",
            "subcategory":"Construction",
            "type":"Services"
        }
    ],
    "sg:phone":"+44 23 8058 0400",
    "sg:postcode":"CR9 6BU",
    "sg:province":"Surrey",
    "sg:tags":[
        "builder",
        "contractor"
    ],
    "wof:name":"Hall & Tawse Western Ltd.",
    "wof:placetype":"venue"
},
  "geometry": {"coordinates":[-0.077039,51.380791],"type":"Point"}
}