{
  "type": "Feature",
  "properties": {
    "addr:full":"29 Lake Road, Denton Manchester Greater Manchester M34 3HD",
    "addr:housenumber":"29",
    "addr:postcode":"m34 3hd",
    "addr:street":"Lake Road",
    "iso:country":"GB",
    "sg:address":"29 Lake Road, Denton",
    "sg:city":"Manchester",
    "sg:classifiers":[
        {
            "category":"Taxi",
            "type":"Transportation"
        },
        {
            "category":"Military Area",
            "subcategory":"Air Force Base",
            "type":"Public Place"
        }
    ],
    "sg:phone":"+44 161 336 3111",
    "sg:postcode":"M34 3HD",
    "sg:province":"Greater Manchester",
    "sg:tags":[
        "mini",
        "hire",
        "private",
        "cab"
    ],
    "wof:name":"Fareways",
    "wof:placetype":"venue"
},
  "geometry": {"coordinates":[-2.1129078865,53.4590568542],"type":"Point"}
}