{
  "type": "Feature",
  "properties": {
    "iso:country":"GB",
    "sg:address":"34 Essex St",
    "sg:city":"Halifax",
    "sg:classifiers":[
        {
            "category":"Home & Garden",
            "subcategory":"Carpets & Floor Coverings",
            "type":"Retail Goods"
        }
    ],
    "sg:phone":"+44 1422 353190",
    "sg:postcode":"HX1 3UE",
    "sg:province":"West Yorkshire",
    "sg:tags":[
        "cleaner",
        "upholstery"
    ],
    "wof:name":"Local Cleaning Services",
    "wof:placetype":"venue"
},
  "geometry": {"coordinates":[-1.88762,53.719086],"type":"Point"}
}