{
  "type": "Feature",
  "properties": {
    "addr:full":"Hart, Leisure Centre, Hitches Lane Fleet Dorset GU13 8HZ",
    "addr:postcode":"gu13 8hz",
    "addr:street":"Hitches Lane",
    "iso:country":"GB",
    "sg:address":"Hart, Leisure Centre, Hitches Lane",
    "sg:city":"Fleet",
    "sg:classifiers":[
        {
            "category":"Community Center",
            "type":"Public Place"
        }
    ],
    "sg:phone":"+44 1252 629030",
    "sg:postcode":"GU13 8HZ",
    "sg:province":"Dorset",
    "sg:tags":[
        "recreation",
        "leisure",
        "centre"
    ],
    "wof:name":"S.L.F Group Ltd",
    "wof:placetype":"venue"
},
  "geometry": {"coordinates":[-0.84235,51.276749],"type":"Point"}
}