{
  "type": "Feature",
  "properties": {
    "addr:full":"Peggotty The Teddy House, 6 St Johns Hill Shrewsbury Shropshire SY1 1JD",
    "addr:housenumber":"6",
    "addr:postcode":"sy1 1jd",
    "addr:street":"St Johns Hill",
    "iso:country":"GB",
    "sg:address":"Peggotty The Teddy House, 6 St Johns Hill",
    "sg:city":"Shrewsbury",
    "sg:classifiers":[
        {
            "category":"Shopping",
            "subcategory":"Hobbies, Toys, & Games",
            "type":"Retail Goods"
        }
    ],
    "sg:phone":"+44 1939 291328",
    "sg:postcode":"SY1 1JD",
    "sg:province":"Shropshire",
    "sg:tags":[
        "collectors'",
        "item"
    ],
    "wof:name":"Peggotty-Specialist Teddy Bears",
    "wof:placetype":"venue"
},
  "geometry": {"coordinates":[-2.756747961,52.7070350647],"type":"Point"}
}