{
  "type": "Feature",
  "properties": {
    "addr:full":"84 Carter Lane Mansfield Nottinghamshire NG18 3DH",
    "addr:housenumber":"84",
    "addr:postcode":"ng18 3dh",
    "addr:street":"Carter Lane",
    "iso:country":"GB",
    "sg:address":"84 Carter Lane",
    "sg:city":"Mansfield",
    "sg:classifiers":[
        {
            "category":"Education",
            "subcategory":"Music School",
            "type":"Public Place"
        }
    ],
    "sg:postcode":"NG18 3DH",
    "sg:province":"Nottinghamshire",
    "sg:tags":[
        "teacher"
    ],
    "wof:name":"D I Buckley",
    "wof:placetype":"venue"
},
  "geometry": {"coordinates":[-1.179847002,53.1411170959],"type":"Point"}
}