{
  "type": "Feature",
  "properties": {
    "addr:full":"51 Leys Avenue Letchworth Hertfordshire SG6 3DN",
    "addr:housenumber":"51",
    "addr:postcode":"sg6 3dn",
    "addr:street":"Leys Avenue Letchworth",
    "iso:country":"GB",
    "sg:address":"51 Leys Avenue",
    "sg:city":"Letchworth",
    "sg:classifiers":[
        {
            "category":"Real Estate",
            "subcategory":"Real Estate Agent",
            "type":"Services"
        }
    ],
    "sg:postcode":"SG6 3DN",
    "sg:province":"Hertfordshire",
    "wof:name":"Crossley & Co",
    "wof:placetype":"venue"
},
  "geometry": {"coordinates":[-0.2254649997,51.9784545898],"type":"Point"}
}