{
  "type": "Feature",
  "properties": {
    "iso:country":"GB",
    "sg:address":"Deer Park Brockhampton, Andoversford",
    "sg:city":"Cheltenham",
    "sg:classifiers":[
        {
            "category":"Building & Trades",
            "subcategory":"Construction",
            "type":"Services"
        }
    ],
    "sg:phone":"+44 1242 821117",
    "sg:postcode":"GL54 5SP",
    "sg:province":"Gloucestershire",
    "sg:tags":[
        "builder"
    ],
    "wof:name":"B & M Babbage & Co. Ltd.",
    "wof:placetype":"venue"
},
  "geometry": {"coordinates":[-1.949689,51.899883],"type":"Point"}
}