{
  "type": "Feature",
  "properties": {
    "addr:full":"11 Clarke Road, Mount Farm, Bletchley Milton Keynes Buckinghamshire MK1 1LG",
    "addr:housenumber":"11",
    "addr:postcode":"mk1 1lg",
    "addr:street":"Clarke Road Mount",
    "iso:country":"GB",
    "sg:address":"11 Clarke Road, Mount Farm, Bletchley",
    "sg:city":"Milton Keynes",
    "sg:classifiers":[
        {
            "category":"Professional",
            "type":"Services"
        }
    ],
    "sg:phone":"+44 1908 631991",
    "sg:postcode":"MK1 1LG",
    "sg:province":"Buckinghamshire",
    "sg:tags":[
        "shopfitters"
    ],
    "wof:name":"Cjn Concept Ltd.",
    "wof:placetype":"venue"
},
  "geometry": {"coordinates":[-0.7260190248,52.0123939514],"type":"Point"}
}