{
  "type": "Feature",
  "properties": {
    "iso:country":"GB",
    "sg:address":"Old Gorricon Building, Picton Street, Kenfig Hill",
    "sg:city":"Bridgend",
    "sg:classifiers":[
        {
            "category":"Retail",
            "subcategory":"Auto Repair",
            "type":"Services"
        }
    ],
    "sg:postcode":"CF33 6EF",
    "sg:province":"Bridgend",
    "sg:tags":[
        "modification",
        "garage"
    ],
    "wof:name":"Lawsons Garage",
    "wof:placetype":"venue"
},
  "geometry": {"coordinates":[-3.6759090424,51.5333786011],"type":"Point"}
}