{
  "type": "Feature",
  "properties": {
    "addr:full":"53 Purbeck Rd Hornchurch Essex RM11 1LX",
    "addr:housenumber":"53",
    "addr:postcode":"rm11 1lx",
    "addr:street":"Purbeck Rd",
    "iso:country":"GB",
    "sg:address":"53 Purbeck Rd",
    "sg:city":"Hornchurch",
    "sg:classifiers":[
        {
            "category":"Building & Trades",
            "subcategory":"Construction",
            "type":"Services"
        }
    ],
    "sg:phone":"+44 1708 473811",
    "sg:postcode":"RM11 1LX",
    "sg:province":"Essex",
    "sg:tags":[
        "roofing"
    ],
    "wof:name":"Home County Roofing & Construction",
    "wof:placetype":"venue"
},
  "geometry": {"coordinates":[0.1983959973,51.567489624],"type":"Point"}
}