{
  "type": "Feature",
  "properties": {
    "iso:country":"GB",
    "sg:address":"20 Sackville Gardens",
    "sg:city":"Hove",
    "sg:classifiers":[
        {
            "category":"Organizations",
            "subcategory":"Membership Organization",
            "type":"Services"
        }
    ],
    "sg:postcode":"BN3 4GH",
    "sg:province":"East Sussex",
    "sg:tags":[
        "club"
    ],
    "wof:name":"20 Sackville Gardens Hove Ltd",
    "wof:placetype":"venue"
},
  "geometry": {"coordinates":[-0.18578,50.827438],"type":"Point"}
}