{
  "type": "Feature",
  "properties": {
    "addr:full":"1c Calton Avenue London Greater London SE21 7DE",
    "addr:housenumber":"1c",
    "addr:postcode":"se21 7de",
    "addr:street":"Calton Avenue",
    "iso:country":"GB",
    "sg:address":"1c Calton Avenue",
    "sg:city":"London",
    "sg:classifiers":[
        {
            "category":"Real Estate",
            "subcategory":"Real Estate Agent",
            "type":"Services"
        }
    ],
    "sg:postcode":"SE21 7DE",
    "sg:province":"Greater London",
    "wof:name":"Spencer Kennedy Estates Ltd.",
    "wof:placetype":"venue"
},
  "geometry": {"coordinates":[-0.083248,51.453346],"type":"Point"}
}