{
  "type": "Feature",
  "properties": {
    "addr:full":"2 Temple Way, Station Road, Coleshill Birmingham Warwickshire B46 1HH",
    "addr:housenumber":"2",
    "addr:postcode":"b46 1hh",
    "addr:street":"Temple Way Station Road",
    "iso:country":"GB",
    "sg:address":"2 Temple Way, Station Road, Coleshill",
    "sg:city":"Birmingham",
    "sg:classifiers":[
        {
            "category":"Freight",
            "type":"Transportation"
        }
    ],
    "sg:phone":"+44 1675 466055",
    "sg:postcode":"B46 1HH",
    "sg:province":"Warwickshire",
    "sg:tags":[
        "shipping"
    ],
    "wof:name":"Evergreen (Uk)",
    "wof:placetype":"venue"
},
  "geometry": {"coordinates":[-1.7081099749,52.5102882385],"type":"Point"}
}