{
  "type": "Feature",
  "properties": {
    "addr:full":"Penrhiw, Freshwater East Pembroke Pembrokeshire SA71 5LG",
    "addr:postcode":"sa71 5lg",
    "addr:street":"East",
    "iso:country":"GB",
    "sg:address":"Penrhiw, Freshwater East",
    "sg:city":"Pembroke",
    "sg:classifiers":[
        {
            "category":"Professional",
            "subcategory":"Engineering",
            "type":"Services"
        }
    ],
    "sg:postcode":"SA71 5LG",
    "sg:province":"Pembrokeshire",
    "sg:tags":[
        "contractor",
        "electrical",
        "engineer"
    ],
    "wof:name":"E S Electrical Engineeers",
    "wof:placetype":"venue"
},
  "geometry": {"coordinates":[-4.915889,51.674725],"type":"Point"}
}