{
  "type": "Feature",
  "properties": {
    "addr:full":"35 Masons Hill Bromley Kent BR2 9HD",
    "addr:housenumber":"35",
    "addr:postcode":"br2 9hd",
    "addr:street":"Masons Hill",
    "iso:country":"GB",
    "sg:address":"35 Masons Hill",
    "sg:city":"Bromley",
    "sg:classifiers":[
        {
            "category":"Education",
            "subcategory":"Library",
            "type":"Public Place"
        }
    ],
    "sg:phone":"+44 20 8466 7960",
    "sg:postcode":"BR2 9HD",
    "sg:province":"Kent",
    "sg:tags":[
        "reproduction",
        "furniture"
    ],
    "wof:name":"Churchills Furniture",
    "wof:placetype":"venue"
},
  "geometry": {"coordinates":[0.018053,51.398991],"type":"Point"}
}