{
  "type": "Feature",
  "properties": {
    "iso:country":"GB",
    "sg:address":"Christchurch Road",
    "sg:city":"New Milton",
    "sg:classifiers":[
        {
            "category":"Bars & Pubs",
            "type":"Food & Drink"
        }
    ],
    "sg:postcode":"BH25 6QJ",
    "sg:province":"Hampshire",
    "sg:tags":[
        "pubs",
        "inn"
    ],
    "wof:name":"Anthony John Carr",
    "wof:placetype":"venue"
},
  "geometry": {"coordinates":[-1.670812,50.745541],"type":"Point"}
}