{
  "type": "Feature",
  "properties": {
    "addr:full":"50 London Road Leicester Leicestershire LE2 5DH",
    "addr:housenumber":"50",
    "addr:postcode":"le2 5dh",
    "addr:street":"London Road",
    "iso:country":"GB",
    "sg:address":"50 London Road",
    "sg:city":"Leicester",
    "sg:classifiers":[
        {
            "category":"Food & Beverages",
            "subcategory":"Bakery",
            "type":"Retail Goods"
        }
    ],
    "sg:postcode":"LE2 5DH",
    "sg:province":"Leicestershire",
    "sg:tags":[
        "baker"
    ],
    "wof:name":"Gingerbread Cottage",
    "wof:placetype":"venue"
},
  "geometry": {"coordinates":[-1.0777260065,52.597026825],"type":"Point"}
}