{
  "type": "Feature",
  "properties": {
    "addr:full":"38 Hackwood Road, High March Daventry Northamptonshire NN11 4HB",
    "addr:housenumber":"38",
    "addr:postcode":"nn11 4hb",
    "addr:street":"Hackwood Road High",
    "iso:country":"GB",
    "sg:address":"38 Hackwood Road, High March",
    "sg:city":"Daventry",
    "sg:classifiers":[
        {
            "category":"Professional",
            "subcategory":"Engineering",
            "type":"Services"
        }
    ],
    "sg:phone":"+44 1327 300599",
    "sg:postcode":"NN11 4HB",
    "sg:province":"Northamptonshire",
    "sg:tags":[
        "precision",
        "engineer"
    ],
    "wof:name":"B D L Tool & die Co. Ltd.",
    "wof:placetype":"venue"
},
  "geometry": {"coordinates":[-1.1472879648,52.248966217],"type":"Point"}
}