{
  "type": "Feature",
  "properties": {
    "addr:full":"30 St James's Close Salisbury Wiltshire SP1 3FB",
    "addr:housenumber":"30",
    "addr:postcode":"sp1 3fb",
    "addr:street":"St James'S Close",
    "iso:country":"GB",
    "sg:address":"30 St James's Close",
    "sg:city":"Salisbury",
    "sg:classifiers":[
        {
            "category":"Retail",
            "subcategory":"Driving School",
            "type":"Services"
        }
    ],
    "sg:postcode":"SP1 3FB",
    "sg:province":"Wiltshire",
    "wof:name":"Jackie's School of Motoring",
    "wof:placetype":"venue"
},
  "geometry": {"coordinates":[-1.865486,51.078217],"type":"Point"}
}