{
  "type": "Feature",
  "properties": {
    "addr:full":"104 St. Mary St Weymouth Dorset DT4 8NY",
    "addr:housenumber":"104",
    "addr:postcode":"dt4 8ny",
    "addr:street":"St. Mary St",
    "iso:country":"GB",
    "sg:address":"104 St. Mary St",
    "sg:city":"Weymouth",
    "sg:classifiers":[
        {
            "category":"Shopping",
            "subcategory":"Clothing, Apparel, & Fashions",
            "type":"Retail Goods"
        },
        {
            "category":"Shopping",
            "subcategory":"Jewelry",
            "type":"Retail Goods"
        }
    ],
    "sg:phone":"+44 1305 766885",
    "sg:postcode":"DT4 8NY",
    "sg:province":"Dorset",
    "sg:tags":[
        "accessory",
        "gold",
        "silversmith"
    ],
    "wof:name":"Claire's Accessories UK Ltd",
    "wof:placetype":"venue"
},
  "geometry": {"coordinates":[-2.454055,50.611244],"type":"Point"}
}