{
  "type": "Feature",
  "properties": {
    "addr:full":"10 The Grn Doncaster East Riding of Yorkshire DN8 5AR",
    "addr:housenumber":"10",
    "addr:street":"The Grn;Riding",
    "iso:country":"GB",
    "sg:address":"10 The Grn",
    "sg:city":"Doncaster",
    "sg:classifiers":[
        {
            "category":"Food & Beverages",
            "subcategory":"Meat & Fish",
            "type":"Retail Goods"
        }
    ],
    "sg:postcode":"DN8 5AR",
    "sg:province":"East Riding of Yorkshire",
    "sg:tags":[
        "butcher"
    ],
    "wof:name":"S Clarke",
    "wof:placetype":"venue"
},
  "geometry": {"coordinates":[-0.954096,53.602478],"type":"Point"}
}