{
  "type": "Feature",
  "properties": {
    "addr:full":"7 Gabriels Hill Maidstone Kent ME15 6HL",
    "addr:housenumber":"7",
    "addr:postcode":"me15 6hl",
    "addr:street":"Gabriels Hill",
    "iso:country":"GB",
    "sg:address":"7 Gabriels Hill",
    "sg:city":"Maidstone",
    "sg:classifiers":[
        {
            "category":"Real Estate",
            "subcategory":"Real Estate Agent",
            "type":"Services"
        }
    ],
    "sg:phone":"+44 1622 751034",
    "sg:postcode":"ME15 6HL",
    "sg:province":"Kent",
    "wof:name":"Oakley Prior Partnership",
    "wof:placetype":"venue"
},
  "geometry": {"coordinates":[0.5236,51.273479],"type":"Point"}
}