{
  "type": "Feature",
  "properties": {
    "iso:country":"GB",
    "sg:address":"2b Ascroft Road, Aintree",
    "sg:city":"Liverpool",
    "sg:classifiers":[
        {
            "category":"Retail",
            "subcategory":"Driving School",
            "type":"Services"
        }
    ],
    "sg:phone":"+44 151 474 6300",
    "sg:postcode":"L9 0LL",
    "sg:province":"Merseyside",
    "wof:name":"Aintree School of Motoring",
    "wof:placetype":"venue"
},
  "geometry": {"coordinates":[-2.955924,53.472389],"type":"Point"}
}