{
  "type": "Feature",
  "properties": {
    "addr:full":"1 Oxford Road, Waterloo Liverpool Merseyside L22 8QE",
    "addr:housenumber":"1",
    "addr:postcode":"l22 8qe",
    "addr:street":"Oxford Road",
    "iso:country":"GB",
    "sg:address":"1 Oxford Road, Waterloo",
    "sg:city":"Liverpool",
    "sg:classifiers":[
        {
            "category":"Personal",
            "subcategory":"Tanning Parlor",
            "type":"Services"
        }
    ],
    "sg:postcode":"L22 8QE",
    "sg:province":"Merseyside",
    "sg:tags":[
        "sunbeds"
    ],
    "wof:name":"Bronze Age",
    "wof:placetype":"venue"
},
  "geometry": {"coordinates":[-3.030821,53.476124],"type":"Point"}
}