{
  "type": "Feature",
  "properties": {
    "addr:full":"Wednesfield Road Willenhall West Midlands WV13 1AA",
    "addr:postcode":"wv13 1aa",
    "addr:street":"Wednesfield Road",
    "iso:country":"GB",
    "sg:address":"Wednesfield Road",
    "sg:city":"Willenhall",
    "sg:classifiers":[
        {
            "category":"Building & Trades",
            "subcategory":"Construction",
            "type":"Services"
        }
    ],
    "sg:phone":"+44 1902 635514",
    "sg:postcode":"WV13 1AA",
    "sg:province":"West Midlands",
    "sg:tags":[
        "glazier"
    ],
    "wof:name":"D K Double Glazing",
    "wof:placetype":"venue"
},
  "geometry": {"coordinates":[-2.058879,52.591148],"type":"Point"}
}