{
  "type": "Feature",
  "properties": {
    "addr:full":"17 Penybanc Bridgend Bridgend CF31 1TP",
    "addr:housenumber":"17",
    "addr:postcode":"cf31 1tp",
    "addr:street":"Penybanc Bridgend",
    "iso:country":"GB",
    "sg:address":"17 Penybanc",
    "sg:city":"Bridgend",
    "sg:classifiers":[
        {
            "category":"Professional",
            "subcategory":"Engineering",
            "type":"Services"
        }
    ],
    "sg:phone":"+44 1656 645914",
    "sg:postcode":"CF31 1TP",
    "sg:province":"Bridgend",
    "sg:tags":[
        "contractor",
        "electrical",
        "engineer"
    ],
    "wof:name":"G Mackay",
    "wof:placetype":"venue"
},
  "geometry": {"coordinates":[-3.570925,51.506725],"type":"Point"}
}