{
  "type": "Feature",
  "properties": {
    "addr:full":"86 Hilton Drive Aberdeen Aberdeen City AB24 4NL",
    "addr:housenumber":"86",
    "addr:postcode":"ab24 4nl",
    "addr:street":"Hilton Drive",
    "iso:country":"GB",
    "sg:address":"86 Hilton Drive",
    "sg:city":"Aberdeen",
    "sg:classifiers":[
        {
            "category":"Communications",
            "type":"Services"
        }
    ],
    "sg:postcode":"AB24 4NL",
    "sg:province":"Aberdeen City",
    "sg:tags":[
        "audio-visual"
    ],
    "wof:name":"A-Line Sound & Publicity Services",
    "wof:placetype":"venue"
},
  "geometry": {"coordinates":[-2.1284461021,57.1646461487],"type":"Point"}
}