{
  "type": "Feature",
  "properties": {
    "iso:country":"GB",
    "sg:address":"Airfield Industrial Estate, Marcus Road Dunkeswell",
    "sg:city":"Honiton",
    "sg:classifiers":[
        {
            "category":"Utilities",
            "subcategory":"Fuel Oil & Lpg",
            "type":"Services"
        }
    ],
    "sg:phone":"+44 1404 891129",
    "sg:postcode":"EX14 4LL",
    "sg:province":"Devon",
    "sg:tags":[
        "distributor"
    ],
    "wof:name":"Oilsure",
    "wof:placetype":"venue"
},
  "geometry": {"coordinates":[-3.227743,50.861824],"type":"Point"}
}