{
  "type": "Feature",
  "properties": {
    "iso:country":"GB",
    "sg:address":"Clockface Rd",
    "sg:city":"Widnes",
    "sg:classifiers":[
        {
            "category":"Freight",
            "type":"Transportation"
        }
    ],
    "sg:phone":"+44 1744 810009",
    "sg:postcode":"WA8 3XQ",
    "sg:province":"Cheshire",
    "sg:tags":[
        "haulage",
        "road"
    ],
    "wof:name":"Derry Bros",
    "wof:placetype":"venue"
},
  "geometry": {"coordinates":[-2.707716,53.408146],"type":"Point"}
}