{
  "type": "Feature",
  "properties": {
    "addr:full":"277 Rutland Road Sheffield South Yorkshire S3 9PZ",
    "addr:housenumber":"277",
    "addr:postcode":"s3 9pz",
    "addr:street":"Rutland Road",
    "iso:country":"GB",
    "sg:address":"277 Rutland Road",
    "sg:city":"Sheffield",
    "sg:classifiers":[
        {
            "category":"Organizations",
            "subcategory":"Non-profit Organization",
            "type":"Services"
        }
    ],
    "sg:phone":"+44 114 275 7212",
    "sg:postcode":"S3 9PZ",
    "sg:province":"South Yorkshire",
    "sg:tags":[
        "charitable",
        "organisation",
        "voluntary",
        "charity"
    ],
    "wof:name":"SCOOP AID",
    "wof:placetype":"venue"
},
  "geometry": {"coordinates":[-1.469917,53.397755],"type":"Point"}
}