{
  "type": "Feature",
  "properties": {
    "iso:country":"GB",
    "sg:address":"Po Box 15",
    "sg:city":"Rochester",
    "sg:classifiers":[
        {
            "category":"Place Of Worship",
            "type":"Public Place"
        }
    ],
    "sg:phone":"+44 1634 727756",
    "sg:postcode":"ME2 3PS",
    "sg:province":"Kent",
    "wof:name":"The Traditional Anglican Church",
    "wof:placetype":"venue"
},
  "geometry": {"coordinates":[0.48917,51.402439],"type":"Point"}
}