{
  "type": "Feature",
  "properties": {
    "addr:full":"Units 11-13, Telford Rd, Thornton Indstl Est Ellesmere Port Cheshire CH65 5EU",
    "addr:housenumber":"units 11-13",
    "addr:postcode":"ch65 5eu",
    "addr:street":"Telford Rd;Indstl Est",
    "iso:country":"GB",
    "sg:address":"Units 11-13, Telford Rd, Thornton Indstl Est",
    "sg:city":"Ellesmere Port",
    "sg:classifiers":[
        {
            "category":"Building & Trades",
            "subcategory":"Construction",
            "type":"Services"
        }
    ],
    "sg:phone":"+44 151 356 7701",
    "sg:postcode":"CH65 5EU",
    "sg:province":"Cheshire",
    "sg:tags":[
        "pipework",
        "contractor"
    ],
    "wof:name":"Key - Tech Fluid Power Ltd",
    "wof:placetype":"venue"
},
  "geometry": {"coordinates":[-2.9055740833,53.2771987915],"type":"Point"}
}