{
  "type": "Feature",
  "properties": {
    "addr:full":"65 Milngavie Rd, Bearsden Glasgow East Dunbartonshire G61 2DW",
    "addr:housenumber":"65",
    "addr:postcode":"g61 2dw",
    "addr:street":"Milngavie Rd",
    "iso:country":"GB",
    "sg:address":"65 Milngavie Rd, Bearsden",
    "sg:city":"Glasgow",
    "sg:classifiers":[
        {
            "category":"Professional",
            "subcategory":"Art Services",
            "type":"Services"
        }
    ],
    "sg:postcode":"G61 2DW",
    "sg:province":"East Dunbartonshire",
    "sg:tags":[
        "photographer"
    ],
    "wof:name":"Fox,Granville,",
    "wof:placetype":"venue"
},
  "geometry": {"coordinates":[-4.321578,55.915565],"type":"Point"}
}