{
  "type": "Feature",
  "properties": {
    "iso:country":"GB",
    "sg:address":"7 High St, Weaverham",
    "sg:city":"Northwich",
    "sg:classifiers":[
        {
            "category":"Banks & Credit Unions",
            "subcategory":"Financial Services",
            "type":"Services"
        }
    ],
    "sg:postcode":"CW8 3EX",
    "sg:province":"Cheshire",
    "sg:tags":[
        "building",
        "society"
    ],
    "wof:name":"Cheshire Building Society",
    "wof:placetype":"venue"
},
  "geometry": {"coordinates":[-2.580843,53.262817],"type":"Point"}
}