{
  "type": "Feature",
  "properties": {
    "iso:country":"GB",
    "sg:address":"Exchange House, The Old Telephone Exhange, Main St",
    "sg:city":"Warrington",
    "sg:classifiers":[
        {
            "category":"Building & Trades",
            "subcategory":"Construction",
            "type":"Services"
        }
    ],
    "sg:phone":"+44 1928 734233",
    "sg:postcode":"WA6 7DF",
    "sg:province":"Cheshire",
    "sg:tags":[
        "management"
    ],
    "wof:name":"Project Management Services",
    "wof:placetype":"venue"
},
  "geometry": {"coordinates":[-2.7288,53.294621],"type":"Point"}
}