{
  "type": "Feature",
  "properties": {
    "addr:full":"25-27 Victoria Street, Old Cwmbran Cwmbran Monmouthshire NP44 3JN",
    "addr:housenumber":"25-27",
    "addr:postcode":"np44 3jn",
    "addr:street":"Victoria Street",
    "iso:country":"GB",
    "sg:address":"25-27 Victoria Street, Old Cwmbran",
    "sg:city":"Cwmbran",
    "sg:classifiers":[
        {
            "category":"Restaurant",
            "type":"Food & Drink"
        }
    ],
    "sg:phone":"+44 1633 874272",
    "sg:postcode":"NP44 3JN",
    "sg:province":"Monmouthshire",
    "sg:tags":[
        "indian"
    ],
    "wof:name":"Nawab Tandoori Restaurant",
    "wof:placetype":"venue"
},
  "geometry": {"coordinates":[-3.022047,51.647137],"type":"Point"}
}