{
  "type": "Feature",
  "properties": {
    "iso:country":"GB",
    "sg:address":"Churchtown, Mullion",
    "sg:city":"Helston",
    "sg:classifiers":[
        {
            "category":"Bars & Pubs",
            "type":"Food & Drink"
        }
    ],
    "sg:phone":"+44 1326 240240",
    "sg:postcode":"TR12 7HN",
    "sg:province":"Cornwall",
    "sg:tags":[
        "pubs",
        "inn"
    ],
    "wof:name":"The Old Inn",
    "wof:placetype":"venue"
},
  "geometry": {"coordinates":[-5.246712,50.023834],"type":"Point"}
}