{
  "type": "Feature",
  "properties": {
    "addr:full":"Regal Buildings, Market St Eastleigh Hampshire SO50 5RL",
    "addr:postcode":"so50 5rl",
    "addr:street":"Market St",
    "iso:country":"GB",
    "sg:address":"Regal Buildings, Market St",
    "sg:city":"Eastleigh",
    "sg:classifiers":[
        {
            "category":"Bars & Pubs",
            "subcategory":"Nightclub",
            "type":"Food & Drink"
        }
    ],
    "sg:phone":"+44 23 8064 2207",
    "sg:postcode":"SO50 5RL",
    "sg:province":"Hampshire",
    "sg:tags":[
        "club",
        "night"
    ],
    "wof:name":"Martines Nightclub",
    "wof:placetype":"venue"
},
  "geometry": {"coordinates":[-1.3505929708,50.9683227539],"type":"Point"}
}