{
  "type": "Feature",
  "properties": {
    "addr:full":"26 Tennyson Road, Woodley Reading Berkshire RG5 3RH",
    "addr:housenumber":"26",
    "addr:postcode":"rg5 3rh",
    "addr:street":"Tennyson Road",
    "iso:country":"GB",
    "sg:address":"26 Tennyson Road, Woodley",
    "sg:city":"Reading",
    "sg:classifiers":[
        {
            "category":"Building & Trades",
            "subcategory":"Landscaping Services",
            "type":"Services"
        }
    ],
    "sg:phone":"+44 118 969 1342",
    "sg:postcode":"RG5 3RH",
    "sg:province":"Berkshire",
    "sg:tags":[
        "landscape",
        "contractor"
    ],
    "wof:name":"Fairwater Landscape & Construction",
    "wof:placetype":"venue"
},
  "geometry": {"coordinates":[-0.906967,51.441185],"type":"Point"}
}