{
  "type": "Feature",
  "properties": {
    "iso:country":"GB",
    "sg:address":"4 Hillside Road",
    "sg:city":"Aldershot",
    "sg:classifiers":[
        {
            "category":"Professional",
            "subcategory":"Advertising",
            "type":"Services"
        }
    ],
    "sg:phone":"+44 1252 660000",
    "sg:postcode":"GU11 3NB",
    "sg:province":"Hampshire",
    "sg:tags":[
        "agency"
    ],
    "wof:name":"Simon Caddy",
    "wof:placetype":"venue"
},
  "geometry": {"coordinates":[-0.7670180202,51.240524292],"type":"Point"}
}