{
  "type": "Feature",
  "properties": {
    "addr:full":"31 Market Street Ely Cambridgeshire CB7 5LQ",
    "addr:housenumber":"31",
    "addr:postcode":"cb7 5lq",
    "addr:street":"Market Street",
    "iso:country":"GB",
    "sg:address":"31 Market Street",
    "sg:city":"Ely",
    "sg:classifiers":[
        {
            "category":"Banks & Credit Unions",
            "subcategory":"Financial Services",
            "type":"Services"
        }
    ],
    "sg:postcode":"CB7 5LQ",
    "sg:province":"Cambridgeshire",
    "sg:tags":[
        "adviser"
    ],
    "wof:name":"Roberts & Davis Trustees Ltd.",
    "wof:placetype":"venue"
},
  "geometry": {"coordinates":[0.383013,52.308651],"type":"Point"}
}