{
  "type": "Feature",
  "properties": {
    "iso:country":"GB",
    "sg:address":"23 Church Street",
    "sg:city":"Oswestry",
    "sg:classifiers":[
        {
            "category":"Food & Beverages",
            "subcategory":"Liquor & Beverages",
            "type":"Retail Goods"
        }
    ],
    "sg:phone":"+44 1691 657582",
    "sg:postcode":"SY11 2SP",
    "sg:province":"Shropshire",
    "sg:tags":[
        "beer",
        "spirit",
        "wines"
    ],
    "wof:name":"Thresher Wine Merchants",
    "wof:placetype":"venue"
},
  "geometry": {"coordinates":[-3.0559060574,52.8585166931],"type":"Point"}
}