{
  "type": "Feature",
  "properties": {
    "addr:full":"Fieldhouse, Awre Newnham Gloucestershire GL14 1EH",
    "addr:postcode":"gl14 1eh",
    "addr:street":"Awre",
    "iso:country":"GB",
    "sg:address":"Fieldhouse, Awre",
    "sg:city":"Newnham",
    "sg:classifiers":[
        {
            "category":"Shopping",
            "subcategory":"Antiques",
            "type":"Retail Goods"
        }
    ],
    "sg:postcode":"GL14 1EH",
    "sg:province":"Gloucestershire",
    "wof:name":"Alison McDermott",
    "wof:placetype":"venue"
},
  "geometry": {"coordinates":[-2.449804,51.803883],"type":"Point"}
}