{
  "type": "Feature",
  "properties": {
    "iso:country":"GB",
    "sg:address":"Praze Forge, School Road, Praze",
    "sg:city":"Camborne",
    "sg:classifiers":[
        {
            "category":"Home & Garden",
            "subcategory":"Building Materials",
            "type":"Retail Goods"
        }
    ],
    "sg:postcode":"TR14 0LB",
    "sg:province":"Cornwall",
    "sg:tags":[
        "ironwork",
        "diy",
        "wrought"
    ],
    "wof:name":"Jay's Gates",
    "wof:placetype":"venue"
},
  "geometry": {"coordinates":[-5.3119921684,50.1745986938],"type":"Point"}
}