{
  "type": "Feature",
  "properties": {
    "addr:full":"6 Roundham Road Paignton Devon TQ4 6EZ",
    "addr:housenumber":"6",
    "addr:postcode":"tq4 6ez",
    "addr:street":"Roundham Road",
    "iso:country":"GB",
    "sg:address":"6 Roundham Road",
    "sg:city":"Paignton",
    "sg:classifiers":[
        {
            "category":"Travel",
            "subcategory":"Hotels & Motels",
            "type":"Entertainment"
        }
    ],
    "sg:phone":"+44 1803 558372",
    "sg:postcode":"TQ4 6EZ",
    "sg:province":"Devon",
    "wof:name":"Amber House Hotel",
    "wof:placetype":"venue"
},
  "geometry": {"coordinates":[-3.5632419586,50.4289512634],"type":"Point"}
}