{
  "type": "Feature",
  "properties": {
    "addr:full":"70 The Mall, The Stratford Centre Stratford Greater London E15 1XQ",
    "addr:housenumber":"70",
    "addr:postcode":"e15 1xq",
    "addr:street":"The Mall The",
    "iso:country":"GB",
    "sg:address":"70 The Mall, The Stratford Centre",
    "sg:city":"Stratford",
    "sg:classifiers":[
        {
            "category":"Home & Garden",
            "subcategory":"Carpets & Floor Coverings",
            "type":"Retail Goods"
        }
    ],
    "sg:phone":"+44 20 8221 1721",
    "sg:postcode":"E15 1XQ",
    "sg:province":"Greater London",
    "sg:tags":[
        "carpets",
        "rug",
        "matting"
    ],
    "wof:name":"Crown Carpets",
    "wof:placetype":"venue"
},
  "geometry": {"coordinates":[0.00062,51.541458],"type":"Point"}
}