{
  "type": "Feature",
  "properties": {
    "addr:full":"14 Chesterfield Road, Chiswick London Greater London W4 3HG",
    "addr:housenumber":"14",
    "addr:postcode":"w4 3hg",
    "addr:street":"Chesterfield Road",
    "iso:country":"GB",
    "sg:address":"14 Chesterfield Road, Chiswick",
    "sg:city":"London",
    "sg:classifiers":[
        {
            "category":"Building & Trades",
            "subcategory":"Construction",
            "type":"Services"
        }
    ],
    "sg:phone":"+44 20 8900 0062",
    "sg:postcode":"W4 3HG",
    "sg:province":"Greater London",
    "sg:tags":[
        "contractor",
        "paving",
        "driveway"
    ],
    "wof:name":"M O'Rourke",
    "wof:placetype":"venue"
},
  "geometry": {"coordinates":[-0.2655200064,51.4858016968],"type":"Point"}
}