{
  "type": "Feature",
  "properties": {
    "addr:full":"Unit 1 Stubbins Lane, Claughton On Brook Preston Lancashire PR3 0QH",
    "addr:housenumber":"unit 1",
    "addr:postcode":"pr3 0qh",
    "addr:street":"Stubbins Lane",
    "iso:country":"GB",
    "sg:address":"Unit 1 Stubbins Lane, Claughton On Brook",
    "sg:city":"Preston",
    "sg:classifiers":[
        {
            "category":"Home & Garden",
            "subcategory":"Hardware",
            "type":"Retail Goods"
        }
    ],
    "sg:postcode":"PR3 0QH",
    "sg:province":"Lancashire",
    "sg:tags":[
        "equipment",
        "welding"
    ],
    "wof:name":"Y P H Welding Supplies",
    "wof:placetype":"venue"
},
  "geometry": {"coordinates":[-2.75772,53.876938],"type":"Point"}
}