{
  "type": "Feature",
  "properties": {
    "addr:full":"Fowler Road Aylesbury Buckinghamshire HP19 7QP",
    "addr:postcode":"hp19 7qp",
    "addr:street":"Fowler Road",
    "iso:country":"GB",
    "sg:address":"Fowler Road",
    "sg:city":"Aylesbury",
    "sg:classifiers":[
        {
            "category":"Education",
            "subcategory":"School",
            "type":"Public Place"
        }
    ],
    "sg:phone":"+44 1296 488331",
    "sg:postcode":"HP19 7QP",
    "sg:province":"Buckinghamshire",
    "sg:tags":[
        "local",
        "authority"
    ],
    "wof:name":"Bearbrook County Combined School",
    "wof:placetype":"venue"
},
  "geometry": {"coordinates":[-0.829852,51.816483],"type":"Point"}
}