{
  "type": "Feature",
  "properties": {
    "iso:country":"GB",
    "sg:address":"Shakespeare House, 42 Newmarket Road",
    "sg:city":"Cambridge",
    "sg:classifiers":[
        {
            "category":"Professional",
            "subcategory":"Lawyer & Legal Services",
            "type":"Services"
        }
    ],
    "sg:phone":"+44 1223 461155",
    "sg:postcode":"CB5 8EP",
    "sg:province":"Cambridgeshire",
    "sg:tags":[
        "solicitor"
    ],
    "wof:name":"Hewitson's",
    "wof:placetype":"venue"
},
  "geometry": {"coordinates":[0.1628299952,52.2122497559],"type":"Point"}
}