{
  "type": "Feature",
  "properties": {
    "addr:full":"139 Barton Road, Stretford Manchester Cheshire M32 8DN",
    "addr:housenumber":"139",
    "addr:postcode":"m32 8dn",
    "addr:street":"Barton Road",
    "iso:country":"GB",
    "sg:address":"139 Barton Road, Stretford",
    "sg:city":"Manchester",
    "sg:classifiers":[
        {
            "category":"Professional",
            "subcategory":"Business Services",
            "type":"Services"
        },
        {
            "category":"Casinos & Gambling",
            "type":"Entertainment"
        }
    ],
    "sg:phone":"+44 161 865 7722",
    "sg:postcode":"M32 8DN",
    "sg:province":"Cheshire",
    "sg:tags":[
        "turf",
        "accountant",
        "bookmaker"
    ],
    "wof:name":"Venture Bookmakers",
    "wof:placetype":"venue"
},
  "geometry": {"coordinates":[-2.3141651154,53.4459075928],"type":"Point"}
}