{
  "type": "Feature",
  "properties": {
    "iso:country":"GB",
    "sg:address":"Government Bldg(s), Whitburn Road",
    "sg:city":"Bathgate",
    "sg:classifiers":[
        {
            "category":"Social Services",
            "type":"Services"
        }
    ],
    "sg:phone":"+44 1506 772000",
    "sg:postcode":"EH48 1HG",
    "sg:province":"West Lothian",
    "sg:tags":[
        "benefit",
        "agency"
    ],
    "wof:name":"Job Centre Plus",
    "wof:placetype":"venue"
},
  "geometry": {"coordinates":[-3.6416289806,55.9007568359],"type":"Point"}
}