{
  "type": "Feature",
  "properties": {
    "addr:full":"73 Easter Road Edinburgh City of Edinburgh EH7 5PW",
    "addr:housenumber":"73",
    "addr:postcode":"eh7 5pw",
    "addr:street":"Easter Road",
    "iso:country":"GB",
    "sg:address":"73 Easter Road",
    "sg:city":"Edinburgh",
    "sg:classifiers":[
        {
            "category":"Professional",
            "subcategory":"Business Services",
            "type":"Services"
        }
    ],
    "sg:phone":"+44 131 661 3617",
    "sg:postcode":"EH7 5PW",
    "sg:province":"City of Edinburgh",
    "sg:tags":[
        "bookmaker"
    ],
    "wof:name":"G B Racing",
    "wof:placetype":"venue"
},
  "geometry": {"coordinates":[-3.1717729568,55.9598846436],"type":"Point"}
}