{
  "type": "Feature",
  "properties": {
    "addr:full":"2 Halkyn Street Holywell Denbighshire CH8 7TX",
    "addr:housenumber":"2",
    "addr:postcode":"ch8 7tx",
    "addr:street":"Halkyn Street",
    "iso:country":"GB",
    "sg:address":"2 Halkyn Street",
    "sg:city":"Holywell",
    "sg:classifiers":[
        {
            "category":"Retail",
            "subcategory":"Funeral Services",
            "type":"Services"
        }
    ],
    "sg:postcode":"CH8 7TX",
    "sg:province":"Denbighshire",
    "wof:name":"J E Davies & Son",
    "wof:placetype":"venue"
},
  "geometry": {"coordinates":[-3.220089,53.2724],"type":"Point"}
}