{
  "type": "Feature",
  "properties": {
    "addr:full":"13 Park Place Leeds West Yorkshire LS1 2RU",
    "addr:housenumber":"13",
    "addr:postcode":"ls1 2ru",
    "addr:street":"Park Place",
    "iso:country":"GB",
    "sg:address":"13 Park Place",
    "sg:city":"Leeds",
    "sg:classifiers":[
        {
            "category":"Real Estate",
            "subcategory":"Surveying",
            "type":"Services"
        }
    ],
    "sg:phone":"+44 113 243 4411",
    "sg:postcode":"LS1 2RU",
    "sg:province":"West Yorkshire",
    "sg:tags":[
        "surveyor",
        "quantity"
    ],
    "wof:name":"Michael Eyres Partnership",
    "wof:placetype":"venue"
},
  "geometry": {"coordinates":[-1.552467,53.797852],"type":"Point"}
}