{
  "type": "Feature",
  "properties": {
    "iso:country":"GB",
    "sg:address":"240 Yeading Lane",
    "sg:city":"Hayes",
    "sg:classifiers":[
        {
            "category":"Personal",
            "subcategory":"Beauty Salon",
            "type":"Services"
        }
    ],
    "sg:phone":"+44 20 8845 6878",
    "sg:postcode":"UB4 9AX",
    "sg:province":"Greater London",
    "sg:tags":[
        "unisex",
        "hairdresser"
    ],
    "wof:name":"Mark Thorpe Salons",
    "wof:placetype":"venue"
},
  "geometry": {"coordinates":[-0.399409,51.526962],"type":"Point"}
}