{
  "type": "Feature",
  "properties": {
    "addr:full":"189 Aragon Road Morden Surrey SM4 4QW",
    "addr:housenumber":"189",
    "addr:postcode":"sm4 4qw",
    "addr:street":"Aragon Road",
    "iso:country":"GB",
    "sg:address":"189 Aragon Road",
    "sg:city":"Morden",
    "sg:classifiers":[
        {
            "category":"Professional",
            "subcategory":"Engineering",
            "type":"Services"
        },
        {
            "category":"Building & Trades",
            "subcategory":"Electrical",
            "type":"Services"
        }
    ],
    "sg:phone":"+44 20 8337 5471",
    "sg:postcode":"SM4 4QW",
    "sg:province":"Surrey",
    "sg:tags":[
        "engineer",
        "electrician",
        "contractor"
    ],
    "wof:name":"J W H ELECTRICS",
    "wof:placetype":"venue"
},
  "geometry": {"coordinates":[-0.219339,51.386112],"type":"Point"}
}