{
  "type": "Feature",
  "properties": {
    "iso:country":"GB",
    "sg:address":"4 Ardmillan Court",
    "sg:city":"Oswestry",
    "sg:classifiers":[
        {
            "category":"Education",
            "subcategory":"University",
            "type":"Public Place"
        }
    ],
    "sg:phone":"+44 1691 654164",
    "sg:postcode":"SY11 2JG",
    "sg:province":"Shropshire",
    "sg:tags":[
        "higher"
    ],
    "wof:name":"A Thomas",
    "wof:placetype":"venue"
},
  "geometry": {"coordinates":[-3.046338,52.860493],"type":"Point"}
}