{
  "type": "Feature",
  "properties": {
    "iso:country":"GB",
    "sg:address":"Sparrow Hall Road",
    "sg:city":"Liverpool",
    "sg:classifiers":[
        {
            "category":"Education",
            "subcategory":"School",
            "type":"Public Place"
        }
    ],
    "sg:postcode":"L9 6BU",
    "sg:province":"Merseyside",
    "sg:tags":[
        "local",
        "authority"
    ],
    "wof:name":"St Philomena's R C Junior School",
    "wof:placetype":"venue"
},
  "geometry": {"coordinates":[-2.922534,53.454784],"type":"Point"}
}