{
  "type": "Feature",
  "properties": {
    "addr:full":"312 Lincoln Road Peterborough Cambridgeshire PE1 2ND",
    "addr:housenumber":"312",
    "addr:postcode":"pe1 2nd",
    "addr:street":"Lincoln Road",
    "iso:country":"GB",
    "sg:address":"312 Lincoln Road",
    "sg:city":"Peterborough",
    "sg:classifiers":[
        {
            "category":"Shopping",
            "subcategory":"Pets & Pet Supplies",
            "type":"Retail Goods"
        }
    ],
    "sg:phone":"+44 1733 703097",
    "sg:postcode":"PE1 2ND",
    "sg:province":"Cambridgeshire",
    "sg:tags":[
        "food",
        "feed",
        "animal"
    ],
    "wof:name":"Animal Crackers",
    "wof:placetype":"venue"
},
  "geometry": {"coordinates":[-0.2481340021,52.5883255005],"type":"Point"}
}