{
  "type": "Feature",
  "properties": {
    "iso:country":"GB",
    "sg:address":"4 Westray Av",
    "sg:city":"Glasgow",
    "sg:classifiers":[
        {
            "category":"Retail",
            "subcategory":"Driving School",
            "type":"Services"
        }
    ],
    "sg:phone":"+44 141 639 7420",
    "sg:postcode":"G77 6JQ",
    "sg:province":"East Ayrshire",
    "wof:name":"Turning Point",
    "wof:placetype":"venue"
},
  "geometry": {"coordinates":[-4.341208,55.784767],"type":"Point"}
}