{
  "type": "Feature",
  "properties": {
    "iso:country":"GB",
    "sg:address":"5 Greenlands Avenue, New Waltham",
    "sg:city":"Grimsby",
    "sg:classifiers":[
        {
            "category":"Fast Food",
            "type":"Food & Drink"
        }
    ],
    "sg:phone":"+44 1472 501113",
    "sg:postcode":"DN36 4YE",
    "sg:province":"Lincolnshire",
    "sg:tags":[
        "away",
        "take"
    ],
    "wof:name":"Torino Pizza Takeway",
    "wof:placetype":"venue"
},
  "geometry": {"coordinates":[-0.060945,53.524883],"type":"Point"}
}