{
  "type": "Feature",
  "properties": {
    "addr:full":"Station Road Wirral Merseyside CH61 0HN",
    "addr:postcode":"ch61 0hn",
    "addr:street":"Station Road",
    "iso:country":"GB",
    "sg:address":"Station Road",
    "sg:city":"Wirral",
    "sg:classifiers":[
        {
            "category":"Manufacturing",
            "subcategory":"Buildings",
            "type":"Manufacturing & Wholesale Goods"
        }
    ],
    "sg:phone":"+44 151 648 5226",
    "sg:postcode":"CH61 0HN",
    "sg:province":"Merseyside",
    "sg:tags":[
        "mobile",
        "home"
    ],
    "wof:name":"Thurstaston Caravan Owners Association",
    "wof:placetype":"venue"
},
  "geometry": {"coordinates":[-3.131708,53.349876],"type":"Point"}
}