{
  "type": "Feature",
  "properties": {
    "addr:full":"7 Midland Rd Stonehouse Gloucestershire GL10 2DQ",
    "addr:housenumber":"7",
    "addr:postcode":"gl10 2dq",
    "addr:street":"Midland Rd",
    "iso:country":"GB",
    "sg:address":"7 Midland Rd",
    "sg:city":"Stonehouse",
    "sg:classifiers":[
        {
            "category":"Education",
            "subcategory":"Music School",
            "type":"Public Place"
        }
    ],
    "sg:phone":"+44 1453 824688",
    "sg:postcode":"GL10 2DQ",
    "sg:province":"Gloucestershire",
    "sg:tags":[
        "conservatory"
    ],
    "wof:name":"Trinity",
    "wof:placetype":"venue"
},
  "geometry": {"coordinates":[-2.288916111,51.7515487671],"type":"Point"}
}