{
  "type": "Feature",
  "properties": {
    "addr:full":"Blenheim St, Tyldesley Manchester Greater Manchester M29 8JL",
    "addr:postcode":"m29 8jl",
    "addr:street":"Blenheim St",
    "iso:country":"GB",
    "sg:address":"Blenheim St, Tyldesley",
    "sg:city":"Manchester",
    "sg:classifiers":[
        {
            "category":"Building & Trades",
            "subcategory":"Construction",
            "type":"Services"
        }
    ],
    "sg:postcode":"M29 8JL",
    "sg:province":"Greater Manchester",
    "sg:tags":[
        "builder"
    ],
    "wof:name":"McDonough,W,",
    "wof:placetype":"venue"
},
  "geometry": {"coordinates":[-2.4761140347,53.5137062073],"type":"Point"}
}