{
  "type": "Feature",
  "properties": {
    "addr:full":"Oakdene Garage, Street End Lane, Broadoaks Heathfield East Sussex TN21 8TU",
    "addr:postcode":"tn21 8tu",
    "addr:street":"Street End Lane",
    "iso:country":"GB",
    "sg:address":"Oakdene Garage, Street End Lane, Broadoaks",
    "sg:city":"Heathfield",
    "sg:classifiers":[
        {
            "category":"Retail",
            "subcategory":"Auto Repair",
            "type":"Services"
        }
    ],
    "sg:phone":"+44 1435 863587",
    "sg:postcode":"TN21 8TU",
    "sg:province":"East Sussex",
    "sg:tags":[
        "modification",
        "garage"
    ],
    "wof:name":"French & Son",
    "wof:placetype":"venue"
},
  "geometry": {"coordinates":[0.252349,50.971859],"type":"Point"}
}