{
  "type": "Feature",
  "properties": {
    "addr:full":"25 Dudley Street Wolverhampton West Midlands WV1 3EY",
    "addr:housenumber":"25",
    "addr:postcode":"wv1 3ey",
    "addr:street":"Dudley Street",
    "iso:country":"GB",
    "sg:address":"25 Dudley Street",
    "sg:city":"Wolverhampton",
    "sg:classifiers":[
        {
            "category":"Sports & Exercise",
            "subcategory":"Sports Center",
            "type":"Entertainment"
        }
    ],
    "sg:phone":"+44 1902 426910",
    "sg:postcode":"WV1 3EY",
    "sg:province":"West Midlands",
    "sg:tags":[
        "shop",
        "good"
    ],
    "wof:name":"Sports Division",
    "wof:placetype":"venue"
},
  "geometry": {"coordinates":[-2.127117,52.584599],"type":"Point"}
}