{
  "type": "Feature",
  "properties": {
    "addr:full":"13 South End Road London Greater London NW3 2PT",
    "addr:housenumber":"13",
    "addr:postcode":"nw3 2pt",
    "addr:street":"South End Road",
    "iso:country":"GB",
    "sg:address":"13 South End Road",
    "sg:city":"London",
    "sg:classifiers":[
        {
            "category":"Shopping",
            "subcategory":"Crafts & Fabrics",
            "type":"Retail Goods"
        }
    ],
    "sg:postcode":"NW3 2PT",
    "sg:province":"Greater London",
    "sg:tags":[
        "material",
        "graphic",
        "art"
    ],
    "wof:name":"F Hegner & Son",
    "wof:placetype":"venue"
},
  "geometry": {"coordinates":[-0.1657859981,51.5543403625],"type":"Point"}
}