{
  "type": "Feature",
  "properties": {
    "addr:full":"1 Glasspool, Denmead Waterlooville Hampshire PO7 6EA",
    "addr:housenumber":"1",
    "addr:postcode":"po7 6ea",
    "addr:street":"Glasspool",
    "iso:country":"GB",
    "sg:address":"1 Glasspool, Denmead",
    "sg:city":"Waterlooville",
    "sg:classifiers":[
        {
            "category":"Manufacturing",
            "subcategory":"Petroleum Products",
            "type":"Manufacturing & Wholesale Goods"
        },
        {
            "category":"Building & Trades",
            "subcategory":"Construction",
            "type":"Services"
        }
    ],
    "sg:phone":"+44 23 9226 9756",
    "sg:postcode":"PO7 6EA",
    "sg:province":"Hampshire",
    "sg:tags":[
        "double",
        "glazing",
        "installers"
    ],
    "wof:name":"R Windows & Doors",
    "wof:placetype":"venue"
},
  "geometry": {"coordinates":[-1.0741989613,50.9051437378],"type":"Point"}
}