{
  "type": "Feature",
  "properties": {
    "addr:full":"Unit 3 Vale St Darwen Lancashire BB3 1LP",
    "addr:housenumber":"unit 3",
    "addr:postcode":"bb3 1lp",
    "addr:street":"Vale St",
    "iso:country":"GB",
    "sg:address":"Unit 3 Vale St",
    "sg:city":"Darwen",
    "sg:classifiers":[
        {
            "category":"Manufacturing",
            "subcategory":"Wood Products",
            "type":"Manufacturing & Wholesale Goods"
        }
    ],
    "sg:phone":"+44 1254 708427",
    "sg:postcode":"BB3 1LP",
    "sg:province":"Lancashire",
    "sg:tags":[
        "packaging",
        "crate",
        "pallets"
    ],
    "wof:name":"Cowell Enterprises Ltd",
    "wof:placetype":"venue"
},
  "geometry": {"coordinates":[-2.472239,53.698921],"type":"Point"}
}