{
  "type": "Feature",
  "properties": {
    "addr:full":"453a New Cross Rd New Cross Greater London SE14 6TA",
    "addr:housenumber":"453a",
    "addr:postcode":"se14 6ta",
    "addr:street":"New Cross Rd New",
    "iso:country":"GB",
    "sg:address":"453a New Cross Rd",
    "sg:city":"New Cross",
    "sg:classifiers":[
        {
            "category":"Health Services",
            "subcategory":"Doctor",
            "type":"Services"
        }
    ],
    "sg:phone":"+44 20 8692 3309",
    "sg:postcode":"SE14 6TA",
    "sg:province":"Greater London",
    "sg:tags":[
        "practitioners"
    ],
    "wof:name":"Patel, N",
    "wof:placetype":"venue"
},
  "geometry": {"coordinates":[-0.029628,51.475647],"type":"Point"}
}