{
  "type": "Feature",
  "properties": {
    "iso:country":"GB",
    "sg:address":"57 Leach Lane",
    "sg:city":"Lytham St. Annes",
    "sg:classifiers":[
        {
            "category":"Retail",
            "subcategory":"Auto Repair",
            "type":"Services"
        }
    ],
    "sg:phone":"+44 1253 714169",
    "sg:postcode":"FY8 3AN",
    "sg:province":"Lancashire",
    "sg:tags":[
        "car",
        "upholsterer"
    ],
    "wof:name":"Andrew Johnson Car Valet",
    "wof:placetype":"venue"
},
  "geometry": {"coordinates":[-3.025773,53.766335],"type":"Point"}
}