{
  "type": "Feature",
  "properties": {
    "iso:country":"GB",
    "sg:address":"Washway Road",
    "sg:city":"Spalding",
    "sg:classifiers":[
        {
            "category":"Bars & Pubs",
            "type":"Food & Drink"
        }
    ],
    "sg:phone":"+44 1406 490339",
    "sg:postcode":"PE12 8AY",
    "sg:province":"Cambridgeshire",
    "sg:tags":[
        "pubs",
        "inn"
    ],
    "wof:name":"The New Saracens Head",
    "wof:placetype":"venue"
},
  "geometry": {"coordinates":[0.00651,52.821667],"type":"Point"}
}