{
  "type": "Feature",
  "properties": {
    "iso:country":"GB",
    "sg:address":"Globe Mills, Hall Lane",
    "sg:city":"Bradford",
    "sg:classifiers":[
        {
            "category":"Manufacturing",
            "subcategory":"Wood Products",
            "type":"Manufacturing & Wholesale Goods"
        }
    ],
    "sg:phone":"+44 1274 741474",
    "sg:postcode":"BD4 7DF",
    "sg:province":"West Yorkshire",
    "sg:tags":[
        "packaging",
        "crate",
        "pallets"
    ],
    "wof:name":"Allsop Gowrie Industrial Fabrics Ltd.",
    "wof:placetype":"venue"
},
  "geometry": {"coordinates":[-1.74422,53.785332],"type":"Point"}
}