{
  "type": "Feature",
  "properties": {
    "iso:country":"GB",
    "sg:address":"Unit C3 Geddings Road",
    "sg:city":"Hoddesdon",
    "sg:classifiers":[
        {
            "category":"Professional",
            "subcategory":"Business Services",
            "type":"Services"
        }
    ],
    "sg:phone":"+44 1992 470146",
    "sg:postcode":"EN11 0NT",
    "sg:province":"Essex",
    "sg:tags":[
        "tile",
        "stockist"
    ],
    "wof:name":"Hoddesdon Tile Centre",
    "wof:placetype":"venue"
},
  "geometry": {"coordinates":[-0.002792,51.760864],"type":"Point"}
}