{
  "type": "Feature",
  "properties": {
    "iso:country":"GB",
    "sg:address":"Weavers Ho, Gardens Rd",
    "sg:city":"Clevedon",
    "sg:classifiers":[
        {
            "category":"Wholesale",
            "subcategory":"Books, Periodicals, & Newspapers",
            "type":"Manufacturing & Wholesale Goods"
        }
    ],
    "sg:phone":"+44 1275 870172",
    "sg:postcode":"BS21 7QQ",
    "sg:province":"Somerset",
    "sg:tags":[
        "publishing"
    ],
    "wof:name":"Property Titles",
    "wof:placetype":"venue"
},
  "geometry": {"coordinates":[-2.855039,51.435925],"type":"Point"}
}