{
  "type": "Feature",
  "properties": {
    "iso:country":"GB",
    "sg:address":"Fennycroft Rd",
    "sg:city":"Hemel Hempstead",
    "sg:classifiers":[
        {
            "category":"Communications",
            "subcategory":"News Services",
            "type":"Services"
        }
    ],
    "sg:phone":"+44 1442 390375",
    "sg:postcode":"HP1 3PD",
    "sg:province":"Hertfordshire",
    "sg:tags":[
        "photo",
        "agency"
    ],
    "wof:name":"Clark Kent Press Agency The",
    "wof:placetype":"venue"
},
  "geometry": {"coordinates":[-0.492025,51.767017],"type":"Point"}
}