{
  "type": "Feature",
  "properties": {
    "addr:full":"Church Road Benfleet Essex SS7 4QW",
    "addr:postcode":"ss7 4qw",
    "addr:street":"Church Road",
    "iso:country":"GB",
    "sg:address":"Church Road",
    "sg:city":"Benfleet",
    "sg:classifiers":[
        {
            "category":"Social Services",
            "subcategory":"Job Training",
            "type":"Services"
        }
    ],
    "sg:phone":"+44 1268 566666",
    "sg:postcode":"SS7 4QW",
    "sg:province":"Essex",
    "sg:tags":[
        "engineering",
        "marine"
    ],
    "wof:name":"International Marine Holdings Ltd.",
    "wof:placetype":"venue"
},
  "geometry": {"coordinates":[0.5610349774,51.5718193054],"type":"Point"}
}