{
  "type": "Feature",
  "properties": {
    "iso:country":"GB",
    "sg:address":"1-3 Paigle Road",
    "sg:city":"Leicester",
    "sg:classifiers":[
        {
            "category":"Building & Trades",
            "subcategory":"Plumbing",
            "type":"Services"
        },
        {
            "category":"Professional",
            "subcategory":"Detective & Security Services",
            "type":"Services"
        }
    ],
    "sg:phone":"+44 116 245 3030",
    "sg:postcode":"LE2 8HP",
    "sg:province":"Leicestershire",
    "sg:tags":[
        "burglar",
        "alarm",
        "system",
        "heating",
        "servicing",
        "central",
        "installation"
    ],
    "wof:name":"WILSON ALARM SYSTEMS LTD",
    "wof:placetype":"venue"
},
  "geometry": {"coordinates":[-1.153367,52.603409],"type":"Point"}
}