{
  "type": "Feature",
  "properties": {
    "addr:full":"36-37 Crown Road Norwich Norfolk NR1 3DT",
    "addr:housenumber":"36-37",
    "addr:postcode":"nr1 3dt",
    "addr:street":"Crown Road Norwich Norfolk",
    "iso:country":"GB",
    "sg:address":"36-37 Crown Road",
    "sg:city":"Norwich",
    "sg:classifiers":[
        {
            "category":"Insurance",
            "subcategory":"Insurance Agent",
            "type":"Services"
        }
    ],
    "sg:phone":"+44 1603 622869",
    "sg:postcode":"NR1 3DT",
    "sg:province":"Norfolk",
    "wof:name":"Britannic Assurance Plc",
    "wof:placetype":"venue"
},
  "geometry": {"coordinates":[1.2990100384,52.6285514832],"type":"Point"}
}