{
  "type": "Feature",
  "properties": {
    "addr:full":"2 Grove Trading Estate Dorchester Dorset DT1 1ST",
    "addr:housenumber":"2",
    "addr:postcode":"dt1 1st",
    "addr:street":"Grove Trading Estate",
    "iso:country":"GB",
    "sg:address":"2 Grove Trading Estate",
    "sg:city":"Dorchester",
    "sg:classifiers":[
        {
            "category":"Professional",
            "type":"Services"
        }
    ],
    "sg:phone":"+44 1305 260851",
    "sg:postcode":"DT1 1ST",
    "sg:province":"Dorset",
    "sg:tags":[
        "exhibition"
    ],
    "wof:name":"Lam-Art",
    "wof:placetype":"venue"
},
  "geometry": {"coordinates":[-2.44588,50.717888],"type":"Point"}
}