{
  "type": "Feature",
  "properties": {
    "addr:full":"163 Mid Street Keith Moray AB55 5BL",
    "addr:housenumber":"163",
    "addr:postcode":"ab55 5bl",
    "addr:street":"Mid Street",
    "iso:country":"GB",
    "sg:address":"163 Mid Street",
    "sg:city":"Keith",
    "sg:classifiers":[
        {
            "category":"Professional",
            "subcategory":"Lawyer & Legal Services",
            "type":"Services"
        }
    ],
    "sg:phone":"+44 1542 886267",
    "sg:postcode":"AB55 5BL",
    "sg:province":"Moray",
    "sg:tags":[
        "solicitor"
    ],
    "wof:name":"Stephen & Robb",
    "wof:placetype":"venue"
},
  "geometry": {"coordinates":[-2.9501650333,57.5392189026],"type":"Point"}
}