{
  "type": "Feature",
  "properties": {
    "addr:full":"162-164 Arthur Road, Wimbledon London Greater London SW19 8AQ",
    "addr:housenumber":"162-164",
    "addr:postcode":"sw19 8aq",
    "addr:street":"Arthur Road",
    "iso:country":"GB",
    "sg:address":"162-164 Arthur Road, Wimbledon",
    "sg:city":"London",
    "sg:classifiers":[
        {
            "category":"Professional",
            "subcategory":"Accounting & Tax Preparation",
            "type":"Services"
        }
    ],
    "sg:phone":"+44 20 8944 1180",
    "sg:postcode":"SW19 8AQ",
    "sg:province":"Greater London",
    "sg:tags":[
        "accountant"
    ],
    "wof:name":"Coulthards Chartered Accountants",
    "wof:placetype":"venue"
},
  "geometry": {"coordinates":[-0.1972949952,51.4348754883],"type":"Point"}
}