{
  "type": "Feature",
  "properties": {
    "addr:full":"Sycamore House, Tanning Lane, New Buckenham Norwich Norfolk NR16 2AR",
    "addr:postcode":"nr16 2ar",
    "addr:street":"Tanning Lane",
    "iso:country":"GB",
    "sg:address":"Sycamore House, Tanning Lane, New Buckenham",
    "sg:city":"Norwich",
    "sg:classifiers":[
        {
            "category":"Building & Trades",
            "subcategory":"Landscaping Services",
            "type":"Services"
        }
    ],
    "sg:phone":"+44 1953 860370",
    "sg:postcode":"NR16 2AR",
    "sg:province":"Norfolk",
    "sg:tags":[
        "forestry",
        "surgeon",
        "tree"
    ],
    "wof:name":"Broadland Tree Services",
    "wof:placetype":"venue"
},
  "geometry": {"coordinates":[1.0754400492,52.4721908569],"type":"Point"}
}