{
  "type": "Feature",
  "properties": {
    "addr:full":"134 Swanbourne Drive Hornchurch Essex RM12 6QZ",
    "addr:housenumber":"134",
    "addr:postcode":"rm12 6qz",
    "addr:street":"Swanbourne Drive",
    "iso:country":"GB",
    "sg:address":"134 Swanbourne Drive",
    "sg:city":"Hornchurch",
    "sg:classifiers":[
        {
            "category":"Professional",
            "subcategory":"Business Services",
            "type":"Services"
        }
    ],
    "sg:phone":"+44 1708 474923",
    "sg:postcode":"RM12 6QZ",
    "sg:province":"Essex",
    "sg:tags":[
        "import",
        "export",
        "agent"
    ],
    "wof:name":"Sainan Ltd.",
    "wof:placetype":"venue"
},
  "geometry": {"coordinates":[0.2109069973,51.5461769104],"type":"Point"}
}