{
  "type": "Feature",
  "properties": {
    "addr:full":"Cuckoo Clo, North Waltham Basingstoke Hampshire RG25 2BJ",
    "addr:postcode":"rg25 2bj",
    "iso:country":"GB",
    "sg:address":"Cuckoo Clo, North Waltham",
    "sg:city":"Basingstoke",
    "sg:classifiers":[
        {
            "category":"Building & Trades",
            "subcategory":"Landscaping Services",
            "type":"Services"
        }
    ],
    "sg:postcode":"RG25 2BJ",
    "sg:province":"Hampshire",
    "sg:tags":[
        "landscape",
        "contractor"
    ],
    "wof:name":"Smith,Robin,",
    "wof:placetype":"venue"
},
  "geometry": {"coordinates":[-1.195548,51.214046],"type":"Point"}
}