{
  "type": "Feature",
  "properties": {
    "addr:full":"23 Harvester Way, Fengate Trading Estate Peterborough Cambridgeshire PE1 5UT",
    "addr:housenumber":"23",
    "addr:postcode":"pe1 5ut",
    "addr:street":"Harvester Way;Trading",
    "iso:country":"GB",
    "sg:address":"23 Harvester Way, Fengate Trading Estate",
    "sg:city":"Peterborough",
    "sg:classifiers":[
        {
            "category":"Building & Trades",
            "subcategory":"Plumbing",
            "type":"Services"
        }
    ],
    "sg:phone":"+44 1733 551339",
    "sg:postcode":"PE1 5UT",
    "sg:province":"Cambridgeshire",
    "sg:tags":[
        "merchant",
        "plumbers'"
    ],
    "wof:name":"Plumb Center",
    "wof:placetype":"venue"
},
  "geometry": {"coordinates":[-0.2273329943,52.5711669922],"type":"Point"}
}