{
  "type": "Feature",
  "properties": {
    "addr:full":"Unit 4 Shipston Indstl Est, Darlingscott Rd Shipston-on-stour Warwickshire CV36 4PR",
    "addr:housenumber":"unit 4",
    "addr:postcode":"cv36 4pr",
    "addr:street":"Shipston Indstl Est Darlingscott Rd",
    "iso:country":"GB",
    "sg:address":"Unit 4 Shipston Indstl Est, Darlingscott Rd",
    "sg:city":"Shipston-on-stour",
    "sg:classifiers":[
        {
            "category":"Food & Beverages",
            "subcategory":"Candy",
            "type":"Retail Goods"
        }
    ],
    "sg:postcode":"CV36 4PR",
    "sg:province":"Warwickshire",
    "sg:tags":[
        "confectionery"
    ],
    "wof:name":"Merideth,Ian,",
    "wof:placetype":"venue"
},
  "geometry": {"coordinates":[-1.627134,52.062271],"type":"Point"}
}