{
  "type": "Feature",
  "properties": {
    "addr:full":"3 Highbury Road Brandon Norfolk IP27 0ND",
    "addr:housenumber":"3",
    "addr:postcode":"ip27 0nd",
    "addr:street":"Highbury Road",
    "iso:country":"GB",
    "sg:address":"3 Highbury Road",
    "sg:city":"Brandon",
    "sg:classifiers":[
        {
            "category":"Retail",
            "subcategory":"Auto Repair",
            "type":"Services"
        }
    ],
    "sg:phone":"+44 1842 814788",
    "sg:postcode":"IP27 0ND",
    "sg:province":"Norfolk",
    "sg:tags":[
        "modification",
        "garage",
        "related"
    ],
    "wof:name":"J & D Autos",
    "wof:placetype":"venue"
},
  "geometry": {"coordinates":[0.608137,52.439575],"type":"Point"}
}