{
  "type": "Feature",
  "properties": {
    "iso:country":"GB",
    "sg:address":"4 High Street",
    "sg:city":"Hawick",
    "sg:classifiers":[
        {
            "category":"Personal",
            "subcategory":"Beauty Salon",
            "type":"Services"
        }
    ],
    "sg:phone":"+44 1450 370941",
    "sg:postcode":"TD9 9EH",
    "sg:province":"Cumbria",
    "sg:tags":[
        "unisex",
        "hairdresser"
    ],
    "wof:name":"Style A Head",
    "wof:placetype":"venue"
},
  "geometry": {"coordinates":[-2.787921,55.421837],"type":"Point"}
}