{
  "type": "Feature",
  "properties": {
    "iso:country":"GB",
    "sg:address":"13 Newport Road",
    "sg:city":"Middlesbrough",
    "sg:classifiers":[
        {
            "category":"Shopping",
            "subcategory":"Books",
            "type":"Retail Goods"
        }
    ],
    "sg:phone":"+44 1642 250365",
    "sg:postcode":"TS1 1LE",
    "sg:province":"North Yorkshire",
    "sg:tags":[
        "bookseller"
    ],
    "wof:name":"Dovechaste Ltd.",
    "wof:placetype":"venue"
},
  "geometry": {"coordinates":[-1.2382769585,54.576751709],"type":"Point"}
}