{
  "type": "Feature",
  "properties": {
    "addr:full":"5 Furness Rd, Middleton Manchester Greater Manchester M24 6FQ",
    "addr:housenumber":"5",
    "addr:postcode":"m24 6fq",
    "addr:street":"Furness Rd",
    "iso:country":"GB",
    "sg:address":"5 Furness Rd, Middleton",
    "sg:city":"Manchester",
    "sg:classifiers":[
        {
            "category":"Social Services",
            "subcategory":"Child Care",
            "type":"Services"
        }
    ],
    "sg:phone":"+44 161 643 3936",
    "sg:postcode":"M24 6FQ",
    "sg:province":"Greater Manchester",
    "sg:tags":[
        "children's",
        "home"
    ],
    "wof:name":"Furness Road",
    "wof:placetype":"venue"
},
  "geometry": {"coordinates":[-2.198458,53.560528],"type":"Point"}
}