{
  "type": "Feature",
  "properties": {
    "addr:full":"29 Chestnut Way Godalming Surrey GU7 1TS",
    "addr:housenumber":"29",
    "addr:postcode":"gu7 1ts",
    "addr:street":"Chestnut Way",
    "iso:country":"GB",
    "sg:address":"29 Chestnut Way",
    "sg:city":"Godalming",
    "sg:classifiers":[
        {
            "category":"Building & Trades",
            "subcategory":"Construction",
            "type":"Services"
        }
    ],
    "sg:phone":"+44 1483 423836",
    "sg:postcode":"GU7 1TS",
    "sg:province":"Surrey",
    "sg:tags":[
        "joiner",
        "carpenter"
    ],
    "wof:name":"S A Williams",
    "wof:placetype":"venue"
},
  "geometry": {"coordinates":[-0.6033009887,51.1752357483],"type":"Point"}
}