{
  "type": "Feature",
  "properties": {
    "addr:full":"2 Church Road London Greater London NW10 9PX",
    "addr:housenumber":"2",
    "addr:postcode":"nw10 9px",
    "addr:street":"Church Road",
    "iso:country":"GB",
    "sg:address":"2 Church Road",
    "sg:city":"London",
    "sg:classifiers":[
        {
            "category":"Autos & Motor Vehicles",
            "subcategory":"Fuel & Gas Station",
            "type":"Retail Goods"
        }
    ],
    "sg:phone":"+44 20 8961 8891",
    "sg:postcode":"NW10 9PX",
    "sg:province":"Greater London",
    "sg:tags":[
        "hr",
        "petrol"
    ],
    "wof:name":"Craven Park Service Station",
    "wof:placetype":"venue"
},
  "geometry": {"coordinates":[-0.252338,51.547543],"type":"Point"}
}