{
  "type": "Feature",
  "properties": {
    "addr:full":"Academy Road Moffat Dumfries and Galloway DG10 9HT",
    "addr:postcode":"dg10 9ht",
    "addr:street":"Academy Road",
    "iso:country":"GB",
    "sg:address":"Academy Road",
    "sg:city":"Moffat",
    "sg:classifiers":[
        {
            "category":"Food & Beverages",
            "subcategory":"Supermarket",
            "type":"Retail Goods"
        },
        {
            "category":"Food & Beverages",
            "subcategory":"Fruits & Vegetables",
            "type":"Retail Goods"
        }
    ],
    "sg:phone":"+44 1683 221020",
    "sg:postcode":"DG10 9HT",
    "sg:province":"Dumfries and Galloway",
    "sg:tags":[
        "greengrocer"
    ],
    "wof:name":"Mini Market",
    "wof:placetype":"venue"
},
  "geometry": {"coordinates":[-3.4455990791,55.335193634],"type":"Point"}
}