{
  "type": "Feature",
  "properties": {
    "addr:full":"79 Worship Street London Greater London EC2A 2EJ",
    "addr:housenumber":"79",
    "addr:postcode":"ec2a 2ej",
    "addr:street":"Worship Street",
    "iso:country":"GB",
    "sg:address":"79 Worship Street",
    "sg:city":"London",
    "sg:classifiers":[
        {
            "category":"Professional",
            "subcategory":"Employment Agencies",
            "type":"Services"
        }
    ],
    "sg:phone":"+44 231337044",
    "sg:postcode":"EC2A 2EJ",
    "sg:province":"Greater London",
    "sg:tags":[
        "consultant"
    ],
    "wof:name":"Williams Lea Resourcing",
    "wof:placetype":"venue"
},
  "geometry": {"coordinates":[-0.0829230025,51.5218963623],"type":"Point"}
}