{
  "type": "Feature",
  "properties": {
    "iso:country":"GB",
    "sg:address":"Ladyship House, Old Lane",
    "sg:city":"Halifax",
    "sg:classifiers":[
        {
            "category":"Building & Trades",
            "subcategory":"Cleaning & Sanitation",
            "type":"Services"
        }
    ],
    "sg:postcode":"HX3 5QN",
    "sg:province":"West Yorkshire",
    "sg:tags":[
        "door",
        "manufacturer"
    ],
    "wof:name":"Wellgate Engineering Co. Ltd.",
    "wof:placetype":"venue"
},
  "geometry": {"coordinates":[-1.862365,53.728497],"type":"Point"}
}