{
  "type": "Feature",
  "properties": {
    "addr:full":"Main Road, East Kirkby Spilsby Lincolnshire PE23 4BZ",
    "addr:postcode":"pe23 4bz",
    "addr:street":"Main Road East",
    "iso:country":"GB",
    "sg:address":"Main Road, East Kirkby",
    "sg:city":"Spilsby",
    "sg:classifiers":[
        {
            "category":"Travel",
            "subcategory":"Hotels & Motels",
            "type":"Entertainment"
        }
    ],
    "sg:phone":"+44 1790 763591",
    "sg:postcode":"PE23 4BZ",
    "sg:province":"Lincolnshire",
    "sg:tags":[
        "house",
        "guest"
    ],
    "wof:name":"Fourways",
    "wof:placetype":"venue"
},
  "geometry": {"coordinates":[-0.0080169998,53.1401786804],"type":"Point"}
}