{
  "type": "Feature",
  "properties": {
    "addr:full":"Unit 38, Mayfield Industrial Estate Dalkeith City of Edinburgh EH22 5RB",
    "addr:housenumber":"unit 38",
    "addr:postcode":"eh22 5rb",
    "addr:street":"Mayfield Industrial Estate",
    "iso:country":"GB",
    "sg:address":"Unit 38, Mayfield Industrial Estate",
    "sg:city":"Dalkeith",
    "sg:classifiers":[
        {
            "category":"Manufacturing",
            "subcategory":"Rubber & Plastics",
            "type":"Manufacturing & Wholesale Goods"
        }
    ],
    "sg:postcode":"EH22 5RB",
    "sg:province":"City of Edinburgh",
    "sg:tags":[
        "injection",
        "moulding"
    ],
    "wof:name":"Fortis Mouldings Ltd.",
    "wof:placetype":"venue"
},
  "geometry": {"coordinates":[-3.052009,55.868851],"type":"Point"}
}