{
  "type": "Feature",
  "properties": {
    "addr:full":"Franklin Industrial Estate, Blaydon Haugh Newcastle-upon-tyne Tyne and Wear NE21 5TL",
    "addr:postcode":"ne21 5tl",
    "addr:street":"Estate",
    "iso:country":"GB",
    "sg:address":"Franklin Industrial Estate, Blaydon Haugh",
    "sg:city":"Newcastle-upon-tyne",
    "sg:classifiers":[
        {
            "category":"Manufacturing",
            "subcategory":"Metals",
            "type":"Manufacturing & Wholesale Goods"
        }
    ],
    "sg:phone":"+44 191 499 0222",
    "sg:postcode":"NE21 5TL",
    "sg:province":"Tyne and Wear",
    "sg:tags":[
        "steel",
        "stockholder"
    ],
    "wof:name":"FRANKLIN STEEL STOCKHOLDERS PLC",
    "wof:placetype":"venue"
},
  "geometry": {"coordinates":[-1.6974029541,54.9668884277],"type":"Point"}
}