{
  "type": "Feature",
  "properties": {
    "iso:country":"GB",
    "sg:address":"1 Eastdean Gardens, Seacroft",
    "sg:city":"Leeds",
    "sg:classifiers":[
        {
            "category":"Building & Trades",
            "subcategory":"Construction",
            "type":"Services"
        }
    ],
    "sg:postcode":"LS14 1HD",
    "sg:province":"West Yorkshire",
    "sg:tags":[
        "joiner",
        "carpenter"
    ],
    "wof:name":"J H Joinery",
    "wof:placetype":"venue"
},
  "geometry": {"coordinates":[-1.465524,53.82616],"type":"Point"}
}