{
  "type": "Feature",
  "properties": {
    "iso:country":"GB",
    "sg:address":"3 High St",
    "sg:city":"Margate",
    "sg:classifiers":[
        {
            "category":"Health Services",
            "subcategory":"Dentist",
            "type":"Services"
        }
    ],
    "sg:phone":"+44 1843 292441",
    "sg:postcode":"CT9 1DL",
    "sg:province":"Kent",
    "wof:name":"J Holland",
    "wof:placetype":"venue"
},
  "geometry": {"coordinates":[1.380521,51.389278],"type":"Point"}
}