{
  "type": "Feature",
  "properties": {
    "addr:full":"35 St Marys York East Riding of Yorkshire YO3 7DD",
    "addr:housenumber":"35",
    "addr:postcode":"yo3 7dd",
    "addr:street":"St Marys",
    "iso:country":"GB",
    "sg:address":"35 St Marys",
    "sg:city":"York",
    "sg:classifiers":[
        {
            "category":"Banks & Credit Unions",
            "subcategory":"Bureau De Change",
            "type":"Services"
        }
    ],
    "sg:phone":"+44 1904 672710",
    "sg:postcode":"YO3 7DD",
    "sg:province":"East Riding of Yorkshire",
    "sg:tags":[
        "town",
        "consultant",
        "planning"
    ],
    "wof:name":"Planning Design Associates",
    "wof:placetype":"venue"
},
  "geometry": {"coordinates":[-1.0893690586,53.9640541077],"type":"Point"}
}