{
  "type": "Feature",
  "properties": {
    "addr:full":"Hatchfield Farm, Fordham Rd Newmarket Cambridgeshire CB8 7AH",
    "addr:postcode":"cb8 7ah",
    "addr:street":"Fordham Rd",
    "iso:country":"GB",
    "sg:address":"Hatchfield Farm, Fordham Rd",
    "sg:city":"Newmarket",
    "sg:classifiers":[
        {
            "category":"Farming",
            "subcategory":"Livestock Farm",
            "type":"Manufacturing & Wholesale Goods"
        }
    ],
    "sg:phone":"+44 1638 662013",
    "sg:postcode":"CB8 7AH",
    "sg:province":"Cambridgeshire",
    "sg:tags":[
        "stud"
    ],
    "wof:name":"Stanley Estate & Stud Co",
    "wof:placetype":"venue"
},
  "geometry": {"coordinates":[0.399165988,52.2498168945],"type":"Point"}
}