{
  "type": "Feature",
  "properties": {
    "iso:country":"GB",
    "sg:address":"Barn Close",
    "sg:city":"Welwyn Garden City",
    "sg:classifiers":[
        {
            "category":"Place Of Worship",
            "type":"Public Place"
        }
    ],
    "sg:phone":"+44 1707 322443",
    "sg:postcode":"AL8 6ST",
    "sg:province":"Hertfordshire",
    "wof:name":"Welwyn Garden Hebrew Congregation",
    "wof:placetype":"venue"
},
  "geometry": {"coordinates":[-0.214554,51.798309],"type":"Point"}
}