{
  "type": "Feature",
  "properties": {
    "addr:full":"Silver Hills Road, Decoy Industrial Estate Newton Abbot Devon TQ12 5ND",
    "addr:housenumber":"abbot",
    "addr:postcode":"tq12 5nd",
    "addr:street":"Silver Hills Road Decoy Industrial Estate",
    "iso:country":"GB",
    "sg:address":"Silver Hills Road, Decoy Industrial Estate",
    "sg:city":"Newton Abbot",
    "sg:classifiers":[
        {
            "category":"Manufacturing",
            "subcategory":"Metals",
            "type":"Manufacturing & Wholesale Goods"
        }
    ],
    "sg:phone":"+44 1626 362255",
    "sg:postcode":"TQ12 5ND",
    "sg:province":"Devon",
    "sg:tags":[
        "steel",
        "fabricator",
        "work",
        "sheet",
        "erectors"
    ],
    "wof:name":"Devlex Engineering Ltd.",
    "wof:placetype":"venue"
},
  "geometry": {"coordinates":[-3.598299,50.517071],"type":"Point"}
}