{
  "type": "Feature",
  "properties": {
    "iso:country":"GB",
    "sg:address":"Milligans Yard, Westgate",
    "sg:city":"Otley",
    "sg:classifiers":[
        {
            "category":"Building & Trades",
            "subcategory":"Plumbing",
            "type":"Services"
        }
    ],
    "sg:postcode":"LS21 3DT",
    "sg:province":"North Yorkshire",
    "sg:tags":[
        "central",
        "heating"
    ],
    "wof:name":"Aa Rosebank Services",
    "wof:placetype":"venue"
},
  "geometry": {"coordinates":[-1.694953,53.90572],"type":"Point"}
}