{
  "type": "Feature",
  "properties": {
    "iso:country":"GB",
    "sg:address":"97 Lonsdale Avenue",
    "sg:city":"Wembley",
    "sg:classifiers":[
        {
            "category":"Professional",
            "subcategory":"Business Services",
            "type":"Services"
        }
    ],
    "sg:phone":"+44 20 7387 3740",
    "sg:postcode":"HA9 7EW",
    "sg:province":"Greater London",
    "sg:tags":[
        "import",
        "export",
        "agent"
    ],
    "wof:name":"London Oriental Ltd.",
    "wof:placetype":"venue"
},
  "geometry": {"coordinates":[-0.2927789986,51.5511131287],"type":"Point"}
}