{
  "type": "Feature",
  "properties": {
    "addr:full":"10 Westwood Avenue Harrow Greater London HA2 8NS",
    "addr:housenumber":"10",
    "addr:postcode":"ha2 8ns",
    "addr:street":"Westwood Avenue",
    "iso:country":"GB",
    "sg:address":"10 Westwood Avenue",
    "sg:city":"Harrow",
    "sg:classifiers":[
        {
            "category":"Retail",
            "subcategory":"Auto Repair",
            "type":"Services"
        }
    ],
    "sg:phone":"+44 20 8423 5816",
    "sg:postcode":"HA2 8NS",
    "sg:province":"Greater London",
    "sg:tags":[
        "modification",
        "garage"
    ],
    "wof:name":"P & J Harrow",
    "wof:placetype":"venue"
},
  "geometry": {"coordinates":[-0.358731,51.559063],"type":"Point"}
}