{
  "type": "Feature",
  "properties": {
    "addr:full":"Buckland Community Centre, Malins Rd Portsmouth Hampshire PO2 7BB",
    "addr:postcode":"hampshire po2 7bb",
    "addr:street":"Malins Rd",
    "iso:country":"GB",
    "sg:address":"Buckland Community Centre, Malins Rd",
    "sg:city":"Portsmouth",
    "sg:classifiers":[
        {
            "category":"Organizations",
            "subcategory":"Non-profit Organization",
            "type":"Services"
        }
    ],
    "sg:phone":"+44 23 9266 5362",
    "sg:postcode":"PO2 7BB",
    "sg:province":"Hampshire",
    "sg:tags":[
        "organisation",
        "voluntary",
        "charity"
    ],
    "wof:name":"Home-Start",
    "wof:placetype":"venue"
},
  "geometry": {"coordinates":[-1.08189,50.809891],"type":"Point"}
}