{
  "type": "Feature",
  "properties": {
    "addr:full":"31 Castlegate Berwick-upon-tweed Northumberland TD15 1LF",
    "addr:housenumber":"31;berwick-upon-tweed",
    "addr:postcode":"td15 1lf",
    "addr:street":"Castlegate;Northumberland",
    "iso:country":"GB",
    "sg:address":"31 Castlegate",
    "sg:city":"Berwick-upon-tweed",
    "sg:classifiers":[
        {
            "category":"Personal",
            "subcategory":"Beauty Salon",
            "type":"Services"
        }
    ],
    "sg:postcode":"TD15 1LF",
    "sg:province":"Northumberland",
    "sg:tags":[
        "lady",
        "hairdresser"
    ],
    "wof:name":"Rainbow Room",
    "wof:placetype":"venue"
},
  "geometry": {"coordinates":[-2.008259058,55.7721366882],"type":"Point"}
}