{
  "type": "Feature",
  "properties": {
    "iso:country":"GB",
    "sg:address":"Wiveliscombe House, 3 The Square, Wiveliscombe",
    "sg:city":"Taunton",
    "sg:classifiers":[
        {
            "category":"Education",
            "subcategory":"Library",
            "type":"Public Place"
        }
    ],
    "sg:phone":"+44 1984 623723",
    "sg:postcode":"TA4 2JT",
    "sg:province":"Devon",
    "sg:tags":[
        "book"
    ],
    "wof:name":"Wiveliscombe Library",
    "wof:placetype":"venue"
},
  "geometry": {"coordinates":[-3.3124740124,51.0422706604],"type":"Point"}
}