{
  "type": "Feature",
  "properties": {
    "iso:country":"GB",
    "sg:address":"Mill Road",
    "sg:city":"Norwich",
    "sg:classifiers":[
        {
            "category":"Government",
            "subcategory":"City Hall",
            "type":"Public Place"
        }
    ],
    "sg:phone":"+44 1953 788219",
    "sg:postcode":"NR16 1AD",
    "sg:province":"Norfolk",
    "wof:name":"Carleton Rode Village Hall",
    "wof:placetype":"venue"
},
  "geometry": {"coordinates":[1.0996049643,52.4959106445],"type":"Point"}
}