{
  "type": "Feature",
  "properties": {
    "addr:full":"Old Bath Road, Charvil Reading Berkshire RG10 9QP",
    "addr:postcode":"rg10 9qp",
    "addr:street":"Old Bath Road",
    "iso:country":"GB",
    "sg:address":"Old Bath Road, Charvil",
    "sg:city":"Reading",
    "sg:classifiers":[
        {
            "category":"Bars & Pubs",
            "type":"Food & Drink"
        }
    ],
    "sg:phone":"+44 118 944 0066",
    "sg:postcode":"RG10 9QP",
    "sg:province":"Berkshire",
    "sg:tags":[
        "pubs",
        "inn"
    ],
    "wof:name":"The Wee Waif",
    "wof:placetype":"venue"
},
  "geometry": {"coordinates":[-0.88467,51.476543],"type":"Point"}
}