{
  "type": "Feature",
  "properties": {
    "addr:full":"90 Derby Road Chesterfield Derbyshire S40 2EF",
    "addr:housenumber":"90",
    "addr:postcode":"s40 2ef",
    "addr:street":"Derby Road",
    "iso:country":"GB",
    "sg:address":"90 Derby Road",
    "sg:city":"Chesterfield",
    "sg:classifiers":[
        {
            "category":"Manufacturing",
            "subcategory":"Tools & Machinery",
            "type":"Manufacturing & Wholesale Goods"
        }
    ],
    "sg:phone":"+44 1246 555880",
    "sg:postcode":"S40 2EF",
    "sg:province":"Derbyshire",
    "sg:tags":[
        "society",
        "friendly"
    ],
    "wof:name":"Martin Edwards Insurance Services Ltd.",
    "wof:placetype":"venue"
},
  "geometry": {"coordinates":[-1.424932003,53.2266693115],"type":"Point"}
}