{
  "type": "Feature",
  "properties": {
    "addr:full":"242 Southport Road Ormskirk Lancashire L39 1LZ",
    "addr:housenumber":"242",
    "addr:postcode":"l39 1lz",
    "addr:street":"Southport Road",
    "iso:country":"GB",
    "sg:address":"242 Southport Road",
    "sg:city":"Ormskirk",
    "sg:classifiers":[
        {
            "category":"Autos & Motor Vehicles",
            "subcategory":"Fuel & Gas Station",
            "type":"Retail Goods"
        }
    ],
    "sg:phone":"+44 1254 871327",
    "sg:postcode":"L39 1LZ",
    "sg:province":"Lancashire",
    "sg:tags":[
        "petrol",
        "filling"
    ],
    "wof:name":"Cooke Petroleum Ltd.",
    "wof:placetype":"venue"
},
  "geometry": {"coordinates":[-2.8954279423,53.5783805847],"type":"Point"}
}