{
  "type": "Feature",
  "properties": {
    "addr:full":"15 Clarence Road Southend-on-sea Essex SS1 1AN",
    "addr:housenumber":"15",
    "addr:postcode":"ss1 1an",
    "addr:street":"Clarence Road",
    "iso:country":"GB",
    "sg:address":"15 Clarence Road",
    "sg:city":"Southend-on-sea",
    "sg:classifiers":[
        {
            "category":"Professional",
            "subcategory":"Lawyer & Legal Services",
            "type":"Services"
        }
    ],
    "sg:phone":"+44 1702 436453",
    "sg:postcode":"SS1 1AN",
    "sg:province":"Essex",
    "sg:tags":[
        "solicitor"
    ],
    "wof:name":"Bodiam Dann & Co",
    "wof:placetype":"venue"
},
  "geometry": {"coordinates":[0.71179,51.535877],"type":"Point"}
}