{
  "type": "Feature",
  "properties": {
    "iso:country":"GB",
    "sg:address":"55 St Peters Street",
    "sg:city":"Bedford",
    "sg:classifiers":[
        {
            "category":"Real Estate",
            "subcategory":"Architect",
            "type":"Services"
        }
    ],
    "sg:phone":"+44 1234 356813",
    "sg:postcode":"MK40 2PR",
    "sg:province":"Bedfordshire",
    "sg:tags":[
        "architectural"
    ],
    "wof:name":"Burnix Design Ltd.",
    "wof:placetype":"venue"
},
  "geometry": {"coordinates":[-0.463216,52.139294],"type":"Point"}
}