{
  "type": "Feature",
  "properties": {
    "iso:country":"GB",
    "sg:address":"Unit 6 The Mead Business Centre, Mead Lane",
    "sg:city":"Hertford",
    "sg:classifiers":[
        {
            "category":"Professional",
            "subcategory":"Printing & Photocopies",
            "type":"Services"
        }
    ],
    "sg:phone":"+44 1992 504438",
    "sg:postcode":"SG13 7BJ",
    "sg:province":"Hertfordshire",
    "sg:tags":[
        "printer"
    ],
    "wof:name":"T J Offset Ltd.",
    "wof:placetype":"venue"
},
  "geometry": {"coordinates":[-0.0262880009,51.7786827087],"type":"Point"}
}