{
  "type": "Feature",
  "properties": {
    "addr:full":"36 Cranmer Road, Cowley Oxford Oxfordshire OX4 2QE",
    "addr:housenumber":"36",
    "addr:postcode":"ox4 2qe",
    "addr:street":"Cranmer Road",
    "iso:country":"GB",
    "sg:address":"36 Cranmer Road, Cowley",
    "sg:city":"Oxford",
    "sg:classifiers":[
        {
            "category":"Utilities",
            "type":"Services"
        }
    ],
    "sg:phone":"+44 1865 451991",
    "sg:postcode":"OX4 2QE",
    "sg:province":"Oxfordshire",
    "sg:tags":[
        "internet"
    ],
    "wof:name":"Laminar Systems Ltd",
    "wof:placetype":"venue"
},
  "geometry": {"coordinates":[-1.202334,51.739723],"type":"Point"}
}