{
  "type": "Feature",
  "properties": {
    "addr:full":"23 Park Street Baldock Bedfordshire SG7 6DY",
    "addr:housenumber":"23",
    "addr:postcode":"sg7 6dy",
    "addr:street":"Park Street",
    "iso:country":"GB",
    "sg:address":"23 Park Street",
    "sg:city":"Baldock",
    "sg:classifiers":[
        {
            "category":"Retail",
            "subcategory":"Driving School",
            "type":"Services"
        }
    ],
    "sg:postcode":"SG7 6DY",
    "sg:province":"Bedfordshire",
    "wof:name":"Harry Peters",
    "wof:placetype":"venue"
},
  "geometry": {"coordinates":[-0.189351,51.987961],"type":"Point"}
}