{
  "type": "Feature",
  "properties": {
    "iso:country":"GB",
    "sg:address":"Redwick House, Green Street, Redwick",
    "sg:city":"Caldicot",
    "sg:classifiers":[
        {
            "category":"Farming",
            "subcategory":"Livestock Farm",
            "type":"Manufacturing & Wholesale Goods"
        }
    ],
    "sg:postcode":"NP26 3DY",
    "sg:province":"Monmouthshire",
    "sg:tags":[
        "others"
    ],
    "wof:name":"R & M Duthie",
    "wof:placetype":"venue"
},
  "geometry": {"coordinates":[-2.8442900181,51.5579986572],"type":"Point"}
}