{
  "type": "Feature",
  "properties": {
    "addr:full":"8 Whitegates, Flaxpits Lane, Winterbourne Bristol Gloucestershire BS36 1JX",
    "addr:housenumber":"8",
    "addr:postcode":"bs36 1jx",
    "addr:street":"Flaxpits Lane",
    "iso:country":"GB",
    "sg:address":"8 Whitegates, Flaxpits Lane, Winterbourne",
    "sg:city":"Bristol",
    "sg:classifiers":[
        {
            "category":"Professional",
            "subcategory":"Accounting & Tax Preparation",
            "type":"Services"
        }
    ],
    "sg:phone":"+44 1454 850001",
    "sg:postcode":"BS36 1JX",
    "sg:province":"Gloucestershire",
    "sg:tags":[
        "accountant"
    ],
    "wof:name":"J Brain",
    "wof:placetype":"venue"
},
  "geometry": {"coordinates":[-2.50793,51.522469],"type":"Point"}
}