{
  "type": "Feature",
  "properties": {
    "addr:full":"Cerney House, Cranmore View Frome Somerset BA11 4DT",
    "addr:postcode":"ba11 4dt",
    "addr:street":"Cranmore View",
    "iso:country":"GB",
    "sg:address":"Cerney House, Cranmore View",
    "sg:city":"Frome",
    "sg:classifiers":[
        {
            "category":"Building & Trades",
            "subcategory":"Construction",
            "type":"Services"
        }
    ],
    "sg:phone":"+44 1373 465960",
    "sg:postcode":"BA11 4DT",
    "sg:province":"Somerset",
    "sg:tags":[
        "contractor",
        "paving",
        "driveway"
    ],
    "wof:name":"Gordon Smith (Surfacing) Ltd.",
    "wof:placetype":"venue"
},
  "geometry": {"coordinates":[-2.3327200413,51.2206840515],"type":"Point"}
}