{
  "type": "Feature",
  "properties": {
    "addr:full":"Stormy Down, Pyle Bridgend Bridgend CF33 4RS",
    "addr:postcode":"cf33 4rs",
    "iso:country":"GB",
    "sg:address":"Stormy Down, Pyle",
    "sg:city":"Bridgend",
    "sg:classifiers":[
        {
            "category":"Recreation",
            "subcategory":"Go Karts",
            "type":"Entertainment"
        }
    ],
    "sg:phone":"+44 1656 773737",
    "sg:postcode":"CF33 4RS",
    "sg:province":"Bridgend",
    "sg:tags":[
        "karting"
    ],
    "wof:name":"Race Hire 2001",
    "wof:placetype":"venue"
},
  "geometry": {"coordinates":[-3.709658,51.51968],"type":"Point"}
}