{
  "type": "Feature",
  "properties": {
    "addr:full":"515 Hywel Road Haverfordwest Pembrokeshire SA61 2TJ",
    "addr:housenumber":"515",
    "addr:postcode":"sa61 2tj",
    "addr:street":"Hywel Road",
    "iso:country":"GB",
    "sg:address":"515 Hywel Road",
    "sg:city":"Haverfordwest",
    "sg:classifiers":[
        {
            "category":"Government",
            "subcategory":"Office",
            "type":"Public Place"
        }
    ],
    "sg:phone":"+44 1437 760464",
    "sg:postcode":"SA61 2TJ",
    "sg:province":"Pembrokeshire",
    "sg:tags":[
        "local"
    ],
    "wof:name":"Hywel Road Family Resource Centre",
    "wof:placetype":"venue"
},
  "geometry": {"coordinates":[-4.989153,51.801262],"type":"Point"}
}