{
  "type": "Feature",
  "properties": {
    "addr:full":"2c Chandos Rd Bristol City of Bristol BS6 6PE",
    "addr:housenumber":"2c",
    "addr:postcode":"bs6 6pe",
    "addr:street":"Chandos Rd",
    "iso:country":"GB",
    "sg:address":"2c Chandos Rd",
    "sg:city":"Bristol",
    "sg:classifiers":[
        {
            "category":"Utilities",
            "subcategory":"Telephone",
            "type":"Services"
        }
    ],
    "sg:phone":"+44 117 973 0435",
    "sg:postcode":"BS6 6PE",
    "sg:province":"City of Bristol",
    "sg:tags":[
        "telecommunication"
    ],
    "wof:name":"Iosis",
    "wof:placetype":"venue"
},
  "geometry": {"coordinates":[-2.600589,51.462551],"type":"Point"}
}