{
  "type": "Feature",
  "properties": {
    "addr:full":"5 Greenhills, Edington Westbury Wiltshire BA13 4PZ",
    "addr:housenumber":"5;edington",
    "addr:postcode":"ba13 4pz",
    "addr:street":"Greenhills",
    "iso:country":"GB",
    "sg:address":"5 Greenhills, Edington",
    "sg:city":"Westbury",
    "sg:classifiers":[
        {
            "category":"Retail",
            "subcategory":"Driving School",
            "type":"Services"
        }
    ],
    "sg:phone":"+44 1380 830877",
    "sg:postcode":"BA13 4PZ",
    "sg:province":"Wiltshire",
    "wof:name":"Ladysafe School of Motoring",
    "wof:placetype":"venue"
},
  "geometry": {"coordinates":[-2.167479,51.263618],"type":"Point"}
}