{
  "type": "Feature",
  "properties": {
    "addr:full":"13 Brook Business Centre, Cowley Mill Rd Uxbridge Buckinghamshire UB8 2FX",
    "addr:housenumber":"13",
    "addr:postcode":"ub8 2fx",
    "addr:street":"Brook Business Centre;Mill Rd",
    "iso:country":"GB",
    "sg:address":"13 Brook Business Centre, Cowley Mill Rd",
    "sg:city":"Uxbridge",
    "sg:classifiers":[
        {
            "category":"Shopping",
            "subcategory":"Stationery & Office Supplies",
            "type":"Retail Goods"
        }
    ],
    "sg:phone":"+44 1895 811499",
    "sg:postcode":"UB8 2FX",
    "sg:province":"Buckinghamshire",
    "sg:tags":[
        "item",
        "promotional"
    ],
    "wof:name":"I D Promotional Services",
    "wof:placetype":"venue"
},
  "geometry": {"coordinates":[-0.4822700024,51.5310516357],"type":"Point"}
}