{
  "type": "Feature",
  "properties": {
    "addr:full":"Pines Industrial Estate Fordham Road Newmarket Cambridgeshire CB8 7LG",
    "addr:housenumber":"estate",
    "addr:postcode":"cb8 7lg",
    "addr:street":"Fordham Road",
    "iso:country":"GB",
    "sg:address":"Pines Industrial Estate Fordham Road",
    "sg:city":"Newmarket",
    "sg:classifiers":[
        {
            "category":"Manufacturing",
            "subcategory":"Glass & Minerals",
            "type":"Manufacturing & Wholesale Goods"
        }
    ],
    "sg:phone":"+44 1638 721912",
    "sg:postcode":"CB8 7LG",
    "sg:province":"Cambridgeshire",
    "sg:tags":[
        "fibre",
        "material"
    ],
    "wof:name":"Saint-Gobain Vetrotex (U K) Ltd.",
    "wof:placetype":"venue"
},
  "geometry": {"coordinates":[0.3874900043,52.2589416504],"type":"Point"}
}