{
  "type": "Feature",
  "properties": {
    "iso:country":"GB",
    "sg:address":"19 Ferrers Avenue",
    "sg:city":"West Drayton",
    "sg:classifiers":[
        {
            "category":"Building & Trades",
            "subcategory":"Cleaning & Sanitation",
            "type":"Services"
        }
    ],
    "sg:phone":"+44 20 8332 6466",
    "sg:postcode":"UB7 7AA",
    "sg:province":"Greater London",
    "sg:tags":[
        "boiler"
    ],
    "wof:name":"The Plumber",
    "wof:placetype":"venue"
},
  "geometry": {"coordinates":[-0.4747340083,51.5078773499],"type":"Point"}
}