{
  "type": "Feature",
  "properties": {
    "addr:full":"60a Norman Rd Tunbridge Wells Kent TN1 2RP",
    "addr:housenumber":"60a",
    "addr:postcode":"tn1 2rp",
    "addr:street":"Norman Rd",
    "iso:country":"GB",
    "sg:address":"60a Norman Rd",
    "sg:city":"Tunbridge Wells",
    "sg:classifiers":[
        {
            "category":"Professional",
            "subcategory":"Printing & Photocopies",
            "type":"Services"
        }
    ],
    "sg:phone":"+44 1892 532532",
    "sg:postcode":"TN1 2RP",
    "sg:province":"Kent",
    "sg:tags":[
        "printer"
    ],
    "wof:name":"Lucas Prints & Productions Ltd",
    "wof:placetype":"venue"
},
  "geometry": {"coordinates":[0.2690519989,51.1379203796],"type":"Point"}
}