{
  "type": "Feature",
  "properties": {
    "iso:country":"GB",
    "sg:address":"23 Parkside",
    "sg:city":"Coventry",
    "sg:classifiers":[
        {
            "category":"Building & Trades",
            "subcategory":"Electrical",
            "type":"Services"
        }
    ],
    "sg:postcode":"CV1 2NE",
    "sg:province":"West Midlands",
    "sg:tags":[
        "consultant",
        "lighting"
    ],
    "wof:name":"B B I Lighting Ltd.",
    "wof:placetype":"venue"
},
  "geometry": {"coordinates":[-1.506019,52.403828],"type":"Point"}
}