{
  "type": "Feature",
  "properties": {
    "addr:full":"51 South Street Dorking Surrey RH4 2JX",
    "addr:housenumber":"51",
    "addr:postcode":"rh4 2jx",
    "addr:street":"South Street",
    "iso:country":"GB",
    "sg:address":"51 South Street",
    "sg:city":"Dorking",
    "sg:classifiers":[
        {
            "category":"Professional",
            "subcategory":"Secretarial Services",
            "type":"Services"
        },
        {
            "category":"Arena",
            "subcategory":"Sports Club",
            "type":"Entertainment"
        }
    ],
    "sg:phone":"+44 1306 640906",
    "sg:postcode":"RH4 2JX",
    "sg:province":"Surrey",
    "wof:name":"Dorking Business Centre",
    "wof:placetype":"venue"
},
  "geometry": {"coordinates":[-0.3281719983,51.224193573],"type":"Point"}
}