{
  "type": "Feature",
  "properties": {
    "addr:full":"Sheldrakes, 6 Royal Square, Deadham Colchester Essex CO7 6AA",
    "addr:housenumber":"6",
    "addr:postcode":"co7 6aa",
    "addr:street":"Sheldrakes;Royal Square Deadham Colchester",
    "iso:country":"GB",
    "sg:address":"Sheldrakes, 6 Royal Square, Deadham",
    "sg:city":"Colchester",
    "sg:classifiers":[
        {
            "category":"Real Estate",
            "subcategory":"Developer",
            "type":"Services"
        }
    ],
    "sg:phone":"+44 1206 323666",
    "sg:postcode":"CO7 6AA",
    "sg:province":"Essex",
    "sg:tags":[
        "property"
    ],
    "wof:name":"Plandraft Ltd.",
    "wof:placetype":"venue"
},
  "geometry": {"coordinates":[0.9938499928,51.9587898254],"type":"Point"}
}