{
  "type": "Feature",
  "properties": {
    "iso:country":"GB",
    "sg:address":"Coleman Street",
    "sg:city":"Derby",
    "sg:classifiers":[
        {
            "category":"Manufacturing",
            "subcategory":"Lumber",
            "type":"Manufacturing & Wholesale Goods"
        }
    ],
    "sg:phone":"+44 1332 574222",
    "sg:postcode":"DE24 8NH",
    "sg:province":"Derbyshire",
    "sg:tags":[
        "merchant",
        "merchants",
        "importer",
        "agent",
        "timber"
    ],
    "wof:name":"Harlow Bros Ltd.",
    "wof:placetype":"venue"
},
  "geometry": {"coordinates":[-1.4447640181,52.8954582214],"type":"Point"}
}