{
  "type": "Feature",
  "properties": {
    "addr:full":"151 Bilford Rd Worcester Worcestershire WR3 8PL",
    "addr:housenumber":"151",
    "addr:postcode":"wr3 8pl",
    "addr:street":"Bilford Rd",
    "iso:country":"GB",
    "sg:address":"151 Bilford Rd",
    "sg:city":"Worcester",
    "sg:classifiers":[
        {
            "category":"Marine",
            "type":"Transportation"
        }
    ],
    "sg:phone":"+44 1905 754506",
    "sg:postcode":"WR3 8PL",
    "sg:province":"Worcestershire",
    "sg:tags":[
        "inland",
        "waterway",
        "river"
    ],
    "wof:name":"British Waterways",
    "wof:placetype":"venue"
},
  "geometry": {"coordinates":[-2.211468935,52.2118225098],"type":"Point"}
}