{
  "type": "Feature",
  "properties": {
    "addr:full":"15 Adderley Cres Dundee Angus DD5 4DS",
    "addr:housenumber":"15",
    "addr:postcode":"dd5 4ds",
    "addr:street":"Adderley Cres",
    "iso:country":"GB",
    "sg:address":"15 Adderley Cres",
    "sg:city":"Dundee",
    "sg:classifiers":[
        {
            "category":"Retail",
            "subcategory":"Driving School",
            "type":"Services"
        }
    ],
    "sg:phone":"+44 1382 534542",
    "sg:postcode":"DD5 4DS",
    "sg:province":"Angus",
    "wof:name":"R.S. Learning",
    "wof:placetype":"venue"
},
  "geometry": {"coordinates":[-2.821188,56.484406],"type":"Point"}
}