{
  "type": "Feature",
  "properties": {
    "iso:country":"GB",
    "sg:address":"22 Warren Gardens, Great Woodley Estate",
    "sg:city":"Romsey",
    "sg:classifiers":[
        {
            "category":"Shopping",
            "type":"Retail Goods"
        }
    ],
    "sg:postcode":"SO51 7TR",
    "sg:province":"Hampshire",
    "sg:tags":[
        "part",
        "accessory"
    ],
    "wof:name":"Romsey Autospares",
    "wof:placetype":"venue"
},
  "geometry": {"coordinates":[-1.47556,51.000504],"type":"Point"}
}