{
  "type": "Feature",
  "properties": {
    "addr:full":"26 Clifford St Newton Abbot Devon TQ13 0LE",
    "addr:housenumber":"26",
    "addr:postcode":"tq13 0le",
    "addr:street":"Clifford St",
    "iso:country":"GB",
    "sg:address":"26 Clifford St",
    "sg:city":"Newton Abbot",
    "sg:classifiers":[
        {
            "category":"Manufacturing",
            "subcategory":"Signs",
            "type":"Manufacturing & Wholesale Goods"
        }
    ],
    "sg:phone":"+44 1626 852736",
    "sg:postcode":"TQ13 0LE",
    "sg:province":"Devon",
    "sg:tags":[
        "writer"
    ],
    "wof:name":"Sign & Design",
    "wof:placetype":"venue"
},
  "geometry": {"coordinates":[-3.598654,50.603718],"type":"Point"}
}