{
  "type": "Feature",
  "properties": {
    "addr:full":"6 Bridge Way, Whetstone Leicester Leicestershire LE8 6LY",
    "addr:housenumber":"6",
    "addr:postcode":"le8 6ly",
    "addr:street":"Bridge Way",
    "iso:country":"GB",
    "sg:address":"6 Bridge Way, Whetstone",
    "sg:city":"Leicester",
    "sg:classifiers":[
        {
            "category":"Building & Trades",
            "subcategory":"Construction",
            "type":"Services"
        }
    ],
    "sg:phone":"+44 116 286 6233",
    "sg:postcode":"LE8 6LY",
    "sg:province":"Leicestershire",
    "sg:tags":[
        "ceiling",
        "suspended",
        "contractor"
    ],
    "wof:name":"Trevor Hodges",
    "wof:placetype":"venue"
},
  "geometry": {"coordinates":[-1.17918396,52.5679512024],"type":"Point"}
}