{
  "type": "Feature",
  "properties": {
    "iso:country":"GB",
    "sg:address":"Taunton Road",
    "sg:city":"Chard",
    "sg:classifiers":[
        {
            "category":"Restaurant",
            "type":"Food & Drink"
        }
    ],
    "sg:phone":"+44 1460 63317",
    "sg:postcode":"TA20 3AQ",
    "sg:province":"Devon",
    "wof:name":"Hornsbury Mill",
    "wof:placetype":"venue"
},
  "geometry": {"coordinates":[-2.9604740143,50.8735237122],"type":"Point"}
}