{
  "type": "Feature",
  "properties": {
    "iso:country":"GB",
    "sg:address":"143 Den Lane, Springhead Oldham",
    "sg:city":"Oldham",
    "sg:classifiers":[
        {
            "category":"Bars & Pubs",
            "type":"Food & Drink"
        },
        {
            "category":"Community Center",
            "subcategory":"Social",
            "type":"Public Place"
        }
    ],
    "sg:phone":"+44 161 665 2272",
    "sg:postcode":"OL4 4RE",
    "sg:province":"Lancashire",
    "sg:tags":[
        "pubs",
        "house",
        "inn",
        "activity"
    ],
    "wof:name":"Peels Arms",
    "wof:placetype":"venue"
},
  "geometry": {"coordinates":[-2.063193,53.543839],"type":"Point"}
}