{
  "type": "Feature",
  "properties": {
    "addr:full":"Main Street, Sicklinghall Wetherby North Yorkshire LS22 4BD",
    "addr:postcode":"ls22 4bd",
    "addr:street":"Main Street",
    "iso:country":"GB",
    "sg:address":"Main Street, Sicklinghall",
    "sg:city":"Wetherby",
    "sg:classifiers":[
        {
            "category":"Bars & Pubs",
            "type":"Food & Drink"
        }
    ],
    "sg:phone":"+44 1937 582100",
    "sg:postcode":"LS22 4BD",
    "sg:province":"North Yorkshire",
    "sg:tags":[
        "pubs",
        "inn"
    ],
    "wof:name":"The Scotts Arms",
    "wof:placetype":"venue"
},
  "geometry": {"coordinates":[-1.4518760443,53.9305877686],"type":"Point"}
}