{
  "type": "Feature",
  "properties": {
    "addr:full":"708-710 Dumbarton Road Glasgow Glasgow City G11 6RB",
    "addr:housenumber":"708-710",
    "addr:postcode":"g11 6rb",
    "addr:street":"Dumbarton Road",
    "iso:country":"GB",
    "sg:address":"708-710 Dumbarton Road",
    "sg:city":"Glasgow",
    "sg:classifiers":[
        {
            "category":"Professional",
            "subcategory":"Art Services",
            "type":"Services"
        },
        {
            "category":"Building & Trades",
            "subcategory":"Construction",
            "type":"Services"
        }
    ],
    "sg:phone":"+44 141 339 3310",
    "sg:postcode":"G11 6RB",
    "sg:province":"Glasgow City",
    "sg:tags":[
        "decorator",
        "painter"
    ],
    "wof:name":"J & R Anderson (Painters) Ltd.",
    "wof:placetype":"venue"
},
  "geometry": {"coordinates":[-4.3213639259,55.8711509705],"type":"Point"}
}