{
  "type": "Feature",
  "properties": {
    "addr:full":"Down-leaze, North Street, Mere Warminster Somerset BA12 6HH",
    "addr:postcode":"ba12 6hh",
    "addr:street":"North Street",
    "iso:country":"GB",
    "sg:address":"Down-leaze, North Street, Mere",
    "sg:city":"Warminster",
    "sg:classifiers":[
        {
            "category":"Professional",
            "type":"Services"
        }
    ],
    "sg:postcode":"BA12 6HH",
    "sg:province":"Somerset",
    "sg:tags":[
        "caterer"
    ],
    "wof:name":"June & Wendy Caterers",
    "wof:placetype":"venue"
},
  "geometry": {"coordinates":[-2.270170927,51.090511322],"type":"Point"}
}