{
  "type": "Feature",
  "properties": {
    "addr:full":"47 Chancery Lane Retford Nottinghamshire DN22 6EU",
    "addr:housenumber":"47",
    "addr:postcode":"dn22 6eu",
    "addr:street":"Chancery Lane",
    "iso:country":"GB",
    "sg:address":"47 Chancery Lane",
    "sg:city":"Retford",
    "sg:classifiers":[
        {
            "category":"Social Services",
            "subcategory":"Adult Care",
            "type":"Services"
        }
    ],
    "sg:phone":"+44 1777 710592",
    "sg:postcode":"DN22 6EU",
    "sg:province":"Nottinghamshire",
    "sg:tags":[
        "home",
        "help",
        "private"
    ],
    "wof:name":"Essential Domestic Services",
    "wof:placetype":"venue"
},
  "geometry": {"coordinates":[-0.944799,53.320751],"type":"Point"}
}