{
  "type": "Feature",
  "properties": {
    "addr:full":"963 Sauchiehall Street Glasgow Glasgow City G3 7TQ",
    "addr:housenumber":"963",
    "addr:postcode":"g3 7tq",
    "addr:street":"Sauchiehall Street",
    "iso:country":"GB",
    "sg:address":"963 Sauchiehall Street",
    "sg:city":"Glasgow",
    "sg:classifiers":[
        {
            "category":"Travel",
            "subcategory":"Hotels & Motels",
            "type":"Entertainment"
        }
    ],
    "sg:phone":"+44 141 339 7674",
    "sg:postcode":"G3 7TQ",
    "sg:province":"Glasgow City",
    "wof:name":"Smith's Hotel",
    "wof:placetype":"venue"
},
  "geometry": {"coordinates":[-4.2863950729,55.8660736084],"type":"Point"}
}