{
  "type": "Feature",
  "properties": {
    "iso:country":"GB",
    "sg:address":"Long Spring, 7 Porters Wood",
    "sg:city":"St Albans",
    "sg:classifiers":[
        {
            "category":"Professional",
            "subcategory":"Printing & Photocopies",
            "type":"Services"
        }
    ],
    "sg:phone":"+44 1727 867994",
    "sg:postcode":"AL3 6PE",
    "sg:province":"Hertfordshire",
    "sg:tags":[
        "printer"
    ],
    "wof:name":"D P Dee & Co Ltd",
    "wof:placetype":"venue"
},
  "geometry": {"coordinates":[-0.32755,51.771278],"type":"Point"}
}