{
  "type": "Feature",
  "properties": {
    "addr:full":"1 Holmwood, Bowdon Altrincham Cheshire WA14 2SP",
    "addr:housenumber":"1",
    "addr:postcode":"wa14 2sp",
    "addr:street":"Holmwood Bowdon",
    "iso:country":"GB",
    "sg:address":"1 Holmwood, Bowdon",
    "sg:city":"Altrincham",
    "sg:classifiers":[
        {
            "category":"Recreation",
            "type":"Entertainment"
        }
    ],
    "sg:phone":"+44 161 928 0777",
    "sg:postcode":"WA14 2SP",
    "sg:province":"Cheshire",
    "sg:tags":[
        "corporate",
        "leisure"
    ],
    "wof:name":"A.A Sporting Days",
    "wof:placetype":"venue"
},
  "geometry": {"coordinates":[-2.3702149391,53.3809394836],"type":"Point"}
}