{
  "type": "Feature",
  "properties": {
    "addr:full":"Tan Lan Holywell Denbighshire CH8 9UU",
    "addr:postcode":"ch8 9uu",
    "iso:country":"GB",
    "sg:address":"Tan Lan",
    "sg:city":"Holywell",
    "sg:classifiers":[
        {
            "category":"Retail",
            "subcategory":"Auto Repair",
            "type":"Services"
        }
    ],
    "sg:postcode":"CH8 9UU",
    "sg:province":"Denbighshire",
    "sg:tags":[
        "modification",
        "garage"
    ],
    "wof:name":"H & M Car Recoveries",
    "wof:placetype":"venue"
},
  "geometry": {"coordinates":[-3.225195,53.274548],"type":"Point"}
}