{
  "type": "Feature",
  "properties": {
    "iso:country":"GB",
    "sg:address":"Unit 3, Mushroom Farm Court, Meadowbank Way, Eastwood",
    "sg:city":"Nottingham",
    "sg:classifiers":[
        {
            "category":"Retail",
            "subcategory":"Auto Repair",
            "type":"Services"
        }
    ],
    "sg:phone":"+44 1773 710707",
    "sg:postcode":"NG16 3SR",
    "sg:province":"Derbyshire",
    "sg:tags":[
        "car",
        "specialist",
        "customizing"
    ],
    "wof:name":"City Sunroofs",
    "wof:placetype":"venue"
},
  "geometry": {"coordinates":[-1.319147,53.019722],"type":"Point"}
}