{
  "type": "Feature",
  "properties": {
    "iso:country":"GB",
    "sg:address":"Tile St",
    "sg:city":"Bury",
    "sg:classifiers":[
        {
            "category":"Retail",
            "subcategory":"Photofinishing",
            "type":"Services"
        }
    ],
    "sg:phone":"+44 161 761 1311",
    "sg:postcode":"BL9 5BR",
    "sg:province":"Lancashire",
    "sg:tags":[
        "photographic",
        "processor"
    ],
    "wof:name":"Colourcare International",
    "wof:placetype":"venue"
},
  "geometry": {"coordinates":[-2.294533968,53.5988502502],"type":"Point"}
}