{
  "type": "Feature",
  "properties": {
    "iso:country":"GB",
    "sg:address":"Nether Auchendrane",
    "sg:city":"Ayr",
    "sg:classifiers":[
        {
            "category":"Health Services",
            "subcategory":"Nursing And Care Facility",
            "type":"Services"
        }
    ],
    "sg:phone":"+44 1292 443981",
    "sg:postcode":"KA7 4EE",
    "sg:province":"South Ayrshire",
    "sg:tags":[
        "home"
    ],
    "wof:name":"Nether Auchendrane Nursing Home",
    "wof:placetype":"venue"
},
  "geometry": {"coordinates":[-4.64407,55.445068],"type":"Point"}
}