{
  "type": "Feature",
  "properties": {
    "iso:country":"GB",
    "sg:address":"Downhead Forge, St Anns Chapel",
    "sg:city":"Gunnislake",
    "sg:classifiers":[
        {
            "category":"Manufacturing",
            "subcategory":"Metals",
            "type":"Manufacturing & Wholesale Goods"
        }
    ],
    "sg:postcode":"PL18 9HA",
    "sg:province":"Cornwall",
    "sg:tags":[
        "blacksmith",
        "forgemasters"
    ],
    "wof:name":"C & N Engineering",
    "wof:placetype":"venue"
},
  "geometry": {"coordinates":[-4.2136640549,50.523891449],"type":"Point"}
}