{
  "type": "Feature",
  "properties": {
    "iso:country":"GB",
    "sg:address":"14 Spa Road",
    "sg:city":"Hockley",
    "sg:classifiers":[
        {
            "category":"Fast Food",
            "type":"Food & Drink"
        }
    ],
    "sg:phone":"+44 1702 204000",
    "sg:postcode":"SS5 4PH",
    "sg:province":"Essex",
    "sg:tags":[
        "away",
        "take"
    ],
    "wof:name":"Oriental Law Take Away",
    "wof:placetype":"venue"
},
  "geometry": {"coordinates":[0.6550459862,51.6012496948],"type":"Point"}
}