{
  "type": "Feature",
  "properties": {
    "iso:country":"GB",
    "sg:address":"16 Attwood Grove",
    "sg:city":"Sunderland",
    "sg:classifiers":[
        {
            "category":"Professional",
            "subcategory":"Detective & Security Services",
            "type":"Services"
        }
    ],
    "sg:phone":"+44 191 549 4571",
    "sg:postcode":"SR5 1RN",
    "sg:province":"Tyne and Wear",
    "sg:tags":[
        "alarm",
        "burglar",
        "system"
    ],
    "wof:name":"Elite Electrical & Security",
    "wof:placetype":"venue"
},
  "geometry": {"coordinates":[-1.3940399885,54.9197883606],"type":"Point"}
}