{
  "type": "Feature",
  "properties": {
    "iso:country":"GB",
    "sg:address":"61 Three Spires Ave",
    "sg:city":"Coventry",
    "sg:classifiers":[
        {
            "category":"Shopping",
            "subcategory":"Bicycles & Sporting Goods",
            "type":"Retail Goods"
        }
    ],
    "sg:postcode":"CV6 1JX",
    "sg:province":"Warwickshire",
    "sg:tags":[
        "dance",
        "balletwear"
    ],
    "wof:name":"Deacon,S,",
    "wof:placetype":"venue"
},
  "geometry": {"coordinates":[-1.5285600424,52.4207954407],"type":"Point"}
}