{
  "type": "Feature",
  "properties": {
    "iso:country":"GB",
    "sg:address":"38 Baldwin Way, Swindon",
    "sg:city":"Dudley",
    "sg:classifiers":[
        {
            "category":"Professional",
            "subcategory":"Detective & Security Services",
            "type":"Services"
        }
    ],
    "sg:postcode":"DY3 4PF",
    "sg:province":"Staffordshire",
    "wof:name":"Grandmaster Security Ltd.",
    "wof:placetype":"venue"
},
  "geometry": {"coordinates":[-2.20621,52.516293],"type":"Point"}
}