{
  "type": "Feature",
  "properties": {
    "addr:full":"24 Aldermans Hill London Greater London N13 4PN",
    "addr:housenumber":"24",
    "addr:postcode":"n13 4pn",
    "addr:street":"Aldermans Hill",
    "iso:country":"GB",
    "sg:address":"24 Aldermans Hill",
    "sg:city":"London",
    "sg:classifiers":[
        {
            "category":"Shopping",
            "subcategory":"News",
            "type":"Retail Goods"
        }
    ],
    "sg:phone":"+44 20 8882 8668",
    "sg:postcode":"N13 4PN",
    "sg:province":"Greater London",
    "sg:tags":[
        "newsagent"
    ],
    "wof:name":"Welcome News",
    "wof:placetype":"venue"
},
  "geometry": {"coordinates":[-0.110296,51.618237],"type":"Point"}
}