{
  "type": "Feature",
  "properties": {
    "addr:full":"12 Grange End, Smallfield Horley Surrey RH6 9NE",
    "addr:housenumber":"12",
    "addr:postcode":"rh6 9ne",
    "addr:street":"Grange End Smallfield",
    "iso:country":"GB",
    "sg:address":"12 Grange End, Smallfield",
    "sg:city":"Horley",
    "sg:classifiers":[
        {
            "category":"Shopping",
            "subcategory":"Antiques",
            "type":"Retail Goods"
        }
    ],
    "sg:phone":"+44 1342 842927",
    "sg:postcode":"RH6 9NE",
    "sg:province":"Surrey",
    "wof:name":"D T E Hussey",
    "wof:placetype":"venue"
},
  "geometry": {"coordinates":[-0.122114,51.172649],"type":"Point"}
}