{
  "type": "Feature",
  "properties": {
    "iso:country":"GB",
    "sg:address":"Southlands, 61 High Town Road",
    "sg:city":"Banbury",
    "sg:classifiers":[
        {
            "category":"Real Estate",
            "subcategory":"Architect",
            "type":"Services"
        }
    ],
    "sg:postcode":"OX16 9BE",
    "sg:province":"Oxfordshire",
    "wof:name":"David J Stewart Associates",
    "wof:placetype":"venue"
},
  "geometry": {"coordinates":[-1.3400280476,52.0611114502],"type":"Point"}
}