{
  "type": "Feature",
  "properties": {
    "addr:full":"Parc Le Breos Farm, Penmaen Swansea Swansea SA3 2HA",
    "addr:postcode":"sa3 2ha",
    "addr:street":"Parc",
    "iso:country":"GB",
    "sg:address":"Parc Le Breos Farm, Penmaen",
    "sg:city":"Swansea",
    "sg:classifiers":[
        {
            "category":"Farming",
            "subcategory":"Livestock Farm",
            "type":"Manufacturing & Wholesale Goods"
        }
    ],
    "sg:postcode":"SA3 2HA",
    "sg:province":"Swansea",
    "sg:tags":[
        "others"
    ],
    "wof:name":"E J Grove",
    "wof:placetype":"venue"
},
  "geometry": {"coordinates":[-4.1278572083,51.5756912231],"type":"Point"}
}