{
  "type": "Feature",
  "properties": {
    "addr:full":"68 Walter Road Swansea Neath Port Talbot SA1 4PT",
    "addr:housenumber":"68",
    "addr:postcode":"sa1 4pt",
    "addr:street":"Walter Road",
    "iso:country":"GB",
    "sg:address":"68 Walter Road",
    "sg:city":"Swansea",
    "sg:classifiers":[
        {
            "category":"Retail",
            "subcategory":"Veterinary Services",
            "type":"Services"
        }
    ],
    "sg:phone":"+44 1792 643906",
    "sg:postcode":"SA1 4PT",
    "sg:province":"Neath Port Talbot",
    "sg:tags":[
        "surgeon"
    ],
    "wof:name":"St.James Veterinary Group",
    "wof:placetype":"venue"
},
  "geometry": {"coordinates":[-3.9599769115,51.6185417175],"type":"Point"}
}