{
  "type": "Feature",
  "properties": {
    "addr:full":"276 Queens Road, Beeston Nottingham Nottinghamshire NG9 2BD",
    "addr:housenumber":"276",
    "addr:postcode":"ng9 2bd",
    "addr:street":"Queens Road",
    "iso:country":"GB",
    "sg:address":"276 Queens Road, Beeston",
    "sg:city":"Nottingham",
    "sg:classifiers":[
        {
            "category":"Communications",
            "type":"Services"
        }
    ],
    "sg:phone":"+44 115 925 7878",
    "sg:postcode":"NG9 2BD",
    "sg:province":"Nottinghamshire",
    "sg:tags":[
        "data",
        "network"
    ],
    "wof:name":"Polareach Data Ltd.",
    "wof:placetype":"venue"
},
  "geometry": {"coordinates":[-1.209598,52.923119],"type":"Point"}
}