{
  "type": "Feature",
  "properties": {
    "iso:country":"GB",
    "sg:address":"18 Tapenhall Road, Fernhill Heath",
    "sg:city":"Worcester",
    "sg:classifiers":[
        {
            "category":"Organizations",
            "subcategory":"Membership Organization",
            "type":"Services"
        }
    ],
    "sg:postcode":"WR3 7TR",
    "sg:province":"Worcestershire",
    "sg:tags":[
        "club"
    ],
    "wof:name":"Corporate Time Management (Worcester) Lt",
    "wof:placetype":"venue"
},
  "geometry": {"coordinates":[-2.2008900642,52.2303276062],"type":"Point"}
}