{
  "type": "Feature",
  "properties": {
    "addr:full":"Unit 4 James Howe Mill Ashton-under-lyne Greater Manchester OL6 8LF",
    "addr:housenumber":"unit 4",
    "addr:postcode":"ol6 8lf",
    "addr:street":"James Howe",
    "iso:country":"GB",
    "sg:address":"Unit 4 James Howe Mill",
    "sg:city":"Ashton-under-lyne",
    "sg:classifiers":[
        {
            "category":"Building & Trades",
            "subcategory":"Plumbing",
            "type":"Services"
        }
    ],
    "sg:phone":"+44 161 343 7922",
    "sg:postcode":"OL6 8LF",
    "sg:province":"Greater Manchester",
    "sg:tags":[
        "merchant",
        "plumbers'"
    ],
    "wof:name":"B C S Associates",
    "wof:placetype":"venue"
},
  "geometry": {"coordinates":[-2.088242,53.489239],"type":"Point"}
}