{
  "type": "Feature",
  "properties": {
    "addr:full":"1 Palace Gate London Greater London W8 5LS",
    "addr:housenumber":"1",
    "addr:postcode":"w8 5ls",
    "addr:street":"Palace Gate",
    "iso:country":"GB",
    "sg:address":"1 Palace Gate",
    "sg:city":"London",
    "sg:classifiers":[
        {
            "category":"Restaurant",
            "type":"Food & Drink"
        }
    ],
    "sg:phone":"+44 20 7581 8778",
    "sg:postcode":"W8 5LS",
    "sg:province":"Greater London",
    "sg:tags":[
        "-",
        "japanese"
    ],
    "wof:name":"Koi Restaurant",
    "wof:placetype":"venue"
},
  "geometry": {"coordinates":[-0.183799997,51.5010147095],"type":"Point"}
}