{
  "type": "Feature",
  "properties": {
    "iso:country":"GB",
    "sg:address":"61 Church Road, Gatley",
    "sg:city":"Cheadle",
    "sg:classifiers":[
        {
            "category":"Home & Garden",
            "subcategory":"Carpets & Floor Coverings",
            "type":"Retail Goods"
        }
    ],
    "sg:phone":"+44 161 428 9708",
    "sg:postcode":"SK8 4NG",
    "sg:province":"Cheshire",
    "sg:tags":[
        "carpets",
        "rug",
        "matting"
    ],
    "wof:name":"Gatley Carpets",
    "wof:placetype":"venue"
},
  "geometry": {"coordinates":[-2.2373120785,53.391292572],"type":"Point"}
}