{
  "type": "Feature",
  "properties": {
    "addr:full":"Spode Street Stoke-on-trent Staffordshire ST4 4DY",
    "addr:postcode":"st4 4dy",
    "addr:street":"Spode Street",
    "iso:country":"GB",
    "sg:address":"Spode Street",
    "sg:city":"Stoke-on-trent",
    "sg:classifiers":[
        {
            "category":"Professional",
            "subcategory":"Engineering",
            "type":"Services"
        }
    ],
    "sg:postcode":"ST4 4DY",
    "sg:province":"Staffordshire",
    "sg:tags":[
        "precision",
        "engineer"
    ],
    "wof:name":"C & K Precision Engineers Ltd.",
    "wof:placetype":"venue"
},
  "geometry": {"coordinates":[-2.185699,52.997425],"type":"Point"}
}