{
  "type": "Feature",
  "properties": {
    "iso:country":"GB",
    "sg:address":"138 Doncaster Road, Thrybergh",
    "sg:city":"Rotherham",
    "sg:classifiers":[
        {
            "category":"Professional",
            "subcategory":"Engineering",
            "type":"Services"
        }
    ],
    "sg:postcode":"S65 4BG",
    "sg:province":"South Yorkshire",
    "sg:tags":[
        "gas",
        "engineer"
    ],
    "wof:name":"K Glossop Plumbing & Electrical Services",
    "wof:placetype":"venue"
},
  "geometry": {"coordinates":[-1.295271,53.457645],"type":"Point"}
}