{
  "type": "Feature",
  "properties": {
    "iso:country":"GB",
    "sg:address":"Wardle Road",
    "sg:city":"Rochdale",
    "sg:classifiers":[
        {
            "category":"Bars & Pubs",
            "type":"Food & Drink"
        },
        {
            "category":"Community Center",
            "subcategory":"Social",
            "type":"Public Place"
        }
    ],
    "sg:phone":"+44 1706 868743",
    "sg:postcode":"OL12 9ER",
    "sg:province":"Lancashire",
    "sg:tags":[
        "pubs",
        "house",
        "inn",
        "activity"
    ],
    "wof:name":"HALF WAY HOUSE",
    "wof:placetype":"venue"
},
  "geometry": {"coordinates":[-2.132834,53.646236],"type":"Point"}
}