{
  "type": "Feature",
  "properties": {
    "iso:country":"GB",
    "sg:address":"32 Buck Street",
    "sg:city":"Bradford",
    "sg:classifiers":[
        {
            "category":"Home & Garden",
            "subcategory":"Kitchen Supply",
            "type":"Retail Goods"
        }
    ],
    "sg:phone":"+44 1274 725170",
    "sg:postcode":"BD3 9QP",
    "sg:province":"West Yorkshire",
    "sg:tags":[
        "confectioner",
        "baker",
        "bakery",
        "equipment"
    ],
    "wof:name":"Prima Continental Bakery",
    "wof:placetype":"venue"
},
  "geometry": {"coordinates":[-1.739519,53.79213],"type":"Point"}
}