{
  "type": "Feature",
  "properties": {
    "addr:full":"44 Overton Drive, Wanstead London Greater London E11 2NJ",
    "addr:housenumber":"44",
    "addr:postcode":"e11 2nj",
    "addr:street":"Overton Drive",
    "iso:country":"GB",
    "sg:address":"44 Overton Drive, Wanstead",
    "sg:city":"London",
    "sg:classifiers":[
        {
            "category":"Social Services",
            "subcategory":"Retirement Home",
            "type":"Services"
        }
    ],
    "sg:phone":"+44 20 8989 7639",
    "sg:postcode":"E11 2NJ",
    "sg:province":"Greater London",
    "sg:tags":[
        "furrier"
    ],
    "wof:name":"Lester Furs Ltd.",
    "wof:placetype":"venue"
},
  "geometry": {"coordinates":[0.02624,51.570442],"type":"Point"}
}