{
  "type": "Feature",
  "properties": {
    "addr:full":"19 Rheidol Mews London Greater London N1 8NU",
    "addr:housenumber":"19",
    "addr:postcode":"n1 8nu",
    "addr:street":"Rheidol Mews",
    "iso:country":"GB",
    "sg:address":"19 Rheidol Mews",
    "sg:city":"London",
    "sg:classifiers":[
        {
            "category":"Communications",
            "type":"Services"
        }
    ],
    "sg:phone":"+44 20 7288 8400",
    "sg:postcode":"N1 8NU",
    "sg:province":"Greater London",
    "sg:tags":[
        "audio-visual"
    ],
    "wof:name":"Illuminations (Television) Ltd.",
    "wof:placetype":"venue"
},
  "geometry": {"coordinates":[-0.098093,51.534786],"type":"Point"}
}