{
  "type": "Feature",
  "properties": {
    "iso:country":"GB",
    "sg:address":"55 Claremont Rd",
    "sg:city":"Whitley Bay",
    "sg:classifiers":[
        {
            "category":"Autos & Motor Vehicles",
            "subcategory":"Automobile Sales",
            "type":"Retail Goods"
        }
    ],
    "sg:phone":"+44 191 251 7600",
    "sg:postcode":"NE26 3TP",
    "sg:province":"Northumberland",
    "sg:tags":[
        "car"
    ],
    "wof:name":"Claremont Garage",
    "wof:placetype":"venue"
},
  "geometry": {"coordinates":[-1.4589680433,55.052696228],"type":"Point"}
}