{
  "type": "Feature",
  "properties": {
    "addr:full":"Rostock Yd, Gilwern Rd Crickhowell Monmouthshire NP8 1HW",
    "addr:postcode":"np8 1hw",
    "addr:street":"Yd Gilwern Rd",
    "iso:country":"GB",
    "sg:address":"Rostock Yd, Gilwern Rd",
    "sg:city":"Crickhowell",
    "sg:classifiers":[
        {
            "category":"Building & Trades",
            "subcategory":"Construction",
            "type":"Services"
        }
    ],
    "sg:postcode":"NP8 1HW",
    "sg:province":"Monmouthshire",
    "sg:tags":[
        "builder"
    ],
    "wof:name":"Toucanstruction Building Contractors",
    "wof:placetype":"venue"
},
  "geometry": {"coordinates":[-3.138122,51.861626],"type":"Point"}
}