{
  "type": "Feature",
  "properties": {
    "addr:full":"85 Clerkenwell Road Clerkenwell Greater London EC1R 5AR",
    "addr:housenumber":"85",
    "addr:postcode":"ec1r 5ar",
    "addr:street":"Clerkenwell Road",
    "iso:country":"GB",
    "sg:address":"85 Clerkenwell Road",
    "sg:city":"Clerkenwell",
    "sg:classifiers":[
        {
            "category":"Communications",
            "type":"Services"
        }
    ],
    "sg:phone":"+44 20 7831 3630",
    "sg:postcode":"EC1R 5AR",
    "sg:province":"Greater London",
    "sg:tags":[
        "audio-visual"
    ],
    "wof:name":"The Presentation Co",
    "wof:placetype":"venue"
},
  "geometry": {"coordinates":[-0.10986,51.521778],"type":"Point"}
}