{
  "type": "Feature",
  "properties": {
    "iso:country":"GB",
    "sg:address":"Spen Lane",
    "sg:city":"Leeds",
    "sg:classifiers":[
        {
            "category":"Bars & Pubs",
            "type":"Food & Drink"
        }
    ],
    "sg:postcode":"LS16 5EL",
    "sg:province":"West Yorkshire",
    "sg:tags":[
        "pubs",
        "inn"
    ],
    "wof:name":"Hark to Rover",
    "wof:placetype":"venue"
},
  "geometry": {"coordinates":[-1.600869,53.836121],"type":"Point"}
}