{
  "type": "Feature",
  "properties": {
    "addr:full":"1 Howe Way, Dog Lane Norwich Norfolk NR10 3DH",
    "addr:housenumber":"1",
    "addr:postcode":"nr10 3dh",
    "addr:street":"Howe Way Dog Lane",
    "iso:country":"GB",
    "sg:address":"1 Howe Way, Dog Lane",
    "sg:city":"Norwich",
    "sg:classifiers":[
        {
            "category":"Building & Trades",
            "subcategory":"Plumbing",
            "type":"Services"
        }
    ],
    "sg:postcode":"NR10 3DH",
    "sg:province":"Norfolk",
    "sg:tags":[
        "heating"
    ],
    "wof:name":"N S L Plumbing & Heating Contractors",
    "wof:placetype":"venue"
},
  "geometry": {"coordinates":[1.2948999405,52.6224937439],"type":"Point"}
}