{
  "type": "Feature",
  "properties": {
    "addr:full":"31 Grimsbury Rd Bristol City of Bristol BS15 2RZ",
    "addr:housenumber":"31",
    "addr:postcode":"bs15 2rz",
    "addr:street":"Grimsbury Rd",
    "iso:country":"GB",
    "sg:address":"31 Grimsbury Rd",
    "sg:city":"Bristol",
    "sg:classifiers":[
        {
            "category":"Professional",
            "subcategory":"Engineering",
            "type":"Services"
        }
    ],
    "sg:phone":"+44 117 967 7339",
    "sg:postcode":"BS15 2RZ",
    "sg:province":"City of Bristol",
    "sg:tags":[
        "contractor",
        "electrical",
        "engineer"
    ],
    "wof:name":"Quality Electrics",
    "wof:placetype":"venue"
},
  "geometry": {"coordinates":[-2.5914289951,51.453666687],"type":"Point"}
}