{
  "type": "Feature",
  "properties": {
    "addr:full":"33b Drummond Road, Landport Portsmouth Hampshire PO1 4HP",
    "addr:housenumber":"33b",
    "addr:postcode":"hampshire po1 4hp",
    "addr:street":"Drummond Road",
    "iso:country":"GB",
    "sg:address":"33b Drummond Road, Landport",
    "sg:city":"Portsmouth",
    "sg:classifiers":[
        {
            "category":"Wholesale",
            "subcategory":"Apparel",
            "type":"Manufacturing & Wholesale Goods"
        }
    ],
    "sg:phone":"+44 23 9279 8155",
    "sg:postcode":"PO1 4HP",
    "sg:province":"Hampshire",
    "sg:tags":[
        "babywear",
        "childrens"
    ],
    "wof:name":"The Phoenix Collection",
    "wof:placetype":"venue"
},
  "geometry": {"coordinates":[-1.082782,50.802776],"type":"Point"}
}