{
  "type": "Feature",
  "properties": {
    "addr:full":"1 Maxwell Square, Brucefield Industrial Park Livingston West Lothian EH54 9BJ",
    "addr:housenumber":"1",
    "addr:postcode":"eh54 9bj",
    "addr:street":"Maxwell Square Brucefield Industrial Park",
    "iso:country":"GB",
    "sg:address":"1 Maxwell Square, Brucefield Industrial Park",
    "sg:city":"Livingston",
    "sg:classifiers":[
        {
            "category":"Building & Trades",
            "subcategory":"Construction",
            "type":"Services"
        }
    ],
    "sg:phone":"+44 1506 412979",
    "sg:postcode":"EH54 9BJ",
    "sg:province":"West Lothian",
    "sg:tags":[
        "glazier"
    ],
    "wof:name":"Anderson Glass Ltd.",
    "wof:placetype":"venue"
},
  "geometry": {"coordinates":[-3.527933,55.867142],"type":"Point"}
}