{
  "type": "Feature",
  "properties": {
    "iso:country":"GB",
    "sg:address":"35 Westgate",
    "sg:city":"Huddersfield",
    "sg:classifiers":[
        {
            "category":"Professional",
            "subcategory":"Management & Consulting",
            "type":"Services"
        }
    ],
    "sg:postcode":"HD1 1PA",
    "sg:province":"West Yorkshire",
    "sg:tags":[
        "consultant",
        "business"
    ],
    "wof:name":"Evolve Consulting Ltd",
    "wof:placetype":"venue"
},
  "geometry": {"coordinates":[-1.78484,53.646954],"type":"Point"}
}