{
  "type": "Feature",
  "properties": {
    "addr:full":"Ingst Rd, Elberton, Olveston Bristol Gloucestershire BS35 4AW",
    "addr:postcode":"bs35 4aw",
    "addr:street":"Ingst Rd",
    "iso:country":"GB",
    "sg:address":"Ingst Rd, Elberton, Olveston",
    "sg:city":"Bristol",
    "sg:classifiers":[
        {
            "category":"Farming",
            "subcategory":"Farm",
            "type":"Manufacturing & Wholesale Goods"
        }
    ],
    "sg:postcode":"BS35 4AW",
    "sg:province":"Gloucestershire",
    "sg:tags":[
        "mixed",
        "crop"
    ],
    "wof:name":"Priestpool Farm,",
    "wof:placetype":"venue"
},
  "geometry": {"coordinates":[-2.577038,51.581676],"type":"Point"}
}