{
  "type": "Feature",
  "properties": {
    "iso:country":"GB",
    "sg:address":"4 Gravel Hill",
    "sg:city":"Wimborne",
    "sg:classifiers":[
        {
            "category":"Professional",
            "subcategory":"Management & Consulting",
            "type":"Services"
        }
    ],
    "sg:phone":"+44 1202 888967",
    "sg:postcode":"BH21 1RR",
    "sg:province":"Dorset",
    "sg:tags":[
        "marketing",
        "consultant"
    ],
    "wof:name":"Osprey Marketing",
    "wof:placetype":"venue"
},
  "geometry": {"coordinates":[-1.978957057,50.7820358276],"type":"Point"}
}