{
  "type": "Feature",
  "properties": {
    "addr:full":"168 Fawcett Road, Southsea Portsmouth Hampshire PO4 0DW",
    "addr:housenumber":"168",
    "addr:postcode":"hampshire po4 0dw",
    "addr:street":"Fawcett Road",
    "iso:country":"GB",
    "sg:address":"168 Fawcett Road, Southsea",
    "sg:city":"Portsmouth",
    "sg:classifiers":[
        {
            "category":"Professional",
            "subcategory":"Printing & Photocopies",
            "type":"Services"
        }
    ],
    "sg:phone":"+44 23 9229 6689",
    "sg:postcode":"PO4 0DW",
    "sg:province":"Hampshire",
    "sg:tags":[
        "printer"
    ],
    "wof:name":"J R Printing Services Ltd.",
    "wof:placetype":"venue"
},
  "geometry": {"coordinates":[-1.07657,50.791195],"type":"Point"}
}