{
  "type": "Feature",
  "properties": {
    "addr:full":"2 George Street Chester Cheshire CH1 3EQ",
    "addr:housenumber":"2",
    "addr:postcode":"ch1 3eq",
    "addr:street":"George Street",
    "iso:country":"GB",
    "sg:address":"2 George Street",
    "sg:city":"Chester",
    "sg:classifiers":[
        {
            "category":"Manufacturing",
            "subcategory":"Furniture",
            "type":"Manufacturing & Wholesale Goods"
        }
    ],
    "sg:postcode":"CH1 3EQ",
    "sg:province":"Cheshire",
    "sg:tags":[
        "retail"
    ],
    "wof:name":"Oriental Interiors",
    "wof:placetype":"venue"
},
  "geometry": {"coordinates":[-2.8924601078,53.1943016052],"type":"Point"}
}