{
  "type": "Feature",
  "properties": {
    "addr:full":"50 High Street Smethwick West Midlands B66 1DT",
    "addr:housenumber":"50",
    "addr:postcode":"b66 1dt",
    "addr:street":"High Street",
    "iso:country":"GB",
    "sg:address":"50 High Street",
    "sg:city":"Smethwick",
    "sg:classifiers":[
        {
            "category":"Shopping",
            "subcategory":"Crafts & Fabrics",
            "type":"Retail Goods"
        }
    ],
    "sg:phone":"+44 121 555 6017",
    "sg:postcode":"B66 1DT",
    "sg:province":"West Midlands",
    "sg:tags":[
        "shop"
    ],
    "wof:name":"Ace Business Solutions Ltd.",
    "wof:placetype":"venue"
},
  "geometry": {"coordinates":[-1.9742799997,52.49741745],"type":"Point"}
}