{
  "type": "Feature",
  "properties": {
    "addr:full":", Applethwaite Keswick Cumbria CA12 4PL",
    "addr:postcode":"ca12 4pl",
    "addr:street":"Applethwaite",
    "iso:country":"GB",
    "sg:address":", Applethwaite",
    "sg:city":"Keswick",
    "sg:classifiers":[
        {
            "category":"Travel",
            "subcategory":"Hotels & Motels",
            "type":"Entertainment"
        }
    ],
    "sg:phone":"+44 17687 72413",
    "sg:postcode":"CA12 4PL",
    "sg:province":"Cumbria",
    "wof:name":"Applethwaite Country House Hotel",
    "wof:placetype":"venue"
},
  "geometry": {"coordinates":[-3.113939,54.596611],"type":"Point"}
}