{
  "type": "Feature",
  "properties": {
    "iso:country":"GB",
    "sg:address":"P O Box 3",
    "sg:city":"Borehamwood",
    "sg:classifiers":[
        {
            "category":"Professional",
            "subcategory":"Business Services",
            "type":"Services"
        }
    ],
    "sg:phone":"+44 20 8905 2500",
    "sg:postcode":"WD6 4HD",
    "sg:province":"Hertfordshire",
    "sg:tags":[
        "answering"
    ],
    "wof:name":"Answering Service (The)",
    "wof:placetype":"venue"
},
  "geometry": {"coordinates":[-0.2757540047,51.6558189392],"type":"Point"}
}