{
  "type": "Feature",
  "properties": {
    "addr:full":"39 Anchorage Road Sutton Coldfield Staffordshire B74 2PJ",
    "addr:housenumber":"39",
    "addr:postcode":"b74 2pj",
    "addr:street":"Anchorage Road",
    "iso:country":"GB",
    "sg:address":"39 Anchorage Road",
    "sg:city":"Sutton Coldfield",
    "sg:classifiers":[
        {
            "category":"Professional",
            "subcategory":"Computer Services",
            "type":"Services"
        }
    ],
    "sg:phone":"+44 121 321 2555",
    "sg:postcode":"B74 2PJ",
    "sg:province":"Staffordshire",
    "sg:tags":[
        "development",
        "system",
        "software"
    ],
    "wof:name":"Gainsborough Software Ltd.",
    "wof:placetype":"venue"
},
  "geometry": {"coordinates":[-1.82432,52.56675],"type":"Point"}
}