{
  "type": "Feature",
  "properties": {
    "addr:full":"Harnham Garage, Newbridge Rd Salisbury Wiltshire SP2 8AA",
    "addr:postcode":"sp2 8aa",
    "addr:street":"Newbridge Rd",
    "iso:country":"GB",
    "sg:address":"Harnham Garage, Newbridge Rd",
    "sg:city":"Salisbury",
    "sg:classifiers":[
        {
            "category":"Autos & Motor Vehicles",
            "subcategory":"Automobile Sales",
            "type":"Retail Goods"
        }
    ],
    "sg:phone":"+44 1722 410077",
    "sg:postcode":"SP2 8AA",
    "sg:province":"Wiltshire",
    "sg:tags":[
        "car"
    ],
    "wof:name":"Haydon Cars Ltd",
    "wof:placetype":"venue"
},
  "geometry": {"coordinates":[-1.8208600283,51.0606193542],"type":"Point"}
}