{
  "type": "Feature",
  "properties": {
    "iso:country":"GB",
    "sg:address":"13 Highpoint Business Village, Henwood",
    "sg:city":"Ashford",
    "sg:classifiers":[
        {
            "category":"Banks & Credit Unions",
            "subcategory":"Financial Services",
            "type":"Services"
        }
    ],
    "sg:postcode":"TN24 8DH",
    "sg:province":"Kent",
    "sg:tags":[
        "adviser"
    ],
    "wof:name":"Aims Financial Ltd",
    "wof:placetype":"venue"
},
  "geometry": {"coordinates":[0.88453,51.150551],"type":"Point"}
}