{
  "type": "Feature",
  "properties": {
    "iso:country":"GB",
    "sg:address":"85-87 Murray Street",
    "sg:city":"Montrose",
    "sg:classifiers":[
        {
            "category":"Retail",
            "subcategory":"Repair Shop",
            "type":"Services"
        },
        {
            "category":"Shopping",
            "subcategory":"Comic Books",
            "type":"Retail Goods"
        }
    ],
    "sg:phone":"+44 1674 673977",
    "sg:postcode":"DD10 8JZ",
    "sg:province":"Aberdeenshire",
    "sg:tags":[
        "jeweller",
        "clocks",
        "watch"
    ],
    "wof:name":"B Crozier",
    "wof:placetype":"venue"
},
  "geometry": {"coordinates":[-2.4674479961,56.7145233154],"type":"Point"}
}