{
  "type": "Feature",
  "properties": {
    "addr:full":"13-17 Station Road, Queensferry Deeside Flintshire CH5 1SU",
    "addr:housenumber":"13-17",
    "addr:postcode":"ch5 1su",
    "addr:street":"Station Road",
    "iso:country":"GB",
    "sg:address":"13-17 Station Road, Queensferry",
    "sg:city":"Deeside",
    "sg:classifiers":[
        {
            "category":"Shopping",
            "subcategory":"News",
            "type":"Retail Goods"
        }
    ],
    "sg:postcode":"CH5 1SU",
    "sg:province":"Flintshire",
    "sg:tags":[
        "newsagent"
    ],
    "wof:name":"I J Pierce & Son",
    "wof:placetype":"venue"
},
  "geometry": {"coordinates":[-3.023029,53.206665],"type":"Point"}
}