{
  "type": "Feature",
  "properties": {
    "iso:country":"GB",
    "sg:address":"351 Stourbridge Road",
    "sg:city":"Bromsgrove",
    "sg:classifiers":[
        {
            "category":"Building & Trades",
            "subcategory":"Cleaning & Sanitation",
            "type":"Services"
        },
        {
            "category":"Retail",
            "subcategory":"Laundry & Dry Cleaning",
            "type":"Services"
        }
    ],
    "sg:postcode":"B61 0BN",
    "sg:province":"Worcestershire",
    "sg:tags":[
        "commercial",
        "alteration"
    ],
    "wof:name":"Buckley Cleaning Services",
    "wof:placetype":"venue"
},
  "geometry": {"coordinates":[-2.063772,52.3577],"type":"Point"}
}