{
  "type": "Feature",
  "properties": {
    "iso:country":"GB",
    "sg:address":"295-297 Church Street",
    "sg:city":"Blackpool",
    "sg:classifiers":[
        {
            "category":"Professional",
            "subcategory":"Accounting & Tax Preparation",
            "type":"Services"
        }
    ],
    "sg:phone":"+44 1253 622385",
    "sg:postcode":"FY1 3PJ",
    "sg:province":"Lancashire",
    "sg:tags":[
        "accountant"
    ],
    "wof:name":"Caine Carter & Watson",
    "wof:placetype":"venue"
},
  "geometry": {"coordinates":[-3.039508,53.81847],"type":"Point"}
}