{
  "type": "Feature",
  "properties": {
    "iso:country":"GB",
    "sg:address":"New Inn Barn, Clapham",
    "sg:city":"Lancaster",
    "sg:classifiers":[
        {
            "category":"Transit Center",
            "subcategory":"Freight",
            "type":"Transportation"
        }
    ],
    "sg:postcode":"LA2 8EH",
    "sg:province":"Lancashire",
    "sg:tags":[
        "shop",
        "craft",
        "centre"
    ],
    "wof:name":"Richard Sexton & Co.",
    "wof:placetype":"venue"
},
  "geometry": {"coordinates":[-2.392048,54.117367],"type":"Point"}
}