{
  "type": "Feature",
  "properties": {
    "addr:full":"Burwood House, 14 -16 Caxton Street London Greater London SW1H 0QT",
    "addr:housenumber":"14 -16",
    "addr:postcode":"sw1h 0qt",
    "addr:street":"Caxton Street",
    "iso:country":"GB",
    "sg:address":"Burwood House, 14 -16 Caxton Street",
    "sg:city":"London",
    "sg:classifiers":[
        {
            "category":"Insurance",
            "subcategory":"Insurance Agent",
            "type":"Services"
        }
    ],
    "sg:phone":"+44 20 7222 7933",
    "sg:postcode":"SW1H 0QT",
    "sg:province":"Greater London",
    "wof:name":"Municipal Mutual Insurance Ltd.",
    "wof:placetype":"venue"
},
  "geometry": {"coordinates":[-0.1359599978,51.498588562],"type":"Point"}
}