{
  "type": "Feature",
  "properties": {
    "addr:full":"Oak Villa, Thorne Rd Doncaster Lincolnshire DN9 3AX",
    "addr:postcode":"dn9 3ax",
    "addr:street":"Thorne Rd",
    "iso:country":"GB",
    "sg:address":"Oak Villa, Thorne Rd",
    "sg:city":"Doncaster",
    "sg:classifiers":[
        {
            "category":"Freight",
            "type":"Transportation"
        }
    ],
    "sg:phone":"+44 1302 770199",
    "sg:postcode":"DN9 3AX",
    "sg:province":"Lincolnshire",
    "sg:tags":[
        "haulage",
        "road"
    ],
    "wof:name":"Peter Alan Isle Haulage",
    "wof:placetype":"venue"
},
  "geometry": {"coordinates":[-0.9846299887,53.5000686646],"type":"Point"}
}