{
  "type": "Feature",
  "properties": {
    "iso:country":"GB",
    "sg:address":"Whitchurch Road, Broomhall",
    "sg:city":"Nantwich",
    "sg:classifiers":[
        {
            "category":"Retail",
            "subcategory":"Auto Repair",
            "type":"Services"
        }
    ],
    "sg:postcode":"CW5 8BZ",
    "sg:province":"Cheshire",
    "sg:tags":[
        "modification",
        "garage"
    ],
    "wof:name":"Paul Evans",
    "wof:placetype":"venue"
},
  "geometry": {"coordinates":[-2.5574638844,53.0245819092],"type":"Point"}
}