{
  "type": "Feature",
  "properties": {
    "addr:full":"Raven Meadows Shrewsbury Shropshire SY1 1PL",
    "addr:postcode":"sy1 1pl",
    "addr:street":"Raven Meadows",
    "iso:country":"GB",
    "sg:address":"Raven Meadows",
    "sg:city":"Shrewsbury",
    "sg:classifiers":[
        {
            "category":"Bars & Pubs",
            "subcategory":"Nightclub",
            "type":"Food & Drink"
        }
    ],
    "sg:phone":"+44 1743 358786",
    "sg:postcode":"SY1 1PL",
    "sg:province":"Shropshire",
    "sg:tags":[
        "club",
        "night"
    ],
    "wof:name":"Park Lane Night Club",
    "wof:placetype":"venue"
},
  "geometry": {"coordinates":[-2.752369,52.711224],"type":"Point"}
}