{
  "type": "Feature",
  "properties": {
    "addr:full":"42 Alexandra Road Blackpool Lancashire FY1 6BU",
    "addr:housenumber":"42",
    "addr:postcode":"fy1 6bu",
    "addr:street":"Alexandra Road",
    "iso:country":"GB",
    "sg:address":"42 Alexandra Road",
    "sg:city":"Blackpool",
    "sg:classifiers":[
        {
            "category":"Travel",
            "subcategory":"Hotels & Motels",
            "type":"Entertainment"
        },
        {
            "category":"Bars & Pubs",
            "subcategory":"Hookah Bar",
            "type":"Food & Drink"
        }
    ],
    "sg:phone":"+44 1253 346183",
    "sg:postcode":"FY1 6BU",
    "sg:province":"Lancashire",
    "sg:tags":[
        "self",
        "holiday",
        "catering"
    ],
    "wof:name":"Greenbank Holiday Flats",
    "wof:placetype":"venue"
},
  "geometry": {"coordinates":[-3.052306,53.801491],"type":"Point"}
}