{
  "type": "Feature",
  "properties": {
    "addr:full":"97 Northbrook St Newbury Berkshire RG14 1AA",
    "addr:housenumber":"97",
    "addr:postcode":"rg14 1aa",
    "addr:street":"Northbrook St",
    "iso:country":"GB",
    "sg:address":"97 Northbrook St",
    "sg:city":"Newbury",
    "sg:classifiers":[
        {
            "category":"Banks & Credit Unions",
            "subcategory":"Bank",
            "type":"Services"
        }
    ],
    "sg:phone":"+44 1635 46970",
    "sg:postcode":"RG14 1AA",
    "sg:province":"Berkshire",
    "wof:name":"Woolwich plc",
    "wof:placetype":"venue"
},
  "geometry": {"coordinates":[-1.3246190548,51.4040718079],"type":"Point"}
}