{
  "type": "Feature",
  "properties": {
    "addr:full":"4 Elm Terrace, Constantine Road London Greater London NW3 2LL",
    "addr:housenumber":"4",
    "addr:postcode":"nw3 2ll",
    "addr:street":"Elm Terrace Constantine Road",
    "iso:country":"GB",
    "sg:address":"4 Elm Terrace, Constantine Road",
    "sg:city":"London",
    "sg:classifiers":[
        {
            "category":"Health Services",
            "subcategory":"Dentist",
            "type":"Services"
        }
    ],
    "sg:phone":"+44 20 7284 2827",
    "sg:postcode":"NW3 2LL",
    "sg:province":"Greater London",
    "wof:name":"Hampstead Orthodontic Practice",
    "wof:placetype":"venue"
},
  "geometry": {"coordinates":[-0.16455,51.554169],"type":"Point"}
}