{
  "type": "Feature",
  "properties": {
    "iso:country":"GB",
    "sg:address":"68 Stoke Green",
    "sg:city":"Coventry",
    "sg:classifiers":[
        {
            "category":"Retail",
            "subcategory":"Driving School",
            "type":"Services"
        }
    ],
    "sg:phone":"+44 24 7645 5707",
    "sg:postcode":"CV3 1FP",
    "sg:province":"Warwickshire",
    "wof:name":"A-z School Of Motoring",
    "wof:placetype":"venue"
},
  "geometry": {"coordinates":[-1.48153,52.403423],"type":"Point"}
}