{
  "type": "Feature",
  "properties": {
    "iso:country":"GB",
    "sg:address":"100 The Parade",
    "sg:city":"Leamington Spa",
    "sg:classifiers":[
        {
            "category":"Shopping",
            "subcategory":"Gifts & Souvenirs",
            "type":"Retail Goods"
        }
    ],
    "sg:phone":"+44 1926 888809",
    "sg:postcode":"CV32 4AQ",
    "sg:province":"Warwickshire",
    "sg:tags":[
        "shop"
    ],
    "wof:name":"Past Times",
    "wof:placetype":"venue"
},
  "geometry": {"coordinates":[-1.535846,52.290909],"type":"Point"}
}