{
  "type": "Feature",
  "properties": {
    "iso:country":"GB",
    "sg:address":"Unit 28d St Bryde Street, East Kilbride",
    "sg:city":"Glasgow",
    "sg:classifiers":[
        {
            "category":"Autos & Motor Vehicles",
            "subcategory":"Auto Supplies",
            "type":"Retail Goods"
        },
        {
            "category":"Retail",
            "subcategory":"Auto Repair",
            "type":"Services"
        }
    ],
    "sg:phone":"+44 1355 242121",
    "sg:postcode":"G74 4HQ",
    "sg:province":"South Lanarkshire",
    "sg:tags":[
        "modification",
        "garage",
        "windscreen"
    ],
    "wof:name":"Euro Windscreens",
    "wof:placetype":"venue"
},
  "geometry": {"coordinates":[-4.173491,55.766613],"type":"Point"}
}