{
  "type": "Feature",
  "properties": {
    "iso:country":"GB",
    "sg:address":"2 Leighton Rd",
    "sg:city":"Wolverhampton",
    "sg:classifiers":[
        {
            "category":"Personal",
            "type":"Services"
        }
    ],
    "sg:phone":"+44 1902 330764",
    "sg:postcode":"WV4 4AR",
    "sg:province":"Staffordshire",
    "sg:tags":[
        "wedding"
    ],
    "wof:name":"Celebration Cakes",
    "wof:placetype":"venue"
},
  "geometry": {"coordinates":[-2.1526210308,52.5665168762],"type":"Point"}
}