{
  "type": "Feature",
  "properties": {
    "iso:country":"GB",
    "sg:address":"Springfield, Troutbeck",
    "sg:city":"Penrith",
    "sg:classifiers":[
        {
            "category":"Bars & Pubs",
            "type":"Food & Drink"
        }
    ],
    "sg:phone":"+44 17684 83231",
    "sg:postcode":"CA11 0SG",
    "sg:province":"Cumbria",
    "sg:tags":[
        "pubs",
        "inn"
    ],
    "wof:name":"The Sportsmans Inn",
    "wof:placetype":"venue"
},
  "geometry": {"coordinates":[-2.947805,54.635651],"type":"Point"}
}