{
  "type": "Feature",
  "properties": {
    "addr:full":"21 Tynewydd Road Barry The Vale of Glamorgan CF62 8HB",
    "addr:housenumber":"21",
    "addr:postcode":"cf62 8hb",
    "addr:street":"Tynewydd Road;Vale",
    "iso:country":"GB",
    "sg:address":"21 Tynewydd Road",
    "sg:city":"Barry",
    "sg:classifiers":[
        {
            "category":"Professional",
            "subcategory":"Lawyer & Legal Services",
            "type":"Services"
        }
    ],
    "sg:phone":"+44 1446 721000",
    "sg:postcode":"CF62 8HB",
    "sg:province":"The Vale of Glamorgan",
    "sg:tags":[
        "solicitor"
    ],
    "sg:website":"http://passmores.com",
    "wof:name":"Passmores Lewis & Jacobs",
    "wof:placetype":"venue"
},
  "geometry": {"coordinates":[-3.2679159641,51.4073143005],"type":"Point"}
}