{
  "type": "Feature",
  "properties": {
    "iso:country":"GB",
    "sg:address":"Unit 9, Hartley Business Park, Selborne",
    "sg:city":"Alton",
    "sg:classifiers":[
        {
            "category":"Building & Trades",
            "subcategory":"Construction",
            "type":"Services"
        }
    ],
    "sg:phone":"+44 1420 511271",
    "sg:postcode":"GU34 3HS",
    "sg:province":"Hampshire",
    "sg:tags":[
        "builder"
    ],
    "wof:name":"Ketley Construction Ltd.",
    "wof:placetype":"venue"
},
  "geometry": {"coordinates":[-0.944309,51.098274],"type":"Point"}
}