{
  "type": "Feature",
  "properties": {
    "iso:country":"GB",
    "sg:address":"Normanton Park, Warwick Avenue",
    "sg:city":"Derby",
    "sg:classifiers":[
        {
            "category":"Community Center",
            "type":"Public Place"
        }
    ],
    "sg:phone":"+44 1332 764245",
    "sg:postcode":"DE23 8DA",
    "sg:province":"Derbyshire",
    "sg:tags":[
        "centre"
    ],
    "wof:name":"Normanton Activity Centre",
    "wof:placetype":"venue"
},
  "geometry": {"coordinates":[-1.48937,52.901791],"type":"Point"}
}