{
  "type": "Feature",
  "properties": {
    "addr:full":"9 Bridge Street Kirkwall Orkney Islands KW15 1HR",
    "addr:housenumber":"9",
    "addr:postcode":"kw15 1hr",
    "addr:street":"Bridge Street",
    "iso:country":"GB",
    "sg:address":"9 Bridge Street",
    "sg:city":"Kirkwall",
    "sg:classifiers":[
        {
            "category":"Shopping",
            "subcategory":"Used Merchandise",
            "type":"Retail Goods"
        }
    ],
    "sg:postcode":"KW15 1HR",
    "sg:province":"Orkney Islands",
    "sg:tags":[
        "furniture"
    ],
    "wof:name":"The Garage Store",
    "wof:placetype":"venue"
},
  "geometry": {"coordinates":[-2.958586,58.984406],"type":"Point"}
}