{
  "type": "Feature",
  "properties": {
    "iso:country":"GB",
    "sg:address":"6 Potter Walk",
    "sg:city":"Hartlepool",
    "sg:classifiers":[
        {
            "category":"Building & Trades",
            "subcategory":"Construction",
            "type":"Services"
        }
    ],
    "sg:phone":"+44 1429 866380",
    "sg:postcode":"TS24 8DY",
    "sg:province":"Durham",
    "sg:tags":[
        "tiling",
        "contractor"
    ],
    "wof:name":"Cleveland Ceramics",
    "wof:placetype":"venue"
},
  "geometry": {"coordinates":[-1.217594,54.691448],"type":"Point"}
}