{
  "type": "Feature",
  "properties": {
    "addr:full":"12 Wood Street Lytham St. Annes Lancashire FY8 1QS",
    "addr:housenumber":"12",
    "addr:postcode":"fy8 1qs",
    "addr:street":"Wood Street",
    "iso:country":"GB",
    "sg:address":"12 Wood Street",
    "sg:city":"Lytham St. Annes",
    "sg:classifiers":[
        {
            "category":"Home & Garden",
            "subcategory":"Furniture",
            "type":"Retail Goods"
        }
    ],
    "sg:phone":"+44 1253 789411",
    "sg:postcode":"FY8 1QS",
    "sg:province":"Lancashire",
    "wof:name":"Michael Dykes",
    "wof:placetype":"venue"
},
  "geometry": {"coordinates":[-3.028553,53.751633],"type":"Point"}
}