{
  "type": "Feature",
  "properties": {
    "iso:country":"GB",
    "sg:address":"The Dutch House, 307-308 High Holborn",
    "sg:city":"London",
    "sg:classifiers":[
        {
            "category":"Professional",
            "subcategory":"Employment Agencies",
            "type":"Services"
        }
    ],
    "sg:postcode":"WC1V 7LS",
    "sg:province":"Greater London",
    "sg:tags":[
        "agricultural",
        "advice"
    ],
    "wof:name":"Hotraco B V",
    "wof:placetype":"venue"
},
  "geometry": {"coordinates":[-0.239846,51.548859],"type":"Point"}
}