{
  "type": "Feature",
  "properties": {
    "addr:full":"The Rectory, Meavy La Yelverton Devon PL20 6AE",
    "addr:postcode":"pl20 6ae",
    "addr:street":"Meavy La Yelverton",
    "iso:country":"GB",
    "sg:address":"The Rectory, Meavy La",
    "sg:city":"Yelverton",
    "sg:classifiers":[
        {
            "category":"Place Of Worship",
            "type":"Public Place"
        }
    ],
    "sg:phone":"+44 1822 852362",
    "sg:postcode":"PL20 6AE",
    "sg:province":"Devon",
    "wof:name":"St Pauls Church Of England",
    "wof:placetype":"venue"
},
  "geometry": {"coordinates":[-4.0878591537,50.4923782349],"type":"Point"}
}