{
  "type": "Feature",
  "properties": {
    "addr:full":"Clayhill, Southend Reading Berkshire RG7 6JR",
    "addr:postcode":"rg7 6jr",
    "iso:country":"GB",
    "sg:address":"Clayhill, Southend",
    "sg:city":"Reading",
    "sg:classifiers":[
        {
            "category":"Retail",
            "subcategory":"Repair Shop",
            "type":"Services"
        }
    ],
    "sg:postcode":"RG7 6JR",
    "sg:province":"Berkshire",
    "sg:tags":[
        "upholsterer"
    ],
    "wof:name":"Kennet Upholstery",
    "wof:placetype":"venue"
},
  "geometry": {"coordinates":[-1.1471639872,51.4315910339],"type":"Point"}
}