{
  "type": "Feature",
  "properties": {
    "iso:country":"GB",
    "sg:address":"19 Northgate Street",
    "sg:city":"Chester",
    "sg:classifiers":[
        {
            "category":"Shopping",
            "subcategory":"Books",
            "type":"Retail Goods"
        }
    ],
    "sg:phone":"+44 1244 346976",
    "sg:postcode":"CH1 2HA",
    "sg:province":"Cheshire",
    "sg:tags":[
        "bookseller"
    ],
    "wof:name":"The Works",
    "wof:placetype":"venue"
},
  "geometry": {"coordinates":[-2.891826,53.190968],"type":"Point"}
}