{
  "type": "Feature",
  "properties": {
    "addr:full":"5 Aldershot Road Fleet Hampshire GU52 8NG",
    "addr:housenumber":"5",
    "addr:postcode":"gu52 8ng",
    "addr:street":"Aldershot Road",
    "iso:country":"GB",
    "sg:address":"5 Aldershot Road",
    "sg:city":"Fleet",
    "sg:classifiers":[
        {
            "category":"Shopping",
            "subcategory":"Florist",
            "type":"Retail Goods"
        }
    ],
    "sg:postcode":"GU52 8NG",
    "sg:province":"Hampshire",
    "wof:name":"J & L Flowers",
    "wof:placetype":"venue"
},
  "geometry": {"coordinates":[-0.8411120176,51.2765083313],"type":"Point"}
}