{
  "type": "Feature",
  "properties": {
    "iso:country":"GB",
    "sg:address":"8 The Haven Millbank Road, Kingsnorth",
    "sg:city":"Ashford",
    "sg:classifiers":[
        {
            "category":"Building & Trades",
            "subcategory":"Plumbing",
            "type":"Services"
        }
    ],
    "sg:phone":"+44 1233 633832",
    "sg:postcode":"TN23 3NA",
    "sg:province":"Kent",
    "sg:tags":[
        "heating"
    ],
    "wof:name":"M & S Refrigeration",
    "wof:placetype":"venue"
},
  "geometry": {"coordinates":[0.85098,51.125881],"type":"Point"}
}