{
  "type": "Feature",
  "properties": {
    "iso:country":"GB",
    "sg:address":"114 High Street",
    "sg:city":"Shoreham-by-sea",
    "sg:classifiers":[
        {
            "category":"Shopping",
            "subcategory":"News",
            "type":"Retail Goods"
        }
    ],
    "sg:phone":"+44 1273 453170",
    "sg:postcode":"BN43 5DB",
    "sg:province":"West Sussex",
    "sg:tags":[
        "newsagent"
    ],
    "wof:name":"Norfolk Newsagents",
    "wof:placetype":"venue"
},
  "geometry": {"coordinates":[-0.2784009874,50.8325386047],"type":"Point"}
}