{
  "type": "Feature",
  "properties": {
    "iso:country":"GB",
    "sg:address":"1-2 St Pirans Road",
    "sg:city":"Perranporth",
    "sg:classifiers":[
        {
            "category":"Shopping",
            "subcategory":"Clothing, Apparel, & Fashions",
            "type":"Retail Goods"
        }
    ],
    "sg:phone":"+44 1872 571997",
    "sg:postcode":"TR6 0BL",
    "sg:province":"Cornwall",
    "sg:tags":[
        "clothing"
    ],
    "wof:name":"Aloha Uk Ltd.",
    "wof:placetype":"venue"
},
  "geometry": {"coordinates":[-5.1541838646,50.3448829651],"type":"Point"}
}