{
  "type": "Feature",
  "properties": {
    "addr:full":"78 Market Street Manchester Greater Manchester M1 1PD",
    "addr:housenumber":"78",
    "addr:postcode":"m1 1pd",
    "addr:street":"Market Street",
    "iso:country":"GB",
    "sg:address":"78 Market Street",
    "sg:city":"Manchester",
    "sg:classifiers":[
        {
            "category":"Communications",
            "type":"Services"
        }
    ],
    "sg:phone":"+44 161 839 8228",
    "sg:postcode":"M1 1PD",
    "sg:province":"Greater Manchester",
    "sg:tags":[
        "telecommunication"
    ],
    "wof:name":"Vodafone Retail Ltd.",
    "wof:placetype":"venue"
},
  "geometry": {"coordinates":[-2.240464,53.482265],"type":"Point"}
}