{
  "type": "Feature",
  "properties": {
    "addr:full":"Unit E1, The Pallasades North Walk Birmingham West Midlands B31 3JB",
    "addr:housenumber":"e1",
    "addr:postcode":"b31 3jb",
    "addr:street":"The Pallasades North Walk",
    "iso:country":"GB",
    "sg:address":"Unit E1, The Pallasades North Walk",
    "sg:city":"Birmingham",
    "sg:classifiers":[
        {
            "category":"Shopping",
            "subcategory":"Jewelry",
            "type":"Retail Goods"
        }
    ],
    "sg:phone":"+44 121 643 6172",
    "sg:postcode":"B31 3JB",
    "sg:province":"West Midlands",
    "sg:tags":[
        "gold",
        "silversmith"
    ],
    "wof:name":"Tie Rack",
    "wof:placetype":"venue"
},
  "geometry": {"coordinates":[-1.9558900595,52.4035797119],"type":"Point"}
}