{
  "type": "Feature",
  "properties": {
    "iso:country":"GB",
    "sg:address":"East Street, Bishops Tawton",
    "sg:city":"Barnstaple",
    "sg:classifiers":[
        {
            "category":"Government",
            "subcategory":"Post Office",
            "type":"Public Place"
        }
    ],
    "sg:postcode":"EX32 0DQ",
    "sg:province":"Devon",
    "wof:name":"Bishops Tawton Post Office",
    "wof:placetype":"venue"
},
  "geometry": {"coordinates":[-4.0452189445,51.0517311096],"type":"Point"}
}