{
  "type": "Feature",
  "properties": {
    "addr:full":"Warwickshire Equestrian Centre, Kenilworth Road, Balsall Common Coventry Warwickshire CV7 7HD",
    "addr:postcode":"cv7 7hd",
    "addr:street":"Kenilworth Road",
    "iso:country":"GB",
    "sg:address":"Warwickshire Equestrian Centre, Kenilworth Road, Balsall Common",
    "sg:city":"Coventry",
    "sg:classifiers":[
        {
            "category":"Professional",
            "type":"Services"
        }
    ],
    "sg:phone":"+44 1676 529100",
    "sg:postcode":"CV7 7HD",
    "sg:province":"Warwickshire",
    "sg:tags":[
        "exhibition"
    ],
    "wof:name":"Sovereign Exhibitions Ltd.",
    "wof:placetype":"venue"
},
  "geometry": {"coordinates":[-1.6461340189,52.3858985901],"type":"Point"}
}