{
  "type": "Feature",
  "properties": {
    "addr:full":", Holt Wimborne Dorset BH21 7DJ",
    "addr:postcode":"bh21 7dj",
    "iso:country":"GB",
    "sg:address":", Holt",
    "sg:city":"Wimborne",
    "sg:classifiers":[
        {
            "category":"Bars & Pubs",
            "type":"Food & Drink"
        }
    ],
    "sg:phone":"+44 1202 883029",
    "sg:postcode":"BH21 7DJ",
    "sg:province":"Dorset",
    "sg:tags":[
        "pubs",
        "inn"
    ],
    "wof:name":"The Old Inn",
    "wof:placetype":"venue"
},
  "geometry": {"coordinates":[-1.9598740339,50.8342781067],"type":"Point"}
}