{
  "type": "Feature",
  "properties": {
    "addr:full":"1022 Chester Road, Erdington Birmingham West Midlands B24 0LL",
    "addr:housenumber":"1022",
    "addr:postcode":"b24 0ll",
    "addr:street":"Chester Road",
    "iso:country":"GB",
    "sg:address":"1022 Chester Road, Erdington",
    "sg:city":"Birmingham",
    "sg:classifiers":[
        {
            "category":"Home & Garden",
            "subcategory":"Building Materials",
            "type":"Retail Goods"
        }
    ],
    "sg:postcode":"B24 0LL",
    "sg:province":"West Midlands",
    "sg:tags":[
        "plaster",
        "ware"
    ],
    "wof:name":"Art Plas",
    "wof:placetype":"venue"
},
  "geometry": {"coordinates":[-1.809594,52.524464],"type":"Point"}
}