{
  "type": "Feature",
  "properties": {
    "iso:country":"GB",
    "sg:address":"290 Barnacres Road, Bennetts End",
    "sg:city":"Hemel Hempstead",
    "sg:classifiers":[
        {
            "category":"Professional",
            "subcategory":"Engineering",
            "type":"Services"
        }
    ],
    "sg:phone":"+44 1442 244757",
    "sg:postcode":"HP3 8JR",
    "sg:province":"Hertfordshire",
    "sg:tags":[
        "contractor",
        "electrical",
        "engineer"
    ],
    "wof:name":"David Dalton",
    "wof:placetype":"venue"
},
  "geometry": {"coordinates":[-0.450465,51.736317],"type":"Point"}
}