{
  "type": "Feature",
  "properties": {
    "addr:full":"46 Beckfield Lane York North Yorkshire YO26 5RJ",
    "addr:housenumber":"46",
    "addr:postcode":"yo26 5rj",
    "addr:street":"Beckfield Lane",
    "iso:country":"GB",
    "sg:address":"46 Beckfield Lane",
    "sg:city":"York",
    "sg:classifiers":[
        {
            "category":"Building & Trades",
            "subcategory":"Construction",
            "type":"Services"
        }
    ],
    "sg:phone":"+44 1904 795788",
    "sg:postcode":"YO26 5RJ",
    "sg:province":"North Yorkshire",
    "sg:tags":[
        "decorator",
        "painter"
    ],
    "wof:name":"T.H Ledgeway",
    "wof:placetype":"venue"
},
  "geometry": {"coordinates":[-1.1352280378,53.9598693848],"type":"Point"}
}