{
  "type": "Feature",
  "properties": {
    "iso:country":"GB",
    "sg:address":"214 Penarth Road",
    "sg:city":"Cardiff",
    "sg:classifiers":[
        {
            "category":"Shopping",
            "type":"Retail Goods"
        }
    ],
    "sg:phone":"+44 29 2038 3535",
    "sg:postcode":"CF1 7NN",
    "sg:province":"Cardiff",
    "sg:tags":[
        "part",
        "accessory"
    ],
    "wof:name":"Halfords",
    "wof:placetype":"venue"
},
  "geometry": {"coordinates":[-3.191905,51.466232],"type":"Point"}
}