{
  "type": "Feature",
  "properties": {
    "iso:country":"GB",
    "sg:address":"14 Eglinton St",
    "sg:city":"Irvine",
    "sg:classifiers":[
        {
            "category":"Real Estate",
            "subcategory":"Architect",
            "type":"Services"
        }
    ],
    "sg:postcode":"KA12 8AS",
    "sg:province":"North Ayrshire",
    "wof:name":"Dunlop,R L,",
    "wof:placetype":"venue"
},
  "geometry": {"coordinates":[-4.6684379578,55.6170425415],"type":"Point"}
}