{
  "type": "Feature",
  "properties": {
    "addr:full":"1-5 Maeshyfryd Road Holyhead Isle of Anglesey LL65 2AL",
    "addr:housenumber":"1-5",
    "addr:postcode":"ll65 2al",
    "addr:street":"Maeshyfryd Road",
    "iso:country":"GB",
    "sg:address":"1-5 Maeshyfryd Road",
    "sg:city":"Holyhead",
    "sg:classifiers":[
        {
            "category":"Personal",
            "subcategory":"Beauty Salon",
            "type":"Services"
        },
        {
            "category":"Personal",
            "subcategory":"Barber",
            "type":"Services"
        }
    ],
    "sg:phone":"+44 1407 764697",
    "sg:postcode":"LL65 2AL",
    "sg:province":"Isle of Anglesey",
    "sg:tags":[
        "unisex",
        "hairdresser"
    ],
    "wof:name":"Gayles Hairdressing",
    "wof:placetype":"venue"
},
  "geometry": {"coordinates":[-4.6358761787,53.3071784973],"type":"Point"}
}