{
  "type": "Feature",
  "properties": {
    "iso:country":"GB",
    "sg:address":"31 New Bond Street",
    "sg:city":"London",
    "sg:classifiers":[
        {
            "category":"Museum",
            "subcategory":"Art Museum",
            "type":"Entertainment"
        }
    ],
    "sg:phone":"+44 20 7491 9911",
    "sg:postcode":"W1S 2RW",
    "sg:province":"Greater London",
    "sg:tags":[
        "gallery"
    ],
    "wof:name":"Marianne Holtermann",
    "wof:placetype":"venue"
},
  "geometry": {"coordinates":[-0.143523,51.511608],"type":"Point"}
}