{
  "type": "Feature",
  "properties": {
    "addr:full":"8 Barrington Gate Spalding Cambridgeshire PE12 7DA",
    "addr:housenumber":"8",
    "addr:postcode":"pe12 7da",
    "addr:street":"Barrington Gate Spalding",
    "iso:country":"GB",
    "sg:address":"8 Barrington Gate",
    "sg:city":"Spalding",
    "sg:classifiers":[
        {
            "category":"Food & Beverages",
            "subcategory":"Meat & Fish",
            "type":"Retail Goods"
        }
    ],
    "sg:postcode":"PE12 7DA",
    "sg:province":"Cambridgeshire",
    "sg:tags":[
        "chip"
    ],
    "wof:name":"Nicks Plaice",
    "wof:placetype":"venue"
},
  "geometry": {"coordinates":[0.016903,52.8029518127],"type":"Point"}
}