{
  "type": "Feature",
  "properties": {
    "iso:country":"GB",
    "sg:address":"Eredine, Retinue Row, Methven",
    "sg:city":"Perth",
    "sg:classifiers":[
        {
            "category":"Freight",
            "type":"Transportation"
        }
    ],
    "sg:postcode":"PH1 3PF",
    "sg:province":"Perth and Kinross",
    "sg:tags":[
        "haulage",
        "road"
    ],
    "wof:name":"Douglas Brown & Partners",
    "wof:placetype":"venue"
},
  "geometry": {"coordinates":[-3.578338,56.41581],"type":"Point"}
}