{
  "type": "Feature",
  "properties": {
    "iso:country":"GB",
    "sg:address":"Glenroyd House, 96-98 St James Road",
    "sg:city":"Northampton",
    "sg:classifiers":[
        {
            "category":"Banks & Credit Unions",
            "subcategory":"Financial Services",
            "type":"Services"
        }
    ],
    "sg:postcode":"NN5 5LG",
    "sg:province":"Northamptonshire",
    "sg:tags":[
        "consultant"
    ],
    "wof:name":"C A Distribution & Finance Ltd",
    "wof:placetype":"venue"
},
  "geometry": {"coordinates":[-0.914353,52.238663],"type":"Point"}
}