{
  "type": "Feature",
  "properties": {
    "addr:full":"13 Sansome Place Worcester Worcestershire WR1 1UA",
    "addr:housenumber":"13",
    "addr:postcode":"wr1 1ua",
    "addr:street":"Sansome Place",
    "iso:country":"GB",
    "sg:address":"13 Sansome Place",
    "sg:city":"Worcester",
    "sg:classifiers":[
        {
            "category":"Real Estate",
            "subcategory":"Surveying",
            "type":"Services"
        }
    ],
    "sg:postcode":"WR1 1UA",
    "sg:province":"Worcestershire",
    "sg:tags":[
        "building",
        "surveyor"
    ],
    "wof:name":"Gerald Collins",
    "wof:placetype":"venue"
},
  "geometry": {"coordinates":[-2.2178790569,52.1956443787],"type":"Point"}
}