{
  "type": "Feature",
  "properties": {
    "iso:country":"GB",
    "sg:address":"91 Kirkintilloch Rd",
    "sg:city":"Glasgow",
    "sg:classifiers":[
        {
            "category":"Health Services",
            "subcategory":"Doctor",
            "type":"Services"
        }
    ],
    "sg:phone":"+44 141 772 8952",
    "sg:postcode":"G64 2LS",
    "sg:province":"East Dunbartonshire",
    "sg:tags":[
        "practitioners"
    ],
    "wof:name":"Wilson, M",
    "wof:placetype":"venue"
},
  "geometry": {"coordinates":[-4.224169,55.905991],"type":"Point"}
}