{
  "type": "Feature",
  "properties": {
    "iso:country":"GB",
    "sg:address":"Chiltern Drive, Ackworth",
    "sg:city":"Pontefract",
    "sg:classifiers":[
        {
            "category":"Social Services",
            "subcategory":"Adult Care",
            "type":"Services"
        },
        {
            "category":"Government",
            "subcategory":"Office",
            "type":"Public Place"
        }
    ],
    "sg:phone":"+44 1977 723150",
    "sg:postcode":"WF7 7DW",
    "sg:province":"West Yorkshire",
    "sg:tags":[
        "housing",
        "local",
        "sheltered"
    ],
    "wof:name":"Chiltern Court Sheltered Housing",
    "wof:placetype":"venue"
},
  "geometry": {"coordinates":[-1.336199,53.639835],"type":"Point"}
}