{
  "type": "Feature",
  "properties": {
    "iso:country":"GB",
    "sg:address":"4b Albany Road, Chorlton",
    "sg:city":"Manchester",
    "sg:classifiers":[
        {
            "category":"Military Area",
            "subcategory":"Coast Guard Base",
            "type":"Public Place"
        }
    ],
    "sg:phone":"+44 161 861 9056",
    "sg:postcode":"M21 0AW",
    "sg:province":"Cheshire",
    "sg:tags":[
        "supplier",
        "meter"
    ],
    "wof:name":"Autometers Exports Ltd.",
    "wof:placetype":"venue"
},
  "geometry": {"coordinates":[-2.276144,53.444561],"type":"Point"}
}