{
  "type": "Feature",
  "properties": {
    "iso:country":"GB",
    "sg:address":"P D Centre, Mold Road, Cefn-y-bedd",
    "sg:city":"Wrexham",
    "sg:classifiers":[
        {
            "category":"Manufacturing",
            "subcategory":"Petroleum Products",
            "type":"Manufacturing & Wholesale Goods"
        }
    ],
    "sg:phone":"+44 1978 761076",
    "sg:postcode":"LL12 9UL",
    "sg:province":"Wrexham",
    "sg:tags":[
        "double",
        "glazing"
    ],
    "wof:name":"Tower Windows",
    "wof:placetype":"venue"
},
  "geometry": {"coordinates":[-3.031069,53.097919],"type":"Point"}
}