{
  "type": "Feature",
  "properties": {
    "iso:country":"GB",
    "sg:address":"11-12 Buckingham Gate",
    "sg:city":"Westminster",
    "sg:classifiers":[
        {
            "category":"Communications",
            "type":"Services"
        }
    ],
    "sg:phone":"+44 20 7976 5900",
    "sg:postcode":"SW1E 6LB",
    "sg:province":"Greater London",
    "sg:tags":[
        "broadcasting"
    ],
    "wof:name":"Worldvision Enterprises (UK) Ltd",
    "wof:placetype":"venue"
},
  "geometry": {"coordinates":[-0.140968,51.500137],"type":"Point"}
}