{
  "type": "Feature",
  "properties": {
    "iso:country":"GB",
    "sg:address":"41 Hailgate, Howden",
    "sg:city":"Goole",
    "sg:classifiers":[
        {
            "category":"Health Services",
            "subcategory":"Nursing And Care Facility",
            "type":"Services"
        }
    ],
    "sg:postcode":"DN14 7SL",
    "sg:province":"East Riding of Yorkshire",
    "sg:tags":[
        "home"
    ],
    "wof:name":"Hailgate House Nursing Home",
    "wof:placetype":"venue"
},
  "geometry": {"coordinates":[-0.864016,53.746475],"type":"Point"}
}