{
  "type": "Feature",
  "properties": {
    "addr:full":"119 Mill Gate Newark Nottinghamshire NG24 4UA",
    "addr:housenumber":"119",
    "addr:postcode":"ng24 4ua",
    "addr:street":"Mill Gate",
    "iso:country":"GB",
    "sg:address":"119 Mill Gate",
    "sg:city":"Newark",
    "sg:classifiers":[
        {
            "category":"Industrial Area",
            "type":"Public Place"
        }
    ],
    "sg:phone":"+44 1454 317448",
    "sg:postcode":"NG24 4UA",
    "sg:province":"Nottinghamshire",
    "sg:tags":[
        "consultant"
    ],
    "wof:name":"Strategic Business Consultancy Ltd",
    "wof:placetype":"venue"
},
  "geometry": {"coordinates":[-0.8192890286,53.0721244812],"type":"Point"}
}