{
  "type": "Feature",
  "properties": {
    "iso:country":"GB",
    "sg:address":"Beehive Lane",
    "sg:city":"Welwyn Garden City",
    "sg:classifiers":[
        {
            "category":"Arena",
            "subcategory":"Stadium",
            "type":"Entertainment"
        },
        {
            "category":"Arena",
            "subcategory":"Sports Club",
            "type":"Entertainment"
        }
    ],
    "sg:phone":"+44 1707 323970",
    "sg:postcode":"AL7 4BP",
    "sg:province":"Hertfordshire",
    "sg:tags":[
        "ground"
    ],
    "wof:name":"King George V Playing Fields",
    "wof:placetype":"venue"
},
  "geometry": {"coordinates":[-0.18244,51.789848],"type":"Point"}
}