{
  "type": "Feature",
  "properties": {
    "addr:full":"Water Works Cottage, Brooke Road, Braunston Oakham Leicestershire LE15 8UJ",
    "addr:postcode":"le15 8uj",
    "addr:street":"Brooke Road",
    "iso:country":"GB",
    "sg:address":"Water Works Cottage, Brooke Road, Braunston",
    "sg:city":"Oakham",
    "sg:classifiers":[
        {
            "category":"Farming",
            "subcategory":"Farm",
            "type":"Manufacturing & Wholesale Goods"
        }
    ],
    "sg:postcode":"LE15 8UJ",
    "sg:province":"Leicestershire",
    "sg:tags":[
        "hatchery"
    ],
    "wof:name":"Brand's Fish Farm",
    "wof:placetype":"venue"
},
  "geometry": {"coordinates":[-0.769656,52.653179],"type":"Point"}
}