{
  "type": "Feature",
  "properties": {
    "iso:country":"GB",
    "sg:address":"Uniter House, 3 Radford Way",
    "sg:city":"Billericay",
    "sg:classifiers":[
        {
            "category":"Shopping",
            "subcategory":"Stationery & Office Supplies",
            "type":"Retail Goods"
        }
    ],
    "sg:phone":"+44 870 400 2000",
    "sg:postcode":"CM12 0DX",
    "sg:province":"Essex",
    "sg:tags":[
        "machine",
        "facsimile"
    ],
    "wof:name":"National Fax Service Ltd.",
    "wof:placetype":"venue"
},
  "geometry": {"coordinates":[0.419593,51.629078],"type":"Point"}
}