{
  "type": "Feature",
  "properties": {
    "addr:full":"White Waltham Airfield Maidenhead Berkshire SL6 3NJ",
    "addr:postcode":"sl6 3nj",
    "addr:street":"White",
    "iso:country":"GB",
    "sg:address":"White Waltham Airfield",
    "sg:city":"Maidenhead",
    "sg:classifiers":[
        {
            "category":"Education",
            "subcategory":"Special Training",
            "type":"Public Place"
        }
    ],
    "sg:phone":"+44 1628 823272",
    "sg:postcode":"SL6 3NJ",
    "sg:province":"Berkshire",
    "sg:tags":[
        "school",
        "flying"
    ],
    "wof:name":"White Waltham Airfield Ltd.",
    "wof:placetype":"venue"
},
  "geometry": {"coordinates":[-0.777337,51.484779],"type":"Point"}
}