{
  "type": "Feature",
  "properties": {
    "iso:country":"GB",
    "sg:address":"Chalfont Clo, Lower Earley",
    "sg:city":"Reading",
    "sg:classifiers":[
        {
            "category":"Community Center",
            "subcategory":"Youth",
            "type":"Public Place"
        }
    ],
    "sg:phone":"+44 118 931 2951",
    "sg:postcode":"RG6 5HZ",
    "sg:province":"Berkshire",
    "sg:tags":[
        "organisation",
        "centre"
    ],
    "wof:name":"Earley Centre Point Youth & Community Centre",
    "wof:placetype":"venue"
},
  "geometry": {"coordinates":[-0.9342589974,51.4259681702],"type":"Point"}
}