{
  "type": "Feature",
  "properties": {
    "addr:full":"424-426 Green Lane Ilford Essex IG3 9LA",
    "addr:housenumber":"424-426",
    "addr:postcode":"ig3 9la",
    "addr:street":"Green Lane",
    "iso:country":"GB",
    "sg:address":"424-426 Green Lane",
    "sg:city":"Ilford",
    "sg:classifiers":[
        {
            "category":"Building & Trades",
            "subcategory":"Plumbing",
            "type":"Services"
        },
        {
            "category":"Home & Garden",
            "subcategory":"Hardware",
            "type":"Retail Goods"
        }
    ],
    "sg:phone":"+44 20 8590 6749",
    "sg:postcode":"IG3 9LA",
    "sg:province":"Essex",
    "sg:tags":[
        "merchant",
        "plumber",
        "plumbers'"
    ],
    "wof:name":"S K S (Ilford) Ltd",
    "wof:placetype":"venue"
},
  "geometry": {"coordinates":[0.0994710028,51.5609397888],"type":"Point"}
}