{
  "type": "Feature",
  "properties": {
    "iso:country":"GB",
    "sg:address":"Gosling Hill, Red Row, Beamish",
    "sg:city":"Stanley",
    "sg:classifiers":[
        {
            "category":"Autos & Motor Vehicles",
            "subcategory":"Automobile Sales",
            "type":"Retail Goods"
        }
    ],
    "sg:phone":"+44 1207 280476",
    "sg:postcode":"DH9 0RW",
    "sg:province":"Durham",
    "sg:tags":[
        "car",
        "specialist",
        "sales",
        "classic"
    ],
    "wof:name":"The Aston Workshop",
    "wof:placetype":"venue"
},
  "geometry": {"coordinates":[-1.690338,54.872379],"type":"Point"}
}