{
  "type": "Feature",
  "properties": {
    "addr:full":"2 Swanmeadow Mills, Swanmeadow Road Wigan Lancashire WN3 5BD",
    "addr:housenumber":"2",
    "addr:postcode":"wn3 5bd",
    "addr:street":"Swanmeadow Mills Swanmeadow Road",
    "iso:country":"GB",
    "sg:address":"2 Swanmeadow Mills, Swanmeadow Road",
    "sg:city":"Wigan",
    "sg:classifiers":[
        {
            "category":"Home & Garden",
            "subcategory":"Hardware",
            "type":"Retail Goods"
        }
    ],
    "sg:phone":"+44 1942 236888",
    "sg:postcode":"WN3 5BD",
    "sg:province":"Lancashire",
    "sg:tags":[
        "product",
        "wire",
        "electrical"
    ],
    "wof:name":"Wire Mesh Fabrications Ltd.",
    "wof:placetype":"venue"
},
  "geometry": {"coordinates":[-2.63801,53.540359],"type":"Point"}
}