{
  "type": "Feature",
  "properties": {
    "addr:full":"Suite 6, 10 Hatherley Gro London Greater London W2 5RB",
    "addr:housenumber":"suite 6 10",
    "addr:postcode":"w2 5rb",
    "iso:country":"GB",
    "sg:address":"Suite 6, 10 Hatherley Gro",
    "sg:city":"London",
    "sg:classifiers":[
        {
            "category":"Professional",
            "subcategory":"Research",
            "type":"Services"
        }
    ],
    "sg:postcode":"W2 5RB",
    "sg:province":"Greater London",
    "sg:tags":[
        "market"
    ],
    "wof:name":"Strategic Business Planning Consultants",
    "wof:placetype":"venue"
},
  "geometry": {"coordinates":[-0.1893250048,51.5160713196],"type":"Point"}
}