{
  "type": "Feature",
  "properties": {
    "addr:full":"Acme Road, Rear Of Leavesden Road Watford Hertfordshire WD24 5EP",
    "addr:postcode":"wd24 5ep",
    "addr:street":"Acme Road;Leavesden Road",
    "iso:country":"GB",
    "sg:address":"Acme Road, Rear Of Leavesden Road",
    "sg:city":"Watford",
    "sg:classifiers":[
        {
            "category":"Autos & Motor Vehicles",
            "subcategory":"Auto Supplies",
            "type":"Retail Goods"
        }
    ],
    "sg:phone":"+44 1923 241045",
    "sg:postcode":"WD24 5EP",
    "sg:province":"Hertfordshire",
    "sg:tags":[
        "tyre"
    ],
    "wof:name":"Fairway Tyre Service",
    "wof:placetype":"venue"
},
  "geometry": {"coordinates":[-0.403009,51.671829],"type":"Point"}
}