{
  "type": "Feature",
  "properties": {
    "addr:full":"Unit 22 W & G Estate, West Challow Wantage Berkshire OX12 9TF",
    "addr:housenumber":"unit 22",
    "addr:postcode":"ox12 9tf",
    "addr:street":"W & G Estate",
    "iso:country":"GB",
    "sg:address":"Unit 22 W & G Estate, West Challow",
    "sg:city":"Wantage",
    "sg:classifiers":[
        {
            "category":"Professional",
            "subcategory":"Engineering",
            "type":"Services"
        }
    ],
    "sg:phone":"+44 1235 760435",
    "sg:postcode":"OX12 9TF",
    "sg:province":"Berkshire",
    "sg:tags":[
        "precision",
        "engineer"
    ],
    "wof:name":"Ridgeway Co-Extrustion Technology Ltd.",
    "wof:placetype":"venue"
},
  "geometry": {"coordinates":[-1.46353,51.597542],"type":"Point"}
}