{
  "type": "Feature",
  "properties": {
    "addr:full":"8 Cumberland Pk London Greater London W3 6SY",
    "addr:housenumber":"8",
    "addr:postcode":"w3 6sy",
    "addr:street":"Cumberland Pk",
    "iso:country":"GB",
    "sg:address":"8 Cumberland Pk",
    "sg:city":"London",
    "sg:classifiers":[
        {
            "category":"Building & Trades",
            "subcategory":"Construction",
            "type":"Services"
        }
    ],
    "sg:postcode":"W3 6SY",
    "sg:province":"Greater London",
    "sg:tags":[
        "builder"
    ],
    "wof:name":"Shields,Frank,",
    "wof:placetype":"venue"
},
  "geometry": {"coordinates":[-0.2656469941,51.5114898682],"type":"Point"}
}