{
  "type": "Feature",
  "properties": {
    "iso:country":"GB",
    "sg:address":"Po Box 596",
    "sg:city":"Ascot",
    "sg:classifiers":[
        {
            "category":"Banks & Credit Unions",
            "subcategory":"Financial Services",
            "type":"Services"
        }
    ],
    "sg:postcode":"SL5 7TD",
    "sg:province":"Berkshire",
    "sg:tags":[
        "consultant"
    ],
    "wof:name":"Cashmaster Plc",
    "wof:placetype":"venue"
},
  "geometry": {"coordinates":[-0.665919,51.41185],"type":"Point"}
}