{
  "type": "Feature",
  "properties": {
    "addr:full":"15-19 Falsgrave Road Scarborough North Yorkshire YO12 5EA",
    "addr:housenumber":"15-19",
    "addr:postcode":"yo12 5ea",
    "addr:street":"Falsgrave Road",
    "iso:country":"GB",
    "sg:address":"15-19 Falsgrave Road",
    "sg:city":"Scarborough",
    "sg:classifiers":[
        {
            "category":"Manufacturing",
            "subcategory":"Tools & Machinery",
            "type":"Manufacturing & Wholesale Goods"
        },
        {
            "category":"Insurance",
            "subcategory":"Insurance Agent",
            "type":"Services"
        }
    ],
    "sg:phone":"+44 1723 361385",
    "sg:postcode":"YO12 5EA",
    "sg:province":"North Yorkshire",
    "sg:tags":[
        "society",
        "broker",
        "friendly"
    ],
    "wof:name":"Co-Operative Insurance Society Ltd.",
    "wof:placetype":"venue"
},
  "geometry": {"coordinates":[-0.4103190005,54.2781562805],"type":"Point"}
}