{
  "type": "Feature",
  "properties": {
    "addr:full":"Woolhall Farm, Wykeham Spalding Cambridgeshire PE12 6HW",
    "addr:postcode":"pe12 6hw",
    "addr:street":"Spalding",
    "iso:country":"GB",
    "sg:address":"Woolhall Farm, Wykeham",
    "sg:city":"Spalding",
    "sg:classifiers":[
        {
            "category":"Farming",
            "subcategory":"Farm",
            "type":"Manufacturing & Wholesale Goods"
        }
    ],
    "sg:phone":"+44 1775 725041",
    "sg:postcode":"PE12 6HW",
    "sg:province":"Cambridgeshire",
    "sg:tags":[
        "mixed",
        "crop"
    ],
    "wof:name":"Van Geest LW (Farms) Ltd",
    "wof:placetype":"venue"
},
  "geometry": {"coordinates":[-0.108599,52.81855],"type":"Point"}
}