{
  "type": "Feature",
  "properties": {
    "iso:country":"GB",
    "sg:address":"25 Calgary Cresent",
    "sg:city":"Folkestone",
    "sg:classifiers":[
        {
            "category":"Building & Trades",
            "subcategory":"Construction",
            "type":"Services"
        }
    ],
    "sg:phone":"+44 1303 258192",
    "sg:postcode":"CT19 6JD",
    "sg:province":"Kent",
    "sg:tags":[
        "builder"
    ],
    "wof:name":"G J N Builders",
    "wof:placetype":"venue"
},
  "geometry": {"coordinates":[1.18536,51.09338],"type":"Point"}
}