{
  "type": "Feature",
  "properties": {
    "iso:country":"GB",
    "sg:address":"Macmillan Drive",
    "sg:city":"Eastbourne",
    "sg:classifiers":[
        {
            "category":"Education",
            "subcategory":"School",
            "type":"Public Place"
        }
    ],
    "sg:phone":"+44 1323 728901",
    "sg:postcode":"BN21 1SN",
    "sg:province":"East Sussex",
    "sg:tags":[
        "local",
        "authority"
    ],
    "wof:name":"Motcombe County Infants School",
    "wof:placetype":"venue"
},
  "geometry": {"coordinates":[0.259369,50.778671],"type":"Point"}
}