{
  "type": "Feature",
  "properties": {
    "iso:country":"GB",
    "sg:address":"30 Palace Gardens Terrace",
    "sg:city":"London",
    "sg:classifiers":[
        {
            "category":"Professional",
            "subcategory":"Management & Consulting",
            "type":"Services"
        }
    ],
    "sg:phone":"+44 20 7610 6633",
    "sg:postcode":"W8 4RP",
    "sg:province":"Greater London",
    "sg:tags":[
        "consultant",
        "business"
    ],
    "wof:name":"Harker Management Services",
    "wof:placetype":"venue"
},
  "geometry": {"coordinates":[-0.1922180057,51.5062561035],"type":"Point"}
}