{
  "type": "Feature",
  "properties": {
    "addr:full":"Webbs Heath Farm Workshops, Siston La Bristol City of Bristol BS15 4QT",
    "addr:postcode":"bs15 4qt",
    "addr:street":"Heath;Siston La",
    "iso:country":"GB",
    "sg:address":"Webbs Heath Farm Workshops, Siston La",
    "sg:city":"Bristol",
    "sg:classifiers":[
        {
            "category":"Home & Garden",
            "subcategory":"Household Appliances",
            "type":"Retail Goods"
        }
    ],
    "sg:phone":"+44 117 976 1760",
    "sg:postcode":"BS15 4QT",
    "sg:province":"City of Bristol",
    "sg:tags":[
        "electrical"
    ],
    "wof:name":"Gilbert & Cole",
    "wof:placetype":"venue"
},
  "geometry": {"coordinates":[-2.49523,51.47049],"type":"Point"}
}