{
  "type": "Feature",
  "properties": {
    "iso:country":"GB",
    "sg:address":"College Street",
    "sg:city":"Millport",
    "sg:classifiers":[
        {
            "category":"Place Of Worship",
            "type":"Public Place"
        }
    ],
    "sg:phone":"+44 1475 530353",
    "sg:postcode":"KA28 0HE",
    "sg:province":"North Ayrshire",
    "wof:name":"The Cathedral Of The Isle",
    "wof:placetype":"venue"
},
  "geometry": {"coordinates":[-4.926011,55.753803],"type":"Point"}
}