{
  "type": "Feature",
  "properties": {
    "addr:full":"Burrows Terrace Burry Port Carmarthenshire SA16 0NH",
    "addr:postcode":"sa16 0nh",
    "addr:street":"Burrows Terrace",
    "iso:country":"GB",
    "sg:address":"Burrows Terrace",
    "sg:city":"Burry Port",
    "sg:classifiers":[
        {
            "category":"Professional",
            "subcategory":"Engineering",
            "type":"Services"
        }
    ],
    "sg:phone":"+44 1554 833358",
    "sg:postcode":"SA16 0NH",
    "sg:province":"Carmarthenshire",
    "wof:name":"Spencer Davies Engineering Ltd.",
    "wof:placetype":"venue"
},
  "geometry": {"coordinates":[-4.2413740158,51.6824913025],"type":"Point"}
}