{
  "type": "Feature",
  "properties": {
    "addr:full":"104 Lambley Lane, Burton Joyce Nottingham Nottinghamshire NG14 5BL",
    "addr:housenumber":"104",
    "addr:postcode":"ng14 5bl",
    "addr:street":"Lambley Lane",
    "iso:country":"GB",
    "sg:address":"104 Lambley Lane, Burton Joyce",
    "sg:city":"Nottingham",
    "sg:classifiers":[
        {
            "category":"Real Estate",
            "subcategory":"Architect",
            "type":"Services"
        }
    ],
    "sg:phone":"+44 115 931 2602",
    "sg:postcode":"NG14 5BL",
    "sg:province":"Nottinghamshire",
    "wof:name":"Trevor Muir",
    "wof:placetype":"venue"
},
  "geometry": {"coordinates":[-1.0471580029,52.9908714294],"type":"Point"}
}