{
  "type": "Feature",
  "properties": {
    "iso:country":"GB",
    "sg:address":", Ansley",
    "sg:city":"Nuneaton",
    "sg:classifiers":[
        {
            "category":"Landmark",
            "subcategory":"Tourist Attraction",
            "type":"Public Place"
        }
    ],
    "sg:phone":"+44 24 7639 8334",
    "sg:postcode":"CV10 0QU",
    "sg:province":"Leicestershire",
    "sg:tags":[
        "interest"
    ],
    "wof:name":"Hoar Park Childrens Farm",
    "wof:placetype":"venue"
},
  "geometry": {"coordinates":[-1.529704,52.53714],"type":"Point"}
}