{
  "type": "Feature",
  "properties": {
    "iso:country":"GB",
    "sg:address":"134 High Street",
    "sg:city":"Burford",
    "sg:classifiers":[
        {
            "category":"Professional",
            "type":"Services"
        },
        {
            "category":"Professional",
            "subcategory":"Art Services",
            "type":"Services"
        }
    ],
    "sg:phone":"+44 1993 822833",
    "sg:postcode":"OX18 4QU",
    "sg:province":"Gloucestershire",
    "sg:tags":[
        "interior",
        "furnishers",
        "designer"
    ],
    "wof:name":"Wright Inn Interiors",
    "wof:placetype":"venue"
},
  "geometry": {"coordinates":[-1.637114,51.807175],"type":"Point"}
}