{
  "type": "Feature",
  "properties": {
    "iso:country":"GB",
    "sg:address":"Langrick Road, Hubberts Bridge",
    "sg:city":"Boston",
    "sg:classifiers":[
        {
            "category":"Community Center",
            "type":"Public Place"
        }
    ],
    "sg:phone":"+44 1205 290450",
    "sg:postcode":"PE20 3SG",
    "sg:province":"Lincolnshire",
    "sg:tags":[
        "centre"
    ],
    "wof:name":"Hubberts Bridge Community Centre",
    "wof:placetype":"venue"
},
  "geometry": {"coordinates":[-0.1063140035,52.991569519],"type":"Point"}
}