{
  "type": "Feature",
  "properties": {
    "addr:full":"High Street, Twyford Winchester Hampshire SO21 1RF",
    "addr:postcode":"so21 1rf",
    "addr:street":"High Street",
    "iso:country":"GB",
    "sg:address":"High Street, Twyford",
    "sg:city":"Winchester",
    "sg:classifiers":[
        {
            "category":"Personal",
            "subcategory":"Beauty Salon",
            "type":"Services"
        }
    ],
    "sg:postcode":"SO21 1RF",
    "sg:province":"Hampshire",
    "sg:tags":[
        "unisex",
        "hairdresser"
    ],
    "wof:name":"Marika Raymonde",
    "wof:placetype":"venue"
},
  "geometry": {"coordinates":[-1.3127390146,51.0235900879],"type":"Point"}
}