{
  "type": "Feature",
  "properties": {
    "iso:country":"GB",
    "sg:address":"Rawcliffe House, 30 Marathon Place, Moss Side Industrial Estate",
    "sg:city":"Preston",
    "sg:classifiers":[
        {
            "category":"Professional",
            "subcategory":"Advertising",
            "type":"Services"
        }
    ],
    "sg:phone":"+44 1772 621803",
    "sg:postcode":"PR26 7QN",
    "sg:province":"Lancashire",
    "wof:name":"Local Map Co. Ltd.",
    "wof:placetype":"venue"
},
  "geometry": {"coordinates":[-2.724463,53.702339],"type":"Point"}
}