{
  "type": "Feature",
  "properties": {
    "addr:full":"Howe Lane Farm, Near White Waltham Maidenhead Berkshire SL6 3JP",
    "addr:postcode":"sl6 3jp",
    "addr:street":"Howe Lane;Near White",
    "iso:country":"GB",
    "sg:address":"Howe Lane Farm, Near White Waltham",
    "sg:city":"Maidenhead",
    "sg:classifiers":[
        {
            "category":"Building & Trades",
            "subcategory":"Construction",
            "type":"Services"
        }
    ],
    "sg:postcode":"SL6 3JP",
    "sg:province":"Berkshire",
    "sg:tags":[
        "joiner",
        "carpenter"
    ],
    "wof:name":"Badcock,Alan,",
    "wof:placetype":"venue"
},
  "geometry": {"coordinates":[-0.7613379955,51.4754867554],"type":"Point"}
}