{
  "type": "Feature",
  "properties": {
    "iso:country":"GB",
    "sg:address":"140 Plummers Hill",
    "sg:city":"Bristol",
    "sg:classifiers":[
        {
            "category":"Banks & Credit Unions",
            "subcategory":"Financial Services",
            "type":"Services"
        }
    ],
    "sg:phone":"+44 117 952 2200",
    "sg:postcode":"BS5 7JJ",
    "sg:province":"City of Bristol",
    "sg:tags":[
        "adviser"
    ],
    "wof:name":"Arnold & Taylor Financial Services",
    "wof:placetype":"venue"
},
  "geometry": {"coordinates":[-2.5411009789,51.4651756287],"type":"Point"}
}