{
  "type": "Feature",
  "properties": {
    "addr:full":"1 Church Path Saffron Walden Cambridgeshire CB10 1JP",
    "addr:housenumber":"1",
    "addr:postcode":"cb10 1jp",
    "addr:street":"Church Path",
    "iso:country":"GB",
    "sg:address":"1 Church Path",
    "sg:city":"Saffron Walden",
    "sg:classifiers":[
        {
            "category":"Shopping",
            "subcategory":"Books",
            "type":"Retail Goods"
        }
    ],
    "sg:phone":"+44 1799 521909",
    "sg:postcode":"CB10 1JP",
    "sg:province":"Cambridgeshire",
    "wof:name":"Feather Press Ltd.",
    "wof:placetype":"venue"
},
  "geometry": {"coordinates":[0.2385720015,52.0237083435],"type":"Point"}
}