{
  "type": "Feature",
  "properties": {
    "addr:full":"451 Kents Hill Road North, Thundersley Benfleet Essex SS7 4AD",
    "addr:housenumber":"451",
    "addr:postcode":"ss7 4ad",
    "addr:street":"Kents Hill Road North Thundersley Benfleet",
    "iso:country":"GB",
    "sg:address":"451 Kents Hill Road North, Thundersley",
    "sg:city":"Benfleet",
    "sg:classifiers":[
        {
            "category":"Building & Trades",
            "subcategory":"Construction",
            "type":"Services"
        }
    ],
    "sg:phone":"+44 1268 794672",
    "sg:postcode":"SS7 4AD",
    "sg:province":"Essex",
    "sg:tags":[
        "conversion",
        "loft"
    ],
    "wof:name":"Robinson & Lyons",
    "wof:placetype":"venue"
},
  "geometry": {"coordinates":[0.563740015,51.5677452087],"type":"Point"}
}