{
  "type": "Feature",
  "properties": {
    "addr:full":"The Pavilion, Vaughan Road Torquay Devon TQ2 5EQ",
    "addr:postcode":"tq2 5eq",
    "addr:street":"Vaughan Road",
    "iso:country":"GB",
    "sg:address":"The Pavilion, Vaughan Road",
    "sg:city":"Torquay",
    "sg:classifiers":[
        {
            "category":"Deli",
            "type":"Food & Drink"
        }
    ],
    "sg:phone":"+44 1803 201087",
    "sg:postcode":"TQ2 5EQ",
    "sg:province":"Devon",
    "sg:tags":[
        "delicatessen"
    ],
    "wof:name":"le Petit Gourmet",
    "wof:placetype":"venue"
},
  "geometry": {"coordinates":[-3.5434639454,50.4671936035],"type":"Point"}
}