{
  "type": "Feature",
  "properties": {
    "iso:country":"GB",
    "sg:address":"112 Homerton High St",
    "sg:city":"Hackney",
    "sg:classifiers":[
        {
            "category":"Autos & Motor Vehicles",
            "subcategory":"Fuel & Gas Station",
            "type":"Retail Goods"
        }
    ],
    "sg:phone":"+44 20 8985 4766",
    "sg:postcode":"E9 6JF",
    "sg:province":"Greater London",
    "sg:tags":[
        "petrol",
        "filling"
    ],
    "wof:name":"Rosny Services",
    "wof:placetype":"venue"
},
  "geometry": {"coordinates":[-0.04522,51.547935],"type":"Point"}
}