{
  "type": "Feature",
  "properties": {
    "addr:full":"2 Restmor Way, Hackbridge Wallington Surrey SM6 7AH",
    "addr:housenumber":"2",
    "addr:postcode":"sm6 7ah",
    "addr:street":"Restmor Way",
    "iso:country":"GB",
    "sg:address":"2 Restmor Way, Hackbridge",
    "sg:city":"Wallington",
    "sg:classifiers":[
        {
            "category":"Professional",
            "subcategory":"Art Services",
            "type":"Services"
        }
    ],
    "sg:phone":"+44 20 8669 2264",
    "sg:postcode":"SM6 7AH",
    "sg:province":"Surrey",
    "sg:tags":[
        "consultant",
        "design"
    ],
    "wof:name":"Inchhead Ltd",
    "wof:placetype":"venue"
},
  "geometry": {"coordinates":[-0.158003,51.376183],"type":"Point"}
}