{
  "type": "Feature",
  "properties": {
    "iso:country":"GB",
    "sg:address":"117 Whitechapel Road",
    "sg:city":"London",
    "sg:classifiers":[
        {
            "category":"Professional",
            "subcategory":"Lawyer & Legal Services",
            "type":"Services"
        }
    ],
    "sg:phone":"+44 20 7247 8458",
    "sg:postcode":"E1 1DT",
    "sg:province":"Greater London",
    "sg:tags":[
        "solicitor"
    ],
    "wof:name":"Malik & Micheal Solicitors",
    "wof:placetype":"venue"
},
  "geometry": {"coordinates":[-0.066145,51.517685],"type":"Point"}
}