{
  "type": "Feature",
  "properties": {
    "addr:full":"Marjorie Hinde House, 61 Bethel Street Norwich Norfolk NR2 1NR",
    "addr:housenumber":"61",
    "addr:postcode":"nr2 1nr",
    "addr:street":"Bethel Street",
    "iso:country":"GB",
    "sg:address":"Marjorie Hinde House, 61 Bethel Street",
    "sg:city":"Norwich",
    "sg:classifiers":[
        {
            "category":"Organizations",
            "subcategory":"Non-profit Organization",
            "type":"Services"
        }
    ],
    "sg:phone":"+44 1603 625982",
    "sg:postcode":"NR2 1NR",
    "sg:province":"Norfolk",
    "sg:tags":[
        "organisation",
        "voluntary",
        "charity"
    ],
    "wof:name":"Ywca",
    "wof:placetype":"venue"
},
  "geometry": {"coordinates":[1.288175,52.628822],"type":"Point"}
}