{
  "type": "Feature",
  "properties": {
    "addr:full":"43a Reading Road, Chineham Basingstoke Hampshire RG24 8LT",
    "addr:housenumber":"43a",
    "addr:postcode":"rg24 8lt",
    "addr:street":"Reading Road",
    "iso:country":"GB",
    "sg:address":"43a Reading Road, Chineham",
    "sg:city":"Basingstoke",
    "sg:classifiers":[
        {
            "category":"Manufacturing",
            "subcategory":"Tools & Machinery",
            "type":"Manufacturing & Wholesale Goods"
        },
        {
            "category":"Communications",
            "type":"Services"
        }
    ],
    "sg:phone":"+44 1256 321059",
    "sg:postcode":"RG24 8LT",
    "sg:province":"Hampshire",
    "sg:tags":[
        "tv",
        "radio",
        "video",
        "power"
    ],
    "wof:name":"Tiltmans",
    "wof:placetype":"venue"
},
  "geometry": {"coordinates":[-1.05917,51.28928],"type":"Point"}
}