{
  "type": "Feature",
  "properties": {
    "iso:country":"GB",
    "sg:address":"16 Bondgate Without",
    "sg:city":"Alnwick",
    "sg:classifiers":[
        {
            "category":"Professional",
            "subcategory":"Accounting & Tax Preparation",
            "type":"Services"
        }
    ],
    "sg:postcode":"NE66 1PP",
    "sg:province":"Northumberland",
    "sg:tags":[
        "accountant",
        "chartered"
    ],
    "wof:name":"Nickalls & Co.",
    "wof:placetype":"venue"
},
  "geometry": {"coordinates":[-1.701766,55.411945],"type":"Point"}
}