{
  "type": "Feature",
  "properties": {
    "addr:full":"West End, Summerbridge Harrogate North Yorkshire HG3 4BA",
    "addr:postcode":"hg3 4ba",
    "iso:country":"GB",
    "sg:address":"West End, Summerbridge",
    "sg:city":"Harrogate",
    "sg:classifiers":[
        {
            "category":"Travel",
            "subcategory":"Hotels & Motels",
            "type":"Entertainment"
        }
    ],
    "sg:phone":"+44 1943 880207",
    "sg:postcode":"HG3 4BA",
    "sg:province":"North Yorkshire",
    "sg:tags":[
        "self",
        "catering"
    ],
    "wof:name":"Margaret & John Verity",
    "wof:placetype":"venue"
},
  "geometry": {"coordinates":[-1.693886,54.057629],"type":"Point"}
}