{
  "type": "Feature",
  "properties": {
    "addr:full":"17 Abbey Enterprise Centre, Abbey Park Indstl Est Romsey Hampshire SO51 9AQ",
    "addr:housenumber":"17",
    "addr:postcode":"so51 9aq",
    "addr:street":"Abbey Enterprise Centre Abbey Park Indstl Est",
    "iso:country":"GB",
    "sg:address":"17 Abbey Enterprise Centre, Abbey Park Indstl Est",
    "sg:city":"Romsey",
    "sg:classifiers":[
        {
            "category":"Government",
            "subcategory":"Fire Station",
            "type":"Public Place"
        }
    ],
    "sg:phone":"+44 1794 521003",
    "sg:postcode":"SO51 9AQ",
    "sg:province":"Hampshire",
    "sg:tags":[
        "security"
    ],
    "wof:name":"Brs Fire Alarms  &  Emergency Lighting L",
    "wof:placetype":"venue"
},
  "geometry": {"coordinates":[-1.4953910112,50.9885826111],"type":"Point"}
}