{
  "type": "Feature",
  "properties": {
    "addr:full":"9b Mill Lane, Upton Chester Cheshire CH2 1BS",
    "addr:housenumber":"9b",
    "addr:postcode":"ch2 1bs",
    "addr:street":"Mill Lane",
    "iso:country":"GB",
    "sg:address":"9b Mill Lane, Upton",
    "sg:city":"Chester",
    "sg:classifiers":[
        {
            "category":"Personal",
            "subcategory":"Beauty Salon",
            "type":"Services"
        }
    ],
    "sg:phone":"+44 1244 371000",
    "sg:postcode":"CH2 1BS",
    "sg:province":"Cheshire",
    "sg:tags":[
        "unisex",
        "hairdresser"
    ],
    "wof:name":"The Bache Barber",
    "wof:placetype":"venue"
},
  "geometry": {"coordinates":[-2.8907461166,53.2105865479],"type":"Point"}
}