{
  "type": "Feature",
  "properties": {
    "addr:full":"29 Spencer Street Chesterfield Derbyshire S40 4SD",
    "addr:housenumber":"29",
    "addr:postcode":"s40 4sd",
    "addr:street":"Spencer Street",
    "iso:country":"GB",
    "sg:address":"29 Spencer Street",
    "sg:city":"Chesterfield",
    "sg:classifiers":[
        {
            "category":"Bars & Pubs",
            "type":"Food & Drink"
        },
        {
            "category":"Community Center",
            "subcategory":"Social",
            "type":"Public Place"
        }
    ],
    "sg:phone":"+44 1246 239607",
    "sg:postcode":"S40 4SD",
    "sg:province":"Derbyshire",
    "sg:tags":[
        "pubs",
        "house",
        "inn",
        "activity"
    ],
    "wof:name":"Wellington Hotel",
    "wof:placetype":"venue"
},
  "geometry": {"coordinates":[-1.302101,53.224525],"type":"Point"}
}