{
  "type": "Feature",
  "properties": {
    "iso:country":"GB",
    "sg:address":"8 O Xford Street",
    "sg:city":"Nottingham",
    "sg:classifiers":[
        {
            "category":"Health Services",
            "subcategory":"Health Practitioner",
            "type":"Services"
        }
    ],
    "sg:phone":"+44 115 941 7714",
    "sg:postcode":"NG1 5BH",
    "sg:province":"Nottinghamshire",
    "sg:tags":[
        "physiotherapist"
    ],
    "wof:name":"Pamela J Marsh",
    "wof:placetype":"venue"
},
  "geometry": {"coordinates":[-1.1576759815,52.9533615112],"type":"Point"}
}