{
  "type": "Feature",
  "properties": {
    "iso:country":"GB",
    "sg:address":"11 Radbrook Road",
    "sg:city":"Shrewsbury",
    "sg:classifiers":[
        {
            "category":"Health Services",
            "subcategory":"Doctor",
            "type":"Services"
        }
    ],
    "sg:postcode":"SY3 9BB",
    "sg:province":"Shropshire",
    "sg:tags":[
        "practitioners"
    ],
    "wof:name":"Jonathan Lane",
    "wof:placetype":"venue"
},
  "geometry": {"coordinates":[-2.774508,52.704678],"type":"Point"}
}