{
  "type": "Feature",
  "properties": {
    "iso:country":"GB",
    "sg:address":"Hay Green Farm, Hay Green La, Blackmore",
    "sg:city":"Ingatestone",
    "sg:classifiers":[
        {
            "category":"Shopping",
            "subcategory":"Antiques",
            "type":"Retail Goods"
        }
    ],
    "sg:postcode":"CM4 0QE",
    "sg:province":"Essex",
    "wof:name":"Hay Green Antiques",
    "wof:placetype":"venue"
},
  "geometry": {"coordinates":[0.383585,51.669922],"type":"Point"}
}