{
  "type": "Feature",
  "properties": {
    "addr:full":"74 Newport Lincoln Lincolnshire LN1 3DP",
    "addr:housenumber":"74",
    "addr:postcode":"ln1 3dp",
    "addr:street":"Newport Lincoln",
    "iso:country":"GB",
    "sg:address":"74 Newport",
    "sg:city":"Lincoln",
    "sg:classifiers":[
        {
            "category":"Health Services",
            "subcategory":"Health Practitioner",
            "type":"Services"
        },
        {
            "category":"Health Services",
            "subcategory":"Podiatrist",
            "type":"Services"
        }
    ],
    "sg:phone":"+44 1522 525986",
    "sg:postcode":"LN1 3DP",
    "sg:province":"Lincolnshire",
    "sg:tags":[
        "physiotherapist",
        "podiatrists",
        "chiropodist"
    ],
    "wof:name":"Alan F Wortley",
    "wof:placetype":"venue"
},
  "geometry": {"coordinates":[-0.53784,53.241512],"type":"Point"}
}