{
  "type": "Feature",
  "properties": {
    "addr:full":"39 Clarkston Road Glasgow East Renfrewshire G44 3BQ",
    "addr:housenumber":"39",
    "addr:postcode":"g44 3bq",
    "addr:street":"Clarkston Road",
    "iso:country":"GB",
    "sg:address":"39 Clarkston Road",
    "sg:city":"Glasgow",
    "sg:classifiers":[
        {
            "category":"Shopping",
            "subcategory":"Department Store",
            "type":"Retail Goods"
        },
        {
            "category":"Food & Beverages",
            "subcategory":"Groceries & Convenience Stores",
            "type":"Retail Goods"
        }
    ],
    "sg:phone":"+44 141 637 2516",
    "sg:postcode":"G44 3BQ",
    "sg:province":"East Renfrewshire",
    "wof:name":"Cathcart Mini Market",
    "wof:placetype":"venue"
},
  "geometry": {"coordinates":[-4.26259,55.816814],"type":"Point"}
}