{
  "type": "Feature",
  "properties": {
    "iso:country":"GB",
    "sg:address":"72 St Osyth Road",
    "sg:city":"Clacton-on-sea",
    "sg:classifiers":[
        {
            "category":"Professional",
            "subcategory":"Engineering",
            "type":"Services"
        }
    ],
    "sg:postcode":"CO15 3BU",
    "sg:province":"Essex",
    "sg:tags":[
        "contractor",
        "electrical",
        "engineer"
    ],
    "wof:name":"M B Electrics",
    "wof:placetype":"venue"
},
  "geometry": {"coordinates":[1.14402,51.793541],"type":"Point"}
}