{
  "type": "Feature",
  "properties": {
    "addr:full":"Unit 5 Eastington Industrial Estate, Meadow Mill Eastington Stonehouse Gloucestershire GL10 3RZ",
    "addr:housenumber":"unit 5",
    "addr:postcode":"gl10 3rz",
    "addr:street":"Industrial Estate Meadow;Eastington;Gloucestershire",
    "iso:country":"GB",
    "sg:address":"Unit 5 Eastington Industrial Estate, Meadow Mill Eastington",
    "sg:city":"Stonehouse",
    "sg:classifiers":[
        {
            "category":"Shopping",
            "subcategory":"Crafts & Fabrics",
            "type":"Retail Goods"
        },
        {
            "category":"Military Area",
            "subcategory":"Air Force Base",
            "type":"Public Place"
        }
    ],
    "sg:phone":"+44 1453 791487",
    "sg:postcode":"GL10 3RZ",
    "sg:province":"Gloucestershire",
    "sg:tags":[
        "contractor",
        "sewing",
        "centre"
    ],
    "wof:name":"Stroud Sewing Services",
    "wof:placetype":"venue"
},
  "geometry": {"coordinates":[-2.325842,51.746082],"type":"Point"}
}