{
  "type": "Feature",
  "properties": {
    "addr:full":"25 High Street Whitchurch Cheshire SY13 1AX",
    "addr:housenumber":"25",
    "addr:postcode":"sy13 1ax",
    "addr:street":"High Street",
    "iso:country":"GB",
    "sg:address":"25 High Street",
    "sg:city":"Whitchurch",
    "sg:classifiers":[
        {
            "category":"Retail",
            "subcategory":"Repair Shop",
            "type":"Services"
        }
    ],
    "sg:phone":"+44 1948 662463",
    "sg:postcode":"SY13 1AX",
    "sg:province":"Cheshire",
    "sg:tags":[
        "radio",
        "television",
        "video"
    ],
    "wof:name":"Barlows Electrical (Whitchurch) Ltd.",
    "wof:placetype":"venue"
},
  "geometry": {"coordinates":[-2.6841459274,52.969745636],"type":"Point"}
}