{
  "type": "Feature",
  "properties": {
    "iso:country":"GB",
    "sg:address":"105 Vignoles Road",
    "sg:city":"Romford",
    "sg:classifiers":[
        {
            "category":"Professional",
            "subcategory":"Accounting & Tax Preparation",
            "type":"Services"
        }
    ],
    "sg:postcode":"RM7 0DU",
    "sg:province":"Essex",
    "sg:tags":[
        "accountant"
    ],
    "wof:name":"R M Accountancy",
    "wof:placetype":"venue"
},
  "geometry": {"coordinates":[0.1532869935,51.5693206787],"type":"Point"}
}