{
  "type": "Feature",
  "properties": {
    "addr:full":"7 Conway Drive, Flitwick Bedford Bedfordshire MK45 1DE",
    "addr:housenumber":"7",
    "addr:postcode":"mk45 1de",
    "addr:street":"Conway Drive",
    "iso:country":"GB",
    "sg:address":"7 Conway Drive, Flitwick",
    "sg:city":"Bedford",
    "sg:classifiers":[
        {
            "category":"Communications",
            "type":"Services"
        }
    ],
    "sg:phone":"+44 1525 759047",
    "sg:postcode":"MK45 1DE",
    "sg:province":"Bedfordshire",
    "sg:tags":[
        "audio-visual"
    ],
    "wof:name":"Insight Production Services Ltd.",
    "wof:placetype":"venue"
},
  "geometry": {"coordinates":[-0.5054349899,52.0002212524],"type":"Point"}
}