{
  "type": "Feature",
  "properties": {
    "iso:country":"GB",
    "sg:address":"59-59a Main Street, Cambuslang",
    "sg:city":"Glasgow",
    "sg:classifiers":[
        {
            "category":"Shopping",
            "subcategory":"Pharmacy",
            "type":"Retail Goods"
        }
    ],
    "sg:phone":"+44 141 641 2698",
    "sg:postcode":"G72 7HB",
    "sg:province":"South Lanarkshire",
    "sg:tags":[
        "pharmacist",
        "chemist"
    ],
    "wof:name":"Moss Chemists",
    "wof:placetype":"venue"
},
  "geometry": {"coordinates":[-4.1683011055,55.8193817139],"type":"Point"}
}