{
  "type": "Feature",
  "properties": {
    "addr:full":"93 Knowsley Road Bootle Merseyside L20 4NH",
    "addr:housenumber":"93",
    "addr:postcode":"l20 4nh",
    "addr:street":"Knowsley Road",
    "iso:country":"GB",
    "sg:address":"93 Knowsley Road",
    "sg:city":"Bootle",
    "sg:classifiers":[
        {
            "category":"Shopping",
            "subcategory":"Pharmacy",
            "type":"Retail Goods"
        }
    ],
    "sg:phone":"+44 151 922 7062",
    "sg:postcode":"L20 4NH",
    "sg:province":"Merseyside",
    "sg:tags":[
        "pharmacist",
        "chemist"
    ],
    "wof:name":"Norman's Pharmacies Ltd.",
    "wof:placetype":"venue"
},
  "geometry": {"coordinates":[-3.0031549931,53.4601974487],"type":"Point"}
}