{
  "type": "Feature",
  "properties": {
    "addr:full":"52 Elmwood Park Livingston West Lothian EH54 8SP",
    "addr:housenumber":"52",
    "addr:postcode":"eh54 8sp",
    "addr:street":"Elmwood Park",
    "iso:country":"GB",
    "sg:address":"52 Elmwood Park",
    "sg:city":"Livingston",
    "sg:classifiers":[
        {
            "category":"Professional",
            "subcategory":"Management & Consulting",
            "type":"Services"
        }
    ],
    "sg:phone":"+44 1506 419912",
    "sg:postcode":"EH54 8SP",
    "sg:province":"West Lothian",
    "sg:tags":[
        "consultant",
        "training"
    ],
    "wof:name":"Rod Sutherland & Partners",
    "wof:placetype":"venue"
},
  "geometry": {"coordinates":[-3.555062,55.904987],"type":"Point"}
}