{
  "type": "Feature",
  "properties": {
    "addr:full":"Lawpark, West Balgrochan Road, Torrance Glasgow East Dunbartonshire G64 4DD",
    "addr:postcode":"g64 4dd",
    "addr:street":"Balgrochan Road",
    "iso:country":"GB",
    "sg:address":"Lawpark, West Balgrochan Road, Torrance",
    "sg:city":"Glasgow",
    "sg:classifiers":[
        {
            "category":"Real Estate",
            "subcategory":"Real Estate Services",
            "type":"Services"
        },
        {
            "category":"Building & Trades",
            "subcategory":"Equipment Rental",
            "type":"Services"
        }
    ],
    "sg:phone":"+44 1360 620584",
    "sg:postcode":"G64 4DD",
    "sg:province":"East Dunbartonshire",
    "sg:tags":[
        "hire",
        "leasing",
        "plant",
        "machinery"
    ],
    "wof:name":"Torrance Transport Co Ltd",
    "wof:placetype":"venue"
},
  "geometry": {"coordinates":[-4.2124137878,55.9382743835],"type":"Point"}
}