{
  "type": "Feature",
  "properties": {
    "addr:full":"39 Newtons La Nottingham Derbyshire NG16 2SB",
    "addr:housenumber":"39",
    "addr:postcode":"ng16 2sb",
    "addr:street":"Newtons La",
    "iso:country":"GB",
    "sg:address":"39 Newtons La",
    "sg:city":"Nottingham",
    "sg:classifiers":[
        {
            "category":"Building & Trades",
            "subcategory":"Landscaping Services",
            "type":"Services"
        }
    ],
    "sg:phone":"+44 115 930 2726",
    "sg:postcode":"NG16 2SB",
    "sg:province":"Derbyshire",
    "sg:tags":[
        "landscape",
        "contractor"
    ],
    "wof:name":"Jim O'Connor",
    "wof:placetype":"venue"
},
  "geometry": {"coordinates":[-1.28661,52.98719],"type":"Point"}
}