{
  "type": "Feature",
  "properties": {
    "addr:full":"Care Of Beatties 92 Grange Road Birkenhead Merseyside CH41 6ED",
    "addr:housenumber":"92",
    "addr:postcode":"ch41 6ed",
    "addr:street":"Grange Road",
    "iso:country":"GB",
    "sg:address":"Care Of Beatties 92 Grange Road",
    "sg:city":"Birkenhead",
    "sg:classifiers":[
        {
            "category":"Shopping",
            "subcategory":"Clothing, Apparel, & Fashions",
            "type":"Retail Goods"
        }
    ],
    "sg:phone":"+44 151 647 7112",
    "sg:postcode":"CH41 6ED",
    "sg:province":"Merseyside",
    "sg:tags":[
        "shop"
    ],
    "wof:name":"Jacques Vert (Retail) Ltd.",
    "wof:placetype":"venue"
},
  "geometry": {"coordinates":[-3.025489,53.392567],"type":"Point"}
}