{
  "type": "Feature",
  "properties": {
    "iso:country":"GB",
    "sg:address":"Oklahoma, Durlett Road, Rowde",
    "sg:city":"Devizes",
    "sg:classifiers":[
        {
            "category":"Farming",
            "subcategory":"Crops",
            "type":"Manufacturing & Wholesale Goods"
        },
        {
            "category":"Farming",
            "subcategory":"Livestock Farm",
            "type":"Manufacturing & Wholesale Goods"
        }
    ],
    "sg:phone":"+44 1380 850357",
    "sg:postcode":"SN10 1SX",
    "sg:province":"Wiltshire",
    "sg:tags":[
        "arable",
        "others"
    ],
    "wof:name":"Richard C Giles",
    "wof:placetype":"venue"
},
  "geometry": {"coordinates":[-1.995031,51.351479],"type":"Point"}
}