{
  "type": "Feature",
  "properties": {
    "addr:full":"6 Trippier Road, Peel Grn, Eccles Manchester Greater Manchester M30 7PT",
    "addr:housenumber":"6",
    "addr:postcode":"m30 7pt",
    "addr:street":"Trippier Road;Grn",
    "iso:country":"GB",
    "sg:address":"6 Trippier Road, Peel Grn, Eccles",
    "sg:city":"Manchester",
    "sg:classifiers":[
        {
            "category":"Building & Trades",
            "subcategory":"Construction",
            "type":"Services"
        }
    ],
    "sg:phone":"+44 161 789 0933",
    "sg:postcode":"M30 7PT",
    "sg:province":"Greater Manchester",
    "sg:tags":[
        "decorator",
        "painter"
    ],
    "wof:name":"Barton Painters & Decorators",
    "wof:placetype":"venue"
},
  "geometry": {"coordinates":[-2.3800320625,53.476890564],"type":"Point"}
}