{
  "type": "Feature",
  "properties": {
    "iso:country":"GB",
    "sg:address":"Cinder Lane",
    "sg:city":"Louth",
    "sg:classifiers":[
        {
            "category":"Utilities",
            "subcategory":"Refuse",
            "type":"Services"
        }
    ],
    "sg:postcode":"LN11 9HS",
    "sg:province":"Lincolnshire",
    "sg:tags":[
        "disposal",
        "waste"
    ],
    "wof:name":"Serviceteam Ltd.",
    "wof:placetype":"venue"
},
  "geometry": {"coordinates":[-0.002504,53.364528656],"type":"Point"}
}