{
  "type": "Feature",
  "properties": {
    "addr:full":"115a Lamb Hall Rd Huddersfield West Yorkshire HD3 3TH",
    "addr:housenumber":"115a",
    "addr:postcode":"hd3 3th",
    "addr:street":"Lamb Hall Rd",
    "iso:country":"GB",
    "sg:address":"115a Lamb Hall Rd",
    "sg:city":"Huddersfield",
    "sg:classifiers":[
        {
            "category":"Shopping",
            "subcategory":"Computers & Home Electronics",
            "type":"Retail Goods"
        }
    ],
    "sg:phone":"+44 1484 460943",
    "sg:postcode":"HD3 3TH",
    "sg:province":"West Yorkshire",
    "sg:tags":[
        "equipment",
        "audio-visual"
    ],
    "wof:name":"David James Television Systems Engineering",
    "wof:placetype":"venue"
},
  "geometry": {"coordinates":[-1.854381,53.657375],"type":"Point"}
}