{
  "type": "Feature",
  "properties": {
    "addr:full":"The Corner House, Amery Street Alton Hampshire GU34 1HN",
    "addr:postcode":"gu34 1hn",
    "addr:street":"Amery Street",
    "iso:country":"GB",
    "sg:address":"The Corner House, Amery Street",
    "sg:city":"Alton",
    "sg:classifiers":[
        {
            "category":"Professional",
            "subcategory":"Management & Consulting",
            "type":"Services"
        },
        {
            "category":"Professional",
            "subcategory":"Employment Agencies",
            "type":"Services"
        }
    ],
    "sg:phone":"+44 1420 83886",
    "sg:postcode":"GU34 1HN",
    "sg:province":"Hampshire",
    "sg:tags":[
        "consultant",
        "business",
        "recruitment"
    ],
    "wof:name":"Portfolio Business Services Ltd.",
    "wof:placetype":"venue"
},
  "geometry": {"coordinates":[-0.977458,51.149799],"type":"Point"}
}