{
  "type": "Feature",
  "properties": {
    "addr:full":"5 Old Christchurch Rd Bournemouth Dorset BH1 1DU",
    "addr:housenumber":"5",
    "addr:postcode":"bh1 1du",
    "addr:street":"Old Christchurch Rd",
    "iso:country":"GB",
    "sg:address":"5 Old Christchurch Rd",
    "sg:city":"Bournemouth",
    "sg:classifiers":[
        {
            "category":"Banks & Credit Unions",
            "subcategory":"Bank",
            "type":"Services"
        }
    ],
    "sg:phone":"+44 1202 292494",
    "sg:postcode":"BH1 1DU",
    "sg:province":"Dorset",
    "wof:name":"NatWest",
    "wof:placetype":"venue"
},
  "geometry": {"coordinates":[-1.876996,50.720715],"type":"Point"}
}