{
  "type": "Feature",
  "properties": {
    "addr:full":"59 Owston Road, Carcroft Doncaster North Yorkshire DN6 8DA",
    "addr:housenumber":"59",
    "addr:postcode":"dn6 8da",
    "addr:street":"Owston Road",
    "iso:country":"GB",
    "sg:address":"59 Owston Road, Carcroft",
    "sg:city":"Doncaster",
    "sg:classifiers":[
        {
            "category":"Autos & Motor Vehicles",
            "subcategory":"Auto Supplies",
            "type":"Retail Goods"
        },
        {
            "category":"Shopping",
            "type":"Retail Goods"
        }
    ],
    "sg:phone":"+44 1302 330361",
    "sg:postcode":"DN6 8DA",
    "sg:province":"North Yorkshire",
    "sg:tags":[
        "car",
        "part",
        "accessory"
    ],
    "wof:name":"Bullseye Motorist Centre",
    "wof:placetype":"venue"
},
  "geometry": {"coordinates":[-1.1795190573,53.5827178955],"type":"Point"}
}