{
  "type": "Feature",
  "properties": {
    "addr:full":"18 The Green, Thorne Doncaster East Riding of Yorkshire DN8 5AT",
    "addr:housenumber":"18",
    "addr:postcode":"dn8 5at",
    "addr:street":"The Green;Riding",
    "iso:country":"GB",
    "sg:address":"18 The Green, Thorne",
    "sg:city":"Doncaster",
    "sg:classifiers":[
        {
            "category":"Farming",
            "subcategory":"Livestock Farm",
            "type":"Manufacturing & Wholesale Goods"
        },
        {
            "category":"Shopping",
            "subcategory":"Florist",
            "type":"Retail Goods"
        }
    ],
    "sg:phone":"+44 1405 813729",
    "sg:postcode":"DN8 5AT",
    "sg:province":"East Riding of Yorkshire",
    "sg:tags":[
        "breeder"
    ],
    "wof:name":"The Floral Boutique",
    "wof:placetype":"venue"
},
  "geometry": {"coordinates":[-0.961637,53.611591],"type":"Point"}
}