{
  "type": "Feature",
  "properties": {
    "addr:full":"Foxhold House, Crookham Common Thatcham Berkshire RG19 8EL",
    "addr:postcode":"rg19 8el",
    "addr:street":"Crookham Common",
    "iso:country":"GB",
    "sg:address":"Foxhold House, Crookham Common",
    "sg:city":"Thatcham",
    "sg:classifiers":[
        {
            "category":"Professional",
            "subcategory":"Management & Consulting",
            "type":"Services"
        },
        {
            "category":"Organizations",
            "subcategory":"Community Association",
            "type":"Services"
        }
    ],
    "sg:phone":"+44 1635 268881",
    "sg:postcode":"RG19 8EL",
    "sg:province":"Berkshire",
    "sg:tags":[
        "organisation",
        "conservation"
    ],
    "wof:name":"English Nature",
    "wof:placetype":"venue"
},
  "geometry": {"coordinates":[-1.2336939573,51.3759155273],"type":"Point"}
}