{
  "type": "Feature",
  "properties": {
    "addr:full":"Gooda, Westhouse Carnforth Cumbria LA6 3PF",
    "addr:postcode":"la6 3pf",
    "iso:country":"GB",
    "sg:address":"Gooda, Westhouse",
    "sg:city":"Carnforth",
    "sg:classifiers":[
        {
            "category":"Banks & Credit Unions",
            "subcategory":"Investment Brokerage",
            "type":"Services"
        },
        {
            "category":"Professional",
            "subcategory":"Employment Agencies",
            "type":"Services"
        }
    ],
    "sg:postcode":"LA6 3PF",
    "sg:province":"Cumbria",
    "sg:tags":[
        "agricultural",
        "advice",
        "contractor"
    ],
    "wof:name":"Hothersall Agricultural Services",
    "wof:placetype":"venue"
},
  "geometry": {"coordinates":[-2.5048639774,54.1614608765],"type":"Point"}
}