{
  "type": "Feature",
  "properties": {
    "addr:full":"3 Field Court, Grays Inn London Greater London WC1R 5EN",
    "addr:housenumber":"3",
    "addr:postcode":"wc1r 5en",
    "addr:street":"Field Court",
    "iso:country":"GB",
    "sg:address":"3 Field Court, Grays Inn",
    "sg:city":"London",
    "sg:classifiers":[
        {
            "category":"Professional",
            "subcategory":"Lawyer & Legal Services",
            "type":"Services"
        }
    ],
    "sg:postcode":"WC1R 5EN",
    "sg:province":"Greater London",
    "sg:tags":[
        "solicitor"
    ],
    "wof:name":"James & Sarch",
    "wof:placetype":"venue"
},
  "geometry": {"coordinates":[-0.113399,51.519089],"type":"Point"}
}