{
  "type": "Feature",
  "properties": {
    "addr:full":"St Annes Gro Fareham Hampshire PO14 1JJ",
    "addr:postcode":"po14 1jj",
    "addr:street":"St Annes Gro",
    "iso:country":"GB",
    "sg:address":"St Annes Gro",
    "sg:city":"Fareham",
    "sg:classifiers":[
        {
            "category":"Education",
            "subcategory":"School",
            "type":"Public Place"
        }
    ],
    "sg:phone":"+44 1329 318003",
    "sg:postcode":"PO14 1JJ",
    "sg:province":"Hampshire",
    "sg:tags":[
        "local",
        "authority"
    ],
    "wof:name":"Neville Lovett Community School",
    "wof:placetype":"venue"
},
  "geometry": {"coordinates":[-1.1942590475,50.8474617004],"type":"Point"}
}