{
  "type": "Feature",
  "properties": {
    "addr:full":"North Bank Viewing Area Ferriby, Road Hessle East Riding of Yorkshire HU13 0LN",
    "addr:postcode":"hu13 0ln",
    "addr:street":"North;Ferriby Road",
    "iso:country":"GB",
    "sg:address":"North Bank Viewing Area Ferriby, Road",
    "sg:city":"Hessle",
    "sg:classifiers":[
        {
            "category":"Landmark",
            "subcategory":"Tourist Information",
            "type":"Public Place"
        }
    ],
    "sg:phone":"+44 1482 640852",
    "sg:postcode":"HU13 0LN",
    "sg:province":"East Riding of Yorkshire",
    "wof:name":"Humber Bridge Tourist Information Centre",
    "wof:placetype":"venue"
},
  "geometry": {"coordinates":[-0.4336189926,53.7230300903],"type":"Point"}
}