{
  "type": "Feature",
  "properties": {
    "iso:country":"GB",
    "sg:address":"194 Savile Park Road",
    "sg:city":"Halifax",
    "sg:classifiers":[
        {
            "category":"Government",
            "subcategory":"Post Office",
            "type":"Public Place"
        }
    ],
    "sg:postcode":"HX1 2XP",
    "sg:province":"West Yorkshire",
    "wof:name":"Bell Hall Post Office",
    "wof:placetype":"venue"
},
  "geometry": {"coordinates":[-1.873066,53.715],"type":"Point"}
}