{
  "type": "Feature",
  "properties": {
    "addr:full":"38 Conduit St London Greater London W1S 2YJ",
    "addr:housenumber":"38",
    "addr:postcode":"w1s 2yj",
    "addr:street":"Conduit St",
    "iso:country":"GB",
    "sg:address":"38 Conduit St",
    "sg:city":"London",
    "sg:classifiers":[
        {
            "category":"Shopping",
            "subcategory":"Clothing, Apparel, & Fashions",
            "type":"Retail Goods"
        }
    ],
    "sg:postcode":"W1S 2YJ",
    "sg:province":"Greater London",
    "sg:tags":[
        "clothing"
    ],
    "wof:name":"Sistovari & Fremder Ltd",
    "wof:placetype":"venue"
},
  "geometry": {"coordinates":[-0.1430049986,51.5111732483],"type":"Point"}
}