{
  "type": "Feature",
  "properties": {
    "addr:full":"3 The Boulevard, Metrocentre Gateshead Tyne and Wear NE11 9YN",
    "addr:housenumber":"3",
    "addr:postcode":"ne11 9yn",
    "addr:street":"The Boulevard Metrocentre",
    "iso:country":"GB",
    "sg:address":"3 The Boulevard, Metrocentre",
    "sg:city":"Gateshead",
    "sg:classifiers":[
        {
            "category":"Shopping",
            "subcategory":"Clothing, Apparel, & Fashions",
            "type":"Retail Goods"
        }
    ],
    "sg:phone":"+44 191 460 3060",
    "sg:postcode":"NE11 9YN",
    "sg:province":"Tyne and Wear",
    "sg:tags":[
        "shop"
    ],
    "wof:name":"Cream Designer Fashions",
    "wof:placetype":"venue"
},
  "geometry": {"coordinates":[-1.6685400009,54.957660675],"type":"Point"}
}