{
  "type": "Feature",
  "properties": {
    "addr:full":"2 St. Johns St Newport Pagnell Buckinghamshire MK16 8HN",
    "addr:housenumber":"2",
    "addr:postcode":"mk16 8hn",
    "addr:street":"St. Johns St",
    "iso:country":"GB",
    "sg:address":"2 St. Johns St",
    "sg:city":"Newport Pagnell",
    "sg:classifiers":[
        {
            "category":"Food & Beverages",
            "subcategory":"Meat & Fish",
            "type":"Retail Goods"
        }
    ],
    "sg:phone":"+44 1908 616484",
    "sg:postcode":"MK16 8HN",
    "sg:province":"Buckinghamshire",
    "sg:tags":[
        "chip"
    ],
    "wof:name":"Golden Fry",
    "wof:placetype":"venue"
},
  "geometry": {"coordinates":[-0.7223129869,52.0867462158],"type":"Point"}
}