{
  "type": "Feature",
  "properties": {
    "iso:country":"GB",
    "sg:address":"8 Furnace Lane, Trench",
    "sg:city":"Telford",
    "sg:classifiers":[
        {
            "category":"Building & Trades",
            "subcategory":"Construction",
            "type":"Services"
        }
    ],
    "sg:phone":"+44 1952 409114",
    "sg:postcode":"TF2 7JX",
    "sg:province":"Shropshire",
    "sg:tags":[
        "tiling",
        "contractor"
    ],
    "wof:name":"P.A Wootton Tiling",
    "wof:placetype":"venue"
},
  "geometry": {"coordinates":[-2.44208,52.710388],"type":"Point"}
}