{
  "type": "Feature",
  "properties": {
    "addr:full":"Longside Road, Mintlaw Peterhead Aberdeenshire AB42 5EJ",
    "addr:postcode":"ab42 5ej",
    "addr:street":"Longside Road",
    "iso:country":"GB",
    "sg:address":"Longside Road, Mintlaw",
    "sg:city":"Peterhead",
    "sg:classifiers":[
        {
            "category":"Professional",
            "subcategory":"Engineering",
            "type":"Services"
        },
        {
            "category":"Freight",
            "type":"Transportation"
        }
    ],
    "sg:phone":"+44 1771 623535",
    "sg:postcode":"AB42 5EJ",
    "sg:province":"Aberdeenshire",
    "sg:tags":[
        "haulage",
        "civil",
        "road",
        "engineer"
    ],
    "wof:name":"les Taylor Contractors Ltd.",
    "wof:placetype":"venue"
},
  "geometry": {"coordinates":[-2.003859,57.525181],"type":"Point"}
}