{
  "type": "Feature",
  "properties": {
    "addr:full":"1 Acre Street Burnley Lancashire BB10 3HS",
    "addr:housenumber":"1",
    "addr:postcode":"bb10 3hs",
    "addr:street":"Acre Street",
    "iso:country":"GB",
    "sg:address":"1 Acre Street",
    "sg:city":"Burnley",
    "sg:classifiers":[
        {
            "category":"Building & Trades",
            "subcategory":"Construction",
            "type":"Services"
        }
    ],
    "sg:postcode":"BB10 3HS",
    "sg:province":"Lancashire",
    "sg:tags":[
        "joinery"
    ],
    "wof:name":"Metcalfe & Burrows",
    "wof:placetype":"venue"
},
  "geometry": {"coordinates":[-2.2309091091,53.8038482666],"type":"Point"}
}