{
  "type": "Feature",
  "properties": {
    "addr:full":"New Farm, Blyton Carr Gainsborough Lincolnshire DN21 3EW",
    "addr:housenumber":"blyton",
    "addr:postcode":"dn21 3ew",
    "addr:street":"Carr Gainsborough",
    "iso:country":"GB",
    "sg:address":"New Farm, Blyton Carr",
    "sg:city":"Gainsborough",
    "sg:classifiers":[
        {
            "category":"Brewery",
            "type":"Food & Drink"
        }
    ],
    "sg:phone":"+44 1427 677901",
    "sg:postcode":"DN21 3EW",
    "sg:province":"Lincolnshire",
    "sg:tags":[
        "brewer"
    ],
    "wof:name":"Big Foot Traditional Ales Ltd",
    "wof:placetype":"venue"
},
  "geometry": {"coordinates":[-0.7229830027,53.4414825439],"type":"Point"}
}