{
  "type": "Feature",
  "properties": {
    "addr:full":"9 Kelsey Park Road Beckenham Kent BR3 6LH",
    "addr:housenumber":"9",
    "addr:postcode":"br3 6lh",
    "addr:street":"Kelsey Park Road",
    "iso:country":"GB",
    "sg:address":"9 Kelsey Park Road",
    "sg:city":"Beckenham",
    "sg:classifiers":[
        {
            "category":"Professional",
            "subcategory":"Management & Consulting",
            "type":"Services"
        }
    ],
    "sg:phone":"+44 20 8658 1187",
    "sg:postcode":"BR3 6LH",
    "sg:province":"Kent",
    "sg:tags":[
        "consultant",
        "business"
    ],
    "wof:name":"Fobister Power Consulting Ltd.",
    "wof:placetype":"venue"
},
  "geometry": {"coordinates":[-0.025184,51.407227],"type":"Point"}
}