{
  "type": "Feature",
  "properties": {
    "iso:country":"GB",
    "sg:address":"267 Cranbrook Road",
    "sg:city":"Ilford",
    "sg:classifiers":[
        {
            "category":"Professional",
            "subcategory":"Detective & Security Services",
            "type":"Services"
        }
    ],
    "sg:phone":"+44 20 8554 3671",
    "sg:postcode":"IG1 4TG",
    "sg:province":"Essex",
    "sg:tags":[
        "activity"
    ],
    "wof:name":"RELIANCE SECURITY SERVICES LTD",
    "wof:placetype":"venue"
},
  "geometry": {"coordinates":[0.0662830025,51.5642852783],"type":"Point"}
}