{
  "type": "Feature",
  "properties": {
    "addr:full":"240 Kings Road Ashton-under-lyne Greater Manchester OL6 8HD",
    "addr:housenumber":"240",
    "addr:postcode":"ol6 8hd",
    "addr:street":"Kings Road",
    "iso:country":"GB",
    "sg:address":"240 Kings Road",
    "sg:city":"Ashton-under-lyne",
    "sg:classifiers":[
        {
            "category":"Professional",
            "subcategory":"Business Services",
            "type":"Services"
        },
        {
            "category":"Casinos & Gambling",
            "type":"Entertainment"
        }
    ],
    "sg:phone":"+44 161 330 1722",
    "sg:postcode":"OL6 8HD",
    "sg:province":"Greater Manchester",
    "sg:tags":[
        "turf",
        "accountant",
        "bookmaker"
    ],
    "wof:name":"J B Aspinall Ltd",
    "wof:placetype":"venue"
},
  "geometry": {"coordinates":[-2.079006,53.500317],"type":"Point"}
}