{
  "type": "Feature",
  "properties": {
    "iso:country":"GB",
    "sg:address":"93 Hambledon Road",
    "sg:city":"Middlesbrough",
    "sg:classifiers":[
        {
            "category":"Bus Charters",
            "type":"Transportation"
        }
    ],
    "sg:phone":"+44 1642 823102",
    "sg:postcode":"TS5 5EF",
    "sg:province":"North Yorkshire",
    "sg:tags":[
        "mini",
        "hire",
        "leasing"
    ],
    "wof:name":"Linthorpe Mini Buses",
    "wof:placetype":"venue"
},
  "geometry": {"coordinates":[-1.259325,54.556755],"type":"Point"}
}