{
  "type": "Feature",
  "properties": {
    "iso:country":"GB",
    "sg:address":"46 High Street",
    "sg:city":"Elgin",
    "sg:classifiers":[
        {
            "category":"Retail",
            "subcategory":"Photofinishing",
            "type":"Services"
        },
        {
            "category":"Shopping",
            "subcategory":"Photographic Equipment",
            "type":"Retail Goods"
        }
    ],
    "sg:phone":"+44 1343 548316",
    "sg:postcode":"IV30 1BU",
    "sg:province":"Moray",
    "sg:tags":[
        "processing",
        "supply"
    ],
    "wof:name":"Photo Factory Ltd",
    "wof:placetype":"venue"
},
  "geometry": {"coordinates":[-3.312481,57.6488],"type":"Point"}
}