{
  "type": "Feature",
  "properties": {
    "iso:country":"GB",
    "sg:address":"Baileys House, Central Walk",
    "sg:city":"Wokingham",
    "sg:classifiers":[
        {
            "category":"Banks & Credit Unions",
            "subcategory":"Investment Brokerage",
            "type":"Services"
        }
    ],
    "sg:phone":"+44 118 977 0079",
    "sg:postcode":"RG40 1AZ",
    "sg:province":"Berkshire",
    "sg:tags":[
        "pension"
    ],
    "wof:name":"Norcros Group (Trustee) Ltd.",
    "wof:placetype":"venue"
},
  "geometry": {"coordinates":[-0.834781,51.411068],"type":"Point"}
}