{
  "type": "Feature",
  "properties": {
    "addr:full":"58 Market Street Wigan Lancashire WN2 3AN",
    "addr:housenumber":"58",
    "addr:postcode":"wn2 3an",
    "addr:street":"Market Street",
    "iso:country":"GB",
    "sg:address":"58 Market Street",
    "sg:city":"Wigan",
    "sg:classifiers":[
        {
            "category":"Cafe",
            "type":"Food & Drink"
        }
    ],
    "sg:phone":"+44 1942 255897",
    "sg:postcode":"WN2 3AN",
    "sg:province":"Lancashire",
    "sg:tags":[
        "tea",
        "room"
    ],
    "wof:name":"Lunchbox",
    "wof:placetype":"venue"
},
  "geometry": {"coordinates":[-2.577423,53.536224],"type":"Point"}
}