{
  "type": "Feature",
  "properties": {
    "addr:full":"57 Jamaica Street Glasgow Glasgow City G1 4NN",
    "addr:housenumber":"57",
    "addr:postcode":"g1 4nn",
    "addr:street":"Jamaica Street",
    "iso:country":"GB",
    "sg:address":"57 Jamaica Street",
    "sg:city":"Glasgow",
    "sg:classifiers":[
        {
            "category":"Home & Garden",
            "subcategory":"Household Appliances",
            "type":"Retail Goods"
        },
        {
            "category":"Transit Center",
            "subcategory":"Freight",
            "type":"Transportation"
        }
    ],
    "sg:phone":"+44 141 226 5551",
    "sg:postcode":"G1 4NN",
    "sg:province":"Glasgow City",
    "sg:tags":[
        "electrical",
        "fi",
        "hi",
        "domestic",
        "centre"
    ],
    "wof:name":"Richer Sounds plc",
    "wof:placetype":"venue"
},
  "geometry": {"coordinates":[-4.2571492195,55.8570365906],"type":"Point"}
}