{
  "type": "Feature",
  "properties": {
    "addr:full":"1a Brookfield Road Rushden Bedfordshire NN10 9TQ",
    "addr:housenumber":"1a",
    "addr:postcode":"nn10 9tq",
    "addr:street":"Brookfield Road",
    "iso:country":"GB",
    "sg:address":"1a Brookfield Road",
    "sg:city":"Rushden",
    "sg:classifiers":[
        {
            "category":"Building & Trades",
            "subcategory":"Construction",
            "type":"Services"
        }
    ],
    "sg:phone":"+44 1933 359996",
    "sg:postcode":"NN10 9TQ",
    "sg:province":"Bedfordshire",
    "sg:tags":[
        "joiner",
        "carpenter"
    ],
    "wof:name":"James Hollis",
    "wof:placetype":"venue"
},
  "geometry": {"coordinates":[-0.605914,52.291767],"type":"Point"}
}