{
  "type": "Feature",
  "properties": {
    "addr:full":"Kenilworth, Hounds Grn, Stinchcombe Dursley Gloucestershire GL11 6AN",
    "addr:postcode":"gl11 6an",
    "addr:street":"Hounds Grn",
    "iso:country":"GB",
    "sg:address":"Kenilworth, Hounds Grn, Stinchcombe",
    "sg:city":"Dursley",
    "sg:classifiers":[
        {
            "category":"Arena",
            "subcategory":"Sports Club",
            "type":"Entertainment"
        }
    ],
    "sg:phone":"+44 1453 543693",
    "sg:postcode":"GL11 6AN",
    "sg:province":"Gloucestershire",
    "wof:name":"Dursley Rugby Club",
    "wof:placetype":"venue"
},
  "geometry": {"coordinates":[-2.3924069405,51.6881752014],"type":"Point"}
}