{
  "type": "Feature",
  "properties": {
    "iso:country":"GB",
    "sg:address":"12 Milbanke Court, Milbanke Way",
    "sg:city":"Bracknell",
    "sg:classifiers":[
        {
            "category":"Shopping",
            "subcategory":"Clothing, Apparel, & Fashions",
            "type":"Retail Goods"
        }
    ],
    "sg:phone":"+44 1344 868586",
    "sg:postcode":"RG12 1RP",
    "sg:province":"Berkshire",
    "sg:tags":[
        "clothing",
        "fabric"
    ],
    "wof:name":"Finn Karelia U K",
    "wof:placetype":"venue"
},
  "geometry": {"coordinates":[-0.768009007,51.4182243347],"type":"Point"}
}