{
  "type": "Feature",
  "properties": {
    "addr:full":"36 Leighton Road Birmingham West Midlands B13 8HD",
    "addr:housenumber":"36",
    "addr:postcode":"b13 8hd",
    "addr:street":"Leighton Road",
    "iso:country":"GB",
    "sg:address":"36 Leighton Road",
    "sg:city":"Birmingham",
    "sg:classifiers":[
        {
            "category":"Health Services",
            "subcategory":"Health Practitioner",
            "type":"Services"
        }
    ],
    "sg:phone":"+44 121 449 9237",
    "sg:postcode":"B13 8HD",
    "sg:province":"West Midlands",
    "sg:tags":[
        "homoeopathic",
        "homeopathic"
    ],
    "wof:name":"Liz Minihane",
    "wof:placetype":"venue"
},
  "geometry": {"coordinates":[-1.888272047,52.444568634],"type":"Point"}
}