{
  "type": "Feature",
  "properties": {
    "addr:full":"25 Deepcut Bridge Road, Deepcut Camberley Hampshire GU16 6QX",
    "addr:housenumber":"25",
    "addr:postcode":"gu16 6qx",
    "addr:street":"Deepcut Bridge Road",
    "iso:country":"GB",
    "sg:address":"25 Deepcut Bridge Road, Deepcut",
    "sg:city":"Camberley",
    "sg:classifiers":[
        {
            "category":"Organizations",
            "subcategory":"Membership Organization",
            "type":"Services"
        }
    ],
    "sg:phone":"+44 1252 835164",
    "sg:postcode":"GU16 6QX",
    "sg:province":"Hampshire",
    "sg:tags":[
        "club"
    ],
    "wof:name":"Metropole Social & Working Mens Club",
    "wof:placetype":"venue"
},
  "geometry": {"coordinates":[-0.7063469887,51.306060791],"type":"Point"}
}