{
  "type": "Feature",
  "properties": {
    "iso:country":"GB",
    "sg:address":"27 Louth Rd",
    "sg:city":"Grimsby",
    "sg:classifiers":[
        {
            "category":"Shopping",
            "subcategory":"Baby Store",
            "type":"Retail Goods"
        }
    ],
    "sg:postcode":"DN33 2ER",
    "sg:province":"Lincolnshire",
    "sg:tags":[
        "babywear",
        "childrens"
    ],
    "wof:name":"Ejay's",
    "wof:placetype":"venue"
},
  "geometry": {"coordinates":[-0.091053,53.537575],"type":"Point"}
}