{
  "type": "Feature",
  "properties": {
    "iso:country":"GB",
    "sg:address":"Market Place",
    "sg:city":"Dalton In Furness",
    "sg:classifiers":[
        {
            "category":"Bars & Pubs",
            "type":"Food & Drink"
        }
    ],
    "sg:phone":"+44 1229 463325",
    "sg:postcode":"LA15 8AZ",
    "sg:province":"Cumbria",
    "sg:tags":[
        "pubs",
        "inn"
    ],
    "wof:name":"Robinsons Brewery",
    "wof:placetype":"venue"
},
  "geometry": {"coordinates":[-3.1860179901,54.1554870605],"type":"Point"}
}