{
  "type": "Feature",
  "properties": {
    "addr:full":"3a Plumstead Road London Greater London SE18 7BZ",
    "addr:housenumber":"3a",
    "addr:postcode":"se18 7bz",
    "addr:street":"Plumstead Road",
    "iso:country":"GB",
    "sg:address":"3a Plumstead Road",
    "sg:city":"London",
    "sg:classifiers":[
        {
            "category":"Shopping",
            "subcategory":"Hobbies, Toys, & Games",
            "type":"Retail Goods"
        }
    ],
    "sg:phone":"+44 20 8854 5996",
    "sg:postcode":"SE18 7BZ",
    "sg:province":"Greater London",
    "sg:tags":[
        "computer"
    ],
    "wof:name":"The Game Shop",
    "wof:placetype":"venue"
},
  "geometry": {"coordinates":[0.0705379993,51.4912071228],"type":"Point"}
}