{
  "type": "Feature",
  "properties": {
    "iso:country":"GB",
    "sg:address":"26 Coach Street",
    "sg:city":"Skipton",
    "sg:classifiers":[
        {
            "category":"Shopping",
            "subcategory":"Hobbies, Toys, & Games",
            "type":"Retail Goods"
        }
    ],
    "sg:phone":"+44 1756 700088",
    "sg:postcode":"BD23 1LH",
    "sg:province":"Lancashire",
    "sg:tags":[
        "computer"
    ],
    "wof:name":"Game X Change",
    "wof:placetype":"venue"
},
  "geometry": {"coordinates":[-2.0193591118,53.9609527588],"type":"Point"}
}