{
  "type": "Feature",
  "properties": {
    "iso:country":"GB",
    "sg:address":"Units 5-8, York House, Langston Road",
    "sg:city":"Loughton",
    "sg:classifiers":[
        {
            "category":"Building & Trades",
            "subcategory":"Plumbing",
            "type":"Services"
        }
    ],
    "sg:phone":"+44 1474 815577",
    "sg:postcode":"IG10 3TL",
    "sg:province":"Essex",
    "sg:tags":[
        "drain",
        "clearance",
        "sewer"
    ],
    "wof:name":"Aquaflow Drainage & Plumbing Services Ltd.",
    "wof:placetype":"venue"
},
  "geometry": {"coordinates":[0.055179,51.647373],"type":"Point"}
}