{
  "type": "Feature",
  "properties": {
    "iso:country":"GB",
    "sg:address":"10 Victoria Road, Ellesmere Park Eccles",
    "sg:city":"Manchester",
    "sg:classifiers":[
        {
            "category":"Social Services",
            "subcategory":"Retirement Home",
            "type":"Services"
        }
    ],
    "sg:phone":"+44 161 789 1041",
    "sg:postcode":"M30 9HB",
    "sg:province":"Greater Manchester",
    "sg:tags":[
        "residential",
        "care"
    ],
    "wof:name":"The New Granville",
    "wof:placetype":"venue"
},
  "geometry": {"coordinates":[-2.341208,53.488304],"type":"Point"}
}