{
  "type": "Feature",
  "properties": {
    "addr:full":"81 Station Road, Deganwy Conwy Conwy LL31 9EJ",
    "addr:housenumber":"81",
    "addr:postcode":"ll31 9ej",
    "addr:street":"Station Road",
    "iso:country":"GB",
    "sg:address":"81 Station Road, Deganwy",
    "sg:city":"Conwy",
    "sg:classifiers":[
        {
            "category":"Real Estate",
            "subcategory":"Architect",
            "type":"Services"
        }
    ],
    "sg:phone":"+44 1492 583036",
    "sg:postcode":"LL31 9EJ",
    "sg:province":"Conwy",
    "wof:name":"Simon Tarmaster",
    "wof:placetype":"venue"
},
  "geometry": {"coordinates":[-3.8316230774,53.2944335938],"type":"Point"}
}