{
  "type": "Feature",
  "properties": {
    "iso:country":"GB",
    "sg:address":"19 Station Road, Clowne",
    "sg:city":"Chesterfield",
    "sg:classifiers":[
        {
            "category":"Utilities",
            "subcategory":"Refuse",
            "type":"Services"
        }
    ],
    "sg:phone":"+44 1246 810215",
    "sg:postcode":"S43 4RN",
    "sg:province":"Derbyshire",
    "sg:tags":[
        "disposal",
        "waste"
    ],
    "wof:name":"Biffa Waste Services",
    "wof:placetype":"venue"
},
  "geometry": {"coordinates":[-1.259363,53.277832],"type":"Point"}
}