{
  "type": "Feature",
  "properties": {
    "iso:country":"GB",
    "sg:address":"The Highland, 82 The Ridgeway",
    "sg:city":"Enfield",
    "sg:classifiers":[
        {
            "category":"Professional",
            "subcategory":"Accounting & Tax Preparation",
            "type":"Services"
        }
    ],
    "sg:phone":"+44 20 8366 0874",
    "sg:postcode":"EN2 8JQ",
    "sg:province":"Greater London",
    "sg:tags":[
        "accountant"
    ],
    "wof:name":"Pyne Gilbert & Co",
    "wof:placetype":"venue"
},
  "geometry": {"coordinates":[-0.104567,51.663536],"type":"Point"}
}