{
  "type": "Feature",
  "properties": {
    "addr:full":"Rising Sun, High St, Bream Lydney Gloucestershire GL15 6JF",
    "addr:postcode":"gl15 6jf",
    "addr:street":"High St",
    "iso:country":"GB",
    "sg:address":"Rising Sun, High St, Bream",
    "sg:city":"Lydney",
    "sg:classifiers":[
        {
            "category":"Bars & Pubs",
            "type":"Food & Drink"
        }
    ],
    "sg:phone":"+44 1594 564555",
    "sg:postcode":"GL15 6JF",
    "sg:province":"Gloucestershire",
    "sg:tags":[
        "pubs",
        "inn"
    ],
    "wof:name":"JP Leisure",
    "wof:placetype":"venue"
},
  "geometry": {"coordinates":[-2.574489,51.750587],"type":"Point"}
}