{
  "type": "Feature",
  "properties": {
    "addr:full":"70 Western Road Brighton East Sussex BN1 2HA",
    "addr:housenumber":"70",
    "addr:postcode":"bn1 2ha",
    "addr:street":"Western Road",
    "iso:country":"GB",
    "sg:address":"70 Western Road",
    "sg:city":"Brighton",
    "sg:classifiers":[
        {
            "category":"Shopping",
            "subcategory":"Clothing, Apparel, & Fashions",
            "type":"Retail Goods"
        }
    ],
    "sg:postcode":"BN1 2HA",
    "sg:province":"East Sussex",
    "sg:tags":[
        "shop"
    ],
    "wof:name":"Denim Den",
    "wof:placetype":"venue"
},
  "geometry": {"coordinates":[-0.149495,50.824211],"type":"Point"}
}