{
  "type": "Feature",
  "properties": {
    "addr:full":"Unit 6 Banbury Av Slough Berkshire SL1 4LR",
    "addr:housenumber":"unit 6",
    "addr:postcode":"sl1 4lr",
    "addr:street":"Banbury Av",
    "iso:country":"GB",
    "sg:address":"Unit 6 Banbury Av",
    "sg:city":"Slough",
    "sg:classifiers":[
        {
            "category":"Retail",
            "subcategory":"Auto Repair",
            "type":"Services"
        }
    ],
    "sg:phone":"+44 1753 821557",
    "sg:postcode":"SL1 4LR",
    "sg:province":"Berkshire",
    "sg:tags":[
        "car",
        "upholsterer"
    ],
    "wof:name":"Burwood Automotive Ltd.",
    "wof:placetype":"venue"
},
  "geometry": {"coordinates":[-0.6338279843,51.5258865356],"type":"Point"}
}