{
  "type": "Feature",
  "properties": {
    "iso:country":"GB",
    "sg:address":"1 Broadway Close",
    "sg:city":"Witney",
    "sg:classifiers":[
        {
            "category":"Personal",
            "type":"Services"
        }
    ],
    "sg:phone":"+44 1993 774173",
    "sg:postcode":"OX28 5GG",
    "sg:province":"Oxfordshire",
    "sg:tags":[
        "dressmaker"
    ],
    "wof:name":"A E Gibb",
    "wof:placetype":"venue"
},
  "geometry": {"coordinates":[-1.5100150108,51.7893409729],"type":"Point"}
}