{
  "type": "Feature",
  "properties": {
    "addr:full":"11 Grosvenor Cresent Westminster Greater London SW1X 7EE",
    "addr:housenumber":"11",
    "addr:postcode":"sw1x 7ee",
    "addr:street":"Grosvenor Cresent",
    "iso:country":"GB",
    "sg:address":"11 Grosvenor Cresent",
    "sg:city":"Westminster",
    "sg:classifiers":[
        {
            "category":"Real Estate",
            "subcategory":"Surveying",
            "type":"Services"
        }
    ],
    "sg:phone":"+44 20 7235 9330",
    "sg:postcode":"SW1X 7EE",
    "sg:province":"Greater London",
    "sg:tags":[
        "building",
        "surveyor"
    ],
    "wof:name":"Santoreid",
    "wof:placetype":"venue"
},
  "geometry": {"coordinates":[-0.154361,51.501957],"type":"Point"}
}