{
  "type": "Feature",
  "properties": {
    "addr:full":"34 Jubilee Drive Loughborough Leicestershire LE11 5TU",
    "addr:housenumber":"34",
    "addr:postcode":"le11 5tu",
    "addr:street":"Jubilee Drive",
    "iso:country":"GB",
    "sg:address":"34 Jubilee Drive",
    "sg:city":"Loughborough",
    "sg:classifiers":[
        {
            "category":"Wholesale",
            "subcategory":"Vending Machines",
            "type":"Manufacturing & Wholesale Goods"
        }
    ],
    "sg:phone":"+44 1509 230481",
    "sg:postcode":"LE11 5TU",
    "sg:province":"Leicestershire",
    "sg:tags":[
        "rental",
        "sale",
        "supply"
    ],
    "wof:name":"Midland Vending Services Ltd.",
    "wof:placetype":"venue"
},
  "geometry": {"coordinates":[-1.214058,52.781036],"type":"Point"}
}