{
  "type": "Feature",
  "properties": {
    "addr:full":"Crouch End Hill Hornsey Greater London N8 8AX",
    "addr:postcode":"n8 8ax",
    "addr:street":"End Hill",
    "iso:country":"GB",
    "sg:address":"Crouch End Hill",
    "sg:city":"Hornsey",
    "sg:classifiers":[
        {
            "category":"Place Of Worship",
            "type":"Public Place"
        }
    ],
    "sg:phone":"+44 20 8340 1566",
    "sg:postcode":"N8 8AX",
    "sg:province":"Greater London",
    "wof:name":"Christ Church C of E Church",
    "wof:placetype":"venue"
},
  "geometry": {"coordinates":[-0.123954,51.578403],"type":"Point"}
}