{
  "type": "Feature",
  "properties": {
    "addr:full":"53 Sloane Street London Greater London SW1X 9SW",
    "addr:housenumber":"53",
    "addr:postcode":"sw1x 9sw",
    "addr:street":"Sloane Street",
    "iso:country":"GB",
    "sg:address":"53 Sloane Street",
    "sg:city":"London",
    "sg:classifiers":[
        {
            "category":"Health Services",
            "subcategory":"Doctor",
            "type":"Services"
        }
    ],
    "sg:postcode":"SW1X 9SW",
    "sg:province":"Greater London",
    "sg:tags":[
        "practitioners"
    ],
    "wof:name":"Knightsbridge Diagnostic Ultra Sound",
    "wof:placetype":"venue"
},
  "geometry": {"coordinates":[-0.1594019979,51.4979553223],"type":"Point"}
}