{
  "type": "Feature",
  "properties": {
    "addr:full":"Exeter Rd South Brent Devon TQ10 9DF",
    "addr:postcode":"tq10 9df",
    "addr:street":"Exeter Rd",
    "iso:country":"GB",
    "sg:address":"Exeter Rd",
    "sg:city":"South Brent",
    "sg:classifiers":[
        {
            "category":"Autos & Motor Vehicles",
            "subcategory":"Fuel & Gas Station",
            "type":"Retail Goods"
        }
    ],
    "sg:phone":"+44 1364 73335",
    "sg:postcode":"TQ10 9DF",
    "sg:province":"Devon",
    "sg:tags":[
        "petrol",
        "filling"
    ],
    "wof:name":"Brooklands Garage",
    "wof:placetype":"venue"
},
  "geometry": {"coordinates":[-3.828564,50.424854],"type":"Point"}
}