{
  "type": "Feature",
  "properties": {
    "iso:country":"GB",
    "sg:address":"386 Coventry Road, Small Heath",
    "sg:city":"Birmingham",
    "sg:classifiers":[
        {
            "category":"Health Services",
            "subcategory":"Optometrist",
            "type":"Services"
        }
    ],
    "sg:phone":"+44 121 773 7327",
    "sg:postcode":"B10 0UF",
    "sg:province":"West Midlands",
    "sg:tags":[
        "optician"
    ],
    "wof:name":"Euro Specs",
    "wof:placetype":"venue"
},
  "geometry": {"coordinates":[-1.862219,52.471371],"type":"Point"}
}