{
  "type": "Feature",
  "properties": {
    "addr:full":"39 Long Street, Wigston Leicester Leicestershire LE18 2AJ",
    "addr:housenumber":"39",
    "addr:postcode":"le18 2aj",
    "addr:street":"Long Street",
    "iso:country":"GB",
    "sg:address":"39 Long Street, Wigston",
    "sg:city":"Leicester",
    "sg:classifiers":[
        {
            "category":"Organizations",
            "subcategory":"Membership Organization",
            "type":"Services"
        }
    ],
    "sg:phone":"+44 116 288 3020",
    "sg:postcode":"LE18 2AJ",
    "sg:province":"Leicestershire",
    "sg:tags":[
        "club"
    ],
    "wof:name":"Great Wigston Working Men's Club & Institute Ltd.",
    "wof:placetype":"venue"
},
  "geometry": {"coordinates":[-1.107046,52.584641],"type":"Point"}
}