{
  "type": "Feature",
  "properties": {
    "addr:full":"6 Kings Park Road Glasgow East Renfrewshire G44 4TU",
    "addr:housenumber":"6",
    "addr:postcode":"g44 4tu",
    "addr:street":"Kings Park Road",
    "iso:country":"GB",
    "sg:address":"6 Kings Park Road",
    "sg:city":"Glasgow",
    "sg:classifiers":[
        {
            "category":"Retail",
            "subcategory":"Laundry & Dry Cleaning",
            "type":"Services"
        }
    ],
    "sg:phone":"+44 141 649 0700",
    "sg:postcode":"G44 4TU",
    "sg:province":"East Renfrewshire",
    "sg:tags":[
        "home",
        "ironing"
    ],
    "wof:name":"Pressed for Success",
    "wof:placetype":"venue"
},
  "geometry": {"coordinates":[-4.258485,55.823055],"type":"Point"}
}