{
  "type": "Feature",
  "properties": {
    "addr:full":"Pry House Hawes North Yorkshire DL8 3LP",
    "addr:postcode":"dl8 3lp",
    "addr:street":"Hawes",
    "iso:country":"GB",
    "sg:address":"Pry House",
    "sg:city":"Hawes",
    "sg:classifiers":[
        {
            "category":"Farming",
            "subcategory":"Livestock Farm",
            "type":"Manufacturing & Wholesale Goods"
        }
    ],
    "sg:postcode":"DL8 3LP",
    "sg:province":"North Yorkshire",
    "sg:tags":[
        "others"
    ],
    "wof:name":"A T Fawcett",
    "wof:placetype":"venue"
},
  "geometry": {"coordinates":[-2.1994268894,54.3041763306],"type":"Point"}
}