{
  "type": "Feature",
  "properties": {
    "addr:full":"The Apex, Tunnockside Park Glasgow Glasgow City G71 5PE",
    "addr:postcode":"g71 5pe",
    "iso:country":"GB",
    "sg:address":"The Apex, Tunnockside Park",
    "sg:city":"Glasgow",
    "sg:classifiers":[
        {
            "category":"Shopping",
            "subcategory":"Stationery & Office Supplies",
            "type":"Retail Goods"
        },
        {
            "category":"Professional",
            "subcategory":"Printing & Photocopies",
            "type":"Services"
        }
    ],
    "sg:phone":"+44 1698 815222",
    "sg:postcode":"G71 5PE",
    "sg:province":"Glasgow City",
    "sg:tags":[
        "process",
        "screen",
        "printer",
        "printers'"
    ],
    "wof:name":"Coates Screen",
    "wof:placetype":"venue"
},
  "geometry": {"coordinates":[-4.0672,55.833649],"type":"Point"}
}