{
  "type": "Feature",
  "properties": {
    "iso:country":"GB",
    "sg:address":"6 Dales Terrace, Stanhope",
    "sg:city":"Bishop Auckland",
    "sg:classifiers":[
        {
            "category":"Real Estate",
            "subcategory":"Real Estate Agent",
            "type":"Services"
        }
    ],
    "sg:phone":"+44 1388 528184",
    "sg:postcode":"DL13 2XH",
    "sg:province":"Durham",
    "wof:name":"J W Wood Ltd",
    "wof:placetype":"venue"
},
  "geometry": {"coordinates":[-2.0026209354,54.7460174561],"type":"Point"}
}