{
  "type": "Feature",
  "properties": {
    "iso:country":"GB",
    "sg:address":"Resident Mangers Flat, 21 Hylton Court, Bowmonts Road",
    "sg:city":"Tadley",
    "sg:classifiers":[
        {
            "category":"Organizations",
            "subcategory":"Community Association",
            "type":"Services"
        }
    ],
    "sg:phone":"+44 118 981 2060",
    "sg:postcode":"RG26 3SH",
    "sg:province":"Berkshire",
    "sg:tags":[
        "co-operatives",
        "society",
        "housing",
        "trust"
    ],
    "wof:name":"Housing 21",
    "wof:placetype":"venue"
},
  "geometry": {"coordinates":[-1.1375410557,51.3501625061],"type":"Point"}
}