{
  "type": "Feature",
  "properties": {
    "addr:full":"Cross St Sudbury Essex CO10 6DP",
    "addr:postcode":"co10 6dp",
    "addr:street":"Cross St",
    "iso:country":"GB",
    "sg:address":"Cross St",
    "sg:city":"Sudbury",
    "sg:classifiers":[
        {
            "category":"Bars & Pubs",
            "type":"Food & Drink"
        }
    ],
    "sg:phone":"+44 1787 377545",
    "sg:postcode":"CO10 6DP",
    "sg:province":"Essex",
    "sg:tags":[
        "pubs",
        "inn"
    ],
    "wof:name":"Spread Eagle",
    "wof:placetype":"venue"
},
  "geometry": {"coordinates":[0.723435,52.037704],"type":"Point"}
}