{
  "type": "Feature",
  "properties": {
    "addr:full":"53 The Warren Worcester Park Surrey KT4 7DH",
    "addr:housenumber":"53",
    "addr:postcode":"kt4 7dh",
    "addr:street":"The Warren;Park",
    "iso:country":"GB",
    "sg:address":"53 The Warren",
    "sg:city":"Worcester Park",
    "sg:classifiers":[
        {
            "category":"Professional",
            "subcategory":"Detective & Security Services",
            "type":"Services"
        }
    ],
    "sg:phone":"+44 20 8337 5332",
    "sg:postcode":"KT4 7DH",
    "sg:province":"Surrey",
    "sg:tags":[
        "alarm",
        "burglar",
        "system"
    ],
    "wof:name":"Bellmont Security Systems",
    "wof:placetype":"venue"
},
  "geometry": {"coordinates":[-0.263275,51.372452],"type":"Point"}
}