{
  "type": "Feature",
  "properties": {
    "addr:full":"Cricket Ground Road Norwich Norfolk NR1 3AZ",
    "addr:postcode":"nr1 3az",
    "addr:street":"Ground Road Norwich Norfolk",
    "iso:country":"GB",
    "sg:address":"Cricket Ground Road",
    "sg:city":"Norwich",
    "sg:classifiers":[
        {
            "category":"Organizations",
            "subcategory":"Membership Organization",
            "type":"Services"
        }
    ],
    "sg:phone":"+44 1603 477489",
    "sg:postcode":"NR1 3AZ",
    "sg:province":"Norfolk",
    "sg:tags":[
        "club"
    ],
    "wof:name":"Norfolk Lawn Tennis Association",
    "wof:placetype":"venue"
},
  "geometry": {"coordinates":[1.3001500368,52.6176185608],"type":"Point"}
}