{
  "type": "Feature",
  "properties": {
    "addr:full":"8 Myrtle Walk, Cambuslang Glasgow South Lanarkshire G72 8BU",
    "addr:housenumber":"8",
    "addr:postcode":"g72 8bu",
    "addr:street":"Myrtle Walk",
    "iso:country":"GB",
    "sg:address":"8 Myrtle Walk, Cambuslang",
    "sg:city":"Glasgow",
    "sg:classifiers":[
        {
            "category":"Building & Trades",
            "subcategory":"Construction",
            "type":"Services"
        }
    ],
    "sg:phone":"+44 141 641 7014",
    "sg:postcode":"G72 8BU",
    "sg:province":"South Lanarkshire",
    "sg:tags":[
        "contractor"
    ],
    "wof:name":"Cope Construction",
    "wof:placetype":"venue"
},
  "geometry": {"coordinates":[-4.1741118431,55.8189048767],"type":"Point"}
}