{
  "type": "Feature",
  "properties": {
    "addr:full":"Conveyancing, 12a High Street Telford Shropshire TF7 5AQ",
    "addr:housenumber":"12a",
    "addr:postcode":"tf7 5aq",
    "addr:street":"Conveyancing;High Street",
    "iso:country":"GB",
    "sg:address":"Conveyancing, 12a High Street",
    "sg:city":"Telford",
    "sg:classifiers":[
        {
            "category":"Professional",
            "subcategory":"Lawyer & Legal Services",
            "type":"Services"
        }
    ],
    "sg:postcode":"TF7 5AQ",
    "sg:province":"Shropshire",
    "sg:tags":[
        "solicitor"
    ],
    "wof:name":"Howells Williams Solicitors",
    "wof:placetype":"venue"
},
  "geometry": {"coordinates":[-2.4493401051,52.6365890503],"type":"Point"}
}