{
  "type": "Feature",
  "properties": {
    "addr:full":"59 Buchanan St Blackpool Lancashire FY1 3LS",
    "addr:housenumber":"59",
    "addr:postcode":"fy1 3ls",
    "addr:street":"Buchanan St",
    "iso:country":"GB",
    "sg:address":"59 Buchanan St",
    "sg:city":"Blackpool",
    "sg:classifiers":[
        {
            "category":"Shopping",
            "subcategory":"Music",
            "type":"Retail Goods"
        }
    ],
    "sg:phone":"+44 1253 292006",
    "sg:postcode":"FY1 3LS",
    "sg:province":"Lancashire",
    "sg:tags":[
        "record",
        "tape",
        "cd"
    ],
    "wof:name":"Club Verge Ltd",
    "wof:placetype":"venue"
},
  "geometry": {"coordinates":[-3.045319,53.820591],"type":"Point"}
}