{
  "type": "Feature",
  "properties": {
    "iso:country":"GB",
    "sg:address":"47 Newgate Street",
    "sg:city":"Morpeth",
    "sg:classifiers":[
        {
            "category":"Professional",
            "subcategory":"Lawyer & Legal Services",
            "type":"Services"
        }
    ],
    "sg:phone":"+44 1670 512391",
    "sg:postcode":"NE61 1AT",
    "sg:province":"Northumberland",
    "sg:tags":[
        "solicitor"
    ],
    "wof:name":"R A W Clark & Co.",
    "wof:placetype":"venue"
},
  "geometry": {"coordinates":[-1.69108,55.168686],"type":"Point"}
}