{
  "type": "Feature",
  "properties": {
    "iso:country":"GB",
    "sg:address":"55 Gowthorpe",
    "sg:city":"Selby",
    "sg:classifiers":[
        {
            "category":"Shopping",
            "subcategory":"Comic Books",
            "type":"Retail Goods"
        }
    ],
    "sg:phone":"+44 1757 703769",
    "sg:postcode":"YO8 4HE",
    "sg:province":"East Riding of Yorkshire",
    "sg:tags":[
        "jeweller"
    ],
    "wof:name":"Rowen Jewellers",
    "wof:placetype":"venue"
},
  "geometry": {"coordinates":[-1.072724,53.783398],"type":"Point"}
}