{
  "type": "Feature",
  "properties": {
    "addr:full":"Unit 35 Winpenny Road, Parkhouse Industrial Estate Newcastle Staffordshire ST5 7RH",
    "addr:housenumber":"unit 35",
    "addr:postcode":"st5 7rh",
    "addr:street":"Winpenny Road Parkhouse Industrial Estate",
    "iso:country":"GB",
    "sg:address":"Unit 35 Winpenny Road, Parkhouse Industrial Estate",
    "sg:city":"Newcastle",
    "sg:classifiers":[
        {
            "category":"Retail",
            "subcategory":"Auto Repair",
            "type":"Services"
        }
    ],
    "sg:postcode":"ST5 7RH",
    "sg:province":"Staffordshire",
    "sg:tags":[
        "modification",
        "garage"
    ],
    "wof:name":"Abbey Motor Services",
    "wof:placetype":"venue"
},
  "geometry": {"coordinates":[-2.239329,53.04734],"type":"Point"}
}