{
  "type": "Feature",
  "properties": {
    "addr:full":"Oakwood, Marsden Lane Huddersfield West Yorkshire HD7 6AF",
    "addr:postcode":"hd7 6af",
    "addr:street":"Marsden Lane",
    "iso:country":"GB",
    "sg:address":"Oakwood, Marsden Lane",
    "sg:city":"Huddersfield",
    "sg:classifiers":[
        {
            "category":"Building & Trades",
            "subcategory":"Construction",
            "type":"Services"
        }
    ],
    "sg:postcode":"HD7 6AF",
    "sg:province":"West Yorkshire",
    "sg:tags":[
        "builder"
    ],
    "wof:name":"Oakwood Building Ltd.",
    "wof:placetype":"venue"
},
  "geometry": {"coordinates":[-1.9212440252,53.6021385193],"type":"Point"}
}