{
  "type": "Feature",
  "properties": {
    "addr:full":"21 Egerton Rd, Davenport Stockport Cheshire SK3 8SR",
    "addr:housenumber":"21",
    "addr:postcode":"sk3 8sr",
    "addr:street":"Egerton Rd",
    "iso:country":"GB",
    "sg:address":"21 Egerton Rd, Davenport",
    "sg:city":"Stockport",
    "sg:classifiers":[
        {
            "category":"Social Services",
            "subcategory":"Child Care",
            "type":"Services"
        }
    ],
    "sg:phone":"+44 161 483 2815",
    "sg:postcode":"SK3 8SR",
    "sg:province":"Cheshire",
    "sg:tags":[
        "children's",
        "home"
    ],
    "wof:name":"Broadfields Children's Homes",
    "wof:placetype":"venue"
},
  "geometry": {"coordinates":[-2.150962,53.38726],"type":"Point"}
}