{
  "type": "Feature",
  "properties": {
    "addr:full":"Unit 3c Off Snowdon Drive, Winterhill Milton Keynes Buckinghamshire MK6 1AJ",
    "addr:housenumber":"unit 3c off",
    "addr:postcode":"mk6 1aj",
    "addr:street":"Snowdon Drive",
    "iso:country":"GB",
    "sg:address":"Unit 3c Off Snowdon Drive, Winterhill",
    "sg:city":"Milton Keynes",
    "sg:classifiers":[
        {
            "category":"Building & Trades",
            "subcategory":"Equipment Rental",
            "type":"Services"
        }
    ],
    "sg:phone":"+44 1908 233411",
    "sg:postcode":"MK6 1AJ",
    "sg:province":"Buckinghamshire",
    "sg:tags":[
        "hire",
        "centre"
    ],
    "wof:name":"Hss Site Services",
    "wof:placetype":"venue"
},
  "geometry": {"coordinates":[-0.762579,52.027676],"type":"Point"}
}