{
  "type": "Feature",
  "properties": {
    "iso:country":"GB",
    "sg:address":"Sales Office, Po Box 83, Castle Works",
    "sg:city":"Cardiff",
    "sg:classifiers":[
        {
            "category":"Manufacturing",
            "subcategory":"Metals",
            "type":"Manufacturing & Wholesale Goods"
        }
    ],
    "sg:phone":"+44 29 2058 2016",
    "sg:postcode":"CF24 2XQ",
    "sg:province":"Cardiff",
    "sg:tags":[
        "steel",
        "mnfrs"
    ],
    "wof:name":"Cardiff Rod & Reinforcement",
    "wof:placetype":"venue"
},
  "geometry": {"coordinates":[-3.1449699402,51.4873504639],"type":"Point"}
}