{
  "type": "Feature",
  "properties": {
    "addr:full":"60 Churchill Square Brighton East Sussex BN1 2TE",
    "addr:housenumber":"60",
    "addr:postcode":"bn1 2te",
    "addr:street":"Churchill Square",
    "iso:country":"GB",
    "sg:address":"60 Churchill Square",
    "sg:city":"Brighton",
    "sg:classifiers":[
        {
            "category":"Shopping",
            "subcategory":"Optician",
            "type":"Retail Goods"
        }
    ],
    "sg:phone":"+44 1273 737901",
    "sg:postcode":"BN1 2TE",
    "sg:province":"East Sussex",
    "wof:name":"Vision Express Optical Lab",
    "wof:placetype":"venue"
},
  "geometry": {"coordinates":[-0.1460600048,50.8225517273],"type":"Point"}
}