{
  "type": "Feature",
  "properties": {
    "addr:full":"28 Cernan Ct Nottingham Nottinghamshire NG6 7AX",
    "addr:housenumber":"28",
    "addr:postcode":"ng6 7ax",
    "addr:street":"Cernan Ct",
    "iso:country":"GB",
    "sg:address":"28 Cernan Ct",
    "sg:city":"Nottingham",
    "sg:classifiers":[
        {
            "category":"Personal",
            "subcategory":"Beauty Salon",
            "type":"Services"
        }
    ],
    "sg:phone":"+44 115 927 4807",
    "sg:postcode":"NG6 7AX",
    "sg:province":"Nottinghamshire",
    "sg:tags":[
        "unisex",
        "hairdresser"
    ],
    "wof:name":"Panache",
    "wof:placetype":"venue"
},
  "geometry": {"coordinates":[-1.21485,52.99419],"type":"Point"}
}