{
  "type": "Feature",
  "properties": {
    "iso:country":"GB",
    "sg:address":"59 Lynton Avenue",
    "sg:city":"Romford",
    "sg:classifiers":[
        {
            "category":"Home & Garden",
            "subcategory":"Building Materials",
            "type":"Retail Goods"
        }
    ],
    "sg:phone":"+44 1708 766661",
    "sg:postcode":"RM7 8NH",
    "sg:province":"Essex",
    "sg:tags":[
        "fencing"
    ],
    "wof:name":"D A Smith Fencing",
    "wof:placetype":"venue"
},
  "geometry": {"coordinates":[0.163149,51.594532],"type":"Point"}
}