{
  "type": "Feature",
  "properties": {
    "addr:full":"Norcroft Farm, Silkstone Lane, Silkstone Barnsley South Yorkshire S75 4JZ",
    "addr:postcode":"s75 4jz",
    "addr:street":"Silkstone Lane;Yorkshire",
    "iso:country":"GB",
    "sg:address":"Norcroft Farm, Silkstone Lane, Silkstone",
    "sg:city":"Barnsley",
    "sg:classifiers":[
        {
            "category":"Farming",
            "subcategory":"Farm",
            "type":"Manufacturing & Wholesale Goods"
        }
    ],
    "sg:postcode":"S75 4JZ",
    "sg:province":"South Yorkshire",
    "sg:tags":[
        "mixed",
        "crop"
    ],
    "wof:name":"Geoffrey Wilson Mosley",
    "wof:placetype":"venue"
},
  "geometry": {"coordinates":[-1.565694,53.54372],"type":"Point"}
}