{
  "type": "Feature",
  "properties": {
    "addr:full":"139 Old Road Clacton-on-sea Essex CO15 3AT",
    "addr:housenumber":"139",
    "addr:postcode":"co15 3at",
    "addr:street":"Old Road",
    "iso:country":"GB",
    "sg:address":"139 Old Road",
    "sg:city":"Clacton-on-sea",
    "sg:classifiers":[
        {
            "category":"Home & Garden",
            "subcategory":"Building Materials",
            "type":"Retail Goods"
        },
        {
            "category":"Home & Garden",
            "subcategory":"Furniture",
            "type":"Retail Goods"
        }
    ],
    "sg:postcode":"CO15 3AT",
    "sg:province":"Essex",
    "sg:tags":[
        "furnishers",
        "bathroom",
        "planner"
    ],
    "wof:name":"Bathroom Studios",
    "wof:placetype":"venue"
},
  "geometry": {"coordinates":[1.1482629776,51.7948913574],"type":"Point"}
}