{
  "type": "Feature",
  "properties": {
    "addr:full":"9 Wood End Road Harpenden Hertfordshire AL5 3EE",
    "addr:housenumber":"9",
    "addr:postcode":"al5 3ee",
    "addr:street":"Wood End Road",
    "iso:country":"GB",
    "sg:address":"9 Wood End Road",
    "sg:city":"Harpenden",
    "sg:classifiers":[
        {
            "category":"Professional",
            "subcategory":"Management & Consulting",
            "type":"Services"
        }
    ],
    "sg:postcode":"AL5 3EE",
    "sg:province":"Hertfordshire",
    "sg:tags":[
        "consultant",
        "business"
    ],
    "wof:name":"Personnel Matters",
    "wof:placetype":"venue"
},
  "geometry": {"coordinates":[-0.377945,51.825459],"type":"Point"}
}