{
  "type": "Feature",
  "properties": {
    "addr:full":"30 Cannon Park Way Middlesbrough North Yorkshire TS1 5JU",
    "addr:housenumber":"30",
    "addr:postcode":"ts1 5ju",
    "addr:street":"Cannon Park Way",
    "iso:country":"GB",
    "sg:address":"30 Cannon Park Way",
    "sg:city":"Middlesbrough",
    "sg:classifiers":[
        {
            "category":"Bus Charters",
            "type":"Transportation"
        }
    ],
    "sg:phone":"+44 1642 223433",
    "sg:postcode":"TS1 5JU",
    "sg:province":"North Yorkshire",
    "sg:tags":[
        "coach"
    ],
    "wof:name":"Community Transport (Middlesbrough) Ltd.",
    "wof:placetype":"venue"
},
  "geometry": {"coordinates":[-1.248567,54.575588],"type":"Point"}
}