{
  "type": "Feature",
  "properties": {
    "addr:full":"Upper Shide Mill House, Blackwater Road Newport Isle of Wight PO30 3BB",
    "addr:postcode":"po30 3bb",
    "addr:street":"Upper Shide;Blackwater Road",
    "iso:country":"GB",
    "sg:address":"Upper Shide Mill House, Blackwater Road",
    "sg:city":"Newport",
    "sg:classifiers":[
        {
            "category":"Organizations",
            "subcategory":"Non-profit Organization",
            "type":"Services"
        }
    ],
    "sg:phone":"+44 1983 523833",
    "sg:postcode":"PO30 3BB",
    "sg:province":"Isle of Wight",
    "sg:tags":[
        "charitable",
        "organisation",
        "voluntary",
        "charity"
    ],
    "wof:name":"Friends of the Earth",
    "wof:placetype":"venue"
},
  "geometry": {"coordinates":[-1.288204,50.689548],"type":"Point"}
}