{
  "type": "Feature",
  "properties": {
    "iso:country":"GB",
    "sg:address":"7 Pen-y-bryn Rd, Gabalfa",
    "sg:city":"Cardiff",
    "sg:classifiers":[
        {
            "category":"Arts & Performance",
            "subcategory":"Music",
            "type":"Entertainment"
        }
    ],
    "sg:postcode":"CF14 3LG",
    "sg:province":"Cardiff",
    "sg:tags":[
        "mobile",
        "disco"
    ],
    "wof:name":"Dimodica,Frank,",
    "wof:placetype":"venue"
},
  "geometry": {"coordinates":[-3.192283,51.50182],"type":"Point"}
}