{
  "type": "Feature",
  "properties": {
    "addr:full":"21 Arndale Centre Eastbourne East Sussex BN21 3NW",
    "addr:housenumber":"21",
    "addr:postcode":"bn21 3nw",
    "addr:street":"Arndale Centre",
    "iso:country":"GB",
    "sg:address":"21 Arndale Centre",
    "sg:city":"Eastbourne",
    "sg:classifiers":[
        {
            "category":"Home & Garden",
            "subcategory":"Household Appliances",
            "type":"Retail Goods"
        }
    ],
    "sg:phone":"+44 1323 728372",
    "sg:postcode":"BN21 3NW",
    "sg:province":"East Sussex",
    "sg:tags":[
        "gas"
    ],
    "wof:name":"British Gas Energy Centre",
    "wof:placetype":"venue"
},
  "geometry": {"coordinates":[0.28535,50.766911],"type":"Point"}
}