{
  "type": "Feature",
  "properties": {
    "addr:full":"Unit 8, Eagle Estate, Brookers Road Billingshurst West Sussex RH14 9RZ",
    "addr:housenumber":"unit 8",
    "addr:postcode":"rh14 9rz",
    "addr:street":"Eagle Estate Brookers Road",
    "iso:country":"GB",
    "sg:address":"Unit 8, Eagle Estate, Brookers Road",
    "sg:city":"Billingshurst",
    "sg:classifiers":[
        {
            "category":"Sports & Exercise",
            "subcategory":"Tennis Court",
            "type":"Entertainment"
        }
    ],
    "sg:phone":"+44 1403 783844",
    "sg:postcode":"RH14 9RZ",
    "sg:province":"West Sussex",
    "sg:tags":[
        "breakdown",
        "recovery"
    ],
    "wof:name":"Billingshurst Auto Engineering",
    "wof:placetype":"venue"
},
  "geometry": {"coordinates":[-0.452428,51.021183],"type":"Point"}
}