{
  "type": "Feature",
  "properties": {
    "addr:full":"8 Ladywell Centre Newtown Powys SY16 1AF",
    "addr:housenumber":"8",
    "addr:postcode":"sy16 1af",
    "addr:street":"Ladywell Centre",
    "iso:country":"GB",
    "sg:address":"8 Ladywell Centre",
    "sg:city":"Newtown",
    "sg:classifiers":[
        {
            "category":"Shopping",
            "subcategory":"Clothing, Apparel, & Fashions",
            "type":"Retail Goods"
        }
    ],
    "sg:phone":"+44 1686 625107",
    "sg:postcode":"SY16 1AF",
    "sg:province":"Powys",
    "sg:tags":[
        "shop"
    ],
    "wof:name":"Volcanic",
    "wof:placetype":"venue"
},
  "geometry": {"coordinates":[-3.3246090412,52.5088615417],"type":"Point"}
}