{
  "type": "Feature",
  "properties": {
    "iso:country":"GB",
    "sg:address":"16 Wellington St",
    "sg:city":"Millom",
    "sg:classifiers":[
        {
            "category":"Personal",
            "subcategory":"Beauty Salon",
            "type":"Services"
        }
    ],
    "sg:phone":"+44 1229 771705",
    "sg:postcode":"LA18 4DE",
    "sg:province":"Cumbria",
    "wof:name":"Elegance Beauty Salon",
    "wof:placetype":"venue"
},
  "geometry": {"coordinates":[-3.26725,54.209473],"type":"Point"}
}