{
  "type": "Feature",
  "properties": {
    "iso:country":"GB",
    "sg:address":"Britannia House, 1 Glenthorne Road",
    "sg:city":"London",
    "sg:classifiers":[
        {
            "category":"Travel",
            "subcategory":"Travel Agent",
            "type":"Entertainment"
        }
    ],
    "sg:phone":"+44 20 8749 6859",
    "sg:postcode":"W6 0LF",
    "sg:province":"Greater London",
    "wof:name":"Patagonia Travel",
    "wof:placetype":"venue"
},
  "geometry": {"coordinates":[-0.22681,51.494331],"type":"Point"}
}