{
  "type": "Feature",
  "properties": {
    "iso:country":"GB",
    "sg:address":"Artillery House, 121 Lynchford Road",
    "sg:city":"Farnborough",
    "sg:classifiers":[
        {
            "category":"Professional",
            "subcategory":"Computer Services",
            "type":"Services"
        }
    ],
    "sg:phone":"+44 1252 521733",
    "sg:postcode":"GU14 6ET",
    "sg:province":"Hampshire",
    "sg:tags":[
        "consultant"
    ],
    "wof:name":"Julian Swift Consultancy",
    "wof:placetype":"venue"
},
  "geometry": {"coordinates":[-0.745671,51.274979],"type":"Point"}
}