{
  "type": "Feature",
  "properties": {
    "iso:country":"GB",
    "sg:address":"11 Hollywood Rd",
    "sg:city":"Chingford",
    "sg:classifiers":[
        {
            "category":"Arts & Performance",
            "subcategory":"Music",
            "type":"Entertainment"
        }
    ],
    "sg:phone":"+44 20 8524 1634",
    "sg:postcode":"E4 8JE",
    "sg:province":"Greater London",
    "sg:tags":[
        "mobile",
        "disco"
    ],
    "wof:name":"Atlanta Disco",
    "wof:placetype":"venue"
},
  "geometry": {"coordinates":[-0.029921,51.614025],"type":"Point"}
}