{
  "type": "Feature",
  "properties": {
    "iso:country":"GB",
    "sg:address":"30 Station Road",
    "sg:city":"Liphook",
    "sg:classifiers":[
        {
            "category":"Shopping",
            "subcategory":"Used Merchandise",
            "type":"Retail Goods"
        }
    ],
    "sg:phone":"+44 1428 724364",
    "sg:postcode":"GU30 7DR",
    "sg:province":"Hampshire",
    "sg:tags":[
        "furniture"
    ],
    "wof:name":"J Robinson",
    "wof:placetype":"venue"
},
  "geometry": {"coordinates":[-0.8016149998,51.0712776184],"type":"Point"}
}