{
  "type": "Feature",
  "properties": {
    "iso:country":"GB",
    "sg:address":"3 Becca House, Market St",
    "sg:city":"Pontefract",
    "sg:classifiers":[
        {
            "category":"Professional",
            "subcategory":"Lawyer & Legal Services",
            "type":"Services"
        }
    ],
    "sg:phone":"+44 1977 615522",
    "sg:postcode":"WF9 4JY",
    "sg:province":"West Yorkshire",
    "sg:tags":[
        "solicitor"
    ],
    "wof:name":"John Jones & Co",
    "wof:placetype":"venue"
},
  "geometry": {"coordinates":[-1.35374,53.61237],"type":"Point"}
}