{
  "type": "Feature",
  "properties": {
    "iso:country":"GB",
    "sg:address":"150 Southampton Row",
    "sg:city":"London",
    "sg:classifiers":[
        {
            "category":"Travel",
            "subcategory":"Travel Agent",
            "type":"Entertainment"
        }
    ],
    "sg:postcode":"WC1B 5AL",
    "sg:province":"Greater London",
    "wof:name":"London House Travel Plc",
    "wof:placetype":"venue"
},
  "geometry": {"coordinates":[-0.086025998,51.4784622192],"type":"Point"}
}