{
  "type": "Feature",
  "properties": {
    "iso:country":"GB",
    "sg:address":"85 Milton Road",
    "sg:city":"Gravesend",
    "sg:classifiers":[
        {
            "category":"Autos & Motor Vehicles",
            "subcategory":"Automobile Sales",
            "type":"Retail Goods"
        },
        {
            "category":"Retail",
            "subcategory":"Auto Repair",
            "type":"Services"
        }
    ],
    "sg:phone":"+44 1474 365026",
    "sg:postcode":"DA12 2PP",
    "sg:province":"Kent",
    "sg:tags":[
        "garage",
        "related",
        "car"
    ],
    "wof:name":"G & M Motors",
    "wof:placetype":"venue"
},
  "geometry": {"coordinates":[0.384189,51.439129],"type":"Point"}
}