{
  "type": "Feature",
  "properties": {
    "addr:full":"Oaklawn, Burnhams Road, Bookham Leatherhead Surrey KT23 3BB",
    "addr:postcode":"kt23 3bb",
    "addr:street":"Burnhams Road",
    "iso:country":"GB",
    "sg:address":"Oaklawn, Burnhams Road, Bookham",
    "sg:city":"Leatherhead",
    "sg:classifiers":[
        {
            "category":"Health Services",
            "subcategory":"Doctor",
            "type":"Services"
        }
    ],
    "sg:phone":"+44 1372 457361",
    "sg:postcode":"KT23 3BB",
    "sg:province":"Surrey",
    "sg:tags":[
        "practitioners"
    ],
    "wof:name":"Oaklawn Chartered Physiotherapy & Sports Clinic",
    "wof:placetype":"venue"
},
  "geometry": {"coordinates":[-0.386797,51.285179],"type":"Point"}
}