{
  "type": "Feature",
  "properties": {
    "addr:full":"Fron Heulog Cemaes Bay Isle of Anglesey LL67 0NA",
    "addr:postcode":"ll67 0na",
    "addr:street":"Cemaes Bay",
    "iso:country":"GB",
    "sg:address":"Fron Heulog",
    "sg:city":"Cemaes Bay",
    "sg:classifiers":[
        {
            "category":"Home & Garden",
            "subcategory":"Garden Supply",
            "type":"Retail Goods"
        },
        {
            "category":"Farming",
            "subcategory":"Farm",
            "type":"Manufacturing & Wholesale Goods"
        }
    ],
    "sg:phone":"+44 1407 710846",
    "sg:postcode":"LL67 0NA",
    "sg:province":"Isle of Anglesey",
    "sg:tags":[
        "mixed",
        "bulb",
        "crop",
        "grower"
    ],
    "wof:name":"Messrs Williams",
    "wof:placetype":"venue"
},
  "geometry": {"coordinates":[-4.4518017769,53.4122467041],"type":"Point"}
}