{
  "type": "Feature",
  "properties": {
    "addr:full":"4 Forster Road, Tottenham London Greater London N17 6QD",
    "addr:housenumber":"4",
    "addr:postcode":"n17 6qd",
    "addr:street":"Forster Road",
    "iso:country":"GB",
    "sg:address":"4 Forster Road, Tottenham",
    "sg:city":"London",
    "sg:classifiers":[
        {
            "category":"Professional",
            "subcategory":"Printing & Photocopies",
            "type":"Services"
        }
    ],
    "sg:phone":"+44 20 8808 1677",
    "sg:postcode":"N17 6QD",
    "sg:province":"Greater London",
    "sg:tags":[
        "printer"
    ],
    "wof:name":"Wernham Printers Ltd.",
    "wof:placetype":"venue"
},
  "geometry": {"coordinates":[-0.070523,51.591667],"type":"Point"}
}