{
  "type": "Feature",
  "properties": {
    "iso:country":"GB",
    "sg:address":"Selside",
    "sg:city":"Kendal",
    "sg:classifiers":[
        {
            "category":"Travel",
            "subcategory":"Hotels & Motels",
            "type":"Entertainment"
        }
    ],
    "sg:phone":"+44 1539 823259",
    "sg:postcode":"LA8 9LE",
    "sg:province":"Cumbria",
    "sg:tags":[
        "house",
        "guest"
    ],
    "wof:name":"Low Jock Scar Guest House",
    "wof:placetype":"venue"
},
  "geometry": {"coordinates":[-2.7167870998,54.3852310181],"type":"Point"}
}