{
  "type": "Feature",
  "properties": {
    "addr:full":"Tree Tops, Linden Chase Uckfield East Sussex TN22 1EE",
    "addr:postcode":"tn22 1ee",
    "addr:street":"Linden Chase",
    "iso:country":"GB",
    "sg:address":"Tree Tops, Linden Chase",
    "sg:city":"Uckfield",
    "sg:classifiers":[
        {
            "category":"Wholesale",
            "subcategory":"Toys & Hobbies",
            "type":"Manufacturing & Wholesale Goods"
        }
    ],
    "sg:phone":"+44 1825 767381",
    "sg:postcode":"TN22 1EE",
    "sg:province":"East Sussex",
    "sg:tags":[
        "balloon",
        "novelty"
    ],
    "wof:name":"Balloon Bazaar",
    "wof:placetype":"venue"
},
  "geometry": {"coordinates":[0.09665,50.971813],"type":"Point"}
}