{
  "type": "Feature",
  "properties": {
    "iso:country":"GB",
    "sg:address":"14 The Green",
    "sg:city":"Broadway",
    "sg:classifiers":[
        {
            "category":"Shopping",
            "subcategory":"Clothing, Apparel, & Fashions",
            "type":"Retail Goods"
        }
    ],
    "sg:phone":"+44 1386 852751",
    "sg:postcode":"WR12 7AA",
    "sg:province":"Gloucestershire",
    "sg:tags":[
        "shop"
    ],
    "wof:name":"Elizabeth",
    "wof:placetype":"venue"
},
  "geometry": {"coordinates":[-1.855794,52.040409],"type":"Point"}
}