{
  "type": "Feature",
  "properties": {
    "iso:country":"GB",
    "sg:address":"21 Vine St",
    "sg:city":"Evesham",
    "sg:classifiers":[
        {
            "category":"Real Estate",
            "subcategory":"Real Estate Operator",
            "type":"Services"
        }
    ],
    "sg:phone":"+44 1386 442139",
    "sg:postcode":"WR11 4RL",
    "sg:province":"Gloucestershire",
    "sg:tags":[
        "letting",
        "agent"
    ],
    "wof:name":"Countrywide Residential Lettings",
    "wof:placetype":"venue"
},
  "geometry": {"coordinates":[-1.948856,52.09156],"type":"Point"}
}