{
  "type": "Feature",
  "properties": {
    "addr:full":"37 Fretherne Road Welwyn Garden City Hertfordshire AL8 6NS",
    "addr:housenumber":"37",
    "addr:postcode":"al8 6ns",
    "addr:street":"Fretherne Road",
    "iso:country":"GB",
    "sg:address":"37 Fretherne Road",
    "sg:city":"Welwyn Garden City",
    "sg:classifiers":[
        {
            "category":"Shopping",
            "subcategory":"Thrift Store",
            "type":"Retail Goods"
        }
    ],
    "sg:phone":"+44 1707 335271",
    "sg:postcode":"AL8 6NS",
    "sg:province":"Hertfordshire",
    "sg:tags":[
        "shop",
        "charity"
    ],
    "sg:website":"http://www.oxfam.org.uk",
    "wof:name":"Oxfam",
    "wof:placetype":"venue"
},
  "geometry": {"coordinates":[-0.2057549953,51.8009338379],"type":"Point"}
}