{
  "type": "Feature",
  "properties": {
    "iso:country":"GB",
    "sg:address":"179 High Street, Rainham",
    "sg:city":"Gillingham",
    "sg:classifiers":[
        {
            "category":"Shopping",
            "subcategory":"News",
            "type":"Retail Goods"
        }
    ],
    "sg:phone":"+44 1634 233488",
    "sg:postcode":"ME8 8AY",
    "sg:province":"Kent",
    "sg:tags":[
        "newsagent"
    ],
    "wof:name":"The Chocolate Box",
    "wof:placetype":"venue"
},
  "geometry": {"coordinates":[0.614856,51.362045],"type":"Point"}
}