{
  "type": "Feature",
  "properties": {
    "addr:full":"Care Of Cathedral Clergy Ho, Westminster Bridge Rd Southwark Greater London SE1 7JE",
    "addr:postcode":"se1 7je",
    "addr:street":"Westminster Bridge Rd",
    "iso:country":"GB",
    "sg:address":"Care Of Cathedral Clergy Ho, Westminster Bridge Rd",
    "sg:city":"Southwark",
    "sg:classifiers":[
        {
            "category":"Organizations",
            "subcategory":"Religious Organization",
            "type":"Services"
        }
    ],
    "sg:phone":"+44 20 7928 9742",
    "sg:postcode":"SE1 7JE",
    "sg:province":"Greater London",
    "sg:tags":[
        "organisation"
    ],
    "wof:name":"Southwark Justice & Peace Office",
    "wof:placetype":"venue"
},
  "geometry": {"coordinates":[-0.109,51.498341],"type":"Point"}
}