{
  "type": "Feature",
  "properties": {
    "iso:country":"GB",
    "sg:address":"Number Two",
    "sg:city":"Lutterworth",
    "sg:classifiers":[
        {
            "category":"Professional",
            "subcategory":"Business Services",
            "type":"Services"
        }
    ],
    "sg:phone":"+44 1455 558720",
    "sg:postcode":"LE17 4BW",
    "sg:province":"Leicestershire",
    "sg:tags":[
        "import",
        "export",
        "agent"
    ],
    "wof:name":"T A P S International Ltd.",
    "wof:placetype":"venue"
},
  "geometry": {"coordinates":[-1.1996239424,52.4562988281],"type":"Point"}
}