{
  "type": "Feature",
  "properties": {
    "addr:full":"Knockdown Tetbury Gloucestershire GL8 8QY",
    "addr:postcode":"gl8 8qy",
    "iso:country":"GB",
    "sg:address":"Knockdown",
    "sg:city":"Tetbury",
    "sg:classifiers":[
        {
            "category":"Mining & Drilling",
            "type":"Manufacturing & Wholesale Goods"
        },
        {
            "category":"Manufacturing",
            "subcategory":"Glass & Minerals",
            "type":"Manufacturing & Wholesale Goods"
        }
    ],
    "sg:phone":"+44 1666 840443",
    "sg:postcode":"GL8 8QY",
    "sg:province":"Gloucestershire",
    "sg:tags":[
        "chalk",
        "stone",
        "slate",
        "quarry"
    ],
    "wof:name":"Knockdown Quarry",
    "wof:placetype":"venue"
},
  "geometry": {"coordinates":[-2.1609759331,51.6378593445],"type":"Point"}
}