{
  "type": "Feature",
  "properties": {
    "addr:full":"43 West St Reading Berkshire RG1 1TZ",
    "addr:housenumber":"43",
    "addr:postcode":"rg1 1tz",
    "addr:street":"West St",
    "iso:country":"GB",
    "sg:address":"43 West St",
    "sg:city":"Reading",
    "sg:classifiers":[
        {
            "category":"Education",
            "subcategory":"Special Training",
            "type":"Public Place"
        }
    ],
    "sg:phone":"+44 118 939 1833",
    "sg:postcode":"RG1 1TZ",
    "sg:province":"Berkshire",
    "sg:tags":[
        "school",
        "language"
    ],
    "wof:name":"Specialist Language Centre",
    "wof:placetype":"venue"
},
  "geometry": {"coordinates":[-0.9761499763,51.4561576843],"type":"Point"}
}