{
  "type": "Feature",
  "properties": {
    "addr:full":"212 Burgess Road Southampton Hampshire SO16 3AY",
    "addr:housenumber":"212",
    "addr:postcode":"so16 3ay",
    "addr:street":"Burgess Road",
    "iso:country":"GB",
    "sg:address":"212 Burgess Road",
    "sg:city":"Southampton",
    "sg:classifiers":[
        {
            "category":"Retail",
            "subcategory":"Repair Shop",
            "type":"Services"
        }
    ],
    "sg:phone":"+44 23 8067 8323",
    "sg:postcode":"SO16 3AY",
    "sg:province":"Hampshire",
    "sg:tags":[
        "radio",
        "television",
        "video"
    ],
    "wof:name":"Sure View Television",
    "wof:placetype":"venue"
},
  "geometry": {"coordinates":[-1.391142,50.938335],"type":"Point"}
}