{
  "type": "Feature",
  "properties": {
    "addr:full":"32 Wellesley Road Croydon Surrey CR9 1PR",
    "addr:housenumber":"32",
    "addr:postcode":"cr9 1pr",
    "addr:street":"Wellesley Road",
    "iso:country":"GB",
    "sg:address":"32 Wellesley Road",
    "sg:city":"Croydon",
    "sg:classifiers":[
        {
            "category":"Insurance",
            "subcategory":"Insurance Agent",
            "type":"Services"
        }
    ],
    "sg:phone":"+44 20 8686 5544",
    "sg:postcode":"CR9 1PR",
    "sg:province":"Surrey",
    "wof:name":"Guardian Royal Exchange",
    "wof:placetype":"venue"
},
  "geometry": {"coordinates":[-0.0981810018,51.3763618469],"type":"Point"}
}