{
  "type": "Feature",
  "properties": {
    "iso:country":"GB",
    "sg:address":"I C G House, Station Approach",
    "sg:city":"Greenford",
    "sg:classifiers":[
        {
            "category":"Building & Trades",
            "subcategory":"Landscaping Services",
            "type":"Services"
        },
        {
            "category":"Building & Trades",
            "subcategory":"Construction",
            "type":"Services"
        }
    ],
    "sg:phone":"+44 20 8575 7788",
    "sg:postcode":"UB6 0AL",
    "sg:province":"Greater London",
    "sg:tags":[
        "flooring",
        "landscape",
        "contractor"
    ],
    "wof:name":"Turfcare",
    "wof:placetype":"venue"
},
  "geometry": {"coordinates":[-0.349049,51.543697],"type":"Point"}
}