{
  "type": "Feature",
  "properties": {
    "addr:full":"301-303 Railton Road, Herne Hill London Greater London SE24 0JN",
    "addr:housenumber":"301-303",
    "addr:postcode":"se24 0jn",
    "addr:street":"Railton Road",
    "iso:country":"GB",
    "sg:address":"301-303 Railton Road, Herne Hill",
    "sg:city":"London",
    "sg:classifiers":[
        {
            "category":"Manufacturing",
            "subcategory":"Lumber",
            "type":"Manufacturing & Wholesale Goods"
        }
    ],
    "sg:postcode":"SE24 0JN",
    "sg:province":"Greater London",
    "sg:tags":[
        "importer",
        "merchants",
        "agent",
        "timber"
    ],
    "wof:name":"Herne Hill Timber Co. Ltd.",
    "wof:placetype":"venue"
},
  "geometry": {"coordinates":[-0.1032020003,51.4534912109],"type":"Point"}
}