{
  "type": "Feature",
  "properties": {
    "addr:full":"4 Wellgarth Road London Greater London NW11 7HR",
    "addr:housenumber":"4",
    "addr:postcode":"nw11 7hr",
    "addr:street":"Wellgarth Road",
    "iso:country":"GB",
    "sg:address":"4 Wellgarth Road",
    "sg:city":"London",
    "sg:classifiers":[
        {
            "category":"Education",
            "subcategory":"Special Training",
            "type":"Public Place"
        }
    ],
    "sg:postcode":"NW11 7HR",
    "sg:province":"Greater London",
    "sg:tags":[
        "school",
        "language"
    ],
    "wof:name":"Kingsley School of English",
    "wof:placetype":"venue"
},
  "geometry": {"coordinates":[-0.1861370057,51.5707206726],"type":"Point"}
}