{
  "type": "Feature",
  "properties": {
    "addr:full":"Rookery Hill, Corringham Stanford-le-hope Essex SS17 9LB",
    "addr:postcode":"ss17 9lb",
    "addr:street":"Rookery Hill",
    "iso:country":"GB",
    "sg:address":"Rookery Hill, Corringham",
    "sg:city":"Stanford-le-hope",
    "sg:classifiers":[
        {
            "category":"Arena",
            "subcategory":"Sports Club",
            "type":"Entertainment"
        }
    ],
    "sg:phone":"+44 1375 644166",
    "sg:postcode":"SS17 9LB",
    "sg:province":"Essex",
    "wof:name":"East Thurrock United Football Club",
    "wof:placetype":"venue"
},
  "geometry": {"coordinates":[0.462855,51.522713],"type":"Point"}
}