{
  "type": "Feature",
  "properties": {
    "addr:full":"65-67 Hyndland Street Glasgow Glasgow City G11 5PS",
    "addr:housenumber":"65-67",
    "addr:postcode":"g11 5ps",
    "addr:street":"Hyndland Street",
    "iso:country":"GB",
    "sg:address":"65-67 Hyndland Street",
    "sg:city":"Glasgow",
    "sg:classifiers":[
        {
            "category":"Education",
            "subcategory":"Library",
            "type":"Public Place"
        }
    ],
    "sg:postcode":"G11 5PS",
    "sg:province":"Glasgow City",
    "sg:tags":[
        "reproduction",
        "furniture"
    ],
    "wof:name":"Maxwell C James",
    "wof:placetype":"venue"
},
  "geometry": {"coordinates":[-4.3024778366,55.8725166321],"type":"Point"}
}