{
  "type": "Feature",
  "properties": {
    "iso:country":"GB",
    "sg:address":"3 Bright Street",
    "sg:city":"Sunderland",
    "sg:classifiers":[
        {
            "category":"Food & Beverages",
            "subcategory":"Liquor & Beverages",
            "type":"Retail Goods"
        }
    ],
    "sg:phone":"+44 191 567 2328",
    "sg:postcode":"SR6 0JQ",
    "sg:province":"Tyne and Wear",
    "sg:tags":[
        "beer",
        "spirit",
        "wines"
    ],
    "wof:name":"Lika & Flix",
    "wof:placetype":"venue"
},
  "geometry": {"coordinates":[-1.376568,54.916435],"type":"Point"}
}