{
  "type": "Feature",
  "properties": {
    "addr:full":"Stavordale Road, Moreton Wirral Merseyside CH46 9PS",
    "addr:postcode":"ch46 9ps",
    "addr:street":"Stavordale Road",
    "iso:country":"GB",
    "sg:address":"Stavordale Road, Moreton",
    "sg:city":"Wirral",
    "sg:classifiers":[
        {
            "category":"Education",
            "subcategory":"School",
            "type":"Public Place"
        },
        {
            "category":"Government",
            "subcategory":"Office",
            "type":"Public Place"
        }
    ],
    "sg:phone":"+44 151 677 3231",
    "sg:postcode":"CH46 9PS",
    "sg:province":"Merseyside",
    "sg:tags":[
        "local",
        "authority"
    ],
    "wof:name":"Sandbrook Primary School",
    "wof:placetype":"venue"
},
  "geometry": {"coordinates":[-3.0992701054,53.4031181335],"type":"Point"}
}