{
  "type": "Feature",
  "properties": {
    "addr:full":"101 Bayham St Camden Greater London NW1 0AG",
    "addr:housenumber":"101",
    "addr:postcode":"nw1 0ag",
    "addr:street":"Bayham St",
    "iso:country":"GB",
    "sg:address":"101 Bayham St",
    "sg:city":"Camden",
    "sg:classifiers":[
        {
            "category":"Communications",
            "subcategory":"Newspaper",
            "type":"Services"
        }
    ],
    "sg:phone":"+44 20 7428 3000",
    "sg:postcode":"NW1 0AG",
    "sg:province":"Greater London",
    "sg:tags":[
        "magazine"
    ],
    "wof:name":"Best Buys For Leisure & Home",
    "wof:placetype":"venue"
},
  "geometry": {"coordinates":[-0.1405120045,51.5379142761],"type":"Point"}
}