{
  "type": "Feature",
  "properties": {
    "addr:full":"1 Ashdown Court, Lewes Road Forest Row East Sussex RH18 5EZ",
    "addr:housenumber":"1",
    "addr:postcode":"rh18 5ez",
    "addr:street":"Ashdown Court Lewes Road",
    "iso:country":"GB",
    "sg:address":"1 Ashdown Court, Lewes Road",
    "sg:city":"Forest Row",
    "sg:classifiers":[
        {
            "category":"Travel",
            "subcategory":"Travel Agent",
            "type":"Entertainment"
        }
    ],
    "sg:postcode":"RH18 5EZ",
    "sg:province":"East Sussex",
    "wof:name":"Suntext Ltd.",
    "wof:placetype":"venue"
},
  "geometry": {"coordinates":[0.033261,51.098259],"type":"Point"}
}