{
  "type": "Feature",
  "properties": {
    "addr:full":"64 Main Street, Dailly Girvan South Ayrshire KA26 9SD",
    "addr:housenumber":"64",
    "addr:postcode":"ka26 9sd",
    "addr:street":"Main Street Dailly",
    "iso:country":"GB",
    "sg:address":"64 Main Street, Dailly",
    "sg:city":"Girvan",
    "sg:classifiers":[
        {
            "category":"Government",
            "subcategory":"Post Office",
            "type":"Public Place"
        }
    ],
    "sg:phone":"+44 1465 811201",
    "sg:postcode":"KA26 9SD",
    "sg:province":"South Ayrshire",
    "wof:name":"Dailly Post Office",
    "wof:placetype":"venue"
},
  "geometry": {"coordinates":[-4.7259788513,55.2780342102],"type":"Point"}
}