{
  "type": "Feature",
  "properties": {
    "addr:full":"365 Clapham Road London Greater London SW9 9BT",
    "addr:housenumber":"365",
    "addr:postcode":"sw9 9bt",
    "addr:street":"Clapham Road",
    "iso:country":"GB",
    "sg:address":"365 Clapham Road",
    "sg:city":"London",
    "sg:classifiers":[
        {
            "category":"Wholesale",
            "subcategory":"Construction Materials",
            "type":"Manufacturing & Wholesale Goods"
        },
        {
            "category":"Manufacturing",
            "subcategory":"Glass & Minerals",
            "type":"Manufacturing & Wholesale Goods"
        }
    ],
    "sg:phone":"+44 20 7738 5888",
    "sg:postcode":"SW9 9BT",
    "sg:province":"Greater London",
    "sg:tags":[
        "merchant",
        "product"
    ],
    "wof:name":"Fusion Glass Designs Ltd.",
    "wof:placetype":"venue"
},
  "geometry": {"coordinates":[-0.1281999946,51.4671592712],"type":"Point"}
}