{
  "type": "Feature",
  "properties": {
    "addr:full":"Richmond Court, 309 Fleet Rd Fleet Dorset GU13 8BU",
    "addr:housenumber":"309",
    "addr:postcode":"gu13 8bu",
    "addr:street":"Richmond;Fleet Rd",
    "iso:country":"GB",
    "sg:address":"Richmond Court, 309 Fleet Rd",
    "sg:city":"Fleet",
    "sg:classifiers":[
        {
            "category":"Real Estate",
            "subcategory":"Real Estate Agent",
            "type":"Services"
        }
    ],
    "sg:phone":"+44 1252 622144",
    "sg:postcode":"GU13 8BU",
    "sg:province":"Dorset",
    "wof:name":"Racal Properties Ltd",
    "wof:placetype":"venue"
},
  "geometry": {"coordinates":[-0.8441410065,51.2792778015],"type":"Point"}
}