{
  "type": "Feature",
  "properties": {
    "addr:full":"Beacontree Plaza Gillette Way Reading Berkshire RG2 0BS",
    "addr:postcode":"rg2 0bs",
    "addr:street":"Gillette Way",
    "iso:country":"GB",
    "sg:address":"Beacontree Plaza Gillette Way",
    "sg:city":"Reading",
    "sg:classifiers":[
        {
            "category":"Professional",
            "subcategory":"Management & Consulting",
            "type":"Services"
        }
    ],
    "sg:phone":"+44 118 921 2877",
    "sg:postcode":"RG2 0BS",
    "sg:province":"Berkshire",
    "sg:tags":[
        "consultant",
        "business"
    ],
    "wof:name":"A D International",
    "wof:placetype":"venue"
},
  "geometry": {"coordinates":[-0.9725400209,51.4324302673],"type":"Point"}
}