{
  "type": "Feature",
  "properties": {
    "addr:full":"69 Ringwood Road Ferndown Dorset BH22 9AA",
    "addr:housenumber":"69",
    "addr:postcode":"bh22 9aa",
    "addr:street":"Ringwood Road",
    "iso:country":"GB",
    "sg:address":"69 Ringwood Road",
    "sg:city":"Ferndown",
    "sg:classifiers":[
        {
            "category":"Communications",
            "subcategory":"Film & Video Production",
            "type":"Services"
        },
        {
            "category":"Communications",
            "subcategory":"Newspaper",
            "type":"Services"
        },
        {
            "category":"Communications",
            "type":"Services"
        },
        {
            "category":"Arts & Performance",
            "subcategory":"Theater",
            "type":"Entertainment"
        }
    ],
    "sg:phone":"+44 1202 576438",
    "sg:postcode":"BH22 9AA",
    "sg:province":"Dorset",
    "sg:tags":[
        "theatrical",
        "tv",
        "magazine",
        "studio",
        "presentation",
        "audio-visual"
    ],
    "wof:name":"Pictures & Words Ltd.",
    "wof:placetype":"venue"
},
  "geometry": {"coordinates":[-1.9087929726,50.7780952454],"type":"Point"}
}