{
  "type": "Feature",
  "properties": {
    "iso:country":"GB",
    "sg:address":"402 Wells Road",
    "sg:city":"Bristol",
    "sg:classifiers":[
        {
            "category":"Travel",
            "subcategory":"Hotels & Motels",
            "type":"Entertainment"
        }
    ],
    "sg:phone":"+44 117 977 9186",
    "sg:postcode":"BS14 9AA",
    "sg:province":"City of Bristol",
    "sg:tags":[
        "house",
        "guest"
    ],
    "wof:name":"Imperial Guest House",
    "wof:placetype":"venue"
},
  "geometry": {"coordinates":[-2.5639150143,51.4299545288],"type":"Point"}
}