{
  "type": "Feature",
  "properties": {
    "iso:country":"GB",
    "sg:address":"Limerick House, Heathside Park Road",
    "sg:city":"Woking",
    "sg:classifiers":[
        {
            "category":"Health Services",
            "subcategory":"Nursing And Care Facility",
            "type":"Services"
        }
    ],
    "sg:phone":"+44 1483 763977",
    "sg:postcode":"GU22 7JF",
    "sg:province":"Surrey",
    "sg:tags":[
        "home"
    ],
    "wof:name":"Rosetower Ltd.",
    "wof:placetype":"venue"
},
  "geometry": {"coordinates":[-0.5516,51.314575],"type":"Point"}
}