{
  "type": "Feature",
  "properties": {
    "addr:full":"159 Farringdon Rd Clerkenwell Greater London EC1R 3AL",
    "addr:housenumber":"159",
    "addr:postcode":"ec1r 3al",
    "addr:street":"Farringdon Rd",
    "iso:country":"GB",
    "sg:address":"159 Farringdon Rd",
    "sg:city":"Clerkenwell",
    "sg:classifiers":[
        {
            "category":"Bars & Pubs",
            "type":"Food & Drink"
        }
    ],
    "sg:phone":"+44 20 7833 2674",
    "sg:postcode":"EC1R 3AL",
    "sg:province":"Greater London",
    "sg:tags":[
        "pubs",
        "inn"
    ],
    "wof:name":"Eagle Gallery",
    "wof:placetype":"venue"
},
  "geometry": {"coordinates":[-0.1098200008,51.5242385864],"type":"Point"}
}