{
  "type": "Feature",
  "properties": {
    "addr:full":"Unit 35 Romsey Industrial Estate, Greatbridge Road Romsey Hampshire SO51 0HR",
    "addr:housenumber":"unit 35",
    "addr:postcode":"so51 0hr",
    "addr:street":"Industrial;Greatbridge Road",
    "iso:country":"GB",
    "sg:address":"Unit 35 Romsey Industrial Estate, Greatbridge Road",
    "sg:city":"Romsey",
    "sg:classifiers":[
        {
            "category":"Shopping",
            "subcategory":"Florist",
            "type":"Retail Goods"
        }
    ],
    "sg:phone":"+44 1794 526460",
    "sg:postcode":"SO51 0HR",
    "sg:province":"Hampshire",
    "wof:name":"British Teleflower Service Ltd.",
    "wof:placetype":"venue"
},
  "geometry": {"coordinates":[-1.4953910112,50.9885826111],"type":"Point"}
}