{
  "type": "Feature",
  "properties": {
    "iso:country":"GB",
    "sg:address":"48 Rufford Ave, Beeston",
    "sg:city":"Nottingham",
    "sg:classifiers":[
        {
            "category":"Building & Trades",
            "subcategory":"Landscaping Services",
            "type":"Services"
        }
    ],
    "sg:postcode":"NG9 3JH",
    "sg:province":"Nottinghamshire",
    "sg:tags":[
        "landscape",
        "contractor"
    ],
    "wof:name":"Montgomery-Scott Landscapes Ltd",
    "wof:placetype":"venue"
},
  "geometry": {"coordinates":[-1.253601,52.934135],"type":"Point"}
}