{
  "type": "Feature",
  "properties": {
    "addr:full":"2 Larch Drive, Gunnersbury Avenue, Chiswick Roundabout London Greater London W4 5QL",
    "addr:housenumber":"2",
    "addr:postcode":"w4 5ql",
    "addr:street":"Larch Drive Gunnersbury Avenue Chiswick Roundabout",
    "iso:country":"GB",
    "sg:address":"2 Larch Drive, Gunnersbury Avenue, Chiswick Roundabout",
    "sg:city":"London",
    "sg:classifiers":[
        {
            "category":"Home & Garden",
            "subcategory":"Hardware",
            "type":"Retail Goods"
        }
    ],
    "sg:phone":"+44 20 8995 8028",
    "sg:postcode":"W4 5QL",
    "sg:province":"Greater London",
    "sg:tags":[
        "retailer",
        "diy"
    ],
    "wof:name":"B & Q Supercentre",
    "wof:placetype":"venue"
},
  "geometry": {"coordinates":[-0.282488,51.492519],"type":"Point"}
}