{
  "type": "Feature",
  "properties": {
    "addr:full":"Jacaleen, Rock Lane Ludlow Herefordshire SY8 1SF",
    "addr:postcode":"sy8 1sf",
    "addr:street":"Rock Lane",
    "iso:country":"GB",
    "sg:address":"Jacaleen, Rock Lane",
    "sg:city":"Ludlow",
    "sg:classifiers":[
        {
            "category":"Building & Trades",
            "subcategory":"Construction",
            "type":"Services"
        }
    ],
    "sg:phone":"+44 1584 878341",
    "sg:postcode":"SY8 1SF",
    "sg:province":"Herefordshire",
    "sg:tags":[
        "dry",
        "lining",
        "plasterers",
        "screeders"
    ],
    "wof:name":"Stuart Preece",
    "wof:placetype":"venue"
},
  "geometry": {"coordinates":[-2.719014,52.370594],"type":"Point"}
}