{
  "type": "Feature",
  "properties": {
    "iso:country":"GB",
    "sg:address":"27 Unitas Road, Mossend",
    "sg:city":"Bellshill",
    "sg:classifiers":[
        {
            "category":"Shopping",
            "subcategory":"Pharmacy",
            "type":"Retail Goods"
        }
    ],
    "sg:postcode":"ML4 1QF",
    "sg:province":"North Lanarkshire",
    "sg:tags":[
        "pharmacist",
        "chemist"
    ],
    "wof:name":"Lloyds Chemist",
    "wof:placetype":"venue"
},
  "geometry": {"coordinates":[-4.010023,55.819077],"type":"Point"}
}