{
  "type": "Feature",
  "properties": {
    "addr:full":"Fore Street, Grampound Truro Cornwall TR2 4DS",
    "addr:postcode":"tr2 4ds",
    "addr:street":"Fore Street",
    "iso:country":"GB",
    "sg:address":"Fore Street, Grampound",
    "sg:city":"Truro",
    "sg:classifiers":[
        {
            "category":"Shopping",
            "subcategory":"Department Store",
            "type":"Retail Goods"
        }
    ],
    "sg:phone":"+44 1726 882463",
    "sg:postcode":"TR2 4DS",
    "sg:province":"Cornwall",
    "wof:name":"Grampound Post Office",
    "wof:placetype":"venue"
},
  "geometry": {"coordinates":[-4.899034,50.298214],"type":"Point"}
}