{
  "type": "Feature",
  "properties": {
    "addr:full":"Mcintosh House, Foxbridge Way, Normanton Industrial Estate Normanton West Yorkshire WF6 1TN",
    "addr:housenumber":"estate",
    "addr:postcode":"wf6 1tn",
    "addr:street":"Foxbridge Way;Industrial;West",
    "iso:country":"GB",
    "sg:address":"Mcintosh House, Foxbridge Way, Normanton Industrial Estate",
    "sg:city":"Normanton",
    "sg:classifiers":[
        {
            "category":"Professional",
            "subcategory":"Printing & Photocopies",
            "type":"Services"
        }
    ],
    "sg:phone":"+44 1924 890000",
    "sg:postcode":"WF6 1TN",
    "sg:province":"West Yorkshire",
    "sg:tags":[
        "printer"
    ],
    "wof:name":"Williams Lea U K Ltd.",
    "wof:placetype":"venue"
},
  "geometry": {"coordinates":[-1.395942,53.704689],"type":"Point"}
}