{
  "type": "Feature",
  "properties": {
    "addr:full":"Ivesley, Waterhouses Durham Durham DH7 9HB",
    "addr:postcode":"dh7 9hb",
    "iso:country":"GB",
    "sg:address":"Ivesley, Waterhouses",
    "sg:city":"Durham",
    "sg:classifiers":[
        {
            "category":"Sports & Exercise",
            "subcategory":"Stables",
            "type":"Entertainment"
        }
    ],
    "sg:phone":"+44 191 373 4324",
    "sg:postcode":"DH7 9HB",
    "sg:province":"Durham",
    "sg:tags":[
        "equestrian",
        "centre",
        "livery",
        "schools",
        "riding",
        "education"
    ],
    "wof:name":"Ivesley Equestrian Centre",
    "wof:placetype":"venue"
},
  "geometry": {"coordinates":[-1.7308,54.764618],"type":"Point"}
}