{
  "type": "Feature",
  "properties": {
    "addr:full":"72 Buckingham Avenue, Slough Trading Estate Slough Berkshire SL1 4PN",
    "addr:housenumber":"72",
    "addr:postcode":"sl1 4pn",
    "addr:street":"Buckingham Avenue;Trading Estate",
    "iso:country":"GB",
    "sg:address":"72 Buckingham Avenue, Slough Trading Estate",
    "sg:city":"Slough",
    "sg:classifiers":[
        {
            "category":"Manufacturing",
            "subcategory":"Buildings",
            "type":"Manufacturing & Wholesale Goods"
        },
        {
            "category":"Building & Trades",
            "subcategory":"Electrical",
            "type":"Services"
        }
    ],
    "sg:phone":"+44 1753 693919",
    "sg:postcode":"SL1 4PN",
    "sg:province":"Berkshire",
    "sg:tags":[
        "system",
        "contractor",
        "air conditioning"
    ],
    "wof:name":"York International Ltd",
    "wof:placetype":"venue"
},
  "geometry": {"coordinates":[-0.621115,51.521164],"type":"Point"}
}