{
  "type": "Feature",
  "properties": {
    "addr:full":"38 Preston Parade Whitstable Kent CT5 4AJ",
    "addr:housenumber":"38",
    "addr:postcode":"ct5 4aj",
    "addr:street":"Preston Parade Whitstable",
    "iso:country":"GB",
    "sg:address":"38 Preston Parade",
    "sg:city":"Whitstable",
    "sg:classifiers":[
        {
            "category":"Building & Trades",
            "subcategory":"Construction",
            "type":"Services"
        }
    ],
    "sg:phone":"+44 1227 272845",
    "sg:postcode":"CT5 4AJ",
    "sg:province":"Kent",
    "sg:tags":[
        "builder"
    ],
    "wof:name":"K C West Construction",
    "wof:placetype":"venue"
},
  "geometry": {"coordinates":[0.9933729768,51.3467102051],"type":"Point"}
}