{
  "type": "Feature",
  "properties": {
    "iso:country":"GB",
    "sg:address":"Eastside, Jackson Street",
    "sg:city":"St Helens",
    "sg:classifiers":[
        {
            "category":"Building & Trades",
            "subcategory":"Construction",
            "type":"Services"
        }
    ],
    "sg:phone":"+44 1744 739225",
    "sg:postcode":"WA9 3AS",
    "sg:province":"Cheshire",
    "sg:tags":[
        "door",
        "patio"
    ],
    "wof:name":"Dual Thermal Products Ltd.",
    "wof:placetype":"venue"
},
  "geometry": {"coordinates":[-2.719719,53.448383],"type":"Point"}
}