{
  "type": "Feature",
  "properties": {
    "iso:country":"GB",
    "sg:address":"Cley View, Clink",
    "sg:city":"Frome",
    "sg:classifiers":[
        {
            "category":"Building & Trades",
            "subcategory":"Construction",
            "type":"Services"
        }
    ],
    "sg:phone":"+44 1373 453855",
    "sg:postcode":"BA11 2EQ",
    "sg:province":"Somerset",
    "sg:tags":[
        "builder"
    ],
    "wof:name":"Western Property Management",
    "wof:placetype":"venue"
},
  "geometry": {"coordinates":[-2.318807,51.228558],"type":"Point"}
}