{
  "type": "Feature",
  "properties": {
    "iso:country":"GB",
    "sg:address":"The Boulevard, Orbital Park",
    "sg:city":"Ashford",
    "sg:classifiers":[
        {
            "category":"Manufacturing",
            "subcategory":"Electronics",
            "type":"Manufacturing & Wholesale Goods"
        }
    ],
    "sg:phone":"+44 1233 501555",
    "sg:postcode":"TN24 0GA",
    "sg:province":"Kent",
    "sg:tags":[
        "mnfr",
        "component",
        "electronic"
    ],
    "wof:name":"Maruwa Europe Ltd.",
    "wof:placetype":"venue"
},
  "geometry": {"coordinates":[0.89725,51.128342],"type":"Point"}
}