{
  "type": "Feature",
  "properties": {
    "iso:country":"GB",
    "sg:address":"20 Masefield Close",
    "sg:city":"Stanley",
    "sg:classifiers":[
        {
            "category":"Shopping",
            "subcategory":"Gifts & Souvenirs",
            "type":"Retail Goods"
        }
    ],
    "sg:phone":"+44 1207 232693",
    "sg:postcode":"DH9 6UQ",
    "sg:province":"Durham",
    "sg:tags":[
        "poster",
        "card"
    ],
    "wof:name":"East Stanley Post Office",
    "wof:placetype":"venue"
},
  "geometry": {"coordinates":[-1.677705,54.871731],"type":"Point"}
}