{
  "type": "Feature",
  "properties": {
    "addr:full":"40 Bellevue Street Filey North Yorkshire YO14 9HY",
    "addr:housenumber":"40",
    "addr:postcode":"yo14 9hy",
    "addr:street":"Bellevue Street",
    "iso:country":"GB",
    "sg:address":"40 Bellevue Street",
    "sg:city":"Filey",
    "sg:classifiers":[
        {
            "category":"Shopping",
            "subcategory":"Gifts & Souvenirs",
            "type":"Retail Goods"
        },
        {
            "category":"Cafe",
            "type":"Food & Drink"
        }
    ],
    "sg:phone":"+44 1723 514805",
    "sg:postcode":"YO14 9HY",
    "sg:province":"North Yorkshire",
    "sg:tags":[
        "shop",
        "tea",
        "room"
    ],
    "wof:name":"BRONTE VINERY",
    "wof:placetype":"venue"
},
  "geometry": {"coordinates":[-0.2882690132,54.2085838318],"type":"Point"}
}