{
  "type": "Feature",
  "properties": {
    "addr:full":"Redburn Industrial Estate, Kilwinning Road Irvine North Ayrshire KA12 8TG",
    "addr:postcode":"ka12 8tg",
    "addr:street":"Estate Kilwinning Road",
    "iso:country":"GB",
    "sg:address":"Redburn Industrial Estate, Kilwinning Road",
    "sg:city":"Irvine",
    "sg:classifiers":[
        {
            "category":"Freight",
            "type":"Transportation"
        }
    ],
    "sg:phone":"+44 1294 272531",
    "sg:postcode":"KA12 8TG",
    "sg:province":"North Ayrshire",
    "sg:tags":[
        "haulage",
        "transport",
        "road"
    ],
    "wof:name":"Maxi Haulage Ltd",
    "wof:placetype":"venue"
},
  "geometry": {"coordinates":[-4.673259,55.601974],"type":"Point"}
}