{
  "type": "Feature",
  "properties": {
    "addr:full":"Back Quay Truro Cornwall TR1 2LL",
    "addr:postcode":"tr1 2ll",
    "addr:street":"Back Quay",
    "iso:country":"GB",
    "sg:address":"Back Quay",
    "sg:city":"Truro",
    "sg:classifiers":[
        {
            "category":"Shopping",
            "subcategory":"Used Merchandise",
            "type":"Retail Goods"
        }
    ],
    "sg:phone":"+44 1872 262505",
    "sg:postcode":"TR1 2LL",
    "sg:province":"Cornwall",
    "sg:tags":[
        "shop",
        "second-hand"
    ],
    "wof:name":"Luke's Kitchenware Stationery & Miscellaneous",
    "wof:placetype":"venue"
},
  "geometry": {"coordinates":[-5.050269,50.262402],"type":"Point"}
}