{
  "type": "Feature",
  "properties": {
    "addr:full":"198 Church Road, St George Bristol City of Bristol BS5 8AD",
    "addr:housenumber":"198",
    "addr:postcode":"bs5 8ad",
    "addr:street":"Church Road",
    "iso:country":"GB",
    "sg:address":"198 Church Road, St George",
    "sg:city":"Bristol",
    "sg:classifiers":[
        {
            "category":"Banks & Credit Unions",
            "subcategory":"Financial Services",
            "type":"Services"
        }
    ],
    "sg:phone":"+44 117 935 1065",
    "sg:postcode":"BS5 8AD",
    "sg:province":"City of Bristol",
    "sg:tags":[
        "claim",
        "assessor"
    ],
    "wof:name":"W D Davis & Son",
    "wof:placetype":"venue"
},
  "geometry": {"coordinates":[-2.550494,51.459534],"type":"Point"}
}