{
  "type": "Feature",
  "properties": {
    "addr:full":"May Terrace, Giffnock Glasgow East Renfrewshire G46 6LD",
    "addr:postcode":"g46 6ld",
    "addr:street":"May Terrace",
    "iso:country":"GB",
    "sg:address":"May Terrace, Giffnock",
    "sg:city":"Glasgow",
    "sg:classifiers":[
        {
            "category":"Organizations",
            "subcategory":"Non-profit Organization",
            "type":"Services"
        }
    ],
    "sg:phone":"+44 141 620 1800",
    "sg:postcode":"G46 6LD",
    "sg:province":"East Renfrewshire",
    "sg:tags":[
        "organisation",
        "voluntary",
        "charity"
    ],
    "wof:name":"Jewish Care Scotland",
    "wof:placetype":"venue"
},
  "geometry": {"coordinates":[-4.2924938202,55.8045578003],"type":"Point"}
}