{
  "type": "Feature",
  "properties": {
    "iso:country":"GB",
    "sg:address":"Rye Farm Rye Lane, Layer De Lane Haye",
    "sg:city":"Colchester",
    "sg:classifiers":[
        {
            "category":"Farming",
            "subcategory":"Farm",
            "type":"Manufacturing & Wholesale Goods"
        }
    ],
    "sg:postcode":"CO2 0JL",
    "sg:province":"Essex",
    "sg:tags":[
        "mixed",
        "crop"
    ],
    "wof:name":"H & D Bunting",
    "wof:placetype":"venue"
},
  "geometry": {"coordinates":[0.85875,51.840618],"type":"Point"}
}