{
  "type": "Feature",
  "properties": {
    "addr:full":"1 Bristol Road Luton Bedfordshire LU3 1SX",
    "addr:housenumber":"1",
    "addr:postcode":"lu3 1sx",
    "addr:street":"Bristol Road",
    "iso:country":"GB",
    "sg:address":"1 Bristol Road",
    "sg:city":"Luton",
    "sg:classifiers":[
        {
            "category":"Farming",
            "subcategory":"Nursery",
            "type":"Manufacturing & Wholesale Goods"
        }
    ],
    "sg:postcode":"LU3 1SX",
    "sg:province":"Bedfordshire",
    "sg:tags":[
        "creche"
    ],
    "wof:name":"Sunshine Day Nursery",
    "wof:placetype":"venue"
},
  "geometry": {"coordinates":[-0.43670699,51.9006118774],"type":"Point"}
}