{
  "type": "Feature",
  "properties": {
    "addr:full":"12 Arden Street Gillingham Kent ME7 1HG",
    "addr:housenumber":"12",
    "addr:postcode":"me7 1hg",
    "addr:street":"Arden Street",
    "iso:country":"GB",
    "sg:address":"12 Arden Street",
    "sg:city":"Gillingham",
    "sg:classifiers":[
        {
            "category":"Taxi",
            "type":"Transportation"
        },
        {
            "category":"Military Area",
            "subcategory":"Air Force Base",
            "type":"Public Place"
        }
    ],
    "sg:phone":"+44 1634 576666",
    "sg:postcode":"ME7 1HG",
    "sg:province":"Kent",
    "sg:tags":[
        "hire",
        "private"
    ],
    "wof:name":"C N C Taxis",
    "wof:placetype":"venue"
},
  "geometry": {"coordinates":[0.5434510112,51.3889884949],"type":"Point"}
}