{
  "type": "Feature",
  "properties": {
    "iso:country":"GB",
    "sg:address":"76a Western Road",
    "sg:city":"Brighton",
    "sg:classifiers":[
        {
            "category":"Personal",
            "type":"Services"
        }
    ],
    "sg:phone":"+44 1273 858580",
    "sg:postcode":"BN1 2LA",
    "sg:province":"East Sussex",
    "sg:tags":[
        "kiss-o-grams"
    ],
    "wof:name":"Kissograms",
    "wof:placetype":"venue"
},
  "geometry": {"coordinates":[-0.150064,50.824337],"type":"Point"}
}