{
  "type": "Feature",
  "properties": {
    "addr:full":"76-78 Nuttall St Accrington Lancashire BB5 2HL",
    "addr:housenumber":"76-78",
    "addr:postcode":"bb5 2hl",
    "addr:street":"Nuttall St",
    "iso:country":"GB",
    "sg:address":"76-78 Nuttall St",
    "sg:city":"Accrington",
    "sg:classifiers":[
        {
            "category":"Retail",
            "subcategory":"Laundry & Dry Cleaning",
            "type":"Services"
        }
    ],
    "sg:phone":"+44 1254 389865",
    "sg:postcode":"BB5 2HL",
    "sg:province":"Lancashire",
    "sg:tags":[
        "launderette"
    ],
    "wof:name":"Launderette The",
    "wof:placetype":"venue"
},
  "geometry": {"coordinates":[-2.364429,53.748051],"type":"Point"}
}