{
  "type": "Feature",
  "properties": {
    "addr:full":"111 Corringham Road Stanford-le-hope Essex SS17 0AH",
    "addr:housenumber":"111",
    "addr:postcode":"ss17 0ah",
    "addr:street":"Corringham Road",
    "iso:country":"GB",
    "sg:address":"111 Corringham Road",
    "sg:city":"Stanford-le-hope",
    "sg:classifiers":[
        {
            "category":"Place Of Worship",
            "type":"Public Place"
        }
    ],
    "sg:phone":"+44 1375 672329",
    "sg:postcode":"SS17 0AH",
    "sg:province":"Essex",
    "wof:name":"Salvation Army",
    "wof:placetype":"venue"
},
  "geometry": {"coordinates":[0.4365639985,51.515953064],"type":"Point"}
}