{
  "type": "Feature",
  "properties": {
    "addr:full":"63 Mount Gould Rd Plymouth Devon PL4 7PU",
    "addr:housenumber":"63",
    "addr:postcode":"pl4 7pu",
    "addr:street":"Mount Gould Rd",
    "iso:country":"GB",
    "sg:address":"63 Mount Gould Rd",
    "sg:city":"Plymouth",
    "sg:classifiers":[
        {
            "category":"Social Services",
            "subcategory":"Retirement Home",
            "type":"Services"
        }
    ],
    "sg:phone":"+44 1752 661953",
    "sg:postcode":"PL4 7PU",
    "sg:province":"Devon",
    "sg:tags":[
        "residential",
        "care"
    ],
    "wof:name":"Iskamar Residential Home",
    "wof:placetype":"venue"
},
  "geometry": {"coordinates":[-4.1207609177,50.3781967163],"type":"Point"}
}