{
  "type": "Feature",
  "properties": {
    "iso:country":"GB",
    "sg:address":"Bolberry Farm Ho",
    "sg:city":"Kingsbridge",
    "sg:classifiers":[
        {
            "category":"Recreation",
            "subcategory":"Campground",
            "type":"Entertainment"
        }
    ],
    "sg:phone":"+44 1548 561251",
    "sg:postcode":"TQ7 3DY",
    "sg:province":"Devon",
    "sg:tags":[
        "site",
        "camping"
    ],
    "wof:name":"Bolberry House Farm Caravaning & Camping Site",
    "wof:placetype":"venue"
},
  "geometry": {"coordinates":[-3.8362600803,50.2380142212],"type":"Point"}
}