{
  "type": "Feature",
  "properties": {
    "iso:country":"GB",
    "sg:address":"271 Kenton Road",
    "sg:city":"Harrow",
    "sg:classifiers":[
        {
            "category":"Manufacturing",
            "subcategory":"Apparel",
            "type":"Manufacturing & Wholesale Goods"
        }
    ],
    "sg:postcode":"HA3 0HQ",
    "sg:province":"Greater London",
    "sg:tags":[
        "garment",
        "designer"
    ],
    "wof:name":"Rosemary Pierce",
    "wof:placetype":"venue"
},
  "geometry": {"coordinates":[-0.311406,51.584724],"type":"Point"}
}