{
  "type": "Feature",
  "properties": {
    "addr:full":"58 Parliament Road Middlesbrough North Yorkshire TS1 4LA",
    "addr:housenumber":"58",
    "addr:postcode":"ts1 4la",
    "addr:street":"Parliament Road",
    "iso:country":"GB",
    "sg:address":"58 Parliament Road",
    "sg:city":"Middlesbrough",
    "sg:classifiers":[
        {
            "category":"Shopping",
            "subcategory":"Hobbies, Toys, & Games",
            "type":"Retail Goods"
        }
    ],
    "sg:phone":"+44 1642 250177",
    "sg:postcode":"TS1 4LA",
    "sg:province":"North Yorkshire",
    "sg:tags":[
        "collectors'",
        "item"
    ],
    "wof:name":"Boro Programmes",
    "wof:placetype":"venue"
},
  "geometry": {"coordinates":[-1.2436000109,54.5679626465],"type":"Point"}
}