{
  "type": "Feature",
  "properties": {
    "iso:country":"GB",
    "sg:address":"5 Springhill Gardens",
    "sg:city":"Lyme Regis",
    "sg:classifiers":[
        {
            "category":"Taxi",
            "type":"Transportation"
        }
    ],
    "sg:phone":"+44 1297 445884",
    "sg:postcode":"DT7 3HL",
    "sg:province":"Devon",
    "sg:tags":[
        "mini",
        "cab"
    ],
    "wof:name":"Rio's Taxis",
    "wof:placetype":"venue"
},
  "geometry": {"coordinates":[-2.9411,50.729481],"type":"Point"}
}