{
  "type": "Feature",
  "properties": {
    "addr:full":"1 The Street, Charlwood Horley Surrey RH6 0BY",
    "addr:housenumber":"1",
    "addr:postcode":"rh6 0by",
    "addr:street":"The Street",
    "iso:country":"GB",
    "sg:address":"1 The Street, Charlwood",
    "sg:city":"Horley",
    "sg:classifiers":[
        {
            "category":"Building & Trades",
            "subcategory":"Construction",
            "type":"Services"
        }
    ],
    "sg:phone":"+44 1293 862171",
    "sg:postcode":"RH6 0BY",
    "sg:province":"Surrey",
    "sg:tags":[
        "builder"
    ],
    "wof:name":"Trumpet Hill Development Ltd.",
    "wof:placetype":"venue"
},
  "geometry": {"coordinates":[-0.2220319957,51.1547737122],"type":"Point"}
}