{
  "type": "Feature",
  "properties": {
    "addr:full":"Flat 16 42 Carlton Drive London Greater London SW15 2DG",
    "addr:housenumber":"flat;42",
    "addr:postcode":"sw15 2dg",
    "addr:street":"Carlton Drive",
    "iso:country":"GB",
    "sg:address":"Flat 16 42 Carlton Drive",
    "sg:city":"London",
    "sg:classifiers":[
        {
            "category":"Organizations",
            "subcategory":"Membership Organization",
            "type":"Services"
        }
    ],
    "sg:phone":"+44 20 8780 3552",
    "sg:postcode":"SW15 2DG",
    "sg:province":"Greater London",
    "sg:tags":[
        "club"
    ],
    "wof:name":"Kwiktemp Management Ltd.",
    "wof:placetype":"venue"
},
  "geometry": {"coordinates":[-0.2182099968,51.4578704834],"type":"Point"}
}