{
  "type": "Feature",
  "properties": {
    "addr:full":"2 Tamworth Clo Northwood Greater London HA6 2GF",
    "addr:housenumber":"2",
    "addr:postcode":"ha6 2gf",
    "addr:street":"Tamworth Clo",
    "iso:country":"GB",
    "sg:address":"2 Tamworth Clo",
    "sg:city":"Northwood",
    "sg:classifiers":[
        {
            "category":"Banks & Credit Unions",
            "subcategory":"Financial Services",
            "type":"Services"
        },
        {
            "category":"Building & Trades",
            "subcategory":"Construction",
            "type":"Services"
        }
    ],
    "sg:phone":"+44 1923 840879",
    "sg:postcode":"HA6 2GF",
    "sg:province":"Greater London",
    "sg:tags":[
        "consultant",
        "builder"
    ],
    "wof:name":"Churston Bywater Ltd",
    "wof:placetype":"venue"
},
  "geometry": {"coordinates":[-0.439955,51.615711],"type":"Point"}
}