{
  "type": "Feature",
  "properties": {
    "addr:full":"Sainham Farm, Sheepwash Lane, Godshill Ventnor Isle of Wight PO38 3JS",
    "addr:postcode":"po38 3js",
    "addr:street":"Sheepwash Lane",
    "iso:country":"GB",
    "sg:address":"Sainham Farm, Sheepwash Lane, Godshill",
    "sg:city":"Ventnor",
    "sg:classifiers":[
        {
            "category":"Professional",
            "subcategory":"Lawyer & Legal Services",
            "type":"Services"
        }
    ],
    "sg:phone":"+44 1983 840900",
    "sg:postcode":"PO38 3JS",
    "sg:province":"Isle of Wight",
    "sg:tags":[
        "solicitor"
    ],
    "wof:name":"Maclean Harrhy Solicitors",
    "wof:placetype":"venue"
},
  "geometry": {"coordinates":[-1.253487,50.632744],"type":"Point"}
}