{
  "type": "Feature",
  "properties": {
    "addr:full":"Staff Club, 197 Brook Hill Sheffield South Yorkshire S3 7HG",
    "addr:housenumber":"197",
    "addr:postcode":"s3 7hg",
    "iso:country":"GB",
    "sg:address":"Staff Club, 197 Brook Hill",
    "sg:city":"Sheffield",
    "sg:classifiers":[
        {
            "category":"Organizations",
            "subcategory":"Membership Organization",
            "type":"Services"
        }
    ],
    "sg:phone":"+44 114 222 2000",
    "sg:postcode":"S3 7HG",
    "sg:province":"South Yorkshire",
    "sg:tags":[
        "club"
    ],
    "wof:name":"Club 197",
    "wof:placetype":"venue"
},
  "geometry": {"coordinates":[-1.4852399826,53.3818817139],"type":"Point"}
}