{
  "type": "Feature",
  "properties": {
    "iso:country":"GB",
    "sg:address":"211 Deepdale Road",
    "sg:city":"Preston",
    "sg:classifiers":[
        {
            "category":"Home & Garden",
            "subcategory":"Carpets & Floor Coverings",
            "type":"Retail Goods"
        }
    ],
    "sg:phone":"+44 1772 562388",
    "sg:postcode":"PR1 6LJ",
    "sg:province":"Lancashire",
    "sg:tags":[
        "carpets",
        "rug",
        "matting"
    ],
    "wof:name":"Kozy Carpets & Home Furnishings",
    "wof:placetype":"venue"
},
  "geometry": {"coordinates":[-2.6916539669,53.7682342529],"type":"Point"}
}