{
  "type": "Feature",
  "properties": {
    "addr:full":"189 Barkerhouse Rd Nelson Lancashire BB9 9NP",
    "addr:housenumber":"189",
    "addr:postcode":"bb9 9np",
    "addr:street":"Barkerhouse Rd",
    "iso:country":"GB",
    "sg:address":"189 Barkerhouse Rd",
    "sg:city":"Nelson",
    "sg:classifiers":[
        {
            "category":"Shopping",
            "subcategory":"News",
            "type":"Retail Goods"
        },
        {
            "category":"Food & Beverages",
            "subcategory":"Groceries & Convenience Stores",
            "type":"Retail Goods"
        }
    ],
    "sg:phone":"+44 1282 613455",
    "sg:postcode":"BB9 9NP",
    "sg:province":"Lancashire",
    "sg:tags":[
        "newsagent"
    ],
    "wof:name":"Marsden News",
    "wof:placetype":"venue"
},
  "geometry": {"coordinates":[-2.196961,53.835804],"type":"Point"}
}