{
  "type": "Feature",
  "properties": {
    "addr:full":"6 Castle Street, Bolsover Chesterfield Derbyshire S44 6PP",
    "addr:housenumber":"6",
    "addr:postcode":"s44 6pp",
    "addr:street":"Castle Street",
    "iso:country":"GB",
    "sg:address":"6 Castle Street, Bolsover",
    "sg:city":"Chesterfield",
    "sg:classifiers":[
        {
            "category":"Retail",
            "subcategory":"Repair Shop",
            "type":"Services"
        }
    ],
    "sg:phone":"+44 1246 826578",
    "sg:postcode":"S44 6PP",
    "sg:province":"Derbyshire",
    "sg:tags":[
        "radio",
        "television",
        "video"
    ],
    "wof:name":"Rileys T V Services",
    "wof:placetype":"venue"
},
  "geometry": {"coordinates":[-1.2933360338,53.2294921875],"type":"Point"}
}