{
  "type": "Feature",
  "properties": {
    "addr:full":"12 Corporation Rd Newport East Riding of Yorkshire NP9 0AJ",
    "addr:housenumber":"12",
    "addr:postcode":"np9 0aj",
    "addr:street":"Corporation Rd",
    "iso:country":"GB",
    "sg:address":"12 Corporation Rd",
    "sg:city":"Newport",
    "sg:classifiers":[
        {
            "category":"Organizations",
            "subcategory":"Non-profit Organization",
            "type":"Services"
        }
    ],
    "sg:phone":"+44 1633 223608",
    "sg:postcode":"NP9 0AJ",
    "sg:province":"East Riding of Yorkshire",
    "sg:tags":[
        "organisation",
        "voluntary",
        "charity"
    ],
    "wof:name":"Alzheimers Disease Society",
    "wof:placetype":"venue"
},
  "geometry": {"coordinates":[-2.9894530773,51.5905189514],"type":"Point"}
}