{
  "type": "Feature",
  "properties": {
    "iso:country":"GB",
    "sg:address":"Suckley",
    "sg:city":"Worcester",
    "sg:classifiers":[
        {
            "category":"Food & Beverages",
            "subcategory":"Farmers Market",
            "type":"Retail Goods"
        }
    ],
    "sg:phone":"+44 1886 880617",
    "sg:postcode":"WR6 5EJ",
    "sg:province":"Herefordshire",
    "sg:tags":[
        "farm",
        "shop",
        "pyo"
    ],
    "wof:name":"Parsons Nose",
    "wof:placetype":"venue"
},
  "geometry": {"coordinates":[-2.4184598923,52.1463813782],"type":"Point"}
}