{
  "type": "Feature",
  "properties": {
    "iso:country":"GB",
    "sg:address":"Albion Business Centre, Albion Road",
    "sg:city":"Edinburgh",
    "sg:classifiers":[
        {
            "category":"Professional",
            "subcategory":"Business Services",
            "type":"Services"
        }
    ],
    "sg:phone":"+44 131 652 0490",
    "sg:postcode":"EH7 5QZ",
    "sg:province":"City of Edinburgh",
    "sg:tags":[
        "tile",
        "stockist"
    ],
    "wof:name":"Ceri White Studio S",
    "wof:placetype":"venue"
},
  "geometry": {"coordinates":[-3.16576,55.960789],"type":"Point"}
}