{
  "type": "Feature",
  "properties": {
    "iso:country":"GB",
    "sg:address":"13 Hartington Place",
    "sg:city":"Eastbourne",
    "sg:classifiers":[
        {
            "category":"Travel",
            "subcategory":"Hotels & Motels",
            "type":"Entertainment"
        }
    ],
    "sg:phone":"+44 1323 724784",
    "sg:postcode":"BN21 3BS",
    "sg:province":"East Sussex",
    "wof:name":"Tiverton House Hotel",
    "wof:placetype":"venue"
},
  "geometry": {"coordinates":[0.289142,50.765469],"type":"Point"}
}