{
  "type": "Feature",
  "properties": {
    "iso:country":"GB",
    "sg:address":"3-4 Kirby Street, Hatton Garden",
    "sg:city":"London",
    "sg:classifiers":[
        {
            "category":"Professional",
            "subcategory":"Advertising",
            "type":"Services"
        }
    ],
    "sg:phone":"+44 20 7025 3500",
    "sg:postcode":"EC1N 8TS",
    "sg:province":"Greater London",
    "sg:tags":[
        "agency"
    ],
    "wof:name":"Ward Diamond Advertising Ltd.",
    "wof:placetype":"venue"
},
  "geometry": {"coordinates":[-0.106984,51.519753],"type":"Point"}
}