{
  "type": "Feature",
  "properties": {
    "addr:full":"Mill House, Old Furness Clo, High St Lydney Gloucestershire GL15 5FB",
    "addr:postcode":"gl15 5fb",
    "addr:street":"Old;High St",
    "iso:country":"GB",
    "sg:address":"Mill House, Old Furness Clo, High St",
    "sg:city":"Lydney",
    "sg:classifiers":[
        {
            "category":"Professional",
            "subcategory":"Management & Consulting",
            "type":"Services"
        }
    ],
    "sg:phone":"+44 1594 840032",
    "sg:postcode":"GL15 5FB",
    "sg:province":"Gloucestershire",
    "sg:tags":[
        "consultant"
    ],
    "wof:name":"Lifetime Communications (U K) Ltd",
    "wof:placetype":"venue"
},
  "geometry": {"coordinates":[-2.5358190536,51.7244911194],"type":"Point"}
}