{
  "type": "Feature",
  "properties": {
    "iso:country":"GB",
    "sg:address":"Unit 1 West Park View, Dudley",
    "sg:city":"Cramlington",
    "sg:classifiers":[
        {
            "category":"Retail",
            "subcategory":"Auto Repair",
            "type":"Services"
        }
    ],
    "sg:phone":"+44 191 250 2807",
    "sg:postcode":"NE23 7AD",
    "sg:province":"Northumberland",
    "sg:tags":[
        "modification",
        "garage"
    ],
    "wof:name":"Mitchell's Garage",
    "wof:placetype":"venue"
},
  "geometry": {"coordinates":[-1.578294,55.055634],"type":"Point"}
}