{
  "type": "Feature",
  "properties": {
    "iso:country":"GB",
    "sg:address":"The Gatehouse, Warsop Trading Estate, Hever Road",
    "sg:city":"Edenbridge",
    "sg:classifiers":[
        {
            "category":"Building & Trades",
            "subcategory":"Construction",
            "type":"Services"
        }
    ],
    "sg:phone":"+44 1732 865066",
    "sg:postcode":"TN8 7NP",
    "sg:province":"East Sussex",
    "sg:tags":[
        "contractor"
    ],
    "wof:name":"Advanced Contractors",
    "wof:placetype":"venue"
},
  "geometry": {"coordinates":[0.1101929992,51.1835021973],"type":"Point"}
}