{
  "type": "Feature",
  "properties": {
    "addr:full":"Trent House, Trent Bridge Nottingham Nottinghamshire NG2 5GN",
    "addr:postcode":"ng2 5gn",
    "addr:street":"Trent Bridge",
    "iso:country":"GB",
    "sg:address":"Trent House, Trent Bridge",
    "sg:city":"Nottingham",
    "sg:classifiers":[
        {
            "category":"Restaurant",
            "type":"Food & Drink"
        }
    ],
    "sg:phone":"+44 115 914 0038",
    "sg:postcode":"NG2 5GN",
    "sg:province":"Nottinghamshire",
    "sg:tags":[
        "-",
        "italian"
    ],
    "wof:name":"PONTE VECCHIO RESTAURANT",
    "wof:placetype":"venue"
},
  "geometry": {"coordinates":[-1.1346069574,52.9375686646],"type":"Point"}
}