{
  "type": "Feature",
  "properties": {
    "addr:full":"7 Woodland Rise, Rilla Mill Callington Cornwall PL17 7NZ",
    "addr:housenumber":"7",
    "addr:postcode":"pl17 7nz",
    "addr:street":"Woodland Rise Rilla",
    "iso:country":"GB",
    "sg:address":"7 Woodland Rise, Rilla Mill",
    "sg:city":"Callington",
    "sg:classifiers":[
        {
            "category":"Retail",
            "subcategory":"Animal Services",
            "type":"Services"
        },
        {
            "category":"Personal",
            "subcategory":"Adult",
            "type":"Services"
        }
    ],
    "sg:postcode":"PL17 7NZ",
    "sg:province":"Cornwall",
    "sg:tags":[
        "farrier",
        "equestrian"
    ],
    "wof:name":"PAUL JOHNSON",
    "wof:placetype":"venue"
},
  "geometry": {"coordinates":[-4.406441,50.534561],"type":"Point"}
}