{
  "type": "Feature",
  "properties": {
    "addr:full":"191 Househillwood Road Glasgow East Renfrewshire G53 6BX",
    "addr:housenumber":"191",
    "addr:postcode":"g53 6bx",
    "addr:street":"Househillwood Road",
    "iso:country":"GB",
    "sg:address":"191 Househillwood Road",
    "sg:city":"Glasgow",
    "sg:classifiers":[
        {
            "category":"Food & Beverages",
            "subcategory":"Liquor & Beverages",
            "type":"Retail Goods"
        }
    ],
    "sg:phone":"+44 141 848 1096",
    "sg:postcode":"G53 6BX",
    "sg:province":"East Renfrewshire",
    "sg:tags":[
        "beer",
        "spirit",
        "wines"
    ],
    "wof:name":"Haddows",
    "wof:placetype":"venue"
},
  "geometry": {"coordinates":[-4.3526201248,55.8184165955],"type":"Point"}
}