{
  "type": "Feature",
  "properties": {
    "iso:country":"GB",
    "sg:address":"1348 Maryhill Road",
    "sg:city":"Glasgow",
    "sg:classifiers":[
        {
            "category":"Restaurant",
            "type":"Food & Drink"
        }
    ],
    "sg:phone":"+44 141 946 7584",
    "sg:postcode":"G20 9DG",
    "sg:province":"Glasgow City",
    "sg:tags":[
        "indian"
    ],
    "wof:name":"Shish Mahal",
    "wof:placetype":"venue"
},
  "geometry": {"coordinates":[-4.2877,55.889153],"type":"Point"}
}