{
  "type": "Feature",
  "properties": {
    "iso:country":"GB",
    "sg:address":"25 Frederick St",
    "sg:city":"Edinburgh",
    "sg:classifiers":[
        {
            "category":"Health Services",
            "subcategory":"Dentist",
            "type":"Services"
        }
    ],
    "sg:phone":"+44 131 225 1558",
    "sg:postcode":"EH2 2ND",
    "sg:province":"City of Edinburgh",
    "wof:name":"James S Sharp",
    "wof:placetype":"venue"
},
  "geometry": {"coordinates":[-3.199901104,55.9525985718],"type":"Point"}
}