{
  "type": "Feature",
  "properties": {
    "addr:full":"13 Trinity Street St Austell Cornwall PL25 5LS",
    "addr:housenumber":"13",
    "addr:postcode":"pl25 5ls",
    "addr:street":"Trinity Street",
    "iso:country":"GB",
    "sg:address":"13 Trinity Street",
    "sg:city":"St Austell",
    "sg:classifiers":[
        {
            "category":"Shopping",
            "subcategory":"Thrift Store",
            "type":"Retail Goods"
        }
    ],
    "sg:phone":"+44 1726 67647",
    "sg:postcode":"PL25 5LS",
    "sg:province":"Cornwall",
    "sg:tags":[
        "shop",
        "charity"
    ],
    "wof:name":"Marie Curie Cancer Care",
    "wof:placetype":"venue"
},
  "geometry": {"coordinates":[-4.795413,50.337746],"type":"Point"}
}