{
  "type": "Feature",
  "properties": {
    "iso:country":"GB",
    "sg:address":"Unit 2 Queen Street",
    "sg:city":"Northwich",
    "sg:classifiers":[
        {
            "category":"Autos & Motor Vehicles",
            "subcategory":"Auto Supplies",
            "type":"Retail Goods"
        },
        {
            "category":"Retail",
            "subcategory":"Auto Repair",
            "type":"Services"
        }
    ],
    "sg:phone":"+44 1606 48525",
    "sg:postcode":"CW9 5JN",
    "sg:province":"Cheshire",
    "sg:tags":[
        "garage",
        "component",
        "related"
    ],
    "wof:name":"RUDHEATH AUTO PARTS LTD",
    "wof:placetype":"venue"
},
  "geometry": {"coordinates":[-2.5140390396,53.2578163147],"type":"Point"}
}