{
  "type": "Feature",
  "properties": {
    "iso:country":"GB",
    "sg:address":"Concorde House, 81 Gloucester Road Patchway",
    "sg:city":"Bristol",
    "sg:classifiers":[
        {
            "category":"Building & Trades",
            "subcategory":"Construction",
            "type":"Services"
        }
    ],
    "sg:postcode":"BS34 5JQ",
    "sg:province":"Gloucestershire",
    "sg:tags":[
        "roofing"
    ],
    "wof:name":"A.A.C. Electrical Ltd",
    "wof:placetype":"venue"
},
  "geometry": {"coordinates":[-2.5706,51.528931],"type":"Point"}
}