{
  "type": "Feature",
  "properties": {
    "iso:country":"GB",
    "sg:address":"10 Wesley Street",
    "sg:city":"Cleckheaton",
    "sg:classifiers":[
        {
            "category":"Home & Garden",
            "subcategory":"Building Materials",
            "type":"Retail Goods"
        }
    ],
    "sg:postcode":"BD19 3PU",
    "sg:province":"West Yorkshire",
    "sg:tags":[
        "insulation",
        "installers"
    ],
    "wof:name":"Winter Warm Insullations",
    "wof:placetype":"venue"
},
  "geometry": {"coordinates":[-1.7153589725,53.7284584045],"type":"Point"}
}