{
  "type": "Feature",
  "properties": {
    "iso:country":"GB",
    "sg:address":"Alresford Ho,, 60 West St,",
    "sg:city":"Farnham",
    "sg:classifiers":[
        {
            "category":"Shopping",
            "subcategory":"Florist",
            "type":"Retail Goods"
        }
    ],
    "sg:postcode":"GU9 7EH",
    "sg:province":"Surrey",
    "wof:name":"Palm Brokers Ltd",
    "wof:placetype":"venue"
},
  "geometry": {"coordinates":[-0.8008369803,51.2143211365],"type":"Point"}
}