{
  "type": "Feature",
  "properties": {
    "addr:full":"48 Bedford Street London Greater London WC2E 9HA",
    "addr:housenumber":"48",
    "addr:postcode":"wc2e 9ha",
    "addr:street":"Bedford Street",
    "iso:country":"GB",
    "sg:address":"48 Bedford Street",
    "sg:city":"London",
    "sg:classifiers":[
        {
            "category":"Health Services",
            "subcategory":"Dentist",
            "type":"Services"
        }
    ],
    "sg:phone":"+44 20 7836 3916",
    "sg:postcode":"WC2E 9HA",
    "sg:province":"Greater London",
    "wof:name":"Michael J Forster",
    "wof:placetype":"venue"
},
  "geometry": {"coordinates":[-0.124099,51.510361],"type":"Point"}
}