{
  "type": "Feature",
  "properties": {
    "iso:country":"GB",
    "sg:address":"Robert St",
    "sg:city":"Wishaw",
    "sg:classifiers":[
        {
            "category":"Farming",
            "subcategory":"Dairy Farm",
            "type":"Manufacturing & Wholesale Goods"
        }
    ],
    "sg:phone":"+44 1698 372939",
    "sg:postcode":"ML2 7JF",
    "sg:province":"North Lanarkshire",
    "wof:name":"J Steel & Son",
    "wof:placetype":"venue"
},
  "geometry": {"coordinates":[-3.920879,55.774391],"type":"Point"}
}