{
  "type": "Feature",
  "properties": {
    "addr:full":"Unit 46 Vulcan House, Vulcan Road Leicester Leicestershire LE5 3EF",
    "addr:housenumber":"unit 46",
    "addr:postcode":"le5 3ef",
    "addr:street":"Vulcan Road",
    "iso:country":"GB",
    "sg:address":"Unit 46 Vulcan House, Vulcan Road",
    "sg:city":"Leicester",
    "sg:classifiers":[
        {
            "category":"Retail",
            "subcategory":"Portrait Studio",
            "type":"Services"
        },
        {
            "category":"Professional",
            "subcategory":"Printing & Photocopies",
            "type":"Services"
        }
    ],
    "sg:phone":"+44 116 251 8383",
    "sg:postcode":"LE5 3EF",
    "sg:province":"Leicestershire",
    "sg:tags":[
        "photographer",
        "commercial",
        "duplicating",
        "copying"
    ],
    "wof:name":"Gavin Harrison",
    "wof:placetype":"venue"
},
  "geometry": {"coordinates":[-1.1145190001,52.6386985779],"type":"Point"}
}