{
  "type": "Feature",
  "properties": {
    "addr:full":"21 Church Road Nuneaton Leicestershire CV10 8LB",
    "addr:housenumber":"21",
    "addr:postcode":"cv10 8lb",
    "addr:street":"Church Road",
    "iso:country":"GB",
    "sg:address":"21 Church Road",
    "sg:city":"Nuneaton",
    "sg:classifiers":[
        {
            "category":"Home & Garden",
            "subcategory":"Hardware",
            "type":"Retail Goods"
        }
    ],
    "sg:postcode":"CV10 8LB",
    "sg:province":"Leicestershire",
    "sg:tags":[
        "retailer",
        "diy"
    ],
    "wof:name":"Greenways",
    "wof:placetype":"venue"
},
  "geometry": {"coordinates":[-1.508374,52.523033],"type":"Point"}
}