{
  "type": "Feature",
  "properties": {
    "iso:country":"GB",
    "sg:address":"Sheriff Court House, Castlehill",
    "sg:city":"Campbeltown",
    "sg:classifiers":[
        {
            "category":"Government",
            "subcategory":"Court House",
            "type":"Public Place"
        }
    ],
    "sg:phone":"+44 1586 552503",
    "sg:postcode":"PA28 6AN",
    "sg:province":"Argyll and Bute",
    "wof:name":"Sheriff Clerk S Office",
    "wof:placetype":"venue"
},
  "geometry": {"coordinates":[-5.6067290306,55.423248291],"type":"Point"}
}