{
  "type": "Feature",
  "properties": {
    "addr:full":"50 High Street, Yatton Bristol Somerset BS49 4HY",
    "addr:housenumber":"50",
    "addr:postcode":"bs49 4hy",
    "addr:street":"High Street",
    "iso:country":"GB",
    "sg:address":"50 High Street, Yatton",
    "sg:city":"Bristol",
    "sg:classifiers":[
        {
            "category":"Manufacturing",
            "subcategory":"Tools & Machinery",
            "type":"Manufacturing & Wholesale Goods"
        }
    ],
    "sg:phone":"+44 1934 834879",
    "sg:postcode":"BS49 4HY",
    "sg:province":"Somerset",
    "sg:tags":[
        "society",
        "friendly"
    ],
    "wof:name":"Beecham & Co.",
    "wof:placetype":"venue"
},
  "geometry": {"coordinates":[-2.7973470688,51.3937835693],"type":"Point"}
}