{
  "type": "Feature",
  "properties": {
    "addr:full":"492 Llangyfelach Rd Swansea Swansea SA5 9EA",
    "addr:housenumber":"492",
    "addr:postcode":"sa5 9ea",
    "addr:street":"Llangyfelach Rd",
    "iso:country":"GB",
    "sg:address":"492 Llangyfelach Rd",
    "sg:city":"Swansea",
    "sg:classifiers":[
        {
            "category":"Retail",
            "subcategory":"Driving School",
            "type":"Services"
        }
    ],
    "sg:phone":"+44 1792 472104",
    "sg:postcode":"SA5 9EA",
    "sg:province":"Swansea",
    "wof:name":"Brynhyfryd Driving School",
    "wof:placetype":"venue"
},
  "geometry": {"coordinates":[-3.94597,51.645176],"type":"Point"}
}