{
  "type": "Feature",
  "properties": {
    "addr:full":"29 Peter Street London Greater London W1F 0AN",
    "addr:housenumber":"29",
    "addr:postcode":"w1f 0an",
    "addr:street":"Peter Street",
    "iso:country":"GB",
    "sg:address":"29 Peter Street",
    "sg:city":"London",
    "sg:classifiers":[
        {
            "category":"Health Services",
            "subcategory":"Optometrist",
            "type":"Services"
        }
    ],
    "sg:phone":"+44 20 7734 8322",
    "sg:postcode":"W1F 0AN",
    "sg:province":"Greater London",
    "sg:tags":[
        "optician"
    ],
    "wof:name":"Sight Care",
    "wof:placetype":"venue"
},
  "geometry": {"coordinates":[-0.1338369995,51.5127677917],"type":"Point"}
}