{
  "type": "Feature",
  "properties": {
    "addr:full":"Po Box 26 Wigan Lancashire WN2 4WZ",
    "addr:housenumber":"po box 26",
    "addr:postcode":"wn2 4wz",
    "iso:country":"GB",
    "sg:address":"Po Box 26",
    "sg:city":"Wigan",
    "sg:classifiers":[
        {
            "category":"Shopping",
            "subcategory":"Crafts & Fabrics",
            "type":"Retail Goods"
        }
    ],
    "sg:phone":"+44 1942 525500",
    "sg:postcode":"WN2 4WZ",
    "sg:province":"Lancashire",
    "sg:tags":[
        "belting"
    ],
    "wof:name":"Contitech United Kingdom Ltd.",
    "wof:placetype":"venue"
},
  "geometry": {"coordinates":[-2.5555400848,53.528301239],"type":"Point"}
}