{
  "type": "Feature",
  "properties": {
    "iso:country":"GB",
    "sg:address":"68-70 Foxhall Road",
    "sg:city":"Blackpool",
    "sg:classifiers":[
        {
            "category":"Organizations",
            "subcategory":"Community Association",
            "type":"Services"
        },
        {
            "category":"Organizations",
            "subcategory":"Membership Organization",
            "type":"Services"
        }
    ],
    "sg:phone":"+44 1253 621039",
    "sg:postcode":"FY1 5BL",
    "sg:province":"Lancashire",
    "sg:tags":[
        "club",
        "social"
    ],
    "wof:name":"The Philharmonic Club",
    "wof:placetype":"venue"
},
  "geometry": {"coordinates":[-3.054791,53.80928],"type":"Point"}
}