{
  "type": "Feature",
  "properties": {
    "addr:full":"45 Baxter Gate Loughborough Leicestershire LE11 1TH",
    "addr:housenumber":"45",
    "addr:postcode":"le11 1th",
    "addr:street":"Baxter Gate",
    "iso:country":"GB",
    "sg:address":"45 Baxter Gate",
    "sg:city":"Loughborough",
    "sg:classifiers":[
        {
            "category":"Retail",
            "subcategory":"Funeral Services",
            "type":"Services"
        }
    ],
    "sg:phone":"+44 1509 214286",
    "sg:postcode":"LE11 1TH",
    "sg:province":"Leicestershire",
    "sg:tags":[
        "director"
    ],
    "wof:name":"Charnwood Funeral Services Ltd",
    "wof:placetype":"venue"
},
  "geometry": {"coordinates":[-1.2032389641,52.7728157043],"type":"Point"}
}