{
  "type": "Feature",
  "properties": {
    "iso:country":"GB",
    "sg:address":"Ford Green Road, Smallthorne",
    "sg:city":"Stoke-on-trent",
    "sg:classifiers":[
        {
            "category":"Government",
            "subcategory":"Office",
            "type":"Public Place"
        },
        {
            "category":"Museum",
            "subcategory":"Art Museum",
            "type":"Entertainment"
        },
        {
            "category":"Landmark",
            "subcategory":"Tourist Attraction",
            "type":"Public Place"
        }
    ],
    "sg:phone":"+44 1782 233195",
    "sg:postcode":"ST6 1NG",
    "sg:province":"Staffordshire",
    "sg:tags":[
        "local",
        "gallery",
        "interest"
    ],
    "wof:name":"Ford Green Hall Museum",
    "wof:placetype":"venue"
},
  "geometry": {"coordinates":[-2.169364,53.0546],"type":"Point"}
}