{
  "type": "Feature",
  "properties": {
    "iso:country":"GB",
    "sg:address":"72 Morris St",
    "sg:city":"Swindon",
    "sg:classifiers":[
        {
            "category":"Professional",
            "subcategory":"Management & Consulting",
            "type":"Services"
        }
    ],
    "sg:postcode":"SN2 2HU",
    "sg:province":"Wiltshire",
    "sg:tags":[
        "consultant",
        "specialist"
    ],
    "wof:name":"Page,Sheila,",
    "wof:placetype":"venue"
},
  "geometry": {"coordinates":[-1.803256,51.564861],"type":"Point"}
}