{
  "type": "Feature",
  "properties": {
    "iso:country":"GB",
    "sg:address":"367 Walmersley Rd",
    "sg:city":"Bury",
    "sg:classifiers":[
        {
            "category":"Government",
            "subcategory":"Office",
            "type":"Public Place"
        }
    ],
    "sg:phone":"+44 161 253 6206",
    "sg:postcode":"BL9 5EZ",
    "sg:province":"Lancashire",
    "sg:tags":[
        "local"
    ],
    "wof:name":"Moorside Neighbourhood Housing Office",
    "wof:placetype":"venue"
},
  "geometry": {"coordinates":[-2.292738,53.610458],"type":"Point"}
}