{
  "type": "Feature",
  "properties": {
    "addr:full":"P O Box 310 Horsham West Sussex RH12 5LE",
    "addr:housenumber":"310",
    "addr:postcode":"rh12 5le",
    "addr:street":"P O Box",
    "iso:country":"GB",
    "sg:address":"P O Box 310",
    "sg:city":"Horsham",
    "sg:classifiers":[
        {
            "category":"Banks & Credit Unions",
            "subcategory":"Bank",
            "type":"Services"
        }
    ],
    "sg:postcode":"RH12 5LE",
    "sg:province":"West Sussex",
    "sg:tags":[
        "broker",
        "mortgage"
    ],
    "wof:name":"Christopher Threadgold",
    "wof:placetype":"venue"
},
  "geometry": {"coordinates":[-0.3291069865,51.0651817322],"type":"Point"}
}