{
  "type": "Feature",
  "properties": {
    "iso:country":"GB",
    "sg:address":"828 Newport Road, Rumney",
    "sg:city":"Cardiff",
    "sg:classifiers":[
        {
            "category":"Food & Beverages",
            "subcategory":"Bakery",
            "type":"Retail Goods"
        }
    ],
    "sg:phone":"+44 29 2079 7759",
    "sg:postcode":"CF3 4LH",
    "sg:province":"Caerphilly",
    "sg:tags":[
        "shop",
        "baker"
    ],
    "wof:name":"Tom Godsall",
    "wof:placetype":"venue"
},
  "geometry": {"coordinates":[-3.130274,51.509544],"type":"Point"}
}