{
  "type": "Feature",
  "properties": {
    "addr:full":"117 Badsey Lane Evesham Gloucestershire WR11 3EY",
    "addr:housenumber":"117",
    "addr:postcode":"wr11 3ey",
    "addr:street":"Badsey Lane",
    "iso:country":"GB",
    "sg:address":"117 Badsey Lane",
    "sg:city":"Evesham",
    "sg:classifiers":[
        {
            "category":"Personal",
            "type":"Services"
        }
    ],
    "sg:phone":"+44 1386 446242",
    "sg:postcode":"WR11 3EY",
    "sg:province":"Gloucestershire",
    "sg:tags":[
        "wedding"
    ],
    "wof:name":"Greensleeves Bridal Wear",
    "wof:placetype":"venue"
},
  "geometry": {"coordinates":[-1.9245760441,52.0882453918],"type":"Point"}
}