{
  "type": "Feature",
  "properties": {
    "iso:country":"GB",
    "sg:address":"11 New Conduit St",
    "sg:city":"King's Lynn",
    "sg:classifiers":[
        {
            "category":"Professional",
            "subcategory":"Business Services",
            "type":"Services"
        }
    ],
    "sg:phone":"+44 1469 554600",
    "sg:postcode":"PE30 1DG",
    "sg:province":"Norfolk",
    "sg:tags":[
        "import",
        "export",
        "agent"
    ],
    "wof:name":"Marine Traders Ltd",
    "wof:placetype":"venue"
},
  "geometry": {"coordinates":[0.3960059881,52.7539634705],"type":"Point"}
}