{
  "type": "Feature",
  "properties": {
    "iso:country":"GB",
    "sg:address":"3 Russell Close, Landkey",
    "sg:city":"Barnstaple",
    "sg:classifiers":[
        {
            "category":"Building & Trades",
            "subcategory":"Pest Control",
            "type":"Services"
        }
    ],
    "sg:phone":"+44 1271 830145",
    "sg:postcode":"EX32 0NZ",
    "sg:province":"Devon",
    "sg:tags":[
        "vermin"
    ],
    "wof:name":"West of Exmoor Pest Control",
    "wof:placetype":"venue"
},
  "geometry": {"coordinates":[-3.997479,51.061295],"type":"Point"}
}