{
  "type": "Feature",
  "properties": {
    "addr:full":"Boundary Road Middlesbrough North Yorkshire TS1 5AQ",
    "addr:postcode":"ts1 5aq",
    "addr:street":"Boundary Road",
    "iso:country":"GB",
    "sg:address":"Boundary Road",
    "sg:city":"Middlesbrough",
    "sg:classifiers":[
        {
            "category":"Autos & Motor Vehicles",
            "subcategory":"Auto Supplies",
            "type":"Retail Goods"
        }
    ],
    "sg:phone":"+44 1642 224494",
    "sg:postcode":"TS1 5AQ",
    "sg:province":"North Yorkshire",
    "sg:tags":[
        "tyre"
    ],
    "wof:name":"Morgans Tyres",
    "wof:placetype":"venue"
},
  "geometry": {"coordinates":[-1.241009,54.578945],"type":"Point"}
}