{
  "type": "Feature",
  "properties": {
    "iso:country":"GB",
    "sg:address":"58 West End",
    "sg:city":"Redruth",
    "sg:classifiers":[
        {
            "category":"Real Estate",
            "subcategory":"Real Estate Agent",
            "type":"Services"
        }
    ],
    "sg:phone":"+44 1209 215566",
    "sg:postcode":"TR15 2SQ",
    "sg:province":"Cornwall",
    "wof:name":"Real Estate",
    "wof:placetype":"venue"
},
  "geometry": {"coordinates":[-5.232055,50.232334],"type":"Point"}
}