{
  "type": "Feature",
  "properties": {
    "iso:country":"GB",
    "sg:address":"16 The Village Workshop, Mountheath Industrial Park, George St Prestwich",
    "sg:city":"Manchester",
    "sg:classifiers":[
        {
            "category":"Wholesale",
            "subcategory":"Medical Equipment & Supplies",
            "type":"Manufacturing & Wholesale Goods"
        }
    ],
    "sg:phone":"+44 161 773 5498",
    "sg:postcode":"M25 9WB",
    "sg:province":"Greater Manchester",
    "sg:tags":[
        "dental"
    ],
    "wof:name":"Teamwax Supplies",
    "wof:placetype":"venue"
},
  "geometry": {"coordinates":[-2.2766900063,53.5176582336],"type":"Point"}
}