{
  "type": "Feature",
  "properties": {
    "addr:full":"9 Kettlehouse Road Birmingham West Midlands B44 9JH",
    "addr:housenumber":"9",
    "addr:postcode":"b44 9jh",
    "addr:street":"Kettlehouse Road",
    "iso:country":"GB",
    "sg:address":"9 Kettlehouse Road",
    "sg:city":"Birmingham",
    "sg:classifiers":[
        {
            "category":"Food & Beverages",
            "subcategory":"Meat & Fish",
            "type":"Retail Goods"
        },
        {
            "category":"Food & Beverages",
            "subcategory":"Groceries & Convenience Stores",
            "type":"Retail Goods"
        }
    ],
    "sg:phone":"+44 121 355 1720",
    "sg:postcode":"B44 9JH",
    "sg:province":"West Midlands",
    "sg:tags":[
        "shop",
        "chip"
    ],
    "wof:name":"Kingstanding Fish Bar",
    "wof:placetype":"venue"
},
  "geometry": {"coordinates":[-1.8847539425,52.553653717],"type":"Point"}
}