{
  "type": "Feature",
  "properties": {
    "iso:country":"GB",
    "sg:address":"Chappel Drive, Wholesale Fruit Market",
    "sg:city":"Doncaster",
    "sg:classifiers":[
        {
            "category":"Wholesale",
            "subcategory":"Fruits & Vegetables",
            "type":"Manufacturing & Wholesale Goods"
        }
    ],
    "sg:phone":"+44 1302 323497",
    "sg:postcode":"DN1 2RF",
    "sg:province":"South Yorkshire",
    "wof:name":"Smalley & Taylor Ltd.",
    "wof:placetype":"venue"
},
  "geometry": {"coordinates":[-1.1308799982,53.5276908875],"type":"Point"}
}