{
  "type": "Feature",
  "properties": {
    "iso:country":"GB",
    "sg:address":"Ultracomp House, Pinehill Road",
    "sg:city":"Crowthorne",
    "sg:classifiers":[
        {
            "category":"Professional",
            "subcategory":"Computer Services",
            "type":"Services"
        }
    ],
    "sg:postcode":"RG45 7JD",
    "sg:province":"Berkshire",
    "sg:tags":[
        "consultant"
    ],
    "wof:name":"Digica Uc Ltd.",
    "wof:placetype":"venue"
},
  "geometry": {"coordinates":[-0.7944539785,51.3647232056],"type":"Point"}
}