{
  "type": "Feature",
  "properties": {
    "addr:full":"Unit 3, Homefield Road Haverhill Essex CB9 8QP",
    "addr:housenumber":"unit 3",
    "addr:postcode":"cb9 8qp",
    "addr:street":"Homefield Road",
    "iso:country":"GB",
    "sg:address":"Unit 3, Homefield Road",
    "sg:city":"Haverhill",
    "sg:classifiers":[
        {
            "category":"Building & Trades",
            "subcategory":"Construction",
            "type":"Services"
        }
    ],
    "sg:phone":"+44 1440 821440",
    "sg:postcode":"CB9 8QP",
    "sg:province":"Essex",
    "sg:tags":[
        "builder"
    ],
    "wof:name":"Haverhill Insulations",
    "wof:placetype":"venue"
},
  "geometry": {"coordinates":[0.428866,52.073559],"type":"Point"}
}