{
  "type": "Feature",
  "properties": {
    "iso:country":"GB",
    "sg:address":"39 Romney Road",
    "sg:city":"Chatham",
    "sg:classifiers":[
        {
            "category":"Retail",
            "subcategory":"Driving School",
            "type":"Services"
        }
    ],
    "sg:postcode":"ME5 7LU",
    "sg:province":"Kent",
    "wof:name":"Kiran's Driving School",
    "wof:placetype":"venue"
},
  "geometry": {"coordinates":[0.535973,51.349926],"type":"Point"}
}