{
  "type": "Feature",
  "properties": {
    "addr:full":"Unit 2 Highcliffe Industrial Estate, Bruntcliffe Lane Leeds West Yorkshire LS27 9LR",
    "addr:housenumber":"unit 2",
    "addr:postcode":"ls27 9lr",
    "addr:street":"Industrial;Bruntcliffe Lane",
    "iso:country":"GB",
    "sg:address":"Unit 2 Highcliffe Industrial Estate, Bruntcliffe Lane",
    "sg:city":"Leeds",
    "sg:classifiers":[
        {
            "category":"Home & Garden",
            "subcategory":"Building Materials",
            "type":"Retail Goods"
        }
    ],
    "sg:phone":"+44 113 259 7335",
    "sg:postcode":"LS27 9LR",
    "sg:province":"West Yorkshire",
    "sg:tags":[
        "shower",
        "unit"
    ],
    "wof:name":"Just Trays Ltd.",
    "wof:placetype":"venue"
},
  "geometry": {"coordinates":[-1.614013,53.748081],"type":"Point"}
}