{
  "type": "Feature",
  "properties": {
    "addr:full":"5 Lion Centre, Hanworth Trading Estate, Hampton Road West Feltham Greater London TW13 6DS",
    "addr:housenumber":"5",
    "addr:postcode":"tw13 6ds",
    "addr:street":"Lion Centre;Trading;Hampton Road West",
    "iso:country":"GB",
    "sg:address":"5 Lion Centre, Hanworth Trading Estate, Hampton Road West",
    "sg:city":"Feltham",
    "sg:classifiers":[
        {
            "category":"Home & Garden",
            "subcategory":"Kitchen Supply",
            "type":"Retail Goods"
        }
    ],
    "sg:phone":"+44 20 8893 8339",
    "sg:postcode":"TW13 6DS",
    "sg:province":"Greater London",
    "sg:tags":[
        "measuring",
        "scale"
    ],
    "wof:name":"Axis (GB) Ltd",
    "wof:placetype":"venue"
},
  "geometry": {"coordinates":[-0.4092040062,51.4470748901],"type":"Point"}
}