{
  "type": "Feature",
  "properties": {
    "iso:country":"GB",
    "sg:address":"Barge Haybay, Heybridge Basin",
    "sg:city":"Maldon",
    "sg:classifiers":[
        {
            "category":"Government",
            "subcategory":"Office",
            "type":"Public Place"
        }
    ],
    "sg:phone":"+44 1621 891213",
    "sg:postcode":"CM9 4RS",
    "sg:province":"Essex",
    "sg:tags":[
        "local"
    ],
    "wof:name":"Newham Outdoor Education Centre",
    "wof:placetype":"venue"
},
  "geometry": {"coordinates":[0.7082899809,51.7333984375],"type":"Point"}
}