{
  "type": "Feature",
  "properties": {
    "addr:full":"102 Tettenhall Road Wolverhampton Shropshire WV6 0BW",
    "addr:housenumber":"102",
    "addr:postcode":"wv6 0bw",
    "addr:street":"Tettenhall Road",
    "iso:country":"GB",
    "sg:address":"102 Tettenhall Road",
    "sg:city":"Wolverhampton",
    "sg:classifiers":[
        {
            "category":"Building & Trades",
            "subcategory":"Landscaping Services",
            "type":"Services"
        }
    ],
    "sg:phone":"+44 1902 754111",
    "sg:postcode":"WV6 0BW",
    "sg:province":"Shropshire",
    "sg:tags":[
        "horticultural",
        "consultant"
    ],
    "wof:name":"Photostatic Copiers (midlands)",
    "wof:placetype":"venue"
},
  "geometry": {"coordinates":[-2.153102,52.592484],"type":"Point"}
}