{
  "type": "Feature",
  "properties": {
    "iso:country":"GB",
    "sg:address":"St Anns Mills, Commercial Road",
    "sg:city":"Leeds",
    "sg:classifiers":[
        {
            "category":"Retail",
            "subcategory":"Auto Repair",
            "type":"Services"
        }
    ],
    "sg:phone":"+44 113 274 4866",
    "sg:postcode":"LS5 3EA",
    "sg:province":"West Yorkshire",
    "sg:tags":[
        "car",
        "specialist",
        "customizing"
    ],
    "wof:name":"St Anns Tyres",
    "wof:placetype":"venue"
},
  "geometry": {"coordinates":[-1.595209,53.817314],"type":"Point"}
}