{
  "type": "Feature",
  "properties": {
    "addr:full":"Willowbank House, Old Road, Handforth Wilmslow Cheshire SK9 3AZ",
    "addr:postcode":"sk9 3az",
    "addr:street":"Old Road",
    "iso:country":"GB",
    "sg:address":"Willowbank House, Old Road, Handforth",
    "sg:city":"Wilmslow",
    "sg:classifiers":[
        {
            "category":"Professional",
            "subcategory":"Detective & Security Services",
            "type":"Services"
        }
    ],
    "sg:phone":"+44 1625 529999",
    "sg:postcode":"SK9 3AZ",
    "sg:province":"Cheshire",
    "sg:tags":[
        "agency"
    ],
    "wof:name":"Specialised Investigation Services Ltd.",
    "wof:placetype":"venue"
},
  "geometry": {"coordinates":[-2.213559,53.346756],"type":"Point"}
}