{
  "type": "Feature",
  "properties": {
    "addr:full":"Area Education, Ainsty Road Harrogate North Yorkshire HG1 4XU",
    "addr:postcode":"hg1 4xu",
    "addr:street":"Ainsty Road",
    "iso:country":"GB",
    "sg:address":"Area Education, Ainsty Road",
    "sg:city":"Harrogate",
    "sg:classifiers":[
        {
            "category":"Government",
            "subcategory":"Office",
            "type":"Public Place"
        }
    ],
    "sg:phone":"+44 1423 700120",
    "sg:postcode":"HG1 4XU",
    "sg:province":"North Yorkshire",
    "sg:tags":[
        "local",
        "agency",
        "education",
        "authority"
    ],
    "wof:name":"North Yorkshire County Council",
    "wof:placetype":"venue"
},
  "geometry": {"coordinates":[-1.5445239544,53.9946899414],"type":"Point"}
}