{
  "type": "Feature",
  "properties": {
    "iso:country":"GB",
    "sg:address":"Ashton Road",
    "sg:city":"Oldham",
    "sg:classifiers":[
        {
            "category":"Home & Garden",
            "subcategory":"Home Furnishings",
            "type":"Retail Goods"
        }
    ],
    "sg:phone":"+44 161 287 0101",
    "sg:postcode":"OL8 1LD",
    "sg:province":"Lancashire",
    "sg:tags":[
        "furnishers",
        "planner",
        "kitchen"
    ],
    "wof:name":"Hills Interiors Ltd.",
    "wof:placetype":"venue"
},
  "geometry": {"coordinates":[-2.1143438816,53.5321807861],"type":"Point"}
}