{
  "type": "Feature",
  "properties": {
    "iso:country":"GB",
    "sg:address":"8-10 Margaret Street",
    "sg:city":"Immingham",
    "sg:classifiers":[
        {
            "category":"Restaurant",
            "type":"Food & Drink"
        },
        {
            "category":"Food & Beverages",
            "subcategory":"Meat & Fish",
            "type":"Retail Goods"
        }
    ],
    "sg:phone":"+44 1469 572879",
    "sg:postcode":"DN40 1JY",
    "sg:province":"Lincolnshire",
    "sg:tags":[
        "chip"
    ],
    "wof:name":"Winners Fish & Chips",
    "wof:placetype":"venue"
},
  "geometry": {"coordinates":[-0.2158109993,53.6140975952],"type":"Point"}
}