{
  "type": "Feature",
  "properties": {
    "iso:country":"GB",
    "sg:address":"Clent Hills Site, Fieldhouse Lane, Romsley",
    "sg:city":"Halesowen",
    "sg:classifiers":[
        {
            "category":"Recreation",
            "subcategory":"Campground",
            "type":"Entertainment"
        }
    ],
    "sg:phone":"+44 1562 710015",
    "sg:postcode":"B62 0NH",
    "sg:province":"West Midlands",
    "sg:tags":[
        "operator",
        "site",
        "camping"
    ],
    "wof:name":"Camping & Caravanning Club Ltd",
    "wof:placetype":"venue"
},
  "geometry": {"coordinates":[-2.057187,52.415447],"type":"Point"}
}