{
  "type": "Feature",
  "properties": {
    "iso:country":"GB",
    "sg:address":"25 Bernard Street",
    "sg:city":"Edinburgh",
    "sg:classifiers":[
        {
            "category":"Government",
            "subcategory":"Embassy",
            "type":"Public Place"
        }
    ],
    "sg:postcode":"EH6 6SH",
    "sg:province":"City of Edinburgh",
    "sg:tags":[
        "consulate"
    ],
    "wof:name":"Portugese Consulate",
    "wof:placetype":"venue"
},
  "geometry": {"coordinates":[-3.1677689552,55.9757347107],"type":"Point"}
}