{
  "type": "Feature",
  "properties": {
    "iso:country":"GB",
    "sg:address":"53a Market Street",
    "sg:city":"Crewe",
    "sg:classifiers":[
        {
            "category":"Home & Garden",
            "subcategory":"Furniture",
            "type":"Retail Goods"
        }
    ],
    "sg:phone":"+44 1270 255122",
    "sg:postcode":"CW1 2EY",
    "sg:province":"Cheshire",
    "wof:name":"Waldmans",
    "wof:placetype":"venue"
},
  "geometry": {"coordinates":[-2.441277,53.098221],"type":"Point"}
}