{
  "type": "Feature",
  "properties": {
    "iso:country":"GB",
    "sg:address":"Camberley, Church Street, Woodhurst",
    "sg:city":"Huntingdon",
    "sg:classifiers":[
        {
            "category":"Manufacturing",
            "subcategory":"Wood Products",
            "type":"Manufacturing & Wholesale Goods"
        }
    ],
    "sg:postcode":"PE28 3BN",
    "sg:province":"Bedfordshire",
    "sg:tags":[
        "packaging",
        "crate",
        "pallets"
    ],
    "wof:name":"Wright & Co.",
    "wof:placetype":"venue"
},
  "geometry": {"coordinates":[-0.0700900033,52.3670425415],"type":"Point"}
}