{
  "type": "Feature",
  "properties": {
    "iso:country":"GB",
    "sg:address":"66 High Street, Ramsey",
    "sg:city":"Huntingdon",
    "sg:classifiers":[
        {
            "category":"Home & Garden",
            "subcategory":"Carpets & Floor Coverings",
            "type":"Retail Goods"
        }
    ],
    "sg:postcode":"PE26 1AA",
    "sg:province":"Cambridgeshire",
    "sg:tags":[
        "carpets",
        "rug",
        "matting"
    ],
    "wof:name":"Kathy Smith",
    "wof:placetype":"venue"
},
  "geometry": {"coordinates":[-0.106664,52.448368],"type":"Point"}
}