{
  "type": "Feature",
  "properties": {
    "iso:country":"GB",
    "sg:address":"The Banks, Blo Norton",
    "sg:city":"Diss",
    "sg:classifiers":[
        {
            "category":"Farming",
            "subcategory":"Farm",
            "type":"Manufacturing & Wholesale Goods"
        }
    ],
    "sg:phone":"+44 1379 898336",
    "sg:postcode":"IP22 2JJ",
    "sg:province":"Norfolk",
    "sg:tags":[
        "mixed",
        "crop"
    ],
    "wof:name":"B G Flatman",
    "wof:placetype":"venue"
},
  "geometry": {"coordinates":[0.955972,52.375137],"type":"Point"}
}