{
  "type": "Feature",
  "properties": {
    "iso:country":"GB",
    "sg:address":"7 Hallsteads, Dove Holes",
    "sg:city":"Buxton",
    "sg:classifiers":[
        {
            "category":"Autos & Motor Vehicles",
            "subcategory":"Fuel & Gas Station",
            "type":"Retail Goods"
        }
    ],
    "sg:postcode":"SK17 8BL",
    "sg:province":"Derbyshire",
    "sg:tags":[
        "petrol",
        "filling"
    ],
    "wof:name":"Western Front Service Station",
    "wof:placetype":"venue"
},
  "geometry": {"coordinates":[-1.887484,53.299198],"type":"Point"}
}