{
  "type": "Feature",
  "properties": {
    "iso:country":"GB",
    "sg:address":"55 Lake Lock Road, Stanley",
    "sg:city":"Wakefield",
    "sg:classifiers":[
        {
            "category":"Fast Food",
            "type":"Food & Drink"
        },
        {
            "category":"Restaurant",
            "type":"Food & Drink"
        }
    ],
    "sg:phone":"+44 1924 827333",
    "sg:postcode":"WF3 4HP",
    "sg:province":"West Yorkshire",
    "sg:tags":[
        "away",
        "take"
    ],
    "wof:name":"Pizza 55",
    "wof:placetype":"venue"
},
  "geometry": {"coordinates":[-1.47464,53.71463],"type":"Point"}
}