{
  "type": "Feature",
  "properties": {
    "iso:country":"GB",
    "sg:address":"1 Riddrievale Ct",
    "sg:city":"Glasgow",
    "sg:classifiers":[
        {
            "category":"Social Services",
            "type":"Services"
        }
    ],
    "sg:phone":"+44 141 770 9106",
    "sg:postcode":"G33 2RN",
    "sg:province":"Glasgow City",
    "wof:name":"Riddrie Centre The",
    "wof:placetype":"venue"
},
  "geometry": {"coordinates":[-4.1858329773,55.8698310852],"type":"Point"}
}