{
  "type": "Feature",
  "properties": {
    "iso:country":"GB",
    "sg:address":"Sandy Hill Lane, Overstone Road, Moulton",
    "sg:city":"Northampton",
    "sg:classifiers":[
        {
            "category":"Manufacturing",
            "subcategory":"Paper Products",
            "type":"Manufacturing & Wholesale Goods"
        }
    ],
    "sg:phone":"+44 1604 644963",
    "sg:postcode":"NN3 7JB",
    "sg:province":"Northamptonshire",
    "sg:tags":[
        "merchant",
        "waste"
    ],
    "wof:name":"Alibone Recycling Ltd.",
    "wof:placetype":"venue"
},
  "geometry": {"coordinates":[-0.842276,52.290173],"type":"Point"}
}