{
  "type": "Feature",
  "properties": {
    "addr:full":"26a-26b Market Place Bolton Lancashire BL1 2AL",
    "addr:housenumber":"26a-26b",
    "addr:postcode":"bl1 2al",
    "addr:street":"Market Place",
    "iso:country":"GB",
    "sg:address":"26a-26b Market Place",
    "sg:city":"Bolton",
    "sg:classifiers":[
        {
            "category":"Sports & Exercise",
            "subcategory":"Sports Center",
            "type":"Entertainment"
        }
    ],
    "sg:phone":"+44 1204 535277",
    "sg:postcode":"BL1 2AL",
    "sg:province":"Lancashire",
    "sg:tags":[
        "shop",
        "good"
    ],
    "wof:name":"Allsports Retail",
    "wof:placetype":"venue"
},
  "geometry": {"coordinates":[-2.430539,53.581165],"type":"Point"}
}