{
  "type": "Feature",
  "properties": {
    "addr:full":"Advance Bookings & Enquiries, The Linkway, Off Mansell Way Bolton Lancashire BL6 6JL",
    "addr:postcode":"bl6 6jl",
    "addr:street":"The Linkway Off Mansell Way",
    "iso:country":"GB",
    "sg:address":"Advance Bookings & Enquiries, The Linkway, Off Mansell Way",
    "sg:city":"Bolton",
    "sg:classifiers":[
        {
            "category":"Cinema",
            "subcategory":"Movie Theater",
            "type":"Entertainment"
        }
    ],
    "sg:phone":"+44 1204 669668",
    "sg:postcode":"BL6 6JL",
    "sg:province":"Lancashire",
    "wof:name":"Vue Cinemas (U K) Ltd.",
    "wof:placetype":"venue"
},
  "geometry": {"coordinates":[-2.5272099972,53.5828781128],"type":"Point"}
}