{
  "type": "Feature",
  "properties": {
    "iso:country":"GB",
    "sg:address":"57 Potters Hill, Crockerton",
    "sg:city":"Warminster",
    "sg:classifiers":[
        {
            "category":"Building & Trades",
            "subcategory":"Construction",
            "type":"Services"
        }
    ],
    "sg:phone":"+44 1985 846092",
    "sg:postcode":"BA12 8AD",
    "sg:province":"Somerset",
    "sg:tags":[
        "flooring"
    ],
    "wof:name":"Unique Driveways",
    "wof:placetype":"venue"
},
  "geometry": {"coordinates":[-2.202251,51.181911],"type":"Point"}
}