{
  "type": "Feature",
  "properties": {
    "addr:full":"Allenby Road Southall Greater London UB1 2HB",
    "addr:postcode":"ub1 2hb",
    "addr:street":"Allenby Road",
    "iso:country":"GB",
    "sg:address":"Allenby Road",
    "sg:city":"Southall",
    "sg:classifiers":[
        {
            "category":"Bars & Pubs",
            "type":"Food & Drink"
        }
    ],
    "sg:phone":"+44 20 8578 2461",
    "sg:postcode":"UB1 2HB",
    "sg:province":"Greater London",
    "sg:tags":[
        "pubs",
        "inn"
    ],
    "wof:name":"The Lord Allenby",
    "wof:placetype":"venue"
},
  "geometry": {"coordinates":[-0.3674289882,51.5290145874],"type":"Point"}
}