{
  "type": "Feature",
  "properties": {
    "iso:country":"GB",
    "sg:address":"Ash View, Stn Rd, Cumwhinton",
    "sg:city":"Carlisle",
    "sg:classifiers":[
        {
            "category":"Personal",
            "type":"Services"
        }
    ],
    "sg:postcode":"CA4 8DJ",
    "sg:province":"Cumbria",
    "sg:tags":[
        "wedding"
    ],
    "wof:name":"Floral Fantasies",
    "wof:placetype":"venue"
},
  "geometry": {"coordinates":[-2.853275,54.868359],"type":"Point"}
}