{
  "type": "Feature",
  "properties": {
    "addr:full":"1 Woolwich Manor Way East Ham Greater London E6 4NT",
    "addr:housenumber":"1",
    "addr:postcode":"e6 4nt",
    "addr:street":"Woolwich Manor Way",
    "iso:country":"GB",
    "sg:address":"1 Woolwich Manor Way",
    "sg:city":"East Ham",
    "sg:classifiers":[
        {
            "category":"Restaurant",
            "type":"Food & Drink"
        }
    ],
    "sg:phone":"+44 20 7511 3840",
    "sg:postcode":"E6 4NT",
    "sg:province":"Greater London",
    "wof:name":"Windsor House Brewers Fayre & Travel Inn",
    "wof:placetype":"venue"
},
  "geometry": {"coordinates":[0.06247,51.524738],"type":"Point"}
}