{
  "type": "Feature",
  "properties": {
    "addr:full":"Drake House, 2 Drake Road Westcliff-on-sea Essex SS0 8LP",
    "addr:housenumber":"2",
    "addr:postcode":"ss0 8lp",
    "addr:street":"Drake Road",
    "iso:country":"GB",
    "sg:address":"Drake House, 2 Drake Road",
    "sg:city":"Westcliff-on-sea",
    "sg:classifiers":[
        {
            "category":"Professional",
            "subcategory":"Accounting & Tax Preparation",
            "type":"Services"
        }
    ],
    "sg:phone":"+44 1702 345856",
    "sg:postcode":"SS0 8LP",
    "sg:province":"Essex",
    "sg:tags":[
        "accountant"
    ],
    "wof:name":"D E J Hampton",
    "wof:placetype":"venue"
},
  "geometry": {"coordinates":[0.6844720244,51.5418357849],"type":"Point"}
}