{
  "type": "Feature",
  "properties": {
    "iso:country":"GB",
    "sg:address":"118 High Street, Staple Hill",
    "sg:city":"Bristol",
    "sg:classifiers":[
        {
            "category":"Autos & Motor Vehicles",
            "subcategory":"Automobile Sales",
            "type":"Retail Goods"
        }
    ],
    "sg:phone":"+44 117 908 9977",
    "sg:postcode":"BS16 5HH",
    "sg:province":"City of Bristol",
    "sg:tags":[
        "car"
    ],
    "wof:name":"Jaguar Investments (Uk) Ltd.",
    "wof:placetype":"venue"
},
  "geometry": {"coordinates":[-2.515334,51.481468],"type":"Point"}
}