{
  "type": "Feature",
  "properties": {
    "addr:full":"133 Cardigan Road Bridlington East Riding of Yorkshire YO15 3LP",
    "addr:housenumber":"133",
    "addr:postcode":"yo15 3lp",
    "addr:street":"Cardigan Road",
    "iso:country":"GB",
    "sg:address":"133 Cardigan Road",
    "sg:city":"Bridlington",
    "sg:classifiers":[
        {
            "category":"Health Services",
            "subcategory":"Nursing And Care Facility",
            "type":"Services"
        }
    ],
    "sg:postcode":"YO15 3LP",
    "sg:province":"East Riding of Yorkshire",
    "sg:tags":[
        "home"
    ],
    "wof:name":"Belvedere View Nursing Home",
    "wof:placetype":"venue"
},
  "geometry": {"coordinates":[-0.2031150013,54.075012207],"type":"Point"}
}