{
  "type": "Feature",
  "properties": {
    "addr:full":"12 Penfold St, Aylsham Norwich Norfolk NR11 6ET",
    "addr:housenumber":"12",
    "addr:postcode":"nr11 6et",
    "addr:street":"Penfold St;Norwich",
    "iso:country":"GB",
    "sg:address":"12 Penfold St, Aylsham",
    "sg:city":"Norwich",
    "sg:classifiers":[
        {
            "category":"Wholesale",
            "subcategory":"Non-durable Goods",
            "type":"Manufacturing & Wholesale Goods"
        }
    ],
    "sg:postcode":"NR11 6ET",
    "sg:province":"Norfolk",
    "sg:tags":[
        "carry",
        "cash"
    ],
    "wof:name":"Macgregor,G,",
    "wof:placetype":"venue"
},
  "geometry": {"coordinates":[1.250768,52.795071],"type":"Point"}
}