{
  "type": "Feature",
  "properties": {
    "iso:country":"GB",
    "sg:address":"5 Glenrosa Road, Tilehurst",
    "sg:city":"Reading",
    "sg:classifiers":[
        {
            "category":"Personal",
            "subcategory":"Hair Removal",
            "type":"Services"
        }
    ],
    "sg:postcode":"RG30 6AN",
    "sg:province":"Berkshire",
    "sg:tags":[
        "electrolysis"
    ],
    "wof:name":"Cecilla Bryant",
    "wof:placetype":"venue"
},
  "geometry": {"coordinates":[-1.022402,51.460449],"type":"Point"}
}