{
  "type": "Feature",
  "properties": {
    "addr:full":"39-41 High Street Northwich Cheshire CW9 5BE",
    "addr:housenumber":"39-41",
    "addr:postcode":"cw9 5be",
    "addr:street":"High Street",
    "iso:country":"GB",
    "sg:address":"39-41 High Street",
    "sg:city":"Northwich",
    "sg:classifiers":[
        {
            "category":"Fast Food",
            "type":"Food & Drink"
        }
    ],
    "sg:phone":"+44 1606 49611",
    "sg:postcode":"CW9 5BE",
    "sg:province":"Cheshire",
    "sg:tags":[
        "away",
        "take"
    ],
    "wof:name":"McDonalds Restaurants Ltd.",
    "wof:placetype":"venue"
},
  "geometry": {"coordinates":[-2.515117,53.26149],"type":"Point"}
}