{
  "type": "Feature",
  "properties": {
    "addr:full":"17 Swakeleys Rd Uxbridge Greater London UB10 8DF",
    "addr:housenumber":"17",
    "addr:postcode":"ub10 8df",
    "addr:street":"Swakeleys Rd",
    "iso:country":"GB",
    "sg:address":"17 Swakeleys Rd",
    "sg:city":"Uxbridge",
    "sg:classifiers":[
        {
            "category":"Food & Beverages",
            "subcategory":"Groceries & Convenience Stores",
            "type":"Retail Goods"
        }
    ],
    "sg:phone":"+44 1895 632116",
    "sg:postcode":"UB10 8DF",
    "sg:province":"Greater London",
    "wof:name":"Rusts",
    "wof:placetype":"venue"
},
  "geometry": {"coordinates":[-0.4450519979,51.5645828247],"type":"Point"}
}