{
  "type": "Feature",
  "properties": {
    "iso:country":"GB",
    "sg:address":"Unit 656, Thorp Arch Trading Estate, Thorp Arch",
    "sg:city":"Wetherby",
    "sg:classifiers":[
        {
            "category":"Building & Trades",
            "subcategory":"Construction",
            "type":"Services"
        }
    ],
    "sg:phone":"+44 1937 843072",
    "sg:postcode":"LS23 7BJ",
    "sg:province":"West Yorkshire",
    "sg:tags":[
        "joinery",
        "carpentry"
    ],
    "sg:website":"http://www.longwood-joinery.co.uk",
    "wof:name":"Longwood Joinery Ltd.",
    "wof:placetype":"venue"
},
  "geometry": {"coordinates":[-1.312009,53.915031],"type":"Point"}
}