{
  "type": "Feature",
  "properties": {
    "addr:full":"Bircholt Road Maidstone Kent ME15 9XH",
    "addr:postcode":"me15 9xh",
    "addr:street":"Bircholt Road",
    "iso:country":"GB",
    "sg:address":"Bircholt Road",
    "sg:city":"Maidstone",
    "sg:classifiers":[
        {
            "category":"Professional",
            "subcategory":"Engineering",
            "type":"Services"
        }
    ],
    "sg:phone":"+44 1622 352410",
    "sg:postcode":"ME15 9XH",
    "sg:province":"Kent",
    "sg:tags":[
        "contractor",
        "electrical",
        "engineer"
    ],
    "wof:name":"Seeboard Plc",
    "wof:placetype":"venue"
},
  "geometry": {"coordinates":[0.5634350181,51.2391395569],"type":"Point"}
}