{
  "type": "Feature",
  "properties": {
    "iso:country":"GB",
    "sg:address":"6 Ranmore Path",
    "sg:city":"Orpington",
    "sg:classifiers":[
        {
            "category":"Personal",
            "subcategory":"Beauty Salon",
            "type":"Services"
        }
    ],
    "sg:phone":"+44 1689 826247",
    "sg:postcode":"BR5 2HP",
    "sg:province":"Kent",
    "sg:tags":[
        "lady",
        "hairdresser"
    ],
    "wof:name":"Giggles",
    "wof:placetype":"venue"
},
  "geometry": {"coordinates":[0.098306,51.393997],"type":"Point"}
}