{
  "type": "Feature",
  "properties": {
    "addr:full":"2nd Floor Scottish Provident House, 76-80 College Road Harrow Greater London HA1 1BQ",
    "addr:housenumber":"2nd floor scottish;76-80",
    "addr:postcode":"ha1 1bq",
    "addr:street":"College Road",
    "iso:country":"GB",
    "sg:address":"2nd Floor Scottish Provident House, 76-80 College Road",
    "sg:city":"Harrow",
    "sg:classifiers":[
        {
            "category":"Professional",
            "subcategory":"Business Services",
            "type":"Services"
        }
    ],
    "sg:phone":"+44 20 8861 5888",
    "sg:postcode":"HA1 1BQ",
    "sg:province":"Greater London",
    "sg:tags":[
        "broker",
        "commodity"
    ],
    "wof:name":"Euro Equity (U K) Ltd.",
    "wof:placetype":"venue"
},
  "geometry": {"coordinates":[-0.33860901,51.5801773071],"type":"Point"}
}