{
  "type": "Feature",
  "properties": {
    "iso:country":"GB",
    "sg:address":"84 Henley Road",
    "sg:city":"Ipswich",
    "sg:classifiers":[
        {
            "category":"Government",
            "subcategory":"Post Office",
            "type":"Public Place"
        }
    ],
    "sg:postcode":"IP1 4NQ",
    "sg:province":"Suffolk",
    "sg:tags":[
        "organisation",
        "soc",
        "research"
    ],
    "wof:name":"Nirmal Consultancy Ltd.",
    "wof:placetype":"venue"
},
  "geometry": {"coordinates":[1.151978,52.071751],"type":"Point"}
}