{
  "type": "Feature",
  "properties": {
    "addr:full":"45 Marlborough Road Mansfield Derbyshire NG19 6DY",
    "addr:housenumber":"45",
    "addr:postcode":"ng19 6dy",
    "addr:street":"Marlborough Road",
    "iso:country":"GB",
    "sg:address":"45 Marlborough Road",
    "sg:city":"Mansfield",
    "sg:classifiers":[
        {
            "category":"Freight",
            "type":"Transportation"
        }
    ],
    "sg:postcode":"NG19 6DY",
    "sg:province":"Derbyshire",
    "sg:tags":[
        "haulage",
        "road"
    ],
    "wof:name":"Phil Sprigg",
    "wof:placetype":"venue"
},
  "geometry": {"coordinates":[-1.2130759954,53.1529769897],"type":"Point"}
}