{
  "type": "Feature",
  "properties": {
    "addr:full":"Warner St Accrington Lancashire BB5 1HN",
    "addr:postcode":"bb5 1hn",
    "addr:street":"Warner St",
    "iso:country":"GB",
    "sg:address":"Warner St",
    "sg:city":"Accrington",
    "sg:classifiers":[
        {
            "category":"Bars & Pubs",
            "type":"Food & Drink"
        }
    ],
    "sg:phone":"+44 1254 386536",
    "sg:postcode":"BB5 1HN",
    "sg:province":"Lancashire",
    "sg:tags":[
        "pubs",
        "inn"
    ],
    "wof:name":"Arcade Bar",
    "wof:placetype":"venue"
},
  "geometry": {"coordinates":[-2.362094,53.752087],"type":"Point"}
}