{
  "type": "Feature",
  "properties": {
    "iso:country":"GB",
    "sg:address":"36 Firth Park Road",
    "sg:city":"Sheffield",
    "sg:classifiers":[
        {
            "category":"Professional",
            "subcategory":"Lawyer & Legal Services",
            "type":"Services"
        }
    ],
    "sg:postcode":"S5 6WN",
    "sg:province":"South Yorkshire",
    "sg:tags":[
        "solicitor"
    ],
    "wof:name":"Wheeler Williams",
    "wof:placetype":"venue"
},
  "geometry": {"coordinates":[-1.450955987,53.4076728821],"type":"Point"}
}