{
  "type": "Feature",
  "properties": {
    "addr:full":"Greenways, Beeches Road, Farnham Common Slough Berkshire SL2 3PR",
    "addr:postcode":"sl2 3pr",
    "addr:street":"Beeches Road",
    "iso:country":"GB",
    "sg:address":"Greenways, Beeches Road, Farnham Common",
    "sg:city":"Slough",
    "sg:classifiers":[
        {
            "category":"Building & Trades",
            "subcategory":"Construction",
            "type":"Services"
        }
    ],
    "sg:phone":"+44 1753 643374",
    "sg:postcode":"SL2 3PR",
    "sg:province":"Berkshire",
    "sg:tags":[
        "builder"
    ],
    "wof:name":"Riteway Builders",
    "wof:placetype":"venue"
},
  "geometry": {"coordinates":[-0.6153190136,51.5570297241],"type":"Point"}
}