{
  "type": "Feature",
  "properties": {
    "addr:full":"157 High Street Cinderford Gloucestershire GL14 2TF",
    "addr:housenumber":"157",
    "addr:postcode":"gl14 2tf",
    "addr:street":"High Street",
    "iso:country":"GB",
    "sg:address":"157 High Street",
    "sg:city":"Cinderford",
    "sg:classifiers":[
        {
            "category":"Autos & Motor Vehicles",
            "subcategory":"Automobile Sales",
            "type":"Retail Goods"
        },
        {
            "category":"Retail",
            "subcategory":"Auto Repair",
            "type":"Services"
        }
    ],
    "sg:phone":"+44 1594 824747",
    "sg:postcode":"GL14 2TF",
    "sg:province":"Gloucestershire",
    "sg:tags":[
        "modification",
        "car",
        "related",
        "garage"
    ],
    "wof:name":"P & J Loveridge",
    "wof:placetype":"venue"
},
  "geometry": {"coordinates":[-2.504586935,51.8300628662],"type":"Point"}
}