{
  "type": "Feature",
  "properties": {
    "iso:country":"GB",
    "sg:address":"34 Guildhall Street",
    "sg:city":"Folkestone",
    "sg:classifiers":[
        {
            "category":"Retail",
            "subcategory":"Repair Shop",
            "type":"Services"
        },
        {
            "category":"Communications",
            "type":"Services"
        }
    ],
    "sg:phone":"+44 1303 255688",
    "sg:postcode":"CT20 1DZ",
    "sg:province":"Kent",
    "sg:tags":[
        "television",
        "good",
        "tv",
        "video",
        "servicing",
        "maintenance",
        "radio"
    ],
    "wof:name":"Halksworth Wheeler Ltd",
    "wof:placetype":"venue"
},
  "geometry": {"coordinates":[1.17604,51.083721],"type":"Point"}
}