{
  "type": "Feature",
  "properties": {
    "addr:full":"3b Park Place Leeds West Yorkshire LS1 2RU",
    "addr:housenumber":"3b",
    "addr:postcode":"ls1 2ru",
    "addr:street":"Park Place",
    "iso:country":"GB",
    "sg:address":"3b Park Place",
    "sg:city":"Leeds",
    "sg:classifiers":[
        {
            "category":"Professional",
            "subcategory":"Employment Agencies",
            "type":"Services"
        }
    ],
    "sg:phone":"+44 113 383 3033",
    "sg:postcode":"LS1 2RU",
    "sg:province":"West Yorkshire",
    "sg:tags":[
        "consultant"
    ],
    "wof:name":"Horizon Recruitment Plc",
    "wof:placetype":"venue"
},
  "geometry": {"coordinates":[-1.550628,53.797577],"type":"Point"}
}