{
  "type": "Feature",
  "properties": {
    "addr:full":"140 Southwark Street Southwark Greater London SE1 0SW",
    "addr:housenumber":"140",
    "addr:postcode":"se1 0sw",
    "addr:street":"Southwark Street",
    "iso:country":"GB",
    "sg:address":"140 Southwark Street",
    "sg:city":"Southwark",
    "sg:classifiers":[
        {
            "category":"Real Estate",
            "subcategory":"Architect",
            "type":"Services"
        }
    ],
    "sg:postcode":"SE1 0SW",
    "sg:province":"Greater London",
    "wof:name":"Kindlehurst Ltd",
    "wof:placetype":"venue"
},
  "geometry": {"coordinates":[-0.1020630002,51.5064048767],"type":"Point"}
}