{
  "type": "Feature",
  "properties": {
    "addr:full":"29 Cimla Crescent Neath Neath Port Talbot SA11 3NN",
    "addr:housenumber":"29",
    "addr:postcode":"sa11 3nn",
    "addr:street":"Cimla Crescent",
    "iso:country":"GB",
    "sg:address":"29 Cimla Crescent",
    "sg:city":"Neath",
    "sg:classifiers":[
        {
            "category":"Building & Trades",
            "subcategory":"Construction",
            "type":"Services"
        }
    ],
    "sg:postcode":"SA11 3NN",
    "sg:province":"Neath Port Talbot",
    "sg:tags":[
        "contractor",
        "pool",
        "swimming"
    ],
    "wof:name":"Measday Pool Services Ltd.",
    "wof:placetype":"venue"
},
  "geometry": {"coordinates":[-3.7942869663,51.6576957703],"type":"Point"}
}