{
  "type": "Feature",
  "properties": {
    "addr:full":"7-13 Alum Rock Road Birmingham West Midlands B8 1LL",
    "addr:housenumber":"7-13",
    "addr:postcode":"b8 1ll",
    "addr:street":"Alum Rock Road",
    "iso:country":"GB",
    "sg:address":"7-13 Alum Rock Road",
    "sg:city":"Birmingham",
    "sg:classifiers":[
        {
            "category":"Food & Beverages",
            "subcategory":"Fruits & Vegetables",
            "type":"Retail Goods"
        }
    ],
    "sg:phone":"+44 121 327 2250",
    "sg:postcode":"B8 1LL",
    "sg:province":"West Midlands",
    "sg:tags":[
        "greengrocer"
    ],
    "wof:name":"P Dent Meats",
    "wof:placetype":"venue"
},
  "geometry": {"coordinates":[-1.859236002,52.4914512634],"type":"Point"}
}