{
  "type": "Feature",
  "properties": {
    "addr:full":"60-61 Middle St South Driffield East Riding of Yorkshire YO25 6PH",
    "addr:housenumber":"60-61",
    "addr:postcode":"yo25 6ph",
    "addr:street":"Middle St South",
    "iso:country":"GB",
    "sg:address":"60-61 Middle St South",
    "sg:city":"Driffield",
    "sg:classifiers":[
        {
            "category":"Food & Beverages",
            "subcategory":"Bakery",
            "type":"Retail Goods"
        }
    ],
    "sg:phone":"+44 1377 241766",
    "sg:postcode":"YO25 6PH",
    "sg:province":"East Riding of Yorkshire",
    "sg:tags":[
        "baker"
    ],
    "wof:name":"Woodhead (Scarborough) Ltd.",
    "wof:placetype":"venue"
},
  "geometry": {"coordinates":[-0.441858,54.008041],"type":"Point"}
}