{
  "type": "Feature",
  "properties": {
    "iso:country":"GB",
    "sg:address":"430 Tonbridge Road",
    "sg:city":"Maidstone",
    "sg:classifiers":[
        {
            "category":"Professional",
            "type":"Services"
        }
    ],
    "sg:phone":"+44 1622 727777",
    "sg:postcode":"ME16 9LW",
    "sg:province":"Kent",
    "sg:tags":[
        "entertainer"
    ],
    "wof:name":"Castle Capers",
    "wof:placetype":"venue"
},
  "geometry": {"coordinates":[0.4842489958,51.266456604],"type":"Point"}
}