{
  "type": "Feature",
  "properties": {
    "iso:country":"GB",
    "sg:address":"Unit 5 Lon Parcwr Industrial Estate",
    "sg:city":"Ruthin",
    "sg:classifiers":[
        {
            "category":"Home & Garden",
            "subcategory":"Hardware",
            "type":"Retail Goods"
        }
    ],
    "sg:postcode":"LL15 1NJ",
    "sg:province":"Denbighshire",
    "sg:tags":[
        "retailer",
        "diy"
    ],
    "wof:name":"Ruthin Decor Centre",
    "wof:placetype":"venue"
},
  "geometry": {"coordinates":[-3.312096,53.121628],"type":"Point"}
}