{
  "type": "Feature",
  "properties": {
    "addr:full":"6 First Floor Offices Hereford Herefordshire HR4 9HX",
    "addr:housenumber":"6 first",
    "addr:postcode":"hr4 9hx",
    "iso:country":"GB",
    "sg:address":"6 First Floor Offices",
    "sg:city":"Hereford",
    "sg:classifiers":[
        {
            "category":"Military Area",
            "subcategory":"Air Force Base",
            "type":"Public Place"
        }
    ],
    "sg:postcode":"HR4 9HX",
    "sg:province":"Herefordshire",
    "sg:tags":[
        "taxi",
        "hire",
        "private"
    ],
    "wof:name":"A & B Private Hire",
    "wof:placetype":"venue"
},
  "geometry": {"coordinates":[-2.7317609787,52.0592041016],"type":"Point"}
}