{
  "type": "Feature",
  "properties": {
    "iso:country":"GB",
    "sg:address":"62 New Road",
    "sg:city":"Rotherham",
    "sg:classifiers":[
        {
            "category":"Retail",
            "subcategory":"Repair Shop",
            "type":"Services"
        }
    ],
    "sg:phone":"+44 1709 555790",
    "sg:postcode":"S61 2DU",
    "sg:province":"South Yorkshire",
    "sg:tags":[
        "plant",
        "machinery"
    ],
    "wof:name":"Fox's Painting Services",
    "wof:placetype":"venue"
},
  "geometry": {"coordinates":[-1.415962,53.425941],"type":"Point"}
}