{
  "type": "Feature",
  "properties": {
    "iso:country":"GB",
    "sg:address":"274 Manchester Road, Lostock Gralam",
    "sg:city":"Northwich",
    "sg:classifiers":[
        {
            "category":"Food & Beverages",
            "subcategory":"Meat & Fish",
            "type":"Retail Goods"
        }
    ],
    "sg:phone":"+44 1606 43579",
    "sg:postcode":"CW9 7PL",
    "sg:province":"Cheshire",
    "sg:tags":[
        "chip"
    ],
    "wof:name":"Wing Sing",
    "wof:placetype":"venue"
},
  "geometry": {"coordinates":[-2.466025,53.270344],"type":"Point"}
}