{
  "type": "Feature",
  "properties": {
    "addr:full":"1 Middle St, Watton Thetford Norfolk IP25 6AG",
    "addr:housenumber":"1",
    "addr:postcode":"ip25 6ag",
    "addr:street":"Middle St Watton",
    "iso:country":"GB",
    "sg:address":"1 Middle St, Watton",
    "sg:city":"Thetford",
    "sg:classifiers":[
        {
            "category":"Bars & Pubs",
            "type":"Food & Drink"
        }
    ],
    "sg:phone":"+44 1953 881863",
    "sg:postcode":"IP25 6AG",
    "sg:province":"Norfolk",
    "sg:tags":[
        "pubs",
        "inn"
    ],
    "wof:name":"Kings Arms",
    "wof:placetype":"venue"
},
  "geometry": {"coordinates":[0.82555902,52.5715255737],"type":"Point"}
}