{
  "type": "Feature",
  "properties": {
    "iso:country":"GB",
    "sg:address":"19 Imperial Rd",
    "sg:city":"Billingham",
    "sg:classifiers":[
        {
            "category":"Professional",
            "subcategory":"Detective & Security Services",
            "type":"Services"
        }
    ],
    "sg:phone":"+44 1642 801555",
    "sg:postcode":"TS23 1DW",
    "sg:province":"Durham",
    "wof:name":"Corporate Security International",
    "wof:placetype":"venue"
},
  "geometry": {"coordinates":[-1.290496,54.587658],"type":"Point"}
}