{
  "type": "Feature",
  "properties": {
    "iso:country":"GB",
    "sg:address":"15 Finnick Glen",
    "sg:city":"Ayr",
    "sg:classifiers":[
        {
            "category":"Building & Trades",
            "subcategory":"Construction",
            "type":"Services"
        }
    ],
    "sg:phone":"+44 1292 441832",
    "sg:postcode":"KA7 4RF",
    "sg:province":"South Ayrshire",
    "sg:tags":[
        "decorator",
        "painter"
    ],
    "wof:name":"W A Hainey",
    "wof:placetype":"venue"
},
  "geometry": {"coordinates":[-4.638993,55.429684],"type":"Point"}
}