{
  "type": "Feature",
  "properties": {
    "iso:country":"GB",
    "sg:address":"7 Jane Street",
    "sg:city":"Edinburgh",
    "sg:classifiers":[
        {
            "category":"Retail",
            "subcategory":"Auto Repair",
            "type":"Services"
        }
    ],
    "sg:phone":"+44 131 553 2588",
    "sg:postcode":"EH6 5HE",
    "sg:province":"City of Edinburgh",
    "sg:tags":[
        "body",
        "car",
        "repairer"
    ],
    "wof:name":"K & E Coachworks",
    "wof:placetype":"venue"
},
  "geometry": {"coordinates":[-3.174854,55.969677],"type":"Point"}
}