{
  "type": "Feature",
  "properties": {
    "addr:full":"71 Park Lane Macclesfield Cheshire SK11 6TX",
    "addr:housenumber":"71",
    "addr:postcode":"sk11 6tx",
    "addr:street":"Park Lane",
    "iso:country":"GB",
    "sg:address":"71 Park Lane",
    "sg:city":"Macclesfield",
    "sg:classifiers":[
        {
            "category":"Building & Trades",
            "subcategory":"Construction",
            "type":"Services"
        }
    ],
    "sg:phone":"+44 1625 615381",
    "sg:postcode":"SK11 6TX",
    "sg:province":"Cheshire",
    "sg:tags":[
        "builder"
    ],
    "wof:name":"Chic Home Improvements",
    "wof:placetype":"venue"
},
  "geometry": {"coordinates":[-2.125419,53.254959],"type":"Point"}
}