{
  "type": "Feature",
  "properties": {
    "iso:country":"GB",
    "sg:address":"49 Main Street, Hornby",
    "sg:city":"Lancaster",
    "sg:classifiers":[
        {
            "category":"Travel",
            "subcategory":"Hotels & Motels",
            "type":"Entertainment"
        }
    ],
    "sg:postcode":"LA2 8JT",
    "sg:province":"Lancashire",
    "wof:name":"CASTLE HOTEL",
    "wof:placetype":"venue"
},
  "geometry": {"coordinates":[-2.63702,54.11179],"type":"Point"}
}