{
  "type": "Feature",
  "properties": {
    "addr:full":"12 West Cornwall Entrprse Cntre, Cardrew Industrial Estate Redruth Cornwall TR15 1ST",
    "addr:housenumber":"12",
    "addr:postcode":"tr15 1st",
    "addr:street":"West Cornwall;Cntre;Industrial Estate",
    "iso:country":"GB",
    "sg:address":"12 West Cornwall Entrprse Cntre, Cardrew Industrial Estate",
    "sg:city":"Redruth",
    "sg:classifiers":[
        {
            "category":"Military Area",
            "subcategory":"Air Force Base",
            "type":"Public Place"
        }
    ],
    "sg:phone":"+44 1209 216677",
    "sg:postcode":"TR15 1ST",
    "sg:province":"Cornwall",
    "sg:tags":[
        "taxi",
        "hire",
        "private"
    ],
    "wof:name":"Jims Cabs (Redruth)",
    "wof:placetype":"venue"
},
  "geometry": {"coordinates":[-5.2113142014,50.2449264526],"type":"Point"}
}