{
  "type": "Feature",
  "properties": {
    "addr:full":"No 6 Watling Close, Sketchley Meadows Business Park Hinckley Leicestershire LE10 3EZ",
    "addr:postcode":"le10 3ez",
    "addr:street":"Watling Close Sketchley Meadows Business Park",
    "iso:country":"GB",
    "sg:address":"No 6 Watling Close, Sketchley Meadows Business Park",
    "sg:city":"Hinckley",
    "sg:classifiers":[
        {
            "category":"Professional",
            "subcategory":"Art Services",
            "type":"Services"
        },
        {
            "category":"Professional",
            "subcategory":"Computer Services",
            "type":"Services"
        }
    ],
    "sg:phone":"+44 1455 890005",
    "sg:postcode":"LE10 3EZ",
    "sg:province":"Leicestershire",
    "sg:tags":[
        "stationery",
        "consultant",
        "design"
    ],
    "wof:name":"Custom Forms Ltd.",
    "wof:placetype":"venue"
},
  "geometry": {"coordinates":[-1.372754,52.542439],"type":"Point"}
}