{
  "type": "Feature",
  "properties": {
    "iso:country":"GB",
    "sg:address":"Unit 4 The Pyramid Centre, Airport Service Road",
    "sg:city":"Portsmouth",
    "sg:classifiers":[
        {
            "category":"Manufacturing",
            "subcategory":"Tools & Machinery",
            "type":"Manufacturing & Wholesale Goods"
        }
    ],
    "sg:phone":"+44 23 9265 3553",
    "sg:postcode":"PO3 5SH",
    "sg:province":"Hampshire",
    "sg:tags":[
        "design",
        "maker"
    ],
    "wof:name":"Printed Circuit Board Tooling Ltd.",
    "wof:placetype":"venue"
},
  "geometry": {"coordinates":[-1.04983,50.822689],"type":"Point"}
}