{
  "type": "Feature",
  "properties": {
    "addr:full":"Central Square Workington Cumbria CA14 3BL",
    "addr:postcode":"ca14 3bl",
    "addr:street":"Square Workington",
    "iso:country":"GB",
    "sg:address":"Central Square",
    "sg:city":"Workington",
    "sg:classifiers":[
        {
            "category":"Professional",
            "subcategory":"Employment Agencies",
            "type":"Services"
        }
    ],
    "sg:phone":"+44 1900 323800",
    "sg:postcode":"CA14 3BL",
    "sg:province":"Cumbria",
    "sg:tags":[
        "consultant"
    ],
    "wof:name":"Employment Service Jobcentre",
    "wof:placetype":"venue"
},
  "geometry": {"coordinates":[-3.546567,54.642685],"type":"Point"}
}