{
  "type": "Feature",
  "properties": {
    "addr:full":"234a Blackfen Rd Sidcup Kent DA15 8PW",
    "addr:housenumber":"234a",
    "addr:postcode":"da15 8pw",
    "addr:street":"Blackfen Rd",
    "iso:country":"GB",
    "sg:address":"234a Blackfen Rd",
    "sg:city":"Sidcup",
    "sg:classifiers":[
        {
            "category":"Government",
            "subcategory":"Post Office",
            "type":"Public Place"
        }
    ],
    "sg:phone":"+44 20 8294 1777",
    "sg:postcode":"DA15 8PW",
    "sg:province":"Kent",
    "sg:tags":[
        "messenger",
        "courier"
    ],
    "wof:name":"Avanti Couriers",
    "wof:placetype":"venue"
},
  "geometry": {"coordinates":[0.101046,51.450752],"type":"Point"}
}