{
  "type": "Feature",
  "properties": {
    "addr:full":"Crompton Pla, Centurion Business Park, Alfreton Road Derby Derbyshire DE21 4AY",
    "addr:postcode":"de21 4ay",
    "addr:street":"Pla Centurion Business Park Alfreton Road",
    "iso:country":"GB",
    "sg:address":"Crompton Pla, Centurion Business Park, Alfreton Road",
    "sg:city":"Derby",
    "sg:classifiers":[
        {
            "category":"Home & Garden",
            "subcategory":"Hardware",
            "type":"Retail Goods"
        }
    ],
    "sg:phone":"+44 1332 207222",
    "sg:postcode":"DE21 4AY",
    "sg:province":"Derbyshire",
    "sg:tags":[
        "merchant",
        "fixing",
        "nuts",
        "ironmonger",
        "bolt"
    ],
    "wof:name":"Raygar Architectural & Engineering Supplies Ltd.",
    "wof:placetype":"venue"
},
  "geometry": {"coordinates":[-1.469414,52.937401],"type":"Point"}
}