{
  "type": "Feature",
  "properties": {
    "addr:full":"Unit A, Coombs Rd Halesowen West Midlands B62 8AA",
    "addr:housenumber":"unit a",
    "addr:postcode":"b62 8aa",
    "addr:street":"Coombs Rd",
    "iso:country":"GB",
    "sg:address":"Unit A, Coombs Rd",
    "sg:city":"Halesowen",
    "sg:classifiers":[
        {
            "category":"Home & Garden",
            "subcategory":"Hardware",
            "type":"Retail Goods"
        }
    ],
    "sg:phone":"+44 121 550 2641",
    "sg:postcode":"B62 8AA",
    "sg:province":"West Midlands",
    "sg:tags":[
        "tarpaulin"
    ],
    "wof:name":"One Stop",
    "wof:placetype":"venue"
},
  "geometry": {"coordinates":[-2.047289,52.466824],"type":"Point"}
}