{
  "type": "Feature",
  "properties": {
    "addr:full":"C/o Sanderson Group Ltd, Newater House 11 Newhall Street Birmingham West Midlands B3 3NY",
    "addr:housenumber":"/ o;newater;11",
    "addr:postcode":"b3 3ny",
    "addr:street":"C;Newhall Street",
    "iso:country":"GB",
    "sg:address":"C/o Sanderson Group Ltd, Newater House 11 Newhall Street",
    "sg:city":"Birmingham",
    "sg:classifiers":[
        {
            "category":"Professional",
            "subcategory":"Computer Services",
            "type":"Services"
        }
    ],
    "sg:postcode":"B3 3NY",
    "sg:province":"West Midlands",
    "sg:tags":[
        "system",
        "software"
    ],
    "wof:name":"Commercial Systems Ltd",
    "wof:placetype":"venue"
},
  "geometry": {"coordinates":[-1.9017330408,52.4814224243],"type":"Point"}
}