{
  "type": "Feature",
  "properties": {
    "addr:full":"660 Great Cambridge Rd Enfield Greater London EN1 3SU",
    "addr:housenumber":"660",
    "addr:postcode":"en1 3su",
    "addr:street":"Great Cambridge Rd",
    "iso:country":"GB",
    "sg:address":"660 Great Cambridge Rd",
    "sg:city":"Enfield",
    "sg:classifiers":[
        {
            "category":"Retail",
            "subcategory":"Auto Repair",
            "type":"Services"
        }
    ],
    "sg:phone":"+44 20 8364 5758",
    "sg:postcode":"EN1 3SU",
    "sg:province":"Greater London",
    "sg:tags":[
        "modification",
        "garage"
    ],
    "wof:name":"German Car Care Centre",
    "wof:placetype":"venue"
},
  "geometry": {"coordinates":[-0.0592710003,51.6556167603],"type":"Point"}
}