{
  "type": "Feature",
  "properties": {
    "iso:country":"GB",
    "sg:address":"478-486 Old Kent Rd",
    "sg:city":"Southwark",
    "sg:classifiers":[
        {
            "category":"Communications",
            "type":"Services"
        }
    ],
    "sg:phone":"+44 20 7232 0547",
    "sg:postcode":"SE1 5AG",
    "sg:province":"Greater London",
    "sg:tags":[
        "tv",
        "video",
        "radio"
    ],
    "wof:name":"Supertel",
    "wof:placetype":"venue"
},
  "geometry": {"coordinates":[-0.0701029971,51.4853096008],"type":"Point"}
}