{
  "type": "Feature",
  "properties": {
    "iso:country":"GB",
    "sg:address":"57-59 Waller St",
    "sg:city":"Hull",
    "sg:classifiers":[
        {
            "category":"Building & Trades",
            "subcategory":"Construction",
            "type":"Services"
        }
    ],
    "sg:phone":"+44 1482 227155",
    "sg:postcode":"HU9 2AH",
    "sg:province":"East Riding of Yorkshire",
    "sg:tags":[
        "decorator",
        "painter"
    ],
    "wof:name":"W A Decorators",
    "wof:placetype":"venue"
},
  "geometry": {"coordinates":[-0.313954,53.751003],"type":"Point"}
}