{
  "type": "Feature",
  "properties": {
    "addr:full":"Coxmoor Road Sutton-in-ashfield Nottinghamshire NG17 5LA",
    "addr:postcode":"ng17 5la",
    "addr:street":"Coxmoor Road",
    "iso:country":"GB",
    "sg:address":"Coxmoor Road",
    "sg:city":"Sutton-in-ashfield",
    "sg:classifiers":[
        {
            "category":"Manufacturing",
            "subcategory":"Textiles",
            "type":"Manufacturing & Wholesale Goods"
        }
    ],
    "sg:phone":"+44 1623 555222",
    "sg:postcode":"NG17 5LA",
    "sg:province":"Nottinghamshire",
    "sg:tags":[
        "knitwear"
    ],
    "wof:name":"Coats Viyella Knitwear",
    "wof:placetype":"venue"
},
  "geometry": {"coordinates":[-1.238888979,53.1262054443],"type":"Point"}
}