{
  "type": "Feature",
  "properties": {
    "iso:country":"GB",
    "sg:address":"Unit 1, Vernon Drive, Battlefield Enterprise Park",
    "sg:city":"Shrewsbury",
    "sg:classifiers":[
        {
            "category":"Retail",
            "subcategory":"Auto Repair",
            "type":"Services"
        }
    ],
    "sg:phone":"+44 1743 463680",
    "sg:postcode":"SY1 3TF",
    "sg:province":"Shropshire",
    "sg:tags":[
        "modification",
        "garage"
    ],
    "wof:name":"W R Motors",
    "wof:placetype":"venue"
},
  "geometry": {"coordinates":[-2.737214,52.744801],"type":"Point"}
}