{
  "type": "Feature",
  "properties": {
    "addr:full":"Ridgacre Stores, 266 Ridgeacre Road Birmingham West Midlands B32 1JR",
    "addr:housenumber":"266",
    "addr:postcode":"b32 1jr",
    "addr:street":"Ridgeacre Road",
    "iso:country":"GB",
    "sg:address":"Ridgacre Stores, 266 Ridgeacre Road",
    "sg:city":"Birmingham",
    "sg:classifiers":[
        {
            "category":"Food & Beverages",
            "subcategory":"Liquor & Beverages",
            "type":"Retail Goods"
        }
    ],
    "sg:phone":"+44 121 423 1130",
    "sg:postcode":"B32 1JR",
    "sg:province":"West Midlands",
    "sg:tags":[
        "beer",
        "spirit",
        "wines"
    ],
    "wof:name":"Victoria Wine",
    "wof:placetype":"venue"
},
  "geometry": {"coordinates":[-1.99609,52.459671],"type":"Point"}
}