{
  "type": "Feature",
  "properties": {
    "addr:full":"57 Stoke Newington High Street London Greater London N16 8EL",
    "addr:housenumber":"57",
    "addr:postcode":"n16 8el",
    "addr:street":"Stoke Newington High Street",
    "iso:country":"GB",
    "sg:address":"57 Stoke Newington High Street",
    "sg:city":"London",
    "sg:classifiers":[
        {
            "category":"Personal",
            "subcategory":"Beauty Salon",
            "type":"Services"
        }
    ],
    "sg:postcode":"N16 8EL",
    "sg:province":"Greater London",
    "sg:tags":[
        "unisex",
        "hairdresser"
    ],
    "wof:name":"Hairbase Plus",
    "wof:placetype":"venue"
},
  "geometry": {"coordinates":[-0.074476,51.558849],"type":"Point"}
}