{
  "type": "Feature",
  "properties": {
    "iso:country":"GB",
    "sg:address":"2a Marriott St, Fenton",
    "sg:city":"Stoke On Trent",
    "sg:classifiers":[
        {
            "category":"Professional",
            "subcategory":"Employment Agencies",
            "type":"Services"
        }
    ],
    "sg:phone":"+44 1782 853838",
    "sg:postcode":"ST4 3HR",
    "sg:province":"Staffordshire",
    "sg:tags":[
        "introduction"
    ],
    "wof:name":"Je T'Aime",
    "wof:placetype":"venue"
},
  "geometry": {"coordinates":[-2.143446,52.995613],"type":"Point"}
}