{
  "type": "Feature",
  "properties": {
    "iso:country":"GB",
    "sg:address":"209 West Street",
    "sg:city":"Fareham",
    "sg:classifiers":[
        {
            "category":"Real Estate",
            "subcategory":"Developer",
            "type":"Services"
        }
    ],
    "sg:phone":"+44 1329 232057",
    "sg:postcode":"PO16 0EN",
    "sg:province":"Hampshire",
    "sg:tags":[
        "property"
    ],
    "wof:name":"Fay & Son Ltd.",
    "wof:placetype":"venue"
},
  "geometry": {"coordinates":[-1.186914,50.852711],"type":"Point"}
}