{
  "type": "Feature",
  "properties": {
    "addr:full":"Penhower Isaf, Caerhun Bangor Gwynedd LL57 4DT",
    "addr:postcode":"ll57 4dt",
    "iso:country":"GB",
    "sg:address":"Penhower Isaf, Caerhun",
    "sg:city":"Bangor",
    "sg:classifiers":[
        {
            "category":"Farming",
            "subcategory":"Livestock Farm",
            "type":"Manufacturing & Wholesale Goods"
        }
    ],
    "sg:phone":"+44 1248 353628",
    "sg:postcode":"LL57 4DT",
    "sg:province":"Gwynedd",
    "sg:tags":[
        "others"
    ],
    "wof:name":"Esaf R Lee",
    "wof:placetype":"venue"
},
  "geometry": {"coordinates":[-4.137094,53.199203],"type":"Point"}
}