{
  "type": "Feature",
  "properties": {
    "iso:country":"GB",
    "sg:address":"1149 Bristol Road South",
    "sg:city":"Birmingham",
    "sg:classifiers":[
        {
            "category":"Fast Food",
            "type":"Food & Drink"
        }
    ],
    "sg:phone":"+44 121 475 1020",
    "sg:postcode":"B31 2SL",
    "sg:province":"West Midlands",
    "sg:tags":[
        "away",
        "take"
    ],
    "wof:name":"Far East Chinese Take Away",
    "wof:placetype":"venue"
},
  "geometry": {"coordinates":[-1.978467,52.405758],"type":"Point"}
}