{
  "type": "Feature",
  "properties": {
    "iso:country":"GB",
    "sg:address":"8 Weavers End, Hanslope",
    "sg:city":"Milton Keynes",
    "sg:classifiers":[
        {
            "category":"Home & Garden",
            "subcategory":"Hardware",
            "type":"Retail Goods"
        }
    ],
    "sg:phone":"+44 1908 510977",
    "sg:postcode":"MK19 7PA",
    "sg:province":"Buckinghamshire",
    "sg:tags":[
        "device",
        "fixing",
        "fastener"
    ],
    "wof:name":"Collated Staple & Nail Supplies",
    "wof:placetype":"venue"
},
  "geometry": {"coordinates":[-0.8250380158,52.1116065979],"type":"Point"}
}