{
  "type": "Feature",
  "properties": {
    "iso:country":"GB",
    "sg:address":"Robin Post Stables, Arlington Road West",
    "sg:city":"Hailsham",
    "sg:classifiers":[
        {
            "category":"Sports & Exercise",
            "subcategory":"Stables",
            "type":"Entertainment"
        }
    ],
    "sg:postcode":"BN27 3RE",
    "sg:province":"East Sussex",
    "sg:tags":[
        "education",
        "equestrian"
    ],
    "wof:name":"Samantha Champney-Warrener",
    "wof:placetype":"venue"
},
  "geometry": {"coordinates":[0.227218,50.858475],"type":"Point"}
}