{
  "type": "Feature",
  "properties": {
    "iso:country":"GB",
    "sg:address":"Stapehill Cres",
    "sg:city":"Wimborne",
    "sg:classifiers":[
        {
            "category":"Food & Beverages",
            "subcategory":"Fruits & Vegetables",
            "type":"Retail Goods"
        }
    ],
    "sg:postcode":"BH21 2ED",
    "sg:province":"Dorset",
    "sg:tags":[
        "greengrocer"
    ],
    "wof:name":"Hayles,Brian,",
    "wof:placetype":"venue"
},
  "geometry": {"coordinates":[-1.943318,50.802341],"type":"Point"}
}