{
  "type": "Feature",
  "properties": {
    "addr:full":"11-19 Harbour Street Stranraer Dumfries and Galloway DG9 7RA",
    "addr:housenumber":"11-19",
    "addr:postcode":"dg9 7ra",
    "addr:street":"Harbour Street",
    "iso:country":"GB",
    "sg:address":"11-19 Harbour Street",
    "sg:city":"Stranraer",
    "sg:classifiers":[
        {
            "category":"Bus Charters",
            "type":"Transportation"
        },
        {
            "category":"Bus Stop",
            "subcategory":"None",
            "type":"Transportation"
        }
    ],
    "sg:phone":"+44 1776 705372",
    "sg:postcode":"DG9 7RA",
    "sg:province":"Dumfries and Galloway",
    "sg:tags":[
        "operator",
        "coach"
    ],
    "wof:name":"Ulsterbus Ltd",
    "wof:placetype":"venue"
},
  "geometry": {"coordinates":[-5.025411,54.905472],"type":"Point"}
}