{
  "type": "Feature",
  "properties": {
    "addr:full":"86 Princess Street Luton Bedfordshire LU1 5AT",
    "addr:housenumber":"86",
    "addr:postcode":"lu1 5at",
    "addr:street":"Princess Street",
    "iso:country":"GB",
    "sg:address":"86 Princess Street",
    "sg:city":"Luton",
    "sg:classifiers":[
        {
            "category":"Shopping",
            "subcategory":"Department Store",
            "type":"Retail Goods"
        }
    ],
    "sg:postcode":"LU1 5AT",
    "sg:province":"Bedfordshire",
    "wof:name":"Contract Cleaning  &  Supplies (Beds) Lt",
    "wof:placetype":"venue"
},
  "geometry": {"coordinates":[-0.4212090075,51.8772125244],"type":"Point"}
}