{
  "type": "Feature",
  "properties": {
    "iso:country":"GB",
    "sg:address":"57 Gabalfa Road, Gabalfa Avenue",
    "sg:city":"Cardiff",
    "sg:classifiers":[
        {
            "category":"Food & Beverages",
            "subcategory":"Fruits & Vegetables",
            "type":"Retail Goods"
        }
    ],
    "sg:postcode":"CF14 2SH",
    "sg:province":"Cardiff",
    "sg:tags":[
        "greengrocer"
    ],
    "wof:name":"Kiwi Fruits",
    "wof:placetype":"venue"
},
  "geometry": {"coordinates":[-3.2232909203,51.4999580383],"type":"Point"}
}