{
  "type": "Feature",
  "properties": {
    "iso:country":"GB",
    "sg:address":"Unit 2-6, 65a Pearl Rd",
    "sg:city":"Walthamstow",
    "sg:classifiers":[
        {
            "category":"Building & Trades",
            "subcategory":"Construction",
            "type":"Services"
        }
    ],
    "sg:phone":"+44 20 8521 5618",
    "sg:postcode":"E17 4QY",
    "sg:province":"Greater London",
    "sg:tags":[
        "joiner",
        "carpenter"
    ],
    "wof:name":"Abbey Joinery",
    "wof:placetype":"venue"
},
  "geometry": {"coordinates":[-0.0217829999,51.5886878967],"type":"Point"}
}