{
  "type": "Feature",
  "properties": {
    "iso:country":"GB",
    "sg:address":"The Steadings, Road Side Croft",
    "sg:city":"Aberdeen",
    "sg:classifiers":[
        {
            "category":"Personal",
            "subcategory":"Tanning Parlor",
            "type":"Services"
        }
    ],
    "sg:phone":"+44 1224 790900",
    "sg:postcode":"AB21 0TL",
    "sg:province":"Aberdeen City",
    "sg:tags":[
        "sunbeds"
    ],
    "wof:name":"Scot-Tan Tanning Systems",
    "wof:placetype":"venue"
},
  "geometry": {"coordinates":[-2.27674,57.197041],"type":"Point"}
}