{
  "type": "Feature",
  "properties": {
    "addr:full":"182 Whiteladies Road, Clifton Bristol City of Bristol BS8 2XU",
    "addr:housenumber":"182",
    "addr:postcode":"bs8 2xu",
    "addr:street":"Whiteladies Road",
    "iso:country":"GB",
    "sg:address":"182 Whiteladies Road, Clifton",
    "sg:city":"Bristol",
    "sg:classifiers":[
        {
            "category":"Real Estate",
            "subcategory":"Real Estate Operator",
            "type":"Services"
        }
    ],
    "sg:phone":"+44 117 973 2004",
    "sg:postcode":"BS8 2XU",
    "sg:province":"City of Bristol",
    "sg:tags":[
        "letting",
        "agent"
    ],
    "wof:name":"Flatline",
    "wof:placetype":"venue"
},
  "geometry": {"coordinates":[-2.6150679588,51.4701728821],"type":"Point"}
}