{
  "type": "Feature",
  "properties": {
    "iso:country":"GB",
    "sg:address":"Old Coach House, Haddfoot Wynd",
    "sg:city":"Anstruther",
    "sg:classifiers":[
        {
            "category":"Professional",
            "subcategory":"Management & Consulting",
            "type":"Services"
        }
    ],
    "sg:phone":"+44 1333 313356",
    "sg:postcode":"KY10 3AD",
    "sg:province":"Fife",
    "sg:tags":[
        "consultant",
        "business"
    ],
    "wof:name":"Alastair Thomson",
    "wof:placetype":"venue"
},
  "geometry": {"coordinates":[-2.6973879337,56.2225341797],"type":"Point"}
}