{
  "type": "Feature",
  "properties": {
    "addr:full":"2228 Coventry Road, Sheldon Birmingham West Midlands B26 3JH",
    "addr:housenumber":"2228",
    "addr:postcode":"b26 3jh",
    "addr:street":"Coventry Road",
    "iso:country":"GB",
    "sg:address":"2228 Coventry Road, Sheldon",
    "sg:city":"Birmingham",
    "sg:classifiers":[
        {
            "category":"Personal",
            "subcategory":"Beauty Salon",
            "type":"Services"
        }
    ],
    "sg:postcode":"B26 3JH",
    "sg:province":"West Midlands",
    "sg:tags":[
        "unisex",
        "hairdresser"
    ],
    "wof:name":"Steve's Hair Studio",
    "wof:placetype":"venue"
},
  "geometry": {"coordinates":[-1.780174,52.451832],"type":"Point"}
}