{
  "type": "Feature",
  "properties": {
    "iso:country":"GB",
    "sg:address":"109 Essex Rd",
    "sg:city":"Islington",
    "sg:classifiers":[
        {
            "category":"Shopping",
            "subcategory":"Florist",
            "type":"Retail Goods"
        }
    ],
    "sg:phone":"+44 20 7704 2050",
    "sg:postcode":"N1 2SL",
    "sg:province":"Greater London",
    "wof:name":"Something Special",
    "wof:placetype":"venue"
},
  "geometry": {"coordinates":[-0.0987609997,51.5388717651],"type":"Point"}
}