{
  "type": "Feature",
  "properties": {
    "iso:country":"GB",
    "sg:address":"15 Sulgrave Road",
    "sg:city":"Leicester",
    "sg:classifiers":[
        {
            "category":"Shopping",
            "subcategory":"Clothing, Apparel, & Fashions",
            "type":"Retail Goods"
        },
        {
            "category":"Manufacturing",
            "subcategory":"Paper Products",
            "type":"Manufacturing & Wholesale Goods"
        }
    ],
    "sg:phone":"+44 116 274 2128",
    "sg:postcode":"LE5 0LH",
    "sg:province":"Leicestershire",
    "sg:tags":[
        "clothing",
        "fabric",
        "manufacturer"
    ],
    "wof:name":"A M Fabrics",
    "wof:placetype":"venue"
},
  "geometry": {"coordinates":[-1.1003290415,52.6426315308],"type":"Point"}
}