{
  "type": "Feature",
  "properties": {
    "addr:full":"42 Mooring Close, Murdishaw Runcorn Cheshire WA7 6DA",
    "addr:housenumber":"42",
    "addr:postcode":"wa7 6da",
    "addr:street":"Mooring Close",
    "iso:country":"GB",
    "sg:address":"42 Mooring Close, Murdishaw",
    "sg:city":"Runcorn",
    "sg:classifiers":[
        {
            "category":"Retail",
            "subcategory":"Auto Repair",
            "type":"Services"
        }
    ],
    "sg:phone":"+44 1928 717200",
    "sg:postcode":"WA7 6DA",
    "sg:province":"Cheshire",
    "sg:tags":[
        "engine",
        "car",
        "specialist"
    ],
    "wof:name":"Hometune-the Experts",
    "wof:placetype":"venue"
},
  "geometry": {"coordinates":[-2.6630249023,53.322883606],"type":"Point"}
}