{
  "type": "Feature",
  "properties": {
    "addr:full":"Unit 8 Inveralmond Way, Inveralmond Industrial Estate Perth Perth and Kinross PH1 3QU",
    "addr:housenumber":"unit 8",
    "addr:postcode":"ph1 3qu",
    "addr:street":"Inveralmond Way Inveralmond Industrial Estate",
    "iso:country":"GB",
    "sg:address":"Unit 8 Inveralmond Way, Inveralmond Industrial Estate",
    "sg:city":"Perth",
    "sg:classifiers":[
        {
            "category":"Building & Trades",
            "subcategory":"Construction",
            "type":"Services"
        }
    ],
    "sg:postcode":"PH1 3QU",
    "sg:province":"Perth and Kinross",
    "sg:tags":[
        "window",
        "replacement"
    ],
    "wof:name":"Broxwood (Scotland) Ltd.",
    "wof:placetype":"venue"
},
  "geometry": {"coordinates":[-3.478464,56.417191],"type":"Point"}
}