{
  "type": "Feature",
  "properties": {
    "iso:country":"GB",
    "sg:address":"1 Silver Street, Midsomer Norton",
    "sg:city":"Bath",
    "sg:classifiers":[
        {
            "category":"Wholesale",
            "subcategory":"Construction Materials",
            "type":"Manufacturing & Wholesale Goods"
        }
    ],
    "sg:phone":"+44 1761 418454",
    "sg:postcode":"BA3 2ET",
    "sg:province":"Somerset",
    "sg:tags":[
        "lift"
    ],
    "wof:name":"Facade Hoists International Ltd.",
    "wof:placetype":"venue"
},
  "geometry": {"coordinates":[-2.4819331169,51.2847251892],"type":"Point"}
}