{
  "type": "Feature",
  "properties": {
    "iso:country":"GB",
    "sg:address":"Blackboy Farm, Bagley Grn",
    "sg:city":"Wellington",
    "sg:classifiers":[
        {
            "category":"Transit Center",
            "subcategory":"Passenger",
            "type":"Transportation"
        },
        {
            "category":"Retail",
            "subcategory":"Pet Boarding",
            "type":"Services"
        }
    ],
    "sg:phone":"+44 1823 663436",
    "sg:postcode":"TA21 9QD",
    "sg:province":"Devon",
    "sg:tags":[
        "kennel",
        "catteries"
    ],
    "wof:name":"Wellington Boarding Kennels & Cattery",
    "wof:placetype":"venue"
},
  "geometry": {"coordinates":[-3.2415790558,50.9434394836],"type":"Point"}
}