{
  "type": "Feature",
  "properties": {
    "addr:full":"17 Rowsham Dell, Giffard Park Milton Keynes Buckinghamshire MK14 5JS",
    "addr:housenumber":"17",
    "addr:postcode":"mk14 5js",
    "addr:street":"Rowsham Dell Giffard Park",
    "iso:country":"GB",
    "sg:address":"17 Rowsham Dell, Giffard Park",
    "sg:city":"Milton Keynes",
    "sg:classifiers":[
        {
            "category":"Professional",
            "subcategory":"Management & Consulting",
            "type":"Services"
        }
    ],
    "sg:postcode":"MK14 5JS",
    "sg:province":"Buckinghamshire",
    "sg:tags":[
        "consultant",
        "business"
    ],
    "wof:name":"S.B.A. Consultants Ltd",
    "wof:placetype":"venue"
},
  "geometry": {"coordinates":[-0.7485550046,52.0779418945],"type":"Point"}
}