{
  "type": "Feature",
  "properties": {
    "addr:full":"13 Dingle Avenue, Shaw Oldham Lancashire OL2 8DD",
    "addr:housenumber":"13",
    "addr:postcode":"ol2 8dd",
    "addr:street":"Dingle Avenue",
    "iso:country":"GB",
    "sg:address":"13 Dingle Avenue, Shaw",
    "sg:city":"Oldham",
    "sg:classifiers":[
        {
            "category":"Food & Beverages",
            "subcategory":"Specialty",
            "type":"Retail Goods"
        },
        {
            "category":"Health Services",
            "subcategory":"Health Practitioner",
            "type":"Services"
        },
        {
            "category":"Government",
            "subcategory":"Office",
            "type":"Public Place"
        }
    ],
    "sg:phone":"+44 1706 847918",
    "sg:postcode":"OL2 8DD",
    "sg:province":"Lancashire",
    "sg:tags":[
        "psychologist",
        "agency",
        "retailer",
        "education",
        "authority"
    ],
    "wof:name":"C A Tarett",
    "wof:placetype":"venue"
},
  "geometry": {"coordinates":[-2.0858659744,53.5884399414],"type":"Point"}
}