{
  "type": "Feature",
  "properties": {
    "addr:full":"Po Box 7324 London Greater London N1 9QS",
    "addr:housenumber":"po",
    "addr:postcode":"n1 9qs",
    "addr:street":"Box 7324",
    "iso:country":"GB",
    "sg:address":"Po Box 7324",
    "sg:city":"London",
    "sg:classifiers":[
        {
            "category":"Personal",
            "type":"Services"
        },
        {
            "category":"Professional",
            "subcategory":"Lawyer & Legal Services",
            "type":"Services"
        }
    ],
    "sg:phone":"+44 20 7837 7324",
    "sg:postcode":"N1 9QS",
    "sg:province":"Greater London",
    "sg:tags":[
        "advice",
        "counselling"
    ],
    "wof:name":"London Lesbian & Gay Switchboard Ltd",
    "wof:placetype":"venue"
},
  "geometry": {"coordinates":[-0.1061490029,51.5327949524],"type":"Point"}
}