{
  "type": "Feature",
  "properties": {
    "addr:full":"Suite 2a Anson Court, Horning Lowe Street Burton-on-trent Derbyshire DE14 1NG",
    "addr:housenumber":"suite 2a",
    "addr:postcode":"de14 1ng",
    "addr:street":"Anson Court;Lowe Street",
    "iso:country":"GB",
    "sg:address":"Suite 2a Anson Court, Horning Lowe Street",
    "sg:city":"Burton-on-trent",
    "sg:classifiers":[
        {
            "category":"Real Estate",
            "subcategory":"Architect",
            "type":"Services"
        }
    ],
    "sg:phone":"+44 1283 515155",
    "sg:postcode":"DE14 1NG",
    "sg:province":"Derbyshire",
    "wof:name":"Acheson Warren Associates",
    "wof:placetype":"venue"
},
  "geometry": {"coordinates":[-1.627051,52.807693],"type":"Point"}
}