{
  "type": "Feature",
  "properties": {
    "addr:full":"Beck La Sutton In Ashfield Nottinghamshire NG17 3AH",
    "addr:postcode":"ng17 3ah",
    "addr:street":"La Sutton In",
    "iso:country":"GB",
    "sg:address":"Beck La",
    "sg:city":"Sutton In Ashfield",
    "sg:classifiers":[
        {
            "category":"Home & Garden",
            "subcategory":"Garden Supply",
            "type":"Retail Goods"
        }
    ],
    "sg:phone":"+44 1623 514608",
    "sg:postcode":"NG17 3AH",
    "sg:province":"Nottinghamshire",
    "sg:tags":[
        "nursery",
        "centre"
    ],
    "wof:name":"Dalestorth Nurseries",
    "wof:placetype":"venue"
},
  "geometry": {"coordinates":[-1.2421070337,53.1433677673],"type":"Point"}
}