{
  "type": "Feature",
  "properties": {
    "addr:full":"24 Theobald Street Borehamwood Hertfordshire WD6 4SE",
    "addr:housenumber":"24",
    "addr:postcode":"wd6 4se",
    "addr:street":"Theobald Street",
    "iso:country":"GB",
    "sg:address":"24 Theobald Street",
    "sg:city":"Borehamwood",
    "sg:classifiers":[
        {
            "category":"Fast Food",
            "type":"Food & Drink"
        }
    ],
    "sg:phone":"+44 20 8207 2105",
    "sg:postcode":"WD6 4SE",
    "sg:province":"Hertfordshire",
    "sg:tags":[
        "away",
        "take"
    ],
    "wof:name":"The Theobald Cottage",
    "wof:placetype":"venue"
},
  "geometry": {"coordinates":[-0.280221,51.655025],"type":"Point"}
}