{
  "type": "Feature",
  "properties": {
    "iso:country":"GB",
    "sg:address":"34 Wheatfield Way",
    "sg:city":"Cranbrook",
    "sg:classifiers":[
        {
            "category":"Building & Trades",
            "subcategory":"Construction",
            "type":"Services"
        }
    ],
    "sg:phone":"+44 1580 714076",
    "sg:postcode":"TN17 3NB",
    "sg:province":"Kent",
    "sg:tags":[
        "decorator",
        "painter"
    ],
    "wof:name":"T F Briley & Sons",
    "wof:placetype":"venue"
},
  "geometry": {"coordinates":[0.5289689898,51.0985031128],"type":"Point"}
}