{
  "type": "Feature",
  "properties": {
    "addr:full":"83 Abbotswood Gardens Ilford Essex IG5 0BH",
    "addr:housenumber":"83",
    "addr:postcode":"ig5 0bh",
    "addr:street":"Abbotswood Gardens",
    "iso:country":"GB",
    "sg:address":"83 Abbotswood Gardens",
    "sg:city":"Ilford",
    "sg:classifiers":[
        {
            "category":"Health Services",
            "subcategory":"Health Practitioner",
            "type":"Services"
        }
    ],
    "sg:phone":"+44 20 8550 5542",
    "sg:postcode":"IG5 0BH",
    "sg:province":"Essex",
    "sg:tags":[
        "hypnotherapists"
    ],
    "wof:name":"Samuel Bernstein",
    "wof:placetype":"venue"
},
  "geometry": {"coordinates":[0.0600339994,51.5882759094],"type":"Point"}
}