{
  "type": "Feature",
  "properties": {
    "addr:full":"Camerton Hall Lane, Main Road Camerton Hull East Riding of Yorkshire HU12 9NP",
    "addr:housenumber":"camerton",
    "addr:postcode":"hu12 9np",
    "addr:street":"Hall Lane Main Road",
    "iso:country":"GB",
    "sg:address":"Camerton Hall Lane, Main Road Camerton",
    "sg:city":"Hull",
    "sg:classifiers":[
        {
            "category":"Building & Trades",
            "subcategory":"Construction",
            "type":"Services"
        }
    ],
    "sg:phone":"+44 1964 670888",
    "sg:postcode":"HU12 9NP",
    "sg:province":"East Riding of Yorkshire",
    "sg:tags":[
        "builder"
    ],
    "wof:name":"Marriott (Builders) Ltd.",
    "wof:placetype":"venue"
},
  "geometry": {"coordinates":[-0.1567980051,53.7177429199],"type":"Point"}
}