{
  "type": "Feature",
  "properties": {
    "iso:country":"GB",
    "sg:address":"Little Cowdray Farm, Highfield Lane, Thursley",
    "sg:city":"Godalming",
    "sg:classifiers":[
        {
            "category":"Professional",
            "type":"Services"
        },
        {
            "category":"Banks & Credit Unions",
            "subcategory":"Investment Brokerage",
            "type":"Services"
        }
    ],
    "sg:phone":"+44 1428 605016",
    "sg:postcode":"GU8 6QJ",
    "sg:province":"Surrey",
    "sg:tags":[
        "farm",
        "agricultural",
        "contractor"
    ],
    "wof:name":"P J Goble",
    "wof:placetype":"venue"
},
  "geometry": {"coordinates":[-0.713469,51.149971],"type":"Point"}
}