{
  "type": "Feature",
  "properties": {
    "addr:full":"The Laindon School, High Road, Laindon Basildon Essex SS15 6DD",
    "addr:postcode":"ss15 6dd",
    "addr:street":"High Road",
    "iso:country":"GB",
    "sg:address":"The Laindon School, High Road, Laindon",
    "sg:city":"Basildon",
    "sg:classifiers":[
        {
            "category":"Farming",
            "subcategory":"Nursery",
            "type":"Manufacturing & Wholesale Goods"
        }
    ],
    "sg:phone":"+44 1268 410937",
    "sg:postcode":"SS15 6DD",
    "sg:province":"Essex",
    "sg:tags":[
        "creche"
    ],
    "wof:name":"First Steps Day Nursery",
    "wof:placetype":"venue"
},
  "geometry": {"coordinates":[0.4103490114,51.5749893188],"type":"Point"}
}