{
  "type": "Feature",
  "properties": {
    "addr:full":"38 Syon La Isleworth Greater London TW7 5NQ",
    "addr:housenumber":"38",
    "addr:postcode":"tw7 5nq",
    "addr:street":"Syon La Isleworth",
    "iso:country":"GB",
    "sg:address":"38 Syon La",
    "sg:city":"Isleworth",
    "sg:classifiers":[
        {
            "category":"Home & Garden",
            "subcategory":"Household Appliances",
            "type":"Retail Goods"
        }
    ],
    "sg:phone":"+44 20 8232 8486",
    "sg:postcode":"TW7 5NQ",
    "sg:province":"Greater London",
    "sg:tags":[
        "electrical",
        "domestic"
    ],
    "wof:name":"Market Refrigeration",
    "wof:placetype":"venue"
},
  "geometry": {"coordinates":[-0.327723,51.483421],"type":"Point"}
}