{
  "type": "Feature",
  "properties": {
    "addr:full":"The Cottage, Chapel Lane Chipping Norton Gloucestershire OX7 4LT",
    "addr:postcode":"ox7 4lt",
    "addr:street":"Chapel Lane",
    "iso:country":"GB",
    "sg:address":"The Cottage, Chapel Lane",
    "sg:city":"Chipping Norton",
    "sg:classifiers":[
        {
            "category":"Building & Trades",
            "subcategory":"Construction",
            "type":"Services"
        }
    ],
    "sg:postcode":"OX7 4LT",
    "sg:province":"Gloucestershire",
    "sg:tags":[
        "builder"
    ],
    "wof:name":"Ridgway Builders",
    "wof:placetype":"venue"
},
  "geometry": {"coordinates":[-1.545913,51.940407],"type":"Point"}
}