{
  "type": "Feature",
  "properties": {
    "addr:full":"Unit 5b Accrington Road Burnley Lancashire BB11 5EF",
    "addr:housenumber":"unit 5b",
    "addr:postcode":"bb11 5ef",
    "addr:street":"Accrington Road",
    "iso:country":"GB",
    "sg:address":"Unit 5b Accrington Road",
    "sg:city":"Burnley",
    "sg:classifiers":[
        {
            "category":"Retail",
            "subcategory":"Repair Shop",
            "type":"Services"
        }
    ],
    "sg:postcode":"BB11 5EF",
    "sg:province":"Lancashire",
    "sg:tags":[
        "upholsterer"
    ],
    "wof:name":"S M Upholstery",
    "wof:placetype":"venue"
},
  "geometry": {"coordinates":[-2.261829,53.787991],"type":"Point"}
}