{
  "type": "Feature",
  "properties": {
    "addr:full":"Clarke Way Hyde Cheshire SK14 2AN",
    "addr:postcode":"sk14 2an",
    "addr:street":"Clarke Way",
    "iso:country":"GB",
    "sg:address":"Clarke Way",
    "sg:city":"Hyde",
    "sg:classifiers":[
        {
            "category":"Home & Garden",
            "subcategory":"Home Furnishings",
            "type":"Retail Goods"
        }
    ],
    "sg:phone":"+44 161 368 4863",
    "sg:postcode":"SK14 2AN",
    "sg:province":"Cheshire",
    "sg:tags":[
        "merchant",
        "diy",
        "decorators'"
    ],
    "wof:name":"Hyde Industrial Supplies Ltd.",
    "wof:placetype":"venue"
},
  "geometry": {"coordinates":[-2.080884,53.454311],"type":"Point"}
}