{
  "type": "Feature",
  "properties": {
    "iso:country":"GB",
    "sg:address":"Pym Street",
    "sg:city":"Tavistock",
    "sg:classifiers":[
        {
            "category":"Home & Garden",
            "subcategory":"Home Furnishings",
            "type":"Retail Goods"
        }
    ],
    "sg:phone":"+44 1822 614408",
    "sg:postcode":"PL19 0AW",
    "sg:province":"Devon",
    "sg:tags":[
        "decorative",
        "glass",
        "mirror"
    ],
    "wof:name":"Plush Bohemia",
    "wof:placetype":"venue"
},
  "geometry": {"coordinates":[-4.145989,50.550419],"type":"Point"}
}