{
  "type": "Feature",
  "properties": {
    "addr:full":"46 Bank Street Galashiels Scottish Borders TD1 1EP",
    "addr:housenumber":"46",
    "addr:postcode":"td1 1ep",
    "addr:street":"Bank Street",
    "iso:country":"GB",
    "sg:address":"46 Bank Street",
    "sg:city":"Galashiels",
    "sg:classifiers":[
        {
            "category":"Banks & Credit Unions",
            "subcategory":"Financial Services",
            "type":"Services"
        }
    ],
    "sg:phone":"+44 1896 753041",
    "sg:postcode":"TD1 1EP",
    "sg:province":"Scottish Borders",
    "sg:tags":[
        "building",
        "society"
    ],
    "wof:name":"Universal Building Society",
    "wof:placetype":"venue"
},
  "geometry": {"coordinates":[-2.807399,55.615379],"type":"Point"}
}