{
  "type": "Feature",
  "properties": {
    "addr:full":"19 Bridlington Street, Hunmanby Filey North Yorkshire YO14 0JR",
    "addr:housenumber":"19",
    "addr:postcode":"yo14 0jr",
    "addr:street":"Bridlington Street",
    "iso:country":"GB",
    "sg:address":"19 Bridlington Street, Hunmanby",
    "sg:city":"Filey",
    "sg:classifiers":[
        {
            "category":"Food & Beverages",
            "subcategory":"Meat & Fish",
            "type":"Retail Goods"
        }
    ],
    "sg:phone":"+44 1723 890363",
    "sg:postcode":"YO14 0JR",
    "sg:province":"North Yorkshire",
    "sg:tags":[
        "chip"
    ],
    "wof:name":"Auntie Ellies",
    "wof:placetype":"venue"
},
  "geometry": {"coordinates":[-0.321179986,54.1802825928],"type":"Point"}
}