{
  "type": "Feature",
  "properties": {
    "iso:country":"GB",
    "sg:address":"Sandy Lane",
    "sg:city":"Dereham",
    "sg:classifiers":[
        {
            "category":"Bars & Pubs",
            "type":"Food & Drink"
        }
    ],
    "sg:phone":"+44 1362 698841",
    "sg:postcode":"NR19 2EA",
    "sg:province":"Norfolk",
    "sg:tags":[
        "pubs",
        "inn"
    ],
    "wof:name":"Gemini",
    "wof:placetype":"venue"
},
  "geometry": {"coordinates":[0.933305,52.688732],"type":"Point"}
}