{
  "type": "Feature",
  "properties": {
    "addr:full":"Clockluine Road, Hillend Dunfermline Fife KY11 7HS",
    "addr:postcode":"ky11 7hs",
    "addr:street":"Clockluine Road",
    "iso:country":"GB",
    "sg:address":"Clockluine Road, Hillend",
    "sg:city":"Dunfermline",
    "sg:classifiers":[
        {
            "category":"Farming",
            "subcategory":"Nursery",
            "type":"Manufacturing & Wholesale Goods"
        },
        {
            "category":"Community Center",
            "type":"Public Place"
        }
    ],
    "sg:phone":"+44 1383 415555",
    "sg:postcode":"KY11 7HS",
    "sg:province":"Fife",
    "sg:tags":[
        "centre"
    ],
    "wof:name":"Growforth Ltd",
    "wof:placetype":"venue"
},
  "geometry": {"coordinates":[-3.37451,56.046276],"type":"Point"}
}