{
  "type": "Feature",
  "properties": {
    "addr:full":"26 County Square Ashford Kent TN23 1YB",
    "addr:housenumber":"26",
    "addr:postcode":"tn23 1yb",
    "addr:street":"County Square",
    "iso:country":"GB",
    "sg:address":"26 County Square",
    "sg:city":"Ashford",
    "sg:classifiers":[
        {
            "category":"Shopping",
            "subcategory":"Hobbies, Toys, & Games",
            "type":"Retail Goods"
        }
    ],
    "sg:phone":"+44 1233 661744",
    "sg:postcode":"TN23 1YB",
    "sg:province":"Kent",
    "sg:tags":[
        "shop",
        "toy"
    ],
    "wof:name":"Carousel Toys Ltd.",
    "wof:placetype":"venue"
},
  "geometry": {"coordinates":[0.87033,51.148319],"type":"Point"}
}