{
  "type": "Feature",
  "properties": {
    "iso:country":"GB",
    "sg:address":"Drip Rd",
    "sg:city":"Stirling",
    "sg:classifiers":[
        {
            "category":"Autos & Motor Vehicles",
            "subcategory":"Fuel & Gas Station",
            "type":"Retail Goods"
        }
    ],
    "sg:phone":"+44 1786 446242",
    "sg:postcode":"FK8 1RE",
    "sg:province":"Stirling",
    "sg:tags":[
        "petrol",
        "filling"
    ],
    "wof:name":"Mogil Service Station",
    "wof:placetype":"venue"
},
  "geometry": {"coordinates":[-3.9579739571,56.1315994263],"type":"Point"}
}