{
  "type": "Feature",
  "properties": {
    "addr:full":"Lode Lane Industrial Estate, Boulton Rd Solihull West Midlands B91 2JU",
    "addr:housenumber":"estate",
    "addr:postcode":"b91 2ju",
    "addr:street":"Lode Lane Industrial;Boulton Rd",
    "iso:country":"GB",
    "sg:address":"Lode Lane Industrial Estate, Boulton Rd",
    "sg:city":"Solihull",
    "sg:classifiers":[
        {
            "category":"Retail",
            "subcategory":"Auto Repair",
            "type":"Services"
        }
    ],
    "sg:phone":"+44 121 704 2688",
    "sg:postcode":"B91 2JU",
    "sg:province":"West Midlands",
    "sg:tags":[
        "car",
        "specialist",
        "customizing"
    ],
    "wof:name":"Tyresales Tyreplus Autoservice",
    "wof:placetype":"venue"
},
  "geometry": {"coordinates":[-1.781067,52.431454],"type":"Point"}
}