{
  "type": "Feature",
  "properties": {
    "addr:full":"101 The Glade Croydon Surrey CR0 7QN",
    "addr:housenumber":"101",
    "addr:postcode":"cr0 7qn",
    "addr:street":"The Glade",
    "iso:country":"GB",
    "sg:address":"101 The Glade",
    "sg:city":"Croydon",
    "sg:classifiers":[
        {
            "category":"Building & Trades",
            "subcategory":"Construction",
            "type":"Services"
        }
    ],
    "sg:phone":"+44 20 8654 8821",
    "sg:postcode":"CR0 7QN",
    "sg:province":"Surrey",
    "sg:tags":[
        "contractor",
        "paving",
        "driveway"
    ],
    "wof:name":"Manor Builders",
    "wof:placetype":"venue"
},
  "geometry": {"coordinates":[-0.045264,51.386848],"type":"Point"}
}