{
  "type": "Feature",
  "properties": {
    "iso:country":"GB",
    "sg:address":"6 Nottingham Street",
    "sg:city":"Melton Mowbray",
    "sg:classifiers":[
        {
            "category":"Bars & Pubs",
            "type":"Food & Drink"
        },
        {
            "category":"Community Center",
            "subcategory":"Social",
            "type":"Public Place"
        }
    ],
    "sg:phone":"+44 1664 562120",
    "sg:postcode":"LE13 1NW",
    "sg:province":"Leicestershire",
    "sg:tags":[
        "pubs",
        "house",
        "inn",
        "activity"
    ],
    "wof:name":"THE HALF MOON INN",
    "wof:placetype":"venue"
},
  "geometry": {"coordinates":[-0.8876730204,52.7656364441],"type":"Point"}
}