{
  "type": "Feature",
  "properties": {
    "iso:country":"GB",
    "sg:address":"34 Townsend Place",
    "sg:city":"Kirkcaldy",
    "sg:classifiers":[
        {
            "category":"Retail",
            "subcategory":"Laundry & Dry Cleaning",
            "type":"Services"
        }
    ],
    "sg:phone":"+44 1592 596677",
    "sg:postcode":"KY1 1HB",
    "sg:province":"Fife",
    "sg:tags":[
        "alteration"
    ],
    "wof:name":"The Long & the Short of It",
    "wof:placetype":"venue"
},
  "geometry": {"coordinates":[-3.158759,56.113449],"type":"Point"}
}