{
  "type": "Feature",
  "properties": {
    "iso:country":"GB",
    "sg:address":"286 Broadway",
    "sg:city":"Bexleyheath",
    "sg:classifiers":[
        {
            "category":"Building & Trades",
            "subcategory":"Landscaping Services",
            "type":"Services"
        }
    ],
    "sg:phone":"+44 20 8298 7722",
    "sg:postcode":"DA6 8AW",
    "sg:province":"Kent",
    "sg:tags":[
        "ladder",
        "loft"
    ],
    "wof:name":"The Loft Shop Group Ltd.",
    "wof:placetype":"venue"
},
  "geometry": {"coordinates":[0.134604,51.458096],"type":"Point"}
}