{
  "type": "Feature",
  "properties": {
    "addr:full":"Unit 3 Mount Pleasant Workshops, Offwell Honiton Devon EX14 9RP",
    "addr:housenumber":"unit 3",
    "addr:postcode":"ex14 9rp",
    "addr:street":"Mount Pleasant",
    "iso:country":"GB",
    "sg:address":"Unit 3 Mount Pleasant Workshops, Offwell",
    "sg:city":"Honiton",
    "sg:classifiers":[
        {
            "category":"Shopping",
            "subcategory":"Antiques",
            "type":"Retail Goods"
        }
    ],
    "sg:postcode":"EX14 9RP",
    "sg:province":"Devon",
    "wof:name":"Ray Poole Antiques & Recycling",
    "wof:placetype":"venue"
},
  "geometry": {"coordinates":[-3.154167,50.796673],"type":"Point"}
}