{
  "type": "Feature",
  "properties": {
    "iso:country":"GB",
    "sg:address":"80 Dalling Rd",
    "sg:city":"Hammersmith",
    "sg:classifiers":[
        {
            "category":"Manufacturing",
            "subcategory":"Signs",
            "type":"Manufacturing & Wholesale Goods"
        }
    ],
    "sg:phone":"+44 20 8741 4306",
    "sg:postcode":"W6 0JA",
    "sg:province":"Greater London",
    "sg:tags":[
        "nameplate"
    ],
    "wof:name":"Dimensional Signs",
    "wof:placetype":"venue"
},
  "geometry": {"coordinates":[-0.234372,51.494648],"type":"Point"}
}