{
  "type": "Feature",
  "properties": {
    "addr:full":"262 Heathersett Close Newmarket Cambridgeshire CB8 7AT",
    "addr:housenumber":"262",
    "addr:postcode":"cb8 7at",
    "addr:street":"Heathersett Close",
    "iso:country":"GB",
    "sg:address":"262 Heathersett Close",
    "sg:city":"Newmarket",
    "sg:classifiers":[
        {
            "category":"Building & Trades",
            "subcategory":"Cleaning & Sanitation",
            "type":"Services"
        }
    ],
    "sg:phone":"+44 1638 662439",
    "sg:postcode":"CB8 7AT",
    "sg:province":"Cambridgeshire",
    "sg:tags":[
        "sweep",
        "chimney"
    ],
    "wof:name":"R J Bristley",
    "wof:placetype":"venue"
},
  "geometry": {"coordinates":[0.3869650066,52.2635192871],"type":"Point"}
}