{
  "type": "Feature",
  "properties": {
    "addr:full":"Tuff-link House, Green Road Colne Lancashire BB8 8AL",
    "addr:postcode":"bb8 8al",
    "addr:street":"Green Road",
    "iso:country":"GB",
    "sg:address":"Tuff-link House, Green Road",
    "sg:city":"Colne",
    "sg:classifiers":[
        {
            "category":"Building & Trades",
            "subcategory":"Landscaping Services",
            "type":"Services"
        }
    ],
    "sg:phone":"+44 1282 873100",
    "sg:postcode":"BB8 8AL",
    "sg:province":"Lancashire",
    "sg:tags":[
        "horticultural"
    ],
    "wof:name":"Farmer Foster",
    "wof:placetype":"venue"
},
  "geometry": {"coordinates":[-2.177774,53.852879],"type":"Point"}
}