{
  "type": "Feature",
  "properties": {
    "iso:country":"GB",
    "sg:address":"2 South Square",
    "sg:city":"London",
    "sg:classifiers":[
        {
            "category":"Freight",
            "type":"Transportation"
        }
    ],
    "sg:postcode":"WC1R 5HR",
    "sg:province":"Greater London",
    "sg:tags":[
        "haulage",
        "road"
    ],
    "wof:name":"A J Logistics Ltd.",
    "wof:placetype":"venue"
},
  "geometry": {"coordinates":[-0.112456,51.518806],"type":"Point"}
}