{
  "type": "Feature",
  "properties": {
    "iso:country":"GB",
    "sg:address":"Workshop 1 Estate Yard, Barkby",
    "sg:city":"Leicester",
    "sg:classifiers":[
        {
            "category":"Manufacturing",
            "subcategory":"Furniture",
            "type":"Manufacturing & Wholesale Goods"
        }
    ],
    "sg:phone":"+44 116 260 2686",
    "sg:postcode":"LE7 3QG",
    "sg:province":"Leicestershire",
    "sg:tags":[
        "polishing",
        "french"
    ],
    "wof:name":"Barkby Framing",
    "wof:placetype":"venue"
},
  "geometry": {"coordinates":[-1.0539189577,52.706829071],"type":"Point"}
}