{
  "type": "Feature",
  "properties": {
    "iso:country":"GB",
    "sg:address":"Unit 1 Freemans Road, Portslade",
    "sg:city":"Brighton",
    "sg:classifiers":[
        {
            "category":"Building & Trades",
            "subcategory":"Construction",
            "type":"Services"
        }
    ],
    "sg:phone":"+44 1273 413443",
    "sg:postcode":"BN41 1SL",
    "sg:province":"East Sussex",
    "sg:tags":[
        "dry",
        "lining",
        "plasterers",
        "screeders"
    ],
    "wof:name":"P & S Fixings",
    "wof:placetype":"venue"
},
  "geometry": {"coordinates":[-0.219964,50.838535],"type":"Point"}
}