{
  "type": "Feature",
  "properties": {
    "iso:country":"GB",
    "sg:address":"Community Mental Health Team, 447 Wellingborough Road",
    "sg:city":"Northampton",
    "sg:classifiers":[
        {
            "category":"Health Services",
            "subcategory":"Clinic",
            "type":"Services"
        }
    ],
    "sg:phone":"+44 1604 795000",
    "sg:postcode":"NN1 4EZ",
    "sg:province":"Northamptonshire",
    "sg:tags":[
        "nh"
    ],
    "wof:name":"Northampton Health Care Trust",
    "wof:placetype":"venue"
},
  "geometry": {"coordinates":[-0.895284,52.23394],"type":"Point"}
}