{
  "type": "Feature",
  "properties": {
    "iso:country":"GB",
    "sg:address":"9 The Bridge",
    "sg:city":"Walsall",
    "sg:classifiers":[
        {
            "category":"Sports & Exercise",
            "subcategory":"Gym",
            "type":"Entertainment"
        }
    ],
    "sg:phone":"+44 1922 637224",
    "sg:postcode":"WS1 1LR",
    "sg:province":"West Midlands",
    "sg:tags":[
        "fitness",
        "health",
        "centre"
    ],
    "wof:name":"Curves & Co",
    "wof:placetype":"venue"
},
  "geometry": {"coordinates":[-1.98113,52.584679],"type":"Point"}
}