{
  "type": "Feature",
  "properties": {
    "addr:full":"Wellcroft Road Liverpool Merseyside L36 7RT",
    "addr:postcode":"l36 7rt",
    "addr:street":"Wellcroft Road",
    "iso:country":"GB",
    "sg:address":"Wellcroft Road",
    "sg:city":"Liverpool",
    "sg:classifiers":[
        {
            "category":"Health Services",
            "subcategory":"Clinic",
            "type":"Services"
        }
    ],
    "sg:phone":"+44 151 489 6136",
    "sg:postcode":"L36 7RT",
    "sg:province":"Merseyside",
    "sg:tags":[
        "nh"
    ],
    "wof:name":"Child Guidance Clinic",
    "wof:placetype":"venue"
},
  "geometry": {"coordinates":[-2.8344140053,53.4205665588],"type":"Point"}
}