{
  "type": "Feature",
  "properties": {
    "addr:full":"109 Duke St Barrow-in-furness Cumbria LA14 1RH",
    "addr:housenumber":"109",
    "addr:postcode":"la14 1rh",
    "addr:street":"Duke St",
    "iso:country":"GB",
    "sg:address":"109 Duke St",
    "sg:city":"Barrow-in-furness",
    "sg:classifiers":[
        {
            "category":"Bars & Pubs",
            "type":"Food & Drink"
        }
    ],
    "sg:postcode":"LA14 1RH",
    "sg:province":"Cumbria",
    "sg:tags":[
        "pubs",
        "inn"
    ],
    "wof:name":"Clarke,June,",
    "wof:placetype":"venue"
},
  "geometry": {"coordinates":[-3.23041,54.113346],"type":"Point"}
}