{
  "type": "Feature",
  "properties": {
    "addr:full":"Hallens Dr Wednesbury West Midlands WS10 7DD",
    "addr:postcode":"ws10 7dd",
    "addr:street":"Hallens Dr",
    "iso:country":"GB",
    "sg:address":"Hallens Dr",
    "sg:city":"Wednesbury",
    "sg:classifiers":[
        {
            "category":"Manufacturing",
            "subcategory":"Metals",
            "type":"Manufacturing & Wholesale Goods"
        }
    ],
    "sg:phone":"+44 121 607 7000",
    "sg:postcode":"WS10 7DD",
    "sg:province":"West Midlands",
    "sg:tags":[
        "steel",
        "stockholder"
    ],
    "wof:name":"Precision Steel Holdings Ltd",
    "wof:placetype":"venue"
},
  "geometry": {"coordinates":[-2.038217,52.554073],"type":"Point"}
}