{
  "type": "Feature",
  "properties": {
    "addr:full":"113 Monkton St Ramsgate Kent CT12 4JQ",
    "addr:housenumber":"113",
    "addr:postcode":"ct12 4jq",
    "addr:street":"Monkton St",
    "iso:country":"GB",
    "sg:address":"113 Monkton St",
    "sg:city":"Ramsgate",
    "sg:classifiers":[
        {
            "category":"Place Of Worship",
            "type":"Public Place"
        }
    ],
    "sg:phone":"+44 1843 602743",
    "sg:postcode":"CT12 4JQ",
    "sg:province":"Kent",
    "wof:name":"Monkton Methodist Church",
    "wof:placetype":"venue"
},
  "geometry": {"coordinates":[1.283755,51.338284],"type":"Point"}
}