{
  "type": "Feature",
  "properties": {
    "iso:country":"GB",
    "sg:address":"7 Piccadilly Arcade",
    "sg:city":"Stoke-on-trent",
    "sg:classifiers":[
        {
            "category":"Shopping",
            "subcategory":"Clothing, Apparel, & Fashions",
            "type":"Retail Goods"
        }
    ],
    "sg:phone":"+44 1782 206188",
    "sg:postcode":"ST1 1DL",
    "sg:province":"Staffordshire",
    "sg:tags":[
        "shop"
    ],
    "wof:name":"Kimberlies",
    "wof:placetype":"venue"
},
  "geometry": {"coordinates":[-2.1765370369,53.0255966187],"type":"Point"}
}