{
  "type": "Feature",
  "properties": {
    "iso:country":"GB",
    "sg:address":"14a Howe Street",
    "sg:city":"Edinburgh",
    "sg:classifiers":[
        {
            "category":"Professional",
            "subcategory":"Advertising",
            "type":"Services"
        }
    ],
    "sg:phone":"+44 131 226 2996",
    "sg:postcode":"EH3 6TD",
    "sg:province":"City of Edinburgh",
    "sg:tags":[
        "mail",
        "direct"
    ],
    "wof:name":"Berger & Co. Plc",
    "wof:placetype":"venue"
},
  "geometry": {"coordinates":[-3.202344,55.955883],"type":"Point"}
}