{
  "type": "Feature",
  "properties": {
    "iso:country":"GB",
    "sg:address":"Appointments, Ecton Brook Road",
    "sg:city":"Northampton",
    "sg:classifiers":[
        {
            "category":"Health Services",
            "subcategory":"Doctor",
            "type":"Services"
        }
    ],
    "sg:phone":"+44 1604 408657",
    "sg:postcode":"NN3 5EN",
    "sg:province":"Northamptonshire",
    "sg:tags":[
        "practitioners"
    ],
    "wof:name":"Brook Medical Centre",
    "wof:placetype":"venue"
},
  "geometry": {"coordinates":[-0.802394,52.254807],"type":"Point"}
}