{
  "type": "Feature",
  "properties": {
    "addr:full":"89 Southfield Av Paignton Devon TQ3 1LQ",
    "addr:housenumber":"89",
    "addr:postcode":"tq3 1lq",
    "addr:street":"Southfield Av",
    "iso:country":"GB",
    "sg:address":"89 Southfield Av",
    "sg:city":"Paignton",
    "sg:classifiers":[
        {
            "category":"Retail",
            "subcategory":"Driving School",
            "type":"Services"
        }
    ],
    "sg:phone":"+44 1803 522092",
    "sg:postcode":"TQ3 1LQ",
    "sg:province":"Devon",
    "wof:name":"Exeter In Torbay School Of Motoring",
    "wof:placetype":"venue"
},
  "geometry": {"coordinates":[-3.5760219097,50.444065094],"type":"Point"}
}