{
  "type": "Feature",
  "properties": {
    "addr:full":"Penybanc Farm, Abergwili Carmarthen Carmarthenshire SA31 2JH",
    "addr:postcode":"sa31 2jh",
    "iso:country":"GB",
    "sg:address":"Penybanc Farm, Abergwili",
    "sg:city":"Carmarthen",
    "sg:classifiers":[
        {
            "category":"Farming",
            "subcategory":"Livestock Farm",
            "type":"Manufacturing & Wholesale Goods"
        }
    ],
    "sg:phone":"+44 1267 231723",
    "sg:postcode":"SA31 2JH",
    "sg:province":"Carmarthenshire",
    "sg:tags":[
        "others"
    ],
    "wof:name":"I S M Lewis",
    "wof:placetype":"venue"
},
  "geometry": {"coordinates":[-4.270389,51.865952],"type":"Point"}
}