{
  "type": "Feature",
  "properties": {
    "addr:full":"205 East Lane Wembley Greater London HA0 3NG",
    "addr:housenumber":"205",
    "addr:postcode":"ha0 3ng",
    "addr:street":"East Lane",
    "iso:country":"GB",
    "sg:address":"205 East Lane",
    "sg:city":"Wembley",
    "sg:classifiers":[
        {
            "category":"Shopping",
            "subcategory":"Department Store",
            "type":"Retail Goods"
        }
    ],
    "sg:phone":"+44 20 8904 1715",
    "sg:postcode":"HA0 3NG",
    "sg:province":"Greater London",
    "wof:name":"Londis",
    "wof:placetype":"venue"
},
  "geometry": {"coordinates":[-0.3056690097,51.5624809265],"type":"Point"}
}