{
  "type": "Feature",
  "properties": {
    "addr:full":"Thame House, Thame Rd, Haddenham Aylesbury Buckinghamshire HP17 8BY",
    "addr:postcode":"hp17 8by",
    "addr:street":"Thame Rd",
    "iso:country":"GB",
    "sg:address":"Thame House, Thame Rd, Haddenham",
    "sg:city":"Aylesbury",
    "sg:classifiers":[
        {
            "category":"Professional",
            "type":"Services"
        }
    ],
    "sg:phone":"+44 870 162 2200",
    "sg:postcode":"HP17 8BY",
    "sg:province":"Buckinghamshire",
    "sg:tags":[
        "repair",
        "tech",
        "maintenance"
    ],
    "wof:name":"IT Solutions",
    "wof:placetype":"venue"
},
  "geometry": {"coordinates":[-0.9293730259,51.7735519409],"type":"Point"}
}