{
  "type": "Feature",
  "properties": {
    "iso:country":"GB",
    "sg:address":"57 Church Road",
    "sg:city":"Swansea",
    "sg:classifiers":[
        {
            "category":"Bars & Pubs",
            "type":"Food & Drink"
        }
    ],
    "sg:phone":"+44 1792 772263",
    "sg:postcode":"SA7 9RL",
    "sg:province":"Neath Port Talbot",
    "sg:tags":[
        "pubs",
        "inn"
    ],
    "wof:name":"Tomos Watkin Ltd.",
    "wof:placetype":"venue"
},
  "geometry": {"coordinates":[-3.9014480114,51.6630859375],"type":"Point"}
}