{
  "type": "Feature",
  "properties": {
    "addr:full":"Blackstoun Road Paisley Renfrewshire PA3 3AA",
    "addr:postcode":"pa3 3aa",
    "addr:street":"Blackstoun Road",
    "iso:country":"GB",
    "sg:address":"Blackstoun Road",
    "sg:city":"Paisley",
    "sg:classifiers":[
        {
            "category":"Arena",
            "subcategory":"Sports Club",
            "type":"Entertainment"
        }
    ],
    "sg:phone":"+44 141 889 7663",
    "sg:postcode":"PA3 3AA",
    "sg:province":"Renfrewshire",
    "wof:name":"Inkerman Bowling Club",
    "wof:placetype":"venue"
},
  "geometry": {"coordinates":[-4.4609098434,55.8573303223],"type":"Point"}
}