{
  "type": "Feature",
  "properties": {
    "iso:country":"GB",
    "sg:address":"Unit 1, Smithy Lane",
    "sg:city":"Lochgilphead",
    "sg:classifiers":[
        {
            "category":"Health Services",
            "subcategory":"Nursing And Care Facility",
            "type":"Services"
        }
    ],
    "sg:phone":"+44 1546 606775",
    "sg:postcode":"PA31 8TA",
    "sg:province":"Argyll and Bute",
    "sg:tags":[
        "home"
    ],
    "wof:name":"Bute Housing Association Ltd",
    "wof:placetype":"venue"
},
  "geometry": {"coordinates":[-5.485689,56.060951],"type":"Point"}
}