{
  "type": "Feature",
  "properties": {
    "addr:full":"43 Latimer Road Eastbourne East Sussex BN22 7DE",
    "addr:housenumber":"43",
    "addr:postcode":"bn22 7de",
    "addr:street":"Latimer Road",
    "iso:country":"GB",
    "sg:address":"43 Latimer Road",
    "sg:city":"Eastbourne",
    "sg:classifiers":[
        {
            "category":"Building & Trades",
            "subcategory":"Construction",
            "type":"Services"
        }
    ],
    "sg:postcode":"BN22 7DE",
    "sg:province":"East Sussex",
    "sg:tags":[
        "builder"
    ],
    "wof:name":"Aqua Plumbing & Heating Supplies",
    "wof:placetype":"venue"
},
  "geometry": {"coordinates":[0.2983579934,50.7744979858],"type":"Point"}
}