{
  "type": "Feature",
  "properties": {
    "addr:full":"15a Blythswood Square Glasgow Glasgow City G2 4BG",
    "addr:housenumber":"15a",
    "addr:postcode":"g2 4bg",
    "addr:street":"Blythswood Square",
    "iso:country":"GB",
    "sg:address":"15a Blythswood Square",
    "sg:city":"Glasgow",
    "sg:classifiers":[
        {
            "category":"Arts & Performance",
            "subcategory":"Art Gallery",
            "type":"Entertainment"
        }
    ],
    "sg:phone":"+44 141 221 6780",
    "sg:postcode":"G2 4BG",
    "sg:province":"Glasgow City",
    "wof:name":"William Hardie Ltd.",
    "wof:placetype":"venue"
},
  "geometry": {"coordinates":[-4.262996,55.862976],"type":"Point"}
}