{
  "type": "Feature",
  "properties": {
    "iso:country":"GB",
    "sg:address":"328 High Road, Billesdon",
    "sg:city":"London",
    "sg:classifiers":[
        {
            "category":"Recreation",
            "subcategory":"Gun Range",
            "type":"Entertainment"
        }
    ],
    "sg:postcode":"NW10 2EN",
    "sg:province":"Greater London",
    "sg:tags":[
        "operator",
        "tour"
    ],
    "wof:name":"Gold Chain Agency Ltd.",
    "wof:placetype":"venue"
},
  "geometry": {"coordinates":[-0.240493,51.548538],"type":"Point"}
}