{
  "type": "Feature",
  "properties": {
    "iso:country":"GB",
    "sg:address":"North East Centre, Flat 2 10 Petershill Court",
    "sg:city":"Glasgow",
    "sg:classifiers":[
        {
            "category":"Organizations",
            "subcategory":"Non-profit Organization",
            "type":"Services"
        }
    ],
    "sg:phone":"+44 141 557 1279",
    "sg:postcode":"G21 4PY",
    "sg:province":"East Dunbartonshire",
    "sg:tags":[
        "organisation",
        "voluntary",
        "charity"
    ],
    "wof:name":"British Red Cross",
    "wof:placetype":"venue"
},
  "geometry": {"coordinates":[-4.20789,55.881001],"type":"Point"}
}