{
  "type": "Feature",
  "properties": {
    "iso:country":"GB",
    "sg:address":"18-19 Princewood Road",
    "sg:city":"Corby",
    "sg:classifiers":[
        {
            "category":"Manufacturing",
            "subcategory":"Metals",
            "type":"Manufacturing & Wholesale Goods"
        }
    ],
    "sg:postcode":"NN17 4AP",
    "sg:province":"Northamptonshire",
    "sg:tags":[
        "fabricator",
        "aluminium",
        "mnfrs"
    ],
    "wof:name":"Aluminium Shapes Ltd.",
    "wof:placetype":"venue"
},
  "geometry": {"coordinates":[-0.69607,52.5131],"type":"Point"}
}