{
  "type": "Feature",
  "properties": {
    "addr:full":"Newark Rd, South Eastfield Ind Est Glenrothes Fife KY7 4NS",
    "addr:postcode":"ky7 4ns",
    "addr:street":"Newark Rd",
    "iso:country":"GB",
    "sg:address":"Newark Rd, South Eastfield Ind Est",
    "sg:city":"Glenrothes",
    "sg:classifiers":[
        {
            "category":"Home & Garden",
            "subcategory":"Building Materials",
            "type":"Retail Goods"
        }
    ],
    "sg:phone":"+44 1592 772828",
    "sg:postcode":"KY7 4NS",
    "sg:province":"Fife",
    "sg:tags":[
        "window",
        "frame"
    ],
    "wof:name":"Planet Windows Glenrothes",
    "wof:placetype":"venue"
},
  "geometry": {"coordinates":[-3.1417520046,56.1858482361],"type":"Point"}
}