{
  "type": "Feature",
  "properties": {
    "iso:country":"GB",
    "sg:address":"2 Upper Bilbohall",
    "sg:city":"Elgin",
    "sg:classifiers":[
        {
            "category":"Food & Beverages",
            "subcategory":"Meat & Fish",
            "type":"Retail Goods"
        }
    ],
    "sg:phone":"+44 1343 542904",
    "sg:postcode":"IV30 3RS",
    "sg:province":"Moray",
    "sg:tags":[
        "chip"
    ],
    "wof:name":"Adolfo Chip Bar",
    "wof:placetype":"venue"
},
  "geometry": {"coordinates":[-3.32902,57.625462],"type":"Point"}
}