{
  "type": "Feature",
  "properties": {
    "iso:country":"GB",
    "sg:address":"15 High St",
    "sg:city":"Newport",
    "sg:classifiers":[
        {
            "category":"Professional",
            "subcategory":"Printing & Photocopies",
            "type":"Services"
        }
    ],
    "sg:phone":"+44 1983 524080",
    "sg:postcode":"PO30 1SS",
    "sg:province":"Isle of Wight",
    "sg:tags":[
        "t-shirt"
    ],
    "wof:name":"Tease Shirt Ink",
    "wof:placetype":"venue"
},
  "geometry": {"coordinates":[-1.291525,50.700279],"type":"Point"}
}