{
  "type": "Feature",
  "properties": {
    "iso:country":"GB",
    "sg:address":"Gogar Station Road",
    "sg:city":"Edinburgh",
    "sg:classifiers":[
        {
            "category":"Arena",
            "subcategory":"Sports Club",
            "type":"Entertainment"
        }
    ],
    "sg:phone":"+44 131 339 1254",
    "sg:postcode":"EH12 9BS",
    "sg:province":"City of Edinburgh",
    "wof:name":"Gogar Park Curling Club Ltd.",
    "wof:placetype":"venue"
},
  "geometry": {"coordinates":[-3.3315041065,55.9376487732],"type":"Point"}
}