{
  "type": "Feature",
  "properties": {
    "addr:full":"199 Abbey Street Rugby Warwickshire CV21 3LW",
    "addr:housenumber":"199",
    "addr:postcode":"cv21 3lw",
    "addr:street":"Abbey Street",
    "iso:country":"GB",
    "sg:address":"199 Abbey Street",
    "sg:city":"Rugby",
    "sg:classifiers":[
        {
            "category":"Professional",
            "subcategory":"Testing Lab",
            "type":"Services"
        },
        {
            "category":"Retail",
            "subcategory":"Auto Repair",
            "type":"Services"
        }
    ],
    "sg:phone":"+44 1788 576456",
    "sg:postcode":"CV21 3LW",
    "sg:province":"Warwickshire",
    "sg:tags":[
        "car",
        "vehicle",
        "commercial",
        "mot"
    ],
    "wof:name":"Stanbridge Motors",
    "wof:placetype":"venue"
},
  "geometry": {"coordinates":[-1.242710948,52.3766822815],"type":"Point"}
}