{
  "type": "Feature",
  "properties": {
    "addr:full":"19 Birch Grn, Formby Liverpool Lancashire L37 1NG",
    "addr:housenumber":"19",
    "addr:postcode":"l37 1ng",
    "addr:street":"Birch Grn Formby",
    "iso:country":"GB",
    "sg:address":"19 Birch Grn, Formby",
    "sg:city":"Liverpool",
    "sg:classifiers":[
        {
            "category":"Sports & Exercise",
            "subcategory":"Golf",
            "type":"Entertainment"
        }
    ],
    "sg:postcode":"L37 1NG",
    "sg:province":"Lancashire",
    "sg:tags":[
        "club",
        "course"
    ],
    "wof:name":"Council of National Golf Unions(The)",
    "wof:placetype":"venue"
},
  "geometry": {"coordinates":[-3.079852,53.56377],"type":"Point"}
}