{
  "type": "Feature",
  "properties": {
    "addr:full":"Chapel Street, Devonport Plymouth Devon PL1 4DU",
    "addr:postcode":"pl1 4du",
    "addr:street":"Chapel Street",
    "iso:country":"GB",
    "sg:address":"Chapel Street, Devonport",
    "sg:city":"Plymouth",
    "sg:classifiers":[
        {
            "category":"Travel",
            "subcategory":"Hotels & Motels",
            "type":"Entertainment"
        }
    ],
    "sg:postcode":"PL1 4DU",
    "sg:province":"Devon",
    "wof:name":"Crown Hotel",
    "wof:placetype":"venue"
},
  "geometry": {"coordinates":[-4.176939,50.373169],"type":"Point"}
}