{
  "type": "Feature",
  "properties": {
    "addr:full":"7 Pavilion Road London Greater London SW1X 0HD",
    "addr:housenumber":"7",
    "addr:postcode":"sw1x 0hd",
    "addr:street":"Pavilion Road",
    "iso:country":"GB",
    "sg:address":"7 Pavilion Road",
    "sg:city":"London",
    "sg:classifiers":[
        {
            "category":"Shopping",
            "subcategory":"Baby Store",
            "type":"Retail Goods"
        }
    ],
    "sg:postcode":"SW1X 0HD",
    "sg:province":"Greater London",
    "sg:tags":[
        "babywear",
        "childrens"
    ],
    "wof:name":"Childrens Pavilion",
    "wof:placetype":"venue"
},
  "geometry": {"coordinates":[-0.160611,51.500629],"type":"Point"}
}