{
  "type": "Feature",
  "properties": {
    "addr:full":"21 Turnberry Pl Glasgow South Lanarkshire G75 8TB",
    "addr:housenumber":"21",
    "addr:postcode":"g75 8tb",
    "addr:street":"Turnberry Pl",
    "iso:country":"GB",
    "sg:address":"21 Turnberry Pl",
    "sg:city":"Glasgow",
    "sg:classifiers":[
        {
            "category":"Place Of Worship",
            "type":"Public Place"
        }
    ],
    "sg:phone":"+44 1355 242564",
    "sg:postcode":"G75 8TB",
    "sg:province":"South Lanarkshire",
    "wof:name":"Greenhills Parish Church",
    "wof:placetype":"venue"
},
  "geometry": {"coordinates":[-4.205203,55.746334],"type":"Point"}
}