{
  "type": "Feature",
  "properties": {
    "addr:full":"121 Peet Street Derby Derbyshire DE22 3RG",
    "addr:housenumber":"121",
    "addr:postcode":"de22 3rg",
    "addr:street":"Peet Street",
    "iso:country":"GB",
    "sg:address":"121 Peet Street",
    "sg:city":"Derby",
    "sg:classifiers":[
        {
            "category":"Shopping",
            "subcategory":"Clothing, Apparel, & Fashions",
            "type":"Retail Goods"
        }
    ],
    "sg:phone":"+44 1332 369230",
    "sg:postcode":"DE22 3RG",
    "sg:province":"Derbyshire",
    "sg:tags":[
        "clothing"
    ],
    "wof:name":"Just Jeans",
    "wof:placetype":"venue"
},
  "geometry": {"coordinates":[-1.490137,52.917442],"type":"Point"}
}