{
  "type": "Feature",
  "properties": {
    "addr:full":"2 Barrie Road, Hillington Industrial Estate Glasgow Glasgow City G52 4PX",
    "addr:housenumber":"2",
    "addr:postcode":"g52 4px",
    "addr:street":"Barrie Road;Industrial Estate",
    "iso:country":"GB",
    "sg:address":"2 Barrie Road, Hillington Industrial Estate",
    "sg:city":"Glasgow",
    "sg:classifiers":[
        {
            "category":"Professional",
            "subcategory":"Engineering",
            "type":"Services"
        }
    ],
    "sg:phone":"+44 141 882 5661",
    "sg:postcode":"G52 4PX",
    "sg:province":"Glasgow City",
    "sg:tags":[
        "contractor",
        "electrical",
        "engineer"
    ],
    "wof:name":"Ian Crichton (Electrical Engineers) Ltd.",
    "wof:placetype":"venue"
},
  "geometry": {"coordinates":[-4.3645730019,55.8577423096],"type":"Point"}
}