{
  "type": "Feature",
  "properties": {
    "iso:country":"GB",
    "sg:address":"65 Stonecot Hill",
    "sg:city":"Sutton",
    "sg:classifiers":[
        {
            "category":"Retail",
            "subcategory":"Auto Repair",
            "type":"Services"
        }
    ],
    "sg:postcode":"SM3 9HJ",
    "sg:province":"Surrey",
    "sg:tags":[
        "car",
        "upholsterer"
    ],
    "wof:name":"Stonecot Car Trimmers",
    "wof:placetype":"venue"
},
  "geometry": {"coordinates":[-0.2136369944,51.3836555481],"type":"Point"}
}