{
  "type": "Feature",
  "properties": {
    "iso:country":"GB",
    "sg:address":"5 Willowdale Gardens",
    "sg:city":"Glasgow",
    "sg:classifiers":[
        {
            "category":"Building & Trades",
            "subcategory":"Construction",
            "type":"Services"
        }
    ],
    "sg:phone":"+44 141 771 2009",
    "sg:postcode":"G69 7NW",
    "sg:province":"East Dunbartonshire",
    "sg:tags":[
        "builder"
    ],
    "wof:name":"Sherriff Land Consultants",
    "wof:placetype":"venue"
},
  "geometry": {"coordinates":[-4.077689,55.856258],"type":"Point"}
}