{
  "type": "Feature",
  "properties": {
    "addr:full":"46 Central Road Worcester Park Surrey KT4 8HY",
    "addr:housenumber":"46",
    "addr:postcode":"kt4 8hy",
    "addr:street":"Central Road",
    "iso:country":"GB",
    "sg:address":"46 Central Road",
    "sg:city":"Worcester Park",
    "sg:classifiers":[
        {
            "category":"Shopping",
            "subcategory":"Gifts & Souvenirs",
            "type":"Retail Goods"
        }
    ],
    "sg:phone":"+44 1932 589999",
    "sg:postcode":"KT4 8HY",
    "sg:province":"Surrey",
    "sg:tags":[
        "greeting",
        "card"
    ],
    "wof:name":"Frozen Image",
    "wof:placetype":"venue"
},
  "geometry": {"coordinates":[-0.2391629964,51.3775253296],"type":"Point"}
}