{
  "type": "Feature",
  "properties": {
    "addr:full":"23 Filey Street Sheffield South Yorkshire S10 2FG",
    "addr:housenumber":"23",
    "addr:postcode":"s10 2fg",
    "addr:street":"Filey Street",
    "iso:country":"GB",
    "sg:address":"23 Filey Street",
    "sg:city":"Sheffield",
    "sg:classifiers":[
        {
            "category":"Organizations",
            "subcategory":"Non-profit Organization",
            "type":"Services"
        }
    ],
    "sg:phone":"+44 114 279 6777",
    "sg:postcode":"S10 2FG",
    "sg:province":"South Yorkshire",
    "sg:tags":[
        "organisation",
        "voluntary",
        "charity"
    ],
    "wof:name":"Community Action Halfway Home Ltd.",
    "wof:placetype":"venue"
},
  "geometry": {"coordinates":[-1.4851770401,53.3779640198],"type":"Point"}
}