{
  "type": "Feature",
  "properties": {
    "addr:full":"28 Broad Street Bath Bath and North East Somerset BA1 5LW",
    "addr:housenumber":"28",
    "addr:postcode":"ba1 5lw",
    "addr:street":"Broad Street",
    "iso:country":"GB",
    "sg:address":"28 Broad Street",
    "sg:city":"Bath",
    "sg:classifiers":[
        {
            "category":"Shopping",
            "subcategory":"Clothing, Apparel, & Fashions",
            "type":"Retail Goods"
        }
    ],
    "sg:postcode":"BA1 5LW",
    "sg:province":"Bath and North East Somerset",
    "sg:tags":[
        "menswear"
    ],
    "wof:name":"Kitchi Gai",
    "wof:placetype":"venue"
},
  "geometry": {"coordinates":[-2.3603539467,51.3844413757],"type":"Point"}
}