{
  "type": "Feature",
  "properties": {
    "iso:country":"GB",
    "sg:address":"5 Winster Cres",
    "sg:city":"Melton Mowbray",
    "sg:classifiers":[
        {
            "category":"Professional",
            "subcategory":"Printing & Photocopies",
            "type":"Services"
        }
    ],
    "sg:postcode":"LE13 0EH",
    "sg:province":"Leicestershire",
    "sg:tags":[
        "trophy"
    ],
    "wof:name":"Squire Trophies",
    "wof:placetype":"venue"
},
  "geometry": {"coordinates":[-0.894967,52.7575],"type":"Point"}
}