{
  "type": "Feature",
  "properties": {
    "iso:country":"GB",
    "sg:address":"27 Arundel Close",
    "sg:city":"Dronfield",
    "sg:classifiers":[
        {
            "category":"Building & Trades",
            "subcategory":"Construction",
            "type":"Services"
        }
    ],
    "sg:phone":"+44 1246 416978",
    "sg:postcode":"S18 8QS",
    "sg:province":"Derbyshire",
    "sg:tags":[
        "window",
        "replacement"
    ],
    "wof:name":"Window Conservatory Fitting Services",
    "wof:placetype":"venue"
},
  "geometry": {"coordinates":[-1.4979809523,53.3005332947],"type":"Point"}
}