{
  "type": "Feature",
  "properties": {
    "addr:full":"Peregrine Way Bicester Oxfordshire OX26 6SX",
    "addr:postcode":"ox26 6sx",
    "addr:street":"Peregrine Way",
    "iso:country":"GB",
    "sg:address":"Peregrine Way",
    "sg:city":"Bicester",
    "sg:classifiers":[
        {
            "category":"Education",
            "subcategory":"School",
            "type":"Public Place"
        }
    ],
    "sg:phone":"+44 1869 369021",
    "sg:postcode":"OX26 6SX",
    "sg:province":"Oxfordshire",
    "sg:tags":[
        "local",
        "authority"
    ],
    "wof:name":"Langford Village County Primary School",
    "wof:placetype":"venue"
},
  "geometry": {"coordinates":[-1.1365540028,51.8921585083],"type":"Point"}
}