{
  "type": "Feature",
  "properties": {
    "addr:full":"Park Road Milnthorpe Cumbria LA7 7AD",
    "addr:postcode":"la7 7ad",
    "addr:street":"Park Road",
    "iso:country":"GB",
    "sg:address":"Park Road",
    "sg:city":"Milnthorpe",
    "sg:classifiers":[
        {
            "category":"Travel",
            "subcategory":"Hotels & Motels",
            "type":"Entertainment"
        }
    ],
    "sg:phone":"+44 15395 62115",
    "sg:postcode":"LA7 7AD",
    "sg:province":"Cumbria",
    "wof:name":"Cross Keys Hotel",
    "wof:placetype":"venue"
},
  "geometry": {"coordinates":[-2.773389,54.226845],"type":"Point"}
}