{
  "type": "Feature",
  "properties": {
    "iso:country":"GB",
    "sg:address":"Sefton House, 113 Tocceride Road",
    "sg:city":"High Wycombe",
    "sg:classifiers":[
        {
            "category":"Professional",
            "subcategory":"Lawyer & Legal Services",
            "type":"Services"
        }
    ],
    "sg:phone":"+44 1494 461361",
    "sg:postcode":"HP13 6EY",
    "sg:province":"Buckinghamshire",
    "sg:tags":[
        "advice",
        "counselling"
    ],
    "wof:name":"Addiction Counselling Trust",
    "wof:placetype":"venue"
},
  "geometry": {"coordinates":[-0.7477890253,51.628944397],"type":"Point"}
}