{
  "type": "Feature",
  "properties": {
    "addr:full":"Station Road, Brightons Falkirk Falkirk FK2 0TY",
    "addr:postcode":"fk2 0ty",
    "addr:street":"Station Road",
    "iso:country":"GB",
    "sg:address":"Station Road, Brightons",
    "sg:city":"Falkirk",
    "sg:classifiers":[
        {
            "category":"Building & Trades",
            "subcategory":"Cleaning & Sanitation",
            "type":"Services"
        }
    ],
    "sg:postcode":"FK2 0TY",
    "sg:province":"Falkirk",
    "sg:tags":[
        "dry",
        "control",
        "damp",
        "rot"
    ],
    "wof:name":"British Damp Proofing",
    "wof:placetype":"venue"
},
  "geometry": {"coordinates":[-3.71153,55.982517],"type":"Point"}
}