{
  "type": "Feature",
  "properties": {
    "iso:country":"GB",
    "sg:address":"48 Western Road",
    "sg:city":"Brentwood",
    "sg:classifiers":[
        {
            "category":"Professional",
            "subcategory":"Accounting & Tax Preparation",
            "type":"Services"
        }
    ],
    "sg:phone":"+44 1277 214479",
    "sg:postcode":"CM14 4SS",
    "sg:province":"Essex",
    "sg:tags":[
        "accountant",
        "activity"
    ],
    "wof:name":"Michael E Greene",
    "wof:placetype":"venue"
},
  "geometry": {"coordinates":[0.2989090085,51.6207695007],"type":"Point"}
}