{
  "type": "Feature",
  "properties": {
    "addr:full":"50 Whalley Road Accrington Lancashire BB5 1AR",
    "addr:housenumber":"50",
    "addr:postcode":"bb5 1ar",
    "addr:street":"Whalley Road",
    "iso:country":"GB",
    "sg:address":"50 Whalley Road",
    "sg:city":"Accrington",
    "sg:classifiers":[
        {
            "category":"Fast Food",
            "type":"Food & Drink"
        }
    ],
    "sg:phone":"+44 1254 385123",
    "sg:postcode":"BB5 1AR",
    "sg:province":"Lancashire",
    "sg:tags":[
        "away",
        "take"
    ],
    "wof:name":"Pizza Spot",
    "wof:placetype":"venue"
},
  "geometry": {"coordinates":[-2.3641130924,53.7554664612],"type":"Point"}
}