{
  "type": "Feature",
  "properties": {
    "addr:full":"Meadow Farm Lake Lane, Barnham Bognor Regis West Sussex PO22 0AE",
    "addr:postcode":"po22 0ae",
    "addr:street":"Meadow Farm Lake Lane",
    "iso:country":"GB",
    "sg:address":"Meadow Farm Lake Lane, Barnham",
    "sg:city":"Bognor Regis",
    "sg:classifiers":[
        {
            "category":"Farming",
            "subcategory":"Livestock Farm",
            "type":"Manufacturing & Wholesale Goods"
        }
    ],
    "sg:postcode":"PO22 0AE",
    "sg:province":"West Sussex",
    "sg:tags":[
        "others"
    ],
    "wof:name":"Hugh R Martin",
    "wof:placetype":"venue"
},
  "geometry": {"coordinates":[-0.6241639853,50.833278656],"type":"Point"}
}