{
  "type": "Feature",
  "properties": {
    "addr:full":"229 Northolt Road Harrow Greater London HA2 8HN",
    "addr:housenumber":"229",
    "addr:postcode":"ha2 8hn",
    "addr:street":"Northolt Road",
    "iso:country":"GB",
    "sg:address":"229 Northolt Road",
    "sg:city":"Harrow",
    "sg:classifiers":[
        {
            "category":"Restaurant",
            "type":"Food & Drink"
        }
    ],
    "sg:phone":"+44 20 8422 2857",
    "sg:postcode":"HA2 8HN",
    "sg:province":"Greater London",
    "wof:name":"Wimpy International Ltd.",
    "wof:placetype":"venue"
},
  "geometry": {"coordinates":[-0.3528009951,51.5646705627],"type":"Point"}
}