{
  "type": "Feature",
  "properties": {
    "addr:full":"Pontardawe Health Centre, Tawe Terrace, Pontardawe Swansea Neath Port Talbot SA8 4HA",
    "addr:postcode":"sa8 4ha",
    "addr:street":"Tawe Terrace",
    "iso:country":"GB",
    "sg:address":"Pontardawe Health Centre, Tawe Terrace, Pontardawe",
    "sg:city":"Swansea",
    "sg:classifiers":[
        {
            "category":"Health Services",
            "subcategory":"Clinic",
            "type":"Services"
        }
    ],
    "sg:phone":"+44 1792 862643",
    "sg:postcode":"SA8 4HA",
    "sg:province":"Neath Port Talbot",
    "sg:tags":[
        "private"
    ],
    "wof:name":"Pontardawe Dental & Chiropody Clinic",
    "wof:placetype":"venue"
},
  "geometry": {"coordinates":[-3.849665,51.71896],"type":"Point"}
}