{
  "type": "Feature",
  "properties": {
    "addr:full":"4 Thompsons Buildings, Philadelphia Houghton-le-spring Durham DH4 4JF",
    "addr:housenumber":"4;houghton-le-spring",
    "addr:postcode":"dh4 4jf",
    "addr:street":"Thompsons Buildings",
    "iso:country":"GB",
    "sg:address":"4 Thompsons Buildings, Philadelphia",
    "sg:city":"Houghton-le-spring",
    "sg:classifiers":[
        {
            "category":"Food & Beverages",
            "subcategory":"Meat & Fish",
            "type":"Retail Goods"
        }
    ],
    "sg:phone":"+44 191 584 3148",
    "sg:postcode":"DH4 4JF",
    "sg:province":"Durham",
    "sg:tags":[
        "butcher"
    ],
    "wof:name":"J W Stewart Butchers",
    "wof:placetype":"venue"
},
  "geometry": {"coordinates":[-1.4827799797,54.8644714355],"type":"Point"}
}