{
  "type": "Feature",
  "properties": {
    "addr:full":"16 Grafton Centre Cambridge Cambridgeshire CB1 1PS",
    "addr:housenumber":"16",
    "addr:postcode":"cb1 1ps",
    "addr:street":"Grafton Centre",
    "iso:country":"GB",
    "sg:address":"16 Grafton Centre",
    "sg:city":"Cambridge",
    "sg:classifiers":[
        {
            "category":"Banks & Credit Unions",
            "subcategory":"Financial Services",
            "type":"Services"
        }
    ],
    "sg:phone":"+44 1223 727851",
    "sg:postcode":"CB1 1PS",
    "sg:province":"Cambridgeshire",
    "sg:tags":[
        "building",
        "society"
    ],
    "wof:name":"Cambridge Building Society",
    "wof:placetype":"venue"
},
  "geometry": {"coordinates":[0.1317159981,52.2054786682],"type":"Point"}
}