{
  "type": "Feature",
  "properties": {
    "addr:full":"North Road, Broadwell Coleford Gloucestershire GL16 7BG",
    "addr:postcode":"gl16 7bg",
    "addr:street":"North Road",
    "iso:country":"GB",
    "sg:address":"North Road, Broadwell",
    "sg:city":"Coleford",
    "sg:classifiers":[
        {
            "category":"Organizations",
            "subcategory":"Community Association",
            "type":"Services"
        },
        {
            "category":"Organizations",
            "subcategory":"Membership Organization",
            "type":"Services"
        }
    ],
    "sg:phone":"+44 1594 833425",
    "sg:postcode":"GL16 7BG",
    "sg:province":"Gloucestershire",
    "sg:tags":[
        "club",
        "social"
    ],
    "wof:name":"BROADWELL & DISTRICT EX-SERVICE & WORKING MEN'S CLUB & INSTITUTE LTD",
    "wof:placetype":"venue"
},
  "geometry": {"coordinates":[-2.6040890217,51.79139328],"type":"Point"}
}