{
  "type": "Feature",
  "properties": {
    "iso:country":"GB",
    "sg:address":"Abbey House, Lincoln Road, Cressex Industrial Estate",
    "sg:city":"High Wycombe",
    "sg:classifiers":[
        {
            "category":"Home & Garden",
            "subcategory":"Kitchen Supply",
            "type":"Retail Goods"
        }
    ],
    "sg:phone":"+44 1494 450001",
    "sg:postcode":"HP12 3RD",
    "sg:province":"Buckinghamshire",
    "sg:tags":[
        "equipment",
        "catering"
    ],
    "wof:name":"Wings Catering Equipment Ltd.",
    "wof:placetype":"venue"
},
  "geometry": {"coordinates":[-0.772314,51.622009],"type":"Point"}
}