{
  "type": "Feature",
  "properties": {
    "iso:country":"GB",
    "sg:address":"10 Station Road",
    "sg:city":"Bognor Regis",
    "sg:classifiers":[
        {
            "category":"Retail",
            "subcategory":"Photofinishing",
            "type":"Services"
        },
        {
            "category":"Professional",
            "subcategory":"Art Services",
            "type":"Services"
        }
    ],
    "sg:phone":"+44 1243 829371",
    "sg:postcode":"PO21 1QE",
    "sg:province":"West Sussex",
    "sg:tags":[
        "picture",
        "processing",
        "photographic",
        "framing",
        "processor"
    ],
    "wof:name":"Fotos & Frames",
    "wof:placetype":"venue"
},
  "geometry": {"coordinates":[-0.675224,50.785801],"type":"Point"}
}