{
  "type": "Feature",
  "properties": {
    "iso:country":"GB",
    "sg:address":"Roxy Cinema, Hollins Road, Hollinwood",
    "sg:city":"Oldham",
    "sg:classifiers":[
        {
            "category":"Cinema",
            "subcategory":"Movie Theater",
            "type":"Entertainment"
        }
    ],
    "sg:phone":"+44 161 681 6250",
    "sg:postcode":"OL8 3QX",
    "sg:province":"Lancashire",
    "wof:name":"Verona Cinema (Guide Bridge) Ltd.",
    "wof:placetype":"venue"
},
  "geometry": {"coordinates":[-2.1446,53.518799],"type":"Point"}
}