{
  "type": "Feature",
  "properties": {
    "addr:full":"Tanhouse Industrial Estate, Dennis Road Widnes Cheshire WA8 0YQ",
    "addr:housenumber":"estate",
    "addr:postcode":"wa8 0yq",
    "addr:street":"Tanhouse Industrial;Dennis Road",
    "iso:country":"GB",
    "sg:address":"Tanhouse Industrial Estate, Dennis Road",
    "sg:city":"Widnes",
    "sg:classifiers":[
        {
            "category":"Building & Trades",
            "subcategory":"Construction",
            "type":"Services"
        }
    ],
    "sg:phone":"+44 151 420 2051",
    "sg:postcode":"WA8 0YQ",
    "sg:province":"Cheshire",
    "sg:tags":[
        "contractor"
    ],
    "wof:name":"Longboat Engineering Ltd.",
    "wof:placetype":"venue"
},
  "geometry": {"coordinates":[-2.734285,53.355553],"type":"Point"}
}