{
  "type": "Feature",
  "properties": {
    "addr:full":"Cornfield Lane Eastbourne East Sussex BN21 4NG",
    "addr:postcode":"bn21 4ng",
    "addr:street":"Cornfield Lane",
    "iso:country":"GB",
    "sg:address":"Cornfield Lane",
    "sg:city":"Eastbourne",
    "sg:classifiers":[
        {
            "category":"Place Of Worship",
            "type":"Public Place"
        }
    ],
    "sg:phone":"+44 1323 722168",
    "sg:postcode":"BN21 4NG",
    "sg:province":"East Sussex",
    "wof:name":"St.Andrews United Reformed Church",
    "wof:placetype":"venue"
},
  "geometry": {"coordinates":[0.284775,50.765476],"type":"Point"}
}