{
  "type": "Feature",
  "properties": {
    "addr:full":"Unit 1/2, Letts Road, Rothersthorpe Avenue Industrial Northampton Northamptonshire NN4 8HQ",
    "addr:housenumber":"unit 1 / 2",
    "addr:postcode":"nn4 8hq",
    "addr:street":"Letts Road Rothersthorpe Avenue Industrial",
    "iso:country":"GB",
    "sg:address":"Unit 1/2, Letts Road, Rothersthorpe Avenue Industrial",
    "sg:city":"Northampton",
    "sg:classifiers":[
        {
            "category":"Manufacturing",
            "subcategory":"Electronics",
            "type":"Manufacturing & Wholesale Goods"
        },
        {
            "category":"Banks & Credit Unions",
            "subcategory":"Atm",
            "type":"Services"
        }
    ],
    "sg:phone":"+44 1604 764520",
    "sg:postcode":"NN4 8HQ",
    "sg:province":"Northamptonshire",
    "sg:tags":[
        "computer",
        "-",
        "printed",
        "circuit",
        "integrated"
    ],
    "wof:name":"Product Support Electronics Ltd.",
    "wof:placetype":"venue"
},
  "geometry": {"coordinates":[-0.9078140259,52.2276191711],"type":"Point"}
}