{
  "type": "Feature",
  "properties": {
    "iso:country":"GB",
    "sg:address":"56 Castleford Road",
    "sg:city":"Normanton",
    "sg:classifiers":[
        {
            "category":"Military Area",
            "subcategory":"Air Force Base",
            "type":"Public Place"
        }
    ],
    "sg:phone":"+44 1924 897193",
    "sg:postcode":"WF6 2EE",
    "sg:province":"West Yorkshire",
    "sg:tags":[
        "taxi",
        "hire",
        "private"
    ],
    "wof:name":"Phillips Travel",
    "wof:placetype":"venue"
},
  "geometry": {"coordinates":[-1.4128479958,53.7006492615],"type":"Point"}
}