{
  "type": "Feature",
  "properties": {
    "addr:full":"Unit 6, Claremont Way Industrial Estate, Claremont Way London Greater London NW2 1BG",
    "addr:housenumber":"unit 6;estate",
    "addr:postcode":"nw2 1bg",
    "addr:street":"Claremont Way Industrial;Claremont Way",
    "iso:country":"GB",
    "sg:address":"Unit 6, Claremont Way Industrial Estate, Claremont Way",
    "sg:city":"London",
    "sg:classifiers":[
        {
            "category":"Manufacturing",
            "subcategory":"Metals",
            "type":"Manufacturing & Wholesale Goods"
        },
        {
            "category":"Wholesale",
            "subcategory":"Scrap",
            "type":"Manufacturing & Wholesale Goods"
        }
    ],
    "sg:phone":"+44 20 8458 0581",
    "sg:postcode":"NW2 1BG",
    "sg:province":"Greater London",
    "sg:tags":[
        "waste"
    ],
    "wof:name":"Acre Metals Ltd",
    "wof:placetype":"venue"
},
  "geometry": {"coordinates":[-0.2223609984,51.5710716248],"type":"Point"}
}