{
  "type": "Feature",
  "properties": {
    "addr:full":"10 Market Hill, Rothwell Kettering Northamptonshire NN14 6EP",
    "addr:housenumber":"10",
    "addr:postcode":"nn14 6ep",
    "addr:street":"Market Hill",
    "iso:country":"GB",
    "sg:address":"10 Market Hill, Rothwell",
    "sg:city":"Kettering",
    "sg:classifiers":[
        {
            "category":"Food & Beverages",
            "subcategory":"Fruits & Vegetables",
            "type":"Retail Goods"
        }
    ],
    "sg:phone":"+44 1536 711822",
    "sg:postcode":"NN14 6EP",
    "sg:province":"Northamptonshire",
    "sg:tags":[
        "greengrocer"
    ],
    "wof:name":"Allen's Green Grocery",
    "wof:placetype":"venue"
},
  "geometry": {"coordinates":[-0.799905,52.422821],"type":"Point"}
}