{
  "type": "Feature",
  "properties": {
    "iso:country":"GB",
    "sg:address":"38 New City Road",
    "sg:city":"Glasgow",
    "sg:classifiers":[
        {
            "category":"Real Estate",
            "subcategory":"Real Estate Operator",
            "type":"Services"
        },
        {
            "category":"Building & Trades",
            "subcategory":"Cleaning & Sanitation",
            "type":"Services"
        },
        {
            "category":"Professional",
            "subcategory":"Engineering",
            "type":"Services"
        }
    ],
    "sg:phone":"+44 141 353 2444",
    "sg:postcode":"G4 9JT",
    "sg:province":"Glasgow City",
    "sg:tags":[
        "engineer",
        "consulting",
        "property",
        "leasing",
        "facility"
    ],
    "wof:name":"HENDERSON WARNOCK FACILITIES MANAGEMENT LTD",
    "wof:placetype":"venue"
},
  "geometry": {"coordinates":[-4.260816,55.868767],"type":"Point"}
}