{
  "type": "Feature",
  "properties": {
    "iso:country":"GB",
    "sg:address":"1 Albert St",
    "sg:city":"Fleetwood",
    "sg:classifiers":[
        {
            "category":"Retail",
            "subcategory":"Laundry & Dry Cleaning",
            "type":"Services"
        }
    ],
    "sg:phone":"+44 1253 873317",
    "sg:postcode":"FY7 6AH",
    "sg:province":"Lancashire",
    "sg:tags":[
        "launderette"
    ],
    "wof:name":"Star Laundry Services Ltd",
    "wof:placetype":"venue"
},
  "geometry": {"coordinates":[-3.0074689388,53.9230804443],"type":"Point"}
}