{
  "type": "Feature",
  "properties": {
    "addr:full":"131a Swift Road Southampton Hampshire SO19 9ES",
    "addr:housenumber":"131a",
    "addr:postcode":"so19 9es",
    "addr:street":"Swift Road",
    "iso:country":"GB",
    "sg:address":"131a Swift Road",
    "sg:city":"Southampton",
    "sg:classifiers":[
        {
            "category":"Social Services",
            "subcategory":"Retirement Home",
            "type":"Services"
        }
    ],
    "sg:postcode":"SO19 9ES",
    "sg:province":"Hampshire",
    "sg:tags":[
        "residential",
        "care"
    ],
    "wof:name":"Rosina Cottage",
    "wof:placetype":"venue"
},
  "geometry": {"coordinates":[-1.372239,50.892799],"type":"Point"}
}