{
  "type": "Feature",
  "properties": {
    "iso:country":"GB",
    "sg:address":"1 Aberderfyn Rd, Ponciau",
    "sg:city":"Wrexham",
    "sg:classifiers":[
        {
            "category":"Shopping",
            "subcategory":"Computers & Home Electronics",
            "type":"Retail Goods"
        }
    ],
    "sg:postcode":"LL14 1SL",
    "sg:province":"Wrexham",
    "sg:tags":[
        "aerial",
        "television",
        "radio"
    ],
    "wof:name":"A.S.A.T.",
    "wof:placetype":"venue"
},
  "geometry": {"coordinates":[-3.0483551025,53.0120735168],"type":"Point"}
}