{
  "type": "Feature",
  "properties": {
    "addr:full":"44 Kensington Road, Selly Park Birmingham West Midlands B29 7LW",
    "addr:housenumber":"44",
    "addr:postcode":"b29 7lw",
    "addr:street":"Kensington Road",
    "iso:country":"GB",
    "sg:address":"44 Kensington Road, Selly Park",
    "sg:city":"Birmingham",
    "sg:classifiers":[
        {
            "category":"Retail",
            "subcategory":"Driving School",
            "type":"Services"
        }
    ],
    "sg:phone":"+44 121 472 2634",
    "sg:postcode":"B29 7LW",
    "sg:province":"West Midlands",
    "wof:name":"The Advantage School of Motoring",
    "wof:placetype":"venue"
},
  "geometry": {"coordinates":[-1.920930028,52.4407424927],"type":"Point"}
}