{
  "type": "Feature",
  "properties": {
    "addr:full":"19-21 Mesnes Street Wigan Lancashire WN1 2DG",
    "addr:housenumber":"19-21",
    "addr:postcode":"wn1 2dg",
    "addr:street":"Mesnes Street",
    "iso:country":"GB",
    "sg:address":"19-21 Mesnes Street",
    "sg:city":"Wigan",
    "sg:classifiers":[
        {
            "category":"Food & Beverages",
            "subcategory":"Bakery",
            "type":"Retail Goods"
        }
    ],
    "sg:phone":"+44 1942 242116",
    "sg:postcode":"WN1 2DG",
    "sg:province":"Lancashire",
    "sg:tags":[
        "baker"
    ],
    "wof:name":"Greenhalgh's Craft Bakery Ltd.",
    "wof:placetype":"venue"
},
  "geometry": {"coordinates":[-2.6341700554,53.5565261841],"type":"Point"}
}