{
  "type": "Feature",
  "properties": {
    "addr:full":"1 Foysters Hall Cottage, Monks Eleigh Ipswich Suffolk IP7 7AX",
    "addr:housenumber":"1;hall",
    "addr:postcode":"ip7 7ax",
    "addr:street":"Foysters",
    "iso:country":"GB",
    "sg:address":"1 Foysters Hall Cottage, Monks Eleigh",
    "sg:city":"Ipswich",
    "sg:classifiers":[
        {
            "category":"Farming",
            "subcategory":"Farm",
            "type":"Manufacturing & Wholesale Goods"
        }
    ],
    "sg:phone":"+44 1449 741667",
    "sg:postcode":"IP7 7AX",
    "sg:province":"Suffolk",
    "sg:tags":[
        "mixed",
        "crop"
    ],
    "wof:name":"Strutt & Parker Farms",
    "wof:placetype":"venue"
},
  "geometry": {"coordinates":[0.8764500022,52.0918312073],"type":"Point"}
}