{
  "type": "Feature",
  "properties": {
    "addr:full":"The Manse, High Oak Road Ware Hertfordshire SG12 7PD",
    "addr:postcode":"sg12 7pd",
    "addr:street":"High Oak Road Ware",
    "iso:country":"GB",
    "sg:address":"The Manse, High Oak Road",
    "sg:city":"Ware",
    "sg:classifiers":[
        {
            "category":"Building & Trades",
            "subcategory":"Plumbing",
            "type":"Services"
        }
    ],
    "sg:phone":"+44 1920 465761",
    "sg:postcode":"SG12 7PD",
    "sg:province":"Hertfordshire",
    "sg:tags":[
        "central",
        "heating"
    ],
    "wof:name":"Anthony John Aldridge",
    "wof:placetype":"venue"
},
  "geometry": {"coordinates":[0.0240390003,51.8215560913],"type":"Point"}
}