{
  "type": "Feature",
  "properties": {
    "addr:full":"23 Middleburg Sq Folkestone Kent CT20 1BL",
    "addr:housenumber":"23",
    "addr:postcode":"ct20 1bl",
    "addr:street":"Middleburg Sq",
    "iso:country":"GB",
    "sg:address":"23 Middleburg Sq",
    "sg:city":"Folkestone",
    "sg:classifiers":[
        {
            "category":"Travel",
            "subcategory":"Hotels & Motels",
            "type":"Entertainment"
        }
    ],
    "sg:postcode":"CT20 1BL",
    "sg:province":"Kent",
    "wof:name":"Bumstead",
    "wof:placetype":"venue"
},
  "geometry": {"coordinates":[1.177945,51.084431],"type":"Point"}
}