{
  "type": "Feature",
  "properties": {
    "addr:full":"9 Christchurch Road Norwich Norfolk NR2 2AE",
    "addr:housenumber":"9",
    "addr:postcode":"nr2 2ae",
    "addr:street":"Christchurch Road Norwich Norfolk",
    "iso:country":"GB",
    "sg:address":"9 Christchurch Road",
    "sg:city":"Norwich",
    "sg:classifiers":[
        {
            "category":"Real Estate",
            "subcategory":"Developer",
            "type":"Services"
        }
    ],
    "sg:phone":"+44 1603 821020",
    "sg:postcode":"NR2 2AE",
    "sg:province":"Norfolk",
    "sg:tags":[
        "property"
    ],
    "wof:name":"Dune Properties Ltd",
    "wof:placetype":"venue"
},
  "geometry": {"coordinates":[1.272832036,52.6193084717],"type":"Point"}
}