{
  "type": "Feature",
  "properties": {
    "addr:full":"3 King George Way Renfrew Renfrewshire PA4 0AY",
    "addr:housenumber":"3",
    "addr:postcode":"pa4 0ay",
    "addr:street":"King George Way",
    "iso:country":"GB",
    "sg:address":"3 King George Way",
    "sg:city":"Renfrew",
    "sg:classifiers":[
        {
            "category":"Communications",
            "subcategory":"Film & Video Production",
            "type":"Services"
        }
    ],
    "sg:phone":"+44 141 885 1292",
    "sg:postcode":"PA4 0AY",
    "sg:province":"Renfrewshire",
    "sg:tags":[
        "tv",
        "radio"
    ],
    "wof:name":"Strathclyde Aerials & Communication Services",
    "wof:placetype":"venue"
},
  "geometry": {"coordinates":[-4.3806219101,55.8684272766],"type":"Point"}
}