{
  "type": "Feature",
  "properties": {
    "addr:full":"19 Aigurth Road Liverpool Merseyside L19 9BN",
    "addr:housenumber":"19",
    "addr:postcode":"l19 9bn",
    "addr:street":"Aigurth Road",
    "iso:country":"GB",
    "sg:address":"19 Aigurth Road",
    "sg:city":"Liverpool",
    "sg:classifiers":[
        {
            "category":"Organizations",
            "subcategory":"Non-profit Organization",
            "type":"Services"
        }
    ],
    "sg:phone":"+44 151 427 6779",
    "sg:postcode":"L19 9BN",
    "sg:province":"Merseyside",
    "sg:tags":[
        "charitable",
        "organisation",
        "voluntary",
        "charity"
    ],
    "wof:name":"The Richmond Fellowship For Community Mental Health",
    "wof:placetype":"venue"
},
  "geometry": {"coordinates":[-2.913453,53.366161],"type":"Point"}
}