{
  "type": "Feature",
  "properties": {
    "iso:country":"GB",
    "sg:address":"143 Rookwood Avenue",
    "sg:city":"Leeds",
    "sg:classifiers":[
        {
            "category":"Health Services",
            "subcategory":"Doctor",
            "type":"Services"
        }
    ],
    "sg:phone":"+44 113 249 3011",
    "sg:postcode":"LS9 0NL",
    "sg:province":"West Yorkshire",
    "sg:tags":[
        "practitioners"
    ],
    "wof:name":"Drs Setia & Leybourne",
    "wof:placetype":"venue"
},
  "geometry": {"coordinates":[-1.487763,53.801498],"type":"Point"}
}