{
  "type": "Feature",
  "properties": {
    "iso:country":"GB",
    "sg:address":"Unit J, Edison Court Yard, Brunel Rd, Earlstree Ind Est",
    "sg:city":"Corby",
    "sg:classifiers":[
        {
            "category":"Government",
            "subcategory":"Post Office",
            "type":"Public Place"
        }
    ],
    "sg:phone":"+44 1536 269172",
    "sg:postcode":"NN17 4LS",
    "sg:province":"Northamptonshire",
    "sg:tags":[
        "messenger",
        "courier"
    ],
    "wof:name":"Speedtrak",
    "wof:placetype":"venue"
},
  "geometry": {"coordinates":[-0.685317,52.508751],"type":"Point"}
}