{
  "type": "Feature",
  "properties": {
    "addr:full":"35 Tallon Road, Hutton Brentwood Essex CM13 1TE",
    "addr:housenumber":"35",
    "addr:postcode":"cm13 1te",
    "addr:street":"Tallon Road Hutton",
    "iso:country":"GB",
    "sg:address":"35 Tallon Road, Hutton",
    "sg:city":"Brentwood",
    "sg:classifiers":[
        {
            "category":"Home & Garden",
            "subcategory":"Home Furnishings",
            "type":"Retail Goods"
        }
    ],
    "sg:postcode":"CM13 1TE",
    "sg:province":"Essex",
    "sg:tags":[
        "furnishers",
        "planner",
        "bedroom"
    ],
    "wof:name":"Malcolm Harrison",
    "wof:placetype":"venue"
},
  "geometry": {"coordinates":[0.354414,51.638241],"type":"Point"}
}