{
  "type": "Feature",
  "properties": {
    "addr:full":"354 Sea Front Road Hayling Island Hampshire PO11 0BA",
    "addr:housenumber":"354",
    "addr:postcode":"po11 0ba",
    "addr:street":"Sea Front Road",
    "iso:country":"GB",
    "sg:address":"354 Sea Front Road",
    "sg:city":"Hayling Island",
    "sg:classifiers":[
        {
            "category":"Health Services",
            "subcategory":"Nursing And Care Facility",
            "type":"Services"
        },
        {
            "category":"Social Services",
            "subcategory":"Retirement Home",
            "type":"Services"
        }
    ],
    "sg:phone":"+44 23 9246 6411",
    "sg:postcode":"PO11 0BA",
    "sg:province":"Hampshire",
    "sg:tags":[
        "residential",
        "rest"
    ],
    "wof:name":"Gorseway Care Ltd",
    "wof:placetype":"venue"
},
  "geometry": {"coordinates":[-0.999016,50.787312],"type":"Point"}
}