{
  "type": "Feature",
  "properties": {
    "addr:full":"Birkholme Stable, Lower Hampton Road Sunbury-on-thames Surrey TW16 5PR",
    "addr:postcode":"tw16 5pr",
    "addr:street":"Lower Hampton Road",
    "iso:country":"GB",
    "sg:address":"Birkholme Stable, Lower Hampton Road",
    "sg:city":"Sunbury-on-thames",
    "sg:classifiers":[
        {
            "category":"Retail",
            "subcategory":"Auto Repair",
            "type":"Services"
        }
    ],
    "sg:postcode":"TW16 5PR",
    "sg:province":"Surrey",
    "sg:tags":[
        "modification",
        "garage"
    ],
    "wof:name":"G P Car Mobile Repairs",
    "wof:placetype":"venue"
},
  "geometry": {"coordinates":[-0.4117690027,51.4041786194],"type":"Point"}
}