{
  "type": "Feature",
  "properties": {
    "iso:country":"GB",
    "sg:address":"53 London Road",
    "sg:city":"Morden",
    "sg:classifiers":[
        {
            "category":"Fast Food",
            "type":"Food & Drink"
        }
    ],
    "sg:phone":"+44 20 8646 5926",
    "sg:postcode":"SM4 5HT",
    "sg:province":"Surrey",
    "sg:tags":[
        "away",
        "take"
    ],
    "wof:name":"The Sandwich Bar",
    "wof:placetype":"venue"
},
  "geometry": {"coordinates":[-0.1938609928,51.4021682739],"type":"Point"}
}