{
  "type": "Feature",
  "properties": {
    "addr:full":"Orchard House, Irthlingborough Wellingborough Northamptonshire NN9 5DB",
    "addr:postcode":"nn9 5db",
    "iso:country":"GB",
    "sg:address":"Orchard House, Irthlingborough",
    "sg:city":"Wellingborough",
    "sg:classifiers":[
        {
            "category":"Manufacturing",
            "subcategory":"Wood Products",
            "type":"Manufacturing & Wholesale Goods"
        },
        {
            "category":"Manufacturing",
            "subcategory":"Food",
            "type":"Manufacturing & Wholesale Goods"
        }
    ],
    "sg:postcode":"NN9 5DB",
    "sg:province":"Northamptonshire",
    "sg:tags":[
        "packaging",
        "crate",
        "pallets",
        "manufacturer"
    ],
    "wof:name":"Trent Foods Ltd.",
    "wof:placetype":"venue"
},
  "geometry": {"coordinates":[-0.614834,52.3251],"type":"Point"}
}