{
  "type": "Feature",
  "properties": {
    "iso:country":"GB",
    "sg:address":"2 Keswick Rd",
    "sg:city":"Putney",
    "sg:classifiers":[
        {
            "category":"Home & Garden",
            "subcategory":"Home Furnishings",
            "type":"Retail Goods"
        }
    ],
    "sg:phone":"+44 20 8875 1611",
    "sg:postcode":"SW15 2JL",
    "sg:province":"Greater London",
    "sg:tags":[
        "awning",
        "canopy",
        "blinds"
    ],
    "wof:name":"Inside Out",
    "wof:placetype":"venue"
},
  "geometry": {"coordinates":[-0.2091699988,51.4587783813],"type":"Point"}
}