{
  "type": "Feature",
  "properties": {
    "iso:country":"GB",
    "sg:address":"Togston East Farm House, Radcliffe",
    "sg:city":"Morpeth",
    "sg:classifiers":[
        {
            "category":"Farming",
            "subcategory":"Farm",
            "type":"Manufacturing & Wholesale Goods"
        }
    ],
    "sg:postcode":"NE65 0HT",
    "sg:province":"Northumberland",
    "sg:tags":[
        "mixed",
        "crop"
    ],
    "wof:name":"Nigel J Forsyth & Sons",
    "wof:placetype":"venue"
},
  "geometry": {"coordinates":[-1.579494,55.314232],"type":"Point"}
}