{
  "type": "Feature",
  "properties": {
    "addr:full":"Unit 9, Acorn Farm, Cublington Road Leighton Buzzard Bedfordshire LU7 0LB",
    "addr:housenumber":"unit 9 acorn farm",
    "addr:postcode":"lu7 0lb",
    "addr:street":"Cublington Road",
    "iso:country":"GB",
    "sg:address":"Unit 9, Acorn Farm, Cublington Road",
    "sg:city":"Leighton Buzzard",
    "sg:classifiers":[
        {
            "category":"Home & Garden",
            "subcategory":"Furniture",
            "type":"Retail Goods"
        }
    ],
    "sg:phone":"+44 1296 681853",
    "sg:postcode":"LU7 0LB",
    "sg:province":"Bedfordshire",
    "wof:name":"Stewkley Pine Cane & Oak",
    "wof:placetype":"venue"
},
  "geometry": {"coordinates":[-0.663909,51.917351],"type":"Point"}
}