{
  "type": "Feature",
  "properties": {
    "addr:full":"Penybont Guest House, Amroth Road, Llanteg Narberth Carmarthenshire SA67 8QL",
    "addr:postcode":"sa67 8ql",
    "addr:street":"Amroth Road",
    "iso:country":"GB",
    "sg:address":"Penybont Guest House, Amroth Road, Llanteg",
    "sg:city":"Narberth",
    "sg:classifiers":[
        {
            "category":"Travel",
            "subcategory":"Hotels & Motels",
            "type":"Entertainment"
        }
    ],
    "sg:phone":"+44 1834 831648",
    "sg:postcode":"SA67 8QL",
    "sg:province":"Carmarthenshire",
    "sg:tags":[
        "house",
        "guest"
    ],
    "wof:name":"R T Maudsley",
    "wof:placetype":"venue"
},
  "geometry": {"coordinates":[-4.663407,51.756413],"type":"Point"}
}