{
  "type": "Feature",
  "properties": {
    "addr:full":"(4-86 Glanmore Road, Uplands Swansea Swansea SA2 0QB",
    "addr:housenumber":"4-86",
    "addr:postcode":"sa2 0qb",
    "addr:street":"Glanmore Road",
    "iso:country":"GB",
    "sg:address":"(4-86 Glanmore Road, Uplands",
    "sg:city":"Swansea",
    "sg:classifiers":[
        {
            "category":"Shopping",
            "subcategory":"Discount & Variety Stores",
            "type":"Retail Goods"
        }
    ],
    "sg:phone":"+44 1792 281288",
    "sg:postcode":"SA2 0QB",
    "sg:province":"Swansea",
    "sg:tags":[
        "cleaning",
        "supply"
    ],
    "wof:name":"Rowser Wales",
    "wof:placetype":"venue"
},
  "geometry": {"coordinates":[-3.9681370258,51.61876297],"type":"Point"}
}