{
  "type": "Feature",
  "properties": {
    "addr:full":"38 Parsons Green Terrace, Meadowbank Edinburgh City of Edinburgh EH8 7AF",
    "addr:housenumber":"38",
    "addr:postcode":"eh8 7af",
    "addr:street":"Parsons Green Terrace",
    "iso:country":"GB",
    "sg:address":"38 Parsons Green Terrace, Meadowbank",
    "sg:city":"Edinburgh",
    "sg:classifiers":[
        {
            "category":"Shopping",
            "subcategory":"Hobbies, Toys, & Games",
            "type":"Retail Goods"
        }
    ],
    "sg:postcode":"EH8 7AF",
    "sg:province":"City of Edinburgh",
    "sg:tags":[
        "toy"
    ],
    "wof:name":"The Balloon Drop Shop",
    "wof:placetype":"venue"
},
  "geometry": {"coordinates":[-3.153789,55.955292],"type":"Point"}
}