{
  "type": "Feature",
  "properties": {
    "addr:full":"1 College Close, Handcross Park, Handcross Haywards Heath East Sussex RH17 6HG",
    "addr:housenumber":"1",
    "addr:postcode":"rh17 6hg",
    "addr:street":"College Close Handcross Park",
    "iso:country":"GB",
    "sg:address":"1 College Close, Handcross Park, Handcross",
    "sg:city":"Haywards Heath",
    "sg:classifiers":[
        {
            "category":"Real Estate",
            "subcategory":"Real Estate Services",
            "type":"Services"
        },
        {
            "category":"Education",
            "subcategory":"School",
            "type":"Public Place"
        }
    ],
    "sg:phone":"+44 1444 401241",
    "sg:postcode":"RH17 6HG",
    "sg:province":"East Sussex",
    "sg:tags":[
        "management",
        "local",
        "authority"
    ],
    "wof:name":"College Close Handcross Management Company Ltd",
    "wof:placetype":"venue"
},
  "geometry": {"coordinates":[-0.0780489966,51.0481262207],"type":"Point"}
}