{
  "type": "Feature",
  "properties": {
    "addr:full":"7 Millfield Cambridge Cambridgeshire CB4 4RE",
    "addr:housenumber":"7",
    "addr:postcode":"cb4 4re",
    "addr:street":"Millfield",
    "iso:country":"GB",
    "sg:address":"7 Millfield",
    "sg:city":"Cambridge",
    "sg:classifiers":[
        {
            "category":"Home & Garden",
            "subcategory":"Building Materials",
            "type":"Retail Goods"
        }
    ],
    "sg:phone":"+44 1954 251900",
    "sg:postcode":"CB4 4RE",
    "sg:province":"Cambridgeshire",
    "sg:tags":[
        "ventilator",
        "ventilation",
        "system"
    ],
    "wof:name":"Fans & Spares",
    "wof:placetype":"venue"
},
  "geometry": {"coordinates":[0.1338700056,52.2271003723],"type":"Point"}
}