{
  "type": "Feature",
  "properties": {
    "addr:full":"11 Station Road Hailsham East Sussex BN27 2BE",
    "addr:housenumber":"11",
    "addr:postcode":"bn27 2be",
    "addr:street":"Station Road",
    "iso:country":"GB",
    "sg:address":"11 Station Road",
    "sg:city":"Hailsham",
    "sg:classifiers":[
        {
            "category":"Retail",
            "subcategory":"Funeral Services",
            "type":"Services"
        }
    ],
    "sg:postcode":"BN27 2BE",
    "sg:province":"East Sussex",
    "wof:name":"Hailsham Funeral Service",
    "wof:placetype":"venue"
},
  "geometry": {"coordinates":[0.257747,50.861385],"type":"Point"}
}