{
  "type": "Feature",
  "properties": {
    "addr:full":"4 Main Street, Keyworth Nottingham Nottinghamshire NG12 5AD",
    "addr:housenumber":"4",
    "addr:postcode":"ng12 5ad",
    "addr:street":"Main Street",
    "iso:country":"GB",
    "sg:address":"4 Main Street, Keyworth",
    "sg:city":"Nottingham",
    "sg:classifiers":[
        {
            "category":"Restaurant",
            "type":"Food & Drink"
        }
    ],
    "sg:phone":"+44 115 937 2895",
    "sg:postcode":"NG12 5AD",
    "sg:province":"Nottinghamshire",
    "wof:name":"Brian Hickling",
    "wof:placetype":"venue"
},
  "geometry": {"coordinates":[-1.0896309614,52.8708839417],"type":"Point"}
}