{
  "type": "Feature",
  "properties": {
    "addr:full":"6b Elgar Estate, Preston Road Reading Berkshire RG2 0BE",
    "addr:housenumber":"6b",
    "addr:postcode":"rg2 0be",
    "addr:street":"Elgar Estate Preston Road",
    "iso:country":"GB",
    "sg:address":"6b Elgar Estate, Preston Road",
    "sg:city":"Reading",
    "sg:classifiers":[
        {
            "category":"Building & Trades",
            "subcategory":"Plumbing",
            "type":"Services"
        }
    ],
    "sg:phone":"+44 118 931 2000",
    "sg:postcode":"RG2 0BE",
    "sg:province":"Berkshire",
    "sg:tags":[
        "merchant",
        "plumbers'"
    ],
    "wof:name":"Instox",
    "wof:placetype":"venue"
},
  "geometry": {"coordinates":[-0.97309798,51.4480781555],"type":"Point"}
}