{
  "type": "Feature",
  "properties": {
    "iso:country":"GB",
    "sg:address":"Willow Park Junior School, Harewood Av",
    "sg:city":"Pontefract",
    "sg:classifiers":[
        {
            "category":"Education",
            "subcategory":"School",
            "type":"Public Place"
        },
        {
            "category":"Government",
            "subcategory":"Office",
            "type":"Public Place"
        }
    ],
    "sg:phone":"+44 1977 723595",
    "sg:postcode":"WF8 2ES",
    "sg:province":"North Yorkshire",
    "sg:tags":[
        "local",
        "authority"
    ],
    "wof:name":"Wakefield Metropolitan District Council",
    "wof:placetype":"venue"
},
  "geometry": {"coordinates":[-1.295404,53.690189],"type":"Point"}
}