{
  "type": "Feature",
  "properties": {
    "addr:full":"89a Rivington Street London Greater London EC2A 3BJ",
    "addr:housenumber":"89a",
    "addr:postcode":"ec2a 3bj",
    "addr:street":"Rivington Street",
    "iso:country":"GB",
    "sg:address":"89a Rivington Street",
    "sg:city":"London",
    "sg:classifiers":[
        {
            "category":"Wholesale",
            "subcategory":"Medical Equipment & Supplies",
            "type":"Manufacturing & Wholesale Goods"
        }
    ],
    "sg:phone":"+44 20 8458 3757",
    "sg:postcode":"EC2A 3BJ",
    "sg:province":"Greater London",
    "sg:tags":[
        "hospital"
    ],
    "wof:name":"Electra House Consulting Ltd.",
    "wof:placetype":"venue"
},
  "geometry": {"coordinates":[-0.0789949968,51.5263900757],"type":"Point"}
}