{
  "type": "Feature",
  "properties": {
    "addr:full":"30 Stoneleigh Bdwy Epsom Surrey KT17 2HS",
    "addr:housenumber":"30;bdwy",
    "addr:postcode":"kt17 2hs",
    "addr:street":"Stoneleigh",
    "iso:country":"GB",
    "sg:address":"30 Stoneleigh Bdwy",
    "sg:city":"Epsom",
    "sg:classifiers":[
        {
            "category":"Food & Beverages",
            "subcategory":"Meat & Fish",
            "type":"Retail Goods"
        }
    ],
    "sg:postcode":"KT17 2HS",
    "sg:province":"Surrey",
    "sg:tags":[
        "butcher"
    ],
    "wof:name":"Macgregors Family Butchers",
    "wof:placetype":"venue"
},
  "geometry": {"coordinates":[-0.2444089949,51.3675193787],"type":"Point"}
}