{
  "type": "Feature",
  "properties": {
    "iso:country":"GB",
    "sg:address":"Ullswater Avenue",
    "sg:city":"Leamington Spa",
    "sg:classifiers":[
        {
            "category":"Education",
            "subcategory":"School",
            "type":"Public Place"
        }
    ],
    "sg:phone":"+44 1926 420051",
    "sg:postcode":"CV32 6NH",
    "sg:province":"Warwickshire",
    "sg:tags":[
        "local",
        "authority"
    ],
    "wof:name":"Brookhurst Primary School",
    "wof:placetype":"venue"
},
  "geometry": {"coordinates":[-1.5554039478,52.2966537476],"type":"Point"}
}