{
  "type": "Feature",
  "properties": {
    "addr:full":"206 High Street, Princes End Tipton West Midlands DY4 9JB",
    "addr:housenumber":"206",
    "addr:postcode":"dy4 9jb",
    "addr:street":"High Street",
    "iso:country":"GB",
    "sg:address":"206 High Street, Princes End",
    "sg:city":"Tipton",
    "sg:classifiers":[
        {
            "category":"Retail",
            "subcategory":"Veterinary Services",
            "type":"Services"
        },
        {
            "category":"Retail",
            "subcategory":"Pet Boarding",
            "type":"Services"
        }
    ],
    "sg:phone":"+44 121 522 2118",
    "sg:postcode":"DY4 9JB",
    "sg:province":"West Midlands",
    "sg:tags":[
        "surgeon",
        "kennel"
    ],
    "wof:name":"D P Cronin",
    "wof:placetype":"venue"
},
  "geometry": {"coordinates":[-2.0596148968,52.5435600281],"type":"Point"}
}