{
  "type": "Feature",
  "properties": {
    "addr:full":"Unit B6 Telford Road Bicester Oxfordshire OX26 4LD",
    "addr:postcode":"ox26 4ld",
    "addr:street":"Telford Road",
    "iso:country":"GB",
    "sg:address":"Unit B6 Telford Road",
    "sg:city":"Bicester",
    "sg:classifiers":[
        {
            "category":"Social Services",
            "type":"Services"
        }
    ],
    "sg:phone":"+44 1869 249506",
    "sg:postcode":"OX26 4LD",
    "sg:province":"Oxfordshire",
    "sg:tags":[
        "disability"
    ],
    "wof:name":"A & E Textile Services",
    "wof:placetype":"venue"
},
  "geometry": {"coordinates":[-1.1315490007,51.9028968811],"type":"Point"}
}