{
  "type": "Feature",
  "properties": {
    "addr:full":"Lymington Rd Torquay Devon TQ1 4AU",
    "addr:postcode":"tq1 4au",
    "addr:street":"Lymington Rd",
    "iso:country":"GB",
    "sg:address":"Lymington Rd",
    "sg:city":"Torquay",
    "sg:classifiers":[
        {
            "category":"Sports & Exercise",
            "subcategory":"Tennis Court",
            "type":"Entertainment"
        }
    ],
    "sg:phone":"+44 1803 200483",
    "sg:postcode":"TQ1 4AU",
    "sg:province":"Devon",
    "wof:name":"Upton Park Tennis Courts",
    "wof:placetype":"venue"
},
  "geometry": {"coordinates":[-3.535824,50.473717],"type":"Point"}
}