{
  "type": "Feature",
  "properties": {
    "addr:full":"9 Manor Park Bognor Regis West Sussex PO21 3JS",
    "addr:housenumber":"9",
    "addr:postcode":"po21 3js",
    "addr:street":"Manor Park",
    "iso:country":"GB",
    "sg:address":"9 Manor Park",
    "sg:city":"Bognor Regis",
    "sg:classifiers":[
        {
            "category":"Wholesale",
            "subcategory":"Fruits & Vegetables",
            "type":"Manufacturing & Wholesale Goods"
        }
    ],
    "sg:phone":"+44 1243 262777",
    "sg:postcode":"PO21 3JS",
    "sg:province":"West Sussex",
    "wof:name":"Janmark Group",
    "wof:placetype":"venue"
},
  "geometry": {"coordinates":[-0.7318419814,50.7780799866],"type":"Point"}
}