{
  "type": "Feature",
  "properties": {
    "iso:country":"GB",
    "sg:address":"1 Barker Street",
    "sg:city":"Leicester",
    "sg:classifiers":[
        {
            "category":"Shopping",
            "subcategory":"Department Store",
            "type":"Retail Goods"
        },
        {
            "category":"Food & Beverages",
            "subcategory":"Groceries & Convenience Stores",
            "type":"Retail Goods"
        }
    ],
    "sg:postcode":"LE5 3LF",
    "sg:province":"Leicestershire",
    "wof:name":"Tara General Store",
    "wof:placetype":"venue"
},
  "geometry": {"coordinates":[-1.106931,52.640797],"type":"Point"}
}