{
  "type": "Feature",
  "properties": {
    "iso:country":"GB",
    "sg:address":"50 Harbour Road",
    "sg:city":"Inverness",
    "sg:classifiers":[
        {
            "category":"Retail",
            "subcategory":"Auto Repair",
            "type":"Services"
        }
    ],
    "sg:phone":"+44 1463 236236",
    "sg:postcode":"IV1 1UF",
    "sg:province":"Highland",
    "sg:tags":[
        "modification",
        "garage"
    ],
    "wof:name":"Summit Motors Ltd.",
    "wof:placetype":"venue"
},
  "geometry": {"coordinates":[-4.209149,57.486351],"type":"Point"}
}