{
  "type": "Feature",
  "properties": {
    "addr:full":"Horsefair Community Centre, Broad St Kidderminster Staffordshire DY10 2LZ",
    "addr:postcode":"dy10 2lz",
    "addr:street":"Broad St",
    "iso:country":"GB",
    "sg:address":"Horsefair Community Centre, Broad St",
    "sg:city":"Kidderminster",
    "sg:classifiers":[
        {
            "category":"Government",
            "subcategory":"Office",
            "type":"Public Place"
        }
    ],
    "sg:phone":"+44 1562 69934",
    "sg:postcode":"DY10 2LZ",
    "sg:province":"Staffordshire",
    "sg:tags":[
        "local"
    ],
    "wof:name":"Federation Of Council Tennants Wyre Forest",
    "wof:placetype":"venue"
},
  "geometry": {"coordinates":[-2.249084,52.388111],"type":"Point"}
}