{
  "type": "Feature",
  "properties": {
    "addr:full":"Unit 1, Reservoir Road Hull East Riding of Yorkshire HU6 7PX",
    "addr:housenumber":"unit 1",
    "addr:postcode":"hu6 7px",
    "addr:street":"Reservoir Road",
    "iso:country":"GB",
    "sg:address":"Unit 1, Reservoir Road",
    "sg:city":"Hull",
    "sg:classifiers":[
        {
            "category":"Manufacturing",
            "subcategory":"Petroleum Products",
            "type":"Manufacturing & Wholesale Goods"
        }
    ],
    "sg:phone":"+44 1482 444590",
    "sg:postcode":"HU6 7PX",
    "sg:province":"East Riding of Yorkshire",
    "sg:tags":[
        "double",
        "glazing"
    ],
    "wof:name":"Select Windows",
    "wof:placetype":"venue"
},
  "geometry": {"coordinates":[-0.3337199986,53.7682418823],"type":"Point"}
}