{
  "type": "Feature",
  "properties": {
    "addr:full":"2 Hartopp Road, Alum Rock Birmingham West Midlands B8 1TE",
    "addr:housenumber":"2",
    "addr:postcode":"b8 1te",
    "addr:street":"Hartopp Road",
    "iso:country":"GB",
    "sg:address":"2 Hartopp Road, Alum Rock",
    "sg:city":"Birmingham",
    "sg:classifiers":[
        {
            "category":"Building & Trades",
            "subcategory":"Cleaning & Sanitation",
            "type":"Services"
        }
    ],
    "sg:postcode":"B8 1TE",
    "sg:province":"West Midlands",
    "sg:tags":[
        "blast"
    ],
    "wof:name":"Atlas Fabrication & Shotblasting",
    "wof:placetype":"venue"
},
  "geometry": {"coordinates":[-1.852957,52.486904],"type":"Point"}
}