{
  "type": "Feature",
  "properties": {
    "iso:country":"GB",
    "sg:address":"14 Polmuir Rd",
    "sg:city":"Aberdeen",
    "sg:classifiers":[
        {
            "category":"Education",
            "subcategory":"Special Training",
            "type":"Public Place"
        }
    ],
    "sg:phone":"+44 1224 581977",
    "sg:postcode":"AB11 7SY",
    "sg:province":"Aberdeen City",
    "sg:tags":[
        "school"
    ],
    "wof:name":"Hostel For The Deaf",
    "wof:placetype":"venue"
},
  "geometry": {"coordinates":[-2.104387,57.135536],"type":"Point"}
}