{
  "type": "Feature",
  "properties": {
    "iso:country":"GB",
    "sg:address":"16 Rozel Ct",
    "sg:city":"Bury St Edmunds",
    "sg:classifiers":[
        {
            "category":"Organizations",
            "subcategory":"Non-profit Organization",
            "type":"Services"
        }
    ],
    "sg:phone":"+44 1638 714370",
    "sg:postcode":"IP28 8AX",
    "sg:province":"Cambridgeshire",
    "sg:tags":[
        "organisation",
        "voluntary",
        "charity"
    ],
    "wof:name":"Arthritis Research Campaign",
    "wof:placetype":"venue"
},
  "geometry": {"coordinates":[0.49726,52.3731],"type":"Point"}
}