{
  "type": "Feature",
  "properties": {
    "iso:country":"GB",
    "sg:address":"Whiteclose Rigg, Longtown",
    "sg:city":"Carlisle",
    "sg:classifiers":[
        {
            "category":"Farming",
            "subcategory":"Dairy Farm",
            "type":"Manufacturing & Wholesale Goods"
        }
    ],
    "sg:phone":"+44 1228 791281",
    "sg:postcode":"CA6 5TY",
    "sg:province":"Cumbria",
    "sg:tags":[
        "farmer"
    ],
    "wof:name":"R & D C CARR",
    "wof:placetype":"venue"
},
  "geometry": {"coordinates":[-2.9694559574,55.0072631836],"type":"Point"}
}