{
  "type": "Feature",
  "properties": {
    "addr:full":"47 Villa Rd Birmingham West Midlands B19 1BH",
    "addr:housenumber":"47",
    "addr:postcode":"b19 1bh",
    "addr:street":"Villa Rd",
    "iso:country":"GB",
    "sg:address":"47 Villa Rd",
    "sg:city":"Birmingham",
    "sg:classifiers":[
        {
            "category":"Health Services",
            "subcategory":"Doctor",
            "type":"Services"
        }
    ],
    "sg:phone":"+44 121 554 2453",
    "sg:postcode":"B19 1BH",
    "sg:province":"West Midlands",
    "sg:tags":[
        "practitioners"
    ],
    "wof:name":"Targett, D H",
    "wof:placetype":"venue"
},
  "geometry": {"coordinates":[-1.919769,52.502071],"type":"Point"}
}