{
  "type": "Feature",
  "properties": {
    "iso:country":"GB",
    "sg:address":"84 English Street",
    "sg:city":"Dumfries",
    "sg:classifiers":[
        {
            "category":"Home & Garden",
            "subcategory":"Home Furnishings",
            "type":"Retail Goods"
        }
    ],
    "sg:phone":"+44 1387 269673",
    "sg:postcode":"DG1 2BY",
    "sg:province":"Dumfries and Galloway",
    "sg:tags":[
        "blind",
        "curtain",
        "fitting"
    ],
    "wof:name":"Marimat",
    "wof:placetype":"venue"
},
  "geometry": {"coordinates":[-3.607836,55.068916],"type":"Point"}
}