{
  "type": "Feature",
  "properties": {
    "iso:country":"GB",
    "sg:address":"26 Portsmouth Close",
    "sg:city":"Grantham",
    "sg:classifiers":[
        {
            "category":"Retail",
            "subcategory":"Driving School",
            "type":"Services"
        }
    ],
    "sg:postcode":"NG31 8BP",
    "sg:province":"Lincolnshire",
    "wof:name":"R Bowles School of Motoring",
    "wof:placetype":"venue"
},
  "geometry": {"coordinates":[-0.655981,52.914902],"type":"Point"}
}