{
  "type": "Feature",
  "properties": {
    "addr:full":"Wenlock Way, Barkby Thorpe Estate Leicester Leicestershire LE4 7HU",
    "addr:postcode":"le4 7hu",
    "addr:street":"Wenlock Way Barkby Thorpe Estate",
    "iso:country":"GB",
    "sg:address":"Wenlock Way, Barkby Thorpe Estate",
    "sg:city":"Leicester",
    "sg:classifiers":[
        {
            "category":"Home & Garden",
            "subcategory":"Household Appliances",
            "type":"Retail Goods"
        }
    ],
    "sg:phone":"+44 116 274 0777",
    "sg:postcode":"LE4 7HU",
    "sg:province":"Leicestershire",
    "sg:tags":[
        "domestic",
        "centre"
    ],
    "wof:name":"Hotta U K Ltd.",
    "wof:placetype":"venue"
},
  "geometry": {"coordinates":[-1.10816,52.662319],"type":"Point"}
}