{
  "type": "Feature",
  "properties": {
    "iso:country":"GB",
    "sg:address":"46-47 Meriden Street",
    "sg:city":"Birmingham",
    "sg:classifiers":[
        {
            "category":"Home & Garden",
            "subcategory":"Home Furnishings",
            "type":"Retail Goods"
        },
        {
            "category":"Home & Garden",
            "subcategory":"Building Materials",
            "type":"Retail Goods"
        }
    ],
    "sg:phone":"+44 121 632 5064",
    "sg:postcode":"B5 5LS",
    "sg:province":"West Midlands",
    "sg:tags":[
        "installers",
        "planner",
        "kitchen",
        "furnishers"
    ],
    "wof:name":"Keywise Kitchens",
    "wof:placetype":"venue"
},
  "geometry": {"coordinates":[-1.88999,52.476273],"type":"Point"}
}