{
  "type": "Feature",
  "properties": {
    "addr:full":"5 Carlisle Street London Greater London W1D 3JX",
    "addr:housenumber":"5",
    "addr:postcode":"w1d 3jx",
    "addr:street":"Carlisle Street",
    "iso:country":"GB",
    "sg:address":"5 Carlisle Street",
    "sg:city":"London",
    "sg:classifiers":[
        {
            "category":"Professional",
            "subcategory":"Advertising",
            "type":"Services"
        }
    ],
    "sg:phone":"+44 20 7494 0482",
    "sg:postcode":"W1D 3JX",
    "sg:province":"Greater London",
    "sg:tags":[
        "mail",
        "direct"
    ],
    "wof:name":"H B H Partnership Ltd.",
    "wof:placetype":"venue"
},
  "geometry": {"coordinates":[-0.133514002,51.5148353577],"type":"Point"}
}