{
  "type": "Feature",
  "properties": {
    "addr:full":"10 Fairview Gro Wolverhampton Staffordshire WV11 1BZ",
    "addr:housenumber":"10",
    "addr:postcode":"wv11 1bz",
    "addr:street":"Fairview Gro",
    "iso:country":"GB",
    "sg:address":"10 Fairview Gro",
    "sg:city":"Wolverhampton",
    "sg:classifiers":[
        {
            "category":"Building & Trades",
            "subcategory":"Construction",
            "type":"Services"
        }
    ],
    "sg:phone":"+44 1902 862314",
    "sg:postcode":"WV11 1BZ",
    "sg:province":"Staffordshire",
    "sg:tags":[
        "dry",
        "lining",
        "plasterers",
        "screeders"
    ],
    "wof:name":"Interior & Exterior Plastering Designers",
    "wof:placetype":"venue"
},
  "geometry": {"coordinates":[-2.094439,52.606693],"type":"Point"}
}