{
  "type": "Feature",
  "properties": {
    "addr:full":"27g-27h Unit Cowbridge The Vale of Glamorgan CF71 7PF",
    "addr:housenumber":"unit cowbridge",
    "addr:postcode":"cf71 7pf",
    "addr:street":"Vale",
    "iso:country":"GB",
    "sg:address":"27g-27h Unit",
    "sg:city":"Cowbridge",
    "sg:classifiers":[
        {
            "category":"Shopping",
            "subcategory":"Computers & Home Electronics",
            "type":"Retail Goods"
        },
        {
            "category":"Home & Garden",
            "subcategory":"Furniture",
            "type":"Retail Goods"
        }
    ],
    "sg:phone":"+44 1446 775063",
    "sg:postcode":"CF71 7PF",
    "sg:province":"The Vale of Glamorgan",
    "wof:name":"Christopher Designs",
    "wof:placetype":"venue"
},
  "geometry": {"coordinates":[-3.4534890652,51.4583587646],"type":"Point"}
}