{
  "type": "Feature",
  "properties": {
    "addr:full":"201 High Street, Wibsey Bradford West Yorkshire BD6 1JU",
    "addr:housenumber":"201",
    "addr:postcode":"bd6 1ju",
    "addr:street":"High Street",
    "iso:country":"GB",
    "sg:address":"201 High Street, Wibsey",
    "sg:city":"Bradford",
    "sg:classifiers":[
        {
            "category":"Personal",
            "subcategory":"Barber",
            "type":"Services"
        }
    ],
    "sg:postcode":"BD6 1JU",
    "sg:province":"West Yorkshire",
    "sg:tags":[
        "men's",
        "gents",
        "hairdresser"
    ],
    "wof:name":"David Allen",
    "wof:placetype":"venue"
},
  "geometry": {"coordinates":[-1.77355,53.767017],"type":"Point"}
}