{
  "type": "Feature",
  "properties": {
    "addr:full":"Ebenezer Place Kettering Northamptonshire NN16 0DE",
    "addr:postcode":"nn16 0de",
    "addr:street":"Ebenezer Place",
    "iso:country":"GB",
    "sg:address":"Ebenezer Place",
    "sg:city":"Kettering",
    "sg:classifiers":[
        {
            "category":"Shopping",
            "subcategory":"Pets & Pet Supplies",
            "type":"Retail Goods"
        }
    ],
    "sg:postcode":"NN16 0DE",
    "sg:province":"Northamptonshire",
    "sg:tags":[
        "shop"
    ],
    "wof:name":"Pets Choice",
    "wof:placetype":"venue"
},
  "geometry": {"coordinates":[-0.7263299823,52.4002799988],"type":"Point"}
}