{
  "type": "Feature",
  "properties": {
    "iso:country":"GB",
    "sg:address":"4 Oakwood Gardens, Knaphill",
    "sg:city":"Woking",
    "sg:classifiers":[
        {
            "category":"Professional",
            "subcategory":"Accounting & Tax Preparation",
            "type":"Services"
        }
    ],
    "sg:phone":"+44 1483 832342",
    "sg:postcode":"GU21 2RX",
    "sg:province":"Surrey",
    "sg:tags":[
        "accountant"
    ],
    "wof:name":"Butlers",
    "wof:placetype":"venue"
},
  "geometry": {"coordinates":[-0.6306020021,51.3144187927],"type":"Point"}
}