{
  "type": "Feature",
  "properties": {
    "iso:country":"GB",
    "sg:address":"193 Mid Street",
    "sg:city":"Keith",
    "sg:classifiers":[
        {
            "category":"Organizations",
            "subcategory":"Professional Association",
            "type":"Services"
        },
        {
            "category":"Government",
            "subcategory":"Office",
            "type":"Public Place"
        }
    ],
    "sg:phone":"+44 1542 882884",
    "sg:postcode":"AB55 5BQ",
    "sg:province":"Moray",
    "sg:tags":[
        "union",
        "chamber",
        "trade",
        "commerce"
    ],
    "wof:name":"N F U",
    "wof:placetype":"venue"
},
  "geometry": {"coordinates":[-2.9494481087,57.5426902771],"type":"Point"}
}