{
  "type": "Feature",
  "properties": {
    "addr:full":"Bank Lane, Burland Nantwich Cheshire CW5 8LS",
    "addr:postcode":"cw5 8ls",
    "addr:street":"Bank Lane",
    "iso:country":"GB",
    "sg:address":"Bank Lane, Burland",
    "sg:city":"Nantwich",
    "sg:classifiers":[
        {
            "category":"Retail",
            "subcategory":"Auto Repair",
            "type":"Services"
        }
    ],
    "sg:phone":"+44 1270 524403",
    "sg:postcode":"CW5 8LS",
    "sg:province":"Cheshire",
    "sg:tags":[
        "modification",
        "garage"
    ],
    "wof:name":"Robert Vaughan Motor Repairs",
    "wof:placetype":"venue"
},
  "geometry": {"coordinates":[-2.57596,53.077332],"type":"Point"}
}