{
  "type": "Feature",
  "properties": {
    "addr:full":"51coast Road, Pevensey Bay Pevensey East Sussex BN24 6LR",
    "addr:postcode":"bn24 6lr",
    "addr:street":"51Coast Road",
    "iso:country":"GB",
    "sg:address":"51coast Road, Pevensey Bay",
    "sg:city":"Pevensey",
    "sg:classifiers":[
        {
            "category":"Building & Trades",
            "subcategory":"Construction",
            "type":"Services"
        }
    ],
    "sg:phone":"+44 1323 766057",
    "sg:postcode":"BN24 6LR",
    "sg:province":"East Sussex",
    "sg:tags":[
        "builder"
    ],
    "wof:name":"D G Wingrove",
    "wof:placetype":"venue"
},
  "geometry": {"coordinates":[0.351132,50.813278],"type":"Point"}
}