{
  "type": "Feature",
  "properties": {
    "iso:country":"GB",
    "sg:address":"36 Westbury Road",
    "sg:city":"New Malden",
    "sg:classifiers":[
        {
            "category":"Professional",
            "subcategory":"Engineering",
            "type":"Services"
        },
        {
            "category":"Building & Trades",
            "subcategory":"Electrical",
            "type":"Services"
        }
    ],
    "sg:phone":"+44 20 8949 6002",
    "sg:postcode":"KT3 5BA",
    "sg:province":"Surrey",
    "sg:tags":[
        "engineer",
        "electrician",
        "contractor"
    ],
    "wof:name":"K BOLDEN & SONS",
    "wof:placetype":"venue"
},
  "geometry": {"coordinates":[-0.264537,51.399288],"type":"Point"}
}