{
  "type": "Feature",
  "properties": {
    "addr:full":"195 Maple Road London Greater London SE20 8HU",
    "addr:housenumber":"195",
    "addr:postcode":"se20 8hu",
    "addr:street":"Maple Road",
    "iso:country":"GB",
    "sg:address":"195 Maple Road",
    "sg:city":"London",
    "sg:classifiers":[
        {
            "category":"Taxi",
            "type":"Transportation"
        }
    ],
    "sg:postcode":"SE20 8HU",
    "sg:province":"Greater London",
    "sg:tags":[
        "mini",
        "cab"
    ],
    "wof:name":"Metros",
    "wof:placetype":"venue"
},
  "geometry": {"coordinates":[-0.055105,51.415157],"type":"Point"}
}