{
  "type": "Feature",
  "properties": {
    "addr:full":"Unit 5, Rennie Business Units, Factory Place Saltcoats North Ayrshire KA21 5LZ",
    "addr:housenumber":"unit 5",
    "addr:postcode":"ka21 5lz",
    "addr:street":"Rennie Business;Factory Place",
    "iso:country":"GB",
    "sg:address":"Unit 5, Rennie Business Units, Factory Place",
    "sg:city":"Saltcoats",
    "sg:classifiers":[
        {
            "category":"Shopping",
            "subcategory":"Event Tickets",
            "type":"Retail Goods"
        }
    ],
    "sg:phone":"+44 1563 574030",
    "sg:postcode":"KA21 5LZ",
    "sg:province":"North Ayrshire",
    "sg:tags":[
        "agency"
    ],
    "wof:name":"John Groves",
    "wof:placetype":"venue"
},
  "geometry": {"coordinates":[-4.787579,55.64344],"type":"Point"}
}