{
  "type": "Feature",
  "properties": {
    "addr:full":"Craig Farm Campus, Maree Walk Livingston West Lothian EH54 5BP",
    "addr:postcode":"eh54 5bp",
    "addr:street":"Craig;Maree Walk",
    "iso:country":"GB",
    "sg:address":"Craig Farm Campus, Maree Walk",
    "sg:city":"Livingston",
    "sg:classifiers":[
        {
            "category":"Communications",
            "subcategory":"Film & Video Production",
            "type":"Services"
        }
    ],
    "sg:phone":"+44 1506 777693",
    "sg:postcode":"EH54 5BP",
    "sg:province":"West Lothian",
    "sg:tags":[
        "recording",
        "studio"
    ],
    "wof:name":"Sound Place Studio",
    "wof:placetype":"venue"
},
  "geometry": {"coordinates":[-3.509834,55.886246],"type":"Point"}
}