{
  "type": "Feature",
  "properties": {
    "addr:full":"20 Jopson Street, Middleton Manchester Greater Manchester M24 2JA",
    "addr:housenumber":"20",
    "addr:postcode":"m24 2ja",
    "addr:street":"Jopson Street",
    "iso:country":"GB",
    "sg:address":"20 Jopson Street, Middleton",
    "sg:city":"Manchester",
    "sg:classifiers":[
        {
            "category":"Building & Trades",
            "subcategory":"Cleaning & Sanitation",
            "type":"Services"
        }
    ],
    "sg:postcode":"M24 2JA",
    "sg:province":"Greater Manchester",
    "sg:tags":[
        "contracting",
        "commercial"
    ],
    "wof:name":"CAV-CLEAN",
    "wof:placetype":"venue"
},
  "geometry": {"coordinates":[-2.176549,53.55619],"type":"Point"}
}