{
  "type": "Feature",
  "properties": {
    "iso:country":"GB",
    "sg:address":"18 Glebe Farm Road",
    "sg:city":"Birmingham",
    "sg:classifiers":[
        {
            "category":"Food & Beverages",
            "subcategory":"Supermarket",
            "type":"Retail Goods"
        }
    ],
    "sg:phone":"+44 121 783 3552",
    "sg:postcode":"B33 9LZ",
    "sg:province":"West Midlands",
    "wof:name":"Pape Supermarket",
    "wof:placetype":"venue"
},
  "geometry": {"coordinates":[-1.793963,52.488197],"type":"Point"}
}