{
  "type": "Feature",
  "properties": {
    "iso:country":"GB",
    "sg:address":"Unit 4a Centre Park, Marston Moor Business Estate",
    "sg:city":"York",
    "sg:classifiers":[
        {
            "category":"Taxi",
            "type":"Transportation"
        },
        {
            "category":"Military Area",
            "subcategory":"Air Force Base",
            "type":"Public Place"
        }
    ],
    "sg:phone":"+44 1423 359000",
    "sg:postcode":"YO26 7QF",
    "sg:province":"North Yorkshire",
    "sg:tags":[
        "hire",
        "private"
    ],
    "wof:name":"S & B Cars",
    "wof:placetype":"venue"
},
  "geometry": {"coordinates":[-1.310989,53.965969],"type":"Point"}
}