{
  "type": "Feature",
  "properties": {
    "addr:full":"Unit 1 Carlington Court, 3 Patterson Street Blaydon-on-tyne Tyne and Wear NE21 5SB",
    "addr:housenumber":"unit 1;3",
    "addr:postcode":"ne21 5sb",
    "addr:street":"Carlington;Patterson Street",
    "iso:country":"GB",
    "sg:address":"Unit 1 Carlington Court, 3 Patterson Street",
    "sg:city":"Blaydon-on-tyne",
    "sg:classifiers":[
        {
            "category":"Wholesale",
            "subcategory":"Construction Materials",
            "type":"Manufacturing & Wholesale Goods"
        }
    ],
    "sg:phone":"+44 191 414 5030",
    "sg:postcode":"NE21 5SB",
    "sg:province":"Tyne and Wear",
    "sg:tags":[
        "merchant",
        "brick"
    ],
    "wof:name":"Brick Services Ltd.",
    "wof:placetype":"venue"
},
  "geometry": {"coordinates":[-1.7004890442,54.9693031311],"type":"Point"}
}