{
  "type": "Feature",
  "properties": {
    "addr:full":"2 Tankerton Rd Whitstable Kent CT5 2AB",
    "addr:housenumber":"2",
    "addr:postcode":"ct5 2ab",
    "addr:street":"Tankerton Rd Whitstable",
    "iso:country":"GB",
    "sg:address":"2 Tankerton Rd",
    "sg:city":"Whitstable",
    "sg:classifiers":[
        {
            "category":"Shopping",
            "subcategory":"Used Merchandise",
            "type":"Retail Goods"
        }
    ],
    "sg:phone":"+44 1227 265081",
    "sg:postcode":"CT5 2AB",
    "sg:province":"Kent",
    "sg:tags":[
        "shop",
        "second-hand"
    ],
    "wof:name":"Something Old Something New",
    "wof:placetype":"venue"
},
  "geometry": {"coordinates":[1.0332360268,51.3633956909],"type":"Point"}
}