{
  "type": "Feature",
  "properties": {
    "iso:country":"GB",
    "sg:address":"Unit 4 Stanton Gate, 49 Mawney Road",
    "sg:city":"Romford",
    "sg:classifiers":[
        {
            "category":"Manufacturing",
            "subcategory":"Petroleum Products",
            "type":"Manufacturing & Wholesale Goods"
        },
        {
            "category":"Home & Garden",
            "subcategory":"Building Materials",
            "type":"Retail Goods"
        }
    ],
    "sg:phone":"+44 1708 747751",
    "sg:postcode":"RM7 7HL",
    "sg:province":"Essex",
    "sg:tags":[
        "double",
        "window",
        "glazing",
        "frame"
    ],
    "wof:name":"Bowater Zenith Windows",
    "wof:placetype":"venue"
},
  "geometry": {"coordinates":[0.174,51.578491],"type":"Point"}
}