{
  "type": "Feature",
  "properties": {
    "addr:full":"54 Ennis Road London Greater London SE18 2QT",
    "addr:housenumber":"54",
    "addr:postcode":"se18 2qt",
    "addr:street":"Ennis Road",
    "iso:country":"GB",
    "sg:address":"54 Ennis Road",
    "sg:city":"London",
    "sg:classifiers":[
        {
            "category":"Building & Trades",
            "subcategory":"Plumbing",
            "type":"Services"
        }
    ],
    "sg:phone":"+44 20 8855 6683",
    "sg:postcode":"SE18 2QT",
    "sg:province":"Greater London",
    "sg:tags":[
        "heating"
    ],
    "wof:name":"R J S Plumbing & Heating",
    "wof:placetype":"venue"
},
  "geometry": {"coordinates":[0.079337,51.479416],"type":"Point"}
}