{
  "type": "Feature",
  "properties": {
    "addr:full":"Suite 2, Unit C Burley Hill Trading Estate, Burley Road Leeds West Yorkshire LS4 2PU",
    "addr:housenumber":"suite 2 unit c",
    "addr:postcode":"ls4 2pu",
    "addr:street":"Burley Hill Trading Estate Burley Road",
    "iso:country":"GB",
    "sg:address":"Suite 2, Unit C Burley Hill Trading Estate, Burley Road",
    "sg:city":"Leeds",
    "sg:classifiers":[
        {
            "category":"Sports & Exercise",
            "subcategory":"Sports Center",
            "type":"Entertainment"
        }
    ],
    "sg:phone":"+44 113 278 7242",
    "sg:postcode":"LS4 2PU",
    "sg:province":"West Yorkshire",
    "sg:tags":[
        "shop",
        "good"
    ],
    "wof:name":"Galaxy Sports Ltd.",
    "wof:placetype":"venue"
},
  "geometry": {"coordinates":[-1.583664,53.810108],"type":"Point"}
}