{
  "type": "Feature",
  "properties": {
    "addr:full":"Leslie Road Glenrothes Fife KY7 5PS",
    "addr:postcode":"ky7 5ps",
    "addr:street":"Leslie Road",
    "iso:country":"GB",
    "sg:address":"Leslie Road",
    "sg:city":"Glenrothes",
    "sg:classifiers":[
        {
            "category":"Autos & Motor Vehicles",
            "subcategory":"Fuel & Gas Station",
            "type":"Retail Goods"
        }
    ],
    "sg:phone":"+44 1592 612980",
    "sg:postcode":"KY7 5PS",
    "sg:province":"Fife",
    "sg:tags":[
        "hr",
        "petrol"
    ],
    "wof:name":"Shell Glenrothes",
    "wof:placetype":"venue"
},
  "geometry": {"coordinates":[-3.17589,56.198505],"type":"Point"}
}