{
  "type": "Feature",
  "properties": {
    "iso:country":"GB",
    "sg:address":"24 Comeytrowe Lane",
    "sg:city":"Taunton",
    "sg:classifiers":[
        {
            "category":"Coffee & Tea",
            "type":"Food & Drink"
        }
    ],
    "sg:phone":"+44 1823 284143",
    "sg:postcode":"TA1 5PA",
    "sg:province":"Somerset",
    "sg:tags":[
        "merchant"
    ],
    "wof:name":"C J Beverages",
    "wof:placetype":"venue"
},
  "geometry": {"coordinates":[-3.1284339428,51.0072174072],"type":"Point"}
}