{
  "type": "Feature",
  "properties": {
    "iso:country":"GB",
    "sg:address":"11 Dixon Road",
    "sg:city":"Sheffield",
    "sg:classifiers":[
        {
            "category":"Personal",
            "subcategory":"Beauty Salon",
            "type":"Services"
        },
        {
            "category":"Personal",
            "subcategory":"Barber",
            "type":"Services"
        }
    ],
    "sg:phone":"+44 114 234 3755",
    "sg:postcode":"S6 4FY",
    "sg:province":"South Yorkshire",
    "sg:tags":[
        "unisex",
        "hairdresser"
    ],
    "wof:name":"Melody's Hair Salon",
    "wof:placetype":"venue"
},
  "geometry": {"coordinates":[-1.504968,53.407181],"type":"Point"}
}