{
  "type": "Feature",
  "properties": {
    "addr:full":"May Suite, Spread Eagle Court, 106-114 Northgate Street Gloucester Gloucestershire GL1 1SL",
    "addr:housenumber":"106-114",
    "addr:postcode":"gl1 1sl",
    "addr:street":"Northgate Street",
    "iso:country":"GB",
    "sg:address":"May Suite, Spread Eagle Court, 106-114 Northgate Street",
    "sg:city":"Gloucester",
    "sg:classifiers":[
        {
            "category":"Professional",
            "subcategory":"Lawyer & Legal Services",
            "type":"Services"
        }
    ],
    "sg:phone":"+44 1452 506450",
    "sg:postcode":"GL1 1SL",
    "sg:province":"Gloucestershire",
    "sg:tags":[
        "advice",
        "counselling"
    ],
    "wof:name":"Victim Support Scheme",
    "wof:placetype":"venue"
},
  "geometry": {"coordinates":[-2.2429170609,51.8666877747],"type":"Point"}
}