{
  "type": "Feature",
  "properties": {
    "addr:full":"Church Street, Woodbury Exeter Devon EX5 1HN",
    "addr:postcode":"ex5 1hn",
    "addr:street":"Church Street",
    "iso:country":"GB",
    "sg:address":"Church Street, Woodbury",
    "sg:city":"Exeter",
    "sg:classifiers":[
        {
            "category":"Bars & Pubs",
            "type":"Food & Drink"
        }
    ],
    "sg:phone":"+44 1395 232221",
    "sg:postcode":"EX5 1HN",
    "sg:province":"Devon",
    "sg:tags":[
        "pubs",
        "inn"
    ],
    "wof:name":"White Hart Inn",
    "wof:placetype":"venue"
},
  "geometry": {"coordinates":[-3.40239,50.673195],"type":"Point"}
}