{
  "type": "Feature",
  "properties": {
    "addr:full":"14 Henconner Gro Leeds West Yorkshire LS7 3NP",
    "addr:housenumber":"14",
    "addr:postcode":"ls7 3np",
    "addr:street":"Henconner Gro Leeds West",
    "iso:country":"GB",
    "sg:address":"14 Henconner Gro",
    "sg:city":"Leeds",
    "sg:classifiers":[
        {
            "category":"Building & Trades",
            "subcategory":"Construction",
            "type":"Services"
        }
    ],
    "sg:postcode":"LS7 3NP",
    "sg:province":"West Yorkshire",
    "sg:tags":[
        "builder"
    ],
    "wof:name":"K Oldroyd Builders",
    "wof:placetype":"venue"
},
  "geometry": {"coordinates":[-1.5407340527,53.8268623352],"type":"Point"}
}