{
  "type": "Feature",
  "properties": {
    "addr:full":"Topwood Farm, Threapwood Malpas Cheshire SY14 7BD",
    "addr:postcode":"sy14 7bd",
    "iso:country":"GB",
    "sg:address":"Topwood Farm, Threapwood",
    "sg:city":"Malpas",
    "sg:classifiers":[
        {
            "category":"Farming",
            "subcategory":"Livestock Farm",
            "type":"Manufacturing & Wholesale Goods"
        }
    ],
    "sg:postcode":"SY14 7BD",
    "sg:province":"Cheshire",
    "sg:tags":[
        "others"
    ],
    "wof:name":"E A Broad",
    "wof:placetype":"venue"
},
  "geometry": {"coordinates":[-2.8362500668,53.0087776184],"type":"Point"}
}