{
  "type": "Feature",
  "properties": {
    "addr:full":"33 Queen Street, Great Harwood Blackburn Lancashire BB6 7QP",
    "addr:housenumber":"33",
    "addr:postcode":"bb6 7qp",
    "addr:street":"Queen Street",
    "iso:country":"GB",
    "sg:address":"33 Queen Street, Great Harwood",
    "sg:city":"Blackburn",
    "sg:classifiers":[
        {
            "category":"Building & Trades",
            "subcategory":"Cleaning & Sanitation",
            "type":"Services"
        },
        {
            "category":"Home & Garden",
            "subcategory":"Carpets & Floor Coverings",
            "type":"Retail Goods"
        }
    ],
    "sg:phone":"+44 1254 876463",
    "sg:postcode":"BB6 7QP",
    "sg:province":"Lancashire",
    "sg:tags":[
        "cleaner",
        "upholstery"
    ],
    "wof:name":"Servicemaster Ltd",
    "wof:placetype":"venue"
},
  "geometry": {"coordinates":[-2.404385,53.786358],"type":"Point"}
}