{
  "type": "Feature",
  "properties": {
    "addr:full":"22 Ellora Rd Streatham Greater London SW16 6JF",
    "addr:housenumber":"22",
    "addr:postcode":"sw16 6jf",
    "addr:street":"Ellora Rd",
    "iso:country":"GB",
    "sg:address":"22 Ellora Rd",
    "sg:city":"Streatham",
    "sg:classifiers":[
        {
            "category":"Bars & Pubs",
            "type":"Food & Drink"
        }
    ],
    "sg:phone":"+44 20 8769 2181",
    "sg:postcode":"SW16 6JF",
    "sg:province":"Greater London",
    "sg:tags":[
        "pubs",
        "inn"
    ],
    "wof:name":"Earl Ferrers",
    "wof:placetype":"venue"
},
  "geometry": {"coordinates":[-0.132663,51.423817],"type":"Point"}
}