{
  "type": "Feature",
  "properties": {
    "addr:full":"18 Hammonds Clo Southampton Hampshire SO40 3RZ",
    "addr:housenumber":"18",
    "addr:postcode":"so40 3rz",
    "addr:street":"Hammonds Clo",
    "iso:country":"GB",
    "sg:address":"18 Hammonds Clo",
    "sg:city":"Southampton",
    "sg:classifiers":[
        {
            "category":"Home & Garden",
            "subcategory":"Home Furnishings",
            "type":"Retail Goods"
        }
    ],
    "sg:phone":"+44 23 8066 3070",
    "sg:postcode":"SO40 3RZ",
    "sg:province":"Hampshire",
    "sg:tags":[
        "awning",
        "canopy",
        "blinds"
    ],
    "wof:name":"Sun 2 Shade Ltd",
    "wof:placetype":"venue"
},
  "geometry": {"coordinates":[-1.50035,50.922382],"type":"Point"}
}