{
  "type": "Feature",
  "properties": {
    "addr:full":"199 Rush Green Rd Romford Essex RM7 0JR",
    "addr:housenumber":"199",
    "addr:postcode":"rm7 0jr",
    "addr:street":"Rush Green Rd",
    "iso:country":"GB",
    "sg:address":"199 Rush Green Rd",
    "sg:city":"Romford",
    "sg:classifiers":[
        {
            "category":"Insurance",
            "subcategory":"Insurance Agent",
            "type":"Services"
        }
    ],
    "sg:postcode":"RM7 0JR",
    "sg:province":"Essex",
    "sg:tags":[
        "broker"
    ],
    "wof:name":"Farmer Insurance Consultants Ltd",
    "wof:placetype":"venue"
},
  "geometry": {"coordinates":[0.16003,51.562698],"type":"Point"}
}