{
  "type": "Feature",
  "properties": {
    "addr:full":"1a Festing Buildings, Highland Road Southsea Hampshire PO4 9BZ",
    "addr:housenumber":"1a",
    "addr:postcode":"po4 9bz",
    "addr:street":"Festing Buildings Highland Road",
    "iso:country":"GB",
    "sg:address":"1a Festing Buildings, Highland Road",
    "sg:city":"Southsea",
    "sg:classifiers":[
        {
            "category":"Recreation",
            "type":"Entertainment"
        }
    ],
    "sg:phone":"+44 23 9282 0758",
    "sg:postcode":"PO4 9BZ",
    "sg:province":"Hampshire",
    "sg:tags":[
        "snooker",
        "billiards",
        "pool"
    ],
    "wof:name":"The Altis Centre",
    "wof:placetype":"venue"
},
  "geometry": {"coordinates":[-1.070203,50.784676],"type":"Point"}
}