{
  "type": "Feature",
  "properties": {
    "iso:country":"GB",
    "sg:address":"Pride Hill Ho, St Marys St",
    "sg:city":"Shrewsbury",
    "sg:classifiers":[
        {
            "category":"Insurance",
            "subcategory":"Insurance Agent",
            "type":"Services"
        }
    ],
    "sg:phone":"+44 1743 235202",
    "sg:postcode":"SY1 1ED",
    "sg:province":"Shropshire",
    "wof:name":"Royal & SunAlliance Life & Pensions",
    "wof:placetype":"venue"
},
  "geometry": {"coordinates":[-2.752894,52.70882],"type":"Point"}
}