{
  "type": "Feature",
  "properties": {
    "addr:full":"Tooke House, 20 Bull Plain Hertford Hertfordshire SG14 1DT",
    "addr:housenumber":"20",
    "addr:postcode":"sg14 1dt",
    "addr:street":"Bull Plain",
    "iso:country":"GB",
    "sg:address":"Tooke House, 20 Bull Plain",
    "sg:city":"Hertford",
    "sg:classifiers":[
        {
            "category":"Professional",
            "subcategory":"Lawyer & Legal Services",
            "type":"Services"
        },
        {
            "category":"Organizations",
            "subcategory":"Non-profit Organization",
            "type":"Services"
        }
    ],
    "sg:phone":"+44 1992 581441",
    "sg:postcode":"SG14 1DT",
    "sg:province":"Hertfordshire",
    "sg:tags":[
        "charitable",
        "advice",
        "organisation",
        "counselling",
        "charity"
    ],
    "sg:website":"http://www.citizensadvice.org.uk",
    "wof:name":"Hertford Citizens Advice Bureau",
    "wof:placetype":"venue"
},
  "geometry": {"coordinates":[-0.078396,51.7976303101],"type":"Point"}
}