{
  "type": "Feature",
  "properties": {
    "addr:full":"43 Meeting House Lane Brighton East Sussex BN1 1HB",
    "addr:housenumber":"43",
    "addr:postcode":"bn1 1hb",
    "addr:street":"Meeting House Lane",
    "iso:country":"GB",
    "sg:address":"43 Meeting House Lane",
    "sg:city":"Brighton",
    "sg:classifiers":[
        {
            "category":"Shopping",
            "subcategory":"Comic Books",
            "type":"Retail Goods"
        }
    ],
    "sg:phone":"+44 1273 202526",
    "sg:postcode":"BN1 1HB",
    "sg:province":"East Sussex",
    "sg:tags":[
        "jeweller"
    ],
    "wof:name":"The Ring Shop",
    "wof:placetype":"venue"
},
  "geometry": {"coordinates":[-0.1403719932,50.8215446472],"type":"Point"}
}