{
  "type": "Feature",
  "properties": {
    "iso:country":"GB",
    "sg:address":"4 Falmouth Road, Ford Estate",
    "sg:city":"Sunderland",
    "sg:classifiers":[
        {
            "category":"Real Estate",
            "subcategory":"Architect",
            "type":"Services"
        }
    ],
    "sg:phone":"+44 191 567 7986",
    "sg:postcode":"SR4 6XF",
    "sg:province":"Tyne and Wear",
    "wof:name":"Newfactor Ltd.",
    "wof:placetype":"venue"
},
  "geometry": {"coordinates":[-1.422352,54.905842],"type":"Point"}
}