{
  "type": "Feature",
  "properties": {
    "iso:country":"GB",
    "sg:address":"James Street West",
    "sg:city":"Bath",
    "sg:classifiers":[
        {
            "category":"Shopping",
            "subcategory":"Gifts & Souvenirs",
            "type":"Retail Goods"
        }
    ],
    "sg:phone":"+44 1225 444228",
    "sg:postcode":"BA1 2BT",
    "sg:province":"Bath and North East Somerset",
    "sg:tags":[
        "greeting",
        "card"
    ],
    "wof:name":"Gordon Fraser Gallery",
    "wof:placetype":"venue"
},
  "geometry": {"coordinates":[-2.367184,51.382038],"type":"Point"}
}