{
  "type": "Feature",
  "properties": {
    "iso:country":"GB",
    "sg:address":"45 Clwyd Street",
    "sg:city":"Ruthin",
    "sg:classifiers":[
        {
            "category":"Fast Food",
            "type":"Food & Drink"
        }
    ],
    "sg:phone":"+44 1824 702518",
    "sg:postcode":"LL15 1HH",
    "sg:province":"Denbighshire",
    "sg:tags":[
        "away",
        "meal",
        "outlet",
        "take"
    ],
    "wof:name":"FINNS",
    "wof:placetype":"venue"
},
  "geometry": {"coordinates":[-3.3131289482,53.1137199402],"type":"Point"}
}