{
  "type": "Feature",
  "properties": {
    "iso:country":"GB",
    "sg:address":"Unit 17 Crown Walks",
    "sg:city":"Bicester",
    "sg:classifiers":[
        {
            "category":"Professional",
            "subcategory":"Business Services",
            "type":"Services"
        }
    ],
    "sg:phone":"+44 1869 320032",
    "sg:postcode":"OX26 6JD",
    "sg:province":"Oxfordshire",
    "sg:tags":[
        "import",
        "export",
        "agent"
    ],
    "wof:name":"Direct Sales",
    "wof:placetype":"venue"
},
  "geometry": {"coordinates":[-1.1535400152,51.8980255127],"type":"Point"}
}