{
  "type": "Feature",
  "properties": {
    "addr:full":"177 Northdown Road, Cliftonville Margate Kent CT9 2PA",
    "addr:housenumber":"177",
    "addr:postcode":"ct9 2pa",
    "addr:street":"Northdown Road;Margate",
    "iso:country":"GB",
    "sg:address":"177 Northdown Road, Cliftonville",
    "sg:city":"Margate",
    "sg:classifiers":[
        {
            "category":"Manufacturing",
            "subcategory":"Petroleum Products",
            "type":"Manufacturing & Wholesale Goods"
        }
    ],
    "sg:phone":"+44 1843 297777",
    "sg:postcode":"CT9 2PA",
    "sg:province":"Kent",
    "sg:tags":[
        "double",
        "glazing"
    ],
    "wof:name":"Just Windows & Conservatories",
    "wof:placetype":"venue"
},
  "geometry": {"coordinates":[1.398342,51.387684],"type":"Point"}
}