{
  "type": "Feature",
  "properties": {
    "addr:full":"1 Pages Bldng(s) Boldon Colliery Tyne and Wear NE35 9AH",
    "addr:housenumber":"1",
    "addr:postcode":"ne35 9ah",
    "addr:street":"S",
    "iso:country":"GB",
    "sg:address":"1 Pages Bldng(s)",
    "sg:city":"Boldon Colliery",
    "sg:classifiers":[
        {
            "category":"Shopping",
            "subcategory":"News",
            "type":"Retail Goods"
        }
    ],
    "sg:phone":"+44 191 536 3492",
    "sg:postcode":"NE35 9AH",
    "sg:province":"Tyne and Wear",
    "sg:tags":[
        "newsagent"
    ],
    "wof:name":"Boldon Newsagents",
    "wof:placetype":"venue"
},
  "geometry": {"coordinates":[-1.4629509449,54.9511375427],"type":"Point"}
}