{
  "type": "Feature",
  "properties": {
    "iso:country":"GB",
    "sg:address":"4 Fairfield Close",
    "sg:city":"Christchurch",
    "sg:classifiers":[
        {
            "category":"Professional",
            "subcategory":"Accounting & Tax Preparation",
            "type":"Services"
        }
    ],
    "sg:postcode":"BH23 1QZ",
    "sg:province":"Dorset",
    "sg:tags":[
        "accountant"
    ],
    "wof:name":"Howard Baker",
    "wof:placetype":"venue"
},
  "geometry": {"coordinates":[-1.780039,50.73967],"type":"Point"}
}