{
  "type": "Feature",
  "properties": {
    "addr:full":"76-78 Duchy Road Harrogate North Yorkshire HG1 2HA",
    "addr:housenumber":"76-78",
    "addr:postcode":"hg1 2ha",
    "addr:street":"Duchy Road",
    "iso:country":"GB",
    "sg:address":"76-78 Duchy Road",
    "sg:city":"Harrogate",
    "sg:classifiers":[
        {
            "category":"Health Services",
            "subcategory":"Nursing And Care Facility",
            "type":"Services"
        }
    ],
    "sg:phone":"+44 1423 523939",
    "sg:postcode":"HG1 2HA",
    "sg:province":"North Yorkshire",
    "sg:tags":[
        "home"
    ],
    "wof:name":"Oakville Park Nursing Residential Home",
    "wof:placetype":"venue"
},
  "geometry": {"coordinates":[-1.556929,53.993771],"type":"Point"}
}