{
  "type": "Feature",
  "properties": {
    "iso:country":"GB",
    "sg:address":"254 Higham Hill Road",
    "sg:city":"Walthamstow",
    "sg:classifiers":[
        {
            "category":"Shopping",
            "subcategory":"Used Merchandise",
            "type":"Retail Goods"
        }
    ],
    "sg:phone":"+44 20 8925 0115",
    "sg:postcode":"E17 5RQ",
    "sg:province":"Greater London",
    "sg:tags":[
        "shop",
        "second-hand"
    ],
    "wof:name":"Let-save",
    "wof:placetype":"venue"
},
  "geometry": {"coordinates":[-0.034717,51.594963],"type":"Point"}
}