{
  "type": "Feature",
  "properties": {
    "iso:country":"GB",
    "sg:address":"Cadogan Street, North Ormesby",
    "sg:city":"Middlesbrough",
    "sg:classifiers":[
        {
            "category":"Education",
            "subcategory":"School",
            "type":"Public Place"
        }
    ],
    "sg:phone":"+44 1642 243400",
    "sg:postcode":"TS3 6PX",
    "sg:province":"North Yorkshire",
    "sg:tags":[
        "local",
        "authority"
    ],
    "wof:name":"St Alphonsus R C Primary School",
    "wof:placetype":"venue"
},
  "geometry": {"coordinates":[-1.2092159986,54.5691261292],"type":"Point"}
}