{
  "type": "Feature",
  "properties": {
    "iso:country":"GB",
    "sg:address":"Marble Arch House, 66-68 Seymour Street",
    "sg:city":"London",
    "sg:classifiers":[
        {
            "category":"Professional",
            "subcategory":"Management & Consulting",
            "type":"Services"
        }
    ],
    "sg:phone":"+44 20 7262 5040",
    "sg:postcode":"W1H 5AF",
    "sg:province":"Greater London",
    "sg:tags":[
        "consultant",
        "business"
    ],
    "wof:name":"Driveglade Ltd.",
    "wof:placetype":"venue"
},
  "geometry": {"coordinates":[-0.1626009941,51.5187034607],"type":"Point"}
}