{
  "type": "Feature",
  "properties": {
    "addr:full":"Park House, Courtenay Park Newton Abbot Devon TQ12 4PS",
    "addr:postcode":"tq12 4ps",
    "addr:street":"Courtenay Park",
    "iso:country":"GB",
    "sg:address":"Park House, Courtenay Park",
    "sg:city":"Newton Abbot",
    "sg:classifiers":[
        {
            "category":"Home & Garden",
            "subcategory":"Garden Supply",
            "type":"Retail Goods"
        },
        {
            "category":"Manufacturing",
            "subcategory":"Glass & Minerals",
            "type":"Manufacturing & Wholesale Goods"
        },
        {
            "category":"Manufacturing",
            "subcategory":"Pottery",
            "type":"Manufacturing & Wholesale Goods"
        }
    ],
    "sg:phone":"+44 1270 765245",
    "sg:postcode":"TQ12 4PS",
    "sg:province":"Devon",
    "sg:tags":[
        "stone",
        "slate",
        "product",
        "chalk",
        "sand",
        "clay",
        "gravel"
    ],
    "wof:name":"W B B Devon Clays Ltd.",
    "wof:placetype":"venue"
},
  "geometry": {"coordinates":[-3.6014380455,50.5299377441],"type":"Point"}
}