{
  "type": "Feature",
  "properties": {
    "addr:full":"Birchill Road, Knowsley Industrial Park Liverpool Lancashire L33 7TD",
    "addr:postcode":"l33 7td",
    "addr:street":"Birchill Road;Industrial Park",
    "iso:country":"GB",
    "sg:address":"Birchill Road, Knowsley Industrial Park",
    "sg:city":"Liverpool",
    "sg:classifiers":[
        {
            "category":"Professional",
            "subcategory":"Engineering",
            "type":"Services"
        }
    ],
    "sg:phone":"+44 151 548 4004",
    "sg:postcode":"L33 7TD",
    "sg:province":"Lancashire",
    "sg:tags":[
        "merchant",
        "engineer"
    ],
    "wof:name":"J R Webster & Co. Ltd.",
    "wof:placetype":"venue"
},
  "geometry": {"coordinates":[-2.8554289341,53.4847564697],"type":"Point"}
}