{
  "type": "Feature",
  "properties": {
    "iso:country":"GB",
    "sg:address":"7 Queen Victoria Road",
    "sg:city":"Coventry",
    "sg:classifiers":[
        {
            "category":"Banks & Credit Unions",
            "subcategory":"Financial Services",
            "type":"Services"
        }
    ],
    "sg:phone":"+44 24 7622 0200",
    "sg:postcode":"CV1 3JS",
    "sg:province":"West Midlands",
    "sg:tags":[
        "adviser",
        "independent"
    ],
    "wof:name":"The Financial Advice Bureau",
    "wof:placetype":"venue"
},
  "geometry": {"coordinates":[-1.515865,52.405602],"type":"Point"}
}