{
  "type": "Feature",
  "properties": {
    "iso:country":"GB",
    "sg:address":"Unit 1a Old Redding Rd",
    "sg:city":"Falkirk",
    "sg:classifiers":[
        {
            "category":"Parking",
            "type":"Transportation"
        }
    ],
    "sg:phone":"+44 1324 639666",
    "sg:postcode":"FK1 5AA",
    "sg:province":"Falkirk",
    "sg:tags":[
        "car",
        "valet"
    ],
    "wof:name":"Quickclean",
    "wof:placetype":"venue"
},
  "geometry": {"coordinates":[-3.78988,55.99765],"type":"Point"}
}