{
  "type": "Feature",
  "properties": {
    "addr:full":"9 London Road Peterborough Cambridgeshire PE2 8AN",
    "addr:housenumber":"9",
    "addr:postcode":"pe2 8an",
    "addr:street":"London Road",
    "iso:country":"GB",
    "sg:address":"9 London Road",
    "sg:city":"Peterborough",
    "sg:classifiers":[
        {
            "category":"Building & Trades",
            "subcategory":"Construction",
            "type":"Services"
        }
    ],
    "sg:phone":"+44 1733 349436",
    "sg:postcode":"PE2 8AN",
    "sg:province":"Cambridgeshire",
    "sg:tags":[
        "window",
        "replacement"
    ],
    "wof:name":"Aspen Windows Ltd.",
    "wof:placetype":"venue"
},
  "geometry": {"coordinates":[-0.2419629991,52.5656547546],"type":"Point"}
}