{
  "type": "Feature",
  "properties": {
    "iso:country":"GB",
    "sg:address":"64-66 High St",
    "sg:city":"Sheerness",
    "sg:classifiers":[
        {
            "category":"Bars & Pubs",
            "type":"Food & Drink"
        }
    ],
    "sg:phone":"+44 1795 580149",
    "sg:postcode":"ME12 1NL",
    "sg:province":"Kent",
    "sg:tags":[
        "pubs",
        "inn"
    ],
    "wof:name":"Tudor Inn (The)",
    "wof:placetype":"venue"
},
  "geometry": {"coordinates":[0.761686,51.44038],"type":"Point"}
}