{
  "type": "Feature",
  "properties": {
    "addr:full":"30a Croham Rd South Croydon Surrey CR2 7BA",
    "addr:housenumber":"30a",
    "addr:postcode":"cr2 7ba",
    "addr:street":"Croham Rd",
    "iso:country":"GB",
    "sg:address":"30a Croham Rd",
    "sg:city":"South Croydon",
    "sg:classifiers":[
        {
            "category":"Building & Trades",
            "subcategory":"Construction",
            "type":"Services"
        }
    ],
    "sg:postcode":"CR2 7BA",
    "sg:province":"Surrey",
    "sg:tags":[
        "welder"
    ],
    "wof:name":"Bush Fabrications",
    "wof:placetype":"venue"
},
  "geometry": {"coordinates":[-0.0936459973,51.3621482849],"type":"Point"}
}