{
  "type": "Feature",
  "properties": {
    "addr:full":"Addenbrooke Street Wednesbury West Midlands WS10 8HQ",
    "addr:postcode":"ws10 8hq",
    "addr:street":"Addenbrooke Street",
    "iso:country":"GB",
    "sg:address":"Addenbrooke Street",
    "sg:city":"Wednesbury",
    "sg:classifiers":[
        {
            "category":"Retail",
            "subcategory":"Auto Repair",
            "type":"Services"
        }
    ],
    "sg:phone":"+44 121 526 2644",
    "sg:postcode":"WS10 8HQ",
    "sg:province":"West Midlands",
    "sg:tags":[
        "modification",
        "garage"
    ],
    "wof:name":"Darlaston Motor Services Ltd.",
    "wof:placetype":"venue"
},
  "geometry": {"coordinates":[-2.037894,52.575726],"type":"Point"}
}