{
  "type": "Feature",
  "properties": {
    "iso:country":"GB",
    "sg:address":"17a Lynn Rd",
    "sg:city":"Swaffham",
    "sg:classifiers":[
        {
            "category":"Shopping",
            "subcategory":"Musical Instruments",
            "type":"Retail Goods"
        }
    ],
    "sg:phone":"+44 1760 720876",
    "sg:postcode":"PE37 7AY",
    "sg:province":"Norfolk",
    "wof:name":"Chris Simmons",
    "wof:placetype":"venue"
},
  "geometry": {"coordinates":[0.682002008,52.6500015259],"type":"Point"}
}