{
  "type": "Feature",
  "properties": {
    "iso:country":"GB",
    "sg:address":"Beaufort Road",
    "sg:city":"Sale",
    "sg:classifiers":[
        {
            "category":"Communications",
            "type":"Services"
        }
    ],
    "sg:postcode":"M33 3WN",
    "sg:province":"Cheshire",
    "sg:tags":[
        "data",
        "network"
    ],
    "wof:name":"Lancelot Communications",
    "wof:placetype":"venue"
},
  "geometry": {"coordinates":[-2.315309,53.416031],"type":"Point"}
}