{
  "type": "Feature",
  "properties": {
    "addr:full":"248 Easter Road Edinburgh City of Edinburgh EH6 8LD",
    "addr:housenumber":"248",
    "addr:postcode":"eh6 8ld",
    "addr:street":"Easter Road",
    "iso:country":"GB",
    "sg:address":"248 Easter Road",
    "sg:city":"Edinburgh",
    "sg:classifiers":[
        {
            "category":"Autos & Motor Vehicles",
            "subcategory":"Auto Supplies",
            "type":"Retail Goods"
        }
    ],
    "sg:phone":"+44 131 554 3344",
    "sg:postcode":"EH6 8LD",
    "sg:province":"City of Edinburgh",
    "sg:tags":[
        "tyre"
    ],
    "wof:name":"Thistle Tyre & Auto Centres Ltd.",
    "wof:placetype":"venue"
},
  "geometry": {"coordinates":[-3.170511961,55.9635772705],"type":"Point"}
}