{
  "type": "Feature",
  "properties": {
    "iso:country":"GB",
    "sg:address":"343 Rayleigh Rd",
    "sg:city":"Benfleet",
    "sg:classifiers":[
        {
            "category":"Professional",
            "subcategory":"Testing Lab",
            "type":"Services"
        }
    ],
    "sg:phone":"+44 1268 741184",
    "sg:postcode":"SS7 3XA",
    "sg:province":"Essex",
    "sg:tags":[
        "mot"
    ],
    "wof:name":"Woodmans Garage",
    "wof:placetype":"venue"
},
  "geometry": {"coordinates":[0.595172,51.569172],"type":"Point"}
}