{
  "type": "Feature",
  "properties": {
    "iso:country":"GB",
    "sg:address":"68c Kirklington Road, Rainworth",
    "sg:city":"Mansfield",
    "sg:classifiers":[
        {
            "category":"Personal",
            "subcategory":"Beauty Salon",
            "type":"Services"
        }
    ],
    "sg:phone":"+44 1623 795511",
    "sg:postcode":"NG21 0JX",
    "sg:province":"Nottinghamshire",
    "sg:tags":[
        "unisex",
        "hairdresser"
    ],
    "wof:name":"Hed Hunters",
    "wof:placetype":"venue"
},
  "geometry": {"coordinates":[-1.108674,53.11935],"type":"Point"}
}