{
  "type": "Feature",
  "properties": {
    "addr:full":"18 Peel Sq Barnsley South Yorkshire S70 1YA",
    "addr:housenumber":"18",
    "addr:postcode":"s70 1ya",
    "addr:street":"Peel Sq;Yorkshire",
    "iso:country":"GB",
    "sg:address":"18 Peel Sq",
    "sg:city":"Barnsley",
    "sg:classifiers":[
        {
            "category":"Bars & Pubs",
            "type":"Food & Drink"
        }
    ],
    "sg:phone":"+44 1226 770564",
    "sg:postcode":"S70 1YA",
    "sg:province":"South Yorkshire",
    "sg:tags":[
        "pubs",
        "inn"
    ],
    "wof:name":"Punch Retail Ltd",
    "wof:placetype":"venue"
},
  "geometry": {"coordinates":[-1.4821289778,53.5522689819],"type":"Point"}
}