{
  "type": "Feature",
  "properties": {
    "addr:full":"82 Above Bar Street Southampton Hampshire SO14 7DT",
    "addr:housenumber":"82",
    "addr:postcode":"so14 7dt",
    "addr:street":"Above Bar Street",
    "iso:country":"GB",
    "sg:address":"82 Above Bar Street",
    "sg:city":"Southampton",
    "sg:classifiers":[
        {
            "category":"Shopping",
            "subcategory":"Bicycles & Sporting Goods",
            "type":"Retail Goods"
        },
        {
            "category":"Sports & Exercise",
            "subcategory":"Sports Center",
            "type":"Entertainment"
        }
    ],
    "sg:phone":"+44 23 8022 5440",
    "sg:postcode":"SO14 7DT",
    "sg:province":"Hampshire",
    "sg:tags":[
        "shop",
        "sale"
    ],
    "wof:name":"J J B Sports Plc",
    "wof:placetype":"venue"
},
  "geometry": {"coordinates":[-1.4042849541,50.9052124023],"type":"Point"}
}