{
  "type": "Feature",
  "properties": {
    "iso:country":"GB",
    "sg:address":"128-130 Carshalton Rd",
    "sg:city":"Sutton",
    "sg:classifiers":[
        {
            "category":"Manufacturing",
            "subcategory":"Electronics",
            "type":"Manufacturing & Wholesale Goods"
        }
    ],
    "sg:phone":"+44 20 8643 0452",
    "sg:postcode":"SM1 4TW",
    "sg:province":"Surrey",
    "sg:tags":[
        "control",
        "component",
        "-",
        "electronic"
    ],
    "wof:name":"Sense Technology",
    "wof:placetype":"venue"
},
  "geometry": {"coordinates":[-0.185462,51.36248],"type":"Point"}
}