{
  "type": "Feature",
  "properties": {
    "addr:full":"22 Cedar Close, Ditton Aylesford Kent ME20 6EN",
    "addr:housenumber":"22",
    "addr:postcode":"me20 6en",
    "addr:street":"Cedar Close;Aylesford",
    "iso:country":"GB",
    "sg:address":"22 Cedar Close, Ditton",
    "sg:city":"Aylesford",
    "sg:classifiers":[
        {
            "category":"Retail",
            "subcategory":"Auto Repair",
            "type":"Services"
        }
    ],
    "sg:phone":"+44 1622 790069",
    "sg:postcode":"ME20 6EN",
    "sg:province":"Kent",
    "sg:tags":[
        "electrician"
    ],
    "wof:name":"Vehicle Electrics & Communications",
    "wof:placetype":"venue"
},
  "geometry": {"coordinates":[0.4584029913,51.2945137024],"type":"Point"}
}