{
  "type": "Feature",
  "properties": {
    "addr:full":"South Ashford Centre Ashford Kent TN23 5RN",
    "addr:postcode":"tn23 5rn",
    "addr:street":"South Ashford Centre",
    "iso:country":"GB",
    "sg:address":"South Ashford Centre",
    "sg:city":"Ashford",
    "sg:classifiers":[
        {
            "category":"Organizations",
            "subcategory":"Membership Organization",
            "type":"Services"
        }
    ],
    "sg:postcode":"TN23 5RN",
    "sg:province":"Kent",
    "sg:tags":[
        "club"
    ],
    "wof:name":"The Funzone",
    "wof:placetype":"venue"
},
  "geometry": {"coordinates":[0.844675,51.128895],"type":"Point"}
}