{
  "type": "Feature",
  "properties": {
    "iso:country":"GB",
    "sg:address":"264 Milton Road",
    "sg:city":"Weston-super-mare",
    "sg:classifiers":[
        {
            "category":"Manufacturing",
            "subcategory":"Metals",
            "type":"Manufacturing & Wholesale Goods"
        }
    ],
    "sg:phone":"+44 1934 412665",
    "sg:postcode":"BS22 8EN",
    "sg:province":"Somerset",
    "sg:tags":[
        "die-casting"
    ],
    "wof:name":"K G Diecasting (Weston) Ltd.",
    "wof:placetype":"venue"
},
  "geometry": {"coordinates":[-2.944067955,51.3538894653],"type":"Point"}
}