{
  "type": "Feature",
  "properties": {
    "addr:full":"Norwich Road, Ludham Great Yarmouth Norfolk NR29 5QA",
    "addr:postcode":"nr29 5qa",
    "addr:street":"Norwich Road;Yarmouth",
    "iso:country":"GB",
    "sg:address":"Norwich Road, Ludham",
    "sg:city":"Great Yarmouth",
    "sg:classifiers":[
        {
            "category":"Cafe",
            "type":"Food & Drink"
        }
    ],
    "sg:phone":"+44 1692 678384",
    "sg:postcode":"NR29 5QA",
    "sg:province":"Norfolk",
    "sg:tags":[
        "tea",
        "room"
    ],
    "wof:name":"Alfresco Eating House",
    "wof:placetype":"venue"
},
  "geometry": {"coordinates":[1.533655,52.709949],"type":"Point"}
}