{
  "type": "Feature",
  "properties": {
    "iso:country":"GB",
    "sg:address":"56 Hillview Crescent",
    "sg:city":"Banbury",
    "sg:classifiers":[
        {
            "category":"Professional",
            "type":"Services"
        }
    ],
    "sg:phone":"+44 1295 250299",
    "sg:postcode":"OX16 1DN",
    "sg:province":"Oxfordshire",
    "sg:tags":[
        "entertainer"
    ],
    "wof:name":"Party Time",
    "wof:placetype":"venue"
},
  "geometry": {"coordinates":[-1.359215,52.069733],"type":"Point"}
}