{
  "type": "Feature",
  "properties": {
    "iso:country":"GB",
    "sg:address":"Unit C St Helens Retail Park, Warrington New Rd",
    "sg:city":"St Helens",
    "sg:classifiers":[
        {
            "category":"Home & Garden",
            "subcategory":"Carpets & Floor Coverings",
            "type":"Retail Goods"
        }
    ],
    "sg:phone":"+44 1744 737275",
    "sg:postcode":"WA9 1JJ",
    "sg:province":"Cheshire",
    "sg:tags":[
        "carpets",
        "rug",
        "matting"
    ],
    "wof:name":"Carpet Depot",
    "wof:placetype":"venue"
},
  "geometry": {"coordinates":[-2.72706,53.449081],"type":"Point"}
}