{
  "type": "Feature",
  "properties": {
    "iso:country":"GB",
    "sg:address":"Tisman's Common",
    "sg:city":"Horsham",
    "sg:classifiers":[
        {
            "category":"Place Of Worship",
            "type":"Public Place"
        }
    ],
    "sg:phone":"+44 1403 822127",
    "sg:postcode":"RH12 3BZ",
    "sg:province":"West Sussex",
    "wof:name":"St John The Baptist C of E Church",
    "wof:placetype":"venue"
},
  "geometry": {"coordinates":[-0.4456200004,51.0925292969],"type":"Point"}
}