{
  "type": "Feature",
  "properties": {
    "addr:full":"Redwither Road Wrexham Wrexham LL13 9RD",
    "addr:postcode":"ll13 9rd",
    "addr:street":"Redwither Road",
    "iso:country":"GB",
    "sg:address":"Redwither Road",
    "sg:city":"Wrexham",
    "sg:classifiers":[
        {
            "category":"Building & Trades",
            "subcategory":"Cleaning & Sanitation",
            "type":"Services"
        }
    ],
    "sg:phone":"+44 1978 661706",
    "sg:postcode":"LL13 9RD",
    "sg:province":"Wrexham",
    "sg:tags":[
        "blast"
    ],
    "wof:name":"R C Motors",
    "wof:placetype":"venue"
},
  "geometry": {"coordinates":[-2.9234340191,53.0386695862],"type":"Point"}
}