{
  "type": "Feature",
  "properties": {
    "iso:country":"GB",
    "sg:address":"4 King Street",
    "sg:city":"Whitehaven",
    "sg:classifiers":[
        {
            "category":"Recreation",
            "subcategory":"Fishing",
            "type":"Entertainment"
        }
    ],
    "sg:postcode":"CA28 7LA",
    "sg:province":"Cumbria",
    "sg:tags":[
        "angling"
    ],
    "wof:name":"The Compleat Angler",
    "wof:placetype":"venue"
},
  "geometry": {"coordinates":[-3.5900990963,54.5480651855],"type":"Point"}
}