{
  "type": "Feature",
  "properties": {
    "iso:country":"GB",
    "sg:address":"2 Victoria Bridge",
    "sg:city":"Penarth",
    "sg:classifiers":[
        {
            "category":"Home & Garden",
            "subcategory":"Household Appliances",
            "type":"Retail Goods"
        }
    ],
    "sg:phone":"+44 29 2070 2137",
    "sg:postcode":"CF64 2AN",
    "sg:province":"The Vale of Glamorgan",
    "sg:tags":[
        "electrical"
    ],
    "wof:name":"Ray Thomas",
    "wof:placetype":"venue"
},
  "geometry": {"coordinates":[-3.1777119637,51.4351654053],"type":"Point"}
}