{
  "type": "Feature",
  "properties": {
    "addr:full":"P O Box 1002 Bristol City of Bristol BS99 1WH",
    "addr:housenumber":"p o;1002",
    "addr:postcode":"bs99 1wh",
    "iso:country":"GB",
    "sg:address":"P O Box 1002",
    "sg:city":"Bristol",
    "sg:classifiers":[
        {
            "category":"Organizations",
            "subcategory":"Political Organization",
            "type":"Services"
        }
    ],
    "sg:phone":"+44 117 909 0063",
    "sg:postcode":"BS99 1WH",
    "sg:province":"City of Bristol",
    "sg:tags":[
        "party"
    ],
    "wof:name":"Dawn Primarolo MP",
    "wof:placetype":"venue"
},
  "geometry": {"coordinates":[-2.57421,51.458401],"type":"Point"}
}