{
  "type": "Feature",
  "properties": {
    "addr:full":"Higher Penrose Farm Helston Cornwall TR13 0RB",
    "addr:housenumber":"helston",
    "addr:postcode":"tr13 0rb",
    "iso:country":"GB",
    "sg:address":"Higher Penrose Farm",
    "sg:city":"Helston",
    "sg:classifiers":[
        {
            "category":"Farming",
            "subcategory":"Livestock Farm",
            "type":"Manufacturing & Wholesale Goods"
        }
    ],
    "sg:phone":"+44 1326 562372",
    "sg:postcode":"TR13 0RB",
    "sg:province":"Cornwall",
    "sg:tags":[
        "others"
    ],
    "wof:name":"J C Lane & Son",
    "wof:placetype":"venue"
},
  "geometry": {"coordinates":[-5.301784,50.08691],"type":"Point"}
}