{
  "type": "Feature",
  "properties": {
    "addr:full":"Redhill Road Ross-on-wye Gloucestershire HR9 5BJ",
    "addr:postcode":"hr9 5bj",
    "addr:street":"Redhill Road",
    "iso:country":"GB",
    "sg:address":"Redhill Road",
    "sg:city":"Ross-on-wye",
    "sg:classifiers":[
        {
            "category":"Professional",
            "subcategory":"Advertising",
            "type":"Services"
        }
    ],
    "sg:phone":"+44 1989 769200",
    "sg:postcode":"HR9 5BJ",
    "sg:province":"Gloucestershire",
    "wof:name":"Castle Leisure",
    "wof:placetype":"venue"
},
  "geometry": {"coordinates":[-2.5896139145,51.9100456238],"type":"Point"}
}