{
  "type": "Feature",
  "properties": {
    "addr:full":"156 Greenford Rd Harrow Greater London HA1 3QS",
    "addr:housenumber":"156",
    "addr:postcode":"ha1 3qs",
    "addr:street":"Greenford Rd",
    "iso:country":"GB",
    "sg:address":"156 Greenford Rd",
    "sg:city":"Harrow",
    "sg:classifiers":[
        {
            "category":"Food & Beverages",
            "subcategory":"Bakery",
            "type":"Retail Goods"
        }
    ],
    "sg:phone":"+44 20 8422 2177",
    "sg:postcode":"HA1 3QS",
    "sg:province":"Greater London",
    "sg:tags":[
        "baker"
    ],
    "wof:name":"Wenzel's The Bakers",
    "wof:placetype":"venue"
},
  "geometry": {"coordinates":[-0.335419,51.557514],"type":"Point"}
}