{
  "type": "Feature",
  "properties": {
    "iso:country":"GB",
    "sg:address":"Church Street, Hunslet",
    "sg:city":"Leeds",
    "sg:classifiers":[
        {
            "category":"Health Services",
            "subcategory":"Nursing And Care Facility",
            "type":"Services"
        }
    ],
    "sg:phone":"+44 113 277 1042",
    "sg:postcode":"LS10 2AY",
    "sg:province":"West Yorkshire",
    "sg:tags":[
        "home"
    ],
    "wof:name":"Copper Hill Residential & Nursing Home",
    "wof:placetype":"venue"
},
  "geometry": {"coordinates":[-1.526099,53.779636],"type":"Point"}
}