{
  "type": "Feature",
  "properties": {
    "addr:full":"15 Chestnut Drive, Berry Hill Mansfield Nottinghamshire NG18 4PW",
    "addr:housenumber":"15",
    "addr:postcode":"ng18 4pw",
    "addr:street":"Chestnut Drive",
    "iso:country":"GB",
    "sg:address":"15 Chestnut Drive, Berry Hill",
    "sg:city":"Mansfield",
    "sg:classifiers":[
        {
            "category":"Personal",
            "subcategory":"Beauty Salon",
            "type":"Services"
        }
    ],
    "sg:phone":"+44 1623 632435",
    "sg:postcode":"NG18 4PW",
    "sg:province":"Nottinghamshire",
    "sg:tags":[
        "unisex",
        "hairdresser"
    ],
    "wof:name":"Duo Hair & Beauty Salon",
    "wof:placetype":"venue"
},
  "geometry": {"coordinates":[-1.177063942,53.1238136292],"type":"Point"}
}