{
  "type": "Feature",
  "properties": {
    "addr:full":"32 Wokingham Road Reading Berkshire RG6 1JH",
    "addr:housenumber":"32",
    "addr:postcode":"rg6 1jh",
    "addr:street":"Wokingham Road",
    "iso:country":"GB",
    "sg:address":"32 Wokingham Road",
    "sg:city":"Reading",
    "sg:classifiers":[
        {
            "category":"Home & Garden",
            "subcategory":"Hardware",
            "type":"Retail Goods"
        }
    ],
    "sg:postcode":"RG6 1JH",
    "sg:province":"Berkshire",
    "sg:tags":[
        "lawnmowers",
        "machinery"
    ],
    "wof:name":"Pile Mower Services",
    "wof:placetype":"venue"
},
  "geometry": {"coordinates":[-0.9455320239,51.4521446228],"type":"Point"}
}