{
  "type": "Feature",
  "properties": {
    "iso:country":"GB",
    "sg:address":"10-12 Waterloo Square",
    "sg:city":"Bognor Regis",
    "sg:classifiers":[
        {
            "category":"Fast Food",
            "type":"Food & Drink"
        }
    ],
    "sg:phone":"+44 1243 840992",
    "sg:postcode":"PO21 1SU",
    "sg:province":"West Sussex",
    "sg:tags":[
        "away",
        "meal",
        "outlet",
        "take"
    ],
    "wof:name":"Pizzaroma",
    "wof:placetype":"venue"
},
  "geometry": {"coordinates":[-0.6755200028,50.7822723389],"type":"Point"}
}