{
  "type": "Feature",
  "properties": {
    "iso:country":"GB",
    "sg:address":"Saberdene, Church Road, Catsfield",
    "sg:city":"Battle",
    "sg:classifiers":[
        {
            "category":"Professional",
            "subcategory":"Computer Services",
            "type":"Services"
        }
    ],
    "sg:phone":"+44 1424 892440",
    "sg:postcode":"TN33 9DP",
    "sg:province":"East Sussex",
    "sg:tags":[
        "information"
    ],
    "wof:name":"The Garlic Centre",
    "wof:placetype":"venue"
},
  "geometry": {"coordinates":[0.448029995,50.8961868286],"type":"Point"}
}