{
  "type": "Feature",
  "properties": {
    "addr:full":"Catherine Crescent, Cymmer Porth Bridgend CF39 9AF",
    "addr:postcode":"cf39 9af",
    "addr:street":"Catherine Crescent",
    "iso:country":"GB",
    "sg:address":"Catherine Crescent, Cymmer",
    "sg:city":"Porth",
    "sg:classifiers":[
        {
            "category":"Manufacturing",
            "subcategory":"Rubber & Plastics",
            "type":"Manufacturing & Wholesale Goods"
        }
    ],
    "sg:phone":"+44 1443 682742",
    "sg:postcode":"CF39 9AF",
    "sg:province":"Bridgend",
    "sg:tags":[
        "injection",
        "moulding"
    ],
    "sg:website":"http://www.i12.com",
    "wof:name":"D K S Trimmings Ltd",
    "wof:placetype":"venue"
},
  "geometry": {"coordinates":[-3.4109508991,51.614982605],"type":"Point"}
}