{
  "type": "Feature",
  "properties": {
    "addr:full":"113 Ley St Ilford Essex IG1 4BH",
    "addr:housenumber":"113",
    "addr:postcode":"ig1 4bh",
    "addr:street":"Ley St",
    "iso:country":"GB",
    "sg:address":"113 Ley St",
    "sg:city":"Ilford",
    "sg:classifiers":[
        {
            "category":"Real Estate",
            "subcategory":"Real Estate Agent",
            "type":"Services"
        }
    ],
    "sg:phone":"+44 20 8478 2624",
    "sg:postcode":"IG1 4BH",
    "sg:province":"Essex",
    "wof:name":"East West Property Services",
    "wof:placetype":"venue"
},
  "geometry": {"coordinates":[0.0774400011,51.5618286133],"type":"Point"}
}