{
  "type": "Feature",
  "properties": {
    "addr:full":"49 Hollands Road Haverhill Essex CB9 8PJ",
    "addr:housenumber":"49",
    "addr:postcode":"cb9 8pj",
    "addr:street":"Hollands Road",
    "iso:country":"GB",
    "sg:address":"49 Hollands Road",
    "sg:city":"Haverhill",
    "sg:classifiers":[
        {
            "category":"Professional",
            "subcategory":"Engineering",
            "type":"Services"
        }
    ],
    "sg:phone":"+44 1440 705666",
    "sg:postcode":"CB9 8PJ",
    "sg:province":"Essex",
    "sg:tags":[
        "consulting",
        "engineer"
    ],
    "wof:name":"Vibration Maintainance Services Ltd.",
    "wof:placetype":"venue"
},
  "geometry": {"coordinates":[0.440188,52.076504],"type":"Point"}
}