{
  "type": "Feature",
  "properties": {
    "addr:full":"31 Earl Street London Greater London EC2A 2HR",
    "addr:housenumber":"31",
    "addr:postcode":"ec2a 2hr",
    "addr:street":"Earl Street",
    "iso:country":"GB",
    "sg:address":"31 Earl Street",
    "sg:city":"London",
    "sg:classifiers":[
        {
            "category":"Real Estate",
            "subcategory":"Architect",
            "type":"Services"
        }
    ],
    "sg:phone":"+44 20 7377 0577",
    "sg:postcode":"EC2A 2HR",
    "sg:province":"Greater London",
    "wof:name":"G A Partnership",
    "wof:placetype":"venue"
},
  "geometry": {"coordinates":[-0.08288,51.520626],"type":"Point"}
}