{
  "type": "Feature",
  "properties": {
    "addr:full":"146 South Park Road, Wimbledon London Greater London SW19 8TA",
    "addr:housenumber":"146",
    "addr:postcode":"sw19 8ta",
    "addr:street":"South Park Road",
    "iso:country":"GB",
    "sg:address":"146 South Park Road, Wimbledon",
    "sg:city":"London",
    "sg:classifiers":[
        {
            "category":"Manufacturing",
            "subcategory":"Building Materials",
            "type":"Manufacturing & Wholesale Goods"
        }
    ],
    "sg:phone":"+44 20 8542 9999",
    "sg:postcode":"SW19 8TA",
    "sg:province":"Greater London",
    "sg:tags":[
        "mnfr",
        "marble",
        "specialist"
    ],
    "wof:name":"Kleever Services Ltd.",
    "wof:placetype":"venue"
},
  "geometry": {"coordinates":[-0.191435,51.420979],"type":"Point"}
}