{
  "type": "Feature",
  "properties": {
    "addr:full":"21 Packham Court, Lavender Avenue Worcester Park Surrey KT4 8RS",
    "addr:housenumber":"21",
    "addr:postcode":"kt4 8rs",
    "addr:street":"Packham Court Lavender Avenue",
    "iso:country":"GB",
    "sg:address":"21 Packham Court, Lavender Avenue",
    "sg:city":"Worcester Park",
    "sg:classifiers":[
        {
            "category":"Arts & Performance",
            "subcategory":"Music",
            "type":"Entertainment"
        }
    ],
    "sg:phone":"+44 20 8330 5751",
    "sg:postcode":"KT4 8RS",
    "sg:province":"Surrey",
    "sg:tags":[
        "mobile",
        "disco"
    ],
    "wof:name":"Peter Lambeth",
    "wof:placetype":"venue"
},
  "geometry": {"coordinates":[-0.234934,51.375065],"type":"Point"}
}