{
  "type": "Feature",
  "properties": {
    "iso:country":"GB",
    "sg:address":"41 Widford Road, Hunsdon",
    "sg:city":"Ware",
    "sg:classifiers":[
        {
            "category":"Professional",
            "subcategory":"Engineering",
            "type":"Services"
        },
        {
            "category":"Building & Trades",
            "subcategory":"Electrical",
            "type":"Services"
        }
    ],
    "sg:phone":"+44 1279 843327",
    "sg:postcode":"SG12 8NN",
    "sg:province":"Hertfordshire",
    "sg:tags":[
        "engineer",
        "electrician",
        "contractor"
    ],
    "wof:name":"Robert P Prosser",
    "wof:placetype":"venue"
},
  "geometry": {"coordinates":[0.0543650016,51.8132705688],"type":"Point"}
}