{
  "type": "Feature",
  "properties": {
    "addr:full":"79 Arden Street Gillingham Kent ME7 1HS",
    "addr:housenumber":"79",
    "addr:postcode":"me7 1hs",
    "addr:street":"Arden Street",
    "iso:country":"GB",
    "sg:address":"79 Arden Street",
    "sg:city":"Gillingham",
    "sg:classifiers":[
        {
            "category":"Bars & Pubs",
            "type":"Food & Drink"
        },
        {
            "category":"Professional",
            "subcategory":"Computer Services",
            "type":"Services"
        }
    ],
    "sg:phone":"+44 1634 852553",
    "sg:postcode":"ME7 1HS",
    "sg:province":"Kent",
    "sg:tags":[
        "pubs",
        "inn",
        "system",
        "software"
    ],
    "wof:name":"Roseneath",
    "wof:placetype":"venue"
},
  "geometry": {"coordinates":[0.5452209711,51.3908348083],"type":"Point"}
}