{
  "type": "Feature",
  "properties": {
    "addr:full":"Weetslade Business Park, Dudley Cramlington Northumberland NE23 7PS",
    "addr:postcode":"ne23 7ps",
    "addr:street":"Dudley;Northumberland",
    "iso:country":"GB",
    "sg:address":"Weetslade Business Park, Dudley",
    "sg:city":"Cramlington",
    "sg:classifiers":[
        {
            "category":"Retail",
            "subcategory":"Auto Repair",
            "type":"Services"
        }
    ],
    "sg:phone":"+44 191 250 1130",
    "sg:postcode":"NE23 7PS",
    "sg:province":"Northumberland",
    "sg:tags":[
        "body",
        "car"
    ],
    "wof:name":"Dave King",
    "wof:placetype":"venue"
},
  "geometry": {"coordinates":[-1.5782940388,55.0556335449],"type":"Point"}
}