{
  "type": "Feature",
  "properties": {
    "iso:country":"GB",
    "sg:address":"35 Park Avenue, Northfleet",
    "sg:city":"Gravesend",
    "sg:classifiers":[
        {
            "category":"Building & Trades",
            "subcategory":"Cleaning & Sanitation",
            "type":"Services"
        }
    ],
    "sg:postcode":"DA11 8DW",
    "sg:province":"Kent",
    "sg:tags":[
        "cleaner",
        "window"
    ],
    "wof:name":"Kingsland Window Cleaning",
    "wof:placetype":"venue"
},
  "geometry": {"coordinates":[0.350302,51.436131],"type":"Point"}
}