{
  "type": "Feature",
  "properties": {
    "iso:country":"GB",
    "sg:address":"28 Old Brompton Road",
    "sg:city":"London",
    "sg:classifiers":[
        {
            "category":"Professional",
            "subcategory":"Management & Consulting",
            "type":"Services"
        }
    ],
    "sg:postcode":"SW7 3DL",
    "sg:province":"Greater London",
    "sg:tags":[
        "sport"
    ],
    "wof:name":"Mediator Worldwide Ltd.",
    "wof:placetype":"venue"
},
  "geometry": {"coordinates":[-0.175388,51.493641],"type":"Point"}
}