{
  "type": "Feature",
  "properties": {
    "addr:full":"29 Marlowe Drive, Whitecross Hereford Herefordshire HR4 0JL",
    "addr:housenumber":"29",
    "addr:postcode":"hr4 0jl",
    "addr:street":"Marlowe Drive Whitecross",
    "iso:country":"GB",
    "sg:address":"29 Marlowe Drive, Whitecross",
    "sg:city":"Hereford",
    "sg:classifiers":[
        {
            "category":"Freight",
            "type":"Transportation"
        }
    ],
    "sg:phone":"+44 1432 356014",
    "sg:postcode":"HR4 0JL",
    "sg:province":"Herefordshire",
    "sg:tags":[
        "haulage",
        "road"
    ],
    "wof:name":"Kens Tipper Hire",
    "wof:placetype":"venue"
},
  "geometry": {"coordinates":[-2.7402911186,52.0603179932],"type":"Point"}
}