{
  "type": "Feature",
  "properties": {
    "iso:country":"GB",
    "sg:address":"102 Tanners Lane",
    "sg:city":"Ilford",
    "sg:classifiers":[
        {
            "category":"Personal",
            "subcategory":"Beauty Salon",
            "type":"Services"
        }
    ],
    "sg:phone":"+44 20 8551 9200",
    "sg:postcode":"IG6 1QE",
    "sg:province":"Essex",
    "sg:tags":[
        "unisex",
        "hairdresser"
    ],
    "wof:name":"Nails & Beauty",
    "wof:placetype":"venue"
},
  "geometry": {"coordinates":[0.0817840025,51.587852478],"type":"Point"}
}