{
  "type": "Feature",
  "properties": {
    "addr:full":"Cantrell Rd, Bulwell Nottingham Nottinghamshire NG6 9HJ",
    "addr:postcode":"ng6 9hj",
    "addr:street":"Cantrell Rd",
    "iso:country":"GB",
    "sg:address":"Cantrell Rd, Bulwell",
    "sg:city":"Nottingham",
    "sg:classifiers":[
        {
            "category":"Education",
            "subcategory":"School",
            "type":"Public Place"
        }
    ],
    "sg:phone":"+44 115 915 5770",
    "sg:postcode":"NG6 9HJ",
    "sg:province":"Nottinghamshire",
    "sg:tags":[
        "local",
        "authority"
    ],
    "wof:name":"Cantrell Primary & Nursery School",
    "wof:placetype":"venue"
},
  "geometry": {"coordinates":[-1.1867640018,53.0016555786],"type":"Point"}
}