{
  "type": "Feature",
  "properties": {
    "iso:country":"GB",
    "sg:address":"Grosmont",
    "sg:city":"Abergavenny",
    "sg:classifiers":[
        {
            "category":"Sports & Exercise",
            "subcategory":"Race Track",
            "type":"Entertainment"
        }
    ],
    "sg:phone":"+44 1981 240254",
    "sg:postcode":"NP7 8HL",
    "sg:province":"Herefordshire",
    "sg:tags":[
        "motor"
    ],
    "wof:name":"The Point",
    "wof:placetype":"venue"
},
  "geometry": {"coordinates":[-2.868297,51.916309],"type":"Point"}
}