{
  "type": "Feature",
  "properties": {
    "iso:country":"GB",
    "sg:address":"Cliff St",
    "sg:city":"Mexborough",
    "sg:classifiers":[
        {
            "category":"Professional",
            "subcategory":"Business Services",
            "type":"Services"
        }
    ],
    "sg:phone":"+44 1709 579177",
    "sg:postcode":"S64 9HU",
    "sg:province":"South Yorkshire",
    "sg:tags":[
        "management",
        "pub"
    ],
    "wof:name":"Pub Management Services",
    "wof:placetype":"venue"
},
  "geometry": {"coordinates":[-1.290934,53.492687],"type":"Point"}
}