{
  "type": "Feature",
  "properties": {
    "iso:country":"GB",
    "sg:address":"68 Burgate",
    "sg:city":"Canterbury",
    "sg:classifiers":[
        {
            "category":"Retail",
            "subcategory":"Event Space",
            "type":"Services"
        },
        {
            "category":"Shopping",
            "subcategory":"News",
            "type":"Retail Goods"
        }
    ],
    "sg:phone":"+44 1227 767858",
    "sg:postcode":"CT1 2HJ",
    "sg:province":"Kent",
    "sg:tags":[
        "product",
        "newsagent",
        "tobacco",
        "sale"
    ],
    "wof:name":"The Pilgrim Shop",
    "wof:placetype":"venue"
},
  "geometry": {"coordinates":[1.084244,51.278046],"type":"Point"}
}