{
  "type": "Feature",
  "properties": {
    "addr:full":"High St Weston Super Mare Somerset BS23 1HP",
    "addr:postcode":"bs23 1hp",
    "addr:street":"High St",
    "iso:country":"GB",
    "sg:address":"High St",
    "sg:city":"Weston Super Mare",
    "sg:classifiers":[
        {
            "category":"Arts & Performance",
            "subcategory":"Theater",
            "type":"Entertainment"
        }
    ],
    "sg:phone":"+44 1934 645544",
    "sg:postcode":"BS23 1HP",
    "sg:province":"Somerset",
    "sg:tags":[
        "hall",
        "theatre",
        "concert"
    ],
    "wof:name":"The Playhouse Theatre",
    "wof:placetype":"venue"
},
  "geometry": {"coordinates":[-2.9792089462,51.3510513306],"type":"Point"}
}