{
  "type": "Feature",
  "properties": {
    "addr:full":"The Roger Ascham Site, Ascham Rd Cambridge Cambridgeshire CB4 2BD",
    "addr:postcode":"cb4 2bd",
    "addr:street":"Ascham Rd",
    "iso:country":"GB",
    "sg:address":"The Roger Ascham Site, Ascham Rd",
    "sg:city":"Cambridge",
    "sg:classifiers":[
        {
            "category":"Education",
            "subcategory":"Library",
            "type":"Public Place"
        }
    ],
    "sg:phone":"+44 1223 318362",
    "sg:postcode":"CB4 2BD",
    "sg:province":"Cambridgeshire",
    "sg:tags":[
        "book"
    ],
    "wof:name":"South Cambs Area Library Service",
    "wof:placetype":"venue"
},
  "geometry": {"coordinates":[0.1280400008,52.2183113098],"type":"Point"}
}