{
  "type": "Feature",
  "properties": {
    "addr:full":"10 Regent Street, Rolvenden Cranbrook Kent TN17 4PE",
    "addr:housenumber":"10",
    "addr:postcode":"tn17 4pe",
    "addr:street":"Regent Street",
    "iso:country":"GB",
    "sg:address":"10 Regent Street, Rolvenden",
    "sg:city":"Cranbrook",
    "sg:classifiers":[
        {
            "category":"Retail",
            "subcategory":"Repair Shop",
            "type":"Services"
        },
        {
            "category":"Shopping",
            "subcategory":"Antiques",
            "type":"Retail Goods"
        }
    ],
    "sg:phone":"+44 1580 241563",
    "sg:postcode":"TN17 4PE",
    "sg:province":"Kent",
    "sg:tags":[
        "restoration"
    ],
    "wof:name":"J D & R M Walters",
    "wof:placetype":"venue"
},
  "geometry": {"coordinates":[0.628248,51.05328],"type":"Point"}
}