{
  "type": "Feature",
  "properties": {
    "addr:full":"1 Arkwright Way, North Newmoor Irvine East Ayrshire KA11 4JU",
    "addr:housenumber":"1",
    "addr:postcode":"ka11 4ju",
    "addr:street":"Arkwright Way North Newmoor",
    "iso:country":"GB",
    "sg:address":"1 Arkwright Way, North Newmoor",
    "sg:city":"Irvine",
    "sg:classifiers":[
        {
            "category":"Wholesale",
            "subcategory":"Non-durable Goods",
            "type":"Manufacturing & Wholesale Goods"
        }
    ],
    "sg:postcode":"KA11 4JU",
    "sg:province":"East Ayrshire",
    "sg:tags":[
        "carry",
        "cash"
    ],
    "wof:name":"Adam Cunningham & Son Ltd.",
    "wof:placetype":"venue"
},
  "geometry": {"coordinates":[-4.6442089081,55.6165084839],"type":"Point"}
}