{
  "type": "Feature",
  "properties": {
    "iso:country":"GB",
    "sg:address":"Piers Cottage Hamlet, Slades Hill",
    "sg:city":"Templecombe",
    "sg:classifiers":[
        {
            "category":"Building & Trades",
            "subcategory":"Construction",
            "type":"Services"
        }
    ],
    "sg:postcode":"BA8 0HJ",
    "sg:province":"Somerset",
    "sg:tags":[
        "glazier"
    ],
    "wof:name":"Feltham,Andrew,",
    "wof:placetype":"venue"
},
  "geometry": {"coordinates":[-2.415287,51.001381],"type":"Point"}
}