{
  "type": "Feature",
  "properties": {
    "addr:full":"Unit 35, The Acorn Centre Oldham Lancashire OL1 3NE",
    "addr:housenumber":"unit 35",
    "addr:postcode":"ol1 3ne",
    "addr:street":"The",
    "iso:country":"GB",
    "sg:address":"Unit 35, The Acorn Centre",
    "sg:city":"Oldham",
    "sg:classifiers":[
        {
            "category":"Building & Trades",
            "subcategory":"Cleaning & Sanitation",
            "type":"Services"
        }
    ],
    "sg:phone":"+44 161 626 0352",
    "sg:postcode":"OL1 3NE",
    "sg:province":"Lancashire",
    "sg:tags":[
        "door",
        "manufacturer"
    ],
    "wof:name":"Waldor",
    "wof:placetype":"venue"
},
  "geometry": {"coordinates":[-2.095757,53.547592],"type":"Point"}
}