{
  "type": "Feature",
  "properties": {
    "iso:country":"GB",
    "sg:address":"77 Porthmawr Road",
    "sg:city":"Cwmbran",
    "sg:classifiers":[
        {
            "category":"Building & Trades",
            "subcategory":"Construction",
            "type":"Services"
        }
    ],
    "sg:phone":"+44 1633 872907",
    "sg:postcode":"NP44 1NA",
    "sg:province":"Monmouthshire",
    "sg:tags":[
        "glazier"
    ],
    "wof:name":"Classic Decorating",
    "wof:placetype":"venue"
},
  "geometry": {"coordinates":[-3.0229790211,51.6595153809],"type":"Point"}
}