{
  "type": "Feature",
  "properties": {
    "iso:country":"GB",
    "sg:address":"Unitg, Wylds Road",
    "sg:city":"Bridgwater",
    "sg:classifiers":[
        {
            "category":"Wholesale",
            "subcategory":"Machinery & Supplies",
            "type":"Manufacturing & Wholesale Goods"
        }
    ],
    "sg:phone":"+44 1278 727600",
    "sg:postcode":"TA6 4BH",
    "sg:province":"Somerset",
    "sg:tags":[
        "equipment",
        "-",
        "sale",
        "hydraulic",
        "accessory"
    ],
    "wof:name":"Hydrax Ltd",
    "wof:placetype":"venue"
},
  "geometry": {"coordinates":[-2.992689,51.139999],"type":"Point"}
}