{
  "type": "Feature",
  "properties": {
    "iso:country":"GB",
    "sg:address":"88 Preston Street",
    "sg:city":"Faversham",
    "sg:classifiers":[
        {
            "category":"Shopping",
            "subcategory":"Comic Books",
            "type":"Retail Goods"
        }
    ],
    "sg:postcode":"ME13 8NU",
    "sg:province":"Kent",
    "sg:tags":[
        "jeweller"
    ],
    "wof:name":"Barkers of Faversham",
    "wof:placetype":"venue"
},
  "geometry": {"coordinates":[0.891496,51.314972],"type":"Point"}
}