{
  "type": "Feature",
  "properties": {
    "iso:country":"GB",
    "sg:address":"55-61 Halton View Rd",
    "sg:city":"Widnes",
    "sg:classifiers":[
        {
            "category":"Cafe",
            "type":"Food & Drink"
        }
    ],
    "sg:phone":"+44 151 495 2337",
    "sg:postcode":"WA8 0TT",
    "sg:province":"Cheshire",
    "sg:tags":[
        "tea",
        "room"
    ],
    "wof:name":"Jaclens Cosy Cafe",
    "wof:placetype":"venue"
},
  "geometry": {"coordinates":[-2.712858,53.372803],"type":"Point"}
}