{
  "type": "Feature",
  "properties": {
    "addr:full":"Polperro Car Park Looe Cornwall PL13 2PL",
    "addr:postcode":"pl13 2pl",
    "iso:country":"GB",
    "sg:address":"Polperro Car Park",
    "sg:city":"Looe",
    "sg:classifiers":[
        {
            "category":"Fast Food",
            "type":"Food & Drink"
        }
    ],
    "sg:postcode":"PL13 2PL",
    "sg:province":"Cornwall",
    "sg:tags":[
        "away",
        "take"
    ],
    "wof:name":"E.K Lovelock",
    "wof:placetype":"venue"
},
  "geometry": {"coordinates":[-4.518862,50.340202],"type":"Point"}
}