{
  "type": "Feature",
  "properties": {
    "iso:country":"GB",
    "sg:address":"43 High Street, South Normanton",
    "sg:city":"Alfreton",
    "sg:classifiers":[
        {
            "category":"Community Center",
            "type":"Public Place"
        }
    ],
    "sg:phone":"+44 1773 810221",
    "sg:postcode":"DE55 2BP",
    "sg:province":"Derbyshire",
    "sg:tags":[
        "recreation",
        "leisure",
        "centre"
    ],
    "wof:name":"Progressions",
    "wof:placetype":"venue"
},
  "geometry": {"coordinates":[-1.3417619467,53.107257843],"type":"Point"}
}