{
  "type": "Feature",
  "properties": {
    "iso:country":"GB",
    "sg:address":"15 Urban Rd, Sale",
    "sg:city":"Manchester",
    "sg:classifiers":[
        {
            "category":"Building & Trades",
            "subcategory":"Construction",
            "type":"Services"
        }
    ],
    "sg:postcode":"M33 7TG",
    "sg:province":"Cheshire",
    "sg:tags":[
        "decorator",
        "painter"
    ],
    "wof:name":"Burke,Colin,",
    "wof:placetype":"venue"
},
  "geometry": {"coordinates":[-2.328956,53.421192],"type":"Point"}
}