{
  "type": "Feature",
  "properties": {
    "iso:country":"GB",
    "sg:address":"Unit4, Ashdon Road Commercial Ctr",
    "sg:city":"Saffron Walden",
    "sg:classifiers":[
        {
            "category":"Building & Trades",
            "subcategory":"Electrical",
            "type":"Services"
        }
    ],
    "sg:phone":"+44 1799 522219",
    "sg:postcode":"CB10 2NG",
    "sg:province":"Cambridgeshire",
    "sg:tags":[
        "galvanising"
    ],
    "wof:name":"Acrow Galvanizing Ltd.",
    "wof:placetype":"venue"
},
  "geometry": {"coordinates":[0.3305799961,52.0188713074],"type":"Point"}
}