{
  "type": "Feature",
  "properties": {
    "addr:full":"9 Orme Court London Greater London W2 4RL",
    "addr:housenumber":"9",
    "addr:postcode":"w2 4rl",
    "addr:street":"Orme Court",
    "iso:country":"GB",
    "sg:address":"9 Orme Court",
    "sg:city":"London",
    "sg:classifiers":[
        {
            "category":"Professional",
            "subcategory":"Employment Agencies",
            "type":"Services"
        }
    ],
    "sg:phone":"+44 20 7243 3005",
    "sg:postcode":"W2 4RL",
    "sg:province":"Greater London",
    "sg:tags":[
        "consultant"
    ],
    "wof:name":"Billy Hughes",
    "wof:placetype":"venue"
},
  "geometry": {"coordinates":[-0.189049,51.510815],"type":"Point"}
}