{
  "type": "Feature",
  "properties": {
    "iso:country":"GB",
    "sg:address":"York Road, Long Marston",
    "sg:city":"York",
    "sg:classifiers":[
        {
            "category":"Bars & Pubs",
            "type":"Food & Drink"
        }
    ],
    "sg:phone":"+44 1904 738258",
    "sg:postcode":"YO5 8PG",
    "sg:province":"East Riding of Yorkshire",
    "sg:tags":[
        "pubs",
        "inn"
    ],
    "wof:name":"The Sun Inn",
    "wof:placetype":"venue"
},
  "geometry": {"coordinates":[-1.2445,53.959648],"type":"Point"}
}