{
  "type": "Feature",
  "properties": {
    "addr:full":"9 Church Road, Upton Wirral Merseyside CH49 6JY",
    "addr:housenumber":"9",
    "addr:postcode":"ch49 6jy",
    "addr:street":"Church Road",
    "iso:country":"GB",
    "sg:address":"9 Church Road, Upton",
    "sg:city":"Wirral",
    "sg:classifiers":[
        {
            "category":"Organizations",
            "subcategory":"Non-profit Organization",
            "type":"Services"
        }
    ],
    "sg:phone":"+44 151 677 9151",
    "sg:postcode":"CH49 6JY",
    "sg:province":"Merseyside",
    "sg:tags":[
        "charitable",
        "organisation",
        "voluntary",
        "charity"
    ],
    "wof:name":"Spina Bifida",
    "wof:placetype":"venue"
},
  "geometry": {"coordinates":[-3.096759,53.385387],"type":"Point"}
}