{
  "type": "Feature",
  "properties": {
    "addr:full":"19 Old Road, Brampton Chesterfield Derbyshire S40 2RE",
    "addr:housenumber":"19",
    "addr:postcode":"s40 2re",
    "addr:street":"Old Road",
    "iso:country":"GB",
    "sg:address":"19 Old Road, Brampton",
    "sg:city":"Chesterfield",
    "sg:classifiers":[
        {
            "category":"Bars & Pubs",
            "type":"Food & Drink"
        }
    ],
    "sg:phone":"+44 1246 220544",
    "sg:postcode":"S40 2RE",
    "sg:province":"Derbyshire",
    "sg:tags":[
        "pubs",
        "inn"
    ],
    "wof:name":"The Prince of Wales",
    "wof:placetype":"venue"
},
  "geometry": {"coordinates":[-1.4491109848,53.2335929871],"type":"Point"}
}