{
  "type": "Feature",
  "properties": {
    "addr:full":"12 Kingsley Avenue, Birkenshaw Bradford West Yorkshire BD11 2NQ",
    "addr:housenumber":"12",
    "addr:postcode":"bd11 2nq",
    "addr:street":"Kingsley Avenue",
    "iso:country":"GB",
    "sg:address":"12 Kingsley Avenue, Birkenshaw",
    "sg:city":"Bradford",
    "sg:classifiers":[
        {
            "category":"Building & Trades",
            "subcategory":"Plumbing",
            "type":"Services"
        }
    ],
    "sg:postcode":"BD11 2NQ",
    "sg:province":"West Yorkshire",
    "sg:tags":[
        "plumber",
        "heating"
    ],
    "wof:name":"P WRIGHT",
    "wof:placetype":"venue"
},
  "geometry": {"coordinates":[-1.6863369942,53.7470169067],"type":"Point"}
}