{
  "type": "Feature",
  "properties": {
    "addr:full":"2a George Street Ramsgate Kent CT11 9AS",
    "addr:housenumber":"2a",
    "addr:postcode":"ct11 9as",
    "addr:street":"George Street Ramsgate",
    "iso:country":"GB",
    "sg:address":"2a George Street",
    "sg:city":"Ramsgate",
    "sg:classifiers":[
        {
            "category":"Professional",
            "type":"Services"
        }
    ],
    "sg:phone":"+44 1843 853239",
    "sg:postcode":"CT11 9AS",
    "sg:province":"Kent",
    "sg:tags":[
        "caterer"
    ],
    "wof:name":"Marsh Caterers",
    "wof:placetype":"venue"
},
  "geometry": {"coordinates":[1.4170520306,51.3342285156],"type":"Point"}
}