{
  "type": "Feature",
  "properties": {
    "addr:full":"88 Earls Rd Southampton Hampshire SO14 6SF",
    "addr:housenumber":"88",
    "addr:postcode":"so14 6sf",
    "addr:street":"Earls Rd",
    "iso:country":"GB",
    "sg:address":"88 Earls Rd",
    "sg:city":"Southampton",
    "sg:classifiers":[
        {
            "category":"Retail",
            "subcategory":"Storage",
            "type":"Services"
        }
    ],
    "sg:phone":"+44 23 8036 3027",
    "sg:postcode":"SO14 6SF",
    "sg:province":"Hampshire",
    "sg:tags":[
        "household",
        "removal"
    ],
    "wof:name":"A A J Removals",
    "wof:placetype":"venue"
},
  "geometry": {"coordinates":[-1.397514,50.918568],"type":"Point"}
}