{
  "type": "Feature",
  "properties": {
    "iso:country":"GB",
    "sg:address":"352 Leyton High Road",
    "sg:city":"London",
    "sg:classifiers":[
        {
            "category":"Banks & Credit Unions",
            "subcategory":"Bank",
            "type":"Services"
        }
    ],
    "sg:postcode":"E10 6QQ",
    "sg:province":"Greater London",
    "sg:tags":[
        "broker",
        "mortgage"
    ],
    "wof:name":"St. James Mortgages & Finance",
    "wof:placetype":"venue"
},
  "geometry": {"coordinates":[-0.010078,51.561825],"type":"Point"}
}