{
  "type": "Feature",
  "properties": {
    "addr:full":"London Road, Pewsham Chippenham Wiltshire SN15 3DE",
    "addr:postcode":"sn15 3de",
    "addr:street":"London Road Pewsham",
    "iso:country":"GB",
    "sg:address":"London Road, Pewsham",
    "sg:city":"Chippenham",
    "sg:classifiers":[
        {
            "category":"Autos & Motor Vehicles",
            "subcategory":"Automobile Sales",
            "type":"Retail Goods"
        }
    ],
    "sg:phone":"+44 1249 655871",
    "sg:postcode":"SN15 3DE",
    "sg:province":"Wiltshire",
    "sg:tags":[
        "car"
    ],
    "wof:name":"Causeway Garage Wiltshire Ltd.",
    "wof:placetype":"venue"
},
  "geometry": {"coordinates":[-2.110494,51.454689],"type":"Point"}
}