{
  "type": "Feature",
  "properties": {
    "iso:country":"GB",
    "sg:address":"Unit B1 Olympic Retail Park, Engineers Way",
    "sg:city":"Wembley",
    "sg:classifiers":[
        {
            "category":"Sports & Exercise",
            "subcategory":"Bowling",
            "type":"Entertainment"
        }
    ],
    "sg:phone":"+44 20 8795 3333",
    "sg:postcode":"HA9 0ER",
    "sg:province":"Greater London",
    "wof:name":"Base Wembley The",
    "wof:placetype":"venue"
},
  "geometry": {"coordinates":[-0.295539,51.552963],"type":"Point"}
}