{
  "type": "Feature",
  "properties": {
    "iso:country":"GB",
    "sg:address":"Not Ascertained",
    "sg:city":"Pwllheli",
    "sg:classifiers":[
        {
            "category":"Shopping",
            "type":"Retail Goods"
        }
    ],
    "sg:phone":"+44 1758 612710",
    "sg:postcode":"LL53 5DP",
    "sg:province":"Gwynedd",
    "sg:tags":[
        "merchant"
    ],
    "wof:name":"Bodegroes Stores",
    "wof:placetype":"venue"
},
  "geometry": {"coordinates":[-4.414314,52.889847],"type":"Point"}
}