{
  "type": "Feature",
  "properties": {
    "iso:country":"GB",
    "sg:address":"191 Green Lane Road",
    "sg:city":"Leicester",
    "sg:classifiers":[
        {
            "category":"Health Services",
            "subcategory":"Podiatrist",
            "type":"Services"
        },
        {
            "category":"Health Services",
            "subcategory":"Chiropractor",
            "type":"Services"
        }
    ],
    "sg:phone":"+44 116 276 9420",
    "sg:postcode":"LE5 4PD",
    "sg:province":"Leicestershire",
    "sg:tags":[
        "podiatrists",
        "chiropodist"
    ],
    "wof:name":"GRAHAM D RAMSEY",
    "wof:placetype":"venue"
},
  "geometry": {"coordinates":[-1.098545,52.637024],"type":"Point"}
}