{
  "type": "Feature",
  "properties": {
    "addr:full":"40 Station Road Redcar North Yorkshire TS10 1AG",
    "addr:housenumber":"40",
    "addr:postcode":"ts10 1ag",
    "addr:street":"Station Road",
    "iso:country":"GB",
    "sg:address":"40 Station Road",
    "sg:city":"Redcar",
    "sg:classifiers":[
        {
            "category":"Shopping",
            "subcategory":"Clothing, Apparel, & Fashions",
            "type":"Retail Goods"
        }
    ],
    "sg:phone":"+44 1642 484061",
    "sg:postcode":"TS10 1AG",
    "sg:province":"North Yorkshire",
    "sg:tags":[
        "lingerie",
        "hosiery"
    ],
    "wof:name":"Pretty Things",
    "wof:placetype":"venue"
},
  "geometry": {"coordinates":[-1.070346,54.619038],"type":"Point"}
}