{
  "type": "Feature",
  "properties": {
    "iso:country":"GB",
    "sg:address":"Dragon Cottage Surgery, 35 Browns Rd",
    "sg:city":"High Wycombe",
    "sg:classifiers":[
        {
            "category":"Health Services",
            "subcategory":"Doctor",
            "type":"Services"
        }
    ],
    "sg:phone":"+44 1494 715924",
    "sg:postcode":"HP15 6RZ",
    "sg:province":"Buckinghamshire",
    "sg:tags":[
        "practitioners"
    ],
    "wof:name":"Tweedy, M",
    "wof:placetype":"venue"
},
  "geometry": {"coordinates":[-0.70067,51.662529],"type":"Point"}
}