{
  "type": "Feature",
  "properties": {
    "addr:full":"261 Portobello Road London Greater London W11 1LR",
    "addr:housenumber":"261",
    "addr:postcode":"w11 1lr",
    "addr:street":"Portobello Road",
    "iso:country":"GB",
    "sg:address":"261 Portobello Road",
    "sg:city":"London",
    "sg:classifiers":[
        {
            "category":"Shopping",
            "subcategory":"Department Store",
            "type":"Retail Goods"
        }
    ],
    "sg:phone":"+44 20 7792 0166",
    "sg:postcode":"W11 1LR",
    "sg:province":"Greater London",
    "wof:name":"Alchemy Shop",
    "wof:placetype":"venue"
},
  "geometry": {"coordinates":[-0.206792,51.517918],"type":"Point"}
}