{
  "type": "Feature",
  "properties": {
    "iso:country":"GB",
    "sg:address":"33 Bellair Av",
    "sg:city":"Liverpool",
    "sg:classifiers":[
        {
            "category":"Retail",
            "subcategory":"Auto Repair",
            "type":"Services"
        }
    ],
    "sg:phone":"+44 151 924 6955",
    "sg:postcode":"L23 9SN",
    "sg:province":"Merseyside",
    "sg:tags":[
        "body",
        "car"
    ],
    "wof:name":"H B Seddon",
    "wof:placetype":"venue"
},
  "geometry": {"coordinates":[-3.0064809322,53.4902572632],"type":"Point"}
}