{
  "type": "Feature",
  "properties": {
    "iso:country":"GB",
    "sg:address":"15 Anglesey Gardens",
    "sg:city":"Carshalton",
    "sg:classifiers":[
        {
            "category":"Retail",
            "subcategory":"Driving School",
            "type":"Services"
        }
    ],
    "sg:phone":"+44 20 8669 3021",
    "sg:postcode":"SM5 3JD",
    "sg:province":"Surrey",
    "wof:name":"Brian's School Of Motoring",
    "wof:placetype":"venue"
},
  "geometry": {"coordinates":[-0.161112994,51.3564949036],"type":"Point"}
}