{
  "type": "Feature",
  "properties": {
    "iso:country":"GB",
    "sg:address":"154 Leeds Rd, Barwick In Elmel",
    "sg:city":"Leeds",
    "sg:classifiers":[
        {
            "category":"Professional",
            "subcategory":"Engineering",
            "type":"Services"
        }
    ],
    "sg:phone":"+44 113 281 3203",
    "sg:postcode":"LS15 4HS",
    "sg:province":"West Yorkshire",
    "sg:tags":[
        "engineer",
        "structural"
    ],
    "wof:name":"Neil Chambers",
    "wof:placetype":"venue"
},
  "geometry": {"coordinates":[-1.408185,53.825687],"type":"Point"}
}