{
  "type": "Feature",
  "properties": {
    "addr:full":"Knockhundred Row Midhurst West Sussex GU29 9DQ",
    "addr:postcode":"gu29 9dq",
    "addr:street":"Knockhundred Row Midhurst",
    "iso:country":"GB",
    "sg:address":"Knockhundred Row",
    "sg:city":"Midhurst",
    "sg:classifiers":[
        {
            "category":"Health Services",
            "subcategory":"Dentist",
            "type":"Services"
        }
    ],
    "sg:phone":"+44 1730 812022",
    "sg:postcode":"GU29 9DQ",
    "sg:province":"West Sussex",
    "wof:name":"St Oswalds Dental Surgery",
    "wof:placetype":"venue"
},
  "geometry": {"coordinates":[-0.7383520007,50.9868545532],"type":"Point"}
}