{
  "type": "Feature",
  "properties": {
    "addr:full":"Baldock Road Hitchin Bedfordshire SG5 4PA",
    "addr:postcode":"sg5 4pa",
    "addr:street":"Baldock Road",
    "iso:country":"GB",
    "sg:address":"Baldock Road",
    "sg:city":"Hitchin",
    "sg:classifiers":[
        {
            "category":"Shopping",
            "subcategory":"Computers & Home Electronics",
            "type":"Retail Goods"
        }
    ],
    "sg:phone":"+44 1462 734111",
    "sg:postcode":"SG5 4PA",
    "sg:province":"Bedfordshire",
    "sg:tags":[
        "electrical"
    ],
    "wof:name":"Hunts Electrical",
    "wof:placetype":"venue"
},
  "geometry": {"coordinates":[-0.22209,52.01276],"type":"Point"}
}