{
  "type": "Feature",
  "properties": {
    "addr:full":"Unit 11 High Hazles Road, Manvers Business Park Nottingham Nottinghamshire NG12 3GZ",
    "addr:housenumber":"unit 11",
    "addr:postcode":"ng12 3gz",
    "addr:street":"High Hazles Road Manvers Business Park",
    "iso:country":"GB",
    "sg:address":"Unit 11 High Hazles Road, Manvers Business Park",
    "sg:city":"Nottingham",
    "sg:classifiers":[
        {
            "category":"Home & Garden",
            "subcategory":"Home Furnishings",
            "type":"Retail Goods"
        }
    ],
    "sg:postcode":"NG12 3GZ",
    "sg:province":"Nottinghamshire",
    "sg:tags":[
        "awning",
        "canopy",
        "blinds"
    ],
    "wof:name":"All Blinds & Awnings",
    "wof:placetype":"venue"
},
  "geometry": {"coordinates":[-1.0342190266,52.9144592285],"type":"Point"}
}