{
  "type": "Feature",
  "properties": {
    "addr:full":"26 Fosse Way West Ealing Greater London W13 0BZ",
    "addr:housenumber":"26",
    "addr:postcode":"w13 0bz",
    "addr:street":"Fosse Way",
    "iso:country":"GB",
    "sg:address":"26 Fosse Way",
    "sg:city":"West Ealing",
    "sg:classifiers":[
        {
            "category":"Professional",
            "subcategory":"Art Services",
            "type":"Services"
        }
    ],
    "sg:phone":"+44 20 8998 1232",
    "sg:postcode":"W13 0BZ",
    "sg:province":"Greater London",
    "sg:tags":[
        "photographer"
    ],
    "wof:name":"Natural Wedding Photography",
    "wof:placetype":"venue"
},
  "geometry": {"coordinates":[-0.3259310126,51.5235977173],"type":"Point"}
}