{
  "type": "Feature",
  "properties": {
    "iso:country":"GB",
    "sg:address":"49 Cothill Crescent, Stoneyburn",
    "sg:city":"Bathgate",
    "sg:classifiers":[
        {
            "category":"Building & Trades",
            "subcategory":"Landscaping Services",
            "type":"Services"
        }
    ],
    "sg:postcode":"EH47 8BJ",
    "sg:province":"North Lanarkshire",
    "sg:tags":[
        "landscape",
        "contractor"
    ],
    "wof:name":"Angus Ferguson Landscaping",
    "wof:placetype":"venue"
},
  "geometry": {"coordinates":[-3.628893,55.848537],"type":"Point"}
}