{
  "type": "Feature",
  "properties": {
    "iso:country":"GB",
    "sg:address":"Unit 10 Honeyborough Industrial Estate, Neyland",
    "sg:city":"Milford Haven",
    "sg:classifiers":[
        {
            "category":"Education",
            "subcategory":"Special Training",
            "type":"Public Place"
        },
        {
            "category":"Education",
            "subcategory":"School",
            "type":"Public Place"
        }
    ],
    "sg:phone":"+44 1646 600808",
    "sg:postcode":"SA73 1SE",
    "sg:province":"Pembrokeshire",
    "sg:tags":[
        "product",
        "local",
        "authority",
        "centre"
    ],
    "wof:name":"Pembrokeshire Skills Park Ltd.",
    "wof:placetype":"venue"
},
  "geometry": {"coordinates":[-5.027044,51.716808],"type":"Point"}
}