{
  "type": "Feature",
  "properties": {
    "iso:country":"GB",
    "sg:address":"1 Whitings Way, East Ham",
    "sg:city":"London",
    "sg:classifiers":[
        {
            "category":"Manufacturing",
            "subcategory":"Metals",
            "type":"Manufacturing & Wholesale Goods"
        }
    ],
    "sg:postcode":"E6 6LR",
    "sg:province":"Greater London",
    "sg:tags":[
        "steel",
        "fabricator",
        "erectors"
    ],
    "wof:name":"Joy Steel Structures (London) Ltd.",
    "wof:placetype":"venue"
},
  "geometry": {"coordinates":[0.062425,51.518467],"type":"Point"}
}