{
  "type": "Feature",
  "properties": {
    "addr:full":"Office Fh/part First Floor, Barratts House, Kingsthorpe Road Northampton Northamptonshire NN2 6EZ",
    "addr:housenumber":"floor barratts house",
    "addr:postcode":"nn2 6ez",
    "addr:street":"Kingsthorpe Road",
    "iso:country":"GB",
    "sg:address":"Office Fh/part First Floor, Barratts House, Kingsthorpe Road",
    "sg:city":"Northampton",
    "sg:classifiers":[
        {
            "category":"Professional",
            "subcategory":"Computer Services",
            "type":"Services"
        }
    ],
    "sg:postcode":"NN2 6EZ",
    "sg:province":"Northamptonshire",
    "sg:tags":[
        "system",
        "software"
    ],
    "wof:name":"Nbg-It Ltd",
    "wof:placetype":"venue"
},
  "geometry": {"coordinates":[-0.895849,52.257404],"type":"Point"}
}