{
  "type": "Feature",
  "properties": {
    "addr:full":"Stoke Wharf, Hanbury Road, Stoke Prior Bromsgrove Worcestershire B60 4LA",
    "addr:postcode":"b60 4la",
    "addr:street":"Hanbury Road",
    "iso:country":"GB",
    "sg:address":"Stoke Wharf, Hanbury Road, Stoke Prior",
    "sg:city":"Bromsgrove",
    "sg:classifiers":[
        {
            "category":"Recreation",
            "subcategory":"Boat Charter",
            "type":"Entertainment"
        }
    ],
    "sg:phone":"+44 1527 575115",
    "sg:postcode":"B60 4LA",
    "sg:province":"Worcestershire",
    "sg:tags":[
        "rental",
        "leasing",
        "excursion"
    ],
    "wof:name":"Black Prince Holidays Ltd.",
    "wof:placetype":"venue"
},
  "geometry": {"coordinates":[-2.055703,52.2729],"type":"Point"}
}