{
  "type": "Feature",
  "properties": {
    "addr:full":"4 Lound Side, Chapeltown Sheffield South Yorkshire S35 2UP",
    "addr:housenumber":"4",
    "addr:postcode":"s35 2up",
    "addr:street":"Lound Side Chapeltown",
    "iso:country":"GB",
    "sg:address":"4 Lound Side, Chapeltown",
    "sg:city":"Sheffield",
    "sg:classifiers":[
        {
            "category":"Personal",
            "subcategory":"Beauty Salon",
            "type":"Services"
        }
    ],
    "sg:phone":"+44 114 257 0992",
    "sg:postcode":"S35 2UP",
    "sg:province":"South Yorkshire",
    "sg:tags":[
        "unisex",
        "hairdresser"
    ],
    "wof:name":"Alfredo 2",
    "wof:placetype":"venue"
},
  "geometry": {"coordinates":[-1.46715,53.462456],"type":"Point"}
}