{
  "type": "Feature",
  "properties": {
    "addr:full":"Bonymaen Road, Bonymaen Swansea Neath Port Talbot SA1 7AT",
    "addr:postcode":"sa1 7at",
    "addr:street":"Bonymaen Road",
    "iso:country":"GB",
    "sg:address":"Bonymaen Road, Bonymaen",
    "sg:city":"Swansea",
    "sg:classifiers":[
        {
            "category":"Education",
            "subcategory":"School",
            "type":"Public Place"
        }
    ],
    "sg:phone":"+44 1792 653186",
    "sg:postcode":"SA1 7AT",
    "sg:province":"Neath Port Talbot",
    "sg:tags":[
        "local",
        "authority"
    ],
    "wof:name":"Pentrechwyth Primary School",
    "wof:placetype":"venue"
},
  "geometry": {"coordinates":[-3.9200739861,51.6399269104],"type":"Point"}
}