{
  "type": "Feature",
  "properties": {
    "addr:full":"43-45 Henshaw St Oldham Lancashire OL1 1NH",
    "addr:housenumber":"43-45",
    "addr:postcode":"ol1 1nh",
    "addr:street":"Henshaw St",
    "iso:country":"GB",
    "sg:address":"43-45 Henshaw St",
    "sg:city":"Oldham",
    "sg:classifiers":[
        {
            "category":"Shopping",
            "subcategory":"Clothing, Apparel, & Fashions",
            "type":"Retail Goods"
        }
    ],
    "sg:phone":"+44 161 626 4772",
    "sg:postcode":"OL1 1NH",
    "sg:province":"Lancashire",
    "sg:tags":[
        "shop"
    ],
    "wof:name":"Winners",
    "wof:placetype":"venue"
},
  "geometry": {"coordinates":[-2.115241,53.543427],"type":"Point"}
}