{
  "type": "Feature",
  "properties": {
    "addr:full":"Malborough House, 179-189 Finchley Road London Greater London NW3 6LB",
    "addr:housenumber":"179-189",
    "addr:postcode":"nw3 6lb",
    "addr:street":"Finchley Road",
    "iso:country":"GB",
    "sg:address":"Malborough House, 179-189 Finchley Road",
    "sg:city":"London",
    "sg:classifiers":[
        {
            "category":"Professional",
            "subcategory":"Business Services",
            "type":"Services"
        }
    ],
    "sg:phone":"+44 20 7624 6014",
    "sg:postcode":"NW3 6LB",
    "sg:province":"Greater London",
    "sg:tags":[
        "import",
        "export",
        "agent"
    ],
    "wof:name":"Extermetal Ltd.",
    "wof:placetype":"venue"
},
  "geometry": {"coordinates":[-0.178656,51.54575],"type":"Point"}
}