{
  "type": "Feature",
  "properties": {
    "iso:country":"GB",
    "sg:address":"Lyndon Farm, Holly Bush Lane",
    "sg:city":"Warrington",
    "sg:classifiers":[
        {
            "category":"Retail",
            "subcategory":"Auto Repair",
            "type":"Services"
        }
    ],
    "sg:phone":"+44 1925 837444",
    "sg:postcode":"WA3 6DZ",
    "sg:province":"Cheshire",
    "sg:tags":[
        "engine",
        "car",
        "specialist"
    ],
    "wof:name":"Micro Precision Engineering Ltd.",
    "wof:placetype":"venue"
},
  "geometry": {"coordinates":[-2.495899,53.417702],"type":"Point"}
}