{
  "type": "Feature",
  "properties": {
    "iso:country":"GB",
    "sg:address":"Unit 5a Bradleys Walk",
    "sg:city":"Gainsborough",
    "sg:classifiers":[
        {
            "category":"Communications",
            "type":"Services"
        }
    ],
    "sg:phone":"+44 1427 615665",
    "sg:postcode":"DN21 2LW",
    "sg:province":"Lincolnshire",
    "sg:tags":[
        "tv",
        "video",
        "radio"
    ],
    "wof:name":"Philip Clark",
    "wof:placetype":"venue"
},
  "geometry": {"coordinates":[-0.7727680206,53.3956947327],"type":"Point"}
}