{
  "type": "Feature",
  "properties": {
    "iso:country":"GB",
    "sg:address":"Newton",
    "sg:city":"Cromarty",
    "sg:classifiers":[
        {
            "category":"Professional",
            "subcategory":"Business Services",
            "type":"Services"
        },
        {
            "category":"Shopping",
            "type":"Retail Goods"
        }
    ],
    "sg:postcode":"IV11 8XT",
    "sg:province":"Highland",
    "sg:tags":[
        "merchant",
        "agricultural"
    ],
    "wof:name":"HUNTERS OF CROMARTY",
    "wof:placetype":"venue"
},
  "geometry": {"coordinates":[-4.0488190651,57.6692085266],"type":"Point"}
}