{
  "type": "Feature",
  "properties": {
    "addr:full":"The Barn, Westwood Farm, High Cross Road Gravesend Kent DA13 9PH",
    "addr:postcode":"da13 9ph",
    "addr:street":"Westwood;High Cross Road",
    "iso:country":"GB",
    "sg:address":"The Barn, Westwood Farm, High Cross Road",
    "sg:city":"Gravesend",
    "sg:classifiers":[
        {
            "category":"Home & Garden",
            "subcategory":"Household Appliances",
            "type":"Retail Goods"
        },
        {
            "category":"Autos & Motor Vehicles",
            "subcategory":"Auto Supplies",
            "type":"Retail Goods"
        }
    ],
    "sg:postcode":"DA13 9PH",
    "sg:province":"Kent",
    "sg:tags":[
        "electrical",
        "electric"
    ],
    "wof:name":"Technique Electrical Repairs",
    "wof:placetype":"venue"
},
  "geometry": {"coordinates":[0.3286539912,51.4186477661],"type":"Point"}
}