{
  "type": "Feature",
  "properties": {
    "iso:country":"GB",
    "sg:address":"92 King St",
    "sg:city":"Bedworth",
    "sg:classifiers":[
        {
            "category":"Professional",
            "subcategory":"Art Services",
            "type":"Services"
        }
    ],
    "sg:phone":"+44 24 7631 5611",
    "sg:postcode":"CV12 8JF",
    "sg:province":"Warwickshire",
    "sg:tags":[
        "graphic",
        "designer"
    ],
    "wof:name":"Auto Signs & Graphics",
    "wof:placetype":"venue"
},
  "geometry": {"coordinates":[-1.468167,52.479115],"type":"Point"}
}