{
  "type": "Feature",
  "properties": {
    "addr:full":"Unit G, Stoney Building, Stoney St Nottingham Nottinghamshire NG1 1LL",
    "addr:housenumber":"unit g",
    "addr:postcode":"ng1 1ll",
    "addr:street":"Stoney St",
    "iso:country":"GB",
    "sg:address":"Unit G, Stoney Building, Stoney St",
    "sg:city":"Nottingham",
    "sg:classifiers":[
        {
            "category":"Shopping",
            "subcategory":"Clothing, Apparel, & Fashions",
            "type":"Retail Goods"
        }
    ],
    "sg:phone":"+44 115 950 7911",
    "sg:postcode":"NG1 1LL",
    "sg:province":"Nottinghamshire",
    "sg:tags":[
        "clothing"
    ],
    "wof:name":"B.B's Typhoon Trading",
    "wof:placetype":"venue"
},
  "geometry": {"coordinates":[-1.1439239979,52.9492263794],"type":"Point"}
}