{
  "type": "Feature",
  "properties": {
    "addr:full":"Residential Unit For People With Disabilities, 2 Lower Stree Stoke On Trent Staffordshire ST6 3BY",
    "addr:housenumber":"2",
    "addr:postcode":"st6 3by",
    "addr:street":"Lower Stree",
    "iso:country":"GB",
    "sg:address":"Residential Unit For People With Disabilities, 2 Lower Stree",
    "sg:city":"Stoke On Trent",
    "sg:classifiers":[
        {
            "category":"Government",
            "subcategory":"Office",
            "type":"Public Place"
        }
    ],
    "sg:phone":"+44 1782 836558",
    "sg:postcode":"ST6 3BY",
    "sg:province":"Staffordshire",
    "sg:tags":[
        "local"
    ],
    "wof:name":"Bursley House",
    "wof:placetype":"venue"
},
  "geometry": {"coordinates":[-2.200150013,53.0392799377],"type":"Point"}
}