{
  "type": "Feature",
  "properties": {
    "iso:country":"GB",
    "sg:address":"26 Church Road, Horspath",
    "sg:city":"Oxford",
    "sg:classifiers":[
        {
            "category":"Bars & Pubs",
            "type":"Food & Drink"
        }
    ],
    "sg:phone":"+44 1865 875567",
    "sg:postcode":"OX33 1RU",
    "sg:province":"Buckinghamshire",
    "sg:tags":[
        "pubs",
        "inn"
    ],
    "wof:name":"The Queens Head",
    "wof:placetype":"venue"
},
  "geometry": {"coordinates":[-1.1730409861,51.739906311],"type":"Point"}
}