{
  "type": "Feature",
  "properties": {
    "iso:country":"GB",
    "sg:address":"16a Aquarium Street",
    "sg:city":"Rhyl",
    "sg:classifiers":[
        {
            "category":"Building & Trades",
            "subcategory":"Plumbing",
            "type":"Services"
        }
    ],
    "sg:phone":"+44 1745 342364",
    "sg:postcode":"LL18 1PG",
    "sg:province":"Conwy",
    "sg:tags":[
        "heating"
    ],
    "wof:name":"Rhyl Home Heating Centre",
    "wof:placetype":"venue"
},
  "geometry": {"coordinates":[-3.497373,53.318829],"type":"Point"}
}