{
  "type": "Feature",
  "properties": {
    "iso:country":"GB",
    "sg:address":"Manor Road",
    "sg:city":"Sidmouth",
    "sg:classifiers":[
        {
            "category":"Real Estate",
            "subcategory":"Developer",
            "type":"Services"
        },
        {
            "category":"Arts & Performance",
            "subcategory":"Theater",
            "type":"Entertainment"
        }
    ],
    "sg:phone":"+44 1395 514413",
    "sg:postcode":"EX10 8RP",
    "sg:province":"Devon",
    "sg:tags":[
        "property",
        "concert",
        "theatre",
        "hall"
    ],
    "wof:name":"Manor Pavilion Theatre",
    "wof:placetype":"venue"
},
  "geometry": {"coordinates":[-3.242529,50.67989],"type":"Point"}
}