{
  "type": "Feature",
  "properties": {
    "iso:country":"GB",
    "sg:address":"45 Bradford Road",
    "sg:city":"Shipley",
    "sg:classifiers":[
        {
            "category":"Shopping",
            "subcategory":"Clothing, Apparel, & Fashions",
            "type":"Retail Goods"
        }
    ],
    "sg:phone":"+44 1274 585991",
    "sg:postcode":"BD18 3DS",
    "sg:province":"West Yorkshire",
    "sg:tags":[
        "shop"
    ],
    "wof:name":"S & I Thwaites",
    "wof:placetype":"venue"
},
  "geometry": {"coordinates":[-1.783369,53.831276],"type":"Point"}
}