{
  "type": "Feature",
  "properties": {
    "addr:full":"Jubilee Ho, Jubilee Ct, Dersingham King's Lynn Norfolk PE31 6HH",
    "addr:postcode":"pe31 6hh",
    "addr:street":"Jubilee Ct;Lynn",
    "iso:country":"GB",
    "sg:address":"Jubilee Ho, Jubilee Ct, Dersingham",
    "sg:city":"King's Lynn",
    "sg:classifiers":[
        {
            "category":"Professional",
            "subcategory":"Engineering",
            "type":"Services"
        }
    ],
    "sg:postcode":"PE31 6HH",
    "sg:province":"Norfolk",
    "sg:tags":[
        "contractor",
        "electrical",
        "engineer"
    ],
    "wof:name":"Lighthouse Contract Ltd",
    "wof:placetype":"venue"
},
  "geometry": {"coordinates":[0.50275,52.845921],"type":"Point"}
}