{
  "type": "Feature",
  "properties": {
    "addr:full":"7 Rempstone Road Swanage Dorset BH19 1DN",
    "addr:housenumber":"7",
    "addr:postcode":"bh19 1dn",
    "addr:street":"Rempstone Road",
    "iso:country":"GB",
    "sg:address":"7 Rempstone Road",
    "sg:city":"Swanage",
    "sg:classifiers":[
        {
            "category":"Travel",
            "subcategory":"Hotels & Motels",
            "type":"Entertainment"
        }
    ],
    "sg:phone":"+44 1929 422892",
    "sg:postcode":"BH19 1DN",
    "sg:province":"Dorset",
    "sg:tags":[
        "house",
        "guest"
    ],
    "wof:name":"Caythorpe House",
    "wof:placetype":"venue"
},
  "geometry": {"coordinates":[-1.959942,50.611267],"type":"Point"}
}