{
  "type": "Feature",
  "properties": {
    "iso:country":"GB",
    "sg:address":"432 Lightwood Rd, Longton",
    "sg:city":"Stoke On Trent",
    "sg:classifiers":[
        {
            "category":"Health Services",
            "subcategory":"Nursing And Care Facility",
            "type":"Services"
        }
    ],
    "sg:phone":"+44 1782 316979",
    "sg:postcode":"ST3 7EY",
    "sg:province":"Staffordshire",
    "sg:tags":[
        "home"
    ],
    "wof:name":"Lightwood House",
    "wof:placetype":"venue"
},
  "geometry": {"coordinates":[-2.121489,52.975174],"type":"Point"}
}