{
  "type": "Feature",
  "properties": {
    "iso:country":"GB",
    "sg:address":"74 Hallfield Road, Ebor Industrial Estate, Layerthorpe",
    "sg:city":"York",
    "sg:classifiers":[
        {
            "category":"Professional",
            "subcategory":"Engineering",
            "type":"Services"
        }
    ],
    "sg:phone":"+44 1904 717220",
    "sg:postcode":"YO31 7XD",
    "sg:province":"North Yorkshire",
    "wof:name":"The Minster Engineering Fabrication Co. Ltd.",
    "wof:placetype":"venue"
},
  "geometry": {"coordinates":[-1.067556,53.96167],"type":"Point"}
}