{
  "type": "Feature",
  "properties": {
    "iso:country":"GB",
    "sg:address":"177 Moorside Rd, Urmston",
    "sg:city":"Manchester",
    "sg:classifiers":[
        {
            "category":"Manufacturing",
            "subcategory":"Tools & Machinery",
            "type":"Manufacturing & Wholesale Goods"
        }
    ],
    "sg:postcode":"M41 5SJ",
    "sg:province":"Cheshire",
    "sg:tags":[
        "society",
        "friendly"
    ],
    "wof:name":"Collyer,J S,(Holdings) Ltd",
    "wof:placetype":"venue"
},
  "geometry": {"coordinates":[-2.370029,53.452023],"type":"Point"}
}