{
  "type": "Feature",
  "properties": {
    "addr:full":"Blenheim House, Dettingen Way Bury St Edmunds Suffolk IP33 3TU",
    "addr:postcode":"ip33 3tu",
    "addr:street":"Dettingen Way",
    "iso:country":"GB",
    "sg:address":"Blenheim House, Dettingen Way",
    "sg:city":"Bury St Edmunds",
    "sg:classifiers":[
        {
            "category":"Insurance",
            "subcategory":"Insurance Agent",
            "type":"Services"
        }
    ],
    "sg:phone":"+44 1284 756565",
    "sg:postcode":"IP33 3TU",
    "sg:province":"Suffolk",
    "sg:tags":[
        "broker"
    ],
    "wof:name":"Mauve Box (6) Ltd.",
    "wof:placetype":"venue"
},
  "geometry": {"coordinates":[0.6908969879,52.2485427856],"type":"Point"}
}