{
  "type": "Feature",
  "properties": {
    "addr:full":"133 Wadsley Lane Sheffield South Yorkshire S6 4EF",
    "addr:housenumber":"133",
    "addr:postcode":"s6 4ef",
    "addr:street":"Wadsley Lane",
    "iso:country":"GB",
    "sg:address":"133 Wadsley Lane",
    "sg:city":"Sheffield",
    "sg:classifiers":[
        {
            "category":"Building & Trades",
            "subcategory":"Construction",
            "type":"Services"
        }
    ],
    "sg:phone":"+44 114 233 7903",
    "sg:postcode":"S6 4EF",
    "sg:province":"South Yorkshire",
    "sg:tags":[
        "joiner",
        "carpenter"
    ],
    "wof:name":"A & L Joinery",
    "wof:placetype":"venue"
},
  "geometry": {"coordinates":[-1.514022,53.410469],"type":"Point"}
}