{
  "type": "Feature",
  "properties": {
    "addr:full":"Unit 5a, West Craigs Industrial Estate Edinburgh City of Edinburgh EH12 0BD",
    "addr:housenumber":"unit 5a",
    "addr:postcode":"eh12 0bd",
    "addr:street":"West Craigs Industrial Estate",
    "iso:country":"GB",
    "sg:address":"Unit 5a, West Craigs Industrial Estate",
    "sg:city":"Edinburgh",
    "sg:classifiers":[
        {
            "category":"Retail",
            "subcategory":"Auto Repair",
            "type":"Services"
        }
    ],
    "sg:phone":"+44 131 317 1174",
    "sg:postcode":"EH12 0BD",
    "sg:province":"City of Edinburgh",
    "sg:tags":[
        "modification",
        "garage",
        "related"
    ],
    "wof:name":"Maybury Garage Services",
    "wof:placetype":"venue"
},
  "geometry": {"coordinates":[-3.3190739155,55.9431915283],"type":"Point"}
}