{
  "type": "Feature",
  "properties": {
    "iso:country":"GB",
    "sg:address":"1 Honiton Way, Penketh",
    "sg:city":"Warrington",
    "sg:classifiers":[
        {
            "category":"Real Estate",
            "subcategory":"Real Estate Agent",
            "type":"Services"
        }
    ],
    "sg:phone":"+44 1925 791423",
    "sg:postcode":"WA5 2EY",
    "sg:province":"Cheshire",
    "wof:name":"Bridgfords",
    "wof:placetype":"venue"
},
  "geometry": {"coordinates":[-2.654768,53.386593],"type":"Point"}
}