{
  "type": "Feature",
  "properties": {
    "iso:country":"GB",
    "sg:address":"26 Queen Victoria Rd, New Tupton",
    "sg:city":"Chesterfield",
    "sg:classifiers":[
        {
            "category":"Building & Trades",
            "subcategory":"Construction",
            "type":"Services"
        }
    ],
    "sg:phone":"+44 1246 865021",
    "sg:postcode":"S42 6BS",
    "sg:province":"Derbyshire",
    "sg:tags":[
        "dry",
        "lining",
        "plasterers",
        "screeders"
    ],
    "wof:name":"B.R Dalton",
    "wof:placetype":"venue"
},
  "geometry": {"coordinates":[-1.406319,53.190632],"type":"Point"}
}