{
  "type": "Feature",
  "properties": {
    "addr:full":"187 Brook St Dundee Angus DD5 1DJ",
    "addr:housenumber":"187",
    "addr:postcode":"dd5 1dj",
    "addr:street":"Brook St",
    "iso:country":"GB",
    "sg:address":"187 Brook St",
    "sg:city":"Dundee",
    "sg:classifiers":[
        {
            "category":"Professional",
            "subcategory":"Art Services",
            "type":"Services"
        },
        {
            "category":"Home & Garden",
            "subcategory":"Furniture",
            "type":"Retail Goods"
        }
    ],
    "sg:postcode":"DD5 1DJ",
    "sg:province":"Angus",
    "sg:tags":[
        "framing"
    ],
    "wof:name":"Heyder,W,& Sons Ltd",
    "wof:placetype":"venue"
},
  "geometry": {"coordinates":[-2.876207,56.467545],"type":"Point"}
}