{
  "type": "Feature",
  "properties": {
    "iso:country":"GB",
    "sg:address":"Hook Lane, Wimblington",
    "sg:city":"March",
    "sg:classifiers":[
        {
            "category":"Wholesale",
            "subcategory":"Farm Supplies",
            "type":"Manufacturing & Wholesale Goods"
        },
        {
            "category":"Wholesale",
            "subcategory":"Fruits & Vegetables",
            "type":"Manufacturing & Wholesale Goods"
        }
    ],
    "sg:phone":"+44 1354 740691",
    "sg:postcode":"PE15 0QN",
    "sg:province":"Cambridgeshire",
    "sg:tags":[
        "wholesaler",
        "merchant",
        "grain"
    ],
    "sg:website":"http://www.fengrain.co.uk",
    "wof:name":"Fengrain Ltd.",
    "wof:placetype":"venue"
},
  "geometry": {"coordinates":[0.0861800015,52.5083847046],"type":"Point"}
}