{
  "type": "Feature",
  "properties": {
    "iso:country":"GB",
    "sg:address":"Joiners Workshop, Bridge Of Dee",
    "sg:city":"Castle Douglas",
    "sg:classifiers":[
        {
            "category":"Building & Trades",
            "subcategory":"Construction",
            "type":"Services"
        }
    ],
    "sg:phone":"+44 1556 680257",
    "sg:postcode":"DG7 1TR",
    "sg:province":"Dumfries and Galloway",
    "sg:tags":[
        "joiner",
        "carpenter"
    ],
    "wof:name":"Bridge of Dee Joinery",
    "wof:placetype":"venue"
},
  "geometry": {"coordinates":[-3.928704,54.94162],"type":"Point"}
}