{
  "type": "Feature",
  "properties": {
    "iso:country":"GB",
    "sg:address":"15 Sedgemoor Ct",
    "sg:city":"Newport",
    "sg:classifiers":[
        {
            "category":"Building & Trades",
            "subcategory":"Landscaping Services",
            "type":"Services"
        }
    ],
    "sg:phone":"+44 1633 216737",
    "sg:postcode":"NP9 5EQ",
    "sg:province":"East Riding of Yorkshire",
    "sg:tags":[
        "landscape",
        "contractor"
    ],
    "wof:name":"R D West",
    "wof:placetype":"venue"
},
  "geometry": {"coordinates":[-3.005792,51.595398],"type":"Point"}
}