{
  "type": "Feature",
  "properties": {
    "iso:country":"GB",
    "sg:address":"13 High Street",
    "sg:city":"Malpas",
    "sg:classifiers":[
        {
            "category":"Food & Beverages",
            "subcategory":"Bakery",
            "type":"Retail Goods"
        }
    ],
    "sg:phone":"+44 1948 860352",
    "sg:postcode":"SY14 8NN",
    "sg:province":"Cheshire",
    "sg:tags":[
        "baker"
    ],
    "wof:name":"Huxley's",
    "wof:placetype":"venue"
},
  "geometry": {"coordinates":[-2.765529,53.020397],"type":"Point"}
}