{
  "type": "Feature",
  "properties": {
    "addr:full":"8 Barncluith Business Centre, Townhead Street Hamilton South Lanarkshire ML3 7DP",
    "addr:housenumber":"8",
    "addr:postcode":"ml3 7dp",
    "addr:street":"Barncluith Business Centre Townhead Street",
    "iso:country":"GB",
    "sg:address":"8 Barncluith Business Centre, Townhead Street",
    "sg:city":"Hamilton",
    "sg:classifiers":[
        {
            "category":"Professional",
            "subcategory":"Business Services",
            "type":"Services"
        }
    ],
    "sg:phone":"+44 1698 285650",
    "sg:postcode":"ML3 7DP",
    "sg:province":"South Lanarkshire",
    "sg:tags":[
        "trade"
    ],
    "wof:name":"The Entrepreneurial Exchange Ltd.",
    "wof:placetype":"venue"
},
  "geometry": {"coordinates":[-4.029104,55.772141],"type":"Point"}
}