{
  "type": "Feature",
  "properties": {
    "addr:full":"Beechlands, Riverhead Driffield East Riding of Yorkshire YO25 7PU",
    "addr:postcode":"yo25 7pu",
    "addr:street":"Beechlands Riverhead",
    "iso:country":"GB",
    "sg:address":"Beechlands, Riverhead",
    "sg:city":"Driffield",
    "sg:classifiers":[
        {
            "category":"Professional",
            "subcategory":"Printing & Photocopies",
            "type":"Services"
        }
    ],
    "sg:phone":"+44 1377 257200",
    "sg:postcode":"YO25 7PU",
    "sg:province":"East Riding of Yorkshire",
    "sg:tags":[
        "printer"
    ],
    "wof:name":"Halstead Print & Publications",
    "wof:placetype":"venue"
},
  "geometry": {"coordinates":[-0.436299,54.008968],"type":"Point"}
}