{
  "type": "Feature",
  "properties": {
    "iso:country":"GB",
    "sg:address":"Basingstoke Leisure Park, Worting Road",
    "sg:city":"Basingstoke",
    "sg:classifiers":[
        {
            "category":"Restaurant",
            "type":"Food & Drink"
        }
    ],
    "sg:phone":"+44 1256 811477",
    "sg:postcode":"RG22 6PG",
    "sg:province":"Hampshire",
    "wof:name":"The Spruce Goose Beefeater",
    "wof:placetype":"venue"
},
  "geometry": {"coordinates":[-1.1195700169,51.2653617859],"type":"Point"}
}