{
  "type": "Feature",
  "properties": {
    "addr:full":"127 Kildare St, Farnworth Bolton Lancashire BL4 9NX",
    "addr:housenumber":"127",
    "addr:postcode":"bl4 9nx",
    "addr:street":"Kildare St",
    "iso:country":"GB",
    "sg:address":"127 Kildare St, Farnworth",
    "sg:city":"Bolton",
    "sg:classifiers":[
        {
            "category":"Building & Trades",
            "subcategory":"Plumbing",
            "type":"Services"
        }
    ],
    "sg:phone":"+44 1204 572021",
    "sg:postcode":"BL4 9NX",
    "sg:province":"Lancashire",
    "sg:tags":[
        "heating"
    ],
    "wof:name":"D.W Roche",
    "wof:placetype":"venue"
},
  "geometry": {"coordinates":[-2.4065439701,53.5448989868],"type":"Point"}
}