{
  "type": "Feature",
  "properties": {
    "addr:full":"17-25 Cavendish Street Ramsgate Kent CT11 9AL",
    "addr:housenumber":"17-25",
    "addr:postcode":"ct11 9al",
    "addr:street":"Cavendish Street Ramsgate",
    "iso:country":"GB",
    "sg:address":"17-25 Cavendish Street",
    "sg:city":"Ramsgate",
    "sg:classifiers":[
        {
            "category":"Professional",
            "subcategory":"Lawyer & Legal Services",
            "type":"Services"
        }
    ],
    "sg:postcode":"CT11 9AL",
    "sg:province":"Kent",
    "sg:tags":[
        "solicitor"
    ],
    "wof:name":"Robinson & Allfree",
    "wof:placetype":"venue"
},
  "geometry": {"coordinates":[1.4182430506,51.3338775635],"type":"Point"}
}