{
  "type": "Feature",
  "properties": {
    "addr:full":"19 Woods Terrace East, Murton Seaham Durham SR7 9AA",
    "addr:housenumber":"19",
    "addr:postcode":"sr7 9aa",
    "addr:street":"Woods Terrace East",
    "iso:country":"GB",
    "sg:address":"19 Woods Terrace East, Murton",
    "sg:city":"Seaham",
    "sg:classifiers":[
        {
            "category":"Fast Food",
            "type":"Food & Drink"
        }
    ],
    "sg:phone":"+44 191 526 6787",
    "sg:postcode":"SR7 9AA",
    "sg:province":"Durham",
    "sg:tags":[
        "away",
        "take"
    ],
    "wof:name":"Murton Cantonese Takeaway",
    "wof:placetype":"venue"
},
  "geometry": {"coordinates":[-1.3838889599,54.817489624],"type":"Point"}
}