{
  "type": "Feature",
  "properties": {
    "iso:country":"GB",
    "sg:address":"17 Carlingford Rd",
    "sg:city":"Chester Le Street",
    "sg:classifiers":[
        {
            "category":"Food & Beverages",
            "subcategory":"Meat & Fish",
            "type":"Retail Goods"
        }
    ],
    "sg:phone":"+44 191 389 2332",
    "sg:postcode":"DH2 3EH",
    "sg:province":"Durham",
    "sg:tags":[
        "chip"
    ],
    "wof:name":"Dulai Fish & Chips",
    "wof:placetype":"venue"
},
  "geometry": {"coordinates":[-1.5833179951,54.848361969],"type":"Point"}
}