{
  "type": "Feature",
  "properties": {
    "addr:full":"Richmond Farm Cottage, Babylon Lane, Hawkenbury Tonbridge Kent TN12 0EG",
    "addr:postcode":"tn12 0eg",
    "addr:street":"Babylon Lane Hawkenbury Tonbridge",
    "iso:country":"GB",
    "sg:address":"Richmond Farm Cottage, Babylon Lane, Hawkenbury",
    "sg:city":"Tonbridge",
    "sg:classifiers":[
        {
            "category":"Retail",
            "subcategory":"Repair Shop",
            "type":"Services"
        }
    ],
    "sg:postcode":"TN12 0EG",
    "sg:province":"Kent",
    "sg:tags":[
        "plant",
        "machinery"
    ],
    "wof:name":"Quadrant Plant",
    "wof:placetype":"venue"
},
  "geometry": {"coordinates":[0.583425,51.178108],"type":"Point"}
}