{
  "type": "Feature",
  "properties": {
    "addr:full":"84 Horton Hill Epsom Surrey KT19 8ST",
    "addr:housenumber":"84",
    "addr:postcode":"kt19 8st",
    "addr:street":"Horton Hill",
    "iso:country":"GB",
    "sg:address":"84 Horton Hill",
    "sg:city":"Epsom",
    "sg:classifiers":[
        {
            "category":"Professional",
            "subcategory":"Computer Services",
            "type":"Services"
        }
    ],
    "sg:postcode":"KT19 8ST",
    "sg:province":"Surrey",
    "sg:tags":[
        "system",
        "software"
    ],
    "wof:name":"Chieftain Projects Ltd",
    "wof:placetype":"venue"
},
  "geometry": {"coordinates":[-0.2751049995,51.3423805237],"type":"Point"}
}