{
  "type": "Feature",
  "properties": {
    "addr:full":"7 The Precinct, London Road Waterlooville Hampshire PO7 7DT",
    "addr:housenumber":"7",
    "addr:postcode":"po7 7dt",
    "addr:street":"Precinct London Road",
    "iso:country":"GB",
    "sg:address":"7 The Precinct, London Road",
    "sg:city":"Waterlooville",
    "sg:classifiers":[
        {
            "category":"Food & Beverages",
            "subcategory":"Bakery",
            "type":"Retail Goods"
        }
    ],
    "sg:phone":"+44 23 9226 3495",
    "sg:postcode":"PO7 7DT",
    "sg:province":"Hampshire",
    "sg:tags":[
        "baker"
    ],
    "wof:name":"Three Cooks Ltd.",
    "wof:placetype":"venue"
},
  "geometry": {"coordinates":[-1.03561,50.877151],"type":"Point"}
}