{
  "type": "Feature",
  "properties": {
    "addr:full":"Foreland Pl Stranraer Dumfries and Galloway DG9 0EB",
    "addr:postcode":"dg9 0eb",
    "addr:street":"Foreland Pl",
    "iso:country":"GB",
    "sg:address":"Foreland Pl",
    "sg:city":"Stranraer",
    "sg:classifiers":[
        {
            "category":"Home & Garden",
            "subcategory":"Furniture",
            "type":"Retail Goods"
        }
    ],
    "sg:postcode":"DG9 0EB",
    "sg:province":"Dumfries and Galloway",
    "wof:name":"Keenan,Carlyn,",
    "wof:placetype":"venue"
},
  "geometry": {"coordinates":[-5.036164,54.90897],"type":"Point"}
}