{
  "type": "Feature",
  "properties": {
    "addr:full":"192 Earls Court Road London Greater London SW5 9QF",
    "addr:housenumber":"192",
    "addr:postcode":"sw5 9qf",
    "addr:street":"Earls Court Road",
    "iso:country":"GB",
    "sg:address":"192 Earls Court Road",
    "sg:city":"London",
    "sg:classifiers":[
        {
            "category":"Food & Beverages",
            "subcategory":"Specialty",
            "type":"Retail Goods"
        }
    ],
    "sg:phone":"+44 20 7370 6868",
    "sg:postcode":"SW5 9QF",
    "sg:province":"Greater London",
    "sg:tags":[
        "product",
        "health"
    ],
    "wof:name":"Holland & Barrett",
    "wof:placetype":"venue"
},
  "geometry": {"coordinates":[-0.1942120045,51.492805481],"type":"Point"}
}