{
  "type": "Feature",
  "properties": {
    "addr:full":"13 The Brittons Braunton Devon EX33 2HE",
    "addr:housenumber":"13",
    "addr:postcode":"ex33 2he",
    "addr:street":"The;Braunton",
    "iso:country":"GB",
    "sg:address":"13 The Brittons",
    "sg:city":"Braunton",
    "sg:classifiers":[
        {
            "category":"Professional",
            "subcategory":"Engineering",
            "type":"Services"
        }
    ],
    "sg:phone":"+44 1271 814417",
    "sg:postcode":"EX33 2HE",
    "sg:province":"Devon",
    "sg:tags":[
        "contractor",
        "electrical",
        "engineer"
    ],
    "wof:name":"D Clements",
    "wof:placetype":"venue"
},
  "geometry": {"coordinates":[-4.157366,51.105991],"type":"Point"}
}