{
  "type": "Feature",
  "properties": {
    "addr:full":"Priddys Yard, Water End, Old Basing Basingstoke Hampshire RG24 7BA",
    "addr:postcode":"rg24 7ba",
    "addr:street":"Water End",
    "iso:country":"GB",
    "sg:address":"Priddys Yard, Water End, Old Basing",
    "sg:city":"Basingstoke",
    "sg:classifiers":[
        {
            "category":"Wholesale",
            "subcategory":"Fruits & Vegetables",
            "type":"Manufacturing & Wholesale Goods"
        }
    ],
    "sg:phone":"+44 1256 763811",
    "sg:postcode":"RG24 7BA",
    "sg:province":"Hampshire",
    "wof:name":"Priddy & Sons Ltd.",
    "wof:placetype":"venue"
},
  "geometry": {"coordinates":[-1.045195,51.263206],"type":"Point"}
}