{
  "type": "Feature",
  "properties": {
    "addr:full":"509 High Road Wembley Greater London HA0 2DH",
    "addr:housenumber":"509",
    "addr:postcode":"ha0 2dh",
    "addr:street":"High Road",
    "iso:country":"GB",
    "sg:address":"509 High Road",
    "sg:city":"Wembley",
    "sg:classifiers":[
        {
            "category":"Shopping",
            "subcategory":"Baby Store",
            "type":"Retail Goods"
        }
    ],
    "sg:postcode":"HA0 2DH",
    "sg:province":"Greater London",
    "sg:tags":[
        "babywear",
        "childrens"
    ],
    "wof:name":"Net Clothing",
    "wof:placetype":"venue"
},
  "geometry": {"coordinates":[-0.298303,51.551937],"type":"Point"}
}