{
  "type": "Feature",
  "properties": {
    "addr:full":"Aidleys Yard, Westbrook Rd, Trafford Park Manchester Cheshire M17 1AY",
    "addr:postcode":"m17 1ay",
    "addr:street":"Westbrook Rd",
    "iso:country":"GB",
    "sg:address":"Aidleys Yard, Westbrook Rd, Trafford Park",
    "sg:city":"Manchester",
    "sg:phone":"+44 161 877 2677",
    "sg:postcode":"M17 1AY",
    "sg:province":"Cheshire",
    "wof:name":"D.J Senior",
    "wof:placetype":"venue"
},
  "geometry": {"coordinates":[-2.308359,53.46814],"type":"Point"}
}