{
  "type": "Feature",
  "properties": {
    "iso:country":"GB",
    "sg:address":"Squirrel Cottage, Shotteswell",
    "sg:city":"Banbury",
    "sg:classifiers":[
        {
            "category":"Community Center",
            "type":"Public Place"
        },
        {
            "category":"Education",
            "subcategory":"Dance Studio",
            "type":"Public Place"
        }
    ],
    "sg:phone":"+44 1295 730004",
    "sg:postcode":"OX17 1HU",
    "sg:province":"Northamptonshire",
    "sg:tags":[
        "school",
        "centre",
        "recreation",
        "leisure",
        "dancing"
    ],
    "wof:name":"Straford Gymnastics Club",
    "wof:placetype":"venue"
},
  "geometry": {"coordinates":[-1.3827300072,52.1075782776],"type":"Point"}
}