{
  "type": "Feature",
  "properties": {
    "addr:full":"Unit 10a Rivergate, The Mall Irvine North Ayrshire KA12 8EH",
    "addr:housenumber":"unit 10a",
    "addr:postcode":"ka12 8eh",
    "addr:street":"Rivergate The Mall",
    "iso:country":"GB",
    "sg:address":"Unit 10a Rivergate, The Mall",
    "sg:city":"Irvine",
    "sg:classifiers":[
        {
            "category":"Bars & Pubs",
            "type":"Food & Drink"
        },
        {
            "category":"Community Center",
            "subcategory":"Social",
            "type":"Public Place"
        }
    ],
    "sg:phone":"+44 1294 271170",
    "sg:postcode":"KA12 8EH",
    "sg:province":"North Ayrshire",
    "sg:tags":[
        "pubs",
        "house",
        "inn",
        "activity"
    ],
    "wof:name":"Eagle Cavern",
    "wof:placetype":"venue"
},
  "geometry": {"coordinates":[-4.668434,55.6035],"type":"Point"}
}