{
  "type": "Feature",
  "properties": {
    "addr:full":"43 Birley Rise Sheffield South Yorkshire S6 1HU",
    "addr:housenumber":"43",
    "addr:postcode":"s6 1hu",
    "addr:street":"Birley Rise",
    "iso:country":"GB",
    "sg:address":"43 Birley Rise",
    "sg:city":"Sheffield",
    "sg:classifiers":[
        {
            "category":"Building & Trades",
            "subcategory":"Construction",
            "type":"Services"
        }
    ],
    "sg:phone":"+44 114 231 4759",
    "sg:postcode":"S6 1HU",
    "sg:province":"South Yorkshire",
    "sg:tags":[
        "roofing"
    ],
    "wof:name":"Malden Roofing Contractors",
    "wof:placetype":"venue"
},
  "geometry": {"coordinates":[-1.500914,53.422344],"type":"Point"}
}