{
  "type": "Feature",
  "properties": {
    "addr:full":"Marchway, Battlefield Enterprise Pk Shrewsbury Shropshire SY1 3JE",
    "addr:postcode":"sy1 3je",
    "addr:street":"Pk Shrewsbury",
    "iso:country":"GB",
    "sg:address":"Marchway, Battlefield Enterprise Pk",
    "sg:city":"Shrewsbury",
    "sg:classifiers":[
        {
            "category":"Personal",
            "type":"Services"
        }
    ],
    "sg:postcode":"SY1 3JE",
    "sg:province":"Shropshire",
    "sg:tags":[
        "wedding"
    ],
    "wof:name":"Muir,Deidre,",
    "wof:placetype":"venue"
},
  "geometry": {"coordinates":[-2.751284,52.706566],"type":"Point"}
}