{
  "type": "Feature",
  "properties": {
    "addr:full":"Estate House, 2 Pembroke Road Sevenoaks Kent TN13 1XR",
    "addr:housenumber":"2",
    "addr:postcode":"tn13 1xr",
    "addr:street":"Pembroke Road",
    "iso:country":"GB",
    "sg:address":"Estate House, 2 Pembroke Road",
    "sg:city":"Sevenoaks",
    "sg:classifiers":[
        {
            "category":"Professional",
            "subcategory":"Lawyer & Legal Services",
            "type":"Services"
        }
    ],
    "sg:postcode":"TN13 1XR",
    "sg:province":"Kent",
    "sg:tags":[
        "solicitor"
    ],
    "wof:name":"Farmar & Shirreff",
    "wof:placetype":"venue"
},
  "geometry": {"coordinates":[0.192245,51.273064],"type":"Point"}
}