{
  "type": "Feature",
  "properties": {
    "addr:full":"2 Baird Rd Enfield Greater London EN1 1EB",
    "addr:housenumber":"2",
    "addr:postcode":"en1 1eb",
    "addr:street":"Baird Rd",
    "iso:country":"GB",
    "sg:address":"2 Baird Rd",
    "sg:city":"Enfield",
    "sg:classifiers":[
        {
            "category":"Shopping",
            "subcategory":"Computers & Home Electronics",
            "type":"Retail Goods"
        }
    ],
    "sg:phone":"+44 20 8805 3131",
    "sg:postcode":"EN1 1EB",
    "sg:province":"Greater London",
    "sg:tags":[
        "electrical"
    ],
    "wof:name":"C R Electrical",
    "wof:placetype":"venue"
},
  "geometry": {"coordinates":[-0.0565330014,51.6502990723],"type":"Point"}
}