{
  "type": "Feature",
  "properties": {
    "addr:full":"The Wharf, Riverside Ind Est, Fazeley Tamworth Staffordshire B78 3SD",
    "addr:postcode":"b78 3sd",
    "addr:street":"Riverside;Est",
    "iso:country":"GB",
    "sg:address":"The Wharf, Riverside Ind Est, Fazeley",
    "sg:city":"Tamworth",
    "sg:classifiers":[
        {
            "category":"Freight",
            "type":"Transportation"
        }
    ],
    "sg:phone":"+44 1827 260128",
    "sg:postcode":"B78 3SD",
    "sg:province":"Staffordshire",
    "sg:tags":[
        "haulage",
        "road"
    ],
    "wof:name":"Beeson Haulage",
    "wof:placetype":"venue"
},
  "geometry": {"coordinates":[-1.7036989927,52.6155509949],"type":"Point"}
}