{
  "type": "Feature",
  "properties": {
    "addr:full":"9 South Street London Greater London W1K 2XA",
    "addr:housenumber":"9",
    "addr:postcode":"w1k 2xa",
    "addr:street":"South Street",
    "iso:country":"GB",
    "sg:address":"9 South Street",
    "sg:city":"London",
    "sg:classifiers":[
        {
            "category":"Professional",
            "subcategory":"Management & Consulting",
            "type":"Services"
        }
    ],
    "sg:phone":"+44 20 7317 0800",
    "sg:postcode":"W1K 2XA",
    "sg:province":"Greater London",
    "sg:tags":[
        "consultant"
    ],
    "wof:name":"Flag Telecom Ltd.",
    "wof:placetype":"venue"
},
  "geometry": {"coordinates":[-0.1527519971,51.508026123],"type":"Point"}
}