{
  "type": "Feature",
  "properties": {
    "addr:full":"22 Narrowgate Alnwick Northumberland NE66 1JG",
    "addr:housenumber":"22",
    "addr:postcode":"ne66 1jg",
    "addr:street":"Narrowgate",
    "iso:country":"GB",
    "sg:address":"22 Narrowgate",
    "sg:city":"Alnwick",
    "sg:classifiers":[
        {
            "category":"Shopping",
            "subcategory":"Books",
            "type":"Retail Goods"
        }
    ],
    "sg:postcode":"NE66 1JG",
    "sg:province":"Northumberland",
    "sg:tags":[
        "bookseller"
    ],
    "wof:name":"Book Harvest",
    "wof:placetype":"venue"
},
  "geometry": {"coordinates":[-1.708082,55.414661],"type":"Point"}
}