{
  "type": "Feature",
  "properties": {
    "addr:full":"Iver Stud, Swan Road Iver Berkshire SL0 9LA",
    "addr:postcode":"sl0 9la",
    "addr:street":"Iver;Swan Road",
    "iso:country":"GB",
    "sg:address":"Iver Stud, Swan Road",
    "sg:city":"Iver",
    "sg:classifiers":[
        {
            "category":"Building & Trades",
            "subcategory":"Landscaping Services",
            "type":"Services"
        }
    ],
    "sg:phone":"+44 1753 652022",
    "sg:postcode":"SL0 9LA",
    "sg:province":"Berkshire",
    "sg:tags":[
        "landscape",
        "contractor"
    ],
    "wof:name":"Practicality Brown Ltd",
    "wof:placetype":"venue"
},
  "geometry": {"coordinates":[-0.510574,51.520699],"type":"Point"}
}