{
  "type": "Feature",
  "properties": {
    "addr:full":"121a Kedleston Road Derby Derbyshire DE22 1FS",
    "addr:housenumber":"121a",
    "addr:postcode":"de22 1fs",
    "addr:street":"Kedleston Road",
    "iso:country":"GB",
    "sg:address":"121a Kedleston Road",
    "sg:city":"Derby",
    "sg:classifiers":[
        {
            "category":"Professional",
            "type":"Services"
        },
        {
            "category":"Food & Beverages",
            "subcategory":"Bakery",
            "type":"Retail Goods"
        }
    ],
    "sg:postcode":"DE22 1FS",
    "sg:province":"Derbyshire",
    "sg:tags":[
        "shop",
        "baker",
        "caterer"
    ],
    "wof:name":"COOPERS CATERING",
    "wof:placetype":"venue"
},
  "geometry": {"coordinates":[-1.49004,52.931873],"type":"Point"}
}