{
  "type": "Feature",
  "properties": {
    "addr:full":"239 Darwen Road, Bromley Cross Bolton Lancashire BL7 9BS",
    "addr:housenumber":"239",
    "addr:postcode":"bl7 9bs",
    "addr:street":"Darwen Road",
    "iso:country":"GB",
    "sg:address":"239 Darwen Road, Bromley Cross",
    "sg:city":"Bolton",
    "sg:classifiers":[
        {
            "category":"Personal",
            "subcategory":"Beauty Salon",
            "type":"Services"
        }
    ],
    "sg:phone":"+44 1204 305328",
    "sg:postcode":"BL7 9BS",
    "sg:province":"Lancashire",
    "sg:tags":[
        "lady",
        "hairdresser"
    ],
    "wof:name":"Bows 'N' Belles",
    "wof:placetype":"venue"
},
  "geometry": {"coordinates":[-2.42026,53.615433],"type":"Point"}
}