{
  "type": "Feature",
  "properties": {
    "addr:full":"167 Boston Rd Hanwell Greater London W7 3QJ",
    "addr:housenumber":"167",
    "addr:postcode":"w7 3qj",
    "addr:street":"Boston Rd",
    "iso:country":"GB",
    "sg:address":"167 Boston Rd",
    "sg:city":"Hanwell",
    "sg:classifiers":[
        {
            "category":"Autos & Motor Vehicles",
            "subcategory":"Fuel & Gas Station",
            "type":"Retail Goods"
        }
    ],
    "sg:phone":"+44 20 8567 1312",
    "sg:postcode":"W7 3QJ",
    "sg:province":"Greater London",
    "sg:tags":[
        "petrol",
        "filling"
    ],
    "wof:name":"Studley Grange Service Station",
    "wof:placetype":"venue"
},
  "geometry": {"coordinates":[-0.333597,51.504204],"type":"Point"}
}