{
  "type": "Feature",
  "properties": {
    "addr:full":"Marton Drive Blackpool Lancashire FY4 3EU",
    "addr:postcode":"fy4 3eu",
    "addr:street":"Marton Drive",
    "iso:country":"GB",
    "sg:address":"Marton Drive",
    "sg:city":"Blackpool",
    "sg:classifiers":[
        {
            "category":"Bars & Pubs",
            "type":"Food & Drink"
        }
    ],
    "sg:phone":"+44 1253 400435",
    "sg:postcode":"FY4 3EU",
    "sg:province":"Lancashire",
    "sg:tags":[
        "pubs",
        "inn"
    ],
    "wof:name":"Royal Hotel",
    "wof:placetype":"venue"
},
  "geometry": {"coordinates":[-3.034314,53.799786],"type":"Point"}
}