{
  "type": "Feature",
  "properties": {
    "addr:full":"27 Lonsdale Road Blackpool Lancashire FY1 6EE",
    "addr:housenumber":"27",
    "addr:postcode":"fy1 6ee",
    "addr:street":"Lonsdale Road",
    "iso:country":"GB",
    "sg:address":"27 Lonsdale Road",
    "sg:city":"Blackpool",
    "sg:classifiers":[
        {
            "category":"Travel",
            "subcategory":"Hotels & Motels",
            "type":"Entertainment"
        }
    ],
    "sg:phone":"+44 1253 346015",
    "sg:postcode":"FY1 6EE",
    "sg:province":"Lancashire",
    "wof:name":"Andora Hotel",
    "wof:placetype":"venue"
},
  "geometry": {"coordinates":[-3.0514819622,53.8052368164],"type":"Point"}
}