{
  "type": "Feature",
  "properties": {
    "addr:full":"249-251 High Street West Bromwich West Midlands B70 7LU",
    "addr:housenumber":"249-251",
    "addr:postcode":"b70 7lu",
    "addr:street":"High Street",
    "iso:country":"GB",
    "sg:address":"249-251 High Street",
    "sg:city":"West Bromwich",
    "sg:classifiers":[
        {
            "category":"Shopping",
            "subcategory":"Thrift Store",
            "type":"Retail Goods"
        }
    ],
    "sg:phone":"+44 121 580 1772",
    "sg:postcode":"B70 7LU",
    "sg:province":"West Midlands",
    "sg:tags":[
        "shop",
        "charity"
    ],
    "wof:name":"Oxfam Super Savings",
    "wof:placetype":"venue"
},
  "geometry": {"coordinates":[-1.9912339449,52.5171661377],"type":"Point"}
}