{
  "type": "Feature",
  "properties": {
    "iso:country":"GB",
    "sg:address":"Terrace Street",
    "sg:city":"Gravesend",
    "sg:classifiers":[
        {
            "category":"Sports & Exercise",
            "subcategory":"Gym",
            "type":"Entertainment"
        }
    ],
    "sg:phone":"+44 1474 326904",
    "sg:postcode":"DA12 2EE",
    "sg:province":"Kent",
    "sg:tags":[
        "fitness",
        "health",
        "centre"
    ],
    "wof:name":"Rhino's Gym",
    "wof:placetype":"venue"
},
  "geometry": {"coordinates":[0.371898,51.443069],"type":"Point"}
}