{
  "type": "Feature",
  "properties": {
    "addr:full":"17 Canonbury St Berkeley Gloucestershire GL13 9BE",
    "addr:housenumber":"17",
    "addr:postcode":"gl13 9be",
    "addr:street":"Canonbury St",
    "iso:country":"GB",
    "sg:address":"17 Canonbury St",
    "sg:city":"Berkeley",
    "sg:classifiers":[
        {
            "category":"Banks & Credit Unions",
            "subcategory":"Bank",
            "type":"Services"
        },
        {
            "category":"Banks & Credit Unions",
            "subcategory":"Financial Services",
            "type":"Services"
        }
    ],
    "sg:postcode":"GL13 9BE",
    "sg:province":"Gloucestershire",
    "sg:tags":[
        "consultant",
        "broker",
        "mortgage"
    ],
    "wof:name":"Cleverley,John,",
    "wof:placetype":"venue"
},
  "geometry": {"coordinates":[-2.4571909904,51.6913223267],"type":"Point"}
}