{
  "type": "Feature",
  "properties": {
    "addr:full":"46 Shepherds Hill Highgate Greater London N6 5RR",
    "addr:housenumber":"46",
    "addr:postcode":"n6 5rr",
    "addr:street":"Shepherds Hill Highgate",
    "iso:country":"GB",
    "sg:address":"46 Shepherds Hill",
    "sg:city":"Highgate",
    "sg:classifiers":[
        {
            "category":"Museum",
            "subcategory":"Art Museum",
            "type":"Entertainment"
        }
    ],
    "sg:phone":"+44 20 8374 5632",
    "sg:postcode":"N6 5RR",
    "sg:province":"Greater London",
    "sg:tags":[
        "gallery"
    ],
    "wof:name":"Portraits Consultancy",
    "wof:placetype":"venue"
},
  "geometry": {"coordinates":[-0.1368400007,51.5783081055],"type":"Point"}
}