{
  "type": "Feature",
  "properties": {
    "addr:full":"183 London Rd Portsmouth Hampshire PO2 9AE",
    "addr:housenumber":"183",
    "addr:postcode":"hampshire po2 9ae",
    "addr:street":"London Rd",
    "iso:country":"GB",
    "sg:address":"183 London Rd",
    "sg:city":"Portsmouth",
    "sg:classifiers":[
        {
            "category":"Food & Beverages",
            "subcategory":"Groceries & Convenience Stores",
            "type":"Retail Goods"
        }
    ],
    "sg:phone":"+44 23 9235 1577",
    "sg:postcode":"PO2 9AE",
    "sg:province":"Hampshire",
    "wof:name":"M & M Groceries",
    "wof:placetype":"venue"
},
  "geometry": {"coordinates":[-1.0787260532,50.8184547424],"type":"Point"}
}