{
  "type": "Feature",
  "properties": {
    "addr:full":"Andrew Street, East Kilbride Glasgow South Lanarkshire G74 1AD",
    "addr:postcode":"g74 1ad",
    "addr:street":"Andrew Street",
    "iso:country":"GB",
    "sg:address":"Andrew Street, East Kilbride",
    "sg:city":"Glasgow",
    "sg:classifiers":[
        {
            "category":"Health Services",
            "subcategory":"Doctor",
            "type":"Services"
        },
        {
            "category":"Health Services",
            "subcategory":"Clinic",
            "type":"Services"
        }
    ],
    "sg:phone":"+44 1355 906622",
    "sg:postcode":"G74 1AD",
    "sg:province":"South Lanarkshire",
    "sg:tags":[
        "nh",
        "practitioners"
    ],
    "wof:name":"The Hunter Health Centre",
    "wof:placetype":"venue"
},
  "geometry": {"coordinates":[-4.1760239601,55.7631568909],"type":"Point"}
}