{
  "type": "Feature",
  "properties": {
    "addr:full":"Devonshire Arcade Penrith Cumbria CA11 7SX",
    "addr:postcode":"ca11 7sx",
    "iso:country":"GB",
    "sg:address":"Devonshire Arcade",
    "sg:city":"Penrith",
    "sg:classifiers":[
        {
            "category":"Cafe",
            "type":"Food & Drink"
        }
    ],
    "sg:phone":"+44 1768 891240",
    "sg:postcode":"CA11 7SX",
    "sg:province":"Cumbria",
    "sg:tags":[
        "tea",
        "room"
    ],
    "wof:name":"The Arcade Coffee Shop",
    "wof:placetype":"venue"
},
  "geometry": {"coordinates":[-2.7574689388,54.6643028259],"type":"Point"}
}