{
  "type": "Feature",
  "properties": {
    "iso:country":"GB",
    "sg:address":"213 North Street",
    "sg:city":"Glenrothes",
    "sg:classifiers":[
        {
            "category":"Professional",
            "subcategory":"Accounting & Tax Preparation",
            "type":"Services"
        }
    ],
    "sg:phone":"+44 1592 774602",
    "sg:postcode":"KY7 5PW",
    "sg:province":"Fife",
    "sg:tags":[
        "payroll"
    ],
    "wof:name":"The Computer Bureau (Fife) Ltd.",
    "wof:placetype":"venue"
},
  "geometry": {"coordinates":[-3.167885,56.197098],"type":"Point"}
}