{
  "type": "Feature",
  "properties": {
    "addr:full":"Hepburn, Seine Lane, Enderby Leicester Leicestershire LE19 4PD",
    "addr:postcode":"le19 4pd",
    "addr:street":"Seine Lane",
    "iso:country":"GB",
    "sg:address":"Hepburn, Seine Lane, Enderby",
    "sg:city":"Leicester",
    "sg:classifiers":[
        {
            "category":"Wholesale",
            "subcategory":"Scrap",
            "type":"Manufacturing & Wholesale Goods"
        }
    ],
    "sg:phone":"+44 116 286 2450",
    "sg:postcode":"LE19 4PD",
    "sg:province":"Leicestershire",
    "sg:tags":[
        "waste",
        "metal"
    ],
    "wof:name":"Enderby Metals",
    "wof:placetype":"venue"
},
  "geometry": {"coordinates":[-1.2064640522,52.5886383057],"type":"Point"}
}