{
  "type": "Feature",
  "properties": {
    "addr:full":"106-108 High Road Loughton Essex IG10 4HN",
    "addr:housenumber":"106-108",
    "addr:postcode":"ig10 4hn",
    "addr:street":"High Road",
    "iso:country":"GB",
    "sg:address":"106-108 High Road",
    "sg:city":"Loughton",
    "sg:classifiers":[
        {
            "category":"Professional",
            "subcategory":"Lawyer & Legal Services",
            "type":"Services"
        }
    ],
    "sg:phone":"+44 20 8502 3991",
    "sg:postcode":"IG10 4HN",
    "sg:province":"Essex",
    "sg:tags":[
        "solicitor"
    ],
    "wof:name":"Foskett Marr Gadsby & Head",
    "wof:placetype":"venue"
},
  "geometry": {"coordinates":[0.052051,51.644451],"type":"Point"}
}