{
  "type": "Feature",
  "properties": {
    "addr:full":"9 Bemisters Lane Gosport Hampshire PO12 1HB",
    "addr:housenumber":"9",
    "addr:postcode":"po12 1hb",
    "addr:street":"Bemisters Lane",
    "iso:country":"GB",
    "sg:address":"9 Bemisters Lane",
    "sg:city":"Gosport",
    "sg:classifiers":[
        {
            "category":"Place Of Worship",
            "type":"Public Place"
        }
    ],
    "sg:phone":"+44 23 9258 9341",
    "sg:postcode":"PO12 1HB",
    "sg:province":"Hampshire",
    "wof:name":"Logos Fellowship Church",
    "wof:placetype":"venue"
},
  "geometry": {"coordinates":[-1.130368948,50.7920608521],"type":"Point"}
}