{
  "type": "Feature",
  "properties": {
    "iso:country":"GB",
    "sg:address":"3 Hearsall La",
    "sg:city":"Coventry",
    "sg:classifiers":[
        {
            "category":"Retail",
            "subcategory":"Laundry & Dry Cleaning",
            "type":"Services"
        }
    ],
    "sg:phone":"+44 24 7667 2505",
    "sg:postcode":"CV5 6HF",
    "sg:province":"West Midlands",
    "sg:tags":[
        "launderette"
    ],
    "wof:name":"Broomfield Launderette",
    "wof:placetype":"venue"
},
  "geometry": {"coordinates":[-1.52981,52.408314],"type":"Point"}
}