{
  "type": "Feature",
  "properties": {
    "addr:full":"34 Mersey Square Stockport Cheshire SK1 1RA",
    "addr:housenumber":"34",
    "addr:postcode":"sk1 1ra",
    "addr:street":"Mersey Square",
    "iso:country":"GB",
    "sg:address":"34 Mersey Square",
    "sg:city":"Stockport",
    "sg:classifiers":[
        {
            "category":"Shopping",
            "subcategory":"Clothing, Apparel, & Fashions",
            "type":"Retail Goods"
        }
    ],
    "sg:phone":"+44 161 476 2701",
    "sg:postcode":"SK1 1RA",
    "sg:province":"Cheshire",
    "sg:tags":[
        "shop"
    ],
    "wof:name":"Bash Corporation Ltd.",
    "wof:placetype":"venue"
},
  "geometry": {"coordinates":[-2.1628820896,53.410243988],"type":"Point"}
}