{
  "type": "Feature",
  "properties": {
    "addr:full":"1 William St Swindon Wiltshire SN1 5LB",
    "addr:housenumber":"1",
    "addr:postcode":"sn1 5lb",
    "addr:street":"William St",
    "iso:country":"GB",
    "sg:address":"1 William St",
    "sg:city":"Swindon",
    "sg:classifiers":[
        {
            "category":"Bars & Pubs",
            "type":"Food & Drink"
        }
    ],
    "sg:phone":"+44 1793 522389",
    "sg:postcode":"SN1 5LB",
    "sg:province":"Wiltshire",
    "sg:tags":[
        "pubs",
        "inn"
    ],
    "wof:name":"Park Hotel The",
    "wof:placetype":"venue"
},
  "geometry": {"coordinates":[-1.791935,51.557121],"type":"Point"}
}