{
  "type": "Feature",
  "properties": {
    "addr:full":"4 Verney Ho, 1b Hollywood Rd London Greater London SW10 9HS",
    "addr:housenumber":"4;1b",
    "addr:postcode":"sw10 9hs",
    "addr:street":"Verney Ho;Hollywood Rd",
    "iso:country":"GB",
    "sg:address":"4 Verney Ho, 1b Hollywood Rd",
    "sg:city":"London",
    "sg:classifiers":[
        {
            "category":"Professional",
            "subcategory":"Management & Consulting",
            "type":"Services"
        }
    ],
    "sg:phone":"+44 20 7376 5322",
    "sg:postcode":"SW10 9HS",
    "sg:province":"Greater London",
    "sg:tags":[
        "marketing",
        "consultant"
    ],
    "wof:name":"Barker,Paul,Consultancy Ltd (The)",
    "wof:placetype":"venue"
},
  "geometry": {"coordinates":[-0.18321,51.485008],"type":"Point"}
}