{
  "type": "Feature",
  "properties": {
    "iso:country":"GB",
    "sg:address":"Leo House, Portsmouth Road",
    "sg:city":"Thames Ditton",
    "sg:classifiers":[
        {
            "category":"Communications",
            "type":"Services"
        }
    ],
    "sg:phone":"+44 20 8398 9898",
    "sg:postcode":"KT7 0XF",
    "sg:province":"Surrey",
    "sg:tags":[
        "audio-visual"
    ],
    "wof:name":"The Leo House Partnership",
    "wof:placetype":"venue"
},
  "geometry": {"coordinates":[-0.325802,51.389183],"type":"Point"}
}