{
  "type": "Feature",
  "properties": {
    "iso:country":"GB",
    "sg:address":"72-74 Bryn Street, Ashton-in-makerfieldbryn",
    "sg:city":"Wigan",
    "sg:classifiers":[
        {
            "category":"Real Estate",
            "subcategory":"Real Estate Operator",
            "type":"Services"
        }
    ],
    "sg:phone":"+44 1942 716539",
    "sg:postcode":"WN4 9AU",
    "sg:province":"Lancashire",
    "sg:tags":[
        "letting",
        "agent"
    ],
    "wof:name":"W Cunliffe Ltd.",
    "wof:placetype":"venue"
},
  "geometry": {"coordinates":[-2.6386818886,53.4882698059],"type":"Point"}
}