{
  "type": "Feature",
  "properties": {
    "addr:full":"15-17 Colindale Avenue London Greater London NW9 5DS",
    "addr:housenumber":"15-17",
    "addr:postcode":"nw9 5ds",
    "addr:street":"Colindale Avenue",
    "iso:country":"GB",
    "sg:address":"15-17 Colindale Avenue",
    "sg:city":"London",
    "sg:classifiers":[
        {
            "category":"Home & Garden",
            "subcategory":"Furniture",
            "type":"Retail Goods"
        }
    ],
    "sg:phone":"+44 20 8205 7547",
    "sg:postcode":"NW9 5DS",
    "sg:province":"Greater London",
    "wof:name":"New Venture Furniture Ltd.",
    "wof:placetype":"venue"
},
  "geometry": {"coordinates":[-0.256076,51.592888],"type":"Point"}
}