{
  "type": "Feature",
  "properties": {
    "addr:full":"Unit 4, Old Mill Road Bristol Somerset BS20 7BX",
    "addr:housenumber":"unit 4",
    "addr:postcode":"bs20 7bx",
    "addr:street":"Old Mill Road",
    "iso:country":"GB",
    "sg:address":"Unit 4, Old Mill Road",
    "sg:city":"Bristol",
    "sg:classifiers":[
        {
            "category":"Shopping",
            "subcategory":"Clothing, Apparel, & Fashions",
            "type":"Retail Goods"
        }
    ],
    "sg:phone":"+44 1275 846119",
    "sg:postcode":"BS20 7BX",
    "sg:province":"Somerset",
    "sg:tags":[
        "workwear",
        "protective"
    ],
    "wof:name":"Lecsafe Ltd.",
    "wof:placetype":"venue"
},
  "geometry": {"coordinates":[-2.7646579742,51.4846878052],"type":"Point"}
}