{
  "type": "Feature",
  "properties": {
    "addr:full":"43 Charlotte Road London Greater London EC2A 3PD",
    "addr:housenumber":"43",
    "addr:postcode":"ec2a 3pd",
    "addr:street":"Charlotte Road",
    "iso:country":"GB",
    "sg:address":"43 Charlotte Road",
    "sg:city":"London",
    "sg:classifiers":[
        {
            "category":"Professional",
            "subcategory":"Art Services",
            "type":"Services"
        }
    ],
    "sg:phone":"+44 20 7729 0122",
    "sg:postcode":"EC2A 3PD",
    "sg:province":"Greater London",
    "sg:tags":[
        "photographer"
    ],
    "wof:name":"Dominic Turner",
    "wof:placetype":"venue"
},
  "geometry": {"coordinates":[-0.080884,51.525257],"type":"Point"}
}