{
  "type": "Feature",
  "properties": {
    "addr:full":"Loddon House, Basing View Basingstoke Hampshire RG21 4JT",
    "addr:postcode":"rg21 4jt",
    "addr:street":"Basing View",
    "iso:country":"GB",
    "sg:address":"Loddon House, Basing View",
    "sg:city":"Basingstoke",
    "sg:classifiers":[
        {
            "category":"Professional",
            "type":"Services"
        }
    ],
    "sg:phone":"+44 1256 842200",
    "sg:postcode":"RG21 4JT",
    "sg:province":"Hampshire",
    "sg:tags":[
        "repair",
        "tech",
        "maintenance"
    ],
    "wof:name":"E D S",
    "wof:placetype":"venue"
},
  "geometry": {"coordinates":[-1.0735419989,51.2688407898],"type":"Point"}
}