{
  "type": "Feature",
  "properties": {
    "iso:country":"GB",
    "sg:address":"98 High Street",
    "sg:city":"Dunbar",
    "sg:classifiers":[
        {
            "category":"Travel",
            "subcategory":"Travel Agent",
            "type":"Entertainment"
        }
    ],
    "sg:phone":"+44 1368 863818",
    "sg:postcode":"EH42 1JJ",
    "sg:province":"East Lothian",
    "wof:name":"Dunbar Travel Bureau",
    "wof:placetype":"venue"
},
  "geometry": {"coordinates":[-2.5162129402,56.0024261475],"type":"Point"}
}