{
  "type": "Feature",
  "properties": {
    "iso:country":"GB",
    "sg:address":"90 Hill Top",
    "sg:city":"Tonbridge",
    "sg:classifiers":[
        {
            "category":"Professional",
            "subcategory":"Accounting & Tax Preparation",
            "type":"Services"
        }
    ],
    "sg:phone":"+44 1732 369708",
    "sg:postcode":"TN9 2UP",
    "sg:province":"Kent",
    "sg:tags":[
        "accountant",
        "activity"
    ],
    "sg:website":"http://www.eurobell.co.uk",
    "wof:name":"Stephen J Kerry",
    "wof:placetype":"venue"
},
  "geometry": {"coordinates":[0.266995,51.183575],"type":"Point"}
}