{
  "type": "Feature",
  "properties": {
    "iso:country":"GB",
    "sg:address":"Oldfield Business Park, Duke Street, Fenton",
    "sg:city":"Stoke-on-trent",
    "sg:classifiers":[
        {
            "category":"Building & Trades",
            "subcategory":"Landscaping Services",
            "type":"Services"
        }
    ],
    "sg:phone":"+44 1782 593444",
    "sg:postcode":"ST4 3NX",
    "sg:province":"Staffordshire",
    "sg:tags":[
        "horticultural",
        "consultant"
    ],
    "wof:name":"Seddons (Plant & Engineers) Ltd.",
    "wof:placetype":"venue"
},
  "geometry": {"coordinates":[-2.154834,52.994953],"type":"Point"}
}