{
  "type": "Feature",
  "properties": {
    "addr:full":"Kebbell House Watford Hertfordshire WD19 5BE",
    "addr:postcode":"wd19 5be",
    "iso:country":"GB",
    "sg:address":"Kebbell House",
    "sg:city":"Watford",
    "sg:classifiers":[
        {
            "category":"Social Services",
            "subcategory":"Job Training",
            "type":"Services"
        }
    ],
    "sg:phone":"+44 20 8428 2829",
    "sg:postcode":"WD19 5BE",
    "sg:province":"Hertfordshire",
    "sg:tags":[
        "translator",
        "interpreter"
    ],
    "wof:name":"Esperanto Translating Service",
    "wof:placetype":"venue"
},
  "geometry": {"coordinates":[-0.3849300146,51.6288795471],"type":"Point"}
}