{
  "type": "Feature",
  "properties": {
    "addr:full":"Ramsey Road St Ives Cambridgeshire PE27 5DA",
    "addr:postcode":"pe27 5da",
    "addr:street":"Ramsey Road",
    "iso:country":"GB",
    "sg:address":"Ramsey Road",
    "sg:city":"St Ives",
    "sg:classifiers":[
        {
            "category":"Manufacturing",
            "subcategory":"Rubber & Plastics",
            "type":"Manufacturing & Wholesale Goods"
        }
    ],
    "sg:phone":"+44 1480 462095",
    "sg:postcode":"PE27 5DA",
    "sg:province":"Cambridgeshire",
    "sg:tags":[
        "injection",
        "moulding"
    ],
    "wof:name":"Permanex Ltd.",
    "wof:placetype":"venue"
},
  "geometry": {"coordinates":[-0.0763589963,52.333065033],"type":"Point"}
}