{
  "type": "Feature",
  "properties": {
    "addr:full":"67 Second Av Pontefract West Yorkshire WF9 5BA",
    "addr:housenumber":"67",
    "addr:postcode":"wf9 5ba",
    "addr:street":"Second Av Pontefract West",
    "iso:country":"GB",
    "sg:address":"67 Second Av",
    "sg:city":"Pontefract",
    "sg:classifiers":[
        {
            "category":"Building & Trades",
            "subcategory":"Construction",
            "type":"Services"
        }
    ],
    "sg:phone":"+44 1977 610469",
    "sg:postcode":"WF9 5BA",
    "sg:province":"West Yorkshire",
    "sg:tags":[
        "window",
        "replacement"
    ],
    "wof:name":"K C Home Improvements",
    "wof:placetype":"venue"
},
  "geometry": {"coordinates":[-1.375947,53.638557],"type":"Point"}
}