{
  "type": "Feature",
  "properties": {
    "iso:country":"GB",
    "sg:address":"4 Queens Sq",
    "sg:city":"Poulton Le Fylde",
    "sg:classifiers":[
        {
            "category":"Cafe",
            "type":"Food & Drink"
        }
    ],
    "sg:phone":"+44 1253 893421",
    "sg:postcode":"FY6 7BN",
    "sg:province":"Lancashire",
    "sg:tags":[
        "tea",
        "room"
    ],
    "wof:name":"Coffee Pot Cafe The",
    "wof:placetype":"venue"
},
  "geometry": {"coordinates":[-2.9917,53.846176],"type":"Point"}
}