{
  "type": "Feature",
  "properties": {
    "addr:full":"Unit 1a Cobbs Wood Industrial Estate, Brunswick Road Ashford Kent TN23 1EL",
    "addr:housenumber":"unit 1a;estate",
    "addr:postcode":"tn23 1el",
    "addr:street":"Cobbs Wood Industrial;Brunswick Road",
    "iso:country":"GB",
    "sg:address":"Unit 1a Cobbs Wood Industrial Estate, Brunswick Road",
    "sg:city":"Ashford",
    "sg:classifiers":[
        {
            "category":"Wholesale",
            "subcategory":"Scrap",
            "type":"Manufacturing & Wholesale Goods"
        }
    ],
    "sg:postcode":"TN23 1EL",
    "sg:province":"Kent",
    "sg:tags":[
        "car",
        "breaker",
        "dismantlers"
    ],
    "wof:name":"D Lindley",
    "wof:placetype":"venue"
},
  "geometry": {"coordinates":[0.8760370016,51.1466331482],"type":"Point"}
}