{
  "type": "Feature",
  "properties": {
    "iso:country":"GB",
    "sg:address":"9 North Parade Avenue",
    "sg:city":"Oxford",
    "sg:classifiers":[
        {
            "category":"Shopping",
            "subcategory":"News",
            "type":"Retail Goods"
        }
    ],
    "sg:phone":"+44 1865 553190",
    "sg:postcode":"OX2 6LX",
    "sg:province":"Oxfordshire",
    "sg:tags":[
        "newsagent"
    ],
    "wof:name":"Leisure & Pleasure",
    "wof:placetype":"venue"
},
  "geometry": {"coordinates":[-1.262464,51.764454],"type":"Point"}
}