{
  "type": "Feature",
  "properties": {
    "addr:full":"Stables East Ct Maidstone Kent ME14 3JX",
    "addr:postcode":"me14 3jx",
    "addr:street":"East Ct",
    "iso:country":"GB",
    "sg:address":"Stables East Ct",
    "sg:city":"Maidstone",
    "sg:classifiers":[
        {
            "category":"Transit Center",
            "subcategory":"Passenger",
            "type":"Transportation"
        },
        {
            "category":"Retail",
            "subcategory":"Pet Boarding",
            "type":"Services"
        }
    ],
    "sg:phone":"+44 1622 736124",
    "sg:postcode":"ME14 3JX",
    "sg:province":"Kent",
    "sg:tags":[
        "kennel",
        "catteries"
    ],
    "wof:name":"Cats Whiskers The",
    "wof:placetype":"venue"
},
  "geometry": {"coordinates":[0.5250849724,51.2737998962],"type":"Point"}
}