{
  "type": "Feature",
  "properties": {
    "iso:country":"GB",
    "sg:address":"Smithfield Road",
    "sg:city":"Shrewsbury",
    "sg:classifiers":[
        {
            "category":"Home & Garden",
            "subcategory":"Furniture",
            "type":"Retail Goods"
        }
    ],
    "sg:phone":"+44 1743 363006",
    "sg:postcode":"SY1 1PB",
    "sg:province":"Shropshire",
    "wof:name":"Simon Boyd",
    "wof:placetype":"venue"
},
  "geometry": {"coordinates":[-2.755906,52.710022],"type":"Point"}
}