{
  "type": "Feature",
  "properties": {
    "iso:country":"GB",
    "sg:address":"Lea Hall, Lea",
    "sg:city":"Matlock",
    "sg:classifiers":[
        {
            "category":"Professional",
            "subcategory":"Printing & Photocopies",
            "type":"Services"
        }
    ],
    "sg:phone":"+44 1629 534265",
    "sg:postcode":"DE4 5GR",
    "sg:province":"Derbyshire",
    "sg:tags":[
        "finishing",
        "tag",
        "computer",
        "label",
        "supply"
    ],
    "wof:name":"Sheldrake Labels",
    "wof:placetype":"venue"
},
  "geometry": {"coordinates":[-1.5401710272,53.1044464111],"type":"Point"}
}