{
  "type": "Feature",
  "properties": {
    "addr:full":"578 Kingstanding Road Birmingham West Midlands B44 9SD",
    "addr:housenumber":"578",
    "addr:postcode":"b44 9sd",
    "addr:street":"Kingstanding Road",
    "iso:country":"GB",
    "sg:address":"578 Kingstanding Road",
    "sg:city":"Birmingham",
    "sg:classifiers":[
        {
            "category":"Wholesale",
            "subcategory":"Construction Materials",
            "type":"Manufacturing & Wholesale Goods"
        }
    ],
    "sg:postcode":"B44 9SD",
    "sg:province":"West Midlands",
    "sg:tags":[
        "merchant",
        "glass"
    ],
    "wof:name":"Key Glass",
    "wof:placetype":"venue"
},
  "geometry": {"coordinates":[-1.8854500055,52.5462646484],"type":"Point"}
}