{
  "type": "Feature",
  "properties": {
    "iso:country":"GB",
    "sg:address":"49 Drake Street",
    "sg:city":"Rochdale",
    "sg:classifiers":[
        {
            "category":"Shopping",
            "subcategory":"Florist",
            "type":"Retail Goods"
        }
    ],
    "sg:postcode":"OL16 1RX",
    "sg:province":"Lancashire",
    "wof:name":"Claphams Interflora",
    "wof:placetype":"venue"
},
  "geometry": {"coordinates":[-2.154747963,53.6158485413],"type":"Point"}
}