{
  "type": "Feature",
  "properties": {
    "addr:full":"The Barton North Tawton Devon EX20 2BB",
    "addr:housenumber":"tawton",
    "addr:postcode":"ex20 2bb",
    "addr:street":"North",
    "iso:country":"GB",
    "sg:address":"The Barton",
    "sg:city":"North Tawton",
    "sg:classifiers":[
        {
            "category":"Building & Trades",
            "subcategory":"Equipment Rental",
            "type":"Services"
        }
    ],
    "sg:phone":"+44 1837 82592",
    "sg:postcode":"EX20 2BB",
    "sg:province":"Devon",
    "sg:tags":[
        "plant",
        "machinery"
    ],
    "wof:name":"Dunn Plant",
    "wof:placetype":"venue"
},
  "geometry": {"coordinates":[-3.8996489048,50.7966346741],"type":"Point"}
}