{
  "type": "Feature",
  "properties": {
    "iso:country":"GB",
    "sg:address":"3 Bryn Rhosog, Loughor",
    "sg:city":"Swansea",
    "sg:classifiers":[
        {
            "category":"Shopping",
            "subcategory":"Clothing, Apparel, & Fashions",
            "type":"Retail Goods"
        }
    ],
    "sg:phone":"+44 1792 897594",
    "sg:postcode":"SA4 6SH",
    "sg:province":"Carmarthenshire",
    "sg:tags":[
        "workwear",
        "protective"
    ],
    "wof:name":"Ritchie's Laundry Services",
    "wof:placetype":"venue"
},
  "geometry": {"coordinates":[-4.054784,51.667744],"type":"Point"}
}