{
  "type": "Feature",
  "properties": {
    "addr:full":"Sanmore House, High Street Henfield West Sussex BN5 9JJ",
    "addr:postcode":"bn5 9jj",
    "addr:street":"High Street",
    "iso:country":"GB",
    "sg:address":"Sanmore House, High Street",
    "sg:city":"Henfield",
    "sg:classifiers":[
        {
            "category":"Retail",
            "subcategory":"Funeral Services",
            "type":"Services"
        }
    ],
    "sg:phone":"+44 1273 494577",
    "sg:postcode":"BN5 9JJ",
    "sg:province":"West Sussex",
    "wof:name":"Radmall Funeral Services",
    "wof:placetype":"venue"
},
  "geometry": {"coordinates":[-0.272319,50.930904],"type":"Point"}
}