{
  "type": "Feature",
  "properties": {
    "iso:country":"GB",
    "sg:address":"Auckland Drive",
    "sg:city":"Birmingham",
    "sg:classifiers":[
        {
            "category":"Education",
            "subcategory":"School",
            "type":"Public Place"
        }
    ],
    "sg:phone":"+44 121 748 1318",
    "sg:postcode":"B36 0DD",
    "sg:province":"West Midlands",
    "sg:tags":[
        "college",
        "commercial"
    ],
    "wof:name":"Bosworth Wood Junior & Infant School",
    "wof:placetype":"venue"
},
  "geometry": {"coordinates":[-1.7515039444,52.5077667236],"type":"Point"}
}