{
  "type": "Feature",
  "properties": {
    "addr:full":"6 Church Street, Mevagissey St Austell Cornwall PL26 6SP",
    "addr:housenumber":"6",
    "addr:postcode":"pl26 6sp",
    "addr:street":"Church Street",
    "iso:country":"GB",
    "sg:address":"6 Church Street, Mevagissey",
    "sg:city":"St Austell",
    "sg:classifiers":[
        {
            "category":"Arts & Performance",
            "subcategory":"Art Gallery",
            "type":"Entertainment"
        }
    ],
    "sg:phone":"+44 1726 844404",
    "sg:postcode":"PL26 6SP",
    "sg:province":"Cornwall",
    "wof:name":"The Kevin Platt Design Studio",
    "wof:placetype":"venue"
},
  "geometry": {"coordinates":[-4.787613,50.270508],"type":"Point"}
}