{
  "type": "Feature",
  "properties": {
    "addr:full":"Unit 1, 10-24 Standard Rd, Park Royal London Greater London NW10 6EU",
    "addr:housenumber":"unit 1",
    "addr:postcode":"10-24;nw10 6eu",
    "addr:street":"Standard Rd",
    "iso:country":"GB",
    "sg:address":"Unit 1, 10-24 Standard Rd, Park Royal",
    "sg:city":"London",
    "sg:classifiers":[
        {
            "category":"Shopping",
            "subcategory":"Clothing, Apparel, & Fashions",
            "type":"Retail Goods"
        }
    ],
    "sg:phone":"+44 20 8961 2326",
    "sg:postcode":"NW10 6EU",
    "sg:province":"Greater London",
    "sg:tags":[
        "clothing"
    ],
    "wof:name":"Sur La Cote Ltd",
    "wof:placetype":"venue"
},
  "geometry": {"coordinates":[-0.260305,51.528629],"type":"Point"}
}