{
  "type": "Feature",
  "properties": {
    "addr:full":"86 St Marys Street Southampton Hampshire SO14 1PA",
    "addr:housenumber":"86",
    "addr:postcode":"so14 1pa",
    "addr:street":"St Marys Street",
    "iso:country":"GB",
    "sg:address":"86 St Marys Street",
    "sg:city":"Southampton",
    "sg:classifiers":[
        {
            "category":"Cafe",
            "type":"Food & Drink"
        }
    ],
    "sg:postcode":"SO14 1PA",
    "sg:province":"Hampshire",
    "sg:tags":[
        "tea",
        "room"
    ],
    "wof:name":"Rodrigues Snack Bar",
    "wof:placetype":"venue"
},
  "geometry": {"coordinates":[-1.3967269659,50.9057502747],"type":"Point"}
}