{
  "type": "Feature",
  "properties": {
    "iso:country":"GB",
    "sg:address":"26 Adastral Clo",
    "sg:city":"Newmarket",
    "sg:classifiers":[
        {
            "category":"Building & Trades",
            "subcategory":"Construction",
            "type":"Services"
        }
    ],
    "sg:phone":"+44 1638 577997",
    "sg:postcode":"CB8 0PX",
    "sg:province":"Cambridgeshire",
    "sg:tags":[
        "builder"
    ],
    "wof:name":"Buildmark Construction",
    "wof:placetype":"venue"
},
  "geometry": {"coordinates":[0.393151,52.246887],"type":"Point"}
}