{
  "type": "Feature",
  "properties": {
    "addr:full":"11 Station Rd Billingham Durham TS23 1AF",
    "addr:housenumber":"11",
    "addr:postcode":"ts23 1af",
    "addr:street":"Station Rd",
    "iso:country":"GB",
    "sg:address":"11 Station Rd",
    "sg:city":"Billingham",
    "sg:classifiers":[
        {
            "category":"Insurance",
            "subcategory":"Insurance Agent",
            "type":"Services"
        }
    ],
    "sg:phone":"+44 1642 365222",
    "sg:postcode":"TS23 1AF",
    "sg:province":"Durham",
    "sg:tags":[
        "broker"
    ],
    "wof:name":"Wilson,H R,& Partners Ltd",
    "wof:placetype":"venue"
},
  "geometry": {"coordinates":[-1.2931859493,54.5962104797],"type":"Point"}
}