{
  "type": "Feature",
  "properties": {
    "addr:full":"Chapel Works, Waldringfield Woodbridge Suffolk IP12 4PT",
    "addr:postcode":"ip12 4pt",
    "iso:country":"GB",
    "sg:address":"Chapel Works, Waldringfield",
    "sg:city":"Woodbridge",
    "sg:classifiers":[
        {
            "category":"Building & Trades",
            "subcategory":"Construction",
            "type":"Services"
        }
    ],
    "sg:postcode":"IP12 4PT",
    "sg:province":"Suffolk",
    "sg:tags":[
        "demolition",
        "contractor"
    ],
    "wof:name":"Clarke Demolition Corporation Ltd",
    "wof:placetype":"venue"
},
  "geometry": {"coordinates":[1.3206429482,52.0527648926],"type":"Point"}
}