{
  "type": "Feature",
  "properties": {
    "addr:full":"468 Chiswick High Road London Greater London W4 5TT",
    "addr:housenumber":"468",
    "addr:postcode":"w4 5tt",
    "addr:street":"Chiswick High Road",
    "iso:country":"GB",
    "sg:address":"468 Chiswick High Road",
    "sg:city":"London",
    "sg:classifiers":[
        {
            "category":"Retail",
            "subcategory":"Funeral Services",
            "type":"Services"
        }
    ],
    "sg:phone":"+44 20 8994 0056",
    "sg:postcode":"W4 5TT",
    "sg:province":"Greater London",
    "sg:tags":[
        "director"
    ],
    "wof:name":"Frederick W Paine",
    "wof:placetype":"venue"
},
  "geometry": {"coordinates":[-0.268108,51.492943],"type":"Point"}
}