{
  "type": "Feature",
  "properties": {
    "iso:country":"GB",
    "sg:address":"12 Vincent Drive, Edgbaston",
    "sg:city":"Birmingham",
    "sg:classifiers":[
        {
            "category":"Shopping",
            "subcategory":"Department Store",
            "type":"Retail Goods"
        },
        {
            "category":"Food & Beverages",
            "subcategory":"Groceries & Convenience Stores",
            "type":"Retail Goods"
        }
    ],
    "sg:phone":"+44 121 472 4655",
    "sg:postcode":"B15 2ST",
    "sg:province":"West Midlands",
    "wof:name":"Vincent Food Store",
    "wof:placetype":"venue"
},
  "geometry": {"coordinates":[-1.9456169605,52.4488182068],"type":"Point"}
}