{
  "type": "Feature",
  "properties": {
    "iso:country":"GB",
    "sg:address":"Hollybush Garden Centre, Warstone Road, Shareshill",
    "sg:city":"Wolverhampton",
    "sg:classifiers":[
        {
            "category":"Home & Garden",
            "subcategory":"Furniture",
            "type":"Retail Goods"
        }
    ],
    "sg:postcode":"WV10 7LX",
    "sg:province":"Staffordshire",
    "wof:name":"Merlin Pine Furnishings",
    "wof:placetype":"venue"
},
  "geometry": {"coordinates":[-2.078614,52.652992],"type":"Point"}
}