{
  "type": "Feature",
  "properties": {
    "addr:full":"The Day Centre, Town Hall Way Dewsbury West Yorkshire WF12 8EE",
    "addr:postcode":"wf12 8ee",
    "addr:street":"Hall Way",
    "iso:country":"GB",
    "sg:address":"The Day Centre, Town Hall Way",
    "sg:city":"Dewsbury",
    "sg:classifiers":[
        {
            "category":"Social Services",
            "type":"Services"
        }
    ],
    "sg:phone":"+44 1924 325070",
    "sg:postcode":"WF12 8EE",
    "sg:province":"West Yorkshire",
    "wof:name":"Social Services Level Best",
    "wof:placetype":"venue"
},
  "geometry": {"coordinates":[-1.6269799471,53.6909599304],"type":"Point"}
}