{
  "type": "Feature",
  "properties": {
    "addr:full":"9 Thorpe Close, Portobello Road London Greater London W10 5XL",
    "addr:housenumber":"9",
    "addr:postcode":"w10 5xl",
    "addr:street":"Thorpe Close Portobello Road",
    "iso:country":"GB",
    "sg:address":"9 Thorpe Close, Portobello Road",
    "sg:city":"London",
    "sg:classifiers":[
        {
            "category":"Professional",
            "type":"Services"
        }
    ],
    "sg:phone":"+44 870 078 0558",
    "sg:postcode":"W10 5XL",
    "sg:province":"Greater London",
    "sg:tags":[
        "directory",
        "pub"
    ],
    "wof:name":"Gestalt Publications Ltd.",
    "wof:placetype":"venue"
},
  "geometry": {"coordinates":[-0.209949,51.518372],"type":"Point"}
}