{
  "type": "Feature",
  "properties": {
    "addr:full":"The Garage, Henley Rd, Sandford-on-thames Oxford Oxfordshire OX4 4YP",
    "addr:postcode":"ox4 4yp",
    "addr:street":"Henley Rd",
    "iso:country":"GB",
    "sg:address":"The Garage, Henley Rd, Sandford-on-thames",
    "sg:city":"Oxford",
    "sg:classifiers":[
        {
            "category":"Autos & Motor Vehicles",
            "subcategory":"Automobile Sales",
            "type":"Retail Goods"
        }
    ],
    "sg:postcode":"OX4 4YP",
    "sg:province":"Oxfordshire",
    "sg:tags":[
        "car"
    ],
    "wof:name":"Cowley Carriage Co",
    "wof:placetype":"venue"
},
  "geometry": {"coordinates":[-1.2234389782,51.7105293274],"type":"Point"}
}