{
  "type": "Feature",
  "properties": {
    "addr:full":"20 Albion Street London Greater London SE16 7JQ",
    "addr:housenumber":"20",
    "addr:postcode":"se16 7jq",
    "addr:street":"Albion Street",
    "iso:country":"GB",
    "sg:address":"20 Albion Street",
    "sg:city":"London",
    "sg:classifiers":[
        {
            "category":"Bars & Pubs",
            "type":"Food & Drink"
        }
    ],
    "sg:phone":"+44 20 7237 0182",
    "sg:postcode":"SE16 7JQ",
    "sg:province":"Greater London",
    "sg:tags":[
        "pubs",
        "inn"
    ],
    "wof:name":"The Albion",
    "wof:placetype":"venue"
},
  "geometry": {"coordinates":[-0.053359,51.499268],"type":"Point"}
}