{
  "type": "Feature",
  "properties": {
    "iso:country":"GB",
    "sg:address":"15 Church Rd, Banks",
    "sg:city":"Southport",
    "sg:classifiers":[
        {
            "category":"Shopping",
            "subcategory":"Pharmacy",
            "type":"Retail Goods"
        }
    ],
    "sg:postcode":"PR9 8ET",
    "sg:province":"Lancashire",
    "sg:tags":[
        "pharmacist",
        "chemist"
    ],
    "wof:name":"Andrew,Michael,",
    "wof:placetype":"venue"
},
  "geometry": {"coordinates":[-2.9237680435,53.68151474],"type":"Point"}
}