{
  "type": "Feature",
  "properties": {
    "addr:full":"2 Glebeland Street Merthyr Tydfil Merthyr Tydfil CF47 8AU",
    "addr:housenumber":"2",
    "addr:postcode":"cf47 8au",
    "addr:street":"Glebeland Street",
    "iso:country":"GB",
    "sg:address":"2 Glebeland Street",
    "sg:city":"Merthyr Tydfil",
    "sg:classifiers":[
        {
            "category":"Food & Beverages",
            "subcategory":"Liquor & Beverages",
            "type":"Retail Goods"
        }
    ],
    "sg:phone":"+44 1685 384379",
    "sg:postcode":"CF47 8AU",
    "sg:province":"Merthyr Tydfil",
    "sg:tags":[
        "beer",
        "spirit",
        "wines"
    ],
    "wof:name":"Thresher Drink Store",
    "wof:placetype":"venue"
},
  "geometry": {"coordinates":[-3.3784580231,51.746295929],"type":"Point"}
}