{
  "type": "Feature",
  "properties": {
    "iso:country":"GB",
    "sg:address":"Eastgate Street",
    "sg:city":"Llanidloes",
    "sg:classifiers":[
        {
            "category":"Health Services",
            "subcategory":"Hospital",
            "type":"Services"
        }
    ],
    "sg:phone":"+44 1686 414200",
    "sg:postcode":"SY18 6HF",
    "sg:province":"Powys",
    "wof:name":"Llanidloes War Memorial Hospital",
    "wof:placetype":"venue"
},
  "geometry": {"coordinates":[-3.538967,52.452396],"type":"Point"}
}