{
  "type": "Feature",
  "properties": {
    "addr:full":"Clackmannan Road Alloa Clackmannanshire FK10 1RY",
    "addr:postcode":"fk10 1ry",
    "addr:street":"Clackmannan Road",
    "iso:country":"GB",
    "sg:address":"Clackmannan Road",
    "sg:city":"Alloa",
    "sg:classifiers":[
        {
            "category":"Autos & Motor Vehicles",
            "subcategory":"Fuel & Gas Station",
            "type":"Retail Goods"
        }
    ],
    "sg:phone":"+44 1259 211413",
    "sg:postcode":"FK10 1RY",
    "sg:province":"Clackmannanshire",
    "sg:tags":[
        "hr",
        "petrol"
    ],
    "wof:name":"Ochil View Service Station",
    "wof:placetype":"venue"
},
  "geometry": {"coordinates":[-3.7818889618,56.1162414551],"type":"Point"}
}