{
  "type": "Feature",
  "properties": {
    "addr:full":"International Ho, 59 Compton Rd London Greater London N1 2YT",
    "addr:housenumber":"59",
    "addr:postcode":"n1 2yt",
    "addr:street":"Compton Rd",
    "iso:country":"GB",
    "sg:address":"International Ho, 59 Compton Rd",
    "sg:city":"London",
    "sg:classifiers":[
        {
            "category":"Professional",
            "subcategory":"Management & Consulting",
            "type":"Services"
        }
    ],
    "sg:postcode":"N1 2YT",
    "sg:province":"Greater London",
    "sg:tags":[
        "consultant",
        "business"
    ],
    "wof:name":"Fleming,Caroline Hamilton,",
    "wof:placetype":"venue"
},
  "geometry": {"coordinates":[-0.100469999,51.5461502075],"type":"Point"}
}