{
  "type": "Feature",
  "properties": {
    "iso:country":"GB",
    "sg:address":"The White House, Waytown",
    "sg:city":"Bridport",
    "sg:classifiers":[
        {
            "category":"Farming",
            "subcategory":"Livestock Farm",
            "type":"Manufacturing & Wholesale Goods"
        }
    ],
    "sg:phone":"+44 1308 488378",
    "sg:postcode":"DT6 5LF",
    "sg:province":"Dorset",
    "sg:tags":[
        "others"
    ],
    "wof:name":"Robert Barnes",
    "wof:placetype":"venue"
},
  "geometry": {"coordinates":[-2.7626609802,50.7266693115],"type":"Point"}
}