{
  "type": "Feature",
  "properties": {
    "addr:full":"17 Gloucester Street Stroud Gloucestershire GL5 1QG",
    "addr:housenumber":"17",
    "addr:postcode":"gl5 1qg",
    "addr:street":"Gloucester Street",
    "iso:country":"GB",
    "sg:address":"17 Gloucester Street",
    "sg:city":"Stroud",
    "sg:classifiers":[
        {
            "category":"Restaurant",
            "type":"Food & Drink"
        }
    ],
    "sg:phone":"+44 1453 766454",
    "sg:postcode":"GL5 1QG",
    "sg:province":"Gloucestershire",
    "sg:tags":[
        "indian",
        "-"
    ],
    "wof:name":"Balti Spice",
    "wof:placetype":"venue"
},
  "geometry": {"coordinates":[-2.2174990177,51.7462501526],"type":"Point"}
}