{
  "type": "Feature",
  "properties": {
    "iso:country":"GB",
    "sg:address":"10 Hurle Crescent",
    "sg:city":"Bristol",
    "sg:classifiers":[
        {
            "category":"Conference Center",
            "type":"Public Place"
        }
    ],
    "sg:postcode":"BS8 2TA",
    "sg:province":"City of Bristol",
    "wof:name":"Conference Management Services",
    "wof:placetype":"venue"
},
  "geometry": {"coordinates":[-2.6138329506,51.4668922424],"type":"Point"}
}