{
  "type": "Feature",
  "properties": {
    "iso:country":"GB",
    "sg:address":"Mole Road, Sindlesham",
    "sg:city":"Wokingham",
    "sg:classifiers":[
        {
            "category":"Retail",
            "subcategory":"Event Space",
            "type":"Services"
        }
    ],
    "sg:phone":"+44 118 978 3902",
    "sg:postcode":"RG41 5DB",
    "sg:province":"Berkshire",
    "sg:tags":[
        "banqueting",
        "room"
    ],
    "wof:name":"Sindlesham Court Ltd.",
    "wof:placetype":"venue"
},
  "geometry": {"coordinates":[-0.8921340108,51.4181213379],"type":"Point"}
}