{
  "type": "Feature",
  "properties": {
    "iso:country":"GB",
    "sg:address":"27 Havelock Crescent",
    "sg:city":"Bridlington",
    "sg:classifiers":[
        {
            "category":"Autos & Motor Vehicles",
            "subcategory":"Automobile Sales",
            "type":"Retail Goods"
        },
        {
            "category":"Retail",
            "subcategory":"Auto Repair",
            "type":"Services"
        }
    ],
    "sg:phone":"+44 1262 400031",
    "sg:postcode":"YO16 4JH",
    "sg:province":"East Riding of Yorkshire",
    "sg:tags":[
        "car",
        "electrician",
        "truck",
        "related",
        "garage"
    ],
    "wof:name":"Fuel Injection Service",
    "wof:placetype":"venue"
},
  "geometry": {"coordinates":[-0.2027769983,54.0890312195],"type":"Point"}
}