{
  "type": "Feature",
  "properties": {
    "addr:full":"434 St Annes Road London Greater London N15 3JH",
    "addr:housenumber":"434",
    "addr:postcode":"n15 3jh",
    "addr:street":"St Annes Road",
    "iso:country":"GB",
    "sg:address":"434 St Annes Road",
    "sg:city":"London",
    "sg:classifiers":[
        {
            "category":"Organizations",
            "subcategory":"Labor Organization",
            "type":"Services"
        },
        {
            "category":"Professional",
            "subcategory":"Business Services",
            "type":"Services"
        }
    ],
    "sg:phone":"+44 20 8800 4499",
    "sg:postcode":"N15 3JH",
    "sg:province":"Greater London",
    "sg:tags":[
        "import",
        "export",
        "agent"
    ],
    "wof:name":"Bayram & Sons Co",
    "wof:placetype":"venue"
},
  "geometry": {"coordinates":[-0.0988600031,51.5824508667],"type":"Point"}
}