{
  "type": "Feature",
  "properties": {
    "addr:full":"51 Bankfield La Southport Lancashire PR9 7NJ",
    "addr:housenumber":"51",
    "addr:postcode":"pr9 7nj",
    "addr:street":"Bankfield La Southport",
    "iso:country":"GB",
    "sg:address":"51 Bankfield La",
    "sg:city":"Southport",
    "sg:classifiers":[
        {
            "category":"Building & Trades",
            "subcategory":"Construction",
            "type":"Services"
        }
    ],
    "sg:postcode":"PR9 7NJ",
    "sg:province":"Lancashire",
    "sg:tags":[
        "builder"
    ],
    "wof:name":"Thorne,R,",
    "wof:placetype":"venue"
},
  "geometry": {"coordinates":[-2.9586000443,53.6604766846],"type":"Point"}
}