{
  "type": "Feature",
  "properties": {
    "addr:full":"Animal Shelter, Nottingham Road, Radcliffe On Trent Nottingham Nottinghamshire NG12 2DW",
    "addr:postcode":"ng12 2dw",
    "addr:street":"Road",
    "iso:country":"GB",
    "sg:address":"Animal Shelter, Nottingham Road, Radcliffe On Trent",
    "sg:city":"Nottingham",
    "sg:classifiers":[
        {
            "category":"Organizations",
            "subcategory":"Non-profit Organization",
            "type":"Services"
        }
    ],
    "sg:phone":"+44 115 933 4422",
    "sg:postcode":"NG12 2DW",
    "sg:province":"Nottinghamshire",
    "sg:tags":[
        "organisation",
        "animal",
        "welfare"
    ],
    "wof:name":"R S P C A",
    "wof:placetype":"venue"
},
  "geometry": {"coordinates":[-1.0287109613,52.9461364746],"type":"Point"}
}