{
  "type": "Feature",
  "properties": {
    "addr:full":"Gelli-deg Farm, Llangynog Carmarthen Carmarthenshire SA33 5DE",
    "addr:postcode":"sa33 5de",
    "iso:country":"GB",
    "sg:address":"Gelli-deg Farm, Llangynog",
    "sg:city":"Carmarthen",
    "sg:classifiers":[
        {
            "category":"Farming",
            "subcategory":"Livestock Farm",
            "type":"Manufacturing & Wholesale Goods"
        }
    ],
    "sg:phone":"+44 1267 211241",
    "sg:postcode":"SA33 5DE",
    "sg:province":"Carmarthenshire",
    "sg:tags":[
        "others"
    ],
    "wof:name":"Ian J H Thomas",
    "wof:placetype":"venue"
},
  "geometry": {"coordinates":[-4.409969,51.821075],"type":"Point"}
}