{
  "type": "Feature",
  "properties": {
    "addr:full":"Approach Farm, Hollicarrs, Escrick York North Yorkshire YO19 6EE",
    "addr:postcode":"yo19 6ee",
    "addr:street":"Approach;Hollicarrs",
    "iso:country":"GB",
    "sg:address":"Approach Farm, Hollicarrs, Escrick",
    "sg:city":"York",
    "sg:classifiers":[
        {
            "category":"Education",
            "subcategory":"Special Training",
            "type":"Public Place"
        }
    ],
    "sg:phone":"+44 1757 248923",
    "sg:postcode":"YO19 6EE",
    "sg:province":"North Yorkshire",
    "sg:tags":[
        "product",
        "centre"
    ],
    "wof:name":"Ouse & Derwent Training",
    "wof:placetype":"venue"
},
  "geometry": {"coordinates":[-1.044655,53.879566],"type":"Point"}
}