{
  "type": "Feature",
  "properties": {
    "iso:country":"GB",
    "sg:address":"10-11 Wimbledon Avenue",
    "sg:city":"Brandon",
    "sg:classifiers":[
        {
            "category":"Manufacturing",
            "subcategory":"Metals",
            "type":"Manufacturing & Wholesale Goods"
        }
    ],
    "sg:phone":"+44 1842 814492",
    "sg:postcode":"IP27 0NZ",
    "sg:province":"Norfolk",
    "sg:tags":[
        "steel",
        "fabricator",
        "erectors"
    ],
    "wof:name":"Sharward Steel Fabrications",
    "wof:placetype":"venue"
},
  "geometry": {"coordinates":[0.606498,52.43642],"type":"Point"}
}