{
  "type": "Feature",
  "properties": {
    "iso:country":"GB",
    "sg:address":"Parish  Cottages, Southill Road, Cardington",
    "sg:city":"Bedford",
    "sg:classifiers":[
        {
            "category":"Professional",
            "subcategory":"Business Services",
            "type":"Services"
        }
    ],
    "sg:postcode":"MK44 3TF",
    "sg:province":"Bedfordshire",
    "sg:tags":[
        "holding"
    ],
    "wof:name":"Boardwalk Holding Ltd",
    "wof:placetype":"venue"
},
  "geometry": {"coordinates":[-0.415984,52.119404],"type":"Point"}
}