{
  "type": "Feature",
  "properties": {
    "addr:full":"198 Broom Road Teddington Greater London TW11 9PQ",
    "addr:housenumber":"198",
    "addr:postcode":"tw11 9pq",
    "addr:street":"Broom Road",
    "iso:country":"GB",
    "sg:address":"198 Broom Road",
    "sg:city":"Teddington",
    "sg:classifiers":[
        {
            "category":"Real Estate",
            "subcategory":"Architect",
            "type":"Services"
        }
    ],
    "sg:phone":"+44 20 8977 2068",
    "sg:postcode":"TW11 9PQ",
    "sg:province":"Greater London",
    "sg:tags":[
        "architectural"
    ],
    "wof:name":"Vernon Fray",
    "wof:placetype":"venue"
},
  "geometry": {"coordinates":[-0.312202,51.421951],"type":"Point"}
}