{
  "type": "Feature",
  "properties": {
    "addr:full":"43-45 High Street Warminster Somerset BA12 9AG",
    "addr:housenumber":"43-45",
    "addr:postcode":"ba12 9ag",
    "addr:street":"High Street",
    "iso:country":"GB",
    "sg:address":"43-45 High Street",
    "sg:city":"Warminster",
    "sg:classifiers":[
        {
            "category":"Shopping",
            "subcategory":"Discount & Variety Stores",
            "type":"Retail Goods"
        }
    ],
    "sg:phone":"+44 1985 847098",
    "sg:postcode":"BA12 9AG",
    "sg:province":"Somerset",
    "sg:tags":[
        "surplus"
    ],
    "wof:name":"H M Supplies",
    "wof:placetype":"venue"
},
  "geometry": {"coordinates":[-2.183493,51.205372],"type":"Point"}
}