{
  "type": "Feature",
  "properties": {
    "iso:country":"GB",
    "sg:address":"414 Harrow Road",
    "sg:city":"London",
    "sg:classifiers":[
        {
            "category":"Cafe",
            "type":"Food & Drink"
        }
    ],
    "sg:phone":"+44 20 7266 4224",
    "sg:postcode":"W9 2HU",
    "sg:province":"Greater London",
    "sg:tags":[
        "tea",
        "room"
    ],
    "wof:name":"Mimma Cafe",
    "wof:placetype":"venue"
},
  "geometry": {"coordinates":[-0.195939,51.52319],"type":"Point"}
}