{
  "type": "Feature",
  "properties": {
    "iso:country":"GB",
    "sg:address":"231 Hamstel Rd",
    "sg:city":"Southend-on-sea",
    "sg:classifiers":[
        {
            "category":"Shopping",
            "type":"Retail Goods"
        }
    ],
    "sg:postcode":"SS2 4LB",
    "sg:province":"Essex",
    "sg:tags":[
        "part",
        "accessory"
    ],
    "wof:name":"L & L Motor Spares",
    "wof:placetype":"venue"
},
  "geometry": {"coordinates":[0.7364420295,51.5477905273],"type":"Point"}
}