{
  "type": "Feature",
  "properties": {
    "iso:country":"GB",
    "sg:address":"Shernhall Street, Walthamstow",
    "sg:city":"London",
    "sg:classifiers":[
        {
            "category":"Place Of Worship",
            "type":"Public Place"
        }
    ],
    "sg:phone":"+44 20 8520 5877",
    "sg:postcode":"E17 9HU",
    "sg:province":"Greater London",
    "wof:name":"CATHOLIC PARISH OF OUR LADY & ST GEORGE",
    "wof:placetype":"venue"
},
  "geometry": {"coordinates":[-0.0080270004,51.5853118896],"type":"Point"}
}