{
  "type": "Feature",
  "properties": {
    "addr:full":"Sunnyside, Charleston, North Kessock Inverness Highland IV1 3YA",
    "addr:postcode":"iv1 3ya",
    "iso:country":"GB",
    "sg:address":"Sunnyside, Charleston, North Kessock",
    "sg:city":"Inverness",
    "sg:classifiers":[
        {
            "category":"Professional",
            "subcategory":"Engineering",
            "type":"Services"
        }
    ],
    "sg:postcode":"IV1 3YA",
    "sg:province":"Highland",
    "sg:tags":[
        "electronic",
        "engineer"
    ],
    "wof:name":"Schmidt Electronics",
    "wof:placetype":"venue"
},
  "geometry": {"coordinates":[-4.2624588013,57.5065155029],"type":"Point"}
}