{
  "type": "Feature",
  "properties": {
    "iso:country":"GB",
    "sg:address":"94-96 Water Lane",
    "sg:city":"Wilmslow",
    "sg:classifiers":[
        {
            "category":"Shopping",
            "subcategory":"Gifts & Souvenirs",
            "type":"Retail Goods"
        }
    ],
    "sg:phone":"+44 1625 529187",
    "sg:postcode":"SK9 5BB",
    "sg:province":"Cheshire",
    "sg:tags":[
        "shop"
    ],
    "wof:name":"House Shops Plc",
    "wof:placetype":"venue"
},
  "geometry": {"coordinates":[-2.236848,53.326733],"type":"Point"}
}