{
  "type": "Feature",
  "properties": {
    "iso:country":"GB",
    "sg:address":"Streatlam Grange, Dentgate Lane, Marwood",
    "sg:city":"Barnard Castle",
    "sg:classifiers":[
        {
            "category":"Farming",
            "subcategory":"Livestock Farm",
            "type":"Manufacturing & Wholesale Goods"
        }
    ],
    "sg:phone":"+44 1833 637344",
    "sg:postcode":"DL12 8RS",
    "sg:province":"Cumbria",
    "sg:tags":[
        "others"
    ],
    "wof:name":"Streatlam Grange",
    "wof:placetype":"venue"
},
  "geometry": {"coordinates":[-1.8864619732,54.5621757507],"type":"Point"}
}