{
  "type": "Feature",
  "properties": {
    "addr:full":"74-76 Station Rd Taunton Somerset TA1 1NX",
    "addr:housenumber":"74-76",
    "addr:postcode":"ta1 1nx",
    "addr:street":"Station Rd",
    "iso:country":"GB",
    "sg:address":"74-76 Station Rd",
    "sg:city":"Taunton",
    "sg:classifiers":[
        {
            "category":"Travel",
            "subcategory":"Hotels & Motels",
            "type":"Entertainment"
        },
        {
            "category":"Community Center",
            "subcategory":"Social",
            "type":"Public Place"
        }
    ],
    "sg:phone":"+44 1823 333384",
    "sg:postcode":"TA1 1NX",
    "sg:province":"Somerset",
    "sg:tags":[
        "house",
        "activity"
    ],
    "wof:name":"Crown & Sceptre Hotel",
    "wof:placetype":"venue"
},
  "geometry": {"coordinates":[-3.103523016,51.0208625793],"type":"Point"}
}