{
  "type": "Feature",
  "properties": {
    "iso:country":"GB",
    "sg:address":"55 Peach Street",
    "sg:city":"Wokingham",
    "sg:classifiers":[
        {
            "category":"Health Services",
            "subcategory":"Medical Lab",
            "type":"Services"
        },
        {
            "category":"Shopping",
            "subcategory":"Pharmacy",
            "type":"Retail Goods"
        }
    ],
    "sg:phone":"+44 118 978 2080",
    "sg:postcode":"RG40 1XP",
    "sg:province":"Berkshire",
    "sg:tags":[
        "medicine",
        "alternative",
        "therapy",
        "treatment"
    ],
    "wof:name":"SYNERGY HEALTH",
    "wof:placetype":"venue"
},
  "geometry": {"coordinates":[-0.830224,51.411064],"type":"Point"}
}