{
  "type": "Feature",
  "properties": {
    "addr:full":"84 High St Yarm North Yorkshire TS15 9AP",
    "addr:housenumber":"84",
    "addr:postcode":"ts15 9ap",
    "addr:street":"High St",
    "iso:country":"GB",
    "sg:address":"84 High St",
    "sg:city":"Yarm",
    "sg:classifiers":[
        {
            "category":"Shopping",
            "subcategory":"Used Merchandise",
            "type":"Retail Goods"
        }
    ],
    "sg:postcode":"TS15 9AP",
    "sg:province":"North Yorkshire",
    "sg:tags":[
        "shop",
        "second-hand"
    ],
    "wof:name":"Nearly New",
    "wof:placetype":"venue"
},
  "geometry": {"coordinates":[-1.3548029661,54.5102233887],"type":"Point"}
}