{
  "type": "Feature",
  "properties": {
    "addr:full":"Rutland Road Stoke-on-trent Staffordshire ST3 1EH",
    "addr:postcode":"st3 1eh",
    "addr:street":"Rutland Road",
    "iso:country":"GB",
    "sg:address":"Rutland Road",
    "sg:city":"Stoke-on-trent",
    "sg:classifiers":[
        {
            "category":"Professional",
            "subcategory":"Employment Agencies",
            "type":"Services"
        }
    ],
    "sg:phone":"+44 1782 297000",
    "sg:postcode":"ST3 1EH",
    "sg:province":"Staffordshire",
    "sg:tags":[
        "career",
        "guidance"
    ],
    "wof:name":"Longton Careers Centre",
    "wof:placetype":"venue"
},
  "geometry": {"coordinates":[-2.1346189976,52.9914131165],"type":"Point"}
}