{
  "type": "Feature",
  "properties": {
    "iso:country":"GB",
    "sg:address":"Unit 1 Station Yard",
    "sg:city":"Torrington",
    "sg:classifiers":[
        {
            "category":"Sports & Exercise",
            "subcategory":"Bicycle Rental",
            "type":"Entertainment"
        }
    ],
    "sg:phone":"+44 1805 622633",
    "sg:postcode":"EX38 8JD",
    "sg:province":"Devon",
    "sg:tags":[
        "renting",
        "cycle"
    ],
    "wof:name":"Torridge Cycle Hire",
    "wof:placetype":"venue"
},
  "geometry": {"coordinates":[-4.142255,50.953152],"type":"Point"}
}