{
  "type": "Feature",
  "properties": {
    "addr:full":"725 High Road Leyton London Greater London E10 5AB",
    "addr:housenumber":"725",
    "addr:postcode":"e10 5ab",
    "addr:street":"High Road",
    "iso:country":"GB",
    "sg:address":"725 High Road Leyton",
    "sg:city":"London",
    "sg:classifiers":[
        {
            "category":"Fast Food",
            "type":"Food & Drink"
        }
    ],
    "sg:phone":"+44 20 8556 0147",
    "sg:postcode":"E10 5AB",
    "sg:province":"Greater London",
    "sg:tags":[
        "away",
        "meal",
        "outlet",
        "take"
    ],
    "wof:name":"Mobeen Take Away",
    "wof:placetype":"venue"
},
  "geometry": {"coordinates":[-0.0086399997,51.5729408264],"type":"Point"}
}