{
  "type": "Feature",
  "properties": {
    "addr:full":"8 Northwood Park Road, Northwood Stoke-on-trent Staffordshire ST1 2DT",
    "addr:housenumber":"8",
    "addr:postcode":"staffordshire st1 2dt",
    "addr:street":"Northwood Park Road",
    "iso:country":"GB",
    "sg:address":"8 Northwood Park Road, Northwood",
    "sg:city":"Stoke-on-trent",
    "sg:classifiers":[
        {
            "category":"Professional",
            "subcategory":"Engineering",
            "type":"Services"
        }
    ],
    "sg:phone":"+44 1782 219970",
    "sg:postcode":"ST1 2DT",
    "sg:province":"Staffordshire",
    "sg:tags":[
        "contractor",
        "electrical",
        "engineer"
    ],
    "wof:name":"Harold Palfreyman Ltd.",
    "wof:placetype":"venue"
},
  "geometry": {"coordinates":[-2.1661419868,53.0298995972],"type":"Point"}
}