{
  "type": "Feature",
  "properties": {
    "iso:country":"GB",
    "sg:address":"49 Dalar Wen",
    "sg:city":"Denbigh",
    "sg:classifiers":[
        {
            "category":"Professional",
            "subcategory":"Art Services",
            "type":"Services"
        },
        {
            "category":"Shopping",
            "subcategory":"Photographic Equipment",
            "type":"Retail Goods"
        }
    ],
    "sg:phone":"+44 1745 814848",
    "sg:postcode":"LL16 3HT",
    "sg:province":"Conwy",
    "sg:tags":[
        "framing"
    ],
    "wof:name":"Pictures Galore",
    "wof:placetype":"venue"
},
  "geometry": {"coordinates":[-3.400947094,53.1885032654],"type":"Point"}
}