{
  "type": "Feature",
  "properties": {
    "iso:country":"GB",
    "sg:address":"4 Trinity Sq",
    "sg:city":"Llandudno",
    "sg:classifiers":[
        {
            "category":"Professional",
            "subcategory":"Management & Consulting",
            "type":"Services"
        }
    ],
    "sg:phone":"+44 70 0036 0540",
    "sg:postcode":"LL30 2PY",
    "sg:province":"Conwy",
    "sg:tags":[
        "sport"
    ],
    "wof:name":"Nimbus",
    "wof:placetype":"venue"
},
  "geometry": {"coordinates":[-3.826478,53.322178],"type":"Point"}
}