{
  "type": "Feature",
  "properties": {
    "addr:full":"64 Park Rd Brentwood Essex CM14 4TU",
    "addr:housenumber":"64",
    "addr:postcode":"cm14 4tu",
    "addr:street":"Park Rd",
    "iso:country":"GB",
    "sg:address":"64 Park Rd",
    "sg:city":"Brentwood",
    "sg:classifiers":[
        {
            "category":"Professional",
            "subcategory":"Advertising",
            "type":"Services"
        }
    ],
    "sg:phone":"+44 1277 232327",
    "sg:postcode":"CM14 4TU",
    "sg:province":"Essex",
    "sg:tags":[
        "agency"
    ],
    "wof:name":"Ad Infinitum",
    "wof:placetype":"venue"
},
  "geometry": {"coordinates":[0.2953360081,51.6221847534],"type":"Point"}
}