{
  "type": "Feature",
  "properties": {
    "addr:full":"70 West Avenue, Rudheath Northwich Cheshire CW9 7ES",
    "addr:housenumber":"70",
    "addr:postcode":"cw9 7es",
    "addr:street":"West Avenue",
    "iso:country":"GB",
    "sg:address":"70 West Avenue, Rudheath",
    "sg:city":"Northwich",
    "sg:classifiers":[
        {
            "category":"Shopping",
            "subcategory":"Stationery & Office Supplies",
            "type":"Retail Goods"
        },
        {
            "category":"Government",
            "subcategory":"Post Office",
            "type":"Public Place"
        }
    ],
    "sg:phone":"+44 1606 42723",
    "sg:postcode":"CW9 7ES",
    "sg:province":"Cheshire",
    "wof:name":"Rudheath Sub Post Office",
    "wof:placetype":"venue"
},
  "geometry": {"coordinates":[-2.483601,53.253132],"type":"Point"}
}