{
  "type": "Feature",
  "properties": {
    "addr:full":"South Rd Lerwick Shetland Islands ZE1 0RB",
    "addr:postcode":"ze1 0rb",
    "addr:street":"South Rd;Shetland",
    "iso:country":"GB",
    "sg:address":"South Rd",
    "sg:city":"Lerwick",
    "sg:classifiers":[
        {
            "category":"Health Services",
            "subcategory":"Hospital",
            "type":"Services"
        }
    ],
    "sg:phone":"+44 1595 743000",
    "sg:postcode":"ZE1 0RB",
    "sg:province":"Shetland Islands",
    "wof:name":"Gilbert Bain Hospital",
    "wof:placetype":"venue"
},
  "geometry": {"coordinates":[-1.152099,60.151619],"type":"Point"}
}