{
  "type": "Feature",
  "properties": {
    "iso:country":"GB",
    "sg:address":"56a Salop Road",
    "sg:city":"Oswestry",
    "sg:classifiers":[
        {
            "category":"Retail",
            "subcategory":"Repair Shop",
            "type":"Services"
        }
    ],
    "sg:postcode":"SY11 2RQ",
    "sg:province":"Shropshire",
    "sg:tags":[
        "upholsterer"
    ],
    "wof:name":"Day's Re-Upholsterey",
    "wof:placetype":"venue"
},
  "geometry": {"coordinates":[-3.051012,52.857201],"type":"Point"}
}