{
  "type": "Feature",
  "properties": {
    "iso:country":"GB",
    "sg:address":"139 Hulme Hall Road, Cheadle Hulme",
    "sg:city":"Cheadle",
    "sg:classifiers":[
        {
            "category":"Social Services",
            "subcategory":"Adult Care",
            "type":"Services"
        }
    ],
    "sg:phone":"+44 161 485 8947",
    "sg:postcode":"SK8 6LQ",
    "sg:province":"Cheshire",
    "sg:tags":[
        "housing",
        "sheltered"
    ],
    "wof:name":"Smithy Green Sheltered Housing",
    "wof:placetype":"venue"
},
  "geometry": {"coordinates":[-2.189987,53.366734],"type":"Point"}
}