{
  "type": "Feature",
  "properties": {
    "addr:full":"72 King Street Southall Greater London UB2 4DD",
    "addr:housenumber":"72",
    "addr:postcode":"ub2 4dd",
    "addr:street":"King Street",
    "iso:country":"GB",
    "sg:address":"72 King Street",
    "sg:city":"Southall",
    "sg:classifiers":[
        {
            "category":"Food & Beverages",
            "subcategory":"Meat & Fish",
            "type":"Retail Goods"
        }
    ],
    "sg:phone":"+44 20 8571 6771",
    "sg:postcode":"UB2 4DD",
    "sg:province":"Greater London",
    "sg:tags":[
        "butcher"
    ],
    "wof:name":"Baloch Halal Meat",
    "wof:placetype":"venue"
},
  "geometry": {"coordinates":[-0.383496,51.499706],"type":"Point"}
}