{
  "type": "Feature",
  "properties": {
    "addr:full":"103 Church Rd, Erdington Birmingham West Midlands B24 9BE",
    "addr:housenumber":"103",
    "addr:postcode":"b24 9be",
    "addr:street":"Church Rd",
    "iso:country":"GB",
    "sg:address":"103 Church Rd, Erdington",
    "sg:city":"Birmingham",
    "sg:classifiers":[
        {
            "category":"Shopping",
            "subcategory":"News",
            "type":"Retail Goods"
        }
    ],
    "sg:postcode":"B24 9BE",
    "sg:province":"West Midlands",
    "sg:tags":[
        "newsagent"
    ],
    "wof:name":"Islam,R M,",
    "wof:placetype":"venue"
},
  "geometry": {"coordinates":[-1.8363889456,52.5207099915],"type":"Point"}
}