{
  "type": "Feature",
  "properties": {
    "iso:country":"GB",
    "sg:address":"Scarth Rd, Sowerby Woods Ind Est",
    "sg:city":"Barrow In Furness",
    "sg:classifiers":[
        {
            "category":"Building & Trades",
            "subcategory":"Electrical",
            "type":"Services"
        }
    ],
    "sg:phone":"+44 1229 838797",
    "sg:postcode":"LA14 1RF",
    "sg:province":"Cumbria",
    "sg:tags":[
        "consultant",
        "lighting"
    ],
    "wof:name":"P & L Lighting",
    "wof:placetype":"venue"
},
  "geometry": {"coordinates":[-3.225847,54.111088],"type":"Point"}
}