{
  "type": "Feature",
  "properties": {
    "addr:full":"Great North Road, Stibbington Peterborough Cambridgeshire PE8 6LN",
    "addr:postcode":"pe8 6ln",
    "addr:street":"Great North Road Stibbington Peterborough",
    "iso:country":"GB",
    "sg:address":"Great North Road, Stibbington",
    "sg:city":"Peterborough",
    "sg:classifiers":[
        {
            "category":"Autos & Motor Vehicles",
            "subcategory":"Fuel & Gas Station",
            "type":"Retail Goods"
        }
    ],
    "sg:phone":"+44 1780 782006",
    "sg:postcode":"PE8 6LN",
    "sg:province":"Cambridgeshire",
    "sg:tags":[
        "petrol",
        "filling"
    ],
    "wof:name":"A1 Service Station",
    "wof:placetype":"venue"
},
  "geometry": {"coordinates":[-0.3993960023,52.5746269226],"type":"Point"}
}