{
  "type": "Feature",
  "properties": {
    "iso:country":"GB",
    "sg:address":"24 Cwrt Llwyn Fedwen, Morriston",
    "sg:city":"Swansea",
    "sg:classifiers":[
        {
            "category":"Building & Trades",
            "subcategory":"Construction",
            "type":"Services"
        }
    ],
    "sg:phone":"+44 1792 792143",
    "sg:postcode":"SA6 6HW",
    "sg:province":"Swansea",
    "sg:tags":[
        "supplier",
        "installers",
        "cladding"
    ],
    "wof:name":"Roofing & Cladding Services Ltd",
    "wof:placetype":"venue"
},
  "geometry": {"coordinates":[-3.9202001095,51.6688728333],"type":"Point"}
}