{
  "type": "Feature",
  "properties": {
    "iso:country":"GB",
    "sg:address":"255 Bog Green Lane, Bradley",
    "sg:city":"Huddersfield",
    "sg:classifiers":[
        {
            "category":"Transit Center",
            "subcategory":"Passenger",
            "type":"Transportation"
        }
    ],
    "sg:postcode":"HD5 0PS",
    "sg:province":"West Yorkshire",
    "sg:tags":[
        "boarding",
        "kennel",
        "catteries"
    ],
    "wof:name":"The Cattery",
    "wof:placetype":"venue"
},
  "geometry": {"coordinates":[-1.7292610407,53.6755371094],"type":"Point"}
}