{
  "type": "Feature",
  "properties": {
    "addr:full":"Redvers, The Green, Dunsfold Godalming Surrey GU8 4LY",
    "addr:postcode":"gu8 4ly",
    "addr:street":"The Green",
    "iso:country":"GB",
    "sg:address":"Redvers, The Green, Dunsfold",
    "sg:city":"Godalming",
    "sg:classifiers":[
        {
            "category":"Professional",
            "type":"Services"
        }
    ],
    "sg:phone":"+44 1483 200612",
    "sg:postcode":"GU8 4LY",
    "sg:province":"Surrey",
    "sg:tags":[
        "interior",
        "furnishers",
        "designer"
    ],
    "wof:name":"Belle Interiors",
    "wof:placetype":"venue"
},
  "geometry": {"coordinates":[-0.5627390146,51.1166038513],"type":"Point"}
}