{
  "type": "Feature",
  "properties": {
    "addr:full":"19 Station Road, Holme Peterborough Cambridgeshire PE7 3PH",
    "addr:housenumber":"19",
    "addr:postcode":"pe7 3ph",
    "addr:street":"Station Road",
    "iso:country":"GB",
    "sg:address":"19 Station Road, Holme",
    "sg:city":"Peterborough",
    "sg:classifiers":[
        {
            "category":"Professional",
            "subcategory":"Accounting & Tax Preparation",
            "type":"Services"
        }
    ],
    "sg:phone":"+44 1487 830759",
    "sg:postcode":"PE7 3PH",
    "sg:province":"Cambridgeshire",
    "sg:tags":[
        "accountant"
    ],
    "wof:name":"Bird & Co.",
    "wof:placetype":"venue"
},
  "geometry": {"coordinates":[-0.243993,52.473839],"type":"Point"}
}