{
  "type": "Feature",
  "properties": {
    "addr:full":"95 Union Road, Oswaldtwistle Accrington Lancashire BB5 3DD",
    "addr:housenumber":"95",
    "addr:postcode":"bb5 3dd",
    "addr:street":"Union Road;Accrington",
    "iso:country":"GB",
    "sg:address":"95 Union Road, Oswaldtwistle",
    "sg:city":"Accrington",
    "sg:classifiers":[
        {
            "category":"Taxi",
            "type":"Transportation"
        },
        {
            "category":"Military Area",
            "subcategory":"Air Force Base",
            "type":"Public Place"
        }
    ],
    "sg:phone":"+44 1254 234627",
    "sg:postcode":"BB5 3DD",
    "sg:province":"Lancashire",
    "sg:tags":[
        "mini",
        "hire",
        "private",
        "cab"
    ],
    "wof:name":"A X L TAXIS",
    "wof:placetype":"venue"
},
  "geometry": {"coordinates":[-2.392252,53.747272],"type":"Point"}
}