{
  "type": "Feature",
  "properties": {
    "addr:full":"3 High Street, Pateley Bridge Harrogate North Yorkshire HG3 5AP",
    "addr:housenumber":"3",
    "addr:postcode":"hg3 5ap",
    "addr:street":"High Street",
    "iso:country":"GB",
    "sg:address":"3 High Street, Pateley Bridge",
    "sg:city":"Harrogate",
    "sg:classifiers":[
        {
            "category":"Personal",
            "subcategory":"Beauty Salon",
            "type":"Services"
        },
        {
            "category":"Personal",
            "subcategory":"Barber",
            "type":"Services"
        }
    ],
    "sg:phone":"+44 1423 711423",
    "sg:postcode":"HG3 5AP",
    "sg:province":"North Yorkshire",
    "sg:tags":[
        "unisex",
        "hairdresser"
    ],
    "wof:name":"Sue's Hair Fashions",
    "wof:placetype":"venue"
},
  "geometry": {"coordinates":[-1.760731,54.085964],"type":"Point"}
}