{
  "type": "Feature",
  "properties": {
    "iso:country":"GB",
    "sg:address":"Balmuto West Lodge",
    "sg:city":"Kirkcaldy",
    "sg:classifiers":[
        {
            "category":"Transit Center",
            "subcategory":"Passenger",
            "type":"Transportation"
        },
        {
            "category":"Retail",
            "subcategory":"Pet Boarding",
            "type":"Services"
        }
    ],
    "sg:phone":"+44 1592 872379",
    "sg:postcode":"KY2 5XA",
    "sg:province":"Fife",
    "sg:tags":[
        "kennel",
        "catteries"
    ],
    "wof:name":"Puddledub Kennels",
    "wof:placetype":"venue"
},
  "geometry": {"coordinates":[-3.2605791092,56.1027908325],"type":"Point"}
}