{
  "type": "Feature",
  "properties": {
    "addr:full":"15 Chapel Lane, Old Sodbury Bristol Gloucestershire BS37 6NQ",
    "addr:housenumber":"15",
    "addr:postcode":"bs37 6nq",
    "addr:street":"Chapel Lane",
    "iso:country":"GB",
    "sg:address":"15 Chapel Lane, Old Sodbury",
    "sg:city":"Bristol",
    "sg:classifiers":[
        {
            "category":"Freight",
            "type":"Transportation"
        }
    ],
    "sg:phone":"+44 1454 325672",
    "sg:postcode":"BS37 6NQ",
    "sg:province":"Gloucestershire",
    "sg:tags":[
        "haulage",
        "road"
    ],
    "wof:name":"A & S Febry",
    "wof:placetype":"venue"
},
  "geometry": {"coordinates":[-2.357886,51.530563],"type":"Point"}
}