{
  "type": "Feature",
  "properties": {
    "addr:full":"131-141 King Street Ramsgate Kent CT11 8PN",
    "addr:housenumber":"131-141",
    "addr:postcode":"ct11 8pn",
    "addr:street":"King Street Ramsgate",
    "iso:country":"GB",
    "sg:address":"131-141 King Street",
    "sg:city":"Ramsgate",
    "sg:classifiers":[
        {
            "category":"Retail",
            "subcategory":"Auto Repair",
            "type":"Services"
        }
    ],
    "sg:postcode":"CT11 8PN",
    "sg:province":"Kent",
    "sg:tags":[
        "modification",
        "garage"
    ],
    "wof:name":"Kings Garage",
    "wof:placetype":"venue"
},
  "geometry": {"coordinates":[1.4225709438,51.3368797302],"type":"Point"}
}