{
  "type": "Feature",
  "properties": {
    "addr:full":"525 Newark Road, South Hykeham Lincoln Lincolnshire LN6 9NH",
    "addr:housenumber":"525",
    "addr:postcode":"ln6 9nh",
    "addr:street":"Newark Road South",
    "iso:country":"GB",
    "sg:address":"525 Newark Road, South Hykeham",
    "sg:city":"Lincoln",
    "sg:classifiers":[
        {
            "category":"Real Estate",
            "subcategory":"Architect",
            "type":"Services"
        }
    ],
    "sg:phone":"+44 1522 880237",
    "sg:postcode":"LN6 9NH",
    "sg:province":"Lincolnshire",
    "wof:name":"Piper Civil Engineering Ltd.",
    "wof:placetype":"venue"
},
  "geometry": {"coordinates":[-0.6183230281,53.1790428162],"type":"Point"}
}