{
  "type": "Feature",
  "properties": {
    "iso:country":"GB",
    "sg:address":"30 Kingsway Place",
    "sg:city":"Dundee",
    "sg:classifiers":[
        {
            "category":"Government",
            "subcategory":"Fire Station",
            "type":"Public Place"
        },
        {
            "category":"Home & Garden",
            "subcategory":"Building Materials",
            "type":"Retail Goods"
        }
    ],
    "sg:phone":"+44 1382 884545",
    "sg:postcode":"DD3 8JY",
    "sg:province":"Dundee City",
    "sg:tags":[
        "paint",
        "security",
        "manufacturer"
    ],
    "wof:name":"THERMOGUARD LTD",
    "wof:placetype":"venue"
},
  "geometry": {"coordinates":[-2.977358,56.482254],"type":"Point"}
}