{
  "type": "Feature",
  "properties": {
    "iso:country":"GB",
    "sg:address":"46 Ty-mawr Rd",
    "sg:city":"Cardiff",
    "sg:classifiers":[
        {
            "category":"Education",
            "subcategory":"Special Training",
            "type":"Public Place"
        }
    ],
    "sg:phone":"+44 29 2055 2348",
    "sg:postcode":"CF4 2FN",
    "sg:province":"Cardiff",
    "sg:tags":[
        "martial art",
        "instruction"
    ],
    "wof:name":"Hawthorn School Of Karate",
    "wof:placetype":"venue"
},
  "geometry": {"coordinates":[-3.131261,51.503544],"type":"Point"}
}