{
  "type": "Feature",
  "properties": {
    "addr:full":"1 Wordsworth Roda Leicester Leicestershire LE2 6BL",
    "addr:housenumber":"1",
    "addr:postcode":"le2 6bl",
    "iso:country":"GB",
    "sg:address":"1 Wordsworth Roda",
    "sg:city":"Leicester",
    "sg:classifiers":[
        {
            "category":"Banks & Credit Unions",
            "subcategory":"Financial Services",
            "type":"Services"
        }
    ],
    "sg:phone":"+44 116 270 3565",
    "sg:postcode":"LE2 6BL",
    "sg:province":"Leicestershire",
    "sg:tags":[
        "adviser"
    ],
    "wof:name":"Olsen & Co",
    "wof:placetype":"venue"
},
  "geometry": {"coordinates":[-1.123902,52.612049],"type":"Point"}
}