{
  "type": "Feature",
  "properties": {
    "iso:country":"GB",
    "sg:address":"20 Springfield Gardens",
    "sg:city":"Upminster",
    "sg:classifiers":[
        {
            "category":"Building & Trades",
            "subcategory":"Plumbing",
            "type":"Services"
        }
    ],
    "sg:phone":"+44 1708 224679",
    "sg:postcode":"RM14 3EJ",
    "sg:province":"Essex",
    "sg:tags":[
        "heating"
    ],
    "wof:name":"Plumbing & Heating Services",
    "wof:placetype":"venue"
},
  "geometry": {"coordinates":[0.250415,51.552822],"type":"Point"}
}