{
  "type": "Feature",
  "properties": {
    "iso:country":"GB",
    "sg:address":"9 Riley Square, Bell Green District Centre",
    "sg:city":"Coventry",
    "sg:classifiers":[
        {
            "category":"Shopping",
            "subcategory":"Pharmacy",
            "type":"Retail Goods"
        }
    ],
    "sg:phone":"+44 24 7668 7011",
    "sg:postcode":"CV2 1LS",
    "sg:province":"Warwickshire",
    "sg:tags":[
        "pharmacist",
        "dispensing",
        "chemist"
    ],
    "wof:name":"Lloyds Pharmacy Ltd",
    "wof:placetype":"venue"
},
  "geometry": {"coordinates":[-1.472324,52.43589],"type":"Point"}
}