{
  "type": "Feature",
  "properties": {
    "iso:country":"GB",
    "sg:address":"Gilmerton Estate",
    "sg:city":"North Berwick",
    "sg:classifiers":[
        {
            "category":"Professional",
            "subcategory":"Engineering",
            "type":"Services"
        }
    ],
    "sg:phone":"+44 1620 880351",
    "sg:postcode":"EH39 5LQ",
    "sg:province":"East Lothian",
    "sg:tags":[
        "precision",
        "engineer"
    ],
    "wof:name":"R Patterson Engineering",
    "wof:placetype":"venue"
},
  "geometry": {"coordinates":[-2.7269001007,55.9890518188],"type":"Point"}
}