{
  "type": "Feature",
  "properties": {
    "iso:country":"GB",
    "sg:address":"15 Market Place",
    "sg:city":"Coleford",
    "sg:classifiers":[
        {
            "category":"Food & Beverages",
            "subcategory":"Specialty",
            "type":"Retail Goods"
        }
    ],
    "sg:postcode":"GL16 8AW",
    "sg:province":"Gloucestershire",
    "sg:tags":[
        "product",
        "health"
    ],
    "wof:name":"Wyedean Wholefoods",
    "wof:placetype":"venue"
},
  "geometry": {"coordinates":[-2.616976,51.793869],"type":"Point"}
}