{
  "type": "Feature",
  "properties": {
    "addr:full":"40 Sandgate Ayr South Ayrshire KA7 1BX",
    "addr:housenumber":"40",
    "addr:postcode":"ka7 1bx",
    "addr:street":"Sandgate",
    "iso:country":"GB",
    "sg:address":"40 Sandgate",
    "sg:city":"Ayr",
    "sg:classifiers":[
        {
            "category":"Shopping",
            "subcategory":"Department Store",
            "type":"Retail Goods"
        },
        {
            "category":"Shopping",
            "subcategory":"Gifts & Souvenirs",
            "type":"Retail Goods"
        }
    ],
    "sg:postcode":"KA7 1BX",
    "sg:province":"South Ayrshire",
    "sg:tags":[
        "shop"
    ],
    "wof:name":"Ward,Frank,",
    "wof:placetype":"venue"
},
  "geometry": {"coordinates":[-4.6340517998,55.46301651],"type":"Point"}
}