{
  "type": "Feature",
  "properties": {
    "addr:full":"8-10 Market Pl Ulverston Cumbria LA12 7BA",
    "addr:housenumber":"8-10",
    "addr:postcode":"la12 7ba",
    "addr:street":"Market Pl",
    "iso:country":"GB",
    "sg:address":"8-10 Market Pl",
    "sg:city":"Ulverston",
    "sg:classifiers":[
        {
            "category":"Travel",
            "subcategory":"Travel Agent",
            "type":"Entertainment"
        }
    ],
    "sg:phone":"+44 1229 584448",
    "sg:postcode":"LA12 7BA",
    "sg:province":"Cumbria",
    "wof:name":"M T G (U K) Ltd",
    "wof:placetype":"venue"
},
  "geometry": {"coordinates":[-3.0962738991,54.1958808899],"type":"Point"}
}