{
  "type": "Feature",
  "properties": {
    "addr:full":"153 Ennerdale Road Newcastle-upon-tyne Tyne and Wear NE6 4DL",
    "addr:housenumber":"153",
    "addr:postcode":"ne6 4dl",
    "addr:street":"Ennerdale Road",
    "iso:country":"GB",
    "sg:address":"153 Ennerdale Road",
    "sg:city":"Newcastle-upon-tyne",
    "sg:classifiers":[
        {
            "category":"Building & Trades",
            "subcategory":"Construction",
            "type":"Services"
        }
    ],
    "sg:phone":"+44 191 234 2872",
    "sg:postcode":"NE6 4DL",
    "sg:province":"Tyne and Wear",
    "sg:tags":[
        "roofing"
    ],
    "wof:name":"Barfoot Roofing & Building",
    "wof:placetype":"venue"
},
  "geometry": {"coordinates":[-1.5451329947,54.979511261],"type":"Point"}
}