{
  "type": "Feature",
  "properties": {
    "iso:country":"GB",
    "sg:address":"61 Homely Walk, Datchet",
    "sg:city":"Slough",
    "sg:classifiers":[
        {
            "category":"Building & Trades",
            "subcategory":"Landscaping Services",
            "type":"Services"
        }
    ],
    "sg:postcode":"SL3 9EW",
    "sg:province":"Berkshire",
    "sg:tags":[
        "ladder",
        "loft"
    ],
    "wof:name":"Lofty Lofty Ladders",
    "wof:placetype":"venue"
},
  "geometry": {"coordinates":[-0.5804880261,51.4840736389],"type":"Point"}
}