{
  "type": "Feature",
  "properties": {
    "iso:country":"GB",
    "sg:address":"Tremont Road",
    "sg:city":"Llandrindod Wells",
    "sg:classifiers":[
        {
            "category":"Home & Garden",
            "subcategory":"Garden Supply",
            "type":"Retail Goods"
        },
        {
            "category":"Home & Garden",
            "subcategory":"Hardware",
            "type":"Retail Goods"
        }
    ],
    "sg:phone":"+44 1597 822259",
    "sg:postcode":"LD1 5BH",
    "sg:province":"Powys",
    "sg:tags":[
        "lawnmowers",
        "sales",
        "machinery"
    ],
    "wof:name":"John Davies Motor Services",
    "wof:placetype":"venue"
},
  "geometry": {"coordinates":[-3.372854948,52.2531967163],"type":"Point"}
}