{
  "type": "Feature",
  "properties": {
    "addr:full":"Church, Side Mansfield Nottinghamshire NG18 1AP",
    "addr:postcode":"ng18 1ap",
    "iso:country":"GB",
    "sg:address":"Church, Side",
    "sg:city":"Mansfield",
    "sg:classifiers":[
        {
            "category":"Community Center",
            "type":"Public Place"
        }
    ],
    "sg:phone":"+44 1623 428775",
    "sg:postcode":"NG18 1AP",
    "sg:province":"Nottinghamshire",
    "sg:tags":[
        "centre"
    ],
    "wof:name":"St. Peters Centre",
    "wof:placetype":"venue"
},
  "geometry": {"coordinates":[-1.193359971,53.1433563232],"type":"Point"}
}