{
  "type": "Feature",
  "properties": {
    "addr:full":"Penmenoth, Ruthern Bridge Bodmin Cornwall PL30 5LY",
    "addr:housenumber":"bodmin",
    "addr:postcode":"pl30 5ly",
    "addr:street":"Bridge",
    "iso:country":"GB",
    "sg:address":"Penmenoth, Ruthern Bridge",
    "sg:city":"Bodmin",
    "sg:classifiers":[
        {
            "category":"Professional",
            "subcategory":"Engineering",
            "type":"Services"
        }
    ],
    "sg:phone":"+44 1208 831771",
    "sg:postcode":"PL30 5LY",
    "sg:province":"Cornwall",
    "sg:tags":[
        "consulting",
        "design",
        "engineer"
    ],
    "wof:name":"J W Wood",
    "wof:placetype":"venue"
},
  "geometry": {"coordinates":[-4.795788765,50.4665336609],"type":"Point"}
}