{
  "type": "Feature",
  "properties": {
    "addr:full":"16 Boroughbridge Road York North Yorkshire YO26 5RU",
    "addr:housenumber":"16",
    "addr:postcode":"yo26 5ru",
    "addr:street":"Boroughbridge Road",
    "iso:country":"GB",
    "sg:address":"16 Boroughbridge Road",
    "sg:city":"York",
    "sg:classifiers":[
        {
            "category":"Retail",
            "subcategory":"Laundry & Dry Cleaning",
            "type":"Services"
        }
    ],
    "sg:phone":"+44 1904 783355",
    "sg:postcode":"YO26 5RU",
    "sg:province":"North Yorkshire",
    "sg:tags":[
        "launderette"
    ],
    "wof:name":"The Washing Well",
    "wof:placetype":"venue"
},
  "geometry": {"coordinates":[-1.116519,53.96312],"type":"Point"}
}