{
  "type": "Feature",
  "properties": {
    "iso:country":"GB",
    "sg:address":"1 Ivanhoe Street",
    "sg:city":"Leicester",
    "sg:classifiers":[
        {
            "category":"Food & Beverages",
            "subcategory":"Fruits & Vegetables",
            "type":"Retail Goods"
        }
    ],
    "sg:phone":"+44 116 233 9522",
    "sg:postcode":"LE3 9GX",
    "sg:province":"Leicestershire",
    "sg:tags":[
        "greengrocer"
    ],
    "wof:name":"J M Fruiters",
    "wof:placetype":"venue"
},
  "geometry": {"coordinates":[-1.155606,52.641045],"type":"Point"}
}