{
  "type": "Feature",
  "properties": {
    "iso:country":"GB",
    "sg:address":"113 Hanover Street",
    "sg:city":"Edinburgh",
    "sg:classifiers":[
        {
            "category":"Personal",
            "subcategory":"Beauty Salon",
            "type":"Services"
        },
        {
            "category":"Personal",
            "subcategory":"Barber",
            "type":"Services"
        }
    ],
    "sg:phone":"+44 131 226 4330",
    "sg:postcode":"EH2 1DJ",
    "sg:province":"City of Edinburgh",
    "sg:tags":[
        "unisex",
        "hairdresser"
    ],
    "wof:name":"Neil Grant",
    "wof:placetype":"venue"
},
  "geometry": {"coordinates":[-3.197659,55.954746],"type":"Point"}
}