{
  "type": "Feature",
  "properties": {
    "addr:full":"73 High Rd Seven Sisters Greater London N15 6DS",
    "addr:housenumber":"73",
    "addr:postcode":"n15 6ds",
    "addr:street":"High Rd",
    "iso:country":"GB",
    "sg:address":"73 High Rd",
    "sg:city":"Seven Sisters",
    "sg:classifiers":[
        {
            "category":"Arts & Performance",
            "subcategory":"Music",
            "type":"Entertainment"
        }
    ],
    "sg:phone":"+44 20 8802 5188",
    "sg:postcode":"N15 6DS",
    "sg:province":"Greater London",
    "sg:tags":[
        "mobile",
        "disco"
    ],
    "wof:name":"Patel Sales & Management",
    "wof:placetype":"venue"
},
  "geometry": {"coordinates":[-0.0731860027,51.5774421692],"type":"Point"}
}