{
  "type": "Feature",
  "properties": {
    "iso:country":"GB",
    "sg:address":"111 Nayland Road, Mile End",
    "sg:city":"Colchester",
    "sg:classifiers":[
        {
            "category":"Autos & Motor Vehicles",
            "subcategory":"Fuel & Gas Station",
            "type":"Retail Goods"
        }
    ],
    "sg:postcode":"CO4 5EW",
    "sg:province":"Essex",
    "sg:tags":[
        "petrol",
        "filling"
    ],
    "wof:name":"Colchester Auto Point",
    "wof:placetype":"venue"
},
  "geometry": {"coordinates":[0.8911629915,51.9150123596],"type":"Point"}
}