{
  "type": "Feature",
  "properties": {
    "addr:full":"1 Blacon Farm Cotts, Snitterfield Lane, Norton Lindsey Warwick Warwickshire CV35 8JJ",
    "addr:housenumber":"1;cotts",
    "addr:postcode":"cv35 8jj",
    "addr:street":"Blacon Farm;Snitterfield Lane",
    "iso:country":"GB",
    "sg:address":"1 Blacon Farm Cotts, Snitterfield Lane, Norton Lindsey",
    "sg:city":"Warwick",
    "sg:classifiers":[
        {
            "category":"Shopping",
            "subcategory":"Bicycles & Sporting Goods",
            "type":"Retail Goods"
        }
    ],
    "sg:phone":"+44 1789 730337",
    "sg:postcode":"CV35 8JJ",
    "sg:province":"Warwickshire",
    "sg:tags":[
        "cycle",
        "accessory"
    ],
    "wof:name":"H & A Jones",
    "wof:placetype":"venue"
},
  "geometry": {"coordinates":[-1.666894,52.265396],"type":"Point"}
}