{
  "type": "Feature",
  "properties": {
    "iso:country":"GB",
    "sg:address":"West Bridgford Probabtion Office, 9 Musters Rd",
    "sg:city":"Nottingham",
    "sg:classifiers":[
        {
            "category":"Government",
            "subcategory":"Office",
            "type":"Public Place"
        }
    ],
    "sg:phone":"+44 115 914 4333",
    "sg:postcode":"NG2 7PP",
    "sg:province":"Nottinghamshire",
    "sg:tags":[
        "central"
    ],
    "wof:name":"Probation Service",
    "wof:placetype":"venue"
},
  "geometry": {"coordinates":[-1.13287,52.935009],"type":"Point"}
}