{
  "type": "Feature",
  "properties": {
    "iso:country":"GB",
    "sg:address":"77 Plashet Rd",
    "sg:city":"London",
    "sg:classifiers":[
        {
            "category":"Shopping",
            "subcategory":"Mobile Phones",
            "type":"Retail Goods"
        }
    ],
    "sg:postcode":"E13 0RA",
    "sg:province":"Greater London",
    "wof:name":"C M S Telecommunications",
    "wof:placetype":"venue"
},
  "geometry": {"coordinates":[0.0267459992,51.5373573303],"type":"Point"}
}