{
  "type": "Feature",
  "properties": {
    "iso:country":"GB",
    "sg:address":"Rich View, Pipers Pool",
    "sg:city":"Launceston",
    "sg:classifiers":[
        {
            "category":"Autos & Motor Vehicles",
            "subcategory":"Automobile Sales",
            "type":"Retail Goods"
        }
    ],
    "sg:phone":"+44 1566 86618",
    "sg:postcode":"PL15 8QR",
    "sg:province":"Cornwall",
    "sg:tags":[
        "car"
    ],
    "wof:name":"R D C Car Sales",
    "wof:placetype":"venue"
},
  "geometry": {"coordinates":[-4.363344,50.636707],"type":"Point"}
}