{
  "type": "Feature",
  "properties": {
    "iso:country":"GB",
    "sg:address":"21 School Lane",
    "sg:city":"Cirencester",
    "sg:classifiers":[
        {
            "category":"Professional",
            "subcategory":"Art Services",
            "type":"Services"
        }
    ],
    "sg:postcode":"GL7 1JX",
    "sg:province":"Gloucestershire",
    "sg:tags":[
        "stone",
        "restoration",
        "cleaning"
    ],
    "wof:name":"Williams Summers",
    "wof:placetype":"venue"
},
  "geometry": {"coordinates":[-1.961772,51.708736],"type":"Point"}
}