{
  "type": "Feature",
  "properties": {
    "addr:full":"185 Penybank Road Ammanford Carmarthenshire SA18 3QP",
    "addr:housenumber":"185",
    "addr:postcode":"sa18 3qp",
    "addr:street":"Penybank Road",
    "iso:country":"GB",
    "sg:address":"185 Penybank Road",
    "sg:city":"Ammanford",
    "sg:classifiers":[
        {
            "category":"Government",
            "subcategory":"Post Office",
            "type":"Public Place"
        }
    ],
    "sg:postcode":"SA18 3QP",
    "sg:province":"Carmarthenshire",
    "wof:name":"Penybank Post Office",
    "wof:placetype":"venue"
},
  "geometry": {"coordinates":[-3.9889450073,51.7923965454],"type":"Point"}
}