{
  "type": "Feature",
  "properties": {
    "addr:full":"182 Monkmoor Road Shrewsbury Shropshire SY2 5BH",
    "addr:housenumber":"182",
    "addr:postcode":"sy2 5bh",
    "addr:street":"Monkmoor Road",
    "iso:country":"GB",
    "sg:address":"182 Monkmoor Road",
    "sg:city":"Shrewsbury",
    "sg:classifiers":[
        {
            "category":"Professional",
            "subcategory":"Business Services",
            "type":"Services"
        }
    ],
    "sg:phone":"+44 1743 236980",
    "sg:postcode":"SY2 5BH",
    "sg:province":"Shropshire",
    "sg:tags":[
        "tile",
        "stockist"
    ],
    "wof:name":"The Tile Shop",
    "wof:placetype":"venue"
},
  "geometry": {"coordinates":[-2.728088,52.716095],"type":"Point"}
}