{
  "type": "Feature",
  "properties": {
    "addr:full":"1 Richmond Avenue, Royton Oldham Lancashire OL2 5RH",
    "addr:housenumber":"1",
    "addr:postcode":"ol2 5rh",
    "addr:street":"Richmond Avenue",
    "iso:country":"GB",
    "sg:address":"1 Richmond Avenue, Royton",
    "sg:city":"Oldham",
    "sg:classifiers":[
        {
            "category":"Food & Beverages",
            "subcategory":"Liquor & Beverages",
            "type":"Retail Goods"
        }
    ],
    "sg:phone":"+44 161 624 7286",
    "sg:postcode":"OL2 5RH",
    "sg:province":"Lancashire",
    "sg:tags":[
        "beer",
        "spirit",
        "wines"
    ],
    "wof:name":"M J's",
    "wof:placetype":"venue"
},
  "geometry": {"coordinates":[-2.1270949841,53.568687439],"type":"Point"}
}