{
  "type": "Feature",
  "properties": {
    "addr:full":"2 Enfield Road Enfield Greater London EN2 7QS",
    "addr:housenumber":"2",
    "addr:postcode":"en2 7qs",
    "addr:street":"Enfield Road",
    "iso:country":"GB",
    "sg:address":"2 Enfield Road",
    "sg:city":"Enfield",
    "sg:classifiers":[
        {
            "category":"Bars & Pubs",
            "type":"Food & Drink"
        },
        {
            "category":"Community Center",
            "subcategory":"Social",
            "type":"Public Place"
        }
    ],
    "sg:phone":"+44 20 8363 1917",
    "sg:postcode":"EN2 7QS",
    "sg:province":"Greater London",
    "sg:tags":[
        "pubs",
        "house",
        "inn",
        "activity"
    ],
    "wof:name":"Jolly Farmers",
    "wof:placetype":"venue"
},
  "geometry": {"coordinates":[-0.1086070016,51.6548995972],"type":"Point"}
}