{
  "type": "Feature",
  "properties": {
    "iso:country":"GB",
    "sg:address":"10 Belvedere Crescent, Milton",
    "sg:city":"Weston-super-mare",
    "sg:classifiers":[
        {
            "category":"Manufacturing",
            "subcategory":"Petroleum Products",
            "type":"Manufacturing & Wholesale Goods"
        }
    ],
    "sg:postcode":"BS22 8EX",
    "sg:province":"Somerset",
    "sg:tags":[
        "double",
        "glazing"
    ],
    "wof:name":"Choice Property Services",
    "wof:placetype":"venue"
},
  "geometry": {"coordinates":[-2.9437589645,51.3546409607],"type":"Point"}
}