{
  "type": "Feature",
  "properties": {
    "iso:country":"GB",
    "sg:address":"Crowhill Farm, Pipwell Gate",
    "sg:city":"Spalding",
    "sg:classifiers":[
        {
            "category":"Professional",
            "subcategory":"Engineering",
            "type":"Services"
        },
        {
            "category":"Retail",
            "subcategory":"Repair Shop",
            "type":"Services"
        }
    ],
    "sg:phone":"+44 1406 426108",
    "sg:postcode":"PE12 8BA",
    "sg:province":"Cambridgeshire",
    "sg:tags":[
        "agricultural",
        "sale",
        "machinery"
    ],
    "wof:name":"A Woods Agricultural Engineers",
    "wof:placetype":"venue"
},
  "geometry": {"coordinates":[-0.0179600008,52.8254013062],"type":"Point"}
}