{
  "type": "Feature",
  "properties": {
    "addr:full":"28 Kingland Crescent Poole Dorset BH15 1TB",
    "addr:housenumber":"28",
    "addr:postcode":"bh15 1tb",
    "addr:street":"Kingland Crescent",
    "iso:country":"GB",
    "sg:address":"28 Kingland Crescent",
    "sg:city":"Poole",
    "sg:classifiers":[
        {
            "category":"Banks & Credit Unions",
            "subcategory":"Financial Services",
            "type":"Services"
        }
    ],
    "sg:phone":"+44 845 730 2010",
    "sg:postcode":"BH15 1TB",
    "sg:province":"Dorset",
    "sg:tags":[
        "building",
        "society"
    ],
    "wof:name":"Nationwide Building Society",
    "wof:placetype":"venue"
},
  "geometry": {"coordinates":[-1.97285,50.717293],"type":"Point"}
}