{
  "type": "Feature",
  "properties": {
    "addr:full":"60 Tradeston St Glasgow Glasgow City G5 8BH",
    "addr:housenumber":"60",
    "addr:postcode":"g5 8bh",
    "addr:street":"Tradeston St",
    "iso:country":"GB",
    "sg:address":"60 Tradeston St",
    "sg:city":"Glasgow",
    "sg:classifiers":[
        {
            "category":"Professional",
            "subcategory":"Art Services",
            "type":"Services"
        }
    ],
    "sg:phone":"+44 141 429 6320",
    "sg:postcode":"G5 8BH",
    "sg:province":"Glasgow City",
    "sg:tags":[
        "consultant",
        "design"
    ],
    "wof:name":"Id8 Design Associates",
    "wof:placetype":"venue"
},
  "geometry": {"coordinates":[-4.2635040283,55.8537712097],"type":"Point"}
}