{
  "type": "Feature",
  "properties": {
    "iso:country":"GB",
    "sg:address":"Unit 5 Riverside, Riverway Estate, Peasmarsh",
    "sg:city":"Guildford",
    "sg:classifiers":[
        {
            "category":"Manufacturing",
            "subcategory":"Wood Products",
            "type":"Manufacturing & Wholesale Goods"
        }
    ],
    "sg:phone":"+44 1483 306464",
    "sg:postcode":"GU3 1LZ",
    "sg:province":"Surrey",
    "sg:tags":[
        "packaging",
        "crate",
        "pallets"
    ],
    "wof:name":"Schofield Packaging Holdings Ltd.",
    "wof:placetype":"venue"
},
  "geometry": {"coordinates":[-0.5824790001,51.2091598511],"type":"Point"}
}