{
  "type": "Feature",
  "properties": {
    "iso:country":"GB",
    "sg:address":"Little Meadows, Bilsham Road",
    "sg:city":"Arundel",
    "sg:classifiers":[
        {
            "category":"Building & Trades",
            "subcategory":"Construction",
            "type":"Services"
        }
    ],
    "sg:phone":"+44 1243 585302",
    "sg:postcode":"BN18 0JY",
    "sg:province":"West Sussex",
    "sg:tags":[
        "fork",
        "lift",
        "truck"
    ],
    "wof:name":"Hyams Autolift",
    "wof:placetype":"venue"
},
  "geometry": {"coordinates":[-0.554589,50.854836],"type":"Point"}
}