{
  "type": "Feature",
  "properties": {
    "addr:full":"30 Cobbold Rd Willesden Greater London NW10 9SX",
    "addr:housenumber":"30",
    "addr:postcode":"nw10 9sx",
    "addr:street":"Cobbold Rd",
    "iso:country":"GB",
    "sg:address":"30 Cobbold Rd",
    "sg:city":"Willesden",
    "sg:classifiers":[
        {
            "category":"Building & Trades",
            "subcategory":"Plumbing",
            "type":"Services"
        }
    ],
    "sg:phone":"+44 20 8459 8984",
    "sg:postcode":"NW10 9SX",
    "sg:province":"Greater London",
    "sg:tags":[
        "central",
        "heating"
    ],
    "wof:name":"LMR Building Services",
    "wof:placetype":"venue"
},
  "geometry": {"coordinates":[-0.247279,51.546925],"type":"Point"}
}