{
  "type": "Feature",
  "properties": {
    "iso:country":"GB",
    "sg:address":"10 Tigers Rd",
    "sg:city":"Wigston",
    "sg:classifiers":[
        {
            "category":"Government",
            "subcategory":"Office",
            "type":"Public Place"
        }
    ],
    "sg:phone":"+44 116 278 5354",
    "sg:postcode":"LE18 4TN",
    "sg:province":"Leicestershire",
    "sg:tags":[
        "central"
    ],
    "wof:name":"Office & Gas Supply Technical Directorate",
    "wof:placetype":"venue"
},
  "geometry": {"coordinates":[-1.139707,52.583603],"type":"Point"}
}