{
  "type": "Feature",
  "properties": {
    "iso:country":"GB",
    "sg:address":"113 Union Street",
    "sg:city":"Oldham",
    "sg:classifiers":[
        {
            "category":"Real Estate",
            "subcategory":"Real Estate Agent",
            "type":"Services"
        }
    ],
    "sg:phone":"+44 161 652 3311",
    "sg:postcode":"OL1 1RU",
    "sg:province":"Lancashire",
    "wof:name":"Simpsons",
    "wof:placetype":"venue"
},
  "geometry": {"coordinates":[-2.108676,53.541103],"type":"Point"}
}