{
  "type": "Feature",
  "properties": {
    "iso:country":"GB",
    "sg:address":"42 Garswood Street, Ashton In Makerfield",
    "sg:city":"Wigan",
    "sg:classifiers":[
        {
            "category":"Shopping",
            "subcategory":"Department Store",
            "type":"Retail Goods"
        }
    ],
    "sg:postcode":"WN4 9AF",
    "sg:province":"Lancashire",
    "wof:name":"Jacksons Cards Ltd",
    "wof:placetype":"venue"
},
  "geometry": {"coordinates":[-2.638868,53.488018],"type":"Point"}
}