{
  "type": "Feature",
  "properties": {
    "addr:full":"12 Wannock Lane Eastbourne East Sussex BN20 9SB",
    "addr:housenumber":"12",
    "addr:postcode":"bn20 9sb",
    "addr:street":"Wannock Lane",
    "iso:country":"GB",
    "sg:address":"12 Wannock Lane",
    "sg:city":"Eastbourne",
    "sg:classifiers":[
        {
            "category":"Professional",
            "type":"Services"
        }
    ],
    "sg:postcode":"BN20 9SB",
    "sg:province":"East Sussex",
    "sg:tags":[
        "reflexologists"
    ],
    "wof:name":"Keith Sampson",
    "wof:placetype":"venue"
},
  "geometry": {"coordinates":[0.2467540056,50.8074493408],"type":"Point"}
}