{
  "type": "Feature",
  "properties": {
    "iso:country":"GB",
    "sg:address":"8 Charlse St",
    "sg:city":"Rotherham",
    "sg:classifiers":[
        {
            "category":"Home & Garden",
            "subcategory":"Building Materials",
            "type":"Retail Goods"
        }
    ],
    "sg:phone":"+44 1709 702167",
    "sg:postcode":"S66 9HQ",
    "sg:province":"South Yorkshire",
    "sg:tags":[
        "ironwork",
        "diy",
        "wrought"
    ],
    "wof:name":"P.P.S Fabrications",
    "wof:placetype":"venue"
},
  "geometry": {"coordinates":[-1.25993,53.395962],"type":"Point"}
}