{
  "type": "Feature",
  "properties": {
    "addr:full":"The Boat House, Canal Close London Greater London W10 5AY",
    "addr:housenumber":"house",
    "addr:postcode":"w10 5ay",
    "addr:street":"Canal Close",
    "iso:country":"GB",
    "sg:address":"The Boat House, Canal Close",
    "sg:city":"London",
    "sg:classifiers":[
        {
            "category":"Government",
            "subcategory":"Office",
            "type":"Public Place"
        }
    ],
    "sg:phone":"+44 20 7937 5464",
    "sg:postcode":"W10 5AY",
    "sg:province":"Greater London",
    "sg:tags":[
        "local"
    ],
    "wof:name":"Royal Borough of Kensington & Chelsea Sports Devel",
    "wof:placetype":"venue"
},
  "geometry": {"coordinates":[-0.2155179977,51.5261459351],"type":"Point"}
}