{
  "type": "Feature",
  "properties": {
    "iso:country":"GB",
    "sg:address":"67 Dulwich Road, Herne Hill",
    "sg:city":"London",
    "sg:classifiers":[
        {
            "category":"Communications",
            "subcategory":"Film & Video Production",
            "type":"Services"
        }
    ],
    "sg:postcode":"SE24 0NJ",
    "sg:province":"Greater London",
    "sg:tags":[
        "recording",
        "studio"
    ],
    "wof:name":"Sparkside Ltd.",
    "wof:placetype":"venue"
},
  "geometry": {"coordinates":[-0.1065630019,51.4538459778],"type":"Point"}
}