{
  "type": "Feature",
  "properties": {
    "iso:country":"GB",
    "sg:address":"Equity House, 11 Dawley Road, Arleston",
    "sg:city":"Telford",
    "sg:classifiers":[
        {
            "category":"Real Estate",
            "subcategory":"Architect",
            "type":"Services"
        }
    ],
    "sg:phone":"+44 1952 222663",
    "sg:postcode":"TF1 2HW",
    "sg:province":"Shropshire",
    "sg:tags":[
        "architectural"
    ],
    "wof:name":"Hayward Design & Build Ltd.",
    "wof:placetype":"venue"
},
  "geometry": {"coordinates":[-2.5050148964,52.6954574585],"type":"Point"}
}