{
  "type": "Feature",
  "properties": {
    "iso:country":"GB",
    "sg:address":"7 Spring Gro",
    "sg:city":"Harrogate",
    "sg:classifiers":[
        {
            "category":"Travel",
            "subcategory":"Hotels & Motels",
            "type":"Entertainment"
        }
    ],
    "sg:postcode":"HG1 2HS",
    "sg:province":"North Yorkshire",
    "sg:tags":[
        "house",
        "guest"
    ],
    "wof:name":"Ashwood House",
    "wof:placetype":"venue"
},
  "geometry": {"coordinates":[-1.543761,53.998196],"type":"Point"}
}