{
  "type": "Feature",
  "properties": {
    "addr:full":"The Surgery, Askew Gate Kirkby In Furness Cumbria LA17 7TE",
    "addr:postcode":"la17 7te",
    "addr:street":"Askew Gate",
    "iso:country":"GB",
    "sg:address":"The Surgery, Askew Gate",
    "sg:city":"Kirkby In Furness",
    "sg:classifiers":[
        {
            "category":"Health Services",
            "subcategory":"Doctor",
            "type":"Services"
        }
    ],
    "sg:phone":"+44 1229 889247",
    "sg:postcode":"LA17 7TE",
    "sg:province":"Cumbria",
    "sg:tags":[
        "practitioners"
    ],
    "wof:name":"Clayson, H",
    "wof:placetype":"venue"
},
  "geometry": {"coordinates":[-3.186103,54.232346],"type":"Point"}
}