{
  "type": "Feature",
  "properties": {
    "addr:full":"Aylestone Lane Wigston Leicestershire LE18 1BA",
    "addr:postcode":"le18 1ba",
    "addr:street":"Aylestone Lane",
    "iso:country":"GB",
    "sg:address":"Aylestone Lane",
    "sg:city":"Wigston",
    "sg:classifiers":[
        {
            "category":"Bars & Pubs",
            "type":"Food & Drink"
        }
    ],
    "sg:phone":"+44 116 288 4131",
    "sg:postcode":"LE18 1BA",
    "sg:province":"Leicestershire",
    "sg:tags":[
        "pubs",
        "inn"
    ],
    "wof:name":"The Nautical William",
    "wof:placetype":"venue"
},
  "geometry": {"coordinates":[-1.124764,52.592609],"type":"Point"}
}