{
  "type": "Feature",
  "properties": {
    "iso:country":"GB",
    "sg:address":"Hithercroft Road",
    "sg:city":"Wallingford",
    "sg:classifiers":[
        {
            "category":"Arena",
            "subcategory":"Sports Club",
            "type":"Entertainment"
        }
    ],
    "sg:phone":"+44 1491 835044",
    "sg:postcode":"OX10 9RB",
    "sg:province":"Oxfordshire",
    "wof:name":"Wallingford Sports Park",
    "wof:placetype":"venue"
},
  "geometry": {"coordinates":[-1.1410089731,51.5980529785],"type":"Point"}
}