{
  "type": "Feature",
  "properties": {
    "addr:full":"71 Merkland Drive, Kirkintilloch Glasgow East Dunbartonshire G66 3SJ",
    "addr:housenumber":"71",
    "addr:postcode":"g66 3sj",
    "addr:street":"Merkland Drive",
    "iso:country":"GB",
    "sg:address":"71 Merkland Drive, Kirkintilloch",
    "sg:city":"Glasgow",
    "sg:classifiers":[
        {
            "category":"Food & Beverages",
            "subcategory":"Bakery",
            "type":"Retail Goods"
        }
    ],
    "sg:phone":"+44 141 775 1661",
    "sg:postcode":"G66 3SJ",
    "sg:province":"East Dunbartonshire",
    "sg:tags":[
        "baker"
    ],
    "wof:name":"Peter's Bakery Ltd.",
    "wof:placetype":"venue"
},
  "geometry": {"coordinates":[-4.130613,55.94236],"type":"Point"}
}