{
  "type": "Feature",
  "properties": {
    "iso:country":"GB",
    "sg:address":"Birchwood Industrial Estate",
    "sg:city":"Waltham Abbey",
    "sg:classifiers":[
        {
            "category":"Communications",
            "subcategory":"Film & Video Production",
            "type":"Services"
        }
    ],
    "sg:postcode":"EN9 2RJ",
    "sg:province":"Essex",
    "sg:tags":[
        "hot",
        "stamping",
        "foil"
    ],
    "wof:name":"Shawe Metal Spinners Ltd.",
    "wof:placetype":"venue"
},
  "geometry": {"coordinates":[0.00149,51.68642],"type":"Point"}
}