{
  "type": "Feature",
  "properties": {
    "addr:full":"2 York Arcade Grangemouth Falkirk FK3 8BD",
    "addr:housenumber":"2",
    "addr:postcode":"fk3 8bd",
    "addr:street":"York Arcade",
    "iso:country":"GB",
    "sg:address":"2 York Arcade",
    "sg:city":"Grangemouth",
    "sg:classifiers":[
        {
            "category":"Shopping",
            "subcategory":"Baby Store",
            "type":"Retail Goods"
        }
    ],
    "sg:phone":"+44 1324 472244",
    "sg:postcode":"FK3 8BD",
    "sg:province":"Falkirk",
    "sg:tags":[
        "babywear",
        "childrens"
    ],
    "wof:name":"Ethel Austin Ltd.",
    "wof:placetype":"venue"
},
  "geometry": {"coordinates":[-3.7238938808,56.0093307495],"type":"Point"}
}