{
  "type": "Feature",
  "properties": {
    "iso:country":"GB",
    "sg:address":"3 Colvilles Road, East Kilbride",
    "sg:city":"Glasgow",
    "sg:classifiers":[
        {
            "category":"Education",
            "subcategory":"Special Training",
            "type":"Public Place"
        }
    ],
    "sg:phone":"+44 1355 222066",
    "sg:postcode":"G75 0RS",
    "sg:province":"South Lanarkshire",
    "sg:tags":[
        "diving",
        "school"
    ],
    "wof:name":"Cameron Bell",
    "wof:placetype":"venue"
},
  "geometry": {"coordinates":[-4.160222,55.748779],"type":"Point"}
}