{
  "type": "Feature",
  "properties": {
    "iso:country":"GB",
    "sg:address":"115 Heaton Moor Road",
    "sg:city":"Stockport",
    "sg:classifiers":[
        {
            "category":"Real Estate",
            "subcategory":"Real Estate Agent",
            "type":"Services"
        }
    ],
    "sg:phone":"+44 161 442 5518",
    "sg:postcode":"SK4 4HY",
    "sg:province":"Cheshire",
    "wof:name":"Bridgfords",
    "wof:placetype":"venue"
},
  "geometry": {"coordinates":[-2.188688,53.418224],"type":"Point"}
}