{
  "type": "Feature",
  "properties": {
    "iso:country":"GB",
    "sg:address":"4 Church Close",
    "sg:city":"Totteridge",
    "sg:classifiers":[
        {
            "category":"Shopping",
            "subcategory":"Books",
            "type":"Retail Goods"
        }
    ],
    "sg:phone":"+44 20 8368 4121",
    "sg:postcode":"N20 0JU",
    "sg:province":"Greater London",
    "wof:name":"Race Tech Magazine",
    "wof:placetype":"venue"
},
  "geometry": {"coordinates":[-0.1626289934,51.6233863831],"type":"Point"}
}