{
  "type": "Feature",
  "properties": {
    "addr:full":"Willowbank, 85 Chertsey La Staines Berkshire TW18 3LF",
    "addr:housenumber":"85",
    "addr:postcode":"tw18 3lf",
    "addr:street":"Willowbank",
    "iso:country":"GB",
    "sg:address":"Willowbank, 85 Chertsey La",
    "sg:city":"Staines",
    "sg:classifiers":[
        {
            "category":"Professional",
            "subcategory":"Engineering",
            "type":"Services"
        }
    ],
    "sg:phone":"+44 1784 465723",
    "sg:postcode":"TW18 3LF",
    "sg:province":"Berkshire",
    "sg:tags":[
        "contractor",
        "electrical",
        "engineer"
    ],
    "wof:name":"P S M Electrical Services",
    "wof:placetype":"venue"
},
  "geometry": {"coordinates":[-0.506604,51.435162],"type":"Point"}
}