{
  "type": "Feature",
  "properties": {
    "iso:country":"GB",
    "sg:address":"High Street",
    "sg:city":"Whitchurch",
    "sg:classifiers":[
        {
            "category":"Education",
            "subcategory":"Library",
            "type":"Public Place"
        }
    ],
    "sg:phone":"+44 1948 662238",
    "sg:postcode":"SY13 1AX",
    "sg:province":"Cheshire",
    "sg:tags":[
        "book"
    ],
    "wof:name":"Whitchurch Library",
    "wof:placetype":"venue"
},
  "geometry": {"coordinates":[-2.6846339703,52.9700050354],"type":"Point"}
}