{
  "type": "Feature",
  "properties": {
    "addr:full":"Lind House, 86 Lind Road Sutton Surrey SM1 4PL",
    "addr:housenumber":"86",
    "addr:postcode":"sm1 4pl",
    "addr:street":"Lind Road",
    "iso:country":"GB",
    "sg:address":"Lind House, 86 Lind Road",
    "sg:city":"Sutton",
    "sg:classifiers":[
        {
            "category":"Real Estate",
            "subcategory":"Developer",
            "type":"Services"
        }
    ],
    "sg:postcode":"SM1 4PL",
    "sg:province":"Surrey",
    "sg:tags":[
        "property"
    ],
    "wof:name":"Sealton Ltd",
    "wof:placetype":"venue"
},
  "geometry": {"coordinates":[-0.185848,51.365231],"type":"Point"}
}