{
  "type": "Feature",
  "properties": {
    "addr:full":"6 Newington Road Edinburgh City of Edinburgh EH9 1QS",
    "addr:housenumber":"6",
    "addr:postcode":"eh9 1qs",
    "addr:street":"Newington Road",
    "iso:country":"GB",
    "sg:address":"6 Newington Road",
    "sg:city":"Edinburgh",
    "sg:classifiers":[
        {
            "category":"Fast Food",
            "type":"Food & Drink"
        }
    ],
    "sg:phone":"+44 131 667 8405",
    "sg:postcode":"EH9 1QS",
    "sg:province":"City of Edinburgh",
    "sg:tags":[
        "away",
        "take"
    ],
    "wof:name":"Goodwill Chinese Takeaway",
    "wof:placetype":"venue"
},
  "geometry": {"coordinates":[-3.179582119,55.9388961792],"type":"Point"}
}