{
  "type": "Feature",
  "properties": {
    "addr:full":"Trinity House, Heather Park Drive Wembley Greater London HA0 1SU",
    "addr:postcode":"ha0 1su",
    "addr:street":"Heather Park Drive",
    "iso:country":"GB",
    "sg:address":"Trinity House, Heather Park Drive",
    "sg:city":"Wembley",
    "sg:classifiers":[
        {
            "category":"Professional",
            "subcategory":"Computer Services",
            "type":"Services"
        }
    ],
    "sg:postcode":"HA0 1SU",
    "sg:province":"Greater London",
    "sg:tags":[
        "system",
        "software"
    ],
    "wof:name":"Geoline Ltd",
    "wof:placetype":"venue"
},
  "geometry": {"coordinates":[-0.282949,51.543411],"type":"Point"}
}