{
  "type": "Feature",
  "properties": {
    "addr:full":"Fatfield Rd Washington Durham NE38 7DE",
    "addr:postcode":"ne38 7de",
    "addr:street":"Fatfield Rd",
    "iso:country":"GB",
    "sg:address":"Fatfield Rd",
    "sg:city":"Washington",
    "sg:classifiers":[
        {
            "category":"Place Of Worship",
            "type":"Public Place"
        }
    ],
    "sg:phone":"+44 191 416 3382",
    "sg:postcode":"NE38 7DE",
    "sg:province":"Durham",
    "wof:name":"Glebe Methodist Church",
    "wof:placetype":"venue"
},
  "geometry": {"coordinates":[-1.51728,54.898079],"type":"Point"}
}