{
  "type": "Feature",
  "properties": {
    "addr:full":"Best Place, 4 Bouverie Street London Greater London EC4Y 8AX",
    "addr:housenumber":"4",
    "addr:postcode":"ec4y 8ax",
    "addr:street":"Best;Bouverie Street",
    "iso:country":"GB",
    "sg:address":"Best Place, 4 Bouverie Street",
    "sg:city":"London",
    "sg:classifiers":[
        {
            "category":"Professional",
            "subcategory":"Employment Agencies",
            "type":"Services"
        }
    ],
    "sg:postcode":"EC4Y 8AX",
    "sg:province":"Greater London",
    "sg:tags":[
        "consultant"
    ],
    "wof:name":"Spring Technology Staffing Services Ltd.",
    "wof:placetype":"venue"
},
  "geometry": {"coordinates":[-0.10813,51.513988],"type":"Point"}
}