{
  "type": "Feature",
  "properties": {
    "iso:country":"GB",
    "sg:address":"Best Place, 4 Bouverie Street",
    "sg:city":"London",
    "sg:classifiers":[
        {
            "category":"Professional",
            "subcategory":"Employment Agencies",
            "type":"Services"
        }
    ],
    "sg:postcode":"EC4Y 8AX",
    "sg:province":"Greater London",
    "sg:tags":[
        "consultant"
    ],
    "wof:name":"Spring Technology Staffing Services Ltd.",
    "wof:placetype":"venue"
},
  "geometry": {"coordinates":[-0.10813,51.513988],"type":"Point"}
}