{
  "type": "Feature",
  "properties": {
    "addr:full":"71 Wolsely House, Dunn Terrace Newcastle-upon-tyne Tyne and Wear NE6 1DA",
    "addr:housenumber":"71",
    "addr:postcode":"ne6 1da",
    "addr:street":"Wolsely;Dunn Terrace",
    "iso:country":"GB",
    "sg:address":"71 Wolsely House, Dunn Terrace",
    "sg:city":"Newcastle-upon-tyne",
    "sg:classifiers":[
        {
            "category":"Organizations",
            "subcategory":"Non-profit Organization",
            "type":"Services"
        }
    ],
    "sg:phone":"+44 191 276 6052",
    "sg:postcode":"NE6 1DA",
    "sg:province":"Tyne and Wear",
    "sg:tags":[
        "organisation",
        "voluntary",
        "charity"
    ],
    "wof:name":"Y M C A",
    "wof:placetype":"venue"
},
  "geometry": {"coordinates":[-1.58427,54.974869],"type":"Point"}
}