{
  "type": "Feature",
  "properties": {
    "addr:full":"Mayflower House, Fifth Avenue, Team Valley Trading Estate Gateshead Tyne and Wear NE11 0HF",
    "addr:postcode":"ne11 0hf",
    "addr:street":"Fifth Avenue Team",
    "iso:country":"GB",
    "sg:address":"Mayflower House, Fifth Avenue, Team Valley Trading Estate",
    "sg:city":"Gateshead",
    "sg:classifiers":[
        {
            "category":"Insurance",
            "subcategory":"Insurance Agent",
            "type":"Services"
        }
    ],
    "sg:phone":"+44 191 491 1666",
    "sg:postcode":"NE11 0HF",
    "sg:province":"Tyne and Wear",
    "wof:name":"Norwich Union Life & Pensions Ltd.",
    "wof:placetype":"venue"
},
  "geometry": {"coordinates":[-1.613705,54.935558],"type":"Point"}
}