{
  "type": "Feature",
  "properties": {
    "addr:full":"2 Perry Way Farnham Surrey GU9 0EU",
    "addr:housenumber":"2",
    "addr:postcode":"gu9 0eu",
    "addr:street":"Perry Way",
    "iso:country":"GB",
    "sg:address":"2 Perry Way",
    "sg:city":"Farnham",
    "sg:classifiers":[
        {
            "category":"Shopping",
            "subcategory":"News",
            "type":"Retail Goods"
        }
    ],
    "sg:postcode":"GU9 0EU",
    "sg:province":"Surrey",
    "sg:tags":[
        "newsagent"
    ],
    "wof:name":"Sandy Hill Stores",
    "wof:placetype":"venue"
},
  "geometry": {"coordinates":[-0.8008369803,51.2143211365],"type":"Point"}
}