{
  "type": "Feature",
  "properties": {
    "iso:country":"GB",
    "sg:address":"Schneider Road",
    "sg:city":"Barrow-in-furness",
    "sg:classifiers":[
        {
            "category":"Education",
            "subcategory":"School",
            "type":"Public Place"
        }
    ],
    "sg:phone":"+44 1229 894651",
    "sg:postcode":"LA14 4AA",
    "sg:province":"Cumbria",
    "sg:tags":[
        "local",
        "authority"
    ],
    "wof:name":"St Pius X R C Primary School",
    "wof:placetype":"venue"
},
  "geometry": {"coordinates":[-3.2337989807,54.1322555542],"type":"Point"}
}