{
  "type": "Feature",
  "properties": {
    "addr:full":"Rhydydefaid, Trefor Holyhead Isle of Anglesey LL65 3YP",
    "addr:postcode":"ll65 3yp",
    "addr:street":"Rhydydefaid",
    "iso:country":"GB",
    "sg:address":"Rhydydefaid, Trefor",
    "sg:city":"Holyhead",
    "sg:classifiers":[
        {
            "category":"Farming",
            "subcategory":"Livestock Farm",
            "type":"Manufacturing & Wholesale Goods"
        }
    ],
    "sg:postcode":"LL65 3YP",
    "sg:province":"Isle of Anglesey",
    "sg:tags":[
        "others"
    ],
    "wof:name":"D B Owen",
    "wof:placetype":"venue"
},
  "geometry": {"coordinates":[-4.439685,53.29216],"type":"Point"}
}