{
  "type": "Feature",
  "properties": {
    "addr:full":"21 Broadwater Down Tunbridge Wells East Sussex TN2 5NL",
    "addr:housenumber":"21",
    "addr:postcode":"tn2 5nl",
    "addr:street":"Broadwater Down Tunbridge Wells",
    "iso:country":"GB",
    "sg:address":"21 Broadwater Down",
    "sg:city":"Tunbridge Wells",
    "sg:classifiers":[
        {
            "category":"Health Services",
            "subcategory":"Health Practitioner",
            "type":"Services"
        }
    ],
    "sg:phone":"+44 1580 212775",
    "sg:postcode":"TN2 5NL",
    "sg:province":"East Sussex",
    "sg:tags":[
        "homoeopathic",
        "homeopathic"
    ],
    "wof:name":"Sarah North",
    "wof:placetype":"venue"
},
  "geometry": {"coordinates":[0.255805999,51.1177482605],"type":"Point"}
}