{
  "type": "Feature",
  "properties": {
    "iso:country":"GB",
    "sg:address":"Station Yard, Harmby Road",
    "sg:city":"Leyburn",
    "sg:classifiers":[
        {
            "category":"Utilities",
            "subcategory":"Fuel Oil & Lpg",
            "type":"Services"
        }
    ],
    "sg:phone":"+44 1969 622234",
    "sg:postcode":"DL10 7NL",
    "sg:province":"North Yorkshire",
    "sg:tags":[
        "coal",
        "smokeless"
    ],
    "wof:name":"R A Metcalfe Solid Fuels",
    "wof:placetype":"venue"
},
  "geometry": {"coordinates":[-1.62978,54.37331],"type":"Point"}
}