{
  "type": "Feature",
  "properties": {
    "iso:country":"GB",
    "sg:address":"24 New Endrick Road, Killearn",
    "sg:city":"Glasgow",
    "sg:classifiers":[
        {
            "category":"Health Services",
            "subcategory":"Nursing And Care Facility",
            "type":"Services"
        }
    ],
    "sg:phone":"+44 1360 550558",
    "sg:postcode":"G63 9QT",
    "sg:province":"Argyll and Bute",
    "sg:tags":[
        "agency"
    ],
    "wof:name":"Endrick Homecare",
    "wof:placetype":"venue"
},
  "geometry": {"coordinates":[-4.379328,56.041931],"type":"Point"}
}