{
  "type": "Feature",
  "properties": {
    "iso:country":"GB",
    "sg:address":"5 West Avenue",
    "sg:city":"Barrow-in-furness",
    "sg:classifiers":[
        {
            "category":"Personal",
            "type":"Services"
        }
    ],
    "sg:postcode":"LA13 9AX",
    "sg:province":"Cumbria",
    "sg:tags":[
        "wedding"
    ],
    "wof:name":"Walmsley's Wedding Cars",
    "wof:placetype":"venue"
},
  "geometry": {"coordinates":[-3.217511,54.120487],"type":"Point"}
}