{
  "type": "Feature",
  "properties": {
    "addr:full":"19 Quay Road Blyth Northumberland NE24 2AR",
    "addr:housenumber":"19",
    "addr:postcode":"ne24 2ar",
    "addr:street":"Quay Road;Northumberland",
    "iso:country":"GB",
    "sg:address":"19 Quay Road",
    "sg:city":"Blyth",
    "sg:classifiers":[
        {
            "category":"Manufacturing",
            "subcategory":"Metals",
            "type":"Manufacturing & Wholesale Goods"
        }
    ],
    "sg:phone":"+44 1670 352185",
    "sg:postcode":"NE24 2AR",
    "sg:province":"Northumberland",
    "sg:tags":[
        "steel",
        "fabricator",
        "erectors"
    ],
    "wof:name":"J Smith & Sons",
    "wof:placetype":"venue"
},
  "geometry": {"coordinates":[-1.5042699575,55.1284751892],"type":"Point"}
}