{
  "type": "Feature",
  "properties": {
    "iso:country":"GB",
    "sg:address":"100 Stroud Green Rd",
    "sg:city":"London",
    "sg:classifiers":[
        {
            "category":"Travel",
            "subcategory":"Travel Agent",
            "type":"Entertainment"
        }
    ],
    "sg:phone":"+44 20 7263 5422",
    "sg:postcode":"N4 3EN",
    "sg:province":"Greater London",
    "wof:name":"Orbit Travel Ltd",
    "wof:placetype":"venue"
},
  "geometry": {"coordinates":[-0.110306,51.568554],"type":"Point"}
}