{
  "type": "Feature",
  "properties": {
    "addr:full":"Hunscot House, Abingdon Rd, Sutton Courtenay Abingdon Oxfordshire OX14 4NF",
    "addr:postcode":"ox14 4nf",
    "addr:street":"Abingdon Rd",
    "iso:country":"GB",
    "sg:address":"Hunscot House, Abingdon Rd, Sutton Courtenay",
    "sg:city":"Abingdon",
    "sg:classifiers":[
        {
            "category":"Banks & Credit Unions",
            "subcategory":"Financial Services",
            "type":"Services"
        }
    ],
    "sg:phone":"+44 1235 848866",
    "sg:postcode":"OX14 4NF",
    "sg:province":"Oxfordshire",
    "sg:tags":[
        "adviser"
    ],
    "wof:name":"Mark Jenner Independent Financial Adviser",
    "wof:placetype":"venue"
},
  "geometry": {"coordinates":[-1.310384,51.649155],"type":"Point"}
}