{
  "type": "Feature",
  "properties": {
    "iso:country":"GB",
    "sg:address":"Hut Grn, Selby Road, Eggborough",
    "sg:city":"Goole",
    "sg:classifiers":[
        {
            "category":"Manufacturing",
            "subcategory":"Building Materials",
            "type":"Manufacturing & Wholesale Goods"
        }
    ],
    "sg:postcode":"DN14 0LD",
    "sg:province":"East Riding of Yorkshire",
    "sg:tags":[
        "merchant",
        "builder"
    ],
    "wof:name":"Pawlett Builders Merchants",
    "wof:placetype":"venue"
},
  "geometry": {"coordinates":[-1.153777,53.706345],"type":"Point"}
}