{
  "type": "Feature",
  "properties": {
    "addr:full":"Unit 33 Charter Market Barnsley South Yorkshire S70 1SY",
    "addr:housenumber":"unit 33 charter market",
    "addr:postcode":"s70 1sy",
    "addr:street":"Yorkshire",
    "iso:country":"GB",
    "sg:address":"Unit 33 Charter Market",
    "sg:city":"Barnsley",
    "sg:classifiers":[
        {
            "category":"Food & Beverages",
            "subcategory":"Fruits & Vegetables",
            "type":"Retail Goods"
        }
    ],
    "sg:phone":"+44 1226 779600",
    "sg:postcode":"S70 1SY",
    "sg:province":"South Yorkshire",
    "sg:tags":[
        "greengrocer"
    ],
    "wof:name":"S Bedford",
    "wof:placetype":"venue"
},
  "geometry": {"coordinates":[-1.4847379923,53.5531921387],"type":"Point"}
}