{
  "type": "Feature",
  "properties": {
    "iso:country":"GB",
    "sg:address":"40 Grt Russell Street",
    "sg:city":"London",
    "sg:classifiers":[
        {
            "category":"Travel",
            "subcategory":"Travel Agent",
            "type":"Entertainment"
        }
    ],
    "sg:phone":"+44 20 7436 3223",
    "sg:postcode":"WC1B 3PH",
    "sg:province":"Greater London",
    "wof:name":"4th Dimension Travel Ltd.",
    "wof:placetype":"venue"
},
  "geometry": {"coordinates":[-0.126902,51.517872],"type":"Point"}
}