{
  "type": "Feature",
  "properties": {
    "addr:full":"Barn Works, Wick Street Littlehampton West Sussex BN17 7JH",
    "addr:postcode":"bn17 7jh",
    "addr:street":"Wick Street",
    "iso:country":"GB",
    "sg:address":"Barn Works, Wick Street",
    "sg:city":"Littlehampton",
    "sg:classifiers":[
        {
            "category":"Wholesale",
            "subcategory":"Scrap",
            "type":"Manufacturing & Wholesale Goods"
        }
    ],
    "sg:postcode":"BN17 7JH",
    "sg:province":"West Sussex",
    "sg:tags":[
        "waste",
        "metal"
    ],
    "wof:name":"H D White",
    "wof:placetype":"venue"
},
  "geometry": {"coordinates":[-0.5389590263,50.8210296631],"type":"Point"}
}