{
  "type": "Feature",
  "properties": {
    "iso:country":"GB",
    "sg:address":"39 Marischal Street",
    "sg:city":"Peterhead",
    "sg:classifiers":[
        {
            "category":"Shopping",
            "subcategory":"Computers & Home Electronics",
            "type":"Retail Goods"
        },
        {
            "category":"Communications",
            "type":"Services"
        }
    ],
    "sg:phone":"+44 1779 475331",
    "sg:postcode":"AB42 1BS",
    "sg:province":"Aberdeenshire",
    "sg:tags":[
        "tv",
        "radio",
        "television",
        "video",
        "sale"
    ],
    "wof:name":"Walter D Allan Ltd",
    "wof:placetype":"venue"
},
  "geometry": {"coordinates":[-1.7763580084,57.5050926208],"type":"Point"}
}