{
  "type": "Feature",
  "properties": {
    "iso:country":"GB",
    "sg:address":"1 Mary Street",
    "sg:city":"Sunderland",
    "sg:classifiers":[
        {
            "category":"Banks & Credit Unions",
            "subcategory":"Financial Services",
            "type":"Services"
        }
    ],
    "sg:phone":"+44 191 565 8161",
    "sg:postcode":"SR1 3NH",
    "sg:province":"Tyne and Wear",
    "sg:tags":[
        "consultant"
    ],
    "wof:name":"Olive Street Finance",
    "wof:placetype":"venue"
},
  "geometry": {"coordinates":[-1.38684,54.902863],"type":"Point"}
}