{
  "type": "Feature",
  "properties": {
    "addr:full":"6 Shenley Grove Maidstone Kent ME14 3BP",
    "addr:housenumber":"6",
    "addr:postcode":"me14 3bp",
    "addr:street":"Shenley Grove",
    "iso:country":"GB",
    "sg:address":"6 Shenley Grove",
    "sg:city":"Maidstone",
    "sg:classifiers":[
        {
            "category":"Professional",
            "subcategory":"Business Services",
            "type":"Services"
        }
    ],
    "sg:phone":"+44 1622 675789",
    "sg:postcode":"ME14 3BP",
    "sg:province":"Kent",
    "wof:name":"The Work Place",
    "wof:placetype":"venue"
},
  "geometry": {"coordinates":[0.518185,51.302483],"type":"Point"}
}