{
  "type": "Feature",
  "properties": {
    "iso:country":"GB",
    "sg:address":"7 Knowsley Road West",
    "sg:city":"Blackburn",
    "sg:classifiers":[
        {
            "category":"Organizations",
            "subcategory":"Non-profit Organization",
            "type":"Services"
        }
    ],
    "sg:phone":"+44 1254 248966",
    "sg:postcode":"BB1 9PW",
    "sg:province":"Lancashire",
    "sg:tags":[
        "organisation",
        "voluntary",
        "charity"
    ],
    "wof:name":"Friends of Chernobyl's & Children",
    "wof:placetype":"venue"
},
  "geometry": {"coordinates":[-2.477761,53.782265],"type":"Point"}
}