{
  "type": "Feature",
  "properties": {
    "addr:full":"2 Gunnersbury Cres, Acton London Greater London W3 9AA",
    "addr:housenumber":"2",
    "addr:postcode":"w3 9aa",
    "addr:street":"Gunnersbury Cres",
    "iso:country":"GB",
    "sg:address":"2 Gunnersbury Cres, Acton",
    "sg:city":"London",
    "sg:classifiers":[
        {
            "category":"Personal",
            "subcategory":"Beauty Salon",
            "type":"Services"
        }
    ],
    "sg:postcode":"W3 9AA",
    "sg:province":"Greater London",
    "wof:name":"Ageless",
    "wof:placetype":"venue"
},
  "geometry": {"coordinates":[-0.283108,51.502415],"type":"Point"}
}