{
  "type": "Feature",
  "properties": {
    "iso:country":"GB",
    "sg:address":"Unit 8 Cunninghame Road, Irvine Industrial Estate",
    "sg:city":"Irvine",
    "sg:classifiers":[
        {
            "category":"Professional",
            "subcategory":"Engineering",
            "type":"Services"
        }
    ],
    "sg:phone":"+44 1294 311595",
    "sg:postcode":"KA12 8JJ",
    "sg:province":"North Ayrshire",
    "wof:name":"Maintenance Services (Irvine)",
    "wof:placetype":"venue"
},
  "geometry": {"coordinates":[-4.672416,55.602608],"type":"Point"}
}