{
  "type": "Feature",
  "properties": {
    "iso:country":"GB",
    "sg:address":"Helks Bank Farm, Wray",
    "sg:city":"Lancaster",
    "sg:classifiers":[
        {
            "category":"Farming",
            "subcategory":"Farm",
            "type":"Manufacturing & Wholesale Goods"
        }
    ],
    "sg:phone":"+44 15242 61307",
    "sg:postcode":"LA2 8QX",
    "sg:province":"Lancashire",
    "sg:tags":[
        "mixed",
        "crop"
    ],
    "wof:name":"C E Middleton",
    "wof:placetype":"venue"
},
  "geometry": {"coordinates":[-2.608847,54.10355],"type":"Point"}
}