{
  "type": "Feature",
  "properties": {
    "addr:full":"25 Belper Road, West Hallam Ilkeston Derbyshire DE7 6GY",
    "addr:housenumber":"25",
    "addr:postcode":"de7 6gy",
    "addr:street":"Belper Road",
    "iso:country":"GB",
    "sg:address":"25 Belper Road, West Hallam",
    "sg:city":"Ilkeston",
    "sg:classifiers":[
        {
            "category":"Food & Beverages",
            "subcategory":"Groceries & Convenience Stores",
            "type":"Retail Goods"
        }
    ],
    "sg:phone":"+44 115 930 6518",
    "sg:postcode":"DE7 6GY",
    "sg:province":"Derbyshire",
    "wof:name":"THE CORNER SHOP",
    "wof:placetype":"venue"
},
  "geometry": {"coordinates":[-1.374222,52.973186],"type":"Point"}
}