{
  "type": "Feature",
  "properties": {
    "addr:full":"Shore Rd Perth Perth and Kinross PH2 8BD",
    "addr:postcode":"ph2 8bd",
    "addr:street":"Shore Rd",
    "iso:country":"GB",
    "sg:address":"Shore Rd",
    "sg:city":"Perth",
    "sg:classifiers":[
        {
            "category":"Organizations",
            "subcategory":"Non-profit Organization",
            "type":"Services"
        }
    ],
    "sg:phone":"+44 1738 451033",
    "sg:postcode":"PH2 8BD",
    "sg:province":"Perth and Kinross",
    "sg:tags":[
        "alarm",
        "system"
    ],
    "wof:name":"A.M Securities",
    "wof:placetype":"venue"
},
  "geometry": {"coordinates":[-3.4263238907,56.3904495239],"type":"Point"}
}