{
  "type": "Feature",
  "properties": {
    "addr:full":"Daryl House, Bridge Road Stockton-on-tees Durham TS18 3BW",
    "addr:postcode":"ts18 3bw",
    "addr:street":"Bridge Road",
    "iso:country":"GB",
    "sg:address":"Daryl House, Bridge Road",
    "sg:city":"Stockton-on-tees",
    "sg:classifiers":[
        {
            "category":"Professional",
            "subcategory":"Employment Agencies",
            "type":"Services"
        }
    ],
    "sg:phone":"+44 1642 398800",
    "sg:postcode":"TS18 3BW",
    "sg:province":"Durham",
    "sg:tags":[
        "consultant"
    ],
    "wof:name":"Employment Service Jobcentre",
    "wof:placetype":"venue"
},
  "geometry": {"coordinates":[-1.312629,54.560799],"type":"Point"}
}