{
  "type": "Feature",
  "properties": {
    "addr:full":"65 Drake Street Rochdale Lancashire OL16 1SB",
    "addr:housenumber":"65",
    "addr:postcode":"ol16 1sb",
    "addr:street":"Drake Street",
    "iso:country":"GB",
    "sg:address":"65 Drake Street",
    "sg:city":"Rochdale",
    "sg:classifiers":[
        {
            "category":"Shopping",
            "subcategory":"Music",
            "type":"Retail Goods"
        }
    ],
    "sg:phone":"+44 1706 521818",
    "sg:postcode":"OL16 1SB",
    "sg:province":"Lancashire",
    "sg:tags":[
        "dvd",
        "record",
        "tape",
        "vinyl",
        "cd"
    ],
    "wof:name":"Rocks Off",
    "wof:placetype":"venue"
},
  "geometry": {"coordinates":[-2.1545128822,53.615688324],"type":"Point"}
}