{
  "type": "Feature",
  "properties": {
    "addr:full":"28 West St Maesteg Bridgend CF34 9AF",
    "addr:housenumber":"28",
    "addr:postcode":"cf34 9af",
    "addr:street":"West St",
    "iso:country":"GB",
    "sg:address":"28 West St",
    "sg:city":"Maesteg",
    "sg:classifiers":[
        {
            "category":"Building & Trades",
            "subcategory":"Plumbing",
            "type":"Services"
        }
    ],
    "sg:phone":"+44 1656 732955",
    "sg:postcode":"CF34 9AF",
    "sg:province":"Bridgend",
    "sg:tags":[
        "central",
        "heating"
    ],
    "wof:name":"Dixon,I,",
    "wof:placetype":"venue"
},
  "geometry": {"coordinates":[-3.659264,51.60532],"type":"Point"}
}