{
  "type": "Feature",
  "properties": {
    "addr:full":"19 Northcote Avenue, Ealing Broadway Greater London W5 3UR",
    "addr:housenumber":"19",
    "addr:postcode":"w5 3ur",
    "addr:street":"Northcote Avenue",
    "iso:country":"GB",
    "sg:address":"19 Northcote Avenue, Ealing",
    "sg:city":"Broadway",
    "sg:classifiers":[
        {
            "category":"Professional",
            "subcategory":"Management & Consulting",
            "type":"Services"
        }
    ],
    "sg:postcode":"W5 3UR",
    "sg:province":"Greater London",
    "sg:tags":[
        "consultant",
        "business"
    ],
    "wof:name":"Fitzroy Consultancy Ltd",
    "wof:placetype":"venue"
},
  "geometry": {"coordinates":[-0.299578,51.513252],"type":"Point"}
}