{
  "type": "Feature",
  "properties": {
    "iso:country":"GB",
    "sg:address":"Flat 2, 8 West Cliffe Mount",
    "sg:city":"Harrogate",
    "sg:classifiers":[
        {
            "category":"Communications",
            "subcategory":"Film & Video Production",
            "type":"Services"
        }
    ],
    "sg:phone":"+44 1423 520771",
    "sg:postcode":"HG2 0PR",
    "sg:province":"North Yorkshire",
    "sg:tags":[
        "illustrator",
        "artist"
    ],
    "wof:name":"Vic Williams Portrait Artist",
    "wof:placetype":"venue"
},
  "geometry": {"coordinates":[-1.5542500019,53.9869689941],"type":"Point"}
}