{
  "type": "Feature",
  "properties": {
    "addr:full":"Alcester Road, Portway Birmingham Worcestershire B48 7HX",
    "addr:postcode":"b48 7hx",
    "addr:street":"Alcester Road Portway",
    "iso:country":"GB",
    "sg:address":"Alcester Road, Portway",
    "sg:city":"Birmingham",
    "sg:classifiers":[
        {
            "category":"Autos & Motor Vehicles",
            "subcategory":"Automobile Sales",
            "type":"Retail Goods"
        }
    ],
    "sg:phone":"+44 1564 822877",
    "sg:postcode":"B48 7HX",
    "sg:province":"Worcestershire",
    "sg:tags":[
        "auction",
        "car"
    ],
    "wof:name":"Portway Motor Centre & Car Auctions",
    "wof:placetype":"venue"
},
  "geometry": {"coordinates":[-1.879579,52.346306],"type":"Point"}
}