{
  "type": "Feature",
  "properties": {
    "addr:full":"104 Wragby Road, Bardney Lincoln Lincolnshire LN3 5XW",
    "addr:housenumber":"104",
    "addr:postcode":"ln3 5xw",
    "addr:street":"Wragby Road",
    "iso:country":"GB",
    "sg:address":"104 Wragby Road, Bardney",
    "sg:city":"Lincoln",
    "sg:classifiers":[
        {
            "category":"Building & Trades",
            "subcategory":"Construction",
            "type":"Services"
        }
    ],
    "sg:postcode":"LN3 5XW",
    "sg:province":"Lincolnshire",
    "sg:tags":[
        "dry",
        "lining",
        "plasterers",
        "screeders"
    ],
    "wof:name":"J W Bandelow",
    "wof:placetype":"venue"
},
  "geometry": {"coordinates":[-0.319214,53.219971],"type":"Point"}
}