{
  "type": "Feature",
  "properties": {
    "iso:country":"GB",
    "sg:address":"Dental Surgery, 99 Guisborough Rd",
    "sg:city":"Middlesbrough",
    "sg:classifiers":[
        {
            "category":"Health Services",
            "subcategory":"Dentist",
            "type":"Services"
        }
    ],
    "sg:phone":"+44 1642 326040",
    "sg:postcode":"TS7 0JS",
    "sg:province":"North Yorkshire",
    "wof:name":"S E Selby",
    "wof:placetype":"venue"
},
  "geometry": {"coordinates":[-1.16858,54.52837],"type":"Point"}
}