{
  "type": "Feature",
  "properties": {
    "addr:full":"Unit 1, Sittingbourne Industrial Park Sittingbourne Kent ME10 3JH",
    "addr:housenumber":"unit 1",
    "addr:postcode":"me10 3jh",
    "addr:street":"Sittingbourne Industrial Park",
    "iso:country":"GB",
    "sg:address":"Unit 1, Sittingbourne Industrial Park",
    "sg:city":"Sittingbourne",
    "sg:classifiers":[
        {
            "category":"Manufacturing",
            "subcategory":"Petroleum Products",
            "type":"Manufacturing & Wholesale Goods"
        },
        {
            "category":"Real Estate",
            "subcategory":"Real Estate Agent",
            "type":"Services"
        }
    ],
    "sg:phone":"+44 1795 425567",
    "sg:postcode":"ME10 3JH",
    "sg:province":"Kent",
    "sg:tags":[
        "double",
        "glazing"
    ],
    "wof:name":"Maxiglaze Ltd",
    "wof:placetype":"venue"
},
  "geometry": {"coordinates":[0.7379099727,51.3408203125],"type":"Point"}
}