{
  "type": "Feature",
  "properties": {
    "iso:country":"GB",
    "sg:address":"7 Grange Road, St Michaels",
    "sg:city":"Tenterden",
    "sg:classifiers":[
        {
            "category":"Personal",
            "subcategory":"Beauty Salon",
            "type":"Services"
        }
    ],
    "sg:phone":"+44 1580 762630",
    "sg:postcode":"TN30 6DL",
    "sg:province":"Kent",
    "sg:tags":[
        "unisex",
        "hairdresser"
    ],
    "wof:name":"Carol's Hair Design",
    "wof:placetype":"venue"
},
  "geometry": {"coordinates":[0.691274,51.084427],"type":"Point"}
}