{
  "type": "Feature",
  "properties": {
    "iso:country":"GB",
    "sg:address":"1 Queens Mere",
    "sg:city":"Slough",
    "sg:classifiers":[
        {
            "category":"Banks & Credit Unions",
            "subcategory":"Bank",
            "type":"Services"
        }
    ],
    "sg:phone":"+44 1753 523822",
    "sg:postcode":"SL1 1DT",
    "sg:province":"Berkshire",
    "wof:name":"Barclays Bank Plc",
    "wof:placetype":"venue"
},
  "geometry": {"coordinates":[-0.58951,51.509178],"type":"Point"}
}