{
  "type": "Feature",
  "properties": {
    "addr:full":"51 Cartersfield Road Waltham Abbey Essex EN9 1JD",
    "addr:housenumber":"51",
    "addr:postcode":"en9 1jd",
    "addr:street":"Cartersfield Road",
    "iso:country":"GB",
    "sg:address":"51 Cartersfield Road",
    "sg:city":"Waltham Abbey",
    "sg:classifiers":[
        {
            "category":"Retail",
            "subcategory":"Auto Repair",
            "type":"Services"
        }
    ],
    "sg:phone":"+44 1992 701201",
    "sg:postcode":"EN9 1JD",
    "sg:province":"Essex",
    "sg:tags":[
        "modification",
        "garage"
    ],
    "wof:name":"Abbey Motorists Centre",
    "wof:placetype":"venue"
},
  "geometry": {"coordinates":[-0.001479,51.68206],"type":"Point"}
}