{
  "type": "Feature",
  "properties": {
    "iso:country":"GB",
    "sg:address":"23 College Gardens, Chingford",
    "sg:city":"London",
    "sg:classifiers":[
        {
            "category":"Building & Trades",
            "subcategory":"Construction",
            "type":"Services"
        }
    ],
    "sg:phone":"+44 20 8524 7706",
    "sg:postcode":"E4 7LQ",
    "sg:province":"Greater London",
    "sg:tags":[
        "decorator",
        "painter"
    ],
    "wof:name":"C J Gibbs",
    "wof:placetype":"venue"
},
  "geometry": {"coordinates":[-0.00872,51.632336],"type":"Point"}
}