{
  "type": "Feature",
  "properties": {
    "addr:full":"Y Fron, Hendy Rd Mold Denbighshire CH7 5JP",
    "addr:postcode":"ch7 5jp",
    "addr:street":"Hendy Rd",
    "iso:country":"GB",
    "sg:address":"Y Fron, Hendy Rd",
    "sg:city":"Mold",
    "sg:classifiers":[
        {
            "category":"Farming",
            "subcategory":"Livestock Farm",
            "type":"Manufacturing & Wholesale Goods"
        }
    ],
    "sg:phone":"+44 1352 754087",
    "sg:postcode":"CH7 5JP",
    "sg:province":"Denbighshire",
    "sg:tags":[
        "others"
    ],
    "wof:name":"H Jones",
    "wof:placetype":"venue"
},
  "geometry": {"coordinates":[-3.204065,53.176537],"type":"Point"}
}