{
  "type": "Feature",
  "properties": {
    "iso:country":"GB",
    "sg:address":"14 Cross Hill",
    "sg:city":"Workington",
    "sg:classifiers":[
        {
            "category":"Bars & Pubs",
            "type":"Food & Drink"
        }
    ],
    "sg:phone":"+44 1900 606821",
    "sg:postcode":"CA14 4ER",
    "sg:province":"Cumbria",
    "sg:tags":[
        "pubs",
        "inn"
    ],
    "wof:name":"Royal George Inn",
    "wof:placetype":"venue"
},
  "geometry": {"coordinates":[-3.5397670269,54.6401138306],"type":"Point"}
}