{
  "type": "Feature",
  "properties": {
    "addr:full":"12 Portland Place Bridport Dorset DT6 5EN",
    "addr:housenumber":"12",
    "addr:postcode":"dt6 5en",
    "addr:street":"Portland Place",
    "iso:country":"GB",
    "sg:address":"12 Portland Place",
    "sg:city":"Bridport",
    "sg:classifiers":[
        {
            "category":"Home & Garden",
            "subcategory":"Building Materials",
            "type":"Retail Goods"
        }
    ],
    "sg:postcode":"DT6 5EN",
    "sg:province":"Dorset",
    "sg:tags":[
        "fencing"
    ],
    "wof:name":"West Dorset Tree Services",
    "wof:placetype":"venue"
},
  "geometry": {"coordinates":[-2.76454,50.735996],"type":"Point"}
}