{
  "type": "Feature",
  "properties": {
    "iso:country":"GB",
    "sg:address":"569 Wilbraham Rd",
    "sg:city":"Manchester",
    "sg:classifiers":[
        {
            "category":"Food & Beverages",
            "subcategory":"Liquor & Beverages",
            "type":"Retail Goods"
        }
    ],
    "sg:phone":"+44 161 881 3362",
    "sg:postcode":"M21 9AF",
    "sg:province":"Cheshire",
    "sg:tags":[
        "beer",
        "spirit",
        "wines"
    ],
    "wof:name":"Thresher",
    "wof:placetype":"venue"
},
  "geometry": {"coordinates":[-2.277229,53.442532],"type":"Point"}
}