{
  "type": "Feature",
  "properties": {
    "iso:country":"GB",
    "sg:address":"1 College St, Higham Ferrers",
    "sg:city":"Rushden",
    "sg:classifiers":[
        {
            "category":"Cinema",
            "subcategory":"Movie Rental",
            "type":"Entertainment"
        }
    ],
    "sg:phone":"+44 1933 317878",
    "sg:postcode":"NN10 8DX",
    "sg:province":"Bedfordshire",
    "sg:tags":[
        "video",
        "library"
    ],
    "wof:name":"White House Videos Ltd",
    "wof:placetype":"venue"
},
  "geometry": {"coordinates":[-0.593025,52.306721],"type":"Point"}
}