{
  "type": "Feature",
  "properties": {
    "iso:country":"GB",
    "sg:address":"3 Old Hillfoot Rd",
    "sg:city":"Ayr",
    "sg:classifiers":[
        {
            "category":"Place Of Worship",
            "type":"Public Place"
        },
        {
            "category":"Organizations",
            "subcategory":"Non-profit Organization",
            "type":"Services"
        }
    ],
    "sg:phone":"+44 1292 267332",
    "sg:postcode":"KA7 3LW",
    "sg:province":"South Ayrshire",
    "sg:tags":[
        "charitable",
        "organisation",
        "charity"
    ],
    "wof:name":"CASTLEHILL PARISH CHURCH",
    "wof:placetype":"venue"
},
  "geometry": {"coordinates":[-4.61382,55.449188],"type":"Point"}
}