{
  "type": "Feature",
  "properties": {
    "addr:full":"29 Pound Way, Cowley Oxford Oxfordshire OX4 3XX",
    "addr:housenumber":"29",
    "addr:postcode":"ox4 3xx",
    "addr:street":"Pound Way",
    "iso:country":"GB",
    "sg:address":"29 Pound Way, Cowley",
    "sg:city":"Oxford",
    "sg:classifiers":[
        {
            "category":"Shopping",
            "subcategory":"Shoes",
            "type":"Retail Goods"
        }
    ],
    "sg:phone":"+44 1865 748942",
    "sg:postcode":"OX4 3XX",
    "sg:province":"Oxfordshire",
    "sg:tags":[
        "shop"
    ],
    "wof:name":"Stead & Simpson Ltd.",
    "wof:placetype":"venue"
},
  "geometry": {"coordinates":[-1.2180689573,51.7316551208],"type":"Point"}
}