{
  "type": "Feature",
  "properties": {
    "addr:full":"Udiam Farm, Junction Road Robertsbridge East Sussex TN32 5XD",
    "addr:postcode":"tn32 5xd",
    "addr:street":"Junction Road",
    "iso:country":"GB",
    "sg:address":"Udiam Farm, Junction Road",
    "sg:city":"Robertsbridge",
    "sg:classifiers":[
        {
            "category":"Retail",
            "subcategory":"Auto Repair",
            "type":"Services"
        }
    ],
    "sg:postcode":"TN32 5XD",
    "sg:province":"East Sussex",
    "sg:tags":[
        "modification",
        "garage"
    ],
    "wof:name":"K A Autos",
    "wof:placetype":"venue"
},
  "geometry": {"coordinates":[0.4744699895,50.9856491089],"type":"Point"}
}