{
  "type": "Feature",
  "properties": {
    "addr:full":"8 Buckingham Palace Road London Greater London SW1W 0QD",
    "addr:housenumber":"8",
    "addr:postcode":"sw1w 0qd",
    "addr:street":"Buckingham Palace Road",
    "iso:country":"GB",
    "sg:address":"8 Buckingham Palace Road",
    "sg:city":"London",
    "sg:classifiers":[
        {
            "category":"Food & Beverages",
            "subcategory":"Supermarket",
            "type":"Retail Goods"
        }
    ],
    "sg:postcode":"SW1W 0QD",
    "sg:province":"Greater London",
    "wof:name":"Costcutter Supermarket",
    "wof:placetype":"venue"
},
  "geometry": {"coordinates":[-0.14406,51.498013],"type":"Point"}
}