{
  "type": "Feature",
  "properties": {
    "iso:country":"GB",
    "sg:address":"28 Gledhow Wood Avenue",
    "sg:city":"Leeds",
    "sg:classifiers":[
        {
            "category":"Shopping",
            "subcategory":"Antiques",
            "type":"Retail Goods"
        }
    ],
    "sg:postcode":"LS8 1NY",
    "sg:province":"West Yorkshire",
    "wof:name":"19 Nort Blob",
    "wof:placetype":"venue"
},
  "geometry": {"coordinates":[-1.51778,53.831219],"type":"Point"}
}