{
  "type": "Feature",
  "properties": {
    "addr:full":"Robert Louis Stevenson Avenue, Westbourne Bournemouth Dorset BH4 8ED",
    "addr:postcode":"bh4 8ed",
    "addr:street":"Stevenson Avenue",
    "iso:country":"GB",
    "sg:address":"Robert Louis Stevenson Avenue, Westbourne",
    "sg:city":"Bournemouth",
    "sg:classifiers":[
        {
            "category":"Building & Trades",
            "subcategory":"Construction",
            "type":"Services"
        }
    ],
    "sg:phone":"+44 1202 768247",
    "sg:postcode":"BH4 8ED",
    "sg:province":"Dorset",
    "sg:tags":[
        "roofing"
    ],
    "wof:name":"Dangerpoint Roofing Supplies",
    "wof:placetype":"venue"
},
  "geometry": {"coordinates":[-1.9037740231,50.7207946777],"type":"Point"}
}