{
  "type": "Feature",
  "properties": {
    "addr:full":"2a Scrooby St, Greasbrough Rotherham South Yorkshire S61 4PH",
    "addr:housenumber":"2a",
    "addr:postcode":"s61 4ph",
    "addr:street":"Scrooby St",
    "iso:country":"GB",
    "sg:address":"2a Scrooby St, Greasbrough",
    "sg:city":"Rotherham",
    "sg:classifiers":[
        {
            "category":"Autos & Motor Vehicles",
            "subcategory":"Motorcycle Sales",
            "type":"Retail Goods"
        }
    ],
    "sg:phone":"+44 114 242 8061",
    "sg:postcode":"S61 4PH",
    "sg:province":"South Yorkshire",
    "sg:tags":[
        "component"
    ],
    "wof:name":"Pro Custom",
    "wof:placetype":"venue"
},
  "geometry": {"coordinates":[-1.363502,53.453545],"type":"Point"}
}