{
  "type": "Feature",
  "properties": {
    "iso:country":"GB",
    "sg:address":"St Edmunds Ho, Rope Walk",
    "sg:city":"Ipswich",
    "sg:classifiers":[
        {
            "category":"Community Center",
            "type":"Public Place"
        }
    ],
    "sg:phone":"+44 1473 583176",
    "sg:postcode":"IP4 1NF",
    "sg:province":"Suffolk",
    "sg:tags":[
        "centre"
    ],
    "wof:name":"Dedham Vale & Stour Valley Project",
    "wof:placetype":"venue"
},
  "geometry": {"coordinates":[1.1634700298,52.0555000305],"type":"Point"}
}