{
  "type": "Feature",
  "properties": {
    "iso:country":"GB",
    "sg:address":"Quemerford",
    "sg:city":"Calne",
    "sg:classifiers":[
        {
            "category":"Travel",
            "subcategory":"Hotels & Motels",
            "type":"Entertainment"
        }
    ],
    "sg:phone":"+44 1249 813275",
    "sg:postcode":"SN11 8UJ",
    "sg:province":"Wiltshire",
    "wof:name":"Hayle Farm Hotel & Restaurant",
    "wof:placetype":"venue"
},
  "geometry": {"coordinates":[-1.96988,51.427719],"type":"Point"}
}