{
  "type": "Feature",
  "properties": {
    "addr:full":"4 Wick Lane Christchurch Dorset BH23 1HX",
    "addr:housenumber":"4",
    "addr:postcode":"bh23 1hx",
    "addr:street":"Wick Lane",
    "iso:country":"GB",
    "sg:address":"4 Wick Lane",
    "sg:city":"Christchurch",
    "sg:classifiers":[
        {
            "category":"Real Estate",
            "subcategory":"Real Estate Agent",
            "type":"Services"
        }
    ],
    "sg:phone":"+44 1202 485187",
    "sg:postcode":"BH23 1HX",
    "sg:province":"Dorset",
    "wof:name":"Bullock & Lees (Christchurch) Ltd.",
    "wof:placetype":"venue"
},
  "geometry": {"coordinates":[-1.7773400545,50.7328453064],"type":"Point"}
}