{
  "type": "Feature",
  "properties": {
    "iso:country":"GB",
    "sg:address":"55 Norwood Drive",
    "sg:city":"Chester",
    "sg:classifiers":[
        {
            "category":"Professional",
            "subcategory":"Management & Consulting",
            "type":"Services"
        }
    ],
    "sg:phone":"+44 1244 679156",
    "sg:postcode":"CH4 7RN",
    "sg:province":"Cheshire",
    "sg:tags":[
        "consultant",
        "business"
    ],
    "wof:name":"Joto Investments",
    "wof:placetype":"venue"
},
  "geometry": {"coordinates":[-2.899774,53.173454],"type":"Point"}
}