{
  "type": "Feature",
  "properties": {
    "addr:full":"26 Darlington Road Ferryhill Durham DL17 8JP",
    "addr:housenumber":"26",
    "addr:postcode":"dl17 8jp",
    "addr:street":"Darlington Road",
    "iso:country":"GB",
    "sg:address":"26 Darlington Road",
    "sg:city":"Ferryhill",
    "sg:classifiers":[
        {
            "category":"Personal",
            "subcategory":"Beauty Salon",
            "type":"Services"
        }
    ],
    "sg:phone":"+44 1740 651445",
    "sg:postcode":"DL17 8JP",
    "sg:province":"Durham",
    "sg:tags":[
        "unisex",
        "hairdresser"
    ],
    "wof:name":"Gladstone's",
    "wof:placetype":"venue"
},
  "geometry": {"coordinates":[-1.55748,54.687016],"type":"Point"}
}