{
  "type": "Feature",
  "properties": {
    "addr:full":"Crossfields, The Common, East Hanningfield Chelmsford Essex CM3 8AH",
    "addr:postcode":"cm3 8ah",
    "addr:street":"The Common East",
    "iso:country":"GB",
    "sg:address":"Crossfields, The Common, East Hanningfield",
    "sg:city":"Chelmsford",
    "sg:classifiers":[
        {
            "category":"Manufacturing",
            "subcategory":"Toys & Sporting Goods",
            "type":"Manufacturing & Wholesale Goods"
        },
        {
            "category":"Wholesale",
            "subcategory":"Sporting Goods",
            "type":"Manufacturing & Wholesale Goods"
        },
        {
            "category":"Professional",
            "subcategory":"Business Services",
            "type":"Services"
        }
    ],
    "sg:phone":"+44 1245 400434",
    "sg:postcode":"CM3 8AH",
    "sg:province":"Essex",
    "sg:tags":[
        "mnfr",
        "manufacturer",
        "sport",
        "sportswear",
        "equipment"
    ],
    "wof:name":"Warsop & Stebbing",
    "wof:placetype":"venue"
},
  "geometry": {"coordinates":[0.55668,51.68454],"type":"Point"}
}