{
  "type": "Feature",
  "properties": {
    "addr:full":"77 Higher Lane Lymm Cheshire WA13 0BZ",
    "addr:housenumber":"77",
    "addr:postcode":"wa13 0bz",
    "addr:street":"Higher Lane",
    "iso:country":"GB",
    "sg:address":"77 Higher Lane",
    "sg:city":"Lymm",
    "sg:classifiers":[
        {
            "category":"Professional",
            "subcategory":"Secretarial Services",
            "type":"Services"
        }
    ],
    "sg:phone":"+44 1925 757179",
    "sg:postcode":"WA13 0BZ",
    "sg:province":"Cheshire",
    "wof:name":"Formby Associates",
    "wof:placetype":"venue"
},
  "geometry": {"coordinates":[-2.4682319164,53.3761062622],"type":"Point"}
}