{
  "type": "Feature",
  "properties": {
    "addr:full":"17 Hamilton Avenue Cobham Surrey KT11 1AU",
    "addr:housenumber":"17",
    "addr:postcode":"kt11 1au",
    "addr:street":"Hamilton Avenue",
    "iso:country":"GB",
    "sg:address":"17 Hamilton Avenue",
    "sg:city":"Cobham",
    "sg:classifiers":[
        {
            "category":"Recreation",
            "subcategory":"Dog Park",
            "type":"Entertainment"
        }
    ],
    "sg:phone":"+44 1932 865033",
    "sg:postcode":"KT11 1AU",
    "sg:province":"Surrey",
    "wof:name":"Paddy Wags Pet Grooming Service",
    "wof:placetype":"venue"
},
  "geometry": {"coordinates":[-0.418367,51.333492],"type":"Point"}
}