{
  "type": "Feature",
  "properties": {
    "addr:full":"51 Park Street, Winterton Scunthorpe Lincolnshire DN15 9UB",
    "addr:housenumber":"51",
    "addr:postcode":"dn15 9ub",
    "addr:street":"Park Street",
    "iso:country":"GB",
    "sg:address":"51 Park Street, Winterton",
    "sg:city":"Scunthorpe",
    "sg:classifiers":[
        {
            "category":"Building & Trades",
            "subcategory":"Construction",
            "type":"Services"
        }
    ],
    "sg:phone":"+44 1724 733013",
    "sg:postcode":"DN15 9UB",
    "sg:province":"Lincolnshire",
    "sg:tags":[
        "joiner",
        "carpenter"
    ],
    "wof:name":"Standerline Joinery Services",
    "wof:placetype":"venue"
},
  "geometry": {"coordinates":[-0.5887830257,53.6541481018],"type":"Point"}
}