{
  "type": "Feature",
  "properties": {
    "addr:full":"St Helens Rd Bolton Lancashire BL3 3NL",
    "addr:postcode":"bl3 3nl",
    "addr:street":"St Helens Rd",
    "iso:country":"GB",
    "sg:address":"St Helens Rd",
    "sg:city":"Bolton",
    "sg:classifiers":[
        {
            "category":"Place Of Worship",
            "type":"Public Place"
        }
    ],
    "sg:phone":"+44 1204 62519",
    "sg:postcode":"BL3 3NL",
    "sg:province":"Lancashire",
    "wof:name":"St Helens Road Methodist Church",
    "wof:placetype":"venue"
},
  "geometry": {"coordinates":[-2.445964098,53.5658531189],"type":"Point"}
}