{
  "type": "Feature",
  "properties": {
    "iso:country":"GB",
    "sg:address":"93-95 Leigh Street",
    "sg:city":"Sheffield",
    "sg:classifiers":[
        {
            "category":"Professional",
            "subcategory":"Engineering",
            "type":"Services"
        }
    ],
    "sg:phone":"+44 114 244 3969",
    "sg:postcode":"S9 2PR",
    "sg:province":"South Yorkshire",
    "sg:tags":[
        "precision",
        "engineer"
    ],
    "wof:name":"Fox Precision Machine Ltd.",
    "wof:placetype":"venue"
},
  "geometry": {"coordinates":[-1.428383,53.399418],"type":"Point"}
}