{
  "type": "Feature",
  "properties": {
    "addr:full":"Canal Bank Loughborough Leicestershire LE11 1QA",
    "addr:postcode":"le11 1qa",
    "addr:street":"Canal Bank",
    "iso:country":"GB",
    "sg:address":"Canal Bank",
    "sg:city":"Loughborough",
    "sg:classifiers":[
        {
            "category":"Bars & Pubs",
            "type":"Food & Drink"
        }
    ],
    "sg:postcode":"LE11 1QA",
    "sg:province":"Leicestershire",
    "sg:tags":[
        "pubs",
        "inn"
    ],
    "wof:name":"The Albion Inn",
    "wof:placetype":"venue"
},
  "geometry": {"coordinates":[-1.210695982,52.7749671936],"type":"Point"}
}