{
  "type": "Feature",
  "properties": {
    "iso:country":"GB",
    "sg:address":"5-7 Tentercroft Street, Industrial Estate",
    "sg:city":"Lincoln",
    "sg:classifiers":[
        {
            "category":"Home & Garden",
            "subcategory":"Furniture",
            "type":"Retail Goods"
        }
    ],
    "sg:postcode":"LN5 7ED",
    "sg:province":"Lincolnshire",
    "wof:name":"Barlis Pine",
    "wof:placetype":"venue"
},
  "geometry": {"coordinates":[-0.54203,53.225346],"type":"Point"}
}