{
  "type": "Feature",
  "properties": {
    "addr:full":"37a High Road Benfleet Essex SS7 5LH",
    "addr:housenumber":"37a",
    "addr:postcode":"ss7 5lh",
    "addr:street":"High Road",
    "iso:country":"GB",
    "sg:address":"37a High Road",
    "sg:city":"Benfleet",
    "sg:classifiers":[
        {
            "category":"Professional",
            "subcategory":"Engineering",
            "type":"Services"
        }
    ],
    "sg:phone":"+44 1268 754266",
    "sg:postcode":"SS7 5LH",
    "sg:province":"Essex",
    "sg:tags":[
        "design",
        "engineer"
    ],
    "wof:name":"Institute Of Domestic Heating & Environmental Engi",
    "wof:placetype":"venue"
},
  "geometry": {"coordinates":[0.563621,51.54718],"type":"Point"}
}