{
  "type": "Feature",
  "properties": {
    "iso:country":"GB",
    "sg:address":"2a Finkle Street, Bentley",
    "sg:city":"Doncaster",
    "sg:classifiers":[
        {
            "category":"Shopping",
            "subcategory":"Party Supplies",
            "type":"Retail Goods"
        }
    ],
    "sg:phone":"+44 1302 890614",
    "sg:postcode":"DN5 0RP",
    "sg:province":"South Yorkshire",
    "sg:tags":[
        "inflatables",
        "bouncy",
        "castle"
    ],
    "wof:name":"Kiddy Winks",
    "wof:placetype":"venue"
},
  "geometry": {"coordinates":[-1.1441479921,53.5468559265],"type":"Point"}
}