{
  "type": "Feature",
  "properties": {
    "addr:full":"Flottergate Mall Grimsby Lincolnshire DN31 1QX",
    "addr:postcode":"dn31 1qx",
    "addr:street":"Flottergate;Grimsby",
    "iso:country":"GB",
    "sg:address":"Flottergate Mall",
    "sg:city":"Grimsby",
    "sg:classifiers":[
        {
            "category":"Home & Garden",
            "subcategory":"Home Furnishings",
            "type":"Retail Goods"
        }
    ],
    "sg:phone":"+44 1472 250551",
    "sg:postcode":"DN31 1QX",
    "sg:province":"Lincolnshire",
    "sg:tags":[
        "blind",
        "curtain",
        "fitting"
    ],
    "wof:name":"A & D Curtains",
    "wof:placetype":"venue"
},
  "geometry": {"coordinates":[-0.08847,53.56514],"type":"Point"}
}