{
  "type": "Feature",
  "properties": {
    "iso:country":"GB",
    "sg:address":"Stott Lane",
    "sg:city":"Bolton",
    "sg:classifiers":[
        {
            "category":"Education",
            "subcategory":"School",
            "type":"Public Place"
        }
    ],
    "sg:phone":"+44 1204 333755",
    "sg:postcode":"BL2 2LR",
    "sg:province":"Lancashire",
    "sg:tags":[
        "local",
        "authority"
    ],
    "wof:name":"Tonge Moor County Primary School",
    "wof:placetype":"venue"
},
  "geometry": {"coordinates":[-2.411754,53.588379],"type":"Point"}
}