{
  "type": "Feature",
  "properties": {
    "addr:full":"Claren House, 14 Warrington Road Prescot Merseyside L34 5RB",
    "addr:housenumber":"14",
    "addr:postcode":"l34 5rb",
    "addr:street":"Warrington Road",
    "iso:country":"GB",
    "sg:address":"Claren House, 14 Warrington Road",
    "sg:city":"Prescot",
    "sg:classifiers":[
        {
            "category":"Retail",
            "subcategory":"Event Space",
            "type":"Services"
        }
    ],
    "sg:postcode":"L34 5RB",
    "sg:province":"Merseyside",
    "sg:tags":[
        "exhibition",
        "organiser"
    ],
    "wof:name":"Colebert  &  Proust Ltd.",
    "wof:placetype":"venue"
},
  "geometry": {"coordinates":[-2.800387,53.42979],"type":"Point"}
}