{
  "type": "Feature",
  "properties": {
    "iso:country":"GB",
    "sg:address":"Torlundy Farm",
    "sg:city":"Fort William",
    "sg:classifiers":[
        {
            "category":"Travel",
            "subcategory":"Hotels & Motels",
            "type":"Entertainment"
        }
    ],
    "sg:phone":"+44 1397 703015",
    "sg:postcode":"PH33 6SW",
    "sg:province":"Highland",
    "sg:tags":[
        "self",
        "catering"
    ],
    "wof:name":"Great Glen Holidays",
    "wof:placetype":"venue"
},
  "geometry": {"coordinates":[-5.1084589958,56.8184318542],"type":"Point"}
}