{
  "type": "Feature",
  "properties": {
    "iso:country":"GB",
    "sg:address":"40 Icknield Way",
    "sg:city":"Baldock",
    "sg:classifiers":[
        {
            "category":"Professional",
            "subcategory":"Art Services",
            "type":"Services"
        }
    ],
    "sg:postcode":"SG7 5AL",
    "sg:province":"Bedfordshire",
    "sg:tags":[
        "graphic",
        "designer"
    ],
    "wof:name":"Judy Design Billson",
    "wof:placetype":"venue"
},
  "geometry": {"coordinates":[-0.190899,51.991825],"type":"Point"}
}