{
  "type": "Feature",
  "properties": {
    "addr:full":"47 Frith Road Croydon Surrey CR0 1TB",
    "addr:housenumber":"47",
    "addr:postcode":"cr0 1tb",
    "addr:street":"Frith Road",
    "iso:country":"GB",
    "sg:address":"47 Frith Road",
    "sg:city":"Croydon",
    "sg:classifiers":[
        {
            "category":"Retail",
            "subcategory":"Repair Shop",
            "type":"Services"
        }
    ],
    "sg:phone":"+44 20 8686 6004",
    "sg:postcode":"CR0 1TB",
    "sg:province":"Surrey",
    "sg:tags":[
        "clocks",
        "watch"
    ],
    "wof:name":"Geraldine",
    "wof:placetype":"venue"
},
  "geometry": {"coordinates":[-0.1028629988,51.3744544983],"type":"Point"}
}