{
  "type": "Feature",
  "properties": {
    "iso:country":"GB",
    "sg:address":"Wickford Business Park, 14-15 Buckingham Square",
    "sg:city":"Wickford",
    "sg:classifiers":[
        {
            "category":"Professional",
            "subcategory":"Printing & Photocopies",
            "type":"Services"
        }
    ],
    "sg:phone":"+44 1268 570824",
    "sg:postcode":"SS11 8YQ",
    "sg:province":"Essex",
    "sg:tags":[
        "computer",
        "tag",
        "label"
    ],
    "wof:name":"T A G Labels Ltd.",
    "wof:placetype":"venue"
},
  "geometry": {"coordinates":[0.5433,51.60276],"type":"Point"}
}