{
  "type": "Feature",
  "properties": {
    "addr:full":"7-8 Watkin Road Wembley Greater London HA9 0NL",
    "addr:housenumber":"7-8",
    "addr:postcode":"ha9 0nl",
    "addr:street":"Watkin Road",
    "iso:country":"GB",
    "sg:address":"7-8 Watkin Road",
    "sg:city":"Wembley",
    "sg:classifiers":[
        {
            "category":"Manufacturing",
            "subcategory":"Rubber & Plastics",
            "type":"Manufacturing & Wholesale Goods"
        }
    ],
    "sg:phone":"+44 20 8902 3161",
    "sg:postcode":"HA9 0NL",
    "sg:province":"Greater London",
    "sg:tags":[
        "product"
    ],
    "wof:name":"Toly Products (U K) Ltd.",
    "wof:placetype":"venue"
},
  "geometry": {"coordinates":[-0.2751089931,51.560585022],"type":"Point"}
}