{
  "type": "Feature",
  "properties": {
    "addr:full":"1 Wesley Street, Blythe Bridge Stoke-on-trent Staffordshire ST11 9QB",
    "addr:housenumber":"1",
    "addr:postcode":"st11 9qb",
    "addr:street":"Wesley Street",
    "iso:country":"GB",
    "sg:address":"1 Wesley Street, Blythe Bridge",
    "sg:city":"Stoke-on-trent",
    "sg:classifiers":[
        {
            "category":"Home & Garden",
            "subcategory":"Home Furnishings",
            "type":"Retail Goods"
        },
        {
            "category":"Home & Garden",
            "subcategory":"Furniture",
            "type":"Retail Goods"
        }
    ],
    "sg:phone":"+44 1782 392952",
    "sg:postcode":"ST11 9QB",
    "sg:province":"Staffordshire",
    "sg:tags":[
        "furnishers",
        "planner",
        "built-in",
        "fitted",
        "kitchen"
    ],
    "wof:name":"Kitchen Supreme Ltd.",
    "wof:placetype":"venue"
},
  "geometry": {"coordinates":[-2.059997,52.966465],"type":"Point"}
}