{
  "type": "Feature",
  "properties": {
    "addr:full":"4 The Parade, Kingston Road Leatherhead Surrey KT22 7SR",
    "addr:housenumber":"4",
    "addr:postcode":"kt22 7sr",
    "addr:street":"The Parade Kingston Road",
    "iso:country":"GB",
    "sg:address":"4 The Parade, Kingston Road",
    "sg:city":"Leatherhead",
    "sg:classifiers":[
        {
            "category":"Shopping",
            "subcategory":"Pharmacy",
            "type":"Retail Goods"
        }
    ],
    "sg:postcode":"KT22 7SR",
    "sg:province":"Surrey",
    "sg:tags":[
        "pharmacist",
        "store",
        "drug",
        "chemist"
    ],
    "wof:name":"K J Marsland",
    "wof:placetype":"venue"
},
  "geometry": {"coordinates":[-0.329418987,51.2963600159],"type":"Point"}
}