{
  "type": "Feature",
  "properties": {
    "iso:country":"GB",
    "sg:address":"Strathmore, The Flatts, Wombleton",
    "sg:city":"York",
    "sg:classifiers":[
        {
            "category":"Home & Garden",
            "subcategory":"Garden Supply",
            "type":"Retail Goods"
        },
        {
            "category":"Farming",
            "subcategory":"Farm",
            "type":"Manufacturing & Wholesale Goods"
        }
    ],
    "sg:phone":"+44 1751 431925",
    "sg:postcode":"YO62 7RU",
    "sg:province":"North Yorkshire",
    "sg:tags":[
        "mixed",
        "bulb",
        "crop",
        "grower"
    ],
    "wof:name":"W D Rickatson",
    "wof:placetype":"venue"
},
  "geometry": {"coordinates":[-0.974659,54.247471],"type":"Point"}
}