{
  "type": "Feature",
  "properties": {
    "addr:full":"8 Kensington Gardens, Hale Altrincham Cheshire WA15 9DP",
    "addr:housenumber":"8",
    "addr:postcode":"wa15 9dp",
    "addr:street":"Kensington Gardens",
    "iso:country":"GB",
    "sg:address":"8 Kensington Gardens, Hale",
    "sg:city":"Altrincham",
    "sg:classifiers":[
        {
            "category":"Professional",
            "subcategory":"Employment Agencies",
            "type":"Services"
        }
    ],
    "sg:phone":"+44 161 904 8676",
    "sg:postcode":"WA15 9DP",
    "sg:province":"Cheshire",
    "sg:tags":[
        "career",
        "guidance"
    ],
    "wof:name":"Independent Schools Careers Organisation",
    "wof:placetype":"venue"
},
  "geometry": {"coordinates":[-2.336796999,53.3745880127],"type":"Point"}
}