{
  "type": "Feature",
  "properties": {
    "iso:country":"GB",
    "sg:address":"Jobswell Ho, Jobswell Rd",
    "sg:city":"Carmarthen",
    "sg:classifiers":[
        {
            "category":"Health Services",
            "subcategory":"Clinic",
            "type":"Services"
        }
    ],
    "sg:phone":"+44 1267 223483",
    "sg:postcode":"SA31 3HB",
    "sg:province":"Carmarthenshire",
    "sg:tags":[
        "abuse",
        "drug"
    ],
    "wof:name":"Derwen Trust Community Drugs Team East Dyfed",
    "wof:placetype":"venue"
},
  "geometry": {"coordinates":[-4.331251,51.859135],"type":"Point"}
}