{
  "type": "Feature",
  "properties": {
    "iso:country":"GB",
    "sg:address":"Unit 2c, Book Lane",
    "sg:city":"Westbury",
    "sg:classifiers":[
        {
            "category":"Autos & Motor Vehicles",
            "subcategory":"Auto Supplies",
            "type":"Retail Goods"
        }
    ],
    "sg:postcode":"BA13 4EN",
    "sg:province":"Wiltshire",
    "sg:tags":[
        "gearbox"
    ],
    "wof:name":"Advanced Transmissions",
    "wof:placetype":"venue"
},
  "geometry": {"coordinates":[-2.20203,51.268135],"type":"Point"}
}