{
  "type": "Feature",
  "properties": {
    "iso:country":"GB",
    "sg:address":"3 Vulcan House",
    "sg:city":"Reading",
    "sg:classifiers":[
        {
            "category":"Shopping",
            "subcategory":"Books",
            "type":"Retail Goods"
        },
        {
            "category":"Travel",
            "subcategory":"Travel Agent",
            "type":"Entertainment"
        }
    ],
    "sg:phone":"+44 118 982 1921",
    "sg:postcode":"RG7 8PA",
    "sg:province":"Berkshire",
    "wof:name":"Open Roads Ltd.",
    "wof:placetype":"venue"
},
  "geometry": {"coordinates":[-1.16256,51.362],"type":"Point"}
}