{
  "type": "Feature",
  "properties": {
    "addr:full":"Glenfoot, Balfron Glasgow Argyll and Bute G63 0SF",
    "addr:postcode":"g63 0sf",
    "iso:country":"GB",
    "sg:address":"Glenfoot, Balfron",
    "sg:city":"Glasgow",
    "sg:classifiers":[
        {
            "category":"Shopping",
            "subcategory":"Pets & Pet Supplies",
            "type":"Retail Goods"
        }
    ],
    "sg:postcode":"G63 0SF",
    "sg:province":"Argyll and Bute",
    "sg:tags":[
        "food"
    ],
    "wof:name":"Glenfoot Petfoods",
    "wof:placetype":"venue"
},
  "geometry": {"coordinates":[-4.336973,56.071014],"type":"Point"}
}