{
  "type": "Feature",
  "properties": {
    "addr:full":"Poplars Yard, Buckwyns Chase Billericay Essex CM12 0TN",
    "addr:postcode":"cm12 0tn",
    "addr:street":"Poplars",
    "iso:country":"GB",
    "sg:address":"Poplars Yard, Buckwyns Chase",
    "sg:city":"Billericay",
    "sg:classifiers":[
        {
            "category":"Building & Trades",
            "subcategory":"Construction",
            "type":"Services"
        }
    ],
    "sg:phone":"+44 1277 651436",
    "sg:postcode":"CM12 0TN",
    "sg:province":"Essex",
    "sg:tags":[
        "dry",
        "plastering",
        "plasterers",
        "lining",
        "related",
        "screeders"
    ],
    "wof:name":"Internal Linings Ltd",
    "wof:placetype":"venue"
},
  "geometry": {"coordinates":[0.4168550074,51.62474823],"type":"Point"}
}