{
  "type": "Feature",
  "properties": {
    "iso:country":"GB",
    "sg:address":"P O Box 26",
    "sg:city":"Telford",
    "sg:classifiers":[
        {
            "category":"Professional",
            "subcategory":"Secretarial Services",
            "type":"Services"
        }
    ],
    "sg:phone":"+44 1952 244420",
    "sg:postcode":"TF5 0WH",
    "sg:province":"Shropshire",
    "wof:name":"Mail Merge Services",
    "wof:placetype":"venue"
},
  "geometry": {"coordinates":[-2.539739,52.7155],"type":"Point"}
}