{
  "type": "Feature",
  "properties": {
    "iso:country":"GB",
    "sg:address":"Armstrong Works, Pump La",
    "sg:city":"Hayes",
    "sg:classifiers":[
        {
            "category":"Professional",
            "subcategory":"Engineering",
            "type":"Services"
        }
    ],
    "sg:phone":"+44 20 8848 8450",
    "sg:postcode":"UB3 3NP",
    "sg:province":"Greater London",
    "sg:tags":[
        "contractor",
        "electrical",
        "engineer"
    ],
    "wof:name":"Westway Developments & Property Ltd",
    "wof:placetype":"venue"
},
  "geometry": {"coordinates":[-0.424756,51.501553],"type":"Point"}
}