{
  "type": "Feature",
  "properties": {
    "addr:full":"Tan Lan Holywell Denbighshire CH8 9UU",
    "addr:postcode":"ch8 9uu",
    "iso:country":"GB",
    "sg:address":"Tan Lan",
    "sg:city":"Holywell",
    "sg:classifiers":[
        {
            "category":"Train Station",
            "subcategory":"Rail",
            "type":"Transportation"
        }
    ],
    "sg:phone":"+44 1745 561115",
    "sg:postcode":"CH8 9UU",
    "sg:province":"Denbighshire",
    "sg:tags":[
        "caravan"
    ],
    "wof:name":"Bancroft Leisure",
    "wof:placetype":"venue"
},
  "geometry": {"coordinates":[-3.225195,53.274548],"type":"Point"}
}