{
  "type": "Feature",
  "properties": {
    "iso:country":"GB",
    "sg:address":"1a Barracks Lane, Blakenall",
    "sg:city":"Walsall",
    "sg:classifiers":[
        {
            "category":"Food & Beverages",
            "subcategory":"Fruits & Vegetables",
            "type":"Retail Goods"
        }
    ],
    "sg:phone":"+44 1922 404350",
    "sg:postcode":"WS3 1LP",
    "sg:province":"Staffordshire",
    "sg:tags":[
        "greengrocer"
    ],
    "wof:name":"Pixie Ices",
    "wof:placetype":"venue"
},
  "geometry": {"coordinates":[-1.9889860153,52.6144599915],"type":"Point"}
}