{
  "type": "Feature",
  "properties": {
    "iso:country":"GB",
    "sg:address":"184 Scotter Rd",
    "sg:city":"Scunthorpe",
    "sg:classifiers":[
        {
            "category":"Building & Trades",
            "subcategory":"Construction",
            "type":"Services"
        }
    ],
    "sg:phone":"+44 1724 855408",
    "sg:postcode":"DN15 7EQ",
    "sg:province":"Lincolnshire",
    "sg:tags":[
        "guttering"
    ],
    "wof:name":"K.F Dawson",
    "wof:placetype":"venue"
},
  "geometry": {"coordinates":[-0.684221983,53.5871582031],"type":"Point"}
}