{
  "type": "Feature",
  "properties": {
    "addr:full":"14 Madoc Street Llandudno Conwy LL30 2TL",
    "addr:housenumber":"14",
    "addr:postcode":"ll30 2tl",
    "addr:street":"Madoc Street",
    "iso:country":"GB",
    "sg:address":"14 Madoc Street",
    "sg:city":"Llandudno",
    "sg:classifiers":[
        {
            "category":"Real Estate",
            "subcategory":"Real Estate Agent",
            "type":"Services"
        },
        {
            "category":"Real Estate",
            "subcategory":"Architect",
            "type":"Services"
        }
    ],
    "sg:phone":"+44 1492 872861",
    "sg:postcode":"LL30 2TL",
    "sg:province":"Conwy",
    "wof:name":"Armstrong Kelsall & Snow",
    "wof:placetype":"venue"
},
  "geometry": {"coordinates":[-3.8312139511,53.3230400085],"type":"Point"}
}