{
  "type": "Feature",
  "properties": {
    "addr:full":"30a Straight Road, Boxted Colchester Essex CO4 5HN",
    "addr:housenumber":"30a",
    "addr:postcode":"co4 5hn",
    "addr:street":"Straight Road",
    "iso:country":"GB",
    "sg:address":"30a Straight Road, Boxted",
    "sg:city":"Colchester",
    "sg:classifiers":[
        {
            "category":"Professional",
            "subcategory":"Business Services",
            "type":"Services"
        }
    ],
    "sg:postcode":"CO4 5HN",
    "sg:province":"Essex",
    "sg:tags":[
        "tile",
        "stockist"
    ],
    "wof:name":"Atticus",
    "wof:placetype":"venue"
},
  "geometry": {"coordinates":[0.899444,51.93364],"type":"Point"}
}