{
  "type": "Feature",
  "properties": {
    "addr:full":"Victoria House, 5 Herne Bay Trading Park, Sea Street Herne Bay Kent CT6 8JZ",
    "addr:housenumber":"5",
    "addr:postcode":"ct6 8jz",
    "addr:street":"Sea Street",
    "iso:country":"GB",
    "sg:address":"Victoria House, 5 Herne Bay Trading Park, Sea Street",
    "sg:city":"Herne Bay",
    "sg:classifiers":[
        {
            "category":"Professional",
            "subcategory":"Accounting & Tax Preparation",
            "type":"Services"
        }
    ],
    "sg:phone":"+44 1227 366999",
    "sg:postcode":"CT6 8JZ",
    "sg:province":"Kent",
    "sg:tags":[
        "accountant"
    ],
    "wof:name":"Actif Accounting Ltd.",
    "wof:placetype":"venue"
},
  "geometry": {"coordinates":[1.1251000166,51.3712158203],"type":"Point"}
}