{
  "type": "Feature",
  "properties": {
    "addr:full":"Musgrove Park Taunton Somerset TA1 5DA",
    "addr:postcode":"ta1 5da",
    "addr:street":"Park",
    "iso:country":"GB",
    "sg:address":"Musgrove Park",
    "sg:city":"Taunton",
    "sg:classifiers":[
        {
            "category":"Organizations",
            "subcategory":"Membership Organization",
            "type":"Services"
        }
    ],
    "sg:phone":"+44 1823 333444",
    "sg:postcode":"TA1 5DA",
    "sg:province":"Somerset",
    "sg:tags":[
        "club"
    ],
    "wof:name":"Taunton Hospital Staff Social Club",
    "wof:placetype":"venue"
},
  "geometry": {"coordinates":[-3.123421,51.013275],"type":"Point"}
}