{
  "type": "Feature",
  "properties": {
    "addr:full":"Mount Street, Bishops Lydeard Taunton Devon TA4 3LH",
    "addr:postcode":"ta4 3lh",
    "addr:street":"Mount Street",
    "iso:country":"GB",
    "sg:address":"Mount Street, Bishops Lydeard",
    "sg:city":"Taunton",
    "sg:classifiers":[
        {
            "category":"Health Services",
            "subcategory":"Doctor",
            "type":"Services"
        },
        {
            "category":"Health Services",
            "subcategory":"Clinic",
            "type":"Services"
        }
    ],
    "sg:phone":"+44 1823 432361",
    "sg:postcode":"TA4 3LH",
    "sg:province":"Devon",
    "sg:tags":[
        "nh",
        "practitioners"
    ],
    "wof:name":"The Surgery",
    "wof:placetype":"venue"
},
  "geometry": {"coordinates":[-3.188399,51.055664],"type":"Point"}
}