{
  "type": "Feature",
  "properties": {
    "iso:country":"GB",
    "sg:address":"221 Albany Road",
    "sg:city":"Coventry",
    "sg:classifiers":[
        {
            "category":"Real Estate",
            "subcategory":"Real Estate Operator",
            "type":"Services"
        }
    ],
    "sg:postcode":"CV5 6NF",
    "sg:province":"West Midlands",
    "sg:tags":[
        "letting",
        "agent"
    ],
    "wof:name":"Three Spires Management Ltd.",
    "wof:placetype":"venue"
},
  "geometry": {"coordinates":[-1.53007,52.399929],"type":"Point"}
}