{
  "type": "Feature",
  "properties": {
    "addr:full":"129 Greenacre Drive Lutterworth Leicestershire LE17 4RW",
    "addr:housenumber":"129",
    "addr:postcode":"le17 4rw",
    "addr:street":"Greenacre Drive",
    "iso:country":"GB",
    "sg:address":"129 Greenacre Drive",
    "sg:city":"Lutterworth",
    "sg:classifiers":[
        {
            "category":"Professional",
            "subcategory":"Engineering",
            "type":"Services"
        }
    ],
    "sg:postcode":"LE17 4RW",
    "sg:province":"Leicestershire",
    "sg:tags":[
        "contractor",
        "electrical",
        "engineer"
    ],
    "wof:name":"Belmont Systems Ltd",
    "wof:placetype":"venue"
},
  "geometry": {"coordinates":[-1.209782958,52.4610176086],"type":"Point"}
}