{
  "type": "Feature",
  "properties": {
    "iso:country":"GB",
    "sg:address":"Kirby Rd",
    "sg:city":"Corby",
    "sg:classifiers":[
        {
            "category":"Arena",
            "subcategory":"Sports Club",
            "type":"Entertainment"
        }
    ],
    "sg:phone":"+44 1536 771607",
    "sg:postcode":"NN17 3DB",
    "sg:province":"Northamptonshire",
    "wof:name":"Gretton Sports Club",
    "wof:placetype":"venue"
},
  "geometry": {"coordinates":[-0.672129,52.53907],"type":"Point"}
}