{
  "type": "Feature",
  "properties": {
    "addr:full":"Linhope Farm Alnwick Northumberland NE66 4LZ",
    "addr:postcode":"ne66 4lz",
    "iso:country":"GB",
    "sg:address":"Linhope Farm",
    "sg:city":"Alnwick",
    "sg:classifiers":[
        {
            "category":"Farming",
            "subcategory":"Livestock Farm",
            "type":"Manufacturing & Wholesale Goods"
        }
    ],
    "sg:phone":"+44 1665 578111",
    "sg:postcode":"NE66 4LZ",
    "sg:province":"Northumberland",
    "sg:tags":[
        "others"
    ],
    "wof:name":"Linhope Estate",
    "wof:placetype":"venue"
},
  "geometry": {"coordinates":[-1.925059,55.442188],"type":"Point"}
}