{
  "type": "Feature",
  "properties": {
    "addr:full":"Benefield Road, Oundle Peterborough Cambridgeshire PE8 4EY",
    "addr:postcode":"pe8 4ey",
    "addr:street":"Benefield Road",
    "iso:country":"GB",
    "sg:address":"Benefield Road, Oundle",
    "sg:city":"Peterborough",
    "sg:classifiers":[
        {
            "category":"Organizations",
            "subcategory":"Non-profit Organization",
            "type":"Services"
        }
    ],
    "sg:phone":"+44 1832 274278",
    "sg:postcode":"PE8 4EY",
    "sg:province":"Cambridgeshire",
    "sg:tags":[
        "charitable",
        "organisation",
        "voluntary",
        "charity"
    ],
    "wof:name":"Rockingham Forest Trust Ltd",
    "wof:placetype":"venue"
},
  "geometry": {"coordinates":[-0.47087,52.480827],"type":"Point"}
}