{
  "type": "Feature",
  "properties": {
    "addr:full":"Westfield Farm, Westfield Road, Long Crendon Aylesbury Buckinghamshire HP18 9EW",
    "addr:postcode":"hp18 9ew",
    "addr:street":"Westfield Road",
    "iso:country":"GB",
    "sg:address":"Westfield Farm, Westfield Road, Long Crendon",
    "sg:city":"Aylesbury",
    "sg:classifiers":[
        {
            "category":"Farming",
            "subcategory":"Livestock Farm",
            "type":"Manufacturing & Wholesale Goods"
        }
    ],
    "sg:phone":"+44 1844 208227",
    "sg:postcode":"HP18 9EW",
    "sg:province":"Buckinghamshire",
    "sg:tags":[
        "others"
    ],
    "wof:name":"R F Brown",
    "wof:placetype":"venue"
},
  "geometry": {"coordinates":[-0.995376,51.773502],"type":"Point"}
}