{
  "type": "Feature",
  "properties": {
    "addr:full":"9 Seymour House, 19 Hanson Street London Greater London W1W 6TJ",
    "addr:housenumber":"9;19",
    "addr:postcode":"w1w 6tj",
    "addr:street":"Seymour;Hanson Street",
    "iso:country":"GB",
    "sg:address":"9 Seymour House, 19 Hanson Street",
    "sg:city":"London",
    "sg:classifiers":[
        {
            "category":"Professional",
            "subcategory":"Computer Services",
            "type":"Services"
        }
    ],
    "sg:postcode":"W1W 6TJ",
    "sg:province":"Greater London",
    "sg:tags":[
        "system",
        "software"
    ],
    "wof:name":"The Knowledge Process Ltd.",
    "wof:placetype":"venue"
},
  "geometry": {"coordinates":[-0.140602,51.519947],"type":"Point"}
}