{
  "type": "Feature",
  "properties": {
    "iso:country":"GB",
    "sg:address":"Garth End Farm",
    "sg:city":"York",
    "sg:classifiers":[
        {
            "category":"Travel",
            "subcategory":"Hotels & Motels",
            "type":"Entertainment"
        }
    ],
    "sg:phone":"+44 1904 738766",
    "sg:postcode":"YO5 8JR",
    "sg:province":"East Riding of Yorkshire",
    "sg:tags":[
        "self",
        "catering"
    ],
    "wof:name":"Filey Holidays",
    "wof:placetype":"venue"
},
  "geometry": {"coordinates":[-1.0834200382,53.9533309937],"type":"Point"}
}