{
  "type": "Feature",
  "properties": {
    "addr:full":"151 High Street Lowestoft Suffolk NR32 1HR",
    "addr:housenumber":"151",
    "addr:postcode":"nr32 1hr",
    "addr:street":"High Street",
    "iso:country":"GB",
    "sg:address":"151 High Street",
    "sg:city":"Lowestoft",
    "sg:classifiers":[
        {
            "category":"Personal",
            "subcategory":"Nail Salon",
            "type":"Services"
        }
    ],
    "sg:phone":"+44 1502 565828",
    "sg:postcode":"NR32 1HR",
    "sg:province":"Suffolk",
    "sg:tags":[
        "solarium",
        "tanning"
    ],
    "wof:name":"Crown Tanning",
    "wof:placetype":"venue"
},
  "geometry": {"coordinates":[1.7561000586,52.4825210571],"type":"Point"}
}