{
  "type": "Feature",
  "properties": {
    "iso:country":"GB",
    "sg:address":"Phoenix House, Plessey Road",
    "sg:city":"Blyth",
    "sg:classifiers":[
        {
            "category":"Building & Trades",
            "subcategory":"Construction",
            "type":"Services"
        }
    ],
    "sg:postcode":"NE24 3HT",
    "sg:province":"Northumberland",
    "sg:tags":[
        "dry",
        "lining",
        "plasterers",
        "screeders"
    ],
    "wof:name":"Phoenix Mouldings",
    "wof:placetype":"venue"
},
  "geometry": {"coordinates":[-1.502284,55.128262],"type":"Point"}
}