{
  "type": "Feature",
  "properties": {
    "addr:full":"61 Roedale Road Brighton East Sussex BN1 7GD",
    "addr:housenumber":"61",
    "addr:postcode":"bn1 7gd",
    "addr:street":"Roedale Road",
    "iso:country":"GB",
    "sg:address":"61 Roedale Road",
    "sg:city":"Brighton",
    "sg:classifiers":[
        {
            "category":"Building & Trades",
            "subcategory":"Construction",
            "type":"Services"
        }
    ],
    "sg:postcode":"BN1 7GD",
    "sg:province":"East Sussex",
    "sg:tags":[
        "roofing"
    ],
    "wof:name":"C Jupp Roofing & Building",
    "wof:placetype":"venue"
},
  "geometry": {"coordinates":[-0.130795002,50.8424911499],"type":"Point"}
}