{
  "type": "Feature",
  "properties": {
    "iso:country":"GB",
    "sg:address":"Willow Lodge, Main Street",
    "sg:city":"Yeovil",
    "sg:classifiers":[
        {
            "category":"Shopping",
            "subcategory":"Department Store",
            "type":"Retail Goods"
        }
    ],
    "sg:postcode":"BA21 5TG",
    "sg:province":"Somerset",
    "wof:name":"Cavalier Carpets & Interior Design",
    "wof:placetype":"venue"
},
  "geometry": {"coordinates":[-2.6392920017,50.9484405518],"type":"Point"}
}