{
  "type": "Feature",
  "properties": {
    "iso:country":"GB",
    "sg:address":"Rear Of 13 Cypress Rd",
    "sg:city":"Southport",
    "sg:classifiers":[
        {
            "category":"Home & Garden",
            "subcategory":"Hardware",
            "type":"Retail Goods"
        }
    ],
    "sg:phone":"+44 1704 535760",
    "sg:postcode":"PR8 6HE",
    "sg:province":"Lancashire",
    "sg:tags":[
        "gear",
        "cutter"
    ],
    "wof:name":"G E A R S",
    "wof:placetype":"venue"
},
  "geometry": {"coordinates":[-3.0063040257,53.6479148865],"type":"Point"}
}