{
  "type": "Feature",
  "properties": {
    "iso:country":"GB",
    "sg:address":"121 Narborough Road",
    "sg:city":"Leicester",
    "sg:classifiers":[
        {
            "category":"Home & Garden",
            "subcategory":"Home Furnishings",
            "type":"Retail Goods"
        },
        {
            "category":"Home & Garden",
            "subcategory":"Furniture",
            "type":"Retail Goods"
        }
    ],
    "sg:phone":"+44 116 233 6788",
    "sg:postcode":"LE3 0PA",
    "sg:province":"Leicestershire",
    "sg:tags":[
        "soft",
        "sale"
    ],
    "wof:name":"Drapes Creative Interior",
    "wof:placetype":"venue"
},
  "geometry": {"coordinates":[-1.150656,52.626999],"type":"Point"}
}