{
  "type": "Feature",
  "properties": {
    "addr:full":"16 Molins Ct, Brideake Clo, Bewbush Crawley West Sussex RH11 8NT",
    "addr:housenumber":"16",
    "addr:postcode":"rh11 8nt",
    "addr:street":"Molins Ct Brideake Clo",
    "iso:country":"GB",
    "sg:address":"16 Molins Ct, Brideake Clo, Bewbush",
    "sg:city":"Crawley",
    "sg:classifiers":[
        {
            "category":"Home & Garden",
            "subcategory":"Household Appliances",
            "type":"Retail Goods"
        }
    ],
    "sg:postcode":"RH11 8NT",
    "sg:province":"West Sussex",
    "sg:tags":[
        "electrical"
    ],
    "wof:name":"Padar,Mohammed,",
    "wof:placetype":"venue"
},
  "geometry": {"coordinates":[-0.2168039978,51.1051063538],"type":"Point"}
}