{
  "type": "Feature",
  "properties": {
    "iso:country":"GB",
    "sg:address":"Straight Road, Boxted",
    "sg:city":"Colchester",
    "sg:classifiers":[
        {
            "category":"Bars & Pubs",
            "type":"Food & Drink"
        },
        {
            "category":"Community Center",
            "subcategory":"Social",
            "type":"Public Place"
        }
    ],
    "sg:postcode":"CO4 5QX",
    "sg:province":"Essex",
    "sg:tags":[
        "pubs",
        "house",
        "inn",
        "activity"
    ],
    "wof:name":"WIG & FIDGETT",
    "wof:placetype":"venue"
},
  "geometry": {"coordinates":[0.91696,51.954449],"type":"Point"}
}