{
  "type": "Feature",
  "properties": {
    "addr:full":"82 Swinefleet Road Goole East Riding of Yorkshire DN14 5TP",
    "addr:housenumber":"82",
    "addr:postcode":"dn14 5tp",
    "addr:street":"Swinefleet Road",
    "iso:country":"GB",
    "sg:address":"82 Swinefleet Road",
    "sg:city":"Goole",
    "sg:classifiers":[
        {
            "category":"Bars & Pubs",
            "type":"Food & Drink"
        }
    ],
    "sg:phone":"+44 1405 764241",
    "sg:postcode":"DN14 5TP",
    "sg:province":"East Riding of Yorkshire",
    "sg:tags":[
        "pubs",
        "inn"
    ],
    "wof:name":"Marcia Dorothy Nicholls",
    "wof:placetype":"venue"
},
  "geometry": {"coordinates":[-0.8673580289,53.6934432983],"type":"Point"}
}