{
  "type": "Feature",
  "properties": {
    "addr:full":"Oriel House, Alec Rose Lane Portsmouth Hampshire PO1 2SA",
    "addr:postcode":"hampshire po1 2sa",
    "addr:street":"Alec Rose Lane",
    "iso:country":"GB",
    "sg:address":"Oriel House, Alec Rose Lane",
    "sg:city":"Portsmouth",
    "sg:classifiers":[
        {
            "category":"Bars & Pubs",
            "subcategory":"Nightclub",
            "type":"Food & Drink"
        },
        {
            "category":"Casinos & Gambling",
            "type":"Entertainment"
        }
    ],
    "sg:phone":"+44 23 9273 6668",
    "sg:postcode":"PO1 2SA",
    "sg:province":"Hampshire",
    "sg:tags":[
        "club",
        "night"
    ],
    "wof:name":"Stanley Casino Portsmouth",
    "wof:placetype":"venue"
},
  "geometry": {"coordinates":[-1.089154,50.796879],"type":"Point"}
}