{
  "type": "Feature",
  "properties": {
    "addr:full":"Becks Green Lane, Ilketshall St. Andrew Beccles Norfolk NR34 8NB",
    "addr:postcode":"nr34 8nb",
    "addr:street":"Becks Green Lane Ilketshall St.",
    "iso:country":"GB",
    "sg:address":"Becks Green Lane, Ilketshall St. Andrew",
    "sg:city":"Beccles",
    "sg:classifiers":[
        {
            "category":"Professional",
            "subcategory":"Art Services",
            "type":"Services"
        }
    ],
    "sg:phone":"+44 1986 781718",
    "sg:postcode":"NR34 8NB",
    "sg:province":"Norfolk",
    "sg:tags":[
        "carver",
        "sculptor"
    ],
    "wof:name":"Little Beck Farm",
    "wof:placetype":"venue"
},
  "geometry": {"coordinates":[1.507875,52.402939],"type":"Point"}
}