{
  "type": "Feature",
  "properties": {
    "addr:full":"16 Lloyd Street Wolverhampton Shropshire WV6 0RL",
    "addr:housenumber":"16",
    "addr:postcode":"wv6 0rl",
    "addr:street":"Lloyd Street",
    "iso:country":"GB",
    "sg:address":"16 Lloyd Street",
    "sg:city":"Wolverhampton",
    "sg:classifiers":[
        {
            "category":"Education",
            "subcategory":"Music School",
            "type":"Public Place"
        }
    ],
    "sg:phone":"+44 1902 312133",
    "sg:postcode":"WV6 0RL",
    "sg:province":"Shropshire",
    "sg:tags":[
        "teacher"
    ],
    "wof:name":"Wolverhampton Guitar Studio",
    "wof:placetype":"venue"
},
  "geometry": {"coordinates":[-2.1512041092,52.5957565308],"type":"Point"}
}