{
  "type": "Feature",
  "properties": {
    "addr:full":"275 Stretford Road Manchester Cheshire M41 9NU",
    "addr:housenumber":"275",
    "addr:postcode":"m41 9nu",
    "addr:street":"Stretford Road",
    "iso:country":"GB",
    "sg:address":"275 Stretford Road",
    "sg:city":"Manchester",
    "sg:classifiers":[
        {
            "category":"Food & Beverages",
            "subcategory":"Fruits & Vegetables",
            "type":"Retail Goods"
        }
    ],
    "sg:postcode":"M41 9NU",
    "sg:province":"Cheshire",
    "sg:tags":[
        "greengrocer"
    ],
    "wof:name":"The Bread Shop",
    "wof:placetype":"venue"
},
  "geometry": {"coordinates":[-2.331439,53.446007],"type":"Point"}
}