{
  "type": "Feature",
  "properties": {
    "addr:full":"Unit 4 & 5 Sherdley Rd Indstl Est, Ormande St St Helens Cheshire WA9 5AE",
    "addr:housenumber":"unit 4 & 5",
    "addr:postcode":"wa9 5ae",
    "addr:street":"Sherdley Rd;Est;St",
    "iso:country":"GB",
    "sg:address":"Unit 4 & 5 Sherdley Rd Indstl Est, Ormande St",
    "sg:city":"St Helens",
    "sg:classifiers":[
        {
            "category":"Retail",
            "subcategory":"Auto Repair",
            "type":"Services"
        }
    ],
    "sg:postcode":"WA9 5AE",
    "sg:province":"Cheshire",
    "sg:tags":[
        "modification",
        "garage"
    ],
    "wof:name":"Hiley's Car Sales",
    "wof:placetype":"venue"
},
  "geometry": {"coordinates":[-2.72569,53.442402],"type":"Point"}
}