{
  "type": "Feature",
  "properties": {
    "addr:full":"Lyon Court Wals Worth Road Hitchin Hertfordshire SG4 9SX",
    "addr:postcode":"sg4 9sx",
    "addr:street":"Lyon Court;Worth Road",
    "iso:country":"GB",
    "sg:address":"Lyon Court Wals Worth Road",
    "sg:city":"Hitchin",
    "sg:classifiers":[
        {
            "category":"Insurance",
            "subcategory":"Insurance Agent",
            "type":"Services"
        }
    ],
    "sg:phone":"+44 1462 440088",
    "sg:postcode":"SG4 9SX",
    "sg:province":"Hertfordshire",
    "sg:tags":[
        "broker"
    ],
    "wof:name":"Nott Pybus & Associates Ltd.",
    "wof:placetype":"venue"
},
  "geometry": {"coordinates":[-0.2677440047,51.9517364502],"type":"Point"}
}