{
  "type": "Feature",
  "properties": {
    "iso:country":"GB",
    "sg:address":"Green Park, Stocks Lane, Penketh",
    "sg:city":"Warrington",
    "sg:classifiers":[
        {
            "category":"Farming",
            "subcategory":"Nursery",
            "type":"Manufacturing & Wholesale Goods"
        }
    ],
    "sg:phone":"+44 1925 791158",
    "sg:postcode":"WA5 3JS",
    "sg:province":"Cheshire",
    "sg:tags":[
        "creche"
    ],
    "wof:name":"First Steps Private Nursery",
    "wof:placetype":"venue"
},
  "geometry": {"coordinates":[-2.658769,53.396133],"type":"Point"}
}