{
  "type": "Feature",
  "properties": {
    "addr:full":"36 Cross Deep Twickenham Greater London TW1 4RA",
    "addr:housenumber":"36",
    "addr:postcode":"tw1 4ra",
    "addr:street":"Cross Deep",
    "iso:country":"GB",
    "sg:address":"36 Cross Deep",
    "sg:city":"Twickenham",
    "sg:classifiers":[
        {
            "category":"Professional",
            "subcategory":"Secretarial Services",
            "type":"Services"
        }
    ],
    "sg:postcode":"TW1 4RA",
    "sg:province":"Greater London",
    "wof:name":"Words Unlimited",
    "wof:placetype":"venue"
},
  "geometry": {"coordinates":[-0.3312549889,51.442855835],"type":"Point"}
}