{
  "type": "Feature",
  "properties": {
    "addr:full":"126 Crackenedge Lane Dewsbury West Yorkshire WF13 1RW",
    "addr:housenumber":"126",
    "addr:postcode":"wf13 1rw",
    "addr:street":"Crackenedge Lane",
    "iso:country":"GB",
    "sg:address":"126 Crackenedge Lane",
    "sg:city":"Dewsbury",
    "sg:classifiers":[
        {
            "category":"Shopping",
            "subcategory":"News",
            "type":"Retail Goods"
        }
    ],
    "sg:phone":"+44 1924 459956",
    "sg:postcode":"WF13 1RW",
    "sg:province":"West Yorkshire",
    "sg:tags":[
        "newsagent"
    ],
    "wof:name":"Ibrahim Patel",
    "wof:placetype":"venue"
},
  "geometry": {"coordinates":[-1.6292630434,53.69739151],"type":"Point"}
}