{
  "type": "Feature",
  "properties": {
    "addr:full":"East View House, Baldwin Close, Off Macmillan Way Northampton Northamptonshire NN3 6AY",
    "addr:postcode":"nn3 6ay",
    "addr:street":"East;Baldwin Close Off Macmillan Way",
    "iso:country":"GB",
    "sg:address":"East View House, Baldwin Close, Off Macmillan Way",
    "sg:city":"Northampton",
    "sg:classifiers":[
        {
            "category":"Health Services",
            "subcategory":"Clinic",
            "type":"Services"
        }
    ],
    "sg:phone":"+44 1604 648114",
    "sg:postcode":"NN3 6AY",
    "sg:province":"Northamptonshire",
    "sg:tags":[
        "nh"
    ],
    "wof:name":"Eastfield Community Resource Centre",
    "wof:placetype":"venue"
},
  "geometry": {"coordinates":[-0.858821,52.265903],"type":"Point"}
}