{
  "type": "Feature",
  "properties": {
    "iso:country":"GB",
    "sg:address":"Whitley Abbey School, Abbey Road",
    "sg:city":"Coventry",
    "sg:classifiers":[
        {
            "category":"Education",
            "subcategory":"School",
            "type":"Public Place"
        },
        {
            "category":"Government",
            "subcategory":"Office",
            "type":"Public Place"
        }
    ],
    "sg:phone":"+44 24 7630 2580",
    "sg:postcode":"CV3 4BD",
    "sg:province":"Warwickshire",
    "sg:tags":[
        "local",
        "authority"
    ],
    "wof:name":"Whitley Abbey Comprehensive School",
    "wof:placetype":"venue"
},
  "geometry": {"coordinates":[-1.4831639528,52.3870010376],"type":"Point"}
}