{
  "type": "Feature",
  "properties": {
    "iso:country":"GB",
    "sg:address":"172 Northdown Road, Cliftonville",
    "sg:city":"Margate",
    "sg:classifiers":[
        {
            "category":"Education",
            "subcategory":"Library",
            "type":"Public Place"
        }
    ],
    "sg:phone":"+44 1843 224017",
    "sg:postcode":"CT9 2QN",
    "sg:province":"Kent",
    "sg:tags":[
        "reproduction",
        "furniture"
    ],
    "wof:name":"McCarthy's",
    "wof:placetype":"venue"
},
  "geometry": {"coordinates":[1.3951460123,51.3881454468],"type":"Point"}
}