{
  "type": "Feature",
  "properties": {
    "iso:country":"GB",
    "sg:address":"Raddon Hill Lodge, Thorverton",
    "sg:city":"Exeter",
    "sg:classifiers":[
        {
            "category":"Banks & Credit Unions",
            "subcategory":"Financial Services",
            "type":"Services"
        },
        {
            "category":"Building & Trades",
            "subcategory":"Construction",
            "type":"Services"
        }
    ],
    "sg:phone":"+44 1392 861212",
    "sg:postcode":"EX5 5PP",
    "sg:province":"Devon",
    "sg:tags":[
        "consultant",
        "contractor"
    ],
    "wof:name":"Manor House Associates",
    "wof:placetype":"venue"
},
  "geometry": {"coordinates":[-3.520387,50.806702],"type":"Point"}
}