{
  "type": "Feature",
  "properties": {
    "iso:country":"GB",
    "sg:address":"Gas House Lane, Sutton Bridge",
    "sg:city":"Spalding",
    "sg:classifiers":[
        {
            "category":"Organizations",
            "subcategory":"Community Association",
            "type":"Services"
        },
        {
            "category":"Organizations",
            "subcategory":"Membership Organization",
            "type":"Services"
        }
    ],
    "sg:phone":"+44 1406 350359",
    "sg:postcode":"PE12 9SP",
    "sg:province":"Cambridgeshire",
    "sg:tags":[
        "club",
        "social"
    ],
    "wof:name":"Sutton Bridge Royal British Legion Social Club Ltd.",
    "wof:placetype":"venue"
},
  "geometry": {"coordinates":[0.185935,52.770134],"type":"Point"}
}