{
  "type": "Feature",
  "properties": {
    "addr:full":"56 Park Lane London Greater London N17 0JS",
    "addr:housenumber":"56",
    "addr:postcode":"n17 0js",
    "addr:street":"Park Lane",
    "iso:country":"GB",
    "sg:address":"56 Park Lane",
    "sg:city":"London",
    "sg:classifiers":[
        {
            "category":"Retail",
            "subcategory":"Auto Repair",
            "type":"Services"
        }
    ],
    "sg:phone":"+44 20 8801 1855",
    "sg:postcode":"N17 0JS",
    "sg:province":"Greater London",
    "sg:tags":[
        "modification",
        "garage"
    ],
    "wof:name":"Vicarage Garage",
    "wof:placetype":"venue"
},
  "geometry": {"coordinates":[-0.0644230023,51.6022720337],"type":"Point"}
}