{
  "type": "Feature",
  "properties": {
    "iso:country":"GB",
    "sg:address":"Cheltenham House, 9 Dark Gate",
    "sg:city":"Carmarthen",
    "sg:classifiers":[
        {
            "category":"Banks & Credit Unions",
            "subcategory":"Bank",
            "type":"Services"
        }
    ],
    "sg:phone":"+44 1267 234222",
    "sg:postcode":"SA31 1PT",
    "sg:province":"Carmarthenshire",
    "wof:name":"Cheltenham & Gloucester Plc",
    "wof:placetype":"venue"
},
  "geometry": {"coordinates":[-4.3081870079,51.8563461304],"type":"Point"}
}