{
  "type": "Feature",
  "properties": {
    "addr:full":"Stonehall, Lydden Dover Kent CT15 7LA",
    "addr:postcode":"ct15 7la",
    "iso:country":"GB",
    "sg:address":"Stonehall, Lydden",
    "sg:city":"Dover",
    "sg:classifiers":[
        {
            "category":"Education",
            "subcategory":"School",
            "type":"Public Place"
        }
    ],
    "sg:phone":"+44 1304 822887",
    "sg:postcode":"CT15 7LA",
    "sg:province":"Kent",
    "sg:tags":[
        "local",
        "authority"
    ],
    "wof:name":"Lydden County Primary School",
    "wof:placetype":"venue"
},
  "geometry": {"coordinates":[1.2364979982,51.1656341553],"type":"Point"}
}