{
  "type": "Feature",
  "properties": {
    "addr:full":"49 Sloane Square Westminster Greater London SW1W 8AX",
    "addr:housenumber":"49",
    "addr:postcode":"sw1w 8ax",
    "addr:street":"Sloane Square",
    "iso:country":"GB",
    "sg:address":"49 Sloane Square",
    "sg:city":"Westminster",
    "sg:classifiers":[
        {
            "category":"Personal",
            "subcategory":"Beauty Salon",
            "type":"Services"
        }
    ],
    "sg:phone":"+44 20 7730 8113",
    "sg:postcode":"SW1W 8AX",
    "sg:province":"Greater London",
    "sg:tags":[
        "unisex",
        "hairdresser"
    ],
    "wof:name":"Toni & Guy",
    "wof:placetype":"venue"
},
  "geometry": {"coordinates":[-0.156561,51.492596],"type":"Point"}
}