{
  "type": "Feature",
  "properties": {
    "addr:full":"Contract Department, Wherstead Park Ipswich Suffolk IP9 2AQ",
    "addr:postcode":"ip9 2aq",
    "iso:country":"GB",
    "sg:address":"Contract Department, Wherstead Park",
    "sg:city":"Ipswich",
    "sg:classifiers":[
        {
            "category":"Utilities",
            "subcategory":"Electric",
            "type":"Services"
        }
    ],
    "sg:phone":"+44 1473 688688",
    "sg:postcode":"IP9 2AQ",
    "sg:province":"Suffolk",
    "sg:tags":[
        "electricity"
    ],
    "wof:name":"Edf Energy Networks (Epn) Plc",
    "wof:placetype":"venue"
},
  "geometry": {"coordinates":[1.09552,51.992199],"type":"Point"}
}