{
  "type": "Feature",
  "properties": {
    "addr:full":"9 High Street, Bethesda Bangor Gwynedd LL57 3AE",
    "addr:housenumber":"9",
    "addr:postcode":"ll57 3ae",
    "addr:street":"High Street",
    "iso:country":"GB",
    "sg:address":"9 High Street, Bethesda",
    "sg:city":"Bangor",
    "sg:classifiers":[
        {
            "category":"Fast Food",
            "type":"Food & Drink"
        }
    ],
    "sg:phone":"+44 1248 601482",
    "sg:postcode":"LL57 3AE",
    "sg:province":"Gwynedd",
    "sg:tags":[
        "away",
        "take"
    ],
    "wof:name":"Ty-isaf Restaurant",
    "wof:placetype":"venue"
},
  "geometry": {"coordinates":[-4.063984,53.180912],"type":"Point"}
}