{
  "type": "Feature",
  "properties": {
    "iso:country":"GB",
    "sg:address":"58a Sandwell St",
    "sg:city":"Walsall",
    "sg:classifiers":[
        {
            "category":"Retail",
            "subcategory":"Auto Repair",
            "type":"Services"
        }
    ],
    "sg:phone":"+44 1922 644448",
    "sg:postcode":"WS1 3EB",
    "sg:province":"West Midlands",
    "sg:tags":[
        "modification",
        "garage"
    ],
    "wof:name":"Sandwell Autos",
    "wof:placetype":"venue"
},
  "geometry": {"coordinates":[-1.978288,52.578388],"type":"Point"}
}