{
  "type": "Feature",
  "properties": {
    "iso:country":"GB",
    "sg:address":"Lynton Ho, Foxhole Rd",
    "sg:city":"Chorley",
    "sg:classifiers":[
        {
            "category":"Building & Trades",
            "subcategory":"Construction",
            "type":"Services"
        }
    ],
    "sg:phone":"+44 1257 238600",
    "sg:postcode":"PR7 1NY",
    "sg:province":"Lancashire",
    "sg:tags":[
        "builder"
    ],
    "wof:name":"Woodrose Ltd",
    "wof:placetype":"venue"
},
  "geometry": {"coordinates":[-2.632134,53.652088],"type":"Point"}
}