{
  "type": "Feature",
  "properties": {
    "iso:country":"GB",
    "sg:address":"1136 New Chester Rd",
    "sg:city":"Wirral",
    "sg:classifiers":[
        {
            "category":"Health Services",
            "subcategory":"Dentist",
            "type":"Services"
        }
    ],
    "sg:phone":"+44 151 327 1381",
    "sg:postcode":"CH62 8AD",
    "sg:province":"Cheshire",
    "wof:name":"Eastham Dental Practice",
    "wof:placetype":"venue"
},
  "geometry": {"coordinates":[-2.963989,53.315941],"type":"Point"}
}