{
  "type": "Feature",
  "properties": {
    "addr:full":"27-37 Perth Road Ilford Essex IG2 6BX",
    "addr:housenumber":"27-37",
    "addr:postcode":"ig2 6bx",
    "addr:street":"Perth Road",
    "iso:country":"GB",
    "sg:address":"27-37 Perth Road",
    "sg:city":"Ilford",
    "sg:classifiers":[
        {
            "category":"Bars & Pubs",
            "type":"Food & Drink"
        },
        {
            "category":"Community Center",
            "subcategory":"Social",
            "type":"Public Place"
        }
    ],
    "sg:phone":"+44 20 8554 6005",
    "sg:postcode":"IG2 6BX",
    "sg:province":"Essex",
    "sg:tags":[
        "pubs",
        "house",
        "inn",
        "activity"
    ],
    "wof:name":"The Valentine",
    "wof:placetype":"venue"
},
  "geometry": {"coordinates":[0.06834,51.575378],"type":"Point"}
}