{
  "type": "Feature",
  "properties": {
    "iso:country":"GB",
    "sg:address":"The Granary 8 Home End, Fulbourn",
    "sg:city":"Cambridge",
    "sg:classifiers":[
        {
            "category":"Manufacturing",
            "subcategory":"Signs",
            "type":"Manufacturing & Wholesale Goods"
        }
    ],
    "sg:phone":"+44 1223 509496",
    "sg:postcode":"CB1 5BS",
    "sg:province":"Cambridgeshire",
    "sg:tags":[
        "writer"
    ],
    "wof:name":"Gary Hickman",
    "wof:placetype":"venue"
},
  "geometry": {"coordinates":[0.2230339944,52.182434082],"type":"Point"}
}