{
  "type": "Feature",
  "properties": {
    "addr:full":"Lower Whiteston Farm Dunblane Perth and Kinross FK15 0JQ",
    "addr:postcode":"fk15 0jq",
    "addr:street":"Dunblane",
    "iso:country":"GB",
    "sg:address":"Lower Whiteston Farm",
    "sg:city":"Dunblane",
    "sg:classifiers":[
        {
            "category":"Utilities",
            "subcategory":"Refuse",
            "type":"Services"
        }
    ],
    "sg:phone":"+44 1786 823983",
    "sg:postcode":"FK15 0JQ",
    "sg:province":"Perth and Kinross",
    "sg:tags":[
        "disposal",
        "waste"
    ],
    "wof:name":"Kinbuck Tip",
    "wof:placetype":"venue"
},
  "geometry": {"coordinates":[-3.9529790878,56.1988601685],"type":"Point"}
}