{
  "type": "Feature",
  "properties": {
    "iso:country":"GB",
    "sg:address":"Little Brookgate, London Road",
    "sg:city":"Etchingham",
    "sg:classifiers":[
        {
            "category":"Professional",
            "type":"Services"
        }
    ],
    "sg:postcode":"TN19 7QY",
    "sg:province":"East Sussex",
    "sg:tags":[
        "caterer"
    ],
    "wof:name":"Rapidfare Ltd",
    "wof:placetype":"venue"
},
  "geometry": {"coordinates":[0.441642,51.00938],"type":"Point"}
}