{
  "type": "Feature",
  "properties": {
    "iso:country":"GB",
    "sg:address":"53 Holloway Road",
    "sg:city":"London",
    "sg:classifiers":[
        {
            "category":"Government",
            "subcategory":"Police Station",
            "type":"Public Place"
        },
        {
            "category":"Government",
            "subcategory":"Office",
            "type":"Public Place"
        }
    ],
    "sg:phone":"+44 20 7609 0913",
    "sg:postcode":"N7 8JD",
    "sg:province":"Greater London",
    "sg:tags":[
        "support",
        "central"
    ],
    "wof:name":"Inner London Probation Service",
    "wof:placetype":"venue"
},
  "geometry": {"coordinates":[-0.105844,51.547939],"type":"Point"}
}