{
  "type": "Feature",
  "properties": {
    "iso:country":"GB",
    "sg:address":"North Pickenham Road",
    "sg:city":"Swaffham",
    "sg:classifiers":[
        {
            "category":"Taxi",
            "type":"Transportation"
        }
    ],
    "sg:phone":"+44 1760 720444",
    "sg:postcode":"PE37 7QT",
    "sg:province":"Norfolk",
    "sg:tags":[
        "mini",
        "cab"
    ],
    "wof:name":"Ace-line Taxis",
    "wof:placetype":"venue"
},
  "geometry": {"coordinates":[0.6943389773,52.646396637],"type":"Point"}
}