{
  "type": "Feature",
  "properties": {
    "addr:full":"Turnpike Road Newbury Berkshire RG14 2NT",
    "addr:postcode":"rg14 2nt",
    "addr:street":"Turnpike Road",
    "iso:country":"GB",
    "sg:address":"Turnpike Road",
    "sg:city":"Newbury",
    "sg:classifiers":[
        {
            "category":"Government",
            "subcategory":"Post Office",
            "type":"Public Place"
        }
    ],
    "sg:phone":"+44 1635 40295",
    "sg:postcode":"RG14 2NT",
    "sg:province":"Berkshire",
    "sg:tags":[
        "organisation",
        "soc",
        "research"
    ],
    "wof:name":"Vincent Processes Ltd.",
    "wof:placetype":"venue"
},
  "geometry": {"coordinates":[-1.301794,51.40884],"type":"Point"}
}