{
  "type": "Feature",
  "properties": {
    "iso:country":"GB",
    "sg:address":"8 Pentreath Av",
    "sg:city":"Guildford",
    "sg:classifiers":[
        {
            "category":"Building & Trades",
            "subcategory":"Plumbing",
            "type":"Services"
        }
    ],
    "sg:phone":"+44 1483 535182",
    "sg:postcode":"GU2 5TA",
    "sg:province":"Surrey",
    "sg:tags":[
        "central",
        "heating"
    ],
    "wof:name":"Oldham R D",
    "wof:placetype":"venue"
},
  "geometry": {"coordinates":[-0.5976729989,51.2401657104],"type":"Point"}
}