{
  "type": "Feature",
  "properties": {
    "addr:full":"18 Blandford Square Newcastle-upon-tyne Tyne and Wear NE1 4HZ",
    "addr:housenumber":"18",
    "addr:postcode":"ne1 4hz",
    "addr:street":"Blandford Square",
    "iso:country":"GB",
    "sg:address":"18 Blandford Square",
    "sg:city":"Newcastle-upon-tyne",
    "sg:classifiers":[
        {
            "category":"Autos & Motor Vehicles",
            "subcategory":"Motorcycle Sales",
            "type":"Retail Goods"
        }
    ],
    "sg:phone":"+44 191 414 5016",
    "sg:postcode":"NE1 4HZ",
    "sg:province":"Tyne and Wear",
    "wof:name":"Classic Collection Motor Cycles",
    "wof:placetype":"venue"
},
  "geometry": {"coordinates":[-1.6240539551,54.9705543518],"type":"Point"}
}