{
  "type": "Feature",
  "properties": {
    "iso:country":"GB",
    "sg:address":"24 Bedford Road, Cefn Cribbwr",
    "sg:city":"Bridgend",
    "sg:classifiers":[
        {
            "category":"Bars & Pubs",
            "type":"Food & Drink"
        },
        {
            "category":"Community Center",
            "subcategory":"Social",
            "type":"Public Place"
        }
    ],
    "sg:phone":"+44 1656 740047",
    "sg:postcode":"CF32 0BW",
    "sg:province":"Bridgend",
    "sg:tags":[
        "pubs",
        "house",
        "inn",
        "activity"
    ],
    "wof:name":"White Lion",
    "wof:placetype":"venue"
},
  "geometry": {"coordinates":[-3.6544039249,51.5372505188],"type":"Point"}
}