{
  "type": "Feature",
  "properties": {
    "addr:full":"1 Brinsmoor Road, Brinsley Nottingham Derbyshire NG16 5DD",
    "addr:housenumber":"1",
    "addr:postcode":"ng16 5dd",
    "addr:street":"Brinsmoor Road",
    "iso:country":"GB",
    "sg:address":"1 Brinsmoor Road, Brinsley",
    "sg:city":"Nottingham",
    "sg:classifiers":[
        {
            "category":"Shopping",
            "subcategory":"Department Store",
            "type":"Retail Goods"
        }
    ],
    "sg:phone":"+44 1773 712076",
    "sg:postcode":"NG16 5DD",
    "sg:province":"Derbyshire",
    "wof:name":"Brinsley Food Fare",
    "wof:placetype":"venue"
},
  "geometry": {"coordinates":[-1.3116710186,53.0407180786],"type":"Point"}
}