{
  "type": "Feature",
  "properties": {
    "iso:country":"GB",
    "sg:address":"8a Coronation Avenue",
    "sg:city":"Yeovil",
    "sg:classifiers":[
        {
            "category":"Shopping",
            "subcategory":"News",
            "type":"Retail Goods"
        }
    ],
    "sg:phone":"+44 1935 474409",
    "sg:postcode":"BA21 3DX",
    "sg:province":"Somerset",
    "sg:tags":[
        "newsagent"
    ],
    "wof:name":"Westfield Post Office",
    "wof:placetype":"venue"
},
  "geometry": {"coordinates":[-2.648335,50.951225],"type":"Point"}
}