{
  "type": "Feature",
  "properties": {
    "addr:full":"55 Goodison Gardens, Erdington Birmingham West Midlands B24 0AQ",
    "addr:housenumber":"55",
    "addr:postcode":"b24 0aq",
    "addr:street":"Goodison Gardens",
    "iso:country":"GB",
    "sg:address":"55 Goodison Gardens, Erdington",
    "sg:city":"Birmingham",
    "sg:classifiers":[
        {
            "category":"Building & Trades",
            "subcategory":"Construction",
            "type":"Services"
        }
    ],
    "sg:postcode":"B24 0AQ",
    "sg:province":"West Midlands",
    "sg:tags":[
        "decorator",
        "painter"
    ],
    "wof:name":"David Smith",
    "wof:placetype":"venue"
},
  "geometry": {"coordinates":[-1.824947,52.529411],"type":"Point"}
}