{
  "type": "Feature",
  "properties": {
    "iso:country":"GB",
    "sg:address":"26 North Road",
    "sg:city":"Lancing",
    "sg:classifiers":[
        {
            "category":"Shopping",
            "subcategory":"Books",
            "type":"Retail Goods"
        }
    ],
    "sg:phone":"+44 1903 765489",
    "sg:postcode":"BN15 9AB",
    "sg:province":"West Sussex",
    "sg:tags":[
        "bookseller"
    ],
    "wof:name":"Lancing Books",
    "wof:placetype":"venue"
},
  "geometry": {"coordinates":[-0.3225030005,50.8277435303],"type":"Point"}
}