{
  "type": "Feature",
  "properties": {
    "addr:full":"Ganborough, Longborough Moreton-in-marsh Gloucestershire GL56 0QZ",
    "addr:postcode":"gl56 0qz",
    "iso:country":"GB",
    "sg:address":"Ganborough, Longborough",
    "sg:city":"Moreton-in-marsh",
    "sg:classifiers":[
        {
            "category":"Bars & Pubs",
            "type":"Food & Drink"
        },
        {
            "category":"Community Center",
            "subcategory":"Social",
            "type":"Public Place"
        }
    ],
    "sg:phone":"+44 1451 830208",
    "sg:postcode":"GL56 0QZ",
    "sg:province":"Gloucestershire",
    "sg:tags":[
        "pubs",
        "house",
        "inn",
        "activity"
    ],
    "wof:name":"Coach & Horses Inn",
    "wof:placetype":"venue"
},
  "geometry": {"coordinates":[-1.745641,51.964954],"type":"Point"}
}