{
  "type": "Feature",
  "properties": {
    "iso:country":"GB",
    "sg:address":"Illogan Churchtown",
    "sg:city":"Redruth",
    "sg:classifiers":[
        {
            "category":"Travel",
            "subcategory":"Hotels & Motels",
            "type":"Entertainment"
        }
    ],
    "sg:phone":"+44 1209 842256",
    "sg:postcode":"TR16 4QZ",
    "sg:province":"Cornwall",
    "wof:name":"Aviary Court Hotel & Restaurant",
    "wof:placetype":"venue"
},
  "geometry": {"coordinates":[-5.27243,50.250221],"type":"Point"}
}