{
  "type": "Feature",
  "properties": {
    "iso:country":"GB",
    "sg:address":"5 St Barnabus La",
    "sg:city":"Sheffield",
    "sg:classifiers":[
        {
            "category":"Retail",
            "subcategory":"Repair Shop",
            "type":"Services"
        }
    ],
    "sg:phone":"+44 114 258 5687",
    "sg:postcode":"S2 4TG",
    "sg:province":"South Yorkshire",
    "sg:tags":[
        "maintenance"
    ],
    "wof:name":"Gregory & Heaton",
    "wof:placetype":"venue"
},
  "geometry": {"coordinates":[-1.475202,53.367332],"type":"Point"}
}