{
  "type": "Feature",
  "properties": {
    "iso:country":"GB",
    "sg:address":"12 Rotterdam Street",
    "sg:city":"Thurso",
    "sg:classifiers":[
        {
            "category":"Shopping",
            "subcategory":"Clothing, Apparel, & Fashions",
            "type":"Retail Goods"
        }
    ],
    "sg:phone":"+44 1847 892006",
    "sg:postcode":"KW14 8EN",
    "sg:province":"Highland",
    "sg:tags":[
        "shop"
    ],
    "wof:name":"Mackays Stores Ltd.",
    "wof:placetype":"venue"
},
  "geometry": {"coordinates":[-3.519798,58.594818],"type":"Point"}
}