{
  "type": "Feature",
  "properties": {
    "iso:country":"GB",
    "sg:address":"Millwood House, Maresfield",
    "sg:city":"Uckfield",
    "sg:classifiers":[
        {
            "category":"Shopping",
            "subcategory":"Computers & Home Electronics",
            "type":"Retail Goods"
        }
    ],
    "sg:phone":"+44 1825 767998",
    "sg:postcode":"TN22 3AS",
    "sg:province":"East Sussex",
    "sg:tags":[
        "aerial",
        "television",
        "radio"
    ],
    "wof:name":"A E T Aerial Services",
    "wof:placetype":"venue"
},
  "geometry": {"coordinates":[0.055445,51.040073],"type":"Point"}
}