{
  "type": "Feature",
  "properties": {
    "iso:country":"GB",
    "sg:address":"18 Kings Park Road",
    "sg:city":"Bournemouth",
    "sg:classifiers":[
        {
            "category":"Social Services",
            "subcategory":"Retirement Home",
            "type":"Services"
        }
    ],
    "sg:postcode":"BH7 7AE",
    "sg:province":"Dorset",
    "sg:tags":[
        "rest"
    ],
    "wof:name":"Christie Lodge",
    "wof:placetype":"venue"
},
  "geometry": {"coordinates":[-1.842475,50.73473],"type":"Point"}
}