{
  "type": "Feature",
  "properties": {
    "iso:country":"GB",
    "sg:address":"Edith Moffatt House, 1-25 Albion Rd",
    "sg:city":"North Shields",
    "sg:classifiers":[
        {
            "category":"Health Services",
            "subcategory":"Nursing And Care Facility",
            "type":"Services"
        }
    ],
    "sg:phone":"+44 191 296 4170",
    "sg:postcode":"NE30 2RJ",
    "sg:province":"Tyne and Wear",
    "sg:tags":[
        "home"
    ],
    "wof:name":"Age Concern",
    "wof:placetype":"venue"
},
  "geometry": {"coordinates":[-1.445087,55.011608],"type":"Point"}
}