{
  "type": "Feature",
  "properties": {
    "iso:country":"GB",
    "sg:address":"3 Oakwood Industrial Park, Gatwick Rd",
    "sg:city":"Crawley",
    "sg:classifiers":[
        {
            "category":"Home & Garden",
            "subcategory":"Building Materials",
            "type":"Retail Goods"
        }
    ],
    "sg:phone":"+44 1293 440046",
    "sg:postcode":"RH10 2AZ",
    "sg:province":"Surrey",
    "sg:tags":[
        "furnishers",
        "bathroom",
        "planner"
    ],
    "wof:name":"O",
    "wof:placetype":"venue"
},
  "geometry": {"coordinates":[-0.184753,51.118458],"type":"Point"}
}