{
  "type": "Feature",
  "properties": {
    "addr:full":"122 Lingfoot Crescent Sheffield Derbyshire S8 8DB",
    "addr:housenumber":"122",
    "addr:postcode":"s8 8db",
    "addr:street":"Lingfoot Crescent",
    "iso:country":"GB",
    "sg:address":"122 Lingfoot Crescent",
    "sg:city":"Sheffield",
    "sg:classifiers":[
        {
            "category":"Professional",
            "subcategory":"Detective & Security Services",
            "type":"Services"
        }
    ],
    "sg:phone":"+44 114 237 3489",
    "sg:postcode":"S8 8DB",
    "sg:province":"Derbyshire",
    "sg:tags":[
        "car"
    ],
    "wof:name":"Unimark",
    "wof:placetype":"venue"
},
  "geometry": {"coordinates":[-1.462691,53.321041],"type":"Point"}
}