{
  "type": "Feature",
  "properties": {
    "addr:full":"Asleigh Court, 20 Fountain Road Birmingham West Midlands B17 8NL",
    "addr:housenumber":"20",
    "addr:postcode":"b17 8nl",
    "addr:street":"Fountain Road",
    "iso:country":"GB",
    "sg:address":"Asleigh Court, 20 Fountain Road",
    "sg:city":"Birmingham",
    "sg:classifiers":[
        {
            "category":"Social Services",
            "subcategory":"Retirement Home",
            "type":"Services"
        }
    ],
    "sg:phone":"+44 121 420 1118",
    "sg:postcode":"B17 8NL",
    "sg:province":"West Midlands",
    "sg:tags":[
        "rest"
    ],
    "wof:name":"Ashleigh Court Residential Home",
    "wof:placetype":"venue"
},
  "geometry": {"coordinates":[-1.9559489489,52.4741249084],"type":"Point"}
}