{
  "type": "Feature",
  "properties": {
    "iso:country":"GB",
    "sg:address":"122 Widemarsh Street",
    "sg:city":"Hereford",
    "sg:classifiers":[
        {
            "category":"Autos & Motor Vehicles",
            "subcategory":"Auto Supplies",
            "type":"Retail Goods"
        }
    ],
    "sg:phone":"+44 1432 269348",
    "sg:postcode":"HR4 9HN",
    "sg:province":"Herefordshire",
    "sg:tags":[
        "tyre"
    ],
    "wof:name":"National Tyres and Autocare",
    "wof:placetype":"venue"
},
  "geometry": {"coordinates":[-2.7142848969,52.060546875],"type":"Point"}
}