{
  "type": "Feature",
  "properties": {
    "addr:full":"147-149 Golders Green Road London Greater London NW11 9BN",
    "addr:housenumber":"147-149",
    "addr:postcode":"nw11 9bn",
    "addr:street":"Golders Green Road",
    "iso:country":"GB",
    "sg:address":"147-149 Golders Green Road",
    "sg:city":"London",
    "sg:classifiers":[
        {
            "category":"Travel",
            "subcategory":"Hotels & Motels",
            "type":"Entertainment"
        }
    ],
    "sg:phone":"+44 20 8458 7127",
    "sg:postcode":"NW11 9BN",
    "sg:province":"Greater London",
    "wof:name":"Golders Green Hotel",
    "wof:placetype":"venue"
},
  "geometry": {"coordinates":[-0.2035990059,51.5753707886],"type":"Point"}
}