{
  "type": "Feature",
  "properties": {
    "addr:full":"Little Rushett, Rushett La Faversham Kent ME13 0SG",
    "addr:postcode":"me13 0sg",
    "iso:country":"GB",
    "sg:address":"Little Rushett, Rushett La",
    "sg:city":"Faversham",
    "sg:classifiers":[
        {
            "category":"Personal",
            "type":"Services"
        }
    ],
    "sg:phone":"+44 1795 522786",
    "sg:postcode":"ME13 0SG",
    "sg:province":"Kent",
    "sg:tags":[
        "wedding"
    ],
    "wof:name":"Regal Cars",
    "wof:placetype":"venue"
},
  "geometry": {"coordinates":[0.88344,51.309605],"type":"Point"}
}