{
  "type": "Feature",
  "properties": {
    "iso:country":"GB",
    "sg:address":"62 Reddish La",
    "sg:city":"Manchester",
    "sg:classifiers":[
        {
            "category":"Retail",
            "subcategory":"Repair Shop",
            "type":"Services"
        },
        {
            "category":"Real Estate",
            "subcategory":"Real Estate Agent",
            "type":"Services"
        }
    ],
    "sg:postcode":"M18 7JL",
    "sg:province":"Greater Manchester",
    "sg:tags":[
        "maintenance"
    ],
    "wof:name":"Bradley & Hackman",
    "wof:placetype":"venue"
},
  "geometry": {"coordinates":[-2.174309,53.456051],"type":"Point"}
}