{
  "type": "Feature",
  "properties": {
    "addr:full":"Unit 2 Market Hall, Camden Lock London Greater London NW1 8AF",
    "addr:housenumber":"unit 2",
    "addr:postcode":"nw1 8af",
    "addr:street":"Market Hall Camden Lock",
    "iso:country":"GB",
    "sg:address":"Unit 2 Market Hall, Camden Lock",
    "sg:city":"London",
    "sg:classifiers":[
        {
            "category":"Home & Garden",
            "subcategory":"Furniture",
            "type":"Retail Goods"
        }
    ],
    "sg:phone":"+44 20 7267 6000",
    "sg:postcode":"NW1 8AF",
    "sg:province":"Greater London",
    "wof:name":"Karaali Trading Co.",
    "wof:placetype":"venue"
},
  "geometry": {"coordinates":[-0.1462800056,51.5414505005],"type":"Point"}
}