{
  "type": "Feature",
  "properties": {
    "addr:full":"124 Swanside Road Liverpool Merseyside L14 7NW",
    "addr:housenumber":"124",
    "addr:postcode":"l14 7nw",
    "addr:street":"Swanside Road",
    "iso:country":"GB",
    "sg:address":"124 Swanside Road",
    "sg:city":"Liverpool",
    "sg:classifiers":[
        {
            "category":"Bus Charters",
            "type":"Transportation"
        }
    ],
    "sg:phone":"+44 151 220 0790",
    "sg:postcode":"L14 7NW",
    "sg:province":"Merseyside",
    "sg:tags":[
        "hire",
        "coach"
    ],
    "wof:name":"Chauffeurs Travel",
    "wof:placetype":"venue"
},
  "geometry": {"coordinates":[-2.887325,53.413258],"type":"Point"}
}