{
  "type": "Feature",
  "properties": {
    "iso:country":"GB",
    "sg:address":"Milton St",
    "sg:city":"Saltburn By The Sea",
    "sg:classifiers":[
        {
            "category":"Place Of Worship",
            "type":"Public Place"
        }
    ],
    "sg:phone":"+44 1287 650409",
    "sg:postcode":"TS12 1DE",
    "sg:province":"North Yorkshire",
    "wof:name":"Saltburn Methodist Church",
    "wof:placetype":"venue"
},
  "geometry": {"coordinates":[-0.971484,54.584095],"type":"Point"}
}