{
  "type": "Feature",
  "properties": {
    "iso:country":"GB",
    "sg:address":"29 Featherbed Lane",
    "sg:city":"Croydon",
    "sg:classifiers":[
        {
            "category":"Building & Trades",
            "subcategory":"Construction",
            "type":"Services"
        }
    ],
    "sg:postcode":"CR0 9AE",
    "sg:province":"Surrey",
    "sg:tags":[
        "builder"
    ],
    "wof:name":"Burrowfield Contractors Ltd.",
    "wof:placetype":"venue"
},
  "geometry": {"coordinates":[-0.03571,51.349171],"type":"Point"}
}