{
  "type": "Feature",
  "properties": {
    "iso:country":"GB",
    "sg:address":"Ashanti, Treliever Road",
    "sg:city":"Penryn",
    "sg:classifiers":[
        {
            "category":"Utilities",
            "type":"Services"
        }
    ],
    "sg:postcode":"TR10 9EX",
    "sg:province":"Cornwall",
    "sg:tags":[
        "internet"
    ],
    "wof:name":"Telesec Ltd.",
    "wof:placetype":"venue"
},
  "geometry": {"coordinates":[-5.129184,50.172733],"type":"Point"}
}