{
  "type": "Feature",
  "properties": {
    "addr:full":"Trerair, Rock Wadebridge Cornwall PL27 6NL",
    "addr:postcode":"pl27 6nl",
    "iso:country":"GB",
    "sg:address":"Trerair, Rock",
    "sg:city":"Wadebridge",
    "sg:classifiers":[
        {
            "category":"Home & Garden",
            "subcategory":"Household Appliances",
            "type":"Retail Goods"
        }
    ],
    "sg:phone":"+44 1208 862464",
    "sg:postcode":"PL27 6NL",
    "sg:province":"Cornwall",
    "sg:tags":[
        "electrical"
    ],
    "wof:name":"John R Marriott",
    "wof:placetype":"venue"
},
  "geometry": {"coordinates":[-4.9036898613,50.5495262146],"type":"Point"}
}