{
  "type": "Feature",
  "properties": {
    "iso:country":"GB",
    "sg:address":"61 Leicester Road, Thurcaston",
    "sg:city":"Leicester",
    "sg:classifiers":[
        {
            "category":"Communications",
            "type":"Services"
        }
    ],
    "sg:phone":"+44 116 232 3238",
    "sg:postcode":"LE7 7JH",
    "sg:province":"Leicestershire",
    "sg:tags":[
        "tv",
        "video",
        "radio"
    ],
    "wof:name":"Datatech Systems",
    "wof:placetype":"venue"
},
  "geometry": {"coordinates":[-1.154082,52.690681],"type":"Point"}
}