{
  "type": "Feature",
  "properties": {
    "addr:full":"10-12 Southernhay Basildon Essex SS14 1EL",
    "addr:housenumber":"10-12",
    "addr:postcode":"ss14 1el",
    "addr:street":"Southernhay Basildon",
    "iso:country":"GB",
    "sg:address":"10-12 Southernhay",
    "sg:city":"Basildon",
    "sg:classifiers":[
        {
            "category":"Professional",
            "subcategory":"Lawyer & Legal Services",
            "type":"Services"
        }
    ],
    "sg:phone":"+44 1268 289555",
    "sg:postcode":"SS14 1EL",
    "sg:province":"Essex",
    "sg:tags":[
        "solicitor"
    ],
    "wof:name":"Martin Nossel & Co",
    "wof:placetype":"venue"
},
  "geometry": {"coordinates":[0.4627569914,51.5717163086],"type":"Point"}
}