{
  "type": "Feature",
  "properties": {
    "iso:country":"GB",
    "sg:address":"Wootton Hall, Wootton Wawen",
    "sg:city":"Solihull",
    "sg:classifiers":[
        {
            "category":"Shopping",
            "subcategory":"Department Store",
            "type":"Retail Goods"
        },
        {
            "category":"Food & Beverages",
            "subcategory":"Supermarket",
            "type":"Retail Goods"
        },
        {
            "category":"Government",
            "subcategory":"Post Office",
            "type":"Public Place"
        }
    ],
    "sg:phone":"+44 1564 792740",
    "sg:postcode":"B95 6EE",
    "sg:province":"Warwickshire",
    "wof:name":"Wootton Wawen Post Office Stores",
    "wof:placetype":"venue"
},
  "geometry": {"coordinates":[-1.7774089575,52.2667312622],"type":"Point"}
}