{
  "type": "Feature",
  "properties": {
    "addr:full":"419 Poulton Road Fleetwood Lancashire FY7 7JY",
    "addr:housenumber":"419",
    "addr:postcode":"fy7 7jy",
    "addr:street":"Poulton Road",
    "iso:country":"GB",
    "sg:address":"419 Poulton Road",
    "sg:city":"Fleetwood",
    "sg:classifiers":[
        {
            "category":"Health Services",
            "subcategory":"Doctor",
            "type":"Services"
        }
    ],
    "sg:phone":"+44 1253 779113",
    "sg:postcode":"FY7 7JY",
    "sg:province":"Lancashire",
    "sg:tags":[
        "practitioners"
    ],
    "wof:name":"C D Ramesh",
    "wof:placetype":"venue"
},
  "geometry": {"coordinates":[-3.03527,53.918144],"type":"Point"}
}