{
  "type": "Feature",
  "properties": {
    "addr:full":"4 Abbey Grn Bath Bath and North East Somerset BA1 1NW",
    "addr:housenumber":"4",
    "addr:postcode":"ba1 1nw",
    "addr:street":"Abbey Grn",
    "iso:country":"GB",
    "sg:address":"4 Abbey Grn",
    "sg:city":"Bath",
    "sg:classifiers":[
        {
            "category":"Personal",
            "subcategory":"Beauty Salon",
            "type":"Services"
        }
    ],
    "sg:phone":"+44 1225 448900",
    "sg:postcode":"BA1 1NW",
    "sg:province":"Bath and North East Somerset",
    "sg:tags":[
        "unisex",
        "hairdresser"
    ],
    "wof:name":"Imago Health & Beauty Salon",
    "wof:placetype":"venue"
},
  "geometry": {"coordinates":[-2.358809948,51.3803787231],"type":"Point"}
}