{
  "type": "Feature",
  "properties": {
    "iso:country":"GB",
    "sg:address":"18 Market Place",
    "sg:city":"Devizes",
    "sg:classifiers":[
        {
            "category":"Retail",
            "subcategory":"Laundry & Dry Cleaning",
            "type":"Services"
        }
    ],
    "sg:phone":"+44 1380 721654",
    "sg:postcode":"SN10 1JQ",
    "sg:province":"Wiltshire",
    "sg:tags":[
        "launderette"
    ],
    "wof:name":"Market Place Launderette",
    "wof:placetype":"venue"
},
  "geometry": {"coordinates":[-1.995904,51.352276],"type":"Point"}
}