{
  "type": "Feature",
  "properties": {
    "iso:country":"GB",
    "sg:address":"1 Green Road",
    "sg:city":"Kendal",
    "sg:classifiers":[
        {
            "category":"Shopping",
            "subcategory":"News",
            "type":"Retail Goods"
        }
    ],
    "sg:phone":"+44 1539 721976",
    "sg:postcode":"LA9 4QR",
    "sg:province":"Cumbria",
    "sg:tags":[
        "newsagent"
    ],
    "wof:name":"MICHAEL M CLEASBY",
    "wof:placetype":"venue"
},
  "geometry": {"coordinates":[-2.752952,54.332886],"type":"Point"}
}