{
  "type": "Feature",
  "properties": {
    "iso:country":"GB",
    "sg:address":"Eastbourne House, 2 Saxbys Lane",
    "sg:city":"Lingfield",
    "sg:classifiers":[
        {
            "category":"Professional",
            "subcategory":"Accounting & Tax Preparation",
            "type":"Services"
        }
    ],
    "sg:phone":"+44 1342 835612",
    "sg:postcode":"RH7 6DN",
    "sg:province":"Surrey",
    "sg:tags":[
        "accountant"
    ],
    "wof:name":"Levy & Co",
    "wof:placetype":"venue"
},
  "geometry": {"coordinates":[-0.013514,51.1774330139],"type":"Point"}
}