{
  "type": "Feature",
  "properties": {
    "iso:country":"GB",
    "sg:address":"Dysons Wood Farm, Tokers Grn",
    "sg:city":"Reading",
    "sg:classifiers":[
        {
            "category":"Farming",
            "subcategory":"Livestock Farm",
            "type":"Manufacturing & Wholesale Goods"
        }
    ],
    "sg:postcode":"RG4 9EU",
    "sg:province":"Berkshire",
    "sg:tags":[
        "others"
    ],
    "wof:name":"D J  Ronaldson",
    "wof:placetype":"venue"
},
  "geometry": {"coordinates":[-0.9915,51.49308],"type":"Point"}
}