{
  "type": "Feature",
  "properties": {
    "iso:country":"GB",
    "sg:address":"1 Southalls Lane",
    "sg:city":"Dudley",
    "sg:classifiers":[
        {
            "category":"Personal",
            "subcategory":"Beauty Salon",
            "type":"Services"
        }
    ],
    "sg:phone":"+44 1384 234334",
    "sg:postcode":"DY1 1UL",
    "sg:province":"West Midlands",
    "sg:tags":[
        "unisex",
        "hairdresser"
    ],
    "wof:name":"The Chair",
    "wof:placetype":"venue"
},
  "geometry": {"coordinates":[-2.0897738934,52.5108146667],"type":"Point"}
}