{
  "type": "Feature",
  "properties": {
    "addr:full":"280 Baldwins Lane Birmingham West Midlands B28 0XB",
    "addr:housenumber":"280",
    "addr:postcode":"b28 0xb",
    "addr:street":"Baldwins Lane",
    "iso:country":"GB",
    "sg:address":"280 Baldwins Lane",
    "sg:city":"Birmingham",
    "sg:classifiers":[
        {
            "category":"Personal",
            "subcategory":"Beauty Salon",
            "type":"Services"
        }
    ],
    "sg:postcode":"B28 0XB",
    "sg:province":"West Midlands",
    "sg:tags":[
        "unisex",
        "hairdresser"
    ],
    "wof:name":"Debonair Hair Studios",
    "wof:placetype":"venue"
},
  "geometry": {"coordinates":[-1.844316,52.414192],"type":"Point"}
}