{
  "type": "Feature",
  "properties": {
    "addr:full":"448 Bull Ring Centre Birmingham West Midlands B5 4PS",
    "addr:housenumber":"448",
    "addr:postcode":"b5 4ps",
    "addr:street":"Bull Ring",
    "iso:country":"GB",
    "sg:address":"448 Bull Ring Centre",
    "sg:city":"Birmingham",
    "sg:classifiers":[
        {
            "category":"Shopping",
            "subcategory":"Clothing, Apparel, & Fashions",
            "type":"Retail Goods"
        }
    ],
    "sg:phone":"+44 121 631 1187",
    "sg:postcode":"B5 4PS",
    "sg:province":"West Midlands",
    "sg:tags":[
        "shop"
    ],
    "wof:name":"Kongo Clothing",
    "wof:placetype":"venue"
},
  "geometry": {"coordinates":[-1.8950200081,52.4767990112],"type":"Point"}
}