{
  "type": "Feature",
  "properties": {
    "addr:full":"13 High St, Wanstead London Greater London E11 2AA",
    "addr:housenumber":"13",
    "addr:postcode":"e11 2aa",
    "addr:street":"High St",
    "iso:country":"GB",
    "sg:address":"13 High St, Wanstead",
    "sg:city":"London",
    "sg:classifiers":[
        {
            "category":"Organizations",
            "subcategory":"Membership Organization",
            "type":"Services"
        }
    ],
    "sg:postcode":"E11 2AA",
    "sg:province":"Greater London",
    "sg:tags":[
        "club"
    ],
    "wof:name":"B.H. Management Ltd",
    "wof:placetype":"venue"
},
  "geometry": {"coordinates":[0.02453,51.579529],"type":"Point"}
}