{
  "type": "Feature",
  "properties": {
    "iso:country":"GB",
    "sg:address":"29 Plymouth Rd",
    "sg:city":"Sheffield",
    "sg:classifiers":[
        {
            "category":"Banks & Credit Unions",
            "subcategory":"Bank",
            "type":"Services"
        }
    ],
    "sg:phone":"+44 114 281 2141",
    "sg:postcode":"S7 2DE",
    "sg:province":"South Yorkshire",
    "sg:tags":[
        "broker",
        "mortgage"
    ],
    "wof:name":"Mortgage Advice",
    "wof:placetype":"venue"
},
  "geometry": {"coordinates":[-1.488481,53.351948],"type":"Point"}
}