{
  "type": "Feature",
  "properties": {
    "iso:country":"GB",
    "sg:address":"12 Glazert Park Drive, Lennoxtown",
    "sg:city":"Glasgow",
    "sg:classifiers":[
        {
            "category":"Building & Trades",
            "subcategory":"Landscaping Services",
            "type":"Services"
        }
    ],
    "sg:phone":"+44 1389 381318",
    "sg:postcode":"G66 7EY",
    "sg:province":"East Dunbartonshire",
    "sg:tags":[
        "landscape",
        "contractor"
    ],
    "wof:name":"B & B Landscapes",
    "wof:placetype":"venue"
},
  "geometry": {"coordinates":[-4.194323,55.969654],"type":"Point"}
}