{
  "type": "Feature",
  "properties": {
    "iso:country":"GB",
    "sg:address":"Unit 71, Murdock Rd",
    "sg:city":"Bedford",
    "sg:classifiers":[
        {
            "category":"Wholesale",
            "subcategory":"Meat",
            "type":"Manufacturing & Wholesale Goods"
        }
    ],
    "sg:phone":"+44 1234 213200",
    "sg:postcode":"MK41 7PL",
    "sg:province":"Bedfordshire",
    "sg:tags":[
        "-"
    ],
    "wof:name":"Manton Wholesale Meats Ltd",
    "wof:placetype":"venue"
},
  "geometry": {"coordinates":[-0.473625,52.154575],"type":"Point"}
}