{
  "type": "Feature",
  "properties": {
    "addr:full":"3 Osborne Villas Newcastle-upon-tyne Tyne and Wear NE2 1JU",
    "addr:housenumber":"3",
    "addr:postcode":"ne2 1ju",
    "addr:street":"Osborne Villas",
    "iso:country":"GB",
    "sg:address":"3 Osborne Villas",
    "sg:city":"Newcastle-upon-tyne",
    "sg:classifiers":[
        {
            "category":"Professional",
            "subcategory":"Art Services",
            "type":"Services"
        }
    ],
    "sg:phone":"+44 191 212 0812",
    "sg:postcode":"NE2 1JU",
    "sg:province":"Tyne and Wear",
    "sg:tags":[
        "consultant",
        "design"
    ],
    "wof:name":"Donald Stewart Associates",
    "wof:placetype":"venue"
},
  "geometry": {"coordinates":[-1.604096,54.98225],"type":"Point"}
}