{
  "type": "Feature",
  "properties": {
    "addr:full":"46 Salway Drive, Salway Ash Bridport Dorset DT6 5LD",
    "addr:housenumber":"46",
    "addr:postcode":"dt6 5ld",
    "addr:street":"Salway Drive Salway",
    "iso:country":"GB",
    "sg:address":"46 Salway Drive, Salway Ash",
    "sg:city":"Bridport",
    "sg:classifiers":[
        {
            "category":"Shopping",
            "subcategory":"Computers & Home Electronics",
            "type":"Retail Goods"
        },
        {
            "category":"Professional",
            "subcategory":"Computer Services",
            "type":"Services"
        }
    ],
    "sg:phone":"+44 1308 488509",
    "sg:postcode":"DT6 5LD",
    "sg:province":"Dorset",
    "sg:tags":[
        "software",
        "sales",
        "system"
    ],
    "wof:name":"Centaur Computer Solutions Ltd",
    "wof:placetype":"venue"
},
  "geometry": {"coordinates":[-2.772219,50.767902],"type":"Point"}
}