{
  "type": "Feature",
  "properties": {
    "addr:full":"Unit 11a, City Business Centre Sth Bermondsey Greater London SE16 2XB",
    "addr:housenumber":"unit 11a city business centre",
    "addr:postcode":"se16 2xb",
    "addr:street":"Sth Bermondsey",
    "iso:country":"GB",
    "sg:address":"Unit 11a, City Business Centre",
    "sg:city":"Sth Bermondsey",
    "sg:classifiers":[
        {
            "category":"Professional",
            "subcategory":"Computer Services",
            "type":"Services"
        }
    ],
    "sg:phone":"+44 20 7252 3488",
    "sg:postcode":"SE16 2XB",
    "sg:province":"Greater London",
    "sg:tags":[
        "consultant"
    ],
    "wof:name":"CCS Computer Services",
    "wof:placetype":"venue"
},
  "geometry": {"coordinates":[-0.05454,51.4986],"type":"Point"}
}