{
  "type": "Feature",
  "properties": {
    "addr:full":"43 Moorfield Rd, Duxford Cambridge Cambridgeshire CB2 4PP",
    "addr:housenumber":"43",
    "addr:postcode":"cb2 4pp",
    "addr:street":"Moorfield Rd",
    "iso:country":"GB",
    "sg:address":"43 Moorfield Rd, Duxford",
    "sg:city":"Cambridge",
    "sg:classifiers":[
        {
            "category":"Personal",
            "subcategory":"Beauty Salon",
            "type":"Services"
        }
    ],
    "sg:postcode":"CB2 4PP",
    "sg:province":"Cambridgeshire",
    "sg:tags":[
        "unisex",
        "hairdresser"
    ],
    "wof:name":"O'Brian,Jennifer,",
    "wof:placetype":"venue"
},
  "geometry": {"coordinates":[0.158548,52.096249],"type":"Point"}
}