{
  "type": "Feature",
  "properties": {
    "addr:full":"10 Wood Gardens Alderley Edge Cheshire SK9 7PL",
    "addr:housenumber":"10",
    "addr:postcode":"sk9 7pl",
    "addr:street":"Wood Gardens",
    "iso:country":"GB",
    "sg:address":"10 Wood Gardens",
    "sg:city":"Alderley Edge",
    "sg:classifiers":[
        {
            "category":"Shopping",
            "subcategory":"Department Store",
            "type":"Retail Goods"
        }
    ],
    "sg:phone":"+44 1625 584828",
    "sg:postcode":"SK9 7PL",
    "sg:province":"Cheshire",
    "wof:name":"The Corner Shop",
    "wof:placetype":"venue"
},
  "geometry": {"coordinates":[-2.2318599224,53.3078384399],"type":"Point"}
}