{
  "type": "Feature",
  "properties": {
    "iso:country":"GB",
    "sg:address":"31 Hillingdon Hill",
    "sg:city":"Uxbridge",
    "sg:classifiers":[
        {
            "category":"Building & Trades",
            "subcategory":"Construction",
            "type":"Services"
        }
    ],
    "sg:phone":"+44 1895 236933",
    "sg:postcode":"UB10 0JF",
    "sg:province":"Greater London",
    "sg:tags":[
        "dry",
        "lining",
        "plasterers",
        "screeders"
    ],
    "wof:name":"R B Jones",
    "wof:placetype":"venue"
},
  "geometry": {"coordinates":[-0.466732,51.535679],"type":"Point"}
}