{
  "type": "Feature",
  "properties": {
    "iso:country":"GB",
    "sg:address":"Alana Moorings, Manna Road",
    "sg:city":"Bembridge",
    "sg:classifiers":[
        {
            "category":"Government",
            "subcategory":"Fire Station",
            "type":"Public Place"
        },
        {
            "category":"Home & Garden",
            "subcategory":"Garden Supply",
            "type":"Retail Goods"
        }
    ],
    "sg:postcode":"PO35 5UZ",
    "sg:province":"Isle of Wight",
    "sg:tags":[
        "w'sale",
        "lighting",
        "wholesale"
    ],
    "wof:name":"Island Lamp Co",
    "wof:placetype":"venue"
},
  "geometry": {"coordinates":[-1.087957,50.68961],"type":"Point"}
}