{
  "type": "Feature",
  "properties": {
    "addr:full":"411 Petre St Sheffield South Yorkshire S4 8LL",
    "addr:housenumber":"411",
    "addr:postcode":"s4 8ll",
    "addr:street":"Petre St",
    "iso:country":"GB",
    "sg:address":"411 Petre St",
    "sg:city":"Sheffield",
    "sg:classifiers":[
        {
            "category":"Professional",
            "type":"Services"
        }
    ],
    "sg:phone":"+44 114 261 8000",
    "sg:postcode":"S4 8LL",
    "sg:province":"South Yorkshire",
    "sg:tags":[
        "auctioneer"
    ],
    "wof:name":"Eadon Lockwood & Riddle Residential",
    "wof:placetype":"venue"
},
  "geometry": {"coordinates":[-1.4430849552,53.4033584595],"type":"Point"}
}