{
  "type": "Feature",
  "properties": {
    "addr:full":"23 Borestone Crescent Stirling Falkirk FK7 9BG",
    "addr:housenumber":"23",
    "addr:postcode":"fk7 9bg",
    "addr:street":"Borestone Crescent",
    "iso:country":"GB",
    "sg:address":"23 Borestone Crescent",
    "sg:city":"Stirling",
    "sg:classifiers":[
        {
            "category":"Retail",
            "subcategory":"Auto Repair",
            "type":"Services"
        }
    ],
    "sg:phone":"+44 1786 471299",
    "sg:postcode":"FK7 9BG",
    "sg:province":"Falkirk",
    "sg:tags":[
        "modification",
        "garage"
    ],
    "wof:name":"H M C Fleet Service",
    "wof:placetype":"venue"
},
  "geometry": {"coordinates":[-3.968164,56.109135],"type":"Point"}
}