{
  "type": "Feature",
  "properties": {
    "iso:country":"GB",
    "sg:address":"2a The Lilacs",
    "sg:city":"Wokingham",
    "sg:classifiers":[
        {
            "category":"Building & Trades",
            "subcategory":"Construction",
            "type":"Services"
        }
    ],
    "sg:phone":"+44 118 977 3409",
    "sg:postcode":"RG41 4UT",
    "sg:province":"Berkshire",
    "sg:tags":[
        "builder"
    ],
    "wof:name":"Galibar Builders",
    "wof:placetype":"venue"
},
  "geometry": {"coordinates":[-0.87366,51.401207],"type":"Point"}
}