{
  "type": "Feature",
  "properties": {
    "addr:full":"Huddersfield Rd Barnsley South Yorkshire S75 1HA",
    "addr:postcode":"s75 1ha",
    "addr:street":"Huddersfield Rd;Yorkshire",
    "iso:country":"GB",
    "sg:address":"Huddersfield Rd",
    "sg:city":"Barnsley",
    "sg:classifiers":[
        {
            "category":"Bars & Pubs",
            "type":"Food & Drink"
        }
    ],
    "sg:phone":"+44 1226 282933",
    "sg:postcode":"S75 1HA",
    "sg:province":"South Yorkshire",
    "sg:tags":[
        "pubs",
        "inn"
    ],
    "wof:name":"Wilthorpe The",
    "wof:placetype":"venue"
},
  "geometry": {"coordinates":[-1.4993389845,53.5645446777],"type":"Point"}
}