{
  "type": "Feature",
  "properties": {
    "addr:full":"14 High Street, Potterspury Towcester Buckinghamshire NN12 7PQ",
    "addr:housenumber":"14",
    "addr:postcode":"nn12 7pq",
    "addr:street":"High Street",
    "iso:country":"GB",
    "sg:address":"14 High Street, Potterspury",
    "sg:city":"Towcester",
    "sg:classifiers":[
        {
            "category":"Professional",
            "subcategory":"Management & Consulting",
            "type":"Services"
        }
    ],
    "sg:postcode":"NN12 7PQ",
    "sg:province":"Buckinghamshire",
    "sg:tags":[
        "project"
    ],
    "wof:name":"Watson Whittaker Partnership",
    "wof:placetype":"venue"
},
  "geometry": {"coordinates":[-0.94426,52.103924],"type":"Point"}
}