{
  "type": "Feature",
  "properties": {
    "iso:country":"GB",
    "sg:address":"Titton",
    "sg:city":"Stourport On Severn",
    "sg:classifiers":[
        {
            "category":"Building & Trades",
            "subcategory":"Landscaping Services",
            "type":"Services"
        },
        {
            "category":"Home & Garden",
            "subcategory":"Garden Supply",
            "type":"Retail Goods"
        }
    ],
    "sg:phone":"+44 1299 828909",
    "sg:postcode":"DY13 9RQ",
    "sg:province":"Worcestershire",
    "sg:tags":[
        "nurseryman",
        "tree",
        "shrub"
    ],
    "wof:name":"Lincomb Nurseries",
    "wof:placetype":"venue"
},
  "geometry": {"coordinates":[-2.25674,52.323689],"type":"Point"}
}