{
  "type": "Feature",
  "properties": {
    "iso:country":"GB",
    "sg:address":"8 Hursley Road, Chandlers Ford",
    "sg:city":"Eastleigh",
    "sg:classifiers":[
        {
            "category":"Personal",
            "subcategory":"Beauty Salon",
            "type":"Services"
        }
    ],
    "sg:phone":"+44 23 8025 4231",
    "sg:postcode":"SO53 2FU",
    "sg:province":"Hampshire",
    "sg:tags":[
        "unisex",
        "hairdresser"
    ],
    "wof:name":"Brook Hairdressers",
    "wof:placetype":"venue"
},
  "geometry": {"coordinates":[-1.384948,50.98394],"type":"Point"}
}