{
  "type": "Feature",
  "properties": {
    "iso:country":"GB",
    "sg:address":"Church Institute, Lenten Pool",
    "sg:city":"Denbigh",
    "sg:classifiers":[
        {
            "category":"Professional",
            "subcategory":"Lawyer & Legal Services",
            "type":"Services"
        }
    ],
    "sg:phone":"+44 1745 814336",
    "sg:postcode":"LL16 3LG",
    "sg:province":"Conwy",
    "sg:tags":[
        "advice",
        "counselling"
    ],
    "wof:name":"Citizens Advice Bureau",
    "wof:placetype":"venue"
},
  "geometry": {"coordinates":[-3.421149,53.183411],"type":"Point"}
}