{
  "type": "Feature",
  "properties": {
    "iso:country":"GB",
    "sg:address":"Four Wantz Corner, Fyfield Rd",
    "sg:city":"Ongar",
    "sg:classifiers":[
        {
            "category":"Home & Garden",
            "subcategory":"Home Furnishings",
            "type":"Retail Goods"
        },
        {
            "category":"Retail",
            "subcategory":"Storage",
            "type":"Services"
        }
    ],
    "sg:phone":"+44 1277 362987",
    "sg:postcode":"CM5 0AH",
    "sg:province":"Essex",
    "sg:tags":[
        "household",
        "furniture",
        "patio",
        "removal"
    ],
    "wof:name":"Ongar Sale Rooms Ltd.",
    "wof:placetype":"venue"
},
  "geometry": {"coordinates":[0.2447409928,51.7127685547],"type":"Point"}
}