{
  "type": "Feature",
  "properties": {
    "addr:full":"11 Anvil Crescent Broadstone Dorset BH18 9DX",
    "addr:housenumber":"11",
    "addr:postcode":"bh18 9dx",
    "addr:street":"Anvil Crescent",
    "iso:country":"GB",
    "sg:address":"11 Anvil Crescent",
    "sg:city":"Broadstone",
    "sg:classifiers":[
        {
            "category":"Professional",
            "subcategory":"Engineering",
            "type":"Services"
        }
    ],
    "sg:phone":"+44 1202 659300",
    "sg:postcode":"BH18 9DX",
    "sg:province":"Dorset",
    "sg:tags":[
        "civil",
        "engineer"
    ],
    "wof:name":"Richard Russell",
    "wof:placetype":"venue"
},
  "geometry": {"coordinates":[-2.005721,50.765278],"type":"Point"}
}