{
  "type": "Feature",
  "properties": {
    "addr:full":"86 Labrador Drive Poole Dorset BH15 1UY",
    "addr:housenumber":"86",
    "addr:postcode":"bh15 1uy",
    "addr:street":"Labrador Drive",
    "iso:country":"GB",
    "sg:address":"86 Labrador Drive",
    "sg:city":"Poole",
    "sg:classifiers":[
        {
            "category":"Organizations",
            "subcategory":"Membership Organization",
            "type":"Services"
        }
    ],
    "sg:postcode":"BH15 1UY",
    "sg:province":"Dorset",
    "sg:tags":[
        "club"
    ],
    "wof:name":"Tarrant (Bournemouth) Management Company",
    "wof:placetype":"venue"
},
  "geometry": {"coordinates":[-1.974256,50.712429],"type":"Point"}
}