{
  "type": "Feature",
  "properties": {
    "addr:full":"Norwich Union House Northampton Northamptonshire NN1 2DY",
    "addr:postcode":"nn1 2dy",
    "iso:country":"GB",
    "sg:address":"Norwich Union House",
    "sg:city":"Northampton",
    "sg:classifiers":[
        {
            "category":"Banks & Credit Unions",
            "subcategory":"Financial Services",
            "type":"Services"
        }
    ],
    "sg:postcode":"NN1 2DY",
    "sg:province":"Northamptonshire",
    "sg:tags":[
        "consultant"
    ],
    "wof:name":"General Guarantee Corporation Ltd.",
    "wof:placetype":"venue"
},
  "geometry": {"coordinates":[-0.903703,52.242229],"type":"Point"}
}