{
  "type": "Feature",
  "properties": {
    "addr:full":"14 Ashdown Road High Wycombe Buckinghamshire HP13 7JD",
    "addr:housenumber":"14",
    "addr:postcode":"hp13 7jd",
    "addr:street":"Ashdown Road",
    "iso:country":"GB",
    "sg:address":"14 Ashdown Road",
    "sg:city":"High Wycombe",
    "sg:classifiers":[
        {
            "category":"Retail",
            "subcategory":"Auto Repair",
            "type":"Services"
        }
    ],
    "sg:postcode":"HP13 7JD",
    "sg:province":"Buckinghamshire",
    "sg:tags":[
        "modification",
        "garage"
    ],
    "wof:name":"Paul's Mobile Services",
    "wof:placetype":"venue"
},
  "geometry": {"coordinates":[-0.714098,51.633617],"type":"Point"}
}