{
  "type": "Feature",
  "properties": {
    "iso:country":"GB",
    "sg:address":"Suite B Kirkgate Business Centre, Chantry Bridge",
    "sg:city":"Wakefield",
    "sg:classifiers":[
        {
            "category":"Professional",
            "subcategory":"Business Services",
            "type":"Services"
        }
    ],
    "sg:phone":"+44 1924 200639",
    "sg:postcode":"WF1 5DL",
    "sg:province":"West Yorkshire",
    "sg:tags":[
        "import",
        "export",
        "agent"
    ],
    "wof:name":"Ample Imports",
    "wof:placetype":"venue"
},
  "geometry": {"coordinates":[-1.4906640053,53.6772842407],"type":"Point"}
}