{
  "type": "Feature",
  "properties": {
    "iso:country":"GB",
    "sg:address":"74 Botley Road, Park Gate",
    "sg:city":"Southampton",
    "sg:classifiers":[
        {
            "category":"Shopping",
            "subcategory":"Used Merchandise",
            "type":"Retail Goods"
        }
    ],
    "sg:phone":"+44 1489 602757",
    "sg:postcode":"SO31 1BA",
    "sg:province":"Hampshire",
    "sg:tags":[
        "shop",
        "second-hand"
    ],
    "wof:name":"Second Thoughts Pour Homme",
    "wof:placetype":"venue"
},
  "geometry": {"coordinates":[-1.2678099871,50.8739395142],"type":"Point"}
}