{
  "type": "Feature",
  "properties": {
    "addr:full":"Carter Street, Fordham Ely Cambridgeshire CB7 5NG",
    "addr:postcode":"cb7 5ng",
    "addr:street":"Carter Street",
    "iso:country":"GB",
    "sg:address":"Carter Street, Fordham",
    "sg:city":"Ely",
    "sg:classifiers":[
        {
            "category":"Autos & Motor Vehicles",
            "subcategory":"Fuel & Gas Station",
            "type":"Retail Goods"
        },
        {
            "category":"Retail",
            "subcategory":"Auto Repair",
            "type":"Services"
        }
    ],
    "sg:phone":"+44 1638 720650",
    "sg:postcode":"CB7 5NG",
    "sg:province":"Cambridgeshire",
    "sg:tags":[
        "petrol",
        "garage",
        "filling",
        "modification",
        "related"
    ],
    "wof:name":"CARTER STREET GARAGES LTD",
    "wof:placetype":"venue"
},
  "geometry": {"coordinates":[0.3840860128,52.3114318848],"type":"Point"}
}