{
  "type": "Feature",
  "properties": {
    "iso:country":"GB",
    "sg:address":"Chalkley Bush Farm, Handscombe End Road, Shillington",
    "sg:city":"Hitchin",
    "sg:classifiers":[
        {
            "category":"Manufacturing",
            "subcategory":"Metals",
            "type":"Manufacturing & Wholesale Goods"
        },
        {
            "category":"Manufacturing",
            "subcategory":"Petroleum Products",
            "type":"Manufacturing & Wholesale Goods"
        }
    ],
    "sg:postcode":"SG5 3HL",
    "sg:province":"Bedfordshire",
    "sg:tags":[
        "steel",
        "double",
        "glazing",
        "erectors",
        "fabricator"
    ],
    "wof:name":"Hanscombe Sealed Units",
    "wof:placetype":"venue"
},
  "geometry": {"coordinates":[-0.3595879972,51.9942855835],"type":"Point"}
}