{
  "type": "Feature",
  "properties": {
    "addr:full":"144 Dalsetter Ave Glasgow Glasgow City G15 8SZ",
    "addr:housenumber":"144",
    "addr:postcode":"g15 8sz",
    "addr:street":"Dalsetter Ave",
    "iso:country":"GB",
    "sg:address":"144 Dalsetter Ave",
    "sg:city":"Glasgow",
    "sg:classifiers":[
        {
            "category":"Retail",
            "subcategory":"Auto Repair",
            "type":"Services"
        }
    ],
    "sg:postcode":"G15 8SZ",
    "sg:province":"Glasgow City",
    "sg:tags":[
        "modification",
        "garage"
    ],
    "wof:name":"Jones,Alistair,",
    "wof:placetype":"venue"
},
  "geometry": {"coordinates":[-4.3700251579,55.9063873291],"type":"Point"}
}