{
  "type": "Feature",
  "properties": {
    "addr:full":"Heddon Way, Middlefields Industrial Estate South Shields Tyne and Wear NE34 0NT",
    "addr:postcode":"ne34 0nt",
    "addr:street":"Heddon Way Middlefields Industrial Estate",
    "iso:country":"GB",
    "sg:address":"Heddon Way, Middlefields Industrial Estate",
    "sg:city":"South Shields",
    "sg:classifiers":[
        {
            "category":"Food & Beverages",
            "subcategory":"Supermarket",
            "type":"Retail Goods"
        },
        {
            "category":"Food & Beverages",
            "subcategory":"Meat & Fish",
            "type":"Retail Goods"
        }
    ],
    "sg:phone":"+44 191 456 3540",
    "sg:postcode":"NE34 0NT",
    "sg:province":"Tyne and Wear",
    "sg:tags":[
        "frozen",
        "butcher"
    ],
    "wof:name":"M I Dickson Ltd",
    "wof:placetype":"venue"
},
  "geometry": {"coordinates":[-1.444939971,54.9752731323],"type":"Point"}
}