{
  "type": "Feature",
  "properties": {
    "iso:country":"GB",
    "sg:address":"Welsh Bridge, Ditton Priors",
    "sg:city":"Bridgnorth",
    "sg:classifiers":[
        {
            "category":"Professional",
            "type":"Services"
        }
    ],
    "sg:phone":"+44 1743 231212",
    "sg:postcode":"WV16 6SQ",
    "sg:province":"Shropshire",
    "sg:tags":[
        "auctioneer"
    ],
    "wof:name":"Halls Fine Art Auctions",
    "wof:placetype":"venue"
},
  "geometry": {"coordinates":[-2.5784900188,52.4997062683],"type":"Point"}
}