{
  "type": "Feature",
  "properties": {
    "iso:country":"GB",
    "sg:address":"Care Of Stafford College, Earl St",
    "sg:city":"Stafford",
    "sg:classifiers":[
        {
            "category":"Farming",
            "subcategory":"Nursery",
            "type":"Manufacturing & Wholesale Goods"
        }
    ],
    "sg:phone":"+44 1785 223800",
    "sg:postcode":"ST16 2QR",
    "sg:province":"Staffordshire",
    "sg:tags":[
        "creche"
    ],
    "wof:name":"Penguins Nursery",
    "wof:placetype":"venue"
},
  "geometry": {"coordinates":[-2.1217679977,52.8039588928],"type":"Point"}
}