{
  "type": "Feature",
  "properties": {
    "iso:country":"GB",
    "sg:address":"10 Buttermere Drive, Heron Hill",
    "sg:city":"Kendal",
    "sg:classifiers":[
        {
            "category":"Professional",
            "subcategory":"Computer Services",
            "type":"Services"
        }
    ],
    "sg:phone":"+44 1539 723947",
    "sg:postcode":"LA9 7PA",
    "sg:province":"Cumbria",
    "sg:tags":[
        "consultant"
    ],
    "wof:name":"Strongdivide Ltd.",
    "wof:placetype":"venue"
},
  "geometry": {"coordinates":[-2.7312738895,54.3146743774],"type":"Point"}
}