{
  "type": "Feature",
  "properties": {
    "addr:full":"44 Elmhurst Avenue Northampton Northamptonshire NN3 2LD",
    "addr:housenumber":"44",
    "addr:postcode":"nn3 2ld",
    "addr:street":"Elmhurst Avenue",
    "iso:country":"GB",
    "sg:address":"44 Elmhurst Avenue",
    "sg:city":"Northampton",
    "sg:classifiers":[
        {
            "category":"Building & Trades",
            "subcategory":"Construction",
            "type":"Services"
        }
    ],
    "sg:phone":"+44 1604 405745",
    "sg:postcode":"NN3 2LD",
    "sg:province":"Northamptonshire",
    "sg:tags":[
        "glazier"
    ],
    "wof:name":"William Walter Warnes",
    "wof:placetype":"venue"
},
  "geometry": {"coordinates":[-0.8670290112,52.259059906],"type":"Point"}
}