{
  "type": "Feature",
  "properties": {
    "iso:country":"GB",
    "sg:address":"226 Eastern Avenue",
    "sg:city":"Ilford",
    "sg:classifiers":[
        {
            "category":"Professional",
            "type":"Services"
        },
        {
            "category":"Professional",
            "subcategory":"Art Services",
            "type":"Services"
        }
    ],
    "sg:phone":"+44 20 8554 5205",
    "sg:postcode":"IG4 5AB",
    "sg:province":"Essex",
    "sg:tags":[
        "interior",
        "furnishers",
        "designer"
    ],
    "wof:name":"Decor Plus Interiors Ltd",
    "wof:placetype":"venue"
},
  "geometry": {"coordinates":[0.053755,51.576103],"type":"Point"}
}