{
  "type": "Feature",
  "properties": {
    "addr:full":"Unit 3 Yarmouth Business Park, Suffolk Road Great Yarmouth Norfolk NR31 0ER",
    "addr:housenumber":"unit 3",
    "addr:postcode":"nr31 0er",
    "addr:street":"Yarmouth Business Park Suffolk Road",
    "iso:country":"GB",
    "sg:address":"Unit 3 Yarmouth Business Park, Suffolk Road",
    "sg:city":"Great Yarmouth",
    "sg:classifiers":[
        {
            "category":"Utilities",
            "subcategory":"Telephone",
            "type":"Services"
        }
    ],
    "sg:phone":"+44 1493 441187",
    "sg:postcode":"NR31 0ER",
    "sg:province":"Norfolk",
    "sg:tags":[
        "telecommunication"
    ],
    "wof:name":"B J Communications",
    "wof:placetype":"venue"
},
  "geometry": {"coordinates":[1.72055,52.595409],"type":"Point"}
}