{
  "type": "Feature",
  "properties": {
    "addr:full":"Derwentwater Road Gateshead Tyne and Wear NE8 2SJ",
    "addr:postcode":"ne8 2sj",
    "addr:street":"Derwentwater Road",
    "iso:country":"GB",
    "sg:address":"Derwentwater Road",
    "sg:city":"Gateshead",
    "sg:classifiers":[
        {
            "category":"Organizations",
            "subcategory":"Community Association",
            "type":"Services"
        },
        {
            "category":"Organizations",
            "subcategory":"Membership Organization",
            "type":"Services"
        }
    ],
    "sg:phone":"+44 191 420 0921",
    "sg:postcode":"NE8 2SJ",
    "sg:province":"Tyne and Wear",
    "sg:tags":[
        "club",
        "social"
    ],
    "wof:name":"Teams & District Social Club Ltd.",
    "wof:placetype":"venue"
},
  "geometry": {"coordinates":[-1.620834,54.954594],"type":"Point"}
}