{
  "type": "Feature",
  "properties": {
    "iso:country":"GB",
    "sg:address":"East Gate, White Lund Industrial Estate",
    "sg:city":"Morecambe",
    "sg:classifiers":[
        {
            "category":"Retail",
            "subcategory":"Auto Repair",
            "type":"Services"
        }
    ],
    "sg:phone":"+44 1524 34422",
    "sg:postcode":"LA3 3DY",
    "sg:province":"Lancashire",
    "sg:tags":[
        "bodybuilder",
        "repairer"
    ],
    "wof:name":"van Bodies (Lancs) Ltd.",
    "wof:placetype":"venue"
},
  "geometry": {"coordinates":[-2.834924,54.059135],"type":"Point"}
}