{
  "type": "Feature",
  "properties": {
    "addr:full":"Unit 2 Industrial Estate, Dunvegan Road Portree Highland IV51 9HD",
    "addr:housenumber":"unit 2",
    "addr:postcode":"iv51 9hd",
    "addr:street":"Industrial Estate Dunvegan Road",
    "iso:country":"GB",
    "sg:address":"Unit 2 Industrial Estate, Dunvegan Road",
    "sg:city":"Portree",
    "sg:classifiers":[
        {
            "category":"Retail",
            "subcategory":"Repair Shop",
            "type":"Services"
        }
    ],
    "sg:phone":"+44 1478 612600",
    "sg:postcode":"IV51 9HD",
    "sg:province":"Highland",
    "sg:tags":[
        "radio",
        "television",
        "video"
    ],
    "wof:name":"Malcolm G Fawkes",
    "wof:placetype":"venue"
},
  "geometry": {"coordinates":[-6.196135,57.412785],"type":"Point"}
}