{
  "type": "Feature",
  "properties": {
    "iso:country":"GB",
    "sg:address":"Mead Park",
    "sg:city":"Slough",
    "sg:classifiers":[
        {
            "category":"Banks & Credit Unions",
            "subcategory":"Financial Services",
            "type":"Services"
        }
    ],
    "sg:postcode":"SL3 8AL",
    "sg:province":"Berkshire",
    "sg:tags":[
        "consultant"
    ],
    "wof:name":"I E C International Ltd.",
    "wof:placetype":"venue"
},
  "geometry": {"coordinates":[-0.5375440121,51.5065345764],"type":"Point"}
}