{
  "type": "Feature",
  "properties": {
    "iso:country":"GB",
    "sg:address":"The Cocked Hat Hotel, Rugby Rd, Binley Wood",
    "sg:city":"Coventry",
    "sg:classifiers":[
        {
            "category":"Health Services",
            "subcategory":"Health Practitioner",
            "type":"Services"
        }
    ],
    "sg:phone":"+44 24 7663 6757",
    "sg:postcode":"CV3 2BB",
    "sg:province":"Warwickshire",
    "sg:tags":[
        "therapist",
        "speech"
    ],
    "wof:name":"The Body Care Massage Centre",
    "wof:placetype":"venue"
},
  "geometry": {"coordinates":[-1.447587,52.395966],"type":"Point"}
}