{
  "type": "Feature",
  "properties": {
    "iso:country":"GB",
    "sg:address":"Suckley",
    "sg:city":"Worcester",
    "sg:classifiers":[
        {
            "category":"Farming",
            "subcategory":"Farm",
            "type":"Manufacturing & Wholesale Goods"
        }
    ],
    "sg:postcode":"WR6 5EH",
    "sg:province":"Herefordshire",
    "sg:tags":[
        "mixed",
        "crop"
    ],
    "wof:name":"R C O Capper",
    "wof:placetype":"venue"
},
  "geometry": {"coordinates":[-2.4148299694,52.1553688049],"type":"Point"}
}