{
  "type": "Feature",
  "properties": {
    "addr:full":"24 Seafield Road East Edinburgh City of Edinburgh EH15 1ED",
    "addr:housenumber":"24",
    "addr:postcode":"eh15 1ed",
    "addr:street":"Seafield Road East Edinburgh",
    "iso:country":"GB",
    "sg:address":"24 Seafield Road East",
    "sg:city":"Edinburgh",
    "sg:classifiers":[
        {
            "category":"Autos & Motor Vehicles",
            "subcategory":"Automobile Sales",
            "type":"Retail Goods"
        }
    ],
    "sg:phone":"+44 131 669 6111",
    "sg:postcode":"EH15 1ED",
    "sg:province":"City of Edinburgh",
    "sg:tags":[
        "car"
    ],
    "wof:name":"Belmont Vauxhall",
    "wof:placetype":"venue"
},
  "geometry": {"coordinates":[-3.12837,55.962662],"type":"Point"}
}