{
  "type": "Feature",
  "properties": {
    "addr:full":"Ainsworth St Rochdale Lancashire OL16 5QX",
    "addr:postcode":"ol16 5qx",
    "addr:street":"Ainsworth St",
    "iso:country":"GB",
    "sg:address":"Ainsworth St",
    "sg:city":"Rochdale",
    "sg:classifiers":[
        {
            "category":"Professional",
            "subcategory":"Printing & Photocopies",
            "type":"Services"
        }
    ],
    "sg:phone":"+44 1706 633442",
    "sg:postcode":"OL16 5QX",
    "sg:province":"Lancashire",
    "sg:tags":[
        "print",
        "finisher"
    ],
    "wof:name":"The Finishing Link",
    "wof:placetype":"venue"
},
  "geometry": {"coordinates":[-2.149134,53.610424],"type":"Point"}
}