{
  "type": "Feature",
  "properties": {
    "iso:country":"GB",
    "sg:address":"St Anns Rd",
    "sg:city":"Seven Sisters",
    "sg:classifiers":[
        {
            "category":"Health Services",
            "subcategory":"Clinic",
            "type":"Services"
        }
    ],
    "sg:phone":"+44 20 8442 6380",
    "sg:postcode":"N15 3TH",
    "sg:province":"Greater London",
    "sg:tags":[
        "nh"
    ],
    "wof:name":"Orchard House Clinic",
    "wof:placetype":"venue"
},
  "geometry": {"coordinates":[-0.097282,51.581825],"type":"Point"}
}