{
  "type": "Feature",
  "properties": {
    "iso:country":"GB",
    "sg:address":"Kingsway, Langley Park",
    "sg:city":"Durham",
    "sg:classifiers":[
        {
            "category":"Health Services",
            "subcategory":"Nursing And Care Facility",
            "type":"Services"
        }
    ],
    "sg:phone":"+44 191 373 6167",
    "sg:postcode":"DH7 9TB",
    "sg:province":"Durham",
    "sg:tags":[
        "home"
    ],
    "wof:name":"Kingsway Nursing Home",
    "wof:placetype":"venue"
},
  "geometry": {"coordinates":[-1.669799,54.80019],"type":"Point"}
}