{
  "type": "Feature",
  "properties": {
    "iso:country":"GB",
    "sg:address":"5 The Thoroughfare",
    "sg:city":"Woodbridge",
    "sg:classifiers":[
        {
            "category":"Deli",
            "type":"Food & Drink"
        }
    ],
    "sg:postcode":"IP12 1AA",
    "sg:province":"Suffolk",
    "sg:tags":[
        "delicatessen"
    ],
    "wof:name":"The Good Food Shop",
    "wof:placetype":"venue"
},
  "geometry": {"coordinates":[1.329924,52.10524],"type":"Point"}
}