{
  "type": "Feature",
  "properties": {
    "addr:full":"18 Church Street Epsom Surrey KT17 4QD",
    "addr:housenumber":"18",
    "addr:postcode":"kt17 4qd",
    "addr:street":"Church Street",
    "iso:country":"GB",
    "sg:address":"18 Church Street",
    "sg:city":"Epsom",
    "sg:classifiers":[
        {
            "category":"Professional",
            "subcategory":"Lawyer & Legal Services",
            "type":"Services"
        }
    ],
    "sg:phone":"+44 1372 725241",
    "sg:postcode":"KT17 4QD",
    "sg:province":"Surrey",
    "sg:tags":[
        "solicitor"
    ],
    "wof:name":"Bowles & Co.",
    "wof:placetype":"venue"
},
  "geometry": {"coordinates":[-0.2608529925,51.3313560486],"type":"Point"}
}