{
  "type": "Feature",
  "properties": {
    "addr:full":"Stockley Park West Uxbridge Greater London UB11 1BT",
    "addr:postcode":"ub11 1bt",
    "addr:street":"Stockley Park West",
    "iso:country":"GB",
    "sg:address":"Stockley Park West",
    "sg:city":"Uxbridge",
    "sg:classifiers":[
        {
            "category":"Shopping",
            "subcategory":"Pharmacy",
            "type":"Retail Goods"
        }
    ],
    "sg:phone":"+44 20 8990 9888",
    "sg:postcode":"UB11 1BT",
    "sg:province":"Greater London",
    "sg:tags":[
        "pharmaceutical"
    ],
    "wof:name":"Allen & Hanburys Ltd.",
    "wof:placetype":"venue"
},
  "geometry": {"coordinates":[-0.450038,51.5116],"type":"Point"}
}