{
  "type": "Feature",
  "properties": {
    "addr:full":"31 Crow Road Glasgow Glasgow City G11 7RT",
    "addr:housenumber":"31",
    "addr:postcode":"g11 7rt",
    "addr:street":"Crow Road",
    "iso:country":"GB",
    "sg:address":"31 Crow Road",
    "sg:city":"Glasgow",
    "sg:classifiers":[
        {
            "category":"Real Estate",
            "subcategory":"Real Estate Operator",
            "type":"Services"
        }
    ],
    "sg:phone":"+44 141 579 0110",
    "sg:postcode":"G11 7RT",
    "sg:province":"Glasgow City",
    "sg:tags":[
        "letting",
        "agent"
    ],
    "wof:name":"Coolbawn Properties",
    "wof:placetype":"venue"
},
  "geometry": {"coordinates":[-4.313358,55.871685],"type":"Point"}
}