{
  "type": "Feature",
  "properties": {
    "iso:country":"GB",
    "sg:address":"5 Appleby Road, Gatley",
    "sg:city":"Cheadle",
    "sg:classifiers":[
        {
            "category":"Organizations",
            "subcategory":"Membership Organization",
            "type":"Services"
        }
    ],
    "sg:phone":"+44 161 491 6630",
    "sg:postcode":"SK8 4QD",
    "sg:province":"Cheshire",
    "sg:tags":[
        "club"
    ],
    "wof:name":"Mosaic Lifestyle Ltd.",
    "wof:placetype":"venue"
},
  "geometry": {"coordinates":[-2.230541,53.387314],"type":"Point"}
}