{
  "type": "Feature",
  "properties": {
    "iso:country":"GB",
    "sg:address":"575 London Road, North Cheam",
    "sg:city":"Sutton",
    "sg:classifiers":[
        {
            "category":"Shopping",
            "subcategory":"News",
            "type":"Retail Goods"
        }
    ],
    "sg:postcode":"SM3 9AE",
    "sg:province":"Surrey",
    "sg:tags":[
        "newsagent"
    ],
    "wof:name":"Angels Newsagents & Tobacconist",
    "wof:placetype":"venue"
},
  "geometry": {"coordinates":[-0.226863,51.372044],"type":"Point"}
}