{
  "type": "Feature",
  "properties": {
    "addr:full":"155 Long Lane Bexleyheath Kent DA7 5AE",
    "addr:housenumber":"155",
    "addr:postcode":"da7 5ae",
    "addr:street":"Long Lane",
    "iso:country":"GB",
    "sg:address":"155 Long Lane",
    "sg:city":"Bexleyheath",
    "sg:classifiers":[
        {
            "category":"Fast Food",
            "type":"Food & Drink"
        },
        {
            "category":"Cafe",
            "type":"Food & Drink"
        }
    ],
    "sg:phone":"+44 20 8303 5200",
    "sg:postcode":"DA7 5AE",
    "sg:province":"Kent",
    "sg:tags":[
        "room",
        "tea",
        "away",
        "outlet",
        "meal",
        "take"
    ],
    "wof:name":"NIX SNAX",
    "wof:placetype":"venue"
},
  "geometry": {"coordinates":[0.145431,51.466053],"type":"Point"}
}