{
  "type": "Feature",
  "properties": {
    "addr:full":"Station Road Beccles Norfolk NR34 9QJ",
    "addr:postcode":"nr34 9qj",
    "addr:street":"Station Road",
    "iso:country":"GB",
    "sg:address":"Station Road",
    "sg:city":"Beccles",
    "sg:classifiers":[
        {
            "category":"Home & Garden",
            "subcategory":"Furniture",
            "type":"Retail Goods"
        }
    ],
    "sg:phone":"+44 1502 715710",
    "sg:postcode":"NR34 9QJ",
    "sg:province":"Norfolk",
    "wof:name":"Gifana Reproduction Furniture Ltd.",
    "wof:placetype":"venue"
},
  "geometry": {"coordinates":[1.5672849417,52.4581565857],"type":"Point"}
}