{
  "type": "Feature",
  "properties": {
    "iso:country":"GB",
    "sg:address":"9a Altway",
    "sg:city":"Liverpool",
    "sg:classifiers":[
        {
            "category":"Food & Beverages",
            "subcategory":"Bakery",
            "type":"Retail Goods"
        }
    ],
    "sg:phone":"+44 151 526 7562",
    "sg:postcode":"L10 3JA",
    "sg:province":"Merseyside",
    "sg:tags":[
        "baker"
    ],
    "wof:name":"Cooks Bakery",
    "wof:placetype":"venue"
},
  "geometry": {"coordinates":[-2.948907,53.486031],"type":"Point"}
}