{
  "type": "Feature",
  "properties": {
    "iso:country":"GB",
    "sg:address":"1-6 Shernbroke Road",
    "sg:city":"Waltham Abbey",
    "sg:classifiers":[
        {
            "category":"Travel",
            "subcategory":"Hostel",
            "type":"Entertainment"
        },
        {
            "category":"Government",
            "subcategory":"Office",
            "type":"Public Place"
        }
    ],
    "sg:phone":"+44 1992 700545",
    "sg:postcode":"EN9 3JF",
    "sg:province":"Essex",
    "sg:tags":[
        "local"
    ],
    "wof:name":"Shernbroke Road Hostel",
    "wof:placetype":"venue"
},
  "geometry": {"coordinates":[0.01994,51.68541],"type":"Point"}
}