{
  "type": "Feature",
  "properties": {
    "iso:country":"GB",
    "sg:address":"39 Palmerston Road",
    "sg:city":"London",
    "sg:classifiers":[
        {
            "category":"Home & Garden",
            "subcategory":"Home Furnishings",
            "type":"Retail Goods"
        }
    ],
    "sg:phone":"+44 20 8520 4229",
    "sg:postcode":"E17 6PR",
    "sg:province":"Greater London",
    "sg:tags":[
        "wall",
        "wallpaper",
        "covering"
    ],
    "wof:name":"Galaxy Wallpapers",
    "wof:placetype":"venue"
},
  "geometry": {"coordinates":[-0.029806,51.586838],"type":"Point"}
}