{
  "type": "Feature",
  "properties": {
    "iso:country":"GB",
    "sg:address":"31 Farndale Avenue",
    "sg:city":"Corby",
    "sg:classifiers":[
        {
            "category":"Professional",
            "subcategory":"Detective & Security Services",
            "type":"Services"
        }
    ],
    "sg:postcode":"NN17 1LS",
    "sg:province":"Northamptonshire",
    "sg:tags":[
        "agency"
    ],
    "wof:name":"Exkaliber Security & Private Investigations",
    "wof:placetype":"venue"
},
  "geometry": {"coordinates":[-0.70436,52.49226],"type":"Point"}
}