{
  "type": "Feature",
  "properties": {
    "addr:full":"244a Plumstead High Street London Greater London SE18 1JN",
    "addr:housenumber":"244a",
    "addr:postcode":"se18 1jn",
    "addr:street":"High Street",
    "iso:country":"GB",
    "sg:address":"244a Plumstead High Street",
    "sg:city":"London",
    "sg:classifiers":[
        {
            "category":"Food & Beverages",
            "subcategory":"Meat & Fish",
            "type":"Retail Goods"
        }
    ],
    "sg:postcode":"SE18 1JN",
    "sg:province":"Greater London",
    "sg:tags":[
        "chip"
    ],
    "wof:name":"Wing Kwong Shum",
    "wof:placetype":"venue"
},
  "geometry": {"coordinates":[0.097695,51.486179],"type":"Point"}
}