{
  "type": "Feature",
  "properties": {
    "iso:country":"GB",
    "sg:address":"Court Farm, Pontrilas",
    "sg:city":"Hereford",
    "sg:classifiers":[
        {
            "category":"Farming",
            "subcategory":"Livestock Farm",
            "type":"Manufacturing & Wholesale Goods"
        }
    ],
    "sg:phone":"+44 1981 240368",
    "sg:postcode":"HR2 0EH",
    "sg:province":"Herefordshire",
    "sg:tags":[
        "others"
    ],
    "wof:name":"R T James",
    "wof:placetype":"venue"
},
  "geometry": {"coordinates":[-2.8807311058,51.9431495667],"type":"Point"}
}