{
  "type": "Feature",
  "properties": {
    "addr:full":"St.helensway, Fisons Way Ind Est Thetford Norfolk IP24 1HT",
    "addr:postcode":"ip24 1ht",
    "addr:street":"Fisons Way;Est",
    "iso:country":"GB",
    "sg:address":"St.helensway, Fisons Way Ind Est",
    "sg:city":"Thetford",
    "sg:classifiers":[
        {
            "category":"Freight",
            "type":"Transportation"
        }
    ],
    "sg:postcode":"IP24 1HT",
    "sg:province":"Norfolk",
    "sg:tags":[
        "haulage",
        "road"
    ],
    "wof:name":"Parceline Ltd",
    "wof:placetype":"venue"
},
  "geometry": {"coordinates":[0.740733,52.413292],"type":"Point"}
}