{
  "type": "Feature",
  "properties": {
    "addr:full":"Unit 3b Hawkins Road Colchester Essex CO2 8JY",
    "addr:housenumber":"unit 3b",
    "addr:postcode":"co2 8jy",
    "addr:street":"Hawkins Road Colchester",
    "iso:country":"GB",
    "sg:address":"Unit 3b Hawkins Road",
    "sg:city":"Colchester",
    "sg:classifiers":[
        {
            "category":"Shopping",
            "subcategory":"Computers & Home Electronics",
            "type":"Retail Goods"
        }
    ],
    "sg:postcode":"CO2 8JY",
    "sg:province":"Essex",
    "sg:tags":[
        "consumables"
    ],
    "wof:name":"K P Paper Converters",
    "wof:placetype":"venue"
},
  "geometry": {"coordinates":[0.9277870059,51.8832130432],"type":"Point"}
}