{
  "type": "Feature",
  "properties": {
    "iso:country":"GB",
    "sg:address":"Trendrennen Farm, St Levan",
    "sg:city":"Penzance",
    "sg:classifiers":[
        {
            "category":"Food & Beverages",
            "subcategory":"Groceries & Convenience Stores",
            "type":"Retail Goods"
        }
    ],
    "sg:phone":"+44 1736 810666",
    "sg:postcode":"TR19 6LH",
    "sg:province":"Cornwall",
    "sg:tags":[
        "merchant",
        "potato"
    ],
    "wof:name":"Duchy Marketing Services Ltd.",
    "wof:placetype":"venue"
},
  "geometry": {"coordinates":[-5.65084,50.050018],"type":"Point"}
}