{
  "type": "Feature",
  "properties": {
    "addr:full":"1a Crookham Road Fleet Hampshire GU51 5DP",
    "addr:housenumber":"1a",
    "addr:postcode":"gu51 5dp",
    "addr:street":"Crookham Road",
    "iso:country":"GB",
    "sg:address":"1a Crookham Road",
    "sg:city":"Fleet",
    "sg:classifiers":[
        {
            "category":"Restaurant",
            "type":"Food & Drink"
        }
    ],
    "sg:phone":"+44 1252 615034",
    "sg:postcode":"GU51 5DP",
    "sg:province":"Hampshire",
    "sg:tags":[
        "chinese"
    ],
    "wof:name":"Water Sky Chinese Restaurant",
    "wof:placetype":"venue"
},
  "geometry": {"coordinates":[-0.845636,51.278061],"type":"Point"}
}