{
  "type": "Feature",
  "properties": {
    "addr:full":"16a Cambridge St Wellingborough Northamptonshire NN8 1DJ",
    "addr:housenumber":"16a",
    "addr:postcode":"nn8 1dj",
    "addr:street":"Cambridge St",
    "iso:country":"GB",
    "sg:address":"16a Cambridge St",
    "sg:city":"Wellingborough",
    "sg:classifiers":[
        {
            "category":"Recreation",
            "subcategory":"Amusement Park",
            "type":"Entertainment"
        }
    ],
    "sg:phone":"+44 1933 227248",
    "sg:postcode":"NN8 1DJ",
    "sg:province":"Northamptonshire",
    "sg:tags":[
        "arcade"
    ],
    "wof:name":"Lots Of Fun",
    "wof:placetype":"venue"
},
  "geometry": {"coordinates":[-0.690276,52.303242],"type":"Point"}
}