{
  "type": "Feature",
  "properties": {
    "iso:country":"GB",
    "sg:address":"Unit 6 Fowler Industrial Estate, Chorley New Road, Horwich",
    "sg:city":"Bolton",
    "sg:classifiers":[
        {
            "category":"Home & Garden",
            "subcategory":"Building Materials",
            "type":"Retail Goods"
        }
    ],
    "sg:phone":"+44 1204 468698",
    "sg:postcode":"BL6 5LU",
    "sg:province":"Lancashire",
    "sg:tags":[
        "garage",
        "door"
    ],
    "wof:name":"N C I Garage Doors Ltd.",
    "wof:placetype":"venue"
},
  "geometry": {"coordinates":[-2.547624,53.595215],"type":"Point"}
}