{
  "type": "Feature",
  "properties": {
    "iso:country":"GB",
    "sg:address":"35-37 Westport",
    "sg:city":"Lanark",
    "sg:classifiers":[
        {
            "category":"Building & Trades",
            "subcategory":"Construction",
            "type":"Services"
        }
    ],
    "sg:postcode":"ML11 9HD",
    "sg:province":"South Lanarkshire",
    "sg:tags":[
        "builder"
    ],
    "wof:name":"Robert Coulter Builders",
    "wof:placetype":"venue"
},
  "geometry": {"coordinates":[-3.7843,55.674618],"type":"Point"}
}