{
  "type": "Feature",
  "properties": {
    "addr:full":"136 Chaldon Way Coulsdon Surrey CR5 1DF",
    "addr:housenumber":"136",
    "addr:postcode":"cr5 1df",
    "addr:street":"Chaldon Way",
    "iso:country":"GB",
    "sg:address":"136 Chaldon Way",
    "sg:city":"Coulsdon",
    "sg:classifiers":[
        {
            "category":"Real Estate",
            "subcategory":"Developer",
            "type":"Services"
        }
    ],
    "sg:phone":"+44 1737 556644",
    "sg:postcode":"CR5 1DF",
    "sg:province":"Surrey",
    "sg:tags":[
        "property"
    ],
    "wof:name":"Rocke Developments Ltd",
    "wof:placetype":"venue"
},
  "geometry": {"coordinates":[-0.1323319972,51.3073196411],"type":"Point"}
}