{
  "type": "Feature",
  "properties": {
    "addr:full":"10b Eastover Bridgwater Somerset TA6 5AB",
    "addr:housenumber":"10b",
    "addr:postcode":"ta6 5ab",
    "addr:street":"Eastover",
    "iso:country":"GB",
    "sg:address":"10b Eastover",
    "sg:city":"Bridgwater",
    "sg:classifiers":[
        {
            "category":"Deli",
            "type":"Food & Drink"
        }
    ],
    "sg:phone":"+44 1278 452169",
    "sg:postcode":"TA6 5AB",
    "sg:province":"Somerset",
    "sg:tags":[
        "delicatessen"
    ],
    "wof:name":"Mcgregor's Family Food",
    "wof:placetype":"venue"
},
  "geometry": {"coordinates":[-3.0003259182,51.1288642883],"type":"Point"}
}