{
  "type": "Feature",
  "properties": {
    "iso:country":"GB",
    "sg:address":"49 Endless Street",
    "sg:city":"Salisbury",
    "sg:classifiers":[
        {
            "category":"Retail",
            "subcategory":"Veterinary Services",
            "type":"Services"
        }
    ],
    "sg:postcode":"SP1 3UH",
    "sg:province":"Wiltshire",
    "sg:tags":[
        "surgeon"
    ],
    "wof:name":"Endell Veterinary Group",
    "wof:placetype":"venue"
},
  "geometry": {"coordinates":[-1.794602,51.07172],"type":"Point"}
}