{
  "type": "Feature",
  "properties": {
    "iso:country":"GB",
    "sg:address":"75 Fylde Road",
    "sg:city":"Preston",
    "sg:classifiers":[
        {
            "category":"Food & Beverages",
            "subcategory":"Meat & Fish",
            "type":"Retail Goods"
        }
    ],
    "sg:phone":"+44 1772 886530",
    "sg:postcode":"PR1 2XQ",
    "sg:province":"Lancashire",
    "sg:tags":[
        "chip"
    ],
    "wof:name":"Fylde Chippy",
    "wof:placetype":"venue"
},
  "geometry": {"coordinates":[-2.710172,53.764244],"type":"Point"}
}