{
  "type": "Feature",
  "properties": {
    "addr:full":"172 Southend Road Rainham Essex RM13 7XR",
    "addr:housenumber":"172",
    "addr:postcode":"rm13 7xr",
    "addr:street":"Southend Road",
    "iso:country":"GB",
    "sg:address":"172 Southend Road",
    "sg:city":"Rainham",
    "sg:classifiers":[
        {
            "category":"Retail",
            "subcategory":"Laundry & Dry Cleaning",
            "type":"Services"
        }
    ],
    "sg:phone":"+44 1708 554949",
    "sg:postcode":"RM13 7XR",
    "sg:province":"Essex",
    "sg:tags":[
        "alteration"
    ],
    "wof:name":"Dove Jahit Dry Cleaners",
    "wof:placetype":"venue"
},
  "geometry": {"coordinates":[0.1925259978,51.5339660645],"type":"Point"}
}