{
  "type": "Feature",
  "properties": {
    "iso:country":"GB",
    "sg:address":"Bucklersbury Ho",
    "sg:city":"St Paul's",
    "sg:classifiers":[
        {
            "category":"Real Estate",
            "subcategory":"Real Estate Agent",
            "type":"Services"
        }
    ],
    "sg:phone":"+44 20 7248 5849",
    "sg:postcode":"EC4N 8EL",
    "sg:province":"Greater London",
    "wof:name":"J Cleur",
    "wof:placetype":"venue"
},
  "geometry": {"coordinates":[-0.094041,51.536476],"type":"Point"}
}