{
  "type": "Feature",
  "properties": {
    "iso:country":"GB",
    "sg:address":"35 Green St",
    "sg:city":"Neath",
    "sg:classifiers":[
        {
            "category":"Banks & Credit Unions",
            "subcategory":"Bank",
            "type":"Services"
        }
    ],
    "sg:phone":"+44 1639 635271",
    "sg:postcode":"SA11 1DF",
    "sg:province":"Neath Port Talbot",
    "wof:name":"NatWest",
    "wof:placetype":"venue"
},
  "geometry": {"coordinates":[-3.806028,51.662495],"type":"Point"}
}