{
  "type": "Feature",
  "properties": {
    "addr:full":"128 Soundwell Rd Bristol City of Bristol BS16 4RT",
    "addr:housenumber":"128",
    "addr:postcode":"bs16 4rt",
    "addr:street":"Soundwell Rd",
    "iso:country":"GB",
    "sg:address":"128 Soundwell Rd",
    "sg:city":"Bristol",
    "sg:classifiers":[
        {
            "category":"Manufacturing",
            "subcategory":"Signs",
            "type":"Manufacturing & Wholesale Goods"
        }
    ],
    "sg:phone":"+44 117 940 6746",
    "sg:postcode":"BS16 4RT",
    "sg:province":"City of Bristol",
    "sg:tags":[
        "nameplate"
    ],
    "wof:name":"Stick Em Up Sign Services",
    "wof:placetype":"venue"
},
  "geometry": {"coordinates":[-2.591429,51.453667],"type":"Point"}
}