{
  "type": "Feature",
  "properties": {
    "iso:country":"GB",
    "sg:address":"3 Gustavus Rd",
    "sg:city":"Camborne",
    "sg:classifiers":[
        {
            "category":"Health Services",
            "subcategory":"Health Practitioner",
            "type":"Services"
        }
    ],
    "sg:phone":"+44 1209 710370",
    "sg:postcode":"TR14 7LL",
    "sg:province":"Cornwall",
    "sg:tags":[
        "physiotherapist"
    ],
    "wof:name":"V J Ivins",
    "wof:placetype":"venue"
},
  "geometry": {"coordinates":[-5.300464,50.216393],"type":"Point"}
}