{
  "type": "Feature",
  "properties": {
    "iso:country":"GB",
    "sg:address":"59 Birmingham New Road",
    "sg:city":"Tipton",
    "sg:classifiers":[
        {
            "category":"Shopping",
            "subcategory":"News",
            "type":"Retail Goods"
        }
    ],
    "sg:phone":"+44 121 557 2236",
    "sg:postcode":"DY4 8JP",
    "sg:province":"West Midlands",
    "sg:tags":[
        "newsagent"
    ],
    "wof:name":"New Road Newsagents",
    "wof:placetype":"venue"
},
  "geometry": {"coordinates":[-2.070306,52.521614],"type":"Point"}
}