{
  "type": "Feature",
  "properties": {
    "iso:country":"GB",
    "sg:address":"183 Station Rd, Bamber Bridge",
    "sg:city":"Preston",
    "sg:classifiers":[
        {
            "category":"Real Estate",
            "subcategory":"Real Estate Agent",
            "type":"Services"
        }
    ],
    "sg:phone":"+44 1772 627776",
    "sg:postcode":"PR5 6LA",
    "sg:province":"Lancashire",
    "wof:name":"Halifax Property Services",
    "wof:placetype":"venue"
},
  "geometry": {"coordinates":[-2.660902,53.729847],"type":"Point"}
}