{
  "type": "Feature",
  "properties": {
    "iso:country":"GB",
    "sg:address":"62a Silver Street",
    "sg:city":"Doncaster",
    "sg:classifiers":[
        {
            "category":"Education",
            "subcategory":"Special Training",
            "type":"Public Place"
        }
    ],
    "sg:postcode":"DN1 1HT",
    "sg:province":"South Yorkshire",
    "sg:tags":[
        "product",
        "centre"
    ],
    "wof:name":"Look & Learn Ltd",
    "wof:placetype":"venue"
},
  "geometry": {"coordinates":[-1.130982,53.524426],"type":"Point"}
}