{
  "type": "Feature",
  "properties": {
    "iso:country":"GB",
    "sg:address":"Unit 12 Retail World T V T E",
    "sg:city":"Gateshead",
    "sg:classifiers":[
        {
            "category":"Sports & Exercise",
            "subcategory":"Sports Center",
            "type":"Entertainment"
        }
    ],
    "sg:phone":"+44 191 487 1319",
    "sg:postcode":"NE11 0BD",
    "sg:province":"Tyne and Wear",
    "sg:tags":[
        "shop",
        "good"
    ],
    "wof:name":"J J B Sports",
    "wof:placetype":"venue"
},
  "geometry": {"coordinates":[-1.62,54.922539],"type":"Point"}
}