{
  "type": "Feature",
  "properties": {
    "addr:full":"Sutton Road, Potton Sandy Bedfordshire SG19 2DT",
    "addr:postcode":"sg19 2dt",
    "addr:street":"Sutton Road",
    "iso:country":"GB",
    "sg:address":"Sutton Road, Potton",
    "sg:city":"Sandy",
    "sg:classifiers":[
        {
            "category":"Farming",
            "subcategory":"Livestock Farm",
            "type":"Manufacturing & Wholesale Goods"
        }
    ],
    "sg:phone":"+44 1767 260248",
    "sg:postcode":"SG19 2DT",
    "sg:province":"Bedfordshire",
    "sg:tags":[
        "others"
    ],
    "wof:name":"D P Smith",
    "wof:placetype":"venue"
},
  "geometry": {"coordinates":[-0.216141,52.126591],"type":"Point"}
}