{
  "type": "Feature",
  "properties": {
    "iso:country":"GB",
    "sg:address":"9 Nimrod Close, Woodley",
    "sg:city":"Reading",
    "sg:classifiers":[
        {
            "category":"Professional",
            "subcategory":"Engineering",
            "type":"Services"
        }
    ],
    "sg:phone":"+44 118 969 7903",
    "sg:postcode":"RG5 4UW",
    "sg:province":"Berkshire",
    "sg:tags":[
        "contractor",
        "electrical",
        "engineer"
    ],
    "wof:name":"G & T Electrical Services Ltd.",
    "wof:placetype":"venue"
},
  "geometry": {"coordinates":[-0.8851199746,51.4545822144],"type":"Point"}
}