{
  "type": "Feature",
  "properties": {
    "iso:country":"GB",
    "sg:address":"12 Ellen Way",
    "sg:city":"Braintree",
    "sg:classifiers":[
        {
            "category":"Shopping",
            "subcategory":"Department Store",
            "type":"Retail Goods"
        }
    ],
    "sg:phone":"+44 1376 345206",
    "sg:postcode":"CM77 7UU",
    "sg:province":"Essex",
    "wof:name":"White Court Stores",
    "wof:placetype":"venue"
},
  "geometry": {"coordinates":[0.533374,51.863525],"type":"Point"}
}