{
  "type": "Feature",
  "properties": {
    "addr:full":"Morton Peto Rd, Gapton Indust Est Great Yarmouth Norfolk NR31 0LT",
    "addr:postcode":"nr31 0lt",
    "addr:street":"Morton Peto Rd;Indust Est",
    "iso:country":"GB",
    "sg:address":"Morton Peto Rd, Gapton Indust Est",
    "sg:city":"Great Yarmouth",
    "sg:classifiers":[
        {
            "category":"Mining & Drilling",
            "type":"Manufacturing & Wholesale Goods"
        }
    ],
    "sg:phone":"+44 1493 603798",
    "sg:postcode":"NR31 0LT",
    "sg:province":"Norfolk",
    "sg:tags":[
        "contractor"
    ],
    "wof:name":"Sperry Sun Drilling Services",
    "wof:placetype":"venue"
},
  "geometry": {"coordinates":[1.71394,52.590912],"type":"Point"}
}