{
  "type": "Feature",
  "properties": {
    "iso:country":"GB",
    "sg:address":"7 Downsview Rd",
    "sg:city":"Upper Norwood",
    "sg:classifiers":[
        {
            "category":"Home & Garden",
            "subcategory":"Building Materials",
            "type":"Retail Goods"
        }
    ],
    "sg:phone":"+44 20 8771 2036",
    "sg:postcode":"SE19 3XB",
    "sg:province":"Greater London",
    "sg:tags":[
        "door",
        "domestic"
    ],
    "wof:name":"Natural Door Co The",
    "wof:placetype":"venue"
},
  "geometry": {"coordinates":[-0.099954,51.417034],"type":"Point"}
}