{
  "type": "Feature",
  "properties": {
    "addr:full":"Fry St Middlesbrough North Yorkshire TS1 1JH",
    "addr:postcode":"ts1 1jh",
    "addr:street":"Fry St",
    "iso:country":"GB",
    "sg:address":"Fry St",
    "sg:city":"Middlesbrough",
    "sg:classifiers":[
        {
            "category":"Bars & Pubs",
            "subcategory":"Nightclub",
            "type":"Food & Drink"
        }
    ],
    "sg:phone":"+44 1642 210000",
    "sg:postcode":"TS1 1JH",
    "sg:province":"North Yorkshire",
    "sg:tags":[
        "club",
        "night"
    ],
    "wof:name":"Stakis Regency Club The",
    "wof:placetype":"venue"
},
  "geometry": {"coordinates":[-1.2311290503,54.5764579773],"type":"Point"}
}