{
  "type": "Feature",
  "properties": {
    "iso:country":"GB",
    "sg:address":"Unit 6 Querns Business Estate, Whitworth Road",
    "sg:city":"Cirencester",
    "sg:classifiers":[
        {
            "category":"Shopping",
            "subcategory":"Hobbies, Toys, & Games",
            "type":"Retail Goods"
        }
    ],
    "sg:phone":"+44 1285 657527",
    "sg:postcode":"GL7 1QH",
    "sg:province":"Gloucestershire",
    "sg:tags":[
        "gunsmith"
    ],
    "wof:name":"Roderick Maconochie",
    "wof:placetype":"venue"
},
  "geometry": {"coordinates":[-1.953541,51.718548],"type":"Point"}
}