{
  "type": "Feature",
  "properties": {
    "addr:full":"113 Redston Rd Hornsey Greater London N8 7HG",
    "addr:housenumber":"113",
    "addr:postcode":"7hg",
    "addr:street":"Redston Rd",
    "iso:country":"GB",
    "sg:address":"113 Redston Rd",
    "sg:city":"Hornsey",
    "sg:classifiers":[
        {
            "category":"Professional",
            "subcategory":"Management & Consulting",
            "type":"Services"
        }
    ],
    "sg:phone":"+44 20 8347 9682",
    "sg:postcode":"N8 7HG",
    "sg:province":"Greater London",
    "sg:tags":[
        "consultant",
        "business"
    ],
    "wof:name":"New Directions For Public Service",
    "wof:placetype":"venue"
},
  "geometry": {"coordinates":[-0.128604,51.589569],"type":"Point"}
}