{
  "type": "Feature",
  "properties": {
    "addr:full":"14 Heritage Close St Albans Hertfordshire AL3 4EB",
    "addr:housenumber":"14",
    "addr:postcode":"al3 4eb",
    "addr:street":"Heritage Close",
    "iso:country":"GB",
    "sg:address":"14 Heritage Close",
    "sg:city":"St Albans",
    "sg:classifiers":[
        {
            "category":"Shopping",
            "subcategory":"Crafts & Fabrics",
            "type":"Retail Goods"
        }
    ],
    "sg:postcode":"AL3 4EB",
    "sg:province":"Hertfordshire",
    "sg:tags":[
        "shop",
        "needlecraft",
        "wool"
    ],
    "wof:name":"Buttons & Bows",
    "wof:placetype":"venue"
},
  "geometry": {"coordinates":[-0.3407489955,51.7508964539],"type":"Point"}
}