{
  "type": "Feature",
  "properties": {
    "addr:full":"Rusland Road, Kirkby Liverpool Merseyside L32 6QW",
    "addr:postcode":"l32 6qw",
    "addr:street":"Rusland Road",
    "iso:country":"GB",
    "sg:address":"Rusland Road, Kirkby",
    "sg:city":"Liverpool",
    "sg:classifiers":[
        {
            "category":"Organizations",
            "subcategory":"Membership Organization",
            "type":"Services"
        }
    ],
    "sg:postcode":"L32 6QW",
    "sg:province":"Merseyside",
    "sg:tags":[
        "club"
    ],
    "wof:name":"12-5 Social Club",
    "wof:placetype":"venue"
},
  "geometry": {"coordinates":[-2.8804941177,53.4728088379],"type":"Point"}
}