{
  "type": "Feature",
  "properties": {
    "addr:full":"Basement Suite, Coverdale House, 14/15 East Parade Leeds West Yorkshire LS1 2BH",
    "addr:housenumber":"basement suite coverdale house 14 / 15",
    "addr:postcode":"ls1 2bh",
    "addr:street":"East Parade",
    "iso:country":"GB",
    "sg:address":"Basement Suite, Coverdale House, 14/15 East Parade",
    "sg:city":"Leeds",
    "sg:classifiers":[
        {
            "category":"Professional",
            "subcategory":"Computer Services",
            "type":"Services"
        },
        {
            "category":"Organizations",
            "subcategory":"Membership Organization",
            "type":"Services"
        }
    ],
    "sg:phone":"+44 113 244 2460",
    "sg:postcode":"LS1 2BH",
    "sg:province":"West Yorkshire",
    "sg:tags":[
        "club",
        "information",
        "social"
    ],
    "wof:name":"Immigration Advisory Service",
    "wof:placetype":"venue"
},
  "geometry": {"coordinates":[-1.5493930578,53.7989349365],"type":"Point"}
}