{
  "type": "Feature",
  "properties": {
    "iso:country":"GB",
    "sg:address":"High Marks, Woodleigh",
    "sg:city":"Kingsbridge",
    "sg:classifiers":[
        {
            "category":"Building & Trades",
            "subcategory":"Landscaping Services",
            "type":"Services"
        }
    ],
    "sg:phone":"+44 1548 821214",
    "sg:postcode":"TQ7 4DN",
    "sg:province":"Devon",
    "sg:tags":[
        "gardening"
    ],
    "wof:name":"A Dunn",
    "wof:placetype":"venue"
},
  "geometry": {"coordinates":[-3.774109,50.325554],"type":"Point"}
}