{
  "type": "Feature",
  "properties": {
    "addr:full":"32 Selsdon Road South Croydon Surrey CR2 6PB",
    "addr:housenumber":"32",
    "addr:postcode":"cr2 6pb",
    "addr:street":"Selsdon Road",
    "iso:country":"GB",
    "sg:address":"32 Selsdon Road",
    "sg:city":"South Croydon",
    "sg:classifiers":[
        {
            "category":"Restaurant",
            "type":"Food & Drink"
        }
    ],
    "sg:phone":"+44 20 8649 9544",
    "sg:postcode":"CR2 6PB",
    "sg:province":"Surrey",
    "sg:tags":[
        "french"
    ],
    "wof:name":"Little Bay Restaurant",
    "wof:placetype":"venue"
},
  "geometry": {"coordinates":[-0.0961780027,51.3618850708],"type":"Point"}
}