{
  "type": "Feature",
  "properties": {
    "iso:country":"GB",
    "sg:address":"5 Homesteads Rd",
    "sg:city":"Basingstoke",
    "sg:classifiers":[
        {
            "category":"Food & Beverages",
            "subcategory":"Fruits & Vegetables",
            "type":"Retail Goods"
        }
    ],
    "sg:phone":"+44 1256 331386",
    "sg:postcode":"RG22 5RP",
    "sg:province":"Hampshire",
    "sg:tags":[
        "greengrocer"
    ],
    "wof:name":"Fruit Basket The",
    "wof:placetype":"venue"
},
  "geometry": {"coordinates":[-1.138605,51.248104],"type":"Point"}
}