{
  "type": "Feature",
  "properties": {
    "addr:full":"Unit H, Hart St Commercial Centre, Hart Street Maidstone Kent ME16 8RF",
    "addr:postcode":"me16 8rf",
    "addr:street":"Hart Street",
    "iso:country":"GB",
    "sg:address":"Unit H, Hart St Commercial Centre, Hart Street",
    "sg:city":"Maidstone",
    "sg:classifiers":[
        {
            "category":"Professional",
            "subcategory":"Art Services",
            "type":"Services"
        }
    ],
    "sg:phone":"+44 1622 754731",
    "sg:postcode":"ME16 8RF",
    "sg:province":"Kent",
    "sg:tags":[
        "decorating",
        "painting"
    ],
    "wof:name":"John Stone's Manders Paints",
    "wof:placetype":"venue"
},
  "geometry": {"coordinates":[0.5161399841,51.2692489624],"type":"Point"}
}