{
  "type": "Feature",
  "properties": {
    "addr:full":"104 Charles Street, Swinton Manchester Greater Manchester M27 9XF",
    "addr:housenumber":"104",
    "addr:postcode":"m27 9xf",
    "addr:street":"Charles Street",
    "iso:country":"GB",
    "sg:address":"104 Charles Street, Swinton",
    "sg:city":"Manchester",
    "sg:classifiers":[
        {
            "category":"Building & Trades",
            "subcategory":"Cleaning & Sanitation",
            "type":"Services"
        },
        {
            "category":"Home & Garden",
            "subcategory":"Carpets & Floor Coverings",
            "type":"Retail Goods"
        }
    ],
    "sg:phone":"+44 161 794 3768",
    "sg:postcode":"M27 9XF",
    "sg:province":"Greater Manchester",
    "sg:tags":[
        "cleaner",
        "upholstery"
    ],
    "wof:name":"Carpet Cleaning Specialist",
    "wof:placetype":"venue"
},
  "geometry": {"coordinates":[-2.3498520851,53.519443512],"type":"Point"}
}