{
  "type": "Feature",
  "properties": {
    "iso:country":"GB",
    "sg:address":"20 Stewart Drive, Clarkston",
    "sg:city":"Glasgow",
    "sg:classifiers":[
        {
            "category":"Banks & Credit Unions",
            "subcategory":"Financial Services",
            "type":"Services"
        }
    ],
    "sg:phone":"+44 141 638 0017",
    "sg:postcode":"G76 7EZ",
    "sg:province":"East Renfrewshire",
    "sg:tags":[
        "consultant"
    ],
    "wof:name":"Project Fishing International",
    "wof:placetype":"venue"
},
  "geometry": {"coordinates":[-4.2816400528,55.7906684875],"type":"Point"}
}