{
  "type": "Feature",
  "properties": {
    "addr:full":"Hollings Hill, Guiseley Leeds West Yorkshire LS20 8NW",
    "addr:postcode":"ls20 8nw",
    "addr:street":"Hollings Hill",
    "iso:country":"GB",
    "sg:address":"Hollings Hill, Guiseley",
    "sg:city":"Leeds",
    "sg:classifiers":[
        {
            "category":"Farming",
            "subcategory":"Livestock Farm",
            "type":"Manufacturing & Wholesale Goods"
        }
    ],
    "sg:postcode":"LS20 8NW",
    "sg:province":"West Yorkshire",
    "sg:tags":[
        "others"
    ],
    "wof:name":"Ian David Briggs",
    "wof:placetype":"venue"
},
  "geometry": {"coordinates":[-1.719302,53.867916],"type":"Point"}
}