{
  "type": "Feature",
  "properties": {
    "iso:country":"GB",
    "sg:address":"Chaddesley House",
    "sg:city":"Dudley",
    "sg:classifiers":[
        {
            "category":"Organizations",
            "subcategory":"Non-profit Organization",
            "type":"Services"
        }
    ],
    "sg:postcode":"DY1 1DZ",
    "sg:province":"West Midlands",
    "sg:tags":[
        "organisation",
        "voluntary",
        "charity"
    ],
    "wof:name":"Headway Black Country",
    "wof:placetype":"venue"
},
  "geometry": {"coordinates":[-2.0860500336,52.5106391907],"type":"Point"}
}