{
  "type": "Feature",
  "properties": {
    "addr:full":"4 Candover St West End Hampshire W1P 7PR",
    "addr:housenumber":"4",
    "addr:postcode":"w1p 7pr",
    "addr:street":"Candover St",
    "iso:country":"GB",
    "sg:address":"4 Candover St",
    "sg:city":"West End",
    "sg:classifiers":[
        {
            "category":"Communications",
            "subcategory":"Newspaper",
            "type":"Services"
        }
    ],
    "sg:phone":"+44 20 7580 9374",
    "sg:postcode":"W1P 7PR",
    "sg:province":"Hampshire",
    "sg:tags":[
        "magazine"
    ],
    "wof:name":"Bob Street",
    "wof:placetype":"venue"
},
  "geometry": {"coordinates":[-0.139824003,51.5192832947],"type":"Point"}
}