{
  "type": "Feature",
  "properties": {
    "addr:full":"Avenue Road Newport Shropshire TF10 7EA",
    "addr:postcode":"tf10 7ea",
    "addr:street":"Avenue Road",
    "iso:country":"GB",
    "sg:address":"Avenue Road",
    "sg:city":"Newport",
    "sg:classifiers":[
        {
            "category":"Freight",
            "type":"Transportation"
        }
    ],
    "sg:phone":"+44 1952 811645",
    "sg:postcode":"TF10 7EA",
    "sg:province":"Shropshire",
    "sg:tags":[
        "haulage",
        "transport",
        "road"
    ],
    "wof:name":"R N Hesbrook & Sons",
    "wof:placetype":"venue"
},
  "geometry": {"coordinates":[-2.373589,52.76704],"type":"Point"}
}