{
  "type": "Feature",
  "properties": {
    "iso:country":"GB",
    "sg:address":"318 Hob Moor Road",
    "sg:city":"Birmingham",
    "sg:classifiers":[
        {
            "category":"Home & Garden",
            "subcategory":"Household Appliances",
            "type":"Retail Goods"
        }
    ],
    "sg:phone":"+44 121 773 4703",
    "sg:postcode":"B10 9HJ",
    "sg:province":"West Midlands",
    "sg:tags":[
        "refrigeration",
        "air conditioning"
    ],
    "wof:name":"Cool Point Refrigeration Services",
    "wof:placetype":"venue"
},
  "geometry": {"coordinates":[-1.8286830187,52.4703445435],"type":"Point"}
}