{
  "type": "Feature",
  "properties": {
    "iso:country":"GB",
    "sg:address":"Majendie Lane, Castle Hedingham",
    "sg:city":"Halstead",
    "sg:classifiers":[
        {
            "category":"Shopping",
            "subcategory":"Bicycles & Sporting Goods",
            "type":"Retail Goods"
        }
    ],
    "sg:postcode":"CO9 3EJ",
    "sg:province":"Essex",
    "sg:tags":[
        "cycle",
        "accessory"
    ],
    "wof:name":"Buckley-Saxon Ltd.",
    "wof:placetype":"venue"
},
  "geometry": {"coordinates":[0.5989249945,51.9897232056],"type":"Point"}
}