{
  "type": "Feature",
  "properties": {
    "iso:country":"GB",
    "sg:address":"Sandbach Road, Lawton Heath End Church Lawton",
    "sg:city":"Stoke-on-trent",
    "sg:classifiers":[
        {
            "category":"Shopping",
            "subcategory":"Computers & Home Electronics",
            "type":"Retail Goods"
        }
    ],
    "sg:phone":"+44 1270 876902",
    "sg:postcode":"ST7 3RA",
    "sg:province":"Cheshire",
    "wof:name":"Printer Products & Consumables (U K) Ltd.",
    "wof:placetype":"venue"
},
  "geometry": {"coordinates":[-2.290393,53.10384],"type":"Point"}
}