{
  "type": "Feature",
  "properties": {
    "iso:country":"GB",
    "sg:address":"Brook House, Brook St, Bishops Waltham",
    "sg:city":"Southampton",
    "sg:classifiers":[
        {
            "category":"Professional",
            "subcategory":"Secretarial Services",
            "type":"Services"
        }
    ],
    "sg:phone":"+44 1489 895222",
    "sg:postcode":"SO32 1GQ",
    "sg:province":"Hampshire",
    "wof:name":"Portfolio Management International",
    "wof:placetype":"venue"
},
  "geometry": {"coordinates":[-1.2130349874,50.9547386169],"type":"Point"}
}