{
  "type": "Feature",
  "properties": {
    "addr:full":"11 Cranwell Close, Shnley Brook End Milton Keynes Buckinghamshire MK5 7BU",
    "addr:housenumber":"11",
    "addr:postcode":"mk5 7bu",
    "addr:street":"Cranwell Close Shnley Brook End",
    "iso:country":"GB",
    "sg:address":"11 Cranwell Close, Shnley Brook End",
    "sg:city":"Milton Keynes",
    "sg:classifiers":[
        {
            "category":"Professional",
            "subcategory":"Accounting & Tax Preparation",
            "type":"Services"
        }
    ],
    "sg:postcode":"MK5 7BU",
    "sg:province":"Buckinghamshire",
    "sg:tags":[
        "accountant"
    ],
    "wof:name":"Mancini Ltd.",
    "wof:placetype":"venue"
},
  "geometry": {"coordinates":[-0.78331,52.009411],"type":"Point"}
}