{
  "type": "Feature",
  "properties": {
    "addr:full":"23 Oxford Crescent Didcot Oxfordshire OX11 7AL",
    "addr:housenumber":"23",
    "addr:postcode":"ox11 7al",
    "addr:street":"Oxford Crescent",
    "iso:country":"GB",
    "sg:address":"23 Oxford Crescent",
    "sg:city":"Didcot",
    "sg:classifiers":[
        {
            "category":"Home & Garden",
            "subcategory":"Garden Supply",
            "type":"Retail Goods"
        }
    ],
    "sg:postcode":"OX11 7AL",
    "sg:province":"Oxfordshire",
    "sg:tags":[
        "sand",
        "gravel"
    ],
    "wof:name":"Richards Sand & Ballast",
    "wof:placetype":"venue"
},
  "geometry": {"coordinates":[-1.259557,51.605839],"type":"Point"}
}