{
  "type": "Feature",
  "properties": {
    "iso:country":"GB",
    "sg:address":"Unit E Port, Falmouth Boatyard, North Pde",
    "sg:city":"Falmouth",
    "sg:classifiers":[
        {
            "category":"Home & Garden",
            "subcategory":"Hardware",
            "type":"Retail Goods"
        },
        {
            "category":"Manufacturing",
            "subcategory":"Textiles",
            "type":"Manufacturing & Wholesale Goods"
        }
    ],
    "sg:phone":"+44 1326 313029",
    "sg:postcode":"TR11 2PB",
    "sg:province":"Cornwall",
    "sg:tags":[
        "mnfrs",
        "sealant",
        "glue",
        "floorcoverings",
        "adhesives"
    ],
    "wof:name":"Deadstop Decking Ltd",
    "wof:placetype":"venue"
},
  "geometry": {"coordinates":[-5.0800328255,50.1522064209],"type":"Point"}
}