{
  "type": "Feature",
  "properties": {
    "addr:full":"Caroline Park House Edinburgh City of Edinburgh EH5 1QJ",
    "addr:postcode":"eh5 1qj",
    "addr:street":"Caroline;House Edinburgh",
    "iso:country":"GB",
    "sg:address":"Caroline Park House",
    "sg:city":"Edinburgh",
    "sg:classifiers":[
        {
            "category":"Retail",
            "subcategory":"Portrait Studio",
            "type":"Services"
        },
        {
            "category":"Professional",
            "subcategory":"Art Services",
            "type":"Services"
        }
    ],
    "sg:phone":"+44 131 551 2424",
    "sg:postcode":"EH5 1QJ",
    "sg:province":"City of Edinburgh",
    "sg:tags":[
        "photographer",
        "commercial"
    ],
    "wof:name":"Andrew Parnell Photographics",
    "wof:placetype":"venue"
},
  "geometry": {"coordinates":[-3.2379889488,55.9780387878],"type":"Point"}
}