{
  "type": "Feature",
  "properties": {
    "iso:country":"GB",
    "sg:address":"Glyndwr Building, Glanfred Lane, Talybont",
    "sg:city":"Aberystwyth",
    "sg:classifiers":[
        {
            "category":"Food & Beverages",
            "subcategory":"Specialty",
            "type":"Retail Goods"
        }
    ],
    "sg:phone":"+44 1970 832511",
    "sg:postcode":"SY24 5BY",
    "sg:province":"Ceredigion",
    "sg:tags":[
        "product",
        "health"
    ],
    "wof:name":"Tropical Forest Products Ltd.",
    "wof:placetype":"venue"
},
  "geometry": {"coordinates":[-3.982149,52.486431],"type":"Point"}
}