{
  "type": "Feature",
  "properties": {
    "addr:full":"101 Unthank Road Norwich Norfolk NR2 2PE",
    "addr:housenumber":"101",
    "addr:postcode":"nr2 2pe",
    "addr:street":"Unthank Road Norwich Norfolk",
    "iso:country":"GB",
    "sg:address":"101 Unthank Road",
    "sg:city":"Norwich",
    "sg:classifiers":[
        {
            "category":"Food & Beverages",
            "subcategory":"Specialty",
            "type":"Retail Goods"
        }
    ],
    "sg:phone":"+44 1603 621650",
    "sg:postcode":"NR2 2PE",
    "sg:province":"Norfolk",
    "sg:tags":[
        "retailer",
        "product",
        "health"
    ],
    "wof:name":"D A Lowe",
    "wof:placetype":"venue"
},
  "geometry": {"coordinates":[1.2778,52.624886],"type":"Point"}
}