{
  "type": "Feature",
  "properties": {
    "addr:full":"2-3 Hambridge Lane Newbury Berkshire RG14 5TU",
    "addr:housenumber":"2-3",
    "addr:postcode":"rg14 5tu",
    "addr:street":"Hambridge Lane",
    "iso:country":"GB",
    "sg:address":"2-3 Hambridge Lane",
    "sg:city":"Newbury",
    "sg:classifiers":[
        {
            "category":"Home & Garden",
            "subcategory":"Home Furnishings",
            "type":"Retail Goods"
        }
    ],
    "sg:phone":"+44 1635 30373",
    "sg:postcode":"RG14 5TU",
    "sg:province":"Berkshire",
    "sg:tags":[
        "glassware",
        "china",
        "household"
    ],
    "wof:name":"Barbecco Ltd.",
    "wof:placetype":"venue"
},
  "geometry": {"coordinates":[-1.2970639467,51.3996276855],"type":"Point"}
}