{
  "type": "Feature",
  "properties": {
    "addr:full":"50 Curzon St West End Hampshire W1Y 7PN",
    "addr:housenumber":"50",
    "addr:postcode":"w1y 7pn",
    "addr:street":"Curzon St",
    "iso:country":"GB",
    "sg:address":"50 Curzon St",
    "sg:city":"West End",
    "sg:classifiers":[
        {
            "category":"Professional",
            "subcategory":"Engineering",
            "type":"Services"
        }
    ],
    "sg:phone":"+44 20 7499 9131",
    "sg:postcode":"W1Y 7PN",
    "sg:province":"Hampshire",
    "wof:name":"Ti Corporate Services Ltd",
    "wof:placetype":"venue"
},
  "geometry": {"coordinates":[-0.145911,51.506966],"type":"Point"}
}