{
  "type": "Feature",
  "properties": {
    "addr:full":"359 Kings Street Stoke-on-trent Staffordshire ST4 3EQ",
    "addr:housenumber":"359",
    "addr:postcode":"st4 3eq",
    "addr:street":"Kings Street",
    "iso:country":"GB",
    "sg:address":"359 Kings Street",
    "sg:city":"Stoke-on-trent",
    "sg:classifiers":[
        {
            "category":"Manufacturing",
            "subcategory":"Pottery",
            "type":"Manufacturing & Wholesale Goods"
        }
    ],
    "sg:phone":"+44 1782 596606",
    "sg:postcode":"ST4 3EQ",
    "sg:province":"Staffordshire",
    "wof:name":"Gift Match China",
    "wof:placetype":"venue"
},
  "geometry": {"coordinates":[-2.1438879967,52.9936065674],"type":"Point"}
}