{
  "type": "Feature",
  "properties": {
    "addr:full":"10 Summertown, Tooting London Greater London SW17 0AY",
    "addr:housenumber":"10",
    "addr:postcode":"sw17 0ay",
    "addr:street":"Summertown",
    "iso:country":"GB",
    "sg:address":"10 Summertown, Tooting",
    "sg:city":"London",
    "sg:classifiers":[
        {
            "category":"Bars & Pubs",
            "type":"Food & Drink"
        }
    ],
    "sg:phone":"+44 20 8946 3521",
    "sg:postcode":"SW17 0AY",
    "sg:province":"Greater London",
    "sg:tags":[
        "pubs",
        "inn"
    ],
    "wof:name":"Riverside Function Hall",
    "wof:placetype":"venue"
},
  "geometry": {"coordinates":[-0.185449,51.433784],"type":"Point"}
}