{
  "type": "Feature",
  "properties": {
    "iso:country":"GB",
    "sg:address":"152 Hawthorn Road",
    "sg:city":"Ashington",
    "sg:classifiers":[
        {
            "category":"Cinema",
            "subcategory":"Movie Rental",
            "type":"Entertainment"
        }
    ],
    "sg:postcode":"NE63 9BG",
    "sg:province":"Northumberland",
    "sg:tags":[
        "video",
        "library"
    ],
    "wof:name":"Pictures Video",
    "wof:placetype":"venue"
},
  "geometry": {"coordinates":[-1.561077,55.180206],"type":"Point"}
}