{
  "type": "Feature",
  "properties": {
    "addr:full":"The Grange, Earthcott Bristol Gloucestershire BS35 3TA",
    "addr:postcode":"bs35 3ta",
    "iso:country":"GB",
    "sg:address":"The Grange, Earthcott",
    "sg:city":"Bristol",
    "sg:classifiers":[
        {
            "category":"Shopping",
            "subcategory":"Department Store",
            "type":"Retail Goods"
        }
    ],
    "sg:postcode":"BS35 3TA",
    "sg:province":"Gloucestershire",
    "wof:name":"Southmead Limes  &  Garden Supplies Ltd",
    "wof:placetype":"venue"
},
  "geometry": {"coordinates":[-2.526344,51.589973],"type":"Point"}
}