{
  "type": "Feature",
  "properties": {
    "iso:country":"GB",
    "sg:address":"27 Station Rd",
    "sg:city":"Rickmansworth",
    "sg:classifiers":[
        {
            "category":"Restaurant",
            "type":"Food & Drink"
        }
    ],
    "sg:phone":"+44 1923 778013",
    "sg:postcode":"WD3 1QP",
    "sg:province":"Hertfordshire",
    "sg:tags":[
        "chinese"
    ],
    "wof:name":"Happy House Peking Cuisine",
    "wof:placetype":"venue"
},
  "geometry": {"coordinates":[-0.4721859992,51.6402053833],"type":"Point"}
}