{
  "type": "Feature",
  "properties": {
    "iso:country":"GB",
    "sg:address":"6 Bowers Close",
    "sg:city":"Guildford",
    "sg:classifiers":[
        {
            "category":"Health Services",
            "subcategory":"Dentist",
            "type":"Services"
        }
    ],
    "sg:phone":"+44 1483 539119",
    "sg:postcode":"GU4 7NE",
    "sg:province":"Surrey",
    "sg:tags":[
        "technician",
        "instrument",
        "dental"
    ],
    "wof:name":"R.O Baker",
    "wof:placetype":"venue"
},
  "geometry": {"coordinates":[-0.5469740033,51.2627792358],"type":"Point"}
}