{
  "type": "Feature",
  "properties": {
    "addr:full":"26 Dorchester Road Huddersfield West Yorkshire HD2 2JZ",
    "addr:housenumber":"26",
    "addr:postcode":"hd2 2jz",
    "addr:street":"Dorchester Road",
    "iso:country":"GB",
    "sg:address":"26 Dorchester Road",
    "sg:city":"Huddersfield",
    "sg:classifiers":[
        {
            "category":"Organizations",
            "subcategory":"Non-profit Organization",
            "type":"Services"
        }
    ],
    "sg:phone":"+44 1484 428626",
    "sg:postcode":"HD2 2JZ",
    "sg:province":"West Yorkshire",
    "sg:tags":[
        "charitable",
        "organisation",
        "voluntary",
        "charity"
    ],
    "wof:name":"Cards for Good Causes Ltd.",
    "wof:placetype":"venue"
},
  "geometry": {"coordinates":[-1.780899,53.680061],"type":"Point"}
}