{
  "type": "Feature",
  "properties": {
    "addr:full":"12a West Langlands Street Kilmarnock East Ayrshire KA1 2PY",
    "addr:housenumber":"12a",
    "addr:postcode":"ka1 2py",
    "addr:street":"West Langlands Street",
    "iso:country":"GB",
    "sg:address":"12a West Langlands Street",
    "sg:city":"Kilmarnock",
    "sg:classifiers":[
        {
            "category":"Organizations",
            "subcategory":"Membership Organization",
            "type":"Services"
        },
        {
            "category":"Recreation",
            "type":"Entertainment"
        }
    ],
    "sg:phone":"+44 1563 532619",
    "sg:postcode":"KA1 2PY",
    "sg:province":"East Ayrshire",
    "sg:tags":[
        "club",
        "snooker",
        "hall"
    ],
    "wof:name":"Pyramid Snooker Club",
    "wof:placetype":"venue"
},
  "geometry": {"coordinates":[-4.5025968552,55.6117362976],"type":"Point"}
}