{
  "type": "Feature",
  "properties": {
    "iso:country":"GB",
    "sg:address":"59 Bruce Street, Plean",
    "sg:city":"Stirling",
    "sg:classifiers":[
        {
            "category":"Bus Charters",
            "type":"Transportation"
        }
    ],
    "sg:phone":"+44 1786 816664",
    "sg:postcode":"FK7 8DH",
    "sg:province":"Falkirk",
    "sg:tags":[
        "hire",
        "coach"
    ],
    "wof:name":"Myles Minicoach Services",
    "wof:placetype":"venue"
},
  "geometry": {"coordinates":[-3.869481,56.063866],"type":"Point"}
}