{
  "type": "Feature",
  "properties": {
    "addr:full":"17 Hatton Road Norwich Norfolk NR1 2PT",
    "addr:housenumber":"17",
    "addr:postcode":"nr1 2pt",
    "addr:street":"Hatton Road Norwich Norfolk",
    "iso:country":"GB",
    "sg:address":"17 Hatton Road",
    "sg:city":"Norwich",
    "sg:classifiers":[
        {
            "category":"Shopping",
            "subcategory":"Antiques",
            "type":"Retail Goods"
        }
    ],
    "sg:phone":"+44 1603 464746",
    "sg:postcode":"NR1 2PT",
    "sg:province":"Norfolk",
    "wof:name":"Silvermans",
    "wof:placetype":"venue"
},
  "geometry": {"coordinates":[1.295554,52.616577],"type":"Point"}
}