{
  "type": "Feature",
  "properties": {
    "addr:full":"Playing Fields, Tamworth Lane Mitcham Greater London CR4 1DH",
    "addr:postcode":"cr4 1dh",
    "addr:street":"Tamworth Lane",
    "iso:country":"GB",
    "sg:address":"Playing Fields, Tamworth Lane",
    "sg:city":"Mitcham",
    "sg:classifiers":[
        {
            "category":"Sports & Exercise",
            "subcategory":"Tennis Court",
            "type":"Entertainment"
        }
    ],
    "sg:phone":"+44 20 8648 3119",
    "sg:postcode":"CR4 1DH",
    "sg:province":"Greater London",
    "sg:tags":[
        "school",
        "leisure"
    ],
    "wof:name":"Westminster City School",
    "wof:placetype":"venue"
},
  "geometry": {"coordinates":[-0.164255,51.40715],"type":"Point"}
}