{
  "type": "Feature",
  "properties": {
    "addr:full":"5 The Pagoda Maidenhead Berkshire SL6 8EU",
    "addr:housenumber":"5",
    "addr:postcode":"sl6 8eu",
    "addr:street":"The Pagoda",
    "iso:country":"GB",
    "sg:address":"5 The Pagoda",
    "sg:city":"Maidenhead",
    "sg:classifiers":[
        {
            "category":"Manufacturing",
            "subcategory":"Buildings",
            "type":"Manufacturing & Wholesale Goods"
        },
        {
            "category":"Home & Garden",
            "subcategory":"Household Appliances",
            "type":"Retail Goods"
        }
    ],
    "sg:phone":"+44 1628 633901",
    "sg:postcode":"SL6 8EU",
    "sg:province":"Berkshire",
    "sg:tags":[
        "system",
        "domestic",
        "sales",
        "air conditioning"
    ],
    "wof:name":"S P G DISTRIBUTORS LTD",
    "wof:placetype":"venue"
},
  "geometry": {"coordinates":[-0.7058979869,51.532913208],"type":"Point"}
}