{
  "type": "Feature",
  "properties": {
    "iso:country":"GB",
    "sg:address":"The Labour Hall, Collingwood Rd",
    "sg:city":"Witham",
    "sg:classifiers":[
        {
            "category":"Organizations",
            "subcategory":"Professional Association",
            "type":"Services"
        }
    ],
    "sg:phone":"+44 1376 502735",
    "sg:postcode":"CM8 2EE",
    "sg:province":"Essex",
    "sg:tags":[
        "union",
        "trade"
    ],
    "wof:name":"GMB",
    "wof:placetype":"venue"
},
  "geometry": {"coordinates":[0.639991,51.800713],"type":"Point"}
}