{
  "type": "Feature",
  "properties": {
    "addr:full":"1 Albert St Huddersfield West Yorkshire HD1 3PJ",
    "addr:housenumber":"1",
    "addr:postcode":"hd1 3pj",
    "addr:street":"Albert St",
    "iso:country":"GB",
    "sg:address":"1 Albert St",
    "sg:city":"Huddersfield",
    "sg:classifiers":[
        {
            "category":"Fast Food",
            "type":"Food & Drink"
        }
    ],
    "sg:postcode":"HD1 3PJ",
    "sg:province":"West Yorkshire",
    "sg:tags":[
        "away",
        "take"
    ],
    "wof:name":"Palmer,C,",
    "wof:placetype":"venue"
},
  "geometry": {"coordinates":[-1.787558,53.638313],"type":"Point"}
}