{
  "type": "Feature",
  "properties": {
    "addr:full":"15 Nottingham Road, Gotham Nottingham Nottinghamshire NG11 0HE",
    "addr:housenumber":"15",
    "addr:postcode":"ng11 0he",
    "addr:street":"Nottingham Road",
    "iso:country":"GB",
    "sg:address":"15 Nottingham Road, Gotham",
    "sg:city":"Nottingham",
    "sg:classifiers":[
        {
            "category":"Organizations",
            "subcategory":"Community Association",
            "type":"Services"
        },
        {
            "category":"Organizations",
            "subcategory":"Membership Organization",
            "type":"Services"
        }
    ],
    "sg:phone":"+44 115 983 0391",
    "sg:postcode":"NG11 0HE",
    "sg:province":"Nottinghamshire",
    "sg:tags":[
        "club",
        "social"
    ],
    "wof:name":"The Royal British Legion",
    "wof:placetype":"venue"
},
  "geometry": {"coordinates":[-1.206054,52.868469],"type":"Point"}
}