{
  "type": "Feature",
  "properties": {
    "addr:full":"2nd Floor, 16 St Stevens Street Bristol City of Bristol BS1 1JR",
    "addr:housenumber":"2nd floor 16",
    "addr:postcode":"bs1 1jr",
    "addr:street":"St Stevens Street",
    "iso:country":"GB",
    "sg:address":"2nd Floor, 16 St Stevens Street",
    "sg:city":"Bristol",
    "sg:classifiers":[
        {
            "category":"Professional",
            "subcategory":"Advertising",
            "type":"Services"
        }
    ],
    "sg:phone":"+44 117 904 1283",
    "sg:postcode":"BS1 1JR",
    "sg:province":"City of Bristol",
    "sg:tags":[
        "directory"
    ],
    "wof:name":"D P Media",
    "wof:placetype":"venue"
},
  "geometry": {"coordinates":[-2.5951,51.453598],"type":"Point"}
}