{
  "type": "Feature",
  "properties": {
    "iso:country":"GB",
    "sg:address":"117 Linacre Rd",
    "sg:city":"Liverpool",
    "sg:classifiers":[
        {
            "category":"Real Estate",
            "subcategory":"Developer",
            "type":"Services"
        }
    ],
    "sg:phone":"+44 151 922 9999",
    "sg:postcode":"L21 8NS",
    "sg:province":"Merseyside",
    "sg:tags":[
        "property"
    ],
    "wof:name":"Ascot Developments",
    "wof:placetype":"venue"
},
  "geometry": {"coordinates":[-2.9978640079,53.4637565613],"type":"Point"}
}