{
  "type": "Feature",
  "properties": {
    "iso:country":"GB",
    "sg:address":"31 High Drive",
    "sg:city":"Gosport",
    "sg:classifiers":[
        {
            "category":"Manufacturing",
            "subcategory":"Tools & Machinery",
            "type":"Manufacturing & Wholesale Goods"
        }
    ],
    "sg:phone":"+44 1329 513039",
    "sg:postcode":"PO13 0QS",
    "sg:province":"Hampshire",
    "wof:name":"Cardinal Tools",
    "wof:placetype":"venue"
},
  "geometry": {"coordinates":[-1.175789,50.816193],"type":"Point"}
}