{
  "type": "Feature",
  "properties": {
    "addr:full":"James St West, Green Park Bath Bath and North East Somerset BA1 2BU",
    "addr:postcode":"ba1 2bu",
    "addr:street":"James St West Green Park",
    "iso:country":"GB",
    "sg:address":"James St West, Green Park",
    "sg:city":"Bath",
    "sg:classifiers":[
        {
            "category":"Farming",
            "subcategory":"Dairy Farm",
            "type":"Manufacturing & Wholesale Goods"
        }
    ],
    "sg:phone":"+44 1225 320800",
    "sg:postcode":"BA1 2BU",
    "sg:province":"Bath and North East Somerset",
    "wof:name":"Lordswood Farms Ltd.",
    "wof:placetype":"venue"
},
  "geometry": {"coordinates":[-2.3650588989,51.3812446594],"type":"Point"}
}