{
  "type": "Feature",
  "properties": {
    "addr:full":"White Lodge, Sandhurst Rd, Sandilands Mablethorpe Lincolnshire LN12 2RH",
    "addr:postcode":"ln12 2rh",
    "addr:street":"Sandhurst Rd",
    "iso:country":"GB",
    "sg:address":"White Lodge, Sandhurst Rd, Sandilands",
    "sg:city":"Mablethorpe",
    "sg:classifiers":[
        {
            "category":"Building & Trades",
            "subcategory":"Construction",
            "type":"Services"
        }
    ],
    "sg:phone":"+44 1507 441402",
    "sg:postcode":"LN12 2RH",
    "sg:province":"Lincolnshire",
    "sg:tags":[
        "builder"
    ],
    "wof:name":"M.D McAlpine",
    "wof:placetype":"venue"
},
  "geometry": {"coordinates":[0.2846809924,53.2996368408],"type":"Point"}
}