{
  "type": "Feature",
  "properties": {
    "iso:country":"GB",
    "sg:address":"18 Kingsway",
    "sg:city":"Harwich",
    "sg:classifiers":[
        {
            "category":"Organizations",
            "subcategory":"Non-profit Organization",
            "type":"Services"
        }
    ],
    "sg:phone":"+44 1255 242064",
    "sg:postcode":"CO12 3AB",
    "sg:province":"Essex",
    "sg:tags":[
        "organisation",
        "voluntary",
        "charity"
    ],
    "wof:name":"R Scott",
    "wof:placetype":"venue"
},
  "geometry": {"coordinates":[1.2806299925,51.9384536743],"type":"Point"}
}