{
  "type": "Feature",
  "properties": {
    "addr:full":"10 Old Road Warrington Cheshire WA4 1AY",
    "addr:housenumber":"10",
    "addr:postcode":"wa4 1ay",
    "addr:street":"Old Road",
    "iso:country":"GB",
    "sg:address":"10 Old Road",
    "sg:city":"Warrington",
    "sg:classifiers":[
        {
            "category":"Sports & Exercise",
            "subcategory":"Gym",
            "type":"Entertainment"
        }
    ],
    "sg:phone":"+44 1925 637335",
    "sg:postcode":"WA4 1AY",
    "sg:province":"Cheshire",
    "sg:tags":[
        "fitness",
        "health",
        "centre"
    ],
    "wof:name":"Warrington Hook & Jab",
    "wof:placetype":"venue"
},
  "geometry": {"coordinates":[-2.591019,53.384762],"type":"Point"}
}