{
  "type": "Feature",
  "properties": {
    "addr:full":"Stall 80 Pannier Market, Market Av Plymouth Devon PL1 1PE",
    "addr:housenumber":"80",
    "addr:postcode":"pl1 1pe",
    "addr:street":"Stall;Av Plymouth",
    "iso:country":"GB",
    "sg:address":"Stall 80 Pannier Market, Market Av",
    "sg:city":"Plymouth",
    "sg:classifiers":[
        {
            "category":"Deli",
            "type":"Food & Drink"
        }
    ],
    "sg:phone":"+44 1752 669563",
    "sg:postcode":"PL1 1PE",
    "sg:province":"Devon",
    "sg:tags":[
        "delicatessen"
    ],
    "wof:name":"Peppers Deli",
    "wof:placetype":"venue"
},
  "geometry": {"coordinates":[-4.14719,50.371479],"type":"Point"}
}