{
  "type": "Feature",
  "properties": {
    "iso:country":"GB",
    "sg:address":"Bank Top",
    "sg:city":"Aberdare",
    "sg:classifiers":[
        {
            "category":"Manufacturing",
            "subcategory":"Metals",
            "type":"Manufacturing & Wholesale Goods"
        },
        {
            "category":"Building & Trades",
            "subcategory":"Construction",
            "type":"Services"
        }
    ],
    "sg:phone":"+44 1685 811818",
    "sg:postcode":"CF44 9YP",
    "sg:province":"Neath Port Talbot",
    "sg:tags":[
        "steel",
        "fabricator",
        "welder",
        "erectors"
    ],
    "wof:name":"Cledwyn Saunders & Son Ltd.",
    "wof:placetype":"venue"
},
  "geometry": {"coordinates":[-3.445954,51.71246],"type":"Point"}
}