{
  "type": "Feature",
  "properties": {
    "iso:country":"GB",
    "sg:address":"15 Davnic Close, Pontypridd Street",
    "sg:city":"Barry",
    "sg:classifiers":[
        {
            "category":"Personal",
            "type":"Services"
        }
    ],
    "sg:postcode":"CF63 2HT",
    "sg:province":"The Vale of Glamorgan",
    "sg:tags":[
        "dressmaker"
    ],
    "wof:name":"Victoria Coppar Bridal",
    "wof:placetype":"venue"
},
  "geometry": {"coordinates":[-3.25424,51.412239],"type":"Point"}
}