{
  "type": "Feature",
  "properties": {
    "iso:country":"GB",
    "sg:address":"381-385 Tyburn Road, Erdington",
    "sg:city":"Birmingham",
    "sg:classifiers":[
        {
            "category":"Professional",
            "subcategory":"Printing & Photocopies",
            "type":"Services"
        }
    ],
    "sg:phone":"+44 121 328 7272",
    "sg:postcode":"B24 8HJ",
    "sg:province":"West Midlands",
    "sg:tags":[
        "duplicating",
        "copying"
    ],
    "wof:name":"Churchill Office Solutions Ltd.",
    "wof:placetype":"venue"
},
  "geometry": {"coordinates":[-1.840031,52.50843],"type":"Point"}
}