{
  "type": "Feature",
  "properties": {
    "iso:country":"GB",
    "sg:address":"Anchor Bay Wharf",
    "sg:city":"Erith",
    "sg:classifiers":[
        {
            "category":"Wholesale",
            "subcategory":"Scrap",
            "type":"Manufacturing & Wholesale Goods"
        }
    ],
    "sg:postcode":"DA8 2AW",
    "sg:province":"Kent",
    "sg:tags":[
        "waste",
        "metal"
    ],
    "wof:name":"Eastwood Metals",
    "wof:placetype":"venue"
},
  "geometry": {"coordinates":[0.180495,51.479221],"type":"Point"}
}