{
  "type": "Feature",
  "properties": {
    "addr:full":"95 Mossy Lea Road, Wrightington Wigan Lancashire WN6 9RE",
    "addr:housenumber":"95",
    "addr:postcode":"wn6 9re",
    "addr:street":"Mossy Lea Road",
    "iso:country":"GB",
    "sg:address":"95 Mossy Lea Road, Wrightington",
    "sg:city":"Wigan",
    "sg:classifiers":[
        {
            "category":"Travel",
            "subcategory":"Hotels & Motels",
            "type":"Entertainment"
        }
    ],
    "sg:postcode":"WN6 9RE",
    "sg:province":"Lancashire",
    "sg:tags":[
        "house",
        "guest"
    ],
    "wof:name":"A & R Sutton",
    "wof:placetype":"venue"
},
  "geometry": {"coordinates":[-2.695693,53.596416],"type":"Point"}
}