{
  "type": "Feature",
  "properties": {
    "iso:country":"GB",
    "sg:address":"Flat 3 De Walden Court, 85-89 New Cavendish Street",
    "sg:city":"West End",
    "sg:classifiers":[
        {
            "category":"Shopping",
            "subcategory":"Gifts & Souvenirs",
            "type":"Retail Goods"
        }
    ],
    "sg:postcode":"W1M 7RA",
    "sg:province":"Hampshire",
    "sg:tags":[
        "diy"
    ],
    "wof:name":"Weiser (u K ) Ltd",
    "wof:placetype":"venue"
},
  "geometry": {"coordinates":[-0.13899,51.50758],"type":"Point"}
}