{
  "type": "Feature",
  "properties": {
    "iso:country":"GB",
    "sg:address":"336 Hoylake Road",
    "sg:city":"Wirral",
    "sg:classifiers":[
        {
            "category":"Building & Trades",
            "subcategory":"Construction",
            "type":"Services"
        }
    ],
    "sg:phone":"+44 151 606 8000",
    "sg:postcode":"CH46 6DF",
    "sg:province":"Merseyside",
    "sg:tags":[
        "specialised",
        "contractor",
        "concrete"
    ],
    "wof:name":"Grade 2 Structural Repairs Ltd.",
    "wof:placetype":"venue"
},
  "geometry": {"coordinates":[-3.119426012,53.3984489441],"type":"Point"}
}