{
  "type": "Feature",
  "properties": {
    "addr:full":"6 Tauber Close, Elstree Borehamwood Hertfordshire WD6 3PE",
    "addr:housenumber":"6",
    "addr:postcode":"wd6 3pe",
    "addr:street":"Tauber Close",
    "iso:country":"GB",
    "sg:address":"6 Tauber Close, Elstree",
    "sg:city":"Borehamwood",
    "sg:classifiers":[
        {
            "category":"Shopping",
            "subcategory":"Beauty & Cosmetics",
            "type":"Retail Goods"
        }
    ],
    "sg:phone":"+44 20 8953 4172",
    "sg:postcode":"WD6 3PE",
    "sg:province":"Hertfordshire",
    "sg:tags":[
        "product"
    ],
    "wof:name":"Perfect Nails",
    "wof:placetype":"venue"
},
  "geometry": {"coordinates":[-0.288022,51.650677],"type":"Point"}
}