{
  "type": "Feature",
  "properties": {
    "addr:full":"2 The Walk, Kingswood Maidstone Kent ME17 3QQ",
    "addr:housenumber":"2",
    "addr:postcode":"me17 3qq",
    "addr:street":"The Walk",
    "iso:country":"GB",
    "sg:address":"2 The Walk, Kingswood",
    "sg:city":"Maidstone",
    "sg:classifiers":[
        {
            "category":"Professional",
            "subcategory":"Engineering",
            "type":"Services"
        }
    ],
    "sg:phone":"+44 1622 843015",
    "sg:postcode":"ME17 3QQ",
    "sg:province":"Kent",
    "sg:tags":[
        "contractor",
        "electrical",
        "engineer"
    ],
    "wof:name":"Dixon Electrical Services",
    "wof:placetype":"venue"
},
  "geometry": {"coordinates":[0.636126,51.227776],"type":"Point"}
}