{
  "type": "Feature",
  "properties": {
    "addr:full":"Eskdale Rd, Telford Est Shrewsbury Shropshire SY2 5UD",
    "addr:postcode":"sy2 5ud",
    "addr:street":"Eskdale Rd",
    "iso:country":"GB",
    "sg:address":"Eskdale Rd, Telford Est",
    "sg:city":"Shrewsbury",
    "sg:classifiers":[
        {
            "category":"Social Services",
            "type":"Services"
        }
    ],
    "sg:phone":"+44 1743 236868",
    "sg:postcode":"SY2 5UD",
    "sg:province":"Shropshire",
    "wof:name":"Shropshire County Council",
    "wof:placetype":"venue"
},
  "geometry": {"coordinates":[-2.721204,52.716927],"type":"Point"}
}