{
  "type": "Feature",
  "properties": {
    "iso:country":"GB",
    "sg:address":"700 Cranbrook Road",
    "sg:city":"Ilford",
    "sg:classifiers":[
        {
            "category":"Health Services",
            "subcategory":"Doctor",
            "type":"Services"
        }
    ],
    "sg:phone":"+44 20 8551 2341",
    "sg:postcode":"IG6 1HP",
    "sg:province":"Essex",
    "sg:tags":[
        "practitioners"
    ],
    "wof:name":"U D Shubhaker Dr",
    "wof:placetype":"venue"
},
  "geometry": {"coordinates":[0.07507,51.582329],"type":"Point"}
}