{
  "type": "Feature",
  "properties": {
    "addr:full":"Gatehead Business Park Oldham Lancashire OL3 5DE",
    "addr:postcode":"ol3 5de",
    "iso:country":"GB",
    "sg:address":"Gatehead Business Park",
    "sg:city":"Oldham",
    "sg:classifiers":[
        {
            "category":"Manufacturing",
            "subcategory":"Signs",
            "type":"Manufacturing & Wholesale Goods"
        }
    ],
    "sg:phone":"+44 1457 878806",
    "sg:postcode":"OL3 5DE",
    "sg:province":"Lancashire",
    "sg:tags":[
        "nameplate"
    ],
    "wof:name":"Sign Logic",
    "wof:placetype":"venue"
},
  "geometry": {"coordinates":[-2.021484,53.562721],"type":"Point"}
}