{
  "type": "Feature",
  "properties": {
    "iso:country":"GB",
    "sg:address":"791-811 Huddersfield Rd",
    "sg:city":"Dewsbury",
    "sg:classifiers":[
        {
            "category":"Autos & Motor Vehicles",
            "subcategory":"Fuel & Gas Station",
            "type":"Retail Goods"
        }
    ],
    "sg:postcode":"WF13 3LR",
    "sg:province":"West Yorkshire",
    "sg:tags":[
        "hr",
        "petrol"
    ],
    "wof:name":"McKeown,Desmond,",
    "wof:placetype":"venue"
},
  "geometry": {"coordinates":[-1.6695450544,53.6768341064],"type":"Point"}
}