{
  "type": "Feature",
  "properties": {
    "addr:full":"57b West Harbour Road, Granton Edinburgh City of Edinburgh EH5 1PP",
    "addr:housenumber":"57b",
    "addr:postcode":"eh5 1pp",
    "addr:street":"West Harbour Road",
    "iso:country":"GB",
    "sg:address":"57b West Harbour Road, Granton",
    "sg:city":"Edinburgh",
    "sg:classifiers":[
        {
            "category":"Utilities",
            "subcategory":"Telephone",
            "type":"Services"
        }
    ],
    "sg:phone":"+44 131 559 3080",
    "sg:postcode":"EH5 1PP",
    "sg:province":"City of Edinburgh",
    "sg:tags":[
        "telecommunication"
    ],
    "wof:name":"Simoco Europe Ltd.",
    "wof:placetype":"venue"
},
  "geometry": {"coordinates":[-3.2256109715,55.9813117981],"type":"Point"}
}