{
  "type": "Feature",
  "properties": {
    "addr:full":"Abbotsham Barton, Abbotsham Bideford Devon EX39 5AP",
    "addr:housenumber":"abbotsham;abbotsham",
    "addr:postcode":"ex39 5ap",
    "iso:country":"GB",
    "sg:address":"Abbotsham Barton, Abbotsham",
    "sg:city":"Bideford",
    "sg:classifiers":[
        {
            "category":"Landmark",
            "subcategory":"Tourist Attraction",
            "type":"Public Place"
        }
    ],
    "sg:phone":"+44 1237 472366",
    "sg:postcode":"EX39 5AP",
    "sg:province":"Devon",
    "sg:tags":[
        "interest"
    ],
    "wof:name":"The Big Sheep",
    "wof:placetype":"venue"
},
  "geometry": {"coordinates":[-4.2479348183,51.0157318115],"type":"Point"}
}