{
  "type": "Feature",
  "properties": {
    "addr:full":"9 Martyns Yard Market Harborough Leicestershire LE16 7AJ",
    "addr:housenumber":"9",
    "addr:postcode":"le16 7aj",
    "addr:street":"Martyns Yard",
    "iso:country":"GB",
    "sg:address":"9 Martyns Yard",
    "sg:city":"Market Harborough",
    "sg:classifiers":[
        {
            "category":"Manufacturing",
            "subcategory":"Apparel",
            "type":"Manufacturing & Wholesale Goods"
        }
    ],
    "sg:postcode":"LE16 7AJ",
    "sg:province":"Leicestershire",
    "sg:tags":[
        "mnfr",
        "footwear"
    ],
    "wof:name":"The Shoe Studio",
    "wof:placetype":"venue"
},
  "geometry": {"coordinates":[-0.9225789905,52.4793968201],"type":"Point"}
}