{
  "type": "Feature",
  "properties": {
    "addr:full":"25 Whitelock Rd Abingdon Oxfordshire OX14 1PA",
    "addr:housenumber":"25",
    "addr:postcode":"ox14 1pa",
    "addr:street":"Whitelock Rd",
    "iso:country":"GB",
    "sg:address":"25 Whitelock Rd",
    "sg:city":"Abingdon",
    "sg:classifiers":[
        {
            "category":"Professional",
            "subcategory":"Engineering",
            "type":"Services"
        }
    ],
    "sg:postcode":"OX14 1PA",
    "sg:province":"Oxfordshire",
    "sg:tags":[
        "civil",
        "engineer"
    ],
    "wof:name":"Whiting,Mack,",
    "wof:placetype":"venue"
},
  "geometry": {"coordinates":[-1.280913,51.679638],"type":"Point"}
}