{
  "type": "Feature",
  "properties": {
    "addr:full":"317 Putney Bridge Road London Greater London SW15 2PN",
    "addr:housenumber":"317",
    "addr:postcode":"sw15 2pn",
    "addr:street":"Putney Bridge Road",
    "iso:country":"GB",
    "sg:address":"317 Putney Bridge Road",
    "sg:city":"London",
    "sg:classifiers":[
        {
            "category":"Organizations",
            "subcategory":"Non-profit Organization",
            "type":"Services"
        }
    ],
    "sg:phone":"+44 20 8780 7200",
    "sg:postcode":"SW15 2PN",
    "sg:province":"Greater London",
    "sg:tags":[
        "organisation",
        "voluntary",
        "charity"
    ],
    "wof:name":"Voluntary Service Overseas",
    "wof:placetype":"venue"
},
  "geometry": {"coordinates":[-0.2134809941,51.4642982483],"type":"Point"}
}