{
  "type": "Feature",
  "properties": {
    "addr:full":"Malting Barn Fields Farm Road, Layer-de-la-haye Colchester Essex CO2 0JN",
    "addr:postcode":"co2 0jn",
    "addr:street":"Fields Farm Road",
    "iso:country":"GB",
    "sg:address":"Malting Barn Fields Farm Road, Layer-de-la-haye",
    "sg:city":"Colchester",
    "sg:classifiers":[
        {
            "category":"Building & Trades",
            "subcategory":"Construction",
            "type":"Services"
        }
    ],
    "sg:phone":"+44 1206 734583",
    "sg:postcode":"CO2 0JN",
    "sg:province":"Essex",
    "sg:tags":[
        "builder"
    ],
    "wof:name":"M W Burtenshaw",
    "wof:placetype":"venue"
},
  "geometry": {"coordinates":[0.85535,51.844631],"type":"Point"}
}