{
  "type": "Feature",
  "properties": {
    "addr:full":"2 West Park Drive Plymouth Devon PL7 2GZ",
    "addr:housenumber":"2",
    "addr:postcode":"pl7 2gz",
    "addr:street":"West Park Drive",
    "iso:country":"GB",
    "sg:address":"2 West Park Drive",
    "sg:city":"Plymouth",
    "sg:classifiers":[
        {
            "category":"Personal",
            "type":"Services"
        }
    ],
    "sg:postcode":"PL7 2GZ",
    "sg:province":"Devon",
    "sg:tags":[
        "wedding"
    ],
    "wof:name":"Yellow Rolls Royce Chauffeur Services",
    "wof:placetype":"venue"
},
  "geometry": {"coordinates":[-4.0234589577,50.3890266418],"type":"Point"}
}