{
  "type": "Feature",
  "properties": {
    "addr:full":"Unit N1 Freight Master Estate, Ferry Lane Rainham Essex RM13 9DA",
    "addr:postcode":"rm13 9da",
    "addr:street":"Ferry Lane",
    "iso:country":"GB",
    "sg:address":"Unit N1 Freight Master Estate, Ferry Lane",
    "sg:city":"Rainham",
    "sg:classifiers":[
        {
            "category":"Wholesale",
            "subcategory":"Scrap",
            "type":"Manufacturing & Wholesale Goods"
        }
    ],
    "sg:phone":"+44 1708 631174",
    "sg:postcode":"RM13 9DA",
    "sg:province":"Essex",
    "sg:tags":[
        "car",
        "breaker",
        "dismantlers"
    ],
    "wof:name":"Kas Auto Spares",
    "wof:placetype":"venue"
},
  "geometry": {"coordinates":[0.190426,51.517914],"type":"Point"}
}