{
  "type": "Feature",
  "properties": {
    "iso:country":"GB",
    "sg:address":"1 Broad Lane, Aughton",
    "sg:city":"Ormskirk",
    "sg:classifiers":[
        {
            "category":"Home & Garden",
            "subcategory":"Garden Supply",
            "type":"Retail Goods"
        }
    ],
    "sg:phone":"+44 151 526 0669",
    "sg:postcode":"L39 7HS",
    "sg:province":"Lancashire",
    "sg:tags":[
        "nursery",
        "centre"
    ],
    "wof:name":"Lloyds Nursery",
    "wof:placetype":"venue"
},
  "geometry": {"coordinates":[-2.9550170898,53.5561447144],"type":"Point"}
}