{
  "type": "Feature",
  "properties": {
    "addr:full":"11 The Triangle Bournemouth Dorset BH2 5RY",
    "addr:housenumber":"11",
    "addr:postcode":"bh2 5ry",
    "addr:street":"The Triangle",
    "iso:country":"GB",
    "sg:address":"11 The Triangle",
    "sg:city":"Bournemouth",
    "sg:classifiers":[
        {
            "category":"Recreation",
            "subcategory":"Dog Park",
            "type":"Entertainment"
        }
    ],
    "sg:phone":"+44 1202 555111",
    "sg:postcode":"BH2 5RY",
    "sg:province":"Dorset",
    "wof:name":"Lesave Dog Shop",
    "wof:placetype":"venue"
},
  "geometry": {"coordinates":[-1.885336,50.720348],"type":"Point"}
}