{
  "type": "Feature",
  "properties": {
    "addr:full":"Unit S8, Inchbrook Trading Estate, Bath Road, Woodchester Stroud Gloucestershire GL5 5EY",
    "addr:postcode":"gl5 5ey",
    "addr:street":"Bath Road",
    "iso:country":"GB",
    "sg:address":"Unit S8, Inchbrook Trading Estate, Bath Road, Woodchester",
    "sg:city":"Stroud",
    "sg:classifiers":[
        {
            "category":"Manufacturing",
            "subcategory":"Metals",
            "type":"Manufacturing & Wholesale Goods"
        },
        {
            "category":"Wholesale",
            "subcategory":"Metals & Minerals",
            "type":"Manufacturing & Wholesale Goods"
        }
    ],
    "sg:phone":"+44 1453 836273",
    "sg:postcode":"GL5 5EY",
    "sg:province":"Gloucestershire",
    "sg:tags":[
        "fabricator",
        "product",
        "sheet",
        "fabricated"
    ],
    "wof:name":"REFLEX METAL FABRICATIONS LTD",
    "wof:placetype":"venue"
},
  "geometry": {"coordinates":[-2.2324409485,51.744934082],"type":"Point"}
}