{
  "type": "Feature",
  "properties": {
    "addr:full":"Millenium House, Progress Way, Denton Manchester Greater Manchester M34 2GP",
    "addr:postcode":"m34 2gp",
    "addr:street":"Progress Way",
    "iso:country":"GB",
    "sg:address":"Millenium House, Progress Way, Denton",
    "sg:city":"Manchester",
    "sg:classifiers":[
        {
            "category":"Professional",
            "subcategory":"Engineering",
            "type":"Services"
        }
    ],
    "sg:phone":"+44 161 320 2700",
    "sg:postcode":"M34 2GP",
    "sg:province":"Greater Manchester",
    "sg:tags":[
        "design",
        "engineer"
    ],
    "wof:name":"Fdt Associates Ltd.",
    "wof:placetype":"venue"
},
  "geometry": {"coordinates":[-2.1419599056,53.4538002014],"type":"Point"}
}