{
  "type": "Feature",
  "properties": {
    "iso:country":"GB",
    "sg:address":"300 Caledonian Road",
    "sg:city":"London",
    "sg:classifiers":[
        {
            "category":"Health Services",
            "subcategory":"Dentist",
            "type":"Services"
        }
    ],
    "sg:phone":"+44 20 7607 2510",
    "sg:postcode":"N1 1BB",
    "sg:province":"Greater London",
    "wof:name":"M M Meer",
    "wof:placetype":"venue"
},
  "geometry": {"coordinates":[-0.1165930033,51.5396194458],"type":"Point"}
}