{
  "type": "Feature",
  "properties": {
    "addr:full":"Unit 3 Hyperion Way Reading Berkshire RG2 0HG",
    "addr:housenumber":"unit 3",
    "addr:postcode":"rg2 0hg",
    "addr:street":"Hyperion Way",
    "iso:country":"GB",
    "sg:address":"Unit 3 Hyperion Way",
    "sg:city":"Reading",
    "sg:classifiers":[
        {
            "category":"Building & Trades",
            "subcategory":"Construction",
            "type":"Services"
        }
    ],
    "sg:phone":"+44 118 975 7505",
    "sg:postcode":"RG2 0HG",
    "sg:province":"Berkshire",
    "sg:tags":[
        "glazier"
    ],
    "wof:name":"Greenberg Glass Ltd.",
    "wof:placetype":"venue"
},
  "geometry": {"coordinates":[-0.969618,51.43618],"type":"Point"}
}