{
  "type": "Feature",
  "properties": {
    "addr:full":"Burwood Farm Craven Arms Herefordshire SY7 9JS",
    "addr:housenumber":"craven",
    "addr:postcode":"sy7 9js",
    "addr:street":"Herefordshire",
    "iso:country":"GB",
    "sg:address":"Burwood Farm",
    "sg:city":"Craven Arms",
    "sg:classifiers":[
        {
            "category":"Banks & Credit Unions",
            "subcategory":"Investment Brokerage",
            "type":"Services"
        }
    ],
    "sg:phone":"+44 1584 861288",
    "sg:postcode":"SY7 9JS",
    "sg:province":"Herefordshire",
    "sg:tags":[
        "contractor"
    ],
    "wof:name":"H R Mold",
    "wof:placetype":"venue"
},
  "geometry": {"coordinates":[-2.8362390995,52.4393882751],"type":"Point"}
}