{
  "type": "Feature",
  "properties": {
    "iso:country":"GB",
    "sg:address":"London Road",
    "sg:city":"Ramsgate",
    "sg:classifiers":[
        {
            "category":"Health Services",
            "subcategory":"Podiatrist",
            "type":"Services"
        }
    ],
    "sg:phone":"+44 1843 594744",
    "sg:postcode":"CT11 0DR",
    "sg:province":"Kent",
    "sg:tags":[
        "podiatrists",
        "chiropodist"
    ],
    "wof:name":"Terri Carter",
    "wof:placetype":"venue"
},
  "geometry": {"coordinates":[1.397255,51.331959],"type":"Point"}
}