{
  "type": "Feature",
  "properties": {
    "iso:country":"GB",
    "sg:address":"Unit 4",
    "sg:city":"Tring",
    "sg:classifiers":[
        {
            "category":"Manufacturing",
            "subcategory":"Rubber & Plastics",
            "type":"Manufacturing & Wholesale Goods"
        }
    ],
    "sg:phone":"+44 1442 891055",
    "sg:postcode":"HP23 4JX",
    "sg:province":"Buckinghamshire",
    "sg:tags":[
        "product"
    ],
    "wof:name":"Cox Thermoforming Ltd.",
    "wof:placetype":"venue"
},
  "geometry": {"coordinates":[-0.675667,51.811363],"type":"Point"}
}