{
  "type": "Feature",
  "properties": {
    "addr:full":"12a Finstall Rd Bromsgrove Worcestershire B60 2DZ",
    "addr:housenumber":"12a",
    "addr:postcode":"b60 2dz",
    "addr:street":"Finstall Rd",
    "iso:country":"GB",
    "sg:address":"12a Finstall Rd",
    "sg:city":"Bromsgrove",
    "sg:classifiers":[
        {
            "category":"Building & Trades",
            "subcategory":"Construction",
            "type":"Services"
        }
    ],
    "sg:phone":"+44 1527 877465",
    "sg:postcode":"B60 2DZ",
    "sg:province":"Worcestershire",
    "sg:tags":[
        "joiner",
        "carpenter"
    ],
    "wof:name":"Lignum Crafts (Bromsgrove) Ltd",
    "wof:placetype":"venue"
},
  "geometry": {"coordinates":[-2.0467700958,52.3236083984],"type":"Point"}
}