{
  "type": "Feature",
  "properties": {
    "iso:country":"GB",
    "sg:address":"Calverhall, Willaston",
    "sg:city":"Whitchurch",
    "sg:classifiers":[
        {
            "category":"Home & Garden",
            "subcategory":"Garden Supply",
            "type":"Retail Goods"
        },
        {
            "category":"Farming",
            "subcategory":"Farm",
            "type":"Manufacturing & Wholesale Goods"
        }
    ],
    "sg:phone":"+44 1948 890668",
    "sg:postcode":"SY13 4PS",
    "sg:province":"Cheshire",
    "sg:tags":[
        "mixed",
        "bulb",
        "crop",
        "grower"
    ],
    "wof:name":"William G Bower",
    "wof:placetype":"venue"
},
  "geometry": {"coordinates":[-2.59314394,52.9317016602],"type":"Point"}
}