{
  "type": "Feature",
  "properties": {
    "addr:full":"Falcon Industrial Park Loughborough Leicestershire LE11 1HL",
    "addr:postcode":"le11 1hl",
    "addr:street":"Falcon Industrial Park",
    "iso:country":"GB",
    "sg:address":"Falcon Industrial Park",
    "sg:city":"Loughborough",
    "sg:classifiers":[
        {
            "category":"Manufacturing",
            "subcategory":"Metals",
            "type":"Manufacturing & Wholesale Goods"
        }
    ],
    "sg:phone":"+44 1509 556677",
    "sg:postcode":"LE11 1HL",
    "sg:province":"Leicestershire",
    "sg:tags":[
        "steel",
        "fabricator",
        "erectors"
    ],
    "wof:name":"ADEY STEEL LTD",
    "wof:placetype":"venue"
},
  "geometry": {"coordinates":[-1.2002899647,52.7803344727],"type":"Point"}
}