{
  "type": "Feature",
  "properties": {
    "iso:country":"GB",
    "sg:address":"Selborne House, Hillbrow Road",
    "sg:city":"Esher",
    "sg:classifiers":[
        {
            "category":"Retail",
            "subcategory":"Veterinary Services",
            "type":"Services"
        }
    ],
    "sg:postcode":"KT10 9UD",
    "sg:province":"Surrey",
    "sg:tags":[
        "surgeon"
    ],
    "wof:name":"John Ball & Associates",
    "wof:placetype":"venue"
},
  "geometry": {"coordinates":[-0.359555,51.371922],"type":"Point"}
}