{
  "type": "Feature",
  "properties": {
    "addr:full":"29 Cloth Fair London Greater London EC1A 7NN",
    "addr:housenumber":"29",
    "addr:postcode":"ec1a 7nn",
    "addr:street":"Cloth Fair",
    "iso:country":"GB",
    "sg:address":"29 Cloth Fair",
    "sg:city":"London",
    "sg:classifiers":[
        {
            "category":"Banks & Credit Unions",
            "subcategory":"Financial Services",
            "type":"Services"
        }
    ],
    "sg:phone":"+44 20 7796 4133",
    "sg:postcode":"EC1A 7NN",
    "sg:province":"Greater London",
    "sg:tags":[
        "adviser"
    ],
    "wof:name":"Hudson Sandler Ltd.",
    "wof:placetype":"venue"
},
  "geometry": {"coordinates":[-0.099405,51.519276],"type":"Point"}
}