{
  "type": "Feature",
  "properties": {
    "addr:full":"Olde Byre, Stoke Street, Rodney Stoke Cheddar Somerset BS27 3UP",
    "addr:postcode":"bs27 3up",
    "addr:street":"Stoke Street",
    "iso:country":"GB",
    "sg:address":"Olde Byre, Stoke Street, Rodney Stoke",
    "sg:city":"Cheddar",
    "sg:classifiers":[
        {
            "category":"Building & Trades",
            "subcategory":"Construction",
            "type":"Services"
        }
    ],
    "sg:phone":"+44 1749 870192",
    "sg:postcode":"BS27 3UP",
    "sg:province":"Somerset",
    "sg:tags":[
        "heating",
        "contractor"
    ],
    "wof:name":"D S I Heating Installations Ltd.",
    "wof:placetype":"venue"
},
  "geometry": {"coordinates":[-2.777659,51.279659],"type":"Point"}
}