{
  "type": "Feature",
  "properties": {
    "addr:full":"Woolcombe Hall, Lawn Vista Sidmouth Devon EX10 9BZ",
    "addr:postcode":"ex10 9bz",
    "addr:street":"Lawn;Sidmouth",
    "iso:country":"GB",
    "sg:address":"Woolcombe Hall, Lawn Vista",
    "sg:city":"Sidmouth",
    "sg:classifiers":[
        {
            "category":"Organizations",
            "subcategory":"Community Association",
            "type":"Services"
        },
        {
            "category":"Organizations",
            "subcategory":"Membership Organization",
            "type":"Services"
        }
    ],
    "sg:phone":"+44 1395 512181",
    "sg:postcode":"EX10 9BZ",
    "sg:province":"Devon",
    "sg:tags":[
        "club",
        "social"
    ],
    "wof:name":"Sidmouth Amateur Dramatics Society",
    "wof:placetype":"venue"
},
  "geometry": {"coordinates":[-3.237619,50.68745],"type":"Point"}
}