{
  "type": "Feature",
  "properties": {
    "addr:full":"26 Ryde Pl Lee On The Solent Hampshire PO13 9AU",
    "addr:housenumber":"26",
    "addr:postcode":"po13 9au",
    "addr:street":"Ryde Pl",
    "iso:country":"GB",
    "sg:address":"26 Ryde Pl",
    "sg:city":"Lee On The Solent",
    "sg:classifiers":[
        {
            "category":"Retail",
            "subcategory":"Driving School",
            "type":"Services"
        }
    ],
    "sg:phone":"+44 23 9255 2322",
    "sg:postcode":"PO13 9AU",
    "sg:province":"Hampshire",
    "wof:name":"Trent School Of Motoring",
    "wof:placetype":"venue"
},
  "geometry": {"coordinates":[-1.1892750263,50.7946014404],"type":"Point"}
}