{
  "type": "Feature",
  "properties": {
    "iso:country":"GB",
    "sg:address":"31b Market Place",
    "sg:city":"Ripley",
    "sg:classifiers":[
        {
            "category":"Health Services",
            "subcategory":"Health Practitioner",
            "type":"Services"
        }
    ],
    "sg:phone":"+44 1773 512249",
    "sg:postcode":"DE5 3HA",
    "sg:province":"Derbyshire",
    "sg:tags":[
        "osteopath"
    ],
    "wof:name":"A Lancashire",
    "wof:placetype":"venue"
},
  "geometry": {"coordinates":[-1.4078840017,53.0503196716],"type":"Point"}
}