{
  "type": "Feature",
  "properties": {
    "iso:country":"GB",
    "sg:address":"215 Deansbrook Road",
    "sg:city":"Edgware",
    "sg:classifiers":[
        {
            "category":"Retail",
            "subcategory":"Laundry & Dry Cleaning",
            "type":"Services"
        }
    ],
    "sg:phone":"+44 20 8959 4116",
    "sg:postcode":"HA8 9BU",
    "sg:province":"Greater London",
    "sg:tags":[
        "alteration"
    ],
    "wof:name":"A Votre Service",
    "wof:placetype":"venue"
},
  "geometry": {"coordinates":[-0.257823,51.610538],"type":"Point"}
}