{
  "type": "Feature",
  "properties": {
    "addr:full":"22 Forge Road Port Talbot Neath Port Talbot SA13 1NU",
    "addr:housenumber":"22",
    "addr:postcode":"sa13 1nu",
    "addr:street":"Forge Road",
    "iso:country":"GB",
    "sg:address":"22 Forge Road",
    "sg:city":"Port Talbot",
    "sg:classifiers":[
        {
            "category":"Retail",
            "subcategory":"Auto Repair",
            "type":"Services"
        }
    ],
    "sg:phone":"+44 1639 881992",
    "sg:postcode":"SA13 1NU",
    "sg:province":"Neath Port Talbot",
    "sg:tags":[
        "body",
        "car"
    ],
    "wof:name":"Spray Care Repairs",
    "wof:placetype":"venue"
},
  "geometry": {"coordinates":[-3.78196311,51.5959968567],"type":"Point"}
}