{
  "type": "Feature",
  "properties": {
    "addr:full":"Beulah Court, Albert Road Horley Surrey RH6 7HP",
    "addr:postcode":"rh6 7hp",
    "addr:street":"Beulah Court Albert Road",
    "iso:country":"GB",
    "sg:address":"Beulah Court, Albert Road",
    "sg:city":"Horley",
    "sg:classifiers":[
        {
            "category":"Airline",
            "type":"Transportation"
        }
    ],
    "sg:phone":"+44 845 607 6760",
    "sg:postcode":"RH6 7HP",
    "sg:province":"Surrey",
    "sg:website":"http://www.coair.com",
    "wof:name":"Continental Airlines Inc",
    "wof:placetype":"venue"
},
  "geometry": {"coordinates":[-0.163174,51.172359],"type":"Point"}
}