{
  "type": "Feature",
  "properties": {
    "addr:full":"68 Albert St London Greater London NW1 7NR",
    "addr:housenumber":"68",
    "addr:postcode":"nw1 7nr",
    "addr:street":"Albert St",
    "iso:country":"GB",
    "sg:address":"68 Albert St",
    "sg:city":"London",
    "sg:classifiers":[
        {
            "category":"Real Estate",
            "subcategory":"Architect",
            "type":"Services"
        }
    ],
    "sg:postcode":"NW1 7NR",
    "sg:province":"Greater London",
    "wof:name":"Matriarchitects Co-Operative Ltd",
    "wof:placetype":"venue"
},
  "geometry": {"coordinates":[-0.142587,51.535721],"type":"Point"}
}