{
  "type": "Feature",
  "properties": {
    "addr:full":"48 Nascot Wood Road Watford Hertfordshire WD17 4SL",
    "addr:housenumber":"48",
    "addr:postcode":"wd17 4sl",
    "addr:street":"Nascot Wood Road",
    "iso:country":"GB",
    "sg:address":"48 Nascot Wood Road",
    "sg:city":"Watford",
    "sg:classifiers":[
        {
            "category":"Professional",
            "type":"Services"
        }
    ],
    "sg:postcode":"WD17 4SL",
    "sg:province":"Hertfordshire",
    "sg:tags":[
        "caterer"
    ],
    "wof:name":"Supreme Caterers",
    "wof:placetype":"venue"
},
  "geometry": {"coordinates":[-0.4154169858,51.6750717163],"type":"Point"}
}