{
  "type": "Feature",
  "properties": {
    "iso:country":"GB",
    "sg:address":"3 Market Place",
    "sg:city":"Shipston-on-stour",
    "sg:classifiers":[
        {
            "category":"Professional",
            "subcategory":"Management & Consulting",
            "type":"Services"
        },
        {
            "category":"Military Area",
            "subcategory":"Air Force Base",
            "type":"Public Place"
        }
    ],
    "sg:phone":"+44 1608 664211",
    "sg:postcode":"CV36 4AG",
    "sg:province":"Warwickshire",
    "sg:tags":[
        "technician",
        "adviser",
        "safety",
        "environmental",
        "consultant"
    ],
    "sg:website":"http://www.habilis.co.uk",
    "wof:name":"Habilis Ltd",
    "wof:placetype":"venue"
},
  "geometry": {"coordinates":[-1.624594,52.063488],"type":"Point"}
}