{
  "type": "Feature",
  "properties": {
    "iso:country":"GB",
    "sg:address":"6 Radnor Green",
    "sg:city":"Middlesbrough",
    "sg:classifiers":[
        {
            "category":"Home & Garden",
            "subcategory":"Carpets & Floor Coverings",
            "type":"Retail Goods"
        }
    ],
    "sg:phone":"+44 1642 310698",
    "sg:postcode":"TS3 0EA",
    "sg:province":"North Yorkshire",
    "sg:tags":[
        "cleaner",
        "upholstery"
    ],
    "wof:name":"Steve McLean",
    "wof:placetype":"venue"
},
  "geometry": {"coordinates":[-1.19363,54.550163],"type":"Point"}
}