{
  "type": "Feature",
  "properties": {
    "addr:full":"3-4 Whitney Chambers, Fanshawe Avenue Barking Essex IG11 8TQ",
    "addr:housenumber":"3-4",
    "addr:postcode":"ig11 8tq",
    "addr:street":"Whitney Chambers Fanshawe Avenue",
    "iso:country":"GB",
    "sg:address":"3-4 Whitney Chambers, Fanshawe Avenue",
    "sg:city":"Barking",
    "sg:classifiers":[
        {
            "category":"Communications",
            "type":"Services"
        }
    ],
    "sg:phone":"+44 20 8507 7773",
    "sg:postcode":"IG11 8TQ",
    "sg:province":"Essex",
    "sg:tags":[
        "telecommunication"
    ],
    "wof:name":"Keep Intouch",
    "wof:placetype":"venue"
},
  "geometry": {"coordinates":[0.0811149999,51.539100647],"type":"Point"}
}