{
  "type": "Feature",
  "properties": {
    "iso:country":"GB",
    "sg:address":"Gloucester Road, Andoversford",
    "sg:city":"Cheltenham",
    "sg:classifiers":[
        {
            "category":"Education",
            "subcategory":"School",
            "type":"Public Place"
        }
    ],
    "sg:phone":"+44 1242 820407",
    "sg:postcode":"GL54 4HR",
    "sg:province":"Gloucestershire",
    "sg:tags":[
        "foundation",
        "college"
    ],
    "wof:name":"Andoversford Primary School",
    "wof:placetype":"venue"
},
  "geometry": {"coordinates":[-1.969802,51.872612],"type":"Point"}
}