{
  "type": "Feature",
  "properties": {
    "addr:full":"Knutsford Road, Rodeheath Stoke-on-trent Cheshire ST7 3QT",
    "addr:postcode":"st7 3qt",
    "addr:street":"Knutsford Road",
    "iso:country":"GB",
    "sg:address":"Knutsford Road, Rodeheath",
    "sg:city":"Stoke-on-trent",
    "sg:classifiers":[
        {
            "category":"Retail",
            "subcategory":"Auto Repair",
            "type":"Services"
        }
    ],
    "sg:postcode":"ST7 3QT",
    "sg:province":"Cheshire",
    "sg:tags":[
        "modification",
        "garage"
    ],
    "wof:name":"Smithy Garage",
    "wof:placetype":"venue"
},
  "geometry": {"coordinates":[-2.2860810757,53.1086120605],"type":"Point"}
}