{
  "type": "Feature",
  "properties": {
    "addr:full":"Highfield Farm, York Road Knaresborough North Yorkshire HG5 0SU",
    "addr:housenumber":"highfield",
    "addr:postcode":"hg5 0su",
    "addr:street":"York Road",
    "iso:country":"GB",
    "sg:address":"Highfield Farm, York Road",
    "sg:city":"Knaresborough",
    "sg:classifiers":[
        {
            "category":"Farming",
            "subcategory":"Livestock Farm",
            "type":"Manufacturing & Wholesale Goods"
        }
    ],
    "sg:phone":"+44 1423 862533",
    "sg:postcode":"HG5 0SU",
    "sg:province":"North Yorkshire",
    "sg:tags":[
        "others"
    ],
    "wof:name":"J R Yates",
    "wof:placetype":"venue"
},
  "geometry": {"coordinates":[-1.4663720131,54.0082893372],"type":"Point"}
}