{
  "type": "Feature",
  "properties": {
    "addr:full":"67 Bradford Road, Riddlesden Keighley West Yorkshire BD21 4EZ",
    "addr:housenumber":"67",
    "addr:postcode":"bd21 4ez",
    "addr:street":"Bradford Road;West",
    "iso:country":"GB",
    "sg:address":"67 Bradford Road, Riddlesden",
    "sg:city":"Keighley",
    "sg:classifiers":[
        {
            "category":"Food & Beverages",
            "subcategory":"Meat & Fish",
            "type":"Retail Goods"
        }
    ],
    "sg:phone":"+44 1535 662437",
    "sg:postcode":"BD21 4EZ",
    "sg:province":"West Yorkshire",
    "sg:tags":[
        "fishmonger",
        "chip",
        "related"
    ],
    "wof:name":"CRESCENT FISHERIES",
    "wof:placetype":"venue"
},
  "geometry": {"coordinates":[-1.8960490227,53.873550415],"type":"Point"}
}