{
  "type": "Feature",
  "properties": {
    "addr:full":"48 Tregenver Rd Falmouth Cornwall TR11 2QP",
    "addr:housenumber":"48",
    "addr:postcode":"tr11 2qp",
    "addr:street":"Tregenver Rd",
    "iso:country":"GB",
    "sg:address":"48 Tregenver Rd",
    "sg:city":"Falmouth",
    "sg:classifiers":[
        {
            "category":"Building & Trades",
            "subcategory":"Construction",
            "type":"Services"
        }
    ],
    "sg:phone":"+44 1326 569544",
    "sg:postcode":"TR11 2QP",
    "sg:province":"Cornwall",
    "sg:tags":[
        "roofing"
    ],
    "wof:name":"B & W Industrial Roofing",
    "wof:placetype":"venue"
},
  "geometry": {"coordinates":[-5.0844750404,50.1542396545],"type":"Point"}
}