{
  "type": "Feature",
  "properties": {
    "iso:country":"GB",
    "sg:address":"Sitwell Way",
    "sg:city":"Port Talbot",
    "sg:classifiers":[
        {
            "category":"Organizations",
            "subcategory":"Membership Organization",
            "type":"Services"
        }
    ],
    "sg:phone":"+44 1639 882434",
    "sg:postcode":"SA12 6BP",
    "sg:province":"Neath Port Talbot",
    "sg:tags":[
        "club"
    ],
    "wof:name":"Green Stars R F C Aberavon",
    "wof:placetype":"venue"
},
  "geometry": {"coordinates":[-3.803222,51.587559],"type":"Point"}
}