{
  "type": "Feature",
  "properties": {
    "iso:country":"GB",
    "sg:address":"167 Telegraph Road, Heswall",
    "sg:city":"Wirral",
    "sg:classifiers":[
        {
            "category":"Home & Garden",
            "subcategory":"Home Furnishings",
            "type":"Retail Goods"
        }
    ],
    "sg:phone":"+44 151 342 8545",
    "sg:postcode":"CH60 7SE",
    "sg:province":"Merseyside",
    "sg:tags":[
        "furnishers",
        "planner",
        "kitchen"
    ],
    "wof:name":"Heswall Kitchens Ltd.",
    "wof:placetype":"venue"
},
  "geometry": {"coordinates":[-3.100005,53.32856],"type":"Point"}
}