{
  "type": "Feature",
  "properties": {
    "addr:full":"Newstead Court, 41 Newstead Road Bournemouth Dorset BH6 3HL",
    "addr:housenumber":"41",
    "addr:postcode":"bh6 3hl",
    "addr:street":"Newstead;Newstead Road",
    "iso:country":"GB",
    "sg:address":"Newstead Court, 41 Newstead Road",
    "sg:city":"Bournemouth",
    "sg:classifiers":[
        {
            "category":"Professional",
            "subcategory":"Management & Consulting",
            "type":"Services"
        }
    ],
    "sg:phone":"+44 1202 425828",
    "sg:postcode":"BH6 3HL",
    "sg:province":"Dorset",
    "sg:tags":[
        "consultant",
        "business"
    ],
    "wof:name":"V A M Associates",
    "wof:placetype":"venue"
},
  "geometry": {"coordinates":[-1.8027240038,50.7231330872],"type":"Point"}
}