{
  "type": "Feature",
  "properties": {
    "addr:full":"Pitt Road, Freemantle Southampton Hampshire SO15 3FQ",
    "addr:postcode":"so15 3fq",
    "addr:street":"Pitt Road",
    "iso:country":"GB",
    "sg:address":"Pitt Road, Freemantle",
    "sg:city":"Southampton",
    "sg:classifiers":[
        {
            "category":"Manufacturing",
            "subcategory":"Metals",
            "type":"Manufacturing & Wholesale Goods"
        }
    ],
    "sg:phone":"+44 23 8022 8014",
    "sg:postcode":"SO15 3FQ",
    "sg:province":"Hampshire",
    "wof:name":"Precise Electro-Plating Works Ltd.",
    "wof:placetype":"venue"
},
  "geometry": {"coordinates":[-1.4265860319,50.9133834839],"type":"Point"}
}