{
  "type": "Feature",
  "properties": {
    "addr:full":"Unit 109, Great Western Designer Village Swindon Wiltshire SN2 2DY",
    "addr:housenumber":"109",
    "addr:postcode":"sn2 2dy",
    "addr:street":"Great;Swindon",
    "iso:country":"GB",
    "sg:address":"Unit 109, Great Western Designer Village",
    "sg:city":"Swindon",
    "sg:classifiers":[
        {
            "category":"Shopping",
            "subcategory":"Clothing, Apparel, & Fashions",
            "type":"Retail Goods"
        }
    ],
    "sg:postcode":"SN2 2DY",
    "sg:province":"Wiltshire",
    "sg:tags":[
        "shop",
        "hat"
    ],
    "wof:name":"Cap It All",
    "wof:placetype":"venue"
},
  "geometry": {"coordinates":[-1.8030289412,51.5688018799],"type":"Point"}
}