{
  "type": "Feature",
  "properties": {
    "iso:country":"GB",
    "sg:address":"37 Grove Park",
    "sg:city":"Tring",
    "sg:classifiers":[
        {
            "category":"Professional",
            "type":"Services"
        },
        {
            "category":"Fast Food",
            "type":"Food & Drink"
        }
    ],
    "sg:phone":"+44 1442 822319",
    "sg:postcode":"HP23 5JS",
    "sg:province":"Buckinghamshire",
    "sg:tags":[
        "take",
        "away",
        "meal",
        "outlet",
        "caterer"
    ],
    "wof:name":"CATERMASTER",
    "wof:placetype":"venue"
},
  "geometry": {"coordinates":[-0.650390029,51.800113678],"type":"Point"}
}