{
  "type": "Feature",
  "properties": {
    "addr:full":"114 Queen Margaret Drive Glasgow Glasgow City G20 8NZ",
    "addr:housenumber":"114",
    "addr:postcode":"g20 8nz",
    "addr:street":"Queen Margaret Drive",
    "iso:country":"GB",
    "sg:address":"114 Queen Margaret Drive",
    "sg:city":"Glasgow",
    "sg:classifiers":[
        {
            "category":"Fast Food",
            "type":"Food & Drink"
        }
    ],
    "sg:phone":"+44 141 945 3603",
    "sg:postcode":"G20 8NZ",
    "sg:province":"Glasgow City",
    "sg:tags":[
        "away",
        "take"
    ],
    "wof:name":"New Curryland Three in One",
    "wof:placetype":"venue"
},
  "geometry": {"coordinates":[-4.284069,55.880951],"type":"Point"}
}