{
  "type": "Feature",
  "properties": {
    "iso:country":"GB",
    "sg:address":"194 High Street",
    "sg:city":"London",
    "sg:classifiers":[
        {
            "category":"Food & Beverages",
            "subcategory":"Fruits & Vegetables",
            "type":"Retail Goods"
        },
        {
            "category":"Food & Beverages",
            "subcategory":"Groceries & Convenience Stores",
            "type":"Retail Goods"
        }
    ],
    "sg:phone":"+44 20 8521 7333",
    "sg:postcode":"E17 7JH",
    "sg:province":"Greater London",
    "sg:tags":[
        "greengrocer"
    ],
    "wof:name":"PAK",
    "wof:placetype":"venue"
},
  "geometry": {"coordinates":[-0.022532,51.584171],"type":"Point"}
}