{
  "type": "Feature",
  "properties": {
    "iso:country":"GB",
    "sg:address":"24 Mayflower Drive",
    "sg:city":"Yateley",
    "sg:classifiers":[
        {
            "category":"Professional",
            "subcategory":"Engineering",
            "type":"Services"
        },
        {
            "category":"Building & Trades",
            "subcategory":"Electrical",
            "type":"Services"
        }
    ],
    "sg:phone":"+44 1252 860771",
    "sg:postcode":"GU46 7RR",
    "sg:province":"Hampshire",
    "sg:tags":[
        "engineer",
        "electrician",
        "contractor"
    ],
    "wof:name":"Alpha Omega Site Services",
    "wof:placetype":"venue"
},
  "geometry": {"coordinates":[-0.845842,51.346542],"type":"Point"}
}