{
  "type": "Feature",
  "properties": {
    "iso:country":"GB",
    "sg:address":"South Norwood A E Centre, Sandown Road",
    "sg:city":"London",
    "sg:classifiers":[
        {
            "category":"Organizations",
            "subcategory":"Non-profit Organization",
            "type":"Services"
        }
    ],
    "sg:phone":"+44 20 8656 4560",
    "sg:postcode":"SE25 4XE",
    "sg:province":"Greater London",
    "sg:tags":[
        "organisation",
        "voluntary",
        "charity"
    ],
    "wof:name":"Refugee Project Croydon",
    "wof:placetype":"venue"
},
  "geometry": {"coordinates":[-0.0641800016,51.3940505981],"type":"Point"}
}