{
  "type": "Feature",
  "properties": {
    "iso:country":"GB",
    "sg:address":"72 Ousegate",
    "sg:city":"Selby",
    "sg:classifiers":[
        {
            "category":"Home & Garden",
            "subcategory":"Furniture",
            "type":"Retail Goods"
        }
    ],
    "sg:phone":"+44 1757 213308",
    "sg:postcode":"YO8 0NJ",
    "sg:province":"East Riding of Yorkshire",
    "wof:name":"Greens Furniture Warehouse",
    "wof:placetype":"venue"
},
  "geometry": {"coordinates":[-1.063812,53.784035],"type":"Point"}
}