{
  "type": "Feature",
  "properties": {
    "iso:country":"GB",
    "sg:address":"South Yorkshire Data Centre, Wentworth Industrial Park, Maple Road",
    "sg:city":"Barnsley",
    "sg:classifiers":[
        {
            "category":"Banks & Credit Unions",
            "subcategory":"Bank",
            "type":"Services"
        }
    ],
    "sg:phone":"+44 1226 749422",
    "sg:postcode":"S75 3DJ",
    "sg:province":"South Yorkshire",
    "wof:name":"Hsbc Bank Plc",
    "wof:placetype":"venue"
},
  "geometry": {"coordinates":[-1.49133,53.489899],"type":"Point"}
}