{
  "type": "Feature",
  "properties": {
    "addr:full":"Unit 5/6 Conder Quay, East Quay Bridgwater Somerset TA6 5AZ",
    "addr:housenumber":"unit 5 / 6",
    "addr:postcode":"ta6 5az",
    "addr:street":"Quay East Quay",
    "iso:country":"GB",
    "sg:address":"Unit 5/6 Conder Quay, East Quay",
    "sg:city":"Bridgwater",
    "sg:classifiers":[
        {
            "category":"Professional",
            "subcategory":"Business Services",
            "type":"Services"
        },
        {
            "category":"Shopping",
            "subcategory":"Pets & Pet Supplies",
            "type":"Retail Goods"
        }
    ],
    "sg:postcode":"TA6 5AZ",
    "sg:province":"Somerset",
    "sg:tags":[
        "import",
        "export",
        "agent"
    ],
    "wof:name":"Superbed",
    "wof:placetype":"venue"
},
  "geometry": {"coordinates":[-3.0138239861,51.1275558472],"type":"Point"}
}