{
  "type": "Feature",
  "properties": {
    "addr:full":"26 Fettiplace Close, Appleton Oxford Oxfordshire OX13 5LQ",
    "addr:housenumber":"26",
    "addr:postcode":"ox13 5lq",
    "addr:street":"Fettiplace Close",
    "iso:country":"GB",
    "sg:address":"26 Fettiplace Close, Appleton",
    "sg:city":"Oxford",
    "sg:classifiers":[
        {
            "category":"Wholesale",
            "subcategory":"Groceries",
            "type":"Manufacturing & Wholesale Goods"
        }
    ],
    "sg:phone":"+44 1865 821511",
    "sg:postcode":"OX13 5LQ",
    "sg:province":"Oxfordshire",
    "sg:tags":[
        "food",
        "supplier",
        "drink"
    ],
    "wof:name":"Candles of Oxford",
    "wof:placetype":"venue"
},
  "geometry": {"coordinates":[-1.359524,51.707539],"type":"Point"}
}