{
  "type": "Feature",
  "properties": {
    "iso:country":"GB",
    "sg:address":"Valelands Farm",
    "sg:city":"Heathfield",
    "sg:classifiers":[
        {
            "category":"Retail",
            "subcategory":"Driving School",
            "type":"Services"
        }
    ],
    "sg:phone":"+44 1883 722432",
    "sg:postcode":"TN21 9HP",
    "sg:province":"East Sussex",
    "wof:name":"Highway Driving Academy The",
    "wof:placetype":"venue"
},
  "geometry": {"coordinates":[0.274553,50.960346],"type":"Point"}
}