{
  "type": "Feature",
  "properties": {
    "iso:country":"GB",
    "sg:address":"Scott-law House, Lynch Road",
    "sg:city":"Berkeley",
    "sg:classifiers":[
        {
            "category":"Shopping",
            "subcategory":"Stationery & Office Supplies",
            "type":"Retail Goods"
        },
        {
            "category":"Professional",
            "subcategory":"Lawyer & Legal Services",
            "type":"Services"
        }
    ],
    "sg:phone":"+44 1453 811444",
    "sg:postcode":"GL13 9TA",
    "sg:province":"Gloucestershire",
    "wof:name":"Scott Law Ltd.",
    "wof:placetype":"venue"
},
  "geometry": {"coordinates":[-2.4682970047,51.6929283142],"type":"Point"}
}