{
  "type": "Feature",
  "properties": {
    "iso:country":"GB",
    "sg:address":"305 Upper Richmond Road West",
    "sg:city":"London",
    "sg:classifiers":[
        {
            "category":"Food & Beverages",
            "subcategory":"Bakery",
            "type":"Retail Goods"
        }
    ],
    "sg:phone":"+44 20 8878 6833",
    "sg:postcode":"SW14 8QS",
    "sg:province":"Greater London",
    "sg:tags":[
        "pizza"
    ],
    "wof:name":"Pizza Express",
    "wof:placetype":"venue"
},
  "geometry": {"coordinates":[-0.263465,51.464863],"type":"Point"}
}