{
  "type": "Feature",
  "properties": {
    "addr:full":"1 Watson Clo Warwick Warwickshire CV34 5SW",
    "addr:housenumber":"1",
    "addr:postcode":"cv34 5sw",
    "addr:street":"Watson Clo",
    "iso:country":"GB",
    "sg:address":"1 Watson Clo",
    "sg:city":"Warwick",
    "sg:classifiers":[
        {
            "category":"Health Services",
            "subcategory":"Health Practitioner",
            "type":"Services"
        }
    ],
    "sg:phone":"+44 1926 497888",
    "sg:postcode":"CV34 5SW",
    "sg:province":"Warwickshire",
    "sg:tags":[
        "acupuncture"
    ],
    "wof:name":"Healthpoint",
    "wof:placetype":"venue"
},
  "geometry": {"coordinates":[-1.585936,52.292717],"type":"Point"}
}