{
  "type": "Feature",
  "properties": {
    "iso:country":"GB",
    "sg:address":"4 Nant Hall Road",
    "sg:city":"Prestatyn",
    "sg:classifiers":[
        {
            "category":"Professional",
            "subcategory":"Lawyer & Legal Services",
            "type":"Services"
        }
    ],
    "sg:phone":"+44 1745 856404",
    "sg:postcode":"LL19 9LH",
    "sg:province":"Denbighshire",
    "sg:tags":[
        "solicitor"
    ],
    "wof:name":"D K Macbryde & Co",
    "wof:placetype":"venue"
},
  "geometry": {"coordinates":[-3.394244,53.336121],"type":"Point"}
}