{
  "type": "Feature",
  "properties": {
    "iso:country":"GB",
    "sg:address":"16 Kirby Road",
    "sg:city":"Blackpool",
    "sg:classifiers":[
        {
            "category":"Travel",
            "subcategory":"Hotels & Motels",
            "type":"Entertainment"
        }
    ],
    "sg:phone":"+44 1253 294717",
    "sg:postcode":"FY1 6EB",
    "sg:province":"Lancashire",
    "wof:name":"Bank House Hotel",
    "wof:placetype":"venue"
},
  "geometry": {"coordinates":[-3.0527620316,53.8060684204],"type":"Point"}
}