{
  "type": "Feature",
  "properties": {
    "iso:country":"GB",
    "sg:address":"The Gables, Toft",
    "sg:city":"Bourne",
    "sg:classifiers":[
        {
            "category":"Farming",
            "subcategory":"Poultry Farm",
            "type":"Manufacturing & Wholesale Goods"
        }
    ],
    "sg:phone":"+44 1778 590281",
    "sg:postcode":"PE10 0JT",
    "sg:province":"Lincolnshire",
    "sg:tags":[
        "game",
        "farmer"
    ],
    "wof:name":"I S A Poultry Services",
    "wof:placetype":"venue"
},
  "geometry": {"coordinates":[-0.4155740142,52.7421188354],"type":"Point"}
}