{
  "type": "Feature",
  "properties": {
    "addr:full":"16 Skeyton New Road North Walsham Norfolk NR28 0BU",
    "addr:housenumber":"16",
    "addr:postcode":"nr28 0bu",
    "addr:street":"Skeyton New Road",
    "iso:country":"GB",
    "sg:address":"16 Skeyton New Road",
    "sg:city":"North Walsham",
    "sg:classifiers":[
        {
            "category":"Professional",
            "subcategory":"Computer Services",
            "type":"Services"
        }
    ],
    "sg:phone":"+44 117 947 5518",
    "sg:postcode":"NR28 0BU",
    "sg:province":"Norfolk",
    "sg:tags":[
        "aided",
        "design"
    ],
    "wof:name":"L G  Engineering Services Ltd.",
    "wof:placetype":"venue"
},
  "geometry": {"coordinates":[1.3783450127,52.8204078674],"type":"Point"}
}