{
  "type": "Feature",
  "properties": {
    "addr:full":"Meadowside, North Street Hailsham East Sussex BN27 4DR",
    "addr:postcode":"bn27 4dr",
    "addr:street":"North Street",
    "iso:country":"GB",
    "sg:address":"Meadowside, North Street",
    "sg:city":"Hailsham",
    "sg:classifiers":[
        {
            "category":"Building & Trades",
            "subcategory":"Plumbing",
            "type":"Services"
        }
    ],
    "sg:phone":"+44 1323 844483",
    "sg:postcode":"BN27 4DR",
    "sg:province":"East Sussex",
    "sg:tags":[
        "heating"
    ],
    "wof:name":"C W Carr & Co",
    "wof:placetype":"venue"
},
  "geometry": {"coordinates":[0.25652,50.865383],"type":"Point"}
}