{
  "type": "Feature",
  "properties": {
    "addr:full":"26 Northbrook Street Newbury Berkshire RG14 1DJ",
    "addr:housenumber":"26",
    "addr:postcode":"rg14 1dj",
    "addr:street":"Northbrook Street",
    "iso:country":"GB",
    "sg:address":"26 Northbrook Street",
    "sg:city":"Newbury",
    "sg:classifiers":[
        {
            "category":"Building & Trades",
            "subcategory":"Construction",
            "type":"Services"
        }
    ],
    "sg:postcode":"RG14 1DJ",
    "sg:province":"Berkshire",
    "sg:tags":[
        "builder"
    ],
    "wof:name":"Denka (construction) Ltd",
    "wof:placetype":"venue"
},
  "geometry": {"coordinates":[-1.3243249655,51.4033737183],"type":"Point"}
}