{
  "type": "Feature",
  "properties": {
    "addr:full":"Hensons Lane, Thringstone Coalville Leicestershire LE67 8LJ",
    "addr:postcode":"le67 8lj",
    "addr:street":"Hensons Lane",
    "iso:country":"GB",
    "sg:address":"Hensons Lane, Thringstone",
    "sg:city":"Coalville",
    "sg:classifiers":[
        {
            "category":"Education",
            "subcategory":"School",
            "type":"Public Place"
        }
    ],
    "sg:postcode":"LE67 8LJ",
    "sg:province":"Leicestershire",
    "sg:tags":[
        "local",
        "authority"
    ],
    "wof:name":"Thringstone County Primary School",
    "wof:placetype":"venue"
},
  "geometry": {"coordinates":[-1.3728640079,52.7602958679],"type":"Point"}
}