{
  "type": "Feature",
  "properties": {
    "addr:full":"Heath Road Skegness Lincolnshire PE25 3ST",
    "addr:postcode":"pe25 3st",
    "addr:street":"Heath Road",
    "iso:country":"GB",
    "sg:address":"Heath Road",
    "sg:city":"Skegness",
    "sg:classifiers":[
        {
            "category":"Home & Garden",
            "subcategory":"Building Materials",
            "type":"Retail Goods"
        }
    ],
    "sg:phone":"+44 1754 611262",
    "sg:postcode":"PE25 3ST",
    "sg:province":"Lincolnshire",
    "sg:tags":[
        "polythene",
        "plastic"
    ],
    "wof:name":"C F N Extrusion Ltd.",
    "wof:placetype":"venue"
},
  "geometry": {"coordinates":[0.325951,53.142879],"type":"Point"}
}