{
  "type": "Feature",
  "properties": {
    "iso:country":"GB",
    "sg:address":"Hydro Garage, Beechgrove",
    "sg:city":"Moffat",
    "sg:classifiers":[
        {
            "category":"Building & Trades",
            "subcategory":"Landscaping Services",
            "type":"Services"
        },
        {
            "category":"Professional",
            "subcategory":"Engineering",
            "type":"Services"
        }
    ],
    "sg:phone":"+44 1683 220025",
    "sg:postcode":"DG10 9RU",
    "sg:province":"Dumfries and Galloway",
    "sg:tags":[
        "horticultural",
        "engineer",
        "agricultural"
    ],
    "wof:name":"D F Paton Agricultural Forest Engineers",
    "wof:placetype":"venue"
},
  "geometry": {"coordinates":[-3.445599,55.335194],"type":"Point"}
}