{
  "type": "Feature",
  "properties": {
    "addr:full":"9 Egremont Place Brighton East Sussex BN2 0GA",
    "addr:housenumber":"9",
    "addr:postcode":"bn2 0ga",
    "addr:street":"Egremont Place",
    "iso:country":"GB",
    "sg:address":"9 Egremont Place",
    "sg:city":"Brighton",
    "sg:classifiers":[
        {
            "category":"Real Estate",
            "subcategory":"Real Estate Agent",
            "type":"Services"
        }
    ],
    "sg:postcode":"BN2 0GA",
    "sg:province":"East Sussex",
    "wof:name":"Applegate Properties Limited",
    "wof:placetype":"venue"
},
  "geometry": {"coordinates":[-0.129395,50.82238],"type":"Point"}
}