{
  "type": "Feature",
  "properties": {
    "addr:full":"9 Crane Way Wimborne Dorset BH21 6FA",
    "addr:housenumber":"9",
    "addr:postcode":"bh21 6fa",
    "addr:street":"Crane Way",
    "iso:country":"GB",
    "sg:address":"9 Crane Way",
    "sg:city":"Wimborne",
    "sg:classifiers":[
        {
            "category":"Autos & Motor Vehicles",
            "subcategory":"Boat Sales",
            "type":"Retail Goods"
        }
    ],
    "sg:postcode":"BH21 6FA",
    "sg:province":"Dorset",
    "sg:tags":[
        "repair",
        "builder"
    ],
    "wof:name":"D J Kershaw Ltd.",
    "wof:placetype":"venue"
},
  "geometry": {"coordinates":[-1.8652089834,50.843624115],"type":"Point"}
}