{
  "type": "Feature",
  "properties": {
    "iso:country":"GB",
    "sg:address":"Cobwebs, Hayes Lane, Compton Dundon",
    "sg:city":"Somerton",
    "sg:classifiers":[
        {
            "category":"Manufacturing",
            "subcategory":"Apparel",
            "type":"Manufacturing & Wholesale Goods"
        }
    ],
    "sg:phone":"+44 1458 273071",
    "sg:postcode":"TA11 6PB",
    "sg:province":"Somerset",
    "sg:tags":[
        "mnfr",
        "footwear"
    ],
    "wof:name":"Feelfree Footwear",
    "wof:placetype":"venue"
},
  "geometry": {"coordinates":[-2.734899044,51.0541648865],"type":"Point"}
}