{
  "type": "Feature",
  "properties": {
    "addr:full":"Daton Pk, Bldg 2, Kelburn Ct, Birchwood Warrington Cheshire WA3 6JA",
    "addr:housenumber":"2",
    "addr:postcode":"wa3 6ja",
    "addr:street":"Daton Pk Bldg;Ct",
    "iso:country":"GB",
    "sg:address":"Daton Pk, Bldg 2, Kelburn Ct, Birchwood",
    "sg:city":"Warrington",
    "sg:classifiers":[
        {
            "category":"Professional",
            "subcategory":"Management & Consulting",
            "type":"Services"
        }
    ],
    "sg:phone":"+44 1925 883000",
    "sg:postcode":"WA3 6JA",
    "sg:province":"Cheshire",
    "sg:tags":[
        "consultant"
    ],
    "wof:name":"Ericsson Ltd",
    "wof:placetype":"venue"
},
  "geometry": {"coordinates":[-2.520899,53.422436],"type":"Point"}
}