{
  "type": "Feature",
  "properties": {
    "addr:full":"240 Lancaster Rd Notting Hill Greater London W11 4AH",
    "addr:housenumber":"240",
    "addr:postcode":"w11 4ah",
    "addr:street":"Lancaster Rd",
    "iso:country":"GB",
    "sg:address":"240 Lancaster Rd",
    "sg:city":"Notting Hill",
    "sg:classifiers":[
        {
            "category":"Organizations",
            "subcategory":"Non-profit Organization",
            "type":"Services"
        }
    ],
    "sg:phone":"+44 20 7792 4026",
    "sg:postcode":"W11 4AH",
    "sg:province":"Greater London",
    "sg:tags":[
        "organisation",
        "voluntary",
        "charity"
    ],
    "wof:name":"St. Mungo's Day Project",
    "wof:placetype":"venue"
},
  "geometry": {"coordinates":[-0.213831,51.515205],"type":"Point"}
}