{
  "type": "Feature",
  "properties": {
    "addr:full":"The Bungalow, Brickhill Pastures, Limbersey Lane Bedford Bedfordshire MK45 2EB",
    "addr:postcode":"mk45 2eb",
    "addr:street":"Limbersey Lane",
    "iso:country":"GB",
    "sg:address":"The Bungalow, Brickhill Pastures, Limbersey Lane",
    "sg:city":"Bedford",
    "sg:classifiers":[
        {
            "category":"Autos & Motor Vehicles",
            "subcategory":"Motorcycle Sales",
            "type":"Retail Goods"
        }
    ],
    "sg:phone":"+44 1525 406420",
    "sg:postcode":"MK45 2EB",
    "sg:province":"Bedfordshire",
    "sg:tags":[
        "chauffeur",
        "driven",
        "car"
    ],
    "wof:name":"Travel Right U K",
    "wof:placetype":"venue"
},
  "geometry": {"coordinates":[-0.4949940145,52.0279464722],"type":"Point"}
}