{
  "type": "Feature",
  "properties": {
    "iso:country":"GB",
    "sg:address":"42 High Street",
    "sg:city":"Barry",
    "sg:classifiers":[
        {
            "category":"Shopping",
            "subcategory":"Pharmacy",
            "type":"Retail Goods"
        }
    ],
    "sg:phone":"+44 1446 735207",
    "sg:postcode":"CF62 7YP",
    "sg:province":"The Vale of Glamorgan",
    "sg:tags":[
        "pharmacist",
        "dispensing",
        "chemist"
    ],
    "wof:name":"ANUERIN EVAN (CHEMIST)",
    "wof:placetype":"venue"
},
  "geometry": {"coordinates":[-3.282254,51.400829],"type":"Point"}
}