{
  "type": "Feature",
  "properties": {
    "iso:country":"GB",
    "sg:address":"Cornelius Drive",
    "sg:city":"Waterlooville",
    "sg:classifiers":[
        {
            "category":"Education",
            "subcategory":"School",
            "type":"Public Place"
        }
    ],
    "sg:phone":"+44 23 9226 8067",
    "sg:postcode":"PO7 8NT",
    "sg:province":"Hampshire",
    "sg:tags":[
        "local",
        "authority"
    ],
    "wof:name":"Queen'S Enclosure Primary School",
    "wof:placetype":"venue"
},
  "geometry": {"coordinates":[-1.013539,50.88636],"type":"Point"}
}