{
  "type": "Feature",
  "properties": {
    "addr:full":"Polston Parks Farm Ivybridge Devon PL21 0SB",
    "addr:housenumber":"ivybridge",
    "addr:postcode":"pl21 0sb",
    "addr:street":"Devon",
    "iso:country":"GB",
    "sg:address":"Polston Parks Farm",
    "sg:city":"Ivybridge",
    "sg:classifiers":[
        {
            "category":"Professional",
            "subcategory":"Engineering",
            "type":"Services"
        }
    ],
    "sg:phone":"+44 1548 830363",
    "sg:postcode":"PL21 0SB",
    "sg:province":"Devon",
    "wof:name":"John S Foale",
    "wof:placetype":"venue"
},
  "geometry": {"coordinates":[-3.9290390015,50.3872642517],"type":"Point"}
}