{
  "type": "Feature",
  "properties": {
    "addr:full":"67 Valley Side London Greater London E4 7SR",
    "addr:housenumber":"67",
    "addr:postcode":"e4 7sr",
    "iso:country":"GB",
    "sg:address":"67 Valley Side",
    "sg:city":"London",
    "sg:classifiers":[
        {
            "category":"Building & Trades",
            "subcategory":"Construction",
            "type":"Services"
        }
    ],
    "sg:phone":"+44 20 8524 6481",
    "sg:postcode":"E4 7SR",
    "sg:province":"Greater London",
    "sg:tags":[
        "builder"
    ],
    "wof:name":"Garden Fencing",
    "wof:placetype":"venue"
},
  "geometry": {"coordinates":[-0.0164989997,51.6300048828],"type":"Point"}
}