{
  "type": "Feature",
  "properties": {
    "addr:full":"36 Halsey St Chelsea Greater London SW3 2PT",
    "addr:housenumber":"36",
    "addr:postcode":"sw3 2pt",
    "addr:street":"Halsey St",
    "iso:country":"GB",
    "sg:address":"36 Halsey St",
    "sg:city":"Chelsea",
    "sg:classifiers":[
        {
            "category":"Professional",
            "subcategory":"Business Services",
            "type":"Services"
        }
    ],
    "sg:phone":"+44 20 7584 9199",
    "sg:postcode":"SW3 2PT",
    "sg:province":"Greater London",
    "sg:tags":[
        "import",
        "export",
        "agent"
    ],
    "wof:name":"Japan Vintners",
    "wof:placetype":"venue"
},
  "geometry": {"coordinates":[-0.163075,51.493652],"type":"Point"}
}