{
  "type": "Feature",
  "properties": {
    "addr:full":"4 Queens Road Brighton East Sussex BN1 3WA",
    "addr:housenumber":"4",
    "addr:postcode":"bn1 3wa",
    "addr:street":"Queens Road",
    "iso:country":"GB",
    "sg:address":"4 Queens Road",
    "sg:city":"Brighton",
    "sg:classifiers":[
        {
            "category":"Retail",
            "subcategory":"Driving School",
            "type":"Services"
        }
    ],
    "sg:phone":"+44 1273 327828",
    "sg:postcode":"BN1 3WA",
    "sg:province":"East Sussex",
    "wof:name":"Bsm",
    "wof:placetype":"venue"
},
  "geometry": {"coordinates":[-0.143376,50.824337],"type":"Point"}
}