{
  "type": "Feature",
  "properties": {
    "iso:country":"GB",
    "sg:address":"88 Bristol Road, Quedgeley",
    "sg:city":"Gloucester",
    "sg:classifiers":[
        {
            "category":"Social Services",
            "subcategory":"Retirement Home",
            "type":"Services"
        }
    ],
    "sg:phone":"+44 1452 883764",
    "sg:postcode":"GL2 6NA",
    "sg:province":"Gloucestershire",
    "sg:tags":[
        "residential",
        "care"
    ],
    "wof:name":"The Padova",
    "wof:placetype":"venue"
},
  "geometry": {"coordinates":[-2.27917,51.8186],"type":"Point"}
}