{
  "type": "Feature",
  "properties": {
    "iso:country":"GB",
    "sg:address":"55 Piccadilly",
    "sg:city":"Manchester",
    "sg:classifiers":[
        {
            "category":"Travel",
            "subcategory":"Hotels & Motels",
            "type":"Entertainment"
        }
    ],
    "sg:phone":"+44 161 236 5155",
    "sg:postcode":"M1 2AP",
    "sg:province":"Greater Manchester",
    "wof:name":"Gardens Hotel",
    "wof:placetype":"venue"
},
  "geometry": {"coordinates":[-2.234727,53.480869],"type":"Point"}
}