{
  "type": "Feature",
  "properties": {
    "addr:full":"Great Lodge Farm Bromsgrove Worcestershire B60 4HW",
    "addr:postcode":"b60 4hw",
    "iso:country":"GB",
    "sg:address":"Great Lodge Farm",
    "sg:city":"Bromsgrove",
    "sg:classifiers":[
        {
            "category":"Farming",
            "subcategory":"Farm",
            "type":"Manufacturing & Wholesale Goods"
        }
    ],
    "sg:phone":"+44 1527 821219",
    "sg:postcode":"B60 4HW",
    "sg:province":"Worcestershire",
    "sg:tags":[
        "mixed",
        "crop"
    ],
    "wof:name":"R Brian",
    "wof:placetype":"venue"
},
  "geometry": {"coordinates":[-2.0385699272,52.2683296204],"type":"Point"}
}