{
  "type": "Feature",
  "properties": {
    "addr:full":"157 High St Dumbarton Argyll and Bute G82 1NZ",
    "addr:housenumber":"157",
    "addr:postcode":"g82 1nz",
    "addr:street":"High St",
    "iso:country":"GB",
    "sg:address":"157 High St",
    "sg:city":"Dumbarton",
    "sg:classifiers":[
        {
            "category":"Home & Garden",
            "subcategory":"Hardware",
            "type":"Retail Goods"
        }
    ],
    "sg:phone":"+44 1389 764103",
    "sg:postcode":"G82 1NZ",
    "sg:province":"Argyll and Bute",
    "wof:name":"Batchelors Home & Garden Centre",
    "wof:placetype":"venue"
},
  "geometry": {"coordinates":[-4.573394,55.944492],"type":"Point"}
}