{
  "type": "Feature",
  "properties": {
    "addr:full":"1 St Johns Row, Murivance Shrewsbury Shropshire SY1 1JP",
    "addr:housenumber":"1",
    "addr:postcode":"murivance;sy1 1jp",
    "addr:street":"St Johns Row",
    "iso:country":"GB",
    "sg:address":"1 St Johns Row, Murivance",
    "sg:city":"Shrewsbury",
    "sg:classifiers":[
        {
            "category":"Professional",
            "subcategory":"Computer Services",
            "type":"Services"
        }
    ],
    "sg:phone":"+44 1743 355022",
    "sg:postcode":"SY1 1JP",
    "sg:province":"Shropshire",
    "sg:tags":[
        "consultant"
    ],
    "wof:name":"Mercurius Projects Ltd.",
    "wof:placetype":"venue"
},
  "geometry": {"coordinates":[-2.7564890385,52.707321167],"type":"Point"}
}