{
  "type": "Feature",
  "properties": {
    "addr:full":"Cobden Street Garage, Cobden Street, Briercliffe Burnley Lancashire BB10 2JP",
    "addr:postcode":"bb10 2jp",
    "addr:street":"Cobden;Cobden Street",
    "iso:country":"GB",
    "sg:address":"Cobden Street Garage, Cobden Street, Briercliffe",
    "sg:city":"Burnley",
    "sg:classifiers":[
        {
            "category":"Retail",
            "subcategory":"Auto Repair",
            "type":"Services"
        }
    ],
    "sg:phone":"+44 1282 832857",
    "sg:postcode":"BB10 2JP",
    "sg:province":"Lancashire",
    "sg:tags":[
        "modification",
        "garage",
        "related"
    ],
    "wof:name":"R H Classics",
    "wof:placetype":"venue"
},
  "geometry": {"coordinates":[-2.203044,53.812786],"type":"Point"}
}