{
  "type": "Feature",
  "properties": {
    "iso:country":"GB",
    "sg:address":"Afonwen, Chwilog",
    "sg:city":"Pwllheli",
    "sg:classifiers":[
        {
            "category":"Retail",
            "subcategory":"Laundry & Dry Cleaning",
            "type":"Services"
        }
    ],
    "sg:phone":"+44 1766 810264",
    "sg:postcode":"LL53 6RX",
    "sg:province":"Gwynedd",
    "sg:tags":[
        "launderette"
    ],
    "wof:name":"Afonwen Services Ltd.",
    "wof:placetype":"venue"
},
  "geometry": {"coordinates":[-4.320765,52.913475],"type":"Point"}
}