{
  "type": "Feature",
  "properties": {
    "addr:full":"Pennyhill Lane West Bromwich West Midlands B71 3RU",
    "addr:postcode":"b71 3ru",
    "addr:street":"Pennyhill Lane West",
    "iso:country":"GB",
    "sg:address":"Pennyhill Lane",
    "sg:city":"West Bromwich",
    "sg:classifiers":[
        {
            "category":"Community Center",
            "subcategory":"Youth",
            "type":"Public Place"
        },
        {
            "category":"Organizations",
            "subcategory":"Community Association",
            "type":"Services"
        }
    ],
    "sg:phone":"+44 121 588 7247",
    "sg:postcode":"B71 3RU",
    "sg:province":"West Midlands",
    "sg:tags":[
        "associations",
        "centre",
        "housing",
        "co-operatives",
        "trust",
        "organisation",
        "societies"
    ],
    "wof:name":"WEST BROMWICH BOYS CLUB",
    "wof:placetype":"venue"
},
  "geometry": {"coordinates":[-1.981769,52.538315],"type":"Point"}
}