{
  "type": "Feature",
  "properties": {
    "addr:full":"Swabey Road Slough Berkshire SL3 8NZ",
    "addr:postcode":"sl3 8nz",
    "addr:street":"Swabey Road",
    "iso:country":"GB",
    "sg:address":"Swabey Road",
    "sg:city":"Slough",
    "sg:classifiers":[
        {
            "category":"Education",
            "subcategory":"School",
            "type":"Public Place"
        }
    ],
    "sg:phone":"+44 1753 543569",
    "sg:postcode":"SL3 8NZ",
    "sg:province":"Berkshire",
    "sg:tags":[
        "local",
        "authority"
    ],
    "wof:name":"Marish Infants School & Nursery Unit (The)",
    "wof:placetype":"venue"
},
  "geometry": {"coordinates":[-0.5447689891,51.501914978],"type":"Point"}
}