{
  "type": "Feature",
  "properties": {
    "addr:full":"60 Heralds Grn, Kingswood Warrington Cheshire WA5 7WT",
    "addr:housenumber":"60",
    "addr:postcode":"wa5 7wt",
    "addr:street":"Heralds Grn",
    "iso:country":"GB",
    "sg:address":"60 Heralds Grn, Kingswood",
    "sg:city":"Warrington",
    "sg:classifiers":[
        {
            "category":"Building & Trades",
            "subcategory":"Plumbing",
            "type":"Services"
        }
    ],
    "sg:postcode":"WA5 7WT",
    "sg:province":"Cheshire",
    "sg:tags":[
        "central",
        "heating"
    ],
    "wof:name":"Appliance Care",
    "wof:placetype":"venue"
},
  "geometry": {"coordinates":[-2.6431879997,53.4107093811],"type":"Point"}
}