{
  "type": "Feature",
  "properties": {
    "iso:country":"GB",
    "sg:address":"56 Lingfield Road",
    "sg:city":"Edenbridge",
    "sg:classifiers":[
        {
            "category":"Building & Trades",
            "subcategory":"Plumbing",
            "type":"Services"
        }
    ],
    "sg:postcode":"TN8 5DZ",
    "sg:province":"East Sussex",
    "sg:tags":[
        "heating"
    ],
    "wof:name":"Bruce  le-Cocq",
    "wof:placetype":"venue"
},
  "geometry": {"coordinates":[0.0588530004,51.1949691772],"type":"Point"}
}