{
  "type": "Feature",
  "properties": {
    "iso:country":"GB",
    "sg:address":"119 Belle Vale Road",
    "sg:city":"Liverpool",
    "sg:classifiers":[
        {
            "category":"Shopping",
            "subcategory":"Pharmacy",
            "type":"Retail Goods"
        }
    ],
    "sg:phone":"+44 151 487 7618",
    "sg:postcode":"L25 2PE",
    "sg:province":"Merseyside",
    "sg:tags":[
        "pharmacist",
        "chemist"
    ],
    "wof:name":"Late Night Chemist",
    "wof:placetype":"venue"
},
  "geometry": {"coordinates":[-2.855234,53.389259],"type":"Point"}
}