{
  "type": "Feature",
  "properties": {
    "addr:full":"Braehead Industrial Estate, Old Govan Road Renfrew Renfrewshire PA4 8XJ",
    "addr:housenumber":"braehead",
    "addr:postcode":"pa4 8xj",
    "addr:street":"Industrial Estate Old Govan Road",
    "iso:country":"GB",
    "sg:address":"Braehead Industrial Estate, Old Govan Road",
    "sg:city":"Renfrew",
    "sg:classifiers":[
        {
            "category":"Building & Trades",
            "subcategory":"Equipment Rental",
            "type":"Services"
        }
    ],
    "sg:postcode":"PA4 8XJ",
    "sg:province":"Renfrewshire",
    "sg:tags":[
        "plant",
        "machinery"
    ],
    "wof:name":"Cross Roads",
    "wof:placetype":"venue"
},
  "geometry": {"coordinates":[-4.3720898628,55.8736991882],"type":"Point"}
}