{
  "type": "Feature",
  "properties": {
    "iso:country":"GB",
    "sg:address":"9 Blaen-y-myarth",
    "sg:city":"Crickhowell",
    "sg:classifiers":[
        {
            "category":"Professional",
            "subcategory":"Management & Consulting",
            "type":"Services"
        }
    ],
    "sg:phone":"+44 1874 730800",
    "sg:postcode":"NP8 1NQ",
    "sg:province":"Monmouthshire",
    "sg:tags":[
        "consultant",
        "business"
    ],
    "wof:name":"Logan Associates",
    "wof:placetype":"venue"
},
  "geometry": {"coordinates":[-3.1674170494,51.8718223572],"type":"Point"}
}