{
  "type": "Feature",
  "properties": {
    "iso:country":"GB",
    "sg:address":"Pant Glas Industrial Estate, Bedwas",
    "sg:city":"Caerphilly",
    "sg:classifiers":[
        {
            "category":"Communications",
            "subcategory":"Film & Video Production",
            "type":"Services"
        },
        {
            "category":"Home & Garden",
            "subcategory":"Home Furnishings",
            "type":"Retail Goods"
        }
    ],
    "sg:postcode":"CF83 8DR",
    "sg:province":"Caerphilly",
    "sg:tags":[
        "wall",
        "wallpaper",
        "covering"
    ],
    "wof:name":"Gallery Home Fashion Ltd.",
    "wof:placetype":"venue"
},
  "geometry": {"coordinates":[-3.189834,51.590469],"type":"Point"}
}