{
  "type": "Feature",
  "properties": {
    "addr:full":"Business & Technology Centre, Bessemer Drive Stevenage Hertfordshire SG1 2DX",
    "addr:postcode":"sg1 2dx",
    "addr:street":"Bessemer Drive",
    "iso:country":"GB",
    "sg:address":"Business & Technology Centre, Bessemer Drive",
    "sg:city":"Stevenage",
    "sg:classifiers":[
        {
            "category":"Manufacturing",
            "subcategory":"Lumber",
            "type":"Manufacturing & Wholesale Goods"
        }
    ],
    "sg:phone":"+44 1438 727278",
    "sg:postcode":"SG1 2DX",
    "sg:province":"Hertfordshire",
    "sg:tags":[
        "importer",
        "merchants",
        "agent",
        "timber"
    ],
    "wof:name":"Practical Timber Components",
    "wof:placetype":"venue"
},
  "geometry": {"coordinates":[-0.2176299989,51.8997001648],"type":"Point"}
}