{
  "type": "Feature",
  "properties": {
    "addr:full":"Bryn Dedwydd Llanymynech Shropshire SY22 6QE",
    "addr:postcode":"sy22 6qe",
    "iso:country":"GB",
    "sg:address":"Bryn Dedwydd",
    "sg:city":"Llanymynech",
    "sg:classifiers":[
        {
            "category":"Freight",
            "type":"Transportation"
        }
    ],
    "sg:phone":"+44 1938 590325",
    "sg:postcode":"SY22 6QE",
    "sg:province":"Shropshire",
    "sg:tags":[
        "haulage",
        "road"
    ],
    "wof:name":"Evans J S",
    "wof:placetype":"venue"
},
  "geometry": {"coordinates":[-3.089354,52.780853],"type":"Point"}
}