{
  "type": "Feature",
  "properties": {
    "iso:country":"GB",
    "sg:address":"80-82 Bronham Road",
    "sg:city":"Bedford",
    "sg:classifiers":[
        {
            "category":"Home & Garden",
            "subcategory":"Furniture",
            "type":"Retail Goods"
        }
    ],
    "sg:postcode":"MK40 2QH",
    "sg:province":"Bedfordshire",
    "wof:name":"J S Raymond Draper",
    "wof:placetype":"venue"
},
  "geometry": {"coordinates":[-0.4754309952,52.1392936707],"type":"Point"}
}