{
  "type": "Feature",
  "properties": {
    "addr:full":"61a Top Moor Side Leeds West Yorkshire LS11 9LH",
    "addr:housenumber":"61a",
    "addr:postcode":"ls11 9lh",
    "addr:street":"Top Moor Side Leeds West",
    "iso:country":"GB",
    "sg:address":"61a Top Moor Side",
    "sg:city":"Leeds",
    "sg:classifiers":[
        {
            "category":"Professional",
            "subcategory":"Business Services",
            "type":"Services"
        }
    ],
    "sg:phone":"+44 113 243 2464",
    "sg:postcode":"LS11 9LH",
    "sg:province":"West Yorkshire",
    "sg:tags":[
        "bookmaker"
    ],
    "wof:name":"Tote Bookmakers",
    "wof:placetype":"venue"
},
  "geometry": {"coordinates":[-1.5595020056,53.7845878601],"type":"Point"}
}