{
  "type": "Feature",
  "properties": {
    "addr:full":"124 High Street Cowes Isle of Wight PO31 7AY",
    "addr:housenumber":"124",
    "addr:postcode":"po31 7ay",
    "addr:street":"High Street",
    "iso:country":"GB",
    "sg:address":"124 High Street",
    "sg:city":"Cowes",
    "sg:classifiers":[
        {
            "category":"Cafe",
            "type":"Food & Drink"
        }
    ],
    "sg:postcode":"PO31 7AY",
    "sg:province":"Isle of Wight",
    "sg:tags":[
        "tea",
        "room"
    ],
    "wof:name":"The  Fastnet",
    "wof:placetype":"venue"
},
  "geometry": {"coordinates":[-1.297489,50.761478],"type":"Point"}
}