{
  "type": "Feature",
  "properties": {
    "iso:country":"GB",
    "sg:address":"221-223 Lord Street",
    "sg:city":"Southport",
    "sg:classifiers":[
        {
            "category":"Home & Garden",
            "subcategory":"Furniture",
            "type":"Retail Goods"
        }
    ],
    "sg:phone":"+44 1704 549630",
    "sg:postcode":"PR8 1PE",
    "sg:province":"Lancashire",
    "wof:name":"Knightingales",
    "wof:placetype":"venue"
},
  "geometry": {"coordinates":[-3.007723,53.647152],"type":"Point"}
}