{
  "type": "Feature",
  "properties": {
    "iso:country":"GB",
    "sg:address":"121 Electric Avenue, Witton",
    "sg:city":"Birmingham",
    "sg:classifiers":[
        {
            "category":"Retail",
            "subcategory":"Auto Repair",
            "type":"Services"
        }
    ],
    "sg:phone":"+44 121 686 1100",
    "sg:postcode":"B6 7DF",
    "sg:province":"West Midlands",
    "sg:tags":[
        "modification",
        "garage"
    ],
    "wof:name":"North Birmingham Fleet Services",
    "wof:placetype":"venue"
},
  "geometry": {"coordinates":[-1.875366,52.508808],"type":"Point"}
}