{
  "type": "Feature",
  "properties": {
    "addr:full":"4 The Mall Livingston West Lothian EH54 5ED",
    "addr:housenumber":"4",
    "addr:postcode":"eh54 5ed",
    "addr:street":"The Mall",
    "iso:country":"GB",
    "sg:address":"4 The Mall",
    "sg:city":"Livingston",
    "sg:classifiers":[
        {
            "category":"Food & Beverages",
            "subcategory":"Bakery",
            "type":"Retail Goods"
        }
    ],
    "sg:phone":"+44 1506 432549",
    "sg:postcode":"EH54 5ED",
    "sg:province":"West Lothian",
    "sg:tags":[
        "baker"
    ],
    "wof:name":"Anderson Bakers",
    "wof:placetype":"venue"
},
  "geometry": {"coordinates":[-3.509834,55.886246],"type":"Point"}
}