{
  "type": "Feature",
  "properties": {
    "iso:country":"GB",
    "sg:address":"101 Churchward Avenue",
    "sg:city":"Swindon",
    "sg:classifiers":[
        {
            "category":"Arena",
            "subcategory":"Sports Club",
            "type":"Entertainment"
        }
    ],
    "sg:phone":"+44 1793 537464",
    "sg:postcode":"SN2 1NW",
    "sg:province":"Wiltshire",
    "wof:name":"The E T T A South West Region Coaching",
    "wof:placetype":"venue"
},
  "geometry": {"coordinates":[-1.790552,51.576145],"type":"Point"}
}