{
  "type": "Feature",
  "properties": {
    "iso:country":"GB",
    "sg:address":"1 Brookside, Dalham",
    "sg:city":"Newmarket",
    "sg:classifiers":[
        {
            "category":"Bars & Pubs",
            "type":"Food & Drink"
        },
        {
            "category":"Community Center",
            "subcategory":"Social",
            "type":"Public Place"
        }
    ],
    "sg:phone":"+44 1638 500306",
    "sg:postcode":"CB8 8TG",
    "sg:province":"Cambridgeshire",
    "sg:tags":[
        "pubs",
        "house",
        "inn",
        "activity"
    ],
    "wof:name":"Affleck Arms",
    "wof:placetype":"venue"
},
  "geometry": {"coordinates":[0.52029,52.226517],"type":"Point"}
}