{
  "type": "Feature",
  "properties": {
    "iso:country":"GB",
    "sg:address":"Clifton Hill, Forton",
    "sg:city":"Preston",
    "sg:classifiers":[
        {
            "category":"Professional",
            "subcategory":"Accounting & Tax Preparation",
            "type":"Services"
        }
    ],
    "sg:phone":"+44 1524 791197",
    "sg:postcode":"PR3 0AR",
    "sg:province":"Lancashire",
    "sg:tags":[
        "accountant"
    ],
    "wof:name":"Stephen Gornall Partnership",
    "wof:placetype":"venue"
},
  "geometry": {"coordinates":[-2.781494,53.956387],"type":"Point"}
}