{
  "type": "Feature",
  "properties": {
    "iso:country":"GB",
    "sg:address":"10 Leyburn Cres",
    "sg:city":"Romford",
    "sg:classifiers":[
        {
            "category":"Retail",
            "subcategory":"Repair Shop",
            "type":"Services"
        }
    ],
    "sg:postcode":"RM3 8RP",
    "sg:province":"Essex",
    "sg:tags":[
        "radio",
        "television",
        "video"
    ],
    "wof:name":"Storey,Simon,",
    "wof:placetype":"venue"
},
  "geometry": {"coordinates":[0.223693,51.600174],"type":"Point"}
}