{
  "type": "Feature",
  "properties": {
    "addr:full":"1 Parkway Shop Units, Corve St Ludlow Herefordshire SY8 1DA",
    "addr:housenumber":"1;units",
    "addr:postcode":"sy8 1da",
    "addr:street":"Parkway;St",
    "iso:country":"GB",
    "sg:address":"1 Parkway Shop Units, Corve St",
    "sg:city":"Ludlow",
    "sg:classifiers":[
        {
            "category":"Travel",
            "subcategory":"Travel Agent",
            "type":"Entertainment"
        }
    ],
    "sg:phone":"+44 1584 876555",
    "sg:postcode":"SY8 1DA",
    "sg:province":"Herefordshire",
    "wof:name":"Travel Trail",
    "wof:placetype":"venue"
},
  "geometry": {"coordinates":[-2.7190139294,52.3705940247],"type":"Point"}
}