{
  "type": "Feature",
  "properties": {
    "iso:country":"GB",
    "sg:address":"65 Pembury Avenue",
    "sg:city":"Worcester Park",
    "sg:classifiers":[
        {
            "category":"Building & Trades",
            "subcategory":"Cleaning & Sanitation",
            "type":"Services"
        }
    ],
    "sg:phone":"+44 20 8337 9265",
    "sg:postcode":"KT4 8BU",
    "sg:province":"Surrey",
    "sg:tags":[
        "cleaner",
        "window"
    ],
    "wof:name":"Four Seasons Window Cleaning Contractors",
    "wof:placetype":"venue"
},
  "geometry": {"coordinates":[-0.2433770001,51.3843688965],"type":"Point"}
}