{
  "type": "Feature",
  "properties": {
    "iso:country":"GB",
    "sg:address":"162 Tarvin Road",
    "sg:city":"Chester",
    "sg:classifiers":[
        {
            "category":"Building & Trades",
            "subcategory":"Construction",
            "type":"Services"
        }
    ],
    "sg:postcode":"CH3 5EE",
    "sg:province":"Cheshire",
    "sg:tags":[
        "decorator",
        "painter"
    ],
    "wof:name":"F C Swift",
    "wof:placetype":"venue"
},
  "geometry": {"coordinates":[-2.861693,53.192451],"type":"Point"}
}