{
  "type": "Feature",
  "properties": {
    "addr:full":"The Lodge, Fosse Road, Flintham Newark Lincolnshire NG23 5LJ",
    "addr:postcode":"ng23 5lj",
    "addr:street":"Fosse Road",
    "iso:country":"GB",
    "sg:address":"The Lodge, Fosse Road, Flintham",
    "sg:city":"Newark",
    "sg:classifiers":[
        {
            "category":"Bus Charters",
            "type":"Transportation"
        }
    ],
    "sg:phone":"+44 1636 525725",
    "sg:postcode":"NG23 5LJ",
    "sg:province":"Lincolnshire",
    "sg:tags":[
        "hire",
        "coach"
    ],
    "wof:name":"Patron Travel",
    "wof:placetype":"venue"
},
  "geometry": {"coordinates":[-0.898251,53.006401],"type":"Point"}
}