{
  "type": "Feature",
  "properties": {
    "iso:country":"GB",
    "sg:address":"48 Cartway",
    "sg:city":"Bridgnorth",
    "sg:classifiers":[
        {
            "category":"Restaurant",
            "type":"Food & Drink"
        }
    ],
    "sg:phone":"+44 1746 763977",
    "sg:postcode":"WV16 4BG",
    "sg:province":"Shropshire",
    "wof:name":"Cartway House The",
    "wof:placetype":"venue"
},
  "geometry": {"coordinates":[-2.41691,52.534554],"type":"Point"}
}