{
  "type": "Feature",
  "properties": {
    "addr:full":"391 Brighton Road Lancing West Sussex BN15 8JX",
    "addr:housenumber":"391",
    "addr:postcode":"bn15 8jx",
    "addr:street":"Brighton Road",
    "iso:country":"GB",
    "sg:address":"391 Brighton Road",
    "sg:city":"Lancing",
    "sg:classifiers":[
        {
            "category":"Food & Beverages",
            "subcategory":"Groceries & Convenience Stores",
            "type":"Retail Goods"
        }
    ],
    "sg:phone":"+44 1903 851285",
    "sg:postcode":"BN15 8JX",
    "sg:province":"West Sussex",
    "wof:name":"N & M Stores",
    "wof:placetype":"venue"
},
  "geometry": {"coordinates":[-0.297753,50.825623],"type":"Point"}
}