{
  "type": "Feature",
  "properties": {
    "iso:country":"GB",
    "sg:address":"Unit 5, Avro Business Centre",
    "sg:city":"Melksham",
    "sg:classifiers":[
        {
            "category":"Home & Garden",
            "subcategory":"Carpets & Floor Coverings",
            "type":"Retail Goods"
        }
    ],
    "sg:phone":"+44 1225 705575",
    "sg:postcode":"SN12 6TP",
    "sg:province":"Wiltshire",
    "sg:tags":[
        "rubber",
        "plastic"
    ],
    "wof:name":"Gda-Elfex Ltd.",
    "wof:placetype":"venue"
},
  "geometry": {"coordinates":[-2.1301040649,51.3586616516],"type":"Point"}
}