{
  "type": "Feature",
  "properties": {
    "iso:country":"GB",
    "sg:address":"366 Leith Walk",
    "sg:city":"Edinburgh",
    "sg:classifiers":[
        {
            "category":"Professional",
            "subcategory":"Computer Services",
            "type":"Services"
        }
    ],
    "sg:phone":"+44 131 554 9393",
    "sg:postcode":"EH6 6EY",
    "sg:province":"City of Edinburgh",
    "sg:tags":[
        "system",
        "software"
    ],
    "wof:name":"PC Trading",
    "wof:placetype":"venue"
},
  "geometry": {"coordinates":[-3.172299,55.977219],"type":"Point"}
}