{
  "type": "Feature",
  "properties": {
    "iso:country":"GB",
    "sg:address":", Porteynon",
    "sg:city":"Swansea",
    "sg:classifiers":[
        {
            "category":"Recreation",
            "subcategory":"Campground",
            "type":"Entertainment"
        }
    ],
    "sg:phone":"+44 1792 390795",
    "sg:postcode":"SA3 1NN",
    "sg:province":"Swansea",
    "sg:tags":[
        "site",
        "camping"
    ],
    "wof:name":"Carreglwyd Camping & Caravan Park",
    "wof:placetype":"venue"
},
  "geometry": {"coordinates":[-4.2131490707,51.5464401245],"type":"Point"}
}