{
  "type": "Feature",
  "properties": {
    "addr:full":"Fourstacks Cottage, Main Street, Tugby Leicester Leicestershire LE7 9WD",
    "addr:postcode":"le7 9wd",
    "addr:street":"Main Street",
    "iso:country":"GB",
    "sg:address":"Fourstacks Cottage, Main Street, Tugby",
    "sg:city":"Leicester",
    "sg:classifiers":[
        {
            "category":"Building & Trades",
            "subcategory":"Construction",
            "type":"Services"
        }
    ],
    "sg:phone":"+44 116 259 8445",
    "sg:postcode":"LE7 9WD",
    "sg:province":"Leicestershire",
    "sg:tags":[
        "decorator",
        "painter"
    ],
    "wof:name":"Martin Horton Decorating",
    "wof:placetype":"venue"
},
  "geometry": {"coordinates":[-0.874699,52.601894],"type":"Point"}
}