{
  "type": "Feature",
  "properties": {
    "iso:country":"GB",
    "sg:address":"32 Bridge Street",
    "sg:city":"Par",
    "sg:classifiers":[
        {
            "category":"Education",
            "subcategory":"Library",
            "type":"Public Place"
        }
    ],
    "sg:phone":"+44 1726 817540",
    "sg:postcode":"PL24 2NS",
    "sg:province":"Cornwall",
    "sg:tags":[
        "reproduction",
        "furniture"
    ],
    "wof:name":"The Enchanted House",
    "wof:placetype":"venue"
},
  "geometry": {"coordinates":[-4.7191591263,50.3500862122],"type":"Point"}
}