{
  "type": "Feature",
  "properties": {
    "addr:full":"10-12 West Street Swadlincote Derbyshire DE11 9DE",
    "addr:housenumber":"10-12",
    "addr:postcode":"de11 9de",
    "addr:street":"West Street",
    "iso:country":"GB",
    "sg:address":"10-12 West Street",
    "sg:city":"Swadlincote",
    "sg:classifiers":[
        {
            "category":"Shopping",
            "subcategory":"Discount & Variety Stores",
            "type":"Retail Goods"
        }
    ],
    "sg:postcode":"DE11 9DE",
    "sg:province":"Derbyshire",
    "sg:tags":[
        "centre"
    ],
    "wof:name":"Mr Pound",
    "wof:placetype":"venue"
},
  "geometry": {"coordinates":[-1.558542,52.771103],"type":"Point"}
}