{
  "type": "Feature",
  "properties": {
    "addr:full":"35 The Round Meade, Maghull Liverpool Lancashire L31 8DY",
    "addr:housenumber":"35",
    "addr:postcode":"l31 8dy",
    "addr:street":"The Round Meade",
    "iso:country":"GB",
    "sg:address":"35 The Round Meade, Maghull",
    "sg:city":"Liverpool",
    "sg:classifiers":[
        {
            "category":"Building & Trades",
            "subcategory":"Plumbing",
            "type":"Services"
        }
    ],
    "sg:phone":"+44 151 526 2373",
    "sg:postcode":"L31 8DY",
    "sg:province":"Lancashire",
    "sg:tags":[
        "heating"
    ],
    "wof:name":"Clearspace Ltd.",
    "wof:placetype":"venue"
},
  "geometry": {"coordinates":[-2.9503099918,53.5133972168],"type":"Point"}
}