{
  "type": "Feature",
  "properties": {
    "iso:country":"GB",
    "sg:address":"Dunollie Road",
    "sg:city":"Oban",
    "sg:classifiers":[
        {
            "category":"Travel",
            "subcategory":"Hotels & Motels",
            "type":"Entertainment"
        }
    ],
    "sg:phone":"+44 1631 562536",
    "sg:postcode":"PA34 5JH",
    "sg:province":"Argyll and Bute",
    "wof:name":"The Kings Knoll Hotel",
    "wof:placetype":"venue"
},
  "geometry": {"coordinates":[-5.4686141014,56.4226531982],"type":"Point"}
}