{
  "type": "Feature",
  "properties": {
    "addr:full":"Rushton Mills, Rushton Spencer Macclesfield Cheshire SK11 0RT",
    "addr:postcode":"sk11 0rt",
    "addr:street":"Rushton",
    "iso:country":"GB",
    "sg:address":"Rushton Mills, Rushton Spencer",
    "sg:city":"Macclesfield",
    "sg:classifiers":[
        {
            "category":"Professional",
            "subcategory":"Business Services",
            "type":"Services"
        },
        {
            "category":"Shopping",
            "type":"Retail Goods"
        }
    ],
    "sg:phone":"+44 1260 226233",
    "sg:postcode":"SK11 0RT",
    "sg:province":"Cheshire",
    "sg:tags":[
        "merchant",
        "agricultural"
    ],
    "wof:name":"John Cook Corn Merchants Ltd",
    "wof:placetype":"venue"
},
  "geometry": {"coordinates":[-2.092087,53.158421],"type":"Point"}
}