{
  "type": "Feature",
  "properties": {
    "iso:country":"GB",
    "sg:address":"Ketley",
    "sg:city":"Telford",
    "sg:classifiers":[
        {
            "category":"Communications",
            "subcategory":"Newspaper",
            "type":"Services"
        }
    ],
    "sg:phone":"+44 1952 242424",
    "sg:postcode":"TF1 5HU",
    "sg:province":"Shropshire",
    "sg:tags":[
        "magazine"
    ],
    "wof:name":"Shropshire Star Ltd.",
    "wof:placetype":"venue"
},
  "geometry": {"coordinates":[-2.48234,52.694771],"type":"Point"}
}