{
  "type": "Feature",
  "properties": {
    "addr:full":"551 Etruria Road, Basford Stoke-on-trent Staffordshire ST4 6HH",
    "addr:housenumber":"551",
    "addr:postcode":"staffordshire st4 6hh",
    "addr:street":"Etruria Road",
    "iso:country":"GB",
    "sg:address":"551 Etruria Road, Basford",
    "sg:city":"Stoke-on-trent",
    "sg:classifiers":[
        {
            "category":"Shopping",
            "subcategory":"Stationery & Office Supplies",
            "type":"Retail Goods"
        }
    ],
    "sg:phone":"+44 1782 711121",
    "sg:postcode":"ST4 6HH",
    "sg:province":"Staffordshire",
    "sg:tags":[
        "equipment"
    ],
    "wof:name":"Smiths Office Furniture Ltd.",
    "wof:placetype":"venue"
},
  "geometry": {"coordinates":[-2.212205,53.016121],"type":"Point"}
}