{
  "type": "Feature",
  "properties": {
    "addr:full":"10 Market Place, Brewood Stafford Shropshire ST19 9BS",
    "addr:housenumber":"10",
    "addr:postcode":"st19 9bs",
    "addr:street":"Market Place",
    "iso:country":"GB",
    "sg:address":"10 Market Place, Brewood",
    "sg:city":"Stafford",
    "sg:classifiers":[
        {
            "category":"Travel",
            "subcategory":"Travel Agent",
            "type":"Entertainment"
        }
    ],
    "sg:phone":"+44 1902 851138",
    "sg:postcode":"ST19 9BS",
    "sg:province":"Shropshire",
    "wof:name":"North American Highways Ltd.",
    "wof:placetype":"venue"
},
  "geometry": {"coordinates":[-2.174079895,52.6767272949],"type":"Point"}
}