{
  "type": "Feature",
  "properties": {
    "addr:full":"1b Sydenham Road Guildford Surrey GU1 3RT",
    "addr:housenumber":"1b",
    "addr:postcode":"gu1 3rt",
    "addr:street":"Sydenham Road",
    "iso:country":"GB",
    "sg:address":"1b Sydenham Road",
    "sg:city":"Guildford",
    "sg:classifiers":[
        {
            "category":"Retail",
            "subcategory":"Laundry & Dry Cleaning",
            "type":"Services"
        }
    ],
    "sg:phone":"+44 1483 563945",
    "sg:postcode":"GU1 3RT",
    "sg:province":"Surrey",
    "sg:tags":[
        "launderette"
    ],
    "wof:name":"Laundromat",
    "wof:placetype":"venue"
},
  "geometry": {"coordinates":[-0.571484,51.234764],"type":"Point"}
}