{
  "type": "Feature",
  "properties": {
    "iso:country":"GB",
    "sg:address":"1 Victoria Place, Pounds Hill",
    "sg:city":"Crediton",
    "sg:classifiers":[
        {
            "category":"Building & Trades",
            "subcategory":"Plumbing",
            "type":"Services"
        }
    ],
    "sg:phone":"+44 1363 772961",
    "sg:postcode":"EX17 1DS",
    "sg:province":"Devon",
    "sg:tags":[
        "heating"
    ],
    "wof:name":"R D Wicker",
    "wof:placetype":"venue"
},
  "geometry": {"coordinates":[-3.654286,50.794266],"type":"Point"}
}