{
  "type": "Feature",
  "properties": {
    "iso:country":"GB",
    "sg:address":"47 Broad St",
    "sg:city":"Glasgow",
    "sg:classifiers":[
        {
            "category":"Shopping",
            "subcategory":"Clothing, Apparel, & Fashions",
            "type":"Retail Goods"
        }
    ],
    "sg:phone":"+44 141 550 4080",
    "sg:postcode":"G40 2QW",
    "sg:province":"Glasgow City",
    "sg:tags":[
        "clothing"
    ],
    "wof:name":"Graham Walker Agencies",
    "wof:placetype":"venue"
},
  "geometry": {"coordinates":[-4.225472,55.850246],"type":"Point"}
}