{
  "type": "Feature",
  "properties": {
    "iso:country":"GB",
    "sg:address":"Linburn Ho, 342 Kilburn High Rd",
    "sg:city":"Kilburn",
    "sg:classifiers":[
        {
            "category":"Government",
            "subcategory":"Post Office",
            "type":"Public Place"
        }
    ],
    "sg:phone":"+44 20 7328 7516",
    "sg:postcode":"NW6 2QJ",
    "sg:province":"Greater London",
    "sg:tags":[
        "messenger",
        "courier"
    ],
    "wof:name":"Epic Couriers & Logistics",
    "wof:placetype":"venue"
},
  "geometry": {"coordinates":[-0.2017,51.54493],"type":"Point"}
}