{
  "type": "Feature",
  "properties": {
    "addr:full":"Beehive, Dolphinton West Linton Midlothian EH46 7HH",
    "addr:postcode":"eh46 7hh",
    "addr:street":"West",
    "iso:country":"GB",
    "sg:address":"Beehive, Dolphinton",
    "sg:city":"West Linton",
    "sg:classifiers":[
        {
            "category":"Organizations",
            "subcategory":"Non-profit Organization",
            "type":"Services"
        }
    ],
    "sg:phone":"+44 1968 682369",
    "sg:postcode":"EH46 7HH",
    "sg:province":"Midlothian",
    "sg:tags":[
        "organisation",
        "voluntary",
        "charity"
    ],
    "wof:name":"Lepra",
    "wof:placetype":"venue"
},
  "geometry": {"coordinates":[-3.3560340405,55.7542991638],"type":"Point"}
}