{
  "type": "Feature",
  "properties": {
    "iso:country":"GB",
    "sg:address":"75 Bulverhythe Rd",
    "sg:city":"St Leonards On Sea",
    "sg:classifiers":[
        {
            "category":"Professional",
            "subcategory":"Printing & Photocopies",
            "type":"Services"
        }
    ],
    "sg:phone":"+44 1424 446193",
    "sg:postcode":"TN38 8AD",
    "sg:province":"East Sussex",
    "sg:tags":[
        "duplicating",
        "copying"
    ],
    "wof:name":"Henry Enterprise Secretarial Service",
    "wof:placetype":"venue"
},
  "geometry": {"coordinates":[0.52777,50.850533],"type":"Point"}
}