{
  "type": "Feature",
  "properties": {
    "addr:full":"R/o 121 High St Brierley Hill West Midlands DY5 3AU",
    "addr:housenumber":"121",
    "addr:postcode":"dy5 3au",
    "addr:street":"/ O;High St",
    "iso:country":"GB",
    "sg:address":"R/o 121 High St",
    "sg:city":"Brierley Hill",
    "sg:classifiers":[
        {
            "category":"Professional",
            "subcategory":"Printing & Photocopies",
            "type":"Services"
        }
    ],
    "sg:phone":"+44 1384 77934",
    "sg:postcode":"DY5 3AU",
    "sg:province":"West Midlands",
    "sg:tags":[
        "printer"
    ],
    "wof:name":"Ernest Evans & Co",
    "wof:placetype":"venue"
},
  "geometry": {"coordinates":[-2.1213009357,52.48204422],"type":"Point"}
}