{
  "type": "Feature",
  "properties": {
    "addr:full":"18 Manor Park Gardens Edgware Greater London HA8 7NA",
    "addr:housenumber":"18",
    "addr:postcode":"ha8 7na",
    "addr:street":"Manor Park Gardens",
    "iso:country":"GB",
    "sg:address":"18 Manor Park Gardens",
    "sg:city":"Edgware",
    "sg:classifiers":[
        {
            "category":"Building & Trades",
            "subcategory":"Landscaping Services",
            "type":"Services"
        }
    ],
    "sg:postcode":"HA8 7NA",
    "sg:province":"Greater London",
    "sg:tags":[
        "forestry",
        "surgeon",
        "tree"
    ],
    "wof:name":"EDGWARE TREE SURGEONS",
    "wof:placetype":"venue"
},
  "geometry": {"coordinates":[-0.278313,51.61401],"type":"Point"}
}