{
  "type": "Feature",
  "properties": {
    "addr:full":"7 Queen Annes Place Enfield Greater London EN1 2QB",
    "addr:housenumber":"7",
    "addr:postcode":"en1 2qb",
    "addr:street":"Queen Annes Place",
    "iso:country":"GB",
    "sg:address":"7 Queen Annes Place",
    "sg:city":"Enfield",
    "sg:classifiers":[
        {
            "category":"Real Estate",
            "subcategory":"Real Estate Agent",
            "type":"Services"
        }
    ],
    "sg:phone":"+44 20 8360 0600",
    "sg:postcode":"EN1 2QB",
    "sg:province":"Greater London",
    "wof:name":"Burston & Whay",
    "wof:placetype":"venue"
},
  "geometry": {"coordinates":[-0.069813,51.641705],"type":"Point"}
}