{
  "type": "Feature",
  "properties": {
    "addr:full":"20-22 Wedgwood Road Bicester Oxfordshire OX26 4UL",
    "addr:housenumber":"20-22",
    "addr:postcode":"ox26 4ul",
    "addr:street":"Wedgwood Road",
    "iso:country":"GB",
    "sg:address":"20-22 Wedgwood Road",
    "sg:city":"Bicester",
    "sg:classifiers":[
        {
            "category":"Manufacturing",
            "subcategory":"Metals",
            "type":"Manufacturing & Wholesale Goods"
        }
    ],
    "sg:phone":"+44 1869 252750",
    "sg:postcode":"OX26 4UL",
    "sg:province":"Oxfordshire",
    "sg:tags":[
        "steel",
        "fabricator",
        "product",
        "erectors",
        "fabricated"
    ],
    "wof:name":"Brady Fabrications Ltd.",
    "wof:placetype":"venue"
},
  "geometry": {"coordinates":[-1.136851,51.904099],"type":"Point"}
}