{
  "type": "Feature",
  "properties": {
    "addr:full":"Ayres Lane, Burghclere Newbury Berkshire RG20 9HG",
    "addr:postcode":"rg20 9hg",
    "addr:street":"Ayres Lane",
    "iso:country":"GB",
    "sg:address":"Ayres Lane, Burghclere",
    "sg:city":"Newbury",
    "sg:classifiers":[
        {
            "category":"Building & Trades",
            "subcategory":"Construction",
            "type":"Services"
        }
    ],
    "sg:phone":"+44 1635 253023",
    "sg:postcode":"RG20 9HG",
    "sg:province":"Berkshire",
    "sg:tags":[
        "builder"
    ],
    "wof:name":"A R Boyles & Son",
    "wof:placetype":"venue"
},
  "geometry": {"coordinates":[-1.325343,51.350628],"type":"Point"}
}