{
  "type": "Feature",
  "properties": {
    "addr:full":"70 High Street Poole Dorset BH15 1DA",
    "addr:housenumber":"70",
    "addr:postcode":"bh15 1da",
    "addr:street":"High Street",
    "iso:country":"GB",
    "sg:address":"70 High Street",
    "sg:city":"Poole",
    "sg:classifiers":[
        {
            "category":"Recreation",
            "subcategory":"Amusement Park",
            "type":"Entertainment"
        }
    ],
    "sg:postcode":"BH15 1DA",
    "sg:province":"Dorset",
    "sg:tags":[
        "arcade"
    ],
    "wof:name":"Real Time",
    "wof:placetype":"venue"
},
  "geometry": {"coordinates":[-1.9864670038,50.7140197754],"type":"Point"}
}