{
  "type": "Feature",
  "properties": {
    "addr:full":"293 Lower High Street Watford Hertfordshire WD17 2HY",
    "addr:housenumber":"293",
    "addr:postcode":"wd17 2hy",
    "addr:street":"Lower High Street",
    "iso:country":"GB",
    "sg:address":"293 Lower High Street",
    "sg:city":"Watford",
    "sg:classifiers":[
        {
            "category":"Retail",
            "subcategory":"Auto Repair",
            "type":"Services"
        }
    ],
    "sg:phone":"+44 1923 255200",
    "sg:postcode":"WD17 2HY",
    "sg:province":"Hertfordshire",
    "sg:tags":[
        "modification",
        "garage"
    ],
    "wof:name":"Viking Autos Ltd.",
    "wof:placetype":"venue"
},
  "geometry": {"coordinates":[-0.3863930106,51.6484260559],"type":"Point"}
}