{
  "type": "Feature",
  "properties": {
    "addr:full":"42 Red Cottage Drive Reading Berkshire RG31 7EZ",
    "addr:housenumber":"42",
    "addr:postcode":"rg31 7ez",
    "addr:street":"Red Cottage Drive",
    "iso:country":"GB",
    "sg:address":"42 Red Cottage Drive",
    "sg:city":"Reading",
    "sg:classifiers":[
        {
            "category":"Building & Trades",
            "subcategory":"Construction",
            "type":"Services"
        }
    ],
    "sg:postcode":"RG31 7EZ",
    "sg:province":"Berkshire",
    "sg:tags":[
        "dry",
        "lining",
        "plasterers",
        "screeders"
    ],
    "wof:name":"Mark Strudley",
    "wof:placetype":"venue"
},
  "geometry": {"coordinates":[-1.046619,51.440895],"type":"Point"}
}