{
  "type": "Feature",
  "properties": {
    "iso:country":"GB",
    "sg:address":"3 Caledonia Road, Stanwell",
    "sg:city":"Staines",
    "sg:classifiers":[
        {
            "category":"Shopping",
            "subcategory":"Party Supplies",
            "type":"Retail Goods"
        }
    ],
    "sg:phone":"+44 1784 210547",
    "sg:postcode":"TW19 7TD",
    "sg:province":"Berkshire",
    "sg:tags":[
        "inflatables",
        "bouncy",
        "castle"
    ],
    "wof:name":"Caledonia Castles",
    "wof:placetype":"venue"
},
  "geometry": {"coordinates":[-0.471702,51.449924],"type":"Point"}
}