{
  "type": "Feature",
  "properties": {
    "addr:full":"2 Old Bond Street West End Hampshire W1X 3TD",
    "addr:housenumber":"2",
    "addr:postcode":"w1x 3td",
    "addr:street":"Old Bond Street",
    "iso:country":"GB",
    "sg:address":"2 Old Bond Street",
    "sg:city":"West End",
    "sg:classifiers":[
        {
            "category":"Banks & Credit Unions",
            "subcategory":"Bank",
            "type":"Services"
        }
    ],
    "sg:postcode":"W1X 3TD",
    "sg:province":"Hampshire",
    "wof:name":"Sturt Ltd",
    "wof:placetype":"venue"
},
  "geometry": {"coordinates":[-0.139963001,51.5082855225],"type":"Point"}
}