{
  "type": "Feature",
  "properties": {
    "addr:full":"342 Main Road, Westerham Hill Westerham Kent TN16 2HL",
    "addr:housenumber":"342",
    "addr:postcode":"tn16 2hl",
    "addr:street":"Main Road",
    "iso:country":"GB",
    "sg:address":"342 Main Road, Westerham Hill",
    "sg:city":"Westerham",
    "sg:classifiers":[
        {
            "category":"Manufacturing",
            "subcategory":"Wood Products",
            "type":"Manufacturing & Wholesale Goods"
        },
        {
            "category":"Retail",
            "subcategory":"Storage",
            "type":"Services"
        }
    ],
    "sg:postcode":"TN16 2HL",
    "sg:province":"Kent",
    "sg:tags":[
        "cold"
    ],
    "wof:name":"Supercold Ltd.",
    "wof:placetype":"venue"
},
  "geometry": {"coordinates":[0.0511340015,51.3030586243],"type":"Point"}
}