{
  "type": "Feature",
  "properties": {
    "iso:country":"GB",
    "sg:address":"279/289 London Road",
    "sg:city":"Romford",
    "sg:classifiers":[
        {
            "category":"Autos & Motor Vehicles",
            "subcategory":"Automobile Sales",
            "type":"Retail Goods"
        }
    ],
    "sg:phone":"+44 1708 737999",
    "sg:postcode":"RM7 9NP",
    "sg:province":"Essex",
    "sg:tags":[
        "car"
    ],
    "wof:name":"Glyn Hopkin Ltd.",
    "wof:placetype":"venue"
},
  "geometry": {"coordinates":[0.16082,51.574551],"type":"Point"}
}