{
  "type": "Feature",
  "properties": {
    "addr:full":"112 Thurrock Lakeside Shop Ctre, West Thurrock Grays Essex RM16 1ZG",
    "addr:housenumber":"112",
    "addr:postcode":"rm16 1zg",
    "addr:street":"Thurrock;West",
    "iso:country":"GB",
    "sg:address":"112 Thurrock Lakeside Shop Ctre, West Thurrock",
    "sg:city":"Grays",
    "sg:classifiers":[
        {
            "category":"Shopping",
            "subcategory":"Clothing, Apparel, & Fashions",
            "type":"Retail Goods"
        }
    ],
    "sg:phone":"+44 1708 890876",
    "sg:postcode":"RM16 1ZG",
    "sg:province":"Essex",
    "sg:tags":[
        "ladieswear"
    ],
    "wof:name":"Bay Trading Co",
    "wof:placetype":"venue"
},
  "geometry": {"coordinates":[0.28655,51.48045],"type":"Point"}
}