{
  "type": "Feature",
  "properties": {
    "addr:full":"Crackenedge Lane Dewsbury West Yorkshire WF13 1RB",
    "addr:postcode":"wf13 1rb",
    "addr:street":"Crackenedge Lane",
    "iso:country":"GB",
    "sg:address":"Crackenedge Lane",
    "sg:city":"Dewsbury",
    "sg:classifiers":[
        {
            "category":"Place Of Worship",
            "type":"Public Place"
        }
    ],
    "sg:phone":"+44 1924 465952",
    "sg:postcode":"WF13 1RB",
    "sg:province":"West Yorkshire",
    "wof:name":"Dewsbury Evangelical Church",
    "wof:placetype":"venue"
},
  "geometry": {"coordinates":[-1.627622962,53.6922454834],"type":"Point"}
}