{
  "type": "Feature",
  "properties": {
    "addr:full":"37-38 East Pk Pde Northampton Northamptonshire NN1 4LB",
    "addr:housenumber":"37-38",
    "addr:postcode":"nn1 4lb",
    "addr:street":"East Pk Pde",
    "iso:country":"GB",
    "sg:address":"37-38 East Pk Pde",
    "sg:city":"Northampton",
    "sg:classifiers":[
        {
            "category":"Travel",
            "subcategory":"Hostel",
            "type":"Entertainment"
        }
    ],
    "sg:postcode":"NN1 4LB",
    "sg:province":"Northamptonshire",
    "wof:name":"East Park Hostel",
    "wof:placetype":"venue"
},
  "geometry": {"coordinates":[-0.88107,52.248692],"type":"Point"}
}