{
  "type": "Feature",
  "properties": {
    "iso:country":"GB",
    "sg:address":"40 Abington St",
    "sg:city":"Northampton",
    "sg:classifiers":[
        {
            "category":"Shopping",
            "subcategory":"Clothing, Apparel, & Fashions",
            "type":"Retail Goods"
        }
    ],
    "sg:postcode":"NN1 2AP",
    "sg:province":"Northamptonshire",
    "sg:tags":[
        "shop"
    ],
    "wof:name":"River Island Clothing Co Ltd",
    "wof:placetype":"venue"
},
  "geometry": {"coordinates":[-0.892296,52.238537],"type":"Point"}
}