{
  "type": "Feature",
  "properties": {
    "iso:country":"GB",
    "sg:address":"Iscoed Road, Hendy, Pontarddulais",
    "sg:city":"Swansea",
    "sg:classifiers":[
        {
            "category":"Education",
            "subcategory":"School",
            "type":"Public Place"
        }
    ],
    "sg:phone":"+44 1792 882940",
    "sg:postcode":"SA4 1UW",
    "sg:province":"Carmarthenshire",
    "sg:tags":[
        "local",
        "authority"
    ],
    "wof:name":"Hendy Mixed & Infants School",
    "wof:placetype":"venue"
},
  "geometry": {"coordinates":[-4.0357499123,51.7119407654],"type":"Point"}
}