{
  "type": "Feature",
  "properties": {
    "addr:full":"24-25 York Villas Brighton East Sussex BN1 3TS",
    "addr:housenumber":"24-25",
    "addr:postcode":"bn1 3ts",
    "addr:street":"York Villas",
    "iso:country":"GB",
    "sg:address":"24-25 York Villas",
    "sg:city":"Brighton",
    "sg:classifiers":[
        {
            "category":"Shopping",
            "subcategory":"Stationery & Office Supplies",
            "type":"Retail Goods"
        }
    ],
    "sg:phone":"+44 1273 321103",
    "sg:postcode":"BN1 3TS",
    "sg:province":"East Sussex",
    "sg:tags":[
        "printers'"
    ],
    "wof:name":"West Sussex Litho",
    "wof:placetype":"venue"
},
  "geometry": {"coordinates":[-0.145664,50.832638],"type":"Point"}
}