{
  "type": "Feature",
  "properties": {
    "addr:full":"Babworth Rd Retford Nottinghamshire DN22 7BP",
    "addr:postcode":"dn22 7bp",
    "addr:street":"Babworth Rd",
    "iso:country":"GB",
    "sg:address":"Babworth Rd",
    "sg:city":"Retford",
    "sg:classifiers":[
        {
            "category":"Place Of Worship",
            "type":"Public Place"
        }
    ],
    "sg:phone":"+44 1777 703373",
    "sg:postcode":"DN22 7BP",
    "sg:province":"Nottinghamshire",
    "wof:name":"St Josephsroman Catholic Church",
    "wof:placetype":"venue"
},
  "geometry": {"coordinates":[-0.9524739981,53.3216552734],"type":"Point"}
}