{
  "type": "Feature",
  "properties": {
    "addr:full":"9-13 Bromley Rd London Greater London SE6 2TS",
    "addr:housenumber":"9-13",
    "addr:postcode":"se6 2ts",
    "addr:street":"Bromley Rd",
    "iso:country":"GB",
    "sg:address":"9-13 Bromley Rd",
    "sg:city":"London",
    "sg:classifiers":[
        {
            "category":"Sports & Exercise",
            "subcategory":"Gym",
            "type":"Entertainment"
        }
    ],
    "sg:postcode":"SE6 2TS",
    "sg:province":"Greater London",
    "sg:tags":[
        "fitness",
        "health",
        "centre"
    ],
    "wof:name":"Phoenix Leisure Centre",
    "wof:placetype":"venue"
},
  "geometry": {"coordinates":[-0.020214,51.442989],"type":"Point"}
}