{
  "type": "Feature",
  "properties": {
    "addr:full":"17 Aylwin Close Newquay Cornwall TR7 3EF",
    "addr:housenumber":"17",
    "addr:postcode":"tr7 3ef",
    "addr:street":"Aylwin Close",
    "iso:country":"GB",
    "sg:address":"17 Aylwin Close",
    "sg:city":"Newquay",
    "sg:classifiers":[
        {
            "category":"Building & Trades",
            "subcategory":"Construction",
            "type":"Services"
        }
    ],
    "sg:postcode":"TR7 3EF",
    "sg:province":"Cornwall",
    "sg:tags":[
        "builder"
    ],
    "wof:name":"Sphereunit Ltd.",
    "wof:placetype":"venue"
},
  "geometry": {"coordinates":[-5.0718588829,50.4120864868],"type":"Point"}
}