{
  "type": "Feature",
  "properties": {
    "iso:country":"GB",
    "sg:address":"Leypark Walk",
    "sg:city":"Plymouth",
    "sg:classifiers":[
        {
            "category":"Community Center",
            "type":"Public Place"
        }
    ],
    "sg:phone":"+44 1752 786696",
    "sg:postcode":"PL6 8UE",
    "sg:province":"Devon",
    "sg:tags":[
        "centre"
    ],
    "wof:name":"Elm Centre The",
    "wof:placetype":"venue"
},
  "geometry": {"coordinates":[-4.095085,50.409828],"type":"Point"}
}