{
  "type": "Feature",
  "properties": {
    "addr:full":"58 Werneth Road, Woodley Stockport Cheshire SK6 1HR",
    "addr:housenumber":"58",
    "addr:postcode":"sk6 1hr",
    "addr:street":"Werneth Road",
    "iso:country":"GB",
    "sg:address":"58 Werneth Road, Woodley",
    "sg:city":"Stockport",
    "sg:classifiers":[
        {
            "category":"Manufacturing",
            "subcategory":"Petroleum Products",
            "type":"Manufacturing & Wholesale Goods"
        }
    ],
    "sg:postcode":"SK6 1HR",
    "sg:province":"Cheshire",
    "sg:tags":[
        "double",
        "glazing"
    ],
    "wof:name":"Chadkirk Construction",
    "wof:placetype":"venue"
},
  "geometry": {"coordinates":[-2.0849740505,53.4259757996],"type":"Point"}
}