{
  "type": "Feature",
  "properties": {
    "iso:country":"GB",
    "sg:address":"179 Chapman St",
    "sg:city":"Manchester",
    "sg:classifiers":[
        {
            "category":"Autos & Motor Vehicles",
            "subcategory":"Automobile Sales",
            "type":"Retail Goods"
        }
    ],
    "sg:phone":"+44 161 223 8883",
    "sg:postcode":"M18 8WP",
    "sg:province":"Greater Manchester",
    "sg:tags":[
        "car"
    ],
    "wof:name":"Advantage Cars",
    "wof:placetype":"venue"
},
  "geometry": {"coordinates":[-2.167414,53.461109],"type":"Point"}
}