{
  "type": "Feature",
  "properties": {
    "iso:country":"GB",
    "sg:address":"2 Tayson Way",
    "sg:city":"Malvern",
    "sg:classifiers":[
        {
            "category":"Home & Garden",
            "subcategory":"Carpets & Floor Coverings",
            "type":"Retail Goods"
        }
    ],
    "sg:phone":"+44 1684 567367",
    "sg:postcode":"WR14 1UF",
    "sg:province":"Herefordshire",
    "sg:tags":[
        "cleaner",
        "upholstery"
    ],
    "wof:name":"A J B Carpet Cleaning Co",
    "wof:placetype":"venue"
},
  "geometry": {"coordinates":[-2.32279,52.133278],"type":"Point"}
}