{
  "type": "Feature",
  "properties": {
    "addr:full":"84/86 Hood St Northampton Northamptonshire NN1 3QU",
    "addr:housenumber":"84 / 86",
    "addr:postcode":"nn1 3qu",
    "addr:street":"Hood St",
    "iso:country":"GB",
    "sg:address":"84/86 Hood St",
    "sg:city":"Northampton",
    "sg:classifiers":[
        {
            "category":"Retail",
            "subcategory":"Laundry & Dry Cleaning",
            "type":"Services"
        }
    ],
    "sg:postcode":"NN1 3QU",
    "sg:province":"Northamptonshire",
    "sg:tags":[
        "alteration"
    ],
    "wof:name":"Dresswell Dry Cleaning Ltd",
    "wof:placetype":"venue"
},
  "geometry": {"coordinates":[-0.88416,52.24593],"type":"Point"}
}