{
  "type": "Feature",
  "properties": {
    "addr:full":"Lifeline House, Station Rd Totnes Devon TQ9 5HW",
    "addr:postcode":"tq9 5hw",
    "addr:street":"Station Rd",
    "iso:country":"GB",
    "sg:address":"Lifeline House, Station Rd",
    "sg:city":"Totnes",
    "sg:classifiers":[
        {
            "category":"Professional",
            "subcategory":"Detective & Security Services",
            "type":"Services"
        }
    ],
    "sg:phone":"+44 1803 867083",
    "sg:postcode":"TQ9 5HW",
    "sg:province":"Devon",
    "wof:name":"Lifeline Alarm Service",
    "wof:placetype":"venue"
},
  "geometry": {"coordinates":[-3.685299,50.433636],"type":"Point"}
}