{
  "type": "Feature",
  "properties": {
    "addr:full":"24 Ermine Street, Caxton Cambridge Cambridgeshire CB3 8PQ",
    "addr:housenumber":"24",
    "addr:postcode":"cb3 8pq",
    "addr:street":"Ermine Street",
    "iso:country":"GB",
    "sg:address":"24 Ermine Street, Caxton",
    "sg:city":"Cambridge",
    "sg:classifiers":[
        {
            "category":"Travel",
            "subcategory":"Hotels & Motels",
            "type":"Entertainment"
        }
    ],
    "sg:phone":"+44 1954 719228",
    "sg:postcode":"CB3 8PQ",
    "sg:province":"Cambridgeshire",
    "sg:tags":[
        "house",
        "guest"
    ],
    "wof:name":"Pauline Benson",
    "wof:placetype":"venue"
},
  "geometry": {"coordinates":[-0.0926269963,52.2064781189],"type":"Point"}
}