{
  "type": "Feature",
  "properties": {
    "iso:country":"GB",
    "sg:address":"21a Church Rd",
    "sg:city":"London",
    "sg:classifiers":[
        {
            "category":"Insurance",
            "subcategory":"Insurance Agent",
            "type":"Services"
        }
    ],
    "sg:postcode":"SE19 2TE",
    "sg:province":"Greater London",
    "sg:tags":[
        "broker"
    ],
    "wof:name":"Johnstone & Rose",
    "wof:placetype":"venue"
},
  "geometry": {"coordinates":[-0.079096,51.419083],"type":"Point"}
}