{
  "type": "Feature",
  "properties": {
    "addr:full":"815-817 High Road London Greater London N12 8PR",
    "addr:housenumber":"815-817",
    "addr:postcode":"n12 8pr",
    "addr:street":"High Road",
    "iso:country":"GB",
    "sg:address":"815-817 High Road",
    "sg:city":"London",
    "sg:classifiers":[
        {
            "category":"Shopping",
            "subcategory":"Discount & Variety Stores",
            "type":"Retail Goods"
        }
    ],
    "sg:phone":"+44 20 8445 5018",
    "sg:postcode":"N12 8PR",
    "sg:province":"Greater London",
    "sg:tags":[
        "centre"
    ],
    "wof:name":"Poundbusters",
    "wof:placetype":"venue"
},
  "geometry": {"coordinates":[-0.176985994,51.6165847778],"type":"Point"}
}