{
  "type": "Feature",
  "properties": {
    "addr:full":"13 Church Street Cobham Surrey KT11 3EG",
    "addr:housenumber":"13",
    "addr:postcode":"kt11 3eg",
    "addr:street":"Church Street",
    "iso:country":"GB",
    "sg:address":"13 Church Street",
    "sg:city":"Cobham",
    "sg:classifiers":[
        {
            "category":"Wholesale",
            "subcategory":"Construction Materials",
            "type":"Manufacturing & Wholesale Goods"
        }
    ],
    "sg:phone":"+44 1932 865156",
    "sg:postcode":"KT11 3EG",
    "sg:province":"Surrey",
    "sg:tags":[
        "merchant",
        "glass"
    ],
    "wof:name":"The Glass Centre",
    "wof:placetype":"venue"
},
  "geometry": {"coordinates":[-0.411255002,51.3265609741],"type":"Point"}
}