{
  "type": "Feature",
  "properties": {
    "addr:full":"The Dovecotes West Bromwich West Midlands B70 0SD",
    "addr:postcode":"b70 0sd",
    "iso:country":"GB",
    "sg:address":"The Dovecotes",
    "sg:city":"West Bromwich",
    "sg:classifiers":[
        {
            "category":"Bars & Pubs",
            "type":"Food & Drink"
        }
    ],
    "sg:phone":"+44 121 556 0008",
    "sg:postcode":"B70 0SD",
    "sg:province":"West Midlands",
    "sg:tags":[
        "pubs",
        "inn"
    ],
    "wof:name":"Full Marks Ltd.",
    "wof:placetype":"venue"
},
  "geometry": {"coordinates":[-1.9902240038,52.5186233521],"type":"Point"}
}