{
  "type": "Feature",
  "properties": {
    "iso:country":"GB",
    "sg:address":"Auction Mart Lane",
    "sg:city":"Penrith",
    "sg:classifiers":[
        {
            "category":"Professional",
            "subcategory":"Computer Services",
            "type":"Services"
        }
    ],
    "sg:phone":"+44 1768 867077",
    "sg:postcode":"CA11 7JG",
    "sg:province":"Cumbria",
    "sg:tags":[
        "system",
        "software"
    ],
    "wof:name":"DSM Y 2 K Computer Consultants",
    "wof:placetype":"venue"
},
  "geometry": {"coordinates":[-2.7557940483,54.6631546021],"type":"Point"}
}