{
  "type": "Feature",
  "properties": {
    "iso:country":"GB",
    "sg:address":"Mundells",
    "sg:city":"Welwyn Garden City",
    "sg:classifiers":[
        {
            "category":"Organizations",
            "subcategory":"Membership Organization",
            "type":"Services"
        }
    ],
    "sg:phone":"+44 1707 322056",
    "sg:postcode":"AL7 1LZ",
    "sg:province":"Hertfordshire",
    "sg:tags":[
        "club"
    ],
    "wof:name":"Avdel Sports & Social Club",
    "wof:placetype":"venue"
},
  "geometry": {"coordinates":[-0.1876399964,51.8091812134],"type":"Point"}
}