{
  "type": "Feature",
  "properties": {
    "addr:full":"61 Camberwell Rd Camberwell Greater London SE5 0EZ",
    "addr:housenumber":"61",
    "addr:postcode":"se5 0ez",
    "addr:street":"Camberwell Rd",
    "iso:country":"GB",
    "sg:address":"61 Camberwell Rd",
    "sg:city":"Camberwell",
    "sg:classifiers":[
        {
            "category":"Autos & Motor Vehicles",
            "subcategory":"Motorcycle Sales",
            "type":"Retail Goods"
        }
    ],
    "sg:phone":"+44 20 7252 7446",
    "sg:postcode":"SE5 0EZ",
    "sg:province":"Greater London",
    "sg:tags":[
        "component"
    ],
    "wof:name":"Carnell Roadsport & Leisure",
    "wof:placetype":"venue"
},
  "geometry": {"coordinates":[-0.0941239968,51.4833984375],"type":"Point"}
}