{
  "type": "Feature",
  "properties": {
    "addr:full":"83-91 Emscote Road Warwick Warwickshire CV34 5QY",
    "addr:housenumber":"83-91",
    "addr:postcode":"cv34 5qy",
    "addr:street":"Emscote Road",
    "iso:country":"GB",
    "sg:address":"83-91 Emscote Road",
    "sg:city":"Warwick",
    "sg:classifiers":[
        {
            "category":"Shopping",
            "subcategory":"Computers & Home Electronics",
            "type":"Retail Goods"
        },
        {
            "category":"Communications",
            "type":"Services"
        }
    ],
    "sg:phone":"+44 1926 492867",
    "sg:postcode":"CV34 5QY",
    "sg:province":"Warwickshire",
    "sg:tags":[
        "tv",
        "radio",
        "television",
        "video",
        "sale"
    ],
    "wof:name":"Owens Radio & T V",
    "wof:placetype":"venue"
},
  "geometry": {"coordinates":[-1.5637569427,52.2879638672],"type":"Point"}
}