{
  "type": "Feature",
  "properties": {
    "addr:full":"St Barbe Chambers, 20 The Hundred Romsey Hampshire SO51 8BW",
    "addr:housenumber":"20",
    "addr:postcode":"so51 8bw",
    "addr:street":"St;The Hundred",
    "iso:country":"GB",
    "sg:address":"St Barbe Chambers, 20 The Hundred",
    "sg:city":"Romsey",
    "sg:classifiers":[
        {
            "category":"Banks & Credit Unions",
            "subcategory":"Financial Services",
            "type":"Services"
        }
    ],
    "sg:phone":"+44 1794 521555",
    "sg:postcode":"SO51 8BW",
    "sg:province":"Hampshire",
    "sg:tags":[
        "adviser"
    ],
    "wof:name":"Roderick Hall Associates",
    "wof:placetype":"venue"
},
  "geometry": {"coordinates":[-1.4953910112,50.9885826111],"type":"Point"}
}