{
  "type": "Feature",
  "properties": {
    "addr:full":"29 Lower Wk, The Pent House Tunbridge Wells East Sussex TN2 5TD",
    "addr:housenumber":"29;pent house tunbridge",
    "addr:postcode":"tn2 5td",
    "addr:street":"Lower Wk The;Wells",
    "iso:country":"GB",
    "sg:address":"29 Lower Wk, The Pent House",
    "sg:city":"Tunbridge Wells",
    "sg:classifiers":[
        {
            "category":"Shopping",
            "subcategory":"Antiques",
            "type":"Retail Goods"
        }
    ],
    "sg:postcode":"TN2 5TD",
    "sg:province":"East Sussex",
    "wof:name":"Beau Nash Antiques",
    "wof:placetype":"venue"
},
  "geometry": {"coordinates":[0.2579300106,51.1259994507],"type":"Point"}
}