{
  "type": "Feature",
  "properties": {
    "iso:country":"GB",
    "sg:address":"167 Praed Street",
    "sg:city":"Bayswater",
    "sg:classifiers":[
        {
            "category":"Shopping",
            "subcategory":"Clothing, Apparel, & Fashions",
            "type":"Retail Goods"
        }
    ],
    "sg:postcode":"W2 1RH",
    "sg:province":"Greater London",
    "sg:tags":[
        "clothing"
    ],
    "wof:name":"Ballet International Ltd",
    "wof:placetype":"venue"
},
  "geometry": {"coordinates":[-0.174959,51.515961],"type":"Point"}
}