{
  "type": "Feature",
  "properties": {
    "addr:full":"Po Box 1572 Ascot Berkshire SL5 0PF",
    "addr:housenumber":"po",
    "addr:postcode":"sl5 0pf",
    "addr:street":"Box 1572",
    "iso:country":"GB",
    "sg:address":"Po Box 1572",
    "sg:city":"Ascot",
    "sg:classifiers":[
        {
            "category":"Communications",
            "subcategory":"Newspaper",
            "type":"Services"
        }
    ],
    "sg:phone":"+44 1344 291398",
    "sg:postcode":"SL5 0PF",
    "sg:province":"Berkshire",
    "sg:tags":[
        "magazine"
    ],
    "wof:name":"Sounds Great",
    "wof:placetype":"venue"
},
  "geometry": {"coordinates":[-0.6390089989,51.4032211304],"type":"Point"}
}