{
  "type": "Feature",
  "properties": {
    "addr:full":"73-75 Newington Causeway London Greater London SE1 6BD",
    "addr:housenumber":"73-75",
    "addr:postcode":"se1 6bd",
    "addr:street":"Newington Causeway",
    "iso:country":"GB",
    "sg:address":"73-75 Newington Causeway",
    "sg:city":"London",
    "sg:classifiers":[
        {
            "category":"Professional",
            "subcategory":"Lawyer & Legal Services",
            "type":"Services"
        }
    ],
    "sg:phone":"+44 20 7407 6520",
    "sg:postcode":"SE1 6BD",
    "sg:province":"Greater London",
    "sg:tags":[
        "solicitor"
    ],
    "wof:name":"O Akodu",
    "wof:placetype":"venue"
},
  "geometry": {"coordinates":[-0.098168,51.49789],"type":"Point"}
}