{
  "type": "Feature",
  "properties": {
    "addr:full":"37 Cornhill Bury St Edmunds Suffolk IP33 1DX",
    "addr:housenumber":"37",
    "addr:postcode":"ip33 1dx",
    "addr:street":"Cornhill",
    "iso:country":"GB",
    "sg:address":"37 Cornhill",
    "sg:city":"Bury St Edmunds",
    "sg:classifiers":[
        {
            "category":"Communications",
            "type":"Services"
        }
    ],
    "sg:phone":"+44 1284 706066",
    "sg:postcode":"IP33 1DX",
    "sg:province":"Suffolk",
    "sg:tags":[
        "telecommunication"
    ],
    "wof:name":"The Link",
    "wof:placetype":"venue"
},
  "geometry": {"coordinates":[0.71256,52.246109],"type":"Point"}
}