{
  "type": "Feature",
  "properties": {
    "addr:full":"W14 Shopping Centre, Brent Cross London Greater London NW4 3FB",
    "addr:postcode":"nw4 3fb",
    "addr:street":"Centre",
    "iso:country":"GB",
    "sg:address":"W14 Shopping Centre, Brent Cross",
    "sg:city":"London",
    "sg:classifiers":[
        {
            "category":"Shopping",
            "subcategory":"Clothing, Apparel, & Fashions",
            "type":"Retail Goods"
        }
    ],
    "sg:phone":"+44 20 8202 4461",
    "sg:postcode":"NW4 3FB",
    "sg:province":"Greater London",
    "sg:tags":[
        "shop",
        "ladieswear"
    ],
    "sg:website":"http://www.missselfridge.co.uk",
    "wof:name":"Miss Selfridge",
    "wof:placetype":"venue"
},
  "geometry": {"coordinates":[-0.2245000005,51.5761184692],"type":"Point"}
}