{
  "type": "Feature",
  "properties": {
    "addr:full":"St. Pauls Rd Coventry Warwickshire CV6 5DE",
    "addr:postcode":"cv6 5de",
    "addr:street":"St. Pauls Rd",
    "iso:country":"GB",
    "sg:address":"St. Pauls Rd",
    "sg:city":"Coventry",
    "sg:classifiers":[
        {
            "category":"Retail",
            "subcategory":"Funeral Services",
            "type":"Services"
        }
    ],
    "sg:phone":"+44 24 7641 5886",
    "sg:postcode":"CV6 5DE",
    "sg:province":"Warwickshire",
    "sg:tags":[
        "cemetery",
        "crematorium"
    ],
    "wof:name":"St Paul's Cemetery",
    "wof:placetype":"venue"
},
  "geometry": {"coordinates":[-1.498177,52.425194],"type":"Point"}
}