{
  "type": "Feature",
  "properties": {
    "addr:full":"2 Black Swan Buildings, Southgate Street Winchester Hampshire SO23 9DT",
    "addr:housenumber":"2",
    "addr:postcode":"so23 9dt",
    "addr:street":"Black Swan Buildings Southgate Street",
    "iso:country":"GB",
    "sg:address":"2 Black Swan Buildings, Southgate Street",
    "sg:city":"Winchester",
    "sg:classifiers":[
        {
            "category":"Real Estate",
            "subcategory":"Real Estate Agent",
            "type":"Services"
        }
    ],
    "sg:phone":"+44 1962 877880",
    "sg:postcode":"SO23 9DT",
    "sg:province":"Hampshire",
    "wof:name":"Downer & Co",
    "wof:placetype":"venue"
},
  "geometry": {"coordinates":[-1.316809,51.063068],"type":"Point"}
}