{
  "type": "Feature",
  "properties": {
    "iso:country":"GB",
    "sg:address":"113 Dumbarton Road",
    "sg:city":"Glasgow",
    "sg:classifiers":[
        {
            "category":"Professional",
            "subcategory":"Management & Consulting",
            "type":"Services"
        }
    ],
    "sg:phone":"+44 141 357 0020",
    "sg:postcode":"G11 6PW",
    "sg:province":"Glasgow City",
    "sg:tags":[
        "consultant",
        "specialist"
    ],
    "wof:name":"Cuticles Nail Design",
    "wof:placetype":"venue"
},
  "geometry": {"coordinates":[-4.2988100052,55.8702468872],"type":"Point"}
}