{
  "type": "Feature",
  "properties": {
    "addr:full":"Hedges Farm, North Orbital Road St Albans Hertfordshire AL2 2ET",
    "addr:postcode":"al2 2et",
    "addr:street":"North Orbital Road",
    "iso:country":"GB",
    "sg:address":"Hedges Farm, North Orbital Road",
    "sg:city":"St Albans",
    "sg:classifiers":[
        {
            "category":"Farming",
            "subcategory":"Farm",
            "type":"Manufacturing & Wholesale Goods"
        }
    ],
    "sg:phone":"+44 1727 853404",
    "sg:postcode":"AL2 2ET",
    "sg:province":"Hertfordshire",
    "sg:tags":[
        "mixed",
        "crop"
    ],
    "wof:name":"Woollatt & Son",
    "wof:placetype":"venue"
},
  "geometry": {"coordinates":[-0.3657610118,51.7201347351],"type":"Point"}
}