{
  "type": "Feature",
  "properties": {
    "addr:full":"65 Dimsdale Parade East, Wolstanton Newcastle Staffordshire ST5 8DP",
    "addr:housenumber":"65",
    "addr:postcode":"st5 8dp",
    "addr:street":"Dimsdale Parade East",
    "iso:country":"GB",
    "sg:address":"65 Dimsdale Parade East, Wolstanton",
    "sg:city":"Newcastle",
    "sg:classifiers":[
        {
            "category":"Building & Trades",
            "subcategory":"Construction",
            "type":"Services"
        }
    ],
    "sg:phone":"+44 1782 639340",
    "sg:postcode":"ST5 8DP",
    "sg:province":"Staffordshire",
    "sg:tags":[
        "roofing"
    ],
    "wof:name":"Major Roofing Services",
    "wof:placetype":"venue"
},
  "geometry": {"coordinates":[-2.2260429859,53.032043457],"type":"Point"}
}