{
  "type": "Feature",
  "properties": {
    "iso:country":"GB",
    "sg:address":"Knockothie House",
    "sg:city":"Ellon",
    "sg:classifiers":[
        {
            "category":"Farming",
            "subcategory":"Dairy Farm",
            "type":"Manufacturing & Wholesale Goods"
        }
    ],
    "sg:phone":"+44 1358 720261",
    "sg:postcode":"AB41 8DN",
    "sg:province":"Aberdeenshire",
    "wof:name":"A Davidson & Son",
    "wof:placetype":"venue"
},
  "geometry": {"coordinates":[-2.044719,57.411362],"type":"Point"}
}