{
  "type": "Feature",
  "properties": {
    "iso:country":"GB",
    "sg:address":"54 Atbara Road",
    "sg:city":"Teddington",
    "sg:classifiers":[
        {
            "category":"Professional",
            "subcategory":"Management & Consulting",
            "type":"Services"
        }
    ],
    "sg:phone":"+44 20 8943 9722",
    "sg:postcode":"TW11 9PD",
    "sg:province":"Greater London",
    "sg:tags":[
        "consultant",
        "business"
    ],
    "wof:name":"Pharos Associates Ltd.",
    "wof:placetype":"venue"
},
  "geometry": {"coordinates":[-0.318731,51.424404],"type":"Point"}
}