{
  "type": "Feature",
  "properties": {
    "iso:country":"GB",
    "sg:address":"32 Fisherbridge Road, Preston",
    "sg:city":"Weymouth",
    "sg:classifiers":[
        {
            "category":"Building & Trades",
            "subcategory":"Cleaning & Sanitation",
            "type":"Services"
        },
        {
            "category":"Home & Garden",
            "subcategory":"Carpets & Floor Coverings",
            "type":"Retail Goods"
        }
    ],
    "sg:phone":"+44 1305 833429",
    "sg:postcode":"DT3 6BT",
    "sg:province":"Dorset",
    "sg:tags":[
        "cleaner",
        "upholstery"
    ],
    "wof:name":"Elite Specialist Cleaning Services",
    "wof:placetype":"venue"
},
  "geometry": {"coordinates":[-2.422629,50.645103],"type":"Point"}
}