{
  "type": "Feature",
  "properties": {
    "addr:full":"The Clubhouse, Grandstand Road Worcester Worcestershire WR1 3EJ",
    "addr:postcode":"wr1 3ej",
    "addr:street":"Grandstand Road",
    "iso:country":"GB",
    "sg:address":"The Clubhouse, Grandstand Road",
    "sg:city":"Worcester",
    "sg:classifiers":[
        {
            "category":"Arena",
            "subcategory":"Sports Club",
            "type":"Entertainment"
        }
    ],
    "sg:phone":"+44 1905 22099",
    "sg:postcode":"WR1 3EJ",
    "sg:province":"Worcestershire",
    "wof:name":"Worcester Rowing Club",
    "wof:placetype":"venue"
},
  "geometry": {"coordinates":[-2.222274,52.191067],"type":"Point"}
}