{
  "type": "Feature",
  "properties": {
    "iso:country":"GB",
    "sg:address":"25 Kings Road",
    "sg:city":"Horsham",
    "sg:classifiers":[
        {
            "category":"Health Services",
            "subcategory":"Nursing And Care Facility",
            "type":"Services"
        },
        {
            "category":"Social Services",
            "subcategory":"Retirement Home",
            "type":"Services"
        }
    ],
    "sg:phone":"+44 1403 265236",
    "sg:postcode":"RH13 5PP",
    "sg:province":"West Sussex",
    "sg:tags":[
        "residential"
    ],
    "wof:name":"Gracelands",
    "wof:placetype":"venue"
},
  "geometry": {"coordinates":[-0.312766,51.069687],"type":"Point"}
}