{
  "type": "Feature",
  "properties": {
    "addr:full":"45 Market Place, Long Eaton Nottingham Derbyshire NG10 1JL",
    "addr:housenumber":"45",
    "addr:postcode":"ng10 1jl",
    "addr:street":"Market Place",
    "iso:country":"GB",
    "sg:address":"45 Market Place, Long Eaton",
    "sg:city":"Nottingham",
    "sg:classifiers":[
        {
            "category":"Bars & Pubs",
            "type":"Food & Drink"
        }
    ],
    "sg:phone":"+44 115 973 4817",
    "sg:postcode":"NG10 1JL",
    "sg:province":"Derbyshire",
    "sg:tags":[
        "pubs",
        "inn"
    ],
    "wof:name":"The Old Bell",
    "wof:placetype":"venue"
},
  "geometry": {"coordinates":[-1.2714380026,52.8984184265],"type":"Point"}
}