{
  "type": "Feature",
  "properties": {
    "iso:country":"GB",
    "sg:address":"1 Uxbridge Rd",
    "sg:city":"Hayes",
    "sg:classifiers":[
        {
            "category":"Communications",
            "subcategory":"Film & Video Production",
            "type":"Services"
        }
    ],
    "sg:postcode":"UB4 0ET",
    "sg:province":"Greater London",
    "sg:tags":[
        "recording",
        "studio"
    ],
    "wof:name":"E M I Group Plc",
    "wof:placetype":"venue"
},
  "geometry": {"coordinates":[-0.39317,51.513527],"type":"Point"}
}