{
  "type": "Feature",
  "properties": {
    "addr:full":"125 Market Street St Andrews Fife KY16 9PE",
    "addr:housenumber":"125",
    "addr:postcode":"ky16 9pe",
    "addr:street":"Market Street",
    "iso:country":"GB",
    "sg:address":"125 Market Street",
    "sg:city":"St Andrews",
    "sg:classifiers":[
        {
            "category":"Food & Beverages",
            "subcategory":"Candy",
            "type":"Retail Goods"
        },
        {
            "category":"Food & Beverages",
            "subcategory":"Bakery",
            "type":"Retail Goods"
        }
    ],
    "sg:postcode":"KY16 9PE",
    "sg:province":"Fife",
    "sg:tags":[
        "confectioner",
        "baker"
    ],
    "wof:name":"Johnsons Fudge Shop",
    "wof:placetype":"venue"
},
  "geometry": {"coordinates":[-2.7974278927,56.3405723572],"type":"Point"}
}