{
  "type": "Feature",
  "properties": {
    "iso:country":"GB",
    "sg:address":"774a Mansfield Road, Woodthorpe",
    "sg:city":"Nottingham",
    "sg:classifiers":[
        {
            "category":"Health Services",
            "subcategory":"Dentist",
            "type":"Services"
        }
    ],
    "sg:postcode":"NG5 3FH",
    "sg:province":"Nottinghamshire",
    "sg:tags":[
        "technician",
        "dental"
    ],
    "wof:name":"Sherwood Dental Laboratories",
    "wof:placetype":"venue"
},
  "geometry": {"coordinates":[-1.139062,52.993023],"type":"Point"}
}