{
  "type": "Feature",
  "properties": {
    "addr:full":"186 Station Street Burton-on-trent Derbyshire DE14 1BH",
    "addr:housenumber":"186",
    "addr:postcode":"de14 1bh",
    "addr:street":"Station Street",
    "iso:country":"GB",
    "sg:address":"186 Station Street",
    "sg:city":"Burton-on-trent",
    "sg:classifiers":[
        {
            "category":"Professional",
            "subcategory":"Art Services",
            "type":"Services"
        }
    ],
    "sg:phone":"+44 1283 563733",
    "sg:postcode":"DE14 1BH",
    "sg:province":"Derbyshire",
    "sg:tags":[
        "decorating",
        "painting"
    ],
    "wof:name":"Johnstone's Manders Paints",
    "wof:placetype":"venue"
},
  "geometry": {"coordinates":[-1.630802989,52.8031692505],"type":"Point"}
}