{
  "type": "Feature",
  "properties": {
    "addr:full":"Blue Boar Lane Norwich Norfolk NR7 8RJ",
    "addr:postcode":"nr7 8rj",
    "addr:street":"Boar Lane",
    "iso:country":"GB",
    "sg:address":"Blue Boar Lane",
    "sg:city":"Norwich",
    "sg:classifiers":[
        {
            "category":"Cafe",
            "type":"Food & Drink"
        }
    ],
    "sg:phone":"+44 1603 485447",
    "sg:postcode":"NR7 8RJ",
    "sg:province":"Norfolk",
    "sg:tags":[
        "tea",
        "room"
    ],
    "wof:name":"The Gardener's Pantry",
    "wof:placetype":"venue"
},
  "geometry": {"coordinates":[1.331974,52.659786],"type":"Point"}
}