{
  "type": "Feature",
  "properties": {
    "addr:full":"92-98 Beaconsfield Road Hastings East Sussex TN34 3TN",
    "addr:housenumber":"92-98",
    "addr:postcode":"tn34 3tn",
    "addr:street":"Beaconsfield Road",
    "iso:country":"GB",
    "sg:address":"92-98 Beaconsfield Road",
    "sg:city":"Hastings",
    "sg:classifiers":[
        {
            "category":"Manufacturing",
            "subcategory":"Petroleum Products",
            "type":"Manufacturing & Wholesale Goods"
        },
        {
            "category":"Building & Trades",
            "subcategory":"Construction",
            "type":"Services"
        }
    ],
    "sg:phone":"+44 1424 436776",
    "sg:postcode":"TN34 3TN",
    "sg:province":"East Sussex",
    "sg:tags":[
        "double",
        "glazier",
        "glazing"
    ],
    "wof:name":"Croft Glass Ltd.",
    "wof:placetype":"venue"
},
  "geometry": {"coordinates":[0.5852140188,50.8667564392],"type":"Point"}
}