{
  "type": "Feature",
  "properties": {
    "addr:full":"Victoria Institute, Main St Dumbarton Argyll and Bute G82 4NA",
    "addr:postcode":"g82 4na",
    "addr:street":"Main St",
    "iso:country":"GB",
    "sg:address":"Victoria Institute, Main St",
    "sg:city":"Dumbarton",
    "sg:classifiers":[
        {
            "category":"Education",
            "subcategory":"Library",
            "type":"Public Place"
        }
    ],
    "sg:phone":"+44 1389 752315",
    "sg:postcode":"G82 4NA",
    "sg:province":"Argyll and Bute",
    "sg:tags":[
        "book"
    ],
    "wof:name":"Lamont Library",
    "wof:placetype":"venue"
},
  "geometry": {"coordinates":[-4.5831189156,55.9645385742],"type":"Point"}
}