{
  "type": "Feature",
  "properties": {
    "addr:full":"1 Chalk Pit Lane, Wool Wareham Dorset BH20 6DW",
    "addr:housenumber":"1",
    "addr:postcode":"bh20 6dw",
    "addr:street":"Chalk Pit Lane",
    "iso:country":"GB",
    "sg:address":"1 Chalk Pit Lane, Wool",
    "sg:city":"Wareham",
    "sg:classifiers":[
        {
            "category":"Health Services",
            "subcategory":"Dentist",
            "type":"Services"
        }
    ],
    "sg:phone":"+44 1929 462269",
    "sg:postcode":"BH20 6DW",
    "sg:province":"Dorset",
    "wof:name":"Mouthpeace Dental Surgery",
    "wof:placetype":"venue"
},
  "geometry": {"coordinates":[-2.2294700146,50.6777076721],"type":"Point"}
}