{
  "type": "Feature",
  "properties": {
    "iso:country":"GB",
    "sg:address":"15 Coronation St",
    "sg:city":"Cambridge",
    "sg:classifiers":[
        {
            "category":"Government",
            "subcategory":"Office",
            "type":"Public Place"
        }
    ],
    "sg:postcode":"CB2 1HJ",
    "sg:province":"Cambridgeshire",
    "sg:tags":[
        "local"
    ],
    "wof:name":"Cambridge City Council",
    "wof:placetype":"venue"
},
  "geometry": {"coordinates":[0.126994,52.196686],"type":"Point"}
}