{
  "type": "Feature",
  "properties": {
    "addr:full":"39-41 Goldhawk Road London Greater London W12 8QP",
    "addr:housenumber":"39-41",
    "addr:postcode":"w12 8qp",
    "addr:street":"Goldhawk Road",
    "iso:country":"GB",
    "sg:address":"39-41 Goldhawk Road",
    "sg:city":"London",
    "sg:classifiers":[
        {
            "category":"Professional",
            "subcategory":"Lawyer & Legal Services",
            "type":"Services"
        }
    ],
    "sg:phone":"+44 20 8746 0077",
    "sg:postcode":"W12 8QP",
    "sg:province":"Greater London",
    "sg:tags":[
        "solicitor"
    ],
    "wof:name":"Hecht & Co",
    "wof:placetype":"venue"
},
  "geometry": {"coordinates":[-0.225047,51.502686],"type":"Point"}
}