{
  "type": "Feature",
  "properties": {
    "addr:full":"Vulcan Way, Bawtry Road, Hatfield Woodhouse Doncaster South Yorkshire DN7 6TD",
    "addr:postcode":"dn7 6td",
    "addr:street":"Vulcan Way Bawtry Road",
    "iso:country":"GB",
    "sg:address":"Vulcan Way, Bawtry Road, Hatfield Woodhouse",
    "sg:city":"Doncaster",
    "sg:classifiers":[
        {
            "category":"Government",
            "subcategory":"Prison",
            "type":"Public Place"
        }
    ],
    "sg:phone":"+44 1302 350575",
    "sg:postcode":"DN7 6TD",
    "sg:province":"South Yorkshire",
    "wof:name":"National Dog Training Centre",
    "wof:placetype":"venue"
},
  "geometry": {"coordinates":[-0.9746130109,53.546546936],"type":"Point"}
}