{
  "type": "Feature",
  "properties": {
    "iso:country":"GB",
    "sg:address":"Sheffield Rd",
    "sg:city":"Doncaster",
    "sg:classifiers":[
        {
            "category":"Wholesale",
            "subcategory":"Non-durable Goods",
            "type":"Manufacturing & Wholesale Goods"
        }
    ],
    "sg:phone":"+44 1709 866940",
    "sg:postcode":"DN12 2AS",
    "sg:province":"South Yorkshire",
    "sg:tags":[
        "carry",
        "cash"
    ],
    "wof:name":"W M Waite",
    "wof:placetype":"venue"
},
  "geometry": {"coordinates":[-1.232884,53.476772],"type":"Point"}
}