{
  "type": "Feature",
  "properties": {
    "iso:country":"GB",
    "sg:address":"28 The Spain",
    "sg:city":"Petersfield",
    "sg:classifiers":[
        {
            "category":"Health Services",
            "subcategory":"Optometrist",
            "type":"Services"
        }
    ],
    "sg:postcode":"GU32 3LA",
    "sg:province":"Hampshire",
    "sg:tags":[
        "optician"
    ],
    "wof:name":"Owen Leigh Optometrist",
    "wof:placetype":"venue"
},
  "geometry": {"coordinates":[-0.940316,51.003441],"type":"Point"}
}