{
  "type": "Feature",
  "properties": {
    "addr:full":"28-29 High Ousegate York North Yorkshire YO1 8RX",
    "addr:housenumber":"28-29",
    "addr:postcode":"yo1 8rx",
    "addr:street":"High Ousegate",
    "iso:country":"GB",
    "sg:address":"28-29 High Ousegate",
    "sg:city":"York",
    "sg:classifiers":[
        {
            "category":"Shopping",
            "subcategory":"Books",
            "type":"Retail Goods"
        }
    ],
    "sg:phone":"+44 1904 628740",
    "sg:postcode":"YO1 8RX",
    "sg:province":"North Yorkshire",
    "sg:tags":[
        "bookseller",
        "retailer"
    ],
    "wof:name":"Waterstone's Booksellers Ltd.",
    "wof:placetype":"venue"
},
  "geometry": {"coordinates":[-1.0818990469,53.9577713013],"type":"Point"}
}