{
  "type": "Feature",
  "properties": {
    "iso:country":"GB",
    "sg:address":"5a St Stephens Road, Cold Norton",
    "sg:city":"Chelmsford",
    "sg:classifiers":[
        {
            "category":"Wholesale",
            "subcategory":"Computers",
            "type":"Manufacturing & Wholesale Goods"
        },
        {
            "category":"Professional",
            "subcategory":"Computer Services",
            "type":"Services"
        }
    ],
    "sg:phone":"+44 1621 828161",
    "sg:postcode":"CM3 6JE",
    "sg:province":"Essex",
    "sg:tags":[
        "supplier",
        "consultant",
        "consumables"
    ],
    "wof:name":"Deepol Services",
    "wof:placetype":"venue"
},
  "geometry": {"coordinates":[0.6701790094,51.6717796326],"type":"Point"}
}