{
  "type": "Feature",
  "properties": {
    "addr:full":"1 West Market Place Cirencester Gloucestershire GL7 2NH",
    "addr:housenumber":"1",
    "addr:postcode":"gl7 2nh",
    "addr:street":"West Market Place",
    "iso:country":"GB",
    "sg:address":"1 West Market Place",
    "sg:city":"Cirencester",
    "sg:classifiers":[
        {
            "category":"Shopping",
            "subcategory":"Clothing, Apparel, & Fashions",
            "type":"Retail Goods"
        }
    ],
    "sg:phone":"+44 1285 651955",
    "sg:postcode":"GL7 2NH",
    "sg:province":"Gloucestershire",
    "sg:tags":[
        "shop"
    ],
    "wof:name":"Edinburgh Woollen Mill",
    "wof:placetype":"venue"
},
  "geometry": {"coordinates":[-1.968767,51.717388],"type":"Point"}
}