{
  "type": "Feature",
  "properties": {
    "iso:country":"GB",
    "sg:address":"Steel Yard, North Street",
    "sg:city":"Stamford",
    "sg:classifiers":[
        {
            "category":"Professional",
            "subcategory":"Engineering",
            "type":"Services"
        }
    ],
    "sg:postcode":"PE9 2YN",
    "sg:province":"Cambridgeshire",
    "sg:tags":[
        "engineer",
        "mechanical"
    ],
    "wof:name":"Alan Smith Motor Engineers",
    "wof:placetype":"venue"
},
  "geometry": {"coordinates":[-0.4802899957,52.6520843506],"type":"Point"}
}