{
  "type": "Feature",
  "properties": {
    "addr:full":"17 Stone Drive, Colwall Malvern Gloucestershire WR13 6QJ",
    "addr:housenumber":"17",
    "addr:postcode":"wr13 6qj",
    "addr:street":"Stone Drive",
    "iso:country":"GB",
    "sg:address":"17 Stone Drive, Colwall",
    "sg:city":"Malvern",
    "sg:classifiers":[
        {
            "category":"Home & Garden",
            "subcategory":"Carpets & Floor Coverings",
            "type":"Retail Goods"
        }
    ],
    "sg:postcode":"WR13 6QJ",
    "sg:province":"Gloucestershire",
    "sg:tags":[
        "cleaner",
        "upholstery"
    ],
    "wof:name":"Suds & Co",
    "wof:placetype":"venue"
},
  "geometry": {"coordinates":[-2.359735,52.081463],"type":"Point"}
}