{
  "type": "Feature",
  "properties": {
    "addr:full":"11 Glen Way Coalville Leicestershire LE67 4BW",
    "addr:housenumber":"11",
    "addr:postcode":"le67 4bw",
    "addr:street":"Glen Way",
    "iso:country":"GB",
    "sg:address":"11 Glen Way",
    "sg:city":"Coalville",
    "sg:classifiers":[
        {
            "category":"Autos & Motor Vehicles",
            "subcategory":"Boat Sales",
            "type":"Retail Goods"
        }
    ],
    "sg:postcode":"LE67 4BW",
    "sg:province":"Leicestershire",
    "sg:tags":[
        "balloon"
    ],
    "wof:name":"Party Image Balloons",
    "wof:placetype":"venue"
},
  "geometry": {"coordinates":[-1.3501189947,52.7169265747],"type":"Point"}
}