{
  "type": "Feature",
  "properties": {
    "addr:full":"116 Birchover Road Nottingham Nottinghamshire NG8 4BW",
    "addr:housenumber":"116",
    "addr:postcode":"ng8 4bw",
    "addr:street":"Birchover Road",
    "iso:country":"GB",
    "sg:address":"116 Birchover Road",
    "sg:city":"Nottingham",
    "sg:classifiers":[
        {
            "category":"Personal",
            "subcategory":"Beauty Salon",
            "type":"Services"
        }
    ],
    "sg:postcode":"NG8 4BW",
    "sg:province":"Nottinghamshire",
    "sg:tags":[
        "unisex",
        "hairdresser"
    ],
    "wof:name":"Gents Jackson Hairdressers",
    "wof:placetype":"venue"
},
  "geometry": {"coordinates":[-1.2405769825,52.9581413269],"type":"Point"}
}