{
  "type": "Feature",
  "properties": {
    "iso:country":"GB",
    "sg:address":"Book House, Vincent Lane",
    "sg:city":"Dorking",
    "sg:classifiers":[
        {
            "category":"Manufacturing",
            "subcategory":"Paper Products",
            "type":"Manufacturing & Wholesale Goods"
        }
    ],
    "sg:phone":"+44 1306 880444",
    "sg:postcode":"RH4 3SB",
    "sg:province":"Surrey",
    "sg:tags":[
        "board"
    ],
    "wof:name":"P D C Agencies Ltd.",
    "wof:placetype":"venue"
},
  "geometry": {"coordinates":[-0.336757,51.227833],"type":"Point"}
}