{
  "type": "Feature",
  "properties": {
    "iso:country":"GB",
    "sg:address":"Attwood Ho, 1 Worcester Walk, New St",
    "sg:city":"Birmingham",
    "sg:classifiers":[
        {
            "category":"Professional",
            "subcategory":"Employment Agencies",
            "type":"Services"
        }
    ],
    "sg:phone":"+44 121 234 2816",
    "sg:postcode":"B2 4NX",
    "sg:province":"West Midlands",
    "sg:tags":[
        "factoring"
    ],
    "wof:name":"Lombard Natwest Commercial Services Ltd",
    "wof:placetype":"venue"
},
  "geometry": {"coordinates":[-1.89628,52.478489],"type":"Point"}
}