{
  "type": "Feature",
  "properties": {
    "iso:country":"GB",
    "sg:address":"16 Keswick Rd, Heaton Chapel",
    "sg:city":"Stockport",
    "sg:classifiers":[
        {
            "category":"Shopping",
            "subcategory":"Pets & Pet Supplies",
            "type":"Retail Goods"
        }
    ],
    "sg:postcode":"SK4 5JS",
    "sg:province":"Cheshire",
    "wof:name":"Haynes,Raymond,",
    "wof:placetype":"venue"
},
  "geometry": {"coordinates":[-2.1689789295,53.4338645935],"type":"Point"}
}