{
  "type": "Feature",
  "properties": {
    "addr:full":"54 High Street Ilfracombe Devon EX34 9QB",
    "addr:housenumber":"54",
    "addr:postcode":"ex34 9qb",
    "addr:street":"High Street",
    "iso:country":"GB",
    "sg:address":"54 High Street",
    "sg:city":"Ilfracombe",
    "sg:classifiers":[
        {
            "category":"Personal",
            "subcategory":"Beauty Salon",
            "type":"Services"
        }
    ],
    "sg:phone":"+44 1271 865061",
    "sg:postcode":"EX34 9QB",
    "sg:province":"Devon",
    "sg:tags":[
        "unisex",
        "hairdresser"
    ],
    "wof:name":"Zig Zags hair shop",
    "wof:placetype":"venue"
},
  "geometry": {"coordinates":[-4.1252660751,51.207195282],"type":"Point"}
}