{
  "type": "Feature",
  "properties": {
    "addr:full":"372-374 Portland Road Hove East Sussex BN3 5SD",
    "addr:housenumber":"372-374",
    "addr:postcode":"bn3 5sd",
    "addr:street":"Portland Road",
    "iso:country":"GB",
    "sg:address":"372-374 Portland Road",
    "sg:city":"Hove",
    "sg:classifiers":[
        {
            "category":"Home & Garden",
            "subcategory":"Carpets & Floor Coverings",
            "type":"Retail Goods"
        }
    ],
    "sg:phone":"+44 1273 422075",
    "sg:postcode":"BN3 5SD",
    "sg:province":"East Sussex",
    "sg:tags":[
        "wall",
        "tie",
        "replacement"
    ],
    "wof:name":"Wallfix Ltd.",
    "wof:placetype":"venue"
},
  "geometry": {"coordinates":[-0.1993560046,50.8347434998],"type":"Point"}
}