{
  "type": "Feature",
  "properties": {
    "addr:full":"Low Street, East Drayton Retford Nottinghamshire DN22 0LN",
    "addr:postcode":"dn22 0ln",
    "addr:street":"Low Street East",
    "iso:country":"GB",
    "sg:address":"Low Street, East Drayton",
    "sg:city":"Retford",
    "sg:classifiers":[
        {
            "category":"Bars & Pubs",
            "type":"Food & Drink"
        }
    ],
    "sg:postcode":"DN22 0LN",
    "sg:province":"Nottinghamshire",
    "sg:tags":[
        "pubs",
        "inn"
    ],
    "wof:name":"J & K Reilly",
    "wof:placetype":"venue"
},
  "geometry": {"coordinates":[-0.8380089998,53.268989563],"type":"Point"}
}