{
  "type": "Feature",
  "properties": {
    "addr:full":"Syringa, The Causeway, Mark Highbridge Somerset TA9 4QA",
    "addr:postcode":"ta9 4qa",
    "addr:street":"The Causeway Mark",
    "iso:country":"GB",
    "sg:address":"Syringa, The Causeway, Mark",
    "sg:city":"Highbridge",
    "sg:classifiers":[
        {
            "category":"Government",
            "subcategory":"Post Office",
            "type":"Public Place"
        }
    ],
    "sg:phone":"+44 1278 641647",
    "sg:postcode":"TA9 4QA",
    "sg:province":"Somerset",
    "sg:tags":[
        "messenger",
        "courier"
    ],
    "wof:name":"T & P Transport",
    "wof:placetype":"venue"
},
  "geometry": {"coordinates":[-2.892619,51.227337],"type":"Point"}
}