{
  "type": "Feature",
  "properties": {
    "addr:full":"48 Vera Road, Fulham London Greater London SW6 6QW",
    "addr:housenumber":"48",
    "addr:postcode":"sw6 6qw",
    "addr:street":"Vera Road",
    "iso:country":"GB",
    "sg:address":"48 Vera Road, Fulham",
    "sg:city":"London",
    "sg:classifiers":[
        {
            "category":"Bus Charters",
            "type":"Transportation"
        }
    ],
    "sg:phone":"+44 20 7736 6693",
    "sg:postcode":"SW6 6QW",
    "sg:province":"Greater London",
    "sg:tags":[
        "hire",
        "coach"
    ],
    "wof:name":"Gaytime Coaches",
    "wof:placetype":"venue"
},
  "geometry": {"coordinates":[-0.2120410055,51.4754333496],"type":"Point"}
}