{
  "type": "Feature",
  "properties": {
    "addr:full":"11 Albion Street, Hyde Park London Greater London W2 2AS",
    "addr:housenumber":"11",
    "addr:postcode":"w2 2as",
    "addr:street":"Albion Street",
    "iso:country":"GB",
    "sg:address":"11 Albion Street, Hyde Park",
    "sg:city":"London",
    "sg:classifiers":[
        {
            "category":"Professional",
            "subcategory":"Management & Consulting",
            "type":"Services"
        }
    ],
    "sg:phone":"+44 20 7471 3900",
    "sg:postcode":"W2 2AS",
    "sg:province":"Greater London",
    "sg:tags":[
        "consultant",
        "business"
    ],
    "wof:name":"L M G International Ltd.",
    "wof:placetype":"venue"
},
  "geometry": {"coordinates":[-0.166883,51.513508],"type":"Point"}
}