{
  "type": "Feature",
  "properties": {
    "iso:country":"GB",
    "sg:address":"32 Castle Street",
    "sg:city":"Beaumaris",
    "sg:classifiers":[
        {
            "category":"Shopping",
            "subcategory":"Books",
            "type":"Retail Goods"
        }
    ],
    "sg:postcode":"LL58 8AP",
    "sg:province":"Isle of Anglesey",
    "sg:tags":[
        "bookseller"
    ],
    "wof:name":"The Bookshop",
    "wof:placetype":"venue"
},
  "geometry": {"coordinates":[-4.0922908783,53.2633094788],"type":"Point"}
}