{
  "type": "Feature",
  "properties": {
    "iso:country":"GB",
    "sg:address":"Hampshire Farm, Westbourne Rd",
    "sg:city":"Emsworth",
    "sg:classifiers":[
        {
            "category":"Manufacturing",
            "subcategory":"Building Materials",
            "type":"Manufacturing & Wholesale Goods"
        }
    ],
    "sg:phone":"+44 1243 376751",
    "sg:postcode":"PO10 7RN",
    "sg:province":"Hampshire",
    "sg:tags":[
        "gate",
        "mnfrs"
    ],
    "wof:name":"Westbournes Steel & Pipe",
    "wof:placetype":"venue"
},
  "geometry": {"coordinates":[-0.937569,50.853851],"type":"Point"}
}