{
  "type": "Feature",
  "properties": {
    "addr:full":"46 Market Square Witney Oxfordshire OX8 6AL",
    "addr:housenumber":"46",
    "addr:postcode":"ox8 6al",
    "addr:street":"Market Square",
    "iso:country":"GB",
    "sg:address":"46 Market Square",
    "sg:city":"Witney",
    "sg:classifiers":[
        {
            "category":"Social Services",
            "subcategory":"Retirement Home",
            "type":"Services"
        }
    ],
    "sg:phone":"+44 1993 708905",
    "sg:postcode":"OX8 6AL",
    "sg:province":"Oxfordshire",
    "sg:tags":[
        "care"
    ],
    "wof:name":"Day & Night Care Assistance",
    "wof:placetype":"venue"
},
  "geometry": {"coordinates":[-1.485638,51.783337],"type":"Point"}
}