{
  "type": "Feature",
  "properties": {
    "addr:full":"151 Cwmamman Road, Garnant Ammanford Carmarthenshire SA18 1NB",
    "addr:housenumber":"151",
    "addr:postcode":"sa18 1nb",
    "addr:street":"Cwmamman Road",
    "iso:country":"GB",
    "sg:address":"151 Cwmamman Road, Garnant",
    "sg:city":"Ammanford",
    "sg:classifiers":[
        {
            "category":"Government",
            "subcategory":"Post Office",
            "type":"Public Place"
        }
    ],
    "sg:phone":"+44 1269 822279",
    "sg:postcode":"SA18 1NB",
    "sg:province":"Carmarthenshire",
    "wof:name":"Garnant Post Office",
    "wof:placetype":"venue"
},
  "geometry": {"coordinates":[-3.926764,51.805183],"type":"Point"}
}