{
  "type": "Feature",
  "properties": {
    "iso:country":"GB",
    "sg:address":"Concept House, 35 Kingston Crescent, North End",
    "sg:city":"Portsmouth",
    "sg:classifiers":[
        {
            "category":"Real Estate",
            "subcategory":"Architect",
            "type":"Services"
        }
    ],
    "sg:phone":"+44 23 9267 3618",
    "sg:postcode":"PO2 8AA",
    "sg:province":"Hampshire",
    "wof:name":"Kenn Scaddan Associates Ltd",
    "wof:placetype":"venue"
},
  "geometry": {"coordinates":[-1.0817799568,50.8133888245],"type":"Point"}
}