{
  "type": "Feature",
  "properties": {
    "addr:full":"31-33 Radnor Road Weybridge Surrey KT13 8JU",
    "addr:housenumber":"31-33",
    "addr:postcode":"kt13 8ju",
    "addr:street":"Radnor Road",
    "iso:country":"GB",
    "sg:address":"31-33 Radnor Road",
    "sg:city":"Weybridge",
    "sg:classifiers":[
        {
            "category":"Home & Garden",
            "subcategory":"Kitchen Supply",
            "type":"Retail Goods"
        }
    ],
    "sg:phone":"+44 1932 849131",
    "sg:postcode":"KT13 8JU",
    "sg:province":"Surrey",
    "sg:tags":[
        "equipment",
        "catering"
    ],
    "wof:name":"Rowlett Rutland Ltd.",
    "wof:placetype":"venue"
},
  "geometry": {"coordinates":[-0.459276,51.377468],"type":"Point"}
}