{
  "type": "Feature",
  "properties": {
    "addr:full":"52 Sands Lane Mirfield West Yorkshire WF14 8HJ",
    "addr:housenumber":"52",
    "addr:postcode":"wf14 8hj",
    "addr:street":"Sands Lane",
    "iso:country":"GB",
    "sg:address":"52 Sands Lane",
    "sg:city":"Mirfield",
    "sg:classifiers":[
        {
            "category":"Health Services",
            "subcategory":"Nursing And Care Facility",
            "type":"Services"
        }
    ],
    "sg:phone":"+44 1924 491570",
    "sg:postcode":"WF14 8HJ",
    "sg:province":"West Yorkshire",
    "sg:tags":[
        "home"
    ],
    "wof:name":"A Saxton",
    "wof:placetype":"venue"
},
  "geometry": {"coordinates":[-1.6670149565,53.6676712036],"type":"Point"}
}