{
  "type": "Feature",
  "properties": {
    "iso:country":"GB",
    "sg:address":"6 Cambridge Rd, Kesgrave",
    "sg:city":"Ipswich",
    "sg:classifiers":[
        {
            "category":"Professional",
            "subcategory":"Testing Lab",
            "type":"Services"
        }
    ],
    "sg:postcode":"IP5 1EN",
    "sg:province":"Suffolk",
    "sg:tags":[
        "laboratory"
    ],
    "wof:name":"E M X (U K) Ltd",
    "wof:placetype":"venue"
},
  "geometry": {"coordinates":[1.224055,52.063469],"type":"Point"}
}