{
  "type": "Feature",
  "properties": {
    "iso:country":"GB",
    "sg:address":"51 Portland Street",
    "sg:city":"Cheltenham",
    "sg:classifiers":[
        {
            "category":"Building & Trades",
            "subcategory":"Construction",
            "type":"Services"
        }
    ],
    "sg:postcode":"GL52 2NX",
    "sg:province":"Gloucestershire",
    "sg:tags":[
        "builder"
    ],
    "wof:name":"Russ Design & Build",
    "wof:placetype":"venue"
},
  "geometry": {"coordinates":[-2.0713570118,51.9037437439],"type":"Point"}
}