{
  "type": "Feature",
  "properties": {
    "iso:country":"GB",
    "sg:address":"Old Hall Farm, Fakenham Road, Attlebridge",
    "sg:city":"Norwich",
    "sg:classifiers":[
        {
            "category":"Farming",
            "subcategory":"Farm",
            "type":"Manufacturing & Wholesale Goods"
        }
    ],
    "sg:postcode":"NR9 5TQ",
    "sg:province":"Norfolk",
    "sg:tags":[
        "mixed",
        "crop"
    ],
    "wof:name":"W D Oram",
    "wof:placetype":"venue"
},
  "geometry": {"coordinates":[1.155095,52.704361],"type":"Point"}
}