{
  "type": "Feature",
  "properties": {
    "addr:full":"Unit A2, Bybow Farm, Orchard Way Dartford Kent DA2 7ER",
    "addr:postcode":"da2 7er",
    "addr:street":"Orchard Way",
    "iso:country":"GB",
    "sg:address":"Unit A2, Bybow Farm, Orchard Way",
    "sg:city":"Dartford",
    "sg:classifiers":[
        {
            "category":"Manufacturing",
            "subcategory":"Metals",
            "type":"Manufacturing & Wholesale Goods"
        }
    ],
    "sg:phone":"+44 1322 273028",
    "sg:postcode":"DA2 7ER",
    "sg:province":"Kent",
    "sg:tags":[
        "steel",
        "fabricator",
        "erectors"
    ],
    "wof:name":"Long & Co. Engineering Designs",
    "wof:placetype":"venue"
},
  "geometry": {"coordinates":[0.2086299956,51.426361084],"type":"Point"}
}