{
  "type": "Feature",
  "properties": {
    "addr:full":"Waterloo House, Walesby Road Market Rasen Lincolnshire LN8 3EX",
    "addr:postcode":"ln8 3ex",
    "addr:street":"Walesby Road",
    "iso:country":"GB",
    "sg:address":"Waterloo House, Walesby Road",
    "sg:city":"Market Rasen",
    "sg:classifiers":[
        {
            "category":"Social Services",
            "subcategory":"Retirement Home",
            "type":"Services"
        }
    ],
    "sg:phone":"+44 1673 842343",
    "sg:postcode":"LN8 3EX",
    "sg:province":"Lincolnshire",
    "sg:tags":[
        "residential",
        "care"
    ],
    "wof:name":"Platinum Care (Lincoln) Ltd.",
    "wof:placetype":"venue"
},
  "geometry": {"coordinates":[-0.3310610056,53.3900489807],"type":"Point"}
}