{
  "type": "Feature",
  "properties": {
    "iso:country":"GB",
    "sg:address":"7 Stone Buildings",
    "sg:city":"London",
    "sg:classifiers":[
        {
            "category":"Professional",
            "subcategory":"Lawyer & Legal Services",
            "type":"Services"
        }
    ],
    "sg:phone":"+44 20 7681 7681",
    "sg:postcode":"WC2A 3SZ",
    "sg:province":"Greater London",
    "sg:tags":[
        "barrister"
    ],
    "wof:name":"Clarendon Chambers",
    "wof:placetype":"venue"
},
  "geometry": {"coordinates":[-0.11355,51.516827],"type":"Point"}
}