{
  "type": "Feature",
  "properties": {
    "addr:full":"Bridgewater Ho, 58-60 Whitworth St Manchester Greater Manchester M1 6LT",
    "addr:housenumber":"58-60",
    "addr:postcode":"m1 6lt",
    "addr:street":"Whitworth St",
    "iso:country":"GB",
    "sg:address":"Bridgewater Ho, 58-60 Whitworth St",
    "sg:city":"Manchester",
    "sg:classifiers":[
        {
            "category":"Professional",
            "subcategory":"Engineering",
            "type":"Services"
        }
    ],
    "sg:postcode":"M1 6LT",
    "sg:province":"Greater Manchester",
    "sg:tags":[
        "consulting",
        "design",
        "engineer"
    ],
    "wof:name":"R O C P Ltd",
    "wof:placetype":"venue"
},
  "geometry": {"coordinates":[-2.24016,53.475182],"type":"Point"}
}