{
  "type": "Feature",
  "properties": {
    "addr:full":"6 Bowsden Terrace Newcastle-upon-tyne Tyne and Wear NE3 1RX",
    "addr:housenumber":"6",
    "addr:postcode":"ne3 1rx",
    "addr:street":"Bowsden Terrace",
    "iso:country":"GB",
    "sg:address":"6 Bowsden Terrace",
    "sg:city":"Newcastle-upon-tyne",
    "sg:classifiers":[
        {
            "category":"Banks & Credit Unions",
            "subcategory":"Financial Services",
            "type":"Services"
        },
        {
            "category":"Health Services",
            "subcategory":"Health Practitioner",
            "type":"Services"
        }
    ],
    "sg:phone":"+44 191 213 1683",
    "sg:postcode":"NE3 1RX",
    "sg:province":"Tyne and Wear",
    "sg:tags":[
        "physiotherapist",
        "consultant"
    ],
    "wof:name":"Alpha Finance",
    "wof:placetype":"venue"
},
  "geometry": {"coordinates":[-1.605831,55.007786],"type":"Point"}
}