{
  "type": "Feature",
  "properties": {
    "addr:full":"17 A Commercial Rd Hawick Cumbria TD9 7AQ",
    "addr:housenumber":"17 a",
    "addr:postcode":"td9 7aq",
    "addr:street":"Commercial Rd",
    "iso:country":"GB",
    "sg:address":"17 A Commercial Rd",
    "sg:city":"Hawick",
    "sg:classifiers":[
        {
            "category":"Manufacturing",
            "subcategory":"Petroleum Products",
            "type":"Manufacturing & Wholesale Goods"
        }
    ],
    "sg:phone":"+44 1450 370011",
    "sg:postcode":"TD9 7AQ",
    "sg:province":"Cumbria",
    "sg:tags":[
        "double",
        "glazing"
    ],
    "wof:name":"Hawick Window Centre",
    "wof:placetype":"venue"
},
  "geometry": {"coordinates":[-2.7879459858,55.4244804382],"type":"Point"}
}