{
  "type": "Feature",
  "properties": {
    "iso:country":"GB",
    "sg:address":"122 High Street, Bathford",
    "sg:city":"Bath",
    "sg:classifiers":[
        {
            "category":"Building & Trades",
            "subcategory":"Landscaping Services",
            "type":"Services"
        }
    ],
    "sg:phone":"+44 1225 859122",
    "sg:postcode":"BA1 7TH",
    "sg:province":"Bath and North East Somerset",
    "sg:tags":[
        "gardening",
        "landscape",
        "contractor"
    ],
    "wof:name":"R J FERGUSSON",
    "wof:placetype":"venue"
},
  "geometry": {"coordinates":[-2.296316,51.399323],"type":"Point"}
}