{
  "type": "Feature",
  "properties": {
    "addr:full":"92 Wood St Liverpool Merseyside L1 4DQ",
    "addr:housenumber":"92",
    "addr:postcode":"l1 4dq",
    "addr:street":"Wood St",
    "iso:country":"GB",
    "sg:address":"92 Wood St",
    "sg:city":"Liverpool",
    "sg:classifiers":[
        {
            "category":"Professional",
            "subcategory":"Art Services",
            "type":"Services"
        }
    ],
    "sg:phone":"+44 151 709 6252",
    "sg:postcode":"L1 4DQ",
    "sg:province":"Merseyside",
    "sg:tags":[
        "graphic",
        "designer"
    ],
    "wof:name":"Shed I D",
    "wof:placetype":"venue"
},
  "geometry": {"coordinates":[-2.9776771069,53.4025688171],"type":"Point"}
}