{
  "type": "Feature",
  "properties": {
    "iso:country":"GB",
    "sg:address":"Peakes Farm, Station Road, Onneley",
    "sg:city":"Crewe",
    "sg:classifiers":[
        {
            "category":"Farming",
            "subcategory":"Livestock Farm",
            "type":"Manufacturing & Wholesale Goods"
        },
        {
            "category":"Farming",
            "subcategory":"Farm",
            "type":"Manufacturing & Wholesale Goods"
        }
    ],
    "sg:postcode":"CW3 9QH",
    "sg:province":"Cheshire",
    "sg:tags":[
        "mixed",
        "crop",
        "others"
    ],
    "wof:name":"R & Y M Moss & Son",
    "wof:placetype":"venue"
},
  "geometry": {"coordinates":[-2.373396,52.98394],"type":"Point"}
}