{
  "type": "Feature",
  "properties": {
    "iso:country":"GB",
    "sg:address":", Cheriton",
    "sg:city":"Alresford",
    "sg:classifiers":[
        {
            "category":"Education",
            "subcategory":"School",
            "type":"Public Place"
        }
    ],
    "sg:phone":"+44 1962 771278",
    "sg:postcode":"SO24 0QA",
    "sg:province":"Hampshire",
    "sg:tags":[
        "local",
        "authority"
    ],
    "wof:name":"Cheriton County Primary School",
    "wof:placetype":"venue"
},
  "geometry": {"coordinates":[-1.170953,51.054394],"type":"Point"}
}