{
  "type": "Feature",
  "properties": {
    "iso:country":"GB",
    "sg:address":"Dene Park",
    "sg:city":"Hexham",
    "sg:classifiers":[
        {
            "category":"Autos & Motor Vehicles",
            "subcategory":"Automobile Sales",
            "type":"Retail Goods"
        },
        {
            "category":"Education",
            "subcategory":"School",
            "type":"Public Place"
        },
        {
            "category":"Retail",
            "subcategory":"Auto Repair",
            "type":"Services"
        }
    ],
    "sg:phone":"+44 800 055 6703",
    "sg:postcode":"NE46 1HN",
    "sg:province":"Northumberland",
    "sg:tags":[
        "modification",
        "car",
        "local",
        "authority",
        "garage"
    ],
    "wof:name":"Gilesgate Ltd.",
    "wof:placetype":"venue"
},
  "geometry": {"coordinates":[-2.087935,54.970367],"type":"Point"}
}