{
  "type": "Feature",
  "properties": {
    "iso:country":"GB",
    "sg:address":"Somersbury Lane",
    "sg:city":"Cranleigh",
    "sg:classifiers":[
        {
            "category":"Retail",
            "subcategory":"Auto Repair",
            "type":"Services"
        }
    ],
    "sg:phone":"+44 1483 278166",
    "sg:postcode":"GU6 7SR",
    "sg:province":"Surrey",
    "sg:tags":[
        "modification",
        "garage"
    ],
    "wof:name":"C C M",
    "wof:placetype":"venue"
},
  "geometry": {"coordinates":[-0.430132,51.12891],"type":"Point"}
}