{
  "type": "Feature",
  "properties": {
    "iso:country":"GB",
    "sg:address":"Cadgwith, Ruan Minor",
    "sg:city":"Helston",
    "sg:classifiers":[
        {
            "category":"Restaurant",
            "type":"Food & Drink"
        }
    ],
    "sg:phone":"+44 1326 290727",
    "sg:postcode":"TR12 7JU",
    "sg:province":"Cornwall",
    "wof:name":"Old Cellars Cafe",
    "wof:placetype":"venue"
},
  "geometry": {"coordinates":[-5.182874,49.993996],"type":"Point"}
}