{
  "type": "Feature",
  "properties": {
    "addr:full":"434 Uxbridge Road London Greater London W12 0NS",
    "addr:housenumber":"434",
    "addr:postcode":"w12 0ns",
    "addr:street":"Uxbridge Road",
    "iso:country":"GB",
    "sg:address":"434 Uxbridge Road",
    "sg:city":"London",
    "sg:classifiers":[
        {
            "category":"Bars & Pubs",
            "type":"Food & Drink"
        }
    ],
    "sg:phone":"+44 20 8743 1697",
    "sg:postcode":"W12 0NS",
    "sg:province":"Greater London",
    "sg:tags":[
        "pubs",
        "house",
        "inn",
        "public",
        "activity"
    ],
    "wof:name":"The British Queen",
    "wof:placetype":"venue"
},
  "geometry": {"coordinates":[-0.238504,51.506447],"type":"Point"}
}