{
  "type": "Feature",
  "properties": {
    "iso:country":"GB",
    "sg:address":"38 Walker Terrace",
    "sg:city":"Tillicoultry",
    "sg:classifiers":[
        {
            "category":"Building & Trades",
            "subcategory":"Landscaping Services",
            "type":"Services"
        }
    ],
    "sg:phone":"+44 1259 753661",
    "sg:postcode":"FK13 6EF",
    "sg:province":"Clackmannanshire",
    "sg:tags":[
        "contractor"
    ],
    "wof:name":"Glen Kemp Ltd",
    "wof:placetype":"venue"
},
  "geometry": {"coordinates":[-3.7459690571,56.1513290405],"type":"Point"}
}