{
  "type": "Feature",
  "properties": {
    "addr:full":"91 High Street Marlow Berkshire SL7 1AB",
    "addr:housenumber":"91",
    "addr:postcode":"sl7 1ab",
    "addr:street":"High Street",
    "iso:country":"GB",
    "sg:address":"91 High Street",
    "sg:city":"Marlow",
    "sg:classifiers":[
        {
            "category":"Shopping",
            "subcategory":"News",
            "type":"Retail Goods"
        }
    ],
    "sg:phone":"+44 1628 482186",
    "sg:postcode":"SL7 1AB",
    "sg:province":"Berkshire",
    "sg:tags":[
        "newsagent"
    ],
    "wof:name":"Paper Chain of Marlow",
    "wof:placetype":"venue"
},
  "geometry": {"coordinates":[-0.7743600011,51.5696372986],"type":"Point"}
}