{
  "type": "Feature",
  "properties": {
    "addr:full":"3rd Floor, 21 Arlington Street London Greater London SW1A 1RN",
    "addr:housenumber":"3rd floor 21",
    "addr:postcode":"sw1a 1rn",
    "addr:street":"Arlington Street",
    "iso:country":"GB",
    "sg:address":"3rd Floor, 21 Arlington Street",
    "sg:city":"London",
    "sg:classifiers":[
        {
            "category":"Professional",
            "subcategory":"Management & Consulting",
            "type":"Services"
        }
    ],
    "sg:phone":"+44 20 8691 1143",
    "sg:postcode":"SW1A 1RN",
    "sg:province":"Greater London",
    "sg:tags":[
        "marketing",
        "consultant"
    ],
    "wof:name":"Levant Group Ltd.",
    "wof:placetype":"venue"
},
  "geometry": {"coordinates":[-0.140807,51.506794],"type":"Point"}
}