{
  "type": "Feature",
  "properties": {
    "addr:full":"Pencraig Ross On Wye Gloucestershire HR9 6HR",
    "addr:postcode":"hr9 6hr",
    "iso:country":"GB",
    "sg:address":"Pencraig",
    "sg:city":"Ross On Wye",
    "sg:classifiers":[
        {
            "category":"Travel",
            "subcategory":"Hotels & Motels",
            "type":"Entertainment"
        }
    ],
    "sg:phone":"+44 1989 770306",
    "sg:postcode":"HR9 6HR",
    "sg:province":"Gloucestershire",
    "wof:name":"Pencraig Court Hotel",
    "wof:placetype":"venue"
},
  "geometry": {"coordinates":[-2.586851,51.924904],"type":"Point"}
}