{
  "type": "Feature",
  "properties": {
    "addr:full":"1 Clarendon Cottages Ossett West Yorkshire WF5 0BP",
    "addr:housenumber":"1",
    "addr:postcode":"wf5 0bp",
    "addr:street":"Clarendon Cottages",
    "iso:country":"GB",
    "sg:address":"1 Clarendon Cottages",
    "sg:city":"Ossett",
    "sg:classifiers":[
        {
            "category":"Building & Trades",
            "subcategory":"Construction",
            "type":"Services"
        }
    ],
    "sg:phone":"+44 1924 273115",
    "sg:postcode":"WF5 0BP",
    "sg:province":"West Yorkshire",
    "sg:tags":[
        "decorator",
        "painter"
    ],
    "wof:name":"Alan Lingwood",
    "wof:placetype":"venue"
},
  "geometry": {"coordinates":[-1.587806,53.684235],"type":"Point"}
}