{
  "type": "Feature",
  "properties": {
    "iso:country":"GB",
    "sg:address":"Church Road",
    "sg:city":"Liverpool",
    "sg:classifiers":[
        {
            "category":"Retail",
            "subcategory":"Auto Repair",
            "type":"Services"
        }
    ],
    "sg:phone":"+44 151 525 2434",
    "sg:postcode":"L4 5TX",
    "sg:province":"Merseyside",
    "sg:tags":[
        "modification",
        "garage"
    ],
    "wof:name":"Church Motors",
    "wof:placetype":"venue"
},
  "geometry": {"coordinates":[-2.962102,53.443275],"type":"Point"}
}