{
  "type": "Feature",
  "properties": {
    "addr:full":"31 West Princes Street Helensburgh Argyll and Bute G84 8TF",
    "addr:housenumber":"31",
    "addr:postcode":"g84 8tf",
    "addr:street":"West Princes Street",
    "iso:country":"GB",
    "sg:address":"31 West Princes Street",
    "sg:city":"Helensburgh",
    "sg:classifiers":[
        {
            "category":"Food & Beverages",
            "subcategory":"Meat & Fish",
            "type":"Retail Goods"
        }
    ],
    "sg:phone":"+44 1436 673795",
    "sg:postcode":"G84 8TF",
    "sg:province":"Argyll and Bute",
    "sg:tags":[
        "butcher"
    ],
    "wof:name":"Joesph Callaghan",
    "wof:placetype":"venue"
},
  "geometry": {"coordinates":[-4.73483181,56.0041618347],"type":"Point"}
}