{
  "type": "Feature",
  "properties": {
    "iso:country":"GB",
    "sg:address":"Clydesdale Place, Moss Side Industrial Estate, Leyland",
    "sg:city":"Preston",
    "sg:classifiers":[
        {
            "category":"Freight",
            "type":"Transportation"
        }
    ],
    "sg:phone":"+44 1772 621754",
    "sg:postcode":"PR5 3QS",
    "sg:province":"Lancashire",
    "sg:tags":[
        "haulage",
        "road"
    ],
    "wof:name":"Norfrost",
    "wof:placetype":"venue"
},
  "geometry": {"coordinates":[-2.6934900284,53.6953392029],"type":"Point"}
}