{
  "type": "Feature",
  "properties": {
    "addr:full":"84 Hoyland Road Sheffield South Yorkshire S3 8AB",
    "addr:housenumber":"84",
    "addr:postcode":"s3 8ab",
    "addr:street":"Hoyland Road",
    "iso:country":"GB",
    "sg:address":"84 Hoyland Road",
    "sg:city":"Sheffield",
    "sg:classifiers":[
        {
            "category":"Home & Garden",
            "subcategory":"Kitchen Supply",
            "type":"Retail Goods"
        }
    ],
    "sg:phone":"+44 114 278 0138",
    "sg:postcode":"S3 8AB",
    "sg:province":"South Yorkshire",
    "sg:tags":[
        "supplier",
        "cutlery"
    ],
    "wof:name":"Designer Consumer Products (D C P) Ltd.",
    "wof:placetype":"venue"
},
  "geometry": {"coordinates":[-1.485158,53.397018],"type":"Point"}
}