{
  "type": "Feature",
  "properties": {
    "iso:country":"GB",
    "sg:address":"Unit 2, Havenlights Industrial Estate",
    "sg:city":"Grimsby",
    "sg:classifiers":[
        {
            "category":"Bars & Pubs",
            "subcategory":"Nightclub",
            "type":"Food & Drink"
        }
    ],
    "sg:postcode":"DN37 9RJ",
    "sg:province":"Lincolnshire",
    "sg:tags":[
        "karaoke"
    ],
    "wof:name":"Budgie Daves",
    "wof:placetype":"venue"
},
  "geometry": {"coordinates":[-0.1378999949,53.5610313416],"type":"Point"}
}