{
  "type": "Feature",
  "properties": {
    "addr:full":"55 The Green Epsom Surrey KT17 3JU",
    "addr:housenumber":"55",
    "addr:postcode":"kt17 3ju",
    "addr:street":"The Green",
    "iso:country":"GB",
    "sg:address":"55 The Green",
    "sg:city":"Epsom",
    "sg:classifiers":[
        {
            "category":"Real Estate",
            "subcategory":"Architect",
            "type":"Services"
        }
    ],
    "sg:postcode":"KT17 3JU",
    "sg:province":"Surrey",
    "wof:name":"Ray Read",
    "wof:placetype":"venue"
},
  "geometry": {"coordinates":[-0.2477129996,51.3371963501],"type":"Point"}
}