{
  "type": "Feature",
  "properties": {
    "iso:country":"GB",
    "sg:address":"89b Durham Road",
    "sg:city":"Consett",
    "sg:classifiers":[
        {
            "category":"Fast Food",
            "type":"Food & Drink"
        }
    ],
    "sg:postcode":"DH8 8RR",
    "sg:province":"Durham",
    "sg:tags":[
        "away",
        "take"
    ],
    "wof:name":"Premier Pizzas",
    "wof:placetype":"venue"
},
  "geometry": {"coordinates":[-1.8492980003,54.8612213135],"type":"Point"}
}