{
  "type": "Feature",
  "properties": {
    "addr:full":"Bank House Farm, Ruskington Fen, Billinghay Lincoln Lincolnshire LN4 4DS",
    "addr:postcode":"ln4 4ds",
    "iso:country":"GB",
    "sg:address":"Bank House Farm, Ruskington Fen, Billinghay",
    "sg:city":"Lincoln",
    "sg:classifiers":[
        {
            "category":"Home & Garden",
            "subcategory":"Garden Supply",
            "type":"Retail Goods"
        },
        {
            "category":"Farming",
            "subcategory":"Livestock Farm",
            "type":"Manufacturing & Wholesale Goods"
        },
        {
            "category":"Farming",
            "subcategory":"Farm",
            "type":"Manufacturing & Wholesale Goods"
        }
    ],
    "sg:phone":"+44 1526 832256",
    "sg:postcode":"LN4 4DS",
    "sg:province":"Lincolnshire",
    "sg:tags":[
        "mixed",
        "bulb",
        "grower",
        "others"
    ],
    "wof:name":"N A Osborne",
    "wof:placetype":"venue"
},
  "geometry": {"coordinates":[-0.2811099887,53.0792541504],"type":"Point"}
}