{
  "type": "Feature",
  "properties": {
    "addr:full":"High Street, Bamfords Yard, Turvey Bedford Bedfordshire MK43 8DE",
    "addr:postcode":"mk43 8de",
    "addr:street":"High Street Bamfords Yard",
    "iso:country":"GB",
    "sg:address":"High Street, Bamfords Yard, Turvey",
    "sg:city":"Bedford",
    "sg:classifiers":[
        {
            "category":"Professional",
            "subcategory":"Art Services",
            "type":"Services"
        }
    ],
    "sg:postcode":"MK43 8DE",
    "sg:province":"Bedfordshire",
    "sg:tags":[
        "photographer"
    ],
    "wof:name":"The Image Works",
    "wof:placetype":"venue"
},
  "geometry": {"coordinates":[-0.62509799,52.1624488831],"type":"Point"}
}