{
  "type": "Feature",
  "properties": {
    "iso:country":"GB",
    "sg:address":"85 Coronation Av",
    "sg:city":"Grays",
    "sg:classifiers":[
        {
            "category":"Health Services",
            "subcategory":"Doctor",
            "type":"Services"
        }
    ],
    "sg:phone":"+44 1375 846232",
    "sg:postcode":"RM18 8SW",
    "sg:province":"Essex",
    "sg:tags":[
        "practitioners"
    ],
    "wof:name":"Khan, A A",
    "wof:placetype":"venue"
},
  "geometry": {"coordinates":[0.42121,51.484558],"type":"Point"}
}