{
  "type": "Feature",
  "properties": {
    "addr:full":"126 Station Rd, Tempsford Sandy Bedfordshire SG19 2AY",
    "addr:housenumber":"126",
    "addr:postcode":"sg19 2ay",
    "addr:street":"Station Rd",
    "iso:country":"GB",
    "sg:address":"126 Station Rd, Tempsford",
    "sg:city":"Sandy",
    "sg:classifiers":[
        {
            "category":"Autos & Motor Vehicles",
            "subcategory":"Auto Supplies",
            "type":"Retail Goods"
        }
    ],
    "sg:phone":"+44 1767 640700",
    "sg:postcode":"SG19 2AY",
    "sg:province":"Bedfordshire",
    "sg:tags":[
        "electric"
    ],
    "wof:name":"Rush Electrical Services",
    "wof:placetype":"venue"
},
  "geometry": {"coordinates":[-0.282168,52.171379],"type":"Point"}
}