{
  "type": "Feature",
  "properties": {
    "addr:full":"17 Dix's Field Exeter Devon EX1 1UZ",
    "addr:housenumber":"17",
    "addr:postcode":"ex1 1uz",
    "addr:street":"Dix'S Field",
    "iso:country":"GB",
    "sg:address":"17 Dix's Field",
    "sg:city":"Exeter",
    "sg:classifiers":[
        {
            "category":"Banks & Credit Unions",
            "subcategory":"Bank",
            "type":"Services"
        }
    ],
    "sg:phone":"+44 1392 609000",
    "sg:postcode":"EX1 1UZ",
    "sg:province":"Devon",
    "wof:name":"Bank of Scotland",
    "wof:placetype":"venue"
},
  "geometry": {"coordinates":[-3.5296850204,50.7203598022],"type":"Point"}
}