{
  "type": "Feature",
  "properties": {
    "iso:country":"GB",
    "sg:address":"Gairie Works, Bellies Brae",
    "sg:city":"Kirriemuir",
    "sg:classifiers":[
        {
            "category":"Manufacturing",
            "subcategory":"Rubber & Plastics",
            "type":"Manufacturing & Wholesale Goods"
        },
        {
            "category":"Manufacturing",
            "subcategory":"Textiles",
            "type":"Manufacturing & Wholesale Goods"
        }
    ],
    "sg:phone":"+44 1575 572502",
    "sg:postcode":"DD8 4BL",
    "sg:province":"Angus",
    "sg:tags":[
        "made-up",
        "manufacturer"
    ],
    "sg:website":"http://www.jdwilkie.co.uk",
    "wof:name":"J & D Wilkie Ltd",
    "wof:placetype":"venue"
},
  "geometry": {"coordinates":[-2.998349,56.675529],"type":"Point"}
}