{
  "type": "Feature",
  "properties": {
    "addr:full":"Great Lime Road Newcastle-upon-tyne Tyne and Wear NE12 0NJ",
    "addr:postcode":"ne12 0nj",
    "addr:street":"Lime Road",
    "iso:country":"GB",
    "sg:address":"Great Lime Road",
    "sg:city":"Newcastle-upon-tyne",
    "sg:classifiers":[
        {
            "category":"Fast Food",
            "type":"Food & Drink"
        }
    ],
    "sg:postcode":"NE12 0NJ",
    "sg:province":"Tyne and Wear",
    "sg:tags":[
        "away",
        "take"
    ],
    "wof:name":"West Moor Tandoori",
    "wof:placetype":"venue"
},
  "geometry": {"coordinates":[-1.5357120037,55.0235710144],"type":"Point"}
}