{
  "type": "Feature",
  "properties": {
    "addr:full":"116 Lubbesthorpe Road Leicester Leicestershire LE3 2XE",
    "addr:housenumber":"116",
    "addr:postcode":"le3 2xe",
    "addr:street":"Lubbesthorpe Road",
    "iso:country":"GB",
    "sg:address":"116 Lubbesthorpe Road",
    "sg:city":"Leicester",
    "sg:classifiers":[
        {
            "category":"Building & Trades",
            "subcategory":"Construction",
            "type":"Services"
        }
    ],
    "sg:postcode":"LE3 2XE",
    "sg:province":"Leicestershire",
    "sg:tags":[
        "decorator",
        "painter"
    ],
    "wof:name":"P W Steans & Sons",
    "wof:placetype":"venue"
},
  "geometry": {"coordinates":[-1.184803,52.603539],"type":"Point"}
}