{
  "type": "Feature",
  "properties": {
    "addr:full":"Moralees Farm, Ingoe Newcastle-upon-tyne Northumberland NE20 0ST",
    "addr:housenumber":"newcastle-upon-tyne",
    "addr:postcode":"ne20 0st",
    "addr:street":"Northumberland",
    "iso:country":"GB",
    "sg:address":"Moralees Farm, Ingoe",
    "sg:city":"Newcastle-upon-tyne",
    "sg:classifiers":[
        {
            "category":"Banks & Credit Unions",
            "subcategory":"Investment Brokerage",
            "type":"Services"
        }
    ],
    "sg:phone":"+44 1661 886350",
    "sg:postcode":"NE20 0ST",
    "sg:province":"Northumberland",
    "sg:tags":[
        "contractor"
    ],
    "wof:name":"J P Harrison",
    "wof:placetype":"venue"
},
  "geometry": {"coordinates":[-1.941344,55.067909],"type":"Point"}
}