{
  "type": "Feature",
  "properties": {
    "iso:country":"GB",
    "sg:address":"174 Bredhurst Rd",
    "sg:city":"Gillingham",
    "sg:classifiers":[
        {
            "category":"Building & Trades",
            "subcategory":"Construction",
            "type":"Services"
        }
    ],
    "sg:phone":"+44 1634 366311",
    "sg:postcode":"ME8 0QX",
    "sg:province":"Kent",
    "sg:tags":[
        "roofing"
    ],
    "wof:name":"Chaplin Roofing Co.Ltd",
    "wof:placetype":"venue"
},
  "geometry": {"coordinates":[0.58365,51.345135],"type":"Point"}
}