{
  "type": "Feature",
  "properties": {
    "addr:full":"Unit C2, Forelle Centre, Ebblake Industrial Estate Wimborne Dorset BH31 6AX",
    "addr:housenumber":"estate",
    "addr:postcode":"bh31 6ax",
    "addr:street":"Industrial",
    "iso:country":"GB",
    "sg:address":"Unit C2, Forelle Centre, Ebblake Industrial Estate",
    "sg:city":"Wimborne",
    "sg:classifiers":[
        {
            "category":"Building & Trades",
            "subcategory":"Plumbing",
            "type":"Services"
        }
    ],
    "sg:phone":"+44 1202 826280",
    "sg:postcode":"BH31 6AX",
    "sg:province":"Dorset",
    "sg:tags":[
        "filtration",
        "system"
    ],
    "wof:name":"Filtakleen (Manufacturing) Ltd.",
    "wof:placetype":"venue"
},
  "geometry": {"coordinates":[-1.8524899483,50.8682403564],"type":"Point"}
}