{
  "type": "Feature",
  "properties": {
    "iso:country":"GB",
    "sg:address":"Uxbridge Road",
    "sg:city":"London",
    "sg:classifiers":[
        {
            "category":"Education",
            "subcategory":"School",
            "type":"Public Place"
        },
        {
            "category":"Government",
            "subcategory":"Office",
            "type":"Public Place"
        }
    ],
    "sg:phone":"+44 20 8743 4483",
    "sg:postcode":"W12 8LH",
    "sg:province":"Greater London",
    "sg:tags":[
        "local",
        "authority"
    ],
    "wof:name":"St Stephen's C of E Primary School",
    "wof:placetype":"venue"
},
  "geometry": {"coordinates":[-0.222285,51.504723],"type":"Point"}
}