{
  "type": "Feature",
  "properties": {
    "addr:full":", Lower Wych Malpas Cheshire SY14 7JX",
    "addr:postcode":"sy14 7jx",
    "addr:street":"Lower Wych",
    "iso:country":"GB",
    "sg:address":", Lower Wych",
    "sg:city":"Malpas",
    "sg:classifiers":[
        {
            "category":"Farming",
            "subcategory":"Nursery",
            "type":"Manufacturing & Wholesale Goods"
        }
    ],
    "sg:phone":"+44 1948 860586",
    "sg:postcode":"SY14 7JX",
    "sg:province":"Cheshire",
    "sg:tags":[
        "creche"
    ],
    "wof:name":"Brookfarm Nursery School",
    "wof:placetype":"venue"
},
  "geometry": {"coordinates":[-2.766258955,53.020980835],"type":"Point"}
}