{
  "type": "Feature",
  "properties": {
    "addr:full":"Hawthorn House, Dudley Road Stourbridge West Midlands DY9 8DS",
    "addr:postcode":"dy9 8ds",
    "addr:street":"Dudley Road",
    "iso:country":"GB",
    "sg:address":"Hawthorn House, Dudley Road",
    "sg:city":"Stourbridge",
    "sg:classifiers":[
        {
            "category":"Home & Garden",
            "subcategory":"Hardware",
            "type":"Retail Goods"
        },
        {
            "category":"Building & Trades",
            "subcategory":"Construction",
            "type":"Services"
        }
    ],
    "sg:phone":"+44 1384 422977",
    "sg:postcode":"DY9 8DS",
    "sg:province":"West Midlands",
    "sg:tags":[
        "tiling",
        "retailer",
        "diy",
        "contractor"
    ],
    "wof:name":"Elite Tile Ltd.",
    "wof:placetype":"venue"
},
  "geometry": {"coordinates":[-2.1176578999,52.458152771],"type":"Point"}
}