{
  "type": "Feature",
  "properties": {
    "addr:full":"8 Turnberry Road Annan Dumfries and Galloway DG12 6LH",
    "addr:housenumber":"8",
    "addr:postcode":"dg12 6lh",
    "addr:street":"Turnberry Road",
    "iso:country":"GB",
    "sg:address":"8 Turnberry Road",
    "sg:city":"Annan",
    "sg:classifiers":[
        {
            "category":"Recreation",
            "subcategory":"Fishing",
            "type":"Entertainment"
        }
    ],
    "sg:postcode":"DG12 6LH",
    "sg:province":"Dumfries and Galloway",
    "sg:tags":[
        "equipment",
        "angling"
    ],
    "wof:name":"Kevin Earl",
    "wof:placetype":"venue"
},
  "geometry": {"coordinates":[-3.245998,54.993397],"type":"Point"}
}