{
  "type": "Feature",
  "properties": {
    "addr:full":", Old Penshaw Houghton Le Spring Durham DH4 7ER",
    "addr:postcode":"dh4 7er",
    "addr:street":"Le Spring",
    "iso:country":"GB",
    "sg:address":", Old Penshaw",
    "sg:city":"Houghton Le Spring",
    "sg:classifiers":[
        {
            "category":"Social Services",
            "subcategory":"Retirement Home",
            "type":"Services"
        }
    ],
    "sg:phone":"+44 191 584 1027",
    "sg:postcode":"DH4 7ER",
    "sg:province":"Durham",
    "sg:tags":[
        "residential",
        "care"
    ],
    "wof:name":"The Monument",
    "wof:placetype":"venue"
},
  "geometry": {"coordinates":[-1.487226963,54.8792572021],"type":"Point"}
}