{
  "type": "Feature",
  "properties": {
    "addr:full":"23 Crow Road Glasgow Glasgow City G11 7RU",
    "addr:housenumber":"23",
    "addr:postcode":"g11 7ru",
    "addr:street":"Crow Road",
    "iso:country":"GB",
    "sg:address":"23 Crow Road",
    "sg:city":"Glasgow",
    "sg:classifiers":[
        {
            "category":"Building & Trades",
            "subcategory":"Construction",
            "type":"Services"
        }
    ],
    "sg:phone":"+44 141 339 7272",
    "sg:postcode":"G11 7RU",
    "sg:province":"Glasgow City",
    "sg:tags":[
        "dry",
        "roofing",
        "screeders",
        "plasterers",
        "lining"
    ],
    "wof:name":"Thomas McMaster & Son Ltd.",
    "wof:placetype":"venue"
},
  "geometry": {"coordinates":[-4.313239,55.871452],"type":"Point"}
}