{
  "type": "Feature",
  "properties": {
    "addr:full":"Station Maltings Witham Essex CM8 1DU",
    "addr:postcode":"cm8 1du",
    "addr:street":"Maltings Witham",
    "iso:country":"GB",
    "sg:address":"Station Maltings",
    "sg:city":"Witham",
    "sg:classifiers":[
        {
            "category":"Professional",
            "subcategory":"Employment Agencies",
            "type":"Services"
        }
    ],
    "sg:postcode":"CM8 1DU",
    "sg:province":"Essex",
    "sg:tags":[
        "agricultural",
        "advice"
    ],
    "wof:name":"Agrochemicals (Arbroath) Ltd.",
    "wof:placetype":"venue"
},
  "geometry": {"coordinates":[0.5913680196,51.8357086182],"type":"Point"}
}