{
  "type": "Feature",
  "properties": {
    "iso:country":"GB",
    "sg:address":"46 Station Road",
    "sg:city":"New Milton",
    "sg:classifiers":[
        {
            "category":"Cafe",
            "type":"Food & Drink"
        }
    ],
    "sg:postcode":"BH25 6JX",
    "sg:province":"Hampshire",
    "sg:tags":[
        "tea",
        "room"
    ],
    "wof:name":"Tastebuds",
    "wof:placetype":"venue"
},
  "geometry": {"coordinates":[-1.655857,50.754074],"type":"Point"}
}