{
  "type": "Feature",
  "properties": {
    "addr:full":"Manor Farm, Long Itchington Southam Warwickshire CV47 9PE",
    "addr:housenumber":"itchington",
    "addr:postcode":"cv47 9pe",
    "addr:street":"Manor",
    "iso:country":"GB",
    "sg:address":"Manor Farm, Long Itchington",
    "sg:city":"Southam",
    "sg:classifiers":[
        {
            "category":"Farming",
            "subcategory":"Livestock Farm",
            "type":"Manufacturing & Wholesale Goods"
        },
        {
            "category":"Farming",
            "subcategory":"Farm",
            "type":"Manufacturing & Wholesale Goods"
        }
    ],
    "sg:postcode":"CV47 9PE",
    "sg:province":"Warwickshire",
    "sg:tags":[
        "mixed",
        "crop",
        "others"
    ],
    "wof:name":"T C Williams & Sons",
    "wof:placetype":"venue"
},
  "geometry": {"coordinates":[-1.392678,52.284271],"type":"Point"}
}