{
  "type": "Feature",
  "properties": {
    "addr:full":"Long Close Chippenham Wiltshire SN15 3JY",
    "addr:postcode":"sn15 3jy",
    "addr:street":"Long Close",
    "iso:country":"GB",
    "sg:address":"Long Close",
    "sg:city":"Chippenham",
    "sg:classifiers":[
        {
            "category":"Community Center",
            "subcategory":"Youth",
            "type":"Public Place"
        }
    ],
    "sg:phone":"+44 1249 658579",
    "sg:postcode":"SN15 3JY",
    "sg:province":"Wiltshire",
    "sg:tags":[
        "organisation",
        "centre"
    ],
    "wof:name":"Chippenham Sea Cadet Unit",
    "wof:placetype":"venue"
},
  "geometry": {"coordinates":[-2.101528883,51.4521141052],"type":"Point"}
}