{
  "type": "Feature",
  "properties": {
    "iso:country":"GB",
    "sg:address":"37 Thisselt Rd",
    "sg:city":"Canvey Island",
    "sg:classifiers":[
        {
            "category":"Place Of Worship",
            "type":"Public Place"
        }
    ],
    "sg:phone":"+44 1268 692982",
    "sg:postcode":"SS8 9BP",
    "sg:province":"Essex",
    "wof:name":"All Island Mission",
    "wof:placetype":"venue"
},
  "geometry": {"coordinates":[0.590063,51.524063],"type":"Point"}
}