{
  "type": "Feature",
  "properties": {
    "iso:country":"GB",
    "sg:address":"1 Fleetham Close",
    "sg:city":"Chester-le-street",
    "sg:classifiers":[
        {
            "category":"Professional",
            "subcategory":"Engineering",
            "type":"Services"
        }
    ],
    "sg:postcode":"DH2 3SX",
    "sg:province":"Durham",
    "sg:tags":[
        "contractor",
        "electrical",
        "engineer"
    ],
    "wof:name":"Marshall Cooper",
    "wof:placetype":"venue"
},
  "geometry": {"coordinates":[-1.5995680094,54.8454246521],"type":"Point"}
}