{
  "type": "Feature",
  "properties": {
    "addr:full":"Century House, Norwich Rd Cromer Norfolk NR27 0HF",
    "addr:postcode":"nr27 0hf",
    "addr:street":"Norwich Rd",
    "iso:country":"GB",
    "sg:address":"Century House, Norwich Rd",
    "sg:city":"Cromer",
    "sg:classifiers":[
        {
            "category":"Professional",
            "subcategory":"Advertising",
            "type":"Services"
        }
    ],
    "sg:phone":"+44 1263 517084",
    "sg:postcode":"NR27 0HF",
    "sg:province":"Norfolk",
    "sg:tags":[
        "telemarketing"
    ],
    "wof:name":"Dvd Marketing Ltd",
    "wof:placetype":"venue"
},
  "geometry": {"coordinates":[1.3032200336,52.9293708801],"type":"Point"}
}