{
  "type": "Feature",
  "properties": {
    "addr:full":"30 Broomgate Lanark South Lanarkshire ML11 9EE",
    "addr:housenumber":"30",
    "addr:postcode":"ml11 9ee",
    "addr:street":"Broomgate Lanark",
    "iso:country":"GB",
    "sg:address":"30 Broomgate",
    "sg:city":"Lanark",
    "sg:classifiers":[
        {
            "category":"Professional",
            "subcategory":"Lawyer & Legal Services",
            "type":"Services"
        }
    ],
    "sg:phone":"+44 1555 662674",
    "sg:postcode":"ML11 9EE",
    "sg:province":"South Lanarkshire",
    "sg:tags":[
        "solicitor"
    ],
    "wof:name":"Criggie Eager & Baker",
    "wof:placetype":"venue"
},
  "geometry": {"coordinates":[-3.781371,55.673325],"type":"Point"}
}