{
  "type": "Feature",
  "properties": {
    "addr:full":"11 Knaresboro Avenue, Marton Blackpool Lancashire FY3 9QW",
    "addr:housenumber":"11",
    "addr:postcode":"fy3 9qw",
    "addr:street":"Knaresboro Avenue",
    "iso:country":"GB",
    "sg:address":"11 Knaresboro Avenue, Marton",
    "sg:city":"Blackpool",
    "sg:classifiers":[
        {
            "category":"Professional",
            "subcategory":"Detective & Security Services",
            "type":"Services"
        }
    ],
    "sg:phone":"+44 1253 769189",
    "sg:postcode":"FY3 9QW",
    "sg:province":"Lancashire",
    "sg:tags":[
        "equipment"
    ],
    "wof:name":"Chris Emm Distribution Services",
    "wof:placetype":"venue"
},
  "geometry": {"coordinates":[-3.021264,53.807739],"type":"Point"}
}