{
  "type": "Feature",
  "properties": {
    "addr:full":"3a Digbeth Walsall West Midlands WS1 1QZ",
    "addr:housenumber":"3a",
    "addr:postcode":"ws1 1qz",
    "addr:street":"Digbeth",
    "iso:country":"GB",
    "sg:address":"3a Digbeth",
    "sg:city":"Walsall",
    "sg:classifiers":[
        {
            "category":"Organizations",
            "subcategory":"Non-profit Organization",
            "type":"Services"
        }
    ],
    "sg:phone":"+44 1922 621496",
    "sg:postcode":"WS1 1QZ",
    "sg:province":"West Midlands",
    "sg:tags":[
        "organisation",
        "voluntary",
        "charity"
    ],
    "wof:name":"The Cancer Research Campaign",
    "wof:placetype":"venue"
},
  "geometry": {"coordinates":[-1.9812159538,52.583770752],"type":"Point"}
}