{
  "type": "Feature",
  "properties": {
    "iso:country":"GB",
    "sg:address":"1 Sophia Way",
    "sg:city":"Newton Abbot",
    "sg:classifiers":[
        {
            "category":"Bus Charters",
            "type":"Transportation"
        }
    ],
    "sg:postcode":"TQ12 1YW",
    "sg:province":"Devon",
    "sg:tags":[
        "hire",
        "coach"
    ],
    "wof:name":"Moor to Sea",
    "wof:placetype":"venue"
},
  "geometry": {"coordinates":[-3.621258,50.523643],"type":"Point"}
}