{
  "type": "Feature",
  "properties": {
    "addr:full":"Market Chambers, 1 Blackfriars Street Hereford Herefordshire HR4 9HS",
    "addr:housenumber":"1",
    "addr:postcode":"hr4 9hs",
    "addr:street":"Blackfriars Street",
    "iso:country":"GB",
    "sg:address":"Market Chambers, 1 Blackfriars Street",
    "sg:city":"Hereford",
    "sg:classifiers":[
        {
            "category":"Professional",
            "subcategory":"Accounting & Tax Preparation",
            "type":"Services"
        }
    ],
    "sg:phone":"+44 1432 277111",
    "sg:postcode":"HR4 9HS",
    "sg:province":"Herefordshire",
    "sg:tags":[
        "accountant"
    ],
    "wof:name":"Knipe Whiting & Heath & Associates",
    "wof:placetype":"venue"
},
  "geometry": {"coordinates":[-2.7317609787,52.0592041016],"type":"Point"}
}