{
  "type": "Feature",
  "properties": {
    "addr:full":"45 Colvilles Place, East Kilbride Glasgow South Lanarkshire G75 0PZ",
    "addr:housenumber":"45",
    "addr:postcode":"g75 0pz",
    "addr:street":"Colvilles Place East",
    "iso:country":"GB",
    "sg:address":"45 Colvilles Place, East Kilbride",
    "sg:city":"Glasgow",
    "sg:classifiers":[
        {
            "category":"Professional",
            "subcategory":"Detective & Security Services",
            "type":"Services"
        }
    ],
    "sg:phone":"+44 1355 268788",
    "sg:postcode":"G75 0PZ",
    "sg:province":"South Lanarkshire",
    "sg:tags":[
        "alarm",
        "burglar",
        "system"
    ],
    "wof:name":"Assure Alarms Ltd.",
    "wof:placetype":"venue"
},
  "geometry": {"coordinates":[-4.15487,55.751629],"type":"Point"}
}