{
  "type": "Feature",
  "properties": {
    "iso:country":"GB",
    "sg:address":"Unit 2, Haweswater Road, Penrith Industrial Estate",
    "sg:city":"Penrith",
    "sg:classifiers":[
        {
            "category":"Shopping",
            "subcategory":"Computers & Home Electronics",
            "type":"Retail Goods"
        }
    ],
    "sg:phone":"+44 1768 864829",
    "sg:postcode":"CA11 9EH",
    "sg:province":"Cumbria",
    "sg:tags":[
        "equipment",
        "audio-visual"
    ],
    "wof:name":"Cannan & Brown A V Services",
    "wof:placetype":"venue"
},
  "geometry": {"coordinates":[-2.7674949169,54.6601524353],"type":"Point"}
}