{
  "type": "Feature",
  "properties": {
    "addr:full":"61 Maid Marian Way Nottingham Nottinghamshire NG1 6AJ",
    "addr:housenumber":"61",
    "addr:postcode":"ng1 6aj",
    "addr:street":"Maid Marian Way",
    "iso:country":"GB",
    "sg:address":"61 Maid Marian Way",
    "sg:city":"Nottingham",
    "sg:classifiers":[
        {
            "category":"Professional",
            "subcategory":"Printing & Photocopies",
            "type":"Services"
        }
    ],
    "sg:phone":"+44 115 953 2600",
    "sg:postcode":"NG1 6AJ",
    "sg:province":"Nottinghamshire",
    "sg:tags":[
        "printer"
    ],
    "wof:name":"Prontaprint",
    "wof:placetype":"venue"
},
  "geometry": {"coordinates":[-1.152251,52.951759],"type":"Point"}
}