{
  "type": "Feature",
  "properties": {
    "addr:full":"Unit 9 Enterprise Centre, Dawsons Lane, Barwell Leicester Leicestershire LE9 8BE",
    "addr:housenumber":"unit 9",
    "addr:postcode":"le9 8be",
    "addr:street":"Enterprise Centre Dawsons Lane",
    "iso:country":"GB",
    "sg:address":"Unit 9 Enterprise Centre, Dawsons Lane, Barwell",
    "sg:city":"Leicester",
    "sg:classifiers":[
        {
            "category":"Building & Trades",
            "subcategory":"Construction",
            "type":"Services"
        }
    ],
    "sg:postcode":"LE9 8BE",
    "sg:province":"Leicestershire",
    "sg:tags":[
        "worker",
        "metal"
    ],
    "wof:name":"Alamac Metal Spinning",
    "wof:placetype":"venue"
},
  "geometry": {"coordinates":[-1.345964,52.567944],"type":"Point"}
}