{
  "type": "Feature",
  "properties": {
    "iso:country":"GB",
    "sg:address":"2 Watling St, Wilnecote",
    "sg:city":"Tamworth",
    "sg:classifiers":[
        {
            "category":"Manufacturing",
            "subcategory":"Building Materials",
            "type":"Manufacturing & Wholesale Goods"
        }
    ],
    "sg:phone":"+44 1827 262771",
    "sg:postcode":"B77 5BP",
    "sg:province":"Staffordshire",
    "sg:tags":[
        "merchant",
        "builder"
    ],
    "wof:name":"Econ Builders & Supplies",
    "wof:placetype":"venue"
},
  "geometry": {"coordinates":[-1.678974,52.610901],"type":"Point"}
}