{
  "type": "Feature",
  "properties": {
    "addr:full":"49 Maybole Road Ayr South Ayrshire KA7 4SF",
    "addr:housenumber":"49",
    "addr:postcode":"ka7 4sf",
    "addr:street":"Maybole Road",
    "iso:country":"GB",
    "sg:address":"49 Maybole Road",
    "sg:city":"Ayr",
    "sg:classifiers":[
        {
            "category":"Travel",
            "subcategory":"Hotels & Motels",
            "type":"Entertainment"
        }
    ],
    "sg:phone":"+44 1292 441986",
    "sg:postcode":"KA7 4SF",
    "sg:province":"South Ayrshire",
    "wof:name":"The Alloway Lodge",
    "wof:placetype":"venue"
},
  "geometry": {"coordinates":[-4.6188077927,55.4413719177],"type":"Point"}
}