{
  "type": "Feature",
  "properties": {
    "iso:country":"GB",
    "sg:address":"2 St Marks Crescent",
    "sg:city":"Maidenhead",
    "sg:classifiers":[
        {
            "category":"Retail",
            "subcategory":"Laundry & Dry Cleaning",
            "type":"Services"
        }
    ],
    "sg:phone":"+44 1753 543233",
    "sg:postcode":"SL6 5DB",
    "sg:province":"Berkshire",
    "sg:tags":[
        "cleaner",
        "launderette"
    ],
    "wof:name":"Launderama",
    "wof:placetype":"venue"
},
  "geometry": {"coordinates":[-0.746945,51.52515],"type":"Point"}
}