{
  "type": "Feature",
  "properties": {
    "iso:country":"GB",
    "sg:address":"47 Ashby Road",
    "sg:city":"Loughborough",
    "sg:classifiers":[
        {
            "category":"Shopping",
            "subcategory":"Bicycles & Sporting Goods",
            "type":"Retail Goods"
        }
    ],
    "sg:phone":"+44 1509 269663",
    "sg:postcode":"LE11 3AA",
    "sg:province":"Leicestershire",
    "sg:tags":[
        "cycle",
        "accessory"
    ],
    "wof:name":"Pedal Power",
    "wof:placetype":"venue"
},
  "geometry": {"coordinates":[-1.213475,52.772469],"type":"Point"}
}