{
  "type": "Feature",
  "properties": {
    "addr:full":"17 Park Terr Carmarthen Carmarthenshire SA31 3DG",
    "addr:housenumber":"17",
    "addr:postcode":"sa31 3dg",
    "addr:street":"Park Terr",
    "iso:country":"GB",
    "sg:address":"17 Park Terr",
    "sg:city":"Carmarthen",
    "sg:classifiers":[
        {
            "category":"Home & Garden",
            "subcategory":"Carpets & Floor Coverings",
            "type":"Retail Goods"
        }
    ],
    "sg:phone":"+44 1267 232763",
    "sg:postcode":"SA31 3DG",
    "sg:province":"Carmarthenshire",
    "sg:tags":[
        "carpets",
        "rug",
        "matting"
    ],
    "wof:name":"Merlin Carpets",
    "wof:placetype":"venue"
},
  "geometry": {"coordinates":[-4.3160481453,51.8561401367],"type":"Point"}
}