{
  "type": "Feature",
  "properties": {
    "addr:full":"Arton Manor Works, Barton Manor Trading Estate, St Philips Bristol City of Bristol BS2 0RL",
    "addr:postcode":"bs2 0rl",
    "addr:street":"Trading Estate St",
    "iso:country":"GB",
    "sg:address":"Arton Manor Works, Barton Manor Trading Estate, St Philips",
    "sg:city":"Bristol",
    "sg:classifiers":[
        {
            "category":"Autos & Motor Vehicles",
            "subcategory":"Auto Supplies",
            "type":"Retail Goods"
        }
    ],
    "sg:phone":"+44 117 955 2481",
    "sg:postcode":"BS2 0RL",
    "sg:province":"City of Bristol",
    "sg:tags":[
        "electric"
    ],
    "wof:name":"Derek White Ltd.",
    "wof:placetype":"venue"
},
  "geometry": {"coordinates":[-2.57591,51.454449],"type":"Point"}
}