{
  "type": "Feature",
  "properties": {
    "iso:country":"GB",
    "sg:address":"Unit 10 Martin Court, Blenheim Industrial Estate",
    "sg:city":"Nottingham",
    "sg:classifiers":[
        {
            "category":"Professional",
            "subcategory":"Detective & Security Services",
            "type":"Services"
        }
    ],
    "sg:postcode":"NG6 8US",
    "sg:province":"Nottinghamshire",
    "sg:tags":[
        "alarm",
        "burglar",
        "system"
    ],
    "wof:name":"Gardiner Technology",
    "wof:placetype":"venue"
},
  "geometry": {"coordinates":[-1.223278,53.009094],"type":"Point"}
}