{
  "type": "Feature",
  "properties": {
    "addr:full":"15 Market St Bolton Lancashire BL1 1BU",
    "addr:housenumber":"15",
    "addr:postcode":"bl1 1bu",
    "addr:street":"Market St",
    "iso:country":"GB",
    "sg:address":"15 Market St",
    "sg:city":"Bolton",
    "sg:classifiers":[
        {
            "category":"Sports & Exercise",
            "subcategory":"Sports Center",
            "type":"Entertainment"
        }
    ],
    "sg:postcode":"BL1 1BU",
    "sg:province":"Lancashire",
    "sg:tags":[
        "shop",
        "good"
    ],
    "wof:name":"Sports Stop Ltd",
    "wof:placetype":"venue"
},
  "geometry": {"coordinates":[-2.429504,53.579906],"type":"Point"}
}