{
  "type": "Feature",
  "properties": {
    "iso:country":"GB",
    "sg:address":"Ladywell Mills, Hall Lane",
    "sg:city":"Bradford",
    "sg:classifiers":[
        {
            "category":"Manufacturing",
            "subcategory":"Textiles",
            "type":"Manufacturing & Wholesale Goods"
        }
    ],
    "sg:phone":"+44 1274 735608",
    "sg:postcode":"BD4 7DF",
    "sg:province":"West Yorkshire",
    "sg:tags":[
        "knitwear"
    ],
    "wof:name":"Morton Fibres Ltd.",
    "wof:placetype":"venue"
},
  "geometry": {"coordinates":[-1.74422,53.785332],"type":"Point"}
}