{
  "type": "Feature",
  "properties": {
    "addr:full":"Bristol Bridge Ho, Redcliff St Bristol City of Bristol BS1 6QP",
    "addr:postcode":"bs1 6qp",
    "addr:street":"Bristol Bridge;Redcliff St",
    "iso:country":"GB",
    "sg:address":"Bristol Bridge Ho, Redcliff St",
    "sg:city":"Bristol",
    "sg:classifiers":[
        {
            "category":"Professional",
            "subcategory":"Employment Agencies",
            "type":"Services"
        }
    ],
    "sg:phone":"+44 117 927 6236",
    "sg:postcode":"BS1 6QP",
    "sg:province":"City of Bristol",
    "sg:tags":[
        "consultant"
    ],
    "wof:name":"Computer People Ltd",
    "wof:placetype":"venue"
},
  "geometry": {"coordinates":[-2.5914289951,51.453666687],"type":"Point"}
}