{
  "type": "Feature",
  "properties": {
    "addr:full":"West Winds Farm, Woodham Aylesbury Buckinghamshire HP18 0QH",
    "addr:housenumber":"woodham",
    "addr:postcode":"hp18 0qh",
    "addr:street":"West;Aylesbury",
    "iso:country":"GB",
    "sg:address":"West Winds Farm, Woodham",
    "sg:city":"Aylesbury",
    "sg:classifiers":[
        {
            "category":"Manufacturing",
            "subcategory":"Building Materials",
            "type":"Manufacturing & Wholesale Goods"
        }
    ],
    "sg:postcode":"HP18 0QH",
    "sg:province":"Buckinghamshire",
    "sg:tags":[
        "gate",
        "mnfrs"
    ],
    "wof:name":"Little Heath Gates",
    "wof:placetype":"venue"
},
  "geometry": {"coordinates":[-0.986228,51.859379],"type":"Point"}
}