{
  "type": "Feature",
  "properties": {
    "iso:country":"GB",
    "sg:address":"Greenhedges, Marshalls Heath La",
    "sg:city":"St Albans",
    "sg:classifiers":[
        {
            "category":"Building & Trades",
            "subcategory":"Landscaping Services",
            "type":"Services"
        }
    ],
    "sg:phone":"+44 1582 833162",
    "sg:postcode":"AL4 8HS",
    "sg:province":"Hertfordshire",
    "sg:tags":[
        "landscape",
        "contractor"
    ],
    "wof:name":"Industrial Landscaping",
    "wof:placetype":"venue"
},
  "geometry": {"coordinates":[-0.316222012,51.8216667175],"type":"Point"}
}