{
  "type": "Feature",
  "properties": {
    "addr:full":"Baytree Ho,stevens La, Lympsham Weston-super-mare Somerset BS24 0BY",
    "addr:postcode":"bs24 0by",
    "addr:street":"Stevens;Lympsham",
    "iso:country":"GB",
    "sg:address":"Baytree Ho,stevens La, Lympsham",
    "sg:city":"Weston-super-mare",
    "sg:classifiers":[
        {
            "category":"Shopping",
            "subcategory":"Antiques",
            "type":"Retail Goods"
        }
    ],
    "sg:postcode":"BS24 0BY",
    "sg:province":"Somerset",
    "wof:name":"Baytree House Antiques",
    "wof:placetype":"venue"
},
  "geometry": {"coordinates":[-2.952351,51.284443],"type":"Point"}
}