{
  "type": "Feature",
  "properties": {
    "addr:full":"190 Muswell Hill Road London Greater London N10 3NG",
    "addr:housenumber":"190",
    "addr:postcode":"n10 3ng",
    "addr:street":"Muswell Hill Road",
    "iso:country":"GB",
    "sg:address":"190 Muswell Hill Road",
    "sg:city":"London",
    "sg:classifiers":[
        {
            "category":"Travel",
            "subcategory":"Hotels & Motels",
            "type":"Entertainment"
        }
    ],
    "sg:phone":"+44 20 8444 7406",
    "sg:postcode":"N10 3NG",
    "sg:province":"Greater London",
    "sg:tags":[
        "house",
        "guest"
    ],
    "wof:name":"Elenion Guest House",
    "wof:placetype":"venue"
},
  "geometry": {"coordinates":[-0.146533,51.588253],"type":"Point"}
}