{
  "type": "Feature",
  "properties": {
    "iso:country":"GB",
    "sg:address":"1 Progress Av",
    "sg:city":"Blackburn",
    "sg:classifiers":[
        {
            "category":"Sports & Exercise",
            "subcategory":"Race Track",
            "type":"Entertainment"
        }
    ],
    "sg:phone":"+44 1282 850124",
    "sg:postcode":"BB1 5NY",
    "sg:province":"Lancashire",
    "sg:tags":[
        "motor"
    ],
    "wof:name":"Autotek",
    "wof:placetype":"venue"
},
  "geometry": {"coordinates":[-2.4663040638,53.7574310303],"type":"Point"}
}