{
  "type": "Feature",
  "properties": {
    "addr:full":"4 Wellbeck, Woodstone Industrial Estate, Woodstone Peterborough Cambridgeshire PE2 7WH",
    "addr:housenumber":"4",
    "addr:postcode":"pe2 7wh",
    "addr:street":"Wellbeck Woodstone Industrial Estate",
    "iso:country":"GB",
    "sg:address":"4 Wellbeck, Woodstone Industrial Estate, Woodstone",
    "sg:city":"Peterborough",
    "sg:classifiers":[
        {
            "category":"Home & Garden",
            "subcategory":"Home Furnishings",
            "type":"Retail Goods"
        }
    ],
    "sg:phone":"+44 1604 588000",
    "sg:postcode":"PE2 7WH",
    "sg:province":"Cambridgeshire",
    "sg:tags":[
        "pipe",
        "fitting"
    ],
    "wof:name":"Barflo-Lca",
    "wof:placetype":"venue"
},
  "geometry": {"coordinates":[-0.2630200088,52.558921814],"type":"Point"}
}