{
  "type": "Feature",
  "properties": {
    "addr:full":"58 Station Road, Rolleston On Dove Burton-on-trent Derbyshire DE13 9AA",
    "addr:housenumber":"58",
    "addr:postcode":"de13 9aa",
    "addr:street":"Station Road",
    "iso:country":"GB",
    "sg:address":"58 Station Road, Rolleston On Dove",
    "sg:city":"Burton-on-trent",
    "sg:classifiers":[
        {
            "category":"Building & Trades",
            "subcategory":"Landscaping Services",
            "type":"Services"
        }
    ],
    "sg:postcode":"DE13 9AA",
    "sg:province":"Derbyshire",
    "sg:tags":[
        "gardening"
    ],
    "wof:name":"David Raymond & John Alton",
    "wof:placetype":"venue"
},
  "geometry": {"coordinates":[-1.642605,52.846645],"type":"Point"}
}