{
  "type": "Feature",
  "properties": {
    "addr:full":"Unit 16 Raleigh Hall Industrial Estate, Eccleshall Stafford Staffordshire ST21 6JL",
    "addr:housenumber":"unit 16",
    "addr:postcode":"st21 6jl",
    "addr:street":"Raleigh Hall Industrial Estate",
    "iso:country":"GB",
    "sg:address":"Unit 16 Raleigh Hall Industrial Estate, Eccleshall",
    "sg:city":"Stafford",
    "sg:classifiers":[
        {
            "category":"Manufacturing",
            "subcategory":"Rubber & Plastics",
            "type":"Manufacturing & Wholesale Goods"
        }
    ],
    "sg:phone":"+44 1785 851842",
    "sg:postcode":"ST21 6JL",
    "sg:province":"Staffordshire",
    "sg:tags":[
        "product"
    ],
    "wof:name":"Castle Plastic",
    "wof:placetype":"venue"
},
  "geometry": {"coordinates":[-2.246274,52.873497],"type":"Point"}
}