{
  "type": "Feature",
  "properties": {
    "iso:country":"GB",
    "sg:address":"296 Carey Gardens, Battersea",
    "sg:city":"London",
    "sg:classifiers":[
        {
            "category":"Organizations",
            "subcategory":"Community Association",
            "type":"Services"
        }
    ],
    "sg:phone":"+44 20 7498 3664",
    "sg:postcode":"SW8 4HW",
    "sg:province":"Greater London",
    "sg:tags":[
        "co-operatives",
        "society",
        "housing",
        "trust"
    ],
    "wof:name":"Carey Gardens Co-Operative Ltd",
    "wof:placetype":"venue"
},
  "geometry": {"coordinates":[-0.1360549927,51.4741630554],"type":"Point"}
}