{
  "type": "Feature",
  "properties": {
    "addr:full":"2 Coleshill Terr Llanelli Carmarthenshire SA15 3DB",
    "addr:housenumber":"2",
    "addr:postcode":"sa15 3db",
    "addr:street":"Terr",
    "iso:country":"GB",
    "sg:address":"2 Coleshill Terr",
    "sg:city":"Llanelli",
    "sg:classifiers":[
        {
            "category":"Professional",
            "subcategory":"Computer Services",
            "type":"Services"
        }
    ],
    "sg:phone":"+44 1554 749419",
    "sg:postcode":"SA15 3DB",
    "sg:province":"Carmarthenshire",
    "sg:tags":[
        "information"
    ],
    "wof:name":"Llanelli Dinefwr Community Health Council",
    "wof:placetype":"venue"
},
  "geometry": {"coordinates":[-4.1638998985,51.6822662354],"type":"Point"}
}