{
  "type": "Feature",
  "properties": {
    "addr:full":"4 Elizabeth Cottages, Kew Richmond Richmond Greater London TW9 3NJ",
    "addr:housenumber":"4",
    "addr:postcode":"tw9 3nj",
    "addr:street":"Elizabeth Cottages",
    "iso:country":"GB",
    "sg:address":"4 Elizabeth Cottages, Kew Richmond",
    "sg:city":"Richmond",
    "sg:classifiers":[
        {
            "category":"Professional",
            "type":"Services"
        }
    ],
    "sg:phone":"+44 20 8332 6777",
    "sg:postcode":"TW9 3NJ",
    "sg:province":"Greater London",
    "sg:tags":[
        "interior",
        "furnishers",
        "designer"
    ],
    "wof:name":"Humphrey Interiors",
    "wof:placetype":"venue"
},
  "geometry": {"coordinates":[-0.2873010039,51.4762153625],"type":"Point"}
}