{
  "type": "Feature",
  "properties": {
    "addr:full":"Station Road, St Helen Auckland Bishop Auckland Durham DL14 9EX",
    "addr:postcode":"dl14 9ex",
    "addr:street":"Station Road St;Auckland",
    "iso:country":"GB",
    "sg:address":"Station Road, St Helen Auckland",
    "sg:city":"Bishop Auckland",
    "sg:classifiers":[
        {
            "category":"Bars & Pubs",
            "type":"Food & Drink"
        }
    ],
    "sg:postcode":"DL14 9EX",
    "sg:province":"Durham",
    "sg:tags":[
        "pubs",
        "inn"
    ],
    "wof:name":"The Arthur Daley",
    "wof:placetype":"venue"
},
  "geometry": {"coordinates":[-1.717685,54.634068],"type":"Point"}
}