{
  "type": "Feature",
  "properties": {
    "addr:full":"20 Bridge Street St Helens Merseyside WA10 1NN",
    "addr:housenumber":"20",
    "addr:postcode":"wa10 1nn",
    "addr:street":"Bridge Street",
    "iso:country":"GB",
    "sg:address":"20 Bridge Street",
    "sg:city":"St Helens",
    "sg:classifiers":[
        {
            "category":"Shopping",
            "subcategory":"Clothing, Apparel, & Fashions",
            "type":"Retail Goods"
        }
    ],
    "sg:phone":"+44 1744 739500",
    "sg:postcode":"WA10 1NN",
    "sg:province":"Merseyside",
    "sg:tags":[
        "menswear"
    ],
    "wof:name":"Greenwoods (Mens Wear)",
    "wof:placetype":"venue"
},
  "geometry": {"coordinates":[-2.7383339405,53.452091217],"type":"Point"}
}