{
  "type": "Feature",
  "properties": {
    "iso:country":"GB",
    "sg:address":"5-7 Elphinstone Road",
    "sg:city":"Tranent",
    "sg:classifiers":[
        {
            "category":"Retail",
            "subcategory":"Auto Repair",
            "type":"Services"
        }
    ],
    "sg:phone":"+44 1875 612490",
    "sg:postcode":"EH33 2HR",
    "sg:province":"East Lothian",
    "sg:tags":[
        "modification",
        "garage"
    ],
    "wof:name":"C & G Wright",
    "wof:placetype":"venue"
},
  "geometry": {"coordinates":[-2.961264,55.943363],"type":"Point"}
}