{
  "type": "Feature",
  "properties": {
    "iso:country":"GB",
    "sg:address":"160 Lytham Road",
    "sg:city":"Blackpool",
    "sg:classifiers":[
        {
            "category":"Food & Beverages",
            "subcategory":"Meat & Fish",
            "type":"Retail Goods"
        }
    ],
    "sg:postcode":"FY1 6DJ",
    "sg:province":"Lancashire",
    "sg:tags":[
        "chip"
    ],
    "wof:name":"Nite Bite",
    "wof:placetype":"venue"
},
  "geometry": {"coordinates":[-3.0515210629,53.8031768799],"type":"Point"}
}