{
  "type": "Feature",
  "properties": {
    "iso:country":"GB",
    "sg:address":"19 Middleflat",
    "sg:city":"Cupar",
    "sg:classifiers":[
        {
            "category":"Health Services",
            "subcategory":"Podiatrist",
            "type":"Services"
        }
    ],
    "sg:phone":"+44 1337 828003",
    "sg:postcode":"KY14 7DG",
    "sg:province":"Fife",
    "sg:tags":[
        "podiatrists",
        "chiropodist"
    ],
    "wof:name":"Botanic Chiropody Practitioners",
    "wof:placetype":"venue"
},
  "geometry": {"coordinates":[-3.226416,56.293991],"type":"Point"}
}