{
  "type": "Feature",
  "properties": {
    "iso:country":"GB",
    "sg:address":"Unit 22-23 Ptarmigan Place, Attleborough Fields Industrial Estate",
    "sg:city":"Nuneaton",
    "sg:classifiers":[
        {
            "category":"Professional",
            "subcategory":"Engineering",
            "type":"Services"
        }
    ],
    "sg:phone":"+44 24 7634 4154",
    "sg:postcode":"CV11 6RX",
    "sg:province":"Leicestershire",
    "wof:name":"Able Equipment (Tools) Ltd.",
    "wof:placetype":"venue"
},
  "geometry": {"coordinates":[-1.447715044,52.5196228027],"type":"Point"}
}