{
  "type": "Feature",
  "properties": {
    "addr:full":"Wonder Street, Ings Road Wakefield West Yorkshire WF1 1NR",
    "addr:postcode":"wf1 1nr",
    "addr:street":"Wonder Street Ings Road",
    "iso:country":"GB",
    "sg:address":"Wonder Street, Ings Road",
    "sg:city":"Wakefield",
    "sg:classifiers":[
        {
            "category":"Home & Garden",
            "subcategory":"Carpets & Floor Coverings",
            "type":"Retail Goods"
        },
        {
            "category":"Home & Garden",
            "subcategory":"Furniture",
            "type":"Retail Goods"
        }
    ],
    "sg:phone":"+44 1924 291211",
    "sg:postcode":"WF1 1NR",
    "sg:province":"West Yorkshire",
    "sg:tags":[
        "carpets",
        "rug",
        "matting",
        "outlet"
    ],
    "sg:website":"http://www.boothscarpets.co.uk",
    "wof:name":"Booco Ltd.",
    "wof:placetype":"venue"
},
  "geometry": {"coordinates":[-1.494174,53.678413],"type":"Point"}
}