{
  "type": "Feature",
  "properties": {
    "iso:country":"GB",
    "sg:address":"14 Addison Close",
    "sg:city":"Wednesbury",
    "sg:classifiers":[
        {
            "category":"Shopping",
            "subcategory":"Party Supplies",
            "type":"Retail Goods"
        }
    ],
    "sg:phone":"+44 121 556 8492",
    "sg:postcode":"WS10 0LP",
    "sg:province":"West Midlands",
    "sg:tags":[
        "inflatables",
        "bouncy",
        "castle"
    ],
    "wof:name":"Bounce About",
    "wof:placetype":"venue"
},
  "geometry": {"coordinates":[-1.980491,52.551521],"type":"Point"}
}