{
  "type": "Feature",
  "properties": {
    "iso:country":"GB",
    "sg:address":"45 Park Avenue",
    "sg:city":"Gillingham",
    "sg:classifiers":[
        {
            "category":"Health Services",
            "subcategory":"Nursing And Care Facility",
            "type":"Services"
        }
    ],
    "sg:phone":"+44 1634 850411",
    "sg:postcode":"ME7 4AH",
    "sg:province":"Kent",
    "sg:tags":[
        "home"
    ],
    "wof:name":"BERENGROVE LTD",
    "wof:placetype":"venue"
},
  "geometry": {"coordinates":[0.5557150245,51.3753623962],"type":"Point"}
}