{
  "type": "Feature",
  "properties": {
    "addr:full":"Hernas Farm, Landfill Site Penryn Cornwall TR10 9DU",
    "addr:postcode":"tr10 9du",
    "iso:country":"GB",
    "sg:address":"Hernas Farm, Landfill Site",
    "sg:city":"Penryn",
    "sg:classifiers":[
        {
            "category":"Wholesale",
            "subcategory":"Construction Materials",
            "type":"Manufacturing & Wholesale Goods"
        }
    ],
    "sg:phone":"+44 1209 861231",
    "sg:postcode":"TR10 9DU",
    "sg:province":"Cornwall",
    "sg:tags":[
        "merchant",
        "stone"
    ],
    "wof:name":"Winn L.I. & Son",
    "wof:placetype":"venue"
},
  "geometry": {"coordinates":[-5.1048088074,50.1685752869],"type":"Point"}
}