{
  "type": "Feature",
  "properties": {
    "addr:full":"10 Cedar Gro, Orrell Wigan Lancashire WN5 8NH",
    "addr:housenumber":"10",
    "addr:postcode":"wn5 8nh",
    "addr:street":"Cedar Gro Orrell",
    "iso:country":"GB",
    "sg:address":"10 Cedar Gro, Orrell",
    "sg:city":"Wigan",
    "sg:classifiers":[
        {
            "category":"Building & Trades",
            "subcategory":"Construction",
            "type":"Services"
        }
    ],
    "sg:phone":"+44 1942 214602",
    "sg:postcode":"WN5 8NH",
    "sg:province":"Lancashire",
    "sg:tags":[
        "roofing"
    ],
    "wof:name":"Arthur Wall",
    "wof:placetype":"venue"
},
  "geometry": {"coordinates":[-2.713779,53.531895],"type":"Point"}
}