{
  "type": "Feature",
  "properties": {
    "addr:full":"Emergencies, 15 Leyton Rd Harpenden Hertfordshire AL5 2HX",
    "addr:housenumber":"15",
    "addr:postcode":"al5 2hx",
    "addr:street":"Emergencies;Leyton Rd",
    "iso:country":"GB",
    "sg:address":"Emergencies, 15 Leyton Rd",
    "sg:city":"Harpenden",
    "sg:classifiers":[
        {
            "category":"Health Services",
            "subcategory":"Doctor",
            "type":"Services"
        }
    ],
    "sg:phone":"+44 1582 712021",
    "sg:postcode":"AL5 2HX",
    "sg:province":"Hertfordshire",
    "sg:tags":[
        "practitioners"
    ],
    "wof:name":"Sanderson, G",
    "wof:placetype":"venue"
},
  "geometry": {"coordinates":[-0.3565590084,51.8162155151],"type":"Point"}
}