{
  "type": "Feature",
  "properties": {
    "addr:full":"73 Swaisland Drive, Crayford Dartford Kent DA1 4HY",
    "addr:housenumber":"73",
    "addr:postcode":"da1 4hy",
    "addr:street":"Swaisland Drive Crayford",
    "iso:country":"GB",
    "sg:address":"73 Swaisland Drive, Crayford",
    "sg:city":"Dartford",
    "sg:classifiers":[
        {
            "category":"Wholesale",
            "subcategory":"Machinery & Supplies",
            "type":"Manufacturing & Wholesale Goods"
        }
    ],
    "sg:phone":"+44 1322 559694",
    "sg:postcode":"DA1 4HY",
    "sg:province":"Kent",
    "sg:tags":[
        "supplier",
        "industrial",
        "commercial",
        "manufacturer"
    ],
    "wof:name":"Veropak Ltd.",
    "wof:placetype":"venue"
},
  "geometry": {"coordinates":[0.1809200048,51.452041626],"type":"Point"}
}