{
  "type": "Feature",
  "properties": {
    "iso:country":"GB",
    "sg:address":"34 Bedford Row",
    "sg:city":"Bloomsbury",
    "sg:classifiers":[
        {
            "category":"Professional",
            "subcategory":"Lawyer & Legal Services",
            "type":"Services"
        }
    ],
    "sg:phone":"+44 20 7242 5974",
    "sg:postcode":"WC1R 4JH",
    "sg:province":"Greater London",
    "sg:tags":[
        "patent",
        "agent"
    ],
    "wof:name":"J Miller & Co",
    "wof:placetype":"venue"
},
  "geometry": {"coordinates":[-0.116214,51.51973],"type":"Point"}
}