{
  "type": "Feature",
  "properties": {
    "addr:full":"264 Lee High Road London Greater London SE13 5PL",
    "addr:housenumber":"264",
    "addr:postcode":"se13 5pl",
    "addr:street":"Lee High Road",
    "iso:country":"GB",
    "sg:address":"264 Lee High Road",
    "sg:city":"London",
    "sg:classifiers":[
        {
            "category":"Shopping",
            "subcategory":"Crafts & Fabrics",
            "type":"Retail Goods"
        }
    ],
    "sg:phone":"+44 20 8852 4183",
    "sg:postcode":"SE13 5PL",
    "sg:province":"Greater London",
    "sg:tags":[
        "material",
        "art"
    ],
    "wof:name":"Morse Art",
    "wof:placetype":"venue"
},
  "geometry": {"coordinates":[0.001061,51.458443],"type":"Point"}
}