{
  "type": "Feature",
  "properties": {
    "addr:full":"54 Main Street, Cross Hill Lochgelly Fife KY5 8AT",
    "addr:housenumber":"54",
    "addr:postcode":"ky5 8at",
    "addr:street":"Main Street",
    "iso:country":"GB",
    "sg:address":"54 Main Street, Cross Hill",
    "sg:city":"Lochgelly",
    "sg:classifiers":[
        {
            "category":"Personal",
            "subcategory":"Beauty Salon",
            "type":"Services"
        },
        {
            "category":"Personal",
            "subcategory":"Barber",
            "type":"Services"
        }
    ],
    "sg:phone":"+44 1592 860340",
    "sg:postcode":"KY5 8AT",
    "sg:province":"Fife",
    "sg:tags":[
        "unisex",
        "hairdresser"
    ],
    "wof:name":"Kutz Hairstylists",
    "wof:placetype":"venue"
},
  "geometry": {"coordinates":[-3.323917,56.150448],"type":"Point"}
}