{
  "type": "Feature",
  "properties": {
    "iso:country":"GB",
    "sg:address":"113 Park Crescent",
    "sg:city":"Barry",
    "sg:classifiers":[
        {
            "category":"Government",
            "subcategory":"Post Office",
            "type":"Public Place"
        }
    ],
    "sg:phone":"+44 1446 734545",
    "sg:postcode":"CF62 6HE",
    "sg:province":"The Vale of Glamorgan",
    "wof:name":"Vale Street Post Office",
    "wof:placetype":"venue"
},
  "geometry": {"coordinates":[-3.2884700298,51.3994064331],"type":"Point"}
}