{
  "type": "Feature",
  "properties": {
    "iso:country":"GB",
    "sg:address":"8 & 9 Pentland Ct, Saltire Centre",
    "sg:city":"Glenrothes",
    "sg:classifiers":[
        {
            "category":"Education",
            "subcategory":"Special Training",
            "type":"Public Place"
        }
    ],
    "sg:phone":"+44 1592 630802",
    "sg:postcode":"KY6 2DA",
    "sg:province":"Fife",
    "sg:tags":[
        "product",
        "centre"
    ],
    "wof:name":"Centre For Industrial Studies",
    "wof:placetype":"venue"
},
  "geometry": {"coordinates":[-3.1845610142,56.1893692017],"type":"Point"}
}