{
  "type": "Feature",
  "properties": {
    "iso:country":"GB",
    "sg:address":"6 Fairfield Drive, Frimley",
    "sg:city":"Camberley",
    "sg:classifiers":[
        {
            "category":"Social Services",
            "subcategory":"Child Care",
            "type":"Services"
        }
    ],
    "sg:phone":"+44 1276 683147",
    "sg:postcode":"GU16 8RL",
    "sg:province":"Hampshire",
    "sg:tags":[
        "agency",
        "nanny"
    ],
    "wof:name":"Childrens Professional Services",
    "wof:placetype":"venue"
},
  "geometry": {"coordinates":[-0.7314100266,51.325302124],"type":"Point"}
}