{
  "type": "Feature",
  "properties": {
    "addr:full":"59 Castle Street Trowbridge Wiltshire BA14 8AU",
    "addr:housenumber":"59",
    "addr:postcode":"ba14 8au",
    "addr:street":"Castle Street",
    "iso:country":"GB",
    "sg:address":"59 Castle Street",
    "sg:city":"Trowbridge",
    "sg:classifiers":[
        {
            "category":"Fast Food",
            "type":"Food & Drink"
        }
    ],
    "sg:phone":"+44 1225 761383",
    "sg:postcode":"BA14 8AU",
    "sg:province":"Wiltshire",
    "sg:tags":[
        "away",
        "take"
    ],
    "wof:name":"Mayflower",
    "wof:placetype":"venue"
},
  "geometry": {"coordinates":[-2.207752943,51.3197174072],"type":"Point"}
}