{
  "type": "Feature",
  "properties": {
    "iso:country":"GB",
    "sg:address":"34-36 Union Street, Rosehearty",
    "sg:city":"Fraserburgh",
    "sg:classifiers":[
        {
            "category":"Professional",
            "subcategory":"Engineering",
            "type":"Services"
        }
    ],
    "sg:phone":"+44 1346 571225",
    "sg:postcode":"AB43 7JQ",
    "sg:province":"Aberdeenshire",
    "sg:tags":[
        "consulting",
        "engineer"
    ],
    "wof:name":"Petpro Services Ltd.",
    "wof:placetype":"venue"
},
  "geometry": {"coordinates":[-2.1138000488,57.6974563599],"type":"Point"}
}