{
  "type": "Feature",
  "properties": {
    "iso:country":"GB",
    "sg:address":"71 Lowther St",
    "sg:city":"Whitehaven",
    "sg:classifiers":[
        {
            "category":"Banks & Credit Unions",
            "subcategory":"Bank",
            "type":"Services"
        }
    ],
    "sg:phone":"+44 1946 67361",
    "sg:postcode":"CA28 7AH",
    "sg:province":"Cumbria",
    "wof:name":"NatWest",
    "wof:placetype":"venue"
},
  "geometry": {"coordinates":[-3.586541,54.547455],"type":"Point"}
}