{
  "type": "Feature",
  "properties": {
    "addr:full":"Unit 7 King William Enterprise, Park King William Street Salford Greater Manchester M5 2UP",
    "addr:housenumber":"unit 7 king",
    "addr:postcode":"m5 2up",
    "addr:street":"Enterprise Park King William Street",
    "iso:country":"GB",
    "sg:address":"Unit 7 King William Enterprise, Park King William Street",
    "sg:city":"Salford",
    "sg:classifiers":[
        {
            "category":"Manufacturing",
            "subcategory":"Signs",
            "type":"Manufacturing & Wholesale Goods"
        }
    ],
    "sg:phone":"+44 161 876 4898",
    "sg:postcode":"M5 2UP",
    "sg:province":"Greater Manchester",
    "sg:tags":[
        "writer"
    ],
    "wof:name":"J W Bollam & Co",
    "wof:placetype":"venue"
},
  "geometry": {"coordinates":[-2.2843,53.489731],"type":"Point"}
}