{
  "type": "Feature",
  "properties": {
    "addr:full":"8 Seraphis Ct, Holbeck Hill Scarborough North Yorkshire YO11 3BL",
    "addr:housenumber":"8",
    "addr:postcode":"yo11 3bl",
    "addr:street":"Seraphis Ct",
    "iso:country":"GB",
    "sg:address":"8 Seraphis Ct, Holbeck Hill",
    "sg:city":"Scarborough",
    "sg:classifiers":[
        {
            "category":"Recreation",
            "subcategory":"Gun Range",
            "type":"Entertainment"
        }
    ],
    "sg:phone":"+44 1723 503100",
    "sg:postcode":"YO11 3BL",
    "sg:province":"North Yorkshire",
    "sg:tags":[
        "operator",
        "tour"
    ],
    "wof:name":"Horncastle Leisure",
    "wof:placetype":"venue"
},
  "geometry": {"coordinates":[-0.39183,54.265331],"type":"Point"}
}