{
  "type": "Feature",
  "properties": {
    "iso:country":"GB",
    "sg:address":"67 Airthrie Road, Goodmayes",
    "sg:city":"Ilford",
    "sg:classifiers":[
        {
            "category":"Building & Trades",
            "subcategory":"Plumbing",
            "type":"Services"
        }
    ],
    "sg:phone":"+44 20 8270 2597",
    "sg:postcode":"IG3 9QT",
    "sg:province":"Essex",
    "sg:tags":[
        "central",
        "heating"
    ],
    "wof:name":"Heyworth Heating Services",
    "wof:placetype":"venue"
},
  "geometry": {"coordinates":[0.114639,51.560577],"type":"Point"}
}