{
  "type": "Feature",
  "properties": {
    "addr:full":"Winsley Bradford-on-avon Wiltshire BA15 2LE",
    "addr:postcode":"ba15 2le",
    "iso:country":"GB",
    "sg:address":"Winsley",
    "sg:city":"Bradford-on-avon",
    "sg:classifiers":[
        {
            "category":"Health Services",
            "subcategory":"Hospice",
            "type":"Services"
        }
    ],
    "sg:phone":"+44 1225 722988",
    "sg:postcode":"BA15 2LE",
    "sg:province":"Wiltshire",
    "wof:name":"The Dorothy House Foundation Ltd.",
    "wof:placetype":"venue"
},
  "geometry": {"coordinates":[-2.2767028809,51.34948349],"type":"Point"}
}