{
  "type": "Feature",
  "properties": {
    "addr:full":"Osborns Ct, High St South Olney Buckinghamshire MK46 4AA",
    "addr:postcode":"mk46 4aa",
    "addr:street":"Osborns Ct High St",
    "iso:country":"GB",
    "sg:address":"Osborns Ct, High St South",
    "sg:city":"Olney",
    "sg:classifiers":[
        {
            "category":"Home & Garden",
            "subcategory":"Home Furnishings",
            "type":"Retail Goods"
        }
    ],
    "sg:postcode":"MK46 4AA",
    "sg:province":"Buckinghamshire",
    "sg:tags":[
        "blind",
        "curtain",
        "fitting"
    ],
    "wof:name":"Curtain Call Agency",
    "wof:placetype":"venue"
},
  "geometry": {"coordinates":[-0.7016739845,52.15209198],"type":"Point"}
}