{
  "type": "Feature",
  "properties": {
    "addr:full":"Boreley Farm House, Boreley Lane, Ombersley Droitwich Worcestershire WR9 0HU",
    "addr:postcode":"wr9 0hu",
    "addr:street":"Boreley Lane;Droitwich",
    "iso:country":"GB",
    "sg:address":"Boreley Farm House, Boreley Lane, Ombersley",
    "sg:city":"Droitwich",
    "sg:classifiers":[
        {
            "category":"Professional",
            "subcategory":"Art Services",
            "type":"Services"
        }
    ],
    "sg:phone":"+44 1905 621622",
    "sg:postcode":"WR9 0HU",
    "sg:province":"Worcestershire",
    "sg:tags":[
        "photographer"
    ],
    "wof:name":"James Hepburn",
    "wof:placetype":"venue"
},
  "geometry": {"coordinates":[-2.255427,52.295868],"type":"Point"}
}