{
  "type": "Feature",
  "properties": {
    "addr:full":"Unit 1, Wem Business Park, New Street Shrewsbury Shropshire SY4 5JX",
    "addr:housenumber":"unit 1",
    "addr:postcode":"sy4 5jx",
    "addr:street":"Wem Business Park New Street",
    "iso:country":"GB",
    "sg:address":"Unit 1, Wem Business Park, New Street",
    "sg:city":"Shrewsbury",
    "sg:classifiers":[
        {
            "category":"Shopping",
            "subcategory":"Gifts & Souvenirs",
            "type":"Retail Goods"
        }
    ],
    "sg:phone":"+44 1939 234466",
    "sg:postcode":"SY4 5JX",
    "sg:province":"Shropshire",
    "sg:tags":[
        "greeting",
        "card"
    ],
    "wof:name":"Halcyon Cards",
    "wof:placetype":"venue"
},
  "geometry": {"coordinates":[-2.72463,52.85638],"type":"Point"}
}