{
  "type": "Feature",
  "properties": {
    "iso:country":"GB",
    "sg:address":"Unit 36 South Gyle Bdwy",
    "sg:city":"Edinburgh",
    "sg:classifiers":[
        {
            "category":"Sports & Exercise",
            "subcategory":"Sports Center",
            "type":"Entertainment"
        }
    ],
    "sg:phone":"+44 131 317 1473",
    "sg:postcode":"EH12 9JR",
    "sg:province":"City of Edinburgh",
    "sg:tags":[
        "shop",
        "good"
    ],
    "wof:name":"Sports Shop (Fife) Ltd (The)",
    "wof:placetype":"venue"
},
  "geometry": {"coordinates":[-3.296475,55.934189],"type":"Point"}
}