{
  "type": "Feature",
  "properties": {
    "iso:country":"GB",
    "sg:address":"Norland, Cefn Bychan Road, Pantymwyn",
    "sg:city":"Mold",
    "sg:classifiers":[
        {
            "category":"Building & Trades",
            "subcategory":"Construction",
            "type":"Services"
        }
    ],
    "sg:phone":"+44 1352 740605",
    "sg:postcode":"CH7 5EW",
    "sg:province":"Denbighshire",
    "sg:tags":[
        "glazier"
    ],
    "wof:name":"Chester Glass & Co",
    "wof:placetype":"venue"
},
  "geometry": {"coordinates":[-3.2091488838,53.1734886169],"type":"Point"}
}