{
  "type": "Feature",
  "properties": {
    "addr:full":"Durie Gardens Cottage Leven Fife KY8 5RF",
    "addr:postcode":"ky8 5rf",
    "addr:street":"Durie;Leven",
    "iso:country":"GB",
    "sg:address":"Durie Gardens Cottage",
    "sg:city":"Leven",
    "sg:classifiers":[
        {
            "category":"Professional",
            "subcategory":"Advertising",
            "type":"Services"
        }
    ],
    "sg:phone":"+44 1333 423453",
    "sg:postcode":"KY8 5RF",
    "sg:province":"Fife",
    "sg:tags":[
        "agency"
    ],
    "wof:name":"Green & Partners",
    "wof:placetype":"venue"
},
  "geometry": {"coordinates":[-3.0525450706,56.1922416687],"type":"Point"}
}