{
  "type": "Feature",
  "properties": {
    "iso:country":"GB",
    "sg:address":"316 Bearwood Rd",
    "sg:city":"Smethwick",
    "sg:classifiers":[
        {
            "category":"Taxi",
            "type":"Transportation"
        }
    ],
    "sg:phone":"+44 121 429 5000",
    "sg:postcode":"B66 4HU",
    "sg:province":"West Midlands",
    "sg:tags":[
        "mini",
        "cab"
    ],
    "wof:name":"Prince Cars",
    "wof:placetype":"venue"
},
  "geometry": {"coordinates":[-1.9685440063,52.4829521179],"type":"Point"}
}