{
  "type": "Feature",
  "properties": {
    "addr:full":"2a Sandcliff Road Erith Kent DA8 1NY",
    "addr:housenumber":"2a",
    "addr:postcode":"da8 1ny",
    "addr:street":"Sandcliff Road",
    "iso:country":"GB",
    "sg:address":"2a Sandcliff Road",
    "sg:city":"Erith",
    "sg:classifiers":[
        {
            "category":"Retail",
            "subcategory":"Auto Repair",
            "type":"Services"
        }
    ],
    "sg:phone":"+44 1322 441604",
    "sg:postcode":"DA8 1NY",
    "sg:province":"Kent",
    "sg:tags":[
        "body",
        "car",
        "repairer"
    ],
    "wof:name":"T S K Auto Centre",
    "wof:placetype":"venue"
},
  "geometry": {"coordinates":[0.1681800038,51.4850502014],"type":"Point"}
}