{
  "type": "Feature",
  "properties": {
    "addr:full":"19 Margaret Road, New Barnet Barnet Hertfordshire EN4 9NP",
    "addr:housenumber":"19",
    "addr:postcode":"en4 9np",
    "addr:street":"Margaret Road",
    "iso:country":"GB",
    "sg:address":"19 Margaret Road, New Barnet",
    "sg:city":"Barnet",
    "sg:classifiers":[
        {
            "category":"Building & Trades",
            "subcategory":"Construction",
            "type":"Services"
        }
    ],
    "sg:phone":"+44 20 8440 7286",
    "sg:postcode":"EN4 9NP",
    "sg:province":"Hertfordshire",
    "sg:tags":[
        "bricklaying"
    ],
    "wof:name":"C F Brickwork",
    "wof:placetype":"venue"
},
  "geometry": {"coordinates":[-0.168683,51.64922],"type":"Point"}
}