{
  "type": "Feature",
  "properties": {
    "addr:full":"Tattenham Works, Leigh Road, Hindley Wigan Lancashire WN2 4SZ",
    "addr:postcode":"wn2 4sz",
    "addr:street":"Leigh Road",
    "iso:country":"GB",
    "sg:address":"Tattenham Works, Leigh Road, Hindley",
    "sg:city":"Wigan",
    "sg:classifiers":[
        {
            "category":"Retail",
            "subcategory":"Auto Repair",
            "type":"Services"
        }
    ],
    "sg:phone":"+44 1942 522731",
    "sg:postcode":"WN2 4SZ",
    "sg:province":"Lancashire",
    "sg:tags":[
        "modification",
        "garage"
    ],
    "wof:name":"Frank Bollard",
    "wof:placetype":"venue"
},
  "geometry": {"coordinates":[-2.54394,53.5215],"type":"Point"}
}