{
  "type": "Feature",
  "properties": {
    "addr:full":"295 Marton Road Middlesbrough North Yorkshire TS4 2HF",
    "addr:housenumber":"295",
    "addr:postcode":"ts4 2hf",
    "addr:street":"Marton Road",
    "iso:country":"GB",
    "sg:address":"295 Marton Road",
    "sg:city":"Middlesbrough",
    "sg:classifiers":[
        {
            "category":"Travel",
            "subcategory":"Hotels & Motels",
            "type":"Entertainment"
        }
    ],
    "sg:phone":"+44 1642 244900",
    "sg:postcode":"TS4 2HF",
    "sg:province":"North Yorkshire",
    "wof:name":"Longlands Hotel",
    "wof:placetype":"venue"
},
  "geometry": {"coordinates":[-1.2235569954,54.5662956238],"type":"Point"}
}