{
  "type": "Feature",
  "properties": {
    "addr:full":"22 Broad Street, The Square South Molton Devon EX36 3AQ",
    "addr:housenumber":"22",
    "addr:postcode":"ex36 3aq",
    "addr:street":"Broad Street The Square South",
    "iso:country":"GB",
    "sg:address":"22 Broad Street, The Square",
    "sg:city":"South Molton",
    "sg:classifiers":[
        {
            "category":"Bus Charters",
            "type":"Transportation"
        }
    ],
    "sg:phone":"+44 1769 572139",
    "sg:postcode":"EX36 3AQ",
    "sg:province":"Devon",
    "sg:tags":[
        "coach"
    ],
    "wof:name":"Terraneau's Tours Ltd.",
    "wof:placetype":"venue"
},
  "geometry": {"coordinates":[-3.8348040581,51.0178222656],"type":"Point"}
}