{
  "type": "Feature",
  "properties": {
    "iso:country":"GB",
    "sg:address":"378 Baring Road",
    "sg:city":"London",
    "sg:classifiers":[
        {
            "category":"Food & Beverages",
            "subcategory":"Bakery",
            "type":"Retail Goods"
        }
    ],
    "sg:phone":"+44 20 8857 4015",
    "sg:postcode":"SE12 0EF",
    "sg:province":"Greater London",
    "sg:tags":[
        "baker"
    ],
    "wof:name":"Lee-Grove Park Post Office",
    "wof:placetype":"venue"
},
  "geometry": {"coordinates":[0.0210420005,51.4296379089],"type":"Point"}
}