{
  "type": "Feature",
  "properties": {
    "iso:country":"GB",
    "sg:address":"34 Lochside Road",
    "sg:city":"Dumfries",
    "sg:classifiers":[
        {
            "category":"Food & Beverages",
            "subcategory":"Meat & Fish",
            "type":"Retail Goods"
        },
        {
            "category":"Food & Beverages",
            "subcategory":"Groceries & Convenience Stores",
            "type":"Retail Goods"
        }
    ],
    "sg:phone":"+44 1387 253714",
    "sg:postcode":"DG2 0LW",
    "sg:province":"Dumfries and Galloway",
    "sg:tags":[
        "shop",
        "chip"
    ],
    "wof:name":"Lochside Cafe",
    "wof:placetype":"venue"
},
  "geometry": {"coordinates":[-3.6299819946,55.0802955627],"type":"Point"}
}