{
  "type": "Feature",
  "properties": {
    "addr:full":"The Royal Pump Rooms, The Parade Leamington Spa Warwickshire CV32 4AB",
    "addr:postcode":"cv32 4ab",
    "addr:street":"The Parade",
    "iso:country":"GB",
    "sg:address":"The Royal Pump Rooms, The Parade",
    "sg:city":"Leamington Spa",
    "sg:classifiers":[
        {
            "category":"Government",
            "subcategory":"Office",
            "type":"Public Place"
        }
    ],
    "sg:phone":"+44 1926 311470",
    "sg:postcode":"CV32 4AB",
    "sg:province":"Warwickshire",
    "sg:tags":[
        "local"
    ],
    "wof:name":"South Warwickshire Tourism Ltd.",
    "wof:placetype":"venue"
},
  "geometry": {"coordinates":[-1.535324,52.289139],"type":"Point"}
}