{
  "type": "Feature",
  "properties": {
    "addr:full":"1 Priory Place Hungerford Berkshire RG17 0AB",
    "addr:housenumber":"1",
    "addr:postcode":"rg17 0ab",
    "addr:street":"Priory Place",
    "iso:country":"GB",
    "sg:address":"1 Priory Place",
    "sg:city":"Hungerford",
    "sg:classifiers":[
        {
            "category":"Shopping",
            "subcategory":"Bicycles & Sporting Goods",
            "type":"Retail Goods"
        }
    ],
    "sg:phone":"+44 1488 682206",
    "sg:postcode":"RG17 0AB",
    "sg:province":"Berkshire",
    "sg:tags":[
        "shop",
        "cycle",
        "accessory"
    ],
    "wof:name":"Hungerford Car & Cycle",
    "wof:placetype":"venue"
},
  "geometry": {"coordinates":[-1.5173389912,51.4104728699],"type":"Point"}
}