{
  "type": "Feature",
  "properties": {
    "addr:full":"Guildford Road Farnham Surrey GU9 9PZ",
    "addr:postcode":"gu9 9pz",
    "addr:street":"Guildford Road",
    "iso:country":"GB",
    "sg:address":"Guildford Road",
    "sg:city":"Farnham",
    "sg:classifiers":[
        {
            "category":"Professional",
            "subcategory":"Business Services",
            "type":"Services"
        }
    ],
    "sg:phone":"+44 1252 733732",
    "sg:postcode":"GU9 9PZ",
    "sg:province":"Surrey",
    "sg:tags":[
        "assessment",
        "quality"
    ],
    "wof:name":"Transducer Laboratories",
    "wof:placetype":"venue"
},
  "geometry": {"coordinates":[-0.7848039865,51.2190666199],"type":"Point"}
}