{
  "type": "Feature",
  "properties": {
    "addr:full":"7 The Square Cumnock East Ayrshire KA18 1BG",
    "addr:housenumber":"7",
    "addr:postcode":"ka18 1bg",
    "addr:street":"The Square Cumnock East",
    "iso:country":"GB",
    "sg:address":"7 The Square",
    "sg:city":"Cumnock",
    "sg:classifiers":[
        {
            "category":"Personal",
            "subcategory":"Beauty Salon",
            "type":"Services"
        }
    ],
    "sg:phone":"+44 1290 421082",
    "sg:postcode":"KA18 1BG",
    "sg:province":"East Ayrshire",
    "wof:name":"Complexions Health & Beauty",
    "wof:placetype":"venue"
},
  "geometry": {"coordinates":[-4.2640991211,55.4532546997],"type":"Point"}
}