{
  "type": "Feature",
  "properties": {
    "addr:full":"29 Mayfield Drive, Caversham Reading Berkshire RG4 5JP",
    "addr:housenumber":"29",
    "addr:postcode":"rg4 5jp",
    "addr:street":"Mayfield Drive",
    "iso:country":"GB",
    "sg:address":"29 Mayfield Drive, Caversham",
    "sg:city":"Reading",
    "sg:classifiers":[
        {
            "category":"Building & Trades",
            "subcategory":"Construction",
            "type":"Services"
        }
    ],
    "sg:postcode":"RG4 5JP",
    "sg:province":"Berkshire",
    "sg:tags":[
        "joiner",
        "carpenter"
    ],
    "wof:name":"Mayfield Carpentry",
    "wof:placetype":"venue"
},
  "geometry": {"coordinates":[-0.957029,51.471771],"type":"Point"}
}