{
  "type": "Feature",
  "properties": {
    "iso:country":"GB",
    "sg:address":"60 Back Sneddon Street",
    "sg:city":"Paisley",
    "sg:classifiers":[
        {
            "category":"Shopping",
            "subcategory":"Musical Instruments",
            "type":"Retail Goods"
        }
    ],
    "sg:phone":"+44 141 887 6160",
    "sg:postcode":"PA3 2BY",
    "sg:province":"Renfrewshire",
    "wof:name":"Peter Smith & Sons Pianos",
    "wof:placetype":"venue"
},
  "geometry": {"coordinates":[-4.424575,55.85062],"type":"Point"}
}