{
  "type": "Feature",
  "properties": {
    "addr:full":"Premier Park, Road, One Ind Est Winsford Cheshire CW7 3PT",
    "addr:postcode":"cw7 3pt",
    "addr:street":"Park Road One Ind Est",
    "iso:country":"GB",
    "sg:address":"Premier Park, Road, One Ind Est",
    "sg:city":"Winsford",
    "sg:classifiers":[
        {
            "category":"Shopping",
            "subcategory":"Stationery & Office Supplies",
            "type":"Retail Goods"
        }
    ],
    "sg:phone":"+44 1606 867017",
    "sg:postcode":"CW7 3PT",
    "sg:province":"Cheshire",
    "sg:tags":[
        "equipment",
        "printing",
        "mech"
    ],
    "wof:name":"Kyocera Service Centre",
    "wof:placetype":"venue"
},
  "geometry": {"coordinates":[-2.4987881184,53.2044258118],"type":"Point"}
}