{
  "type": "Feature",
  "properties": {
    "iso:country":"GB",
    "sg:address":"Unit 8 Gratton Ct, Gratton Way, Roundswell",
    "sg:city":"Barnstaple",
    "sg:classifiers":[
        {
            "category":"Professional",
            "subcategory":"Printing & Photocopies",
            "type":"Services"
        }
    ],
    "sg:postcode":"EX31 3NL",
    "sg:province":"Devon",
    "sg:tags":[
        "trophy"
    ],
    "wof:name":"Trophyman",
    "wof:placetype":"venue"
},
  "geometry": {"coordinates":[-4.0796861649,51.0661506653],"type":"Point"}
}