{
  "type": "Feature",
  "properties": {
    "iso:country":"GB",
    "sg:address":"Nettlecombe Court, Williton",
    "sg:city":"Taunton",
    "sg:classifiers":[
        {
            "category":"Government",
            "subcategory":"Office",
            "type":"Public Place"
        }
    ],
    "sg:phone":"+44 1984 640320",
    "sg:postcode":"TA4 4HT",
    "sg:province":"Devon",
    "sg:tags":[
        "education",
        "agency",
        "authority"
    ],
    "wof:name":"Field Studies Council",
    "wof:placetype":"venue"
},
  "geometry": {"coordinates":[-3.319223,51.159161],"type":"Point"}
}