{
  "type": "Feature",
  "properties": {
    "addr:full":"25 Gordondale Rd Wimbledon Greater London SW19 8EN",
    "addr:housenumber":"25",
    "addr:postcode":"sw19 8en",
    "addr:street":"Gordondale Rd",
    "iso:country":"GB",
    "sg:address":"25 Gordondale Rd",
    "sg:city":"Wimbledon",
    "sg:classifiers":[
        {
            "category":"Utilities",
            "type":"Services"
        }
    ],
    "sg:phone":"+44 20 8947 9513",
    "sg:postcode":"SW19 8EN",
    "sg:province":"Greater London",
    "sg:tags":[
        "internet"
    ],
    "wof:name":"Internet Services (UK)",
    "wof:placetype":"venue"
},
  "geometry": {"coordinates":[-0.195896998,51.4394683838],"type":"Point"}
}