{
  "type": "Feature",
  "properties": {
    "iso:country":"GB",
    "sg:address":"Manor Farm House, Irby",
    "sg:city":"Grimsby",
    "sg:classifiers":[
        {
            "category":"Community Center",
            "type":"Public Place"
        }
    ],
    "sg:phone":"+44 1472 371355",
    "sg:postcode":"DN37 7JS",
    "sg:province":"Lincolnshire",
    "sg:tags":[
        "nursery",
        "centre"
    ],
    "wof:name":"Manor Nurseries",
    "wof:placetype":"venue"
},
  "geometry": {"coordinates":[-0.198274,53.526451],"type":"Point"}
}