{
  "type": "Feature",
  "properties": {
    "addr:full":"Saltash Industrial Estate Saltash Cornwall PL12 6LF",
    "addr:postcode":"pl12 6lf",
    "addr:street":"Estate",
    "iso:country":"GB",
    "sg:address":"Saltash Industrial Estate",
    "sg:city":"Saltash",
    "sg:classifiers":[
        {
            "category":"Manufacturing",
            "subcategory":"Building Materials",
            "type":"Manufacturing & Wholesale Goods"
        }
    ],
    "sg:phone":"+44 1752 847222",
    "sg:postcode":"PL12 6LF",
    "sg:province":"Cornwall",
    "sg:tags":[
        "merchant",
        "builder"
    ],
    "wof:name":"Travis Perkins Trading Co. Ltd.",
    "wof:placetype":"venue"
},
  "geometry": {"coordinates":[-4.2128839493,50.4087486267],"type":"Point"}
}