{
  "type": "Feature",
  "properties": {
    "iso:country":"GB",
    "sg:address":"1 Woodgate",
    "sg:city":"Loughborough",
    "sg:classifiers":[
        {
            "category":"Health Services",
            "subcategory":"Dentist",
            "type":"Services"
        }
    ],
    "sg:phone":"+44 1509 262477",
    "sg:postcode":"LE11 2TY",
    "sg:province":"Leicestershire",
    "wof:name":"Jancis Nicholls Dental Practice",
    "wof:placetype":"venue"
},
  "geometry": {"coordinates":[-1.184905,52.827103],"type":"Point"}
}