{
  "type": "Feature",
  "properties": {
    "addr:full":"Unit 1 Crescent Industrial Park, Peartree Lane Dudley West Midlands DY2 0QQ",
    "addr:housenumber":"unit 1",
    "addr:postcode":"dy2 0qq",
    "addr:street":"Crescent Industrial Park Peartree Lane",
    "iso:country":"GB",
    "sg:address":"Unit 1 Crescent Industrial Park, Peartree Lane",
    "sg:city":"Dudley",
    "sg:classifiers":[
        {
            "category":"Building & Trades",
            "subcategory":"Construction",
            "type":"Services"
        }
    ],
    "sg:phone":"+44 1384 251000",
    "sg:postcode":"DY2 0QQ",
    "sg:province":"West Midlands",
    "sg:tags":[
        "ventilation",
        "contractor"
    ],
    "wof:name":"Remtox Ltd.",
    "wof:placetype":"venue"
},
  "geometry": {"coordinates":[-2.099779,52.497486],"type":"Point"}
}