{
  "type": "Feature",
  "properties": {
    "addr:full":"4 Horsefair Pontefract North Yorkshire WF8 1PE",
    "addr:housenumber":"4",
    "addr:postcode":"wf8 1pe",
    "addr:street":"Horsefair Pontefract",
    "iso:country":"GB",
    "sg:address":"4 Horsefair",
    "sg:city":"Pontefract",
    "sg:classifiers":[
        {
            "category":"Professional",
            "subcategory":"Business Services",
            "type":"Services"
        }
    ],
    "sg:postcode":"WF8 1PE",
    "sg:province":"North Yorkshire",
    "sg:tags":[
        "bookmaker"
    ],
    "wof:name":"Seymour & Story (Yorks)",
    "wof:placetype":"venue"
},
  "geometry": {"coordinates":[-1.3068139553,53.6934585571],"type":"Point"}
}