{
  "type": "Feature",
  "properties": {
    "addr:full":"10 Park Road West Southport Lancashire PR9 0JT",
    "addr:housenumber":"10",
    "addr:postcode":"pr9 0jt",
    "addr:street":"Park Road West",
    "iso:country":"GB",
    "sg:address":"10 Park Road West",
    "sg:city":"Southport",
    "sg:classifiers":[
        {
            "category":"Building & Trades",
            "subcategory":"Construction",
            "type":"Services"
        },
        {
            "category":"Organizations",
            "subcategory":"Membership Organization",
            "type":"Services"
        }
    ],
    "sg:phone":"+44 1704 531289",
    "sg:postcode":"PR9 0JT",
    "sg:province":"Lancashire",
    "sg:tags":[
        "club",
        "concrete",
        "contractor"
    ],
    "wof:name":"Coastal Court (Southport) Co. Ltd.",
    "wof:placetype":"venue"
},
  "geometry": {"coordinates":[-2.9933269024,53.6568641663],"type":"Point"}
}