{
  "type": "Feature",
  "properties": {
    "addr:full":"45 Fords Road Edinburgh City of Edinburgh EH11 3HS",
    "addr:housenumber":"45",
    "addr:postcode":"eh11 3hs",
    "addr:street":"Fords Road",
    "iso:country":"GB",
    "sg:address":"45 Fords Road",
    "sg:city":"Edinburgh",
    "sg:classifiers":[
        {
            "category":"Shopping",
            "subcategory":"Florist",
            "type":"Retail Goods"
        }
    ],
    "sg:postcode":"EH11 3HS",
    "sg:province":"City of Edinburgh",
    "wof:name":"Fantoosh Flooers",
    "wof:placetype":"venue"
},
  "geometry": {"coordinates":[-3.2520990372,55.9332695007],"type":"Point"}
}