{
  "type": "Feature",
  "properties": {
    "iso:country":"GB",
    "sg:address":"30 Milbank Terrace",
    "sg:city":"Redcar",
    "sg:classifiers":[
        {
            "category":"Professional",
            "subcategory":"Management & Consulting",
            "type":"Services"
        }
    ],
    "sg:phone":"+44 1642 475716",
    "sg:postcode":"TS10 1ED",
    "sg:province":"North Yorkshire",
    "sg:tags":[
        "consultant",
        "specialist"
    ],
    "wof:name":"Nicola Beauty Care",
    "wof:placetype":"venue"
},
  "geometry": {"coordinates":[-1.069909,54.617943],"type":"Point"}
}