{
  "type": "Feature",
  "properties": {
    "addr:full":"19-21 Pitsford St Birmingham West Midlands B18 6LJ",
    "addr:housenumber":"19-21",
    "addr:postcode":"b18 6lj",
    "addr:street":"Pitsford St",
    "iso:country":"GB",
    "sg:address":"19-21 Pitsford St",
    "sg:city":"Birmingham",
    "sg:classifiers":[
        {
            "category":"Shopping",
            "subcategory":"Jewelry",
            "type":"Retail Goods"
        }
    ],
    "sg:phone":"+44 121 551 5592",
    "sg:postcode":"B18 6LJ",
    "sg:province":"West Midlands",
    "sg:tags":[
        "gold",
        "silversmith"
    ],
    "wof:name":"K M Silver Ltd",
    "wof:placetype":"venue"
},
  "geometry": {"coordinates":[-1.914492,52.489098],"type":"Point"}
}