{
  "type": "Feature",
  "properties": {
    "addr:full":"3 Dingle Road, Upholland Skelmersdale Lancashire WN8 0EN",
    "addr:housenumber":"3",
    "addr:postcode":"wn8 0en",
    "addr:street":"Dingle Road",
    "iso:country":"GB",
    "sg:address":"3 Dingle Road, Upholland",
    "sg:city":"Skelmersdale",
    "sg:classifiers":[
        {
            "category":"Shopping",
            "subcategory":"Florist",
            "type":"Retail Goods"
        }
    ],
    "sg:postcode":"WN8 0EN",
    "sg:province":"Lancashire",
    "wof:name":"Smith & Joans",
    "wof:placetype":"venue"
},
  "geometry": {"coordinates":[-2.7278780937,53.5424690247],"type":"Point"}
}