{
  "type": "Feature",
  "properties": {
    "iso:country":"GB",
    "sg:address":"St Mary Street, Nether Stowey",
    "sg:city":"Bridgwater",
    "sg:classifiers":[
        {
            "category":"Retail",
            "subcategory":"Auto Repair",
            "type":"Services"
        }
    ],
    "sg:phone":"+44 1278 732225",
    "sg:postcode":"TA5 1LJ",
    "sg:province":"Somerset",
    "sg:tags":[
        "modification",
        "garage"
    ],
    "wof:name":"Gullifords Garage",
    "wof:placetype":"venue"
},
  "geometry": {"coordinates":[-3.155381,51.150513],"type":"Point"}
}