{
  "type": "Feature",
  "properties": {
    "iso:country":"GB",
    "sg:address":"Lane End, Rumsam Road",
    "sg:city":"Barnstaple",
    "sg:classifiers":[
        {
            "category":"Building & Trades",
            "subcategory":"Construction",
            "type":"Services"
        }
    ],
    "sg:postcode":"EX32 9ER",
    "sg:province":"Devon",
    "sg:tags":[
        "builder"
    ],
    "wof:name":"A Brooks",
    "wof:placetype":"venue"
},
  "geometry": {"coordinates":[-4.056222,51.078323],"type":"Point"}
}