{
  "type": "Feature",
  "properties": {
    "addr:full":"10 Doctors Hill, Bournheath Bromsgrove Worcestershire B61 9JE",
    "addr:housenumber":"10",
    "addr:postcode":"b61 9je",
    "addr:street":"Doctors Hill Bournheath",
    "iso:country":"GB",
    "sg:address":"10 Doctors Hill, Bournheath",
    "sg:city":"Bromsgrove",
    "sg:classifiers":[
        {
            "category":"Bars & Pubs",
            "type":"Food & Drink"
        },
        {
            "category":"Community Center",
            "subcategory":"Social",
            "type":"Public Place"
        }
    ],
    "sg:phone":"+44 1527 873094",
    "sg:postcode":"B61 9JE",
    "sg:province":"Worcestershire",
    "sg:tags":[
        "pubs",
        "house",
        "inn",
        "activity"
    ],
    "wof:name":"The New Inn",
    "wof:placetype":"venue"
},
  "geometry": {"coordinates":[-2.0762400627,52.3616294861],"type":"Point"}
}