{
  "type": "Feature",
  "properties": {
    "addr:full":"Unit 7, Cambridge Trading Estate, Cambridge Road London Greater London W7 3UP",
    "addr:housenumber":"unit 7",
    "addr:postcode":"w7 3up",
    "addr:street":"Cambridge Trading Estate Cambridge Road",
    "iso:country":"GB",
    "sg:address":"Unit 7, Cambridge Trading Estate, Cambridge Road",
    "sg:city":"London",
    "sg:classifiers":[
        {
            "category":"Building & Trades",
            "subcategory":"Construction",
            "type":"Services"
        }
    ],
    "sg:phone":"+44 20 8840 7066",
    "sg:postcode":"W7 3UP",
    "sg:province":"Greater London",
    "sg:tags":[
        "welder"
    ],
    "wof:name":"K S N Welding",
    "wof:placetype":"venue"
},
  "geometry": {"coordinates":[-0.33412,51.505219],"type":"Point"}
}