{
  "type": "Feature",
  "properties": {
    "iso:country":"GB",
    "sg:address":"Lancaster House, Sopwith Crescent, Hurrican Way",
    "sg:city":"Wickford",
    "sg:classifiers":[
        {
            "category":"Freight",
            "type":"Transportation"
        }
    ],
    "sg:phone":"+44 1268 450073",
    "sg:postcode":"SS11 8YU",
    "sg:province":"Essex",
    "sg:tags":[
        "overseas",
        "shipping",
        "removal"
    ],
    "wof:name":"Jones Lane Watson & Co. Ltd.",
    "wof:placetype":"venue"
},
  "geometry": {"coordinates":[0.548659,51.60104],"type":"Point"}
}