{
  "type": "Feature",
  "properties": {
    "addr:full":"Terminus House, The High Harlow Essex CM20 1TZ",
    "addr:postcode":"cm20 1tz",
    "addr:street":"The",
    "iso:country":"GB",
    "sg:address":"Terminus House, The High",
    "sg:city":"Harlow",
    "sg:classifiers":[
        {
            "category":"Organizations",
            "subcategory":"Professional Association",
            "type":"Services"
        }
    ],
    "sg:postcode":"CM20 1TZ",
    "sg:province":"Essex",
    "sg:tags":[
        "union",
        "trade"
    ],
    "wof:name":"The Federation Union of Management & Professional Officers",
    "wof:placetype":"venue"
},
  "geometry": {"coordinates":[0.0975060016,51.7731513977],"type":"Point"}
}