{
  "type": "Feature",
  "properties": {
    "addr:full":"27 Canterbury Rd Herne Bay Kent CT6 5DQ",
    "addr:housenumber":"27",
    "addr:postcode":"ct6 5dq",
    "addr:street":"Canterbury Rd",
    "iso:country":"GB",
    "sg:address":"27 Canterbury Rd",
    "sg:city":"Herne Bay",
    "sg:classifiers":[
        {
            "category":"Health Services",
            "subcategory":"Doctor",
            "type":"Services"
        }
    ],
    "sg:phone":"+44 1227 374040",
    "sg:postcode":"CT6 5DQ",
    "sg:province":"Kent",
    "sg:tags":[
        "practitioners"
    ],
    "wof:name":"Drs Boyle Wharfe & Garrod",
    "wof:placetype":"venue"
},
  "geometry": {"coordinates":[1.133983,51.370556],"type":"Point"}
}