{
  "type": "Feature",
  "properties": {
    "addr:full":"Herbert St, Sydney Crewe Cheshire CW1 5LZ",
    "addr:postcode":"cw1 5lz",
    "addr:street":"Herbert St",
    "iso:country":"GB",
    "sg:address":"Herbert St, Sydney",
    "sg:city":"Crewe",
    "sg:classifiers":[
        {
            "category":"Manufacturing",
            "subcategory":"Metals",
            "type":"Manufacturing & Wholesale Goods"
        }
    ],
    "sg:phone":"+44 1270 582862",
    "sg:postcode":"CW1 5LZ",
    "sg:province":"Cheshire",
    "sg:tags":[
        "steel",
        "fabricator",
        "erectors"
    ],
    "wof:name":"Huelins Ltd",
    "wof:placetype":"venue"
},
  "geometry": {"coordinates":[-2.415073,53.105228],"type":"Point"}
}