{
  "type": "Feature",
  "properties": {
    "iso:country":"GB",
    "sg:address":"Unit 2 Whitworth Industrial Estate, Tilton Road",
    "sg:city":"Birmingham",
    "sg:classifiers":[
        {
            "category":"Home & Garden",
            "subcategory":"Kitchen Supply",
            "type":"Retail Goods"
        }
    ],
    "sg:phone":"+44 121 771 3116",
    "sg:postcode":"B9 4PP",
    "sg:province":"West Midlands",
    "sg:tags":[
        "catering"
    ],
    "wof:name":"Prima Catering Supplies Ltd.",
    "wof:placetype":"venue"
},
  "geometry": {"coordinates":[-1.8654299974,52.4767799377],"type":"Point"}
}