{
  "type": "Feature",
  "properties": {
    "iso:country":"GB",
    "sg:address":"94 Charlton Road",
    "sg:city":"Andover",
    "sg:classifiers":[
        {
            "category":"Retail",
            "subcategory":"Auto Repair",
            "type":"Services"
        }
    ],
    "sg:phone":"+44 1264 353711",
    "sg:postcode":"SP10 3JZ",
    "sg:province":"Hampshire",
    "sg:tags":[
        "body",
        "car"
    ],
    "wof:name":"G & J Smith Vehicle Body Repairs",
    "wof:placetype":"venue"
},
  "geometry": {"coordinates":[-1.493347,51.213886],"type":"Point"}
}