{
  "type": "Feature",
  "properties": {
    "addr:full":"33 Rockwood Rd, Brynteg Wrexham Wrexham LL11 6LU",
    "addr:housenumber":"33",
    "addr:postcode":"ll11 6lu",
    "addr:street":"Rockwood Rd",
    "iso:country":"GB",
    "sg:address":"33 Rockwood Rd, Brynteg",
    "sg:city":"Wrexham",
    "sg:classifiers":[
        {
            "category":"Freight",
            "type":"Transportation"
        }
    ],
    "sg:phone":"+44 1978 753412",
    "sg:postcode":"LL11 6LU",
    "sg:province":"Wrexham",
    "sg:tags":[
        "haulage",
        "road"
    ],
    "wof:name":"Rockwood Parcel Deliveries",
    "wof:placetype":"venue"
},
  "geometry": {"coordinates":[-3.0357749462,53.0641899109],"type":"Point"}
}