{
  "type": "Feature",
  "properties": {
    "addr:full":"88 Sheep Street Bicester Oxfordshire OX26 6LP",
    "addr:housenumber":"88",
    "addr:postcode":"ox26 6lp",
    "addr:street":"Sheep Street",
    "iso:country":"GB",
    "sg:address":"88 Sheep Street",
    "sg:city":"Bicester",
    "sg:classifiers":[
        {
            "category":"Personal",
            "subcategory":"Barber",
            "type":"Services"
        }
    ],
    "sg:phone":"+44 1869 369606",
    "sg:postcode":"OX26 6LP",
    "sg:province":"Oxfordshire",
    "sg:tags":[
        "men's",
        "hairdresser"
    ],
    "wof:name":"A Barber Shop",
    "wof:placetype":"venue"
},
  "geometry": {"coordinates":[-1.152930975,51.8998184204],"type":"Point"}
}