{
  "type": "Feature",
  "properties": {
    "iso:country":"GB",
    "sg:address":"16 Miller Road",
    "sg:city":"Ayr",
    "sg:classifiers":[
        {
            "category":"Professional",
            "subcategory":"Lawyer & Legal Services",
            "type":"Services"
        }
    ],
    "sg:phone":"+44 1292 262266",
    "sg:postcode":"KA7 2AY",
    "sg:province":"South Ayrshire",
    "sg:tags":[
        "solicitor"
    ],
    "wof:name":"Lamonts",
    "wof:placetype":"venue"
},
  "geometry": {"coordinates":[-4.6313672066,55.4583053589],"type":"Point"}
}