{
  "type": "Feature",
  "properties": {
    "iso:country":"GB",
    "sg:address":"Dingwall Primary School, Tulloch Castle Drive",
    "sg:city":"Dingwall",
    "sg:classifiers":[
        {
            "category":"Health Services",
            "subcategory":"Dentist",
            "type":"Services"
        }
    ],
    "sg:phone":"+44 1349 864367",
    "sg:postcode":"IV15 9TU",
    "sg:province":"Highland",
    "wof:name":"Salaried Dental Clinics",
    "wof:placetype":"venue"
},
  "geometry": {"coordinates":[-4.431448,57.59618],"type":"Point"}
}