{
  "type": "Feature",
  "properties": {
    "addr:full":"37 The Village York North Yorkshire YO32 2HU",
    "addr:housenumber":"37",
    "addr:postcode":"yo32 2hu",
    "addr:street":"The Village",
    "iso:country":"GB",
    "sg:address":"37 The Village",
    "sg:city":"York",
    "sg:classifiers":[
        {
            "category":"Banks & Credit Unions",
            "subcategory":"Bank",
            "type":"Services"
        }
    ],
    "sg:phone":"+44 1904 884000",
    "sg:postcode":"YO32 2HU",
    "sg:province":"North Yorkshire",
    "wof:name":"Hsbc Bank Plc",
    "wof:placetype":"venue"
},
  "geometry": {"coordinates":[-1.086626,54.019051],"type":"Point"}
}