{
  "type": "Feature",
  "properties": {
    "addr:full":"Cecil Court, Cecil Rd, Hale Altrincham Cheshire WA15 9PA",
    "addr:postcode":"wa15 9pa",
    "addr:street":"Cecil Court Cecil Rd;Altrincham",
    "iso:country":"GB",
    "sg:address":"Cecil Court, Cecil Rd, Hale",
    "sg:city":"Altrincham",
    "sg:classifiers":[
        {
            "category":"Communications",
            "subcategory":"Film & Video Production",
            "type":"Services"
        }
    ],
    "sg:phone":"+44 161 929 9001",
    "sg:postcode":"WA15 9PA",
    "sg:province":"Cheshire",
    "sg:tags":[
        "pr",
        "telemarketing"
    ],
    "wof:name":"Appointments Factory",
    "wof:placetype":"venue"
},
  "geometry": {"coordinates":[-2.3466420174,53.3769264221],"type":"Point"}
}