{
  "type": "Feature",
  "properties": {
    "addr:full":"Lee Park Avenue Liverpool Merseyside L25 3RS",
    "addr:postcode":"l25 3rs",
    "addr:street":"Lee Park Avenue",
    "iso:country":"GB",
    "sg:address":"Lee Park Avenue",
    "sg:city":"Liverpool",
    "sg:classifiers":[
        {
            "category":"Bars & Pubs",
            "type":"Food & Drink"
        }
    ],
    "sg:phone":"+44 151 487 0179",
    "sg:postcode":"L25 3RS",
    "sg:province":"Merseyside",
    "sg:tags":[
        "pubs",
        "inn"
    ],
    "wof:name":"The Lee Park Hotel",
    "wof:placetype":"venue"
},
  "geometry": {"coordinates":[-2.854284,53.389091],"type":"Point"}
}