{
  "type": "Feature",
  "properties": {
    "iso:country":"GB",
    "sg:address":"7 Meadowfield Ct, Meadowfields Indstl Es, Ponteland",
    "sg:city":"Newcastle-upon-tyne",
    "sg:classifiers":[
        {
            "category":"Shopping",
            "subcategory":"Catalog Store",
            "type":"Retail Goods"
        }
    ],
    "sg:postcode":"NE20 9SD",
    "sg:province":"Northumberland",
    "sg:tags":[
        "mail",
        "order"
    ],
    "wof:name":"First Line Products",
    "wof:placetype":"venue"
},
  "geometry": {"coordinates":[-1.7496800423,55.0518302917],"type":"Point"}
}