{
  "type": "Feature",
  "properties": {
    "addr:full":"1 Woodville Street Lancaster Lancashire LA1 3QD",
    "addr:housenumber":"1",
    "addr:postcode":"la1 3qd",
    "addr:street":"Woodville Street",
    "iso:country":"GB",
    "sg:address":"1 Woodville Street",
    "sg:city":"Lancaster",
    "sg:classifiers":[
        {
            "category":"Personal",
            "subcategory":"Beauty Salon",
            "type":"Services"
        },
        {
            "category":"Personal",
            "subcategory":"Barber",
            "type":"Services"
        }
    ],
    "sg:phone":"+44 1524 65095",
    "sg:postcode":"LA1 3QD",
    "sg:province":"Lancashire",
    "sg:tags":[
        "unisex",
        "hairdresser"
    ],
    "wof:name":"Aztec Hair",
    "wof:placetype":"venue"
},
  "geometry": {"coordinates":[-2.792806,54.0494],"type":"Point"}
}