{
  "type": "Feature",
  "properties": {
    "addr:full":"127d Above Bar St Southampton Hampshire SO14 7FN",
    "addr:housenumber":"127d",
    "addr:postcode":"so14 7fn",
    "addr:street":"Above Bar St",
    "iso:country":"GB",
    "sg:address":"127d Above Bar St",
    "sg:city":"Southampton",
    "sg:classifiers":[
        {
            "category":"Shopping",
            "subcategory":"Thrift Store",
            "type":"Retail Goods"
        }
    ],
    "sg:postcode":"SO14 7FN",
    "sg:province":"Hampshire",
    "sg:tags":[
        "shop",
        "charity"
    ],
    "wof:name":"Oxfam",
    "wof:placetype":"venue"
},
  "geometry": {"coordinates":[-1.4047549963,50.9067115784],"type":"Point"}
}