{
  "type": "Feature",
  "properties": {
    "addr:full":"Alexandra Cottage, Main Street, Walberswick Southwold Suffolk IP18 6UG",
    "addr:postcode":"ip18 6ug",
    "addr:street":"Main Street",
    "iso:country":"GB",
    "sg:address":"Alexandra Cottage, Main Street, Walberswick",
    "sg:city":"Southwold",
    "sg:classifiers":[
        {
            "category":"Professional",
            "subcategory":"Lawyer & Legal Services",
            "type":"Services"
        }
    ],
    "sg:postcode":"IP18 6UG",
    "sg:province":"Suffolk",
    "sg:tags":[
        "solicitor"
    ],
    "wof:name":"R J Winyard",
    "wof:placetype":"venue"
},
  "geometry": {"coordinates":[1.6762000322,52.328163147],"type":"Point"}
}