{
  "type": "Feature",
  "properties": {
    "addr:full":"125 Boxley Drive, West Bridgford Nottingham Nottinghamshire NG2 7GN",
    "addr:housenumber":"125",
    "addr:postcode":"ng2 7gn",
    "addr:street":"Boxley Drive",
    "iso:country":"GB",
    "sg:address":"125 Boxley Drive, West Bridgford",
    "sg:city":"Nottingham",
    "sg:classifiers":[
        {
            "category":"Professional",
            "type":"Services"
        }
    ],
    "sg:phone":"+44 115 923 5747",
    "sg:postcode":"NG2 7GN",
    "sg:province":"Nottinghamshire",
    "sg:tags":[
        "entertainer"
    ],
    "wof:name":"J B Entertainments",
    "wof:placetype":"venue"
},
  "geometry": {"coordinates":[-1.14632,52.917286],"type":"Point"}
}