{
  "type": "Feature",
  "properties": {
    "addr:full":"56 Northfield Rd West Ealing Greater London W13 9SY",
    "addr:housenumber":"56",
    "addr:postcode":"w13 9sy",
    "addr:street":"Northfield Rd",
    "iso:country":"GB",
    "sg:address":"56 Northfield Rd",
    "sg:city":"West Ealing",
    "sg:classifiers":[
        {
            "category":"Building & Trades",
            "subcategory":"Construction",
            "type":"Services"
        }
    ],
    "sg:phone":"+44 20 8566 0606",
    "sg:postcode":"W13 9SY",
    "sg:province":"Greater London",
    "sg:tags":[
        "joiner",
        "carpenter"
    ],
    "wof:name":"31797",
    "wof:placetype":"venue"
},
  "geometry": {"coordinates":[-0.3212389946,51.5043449402],"type":"Point"}
}