{
  "type": "Feature",
  "properties": {
    "iso:country":"GB",
    "sg:address":"The Gallery, Park Road",
    "sg:city":"Ruthin",
    "sg:classifiers":[
        {
            "category":"Banks & Credit Unions",
            "subcategory":"Financial Services",
            "type":"Services"
        }
    ],
    "sg:phone":"+44 1824 707027",
    "sg:postcode":"LL15 1NB",
    "sg:province":"Denbighshire",
    "sg:tags":[
        "consultant"
    ],
    "wof:name":"Ml Financial Management",
    "wof:placetype":"venue"
},
  "geometry": {"coordinates":[-3.304522,53.114017],"type":"Point"}
}