{
  "type": "Feature",
  "properties": {
    "addr:full":"5 Smoke Lane Bristol City of Bristol BS11 0YA",
    "addr:housenumber":"5",
    "addr:postcode":"bs11 0ya",
    "addr:street":"Smoke Lane",
    "iso:country":"GB",
    "sg:address":"5 Smoke Lane",
    "sg:city":"Bristol",
    "sg:classifiers":[
        {
            "category":"Personal",
            "type":"Services"
        }
    ],
    "sg:phone":"+44 117 916 2318",
    "sg:postcode":"BS11 0YA",
    "sg:province":"City of Bristol",
    "sg:tags":[
        "delivery"
    ],
    "wof:name":"Exel Rover Contracts",
    "wof:placetype":"venue"
},
  "geometry": {"coordinates":[-2.677235,51.52673],"type":"Point"}
}