{
  "type": "Feature",
  "properties": {
    "addr:full":"34 Marlborough Road Luton Bedfordshire LU3 1EF",
    "addr:housenumber":"34",
    "addr:postcode":"lu3 1ef",
    "addr:street":"Marlborough Road",
    "iso:country":"GB",
    "sg:address":"34 Marlborough Road",
    "sg:city":"Luton",
    "sg:classifiers":[
        {
            "category":"Building & Trades",
            "subcategory":"Construction",
            "type":"Services"
        }
    ],
    "sg:phone":"+44 1582 736752",
    "sg:postcode":"LU3 1EF",
    "sg:province":"Bedfordshire",
    "sg:tags":[
        "glazier"
    ],
    "wof:name":"M A Beare",
    "wof:placetype":"venue"
},
  "geometry": {"coordinates":[-0.4249530137,51.8898048401],"type":"Point"}
}