{
  "type": "Feature",
  "properties": {
    "addr:full":"The Saddler Centre Walsall West Midlands WS2 9JS",
    "addr:postcode":"ws2 9js",
    "iso:country":"GB",
    "sg:address":"The Saddler Centre",
    "sg:city":"Walsall",
    "sg:classifiers":[
        {
            "category":"Shopping",
            "subcategory":"Florist",
            "type":"Retail Goods"
        }
    ],
    "sg:postcode":"WS2 9JS",
    "sg:province":"West Midlands",
    "wof:name":"Flower Station",
    "wof:placetype":"venue"
},
  "geometry": {"coordinates":[-1.98555,52.584209],"type":"Point"}
}