{
  "type": "Feature",
  "properties": {
    "addr:full":"6 Abbey Square Chester Cheshire CH1 2HU",
    "addr:housenumber":"6",
    "addr:postcode":"ch1 2hu",
    "addr:street":"Abbey Square",
    "iso:country":"GB",
    "sg:address":"6 Abbey Square",
    "sg:city":"Chester",
    "sg:classifiers":[
        {
            "category":"Communications",
            "subcategory":"Newspaper",
            "type":"Services"
        }
    ],
    "sg:phone":"+44 1244 342878",
    "sg:postcode":"CH1 2HU",
    "sg:province":"Cheshire",
    "sg:tags":[
        "magazine"
    ],
    "wof:name":"International Union of Crystallography",
    "wof:placetype":"venue"
},
  "geometry": {"coordinates":[-2.892194,53.192253],"type":"Point"}
}