{
  "type": "Feature",
  "properties": {
    "addr:full":"Wallace Ho, 3 Boswell Rd Edinburgh City of Edinburgh EH5 3RJ",
    "addr:housenumber":"3",
    "addr:postcode":"eh5 3rj",
    "addr:street":"Boswell Rd",
    "iso:country":"GB",
    "sg:address":"Wallace Ho, 3 Boswell Rd",
    "sg:city":"Edinburgh",
    "sg:classifiers":[
        {
            "category":"Professional",
            "subcategory":"Lawyer & Legal Services",
            "type":"Services"
        },
        {
            "category":"Organizations",
            "subcategory":"Non-profit Organization",
            "type":"Services"
        }
    ],
    "sg:phone":"+44 131 538 7288",
    "sg:postcode":"EH5 3RJ",
    "sg:province":"City of Edinburgh",
    "sg:tags":[
        "charitable",
        "advice",
        "organisation",
        "counselling",
        "charity"
    ],
    "wof:name":"Post Natal Depression Project",
    "wof:placetype":"venue"
},
  "geometry": {"coordinates":[-3.2066190243,55.9759902954],"type":"Point"}
}