{
  "type": "Feature",
  "properties": {
    "iso:country":"GB",
    "sg:address":"The Moor, Bodenham",
    "sg:city":"Hereford",
    "sg:classifiers":[
        {
            "category":"Shopping",
            "subcategory":"Discount & Variety Stores",
            "type":"Retail Goods"
        }
    ],
    "sg:phone":"+44 1568 797319",
    "sg:postcode":"HR1 3HT",
    "sg:province":"Herefordshire",
    "sg:tags":[
        "centre"
    ],
    "wof:name":"Baches Bargain Warehouse",
    "wof:placetype":"venue"
},
  "geometry": {"coordinates":[-2.668203,52.158195],"type":"Point"}
}