{
  "type": "Feature",
  "properties": {
    "addr:full":"Paradise Lane, Leyland Preston Lancashire PR26 7ST",
    "addr:postcode":"pr26 7st",
    "addr:street":"Paradise Lane",
    "iso:country":"GB",
    "sg:address":"Paradise Lane, Leyland",
    "sg:city":"Preston",
    "sg:classifiers":[
        {
            "category":"Education",
            "subcategory":"School",
            "type":"Public Place"
        }
    ],
    "sg:phone":"+44 1772 432048",
    "sg:postcode":"PR26 7ST",
    "sg:province":"Lancashire",
    "sg:tags":[
        "local",
        "authority"
    ],
    "wof:name":"Moss Side County Primary School",
    "wof:placetype":"venue"
},
  "geometry": {"coordinates":[-2.7298989296,53.6943893433],"type":"Point"}
}