{
  "type": "Feature",
  "properties": {
    "addr:full":"26 Ralph Terrace Llanelli Carmarthenshire SA15 2UB",
    "addr:housenumber":"26",
    "addr:postcode":"sa15 2ub",
    "addr:street":"Ralph Terrace",
    "iso:country":"GB",
    "sg:address":"26 Ralph Terrace",
    "sg:city":"Llanelli",
    "sg:classifiers":[
        {
            "category":"Retail",
            "subcategory":"Auto Repair",
            "type":"Services"
        }
    ],
    "sg:phone":"+44 1554 770321",
    "sg:postcode":"SA15 2UB",
    "sg:province":"Carmarthenshire",
    "sg:tags":[
        "car",
        "servicing",
        "radiator"
    ],
    "wof:name":"Dyfed Radiators",
    "wof:placetype":"venue"
},
  "geometry": {"coordinates":[-4.166231,51.676441],"type":"Point"}
}