{
  "type": "Feature",
  "properties": {
    "addr:full":"1 The Colonade, Overdown Road, Tilehurst Reading Berkshire RG31 6PR",
    "addr:housenumber":"1",
    "addr:postcode":"rg31 6pr",
    "addr:street":"The Colonade Overdown Road",
    "iso:country":"GB",
    "sg:address":"1 The Colonade, Overdown Road, Tilehurst",
    "sg:city":"Reading",
    "sg:classifiers":[
        {
            "category":"Food & Beverages",
            "subcategory":"Supermarket",
            "type":"Retail Goods"
        }
    ],
    "sg:postcode":"RG31 6PR",
    "sg:province":"Berkshire",
    "wof:name":"Rusts Ltd.",
    "wof:placetype":"venue"
},
  "geometry": {"coordinates":[-1.04445,51.469688],"type":"Point"}
}