{
  "type": "Feature",
  "properties": {
    "iso:country":"GB",
    "sg:address":"128 Capstone Road",
    "sg:city":"Bournemouth",
    "sg:classifiers":[
        {
            "category":"Retail",
            "subcategory":"Auto Repair",
            "type":"Services"
        }
    ],
    "sg:postcode":"BH8 8RT",
    "sg:province":"Dorset",
    "sg:tags":[
        "modification",
        "garage"
    ],
    "wof:name":"D & B Autos",
    "wof:placetype":"venue"
},
  "geometry": {"coordinates":[-1.8580429554,50.7347145081],"type":"Point"}
}