{
  "type": "Feature",
  "properties": {
    "addr:full":"7 Bowmont Street Kelso Scottish Borders TD5 7JH",
    "addr:housenumber":"7",
    "addr:postcode":"td5 7jh",
    "addr:street":"Bowmont Street",
    "iso:country":"GB",
    "sg:address":"7 Bowmont Street",
    "sg:city":"Kelso",
    "sg:classifiers":[
        {
            "category":"Restaurant",
            "type":"Food & Drink"
        }
    ],
    "sg:phone":"+44 1573 223548",
    "sg:postcode":"TD5 7JH",
    "sg:province":"Scottish Borders",
    "wof:name":"Cobbles Inn Restaurant Ltd.",
    "wof:placetype":"venue"
},
  "geometry": {"coordinates":[-2.4352269173,55.6002807617],"type":"Point"}
}