{
  "type": "Feature",
  "properties": {
    "addr:full":"79 Greenview Dr Northampton Northamptonshire NN2 7LE",
    "addr:housenumber":"79",
    "addr:postcode":"nn2 7le",
    "addr:street":"Greenview Dr",
    "iso:country":"GB",
    "sg:address":"79 Greenview Dr",
    "sg:city":"Northampton",
    "sg:classifiers":[
        {
            "category":"Communications",
            "subcategory":"Film & Video Production",
            "type":"Services"
        }
    ],
    "sg:phone":"+44 1604 712283",
    "sg:postcode":"NN2 7LE",
    "sg:province":"Northamptonshire",
    "sg:tags":[
        "recording",
        "studio"
    ],
    "wof:name":"M & M Records",
    "wof:placetype":"venue"
},
  "geometry": {"coordinates":[-0.8825680017,52.2616081238],"type":"Point"}
}