{
  "type": "Feature",
  "properties": {
    "addr:full":"13 Stockton Gardens London Greater London NW7 3AB",
    "addr:housenumber":"13",
    "addr:postcode":"nw7 3ab",
    "addr:street":"Stockton Gardens",
    "iso:country":"GB",
    "sg:address":"13 Stockton Gardens",
    "sg:city":"London",
    "sg:classifiers":[
        {
            "category":"Building & Trades",
            "subcategory":"Plumbing",
            "type":"Services"
        }
    ],
    "sg:postcode":"NW7 3AB",
    "sg:province":"Greater London",
    "sg:tags":[
        "central",
        "heating"
    ],
    "wof:name":"Bribern Heating",
    "wof:placetype":"venue"
},
  "geometry": {"coordinates":[-0.252972,51.625465],"type":"Point"}
}