{
  "type": "Feature",
  "properties": {
    "addr:full":"34 Commercial Road Leven Fife KY8 4LD",
    "addr:housenumber":"34",
    "addr:postcode":"ky8 4ld",
    "addr:street":"Commercial Road",
    "iso:country":"GB",
    "sg:address":"34 Commercial Road",
    "sg:city":"Leven",
    "sg:classifiers":[
        {
            "category":"Organizations",
            "subcategory":"Non-profit Organization",
            "type":"Services"
        }
    ],
    "sg:phone":"+44 1333 592640",
    "sg:postcode":"KY8 4LD",
    "sg:province":"Fife",
    "sg:tags":[
        "organisation",
        "voluntary",
        "charity"
    ],
    "wof:name":"Cornerstone Resource Centre",
    "wof:placetype":"venue"
},
  "geometry": {"coordinates":[-2.998517,56.196442],"type":"Point"}
}