{
  "type": "Feature",
  "properties": {
    "iso:country":"GB",
    "sg:address":"Gables, Kingston Road",
    "sg:city":"Lewes",
    "sg:classifiers":[
        {
            "category":"Professional",
            "subcategory":"Management & Consulting",
            "type":"Services"
        }
    ],
    "sg:phone":"+44 1273 779212",
    "sg:postcode":"BN7 1YH",
    "sg:province":"East Sussex",
    "sg:tags":[
        "consultant",
        "business"
    ],
    "wof:name":"Bentley Associates Ltd.",
    "wof:placetype":"venue"
},
  "geometry": {"coordinates":[-0.000101,50.867775],"type":"Point"}
}