{
  "type": "Feature",
  "properties": {
    "iso:country":"GB",
    "sg:address":"Whitehall Street",
    "sg:city":"Darwen",
    "sg:classifiers":[
        {
            "category":"Professional",
            "subcategory":"Engineering",
            "type":"Services"
        }
    ],
    "sg:postcode":"BB3 2LP",
    "sg:province":"Lancashire",
    "wof:name":"Shadow Engineering Ltd.",
    "wof:placetype":"venue"
},
  "geometry": {"coordinates":[-2.4591391087,53.6800537109],"type":"Point"}
}