{
  "type": "Feature",
  "properties": {
    "iso:country":"GB",
    "sg:address":"16 Little Belmont Street",
    "sg:city":"Aberdeen",
    "sg:classifiers":[
        {
            "category":"Fast Food",
            "type":"Food & Drink"
        },
        {
            "category":"Restaurant",
            "type":"Food & Drink"
        }
    ],
    "sg:phone":"+44 1224 652370",
    "sg:postcode":"AB10 1JG",
    "sg:province":"Aberdeen City",
    "sg:tags":[
        "away",
        "take"
    ],
    "wof:name":"Little Belmont Hut",
    "wof:placetype":"venue"
},
  "geometry": {"coordinates":[-2.101106,57.146954],"type":"Point"}
}