{
  "type": "Feature",
  "properties": {
    "addr:full":"15 Ringwood Road, Totton Southampton Hampshire SO40 8DA",
    "addr:housenumber":"15",
    "addr:postcode":"so40 8da",
    "addr:street":"Ringwood Road",
    "iso:country":"GB",
    "sg:address":"15 Ringwood Road, Totton",
    "sg:city":"Southampton",
    "sg:classifiers":[
        {
            "category":"Building & Trades",
            "subcategory":"Landscaping Services",
            "type":"Services"
        }
    ],
    "sg:phone":"+44 23 8086 8529",
    "sg:postcode":"SO40 8DA",
    "sg:province":"Hampshire",
    "sg:tags":[
        "pond",
        "aquarium"
    ],
    "wof:name":"Creature Comforts & Aquatic Centre",
    "wof:placetype":"venue"
},
  "geometry": {"coordinates":[-1.4912,50.917816],"type":"Point"}
}