{
  "type": "Feature",
  "properties": {
    "iso:country":"GB",
    "sg:address":"Unit 1b Grange Hill Industrial Estate, Bratton Fleming",
    "sg:city":"Barnstaple",
    "sg:classifiers":[
        {
            "category":"Professional",
            "subcategory":"Engineering",
            "type":"Services"
        }
    ],
    "sg:postcode":"EX31 4UH",
    "sg:province":"Devon",
    "sg:tags":[
        "precision",
        "engineer"
    ],
    "wof:name":"Roanoke Precision Engineering",
    "wof:placetype":"venue"
},
  "geometry": {"coordinates":[-3.932097,51.123859],"type":"Point"}
}