{
  "type": "Feature",
  "properties": {
    "addr:full":"179 Morningside Road Edinburgh City of Edinburgh EH10 4QP",
    "addr:housenumber":"179",
    "addr:postcode":"eh10 4qp",
    "addr:street":"Morningside Road",
    "iso:country":"GB",
    "sg:address":"179 Morningside Road",
    "sg:city":"Edinburgh",
    "sg:classifiers":[
        {
            "category":"Organizations",
            "subcategory":"Non-profit Organization",
            "type":"Services"
        }
    ],
    "sg:postcode":"EH10 4QP",
    "sg:province":"City of Edinburgh",
    "sg:tags":[
        "organisation",
        "voluntary",
        "charity"
    ],
    "wof:name":"Capability Scotland",
    "wof:placetype":"venue"
},
  "geometry": {"coordinates":[-3.2093689442,55.9292144775],"type":"Point"}
}