{
  "type": "Feature",
  "properties": {
    "iso:country":"GB",
    "sg:address":"255 Mansfield Road",
    "sg:city":"Nottingham",
    "sg:classifiers":[
        {
            "category":"Restaurant",
            "type":"Food & Drink"
        }
    ],
    "sg:phone":"+44 115 941 1854",
    "sg:postcode":"NG1 3FT",
    "sg:province":"Nottinghamshire",
    "sg:tags":[
        "indian",
        "-"
    ],
    "wof:name":"Himalaya Tandoori Restaurant",
    "wof:placetype":"venue"
},
  "geometry": {"coordinates":[-1.15265,52.964382],"type":"Point"}
}