{
  "type": "Feature",
  "properties": {
    "addr:full":"Peppard House, 45 Woodcote Rd, Caversham Reading Berkshire RG4 7BB",
    "addr:housenumber":"45",
    "addr:postcode":"rg4 7bb",
    "addr:street":"Woodcote Rd",
    "iso:country":"GB",
    "sg:address":"Peppard House, 45 Woodcote Rd, Caversham",
    "sg:city":"Reading",
    "sg:classifiers":[
        {
            "category":"Organizations",
            "subcategory":"Non-profit Organization",
            "type":"Services"
        }
    ],
    "sg:phone":"+44 118 947 2067",
    "sg:postcode":"RG4 7BB",
    "sg:province":"Berkshire",
    "sg:tags":[
        "organisation",
        "voluntary",
        "charity"
    ],
    "wof:name":"Choice Ltd",
    "wof:placetype":"venue"
},
  "geometry": {"coordinates":[-0.9888749719,51.4738502502],"type":"Point"}
}