{
  "type": "Feature",
  "properties": {
    "iso:country":"GB",
    "sg:address":"54 Percheron Rd",
    "sg:city":"Borehamwood",
    "sg:classifiers":[
        {
            "category":"Building & Trades",
            "subcategory":"Landscaping Services",
            "type":"Services"
        }
    ],
    "sg:phone":"+44 20 8386 7885",
    "sg:postcode":"WD6 2SR",
    "sg:province":"Hertfordshire",
    "sg:tags":[
        "gardening"
    ],
    "wof:name":"Fresh Start Gardening Services",
    "wof:placetype":"venue"
},
  "geometry": {"coordinates":[-0.257831,51.644493],"type":"Point"}
}