{
  "type": "Feature",
  "properties": {
    "addr:full":"82 Queen St Newton Abbot Devon TQ12 2ET",
    "addr:housenumber":"82",
    "addr:postcode":"tq12 2et",
    "addr:street":"Queen St",
    "iso:country":"GB",
    "sg:address":"82 Queen St",
    "sg:city":"Newton Abbot",
    "sg:classifiers":[
        {
            "category":"Food & Beverages",
            "subcategory":"Bakery",
            "type":"Retail Goods"
        }
    ],
    "sg:phone":"+44 1626 204135",
    "sg:postcode":"TQ12 2ET",
    "sg:province":"Devon",
    "sg:tags":[
        "baker"
    ],
    "wof:name":"Harvesters Bakery",
    "wof:placetype":"venue"
},
  "geometry": {"coordinates":[-3.6048510075,50.5307006836],"type":"Point"}
}