{
  "type": "Feature",
  "properties": {
    "iso:country":"GB",
    "sg:address":"3 Corn Street",
    "sg:city":"Bristol",
    "sg:classifiers":[
        {
            "category":"Professional",
            "subcategory":"Management & Consulting",
            "type":"Services"
        }
    ],
    "sg:phone":"+44 117 925 5625",
    "sg:postcode":"BS1 1HT",
    "sg:province":"City of Bristol",
    "sg:tags":[
        "marketing",
        "consultant"
    ],
    "wof:name":"Crisp Marketing Associates (Bristol) Ltd.",
    "wof:placetype":"venue"
},
  "geometry": {"coordinates":[-2.595119,51.454109],"type":"Point"}
}