{
  "type": "Feature",
  "properties": {
    "iso:country":"GB",
    "sg:address":"10 Ash Hill Road",
    "sg:city":"Torquay",
    "sg:classifiers":[
        {
            "category":"Travel",
            "subcategory":"Hotels & Motels",
            "type":"Entertainment"
        }
    ],
    "sg:postcode":"TQ1 3HZ",
    "sg:province":"Devon",
    "wof:name":"Craig Court Hotel",
    "wof:placetype":"venue"
},
  "geometry": {"coordinates":[-3.530676,50.469994],"type":"Point"}
}