{
  "type": "Feature",
  "properties": {
    "iso:country":"GB",
    "sg:address":"3 Saracens Close, Gillingham Business Park",
    "sg:city":"Gillingham",
    "sg:classifiers":[
        {
            "category":"Professional",
            "subcategory":"Printing & Photocopies",
            "type":"Services"
        }
    ],
    "sg:phone":"+44 1634 266880",
    "sg:postcode":"ME8 0QN",
    "sg:province":"Kent",
    "sg:tags":[
        "printer"
    ],
    "wof:name":"Kent Litho Ltd.",
    "wof:placetype":"venue"
},
  "geometry": {"coordinates":[0.57712,51.366116],"type":"Point"}
}