{
  "type": "Feature",
  "properties": {
    "addr:full":"7 Springfield Road Teddington Greater London TW11 9AP",
    "addr:housenumber":"7",
    "addr:postcode":"tw11 9ap",
    "addr:street":"Springfield Road",
    "iso:country":"GB",
    "sg:address":"7 Springfield Road",
    "sg:city":"Teddington",
    "sg:classifiers":[
        {
            "category":"Shopping",
            "subcategory":"Stationery & Office Supplies",
            "type":"Retail Goods"
        }
    ],
    "sg:phone":"+44 20 8977 9772",
    "sg:postcode":"TW11 9AP",
    "sg:province":"Greater London",
    "sg:tags":[
        "item",
        "promotional"
    ],
    "wof:name":"Oceanshade Ltd.",
    "wof:placetype":"venue"
},
  "geometry": {"coordinates":[-0.329973,51.426586],"type":"Point"}
}