{
  "type": "Feature",
  "properties": {
    "iso:country":"GB",
    "sg:address":"Blanche St, Ashton-on-ribble",
    "sg:city":"Preston",
    "sg:classifiers":[
        {
            "category":"Shopping",
            "subcategory":"Pharmacy",
            "type":"Retail Goods"
        }
    ],
    "sg:phone":"+44 1772 721893",
    "sg:postcode":"PR2 2RL",
    "sg:province":"Lancashire",
    "sg:tags":[
        "pharmacist",
        "chemist"
    ],
    "wof:name":"G.S Birch M.P.S.",
    "wof:placetype":"venue"
},
  "geometry": {"coordinates":[-2.72206,53.764782],"type":"Point"}
}