{
  "type": "Feature",
  "properties": {
    "addr:full":"Unit 28-30 Thaydon Road London Greater London E5 9ND",
    "addr:housenumber":"unit 28-30",
    "addr:postcode":"e5 9nd",
    "addr:street":"Thaydon Road",
    "iso:country":"GB",
    "sg:address":"Unit 28-30 Thaydon Road",
    "sg:city":"London",
    "sg:classifiers":[
        {
            "category":"Professional",
            "subcategory":"Printing & Photocopies",
            "type":"Services"
        }
    ],
    "sg:phone":"+44 20 8806 9966",
    "sg:postcode":"E5 9ND",
    "sg:province":"Greater London",
    "sg:tags":[
        "printer"
    ],
    "wof:name":"Tecprint (U K) Ltd.",
    "wof:placetype":"venue"
},
  "geometry": {"coordinates":[-0.0520169996,51.563205719],"type":"Point"}
}