{
  "type": "Feature",
  "properties": {
    "addr:full":"17 Ashby Road, Moira Swadlincote Derbyshire DE12 6DJ",
    "addr:housenumber":"17",
    "addr:postcode":"de12 6dj",
    "addr:street":"Ashby Road",
    "iso:country":"GB",
    "sg:address":"17 Ashby Road, Moira",
    "sg:city":"Swadlincote",
    "sg:classifiers":[
        {
            "category":"Professional",
            "subcategory":"Management & Consulting",
            "type":"Services"
        }
    ],
    "sg:phone":"+44 1283 224600",
    "sg:postcode":"DE12 6DJ",
    "sg:province":"Derbyshire",
    "sg:tags":[
        "environmental",
        "consultant"
    ],
    "wof:name":"Julien Williams",
    "wof:placetype":"venue"
},
  "geometry": {"coordinates":[-1.511869,52.74601],"type":"Point"}
}