{
  "type": "Feature",
  "properties": {
    "addr:full":"First Floor, South House Dorking Surrey RH4 2JZ",
    "addr:postcode":"rh4 2jz",
    "addr:street":"Dorking",
    "iso:country":"GB",
    "sg:address":"First Floor, South House",
    "sg:city":"Dorking",
    "sg:classifiers":[
        {
            "category":"Professional",
            "subcategory":"Accounting & Tax Preparation",
            "type":"Services"
        }
    ],
    "sg:phone":"+44 1306 743939",
    "sg:postcode":"RH4 2JZ",
    "sg:province":"Surrey",
    "sg:tags":[
        "accountant"
    ],
    "wof:name":"Bradney & Co. Ltd.",
    "wof:placetype":"venue"
},
  "geometry": {"coordinates":[-0.3288139999,51.233341217],"type":"Point"}
}