{
  "type": "Feature",
  "properties": {
    "addr:full":"Brook Ho Totnes Devon TQ9 6DJ",
    "addr:postcode":"tq9 6dj",
    "addr:street":"Brook",
    "iso:country":"GB",
    "sg:address":"Brook Ho",
    "sg:city":"Totnes",
    "sg:classifiers":[
        {
            "category":"Retail",
            "subcategory":"Auto Repair",
            "type":"Services"
        }
    ],
    "sg:postcode":"TQ9 6DJ",
    "sg:province":"Devon",
    "sg:tags":[
        "modification",
        "garage"
    ],
    "wof:name":"Croad,I P,",
    "wof:placetype":"venue"
},
  "geometry": {"coordinates":[-3.710699,50.433731],"type":"Point"}
}