{
  "type": "Feature",
  "properties": {
    "iso:country":"GB",
    "sg:address":"6 West Clo, Waresley",
    "sg:city":"Sandy",
    "sg:classifiers":[
        {
            "category":"Building & Trades",
            "subcategory":"Construction",
            "type":"Services"
        }
    ],
    "sg:phone":"+44 1767 650768",
    "sg:postcode":"SG19 3BY",
    "sg:province":"Bedfordshire",
    "sg:tags":[
        "dry",
        "lining",
        "builder",
        "plasterers",
        "screeders"
    ],
    "wof:name":"Poulton,R B,",
    "wof:placetype":"venue"
},
  "geometry": {"coordinates":[-0.180589,52.177151],"type":"Point"}
}