{
  "type": "Feature",
  "properties": {
    "addr:full":"271 Old Shoreham Road Hove East Sussex BN3 7ED",
    "addr:housenumber":"271",
    "addr:postcode":"bn3 7ed",
    "addr:street":"Old Shoreham Road",
    "iso:country":"GB",
    "sg:address":"271 Old Shoreham Road",
    "sg:city":"Hove",
    "sg:classifiers":[
        {
            "category":"Food & Beverages",
            "subcategory":"Liquor & Beverages",
            "type":"Retail Goods"
        }
    ],
    "sg:phone":"+44 1273 777085",
    "sg:postcode":"BN3 7ED",
    "sg:province":"East Sussex",
    "sg:tags":[
        "beer",
        "spirit",
        "wines"
    ],
    "wof:name":"Majestic Wine Warehouses Ltd.",
    "wof:placetype":"venue"
},
  "geometry": {"coordinates":[-0.190228,50.838413],"type":"Point"}
}