{
  "type": "Feature",
  "properties": {
    "addr:full":"Watling Street Lichfield Staffordshire WS14 0AN",
    "addr:postcode":"ws14 0an",
    "addr:street":"Watling Street",
    "iso:country":"GB",
    "sg:address":"Watling Street",
    "sg:city":"Lichfield",
    "sg:classifiers":[
        {
            "category":"Restaurant",
            "type":"Food & Drink"
        }
    ],
    "sg:phone":"+44 1543 480413",
    "sg:postcode":"WS14 0AN",
    "sg:province":"Staffordshire",
    "wof:name":"Troopers Restaurant",
    "wof:placetype":"venue"
},
  "geometry": {"coordinates":[-1.8344089985,52.6557312012],"type":"Point"}
}