{
  "type": "Feature",
  "properties": {
    "iso:country":"GB",
    "sg:address":"22 Palace Gates Rd",
    "sg:city":"London",
    "sg:classifiers":[
        {
            "category":"Bars & Pubs",
            "type":"Food & Drink"
        }
    ],
    "sg:phone":"+44 20 8889 0468",
    "sg:postcode":"N22 7BN",
    "sg:province":"Greater London",
    "sg:tags":[
        "pubs",
        "inn"
    ],
    "wof:name":"Palace Gates",
    "wof:placetype":"venue"
},
  "geometry": {"coordinates":[-0.122871,51.598923],"type":"Point"}
}