{
  "type": "Feature",
  "properties": {
    "addr:full":"Earleydene Orchard, Earleydene Ascot Berkshire SL5 9JY",
    "addr:postcode":"sl5 9jy",
    "iso:country":"GB",
    "sg:address":"Earleydene Orchard, Earleydene",
    "sg:city":"Ascot",
    "sg:classifiers":[
        {
            "category":"Building & Trades",
            "subcategory":"Landscaping Services",
            "type":"Services"
        }
    ],
    "sg:phone":"+44 1344 626523",
    "sg:postcode":"SL5 9JY",
    "sg:province":"Berkshire",
    "sg:tags":[
        "gardening"
    ],
    "wof:name":"Watson Wight",
    "wof:placetype":"venue"
},
  "geometry": {"coordinates":[-0.66725,51.386875],"type":"Point"}
}