{
  "type": "Feature",
  "properties": {
    "addr:full":"3 Fayrefield Road, Melton Woodbridge Suffolk IP12 1NX",
    "addr:housenumber":"3",
    "addr:postcode":"ip12 1nx",
    "addr:street":"Fayrefield Road",
    "iso:country":"GB",
    "sg:address":"3 Fayrefield Road, Melton",
    "sg:city":"Woodbridge",
    "sg:classifiers":[
        {
            "category":"Freight",
            "type":"Transportation"
        }
    ],
    "sg:phone":"+44 1394 384861",
    "sg:postcode":"IP12 1NX",
    "sg:province":"Suffolk",
    "sg:tags":[
        "haulage",
        "road"
    ],
    "wof:name":"D W Everard Transport",
    "wof:placetype":"venue"
},
  "geometry": {"coordinates":[1.3276540041,52.1016731262],"type":"Point"}
}