{
  "type": "Feature",
  "properties": {
    "iso:country":"GB",
    "sg:address":"30d Catisfield Lane",
    "sg:city":"Fareham",
    "sg:classifiers":[
        {
            "category":"Shopping",
            "subcategory":"Clothing, Apparel, & Fashions",
            "type":"Retail Goods"
        }
    ],
    "sg:phone":"+44 1329 512835",
    "sg:postcode":"PO15 5NN",
    "sg:province":"Hampshire",
    "sg:tags":[
        "t-shirt"
    ],
    "wof:name":"Sunshine Promotions Screen Printing",
    "wof:placetype":"venue"
},
  "geometry": {"coordinates":[-1.221854,50.853344],"type":"Point"}
}