{
  "type": "Feature",
  "properties": {
    "addr:full":"Unit 7 Plasmarl Indstl Est, Beaufort Rd Swansea Swansea SA6 8EY",
    "addr:housenumber":"unit 7",
    "addr:postcode":"sa6 8ey",
    "addr:street":"Indstl;Beaufort Rd",
    "iso:country":"GB",
    "sg:address":"Unit 7 Plasmarl Indstl Est, Beaufort Rd",
    "sg:city":"Swansea",
    "sg:classifiers":[
        {
            "category":"Manufacturing",
            "subcategory":"Petroleum Products",
            "type":"Manufacturing & Wholesale Goods"
        }
    ],
    "sg:postcode":"SA6 8EY",
    "sg:province":"Swansea",
    "sg:tags":[
        "double",
        "glazing"
    ],
    "wof:name":"Limbert,Rodney,",
    "wof:placetype":"venue"
},
  "geometry": {"coordinates":[-3.9282999039,51.6513786316],"type":"Point"}
}