{
  "type": "Feature",
  "properties": {
    "iso:country":"GB",
    "sg:address":"Keyford House, Dorchester Rd",
    "sg:city":"Yeovil",
    "sg:classifiers":[
        {
            "category":"Professional",
            "subcategory":"Detective & Security Services",
            "type":"Services"
        }
    ],
    "sg:phone":"+44 1935 433770",
    "sg:postcode":"BA22 9RA",
    "sg:province":"Dorset",
    "sg:tags":[
        "activity"
    ],
    "wof:name":"Aide Memoire",
    "wof:placetype":"venue"
},
  "geometry": {"coordinates":[-2.6244189739,50.9103507996],"type":"Point"}
}