{
  "type": "Feature",
  "properties": {
    "addr:full":"32 Redhouse Road Bathgate North Lanarkshire EH47 7BS",
    "addr:housenumber":"32",
    "addr:postcode":"eh47 7bs",
    "addr:street":"Redhouse Road Bathgate",
    "iso:country":"GB",
    "sg:address":"32 Redhouse Road",
    "sg:city":"Bathgate",
    "sg:classifiers":[
        {
            "category":"Building & Trades",
            "subcategory":"Cleaning & Sanitation",
            "type":"Services"
        }
    ],
    "sg:phone":"+44 1506 633550",
    "sg:postcode":"EH47 7BS",
    "sg:province":"North Lanarkshire",
    "sg:tags":[
        "steam"
    ],
    "wof:name":"R D Services",
    "wof:placetype":"venue"
},
  "geometry": {"coordinates":[-3.592559,55.877464],"type":"Point"}
}