{
  "type": "Feature",
  "properties": {
    "iso:country":"GB",
    "sg:address":"14d Hampton Road",
    "sg:city":"Teddington",
    "sg:classifiers":[
        {
            "category":"Professional",
            "subcategory":"Accounting & Tax Preparation",
            "type":"Services"
        }
    ],
    "sg:phone":"+44 20 8287 5528",
    "sg:postcode":"TW11 0JW",
    "sg:province":"Greater London",
    "sg:tags":[
        "accountant"
    ],
    "wof:name":"Wondertrade Ltd.",
    "wof:placetype":"venue"
},
  "geometry": {"coordinates":[-0.342572,51.426991],"type":"Point"}
}