{
  "type": "Feature",
  "properties": {
    "iso:country":"GB",
    "sg:address":"21 Riffhams Drive, Great Baddow",
    "sg:city":"Chelmsford",
    "sg:classifiers":[
        {
            "category":"Social Services",
            "subcategory":"Child Care",
            "type":"Services"
        }
    ],
    "sg:phone":"+44 1245 471114",
    "sg:postcode":"CM2 7DE",
    "sg:province":"Essex",
    "sg:tags":[
        "childminders"
    ],
    "wof:name":"Dawn Cotterill",
    "wof:placetype":"venue"
},
  "geometry": {"coordinates":[0.5042610168,51.7202835083],"type":"Point"}
}