{
  "type": "Feature",
  "properties": {
    "iso:country":"GB",
    "sg:address":"Cuxton Industrial Estate, Station Road, Cuxton",
    "sg:city":"Rochester",
    "sg:classifiers":[
        {
            "category":"Home & Garden",
            "subcategory":"Kitchen Supply",
            "type":"Retail Goods"
        }
    ],
    "sg:phone":"+44 1634 721942",
    "sg:postcode":"ME2 1AB",
    "sg:province":"Kent",
    "sg:tags":[
        "equipment",
        "brewer"
    ],
    "wof:name":"Brupart Ltd.",
    "wof:placetype":"venue"
},
  "geometry": {"coordinates":[0.4577940106,51.3730621338],"type":"Point"}
}