{
  "type": "Feature",
  "properties": {
    "addr:full":"4 Champion Hill Camberwell Greater London SE5 8AP",
    "addr:housenumber":"4",
    "addr:postcode":"se5 8ap",
    "addr:street":"Champion Hill",
    "iso:country":"GB",
    "sg:address":"4 Champion Hill",
    "sg:city":"Camberwell",
    "sg:classifiers":[
        {
            "category":"Community Center",
            "subcategory":"Youth",
            "type":"Public Place"
        }
    ],
    "sg:phone":"+44 20 7737 7910",
    "sg:postcode":"SE5 8AP",
    "sg:province":"Greater London",
    "sg:tags":[
        "organisation",
        "centre"
    ],
    "wof:name":"343 Camberwell Squadron Air Training Corps",
    "wof:placetype":"venue"
},
  "geometry": {"coordinates":[-0.084596,51.464455],"type":"Point"}
}