{
  "type": "Feature",
  "properties": {
    "iso:country":"GB",
    "sg:address":"5 Victoria Road",
    "sg:city":"Malton",
    "sg:classifiers":[
        {
            "category":"Professional",
            "subcategory":"Business Services",
            "type":"Services"
        }
    ],
    "sg:postcode":"YO17 7JJ",
    "sg:province":"North Yorkshire",
    "sg:tags":[
        "import",
        "export",
        "agent"
    ],
    "wof:name":"Derventio Ltd.",
    "wof:placetype":"venue"
},
  "geometry": {"coordinates":[-0.800891,54.136448],"type":"Point"}
}