{
  "type": "Feature",
  "properties": {
    "addr:full":"1 Powells Crescent Scunthorpe Lincolnshire DN16 3DN",
    "addr:housenumber":"1",
    "addr:postcode":"dn16 3dn",
    "addr:street":"Powells Crescent",
    "iso:country":"GB",
    "sg:address":"1 Powells Crescent",
    "sg:city":"Scunthorpe",
    "sg:classifiers":[
        {
            "category":"Building & Trades",
            "subcategory":"Cleaning & Sanitation",
            "type":"Services"
        },
        {
            "category":"Home & Garden",
            "subcategory":"Carpets & Floor Coverings",
            "type":"Retail Goods"
        }
    ],
    "sg:phone":"+44 1724 852053",
    "sg:postcode":"DN16 3DN",
    "sg:province":"Lincolnshire",
    "sg:tags":[
        "cleaner",
        "upholstery"
    ],
    "wof:name":"Ashby Cleaning Services",
    "wof:placetype":"venue"
},
  "geometry": {"coordinates":[-0.642954,53.565712],"type":"Point"}
}