{
  "type": "Feature",
  "properties": {
    "addr:full":"North Lane, West Hoathly East Grinstead East Sussex RH19 4QG",
    "addr:postcode":"rh19 4qg",
    "addr:street":"North Lane",
    "iso:country":"GB",
    "sg:address":"North Lane, West Hoathly",
    "sg:city":"East Grinstead",
    "sg:classifiers":[
        {
            "category":"Food & Beverages",
            "subcategory":"Fruits & Vegetables",
            "type":"Retail Goods"
        }
    ],
    "sg:phone":"+44 1342 810353",
    "sg:postcode":"RH19 4QG",
    "sg:province":"East Sussex",
    "sg:tags":[
        "greengrocer"
    ],
    "wof:name":"R Ashby",
    "wof:placetype":"venue"
},
  "geometry": {"coordinates":[-0.0534109995,51.0793151855],"type":"Point"}
}