{
  "type": "Feature",
  "properties": {
    "iso:country":"GB",
    "sg:address":"34 Gregories Rd",
    "sg:city":"Beaconsfield",
    "sg:classifiers":[
        {
            "category":"Fast Food",
            "type":"Food & Drink"
        }
    ],
    "sg:phone":"+44 1494 671288",
    "sg:postcode":"HP9 1HQ",
    "sg:province":"Buckinghamshire",
    "sg:tags":[
        "away",
        "meal",
        "outlet",
        "take"
    ],
    "wof:name":"Tao Takeaway",
    "wof:placetype":"venue"
},
  "geometry": {"coordinates":[-0.647307,51.610611],"type":"Point"}
}