{
  "type": "Feature",
  "properties": {
    "addr:full":"27 Waterloo Street, Clifton Bristol City of Bristol BS8 4BT",
    "addr:housenumber":"27",
    "addr:postcode":"bs8 4bt",
    "addr:street":"Waterloo Street",
    "iso:country":"GB",
    "sg:address":"27 Waterloo Street, Clifton",
    "sg:city":"Bristol",
    "sg:classifiers":[
        {
            "category":"Professional",
            "subcategory":"Art Services",
            "type":"Services"
        }
    ],
    "sg:postcode":"BS8 4BT",
    "sg:province":"City of Bristol",
    "sg:tags":[
        "framing"
    ],
    "wof:name":"Sky",
    "wof:placetype":"venue"
},
  "geometry": {"coordinates":[-2.619872,51.454868],"type":"Point"}
}