{
  "type": "Feature",
  "properties": {
    "addr:full":"13 Wellington Avenue Wolverhampton Staffordshire WV3 7EP",
    "addr:housenumber":"13",
    "addr:postcode":"wv3 7ep",
    "addr:street":"Wellington Avenue",
    "iso:country":"GB",
    "sg:address":"13 Wellington Avenue",
    "sg:city":"Wolverhampton",
    "sg:classifiers":[
        {
            "category":"Building & Trades",
            "subcategory":"Plumbing",
            "type":"Services"
        }
    ],
    "sg:phone":"+44 1902 344776",
    "sg:postcode":"WV3 7EP",
    "sg:province":"Staffordshire",
    "sg:tags":[
        "heating"
    ],
    "wof:name":"Dave Jones Plumbing & Heating",
    "wof:placetype":"venue"
},
  "geometry": {"coordinates":[-2.155,52.573429],"type":"Point"}
}