{
  "type": "Feature",
  "properties": {
    "addr:full":"9 The Progression Centre, Mark Road, Hemel Hempstead Industrial Estat Hemel Hempstead Hertfordshire HP2 7DW",
    "addr:housenumber":"9",
    "addr:postcode":"hp2 7dw",
    "addr:street":"Mark Road;Hempstead",
    "iso:country":"GB",
    "sg:address":"9 The Progression Centre, Mark Road, Hemel Hempstead Industrial Estat",
    "sg:city":"Hemel Hempstead",
    "sg:classifiers":[
        {
            "category":"Professional",
            "type":"Services"
        }
    ],
    "sg:phone":"+44 1442 239015",
    "sg:postcode":"HP2 7DW",
    "sg:province":"Hertfordshire",
    "sg:tags":[
        "repair",
        "tech",
        "maintenance"
    ],
    "wof:name":"Effective Computer Solutions Ltd.",
    "wof:placetype":"venue"
},
  "geometry": {"coordinates":[-0.438657999,51.7620239258],"type":"Point"}
}