{
  "type": "Feature",
  "properties": {
    "addr:full":"8 Church Street Cramlington Northumberland NE23 6QQ",
    "addr:housenumber":"8",
    "addr:postcode":"ne23 6qq",
    "addr:street":"Church Street;Northumberland",
    "iso:country":"GB",
    "sg:address":"8 Church Street",
    "sg:city":"Cramlington",
    "sg:classifiers":[
        {
            "category":"Health Services",
            "subcategory":"Dentist",
            "type":"Services"
        }
    ],
    "sg:phone":"+44 1670 716671",
    "sg:postcode":"NE23 6QQ",
    "sg:province":"Northumberland",
    "wof:name":"R Hurst",
    "wof:placetype":"venue"
},
  "geometry": {"coordinates":[-1.564857,55.078117],"type":"Point"}
}