{
  "type": "Feature",
  "properties": {
    "iso:country":"GB",
    "sg:address":"93-95 Hyndland Street",
    "sg:city":"Glasgow",
    "sg:classifiers":[
        {
            "category":"Restaurant",
            "type":"Food & Drink"
        }
    ],
    "sg:phone":"+44 141 357 5827",
    "sg:postcode":"G11 5PX",
    "sg:province":"Glasgow City",
    "sg:tags":[
        "mexican"
    ],
    "wof:name":"Cottier's",
    "wof:placetype":"venue"
},
  "geometry": {"coordinates":[-4.3019599915,55.8736305237],"type":"Point"}
}