{
  "type": "Feature",
  "properties": {
    "iso:country":"GB",
    "sg:address":"Mansfield Rd",
    "sg:city":"Balerno",
    "sg:classifiers":[
        {
            "category":"Education",
            "subcategory":"School",
            "type":"Public Place"
        }
    ],
    "sg:phone":"+44 131 449 5002",
    "sg:postcode":"EH14 7JY",
    "sg:province":"City of Edinburgh",
    "sg:tags":[
        "college"
    ],
    "wof:name":"Harmeny School",
    "wof:placetype":"venue"
},
  "geometry": {"coordinates":[-3.346687,55.883175],"type":"Point"}
}