{
  "type": "Feature",
  "properties": {
    "addr:full":"Greenacres Farm, Elsted Midhurst West Sussex GU29 0JT",
    "addr:postcode":"gu29 0jt",
    "iso:country":"GB",
    "sg:address":"Greenacres Farm, Elsted",
    "sg:city":"Midhurst",
    "sg:classifiers":[
        {
            "category":"Farming",
            "subcategory":"Poultry Farm",
            "type":"Manufacturing & Wholesale Goods"
        }
    ],
    "sg:phone":"+44 1730 813624",
    "sg:postcode":"GU29 0JT",
    "sg:province":"West Sussex",
    "sg:tags":[
        "game"
    ],
    "wof:name":"D G Barnes",
    "wof:placetype":"venue"
},
  "geometry": {"coordinates":[-0.8394060135,50.9698104858],"type":"Point"}
}