{
  "type": "Feature",
  "properties": {
    "iso:country":"GB",
    "sg:address":"82 Guildford Road",
    "sg:city":"Lightwater",
    "sg:classifiers":[
        {
            "category":"Health Services",
            "subcategory":"Dentist",
            "type":"Services"
        }
    ],
    "sg:postcode":"GU18 5RY",
    "sg:province":"Surrey",
    "wof:name":"Orchard Cottage Dental Surgery",
    "wof:placetype":"venue"
},
  "geometry": {"coordinates":[-0.66507,51.351742],"type":"Point"}
}