{
  "type": "Feature",
  "properties": {
    "addr:full":"177 Battersea High Street London Greater London SW11 3JS",
    "addr:housenumber":"177",
    "addr:postcode":"sw11 3js",
    "addr:street":"Battersea High Street",
    "iso:country":"GB",
    "sg:address":"177 Battersea High Street",
    "sg:city":"London",
    "sg:classifiers":[
        {
            "category":"Real Estate",
            "subcategory":"Surveying",
            "type":"Services"
        },
        {
            "category":"Real Estate",
            "subcategory":"Architect",
            "type":"Services"
        }
    ],
    "sg:phone":"+44 20 7223 7446",
    "sg:postcode":"SW11 3JS",
    "sg:province":"Greater London",
    "sg:tags":[
        "surveyor",
        "valuer"
    ],
    "wof:name":"Cook Steed Associates",
    "wof:placetype":"venue"
},
  "geometry": {"coordinates":[-0.173281,51.472763],"type":"Point"}
}