{
  "type": "Feature",
  "properties": {
    "addr:full":"Clough Lane Halifax West Yorkshire HX2 8SH",
    "addr:postcode":"hx2 8sh",
    "addr:street":"Clough Lane",
    "iso:country":"GB",
    "sg:address":"Clough Lane",
    "sg:city":"Halifax",
    "sg:classifiers":[
        {
            "category":"Community Center",
            "subcategory":"Youth",
            "type":"Public Place"
        }
    ],
    "sg:phone":"+44 1422 244609",
    "sg:postcode":"HX2 8SH",
    "sg:province":"West Yorkshire",
    "sg:tags":[
        "organisation",
        "centre"
    ],
    "wof:name":"Mixenden Youth & Community Centre",
    "wof:placetype":"venue"
},
  "geometry": {"coordinates":[-1.9094699621,53.7537193298],"type":"Point"}
}