{
  "type": "Feature",
  "properties": {
    "addr:full":"Unit 9 Ninian Park, Ninian Way, Wilnecote Tamworth Staffordshire B77 5ES",
    "addr:housenumber":"unit 9",
    "addr:postcode":"b77 5es",
    "addr:street":"Ninian Park Ninian Way",
    "iso:country":"GB",
    "sg:address":"Unit 9 Ninian Park, Ninian Way, Wilnecote",
    "sg:city":"Tamworth",
    "sg:classifiers":[
        {
            "category":"Recreation",
            "subcategory":"Amusement Park",
            "type":"Entertainment"
        },
        {
            "category":"Autos & Motor Vehicles",
            "subcategory":"Boat Sales",
            "type":"Retail Goods"
        }
    ],
    "sg:phone":"+44 1827 288600",
    "sg:postcode":"B77 5ES",
    "sg:province":"Staffordshire",
    "sg:tags":[
        "machine",
        "gaming",
        "arcade"
    ],
    "wof:name":"Premier Automatic Machines Ltd",
    "wof:placetype":"venue"
},
  "geometry": {"coordinates":[-1.676449,52.60181],"type":"Point"}
}