{
  "type": "Feature",
  "properties": {
    "addr:full":"53 Montagu Street Kettering Northamptonshire NN16 8XQ",
    "addr:housenumber":"53",
    "addr:postcode":"nn16 8xq",
    "addr:street":"Montagu Street",
    "iso:country":"GB",
    "sg:address":"53 Montagu Street",
    "sg:city":"Kettering",
    "sg:classifiers":[
        {
            "category":"Fast Food",
            "type":"Food & Drink"
        }
    ],
    "sg:phone":"+44 1536 392020",
    "sg:postcode":"NN16 8XQ",
    "sg:province":"Northamptonshire",
    "sg:tags":[
        "away",
        "take"
    ],
    "wof:name":"Pizza Shed",
    "wof:placetype":"venue"
},
  "geometry": {"coordinates":[-0.7223970294,52.4017181396],"type":"Point"}
}