{
  "type": "Feature",
  "properties": {
    "addr:full":"12 Balcarres Terr Dundee Dundee City DD4 8QX",
    "addr:housenumber":"12",
    "addr:postcode":"dd4 8qx",
    "addr:street":"Balcarres Terr",
    "iso:country":"GB",
    "sg:address":"12 Balcarres Terr",
    "sg:city":"Dundee",
    "sg:classifiers":[
        {
            "category":"Social Services",
            "subcategory":"Adult Care",
            "type":"Services"
        }
    ],
    "sg:phone":"+44 1382 776963",
    "sg:postcode":"DD4 8QX",
    "sg:province":"Dundee City",
    "sg:tags":[
        "housing",
        "sheltered"
    ],
    "wof:name":"Balcarres Sheltered Housing",
    "wof:placetype":"venue"
},
  "geometry": {"coordinates":[-2.90815,56.4799],"type":"Point"}
}