{
  "type": "Feature",
  "properties": {
    "addr:full":"Beech Av Harrogate North Yorkshire HG2 8DS",
    "addr:postcode":"hg2 8ds",
    "addr:street":"Beech Av",
    "iso:country":"GB",
    "sg:address":"Beech Av",
    "sg:city":"Harrogate",
    "sg:classifiers":[
        {
            "category":"Shopping",
            "subcategory":"Clothing, Apparel, & Fashions",
            "type":"Retail Goods"
        }
    ],
    "sg:phone":"+44 1423 874515",
    "sg:postcode":"HG2 8DS",
    "sg:province":"North Yorkshire",
    "sg:tags":[
        "clothing",
        "fabric"
    ],
    "wof:name":"Brindley James",
    "wof:placetype":"venue"
},
  "geometry": {"coordinates":[-1.5288139582,53.9768295288],"type":"Point"}
}