{
  "type": "Feature",
  "properties": {
    "addr:full":"Maritime House, North Crescent Road Ardrossan North Ayrshire KA22 8LR",
    "addr:postcode":"ka22 8lr",
    "addr:street":"North Crescent Road",
    "iso:country":"GB",
    "sg:address":"Maritime House, North Crescent Road",
    "sg:city":"Ardrossan",
    "sg:classifiers":[
        {
            "category":"Professional",
            "subcategory":"Computer Services",
            "type":"Services"
        }
    ],
    "sg:postcode":"KA22 8LR",
    "sg:province":"North Ayrshire",
    "sg:tags":[
        "bureau",
        "facility"
    ],
    "wof:name":"Saztec Europe Ltd.",
    "wof:placetype":"venue"
},
  "geometry": {"coordinates":[-4.8173389435,55.6504898071],"type":"Point"}
}