{
  "type": "Feature",
  "properties": {
    "iso:country":"GB",
    "sg:address":"Benfield Motors, Portland Road",
    "sg:city":"Newcastle-upon-tyne",
    "sg:classifiers":[
        {
            "category":"Retail",
            "subcategory":"Auto Rental",
            "type":"Services"
        }
    ],
    "sg:postcode":"NE2 1AR",
    "sg:province":"Tyne and Wear",
    "sg:tags":[
        "car",
        "hire",
        "truck"
    ],
    "wof:name":"Rosedale Finance & Leasing Ltd.",
    "wof:placetype":"venue"
},
  "geometry": {"coordinates":[-1.5998599529,54.9798088074],"type":"Point"}
}