{
  "type": "Feature",
  "properties": {
    "addr:full":"Leicester Rd Leicester Leicestershire LE2 5BD",
    "addr:postcode":"le2 5bd",
    "addr:street":"Leicester Rd",
    "iso:country":"GB",
    "sg:address":"Leicester Rd",
    "sg:city":"Leicester",
    "sg:classifiers":[
        {
            "category":"Place Of Worship",
            "type":"Public Place"
        }
    ],
    "sg:phone":"+44 116 271 2300",
    "sg:postcode":"LE2 5BD",
    "sg:province":"Leicestershire",
    "wof:name":"Oadby Baptist Church",
    "wof:placetype":"venue"
},
  "geometry": {"coordinates":[-1.083301,52.598675],"type":"Point"}
}