{
  "type": "Feature",
  "properties": {
    "iso:country":"GB",
    "sg:address":"49 The Avenue",
    "sg:city":"Prestatyn",
    "sg:classifiers":[
        {
            "category":"Health Services",
            "subcategory":"Hospital",
            "type":"Services"
        }
    ],
    "sg:phone":"+44 1745 887812",
    "sg:postcode":"LL19 9RD",
    "sg:province":"Denbighshire",
    "wof:name":"Prestatyn Community Hospital",
    "wof:placetype":"venue"
},
  "geometry": {"coordinates":[-3.4010589123,53.3259086609],"type":"Point"}
}