{
  "type": "Feature",
  "properties": {
    "iso:country":"GB",
    "sg:address":"1 Harwood Meadow",
    "sg:city":"Bolton",
    "sg:classifiers":[
        {
            "category":"Building & Trades",
            "subcategory":"Construction",
            "type":"Services"
        }
    ],
    "sg:phone":"+44 1204 394800",
    "sg:postcode":"BL2 3QP",
    "sg:province":"Lancashire",
    "sg:tags":[
        "builder"
    ],
    "wof:name":"A Class Builders",
    "wof:placetype":"venue"
},
  "geometry": {"coordinates":[-2.384237,53.598309],"type":"Point"}
}