{
  "type": "Feature",
  "properties": {
    "iso:country":"GB",
    "sg:address":"10 Wheatsheaf Way, Linton",
    "sg:city":"Cambridge",
    "sg:classifiers":[
        {
            "category":"Professional",
            "subcategory":"Detective & Security Services",
            "type":"Services"
        }
    ],
    "sg:phone":"+44 1223 892806",
    "sg:postcode":"CB1 6XB",
    "sg:province":"Cambridgeshire",
    "wof:name":"The Home Service",
    "wof:placetype":"venue"
},
  "geometry": {"coordinates":[0.2913739979,52.0987548828],"type":"Point"}
}