{
  "type": "Feature",
  "properties": {
    "addr:full":"12 King Street Carmarthen Carmarthenshire SA31 1BH",
    "addr:housenumber":"12",
    "addr:postcode":"sa31 1bh",
    "addr:street":"King Street",
    "iso:country":"GB",
    "sg:address":"12 King Street",
    "sg:city":"Carmarthen",
    "sg:classifiers":[
        {
            "category":"Organizations",
            "subcategory":"Non-profit Organization",
            "type":"Services"
        }
    ],
    "sg:phone":"+44 1267 223365",
    "sg:postcode":"SA31 1BH",
    "sg:province":"Carmarthenshire",
    "sg:tags":[
        "organisation",
        "voluntary",
        "charity"
    ],
    "wof:name":"National Schizophrenia Fellowship",
    "wof:placetype":"venue"
},
  "geometry": {"coordinates":[-4.304379,51.857616],"type":"Point"}
}