{
  "type": "Feature",
  "properties": {
    "iso:country":"GB",
    "sg:address":"1 Cullarnie Road",
    "sg:city":"Inverness",
    "sg:classifiers":[
        {
            "category":"Building & Trades",
            "subcategory":"Landscaping Services",
            "type":"Services"
        },
        {
            "category":"Building & Trades",
            "subcategory":"Construction",
            "type":"Services"
        }
    ],
    "sg:phone":"+44 1463 791803",
    "sg:postcode":"IV2 7HF",
    "sg:province":"Highland",
    "sg:tags":[
        "preservation",
        "timber"
    ],
    "wof:name":"K  Macvicark",
    "wof:placetype":"venue"
},
  "geometry": {"coordinates":[-4.109315,57.495712],"type":"Point"}
}