{
  "type": "Feature",
  "properties": {
    "iso:country":"GB",
    "sg:address":"23 Rokeby Court",
    "sg:city":"Woking",
    "sg:classifiers":[
        {
            "category":"Taxi",
            "type":"Transportation"
        },
        {
            "category":"Military Area",
            "subcategory":"Air Force Base",
            "type":"Public Place"
        }
    ],
    "sg:phone":"+44 1483 480004",
    "sg:postcode":"GU21 8AS",
    "sg:province":"Surrey",
    "sg:tags":[
        "hire",
        "private"
    ],
    "wof:name":"A A TAXIS",
    "wof:placetype":"venue"
},
  "geometry": {"coordinates":[-0.60178,51.317421],"type":"Point"}
}