{
  "type": "Feature",
  "properties": {
    "addr:full":"Jubilee Centre, Room M, 10-12 Lombard Road London Greater London SW19 3TZ",
    "addr:housenumber":"10-12",
    "addr:postcode":"sw19 3tz",
    "addr:street":"Lombard Road",
    "iso:country":"GB",
    "sg:address":"Jubilee Centre, Room M, 10-12 Lombard Road",
    "sg:city":"London",
    "sg:classifiers":[
        {
            "category":"Professional",
            "type":"Services"
        }
    ],
    "sg:phone":"+44 20 8543 6596",
    "sg:postcode":"SW19 3TZ",
    "sg:province":"Greater London",
    "sg:tags":[
        "specialist",
        "coating"
    ],
    "wof:name":"Wallcote Ltd.",
    "wof:placetype":"venue"
},
  "geometry": {"coordinates":[-0.19045,51.409279],"type":"Point"}
}