{
  "type": "Feature",
  "properties": {
    "iso:country":"GB",
    "sg:address":"104 West Road, Shoeburyness",
    "sg:city":"Southend-on-sea",
    "sg:classifiers":[
        {
            "category":"Food & Beverages",
            "subcategory":"Meat & Fish",
            "type":"Retail Goods"
        }
    ],
    "sg:phone":"+44 1702 293380",
    "sg:postcode":"SS3 9DS",
    "sg:province":"Essex",
    "sg:tags":[
        "chip"
    ],
    "wof:name":"West Road Fish Shop",
    "wof:placetype":"venue"
},
  "geometry": {"coordinates":[0.780399,51.530613],"type":"Point"}
}