{
  "type": "Feature",
  "properties": {
    "iso:country":"GB",
    "sg:address":"128 Boden Street",
    "sg:city":"Glasgow",
    "sg:classifiers":[
        {
            "category":"Autos & Motor Vehicles",
            "subcategory":"Auto Supplies",
            "type":"Retail Goods"
        }
    ],
    "sg:phone":"+44 141 554 6594",
    "sg:postcode":"G40 3QD",
    "sg:province":"Glasgow City",
    "sg:tags":[
        "tyre"
    ],
    "wof:name":"National Tyres and Autocare",
    "wof:placetype":"venue"
},
  "geometry": {"coordinates":[-4.214799881,55.8456268311],"type":"Point"}
}