{
  "type": "Feature",
  "properties": {
    "addr:full":"11 Gladstone Pl Stirling Stirling FK8 2NN",
    "addr:housenumber":"11",
    "addr:postcode":"fk8 2nn",
    "addr:street":"Gladstone Pl",
    "iso:country":"GB",
    "sg:address":"11 Gladstone Pl",
    "sg:city":"Stirling",
    "sg:classifiers":[
        {
            "category":"Government",
            "subcategory":"Office",
            "type":"Public Place"
        }
    ],
    "sg:phone":"+44 1786 463812",
    "sg:postcode":"FK8 2NN",
    "sg:province":"Stirling",
    "sg:tags":[
        "local"
    ],
    "wof:name":"Criminal Justice Service",
    "wof:placetype":"venue"
},
  "geometry": {"coordinates":[-3.9425690174,56.1120605469],"type":"Point"}
}