{
  "type": "Feature",
  "properties": {
    "addr:full":"158 Allport Rd Wirral Cheshire CH62 6BB",
    "addr:housenumber":"158",
    "addr:postcode":"ch62 6bb",
    "addr:street":"Allport Rd",
    "iso:country":"GB",
    "sg:address":"158 Allport Rd",
    "sg:city":"Wirral",
    "sg:classifiers":[
        {
            "category":"Government",
            "subcategory":"Post Office",
            "type":"Public Place"
        }
    ],
    "sg:phone":"+44 151 343 1932",
    "sg:postcode":"CH62 6BB",
    "sg:province":"Cheshire",
    "wof:name":"Allport Road Sub Post Office",
    "wof:placetype":"venue"
},
  "geometry": {"coordinates":[-2.984347105,53.3223228455],"type":"Point"}
}