{
  "type": "Feature",
  "properties": {
    "addr:full":"West Sleekburn Works, West Sleekburn Bedlington Northumberland NE22 7DJ",
    "addr:postcode":"ne22 7dj",
    "addr:street":"West;West Sleekburn",
    "iso:country":"GB",
    "sg:address":"West Sleekburn Works, West Sleekburn",
    "sg:city":"Bedlington",
    "sg:classifiers":[
        {
            "category":"Freight",
            "type":"Transportation"
        }
    ],
    "sg:phone":"+44 1670 823153",
    "sg:postcode":"NE22 7DJ",
    "sg:province":"Northumberland",
    "sg:tags":[
        "haulage",
        "road"
    ],
    "wof:name":"T James (Bedlington) Ltd.",
    "wof:placetype":"venue"
},
  "geometry": {"coordinates":[-1.5537910461,55.1573448181],"type":"Point"}
}