{
  "type": "Feature",
  "properties": {
    "iso:country":"GB",
    "sg:address":"17-21 Chorlton St",
    "sg:city":"Manchester",
    "sg:classifiers":[
        {
            "category":"Government",
            "subcategory":"Office",
            "type":"Public Place"
        }
    ],
    "sg:phone":"+44 161 934 5400",
    "sg:postcode":"M1 3HY",
    "sg:province":"Greater Manchester",
    "sg:tags":[
        "central"
    ],
    "wof:name":"Insolvency Service",
    "wof:placetype":"venue"
},
  "geometry": {"coordinates":[-2.236319,53.477779],"type":"Point"}
}