{
  "type": "Feature",
  "properties": {
    "iso:country":"GB",
    "sg:address":"Loverstone Works, Chillerton",
    "sg:city":"Newport",
    "sg:classifiers":[
        {
            "category":"Home & Garden",
            "subcategory":"Building Materials",
            "type":"Retail Goods"
        }
    ],
    "sg:phone":"+44 1983 721457",
    "sg:postcode":"PO30 3EL",
    "sg:province":"Isle of Wight",
    "sg:tags":[
        "dust",
        "extraction",
        "system"
    ],
    "wof:name":"Zeta Flow Ltd",
    "wof:placetype":"venue"
},
  "geometry": {"coordinates":[-1.306129,50.656586],"type":"Point"}
}