{
  "type": "Feature",
  "properties": {
    "iso:country":"GB",
    "sg:address":"34 Meadow Road",
    "sg:city":"Wolverhampton",
    "sg:classifiers":[
        {
            "category":"Building & Trades",
            "subcategory":"Plumbing",
            "type":"Services"
        }
    ],
    "sg:postcode":"WV3 8EZ",
    "sg:province":"Staffordshire",
    "sg:tags":[
        "heating"
    ],
    "wof:name":"Trevor Hobbs",
    "wof:placetype":"venue"
},
  "geometry": {"coordinates":[-2.171890974,52.5783348083],"type":"Point"}
}