{
  "type": "Feature",
  "properties": {
    "iso:country":"GB",
    "sg:address":"Health Centre, Gotham Rd",
    "sg:city":"Loughborough",
    "sg:classifiers":[
        {
            "category":"Health Services",
            "subcategory":"Dentist",
            "type":"Services"
        }
    ],
    "sg:phone":"+44 1509 856041",
    "sg:postcode":"LE12 6JG",
    "sg:province":"Leicestershire",
    "wof:name":"M Hewitt",
    "wof:placetype":"venue"
},
  "geometry": {"coordinates":[-1.17709,52.83403],"type":"Point"}
}