{
  "type": "Feature",
  "properties": {
    "iso:country":"GB",
    "sg:address":"Heydons Lane",
    "sg:city":"Sidmouth",
    "sg:classifiers":[
        {
            "category":"Arena",
            "subcategory":"Sports Club",
            "type":"Entertainment"
        }
    ],
    "sg:phone":"+44 1392 252016",
    "sg:postcode":"EX10 8NJ",
    "sg:province":"Devon",
    "wof:name":"Sidmouth Rugby Club",
    "wof:placetype":"venue"
},
  "geometry": {"coordinates":[-3.241184,50.680229],"type":"Point"}
}