{
  "type": "Feature",
  "properties": {
    "addr:full":"92 Hill Street, Burnbank Hamilton South Lanarkshire ML3 9LH",
    "addr:housenumber":"92",
    "addr:postcode":"ml3 9lh",
    "addr:street":"Hill Street",
    "iso:country":"GB",
    "sg:address":"92 Hill Street, Burnbank",
    "sg:city":"Hamilton",
    "sg:classifiers":[
        {
            "category":"Building & Trades",
            "subcategory":"Construction",
            "type":"Services"
        }
    ],
    "sg:phone":"+44 1698 829039",
    "sg:postcode":"ML3 9LH",
    "sg:province":"South Lanarkshire",
    "sg:tags":[
        "roofing"
    ],
    "wof:name":"K S G Roofing",
    "wof:placetype":"venue"
},
  "geometry": {"coordinates":[-4.077162,55.774822],"type":"Point"}
}