{
  "type": "Feature",
  "properties": {
    "iso:country":"GB",
    "sg:address":"Ochrwyth, Risca",
    "sg:city":"Newport",
    "sg:classifiers":[
        {
            "category":"Shopping",
            "subcategory":"Pets & Pet Supplies",
            "type":"Retail Goods"
        }
    ],
    "sg:postcode":"NP11 6EL",
    "sg:province":"Blaenau Gwent",
    "wof:name":"Lascoed Boarding Kennels & Cattery",
    "wof:placetype":"venue"
},
  "geometry": {"coordinates":[-3.100178,51.606739],"type":"Point"}
}