{
  "type": "Feature",
  "properties": {
    "iso:country":"GB",
    "sg:address":"103 Elm Gro",
    "sg:city":"Southsea",
    "sg:classifiers":[
        {
            "category":"Cinema",
            "subcategory":"Movie Rental",
            "type":"Entertainment"
        }
    ],
    "sg:postcode":"PO5 1LH",
    "sg:province":"Hampshire",
    "sg:tags":[
        "video",
        "library"
    ],
    "wof:name":"Cussen,Robert,",
    "wof:placetype":"venue"
},
  "geometry": {"coordinates":[-1.0863330364,50.7900047302],"type":"Point"}
}