{
  "type": "Feature",
  "properties": {
    "iso:country":"GB",
    "sg:address":"Balls Farm Tye Road, Elmstead",
    "sg:city":"Colchester",
    "sg:classifiers":[
        {
            "category":"Professional",
            "subcategory":"Accounting & Tax Preparation",
            "type":"Services"
        },
        {
            "category":"Organizations",
            "subcategory":"Non-profit Organization",
            "type":"Services"
        }
    ],
    "sg:phone":"+44 1206 822514",
    "sg:postcode":"CO7 7BB",
    "sg:province":"Essex",
    "sg:tags":[
        "voluntary",
        "accountant",
        "organisation",
        "charity"
    ],
    "wof:name":"Colchester Commitee",
    "wof:placetype":"venue"
},
  "geometry": {"coordinates":[0.997777,51.893375],"type":"Point"}
}