{
  "type": "Feature",
  "properties": {
    "addr:full":"50 High Street, Holbeach Spalding Cambridgeshire PE12 7ED",
    "addr:housenumber":"50",
    "addr:postcode":"pe12 7ed",
    "addr:street":"High Street",
    "iso:country":"GB",
    "sg:address":"50 High Street, Holbeach",
    "sg:city":"Spalding",
    "sg:classifiers":[
        {
            "category":"Shopping",
            "subcategory":"Shoes",
            "type":"Retail Goods"
        }
    ],
    "sg:phone":"+44 1406 423350",
    "sg:postcode":"PE12 7ED",
    "sg:province":"Cambridgeshire",
    "sg:tags":[
        "shop"
    ],
    "wof:name":"Susan Shoes",
    "wof:placetype":"venue"
},
  "geometry": {"coordinates":[0.01744,52.803471],"type":"Point"}
}