{
  "type": "Feature",
  "properties": {
    "addr:full":"140 Manor Road New Milton Hampshire BH25 5ED",
    "addr:housenumber":"140",
    "addr:postcode":"bh25 5ed",
    "addr:street":"Manor Road",
    "iso:country":"GB",
    "sg:address":"140 Manor Road",
    "sg:city":"New Milton",
    "sg:classifiers":[
        {
            "category":"Professional",
            "type":"Services"
        }
    ],
    "sg:phone":"+44 1425 612830",
    "sg:postcode":"BH25 5ED",
    "sg:province":"Hampshire",
    "sg:tags":[
        "entertainer"
    ],
    "wof:name":"The Good the Bad & the Cuddly Puppet Theatre",
    "wof:placetype":"venue"
},
  "geometry": {"coordinates":[-1.645087,50.761116],"type":"Point"}
}