{
  "type": "Feature",
  "properties": {
    "iso:country":"GB",
    "sg:address":"The Gables, Parsons Drove, Billinghay Fen",
    "sg:city":"Lincoln",
    "sg:classifiers":[
        {
            "category":"Farming",
            "subcategory":"Livestock Farm",
            "type":"Manufacturing & Wholesale Goods"
        }
    ],
    "sg:postcode":"LN4 4BB",
    "sg:province":"Lincolnshire",
    "sg:tags":[
        "others"
    ],
    "wof:name":"T G Gilbert (Walcot) Ltd.",
    "wof:placetype":"venue"
},
  "geometry": {"coordinates":[-0.28111,53.079254],"type":"Point"}
}