{
  "type": "Feature",
  "properties": {
    "iso:country":"GB",
    "sg:address":"43 Old Gosport Rd",
    "sg:city":"Fareham",
    "sg:classifiers":[
        {
            "category":"Autos & Motor Vehicles",
            "subcategory":"Boat Sales",
            "type":"Retail Goods"
        }
    ],
    "sg:phone":"+44 1329 233255",
    "sg:postcode":"PO16 0XH",
    "sg:province":"Hampshire",
    "sg:tags":[
        "repair",
        "builder"
    ],
    "wof:name":"Chasecraft Fareham",
    "wof:placetype":"venue"
},
  "geometry": {"coordinates":[-1.180107,50.847893],"type":"Point"}
}