{
  "type": "Feature",
  "properties": {
    "addr:full":"10 Hailgate Clo Goole East Riding of Yorkshire DN14 7SG",
    "addr:housenumber":"10",
    "addr:postcode":"dn14 7sg",
    "addr:street":"Hailgate Clo",
    "iso:country":"GB",
    "sg:address":"10 Hailgate Clo",
    "sg:city":"Goole",
    "sg:classifiers":[
        {
            "category":"Place Of Worship",
            "type":"Public Place"
        }
    ],
    "sg:phone":"+44 1430 432044",
    "sg:postcode":"DN14 7SG",
    "sg:province":"East Riding of Yorkshire",
    "wof:name":"Howden Methodist Church",
    "wof:placetype":"venue"
},
  "geometry": {"coordinates":[-0.859699,53.746433],"type":"Point"}
}