{
  "type": "Feature",
  "properties": {
    "addr:full":"Waters Wallow Quarry, Fairfield Buxton Derbyshire SK17 7JP",
    "addr:housenumber":"fairfield",
    "addr:postcode":"sk17 7jp",
    "addr:street":"Quarry",
    "iso:country":"GB",
    "sg:address":"Waters Wallow Quarry, Fairfield",
    "sg:city":"Buxton",
    "sg:classifiers":[
        {
            "category":"Professional",
            "subcategory":"Engineering",
            "type":"Services"
        }
    ],
    "sg:phone":"+44 1298 79888",
    "sg:postcode":"SK17 7JP",
    "sg:province":"Derbyshire",
    "sg:tags":[
        "contractor",
        "electrical",
        "engineer"
    ],
    "wof:name":"H & L Electrical Ltd.",
    "wof:placetype":"venue"
},
  "geometry": {"coordinates":[-1.9016129971,53.2630958557],"type":"Point"}
}