{
  "type": "Feature",
  "properties": {
    "addr:full":"39 Bristol Road Gloucester Gloucestershire GL1 5SA",
    "addr:housenumber":"39",
    "addr:postcode":"gl1 5sa",
    "addr:street":"Bristol Road",
    "iso:country":"GB",
    "sg:address":"39 Bristol Road",
    "sg:city":"Gloucester",
    "sg:classifiers":[
        {
            "category":"Bars & Pubs",
            "type":"Food & Drink"
        }
    ],
    "sg:postcode":"GL1 5SA",
    "sg:province":"Gloucestershire",
    "sg:tags":[
        "pubs",
        "inn"
    ],
    "wof:name":"The Robin Hood",
    "wof:placetype":"venue"
},
  "geometry": {"coordinates":[-2.252279,51.855747],"type":"Point"}
}