{
  "type": "Feature",
  "properties": {
    "iso:country":"GB",
    "sg:address":"Units 147-148 Camford Way",
    "sg:city":"Luton",
    "sg:classifiers":[
        {
            "category":"Personal",
            "type":"Services"
        }
    ],
    "sg:phone":"+44 1582 847484",
    "sg:postcode":"LU3 3AN",
    "sg:province":"Bedfordshire",
    "sg:tags":[
        "wedding"
    ],
    "wof:name":"Barton-hall Limousine",
    "wof:placetype":"venue"
},
  "geometry": {"coordinates":[-0.48194,51.922192],"type":"Point"}
}