{
  "type": "Feature",
  "properties": {
    "addr:full":"Wemco House, 477 Whippendell Road Watford Hertfordshire WD18 7QY",
    "addr:housenumber":"477",
    "addr:postcode":"wd18 7qy",
    "addr:street":"Whippendell Road",
    "iso:country":"GB",
    "sg:address":"Wemco House, 477 Whippendell Road",
    "sg:city":"Watford",
    "sg:classifiers":[
        {
            "category":"Wholesale",
            "subcategory":"Office Equipment",
            "type":"Manufacturing & Wholesale Goods"
        }
    ],
    "sg:phone":"+44 1923 236906",
    "sg:postcode":"WD18 7QY",
    "sg:province":"Hertfordshire",
    "sg:tags":[
        "partition",
        "cubicle"
    ],
    "wof:name":"Becker (Sliding Partitions) Ltd.",
    "wof:placetype":"venue"
},
  "geometry": {"coordinates":[-0.418596,51.651096],"type":"Point"}
}