{
  "type": "Feature",
  "properties": {
    "addr:full":"Griggs Piece, North Crawley Newport Pagnell Buckinghamshire MK16 9LQ",
    "addr:postcode":"mk16 9lq",
    "addr:street":"Griggs Piece",
    "iso:country":"GB",
    "sg:address":"Griggs Piece, North Crawley",
    "sg:city":"Newport Pagnell",
    "sg:classifiers":[
        {
            "category":"Food & Beverages",
            "subcategory":"Farmers Market",
            "type":"Retail Goods"
        }
    ],
    "sg:phone":"+44 1234 391513",
    "sg:postcode":"MK16 9LQ",
    "sg:province":"Buckinghamshire",
    "sg:tags":[
        "gardener"
    ],
    "wof:name":"Ronnie P O'Haren",
    "wof:placetype":"venue"
},
  "geometry": {"coordinates":[-0.648625,52.093136],"type":"Point"}
}