{
  "type": "Feature",
  "properties": {
    "addr:full":"71-77 Powis St, Woolwich London Greater London SE18 6JB",
    "addr:housenumber":"71-77",
    "addr:postcode":"se18 6jb",
    "addr:street":"Powis St",
    "iso:country":"GB",
    "sg:address":"71-77 Powis St, Woolwich",
    "sg:city":"London",
    "sg:classifiers":[
        {
            "category":"Shopping",
            "subcategory":"Catalog Store",
            "type":"Retail Goods"
        }
    ],
    "sg:phone":"+44 20 8317 0311",
    "sg:postcode":"SE18 6JB",
    "sg:province":"Greater London",
    "sg:tags":[
        "catalogue",
        "showroom"
    ],
    "wof:name":"Index Ltd",
    "wof:placetype":"venue"
},
  "geometry": {"coordinates":[0.06459,51.49202],"type":"Point"}
}