{
  "type": "Feature",
  "properties": {
    "addr:full":"Cannock Community Centre, Avon Road Cannock Staffordshire WS11 1LG",
    "addr:postcode":"ws11 1lg",
    "addr:street":"Avon Road",
    "iso:country":"GB",
    "sg:address":"Cannock Community Centre, Avon Road",
    "sg:city":"Cannock",
    "sg:classifiers":[
        {
            "category":"Retail",
            "subcategory":"Driving School",
            "type":"Services"
        }
    ],
    "sg:phone":"+44 1543 573762",
    "sg:postcode":"WS11 1LG",
    "sg:province":"Staffordshire",
    "sg:tags":[
        "instruction",
        "cycling",
        "motor"
    ],
    "wof:name":"N F L Motor Cycle Training",
    "wof:placetype":"venue"
},
  "geometry": {"coordinates":[-2.0331449509,52.690952301],"type":"Point"}
}