{
  "type": "Feature",
  "properties": {
    "iso:country":"GB",
    "sg:address":"20 Kingsley Rd",
    "sg:city":"Hounslow",
    "sg:classifiers":[
        {
            "category":"Shopping",
            "subcategory":"Pharmacy",
            "type":"Retail Goods"
        }
    ],
    "sg:phone":"+44 20 8577 5831",
    "sg:postcode":"TW3 1NP",
    "sg:province":"Greater London",
    "sg:tags":[
        "store",
        "drug"
    ],
    "wof:name":"Sasta Drug Store Ltd",
    "wof:placetype":"venue"
},
  "geometry": {"coordinates":[-0.355527,51.471241],"type":"Point"}
}