{
  "type": "Feature",
  "properties": {
    "addr:full":"93 Fleet Street London Greater London EC4Y 1DH",
    "addr:housenumber":"93",
    "addr:postcode":"ec4y 1dh",
    "addr:street":"Fleet Street",
    "iso:country":"GB",
    "sg:address":"93 Fleet Street",
    "sg:city":"London",
    "sg:classifiers":[
        {
            "category":"Communications",
            "type":"Services"
        }
    ],
    "sg:phone":"+44 20 7353 9391",
    "sg:postcode":"EC4Y 1DH",
    "sg:province":"Greater London",
    "sg:tags":[
        "telecommunication"
    ],
    "wof:name":"The Link",
    "wof:placetype":"venue"
},
  "geometry": {"coordinates":[-0.1054020002,51.5140838623],"type":"Point"}
}