{
  "type": "Feature",
  "properties": {
    "addr:full":"54 London Road Romford Essex RM7 9QX",
    "addr:housenumber":"54",
    "addr:postcode":"rm7 9qx",
    "addr:street":"London Road",
    "iso:country":"GB",
    "sg:address":"54 London Road",
    "sg:city":"Romford",
    "sg:classifiers":[
        {
            "category":"Personal",
            "subcategory":"Nail Salon",
            "type":"Services"
        }
    ],
    "sg:postcode":"RM7 9QX",
    "sg:province":"Essex",
    "sg:tags":[
        "technician"
    ],
    "wof:name":"Beauty Tips",
    "wof:placetype":"venue"
},
  "geometry": {"coordinates":[0.175311,51.575329],"type":"Point"}
}