{
  "type": "Feature",
  "properties": {
    "addr:full":"5 Marina Court, Fulwell Sunderland Tyne and Wear SR6 9AQ",
    "addr:housenumber":"5",
    "addr:postcode":"sr6 9aq",
    "addr:street":"Marina Court",
    "iso:country":"GB",
    "sg:address":"5 Marina Court, Fulwell",
    "sg:city":"Sunderland",
    "sg:classifiers":[
        {
            "category":"Building & Trades",
            "subcategory":"Construction",
            "type":"Services"
        }
    ],
    "sg:postcode":"SR6 9AQ",
    "sg:province":"Tyne and Wear",
    "sg:tags":[
        "joiner",
        "carpenter"
    ],
    "wof:name":"Bryan Short",
    "wof:placetype":"venue"
},
  "geometry": {"coordinates":[-1.384433,54.927959],"type":"Point"}
}