{
  "type": "Feature",
  "properties": {
    "iso:country":"GB",
    "sg:address":"62 Corporation Street",
    "sg:city":"Corby",
    "sg:classifiers":[
        {
            "category":"Food & Beverages",
            "subcategory":"Meat & Fish",
            "type":"Retail Goods"
        }
    ],
    "sg:phone":"+44 1536 268181",
    "sg:postcode":"NN17 1NH",
    "sg:province":"Northamptonshire",
    "sg:tags":[
        "chip"
    ],
    "wof:name":"Hadleighs Fish & Chip Restaurant",
    "wof:placetype":"venue"
},
  "geometry": {"coordinates":[-0.6997489929,52.4877891541],"type":"Point"}
}