{
  "type": "Feature",
  "properties": {
    "iso:country":"GB",
    "sg:address":"1 Breck Road",
    "sg:city":"Poulton-le-fylde",
    "sg:classifiers":[
        {
            "category":"Shopping",
            "subcategory":"Clothing, Apparel, & Fashions",
            "type":"Retail Goods"
        }
    ],
    "sg:phone":"+44 1253 895000",
    "sg:postcode":"FY6 7AA",
    "sg:province":"Lancashire",
    "sg:tags":[
        "shop"
    ],
    "wof:name":"Femme",
    "wof:placetype":"venue"
},
  "geometry": {"coordinates":[-2.99148,53.847691],"type":"Point"}
}