{
  "type": "Feature",
  "properties": {
    "addr:full":"20 Westway Liverpool Lancashire L31 0DQ",
    "addr:housenumber":"20",
    "addr:postcode":"l31 0dq",
    "addr:street":"Westway",
    "iso:country":"GB",
    "sg:address":"20 Westway",
    "sg:city":"Liverpool",
    "sg:classifiers":[
        {
            "category":"Sports & Exercise",
            "subcategory":"Sports Center",
            "type":"Entertainment"
        }
    ],
    "sg:phone":"+44 151 531 0868",
    "sg:postcode":"L31 0DQ",
    "sg:province":"Lancashire",
    "sg:tags":[
        "shop",
        "good"
    ],
    "wof:name":"4 B Sports",
    "wof:placetype":"venue"
},
  "geometry": {"coordinates":[-2.94191,53.516544],"type":"Point"}
}