{
  "type": "Feature",
  "properties": {
    "addr:full":"1 Oxhill Road, Shirley Solihull West Midlands B90 1LR",
    "addr:housenumber":"1",
    "addr:postcode":"b90 1lr",
    "addr:street":"Oxhill Road",
    "iso:country":"GB",
    "sg:address":"1 Oxhill Road, Shirley",
    "sg:city":"Solihull",
    "sg:classifiers":[
        {
            "category":"Personal",
            "subcategory":"Beauty Salon",
            "type":"Services"
        }
    ],
    "sg:phone":"+44 121 430 4611",
    "sg:postcode":"B90 1LR",
    "sg:province":"West Midlands",
    "sg:tags":[
        "unisex",
        "hairdresser"
    ],
    "wof:name":"Checkers",
    "wof:placetype":"venue"
},
  "geometry": {"coordinates":[-1.861060977,52.4068450928],"type":"Point"}
}