{
  "type": "Feature",
  "properties": {
    "addr:full":"Wyndham Sq Plymouth Devon PL1 5EG",
    "addr:postcode":"pl1 5eg",
    "addr:street":"Wyndham Sq",
    "iso:country":"GB",
    "sg:address":"Wyndham Sq",
    "sg:city":"Plymouth",
    "sg:classifiers":[
        {
            "category":"Place Of Worship",
            "type":"Public Place"
        }
    ],
    "sg:phone":"+44 1752 222007",
    "sg:postcode":"PL1 5EG",
    "sg:province":"Devon",
    "wof:name":"St Peters Church",
    "wof:placetype":"venue"
},
  "geometry": {"coordinates":[-4.1552991867,50.3729133606],"type":"Point"}
}