{
  "type": "Feature",
  "properties": {
    "iso:country":"GB",
    "sg:address":"24a Longley Road, Rainham",
    "sg:city":"Gillingham",
    "sg:classifiers":[
        {
            "category":"Shopping",
            "subcategory":"Computers & Home Electronics",
            "type":"Retail Goods"
        }
    ],
    "sg:phone":"+44 1634 268888",
    "sg:postcode":"ME8 7RU",
    "sg:province":"Kent",
    "sg:tags":[
        "electrical"
    ],
    "wof:name":"Kent Electrical Supplies Ltd.",
    "wof:placetype":"venue"
},
  "geometry": {"coordinates":[0.606753,51.364708],"type":"Point"}
}