{
  "type": "Feature",
  "properties": {
    "addr:full":"Alsop Buildings, Brownlow Hill Liverpool Merseyside L3 5TX",
    "addr:postcode":"l3 5tx",
    "addr:street":"Brownlow Hill",
    "iso:country":"GB",
    "sg:address":"Alsop Buildings, Brownlow Hill",
    "sg:city":"Liverpool",
    "sg:classifiers":[
        {
            "category":"Shopping",
            "subcategory":"Books",
            "type":"Retail Goods"
        }
    ],
    "sg:phone":"+44 151 709 8146",
    "sg:postcode":"L3 5TX",
    "sg:province":"Merseyside",
    "sg:tags":[
        "bookseller",
        "retailer"
    ],
    "wof:name":"Blackwells University Bookshop",
    "wof:placetype":"venue"
},
  "geometry": {"coordinates":[-2.9727799892,53.4064903259],"type":"Point"}
}