{
  "type": "Feature",
  "properties": {
    "iso:country":"GB",
    "sg:address":"310 Barking Rd",
    "sg:city":"Plaistow",
    "sg:classifiers":[
        {
            "category":"Organizations",
            "subcategory":"Non-profit Organization",
            "type":"Services"
        }
    ],
    "sg:phone":"+44 20 7511 0243",
    "sg:postcode":"E13 8HL",
    "sg:province":"Greater London",
    "sg:tags":[
        "organisation",
        "voluntary",
        "charity"
    ],
    "wof:name":"Neighbourhood Care Project",
    "wof:placetype":"venue"
},
  "geometry": {"coordinates":[0.0202469993,51.5210990906],"type":"Point"}
}