{
  "type": "Feature",
  "properties": {
    "iso:country":"GB",
    "sg:address":"25 Ashford Road",
    "sg:city":"Tenterden",
    "sg:classifiers":[
        {
            "category":"Professional",
            "subcategory":"Art Services",
            "type":"Services"
        }
    ],
    "sg:postcode":"TN30 6LL",
    "sg:province":"Kent",
    "sg:tags":[
        "photographer"
    ],
    "wof:name":"Ian Pooley",
    "wof:placetype":"venue"
},
  "geometry": {"coordinates":[0.690867,51.071918],"type":"Point"}
}