{
  "type": "Feature",
  "properties": {
    "iso:country":"GB",
    "sg:address":"Unit 3 Broombank Park, Sheepbridge Industrial Estate",
    "sg:city":"Chesterfield",
    "sg:classifiers":[
        {
            "category":"Manufacturing",
            "subcategory":"Motor Vehicles & Parts",
            "type":"Manufacturing & Wholesale Goods"
        }
    ],
    "sg:phone":"+44 1246 261297",
    "sg:postcode":"S41 9RT",
    "sg:province":"Derbyshire",
    "sg:tags":[
        "bearing"
    ],
    "wof:name":"Wyko Industrial Services Ltd.",
    "wof:placetype":"venue"
},
  "geometry": {"coordinates":[-1.449493,53.271336],"type":"Point"}
}