{
  "type": "Feature",
  "properties": {
    "iso:country":"GB",
    "sg:address":"313 Orbiston St",
    "sg:city":"Motherwell",
    "sg:classifiers":[
        {
            "category":"Parking",
            "type":"Transportation"
        }
    ],
    "sg:postcode":"ML1 1QH",
    "sg:province":"North Lanarkshire",
    "sg:tags":[
        "car",
        "valet"
    ],
    "wof:name":"Holmes,Spencer,",
    "wof:placetype":"venue"
},
  "geometry": {"coordinates":[-3.978782,55.783733],"type":"Point"}
}