{
  "type": "Feature",
  "properties": {
    "addr:full":"15 Boroughgate Otley North Yorkshire LS21 3AL",
    "addr:housenumber":"15",
    "addr:postcode":"ls21 3al",
    "addr:street":"Boroughgate",
    "iso:country":"GB",
    "sg:address":"15 Boroughgate",
    "sg:city":"Otley",
    "sg:classifiers":[
        {
            "category":"Organizations",
            "subcategory":"Membership Organization",
            "type":"Services"
        }
    ],
    "sg:phone":"+44 1943 461283",
    "sg:postcode":"LS21 3AL",
    "sg:province":"North Yorkshire",
    "sg:tags":[
        "club"
    ],
    "wof:name":"Otley Conservative Club",
    "wof:placetype":"venue"
},
  "geometry": {"coordinates":[-1.6927870512,53.905582428],"type":"Point"}
}