{
  "type": "Feature",
  "properties": {
    "iso:country":"GB",
    "sg:address":"14 Durham Terrace",
    "sg:city":"Sunderland",
    "sg:classifiers":[
        {
            "category":"Personal",
            "subcategory":"Beauty Salon",
            "type":"Services"
        }
    ],
    "sg:postcode":"SR3 1BW",
    "sg:province":"Tyne and Wear",
    "sg:tags":[
        "unisex",
        "hairdresser"
    ],
    "wof:name":"Anne's Hair Fashions",
    "wof:placetype":"venue"
},
  "geometry": {"coordinates":[-1.4069310427,54.8797607422],"type":"Point"}
}