{
  "type": "Feature",
  "properties": {
    "addr:full":"Unit 21, Empire Centre, Imperial Way Watford Hertfordshire WD24 4TS",
    "addr:housenumber":"unit 21",
    "addr:postcode":"wd24 4ts",
    "addr:street":"Empire Centre Imperial Way",
    "iso:country":"GB",
    "sg:address":"Unit 21, Empire Centre, Imperial Way",
    "sg:city":"Watford",
    "sg:classifiers":[
        {
            "category":"Home & Garden",
            "subcategory":"Hardware",
            "type":"Retail Goods"
        }
    ],
    "sg:phone":"+44 1923 239668",
    "sg:postcode":"WD24 4TS",
    "sg:province":"Hertfordshire",
    "sg:tags":[
        "compressor",
        "air"
    ],
    "wof:name":"Nitto Kohki Europe Co. Ltd.",
    "wof:placetype":"venue"
},
  "geometry": {"coordinates":[-0.3924300075,51.6693611145],"type":"Point"}
}