{
  "type": "Feature",
  "properties": {
    "addr:full":"Taverham Road Norwich Norfolk NR10 4DS",
    "addr:postcode":"nr10 4ds",
    "addr:street":"Taverham Road Norwich",
    "iso:country":"GB",
    "sg:address":"Taverham Road",
    "sg:city":"Norwich",
    "sg:classifiers":[
        {
            "category":"Retail",
            "subcategory":"Repair Shop",
            "type":"Services"
        }
    ],
    "sg:postcode":"NR10 4DS",
    "sg:province":"Norfolk",
    "sg:tags":[
        "sharpening",
        "tool"
    ],
    "wof:name":"Felthorpe Saw Services",
    "wof:placetype":"venue"
},
  "geometry": {"coordinates":[1.2014479637,52.7131271362],"type":"Point"}
}