{
  "type": "Feature",
  "properties": {
    "addr:full":"69 The Avenue Southampton Hampshire SO15 2TU",
    "addr:housenumber":"69",
    "addr:postcode":"so15 2tu",
    "addr:street":"The Avenue",
    "iso:country":"GB",
    "sg:address":"69 The Avenue",
    "sg:city":"Southampton",
    "sg:classifiers":[
        {
            "category":"Bars & Pubs",
            "subcategory":"Wine Bar",
            "type":"Food & Drink"
        }
    ],
    "sg:postcode":"SO15 2TU",
    "sg:province":"Hampshire",
    "wof:name":"Willies Wine Bar",
    "wof:placetype":"venue"
},
  "geometry": {"coordinates":[-1.4022580385,50.9142494202],"type":"Point"}
}