{
  "type": "Feature",
  "properties": {
    "addr:full":"Whiteholme Mill Skipton Lancashire BB8 8RA",
    "addr:postcode":"bb8 8ra",
    "iso:country":"GB",
    "sg:address":"Whiteholme Mill",
    "sg:city":"Skipton",
    "sg:classifiers":[
        {
            "category":"Food & Beverages",
            "subcategory":"Fruits & Vegetables",
            "type":"Retail Goods"
        }
    ],
    "sg:postcode":"BB8 8RA",
    "sg:province":"Lancashire",
    "sg:tags":[
        "greengrocer"
    ],
    "wof:name":"Richard Wellock & Sons Ltd.",
    "wof:placetype":"venue"
},
  "geometry": {"coordinates":[-2.1359539032,53.8467216492],"type":"Point"}
}