{
  "type": "Feature",
  "properties": {
    "addr:full":"88-90 Holton Road Barry The Vale of Glamorgan CF63 4HJ",
    "addr:housenumber":"88-90",
    "addr:postcode":"cf63 4hj",
    "addr:street":"Holton Road;Vale",
    "iso:country":"GB",
    "sg:address":"88-90 Holton Road",
    "sg:city":"Barry",
    "sg:classifiers":[
        {
            "category":"Cinema",
            "subcategory":"Movie Rental",
            "type":"Entertainment"
        }
    ],
    "sg:phone":"+44 1446 700889",
    "sg:postcode":"CF63 4HJ",
    "sg:province":"The Vale of Glamorgan",
    "sg:tags":[
        "video",
        "library"
    ],
    "wof:name":"Blockbuster Video",
    "wof:placetype":"venue"
},
  "geometry": {"coordinates":[-3.2684409618,51.4056434631],"type":"Point"}
}