{
  "type": "Feature",
  "properties": {
    "addr:full":"12 New Road Oxford Oxfordshire OX1 1LT",
    "addr:housenumber":"12",
    "addr:postcode":"ox1 1lt",
    "addr:street":"New Road",
    "iso:country":"GB",
    "sg:address":"12 New Road",
    "sg:city":"Oxford",
    "sg:classifiers":[
        {
            "category":"Bars & Pubs",
            "type":"Food & Drink"
        }
    ],
    "sg:phone":"+44 1865 250099",
    "sg:postcode":"OX1 1LT",
    "sg:province":"Oxfordshire",
    "sg:tags":[
        "pubs",
        "inn"
    ],
    "wof:name":"The Westgate",
    "wof:placetype":"venue"
},
  "geometry": {"coordinates":[-1.261439,51.752144],"type":"Point"}
}