{
  "type": "Feature",
  "properties": {
    "addr:full":"189 High Street Berkhamsted Bedfordshire HP4 1AY",
    "addr:housenumber":"189",
    "addr:postcode":"hp4 1ay",
    "addr:street":"High Street",
    "iso:country":"GB",
    "sg:address":"189 High Street",
    "sg:city":"Berkhamsted",
    "sg:classifiers":[
        {
            "category":"Banks & Credit Unions",
            "subcategory":"Bank",
            "type":"Services"
        }
    ],
    "sg:phone":"+44 845 755 5555",
    "sg:postcode":"HP4 1AY",
    "sg:province":"Bedfordshire",
    "sg:tags":[
        "financial",
        "institution"
    ],
    "wof:name":"BARCLAYS BANK PLC",
    "wof:placetype":"venue"
},
  "geometry": {"coordinates":[-0.5655170083,51.7606430054],"type":"Point"}
}