{
  "type": "Feature",
  "properties": {
    "addr:full":"Wharf Farm, Uffington Faringdon Oxfordshire SN7 7PS",
    "addr:postcode":"sn7 7ps",
    "addr:street":"Wharf",
    "iso:country":"GB",
    "sg:address":"Wharf Farm, Uffington",
    "sg:city":"Faringdon",
    "sg:classifiers":[
        {
            "category":"Farming",
            "subcategory":"Livestock Farm",
            "type":"Manufacturing & Wholesale Goods"
        }
    ],
    "sg:phone":"+44 1367 820273",
    "sg:postcode":"SN7 7PS",
    "sg:province":"Oxfordshire",
    "sg:tags":[
        "others"
    ],
    "wof:name":"L I Richings",
    "wof:placetype":"venue"
},
  "geometry": {"coordinates":[-1.5866539478,51.6561698914],"type":"Point"}
}