{
  "type": "Feature",
  "properties": {
    "addr:full":"262 Scalby Road Scarborough North Yorkshire YO12 6EA",
    "addr:housenumber":"262",
    "addr:postcode":"yo12 6ea",
    "addr:street":"Scalby Road",
    "iso:country":"GB",
    "sg:address":"262 Scalby Road",
    "sg:city":"Scarborough",
    "sg:classifiers":[
        {
            "category":"Education",
            "subcategory":"Music School",
            "type":"Public Place"
        }
    ],
    "sg:phone":"+44 1723 377114",
    "sg:postcode":"YO12 6EA",
    "sg:province":"North Yorkshire",
    "sg:tags":[
        "conservatory"
    ],
    "wof:name":"Abi Canopies",
    "wof:placetype":"venue"
},
  "geometry": {"coordinates":[-0.433694,54.286369],"type":"Point"}
}