{
  "type": "Feature",
  "properties": {
    "iso:country":"GB",
    "sg:address":"68a Camden Rd",
    "sg:city":"Tunbridge Wells",
    "sg:classifiers":[
        {
            "category":"Professional",
            "type":"Services"
        }
    ],
    "sg:phone":"+44 70 0038 6348",
    "sg:postcode":"TN1 2QP",
    "sg:province":"Kent",
    "sg:tags":[
        "leasing"
    ],
    "wof:name":"Chelco",
    "wof:placetype":"venue"
},
  "geometry": {"coordinates":[0.269055,51.135986],"type":"Point"}
}