{
  "type": "Feature",
  "properties": {
    "iso:country":"GB",
    "sg:address":"Inchford Brook House, Kites Nest Lane, Beausale",
    "sg:city":"Warwick",
    "sg:classifiers":[
        {
            "category":"Real Estate",
            "subcategory":"Surveying",
            "type":"Services"
        }
    ],
    "sg:phone":"+44 1926 484300",
    "sg:postcode":"CV35 7PB",
    "sg:province":"Warwickshire",
    "sg:tags":[
        "surveyor",
        "quantity"
    ],
    "wof:name":"Robert S & Associates Newman",
    "wof:placetype":"venue"
},
  "geometry": {"coordinates":[-1.638749,52.324066],"type":"Point"}
}