{
  "type": "Feature",
  "properties": {
    "iso:country":"GB",
    "sg:address":"7 Spring Lake",
    "sg:city":"Stanmore",
    "sg:classifiers":[
        {
            "category":"Health Services",
            "subcategory":"Dentist",
            "type":"Services"
        }
    ],
    "sg:phone":"+44 20 8954 0666",
    "sg:postcode":"HA7 3BX",
    "sg:province":"Greater London",
    "wof:name":"Abrahams B",
    "wof:placetype":"venue"
},
  "geometry": {"coordinates":[-0.316592,51.622063],"type":"Point"}
}