{
  "type": "Feature",
  "properties": {
    "iso:country":"GB",
    "sg:address":"31 Silverstone",
    "sg:city":"Newcastle-upon-tyne",
    "sg:classifiers":[
        {
            "category":"Wholesale",
            "subcategory":"Computers",
            "type":"Manufacturing & Wholesale Goods"
        },
        {
            "category":"Professional",
            "subcategory":"Computer Services",
            "type":"Services"
        }
    ],
    "sg:phone":"+44 191 268 1831",
    "sg:postcode":"NE12 6LS",
    "sg:province":"Tyne and Wear",
    "sg:tags":[
        "supplier",
        "consumables",
        "system",
        "software"
    ],
    "wof:name":"M S C Computer Training",
    "wof:placetype":"venue"
},
  "geometry": {"coordinates":[-1.558301,55.033714],"type":"Point"}
}