{
  "type": "Feature",
  "properties": {
    "iso:country":"GB",
    "sg:address":"9 The Paddock, Hemsby",
    "sg:city":"Great Yarmouth",
    "sg:classifiers":[
        {
            "category":"Education",
            "subcategory":"School",
            "type":"Public Place"
        }
    ],
    "sg:phone":"+44 1493 730569",
    "sg:postcode":"NR29 4HG",
    "sg:province":"Norfolk",
    "sg:tags":[
        "local",
        "authority"
    ],
    "wof:name":"Civictop Ltd",
    "wof:placetype":"venue"
},
  "geometry": {"coordinates":[1.687863,52.699757],"type":"Point"}
}