{
  "type": "Feature",
  "properties": {
    "addr:full":"The Gables, Fairview Road, Denbury Newton Abbot Devon TQ12 6ET",
    "addr:postcode":"tq12 6et",
    "addr:street":"Fairview Road",
    "iso:country":"GB",
    "sg:address":"The Gables, Fairview Road, Denbury",
    "sg:city":"Newton Abbot",
    "sg:classifiers":[
        {
            "category":"Professional",
            "subcategory":"Engineering",
            "type":"Services"
        }
    ],
    "sg:postcode":"TQ12 6ET",
    "sg:province":"Devon",
    "sg:tags":[
        "contractor",
        "electrical",
        "engineer"
    ],
    "wof:name":"W Langler",
    "wof:placetype":"venue"
},
  "geometry": {"coordinates":[-3.607659,50.52887],"type":"Point"}
}