{
  "type": "Feature",
  "properties": {
    "addr:full":"14 Darwell Drive, Stone Cross Pevensey East Sussex BN24 5PG",
    "addr:housenumber":"14",
    "addr:postcode":"bn24 5pg",
    "addr:street":"Darwell Drive",
    "iso:country":"GB",
    "sg:address":"14 Darwell Drive, Stone Cross",
    "sg:city":"Pevensey",
    "sg:classifiers":[
        {
            "category":"Social Services",
            "subcategory":"Job Training",
            "type":"Services"
        }
    ],
    "sg:phone":"+44 1323 768920",
    "sg:postcode":"BN24 5PG",
    "sg:province":"East Sussex",
    "sg:tags":[
        "draughtsman",
        "drawing"
    ],
    "wof:name":"Tim Ginno",
    "wof:placetype":"venue"
},
  "geometry": {"coordinates":[0.284138,50.816463],"type":"Point"}
}