{
  "type": "Feature",
  "properties": {
    "iso:country":"GB",
    "sg:address":"62 Fleet Walk",
    "sg:city":"Torquay",
    "sg:classifiers":[
        {
            "category":"Shopping",
            "subcategory":"Books",
            "type":"Retail Goods"
        }
    ],
    "sg:phone":"+44 1803 200304",
    "sg:postcode":"TQ2 5ED",
    "sg:province":"Devon",
    "sg:tags":[
        "bookseller"
    ],
    "wof:name":"WHSmith High Street",
    "wof:placetype":"venue"
},
  "geometry": {"coordinates":[-3.5261929035,50.4627723694],"type":"Point"}
}