{
  "type": "Feature",
  "properties": {
    "addr:full":"184 Mare Street London Greater London E8 3RD",
    "addr:housenumber":"184",
    "addr:postcode":"e8 3rd",
    "addr:street":"Mare Street",
    "iso:country":"GB",
    "sg:address":"184 Mare Street",
    "sg:city":"London",
    "sg:classifiers":[
        {
            "category":"Place Of Worship",
            "type":"Public Place"
        }
    ],
    "sg:phone":"+44 20 8985 5803",
    "sg:postcode":"E8 3RD",
    "sg:province":"Greater London",
    "wof:name":"Greek Orthodox Church Of St John The Theologian",
    "wof:placetype":"venue"
},
  "geometry": {"coordinates":[-0.055121,51.541267],"type":"Point"}
}