{
  "type": "Feature",
  "properties": {
    "iso:country":"GB",
    "sg:address":"21 Station Road",
    "sg:city":"Studley",
    "sg:classifiers":[
        {
            "category":"Retail",
            "subcategory":"Veterinary Services",
            "type":"Services"
        }
    ],
    "sg:phone":"+44 1527 853304",
    "sg:postcode":"B80 7HR",
    "sg:province":"Warwickshire",
    "sg:tags":[
        "surgeon",
        "activity"
    ],
    "wof:name":"Acorn Veterinary Centre",
    "wof:placetype":"venue"
},
  "geometry": {"coordinates":[-1.90226,52.271061],"type":"Point"}
}