{
  "type": "Feature",
  "properties": {
    "addr:full":"40-41 New Road Trowbridge Wiltshire BA14 7AA",
    "addr:housenumber":"40-41",
    "addr:postcode":"ba14 7aa",
    "addr:street":"New Road",
    "iso:country":"GB",
    "sg:address":"40-41 New Road",
    "sg:city":"Trowbridge",
    "sg:classifiers":[
        {
            "category":"Autos & Motor Vehicles",
            "subcategory":"Auto Supplies",
            "type":"Retail Goods"
        }
    ],
    "sg:phone":"+44 1225 765148",
    "sg:postcode":"BA14 7AA",
    "sg:province":"Wiltshire",
    "sg:tags":[
        "exhaust",
        "absorber",
        "shock",
        "tyre"
    ],
    "wof:name":"Exhaust & Tyre Centre",
    "wof:placetype":"venue"
},
  "geometry": {"coordinates":[-2.2090740204,51.3158378601],"type":"Point"}
}