{
  "type": "Feature",
  "properties": {
    "addr:full":"Owenshaw Works, Old Cawsey, Sowerby Bridge Halifax West Yorkshire HX6 2AJ",
    "addr:postcode":"hx6 2aj",
    "addr:street":"Old;Bridge",
    "iso:country":"GB",
    "sg:address":"Owenshaw Works, Old Cawsey, Sowerby Bridge",
    "sg:city":"Halifax",
    "sg:classifiers":[
        {
            "category":"Autos & Motor Vehicles",
            "subcategory":"Auto Supplies",
            "type":"Retail Goods"
        }
    ],
    "sg:phone":"+44 1422 839010",
    "sg:postcode":"HX6 2AJ",
    "sg:province":"West Yorkshire",
    "sg:tags":[
        "component"
    ],
    "wof:name":"S & D Autoparts Ltd.",
    "wof:placetype":"venue"
},
  "geometry": {"coordinates":[-1.90503,53.709759],"type":"Point"}
}