{
  "type": "Feature",
  "properties": {
    "iso:country":"GB",
    "sg:address":"479 Liverpool Road, Eccles",
    "sg:city":"Manchester",
    "sg:classifiers":[
        {
            "category":"Retail",
            "subcategory":"Auto Rental",
            "type":"Services"
        }
    ],
    "sg:phone":"+44 161 789 0669",
    "sg:postcode":"M30 7HY",
    "sg:province":"Greater Manchester",
    "sg:tags":[
        "car"
    ],
    "wof:name":"Unicorn Self Drive Ltd.",
    "wof:placetype":"venue"
},
  "geometry": {"coordinates":[-2.366089,53.478069],"type":"Point"}
}