{
  "type": "Feature",
  "properties": {
    "addr:full":"3 Copperworks Road Llanelli Carmarthenshire SA15 2EW",
    "addr:housenumber":"3",
    "addr:postcode":"sa15 2ew",
    "addr:street":"Copperworks Road",
    "iso:country":"GB",
    "sg:address":"3 Copperworks Road",
    "sg:city":"Llanelli",
    "sg:classifiers":[
        {
            "category":"Building & Trades",
            "subcategory":"Plumbing",
            "type":"Services"
        }
    ],
    "sg:phone":"+44 1554 775551",
    "sg:postcode":"SA15 2EW",
    "sg:province":"Carmarthenshire",
    "sg:tags":[
        "heating"
    ],
    "wof:name":"J Newcombe Plumbing & Heating",
    "wof:placetype":"venue"
},
  "geometry": {"coordinates":[-4.1592898369,51.672870636],"type":"Point"}
}