{
  "type": "Feature",
  "properties": {
    "addr:full":"Venables Road Northwich Cheshire CW9 5RT",
    "addr:postcode":"cw9 5rt",
    "addr:street":"Venables Road",
    "iso:country":"GB",
    "sg:address":"Venables Road",
    "sg:city":"Northwich",
    "sg:classifiers":[
        {
            "category":"Food & Beverages",
            "subcategory":"Supermarket",
            "type":"Retail Goods"
        }
    ],
    "sg:phone":"+44 1606 330092",
    "sg:postcode":"CW9 5RT",
    "sg:province":"Cheshire",
    "wof:name":"J Sainsbury",
    "wof:placetype":"venue"
},
  "geometry": {"coordinates":[-2.507199049,53.2647209167],"type":"Point"}
}