{
  "type": "Feature",
  "properties": {
    "iso:country":"GB",
    "sg:address":"52 Nunsfield Road",
    "sg:city":"Buxton",
    "sg:classifiers":[
        {
            "category":"Building & Trades",
            "subcategory":"Construction",
            "type":"Services"
        }
    ],
    "sg:postcode":"SK17 7BW",
    "sg:province":"Derbyshire",
    "sg:tags":[
        "decorator",
        "painter"
    ],
    "wof:name":"Trevor Wheeldon",
    "wof:placetype":"venue"
},
  "geometry": {"coordinates":[-1.905248,53.263424],"type":"Point"}
}