{
  "type": "Feature",
  "properties": {
    "iso:country":"GB",
    "sg:address":"Grange Lane",
    "sg:city":"Sutton Coldfield",
    "sg:classifiers":[
        {
            "category":"Organizations",
            "subcategory":"Non-profit Organization",
            "type":"Services"
        },
        {
            "category":"Organizations",
            "subcategory":"Religious Organization",
            "type":"Services"
        }
    ],
    "sg:phone":"+44 121 308 0331",
    "sg:postcode":"B75 5JX",
    "sg:province":"Staffordshire",
    "sg:tags":[
        "charitable",
        "organisation",
        "charity"
    ],
    "wof:name":"Four Oaks baptist Church",
    "wof:placetype":"venue"
},
  "geometry": {"coordinates":[-1.818665,52.594193],"type":"Point"}
}