{
  "type": "Feature",
  "properties": {
    "addr:full":"36 Meliden Road Prestatyn Denbighshire LL19 9RT",
    "addr:housenumber":"36",
    "addr:postcode":"ll19 9rt",
    "addr:street":"Meliden Road",
    "iso:country":"GB",
    "sg:address":"36 Meliden Road",
    "sg:city":"Prestatyn",
    "sg:classifiers":[
        {
            "category":"Shopping",
            "subcategory":"Crafts & Fabrics",
            "type":"Retail Goods"
        },
        {
            "category":"Home & Garden",
            "subcategory":"Furniture",
            "type":"Retail Goods"
        }
    ],
    "sg:phone":"+44 1745 851000",
    "sg:postcode":"LL19 9RT",
    "sg:province":"Denbighshire",
    "sg:tags":[
        "retailer"
    ],
    "wof:name":"Curtain Up",
    "wof:placetype":"venue"
},
  "geometry": {"coordinates":[-3.40239501,53.3311233521],"type":"Point"}
}