{
  "type": "Feature",
  "properties": {
    "iso:country":"GB",
    "sg:address":"72 Mill Road",
    "sg:city":"Cambridge",
    "sg:classifiers":[
        {
            "category":"Shopping",
            "subcategory":"News",
            "type":"Retail Goods"
        }
    ],
    "sg:phone":"+44 1223 564185",
    "sg:postcode":"CB1 2AS",
    "sg:province":"Cambridgeshire",
    "sg:tags":[
        "newsagent"
    ],
    "wof:name":"S M News",
    "wof:placetype":"venue"
},
  "geometry": {"coordinates":[0.1362809986,52.200340271],"type":"Point"}
}