{
  "type": "Feature",
  "properties": {
    "iso:country":"GB",
    "sg:address":"215 Blackhorse Rd",
    "sg:city":"Walthamstow",
    "sg:classifiers":[
        {
            "category":"Manufacturing",
            "subcategory":"Building Materials",
            "type":"Manufacturing & Wholesale Goods"
        }
    ],
    "sg:phone":"+44 20 8503 6161",
    "sg:postcode":"E17 6NG",
    "sg:province":"Greater London",
    "sg:tags":[
        "merchant",
        "builder"
    ],
    "wof:name":"Graham Builders Merchants",
    "wof:placetype":"venue"
},
  "geometry": {"coordinates":[-0.039514,51.585941],"type":"Point"}
}