{
  "type": "Feature",
  "properties": {
    "addr:full":"2 Naddervale Cotts), Shaftesbury Road, Wilton Salisbury Wiltshire SP2 0ED",
    "addr:housenumber":"2;cotts",
    "addr:postcode":"sp2 0ed",
    "addr:street":"Naddervale;Shaftesbury Road",
    "iso:country":"GB",
    "sg:address":"2 Naddervale Cotts), Shaftesbury Road, Wilton",
    "sg:city":"Salisbury",
    "sg:classifiers":[
        {
            "category":"Building & Trades",
            "subcategory":"Landscaping Services",
            "type":"Services"
        }
    ],
    "sg:postcode":"SP2 0ED",
    "sg:province":"Wiltshire",
    "sg:tags":[
        "forestry",
        "tree"
    ],
    "wof:name":"Town & Country Tree Surgeons",
    "wof:placetype":"venue"
},
  "geometry": {"coordinates":[-1.863277,51.079548],"type":"Point"}
}