{
  "type": "Feature",
  "properties": {
    "addr:full":"140 Walkley Lane Sheffield South Yorkshire S6 2NZ",
    "addr:housenumber":"140",
    "addr:postcode":"s6 2nz",
    "addr:street":"Walkley Lane",
    "iso:country":"GB",
    "sg:address":"140 Walkley Lane",
    "sg:city":"Sheffield",
    "sg:classifiers":[
        {
            "category":"Recreation",
            "subcategory":"Amusement Park",
            "type":"Entertainment"
        },
        {
            "category":"Autos & Motor Vehicles",
            "subcategory":"Boat Sales",
            "type":"Retail Goods"
        }
    ],
    "sg:phone":"+44 114 234 9808",
    "sg:postcode":"S6 2NZ",
    "sg:province":"South Yorkshire",
    "sg:tags":[
        "machine",
        "gaming",
        "arcade"
    ],
    "wof:name":"Amusement Caterers Sheffield Ltd",
    "wof:placetype":"venue"
},
  "geometry": {"coordinates":[-1.500814,53.396042],"type":"Point"}
}