{
  "type": "Feature",
  "properties": {
    "addr:full":"Britannia Terrace, Fence Houses Houghton-le-spring Durham DH4 6HL",
    "addr:postcode":"dh4 6hl",
    "addr:street":"Terrace",
    "iso:country":"GB",
    "sg:address":"Britannia Terrace, Fence Houses",
    "sg:city":"Houghton-le-spring",
    "sg:classifiers":[
        {
            "category":"Education",
            "subcategory":"School",
            "type":"Public Place"
        },
        {
            "category":"Government",
            "subcategory":"Office",
            "type":"Public Place"
        }
    ],
    "sg:phone":"+44 191 382 3065",
    "sg:postcode":"DH4 6HL",
    "sg:province":"Durham",
    "sg:tags":[
        "local",
        "authority"
    ],
    "wof:name":"Dubmire Infant School",
    "wof:placetype":"venue"
},
  "geometry": {"coordinates":[-1.4985380173,54.842628479],"type":"Point"}
}