{
  "type": "Feature",
  "properties": {
    "addr:full":"33-35 Bath Street Ilkeston Derbyshire DE7 8AH",
    "addr:housenumber":"33-35",
    "addr:postcode":"de7 8ah",
    "addr:street":"Bath Street",
    "iso:country":"GB",
    "sg:address":"33-35 Bath Street",
    "sg:city":"Ilkeston",
    "sg:classifiers":[
        {
            "category":"Home & Garden",
            "subcategory":"Household Appliances",
            "type":"Retail Goods"
        }
    ],
    "sg:phone":"+44 115 944 0352",
    "sg:postcode":"DE7 8AH",
    "sg:province":"Derbyshire",
    "sg:tags":[
        "electrical",
        "domestic"
    ],
    "wof:name":"Dixons",
    "wof:placetype":"venue"
},
  "geometry": {"coordinates":[-1.3090670109,52.9727592468],"type":"Point"}
}