{
  "type": "Feature",
  "properties": {
    "addr:full":"29 Swanborough Rd Newton Abbot Devon TQ12 4JL",
    "addr:housenumber":"29",
    "addr:postcode":"tq12 4jl",
    "addr:street":"Swanborough Rd",
    "iso:country":"GB",
    "sg:address":"29 Swanborough Rd",
    "sg:city":"Newton Abbot",
    "sg:classifiers":[
        {
            "category":"Building & Trades",
            "subcategory":"Construction",
            "type":"Services"
        }
    ],
    "sg:postcode":"TQ12 4JL",
    "sg:province":"Devon",
    "sg:tags":[
        "builder"
    ],
    "wof:name":"Hall,Barry",
    "wof:placetype":"venue"
},
  "geometry": {"coordinates":[-3.5815689564,50.5236053467],"type":"Point"}
}