{
  "type": "Feature",
  "properties": {
    "addr:full":"School Road, Waldringfield Woodbridge Suffolk IP12 4QR",
    "addr:postcode":"ip12 4qr",
    "addr:street":"School Road",
    "iso:country":"GB",
    "sg:address":"School Road, Waldringfield",
    "sg:city":"Woodbridge",
    "sg:classifiers":[
        {
            "category":"Retail",
            "subcategory":"Auto Repair",
            "type":"Services"
        }
    ],
    "sg:phone":"+44 1473 736219",
    "sg:postcode":"IP12 4QR",
    "sg:province":"Suffolk",
    "sg:tags":[
        "modification",
        "garage",
        "related"
    ],
    "wof:name":"Oak Garage",
    "wof:placetype":"venue"
},
  "geometry": {"coordinates":[1.3206429482,52.0527648926],"type":"Point"}
}