{
  "type": "Feature",
  "properties": {
    "addr:full":"Priestner Buildings, Chester Road, Helsby Frodsham Cheshire WA6 0AD",
    "addr:postcode":"wa6 0ad",
    "addr:street":"Chester Road",
    "iso:country":"GB",
    "sg:address":"Priestner Buildings, Chester Road, Helsby",
    "sg:city":"Frodsham",
    "sg:classifiers":[
        {
            "category":"Home & Garden",
            "subcategory":"Carpets & Floor Coverings",
            "type":"Retail Goods"
        }
    ],
    "sg:postcode":"WA6 0AD",
    "sg:province":"Cheshire",
    "sg:tags":[
        "carpets",
        "rug",
        "matting"
    ],
    "wof:name":"Perfect Floors & Interiors",
    "wof:placetype":"venue"
},
  "geometry": {"coordinates":[-2.7687609196,53.2743034363],"type":"Point"}
}