{
  "type": "Feature",
  "properties": {
    "iso:country":"GB",
    "sg:address":"Blackmore Street",
    "sg:city":"Derby",
    "sg:classifiers":[
        {
            "category":"Education",
            "subcategory":"School",
            "type":"Public Place"
        }
    ],
    "sg:phone":"+44 1332 760062",
    "sg:postcode":"DE23 8AX",
    "sg:province":"Derbyshire",
    "sg:tags":[
        "local",
        "authority"
    ],
    "wof:name":"Normanton Infants School",
    "wof:placetype":"venue"
},
  "geometry": {"coordinates":[-1.488294,52.894421],"type":"Point"}
}