{
  "type": "Feature",
  "properties": {
    "iso:country":"GB",
    "sg:address":"6 Duke Street, Formby",
    "sg:city":"Liverpool",
    "sg:classifiers":[
        {
            "category":"Health Services",
            "subcategory":"Dentist",
            "type":"Services"
        }
    ],
    "sg:phone":"+44 1704 876200",
    "sg:postcode":"L37 4AS",
    "sg:province":"Lancashire",
    "wof:name":"The Dental Practice",
    "wof:placetype":"venue"
},
  "geometry": {"coordinates":[-3.069847,53.553032],"type":"Point"}
}