{
  "type": "Feature",
  "properties": {
    "iso:country":"GB",
    "sg:address":"87 Normanton Road",
    "sg:city":"Derby",
    "sg:classifiers":[
        {
            "category":"Retail",
            "subcategory":"Laundry & Dry Cleaning",
            "type":"Services"
        }
    ],
    "sg:phone":"+44 1332 292495",
    "sg:postcode":"DE1 2GH",
    "sg:province":"Derbyshire",
    "sg:tags":[
        "launderette"
    ],
    "wof:name":"Bubbles Launderette",
    "wof:placetype":"venue"
},
  "geometry": {"coordinates":[-1.4775259495,52.9153862],"type":"Point"}
}