{
  "type": "Feature",
  "properties": {
    "addr:full":"66 Walton Road Chesterfield Derbyshire S40 3BY",
    "addr:housenumber":"66",
    "addr:postcode":"s40 3by",
    "addr:street":"Walton Road",
    "iso:country":"GB",
    "sg:address":"66 Walton Road",
    "sg:city":"Chesterfield",
    "sg:classifiers":[
        {
            "category":"Building & Trades",
            "subcategory":"Construction",
            "type":"Services"
        }
    ],
    "sg:postcode":"S40 3BY",
    "sg:province":"Derbyshire",
    "sg:tags":[
        "builder"
    ],
    "wof:name":"P A Wibberley Building",
    "wof:placetype":"venue"
},
  "geometry": {"coordinates":[-1.452752,53.227741],"type":"Point"}
}