{
  "type": "Feature",
  "properties": {
    "iso:country":"GB",
    "sg:address":"4 Church Street",
    "sg:city":"Cramlington",
    "sg:classifiers":[
        {
            "category":"Personal",
            "subcategory":"Barber",
            "type":"Services"
        }
    ],
    "sg:phone":"+44 1670 730074",
    "sg:postcode":"NE23 6QQ",
    "sg:province":"Northumberland",
    "sg:tags":[
        "men's",
        "hairdresser"
    ],
    "wof:name":"Village Barber Shop",
    "wof:placetype":"venue"
},
  "geometry": {"coordinates":[-1.564857,55.078117],"type":"Point"}
}