{
  "type": "Feature",
  "properties": {
    "addr:full":"27 Hickling, Hoveton Close King's Lynn Norfolk PE30 4XH",
    "addr:housenumber":"27",
    "addr:postcode":"pe30 4xh",
    "addr:street":"Hickling Hoveton Close",
    "iso:country":"GB",
    "sg:address":"27 Hickling, Hoveton Close",
    "sg:city":"King's Lynn",
    "sg:classifiers":[
        {
            "category":"Parking",
            "type":"Transportation"
        }
    ],
    "sg:postcode":"PE30 4XH",
    "sg:province":"Norfolk",
    "sg:tags":[
        "car",
        "valet"
    ],
    "wof:name":"Image",
    "wof:placetype":"venue"
},
  "geometry": {"coordinates":[0.4399400055,52.7540206909],"type":"Point"}
}