{
  "type": "Feature",
  "properties": {
    "iso:country":"GB",
    "sg:address":"Suite 1, Imperial Buildings, Corporation Street",
    "sg:city":"Rotherham",
    "sg:classifiers":[
        {
            "category":"Professional",
            "subcategory":"Employment Agencies",
            "type":"Services"
        }
    ],
    "sg:phone":"+44 1709 375700",
    "sg:postcode":"S60 1NP",
    "sg:province":"South Yorkshire",
    "sg:tags":[
        "consultant"
    ],
    "wof:name":"Travail Employment Group",
    "wof:placetype":"venue"
},
  "geometry": {"coordinates":[-1.3542430401,53.4298744202],"type":"Point"}
}