{
  "type": "Feature",
  "properties": {
    "addr:full":"Lion House, 81 Haltwhistle Road, South Woodham Ferrers Chelmsford Essex CM3 5ZA",
    "addr:housenumber":"81",
    "addr:postcode":"cm3 5za",
    "addr:street":"Haltwhistle Road",
    "iso:country":"GB",
    "sg:address":"Lion House, 81 Haltwhistle Road, South Woodham Ferrers",
    "sg:city":"Chelmsford",
    "sg:classifiers":[
        {
            "category":"Manufacturing",
            "subcategory":"Rubber & Plastics",
            "type":"Manufacturing & Wholesale Goods"
        }
    ],
    "sg:postcode":"CM3 5ZA",
    "sg:province":"Essex",
    "sg:tags":[
        "supplier",
        "stockist"
    ],
    "wof:name":"D L Geaves & Partners Ltd.",
    "wof:placetype":"venue"
},
  "geometry": {"coordinates":[0.604765,51.648399],"type":"Point"}
}