{
  "type": "Feature",
  "properties": {
    "iso:country":"GB",
    "sg:address":"31 The Cross",
    "sg:city":"Worcester",
    "sg:classifiers":[
        {
            "category":"Building & Trades",
            "subcategory":"Equipment Rental",
            "type":"Services"
        }
    ],
    "sg:phone":"+44 1905 29000",
    "sg:postcode":"WR1 3PZ",
    "sg:province":"Worcestershire",
    "sg:tags":[
        "supply"
    ],
    "wof:name":"Burnstyle Wholesale Ltd",
    "wof:placetype":"venue"
},
  "geometry": {"coordinates":[-2.221224,52.193146],"type":"Point"}
}