{
  "type": "Feature",
  "properties": {
    "addr:full":"New Road, Burntwood Walsall Staffordshire WS7 0BT",
    "addr:postcode":"ws7 0bt",
    "addr:street":"New Road",
    "iso:country":"GB",
    "sg:address":"New Road, Burntwood",
    "sg:city":"Walsall",
    "sg:classifiers":[
        {
            "category":"Freight",
            "type":"Transportation"
        }
    ],
    "sg:phone":"+44 1543 684339",
    "sg:postcode":"WS7 0BT",
    "sg:province":"Staffordshire",
    "sg:tags":[
        "haulage",
        "road"
    ],
    "wof:name":"A & J Transport Services",
    "wof:placetype":"venue"
},
  "geometry": {"coordinates":[-1.915184021,52.6784515381],"type":"Point"}
}