{
  "type": "Feature",
  "properties": {
    "iso:country":"GB",
    "sg:address":"10 Blenheim Crescent",
    "sg:city":"London",
    "sg:classifiers":[
        {
            "category":"Shopping",
            "subcategory":"Gifts & Souvenirs",
            "type":"Retail Goods"
        }
    ],
    "sg:phone":"+44 20 7727 0288",
    "sg:postcode":"W11 1NN",
    "sg:province":"Greater London",
    "sg:tags":[
        "shop"
    ],
    "sg:website":"http://www.ceramicablue.co.uk",
    "wof:name":"Ceramica Blue",
    "wof:placetype":"venue"
},
  "geometry": {"coordinates":[-0.20564,51.515884],"type":"Point"}
}