{
  "type": "Feature",
  "properties": {
    "iso:country":"GB",
    "sg:address":"30 Berney Road",
    "sg:city":"Croydon",
    "sg:classifiers":[
        {
            "category":"Professional",
            "subcategory":"Art Services",
            "type":"Services"
        }
    ],
    "sg:phone":"+44 20 8684 5363",
    "sg:postcode":"CR0 2JX",
    "sg:province":"Surrey",
    "sg:tags":[
        "photographer"
    ],
    "wof:name":"Breeze Photographers",
    "wof:placetype":"venue"
},
  "geometry": {"coordinates":[-0.095016,51.384602],"type":"Point"}
}