{
  "type": "Feature",
  "properties": {
    "addr:full":", Slapton Kingsbridge Devon TQ7 2PN",
    "addr:housenumber":"slapton",
    "addr:postcode":"tq7 2pn",
    "addr:street":"Kingsbridge Devon",
    "iso:country":"GB",
    "sg:address":", Slapton",
    "sg:city":"Kingsbridge",
    "sg:classifiers":[
        {
            "category":"Bars & Pubs",
            "type":"Food & Drink"
        }
    ],
    "sg:phone":"+44 1548 580800",
    "sg:postcode":"TQ7 2PN",
    "sg:province":"Devon",
    "sg:tags":[
        "pubs",
        "inn"
    ],
    "wof:name":"Queens Arms",
    "wof:placetype":"venue"
},
  "geometry": {"coordinates":[-3.6965789795,50.2690925598],"type":"Point"}
}