{
  "type": "Feature",
  "properties": {
    "iso:country":"GB",
    "sg:address":"18a Moat Road, Pleck",
    "sg:city":"Walsall",
    "sg:classifiers":[
        {
            "category":"Building & Trades",
            "subcategory":"Construction",
            "type":"Services"
        }
    ],
    "sg:phone":"+44 1922 648791",
    "sg:postcode":"WS2 9PJ",
    "sg:province":"West Midlands",
    "sg:tags":[
        "roofing"
    ],
    "wof:name":"Highgate Felt Roofing Co. Ltd.",
    "wof:placetype":"venue"
},
  "geometry": {"coordinates":[-1.996263,52.584591],"type":"Point"}
}