{
  "type": "Feature",
  "properties": {
    "iso:country":"GB",
    "sg:address":"36 Wedderburn Street",
    "sg:city":"Dunfermline",
    "sg:classifiers":[
        {
            "category":"Home & Garden",
            "subcategory":"Home Furnishings",
            "type":"Retail Goods"
        },
        {
            "category":"Building & Trades",
            "subcategory":"Construction",
            "type":"Services"
        }
    ],
    "sg:phone":"+44 1383 622690",
    "sg:postcode":"KY11 4PT",
    "sg:province":"Fife",
    "sg:tags":[
        "mantelpiece",
        "fireplace"
    ],
    "wof:name":"Peter Maccaskill Fireplace Specialist",
    "wof:placetype":"venue"
},
  "geometry": {"coordinates":[-3.439472,56.064053],"type":"Point"}
}