{
  "type": "Feature",
  "properties": {
    "iso:country":"GB",
    "sg:address":"Ewer House 44-46 Crouch Street",
    "sg:city":"Colchester",
    "sg:classifiers":[
        {
            "category":"Utilities",
            "type":"Services"
        }
    ],
    "sg:phone":"+44 1206 544445",
    "sg:postcode":"CO3 3HH",
    "sg:province":"Essex",
    "sg:tags":[
        "internet"
    ],
    "wof:name":"C C O M Internet Services Ltd.",
    "wof:placetype":"venue"
},
  "geometry": {"coordinates":[0.892985,51.887554],"type":"Point"}
}