{
  "type": "Feature",
  "properties": {
    "addr:full":"19 Westkirke Avenue Grimsby Lincolnshire DN33 2HS",
    "addr:housenumber":"19",
    "addr:postcode":"dn33 2hs",
    "addr:street":"Westkirke Avenue",
    "iso:country":"GB",
    "sg:address":"19 Westkirke Avenue",
    "sg:city":"Grimsby",
    "sg:classifiers":[
        {
            "category":"Wholesale",
            "subcategory":"Sporting Goods",
            "type":"Manufacturing & Wholesale Goods"
        }
    ],
    "sg:phone":"+44 1472 878246",
    "sg:postcode":"DN33 2HS",
    "sg:province":"Lincolnshire",
    "sg:tags":[
        "mnfr",
        "sport",
        "equipment"
    ],
    "wof:name":"Mr Stringer",
    "wof:placetype":"venue"
},
  "geometry": {"coordinates":[-0.0876400024,53.5360336304],"type":"Point"}
}