{
  "type": "Feature",
  "properties": {
    "addr:full":"Chestnut Field House, Chestnut Field, Regents Place Rugby Warwickshire CV21 2TL",
    "addr:postcode":"cv21 2tl",
    "addr:street":"Chestnut Field Regents Place",
    "iso:country":"GB",
    "sg:address":"Chestnut Field House, Chestnut Field, Regents Place",
    "sg:city":"Rugby",
    "sg:classifiers":[
        {
            "category":"Insurance",
            "subcategory":"Insurance Agent",
            "type":"Services"
        }
    ],
    "sg:postcode":"CV21 2TL",
    "sg:province":"Warwickshire",
    "sg:tags":[
        "broker"
    ],
    "wof:name":"Appleton Insurance",
    "wof:placetype":"venue"
},
  "geometry": {"coordinates":[-1.261454,52.373615],"type":"Point"}
}