{
  "type": "Feature",
  "properties": {
    "addr:full":"Unit 56/57 Market Hall Sunderland Tyne and Wear SR1 3DG",
    "addr:housenumber":"unit 56 / 57",
    "addr:postcode":"sr1 3dg",
    "addr:street":"Market Hall",
    "iso:country":"GB",
    "sg:address":"Unit 56/57 Market Hall",
    "sg:city":"Sunderland",
    "sg:classifiers":[
        {
            "category":"Shopping",
            "subcategory":"Hobbies, Toys, & Games",
            "type":"Retail Goods"
        }
    ],
    "sg:phone":"+44 191 510 0277",
    "sg:postcode":"SR1 3DG",
    "sg:province":"Tyne and Wear",
    "sg:tags":[
        "shop",
        "toy"
    ],
    "wof:name":"Harlequin Gifts",
    "wof:placetype":"venue"
},
  "geometry": {"coordinates":[-1.3887490034,54.9046516418],"type":"Point"}
}