{
  "type": "Feature",
  "properties": {
    "addr:full":"London Road, Kelvedon Colchester Essex CO5 9AP",
    "addr:postcode":"co5 9ap",
    "addr:street":"London Road",
    "iso:country":"GB",
    "sg:address":"London Road, Kelvedon",
    "sg:city":"Colchester",
    "sg:classifiers":[
        {
            "category":"Social Services",
            "subcategory":"Retirement Home",
            "type":"Services"
        }
    ],
    "sg:phone":"+44 1376 570359",
    "sg:postcode":"CO5 9AP",
    "sg:province":"Essex",
    "sg:tags":[
        "residential",
        "care"
    ],
    "wof:name":"St.Dominics Residential Home Ltd.",
    "wof:placetype":"venue"
},
  "geometry": {"coordinates":[0.705185,51.839973],"type":"Point"}
}