{
  "type": "Feature",
  "properties": {
    "iso:country":"GB",
    "sg:address":"10 Billy Lane",
    "sg:city":"Hebden Bridge",
    "sg:classifiers":[
        {
            "category":"Communications",
            "type":"Services"
        }
    ],
    "sg:phone":"+44 1422 847246",
    "sg:postcode":"HX7 8RY",
    "sg:province":"West Yorkshire",
    "sg:tags":[
        "data",
        "network"
    ],
    "wof:name":"Advanced Recognition Ltd",
    "wof:placetype":"venue"
},
  "geometry": {"coordinates":[-1.999613,53.751362],"type":"Point"}
}