{
  "type": "Feature",
  "properties": {
    "addr:full":"Oak House, Pond Lane, Greetham Oakham Leicestershire LE15 7NW",
    "addr:postcode":"le15 7nw",
    "addr:street":"Pond Lane",
    "iso:country":"GB",
    "sg:address":"Oak House, Pond Lane, Greetham",
    "sg:city":"Oakham",
    "sg:classifiers":[
        {
            "category":"Health Services",
            "subcategory":"Nursing And Care Facility",
            "type":"Services"
        },
        {
            "category":"Social Services",
            "subcategory":"Retirement Home",
            "type":"Services"
        }
    ],
    "sg:phone":"+44 1572 812647",
    "sg:postcode":"LE15 7NW",
    "sg:province":"Leicestershire",
    "sg:tags":[
        "residential"
    ],
    "wof:name":"Oak House Residential Home",
    "wof:placetype":"venue"
},
  "geometry": {"coordinates":[-0.6296079755,52.7201576233],"type":"Point"}
}