{
  "type": "Feature",
  "properties": {
    "iso:country":"GB",
    "sg:address":"3 Marine Terrace Mews",
    "sg:city":"Brighton",
    "sg:classifiers":[
        {
            "category":"Retail",
            "subcategory":"Auto Repair",
            "type":"Services"
        }
    ],
    "sg:phone":"+44 1273 697712",
    "sg:postcode":"BN2 1AR",
    "sg:province":"East Sussex",
    "sg:tags":[
        "modification",
        "garage"
    ],
    "wof:name":"Marine Garage",
    "wof:placetype":"venue"
},
  "geometry": {"coordinates":[-0.126451,50.819145],"type":"Point"}
}