{
  "type": "Feature",
  "properties": {
    "iso:country":"GB",
    "sg:address":"60 Robsart Place, Cumnor",
    "sg:city":"Oxford",
    "sg:classifiers":[
        {
            "category":"Building & Trades",
            "subcategory":"Construction",
            "type":"Services"
        }
    ],
    "sg:postcode":"OX2 9QT",
    "sg:province":"Oxfordshire",
    "sg:tags":[
        "builder"
    ],
    "wof:name":"C.J. Lennox Ltd",
    "wof:placetype":"venue"
},
  "geometry": {"coordinates":[-1.332045,51.730965],"type":"Point"}
}