{
  "type": "Feature",
  "properties": {
    "iso:country":"GB",
    "sg:address":"59a Gerard St, Ashton-in-makerfield",
    "sg:city":"Wigan",
    "sg:classifiers":[
        {
            "category":"Taxi",
            "type":"Transportation"
        }
    ],
    "sg:phone":"+44 1942 703103",
    "sg:postcode":"WN4 9AG",
    "sg:province":"Lancashire",
    "sg:tags":[
        "mini",
        "cab"
    ],
    "wof:name":"A B C Cars",
    "wof:placetype":"venue"
},
  "geometry": {"coordinates":[-2.637744,53.486378],"type":"Point"}
}