{
  "type": "Feature",
  "properties": {
    "addr:full":"Cessnock Road, Hurlford Kilmarnock East Ayrshire KA1 5DD",
    "addr:postcode":"ka1 5dd",
    "addr:street":"Cessnock Road",
    "iso:country":"GB",
    "sg:address":"Cessnock Road, Hurlford",
    "sg:city":"Kilmarnock",
    "sg:classifiers":[
        {
            "category":"Sports & Exercise",
            "subcategory":"Skate Park",
            "type":"Entertainment"
        }
    ],
    "sg:phone":"+44 1563 546000",
    "sg:postcode":"KA1 5DD",
    "sg:province":"East Ayrshire",
    "sg:tags":[
        "mnfrs",
        "brake",
        "clutch"
    ],
    "wof:name":"Federal-Mogul Eurofriction Ltd.",
    "wof:placetype":"venue"
},
  "geometry": {"coordinates":[-4.4498062134,55.5991287231],"type":"Point"}
}