{
  "type": "Feature",
  "properties": {
    "addr:full":"125 North Rd Chesterfield Derbyshire S43 4PQ",
    "addr:housenumber":"125",
    "addr:postcode":"s43 4pq",
    "addr:street":"North Rd",
    "iso:country":"GB",
    "sg:address":"125 North Rd",
    "sg:city":"Chesterfield",
    "sg:classifiers":[
        {
            "category":"Retail",
            "subcategory":"Driving School",
            "type":"Services"
        }
    ],
    "sg:phone":"+44 1246 812115",
    "sg:postcode":"S43 4PQ",
    "sg:province":"Derbyshire",
    "wof:name":"Roger Harvey",
    "wof:placetype":"venue"
},
  "geometry": {"coordinates":[-1.26414,53.278744],"type":"Point"}
}