{
  "type": "Feature",
  "properties": {
    "addr:full":"Dukes Valley, Windsor Rd Gerrards Cross Buckinghamshire SL9 8SR",
    "addr:postcode":"sl9 8sr",
    "addr:street":"Windsor Rd",
    "iso:country":"GB",
    "sg:address":"Dukes Valley, Windsor Rd",
    "sg:city":"Gerrards Cross",
    "sg:classifiers":[
        {
            "category":"Wholesale",
            "subcategory":"Scrap",
            "type":"Manufacturing & Wholesale Goods"
        }
    ],
    "sg:phone":"+44 1753 662666",
    "sg:postcode":"SL9 8SR",
    "sg:province":"Buckinghamshire",
    "sg:tags":[
        "waste",
        "metal"
    ],
    "wof:name":"Regalzone (U K) Ltd",
    "wof:placetype":"venue"
},
  "geometry": {"coordinates":[-0.5752279758,51.5701828003],"type":"Point"}
}