{
  "type": "Feature",
  "properties": {
    "addr:full":"70 Plains Road, Mapperley Nottingham Nottinghamshire NG3 5LE",
    "addr:housenumber":"70",
    "addr:postcode":"ng3 5le",
    "addr:street":"Plains Road",
    "iso:country":"GB",
    "sg:address":"70 Plains Road, Mapperley",
    "sg:city":"Nottingham",
    "sg:classifiers":[
        {
            "category":"Freight",
            "type":"Transportation"
        }
    ],
    "sg:postcode":"NG3 5LE",
    "sg:province":"Nottinghamshire",
    "sg:tags":[
        "haulage",
        "road"
    ],
    "wof:name":"Michael J Scottney",
    "wof:placetype":"venue"
},
  "geometry": {"coordinates":[-1.1132609844,52.9892883301],"type":"Point"}
}