{
  "type": "Feature",
  "properties": {
    "addr:full":"11 Main Street, Cairnbulg Fraserburgh Aberdeenshire AB43 8YJ",
    "addr:housenumber":"11",
    "addr:postcode":"ab43 8yj",
    "addr:street":"Main Street",
    "iso:country":"GB",
    "sg:address":"11 Main Street, Cairnbulg",
    "sg:city":"Fraserburgh",
    "sg:classifiers":[
        {
            "category":"Freight",
            "type":"Transportation"
        }
    ],
    "sg:phone":"+44 1346 582644",
    "sg:postcode":"AB43 8YJ",
    "sg:province":"Aberdeenshire",
    "sg:tags":[
        "haulage",
        "transport",
        "road"
    ],
    "wof:name":"Ronald Noble",
    "wof:placetype":"venue"
},
  "geometry": {"coordinates":[-1.9330459833,57.6769981384],"type":"Point"}
}