{
  "type": "Feature",
  "properties": {
    "addr:full":"51 Bargates Christchurch Dorset BH23 1QE",
    "addr:housenumber":"51",
    "addr:postcode":"bh23 1qe",
    "addr:street":"Bargates",
    "iso:country":"GB",
    "sg:address":"51 Bargates",
    "sg:city":"Christchurch",
    "sg:classifiers":[
        {
            "category":"Banks & Credit Unions",
            "subcategory":"Investment Brokerage",
            "type":"Services"
        },
        {
            "category":"Banks & Credit Unions",
            "subcategory":"Financial Services",
            "type":"Services"
        }
    ],
    "sg:phone":"+44 1202 386386",
    "sg:postcode":"BH23 1QE",
    "sg:province":"Dorset",
    "sg:tags":[
        "adviser",
        "consultant",
        "vehicle",
        "independent"
    ],
    "wof:name":"Kingstons Investment Partnership Ltd",
    "wof:placetype":"venue"
},
  "geometry": {"coordinates":[-1.780132,50.736996],"type":"Point"}
}