{
  "type": "Feature",
  "properties": {
    "addr:full":"Saddlers Yd, 71 Saddler St Durham Durham DH1 3NP",
    "addr:housenumber":"71",
    "addr:postcode":"dh1 3np",
    "addr:street":"Yd;Saddler St",
    "iso:country":"GB",
    "sg:address":"Saddlers Yd, 71 Saddler St",
    "sg:city":"Durham",
    "sg:classifiers":[
        {
            "category":"Cafe",
            "type":"Food & Drink"
        }
    ],
    "sg:postcode":"DH1 3NP",
    "sg:province":"Durham",
    "sg:tags":[
        "tea",
        "room"
    ],
    "wof:name":"Powney,Michael,",
    "wof:placetype":"venue"
},
  "geometry": {"coordinates":[-1.5746079683,54.7775344849],"type":"Point"}
}