{
  "type": "Feature",
  "properties": {
    "iso:country":"GB",
    "sg:address":"63 Queensland Road",
    "sg:city":"Hartlepool",
    "sg:classifiers":[
        {
            "category":"Building & Trades",
            "subcategory":"Construction",
            "type":"Services"
        }
    ],
    "sg:phone":"+44 1429 276107",
    "sg:postcode":"TS25 1LY",
    "sg:province":"Durham",
    "sg:tags":[
        "tiling",
        "contractor"
    ],
    "wof:name":"P & P Improvements",
    "wof:placetype":"venue"
},
  "geometry": {"coordinates":[-1.2180839777,54.6649284363],"type":"Point"}
}