{
  "type": "Feature",
  "properties": {
    "iso:country":"GB",
    "sg:address":"Pett Level Road, Pett Level",
    "sg:city":"Hastings",
    "sg:classifiers":[
        {
            "category":"Organizations",
            "subcategory":"Membership Organization",
            "type":"Services"
        }
    ],
    "sg:phone":"+44 1424 812080",
    "sg:postcode":"TN35 4EH",
    "sg:province":"East Sussex",
    "sg:tags":[
        "club"
    ],
    "wof:name":"New Beach Club",
    "wof:placetype":"venue"
},
  "geometry": {"coordinates":[0.67302,50.881939],"type":"Point"}
}