{
  "type": "Feature",
  "properties": {
    "addr:full":"99 Aberdale Rd Leicester Leicestershire LE2 6GE",
    "addr:housenumber":"99",
    "addr:postcode":"le2 6ge",
    "addr:street":"Aberdale Rd",
    "iso:country":"GB",
    "sg:address":"99 Aberdale Rd",
    "sg:city":"Leicester",
    "sg:classifiers":[
        {
            "category":"Fast Food",
            "type":"Food & Drink"
        }
    ],
    "sg:phone":"+44 116 257 0981",
    "sg:postcode":"LE2 6GE",
    "sg:province":"Leicestershire",
    "sg:tags":[
        "away",
        "take"
    ],
    "wof:name":"Loon Shing",
    "wof:placetype":"venue"
},
  "geometry": {"coordinates":[-1.1205830574,52.5987434387],"type":"Point"}
}