{
  "type": "Feature",
  "properties": {
    "iso:country":"GB",
    "sg:address":"1 Fielding Street",
    "sg:city":"Stoke-on-trent",
    "sg:classifiers":[
        {
            "category":"Professional",
            "subcategory":"Engineering",
            "type":"Services"
        }
    ],
    "sg:phone":"+44 1782 844495",
    "sg:postcode":"ST4 4HD",
    "sg:province":"Staffordshire",
    "wof:name":"Glass Shearing Services Ltd.",
    "wof:placetype":"venue"
},
  "geometry": {"coordinates":[-2.182694912,52.9967041016],"type":"Point"}
}