{
  "type": "Feature",
  "properties": {
    "addr:full":"The Water Mill, Station Road, South Luffenham Oakham Leicestershire LE15 8NB",
    "addr:postcode":"le15 8nb",
    "addr:street":"Station Road South",
    "iso:country":"GB",
    "sg:address":"The Water Mill, Station Road, South Luffenham",
    "sg:city":"Oakham",
    "sg:classifiers":[
        {
            "category":"Professional",
            "subcategory":"Business Services",
            "type":"Services"
        }
    ],
    "sg:phone":"+44 1780 722900",
    "sg:postcode":"LE15 8NB",
    "sg:province":"Leicestershire",
    "sg:tags":[
        "organisation",
        "trade"
    ],
    "sg:website":"http://www.icm.org.uk",
    "wof:name":"Institute of Credit Management",
    "wof:placetype":"venue"
},
  "geometry": {"coordinates":[-0.609858,52.605846],"type":"Point"}
}