{
  "type": "Feature",
  "properties": {
    "addr:full":"33 Bridge Street Heywood Lancashire OL10 1JF",
    "addr:housenumber":"33",
    "addr:postcode":"ol10 1jf",
    "addr:street":"Bridge Street",
    "iso:country":"GB",
    "sg:address":"33 Bridge Street",
    "sg:city":"Heywood",
    "sg:classifiers":[
        {
            "category":"Fast Food",
            "type":"Food & Drink"
        }
    ],
    "sg:phone":"+44 1706 360850",
    "sg:postcode":"OL10 1JF",
    "sg:province":"Lancashire",
    "sg:tags":[
        "away",
        "meal",
        "outlet",
        "take"
    ],
    "wof:name":"KEBAB CENTRE",
    "wof:placetype":"venue"
},
  "geometry": {"coordinates":[-2.225781,53.59383],"type":"Point"}
}