{
  "type": "Feature",
  "properties": {
    "iso:country":"GB",
    "sg:address":"607 Holloway Rd",
    "sg:city":"London",
    "sg:classifiers":[
        {
            "category":"Professional",
            "subcategory":"Business Services",
            "type":"Services"
        }
    ],
    "sg:phone":"+44 20 7561 0541",
    "sg:postcode":"N19 4DJ",
    "sg:province":"Greater London",
    "wof:name":"Eurofast Systems Ltd",
    "wof:placetype":"venue"
},
  "geometry": {"coordinates":[-0.129229,51.563839],"type":"Point"}
}