{
  "type": "Feature",
  "properties": {
    "addr:full":"209 Crewe Road West Edinburgh City of Edinburgh EH5 2PG",
    "addr:housenumber":"209",
    "addr:postcode":"eh5 2pg",
    "addr:street":"Crewe Road West Edinburgh",
    "iso:country":"GB",
    "sg:address":"209 Crewe Road West",
    "sg:city":"Edinburgh",
    "sg:classifiers":[
        {
            "category":"Retail",
            "subcategory":"Storage",
            "type":"Services"
        }
    ],
    "sg:phone":"+44 131 657 1766",
    "sg:postcode":"EH5 2PG",
    "sg:province":"City of Edinburgh",
    "sg:tags":[
        "household",
        "activity",
        "domestic",
        "removal"
    ],
    "wof:name":"Cheap Removals",
    "wof:placetype":"venue"
},
  "geometry": {"coordinates":[-3.2395560741,55.9764671326],"type":"Point"}
}