{
  "type": "Feature",
  "properties": {
    "addr:full":"Marshall St Alfreton Derbyshire DE55 7BW",
    "addr:postcode":"de55 7bw",
    "addr:street":"Marshall St",
    "iso:country":"GB",
    "sg:address":"Marshall St",
    "sg:city":"Alfreton",
    "sg:classifiers":[
        {
            "category":"Farming",
            "subcategory":"Nursery",
            "type":"Manufacturing & Wholesale Goods"
        }
    ],
    "sg:postcode":"DE55 7BW",
    "sg:province":"Derbyshire",
    "sg:tags":[
        "creche"
    ],
    "wof:name":"Grange Day Nursery (The)",
    "wof:placetype":"venue"
},
  "geometry": {"coordinates":[-1.3880339861,53.0949745178],"type":"Point"}
}