{
  "type": "Feature",
  "properties": {
    "addr:full":"Irthlingborough Road Wellingborough Northamptonshire NN8 1RA",
    "addr:postcode":"nn8 1ra",
    "addr:street":"Irthlingborough Road",
    "iso:country":"GB",
    "sg:address":"Irthlingborough Road",
    "sg:city":"Wellingborough",
    "sg:classifiers":[
        {
            "category":"Professional",
            "subcategory":"Testing Lab",
            "type":"Services"
        }
    ],
    "sg:postcode":"NN8 1RA",
    "sg:province":"Northamptonshire",
    "sg:tags":[
        "mot"
    ],
    "wof:name":"Alton Motors",
    "wof:placetype":"venue"
},
  "geometry": {"coordinates":[-0.6774340272,52.2982063293],"type":"Point"}
}