{
  "type": "Feature",
  "properties": {
    "addr:full":"27 High Street Hythe Kent CT21 5AD",
    "addr:housenumber":"27",
    "addr:postcode":"ct21 5ad",
    "addr:street":"High Street",
    "iso:country":"GB",
    "sg:address":"27 High Street",
    "sg:city":"Hythe",
    "sg:classifiers":[
        {
            "category":"Banks & Credit Unions",
            "subcategory":"Bank",
            "type":"Services"
        },
        {
            "category":"Home & Garden",
            "subcategory":"Furniture",
            "type":"Retail Goods"
        }
    ],
    "sg:phone":"+44 1303 266187",
    "sg:postcode":"CT21 5AD",
    "sg:province":"Kent",
    "sg:tags":[
        "broker",
        "mortgage"
    ],
    "wof:name":"Newman Furnishers",
    "wof:placetype":"venue"
},
  "geometry": {"coordinates":[1.081746,51.071445],"type":"Point"}
}