{
  "type": "Feature",
  "properties": {
    "addr:full":"136 Townhill Road Swansea Neath Port Talbot SA1 6PN",
    "addr:housenumber":"136",
    "addr:postcode":"sa1 6pn",
    "addr:street":"Townhill Road",
    "iso:country":"GB",
    "sg:address":"136 Townhill Road",
    "sg:city":"Swansea",
    "sg:classifiers":[
        {
            "category":"Shopping",
            "subcategory":"Musical Instruments",
            "type":"Retail Goods"
        }
    ],
    "sg:phone":"+44 1792 469159",
    "sg:postcode":"SA1 6PN",
    "sg:province":"Neath Port Talbot",
    "wof:name":"T O'Brien",
    "wof:placetype":"venue"
},
  "geometry": {"coordinates":[-3.971378,51.627426],"type":"Point"}
}