{
  "type": "Feature",
  "properties": {
    "addr:full":"2 Beastfair Pontefract North Yorkshire WF8 1AW",
    "addr:housenumber":"2",
    "addr:postcode":"wf8 1aw",
    "addr:street":"Beastfair Pontefract",
    "iso:country":"GB",
    "sg:address":"2 Beastfair",
    "sg:city":"Pontefract",
    "sg:classifiers":[
        {
            "category":"Shopping",
            "subcategory":"News",
            "type":"Retail Goods"
        }
    ],
    "sg:phone":"+44 1977 600918",
    "sg:postcode":"WF8 1AW",
    "sg:province":"North Yorkshire",
    "sg:tags":[
        "newsagent"
    ],
    "wof:name":"News Affair",
    "wof:placetype":"venue"
},
  "geometry": {"coordinates":[-1.312399,53.69138],"type":"Point"}
}