{
  "type": "Feature",
  "properties": {
    "addr:full":"1247 Dumbarton Road Glasgow Glasgow City G14 9UU",
    "addr:housenumber":"1247",
    "addr:postcode":"g14 9uu",
    "addr:street":"Dumbarton Road",
    "iso:country":"GB",
    "sg:address":"1247 Dumbarton Road",
    "sg:city":"Glasgow",
    "sg:classifiers":[
        {
            "category":"Retail",
            "subcategory":"Repair Shop",
            "type":"Services"
        }
    ],
    "sg:phone":"+44 141 954 5300",
    "sg:postcode":"G14 9UU",
    "sg:province":"Glasgow City",
    "sg:tags":[
        "upholstering",
        "upholsterer"
    ],
    "wof:name":"Stitch 'N' Time",
    "wof:placetype":"venue"
},
  "geometry": {"coordinates":[-4.3394780159,55.8746948242],"type":"Point"}
}