{
  "type": "Feature",
  "properties": {
    "addr:full":"10 South Walk Cwmbran Monmouthshire NP44 1PU",
    "addr:housenumber":"10",
    "addr:postcode":"np44 1pu",
    "addr:street":"South Walk",
    "iso:country":"GB",
    "sg:address":"10 South Walk",
    "sg:city":"Cwmbran",
    "sg:classifiers":[
        {
            "category":"Travel",
            "subcategory":"Travel Agent",
            "type":"Entertainment"
        }
    ],
    "sg:phone":"+44 1633 872521",
    "sg:postcode":"NP44 1PU",
    "sg:province":"Monmouthshire",
    "wof:name":"Going Places Leisure Travel",
    "wof:placetype":"venue"
},
  "geometry": {"coordinates":[-3.0258638859,51.6574668884],"type":"Point"}
}