{
  "type": "Feature",
  "properties": {
    "addr:full":"Main Street, Greenodd Ulverston Cumbria LA12 7RB",
    "addr:postcode":"la12 7rb",
    "addr:street":"Main Street",
    "iso:country":"GB",
    "sg:address":"Main Street, Greenodd",
    "sg:city":"Ulverston",
    "sg:classifiers":[
        {
            "category":"Government",
            "subcategory":"Post Office",
            "type":"Public Place"
        }
    ],
    "sg:phone":"+44 1229 861201",
    "sg:postcode":"LA12 7RB",
    "sg:province":"Cumbria",
    "wof:name":"GREENODD POST OFFICE",
    "wof:placetype":"venue"
},
  "geometry": {"coordinates":[-3.092354,54.196732],"type":"Point"}
}