{
  "type": "Feature",
  "properties": {
    "addr:full":"13b Hopetoun La Bathgate West Lothian EH48 1PP",
    "addr:housenumber":"13b",
    "addr:postcode":"eh48 1pp",
    "addr:street":"Hopetoun La Bathgate",
    "iso:country":"GB",
    "sg:address":"13b Hopetoun La",
    "sg:city":"Bathgate",
    "sg:classifiers":[
        {
            "category":"Professional",
            "subcategory":"Employment Agencies",
            "type":"Services"
        }
    ],
    "sg:phone":"+44 1506 656969",
    "sg:postcode":"EH48 1PP",
    "sg:province":"West Lothian",
    "sg:tags":[
        "recr",
        "hire",
        "driver"
    ],
    "wof:name":"Temp Drive",
    "wof:placetype":"venue"
},
  "geometry": {"coordinates":[-3.640654,55.902374],"type":"Point"}
}