{
  "type": "Feature",
  "properties": {
    "iso:country":"GB",
    "sg:address":"58h Arthur Street",
    "sg:city":"Redditch",
    "sg:classifiers":[
        {
            "category":"Professional",
            "subcategory":"Engineering",
            "type":"Services"
        }
    ],
    "sg:phone":"+44 1527 510092",
    "sg:postcode":"B98 8JY",
    "sg:province":"Warwickshire",
    "wof:name":"Avalon Engineering Ltd.",
    "wof:placetype":"venue"
},
  "geometry": {"coordinates":[-1.921346,52.302628],"type":"Point"}
}