{
  "type": "Feature",
  "properties": {
    "addr:full":"58h Arthur Street Redditch Warwickshire B98 8JY",
    "addr:housenumber":"58h",
    "addr:postcode":"b98 8jy",
    "addr:street":"Arthur Street",
    "iso:country":"GB",
    "sg:address":"58h Arthur Street",
    "sg:city":"Redditch",
    "sg:classifiers":[
        {
            "category":"Professional",
            "subcategory":"Engineering",
            "type":"Services"
        }
    ],
    "sg:phone":"+44 1527 510092",
    "sg:postcode":"B98 8JY",
    "sg:province":"Warwickshire",
    "wof:name":"Avalon Engineering Ltd.",
    "wof:placetype":"venue"
},
  "geometry": {"coordinates":[-1.921346,52.302628],"type":"Point"}
}