{
  "type": "Feature",
  "properties": {
    "addr:full":"Maynard Road, Wincheap Industrial Estate Canterbury Kent CT1 3RH",
    "addr:housenumber":"estate",
    "addr:postcode":"ct1 3rh",
    "addr:street":"Maynard Road Wincheap Industrial",
    "iso:country":"GB",
    "sg:address":"Maynard Road, Wincheap Industrial Estate",
    "sg:city":"Canterbury",
    "sg:classifiers":[
        {
            "category":"Shopping",
            "subcategory":"Stationery & Office Supplies",
            "type":"Retail Goods"
        }
    ],
    "sg:phone":"+44 1227 763637",
    "sg:postcode":"CT1 3RH",
    "sg:province":"Kent",
    "sg:tags":[
        "equipment"
    ],
    "wof:name":"Lesco Products Ltd.",
    "wof:placetype":"venue"
},
  "geometry": {"coordinates":[1.068517,51.273754],"type":"Point"}
}