{
  "type": "Feature",
  "properties": {
    "addr:full":"Hodgkinsons Farm, Boot Lane Bolton Lancashire BL1 5ST",
    "addr:postcode":"bl1 5st",
    "addr:street":"Boot Lane",
    "iso:country":"GB",
    "sg:address":"Hodgkinsons Farm, Boot Lane",
    "sg:city":"Bolton",
    "sg:classifiers":[
        {
            "category":"Farming",
            "subcategory":"Livestock Farm",
            "type":"Manufacturing & Wholesale Goods"
        }
    ],
    "sg:postcode":"BL1 5ST",
    "sg:province":"Lancashire",
    "sg:tags":[
        "others"
    ],
    "wof:name":"Frank Thompson",
    "wof:placetype":"venue"
},
  "geometry": {"coordinates":[-2.426594,53.578289],"type":"Point"}
}