{
  "type": "Feature",
  "properties": {
    "addr:full":"8-12 St Mary's Gate Rochdale Lancashire OL16 1DZ",
    "addr:housenumber":"8-12",
    "addr:postcode":"ol16 1dz",
    "addr:street":"St Mary'S Gate",
    "iso:country":"GB",
    "sg:address":"8-12 St Mary's Gate",
    "sg:city":"Rochdale",
    "sg:classifiers":[
        {
            "category":"Home & Garden",
            "subcategory":"Furniture",
            "type":"Retail Goods"
        }
    ],
    "sg:postcode":"OL16 1DZ",
    "sg:province":"Lancashire",
    "wof:name":"Donnellys (Rochdale) Ltd.",
    "wof:placetype":"venue"
},
  "geometry": {"coordinates":[-2.1579101086,53.6194000244],"type":"Point"}
}