{
  "type": "Feature",
  "properties": {
    "addr:full":"10 Allenby Rd Maidenhead Berkshire SL6 5BB",
    "addr:housenumber":"10",
    "addr:postcode":"sl6 5bb",
    "addr:street":"Allenby Rd",
    "iso:country":"GB",
    "sg:address":"10 Allenby Rd",
    "sg:city":"Maidenhead",
    "sg:classifiers":[
        {
            "category":"Personal",
            "type":"Services"
        }
    ],
    "sg:phone":"+44 1628 626852",
    "sg:postcode":"SL6 5BB",
    "sg:province":"Berkshire",
    "sg:tags":[
        "wedding"
    ],
    "wof:name":"Garlands",
    "wof:placetype":"venue"
},
  "geometry": {"coordinates":[-0.747305,51.522213],"type":"Point"}
}