{
  "type": "Feature",
  "properties": {
    "addr:full":"11 Wester Coates Gardens Edinburgh City of Edinburgh EH12 5LT",
    "addr:housenumber":"11",
    "addr:postcode":"eh12 5lt",
    "addr:street":"Wester Coates Gardens",
    "iso:country":"GB",
    "sg:address":"11 Wester Coates Gardens",
    "sg:city":"Edinburgh",
    "sg:classifiers":[
        {
            "category":"Professional",
            "subcategory":"Research",
            "type":"Services"
        }
    ],
    "sg:postcode":"EH12 5LT",
    "sg:province":"City of Edinburgh",
    "sg:tags":[
        "market"
    ],
    "wof:name":"Jack Hamilton Associates",
    "wof:placetype":"venue"
},
  "geometry": {"coordinates":[-3.231623,55.947536],"type":"Point"}
}