{
  "type": "Feature",
  "properties": {
    "iso:country":"GB",
    "sg:address":"Head Quarters, 28 Castle Street",
    "sg:city":"Hertford",
    "sg:classifiers":[
        {
            "category":"Professional",
            "subcategory":"Employment Agencies",
            "type":"Services"
        }
    ],
    "sg:phone":"+44 1992 555793",
    "sg:postcode":"SG14 1HH",
    "sg:province":"Hertfordshire",
    "sg:tags":[
        "career",
        "guidance"
    ],
    "wof:name":"Hertfordshire Careers Services",
    "wof:placetype":"venue"
},
  "geometry": {"coordinates":[-0.082699,51.796341],"type":"Point"}
}