{
  "type": "Feature",
  "properties": {
    "addr:full":"131 Walm Lane London Greater London NW2 3AU",
    "addr:housenumber":"131",
    "addr:postcode":"nw2 3au",
    "addr:street":"Walm Lane",
    "iso:country":"GB",
    "sg:address":"131 Walm Lane",
    "sg:city":"London",
    "sg:classifiers":[
        {
            "category":"Place Of Worship",
            "type":"Public Place"
        }
    ],
    "sg:phone":"+44 20 8452 1739",
    "sg:postcode":"NW2 3AU",
    "sg:province":"Greater London",
    "wof:name":"Cricklewood Synagogue",
    "wof:placetype":"venue"
},
  "geometry": {"coordinates":[-0.2174459994,51.5528106689],"type":"Point"}
}