{
  "type": "Feature",
  "properties": {
    "iso:country":"GB",
    "sg:address":"25 Stert Street",
    "sg:city":"Abingdon",
    "sg:classifiers":[
        {
            "category":"Personal",
            "subcategory":"Beauty Salon",
            "type":"Services"
        },
        {
            "category":"Personal",
            "subcategory":"Barber",
            "type":"Services"
        }
    ],
    "sg:phone":"+44 1235 520569",
    "sg:postcode":"OX14 3JF",
    "sg:province":"Oxfordshire",
    "sg:tags":[
        "unisex",
        "hairdresser"
    ],
    "wof:name":"Gemini Hair Stylist",
    "wof:placetype":"venue"
},
  "geometry": {"coordinates":[-1.281096,51.670929],"type":"Point"}
}