{
  "type": "Feature",
  "properties": {
    "addr:full":"Po Box 221, Langley Wood Walsall Staffordshire WS6 7YL",
    "addr:housenumber":"po",
    "addr:postcode":"ws6 7yl",
    "addr:street":"Box 221 Langley",
    "iso:country":"GB",
    "sg:address":"Po Box 221, Langley Wood",
    "sg:city":"Walsall",
    "sg:classifiers":[
        {
            "category":"Home & Garden",
            "subcategory":"Hardware",
            "type":"Retail Goods"
        },
        {
            "category":"Utilities",
            "subcategory":"Cable",
            "type":"Services"
        }
    ],
    "sg:phone":"+44 121 327 1886",
    "sg:postcode":"WS6 7YL",
    "sg:province":"Staffordshire",
    "sg:tags":[
        "tv",
        "equipment",
        "wire"
    ],
    "wof:name":"Siltech Co. Ltd.",
    "wof:placetype":"venue"
},
  "geometry": {"coordinates":[-2.02313,52.65905],"type":"Point"}
}