{
  "type": "Feature",
  "properties": {
    "iso:country":"GB",
    "sg:address":"Thames Ho, Crete Hall Rd",
    "sg:city":"Gravesend",
    "sg:classifiers":[
        {
            "category":"Professional",
            "subcategory":"Art Services",
            "type":"Services"
        }
    ],
    "sg:phone":"+44 1474 336809",
    "sg:postcode":"DA11 9AD",
    "sg:province":"Kent",
    "sg:tags":[
        "photographer"
    ],
    "wof:name":"Alan R Fuller",
    "wof:placetype":"venue"
},
  "geometry": {"coordinates":[0.34048,51.44492],"type":"Point"}
}