{
  "type": "Feature",
  "properties": {
    "iso:country":"GB",
    "sg:address":"Club House, Brownberrie Lane, Horsforth",
    "sg:city":"Leeds",
    "sg:classifiers":[
        {
            "category":"Arena",
            "subcategory":"Sports Club",
            "type":"Entertainment"
        }
    ],
    "sg:phone":"+44 113 258 1346",
    "sg:postcode":"LS18 5HB",
    "sg:province":"West Yorkshire",
    "wof:name":"(Horsforth) R F C Yarnbury",
    "wof:placetype":"venue"
},
  "geometry": {"coordinates":[-1.6400289536,53.8490905762],"type":"Point"}
}