{
  "type": "Feature",
  "properties": {
    "addr:full":"235 Seaview Rd Wallasey Merseyside L45 4PD",
    "addr:housenumber":"235",
    "addr:postcode":"l45 4pd",
    "addr:street":"Seaview Rd",
    "iso:country":"GB",
    "sg:address":"235 Seaview Rd",
    "sg:city":"Wallasey",
    "sg:classifiers":[
        {
            "category":"Food & Beverages",
            "subcategory":"Meat & Fish",
            "type":"Retail Goods"
        }
    ],
    "sg:phone":"+44 151 639 3156",
    "sg:postcode":"L45 4PD",
    "sg:province":"Merseyside",
    "sg:tags":[
        "butcher"
    ],
    "wof:name":"J C Tomkins",
    "wof:placetype":"venue"
},
  "geometry": {"coordinates":[-3.052061,53.428539],"type":"Point"}
}