{
  "type": "Feature",
  "properties": {
    "addr:full":"268 Regents Park Rd Finchley Central Greater London N3 3HN",
    "addr:housenumber":"268",
    "addr:postcode":"n3 3hn",
    "addr:street":"Regents Park Rd",
    "iso:country":"GB",
    "sg:address":"268 Regents Park Rd",
    "sg:city":"Finchley Central",
    "sg:classifiers":[
        {
            "category":"Banks & Credit Unions",
            "subcategory":"Financial Services",
            "type":"Services"
        }
    ],
    "sg:phone":"+44 20 8346 6520",
    "sg:postcode":"N3 3HN",
    "sg:province":"Greater London",
    "sg:tags":[
        "consultant"
    ],
    "wof:name":"Trade & Credits",
    "wof:placetype":"venue"
},
  "geometry": {"coordinates":[-0.19728,51.597824],"type":"Point"}
}