{
  "type": "Feature",
  "properties": {
    "addr:full":"64 Boutport Street Barnstaple Devon EX31 1HG",
    "addr:housenumber":"64",
    "addr:postcode":"ex31 1hg",
    "addr:street":"Boutport Street",
    "iso:country":"GB",
    "sg:address":"64 Boutport Street",
    "sg:city":"Barnstaple",
    "sg:classifiers":[
        {
            "category":"Shopping",
            "subcategory":"Clothing, Apparel, & Fashions",
            "type":"Retail Goods"
        }
    ],
    "sg:phone":"+44 1271 346624",
    "sg:postcode":"EX31 1HG",
    "sg:province":"Devon",
    "sg:tags":[
        "shop"
    ],
    "wof:name":"Earth Angel",
    "wof:placetype":"venue"
},
  "geometry": {"coordinates":[-4.0610280037,51.0828895569],"type":"Point"}
}