{
  "type": "Feature",
  "properties": {
    "addr:full":"Victoria Rd, Fauldhouse Bathgate North Lanarkshire EH47 9LF",
    "addr:postcode":"eh47 9lf",
    "addr:street":"Victoria Rd;Bathgate",
    "iso:country":"GB",
    "sg:address":"Victoria Rd, Fauldhouse",
    "sg:city":"Bathgate",
    "sg:classifiers":[
        {
            "category":"Arena",
            "subcategory":"Sports Club",
            "type":"Entertainment"
        }
    ],
    "sg:phone":"+44 1501 770330",
    "sg:postcode":"EH47 9LF",
    "sg:province":"North Lanarkshire",
    "wof:name":"Fauldhouse Cricket Club",
    "wof:placetype":"venue"
},
  "geometry": {"coordinates":[-3.7066040039,55.8278808594],"type":"Point"}
}