{
  "type": "Feature",
  "properties": {
    "iso:country":"GB",
    "sg:address":"105 Green Lane, Leamore",
    "sg:city":"Walsall",
    "sg:classifiers":[
        {
            "category":"Personal",
            "subcategory":"Beauty Salon",
            "type":"Services"
        }
    ],
    "sg:phone":"+44 1922 407823",
    "sg:postcode":"WS3 2BN",
    "sg:province":"Staffordshire",
    "sg:tags":[
        "unisex",
        "hairdresser"
    ],
    "wof:name":"Chase Hair Design",
    "wof:placetype":"venue"
},
  "geometry": {"coordinates":[-1.999287,52.607296],"type":"Point"}
}