{
  "type": "Feature",
  "properties": {
    "iso:country":"GB",
    "sg:address":"Unit F12, Speedwell Way",
    "sg:city":"Harleston",
    "sg:classifiers":[
        {
            "category":"Professional",
            "type":"Services"
        }
    ],
    "sg:phone":"+44 1379 854488",
    "sg:postcode":"IP20 9EH",
    "sg:province":"Norfolk",
    "sg:tags":[
        "entertainer"
    ],
    "wof:name":"Breckland Tattoo",
    "wof:placetype":"venue"
},
  "geometry": {"coordinates":[1.303788,52.396381],"type":"Point"}
}