{
  "type": "Feature",
  "properties": {
    "addr:full":"38 Sherwood Road, Aston Fields Industrial Estate Bromsgrove Worcestershire B60 3DR",
    "addr:housenumber":"38",
    "addr:postcode":"b60 3dr",
    "addr:street":"Sherwood Road Aston Fields Industrial Estate",
    "iso:country":"GB",
    "sg:address":"38 Sherwood Road, Aston Fields Industrial Estate",
    "sg:city":"Bromsgrove",
    "sg:classifiers":[
        {
            "category":"Professional",
            "subcategory":"Engineering",
            "type":"Services"
        }
    ],
    "sg:phone":"+44 1527 576555",
    "sg:postcode":"B60 3DR",
    "sg:province":"Worcestershire",
    "sg:tags":[
        "hydraulic",
        "engineer"
    ],
    "wof:name":"Link Hydraulic Services Ltd.",
    "wof:placetype":"venue"
},
  "geometry": {"coordinates":[-2.060292,52.318356],"type":"Point"}
}