{
  "type": "Feature",
  "properties": {
    "iso:country":"GB",
    "sg:address":"60 Liverpool Road North",
    "sg:city":"Ormskirk",
    "sg:classifiers":[
        {
            "category":"Food & Beverages",
            "subcategory":"Liquor & Beverages",
            "type":"Retail Goods"
        }
    ],
    "sg:phone":"+44 1704 893305",
    "sg:postcode":"L40 4BY",
    "sg:province":"Lancashire",
    "sg:tags":[
        "beer",
        "spirit",
        "wines"
    ],
    "wof:name":"Drinks Cabin",
    "wof:placetype":"venue"
},
  "geometry": {"coordinates":[-2.840015,53.605858],"type":"Point"}
}