{
  "type": "Feature",
  "properties": {
    "iso:country":"GB",
    "sg:address":"Civic Way",
    "sg:city":"Middlewich",
    "sg:classifiers":[
        {
            "category":"Community Center",
            "type":"Public Place"
        }
    ],
    "sg:phone":"+44 1606 835301",
    "sg:postcode":"CW10 9BX",
    "sg:province":"Cheshire",
    "sg:tags":[
        "recreation",
        "leisure",
        "centre"
    ],
    "wof:name":"Middlewich Community Centre",
    "wof:placetype":"venue"
},
  "geometry": {"coordinates":[-2.444261,53.190929],"type":"Point"}
}