{
  "type": "Feature",
  "properties": {
    "addr:full":"Inside Communications, 1 Canada Square London Greater London E14 5AP",
    "addr:housenumber":"1",
    "addr:postcode":"e14 5ap",
    "addr:street":"Canada Square",
    "iso:country":"GB",
    "sg:address":"Inside Communications, 1 Canada Square",
    "sg:city":"London",
    "sg:classifiers":[
        {
            "category":"Retail",
            "subcategory":"Event Space",
            "type":"Services"
        }
    ],
    "sg:phone":"+44 20 7772 8300",
    "sg:postcode":"E14 5AP",
    "sg:province":"Greater London",
    "sg:tags":[
        "exhibition",
        "organiser"
    ],
    "wof:name":"Wedding Shows (U K) Ltd.",
    "wof:placetype":"venue"
},
  "geometry": {"coordinates":[-0.01943,51.504902],"type":"Point"}
}