{
  "type": "Feature",
  "properties": {
    "addr:full":"1615 Wimborne Road Bournemouth Dorset BH11 9AP",
    "addr:housenumber":"1615",
    "addr:postcode":"bh11 9ap",
    "addr:street":"Wimborne Road",
    "iso:country":"GB",
    "sg:address":"1615 Wimborne Road",
    "sg:city":"Bournemouth",
    "sg:classifiers":[
        {
            "category":"Fast Food",
            "type":"Food & Drink"
        }
    ],
    "sg:phone":"+44 1202 582532",
    "sg:postcode":"BH11 9AP",
    "sg:province":"Dorset",
    "sg:tags":[
        "away",
        "take"
    ],
    "wof:name":"Royal Bangal Tiger",
    "wof:placetype":"venue"
},
  "geometry": {"coordinates":[-1.90311,50.769211],"type":"Point"}
}