{
  "type": "Feature",
  "properties": {
    "addr:full":"79 Otley Road Shipley West Yorkshire BD18 2BJ",
    "addr:housenumber":"79",
    "addr:postcode":"bd18 2bj",
    "addr:street":"Otley Road",
    "iso:country":"GB",
    "sg:address":"79 Otley Road",
    "sg:city":"Shipley",
    "sg:classifiers":[
        {
            "category":"Autos & Motor Vehicles",
            "subcategory":"Automobile Sales",
            "type":"Retail Goods"
        }
    ],
    "sg:phone":"+44 1274 587331",
    "sg:postcode":"BD18 2BJ",
    "sg:province":"West Yorkshire",
    "sg:tags":[
        "car"
    ],
    "wof:name":"Staveley Civic Ltd.",
    "wof:placetype":"venue"
},
  "geometry": {"coordinates":[-1.775659,53.831692],"type":"Point"}
}