{
  "type": "Feature",
  "properties": {
    "addr:full":"Legal Chambers, 49-51 Bancroft Hitchin Bedfordshire SG5 1LL",
    "addr:housenumber":"49-51",
    "addr:postcode":"sg5 1ll",
    "addr:street":"Bancroft",
    "iso:country":"GB",
    "sg:address":"Legal Chambers, 49-51 Bancroft",
    "sg:city":"Hitchin",
    "sg:classifiers":[
        {
            "category":"Professional",
            "subcategory":"Computer Services",
            "type":"Services"
        }
    ],
    "sg:phone":"+44 1462 457700",
    "sg:postcode":"SG5 1LL",
    "sg:province":"Bedfordshire",
    "sg:tags":[
        "system",
        "software"
    ],
    "wof:name":"Control Technology International Ltd.",
    "wof:placetype":"venue"
},
  "geometry": {"coordinates":[-0.2844080031,51.9524345398],"type":"Point"}
}