{
  "type": "Feature",
  "properties": {
    "addr:full":"1-3 St. Helens Rd Bolton Lancashire BL3 3NL",
    "addr:housenumber":"1-3",
    "addr:postcode":"bl3 3nl",
    "addr:street":"St. Helens Rd",
    "iso:country":"GB",
    "sg:address":"1-3 St. Helens Rd",
    "sg:city":"Bolton",
    "sg:classifiers":[
        {
            "category":"Communications",
            "type":"Services"
        }
    ],
    "sg:phone":"+44 1204 656969",
    "sg:postcode":"BL3 3NL",
    "sg:province":"Lancashire",
    "sg:tags":[
        "telecommunication"
    ],
    "wof:name":"Kodafone & Shop",
    "wof:placetype":"venue"
},
  "geometry": {"coordinates":[-2.4455211163,53.565952301],"type":"Point"}
}