{
  "type": "Feature",
  "properties": {
    "addr:full":"121 Skerton Road Manchester Cheshire M16 0LT",
    "addr:housenumber":"121",
    "addr:postcode":"m16 0lt",
    "addr:street":"Skerton Road",
    "iso:country":"GB",
    "sg:address":"121 Skerton Road",
    "sg:city":"Manchester",
    "sg:classifiers":[
        {
            "category":"Personal",
            "subcategory":"Barber",
            "type":"Services"
        }
    ],
    "sg:phone":"+44 161 876 4212",
    "sg:postcode":"M16 0LT",
    "sg:province":"Cheshire",
    "sg:tags":[
        "men's",
        "hairdresser"
    ],
    "wof:name":"Peter's Barber Shop",
    "wof:placetype":"venue"
},
  "geometry": {"coordinates":[-2.273349,53.452888],"type":"Point"}
}