{
  "type": "Feature",
  "properties": {
    "iso:country":"GB",
    "sg:address":"119 The Grove",
    "sg:city":"London",
    "sg:classifiers":[
        {
            "category":"Bars & Pubs",
            "type":"Food & Drink"
        }
    ],
    "sg:postcode":"E15 1EN",
    "sg:province":"Greater London",
    "sg:tags":[
        "pubs",
        "inn"
    ],
    "wof:name":"The Coronet",
    "wof:placetype":"venue"
},
  "geometry": {"coordinates":[0.0046879998,51.5449714661],"type":"Point"}
}