{
  "type": "Feature",
  "properties": {
    "addr:full":"3rd Floor, 40-44 Rothesay Road Luton Bedfordshire LU1 1QZ",
    "addr:housenumber":"3rd floor 40-44",
    "addr:postcode":"lu1 1qz",
    "addr:street":"Rothesay Road",
    "iso:country":"GB",
    "sg:address":"3rd Floor, 40-44 Rothesay Road",
    "sg:city":"Luton",
    "sg:classifiers":[
        {
            "category":"Manufacturing",
            "subcategory":"Tools & Machinery",
            "type":"Manufacturing & Wholesale Goods"
        },
        {
            "category":"Insurance",
            "subcategory":"Insurance Agent",
            "type":"Services"
        }
    ],
    "sg:phone":"+44 1582 731851",
    "sg:postcode":"LU1 1QZ",
    "sg:province":"Bedfordshire",
    "sg:tags":[
        "society",
        "broker",
        "friendly"
    ],
    "wof:name":"Co-Operative Insurance Society Ltd",
    "wof:placetype":"venue"
},
  "geometry": {"coordinates":[-0.4231359959,51.8781776428],"type":"Point"}
}