{
  "type": "Feature",
  "properties": {
    "addr:full":"37 High Street, Ealing London Greater London W5 5DB",
    "addr:housenumber":"37",
    "addr:postcode":"w5 5db",
    "addr:street":"High Street",
    "iso:country":"GB",
    "sg:address":"37 High Street, Ealing",
    "sg:city":"London",
    "sg:classifiers":[
        {
            "category":"Real Estate",
            "subcategory":"Real Estate Operator",
            "type":"Services"
        },
        {
            "category":"Real Estate",
            "subcategory":"Real Estate Agent",
            "type":"Services"
        }
    ],
    "sg:phone":"+44 20 8810 0101",
    "sg:postcode":"W5 5DB",
    "sg:province":"Greater London",
    "sg:tags":[
        "letting"
    ],
    "sg:website":"http://www.bradley-beazley.co.uk",
    "wof:name":"Bradley Beazley Residential Ltd.",
    "wof:placetype":"venue"
},
  "geometry": {"coordinates":[-0.3052839935,51.5115966797],"type":"Point"}
}