{
  "type": "Feature",
  "properties": {
    "iso:country":"GB",
    "sg:address":"Restdale House",
    "sg:city":"Worcester",
    "sg:classifiers":[
        {
            "category":"Banks & Credit Unions",
            "subcategory":"Bank",
            "type":"Services"
        }
    ],
    "sg:phone":"+44 1584 856789",
    "sg:postcode":"WR1 1EE",
    "sg:province":"Worcestershire",
    "sg:tags":[
        "broker",
        "mortgage"
    ],
    "wof:name":"Allied Capital",
    "wof:placetype":"venue"
},
  "geometry": {"coordinates":[-2.222274,52.191067],"type":"Point"}
}