{
  "type": "Feature",
  "properties": {
    "addr:full":"3-23 Suffolk Road Lowestoft Suffolk NR32 1DZ",
    "addr:housenumber":"3-23",
    "addr:postcode":"nr32 1dz",
    "addr:street":"Suffolk Road",
    "iso:country":"GB",
    "sg:address":"3-23 Suffolk Road",
    "sg:city":"Lowestoft",
    "sg:classifiers":[
        {
            "category":"Building & Trades",
            "subcategory":"Plumbing",
            "type":"Services"
        },
        {
            "category":"Food & Beverages",
            "subcategory":"Supermarket",
            "type":"Retail Goods"
        }
    ],
    "sg:phone":"+44 1502 516298",
    "sg:postcode":"NR32 1DZ",
    "sg:province":"Suffolk",
    "sg:tags":[
        "merchant",
        "plumbers'"
    ],
    "wof:name":"L R Godfrey (Lowestoft) Ltd.",
    "wof:placetype":"venue"
},
  "geometry": {"coordinates":[1.7517260313,52.4742736816],"type":"Point"}
}