{
  "type": "Feature",
  "properties": {
    "iso:country":"GB",
    "sg:address":"8 Tor Hill House, Union Street",
    "sg:city":"Torquay",
    "sg:classifiers":[
        {
            "category":"Food & Beverages",
            "subcategory":"Bakery",
            "type":"Retail Goods"
        }
    ],
    "sg:phone":"+44 1803 293000",
    "sg:postcode":"TQ2 5QW",
    "sg:province":"Devon",
    "sg:tags":[
        "pizza"
    ],
    "wof:name":"Cafe Prague",
    "wof:placetype":"venue"
},
  "geometry": {"coordinates":[-3.543464,50.467194],"type":"Point"}
}