{
  "type": "Feature",
  "properties": {
    "addr:full":"Ansteys Cottage, Cheap St, Chedworth Cheltenham Gloucestershire GL54 4AB",
    "addr:postcode":"gl54 4ab",
    "addr:street":"Cheap St",
    "iso:country":"GB",
    "sg:address":"Ansteys Cottage, Cheap St, Chedworth",
    "sg:city":"Cheltenham",
    "sg:classifiers":[
        {
            "category":"Wholesale",
            "subcategory":"Sporting Goods",
            "type":"Manufacturing & Wholesale Goods"
        }
    ],
    "sg:phone":"+44 1285 720259",
    "sg:postcode":"GL54 4AB",
    "sg:province":"Gloucestershire",
    "sg:tags":[
        "mnfr",
        "sport",
        "equipment"
    ],
    "wof:name":"Chedworth Golf Group",
    "wof:placetype":"venue"
},
  "geometry": {"coordinates":[-1.9252170324,51.8057937622],"type":"Point"}
}