{
  "type": "Feature",
  "properties": {
    "addr:full":"99 White Lion St Islington Greater London N1 9PF",
    "addr:housenumber":"99",
    "addr:postcode":"n1 9pf",
    "addr:street":"White Lion St",
    "iso:country":"GB",
    "sg:address":"99 White Lion St",
    "sg:city":"Islington",
    "sg:classifiers":[
        {
            "category":"Organizations",
            "subcategory":"Non-profit Organization",
            "type":"Services"
        }
    ],
    "sg:phone":"+44 20 7837 1132",
    "sg:postcode":"N1 9PF",
    "sg:province":"Greater London",
    "sg:tags":[
        "organisation",
        "voluntary",
        "charity"
    ],
    "wof:name":"Women's Royal Voluntary Service",
    "wof:placetype":"venue"
},
  "geometry": {"coordinates":[-0.1064350009,51.5329246521],"type":"Point"}
}