{
  "type": "Feature",
  "properties": {
    "iso:country":"GB",
    "sg:address":"Home Farm House, Dunton Lane",
    "sg:city":"Biggleswade",
    "sg:classifiers":[
        {
            "category":"Transit Center",
            "subcategory":"Passenger",
            "type":"Transportation"
        }
    ],
    "sg:phone":"+44 1767 314959",
    "sg:postcode":"SG18 8QU",
    "sg:province":"Bedfordshire",
    "sg:tags":[
        "boarding",
        "kennel",
        "catteries"
    ],
    "wof:name":"Biggleswade Cat Lodge",
    "wof:placetype":"venue"
},
  "geometry": {"coordinates":[-0.244259,52.076939],"type":"Point"}
}