{
  "type": "Feature",
  "properties": {
    "addr:full":"15 London Street London Greater London W2 1HL",
    "addr:housenumber":"15",
    "addr:postcode":"w2 1hl",
    "addr:street":"London Street",
    "iso:country":"GB",
    "sg:address":"15 London Street",
    "sg:city":"London",
    "sg:classifiers":[
        {
            "category":"Food & Beverages",
            "subcategory":"Groceries & Convenience Stores",
            "type":"Retail Goods"
        }
    ],
    "sg:phone":"+44 20 7262 2528",
    "sg:postcode":"W2 1HL",
    "sg:province":"Greater London",
    "wof:name":"Portland Food & Wine",
    "wof:placetype":"venue"
},
  "geometry": {"coordinates":[-0.174147,51.515198],"type":"Point"}
}