{
  "type": "Feature",
  "properties": {
    "addr:full":"Oldbury Buildings, Northway La Tewkesbury Gloucestershire GL20 8JG",
    "addr:postcode":"gl20 8jg",
    "addr:street":"Northway La Tewkesbury",
    "iso:country":"GB",
    "sg:address":"Oldbury Buildings, Northway La",
    "sg:city":"Tewkesbury",
    "sg:classifiers":[
        {
            "category":"Professional",
            "type":"Services"
        }
    ],
    "sg:phone":"+44 1684 291726",
    "sg:postcode":"GL20 8JG",
    "sg:province":"Gloucestershire",
    "sg:tags":[
        "repair",
        "tech",
        "maintenance"
    ],
    "wof:name":"Euro Telecom Maintenance & Distribution",
    "wof:placetype":"venue"
},
  "geometry": {"coordinates":[-2.1038041115,51.9978027344],"type":"Point"}
}