{
  "type": "Feature",
  "properties": {
    "addr:full":"Badgers, Fedwen Arian, Llangernyw Abergele Conwy LL22 8PQ",
    "addr:postcode":"ll22 8pq",
    "addr:street":"Llangernyw",
    "iso:country":"GB",
    "sg:address":"Badgers, Fedwen Arian, Llangernyw",
    "sg:city":"Abergele",
    "sg:classifiers":[
        {
            "category":"Real Estate",
            "subcategory":"Developer",
            "type":"Services"
        },
        {
            "category":"Building & Trades",
            "subcategory":"Construction",
            "type":"Services"
        }
    ],
    "sg:phone":"+44 1745 860547",
    "sg:postcode":"LL22 8PQ",
    "sg:province":"Conwy",
    "sg:tags":[
        "property",
        "contractor"
    ],
    "wof:name":"Rossisle Development Co. Ltd.",
    "wof:placetype":"venue"
},
  "geometry": {"coordinates":[-3.6855990887,53.1925048828],"type":"Point"}
}