{
  "type": "Feature",
  "properties": {
    "addr:full":"3 Hare Street Rd Buntingford Hertfordshire SG9 9HN",
    "addr:housenumber":"3",
    "addr:postcode":"sg9 9hn",
    "addr:street":"Hare Street Rd",
    "iso:country":"GB",
    "sg:address":"3 Hare Street Rd",
    "sg:city":"Buntingford",
    "sg:classifiers":[
        {
            "category":"Professional",
            "subcategory":"Secretarial Services",
            "type":"Services"
        }
    ],
    "sg:postcode":"SG9 9HN",
    "sg:province":"Hertfordshire",
    "wof:name":"Busibody",
    "wof:placetype":"venue"
},
  "geometry": {"coordinates":[-0.0135089997,51.9460411072],"type":"Point"}
}