{
  "type": "Feature",
  "properties": {
    "iso:country":"GB",
    "sg:address":"432 Little Wakering Road, Great Wakering",
    "sg:city":"Southend-on-sea",
    "sg:classifiers":[
        {
            "category":"Government",
            "subcategory":"City Hall",
            "type":"Public Place"
        }
    ],
    "sg:phone":"+44 1702 219416",
    "sg:postcode":"SS3 0LN",
    "sg:province":"Essex",
    "wof:name":"Barling Magna Parish Hall",
    "wof:placetype":"venue"
},
  "geometry": {"coordinates":[0.799885,51.553196],"type":"Point"}
}