{
  "type": "Feature",
  "properties": {
    "iso:country":"GB",
    "sg:address":"22 Mandley Close, Little Lever",
    "sg:city":"Bolton",
    "sg:classifiers":[
        {
            "category":"Home & Garden",
            "subcategory":"Carpets & Floor Coverings",
            "type":"Retail Goods"
        }
    ],
    "sg:postcode":"BL3 1PZ",
    "sg:province":"Lancashire",
    "sg:tags":[
        "carpets",
        "rug",
        "matting"
    ],
    "wof:name":"Carpet Fitting Service",
    "wof:placetype":"venue"
},
  "geometry": {"coordinates":[-2.3713130951,53.5695953369],"type":"Point"}
}