{
  "type": "Feature",
  "properties": {
    "iso:country":"GB",
    "sg:address":"474 Broadway, Chadderton",
    "sg:city":"Oldham",
    "sg:classifiers":[
        {
            "category":"Shopping",
            "subcategory":"Clothing, Apparel, & Fashions",
            "type":"Retail Goods"
        }
    ],
    "sg:postcode":"OL9 9NF",
    "sg:province":"Lancashire",
    "sg:tags":[
        "shop"
    ],
    "wof:name":"Christine Marsh",
    "wof:placetype":"venue"
},
  "geometry": {"coordinates":[-2.1616680622,53.5263824463],"type":"Point"}
}