{
  "type": "Feature",
  "properties": {
    "addr:full":"Victoria Wharf, Clovelly Road Plymouth Devon PL4 0RF",
    "addr:postcode":"pl4 0rf",
    "addr:street":"Victoria;Clovelly Road",
    "iso:country":"GB",
    "sg:address":"Victoria Wharf, Clovelly Road",
    "sg:city":"Plymouth",
    "sg:classifiers":[
        {
            "category":"Utilities",
            "subcategory":"Fuel Oil & Lpg",
            "type":"Services"
        }
    ],
    "sg:phone":"+44 1752 223111",
    "sg:postcode":"PL4 0RF",
    "sg:province":"Devon",
    "sg:tags":[
        "distributor"
    ],
    "wof:name":"TOTAL BUTLER",
    "wof:placetype":"venue"
},
  "geometry": {"coordinates":[-4.1256828308,50.3656234741],"type":"Point"}
}