{
  "type": "Feature",
  "properties": {
    "iso:country":"GB",
    "sg:address":"8 Fantail Lane",
    "sg:city":"Tring",
    "sg:classifiers":[
        {
            "category":"Home & Garden",
            "subcategory":"Carpets & Floor Coverings",
            "type":"Retail Goods"
        }
    ],
    "sg:phone":"+44 1442 822799",
    "sg:postcode":"HP23 4EN",
    "sg:province":"Buckinghamshire",
    "sg:tags":[
        "carpets",
        "retailer",
        "rug",
        "matting"
    ],
    "wof:name":"Criterion Flooring",
    "wof:placetype":"venue"
},
  "geometry": {"coordinates":[-0.672277987,51.797504425],"type":"Point"}
}