{
  "type": "Feature",
  "properties": {
    "addr:full":"38 West St Brighton East Sussex BN1 2RE",
    "addr:housenumber":"38",
    "addr:postcode":"bn1 2re",
    "addr:street":"West St",
    "iso:country":"GB",
    "sg:address":"38 West St",
    "sg:city":"Brighton",
    "sg:classifiers":[
        {
            "category":"Retail",
            "subcategory":"Laundry & Dry Cleaning",
            "type":"Services"
        }
    ],
    "sg:phone":"+44 1273 327138",
    "sg:postcode":"BN1 2RE",
    "sg:province":"East Sussex",
    "sg:tags":[
        "alteration"
    ],
    "wof:name":"Bollom Ltd",
    "wof:placetype":"venue"
},
  "geometry": {"coordinates":[-0.1438460052,50.8233413696],"type":"Point"}
}