{
  "type": "Feature",
  "properties": {
    "iso:country":"GB",
    "sg:address":"Eastbury, Clanver End",
    "sg:city":"Saffron Walden",
    "sg:classifiers":[
        {
            "category":"Personal",
            "subcategory":"Beauty Salon",
            "type":"Services"
        },
        {
            "category":"Professional",
            "subcategory":"Art Services",
            "type":"Services"
        }
    ],
    "sg:phone":"+44 1799 540256",
    "sg:postcode":"CB11 4UL",
    "sg:province":"Essex",
    "sg:tags":[
        "unisex",
        "consultant",
        "design",
        "hairdresser"
    ],
    "wof:name":"R N Wilson",
    "wof:placetype":"venue"
},
  "geometry": {"coordinates":[0.17734,52.00423],"type":"Point"}
}