{
  "type": "Feature",
  "properties": {
    "iso:country":"GB",
    "sg:address":"11-13 High Street, Wavertree",
    "sg:city":"Liverpool",
    "sg:classifiers":[
        {
            "category":"Home & Garden",
            "subcategory":"Home Furnishings",
            "type":"Retail Goods"
        }
    ],
    "sg:phone":"+44 151 734 2828",
    "sg:postcode":"L15 8HE",
    "sg:province":"Merseyside",
    "sg:tags":[
        "furnishers",
        "planner",
        "bedroom"
    ],
    "wof:name":"Sleep in Style",
    "wof:placetype":"venue"
},
  "geometry": {"coordinates":[-2.921531,53.399113],"type":"Point"}
}