{
  "type": "Feature",
  "properties": {
    "addr:full":"7 Cranston Close Uxbridge Greater London UB10 8TH",
    "addr:housenumber":"7",
    "addr:postcode":"ub10 8th",
    "addr:street":"Cranston Close",
    "iso:country":"GB",
    "sg:address":"7 Cranston Close",
    "sg:city":"Uxbridge",
    "sg:classifiers":[
        {
            "category":"Professional",
            "subcategory":"Computer Services",
            "type":"Services"
        }
    ],
    "sg:postcode":"UB10 8TH",
    "sg:province":"Greater London",
    "sg:tags":[
        "system",
        "software"
    ],
    "wof:name":"Thistleworth Ltd",
    "wof:placetype":"venue"
},
  "geometry": {"coordinates":[-0.4354330003,51.5679130554],"type":"Point"}
}