{
  "type": "Feature",
  "properties": {
    "addr:full":"3 All Saints Passage Huntingdon Cambridgeshire PE29 3LE",
    "addr:housenumber":"3",
    "addr:postcode":"pe29 3le",
    "addr:street":"All Saints Passage Huntingdon",
    "iso:country":"GB",
    "sg:address":"3 All Saints Passage",
    "sg:city":"Huntingdon",
    "sg:classifiers":[
        {
            "category":"Shopping",
            "subcategory":"Department Store",
            "type":"Retail Goods"
        }
    ],
    "sg:phone":"+44 1480 356776",
    "sg:postcode":"PE29 3LE",
    "sg:province":"Cambridgeshire",
    "wof:name":"Slapstick",
    "wof:placetype":"venue"
},
  "geometry": {"coordinates":[-0.184409,52.330475],"type":"Point"}
}