{
  "type": "Feature",
  "properties": {
    "iso:country":"GB",
    "sg:address":"Unit 8 Gremista Industrial Estate, 8 Lower Blackhill",
    "sg:city":"Lerwick",
    "sg:classifiers":[
        {
            "category":"Shopping",
            "subcategory":"Clothing, Apparel, & Fashions",
            "type":"Retail Goods"
        }
    ],
    "sg:phone":"+44 1595 696222",
    "sg:postcode":"ZE1 0PX",
    "sg:province":"Shetland Islands",
    "sg:tags":[
        "protective",
        "clothing"
    ],
    "wof:name":"Globus Ltd",
    "wof:placetype":"venue"
},
  "geometry": {"coordinates":[-1.145224,60.151829],"type":"Point"}
}