{
  "type": "Feature",
  "properties": {
    "iso:country":"GB",
    "sg:address":"35 Becton Lane, Barton On Sea",
    "sg:city":"New Milton",
    "sg:classifiers":[
        {
            "category":"Travel",
            "subcategory":"Hotels & Motels",
            "type":"Entertainment"
        }
    ],
    "sg:postcode":"BH25 7AB",
    "sg:province":"Hampshire",
    "sg:tags":[
        "house",
        "guest"
    ],
    "wof:name":"Sunnycroft",
    "wof:placetype":"venue"
},
  "geometry": {"coordinates":[-1.651588,50.742687],"type":"Point"}
}