{
  "type": "Feature",
  "properties": {
    "iso:country":"GB",
    "sg:address":"101 Felixstowe Road",
    "sg:city":"Ipswich",
    "sg:classifiers":[
        {
            "category":"Fast Food",
            "type":"Food & Drink"
        }
    ],
    "sg:phone":"+44 1473 724394",
    "sg:postcode":"IP3 8DZ",
    "sg:province":"Suffolk",
    "sg:tags":[
        "away",
        "take"
    ],
    "wof:name":"Golden Flower",
    "wof:placetype":"venue"
},
  "geometry": {"coordinates":[1.1780910492,52.0487174988],"type":"Point"}
}