{
  "type": "Feature",
  "properties": {
    "addr:full":"17 Cooper Road, Lordswood Chatham Kent ME5 8DH",
    "addr:housenumber":"17",
    "addr:postcode":"me5 8dh",
    "addr:street":"Cooper Road Lordswood",
    "iso:country":"GB",
    "sg:address":"17 Cooper Road, Lordswood",
    "sg:city":"Chatham",
    "sg:classifiers":[
        {
            "category":"Personal",
            "subcategory":"Beauty Salon",
            "type":"Services"
        }
    ],
    "sg:postcode":"ME5 8DH",
    "sg:province":"Kent",
    "sg:tags":[
        "unisex",
        "hairdresser"
    ],
    "wof:name":"Junes Mobile Family Hairdresser",
    "wof:placetype":"venue"
},
  "geometry": {"coordinates":[0.5335940123,51.3415184021],"type":"Point"}
}