{
  "type": "Feature",
  "properties": {
    "addr:full":"26 Gayal Croft Milton Keynes Buckinghamshire MK5 7HX",
    "addr:housenumber":"26",
    "addr:postcode":"mk5 7hx",
    "addr:street":"Gayal Croft",
    "iso:country":"GB",
    "sg:address":"26 Gayal Croft",
    "sg:city":"Milton Keynes",
    "sg:classifiers":[
        {
            "category":"Building & Trades",
            "subcategory":"Cleaning & Sanitation",
            "type":"Services"
        }
    ],
    "sg:phone":"+44 1908 505562",
    "sg:postcode":"MK5 7HX",
    "sg:province":"Buckinghamshire",
    "sg:tags":[
        "cleaner",
        "window"
    ],
    "wof:name":"Graduate Cleaning Services",
    "wof:placetype":"venue"
},
  "geometry": {"coordinates":[-0.7816190124,52.013168335],"type":"Point"}
}