{
  "type": "Feature",
  "properties": {
    "addr:full":"8 Front Street Consett Durham DH8 5AQ",
    "addr:housenumber":"8",
    "addr:postcode":"dh8 5aq",
    "addr:street":"Front Street",
    "iso:country":"GB",
    "sg:address":"8 Front Street",
    "sg:city":"Consett",
    "sg:classifiers":[
        {
            "category":"Professional",
            "subcategory":"Accounting & Tax Preparation",
            "type":"Services"
        }
    ],
    "sg:postcode":"DH8 5AQ",
    "sg:province":"Durham",
    "sg:tags":[
        "accountant"
    ],
    "wof:name":"G Vasey",
    "wof:placetype":"venue"
},
  "geometry": {"coordinates":[-1.83197999,54.8512191772],"type":"Point"}
}