{
  "type": "Feature",
  "properties": {
    "iso:country":"GB",
    "sg:address":"Karibuni, 20 Cintra Avenue",
    "sg:city":"Reading",
    "sg:classifiers":[
        {
            "category":"Shopping",
            "subcategory":"Pharmacy",
            "type":"Retail Goods"
        }
    ],
    "sg:postcode":"RG2 7AU",
    "sg:province":"Berkshire",
    "sg:tags":[
        "medicine",
        "therapy"
    ],
    "wof:name":"Helen & Jeremy Rowe",
    "wof:placetype":"venue"
},
  "geometry": {"coordinates":[-0.9599400163,51.4427185059],"type":"Point"}
}