{
  "type": "Feature",
  "properties": {
    "addr:full":"Unit 6 Angel La Penrith Cumbria CA11 7BP",
    "addr:housenumber":"unit 6",
    "addr:postcode":"ca11 7bp",
    "addr:street":"Angel La Penrith",
    "iso:country":"GB",
    "sg:address":"Unit 6 Angel La",
    "sg:city":"Penrith",
    "sg:classifiers":[
        {
            "category":"Communications",
            "subcategory":"Film & Video Production",
            "type":"Services"
        }
    ],
    "sg:phone":"+44 1768 867638",
    "sg:postcode":"CA11 7BP",
    "sg:province":"Cumbria",
    "sg:tags":[
        "tv"
    ],
    "wof:name":"Radio Rentals",
    "wof:placetype":"venue"
},
  "geometry": {"coordinates":[-2.752574,54.663456],"type":"Point"}
}