{
  "type": "Feature",
  "properties": {
    "iso:country":"GB",
    "sg:address":"163 Turnpike Link",
    "sg:city":"Croydon",
    "sg:classifiers":[
        {
            "category":"Professional",
            "subcategory":"Computer Services",
            "type":"Services"
        }
    ],
    "sg:phone":"+44 20 8688 8002",
    "sg:postcode":"CR0 5NW",
    "sg:province":"Surrey",
    "sg:tags":[
        "system",
        "software"
    ],
    "wof:name":"Project Central Ltd.",
    "wof:placetype":"venue"
},
  "geometry": {"coordinates":[-0.085335,51.373409],"type":"Point"}
}