{
  "type": "Feature",
  "properties": {
    "iso:country":"GB",
    "sg:address":"89 St James's Street",
    "sg:city":"Brighton",
    "sg:classifiers":[
        {
            "category":"Fast Food",
            "type":"Food & Drink"
        }
    ],
    "sg:phone":"+44 1273 688111",
    "sg:postcode":"BN2 1TP",
    "sg:province":"East Sussex",
    "sg:tags":[
        "away",
        "take"
    ],
    "wof:name":"Grubbs",
    "wof:placetype":"venue"
},
  "geometry": {"coordinates":[-0.1242159978,50.8230781555],"type":"Point"}
}