{
  "type": "Feature",
  "properties": {
    "iso:country":"GB",
    "sg:address":"28 Strathmore Rd",
    "sg:city":"Teddington",
    "sg:classifiers":[
        {
            "category":"Building & Trades",
            "subcategory":"Plumbing",
            "type":"Services"
        }
    ],
    "sg:postcode":"TW11 8UJ",
    "sg:province":"Greater London",
    "sg:tags":[
        "heating"
    ],
    "wof:name":"Andrew Light Plumbing & Heating",
    "wof:placetype":"venue"
},
  "geometry": {"coordinates":[-0.3439069986,51.433013916],"type":"Point"}
}