{
  "type": "Feature",
  "properties": {
    "iso:country":"GB",
    "sg:address":"Central House, Central Avenue",
    "sg:city":"Sittingbourne",
    "sg:classifiers":[
        {
            "category":"Organizations",
            "subcategory":"Non-profit Organization",
            "type":"Services"
        }
    ],
    "sg:phone":"+44 1795 479794",
    "sg:postcode":"ME10 4NU",
    "sg:province":"Kent",
    "sg:tags":[
        "organisation",
        "voluntary",
        "charity"
    ],
    "wof:name":"Victims Support Swale",
    "wof:placetype":"venue"
},
  "geometry": {"coordinates":[0.7348949909,51.3391036987],"type":"Point"}
}