{
  "type": "Feature",
  "properties": {
    "iso:country":"GB",
    "sg:address":"Tweedmill Buildings, Soroba Road",
    "sg:city":"Oban",
    "sg:classifiers":[
        {
            "category":"Food & Beverages",
            "subcategory":"Bakery",
            "type":"Retail Goods"
        },
        {
            "category":"Wholesale",
            "subcategory":"Fruits & Vegetables",
            "type":"Manufacturing & Wholesale Goods"
        }
    ],
    "sg:phone":"+44 1631 563711",
    "sg:postcode":"PA34 4HQ",
    "sg:province":"Argyll and Bute",
    "sg:tags":[
        "baker"
    ],
    "wof:name":"L & S Macdonald Ltd.",
    "wof:placetype":"venue"
},
  "geometry": {"coordinates":[-5.469119,56.407982],"type":"Point"}
}