{
  "type": "Feature",
  "properties": {
    "addr:full":"167 Sauchiehall Street Glasgow Glasgow City G2 3ER",
    "addr:housenumber":"167",
    "addr:postcode":"g2 3er",
    "addr:street":"Sauchiehall Street",
    "iso:country":"GB",
    "sg:address":"167 Sauchiehall Street",
    "sg:city":"Glasgow",
    "sg:classifiers":[
        {
            "category":"Shopping",
            "subcategory":"Pharmacy",
            "type":"Retail Goods"
        }
    ],
    "sg:phone":"+44 141 332 4284",
    "sg:postcode":"G2 3ER",
    "sg:province":"Glasgow City",
    "sg:tags":[
        "store",
        "drug",
        "outlet"
    ],
    "wof:name":"Superdrug Stores plc",
    "wof:placetype":"venue"
},
  "geometry": {"coordinates":[-4.25912714,55.8647651672],"type":"Point"}
}