{
  "type": "Feature",
  "properties": {
    "addr:full":"Groves Centre, Manor Gro Tonbridge Kent TN10 3DT",
    "addr:postcode":"tn10 3dt",
    "addr:street":"Gro Tonbridge",
    "iso:country":"GB",
    "sg:address":"Groves Centre, Manor Gro",
    "sg:city":"Tonbridge",
    "sg:classifiers":[
        {
            "category":"Organizations",
            "subcategory":"Non-profit Organization",
            "type":"Services"
        }
    ],
    "sg:phone":"+44 1732 362699",
    "sg:postcode":"TN10 3DT",
    "sg:province":"Kent",
    "sg:tags":[
        "organisation",
        "voluntary",
        "charity"
    ],
    "wof:name":"Tonbridge Voluntary Service Unit",
    "wof:placetype":"venue"
},
  "geometry": {"coordinates":[0.2764399946,51.2026290894],"type":"Point"}
}