{
  "type": "Feature",
  "properties": {
    "iso:country":"GB",
    "sg:address":"74 High Street",
    "sg:city":"Lee-on-the-solent",
    "sg:classifiers":[
        {
            "category":"Shopping",
            "subcategory":"Bicycles & Sporting Goods",
            "type":"Retail Goods"
        }
    ],
    "sg:phone":"+44 23 9255 1825",
    "sg:postcode":"PO13 9DA",
    "sg:province":"Hampshire",
    "sg:tags":[
        "cycle",
        "accessory"
    ],
    "wof:name":"Wheels",
    "wof:placetype":"venue"
},
  "geometry": {"coordinates":[-1.201254,50.801208],"type":"Point"}
}