{
  "type": "Feature",
  "properties": {
    "addr:full":"16 Uplands Road Orpington Kent BR6 0RJ",
    "addr:housenumber":"16",
    "addr:postcode":"br6 0rj",
    "addr:street":"Uplands Road",
    "iso:country":"GB",
    "sg:address":"16 Uplands Road",
    "sg:city":"Orpington",
    "sg:classifiers":[
        {
            "category":"Building & Trades",
            "subcategory":"Landscaping Services",
            "type":"Services"
        }
    ],
    "sg:phone":"+44 1689 833405",
    "sg:postcode":"BR6 0RJ",
    "sg:province":"Kent",
    "sg:tags":[
        "landscape",
        "contractor"
    ],
    "wof:name":"H & H Landscapes",
    "wof:placetype":"venue"
},
  "geometry": {"coordinates":[0.1052919999,51.3754196167],"type":"Point"}
}