{
  "type": "Feature",
  "properties": {
    "iso:country":"GB",
    "sg:address":"25 Stamford Street",
    "sg:city":"Altrincham",
    "sg:classifiers":[
        {
            "category":"Retail",
            "subcategory":"Laundry & Dry Cleaning",
            "type":"Services"
        }
    ],
    "sg:postcode":"WA14 1EX",
    "sg:province":"Cheshire",
    "sg:tags":[
        "alteration"
    ],
    "wof:name":"Needles & Pins",
    "wof:placetype":"venue"
},
  "geometry": {"coordinates":[-2.348354,53.389286],"type":"Point"}
}