{
  "type": "Feature",
  "properties": {
    "addr:full":"232 Hangleton Rd Hove East Sussex BN3 7LP",
    "addr:housenumber":"232",
    "addr:postcode":"bn3 7lp",
    "addr:street":"Hangleton Rd",
    "iso:country":"GB",
    "sg:address":"232 Hangleton Rd",
    "sg:city":"Hove",
    "sg:classifiers":[
        {
            "category":"Health Services",
            "subcategory":"Podiatrist",
            "type":"Services"
        }
    ],
    "sg:phone":"+44 1273 736852",
    "sg:postcode":"BN3 7LP",
    "sg:province":"East Sussex",
    "sg:tags":[
        "podiatrists",
        "chiropodist"
    ],
    "wof:name":"I M Johnson",
    "wof:placetype":"venue"
},
  "geometry": {"coordinates":[-0.190938,50.846069],"type":"Point"}
}