{
  "type": "Feature",
  "properties": {
    "addr:full":"3 Walmesley Terrace Bath Bath and North East Somerset BA1 6DW",
    "addr:housenumber":"3",
    "addr:postcode":"ba1 6dw",
    "addr:street":"Walmesley Terrace",
    "iso:country":"GB",
    "sg:address":"3 Walmesley Terrace",
    "sg:city":"Bath",
    "sg:classifiers":[
        {
            "category":"Professional",
            "subcategory":"Management & Consulting",
            "type":"Services"
        }
    ],
    "sg:postcode":"BA1 6DW",
    "sg:province":"Bath and North East Somerset",
    "sg:tags":[
        "consultant",
        "business"
    ],
    "wof:name":"Hambledon Consulting Ltd.",
    "wof:placetype":"venue"
},
  "geometry": {"coordinates":[-2.3534440994,51.3936538696],"type":"Point"}
}