{
  "type": "Feature",
  "properties": {
    "iso:country":"GB",
    "sg:address":"45 Derngate",
    "sg:city":"Northampton",
    "sg:classifiers":[
        {
            "category":"Professional",
            "subcategory":"Art Services",
            "type":"Services"
        }
    ],
    "sg:phone":"+44 1604 634848",
    "sg:postcode":"NN1 1UE",
    "sg:province":"Northamptonshire",
    "sg:tags":[
        "photographer"
    ],
    "wof:name":"T Sherwood",
    "wof:placetype":"venue"
},
  "geometry": {"coordinates":[-0.891716,52.236294],"type":"Point"}
}