{
  "type": "Feature",
  "properties": {
    "addr:full":"33 Stirling Avenue Shepperton Surrey TW17 8TH",
    "addr:housenumber":"33",
    "addr:postcode":"tw17 8th",
    "addr:street":"Stirling Avenue",
    "iso:country":"GB",
    "sg:address":"33 Stirling Avenue",
    "sg:city":"Shepperton",
    "sg:classifiers":[
        {
            "category":"Taxi",
            "type":"Transportation"
        }
    ],
    "sg:phone":"+44 1932 785732",
    "sg:postcode":"TW17 8TH",
    "sg:province":"Surrey",
    "sg:tags":[
        "mini",
        "cab"
    ],
    "wof:name":"Pack of Cars",
    "wof:placetype":"venue"
},
  "geometry": {"coordinates":[-0.448547,51.394321],"type":"Point"}
}