{
  "type": "Feature",
  "properties": {
    "iso:country":"GB",
    "sg:address":"179 High St, Tunstall",
    "sg:city":"Stoke On Trent",
    "sg:classifiers":[
        {
            "category":"Shopping",
            "subcategory":"Shoes",
            "type":"Retail Goods"
        }
    ],
    "sg:phone":"+44 1782 835196",
    "sg:postcode":"ST6 5EA",
    "sg:province":"Staffordshire",
    "sg:tags":[
        "shop"
    ],
    "wof:name":"Benson Shoe",
    "wof:placetype":"venue"
},
  "geometry": {"coordinates":[-2.2107720375,53.0592460632],"type":"Point"}
}