{
  "type": "Feature",
  "properties": {
    "addr:full":"27 High Street Bangor Gwynedd LL57 1NP",
    "addr:housenumber":"27",
    "addr:postcode":"ll57 1np",
    "addr:street":"High Street",
    "iso:country":"GB",
    "sg:address":"27 High Street",
    "sg:city":"Bangor",
    "sg:classifiers":[
        {
            "category":"Food & Beverages",
            "subcategory":"Groceries & Convenience Stores",
            "type":"Retail Goods"
        }
    ],
    "sg:phone":"+44 1248 351148",
    "sg:postcode":"LL57 1NP",
    "sg:province":"Gwynedd",
    "wof:name":"Parkers",
    "wof:placetype":"venue"
},
  "geometry": {"coordinates":[-4.1145119667,53.2309417725],"type":"Point"}
}