{
  "type": "Feature",
  "properties": {
    "iso:country":"GB",
    "sg:address":"Unit 3 Javel Industrial Estate, Three Cocks",
    "sg:city":"Brecon",
    "sg:classifiers":[
        {
            "category":"Manufacturing",
            "subcategory":"Petroleum Products",
            "type":"Manufacturing & Wholesale Goods"
        }
    ],
    "sg:phone":"+44 1497 847771",
    "sg:postcode":"LD3 0SD",
    "sg:province":"Powys",
    "sg:tags":[
        "double",
        "glazing"
    ],
    "wof:name":"Wye Valley Windows West Ltd.",
    "wof:placetype":"venue"
},
  "geometry": {"coordinates":[-3.2059419155,52.0324287415],"type":"Point"}
}