{
  "type": "Feature",
  "properties": {
    "addr:full":"The Threshing Barn, Bignell Park Barnes Bicester Oxfordshire OX26 1TD",
    "addr:postcode":"ox26 1td",
    "addr:street":"Bignell Park Barnes",
    "iso:country":"GB",
    "sg:address":"The Threshing Barn, Bignell Park Barnes",
    "sg:city":"Bicester",
    "sg:classifiers":[
        {
            "category":"Autos & Motor Vehicles",
            "subcategory":"Automobile Sales",
            "type":"Retail Goods"
        }
    ],
    "sg:phone":"+44 1869 322050",
    "sg:postcode":"OX26 1TD",
    "sg:province":"Oxfordshire",
    "sg:tags":[
        "car"
    ],
    "wof:name":"The Dutton-Forshaw Motor Co. Ltd.",
    "wof:placetype":"venue"
},
  "geometry": {"coordinates":[-1.15354,51.898026],"type":"Point"}
}