{
  "type": "Feature",
  "properties": {
    "addr:full":"Whittingehame Haddington East Lothian EH41 4QA",
    "addr:postcode":"eh41 4qa",
    "iso:country":"GB",
    "sg:address":"Whittingehame",
    "sg:city":"Haddington",
    "sg:classifiers":[
        {
            "category":"Farming",
            "subcategory":"Farm",
            "type":"Manufacturing & Wholesale Goods"
        }
    ],
    "sg:phone":"+44 1620 860254",
    "sg:postcode":"EH41 4QA",
    "sg:province":"East Lothian",
    "sg:tags":[
        "mixed",
        "crop"
    ],
    "wof:name":"Whittingehame Estate",
    "wof:placetype":"venue"
},
  "geometry": {"coordinates":[-2.772574,55.956551],"type":"Point"}
}