{
  "type": "Feature",
  "properties": {
    "iso:country":"GB",
    "sg:address":"64 Frogmore St",
    "sg:city":"Abergavenny",
    "sg:classifiers":[
        {
            "category":"Shopping",
            "subcategory":"Thrift Store",
            "type":"Retail Goods"
        }
    ],
    "sg:phone":"+44 1873 856606",
    "sg:postcode":"NP7 5AU",
    "sg:province":"Herefordshire",
    "sg:tags":[
        "shop",
        "charity"
    ],
    "wof:name":"Marie Curie Cancer Care",
    "wof:placetype":"venue"
},
  "geometry": {"coordinates":[-3.020384,51.82394],"type":"Point"}
}