{
  "type": "Feature",
  "properties": {
    "iso:country":"GB",
    "sg:address":"Coed Cyrnol, Mona Road",
    "sg:city":"Menai Bridge",
    "sg:classifiers":[
        {
            "category":"Home & Garden",
            "subcategory":"Furniture",
            "type":"Retail Goods"
        }
    ],
    "sg:phone":"+44 1248 714128",
    "sg:postcode":"LL59 5EA",
    "sg:province":"Isle of Anglesey",
    "wof:name":"Hilary Tomkins Soft Furnishings",
    "wof:placetype":"venue"
},
  "geometry": {"coordinates":[-4.163441,53.224579],"type":"Point"}
}