{
  "type": "Feature",
  "properties": {
    "addr:full":"London House, 266 Fulham Rd West Brompton Greater London SW10 9EL",
    "addr:housenumber":"266",
    "addr:postcode":"sw10 9el",
    "addr:street":"Fulham Rd",
    "iso:country":"GB",
    "sg:address":"London House, 266 Fulham Rd",
    "sg:city":"West Brompton",
    "sg:classifiers":[
        {
            "category":"Shopping",
            "subcategory":"Computers & Home Electronics",
            "type":"Retail Goods"
        }
    ],
    "sg:postcode":"SW10 9EL",
    "sg:province":"Greater London",
    "wof:name":"Genesis Computers",
    "wof:placetype":"venue"
},
  "geometry": {"coordinates":[-0.1842209995,51.484249115],"type":"Point"}
}