{
  "type": "Feature",
  "properties": {
    "addr:full":"Unit 3 Greenclose Road Ilfracombe Devon EX34 8BT",
    "addr:housenumber":"unit 3",
    "addr:postcode":"ex34 8bt",
    "addr:street":"Greenclose Road",
    "iso:country":"GB",
    "sg:address":"Unit 3 Greenclose Road",
    "sg:city":"Ilfracombe",
    "sg:classifiers":[
        {
            "category":"Home & Garden",
            "subcategory":"Building Materials",
            "type":"Retail Goods"
        },
        {
            "category":"Building & Trades",
            "subcategory":"Construction",
            "type":"Services"
        }
    ],
    "sg:phone":"+44 1271 863301",
    "sg:postcode":"EX34 8BT",
    "sg:province":"Devon",
    "sg:tags":[
        "ironwork",
        "product",
        "builder",
        "production",
        "design",
        "diy",
        "iron",
        "wrought"
    ],
    "wof:name":"North Devon Wrought Iron Design",
    "wof:placetype":"venue"
},
  "geometry": {"coordinates":[-4.126399,51.207699],"type":"Point"}
}