{
  "type": "Feature",
  "properties": {
    "addr:full":"21 Guildhall Street Thetford Norfolk IP24 2DT",
    "addr:housenumber":"21",
    "addr:postcode":"ip24 2dt",
    "addr:street":"Guildhall Street",
    "iso:country":"GB",
    "sg:address":"21 Guildhall Street",
    "sg:city":"Thetford",
    "sg:classifiers":[
        {
            "category":"Shopping",
            "subcategory":"Baby Store",
            "type":"Retail Goods"
        }
    ],
    "sg:postcode":"IP24 2DT",
    "sg:province":"Norfolk",
    "sg:tags":[
        "nursery",
        "accessory"
    ],
    "wof:name":"Tots to Teens",
    "wof:placetype":"venue"
},
  "geometry": {"coordinates":[0.7514399886,52.4126777649],"type":"Point"}
}