{
  "type": "Feature",
  "properties": {
    "addr:full":"14 Woodlands Terrace Glasgow Glasgow City G3 6DF",
    "addr:housenumber":"14",
    "addr:postcode":"g3 6df",
    "addr:street":"Woodlands Terrace",
    "iso:country":"GB",
    "sg:address":"14 Woodlands Terrace",
    "sg:city":"Glasgow",
    "sg:classifiers":[
        {
            "category":"Real Estate",
            "subcategory":"Architect",
            "type":"Services"
        }
    ],
    "sg:postcode":"G3 6DF",
    "sg:province":"Glasgow City",
    "wof:name":"Inhouse Design",
    "wof:placetype":"venue"
},
  "geometry": {"coordinates":[-4.2788381577,55.8684196472],"type":"Point"}
}