{
  "type": "Feature",
  "properties": {
    "addr:full":"Lombard House, Upper Bridge Street Canterbury Kent CT1 2NF",
    "addr:postcode":"ct1 2nf",
    "addr:street":"Upper Bridge Street",
    "iso:country":"GB",
    "sg:address":"Lombard House, Upper Bridge Street",
    "sg:city":"Canterbury",
    "sg:classifiers":[
        {
            "category":"Professional",
            "subcategory":"Management & Consulting",
            "type":"Services"
        }
    ],
    "sg:phone":"+44 1227 787211",
    "sg:postcode":"CT1 2NF",
    "sg:province":"Kent",
    "sg:tags":[
        "consultant",
        "business"
    ],
    "wof:name":"John Dean",
    "wof:placetype":"venue"
},
  "geometry": {"coordinates":[1.083511,51.276615],"type":"Point"}
}