{
  "type": "Feature",
  "properties": {
    "iso:country":"GB",
    "sg:address":"27 Abington Square",
    "sg:city":"Northampton",
    "sg:classifiers":[
        {
            "category":"Health Services",
            "subcategory":"Optometrist",
            "type":"Services"
        }
    ],
    "sg:postcode":"NN1 4AE",
    "sg:province":"Northamptonshire",
    "sg:tags":[
        "optician"
    ],
    "wof:name":"W P S Optmetrists",
    "wof:placetype":"venue"
},
  "geometry": {"coordinates":[-0.888053,52.240314],"type":"Point"}
}