{
  "type": "Feature",
  "properties": {
    "iso:country":"GB",
    "sg:address":"Cardigan Road",
    "sg:city":"Oldham",
    "sg:classifiers":[
        {
            "category":"Building & Trades",
            "subcategory":"Construction",
            "type":"Services"
        }
    ],
    "sg:phone":"+44 161 682 4958",
    "sg:postcode":"OL8 4SF",
    "sg:province":"Lancashire",
    "sg:tags":[
        "glazier"
    ],
    "wof:name":"Ian Donnelly",
    "wof:placetype":"venue"
},
  "geometry": {"coordinates":[-2.1395030022,53.5219573975],"type":"Point"}
}