{
  "type": "Feature",
  "properties": {
    "addr:full":"Queensville Retail Park, Silkmore Lane Stafford Staffordshire ST17 4TS",
    "addr:postcode":"st17 4ts",
    "addr:street":"Queensville Retail Park Silkmore Lane",
    "iso:country":"GB",
    "sg:address":"Queensville Retail Park, Silkmore Lane",
    "sg:city":"Stafford",
    "sg:classifiers":[
        {
            "category":"Home & Garden",
            "subcategory":"Furniture",
            "type":"Retail Goods"
        }
    ],
    "sg:phone":"+44 1785 248433",
    "sg:postcode":"ST17 4TS",
    "sg:province":"Staffordshire",
    "wof:name":"Dunelm Mill Shop",
    "wof:placetype":"venue"
},
  "geometry": {"coordinates":[-2.09151,52.79187],"type":"Point"}
}