{
  "type": "Feature",
  "properties": {
    "iso:country":"GB",
    "sg:address":"5 Wolverhampton Road",
    "sg:city":"Stafford",
    "sg:classifiers":[
        {
            "category":"Personal",
            "subcategory":"Beauty Salon",
            "type":"Services"
        }
    ],
    "sg:phone":"+44 1785 258481",
    "sg:postcode":"ST17 4BN",
    "sg:province":"Staffordshire",
    "sg:tags":[
        "unisex",
        "hairdresser"
    ],
    "wof:name":"Classique Traditional Hairdressers",
    "wof:placetype":"venue"
},
  "geometry": {"coordinates":[-2.11379,52.803009],"type":"Point"}
}