{
  "type": "Feature",
  "properties": {
    "iso:country":"GB",
    "sg:address":"2 Church Lane",
    "sg:city":"London",
    "sg:classifiers":[
        {
            "category":"Fast Food",
            "type":"Food & Drink"
        }
    ],
    "sg:phone":"+44 20 8767 7377",
    "sg:postcode":"SW17 9PP",
    "sg:province":"Greater London",
    "sg:tags":[
        "away",
        "take"
    ],
    "wof:name":"Curry Express",
    "wof:placetype":"venue"
},
  "geometry": {"coordinates":[-0.163375,51.424858],"type":"Point"}
}