{
  "type": "Feature",
  "properties": {
    "iso:country":"GB",
    "sg:address":"327 Foleshill Rd",
    "sg:city":"Coventry",
    "sg:classifiers":[
        {
            "category":"Manufacturing",
            "subcategory":"Tools & Machinery",
            "type":"Manufacturing & Wholesale Goods"
        }
    ],
    "sg:phone":"+44 247663978",
    "sg:postcode":"CV1 4JS",
    "sg:province":"West Midlands",
    "sg:tags":[
        "society",
        "friendly"
    ],
    "wof:name":"Nesh Financial Insurance Service",
    "wof:placetype":"venue"
},
  "geometry": {"coordinates":[-1.504836,52.422382],"type":"Point"}
}