{
  "type": "Feature",
  "properties": {
    "iso:country":"GB",
    "sg:address":"28 High St",
    "sg:city":"Aylesbury",
    "sg:classifiers":[
        {
            "category":"Communications",
            "type":"Services"
        }
    ],
    "sg:phone":"+44 1296 622958",
    "sg:postcode":"HP22 6EA",
    "sg:province":"Buckinghamshire",
    "sg:tags":[
        "tv",
        "video",
        "radio"
    ],
    "wof:name":"Wendover Televisions",
    "wof:placetype":"venue"
},
  "geometry": {"coordinates":[-0.743882,51.762234],"type":"Point"}
}