{
  "type": "Feature",
  "properties": {
    "addr:full":"Rose Hill, Heywood Road Bideford Devon EX39 3PG",
    "addr:postcode":"ex39 3pg",
    "addr:street":"Heywood Road",
    "iso:country":"GB",
    "sg:address":"Rose Hill, Heywood Road",
    "sg:city":"Bideford",
    "sg:classifiers":[
        {
            "category":"Health Services",
            "subcategory":"Nursing And Care Facility",
            "type":"Services"
        },
        {
            "category":"Social Services",
            "subcategory":"Retirement Home",
            "type":"Services"
        }
    ],
    "sg:phone":"+44 1237 477238",
    "sg:postcode":"EX39 3PG",
    "sg:province":"Devon",
    "sg:tags":[
        "residential"
    ],
    "wof:name":"Northam Lodge",
    "wof:placetype":"venue"
},
  "geometry": {"coordinates":[-4.204259,51.019249],"type":"Point"}
}