{
  "type": "Feature",
  "properties": {
    "addr:full":"45 Windmill Close Brixham Devon TQ5 9SQ",
    "addr:housenumber":"45",
    "addr:postcode":"tq5 9sq",
    "addr:street":"Windmill Close",
    "iso:country":"GB",
    "sg:address":"45 Windmill Close",
    "sg:city":"Brixham",
    "sg:classifiers":[
        {
            "category":"Health Services",
            "subcategory":"Health Practitioner",
            "type":"Services"
        }
    ],
    "sg:phone":"+44 1803 851916",
    "sg:postcode":"TQ5 9SQ",
    "sg:province":"Devon",
    "sg:tags":[
        "acupuncture"
    ],
    "wof:name":"W J Dyer",
    "wof:placetype":"venue"
},
  "geometry": {"coordinates":[-3.5131869316,50.3913917542],"type":"Point"}
}