{
  "type": "Feature",
  "properties": {
    "iso:country":"GB",
    "sg:address":"31a High Street",
    "sg:city":"East Grinstead",
    "sg:classifiers":[
        {
            "category":"Social Services",
            "subcategory":"Job Training",
            "type":"Services"
        },
        {
            "category":"Education",
            "subcategory":"Special Training",
            "type":"Public Place"
        }
    ],
    "sg:phone":"+44 1342 323089",
    "sg:postcode":"RH19 3AF",
    "sg:province":"East Sussex",
    "sg:tags":[
        "product",
        "centre"
    ],
    "wof:name":"The Hubbard College of Administration",
    "wof:placetype":"venue"
},
  "geometry": {"coordinates":[-0.007057,51.124004],"type":"Point"}
}