{
  "type": "Feature",
  "properties": {
    "iso:country":"GB",
    "sg:address":"182 New Road, Skewen",
    "sg:city":"Neath",
    "sg:classifiers":[
        {
            "category":"Shopping",
            "subcategory":"Pets & Pet Supplies",
            "type":"Retail Goods"
        }
    ],
    "sg:postcode":"SA10 6HD",
    "sg:province":"Neath Port Talbot",
    "sg:tags":[
        "food"
    ],
    "wof:name":"Skewen Pet Supplies",
    "wof:placetype":"venue"
},
  "geometry": {"coordinates":[-3.845755,51.660812],"type":"Point"}
}