{
  "type": "Feature",
  "properties": {
    "iso:country":"GB",
    "sg:address":"7 Cricketers Parade, Broadwater St West",
    "sg:city":"Worthing",
    "sg:classifiers":[
        {
            "category":"Health Services",
            "subcategory":"Optometrist",
            "type":"Services"
        }
    ],
    "sg:phone":"+44 1903 231041",
    "sg:postcode":"BN14 9DB",
    "sg:province":"West Sussex",
    "sg:tags":[
        "optician"
    ],
    "wof:name":"T H Collison",
    "wof:placetype":"venue"
},
  "geometry": {"coordinates":[-0.3750599921,50.8291893005],"type":"Point"}
}