{
  "type": "Feature",
  "properties": {
    "addr:full":"65 Carters Rise, Calcot Reading Berkshire RG31 7YS",
    "addr:housenumber":"65",
    "addr:postcode":"rg31 7ys",
    "addr:street":"Carters Rise",
    "iso:country":"GB",
    "sg:address":"65 Carters Rise, Calcot",
    "sg:city":"Reading",
    "sg:classifiers":[
        {
            "category":"Retail",
            "subcategory":"Auto Repair",
            "type":"Services"
        }
    ],
    "sg:postcode":"RG31 7YS",
    "sg:province":"Berkshire",
    "sg:tags":[
        "modification",
        "garage"
    ],
    "wof:name":"Metrocare Mobile",
    "wof:placetype":"venue"
},
  "geometry": {"coordinates":[-1.0254609585,51.4397621155],"type":"Point"}
}