{
  "type": "Feature",
  "properties": {
    "iso:country":"GB",
    "sg:address":"350-366 Wellington Rd North",
    "sg:city":"Stockport",
    "sg:classifiers":[
        {
            "category":"Retail",
            "subcategory":"Laundry & Dry Cleaning",
            "type":"Services"
        }
    ],
    "sg:phone":"+44 161 975 0230",
    "sg:postcode":"SK4 4QP",
    "sg:province":"Cheshire",
    "sg:tags":[
        "alteration"
    ],
    "wof:name":"Johnsons The Cleaners",
    "wof:placetype":"venue"
},
  "geometry": {"coordinates":[-2.177529,53.42786],"type":"Point"}
}