{
  "type": "Feature",
  "properties": {
    "iso:country":"GB",
    "sg:address":"23 Wolborough St",
    "sg:city":"Newton Abbot",
    "sg:classifiers":[
        {
            "category":"Shopping",
            "subcategory":"News",
            "type":"Retail Goods"
        }
    ],
    "sg:phone":"+44 1626 365166",
    "sg:postcode":"TQ12 1JR",
    "sg:province":"Devon",
    "sg:tags":[
        "newsagent"
    ],
    "wof:name":"V H Oliver & Son",
    "wof:placetype":"venue"
},
  "geometry": {"coordinates":[-3.614053,50.528931],"type":"Point"}
}