{
  "type": "Feature",
  "properties": {
    "iso:country":"GB",
    "sg:address":"Acorn Stores, Market Place",
    "sg:city":"Banbury",
    "sg:classifiers":[
        {
            "category":"Shopping",
            "subcategory":"Department Store",
            "type":"Retail Goods"
        }
    ],
    "sg:phone":"+44 1869 338291",
    "sg:postcode":"OX15 0SB",
    "sg:province":"Oxfordshire",
    "wof:name":"Oxford Swindon & Gloucester Co-Operative Society Ltd.",
    "wof:placetype":"venue"
},
  "geometry": {"coordinates":[-1.32092,51.981171],"type":"Point"}
}