{
  "type": "Feature",
  "properties": {
    "addr:full":"4 Picture House Buildings Billingham Durham TS23 1HE",
    "addr:housenumber":"4",
    "addr:postcode":"ts23 1he",
    "addr:street":"Billingham",
    "iso:country":"GB",
    "sg:address":"4 Picture House Buildings",
    "sg:city":"Billingham",
    "sg:classifiers":[
        {
            "category":"Cafe",
            "type":"Food & Drink"
        }
    ],
    "sg:postcode":"TS23 1HE",
    "sg:province":"Durham",
    "sg:tags":[
        "tea",
        "room"
    ],
    "wof:name":"Lelly's Sandwich Bar",
    "wof:placetype":"venue"
},
  "geometry": {"coordinates":[-1.293645,54.606857],"type":"Point"}
}