{
  "type": "Feature",
  "properties": {
    "iso:country":"GB",
    "sg:address":"Snowdrop Cottage, Manningford Bruce",
    "sg:city":"Pewsey",
    "sg:classifiers":[
        {
            "category":"Professional",
            "subcategory":"Accounting & Tax Preparation",
            "type":"Services"
        }
    ],
    "sg:phone":"+44 1980 630910",
    "sg:postcode":"SN9 6JW",
    "sg:province":"Wiltshire",
    "sg:tags":[
        "accountant"
    ],
    "wof:name":"Finalhall Ltd.",
    "wof:placetype":"venue"
},
  "geometry": {"coordinates":[-1.803116,51.328327],"type":"Point"}
}