{
  "type": "Feature",
  "properties": {
    "addr:full":"89 Drayton Avenue, Ealing London Greater London W13 0LE",
    "addr:housenumber":"89",
    "addr:postcode":"w13 0le",
    "addr:street":"Drayton Avenue",
    "iso:country":"GB",
    "sg:address":"89 Drayton Avenue, Ealing",
    "sg:city":"London",
    "sg:classifiers":[
        {
            "category":"Professional",
            "subcategory":"Management & Consulting",
            "type":"Services"
        }
    ],
    "sg:phone":"+44 70 7444 4111",
    "sg:postcode":"W13 0LE",
    "sg:province":"Greater London",
    "sg:tags":[
        "consultant",
        "promotion",
        "direct",
        "sale"
    ],
    "wof:name":"Savannah (U K) Ltd.",
    "wof:placetype":"venue"
},
  "geometry": {"coordinates":[-0.325274,51.513756],"type":"Point"}
}