{
  "type": "Feature",
  "properties": {
    "addr:full":"Chatham & Gillingham Division, Balmoral Rd Gillingham Kent ME7 4PU",
    "addr:postcode":"me7 4pu",
    "addr:street":"Balmoral Rd",
    "iso:country":"GB",
    "sg:address":"Chatham & Gillingham Division, Balmoral Rd",
    "sg:city":"Gillingham",
    "sg:classifiers":[
        {
            "category":"Education",
            "subcategory":"Special Training",
            "type":"Public Place"
        }
    ],
    "sg:phone":"+44 1634 280519",
    "sg:postcode":"ME7 4PU",
    "sg:province":"Kent",
    "sg:tags":[
        "aid",
        "first"
    ],
    "wof:name":"St John Ambulance",
    "wof:placetype":"venue"
},
  "geometry": {"coordinates":[0.54644,51.379768],"type":"Point"}
}