{
  "type": "Feature",
  "properties": {
    "addr:full":"Estate Office Penrith Cumbria CA10 2HG",
    "addr:postcode":"ca10 2hg",
    "addr:street":"Penrith",
    "iso:country":"GB",
    "sg:address":"Estate Office",
    "sg:city":"Penrith",
    "sg:classifiers":[
        {
            "category":"Farming",
            "subcategory":"Farm",
            "type":"Manufacturing & Wholesale Goods"
        }
    ],
    "sg:phone":"+44 1931 712407",
    "sg:postcode":"CA10 2HG",
    "sg:province":"Cumbria",
    "sg:tags":[
        "mixed",
        "crop"
    ],
    "wof:name":"Lowther Park Farms Ltd.",
    "wof:placetype":"venue"
},
  "geometry": {"coordinates":[-2.73419,54.61058],"type":"Point"}
}