{
  "type": "Feature",
  "properties": {
    "addr:full":"Care Of St Georges Hospital Morpeth Northumberland NE61 2NU",
    "addr:postcode":"ne61 2nu",
    "addr:street":"Northumberland",
    "iso:country":"GB",
    "sg:address":"Care Of St Georges Hospital",
    "sg:city":"Morpeth",
    "sg:classifiers":[
        {
            "category":"Home & Garden",
            "subcategory":"Garden Supply",
            "type":"Retail Goods"
        }
    ],
    "sg:phone":"+44 1670 503217",
    "sg:postcode":"NE61 2NU",
    "sg:province":"Northumberland",
    "sg:tags":[
        "nursery",
        "centre"
    ],
    "wof:name":"New Horizons Garden Centre",
    "wof:placetype":"venue"
},
  "geometry": {"coordinates":[-1.69444,55.174858],"type":"Point"}
}