{
  "type": "Feature",
  "properties": {
    "addr:full":"8 Angus Close Banbury Oxfordshire OX16 7UQ",
    "addr:housenumber":"8",
    "addr:postcode":"ox16 7uq",
    "addr:street":"Angus Close",
    "iso:country":"GB",
    "sg:address":"8 Angus Close",
    "sg:city":"Banbury",
    "sg:classifiers":[
        {
            "category":"Professional",
            "subcategory":"Art Services",
            "type":"Services"
        }
    ],
    "sg:phone":"+44 1295 258746",
    "sg:postcode":"OX16 7UQ",
    "sg:province":"Oxfordshire",
    "sg:tags":[
        "photographer"
    ],
    "wof:name":"Curzon Photographic",
    "wof:placetype":"venue"
},
  "geometry": {"coordinates":[-1.358678,52.073826],"type":"Point"}
}