{
  "type": "Feature",
  "properties": {
    "addr:full":"69 Swallow Lane, Golcar Huddersfield West Yorkshire HD7 4NB",
    "addr:housenumber":"69",
    "addr:postcode":"hd7 4nb",
    "addr:street":"Swallow Lane;West",
    "iso:country":"GB",
    "sg:address":"69 Swallow Lane, Golcar",
    "sg:city":"Huddersfield",
    "sg:classifiers":[
        {
            "category":"Building & Trades",
            "subcategory":"Construction",
            "type":"Services"
        }
    ],
    "sg:postcode":"HD7 4NB",
    "sg:province":"West Yorkshire",
    "sg:tags":[
        "roofing"
    ],
    "wof:name":"Hart & Ringrose",
    "wof:placetype":"venue"
},
  "geometry": {"coordinates":[-1.8599179983,53.6408042908],"type":"Point"}
}