{
  "type": "Feature",
  "properties": {
    "iso:country":"GB",
    "sg:address":"Inchmartine, Inchture",
    "sg:city":"Perth",
    "sg:classifiers":[
        {
            "category":"Banks & Credit Unions",
            "subcategory":"Financial Services",
            "type":"Services"
        }
    ],
    "sg:phone":"+44 1828 686740",
    "sg:postcode":"PH14 9QQ",
    "sg:province":"Perth and Kinross",
    "sg:tags":[
        "adviser"
    ],
    "wof:name":"George McConnachie",
    "wof:placetype":"venue"
},
  "geometry": {"coordinates":[-3.168468,56.446461],"type":"Point"}
}