{
  "type": "Feature",
  "properties": {
    "addr:full":"The Old School, School Lane Maidstone Kent ME15 8DU",
    "addr:postcode":"me15 8du",
    "addr:street":"School Lane",
    "iso:country":"GB",
    "sg:address":"The Old School, School Lane",
    "sg:city":"Maidstone",
    "sg:classifiers":[
        {
            "category":"Organizations",
            "subcategory":"Non-profit Organization",
            "type":"Services"
        }
    ],
    "sg:phone":"+44 1622 758643",
    "sg:postcode":"ME15 8DU",
    "sg:province":"Kent",
    "sg:tags":[
        "organisation",
        "voluntary",
        "charity"
    ],
    "wof:name":"British Red Cross",
    "wof:placetype":"venue"
},
  "geometry": {"coordinates":[0.55394,51.25843],"type":"Point"}
}