{
  "type": "Feature",
  "properties": {
    "iso:country":"GB",
    "sg:address":"Tyllwyd, Golden Gro",
    "sg:city":"Carmarthen",
    "sg:classifiers":[
        {
            "category":"Farming",
            "subcategory":"Livestock Farm",
            "type":"Manufacturing & Wholesale Goods"
        }
    ],
    "sg:postcode":"SA32 8NE",
    "sg:province":"Carmarthenshire",
    "sg:tags":[
        "others"
    ],
    "wof:name":"John Owen",
    "wof:placetype":"venue"
},
  "geometry": {"coordinates":[-4.062019825,51.8518714905],"type":"Point"}
}