{
  "type": "Feature",
  "properties": {
    "addr:full":"Osney Mead Trading Estate Oxford Oxfordshire OX2 0ES",
    "addr:postcode":"ox2 0es",
    "addr:street":"Osney;Trading Estate",
    "iso:country":"GB",
    "sg:address":"Osney Mead Trading Estate",
    "sg:city":"Oxford",
    "sg:classifiers":[
        {
            "category":"Professional",
            "subcategory":"Engineering",
            "type":"Services"
        }
    ],
    "sg:phone":"+44 1865 240696",
    "sg:postcode":"OX2 0ES",
    "sg:province":"Oxfordshire",
    "sg:tags":[
        "precision",
        "engineer"
    ],
    "wof:name":"Teknox",
    "wof:placetype":"venue"
},
  "geometry": {"coordinates":[-1.270274,51.746639],"type":"Point"}
}