{
  "type": "Feature",
  "properties": {
    "iso:country":"GB",
    "sg:address":"63b Clerkenwell Road",
    "sg:city":"London",
    "sg:classifiers":[
        {
            "category":"Retail",
            "subcategory":"Laundry & Dry Cleaning",
            "type":"Services"
        },
        {
            "category":"Bars & Pubs",
            "subcategory":"Nightclub",
            "type":"Food & Drink"
        }
    ],
    "sg:phone":"+44 20 7250 3409",
    "sg:postcode":"EC1M 5NP",
    "sg:province":"Greater London",
    "sg:tags":[
        "club",
        "alteration",
        "night"
    ],
    "wof:name":"Turnmills",
    "wof:placetype":"venue"
},
  "geometry": {"coordinates":[-0.105182,51.522202],"type":"Point"}
}