{
  "type": "Feature",
  "properties": {
    "iso:country":"GB",
    "sg:address":"248 Washwood Heath Road, Washwood Heath",
    "sg:city":"Birmingham",
    "sg:classifiers":[
        {
            "category":"Shopping",
            "subcategory":"Stationery & Office Supplies",
            "type":"Retail Goods"
        }
    ],
    "sg:phone":"+44 121 327 2130",
    "sg:postcode":"B8 1RJ",
    "sg:province":"West Midlands",
    "wof:name":"Washwood Heath Post Office",
    "wof:placetype":"venue"
},
  "geometry": {"coordinates":[-1.851222,52.496277],"type":"Point"}
}