{
  "type": "Feature",
  "properties": {
    "addr:full":"Cinderhill Trading Estate, Weston Coyney Road Stoke-on-trent Staffordshire ST3 5JU",
    "addr:postcode":"st3 5ju",
    "addr:street":"Coyney Road",
    "iso:country":"GB",
    "sg:address":"Cinderhill Trading Estate, Weston Coyney Road",
    "sg:city":"Stoke-on-trent",
    "sg:classifiers":[
        {
            "category":"Professional",
            "subcategory":"Engineering",
            "type":"Services"
        }
    ],
    "sg:phone":"+44 1782 329348",
    "sg:postcode":"ST3 5JU",
    "sg:province":"Staffordshire",
    "wof:name":"Ferropol Engineering",
    "wof:placetype":"venue"
},
  "geometry": {"coordinates":[-2.1125259399,52.9883270264],"type":"Point"}
}