{
  "type": "Feature",
  "properties": {
    "addr:full":"Church Hall, Church La, Godmanstone Dorchester Dorset DT2 7AQ",
    "addr:postcode":"dt2 7aq",
    "addr:street":"La Godmanstone",
    "iso:country":"GB",
    "sg:address":"Church Hall, Church La, Godmanstone",
    "sg:city":"Dorchester",
    "sg:classifiers":[
        {
            "category":"Farming",
            "subcategory":"Nursery",
            "type":"Manufacturing & Wholesale Goods"
        }
    ],
    "sg:postcode":"DT2 7AQ",
    "sg:province":"Dorset",
    "sg:tags":[
        "creche"
    ],
    "wof:name":"Three Valleys Pre School Nursery",
    "wof:placetype":"venue"
},
  "geometry": {"coordinates":[-2.4749538898,50.7718887329],"type":"Point"}
}