{
  "type": "Feature",
  "properties": {
    "addr:full":"44 Torbay Rd Harrow Greater London HA2 9QH",
    "addr:housenumber":"44",
    "addr:postcode":"ha2 9qh",
    "addr:street":"Torbay Rd",
    "iso:country":"GB",
    "sg:address":"44 Torbay Rd",
    "sg:city":"Harrow",
    "sg:classifiers":[
        {
            "category":"Building & Trades",
            "subcategory":"Plumbing",
            "type":"Services"
        }
    ],
    "sg:phone":"+44 20 8864 6534",
    "sg:postcode":"HA2 9QH",
    "sg:province":"Greater London",
    "sg:tags":[
        "heating"
    ],
    "wof:name":"J W Langston",
    "wof:placetype":"venue"
},
  "geometry": {"coordinates":[-0.381329,51.56432],"type":"Point"}
}