{
  "type": "Feature",
  "properties": {
    "iso:country":"GB",
    "sg:address":"Outney Common",
    "sg:city":"Bungay",
    "sg:classifiers":[
        {
            "category":"Sports & Exercise",
            "subcategory":"Golf",
            "type":"Entertainment"
        }
    ],
    "sg:phone":"+44 1986 892337",
    "sg:postcode":"NR35 1DS",
    "sg:province":"Norfolk",
    "sg:tags":[
        "club",
        "course"
    ],
    "wof:name":"Bungay & Waveney Valley Golf Club",
    "wof:placetype":"venue"
},
  "geometry": {"coordinates":[1.443709,52.44997],"type":"Point"}
}