{
  "type": "Feature",
  "properties": {
    "iso:country":"GB",
    "sg:address":"Darkes Court Cotts, Polyphant",
    "sg:city":"Launceston",
    "sg:classifiers":[
        {
            "category":"Travel",
            "subcategory":"Hotels & Motels",
            "type":"Entertainment"
        }
    ],
    "sg:postcode":"PL15 7PS",
    "sg:province":"Cornwall",
    "sg:tags":[
        "house",
        "guest"
    ],
    "wof:name":"Darkes Court Cottages",
    "wof:placetype":"venue"
},
  "geometry": {"coordinates":[-4.457619,50.611946],"type":"Point"}
}