{
  "type": "Feature",
  "properties": {
    "addr:full":"66 Eversholt Street London Greater London NW1 1DA",
    "addr:housenumber":"66",
    "addr:postcode":"nw1 1da",
    "addr:street":"Eversholt Street",
    "iso:country":"GB",
    "sg:address":"66 Eversholt Street",
    "sg:city":"London",
    "sg:classifiers":[
        {
            "category":"Cafe",
            "type":"Food & Drink"
        }
    ],
    "sg:phone":"+44 20 7387 0262",
    "sg:postcode":"NW1 1DA",
    "sg:province":"Greater London",
    "sg:tags":[
        "tea",
        "room"
    ],
    "wof:name":"Double Six Cafe",
    "wof:placetype":"venue"
},
  "geometry": {"coordinates":[-0.13299,51.529552],"type":"Point"}
}