{
  "type": "Feature",
  "properties": {
    "iso:country":"GB",
    "sg:address":"St Neots Rd",
    "sg:city":"Sandy",
    "sg:classifiers":[
        {
            "category":"Place Of Worship",
            "type":"Public Place"
        }
    ],
    "sg:phone":"+44 1767 312156",
    "sg:postcode":"SG19 1BU",
    "sg:province":"Bedfordshire",
    "wof:name":"Sandy Methodist Church",
    "wof:placetype":"venue"
},
  "geometry": {"coordinates":[-0.297748,52.137524],"type":"Point"}
}