{
  "type": "Feature",
  "properties": {
    "addr:full":"8 Canterbury Parade, South Road South Ockendon Essex RM15 6NH",
    "addr:housenumber":"8",
    "addr:postcode":"rm15 6nh",
    "addr:street":"Canterbury Parade South Road",
    "iso:country":"GB",
    "sg:address":"8 Canterbury Parade, South Road",
    "sg:city":"South Ockendon",
    "sg:classifiers":[
        {
            "category":"Food & Beverages",
            "subcategory":"Bakery",
            "type":"Retail Goods"
        }
    ],
    "sg:phone":"+44 1708 851800",
    "sg:postcode":"RM15 6NH",
    "sg:province":"Essex",
    "sg:tags":[
        "confectionery"
    ],
    "wof:name":"South Ockendon Bakery",
    "wof:placetype":"venue"
},
  "geometry": {"coordinates":[0.2836500108,51.5024757385],"type":"Point"}
}