{
  "type": "Feature",
  "properties": {
    "iso:country":"GB",
    "sg:address":"2 High Greave Place",
    "sg:city":"Rotherham",
    "sg:classifiers":[
        {
            "category":"Social Services",
            "subcategory":"Adult Care",
            "type":"Services"
        },
        {
            "category":"Government",
            "subcategory":"Office",
            "type":"Public Place"
        }
    ],
    "sg:phone":"+44 1709 850644",
    "sg:postcode":"S65 3PH",
    "sg:province":"South Yorkshire",
    "sg:tags":[
        "housing",
        "local",
        "sheltered"
    ],
    "wof:name":"High Greave Pl Bungalows",
    "wof:placetype":"venue"
},
  "geometry": {"coordinates":[-1.3207019567,53.4354286194],"type":"Point"}
}