{
  "type": "Feature",
  "properties": {
    "iso:country":"GB",
    "sg:address":"162 Queen Margaret Drive",
    "sg:city":"Glasgow",
    "sg:classifiers":[
        {
            "category":"Autos & Motor Vehicles",
            "subcategory":"Fuel & Gas Station",
            "type":"Retail Goods"
        }
    ],
    "sg:phone":"+44 141 948 0500",
    "sg:postcode":"G20 8NX",
    "sg:province":"Glasgow City",
    "sg:tags":[
        "hr",
        "petrol"
    ],
    "wof:name":"Shell U K Ltd.",
    "wof:placetype":"venue"
},
  "geometry": {"coordinates":[-4.283109,55.881535],"type":"Point"}
}