{
  "type": "Feature",
  "properties": {
    "addr:full":"9 Bar Lane Nottingham Nottinghamshire NG6 0HT",
    "addr:housenumber":"9",
    "addr:postcode":"ng6 0ht",
    "addr:street":"Bar Lane",
    "iso:country":"GB",
    "sg:address":"9 Bar Lane",
    "sg:city":"Nottingham",
    "sg:classifiers":[
        {
            "category":"Autos & Motor Vehicles",
            "subcategory":"Auto Supplies",
            "type":"Retail Goods"
        },
        {
            "category":"Retail",
            "subcategory":"Auto Repair",
            "type":"Services"
        }
    ],
    "sg:phone":"+44 115 979 0950",
    "sg:postcode":"NG6 0HT",
    "sg:province":"Nottinghamshire",
    "sg:tags":[
        "windscreen",
        "replacement"
    ],
    "wof:name":"The Nottingham Windscreen Co.",
    "wof:placetype":"venue"
},
  "geometry": {"coordinates":[-1.1907769442,52.9780769348],"type":"Point"}
}