{
  "type": "Feature",
  "properties": {
    "addr:full":"Unit 9 Pitt Street, Denton Manchester Greater Manchester M34 6DD",
    "addr:housenumber":"unit 9",
    "addr:postcode":"m34 6dd",
    "addr:street":"Pitt Street",
    "iso:country":"GB",
    "sg:address":"Unit 9 Pitt Street, Denton",
    "sg:city":"Manchester",
    "sg:classifiers":[
        {
            "category":"Manufacturing",
            "subcategory":"Petroleum Products",
            "type":"Manufacturing & Wholesale Goods"
        }
    ],
    "sg:phone":"+44 161 336 0211",
    "sg:postcode":"M34 6DD",
    "sg:province":"Greater Manchester",
    "sg:tags":[
        "double",
        "glazing"
    ],
    "wof:name":"Richkay Windows",
    "wof:placetype":"venue"
},
  "geometry": {"coordinates":[-2.112344,53.454109],"type":"Point"}
}