{
  "type": "Feature",
  "properties": {
    "iso:country":"GB",
    "sg:address":"37 Broomfield Road",
    "sg:city":"Chelmsford",
    "sg:classifiers":[
        {
            "category":"Shopping",
            "subcategory":"Florist",
            "type":"Retail Goods"
        }
    ],
    "sg:phone":"+44 1245 263113",
    "sg:postcode":"CM1 1SY",
    "sg:province":"Essex",
    "wof:name":"A & B Florists",
    "wof:placetype":"venue"
},
  "geometry": {"coordinates":[0.465972,51.738441],"type":"Point"}
}