{
  "type": "Feature",
  "properties": {
    "iso:country":"GB",
    "sg:address":"19 Seaham Street, Silksworth",
    "sg:city":"Sunderland",
    "sg:classifiers":[
        {
            "category":"Building & Trades",
            "subcategory":"Construction",
            "type":"Services"
        }
    ],
    "sg:postcode":"SR3 1EX",
    "sg:province":"Tyne and Wear",
    "sg:tags":[
        "roofing"
    ],
    "wof:name":"Thomas Fowle",
    "wof:placetype":"venue"
},
  "geometry": {"coordinates":[-1.405295,54.874489],"type":"Point"}
}