{
  "type": "Feature",
  "properties": {
    "addr:full":"Flat 3 The Mews, Wootton Hall, Wootton Wawen Solihull Warwickshire B95 6EE",
    "addr:postcode":"b95 6ee",
    "addr:street":"The Mews Wootton Hall",
    "iso:country":"GB",
    "sg:address":"Flat 3 The Mews, Wootton Hall, Wootton Wawen",
    "sg:city":"Solihull",
    "sg:classifiers":[
        {
            "category":"Professional",
            "subcategory":"Art Services",
            "type":"Services"
        }
    ],
    "sg:phone":"+44 1564 793467",
    "sg:postcode":"B95 6EE",
    "sg:province":"Warwickshire",
    "sg:tags":[
        "picture",
        "restoration",
        "cleaning"
    ],
    "wof:name":"Studio Restorations",
    "wof:placetype":"venue"
},
  "geometry": {"coordinates":[-1.7774089575,52.2667312622],"type":"Point"}
}