{
  "type": "Feature",
  "properties": {
    "addr:full":"Ferndale, Broadstone Lane, Hardington Manderville Yeovil Dorset BA22 9PR",
    "addr:postcode":"ba22 9pr",
    "addr:street":"Broadstone Lane;Manderville",
    "iso:country":"GB",
    "sg:address":"Ferndale, Broadstone Lane, Hardington Manderville",
    "sg:city":"Yeovil",
    "sg:classifiers":[
        {
            "category":"Shopping",
            "subcategory":"Optician",
            "type":"Retail Goods"
        },
        {
            "category":"Professional",
            "subcategory":"Engineering",
            "type":"Services"
        }
    ],
    "sg:phone":"+44 1935 863468",
    "sg:postcode":"BA22 9PR",
    "sg:province":"Dorset",
    "sg:tags":[
        "engineer",
        "electrical",
        "contractor"
    ],
    "wof:name":"A R Hawkins",
    "wof:placetype":"venue"
},
  "geometry": {"coordinates":[-2.6986150742,50.905166626],"type":"Point"}
}