{
  "type": "Feature",
  "properties": {
    "addr:full":"2 Church Cres, Langford Biggleswade Bedfordshire SG18 9QE",
    "addr:housenumber":"2",
    "addr:postcode":"sg18 9qe",
    "addr:street":"Church Cres",
    "iso:country":"GB",
    "sg:address":"2 Church Cres, Langford",
    "sg:city":"Biggleswade",
    "sg:classifiers":[
        {
            "category":"Home & Garden",
            "subcategory":"Garden Supply",
            "type":"Retail Goods"
        }
    ],
    "sg:postcode":"SG18 9QE",
    "sg:province":"Bedfordshire",
    "sg:tags":[
        "fertiliser"
    ],
    "wof:name":"Agtec Ltd",
    "wof:placetype":"venue"
},
  "geometry": {"coordinates":[-0.273216,52.057873],"type":"Point"}
}