{
  "type": "Feature",
  "properties": {
    "addr:full":"Chute Ho, Lower Church St Basingstoke Hampshire RG21 7QT",
    "addr:postcode":"rg21 7qt",
    "addr:street":"Chute;Lower Church St",
    "iso:country":"GB",
    "sg:address":"Chute Ho, Lower Church St",
    "sg:city":"Basingstoke",
    "sg:classifiers":[
        {
            "category":"Professional",
            "subcategory":"Lawyer & Legal Services",
            "type":"Services"
        }
    ],
    "sg:phone":"+44 1256 324364",
    "sg:postcode":"RG21 7QT",
    "sg:province":"Hampshire",
    "sg:tags":[
        "advice",
        "counselling"
    ],
    "wof:name":"Relate",
    "wof:placetype":"venue"
},
  "geometry": {"coordinates":[-1.083089,51.262444],"type":"Point"}
}