{
  "type": "Feature",
  "properties": {
    "iso:country":"GB",
    "sg:address":"Cockspur Street, Birchmoor",
    "sg:city":"Tamworth",
    "sg:classifiers":[
        {
            "category":"Bars & Pubs",
            "type":"Food & Drink"
        },
        {
            "category":"Community Center",
            "subcategory":"Social",
            "type":"Public Place"
        }
    ],
    "sg:phone":"+44 1827 331254",
    "sg:postcode":"B78 1AH",
    "sg:province":"Staffordshire",
    "sg:tags":[
        "pubs",
        "house",
        "inn",
        "activity"
    ],
    "wof:name":"The Gamecock Inn",
    "wof:placetype":"venue"
},
  "geometry": {"coordinates":[-1.628824,52.610966],"type":"Point"}
}