{
  "type": "Feature",
  "properties": {
    "iso:country":"GB",
    "sg:address":"34a Stockport Rd",
    "sg:city":"Cheadle",
    "sg:classifiers":[
        {
            "category":"Fast Food",
            "type":"Food & Drink"
        }
    ],
    "sg:phone":"+44 161 428 2883",
    "sg:postcode":"SK8 2AA",
    "sg:province":"Cheshire",
    "sg:tags":[
        "away",
        "take"
    ],
    "wof:name":"2 Miss Muffins",
    "wof:placetype":"venue"
},
  "geometry": {"coordinates":[-2.210217,53.39513],"type":"Point"}
}