{
  "type": "Feature",
  "properties": {
    "addr:full":"Unit A 3 Sovereign Park Indust Est Market Harborough Leicestershire LE16 9EG",
    "addr:housenumber":"unit a 3",
    "addr:postcode":"le16 9eg",
    "addr:street":"Sovereign Park Indust Est",
    "iso:country":"GB",
    "sg:address":"Unit A 3 Sovereign Park Indust Est",
    "sg:city":"Market Harborough",
    "sg:classifiers":[
        {
            "category":"Professional",
            "subcategory":"Business Services",
            "type":"Services"
        }
    ],
    "sg:phone":"+44 1858 461188",
    "sg:postcode":"LE16 9EG",
    "sg:province":"Leicestershire",
    "sg:tags":[
        "import",
        "export",
        "agent"
    ],
    "wof:name":"C K (UK) Ltd",
    "wof:placetype":"venue"
},
  "geometry": {"coordinates":[-0.9225789905,52.4793968201],"type":"Point"}
}