{
  "type": "Feature",
  "properties": {
    "addr:full":"273 High Road Benfleet Essex SS7 5HA",
    "addr:housenumber":"273",
    "addr:postcode":"ss7 5ha",
    "addr:street":"High Road",
    "iso:country":"GB",
    "sg:address":"273 High Road",
    "sg:city":"Benfleet",
    "sg:classifiers":[
        {
            "category":"Banks & Credit Unions",
            "subcategory":"Bank",
            "type":"Services"
        }
    ],
    "sg:phone":"+44 1268 751050",
    "sg:postcode":"SS7 5HA",
    "sg:province":"Essex",
    "wof:name":"Woolwich Building Society",
    "wof:placetype":"venue"
},
  "geometry": {"coordinates":[0.5595499873,51.5536003113],"type":"Point"}
}