{
  "type": "Feature",
  "properties": {
    "addr:full":"2 Sutherland Avenue London Greater London W9 2HQ",
    "addr:housenumber":"2",
    "addr:postcode":"w9 2hq",
    "addr:street":"Sutherland Avenue",
    "iso:country":"GB",
    "sg:address":"2 Sutherland Avenue",
    "sg:city":"London",
    "sg:classifiers":[
        {
            "category":"Government",
            "subcategory":"Post Office",
            "type":"Public Place"
        }
    ],
    "sg:phone":"+44 20 7286 6514",
    "sg:postcode":"W9 2HQ",
    "sg:province":"Greater London",
    "wof:name":"Sutherland Avenue Post Office",
    "wof:placetype":"venue"
},
  "geometry": {"coordinates":[-0.194552,51.52306],"type":"Point"}
}