{
  "type": "Feature",
  "properties": {
    "iso:country":"GB",
    "sg:address":"1 Main Street, Fleckney",
    "sg:city":"Leicester",
    "sg:classifiers":[
        {
            "category":"Food & Beverages",
            "subcategory":"Meat & Fish",
            "type":"Retail Goods"
        }
    ],
    "sg:phone":"+44 116 240 2407",
    "sg:postcode":"LE8 8AP",
    "sg:province":"Leicestershire",
    "sg:tags":[
        "butcher"
    ],
    "wof:name":"Williams Butchers",
    "wof:placetype":"venue"
},
  "geometry": {"coordinates":[-1.044416,52.535297],"type":"Point"}
}