{
  "type": "Feature",
  "properties": {
    "iso:country":"GB",
    "sg:address":"Chapel Ho, Garston Old Rd",
    "sg:city":"Liverpool",
    "sg:classifiers":[
        {
            "category":"Place Of Worship",
            "type":"Public Place"
        }
    ],
    "sg:phone":"+44 151 427 3672",
    "sg:postcode":"L19 1QL",
    "sg:province":"Merseyside",
    "wof:name":"Island Road Methodist Church",
    "wof:placetype":"venue"
},
  "geometry": {"coordinates":[-2.898936,53.357441],"type":"Point"}
}