{
  "type": "Feature",
  "properties": {
    "addr:full":"Blandford Street Newcastle-upon-tyne Tyne and Wear NE1 4HW",
    "addr:postcode":"ne1 4hw",
    "addr:street":"Blandford Street",
    "iso:country":"GB",
    "sg:address":"Blandford Street",
    "sg:city":"Newcastle-upon-tyne",
    "sg:classifiers":[
        {
            "category":"Shopping",
            "subcategory":"Clothing, Apparel, & Fashions",
            "type":"Retail Goods"
        }
    ],
    "sg:phone":"+44 191 261 2060",
    "sg:postcode":"NE1 4HW",
    "sg:province":"Tyne and Wear",
    "sg:tags":[
        "clothing"
    ],
    "wof:name":"Zebu Clothing Co. Ltd.",
    "wof:placetype":"venue"
},
  "geometry": {"coordinates":[-1.6241439581,54.9683685303],"type":"Point"}
}