{
  "type": "Feature",
  "properties": {
    "addr:full":"92-96 Birkenhead Rd Wallasey Merseyside CH44 7BZ",
    "addr:housenumber":"92-96",
    "addr:postcode":"ch44 7bz",
    "addr:street":"Birkenhead Rd",
    "iso:country":"GB",
    "sg:address":"92-96 Birkenhead Rd",
    "sg:city":"Wallasey",
    "sg:classifiers":[
        {
            "category":"Wholesale",
            "subcategory":"Scrap",
            "type":"Manufacturing & Wholesale Goods"
        }
    ],
    "sg:phone":"+44 151 639 2727",
    "sg:postcode":"CH44 7BZ",
    "sg:province":"Merseyside",
    "sg:tags":[
        "car",
        "breaker",
        "dismantlers"
    ],
    "wof:name":"Wallasey Car Spares",
    "wof:placetype":"venue"
},
  "geometry": {"coordinates":[-3.019687891,53.406829834],"type":"Point"}
}