{
  "type": "Feature",
  "properties": {
    "addr:full":"6 Aston Court, Kingsland Grange, Woolston Warrington Cheshire WA1 4SG",
    "addr:housenumber":"6",
    "addr:postcode":"wa1 4sg",
    "addr:street":"Aston Court",
    "iso:country":"GB",
    "sg:address":"6 Aston Court, Kingsland Grange, Woolston",
    "sg:city":"Warrington",
    "sg:classifiers":[
        {
            "category":"Professional",
            "subcategory":"Art Services",
            "type":"Services"
        }
    ],
    "sg:phone":"+44 1925 828222",
    "sg:postcode":"WA1 4SG",
    "sg:province":"Cheshire",
    "sg:tags":[
        "photographer"
    ],
    "wof:name":"Photo-Me International",
    "wof:placetype":"venue"
},
  "geometry": {"coordinates":[-2.537629,53.407417],"type":"Point"}
}