{
  "type": "Feature",
  "properties": {
    "addr:full":"30a Braces Lane Bromsgrove Worcestershire B60 1DY",
    "addr:housenumber":"30a",
    "addr:postcode":"b60 1dy",
    "addr:street":"Braces Lane",
    "iso:country":"GB",
    "sg:address":"30a Braces Lane",
    "sg:city":"Bromsgrove",
    "sg:classifiers":[
        {
            "category":"Banks & Credit Unions",
            "subcategory":"Financial Services",
            "type":"Services"
        }
    ],
    "sg:phone":"+44 121 445 6363",
    "sg:postcode":"B60 1DY",
    "sg:province":"Worcestershire",
    "sg:tags":[
        "consultant"
    ],
    "wof:name":"M C Independent Financial Services",
    "wof:placetype":"venue"
},
  "geometry": {"coordinates":[-2.042783,52.365795],"type":"Point"}
}