{
  "type": "Feature",
  "properties": {
    "iso:country":"GB",
    "sg:address":"146-152 West End Lane",
    "sg:city":"Kilburn",
    "sg:classifiers":[
        {
            "category":"Retail",
            "subcategory":"Storage",
            "type":"Services"
        }
    ],
    "sg:phone":"+44 20 7625 1313",
    "sg:postcode":"NW6 1SD",
    "sg:province":"Greater London",
    "sg:tags":[
        "household",
        "removal"
    ],
    "wof:name":"T.B.T Van Hire",
    "wof:placetype":"venue"
},
  "geometry": {"coordinates":[-0.190789,51.547825],"type":"Point"}
}