{
  "type": "Feature",
  "properties": {
    "iso:country":"GB",
    "sg:address":"274 Woodstock Road",
    "sg:city":"Oxford",
    "sg:classifiers":[
        {
            "category":"Shopping",
            "subcategory":"News",
            "type":"Retail Goods"
        }
    ],
    "sg:phone":"+44 1865 558829",
    "sg:postcode":"OX2 7NW",
    "sg:province":"Oxfordshire",
    "sg:tags":[
        "newsagent"
    ],
    "wof:name":"Summertown Newsagency",
    "wof:placetype":"venue"
},
  "geometry": {"coordinates":[-1.270754,51.778393],"type":"Point"}
}