{
  "type": "Feature",
  "properties": {
    "addr:full":"113 St Georges Terrace, Jesmond Newcastle-upon-tyne Tyne and Wear NE2 2DN",
    "addr:housenumber":"113",
    "addr:postcode":"ne2 2dn",
    "addr:street":"St Georges Terrace",
    "iso:country":"GB",
    "sg:address":"113 St Georges Terrace, Jesmond",
    "sg:city":"Newcastle-upon-tyne",
    "sg:classifiers":[
        {
            "category":"Health Services",
            "subcategory":"Optometrist",
            "type":"Services"
        },
        {
            "category":"Shopping",
            "subcategory":"Optician",
            "type":"Retail Goods"
        }
    ],
    "sg:phone":"+44 191 281 8810",
    "sg:postcode":"NE2 2DN",
    "sg:province":"Tyne and Wear",
    "sg:tags":[
        "ophthalmic"
    ],
    "wof:name":"Long & Pickard",
    "wof:placetype":"venue"
},
  "geometry": {"coordinates":[-1.6058000326,54.9952087402],"type":"Point"}
}