{
  "type": "Feature",
  "properties": {
    "iso:country":"GB",
    "sg:address":"74 Norman Road",
    "sg:city":"St Leonards-on-sea",
    "sg:classifiers":[
        {
            "category":"Shopping",
            "subcategory":"Discount & Variety Stores",
            "type":"Retail Goods"
        }
    ],
    "sg:phone":"+44 1424 446101",
    "sg:postcode":"TN38 0EJ",
    "sg:province":"East Sussex",
    "sg:tags":[
        "shop",
        "model"
    ],
    "wof:name":"Train & Car Man",
    "wof:placetype":"venue"
},
  "geometry": {"coordinates":[0.55798,50.851688],"type":"Point"}
}