{
  "type": "Feature",
  "properties": {
    "iso:country":"GB",
    "sg:address":"Principal House, 6 Chertsey Rd",
    "sg:city":"Woking",
    "sg:classifiers":[
        {
            "category":"Real Estate",
            "subcategory":"Real Estate Operator",
            "type":"Services"
        }
    ],
    "sg:phone":"+44 1483 762626",
    "sg:postcode":"GU21 5AB",
    "sg:province":"Surrey",
    "sg:tags":[
        "letting",
        "agent"
    ],
    "wof:name":"Principal Residential Letting Agents",
    "wof:placetype":"venue"
},
  "geometry": {"coordinates":[-0.556946,51.319237],"type":"Point"}
}