{
  "type": "Feature",
  "properties": {
    "addr:full":"49 Elizabeth Street London Greater London SW1W 9PP",
    "addr:housenumber":"49",
    "addr:postcode":"sw1w 9pp",
    "addr:street":"Elizabeth Street",
    "iso:country":"GB",
    "sg:address":"49 Elizabeth Street",
    "sg:city":"London",
    "sg:classifiers":[
        {
            "category":"Restaurant",
            "type":"Food & Drink"
        }
    ],
    "sg:phone":"+44 20 7730 0074",
    "sg:postcode":"SW1W 9PP",
    "sg:province":"Greater London",
    "sg:tags":[
        "italian"
    ],
    "wof:name":"Oliveto",
    "wof:placetype":"venue"
},
  "geometry": {"coordinates":[-0.150729,51.493389],"type":"Point"}
}