{
  "type": "Feature",
  "properties": {
    "iso:country":"GB",
    "sg:address":"Ivel Road",
    "sg:city":"Shefford",
    "sg:classifiers":[
        {
            "category":"Professional",
            "type":"Services"
        }
    ],
    "sg:phone":"+44 1462 857955",
    "sg:postcode":"SG17 5JU",
    "sg:province":"Bedfordshire",
    "sg:tags":[
        "repair",
        "tech",
        "maintenance"
    ],
    "wof:name":"D M S Systems Ltd.",
    "wof:placetype":"venue"
},
  "geometry": {"coordinates":[-0.331114,52.037449],"type":"Point"}
}