{
  "type": "Feature",
  "properties": {
    "addr:full":"253 Henleaze Rd Bristol City of Bristol BS9 4NQ",
    "addr:housenumber":"253",
    "addr:postcode":"bs9 4nq",
    "addr:street":"Henleaze Rd",
    "iso:country":"GB",
    "sg:address":"253 Henleaze Rd",
    "sg:city":"Bristol",
    "sg:classifiers":[
        {
            "category":"Professional",
            "subcategory":"Accounting & Tax Preparation",
            "type":"Services"
        }
    ],
    "sg:phone":"+44 117 962 2721",
    "sg:postcode":"BS9 4NQ",
    "sg:province":"City of Bristol",
    "sg:tags":[
        "consultant"
    ],
    "wof:name":"Nichols,I,",
    "wof:placetype":"venue"
},
  "geometry": {"coordinates":[-2.609549,51.486889],"type":"Point"}
}