{
  "type": "Feature",
  "properties": {
    "iso:country":"GB",
    "sg:address":"Dewey House, North Row",
    "sg:city":"Warminster",
    "sg:classifiers":[
        {
            "category":"Professional",
            "subcategory":"Employment Agencies",
            "type":"Services"
        }
    ],
    "sg:phone":"+44 1985 217342",
    "sg:postcode":"BA12 9AD",
    "sg:province":"Somerset",
    "sg:tags":[
        "consultant"
    ],
    "wof:name":"Warminster Job Club",
    "wof:placetype":"venue"
},
  "geometry": {"coordinates":[-2.181025,51.20594],"type":"Point"}
}