{
  "type": "Feature",
  "properties": {
    "iso:country":"GB",
    "sg:address":"Cleobury Road",
    "sg:city":"Bewdley",
    "sg:classifiers":[
        {
            "category":"Recreation",
            "subcategory":"Dog Park",
            "type":"Entertainment"
        }
    ],
    "sg:postcode":"DY12 2QJ",
    "sg:province":"Shropshire",
    "wof:name":"Jayn Court Kennels",
    "wof:placetype":"venue"
},
  "geometry": {"coordinates":[-2.3270640373,52.3751945496],"type":"Point"}
}