{
  "type": "Feature",
  "properties": {
    "addr:full":"2 Westgate Hill Pembroke Pembrokeshire SA71 4LB",
    "addr:housenumber":"2",
    "addr:postcode":"sa71 4lb",
    "addr:street":"Westgate Hill",
    "iso:country":"GB",
    "sg:address":"2 Westgate Hill",
    "sg:city":"Pembroke",
    "sg:classifiers":[
        {
            "category":"Bars & Pubs",
            "type":"Food & Drink"
        }
    ],
    "sg:phone":"+44 1646 682223",
    "sg:postcode":"SA71 4LB",
    "sg:province":"Pembrokeshire",
    "sg:tags":[
        "pubs",
        "inn"
    ],
    "wof:name":"Cromwell's Tavern",
    "wof:placetype":"venue"
},
  "geometry": {"coordinates":[-4.918969,51.676136],"type":"Point"}
}