{
  "type": "Feature",
  "properties": {
    "addr:full":"Crompton Road Stevenage Hertfordshire SG1 2EE",
    "addr:postcode":"sg1 2ee",
    "addr:street":"Crompton Road",
    "iso:country":"GB",
    "sg:address":"Crompton Road",
    "sg:city":"Stevenage",
    "sg:classifiers":[
        {
            "category":"Home & Garden",
            "subcategory":"Hardware",
            "type":"Retail Goods"
        },
        {
            "category":"Government",
            "subcategory":"Post Office",
            "type":"Public Place"
        }
    ],
    "sg:phone":"+44 1438 741542",
    "sg:postcode":"SG1 2EE",
    "sg:province":"Hertfordshire",
    "sg:tags":[
        "sale",
        "generator"
    ],
    "wof:name":"S L D Genlite Ltd",
    "wof:placetype":"venue"
},
  "geometry": {"coordinates":[-0.2211399972,51.9060592651],"type":"Point"}
}