{
  "type": "Feature",
  "properties": {
    "iso:country":"GB",
    "sg:address":"Friddygog",
    "sg:city":"Corwen",
    "sg:classifiers":[
        {
            "category":"Home & Garden",
            "subcategory":"Garden Supply",
            "type":"Retail Goods"
        }
    ],
    "sg:postcode":"LL21 9RP",
    "sg:province":"Conwy",
    "sg:tags":[
        "nursery",
        "centre"
    ],
    "wof:name":"David G Watkins",
    "wof:placetype":"venue"
},
  "geometry": {"coordinates":[-3.3937330246,53.0138092041],"type":"Point"}
}