{
  "type": "Feature",
  "properties": {
    "iso:country":"GB",
    "sg:address":"Colinshiel View, Armadale",
    "sg:city":"Bathgate",
    "sg:classifiers":[
        {
            "category":"Wholesale",
            "subcategory":"Scrap",
            "type":"Manufacturing & Wholesale Goods"
        },
        {
            "category":"Wholesale",
            "subcategory":"Auto Parts",
            "type":"Manufacturing & Wholesale Goods"
        }
    ],
    "sg:phone":"+44 1501 731876",
    "sg:postcode":"EH48 3QE",
    "sg:province":"West Lothian",
    "sg:tags":[
        "car",
        "breaker",
        "dismantlers"
    ],
    "wof:name":"Campbells Auto Salvage",
    "wof:placetype":"venue"
},
  "geometry": {"coordinates":[-3.697466,55.902122],"type":"Point"}
}