{
  "type": "Feature",
  "properties": {
    "addr:full":"12 Godstone Road Kenley Surrey CR8 5JE",
    "addr:housenumber":"12",
    "addr:postcode":"cr8 5je",
    "addr:street":"Godstone Road",
    "iso:country":"GB",
    "sg:address":"12 Godstone Road",
    "sg:city":"Kenley",
    "sg:classifiers":[
        {
            "category":"Shopping",
            "subcategory":"Pharmacy",
            "type":"Retail Goods"
        }
    ],
    "sg:phone":"+44 20 8660 1970",
    "sg:postcode":"CR8 5JE",
    "sg:province":"Surrey",
    "sg:tags":[
        "pharmacist",
        "dispensing",
        "chemist"
    ],
    "wof:name":"Kenley Pharmacy",
    "wof:placetype":"venue"
},
  "geometry": {"coordinates":[-0.1074599996,51.3289833069],"type":"Point"}
}