{
  "type": "Feature",
  "properties": {
    "iso:country":"GB",
    "sg:address":"224-226 High Street, Dovercourt",
    "sg:city":"Harwich",
    "sg:classifiers":[
        {
            "category":"Shopping",
            "subcategory":"Pharmacy",
            "type":"Retail Goods"
        }
    ],
    "sg:phone":"+44 1255 503508",
    "sg:postcode":"CO12 3AJ",
    "sg:province":"Essex",
    "sg:tags":[
        "pharmacist",
        "chemist"
    ],
    "wof:name":"Boots the Chemists Ltd.",
    "wof:placetype":"venue"
},
  "geometry": {"coordinates":[1.285515,51.938747],"type":"Point"}
}