{
  "type": "Feature",
  "properties": {
    "addr:full":"4 Tynedale Mews, Market Place Corbridge Northumberland NE45 5AW",
    "addr:housenumber":"4",
    "addr:postcode":"ne45 5aw",
    "addr:street":"Tynedale Mews Market Place;Northumberland",
    "iso:country":"GB",
    "sg:address":"4 Tynedale Mews, Market Place",
    "sg:city":"Corbridge",
    "sg:classifiers":[
        {
            "category":"Health Services",
            "subcategory":"Health Practitioner",
            "type":"Services"
        }
    ],
    "sg:phone":"+44 1434 632427",
    "sg:postcode":"NE45 5AW",
    "sg:province":"Northumberland",
    "sg:tags":[
        "osteopath"
    ],
    "wof:name":"Gelson Osteopathic Clinic",
    "wof:placetype":"venue"
},
  "geometry": {"coordinates":[-2.0132040977,54.9759368896],"type":"Point"}
}