{
  "type": "Feature",
  "properties": {
    "addr:full":"6 Penyard Road Neath Neath Port Talbot SA10 7EU",
    "addr:housenumber":"6",
    "addr:postcode":"sa10 7eu",
    "addr:street":"Penyard Road",
    "iso:country":"GB",
    "sg:address":"6 Penyard Road",
    "sg:city":"Neath",
    "sg:classifiers":[
        {
            "category":"Professional",
            "subcategory":"Art Services",
            "type":"Services"
        },
        {
            "category":"Utilities",
            "type":"Services"
        }
    ],
    "sg:phone":"+44 1792 816699",
    "sg:postcode":"SA10 7EU",
    "sg:province":"Neath Port Talbot",
    "sg:tags":[
        "graphic",
        "designer",
        "internet"
    ],
    "wof:name":"Creative Media Ltd.",
    "wof:placetype":"venue"
},
  "geometry": {"coordinates":[-3.8266460896,51.6649780273],"type":"Point"}
}