{
  "type": "Feature",
  "properties": {
    "addr:full":"Hillsfoot, Burnt House Lane, Cowfold Horsham West Sussex RH13 8DG",
    "addr:postcode":"rh13 8dg",
    "addr:street":"Burnt House Lane",
    "iso:country":"GB",
    "sg:address":"Hillsfoot, Burnt House Lane, Cowfold",
    "sg:city":"Horsham",
    "sg:classifiers":[
        {
            "category":"Building & Trades",
            "subcategory":"Construction",
            "type":"Services"
        }
    ],
    "sg:postcode":"RH13 8DG",
    "sg:province":"West Sussex",
    "sg:tags":[
        "joiner",
        "carpenter"
    ],
    "wof:name":"F C G Contractors",
    "wof:placetype":"venue"
},
  "geometry": {"coordinates":[-0.272624,50.990219],"type":"Point"}
}