{
  "type": "Feature",
  "properties": {
    "iso:country":"GB",
    "sg:address":"The Clinic, Oxlow Lane",
    "sg:city":"Dagenham",
    "sg:classifiers":[
        {
            "category":"Health Services",
            "subcategory":"Clinic",
            "type":"Services"
        }
    ],
    "sg:phone":"+44 20 8592 7748",
    "sg:postcode":"RM10 7YU",
    "sg:province":"Essex",
    "sg:tags":[
        "abuse",
        "drug"
    ],
    "wof:name":"Community Drug Advice Service",
    "wof:placetype":"venue"
},
  "geometry": {"coordinates":[0.1479610056,51.5416183472],"type":"Point"}
}