{
  "type": "Feature",
  "properties": {
    "addr:full":"Unit A Ladymead Retail Prk, Europa Prk Way Guildford Surrey GU1 1AJ",
    "addr:housenumber":"unit a",
    "addr:postcode":"gu1 1aj",
    "addr:street":"Ladymead;Prk Way",
    "iso:country":"GB",
    "sg:address":"Unit A Ladymead Retail Prk, Europa Prk Way",
    "sg:city":"Guildford",
    "sg:classifiers":[
        {
            "category":"Home & Garden",
            "subcategory":"Household Appliances",
            "type":"Retail Goods"
        }
    ],
    "sg:phone":"+44 845 600 7002",
    "sg:postcode":"GU1 1AJ",
    "sg:province":"Surrey",
    "sg:tags":[
        "electrical",
        "domestic"
    ],
    "wof:name":"Comet",
    "wof:placetype":"venue"
},
  "geometry": {"coordinates":[-0.5705159903,51.2370872498],"type":"Point"}
}