{
  "type": "Feature",
  "properties": {
    "iso:country":"GB",
    "sg:address":"Southgate Innovation Centre, Southgate Retail Park",
    "sg:city":"Derby",
    "sg:classifiers":[
        {
            "category":"Social Services",
            "subcategory":"Job Training",
            "type":"Services"
        }
    ],
    "sg:phone":"+44 1332 360242",
    "sg:postcode":"DE23 6UQ",
    "sg:province":"Derbyshire",
    "sg:tags":[
        "translator",
        "interpreter"
    ],
    "wof:name":"Brack & Associates Ltd.",
    "wof:placetype":"venue"
},
  "geometry": {"coordinates":[-1.48071,52.91008],"type":"Point"}
}