{
  "type": "Feature",
  "properties": {
    "addr:full":"1 Pemberton Row London Greater London EC4A 3HY",
    "addr:housenumber":"1",
    "addr:postcode":"ec4a 3hy",
    "addr:street":"Pemberton Row",
    "iso:country":"GB",
    "sg:address":"1 Pemberton Row",
    "sg:city":"London",
    "sg:classifiers":[
        {
            "category":"Banks & Credit Unions",
            "subcategory":"Financial Services",
            "type":"Services"
        }
    ],
    "sg:postcode":"EC4A 3HY",
    "sg:province":"Greater London",
    "sg:tags":[
        "consultant"
    ],
    "wof:name":"Oriental & African Strategic Investment Services Ltd.",
    "wof:placetype":"venue"
},
  "geometry": {"coordinates":[-0.108564,51.515072],"type":"Point"}
}