{
  "type": "Feature",
  "properties": {
    "addr:full":"139 Polwhele Rd Newquay Cornwall TR7 2SZ",
    "addr:housenumber":"139",
    "addr:postcode":"tr7 2sz",
    "addr:street":"Polwhele Rd",
    "iso:country":"GB",
    "sg:address":"139 Polwhele Rd",
    "sg:city":"Newquay",
    "sg:classifiers":[
        {
            "category":"Social Services",
            "subcategory":"Adult Care",
            "type":"Services"
        }
    ],
    "sg:phone":"+44 1637 851755",
    "sg:postcode":"TR7 2SZ",
    "sg:province":"Cornwall",
    "sg:tags":[
        "domestic",
        "cleaning"
    ],
    "wof:name":"Selclene",
    "wof:placetype":"venue"
},
  "geometry": {"coordinates":[-5.065611,50.402447],"type":"Point"}
}