{
  "type": "Feature",
  "properties": {
    "addr:full":"19 Ludlow Drive Thame Buckinghamshire OX9 3XS",
    "addr:housenumber":"19",
    "addr:postcode":"ox9 3xs",
    "addr:street":"Ludlow Drive",
    "iso:country":"GB",
    "sg:address":"19 Ludlow Drive",
    "sg:city":"Thame",
    "sg:classifiers":[
        {
            "category":"Building & Trades",
            "subcategory":"Plumbing",
            "type":"Services"
        }
    ],
    "sg:phone":"+44 1844 214015",
    "sg:postcode":"OX9 3XS",
    "sg:province":"Buckinghamshire",
    "sg:tags":[
        "central",
        "heating"
    ],
    "wof:name":"D E Gaskin",
    "wof:placetype":"venue"
},
  "geometry": {"coordinates":[-0.9698500037,51.7482872009],"type":"Point"}
}