{
  "type": "Feature",
  "properties": {
    "addr:full":"Omoa Works, Newarthill Motherwell North Lanarkshire ML1 5LY",
    "addr:housenumber":"omoa",
    "addr:postcode":"ml1 5ly",
    "addr:street":"Newarthill",
    "iso:country":"GB",
    "sg:address":"Omoa Works, Newarthill",
    "sg:city":"Motherwell",
    "sg:classifiers":[
        {
            "category":"Wholesale",
            "subcategory":"Non-durable Goods",
            "type":"Manufacturing & Wholesale Goods"
        }
    ],
    "sg:phone":"+44 1698 860149",
    "sg:postcode":"ML1 5LY",
    "sg:province":"North Lanarkshire",
    "sg:tags":[
        "animal",
        "by-product"
    ],
    "wof:name":"W C Hodgkinson (Cleland) Ltd.",
    "wof:placetype":"venue"
},
  "geometry": {"coordinates":[-3.9351489544,55.8130226135],"type":"Point"}
}