{
  "type": "Feature",
  "properties": {
    "iso:country":"GB",
    "sg:address":"North Ballachulish",
    "sg:city":"Fort William",
    "sg:classifiers":[
        {
            "category":"Travel",
            "subcategory":"Hotels & Motels",
            "type":"Entertainment"
        }
    ],
    "sg:phone":"+44 1855 821236",
    "sg:postcode":"PH33 6SA",
    "sg:province":"Highland",
    "wof:name":"Loch Leven Hotel",
    "wof:placetype":"venue"
},
  "geometry": {"coordinates":[-5.17466,56.692928],"type":"Point"}
}