{
  "type": "Feature",
  "properties": {
    "addr:full":"7th Floor, Oakland Ho, Talbot Rd, Old Trafford Manchester Greater Manchester M13 0AX",
    "addr:housenumber":"7th floor",
    "addr:postcode":"m13 0ax",
    "addr:street":"Oakland Ho Talbot Rd",
    "iso:country":"GB",
    "sg:address":"7th Floor, Oakland Ho, Talbot Rd, Old Trafford",
    "sg:city":"Manchester",
    "sg:classifiers":[
        {
            "category":"Professional",
            "subcategory":"Art Services",
            "type":"Services"
        }
    ],
    "sg:phone":"+44 161 908 8150",
    "sg:postcode":"M13 0AX",
    "sg:province":"Greater Manchester",
    "sg:tags":[
        "consultant",
        "design"
    ],
    "wof:name":"Insight Strategic Design Consultants Ltd",
    "wof:placetype":"venue"
},
  "geometry": {"coordinates":[-2.2186899185,53.4616012573],"type":"Point"}
}