{
  "type": "Feature",
  "properties": {
    "addr:full":"Unit 21 Bickford Road Birmingham West Midlands B6 7EE",
    "addr:housenumber":"unit 21",
    "addr:postcode":"b6 7ee",
    "addr:street":"Bickford Road",
    "iso:country":"GB",
    "sg:address":"Unit 21 Bickford Road",
    "sg:city":"Birmingham",
    "sg:classifiers":[
        {
            "category":"Manufacturing",
            "subcategory":"Tools & Machinery",
            "type":"Manufacturing & Wholesale Goods"
        }
    ],
    "sg:phone":"+44 121 327 0420",
    "sg:postcode":"B6 7EE",
    "sg:province":"West Midlands",
    "sg:tags":[
        "design",
        "maker"
    ],
    "wof:name":"Regal Tools",
    "wof:placetype":"venue"
},
  "geometry": {"coordinates":[-1.8767039776,52.5108184814],"type":"Point"}
}