{
  "type": "Feature",
  "properties": {
    "addr:full":"Ayre Cottage, Cooks Green, Holland Road Clacton-on-sea Essex CO16 9QG",
    "addr:housenumber":"cooks",
    "addr:postcode":"co16 9qg",
    "addr:street":"Green Holland Road",
    "iso:country":"GB",
    "sg:address":"Ayre Cottage, Cooks Green, Holland Road",
    "sg:city":"Clacton-on-sea",
    "sg:classifiers":[
        {
            "category":"Organizations",
            "subcategory":"Non-profit Organization",
            "type":"Services"
        }
    ],
    "sg:postcode":"CO16 9QG",
    "sg:province":"Essex",
    "sg:tags":[
        "organisation",
        "voluntary",
        "charity"
    ],
    "wof:name":"Lifeboat",
    "wof:placetype":"venue"
},
  "geometry": {"coordinates":[1.17719,51.825359],"type":"Point"}
}