{
  "type": "Feature",
  "properties": {
    "iso:country":"GB",
    "sg:address":"1 Diplocks Way Trading Estate, Diplocks Way",
    "sg:city":"Hailsham",
    "sg:classifiers":[
        {
            "category":"Health Services",
            "subcategory":"Optometrist",
            "type":"Services"
        }
    ],
    "sg:phone":"+44 1323 442885",
    "sg:postcode":"BN27 3JF",
    "sg:province":"East Sussex",
    "sg:tags":[
        "optician"
    ],
    "wof:name":"C.W Dixey & Son",
    "wof:placetype":"venue"
},
  "geometry": {"coordinates":[0.24796,50.863968],"type":"Point"}
}