{
  "type": "Feature",
  "properties": {
    "addr:full":"Chorley Road, Bispham Ormskirk Lancashire L40 3SL",
    "addr:postcode":"l40 3sl",
    "addr:street":"Chorley Road",
    "iso:country":"GB",
    "sg:address":"Chorley Road, Bispham",
    "sg:city":"Ormskirk",
    "sg:classifiers":[
        {
            "category":"Education",
            "subcategory":"School",
            "type":"Public Place"
        },
        {
            "category":"Government",
            "subcategory":"Office",
            "type":"Public Place"
        }
    ],
    "sg:phone":"+44 1257 462968",
    "sg:postcode":"L40 3SL",
    "sg:province":"Lancashire",
    "sg:tags":[
        "local",
        "authority"
    ],
    "wof:name":"Richard Durnings Endowed Primary School",
    "wof:placetype":"venue"
},
  "geometry": {"coordinates":[-2.7742140293,53.6155281067],"type":"Point"}
}