{
  "type": "Feature",
  "properties": {
    "addr:full":"31 Babbacombe Road Torquay Devon TQ1 3SB",
    "addr:housenumber":"31",
    "addr:postcode":"tq1 3sb",
    "addr:street":"Babbacombe Road",
    "iso:country":"GB",
    "sg:address":"31 Babbacombe Road",
    "sg:city":"Torquay",
    "sg:classifiers":[
        {
            "category":"Shopping",
            "subcategory":"Clothing, Apparel, & Fashions",
            "type":"Retail Goods"
        }
    ],
    "sg:postcode":"TQ1 3SB",
    "sg:province":"Devon",
    "sg:tags":[
        "shop"
    ],
    "wof:name":"Sally's of Babbacombe",
    "wof:placetype":"venue"
},
  "geometry": {"coordinates":[-3.520011,50.480598],"type":"Point"}
}