{
  "type": "Feature",
  "properties": {
    "iso:country":"GB",
    "sg:address":"Linthorpe Rd",
    "sg:city":"Middlesbrough",
    "sg:classifiers":[
        {
            "category":"Place Of Worship",
            "type":"Public Place"
        }
    ],
    "sg:phone":"+44 1642 248585",
    "sg:postcode":"TS1 2JR",
    "sg:province":"North Yorkshire",
    "wof:name":"Linthorpe Road Methodist Church",
    "wof:placetype":"venue"
},
  "geometry": {"coordinates":[-1.236264,54.578075],"type":"Point"}
}