{
  "type": "Feature",
  "properties": {
    "iso:country":"GB",
    "sg:address":"Clee House, Lanes Court",
    "sg:city":"Tewkesbury",
    "sg:classifiers":[
        {
            "category":"Organizations",
            "subcategory":"Community Association",
            "type":"Services"
        }
    ],
    "sg:phone":"+44 1684 295029",
    "sg:postcode":"GL20 5JQ",
    "sg:province":"Gloucestershire",
    "sg:tags":[
        "society",
        "housing"
    ],
    "wof:name":"Clee House",
    "wof:placetype":"venue"
},
  "geometry": {"coordinates":[-2.149463,51.992958],"type":"Point"}
}