{
  "type": "Feature",
  "properties": {
    "addr:full":"Verulam Avenue London Greater London E17 8ER",
    "addr:postcode":"e17 8er",
    "addr:street":"Verulam Avenue",
    "iso:country":"GB",
    "sg:address":"Verulam Avenue",
    "sg:city":"London",
    "sg:classifiers":[
        {
            "category":"Education",
            "subcategory":"School",
            "type":"Public Place"
        }
    ],
    "sg:phone":"+44 20 8520 0612",
    "sg:postcode":"E17 8ER",
    "sg:province":"Greater London",
    "sg:tags":[
        "local",
        "authority"
    ],
    "wof:name":"St Saviour's C of E Primary School",
    "wof:placetype":"venue"
},
  "geometry": {"coordinates":[-0.0294589996,51.5742149353],"type":"Point"}
}