{
  "type": "Feature",
  "properties": {
    "iso:country":"GB",
    "sg:address":"75 Abbeville Road",
    "sg:city":"London",
    "sg:classifiers":[
        {
            "category":"Food & Beverages",
            "subcategory":"Bakery",
            "type":"Retail Goods"
        }
    ],
    "sg:phone":"+44 20 8675 8640",
    "sg:postcode":"SW4 9JN",
    "sg:province":"Greater London",
    "sg:tags":[
        "pizza"
    ],
    "wof:name":"Pizza Hut",
    "wof:placetype":"venue"
},
  "geometry": {"coordinates":[-0.1391520053,51.455329895],"type":"Point"}
}