{
  "type": "Feature",
  "properties": {
    "addr:full":"6 Lavenham Way Stowmarket Suffolk IP14 2BE",
    "addr:housenumber":"6",
    "addr:postcode":"ip14 2be",
    "addr:street":"Lavenham Way",
    "iso:country":"GB",
    "sg:address":"6 Lavenham Way",
    "sg:city":"Stowmarket",
    "sg:classifiers":[
        {
            "category":"Professional",
            "subcategory":"Engineering",
            "type":"Services"
        }
    ],
    "sg:phone":"+44 1449 613877",
    "sg:postcode":"IP14 2BE",
    "sg:province":"Suffolk",
    "sg:tags":[
        "contractor",
        "electrical",
        "engineer"
    ],
    "wof:name":"Geoffrey K Freeman",
    "wof:placetype":"venue"
},
  "geometry": {"coordinates":[0.999136,52.176643],"type":"Point"}
}