{
  "type": "Feature",
  "properties": {
    "addr:full":"Events, Arncotts, Shaftesbury Rd Woking Surrey GU22 7DU",
    "addr:postcode":"gu22 7du",
    "addr:street":"Shaftesbury Rd",
    "iso:country":"GB",
    "sg:address":"Events, Arncotts, Shaftesbury Rd",
    "sg:city":"Woking",
    "sg:classifiers":[
        {
            "category":"Health Services",
            "subcategory":"Hospice",
            "type":"Services"
        }
    ],
    "sg:phone":"+44 1483 772883",
    "sg:postcode":"GU22 7DU",
    "sg:province":"Surrey",
    "wof:name":"Woking Hospice",
    "wof:placetype":"venue"
},
  "geometry": {"coordinates":[-0.54145,51.318378],"type":"Point"}
}