{
  "type": "Feature",
  "properties": {
    "addr:full":"83 Swansea Road Llanelli Carmarthenshire SA15 3BJ",
    "addr:housenumber":"83",
    "addr:postcode":"sa15 3bj",
    "addr:street":"Swansea Road",
    "iso:country":"GB",
    "sg:address":"83 Swansea Road",
    "sg:city":"Llanelli",
    "sg:classifiers":[
        {
            "category":"Autos & Motor Vehicles",
            "subcategory":"Auto Supplies",
            "type":"Retail Goods"
        }
    ],
    "sg:phone":"+44 1554 758896",
    "sg:postcode":"SA15 3BJ",
    "sg:province":"Carmarthenshire",
    "sg:tags":[
        "rubber",
        "tyre"
    ],
    "wof:name":"Thomas Tyres",
    "wof:placetype":"venue"
},
  "geometry": {"coordinates":[-4.151855,51.685413],"type":"Point"}
}