{
  "type": "Feature",
  "properties": {
    "addr:full":"Trent Road Nelson Lancashire BB9 0NX",
    "addr:postcode":"bb9 0nx",
    "addr:street":"Trent Road",
    "iso:country":"GB",
    "sg:address":"Trent Road",
    "sg:city":"Nelson",
    "sg:classifiers":[
        {
            "category":"Education",
            "subcategory":"School",
            "type":"Public Place"
        }
    ],
    "sg:phone":"+44 1282 615055",
    "sg:postcode":"BB9 0NX",
    "sg:province":"Lancashire",
    "sg:tags":[
        "local",
        "authority"
    ],
    "wof:name":"St John's C of E Primary School",
    "wof:placetype":"venue"
},
  "geometry": {"coordinates":[-2.1916110516,53.8342857361],"type":"Point"}
}