{
  "type": "Feature",
  "properties": {
    "addr:full":"Guildford Lawn Ramsgate Kent CT11 9AY",
    "addr:postcode":"ct11 9ay",
    "addr:street":"Ramsgate",
    "iso:country":"GB",
    "sg:address":"Guildford Lawn",
    "sg:city":"Ramsgate",
    "sg:classifiers":[
        {
            "category":"Education",
            "subcategory":"Library",
            "type":"Public Place"
        }
    ],
    "sg:phone":"+44 1843 593532",
    "sg:postcode":"CT11 9AY",
    "sg:province":"Kent",
    "sg:tags":[
        "book"
    ],
    "wof:name":"Ramsgate Library",
    "wof:placetype":"venue"
},
  "geometry": {"coordinates":[1.415692,51.33419],"type":"Point"}
}