{
  "type": "Feature",
  "properties": {
    "iso:country":"GB",
    "sg:address":"216 Straight Mile Road, Rotherwas",
    "sg:city":"Hereford",
    "sg:classifiers":[
        {
            "category":"Professional",
            "subcategory":"Computer Services",
            "type":"Services"
        }
    ],
    "sg:phone":"+44 1432 372100",
    "sg:postcode":"HR2 6JP",
    "sg:province":"Herefordshire",
    "sg:tags":[
        "development",
        "system",
        "software"
    ],
    "wof:name":"Pracctice Ltd",
    "wof:placetype":"venue"
},
  "geometry": {"coordinates":[-2.6783390045,52.0369262695],"type":"Point"}
}