{
  "type": "Feature",
  "properties": {
    "addr:full":"74 Crayford Road Dartford Kent DA1 4AU",
    "addr:housenumber":"74",
    "addr:postcode":"da1 4au",
    "addr:street":"Crayford Road",
    "iso:country":"GB",
    "sg:address":"74 Crayford Road",
    "sg:city":"Dartford",
    "sg:classifiers":[
        {
            "category":"Manufacturing",
            "subcategory":"Textiles",
            "type":"Manufacturing & Wholesale Goods"
        }
    ],
    "sg:postcode":"DA1 4AU",
    "sg:province":"Kent",
    "sg:tags":[
        "made-up"
    ],
    "wof:name":"Curtain Craft",
    "wof:placetype":"venue"
},
  "geometry": {"coordinates":[0.179550007,51.4506912231],"type":"Point"}
}