{
  "type": "Feature",
  "properties": {
    "addr:full":"Room 9 Arthur Last House, Altbarn Road Colchester Essex CO2 8LG",
    "addr:housenumber":"9",
    "addr:postcode":"co2 8lg",
    "addr:street":"Arthur Last;Altbarn Road Colchester",
    "iso:country":"GB",
    "sg:address":"Room 9 Arthur Last House, Altbarn Road",
    "sg:city":"Colchester",
    "sg:classifiers":[
        {
            "category":"Professional",
            "subcategory":"Detective & Security Services",
            "type":"Services"
        }
    ],
    "sg:phone":"+44 1206 860888",
    "sg:postcode":"CO2 8LG",
    "sg:province":"Essex",
    "wof:name":"T L C Key Holding",
    "wof:placetype":"venue"
},
  "geometry": {"coordinates":[0.9277870059,51.8832130432],"type":"Point"}
}