{
  "type": "Feature",
  "properties": {
    "addr:full":"1 Sycamore Close, Frimley Camberley Hampshire GU16 8PJ",
    "addr:housenumber":"1",
    "addr:postcode":"gu16 8pj",
    "addr:street":"Sycamore Close",
    "iso:country":"GB",
    "sg:address":"1 Sycamore Close, Frimley",
    "sg:city":"Camberley",
    "sg:classifiers":[
        {
            "category":"Government",
            "subcategory":"Post Office",
            "type":"Public Place"
        }
    ],
    "sg:postcode":"GU16 8PJ",
    "sg:province":"Hampshire",
    "sg:tags":[
        "messenger",
        "courier"
    ],
    "wof:name":"Southern Express",
    "wof:placetype":"venue"
},
  "geometry": {"coordinates":[-0.7337620258,51.318271637],"type":"Point"}
}