{
  "type": "Feature",
  "properties": {
    "addr:full":"Burhope Farm, Orcop Hereford Herefordshire HR2 8EU",
    "addr:postcode":"hr2 8eu",
    "iso:country":"GB",
    "sg:address":"Burhope Farm, Orcop",
    "sg:city":"Hereford",
    "sg:classifiers":[
        {
            "category":"Farming",
            "subcategory":"Dairy Farm",
            "type":"Manufacturing & Wholesale Goods"
        }
    ],
    "sg:phone":"+44 1981 580275",
    "sg:postcode":"HR2 8EU",
    "sg:province":"Herefordshire",
    "sg:tags":[
        "farmer"
    ],
    "wof:name":"P A Hale",
    "wof:placetype":"venue"
},
  "geometry": {"coordinates":[-2.766487,51.931873],"type":"Point"}
}