{
  "type": "Feature",
  "properties": {
    "iso:country":"GB",
    "sg:address":"George Street",
    "sg:city":"Chelmsford",
    "sg:classifiers":[
        {
            "category":"Parking",
            "type":"Transportation"
        }
    ],
    "sg:phone":"+44 1245 356986",
    "sg:postcode":"CM2 0JU",
    "sg:province":"Essex",
    "sg:tags":[
        "car",
        "park"
    ],
    "wof:name":"George Street Car Park",
    "wof:placetype":"venue"
},
  "geometry": {"coordinates":[0.469458,51.728912],"type":"Point"}
}