{
  "type": "Feature",
  "properties": {
    "iso:country":"GB",
    "sg:address":"85 Renfield Street",
    "sg:city":"Glasgow",
    "sg:classifiers":[
        {
            "category":"Restaurant",
            "type":"Food & Drink"
        }
    ],
    "sg:phone":"+44 141 353 6616",
    "sg:postcode":"G2 1LP",
    "sg:province":"Glasgow City",
    "sg:tags":[
        "italian"
    ],
    "wof:name":"Arigo Restaurant",
    "wof:placetype":"venue"
},
  "geometry": {"coordinates":[-4.25609,55.863647],"type":"Point"}
}