{
  "type": "Feature",
  "properties": {
    "iso:country":"GB",
    "sg:address":"53 Bath Street",
    "sg:city":"Gravesend",
    "sg:classifiers":[
        {
            "category":"Utilities",
            "subcategory":"Telephone",
            "type":"Services"
        },
        {
            "category":"Shopping",
            "subcategory":"Computers & Home Electronics",
            "type":"Retail Goods"
        }
    ],
    "sg:phone":"+44 1474 561111",
    "sg:postcode":"DA11 0DF",
    "sg:province":"Kent",
    "sg:tags":[
        "telecom",
        "equipment",
        "system",
        "telecommunication"
    ],
    "wof:name":"Computertel Ltd",
    "wof:placetype":"venue"
},
  "geometry": {"coordinates":[0.366152,51.444542],"type":"Point"}
}