{
  "type": "Feature",
  "properties": {
    "iso:country":"GB",
    "sg:address":"59 High Street, Ecton",
    "sg:city":"Northampton",
    "sg:classifiers":[
        {
            "category":"Professional",
            "subcategory":"Advertising",
            "type":"Services"
        }
    ],
    "sg:postcode":"NN6 0QA",
    "sg:province":"Northamptonshire",
    "sg:tags":[
        "mail",
        "direct"
    ],
    "wof:name":"Graham Thompson",
    "wof:placetype":"venue"
},
  "geometry": {"coordinates":[-0.751422,52.266281],"type":"Point"}
}