{
  "type": "Feature",
  "properties": {
    "addr:full":"3 Bulkeley Close, Englefield Grn Egham Surrey TW20 0NS",
    "addr:housenumber":"3",
    "addr:postcode":"tw20 0ns",
    "addr:street":"Bulkeley Close Englefield Grn Egham",
    "iso:country":"GB",
    "sg:address":"3 Bulkeley Close, Englefield Grn",
    "sg:city":"Egham",
    "sg:classifiers":[
        {
            "category":"Professional",
            "subcategory":"Printing & Photocopies",
            "type":"Services"
        }
    ],
    "sg:postcode":"TW20 0NS",
    "sg:province":"Surrey",
    "sg:tags":[
        "embroiderer"
    ],
    "wof:name":"Punch People",
    "wof:placetype":"venue"
},
  "geometry": {"coordinates":[-0.571926,51.432812],"type":"Point"}
}