{
  "type": "Feature",
  "properties": {
    "iso:country":"GB",
    "sg:address":"145 Walmgate",
    "sg:city":"York",
    "sg:classifiers":[
        {
            "category":"Home & Garden",
            "subcategory":"Home Furnishings",
            "type":"Retail Goods"
        }
    ],
    "sg:phone":"+44 1904 612368",
    "sg:postcode":"YO1 2UB",
    "sg:province":"North Yorkshire",
    "sg:tags":[
        "blind",
        "curtain",
        "fitting"
    ],
    "wof:name":"Karens Curtains",
    "wof:placetype":"venue"
},
  "geometry": {"coordinates":[-1.0713700056,53.9552688599],"type":"Point"}
}