{
  "type": "Feature",
  "properties": {
    "addr:full":"Harmire Enterprise Park, Harmire Road Barnard Castle Cumbria DL12 8BN",
    "addr:postcode":"dl12 8bn",
    "addr:street":"Harmire Enterprise Park Harmire Road",
    "iso:country":"GB",
    "sg:address":"Harmire Enterprise Park, Harmire Road",
    "sg:city":"Barnard Castle",
    "sg:classifiers":[
        {
            "category":"Military Area",
            "subcategory":"Air Force Base",
            "type":"Public Place"
        },
        {
            "category":"Real Estate",
            "subcategory":"Architect",
            "type":"Services"
        }
    ],
    "sg:phone":"+44 1833 690101",
    "sg:postcode":"DL12 8BN",
    "sg:province":"Cumbria",
    "sg:tags":[
        "water",
        "treatment"
    ],
    "wof:name":"Honeyman Group Ltd.",
    "wof:placetype":"venue"
},
  "geometry": {"coordinates":[-1.923809,54.543152],"type":"Point"}
}