{
  "type": "Feature",
  "properties": {
    "addr:full":"121 High Oak Road Ware Hertfordshire SG12 7PA",
    "addr:housenumber":"121",
    "addr:postcode":"sg12 7pa",
    "addr:street":"High Oak Road Ware",
    "iso:country":"GB",
    "sg:address":"121 High Oak Road",
    "sg:city":"Ware",
    "sg:classifiers":[
        {
            "category":"Building & Trades",
            "subcategory":"Landscaping Services",
            "type":"Services"
        }
    ],
    "sg:phone":"+44 1920 467440",
    "sg:postcode":"SG12 7PA",
    "sg:province":"Hertfordshire",
    "sg:tags":[
        "forestry",
        "surgeon",
        "tree"
    ],
    "wof:name":"K & B Tree Contractors",
    "wof:placetype":"venue"
},
  "geometry": {"coordinates":[-0.0281719994,51.8178482056],"type":"Point"}
}