{
  "type": "Feature",
  "properties": {
    "iso:country":"GB",
    "sg:address":"46 St Chads Parade",
    "sg:city":"Liverpool",
    "sg:classifiers":[
        {
            "category":"Home & Garden",
            "subcategory":"Household Appliances",
            "type":"Retail Goods"
        }
    ],
    "sg:postcode":"L32 8RH",
    "sg:province":"Merseyside",
    "sg:tags":[
        "electrical",
        "domestic"
    ],
    "wof:name":"Lazer Electrics",
    "wof:placetype":"venue"
},
  "geometry": {"coordinates":[-2.885244,53.482552],"type":"Point"}
}