{
  "type": "Feature",
  "properties": {
    "iso:country":"GB",
    "sg:address":"170 High Street, Eston",
    "sg:city":"Middlesbrough",
    "sg:classifiers":[
        {
            "category":"Fast Food",
            "type":"Food & Drink"
        }
    ],
    "sg:phone":"+44 1642 466777",
    "sg:postcode":"TS6 9JA",
    "sg:province":"North Yorkshire",
    "sg:tags":[
        "away",
        "take"
    ],
    "wof:name":"Wah Sun Takeaway",
    "wof:placetype":"venue"
},
  "geometry": {"coordinates":[-1.142635,54.559418],"type":"Point"}
}