{
  "type": "Feature",
  "properties": {
    "iso:country":"GB",
    "sg:address":"53 Ashenden Walk",
    "sg:city":"Tunbridge Wells",
    "sg:classifiers":[
        {
            "category":"Farming",
            "subcategory":"Dairy Farm",
            "type":"Manufacturing & Wholesale Goods"
        }
    ],
    "sg:postcode":"TN2 3UJ",
    "sg:province":"East Sussex",
    "wof:name":"Toad Rock Dairy",
    "wof:placetype":"venue"
},
  "geometry": {"coordinates":[0.2878719866,51.1523094177],"type":"Point"}
}