{
  "type": "Feature",
  "properties": {
    "addr:full":"13 Harrow Place London Greater London E1 7DB",
    "addr:housenumber":"13",
    "addr:postcode":"e1 7db",
    "addr:street":"Harrow Place",
    "iso:country":"GB",
    "sg:address":"13 Harrow Place",
    "sg:city":"London",
    "sg:classifiers":[
        {
            "category":"Organizations",
            "subcategory":"Labor Organization",
            "type":"Services"
        },
        {
            "category":"Professional",
            "subcategory":"Business Services",
            "type":"Services"
        }
    ],
    "sg:phone":"+44 20 7247 9247",
    "sg:postcode":"E1 7DB",
    "sg:province":"Greater London",
    "sg:tags":[
        "import",
        "export",
        "agent"
    ],
    "wof:name":"Rahul Enterprises",
    "wof:placetype":"venue"
},
  "geometry": {"coordinates":[-0.0777010024,51.5158920288],"type":"Point"}
}