{
  "type": "Feature",
  "properties": {
    "iso:country":"GB",
    "sg:address":"Unit 4, 1 Old Union Mill",
    "sg:city":"Birmingham",
    "sg:classifiers":[
        {
            "category":"Arts & Performance",
            "subcategory":"Arts Center",
            "type":"Entertainment"
        }
    ],
    "sg:postcode":"B16 8HW",
    "sg:province":"West Midlands",
    "sg:tags":[
        "centre"
    ],
    "wof:name":"Mark Renn & Mick Thacker",
    "wof:placetype":"venue"
},
  "geometry": {"coordinates":[-1.908604,52.478596],"type":"Point"}
}