{
  "type": "Feature",
  "properties": {
    "addr:full":"Distribution Centre, Knight Rd, Strood Rochester Kent ME2 2HF",
    "addr:postcode":"me2 2hf",
    "addr:street":"Knight Rd",
    "iso:country":"GB",
    "sg:address":"Distribution Centre, Knight Rd, Strood",
    "sg:city":"Rochester",
    "sg:classifiers":[
        {
            "category":"Professional",
            "subcategory":"Business Services",
            "type":"Services"
        }
    ],
    "sg:phone":"+44 1634 290100",
    "sg:postcode":"ME2 2HF",
    "sg:province":"Kent",
    "sg:tags":[
        "distribution"
    ],
    "wof:name":"Tibbett & Britten Group Plc",
    "wof:placetype":"venue"
},
  "geometry": {"coordinates":[0.48608,51.386902],"type":"Point"}
}