{
  "type": "Feature",
  "properties": {
    "iso:country":"GB",
    "sg:address":"Unit 27, Church Road Business Centre, Church Road",
    "sg:city":"Sittingbourne",
    "sg:classifiers":[
        {
            "category":"Retail",
            "subcategory":"Auto Repair",
            "type":"Services"
        }
    ],
    "sg:phone":"+44 1795 473330",
    "sg:postcode":"ME10 3RS",
    "sg:province":"Kent",
    "sg:tags":[
        "modification",
        "garage"
    ],
    "wof:name":"Houston Motors",
    "wof:placetype":"venue"
},
  "geometry": {"coordinates":[0.752885,51.340225],"type":"Point"}
}