{
  "type": "Feature",
  "properties": {
    "addr:full":"18 Oyster Place, Montrose Road, Dukes Park Industrial Estate Chelmsford Essex CM2 6TX",
    "addr:housenumber":"18",
    "addr:postcode":"cm2 6tx",
    "addr:street":"Oyster Place Montrose Road Dukes Park Industrial Estate",
    "iso:country":"GB",
    "sg:address":"18 Oyster Place, Montrose Road, Dukes Park Industrial Estate",
    "sg:city":"Chelmsford",
    "sg:classifiers":[
        {
            "category":"Manufacturing",
            "subcategory":"Signs",
            "type":"Manufacturing & Wholesale Goods"
        }
    ],
    "sg:phone":"+44 1245 462426",
    "sg:postcode":"CM2 6TX",
    "sg:province":"Essex",
    "sg:tags":[
        "nameplate"
    ],
    "wof:name":"Dartcase Ltd.",
    "wof:placetype":"venue"
},
  "geometry": {"coordinates":[0.50201,51.742271],"type":"Point"}
}