{
  "type": "Feature",
  "properties": {
    "addr:full":"Suite 418, Crown House, North Circular Road London Greater London NW10 7PN",
    "addr:housenumber":"suite 418",
    "addr:postcode":"nw10 7pn",
    "addr:street":"Crown;North Circular Road",
    "iso:country":"GB",
    "sg:address":"Suite 418, Crown House, North Circular Road",
    "sg:city":"London",
    "sg:classifiers":[
        {
            "category":"Shopping",
            "subcategory":"Computers & Home Electronics",
            "type":"Retail Goods"
        }
    ],
    "sg:phone":"+44 20 8838 5111",
    "sg:postcode":"NW10 7PN",
    "sg:province":"Greater London",
    "sg:tags":[
        "consumables"
    ],
    "wof:name":"Metcom Consumables Ltd.",
    "wof:placetype":"venue"
},
  "geometry": {"coordinates":[-0.2843399942,51.537399292],"type":"Point"}
}