{
  "type": "Feature",
  "properties": {
    "iso:country":"GB",
    "sg:address":"Harrogate Rd",
    "sg:city":"Bradford",
    "sg:classifiers":[
        {
            "category":"Retail",
            "subcategory":"Auto Repair",
            "type":"Services"
        }
    ],
    "sg:postcode":"BD10 0NN",
    "sg:province":"West Yorkshire",
    "sg:tags":[
        "modification",
        "garage"
    ],
    "wof:name":"Vento,Andrew,",
    "wof:placetype":"venue"
},
  "geometry": {"coordinates":[-1.705534,53.836617],"type":"Point"}
}