{
  "type": "Feature",
  "properties": {
    "addr:full":"Hinckley Road, Walsgrave-on-sowe Coventry Warwickshire CV2 2HP",
    "addr:postcode":"cv2 2hp",
    "addr:street":"Hinckley Road Walsgrave-On-Sowe",
    "iso:country":"GB",
    "sg:address":"Hinckley Road, Walsgrave-on-sowe",
    "sg:city":"Coventry",
    "sg:classifiers":[
        {
            "category":"Cinema",
            "subcategory":"Movie Rental",
            "type":"Entertainment"
        }
    ],
    "sg:phone":"+44 24 7660 4700",
    "sg:postcode":"CV2 2HP",
    "sg:province":"Warwickshire",
    "sg:tags":[
        "video",
        "library"
    ],
    "wof:name":"Blockbuster Video",
    "wof:placetype":"venue"
},
  "geometry": {"coordinates":[-1.439962,52.428722],"type":"Point"}
}