{
  "type": "Feature",
  "properties": {
    "iso:country":"GB",
    "sg:address":"1 Kimberley Rd, Nuthall",
    "sg:city":"Nottingham",
    "sg:classifiers":[
        {
            "category":"Government",
            "subcategory":"Post Office",
            "type":"Public Place"
        }
    ],
    "sg:phone":"+44 115 938 3134",
    "sg:postcode":"NG16 1DA",
    "sg:province":"Derbyshire",
    "wof:name":"Nuthall P.O",
    "wof:placetype":"venue"
},
  "geometry": {"coordinates":[-1.233529,52.995251],"type":"Point"}
}