{
  "type": "Feature",
  "properties": {
    "iso:country":"GB",
    "sg:address":"Trefechan Fach Farm, College Road",
    "sg:city":"Carmarthen",
    "sg:classifiers":[
        {
            "category":"Farming",
            "subcategory":"Livestock Farm",
            "type":"Manufacturing & Wholesale Goods"
        }
    ],
    "sg:postcode":"SA31 3RG",
    "sg:province":"Carmarthenshire",
    "sg:tags":[
        "others"
    ],
    "wof:name":"George Davies",
    "wof:placetype":"venue"
},
  "geometry": {"coordinates":[-4.2994041443,51.8602752686],"type":"Point"}
}