{
  "type": "Feature",
  "properties": {
    "iso:country":"GB",
    "sg:address":"132 Thetford Chase, Telford Town Centre",
    "sg:city":"Telford",
    "sg:classifiers":[
        {
            "category":"Manufacturing",
            "subcategory":"Apparel",
            "type":"Manufacturing & Wholesale Goods"
        }
    ],
    "sg:postcode":"TF3 4BJ",
    "sg:province":"Shropshire",
    "sg:tags":[
        "garment",
        "designer"
    ],
    "wof:name":"Roman Menswear",
    "wof:placetype":"venue"
},
  "geometry": {"coordinates":[-2.444159,52.673939],"type":"Point"}
}