{
  "type": "Feature",
  "properties": {
    "addr:full":"1 Blick Road, Heathcote Industrial Estate Warwick Warwickshire CV34 6TA",
    "addr:housenumber":"1",
    "addr:postcode":"cv34 6ta",
    "addr:street":"Blick Road;Industrial Estate",
    "iso:country":"GB",
    "sg:address":"1 Blick Road, Heathcote Industrial Estate",
    "sg:city":"Warwick",
    "sg:classifiers":[
        {
            "category":"Manufacturing",
            "subcategory":"Metals",
            "type":"Manufacturing & Wholesale Goods"
        },
        {
            "category":"Wholesale",
            "subcategory":"Metals & Minerals",
            "type":"Manufacturing & Wholesale Goods"
        }
    ],
    "sg:phone":"+44 1926 313801",
    "sg:postcode":"CV34 6TA",
    "sg:province":"Warwickshire",
    "sg:tags":[
        "fabricator",
        "work",
        "sheet"
    ],
    "wof:name":"Radford Panel Co. Ltd.",
    "wof:placetype":"venue"
},
  "geometry": {"coordinates":[-1.554229,52.272118],"type":"Point"}
}