{
  "type": "Feature",
  "properties": {
    "iso:country":"GB",
    "sg:address":"18 Slater St",
    "sg:city":"Leicester",
    "sg:classifiers":[
        {
            "category":"Shopping",
            "subcategory":"Stationery & Office Supplies",
            "type":"Retail Goods"
        }
    ],
    "sg:phone":"+44 116 253 3352",
    "sg:postcode":"LE3 5AY",
    "sg:province":"Leicestershire",
    "sg:tags":[
        "box",
        "carton"
    ],
    "wof:name":"Jaycee Cartons",
    "wof:placetype":"venue"
},
  "geometry": {"coordinates":[-1.142263,52.642075],"type":"Point"}
}