{
  "type": "Feature",
  "properties": {
    "addr:full":"3 Black Abbey Street Accrington Lancashire BB5 1HT",
    "addr:housenumber":"3",
    "addr:postcode":"bb5 1ht",
    "addr:street":"Black Abbey Street",
    "iso:country":"GB",
    "sg:address":"3 Black Abbey Street",
    "sg:city":"Accrington",
    "sg:classifiers":[
        {
            "category":"Home & Garden",
            "subcategory":"Building Materials",
            "type":"Retail Goods"
        },
        {
            "category":"Education",
            "subcategory":"University",
            "type":"Public Place"
        }
    ],
    "sg:phone":"+44 1254 232524",
    "sg:postcode":"BB5 1HT",
    "sg:province":"Lancashire",
    "sg:tags":[
        "roofing",
        "educational",
        "rafter",
        "beams"
    ],
    "wof:name":"Kerrcraft",
    "wof:placetype":"venue"
},
  "geometry": {"coordinates":[-2.361149,53.750912],"type":"Point"}
}