{
  "type": "Feature",
  "properties": {
    "iso:country":"GB",
    "sg:address":"Humber Marsh, Stoke Prior",
    "sg:city":"Leominster",
    "sg:classifiers":[
        {
            "category":"Sports & Exercise",
            "subcategory":"Playing Field",
            "type":"Entertainment"
        }
    ],
    "sg:phone":"+44 1568 760671",
    "sg:postcode":"HR6 0NE",
    "sg:province":"Herefordshire",
    "sg:tags":[
        "windmill",
        "mnfrs",
        "power",
        "wind"
    ],
    "wof:name":"Wind & Sun Ltd.",
    "wof:placetype":"venue"
},
  "geometry": {"coordinates":[-2.7021501064,52.206161499],"type":"Point"}
}