{
  "type": "Feature",
  "properties": {
    "addr:full":"8 North Balfern, Kirkinner Newton Stewart Dumfries and Galloway DG8 9AP",
    "addr:housenumber":"8",
    "addr:postcode":"dg8 9ap",
    "addr:street":"North Balfern Kirkinner Newton Stewart",
    "iso:country":"GB",
    "sg:address":"8 North Balfern, Kirkinner",
    "sg:city":"Newton Stewart",
    "sg:classifiers":[
        {
            "category":"Home & Garden",
            "subcategory":"Garden Supply",
            "type":"Retail Goods"
        },
        {
            "category":"Banks & Credit Unions",
            "subcategory":"Investment Brokerage",
            "type":"Services"
        },
        {
            "category":"Professional",
            "type":"Services"
        }
    ],
    "sg:phone":"+44 1988 840229",
    "sg:postcode":"DG8 9AP",
    "sg:province":"Dumfries and Galloway",
    "sg:tags":[
        "farm",
        "bulb",
        "agricultural",
        "grower",
        "contractor"
    ],
    "wof:name":"William S Harper",
    "wof:placetype":"venue"
},
  "geometry": {"coordinates":[-4.457845211,54.8329658508],"type":"Point"}
}