{
  "type": "Feature",
  "properties": {
    "iso:country":"GB",
    "sg:address":"11 Homefield Close",
    "sg:city":"High Wycombe",
    "sg:classifiers":[
        {
            "category":"Building & Trades",
            "subcategory":"Construction",
            "type":"Services"
        }
    ],
    "sg:postcode":"HP14 3PY",
    "sg:province":"Buckinghamshire",
    "sg:tags":[
        "builder"
    ],
    "wof:name":"G Simmons",
    "wof:placetype":"venue"
},
  "geometry": {"coordinates":[-0.901376,51.657913],"type":"Point"}
}