{
  "type": "Feature",
  "properties": {
    "addr:full":"10b High St Falmouth Cornwall TR11 2AB",
    "addr:housenumber":"10b",
    "addr:postcode":"tr11 2ab",
    "addr:street":"High St",
    "iso:country":"GB",
    "sg:address":"10b High St",
    "sg:city":"Falmouth",
    "sg:classifiers":[
        {
            "category":"Shopping",
            "subcategory":"Antiques",
            "type":"Retail Goods"
        }
    ],
    "sg:postcode":"TR11 2AB",
    "sg:province":"Cornwall",
    "wof:name":"Putnam Antiques & Design",
    "wof:placetype":"venue"
},
  "geometry": {"coordinates":[-5.072674,50.15733],"type":"Point"}
}