{
  "type": "Feature",
  "properties": {
    "iso:country":"GB",
    "sg:address":"Dye House, Bush",
    "sg:city":"Bude",
    "sg:classifiers":[
        {
            "category":"Park",
            "subcategory":"Provincial",
            "type":"Public Place"
        },
        {
            "category":"Recreation",
            "subcategory":"Campground",
            "type":"Entertainment"
        }
    ],
    "sg:phone":"+44 1288 353104",
    "sg:postcode":"EX23 9LB",
    "sg:province":"Cornwall",
    "sg:tags":[
        "holiday",
        "camp",
        "site",
        "camping"
    ],
    "wof:name":"Willow Valley Holiday Park",
    "wof:placetype":"venue"
},
  "geometry": {"coordinates":[-4.509673,50.842525],"type":"Point"}
}