{
  "type": "Feature",
  "properties": {
    "iso:country":"GB",
    "sg:address":"Random Ho, 20 Vauxhall Bridge Rd",
    "sg:city":"Westminster",
    "sg:classifiers":[
        {
            "category":"Shopping",
            "subcategory":"Books",
            "type":"Retail Goods"
        }
    ],
    "sg:phone":"+44 20 7840 8400",
    "sg:postcode":"SW1V 2SA",
    "sg:province":"Greater London",
    "wof:name":"Pimlico",
    "wof:placetype":"venue"
},
  "geometry": {"coordinates":[-0.13173,51.489868],"type":"Point"}
}