{
  "type": "Feature",
  "properties": {
    "addr:full":"Drayton Lane, Shopwyke Chichester West Sussex PO20 2BN",
    "addr:postcode":"po20 2bn",
    "addr:street":"Drayton Lane Shopwyke",
    "iso:country":"GB",
    "sg:address":"Drayton Lane, Shopwyke",
    "sg:city":"Chichester",
    "sg:classifiers":[
        {
            "category":"Wholesale",
            "subcategory":"Fruits & Vegetables",
            "type":"Manufacturing & Wholesale Goods"
        }
    ],
    "sg:postcode":"PO20 2BN",
    "sg:province":"West Sussex",
    "wof:name":"Lansdowne Nursery Ltd.",
    "wof:placetype":"venue"
},
  "geometry": {"coordinates":[-0.7365139723,50.8318481445],"type":"Point"}
}