{
  "type": "Feature",
  "properties": {
    "addr:full":"82 Hatfield Rd Ipswich Suffolk IP3 9AG",
    "addr:housenumber":"82",
    "addr:postcode":"ip3 9ag",
    "addr:street":"Hatfield Rd",
    "iso:country":"GB",
    "sg:address":"82 Hatfield Rd",
    "sg:city":"Ipswich",
    "sg:classifiers":[
        {
            "category":"Recreation",
            "subcategory":"Boat Charter",
            "type":"Entertainment"
        }
    ],
    "sg:postcode":"IP3 9AG",
    "sg:province":"Suffolk",
    "sg:tags":[
        "excursion"
    ],
    "wof:name":"Hancock,Margaret,",
    "wof:placetype":"venue"
},
  "geometry": {"coordinates":[1.181333,52.045273],"type":"Point"}
}