{
  "type": "Feature",
  "properties": {
    "iso:country":"GB",
    "sg:address":"Unit 9 Fairhill Industrial Estate, Woodrow Way, Irlam",
    "sg:city":"Manchester",
    "sg:classifiers":[
        {
            "category":"Freight",
            "type":"Transportation"
        }
    ],
    "sg:phone":"+44 161 776 2000",
    "sg:postcode":"M44 6ZQ",
    "sg:province":"Greater Manchester",
    "sg:tags":[
        "forwarders"
    ],
    "wof:name":"Skantrans P S L Ltd.",
    "wof:placetype":"venue"
},
  "geometry": {"coordinates":[-2.4242870808,53.4386024475],"type":"Point"}
}