{
  "type": "Feature",
  "properties": {
    "addr:full":"20 Heath Road, Upton Chester Cheshire CH2 1HX",
    "addr:housenumber":"20",
    "addr:postcode":"ch2 1hx",
    "addr:street":"Heath Road",
    "iso:country":"GB",
    "sg:address":"20 Heath Road, Upton",
    "sg:city":"Chester",
    "sg:classifiers":[
        {
            "category":"Organizations",
            "subcategory":"Membership Organization",
            "type":"Services"
        }
    ],
    "sg:phone":"+44 1244 390046",
    "sg:postcode":"CH2 1HX",
    "sg:province":"Cheshire",
    "sg:tags":[
        "club"
    ],
    "wof:name":"The Royal British Legion",
    "wof:placetype":"venue"
},
  "geometry": {"coordinates":[-2.8822329044,53.2190895081],"type":"Point"}
}