{
  "type": "Feature",
  "properties": {
    "addr:full":"25/26 New Ho, 67-68 Hatton Gdn London Greater London EC1N 8JY",
    "addr:housenumber":"25 / 26;67-68",
    "addr:postcode":"ec1n 8jy",
    "addr:street":"New Ho;Hatton Gdn",
    "iso:country":"GB",
    "sg:address":"25/26 New Ho, 67-68 Hatton Gdn",
    "sg:city":"London",
    "sg:classifiers":[
        {
            "category":"Professional",
            "subcategory":"Business Services",
            "type":"Services"
        }
    ],
    "sg:phone":"+44 20 7404 1258",
    "sg:postcode":"EC1N 8JY",
    "sg:province":"Greater London",
    "sg:tags":[
        "import",
        "export",
        "agent"
    ],
    "wof:name":"Kalco International Ltd",
    "wof:placetype":"venue"
},
  "geometry": {"coordinates":[-0.1087500006,51.5208396912],"type":"Point"}
}