{
  "type": "Feature",
  "properties": {
    "iso:country":"GB",
    "sg:address":"Rockfield Stables, Brigsteer Rd",
    "sg:city":"Kendal",
    "sg:classifiers":[
        {
            "category":"Personal",
            "subcategory":"Adult",
            "type":"Services"
        }
    ],
    "sg:phone":"+44 15395 61195",
    "sg:postcode":"LA8 8NX",
    "sg:province":"Cumbria",
    "sg:tags":[
        "equestrian"
    ],
    "wof:name":"R Knipe",
    "wof:placetype":"venue"
},
  "geometry": {"coordinates":[-2.79002,54.276402],"type":"Point"}
}