{
  "type": "Feature",
  "properties": {
    "addr:full":"1 Aerial House, School Aycliffe Lane Newton Aycliffe Durham DL5 6QF",
    "addr:housenumber":"1",
    "addr:postcode":"dl5 6qf",
    "addr:street":"Aerial;Aycliffe Lane",
    "iso:country":"GB",
    "sg:address":"1 Aerial House, School Aycliffe Lane",
    "sg:city":"Newton Aycliffe",
    "sg:classifiers":[
        {
            "category":"Professional",
            "subcategory":"Engineering",
            "type":"Services"
        }
    ],
    "sg:phone":"+44 1325 315315",
    "sg:postcode":"DL5 6QF",
    "sg:province":"Durham",
    "sg:tags":[
        "contractor",
        "electrical",
        "engineer"
    ],
    "wof:name":"Lacegold Electrical & Mechanical Services Ltd.",
    "wof:placetype":"venue"
},
  "geometry": {"coordinates":[-1.563024,54.596272],"type":"Point"}
}