{
  "type": "Feature",
  "properties": {
    "addr:full":"110b Park Rd Altrincham Cheshire WA15 6TE",
    "addr:housenumber":"110b",
    "addr:postcode":"wa15 6te",
    "addr:street":"Park Rd",
    "iso:country":"GB",
    "sg:address":"110b Park Rd",
    "sg:city":"Altrincham",
    "sg:classifiers":[
        {
            "category":"Deli",
            "type":"Food & Drink"
        }
    ],
    "sg:postcode":"WA15 6TE",
    "sg:province":"Cheshire",
    "sg:tags":[
        "delivery",
        "sandwich"
    ],
    "wof:name":"Torbati,H,",
    "wof:placetype":"venue"
},
  "geometry": {"coordinates":[-2.336448,53.4034],"type":"Point"}
}