{
  "type": "Feature",
  "properties": {
    "addr:full":"Lemon Tree Rest Home, 133 Hornby Road Blackpool Lancashire FY1 4JG",
    "addr:housenumber":"133",
    "addr:postcode":"fy1 4jg",
    "addr:street":"Hornby Road",
    "iso:country":"GB",
    "sg:address":"Lemon Tree Rest Home, 133 Hornby Road",
    "sg:city":"Blackpool",
    "sg:classifiers":[
        {
            "category":"Social Services",
            "subcategory":"Retirement Home",
            "type":"Services"
        }
    ],
    "sg:phone":"+44 1253 621463",
    "sg:postcode":"FY1 4JG",
    "sg:province":"Lancashire",
    "sg:tags":[
        "rest"
    ],
    "wof:name":"Lemon Tree Rest Home",
    "wof:placetype":"venue"
},
  "geometry": {"coordinates":[-3.043921,53.815113],"type":"Point"}
}