{
  "type": "Feature",
  "properties": {
    "iso:country":"GB",
    "sg:address":"100 Park Lane",
    "sg:city":"Croydon",
    "sg:classifiers":[
        {
            "category":"Real Estate",
            "subcategory":"Real Estate Agent",
            "type":"Services"
        }
    ],
    "sg:phone":"+44 20 8649 9292",
    "sg:postcode":"CR0 1JB",
    "sg:province":"Surrey",
    "wof:name":"Frost Commercial",
    "wof:placetype":"venue"
},
  "geometry": {"coordinates":[-0.096429,51.367741],"type":"Point"}
}