{
  "type": "Feature",
  "properties": {
    "iso:country":"GB",
    "sg:address":"Mission Works, Mission Street",
    "sg:city":"Brighouse",
    "sg:classifiers":[
        {
            "category":"Home & Garden",
            "subcategory":"Hardware",
            "type":"Retail Goods"
        }
    ],
    "sg:phone":"+44 1422 370766",
    "sg:postcode":"HD6 1NQ",
    "sg:province":"West Yorkshire",
    "sg:tags":[
        "fixing",
        "nuts",
        "bolt"
    ],
    "wof:name":"Nolan Snacks Ltd.",
    "wof:placetype":"venue"
},
  "geometry": {"coordinates":[-1.773737,53.702194],"type":"Point"}
}