{
  "type": "Feature",
  "properties": {
    "iso:country":"GB",
    "sg:address":"Killigrew Street",
    "sg:city":"Falmouth",
    "sg:classifiers":[
        {
            "category":"Food & Beverages",
            "subcategory":"Supermarket",
            "type":"Retail Goods"
        }
    ],
    "sg:phone":"+44 1326 437400",
    "sg:postcode":"TR11 3PQ",
    "sg:province":"Cornwall",
    "wof:name":"Tesco Stores Ltd.",
    "wof:placetype":"venue"
},
  "geometry": {"coordinates":[-5.0715479851,50.1557350159],"type":"Point"}
}