{
  "type": "Feature",
  "properties": {
    "addr:full":"Kent House, Romney Place Maidstone Kent ME15 6JT",
    "addr:postcode":"me15 6jt",
    "addr:street":"Romney Place",
    "iso:country":"GB",
    "sg:address":"Kent House, Romney Place",
    "sg:city":"Maidstone",
    "sg:classifiers":[
        {
            "category":"Banks & Credit Unions",
            "subcategory":"Financial Services",
            "type":"Services"
        }
    ],
    "sg:phone":"+44 1622 690712",
    "sg:postcode":"ME15 6JT",
    "sg:province":"Kent",
    "sg:tags":[
        "consultant"
    ],
    "wof:name":"Welcome Financial Services",
    "wof:placetype":"venue"
},
  "geometry": {"coordinates":[0.5257850289,51.271648407],"type":"Point"}
}