{
  "type": "Feature",
  "properties": {
    "iso:country":"GB",
    "sg:address":"84 The Broadway",
    "sg:city":"Chesham",
    "sg:classifiers":[
        {
            "category":"Professional",
            "subcategory":"Management & Consulting",
            "type":"Services"
        }
    ],
    "sg:phone":"+44 1494 793233",
    "sg:postcode":"HP5 1EG",
    "sg:province":"Buckinghamshire",
    "sg:tags":[
        "consultant",
        "promotion",
        "direct",
        "sale"
    ],
    "wof:name":"Millennium Superstore Ltd.",
    "wof:placetype":"venue"
},
  "geometry": {"coordinates":[-0.612114,51.706348],"type":"Point"}
}