{
  "type": "Feature",
  "properties": {
    "iso:country":"GB",
    "sg:address":"Unit 10 Botany Commercial Park, Botany Avenue",
    "sg:city":"Mansfield",
    "sg:classifiers":[
        {
            "category":"Real Estate",
            "subcategory":"Architect",
            "type":"Services"
        }
    ],
    "sg:phone":"+44 1623 489689",
    "sg:postcode":"NG18 5NF",
    "sg:province":"Nottinghamshire",
    "sg:tags":[
        "architectural"
    ],
    "wof:name":"Jarvis Stone Developments Ltd.",
    "wof:placetype":"venue"
},
  "geometry": {"coordinates":[-1.211534,53.142021],"type":"Point"}
}