{
  "type": "Feature",
  "properties": {
    "addr:full":"21 Congreve Close Warwick Warwickshire CV34 5RQ",
    "addr:housenumber":"21",
    "addr:postcode":"cv34 5rq",
    "addr:street":"Congreve Close",
    "iso:country":"GB",
    "sg:address":"21 Congreve Close",
    "sg:city":"Warwick",
    "sg:classifiers":[
        {
            "category":"Communications",
            "type":"Services"
        }
    ],
    "sg:postcode":"CV34 5RQ",
    "sg:province":"Warwickshire",
    "sg:tags":[
        "telecommunication",
        "audio-visual"
    ],
    "wof:name":"D B I Communication",
    "wof:placetype":"venue"
},
  "geometry": {"coordinates":[-1.5823309422,52.2978744507],"type":"Point"}
}