{
  "type": "Feature",
  "properties": {
    "iso:country":"GB",
    "sg:address":"38a Roundstone St",
    "sg:city":"Trowbridge",
    "sg:classifiers":[
        {
            "category":"Health Services",
            "subcategory":"Dentist",
            "type":"Services"
        }
    ],
    "sg:phone":"+44 1225 760045",
    "sg:postcode":"BA14 8DE",
    "sg:province":"Wiltshire",
    "wof:name":"R.M Thomson",
    "wof:placetype":"venue"
},
  "geometry": {"coordinates":[-2.2053639889,51.3212165833],"type":"Point"}
}