{
  "type": "Feature",
  "properties": {
    "iso:country":"GB",
    "sg:address":"25-26 Kenynon Street",
    "sg:city":"Birmingham",
    "sg:classifiers":[
        {
            "category":"Manufacturing",
            "subcategory":"Jewelry",
            "type":"Manufacturing & Wholesale Goods"
        }
    ],
    "sg:phone":"+44 121 236 8443",
    "sg:postcode":"B18 6AR",
    "sg:province":"West Midlands",
    "sg:tags":[
        "repair",
        "jewellery"
    ],
    "wof:name":"David Charles",
    "wof:placetype":"venue"
},
  "geometry": {"coordinates":[-1.908327,52.487549],"type":"Point"}
}