{
  "type": "Feature",
  "properties": {
    "addr:full":"45 Pimlico Road London Greater London SW1W 8NE",
    "addr:housenumber":"45",
    "addr:postcode":"sw1w 8ne",
    "addr:street":"Pimlico Road",
    "iso:country":"GB",
    "sg:address":"45 Pimlico Road",
    "sg:city":"London",
    "sg:classifiers":[
        {
            "category":"Arts & Performance",
            "subcategory":"Art Gallery",
            "type":"Entertainment"
        }
    ],
    "sg:phone":"+44 20 7730 2972",
    "sg:postcode":"SW1W 8NE",
    "sg:province":"Greater London",
    "wof:name":"Chaucer Fine Arts Ltd.",
    "wof:placetype":"venue"
},
  "geometry": {"coordinates":[-0.152449,51.490498],"type":"Point"}
}