{
  "type": "Feature",
  "properties": {
    "addr:full":"198 Gibbons Road, Garswood Wigan Lancashire WN4 0YA",
    "addr:housenumber":"198",
    "addr:postcode":"wn4 0ya",
    "addr:street":"Gibbons Road",
    "iso:country":"GB",
    "sg:address":"198 Gibbons Road, Garswood",
    "sg:city":"Wigan",
    "sg:classifiers":[
        {
            "category":"Building & Trades",
            "subcategory":"Equipment Rental",
            "type":"Services"
        }
    ],
    "sg:phone":"+44 1942 725341",
    "sg:postcode":"WN4 0YA",
    "sg:province":"Lancashire",
    "sg:tags":[
        "hire",
        "centre"
    ],
    "wof:name":"Mabey Hire Ltd.",
    "wof:placetype":"venue"
},
  "geometry": {"coordinates":[-2.664513,53.489227],"type":"Point"}
}