{
  "type": "Feature",
  "properties": {
    "iso:country":"GB",
    "sg:address":"29 Pennywell Road",
    "sg:city":"Edinburgh",
    "sg:classifiers":[
        {
            "category":"Cinema",
            "subcategory":"Movie Rental",
            "type":"Entertainment"
        }
    ],
    "sg:phone":"+44 131 332 8420",
    "sg:postcode":"EH4 4TY",
    "sg:province":"City of Edinburgh",
    "sg:tags":[
        "video",
        "library"
    ],
    "wof:name":"Global Video (Uk)",
    "wof:placetype":"venue"
},
  "geometry": {"coordinates":[-3.2523779869,55.9713134766],"type":"Point"}
}