{
  "type": "Feature",
  "properties": {
    "addr:full":"15 Sheep Lane, Woburn Milton Keynes Bedfordshire MK17 9HD",
    "addr:housenumber":"15",
    "addr:postcode":"mk17 9hd",
    "addr:street":"Sheep Lane",
    "iso:country":"GB",
    "sg:address":"15 Sheep Lane, Woburn",
    "sg:city":"Milton Keynes",
    "sg:classifiers":[
        {
            "category":"Professional",
            "subcategory":"Management & Consulting",
            "type":"Services"
        }
    ],
    "sg:phone":"+44 1525 290922",
    "sg:postcode":"MK17 9HD",
    "sg:province":"Bedfordshire",
    "sg:tags":[
        "consultant",
        "safety"
    ],
    "wof:name":"Safe & Sound Management Consultants Ltd.",
    "wof:placetype":"venue"
},
  "geometry": {"coordinates":[-0.639372,51.976376],"type":"Point"}
}