{
  "type": "Feature",
  "properties": {
    "addr:full":"6 Midland Road Derby Derbyshire DE1 2SN",
    "addr:housenumber":"6",
    "addr:postcode":"de1 2sn",
    "addr:street":"Midland Road",
    "iso:country":"GB",
    "sg:address":"6 Midland Road",
    "sg:city":"Derby",
    "sg:classifiers":[
        {
            "category":"Restaurant",
            "type":"Food & Drink"
        }
    ],
    "sg:phone":"+44 1332 341143",
    "sg:postcode":"DE1 2SN",
    "sg:province":"Derbyshire",
    "wof:name":"Seven Kings of Cyprus",
    "wof:placetype":"venue"
},
  "geometry": {"coordinates":[-1.4667220116,52.9151802063],"type":"Point"}
}