{
  "type": "Feature",
  "properties": {
    "iso:country":"GB",
    "sg:address":"27 Clough Av",
    "sg:city":"Wilmslow",
    "sg:classifiers":[
        {
            "category":"Building & Trades",
            "subcategory":"Construction",
            "type":"Services"
        }
    ],
    "sg:phone":"+44 1625 533471",
    "sg:postcode":"SK9 4BY",
    "sg:province":"Cheshire",
    "sg:tags":[
        "builder"
    ],
    "wof:name":"Evans Home Improvement",
    "wof:placetype":"venue"
},
  "geometry": {"coordinates":[-2.229386,53.339462],"type":"Point"}
}