{
  "type": "Feature",
  "properties": {
    "iso:country":"GB",
    "sg:address":"1 Croft Cotts",
    "sg:city":"Warrington",
    "sg:classifiers":[
        {
            "category":"Building & Trades",
            "subcategory":"Plumbing",
            "type":"Services"
        }
    ],
    "sg:postcode":"WA6 0LZ",
    "sg:province":"Cheshire",
    "sg:tags":[
        "heating"
    ],
    "wof:name":"Robin A Goulbourne",
    "wof:placetype":"venue"
},
  "geometry": {"coordinates":[-2.7761609554,53.2665176392],"type":"Point"}
}