{
  "type": "Feature",
  "properties": {
    "addr:full":"87a Holton Road Barry The Vale of Glamorgan CF63 4HG",
    "addr:housenumber":"87a",
    "addr:postcode":"cf63 4hg",
    "addr:street":"Holton Road;Vale",
    "iso:country":"GB",
    "sg:address":"87a Holton Road",
    "sg:city":"Barry",
    "sg:classifiers":[
        {
            "category":"Professional",
            "subcategory":"Lawyer & Legal Services",
            "type":"Services"
        }
    ],
    "sg:phone":"+44 1446 741919",
    "sg:postcode":"CF63 4HG",
    "sg:province":"The Vale of Glamorgan",
    "sg:tags":[
        "solicitor"
    ],
    "wof:name":"James & Lloyd",
    "wof:placetype":"venue"
},
  "geometry": {"coordinates":[-3.267772913,51.4061393738],"type":"Point"}
}