{
  "type": "Feature",
  "properties": {
    "iso:country":"GB",
    "sg:address":"59 Victoria Road",
    "sg:city":"Diss",
    "sg:classifiers":[
        {
            "category":"Home & Garden",
            "subcategory":"Hardware",
            "type":"Retail Goods"
        }
    ],
    "sg:phone":"+44 1379 651020",
    "sg:postcode":"IP22 4JE",
    "sg:province":"Norfolk",
    "sg:tags":[
        "lawnmowers",
        "machinery"
    ],
    "wof:name":"Michaels Mowers",
    "wof:placetype":"venue"
},
  "geometry": {"coordinates":[1.123255,52.369637],"type":"Point"}
}