{
  "type": "Feature",
  "properties": {
    "addr:full":"1f Ashfield Av Birmingham West Midlands B14 7AT",
    "addr:housenumber":"1f",
    "addr:postcode":"b14 7at",
    "addr:street":"Ashfield Av",
    "iso:country":"GB",
    "sg:address":"1f Ashfield Av",
    "sg:city":"Birmingham",
    "sg:classifiers":[
        {
            "category":"Building & Trades",
            "subcategory":"Plumbing",
            "type":"Services"
        }
    ],
    "sg:phone":"+44 121 441 5371",
    "sg:postcode":"B14 7AT",
    "sg:province":"West Midlands",
    "sg:tags":[
        "heating"
    ],
    "wof:name":"AB Plumbwise",
    "wof:placetype":"venue"
},
  "geometry": {"coordinates":[-1.892011,52.439243],"type":"Point"}
}