{
  "type": "Feature",
  "properties": {
    "iso:country":"GB",
    "sg:address":"79 High Street",
    "sg:city":"Newcastle",
    "sg:classifiers":[
        {
            "category":"Fast Food",
            "type":"Food & Drink"
        }
    ],
    "sg:phone":"+44 1782 710788",
    "sg:postcode":"ST5 6LY",
    "sg:province":"Staffordshire",
    "sg:tags":[
        "away",
        "take"
    ],
    "wof:name":"Chow Dsk Take Away",
    "wof:placetype":"venue"
},
  "geometry": {"coordinates":[-2.268163,53.014984],"type":"Point"}
}