{
  "type": "Feature",
  "properties": {
    "iso:country":"GB",
    "sg:address":"24 The Cent Cres",
    "sg:city":"Lytham St Annes",
    "sg:classifiers":[
        {
            "category":"Retail",
            "subcategory":"Photofinishing",
            "type":"Services"
        }
    ],
    "sg:phone":"+44 1253 721492",
    "sg:postcode":"FY8 1SZ",
    "sg:province":"Lancashire",
    "sg:tags":[
        "photographic",
        "processor"
    ],
    "wof:name":"Fylde Colour Laboratory (1984) Ltd",
    "wof:placetype":"venue"
},
  "geometry": {"coordinates":[-2.991574,53.749516],"type":"Point"}
}