{
  "type": "Feature",
  "properties": {
    "iso:country":"GB",
    "sg:address":"Neville Road, North Tees Industrial Estate",
    "sg:city":"Stockton-on-tees",
    "sg:classifiers":[
        {
            "category":"Manufacturing",
            "subcategory":"Petroleum Products",
            "type":"Manufacturing & Wholesale Goods"
        }
    ],
    "sg:phone":"+44 1642 673500",
    "sg:postcode":"TS18 2RJ",
    "sg:province":"Durham",
    "sg:tags":[
        "double",
        "glazing"
    ],
    "wof:name":"Orchard Windows & Conservatories",
    "wof:placetype":"venue"
},
  "geometry": {"coordinates":[-1.272734046,54.5756950378],"type":"Point"}
}