{
  "type": "Feature",
  "properties": {
    "addr:full":"27 The Street Norwich Norfolk NR14 7RA",
    "addr:housenumber":"27",
    "addr:postcode":"nr14 7ra",
    "addr:street":"The Street",
    "iso:country":"GB",
    "sg:address":"27 The Street",
    "sg:city":"Norwich",
    "sg:classifiers":[
        {
            "category":"Health Services",
            "subcategory":"Dentist",
            "type":"Services"
        }
    ],
    "sg:phone":"+44 1508 494599",
    "sg:postcode":"NR14 7RA",
    "sg:province":"Norfolk",
    "wof:name":"Crosby & Desai",
    "wof:placetype":"venue"
},
  "geometry": {"coordinates":[1.343313,52.573631],"type":"Point"}
}