{
  "type": "Feature",
  "properties": {
    "addr:full":"139 Main St, Sutton Bonington Loughborough Leicestershire LE12 5PE",
    "addr:housenumber":"139",
    "addr:postcode":"le12 5pe",
    "addr:street":"Main St",
    "iso:country":"GB",
    "sg:address":"139 Main St, Sutton Bonington",
    "sg:city":"Loughborough",
    "sg:classifiers":[
        {
            "category":"Shopping",
            "subcategory":"News",
            "type":"Retail Goods"
        }
    ],
    "sg:phone":"+44 1509 672577",
    "sg:postcode":"LE12 5PE",
    "sg:province":"Leicestershire",
    "sg:tags":[
        "newsagent"
    ],
    "wof:name":"B.M Wood",
    "wof:placetype":"venue"
},
  "geometry": {"coordinates":[-1.2542610168,52.8241081238],"type":"Point"}
}