{
  "type": "Feature",
  "properties": {
    "addr:full":"Ebor Works, Chapel Lane, Sands High Wycombe Buckinghamshire HP12 4BS",
    "addr:postcode":"hp12 4bs",
    "addr:street":"Chapel Lane Sands",
    "iso:country":"GB",
    "sg:address":"Ebor Works, Chapel Lane, Sands",
    "sg:city":"High Wycombe",
    "sg:classifiers":[
        {
            "category":"Retail",
            "subcategory":"Auto Repair",
            "type":"Services"
        }
    ],
    "sg:phone":"+44 1494 450088",
    "sg:postcode":"HP12 4BS",
    "sg:province":"Buckinghamshire",
    "sg:tags":[
        "body",
        "car"
    ],
    "wof:name":"Lane & Fulwell Motor Engineers",
    "wof:placetype":"venue"
},
  "geometry": {"coordinates":[-0.7843099833,51.6357192993],"type":"Point"}
}