{
  "type": "Feature",
  "properties": {
    "addr:full":"75 Sunny Blunts Peterlee Durham SR8 1LP",
    "addr:housenumber":"75",
    "addr:postcode":"sr8 1lp",
    "addr:street":"Sunny Blunts",
    "iso:country":"GB",
    "sg:address":"75 Sunny Blunts",
    "sg:city":"Peterlee",
    "sg:classifiers":[
        {
            "category":"Communications",
            "subcategory":"Film & Video Production",
            "type":"Services"
        }
    ],
    "sg:phone":"+44 191 518 1475",
    "sg:postcode":"SR8 1LP",
    "sg:province":"Durham",
    "sg:tags":[
        "recording",
        "studio"
    ],
    "wof:name":"Pete Carney",
    "wof:placetype":"venue"
},
  "geometry": {"coordinates":[-1.3407919407,54.7497367859],"type":"Point"}
}