{
  "type": "Feature",
  "properties": {
    "addr:full":"2 Lickhill Road Calne Wiltshire SN11 9DD",
    "addr:housenumber":"2",
    "addr:postcode":"sn11 9dd",
    "addr:street":"Lickhill Road",
    "iso:country":"GB",
    "sg:address":"2 Lickhill Road",
    "sg:city":"Calne",
    "sg:classifiers":[
        {
            "category":"Social Services",
            "subcategory":"Retirement Home",
            "type":"Services"
        }
    ],
    "sg:postcode":"SN11 9DD",
    "sg:province":"Wiltshire",
    "sg:tags":[
        "residential",
        "care"
    ],
    "wof:name":"The Firs Residential Home",
    "wof:placetype":"venue"
},
  "geometry": {"coordinates":[-2.007319,51.443638],"type":"Point"}
}