{
  "type": "Feature",
  "properties": {
    "addr:full":"Curdridge Lane, Curdridge Southampton Hampshire SO32 2BH",
    "addr:postcode":"so32 2bh",
    "addr:street":"Curdridge Lane",
    "iso:country":"GB",
    "sg:address":"Curdridge Lane, Curdridge",
    "sg:city":"Southampton",
    "sg:classifiers":[
        {
            "category":"Bars & Pubs",
            "type":"Food & Drink"
        }
    ],
    "sg:phone":"+44 1489 784420",
    "sg:postcode":"SO32 2BH",
    "sg:province":"Hampshire",
    "sg:tags":[
        "pubs",
        "inn"
    ],
    "wof:name":"The Cricketers Inn",
    "wof:placetype":"venue"
},
  "geometry": {"coordinates":[-1.2506040335,50.9211807251],"type":"Point"}
}