{
  "type": "Feature",
  "properties": {
    "addr:full":"20 Cheriton Avenue Bournemouth Dorset BH7 6SD",
    "addr:housenumber":"20",
    "addr:postcode":"bh7 6sd",
    "addr:street":"Cheriton Avenue",
    "iso:country":"GB",
    "sg:address":"20 Cheriton Avenue",
    "sg:city":"Bournemouth",
    "sg:classifiers":[
        {
            "category":"Arena",
            "subcategory":"Sports Club",
            "type":"Entertainment"
        }
    ],
    "sg:phone":"+44 1202 424224",
    "sg:postcode":"BH7 6SD",
    "sg:province":"Dorset",
    "wof:name":"European Lifeguard Academy",
    "wof:placetype":"venue"
},
  "geometry": {"coordinates":[-1.814661,50.74147],"type":"Point"}
}