{
  "type": "Feature",
  "properties": {
    "iso:country":"GB",
    "sg:address":"111 Lawsons Road",
    "sg:city":"Thornton-cleveleys",
    "sg:classifiers":[
        {
            "category":"Transit Center",
            "subcategory":"Passenger",
            "type":"Transportation"
        },
        {
            "category":"Building & Trades",
            "subcategory":"Construction",
            "type":"Services"
        },
        {
            "category":"Retail",
            "subcategory":"Pet Boarding",
            "type":"Services"
        }
    ],
    "sg:phone":"+44 1253 823728",
    "sg:postcode":"FY5 4PP",
    "sg:province":"Lancashire",
    "sg:tags":[
        "dry",
        "plasterers",
        "lining",
        "catteries",
        "kennel",
        "screeders"
    ],
    "wof:name":"Thornton Boarding Cattery",
    "wof:placetype":"venue"
},
  "geometry": {"coordinates":[-3.0019359589,53.8762207031],"type":"Point"}
}