{
  "type": "Feature",
  "properties": {
    "addr:full":"278 High St Aldershot Hampshire GU12 4LT",
    "addr:housenumber":"278",
    "addr:postcode":"gu12 4lt",
    "addr:street":"High St",
    "iso:country":"GB",
    "sg:address":"278 High St",
    "sg:city":"Aldershot",
    "sg:classifiers":[
        {
            "category":"Food & Beverages",
            "subcategory":"Meat & Fish",
            "type":"Retail Goods"
        }
    ],
    "sg:postcode":"GU12 4LT",
    "sg:province":"Hampshire",
    "sg:tags":[
        "chip"
    ],
    "wof:name":"Ho's Fish 'N' Chips",
    "wof:placetype":"venue"
},
  "geometry": {"coordinates":[-0.754395,51.245453],"type":"Point"}
}