{
  "type": "Feature",
  "properties": {
    "iso:country":"GB",
    "sg:address":"1 Newlands Shop, Delffordd",
    "sg:city":"Swansea",
    "sg:classifiers":[
        {
            "category":"Fast Food",
            "type":"Food & Drink"
        }
    ],
    "sg:postcode":"SA8 3ED",
    "sg:province":"Neath Port Talbot",
    "sg:tags":[
        "away",
        "take"
    ],
    "wof:name":"Chan,Henry,",
    "wof:placetype":"venue"
},
  "geometry": {"coordinates":[-3.84833,51.718929],"type":"Point"}
}