{
  "type": "Feature",
  "properties": {
    "iso:country":"GB",
    "sg:address":"Old Farm Cottages, Tunstead",
    "sg:city":"Norwich",
    "sg:classifiers":[
        {
            "category":"Travel",
            "subcategory":"Hotels & Motels",
            "type":"Entertainment"
        },
        {
            "category":"Bars & Pubs",
            "subcategory":"Hookah Bar",
            "type":"Food & Drink"
        }
    ],
    "sg:phone":"+44 1692 536612",
    "sg:postcode":"NR12 8HS",
    "sg:province":"Norfolk",
    "sg:tags":[
        "self",
        "holiday",
        "catering"
    ],
    "wof:name":"Old Farm Holiday Cottages",
    "wof:placetype":"venue"
},
  "geometry": {"coordinates":[1.4345599413,52.7575912476],"type":"Point"}
}