{
  "type": "Feature",
  "properties": {
    "iso:country":"GB",
    "sg:address":"22 Bute Walk",
    "sg:city":"Derby",
    "sg:classifiers":[
        {
            "category":"Social Services",
            "type":"Services"
        }
    ],
    "sg:phone":"+44 1332 717477",
    "sg:postcode":"DE21 6BN",
    "sg:province":"Derbyshire",
    "wof:name":"Bute Walk Family Centre",
    "wof:placetype":"venue"
},
  "geometry": {"coordinates":[-1.458429,52.931946],"type":"Point"}
}