{
  "type": "Feature",
  "properties": {
    "addr:full":"5 Evesham Walk, Kingfisher Shopping Centre Redditch Warwickshire B97 4ET",
    "addr:housenumber":"5",
    "addr:postcode":"b97 4et",
    "addr:street":"Evesham Walk;Shopping",
    "iso:country":"GB",
    "sg:address":"5 Evesham Walk, Kingfisher Shopping Centre",
    "sg:city":"Redditch",
    "sg:classifiers":[
        {
            "category":"Shopping",
            "subcategory":"Hobbies, Toys, & Games",
            "type":"Retail Goods"
        }
    ],
    "sg:phone":"+44 1527 591460",
    "sg:postcode":"B97 4ET",
    "sg:province":"Warwickshire",
    "sg:tags":[
        "shop",
        "toy",
        "sale"
    ],
    "sg:website":"http://www.elc.co.uk",
    "wof:name":"Early Learning Centre",
    "wof:placetype":"venue"
},
  "geometry": {"coordinates":[-1.9412670135,52.30727005],"type":"Point"}
}