{
  "type": "Feature",
  "properties": {
    "addr:full":"7 The Hurst, Moseley Birmingham West Midlands B13 0DA",
    "addr:housenumber":"7",
    "addr:postcode":"b13 0da",
    "addr:street":"The Hurst",
    "iso:country":"GB",
    "sg:address":"7 The Hurst, Moseley",
    "sg:city":"Birmingham",
    "sg:classifiers":[
        {
            "category":"Professional",
            "subcategory":"Computer Services",
            "type":"Services"
        }
    ],
    "sg:postcode":"B13 0DA",
    "sg:province":"West Midlands",
    "sg:tags":[
        "system",
        "software"
    ],
    "wof:name":"Enterprise 2000",
    "wof:placetype":"venue"
},
  "geometry": {"coordinates":[-1.8636139631,52.4298362732],"type":"Point"}
}