{
  "type": "Feature",
  "properties": {
    "iso:country":"GB",
    "sg:address":"Manhood Workshop, Brimfast Lane, Sidlesham Common",
    "sg:city":"Chichester",
    "sg:classifiers":[
        {
            "category":"Banks & Credit Unions",
            "subcategory":"Investment Brokerage",
            "type":"Services"
        }
    ],
    "sg:phone":"+44 1243 641561",
    "sg:postcode":"PO20 7PZ",
    "sg:province":"West Sussex",
    "sg:tags":[
        "contractor"
    ],
    "wof:name":"M T Clarkeson Forage Services",
    "wof:placetype":"venue"
},
  "geometry": {"coordinates":[-0.787379,50.776985],"type":"Point"}
}