{
  "type": "Feature",
  "properties": {
    "addr:full":"7a Beaconsfield Road Weston-super-mare Somerset BS23 1YE",
    "addr:housenumber":"7a",
    "addr:postcode":"bs23 1ye",
    "addr:street":"Beaconsfield Road",
    "iso:country":"GB",
    "sg:address":"7a Beaconsfield Road",
    "sg:city":"Weston-super-mare",
    "sg:classifiers":[
        {
            "category":"Organizations",
            "subcategory":"Non-profit Organization",
            "type":"Services"
        }
    ],
    "sg:phone":"+44 1934 629657",
    "sg:postcode":"BS23 1YE",
    "sg:province":"Somerset",
    "sg:tags":[
        "organisation",
        "voluntary",
        "charity"
    ],
    "wof:name":"Weston & District Community Transport Ltd.",
    "wof:placetype":"venue"
},
  "geometry": {"coordinates":[-2.976071,51.344509],"type":"Point"}
}