{
  "type": "Feature",
  "properties": {
    "iso:country":"GB",
    "sg:address":"103a Queensway",
    "sg:city":"Orpington",
    "sg:classifiers":[
        {
            "category":"Restaurant",
            "type":"Food & Drink"
        }
    ],
    "sg:phone":"+44 1689 823691",
    "sg:postcode":"BR5 1DQ",
    "sg:province":"Kent",
    "wof:name":"The Kyrenia Eating House",
    "wof:placetype":"venue"
},
  "geometry": {"coordinates":[0.072513,51.389],"type":"Point"}
}