{
  "type": "Feature",
  "properties": {
    "iso:country":"GB",
    "sg:address":"105 Canons Walk",
    "sg:city":"Thetford",
    "sg:classifiers":[
        {
            "category":"Fast Food",
            "type":"Food & Drink"
        }
    ],
    "sg:phone":"+44 1842 755413",
    "sg:postcode":"IP24 3PT",
    "sg:province":"Norfolk",
    "sg:tags":[
        "away",
        "take"
    ],
    "wof:name":"Nicola Perry",
    "wof:placetype":"venue"
},
  "geometry": {"coordinates":[0.739263,52.413857],"type":"Point"}
}