{
  "type": "Feature",
  "properties": {
    "iso:country":"GB",
    "sg:address":"1923 Lower Bridge Street",
    "sg:city":"Canterbury",
    "sg:classifiers":[
        {
            "category":"Shopping",
            "subcategory":"Bicycles & Sporting Goods",
            "type":"Retail Goods"
        }
    ],
    "sg:phone":"+44 1227 761488",
    "sg:postcode":"CT1 2LG",
    "sg:province":"Kent",
    "sg:tags":[
        "cycle",
        "accessory"
    ],
    "wof:name":"Cyclesmart Ltd.",
    "wof:placetype":"venue"
},
  "geometry": {"coordinates":[1.08134,51.27562],"type":"Point"}
}