{
  "type": "Feature",
  "properties": {
    "addr:full":"P O Box 14, Shirley Solihull West Midlands B90 1PY",
    "addr:housenumber":"box 14",
    "addr:postcode":"b90 1py",
    "addr:street":"P O",
    "iso:country":"GB",
    "sg:address":"P O Box 14, Shirley",
    "sg:city":"Solihull",
    "sg:classifiers":[
        {
            "category":"Professional",
            "subcategory":"Business Services",
            "type":"Services"
        }
    ],
    "sg:postcode":"B90 1PY",
    "sg:province":"West Midlands",
    "sg:tags":[
        "agent",
        "manufacturers'"
    ],
    "wof:name":"Conbat",
    "wof:placetype":"venue"
},
  "geometry": {"coordinates":[-1.85187,52.399502],"type":"Point"}
}