{
  "type": "Feature",
  "properties": {
    "addr:full":"66c Kent Ho Rd Sydenham Greater London SE26 5LF",
    "addr:housenumber":"66c",
    "addr:postcode":"se26 5lf",
    "addr:street":"Kent Ho Rd",
    "iso:country":"GB",
    "sg:address":"66c Kent Ho Rd",
    "sg:city":"Sydenham",
    "sg:classifiers":[
        {
            "category":"Home & Garden",
            "subcategory":"Carpets & Floor Coverings",
            "type":"Retail Goods"
        }
    ],
    "sg:phone":"+44 20 8676 9723",
    "sg:postcode":"SE26 5LF",
    "sg:province":"Greater London",
    "sg:tags":[
        "cleaner",
        "upholstery"
    ],
    "wof:name":"BBC",
    "wof:placetype":"venue"
},
  "geometry": {"coordinates":[-0.0430420004,51.4231719971],"type":"Point"}
}