{
  "type": "Feature",
  "properties": {
    "addr:full":"2 Middle Row Faversham Kent ME13 7AJ",
    "addr:housenumber":"2",
    "addr:postcode":"me13 7aj",
    "addr:street":"Middle Row",
    "iso:country":"GB",
    "sg:address":"2 Middle Row",
    "sg:city":"Faversham",
    "sg:classifiers":[
        {
            "category":"Organizations",
            "subcategory":"Non-profit Organization",
            "type":"Services"
        }
    ],
    "sg:phone":"+44 1795 532766",
    "sg:postcode":"ME13 7AJ",
    "sg:province":"Kent",
    "sg:tags":[
        "organisation",
        "voluntary",
        "charity"
    ],
    "wof:name":"Age Concern",
    "wof:placetype":"venue"
},
  "geometry": {"coordinates":[0.892009,51.316227],"type":"Point"}
}