{
  "type": "Feature",
  "properties": {
    "iso:country":"GB",
    "sg:address":"4 Alness Terr",
    "sg:city":"Hamilton",
    "sg:classifiers":[
        {
            "category":"Shopping",
            "subcategory":"Department Store",
            "type":"Retail Goods"
        },
        {
            "category":"Food & Beverages",
            "subcategory":"Supermarket",
            "type":"Retail Goods"
        }
    ],
    "sg:postcode":"ML3 6TQ",
    "sg:province":"South Lanarkshire",
    "wof:name":"Taylor,Brian,",
    "wof:placetype":"venue"
},
  "geometry": {"coordinates":[-4.047305,55.767887],"type":"Point"}
}