{
  "type": "Feature",
  "properties": {
    "addr:full":"23 Ouse Rd St Ives Cambridgeshire PE27 3FT",
    "addr:housenumber":"23",
    "addr:postcode":"pe27 3ft",
    "addr:street":"Ouse Rd",
    "iso:country":"GB",
    "sg:address":"23 Ouse Rd",
    "sg:city":"St Ives",
    "sg:classifiers":[
        {
            "category":"Professional",
            "subcategory":"Computer Services",
            "type":"Services"
        }
    ],
    "sg:postcode":"PE27 3FT",
    "sg:province":"Cambridgeshire",
    "sg:tags":[
        "system",
        "software"
    ],
    "wof:name":"Mariton Computer Solutions Ltd",
    "wof:placetype":"venue"
},
  "geometry": {"coordinates":[-0.07121,52.340096],"type":"Point"}
}