{
  "type": "Feature",
  "properties": {
    "addr:full":"5 Glenalmond Road, Kenton Harrow Greater London HA3 9JY",
    "addr:housenumber":"5",
    "addr:postcode":"ha3 9jy",
    "addr:street":"Glenalmond Road",
    "iso:country":"GB",
    "sg:address":"5 Glenalmond Road, Kenton",
    "sg:city":"Harrow",
    "sg:classifiers":[
        {
            "category":"Building & Trades",
            "subcategory":"Cleaning & Sanitation",
            "type":"Services"
        }
    ],
    "sg:postcode":"HA3 9JY",
    "sg:province":"Greater London",
    "sg:tags":[
        "commercial"
    ],
    "wof:name":"L R Dellar",
    "wof:placetype":"venue"
},
  "geometry": {"coordinates":[-0.29442,51.591057],"type":"Point"}
}