{
  "type": "Feature",
  "properties": {
    "iso:country":"GB",
    "sg:address":"Cote Green Wine, 45-47 Compstall Rd",
    "sg:city":"Stockport",
    "sg:classifiers":[
        {
            "category":"Food & Beverages",
            "subcategory":"Liquor & Beverages",
            "type":"Retail Goods"
        }
    ],
    "sg:phone":"+44 161 426 0155",
    "sg:postcode":"SK6 5HG",
    "sg:province":"Cheshire",
    "sg:tags":[
        "beer",
        "spirit",
        "wines"
    ],
    "wof:name":"Wine Club",
    "wof:placetype":"venue"
},
  "geometry": {"coordinates":[-2.0565290451,53.4154891968],"type":"Point"}
}