{
  "type": "Feature",
  "properties": {
    "addr:full":"Barton Road, Elsham Brigg Lincolnshire DN20 0LS",
    "addr:postcode":"dn20 0ls",
    "addr:street":"Barton Road;Brigg",
    "iso:country":"GB",
    "sg:address":"Barton Road, Elsham",
    "sg:city":"Brigg",
    "sg:classifiers":[
        {
            "category":"Sports & Exercise",
            "subcategory":"Golf",
            "type":"Entertainment"
        }
    ],
    "sg:phone":"+44 1652 688382",
    "sg:postcode":"DN20 0LS",
    "sg:province":"Lincolnshire",
    "sg:tags":[
        "club",
        "course"
    ],
    "wof:name":"Elsham Golf Club Ltd.",
    "wof:placetype":"venue"
},
  "geometry": {"coordinates":[-0.4407239854,53.5973739624],"type":"Point"}
}