{
  "type": "Feature",
  "properties": {
    "iso:country":"GB",
    "sg:address":"Tan House, Tan House Lane, Navestockside",
    "sg:city":"Brentwood",
    "sg:classifiers":[
        {
            "category":"Retail",
            "subcategory":"Laundry & Dry Cleaning",
            "type":"Services"
        }
    ],
    "sg:phone":"+44 1277 372232",
    "sg:postcode":"CM14 5SN",
    "sg:province":"Essex",
    "sg:tags":[
        "straw",
        "hay"
    ],
    "wof:name":"R & A.R Hoyle",
    "wof:placetype":"venue"
},
  "geometry": {"coordinates":[0.237245,51.644794],"type":"Point"}
}