{
  "type": "Feature",
  "properties": {
    "iso:country":"GB",
    "sg:address":"Baughton Village, Earls Croome",
    "sg:city":"Worcester",
    "sg:classifiers":[
        {
            "category":"Professional",
            "subcategory":"Engineering",
            "type":"Services"
        }
    ],
    "sg:postcode":"WR8 9DQ",
    "sg:province":"Gloucestershire",
    "sg:tags":[
        "agricultural",
        "engineer"
    ],
    "wof:name":"Swinbourne Bros",
    "wof:placetype":"venue"
},
  "geometry": {"coordinates":[-2.192059,52.07851],"type":"Point"}
}