{
  "type": "Feature",
  "properties": {
    "iso:country":"GB",
    "sg:address":"106 Kings Street, Arndale Centre, Stretford",
    "sg:city":"Manchester",
    "sg:classifiers":[
        {
            "category":"Food & Beverages",
            "subcategory":"Groceries & Convenience Stores",
            "type":"Retail Goods"
        }
    ],
    "sg:phone":"+44 161 865 8998",
    "sg:postcode":"M32 9BA",
    "sg:province":"Cheshire",
    "wof:name":"Supascoop",
    "wof:placetype":"venue"
},
  "geometry": {"coordinates":[-2.327473,53.449219],"type":"Point"}
}