{
  "type": "Feature",
  "properties": {
    "iso:country":"GB",
    "sg:address":"Flat 33 Abbey Lodge",
    "sg:city":"London",
    "sg:classifiers":[
        {
            "category":"Professional",
            "type":"Services"
        }
    ],
    "sg:phone":"+44 20 7262 2181",
    "sg:postcode":"NW8 7RJ",
    "sg:province":"Greater London",
    "sg:tags":[
        "entertainer"
    ],
    "wof:name":"Aida Foster Ltd.",
    "wof:placetype":"venue"
},
  "geometry": {"coordinates":[-0.16455,51.527939],"type":"Point"}
}