{
  "type": "Feature",
  "properties": {
    "iso:country":"GB",
    "sg:address":"Stoke Rd, Methwold",
    "sg:city":"Thetford",
    "sg:classifiers":[
        {
            "category":"Retail",
            "subcategory":"Funeral Services",
            "type":"Services"
        }
    ],
    "sg:phone":"+44 1366 728467",
    "sg:postcode":"IP26 4PE",
    "sg:province":"Norfolk",
    "wof:name":"T R Bowers",
    "wof:placetype":"venue"
},
  "geometry": {"coordinates":[0.548016,52.522072],"type":"Point"}
}