{
  "type": "Feature",
  "properties": {
    "addr:full":"9 Elm Gro Hayling Island Hampshire PO11 9EA",
    "addr:housenumber":"9",
    "addr:postcode":"po11 9ea",
    "addr:street":"Elm Gro",
    "iso:country":"GB",
    "sg:address":"9 Elm Gro",
    "sg:city":"Hayling Island",
    "sg:classifiers":[
        {
            "category":"Retail",
            "subcategory":"Laundry & Dry Cleaning",
            "type":"Services"
        }
    ],
    "sg:phone":"+44 23 9246 4193",
    "sg:postcode":"PO11 9EA",
    "sg:province":"Hampshire",
    "sg:tags":[
        "alteration"
    ],
    "wof:name":"Cleancare Hayling Island",
    "wof:placetype":"venue"
},
  "geometry": {"coordinates":[-0.977286,50.788425],"type":"Point"}
}