{
  "type": "Feature",
  "properties": {
    "iso:country":"GB",
    "sg:address":"16 Queen St",
    "sg:city":"Blackpool",
    "sg:classifiers":[
        {
            "category":"Shopping",
            "subcategory":"Pets & Pet Supplies",
            "type":"Retail Goods"
        }
    ],
    "sg:phone":"+44 1253 753700",
    "sg:postcode":"FY1 1PD",
    "sg:province":"Lancashire",
    "wof:name":"Magna-cell",
    "wof:placetype":"venue"
},
  "geometry": {"coordinates":[-3.053905,53.820255],"type":"Point"}
}