{
  "type": "Feature",
  "properties": {
    "addr:full":"3 Lewis Street Pembroke Dock Pembrokeshire SA72 6DD",
    "addr:housenumber":"3",
    "addr:postcode":"sa72 6dd",
    "addr:street":"Lewis Street",
    "iso:country":"GB",
    "sg:address":"3 Lewis Street",
    "sg:city":"Pembroke Dock",
    "sg:classifiers":[
        {
            "category":"Bars & Pubs",
            "type":"Food & Drink"
        }
    ],
    "sg:postcode":"SA72 6DD",
    "sg:province":"Pembrokeshire",
    "sg:tags":[
        "pubs",
        "inn"
    ],
    "wof:name":"The Bird in Hand",
    "wof:placetype":"venue"
},
  "geometry": {"coordinates":[-4.941079,51.693439],"type":"Point"}
}