{
  "type": "Feature",
  "properties": {
    "iso:country":"GB",
    "sg:address":"Towerfield Business Park, Fane Road",
    "sg:city":"Benfleet",
    "sg:classifiers":[
        {
            "category":"Building & Trades",
            "subcategory":"Plumbing",
            "type":"Services"
        }
    ],
    "sg:phone":"+44 1268 778133",
    "sg:postcode":"SS7 3NH",
    "sg:province":"Essex",
    "sg:tags":[
        "central",
        "heating"
    ],
    "wof:name":"Castle Point Gas & Heating Co. Ltd.",
    "wof:placetype":"venue"
},
  "geometry": {"coordinates":[0.56264,51.543316],"type":"Point"}
}