{
  "type": "Feature",
  "properties": {
    "addr:full":"159 High Street Honiton Devon EX14 1LJ",
    "addr:housenumber":"159",
    "addr:postcode":"ex14 1lj",
    "addr:street":"High Street",
    "iso:country":"GB",
    "sg:address":"159 High Street",
    "sg:city":"Honiton",
    "sg:classifiers":[
        {
            "category":"Shopping",
            "subcategory":"Antiques",
            "type":"Retail Goods"
        }
    ],
    "sg:phone":"+44 1404 43436",
    "sg:postcode":"EX14 1LJ",
    "sg:province":"Devon",
    "wof:name":"C & S Antiques",
    "wof:placetype":"venue"
},
  "geometry": {"coordinates":[-3.192175,50.79892],"type":"Point"}
}