{
  "type": "Feature",
  "properties": {
    "iso:country":"GB",
    "sg:address":"44 Fore Street",
    "sg:city":"Totnes",
    "sg:classifiers":[
        {
            "category":"Shopping",
            "subcategory":"Bicycles & Sporting Goods",
            "type":"Retail Goods"
        }
    ],
    "sg:phone":"+44 1803 865174",
    "sg:postcode":"TQ9 5RP",
    "sg:province":"Devon",
    "sg:tags":[
        "cycle",
        "accessory"
    ],
    "wof:name":"Hot Pursuit",
    "wof:placetype":"venue"
},
  "geometry": {"coordinates":[-3.685063,50.430981],"type":"Point"}
}