{
  "type": "Feature",
  "properties": {
    "iso:country":"GB",
    "sg:address":"70 Littleworth, Wing",
    "sg:city":"Leighton Buzzard",
    "sg:classifiers":[
        {
            "category":"Social Services",
            "subcategory":"Retirement Home",
            "type":"Services"
        }
    ],
    "sg:phone":"+44 1296 681822",
    "sg:postcode":"LU7 0JX",
    "sg:province":"Bedfordshire",
    "sg:tags":[
        "residential",
        "care"
    ],
    "wof:name":"Alexandria House",
    "wof:placetype":"venue"
},
  "geometry": {"coordinates":[-0.7136290073,51.8978500366],"type":"Point"}
}