{
  "type": "Feature",
  "properties": {
    "addr:full":"83 Church Street Gillingham Kent ME7 1TR",
    "addr:housenumber":"83",
    "addr:postcode":"me7 1tr",
    "addr:street":"Church Street",
    "iso:country":"GB",
    "sg:address":"83 Church Street",
    "sg:city":"Gillingham",
    "sg:classifiers":[
        {
            "category":"Fast Food",
            "type":"Food & Drink"
        }
    ],
    "sg:postcode":"ME7 1TR",
    "sg:province":"Kent",
    "sg:tags":[
        "away",
        "take"
    ],
    "wof:name":"Paul's Fish Bar",
    "wof:placetype":"venue"
},
  "geometry": {"coordinates":[0.5608710051,51.3928489685],"type":"Point"}
}