{
  "type": "Feature",
  "properties": {
    "addr:full":"211 Gleneagles Rd Sunderland Tyne and Wear SR4 8JD",
    "addr:housenumber":"211",
    "addr:postcode":"sr4 8jd",
    "addr:street":"Gleneagles Rd",
    "iso:country":"GB",
    "sg:address":"211 Gleneagles Rd",
    "sg:city":"Sunderland",
    "sg:classifiers":[
        {
            "category":"Government",
            "subcategory":"Office",
            "type":"Public Place"
        }
    ],
    "sg:phone":"+44 191 553 6800",
    "sg:postcode":"SR4 8JD",
    "sg:province":"Tyne and Wear",
    "sg:tags":[
        "local"
    ],
    "wof:name":"Grindon Neighbourhood Office The",
    "wof:placetype":"venue"
},
  "geometry": {"coordinates":[-1.4426170588,54.8868408203],"type":"Point"}
}