{
  "type": "Feature",
  "properties": {
    "iso:country":"GB",
    "sg:address":"10 Chapel Field",
    "sg:city":"Norwich",
    "sg:classifiers":[
        {
            "category":"Professional",
            "subcategory":"Lawyer & Legal Services",
            "type":"Services"
        }
    ],
    "sg:phone":"+44 1493 700407",
    "sg:postcode":"NR13 3LY",
    "sg:province":"Norfolk",
    "sg:tags":[
        "practitioner",
        "insolvency"
    ],
    "wof:name":"Tree N",
    "wof:placetype":"venue"
},
  "geometry": {"coordinates":[1.5694049597,52.5610389709],"type":"Point"}
}