{
  "type": "Feature",
  "properties": {
    "iso:country":"GB",
    "sg:address":"Piccadilly",
    "sg:city":"London",
    "sg:classifiers":[
        {
            "category":"Shopping",
            "subcategory":"Beauty & Cosmetics",
            "type":"Retail Goods"
        }
    ],
    "sg:phone":"+44 20 7494 0485",
    "sg:postcode":"W1J 0DA",
    "sg:province":"Greater London",
    "sg:tags":[
        "product"
    ],
    "wof:name":"The Body Shop",
    "wof:placetype":"venue"
},
  "geometry": {"coordinates":[-0.13516,51.509521],"type":"Point"}
}