{
  "type": "Feature",
  "properties": {
    "addr:full":"10, Rathan Court, 10 Lewes Road Newhaven East Sussex BN9 9RZ",
    "addr:housenumber":"10;10",
    "addr:postcode":"bn9 9rz",
    "addr:street":"Rathan;Lewes Road",
    "iso:country":"GB",
    "sg:address":"10, Rathan Court, 10 Lewes Road",
    "sg:city":"Newhaven",
    "sg:classifiers":[
        {
            "category":"Government",
            "subcategory":"Office",
            "type":"Public Place"
        },
        {
            "category":"Social Services",
            "subcategory":"Adult Care",
            "type":"Services"
        },
        {
            "category":"Social Services",
            "subcategory":"Retirement Home",
            "type":"Services"
        }
    ],
    "sg:phone":"+44 1273 517470",
    "sg:postcode":"BN9 9RZ",
    "sg:province":"East Sussex",
    "sg:tags":[
        "housing",
        "local",
        "accommodation",
        "sheltered"
    ],
    "wof:name":"Rathan Court Sheltered Housing",
    "wof:placetype":"venue"
},
  "geometry": {"coordinates":[0.046404,50.794575],"type":"Point"}
}