{
  "type": "Feature",
  "properties": {
    "iso:country":"GB",
    "sg:address":"Redesmere Rd",
    "sg:city":"Wilmslow",
    "sg:classifiers":[
        {
            "category":"Social Services",
            "subcategory":"Adult Care",
            "type":"Services"
        }
    ],
    "sg:phone":"+44 1625 251251",
    "sg:postcode":"SK9 3RX",
    "sg:province":"Cheshire",
    "sg:tags":[
        "day",
        "centre"
    ],
    "wof:name":"Redesmere Centre",
    "wof:placetype":"venue"
},
  "geometry": {"coordinates":[-2.214886,53.354786],"type":"Point"}
}