{
  "type": "Feature",
  "properties": {
    "addr:full":"Abbey Wood Podiatry Clinic, 124 Mcleod Rd Abbey Wood Greater London SE2 0BS",
    "addr:housenumber":"124",
    "addr:postcode":"se2 0bs",
    "addr:street":"Mcleod Rd",
    "iso:country":"GB",
    "sg:address":"Abbey Wood Podiatry Clinic, 124 Mcleod Rd",
    "sg:city":"Abbey Wood",
    "sg:classifiers":[
        {
            "category":"Health Services",
            "subcategory":"Health Practitioner",
            "type":"Services"
        }
    ],
    "sg:phone":"+44 20 8311 1660",
    "sg:postcode":"SE2 0BS",
    "sg:province":"Greater London",
    "sg:tags":[
        "homoeopathic"
    ],
    "wof:name":"J Usher",
    "wof:placetype":"venue"
},
  "geometry": {"coordinates":[0.113470003,51.4875106812],"type":"Point"}
}