{
  "type": "Feature",
  "properties": {
    "iso:country":"GB",
    "sg:address":"13 Hermitage Road",
    "sg:city":"Hitchin",
    "sg:classifiers":[
        {
            "category":"Home & Garden",
            "subcategory":"Home Furnishings",
            "type":"Retail Goods"
        },
        {
            "category":"Manufacturing",
            "subcategory":"Textiles",
            "type":"Manufacturing & Wholesale Goods"
        }
    ],
    "sg:phone":"+44 1462 631599",
    "sg:postcode":"SG5 1BT",
    "sg:province":"Bedfordshire",
    "sg:tags":[
        "blind",
        "made-up",
        "fitting",
        "curtain"
    ],
    "wof:name":"Peter B Jones",
    "wof:placetype":"venue"
},
  "geometry": {"coordinates":[-0.276359,51.949703],"type":"Point"}
}