{
  "type": "Feature",
  "properties": {
    "iso:country":"GB",
    "sg:address":"Waymills",
    "sg:city":"Whitchurch",
    "sg:classifiers":[
        {
            "category":"Building & Trades",
            "subcategory":"Equipment Rental",
            "type":"Services"
        }
    ],
    "sg:phone":"+44 1948 665149",
    "sg:postcode":"SY13 1RT",
    "sg:province":"Cheshire",
    "sg:tags":[
        "plant",
        "machinery"
    ],
    "wof:name":"Scanlan's Plant Hire",
    "wof:placetype":"venue"
},
  "geometry": {"coordinates":[-2.6712551117,52.9672279358],"type":"Point"}
}