{
  "type": "Feature",
  "properties": {
    "addr:full":"12 High Street Herne Bay Kent CT6 5LH",
    "addr:housenumber":"12",
    "addr:postcode":"ct6 5lh",
    "addr:street":"High Street",
    "iso:country":"GB",
    "sg:address":"12 High Street",
    "sg:city":"Herne Bay",
    "sg:classifiers":[
        {
            "category":"Shopping",
            "subcategory":"Used Merchandise",
            "type":"Retail Goods"
        }
    ],
    "sg:phone":"+44 1227 742625",
    "sg:postcode":"CT6 5LH",
    "sg:province":"Kent",
    "sg:tags":[
        "shop",
        "second-hand"
    ],
    "wof:name":"Herne Bay Trading Post",
    "wof:placetype":"venue"
},
  "geometry": {"coordinates":[1.121858,51.370975],"type":"Point"}
}