{
  "type": "Feature",
  "properties": {
    "addr:full":"Beaver House, 125 Portland Street Manchester Greater Manchester M1 4QD",
    "addr:housenumber":"125",
    "addr:postcode":"m1 4qd",
    "addr:street":"Portland Street",
    "iso:country":"GB",
    "sg:address":"Beaver House, 125 Portland Street",
    "sg:city":"Manchester",
    "sg:classifiers":[
        {
            "category":"Insurance",
            "subcategory":"Insurance Agent",
            "type":"Services"
        }
    ],
    "sg:phone":"+44 161 237 8275",
    "sg:postcode":"M1 4QD",
    "sg:province":"Greater Manchester",
    "sg:tags":[
        "broker"
    ],
    "wof:name":"THE STANDARD LIFE ASSURANCE COMPANY 2006",
    "wof:placetype":"venue"
},
  "geometry": {"coordinates":[-2.241467,53.47657],"type":"Point"}
}