{
  "type": "Feature",
  "properties": {
    "addr:full":"Cedar Way, Gurnos Estate Merthyr Tydfil Merthyr Tydfil CF47 9PA",
    "addr:postcode":"cf47 9pa",
    "addr:street":"Cedar Way;Tydfil",
    "iso:country":"GB",
    "sg:address":"Cedar Way, Gurnos Estate",
    "sg:city":"Merthyr Tydfil",
    "sg:classifiers":[
        {
            "category":"Education",
            "subcategory":"School",
            "type":"Public Place"
        }
    ],
    "sg:phone":"+44 1685 721741",
    "sg:postcode":"CF47 9PA",
    "sg:province":"Merthyr Tydfil",
    "sg:tags":[
        "local",
        "authority"
    ],
    "wof:name":"St.Aloysius R C Primary School",
    "wof:placetype":"venue"
},
  "geometry": {"coordinates":[-3.383286,51.759747],"type":"Point"}
}