{
  "type": "Feature",
  "properties": {
    "iso:country":"GB",
    "sg:address":"82 High Street",
    "sg:city":"Dunmow",
    "sg:classifiers":[
        {
            "category":"Social Services",
            "type":"Services"
        },
        {
            "category":"Health Services",
            "subcategory":"Nursing And Care Facility",
            "type":"Services"
        }
    ],
    "sg:phone":"+44 1371 873433",
    "sg:postcode":"CM6 1AP",
    "sg:province":"Essex",
    "sg:tags":[
        "home",
        "disability"
    ],
    "wof:name":"Blue Pear Care Services",
    "wof:placetype":"venue"
},
  "geometry": {"coordinates":[0.365595,51.869762],"type":"Point"}
}