{
  "type": "Feature",
  "properties": {
    "iso:country":"GB",
    "sg:address":"1st Floor, Linksfield Academy, King Street",
    "sg:city":"Aberdeen",
    "sg:classifiers":[
        {
            "category":"Education",
            "subcategory":"Preschool",
            "type":"Public Place"
        },
        {
            "category":"Community Center",
            "subcategory":"Youth",
            "type":"Public Place"
        }
    ],
    "sg:phone":"+44 1224 483187",
    "sg:postcode":"AB24 5SS",
    "sg:province":"Aberdeen City",
    "sg:tags":[
        "children's",
        "pre-school",
        "playgroups",
        "activity"
    ],
    "wof:name":"Seaton Links After School Club",
    "wof:placetype":"venue"
},
  "geometry": {"coordinates":[-2.095164,57.162254],"type":"Point"}
}