{
  "type": "Feature",
  "properties": {
    "iso:country":"GB",
    "sg:address":"43 High Street",
    "sg:city":"Pershore",
    "sg:classifiers":[
        {
            "category":"Shopping",
            "subcategory":"Comic Books",
            "type":"Retail Goods"
        }
    ],
    "sg:postcode":"WR10 1EU",
    "sg:province":"Worcestershire",
    "sg:tags":[
        "jeweller"
    ],
    "wof:name":"Nilsen Jewellers",
    "wof:placetype":"venue"
},
  "geometry": {"coordinates":[-2.0754508972,52.1115341187],"type":"Point"}
}