{
  "type": "Feature",
  "properties": {
    "iso:country":"GB",
    "sg:address":"269 Warwick Road",
    "sg:city":"Carlisle",
    "sg:classifiers":[
        {
            "category":"Personal",
            "subcategory":"Beauty Salon",
            "type":"Services"
        }
    ],
    "sg:phone":"+44 1228 524037",
    "sg:postcode":"CA1 1LJ",
    "sg:province":"Cumbria",
    "sg:tags":[
        "unisex",
        "lady",
        "hairdresser"
    ],
    "wof:name":"Glenlorn Hair Fashions",
    "wof:placetype":"venue"
},
  "geometry": {"coordinates":[-2.913631,54.894646],"type":"Point"}
}