{
  "type": "Feature",
  "properties": {
    "addr:full":"High Trees, Manor Road Hayling Island Hampshire PO11 0QH",
    "addr:postcode":"po11 0qh",
    "addr:street":"Manor Road",
    "iso:country":"GB",
    "sg:address":"High Trees, Manor Road",
    "sg:city":"Hayling Island",
    "sg:classifiers":[
        {
            "category":"Building & Trades",
            "subcategory":"Pest Control",
            "type":"Services"
        }
    ],
    "sg:postcode":"PO11 0QH",
    "sg:province":"Hampshire",
    "sg:tags":[
        "vermin"
    ],
    "wof:name":"R E Blanks Pest Control",
    "wof:placetype":"venue"
},
  "geometry": {"coordinates":[-0.977634,50.831841],"type":"Point"}
}