{
  "type": "Feature",
  "properties": {
    "addr:full":"33 Dudley Street Grimsby Lincolnshire DN31 2AW",
    "addr:housenumber":"33",
    "addr:postcode":"dn31 2aw",
    "addr:street":"Dudley Street",
    "iso:country":"GB",
    "sg:address":"33 Dudley Street",
    "sg:city":"Grimsby",
    "sg:classifiers":[
        {
            "category":"Shopping",
            "subcategory":"Antiques",
            "type":"Retail Goods"
        }
    ],
    "sg:phone":"+44 1472 356622",
    "sg:postcode":"DN31 2AW",
    "sg:province":"Lincolnshire",
    "wof:name":"Old Dock Antiques",
    "wof:placetype":"venue"
},
  "geometry": {"coordinates":[-0.095864,53.563622],"type":"Point"}
}