{
  "type": "Feature",
  "properties": {
    "addr:full":"8 The Quay Bideford Devon EX39 2HW",
    "addr:housenumber":"8",
    "addr:postcode":"ex39 2hw",
    "addr:street":"The Quay",
    "iso:country":"GB",
    "sg:address":"8 The Quay",
    "sg:city":"Bideford",
    "sg:classifiers":[
        {
            "category":"Professional",
            "subcategory":"Employment Agencies",
            "type":"Services"
        }
    ],
    "sg:postcode":"EX39 2HW",
    "sg:province":"Devon",
    "sg:tags":[
        "consultant"
    ],
    "wof:name":"North Devon Employment Agency",
    "wof:placetype":"venue"
},
  "geometry": {"coordinates":[-4.204914,51.017639],"type":"Point"}
}