{
  "type": "Feature",
  "properties": {
    "iso:country":"GB",
    "sg:address":"38 Water Ditchampton, Wilton",
    "sg:city":"Salisbury",
    "sg:classifiers":[
        {
            "category":"Personal",
            "subcategory":"Adult",
            "type":"Services"
        }
    ],
    "sg:postcode":"SP2 0JB",
    "sg:province":"Wiltshire",
    "sg:tags":[
        "equestrian"
    ],
    "wof:name":"M W Hewlett & R Alford",
    "wof:placetype":"venue"
},
  "geometry": {"coordinates":[-1.870477,51.085678],"type":"Point"}
}