{
  "type": "Feature",
  "properties": {
    "addr:full":"34 Heathhurst Rd South Croydon Surrey CR2 0BA",
    "addr:housenumber":"34",
    "addr:postcode":"cr2 0ba",
    "addr:street":"Heathhurst Rd",
    "iso:country":"GB",
    "sg:address":"34 Heathhurst Rd",
    "sg:city":"South Croydon",
    "sg:classifiers":[
        {
            "category":"Wholesale",
            "subcategory":"Books, Periodicals, & Newspapers",
            "type":"Manufacturing & Wholesale Goods"
        }
    ],
    "sg:phone":"+44 20 8651 4844",
    "sg:postcode":"CR2 0BA",
    "sg:province":"Surrey",
    "sg:tags":[
        "publishing"
    ],
    "wof:name":"Legal World Communications Ltd",
    "wof:placetype":"venue"
},
  "geometry": {"coordinates":[-0.093061,51.346752],"type":"Point"}
}