{
  "type": "Feature",
  "properties": {
    "iso:country":"GB",
    "sg:address":"2 Bibury Close, Woodley",
    "sg:city":"Reading",
    "sg:classifiers":[
        {
            "category":"Professional",
            "subcategory":"Management & Consulting",
            "type":"Services"
        }
    ],
    "sg:phone":"+44 118 944 1520",
    "sg:postcode":"RG5 3PE",
    "sg:province":"Berkshire",
    "sg:tags":[
        "consultant",
        "business"
    ],
    "wof:name":"Saxton Contracts Consultancy Ltd.",
    "wof:placetype":"venue"
},
  "geometry": {"coordinates":[-0.908302,51.441784],"type":"Point"}
}