{
  "type": "Feature",
  "properties": {
    "addr:full":"Station Road Industrial Estate, Station Road Nuneaton Leicestershire CV13 0PE",
    "addr:postcode":"cv13 0pe",
    "addr:street":"Station Road Industrial Estate Station Road",
    "iso:country":"GB",
    "sg:address":"Station Road Industrial Estate, Station Road",
    "sg:city":"Nuneaton",
    "sg:classifiers":[
        {
            "category":"Professional",
            "subcategory":"Engineering",
            "type":"Services"
        }
    ],
    "sg:phone":"+44 1455 291313",
    "sg:postcode":"CV13 0PE",
    "sg:province":"Leicestershire",
    "sg:tags":[
        "precision",
        "engineer"
    ],
    "wof:name":"James Star Ltd.",
    "wof:placetype":"venue"
},
  "geometry": {"coordinates":[-1.411946,52.624763],"type":"Point"}
}