{
  "type": "Feature",
  "properties": {
    "addr:full":"Beck House, Barrow Haven Barrow-upon-humber Lincolnshire DN19 7EX",
    "addr:postcode":"dn19 7ex",
    "addr:street":"Barrow;Barrow-Upon-Humber",
    "iso:country":"GB",
    "sg:address":"Beck House, Barrow Haven",
    "sg:city":"Barrow-upon-humber",
    "sg:classifiers":[
        {
            "category":"Professional",
            "subcategory":"Engineering",
            "type":"Services"
        }
    ],
    "sg:postcode":"DN19 7EX",
    "sg:province":"Lincolnshire",
    "sg:tags":[
        "electronic",
        "engineer"
    ],
    "wof:name":"Keith Dye",
    "wof:placetype":"venue"
},
  "geometry": {"coordinates":[-0.3818379939,53.6750106812],"type":"Point"}
}