{
  "type": "Feature",
  "properties": {
    "iso:country":"GB",
    "sg:address":"4 Warwick Parade, South Woodham Ferrers",
    "sg:city":"Chelmsford",
    "sg:classifiers":[
        {
            "category":"Personal",
            "subcategory":"Beauty Salon",
            "type":"Services"
        }
    ],
    "sg:phone":"+44 1245 321421",
    "sg:postcode":"CM3 5JT",
    "sg:province":"Essex",
    "sg:tags":[
        "unisex",
        "hairdresser"
    ],
    "wof:name":"Apollo 2 Hair Design & Beauty",
    "wof:placetype":"venue"
},
  "geometry": {"coordinates":[0.60922,51.649181],"type":"Point"}
}