{
  "type": "Feature",
  "properties": {
    "addr:full":"Unit 22 23 Harbour Rd Inverness Highland IV1 1UA",
    "addr:housenumber":"unit;23",
    "addr:postcode":"iv1 1ua",
    "addr:street":"Harbour Rd",
    "iso:country":"GB",
    "sg:address":"Unit 22 23 Harbour Rd",
    "sg:city":"Inverness",
    "sg:classifiers":[
        {
            "category":"Communications",
            "subcategory":"Newspaper",
            "type":"Services"
        }
    ],
    "sg:phone":"+44 1387 266088",
    "sg:postcode":"IV1 1UA",
    "sg:province":"Highland",
    "sg:tags":[
        "magazine"
    ],
    "wof:name":"Scottish Supermart",
    "wof:placetype":"venue"
},
  "geometry": {"coordinates":[-4.222722,57.485767],"type":"Point"}
}