{
  "type": "Feature",
  "properties": {
    "iso:country":"GB",
    "sg:address":"151-153 Folkstone Road, Dover Business Cntr",
    "sg:city":"Dover",
    "sg:classifiers":[
        {
            "category":"Social Services",
            "subcategory":"Retirement Home",
            "type":"Services"
        }
    ],
    "sg:phone":"+44 1304 242363",
    "sg:postcode":"CT17 9EJ",
    "sg:province":"Kent",
    "sg:tags":[
        "residential",
        "care"
    ],
    "wof:name":"Robinia Care South East Ltd.",
    "wof:placetype":"venue"
},
  "geometry": {"coordinates":[1.300937,51.124115],"type":"Point"}
}