{
  "type": "Feature",
  "properties": {
    "addr:full":"Unit 5a, Tern Valley Buss Park Market Drayton Shropshire TF9 3SQ",
    "addr:housenumber":"unit 5a",
    "addr:postcode":"tf9 3sq",
    "addr:street":"Tern Valley Buss Park",
    "iso:country":"GB",
    "sg:address":"Unit 5a, Tern Valley Buss Park",
    "sg:city":"Market Drayton",
    "sg:classifiers":[
        {
            "category":"Home & Garden",
            "subcategory":"Hardware",
            "type":"Retail Goods"
        },
        {
            "category":"Home & Garden",
            "subcategory":"Carpets & Floor Coverings",
            "type":"Retail Goods"
        }
    ],
    "sg:phone":"+44 1630 656595",
    "sg:postcode":"TF9 3SQ",
    "sg:province":"Shropshire",
    "sg:tags":[
        "device",
        "fixing",
        "fastener"
    ],
    "wof:name":"Trent Fasteners & Fixings Ltd",
    "wof:placetype":"venue"
},
  "geometry": {"coordinates":[-2.486172,52.904091],"type":"Point"}
}