{
  "type": "Feature",
  "properties": {
    "iso:country":"GB",
    "sg:address":"Priory Mill, West Street",
    "sg:city":"Wells",
    "sg:classifiers":[
        {
            "category":"Shopping",
            "subcategory":"Used Merchandise",
            "type":"Retail Goods"
        }
    ],
    "sg:postcode":"BA5 2HL",
    "sg:province":"Somerset",
    "sg:tags":[
        "furniture"
    ],
    "wof:name":"Wells Trading Post",
    "wof:placetype":"venue"
},
  "geometry": {"coordinates":[-2.645954,51.211349],"type":"Point"}
}