{
  "type": "Feature",
  "properties": {
    "iso:country":"GB",
    "sg:address":"4 Sawmill Lane, Meadowfield",
    "sg:city":"Durham",
    "sg:classifiers":[
        {
            "category":"Shopping",
            "subcategory":"Pharmacy",
            "type":"Retail Goods"
        }
    ],
    "sg:phone":"+44 191 378 0033",
    "sg:postcode":"DH7 8BJ",
    "sg:province":"Durham",
    "sg:tags":[
        "pharmacist",
        "chemist"
    ],
    "wof:name":"M & M Chemist",
    "wof:placetype":"venue"
},
  "geometry": {"coordinates":[-1.6391400099,54.7529373169],"type":"Point"}
}