{
  "type": "Feature",
  "properties": {
    "iso:country":"GB",
    "sg:address":"Adair Road",
    "sg:city":"Ipswich",
    "sg:classifiers":[
        {
            "category":"Shopping",
            "subcategory":"News",
            "type":"Retail Goods"
        },
        {
            "category":"Government",
            "subcategory":"Post Office",
            "type":"Public Place"
        }
    ],
    "sg:phone":"+44 1473 462308",
    "sg:postcode":"IP1 5BD",
    "sg:province":"Suffolk",
    "sg:tags":[
        "newsagent"
    ],
    "wof:name":"Adair Road Sub Post Office",
    "wof:placetype":"venue"
},
  "geometry": {"coordinates":[1.1180100441,52.0691452026],"type":"Point"}
}