{
  "type": "Feature",
  "properties": {
    "iso:country":"GB",
    "sg:address":"12 Esthers Lane, Weaverham",
    "sg:city":"Northwich",
    "sg:classifiers":[
        {
            "category":"Building & Trades",
            "subcategory":"Construction",
            "type":"Services"
        }
    ],
    "sg:phone":"+44 1606 852431",
    "sg:postcode":"CW8 3JR",
    "sg:province":"Cheshire",
    "sg:tags":[
        "contractor",
        "paving",
        "driveway"
    ],
    "wof:name":"Franks Paving & Fencing",
    "wof:placetype":"venue"
},
  "geometry": {"coordinates":[-2.5730950832,53.2613563538],"type":"Point"}
}