{
  "type": "Feature",
  "properties": {
    "iso:country":"GB",
    "sg:address":"12 Darley Road",
    "sg:city":"Ferndown",
    "sg:classifiers":[
        {
            "category":"Professional",
            "subcategory":"Accounting & Tax Preparation",
            "type":"Services"
        }
    ],
    "sg:postcode":"BH22 8QX",
    "sg:province":"Dorset",
    "sg:tags":[
        "accountant"
    ],
    "wof:name":"B & D M Services",
    "wof:placetype":"venue"
},
  "geometry": {"coordinates":[-1.897341,50.791691],"type":"Point"}
}