{
  "type": "Feature",
  "properties": {
    "addr:full":"Time Square Southernhay Basildon Essex SS14 1DJ",
    "addr:postcode":"ss14 1dj",
    "addr:street":"Southernhay Basildon",
    "iso:country":"GB",
    "sg:address":"Time Square Southernhay",
    "sg:city":"Basildon",
    "sg:classifiers":[
        {
            "category":"Farming",
            "subcategory":"Dairy Farm",
            "type":"Manufacturing & Wholesale Goods"
        }
    ],
    "sg:phone":"+44 1268 522613",
    "sg:postcode":"SS14 1DJ",
    "sg:province":"Essex",
    "wof:name":"Dairy Crest Dairies",
    "wof:placetype":"venue"
},
  "geometry": {"coordinates":[0.4537099898,51.5689849854],"type":"Point"}
}