{
  "type": "Feature",
  "properties": {
    "addr:full":"24 Virdin Exchange, High St Winsford Cheshire CW7 2AN",
    "addr:housenumber":"24",
    "addr:postcode":"cw7 2an",
    "addr:street":"Virdin;High St",
    "iso:country":"GB",
    "sg:address":"24 Virdin Exchange, High St",
    "sg:city":"Winsford",
    "sg:classifiers":[
        {
            "category":"Banks & Credit Unions",
            "subcategory":"Financial Services",
            "type":"Services"
        }
    ],
    "sg:phone":"+44 1457 865974",
    "sg:postcode":"CW7 2AN",
    "sg:province":"Cheshire",
    "sg:tags":[
        "claim",
        "assessor"
    ],
    "wof:name":"High Peak Assessors",
    "wof:placetype":"venue"
},
  "geometry": {"coordinates":[-2.5303459167,53.1918144226],"type":"Point"}
}