{
  "type": "Feature",
  "properties": {
    "addr:full":"59 Plungington Rd Preston Lancashire PR1 7EN",
    "addr:housenumber":"59",
    "addr:postcode":"pr1 7en",
    "addr:street":"Plungington Rd",
    "iso:country":"GB",
    "sg:address":"59 Plungington Rd",
    "sg:city":"Preston",
    "sg:classifiers":[
        {
            "category":"Shopping",
            "subcategory":"Pharmacy",
            "type":"Retail Goods"
        }
    ],
    "sg:phone":"+44 1772 556030",
    "sg:postcode":"PR1 7EN",
    "sg:province":"Lancashire",
    "sg:tags":[
        "pharmacist",
        "chemist"
    ],
    "wof:name":"D D L Davies",
    "wof:placetype":"venue"
},
  "geometry": {"coordinates":[-2.711007,53.769527],"type":"Point"}
}