{
  "type": "Feature",
  "properties": {
    "addr:full":"Walsall Road, Darlaston Walsall West Midlands WS10 9SS",
    "addr:postcode":"ws10 9ss",
    "addr:street":"Walsall Road",
    "iso:country":"GB",
    "sg:address":"Walsall Road, Darlaston",
    "sg:city":"Walsall",
    "sg:classifiers":[
        {
            "category":"Autos & Motor Vehicles",
            "subcategory":"Automobile Sales",
            "type":"Retail Goods"
        }
    ],
    "sg:phone":"+44 121 568 3800",
    "sg:postcode":"WS10 9SS",
    "sg:province":"West Midlands",
    "sg:tags":[
        "car"
    ],
    "wof:name":"Hyundaicentre.co.uk",
    "wof:placetype":"venue"
},
  "geometry": {"coordinates":[-2.034454,52.566963],"type":"Point"}
}