{
  "type": "Feature",
  "properties": {
    "addr:full":"50 Dalderse Avenue Falkirk Falkirk FK2 7EG",
    "addr:housenumber":"50",
    "addr:postcode":"fk2 7eg",
    "addr:street":"Dalderse Avenue",
    "iso:country":"GB",
    "sg:address":"50 Dalderse Avenue",
    "sg:city":"Falkirk",
    "sg:classifiers":[
        {
            "category":"Autos & Motor Vehicles",
            "subcategory":"Auto Supplies",
            "type":"Retail Goods"
        }
    ],
    "sg:phone":"+44 1324 621528",
    "sg:postcode":"FK2 7EG",
    "sg:province":"Falkirk",
    "sg:tags":[
        "tyre"
    ],
    "wof:name":"M T S Properties Ltd.",
    "wof:placetype":"venue"
},
  "geometry": {"coordinates":[-3.7814049721,56.0083351135],"type":"Point"}
}