{
  "type": "Feature",
  "properties": {
    "iso:country":"GB",
    "sg:address":"Units 6-9, Edison Road, Elms Farm Industrial Estate",
    "sg:city":"Bedford",
    "sg:classifiers":[
        {
            "category":"Manufacturing",
            "subcategory":"Metals",
            "type":"Manufacturing & Wholesale Goods"
        }
    ],
    "sg:phone":"+44 1234 328678",
    "sg:postcode":"MK41 0HU",
    "sg:province":"Bedfordshire",
    "sg:tags":[
        "work",
        "sheet"
    ],
    "wof:name":"Metco Precision Metalworks Ltd.",
    "wof:placetype":"venue"
},
  "geometry": {"coordinates":[-0.412639,52.148869],"type":"Point"}
}