{
  "type": "Feature",
  "properties": {
    "addr:full":"172 Park Lane West Tipton West Midlands DY4 8LD",
    "addr:housenumber":"172",
    "addr:postcode":"dy4 8ld",
    "addr:street":"Park Lane West Tipton",
    "iso:country":"GB",
    "sg:address":"172 Park Lane West",
    "sg:city":"Tipton",
    "sg:classifiers":[
        {
            "category":"Bars & Pubs",
            "type":"Food & Drink"
        }
    ],
    "sg:phone":"+44 121 520 7502",
    "sg:postcode":"DY4 8LD",
    "sg:province":"West Midlands",
    "sg:tags":[
        "pubs",
        "inn"
    ],
    "wof:name":"The Red Lion",
    "wof:placetype":"venue"
},
  "geometry": {"coordinates":[-2.0697638988,52.5263366699],"type":"Point"}
}