{
  "type": "Feature",
  "properties": {
    "addr:full":"Unit 4 St. Thomas Close Workshops Prudhoe Northumberland NE42 5LU",
    "addr:housenumber":"unit 4",
    "addr:postcode":"workshops;ne42 5lu",
    "addr:street":"St. Thomas Close",
    "iso:country":"GB",
    "sg:address":"Unit 4 St. Thomas Close Workshops",
    "sg:city":"Prudhoe",
    "sg:classifiers":[
        {
            "category":"Bus Charters",
            "type":"Transportation"
        }
    ],
    "sg:phone":"+44 1665 604133",
    "sg:postcode":"NE42 5LU",
    "sg:province":"Northumberland",
    "sg:tags":[
        "hire",
        "coach"
    ],
    "wof:name":"Barrons Minibuses",
    "wof:placetype":"venue"
},
  "geometry": {"coordinates":[-1.850924015,54.9616546631],"type":"Point"}
}