{
  "type": "Feature",
  "properties": {
    "addr:full":"98 The Street Norwich Norfolk NR16 1NA",
    "addr:housenumber":"98",
    "addr:postcode":"nr16 1na",
    "addr:street":"The Street",
    "iso:country":"GB",
    "sg:address":"98 The Street",
    "sg:city":"Norwich",
    "sg:classifiers":[
        {
            "category":"Food & Beverages",
            "subcategory":"Groceries & Convenience Stores",
            "type":"Retail Goods"
        }
    ],
    "sg:postcode":"NR16 1NA",
    "sg:province":"Norfolk",
    "wof:name":"Bunwell's Country Store",
    "wof:placetype":"venue"
},
  "geometry": {"coordinates":[1.150668,52.522308],"type":"Point"}
}