{
  "type": "Feature",
  "properties": {
    "iso:country":"GB",
    "sg:address":"6 Henley Street",
    "sg:city":"Stratford-upon-avon",
    "sg:classifiers":[
        {
            "category":"Home & Garden",
            "subcategory":"Kitchen Supply",
            "type":"Retail Goods"
        }
    ],
    "sg:phone":"+44 1789 292195",
    "sg:postcode":"CV37 6PT",
    "sg:province":"Warwickshire",
    "sg:tags":[
        "glassware",
        "china"
    ],
    "wof:name":"The Crystal Shop",
    "wof:placetype":"venue"
},
  "geometry": {"coordinates":[-1.706971,52.19323],"type":"Point"}
}