{
  "type": "Feature",
  "properties": {
    "addr:full":"Overlee Pavilion, Moray Drive Glasgow East Renfrewshire G76 8NL",
    "addr:postcode":"g76 8nl",
    "addr:street":"Moray Drive",
    "iso:country":"GB",
    "sg:address":"Overlee Pavilion, Moray Drive",
    "sg:city":"Glasgow",
    "sg:classifiers":[
        {
            "category":"Recreation",
            "subcategory":"Dog Park",
            "type":"Entertainment"
        }
    ],
    "sg:postcode":"G76 8NL",
    "sg:province":"East Renfrewshire",
    "wof:name":"Glasgow Obedience Dog Training Club",
    "wof:placetype":"venue"
},
  "geometry": {"coordinates":[-4.2694301605,55.7874794006],"type":"Point"}
}