{
  "type": "Feature",
  "properties": {
    "iso:country":"GB",
    "sg:address":"Unit 1, Jubilee Works, Stickling Grn",
    "sg:city":"Saffron Walden",
    "sg:classifiers":[
        {
            "category":"Retail",
            "subcategory":"Repair Shop",
            "type":"Services"
        },
        {
            "category":"Manufacturing",
            "subcategory":"Furniture",
            "type":"Manufacturing & Wholesale Goods"
        }
    ],
    "sg:phone":"+44 1799 550910",
    "sg:postcode":"CB11 4QX",
    "sg:province":"Essex",
    "sg:tags":[
        "mnfr",
        "upholsterer"
    ],
    "wof:name":"Upholstery Centre",
    "wof:placetype":"venue"
},
  "geometry": {"coordinates":[0.14485,51.973701],"type":"Point"}
}