{
  "type": "Feature",
  "properties": {
    "iso:country":"GB",
    "sg:address":"12-14 Gloddaeth Street",
    "sg:city":"Llandudno",
    "sg:classifiers":[
        {
            "category":"Shopping",
            "subcategory":"News",
            "type":"Retail Goods"
        }
    ],
    "sg:postcode":"LL30 2DS",
    "sg:province":"Conwy",
    "sg:tags":[
        "newsagent"
    ],
    "wof:name":"Nigel Roberts Newsagents",
    "wof:placetype":"venue"
},
  "geometry": {"coordinates":[-3.8327929974,53.3253746033],"type":"Point"}
}