{
  "type": "Feature",
  "properties": {
    "addr:full":"10 Boynton Street Bradford West Yorkshire BD5 7DB",
    "addr:housenumber":"10",
    "addr:postcode":"bd5 7db",
    "addr:street":"Boynton Street",
    "iso:country":"GB",
    "sg:address":"10 Boynton Street",
    "sg:city":"Bradford",
    "sg:classifiers":[
        {
            "category":"Professional",
            "subcategory":"Detective & Security Services",
            "type":"Services"
        }
    ],
    "sg:phone":"+44 1274 726561",
    "sg:postcode":"BD5 7DB",
    "sg:province":"West Yorkshire",
    "sg:tags":[
        "alarm",
        "burglar",
        "system"
    ],
    "wof:name":"Hawk Ltd.",
    "wof:placetype":"venue"
},
  "geometry": {"coordinates":[-1.757726,53.776661],"type":"Point"}
}