{
  "type": "Feature",
  "properties": {
    "addr:full":"53-55 Church Street, Caversham Reading Berkshire RG4 8AX",
    "addr:housenumber":"53-55",
    "addr:postcode":"rg4 8ax",
    "addr:street":"Church Street",
    "iso:country":"GB",
    "sg:address":"53-55 Church Street, Caversham",
    "sg:city":"Reading",
    "sg:classifiers":[
        {
            "category":"Retail",
            "subcategory":"Event Space",
            "type":"Services"
        }
    ],
    "sg:phone":"+44 118 947 2111",
    "sg:postcode":"RG4 8AX",
    "sg:province":"Berkshire",
    "sg:tags":[
        "product",
        "direct"
    ],
    "wof:name":"Motor Warranty Direct Ltd.",
    "wof:placetype":"venue"
},
  "geometry": {"coordinates":[-0.974161,51.467476],"type":"Point"}
}