{
  "type": "Feature",
  "properties": {
    "iso:country":"GB",
    "sg:address":"1 Steyne Road",
    "sg:city":"Bembridge",
    "sg:classifiers":[
        {
            "category":"Travel",
            "subcategory":"Hotels & Motels",
            "type":"Entertainment"
        }
    ],
    "sg:phone":"+44 1983 872875",
    "sg:postcode":"PO35 5UH",
    "sg:province":"Isle of Wight",
    "wof:name":"The Birdham Hotel",
    "wof:placetype":"venue"
},
  "geometry": {"coordinates":[-1.083428,50.685905],"type":"Point"}
}