{
  "type": "Feature",
  "properties": {
    "addr:full":"75 Eltham High St Eltham Greater London SE9 1TD",
    "addr:housenumber":"75",
    "addr:postcode":"se9 1td",
    "addr:street":"Eltham High St",
    "iso:country":"GB",
    "sg:address":"75 Eltham High St",
    "sg:city":"Eltham",
    "sg:classifiers":[
        {
            "category":"Shopping",
            "subcategory":"Clothing, Apparel, & Fashions",
            "type":"Retail Goods"
        }
    ],
    "sg:phone":"+44 20 8859 4898",
    "sg:postcode":"SE9 1TD",
    "sg:province":"Greater London",
    "sg:tags":[
        "menswear"
    ],
    "wof:name":"Direction",
    "wof:placetype":"venue"
},
  "geometry": {"coordinates":[0.0531399995,51.45079422],"type":"Point"}
}