{
  "type": "Feature",
  "properties": {
    "iso:country":"GB",
    "sg:address":"27 Regent Street",
    "sg:city":"Hinckley",
    "sg:classifiers":[
        {
            "category":"Shopping",
            "subcategory":"Comic Books",
            "type":"Retail Goods"
        }
    ],
    "sg:phone":"+44 1455 617625",
    "sg:postcode":"LE10 0AZ",
    "sg:province":"Leicestershire",
    "sg:tags":[
        "jeweller"
    ],
    "wof:name":"Village Jewellery",
    "wof:placetype":"venue"
},
  "geometry": {"coordinates":[-1.374548,52.54063],"type":"Point"}
}