{
  "type": "Feature",
  "properties": {
    "addr:full":"Smallfield Surgery, Wheelers Lane Horley Surrey RH6 9PT",
    "addr:postcode":"rh6 9pt",
    "addr:street":"Wheelers Lane",
    "iso:country":"GB",
    "sg:address":"Smallfield Surgery, Wheelers Lane",
    "sg:city":"Horley",
    "sg:classifiers":[
        {
            "category":"Health Services",
            "subcategory":"Doctor",
            "type":"Services"
        }
    ],
    "sg:phone":"+44 1342 843822",
    "sg:postcode":"RH6 9PT",
    "sg:province":"Surrey",
    "sg:tags":[
        "practitioners"
    ],
    "wof:name":"Terence A Conaty",
    "wof:placetype":"venue"
},
  "geometry": {"coordinates":[-0.116141,51.172573],"type":"Point"}
}