{
  "type": "Feature",
  "properties": {
    "addr:full":"20 High Street Cardigan Ceredigion SA43 1JJ",
    "addr:housenumber":"20",
    "addr:postcode":"sa43 1jj",
    "addr:street":"High Street",
    "iso:country":"GB",
    "sg:address":"20 High Street",
    "sg:city":"Cardigan",
    "sg:classifiers":[
        {
            "category":"Insurance",
            "subcategory":"Insurance Agent",
            "type":"Services"
        },
        {
            "category":"Real Estate",
            "subcategory":"Real Estate Agent",
            "type":"Services"
        }
    ],
    "sg:phone":"+44 1239 613760",
    "sg:postcode":"SA43 1JJ",
    "sg:province":"Ceredigion",
    "sg:tags":[
        "broker"
    ],
    "wof:name":"Sterling Properties",
    "wof:placetype":"venue"
},
  "geometry": {"coordinates":[-4.6612830162,52.0833320618],"type":"Point"}
}