{
  "type": "Feature",
  "properties": {
    "addr:full":"The Square, Mintlaw Peterhead Aberdeenshire AB42 5EH",
    "addr:postcode":"ab42 5eh",
    "addr:street":"The Square Mintlaw",
    "iso:country":"GB",
    "sg:address":"The Square, Mintlaw",
    "sg:city":"Peterhead",
    "sg:classifiers":[
        {
            "category":"Shopping",
            "subcategory":"Pharmacy",
            "type":"Retail Goods"
        }
    ],
    "sg:phone":"+44 1771 623627",
    "sg:postcode":"AB42 5EH",
    "sg:province":"Aberdeenshire",
    "sg:tags":[
        "pharmacist",
        "chemist"
    ],
    "wof:name":"Gordon Maurice Shepherd",
    "wof:placetype":"venue"
},
  "geometry": {"coordinates":[-2.001046,57.52523],"type":"Point"}
}