{
  "type": "Feature",
  "properties": {
    "addr:full":"98-100 Main Street Alexandria Argyll and Bute G83 0PB",
    "addr:housenumber":"98-100",
    "addr:postcode":"g83 0pb",
    "addr:street":"Main Street",
    "iso:country":"GB",
    "sg:address":"98-100 Main Street",
    "sg:city":"Alexandria",
    "sg:classifiers":[
        {
            "category":"Government",
            "subcategory":"Post Office",
            "type":"Public Place"
        }
    ],
    "sg:phone":"+44 1389 752770",
    "sg:postcode":"G83 0PB",
    "sg:province":"Argyll and Bute",
    "wof:name":"Alexandria Post Office",
    "wof:placetype":"venue"
},
  "geometry": {"coordinates":[-4.582406044,55.987827301],"type":"Point"}
}