{
  "type": "Feature",
  "properties": {
    "addr:full":"9 Viking Way, Bar Hill Cambridge Cambridgeshire CB3 8EL",
    "addr:housenumber":"9",
    "addr:postcode":"cb3 8el",
    "addr:street":"Viking Way Bar",
    "iso:country":"GB",
    "sg:address":"9 Viking Way, Bar Hill",
    "sg:city":"Cambridge",
    "sg:classifiers":[
        {
            "category":"Professional",
            "subcategory":"Engineering",
            "type":"Services"
        }
    ],
    "sg:postcode":"CB3 8EL",
    "sg:province":"Cambridgeshire",
    "sg:tags":[
        "precision",
        "engineer"
    ],
    "wof:name":"Metal Technology",
    "wof:placetype":"venue"
},
  "geometry": {"coordinates":[0.016909,52.253613],"type":"Point"}
}