{
  "type": "Feature",
  "properties": {
    "iso:country":"GB",
    "sg:address":"Tyne Brewery, Gallowgate",
    "sg:city":"Newcastle-upon-tyne",
    "sg:classifiers":[
        {
            "category":"Organizations",
            "subcategory":"Non-profit Organization",
            "type":"Services"
        }
    ],
    "sg:phone":"+44 151 794 8800",
    "sg:postcode":"NE99 1RA",
    "sg:province":"Tyne and Wear",
    "sg:tags":[
        "organisation",
        "voluntary",
        "charity"
    ],
    "wof:name":"The Roy Castle Lung Cancer Foundation",
    "wof:placetype":"venue"
},
  "geometry": {"coordinates":[-1.61577,54.967701],"type":"Point"}
}