{
  "type": "Feature",
  "properties": {
    "addr:full":"Bellfield Parade, 27 Brindley Avenue High Wycombe Buckinghamshire HP13 5SX",
    "addr:housenumber":"27",
    "addr:postcode":"hp13 5sx",
    "addr:street":"Bellfield Parade;Brindley Avenue",
    "iso:country":"GB",
    "sg:address":"Bellfield Parade, 27 Brindley Avenue",
    "sg:city":"High Wycombe",
    "sg:classifiers":[
        {
            "category":"Professional",
            "subcategory":"Business Services",
            "type":"Services"
        }
    ],
    "sg:phone":"+44 1494 510511",
    "sg:postcode":"HP13 5SX",
    "sg:province":"Buckinghamshire",
    "sg:tags":[
        "bookmaker"
    ],
    "wof:name":"Taylor Racing",
    "wof:placetype":"venue"
},
  "geometry": {"coordinates":[-0.747789,51.628944],"type":"Point"}
}