{
  "type": "Feature",
  "properties": {
    "addr:full":"Reginald Street Boldon Colliery Tyne and Wear NE35 9DG",
    "addr:postcode":"ne35 9dg",
    "addr:street":"Reginald Street",
    "iso:country":"GB",
    "sg:address":"Reginald Street",
    "sg:city":"Boldon Colliery",
    "sg:classifiers":[
        {
            "category":"Farming",
            "subcategory":"Nursery",
            "type":"Manufacturing & Wholesale Goods"
        },
        {
            "category":"Education",
            "subcategory":"Preschool",
            "type":"Public Place"
        },
        {
            "category":"Government",
            "subcategory":"Office",
            "type":"Public Place"
        }
    ],
    "sg:phone":"+44 191 536 3669",
    "sg:postcode":"NE35 9DG",
    "sg:province":"Tyne and Wear",
    "sg:tags":[
        "local",
        "school",
        "creche"
    ],
    "wof:name":"Boldon Nursery School",
    "wof:placetype":"venue"
},
  "geometry": {"coordinates":[-1.455699,54.949169],"type":"Point"}
}