{
  "type": "Feature",
  "properties": {
    "addr:full":"Units 1-3 Buckland Road Leicester Leicestershire LE5 0NX",
    "addr:housenumber":"units 1-3",
    "addr:postcode":"le5 0nx",
    "addr:street":"Buckland Road",
    "iso:country":"GB",
    "sg:address":"Units 1-3 Buckland Road",
    "sg:city":"Leicester",
    "sg:classifiers":[
        {
            "category":"Manufacturing",
            "subcategory":"Wood Products",
            "type":"Manufacturing & Wholesale Goods"
        }
    ],
    "sg:phone":"+44 116 276 9992",
    "sg:postcode":"LE5 0NX",
    "sg:province":"Leicestershire",
    "sg:tags":[
        "packaging",
        "crate",
        "pallets"
    ],
    "wof:name":"Universal Flexible Packaging Ltd.",
    "wof:placetype":"venue"
},
  "geometry": {"coordinates":[-1.1003199816,52.6453781128],"type":"Point"}
}