{
  "type": "Feature",
  "properties": {
    "addr:full":"133 Main Rd, Naphill High Wycombe Buckinghamshire HP14 4SA",
    "addr:housenumber":"133",
    "addr:postcode":"hp14 4sa",
    "addr:street":"Main Rd Naphill",
    "iso:country":"GB",
    "sg:address":"133 Main Rd, Naphill",
    "sg:city":"High Wycombe",
    "sg:classifiers":[
        {
            "category":"Professional",
            "subcategory":"Printing & Photocopies",
            "type":"Services"
        }
    ],
    "sg:phone":"+44 1494 563631",
    "sg:postcode":"HP14 4SA",
    "sg:province":"Buckinghamshire",
    "sg:tags":[
        "trophy",
        "medal"
    ],
    "wof:name":"R.A McKew",
    "wof:placetype":"venue"
},
  "geometry": {"coordinates":[-0.7808820009,51.6674957275],"type":"Point"}
}