{
  "type": "Feature",
  "properties": {
    "addr:full":"328 Seven Sisters Rd London Greater London N4 2AP",
    "addr:housenumber":"328",
    "addr:postcode":"n4 2ap",
    "addr:street":"Seven Sisters Rd",
    "iso:country":"GB",
    "sg:address":"328 Seven Sisters Rd",
    "sg:city":"London",
    "sg:classifiers":[
        {
            "category":"Travel",
            "subcategory":"Hotels & Motels",
            "type":"Entertainment"
        }
    ],
    "sg:phone":"+44 20 7354 5544",
    "sg:postcode":"N4 2AP",
    "sg:province":"Greater London",
    "wof:name":"Calhurst Ltd",
    "wof:placetype":"venue"
},
  "geometry": {"coordinates":[-0.102109,51.566055],"type":"Point"}
}