{
  "type": "Feature",
  "properties": {
    "iso:country":"GB",
    "sg:address":"24a Queens Road, Hannington",
    "sg:city":"Swindon",
    "sg:classifiers":[
        {
            "category":"Professional",
            "subcategory":"Computer Services",
            "type":"Services"
        }
    ],
    "sg:postcode":"SN6 7RS",
    "sg:province":"Gloucestershire",
    "sg:tags":[
        "system",
        "software"
    ],
    "wof:name":"Eudoxus Ltd",
    "wof:placetype":"venue"
},
  "geometry": {"coordinates":[-1.7484730482,51.6377487183],"type":"Point"}
}