{
  "type": "Feature",
  "properties": {
    "iso:country":"GB",
    "sg:address":"Notte Street",
    "sg:city":"Plymouth",
    "sg:classifiers":[
        {
            "category":"Place Of Worship",
            "type":"Public Place"
        }
    ],
    "sg:phone":"+44 1752 290091",
    "sg:postcode":"PL1 2AQ",
    "sg:province":"Devon",
    "wof:name":"Unitarian Church",
    "wof:placetype":"venue"
},
  "geometry": {"coordinates":[-4.140684,50.368355],"type":"Point"}
}