{
  "type": "Feature",
  "properties": {
    "addr:full":"Scoonie Road Leven Fife KY8 4SB",
    "addr:postcode":"ky8 4sb",
    "addr:street":"Scoonie Road",
    "iso:country":"GB",
    "sg:address":"Scoonie Road",
    "sg:city":"Leven",
    "sg:classifiers":[
        {
            "category":"Shopping",
            "subcategory":"Department Store",
            "type":"Retail Goods"
        }
    ],
    "sg:postcode":"KY8 4SB",
    "sg:province":"Fife",
    "wof:name":"Glen Groceries",
    "wof:placetype":"venue"
},
  "geometry": {"coordinates":[-2.9965839386,56.2025909424],"type":"Point"}
}