{
  "type": "Feature",
  "properties": {
    "addr:full":"Fieldview Cottage, Cumbernauld Glasgow East Dunbartonshire G68 0EA",
    "addr:postcode":"g68 0ea",
    "iso:country":"GB",
    "sg:address":"Fieldview Cottage, Cumbernauld",
    "sg:city":"Glasgow",
    "sg:classifiers":[
        {
            "category":"Professional",
            "type":"Services"
        }
    ],
    "sg:phone":"+44 1236 722152",
    "sg:postcode":"G68 0EA",
    "sg:province":"East Dunbartonshire",
    "sg:tags":[
        "repair",
        "tech",
        "maintenance"
    ],
    "wof:name":"Field Computers",
    "wof:placetype":"venue"
},
  "geometry": {"coordinates":[-4.0153,55.956322],"type":"Point"}
}