{
  "type": "Feature",
  "properties": {
    "iso:country":"GB",
    "sg:address":"15-17 Priory Street",
    "sg:city":"York",
    "sg:classifiers":[
        {
            "category":"Social Services",
            "subcategory":"Child Care",
            "type":"Services"
        },
        {
            "category":"Education",
            "subcategory":"Preschool",
            "type":"Public Place"
        }
    ],
    "sg:phone":"+44 1904 639968",
    "sg:postcode":"YO1 6ET",
    "sg:province":"North Yorkshire",
    "sg:tags":[
        "playgroups",
        "pre-school",
        "creche"
    ],
    "wof:name":"Priory Street Nursery",
    "wof:placetype":"venue"
},
  "geometry": {"coordinates":[-1.087919,53.955109],"type":"Point"}
}