{
  "type": "Feature",
  "properties": {
    "iso:country":"GB",
    "sg:address":"Porth Farm Surgery",
    "sg:city":"Porth",
    "sg:classifiers":[
        {
            "category":"Health Services",
            "subcategory":"Doctor",
            "type":"Services"
        }
    ],
    "sg:phone":"+44 1443 682579",
    "sg:postcode":"CF39 9RR",
    "sg:province":"Bridgend",
    "sg:tags":[
        "practitioners"
    ],
    "wof:name":"Porth Farm Surgery",
    "wof:placetype":"venue"
},
  "geometry": {"coordinates":[-3.410951,51.614983],"type":"Point"}
}