{
  "type": "Feature",
  "properties": {
    "iso:country":"GB",
    "sg:address":"The Old Exchange, West St",
    "sg:city":"Farnham",
    "sg:classifiers":[
        {
            "category":"Real Estate",
            "subcategory":"Architect",
            "type":"Services"
        }
    ],
    "sg:phone":"+44 1252 733774",
    "sg:postcode":"GU9 7AS",
    "sg:province":"Surrey",
    "sg:tags":[
        "architectural"
    ],
    "wof:name":"Ingatrans Ltd",
    "wof:placetype":"venue"
},
  "geometry": {"coordinates":[-0.8008369803,51.2143211365],"type":"Point"}
}