{
  "type": "Feature",
  "properties": {
    "addr:full":"Sydney Road Crewe Cheshire CW1 5LU",
    "addr:postcode":"cw1 5lu",
    "addr:street":"Sydney Road",
    "iso:country":"GB",
    "sg:address":"Sydney Road",
    "sg:city":"Crewe",
    "sg:classifiers":[
        {
            "category":"Arena",
            "subcategory":"Sports Club",
            "type":"Entertainment"
        }
    ],
    "sg:phone":"+44 1270 587739",
    "sg:postcode":"CW1 5LU",
    "sg:province":"Cheshire",
    "wof:name":"Crewe G P O Sports Club",
    "wof:placetype":"venue"
},
  "geometry": {"coordinates":[-2.420279,53.103519],"type":"Point"}
}