{
  "type": "Feature",
  "properties": {
    "iso:country":"GB",
    "sg:address":"Vaughan Rd",
    "sg:city":"Harpenden",
    "sg:classifiers":[
        {
            "category":"Government",
            "subcategory":"Police Station",
            "type":"Public Place"
        }
    ],
    "sg:phone":"+44 1582 768769",
    "sg:postcode":"AL5 4EP",
    "sg:province":"Hertfordshire",
    "sg:tags":[
        "support"
    ],
    "wof:name":"Hertfordshire Constabulary",
    "wof:placetype":"venue"
},
  "geometry": {"coordinates":[-0.353394,51.816093],"type":"Point"}
}