{
  "type": "Feature",
  "properties": {
    "addr:full":"Unit 1 Woodlands Works, Ashcroft Road Liverpool Lancashire L33 7TW",
    "addr:housenumber":"unit 1",
    "addr:postcode":"l33 7tw",
    "addr:street":"Woodlands Works Ashcroft Road",
    "iso:country":"GB",
    "sg:address":"Unit 1 Woodlands Works, Ashcroft Road",
    "sg:city":"Liverpool",
    "sg:classifiers":[
        {
            "category":"Professional",
            "subcategory":"Business Services",
            "type":"Services"
        }
    ],
    "sg:phone":"+44 151 546 6399",
    "sg:postcode":"L33 7TW",
    "sg:province":"Lancashire",
    "sg:tags":[
        "import",
        "export",
        "agent"
    ],
    "wof:name":"Globe International Trading",
    "wof:placetype":"venue"
},
  "geometry": {"coordinates":[-2.8542599678,53.4851112366],"type":"Point"}
}