{
  "type": "Feature",
  "properties": {
    "iso:country":"GB",
    "sg:address":"The Portway, Station App",
    "sg:city":"Frome",
    "sg:classifiers":[
        {
            "category":"Home & Garden",
            "subcategory":"Hardware",
            "type":"Retail Goods"
        }
    ],
    "sg:phone":"+44 1373 467658",
    "sg:postcode":"BA11 1RE",
    "sg:province":"Somerset",
    "sg:tags":[
        "retailer",
        "diy"
    ],
    "wof:name":"Focus",
    "wof:placetype":"venue"
},
  "geometry": {"coordinates":[-2.3188068867,51.2285575867],"type":"Point"}
}