{
  "type": "Feature",
  "properties": {
    "iso:country":"GB",
    "sg:address":"Cotton Lane Veterinary Clinic, Cotton Lane",
    "sg:city":"Bury St Edmunds",
    "sg:classifiers":[
        {
            "category":"Retail",
            "subcategory":"Veterinary Services",
            "type":"Services"
        }
    ],
    "sg:phone":"+44 1284 753961",
    "sg:postcode":"IP33 1XW",
    "sg:province":"Suffolk",
    "sg:tags":[
        "surgeon",
        "activity"
    ],
    "wof:name":"Eastgate Veterinary Group",
    "wof:placetype":"venue"
},
  "geometry": {"coordinates":[0.71709,52.250099],"type":"Point"}
}