{
  "type": "Feature",
  "properties": {
    "iso:country":"GB",
    "sg:address":"67 High Street, Bentley",
    "sg:city":"Doncaster",
    "sg:classifiers":[
        {
            "category":"Professional",
            "subcategory":"Management & Consulting",
            "type":"Services"
        }
    ],
    "sg:phone":"+44 1302 873071",
    "sg:postcode":"DN5 0AA",
    "sg:province":"South Yorkshire",
    "sg:tags":[
        "consultant",
        "specialist"
    ],
    "wof:name":"English Rose",
    "wof:placetype":"venue"
},
  "geometry": {"coordinates":[-1.146431,53.546001],"type":"Point"}
}