{
  "type": "Feature",
  "properties": {
    "addr:full":"62 High Street Lyndhurst Hampshire SO43 7BJ",
    "addr:housenumber":"62",
    "addr:postcode":"so43 7bj",
    "addr:street":"High Street",
    "iso:country":"GB",
    "sg:address":"62 High Street",
    "sg:city":"Lyndhurst",
    "sg:classifiers":[
        {
            "category":"Retail",
            "subcategory":"Laundry & Dry Cleaning",
            "type":"Services"
        }
    ],
    "sg:postcode":"SO43 7BJ",
    "sg:province":"Hampshire",
    "sg:tags":[
        "alteration"
    ],
    "wof:name":"Trio Cleaning Co.",
    "wof:placetype":"venue"
},
  "geometry": {"coordinates":[-1.5730359554,50.8721923828],"type":"Point"}
}