{
  "type": "Feature",
  "properties": {
    "addr:full":"Willow Brook Farm, Church Lane, Shearsby Lutterworth Leicestershire LE17 6PG",
    "addr:postcode":"le17 6pg",
    "addr:street":"Church Lane",
    "iso:country":"GB",
    "sg:address":"Willow Brook Farm, Church Lane, Shearsby",
    "sg:city":"Lutterworth",
    "sg:classifiers":[
        {
            "category":"Farming",
            "subcategory":"Livestock Farm",
            "type":"Manufacturing & Wholesale Goods"
        }
    ],
    "sg:postcode":"LE17 6PG",
    "sg:province":"Leicestershire",
    "sg:tags":[
        "others"
    ],
    "wof:name":"C A & G Barnacle",
    "wof:placetype":"venue"
},
  "geometry": {"coordinates":[-1.076739,52.510811],"type":"Point"}
}