{
  "type": "Feature",
  "properties": {
    "addr:full":"Bury Lane, Codicote Hitchin Hertfordshire SG4 8XX",
    "addr:postcode":"sg4 8xx",
    "addr:street":"Bury Lane",
    "iso:country":"GB",
    "sg:address":"Bury Lane, Codicote",
    "sg:city":"Hitchin",
    "sg:classifiers":[
        {
            "category":"Social Services",
            "subcategory":"Adult Care",
            "type":"Services"
        }
    ],
    "sg:phone":"+44 1438 820095",
    "sg:postcode":"SG4 8XX",
    "sg:province":"Hertfordshire",
    "sg:tags":[
        "housing",
        "sheltered"
    ],
    "wof:name":"Bury Sheltered Housing",
    "wof:placetype":"venue"
},
  "geometry": {"coordinates":[-0.235359,51.849232],"type":"Point"}
}