{
  "type": "Feature",
  "properties": {
    "iso:country":"GB",
    "sg:address":"170 Clare Road",
    "sg:city":"Cardiff",
    "sg:classifiers":[
        {
            "category":"Shopping",
            "subcategory":"Crafts & Fabrics",
            "type":"Retail Goods"
        }
    ],
    "sg:phone":"+44 29 2022 8196",
    "sg:postcode":"CF11 6RX",
    "sg:province":"Cardiff",
    "sg:tags":[
        "shop",
        "needlecraft",
        "wool"
    ],
    "wof:name":"Shaws the Drapers",
    "wof:placetype":"venue"
},
  "geometry": {"coordinates":[-3.188749,51.477715],"type":"Point"}
}