{
  "type": "Feature",
  "properties": {
    "iso:country":"GB",
    "sg:address":"11 Lynnlea Avenue",
    "sg:city":"Haddington",
    "sg:classifiers":[
        {
            "category":"Building & Trades",
            "subcategory":"Construction",
            "type":"Services"
        }
    ],
    "sg:postcode":"EH41 4AF",
    "sg:province":"East Lothian",
    "sg:tags":[
        "decorator",
        "painter"
    ],
    "wof:name":"Brian Cockburn",
    "wof:placetype":"venue"
},
  "geometry": {"coordinates":[-2.767332077,55.9532546997],"type":"Point"}
}