{
  "type": "Feature",
  "properties": {
    "addr:full":"68-70 Huddersfield Road Elland West Yorkshire HX5 9AA",
    "addr:housenumber":"68-70",
    "addr:postcode":"hx5 9aa",
    "addr:street":"Huddersfield Road",
    "iso:country":"GB",
    "sg:address":"68-70 Huddersfield Road",
    "sg:city":"Elland",
    "sg:classifiers":[
        {
            "category":"Personal",
            "subcategory":"Beauty Salon",
            "type":"Services"
        }
    ],
    "sg:postcode":"HX5 9AA",
    "sg:province":"West Yorkshire",
    "sg:tags":[
        "unisex",
        "hairdresser"
    ],
    "wof:name":"John Hair Salon Lewis",
    "wof:placetype":"venue"
},
  "geometry": {"coordinates":[-1.8339370489,53.6832084656],"type":"Point"}
}