{
  "type": "Feature",
  "properties": {
    "addr:full":"Redkiln Way Horsham West Sussex RH13 5TN",
    "addr:postcode":"rh13 5tn",
    "addr:street":"Redkiln Way",
    "iso:country":"GB",
    "sg:address":"Redkiln Way",
    "sg:city":"Horsham",
    "sg:classifiers":[
        {
            "category":"Building & Trades",
            "subcategory":"Plumbing",
            "type":"Services"
        },
        {
            "category":"Building & Trades",
            "subcategory":"Construction",
            "type":"Services"
        }
    ],
    "sg:phone":"+44 1403 254213",
    "sg:postcode":"RH13 5TN",
    "sg:province":"West Sussex",
    "sg:tags":[
        "central",
        "installation",
        "system",
        "servicing",
        "heating"
    ],
    "wof:name":"C A Goodwin Ltd.",
    "wof:placetype":"venue"
},
  "geometry": {"coordinates":[-0.3053539991,51.0696792603],"type":"Point"}
}