{
  "type": "Feature",
  "properties": {
    "iso:country":"GB",
    "sg:address":"393 Great Western Road",
    "sg:city":"Glasgow",
    "sg:classifiers":[
        {
            "category":"Transit Center",
            "subcategory":"Freight",
            "type":"Transportation"
        }
    ],
    "sg:phone":"+44 141 337 6807",
    "sg:postcode":"G4 9HY",
    "sg:province":"Glasgow City",
    "sg:tags":[
        "shop",
        "craft",
        "centre"
    ],
    "wof:name":"Uraeus",
    "wof:placetype":"venue"
},
  "geometry": {"coordinates":[-4.2777237892,55.8739356995],"type":"Point"}
}