{
  "type": "Feature",
  "properties": {
    "addr:full":"Sexton Cottage, Church Rd, Lee Brockhurst Shrewsbury Shropshire SY4 5QQ",
    "addr:postcode":"sy4 5qq",
    "addr:street":"Church Rd",
    "iso:country":"GB",
    "sg:address":"Sexton Cottage, Church Rd, Lee Brockhurst",
    "sg:city":"Shrewsbury",
    "sg:classifiers":[
        {
            "category":"Professional",
            "subcategory":"Secretarial Services",
            "type":"Services"
        }
    ],
    "sg:phone":"+44 1939 200303",
    "sg:postcode":"SY4 5QQ",
    "sg:province":"Shropshire",
    "wof:name":"Sexton Secretarial Services",
    "wof:placetype":"venue"
},
  "geometry": {"coordinates":[-2.6705229282,52.8365364075],"type":"Point"}
}