{
  "type": "Feature",
  "properties": {
    "iso:country":"GB",
    "sg:address":"Unit 1 Searle Cres, Winterstoke Commercial Centre",
    "sg:city":"Weston-super-mare",
    "sg:classifiers":[
        {
            "category":"Retail",
            "subcategory":"Auto Repair",
            "type":"Services"
        }
    ],
    "sg:phone":"+44 1934 612332",
    "sg:postcode":"BS23 3XP",
    "sg:province":"Somerset",
    "sg:tags":[
        "modification",
        "garage"
    ],
    "wof:name":"Somerset Way Motor Co Ltd (The)",
    "wof:placetype":"venue"
},
  "geometry": {"coordinates":[-2.9586288929,51.3417854309],"type":"Point"}
}