{
  "type": "Feature",
  "properties": {
    "addr:full":"5 Nalders Court Truro Cornwall TR1 2XH",
    "addr:housenumber":"5",
    "addr:postcode":"tr1 2xh",
    "addr:street":"Nalders Court",
    "iso:country":"GB",
    "sg:address":"5 Nalders Court",
    "sg:city":"Truro",
    "sg:classifiers":[
        {
            "category":"Shopping",
            "subcategory":"Clothing, Apparel, & Fashions",
            "type":"Retail Goods"
        }
    ],
    "sg:phone":"+44 1872 223767",
    "sg:postcode":"TR1 2XH",
    "sg:province":"Cornwall",
    "sg:tags":[
        "ladieswear"
    ],
    "wof:name":"Melange",
    "wof:placetype":"venue"
},
  "geometry": {"coordinates":[-5.0531439781,50.2639312744],"type":"Point"}
}