{
  "type": "Feature",
  "properties": {
    "iso:country":"GB",
    "sg:address":"59 Palace Aveune",
    "sg:city":"Paignton",
    "sg:classifiers":[
        {
            "category":"Professional",
            "subcategory":"Accounting & Tax Preparation",
            "type":"Services"
        }
    ],
    "sg:phone":"+44 1803 664120",
    "sg:postcode":"TQ3 3EN",
    "sg:province":"Devon",
    "sg:tags":[
        "accountant"
    ],
    "wof:name":"M G Breed",
    "wof:placetype":"venue"
},
  "geometry": {"coordinates":[-3.571082,50.435474],"type":"Point"}
}