{
  "type": "Feature",
  "properties": {
    "addr:full":"George West House, 2-3 Clapham Common North Side London Greater London SW4 0QW",
    "addr:housenumber":"2-3",
    "addr:postcode":"sw4 0qw",
    "addr:street":"George;Clapham Common North Side",
    "iso:country":"GB",
    "sg:address":"George West House, 2-3 Clapham Common North Side",
    "sg:city":"London",
    "sg:classifiers":[
        {
            "category":"Professional",
            "subcategory":"Computer Services",
            "type":"Services"
        }
    ],
    "sg:phone":"+44 20 7498 7777",
    "sg:postcode":"SW4 0QW",
    "sg:province":"Greater London",
    "sg:tags":[
        "system",
        "software"
    ],
    "wof:name":"Qas Systems Ltd.",
    "wof:placetype":"venue"
},
  "geometry": {"coordinates":[-0.1426769942,51.4631881714],"type":"Point"}
}