{
  "type": "Feature",
  "properties": {
    "iso:country":"GB",
    "sg:address":"758 The Big Peg 120 Vyse St, Hockley",
    "sg:city":"Birmingham",
    "sg:classifiers":[
        {
            "category":"Professional",
            "type":"Services"
        }
    ],
    "sg:phone":"+44 121 247 8844",
    "sg:postcode":"B18 6NF",
    "sg:province":"West Midlands",
    "sg:tags":[
        "repair",
        "tech",
        "maintenance"
    ],
    "wof:name":"Gibara Dunn",
    "wof:placetype":"venue"
},
  "geometry": {"coordinates":[-1.908604,52.478596],"type":"Point"}
}