{
  "type": "Feature",
  "properties": {
    "iso:country":"GB",
    "sg:address":"Riddings House, Riddings Lane",
    "sg:city":"Harlow",
    "sg:classifiers":[
        {
            "category":"Retail",
            "subcategory":"Portrait Studio",
            "type":"Services"
        },
        {
            "category":"Professional",
            "subcategory":"Art Services",
            "type":"Services"
        }
    ],
    "sg:phone":"+44 1279 415957",
    "sg:postcode":"CM18 7HT",
    "sg:province":"Essex",
    "sg:tags":[
        "photographer",
        "commercial"
    ],
    "wof:name":"S & S CATHERALL",
    "wof:placetype":"venue"
},
  "geometry": {"coordinates":[0.1135950014,51.7493515015],"type":"Point"}
}