{
  "type": "Feature",
  "properties": {
    "iso:country":"GB",
    "sg:address":"204 Fairmile Rd",
    "sg:city":"Christchurch",
    "sg:classifiers":[
        {
            "category":"Autos & Motor Vehicles",
            "subcategory":"Fuel & Gas Station",
            "type":"Retail Goods"
        }
    ],
    "sg:phone":"+44 1202 409850",
    "sg:postcode":"BH23 2LP",
    "sg:province":"Dorset",
    "sg:tags":[
        "petrol",
        "filling"
    ],
    "wof:name":"Texaco",
    "wof:placetype":"venue"
},
  "geometry": {"coordinates":[-1.79297,50.748142],"type":"Point"}
}