{
  "type": "Feature",
  "properties": {
    "iso:country":"GB",
    "sg:address":"The Roe",
    "sg:city":"St Asaph",
    "sg:classifiers":[
        {
            "category":"Autos & Motor Vehicles",
            "subcategory":"Automobile Sales",
            "type":"Retail Goods"
        }
    ],
    "sg:phone":"+44 1745 582525",
    "sg:postcode":"LL17 0NA",
    "sg:province":"Conwy",
    "sg:tags":[
        "car"
    ],
    "wof:name":"Barker,john, & Price,kevin,",
    "wof:placetype":"venue"
},
  "geometry": {"coordinates":[-3.455794096,53.2672958374],"type":"Point"}
}