{
  "type": "Feature",
  "properties": {
    "iso:country":"GB",
    "sg:address":"Unwin Road",
    "sg:city":"Sutton-in-ashfield",
    "sg:classifiers":[
        {
            "category":"Organizations",
            "subcategory":"Membership Organization",
            "type":"Services"
        }
    ],
    "sg:phone":"+44 1623 559703",
    "sg:postcode":"NG17 4HN",
    "sg:province":"Nottinghamshire",
    "sg:tags":[
        "club"
    ],
    "wof:name":"Unwin Social Club",
    "wof:placetype":"venue"
},
  "geometry": {"coordinates":[-1.238176,53.130798],"type":"Point"}
}