{
  "type": "Feature",
  "properties": {
    "iso:country":"GB",
    "sg:address":"Hoden Lane, Cleeve Prior",
    "sg:city":"Evesham",
    "sg:classifiers":[
        {
            "category":"Farming",
            "subcategory":"Livestock Farm",
            "type":"Manufacturing & Wholesale Goods"
        }
    ],
    "sg:postcode":"WR11 8LH",
    "sg:province":"Gloucestershire",
    "sg:tags":[
        "others"
    ],
    "wof:name":"Upper Hoden Farm",
    "wof:placetype":"venue"
},
  "geometry": {"coordinates":[-1.8790689707,52.1440010071],"type":"Point"}
}