{
  "type": "Feature",
  "properties": {
    "iso:country":"GB",
    "sg:address":"55 Market Place",
    "sg:city":"Henley-on-thames",
    "sg:classifiers":[
        {
            "category":"Place Of Worship",
            "type":"Public Place"
        }
    ],
    "sg:phone":"+44 1491 577414",
    "sg:postcode":"RG9 2AA",
    "sg:province":"Berkshire",
    "wof:name":"Dayspring Christian Centre",
    "wof:placetype":"venue"
},
  "geometry": {"coordinates":[-0.906965,51.536983],"type":"Point"}
}