{
  "type": "Feature",
  "properties": {
    "addr:full":"Units 4 & 7 The Castle Combe Enterprise Centre Chippenham Gloucestershire SN14 7QE",
    "addr:housenumber":"units 4 & 7;castle combe enterprise",
    "addr:postcode":"sn14 7qe",
    "addr:street":"The;Centre",
    "iso:country":"GB",
    "sg:address":"Units 4 & 7 The Castle Combe Enterprise Centre",
    "sg:city":"Chippenham",
    "sg:classifiers":[
        {
            "category":"Retail",
            "subcategory":"Auto Repair",
            "type":"Services"
        }
    ],
    "sg:phone":"+44 1249 783123",
    "sg:postcode":"SN14 7QE",
    "sg:province":"Gloucestershire",
    "sg:tags":[
        "modification",
        "garage"
    ],
    "wof:name":"Auto Aid UK Ltd",
    "wof:placetype":"venue"
},
  "geometry": {"coordinates":[-2.129204,51.456776],"type":"Point"}
}