{
  "type": "Feature",
  "properties": {
    "addr:full":"Barclays Bank House, Baxtergate Whitby North Yorkshire YO21 1BW",
    "addr:postcode":"yo21 1bw",
    "addr:street":"Baxtergate",
    "iso:country":"GB",
    "sg:address":"Barclays Bank House, Baxtergate",
    "sg:city":"Whitby",
    "sg:classifiers":[
        {
            "category":"Building & Trades",
            "subcategory":"Construction",
            "type":"Services"
        },
        {
            "category":"Real Estate",
            "subcategory":"Architect",
            "type":"Services"
        }
    ],
    "sg:phone":"+44 1947 604353",
    "sg:postcode":"YO21 1BW",
    "sg:province":"North Yorkshire",
    "sg:tags":[
        "consultant",
        "advisor"
    ],
    "wof:name":"Riverside Design Group Consultants",
    "wof:placetype":"venue"
},
  "geometry": {"coordinates":[-0.6138340235,54.4865531921],"type":"Point"}
}