{
  "type": "Feature",
  "properties": {
    "iso:country":"GB",
    "sg:address":"40 Eastlake Street",
    "sg:city":"Plymouth",
    "sg:classifiers":[
        {
            "category":"Health Services",
            "subcategory":"Health Practitioner",
            "type":"Services"
        }
    ],
    "sg:phone":"+44 1752 225567",
    "sg:postcode":"PL1 1BE",
    "sg:province":"Devon",
    "sg:tags":[
        "osteopath"
    ],
    "wof:name":"Eastlake Street Osteopathic Clinic",
    "wof:placetype":"venue"
},
  "geometry": {"coordinates":[-4.139342,50.373142],"type":"Point"}
}