{
  "type": "Feature",
  "properties": {
    "iso:country":"GB",
    "sg:address":"39 Laindon Centre",
    "sg:city":"Basildon",
    "sg:classifiers":[
        {
            "category":"Shopping",
            "subcategory":"Thrift Store",
            "type":"Retail Goods"
        }
    ],
    "sg:phone":"+44 1268 411862",
    "sg:postcode":"SS15 5TQ",
    "sg:province":"Essex",
    "sg:tags":[
        "shop",
        "charity"
    ],
    "wof:name":"Sue Ryder Foundation",
    "wof:placetype":"venue"
},
  "geometry": {"coordinates":[0.4378559887,51.5682258606],"type":"Point"}
}