{
  "type": "Feature",
  "properties": {
    "addr:full":"9 Burlington Slough Berkshire SL1 7BQ",
    "addr:housenumber":"9",
    "addr:postcode":"sl1 7bq",
    "addr:street":"Burlington",
    "iso:country":"GB",
    "sg:address":"9 Burlington",
    "sg:city":"Slough",
    "sg:classifiers":[
        {
            "category":"Professional",
            "subcategory":"Art Services",
            "type":"Services"
        }
    ],
    "sg:phone":"+44 1628 559048",
    "sg:postcode":"SL1 7BQ",
    "sg:province":"Berkshire",
    "sg:tags":[
        "photographer"
    ],
    "wof:name":"Words & Pictures",
    "wof:placetype":"venue"
},
  "geometry": {"coordinates":[-0.665904,51.529518],"type":"Point"}
}