{
  "type": "Feature",
  "properties": {
    "addr:full":"Unit 3 Mackay Clo, Lynch La, Weymouth Dorset DT4 9DN",
    "addr:housenumber":"unit 3",
    "addr:postcode":"dt4 9dn",
    "addr:street":"Clo Lynch La Weymouth",
    "iso:country":"GB",
    "sg:address":"Unit 3 Mackay Clo, Lynch La,",
    "sg:city":"Weymouth",
    "sg:classifiers":[
        {
            "category":"Retail",
            "subcategory":"Auto Repair",
            "type":"Services"
        }
    ],
    "sg:postcode":"DT4 9DN",
    "sg:province":"Dorset",
    "sg:tags":[
        "modification",
        "garage"
    ],
    "wof:name":"Jakeham,Frank,",
    "wof:placetype":"venue"
},
  "geometry": {"coordinates":[-2.4592061043,50.6099014282],"type":"Point"}
}