{
  "type": "Feature",
  "properties": {
    "iso:country":"GB",
    "sg:address":"The Lodge, Broadhurst Manor, Broadhurst Manor Rd, Horsted Keynes",
    "sg:city":"Haywards Heath",
    "sg:classifiers":[
        {
            "category":"Organizations",
            "subcategory":"Non-profit Organization",
            "type":"Services"
        }
    ],
    "sg:phone":"+44 1342 811377",
    "sg:postcode":"RH17 7BG",
    "sg:province":"East Sussex",
    "sg:tags":[
        "organisation",
        "animal",
        "welfare"
    ],
    "wof:name":"The Protesters Animal Information Network",
    "wof:placetype":"venue"
},
  "geometry": {"coordinates":[-0.028284,51.036671],"type":"Point"}
}