{
  "type": "Feature",
  "properties": {
    "iso:country":"GB",
    "sg:address":"Room 105 Police Station, Berw Rd",
    "sg:city":"Pontypridd",
    "sg:classifiers":[
        {
            "category":"Personal",
            "type":"Services"
        },
        {
            "category":"Professional",
            "subcategory":"Lawyer & Legal Services",
            "type":"Services"
        }
    ],
    "sg:phone":"+44 1443 485202",
    "sg:postcode":"CF37 2AA",
    "sg:province":"Caerphilly",
    "sg:tags":[
        "advice",
        "counselling"
    ],
    "wof:name":"Taff Ely Victim Support Scheme",
    "wof:placetype":"venue"
},
  "geometry": {"coordinates":[-3.330959,51.597549],"type":"Point"}
}