{
  "type": "Feature",
  "properties": {
    "iso:country":"GB",
    "sg:address":"28 New Market Street",
    "sg:city":"Ulverston",
    "sg:classifiers":[
        {
            "category":"Home & Garden",
            "subcategory":"Hardware",
            "type":"Retail Goods"
        }
    ],
    "sg:phone":"+44 1229 582029",
    "sg:postcode":"LA12 7LN",
    "sg:province":"Cumbria",
    "wof:name":"Pelleymounters",
    "wof:placetype":"venue"
},
  "geometry": {"coordinates":[-3.095101,54.194977],"type":"Point"}
}