{
  "type": "Feature",
  "properties": {
    "iso:country":"GB",
    "sg:address":"1 Penton Hook Road",
    "sg:city":"Staines",
    "sg:classifiers":[
        {
            "category":"Building & Trades",
            "subcategory":"Construction",
            "type":"Services"
        }
    ],
    "sg:postcode":"TW18 2HT",
    "sg:province":"Berkshire",
    "sg:tags":[
        "contractor",
        "paving",
        "driveway"
    ],
    "wof:name":"Colescrete",
    "wof:placetype":"venue"
},
  "geometry": {"coordinates":[-0.507737,51.420307],"type":"Point"}
}