{
  "type": "Feature",
  "properties": {
    "iso:country":"GB",
    "sg:address":"9 Elland Close, Fair Oak",
    "sg:city":"Eastleigh",
    "sg:classifiers":[
        {
            "category":"Home & Garden",
            "subcategory":"Household Appliances",
            "type":"Retail Goods"
        }
    ],
    "sg:postcode":"SO50 7JY",
    "sg:province":"Hampshire",
    "sg:tags":[
        "electrical"
    ],
    "wof:name":"D D Domestics",
    "wof:placetype":"venue"
},
  "geometry": {"coordinates":[-1.2982369661,50.9618759155],"type":"Point"}
}