{
  "type": "Feature",
  "properties": {
    "iso:country":"GB",
    "sg:address":"2 King Square",
    "sg:city":"Bridgwater",
    "sg:classifiers":[
        {
            "category":"Organizations",
            "subcategory":"Community Association",
            "type":"Services"
        }
    ],
    "sg:phone":"+44 1278 444344",
    "sg:postcode":"TA6 3DG",
    "sg:province":"Somerset",
    "sg:tags":[
        "co-operatives",
        "society",
        "housing",
        "trust"
    ],
    "sg:website":"http://www.shal.org",
    "wof:name":"Shal Housing Ltd",
    "wof:placetype":"venue"
},
  "geometry": {"coordinates":[-3.0040810108,51.1293144226],"type":"Point"}
}