{
  "type": "Feature",
  "properties": {
    "addr:full":"25 The Borough Farnham Surrey GU9 7NJ",
    "addr:housenumber":"25",
    "addr:postcode":"gu9 7nj",
    "addr:street":"The Borough Farnham",
    "iso:country":"GB",
    "sg:address":"25 The Borough",
    "sg:city":"Farnham",
    "sg:classifiers":[
        {
            "category":"Shopping",
            "subcategory":"Books",
            "type":"Retail Goods"
        }
    ],
    "sg:phone":"+44 1252 719262",
    "sg:postcode":"GU9 7NJ",
    "sg:province":"Surrey",
    "sg:tags":[
        "bookseller"
    ],
    "wof:name":"Bookends Wholesale Ltd.",
    "wof:placetype":"venue"
},
  "geometry": {"coordinates":[-0.797758,51.215309],"type":"Point"}
}