{
  "type": "Feature",
  "properties": {
    "iso:country":"GB",
    "sg:address":"Packaging House, Pelham Street",
    "sg:city":"Mansfield",
    "sg:classifiers":[
        {
            "category":"Professional",
            "subcategory":"Advertising",
            "type":"Services"
        },
        {
            "category":"Government",
            "subcategory":"Post Office",
            "type":"Public Place"
        }
    ],
    "sg:phone":"+44 1623 423712",
    "sg:postcode":"NG18 2EY",
    "sg:province":"Nottinghamshire",
    "sg:tags":[
        "mail",
        "direct",
        "provider"
    ],
    "wof:name":"Mansfield Direct Mail & Packing Co",
    "wof:placetype":"venue"
},
  "geometry": {"coordinates":[-1.1887789965,53.143699646],"type":"Point"}
}