{
  "type": "Feature",
  "properties": {
    "iso:country":"GB",
    "sg:address":"Moat Farm, Moat Lane",
    "sg:city":"Rotherham",
    "sg:classifiers":[
        {
            "category":"Building & Trades",
            "subcategory":"Construction",
            "type":"Services"
        }
    ],
    "sg:phone":"+44 1709 549734",
    "sg:postcode":"S66 1DZ",
    "sg:province":"South Yorkshire",
    "sg:tags":[
        "builder"
    ],
    "wof:name":"Habco Property Investment Co. Ltd.",
    "wof:placetype":"venue"
},
  "geometry": {"coordinates":[-1.27295,53.4086],"type":"Point"}
}