{
  "type": "Feature",
  "properties": {
    "addr:full":"14 Barn Road Carmarthen Carmarthenshire SA31 1DD",
    "addr:housenumber":"14",
    "addr:postcode":"sa31 1dd",
    "addr:street":"Barn Road",
    "iso:country":"GB",
    "sg:address":"14 Barn Road",
    "sg:city":"Carmarthen",
    "sg:classifiers":[
        {
            "category":"Professional",
            "subcategory":"Accounting & Tax Preparation",
            "type":"Services"
        }
    ],
    "sg:phone":"+44 1267 221777",
    "sg:postcode":"SA31 1DD",
    "sg:province":"Carmarthenshire",
    "sg:tags":[
        "accountant"
    ],
    "wof:name":"Charles & Co.",
    "wof:placetype":"venue"
},
  "geometry": {"coordinates":[-4.3078432083,51.8584213257],"type":"Point"}
}