{
  "type": "Feature",
  "properties": {
    "addr:full":"83 Southchurch Avenue Southend-on-sea Essex SS1 2RS",
    "addr:housenumber":"83",
    "addr:postcode":"ss1 2rs",
    "addr:street":"Southchurch Avenue",
    "iso:country":"GB",
    "sg:address":"83 Southchurch Avenue",
    "sg:city":"Southend-on-sea",
    "sg:classifiers":[
        {
            "category":"Fast Food",
            "type":"Food & Drink"
        }
    ],
    "sg:phone":"+44 1702 600739",
    "sg:postcode":"SS1 2RS",
    "sg:province":"Essex",
    "sg:tags":[
        "away",
        "take"
    ],
    "wof:name":"Tandoori Hut",
    "wof:placetype":"venue"
},
  "geometry": {"coordinates":[0.723574996,51.5361099243],"type":"Point"}
}