{
  "type": "Feature",
  "properties": {
    "addr:full":"28-30 Little Russell Street London Greater London WC1A 2HN",
    "addr:housenumber":"28-30",
    "addr:postcode":"wc1a 2hn",
    "addr:street":"Little Russell Street",
    "iso:country":"GB",
    "sg:address":"28-30 Little Russell Street",
    "sg:city":"London",
    "sg:classifiers":[
        {
            "category":"Health Services",
            "subcategory":"Nursing And Care Facility",
            "type":"Services"
        }
    ],
    "sg:phone":"+44 20 7405 7677",
    "sg:postcode":"WC1A 2HN",
    "sg:province":"Greater London",
    "sg:tags":[
        "agency"
    ],
    "wof:name":"Nightingale Nursing Bureau Ltd.",
    "wof:placetype":"venue"
},
  "geometry": {"coordinates":[-0.1254040003,51.5179748535],"type":"Point"}
}