{
  "type": "Feature",
  "properties": {
    "addr:full":"40 Greenfield Avenue, Ickleford Hitchin Bedfordshire SG5 3XR",
    "addr:housenumber":"40",
    "addr:postcode":"sg5 3xr",
    "addr:street":"Greenfield Avenue",
    "iso:country":"GB",
    "sg:address":"40 Greenfield Avenue, Ickleford",
    "sg:city":"Hitchin",
    "sg:classifiers":[
        {
            "category":"Building & Trades",
            "subcategory":"Cleaning & Sanitation",
            "type":"Services"
        }
    ],
    "sg:phone":"+44 1462 450140",
    "sg:postcode":"SG5 3XR",
    "sg:province":"Bedfordshire",
    "sg:tags":[
        "commercial"
    ],
    "wof:name":"Colin Hull",
    "wof:placetype":"venue"
},
  "geometry": {"coordinates":[-0.282817,51.970867],"type":"Point"}
}