{
  "type": "Feature",
  "properties": {
    "addr:full":"7 Eastwood Crescent, Thornliebank Glasgow East Renfrewshire G46 8NS",
    "addr:housenumber":"7",
    "addr:postcode":"g46 8ns",
    "addr:street":"Eastwood Crescent",
    "iso:country":"GB",
    "sg:address":"7 Eastwood Crescent, Thornliebank",
    "sg:city":"Glasgow",
    "sg:classifiers":[
        {
            "category":"Organizations",
            "subcategory":"Community Association",
            "type":"Services"
        }
    ],
    "sg:phone":"+44 141 638 2300",
    "sg:postcode":"G46 8NS",
    "sg:province":"East Renfrewshire",
    "sg:tags":[
        "society",
        "housing"
    ],
    "wof:name":"Kirkcare Housing Association Ltd.",
    "wof:placetype":"venue"
},
  "geometry": {"coordinates":[-4.3172001839,55.8083686829],"type":"Point"}
}