{
  "type": "Feature",
  "properties": {
    "addr:full":"Harrop House, Macclesfield Road Macclesfield Cheshire SK10 5UU",
    "addr:postcode":"sk10 5uu",
    "addr:street":"Macclesfield Road",
    "iso:country":"GB",
    "sg:address":"Harrop House, Macclesfield Road",
    "sg:city":"Macclesfield",
    "sg:classifiers":[
        {
            "category":"Freight",
            "type":"Transportation"
        },
        {
            "category":"Train Station",
            "subcategory":"Light Rail",
            "type":"Transportation"
        }
    ],
    "sg:postcode":"SK10 5UU",
    "sg:province":"Cheshire",
    "sg:tags":[
        "haulage",
        "distributor",
        "lime",
        "road",
        "mnfrs"
    ],
    "wof:name":"I F & J Bolshaw Haulage Ltd.",
    "wof:placetype":"venue"
},
  "geometry": {"coordinates":[-2.0037219524,53.3189506531],"type":"Point"}
}