{
  "type": "Feature",
  "properties": {
    "iso:country":"GB",
    "sg:address":"Lindred Road, Lomeshaye Industrial Estate, Brierfield",
    "sg:city":"Nelson",
    "sg:classifiers":[
        {
            "category":"Manufacturing",
            "subcategory":"Wood Products",
            "type":"Manufacturing & Wholesale Goods"
        }
    ],
    "sg:phone":"+44 1282 616699",
    "sg:postcode":"BB9 5SR",
    "sg:province":"Lancashire",
    "sg:tags":[
        "packaging",
        "crate",
        "pallets"
    ],
    "wof:name":"Strategy Group Ltd.",
    "wof:placetype":"venue"
},
  "geometry": {"coordinates":[-2.233859,53.833817],"type":"Point"}
}