{
  "type": "Feature",
  "properties": {
    "iso:country":"GB",
    "sg:address":"16 Clapham Common South Side",
    "sg:city":"London",
    "sg:classifiers":[
        {
            "category":"Personal",
            "subcategory":"Beauty Salon",
            "type":"Services"
        }
    ],
    "sg:phone":"+44 20 7622 4777",
    "sg:postcode":"SW4 7AB",
    "sg:province":"Greater London",
    "sg:tags":[
        "unisex",
        "hairdresser"
    ],
    "wof:name":"Hazel's Unisex Hairdresser",
    "wof:placetype":"venue"
},
  "geometry": {"coordinates":[-0.13916,51.460949],"type":"Point"}
}