{
  "type": "Feature",
  "properties": {
    "iso:country":"GB",
    "sg:address":"The Bungalow, Great Hockham Hall",
    "sg:city":"Thetford",
    "sg:classifiers":[
        {
            "category":"Building & Trades",
            "subcategory":"Construction",
            "type":"Services"
        }
    ],
    "sg:postcode":"IP24 1NZ",
    "sg:province":"Norfolk",
    "sg:tags":[
        "builder"
    ],
    "wof:name":"A Seeley",
    "wof:placetype":"venue"
},
  "geometry": {"coordinates":[0.875265,52.497288],"type":"Point"}
}