{
  "type": "Feature",
  "properties": {
    "addr:full":"11 Bridport Road Dorchester Dorset DT1 2NG",
    "addr:housenumber":"11",
    "addr:postcode":"dt1 2ng",
    "addr:street":"Bridport Road",
    "iso:country":"GB",
    "sg:address":"11 Bridport Road",
    "sg:city":"Dorchester",
    "sg:classifiers":[
        {
            "category":"Bars & Pubs",
            "type":"Food & Drink"
        }
    ],
    "sg:phone":"+44 1305 259250",
    "sg:postcode":"DT1 2NG",
    "sg:province":"Dorset",
    "sg:tags":[
        "pubs",
        "inn"
    ],
    "wof:name":"The Sydney Arms",
    "wof:placetype":"venue"
},
  "geometry": {"coordinates":[-2.446122,50.714176],"type":"Point"}
}