{
  "type": "Feature",
  "properties": {
    "iso:country":"GB",
    "sg:address":"Milnfield",
    "sg:city":"Elgin",
    "sg:classifiers":[
        {
            "category":"Utilities",
            "subcategory":"Fuel Oil & Lpg",
            "type":"Services"
        }
    ],
    "sg:phone":"+44 1343 557400",
    "sg:postcode":"IV30 1UZ",
    "sg:province":"Moray",
    "sg:tags":[
        "distributor"
    ],
    "wof:name":"Gleaner Oils Ltd.",
    "wof:placetype":"venue"
},
  "geometry": {"coordinates":[-3.317869,57.649368],"type":"Point"}
}