{
  "type": "Feature",
  "properties": {
    "iso:country":"GB",
    "sg:address":"Wakefield Rd",
    "sg:city":"Barnsley",
    "sg:classifiers":[
        {
            "category":"Shopping",
            "subcategory":"Pharmacy",
            "type":"Retail Goods"
        }
    ],
    "sg:phone":"+44 1226 203928",
    "sg:postcode":"S71 3TY",
    "sg:province":"South Yorkshire",
    "sg:tags":[
        "pharmacist",
        "dispensing",
        "chemist"
    ],
    "wof:name":"Co Op Pharmacy",
    "wof:placetype":"venue"
},
  "geometry": {"coordinates":[-1.478465,53.577988],"type":"Point"}
}