{
  "type": "Feature",
  "properties": {
    "addr:full":"38-42 Glendale Gardens Leigh-on-sea Essex SS9 2AS",
    "addr:housenumber":"38-42",
    "addr:postcode":"ss9 2as",
    "addr:street":"Glendale Gardens",
    "iso:country":"GB",
    "sg:address":"38-42 Glendale Gardens",
    "sg:city":"Leigh-on-sea",
    "sg:classifiers":[
        {
            "category":"Recreation",
            "type":"Entertainment"
        }
    ],
    "sg:phone":"+44 1702 713881",
    "sg:postcode":"SS9 2AS",
    "sg:province":"Essex",
    "sg:tags":[
        "snooker",
        "billiards",
        "pool"
    ],
    "wof:name":"Snooker Sports (Manufacturing) Ltd.",
    "wof:placetype":"venue"
},
  "geometry": {"coordinates":[0.6525760293,51.5445518494],"type":"Point"}
}