{
  "type": "Feature",
  "properties": {
    "iso:country":"GB",
    "sg:address":"3 Gladstone Way",
    "sg:city":"Thornton-cleveleys",
    "sg:classifiers":[
        {
            "category":"Wholesale",
            "subcategory":"Computers",
            "type":"Manufacturing & Wholesale Goods"
        },
        {
            "category":"Professional",
            "subcategory":"Computer Services",
            "type":"Services"
        }
    ],
    "sg:phone":"+44 1253 868687",
    "sg:postcode":"FY5 3TL",
    "sg:province":"Lancashire",
    "sg:tags":[
        "supplier",
        "consultant",
        "consumables"
    ],
    "wof:name":"RICHARD CUTTLE",
    "wof:placetype":"venue"
},
  "geometry": {"coordinates":[-3.0264959335,53.8713912964],"type":"Point"}
}