{
  "type": "Feature",
  "properties": {
    "addr:full":"122 Rushden Road, Wymington Rushden Bedfordshire NN10 9LH",
    "addr:housenumber":"122",
    "addr:postcode":"nn10 9lh",
    "addr:street":"Rushden Road",
    "iso:country":"GB",
    "sg:address":"122 Rushden Road, Wymington",
    "sg:city":"Rushden",
    "sg:classifiers":[
        {
            "category":"Building & Trades",
            "subcategory":"Construction",
            "type":"Services"
        }
    ],
    "sg:postcode":"NN10 9LH",
    "sg:province":"Bedfordshire",
    "sg:tags":[
        "contractor",
        "paving",
        "driveway"
    ],
    "wof:name":"Buildall",
    "wof:placetype":"venue"
},
  "geometry": {"coordinates":[-0.6015769839,52.2755966187],"type":"Point"}
}