{
  "type": "Feature",
  "properties": {
    "addr:full":"4 Broadway Parade, Station Road West Drayton Greater London UB7 7DE",
    "addr:housenumber":"4",
    "addr:postcode":"ub7 7de",
    "addr:street":"Broadway Parade Station Road",
    "iso:country":"GB",
    "sg:address":"4 Broadway Parade, Station Road",
    "sg:city":"West Drayton",
    "sg:classifiers":[
        {
            "category":"Personal",
            "subcategory":"Beauty Salon",
            "type":"Services"
        }
    ],
    "sg:postcode":"UB7 7DE",
    "sg:province":"Greater London",
    "sg:tags":[
        "lady",
        "hairdresser"
    ],
    "wof:name":"Curl Inn",
    "wof:placetype":"venue"
},
  "geometry": {"coordinates":[-0.4739899933,51.5091171265],"type":"Point"}
}