{
  "type": "Feature",
  "properties": {
    "addr:full":"59 Hatfield Rd St Albans Hertfordshire AL1 4JE",
    "addr:housenumber":"59",
    "addr:postcode":"al1 4je",
    "addr:street":"Hatfield Rd",
    "iso:country":"GB",
    "sg:address":"59 Hatfield Rd",
    "sg:city":"St Albans",
    "sg:classifiers":[
        {
            "category":"Health Services",
            "subcategory":"Dentist",
            "type":"Services"
        }
    ],
    "sg:phone":"+44 1727 853573",
    "sg:postcode":"AL1 4JE",
    "sg:province":"Hertfordshire",
    "wof:name":"D Van-Vledder",
    "wof:placetype":"venue"
},
  "geometry": {"coordinates":[-0.32248,51.751694],"type":"Point"}
}