{
  "type": "Feature",
  "properties": {
    "iso:country":"GB",
    "sg:address":"4 Ringstead Way",
    "sg:city":"Aylesbury",
    "sg:classifiers":[
        {
            "category":"Home & Garden",
            "subcategory":"Building Materials",
            "type":"Retail Goods"
        },
        {
            "category":"Building & Trades",
            "subcategory":"Construction",
            "type":"Services"
        }
    ],
    "sg:postcode":"HP21 7ND",
    "sg:province":"Buckinghamshire",
    "sg:tags":[
        "insulation",
        "installers",
        "glazier"
    ],
    "wof:name":"Lambert,Victor,",
    "wof:placetype":"venue"
},
  "geometry": {"coordinates":[-0.798353,51.803982],"type":"Point"}
}