{
  "type": "Feature",
  "properties": {
    "iso:country":"GB",
    "sg:address":"The Old Stables, Lower Chantry Lane",
    "sg:city":"Canterbury",
    "sg:classifiers":[
        {
            "category":"Real Estate",
            "subcategory":"Real Estate Agent",
            "type":"Services"
        }
    ],
    "sg:phone":"+44 1227 762280",
    "sg:postcode":"CT1 1UF",
    "sg:province":"Kent",
    "wof:name":"Abbott Bros (Kent) Ltd.",
    "wof:placetype":"venue"
},
  "geometry": {"coordinates":[1.07561,51.27597],"type":"Point"}
}