{
  "type": "Feature",
  "properties": {
    "iso:country":"GB",
    "sg:address":"Oxford Road, Guiseley",
    "sg:city":"Leeds",
    "sg:classifiers":[
        {
            "category":"Personal",
            "subcategory":"Barber",
            "type":"Services"
        }
    ],
    "sg:postcode":"LS20 9AS",
    "sg:province":"West Yorkshire",
    "sg:tags":[
        "men's",
        "hairdresser"
    ],
    "wof:name":"Headmasters",
    "wof:placetype":"venue"
},
  "geometry": {"coordinates":[-1.709172,53.87582],"type":"Point"}
}