{
  "type": "Feature",
  "properties": {
    "addr:full":"16 Dereham Place London Greater London EC2A 3HJ",
    "addr:housenumber":"16",
    "addr:postcode":"ec2a 3hj",
    "addr:street":"Dereham Place",
    "iso:country":"GB",
    "sg:address":"16 Dereham Place",
    "sg:city":"London",
    "sg:classifiers":[
        {
            "category":"Real Estate",
            "subcategory":"Architect",
            "type":"Services"
        }
    ],
    "sg:phone":"+44 20 7684 1911",
    "sg:postcode":"EC2A 3HJ",
    "sg:province":"Greater London",
    "wof:name":"Cghp Architects Ltd.",
    "wof:placetype":"venue"
},
  "geometry": {"coordinates":[-0.078401,51.525654],"type":"Point"}
}