{
  "type": "Feature",
  "properties": {
    "addr:full":"8 North Street Industrial Estate Droitwich Worcestershire WR9 8JB",
    "addr:housenumber":"8",
    "addr:postcode":"estate;wr9 8jb",
    "addr:street":"North Street Industrial",
    "iso:country":"GB",
    "sg:address":"8 North Street Industrial Estate",
    "sg:city":"Droitwich",
    "sg:classifiers":[
        {
            "category":"Manufacturing",
            "subcategory":"Textiles",
            "type":"Manufacturing & Wholesale Goods"
        }
    ],
    "sg:postcode":"WR9 8JB",
    "sg:province":"Worcestershire",
    "sg:tags":[
        "mnfr",
        "sewing",
        "thread"
    ],
    "wof:name":"Dacoma Ltd",
    "wof:placetype":"venue"
},
  "geometry": {"coordinates":[-2.155944109,52.2682800293],"type":"Point"}
}