{
  "type": "Feature",
  "properties": {
    "addr:full":"55 Carlton Rd Manchester Cheshire M16 8BZ",
    "addr:housenumber":"55",
    "addr:postcode":"m16 8bz",
    "addr:street":"Carlton Rd",
    "iso:country":"GB",
    "sg:address":"55 Carlton Rd",
    "sg:city":"Manchester",
    "sg:classifiers":[
        {
            "category":"Social Services",
            "subcategory":"Child Care",
            "type":"Services"
        }
    ],
    "sg:phone":"+44 161 226 8228",
    "sg:postcode":"M16 8BZ",
    "sg:province":"Cheshire",
    "sg:tags":[
        "children's",
        "home"
    ],
    "wof:name":"Woodlands Residential Unit",
    "wof:placetype":"venue"
},
  "geometry": {"coordinates":[-2.260681,53.453541],"type":"Point"}
}