{
  "type": "Feature",
  "properties": {
    "iso:country":"GB",
    "sg:address":"Thistley Haugh Farm, Longhorsley",
    "sg:city":"Morpeth",
    "sg:classifiers":[
        {
            "category":"Farming",
            "subcategory":"Livestock Farm",
            "type":"Manufacturing & Wholesale Goods"
        }
    ],
    "sg:phone":"+44 1665 570629",
    "sg:postcode":"NE65 8RG",
    "sg:province":"Northumberland",
    "sg:tags":[
        "others"
    ],
    "wof:name":"H L Nelless",
    "wof:placetype":"venue"
},
  "geometry": {"coordinates":[-1.7684099674,55.2459602356],"type":"Point"}
}