{
  "type": "Feature",
  "properties": {
    "addr:full":"118 Battersea Park Road London Greater London SW11 4LY",
    "addr:housenumber":"118",
    "addr:postcode":"sw11 4ly",
    "addr:street":"Battersea Park Road",
    "iso:country":"GB",
    "sg:address":"118 Battersea Park Road",
    "sg:city":"London",
    "sg:classifiers":[
        {
            "category":"Restaurant",
            "type":"Food & Drink"
        }
    ],
    "sg:phone":"+44 20 7622 0776",
    "sg:postcode":"SW11 4LY",
    "sg:province":"Greater London",
    "wof:name":"Starburger",
    "wof:placetype":"venue"
},
  "geometry": {"coordinates":[-0.154745,51.474697],"type":"Point"}
}