{
  "type": "Feature",
  "properties": {
    "addr:full":"North Lodge House, Cambusnethan Estate Wishaw North Lanarkshire ML2 0RL",
    "addr:postcode":"ml2 0rl",
    "addr:street":"Cambusnethan Estate",
    "iso:country":"GB",
    "sg:address":"North Lodge House, Cambusnethan Estate",
    "sg:city":"Wishaw",
    "sg:classifiers":[
        {
            "category":"Recreation",
            "subcategory":"Dog Park",
            "type":"Entertainment"
        },
        {
            "category":"Retail",
            "subcategory":"Pet Boarding",
            "type":"Services"
        }
    ],
    "sg:phone":"+44 1698 373868",
    "sg:postcode":"ML2 0RL",
    "sg:province":"North Lanarkshire",
    "sg:tags":[
        "kennel"
    ],
    "wof:name":"Priory Lodge Kennels",
    "wof:placetype":"venue"
},
  "geometry": {"coordinates":[-3.892439,55.779079],"type":"Point"}
}