{
  "type": "Feature",
  "properties": {
    "addr:full":"1 Garden St North Halifax West Yorkshire HX3 6AE",
    "addr:housenumber":"1",
    "addr:postcode":"hx3 6ae",
    "addr:street":"Garden St",
    "iso:country":"GB",
    "sg:address":"1 Garden St North",
    "sg:city":"Halifax",
    "sg:classifiers":[
        {
            "category":"Shopping",
            "subcategory":"Books",
            "type":"Retail Goods"
        }
    ],
    "sg:phone":"+44 1422 344344",
    "sg:postcode":"HX3 6AE",
    "sg:province":"West Yorkshire",
    "wof:name":"True North Books Ltd.",
    "wof:placetype":"venue"
},
  "geometry": {"coordinates":[-1.856009,53.727982],"type":"Point"}
}