{
  "type": "Feature",
  "properties": {
    "iso:country":"GB",
    "sg:address":"Rocklands, Brynmor Terrace",
    "sg:city":"Penmaenmawr",
    "sg:classifiers":[
        {
            "category":"Freight",
            "type":"Transportation"
        }
    ],
    "sg:phone":"+44 1492 593168",
    "sg:postcode":"LL34 6AP",
    "sg:province":"Conwy",
    "sg:tags":[
        "haulage",
        "road"
    ],
    "wof:name":"Fedrick Plant Services",
    "wof:placetype":"venue"
},
  "geometry": {"coordinates":[-3.937264,53.266945],"type":"Point"}
}