{
  "type": "Feature",
  "properties": {
    "iso:country":"GB",
    "sg:address":"110 Marl Close",
    "sg:city":"Yeovil",
    "sg:classifiers":[
        {
            "category":"Retail",
            "subcategory":"Repair Shop",
            "type":"Services"
        },
        {
            "category":"Building & Trades",
            "subcategory":"Construction",
            "type":"Services"
        }
    ],
    "sg:phone":"+44 1935 422146",
    "sg:postcode":"BA21 3NQ",
    "sg:province":"Somerset",
    "sg:tags":[
        "builder",
        "upholsterer"
    ],
    "wof:name":"David J Field",
    "wof:placetype":"venue"
},
  "geometry": {"coordinates":[-2.649904,50.952736],"type":"Point"}
}