{
  "type": "Feature",
  "properties": {
    "iso:country":"GB",
    "sg:address":"6 Broad Street",
    "sg:city":"Fraserburgh",
    "sg:classifiers":[
        {
            "category":"Professional",
            "subcategory":"Lawyer & Legal Services",
            "type":"Services"
        },
        {
            "category":"Real Estate",
            "subcategory":"Real Estate Agent",
            "type":"Services"
        }
    ],
    "sg:phone":"+44 1346 513338",
    "sg:postcode":"AB43 9AH",
    "sg:province":"Aberdeenshire",
    "sg:tags":[
        "solicitor"
    ],
    "wof:name":"MASSON & GLENNIE",
    "wof:placetype":"venue"
},
  "geometry": {"coordinates":[-2.004787,57.692772],"type":"Point"}
}