{
  "type": "Feature",
  "properties": {
    "addr:full":"Rear Of 100 Cleveland St Doncaster South Yorkshire DN1 3DP",
    "addr:postcode":"dn1 3dp",
    "addr:street":"Cleveland St",
    "iso:country":"GB",
    "sg:address":"Rear Of 100 Cleveland St",
    "sg:city":"Doncaster",
    "sg:classifiers":[
        {
            "category":"Autos & Motor Vehicles",
            "subcategory":"Auto Supplies",
            "type":"Retail Goods"
        }
    ],
    "sg:phone":"+44 1302 739500",
    "sg:postcode":"DN1 3DP",
    "sg:province":"South Yorkshire",
    "sg:tags":[
        "machine",
        "laundry",
        "washing"
    ],
    "wof:name":"Markdown Appliance Warehouse",
    "wof:placetype":"venue"
},
  "geometry": {"coordinates":[-1.130565,53.524391],"type":"Point"}
}