{
  "type": "Feature",
  "properties": {
    "iso:country":"GB",
    "sg:address":"Head Office, 27 Mayfield Rd",
    "sg:city":"Walton On Thames",
    "sg:classifiers":[
        {
            "category":"Professional",
            "type":"Services"
        }
    ],
    "sg:phone":"+44 1932 267227",
    "sg:postcode":"KT12 5PL",
    "sg:province":"Surrey",
    "sg:tags":[
        "caterer"
    ],
    "wof:name":"Compton Rhodes Ltd",
    "wof:placetype":"venue"
},
  "geometry": {"coordinates":[-0.420704,51.384346],"type":"Point"}
}