{
  "type": "Feature",
  "properties": {
    "iso:country":"GB",
    "sg:address":"Unit 6, Haleacre Industrial Area, Watchet Lane",
    "sg:city":"Great Missenden",
    "sg:classifiers":[
        {
            "category":"Retail",
            "subcategory":"Repair Shop",
            "type":"Services"
        }
    ],
    "sg:postcode":"HP16 0DR",
    "sg:province":"Buckinghamshire",
    "sg:tags":[
        "furniture"
    ],
    "wof:name":"Andrew Lucas",
    "wof:placetype":"venue"
},
  "geometry": {"coordinates":[-0.709043026,51.7040672302],"type":"Point"}
}