{
  "type": "Feature",
  "properties": {
    "addr:full":"40 Richmond Road Kingston-upon-thames Greater London KT2 5EE",
    "addr:housenumber":"40",
    "addr:postcode":"kt2 5ee",
    "addr:street":"Richmond Road",
    "iso:country":"GB",
    "sg:address":"40 Richmond Road",
    "sg:city":"Kingston-upon-thames",
    "sg:classifiers":[
        {
            "category":"Retail",
            "subcategory":"Storage",
            "type":"Services"
        }
    ],
    "sg:phone":"+44 20 8974 6544",
    "sg:postcode":"KT2 5EE",
    "sg:province":"Greater London",
    "sg:tags":[
        "household",
        "removal"
    ],
    "wof:name":"Cox Thornbury",
    "wof:placetype":"venue"
},
  "geometry": {"coordinates":[-0.300496012,51.4140434265],"type":"Point"}
}