{
  "type": "Feature",
  "properties": {
    "iso:country":"GB",
    "sg:address":"29 Hamilton Sq",
    "sg:city":"Birkenhead",
    "sg:classifiers":[
        {
            "category":"Professional",
            "subcategory":"Employment Agencies",
            "type":"Services"
        }
    ],
    "sg:phone":"+44 151 666 2627",
    "sg:postcode":"L41 6AZ",
    "sg:province":"Merseyside",
    "sg:tags":[
        "modelling"
    ],
    "wof:name":"Sirens Modelling Agency",
    "wof:placetype":"venue"
},
  "geometry": {"coordinates":[-3.01715,53.393101],"type":"Point"}
}