{
  "type": "Feature",
  "properties": {
    "addr:full":"118 Whinbush Road Hitchin Bedfordshire SG5 1PN",
    "addr:housenumber":"118",
    "addr:postcode":"sg5 1pn",
    "addr:street":"Whinbush Road",
    "iso:country":"GB",
    "sg:address":"118 Whinbush Road",
    "sg:city":"Hitchin",
    "sg:classifiers":[
        {
            "category":"Health Services",
            "subcategory":"Health Practitioner",
            "type":"Services"
        }
    ],
    "sg:postcode":"SG5 1PN",
    "sg:province":"Bedfordshire",
    "sg:tags":[
        "osteopath"
    ],
    "wof:name":"David Kellett",
    "wof:placetype":"venue"
},
  "geometry": {"coordinates":[-0.2737700045,51.9497795105],"type":"Point"}
}