{
  "type": "Feature",
  "properties": {
    "iso:country":"GB",
    "sg:address":"Ferry Road, Fiskerton",
    "sg:city":"Lincoln",
    "sg:classifiers":[
        {
            "category":"Education",
            "subcategory":"School",
            "type":"Public Place"
        },
        {
            "category":"Government",
            "subcategory":"Office",
            "type":"Public Place"
        }
    ],
    "sg:phone":"+44 1522 751049",
    "sg:postcode":"LN3 4HU",
    "sg:province":"Lincolnshire",
    "sg:tags":[
        "local",
        "authority"
    ],
    "wof:name":"Fiskerton C of E Primary School",
    "wof:placetype":"venue"
},
  "geometry": {"coordinates":[-0.4257259965,53.2355384827],"type":"Point"}
}