{
  "type": "Feature",
  "properties": {
    "iso:country":"GB",
    "sg:address":"148 Battlefield Road",
    "sg:city":"Glasgow",
    "sg:classifiers":[
        {
            "category":"Health Services",
            "subcategory":"Doctor",
            "type":"Services"
        }
    ],
    "sg:phone":"+44 141 632 6310",
    "sg:postcode":"G42 9JT",
    "sg:province":"Glasgow City",
    "sg:tags":[
        "practitioners"
    ],
    "wof:name":"Lynn Jacobs Dr",
    "wof:placetype":"venue"
},
  "geometry": {"coordinates":[-4.2650208473,55.8260917664],"type":"Point"}
}