{
  "type": "Feature",
  "properties": {
    "iso:country":"GB",
    "sg:address":"19 Sedgeford Road",
    "sg:city":"Shepherd's Bush",
    "sg:classifiers":[
        {
            "category":"Banks & Credit Unions",
            "subcategory":"Financial Services",
            "type":"Services"
        }
    ],
    "sg:postcode":"W12 0NA",
    "sg:province":"Greater London",
    "sg:tags":[
        "consultant"
    ],
    "wof:name":"Dromelia Investments Ltd",
    "wof:placetype":"venue"
},
  "geometry": {"coordinates":[-0.24442,51.508953],"type":"Point"}
}