{
  "type": "Feature",
  "properties": {
    "iso:country":"GB",
    "sg:address":"234 Oystermouth Road",
    "sg:city":"Swansea",
    "sg:classifiers":[
        {
            "category":"Bars & Pubs",
            "type":"Food & Drink"
        },
        {
            "category":"Health Services",
            "subcategory":"Nursing And Care Facility",
            "type":"Services"
        }
    ],
    "sg:phone":"+44 1792 646702",
    "sg:postcode":"SA1 3UH",
    "sg:province":"Neath Port Talbot",
    "sg:tags":[
        "pubs",
        "home",
        "inn"
    ],
    "wof:name":"The Sea Beach",
    "wof:placetype":"venue"
},
  "geometry": {"coordinates":[-3.9515109062,51.6142654419],"type":"Point"}
}