{
  "type": "Feature",
  "properties": {
    "iso:country":"GB",
    "sg:address":"The Old Church Hall, Church St South",
    "sg:city":"Liskeard",
    "sg:classifiers":[
        {
            "category":"Sports & Exercise",
            "subcategory":"Gym",
            "type":"Entertainment"
        }
    ],
    "sg:phone":"+44 1579 347374",
    "sg:postcode":"PL14 3AZ",
    "sg:province":"Cornwall",
    "sg:tags":[
        "fitness",
        "health",
        "centre"
    ],
    "wof:name":"Liskeard Gymnasium Centre",
    "wof:placetype":"venue"
},
  "geometry": {"coordinates":[-4.4658341408,50.4537963867],"type":"Point"}
}