{
  "type": "Feature",
  "properties": {
    "addr:full":"Meaton Farm, Wyre Forest, Rock Kidderminster Shropshire DY14 8NT",
    "addr:postcode":"dy14 8nt",
    "addr:street":"Wyre Forest",
    "iso:country":"GB",
    "sg:address":"Meaton Farm, Wyre Forest, Rock",
    "sg:city":"Kidderminster",
    "sg:classifiers":[
        {
            "category":"Home & Garden",
            "subcategory":"Garden Supply",
            "type":"Retail Goods"
        },
        {
            "category":"Farming",
            "subcategory":"Crops",
            "type":"Manufacturing & Wholesale Goods"
        },
        {
            "category":"Farming",
            "subcategory":"Livestock Farm",
            "type":"Manufacturing & Wholesale Goods"
        }
    ],
    "sg:phone":"+44 1299 841241",
    "sg:postcode":"DY14 8NT",
    "sg:province":"Shropshire",
    "sg:tags":[
        "bulb",
        "arable",
        "grower",
        "others"
    ],
    "wof:name":"John & Edwina Guest",
    "wof:placetype":"venue"
},
  "geometry": {"coordinates":[-2.38997,52.33881],"type":"Point"}
}