{
  "type": "Feature",
  "properties": {
    "addr:full":"150 Canterbury Road Croydon Surrey CR0 3HD",
    "addr:housenumber":"150",
    "addr:postcode":"cr0 3hd",
    "addr:street":"Canterbury Road",
    "iso:country":"GB",
    "sg:address":"150 Canterbury Road",
    "sg:city":"Croydon",
    "sg:classifiers":[
        {
            "category":"Freight",
            "type":"Transportation"
        },
        {
            "category":"Building & Trades",
            "subcategory":"Construction",
            "type":"Services"
        },
        {
            "category":"Manufacturing",
            "subcategory":"Lumber",
            "type":"Manufacturing & Wholesale Goods"
        }
    ],
    "sg:phone":"+44 20 8684 3537",
    "sg:postcode":"CR0 3HD",
    "sg:province":"Surrey",
    "sg:tags":[
        "merchants",
        "haulage",
        "agent",
        "contractor",
        "importer",
        "demolition",
        "road",
        "timber"
    ],
    "wof:name":"W O'Brien Haulage & Demolition Contractors Ltd.",
    "wof:placetype":"venue"
},
  "geometry": {"coordinates":[-0.1185870022,51.3857345581],"type":"Point"}
}