{
  "type": "Feature",
  "properties": {
    "addr:full":"Frimley Rd Aldershot Hampshire GU12 5NU",
    "addr:postcode":"gu12 5nu",
    "addr:street":"Frimley Rd",
    "iso:country":"GB",
    "sg:address":"Frimley Rd",
    "sg:city":"Aldershot",
    "sg:classifiers":[
        {
            "category":"Professional",
            "subcategory":"Business Services",
            "type":"Services"
        }
    ],
    "sg:phone":"+44 1252 549315",
    "sg:postcode":"GU12 5NU",
    "sg:province":"Hampshire",
    "sg:tags":[
        "shop",
        "cleaning"
    ],
    "wof:name":"Brite Cleaning Services",
    "wof:placetype":"venue"
},
  "geometry": {"coordinates":[-0.7226189971,51.2748184204],"type":"Point"}
}