{
  "type": "Feature",
  "properties": {
    "iso:country":"GB",
    "sg:address":"Colne Valley Business Park",
    "sg:city":"Huddersfield",
    "sg:classifiers":[
        {
            "category":"Wholesale",
            "subcategory":"Groceries",
            "type":"Manufacturing & Wholesale Goods"
        }
    ],
    "sg:phone":"+44 1484 846120",
    "sg:postcode":"HD7 5QG",
    "sg:province":"West Yorkshire",
    "sg:tags":[
        "food",
        "supplier",
        "drink"
    ],
    "wof:name":"Plus Foods",
    "wof:placetype":"venue"
},
  "geometry": {"coordinates":[-1.8570640087,53.624710083],"type":"Point"}
}