{
  "type": "Feature",
  "properties": {
    "addr:full":"1 The Green Marlborough Berkshire SN8 1AL",
    "addr:housenumber":"1",
    "addr:postcode":"sn8 1al",
    "addr:street":"The Green",
    "iso:country":"GB",
    "sg:address":"1 The Green",
    "sg:city":"Marlborough",
    "sg:classifiers":[
        {
            "category":"Organizations",
            "subcategory":"Non-profit Organization",
            "type":"Services"
        }
    ],
    "sg:phone":"+44 1672 516466",
    "sg:postcode":"SN8 1AL",
    "sg:province":"Berkshire",
    "sg:tags":[
        "organisation",
        "voluntary",
        "charity"
    ],
    "wof:name":"The Royal British Legion",
    "wof:placetype":"venue"
},
  "geometry": {"coordinates":[-1.7271540165,51.422328949],"type":"Point"}
}