{
  "type": "Feature",
  "properties": {
    "iso:country":"GB",
    "sg:address":"Smith Cottage",
    "sg:city":"Chorley",
    "sg:classifiers":[
        {
            "category":"Health Services",
            "subcategory":"Nursing And Care Facility",
            "type":"Services"
        },
        {
            "category":"Social Services",
            "subcategory":"Adult Care",
            "type":"Services"
        },
        {
            "category":"Social Services",
            "subcategory":"Retirement Home",
            "type":"Services"
        }
    ],
    "sg:phone":"+44 1257 263326",
    "sg:postcode":"PR7 1JF",
    "sg:province":"Lancashire",
    "sg:tags":[
        "provider"
    ],
    "wof:name":"Watch Home Care Services Ltd.",
    "wof:placetype":"venue"
},
  "geometry": {"coordinates":[-2.627004,53.645012],"type":"Point"}
}