{
  "type": "Feature",
  "properties": {
    "addr:full":"291 Maxwell Road Glasgow Glasgow City G41 1TD",
    "addr:housenumber":"291",
    "addr:postcode":"g41 1td",
    "addr:street":"Maxwell Road",
    "iso:country":"GB",
    "sg:address":"291 Maxwell Road",
    "sg:city":"Glasgow",
    "sg:classifiers":[
        {
            "category":"Cinema",
            "subcategory":"Movie Rental",
            "type":"Entertainment"
        }
    ],
    "sg:phone":"+44 141 429 0595",
    "sg:postcode":"G41 1TD",
    "sg:province":"Glasgow City",
    "sg:tags":[
        "video",
        "library"
    ],
    "wof:name":"Bobby Enterprises Indo Pak",
    "wof:placetype":"venue"
},
  "geometry": {"coordinates":[-4.273505,55.844234],"type":"Point"}
}