{
  "type": "Feature",
  "properties": {
    "iso:country":"GB",
    "sg:address":"Harmony House, 4 St Georges Place",
    "sg:city":"Llandudno",
    "sg:classifiers":[
        {
            "category":"Home & Garden",
            "subcategory":"Home Furnishings",
            "type":"Retail Goods"
        }
    ],
    "sg:phone":"+44 1492 860752",
    "sg:postcode":"LL30 2NR",
    "sg:province":"Conwy",
    "sg:tags":[
        "furnishers",
        "planner",
        "kitchen"
    ],
    "wof:name":"Moben Kitchens",
    "wof:placetype":"venue"
},
  "geometry": {"coordinates":[-3.8295450211,53.3244476318],"type":"Point"}
}