{
  "type": "Feature",
  "properties": {
    "addr:full":"John Storer House, Wards End Loughborough Leicestershire LE11 3HA",
    "addr:postcode":"le11 3ha",
    "addr:street":"Wards End",
    "iso:country":"GB",
    "sg:address":"John Storer House, Wards End",
    "sg:city":"Loughborough",
    "sg:classifiers":[
        {
            "category":"Organizations",
            "subcategory":"Non-profit Organization",
            "type":"Services"
        }
    ],
    "sg:phone":"+44 1509 265197",
    "sg:postcode":"LE11 3HA",
    "sg:province":"Leicestershire",
    "sg:tags":[
        "organisation",
        "voluntary",
        "charity"
    ],
    "wof:name":"The Shelthorpe Young Womens Project",
    "wof:placetype":"venue"
},
  "geometry": {"coordinates":[-1.2076590061,52.7691268921],"type":"Point"}
}