{
  "type": "Feature",
  "properties": {
    "addr:full":"64 Station Road Wallsend Tyne and Wear NE28 6TB",
    "addr:housenumber":"64",
    "addr:postcode":"ne28 6tb",
    "addr:street":"Station Road",
    "iso:country":"GB",
    "sg:address":"64 Station Road",
    "sg:city":"Wallsend",
    "sg:classifiers":[
        {
            "category":"Fast Food",
            "type":"Food & Drink"
        }
    ],
    "sg:phone":"+44 191 287 0123",
    "sg:postcode":"NE28 6TB",
    "sg:province":"Tyne and Wear",
    "sg:tags":[
        "away",
        "take"
    ],
    "wof:name":"The Big Sandwich Shop",
    "wof:placetype":"venue"
},
  "geometry": {"coordinates":[-1.532359,54.990257],"type":"Point"}
}