{
  "type": "Feature",
  "properties": {
    "addr:full":"Unit 1 Empress Business Ctr, Chester Road Manchester Cheshire M16 9EA",
    "addr:housenumber":"unit 1",
    "addr:postcode":"m16 9ea",
    "addr:street":"Empress Business Ctr Chester Road",
    "iso:country":"GB",
    "sg:address":"Unit 1 Empress Business Ctr, Chester Road",
    "sg:city":"Manchester",
    "sg:classifiers":[
        {
            "category":"Communications",
            "subcategory":"Film & Video Production",
            "type":"Services"
        }
    ],
    "sg:phone":"+44 161 877 9309",
    "sg:postcode":"M16 9EA",
    "sg:province":"Cheshire",
    "sg:tags":[
        "tv",
        "studio"
    ],
    "wof:name":"Feature Films for Families (U K)",
    "wof:placetype":"venue"
},
  "geometry": {"coordinates":[-2.2680590153,53.4667510986],"type":"Point"}
}