{
  "type": "Feature",
  "properties": {
    "addr:full":"Wycombe Road Marlow Berkshire SL7 3RA",
    "addr:postcode":"sl7 3ra",
    "addr:street":"Wycombe Road",
    "iso:country":"GB",
    "sg:address":"Wycombe Road",
    "sg:city":"Marlow",
    "sg:classifiers":[
        {
            "category":"Bars & Pubs",
            "type":"Food & Drink"
        }
    ],
    "sg:phone":"+44 1628 483109",
    "sg:postcode":"SL7 3RA",
    "sg:province":"Berkshire",
    "sg:tags":[
        "pubs",
        "inn"
    ],
    "wof:name":"The Three Horseshoes",
    "wof:placetype":"venue"
},
  "geometry": {"coordinates":[-0.7680190206,51.5810012817],"type":"Point"}
}