{
  "type": "Feature",
  "properties": {
    "addr:full":"81 Hormare Crescent, Storington Pulborough West Sussex RH20 4QW",
    "addr:housenumber":"81",
    "addr:postcode":"rh20 4qw",
    "addr:street":"Hormare Crescent Storington Pulborough",
    "iso:country":"GB",
    "sg:address":"81 Hormare Crescent, Storington",
    "sg:city":"Pulborough",
    "sg:classifiers":[
        {
            "category":"Bus Stop",
            "subcategory":"None",
            "type":"Transportation"
        }
    ],
    "sg:phone":"+44 1903 743571",
    "sg:postcode":"RH20 4QW",
    "sg:province":"West Sussex",
    "sg:tags":[
        "filter"
    ],
    "wof:name":"Liquid Systems (Sales) Ltd.",
    "wof:placetype":"venue"
},
  "geometry": {"coordinates":[-0.465593,50.922386],"type":"Point"}
}