{
  "type": "Feature",
  "properties": {
    "iso:country":"GB",
    "sg:address":"78 North Rd",
    "sg:city":"Saltash",
    "sg:classifiers":[
        {
            "category":"Health Services",
            "subcategory":"Nursing And Care Facility",
            "type":"Services"
        }
    ],
    "sg:phone":"+44 1752 846822",
    "sg:postcode":"PL12 6BE",
    "sg:province":"Cornwall",
    "sg:tags":[
        "home"
    ],
    "wof:name":"Boisdale & Penkelly House",
    "wof:placetype":"venue"
},
  "geometry": {"coordinates":[-4.211903,50.410599],"type":"Point"}
}