{
  "type": "Feature",
  "properties": {
    "iso:country":"GB",
    "sg:address":"King Street, East Harling",
    "sg:city":"Norwich",
    "sg:classifiers":[
        {
            "category":"Retail",
            "subcategory":"Auto Repair",
            "type":"Services"
        }
    ],
    "sg:phone":"+44 1953 717383",
    "sg:postcode":"NR16 2QG",
    "sg:province":"Norfolk",
    "sg:tags":[
        "modification",
        "garage"
    ],
    "wof:name":"Chiswell's Garage Services Ltd.",
    "wof:placetype":"venue"
},
  "geometry": {"coordinates":[0.933933,52.438038],"type":"Point"}
}