{
  "type": "Feature",
  "properties": {
    "iso:country":"GB",
    "sg:address":"67 Bayswater Road",
    "sg:city":"Leeds",
    "sg:classifiers":[
        {
            "category":"Organizations",
            "subcategory":"Non-profit Organization",
            "type":"Services"
        }
    ],
    "sg:phone":"+44 113 240 5894",
    "sg:postcode":"LS8 5LN",
    "sg:province":"West Yorkshire",
    "sg:tags":[
        "charitable",
        "organisation",
        "voluntary",
        "charity"
    ],
    "sg:website":"http://www.getawaygirls.co.uk",
    "wof:name":"Getaway Girls Ltd",
    "wof:placetype":"venue"
},
  "geometry": {"coordinates":[-1.521,53.810211],"type":"Point"}
}