{
  "type": "Feature",
  "properties": {
    "addr:full":"3 The Ginnel, Market Place Devizes Wiltshire SN10 1HN",
    "addr:housenumber":"3",
    "addr:postcode":"sn10 1hn",
    "addr:street":"The;Market Place",
    "iso:country":"GB",
    "sg:address":"3 The Ginnel, Market Place",
    "sg:city":"Devizes",
    "sg:classifiers":[
        {
            "category":"Personal",
            "subcategory":"Beauty Salon",
            "type":"Services"
        }
    ],
    "sg:phone":"+44 1380 725221",
    "sg:postcode":"SN10 1HN",
    "sg:province":"Wiltshire",
    "wof:name":"The Beauty Clinic",
    "wof:placetype":"venue"
},
  "geometry": {"coordinates":[-1.995031,51.351479],"type":"Point"}
}