{
  "type": "Feature",
  "properties": {
    "iso:country":"GB",
    "sg:address":"Haykin, St Margarets Lane",
    "sg:city":"Fareham",
    "sg:classifiers":[
        {
            "category":"Retail",
            "subcategory":"Auto Repair",
            "type":"Services"
        }
    ],
    "sg:postcode":"PO14 4BN",
    "sg:province":"Hampshire",
    "sg:tags":[
        "modification",
        "garage"
    ],
    "wof:name":"S P Autos",
    "wof:placetype":"venue"
},
  "geometry": {"coordinates":[-1.2416030169,50.848449707],"type":"Point"}
}