{
  "type": "Feature",
  "properties": {
    "addr:full":"The Rest, Murrayfield, St Abbs Eyemouth Scottish Borders TD14 5PP",
    "addr:postcode":"td14 5pp",
    "addr:street":"Rest;St",
    "iso:country":"GB",
    "sg:address":"The Rest, Murrayfield, St Abbs",
    "sg:city":"Eyemouth",
    "sg:classifiers":[
        {
            "category":"Professional",
            "subcategory":"Accounting & Tax Preparation",
            "type":"Services"
        }
    ],
    "sg:postcode":"TD14 5PP",
    "sg:province":"Scottish Borders",
    "sg:tags":[
        "accountant"
    ],
    "wof:name":"J C Gibson & Co",
    "wof:placetype":"venue"
},
  "geometry": {"coordinates":[-2.0951159,55.8731422424],"type":"Point"}
}