{
  "type": "Feature",
  "properties": {
    "iso:country":"GB",
    "sg:address":"Albion Street",
    "sg:city":"Otley",
    "sg:classifiers":[
        {
            "category":"Real Estate",
            "subcategory":"Developer",
            "type":"Services"
        }
    ],
    "sg:phone":"+44 1943 464100",
    "sg:postcode":"LS21 1RT",
    "sg:province":"North Yorkshire",
    "sg:tags":[
        "property"
    ],
    "wof:name":"Dalesgate Developments Ltd.",
    "wof:placetype":"venue"
},
  "geometry": {"coordinates":[-1.686499,53.903801],"type":"Point"}
}