{
  "type": "Feature",
  "properties": {
    "iso:country":"GB",
    "sg:address":"16 Kirkham Street",
    "sg:city":"London",
    "sg:classifiers":[
        {
            "category":"Personal",
            "subcategory":"Beauty Salon",
            "type":"Services"
        }
    ],
    "sg:phone":"+44 20 8854 9383",
    "sg:postcode":"SE18 2JU",
    "sg:province":"Greater London",
    "sg:tags":[
        "unisex",
        "hairdresser"
    ],
    "wof:name":"Babs Hair Fashions",
    "wof:placetype":"venue"
},
  "geometry": {"coordinates":[0.088253,51.479164],"type":"Point"}
}