{
  "type": "Feature",
  "properties": {
    "addr:full":"44 High Street, Lochmaben Lockerbie Dumfries and Galloway DG11 1NH",
    "addr:housenumber":"44",
    "addr:postcode":"dg11 1nh",
    "addr:street":"High Street",
    "iso:country":"GB",
    "sg:address":"44 High Street, Lochmaben",
    "sg:city":"Lockerbie",
    "sg:classifiers":[
        {
            "category":"Health Services",
            "subcategory":"Doctor",
            "type":"Services"
        }
    ],
    "sg:phone":"+44 1387 810252",
    "sg:postcode":"DG11 1NH",
    "sg:province":"Dumfries and Galloway",
    "sg:tags":[
        "practitioners"
    ],
    "wof:name":"THE SURGERY",
    "wof:placetype":"venue"
},
  "geometry": {"coordinates":[-3.439456,55.127396],"type":"Point"}
}