{
  "type": "Feature",
  "properties": {
    "iso:country":"GB",
    "sg:address":"25 Darenth Road",
    "sg:city":"London",
    "sg:classifiers":[
        {
            "category":"Shopping",
            "subcategory":"Department Store",
            "type":"Retail Goods"
        }
    ],
    "sg:postcode":"N16 6EP",
    "sg:province":"Greater London",
    "wof:name":"Euro Antique Watches Ltd.",
    "wof:placetype":"venue"
},
  "geometry": {"coordinates":[-0.0698829964,51.5688209534],"type":"Point"}
}