{
  "type": "Feature",
  "properties": {
    "addr:full":"Unit 6, Solent Rd Havant Hampshire PO9 1JH",
    "addr:housenumber":"unit 6",
    "addr:postcode":"po9 1jh",
    "addr:street":"Solent Rd",
    "iso:country":"GB",
    "sg:address":"Unit 6, Solent Rd",
    "sg:city":"Havant",
    "sg:classifiers":[
        {
            "category":"Retail",
            "subcategory":"Auto Repair",
            "type":"Services"
        }
    ],
    "sg:phone":"+44 23 9249 2510",
    "sg:postcode":"PO9 1JH",
    "sg:province":"Hampshire",
    "sg:tags":[
        "modification",
        "garage"
    ],
    "wof:name":"Seward Service Centre",
    "wof:placetype":"venue"
},
  "geometry": {"coordinates":[-0.9919490218,50.8498687744],"type":"Point"}
}