{
  "type": "Feature",
  "properties": {
    "addr:full":"Unit 1, Sproughton Business Park, Farthing Road Ipswich Suffolk IP1 5AP",
    "addr:housenumber":"unit 1 sproughton business",
    "addr:postcode":"ip1 5ap",
    "addr:street":"Park Farthing Road",
    "iso:country":"GB",
    "sg:address":"Unit 1, Sproughton Business Park, Farthing Road",
    "sg:city":"Ipswich",
    "sg:classifiers":[
        {
            "category":"Manufacturing",
            "subcategory":"Chemicals & Compounds",
            "type":"Manufacturing & Wholesale Goods"
        },
        {
            "category":"Shopping",
            "type":"Retail Goods"
        }
    ],
    "sg:postcode":"IP1 5AP",
    "sg:province":"Suffolk",
    "sg:tags":[
        "merchant"
    ],
    "wof:name":"Auto Valets Supplies",
    "wof:placetype":"venue"
},
  "geometry": {"coordinates":[1.1437879801,52.0577774048],"type":"Point"}
}