{
  "type": "Feature",
  "properties": {
    "addr:full":"14 Eden Road Dunfermline Fife KY11 4RU",
    "addr:housenumber":"14",
    "addr:postcode":"ky11 4ru",
    "addr:street":"Eden Road",
    "iso:country":"GB",
    "sg:address":"14 Eden Road",
    "sg:city":"Dunfermline",
    "sg:classifiers":[
        {
            "category":"Retail",
            "subcategory":"Repair Shop",
            "type":"Services"
        }
    ],
    "sg:phone":"+44 1383 735730",
    "sg:postcode":"KY11 4RU",
    "sg:province":"Fife",
    "sg:tags":[
        "maintenance"
    ],
    "wof:name":"Tennent Allcare Property Maintenance",
    "wof:placetype":"venue"
},
  "geometry": {"coordinates":[-3.4282519817,56.0637054443],"type":"Point"}
}