{
  "type": "Feature",
  "properties": {
    "iso:country":"GB",
    "sg:address":"13 Harewood Terrace",
    "sg:city":"Haverhill",
    "sg:classifiers":[
        {
            "category":"Shopping",
            "subcategory":"Pharmacy",
            "type":"Retail Goods"
        }
    ],
    "sg:phone":"+44 1440 713365",
    "sg:postcode":"CB9 8JL",
    "sg:province":"Essex",
    "sg:tags":[
        "pharmacist",
        "chemist"
    ],
    "wof:name":"D Holland",
    "wof:placetype":"venue"
},
  "geometry": {"coordinates":[0.42728,52.077763],"type":"Point"}
}