{
  "type": "Feature",
  "properties": {
    "addr:full":"1 Gibraltar Walk London Greater London E2 7LH",
    "addr:housenumber":"1",
    "addr:postcode":"e2 7lh",
    "addr:street":"Gibraltar Walk",
    "iso:country":"GB",
    "sg:address":"1 Gibraltar Walk",
    "sg:city":"London",
    "sg:classifiers":[
        {
            "category":"Manufacturing",
            "subcategory":"Tools & Machinery",
            "type":"Manufacturing & Wholesale Goods"
        }
    ],
    "sg:postcode":"E2 7LH",
    "sg:province":"Greater London",
    "sg:tags":[
        "society",
        "friendly"
    ],
    "wof:name":"Summers Henderson & Co",
    "wof:placetype":"venue"
},
  "geometry": {"coordinates":[-0.0704080015,51.5257492065],"type":"Point"}
}