{
  "type": "Feature",
  "properties": {
    "iso:country":"GB",
    "sg:address":"Greenacres, Roughcote Lane, Caverswall",
    "sg:city":"Stoke-on-trent",
    "sg:classifiers":[
        {
            "category":"Freight",
            "type":"Transportation"
        }
    ],
    "sg:phone":"+44 1782 392319",
    "sg:postcode":"ST11 9ET",
    "sg:province":"Staffordshire",
    "sg:tags":[
        "haulage",
        "road"
    ],
    "wof:name":"H Ratcliffe & Son",
    "wof:placetype":"venue"
},
  "geometry": {"coordinates":[-2.074084,52.983345],"type":"Point"}
}