{
  "type": "Feature",
  "properties": {
    "iso:country":"GB",
    "sg:address":"66 Coningsby Gardens",
    "sg:city":"Chingford",
    "sg:classifiers":[
        {
            "category":"Personal",
            "subcategory":"Tanning Parlor",
            "type":"Services"
        }
    ],
    "sg:phone":"+44 20 8531 8647",
    "sg:postcode":"E4 9BD",
    "sg:province":"Greater London",
    "sg:tags":[
        "sunbeds"
    ],
    "wof:name":"Sunbed Hire",
    "wof:placetype":"venue"
},
  "geometry": {"coordinates":[-0.011059,51.608845],"type":"Point"}
}