{
  "type": "Feature",
  "properties": {
    "addr:full":"1 Queen Alexandra Road North Shields Tyne and Wear NE29 9AS",
    "addr:housenumber":"1",
    "addr:postcode":"ne29 9as",
    "addr:street":"Queen Alexandra Road",
    "iso:country":"GB",
    "sg:address":"1 Queen Alexandra Road",
    "sg:city":"North Shields",
    "sg:classifiers":[
        {
            "category":"Government",
            "subcategory":"Post Office",
            "type":"Public Place"
        }
    ],
    "sg:phone":"+44 191 257 5757",
    "sg:postcode":"NE29 9AS",
    "sg:province":"Tyne and Wear",
    "wof:name":"Preston Road Post Office",
    "wof:placetype":"venue"
},
  "geometry": {"coordinates":[-1.4507950544,55.014881134],"type":"Point"}
}