{
  "type": "Feature",
  "properties": {
    "iso:country":"GB",
    "sg:address":"31 Chapel Walk",
    "sg:city":"Sheffield",
    "sg:classifiers":[
        {
            "category":"Food & Beverages",
            "subcategory":"Fruits & Vegetables",
            "type":"Retail Goods"
        }
    ],
    "sg:phone":"+44 114 272 0839",
    "sg:postcode":"S1 2PD",
    "sg:province":"South Yorkshire",
    "sg:tags":[
        "greengrocer"
    ],
    "wof:name":"J W Bradshaw & Sons (Sheffield) Ltd.",
    "wof:placetype":"venue"
},
  "geometry": {"coordinates":[-1.4677779675,53.3818855286],"type":"Point"}
}