{
  "type": "Feature",
  "properties": {
    "addr:full":"66-68 Hill Head Road, Hill Head Fareham Hampshire PO14 3JP",
    "addr:housenumber":"66-68",
    "addr:postcode":"po14 3jp",
    "addr:street":"Hill Head Road Hill",
    "iso:country":"GB",
    "sg:address":"66-68 Hill Head Road, Hill Head",
    "sg:city":"Fareham",
    "sg:classifiers":[
        {
            "category":"Shopping",
            "subcategory":"Clothing, Apparel, & Fashions",
            "type":"Retail Goods"
        },
        {
            "category":"Cafe",
            "type":"Food & Drink"
        }
    ],
    "sg:postcode":"PO14 3JP",
    "sg:province":"Hampshire",
    "sg:tags":[
        "shop",
        "tea",
        "room"
    ],
    "wof:name":"Emma's Ladies Fashions",
    "wof:placetype":"venue"
},
  "geometry": {"coordinates":[-1.233048,50.816845],"type":"Point"}
}