{
  "type": "Feature",
  "properties": {
    "iso:country":"GB",
    "sg:address":"56 Main Street, Buchlyvie",
    "sg:city":"Stirling",
    "sg:classifiers":[
        {
            "category":"Retail",
            "subcategory":"Laundry & Dry Cleaning",
            "type":"Services"
        },
        {
            "category":"Professional",
            "subcategory":"Art Services",
            "type":"Services"
        },
        {
            "category":"Building & Trades",
            "subcategory":"Construction",
            "type":"Services"
        }
    ],
    "sg:phone":"+44 1360 850441",
    "sg:postcode":"FK8 3LX",
    "sg:province":"Stirling",
    "sg:tags":[
        "ironing",
        "painter",
        "decorator",
        "home"
    ],
    "wof:name":"Andrew J Blain",
    "wof:placetype":"venue"
},
  "geometry": {"coordinates":[-4.293129921,56.1153678894],"type":"Point"}
}