{
  "type": "Feature",
  "properties": {
    "addr:full":"St Annes Close, Breamish Street Newcastle-upon-tyne Tyne and Wear NE1 2QP",
    "addr:postcode":"ne1 2qp",
    "addr:street":"St Annes Close Breamish Street",
    "iso:country":"GB",
    "sg:address":"St Annes Close, Breamish Street",
    "sg:city":"Newcastle-upon-tyne",
    "sg:classifiers":[
        {
            "category":"Organizations",
            "subcategory":"Non-profit Organization",
            "type":"Services"
        }
    ],
    "sg:phone":"+44 191 261 1516",
    "sg:postcode":"NE1 2QP",
    "sg:province":"Tyne and Wear",
    "sg:tags":[
        "organisation",
        "voluntary",
        "charity"
    ],
    "wof:name":"St.Annes Tenants Association",
    "wof:placetype":"venue"
},
  "geometry": {"coordinates":[-1.593739,54.973526],"type":"Point"}
}