{
  "type": "Feature",
  "properties": {
    "addr:full":"Bridge Garage, Culmington Road London Greater London W13 9NB",
    "addr:postcode":"w13 9nb",
    "addr:street":"Culmington Road",
    "iso:country":"GB",
    "sg:address":"Bridge Garage, Culmington Road",
    "sg:city":"London",
    "sg:classifiers":[
        {
            "category":"Retail",
            "subcategory":"Auto Repair",
            "type":"Services"
        }
    ],
    "sg:postcode":"W13 9NB",
    "sg:province":"Greater London",
    "sg:tags":[
        "modification",
        "garage"
    ],
    "wof:name":"The Impact Group",
    "wof:placetype":"venue"
},
  "geometry": {"coordinates":[-0.3143300116,51.511631012],"type":"Point"}
}