{
  "type": "Feature",
  "properties": {
    "iso:country":"GB",
    "sg:address":"16 Margaret Street, Outwood",
    "sg:city":"Wakefield",
    "sg:classifiers":[
        {
            "category":"Professional",
            "subcategory":"Engineering",
            "type":"Services"
        }
    ],
    "sg:phone":"+44 1924 829671",
    "sg:postcode":"WF1 2NJ",
    "sg:province":"West Yorkshire",
    "sg:tags":[
        "gas",
        "engineer"
    ],
    "wof:name":"Five Star Property Services",
    "wof:placetype":"venue"
},
  "geometry": {"coordinates":[-1.509548,53.707539],"type":"Point"}
}