{
  "type": "Feature",
  "properties": {
    "addr:full":"Cadmore Lane, Cheshunt Waltham Cross Essex EN8 9LQ",
    "addr:postcode":"en8 9lq",
    "addr:street":"Cadmore Lane;Cross",
    "iso:country":"GB",
    "sg:address":"Cadmore Lane, Cheshunt",
    "sg:city":"Waltham Cross",
    "sg:classifiers":[
        {
            "category":"Utilities",
            "subcategory":"Refuse",
            "type":"Services"
        }
    ],
    "sg:postcode":"EN8 9LQ",
    "sg:province":"Essex",
    "sg:tags":[
        "disposal",
        "waste"
    ],
    "wof:name":"Tigger Hygiene",
    "wof:placetype":"venue"
},
  "geometry": {"coordinates":[-0.0347179994,51.7098388672],"type":"Point"}
}