{
  "type": "Feature",
  "properties": {
    "iso:country":"GB",
    "sg:address":"10-16 Bourne Road",
    "sg:city":"Southampton",
    "sg:classifiers":[
        {
            "category":"Autos & Motor Vehicles",
            "subcategory":"Automobile Sales",
            "type":"Retail Goods"
        }
    ],
    "sg:postcode":"SO15 3AA",
    "sg:province":"Hampshire",
    "sg:tags":[
        "car"
    ],
    "wof:name":"B LAWTON",
    "wof:placetype":"venue"
},
  "geometry": {"coordinates":[-1.4182460308,50.9094429016],"type":"Point"}
}