{
  "type": "Feature",
  "properties": {
    "addr:full":"Unit 6, Station Approach Road Coulsdon Surrey CR5 2NR",
    "addr:housenumber":"unit 6",
    "addr:postcode":"cr5 2nr",
    "addr:street":"Station Approach Road",
    "iso:country":"GB",
    "sg:address":"Unit 6, Station Approach Road",
    "sg:city":"Coulsdon",
    "sg:classifiers":[
        {
            "category":"Personal",
            "type":"Services"
        }
    ],
    "sg:phone":"+44 20 8664 8333",
    "sg:postcode":"CR5 2NR",
    "sg:province":"Surrey",
    "sg:tags":[
        "delivery"
    ],
    "wof:name":"Lynx Express Delivery Network",
    "wof:placetype":"venue"
},
  "geometry": {"coordinates":[-0.1354690045,51.3211631775],"type":"Point"}
}