{
  "type": "Feature",
  "properties": {
    "addr:full":"35 Beacon Way Banstead Surrey SM7 1DZ",
    "addr:housenumber":"35",
    "addr:postcode":"sm7 1dz",
    "addr:street":"Beacon Way",
    "iso:country":"GB",
    "sg:address":"35 Beacon Way",
    "sg:city":"Banstead",
    "sg:classifiers":[
        {
            "category":"Communications",
            "type":"Services"
        },
        {
            "category":"Professional",
            "subcategory":"Computer Services",
            "type":"Services"
        }
    ],
    "sg:phone":"+44 1737 379999",
    "sg:postcode":"SM7 1DZ",
    "sg:province":"Surrey",
    "sg:tags":[
        "data",
        "network"
    ],
    "sg:website":"http://www.odrl.co.uk",
    "wof:name":"Optical Drive Repair Ltd.",
    "wof:placetype":"venue"
},
  "geometry": {"coordinates":[-0.2214079946,51.318107605],"type":"Point"}
}