{
  "type": "Feature",
  "properties": {
    "iso:country":"GB",
    "sg:address":"8 St Vigeans Gardens",
    "sg:city":"Arbroath",
    "sg:classifiers":[
        {
            "category":"Military Area",
            "subcategory":"Air Force Base",
            "type":"Public Place"
        }
    ],
    "sg:phone":"+44 1241 439439",
    "sg:postcode":"DD11 4EB",
    "sg:province":"Angus",
    "sg:tags":[
        "taxi",
        "hire",
        "private"
    ],
    "wof:name":"Condie Taxis",
    "wof:placetype":"venue"
},
  "geometry": {"coordinates":[-2.5932021141,56.56407547],"type":"Point"}
}