{
  "type": "Feature",
  "properties": {
    "addr:full":"Garden St Wakefield West Yorkshire WF1 1DX",
    "addr:postcode":"wf1 1dx",
    "addr:street":"Garden St",
    "iso:country":"GB",
    "sg:address":"Garden St",
    "sg:city":"Wakefield",
    "sg:classifiers":[
        {
            "category":"Organizations",
            "subcategory":"Non-profit Organization",
            "type":"Services"
        }
    ],
    "sg:phone":"+44 1924 365625",
    "sg:postcode":"WF1 1DX",
    "sg:province":"West Yorkshire",
    "sg:tags":[
        "organisation",
        "animal",
        "welfare"
    ],
    "wof:name":"RSPCA",
    "wof:placetype":"venue"
},
  "geometry": {"coordinates":[-1.502819,53.680908],"type":"Point"}
}