{
  "type": "Feature",
  "properties": {
    "addr:full":"1st Floor, 18 Hall Street St Helens Merseyside WA10 1DL",
    "addr:housenumber":"18",
    "addr:postcode":"wa10 1dl",
    "addr:street":"Hall Street",
    "iso:country":"GB",
    "sg:address":"1st Floor, 18 Hall Street",
    "sg:city":"St Helens",
    "sg:classifiers":[
        {
            "category":"Personal",
            "type":"Services"
        }
    ],
    "sg:phone":"+44 1744 25050",
    "sg:postcode":"WA10 1DL",
    "sg:province":"Merseyside",
    "sg:tags":[
        "wedding"
    ],
    "wof:name":"Sheena Conroy",
    "wof:placetype":"venue"
},
  "geometry": {"coordinates":[-2.7327730656,53.4524841309],"type":"Point"}
}