{
  "type": "Feature",
  "properties": {
    "iso:country":"GB",
    "sg:address":"Axbridge Road, Knowle",
    "sg:city":"Bristol",
    "sg:classifiers":[
        {
            "category":"Bars & Pubs",
            "type":"Food & Drink"
        }
    ],
    "sg:phone":"+44 117 977 6926",
    "sg:postcode":"BS4 2RU",
    "sg:province":"City of Bristol",
    "sg:tags":[
        "pubs",
        "inn"
    ],
    "wof:name":"Friendship Club",
    "wof:placetype":"venue"
},
  "geometry": {"coordinates":[-2.5787510872,51.4340133667],"type":"Point"}
}