{
  "type": "Feature",
  "properties": {
    "addr:full":"2 All Hallows Road, Bispham Blackpool Lancashire FY2 0AU",
    "addr:housenumber":"2",
    "addr:postcode":"fy2 0au",
    "addr:street":"All Hallows Road",
    "iso:country":"GB",
    "sg:address":"2 All Hallows Road, Bispham",
    "sg:city":"Blackpool",
    "sg:classifiers":[
        {
            "category":"Banks & Credit Unions",
            "subcategory":"Bank",
            "type":"Services"
        }
    ],
    "sg:phone":"+44 1253 613200",
    "sg:postcode":"FY2 0AU",
    "sg:province":"Lancashire",
    "wof:name":"Hsbc Bank Plc",
    "wof:placetype":"venue"
},
  "geometry": {"coordinates":[-3.039348,53.852402],"type":"Point"}
}