{
  "type": "Feature",
  "properties": {
    "iso:country":"GB",
    "sg:address":"30a Davy's Lane, Bracebridge Heath",
    "sg:city":"Lincoln",
    "sg:classifiers":[
        {
            "category":"Building & Trades",
            "subcategory":"Construction",
            "type":"Services"
        }
    ],
    "sg:phone":"+44 1522 529882",
    "sg:postcode":"LN4 2NB",
    "sg:province":"Lincolnshire",
    "sg:tags":[
        "builder"
    ],
    "wof:name":"Melladay & Sons",
    "wof:placetype":"venue"
},
  "geometry": {"coordinates":[-0.5383999944,53.2167053223],"type":"Point"}
}