{
  "type": "Feature",
  "properties": {
    "iso:country":"GB",
    "sg:address":"4 Garden Street",
    "sg:city":"Hebden Bridge",
    "sg:classifiers":[
        {
            "category":"Insurance",
            "subcategory":"Health Insurance",
            "type":"Services"
        }
    ],
    "sg:phone":"+44 1422 847400",
    "sg:postcode":"HX7 8AQ",
    "sg:province":"West Yorkshire",
    "wof:name":"E B I Healthwise Ltd.",
    "wof:placetype":"venue"
},
  "geometry": {"coordinates":[-2.011176,53.74144],"type":"Point"}
}