{
  "type": "Feature",
  "properties": {
    "addr:full":"96 Kingsland High Street London Greater London E8 2NS",
    "addr:housenumber":"96",
    "addr:postcode":"e8 2ns",
    "addr:street":"Kingsland High Street",
    "iso:country":"GB",
    "sg:address":"96 Kingsland High Street",
    "sg:city":"London",
    "sg:classifiers":[
        {
            "category":"Shopping",
            "subcategory":"Clothing, Apparel, & Fashions",
            "type":"Retail Goods"
        }
    ],
    "sg:phone":"+44 20 7503 8191",
    "sg:postcode":"E8 2NS",
    "sg:province":"Greater London",
    "sg:tags":[
        "shop",
        "ladieswear"
    ],
    "wof:name":"Fashion Express",
    "wof:placetype":"venue"
},
  "geometry": {"coordinates":[-0.07515,51.548946],"type":"Point"}
}