{
  "type": "Feature",
  "properties": {
    "addr:full":"18a St Johns Road Isleworth Greater London TW7 6NW",
    "addr:housenumber":"18a",
    "addr:postcode":"tw7 6nw",
    "addr:street":"St Johns Road",
    "iso:country":"GB",
    "sg:address":"18a St Johns Road",
    "sg:city":"Isleworth",
    "sg:classifiers":[
        {
            "category":"Home & Garden",
            "subcategory":"Building Materials",
            "type":"Retail Goods"
        }
    ],
    "sg:phone":"+44 20 8568 6781",
    "sg:postcode":"TW7 6NW",
    "sg:province":"Greater London",
    "sg:tags":[
        "gate",
        "door",
        "barrier"
    ],
    "wof:name":"Automatic Doors & Gates",
    "wof:placetype":"venue"
},
  "geometry": {"coordinates":[-0.3380439878,51.4739837646],"type":"Point"}
}