{
  "type": "Feature",
  "properties": {
    "iso:country":"GB",
    "sg:address":"4 Eldon Way Industrial Estate",
    "sg:city":"Hockley",
    "sg:classifiers":[
        {
            "category":"Building & Trades",
            "subcategory":"Construction",
            "type":"Services"
        }
    ],
    "sg:phone":"+44 1702 202008",
    "sg:postcode":"SS5 4AD",
    "sg:province":"Essex",
    "sg:tags":[
        "builder"
    ],
    "wof:name":"Justcrown Ltd.",
    "wof:placetype":"venue"
},
  "geometry": {"coordinates":[0.65642,51.60281],"type":"Point"}
}