{
  "type": "Feature",
  "properties": {
    "addr:full":"7 Sanders Close, Finedon Road Industrial Estate Wellingborough Northamptonshire NN8 4HQ",
    "addr:housenumber":"7",
    "addr:postcode":"nn8 4hq",
    "addr:street":"Sanders Close Finedon Road Industrial Estate",
    "iso:country":"GB",
    "sg:address":"7 Sanders Close, Finedon Road Industrial Estate",
    "sg:city":"Wellingborough",
    "sg:classifiers":[
        {
            "category":"Manufacturing",
            "subcategory":"Wood Products",
            "type":"Manufacturing & Wholesale Goods"
        },
        {
            "category":"Manufacturing",
            "subcategory":"Paper Products",
            "type":"Manufacturing & Wholesale Goods"
        }
    ],
    "sg:phone":"+44 1933 224875",
    "sg:postcode":"NN8 4HQ",
    "sg:province":"Northamptonshire",
    "sg:tags":[
        "packaging",
        "material",
        "crate",
        "pallets",
        "manufacturer"
    ],
    "wof:name":"Fillmore Packaging Ltd",
    "wof:placetype":"venue"
},
  "geometry": {"coordinates":[-0.683503,52.321083],"type":"Point"}
}