{
  "type": "Feature",
  "properties": {
    "iso:country":"GB",
    "sg:address":"16 Windsor Terrace, Leeholme",
    "sg:city":"Bishop Auckland",
    "sg:classifiers":[
        {
            "category":"Manufacturing",
            "subcategory":"Signs",
            "type":"Manufacturing & Wholesale Goods"
        }
    ],
    "sg:postcode":"DL14 8HZ",
    "sg:province":"Durham",
    "sg:tags":[
        "writer"
    ],
    "wof:name":"Alan Stephenson",
    "wof:placetype":"venue"
},
  "geometry": {"coordinates":[-1.6163320541,54.6643714905],"type":"Point"}
}