{
  "type": "Feature",
  "properties": {
    "iso:country":"GB",
    "sg:address":"79 Egbert Gardens",
    "sg:city":"Wickford",
    "sg:classifiers":[
        {
            "category":"Shopping",
            "subcategory":"Stationery & Office Supplies",
            "type":"Retail Goods"
        }
    ],
    "sg:phone":"+44 1268 766176",
    "sg:postcode":"SS11 7BW",
    "sg:province":"Essex",
    "sg:tags":[
        "mobile",
        "catering"
    ],
    "wof:name":"Stans Snacks",
    "wof:placetype":"venue"
},
  "geometry": {"coordinates":[0.5279870033,51.6223106384],"type":"Point"}
}