{
  "type": "Feature",
  "properties": {
    "iso:country":"GB",
    "sg:address":"P O Box 4570, 1 Garden House, Meyrick Road",
    "sg:city":"Bournemouth",
    "sg:classifiers":[
        {
            "category":"Home & Garden",
            "subcategory":"Carpets & Floor Coverings",
            "type":"Retail Goods"
        }
    ],
    "sg:phone":"+44 1202 297778",
    "sg:postcode":"BH1 3EX",
    "sg:province":"Dorset",
    "sg:tags":[
        "cleaner",
        "upholstery"
    ],
    "wof:name":"C-U-C Carpet & Upholstery Cleaner",
    "wof:placetype":"venue"
},
  "geometry": {"coordinates":[-1.84894,50.722118],"type":"Point"}
}