{
  "type": "Feature",
  "properties": {
    "addr:full":"5 Avondale Industrial Estate, Avondale Road Stockport Cheshire SK3 0UD",
    "addr:housenumber":"5;estate",
    "addr:postcode":"sk3 0ud",
    "addr:street":"Avondale Industrial;Avondale Road",
    "iso:country":"GB",
    "sg:address":"5 Avondale Industrial Estate, Avondale Road",
    "sg:city":"Stockport",
    "sg:classifiers":[
        {
            "category":"Manufacturing",
            "subcategory":"Buildings",
            "type":"Manufacturing & Wholesale Goods"
        }
    ],
    "sg:postcode":"SK3 0UD",
    "sg:province":"Cheshire",
    "sg:tags":[
        "system",
        "air conditioning"
    ],
    "wof:name":"Air Conditioning Distribution Ltd.",
    "wof:placetype":"venue"
},
  "geometry": {"coordinates":[-2.161516,53.408409],"type":"Point"}
}