{
  "type": "Feature",
  "properties": {
    "iso:country":"GB",
    "sg:address":"5 Avondale Industrial Estate, Avondale Road",
    "sg:city":"Stockport",
    "sg:classifiers":[
        {
            "category":"Manufacturing",
            "subcategory":"Buildings",
            "type":"Manufacturing & Wholesale Goods"
        }
    ],
    "sg:postcode":"SK3 0UD",
    "sg:province":"Cheshire",
    "sg:tags":[
        "system",
        "air conditioning"
    ],
    "wof:name":"Air Conditioning Distribution Ltd.",
    "wof:placetype":"venue"
},
  "geometry": {"coordinates":[-2.161516,53.408409],"type":"Point"}
}