{
  "type": "Feature",
  "properties": {
    "addr:full":"110 Wandsworth Bridge Rd Fulham Greater London SW6 2TF",
    "addr:housenumber":"110",
    "addr:postcode":"sw6 2tf",
    "addr:street":"Wandsworth Bridge Rd",
    "iso:country":"GB",
    "sg:address":"110 Wandsworth Bridge Rd",
    "sg:city":"Fulham",
    "sg:classifiers":[
        {
            "category":"Professional",
            "type":"Services"
        }
    ],
    "sg:phone":"+44 20 7736 2653",
    "sg:postcode":"SW6 2TF",
    "sg:province":"Greater London",
    "sg:tags":[
        "entertainer"
    ],
    "wof:name":"Oriental Service",
    "wof:placetype":"venue"
},
  "geometry": {"coordinates":[-0.192012,51.473202],"type":"Point"}
}