{
  "type": "Feature",
  "properties": {
    "addr:full":"11 Liddington Hall Drive Guildford Surrey GU3 3AE",
    "addr:housenumber":"11",
    "addr:postcode":"gu3 3ae",
    "addr:street":"Liddington Hall Drive",
    "iso:country":"GB",
    "sg:address":"11 Liddington Hall Drive",
    "sg:city":"Guildford",
    "sg:classifiers":[
        {
            "category":"Professional",
            "subcategory":"Management & Consulting",
            "type":"Services"
        },
        {
            "category":"Professional",
            "subcategory":"Research",
            "type":"Services"
        }
    ],
    "sg:phone":"+44 1483 237681",
    "sg:postcode":"GU3 3AE",
    "sg:province":"Surrey",
    "sg:tags":[
        "marketing",
        "market",
        "consultant"
    ],
    "wof:name":"N L K Consultants",
    "wof:placetype":"venue"
},
  "geometry": {"coordinates":[-0.606679976,51.2564125061],"type":"Point"}
}