{
  "type": "Feature",
  "properties": {
    "addr:full":"Glossop Brook Road Glossop Derbyshire SK13 8GF",
    "addr:postcode":"sk13 8gf",
    "addr:street":"Brook Road",
    "iso:country":"GB",
    "sg:address":"Glossop Brook Road",
    "sg:city":"Glossop",
    "sg:classifiers":[
        {
            "category":"Manufacturing",
            "subcategory":"Textiles",
            "type":"Manufacturing & Wholesale Goods"
        }
    ],
    "sg:phone":"+44 1457 866927",
    "sg:postcode":"SK13 8GF",
    "sg:province":"Derbyshire",
    "sg:tags":[
        "knitwear"
    ],
    "wof:name":"Claremont Fabrics Ltd.",
    "wof:placetype":"venue"
},
  "geometry": {"coordinates":[-1.9595609903,53.4442024231],"type":"Point"}
}