{
  "type": "Feature",
  "properties": {
    "addr:full":"Mill Lane Works, Rhodes Street Hyde Cheshire SK14 2DS",
    "addr:postcode":"sk14 2ds",
    "addr:street":"Mill Lane;Rhodes Street",
    "iso:country":"GB",
    "sg:address":"Mill Lane Works, Rhodes Street",
    "sg:city":"Hyde",
    "sg:classifiers":[
        {
            "category":"Professional",
            "type":"Services"
        }
    ],
    "sg:phone":"+44 161 368 3267",
    "sg:postcode":"SK14 2DS",
    "sg:province":"Cheshire",
    "sg:tags":[
        "pattern",
        "industrial",
        "maker"
    ],
    "wof:name":"Pennington Pattern Makers Ltd.",
    "wof:placetype":"venue"
},
  "geometry": {"coordinates":[-2.0901689529,53.4526786804],"type":"Point"}
}