{
  "type": "Feature",
  "properties": {
    "addr:full":"43 Central Square Wembley Greater London HA9 7AL",
    "addr:housenumber":"43",
    "addr:postcode":"ha9 7al",
    "addr:street":"Central",
    "iso:country":"GB",
    "sg:address":"43 Central Square",
    "sg:city":"Wembley",
    "sg:classifiers":[
        {
            "category":"Banks & Credit Unions",
            "subcategory":"Financial Services",
            "type":"Services"
        }
    ],
    "sg:phone":"+44 20 8902 3636",
    "sg:postcode":"HA9 7AL",
    "sg:province":"Greater London",
    "sg:tags":[
        "cashing",
        "cheque"
    ],
    "wof:name":"C-4-c",
    "wof:placetype":"venue"
},
  "geometry": {"coordinates":[-0.3167760074,51.5531005859],"type":"Point"}
}