{
  "type": "Feature",
  "properties": {
    "iso:country":"GB",
    "sg:address":"9 Guild St",
    "sg:city":"Stratford Upon Avon",
    "sg:classifiers":[
        {
            "category":"Shopping",
            "subcategory":"Clothing, Apparel, & Fashions",
            "type":"Retail Goods"
        }
    ],
    "sg:phone":"+44 1789 263671",
    "sg:postcode":"CV37 6RE",
    "sg:province":"Warwickshire",
    "sg:tags":[
        "shop",
        "hat"
    ],
    "wof:name":"Hat Elegance",
    "wof:placetype":"venue"
},
  "geometry": {"coordinates":[-1.707148,52.194248],"type":"Point"}
}