{
  "type": "Feature",
  "properties": {
    "addr:full":"Cloisters House, Cloisters Business Park, 8 Battersea Park Road London Greater London SW8 4BH",
    "addr:housenumber":"8",
    "addr:postcode":"sw8 4bh",
    "addr:street":"Park;Battersea Park Road",
    "iso:country":"GB",
    "sg:address":"Cloisters House, Cloisters Business Park, 8 Battersea Park Road",
    "sg:city":"London",
    "sg:classifiers":[
        {
            "category":"Personal",
            "type":"Services"
        },
        {
            "category":"Professional",
            "subcategory":"Lawyer & Legal Services",
            "type":"Services"
        }
    ],
    "sg:phone":"+44 20 7498 5575",
    "sg:postcode":"SW8 4BH",
    "sg:province":"Greater London",
    "sg:tags":[
        "advice",
        "counselling"
    ],
    "wof:name":"The Property Service Partnership Plc",
    "wof:placetype":"venue"
},
  "geometry": {"coordinates":[-0.1474599987,51.4772186279],"type":"Point"}
}