{
  "type": "Feature",
  "properties": {
    "addr:full":"Inverhouse Dental Practice, 6 Glan Y Mor Rd Llandudno Conwy LL30 3NL",
    "addr:housenumber":"6",
    "addr:postcode":"ll30 3nl",
    "addr:street":"Glan Y Mor Rd",
    "iso:country":"GB",
    "sg:address":"Inverhouse Dental Practice, 6 Glan Y Mor Rd",
    "sg:city":"Llandudno",
    "sg:classifiers":[
        {
            "category":"Health Services",
            "subcategory":"Dentist",
            "type":"Services"
        }
    ],
    "sg:phone":"+44 1492 543258",
    "sg:postcode":"LL30 3NL",
    "sg:province":"Conwy",
    "wof:name":"Paul Blears Denplan",
    "wof:placetype":"venue"
},
  "geometry": {"coordinates":[-3.77573,53.317612],"type":"Point"}
}