{
  "type": "Feature",
  "properties": {
    "iso:country":"GB",
    "sg:address":"134 Harley Street",
    "sg:city":"London",
    "sg:classifiers":[
        {
            "category":"Health Services",
            "subcategory":"Doctor",
            "type":"Services"
        }
    ],
    "sg:phone":"+44 20 7486 2622",
    "sg:postcode":"W1G 7JZ",
    "sg:province":"Greater London",
    "sg:tags":[
        "surgeon"
    ],
    "wof:name":"Orthopaedic Surgeon",
    "wof:placetype":"venue"
},
  "geometry": {"coordinates":[-0.1483580023,51.5226097107],"type":"Point"}
}