{
  "type": "Feature",
  "properties": {
    "iso:country":"GB",
    "sg:address":"13 Ryecroft Park",
    "sg:city":"Wooler",
    "sg:classifiers":[
        {
            "category":"Professional",
            "type":"Services"
        }
    ],
    "sg:postcode":"NE71 6AS",
    "sg:province":"Northumberland",
    "sg:tags":[
        "writer"
    ],
    "wof:name":"Page Up",
    "wof:placetype":"venue"
},
  "geometry": {"coordinates":[-2.0176050663,55.5506362915],"type":"Point"}
}