{
  "type": "Feature",
  "properties": {
    "iso:country":"GB",
    "sg:address":"15a Church Rd, East Huntspill",
    "sg:city":"Highbridge",
    "sg:classifiers":[
        {
            "category":"Manufacturing",
            "subcategory":"Rubber & Plastics",
            "type":"Manufacturing & Wholesale Goods"
        }
    ],
    "sg:phone":"+44 1278 783997",
    "sg:postcode":"TA9 3PG",
    "sg:province":"Somerset",
    "sg:tags":[
        "product"
    ],
    "wof:name":"Econo-pak Ltd",
    "wof:placetype":"venue"
},
  "geometry": {"coordinates":[-2.9408960342,51.1998748779],"type":"Point"}
}