{
  "type": "Feature",
  "properties": {
    "addr:full":"Bakers Cross, Dorothy Avenue, Bakers Cross Cranbrook Kent TN17 3AL",
    "addr:postcode":"tn17 3al",
    "addr:street":"Dorothy Avenue",
    "iso:country":"GB",
    "sg:address":"Bakers Cross, Dorothy Avenue, Bakers Cross",
    "sg:city":"Cranbrook",
    "sg:classifiers":[
        {
            "category":"Shopping",
            "subcategory":"Computers & Home Electronics",
            "type":"Retail Goods"
        },
        {
            "category":"Manufacturing",
            "subcategory":"Lumber",
            "type":"Manufacturing & Wholesale Goods"
        }
    ],
    "sg:phone":"+44 1580 712465",
    "sg:postcode":"TN17 3AL",
    "sg:province":"Kent",
    "sg:tags":[
        "merchants",
        "importer",
        "agent",
        "timber"
    ],
    "wof:name":"Tudor Oak (Kent) Ltd.",
    "wof:placetype":"venue"
},
  "geometry": {"coordinates":[0.541203022,51.0943984985],"type":"Point"}
}