{
  "type": "Feature",
  "properties": {
    "addr:full":"Chester Green Road Derby Derbyshire DE1 3SF",
    "addr:postcode":"de1 3sf",
    "addr:street":"Green Road",
    "iso:country":"GB",
    "sg:address":"Chester Green Road",
    "sg:city":"Derby",
    "sg:classifiers":[
        {
            "category":"Professional",
            "subcategory":"Business Services",
            "type":"Services"
        }
    ],
    "sg:phone":"+44 1332 345240",
    "sg:postcode":"DE1 3SF",
    "sg:province":"Derbyshire",
    "sg:tags":[
        "bookmaker"
    ],
    "wof:name":"Chester Green Bookmakers",
    "wof:placetype":"venue"
},
  "geometry": {"coordinates":[-1.474415,52.932419],"type":"Point"}
}