{
  "type": "Feature",
  "properties": {
    "iso:country":"GB",
    "sg:address":"387-389 Dudley Road",
    "sg:city":"Birmingham",
    "sg:classifiers":[
        {
            "category":"Shopping",
            "subcategory":"Mobile Phones",
            "type":"Retail Goods"
        }
    ],
    "sg:postcode":"B18 4HD",
    "sg:province":"West Midlands",
    "wof:name":"Avmal Communications",
    "wof:placetype":"venue"
},
  "geometry": {"coordinates":[-1.9451869726,52.4872055054],"type":"Point"}
}