{
  "type": "Feature",
  "properties": {
    "addr:full":"8 Spark Hill, Cam Dursley Gloucestershire GL11 5UN",
    "addr:housenumber":"8",
    "addr:postcode":"gl11 5un",
    "addr:street":"Spark Hill Cam Dursley",
    "iso:country":"GB",
    "sg:address":"8 Spark Hill, Cam",
    "sg:city":"Dursley",
    "sg:classifiers":[
        {
            "category":"Professional",
            "subcategory":"Art Services",
            "type":"Services"
        }
    ],
    "sg:phone":"+44 1453 542536",
    "sg:postcode":"GL11 5UN",
    "sg:province":"Gloucestershire",
    "sg:tags":[
        "photographer"
    ],
    "wof:name":"Vision Photographics",
    "wof:placetype":"venue"
},
  "geometry": {"coordinates":[-2.3700299263,51.7028846741],"type":"Point"}
}