{
  "type": "Feature",
  "properties": {
    "iso:country":"GB",
    "sg:address":"Manor Farm, The Street, Tuddenham",
    "sg:city":"Ipswich",
    "sg:classifiers":[
        {
            "category":"Professional",
            "subcategory":"Detective & Security Services",
            "type":"Services"
        }
    ],
    "sg:phone":"+44 1473 785058",
    "sg:postcode":"IP6 9BT",
    "sg:province":"Suffolk",
    "sg:tags":[
        "locksmith"
    ],
    "wof:name":"Select Security",
    "wof:placetype":"venue"
},
  "geometry": {"coordinates":[1.196563,52.090988],"type":"Point"}
}