{
  "type": "Feature",
  "properties": {
    "addr:full":"198 Whitecross Road, Wilburton Ely Cambridgeshire CB6 3QB",
    "addr:housenumber":"198",
    "addr:postcode":"cb6 3qb",
    "addr:street":"Whitecross Road",
    "iso:country":"GB",
    "sg:address":"198 Whitecross Road, Wilburton",
    "sg:city":"Ely",
    "sg:classifiers":[
        {
            "category":"Recreation",
            "subcategory":"Amusement Park",
            "type":"Entertainment"
        }
    ],
    "sg:phone":"+44 1353 649861",
    "sg:postcode":"CB6 3QB",
    "sg:province":"Cambridgeshire",
    "sg:tags":[
        "arcade"
    ],
    "wof:name":"Protech Amusement Rides Ltd.",
    "wof:placetype":"venue"
},
  "geometry": {"coordinates":[0.203985,52.362865],"type":"Point"}
}