{
  "type": "Feature",
  "properties": {
    "addr:full":"Elizabeth House Sheltered Hsg, Sudellside Street Darwen Lancashire BB3 3EW",
    "addr:postcode":"bb3 3ew",
    "addr:street":"Sudellside Street",
    "iso:country":"GB",
    "sg:address":"Elizabeth House Sheltered Hsg, Sudellside Street",
    "sg:city":"Darwen",
    "sg:classifiers":[
        {
            "category":"Social Services",
            "subcategory":"Retirement Home",
            "type":"Services"
        },
        {
            "category":"Real Estate",
            "subcategory":"Real Estate Agent",
            "type":"Services"
        }
    ],
    "sg:phone":"+44 1254 703428",
    "sg:postcode":"BB3 3EW",
    "sg:province":"Lancashire",
    "sg:tags":[
        "accomodation",
        "housing",
        "sheltered"
    ],
    "wof:name":"Blackburn With Darwin Borough Council",
    "wof:placetype":"venue"
},
  "geometry": {"coordinates":[-2.4671690464,53.6941986084],"type":"Point"}
}