{
  "type": "Feature",
  "properties": {
    "iso:country":"GB",
    "sg:address":"4 Queens Avenue",
    "sg:city":"Hastings",
    "sg:classifiers":[
        {
            "category":"Food & Beverages",
            "subcategory":"Meat & Fish",
            "type":"Retail Goods"
        }
    ],
    "sg:phone":"+44 1424 423400",
    "sg:postcode":"TN34 1PA",
    "sg:province":"East Sussex",
    "sg:tags":[
        "butcher"
    ],
    "wof:name":"Arcade Butchers",
    "wof:placetype":"venue"
},
  "geometry": {"coordinates":[0.581168,50.856247],"type":"Point"}
}