{
  "type": "Feature",
  "properties": {
    "addr:full":"20 Norland Avenue Hull East Riding of Yorkshire HU4 7RB",
    "addr:housenumber":"20",
    "addr:postcode":"hu4 7rb",
    "addr:street":"Norland Avenue",
    "iso:country":"GB",
    "sg:address":"20 Norland Avenue",
    "sg:city":"Hull",
    "sg:classifiers":[
        {
            "category":"Freight",
            "type":"Transportation"
        },
        {
            "category":"Retail",
            "subcategory":"Storage",
            "type":"Services"
        }
    ],
    "sg:postcode":"HU4 7RB",
    "sg:province":"East Riding of Yorkshire",
    "sg:tags":[
        "haulage",
        "household",
        "road",
        "removal"
    ],
    "wof:name":"Swift Removals",
    "wof:placetype":"venue"
},
  "geometry": {"coordinates":[-0.408241,53.745205],"type":"Point"}
}