{
  "type": "Feature",
  "properties": {
    "addr:full":"West Carr Lane, Suttonfields Industrial Estate Hull East Riding of Yorkshire HU7 0BU",
    "addr:postcode":"hu7 0bu",
    "addr:street":"West Carr Lane Suttonfields Industrial Estate",
    "iso:country":"GB",
    "sg:address":"West Carr Lane, Suttonfields Industrial Estate",
    "sg:city":"Hull",
    "sg:classifiers":[
        {
            "category":"Bars & Pubs",
            "subcategory":"Wine Bar",
            "type":"Food & Drink"
        }
    ],
    "sg:phone":"+44 1482 836222",
    "sg:postcode":"HU7 0BU",
    "sg:province":"East Riding of Yorkshire",
    "sg:tags":[
        "industrial",
        "aerosol"
    ],
    "wof:name":"Aerosol Products Ltd.",
    "wof:placetype":"venue"
},
  "geometry": {"coordinates":[-0.3331339955,53.7785148621],"type":"Point"}
}