{
  "type": "Feature",
  "properties": {
    "addr:full":"Unit 1, Mavros House, 95 Vale Rd Finsbury Park Greater London N4 1TG",
    "addr:housenumber":"unit 1 mavros house 95",
    "addr:postcode":"n4 1tg",
    "addr:street":"Vale Rd",
    "iso:country":"GB",
    "sg:address":"Unit 1, Mavros House, 95 Vale Rd",
    "sg:city":"Finsbury Park",
    "sg:classifiers":[
        {
            "category":"Shopping",
            "subcategory":"Clothing, Apparel, & Fashions",
            "type":"Retail Goods"
        }
    ],
    "sg:phone":"+44 20 8880 1134",
    "sg:postcode":"N4 1TG",
    "sg:province":"Greater London",
    "sg:tags":[
        "clothing",
        "fabric"
    ],
    "wof:name":"Starpax",
    "wof:placetype":"venue"
},
  "geometry": {"coordinates":[-0.092239,51.574699],"type":"Point"}
}