{
  "type": "Feature",
  "properties": {
    "iso:country":"GB",
    "sg:address":"Ripley Drive, Normington Industrial Estate",
    "sg:city":"Normanton",
    "sg:classifiers":[
        {
            "category":"Manufacturing",
            "subcategory":"Chemicals & Compounds",
            "type":"Manufacturing & Wholesale Goods"
        }
    ],
    "sg:phone":"+44 1924 220213",
    "sg:postcode":"WF6 1QT",
    "sg:province":"West Yorkshire",
    "wof:name":"Proton Chemicals (London) Ltd.",
    "wof:placetype":"venue"
},
  "geometry": {"coordinates":[-1.414549,53.691971],"type":"Point"}
}