{
  "type": "Feature",
  "properties": {
    "iso:country":"GB",
    "sg:address":"Craigie Hall, 6 Rowan Road",
    "sg:city":"Glasgow",
    "sg:classifiers":[
        {
            "category":"Real Estate",
            "subcategory":"Surveying",
            "type":"Services"
        }
    ],
    "sg:phone":"+44 141 427 9626",
    "sg:postcode":"G41 5BS",
    "sg:province":"Glasgow City",
    "sg:tags":[
        "surveyor",
        "quantity"
    ],
    "wof:name":"McDougall Surveyors",
    "wof:placetype":"venue"
},
  "geometry": {"coordinates":[-4.304599762,55.8467597961],"type":"Point"}
}