{
  "type": "Feature",
  "properties": {
    "addr:full":"89 Woodside Business Park Birkenhead Merseyside L41 1EH",
    "addr:housenumber":"89",
    "addr:postcode":"l41 1eh",
    "addr:street":"Woodside Business Park",
    "iso:country":"GB",
    "sg:address":"89 Woodside Business Park",
    "sg:city":"Birkenhead",
    "sg:classifiers":[
        {
            "category":"Home & Garden",
            "subcategory":"Hardware",
            "type":"Retail Goods"
        }
    ],
    "sg:phone":"+44 151 647 4894",
    "sg:postcode":"L41 1EH",
    "sg:province":"Merseyside",
    "sg:tags":[
        "retailer",
        "lighting"
    ],
    "wof:name":"Craftplan Ltd The Chester Candle Shop",
    "wof:placetype":"venue"
},
  "geometry": {"coordinates":[-3.010172,53.39653],"type":"Point"}
}