{
  "type": "Feature",
  "properties": {
    "addr:full":"21 Pittodrie Pl Aberdeen Aberdeen City AB24 5QR",
    "addr:housenumber":"21",
    "addr:postcode":"ab24 5qr",
    "addr:street":"Pittodrie Pl",
    "iso:country":"GB",
    "sg:address":"21 Pittodrie Pl",
    "sg:city":"Aberdeen",
    "sg:classifiers":[
        {
            "category":"Shopping",
            "subcategory":"Department Store",
            "type":"Retail Goods"
        },
        {
            "category":"Food & Beverages",
            "subcategory":"Supermarket",
            "type":"Retail Goods"
        }
    ],
    "sg:postcode":"AB24 5QR",
    "sg:province":"Aberdeen City",
    "wof:name":"Milne,Peter,",
    "wof:placetype":"venue"
},
  "geometry": {"coordinates":[-2.092738,57.160721],"type":"Point"}
}