{
  "type": "Feature",
  "properties": {
    "addr:full":"19 New Bond Street London Greater London W1S 2RD",
    "addr:housenumber":"19",
    "addr:postcode":"w1s 2rd",
    "addr:street":"New Bond Street",
    "iso:country":"GB",
    "sg:address":"19 New Bond Street",
    "sg:city":"London",
    "sg:classifiers":[
        {
            "category":"Shopping",
            "subcategory":"Clothing, Apparel, & Fashions",
            "type":"Retail Goods"
        }
    ],
    "sg:phone":"+44 20 7495 3100",
    "sg:postcode":"W1S 2RD",
    "sg:province":"Greater London",
    "sg:tags":[
        "shop"
    ],
    "wof:name":"The Donna Karan Co. Store (U K) Ltd.",
    "wof:placetype":"venue"
},
  "geometry": {"coordinates":[-0.142671,51.510803],"type":"Point"}
}