{
  "type": "Feature",
  "properties": {
    "addr:full":"Unit 4, Lisle Road High Wycombe Buckinghamshire HP13 5SH",
    "addr:housenumber":"unit 4",
    "addr:postcode":"hp13 5sh",
    "addr:street":"Lisle Road",
    "iso:country":"GB",
    "sg:address":"Unit 4, Lisle Road",
    "sg:city":"High Wycombe",
    "sg:classifiers":[
        {
            "category":"Manufacturing",
            "subcategory":"Metals",
            "type":"Manufacturing & Wholesale Goods"
        },
        {
            "category":"Wholesale",
            "subcategory":"Metals & Minerals",
            "type":"Manufacturing & Wholesale Goods"
        }
    ],
    "sg:phone":"+44 1494 451251",
    "sg:postcode":"HP13 5SH",
    "sg:province":"Buckinghamshire",
    "sg:tags":[
        "fabricator",
        "work",
        "sheet"
    ],
    "wof:name":"Advanced Sheet Metal Engineering Ltd",
    "wof:placetype":"venue"
},
  "geometry": {"coordinates":[-0.755524,51.639236],"type":"Point"}
}