{
  "type": "Feature",
  "properties": {
    "addr:full":"20 Pencester Road Dover Kent CT16 1BW",
    "addr:housenumber":"20",
    "addr:postcode":"ct16 1bw",
    "addr:street":"Pencester Road",
    "iso:country":"GB",
    "sg:address":"20 Pencester Road",
    "sg:city":"Dover",
    "sg:classifiers":[
        {
            "category":"Retail",
            "subcategory":"Laundry & Dry Cleaning",
            "type":"Services"
        }
    ],
    "sg:phone":"+44 1304 201054",
    "sg:postcode":"CT16 1BW",
    "sg:province":"Kent",
    "sg:tags":[
        "cleaner",
        "alteration"
    ],
    "wof:name":"Elms Vale Cleaners Ltd",
    "wof:placetype":"venue"
},
  "geometry": {"coordinates":[1.313382,51.128216],"type":"Point"}
}