{
  "type": "Feature",
  "properties": {
    "iso:country":"GB",
    "sg:address":"Within Marks & Spencer, 118 Bonnar St",
    "sg:city":"Dunfermline",
    "sg:classifiers":[
        {
            "category":"Utilities",
            "subcategory":"Electric",
            "type":"Services"
        }
    ],
    "sg:phone":"+44 1383 724136",
    "sg:postcode":"KY12 7BE",
    "sg:province":"Fife",
    "sg:tags":[
        "electricity"
    ],
    "wof:name":"ScottishPower",
    "wof:placetype":"venue"
},
  "geometry": {"coordinates":[-3.4597,56.071678],"type":"Point"}
}