{
  "type": "Feature",
  "properties": {
    "addr:full":"Gladstone House, Adelaide Road London Greater London SW18 1DA",
    "addr:postcode":"sw18 1da",
    "addr:street":"Adelaide Road",
    "iso:country":"GB",
    "sg:address":"Gladstone House, Adelaide Road",
    "sg:city":"London",
    "sg:classifiers":[
        {
            "category":"Professional",
            "subcategory":"Management & Consulting",
            "type":"Services"
        },
        {
            "category":"Professional",
            "subcategory":"Art Services",
            "type":"Services"
        }
    ],
    "sg:phone":"+44 20 8875 1216",
    "sg:postcode":"SW18 1DA",
    "sg:province":"Greater London",
    "sg:tags":[
        "marketing",
        "graphic",
        "design",
        "designer",
        "consultant"
    ],
    "wof:name":"The Brand Works",
    "wof:placetype":"venue"
},
  "geometry": {"coordinates":[-0.19886,51.459789],"type":"Point"}
}