{
  "type": "Feature",
  "properties": {
    "iso:country":"GB",
    "sg:address":"30 Parksinde Avenue, Long Eaton",
    "sg:city":"Nottingham",
    "sg:classifiers":[
        {
            "category":"Professional",
            "subcategory":"Art Services",
            "type":"Services"
        }
    ],
    "sg:phone":"+44 115 972 5210",
    "sg:postcode":"NG10 4AN",
    "sg:province":"Derbyshire",
    "sg:tags":[
        "graphic",
        "designer"
    ],
    "wof:name":"Accent Promotions Ltd.",
    "wof:placetype":"venue"
},
  "geometry": {"coordinates":[-1.2826269865,52.9018630981],"type":"Point"}
}