{
  "type": "Feature",
  "properties": {
    "iso:country":"GB",
    "sg:address":"Flat 8, 1 Lady Nairne Pl",
    "sg:city":"Edinburgh",
    "sg:classifiers":[
        {
            "category":"Building & Trades",
            "subcategory":"Construction",
            "type":"Services"
        }
    ],
    "sg:postcode":"EH8 7LZ",
    "sg:province":"City of Edinburgh",
    "sg:tags":[
        "decorator",
        "painter"
    ],
    "wof:name":"Johnston,Brian,",
    "wof:placetype":"venue"
},
  "geometry": {"coordinates":[-3.1412,55.945862],"type":"Point"}
}