{
  "type": "Feature",
  "properties": {
    "addr:full":"159 Dialstone Lane Stockport Cheshire SK2 6AU",
    "addr:housenumber":"159",
    "addr:postcode":"sk2 6au",
    "addr:street":"Dialstone Lane",
    "iso:country":"GB",
    "sg:address":"159 Dialstone Lane",
    "sg:city":"Stockport",
    "sg:classifiers":[
        {
            "category":"Retail",
            "subcategory":"Portrait Studio",
            "type":"Services"
        },
        {
            "category":"Professional",
            "subcategory":"Art Services",
            "type":"Services"
        }
    ],
    "sg:phone":"+44 161 483 3114",
    "sg:postcode":"SK2 6AU",
    "sg:province":"Cheshire",
    "sg:tags":[
        "photographer",
        "commercial"
    ],
    "wof:name":"GEORGE & GLENYS DAWBER",
    "wof:placetype":"venue"
},
  "geometry": {"coordinates":[-2.132519,53.394669],"type":"Point"}
}