{
  "type": "Feature",
  "properties": {
    "addr:full":"Strathallan Isle Of Skye Highland IV41 8PN",
    "addr:postcode":"iv41 8pn",
    "addr:street":"Strathallan Isle",
    "iso:country":"GB",
    "sg:address":"Strathallan",
    "sg:city":"Isle Of Skye",
    "sg:classifiers":[
        {
            "category":"Communications",
            "type":"Services"
        }
    ],
    "sg:phone":"+44 1599 534525",
    "sg:postcode":"IV41 8PN",
    "sg:province":"Highland",
    "sg:tags":[
        "tv",
        "video",
        "radio"
    ],
    "wof:name":"John Ross",
    "wof:placetype":"venue"
},
  "geometry": {"coordinates":[-5.7273001671,57.2717895508],"type":"Point"}
}