{
  "type": "Feature",
  "properties": {
    "addr:full":"248 Telegraph Road, Heswall Wirral Merseyside CH60 7SG",
    "addr:housenumber":"248",
    "addr:postcode":"ch60 7sg",
    "addr:street":"Telegraph Road",
    "iso:country":"GB",
    "sg:address":"248 Telegraph Road, Heswall",
    "sg:city":"Wirral",
    "sg:classifiers":[
        {
            "category":"Shopping",
            "subcategory":"Books",
            "type":"Retail Goods"
        }
    ],
    "sg:phone":"+44 151 342 7290",
    "sg:postcode":"CH60 7SG",
    "sg:province":"Merseyside",
    "sg:tags":[
        "bookseller"
    ],
    "wof:name":"Linghams",
    "wof:placetype":"venue"
},
  "geometry": {"coordinates":[-3.101104,53.329384],"type":"Point"}
}