{
  "type": "Feature",
  "properties": {
    "addr:full":"183 Sheffield Road Chesterfield Derbyshire S41 7JQ",
    "addr:housenumber":"183",
    "addr:postcode":"s41 7jq",
    "addr:street":"Sheffield Road",
    "iso:country":"GB",
    "sg:address":"183 Sheffield Road",
    "sg:city":"Chesterfield",
    "sg:classifiers":[
        {
            "category":"Shopping",
            "subcategory":"News",
            "type":"Retail Goods"
        }
    ],
    "sg:postcode":"S41 7JQ",
    "sg:province":"Derbyshire",
    "sg:tags":[
        "newsagent"
    ],
    "wof:name":"Stonegravels Post Office",
    "wof:placetype":"venue"
},
  "geometry": {"coordinates":[-1.4278240204,53.2496337891],"type":"Point"}
}