{
  "type": "Feature",
  "properties": {
    "addr:full":"918 Oldham Rd Manchester Greater Manchester M40 2BS",
    "addr:housenumber":"918",
    "addr:postcode":"m40 2bs",
    "addr:street":"Oldham Rd",
    "iso:country":"GB",
    "sg:address":"918 Oldham Rd",
    "sg:city":"Manchester",
    "sg:classifiers":[
        {
            "category":"Fast Food",
            "type":"Food & Drink"
        }
    ],
    "sg:phone":"+44 161 205 0096",
    "sg:postcode":"M40 2BS",
    "sg:province":"Greater Manchester",
    "sg:tags":[
        "away",
        "take"
    ],
    "wof:name":"Woodys",
    "wof:placetype":"venue"
},
  "geometry": {"coordinates":[-2.192779,53.497509],"type":"Point"}
}