{
  "type": "Feature",
  "properties": {
    "iso:country":"GB",
    "sg:address":"15 Chertsey Road",
    "sg:city":"Ashford",
    "sg:classifiers":[
        {
            "category":"Home & Garden",
            "subcategory":"Garden Supply",
            "type":"Retail Goods"
        }
    ],
    "sg:phone":"+44 1784 252310",
    "sg:postcode":"TW15 1SP",
    "sg:province":"Greater London",
    "sg:tags":[
        "water"
    ],
    "wof:name":"Lily Pad Pond Renovations",
    "wof:placetype":"venue"
},
  "geometry": {"coordinates":[-0.439121,51.422798],"type":"Point"}
}