{
  "type": "Feature",
  "properties": {
    "addr:full":"316 Bradford Road Huddersfield West Yorkshire HD1 6LQ",
    "addr:housenumber":"316",
    "addr:postcode":"hd1 6lq",
    "addr:street":"Bradford Road",
    "iso:country":"GB",
    "sg:address":"316 Bradford Road",
    "sg:city":"Huddersfield",
    "sg:classifiers":[
        {
            "category":"Home & Garden",
            "subcategory":"Hardware",
            "type":"Retail Goods"
        }
    ],
    "sg:phone":"+44 1484 420698",
    "sg:postcode":"HD1 6LQ",
    "sg:province":"West Yorkshire",
    "sg:tags":[
        "retailer",
        "diy"
    ],
    "wof:name":"Fartown Diy",
    "wof:placetype":"venue"
},
  "geometry": {"coordinates":[-1.780513,53.661118],"type":"Point"}
}