{
  "type": "Feature",
  "properties": {
    "iso:country":"GB",
    "sg:address":"8 Birches Road, Codsall",
    "sg:city":"Wolverhampton",
    "sg:classifiers":[
        {
            "category":"Personal",
            "subcategory":"Beauty Salon",
            "type":"Services"
        },
        {
            "category":"Personal",
            "subcategory":"Barber",
            "type":"Services"
        }
    ],
    "sg:phone":"+44 1902 843616",
    "sg:postcode":"WV8 2JR",
    "sg:province":"Shropshire",
    "sg:tags":[
        "unisex",
        "hairdresser"
    ],
    "wof:name":"Look Ahead Ltd.",
    "wof:placetype":"venue"
},
  "geometry": {"coordinates":[-2.174781,52.61787],"type":"Point"}
}