{
  "type": "Feature",
  "properties": {
    "iso:country":"GB",
    "sg:address":"Newstead Lodge, Bullpit Road, Balderton",
    "sg:city":"Newark",
    "sg:classifiers":[
        {
            "category":"Farming",
            "subcategory":"Livestock Farm",
            "type":"Manufacturing & Wholesale Goods"
        }
    ],
    "sg:phone":"+44 1636 702070",
    "sg:postcode":"NG24 3LZ",
    "sg:province":"Nottinghamshire",
    "sg:tags":[
        "others"
    ],
    "wof:name":"Dessurne & Son",
    "wof:placetype":"venue"
},
  "geometry": {"coordinates":[-0.784139,53.05579],"type":"Point"}
}