{
  "type": "Feature",
  "properties": {
    "addr:full":"2 Foord Street Rochester Kent ME1 2BX",
    "addr:housenumber":"2",
    "addr:postcode":"me1 2bx",
    "addr:street":"Foord Street",
    "iso:country":"GB",
    "sg:address":"2 Foord Street",
    "sg:city":"Rochester",
    "sg:classifiers":[
        {
            "category":"Personal",
            "subcategory":"Shoe Repair & Shine",
            "type":"Services"
        },
        {
            "category":"Shopping",
            "subcategory":"Shoes",
            "type":"Retail Goods"
        }
    ],
    "sg:phone":"+44 1634 403775",
    "sg:postcode":"ME1 2BX",
    "sg:province":"Kent",
    "wof:name":"Cobblers",
    "wof:placetype":"venue"
},
  "geometry": {"coordinates":[0.5077800155,51.3833961487],"type":"Point"}
}