{
  "type": "Feature",
  "properties": {
    "iso:country":"GB",
    "sg:address":"6 Manor Road",
    "sg:city":"Wallasey",
    "sg:classifiers":[
        {
            "category":"Travel",
            "subcategory":"Hotels & Motels",
            "type":"Entertainment"
        }
    ],
    "sg:postcode":"CH45 4JB",
    "sg:province":"Merseyside",
    "sg:tags":[
        "house",
        "guest"
    ],
    "wof:name":"Carross Uk Ltd",
    "wof:placetype":"venue"
},
  "geometry": {"coordinates":[-3.043742,53.421143],"type":"Point"}
}