{
  "type": "Feature",
  "properties": {
    "addr:full":"106 Marsh Road Pinner Greater London HA5 5NA",
    "addr:housenumber":"106",
    "addr:postcode":"ha5 5na",
    "addr:street":"Marsh Road",
    "iso:country":"GB",
    "sg:address":"106 Marsh Road",
    "sg:city":"Pinner",
    "sg:classifiers":[
        {
            "category":"Personal",
            "subcategory":"Beauty Salon",
            "type":"Services"
        }
    ],
    "sg:phone":"+44 20 8866 4072",
    "sg:postcode":"HA5 5NA",
    "sg:province":"Greater London",
    "sg:tags":[
        "unisex",
        "hairdresser"
    ],
    "wof:name":"Lorusso Hairdressing",
    "wof:placetype":"venue"
},
  "geometry": {"coordinates":[-0.3818210065,51.5924263],"type":"Point"}
}