{
  "type": "Feature",
  "properties": {
    "iso:country":"GB",
    "sg:address":"53 Briarly Ho, Bury Rd",
    "sg:city":"Newmarket",
    "sg:classifiers":[
        {
            "category":"Food & Beverages",
            "subcategory":"Liquor & Beverages",
            "type":"Retail Goods"
        }
    ],
    "sg:phone":"+44 1638 751099",
    "sg:postcode":"CB8 7PY",
    "sg:province":"Cambridgeshire",
    "sg:tags":[
        "beer",
        "spirit",
        "wines"
    ],
    "wof:name":"G P Jones & Son",
    "wof:placetype":"venue"
},
  "geometry": {"coordinates":[0.399165988,52.2498168945],"type":"Point"}
}