{
  "type": "Feature",
  "properties": {
    "iso:country":"GB",
    "sg:address":"146 New Cavendish Street",
    "sg:city":"London",
    "sg:classifiers":[
        {
            "category":"Banks & Credit Unions",
            "subcategory":"Financial Services",
            "type":"Services"
        }
    ],
    "sg:postcode":"W1W 6YR",
    "sg:province":"Greater London",
    "sg:tags":[
        "consultant"
    ],
    "wof:name":"Farlind Investments Ltd",
    "wof:placetype":"venue"
},
  "geometry": {"coordinates":[-0.140158,51.520439],"type":"Point"}
}