{
  "type": "Feature",
  "properties": {
    "iso:country":"GB",
    "sg:address":"Sandars Road, Heapham Road Industrial Estate",
    "sg:city":"Gainsborough",
    "sg:classifiers":[
        {
            "category":"Autos & Motor Vehicles",
            "subcategory":"Auto Supplies",
            "type":"Retail Goods"
        }
    ],
    "sg:phone":"+44 1427 811211",
    "sg:postcode":"DN21 1RZ",
    "sg:province":"Lincolnshire",
    "sg:tags":[
        "component",
        "commercial"
    ],
    "wof:name":"Gainsborough Motor Factors",
    "wof:placetype":"venue"
},
  "geometry": {"coordinates":[-0.750004,53.39407],"type":"Point"}
}