{
  "type": "Feature",
  "properties": {
    "addr:full":"8 Cambridge Road, Granby Industrial Estate Weymouth Dorset DT4 9TJ",
    "addr:housenumber":"8;estate",
    "addr:postcode":"dt4 9tj",
    "addr:street":"Cambridge Road;Industrial",
    "iso:country":"GB",
    "sg:address":"8 Cambridge Road, Granby Industrial Estate",
    "sg:city":"Weymouth",
    "sg:classifiers":[
        {
            "category":"Home & Garden",
            "subcategory":"Home Furnishings",
            "type":"Retail Goods"
        },
        {
            "category":"Home & Garden",
            "subcategory":"Carpets & Floor Coverings",
            "type":"Retail Goods"
        }
    ],
    "sg:phone":"+44 1305 761740",
    "sg:postcode":"DT4 9TJ",
    "sg:province":"Dorset",
    "sg:tags":[
        "furnishers",
        "planner",
        "bedroom"
    ],
    "wof:name":"Bedroom Ideas Ltd",
    "wof:placetype":"venue"
},
  "geometry": {"coordinates":[-2.488292,50.612862],"type":"Point"}
}