{
  "type": "Feature",
  "properties": {
    "addr:full":"St Peters Villa, Ridley Lane, Mawdesley Ormskirk Lancashire L40 3SX",
    "addr:postcode":"l40 3sx",
    "addr:street":"Ridley Lane",
    "iso:country":"GB",
    "sg:address":"St Peters Villa, Ridley Lane, Mawdesley",
    "sg:city":"Ormskirk",
    "sg:classifiers":[
        {
            "category":"Retail",
            "subcategory":"Funeral Services",
            "type":"Services"
        }
    ],
    "sg:phone":"+44 1704 821900",
    "sg:postcode":"L40 3SX",
    "sg:province":"Lancashire",
    "wof:name":"Peace Burials Ltd.",
    "wof:placetype":"venue"
},
  "geometry": {"coordinates":[-2.7430799007,53.6242980957],"type":"Point"}
}