{
  "type": "Feature",
  "properties": {
    "addr:full":"217 Union Street Torquay Devon TQ1 4BZ",
    "addr:housenumber":"217",
    "addr:postcode":"tq1 4bz",
    "addr:street":"Union Street",
    "iso:country":"GB",
    "sg:address":"217 Union Street",
    "sg:city":"Torquay",
    "sg:classifiers":[
        {
            "category":"Bars & Pubs",
            "type":"Food & Drink"
        }
    ],
    "sg:phone":"+44 1803 292518",
    "sg:postcode":"TQ1 4BZ",
    "sg:province":"Devon",
    "sg:tags":[
        "pubs",
        "house",
        "inn",
        "public",
        "activity"
    ],
    "wof:name":"Fox & Firkin",
    "wof:placetype":"venue"
},
  "geometry": {"coordinates":[-3.537774086,50.4705123901],"type":"Point"}
}