{
  "type": "Feature",
  "properties": {
    "addr:full":"Tenby Ho, Fairplace Terr Okehampton Devon EX20 1DT",
    "addr:postcode":"ex20 1dt",
    "addr:street":"Terr",
    "iso:country":"GB",
    "sg:address":"Tenby Ho, Fairplace Terr",
    "sg:city":"Okehampton",
    "sg:classifiers":[
        {
            "category":"Organizations",
            "subcategory":"Non-profit Organization",
            "type":"Services"
        }
    ],
    "sg:phone":"+44 1837 53441",
    "sg:postcode":"EX20 1DT",
    "sg:province":"Devon",
    "sg:tags":[
        "organisation",
        "voluntary",
        "charity"
    ],
    "wof:name":"Home-Start Okehampton",
    "wof:placetype":"venue"
},
  "geometry": {"coordinates":[-4.002245903,50.7382965088],"type":"Point"}
}