{
  "type": "Feature",
  "properties": {
    "addr:full":"67 Northstead Manor Drive Scarborough North Yorkshire YO12 6AF",
    "addr:housenumber":"67",
    "addr:postcode":"yo12 6af",
    "addr:street":"Northstead Manor Drive",
    "iso:country":"GB",
    "sg:address":"67 Northstead Manor Drive",
    "sg:city":"Scarborough",
    "sg:classifiers":[
        {
            "category":"Travel",
            "subcategory":"Hotels & Motels",
            "type":"Entertainment"
        }
    ],
    "sg:phone":"+44 1723 365720",
    "sg:postcode":"YO12 6AF",
    "sg:province":"North Yorkshire",
    "wof:name":"Manor Heath Hotel",
    "wof:placetype":"venue"
},
  "geometry": {"coordinates":[-0.4127680063,54.2913093567],"type":"Point"}
}