{
  "type": "Feature",
  "properties": {
    "addr:full":"23 South Street Bridport Dorset DT6 3NU",
    "addr:housenumber":"23",
    "addr:postcode":"dt6 3nu",
    "addr:street":"South Street",
    "iso:country":"GB",
    "sg:address":"23 South Street",
    "sg:city":"Bridport",
    "sg:classifiers":[
        {
            "category":"Real Estate",
            "subcategory":"Real Estate Agent",
            "type":"Services"
        }
    ],
    "sg:phone":"+44 1308 422092",
    "sg:postcode":"DT6 3NU",
    "sg:province":"Dorset",
    "wof:name":"R & C Snell",
    "wof:placetype":"venue"
},
  "geometry": {"coordinates":[-2.75804,50.732483],"type":"Point"}
}