{
  "type": "Feature",
  "properties": {
    "iso:country":"GB",
    "sg:address":"Maybrook House, Queens Way",
    "sg:city":"Milton Keynes",
    "sg:classifiers":[
        {
            "category":"Home & Garden",
            "subcategory":"Household Appliances",
            "type":"Retail Goods"
        }
    ],
    "sg:phone":"+44 870 839 2801",
    "sg:postcode":"MK2 2DG",
    "sg:province":"Buckinghamshire",
    "sg:tags":[
        "electrical"
    ],
    "wof:name":"Calbarrie Ltd.",
    "wof:placetype":"venue"
},
  "geometry": {"coordinates":[-0.72371,51.995968],"type":"Point"}
}