{
  "type": "Feature",
  "properties": {
    "addr:full":"85 Pontcanna Street Cardiff Cardiff CF11 9HS",
    "addr:housenumber":"85",
    "addr:postcode":"cf11 9hs",
    "addr:street":"Pontcanna Street",
    "iso:country":"GB",
    "sg:address":"85 Pontcanna Street",
    "sg:city":"Cardiff",
    "sg:classifiers":[
        {
            "category":"Coffee & Tea",
            "type":"Food & Drink"
        }
    ],
    "sg:phone":"+44 29 2022 6554",
    "sg:postcode":"CF11 9HS",
    "sg:province":"Cardiff",
    "wof:name":"Crc Agencies Ltd.",
    "wof:placetype":"venue"
},
  "geometry": {"coordinates":[-3.200386,51.488354],"type":"Point"}
}