{
  "type": "Feature",
  "properties": {
    "iso:country":"GB",
    "sg:address":"58 High Street",
    "sg:city":"Tranent",
    "sg:classifiers":[
        {
            "category":"Communications",
            "type":"Services"
        }
    ],
    "sg:phone":"+44 1875 610310",
    "sg:postcode":"EH33 1HH",
    "sg:province":"East Lothian",
    "sg:tags":[
        "tv",
        "video",
        "radio"
    ],
    "wof:name":"Bisset & Steedman Ltd.",
    "wof:placetype":"venue"
},
  "geometry": {"coordinates":[-2.9518039227,55.9439086914],"type":"Point"}
}