{
  "type": "Feature",
  "properties": {
    "addr:full":"Mainscare Drive, Stonehouse Larkhall South Lanarkshire ML9 3QH",
    "addr:postcode":"ml9 3qh",
    "addr:street":"Mainscare Drive",
    "iso:country":"GB",
    "sg:address":"Mainscare Drive, Stonehouse",
    "sg:city":"Larkhall",
    "sg:classifiers":[
        {
            "category":"Place Of Worship",
            "type":"Public Place"
        }
    ],
    "sg:phone":"+44 1698 792870",
    "sg:postcode":"ML9 3QH",
    "sg:province":"South Lanarkshire",
    "wof:name":"The Salvation Army",
    "wof:placetype":"venue"
},
  "geometry": {"coordinates":[-3.9979450703,55.690322876],"type":"Point"}
}