{
  "type": "Feature",
  "properties": {
    "iso:country":"GB",
    "sg:address":"Rosemary Lane",
    "sg:city":"Beaumaris",
    "sg:classifiers":[
        {
            "category":"Professional",
            "subcategory":"Engineering",
            "type":"Services"
        }
    ],
    "sg:phone":"+44 1248 810463",
    "sg:postcode":"LL58 8ED",
    "sg:province":"Isle of Anglesey",
    "sg:tags":[
        "precision",
        "engineer"
    ],
    "wof:name":"Bico Ltd.",
    "wof:placetype":"venue"
},
  "geometry": {"coordinates":[-4.094774,53.263035],"type":"Point"}
}