{
  "type": "Feature",
  "properties": {
    "addr:full":"Unit 2 Kelverdale Court, Market Place Leyburn North Yorkshire DL8 5AQ",
    "addr:housenumber":"unit 2",
    "addr:postcode":"dl8 5aq",
    "addr:street":"Kelverdale;Market Place",
    "iso:country":"GB",
    "sg:address":"Unit 2 Kelverdale Court, Market Place",
    "sg:city":"Leyburn",
    "sg:classifiers":[
        {
            "category":"Building & Trades",
            "subcategory":"Cleaning & Sanitation",
            "type":"Services"
        }
    ],
    "sg:phone":"+44 1969 623639",
    "sg:postcode":"DL8 5AQ",
    "sg:province":"North Yorkshire",
    "sg:tags":[
        "commercial"
    ],
    "wof:name":"Racing Clean",
    "wof:placetype":"venue"
},
  "geometry": {"coordinates":[-1.829477,54.309643],"type":"Point"}
}