{
  "type": "Feature",
  "properties": {
    "iso:country":"GB",
    "sg:address":"31 The Avenue",
    "sg:city":"Clevedon",
    "sg:classifiers":[
        {
            "category":"Professional",
            "subcategory":"Management & Consulting",
            "type":"Services"
        }
    ],
    "sg:phone":"+44 1275 871511",
    "sg:postcode":"BS21 7DZ",
    "sg:province":"Somerset",
    "sg:tags":[
        "marketing",
        "consultant"
    ],
    "wof:name":"Cyfle Associates",
    "wof:placetype":"venue"
},
  "geometry": {"coordinates":[-2.8480200768,51.4489212036],"type":"Point"}
}