{
  "type": "Feature",
  "properties": {
    "addr:full":"44 Bradford St Birmingham West Midlands B5 6HX",
    "addr:housenumber":"44",
    "addr:postcode":"b5 6hx",
    "addr:street":"Bradford St",
    "iso:country":"GB",
    "sg:address":"44 Bradford St",
    "sg:city":"Birmingham",
    "sg:classifiers":[
        {
            "category":"Organizations",
            "subcategory":"Community Association",
            "type":"Services"
        }
    ],
    "sg:phone":"+44 121 687 6099",
    "sg:postcode":"B5 6HX",
    "sg:province":"West Midlands",
    "sg:tags":[
        "society",
        "housing"
    ],
    "wof:name":"Focus Housing Group",
    "wof:placetype":"venue"
},
  "geometry": {"coordinates":[-1.888234973,52.4740791321],"type":"Point"}
}