{
  "type": "Feature",
  "properties": {
    "addr:full":"65 Brickmakers Lane Hemel Hempstead Hertfordshire HP3 8PA",
    "addr:housenumber":"65",
    "addr:postcode":"hp3 8pa",
    "addr:street":"Brickmakers Lane",
    "iso:country":"GB",
    "sg:address":"65 Brickmakers Lane",
    "sg:city":"Hemel Hempstead",
    "sg:classifiers":[
        {
            "category":"Professional",
            "subcategory":"Art Services",
            "type":"Services"
        }
    ],
    "sg:phone":"+44 1442 60962",
    "sg:postcode":"HP3 8PA",
    "sg:province":"Hertfordshire",
    "sg:tags":[
        "photographer"
    ],
    "wof:name":"Bob Hughes Partnership",
    "wof:placetype":"venue"
},
  "geometry": {"coordinates":[-0.4412359893,51.7498092651],"type":"Point"}
}