{
  "type": "Feature",
  "properties": {
    "addr:full":"8 Regent Street Barnsley South Yorkshire S70 2EJ",
    "addr:housenumber":"8",
    "addr:postcode":"s70 2ej",
    "addr:street":"Regent Street;Yorkshire",
    "iso:country":"GB",
    "sg:address":"8 Regent Street",
    "sg:city":"Barnsley",
    "sg:classifiers":[
        {
            "category":"Professional",
            "subcategory":"Lawyer & Legal Services",
            "type":"Services"
        }
    ],
    "sg:phone":"+44 1226 770909",
    "sg:postcode":"S70 2EJ",
    "sg:province":"South Yorkshire",
    "sg:tags":[
        "solicitor"
    ],
    "wof:name":"L A Steel Solicitors",
    "wof:placetype":"venue"
},
  "geometry": {"coordinates":[-1.481669,53.554443],"type":"Point"}
}