{
  "type": "Feature",
  "properties": {
    "addr:full":"18 Queen St Cardiff Cardiff CF1 4BU",
    "addr:housenumber":"18",
    "addr:postcode":"cf1 4bu",
    "addr:street":"Queen St",
    "iso:country":"GB",
    "sg:address":"18 Queen St",
    "sg:city":"Cardiff",
    "sg:classifiers":[
        {
            "category":"Real Estate",
            "subcategory":"Surveying",
            "type":"Services"
        }
    ],
    "sg:phone":"+44 29 2022 1428",
    "sg:postcode":"CF1 4BU",
    "sg:province":"Cardiff",
    "sg:tags":[
        "surveyor",
        "land"
    ],
    "wof:name":"Ekins Surveyors",
    "wof:placetype":"venue"
},
  "geometry": {"coordinates":[-3.2512869835,51.5311050415],"type":"Point"}
}