{
  "type": "Feature",
  "properties": {
    "addr:full":"Maxy House, Sandy La, Cottam Preston Lancashire PR4 0LE",
    "addr:postcode":"pr4 0le",
    "addr:street":"Sandy;Preston",
    "iso:country":"GB",
    "sg:address":"Maxy House, Sandy La, Cottam",
    "sg:city":"Preston",
    "sg:classifiers":[
        {
            "category":"Sports & Exercise",
            "subcategory":"Stables",
            "type":"Entertainment"
        }
    ],
    "sg:postcode":"PR4 0LE",
    "sg:province":"Lancashire",
    "sg:tags":[
        "education",
        "equestrian"
    ],
    "wof:name":"Maxy House Farm Livery",
    "wof:placetype":"venue"
},
  "geometry": {"coordinates":[-2.7602739334,53.7865753174],"type":"Point"}
}