{
  "type": "Feature",
  "properties": {
    "addr:full":"472 Bethnal Green Road London Greater London E2 0EA",
    "addr:housenumber":"472",
    "addr:postcode":"e2 0ea",
    "addr:street":"Bethnal Green Road",
    "iso:country":"GB",
    "sg:address":"472 Bethnal Green Road",
    "sg:city":"London",
    "sg:classifiers":[
        {
            "category":"Shopping",
            "subcategory":"News",
            "type":"Retail Goods"
        }
    ],
    "sg:phone":"+44 20 7739 8658",
    "sg:postcode":"E2 0EA",
    "sg:province":"Greater London",
    "sg:tags":[
        "newsagent"
    ],
    "wof:name":"W Goodmans",
    "wof:placetype":"venue"
},
  "geometry": {"coordinates":[-0.057638,51.527218],"type":"Point"}
}