{
  "type": "Feature",
  "properties": {
    "iso:country":"GB",
    "sg:address":"Unit 8, Keighley Business Centre",
    "sg:city":"Keighley",
    "sg:classifiers":[
        {
            "category":"Building & Trades",
            "subcategory":"Construction",
            "type":"Services"
        }
    ],
    "sg:postcode":"BD21 1AG",
    "sg:province":"West Yorkshire",
    "sg:tags":[
        "builder"
    ],
    "wof:name":"Spandrel Techniks Ltd",
    "wof:placetype":"venue"
},
  "geometry": {"coordinates":[-1.905754,53.87009],"type":"Point"}
}