{
  "type": "Feature",
  "properties": {
    "addr:full":"7 Kingfisher Court, Denton Drive Industrial Estate Northwich Cheshire CW9 7TT",
    "addr:housenumber":"7",
    "addr:postcode":"cw9 7tt",
    "addr:street":"Kingfisher Court Denton Drive Industrial Estate",
    "iso:country":"GB",
    "sg:address":"7 Kingfisher Court, Denton Drive Industrial Estate",
    "sg:city":"Northwich",
    "sg:classifiers":[
        {
            "category":"Shopping",
            "subcategory":"Clothing, Apparel, & Fashions",
            "type":"Retail Goods"
        }
    ],
    "sg:phone":"+44 1606 331137",
    "sg:postcode":"CW9 7TT",
    "sg:province":"Cheshire",
    "sg:tags":[
        "accessory"
    ],
    "wof:name":"Gaby's Fashion Ltd.",
    "wof:placetype":"venue"
},
  "geometry": {"coordinates":[-2.4926140308,53.2666664124],"type":"Point"}
}