{
  "type": "Feature",
  "properties": {
    "addr:full":"217 Albert Road Southsea Hampshire PO4 0JP",
    "addr:housenumber":"217",
    "addr:postcode":"po4 0jp",
    "addr:street":"Albert Road",
    "iso:country":"GB",
    "sg:address":"217 Albert Road",
    "sg:city":"Southsea",
    "sg:classifiers":[
        {
            "category":"Food & Beverages",
            "subcategory":"Bakery",
            "type":"Retail Goods"
        }
    ],
    "sg:postcode":"PO4 0JP",
    "sg:province":"Hampshire",
    "sg:tags":[
        "baker"
    ],
    "wof:name":"Beglinger's Swiss Patisserie",
    "wof:placetype":"venue"
},
  "geometry": {"coordinates":[-1.0730479956,50.7867355347],"type":"Point"}
}