{
  "type": "Feature",
  "properties": {
    "iso:country":"GB",
    "sg:address":"26 Tottenham Street",
    "sg:city":"London",
    "sg:classifiers":[
        {
            "category":"Shopping",
            "subcategory":"Shoes",
            "type":"Retail Goods"
        }
    ],
    "sg:postcode":"W1T 4RQ",
    "sg:province":"Greater London",
    "wof:name":"The Complete Cobbler",
    "wof:placetype":"venue"
},
  "geometry": {"coordinates":[-0.137129,51.519821],"type":"Point"}
}