{
  "type": "Feature",
  "properties": {
    "addr:full":"Red House, 10-12 Market Square Amersham Buckinghamshire HP7 0DQ",
    "addr:housenumber":"10-12",
    "addr:postcode":"hp7 0dq",
    "addr:street":"Market Square Amersham",
    "iso:country":"GB",
    "sg:address":"Red House, 10-12 Market Square",
    "sg:city":"Amersham",
    "sg:classifiers":[
        {
            "category":"Professional",
            "subcategory":"Printing & Photocopies",
            "type":"Services"
        }
    ],
    "sg:phone":"+44 1494 431314",
    "sg:postcode":"HP7 0DQ",
    "sg:province":"Buckinghamshire",
    "sg:tags":[
        "engraving"
    ],
    "wof:name":"Fine Engravings",
    "wof:placetype":"venue"
},
  "geometry": {"coordinates":[-0.616855,51.666534],"type":"Point"}
}