{
  "type": "Feature",
  "properties": {
    "addr:full":"Unit 9 Racecourse Industrial Park, Mansfield Road Derby Derbyshire DE21 4SX",
    "addr:housenumber":"unit 9",
    "addr:postcode":"de21 4sx",
    "addr:street":"Racecourse Industrial Park Mansfield Road",
    "iso:country":"GB",
    "sg:address":"Unit 9 Racecourse Industrial Park, Mansfield Road",
    "sg:city":"Derby",
    "sg:classifiers":[
        {
            "category":"Shopping",
            "subcategory":"Discount & Variety Stores",
            "type":"Retail Goods"
        }
    ],
    "sg:postcode":"DE21 4SX",
    "sg:province":"Derbyshire",
    "sg:tags":[
        "cleaning",
        "supply"
    ],
    "wof:name":"Hygienix",
    "wof:placetype":"venue"
},
  "geometry": {"coordinates":[-1.464124,52.936958],"type":"Point"}
}