{
  "type": "Feature",
  "properties": {
    "addr:full":"Kirby Grange, Kirby Wiske Thirsk North Yorkshire YO7 4EU",
    "addr:postcode":"yo7 4eu",
    "iso:country":"GB",
    "sg:address":"Kirby Grange, Kirby Wiske",
    "sg:city":"Thirsk",
    "sg:classifiers":[
        {
            "category":"Farming",
            "subcategory":"Livestock Farm",
            "type":"Manufacturing & Wholesale Goods"
        }
    ],
    "sg:phone":"+44 1845 587275",
    "sg:postcode":"YO7 4EU",
    "sg:province":"North Yorkshire",
    "sg:tags":[
        "others"
    ],
    "wof:name":"W Reed & Son",
    "wof:placetype":"venue"
},
  "geometry": {"coordinates":[-1.4243329763,54.2578811646],"type":"Point"}
}