{
  "type": "Feature",
  "properties": {
    "iso:country":"GB",
    "sg:address":"Po Box 620, Knaphill",
    "sg:city":"Woking",
    "sg:classifiers":[
        {
            "category":"Professional",
            "subcategory":"Business Services",
            "type":"Services"
        }
    ],
    "sg:phone":"+44 1483 488489",
    "sg:postcode":"GU21 2YZ",
    "sg:province":"Surrey",
    "sg:tags":[
        "food",
        "import",
        "export",
        "agent"
    ],
    "wof:name":"Ame (Direct Sales) Ltd.",
    "wof:placetype":"venue"
},
  "geometry": {"coordinates":[-0.615754,51.316921],"type":"Point"}
}