{
  "type": "Feature",
  "properties": {
    "iso:country":"GB",
    "sg:address":"1 High Street, Roydon",
    "sg:city":"Harlow",
    "sg:classifiers":[
        {
            "category":"Professional",
            "subcategory":"Accounting & Tax Preparation",
            "type":"Services"
        },
        {
            "category":"Professional",
            "subcategory":"Secretarial Services",
            "type":"Services"
        }
    ],
    "sg:phone":"+44 1279 793535",
    "sg:postcode":"CM19 5HJ",
    "sg:province":"Essex",
    "sg:tags":[
        "accountant"
    ],
    "wof:name":"Roydon Business Centre",
    "wof:placetype":"venue"
},
  "geometry": {"coordinates":[0.040941,51.770161],"type":"Point"}
}