{
  "type": "Feature",
  "properties": {
    "addr:full":"5 Maes Y Dderwen Newcastle Emlyn Carmarthenshire SA38 9JW",
    "addr:housenumber":"5",
    "addr:postcode":"sa38 9jw",
    "addr:street":"Maes Y Dderwen",
    "iso:country":"GB",
    "sg:address":"5 Maes Y Dderwen",
    "sg:city":"Newcastle Emlyn",
    "sg:classifiers":[
        {
            "category":"Autos & Motor Vehicles",
            "subcategory":"Automobile Sales",
            "type":"Retail Goods"
        }
    ],
    "sg:phone":"+44 1239 710743",
    "sg:postcode":"SA38 9JW",
    "sg:province":"Carmarthenshire",
    "sg:tags":[
        "car"
    ],
    "wof:name":"E D Walters",
    "wof:placetype":"venue"
},
  "geometry": {"coordinates":[-4.4679841995,52.0359191895],"type":"Point"}
}