{
  "type": "Feature",
  "properties": {
    "addr:full":"33-35 Marsh Rd Luton Bedfordshire LU3 2QF",
    "addr:housenumber":"33-35",
    "addr:postcode":"lu3 2qf",
    "addr:street":"Marsh Rd",
    "iso:country":"GB",
    "sg:address":"33-35 Marsh Rd",
    "sg:city":"Luton",
    "sg:classifiers":[
        {
            "category":"Social Services",
            "subcategory":"Retirement Home",
            "type":"Services"
        }
    ],
    "sg:phone":"+44 1582 492290",
    "sg:postcode":"LU3 2QF",
    "sg:province":"Bedfordshire",
    "sg:tags":[
        "residential",
        "care"
    ],
    "wof:name":"Atwell House",
    "wof:placetype":"venue"
},
  "geometry": {"coordinates":[-0.448643,51.900234],"type":"Point"}
}