{
  "type": "Feature",
  "properties": {
    "addr:full":"499 Warrington Road, Rainhill Prescot Cheshire L35 0LX",
    "addr:housenumber":"499",
    "addr:postcode":"l35 0lx",
    "addr:street":"Warrington Road",
    "iso:country":"GB",
    "sg:address":"499 Warrington Road, Rainhill",
    "sg:city":"Prescot",
    "sg:classifiers":[
        {
            "category":"Professional",
            "subcategory":"Lawyer & Legal Services",
            "type":"Services"
        }
    ],
    "sg:phone":"+44 151 426 7001",
    "sg:postcode":"L35 0LX",
    "sg:province":"Cheshire",
    "sg:tags":[
        "solicitor"
    ],
    "wof:name":"Norton & Co. Solicitors",
    "wof:placetype":"venue"
},
  "geometry": {"coordinates":[-2.7660589218,53.4165611267],"type":"Point"}
}