{
  "type": "Feature",
  "properties": {
    "addr:full":"188 Moor Lane York North Yorkshire YO24 2YZ",
    "addr:housenumber":"188",
    "addr:postcode":"yo24 2yz",
    "addr:street":"Moor Lane",
    "iso:country":"GB",
    "sg:address":"188 Moor Lane",
    "sg:city":"York",
    "sg:classifiers":[
        {
            "category":"Professional",
            "subcategory":"Management & Consulting",
            "type":"Services"
        }
    ],
    "sg:postcode":"YO24 2YZ",
    "sg:province":"North Yorkshire",
    "sg:tags":[
        "consultant",
        "business"
    ],
    "wof:name":"J Quin & Associates",
    "wof:placetype":"venue"
},
  "geometry": {"coordinates":[-1.1400760412,53.933467865],"type":"Point"}
}