{
  "type": "Feature",
  "properties": {
    "iso:country":"GB",
    "sg:address":"6 Byron Rd",
    "sg:city":"New Milton",
    "sg:classifiers":[
        {
            "category":"Building & Trades",
            "subcategory":"Construction",
            "type":"Services"
        }
    ],
    "sg:postcode":"BH25 7NX",
    "sg:province":"Hampshire",
    "sg:tags":[
        "glazier"
    ],
    "wof:name":"Barrett,Colin,",
    "wof:placetype":"venue"
},
  "geometry": {"coordinates":[-1.6740219593,50.7445678711],"type":"Point"}
}