{
  "type": "Feature",
  "properties": {
    "iso:country":"GB",
    "sg:address":"17 School St",
    "sg:city":"Halifax",
    "sg:classifiers":[
        {
            "category":"Professional",
            "type":"Services"
        }
    ],
    "sg:phone":"+44 1422 378416",
    "sg:postcode":"HX4 8JB",
    "sg:province":"West Yorkshire",
    "sg:tags":[
        "caterer"
    ],
    "wof:name":"Tasty Morsels",
    "wof:placetype":"venue"
},
  "geometry": {"coordinates":[-1.8707050085,53.6904830933],"type":"Point"}
}