{
  "type": "Feature",
  "properties": {
    "addr:full":"Halstead Careers Centre, 3-4 East Dene Halstead Essex CO9 1JF",
    "addr:housenumber":"3-4",
    "addr:postcode":"co9 1jf",
    "addr:street":"East Dene",
    "iso:country":"GB",
    "sg:address":"Halstead Careers Centre, 3-4 East Dene",
    "sg:city":"Halstead",
    "sg:classifiers":[
        {
            "category":"Professional",
            "subcategory":"Employment Agencies",
            "type":"Services"
        }
    ],
    "sg:postcode":"CO9 1JF",
    "sg:province":"Essex",
    "sg:tags":[
        "career",
        "guidance"
    ],
    "wof:name":"Essex Careers & Business Partnership Ltd.",
    "wof:placetype":"venue"
},
  "geometry": {"coordinates":[0.6358249784,51.9439964294],"type":"Point"}
}