{
  "type": "Feature",
  "properties": {
    "iso:country":"GB",
    "sg:address":"7 Linden Walk",
    "sg:city":"Prestatyn",
    "sg:classifiers":[
        {
            "category":"Building & Trades",
            "subcategory":"Construction",
            "type":"Services"
        }
    ],
    "sg:phone":"+44 1745 856823",
    "sg:postcode":"LL19 9ED",
    "sg:province":"Denbighshire",
    "sg:tags":[
        "roofing",
        "contracting"
    ],
    "wof:name":"PETER CARL RICH",
    "wof:placetype":"venue"
},
  "geometry": {"coordinates":[-3.39705,53.332836],"type":"Point"}
}