{
  "type": "Feature",
  "properties": {
    "iso:country":"GB",
    "sg:address":"4c Leys Avenue",
    "sg:city":"Letchworth",
    "sg:classifiers":[
        {
            "category":"Professional",
            "subcategory":"Computer Services",
            "type":"Services"
        }
    ],
    "sg:postcode":"SG6 3EU",
    "sg:province":"Hertfordshire",
    "sg:tags":[
        "system",
        "software"
    ],
    "wof:name":"Ewing Communications Ltd",
    "wof:placetype":"venue"
},
  "geometry": {"coordinates":[-0.228091,51.979465],"type":"Point"}
}