{
  "type": "Feature",
  "properties": {
    "addr:full":"46 Poplar Gro Maidstone Kent ME16 0AN",
    "addr:housenumber":"46",
    "addr:postcode":"me16 0an",
    "addr:street":"Poplar Gro",
    "iso:country":"GB",
    "sg:address":"46 Poplar Gro",
    "sg:city":"Maidstone",
    "sg:classifiers":[
        {
            "category":"Building & Trades",
            "subcategory":"Construction",
            "type":"Services"
        }
    ],
    "sg:phone":"+44 1622 762371",
    "sg:postcode":"ME16 0AN",
    "sg:province":"Kent",
    "sg:tags":[
        "builder"
    ],
    "wof:name":"Daveral Construction",
    "wof:placetype":"venue"
},
  "geometry": {"coordinates":[0.4972879887,51.2799453735],"type":"Point"}
}