{
  "type": "Feature",
  "properties": {
    "addr:full":"82 South Bridge Street Airdrie North Lanarkshire ML6 6JA",
    "addr:housenumber":"82",
    "addr:postcode":"ml6 6ja",
    "addr:street":"South Bridge Street",
    "iso:country":"GB",
    "sg:address":"82 South Bridge Street",
    "sg:city":"Airdrie",
    "sg:classifiers":[
        {
            "category":"Shopping",
            "subcategory":"News",
            "type":"Retail Goods"
        }
    ],
    "sg:phone":"+44 1236 763656",
    "sg:postcode":"ML6 6JA",
    "sg:province":"North Lanarkshire",
    "sg:tags":[
        "newsagent"
    ],
    "wof:name":"The Paper Rack",
    "wof:placetype":"venue"
},
  "geometry": {"coordinates":[-3.9814960957,55.8673286438],"type":"Point"}
}