{
  "type": "Feature",
  "properties": {
    "iso:country":"GB",
    "sg:address":"Harlaxton Road",
    "sg:city":"Grantham",
    "sg:classifiers":[
        {
            "category":"Farming",
            "subcategory":"Livestock Farm",
            "type":"Manufacturing & Wholesale Goods"
        },
        {
            "category":"Farming",
            "subcategory":"Farm",
            "type":"Manufacturing & Wholesale Goods"
        }
    ],
    "sg:phone":"+44 1476 563449",
    "sg:postcode":"NG32 1AB",
    "sg:province":"Leicestershire",
    "sg:tags":[
        "mixed",
        "crop",
        "others"
    ],
    "wof:name":"Charles E Richardson",
    "wof:placetype":"venue"
},
  "geometry": {"coordinates":[-0.6892120242,52.8870429993],"type":"Point"}
}