{
  "type": "Feature",
  "properties": {
    "iso:country":"GB",
    "sg:address":"1 West Bell Street",
    "sg:city":"Dundee",
    "sg:classifiers":[
        {
            "category":"Professional",
            "subcategory":"Lawyer & Legal Services",
            "type":"Services"
        }
    ],
    "sg:phone":"+44 1382 223145",
    "sg:postcode":"DD1 1EX",
    "sg:province":"Dundee City",
    "sg:tags":[
        "solicitor"
    ],
    "wof:name":"Flynn & Co",
    "wof:placetype":"venue"
},
  "geometry": {"coordinates":[-2.9752678871,56.4626464844],"type":"Point"}
}