{
  "type": "Feature",
  "properties": {
    "addr:full":"Petherton Road, North Newton Bridgwater Somerset TA7 0BB",
    "addr:postcode":"ta7 0bb",
    "addr:street":"Petherton Road North Newton",
    "iso:country":"GB",
    "sg:address":"Petherton Road, North Newton",
    "sg:city":"Bridgwater",
    "sg:classifiers":[
        {
            "category":"Transit Center",
            "subcategory":"Passenger",
            "type":"Transportation"
        }
    ],
    "sg:phone":"+44 1278 662256",
    "sg:postcode":"TA7 0BB",
    "sg:province":"Somerset",
    "sg:tags":[
        "boarding",
        "kennel",
        "catteries"
    ],
    "wof:name":"Bridge Farm Kennels",
    "wof:placetype":"venue"
},
  "geometry": {"coordinates":[-3.002425909,51.073841095],"type":"Point"}
}