{
  "type": "Feature",
  "properties": {
    "addr:full":"43 Dover Street, Piccadilly London Greater London W1S 4NU",
    "addr:housenumber":"43",
    "addr:postcode":"w1s 4nu",
    "addr:street":"Dover Street",
    "iso:country":"GB",
    "sg:address":"43 Dover Street, Piccadilly",
    "sg:city":"London",
    "sg:classifiers":[
        {
            "category":"Arts & Performance",
            "subcategory":"Art Gallery",
            "type":"Entertainment"
        },
        {
            "category":"Museum",
            "subcategory":"Art Museum",
            "type":"Entertainment"
        }
    ],
    "sg:phone":"+44 20 7493 0706",
    "sg:postcode":"W1S 4NU",
    "sg:province":"Greater London",
    "wof:name":"Portal Gallery Ltd.",
    "wof:placetype":"venue"
},
  "geometry": {"coordinates":[-0.142096,51.508213],"type":"Point"}
}