{
  "type": "Feature",
  "properties": {
    "addr:full":"2 Mayfield St Neots Bedfordshire PE19 5SZ",
    "addr:housenumber":"2",
    "addr:postcode":"pe19 5sz",
    "addr:street":"Mayfield",
    "iso:country":"GB",
    "sg:address":"2 Mayfield",
    "sg:city":"St Neots",
    "sg:classifiers":[
        {
            "category":"Professional",
            "type":"Services"
        }
    ],
    "sg:postcode":"PE19 5SZ",
    "sg:province":"Bedfordshire",
    "sg:tags":[
        "interior",
        "furnishers",
        "designer"
    ],
    "wof:name":"Ian Dilworth",
    "wof:placetype":"venue"
},
  "geometry": {"coordinates":[-0.2667990029,52.2782554626],"type":"Point"}
}