{
  "type": "Feature",
  "properties": {
    "iso:country":"GB",
    "sg:address":"Unit 35, City Business Centre, Lower Road",
    "sg:city":"London",
    "sg:classifiers":[
        {
            "category":"Professional",
            "subcategory":"Accounting & Tax Preparation",
            "type":"Services"
        }
    ],
    "sg:phone":"+44 20 7232 0707",
    "sg:postcode":"SE16 2XB",
    "sg:province":"Greater London",
    "sg:tags":[
        "accountant"
    ],
    "wof:name":"Poole Mordant",
    "wof:placetype":"venue"
},
  "geometry": {"coordinates":[-0.05454,51.4986],"type":"Point"}
}