{
  "type": "Feature",
  "properties": {
    "iso:country":"GB",
    "sg:address":"64 High St, Thrapston",
    "sg:city":"Kettering",
    "sg:classifiers":[
        {
            "category":"Fast Food",
            "type":"Food & Drink"
        }
    ],
    "sg:postcode":"NN14 4JH",
    "sg:province":"Northamptonshire",
    "sg:tags":[
        "away",
        "take"
    ],
    "wof:name":"Albain,Ziad,",
    "wof:placetype":"venue"
},
  "geometry": {"coordinates":[-0.555792,52.366871],"type":"Point"}
}