{
  "type": "Feature",
  "properties": {
    "addr:full":"1 Clarendon Drive, Wymbush Milton Keynes Buckinghamshire MK8 8DA",
    "addr:housenumber":"1",
    "addr:postcode":"mk8 8da",
    "addr:street":"Clarendon Drive",
    "iso:country":"GB",
    "sg:address":"1 Clarendon Drive, Wymbush",
    "sg:city":"Milton Keynes",
    "sg:classifiers":[
        {
            "category":"Communications",
            "type":"Services"
        }
    ],
    "sg:phone":"+44 1908 560597",
    "sg:postcode":"MK8 8DA",
    "sg:province":"Buckinghamshire",
    "sg:tags":[
        "telecommunication"
    ],
    "wof:name":"Ctdi Nethouse Services Ltd.",
    "wof:placetype":"venue"
},
  "geometry": {"coordinates":[-0.7935990095,52.041519165],"type":"Point"}
}