{
  "type": "Feature",
  "properties": {
    "iso:country":"GB",
    "sg:address":"St Annes Mills, Commercial Road Kirkstall",
    "sg:city":"Leeds",
    "sg:classifiers":[
        {
            "category":"Home & Garden",
            "subcategory":"Building Materials",
            "type":"Retail Goods"
        }
    ],
    "sg:phone":"+44 113 278 0482",
    "sg:postcode":"LS5 3AE",
    "sg:province":"West Yorkshire",
    "sg:tags":[
        "fencing"
    ],
    "wof:name":"James B & M",
    "wof:placetype":"venue"
},
  "geometry": {"coordinates":[-1.597249,53.816902],"type":"Point"}
}