{
  "type": "Feature",
  "properties": {
    "iso:country":"GB",
    "sg:address":"David Lloyd Sports Centre, 5 Knole Rd",
    "sg:city":"Bournemouth",
    "sg:classifiers":[
        {
            "category":"Personal",
            "subcategory":"Beauty Salon",
            "type":"Services"
        }
    ],
    "sg:postcode":"BH1 4DQ",
    "sg:province":"Dorset",
    "sg:tags":[
        "unisex",
        "hairdresser"
    ],
    "wof:name":"Gooden,Toby,",
    "wof:placetype":"venue"
},
  "geometry": {"coordinates":[-1.84802,50.723759],"type":"Point"}
}