{
  "type": "Feature",
  "properties": {
    "iso:country":"GB",
    "sg:address":"55 Solly Street",
    "sg:city":"Sheffield",
    "sg:classifiers":[
        {
            "category":"Building & Trades",
            "subcategory":"Construction",
            "type":"Services"
        }
    ],
    "sg:phone":"+44 114 275 5415",
    "sg:postcode":"S1 4BA",
    "sg:province":"South Yorkshire",
    "sg:tags":[
        "furnace"
    ],
    "wof:name":"Chapman Brack (Contractors) Ltd.",
    "wof:placetype":"venue"
},
  "geometry": {"coordinates":[-1.4805489779,53.3830299377],"type":"Point"}
}