{
  "type": "Feature",
  "properties": {
    "addr:full":"46-50 Station Road West Oxted Surrey RH8 9EU",
    "addr:housenumber":"46-50",
    "addr:postcode":"rh8 9eu",
    "addr:street":"Station Road West Oxted",
    "iso:country":"GB",
    "sg:address":"46-50 Station Road West",
    "sg:city":"Oxted",
    "sg:classifiers":[
        {
            "category":"Home & Garden",
            "subcategory":"Home Furnishings",
            "type":"Retail Goods"
        },
        {
            "category":"Home & Garden",
            "subcategory":"Furniture",
            "type":"Retail Goods"
        }
    ],
    "sg:phone":"+44 1883 712210",
    "sg:postcode":"RH8 9EU",
    "sg:province":"Surrey",
    "sg:tags":[
        "furnishers",
        "planner",
        "bedroom"
    ],
    "wof:name":"M B Job Ltd.",
    "wof:placetype":"venue"
},
  "geometry": {"coordinates":[-0.005392,51.257408],"type":"Point"}
}