{
  "type": "Feature",
  "properties": {
    "iso:country":"GB",
    "sg:address":"Fairview House, Hinton Road",
    "sg:city":"Bournemouth",
    "sg:classifiers":[
        {
            "category":"Organizations",
            "subcategory":"Membership Organization",
            "type":"Services"
        }
    ],
    "sg:postcode":"BH1 2EE",
    "sg:province":"Dorset",
    "sg:tags":[
        "club"
    ],
    "wof:name":"The British Slot Car Club Ltd",
    "wof:placetype":"venue"
},
  "geometry": {"coordinates":[-1.873999,50.718952],"type":"Point"}
}