{
  "type": "Feature",
  "properties": {
    "iso:country":"GB",
    "sg:address":"The Street",
    "sg:city":"Reading",
    "sg:classifiers":[
        {
            "category":"Military Area",
            "subcategory":"Air Force Base",
            "type":"Public Place"
        }
    ],
    "sg:phone":"+44 118 964 9006",
    "sg:postcode":"RG7 5ES",
    "sg:province":"Berkshire",
    "sg:tags":[
        "water",
        "treatment"
    ],
    "wof:name":"Satec",
    "wof:placetype":"venue"
},
  "geometry": {"coordinates":[-1.099593,51.444157],"type":"Point"}
}