{
  "type": "Feature",
  "properties": {
    "iso:country":"GB",
    "sg:address":"16 The Mount",
    "sg:city":"Teignmouth",
    "sg:classifiers":[
        {
            "category":"Professional",
            "subcategory":"Accounting & Tax Preparation",
            "type":"Services"
        }
    ],
    "sg:phone":"+44 1626 778009",
    "sg:postcode":"TQ14 8NZ",
    "sg:province":"Devon",
    "sg:tags":[
        "herb",
        "spice"
    ],
    "wof:name":"South West Seasoning Ltd",
    "wof:placetype":"venue"
},
  "geometry": {"coordinates":[-3.500312,50.553177],"type":"Point"}
}