{
  "type": "Feature",
  "properties": {
    "addr:full":"6 Mercers Row Northampton Northamptonshire NN1 2QL",
    "addr:housenumber":"6",
    "addr:postcode":"nn1 2ql",
    "addr:street":"Mercers Row",
    "iso:country":"GB",
    "sg:address":"6 Mercers Row",
    "sg:city":"Northampton",
    "sg:classifiers":[
        {
            "category":"Real Estate",
            "subcategory":"Real Estate Operator",
            "type":"Services"
        }
    ],
    "sg:phone":"+44 1604 602977",
    "sg:postcode":"NN1 2QL",
    "sg:province":"Northamptonshire",
    "sg:tags":[
        "letting",
        "property",
        "leasing",
        "agent"
    ],
    "wof:name":"LIELL PINKHAM LETTINGS LTD",
    "wof:placetype":"venue"
},
  "geometry": {"coordinates":[-0.896616,52.237324],"type":"Point"}
}