{
  "type": "Feature",
  "properties": {
    "addr:full":"Unit 1 Brook Street, Syston Leicester Leicestershire LE7 1GD",
    "addr:housenumber":"unit 1",
    "addr:postcode":"le7 1gd",
    "addr:street":"Brook Street",
    "iso:country":"GB",
    "sg:address":"Unit 1 Brook Street, Syston",
    "sg:city":"Leicester",
    "sg:classifiers":[
        {
            "category":"Shopping",
            "subcategory":"Crafts & Fabrics",
            "type":"Retail Goods"
        }
    ],
    "sg:phone":"+44 116 260 2917",
    "sg:postcode":"LE7 1GD",
    "sg:province":"Leicestershire",
    "sg:tags":[
        "material",
        "art"
    ],
    "wof:name":"Elson Graphics Ltd.",
    "wof:placetype":"venue"
},
  "geometry": {"coordinates":[-1.0777050257,52.6996002197],"type":"Point"}
}