{
  "type": "Feature",
  "properties": {
    "addr:full":"City Gate House, 399 Easternavenue Ilford Essex IG2 6LR",
    "addr:housenumber":"399",
    "addr:postcode":"ig2 6lr",
    "addr:street":"Gate;Easternavenue Ilford",
    "iso:country":"GB",
    "sg:address":"City Gate House, 399 Easternavenue",
    "sg:city":"Ilford",
    "sg:classifiers":[
        {
            "category":"Professional",
            "subcategory":"Business Services",
            "type":"Services"
        }
    ],
    "sg:postcode":"IG2 6LR",
    "sg:province":"Essex",
    "sg:tags":[
        "accomodation"
    ],
    "wof:name":"M & G Taverns Ltd",
    "wof:placetype":"venue"
},
  "geometry": {"coordinates":[0.069214,51.576195],"type":"Point"}
}