{
  "type": "Feature",
  "properties": {
    "addr:full":"Station Yard, Coed Talon Mold Denbighshire CH7 4TG",
    "addr:postcode":"ch7 4tg",
    "iso:country":"GB",
    "sg:address":"Station Yard, Coed Talon",
    "sg:city":"Mold",
    "sg:classifiers":[
        {
            "category":"Retail",
            "subcategory":"Auto Repair",
            "type":"Services"
        }
    ],
    "sg:phone":"+44 1352 771777",
    "sg:postcode":"CH7 4TG",
    "sg:province":"Denbighshire",
    "sg:tags":[
        "bodybuilder",
        "repairer"
    ],
    "wof:name":"Mold Commercial Bodies",
    "wof:placetype":"venue"
},
  "geometry": {"coordinates":[-3.084305,53.151482],"type":"Point"}
}