{
  "type": "Feature",
  "properties": {
    "iso:country":"GB",
    "sg:address":"Unit 2, Gibbons Lane, Pensnett",
    "sg:city":"Brierley Hill",
    "sg:classifiers":[
        {
            "category":"Home & Garden",
            "subcategory":"Hardware",
            "type":"Retail Goods"
        }
    ],
    "sg:postcode":"DY5 4RY",
    "sg:province":"West Midlands",
    "sg:tags":[
        "device",
        "fixing",
        "fastener"
    ],
    "wof:name":"Mallard Productions",
    "wof:placetype":"venue"
},
  "geometry": {"coordinates":[-2.142298,52.501511],"type":"Point"}
}