{
  "type": "Feature",
  "properties": {
    "addr:full":"2 The Cottages Richmond North Yorkshire DL10 5HZ",
    "addr:housenumber":"2",
    "addr:postcode":"dl10 5hz",
    "addr:street":"The Cottages",
    "iso:country":"GB",
    "sg:address":"2 The Cottages",
    "sg:city":"Richmond",
    "sg:classifiers":[
        {
            "category":"Building & Trades",
            "subcategory":"Equipment Rental",
            "type":"Services"
        }
    ],
    "sg:phone":"+44 1748 826247",
    "sg:postcode":"DL10 5HZ",
    "sg:province":"North Yorkshire",
    "sg:tags":[
        "hire",
        "centre"
    ],
    "wof:name":"MacPlant & Tool Hire",
    "wof:placetype":"venue"
},
  "geometry": {"coordinates":[-1.738664031,54.4043388367],"type":"Point"}
}