{
  "type": "Feature",
  "properties": {
    "iso:country":"GB",
    "sg:address":"1 Woodbridge Rd",
    "sg:city":"Ipswich",
    "sg:classifiers":[
        {
            "category":"Organizations",
            "subcategory":"Political Organization",
            "type":"Services"
        }
    ],
    "sg:phone":"+44 1473 231602",
    "sg:postcode":"IP4 2EA",
    "sg:province":"Suffolk",
    "sg:tags":[
        "party"
    ],
    "wof:name":"Ipswich Liberal Democrats",
    "wof:placetype":"venue"
},
  "geometry": {"coordinates":[1.159061,52.058342],"type":"Point"}
}