{
  "type": "Feature",
  "properties": {
    "iso:country":"GB",
    "sg:address":"Liverpool Road, Eccles",
    "sg:city":"Manchester",
    "sg:classifiers":[
        {
            "category":"Place Of Worship",
            "type":"Public Place"
        },
        {
            "category":"Organizations",
            "subcategory":"Community Association",
            "type":"Services"
        },
        {
            "category":"Organizations",
            "subcategory":"Membership Organization",
            "type":"Services"
        }
    ],
    "sg:phone":"+44 161 789 4237",
    "sg:postcode":"M30 7LP",
    "sg:province":"Greater Manchester",
    "sg:tags":[
        "club",
        "social"
    ],
    "wof:name":"St Michaels Social Club",
    "wof:placetype":"venue"
},
  "geometry": {"coordinates":[-2.3637039661,53.4793434143],"type":"Point"}
}