{
  "type": "Feature",
  "properties": {
    "addr:full":"Ship Farm, Horsley Road, Horsley Derby Derbyshire DE21 5BR",
    "addr:postcode":"de21 5br",
    "addr:street":"Horsley Road",
    "iso:country":"GB",
    "sg:address":"Ship Farm, Horsley Road, Horsley",
    "sg:city":"Derby",
    "sg:classifiers":[
        {
            "category":"Personal",
            "subcategory":"Beauty Salon",
            "type":"Services"
        }
    ],
    "sg:postcode":"DE21 5BR",
    "sg:province":"Derbyshire",
    "wof:name":"Elizabeth Cartwright Ltd",
    "wof:placetype":"venue"
},
  "geometry": {"coordinates":[-1.439339,52.996262],"type":"Point"}
}