{
  "type": "Feature",
  "properties": {
    "iso:country":"GB",
    "sg:address":"Unit 9, Lingen Rd, Ludlow Business Park",
    "sg:city":"Ludlow",
    "sg:classifiers":[
        {
            "category":"Shopping",
            "subcategory":"Computers & Home Electronics",
            "type":"Retail Goods"
        }
    ],
    "sg:phone":"+44 1584 874874",
    "sg:postcode":"SY8 1XD",
    "sg:province":"Herefordshire",
    "wof:name":"Advantech Services Ltd",
    "wof:placetype":"venue"
},
  "geometry": {"coordinates":[-2.697648,52.368999],"type":"Point"}
}