{
  "type": "Feature",
  "properties": {
    "iso:country":"GB",
    "sg:address":"Arlington House, 48 St Pauls Road",
    "sg:city":"Bristol",
    "sg:classifiers":[
        {
            "category":"Shopping",
            "subcategory":"Department Store",
            "type":"Retail Goods"
        }
    ],
    "sg:postcode":"BS8 1LP",
    "sg:province":"City of Bristol",
    "wof:name":"G E Worthington Ltd.",
    "wof:placetype":"venue"
},
  "geometry": {"coordinates":[-2.6117169857,51.4587135315],"type":"Point"}
}