{
  "type": "Feature",
  "properties": {
    "iso:country":"GB",
    "sg:address":"18 Cheshire Street",
    "sg:city":"Market Drayton",
    "sg:classifiers":[
        {
            "category":"Social Services",
            "subcategory":"Job Training",
            "type":"Services"
        }
    ],
    "sg:postcode":"TF9 1PD",
    "sg:province":"Shropshire",
    "sg:tags":[
        "translator",
        "interpreter"
    ],
    "wof:name":"Translations for Industry",
    "wof:placetype":"venue"
},
  "geometry": {"coordinates":[-2.4845910072,52.9044456482],"type":"Point"}
}