{
  "type": "Feature",
  "properties": {
    "addr:full":"Syne Hills Care Home Ltd, Syne Avenue Skegness Lincolnshire PE25 3DJ",
    "addr:postcode":"pe25 3dj",
    "addr:street":"Syne;Syne Avenue",
    "iso:country":"GB",
    "sg:address":"Syne Hills Care Home Ltd, Syne Avenue",
    "sg:city":"Skegness",
    "sg:classifiers":[
        {
            "category":"Health Services",
            "subcategory":"Nursing And Care Facility",
            "type":"Services"
        },
        {
            "category":"Social Services",
            "subcategory":"Retirement Home",
            "type":"Services"
        }
    ],
    "sg:phone":"+44 1754 764329",
    "sg:postcode":"PE25 3DJ",
    "sg:province":"Lincolnshire",
    "sg:tags":[
        "residential"
    ],
    "wof:name":"SYNE HILLS CARE HOME LTD",
    "wof:placetype":"venue"
},
  "geometry": {"coordinates":[0.340235,53.133194],"type":"Point"}
}