{
  "type": "Feature",
  "properties": {
    "addr:full":"Jockey Lane, Huntington York North Yorkshire YO32 9NE",
    "addr:postcode":"yo32 9ne",
    "addr:street":"Jockey Lane",
    "iso:country":"GB",
    "sg:address":"Jockey Lane, Huntington",
    "sg:city":"York",
    "sg:classifiers":[
        {
            "category":"Shopping",
            "subcategory":"Pets & Pet Supplies",
            "type":"Retail Goods"
        }
    ],
    "sg:phone":"+44 1904 620527",
    "sg:postcode":"YO32 9NE",
    "sg:province":"North Yorkshire",
    "wof:name":"Pets Pantry",
    "wof:placetype":"venue"
},
  "geometry": {"coordinates":[-1.068378,53.988235],"type":"Point"}
}