{
  "type": "Feature",
  "properties": {
    "iso:country":"GB",
    "sg:address":"Nottingham Road, Keyworth",
    "sg:city":"Nottingham",
    "sg:classifiers":[
        {
            "category":"Bars & Pubs",
            "type":"Food & Drink"
        },
        {
            "category":"Community Center",
            "subcategory":"Social",
            "type":"Public Place"
        }
    ],
    "sg:phone":"+44 115 937 5258",
    "sg:postcode":"NG12 5GW",
    "sg:province":"Nottinghamshire",
    "sg:tags":[
        "pubs",
        "house",
        "inn",
        "activity"
    ],
    "wof:name":"The Fairway",
    "wof:placetype":"venue"
},
  "geometry": {"coordinates":[-1.085457,52.877865],"type":"Point"}
}