{
  "type": "Feature",
  "properties": {
    "addr:full":"7 Castle Meadows Launceston Cornwall PL15 7DZ",
    "addr:housenumber":"7",
    "addr:postcode":"pl15 7dz",
    "addr:street":"Castle Meadows",
    "iso:country":"GB",
    "sg:address":"7 Castle Meadows",
    "sg:city":"Launceston",
    "sg:classifiers":[
        {
            "category":"Home & Garden",
            "subcategory":"Household Appliances",
            "type":"Retail Goods"
        }
    ],
    "sg:phone":"+44 1566 775583",
    "sg:postcode":"PL15 7DZ",
    "sg:province":"Cornwall",
    "sg:tags":[
        "refrigeration",
        "air conditioning"
    ],
    "wof:name":"Kivell Refigeration & Air Conditioning",
    "wof:placetype":"venue"
},
  "geometry": {"coordinates":[-4.3687701225,50.6310806274],"type":"Point"}
}