{
  "type": "Feature",
  "properties": {
    "addr:full":"101 High Street Banstead Surrey SM7 2NL",
    "addr:housenumber":"101",
    "addr:postcode":"sm7 2nl",
    "addr:street":"High Street",
    "iso:country":"GB",
    "sg:address":"101 High Street",
    "sg:city":"Banstead",
    "sg:classifiers":[
        {
            "category":"Real Estate",
            "subcategory":"Real Estate Agent",
            "type":"Services"
        }
    ],
    "sg:phone":"+44 1737 361821",
    "sg:postcode":"SM7 2NL",
    "sg:province":"Surrey",
    "wof:name":"Frost Brothers Ltd.",
    "wof:placetype":"venue"
},
  "geometry": {"coordinates":[-0.199982,51.323151],"type":"Point"}
}