{
  "type": "Feature",
  "properties": {
    "iso:country":"GB",
    "sg:address":"Unit 6b St James Business Centre, Linwood Road, Linwood",
    "sg:city":"Paisley",
    "sg:classifiers":[
        {
            "category":"Wholesale",
            "subcategory":"Scrap",
            "type":"Manufacturing & Wholesale Goods"
        }
    ],
    "sg:phone":"+44 141 887 3389",
    "sg:postcode":"PA3 3AT",
    "sg:province":"Renfrewshire",
    "sg:tags":[
        "waste",
        "metal"
    ],
    "wof:name":"Wrg Environmental Ltd.",
    "wof:placetype":"venue"
},
  "geometry": {"coordinates":[-4.490099,55.846378],"type":"Point"}
}