{
  "type": "Feature",
  "properties": {
    "addr:full":"67 Brive Rd Dunstable Bedfordshire LU5 4EJ",
    "addr:housenumber":"67",
    "addr:postcode":"lu5 4ej",
    "addr:street":"Brive Rd",
    "iso:country":"GB",
    "sg:address":"67 Brive Rd",
    "sg:city":"Dunstable",
    "sg:classifiers":[
        {
            "category":"Building & Trades",
            "subcategory":"Construction",
            "type":"Services"
        }
    ],
    "sg:phone":"+44 1582 660272",
    "sg:postcode":"LU5 4EJ",
    "sg:province":"Bedfordshire",
    "sg:tags":[
        "contractor",
        "paving",
        "driveway"
    ],
    "wof:name":"Elegant Driveways",
    "wof:placetype":"venue"
},
  "geometry": {"coordinates":[-0.5012019873,51.877407074],"type":"Point"}
}