{
  "type": "Feature",
  "properties": {
    "iso:country":"GB",
    "sg:address":"Broadview, Luton Road",
    "sg:city":"St Albans",
    "sg:classifiers":[
        {
            "category":"Home & Garden",
            "subcategory":"Hardware",
            "type":"Retail Goods"
        }
    ],
    "sg:postcode":"AL3 8PZ",
    "sg:province":"Hertfordshire",
    "sg:tags":[
        "lawnmowers",
        "machinery"
    ],
    "wof:name":"Markyate Mowers",
    "wof:placetype":"venue"
},
  "geometry": {"coordinates":[-0.457370013,51.8408813477],"type":"Point"}
}