{
  "type": "Feature",
  "properties": {
    "iso:country":"GB",
    "sg:address":"Wenden Ct, Off Station Rd, Wenden Ambo",
    "sg:city":"Saffron Walden",
    "sg:classifiers":[
        {
            "category":"Home & Garden",
            "subcategory":"Kitchen Supply",
            "type":"Retail Goods"
        }
    ],
    "sg:postcode":"CB11 4LB",
    "sg:province":"Essex",
    "sg:tags":[
        "equipment",
        "catering"
    ],
    "wof:name":"Rodgers,Terry F,",
    "wof:placetype":"venue"
},
  "geometry": {"coordinates":[0.2276120037,52.0169029236],"type":"Point"}
}