{
  "type": "Feature",
  "properties": {
    "iso:country":"GB",
    "sg:address":"1 Butts Pond Industrial Estate",
    "sg:city":"Sturminster Newton",
    "sg:classifiers":[
        {
            "category":"Professional",
            "subcategory":"Printing & Photocopies",
            "type":"Services"
        }
    ],
    "sg:phone":"+44 1258 473521",
    "sg:postcode":"DT10 1AZ",
    "sg:province":"Dorset",
    "sg:tags":[
        "printer"
    ],
    "wof:name":"Dorset Graphic Arts",
    "wof:placetype":"venue"
},
  "geometry": {"coordinates":[-2.3051490784,50.9266242981],"type":"Point"}
}