{
  "type": "Feature",
  "properties": {
    "iso:country":"GB",
    "sg:address":"Staplake, Staplake Lane",
    "sg:city":"Exeter",
    "sg:classifiers":[
        {
            "category":"Wholesale",
            "subcategory":"Scrap",
            "type":"Manufacturing & Wholesale Goods"
        }
    ],
    "sg:postcode":"EX6 8QT",
    "sg:province":"Devon",
    "sg:tags":[
        "waste",
        "metal"
    ],
    "wof:name":"Peter R Williams",
    "wof:placetype":"venue"
},
  "geometry": {"coordinates":[-3.458954,50.623692],"type":"Point"}
}