{
  "type": "Feature",
  "properties": {
    "addr:full":"86 Fitzwilliam Street Huddersfield West Yorkshire HD1 5BB",
    "addr:housenumber":"86",
    "addr:postcode":"hd1 5bb",
    "addr:street":"Fitzwilliam Street",
    "iso:country":"GB",
    "sg:address":"86 Fitzwilliam Street",
    "sg:city":"Huddersfield",
    "sg:classifiers":[
        {
            "category":"Organizations",
            "subcategory":"Membership Organization",
            "type":"Services"
        }
    ],
    "sg:postcode":"HD1 5BB",
    "sg:province":"West Yorkshire",
    "sg:tags":[
        "club"
    ],
    "wof:name":"Polish Ex-Servicemens Club",
    "wof:placetype":"venue"
},
  "geometry": {"coordinates":[-1.786025,53.650059],"type":"Point"}
}