{
  "type": "Feature",
  "properties": {
    "iso:country":"GB",
    "sg:address":"18 Farrers Walk",
    "sg:city":"Ashford",
    "sg:classifiers":[
        {
            "category":"Professional",
            "subcategory":"Management & Consulting",
            "type":"Services"
        }
    ],
    "sg:phone":"+44 1233 503567",
    "sg:postcode":"TN23 3NL",
    "sg:province":"Kent",
    "sg:tags":[
        "consultant",
        "business"
    ],
    "wof:name":"Quality Management Systems",
    "wof:placetype":"venue"
},
  "geometry": {"coordinates":[0.870378,51.122543],"type":"Point"}
}