{
  "type": "Feature",
  "properties": {
    "addr:full":"2 School Wynd Kilbirnie North Ayrshire KA25 7AY",
    "addr:housenumber":"2",
    "addr:postcode":"ka25 7ay",
    "addr:street":"School Wynd",
    "iso:country":"GB",
    "sg:address":"2 School Wynd",
    "sg:city":"Kilbirnie",
    "sg:classifiers":[
        {
            "category":"Real Estate",
            "subcategory":"Architect",
            "type":"Services"
        }
    ],
    "sg:postcode":"KA25 7AY",
    "sg:province":"North Ayrshire",
    "wof:name":"Houston Harper",
    "wof:placetype":"venue"
},
  "geometry": {"coordinates":[-4.6879220009,55.7559585571],"type":"Point"}
}