{
  "type": "Feature",
  "properties": {
    "addr:full":"4 Moss End Industrial Estate Stornoway Eilean Siar HS1 2DG",
    "addr:housenumber":"4;estate",
    "addr:postcode":"hs1 2dg",
    "addr:street":"Moss End Industrial",
    "iso:country":"GB",
    "sg:address":"4 Moss End Industrial Estate",
    "sg:city":"Stornoway",
    "sg:classifiers":[
        {
            "category":"Home & Garden",
            "subcategory":"Carpets & Floor Coverings",
            "type":"Retail Goods"
        }
    ],
    "sg:phone":"+44 1851 702791",
    "sg:postcode":"HS1 2DG",
    "sg:province":"Eilean Siar",
    "sg:tags":[
        "carpets",
        "rug",
        "matting"
    ],
    "wof:name":"Lewis Carpet Contracts",
    "wof:placetype":"venue"
},
  "geometry": {"coordinates":[-6.375239,58.206383],"type":"Point"}
}