{
  "type": "Feature",
  "properties": {
    "iso:country":"GB",
    "sg:address":"24 Lambrook Rd, Fishponds",
    "sg:city":"Bristol",
    "sg:classifiers":[
        {
            "category":"Utilities",
            "subcategory":"Refuse",
            "type":"Services"
        }
    ],
    "sg:postcode":"BS16 4XZ",
    "sg:province":"City of Bristol",
    "sg:tags":[
        "skip",
        "hire"
    ],
    "wof:name":"Bennett,G H,",
    "wof:placetype":"venue"
},
  "geometry": {"coordinates":[-2.5914289951,51.453666687],"type":"Point"}
}