{
  "type": "Feature",
  "properties": {
    "addr:full":"5 Windermere Avenue, North Hykeham Lincoln Lincolnshire LN6 8EN",
    "addr:housenumber":"5",
    "addr:postcode":"ln6 8en",
    "addr:street":"Windermere Avenue",
    "iso:country":"GB",
    "sg:address":"5 Windermere Avenue, North Hykeham",
    "sg:city":"Lincoln",
    "sg:classifiers":[
        {
            "category":"Shopping",
            "subcategory":"News",
            "type":"Retail Goods"
        }
    ],
    "sg:postcode":"LN6 8EN",
    "sg:province":"Lincolnshire",
    "sg:tags":[
        "newsagent"
    ],
    "wof:name":"John Nigel & Jeanette Sharpe",
    "wof:placetype":"venue"
},
  "geometry": {"coordinates":[-0.5768190026,53.1888198853],"type":"Point"}
}