{
  "type": "Feature",
  "properties": {
    "iso:country":"GB",
    "sg:address":"434 Whitmore Way",
    "sg:city":"Basildon",
    "sg:classifiers":[
        {
            "category":"Food & Beverages",
            "subcategory":"Bakery",
            "type":"Retail Goods"
        }
    ],
    "sg:phone":"+44 1268 527287",
    "sg:postcode":"SS14 2HB",
    "sg:province":"Essex",
    "sg:tags":[
        "baker"
    ],
    "wof:name":"Ovenfresh",
    "wof:placetype":"venue"
},
  "geometry": {"coordinates":[0.473981,51.577698],"type":"Point"}
}