{
  "type": "Feature",
  "properties": {
    "addr:full":"25 Cross Street, Wallheath, Kingswinford Brierley Hill Staffordshire DY6 0NB",
    "addr:housenumber":"25",
    "addr:postcode":"dy6 0nb",
    "addr:street":"Cross Street;Kingswinford;Hill",
    "iso:country":"GB",
    "sg:address":"25 Cross Street, Wallheath, Kingswinford",
    "sg:city":"Brierley Hill",
    "sg:classifiers":[
        {
            "category":"Building & Trades",
            "subcategory":"Construction",
            "type":"Services"
        }
    ],
    "sg:phone":"+44 1384 401912",
    "sg:postcode":"DY6 0NB",
    "sg:province":"Staffordshire",
    "sg:tags":[
        "decorator",
        "painter"
    ],
    "wof:name":"Harry Moseley Painter & Decorator",
    "wof:placetype":"venue"
},
  "geometry": {"coordinates":[-2.182289,52.505444],"type":"Point"}
}