{
  "type": "Feature",
  "properties": {
    "addr:full":"49 Queensway Stourbridge West Midlands DY9 9HJ",
    "addr:housenumber":"49",
    "addr:postcode":"dy9 9hj",
    "addr:street":"Queensway",
    "iso:country":"GB",
    "sg:address":"49 Queensway",
    "sg:city":"Stourbridge",
    "sg:classifiers":[
        {
            "category":"Government",
            "subcategory":"Post Office",
            "type":"Public Place"
        }
    ],
    "sg:phone":"+44 1562 885665",
    "sg:postcode":"DY9 9HJ",
    "sg:province":"West Midlands",
    "wof:name":"Queensway P.O",
    "wof:placetype":"venue"
},
  "geometry": {"coordinates":[-2.116993,52.442188],"type":"Point"}
}