{
  "type": "Feature",
  "properties": {
    "iso:country":"GB",
    "sg:address":"291 Hanley Road, Sneyd Green",
    "sg:city":"Stoke On Trent",
    "sg:classifiers":[
        {
            "category":"Shopping",
            "subcategory":"Florist",
            "type":"Retail Goods"
        }
    ],
    "sg:phone":"+44 1782 205200",
    "sg:postcode":"ST1 6DF",
    "sg:province":"Staffordshire",
    "wof:name":"The Flower Centre",
    "wof:placetype":"venue"
},
  "geometry": {"coordinates":[-2.172105,53.043343],"type":"Point"}
}