{
  "type": "Feature",
  "properties": {
    "addr:full":"Dental Surgery, 3 Dalreoch Pl Perth Perth and Kinross PH1 2HU",
    "addr:housenumber":"3",
    "addr:postcode":"ph1 2hu",
    "addr:street":"Dalreoch Pl",
    "iso:country":"GB",
    "sg:address":"Dental Surgery, 3 Dalreoch Pl",
    "sg:city":"Perth",
    "sg:classifiers":[
        {
            "category":"Health Services",
            "subcategory":"Dentist",
            "type":"Services"
        }
    ],
    "sg:phone":"+44 1738 626904",
    "sg:postcode":"PH1 2HU",
    "sg:province":"Perth and Kinross",
    "wof:name":"N T Renfrew",
    "wof:placetype":"venue"
},
  "geometry": {"coordinates":[-3.4716699123,56.4016189575],"type":"Point"}
}