{
  "type": "Feature",
  "properties": {
    "iso:country":"GB",
    "sg:address":"174 Station Rd",
    "sg:city":"Billingham",
    "sg:classifiers":[
        {
            "category":"Fast Food",
            "type":"Food & Drink"
        }
    ],
    "sg:postcode":"TS23 2RT",
    "sg:province":"Durham",
    "sg:tags":[
        "away",
        "take"
    ],
    "wof:name":"Unos Pizzeria",
    "wof:placetype":"venue"
},
  "geometry": {"coordinates":[-1.297869,54.60326],"type":"Point"}
}