{
  "type": "Feature",
  "properties": {
    "iso:country":"GB",
    "sg:address":"275 Kensal Rd",
    "sg:city":"Ladbroke Grove",
    "sg:classifiers":[
        {
            "category":"Communications",
            "subcategory":"Film & Video Production",
            "type":"Services"
        }
    ],
    "sg:phone":"+44 20 8969 2629",
    "sg:postcode":"W10 5DB",
    "sg:province":"Greater London",
    "sg:tags":[
        "tv",
        "studio"
    ],
    "wof:name":"Rat Tango Productions Ltd",
    "wof:placetype":"venue"
},
  "geometry": {"coordinates":[-0.212795,51.526127],"type":"Point"}
}