{
  "type": "Feature",
  "properties": {
    "addr:full":"47 Belvedere Gardens, Chineham Basingstoke Hampshire RG24 8GB",
    "addr:housenumber":"47",
    "addr:postcode":"rg24 8gb",
    "addr:street":"Belvedere Gardens",
    "iso:country":"GB",
    "sg:address":"47 Belvedere Gardens, Chineham",
    "sg:city":"Basingstoke",
    "sg:classifiers":[
        {
            "category":"Education",
            "subcategory":"Special Training",
            "type":"Public Place"
        }
    ],
    "sg:phone":"+44 1256 358302",
    "sg:postcode":"RG24 8GB",
    "sg:province":"Hampshire",
    "sg:tags":[
        "product",
        "centre"
    ],
    "wof:name":"A S Training",
    "wof:placetype":"venue"
},
  "geometry": {"coordinates":[-1.0477310419,51.2980575562],"type":"Point"}
}