{
  "type": "Feature",
  "properties": {
    "iso:country":"GB",
    "sg:address":"46 West Road",
    "sg:city":"Congleton",
    "sg:classifiers":[
        {
            "category":"Retail",
            "subcategory":"Auto Rental",
            "type":"Services"
        }
    ],
    "sg:phone":"+44 1260 280433",
    "sg:postcode":"CW12 4ES",
    "sg:province":"Cheshire",
    "sg:tags":[
        "car"
    ],
    "wof:name":"Cheshire Vehicle Rental",
    "wof:placetype":"venue"
},
  "geometry": {"coordinates":[-2.223344,53.164536],"type":"Point"}
}