{
  "type": "Feature",
  "properties": {
    "addr:full":"19 Coedcae Road Llanelli Carmarthenshire SA15 1HJ",
    "addr:housenumber":"19",
    "addr:postcode":"sa15 1hj",
    "addr:street":"Coedcae Road",
    "iso:country":"GB",
    "sg:address":"19 Coedcae Road",
    "sg:city":"Llanelli",
    "sg:classifiers":[
        {
            "category":"Building & Trades",
            "subcategory":"Construction",
            "type":"Services"
        }
    ],
    "sg:postcode":"SA15 1HJ",
    "sg:province":"Carmarthenshire",
    "sg:tags":[
        "decorator",
        "painter"
    ],
    "wof:name":"Parkin Decorators",
    "wof:placetype":"venue"
},
  "geometry": {"coordinates":[-4.1382951736,51.6828613281],"type":"Point"}
}