{
  "type": "Feature",
  "properties": {
    "addr:full":"73 Grosvenor Park Rd Walthamstow Greater London E17 9PD",
    "addr:housenumber":"73",
    "addr:postcode":"e17 9pd",
    "addr:street":"Grosvenor Park Rd",
    "iso:country":"GB",
    "sg:address":"73 Grosvenor Park Rd",
    "sg:city":"Walthamstow",
    "sg:classifiers":[
        {
            "category":"Shopping",
            "subcategory":"Clothing, Apparel, & Fashions",
            "type":"Retail Goods"
        }
    ],
    "sg:phone":"+44 20 8520 6520",
    "sg:postcode":"E17 9PD",
    "sg:province":"Greater London",
    "sg:tags":[
        "tie",
        "neckwear"
    ],
    "wof:name":"D Bellefontaine",
    "wof:placetype":"venue"
},
  "geometry": {"coordinates":[-0.0168709997,51.5794143677],"type":"Point"}
}