{
  "type": "Feature",
  "properties": {
    "iso:country":"GB",
    "sg:address":"66 King Street",
    "sg:city":"Manchester",
    "sg:classifiers":[
        {
            "category":"Shopping",
            "subcategory":"Clothing, Apparel, & Fashions",
            "type":"Retail Goods"
        }
    ],
    "sg:phone":"+44 161 834 7023",
    "sg:postcode":"M2 4ND",
    "sg:province":"Greater Manchester",
    "sg:tags":[
        "shop"
    ],
    "wof:name":"Kookai Ladies Fashion",
    "wof:placetype":"venue"
},
  "geometry": {"coordinates":[-2.24541,53.480968],"type":"Point"}
}