{
  "type": "Feature",
  "properties": {
    "addr:full":"Holly Lodge, Hatfield Lane, Norton Worcester Worcestershire WR5 2PY",
    "addr:postcode":"wr5 2py",
    "addr:street":"Hatfield Lane",
    "iso:country":"GB",
    "sg:address":"Holly Lodge, Hatfield Lane, Norton",
    "sg:city":"Worcester",
    "sg:classifiers":[
        {
            "category":"Organizations",
            "subcategory":"Membership Organization",
            "type":"Services"
        }
    ],
    "sg:postcode":"WR5 2PY",
    "sg:province":"Worcestershire",
    "sg:tags":[
        "club"
    ],
    "wof:name":"Florida Travel Club",
    "wof:placetype":"venue"
},
  "geometry": {"coordinates":[-2.179164,52.158844],"type":"Point"}
}