{
  "type": "Feature",
  "properties": {
    "addr:full":"156 Wellington Road Bilston West Midlands WV14 6AZ",
    "addr:housenumber":"156",
    "addr:postcode":"wv14 6az",
    "addr:street":"Wellington Road",
    "iso:country":"GB",
    "sg:address":"156 Wellington Road",
    "sg:city":"Bilston",
    "sg:classifiers":[
        {
            "category":"Travel",
            "subcategory":"Hotels & Motels",
            "type":"Entertainment"
        }
    ],
    "sg:postcode":"WV14 6AZ",
    "sg:province":"West Midlands",
    "sg:tags":[
        "house",
        "guest"
    ],
    "wof:name":"Wellington Lodge",
    "wof:placetype":"venue"
},
  "geometry": {"coordinates":[-2.085465,52.569191],"type":"Point"}
}