{
  "type": "Feature",
  "properties": {
    "iso:country":"GB",
    "sg:address":"Cranesgate Farm, Whaplode",
    "sg:city":"Spalding",
    "sg:classifiers":[
        {
            "category":"Farming",
            "subcategory":"Livestock Farm",
            "type":"Manufacturing & Wholesale Goods"
        }
    ],
    "sg:phone":"+44 1406 422710",
    "sg:postcode":"PE12 6TY",
    "sg:province":"Cambridgeshire",
    "sg:tags":[
        "others"
    ],
    "wof:name":"P Pocklington & Son",
    "wof:placetype":"venue"
},
  "geometry": {"coordinates":[-0.0369829983,52.8001785278],"type":"Point"}
}