{
  "type": "Feature",
  "properties": {
    "addr:full":"12 Iona Road, Syston Leicester Leicestershire LE7 1QP",
    "addr:housenumber":"12",
    "addr:postcode":"le7 1qp",
    "addr:street":"Iona Road",
    "iso:country":"GB",
    "sg:address":"12 Iona Road, Syston",
    "sg:city":"Leicester",
    "sg:classifiers":[
        {
            "category":"Building & Trades",
            "subcategory":"Construction",
            "type":"Services"
        }
    ],
    "sg:postcode":"LE7 1QP",
    "sg:province":"Leicestershire",
    "sg:tags":[
        "decorator",
        "painter"
    ],
    "wof:name":"Bryan Summerfield",
    "wof:placetype":"venue"
},
  "geometry": {"coordinates":[-1.0881910324,52.6976737976],"type":"Point"}
}