{
  "type": "Feature",
  "properties": {
    "addr:full":"135 Wright Street, Small Health Birmingham West Midlands B10 9RP",
    "addr:housenumber":"135",
    "addr:postcode":"b10 9rp",
    "addr:street":"Wright Street",
    "iso:country":"GB",
    "sg:address":"135 Wright Street, Small Health",
    "sg:city":"Birmingham",
    "sg:classifiers":[
        {
            "category":"Food & Beverages",
            "subcategory":"Meat & Fish",
            "type":"Retail Goods"
        }
    ],
    "sg:phone":"+44 121 772 0719",
    "sg:postcode":"B10 9RP",
    "sg:province":"West Midlands",
    "sg:tags":[
        "butcher"
    ],
    "wof:name":"Rapyal Halal Meat & Poultry Wholesalers (The)",
    "wof:placetype":"venue"
},
  "geometry": {"coordinates":[-1.8605200052,52.4713668823],"type":"Point"}
}