{
  "type": "Feature",
  "properties": {
    "iso:country":"GB",
    "sg:address":"6 Bute Street",
    "sg:city":"Luton",
    "sg:classifiers":[
        {
            "category":"Professional",
            "subcategory":"Employment Agencies",
            "type":"Services"
        }
    ],
    "sg:phone":"+44 1582 401636",
    "sg:postcode":"LU1 2BU",
    "sg:province":"Bedfordshire",
    "sg:tags":[
        "consultant"
    ],
    "wof:name":"Blue Arrow Ltd.",
    "wof:placetype":"venue"
},
  "geometry": {"coordinates":[-0.415459,51.880329],"type":"Point"}
}