{
  "type": "Feature",
  "properties": {
    "addr:full":"Investment House 6 Union Row Aberdeen Aberdeen City AB10 1DQ",
    "addr:housenumber":"6",
    "addr:postcode":"ab10 1dq",
    "addr:street":"Union Row",
    "iso:country":"GB",
    "sg:address":"Investment House 6 Union Row",
    "sg:city":"Aberdeen",
    "sg:classifiers":[
        {
            "category":"Organizations",
            "subcategory":"Membership Organization",
            "type":"Services"
        }
    ],
    "sg:postcode":"AB10 1DQ",
    "sg:province":"Aberdeen City",
    "sg:tags":[
        "club"
    ],
    "wof:name":"Yogi Management Ltd",
    "wof:placetype":"venue"
},
  "geometry": {"coordinates":[-2.107838,57.144756],"type":"Point"}
}