{
  "type": "Feature",
  "properties": {
    "iso:country":"GB",
    "sg:address":"The Old Post Office, 52 Bridge Of Weir Rd, Brookfield",
    "sg:city":"Johnstone",
    "sg:classifiers":[
        {
            "category":"Building & Trades",
            "subcategory":"Construction",
            "type":"Services"
        }
    ],
    "sg:postcode":"PA5 8UL",
    "sg:province":"Renfrewshire",
    "sg:tags":[
        "builder"
    ],
    "wof:name":"Brookfield Contracting Services",
    "wof:placetype":"venue"
},
  "geometry": {"coordinates":[-4.5083441734,55.8361091614],"type":"Point"}
}