{
  "type": "Feature",
  "properties": {
    "addr:full":"23 Wakehurst Drive, East Hunsbury Northampton Northamptonshire NN4 0TN",
    "addr:housenumber":"23",
    "addr:postcode":"nn4 0tn",
    "addr:street":"Wakehurst Drive East Hunsbury",
    "iso:country":"GB",
    "sg:address":"23 Wakehurst Drive, East Hunsbury",
    "sg:city":"Northampton",
    "sg:classifiers":[
        {
            "category":"Communications",
            "type":"Services"
        }
    ],
    "sg:phone":"+44 1604 766236",
    "sg:postcode":"NN4 0TN",
    "sg:province":"Northamptonshire",
    "sg:tags":[
        "broadcasting"
    ],
    "wof:name":"Immediate Video Services",
    "wof:placetype":"venue"
},
  "geometry": {"coordinates":[-0.8989390135,52.2071113586],"type":"Point"}
}