{
  "type": "Feature",
  "properties": {
    "iso:country":"GB",
    "sg:address":"P O Box 7",
    "sg:city":"Harwich",
    "sg:classifiers":[
        {
            "category":"Professional",
            "subcategory":"Lawyer & Legal Services",
            "type":"Services"
        }
    ],
    "sg:postcode":"CO12 5DJ",
    "sg:province":"Essex",
    "wof:name":"Kenneth F Burtsal",
    "wof:placetype":"venue"
},
  "geometry": {"coordinates":[1.21402,51.927502],"type":"Point"}
}