{
  "type": "Feature",
  "properties": {
    "addr:full":"Unit 6 Sandy Bridge Ware House, Sandy Rd Llanelli Carmarthenshire SA15 3EU",
    "addr:housenumber":"unit 6;ware house",
    "addr:postcode":"sa15 3eu",
    "addr:street":"Sandy Bridge;Sandy Rd",
    "iso:country":"GB",
    "sg:address":"Unit 6 Sandy Bridge Ware House, Sandy Rd",
    "sg:city":"Llanelli",
    "sg:classifiers":[
        {
            "category":"Bars & Pubs",
            "subcategory":"Wine Bar",
            "type":"Food & Drink"
        }
    ],
    "sg:phone":"+44 1554 751663",
    "sg:postcode":"SA15 3EU",
    "sg:province":"Carmarthenshire",
    "sg:tags":[
        "fitter"
    ],
    "wof:name":"John Long Contracts Ltd",
    "wof:placetype":"venue"
},
  "geometry": {"coordinates":[-4.1845312119,51.6851348877],"type":"Point"}
}