{
  "type": "Feature",
  "properties": {
    "addr:full":"83 Walton Vale Liverpool Merseyside L9 4RQ",
    "addr:housenumber":"83",
    "addr:postcode":"l9 4rq",
    "addr:street":"Walton Vale",
    "iso:country":"GB",
    "sg:address":"83 Walton Vale",
    "sg:city":"Liverpool",
    "sg:classifiers":[
        {
            "category":"Banks & Credit Unions",
            "subcategory":"Bank",
            "type":"Services"
        },
        {
            "category":"Banks & Credit Unions",
            "subcategory":"Financial Services",
            "type":"Services"
        }
    ],
    "sg:phone":"+44 151 523 2808",
    "sg:postcode":"L9 4RQ",
    "sg:province":"Merseyside",
    "sg:tags":[
        "building",
        "society",
        "institution"
    ],
    "wof:name":"Bradford & Bingley Plc",
    "wof:placetype":"venue"
},
  "geometry": {"coordinates":[-2.959337,53.463589],"type":"Point"}
}