{
  "type": "Feature",
  "properties": {
    "iso:country":"GB",
    "sg:address":"Unit 13-16 The Coliseum, Church Street",
    "sg:city":"Manchester",
    "sg:classifiers":[
        {
            "category":"Shopping",
            "subcategory":"Clothing, Apparel, & Fashions",
            "type":"Retail Goods"
        }
    ],
    "sg:phone":"+44 161 907 3285",
    "sg:postcode":"M4 1PN",
    "sg:province":"Greater Manchester",
    "sg:tags":[
        "shop"
    ],
    "wof:name":"Rock Stop",
    "wof:placetype":"venue"
},
  "geometry": {"coordinates":[-2.23787,53.482979],"type":"Point"}
}