{
  "type": "Feature",
  "properties": {
    "addr:full":"81 Forest Walk, Halton Lea Runcorn Cheshire WA7 2GX",
    "addr:housenumber":"81",
    "addr:postcode":"wa7 2gx",
    "addr:street":"Forest Walk",
    "iso:country":"GB",
    "sg:address":"81 Forest Walk, Halton Lea",
    "sg:city":"Runcorn",
    "sg:classifiers":[
        {
            "category":"Shopping",
            "subcategory":"Clothing, Apparel, & Fashions",
            "type":"Retail Goods"
        }
    ],
    "sg:phone":"+44 1928 711672",
    "sg:postcode":"WA7 2GX",
    "sg:province":"Cheshire",
    "sg:tags":[
        "shop"
    ],
    "wof:name":"New Look Retailers Ltd.",
    "wof:placetype":"venue"
},
  "geometry": {"coordinates":[-2.695217,53.331638],"type":"Point"}
}