{
  "type": "Feature",
  "properties": {
    "addr:full":"Carr House Drive Durham Durham DH1 5LT",
    "addr:postcode":"dh1 5lt",
    "addr:street":"House Drive",
    "iso:country":"GB",
    "sg:address":"Carr House Drive",
    "sg:city":"Durham",
    "sg:classifiers":[
        {
            "category":"Food & Beverages",
            "subcategory":"Supermarket",
            "type":"Retail Goods"
        }
    ],
    "sg:phone":"+44 191 384 1088",
    "sg:postcode":"DH1 5LT",
    "sg:province":"Durham",
    "wof:name":"North Eastern Co-Operative",
    "wof:placetype":"venue"
},
  "geometry": {"coordinates":[-1.5637389421,54.8005943298],"type":"Point"}
}