{
  "type": "Feature",
  "properties": {
    "addr:full":"Bilberry Street Rochdale Lancashire OL16 5NN",
    "addr:postcode":"ol16 5nn",
    "addr:street":"Bilberry Street",
    "iso:country":"GB",
    "sg:address":"Bilberry Street",
    "sg:city":"Rochdale",
    "sg:classifiers":[
        {
            "category":"Autos & Motor Vehicles",
            "subcategory":"Auto Supplies",
            "type":"Retail Goods"
        }
    ],
    "sg:phone":"+44 1706 359666",
    "sg:postcode":"OL16 5NN",
    "sg:province":"Lancashire",
    "sg:tags":[
        "component"
    ],
    "wof:name":"MAGNUM CAR PANELS LTD",
    "wof:placetype":"venue"
},
  "geometry": {"coordinates":[-2.1426639557,53.6121253967],"type":"Point"}
}