{
  "type": "Feature",
  "properties": {
    "iso:country":"GB",
    "sg:address":"165b Junction Rd",
    "sg:city":"Archway",
    "sg:classifiers":[
        {
            "category":"Autos & Motor Vehicles",
            "subcategory":"Motorcycle Sales",
            "type":"Retail Goods"
        }
    ],
    "sg:phone":"+44 20 7272 0900",
    "sg:postcode":"N19 5PZ",
    "sg:province":"Greater London",
    "sg:tags":[
        "chauffeur",
        "driven",
        "car"
    ],
    "wof:name":"Peach Airport Transfers",
    "wof:placetype":"venue"
},
  "geometry": {"coordinates":[-0.1370580047,51.5608024597],"type":"Point"}
}