{
  "type": "Feature",
  "properties": {
    "iso:country":"GB",
    "sg:address":"White Moss Road East",
    "sg:city":"Manchester",
    "sg:classifiers":[
        {
            "category":"Education",
            "subcategory":"School",
            "type":"Public Place"
        }
    ],
    "sg:phone":"+44 161 795 8493",
    "sg:postcode":"M9 6EF",
    "sg:province":"Greater Manchester",
    "sg:tags":[
        "local",
        "authority"
    ],
    "wof:name":"Crosslee Primary School",
    "wof:placetype":"venue"
},
  "geometry": {"coordinates":[-2.201217,53.529606],"type":"Point"}
}