{
  "type": "Feature",
  "properties": {
    "iso:country":"GB",
    "sg:address":"2 Easthill Lane",
    "sg:city":"Castle Cary",
    "sg:classifiers":[
        {
            "category":"Farming",
            "subcategory":"Livestock Farm",
            "type":"Manufacturing & Wholesale Goods"
        }
    ],
    "sg:phone":"+44 1963 350530",
    "sg:postcode":"BA7 7PL",
    "sg:province":"Somerset",
    "sg:tags":[
        "others"
    ],
    "wof:name":"Wykes Farms",
    "wof:placetype":"venue"
},
  "geometry": {"coordinates":[-2.507946,51.110119],"type":"Point"}
}