{
  "type": "Feature",
  "properties": {
    "addr:full":"38 Cable Street Lancaster Lancashire LA1 1HH",
    "addr:housenumber":"38",
    "addr:postcode":"la1 1hh",
    "addr:street":"Cable Street",
    "iso:country":"GB",
    "sg:address":"38 Cable Street",
    "sg:city":"Lancaster",
    "sg:classifiers":[
        {
            "category":"Shopping",
            "subcategory":"Crafts & Fabrics",
            "type":"Retail Goods"
        }
    ],
    "sg:phone":"+44 1524 67928",
    "sg:postcode":"LA1 1HH",
    "sg:province":"Lancashire",
    "sg:tags":[
        "shop"
    ],
    "wof:name":"Lancaster Fabric Centre",
    "wof:placetype":"venue"
},
  "geometry": {"coordinates":[-2.799686,54.050961],"type":"Point"}
}