{
  "type": "Feature",
  "properties": {
    "addr:full":"Govan Road, Fenton Industrial Estate Stoke-on-trent Staffordshire ST4 2RS",
    "addr:postcode":"st4 2rs",
    "addr:street":"Govan Road;Industrial Estate",
    "iso:country":"GB",
    "sg:address":"Govan Road, Fenton Industrial Estate",
    "sg:city":"Stoke-on-trent",
    "sg:classifiers":[
        {
            "category":"Home & Garden",
            "subcategory":"Building Materials",
            "type":"Retail Goods"
        }
    ],
    "sg:phone":"+44 1782 745353",
    "sg:postcode":"ST4 2RS",
    "sg:province":"Staffordshire",
    "sg:tags":[
        "ready",
        "mixed",
        "concrete"
    ],
    "wof:name":"Tarmac Top Mix",
    "wof:placetype":"venue"
},
  "geometry": {"coordinates":[-2.1570689678,53.0087814331],"type":"Point"}
}