{
  "type": "Feature",
  "properties": {
    "addr:full":"Unit 3 Addlestone Surrey KT15 2SD",
    "addr:housenumber":"unit 3",
    "addr:postcode":"kt15 2sd",
    "addr:street":"Addlestone",
    "iso:country":"GB",
    "sg:address":"Unit 3",
    "sg:city":"Addlestone",
    "sg:classifiers":[
        {
            "category":"Freight",
            "type":"Transportation"
        }
    ],
    "sg:phone":"+44 1932 831551",
    "sg:postcode":"KT15 2SD",
    "sg:province":"Surrey",
    "sg:tags":[
        "forwarders"
    ],
    "wof:name":"Western Air Freight Ltd.",
    "wof:placetype":"venue"
},
  "geometry": {"coordinates":[-0.492578,51.381222],"type":"Point"}
}