{
  "type": "Feature",
  "properties": {
    "iso:country":"GB",
    "sg:address":"Unit 30 Clocktower Business Centre, Works Rd",
    "sg:city":"Chesterfield",
    "sg:classifiers":[
        {
            "category":"Deli",
            "type":"Food & Drink"
        }
    ],
    "sg:phone":"+44 1246 470593",
    "sg:postcode":"S43 2PE",
    "sg:province":"Derbyshire",
    "sg:tags":[
        "delivery",
        "sandwich"
    ],
    "wof:name":"Gourmet Sandwich,The Co",
    "wof:placetype":"venue"
},
  "geometry": {"coordinates":[-1.37703,53.270142],"type":"Point"}
}