{
  "type": "Feature",
  "properties": {
    "iso:country":"GB",
    "sg:address":"Cwrt-y-parc, Earlswood Rd, Llanishen",
    "sg:city":"Cardiff",
    "sg:classifiers":[
        {
            "category":"Travel",
            "subcategory":"Travel Agent",
            "type":"Entertainment"
        }
    ],
    "sg:phone":"+44 29 2076 4477",
    "sg:postcode":"CF14 5GH",
    "sg:province":"Cardiff",
    "wof:name":"Intervoyages (G B) Ltd",
    "wof:placetype":"venue"
},
  "geometry": {"coordinates":[-3.195525,51.528248],"type":"Point"}
}