{
  "type": "Feature",
  "properties": {
    "addr:full":"6 Burkeley St Stone Staffordshire ST15 8LS",
    "addr:housenumber":"6",
    "addr:postcode":"st15 8ls",
    "addr:street":"Burkeley St",
    "iso:country":"GB",
    "sg:address":"6 Burkeley St",
    "sg:city":"Stone",
    "sg:classifiers":[
        {
            "category":"Health Services",
            "subcategory":"Chiropractor",
            "type":"Services"
        }
    ],
    "sg:phone":"+44 1785 616010",
    "sg:postcode":"ST15 8LS",
    "sg:province":"Staffordshire",
    "wof:name":"Staffordshire McTimoney Chiropractic Clinic",
    "wof:placetype":"venue"
},
  "geometry": {"coordinates":[-2.1516990662,52.9081192017],"type":"Point"}
}