{
  "type": "Feature",
  "properties": {
    "addr:full":"Church Farm, Church Hill, Olveston Bristol Gloucestershire BS35 4BZ",
    "addr:postcode":"bs35 4bz",
    "addr:street":"Church Hill",
    "iso:country":"GB",
    "sg:address":"Church Farm, Church Hill, Olveston",
    "sg:city":"Bristol",
    "sg:classifiers":[
        {
            "category":"Farming",
            "subcategory":"Dairy Farm",
            "type":"Manufacturing & Wholesale Goods"
        }
    ],
    "sg:phone":"+44 1454 612182",
    "sg:postcode":"BS35 4BZ",
    "sg:province":"Gloucestershire",
    "sg:tags":[
        "farmer"
    ],
    "wof:name":"L F Cryer & Son",
    "wof:placetype":"venue"
},
  "geometry": {"coordinates":[-2.577038,51.581676],"type":"Point"}
}