{
  "type": "Feature",
  "properties": {
    "addr:full":"10 Hills Road Cambridge Cambridgeshire CB2 1JT",
    "addr:housenumber":"10",
    "addr:postcode":"cb2 1jt",
    "addr:street":"Hills Road",
    "iso:country":"GB",
    "sg:address":"10 Hills Road",
    "sg:city":"Cambridge",
    "sg:classifiers":[
        {
            "category":"Real Estate",
            "subcategory":"Surveying",
            "type":"Services"
        }
    ],
    "sg:phone":"+44 1223 355665",
    "sg:postcode":"CB2 1JT",
    "sg:province":"Cambridgeshire",
    "sg:tags":[
        "surveyor",
        "valuer"
    ],
    "wof:name":"Westley & Huff",
    "wof:placetype":"venue"
},
  "geometry": {"coordinates":[0.128349,52.197895],"type":"Point"}
}