{
  "type": "Feature",
  "properties": {
    "addr:full":"3-11 Fulbar Road Paisley East Renfrewshire PA2 9AW",
    "addr:housenumber":"3-11",
    "addr:postcode":"pa2 9aw",
    "addr:street":"Fulbar Road",
    "iso:country":"GB",
    "sg:address":"3-11 Fulbar Road",
    "sg:city":"Paisley",
    "sg:classifiers":[
        {
            "category":"Building & Trades",
            "subcategory":"Construction",
            "type":"Services"
        }
    ],
    "sg:phone":"+44 141 889 2072",
    "sg:postcode":"PA2 9AW",
    "sg:province":"East Renfrewshire",
    "sg:tags":[
        "welder"
    ],
    "wof:name":"Paisley Welding & Fabrication Ltd.",
    "wof:placetype":"venue"
},
  "geometry": {"coordinates":[-4.4601140022,55.8345718384],"type":"Point"}
}