{
  "type": "Feature",
  "properties": {
    "iso:country":"GB",
    "sg:address":"250 Slade Rd, Erdington",
    "sg:city":"Birmingham",
    "sg:classifiers":[
        {
            "category":"Food & Beverages",
            "subcategory":"Liquor & Beverages",
            "type":"Retail Goods"
        }
    ],
    "sg:postcode":"B23 7RH",
    "sg:province":"West Midlands",
    "sg:tags":[
        "beer",
        "spirit",
        "wines"
    ],
    "wof:name":"Slade Wine Lodge",
    "wof:placetype":"venue"
},
  "geometry": {"coordinates":[-1.856262,52.516689],"type":"Point"}
}