{
  "type": "Feature",
  "properties": {
    "iso:country":"GB",
    "sg:address":"Bell Lane",
    "sg:city":"Lewes",
    "sg:classifiers":[
        {
            "category":"Shopping",
            "subcategory":"Pharmacy",
            "type":"Retail Goods"
        }
    ],
    "sg:phone":"+44 1273 480444",
    "sg:postcode":"BN7 1LG",
    "sg:province":"East Sussex",
    "sg:tags":[
        "pharmacist",
        "chemist"
    ],
    "wof:name":"Boehringer Mannheim U K Ltd.",
    "wof:placetype":"venue"
},
  "geometry": {"coordinates":[-0.002697,50.8690299988],"type":"Point"}
}