{
  "type": "Feature",
  "properties": {
    "addr:full":"25 Trowers Way, Holmethorpe Industrial Estate Redhill Surrey RH1 2LH",
    "addr:housenumber":"25",
    "addr:postcode":"rh1 2lh",
    "addr:street":"Trowers Way Holmethorpe Industrial Estate",
    "iso:country":"GB",
    "sg:address":"25 Trowers Way, Holmethorpe Industrial Estate",
    "sg:city":"Redhill",
    "sg:classifiers":[
        {
            "category":"Professional",
            "subcategory":"Management & Consulting",
            "type":"Services"
        }
    ],
    "sg:postcode":"RH1 2LH",
    "sg:province":"Surrey",
    "sg:tags":[
        "marketing",
        "consultant"
    ],
    "wof:name":"Marketman Marketing Ltd.",
    "wof:placetype":"venue"
},
  "geometry": {"coordinates":[-0.1548,51.251133],"type":"Point"}
}