{
  "type": "Feature",
  "properties": {
    "addr:full":"Monsall Mill, Monsall Rd Manchester Greater Manchester M40 8NQ",
    "addr:postcode":"m40 8nq",
    "addr:street":"Monsall;Monsall Rd",
    "iso:country":"GB",
    "sg:address":"Monsall Mill, Monsall Rd",
    "sg:city":"Manchester",
    "sg:classifiers":[
        {
            "category":"Shopping",
            "subcategory":"Crafts & Fabrics",
            "type":"Retail Goods"
        }
    ],
    "sg:phone":"+44 161 205 2443",
    "sg:postcode":"M40 8NQ",
    "sg:province":"Greater Manchester",
    "sg:tags":[
        "upholsterers'",
        "supply"
    ],
    "wof:name":"A J Frames",
    "wof:placetype":"venue"
},
  "geometry": {"coordinates":[-2.20868,53.504639],"type":"Point"}
}