{
  "type": "Feature",
  "properties": {
    "addr:full":"295 Lincoln Road Peterborough Cambridgeshire PE1 2PH",
    "addr:housenumber":"295",
    "addr:postcode":"pe1 2ph",
    "addr:street":"Lincoln Road",
    "iso:country":"GB",
    "sg:address":"295 Lincoln Road",
    "sg:city":"Peterborough",
    "sg:classifiers":[
        {
            "category":"Shopping",
            "subcategory":"News",
            "type":"Retail Goods"
        }
    ],
    "sg:phone":"+44 1733 343760",
    "sg:postcode":"PE1 2PH",
    "sg:province":"Cambridgeshire",
    "sg:tags":[
        "newsagent"
    ],
    "wof:name":"Petes Newsagents",
    "wof:placetype":"venue"
},
  "geometry": {"coordinates":[-0.246287,52.586964],"type":"Point"}
}