{
  "type": "Feature",
  "properties": {
    "iso:country":"GB",
    "sg:address":"6 Spring Gardens",
    "sg:city":"Newark",
    "sg:classifiers":[
        {
            "category":"Retail",
            "subcategory":"Repair Shop",
            "type":"Services"
        },
        {
            "category":"Shopping",
            "subcategory":"Antiques",
            "type":"Retail Goods"
        }
    ],
    "sg:phone":"+44 1636 611030",
    "sg:postcode":"NG24 4UW",
    "sg:province":"Nottinghamshire",
    "sg:tags":[
        "restoration"
    ],
    "wof:name":"Stitch & Stuff",
    "wof:placetype":"venue"
},
  "geometry": {"coordinates":[-0.8142499924,53.0715904236],"type":"Point"}
}