{
  "type": "Feature",
  "properties": {
    "addr:full":"Backshot Farm, Forth Lanark South Lanarkshire ML11 8EN",
    "addr:postcode":"ml11 8en",
    "addr:street":"Forth",
    "iso:country":"GB",
    "sg:address":"Backshot Farm, Forth",
    "sg:city":"Lanark",
    "sg:classifiers":[
        {
            "category":"Farming",
            "subcategory":"Livestock Farm",
            "type":"Manufacturing & Wholesale Goods"
        }
    ],
    "sg:phone":"+44 1555 811285",
    "sg:postcode":"ML11 8EN",
    "sg:province":"South Lanarkshire",
    "sg:tags":[
        "others"
    ],
    "wof:name":"J Gemmell & Partner",
    "wof:placetype":"venue"
},
  "geometry": {"coordinates":[-3.6883490086,55.7654800415],"type":"Point"}
}