{
  "type": "Feature",
  "properties": {
    "addr:full":"31 The Crescent Salford Greater Manchester M5 4PF",
    "addr:housenumber":"31",
    "addr:postcode":"m5 4pf",
    "addr:street":"The Crescent",
    "iso:country":"GB",
    "sg:address":"31 The Crescent",
    "sg:city":"Salford",
    "sg:classifiers":[
        {
            "category":"Real Estate",
            "subcategory":"Architect",
            "type":"Services"
        }
    ],
    "sg:phone":"+44 161 736 1447",
    "sg:postcode":"M5 4PF",
    "sg:province":"Greater Manchester",
    "wof:name":"BRITCH & ASSOCIATES LIMITED",
    "wof:placetype":"venue"
},
  "geometry": {"coordinates":[-2.2682840824,53.4829711914],"type":"Point"}
}