{
  "type": "Feature",
  "properties": {
    "iso:country":"GB",
    "sg:address":"123 Waterloo Road",
    "sg:city":"Llanelli",
    "sg:classifiers":[
        {
            "category":"Building & Trades",
            "subcategory":"Construction",
            "type":"Services"
        }
    ],
    "sg:postcode":"SA14 7PU",
    "sg:province":"Carmarthenshire",
    "sg:tags":[
        "builder"
    ],
    "wof:name":"Sutton Bros Building & Civil Engineering Contracto",
    "wof:placetype":"venue"
},
  "geometry": {"coordinates":[-4.0492358208,51.7964019775],"type":"Point"}
}