{
  "type": "Feature",
  "properties": {
    "addr:full":"Platform 14, Victoria Station London Greater London SW1V 1JT",
    "addr:postcode":"sw1v 1jt",
    "addr:street":"Victoria Station",
    "iso:country":"GB",
    "sg:address":"Platform 14, Victoria Station",
    "sg:city":"London",
    "sg:classifiers":[
        {
            "category":"Food & Beverages",
            "subcategory":"Bakery",
            "type":"Retail Goods"
        }
    ],
    "sg:phone":"+44 20 7233 8226",
    "sg:postcode":"SW1V 1JT",
    "sg:province":"Greater London",
    "sg:tags":[
        "baker"
    ],
    "wof:name":"Mario's Bakes Store",
    "wof:placetype":"venue"
},
  "geometry": {"coordinates":[-0.1403660029,51.4938774109],"type":"Point"}
}