{
  "type": "Feature",
  "properties": {
    "addr:full":"C/o Secretary Registrars, The Quadrangle London Greater London W1F 8FY",
    "addr:postcode":"w1f 8fy",
    "addr:street":"C",
    "iso:country":"GB",
    "sg:address":"C/o Secretary Registrars, The Quadrangle",
    "sg:city":"London",
    "sg:classifiers":[
        {
            "category":"Professional",
            "subcategory":"Art Services",
            "type":"Services"
        }
    ],
    "sg:postcode":"W1F 8FY",
    "sg:province":"Greater London",
    "sg:tags":[
        "consultant",
        "design"
    ],
    "wof:name":"Finnemore & Field Trustees Ltd",
    "wof:placetype":"venue"
},
  "geometry": {"coordinates":[-0.1352600008,51.5156097412],"type":"Point"}
}