{
  "type": "Feature",
  "properties": {
    "addr:full":"Quantum House, 10 Bracknell Beeches Bracknell Berkshire RG12 7BW",
    "addr:housenumber":"10",
    "addr:postcode":"rg12 7bw",
    "iso:country":"GB",
    "sg:address":"Quantum House, 10 Bracknell Beeches",
    "sg:city":"Bracknell",
    "sg:classifiers":[
        {
            "category":"Retail",
            "subcategory":"Storage",
            "type":"Services"
        },
        {
            "category":"Professional",
            "subcategory":"Computer Services",
            "type":"Services"
        }
    ],
    "sg:phone":"+44 1344 353500",
    "sg:postcode":"RG12 7BW",
    "sg:province":"Berkshire",
    "sg:tags":[
        "operation",
        "software",
        "system",
        "facility"
    ],
    "sg:website":"http://www.quantum.com",
    "wof:name":"Quantum Peripheral Products Ltd",
    "wof:placetype":"venue"
},
  "geometry": {"coordinates":[-0.755009,51.411865],"type":"Point"}
}