{
  "type": "Feature",
  "properties": {
    "addr:full":"15 Station Road, Milngavie Glasgow East Dunbartonshire G62 8PG",
    "addr:housenumber":"15",
    "addr:postcode":"g62 8pg",
    "addr:street":"Station Road",
    "iso:country":"GB",
    "sg:address":"15 Station Road, Milngavie",
    "sg:city":"Glasgow",
    "sg:classifiers":[
        {
            "category":"Restaurant",
            "type":"Food & Drink"
        }
    ],
    "sg:phone":"+44 141 956 5413",
    "sg:postcode":"G62 8PG",
    "sg:province":"East Dunbartonshire",
    "sg:tags":[
        "-",
        "chinese"
    ],
    "wof:name":"ROYAL GARDEN",
    "wof:placetype":"venue"
},
  "geometry": {"coordinates":[-4.315719,55.942169],"type":"Point"}
}