{
  "type": "Feature",
  "properties": {
    "iso:country":"GB",
    "sg:address":"7 Lon Caron",
    "sg:city":"Swansea",
    "sg:classifiers":[
        {
            "category":"Retail",
            "subcategory":"Repair Shop",
            "type":"Services"
        }
    ],
    "sg:phone":"+44 1792 204140",
    "sg:postcode":"SA2 0TW",
    "sg:province":"Swansea",
    "sg:tags":[
        "radio",
        "television",
        "video"
    ],
    "wof:name":"Sketty Vision",
    "wof:placetype":"venue"
},
  "geometry": {"coordinates":[-3.980641,51.622906],"type":"Point"}
}