{
  "type": "Feature",
  "properties": {
    "iso:country":"GB",
    "sg:address":"48 Bartel Close",
    "sg:city":"Hemel Hempstead",
    "sg:classifiers":[
        {
            "category":"Autos & Motor Vehicles",
            "subcategory":"Automobile Sales",
            "type":"Retail Goods"
        }
    ],
    "sg:postcode":"HP3 8LY",
    "sg:province":"Hertfordshire",
    "sg:tags":[
        "auction",
        "car"
    ],
    "wof:name":"Fleet Car Acquisitions Limited",
    "wof:placetype":"venue"
},
  "geometry": {"coordinates":[-0.425576,51.745281],"type":"Point"}
}