{
  "type": "Feature",
  "properties": {
    "addr:full":"Unit 8 Brook Industrial Estate, Bullsbrook Road Hayes Greater London UB4 0JZ",
    "addr:housenumber":"unit 8",
    "addr:postcode":"ub4 0jz",
    "addr:street":"Brook Industrial Estate Bullsbrook Road",
    "iso:country":"GB",
    "sg:address":"Unit 8 Brook Industrial Estate, Bullsbrook Road",
    "sg:city":"Hayes",
    "sg:classifiers":[
        {
            "category":"Professional",
            "subcategory":"Business Services",
            "type":"Services"
        }
    ],
    "sg:phone":"+44 20 8573 3150",
    "sg:postcode":"UB4 0JZ",
    "sg:province":"Greater London",
    "sg:tags":[
        "distribution"
    ],
    "wof:name":"W & G Sissons (Stainless Steel)",
    "wof:placetype":"venue"
},
  "geometry": {"coordinates":[-0.3936800063,51.5103683472],"type":"Point"}
}