{
  "type": "Feature",
  "properties": {
    "addr:full":"6 Edgefield Court Barking Essex IG11 9JP",
    "addr:housenumber":"6",
    "addr:postcode":"ig11 9jp",
    "addr:street":"Edgefield Court",
    "iso:country":"GB",
    "sg:address":"6 Edgefield Court",
    "sg:city":"Barking",
    "sg:classifiers":[
        {
            "category":"Retail",
            "subcategory":"Auto Repair",
            "type":"Services"
        }
    ],
    "sg:phone":"+44 20 8598 2000",
    "sg:postcode":"IG11 9JP",
    "sg:province":"Essex",
    "sg:tags":[
        "modification",
        "garage"
    ],
    "wof:name":"M K Auto Electrics",
    "wof:placetype":"venue"
},
  "geometry": {"coordinates":[0.104344,51.539177],"type":"Point"}
}