{
  "type": "Feature",
  "properties": {
    "addr:full":"81 St Brelades Avenue, Parkstone Poole Dorset BH12 4JR",
    "addr:housenumber":"81",
    "addr:postcode":"bh12 4jr",
    "addr:street":"St Brelades Avenue",
    "iso:country":"GB",
    "sg:address":"81 St Brelades Avenue, Parkstone",
    "sg:city":"Poole",
    "sg:classifiers":[
        {
            "category":"Building & Trades",
            "subcategory":"Construction",
            "type":"Services"
        }
    ],
    "sg:phone":"+44 1202 744324",
    "sg:postcode":"BH12 4JR",
    "sg:province":"Dorset",
    "sg:tags":[
        "tile",
        "fitting",
        "tiling",
        "laying",
        "contractor"
    ],
    "wof:name":"R F Lucas",
    "wof:placetype":"venue"
},
  "geometry": {"coordinates":[-1.933819,50.75024],"type":"Point"}
}