{
  "type": "Feature",
  "properties": {
    "addr:full":"83 Binfield Road Bracknell Berkshire RG42 2AW",
    "addr:housenumber":"83",
    "addr:postcode":"rg42 2aw",
    "addr:street":"Binfield Road",
    "iso:country":"GB",
    "sg:address":"83 Binfield Road",
    "sg:city":"Bracknell",
    "sg:classifiers":[
        {
            "category":"Shopping",
            "subcategory":"Department Store",
            "type":"Retail Goods"
        },
        {
            "category":"Shopping",
            "subcategory":"News",
            "type":"Retail Goods"
        }
    ],
    "sg:phone":"+44 1344 425139",
    "sg:postcode":"RG42 2AW",
    "sg:province":"Berkshire",
    "sg:tags":[
        "newsagent"
    ],
    "wof:name":"Priestwood Post Office",
    "wof:placetype":"venue"
},
  "geometry": {"coordinates":[-0.7571049929,51.419921875],"type":"Point"}
}