{
  "type": "Feature",
  "properties": {
    "addr:full":"16 Dufours Place London Greater London W1F 7SL",
    "addr:housenumber":"16",
    "addr:postcode":"w1f 7sl",
    "addr:street":"Dufours Place",
    "iso:country":"GB",
    "sg:address":"16 Dufours Place",
    "sg:city":"London",
    "sg:classifiers":[
        {
            "category":"Professional",
            "subcategory":"Management & Consulting",
            "type":"Services"
        }
    ],
    "sg:postcode":"W1F 7SL",
    "sg:province":"Greater London",
    "sg:tags":[
        "consultant",
        "business"
    ],
    "wof:name":"Corporate Communications Strategy",
    "wof:placetype":"venue"
},
  "geometry": {"coordinates":[-0.1374419928,51.5135612488],"type":"Point"}
}