{
  "type": "Feature",
  "properties": {
    "addr:full":"8 Parkhead Gardens Edinburgh City of Edinburgh EH11 4SQ",
    "addr:housenumber":"8",
    "addr:postcode":"eh11 4sq",
    "addr:street":"Parkhead Gardens",
    "iso:country":"GB",
    "sg:address":"8 Parkhead Gardens",
    "sg:city":"Edinburgh",
    "sg:classifiers":[
        {
            "category":"Food & Beverages",
            "subcategory":"Bakery",
            "type":"Retail Goods"
        }
    ],
    "sg:phone":"+44 131 476 7017",
    "sg:postcode":"EH11 4SQ",
    "sg:province":"City of Edinburgh",
    "sg:tags":[
        "baker"
    ],
    "wof:name":"R & M Bakery",
    "wof:placetype":"venue"
},
  "geometry": {"coordinates":[-3.277002,55.924484],"type":"Point"}
}