{
  "type": "Feature",
  "properties": {
    "addr:full":"7 The Broadway London Greater London N22 6DU",
    "addr:housenumber":"7",
    "addr:postcode":"n22 6du",
    "addr:street":"The Broadway",
    "iso:country":"GB",
    "sg:address":"7 The Broadway",
    "sg:city":"London",
    "sg:classifiers":[
        {
            "category":"Food & Beverages",
            "subcategory":"Bakery",
            "type":"Retail Goods"
        }
    ],
    "sg:phone":"+44 20 8881 9067",
    "sg:postcode":"N22 6DU",
    "sg:province":"Greater London",
    "sg:tags":[
        "baker"
    ],
    "wof:name":"Greggs Plc",
    "wof:placetype":"venue"
},
  "geometry": {"coordinates":[-0.12409,51.578671],"type":"Point"}
}