{
  "type": "Feature",
  "properties": {
    "addr:full":"8-10 Manchester St Heywood Lancashire OL10 2AH",
    "addr:housenumber":"8-10",
    "addr:postcode":"ol10 2ah",
    "addr:street":"Manchester St",
    "iso:country":"GB",
    "sg:address":"8-10 Manchester St",
    "sg:city":"Heywood",
    "sg:classifiers":[
        {
            "category":"Food & Beverages",
            "subcategory":"Fruits & Vegetables",
            "type":"Retail Goods"
        }
    ],
    "sg:postcode":"OL10 2AH",
    "sg:province":"Lancashire",
    "sg:tags":[
        "greengrocer"
    ],
    "wof:name":"Settle,P & M,",
    "wof:placetype":"venue"
},
  "geometry": {"coordinates":[-2.2109670639,53.5887908936],"type":"Point"}
}