{
  "type": "Feature",
  "properties": {
    "addr:full":"Higher Kingston Farm, Higher Kingston Dorchester Dorset DT2 8QE",
    "addr:housenumber":"higher kingston dorchester",
    "addr:postcode":"dt2 8qe",
    "addr:street":"Dorset",
    "iso:country":"GB",
    "sg:address":"Higher Kingston Farm, Higher Kingston",
    "sg:city":"Dorchester",
    "sg:classifiers":[
        {
            "category":"Farming",
            "subcategory":"Livestock Farm",
            "type":"Manufacturing & Wholesale Goods"
        }
    ],
    "sg:postcode":"DT2 8QE",
    "sg:province":"Dorset",
    "sg:tags":[
        "others"
    ],
    "wof:name":"Hollands (Farms) Ltd.",
    "wof:placetype":"venue"
},
  "geometry": {"coordinates":[-2.4038898945,50.7352485657],"type":"Point"}
}