{
  "type": "Feature",
  "properties": {
    "addr:full":"Hughenden Yard, High Street Marlborough Berkshire SN8 1LT",
    "addr:postcode":"sn8 1lt",
    "addr:street":"Hughenden;High Street",
    "iso:country":"GB",
    "sg:address":"Hughenden Yard, High Street",
    "sg:city":"Marlborough",
    "sg:classifiers":[
        {
            "category":"Personal",
            "subcategory":"Beauty Salon",
            "type":"Services"
        }
    ],
    "sg:phone":"+44 1672 514236",
    "sg:postcode":"SN8 1LT",
    "sg:province":"Berkshire",
    "wof:name":"Snippets & Blushes",
    "wof:placetype":"venue"
},
  "geometry": {"coordinates":[-1.7298890352,51.421333313],"type":"Point"}
}