{
  "type": "Feature",
  "properties": {
    "addr:full":"29 Little Tennis Street Nottingham Nottinghamshire NG2 4EL",
    "addr:housenumber":"29",
    "addr:postcode":"ng2 4el",
    "addr:street":"Little Tennis Street",
    "iso:country":"GB",
    "sg:address":"29 Little Tennis Street",
    "sg:city":"Nottingham",
    "sg:classifiers":[
        {
            "category":"Retail",
            "subcategory":"Auto Repair",
            "type":"Services"
        }
    ],
    "sg:phone":"+44 115 911 9770",
    "sg:postcode":"NG2 4EL",
    "sg:province":"Nottinghamshire",
    "sg:tags":[
        "body",
        "car"
    ],
    "wof:name":"R White",
    "wof:placetype":"venue"
},
  "geometry": {"coordinates":[-1.12031,52.946121],"type":"Point"}
}