{
  "type": "Feature",
  "properties": {
    "iso:country":"GB",
    "sg:address":"35 Bridge Street",
    "sg:city":"Usk",
    "sg:classifiers":[
        {
            "category":"Food & Beverages",
            "subcategory":"Meat & Fish",
            "type":"Retail Goods"
        }
    ],
    "sg:postcode":"NP15 1BQ",
    "sg:province":"Monmouthshire",
    "sg:tags":[
        "butcher"
    ],
    "wof:name":"E J Harley & Sons",
    "wof:placetype":"venue"
},
  "geometry": {"coordinates":[-2.904689,51.70261],"type":"Point"}
}