{
  "type": "Feature",
  "properties": {
    "addr:full":"2 Barton Road Rugby Warwickshire CV22 7PT",
    "addr:housenumber":"2",
    "addr:postcode":"cv22 7pt",
    "addr:street":"Barton Road",
    "iso:country":"GB",
    "sg:address":"2 Barton Road",
    "sg:city":"Rugby",
    "sg:classifiers":[
        {
            "category":"Building & Trades",
            "subcategory":"Plumbing",
            "type":"Services"
        }
    ],
    "sg:postcode":"CV22 7PT",
    "sg:province":"Warwickshire",
    "sg:tags":[
        "heating"
    ],
    "wof:name":"Burden Kenneth Plumbing & Central Heating Services",
    "wof:placetype":"venue"
},
  "geometry": {"coordinates":[-1.2814019918,52.3575553894],"type":"Point"}
}