{
  "type": "Feature",
  "properties": {
    "addr:full":"2 Mill View, Clifford Street Newton Abbot Devon TQ13 0LQ",
    "addr:housenumber":"2",
    "addr:postcode":"tq13 0lq",
    "addr:street":"Mill View Clifford Street",
    "iso:country":"GB",
    "sg:address":"2 Mill View, Clifford Street",
    "sg:city":"Newton Abbot",
    "sg:classifiers":[
        {
            "category":"Arts & Performance",
            "subcategory":"Music",
            "type":"Entertainment"
        }
    ],
    "sg:phone":"+44 1626 853719",
    "sg:postcode":"TQ13 0LQ",
    "sg:province":"Devon",
    "sg:tags":[
        "mobile",
        "disco"
    ],
    "wof:name":"Richsounds Disco",
    "wof:placetype":"venue"
},
  "geometry": {"coordinates":[-3.597164,50.602726],"type":"Point"}
}