{
  "type": "Feature",
  "properties": {
    "iso:country":"GB",
    "sg:address":"33 Colegate",
    "sg:city":"Norwich",
    "sg:classifiers":[
        {
            "category":"Organizations",
            "subcategory":"Membership Organization",
            "type":"Services"
        }
    ],
    "sg:phone":"+44 1603 625057",
    "sg:postcode":"NR3 1BN",
    "sg:province":"Norfolk",
    "sg:tags":[
        "club"
    ],
    "wof:name":"The City Club",
    "wof:placetype":"venue"
},
  "geometry": {"coordinates":[1.295320034,52.6333084106],"type":"Point"}
}