{
  "type": "Feature",
  "properties": {
    "iso:country":"GB",
    "sg:address":"Beech Court, Hallcourt Cresent",
    "sg:city":"Cannock",
    "sg:classifiers":[
        {
            "category":"Professional",
            "subcategory":"Management & Consulting",
            "type":"Services"
        }
    ],
    "sg:phone":"+44 1543 468868",
    "sg:postcode":"WS11 3AD",
    "sg:province":"Staffordshire",
    "sg:tags":[
        "environmental",
        "consultant"
    ],
    "wof:name":"Safety Training Consultancy",
    "wof:placetype":"venue"
},
  "geometry": {"coordinates":[-2.027097,52.685982],"type":"Point"}
}