{
  "type": "Feature",
  "properties": {
    "iso:country":"GB",
    "sg:address":"Church Road, Copthorne",
    "sg:city":"Crawley",
    "sg:classifiers":[
        {
            "category":"Shopping",
            "subcategory":"Pharmacy",
            "type":"Retail Goods"
        }
    ],
    "sg:phone":"+44 1342 716133",
    "sg:postcode":"RH10 3RA",
    "sg:province":"Surrey",
    "sg:tags":[
        "pharmacist",
        "chemist"
    ],
    "wof:name":"Rivermead",
    "wof:placetype":"venue"
},
  "geometry": {"coordinates":[-0.121961,51.133877],"type":"Point"}
}