{
  "type": "Feature",
  "properties": {
    "addr:full":"489 Bromley Road, Downham Bromley Kent BR1 4PQ",
    "addr:housenumber":"489",
    "addr:postcode":"br1 4pq",
    "addr:street":"Bromley Road",
    "iso:country":"GB",
    "sg:address":"489 Bromley Road, Downham",
    "sg:city":"Bromley",
    "sg:classifiers":[
        {
            "category":"Manufacturing",
            "subcategory":"Petroleum Products",
            "type":"Manufacturing & Wholesale Goods"
        }
    ],
    "sg:phone":"+44 20 8697 8081",
    "sg:postcode":"BR1 4PQ",
    "sg:province":"Kent",
    "sg:tags":[
        "double",
        "glazing"
    ],
    "wof:name":"Homecastle Home Improvements Ltd.",
    "wof:placetype":"venue"
},
  "geometry": {"coordinates":[-0.0032200001,51.4236946106],"type":"Point"}
}