{
  "type": "Feature",
  "properties": {
    "iso:country":"GB",
    "sg:address":"Burton Pl",
    "sg:city":"Taunton",
    "sg:classifiers":[
        {
            "category":"Government",
            "subcategory":"Office",
            "type":"Public Place"
        }
    ],
    "sg:phone":"+44 1823 321501",
    "sg:postcode":"TA1 4HE",
    "sg:province":"Somerset",
    "sg:tags":[
        "local"
    ],
    "wof:name":"W S Atkins Highway Maintenance S W Are",
    "wof:placetype":"venue"
},
  "geometry": {"coordinates":[-3.107964,51.011845],"type":"Point"}
}