{
  "type": "Feature",
  "properties": {
    "iso:country":"GB",
    "sg:address":"2 Wingfield Street, Stretford",
    "sg:city":"Manchester",
    "sg:classifiers":[
        {
            "category":"Food & Beverages",
            "subcategory":"Liquor & Beverages",
            "type":"Retail Goods"
        }
    ],
    "sg:phone":"+44 161 865 1895",
    "sg:postcode":"M32 0PL",
    "sg:province":"Cheshire",
    "sg:tags":[
        "beer",
        "spirit",
        "wines"
    ],
    "wof:name":"Murray's",
    "wof:placetype":"venue"
},
  "geometry": {"coordinates":[-2.301917,53.45676],"type":"Point"}
}