{
  "type": "Feature",
  "properties": {
    "iso:country":"GB",
    "sg:address":"Bothal Rectory, Longhirst Rd",
    "sg:city":"Morpeth",
    "sg:classifiers":[
        {
            "category":"Place Of Worship",
            "type":"Public Place"
        }
    ],
    "sg:phone":"+44 1670 510793",
    "sg:postcode":"NE61 6XF",
    "sg:province":"Northumberland",
    "wof:name":"Bothal Church",
    "wof:placetype":"venue"
},
  "geometry": {"coordinates":[-1.625599,55.174252],"type":"Point"}
}