{
  "type": "Feature",
  "properties": {
    "iso:country":"GB",
    "sg:address":"Blacklaw Garage, Aberchirder",
    "sg:city":"Huntly",
    "sg:classifiers":[
        {
            "category":"Retail",
            "subcategory":"Auto Repair",
            "type":"Services"
        }
    ],
    "sg:phone":"+44 1466 780076",
    "sg:postcode":"AB54 7PX",
    "sg:province":"Aberdeenshire",
    "sg:tags":[
        "modification",
        "garage"
    ],
    "wof:name":"R J Autobodies",
    "wof:placetype":"venue"
},
  "geometry": {"coordinates":[-2.628814,57.560955],"type":"Point"}
}