{
  "type": "Feature",
  "properties": {
    "addr:full":"12 Midland Road Olney Buckinghamshire MK46 4BL",
    "addr:housenumber":"12",
    "addr:postcode":"mk46 4bl",
    "addr:street":"Midland Road",
    "iso:country":"GB",
    "sg:address":"12 Midland Road",
    "sg:city":"Olney",
    "sg:classifiers":[
        {
            "category":"Building & Trades",
            "subcategory":"Cleaning & Sanitation",
            "type":"Services"
        }
    ],
    "sg:phone":"+44 1234 241234",
    "sg:postcode":"MK46 4BL",
    "sg:province":"Buckinghamshire",
    "sg:tags":[
        "dry",
        "control",
        "damp",
        "rot"
    ],
    "wof:name":"Buzzard Preservation",
    "wof:placetype":"venue"
},
  "geometry": {"coordinates":[-0.7016569972,52.1597442627],"type":"Point"}
}