{
  "type": "Feature",
  "properties": {
    "addr:full":"The Old Church, Bollington Macclesfield Cheshire SK10 5PW",
    "addr:postcode":"sk10 5pw",
    "iso:country":"GB",
    "sg:address":"The Old Church, Bollington",
    "sg:city":"Macclesfield",
    "sg:classifiers":[
        {
            "category":"Professional",
            "subcategory":"Art Services",
            "type":"Services"
        }
    ],
    "sg:postcode":"SK10 5PW",
    "sg:province":"Cheshire",
    "sg:tags":[
        "graphic",
        "designer"
    ],
    "wof:name":"Fourth Dimension Computer Graphics Ltd",
    "wof:placetype":"venue"
},
  "geometry": {"coordinates":[-2.1103689671,53.2933883667],"type":"Point"}
}