{
  "type": "Feature",
  "properties": {
    "iso:country":"GB",
    "sg:address":"105 Bedale Drive, Skelmanthorpe",
    "sg:city":"Huddersfield",
    "sg:classifiers":[
        {
            "category":"Professional",
            "subcategory":"Engineering",
            "type":"Services"
        }
    ],
    "sg:phone":"+44 1484 863214",
    "sg:postcode":"HD8 9EU",
    "sg:province":"South Yorkshire",
    "sg:tags":[
        "contractor",
        "electrical",
        "engineer"
    ],
    "wof:name":"Martyn Wadsworth Electrician",
    "wof:placetype":"venue"
},
  "geometry": {"coordinates":[-1.659452,53.590172],"type":"Point"}
}