{
  "type": "Feature",
  "properties": {
    "addr:full":"30-31 Saxon Square Christchurch Dorset BH23 1QB",
    "addr:housenumber":"30-31",
    "addr:postcode":"bh23 1qb",
    "addr:street":"Saxon Square",
    "iso:country":"GB",
    "sg:address":"30-31 Saxon Square",
    "sg:city":"Christchurch",
    "sg:classifiers":[
        {
            "category":"Shopping",
            "subcategory":"Hobbies, Toys, & Games",
            "type":"Retail Goods"
        }
    ],
    "sg:phone":"+44 1202 486611",
    "sg:postcode":"BH23 1QB",
    "sg:province":"Dorset",
    "sg:tags":[
        "stamp",
        "shop",
        "toy"
    ],
    "wof:name":"Hobbies Models & Toys Ltd.",
    "wof:placetype":"venue"
},
  "geometry": {"coordinates":[-1.777609,50.735001],"type":"Point"}
}