{
  "type": "Feature",
  "properties": {
    "iso:country":"GB",
    "sg:address":"2 Northlands Pavement, Pitsea Centre",
    "sg:city":"Basildon",
    "sg:classifiers":[
        {
            "category":"Shopping",
            "subcategory":"Clothing, Apparel, & Fashions",
            "type":"Retail Goods"
        }
    ],
    "sg:postcode":"SS13 3DU",
    "sg:province":"Essex",
    "sg:tags":[
        "shop"
    ],
    "wof:name":"Aeon Clothing Ltd.",
    "wof:placetype":"venue"
},
  "geometry": {"coordinates":[0.50455,51.564823],"type":"Point"}
}