{
  "type": "Feature",
  "properties": {
    "addr:full":"4 Alison Road London Greater London W3 6JE",
    "addr:housenumber":"4",
    "addr:postcode":"w3 6je",
    "addr:street":"Alison Road",
    "iso:country":"GB",
    "sg:address":"4 Alison Road",
    "sg:city":"London",
    "sg:classifiers":[
        {
            "category":"Shopping",
            "subcategory":"Pharmacy",
            "type":"Retail Goods"
        }
    ],
    "sg:postcode":"W3 6JE",
    "sg:province":"Greater London",
    "sg:tags":[
        "pharmacist",
        "chemist"
    ],
    "wof:name":"Mohammed S Merchant",
    "wof:placetype":"venue"
},
  "geometry": {"coordinates":[-0.266592,51.515469],"type":"Point"}
}