{
  "type": "Feature",
  "properties": {
    "addr:full":"20 Hollingworth Avenue, Sandiacre Nottingham Derbyshire NG10 5LY",
    "addr:housenumber":"20",
    "addr:postcode":"ng10 5ly",
    "addr:street":"Hollingworth Avenue",
    "iso:country":"GB",
    "sg:address":"20 Hollingworth Avenue, Sandiacre",
    "sg:city":"Nottingham",
    "sg:classifiers":[
        {
            "category":"Building & Trades",
            "subcategory":"Cleaning & Sanitation",
            "type":"Services"
        },
        {
            "category":"Home & Garden",
            "subcategory":"Carpets & Floor Coverings",
            "type":"Retail Goods"
        }
    ],
    "sg:phone":"+44 115 973 1648",
    "sg:postcode":"NG10 5LY",
    "sg:province":"Derbyshire",
    "sg:tags":[
        "cleaner",
        "upholstery"
    ],
    "wof:name":"B J Cleaning",
    "wof:placetype":"venue"
},
  "geometry": {"coordinates":[-1.2921249866,52.9134368896],"type":"Point"}
}