{
  "type": "Feature",
  "properties": {
    "addr:full":"1 Boot Lane, Bedminster Bristol City of Bristol BS3 4ED",
    "addr:housenumber":"1",
    "addr:postcode":"bs3 4ed",
    "addr:street":"Boot Lane",
    "iso:country":"GB",
    "sg:address":"1 Boot Lane, Bedminster",
    "sg:city":"Bristol",
    "sg:classifiers":[
        {
            "category":"Autos & Motor Vehicles",
            "subcategory":"Automobile Sales",
            "type":"Retail Goods"
        }
    ],
    "sg:phone":"+44 117 914 3332",
    "sg:postcode":"BS3 4ED",
    "sg:province":"City of Bristol",
    "sg:tags":[
        "car",
        "specialist",
        "sales",
        "classic"
    ],
    "wof:name":"Memory Lane Motors",
    "wof:placetype":"venue"
},
  "geometry": {"coordinates":[-2.592424,51.444534],"type":"Point"}
}