{
  "type": "Feature",
  "properties": {
    "addr:full":"Unit C Millshaw Park, Millshaw Industrial Estate Leeds West Yorkshire LS11 0HD",
    "addr:housenumber":"unit c millshaw",
    "addr:postcode":"ls11 0hd",
    "addr:street":"Park Millshaw Industrial Estate",
    "iso:country":"GB",
    "sg:address":"Unit C Millshaw Park, Millshaw Industrial Estate",
    "sg:city":"Leeds",
    "sg:classifiers":[
        {
            "category":"Freight",
            "type":"Transportation"
        }
    ],
    "sg:phone":"+44 113 271 8800",
    "sg:postcode":"LS11 0HD",
    "sg:province":"West Yorkshire",
    "sg:tags":[
        "haulage",
        "road"
    ],
    "wof:name":"Freelance Freight",
    "wof:placetype":"venue"
},
  "geometry": {"coordinates":[-1.5770640373,53.7646141052],"type":"Point"}
}