{
  "type": "Feature",
  "properties": {
    "iso:country":"GB",
    "sg:address":"432 Whitmore Way",
    "sg:city":"Basildon",
    "sg:classifiers":[
        {
            "category":"Retail",
            "subcategory":"Laundry & Dry Cleaning",
            "type":"Services"
        }
    ],
    "sg:phone":"+44 1268 520361",
    "sg:postcode":"SS14 2HB",
    "sg:province":"Essex",
    "sg:tags":[
        "alteration"
    ],
    "wof:name":"Quality Klean",
    "wof:placetype":"venue"
},
  "geometry": {"coordinates":[0.474015,51.577702],"type":"Point"}
}