{
  "type": "Feature",
  "properties": {
    "iso:country":"GB",
    "sg:address":"2 St Stephens Hill",
    "sg:city":"Canterbury",
    "sg:classifiers":[
        {
            "category":"Professional",
            "subcategory":"Detective & Security Services",
            "type":"Services"
        }
    ],
    "sg:phone":"+44 1227 766744",
    "sg:postcode":"CT2 7AX",
    "sg:province":"Kent",
    "sg:tags":[
        "locksmith"
    ],
    "wof:name":"Canterbury Locksmiths",
    "wof:placetype":"venue"
},
  "geometry": {"coordinates":[1.080517,51.285805],"type":"Point"}
}