{
  "type": "Feature",
  "properties": {
    "addr:full":"702c Fulham Road London Greater London SW6 5SA",
    "addr:housenumber":"702c",
    "addr:postcode":"sw6 5sa",
    "addr:street":"Fulham Road",
    "iso:country":"GB",
    "sg:address":"702c Fulham Road",
    "sg:city":"London",
    "sg:classifiers":[
        {
            "category":"Food & Beverages",
            "subcategory":"Bakery",
            "type":"Retail Goods"
        }
    ],
    "sg:phone":"+44 20 7736 4090",
    "sg:postcode":"SW6 5SA",
    "sg:province":"Greater London",
    "sg:tags":[
        "baker"
    ],
    "wof:name":"Greggs",
    "wof:placetype":"venue"
},
  "geometry": {"coordinates":[-0.2069739997,51.4744148254],"type":"Point"}
}