{
  "type": "Feature",
  "properties": {
    "iso:country":"GB",
    "sg:address":"11-13 Sciennes House Place",
    "sg:city":"Edinburgh",
    "sg:classifiers":[
        {
            "category":"Shopping",
            "subcategory":"Stationery & Office Supplies",
            "type":"Retail Goods"
        }
    ],
    "sg:phone":"+44 131 667 7111",
    "sg:postcode":"EH9 1NN",
    "sg:province":"City of Edinburgh",
    "sg:tags":[
        "merchant",
        "paper"
    ],
    "wof:name":"Donald Murray (Paper) Ltd.",
    "wof:placetype":"venue"
},
  "geometry": {"coordinates":[-3.181477,55.937927],"type":"Point"}
}