{
  "type": "Feature",
  "properties": {
    "iso:country":"GB",
    "sg:address":"6 Dean Road",
    "sg:city":"South Shields",
    "sg:classifiers":[
        {
            "category":"Government",
            "subcategory":"Post Office",
            "type":"Public Place"
        }
    ],
    "sg:phone":"+44 191 456 0082",
    "sg:postcode":"NE33 3PT",
    "sg:province":"Tyne and Wear",
    "wof:name":"Westoe Post Office",
    "wof:placetype":"venue"
},
  "geometry": {"coordinates":[-1.4232499599,54.9874916077],"type":"Point"}
}