{
  "type": "Feature",
  "properties": {
    "iso:country":"GB",
    "sg:address":"166 Streatham Hill",
    "sg:city":"London",
    "sg:classifiers":[
        {
            "category":"Professional",
            "subcategory":"Accounting & Tax Preparation",
            "type":"Services"
        }
    ],
    "sg:phone":"+44 20 8671 9074",
    "sg:postcode":"SW2 4RU",
    "sg:province":"Greater London",
    "sg:tags":[
        "accountant"
    ],
    "wof:name":"Hardy & Co",
    "wof:placetype":"venue"
},
  "geometry": {"coordinates":[-0.126708,51.438801],"type":"Point"}
}