{
  "type": "Feature",
  "properties": {
    "addr:full":"3 Benson Court, Nelson Street Chepstow Gloucestershire NP16 5HT",
    "addr:housenumber":"3",
    "addr:postcode":"np16 5ht",
    "addr:street":"Benson Court Nelson Street",
    "iso:country":"GB",
    "sg:address":"3 Benson Court, Nelson Street",
    "sg:city":"Chepstow",
    "sg:classifiers":[
        {
            "category":"Manufacturing",
            "subcategory":"Wood Products",
            "type":"Manufacturing & Wholesale Goods"
        },
        {
            "category":"Home & Garden",
            "subcategory":"Building Materials",
            "type":"Retail Goods"
        }
    ],
    "sg:phone":"+44 1291 630382",
    "sg:postcode":"NP16 5HT",
    "sg:province":"Gloucestershire",
    "sg:tags":[
        "installers",
        "planner",
        "maker",
        "kitchen",
        "cabinet"
    ],
    "wof:name":"Kitchen Delight Ltd.",
    "wof:placetype":"venue"
},
  "geometry": {"coordinates":[-2.6798119545,51.637878418],"type":"Point"}
}