{
  "type": "Feature",
  "properties": {
    "addr:full":"2 Cambridge Road, Dunton Biggleswade Bedfordshire SG18 8RS",
    "addr:housenumber":"2",
    "addr:postcode":"sg18 8rs",
    "addr:street":"Cambridge Road",
    "iso:country":"GB",
    "sg:address":"2 Cambridge Road, Dunton",
    "sg:city":"Biggleswade",
    "sg:classifiers":[
        {
            "category":"Professional",
            "subcategory":"Management & Consulting",
            "type":"Services"
        }
    ],
    "sg:phone":"+44 1767 318600",
    "sg:postcode":"SG18 8RS",
    "sg:province":"Bedfordshire",
    "sg:tags":[
        "consultant",
        "training"
    ],
    "wof:name":"Buro Business Centre Ltd.",
    "wof:placetype":"venue"
},
  "geometry": {"coordinates":[-0.1954970062,52.0830764771],"type":"Point"}
}