{
  "type": "Feature",
  "properties": {
    "addr:full":"343 Archway Road London Greater London N6 5AA",
    "addr:housenumber":"343",
    "addr:postcode":"n6 5aa",
    "addr:street":"Archway Road",
    "iso:country":"GB",
    "sg:address":"343 Archway Road",
    "sg:city":"London",
    "sg:classifiers":[
        {
            "category":"Deli",
            "type":"Food & Drink"
        }
    ],
    "sg:phone":"+44 20 8340 8632",
    "sg:postcode":"N6 5AA",
    "sg:province":"Greater London",
    "sg:tags":[
        "delicatessen"
    ],
    "wof:name":"Gate Delicatessen",
    "wof:placetype":"venue"
},
  "geometry": {"coordinates":[-0.147066,51.577526],"type":"Point"}
}