{
  "type": "Feature",
  "properties": {
    "addr:full":"9 Lyttelton Rd, Edgbaston Birmingham West Midlands B16 9JN",
    "addr:housenumber":"9",
    "addr:postcode":"b16 9jn",
    "addr:street":"Lyttelton Rd",
    "iso:country":"GB",
    "sg:address":"9 Lyttelton Rd, Edgbaston",
    "sg:city":"Birmingham",
    "sg:classifiers":[
        {
            "category":"Place Of Worship",
            "type":"Public Place"
        }
    ],
    "sg:phone":"+44 121 454 8242",
    "sg:postcode":"B16 9JN",
    "sg:province":"West Midlands",
    "wof:name":"St. Augustines Church C of E",
    "wof:placetype":"venue"
},
  "geometry": {"coordinates":[-1.94525,52.473465],"type":"Point"}
}