{
  "type": "Feature",
  "properties": {
    "addr:full":"17 Macclesfield Road Wilmslow Cheshire SK9 2AA",
    "addr:housenumber":"17",
    "addr:postcode":"sk9 2aa",
    "addr:street":"Macclesfield Road",
    "iso:country":"GB",
    "sg:address":"17 Macclesfield Road",
    "sg:city":"Wilmslow",
    "sg:classifiers":[
        {
            "category":"Health Services",
            "subcategory":"Doctor",
            "type":"Services"
        }
    ],
    "sg:phone":"+44 1625 523292",
    "sg:postcode":"SK9 2AA",
    "sg:province":"Cheshire",
    "sg:tags":[
        "practitioners"
    ],
    "wof:name":"J R Bird",
    "wof:placetype":"venue"
},
  "geometry": {"coordinates":[-2.221965,53.325665],"type":"Point"}
}