{
  "type": "Feature",
  "properties": {
    "addr:full":"53 St Peter Street Tiverton Devon EX16 6NW",
    "addr:housenumber":"53",
    "addr:postcode":"ex16 6nw",
    "addr:street":"St Peter Street",
    "iso:country":"GB",
    "sg:address":"53 St Peter Street",
    "sg:city":"Tiverton",
    "sg:classifiers":[
        {
            "category":"Professional",
            "subcategory":"Lawyer & Legal Services",
            "type":"Services"
        }
    ],
    "sg:phone":"+44 1884 242091",
    "sg:postcode":"EX16 6NW",
    "sg:province":"Devon",
    "sg:tags":[
        "solicitor"
    ],
    "wof:name":"VEITCH PENNY SERVICES",
    "wof:placetype":"venue"
},
  "geometry": {"coordinates":[-3.4885621071,50.9048843384],"type":"Point"}
}