{
  "type": "Feature",
  "properties": {
    "addr:full":"8 Cocoa Yard, Pillory Street Nantwich Cheshire CW5 5BL",
    "addr:housenumber":"8",
    "addr:postcode":"cw5 5bl",
    "addr:street":"Cocoa Yard Pillory Street",
    "iso:country":"GB",
    "sg:address":"8 Cocoa Yard, Pillory Street",
    "sg:city":"Nantwich",
    "sg:classifiers":[
        {
            "category":"Shopping",
            "subcategory":"Antiques",
            "type":"Retail Goods"
        }
    ],
    "sg:postcode":"CW5 5BL",
    "sg:province":"Cheshire",
    "wof:name":"Barn Antiques",
    "wof:placetype":"venue"
},
  "geometry": {"coordinates":[-2.516502,53.065891],"type":"Point"}
}