{
  "type": "Feature",
  "properties": {
    "iso:country":"GB",
    "sg:address":"92 Epsom Road",
    "sg:city":"Sutton",
    "sg:classifiers":[
        {
            "category":"Health Services",
            "subcategory":"Dentist",
            "type":"Services"
        }
    ],
    "sg:phone":"+44 20 8337 1168",
    "sg:postcode":"SM3 9ES",
    "sg:province":"Surrey",
    "wof:name":"D & S Carr Dental Surgery",
    "wof:placetype":"venue"
},
  "geometry": {"coordinates":[-0.209483,51.387581],"type":"Point"}
}