{
  "type": "Feature",
  "properties": {
    "addr:full":"360 Kingston Road Epsom Surrey KT19 0DT",
    "addr:housenumber":"360",
    "addr:postcode":"kt19 0dt",
    "addr:street":"Kingston Road",
    "iso:country":"GB",
    "sg:address":"360 Kingston Road",
    "sg:city":"Epsom",
    "sg:classifiers":[
        {
            "category":"Shopping",
            "subcategory":"Clothing, Apparel, & Fashions",
            "type":"Retail Goods"
        }
    ],
    "sg:phone":"+44 20 8393 2626",
    "sg:postcode":"KT19 0DT",
    "sg:province":"Surrey",
    "sg:tags":[
        "shop",
        "dress",
        "fancy"
    ],
    "wof:name":"Masquerade",
    "wof:placetype":"venue"
},
  "geometry": {"coordinates":[-0.264617,51.368668],"type":"Point"}
}