{
  "type": "Feature",
  "properties": {
    "iso:country":"GB",
    "sg:address":"4 Falcon Yard",
    "sg:city":"Chesterfield",
    "sg:classifiers":[
        {
            "category":"Health Services",
            "subcategory":"Clinic",
            "type":"Services"
        }
    ],
    "sg:phone":"+44 1246 277323",
    "sg:postcode":"S40 1PF",
    "sg:province":"Derbyshire",
    "sg:tags":[
        "aromatherapy"
    ],
    "wof:name":"Rubber Duck Co The",
    "wof:placetype":"venue"
},
  "geometry": {"coordinates":[-1.4275000095,53.2348213196],"type":"Point"}
}