{
  "type": "Feature",
  "properties": {
    "iso:country":"GB",
    "sg:address":"138 Bellegrove Road",
    "sg:city":"Welling",
    "sg:classifiers":[
        {
            "category":"Restaurant",
            "type":"Food & Drink"
        }
    ],
    "sg:phone":"+44 20 8303 2121",
    "sg:postcode":"DA16 3QR",
    "sg:province":"Kent",
    "sg:tags":[
        "indian"
    ],
    "wof:name":"Bengal Brasserie",
    "wof:placetype":"venue"
},
  "geometry": {"coordinates":[0.0990620032,51.4639587402],"type":"Point"}
}