{
  "type": "Feature",
  "properties": {
    "addr:full":"35 Camperdown St Plymouth Devon PL2 1JQ",
    "addr:housenumber":"35",
    "addr:postcode":"pl2 1jq",
    "addr:street":"Camperdown St",
    "iso:country":"GB",
    "sg:address":"35 Camperdown St",
    "sg:city":"Plymouth",
    "sg:classifiers":[
        {
            "category":"Shopping",
            "subcategory":"News",
            "type":"Retail Goods"
        }
    ],
    "sg:postcode":"PL2 1JQ",
    "sg:province":"Devon",
    "sg:tags":[
        "newsagent"
    ],
    "wof:name":"Camperdown News",
    "wof:placetype":"venue"
},
  "geometry": {"coordinates":[-4.174826,50.382706],"type":"Point"}
}