{
  "type": "Feature",
  "properties": {
    "iso:country":"GB",
    "sg:address":"Unit 5c No 1 Indust Est, Medomsley Rd",
    "sg:city":"Consett",
    "sg:classifiers":[
        {
            "category":"Autos & Motor Vehicles",
            "subcategory":"Auto Supplies",
            "type":"Retail Goods"
        }
    ],
    "sg:phone":"+44 1207 502023",
    "sg:postcode":"DH8 6SY",
    "sg:province":"Durham",
    "sg:tags":[
        "component"
    ],
    "wof:name":"Brown Bros Group",
    "wof:placetype":"venue"
},
  "geometry": {"coordinates":[-1.8165129423,54.8831329346],"type":"Point"}
}