{
  "type": "Feature",
  "properties": {
    "addr:full":", Lucton Leominster Herefordshire HR6 9PN",
    "addr:postcode":"hr6 9pn",
    "addr:street":"Herefordshire",
    "iso:country":"GB",
    "sg:address":", Lucton",
    "sg:city":"Leominster",
    "sg:classifiers":[
        {
            "category":"Education",
            "subcategory":"School",
            "type":"Public Place"
        }
    ],
    "sg:phone":"+44 1568 780686",
    "sg:postcode":"HR6 9PN",
    "sg:province":"Herefordshire",
    "sg:tags":[
        "independent",
        "preparatory"
    ],
    "wof:name":"Lucton School",
    "wof:placetype":"venue"
},
  "geometry": {"coordinates":[-2.8305239677,52.2766609192],"type":"Point"}
}