{
  "type": "Feature",
  "properties": {
    "iso:country":"GB",
    "sg:address":"129 Alder Road",
    "sg:city":"Poole",
    "sg:classifiers":[
        {
            "category":"Place Of Worship",
            "type":"Public Place"
        }
    ],
    "sg:phone":"+44 1202 746938",
    "sg:postcode":"BH12 4AA",
    "sg:province":"Dorset",
    "sg:website":"http://www.arbc.org.uk",
    "wof:name":"Alder Road Baptist Church",
    "wof:placetype":"venue"
},
  "geometry": {"coordinates":[-1.920476,50.735004],"type":"Point"}
}