{
  "type": "Feature",
  "properties": {
    "addr:full":"220 Beckhampton Road Nottingham Nottinghamshire NG5 5PA",
    "addr:housenumber":"220",
    "addr:postcode":"ng5 5pa",
    "addr:street":"Beckhampton Road",
    "iso:country":"GB",
    "sg:address":"220 Beckhampton Road",
    "sg:city":"Nottingham",
    "sg:classifiers":[
        {
            "category":"Shopping",
            "subcategory":"Thrift Store",
            "type":"Retail Goods"
        }
    ],
    "sg:phone":"+44 115 967 1548",
    "sg:postcode":"NG5 5PA",
    "sg:province":"Nottinghamshire",
    "sg:tags":[
        "shop",
        "charity"
    ],
    "wof:name":"Hayward House Charity Shop",
    "wof:placetype":"venue"
},
  "geometry": {"coordinates":[-1.157724,53.002911],"type":"Point"}
}