{
  "type": "Feature",
  "properties": {
    "iso:country":"GB",
    "sg:address":"Whaley Farm, Mill Lane, New York",
    "sg:city":"Lincoln",
    "sg:classifiers":[
        {
            "category":"Farming",
            "subcategory":"Dairy Farm",
            "type":"Manufacturing & Wholesale Goods"
        }
    ],
    "sg:phone":"+44 1205 280329",
    "sg:postcode":"LN4 4XQ",
    "sg:province":"Lincolnshire",
    "sg:tags":[
        "farmer"
    ],
    "wof:name":"W & G Shaw",
    "wof:placetype":"venue"
},
  "geometry": {"coordinates":[-0.140104,53.078812],"type":"Point"}
}