{
  "type": "Feature",
  "properties": {
    "addr:full":"41 Queens Walk Peterborough Cambridgeshire PE2 9AN",
    "addr:housenumber":"41",
    "addr:postcode":"pe2 9an",
    "addr:street":"Queens Walk",
    "iso:country":"GB",
    "sg:address":"41 Queens Walk",
    "sg:city":"Peterborough",
    "sg:classifiers":[
        {
            "category":"Home & Garden",
            "subcategory":"Hardware",
            "type":"Retail Goods"
        }
    ],
    "sg:phone":"+44 1733 707008",
    "sg:postcode":"PE2 9AN",
    "sg:province":"Cambridgeshire",
    "sg:tags":[
        "equipment",
        "wire",
        "cable"
    ],
    "wof:name":"Fibretek",
    "wof:placetype":"venue"
},
  "geometry": {"coordinates":[-0.245047003,52.5629577637],"type":"Point"}
}