{
  "type": "Feature",
  "properties": {
    "iso:country":"GB",
    "sg:address":"37 Harpe Inge",
    "sg:city":"Huddersfield",
    "sg:classifiers":[
        {
            "category":"Food & Beverages",
            "subcategory":"Fruits & Vegetables",
            "type":"Retail Goods"
        }
    ],
    "sg:postcode":"HD5 9RD",
    "sg:province":"West Yorkshire",
    "sg:tags":[
        "greengrocer"
    ],
    "wof:name":"Fruit & Veg Corner",
    "wof:placetype":"venue"
},
  "geometry": {"coordinates":[-1.7542799711,53.6517677307],"type":"Point"}
}