{
  "type": "Feature",
  "properties": {
    "addr:full":"Counthorpe Grantham Leicestershire NG33 4QG",
    "addr:postcode":"ng33 4qg",
    "iso:country":"GB",
    "sg:address":"Counthorpe",
    "sg:city":"Grantham",
    "sg:classifiers":[
        {
            "category":"Home & Garden",
            "subcategory":"Garden Supply",
            "type":"Retail Goods"
        },
        {
            "category":"Manufacturing",
            "subcategory":"Glass & Minerals",
            "type":"Manufacturing & Wholesale Goods"
        }
    ],
    "sg:phone":"+44 1780 410933",
    "sg:postcode":"NG33 4QG",
    "sg:province":"Leicestershire",
    "sg:tags":[
        "chalk",
        "stone",
        "gravel",
        "slate",
        "sand"
    ],
    "wof:name":"Bardo (Midlands) Ltd.",
    "wof:placetype":"venue"
},
  "geometry": {"coordinates":[-0.5340570211,52.7597694397],"type":"Point"}
}