{
  "type": "Feature",
  "properties": {
    "addr:full":"Cross Street Chambers, Cross Street Wakefield West Yorkshire WF1 3BW",
    "addr:postcode":"wf1 3bw",
    "addr:street":"Cross;Cross Street",
    "iso:country":"GB",
    "sg:address":"Cross Street Chambers, Cross Street",
    "sg:city":"Wakefield",
    "sg:classifiers":[
        {
            "category":"Professional",
            "subcategory":"Accounting & Tax Preparation",
            "type":"Services"
        }
    ],
    "sg:phone":"+44 1924 372954",
    "sg:postcode":"WF1 3BW",
    "sg:province":"West Yorkshire",
    "sg:tags":[
        "accountant",
        "activity"
    ],
    "sg:website":"http://www.beaumonts.co.uk",
    "wof:name":"Beaumonts Chartered Accountants",
    "wof:placetype":"venue"
},
  "geometry": {"coordinates":[-1.499669,53.684013],"type":"Point"}
}