{
  "type": "Feature",
  "properties": {
    "iso:country":"GB",
    "sg:address":"Watton Road, Ashill",
    "sg:city":"Thetford",
    "sg:classifiers":[
        {
            "category":"Social Services",
            "subcategory":"Retirement Home",
            "type":"Services"
        }
    ],
    "sg:phone":"+44 1760 440433",
    "sg:postcode":"IP25 7AQ",
    "sg:province":"Norfolk",
    "sg:tags":[
        "residential",
        "care"
    ],
    "wof:name":"Lodge Care Home",
    "wof:placetype":"venue"
},
  "geometry": {"coordinates":[0.780673,52.602528],"type":"Point"}
}