{
  "type": "Feature",
  "properties": {
    "iso:country":"GB",
    "sg:address":"Burnley Road East",
    "sg:city":"Rossendale",
    "sg:classifiers":[
        {
            "category":"Place Of Worship",
            "type":"Public Place"
        }
    ],
    "sg:phone":"+44 1706 874841",
    "sg:postcode":"BB4 9NT",
    "sg:province":"Lancashire",
    "wof:name":"Whitewell Bottom Methodist Church",
    "wof:placetype":"venue"
},
  "geometry": {"coordinates":[-2.243809,53.725288],"type":"Point"}
}