{
  "type": "Feature",
  "properties": {
    "iso:country":"GB",
    "sg:address":"272-278 St. John St",
    "sg:city":"Clerkenwell",
    "sg:classifiers":[
        {
            "category":"Food & Beverages",
            "subcategory":"Supermarket",
            "type":"Retail Goods"
        }
    ],
    "sg:phone":"+44 20 7250 1694",
    "sg:postcode":"EC1V 4PD",
    "sg:province":"Greater London",
    "wof:name":"St John Supermarket",
    "wof:placetype":"venue"
},
  "geometry": {"coordinates":[-0.103888,51.526798],"type":"Point"}
}