{
  "type": "Feature",
  "properties": {
    "iso:country":"GB",
    "sg:address":"Granitehill Road",
    "sg:city":"Aberdeen",
    "sg:classifiers":[
        {
            "category":"Professional",
            "subcategory":"Business Services",
            "type":"Services"
        },
        {
            "category":"Government",
            "subcategory":"Office",
            "type":"Public Place"
        }
    ],
    "sg:postcode":"AB16 7AX",
    "sg:province":"Aberdeen City",
    "sg:tags":[
        "accomodation",
        "local"
    ],
    "wof:name":"Granitehill Enterprise Centre",
    "wof:placetype":"venue"
},
  "geometry": {"coordinates":[-2.1540689468,57.1681747437],"type":"Point"}
}