{
  "type": "Feature",
  "properties": {
    "iso:country":"GB",
    "sg:address":"Tenter Terr",
    "sg:city":"Durham",
    "sg:classifiers":[
        {
            "category":"Place Of Worship",
            "type":"Public Place"
        }
    ],
    "sg:phone":"+44 191 384 3117",
    "sg:postcode":"DH1 4RD",
    "sg:province":"Durham",
    "wof:name":"St Bede's R C Church",
    "wof:placetype":"venue"
},
  "geometry": {"coordinates":[-1.5814739466,54.777923584],"type":"Point"}
}