{
  "type": "Feature",
  "properties": {
    "addr:full":"160a Midland Road London Greater London E10 6JS",
    "addr:housenumber":"160a",
    "addr:postcode":"e10 6js",
    "addr:street":"Midland Road",
    "iso:country":"GB",
    "sg:address":"160a Midland Road",
    "sg:city":"London",
    "sg:classifiers":[
        {
            "category":"Retail",
            "subcategory":"Auto Repair",
            "type":"Services"
        }
    ],
    "sg:phone":"+44 20 8556 0544",
    "sg:postcode":"E10 6JS",
    "sg:province":"Greater London",
    "sg:tags":[
        "modification",
        "garage"
    ],
    "wof:name":"Station Vehicles",
    "wof:placetype":"venue"
},
  "geometry": {"coordinates":[-0.006199,51.56929],"type":"Point"}
}