{
  "type": "Feature",
  "properties": {
    "addr:full":"16 Elliot Street, Elliots Town New Tredegar Caerphilly NP24 6DP",
    "addr:housenumber":"16",
    "addr:postcode":"np24 6dp",
    "addr:street":"Elliot Street",
    "iso:country":"GB",
    "sg:address":"16 Elliot Street, Elliots Town",
    "sg:city":"New Tredegar",
    "sg:classifiers":[
        {
            "category":"Shopping",
            "subcategory":"Department Store",
            "type":"Retail Goods"
        }
    ],
    "sg:phone":"+44 1443 837493",
    "sg:postcode":"NP24 6DP",
    "sg:province":"Caerphilly",
    "wof:name":"New Tredegar General Stores",
    "wof:placetype":"venue"
},
  "geometry": {"coordinates":[-3.2377490997,51.7186431885],"type":"Point"}
}