{
  "type": "Feature",
  "properties": {
    "addr:full":"The County Ground, Riverside Chester-le-street Durham DH3 3QR",
    "addr:postcode":"dh3 3qr",
    "addr:street":"Chester-Le-Street",
    "iso:country":"GB",
    "sg:address":"The County Ground, Riverside",
    "sg:city":"Chester-le-street",
    "sg:classifiers":[
        {
            "category":"Arena",
            "subcategory":"Sports Club",
            "type":"Entertainment"
        }
    ],
    "sg:phone":"+44 191 387 1717",
    "sg:postcode":"DH3 3QR",
    "sg:province":"Durham",
    "wof:name":"Durham County Cricket Club",
    "wof:placetype":"venue"
},
  "geometry": {"coordinates":[-1.5621900558,54.84897995],"type":"Point"}
}