{
  "type": "Feature",
  "properties": {
    "addr:full":"1-2 Swanside Parade Liverpool Merseyside L14 7QH",
    "addr:housenumber":"1-2",
    "addr:postcode":"l14 7qh",
    "addr:street":"Swanside Parade",
    "iso:country":"GB",
    "sg:address":"1-2 Swanside Parade",
    "sg:city":"Liverpool",
    "sg:classifiers":[
        {
            "category":"Health Services",
            "subcategory":"Dentist",
            "type":"Services"
        }
    ],
    "sg:phone":"+44 151 220 0360",
    "sg:postcode":"L14 7QH",
    "sg:province":"Merseyside",
    "wof:name":"Mr Chan",
    "wof:placetype":"venue"
},
  "geometry": {"coordinates":[-2.880744,53.415874],"type":"Point"}
}