{
  "type": "Feature",
  "properties": {
    "addr:full":"Capel Hendre Industrial Estate Ammanford Carmarthenshire SA18 3SJ",
    "addr:postcode":"sa18 3sj",
    "addr:street":"Industrial Estate",
    "iso:country":"GB",
    "sg:address":"Capel Hendre Industrial Estate",
    "sg:city":"Ammanford",
    "sg:classifiers":[
        {
            "category":"Ice Cream",
            "type":"Food & Drink"
        }
    ],
    "sg:phone":"+44 1269 832400",
    "sg:postcode":"SA18 3SJ",
    "sg:province":"Carmarthenshire",
    "sg:tags":[
        "mnfr"
    ],
    "wof:name":"Franks Ice Cream Ltd.",
    "wof:placetype":"venue"
},
  "geometry": {"coordinates":[-3.988945,51.792397],"type":"Point"}
}