{
  "type": "Feature",
  "properties": {
    "addr:full":"29 Corporation Street Birmingham West Midlands B2 4LS",
    "addr:housenumber":"29",
    "addr:postcode":"b2 4ls",
    "addr:street":"Corporation Street",
    "iso:country":"GB",
    "sg:address":"29 Corporation Street",
    "sg:city":"Birmingham",
    "sg:classifiers":[
        {
            "category":"Shopping",
            "subcategory":"Department Store",
            "type":"Retail Goods"
        }
    ],
    "sg:postcode":"B2 4LS",
    "sg:province":"West Midlands",
    "wof:name":"Roberts",
    "wof:placetype":"venue"
},
  "geometry": {"coordinates":[-1.8973380327,52.4798202515],"type":"Point"}
}