{
  "type": "Feature",
  "properties": {
    "iso:country":"GB",
    "sg:address":"Turners Hill Chamber, 1 Albury Grove Road, Cheshunt",
    "sg:city":"Waltham Cross",
    "sg:classifiers":[
        {
            "category":"Professional",
            "subcategory":"Lawyer & Legal Services",
            "type":"Services"
        }
    ],
    "sg:postcode":"EN8 8XR",
    "sg:province":"Essex",
    "sg:tags":[
        "solicitor"
    ],
    "wof:name":"Breeze & Wyles",
    "wof:placetype":"venue"
},
  "geometry": {"coordinates":[-0.0345190018,51.7013549805],"type":"Point"}
}