{
  "type": "Feature",
  "properties": {
    "iso:country":"GB",
    "sg:address":"Valley Road, Bilson",
    "sg:city":"Cinderford",
    "sg:classifiers":[
        {
            "category":"Social Services",
            "subcategory":"Adult Care",
            "type":"Services"
        },
        {
            "category":"Government",
            "subcategory":"Office",
            "type":"Public Place"
        }
    ],
    "sg:phone":"+44 1594 825484",
    "sg:postcode":"GL14 2LJ",
    "sg:province":"Gloucestershire",
    "sg:tags":[
        "local",
        "day",
        "centre"
    ],
    "wof:name":"Foxes Bridge Day Centre",
    "wof:placetype":"venue"
},
  "geometry": {"coordinates":[-2.5060329437,51.8296127319],"type":"Point"}
}