{
  "type": "Feature",
  "properties": {
    "addr:full":"303 Tong Street Bradford West Yorkshire BD4 9QS",
    "addr:housenumber":"303",
    "addr:postcode":"bd4 9qs",
    "addr:street":"Tong Street",
    "iso:country":"GB",
    "sg:address":"303 Tong Street",
    "sg:city":"Bradford",
    "sg:classifiers":[
        {
            "category":"Shopping",
            "subcategory":"Pharmacy",
            "type":"Retail Goods"
        }
    ],
    "sg:phone":"+44 1274 681320",
    "sg:postcode":"BD4 9QS",
    "sg:province":"West Yorkshire",
    "sg:tags":[
        "pharmacist",
        "chemist"
    ],
    "wof:name":"W H Chanter Ltd.",
    "wof:placetype":"venue"
},
  "geometry": {"coordinates":[-1.7153609991,53.7694206238],"type":"Point"}
}