{
  "type": "Feature",
  "properties": {
    "iso:country":"GB",
    "sg:address":"4 Jasper Close, Barlaston",
    "sg:city":"Stoke-on-trent",
    "sg:classifiers":[
        {
            "category":"Building & Trades",
            "subcategory":"Cleaning & Sanitation",
            "type":"Services"
        }
    ],
    "sg:phone":"+44 1782 373033",
    "sg:postcode":"ST12 9BL",
    "sg:province":"Staffordshire",
    "sg:tags":[
        "commercial"
    ],
    "wof:name":"Cleanex Contract Services",
    "wof:placetype":"venue"
},
  "geometry": {"coordinates":[-2.157354,52.957142],"type":"Point"}
}