{
  "type": "Feature",
  "properties": {
    "addr:full":"Flat 2, 178 Horn Lane North Acton London Greater London W3 7PJ",
    "addr:housenumber":"178",
    "addr:postcode":"w3 7pj",
    "addr:street":"Horn Lane",
    "iso:country":"GB",
    "sg:address":"Flat 2, 178 Horn Lane North Acton",
    "sg:city":"London",
    "sg:classifiers":[
        {
            "category":"Professional",
            "subcategory":"Management & Consulting",
            "type":"Services"
        }
    ],
    "sg:postcode":"W3 7PJ",
    "sg:province":"Greater London",
    "sg:tags":[
        "consultant",
        "business"
    ],
    "wof:name":"S.L.H. Consultancy Services Ltd",
    "wof:placetype":"venue"
},
  "geometry": {"coordinates":[-0.2569,51.517471],"type":"Point"}
}