{
  "type": "Feature",
  "properties": {
    "addr:full":"51 Merthyr Ave, Drayton Portsmouth Hampshire PO6 2AR",
    "addr:housenumber":"51",
    "addr:postcode":"hampshire po6 2ar",
    "addr:street":"Merthyr Ave",
    "iso:country":"GB",
    "sg:address":"51 Merthyr Ave, Drayton",
    "sg:city":"Portsmouth",
    "sg:classifiers":[
        {
            "category":"Professional",
            "subcategory":"Advertising",
            "type":"Services"
        }
    ],
    "sg:postcode":"PO6 2AR",
    "sg:province":"Hampshire",
    "sg:tags":[
        "medium"
    ],
    "wof:name":"Modular Media Ltd",
    "wof:placetype":"venue"
},
  "geometry": {"coordinates":[-1.0516519547,50.8502616882],"type":"Point"}
}