{
  "type": "Feature",
  "properties": {
    "addr:full":"Stoneferry Road Hull East Riding of Yorkshire HU8 8DE",
    "addr:postcode":"hu8 8de",
    "addr:street":"Stoneferry Road",
    "iso:country":"GB",
    "sg:address":"Stoneferry Road",
    "sg:city":"Hull",
    "sg:classifiers":[
        {
            "category":"Professional",
            "subcategory":"Testing Lab",
            "type":"Services"
        },
        {
            "category":"Autos & Motor Vehicles",
            "subcategory":"Auto Supplies",
            "type":"Retail Goods"
        },
        {
            "category":"Autos & Motor Vehicles",
            "subcategory":"Motorcycle Sales",
            "type":"Retail Goods"
        }
    ],
    "sg:phone":"+44 1482 327615",
    "sg:postcode":"HU8 8DE",
    "sg:province":"East Riding of Yorkshire",
    "sg:tags":[
        "towing",
        "trailer",
        "eqpt",
        "mot"
    ],
    "wof:name":"Micks Motorcycles",
    "wof:placetype":"venue"
},
  "geometry": {"coordinates":[-0.3282690048,53.7623291016],"type":"Point"}
}