{
  "type": "Feature",
  "properties": {
    "addr:full":"302 Oxgangs Road North Edinburgh City of Edinburgh EH13 9ND",
    "addr:housenumber":"302",
    "addr:postcode":"eh13 9nd",
    "addr:street":"Oxgangs Road North Edinburgh",
    "iso:country":"GB",
    "sg:address":"302 Oxgangs Road North",
    "sg:city":"Edinburgh",
    "sg:classifiers":[
        {
            "category":"Health Services",
            "subcategory":"Dentist",
            "type":"Services"
        }
    ],
    "sg:phone":"+44 131 441 3231",
    "sg:postcode":"EH13 9ND",
    "sg:province":"City of Edinburgh",
    "sg:tags":[
        "technician",
        "dental"
    ],
    "wof:name":"Dental Surgery",
    "wof:placetype":"venue"
},
  "geometry": {"coordinates":[-3.226521,55.906967],"type":"Point"}
}