{
  "type": "Feature",
  "properties": {
    "addr:full":"30 Ivinghoe Rd, Bushey Watford Hertfordshire WD2 3SW",
    "addr:housenumber":"30",
    "addr:postcode":"wd2 3sw",
    "addr:street":"Ivinghoe Rd",
    "iso:country":"GB",
    "sg:address":"30 Ivinghoe Rd, Bushey",
    "sg:city":"Watford",
    "sg:classifiers":[
        {
            "category":"Manufacturing",
            "subcategory":"Metals",
            "type":"Manufacturing & Wholesale Goods"
        }
    ],
    "sg:phone":"+44 20 8950 0499",
    "sg:postcode":"WD2 3SW",
    "sg:province":"Hertfordshire",
    "sg:tags":[
        "die-casting"
    ],
    "wof:name":"Galvanoform",
    "wof:placetype":"venue"
},
  "geometry": {"coordinates":[-0.36307,51.644341],"type":"Point"}
}