{
  "type": "Feature",
  "properties": {
    "addr:full":"863 Forest Road Walthamstow Greater London E17 4AT",
    "addr:housenumber":"863",
    "addr:postcode":"e17 4at",
    "addr:street":"Forest Road",
    "iso:country":"GB",
    "sg:address":"863 Forest Road",
    "sg:city":"Walthamstow",
    "sg:classifiers":[
        {
            "category":"Food & Beverages",
            "subcategory":"Fruits & Vegetables",
            "type":"Retail Goods"
        }
    ],
    "sg:phone":"+44 20 8531 2191",
    "sg:postcode":"E17 4AT",
    "sg:province":"Greater London",
    "sg:tags":[
        "greengrocer"
    ],
    "wof:name":"Linkup Enterprise",
    "wof:placetype":"venue"
},
  "geometry": {"coordinates":[-0.0052009998,51.5917053223],"type":"Point"}
}