{
  "type": "Feature",
  "properties": {
    "iso:country":"GB",
    "sg:address":"285 East Bawtry Rd",
    "sg:city":"Rotherham",
    "sg:classifiers":[
        {
            "category":"Bars & Pubs",
            "type":"Food & Drink"
        }
    ],
    "sg:phone":"+44 1709 704350",
    "sg:postcode":"S60 4EP",
    "sg:province":"South Yorkshire",
    "sg:tags":[
        "pubs",
        "inn"
    ],
    "wof:name":"Hind The",
    "wof:placetype":"venue"
},
  "geometry": {"coordinates":[-1.3239300251,53.4120178223],"type":"Point"}
}