{
  "type": "Feature",
  "properties": {
    "addr:full":"30 Sherburn Rd, Gresgate Durham Durham DH1 2UR",
    "addr:housenumber":"30",
    "addr:postcode":"dh1 2ur",
    "addr:street":"Sherburn Rd Gresgate",
    "iso:country":"GB",
    "sg:address":"30 Sherburn Rd, Gresgate",
    "sg:city":"Durham",
    "sg:classifiers":[
        {
            "category":"Farming",
            "subcategory":"Dairy Farm",
            "type":"Manufacturing & Wholesale Goods"
        }
    ],
    "sg:postcode":"DH1 2UR",
    "sg:province":"Durham",
    "wof:name":"Tindle,Peter,",
    "wof:placetype":"venue"
},
  "geometry": {"coordinates":[-1.5547150373,54.7787704468],"type":"Point"}
}