{
  "type": "Feature",
  "properties": {
    "addr:full":"141 South Street, Pondersend Enfield Greater London EN3 4PX",
    "addr:housenumber":"141",
    "addr:postcode":"en3 4px",
    "addr:street":"South Street Pondersend",
    "iso:country":"GB",
    "sg:address":"141 South Street, Pondersend",
    "sg:city":"Enfield",
    "sg:classifiers":[
        {
            "category":"Organizations",
            "subcategory":"Non-profit Organization",
            "type":"Services"
        }
    ],
    "sg:phone":"+44 20 8805 8712",
    "sg:postcode":"EN3 4PX",
    "sg:province":"Greater London",
    "sg:tags":[
        "organisation",
        "voluntary",
        "charity"
    ],
    "wof:name":"Welcome Point Community Centre",
    "wof:placetype":"venue"
},
  "geometry": {"coordinates":[-0.037747,51.642597],"type":"Point"}
}