{
  "type": "Feature",
  "properties": {
    "iso:country":"GB",
    "sg:address":"33 Greenway",
    "sg:city":"Wirral",
    "sg:classifiers":[
        {
            "category":"Retail",
            "subcategory":"Driving School",
            "type":"Services"
        }
    ],
    "sg:phone":"+44 151 677 8785",
    "sg:postcode":"CH49 2NN",
    "sg:province":"Merseyside",
    "wof:name":"Hallmark LGV PCV Training",
    "wof:placetype":"venue"
},
  "geometry": {"coordinates":[-3.112082,53.384224],"type":"Point"}
}