{
  "type": "Feature",
  "properties": {
    "iso:country":"GB",
    "sg:address":"15 Lordship Lane",
    "sg:city":"London",
    "sg:classifiers":[
        {
            "category":"Shopping",
            "subcategory":"Used Merchandise",
            "type":"Retail Goods"
        }
    ],
    "sg:postcode":"SE22 8EW",
    "sg:province":"Greater London",
    "sg:tags":[
        "shop",
        "second-hand"
    ],
    "wof:name":"C & G's Bargain Shop",
    "wof:placetype":"venue"
},
  "geometry": {"coordinates":[-0.075011,51.460136],"type":"Point"}
}