{
  "type": "Feature",
  "properties": {
    "iso:country":"GB",
    "sg:address":"29 Summit Avenue, Kingsbury",
    "sg:city":"London",
    "sg:classifiers":[
        {
            "category":"Building & Trades",
            "subcategory":"Construction",
            "type":"Services"
        }
    ],
    "sg:phone":"+44 20 8205 2784",
    "sg:postcode":"NW9 0TH",
    "sg:province":"Greater London",
    "sg:tags":[
        "builder"
    ],
    "wof:name":"Regal Construction 2000 Ltd.",
    "wof:placetype":"venue"
},
  "geometry": {"coordinates":[-0.2576889992,51.5846633911],"type":"Point"}
}