{
  "type": "Feature",
  "properties": {
    "iso:country":"GB",
    "sg:address":"9 Parkside Industrial Estate",
    "sg:city":"Ringwood",
    "sg:classifiers":[
        {
            "category":"Professional",
            "subcategory":"Engineering",
            "type":"Services"
        }
    ],
    "sg:phone":"+44 1425 479177",
    "sg:postcode":"BH24 3SG",
    "sg:province":"Dorset",
    "wof:name":"K & T (Engineers) Ltd.",
    "wof:placetype":"venue"
},
  "geometry": {"coordinates":[-1.792989,50.846329],"type":"Point"}
}