{
  "type": "Feature",
  "properties": {
    "addr:full":"52 High Street Street Somerset BA16 0EQ",
    "addr:housenumber":"52",
    "addr:postcode":"ba16 0eq",
    "addr:street":"High Street Street",
    "iso:country":"GB",
    "sg:address":"52 High Street",
    "sg:city":"Street",
    "sg:classifiers":[
        {
            "category":"Shopping",
            "subcategory":"Clothing, Apparel, & Fashions",
            "type":"Retail Goods"
        }
    ],
    "sg:postcode":"BA16 0EQ",
    "sg:province":"Somerset",
    "sg:tags":[
        "shop"
    ],
    "wof:name":"White & Son",
    "wof:placetype":"venue"
},
  "geometry": {"coordinates":[-2.739008,51.127522],"type":"Point"}
}