{
  "type": "Feature",
  "properties": {
    "addr:full":"Percy Road London Greater London W1Y 4BE",
    "addr:postcode":"w1y 4be",
    "addr:street":"Percy Road",
    "iso:country":"GB",
    "sg:address":"Percy Road",
    "sg:city":"London",
    "sg:classifiers":[
        {
            "category":"Parking",
            "type":"Transportation"
        }
    ],
    "sg:phone":"+44 20 7409 1749",
    "sg:postcode":"W1Y 4BE",
    "sg:province":"Greater London",
    "sg:tags":[
        "car",
        "park"
    ],
    "wof:name":"National Car Parks Ltd.",
    "wof:placetype":"venue"
},
  "geometry": {"coordinates":[-0.196401,51.5311164856],"type":"Point"}
}