{
  "type": "Feature",
  "properties": {
    "iso:country":"GB",
    "sg:address":"Hall Lane, Appley Bridge",
    "sg:city":"Wigan",
    "sg:classifiers":[
        {
            "category":"Health Services",
            "subcategory":"Hospital",
            "type":"Services"
        }
    ],
    "sg:phone":"+44 1257 252211",
    "sg:postcode":"WN6 9EP",
    "sg:province":"Lancashire",
    "wof:name":"Wrightington Hospital N H S Trust",
    "wof:placetype":"venue"
},
  "geometry": {"coordinates":[-2.7122879028,53.5913658142],"type":"Point"}
}