{
  "type": "Feature",
  "properties": {
    "iso:country":"GB",
    "sg:address":"Elizabeth Court, Milmans Street",
    "sg:city":"London",
    "sg:classifiers":[
        {
            "category":"Organizations",
            "subcategory":"Community Association",
            "type":"Services"
        }
    ],
    "sg:phone":"+44 20 7351 2419",
    "sg:postcode":"SW10 0DA",
    "sg:province":"Greater London",
    "sg:tags":[
        "associations",
        "housing",
        "co-operatives",
        "society",
        "trust",
        "societies"
    ],
    "wof:name":"Anchor Trust",
    "wof:placetype":"venue"
},
  "geometry": {"coordinates":[-0.17535,51.482651],"type":"Point"}
}