{
  "type": "Feature",
  "properties": {
    "addr:full":"Elsenham Road Stansted Essex CM24 8ST",
    "addr:postcode":"cm24 8st",
    "addr:street":"Elsenham Road",
    "iso:country":"GB",
    "sg:address":"Elsenham Road",
    "sg:city":"Stansted",
    "sg:classifiers":[
        {
            "category":"Shopping",
            "subcategory":"Crafts & Fabrics",
            "type":"Retail Goods"
        }
    ],
    "sg:phone":"+44 1279 817226",
    "sg:postcode":"CM24 8ST",
    "sg:province":"Essex",
    "sg:tags":[
        "ceramic"
    ],
    "wof:name":"Down to Earth Ceramics Ltd.",
    "wof:placetype":"venue"
},
  "geometry": {"coordinates":[0.21664,51.906712],"type":"Point"}
}