{
  "type": "Feature",
  "properties": {
    "iso:country":"GB",
    "sg:address":"Silver Street",
    "sg:city":"Wellingborough",
    "sg:classifiers":[
        {
            "category":"Bars & Pubs",
            "type":"Food & Drink"
        }
    ],
    "sg:phone":"+44 1933 273892",
    "sg:postcode":"NN8 1AY",
    "sg:province":"Northamptonshire",
    "sg:tags":[
        "pubs",
        "inn"
    ],
    "wof:name":"The Old Swan",
    "wof:placetype":"venue"
},
  "geometry": {"coordinates":[-0.695209,52.301575],"type":"Point"}
}