{
  "type": "Feature",
  "properties": {
    "addr:full":"Unit 15g Elscar Project Centre, Wath Rd, Elsecar Barnsley South Yorkshire S74 8HJ",
    "addr:housenumber":"unit 15g",
    "addr:postcode":"s74 8hj",
    "addr:street":"Wath Rd;Yorkshire",
    "iso:country":"GB",
    "sg:address":"Unit 15g Elscar Project Centre, Wath Rd, Elsecar",
    "sg:city":"Barnsley",
    "sg:classifiers":[
        {
            "category":"Shopping",
            "subcategory":"Gifts & Souvenirs",
            "type":"Retail Goods"
        }
    ],
    "sg:postcode":"S74 8HJ",
    "sg:province":"South Yorkshire",
    "sg:tags":[
        "giftware"
    ],
    "wof:name":"House of Wentworth",
    "wof:placetype":"venue"
},
  "geometry": {"coordinates":[-1.4186500311,53.4962348938],"type":"Point"}
}