{
  "type": "Feature",
  "properties": {
    "addr:full":"39 Longbridge Close, New Mill Tring Buckinghamshire HP23 5HG",
    "addr:housenumber":"39",
    "addr:postcode":"hp23 5hg",
    "addr:street":"Longbridge Close New Mill",
    "iso:country":"GB",
    "sg:address":"39 Longbridge Close, New Mill",
    "sg:city":"Tring",
    "sg:classifiers":[
        {
            "category":"Social Services",
            "subcategory":"Adult Care",
            "type":"Services"
        }
    ],
    "sg:phone":"+44 1442 827184",
    "sg:postcode":"HP23 5HG",
    "sg:province":"Buckinghamshire",
    "sg:tags":[
        "domestic",
        "cleaning"
    ],
    "wof:name":"Home Shine",
    "wof:placetype":"venue"
},
  "geometry": {"coordinates":[-0.6606659889,51.8063430786],"type":"Point"}
}