{
  "type": "Feature",
  "properties": {
    "iso:country":"GB",
    "sg:address":"Eastcott, Crackington Haven",
    "sg:city":"Bude",
    "sg:classifiers":[
        {
            "category":"Home & Garden",
            "subcategory":"Garden Supply",
            "type":"Retail Goods"
        }
    ],
    "sg:phone":"+44 1840 230308",
    "sg:postcode":"EX23 0JN",
    "sg:province":"Cornwall",
    "sg:tags":[
        "ornament"
    ],
    "wof:name":"N.J Pickard",
    "wof:placetype":"venue"
},
  "geometry": {"coordinates":[-4.632869,50.741505],"type":"Point"}
}