{
  "type": "Feature",
  "properties": {
    "addr:full":"Knighton Fields Rd West Leicester Leicestershire LE2 6LG",
    "addr:postcode":"le2 6lg",
    "addr:street":"Fields Rd",
    "iso:country":"GB",
    "sg:address":"Knighton Fields Rd West",
    "sg:city":"Leicester",
    "sg:classifiers":[
        {
            "category":"Autos & Motor Vehicles",
            "subcategory":"Boat Sales",
            "type":"Retail Goods"
        }
    ],
    "sg:phone":"+44 116 283 0659",
    "sg:postcode":"LE2 6LG",
    "sg:province":"Leicestershire",
    "sg:tags":[
        "repair",
        "builder"
    ],
    "wof:name":"Mobile Adventure Ltd",
    "wof:placetype":"venue"
},
  "geometry": {"coordinates":[-1.1327140331,52.6116142273],"type":"Point"}
}