{
  "type": "Feature",
  "properties": {
    "addr:full":"Belceto Andover Road, Highclere Newbury Berkshire RG20 9QX",
    "addr:postcode":"rg20 9qx",
    "addr:street":"Andover Road",
    "iso:country":"GB",
    "sg:address":"Belceto Andover Road, Highclere",
    "sg:city":"Newbury",
    "sg:classifiers":[
        {
            "category":"Professional",
            "subcategory":"Art Services",
            "type":"Services"
        }
    ],
    "sg:phone":"+44 1635 254492",
    "sg:postcode":"RG20 9QX",
    "sg:province":"Berkshire",
    "sg:tags":[
        "photographer"
    ],
    "wof:name":"Paddock Studios",
    "wof:placetype":"venue"
},
  "geometry": {"coordinates":[-1.3719539642,51.3449363708],"type":"Point"}
}