{
  "type": "Feature",
  "properties": {
    "addr:full":"145-147 East Barnet Road Barnet Hertfordshire EN4 8QZ",
    "addr:housenumber":"145-147",
    "addr:postcode":"en4 8qz",
    "addr:street":"East Barnet Road",
    "iso:country":"GB",
    "sg:address":"145-147 East Barnet Road",
    "sg:city":"Barnet",
    "sg:classifiers":[
        {
            "category":"Shopping",
            "subcategory":"Pharmacy",
            "type":"Retail Goods"
        }
    ],
    "sg:phone":"+44 20 8440 4430",
    "sg:postcode":"EN4 8QZ",
    "sg:province":"Hertfordshire",
    "sg:tags":[
        "pharmacist",
        "chemist"
    ],
    "wof:name":"S V R Chemist",
    "wof:placetype":"venue"
},
  "geometry": {"coordinates":[-0.167044,51.647057],"type":"Point"}
}