{
  "type": "Feature",
  "properties": {
    "iso:country":"GB",
    "sg:address":"42 Upper Bond Street",
    "sg:city":"Hinckley",
    "sg:classifiers":[
        {
            "category":"Shopping",
            "subcategory":"Florist",
            "type":"Retail Goods"
        }
    ],
    "sg:phone":"+44 1455 634823",
    "sg:postcode":"LE10 1RJ",
    "sg:province":"Leicestershire",
    "wof:name":"Jilly Flowers",
    "wof:placetype":"venue"
},
  "geometry": {"coordinates":[-1.371564,52.54649],"type":"Point"}
}