{
  "type": "Feature",
  "properties": {
    "iso:country":"GB",
    "sg:address":"West View",
    "sg:city":"Letchworth",
    "sg:classifiers":[
        {
            "category":"Place Of Worship",
            "type":"Public Place"
        }
    ],
    "sg:phone":"+44 1462 482780",
    "sg:postcode":"SG6 3RQ",
    "sg:province":"Hertfordshire",
    "wof:name":"Letchworth baptist Church",
    "wof:placetype":"venue"
},
  "geometry": {"coordinates":[-0.233032,51.97501],"type":"Point"}
}