{
  "type": "Feature",
  "properties": {
    "addr:full":"34b High Street, Starbeck Harrogate North Yorkshire HG2 7JE",
    "addr:housenumber":"34b",
    "addr:postcode":"hg2 7je",
    "addr:street":"High Street",
    "iso:country":"GB",
    "sg:address":"34b High Street, Starbeck",
    "sg:city":"Harrogate",
    "sg:classifiers":[
        {
            "category":"Health Services",
            "subcategory":"Clinic",
            "type":"Services"
        }
    ],
    "sg:phone":"+44 1423 540530",
    "sg:postcode":"HG2 7JE",
    "sg:province":"North Yorkshire",
    "sg:tags":[
        "aromatherapy"
    ],
    "wof:name":"Beauty by Zoe",
    "wof:placetype":"venue"
},
  "geometry": {"coordinates":[-1.4994479418,53.9986038208],"type":"Point"}
}