{
  "type": "Feature",
  "properties": {
    "addr:full":"18th Floor, St Alphage House, 2 Fore Street London Greater London EC2Y 5DA",
    "addr:housenumber":"2",
    "addr:postcode":"ec2y 5da",
    "addr:street":"Floor St;Fore Street",
    "iso:country":"GB",
    "sg:address":"18th Floor, St Alphage House, 2 Fore Street",
    "sg:city":"London",
    "sg:classifiers":[
        {
            "category":"Manufacturing",
            "subcategory":"Tools & Machinery",
            "type":"Manufacturing & Wholesale Goods"
        }
    ],
    "sg:phone":"+44 20 7663 5642",
    "sg:postcode":"EC2Y 5DA",
    "sg:province":"Greater London",
    "sg:tags":[
        "society",
        "friendly"
    ],
    "wof:name":"Woodgate & Clark Ltd.",
    "wof:placetype":"venue"
},
  "geometry": {"coordinates":[-0.091664,51.51804],"type":"Point"}
}