{
  "type": "Feature",
  "properties": {
    "addr:full":"The Square Gosport Hampshire PO12 4LH",
    "addr:postcode":"po12 4lh",
    "addr:street":"The Square",
    "iso:country":"GB",
    "sg:address":"The Square",
    "sg:city":"Gosport",
    "sg:classifiers":[
        {
            "category":"Home & Garden",
            "subcategory":"Home Furnishings",
            "type":"Retail Goods"
        }
    ],
    "sg:phone":"+44 23 9236 1223",
    "sg:postcode":"PO12 4LH",
    "sg:province":"Hampshire",
    "sg:tags":[
        "homefurnishings"
    ],
    "wof:name":"Unit 4 Small Works",
    "wof:placetype":"venue"
},
  "geometry": {"coordinates":[-1.135124,50.812729],"type":"Point"}
}