{
  "type": "Feature",
  "properties": {
    "iso:country":"GB",
    "sg:address":"B2 Stadium Court, Skippers Lane Industrial Estate",
    "sg:city":"Middlesbrough",
    "sg:classifiers":[
        {
            "category":"Professional",
            "subcategory":"Printing & Photocopies",
            "type":"Services"
        }
    ],
    "sg:phone":"+44 1642 462926",
    "sg:postcode":"TS6 6JB",
    "sg:province":"North Yorkshire",
    "sg:tags":[
        "screen",
        "printer"
    ],
    "wof:name":"Steel River Textiles",
    "wof:placetype":"venue"
},
  "geometry": {"coordinates":[-1.18155,54.572269],"type":"Point"}
}