{
  "type": "Feature",
  "properties": {
    "addr:full":"55 Fleckney Road, Kibworth Leicester Leicestershire LE8 0HH",
    "addr:housenumber":"55",
    "addr:postcode":"le8 0hh",
    "addr:street":"Fleckney Road",
    "iso:country":"GB",
    "sg:address":"55 Fleckney Road, Kibworth",
    "sg:city":"Leicester",
    "sg:classifiers":[
        {
            "category":"Professional",
            "subcategory":"Art Services",
            "type":"Services"
        },
        {
            "category":"Building & Trades",
            "subcategory":"Construction",
            "type":"Services"
        }
    ],
    "sg:phone":"+44 116 279 2236",
    "sg:postcode":"LE8 0HH",
    "sg:province":"Leicestershire",
    "sg:tags":[
        "decorator",
        "painter"
    ],
    "wof:name":"C D Simons & Son",
    "wof:placetype":"venue"
},
  "geometry": {"coordinates":[-1.004032,52.536877],"type":"Point"}
}