{
  "type": "Feature",
  "properties": {
    "addr:full":"265-267 Seabank Rd Wallasey Merseyside L45 1HE",
    "addr:postcode":"265-267;l45 1he",
    "addr:street":"Seabank Rd",
    "iso:country":"GB",
    "sg:address":"265-267 Seabank Rd",
    "sg:city":"Wallasey",
    "sg:classifiers":[
        {
            "category":"Shopping",
            "subcategory":"Department Store",
            "type":"Retail Goods"
        }
    ],
    "sg:phone":"+44 151 691 1114",
    "sg:postcode":"L45 1HE",
    "sg:province":"Merseyside",
    "wof:name":"Best Buy Food & Drink Store",
    "wof:placetype":"venue"
},
  "geometry": {"coordinates":[-3.0403730869,53.4323768616],"type":"Point"}
}