{
  "type": "Feature",
  "properties": {
    "addr:full":"Old London Road A23 Haywards Heath East Sussex RH17 5RL",
    "addr:postcode":"rh17 5rl",
    "addr:street":"Old London Road A23",
    "iso:country":"GB",
    "sg:address":"Old London Road A23",
    "sg:city":"Haywards Heath",
    "sg:classifiers":[
        {
            "category":"Shopping",
            "subcategory":"Clothing, Apparel, & Fashions",
            "type":"Retail Goods"
        }
    ],
    "sg:phone":"+44 1444 881255",
    "sg:postcode":"RH17 5RL",
    "sg:province":"East Sussex",
    "sg:tags":[
        "menswear"
    ],
    "wof:name":"Impulse",
    "wof:placetype":"venue"
},
  "geometry": {"coordinates":[-0.19826,51.000462],"type":"Point"}
}