{
  "type": "Feature",
  "properties": {
    "addr:full":"Hillcrest, Coach & Horses Lane, Danehill Haywards Heath East Sussex RH17 7JF",
    "addr:postcode":"rh17 7jf",
    "addr:street":"Lane",
    "iso:country":"GB",
    "sg:address":"Hillcrest, Coach & Horses Lane, Danehill",
    "sg:city":"Haywards Heath",
    "sg:classifiers":[
        {
            "category":"Banks & Credit Unions",
            "subcategory":"Financial Services",
            "type":"Services"
        }
    ],
    "sg:phone":"+44 1825 740137",
    "sg:postcode":"RH17 7JF",
    "sg:province":"East Sussex",
    "sg:tags":[
        "adviser"
    ],
    "wof:name":"Inter County Insurance Services",
    "wof:placetype":"venue"
},
  "geometry": {"coordinates":[0.0106199998,51.0393791199],"type":"Point"}
}