{
  "type": "Feature",
  "properties": {
    "iso:country":"GB",
    "sg:address":"Unit 2, Westland Sq",
    "sg:city":"Leeds",
    "sg:classifiers":[
        {
            "category":"Brewery",
            "type":"Food & Drink"
        }
    ],
    "sg:phone":"+44 113 270 4542",
    "sg:postcode":"LS11 5SS",
    "sg:province":"West Yorkshire",
    "sg:tags":[
        "brewer"
    ],
    "wof:name":"Old F Art Ltd",
    "wof:placetype":"venue"
},
  "geometry": {"coordinates":[-1.548937,53.765064],"type":"Point"}
}