{
  "type": "Feature",
  "properties": {
    "addr:full":"Weston Crescent Walsall Staffordshire WS9 0HA",
    "addr:postcode":"ws9 0ha",
    "addr:street":"Weston Crescent",
    "iso:country":"GB",
    "sg:address":"Weston Crescent",
    "sg:city":"Walsall",
    "sg:classifiers":[
        {
            "category":"Education",
            "subcategory":"School",
            "type":"Public Place"
        },
        {
            "category":"Government",
            "subcategory":"Office",
            "type":"Public Place"
        }
    ],
    "sg:phone":"+44 1922 743411",
    "sg:postcode":"WS9 0HA",
    "sg:province":"Staffordshire",
    "sg:tags":[
        "local",
        "authority"
    ],
    "wof:name":"St. Mary of the Angels R C Junior Mixed & Infant S",
    "wof:placetype":"venue"
},
  "geometry": {"coordinates":[-1.9168889523,52.5971984863],"type":"Point"}
}