{
  "type": "Feature",
  "properties": {
    "iso:country":"GB",
    "sg:address":"114 Elm Lane",
    "sg:city":"Sheffield",
    "sg:classifiers":[
        {
            "category":"Health Services",
            "subcategory":"Podiatrist",
            "type":"Services"
        }
    ],
    "sg:phone":"+44 114 240 0734",
    "sg:postcode":"S5 7TW",
    "sg:province":"South Yorkshire",
    "sg:tags":[
        "podiatrists",
        "chiropodist"
    ],
    "wof:name":"Christine A Fisher",
    "wof:placetype":"venue"
},
  "geometry": {"coordinates":[-1.4603669643,53.4216308594],"type":"Point"}
}