{
  "type": "Feature",
  "properties": {
    "addr:full":"725-729 Ormskirk Road, Pemberton Wigan Lancashire WN5 8AT",
    "addr:postcode":"725-729;wn5 8at",
    "addr:street":"Ormskirk Road",
    "iso:country":"GB",
    "sg:address":"725-729 Ormskirk Road, Pemberton",
    "sg:city":"Wigan",
    "sg:classifiers":[
        {
            "category":"Shopping",
            "subcategory":"Bicycles & Sporting Goods",
            "type":"Retail Goods"
        }
    ],
    "sg:phone":"+44 1942 214864",
    "sg:postcode":"WN5 8AT",
    "sg:province":"Lancashire",
    "sg:tags":[
        "cycle",
        "accessory"
    ],
    "wof:name":"John Winstanley & Co. Ltd.",
    "wof:placetype":"venue"
},
  "geometry": {"coordinates":[-2.6834700108,53.5363883972],"type":"Point"}
}