{
  "type": "Feature",
  "properties": {
    "addr:full":"80 Wellington Rd South Stockport Cheshire SK1 3SU",
    "addr:housenumber":"80",
    "addr:postcode":"sk1 3su",
    "addr:street":"Wellington Rd",
    "iso:country":"GB",
    "sg:address":"80 Wellington Rd South",
    "sg:city":"Stockport",
    "sg:classifiers":[
        {
            "category":"Professional",
            "subcategory":"Accounting & Tax Preparation",
            "type":"Services"
        }
    ],
    "sg:postcode":"SK1 3SU",
    "sg:province":"Cheshire",
    "sg:tags":[
        "accountant"
    ],
    "wof:name":"Bradley,Mary,",
    "wof:placetype":"venue"
},
  "geometry": {"coordinates":[-2.1596260071,53.4065628052],"type":"Point"}
}