{
  "type": "Feature",
  "properties": {
    "iso:country":"GB",
    "sg:address":"15 Newton Place",
    "sg:city":"Newcastle-upon-tyne",
    "sg:classifiers":[
        {
            "category":"Personal",
            "subcategory":"Beauty Salon",
            "type":"Services"
        }
    ],
    "sg:postcode":"NE7 7HD",
    "sg:province":"Tyne and Wear",
    "sg:tags":[
        "unisex",
        "hairdresser"
    ],
    "wof:name":"Kathleen Elliot",
    "wof:placetype":"venue"
},
  "geometry": {"coordinates":[-1.586204,54.995632],"type":"Point"}
}