{
  "type": "Feature",
  "properties": {
    "addr:full":"St Annes Chambers, St. Annes Rd Wst, Lytham St Annes Lytham St. Annes Lancashire FY8 1RF",
    "addr:postcode":"fy8 1rf",
    "addr:street":"Chambers St. Annes Rd;St;St. Annes",
    "iso:country":"GB",
    "sg:address":"St Annes Chambers, St. Annes Rd Wst, Lytham St Annes",
    "sg:city":"Lytham St. Annes",
    "sg:classifiers":[
        {
            "category":"Professional",
            "subcategory":"Management & Consulting",
            "type":"Services"
        }
    ],
    "sg:phone":"+44 1253 781800",
    "sg:postcode":"FY8 1RF",
    "sg:province":"Lancashire",
    "sg:tags":[
        "marketing",
        "consultant"
    ],
    "wof:name":"Hay Marketing",
    "wof:placetype":"venue"
},
  "geometry": {"coordinates":[-3.0250000954,53.7546195984],"type":"Point"}
}