{
  "type": "Feature",
  "properties": {
    "addr:full":"45 Severn Avenue, Tuttshill Chepstow Gloucestershire NP16 7EE",
    "addr:housenumber":"45",
    "addr:postcode":"np16 7ee",
    "addr:street":"Severn Avenue Tuttshill",
    "iso:country":"GB",
    "sg:address":"45 Severn Avenue, Tuttshill",
    "sg:city":"Chepstow",
    "sg:classifiers":[
        {
            "category":"Shopping",
            "subcategory":"Computers & Home Electronics",
            "type":"Retail Goods"
        }
    ],
    "sg:phone":"+44 1291 623037",
    "sg:postcode":"NP16 7EE",
    "sg:province":"Gloucestershire",
    "wof:name":"N A Design",
    "wof:placetype":"venue"
},
  "geometry": {"coordinates":[-2.662804,51.645676],"type":"Point"}
}