{
  "type": "Feature",
  "properties": {
    "iso:country":"GB",
    "sg:address":"345 Liverpool Road",
    "sg:city":"St Helens",
    "sg:classifiers":[
        {
            "category":"Farming",
            "subcategory":"Dairy Farm",
            "type":"Manufacturing & Wholesale Goods"
        }
    ],
    "sg:phone":"+44 1744 20456",
    "sg:postcode":"WA11 0UN",
    "sg:province":"Lancashire",
    "wof:name":"J Jaundrill",
    "wof:placetype":"venue"
},
  "geometry": {"coordinates":[-2.6900539398,53.4698295593],"type":"Point"}
}