{
  "type": "Feature",
  "properties": {
    "iso:country":"GB",
    "sg:address":"243 Worcester Road",
    "sg:city":"Malvern",
    "sg:classifiers":[
        {
            "category":"Restaurant",
            "type":"Food & Drink"
        }
    ],
    "sg:phone":"+44 1684 569817",
    "sg:postcode":"WR14 1SY",
    "sg:province":"Herefordshire",
    "sg:tags":[
        "indian"
    ],
    "wof:name":"Ajanta Indian Cuisine",
    "wof:placetype":"venue"
},
  "geometry": {"coordinates":[-2.313978,52.12846],"type":"Point"}
}