{
  "type": "Feature",
  "properties": {
    "addr:full":"Windsor House Telford Shropshire TF3 4NB",
    "addr:postcode":"tf3 4nb",
    "addr:street":"Telford",
    "iso:country":"GB",
    "sg:address":"Windsor House",
    "sg:city":"Telford",
    "sg:classifiers":[
        {
            "category":"Insurance",
            "subcategory":"Life Insurance",
            "type":"Services"
        }
    ],
    "sg:phone":"+44 1952 292929",
    "sg:postcode":"TF3 4NB",
    "sg:province":"Shropshire",
    "sg:tags":[
        "assurance"
    ],
    "wof:name":"Wlic",
    "wof:placetype":"venue"
},
  "geometry": {"coordinates":[-2.450119,52.67886],"type":"Point"}
}