{
  "type": "Feature",
  "properties": {
    "iso:country":"GB",
    "sg:address":"40a Yukon Rd",
    "sg:city":"Balham",
    "sg:classifiers":[
        {
            "category":"Building & Trades",
            "subcategory":"Construction",
            "type":"Services"
        }
    ],
    "sg:phone":"+44 20 8675 2559",
    "sg:postcode":"SW12 9PX",
    "sg:province":"Greater London",
    "sg:tags":[
        "builder"
    ],
    "wof:name":"Nethaway Bros",
    "wof:placetype":"venue"
},
  "geometry": {"coordinates":[-0.145272,51.449184],"type":"Point"}
}