{
  "type": "Feature",
  "properties": {
    "addr:full":"9-13 Caen St Braunton Devon EX33 1AA",
    "addr:housenumber":"9-13",
    "addr:postcode":"ex33 1aa",
    "addr:street":"Caen St",
    "iso:country":"GB",
    "sg:address":"9-13 Caen St",
    "sg:city":"Braunton",
    "sg:classifiers":[
        {
            "category":"Shopping",
            "subcategory":"Pharmacy",
            "type":"Retail Goods"
        }
    ],
    "sg:phone":"+44 1271 812081",
    "sg:postcode":"EX33 1AA",
    "sg:province":"Devon",
    "sg:tags":[
        "pharmacist",
        "chemist"
    ],
    "wof:name":"Lloyds Pharmacy",
    "wof:placetype":"venue"
},
  "geometry": {"coordinates":[-4.1621551514,51.1084823608],"type":"Point"}
}