{
  "type": "Feature",
  "properties": {
    "iso:country":"GB",
    "sg:address":"Knowle Green, Bowerchalke",
    "sg:city":"Salisbury",
    "sg:classifiers":[
        {
            "category":"Farming",
            "subcategory":"Farm",
            "type":"Manufacturing & Wholesale Goods"
        }
    ],
    "sg:phone":"+44 1722 780467",
    "sg:postcode":"SP5 5BQ",
    "sg:province":"Dorset",
    "sg:tags":[
        "hatchery"
    ],
    "wof:name":"Chalke Valley Trout Farms Ltd.",
    "wof:placetype":"venue"
},
  "geometry": {"coordinates":[-1.9657299519,51.0110702515],"type":"Point"}
}