{
  "type": "Feature",
  "properties": {
    "addr:full":"98 Windermere Rd Kendal Cumbria LA9 5EZ",
    "addr:housenumber":"98",
    "addr:postcode":"la9 5ez",
    "addr:street":"Windermere Rd",
    "iso:country":"GB",
    "sg:address":"98 Windermere Rd",
    "sg:city":"Kendal",
    "sg:classifiers":[
        {
            "category":"Travel",
            "subcategory":"Hotels & Motels",
            "type":"Entertainment"
        }
    ],
    "sg:phone":"+44 1539 722680",
    "sg:postcode":"LA9 5EZ",
    "sg:province":"Cumbria",
    "wof:name":"Hillcrest Hotel",
    "wof:placetype":"venue"
},
  "geometry": {"coordinates":[-2.7548611164,54.333442688],"type":"Point"}
}