{
  "type": "Feature",
  "properties": {
    "iso:country":"GB",
    "sg:address":"41 Langford Road",
    "sg:city":"Weston-super-mare",
    "sg:classifiers":[
        {
            "category":"Autos & Motor Vehicles",
            "subcategory":"Fuel & Gas Station",
            "type":"Retail Goods"
        }
    ],
    "sg:postcode":"BS23 3PQ",
    "sg:province":"Somerset",
    "sg:tags":[
        "engine",
        "sale"
    ],
    "wof:name":"Langford Road Garage",
    "wof:placetype":"venue"
},
  "geometry": {"coordinates":[-2.961528,51.343407],"type":"Point"}
}