{
  "type": "Feature",
  "properties": {
    "iso:country":"GB",
    "sg:address":"Celyn Coed Y Caerau, Kemeys Inferior",
    "sg:city":"Newport",
    "sg:classifiers":[
        {
            "category":"Banks & Credit Unions",
            "subcategory":"Financial Services",
            "type":"Services"
        }
    ],
    "sg:phone":"+44 1633 400626",
    "sg:postcode":"NP18 1JR",
    "sg:province":"Monmouthshire",
    "sg:tags":[
        "consultant"
    ],
    "wof:name":"Veronica Hughes",
    "wof:placetype":"venue"
},
  "geometry": {"coordinates":[-2.906365,51.623508],"type":"Point"}
}