{
  "type": "Feature",
  "properties": {
    "iso:country":"GB",
    "sg:address":"20 Queen Street",
    "sg:city":"Wells",
    "sg:classifiers":[
        {
            "category":"Retail",
            "subcategory":"Laundry & Dry Cleaning",
            "type":"Services"
        }
    ],
    "sg:phone":"+44 1749 671215",
    "sg:postcode":"BA5 2DP",
    "sg:province":"Somerset",
    "sg:tags":[
        "cleaner",
        "alteration"
    ],
    "wof:name":"Wells Cleaners",
    "wof:placetype":"venue"
},
  "geometry": {"coordinates":[-2.6485929489,51.2074165344],"type":"Point"}
}