{
  "type": "Feature",
  "properties": {
    "iso:country":"GB",
    "sg:address":"13 Old Road",
    "sg:city":"Billingham",
    "sg:classifiers":[
        {
            "category":"Bus Charters",
            "type":"Transportation"
        }
    ],
    "sg:phone":"+44 1642 550660",
    "sg:postcode":"TS23 1DS",
    "sg:province":"Durham",
    "sg:tags":[
        "hire",
        "coach"
    ],
    "wof:name":"Rainbow Coaches",
    "wof:placetype":"venue"
},
  "geometry": {"coordinates":[-1.293951,54.592037],"type":"Point"}
}