{
  "type": "Feature",
  "properties": {
    "addr:full":"Whitburn Road London Greater London SE13 7UQ",
    "addr:postcode":"se13 7uq",
    "addr:street":"Whitburn Road",
    "iso:country":"GB",
    "sg:address":"Whitburn Road",
    "sg:city":"London",
    "sg:classifiers":[
        {
            "category":"Shopping",
            "type":"Retail Goods"
        }
    ],
    "sg:postcode":"SE13 7UQ",
    "sg:province":"Greater London",
    "sg:tags":[
        "part",
        "accessory"
    ],
    "wof:name":"Rainbow Rugs",
    "wof:placetype":"venue"
},
  "geometry": {"coordinates":[-0.015344,51.457497],"type":"Point"}
}