{
  "type": "Feature",
  "properties": {
    "addr:full":"Main Street, Craigrothie Cupar Fife KY15 5QA",
    "addr:postcode":"ky15 5qa",
    "addr:street":"Main Street",
    "iso:country":"GB",
    "sg:address":"Main Street, Craigrothie",
    "sg:city":"Cupar",
    "sg:classifiers":[
        {
            "category":"Education",
            "subcategory":"School",
            "type":"Public Place"
        },
        {
            "category":"Government",
            "subcategory":"Office",
            "type":"Public Place"
        }
    ],
    "sg:phone":"+44 1334 828258",
    "sg:postcode":"KY15 5QA",
    "sg:province":"Fife",
    "sg:tags":[
        "local",
        "authority"
    ],
    "wof:name":"Craigrothie Primary School",
    "wof:placetype":"venue"
},
  "geometry": {"coordinates":[-3.0048890114,56.2870140076],"type":"Point"}
}