{
  "type": "Feature",
  "properties": {
    "iso:country":"GB",
    "sg:address":"Willow Tree Farm, Wickenby",
    "sg:city":"Lincoln",
    "sg:classifiers":[
        {
            "category":"Farming",
            "subcategory":"Farm",
            "type":"Manufacturing & Wholesale Goods"
        }
    ],
    "sg:phone":"+44 1673 885298",
    "sg:postcode":"LN3 5AB",
    "sg:province":"Lincolnshire",
    "sg:tags":[
        "mixed",
        "crop"
    ],
    "wof:name":"N E & K B Thornalley",
    "wof:placetype":"venue"
},
  "geometry": {"coordinates":[-0.3684189916,53.3236045837],"type":"Point"}
}