{
  "type": "Feature",
  "properties": {
    "addr:full":"Unit 4d Triumph Trading Est, Tariff Rd Tottenham Greater London N17 0EB",
    "addr:housenumber":"unit 4d",
    "addr:postcode":"n17 0eb",
    "addr:street":"Tariff Rd",
    "iso:country":"GB",
    "sg:address":"Unit 4d Triumph Trading Est, Tariff Rd",
    "sg:city":"Tottenham",
    "sg:classifiers":[
        {
            "category":"Communications",
            "subcategory":"News Services",
            "type":"Services"
        }
    ],
    "sg:phone":"+44 20 8808 8916",
    "sg:postcode":"N17 0EB",
    "sg:province":"Greater London",
    "sg:tags":[
        "press"
    ],
    "wof:name":"B S E Press Knives Co Ltd",
    "wof:placetype":"venue"
},
  "geometry": {"coordinates":[-0.059971001,51.606967926],"type":"Point"}
}