{
  "type": "Feature",
  "properties": {
    "addr:full":"106 Grafton Centre Cambridge Cambridgeshire CB1 1PS",
    "addr:housenumber":"106",
    "addr:postcode":"cb1 1ps",
    "addr:street":"Grafton Centre",
    "iso:country":"GB",
    "sg:address":"106 Grafton Centre",
    "sg:city":"Cambridge",
    "sg:classifiers":[
        {
            "category":"Restaurant",
            "type":"Food & Drink"
        }
    ],
    "sg:phone":"+44 1223 462464",
    "sg:postcode":"CB1 1PS",
    "sg:province":"Cambridgeshire",
    "wof:name":"Mama Amalfi",
    "wof:placetype":"venue"
},
  "geometry": {"coordinates":[0.1328399926,52.2050209045],"type":"Point"}
}