{
  "type": "Feature",
  "properties": {
    "addr:full":"170 Lavender Hill London Greater London SW11 5TG",
    "addr:housenumber":"170",
    "addr:postcode":"sw11 5tg",
    "addr:street":"Lavender Hill",
    "iso:country":"GB",
    "sg:address":"170 Lavender Hill",
    "sg:city":"London",
    "sg:classifiers":[
        {
            "category":"Professional",
            "subcategory":"Printing & Photocopies",
            "type":"Services"
        }
    ],
    "sg:phone":"+44 20 7223 8953",
    "sg:postcode":"SW11 5TG",
    "sg:province":"Greater London",
    "sg:tags":[
        "printer"
    ],
    "wof:name":"H Kutner",
    "wof:placetype":"venue"
},
  "geometry": {"coordinates":[-0.1613709927,51.4647026062],"type":"Point"}
}