{
  "type": "Feature",
  "properties": {
    "addr:full":"46a Lozells Road Birmingham West Midlands B19 2TH",
    "addr:housenumber":"46a;b19",
    "addr:postcode":"2th",
    "addr:street":"Lozells Road",
    "iso:country":"GB",
    "sg:address":"46a Lozells Road",
    "sg:city":"Birmingham",
    "sg:classifiers":[
        {
            "category":"Taxi",
            "type":"Transportation"
        },
        {
            "category":"Military Area",
            "subcategory":"Air Force Base",
            "type":"Public Place"
        }
    ],
    "sg:phone":"+44 121 359 3131",
    "sg:postcode":"B19 2TH",
    "sg:province":"West Midlands",
    "sg:tags":[
        "hire",
        "private"
    ],
    "wof:name":"Blue Line Cars",
    "wof:placetype":"venue"
},
  "geometry": {"coordinates":[-1.9019869566,52.5024757385],"type":"Point"}
}