{
  "type": "Feature",
  "properties": {
    "iso:country":"GB",
    "sg:address":"Queens Parade, North Road",
    "sg:city":"Lancing",
    "sg:classifiers":[
        {
            "category":"Food & Beverages",
            "subcategory":"Supermarket",
            "type":"Retail Goods"
        }
    ],
    "sg:phone":"+44 1903 753665",
    "sg:postcode":"BN15 9BA",
    "sg:province":"West Sussex",
    "wof:name":"Somerfield",
    "wof:placetype":"venue"
},
  "geometry": {"coordinates":[-0.318039,50.821899],"type":"Point"}
}