{
  "type": "Feature",
  "properties": {
    "addr:full":"Tigh Mhicleiod, Colchester Square Lochgilphead Argyll and Bute PA31 8JL",
    "addr:postcode":"pa31 8jl",
    "addr:street":"Square Lochgilphead",
    "iso:country":"GB",
    "sg:address":"Tigh Mhicleiod, Colchester Square",
    "sg:city":"Lochgilphead",
    "sg:classifiers":[
        {
            "category":"Organizations",
            "subcategory":"Non-profit Organization",
            "type":"Services"
        }
    ],
    "sg:phone":"+44 1546 606584",
    "sg:postcode":"PA31 8JL",
    "sg:province":"Argyll and Bute",
    "sg:tags":[
        "charitable",
        "organisation",
        "voluntary",
        "charity"
    ],
    "wof:name":"The Prince's Scottish Youth Business Trust Ltd.",
    "wof:placetype":"venue"
},
  "geometry": {"coordinates":[-5.4318242073,56.0361061096],"type":"Point"}
}