{
  "type": "Feature",
  "properties": {
    "iso:country":"GB",
    "sg:address":"12 Church Street",
    "sg:city":"Glenrothes",
    "sg:classifiers":[
        {
            "category":"Fast Food",
            "type":"Food & Drink"
        }
    ],
    "sg:phone":"+44 1592 612888",
    "sg:postcode":"KY7 5ND",
    "sg:province":"Fife",
    "sg:tags":[
        "away",
        "take"
    ],
    "wof:name":"Mayflower",
    "wof:placetype":"venue"
},
  "geometry": {"coordinates":[-3.166437,56.196709],"type":"Point"}
}