{
  "type": "Feature",
  "properties": {
    "addr:full":"Little Manor Farm, Nawton York North Yorkshire YO62 7TU",
    "addr:postcode":"yo62 7tu",
    "iso:country":"GB",
    "sg:address":"Little Manor Farm, Nawton",
    "sg:city":"York",
    "sg:classifiers":[
        {
            "category":"Sports & Exercise",
            "subcategory":"Stables",
            "type":"Entertainment"
        },
        {
            "category":"Personal",
            "subcategory":"Adult",
            "type":"Services"
        }
    ],
    "sg:phone":"+44 1439 771672",
    "sg:postcode":"YO62 7TU",
    "sg:province":"North Yorkshire",
    "sg:tags":[
        "education",
        "equestrian"
    ],
    "wof:name":"Maurice Avison",
    "wof:placetype":"venue"
},
  "geometry": {"coordinates":[-0.995415,54.253433],"type":"Point"}
}