{
  "type": "Feature",
  "properties": {
    "addr:full":"48 King Street Wigton Cumbria CA7 9EJ",
    "addr:housenumber":"48",
    "addr:postcode":"ca7 9ej",
    "addr:street":"King Street",
    "iso:country":"GB",
    "sg:address":"48 King Street",
    "sg:city":"Wigton",
    "sg:classifiers":[
        {
            "category":"Food & Beverages",
            "subcategory":"Candy",
            "type":"Retail Goods"
        }
    ],
    "sg:phone":"+44 16973 43618",
    "sg:postcode":"CA7 9EJ",
    "sg:province":"Cumbria",
    "sg:tags":[
        "confectioner"
    ],
    "wof:name":"Christie's",
    "wof:placetype":"venue"
},
  "geometry": {"coordinates":[-3.1594409943,54.8256874084],"type":"Point"}
}