{
  "type": "Feature",
  "properties": {
    "iso:country":"GB",
    "sg:address":"134 Kensington",
    "sg:city":"Liverpool",
    "sg:classifiers":[
        {
            "category":"Retail",
            "subcategory":"Laundry & Dry Cleaning",
            "type":"Services"
        }
    ],
    "sg:phone":"+44 151 280 5181",
    "sg:postcode":"L7 8XE",
    "sg:province":"Merseyside",
    "sg:tags":[
        "launderette"
    ],
    "wof:name":"Liver Launderettes",
    "wof:placetype":"venue"
},
  "geometry": {"coordinates":[-2.955952,53.411655],"type":"Point"}
}