{
  "type": "Feature",
  "properties": {
    "addr:full":"Ger Y Llan Llanelli Carmarthenshire SA15 1DP",
    "addr:postcode":"sa15 1dp",
    "addr:street":"Llan;Carmarthenshire",
    "iso:country":"GB",
    "sg:address":"Ger Y Llan",
    "sg:city":"Llanelli",
    "sg:classifiers":[
        {
            "category":"Organizations",
            "subcategory":"Non-profit Organization",
            "type":"Services"
        }
    ],
    "sg:phone":"+44 1554 775338",
    "sg:postcode":"SA15 1DP",
    "sg:province":"Carmarthenshire",
    "sg:tags":[
        "charitable",
        "organisation",
        "voluntary",
        "charity"
    ],
    "wof:name":"St Paul'S Family Centre",
    "wof:placetype":"venue"
},
  "geometry": {"coordinates":[-4.157644,51.677132],"type":"Point"}
}