{
  "type": "Feature",
  "properties": {
    "addr:full":"The Old Brickyard, Ashton Keynes Swindon Gloucestershire SN6 6QR",
    "addr:postcode":"sn6 6qr",
    "iso:country":"GB",
    "sg:address":"The Old Brickyard, Ashton Keynes",
    "sg:city":"Swindon",
    "sg:classifiers":[
        {
            "category":"Shopping",
            "subcategory":"Books",
            "type":"Retail Goods"
        }
    ],
    "sg:postcode":"SN6 6QR",
    "sg:province":"Gloucestershire",
    "sg:tags":[
        "bookseller"
    ],
    "wof:name":"M B E Books",
    "wof:placetype":"venue"
},
  "geometry": {"coordinates":[-1.940819,51.641937],"type":"Point"}
}