{
  "type": "Feature",
  "properties": {
    "addr:full":"20 Marigold Clo, Oakwood Derby Derbyshire DE21 2SE",
    "addr:housenumber":"20",
    "addr:postcode":"de21 2se",
    "addr:street":"Marigold Clo",
    "iso:country":"GB",
    "sg:address":"20 Marigold Clo, Oakwood",
    "sg:city":"Derby",
    "sg:classifiers":[
        {
            "category":"Building & Trades",
            "subcategory":"Plumbing",
            "type":"Services"
        }
    ],
    "sg:postcode":"DE21 2SE",
    "sg:province":"Derbyshire",
    "sg:tags":[
        "central",
        "heating"
    ],
    "wof:name":"Smith,Barry,",
    "wof:placetype":"venue"
},
  "geometry": {"coordinates":[-1.427183032,52.9474411011],"type":"Point"}
}