{
  "type": "Feature",
  "properties": {
    "addr:full":"Winfrith Technology Centre, Winfrith Newburgh Dorchester Dorset DT2 8DH",
    "addr:housenumber":"winfrith;centre winfrith",
    "addr:postcode":"dt2 8dh",
    "iso:country":"GB",
    "sg:address":"Winfrith Technology Centre, Winfrith Newburgh",
    "sg:city":"Dorchester",
    "sg:classifiers":[
        {
            "category":"Home & Garden",
            "subcategory":"Hardware",
            "type":"Retail Goods"
        },
        {
            "category":"Manufacturing",
            "subcategory":"Building Materials",
            "type":"Manufacturing & Wholesale Goods"
        }
    ],
    "sg:phone":"+44 1305 853090",
    "sg:postcode":"DT2 8DH",
    "sg:province":"Dorset",
    "sg:tags":[
        "supp",
        "component",
        "shutter",
        "door",
        "electronic"
    ],
    "wof:name":"Keystone Electronics Ltd.",
    "wof:placetype":"venue"
},
  "geometry": {"coordinates":[-2.2526,50.682899],"type":"Point"}
}