{
  "type": "Feature",
  "properties": {
    "addr:full":"93 Royden Road Wirral Merseyside CH49 4LX",
    "addr:housenumber":"93",
    "addr:postcode":"ch49 4lx",
    "addr:street":"Royden Road",
    "iso:country":"GB",
    "sg:address":"93 Royden Road",
    "sg:city":"Wirral",
    "sg:classifiers":[
        {
            "category":"Personal",
            "subcategory":"Beauty Salon",
            "type":"Services"
        }
    ],
    "sg:phone":"+44 151 604 1614",
    "sg:postcode":"CH49 4LX",
    "sg:province":"Merseyside",
    "sg:tags":[
        "unisex",
        "hairdresser"
    ],
    "wof:name":"Kool Cuts",
    "wof:placetype":"venue"
},
  "geometry": {"coordinates":[-3.1079759598,53.3893356323],"type":"Point"}
}