{
  "type": "Feature",
  "properties": {
    "iso:country":"GB",
    "sg:address":"Ashleigh, Terrace Road South",
    "sg:city":"Bracknell",
    "sg:classifiers":[
        {
            "category":"Shopping",
            "subcategory":"Bicycles & Sporting Goods",
            "type":"Retail Goods"
        }
    ],
    "sg:postcode":"RG42 4DS",
    "sg:province":"Berkshire",
    "sg:tags":[
        "riding",
        "saddlery",
        "wear"
    ],
    "wof:name":"The Millwheel Tack Shop",
    "wof:placetype":"venue"
},
  "geometry": {"coordinates":[-0.788429,51.428215],"type":"Point"}
}