{
  "type": "Feature",
  "properties": {
    "addr:full":"The Ffwrrwm High Street, Caerleon Newport Monmouthshire NP18 1AH",
    "addr:postcode":"np18 1ah",
    "addr:street":"High Street",
    "iso:country":"GB",
    "sg:address":"The Ffwrrwm High Street, Caerleon",
    "sg:city":"Newport",
    "sg:classifiers":[
        {
            "category":"Shopping",
            "subcategory":"Gifts & Souvenirs",
            "type":"Retail Goods"
        }
    ],
    "sg:phone":"+44 1633 430046",
    "sg:postcode":"NP18 1AH",
    "sg:province":"Monmouthshire",
    "sg:tags":[
        "shop"
    ],
    "wof:name":"Satinside",
    "wof:placetype":"venue"
},
  "geometry": {"coordinates":[-2.9532001019,51.6091194153],"type":"Point"}
}