{
  "type": "Feature",
  "properties": {
    "iso:country":"GB",
    "sg:address":"90-96 Evelina Road, Peckham",
    "sg:city":"London",
    "sg:classifiers":[
        {
            "category":"Building & Trades",
            "subcategory":"Plumbing",
            "type":"Services"
        }
    ],
    "sg:phone":"+44 20 7639 0457",
    "sg:postcode":"SE15 3HL",
    "sg:province":"Greater London",
    "sg:tags":[
        "merchant",
        "plumbers'"
    ],
    "wof:name":"M K K Services",
    "wof:placetype":"venue"
},
  "geometry": {"coordinates":[-0.055952,51.466732],"type":"Point"}
}