{
  "type": "Feature",
  "properties": {
    "iso:country":"GB",
    "sg:address":"19 Crayford High Street",
    "sg:city":"Dartford",
    "sg:classifiers":[
        {
            "category":"Fast Food",
            "type":"Food & Drink"
        }
    ],
    "sg:phone":"+44 1322 557735",
    "sg:postcode":"DA1 4HH",
    "sg:province":"Kent",
    "sg:tags":[
        "away",
        "take"
    ],
    "wof:name":"The Curry Manzil",
    "wof:placetype":"venue"
},
  "geometry": {"coordinates":[0.1894010007,51.4492073059],"type":"Point"}
}