{
  "type": "Feature",
  "properties": {
    "iso:country":"GB",
    "sg:address":"8 Woodgreen Rd",
    "sg:city":"Liverpool",
    "sg:classifiers":[
        {
            "category":"Professional",
            "subcategory":"Engineering",
            "type":"Services"
        }
    ],
    "sg:phone":"+44 151 220 9368",
    "sg:postcode":"L15 4LH",
    "sg:province":"Merseyside",
    "sg:tags":[
        "gas",
        "engineer"
    ],
    "wof:name":"Discount Gas Heating & Sales Ltd",
    "wof:placetype":"venue"
},
  "geometry": {"coordinates":[-2.9144740105,53.4171867371],"type":"Point"}
}