{
  "type": "Feature",
  "properties": {
    "addr:full":"47f Blackborough Rd Reigate Surrey RH2 7BU",
    "addr:housenumber":"47f",
    "addr:postcode":"rh2 7bu",
    "addr:street":"Blackborough Rd",
    "iso:country":"GB",
    "sg:address":"47f Blackborough Rd",
    "sg:city":"Reigate",
    "sg:classifiers":[
        {
            "category":"Retail",
            "subcategory":"Storage",
            "type":"Services"
        }
    ],
    "sg:phone":"+44 1737 243750",
    "sg:postcode":"RH2 7BU",
    "sg:province":"Surrey",
    "sg:tags":[
        "household",
        "removal"
    ],
    "wof:name":"M D Boud Archive Storage",
    "wof:placetype":"venue"
},
  "geometry": {"coordinates":[-0.1950069964,51.2348480225],"type":"Point"}
}