{
  "type": "Feature",
  "properties": {
    "addr:full":"3-4 The Arcade Bedford Bedfordshire MK40 1NS",
    "addr:housenumber":"3-4",
    "addr:postcode":"mk40 1ns",
    "addr:street":"The Arcade",
    "iso:country":"GB",
    "sg:address":"3-4 The Arcade",
    "sg:city":"Bedford",
    "sg:classifiers":[
        {
            "category":"Health Services",
            "subcategory":"Optometrist",
            "type":"Services"
        }
    ],
    "sg:postcode":"MK40 1NS",
    "sg:province":"Bedfordshire",
    "sg:tags":[
        "optician"
    ],
    "wof:name":"Simon Donne Opticians",
    "wof:placetype":"venue"
},
  "geometry": {"coordinates":[-0.477508,52.137833],"type":"Point"}
}