{
  "type": "Feature",
  "properties": {
    "iso:country":"GB",
    "sg:address":"221 Aston La, Handsworth",
    "sg:city":"Birmingham",
    "sg:classifiers":[
        {
            "category":"Shopping",
            "subcategory":"Pharmacy",
            "type":"Retail Goods"
        }
    ],
    "sg:postcode":"B20 3HY",
    "sg:province":"West Midlands",
    "sg:tags":[
        "pharmacist",
        "chemist"
    ],
    "wof:name":"Lanley,Roger K,",
    "wof:placetype":"venue"
},
  "geometry": {"coordinates":[-1.8915339708,52.5139656067],"type":"Point"}
}