{
  "type": "Feature",
  "properties": {
    "iso:country":"GB",
    "sg:address":"35 The Brunel Centre, The Concourse",
    "sg:city":"Milton Keynes",
    "sg:classifiers":[
        {
            "category":"Professional",
            "subcategory":"Business Services",
            "type":"Services"
        }
    ],
    "sg:phone":"+44 1908 376300",
    "sg:postcode":"MK2 2ES",
    "sg:province":"Buckinghamshire",
    "sg:tags":[
        "information"
    ],
    "wof:name":"Town Centre Management Office",
    "wof:placetype":"venue"
},
  "geometry": {"coordinates":[-0.7333599925,51.9940414429],"type":"Point"}
}