{
  "type": "Feature",
  "properties": {
    "addr:full":"22 Inglesley Road, Bollington Macclesfield Cheshire SK10 5RF",
    "addr:housenumber":"22",
    "addr:postcode":"sk10 5rf",
    "addr:street":"Inglesley Road",
    "iso:country":"GB",
    "sg:address":"22 Inglesley Road, Bollington",
    "sg:city":"Macclesfield",
    "sg:classifiers":[
        {
            "category":"Restaurant",
            "type":"Food & Drink"
        }
    ],
    "sg:phone":"+44 1625 573006",
    "sg:postcode":"SK10 5RF",
    "sg:province":"Cheshire",
    "sg:tags":[
        "indian",
        "-"
    ],
    "wof:name":"Viceroy Indian Cuisine",
    "wof:placetype":"venue"
},
  "geometry": {"coordinates":[-2.1103689671,53.2933883667],"type":"Point"}
}