{
  "type": "Feature",
  "properties": {
    "addr:full":"25 High Street Dunblane Perth and Kinross FK15 0EE",
    "addr:housenumber":"25",
    "addr:postcode":"fk15 0ee",
    "addr:street":"High Street",
    "iso:country":"GB",
    "sg:address":"25 High Street",
    "sg:city":"Dunblane",
    "sg:classifiers":[
        {
            "category":"Shopping",
            "subcategory":"Books",
            "type":"Retail Goods"
        },
        {
            "category":"Shopping",
            "subcategory":"News",
            "type":"Retail Goods"
        }
    ],
    "sg:phone":"+44 1786 824738",
    "sg:postcode":"FK15 0EE",
    "sg:province":"Perth and Kinross",
    "sg:tags":[
        "bookseller",
        "newsagent"
    ],
    "wof:name":"Browsers",
    "wof:placetype":"venue"
},
  "geometry": {"coordinates":[-3.9643070698,56.1872444153],"type":"Point"}
}