{
  "type": "Feature",
  "properties": {
    "iso:country":"GB",
    "sg:address":"Hillhouse, 1 Little New Street",
    "sg:city":"London",
    "sg:classifiers":[
        {
            "category":"Shopping",
            "subcategory":"Baby Store",
            "type":"Retail Goods"
        }
    ],
    "sg:phone":"+44 20 7387 5050",
    "sg:postcode":"EC2M 4TP",
    "sg:province":"Greater London",
    "sg:tags":[
        "nursery",
        "accessory"
    ],
    "wof:name":"Tamsit International Ltd.",
    "wof:placetype":"venue"
},
  "geometry": {"coordinates":[-0.0794999972,51.5173416138],"type":"Point"}
}