{
  "type": "Feature",
  "properties": {
    "iso:country":"GB",
    "sg:address":"158-172 East Prescot Rd, Knotty Ash",
    "sg:city":"Liverpool",
    "sg:classifiers":[
        {
            "category":"Retail",
            "subcategory":"Auto Repair",
            "type":"Services"
        }
    ],
    "sg:phone":"+44 151 228 8410",
    "sg:postcode":"L14 5ND",
    "sg:province":"Merseyside",
    "sg:tags":[
        "modification",
        "garage"
    ],
    "wof:name":"Springfield Service Station",
    "wof:placetype":"venue"
},
  "geometry": {"coordinates":[-2.897879,53.416908],"type":"Point"}
}