{
  "type": "Feature",
  "properties": {
    "iso:country":"GB",
    "sg:address":"Thorpe House, High Street, Ravensthorpe",
    "sg:city":"Northampton",
    "sg:classifiers":[
        {
            "category":"Retail",
            "subcategory":"Auto Repair",
            "type":"Services"
        }
    ],
    "sg:phone":"+44 1604 770330",
    "sg:postcode":"NN6 8PJ",
    "sg:province":"Northamptonshire",
    "sg:tags":[
        "modification",
        "garage"
    ],
    "wof:name":"Ravensthorpe Service Station Ltd.",
    "wof:placetype":"venue"
},
  "geometry": {"coordinates":[-0.962994,52.341454],"type":"Point"}
}