{
  "type": "Feature",
  "properties": {
    "addr:full":"14 Moorham Road Winscombe Somerset BS25 1HS",
    "addr:housenumber":"14",
    "addr:postcode":"bs25 1hs",
    "addr:street":"Moorham Road",
    "iso:country":"GB",
    "sg:address":"14 Moorham Road",
    "sg:city":"Winscombe",
    "sg:classifiers":[
        {
            "category":"Professional",
            "subcategory":"Engineering",
            "type":"Services"
        }
    ],
    "sg:postcode":"BS25 1HS",
    "sg:province":"Somerset",
    "sg:tags":[
        "contractor",
        "electrical",
        "engineer"
    ],
    "wof:name":"I R H Electrical & Alarms",
    "wof:placetype":"venue"
},
  "geometry": {"coordinates":[-2.832136,51.318764],"type":"Point"}
}