{
  "type": "Feature",
  "properties": {
    "addr:full":"Unit 9, Hamble Court, Hamble Lane Southampton Hampshire SO31 4HX",
    "addr:housenumber":"unit 9",
    "addr:postcode":"so31 4hx",
    "addr:street":"Hamble Court Hamble Lane",
    "iso:country":"GB",
    "sg:address":"Unit 9, Hamble Court, Hamble Lane",
    "sg:city":"Southampton",
    "sg:classifiers":[
        {
            "category":"Manufacturing",
            "subcategory":"Metals",
            "type":"Manufacturing & Wholesale Goods"
        }
    ],
    "sg:phone":"+44 23 8045 3535",
    "sg:postcode":"SO31 4HX",
    "sg:province":"Hampshire",
    "sg:tags":[
        "product",
        "fabricated"
    ],
    "wof:name":"Bartlett Metal Products Ltd.",
    "wof:placetype":"venue"
},
  "geometry": {"coordinates":[-1.328794,50.863125],"type":"Point"}
}