{
  "type": "Feature",
  "properties": {
    "addr:full":"599 High Rd, Tottenham Tottenham Greater London N17 6EW",
    "addr:housenumber":"599",
    "addr:postcode":"n17 6ew",
    "addr:street":"High Rd",
    "iso:country":"GB",
    "sg:address":"599 High Rd, Tottenham",
    "sg:city":"Tottenham",
    "sg:classifiers":[
        {
            "category":"Professional",
            "subcategory":"Lawyer & Legal Services",
            "type":"Services"
        }
    ],
    "sg:phone":"+44 20 8808 6622",
    "sg:postcode":"N17 6EW",
    "sg:province":"Greater London",
    "sg:tags":[
        "solicitor"
    ],
    "wof:name":"Needham",
    "wof:placetype":"venue"
},
  "geometry": {"coordinates":[-0.068506,51.596951],"type":"Point"}
}