{
  "type": "Feature",
  "properties": {
    "addr:full":"Pathfields Road Clacton-on-sea Essex CO15 3JL",
    "addr:postcode":"co15 3jl",
    "addr:street":"Pathfields Road",
    "iso:country":"GB",
    "sg:address":"Pathfields Road",
    "sg:city":"Clacton-on-sea",
    "sg:classifiers":[
        {
            "category":"Education",
            "subcategory":"School",
            "type":"Public Place"
        }
    ],
    "sg:phone":"+44 1255 428131",
    "sg:postcode":"CO15 3JL",
    "sg:province":"Essex",
    "sg:tags":[
        "college"
    ],
    "wof:name":"Colbayns High School",
    "wof:placetype":"venue"
},
  "geometry": {"coordinates":[1.1425499916,51.7989463806],"type":"Point"}
}