{
  "type": "Feature",
  "properties": {
    "addr:full":"Stirling House Kingston-upon-thames Greater London KT2 5EE",
    "addr:postcode":"kt2 5ee",
    "addr:street":"Kingston-Upon-Thames",
    "iso:country":"GB",
    "sg:address":"Stirling House",
    "sg:city":"Kingston-upon-thames",
    "sg:classifiers":[
        {
            "category":"Professional",
            "subcategory":"Employment Agencies",
            "type":"Services"
        }
    ],
    "sg:phone":"+44 20 8974 5566",
    "sg:postcode":"KT2 5EE",
    "sg:province":"Greater London",
    "sg:tags":[
        "consultant"
    ],
    "wof:name":"Stirling Metro-Rail Ltd.",
    "wof:placetype":"venue"
},
  "geometry": {"coordinates":[-0.2914740145,51.411026001],"type":"Point"}
}