{
  "type": "Feature",
  "properties": {
    "addr:full":"Lochee Lodge Fraserburgh Aberdeenshire AB43 8UT",
    "addr:postcode":"ab43 8ut",
    "iso:country":"GB",
    "sg:address":"Lochee Lodge",
    "sg:city":"Fraserburgh",
    "sg:classifiers":[
        {
            "category":"Building & Trades",
            "subcategory":"Construction",
            "type":"Services"
        }
    ],
    "sg:postcode":"AB43 8UT",
    "sg:province":"Aberdeenshire",
    "sg:tags":[
        "joiner",
        "carpenter"
    ],
    "wof:name":"A W Anderson",
    "wof:placetype":"venue"
},
  "geometry": {"coordinates":[-2.0158441067,57.6944198608],"type":"Point"}
}