{
  "type": "Feature",
  "properties": {
    "iso:country":"GB",
    "sg:address":"2 Rogers Indust Est, Yalberton Rd",
    "sg:city":"Paignton",
    "sg:classifiers":[
        {
            "category":"Social Services",
            "type":"Services"
        }
    ],
    "sg:phone":"+44 1803 521612",
    "sg:postcode":"TQ4 7PJ",
    "sg:province":"Devon",
    "wof:name":"Nidus",
    "wof:placetype":"venue"
},
  "geometry": {"coordinates":[-3.5933909416,50.4221572876],"type":"Point"}
}