{
  "type": "Feature",
  "properties": {
    "addr:full":"Philip House, Honiton Road Exeter Devon EX1 3RU",
    "addr:postcode":"ex1 3ru",
    "addr:street":"Honiton Road",
    "iso:country":"GB",
    "sg:address":"Philip House, Honiton Road",
    "sg:city":"Exeter",
    "sg:classifiers":[
        {
            "category":"Shopping",
            "subcategory":"Stationery & Office Supplies",
            "type":"Retail Goods"
        }
    ],
    "sg:phone":"+44 1392 369607",
    "sg:postcode":"EX1 3RU",
    "sg:province":"Devon",
    "sg:tags":[
        "equipment"
    ],
    "wof:name":"Office Wholesale",
    "wof:placetype":"venue"
},
  "geometry": {"coordinates":[-3.4620890617,50.7289848328],"type":"Point"}
}