{
  "type": "Feature",
  "properties": {
    "iso:country":"GB",
    "sg:address":"Netherlands, Fox Lane Ends",
    "sg:city":"Preston",
    "sg:classifiers":[
        {
            "category":"Shopping",
            "subcategory":"Clothing, Apparel, & Fashions",
            "type":"Retail Goods"
        }
    ],
    "sg:postcode":"PR4 2PJ",
    "sg:province":"Lancashire",
    "sg:tags":[
        "shop"
    ],
    "wof:name":"E J & E P J Walton",
    "wof:placetype":"venue"
},
  "geometry": {"coordinates":[-2.919959,53.781147],"type":"Point"}
}