{
  "type": "Feature",
  "properties": {
    "iso:country":"GB",
    "sg:address":"181 Westbourne Gro",
    "sg:city":"London",
    "sg:classifiers":[
        {
            "category":"Shopping",
            "subcategory":"Antiques",
            "type":"Retail Goods"
        }
    ],
    "sg:phone":"+44 20 7221 4391",
    "sg:postcode":"W11 2SB",
    "sg:province":"Greater London",
    "wof:name":"Alders,Michael,",
    "wof:placetype":"venue"
},
  "geometry": {"coordinates":[-0.1980530024,51.5145301819],"type":"Point"}
}