{
  "type": "Feature",
  "properties": {
    "iso:country":"GB",
    "sg:address":"11 Broad Street",
    "sg:city":"Denny",
    "sg:classifiers":[
        {
            "category":"Military Area",
            "subcategory":"Air Force Base",
            "type":"Public Place"
        }
    ],
    "sg:phone":"+44 1324 825747",
    "sg:postcode":"FK6 6DX",
    "sg:province":"Falkirk",
    "sg:tags":[
        "taxi",
        "hire",
        "private"
    ],
    "wof:name":"Rainbow Taxis",
    "wof:placetype":"venue"
},
  "geometry": {"coordinates":[-3.906786,56.02298],"type":"Point"}
}