{
  "type": "Feature",
  "properties": {
    "addr:full":"25 St Peters Street Ipswich Suffolk IP1 1XF",
    "addr:housenumber":"25",
    "addr:postcode":"ip1 1xf",
    "addr:street":"St Peters Street",
    "iso:country":"GB",
    "sg:address":"25 St Peters Street",
    "sg:city":"Ipswich",
    "sg:classifiers":[
        {
            "category":"Shopping",
            "subcategory":"Antiques",
            "type":"Retail Goods"
        },
        {
            "category":"Shopping",
            "subcategory":"Used Merchandise",
            "type":"Retail Goods"
        }
    ],
    "sg:phone":"+44 1473 221057",
    "sg:postcode":"IP1 1XF",
    "sg:province":"Suffolk",
    "sg:tags":[
        "shop",
        "second-hand"
    ],
    "wof:name":"Maud's Attic",
    "wof:placetype":"venue"
},
  "geometry": {"coordinates":[1.1536560059,52.0538978577],"type":"Point"}
}