{
  "type": "Feature",
  "properties": {
    "addr:full":"94 Lansbury Drive Hayes Greater London UB4 8SD",
    "addr:housenumber":"94",
    "addr:postcode":"ub4 8sd",
    "addr:street":"Lansbury Drive",
    "iso:country":"GB",
    "sg:address":"94 Lansbury Drive",
    "sg:city":"Hayes",
    "sg:classifiers":[
        {
            "category":"Home & Garden",
            "subcategory":"Household Appliances",
            "type":"Retail Goods"
        }
    ],
    "sg:postcode":"UB4 8SD",
    "sg:province":"Greater London",
    "sg:tags":[
        "electrical"
    ],
    "wof:name":"Kin's Audio & Tv",
    "wof:placetype":"venue"
},
  "geometry": {"coordinates":[-0.4192920029,51.5260238647],"type":"Point"}
}