{
  "type": "Feature",
  "properties": {
    "iso:country":"GB",
    "sg:address":"10 Arden Road, Broomfield",
    "sg:city":"Herne Bay",
    "sg:classifiers":[
        {
            "category":"Professional",
            "subcategory":"Detective & Security Services",
            "type":"Services"
        }
    ],
    "sg:phone":"+44 1227 364112",
    "sg:postcode":"CT6 7DT",
    "sg:province":"Kent",
    "wof:name":"Optima Alarms Ltd.",
    "wof:placetype":"venue"
},
  "geometry": {"coordinates":[1.145211,51.356606],"type":"Point"}
}