{
  "type": "Feature",
  "properties": {
    "addr:full":"33 Wakefield Road Stalybridge Greater Manchester SK15 1AJ",
    "addr:housenumber":"33",
    "addr:postcode":"sk15 1aj",
    "addr:street":"Wakefield Road",
    "iso:country":"GB",
    "sg:address":"33 Wakefield Road",
    "sg:city":"Stalybridge",
    "sg:classifiers":[
        {
            "category":"Food & Beverages",
            "subcategory":"Fruits & Vegetables",
            "type":"Retail Goods"
        }
    ],
    "sg:phone":"+44 161 303 1080",
    "sg:postcode":"SK15 1AJ",
    "sg:province":"Greater Manchester",
    "sg:tags":[
        "greengrocer"
    ],
    "wof:name":"V & J Wine & Food Store",
    "wof:placetype":"venue"
},
  "geometry": {"coordinates":[-2.0565540791,53.4858398438],"type":"Point"}
}