{
  "type": "Feature",
  "properties": {
    "iso:country":"GB",
    "sg:address":"1 Commerce Road",
    "sg:city":"Brentford",
    "sg:classifiers":[
        {
            "category":"Shopping",
            "subcategory":"Clothing, Apparel, & Fashions",
            "type":"Retail Goods"
        }
    ],
    "sg:phone":"+44 20 8568 6191",
    "sg:postcode":"TW8 8LE",
    "sg:province":"Greater London",
    "sg:tags":[
        "shop",
        "clothing"
    ],
    "wof:name":"India Imports of Rhode Island Ltd.",
    "wof:placetype":"venue"
},
  "geometry": {"coordinates":[-0.3125649989,51.4826126099],"type":"Point"}
}