{
  "type": "Feature",
  "properties": {
    "addr:full":"Snowdon Lodge, Nant Ffrancon, Bethesda Bangor Gwynedd LL57 3LX",
    "addr:postcode":"ll57 3lx",
    "addr:street":"Nant Ffrancon",
    "iso:country":"GB",
    "sg:address":"Snowdon Lodge, Nant Ffrancon, Bethesda",
    "sg:city":"Bangor",
    "sg:classifiers":[
        {
            "category":"Organizations",
            "subcategory":"Non-profit Organization",
            "type":"Services"
        }
    ],
    "sg:phone":"+44 1248 602900",
    "sg:postcode":"LL57 3LX",
    "sg:province":"Gwynedd",
    "sg:tags":[
        "organisation",
        "voluntary",
        "charity"
    ],
    "wof:name":"Life Foundation School of Therapeutics",
    "wof:placetype":"venue"
},
  "geometry": {"coordinates":[-4.062503,53.180202],"type":"Point"}
}