{
  "type": "Feature",
  "properties": {
    "addr:full":"Skinner St Wolverhampton West Midlands WV1 4LD",
    "addr:postcode":"wv1 4ld",
    "addr:street":"Skinner St",
    "iso:country":"GB",
    "sg:address":"Skinner St",
    "sg:city":"Wolverhampton",
    "sg:classifiers":[
        {
            "category":"Home & Garden",
            "subcategory":"Hardware",
            "type":"Retail Goods"
        }
    ],
    "sg:phone":"+44 1902 428388",
    "sg:postcode":"WV1 4LD",
    "sg:province":"West Midlands",
    "sg:tags":[
        "centre",
        "improvement"
    ],
    "wof:name":"Wolvehampton Home & Gardens",
    "wof:placetype":"venue"
},
  "geometry": {"coordinates":[-2.1312539577,52.5843353271],"type":"Point"}
}