{
  "type": "Feature",
  "properties": {
    "addr:full":"21-23 Spittal Street Marlow Berkshire SL7 3HJ",
    "addr:housenumber":"21-23",
    "addr:postcode":"sl7 3hj",
    "addr:street":"Spittal Street",
    "iso:country":"GB",
    "sg:address":"21-23 Spittal Street",
    "sg:city":"Marlow",
    "sg:classifiers":[
        {
            "category":"Shopping",
            "subcategory":"Florist",
            "type":"Retail Goods"
        }
    ],
    "sg:phone":"+44 1628 473334",
    "sg:postcode":"SL7 3HJ",
    "sg:province":"Berkshire",
    "wof:name":"Nash & Sons Florists",
    "wof:placetype":"venue"
},
  "geometry": {"coordinates":[-0.776812,51.572598],"type":"Point"}
}