{
  "type": "Feature",
  "properties": {
    "iso:country":"GB",
    "sg:address":"119 Bunstead, Hursley",
    "sg:city":"Winchester",
    "sg:classifiers":[
        {
            "category":"Building & Trades",
            "subcategory":"Equipment Rental",
            "type":"Services"
        }
    ],
    "sg:phone":"+44 1962 775472",
    "sg:postcode":"SO21 2LQ",
    "sg:province":"Hampshire",
    "sg:tags":[
        "plant",
        "machinery"
    ],
    "wof:name":"Barry Richar Steele",
    "wof:placetype":"venue"
},
  "geometry": {"coordinates":[-1.3621490002,51.0205802917],"type":"Point"}
}