{
  "type": "Feature",
  "properties": {
    "addr:full":"5 Scotshaw Brook Business Park, Branch Road Blackburn Lancashire BB3 0PR",
    "addr:housenumber":"5",
    "addr:postcode":"bb3 0pr",
    "addr:street":"Scotshaw Brook Business Park Branch Road",
    "iso:country":"GB",
    "sg:address":"5 Scotshaw Brook Business Park, Branch Road",
    "sg:city":"Blackburn",
    "sg:classifiers":[
        {
            "category":"Professional",
            "type":"Services"
        }
    ],
    "sg:postcode":"BB3 0PR",
    "sg:province":"Lancashire",
    "sg:tags":[
        "control",
        "system"
    ],
    "wof:name":"M C Drives & Systems Ltd.",
    "wof:placetype":"venue"
},
  "geometry": {"coordinates":[-2.47654,53.721329],"type":"Point"}
}