{
  "type": "Feature",
  "properties": {
    "iso:country":"GB",
    "sg:address":"34 Harborough Road",
    "sg:city":"Northampton",
    "sg:classifiers":[
        {
            "category":"Wholesale",
            "subcategory":"Construction Materials",
            "type":"Manufacturing & Wholesale Goods"
        }
    ],
    "sg:phone":"+44 1604 712700",
    "sg:postcode":"NN5 5DU",
    "sg:province":"Northamptonshire",
    "sg:tags":[
        "lift"
    ],
    "wof:name":"Chevron Lifts Ltd.",
    "wof:placetype":"venue"
},
  "geometry": {"coordinates":[-0.900577,52.260887],"type":"Point"}
}