{
  "type": "Feature",
  "properties": {
    "iso:country":"GB",
    "sg:address":"20 Jay Mews",
    "sg:city":"London",
    "sg:classifiers":[
        {
            "category":"Arts & Performance",
            "subcategory":"Theater",
            "type":"Entertainment"
        }
    ],
    "sg:phone":"+44 20 7581 8515",
    "sg:postcode":"SW7 2EP",
    "sg:province":"Greater London",
    "sg:tags":[
        "theatrical",
        "agency"
    ],
    "wof:name":"Vincent Shaw Associates Ltd.",
    "wof:placetype":"venue"
},
  "geometry": {"coordinates":[-0.179370001,51.500377655],"type":"Point"}
}