{
  "type": "Feature",
  "properties": {
    "addr:full":"4 Castle Crescent, Chirk Wrexham Wrexham LL14 5LY",
    "addr:housenumber":"4",
    "addr:postcode":"ll14 5ly",
    "addr:street":"Castle Crescent",
    "iso:country":"GB",
    "sg:address":"4 Castle Crescent, Chirk",
    "sg:city":"Wrexham",
    "sg:classifiers":[
        {
            "category":"Government",
            "subcategory":"Office",
            "type":"Public Place"
        }
    ],
    "sg:phone":"+44 1691 772596",
    "sg:postcode":"LL14 5LY",
    "sg:province":"Wrexham",
    "sg:tags":[
        "local"
    ],
    "wof:name":"Chirk Town Council",
    "wof:placetype":"venue"
},
  "geometry": {"coordinates":[-3.0600450039,52.9320869446],"type":"Point"}
}