{
  "type": "Feature",
  "properties": {
    "iso:country":"GB",
    "sg:address":"Unit 5 Station Court, Park Mill Way, Clayton West",
    "sg:city":"Huddersfield",
    "sg:classifiers":[
        {
            "category":"Shopping",
            "subcategory":"Gifts & Souvenirs",
            "type":"Retail Goods"
        }
    ],
    "sg:phone":"+44 1484 866164",
    "sg:postcode":"HD8 9XJ",
    "sg:province":"South Yorkshire",
    "sg:tags":[
        "watch",
        "clock"
    ],
    "wof:name":"Sinclair Harding (U K) Ltd.",
    "wof:placetype":"venue"
},
  "geometry": {"coordinates":[-1.614015,53.596287],"type":"Point"}
}