{
  "type": "Feature",
  "properties": {
    "iso:country":"GB",
    "sg:address":"1 Rupert Kettle Drive, Bishops Itchington",
    "sg:city":"Southam",
    "sg:classifiers":[
        {
            "category":"Communications",
            "type":"Services"
        }
    ],
    "sg:phone":"+44 1926 613002",
    "sg:postcode":"CV47 2PU",
    "sg:province":"Warwickshire",
    "sg:tags":[
        "audio-visual"
    ],
    "wof:name":"R C A D Multimedia",
    "wof:placetype":"venue"
},
  "geometry": {"coordinates":[-1.429557,52.217766],"type":"Point"}
}