{
  "type": "Feature",
  "properties": {
    "addr:full":"Fabric Cutting Service Only, 7 Sampson Ho, Arterial Rd Basildon Essex SS15 6DR",
    "addr:housenumber":"7",
    "addr:postcode":"ss15 6dr",
    "addr:street":"Sampson Ho Arterial Rd",
    "iso:country":"GB",
    "sg:address":"Fabric Cutting Service Only, 7 Sampson Ho, Arterial Rd",
    "sg:city":"Basildon",
    "sg:classifiers":[
        {
            "category":"Shopping",
            "subcategory":"Clothing, Apparel, & Fashions",
            "type":"Retail Goods"
        }
    ],
    "sg:phone":"+44 1268 541229",
    "sg:postcode":"SS15 6DR",
    "sg:province":"Essex",
    "sg:tags":[
        "clothing",
        "fabric"
    ],
    "wof:name":"Cutting Edge",
    "wof:placetype":"venue"
},
  "geometry": {"coordinates":[0.4445559978,51.5677947998],"type":"Point"}
}