{
  "type": "Feature",
  "properties": {
    "addr:full":"Unit 1c Summit Business Park, Hanworth Road Sunbury-on-thames Surrey TW16 5DB",
    "addr:housenumber":"unit 1c",
    "addr:postcode":"tw16 5db",
    "addr:street":"Summit Business Park Hanworth Road",
    "iso:country":"GB",
    "sg:address":"Unit 1c Summit Business Park, Hanworth Road",
    "sg:city":"Sunbury-on-thames",
    "sg:classifiers":[
        {
            "category":"Government",
            "subcategory":"Post Office",
            "type":"Public Place"
        }
    ],
    "sg:postcode":"TW16 5DB",
    "sg:province":"Surrey",
    "sg:tags":[
        "print",
        "typesetter"
    ],
    "wof:name":"Haywoods by Design",
    "wof:placetype":"venue"
},
  "geometry": {"coordinates":[-0.411769,51.404179],"type":"Point"}
}