{
  "type": "Feature",
  "properties": {
    "iso:country":"GB",
    "sg:address":"1 The Bramley Business Centre, Station Road Bramley",
    "sg:city":"Guildford",
    "sg:classifiers":[
        {
            "category":"Professional",
            "type":"Services"
        }
    ],
    "sg:postcode":"GU5 0AZ",
    "sg:province":"Surrey",
    "sg:tags":[
        "caterer"
    ],
    "wof:name":"Remontant Ltd",
    "wof:placetype":"venue"
},
  "geometry": {"coordinates":[-0.558077,51.194248],"type":"Point"}
}