{
  "type": "Feature",
  "properties": {
    "iso:country":"GB",
    "sg:address":"11 Cardigan Street, Royton",
    "sg:city":"Oldham",
    "sg:classifiers":[
        {
            "category":"Professional",
            "subcategory":"Printing & Photocopies",
            "type":"Services"
        }
    ],
    "sg:phone":"+44 161 633 2118",
    "sg:postcode":"OL2 6RA",
    "sg:province":"Lancashire",
    "sg:tags":[
        "printer"
    ],
    "wof:name":"Butterworth Print Ltd.",
    "wof:placetype":"venue"
},
  "geometry": {"coordinates":[-2.121386,53.56739],"type":"Point"}
}