{
  "type": "Feature",
  "properties": {
    "addr:full":"Unit 27 Laundry Rd, Laundry Rd Industrial Park Ramsgate Kent CT12 4HY",
    "addr:housenumber":"unit",
    "addr:postcode":"ct12 4hy",
    "addr:street":"Laundry;Laundry Rd Industrial Park",
    "iso:country":"GB",
    "sg:address":"Unit 27 Laundry Rd, Laundry Rd Industrial Park",
    "sg:city":"Ramsgate",
    "sg:classifiers":[
        {
            "category":"Education",
            "subcategory":"Special Training",
            "type":"Public Place"
        }
    ],
    "sg:phone":"+44 1843 822870",
    "sg:postcode":"CT12 4HY",
    "sg:province":"Kent",
    "sg:tags":[
        "product",
        "centre"
    ],
    "wof:name":"Eurosafe Training",
    "wof:placetype":"venue"
},
  "geometry": {"coordinates":[1.323964,51.336472],"type":"Point"}
}