{
  "type": "Feature",
  "properties": {
    "iso:country":"GB",
    "sg:address":"Family Centre, 71 Palgrave Road",
    "sg:city":"Sheffield",
    "sg:classifiers":[
        {
            "category":"Organizations",
            "subcategory":"Non-profit Organization",
            "type":"Services"
        }
    ],
    "sg:phone":"+44 114 231 2512",
    "sg:postcode":"S5 8GS",
    "sg:province":"South Yorkshire",
    "sg:tags":[
        "organisation",
        "voluntary",
        "charity"
    ],
    "wof:name":"N C H Action for Children",
    "wof:placetype":"venue"
},
  "geometry": {"coordinates":[-1.48782,53.421589],"type":"Point"}
}