{
  "type": "Feature",
  "properties": {
    "addr:full":"The Green House, 19-27 Shaw Street St Helens Merseyside WA10 1DF",
    "addr:housenumber":"19-27",
    "addr:postcode":"wa10 1df",
    "addr:street":"Shaw Street",
    "iso:country":"GB",
    "sg:address":"The Green House, 19-27 Shaw Street",
    "sg:city":"St Helens",
    "sg:classifiers":[
        {
            "category":"Professional",
            "subcategory":"Engineering",
            "type":"Services"
        }
    ],
    "sg:phone":"+44 1744 739396",
    "sg:postcode":"WA10 1DF",
    "sg:province":"Merseyside",
    "sg:tags":[
        "consulting",
        "engineer"
    ],
    "wof:name":"The Groundwork Trust Ltd.",
    "wof:placetype":"venue"
},
  "geometry": {"coordinates":[-2.7310190201,53.4522399902],"type":"Point"}
}