{
  "type": "Feature",
  "properties": {
    "iso:country":"GB",
    "sg:address":"17-18 Upper Dock Street",
    "sg:city":"Newport",
    "sg:classifiers":[
        {
            "category":"Shopping",
            "subcategory":"Bicycles & Sporting Goods",
            "type":"Retail Goods"
        },
        {
            "category":"Sports & Exercise",
            "subcategory":"Sports Center",
            "type":"Entertainment"
        }
    ],
    "sg:phone":"+44 1633 264026",
    "sg:postcode":"NP20 1DH",
    "sg:province":"Newport",
    "sg:tags":[
        "shop",
        "sale"
    ],
    "wof:name":"Sport Sales",
    "wof:placetype":"venue"
},
  "geometry": {"coordinates":[-2.9954528809,51.5882339478],"type":"Point"}
}