{
  "type": "Feature",
  "properties": {
    "iso:country":"GB",
    "sg:address":"22 Kindleton, Great Linford",
    "sg:city":"Milton Keynes",
    "sg:classifiers":[
        {
            "category":"Professional",
            "type":"Services"
        }
    ],
    "sg:phone":"+44 1908 690023",
    "sg:postcode":"MK14 5EA",
    "sg:province":"Buckinghamshire",
    "sg:tags":[
        "entertainer"
    ],
    "wof:name":"Apple Jack the Clown",
    "wof:placetype":"venue"
},
  "geometry": {"coordinates":[-0.750123,52.066967],"type":"Point"}
}