{
  "type": "Feature",
  "properties": {
    "iso:country":"GB",
    "sg:address":"Unit 2 Blind Pond Indust Est, Bow Brickhill Rd",
    "sg:city":"Milton Keynes",
    "sg:classifiers":[
        {
            "category":"Retail",
            "subcategory":"Auto Repair",
            "type":"Services"
        }
    ],
    "sg:phone":"+44 1908 366932",
    "sg:postcode":"MK17 9JL",
    "sg:province":"Bedfordshire",
    "sg:tags":[
        "engine",
        "car",
        "specialist"
    ],
    "wof:name":"Car Tuning",
    "wof:placetype":"venue"
},
  "geometry": {"coordinates":[-0.681679,52.002537],"type":"Point"}
}