{
  "type": "Feature",
  "properties": {
    "addr:full":"14 Fox St Treharris Caerphilly CF46 5HE",
    "addr:housenumber":"14",
    "addr:postcode":"cf46 5he",
    "addr:street":"Fox St",
    "iso:country":"GB",
    "sg:address":"14 Fox St",
    "sg:city":"Treharris",
    "sg:classifiers":[
        {
            "category":"Banks & Credit Unions",
            "subcategory":"Bank",
            "type":"Services"
        }
    ],
    "sg:phone":"+44 1443 412550",
    "sg:postcode":"CF46 5HE",
    "sg:province":"Caerphilly",
    "sg:tags":[
        "broker",
        "mortgage"
    ],
    "wof:name":"The Cathedral Group",
    "wof:placetype":"venue"
},
  "geometry": {"coordinates":[-3.304038,51.665451],"type":"Point"}
}