{
  "type": "Feature",
  "properties": {
    "addr:full":"1 Church Road, Codsall Wolverhampton Shropshire WV8 1EA",
    "addr:housenumber":"1",
    "addr:postcode":"wv8 1ea",
    "addr:street":"Church Road",
    "iso:country":"GB",
    "sg:address":"1 Church Road, Codsall",
    "sg:city":"Wolverhampton",
    "sg:classifiers":[
        {
            "category":"Shopping",
            "subcategory":"Gifts & Souvenirs",
            "type":"Retail Goods"
        }
    ],
    "sg:phone":"+44 1902 845562",
    "sg:postcode":"WV8 1EA",
    "sg:province":"Shropshire",
    "sg:tags":[
        "shop"
    ],
    "wof:name":"Flappers",
    "wof:placetype":"venue"
},
  "geometry": {"coordinates":[-2.200419,52.631187],"type":"Point"}
}