{
  "type": "Feature",
  "properties": {
    "iso:country":"GB",
    "sg:address":"4-5 High Street, Goring-on-thames",
    "sg:city":"Reading",
    "sg:classifiers":[
        {
            "category":"Real Estate",
            "subcategory":"Real Estate Agent",
            "type":"Services"
        }
    ],
    "sg:phone":"+44 1491 875011",
    "sg:postcode":"RG8 9AT",
    "sg:province":"Berkshire",
    "wof:name":"Warmingham & Co",
    "wof:placetype":"venue"
},
  "geometry": {"coordinates":[-1.13737,51.522537],"type":"Point"}
}