{
  "type": "Feature",
  "properties": {
    "addr:full":"Waungron Road Cardiff Cardiff CF5 2JL",
    "addr:postcode":"cf5 2jl",
    "addr:street":"Waungron Road",
    "iso:country":"GB",
    "sg:address":"Waungron Road",
    "sg:city":"Cardiff",
    "sg:classifiers":[
        {
            "category":"Shopping",
            "subcategory":"News",
            "type":"Retail Goods"
        }
    ],
    "sg:phone":"+44 29 2056 1619",
    "sg:postcode":"CF5 2JL",
    "sg:province":"Cardiff",
    "sg:tags":[
        "newsagent"
    ],
    "wof:name":"The Cabin",
    "wof:placetype":"venue"
},
  "geometry": {"coordinates":[-3.2268159389,51.4884376526],"type":"Point"}
}