{
  "type": "Feature",
  "properties": {
    "addr:full":"Tilford House, Farnham Business Park, Weydon Lane Farnham Surrey GU9 8QT",
    "addr:postcode":"gu9 8qt",
    "addr:street":"Farnham Business Park Weydon Lane",
    "iso:country":"GB",
    "sg:address":"Tilford House, Farnham Business Park, Weydon Lane",
    "sg:city":"Farnham",
    "sg:classifiers":[
        {
            "category":"Professional",
            "subcategory":"Computer Services",
            "type":"Services"
        }
    ],
    "sg:phone":"+44 1252 732100",
    "sg:postcode":"GU9 8QT",
    "sg:province":"Surrey",
    "sg:tags":[
        "system",
        "software"
    ],
    "wof:name":"Abb Forstar Ltd",
    "wof:placetype":"venue"
},
  "geometry": {"coordinates":[-0.800837,51.214321],"type":"Point"}
}