{
  "type": "Feature",
  "properties": {
    "addr:full":"111-115 Cavendish Street Keighley West Yorkshire BD21 3DG",
    "addr:housenumber":"111-115",
    "addr:postcode":"bd21 3dg",
    "addr:street":"Cavendish Street",
    "iso:country":"GB",
    "sg:address":"111-115 Cavendish Street",
    "sg:city":"Keighley",
    "sg:classifiers":[
        {
            "category":"Home & Garden",
            "subcategory":"Building Materials",
            "type":"Retail Goods"
        }
    ],
    "sg:phone":"+44 1535 664578",
    "sg:postcode":"BD21 3DG",
    "sg:province":"West Yorkshire",
    "sg:tags":[
        "furnishers",
        "bathroom",
        "planner"
    ],
    "wof:name":"Regal Interiors",
    "wof:placetype":"venue"
},
  "geometry": {"coordinates":[-1.908121,53.868164],"type":"Point"}
}