{
  "type": "Feature",
  "properties": {
    "addr:full":"Dene Road, Cotford St Luke Taunton Devon TA4 1DB",
    "addr:postcode":"ta4 1db",
    "addr:street":"Dene Road",
    "iso:country":"GB",
    "sg:address":"Dene Road, Cotford St Luke",
    "sg:city":"Taunton",
    "sg:classifiers":[
        {
            "category":"Health Services",
            "subcategory":"Hospital",
            "type":"Services"
        }
    ],
    "sg:phone":"+44 1823 432211",
    "sg:postcode":"TA4 1DB",
    "sg:province":"Devon",
    "wof:name":"Orchard Lodge Young Peoples Unit",
    "wof:placetype":"venue"
},
  "geometry": {"coordinates":[-3.183405,51.041481],"type":"Point"}
}