{
  "type": "Feature",
  "properties": {
    "addr:full":"Hodder Lane, Emerson Valley Milton Keynes Buckinghamshire MK4 2JR",
    "addr:postcode":"mk4 2jr",
    "addr:street":"Hodder Lane",
    "iso:country":"GB",
    "sg:address":"Hodder Lane, Emerson Valley",
    "sg:city":"Milton Keynes",
    "sg:classifiers":[
        {
            "category":"Education",
            "subcategory":"School",
            "type":"Public Place"
        }
    ],
    "sg:phone":"+44 1908 507914",
    "sg:postcode":"MK4 2JR",
    "sg:province":"Buckinghamshire",
    "sg:tags":[
        "local",
        "authority"
    ],
    "wof:name":"Emerson Valley School",
    "wof:placetype":"venue"
},
  "geometry": {"coordinates":[-0.772105,52.006241],"type":"Point"}
}