{
  "type": "Feature",
  "properties": {
    "addr:full":"26 Goward Street Market Harborough Leicestershire LE16 9AF",
    "addr:housenumber":"26",
    "addr:postcode":"le16 9af",
    "addr:street":"Goward Street",
    "iso:country":"GB",
    "sg:address":"26 Goward Street",
    "sg:city":"Market Harborough",
    "sg:classifiers":[
        {
            "category":"Personal",
            "subcategory":"Beauty Salon",
            "type":"Services"
        },
        {
            "category":"Personal",
            "subcategory":"Barber",
            "type":"Services"
        }
    ],
    "sg:phone":"+44 1858 462633",
    "sg:postcode":"LE16 9AF",
    "sg:province":"Leicestershire",
    "sg:tags":[
        "unisex",
        "hairdresser"
    ],
    "wof:name":"A Cut Above",
    "wof:placetype":"venue"
},
  "geometry": {"coordinates":[-0.925843,52.478539],"type":"Point"}
}