{
  "type": "Feature",
  "properties": {
    "addr:full":"2/4 Southgate Chichester West Sussex PO19 2DJ",
    "addr:housenumber":"2 / 4",
    "addr:postcode":"po19 2dj",
    "addr:street":"Southgate Chichester",
    "iso:country":"GB",
    "sg:address":"2/4 Southgate",
    "sg:city":"Chichester",
    "sg:classifiers":[
        {
            "category":"Retail",
            "subcategory":"Auto Repair",
            "type":"Services"
        }
    ],
    "sg:postcode":"PO19 2DJ",
    "sg:province":"West Sussex",
    "sg:tags":[
        "engine",
        "car",
        "specialist"
    ],
    "wof:name":"Greenpower",
    "wof:placetype":"venue"
},
  "geometry": {"coordinates":[-0.7801290154,50.8332481384],"type":"Point"}
}