{
  "type": "Feature",
  "properties": {
    "iso:country":"GB",
    "sg:address":"Shepherds Way",
    "sg:city":"Maidstone",
    "sg:classifiers":[
        {
            "category":"Government",
            "subcategory":"Post Office",
            "type":"Public Place"
        }
    ],
    "sg:phone":"+44 1622 863435",
    "sg:postcode":"ME17 3LJ",
    "sg:province":"Kent",
    "wof:name":"Shepherds Way Post Office",
    "wof:placetype":"venue"
},
  "geometry": {"coordinates":[0.5936149955,51.2348632812],"type":"Point"}
}