{
  "type": "Feature",
  "properties": {
    "iso:country":"GB",
    "sg:address":"22 West High St",
    "sg:city":"Forfar",
    "sg:classifiers":[
        {
            "category":"Insurance",
            "subcategory":"Insurance Agent",
            "type":"Services"
        }
    ],
    "sg:phone":"+44 1307 462529",
    "sg:postcode":"DD8 1BA",
    "sg:province":"Angus",
    "sg:tags":[
        "broker"
    ],
    "wof:name":"Angus Insurance Brokers Ltd",
    "wof:placetype":"venue"
},
  "geometry": {"coordinates":[-2.889446,56.644127],"type":"Point"}
}