{
  "type": "Feature",
  "properties": {
    "addr:full":"Southfield Nurseries, Redmarley Road Newent Gloucestershire GL18 1DR",
    "addr:postcode":"gl18 1dr",
    "addr:street":"Redmarley Road",
    "iso:country":"GB",
    "sg:address":"Southfield Nurseries, Redmarley Road",
    "sg:city":"Newent",
    "sg:classifiers":[
        {
            "category":"Food & Beverages",
            "subcategory":"Farmers Market",
            "type":"Retail Goods"
        }
    ],
    "sg:postcode":"GL18 1DR",
    "sg:province":"Gloucestershire",
    "sg:tags":[
        "gardener"
    ],
    "wof:name":"V G & P K Bennett",
    "wof:placetype":"venue"
},
  "geometry": {"coordinates":[-2.4061338902,51.9308280945],"type":"Point"}
}