{
  "type": "Feature",
  "properties": {
    "iso:country":"GB",
    "sg:address":"8-16 Peel Road",
    "sg:city":"Wembley",
    "sg:classifiers":[
        {
            "category":"Retail",
            "subcategory":"Auto Repair",
            "type":"Services"
        }
    ],
    "sg:phone":"+44 20 8904 3432",
    "sg:postcode":"HA9 7LU",
    "sg:province":"Greater London",
    "sg:tags":[
        "modification",
        "garage",
        "related"
    ],
    "wof:name":"Car Clinic",
    "wof:placetype":"venue"
},
  "geometry": {"coordinates":[-0.304819,51.563099],"type":"Point"}
}