{
  "type": "Feature",
  "properties": {
    "iso:country":"GB",
    "sg:address":"The Co-op Centre, 11 Mowll Street",
    "sg:city":"London",
    "sg:classifiers":[
        {
            "category":"Social Services",
            "type":"Services"
        }
    ],
    "sg:phone":"+44 20 7735 7700",
    "sg:postcode":"SW9 6BG",
    "sg:province":"Greater London",
    "wof:name":"Choices Independent Living & Community Support Service",
    "wof:placetype":"venue"
},
  "geometry": {"coordinates":[-0.113476,51.477627],"type":"Point"}
}