{
  "type": "Feature",
  "properties": {
    "addr:full":"Unit 12 Shifnal Industrial Estate, Lamledge Lane Shifnal Shropshire TF11 8SD",
    "addr:housenumber":"unit 12",
    "addr:postcode":"tf11 8sd",
    "addr:street":"Industrial Estate Lamledge Lane",
    "iso:country":"GB",
    "sg:address":"Unit 12 Shifnal Industrial Estate, Lamledge Lane",
    "sg:city":"Shifnal",
    "sg:classifiers":[
        {
            "category":"Wholesale",
            "subcategory":"Scrap",
            "type":"Manufacturing & Wholesale Goods"
        }
    ],
    "sg:postcode":"TF11 8SD",
    "sg:province":"Shropshire",
    "sg:tags":[
        "breaker",
        "dismantlers"
    ],
    "wof:name":"I B Dismantlers",
    "wof:placetype":"venue"
},
  "geometry": {"coordinates":[-2.3727788925,52.6654853821],"type":"Point"}
}