{
  "type": "Feature",
  "properties": {
    "iso:country":"GB",
    "sg:address":"The Shop",
    "sg:city":"Isle Of Lewis",
    "sg:classifiers":[
        {
            "category":"Food & Beverages",
            "subcategory":"Supermarket",
            "type":"Retail Goods"
        }
    ],
    "sg:phone":"+44 1851 612282",
    "sg:postcode":"HS2 9LP",
    "sg:province":"Eilean Siar",
    "wof:name":"William W Johnston",
    "wof:placetype":"venue"
},
  "geometry": {"coordinates":[-6.82991,58.202358],"type":"Point"}
}