{
  "type": "Feature",
  "properties": {
    "iso:country":"GB",
    "sg:address":"Unit 8-9 Crawford Industrial Estate, Crawford Street",
    "sg:city":"Newport",
    "sg:classifiers":[
        {
            "category":"Autos & Motor Vehicles",
            "subcategory":"Auto Supplies",
            "type":"Retail Goods"
        }
    ],
    "sg:postcode":"NP19 7AY",
    "sg:province":"Newport",
    "sg:tags":[
        "part",
        "motorcycle",
        "accessory"
    ],
    "wof:name":"Rebb's Custom Motorcycle International",
    "wof:placetype":"venue"
},
  "geometry": {"coordinates":[-2.9882569313,51.5910491943],"type":"Point"}
}