{
  "type": "Feature",
  "properties": {
    "iso:country":"GB",
    "sg:address":"21 Robert Tressell Close",
    "sg:city":"Hastings",
    "sg:classifiers":[
        {
            "category":"Personal",
            "subcategory":"Psychics & Astrologers",
            "type":"Services"
        }
    ],
    "sg:postcode":"TN34 1UP",
    "sg:province":"East Sussex",
    "wof:name":"Erehon Astrology",
    "wof:placetype":"venue"
},
  "geometry": {"coordinates":[0.575396,50.863506],"type":"Point"}
}