{
  "type": "Feature",
  "properties": {
    "iso:country":"GB",
    "sg:address":"4 Keswick Green",
    "sg:city":"Leamington Spa",
    "sg:classifiers":[
        {
            "category":"Utilities",
            "type":"Services"
        }
    ],
    "sg:phone":"+44 1926 770191",
    "sg:postcode":"CV32 6NA",
    "sg:province":"Warwickshire",
    "sg:tags":[
        "internet"
    ],
    "wof:name":"Imagenet (Bristol) Ltd",
    "wof:placetype":"venue"
},
  "geometry": {"coordinates":[-1.5508350134,52.2935371399],"type":"Point"}
}