{
  "type": "Feature",
  "properties": {
    "addr:full":"113 Great North Road, New Barnet Barnet Hertfordshire EN5 1AW",
    "addr:housenumber":"113",
    "addr:postcode":"en5 1aw",
    "addr:street":"Great North Road",
    "iso:country":"GB",
    "sg:address":"113 Great North Road, New Barnet",
    "sg:city":"Barnet",
    "sg:classifiers":[
        {
            "category":"Autos & Motor Vehicles",
            "subcategory":"Automobile Sales",
            "type":"Retail Goods"
        }
    ],
    "sg:phone":"+44 20 8449 6489",
    "sg:postcode":"EN5 1AW",
    "sg:province":"Hertfordshire",
    "sg:tags":[
        "car"
    ],
    "wof:name":"Company Car Consultancy",
    "wof:placetype":"venue"
},
  "geometry": {"coordinates":[-0.1816390008,51.6420211792],"type":"Point"}
}