{
  "type": "Feature",
  "properties": {
    "addr:full":"Rabart House, Pontsarn Road Merthyr Tydfil Caerphilly CF48 2SR",
    "addr:postcode":"cf48 2sr",
    "addr:street":"Pontsarn Road",
    "iso:country":"GB",
    "sg:address":"Rabart House, Pontsarn Road",
    "sg:city":"Merthyr Tydfil",
    "sg:classifiers":[
        {
            "category":"Professional",
            "subcategory":"Accounting & Tax Preparation",
            "type":"Services"
        }
    ],
    "sg:postcode":"CF48 2SR",
    "sg:province":"Caerphilly",
    "sg:tags":[
        "accountant"
    ],
    "wof:name":"Martin Howell & Co",
    "wof:placetype":"venue"
},
  "geometry": {"coordinates":[-3.3832840919,51.7756614685],"type":"Point"}
}