{
  "type": "Feature",
  "properties": {
    "addr:full":"Bryanston Street London Greater London W1H 7AA",
    "addr:postcode":"w1h 7aa",
    "addr:street":"Bryanston Street",
    "iso:country":"GB",
    "sg:address":"Bryanston Street",
    "sg:city":"London",
    "sg:classifiers":[
        {
            "category":"Banks & Credit Unions",
            "subcategory":"Bank",
            "type":"Services"
        }
    ],
    "sg:phone":"+44 20 7563 3300",
    "sg:postcode":"W1H 7AA",
    "sg:province":"Greater London",
    "wof:name":"Ruesch International Ltd.",
    "wof:placetype":"venue"
},
  "geometry": {"coordinates":[-0.1572040021,51.5144004822],"type":"Point"}
}