{
  "type": "Feature",
  "properties": {
    "iso:country":"GB",
    "sg:address":"Leach Farm, Swaindrod Lane",
    "sg:city":"Littleborough",
    "sg:classifiers":[
        {
            "category":"Recreation",
            "subcategory":"Campground",
            "type":"Entertainment"
        }
    ],
    "sg:phone":"+44 1706 377061",
    "sg:postcode":"OL15 0LE",
    "sg:province":"Lancashire",
    "sg:tags":[
        "holiday",
        "centre",
        "camp"
    ],
    "wof:name":"South Pennine Trail Centre",
    "wof:placetype":"venue"
},
  "geometry": {"coordinates":[-2.0969130993,53.643787384],"type":"Point"}
}