{
  "type": "Feature",
  "properties": {
    "iso:country":"GB",
    "sg:address":"39 Crescent Road",
    "sg:city":"Windermere",
    "sg:classifiers":[
        {
            "category":"Travel",
            "subcategory":"Travel Agent",
            "type":"Entertainment"
        }
    ],
    "sg:phone":"+44 15394 46152",
    "sg:postcode":"LA23 1BL",
    "sg:province":"Cumbria",
    "wof:name":"Westmorland Travel",
    "wof:placetype":"venue"
},
  "geometry": {"coordinates":[-2.90564,54.377659],"type":"Point"}
}