{
  "type": "Feature",
  "properties": {
    "addr:full":"3a Appledore Ct, Hildenborough Cres Maidstone Kent ME16 0PA",
    "addr:housenumber":"3a",
    "addr:postcode":"me16 0pa",
    "addr:street":"Appledore Ct;Cres",
    "iso:country":"GB",
    "sg:address":"3a Appledore Ct, Hildenborough Cres",
    "sg:city":"Maidstone",
    "sg:classifiers":[
        {
            "category":"Food & Beverages",
            "subcategory":"Meat & Fish",
            "type":"Retail Goods"
        }
    ],
    "sg:phone":"+44 1622 757381",
    "sg:postcode":"ME16 0PA",
    "sg:province":"Kent",
    "sg:tags":[
        "butcher"
    ],
    "wof:name":"D Wilkins",
    "wof:placetype":"venue"
},
  "geometry": {"coordinates":[0.497321,51.288055],"type":"Point"}
}