{
  "type": "Feature",
  "properties": {
    "addr:full":"Gamull Lane, Ribbleton Preston Lancashire PR2 6SJ",
    "addr:postcode":"pr2 6sj",
    "addr:street":"Gamull Lane",
    "iso:country":"GB",
    "sg:address":"Gamull Lane, Ribbleton",
    "sg:city":"Preston",
    "sg:classifiers":[
        {
            "category":"Education",
            "subcategory":"School",
            "type":"Public Place"
        }
    ],
    "sg:phone":"+44 1772 700052",
    "sg:postcode":"PR2 6SJ",
    "sg:province":"Lancashire",
    "sg:tags":[
        "local",
        "authority"
    ],
    "wof:name":"St Maria Goretti R C Primary School",
    "wof:placetype":"venue"
},
  "geometry": {"coordinates":[-2.6687889099,53.7689781189],"type":"Point"}
}