{
  "type": "Feature",
  "properties": {
    "addr:full":"Unit 1 Sycamore Industrial Estate, Walkley Lane Heckmondwike West Yorkshire WF16 0NL",
    "addr:housenumber":"unit 1;estate",
    "addr:postcode":"wf16 0nl",
    "addr:street":"Sycamore Industrial;Walkley Lane",
    "iso:country":"GB",
    "sg:address":"Unit 1 Sycamore Industrial Estate, Walkley Lane",
    "sg:city":"Heckmondwike",
    "sg:classifiers":[
        {
            "category":"Professional",
            "subcategory":"Detective & Security Services",
            "type":"Services"
        }
    ],
    "sg:phone":"+44 1924 412666",
    "sg:postcode":"WF16 0NL",
    "sg:province":"West Yorkshire",
    "wof:name":"Amo Security Roller Systems Ltd.",
    "wof:placetype":"venue"
},
  "geometry": {"coordinates":[-1.6775239706,53.7136611938],"type":"Point"}
}