{
  "type": "Feature",
  "properties": {
    "iso:country":"GB",
    "sg:address":"878 Warrington Road",
    "sg:city":"Wigan",
    "sg:classifiers":[
        {
            "category":"Autos & Motor Vehicles",
            "subcategory":"Fuel & Gas Station",
            "type":"Retail Goods"
        }
    ],
    "sg:phone":"+44 1942 823900",
    "sg:postcode":"WN3 6XN",
    "sg:province":"Lancashire",
    "sg:tags":[
        "hr",
        "petrol"
    ],
    "wof:name":"Shell Direct (U K) Ltd.",
    "wof:placetype":"venue"
},
  "geometry": {"coordinates":[-2.6523718834,53.5167121887],"type":"Point"}
}