{
  "type": "Feature",
  "properties": {
    "addr:full":"Dental Surgery, 27 Spring La Manchester Greater Manchester M26 2TQ",
    "addr:housenumber":"27",
    "addr:postcode":"m26 2tq",
    "addr:street":"Spring La Manchester",
    "iso:country":"GB",
    "sg:address":"Dental Surgery, 27 Spring La",
    "sg:city":"Manchester",
    "sg:classifiers":[
        {
            "category":"Health Services",
            "subcategory":"Dentist",
            "type":"Services"
        }
    ],
    "sg:phone":"+44 161 724 8500",
    "sg:postcode":"M26 2TQ",
    "sg:province":"Greater Manchester",
    "wof:name":"G Maclean",
    "wof:placetype":"venue"
},
  "geometry": {"coordinates":[-2.3272500038,53.5629310608],"type":"Point"}
}