{
  "type": "Feature",
  "properties": {
    "addr:full":"Poldark, Polmassick St Austell Cornwall PL26 6HA",
    "addr:postcode":"pl26 6ha",
    "iso:country":"GB",
    "sg:address":"Poldark, Polmassick",
    "sg:city":"St Austell",
    "sg:classifiers":[
        {
            "category":"Professional",
            "subcategory":"Engineering",
            "type":"Services"
        }
    ],
    "sg:phone":"+44 1726 843905",
    "sg:postcode":"PL26 6HA",
    "sg:province":"Cornwall",
    "sg:tags":[
        "civil",
        "engineer"
    ],
    "wof:name":"Johns Plant Hire",
    "wof:placetype":"venue"
},
  "geometry": {"coordinates":[-4.848034,50.275105],"type":"Point"}
}