{
  "type": "Feature",
  "properties": {
    "addr:full":"Duke Nurseries, Shelf Halifax West Yorkshire HX3 7PF",
    "addr:postcode":"hx3 7pf",
    "addr:street":"Shelf;West",
    "iso:country":"GB",
    "sg:address":"Duke Nurseries, Shelf",
    "sg:city":"Halifax",
    "sg:classifiers":[
        {
            "category":"Building & Trades",
            "subcategory":"Landscaping Services",
            "type":"Services"
        }
    ],
    "sg:phone":"+44 1274 677731",
    "sg:postcode":"HX3 7PF",
    "sg:province":"West Yorkshire",
    "sg:tags":[
        "landscape",
        "contractor"
    ],
    "wof:name":"A Ashworth & Son (Landscapes) Ltd.",
    "wof:placetype":"venue"
},
  "geometry": {"coordinates":[-1.816379,53.752666],"type":"Point"}
}