{
  "type": "Feature",
  "properties": {
    "addr:full":"160 Waterloo Road Middlesbrough North Yorkshire TS1 3JB",
    "addr:housenumber":"160",
    "addr:postcode":"ts1 3jb",
    "addr:street":"Waterloo Road",
    "iso:country":"GB",
    "sg:address":"160 Waterloo Road",
    "sg:city":"Middlesbrough",
    "sg:classifiers":[
        {
            "category":"Retail",
            "subcategory":"Laundry & Dry Cleaning",
            "type":"Services"
        }
    ],
    "sg:postcode":"TS1 3JB",
    "sg:province":"North Yorkshire",
    "sg:tags":[
        "launderette"
    ],
    "wof:name":"M Anwar",
    "wof:placetype":"venue"
},
  "geometry": {"coordinates":[-1.230223,54.568474],"type":"Point"}
}