{
  "type": "Feature",
  "properties": {
    "iso:country":"GB",
    "sg:address":"Sandhurst, Grove Green Road, Weavering",
    "sg:city":"Maidstone",
    "sg:classifiers":[
        {
            "category":"Professional",
            "subcategory":"Advertising",
            "type":"Services"
        },
        {
            "category":"Government",
            "subcategory":"Post Office",
            "type":"Public Place"
        }
    ],
    "sg:phone":"+44 1622 736821",
    "sg:postcode":"ME14 5JT",
    "sg:province":"Kent",
    "sg:tags":[
        "mail",
        "direct",
        "provider"
    ],
    "wof:name":"Pickford's Publications",
    "wof:placetype":"venue"
},
  "geometry": {"coordinates":[0.55752,51.274261],"type":"Point"}
}