{
  "type": "Feature",
  "properties": {
    "addr:full":"17 St Andrews Grantham Lincolnshire NG31 9PE",
    "addr:housenumber":"17",
    "addr:postcode":"ng31 9pe",
    "addr:street":"St Andrews Grantham",
    "iso:country":"GB",
    "sg:address":"17 St Andrews",
    "sg:city":"Grantham",
    "sg:classifiers":[
        {
            "category":"Home & Garden",
            "subcategory":"Furniture",
            "type":"Retail Goods"
        }
    ],
    "sg:phone":"+44 1476 573859",
    "sg:postcode":"NG31 9PE",
    "sg:province":"Lincolnshire",
    "wof:name":"Bedroom Designs Grantham",
    "wof:placetype":"venue"
},
  "geometry": {"coordinates":[-0.6252310276,52.9260253906],"type":"Point"}
}