{
  "type": "Feature",
  "properties": {
    "addr:full":"51 Lincolns Inn Fields London Greater London WC2A 3LZ",
    "addr:housenumber":"51",
    "addr:postcode":"wc2a 3lz",
    "addr:street":"Lincolns;Fields",
    "iso:country":"GB",
    "sg:address":"51 Lincolns Inn Fields",
    "sg:city":"London",
    "sg:classifiers":[
        {
            "category":"Professional",
            "subcategory":"Lawyer & Legal Services",
            "type":"Services"
        }
    ],
    "sg:phone":"+44 20 7430 2277",
    "sg:postcode":"WC2A 3LZ",
    "sg:province":"Greater London",
    "sg:tags":[
        "solicitor"
    ],
    "wof:name":"Burton Copeland",
    "wof:placetype":"venue"
},
  "geometry": {"coordinates":[-0.117629,51.515209],"type":"Point"}
}