{
  "type": "Feature",
  "properties": {
    "addr:full":"Wheelright House, Pipe Ridware Rugeley Staffordshire WS15 3QL",
    "addr:postcode":"ws15 3ql",
    "addr:street":"Pipe Ridware",
    "iso:country":"GB",
    "sg:address":"Wheelright House, Pipe Ridware",
    "sg:city":"Rugeley",
    "sg:classifiers":[
        {
            "category":"Arts & Performance",
            "subcategory":"Theater",
            "type":"Entertainment"
        }
    ],
    "sg:phone":"+44 1889 504380",
    "sg:postcode":"WS15 3QL",
    "sg:province":"Staffordshire",
    "sg:tags":[
        "hall",
        "theatre",
        "concert"
    ],
    "wof:name":"Ridware Theatre Trust",
    "wof:placetype":"venue"
},
  "geometry": {"coordinates":[-1.8754440546,52.7553405762],"type":"Point"}
}