{
  "type": "Feature",
  "properties": {
    "addr:full":"30 Wigmore Lane Reading Berkshire RG30 1HY",
    "addr:housenumber":"30",
    "addr:postcode":"rg30 1hy",
    "addr:street":"Wigmore Lane",
    "iso:country":"GB",
    "sg:address":"30 Wigmore Lane",
    "sg:city":"Reading",
    "sg:classifiers":[
        {
            "category":"Home & Garden",
            "subcategory":"Building Materials",
            "type":"Retail Goods"
        },
        {
            "category":"Building & Trades",
            "subcategory":"Construction",
            "type":"Services"
        }
    ],
    "sg:phone":"+44 118 942 3705",
    "sg:postcode":"RG30 1HY",
    "sg:province":"Berkshire",
    "sg:tags":[
        "roofing"
    ],
    "wof:name":"Southern Roofing",
    "wof:placetype":"venue"
},
  "geometry": {"coordinates":[-1.012403965,51.4627952576],"type":"Point"}
}