{
  "type": "Feature",
  "properties": {
    "iso:country":"GB",
    "sg:address":"Oakfield House, Binswood Avenue",
    "sg:city":"Leamington Spa",
    "sg:classifiers":[
        {
            "category":"Organizations",
            "subcategory":"Community Association",
            "type":"Services"
        }
    ],
    "sg:phone":"+44 1926 450008",
    "sg:postcode":"CV32 5RZ",
    "sg:province":"Warwickshire",
    "sg:tags":[
        "society",
        "housing"
    ],
    "wof:name":"Orbit Housing Association",
    "wof:placetype":"venue"
},
  "geometry": {"coordinates":[-1.531954,52.29636],"type":"Point"}
}