{
  "type": "Feature",
  "properties": {
    "addr:full":"2 Gold Street Kettering Northamptonshire NN16 8JA",
    "addr:housenumber":"2",
    "addr:postcode":"nn16 8ja",
    "addr:street":"Gold Street",
    "iso:country":"GB",
    "sg:address":"2 Gold Street",
    "sg:city":"Kettering",
    "sg:classifiers":[
        {
            "category":"Real Estate",
            "subcategory":"Real Estate Agent",
            "type":"Services"
        }
    ],
    "sg:phone":"+44 1536 517003",
    "sg:postcode":"NN16 8JA",
    "sg:province":"Northamptonshire",
    "sg:website":"http://www.parkhouseandpartners.co.uk/",
    "wof:name":"Parkhouse & Partners",
    "wof:placetype":"venue"
},
  "geometry": {"coordinates":[-0.727569,52.400558],"type":"Point"}
}