{
  "type": "Feature",
  "properties": {
    "addr:full":"Unit 62, Atcham Industrial Estate, Upton Magna Shrewsbury Shropshire SY4 4UG",
    "addr:housenumber":"unit 62",
    "addr:postcode":"sy4 4ug",
    "addr:street":"Industrial Estate",
    "iso:country":"GB",
    "sg:address":"Unit 62, Atcham Industrial Estate, Upton Magna",
    "sg:city":"Shrewsbury",
    "sg:classifiers":[
        {
            "category":"Government",
            "subcategory":"Fire Station",
            "type":"Public Place"
        }
    ],
    "sg:phone":"+44 1743 761186",
    "sg:postcode":"SY4 4UG",
    "sg:province":"Shropshire",
    "sg:tags":[
        "security"
    ],
    "wof:name":"Modern Fire Extinguisher Services Ltd.",
    "wof:placetype":"venue"
},
  "geometry": {"coordinates":[-2.636718,52.68829],"type":"Point"}
}