{
  "type": "Feature",
  "properties": {
    "addr:full":"Clayford Farm, Clayford Wimborne Dorset BH21 7BJ",
    "addr:postcode":"bh21 7bj",
    "iso:country":"GB",
    "sg:address":"Clayford Farm, Clayford",
    "sg:city":"Wimborne",
    "sg:classifiers":[
        {
            "category":"Farming",
            "subcategory":"Poultry Farm",
            "type":"Manufacturing & Wholesale Goods"
        }
    ],
    "sg:phone":"+44 1202 894221",
    "sg:postcode":"BH21 7BJ",
    "sg:province":"Dorset",
    "sg:tags":[
        "game"
    ],
    "wof:name":"Europoul",
    "wof:placetype":"venue"
},
  "geometry": {"coordinates":[-1.988709,50.802235],"type":"Point"}
}