{
  "type": "Feature",
  "properties": {
    "addr:full":"Ingleside, 190 Ashby Road Loughborough Leicestershire LE11 3AG",
    "addr:housenumber":"190",
    "addr:postcode":"le11 3ag",
    "addr:street":"Ashby Road",
    "iso:country":"GB",
    "sg:address":"Ingleside, 190 Ashby Road",
    "sg:city":"Loughborough",
    "sg:classifiers":[
        {
            "category":"Social Services",
            "subcategory":"Adult Care",
            "type":"Services"
        }
    ],
    "sg:phone":"+44 1509 212888",
    "sg:postcode":"LE11 3AG",
    "sg:province":"Leicestershire",
    "sg:tags":[
        "housing",
        "sheltered"
    ],
    "wof:name":"Abbeyfield Loughborough Society",
    "wof:placetype":"venue"
},
  "geometry": {"coordinates":[-1.223474,52.768524],"type":"Point"}
}