{
  "type": "Feature",
  "properties": {
    "iso:country":"GB",
    "sg:address":"Unit D1, Salcombe Road",
    "sg:city":"Alfreton",
    "sg:classifiers":[
        {
            "category":"Utilities",
            "subcategory":"Mobile Phone",
            "type":"Services"
        }
    ],
    "sg:phone":"+44 1773 520033",
    "sg:postcode":"DE55 7RG",
    "sg:province":"Derbyshire",
    "sg:tags":[
        "battery",
        "servicing"
    ],
    "wof:name":"Motive Power Service",
    "wof:placetype":"venue"
},
  "geometry": {"coordinates":[-1.3751289845,53.1016387939],"type":"Point"}
}