{
  "type": "Feature",
  "properties": {
    "iso:country":"GB",
    "sg:address":"10 Headland Clo",
    "sg:city":"Chesterfield",
    "sg:classifiers":[
        {
            "category":"Professional",
            "subcategory":"Employment Agencies",
            "type":"Services"
        }
    ],
    "sg:phone":"+44 1246 556948",
    "sg:postcode":"S43 1QU",
    "sg:province":"Derbyshire",
    "sg:tags":[
        "consultant"
    ],
    "wof:name":"Frieght Services Employment Agency",
    "wof:placetype":"venue"
},
  "geometry": {"coordinates":[-1.398601,53.255108],"type":"Point"}
}