{
  "type": "Feature",
  "properties": {
    "iso:country":"GB",
    "sg:address":"Ashprington",
    "sg:city":"Totnes",
    "sg:classifiers":[
        {
            "category":"Bars & Pubs",
            "type":"Food & Drink"
        }
    ],
    "sg:phone":"+44 1803 732214",
    "sg:postcode":"TQ9 7EG",
    "sg:province":"Devon",
    "sg:tags":[
        "pubs",
        "inn"
    ],
    "wof:name":"Watermans Arms",
    "wof:placetype":"venue"
},
  "geometry": {"coordinates":[-3.715349,50.37318],"type":"Point"}
}