{
  "type": "Feature",
  "properties": {
    "iso:country":"GB",
    "sg:address":"1214a Warwick Road, Acocks Green",
    "sg:city":"Birmingham",
    "sg:classifiers":[
        {
            "category":"Taxi",
            "type":"Transportation"
        },
        {
            "category":"Military Area",
            "subcategory":"Air Force Base",
            "type":"Public Place"
        }
    ],
    "sg:phone":"+44 121 604 4000",
    "sg:postcode":"B27 6BY",
    "sg:province":"West Midlands",
    "sg:tags":[
        "hire",
        "private"
    ],
    "wof:name":"Blue Circles & Solihull Radio Cars",
    "wof:placetype":"venue"
},
  "geometry": {"coordinates":[-1.815751,52.44511],"type":"Point"}
}