{
  "type": "Feature",
  "properties": {
    "addr:full":"8 Home Ground, Cricklade Swindon Gloucestershire SN6 6JG",
    "addr:housenumber":"8",
    "addr:postcode":"sn6 6jg",
    "addr:street":"Home Ground",
    "iso:country":"GB",
    "sg:address":"8 Home Ground, Cricklade",
    "sg:city":"Swindon",
    "sg:classifiers":[
        {
            "category":"Professional",
            "subcategory":"Computer Services",
            "type":"Services"
        }
    ],
    "sg:phone":"+44 1793 752718",
    "sg:postcode":"SN6 6JG",
    "sg:province":"Gloucestershire",
    "sg:tags":[
        "system",
        "software"
    ],
    "wof:name":"Jade Software Ltd.",
    "wof:placetype":"venue"
},
  "geometry": {"coordinates":[-1.868869,51.643131],"type":"Point"}
}