{
  "type": "Feature",
  "properties": {
    "addr:full":"117a Penycae Road Port Talbot Neath Port Talbot SA13 2EG",
    "addr:housenumber":"117a",
    "addr:postcode":"sa13 2eg",
    "addr:street":"Penycae Road",
    "iso:country":"GB",
    "sg:address":"117a Penycae Road",
    "sg:city":"Port Talbot",
    "sg:classifiers":[
        {
            "category":"Building & Trades",
            "subcategory":"Landscaping Services",
            "type":"Services"
        }
    ],
    "sg:postcode":"SA13 2EG",
    "sg:province":"Neath Port Talbot",
    "sg:tags":[
        "forestry",
        "tree"
    ],
    "wof:name":"J Griffiths",
    "wof:placetype":"venue"
},
  "geometry": {"coordinates":[-3.7696619034,51.5923118591],"type":"Point"}
}