{
  "type": "Feature",
  "properties": {
    "iso:country":"GB",
    "sg:address":"Unit 2",
    "sg:city":"Bridport",
    "sg:classifiers":[
        {
            "category":"Home & Garden",
            "subcategory":"Hardware",
            "type":"Retail Goods"
        }
    ],
    "sg:phone":"+44 1308 421904",
    "sg:postcode":"DT6 3EX",
    "sg:province":"Dorset",
    "sg:tags":[
        "lawnmowers",
        "machinery"
    ],
    "wof:name":"Bridport Garden Machinery",
    "wof:placetype":"venue"
},
  "geometry": {"coordinates":[-2.7373890877,50.7455482483],"type":"Point"}
}