{
  "type": "Feature",
  "properties": {
    "addr:full":"120 Rosemount Viaduct Aberdeen Aberdeen City AB25 1NX",
    "addr:housenumber":"120",
    "addr:postcode":"ab25 1nx",
    "addr:street":"Rosemount Viaduct",
    "iso:country":"GB",
    "sg:address":"120 Rosemount Viaduct",
    "sg:city":"Aberdeen",
    "sg:classifiers":[
        {
            "category":"Food & Beverages",
            "subcategory":"Supermarket",
            "type":"Retail Goods"
        }
    ],
    "sg:phone":"+44 1224 641723",
    "sg:postcode":"AB25 1NX",
    "sg:province":"Aberdeen City",
    "wof:name":"Spar",
    "wof:placetype":"venue"
},
  "geometry": {"coordinates":[-2.1103549004,57.1490364075],"type":"Point"}
}