{
  "type": "Feature",
  "properties": {
    "addr:full":"96 Greenall Rd Northwich Cheshire CW9 5RN",
    "addr:housenumber":"96",
    "addr:postcode":"cw9 5rn",
    "addr:street":"Greenall Rd",
    "iso:country":"GB",
    "sg:address":"96 Greenall Rd",
    "sg:city":"Northwich",
    "sg:classifiers":[
        {
            "category":"Social Services",
            "subcategory":"Job Training",
            "type":"Services"
        }
    ],
    "sg:phone":"+44 1606 46143",
    "sg:postcode":"CW9 5RN",
    "sg:province":"Cheshire",
    "sg:tags":[
        "translator",
        "interpreter"
    ],
    "wof:name":"Transfrance",
    "wof:placetype":"venue"
},
  "geometry": {"coordinates":[-2.5002379417,53.2601547241],"type":"Point"}
}