{
  "type": "Feature",
  "properties": {
    "addr:full":"5a Victoria Park Rd Exeter Devon EX2 4NT",
    "addr:housenumber":"5a",
    "addr:postcode":"ex2 4nt",
    "addr:street":"Victoria Park Rd",
    "iso:country":"GB",
    "sg:address":"5a Victoria Park Rd",
    "sg:city":"Exeter",
    "sg:classifiers":[
        {
            "category":"Health Services",
            "subcategory":"Doctor",
            "type":"Services"
        }
    ],
    "sg:phone":"+44 1392 275360",
    "sg:postcode":"EX2 4NT",
    "sg:province":"Devon",
    "sg:tags":[
        "practitioners"
    ],
    "wof:name":"Thomas L Bradbeer FRCS",
    "wof:placetype":"venue"
},
  "geometry": {"coordinates":[-3.5134840012,50.7210121155],"type":"Point"}
}