{
  "type": "Feature",
  "properties": {
    "iso:country":"GB",
    "sg:address":"Garrison Lane",
    "sg:city":"Felixstowe",
    "sg:classifiers":[
        {
            "category":"Freight",
            "type":"Transportation"
        }
    ],
    "sg:phone":"+44 1394 605200",
    "sg:postcode":"IP11 7SH",
    "sg:province":"Suffolk",
    "sg:tags":[
        "forwarders"
    ],
    "wof:name":"Grange Shipping Ltd.",
    "wof:placetype":"venue"
},
  "geometry": {"coordinates":[1.34615,51.966557],"type":"Point"}
}