{
  "type": "Feature",
  "properties": {
    "iso:country":"GB",
    "sg:address":"24 Fairfield Industrial Park, Bill Quay",
    "sg:city":"Gateshead",
    "sg:classifiers":[
        {
            "category":"Building & Trades",
            "subcategory":"Construction",
            "type":"Services"
        }
    ],
    "sg:phone":"+44 191 495 2267",
    "sg:postcode":"NE10 0UR",
    "sg:province":"Tyne and Wear",
    "sg:tags":[
        "paint",
        "household",
        "spraying"
    ],
    "wof:name":"Industrial Finishing Equipment",
    "wof:placetype":"venue"
},
  "geometry": {"coordinates":[-1.5431599617,54.9591712952],"type":"Point"}
}