{
  "type": "Feature",
  "properties": {
    "iso:country":"GB",
    "sg:address":"Unit C49 Enterprise Centre, Brunswick Dock",
    "sg:city":"Liverpool",
    "sg:classifiers":[
        {
            "category":"Cafe",
            "type":"Food & Drink"
        }
    ],
    "sg:phone":"+44 151 707 0728",
    "sg:postcode":"L3 4AR",
    "sg:province":"Merseyside",
    "sg:tags":[
        "tea",
        "room"
    ],
    "wof:name":"Noels",
    "wof:placetype":"venue"
},
  "geometry": {"coordinates":[-2.9827001095,53.3871688843],"type":"Point"}
}