{
  "type": "Feature",
  "properties": {
    "iso:country":"GB",
    "sg:address":"6-7 Church Place",
    "sg:city":"Dumfries",
    "sg:classifiers":[
        {
            "category":"Bars & Pubs",
            "subcategory":"Nightclub",
            "type":"Food & Drink"
        }
    ],
    "sg:phone":"+44 1387 263623",
    "sg:postcode":"DG1 1BW",
    "sg:province":"Dumfries and Galloway",
    "sg:tags":[
        "club",
        "night",
        "activity"
    ],
    "wof:name":"RENEGADE COMMUNICATIONS LTD",
    "wof:placetype":"venue"
},
  "geometry": {"coordinates":[-3.6120760441,55.0704574585],"type":"Point"}
}