{
  "type": "Feature",
  "properties": {
    "iso:country":"GB",
    "sg:address":"259 Gloucester Road, Bishopston",
    "sg:city":"Bristol",
    "sg:classifiers":[
        {
            "category":"Shopping",
            "subcategory":"Books",
            "type":"Retail Goods"
        }
    ],
    "sg:phone":"+44 117 944 5303",
    "sg:postcode":"BS7 8NY",
    "sg:province":"City of Bristol",
    "sg:tags":[
        "bookseller"
    ],
    "wof:name":"Bishopston Books",
    "wof:placetype":"venue"
},
  "geometry": {"coordinates":[-2.589438,51.478577],"type":"Point"}
}