{
  "type": "Feature",
  "properties": {
    "addr:full":"Suite 6 Spain Bldgs, 28 The Spain Petersfield Hampshire GU32 3LA",
    "addr:housenumber":"suite 6;28;spain",
    "addr:postcode":"gu32 3la",
    "addr:street":"Bldgs;The",
    "iso:country":"GB",
    "sg:address":"Suite 6 Spain Bldgs, 28 The Spain",
    "sg:city":"Petersfield",
    "sg:classifiers":[
        {
            "category":"Professional",
            "subcategory":"Management & Consulting",
            "type":"Services"
        }
    ],
    "sg:postcode":"GU32 3LA",
    "sg:province":"Hampshire",
    "sg:tags":[
        "consultant",
        "business"
    ],
    "wof:name":"McHugh,Peter,",
    "wof:placetype":"venue"
},
  "geometry": {"coordinates":[-0.935826,51.003796],"type":"Point"}
}