{
  "type": "Feature",
  "properties": {
    "addr:full":"The Royal Forest Factory Coleford Gloucestershire GL16 8JB",
    "addr:postcode":"gl16 8jb",
    "iso:country":"GB",
    "sg:address":"The Royal Forest Factory",
    "sg:city":"Coleford",
    "sg:classifiers":[
        {
            "category":"Manufacturing",
            "subcategory":"Food",
            "type":"Manufacturing & Wholesale Goods"
        },
        {
            "category":"Shopping",
            "subcategory":"Pharmacy",
            "type":"Retail Goods"
        }
    ],
    "sg:phone":"+44 1594 812800",
    "sg:postcode":"GL16 8JB",
    "sg:province":"Gloucestershire",
    "sg:tags":[
        "mnfr",
        "drink",
        "soft",
        "dispensing",
        "chemist"
    ],
    "wof:name":"Smithkline Beecham (S W G) Ltd.",
    "wof:placetype":"venue"
},
  "geometry": {"coordinates":[-2.612778,51.769199],"type":"Point"}
}