{
  "type": "Feature",
  "properties": {
    "iso:country":"GB",
    "sg:address":"57 St Marys Street",
    "sg:city":"Bridgnorth",
    "sg:classifiers":[
        {
            "category":"Manufacturing",
            "subcategory":"Tools & Machinery",
            "type":"Manufacturing & Wholesale Goods"
        }
    ],
    "sg:phone":"+44 1746 763261",
    "sg:postcode":"WV16 4DR",
    "sg:province":"Shropshire",
    "sg:tags":[
        "design",
        "maker"
    ],
    "wof:name":"P L Jones & Son",
    "wof:placetype":"venue"
},
  "geometry": {"coordinates":[-2.421176,52.535069],"type":"Point"}
}