{
  "type": "Feature",
  "properties": {
    "addr:full":"Hill Road, Watlington Oxford Oxfordshire OX49 5AD",
    "addr:postcode":"ox49 5ad",
    "addr:street":"Hill Road",
    "iso:country":"GB",
    "sg:address":"Hill Road, Watlington",
    "sg:city":"Oxford",
    "sg:classifiers":[
        {
            "category":"Bars & Pubs",
            "type":"Food & Drink"
        }
    ],
    "sg:phone":"+44 1491 613470",
    "sg:postcode":"OX49 5AD",
    "sg:province":"Oxfordshire",
    "sg:tags":[
        "pubs",
        "inn"
    ],
    "wof:name":"The Carriers Arms",
    "wof:placetype":"venue"
},
  "geometry": {"coordinates":[-1.0039399862,51.6448898315],"type":"Point"}
}