{
  "type": "Feature",
  "properties": {
    "iso:country":"GB",
    "sg:address":"The Studio, 125 High Street, South Milford",
    "sg:city":"Leeds",
    "sg:classifiers":[
        {
            "category":"Wholesale",
            "subcategory":"Books, Periodicals, & Newspapers",
            "type":"Manufacturing & Wholesale Goods"
        }
    ],
    "sg:phone":"+44 1937 838070",
    "sg:postcode":"LS25 5AR",
    "sg:province":"North Yorkshire",
    "sg:tags":[
        "publishing"
    ],
    "wof:name":"Splash Holdings Ltd.",
    "wof:placetype":"venue"
},
  "geometry": {"coordinates":[-1.2504199743,53.7788238525],"type":"Point"}
}