{
  "type": "Feature",
  "properties": {
    "addr:full":"89 Watlands View Newcastle Staffordshire ST5 8AG",
    "addr:housenumber":"89",
    "addr:postcode":"st5 8ag",
    "addr:street":"Watlands View",
    "iso:country":"GB",
    "sg:address":"89 Watlands View",
    "sg:city":"Newcastle",
    "sg:classifiers":[
        {
            "category":"Shopping",
            "subcategory":"Florist",
            "type":"Retail Goods"
        }
    ],
    "sg:postcode":"ST5 8AG",
    "sg:province":"Staffordshire",
    "wof:name":"Daisy Chain",
    "wof:placetype":"venue"
},
  "geometry": {"coordinates":[-2.2247,53.034454],"type":"Point"}
}