{
  "type": "Feature",
  "properties": {
    "addr:full":"Anglia House, 22 Rowena Crescent London Greater London SW11 2PT",
    "addr:housenumber":"22",
    "addr:postcode":"sw11 2pt",
    "addr:street":"Rowena Crescent",
    "iso:country":"GB",
    "sg:address":"Anglia House, 22 Rowena Crescent",
    "sg:city":"London",
    "sg:classifiers":[
        {
            "category":"Manufacturing",
            "subcategory":"Tools & Machinery",
            "type":"Manufacturing & Wholesale Goods"
        }
    ],
    "sg:postcode":"SW11 2PT",
    "sg:province":"Greater London",
    "wof:name":"Anglia House Ltd.",
    "wof:placetype":"venue"
},
  "geometry": {"coordinates":[-0.167993,51.470425],"type":"Point"}
}