{
  "type": "Feature",
  "properties": {
    "addr:full":"Unit 6 Cossack Square, Nailsworth Stroud Gloucestershire GL6 0DB",
    "addr:housenumber":"unit 6",
    "addr:postcode":"gl6 0db",
    "addr:street":"Cossack Square",
    "iso:country":"GB",
    "sg:address":"Unit 6 Cossack Square, Nailsworth",
    "sg:city":"Stroud",
    "sg:classifiers":[
        {
            "category":"Building & Trades",
            "subcategory":"Construction",
            "type":"Services"
        }
    ],
    "sg:postcode":"GL6 0DB",
    "sg:province":"Gloucestershire",
    "sg:tags":[
        "ceiling",
        "contractor"
    ],
    "wof:name":"K J Scudamore",
    "wof:placetype":"venue"
},
  "geometry": {"coordinates":[-2.2204389572,51.6938400269],"type":"Point"}
}