{
  "type": "Feature",
  "properties": {
    "iso:country":"GB",
    "sg:address":"7 Lynedoch Street",
    "sg:city":"Glasgow",
    "sg:classifiers":[
        {
            "category":"Real Estate",
            "subcategory":"Architect",
            "type":"Services"
        }
    ],
    "sg:phone":"+44 141 332 5176",
    "sg:postcode":"G3 6EF",
    "sg:province":"Glasgow City",
    "wof:name":"Munro Associates",
    "wof:placetype":"venue"
},
  "geometry": {"coordinates":[-4.27357,55.868481],"type":"Point"}
}