{
  "type": "Feature",
  "properties": {
    "addr:full":"3 South Street Wincanton Somerset BA9 9DH",
    "addr:housenumber":"3",
    "addr:postcode":"ba9 9dh",
    "addr:street":"South Street",
    "iso:country":"GB",
    "sg:address":"3 South Street",
    "sg:city":"Wincanton",
    "sg:classifiers":[
        {
            "category":"Community Center",
            "subcategory":"Social",
            "type":"Public Place"
        }
    ],
    "sg:postcode":"BA9 9DH",
    "sg:province":"Somerset",
    "sg:tags":[
        "frozen",
        "food",
        "freezer",
        "centre"
    ],
    "wof:name":"Fresh & Frozen Centre",
    "wof:placetype":"venue"
},
  "geometry": {"coordinates":[-2.4101,51.05402],"type":"Point"}
}