{
  "type": "Feature",
  "properties": {
    "iso:country":"GB",
    "sg:address":"Marine Activity Centre, North Dock",
    "sg:city":"Sunderland",
    "sg:classifiers":[
        {
            "category":"Arena",
            "subcategory":"Sports Club",
            "type":"Entertainment"
        }
    ],
    "sg:phone":"+44 191 567 5313",
    "sg:postcode":"SR6 0PW",
    "sg:province":"Tyne and Wear",
    "wof:name":"Wear Boating Association",
    "wof:placetype":"venue"
},
  "geometry": {"coordinates":[-1.3674299717,54.9199981689],"type":"Point"}
}