{
  "type": "Feature",
  "properties": {
    "addr:full":"Illeybrook Square Birmingham West Midlands B32 3DD",
    "addr:postcode":"b32 3dd",
    "addr:street":"Square",
    "iso:country":"GB",
    "sg:address":"Illeybrook Square",
    "sg:city":"Birmingham",
    "sg:classifiers":[
        {
            "category":"Bars & Pubs",
            "type":"Food & Drink"
        }
    ],
    "sg:phone":"+44 121 427 9731",
    "sg:postcode":"B32 3DD",
    "sg:province":"West Midlands",
    "sg:tags":[
        "pubs",
        "inn"
    ],
    "wof:name":"Hobsons Choice",
    "wof:placetype":"venue"
},
  "geometry": {"coordinates":[-1.9946490526,52.4420890808],"type":"Point"}
}