{
  "type": "Feature",
  "properties": {
    "addr:full":"538 Lea Bridge Rd London Greater London E10 7DT",
    "addr:housenumber":"538",
    "addr:postcode":"e10 7dt",
    "addr:street":"Lea Bridge Rd",
    "iso:country":"GB",
    "sg:address":"538 Lea Bridge Rd",
    "sg:city":"London",
    "sg:classifiers":[
        {
            "category":"Shopping",
            "type":"Retail Goods"
        }
    ],
    "sg:postcode":"E10 7DT",
    "sg:province":"Greater London",
    "sg:tags":[
        "part",
        "accessory"
    ],
    "wof:name":"Star Motors",
    "wof:placetype":"venue"
},
  "geometry": {"coordinates":[-0.016785,51.572826],"type":"Point"}
}