{
  "type": "Feature",
  "properties": {
    "iso:country":"GB",
    "sg:address":"538 Lea Bridge Rd",
    "sg:city":"London",
    "sg:classifiers":[
        {
            "category":"Shopping",
            "type":"Retail Goods"
        }
    ],
    "sg:postcode":"E10 7DT",
    "sg:province":"Greater London",
    "sg:tags":[
        "part",
        "accessory"
    ],
    "wof:name":"Star Motors",
    "wof:placetype":"venue"
},
  "geometry": {"coordinates":[-0.016785,51.572826],"type":"Point"}
}