{
  "type": "Feature",
  "properties": {
    "addr:full":"Church Office West Avenue, Gosforth Newcastle-upon-tyne Tyne and Wear NE3 4ES",
    "addr:postcode":"ne3 4es",
    "addr:street":"West Avenue",
    "iso:country":"GB",
    "sg:address":"Church Office West Avenue, Gosforth",
    "sg:city":"Newcastle-upon-tyne",
    "sg:classifiers":[
        {
            "category":"Place Of Worship",
            "type":"Public Place"
        }
    ],
    "sg:phone":"+44 191 213 0450",
    "sg:postcode":"NE3 4ES",
    "sg:province":"Tyne and Wear",
    "wof:name":"All Saints Church",
    "wof:placetype":"venue"
},
  "geometry": {"coordinates":[-1.6224399805,55.0047111511],"type":"Point"}
}