{
  "type": "Feature",
  "properties": {
    "iso:country":"GB",
    "sg:address":"23 Market Place, The Martlets",
    "sg:city":"Burgess Hill",
    "sg:classifiers":[
        {
            "category":"Retail",
            "subcategory":"Laundry & Dry Cleaning",
            "type":"Services"
        }
    ],
    "sg:phone":"+44 1444 248206",
    "sg:postcode":"RH15 9NP",
    "sg:province":"East Sussex",
    "sg:tags":[
        "alteration"
    ],
    "wof:name":"Vic Davis Professional Dry Cleaners",
    "wof:placetype":"venue"
},
  "geometry": {"coordinates":[-0.129265,50.954746],"type":"Point"}
}