{
  "type": "Feature",
  "properties": {
    "iso:country":"GB",
    "sg:address":"Balcombe Road",
    "sg:city":"Crawley",
    "sg:classifiers":[
        {
            "category":"Retail",
            "subcategory":"Funeral Services",
            "type":"Services"
        }
    ],
    "sg:phone":"+44 1293 882345",
    "sg:postcode":"RH10 3NQ",
    "sg:province":"Surrey",
    "sg:tags":[
        "cemetery",
        "crematorium"
    ],
    "wof:name":"Surrey & Sussex Crematorium",
    "wof:placetype":"venue"
},
  "geometry": {"coordinates":[-0.146889,51.13464],"type":"Point"}
}