{
  "type": "Feature",
  "properties": {
    "iso:country":"GB",
    "sg:address":"34 Lloyds Ave",
    "sg:city":"Ipswich",
    "sg:classifiers":[
        {
            "category":"Banks & Credit Unions",
            "subcategory":"Bank",
            "type":"Services"
        }
    ],
    "sg:phone":"+44 1473 214884",
    "sg:postcode":"IP1 3HD",
    "sg:province":"Suffolk",
    "wof:name":"Beneficial Ltd",
    "wof:placetype":"venue"
},
  "geometry": {"coordinates":[1.1530419588,52.0582618713],"type":"Point"}
}