{
  "type": "Feature",
  "properties": {
    "addr:full":"79 Springbank Rd Lewisham Greater London SE13 6SS",
    "addr:housenumber":"79",
    "addr:postcode":"se13 6ss",
    "addr:street":"Springbank Rd",
    "iso:country":"GB",
    "sg:address":"79 Springbank Rd",
    "sg:city":"Lewisham",
    "sg:classifiers":[
        {
            "category":"Restaurant",
            "type":"Food & Drink"
        }
    ],
    "sg:phone":"+44 20 8244 2442",
    "sg:postcode":"SE13 6SS",
    "sg:province":"Greater London",
    "sg:tags":[
        "indian"
    ],
    "wof:name":"Bengal Brasserie",
    "wof:placetype":"venue"
},
  "geometry": {"coordinates":[0.000585,51.449654],"type":"Point"}
}