{
  "type": "Feature",
  "properties": {
    "addr:full":"118-120 Great Titchfield Street London Greater London W1W 6SP",
    "addr:housenumber":"118-120",
    "addr:postcode":"w1w 6sp",
    "addr:street":"Great Titchfield Street",
    "iso:country":"GB",
    "sg:address":"118-120 Great Titchfield Street",
    "sg:city":"London",
    "sg:classifiers":[
        {
            "category":"Professional",
            "subcategory":"Printing & Photocopies",
            "type":"Services"
        }
    ],
    "sg:phone":"+44 20 7323 6702",
    "sg:postcode":"W1W 6SP",
    "sg:province":"Greater London",
    "sg:tags":[
        "embroiderer"
    ],
    "wof:name":"Embroidery Techniques Ltd.",
    "wof:placetype":"venue"
},
  "geometry": {"coordinates":[-0.141129002,51.5202636719],"type":"Point"}
}