{
  "type": "Feature",
  "properties": {
    "iso:country":"GB",
    "sg:address":"174 Main Street, Swithland",
    "sg:city":"Loughborough",
    "sg:classifiers":[
        {
            "category":"Bars & Pubs",
            "type":"Food & Drink"
        },
        {
            "category":"Community Center",
            "subcategory":"Social",
            "type":"Public Place"
        }
    ],
    "sg:phone":"+44 1509 890535",
    "sg:postcode":"LE12 8TJ",
    "sg:province":"Leicestershire",
    "sg:tags":[
        "pubs",
        "house",
        "inn",
        "activity"
    ],
    "wof:name":"Griffin Inn",
    "wof:placetype":"venue"
},
  "geometry": {"coordinates":[-1.196529,52.713493],"type":"Point"}
}