{
  "type": "Feature",
  "properties": {
    "addr:full":"Leasowe Road, Moreton Wirral Merseyside CH46 3RD",
    "addr:postcode":"ch46 3rd",
    "addr:street":"Leasowe Road",
    "iso:country":"GB",
    "sg:address":"Leasowe Road, Moreton",
    "sg:city":"Wirral",
    "sg:classifiers":[
        {
            "category":"Sports & Exercise",
            "subcategory":"Golf",
            "type":"Entertainment"
        }
    ],
    "sg:phone":"+44 151 677 5852",
    "sg:postcode":"CH46 3RD",
    "sg:province":"Merseyside",
    "sg:tags":[
        "club",
        "course"
    ],
    "wof:name":"Leasowe Golf Club",
    "wof:placetype":"venue"
},
  "geometry": {"coordinates":[-3.1063139439,53.4167518616],"type":"Point"}
}