{
  "type": "Feature",
  "properties": {
    "addr:full":"6 Church View, Beckingham Doncaster Lincolnshire DN10 4PU",
    "addr:housenumber":"6",
    "addr:postcode":"dn10 4pu",
    "addr:street":"Church View",
    "iso:country":"GB",
    "sg:address":"6 Church View, Beckingham",
    "sg:city":"Doncaster",
    "sg:classifiers":[
        {
            "category":"Building & Trades",
            "subcategory":"Construction",
            "type":"Services"
        }
    ],
    "sg:postcode":"DN10 4PU",
    "sg:province":"Lincolnshire",
    "sg:tags":[
        "builder"
    ],
    "wof:name":"J H Burley Building Contractors",
    "wof:placetype":"venue"
},
  "geometry": {"coordinates":[-0.8296880126,53.4040794373],"type":"Point"}
}