{
  "type": "Feature",
  "properties": {
    "iso:country":"GB",
    "sg:address":"Northern Perimeter Road, London Heathrow Airport",
    "sg:city":"Hounslow",
    "sg:classifiers":[
        {
            "category":"Parking",
            "type":"Transportation"
        },
        {
            "category":"Parking",
            "subcategory":"Bicycle",
            "type":"Transportation"
        }
    ],
    "sg:phone":"+44 20 8564 8811",
    "sg:postcode":"TW6 2RL",
    "sg:province":"Greater London",
    "sg:tags":[
        "car",
        "garaging",
        "park"
    ],
    "wof:name":"Pink Elephant Parking",
    "wof:placetype":"venue"
},
  "geometry": {"coordinates":[-0.433049,51.47945],"type":"Point"}
}