{
  "type": "Feature",
  "properties": {
    "addr:full":"Hill Farm, Bakers Lane Banbury Oxfordshire OX15 5EN",
    "addr:postcode":"ox15 5en",
    "addr:street":"Hill;Bakers Lane",
    "iso:country":"GB",
    "sg:address":"Hill Farm, Bakers Lane",
    "sg:city":"Banbury",
    "sg:classifiers":[
        {
            "category":"Sports & Exercise",
            "subcategory":"Stables",
            "type":"Entertainment"
        }
    ],
    "sg:postcode":"OX15 5EN",
    "sg:province":"Oxfordshire",
    "sg:tags":[
        "education",
        "equestrian"
    ],
    "wof:name":"Hill Farm Stables",
    "wof:placetype":"venue"
},
  "geometry": {"coordinates":[-1.449450016,52.0370597839],"type":"Point"}
}