{
  "type": "Feature",
  "properties": {
    "addr:full":"Powell Duffryn House, Herbert Walker Avenue, Berth 101 Western Docks Southampton Hampshire SO15 1HJ",
    "addr:housenumber":"101",
    "addr:postcode":"so15 1hj",
    "addr:street":"Walker Avenue Berth",
    "iso:country":"GB",
    "sg:address":"Powell Duffryn House, Herbert Walker Avenue, Berth 101 Western Docks",
    "sg:city":"Southampton",
    "sg:classifiers":[
        {
            "category":"Freight",
            "type":"Transportation"
        }
    ],
    "sg:phone":"+44 23 8033 9775",
    "sg:postcode":"SO15 1HJ",
    "sg:province":"Hampshire",
    "sg:tags":[
        "forwarders"
    ],
    "wof:name":"Gibbons Freight Ltd.",
    "wof:placetype":"venue"
},
  "geometry": {"coordinates":[-1.4196289778,50.9056396484],"type":"Point"}
}