{
  "type": "Feature",
  "properties": {
    "addr:full":"Holly Lodge, Newick Lewes East Sussex BN8 4RA",
    "addr:postcode":"bn8 4ra",
    "addr:street":"Newick",
    "iso:country":"GB",
    "sg:address":"Holly Lodge, Newick",
    "sg:city":"Lewes",
    "sg:classifiers":[
        {
            "category":"Wholesale",
            "subcategory":"Meat",
            "type":"Manufacturing & Wholesale Goods"
        },
        {
            "category":"Professional",
            "subcategory":"Business Services",
            "type":"Services"
        },
        {
            "category":"Wholesale",
            "subcategory":"Fruits & Vegetables",
            "type":"Manufacturing & Wholesale Goods"
        }
    ],
    "sg:phone":"+44 1825 723624",
    "sg:postcode":"BN8 4RA",
    "sg:province":"East Sussex",
    "sg:tags":[
        "wholesaler",
        "distribution"
    ],
    "wof:name":"Morgan Fresh Foods",
    "wof:placetype":"venue"
},
  "geometry": {"coordinates":[0.0074049998,50.9729347229],"type":"Point"}
}