{
  "type": "Feature",
  "properties": {
    "addr:full":"25 Guildford Road, Normandy Middlesbrough North Yorkshire TS6 0PZ",
    "addr:housenumber":"25",
    "addr:postcode":"ts6 0pz",
    "addr:street":"Guildford Road",
    "iso:country":"GB",
    "sg:address":"25 Guildford Road, Normandy",
    "sg:city":"Middlesbrough",
    "sg:classifiers":[
        {
            "category":"Building & Trades",
            "subcategory":"Construction",
            "type":"Services"
        }
    ],
    "sg:phone":"+44 1642 461531",
    "sg:postcode":"TS6 0PZ",
    "sg:province":"North Yorkshire",
    "sg:tags":[
        "joiner",
        "carpenter"
    ],
    "wof:name":"Joinery & Building Services",
    "wof:placetype":"venue"
},
  "geometry": {"coordinates":[-1.1535489559,54.5486335754],"type":"Point"}
}