{
  "type": "Feature",
  "properties": {
    "addr:full":"172 Dunkeld Road Perth Perth and Kinross PH1 3XL",
    "addr:housenumber":"172",
    "addr:postcode":"ph1 3xl",
    "addr:street":"Dunkeld Road",
    "iso:country":"GB",
    "sg:address":"172 Dunkeld Road",
    "sg:city":"Perth",
    "sg:classifiers":[
        {
            "category":"Home & Garden",
            "subcategory":"Hardware",
            "type":"Retail Goods"
        }
    ],
    "sg:phone":"+44 1738 630550",
    "sg:postcode":"PH1 3XL",
    "sg:province":"Perth and Kinross",
    "sg:tags":[
        "part",
        "accessory"
    ],
    "wof:name":"Joh R Weir Honda",
    "wof:placetype":"venue"
},
  "geometry": {"coordinates":[-3.4567539692,56.4134902954],"type":"Point"}
}