{
  "type": "Feature",
  "properties": {
    "iso:country":"GB",
    "sg:address":"The Rear Of 1 Howells Avenue",
    "sg:city":"Manchester",
    "sg:classifiers":[
        {
            "category":"Home & Garden",
            "subcategory":"Home Furnishings",
            "type":"Retail Goods"
        }
    ],
    "sg:postcode":"M33 7EU",
    "sg:province":"Cheshire",
    "sg:tags":[
        "homefurnishings"
    ],
    "wof:name":"N T & P R Mackenna",
    "wof:placetype":"venue"
},
  "geometry": {"coordinates":[-2.2488090992,53.4796218872],"type":"Point"}
}