{
  "type": "Feature",
  "properties": {
    "addr:full":"660 High Rd North Finchley Greater London N12 0NL",
    "addr:housenumber":"660",
    "addr:postcode":"n12 0nl",
    "addr:street":"High Rd",
    "iso:country":"GB",
    "sg:address":"660 High Rd",
    "sg:city":"North Finchley",
    "sg:classifiers":[
        {
            "category":"Home & Garden",
            "subcategory":"Household Appliances",
            "type":"Retail Goods"
        }
    ],
    "sg:phone":"+44 20 8445 1515",
    "sg:postcode":"N12 0NL",
    "sg:province":"Greater London",
    "sg:tags":[
        "electrical"
    ],
    "wof:name":"Able Repairs",
    "wof:placetype":"venue"
},
  "geometry": {"coordinates":[-0.1754750013,51.6121025085],"type":"Point"}
}