{
  "type": "Feature",
  "properties": {
    "iso:country":"GB",
    "sg:address":"353 Railway Arches, Laburnum Street",
    "sg:city":"London",
    "sg:classifiers":[
        {
            "category":"Retail",
            "subcategory":"Auto Repair",
            "type":"Services"
        }
    ],
    "sg:phone":"+44 20 7739 0763",
    "sg:postcode":"E2 8BB",
    "sg:province":"Greater London",
    "sg:tags":[
        "modification",
        "garage"
    ],
    "wof:name":"W Auto Care",
    "wof:placetype":"venue"
},
  "geometry": {"coordinates":[-0.07578,51.535042],"type":"Point"}
}