{
  "type": "Feature",
  "properties": {
    "addr:full":"Page Street London Greater London NW7 2EJ",
    "addr:postcode":"nw7 2ej",
    "addr:street":"Page Street",
    "iso:country":"GB",
    "sg:address":"Page Street",
    "sg:city":"London",
    "sg:classifiers":[
        {
            "category":"Arena",
            "subcategory":"Sports Club",
            "type":"Entertainment"
        }
    ],
    "sg:phone":"+44 20 8203 0685",
    "sg:postcode":"NW7 2EJ",
    "sg:province":"Greater London",
    "wof:name":"Mill Hill Rugby Football Club",
    "wof:placetype":"venue"
},
  "geometry": {"coordinates":[-0.233392,51.60984],"type":"Point"}
}