{
  "type": "Feature",
  "properties": {
    "iso:country":"GB",
    "sg:address":"University Of Lancaster, Alexandra Square, Bailrigg",
    "sg:city":"Lancaster",
    "sg:classifiers":[
        {
            "category":"Insurance",
            "subcategory":"Insurance Agent",
            "type":"Services"
        }
    ],
    "sg:phone":"+44 1524 67301",
    "sg:postcode":"LA1 4XX",
    "sg:province":"Lancashire",
    "wof:name":"Endsleigh Insurance Services Ltd.",
    "wof:placetype":"venue"
},
  "geometry": {"coordinates":[-2.796544075,54.017490387],"type":"Point"}
}