{
  "type": "Feature",
  "properties": {
    "addr:full":"Beechings Way Gillingham Kent ME8 6AD",
    "addr:postcode":"me8 6ad",
    "addr:street":"Beechings Way",
    "iso:country":"GB",
    "sg:address":"Beechings Way",
    "sg:city":"Gillingham",
    "sg:classifiers":[
        {
            "category":"Farming",
            "subcategory":"Nursery",
            "type":"Manufacturing & Wholesale Goods"
        }
    ],
    "sg:phone":"+44 1325 460440",
    "sg:postcode":"ME8 6AD",
    "sg:province":"Kent",
    "sg:tags":[
        "creche"
    ],
    "wof:name":"Just Learning Ltd.",
    "wof:placetype":"venue"
},
  "geometry": {"coordinates":[0.578495,51.379314],"type":"Point"}
}