{
  "type": "Feature",
  "properties": {
    "addr:full":"291 Brereton Avenue Cleethorpes Lincolnshire DN35 7QX",
    "addr:housenumber":"291",
    "addr:postcode":"dn35 7qx",
    "addr:street":"Brereton Avenue",
    "iso:country":"GB",
    "sg:address":"291 Brereton Avenue",
    "sg:city":"Cleethorpes",
    "sg:classifiers":[
        {
            "category":"Shopping",
            "subcategory":"Bicycles & Sporting Goods",
            "type":"Retail Goods"
        },
        {
            "category":"Recreation",
            "subcategory":"Fishing",
            "type":"Entertainment"
        }
    ],
    "sg:phone":"+44 1472 602002",
    "sg:postcode":"DN35 7QX",
    "sg:province":"Lincolnshire",
    "sg:tags":[
        "equipment",
        "angling"
    ],
    "wof:name":"Cleethorpes Angling Centre",
    "wof:placetype":"venue"
},
  "geometry": {"coordinates":[-0.0458029993,53.5659599304],"type":"Point"}
}