{
  "type": "Feature",
  "properties": {
    "iso:country":"GB",
    "sg:address":"4th Floor, 98 Cannon Street",
    "sg:city":"London",
    "sg:classifiers":[
        {
            "category":"Manufacturing",
            "subcategory":"Metals",
            "type":"Manufacturing & Wholesale Goods"
        }
    ],
    "sg:phone":"+44 20 7410 4950",
    "sg:postcode":"EC4N 6EN",
    "sg:province":"Greater London",
    "sg:tags":[
        "product",
        "fabricated"
    ],
    "wof:name":"Umicore Finance Uk Ltd.",
    "wof:placetype":"venue"
},
  "geometry": {"coordinates":[-0.08887,51.511223],"type":"Point"}
}