{
  "type": "Feature",
  "properties": {
    "addr:full":"21 Stirling Drive, Thurnby Leicester Leicestershire LE7 9QT",
    "addr:housenumber":"21",
    "addr:postcode":"le7 9qt",
    "addr:street":"Stirling Drive",
    "iso:country":"GB",
    "sg:address":"21 Stirling Drive, Thurnby",
    "sg:city":"Leicester",
    "sg:classifiers":[
        {
            "category":"Professional",
            "type":"Services"
        }
    ],
    "sg:phone":"+44 116 243 4545",
    "sg:postcode":"LE7 9QT",
    "sg:province":"Leicestershire",
    "sg:tags":[
        "writer"
    ],
    "wof:name":"The Finished Article",
    "wof:placetype":"venue"
},
  "geometry": {"coordinates":[-1.042299,52.634857],"type":"Point"}
}