{
  "type": "Feature",
  "properties": {
    "addr:full":"20 New Street Lymington Hampshire SO41 9BQ",
    "addr:housenumber":"20",
    "addr:postcode":"so41 9bq",
    "addr:street":"New Street",
    "iso:country":"GB",
    "sg:address":"20 New Street",
    "sg:city":"Lymington",
    "sg:classifiers":[
        {
            "category":"Banks & Credit Unions",
            "subcategory":"Investment Brokerage",
            "type":"Services"
        },
        {
            "category":"Professional",
            "subcategory":"Business Services",
            "type":"Services"
        }
    ],
    "sg:phone":"+44 1590 677058",
    "sg:postcode":"SO41 9BQ",
    "sg:province":"Hampshire",
    "sg:tags":[
        "property",
        "holding"
    ],
    "wof:name":"Sea Corner Group Ltd.",
    "wof:placetype":"venue"
},
  "geometry": {"coordinates":[-1.54278,50.759701],"type":"Point"}
}