{
  "type": "Feature",
  "properties": {
    "addr:full":"98 Pennsylvania Road Exeter Devon EX4 6DQ",
    "addr:housenumber":"98",
    "addr:postcode":"ex4 6dq",
    "addr:street":"Pennsylvania Road",
    "iso:country":"GB",
    "sg:address":"98 Pennsylvania Road",
    "sg:city":"Exeter",
    "sg:classifiers":[
        {
            "category":"Building & Trades",
            "subcategory":"Construction",
            "type":"Services"
        }
    ],
    "sg:postcode":"EX4 6DQ",
    "sg:province":"Devon",
    "sg:tags":[
        "builder"
    ],
    "wof:name":"Complete Building Services",
    "wof:placetype":"venue"
},
  "geometry": {"coordinates":[-3.5245571136,50.7340164185],"type":"Point"}
}