{
  "type": "Feature",
  "properties": {
    "addr:full":"28 Avenue Road Sandown Isle of Wight PO36 8BN",
    "addr:housenumber":"28",
    "addr:postcode":"po36 8bn",
    "addr:street":"Avenue Road",
    "iso:country":"GB",
    "sg:address":"28 Avenue Road",
    "sg:city":"Sandown",
    "sg:classifiers":[
        {
            "category":"Home & Garden",
            "subcategory":"Building Materials",
            "type":"Retail Goods"
        }
    ],
    "sg:postcode":"PO36 8BN",
    "sg:province":"Isle of Wight",
    "sg:tags":[
        "garage",
        "door"
    ],
    "wof:name":"Steve O'Keeffe",
    "wof:placetype":"venue"
},
  "geometry": {"coordinates":[-1.1502039433,50.6576118469],"type":"Point"}
}