{
  "type": "Feature",
  "properties": {
    "addr:full":"192 High St Harrow Greater London HA3 7AY",
    "addr:housenumber":"192",
    "addr:postcode":"ha3 7ay",
    "addr:street":"High St",
    "iso:country":"GB",
    "sg:address":"192 High St",
    "sg:city":"Harrow",
    "sg:classifiers":[
        {
            "category":"Organizations",
            "subcategory":"Religious Organization",
            "type":"Services"
        }
    ],
    "sg:phone":"+44 20 8427 1541",
    "sg:postcode":"HA3 7AY",
    "sg:province":"Greater London",
    "sg:tags":[
        "organisation"
    ],
    "wof:name":"Sisters Of Our Lady Of The Missions",
    "wof:placetype":"venue"
},
  "geometry": {"coordinates":[-0.337507,51.600147],"type":"Point"}
}