{
  "type": "Feature",
  "properties": {
    "iso:country":"GB",
    "sg:address":"Oriel Farm, Stockton On The Forest",
    "sg:city":"York",
    "sg:classifiers":[
        {
            "category":"Farming",
            "subcategory":"Livestock Farm",
            "type":"Manufacturing & Wholesale Goods"
        }
    ],
    "sg:postcode":"YO32 9UT",
    "sg:province":"North Yorkshire",
    "sg:tags":[
        "others"
    ],
    "wof:name":"Sandy Hill Farm",
    "wof:placetype":"venue"
},
  "geometry": {"coordinates":[-0.9887539744,54.00365448],"type":"Point"}
}