{
  "type": "Feature",
  "properties": {
    "addr:full":"60 Guildford Rd, Ash Aldershot Hampshire GU12 6BT",
    "addr:housenumber":"60",
    "addr:postcode":"gu12 6bt",
    "addr:street":"Guildford Rd",
    "iso:country":"GB",
    "sg:address":"60 Guildford Rd, Ash",
    "sg:city":"Aldershot",
    "sg:classifiers":[
        {
            "category":"Fast Food",
            "type":"Food & Drink"
        }
    ],
    "sg:postcode":"GU12 6BT",
    "sg:province":"Hampshire",
    "sg:tags":[
        "away",
        "take"
    ],
    "wof:name":"Coker,Ronald William,",
    "wof:placetype":"venue"
},
  "geometry": {"coordinates":[-0.7107999921,51.2511863708],"type":"Point"}
}