{
  "type": "Feature",
  "properties": {
    "iso:country":"GB",
    "sg:address":"North Perrece Garage",
    "sg:city":"Bury St Edmunds",
    "sg:classifiers":[
        {
            "category":"Retail",
            "subcategory":"Auto Repair",
            "type":"Services"
        }
    ],
    "sg:phone":"+44 1638 515600",
    "sg:postcode":"IP28 7AA",
    "sg:province":"Cambridgeshire",
    "sg:tags":[
        "modification",
        "garage"
    ],
    "wof:name":"Ultratop Ltd.",
    "wof:placetype":"venue"
},
  "geometry": {"coordinates":[0.51095,52.34602],"type":"Point"}
}