{
  "type": "Feature",
  "properties": {
    "addr:full":"Estuary House, 196 Ballards Road Dagenham Essex RM10 9AB",
    "addr:housenumber":"196",
    "addr:postcode":"rm10 9ab",
    "addr:street":"Ballards Road",
    "iso:country":"GB",
    "sg:address":"Estuary House, 196 Ballards Road",
    "sg:city":"Dagenham",
    "sg:classifiers":[
        {
            "category":"Freight",
            "type":"Transportation"
        }
    ],
    "sg:phone":"+44 20 8595 5039",
    "sg:postcode":"RM10 9AB",
    "sg:province":"Essex",
    "sg:tags":[
        "overseas",
        "shipping",
        "removal"
    ],
    "wof:name":"World Cargo International",
    "wof:placetype":"venue"
},
  "geometry": {"coordinates":[0.15714,51.533649],"type":"Point"}
}