{
  "type": "Feature",
  "properties": {
    "addr:full":"Wimblington Road March Cambridgeshire PE15 0YB",
    "addr:postcode":"pe15 0yb",
    "addr:street":"Wimblington Road",
    "iso:country":"GB",
    "sg:address":"Wimblington Road",
    "sg:city":"March",
    "sg:classifiers":[
        {
            "category":"Parking",
            "type":"Transportation"
        }
    ],
    "sg:phone":"+44 1354 656408",
    "sg:postcode":"PE15 0YB",
    "sg:province":"Cambridgeshire",
    "sg:tags":[
        "car",
        "valet"
    ],
    "wof:name":"Paul's Car Valeting Service",
    "wof:placetype":"venue"
},
  "geometry": {"coordinates":[0.08325,52.523621],"type":"Point"}
}