{
  "type": "Feature",
  "properties": {
    "addr:full":"Magpies, Small Gains Lane Ingatestone Essex CM4 9PR",
    "addr:postcode":"cm4 9pr",
    "addr:street":"Gains Lane",
    "iso:country":"GB",
    "sg:address":"Magpies, Small Gains Lane",
    "sg:city":"Ingatestone",
    "sg:classifiers":[
        {
            "category":"Building & Trades",
            "subcategory":"Plumbing",
            "type":"Services"
        }
    ],
    "sg:phone":"+44 1277 840764",
    "sg:postcode":"CM4 9PR",
    "sg:province":"Essex",
    "sg:tags":[
        "plumber",
        "heating"
    ],
    "wof:name":"B W Henderson",
    "wof:placetype":"venue"
},
  "geometry": {"coordinates":[0.446644,51.653839],"type":"Point"}
}