{
  "type": "Feature",
  "properties": {
    "iso:country":"GB",
    "sg:address":"Bessborough Ho, 17 Cavendish Sq",
    "sg:city":"London",
    "sg:classifiers":[
        {
            "category":"Retail",
            "subcategory":"Event Space",
            "type":"Services"
        }
    ],
    "sg:phone":"+44 20 7665 1838",
    "sg:postcode":"W1G 0PH",
    "sg:province":"Greater London",
    "sg:tags":[
        "exhibition",
        "organiser"
    ],
    "wof:name":"Sales Agency Ltd (The)",
    "wof:placetype":"venue"
},
  "geometry": {"coordinates":[-0.14607,51.516762],"type":"Point"}
}