{
  "type": "Feature",
  "properties": {
    "addr:full":"105 Alexandra Road Swadlincote Derbyshire DE15 0JB",
    "addr:housenumber":"105",
    "addr:postcode":"de15 0jb",
    "addr:street":"Alexandra Road",
    "iso:country":"GB",
    "sg:address":"105 Alexandra Road",
    "sg:city":"Swadlincote",
    "sg:classifiers":[
        {
            "category":"Shopping",
            "subcategory":"News",
            "type":"Retail Goods"
        }
    ],
    "sg:phone":"+44 1283 217959",
    "sg:postcode":"DE15 0JB",
    "sg:province":"Derbyshire",
    "sg:tags":[
        "newsagent"
    ],
    "wof:name":"Hilltop News-Hallams",
    "wof:placetype":"venue"
},
  "geometry": {"coordinates":[-1.559118,52.77002],"type":"Point"}
}