{
  "type": "Feature",
  "properties": {
    "iso:country":"GB",
    "sg:address":"2 Church Close",
    "sg:city":"Andover",
    "sg:classifiers":[
        {
            "category":"Retail",
            "subcategory":"Funeral Services",
            "type":"Services"
        }
    ],
    "sg:postcode":"SP10 1DP",
    "sg:province":"Hampshire",
    "wof:name":"Dunning Funeral Services",
    "wof:placetype":"venue"
},
  "geometry": {"coordinates":[-1.4774949551,51.2096824646],"type":"Point"}
}