{
  "type": "Feature",
  "properties": {
    "addr:full":"18 Queens Drive Halesworth Suffolk IP19 8DN",
    "addr:housenumber":"18",
    "addr:postcode":"ip19 8dn",
    "addr:street":"Queens Drive",
    "iso:country":"GB",
    "sg:address":"18 Queens Drive",
    "sg:city":"Halesworth",
    "sg:classifiers":[
        {
            "category":"Military Area",
            "subcategory":"Air Force Base",
            "type":"Public Place"
        }
    ],
    "sg:phone":"+44 1986 873213",
    "sg:postcode":"IP19 8DN",
    "sg:province":"Suffolk",
    "sg:tags":[
        "taxi",
        "hire",
        "private"
    ],
    "wof:name":"Prime & Cowles",
    "wof:placetype":"venue"
},
  "geometry": {"coordinates":[1.4959230423,52.3367462158],"type":"Point"}
}