{
  "type": "Feature",
  "properties": {
    "addr:full":"Olton Boulevard West, Tyseley Birmingham West Midlands B11 3HX",
    "addr:postcode":"b11 3hx",
    "addr:street":"Olton Boulevard West",
    "iso:country":"GB",
    "sg:address":"Olton Boulevard West, Tyseley",
    "sg:city":"Birmingham",
    "sg:classifiers":[
        {
            "category":"Retail",
            "subcategory":"Auto Repair",
            "type":"Services"
        }
    ],
    "sg:phone":"+44 121 706 5533",
    "sg:postcode":"B11 3HX",
    "sg:province":"West Midlands",
    "sg:tags":[
        "car",
        "specialist",
        "customizing"
    ],
    "wof:name":"Tyresales TyrePlus Autoservice",
    "wof:placetype":"venue"
},
  "geometry": {"coordinates":[-1.839806,52.44635],"type":"Point"}
}