{
  "type": "Feature",
  "properties": {
    "addr:full":"Hedley Hill Villa Durham Durham DH7 9EX",
    "addr:postcode":"dh7 9ex",
    "addr:street":"Hedley Hill",
    "iso:country":"GB",
    "sg:address":"Hedley Hill Villa",
    "sg:city":"Durham",
    "sg:classifiers":[
        {
            "category":"Health Services",
            "subcategory":"Health Practitioner",
            "type":"Services"
        }
    ],
    "sg:phone":"+44 191 373 3102",
    "sg:postcode":"DH7 9EX",
    "sg:province":"Durham",
    "sg:tags":[
        "osteopath"
    ],
    "wof:name":"G A Carhart-Harris",
    "wof:placetype":"venue"
},
  "geometry": {"coordinates":[-1.668834,54.800049],"type":"Point"}
}