{
  "type": "Feature",
  "properties": {
    "addr:full":"128 Vicar Lane Leeds West Yorkshire LS2 7NL",
    "addr:housenumber":"128",
    "addr:postcode":"ls2 7nl",
    "addr:street":"Vicar Lane",
    "iso:country":"GB",
    "sg:address":"128 Vicar Lane",
    "sg:city":"Leeds",
    "sg:classifiers":[
        {
            "category":"Restaurant",
            "type":"Food & Drink"
        }
    ],
    "sg:phone":"+44 113 234 3612",
    "sg:postcode":"LS2 7NL",
    "sg:province":"West Yorkshire",
    "wof:name":"Wongs Restaurant",
    "wof:placetype":"venue"
},
  "geometry": {"coordinates":[-1.5395350456,53.7999763489],"type":"Point"}
}