{
  "type": "Feature",
  "properties": {
    "addr:full":"Rhyd Y Garnedd Farm Tywyn Gwynedd LL36 9LG",
    "addr:postcode":"ll36 9lg",
    "addr:street":"Rhyd Y Garnedd",
    "iso:country":"GB",
    "sg:address":"Rhyd Y Garnedd Farm",
    "sg:city":"Tywyn",
    "sg:classifiers":[
        {
            "category":"Farming",
            "subcategory":"Farm",
            "type":"Manufacturing & Wholesale Goods"
        }
    ],
    "sg:phone":"+44 1654 710315",
    "sg:postcode":"LL36 9LG",
    "sg:province":"Gwynedd",
    "sg:tags":[
        "mixed",
        "crop"
    ],
    "wof:name":"S Tudor",
    "wof:placetype":"venue"
},
  "geometry": {"coordinates":[-4.0884189606,52.5865859985],"type":"Point"}
}