{
  "type": "Feature",
  "properties": {
    "addr:full":"39a High Street, Warsop Mansfield Derbyshire NG20 0AB",
    "addr:housenumber":"39a",
    "addr:postcode":"ng20 0ab",
    "addr:street":"High Street",
    "iso:country":"GB",
    "sg:address":"39a High Street, Warsop",
    "sg:city":"Mansfield",
    "sg:classifiers":[
        {
            "category":"Personal",
            "subcategory":"Beauty Salon",
            "type":"Services"
        }
    ],
    "sg:phone":"+44 1623 842627",
    "sg:postcode":"NG20 0AB",
    "sg:province":"Derbyshire",
    "sg:tags":[
        "unisex",
        "hairdresser"
    ],
    "wof:name":"New Image",
    "wof:placetype":"venue"
},
  "geometry": {"coordinates":[-1.154047966,53.2040519714],"type":"Point"}
}