{
  "type": "Feature",
  "properties": {
    "iso:country":"GB",
    "sg:address":"32-38 Saffron Hill",
    "sg:city":"London",
    "sg:classifiers":[
        {
            "category":"Manufacturing",
            "subcategory":"Jewelry",
            "type":"Manufacturing & Wholesale Goods"
        }
    ],
    "sg:postcode":"EC1N 8FH",
    "sg:province":"Greater London",
    "sg:tags":[
        "repair",
        "jewellery"
    ],
    "wof:name":"M Gungoo",
    "wof:placetype":"venue"
},
  "geometry": {"coordinates":[-0.1061350033,51.519859314],"type":"Point"}
}