{
  "type": "Feature",
  "properties": {
    "addr:full":"187 Mcgregor Road, Cumbernauld Glasgow Falkirk G67 1JQ",
    "addr:housenumber":"187",
    "addr:postcode":"g67 1jq",
    "addr:street":"Mcgregor Road",
    "iso:country":"GB",
    "sg:address":"187 Mcgregor Road, Cumbernauld",
    "sg:city":"Glasgow",
    "sg:classifiers":[
        {
            "category":"Manufacturing",
            "subcategory":"Petroleum Products",
            "type":"Manufacturing & Wholesale Goods"
        }
    ],
    "sg:postcode":"G67 1JQ",
    "sg:province":"Falkirk",
    "sg:tags":[
        "double",
        "glazing"
    ],
    "wof:name":"Double Glazing Repairs",
    "wof:placetype":"venue"
},
  "geometry": {"coordinates":[-3.996836,55.943974],"type":"Point"}
}