{
  "type": "Feature",
  "properties": {
    "iso:country":"GB",
    "sg:address":"2 Broadmoor Road, Corfe Mullen",
    "sg:city":"Wimborne",
    "sg:classifiers":[
        {
            "category":"Professional",
            "subcategory":"Accounting & Tax Preparation",
            "type":"Services"
        }
    ],
    "sg:postcode":"BH21 3RA",
    "sg:province":"Dorset",
    "sg:tags":[
        "accountant"
    ],
    "wof:name":"C & D Book-Keeping Services",
    "wof:placetype":"venue"
},
  "geometry": {"coordinates":[-2.024973,50.777298],"type":"Point"}
}