{
  "type": "Feature",
  "properties": {
    "addr:full":"6 Oakleigh Court, Newbury Gillingham Dorset SP8 4HZ",
    "addr:housenumber":"6",
    "addr:postcode":"sp8 4hz",
    "addr:street":"Oakleigh Court",
    "iso:country":"GB",
    "sg:address":"6 Oakleigh Court, Newbury",
    "sg:city":"Gillingham",
    "sg:classifiers":[
        {
            "category":"Social Services",
            "subcategory":"Adult Care",
            "type":"Services"
        }
    ],
    "sg:phone":"+44 1747 826505",
    "sg:postcode":"SP8 4HZ",
    "sg:province":"Dorset",
    "sg:tags":[
        "home",
        "help",
        "private"
    ],
    "wof:name":"Drake Family Care Services Ltd.",
    "wof:placetype":"venue"
},
  "geometry": {"coordinates":[-2.27862,51.038097],"type":"Point"}
}