{
  "type": "Feature",
  "properties": {
    "addr:full":"St Margarets Cottage, St Margarets Lane Fareham Hampshire PO14 4BG",
    "addr:postcode":"po14 4bg",
    "addr:street":"St Margarets Lane",
    "iso:country":"GB",
    "sg:address":"St Margarets Cottage, St Margarets Lane",
    "sg:city":"Fareham",
    "sg:classifiers":[
        {
            "category":"Home & Garden",
            "subcategory":"Garden Supply",
            "type":"Retail Goods"
        }
    ],
    "sg:phone":"+44 1329 846006",
    "sg:postcode":"PO14 4BG",
    "sg:province":"Hampshire",
    "sg:tags":[
        "nursery",
        "centre"
    ],
    "wof:name":"St.Margarets Nurseries",
    "wof:placetype":"venue"
},
  "geometry": {"coordinates":[-1.2416030169,50.848449707],"type":"Point"}
}