{
  "type": "Feature",
  "properties": {
    "addr:full":"18 Claudia Place London Greater London SW19 6ES",
    "addr:housenumber":"18",
    "addr:postcode":"sw19 6es",
    "addr:street":"Claudia Place",
    "iso:country":"GB",
    "sg:address":"18 Claudia Place",
    "sg:city":"London",
    "sg:classifiers":[
        {
            "category":"Professional",
            "subcategory":"Secretarial Services",
            "type":"Services"
        }
    ],
    "sg:phone":"+44 20 8789 0089",
    "sg:postcode":"SW19 6ES",
    "sg:province":"Greater London",
    "wof:name":"Juwal Services",
    "wof:placetype":"venue"
},
  "geometry": {"coordinates":[-0.215231,51.443596],"type":"Point"}
}