{
  "type": "Feature",
  "properties": {
    "iso:country":"GB",
    "sg:address":"Peartree Ho, Peartree La",
    "sg:city":"Dudley",
    "sg:classifiers":[
        {
            "category":"Home & Garden",
            "subcategory":"Building Materials",
            "type":"Retail Goods"
        }
    ],
    "sg:phone":"+44 1384 74062",
    "sg:postcode":"DY2 0QU",
    "sg:province":"West Midlands",
    "sg:tags":[
        "ventilator",
        "ventilation",
        "system"
    ],
    "wof:name":"Roof Units",
    "wof:placetype":"venue"
},
  "geometry": {"coordinates":[-2.097271,52.497711],"type":"Point"}
}