{
  "type": "Feature",
  "properties": {
    "addr:full":"Malton Road Garage, Malton Road Pickering North Yorkshire YO18 7JL",
    "addr:postcode":"yo18 7jl",
    "addr:street":"Malton;Malton Road",
    "iso:country":"GB",
    "sg:address":"Malton Road Garage, Malton Road",
    "sg:city":"Pickering",
    "sg:classifiers":[
        {
            "category":"Autos & Motor Vehicles",
            "subcategory":"Fuel & Gas Station",
            "type":"Retail Goods"
        },
        {
            "category":"Retail",
            "subcategory":"Auto Repair",
            "type":"Services"
        }
    ],
    "sg:phone":"+44 1751 475286",
    "sg:postcode":"YO18 7JL",
    "sg:province":"North Yorkshire",
    "sg:tags":[
        "petrol",
        "garage",
        "filling",
        "modification",
        "related"
    ],
    "wof:name":"G & N Harland Ltd",
    "wof:placetype":"venue"
},
  "geometry": {"coordinates":[-0.775679,54.241394],"type":"Point"}
}