{
  "type": "Feature",
  "properties": {
    "addr:full":"Philpott Avenue Southend-on-sea Essex SS2 4RL",
    "addr:postcode":"ss2 4rl",
    "addr:street":"Philpott Avenue",
    "iso:country":"GB",
    "sg:address":"Philpott Avenue",
    "sg:city":"Southend-on-sea",
    "sg:classifiers":[
        {
            "category":"Education",
            "subcategory":"School",
            "type":"Public Place"
        }
    ],
    "sg:phone":"+44 1702 462322",
    "sg:postcode":"SS2 4RL",
    "sg:province":"Essex",
    "sg:tags":[
        "local",
        "authority"
    ],
    "wof:name":"St Nicholas School",
    "wof:placetype":"venue"
},
  "geometry": {"coordinates":[0.739421,51.547611],"type":"Point"}
}