{
  "type": "Feature",
  "properties": {
    "addr:full":"548 Uxbridge Road Pinner Greater London HA5 3QA",
    "addr:housenumber":"548",
    "addr:postcode":"ha5 3qa",
    "addr:street":"Uxbridge Road",
    "iso:country":"GB",
    "sg:address":"548 Uxbridge Road",
    "sg:city":"Pinner",
    "sg:classifiers":[
        {
            "category":"Building & Trades",
            "subcategory":"Construction",
            "type":"Services"
        }
    ],
    "sg:phone":"+44 20 8429 1502",
    "sg:postcode":"HA5 3QA",
    "sg:province":"Greater London",
    "sg:tags":[
        "dry",
        "lining",
        "plasterers",
        "screeders"
    ],
    "wof:name":"Christopher Tobin & Sons",
    "wof:placetype":"venue"
},
  "geometry": {"coordinates":[-0.3832240105,51.6039161682],"type":"Point"}
}