{
  "type": "Feature",
  "properties": {
    "addr:full":"Blakely Road Saltcoats North Ayrshire KA21 5JQ",
    "addr:postcode":"ka21 5jq",
    "addr:street":"Blakely Road",
    "iso:country":"GB",
    "sg:address":"Blakely Road",
    "sg:city":"Saltcoats",
    "sg:classifiers":[
        {
            "category":"Wholesale",
            "subcategory":"Meat",
            "type":"Manufacturing & Wholesale Goods"
        }
    ],
    "sg:phone":"+44 1294 461921",
    "sg:postcode":"KA21 5JQ",
    "sg:province":"North Ayrshire",
    "sg:tags":[
        "product"
    ],
    "wof:name":"Capalbo Ltd.",
    "wof:placetype":"venue"
},
  "geometry": {"coordinates":[-4.77168,55.634357],"type":"Point"}
}