{
  "type": "Feature",
  "properties": {
    "addr:full":"17 Prospect St Lancaster Lancashire LA1 3BL",
    "addr:housenumber":"17",
    "addr:postcode":"la1 3bl",
    "addr:street":"Prospect St",
    "iso:country":"GB",
    "sg:address":"17 Prospect St",
    "sg:city":"Lancaster",
    "sg:classifiers":[
        {
            "category":"Food & Beverages",
            "subcategory":"Groceries & Convenience Stores",
            "type":"Retail Goods"
        }
    ],
    "sg:phone":"+44 1524 68573",
    "sg:postcode":"LA1 3BL",
    "sg:province":"Lancashire",
    "wof:name":"Master Mini Market",
    "wof:placetype":"venue"
},
  "geometry": {"coordinates":[-2.7926440239,54.0439987183],"type":"Point"}
}