{
  "type": "Feature",
  "properties": {
    "iso:country":"GB",
    "sg:address":"Sterling House, 3 Dendy Road",
    "sg:city":"Paignton",
    "sg:classifiers":[
        {
            "category":"Building & Trades",
            "subcategory":"Construction",
            "type":"Services"
        }
    ],
    "sg:postcode":"TQ4 5DB",
    "sg:province":"Devon",
    "sg:tags":[
        "joiner",
        "carpenter"
    ],
    "wof:name":"Peninsular Ceilings Ltd.",
    "wof:placetype":"venue"
},
  "geometry": {"coordinates":[-3.565969,50.43618],"type":"Point"}
}