{
  "type": "Feature",
  "properties": {
    "addr:full":"65 Deepcut Bridge Road, Deepcut Camberley Hampshire GU16 6QP",
    "addr:housenumber":"65",
    "addr:postcode":"gu16 6qp",
    "addr:street":"Deepcut Bridge Road",
    "iso:country":"GB",
    "sg:address":"65 Deepcut Bridge Road, Deepcut",
    "sg:city":"Camberley",
    "sg:classifiers":[
        {
            "category":"Professional",
            "subcategory":"Art Services",
            "type":"Services"
        }
    ],
    "sg:phone":"+44 1252 838550",
    "sg:postcode":"GU16 6QP",
    "sg:province":"Hampshire",
    "sg:tags":[
        "framing"
    ],
    "wof:name":"Bonds Framing",
    "wof:placetype":"venue"
},
  "geometry": {"coordinates":[-0.7046340108,51.3077583313],"type":"Point"}
}