{
  "type": "Feature",
  "properties": {
    "iso:country":"GB",
    "sg:address":"Chester Road, Acton",
    "sg:city":"Nantwich",
    "sg:classifiers":[
        {
            "category":"Farming",
            "subcategory":"Farm",
            "type":"Manufacturing & Wholesale Goods"
        }
    ],
    "sg:phone":"+44 1270 625245",
    "sg:postcode":"CW5 8LD",
    "sg:province":"Cheshire",
    "sg:tags":[
        "mixed",
        "crop"
    ],
    "wof:name":"R C Roundell Partnership",
    "wof:placetype":"venue"
},
  "geometry": {"coordinates":[-2.550179,53.072826],"type":"Point"}
}