{
  "type": "Feature",
  "properties": {
    "iso:country":"GB",
    "sg:address":"14 Wren Croft, Ladybalk",
    "sg:city":"Pontefract",
    "sg:classifiers":[
        {
            "category":"Building & Trades",
            "subcategory":"Landscaping Services",
            "type":"Services"
        },
        {
            "category":"Building & Trades",
            "subcategory":"Construction",
            "type":"Services"
        }
    ],
    "sg:phone":"+44 1977 790768",
    "sg:postcode":"WF8 1SG",
    "sg:province":"North Yorkshire",
    "sg:tags":[
        "forestry",
        "tree",
        "decorator",
        "painter"
    ],
    "wof:name":"C Beecher Tree Surgeon",
    "wof:placetype":"venue"
},
  "geometry": {"coordinates":[-1.307723999,53.7034416199],"type":"Point"}
}