{
  "type": "Feature",
  "properties": {
    "iso:country":"GB",
    "sg:address":"Station Approach",
    "sg:city":"Huntingdon",
    "sg:classifiers":[
        {
            "category":"Retail",
            "subcategory":"Auto Repair",
            "type":"Services"
        }
    ],
    "sg:phone":"+44 1480 458092",
    "sg:postcode":"PE29 3BP",
    "sg:province":"Cambridgeshire",
    "sg:tags":[
        "modification",
        "garage"
    ],
    "wof:name":"Serviceman",
    "wof:placetype":"venue"
},
  "geometry": {"coordinates":[-0.189304,52.33514],"type":"Point"}
}