{
  "type": "Feature",
  "properties": {
    "iso:country":"GB",
    "sg:address":"22 Hamilton Road",
    "sg:city":"Gullane",
    "sg:classifiers":[
        {
            "category":"Real Estate",
            "subcategory":"Architect",
            "type":"Services"
        }
    ],
    "sg:postcode":"EH31 2HP",
    "sg:province":"East Lothian",
    "wof:name":"John Murray Architects",
    "wof:placetype":"venue"
},
  "geometry": {"coordinates":[-2.825931,56.035492],"type":"Point"}
}