{
  "type": "Feature",
  "properties": {
    "iso:country":"GB",
    "sg:address":"108 Monksmead",
    "sg:city":"Tavistock",
    "sg:classifiers":[
        {
            "category":"Arts & Performance",
            "subcategory":"Music",
            "type":"Entertainment"
        }
    ],
    "sg:postcode":"PL19 8PR",
    "sg:province":"Devon",
    "sg:tags":[
        "mobile",
        "disco"
    ],
    "wof:name":"Paul King Disco Roadshow",
    "wof:placetype":"venue"
},
  "geometry": {"coordinates":[-4.156789,50.541958],"type":"Point"}
}