{
  "type": "Feature",
  "properties": {
    "iso:country":"GB",
    "sg:address":"194 Ealing Rd",
    "sg:city":"Wembley",
    "sg:classifiers":[
        {
            "category":"Food & Beverages",
            "subcategory":"Fruits & Vegetables",
            "type":"Retail Goods"
        }
    ],
    "sg:phone":"+44 20 8903 5823",
    "sg:postcode":"HA0 4QG",
    "sg:province":"Greater London",
    "sg:tags":[
        "greengrocer"
    ],
    "wof:name":"M Qadri",
    "wof:placetype":"venue"
},
  "geometry": {"coordinates":[-0.2971140146,51.5449905396],"type":"Point"}
}