{
  "type": "Feature",
  "properties": {
    "iso:country":"GB",
    "sg:address":"Station Road",
    "sg:city":"Bracknell",
    "sg:classifiers":[
        {
            "category":"Bars & Pubs",
            "type":"Food & Drink"
        }
    ],
    "sg:phone":"+44 1344 451734",
    "sg:postcode":"RG12 1HY",
    "sg:province":"Berkshire",
    "sg:tags":[
        "pubs",
        "inn"
    ],
    "wof:name":"Punch Leisure Ltd.",
    "wof:placetype":"venue"
},
  "geometry": {"coordinates":[-0.751649,51.414223],"type":"Point"}
}