{
  "type": "Feature",
  "properties": {
    "addr:full":"Unit 1 Ermington Workshop Ivybridge Devon PL21 9NT",
    "addr:housenumber":"unit 1",
    "addr:postcode":"pl21 9nt",
    "iso:country":"GB",
    "sg:address":"Unit 1 Ermington Workshop",
    "sg:city":"Ivybridge",
    "sg:classifiers":[
        {
            "category":"Shopping",
            "subcategory":"Hobbies, Toys, & Games",
            "type":"Retail Goods"
        }
    ],
    "sg:phone":"+44 1548 831013",
    "sg:postcode":"PL21 9NT",
    "sg:province":"Devon",
    "sg:tags":[
        "toy"
    ],
    "wof:name":"Erme Wood",
    "wof:placetype":"venue"
},
  "geometry": {"coordinates":[-3.945171,50.39365],"type":"Point"}
}