{
  "type": "Feature",
  "properties": {
    "addr:full":"9 Freebournes Court Witham Essex CM8 2BL",
    "addr:housenumber":"9",
    "addr:postcode":"cm8 2bl",
    "addr:street":"Freebournes Court",
    "iso:country":"GB",
    "sg:address":"9 Freebournes Court",
    "sg:city":"Witham",
    "sg:classifiers":[
        {
            "category":"Banks & Credit Unions",
            "subcategory":"Financial Services",
            "type":"Services"
        }
    ],
    "sg:phone":"+44 1376 503500",
    "sg:postcode":"CM8 2BL",
    "sg:province":"Essex",
    "sg:tags":[
        "consultant"
    ],
    "sg:website":"http://www.manifest.co.uk",
    "wof:name":"Manifest Voting Agency Ltd",
    "wof:placetype":"venue"
},
  "geometry": {"coordinates":[0.64231,51.801384],"type":"Point"}
}