{
  "type": "Feature",
  "properties": {
    "addr:full":"131 Latchmere Lane Kingston-upon-thames Greater London KT2 5NX",
    "addr:housenumber":"131",
    "addr:postcode":"kt2 5nx",
    "addr:street":"Latchmere Lane",
    "iso:country":"GB",
    "sg:address":"131 Latchmere Lane",
    "sg:city":"Kingston-upon-thames",
    "sg:classifiers":[
        {
            "category":"Building & Trades",
            "subcategory":"Cleaning & Sanitation",
            "type":"Services"
        }
    ],
    "sg:postcode":"KT2 5NX",
    "sg:province":"Greater London",
    "sg:tags":[
        "commercial"
    ],
    "wof:name":"S J M Cleaning Services",
    "wof:placetype":"venue"
},
  "geometry": {"coordinates":[-0.2949669957,51.4272918701],"type":"Point"}
}