{
  "type": "Feature",
  "properties": {
    "addr:full":"South Street Rochdale Lancashire OL16 2EP",
    "addr:postcode":"ol16 2ep",
    "addr:street":"South Street",
    "iso:country":"GB",
    "sg:address":"South Street",
    "sg:city":"Rochdale",
    "sg:classifiers":[
        {
            "category":"Farming",
            "subcategory":"Nursery",
            "type":"Manufacturing & Wholesale Goods"
        },
        {
            "category":"Government",
            "subcategory":"Office",
            "type":"Public Place"
        }
    ],
    "sg:phone":"+44 1706 645435",
    "sg:postcode":"OL16 2EP",
    "sg:province":"Lancashire",
    "sg:tags":[
        "local",
        "creche"
    ],
    "wof:name":"South Street Nursery School",
    "wof:placetype":"venue"
},
  "geometry": {"coordinates":[-2.146224,53.621078],"type":"Point"}
}