{
  "type": "Feature",
  "properties": {
    "addr:full":"Church Street Liskeard Cornwall PL14 3AQ",
    "addr:postcode":"pl14 3aq",
    "addr:street":"Church Street",
    "iso:country":"GB",
    "sg:address":"Church Street",
    "sg:city":"Liskeard",
    "sg:classifiers":[
        {
            "category":"Bars & Pubs",
            "type":"Food & Drink"
        }
    ],
    "sg:postcode":"PL14 3AQ",
    "sg:province":"Cornwall",
    "sg:tags":[
        "pubs",
        "inn"
    ],
    "wof:name":"Barley Sheaf",
    "wof:placetype":"venue"
},
  "geometry": {"coordinates":[-4.4628939629,50.4545440674],"type":"Point"}
}