{
  "type": "Feature",
  "properties": {
    "iso:country":"GB",
    "sg:address":"24 Ashfield Avenue",
    "sg:city":"Malton",
    "sg:classifiers":[
        {
            "category":"Building & Trades",
            "subcategory":"Construction",
            "type":"Services"
        }
    ],
    "sg:phone":"+44 1653 694240",
    "sg:postcode":"YO17 7LE",
    "sg:province":"North Yorkshire",
    "sg:tags":[
        "joinery",
        "joiner",
        "carpenter",
        "carpentry"
    ],
    "wof:name":"Barry Atkinson",
    "wof:placetype":"venue"
},
  "geometry": {"coordinates":[-0.7906240225,54.1391410828],"type":"Point"}
}