{
  "type": "Feature",
  "properties": {
    "addr:full":"174 Putney High Street London Greater London SW15 1RS",
    "addr:housenumber":"174",
    "addr:postcode":"sw15 1rs",
    "addr:street":"Putney High Street",
    "iso:country":"GB",
    "sg:address":"174 Putney High Street",
    "sg:city":"London",
    "sg:classifiers":[
        {
            "category":"Personal",
            "subcategory":"Beauty Salon",
            "type":"Services"
        }
    ],
    "sg:phone":"+44 20 8789 2211",
    "sg:postcode":"SW15 1RS",
    "sg:province":"Greater London",
    "sg:tags":[
        "unisex",
        "hairdresser"
    ],
    "wof:name":"Philip Harvey Hairdressing",
    "wof:placetype":"venue"
},
  "geometry": {"coordinates":[-0.2168750018,51.4618339539],"type":"Point"}
}