{
  "type": "Feature",
  "properties": {
    "iso:country":"GB",
    "sg:address":"Head Office, The Hall, Marine Villa Road",
    "sg:city":"Knottingley",
    "sg:classifiers":[
        {
            "category":"Shopping",
            "subcategory":"Books",
            "type":"Retail Goods"
        }
    ],
    "sg:phone":"+44 1977 558163",
    "sg:postcode":"WF11 8ER",
    "sg:province":"North Yorkshire",
    "sg:tags":[
        "bookseller"
    ],
    "wof:name":"G & G Cards & Books (Yorkshire) Ltd.",
    "wof:placetype":"venue"
},
  "geometry": {"coordinates":[-1.259354949,53.7076072693],"type":"Point"}
}