{
  "type": "Feature",
  "properties": {
    "addr:full":"37 Avon Rd Basingstoke Hampshire RG23 7DJ",
    "addr:housenumber":"37",
    "addr:postcode":"rg23 7dj",
    "addr:street":"Avon Rd",
    "iso:country":"GB",
    "sg:address":"37 Avon Rd",
    "sg:city":"Basingstoke",
    "sg:classifiers":[
        {
            "category":"Professional",
            "subcategory":"Accounting & Tax Preparation",
            "type":"Services"
        }
    ],
    "sg:phone":"+44 1256 782056",
    "sg:postcode":"RG23 7DJ",
    "sg:province":"Hampshire",
    "sg:tags":[
        "accountant"
    ],
    "wof:name":"Admin Helpline Services Ltd",
    "wof:placetype":"venue"
},
  "geometry": {"coordinates":[-1.1696900129,51.2502365112],"type":"Point"}
}