{
  "type": "Feature",
  "properties": {
    "addr:full":"Home Farm, Arnage Ellon Aberdeenshire AB41 8PY",
    "addr:postcode":"ab41 8py",
    "iso:country":"GB",
    "sg:address":"Home Farm, Arnage",
    "sg:city":"Ellon",
    "sg:classifiers":[
        {
            "category":"Farming",
            "subcategory":"Farm",
            "type":"Manufacturing & Wholesale Goods"
        }
    ],
    "sg:postcode":"AB41 8PY",
    "sg:province":"Aberdeenshire",
    "sg:tags":[
        "mixed",
        "crop"
    ],
    "wof:name":"James F Gillanders",
    "wof:placetype":"venue"
},
  "geometry": {"coordinates":[-2.072814,57.364136],"type":"Point"}
}