{
  "type": "Feature",
  "properties": {
    "addr:full":"Weavers Loft Common Wood, Wem Shrewsbury Shropshire SY4 5SJ",
    "addr:postcode":"sy4 5sj",
    "addr:street":"Common Wood",
    "iso:country":"GB",
    "sg:address":"Weavers Loft Common Wood, Wem",
    "sg:city":"Shrewsbury",
    "sg:classifiers":[
        {
            "category":"Professional",
            "subcategory":"Computer Services",
            "type":"Services"
        }
    ],
    "sg:phone":"+44 1939 236193",
    "sg:postcode":"SY4 5SJ",
    "sg:province":"Shropshire",
    "sg:tags":[
        "system",
        "software"
    ],
    "wof:name":"A.j Goddard",
    "wof:placetype":"venue"
},
  "geometry": {"coordinates":[-2.7598400116,52.8472099304],"type":"Point"}
}