{
  "type": "Feature",
  "properties": {
    "addr:full":"P O Box 1145 London Greater London SW7 5QB",
    "addr:housenumber":"p o;1145",
    "addr:postcode":"sw7 5qb",
    "iso:country":"GB",
    "sg:address":"P O Box 1145",
    "sg:city":"London",
    "sg:classifiers":[
        {
            "category":"Real Estate",
            "subcategory":"Real Estate Agent",
            "type":"Services"
        }
    ],
    "sg:postcode":"SW7 5QB",
    "sg:province":"Greater London",
    "wof:name":"Vanguard Metropolitan Ltd.",
    "wof:placetype":"venue"
},
  "geometry": {"coordinates":[-0.18086,51.496639],"type":"Point"}
}