{
  "type": "Feature",
  "properties": {
    "iso:country":"GB",
    "sg:address":"4a Ford Airfield Industrial Estate, Ford",
    "sg:city":"Arundel",
    "sg:classifiers":[
        {
            "category":"Shopping",
            "subcategory":"Pets & Pet Supplies",
            "type":"Retail Goods"
        }
    ],
    "sg:postcode":"BN18 0BE",
    "sg:province":"West Sussex",
    "sg:tags":[
        "food"
    ],
    "wof:name":"Castle Stables Ltd.",
    "wof:placetype":"venue"
},
  "geometry": {"coordinates":[-0.580514,50.823326],"type":"Point"}
}