{
  "type": "Feature",
  "properties": {
    "addr:full":"Ashfield House, 190 Front Street Chester-le-street Durham DH3 3AZ",
    "addr:housenumber":"190",
    "addr:postcode":"dh3 3az",
    "addr:street":"Front Street",
    "iso:country":"GB",
    "sg:address":"Ashfield House, 190 Front Street",
    "sg:city":"Chester-le-street",
    "sg:classifiers":[
        {
            "category":"Shopping",
            "subcategory":"Florist",
            "type":"Retail Goods"
        }
    ],
    "sg:phone":"+44 191 388 3487",
    "sg:postcode":"DH3 3AZ",
    "sg:province":"Durham",
    "wof:name":"Richards Florist",
    "wof:placetype":"venue"
},
  "geometry": {"coordinates":[-1.572947979,54.8519897461],"type":"Point"}
}