{
  "type": "Feature",
  "properties": {
    "iso:country":"GB",
    "sg:address":"148-149 Fore Street",
    "sg:city":"Exeter",
    "sg:classifiers":[
        {
            "category":"Shopping",
            "subcategory":"Bicycles & Sporting Goods",
            "type":"Retail Goods"
        }
    ],
    "sg:phone":"+44 1392 432681",
    "sg:postcode":"EX4 3AN",
    "sg:province":"Devon",
    "sg:tags":[
        "equipment",
        "camping"
    ],
    "wof:name":"Percy Hodge (Sports) Ltd.",
    "wof:placetype":"venue"
},
  "geometry": {"coordinates":[-3.534761,50.721054],"type":"Point"}
}