{
  "type": "Feature",
  "properties": {
    "addr:full":"287 Goldhawk Road, Shepherds Bush London Greater London W12 8EU",
    "addr:housenumber":"287",
    "addr:postcode":"w12 8eu",
    "addr:street":"Goldhawk Road",
    "iso:country":"GB",
    "sg:address":"287 Goldhawk Road, Shepherds Bush",
    "sg:city":"London",
    "sg:classifiers":[
        {
            "category":"Education",
            "subcategory":"School",
            "type":"Public Place"
        }
    ],
    "sg:phone":"+44 20 8846 8519",
    "sg:postcode":"W12 8EU",
    "sg:province":"Greater London",
    "sg:tags":[
        "independent",
        "preparatory"
    ],
    "wof:name":"Ladybird Nursery",
    "wof:placetype":"venue"
},
  "geometry": {"coordinates":[-0.2412540019,51.4990310669],"type":"Point"}
}