{
  "type": "Feature",
  "properties": {
    "addr:full":"11 Whitletts Ct Ayr South Ayrshire KA8 0LH",
    "addr:housenumber":"11",
    "addr:postcode":"ka8 0lh",
    "addr:street":"Whitletts Ct",
    "iso:country":"GB",
    "sg:address":"11 Whitletts Ct",
    "sg:city":"Ayr",
    "sg:classifiers":[
        {
            "category":"Social Services",
            "subcategory":"Adult Care",
            "type":"Services"
        }
    ],
    "sg:phone":"+44 1292 263181",
    "sg:postcode":"KA8 0LH",
    "sg:province":"South Ayrshire",
    "sg:tags":[
        "housing",
        "sheltered"
    ],
    "wof:name":"Whitletts Court Sheltered Housing",
    "wof:placetype":"venue"
},
  "geometry": {"coordinates":[-4.5936799049,55.47315979],"type":"Point"}
}