{
  "type": "Feature",
  "properties": {
    "addr:full":"Thorpland Farm, Runcton Holme King's Lynn Norfolk PE33 0AD",
    "addr:housenumber":"runcton holme",
    "addr:postcode":"pe33 0ad",
    "iso:country":"GB",
    "sg:address":"Thorpland Farm, Runcton Holme",
    "sg:city":"King's Lynn",
    "sg:classifiers":[
        {
            "category":"Farming",
            "subcategory":"Farm",
            "type":"Manufacturing & Wholesale Goods"
        }
    ],
    "sg:phone":"+44 1553 811190",
    "sg:postcode":"PE33 0AD",
    "sg:province":"Norfolk",
    "sg:tags":[
        "mixed",
        "crop"
    ],
    "wof:name":"W H C Flint & Son",
    "wof:placetype":"venue"
},
  "geometry": {"coordinates":[0.3877800107,52.6533889771],"type":"Point"}
}