{
  "type": "Feature",
  "properties": {
    "addr:full":"64 Whitburn Street Bridgnorth Shropshire WV16 4QP",
    "addr:housenumber":"64",
    "addr:postcode":"wv16 4qp",
    "addr:street":"Whitburn Street",
    "iso:country":"GB",
    "sg:address":"64 Whitburn Street",
    "sg:city":"Bridgnorth",
    "sg:classifiers":[
        {
            "category":"Professional",
            "subcategory":"Management & Consulting",
            "type":"Services"
        }
    ],
    "sg:phone":"+44 1746 768427",
    "sg:postcode":"WV16 4QP",
    "sg:province":"Shropshire",
    "sg:tags":[
        "consultant",
        "specialist"
    ],
    "wof:name":"Beauty & Electrolysis",
    "wof:placetype":"venue"
},
  "geometry": {"coordinates":[-2.422868,52.53587],"type":"Point"}
}