{
  "type": "Feature",
  "properties": {
    "addr:full":"53 Railway Road Leigh Lancashire WN7 4AD",
    "addr:housenumber":"53",
    "addr:postcode":"wn7 4ad",
    "addr:street":"Railway Road Leigh",
    "iso:country":"GB",
    "sg:address":"53 Railway Road",
    "sg:city":"Leigh",
    "sg:classifiers":[
        {
            "category":"Personal",
            "subcategory":"Beauty Salon",
            "type":"Services"
        }
    ],
    "sg:postcode":"WN7 4AD",
    "sg:province":"Lancashire",
    "sg:tags":[
        "unisex",
        "hairdresser"
    ],
    "wof:name":"David Morris",
    "wof:placetype":"venue"
},
  "geometry": {"coordinates":[-2.5216419697,53.4970741272],"type":"Point"}
}