{
  "type": "Feature",
  "properties": {
    "addr:full":"Cedar Ho, 14 The Pde, Frimley High St, Frimley Camberley Hampshire GU16 7HY",
    "addr:housenumber":"14",
    "addr:postcode":"gu16 7hy",
    "addr:street":"Cedar;The Pde;High St",
    "iso:country":"GB",
    "sg:address":"Cedar Ho, 14 The Pde, Frimley High St, Frimley",
    "sg:city":"Camberley",
    "sg:classifiers":[
        {
            "category":"Professional",
            "subcategory":"Art Services",
            "type":"Services"
        }
    ],
    "sg:postcode":"GU16 7HY",
    "sg:province":"Hampshire",
    "sg:tags":[
        "graphic",
        "designer"
    ],
    "wof:name":"Begg,Stephen,",
    "wof:placetype":"venue"
},
  "geometry": {"coordinates":[-0.7452790141,51.3132591248],"type":"Point"}
}