{
  "type": "Feature",
  "properties": {
    "addr:full":"Office 5 Telfords Yard London Greater London E1W 2BS",
    "addr:housenumber":"5",
    "addr:postcode":"e1w 2bs",
    "addr:street":"Telfords Yard",
    "iso:country":"GB",
    "sg:address":"Office 5 Telfords Yard",
    "sg:city":"London",
    "sg:classifiers":[
        {
            "category":"Professional",
            "subcategory":"Computer Services",
            "type":"Services"
        }
    ],
    "sg:phone":"+44 20 7488 2100",
    "sg:postcode":"E1W 2BS",
    "sg:province":"Greater London",
    "sg:tags":[
        "consultant",
        "system",
        "software"
    ],
    "wof:name":"Corporate Computer Consultants Ltd.",
    "wof:placetype":"venue"
},
  "geometry": {"coordinates":[-0.065128997,51.5092658997],"type":"Point"}
}