{
  "type": "Feature",
  "properties": {
    "iso:country":"GB",
    "sg:address":"14 Tolroy Road, St Erth-praze, Praze",
    "sg:city":"Hayle",
    "sg:classifiers":[
        {
            "category":"Professional",
            "subcategory":"Engineering",
            "type":"Services"
        }
    ],
    "sg:postcode":"TR27 6EA",
    "sg:province":"Cornwall",
    "sg:tags":[
        "contractor",
        "electrical",
        "engineer"
    ],
    "wof:name":"Tony Miller",
    "wof:placetype":"venue"
},
  "geometry": {"coordinates":[-5.410893,50.170177],"type":"Point"}
}