{
  "type": "Feature",
  "properties": {
    "addr:full":"20 Milton Dene Hemel Hempstead Hertfordshire HP2 7PE",
    "addr:housenumber":"20",
    "addr:postcode":"hp2 7pe",
    "addr:street":"Milton Dene;Hempstead",
    "iso:country":"GB",
    "sg:address":"20 Milton Dene",
    "sg:city":"Hemel Hempstead",
    "sg:classifiers":[
        {
            "category":"Professional",
            "subcategory":"Engineering",
            "type":"Services"
        },
        {
            "category":"Building & Trades",
            "subcategory":"Plumbing",
            "type":"Services"
        }
    ],
    "sg:phone":"+44 1442 231804",
    "sg:postcode":"HP2 7PE",
    "sg:province":"Hertfordshire",
    "sg:tags":[
        "plumber",
        "gas",
        "engineer"
    ],
    "wof:name":"A First Class Job",
    "wof:placetype":"venue"
},
  "geometry": {"coordinates":[-0.437428,51.778149],"type":"Point"}
}