{
  "type": "Feature",
  "properties": {
    "iso:country":"GB",
    "sg:address":"Kings Farm, Langwood Fen",
    "sg:city":"Chatteris",
    "sg:classifiers":[
        {
            "category":"Farming",
            "subcategory":"Farm",
            "type":"Manufacturing & Wholesale Goods"
        }
    ],
    "sg:phone":"+44 1354 694511",
    "sg:postcode":"PE16 6XF",
    "sg:province":"Cambridgeshire",
    "sg:tags":[
        "mixed",
        "crop"
    ],
    "wof:name":"Allen Partners",
    "wof:placetype":"venue"
},
  "geometry": {"coordinates":[0.048666,52.453632],"type":"Point"}
}