{
  "type": "Feature",
  "properties": {
    "addr:full":"35 Dormer Avenue, Wing Leighton Buzzard Bedfordshire LU7 0TF",
    "addr:housenumber":"35",
    "addr:postcode":"lu7 0tf",
    "addr:street":"Dormer Avenue",
    "iso:country":"GB",
    "sg:address":"35 Dormer Avenue, Wing",
    "sg:city":"Leighton Buzzard",
    "sg:classifiers":[
        {
            "category":"Personal",
            "type":"Services"
        }
    ],
    "sg:postcode":"LU7 0TF",
    "sg:province":"Bedfordshire",
    "sg:tags":[
        "wedding"
    ],
    "wof:name":"Bowvells Bridal",
    "wof:placetype":"venue"
},
  "geometry": {"coordinates":[-0.720248,51.900097],"type":"Point"}
}