{
  "type": "Feature",
  "properties": {
    "iso:country":"GB",
    "sg:address":"Broadmeadows Yard, Station Drive",
    "sg:city":"Ross-on-wye",
    "sg:classifiers":[
        {
            "category":"Utilities",
            "subcategory":"Refuse",
            "type":"Services"
        }
    ],
    "sg:phone":"+44 1989 562986",
    "sg:postcode":"HR9 5NA",
    "sg:province":"Gloucestershire",
    "sg:tags":[
        "skip",
        "hire"
    ],
    "wof:name":"Wye Waste",
    "wof:placetype":"venue"
},
  "geometry": {"coordinates":[-2.581733,51.916481],"type":"Point"}
}