{
  "type": "Feature",
  "properties": {
    "addr:full":"42 Green Lane Thornton Heath Surrey CR7 8BB",
    "addr:housenumber":"42",
    "addr:postcode":"cr7 8bb",
    "addr:street":"Green Lane",
    "iso:country":"GB",
    "sg:address":"42 Green Lane",
    "sg:city":"Thornton Heath",
    "sg:classifiers":[
        {
            "category":"Food & Beverages",
            "subcategory":"Liquor & Beverages",
            "type":"Retail Goods"
        }
    ],
    "sg:phone":"+44 20 8764 1263",
    "sg:postcode":"CR7 8BB",
    "sg:province":"Surrey",
    "sg:tags":[
        "beer",
        "spirit",
        "wines"
    ],
    "wof:name":"Threshers",
    "wof:placetype":"venue"
},
  "geometry": {"coordinates":[-0.106333,51.409107],"type":"Point"}
}