{
  "type": "Feature",
  "properties": {
    "addr:full":"Bradley Alresford Hampshire SO24 9RY",
    "addr:postcode":"so24 9ry",
    "iso:country":"GB",
    "sg:address":"Bradley",
    "sg:city":"Alresford",
    "sg:classifiers":[
        {
            "category":"Recreation",
            "subcategory":"Dog Park",
            "type":"Entertainment"
        }
    ],
    "sg:phone":"+44 1256 389733",
    "sg:postcode":"SO24 9RY",
    "sg:province":"Hampshire",
    "wof:name":"Sheer Bliss",
    "wof:placetype":"venue"
},
  "geometry": {"coordinates":[-1.094071,51.171543],"type":"Point"}
}