{
  "type": "Feature",
  "properties": {
    "iso:country":"GB",
    "sg:address":"14 East View, Essendon",
    "sg:city":"Hatfield",
    "sg:classifiers":[
        {
            "category":"Professional",
            "subcategory":"Computer Services",
            "type":"Services"
        }
    ],
    "sg:phone":"+44 1707 263551",
    "sg:postcode":"AL9 6HJ",
    "sg:province":"Hertfordshire",
    "sg:tags":[
        "consultant"
    ],
    "wof:name":"I N Parker",
    "wof:placetype":"venue"
},
  "geometry": {"coordinates":[-0.1499260068,51.76222229],"type":"Point"}
}