{
  "type": "Feature",
  "properties": {
    "addr:full":"Trull Barn Tetbury Gloucestershire GL8 8SQ",
    "addr:postcode":"gl8 8sq",
    "iso:country":"GB",
    "sg:address":"Trull Barn",
    "sg:city":"Tetbury",
    "sg:classifiers":[
        {
            "category":"Wholesale",
            "subcategory":"Office Equipment",
            "type":"Manufacturing & Wholesale Goods"
        }
    ],
    "sg:postcode":"GL8 8SQ",
    "sg:province":"Gloucestershire",
    "sg:tags":[
        "partition",
        "cubicle"
    ],
    "wof:name":"Wilmead Acoustic Systems Ltd",
    "wof:placetype":"venue"
},
  "geometry": {"coordinates":[-2.160976,51.637859],"type":"Point"}
}