{
  "type": "Feature",
  "properties": {
    "addr:full":"Unit 5, Aveley Ind Est, Ardmore Rd South Ockendon Essex RM15 5TH",
    "addr:housenumber":"unit 5",
    "addr:postcode":"rm15 5th",
    "addr:street":"Ardmore Rd",
    "iso:country":"GB",
    "sg:address":"Unit 5, Aveley Ind Est, Ardmore Rd",
    "sg:city":"South Ockendon",
    "sg:classifiers":[
        {
            "category":"Professional",
            "subcategory":"Employment Agencies",
            "type":"Services"
        }
    ],
    "sg:phone":"+44 1708 851883",
    "sg:postcode":"RM15 5TH",
    "sg:province":"Essex",
    "sg:tags":[
        "asbestos",
        "mnfrs",
        "removal"
    ],
    "wof:name":"Grangewood MSK Ltd",
    "wof:placetype":"venue"
},
  "geometry": {"coordinates":[0.28365,51.502476],"type":"Point"}
}