{
  "type": "Feature",
  "properties": {
    "iso:country":"GB",
    "sg:address":"Unit 1 Mill Yard Craft Centre, Swan St",
    "sg:city":"West Malling",
    "sg:classifiers":[
        {
            "category":"Wholesale",
            "subcategory":"Toys & Hobbies",
            "type":"Manufacturing & Wholesale Goods"
        }
    ],
    "sg:postcode":"ME19 6LP",
    "sg:province":"Kent",
    "sg:tags":[
        "hospital",
        "doll"
    ],
    "wof:name":"Jacobs,Caroline,",
    "wof:placetype":"venue"
},
  "geometry": {"coordinates":[0.4129399955,51.2937088013],"type":"Point"}
}