{
  "type": "Feature",
  "properties": {
    "iso:country":"GB",
    "sg:address":"100 Cowbridge Road East",
    "sg:city":"Cardiff",
    "sg:classifiers":[
        {
            "category":"Health Services",
            "subcategory":"Optometrist",
            "type":"Services"
        }
    ],
    "sg:postcode":"CF11 9DX",
    "sg:province":"Cardiff",
    "sg:tags":[
        "optician"
    ],
    "wof:name":"Helen Jenkyn Opticians",
    "wof:placetype":"venue"
},
  "geometry": {"coordinates":[-3.197786,51.481651],"type":"Point"}
}