{
  "type": "Feature",
  "properties": {
    "addr:full":"9 Crown Walk, High Street Oakham Leicestershire LE15 6BZ",
    "addr:housenumber":"9",
    "addr:postcode":"le15 6bz",
    "addr:street":"Crown Walk High Street",
    "iso:country":"GB",
    "sg:address":"9 Crown Walk, High Street",
    "sg:city":"Oakham",
    "sg:classifiers":[
        {
            "category":"Shopping",
            "subcategory":"Gifts & Souvenirs",
            "type":"Retail Goods"
        }
    ],
    "sg:phone":"+44 1572 770943",
    "sg:postcode":"LE15 6BZ",
    "sg:province":"Leicestershire",
    "sg:tags":[
        "shop",
        "poster",
        "card"
    ],
    "wof:name":"CUT PRICE CARDS",
    "wof:placetype":"venue"
},
  "geometry": {"coordinates":[-0.730749,52.669979],"type":"Point"}
}