{
  "type": "Feature",
  "properties": {
    "addr:full":"22 Claremont Rd Surbiton Surrey KT6 4QU",
    "addr:housenumber":"22",
    "addr:postcode":"kt6 4qu",
    "addr:street":"Claremont Rd",
    "iso:country":"GB",
    "sg:address":"22 Claremont Rd",
    "sg:city":"Surbiton",
    "sg:classifiers":[
        {
            "category":"Real Estate",
            "subcategory":"Real Estate Agent",
            "type":"Services"
        }
    ],
    "sg:phone":"+44 20 8390 6522",
    "sg:postcode":"KT6 4QU",
    "sg:province":"Surrey",
    "wof:name":"General Accident Property Services",
    "wof:placetype":"venue"
},
  "geometry": {"coordinates":[-0.304039,51.394508],"type":"Point"}
}