{
  "type": "Feature",
  "properties": {
    "addr:full":"150 Belgrave Road Leicester Leicestershire LE4 5AT",
    "addr:housenumber":"150",
    "addr:postcode":"le4 5at",
    "addr:street":"Belgrave Road",
    "iso:country":"GB",
    "sg:address":"150 Belgrave Road",
    "sg:city":"Leicester",
    "sg:classifiers":[
        {
            "category":"Shopping",
            "subcategory":"Jewelry",
            "type":"Retail Goods"
        },
        {
            "category":"Shopping",
            "subcategory":"Comic Books",
            "type":"Retail Goods"
        }
    ],
    "sg:postcode":"LE4 5AT",
    "sg:province":"Leicestershire",
    "sg:tags":[
        "jeweller",
        "sale",
        "jewellery"
    ],
    "wof:name":"TRIDEV JEWELLERS",
    "wof:placetype":"venue"
},
  "geometry": {"coordinates":[-1.1234010458,52.6490821838],"type":"Point"}
}