{
  "type": "Feature",
  "properties": {
    "iso:country":"GB",
    "sg:address":"Unit 12 Lyndean Indstl Est, Felixstow Rd",
    "sg:city":"London",
    "sg:classifiers":[
        {
            "category":"Professional",
            "subcategory":"Printing & Photocopies",
            "type":"Services"
        }
    ],
    "sg:postcode":"SE2 9SG",
    "sg:province":"Greater London",
    "sg:tags":[
        "printer"
    ],
    "wof:name":"Well Hall Press Ltd",
    "wof:placetype":"venue"
},
  "geometry": {"coordinates":[0.11884,51.492222],"type":"Point"}
}