{
  "type": "Feature",
  "properties": {
    "addr:full":"Unit 3 Sketchley Indstl Est Hinckley Leicestershire LE10 3EN",
    "addr:housenumber":"unit 3",
    "addr:postcode":"le10 3en",
    "addr:street":"Sketchley Indstl Est",
    "iso:country":"GB",
    "sg:address":"Unit 3 Sketchley Indstl Est",
    "sg:city":"Hinckley",
    "sg:classifiers":[
        {
            "category":"Manufacturing",
            "subcategory":"Metals",
            "type":"Manufacturing & Wholesale Goods"
        }
    ],
    "sg:phone":"+44 1455 610338",
    "sg:postcode":"LE10 3EN",
    "sg:province":"Leicestershire",
    "wof:name":"Kerr Associates Ltd",
    "wof:placetype":"venue"
},
  "geometry": {"coordinates":[-1.375123,52.526314],"type":"Point"}
}