{
  "type": "Feature",
  "properties": {
    "addr:full":"48 High St Newport Isle of Wight PO30 1SE",
    "addr:housenumber":"48",
    "addr:postcode":"po30 1se",
    "addr:street":"High St",
    "iso:country":"GB",
    "sg:address":"48 High St",
    "sg:city":"Newport",
    "sg:classifiers":[
        {
            "category":"Shopping",
            "subcategory":"Discount & Variety Stores",
            "type":"Retail Goods"
        }
    ],
    "sg:phone":"+44 1983 821120",
    "sg:postcode":"PO30 1SE",
    "sg:province":"Isle of Wight",
    "sg:tags":[
        "cleaning",
        "supply"
    ],
    "wof:name":"Forest Products",
    "wof:placetype":"venue"
},
  "geometry": {"coordinates":[-1.2951879501,50.6997489929],"type":"Point"}
}