{
  "type": "Feature",
  "properties": {
    "addr:full":"92 Kentsford Rd Grange Over Sands Cumbria LA11 7BB",
    "addr:housenumber":"92",
    "addr:postcode":"la11 7bb",
    "addr:street":"Kentsford Rd;Over Sands",
    "iso:country":"GB",
    "sg:address":"92 Kentsford Rd",
    "sg:city":"Grange Over Sands",
    "sg:classifiers":[
        {
            "category":"Food & Beverages",
            "subcategory":"Liquor & Beverages",
            "type":"Retail Goods"
        }
    ],
    "sg:phone":"+44 15395 33328",
    "sg:postcode":"LA11 7BB",
    "sg:province":"Cumbria",
    "sg:tags":[
        "beer",
        "spirit",
        "wines"
    ],
    "wof:name":"Al Vose & Co Ltd",
    "wof:placetype":"venue"
},
  "geometry": {"coordinates":[-2.9245259762,54.1735572815],"type":"Point"}
}