{
  "type": "Feature",
  "properties": {
    "iso:country":"GB",
    "sg:address":"Baltic Chambers, Suite 424, 50 Wellington Street",
    "sg:city":"Glasgow",
    "sg:classifiers":[
        {
            "category":"Shopping",
            "subcategory":"Bicycles & Sporting Goods",
            "type":"Retail Goods"
        }
    ],
    "sg:phone":"+44 141 204 2107",
    "sg:postcode":"G2 6HJ",
    "sg:province":"Glasgow City",
    "sg:tags":[
        "equipment",
        "marine",
        "supply"
    ],
    "wof:name":"Scana Ramnas Ltd.",
    "wof:placetype":"venue"
},
  "geometry": {"coordinates":[-4.26076,55.85918],"type":"Point"}
}