{
  "type": "Feature",
  "properties": {
    "iso:country":"GB",
    "sg:address":"217 Halliwell Road",
    "sg:city":"Bolton",
    "sg:classifiers":[
        {
            "category":"Home & Garden",
            "subcategory":"Household Appliances",
            "type":"Retail Goods"
        }
    ],
    "sg:postcode":"BL1 3NT",
    "sg:province":"Lancashire",
    "sg:tags":[
        "electrical"
    ],
    "wof:name":"L A Roberts",
    "wof:placetype":"venue"
},
  "geometry": {"coordinates":[-2.436289,53.59177],"type":"Point"}
}