{
  "type": "Feature",
  "properties": {
    "iso:country":"GB",
    "sg:address":"Wellington New Mill, Chadwick Street",
    "sg:city":"Blackburn",
    "sg:classifiers":[
        {
            "category":"Shopping",
            "type":"Retail Goods"
        }
    ],
    "sg:phone":"+44 1254 690209",
    "sg:postcode":"BB2 4AA",
    "sg:province":"Lancashire",
    "sg:tags":[
        "part",
        "accessory"
    ],
    "wof:name":"Steve Payne Auto Parts",
    "wof:placetype":"venue"
},
  "geometry": {"coordinates":[-2.48899,53.738609],"type":"Point"}
}