{
  "type": "Feature",
  "properties": {
    "addr:full":"39 Dames Road London Greater London E7 0DR",
    "addr:housenumber":"39",
    "addr:postcode":"e7 0dr",
    "addr:street":"Dames Road",
    "iso:country":"GB",
    "sg:address":"39 Dames Road",
    "sg:city":"London",
    "sg:classifiers":[
        {
            "category":"Bars & Pubs",
            "type":"Food & Drink"
        },
        {
            "category":"Community Center",
            "subcategory":"Social",
            "type":"Public Place"
        }
    ],
    "sg:phone":"+44 20 8257 1457",
    "sg:postcode":"E7 0DR",
    "sg:province":"Greater London",
    "sg:tags":[
        "pubs",
        "house",
        "inn",
        "activity"
    ],
    "wof:name":"The Forest Glen",
    "wof:placetype":"venue"
},
  "geometry": {"coordinates":[0.0237230007,51.5532913208],"type":"Point"}
}