{
  "type": "Feature",
  "properties": {
    "iso:country":"GB",
    "sg:address":"253 Station Rd",
    "sg:city":"Harrow",
    "sg:classifiers":[
        {
            "category":"Shopping",
            "subcategory":"Clothing, Apparel, & Fashions",
            "type":"Retail Goods"
        }
    ],
    "sg:phone":"+44 20 8427 4788",
    "sg:postcode":"HA1 2TB",
    "sg:province":"Greater London",
    "sg:tags":[
        "shop"
    ],
    "wof:name":"Chezelle",
    "wof:placetype":"venue"
},
  "geometry": {"coordinates":[-0.332368,51.582611],"type":"Point"}
}