{
  "type": "Feature",
  "properties": {
    "addr:full":"82c Mantle Street Wellington Devon TA21 8BD",
    "addr:housenumber":"82c",
    "addr:postcode":"ta21 8bd",
    "addr:street":"Mantle Street",
    "iso:country":"GB",
    "sg:address":"82c Mantle Street",
    "sg:city":"Wellington",
    "sg:classifiers":[
        {
            "category":"Home & Garden",
            "subcategory":"Household Appliances",
            "type":"Retail Goods"
        }
    ],
    "sg:postcode":"TA21 8BD",
    "sg:province":"Devon",
    "sg:tags":[
        "electrical"
    ],
    "wof:name":"Alan Dummett Electrical",
    "wof:placetype":"venue"
},
  "geometry": {"coordinates":[-3.2324090004,50.9757957458],"type":"Point"}
}