{
  "type": "Feature",
  "properties": {
    "addr:full":"68 Bridge Rd Chessington Surrey KT9 2EP",
    "addr:housenumber":"68",
    "addr:postcode":"kt9 2ep",
    "addr:street":"Bridge Rd",
    "iso:country":"GB",
    "sg:address":"68 Bridge Rd",
    "sg:city":"Chessington",
    "sg:classifiers":[
        {
            "category":"Professional",
            "type":"Services"
        }
    ],
    "sg:postcode":"KT9 2EP",
    "sg:province":"Surrey",
    "sg:tags":[
        "directory",
        "pub"
    ],
    "wof:name":"Anderson,Jacky,",
    "wof:placetype":"venue"
},
  "geometry": {"coordinates":[-0.30371,51.363098],"type":"Point"}
}