{
  "type": "Feature",
  "properties": {
    "iso:country":"GB",
    "sg:address":"16 Beulah Street",
    "sg:city":"King's Lynn",
    "sg:classifiers":[
        {
            "category":"Retail",
            "subcategory":"Auto Repair",
            "type":"Services"
        }
    ],
    "sg:phone":"+44 1553 671124",
    "sg:postcode":"PE30 4DN",
    "sg:province":"Norfolk",
    "sg:tags":[
        "modification",
        "garage",
        "related"
    ],
    "wof:name":"Souttar Services",
    "wof:placetype":"venue"
},
  "geometry": {"coordinates":[0.423696,52.761585],"type":"Point"}
}