{
  "type": "Feature",
  "properties": {
    "iso:country":"GB",
    "sg:address":"Caunton Road, Hockerton",
    "sg:city":"Southwell",
    "sg:classifiers":[
        {
            "category":"Bars & Pubs",
            "type":"Food & Drink"
        },
        {
            "category":"Community Center",
            "subcategory":"Social",
            "type":"Public Place"
        }
    ],
    "sg:phone":"+44 1636 812019",
    "sg:postcode":"NG25 0PL",
    "sg:province":"Nottinghamshire",
    "sg:tags":[
        "pubs",
        "house",
        "inn",
        "activity"
    ],
    "wof:name":"The Spread Eagle",
    "wof:placetype":"venue"
},
  "geometry": {"coordinates":[-0.929228,53.104179],"type":"Point"}
}