{
  "type": "Feature",
  "properties": {
    "addr:full":"147-149 Portobello High Street Edinburgh City of Edinburgh EH15 1AF",
    "addr:housenumber":"147-149",
    "addr:postcode":"eh15 1af",
    "addr:street":"Portobello High Street",
    "iso:country":"GB",
    "sg:address":"147-149 Portobello High Street",
    "sg:city":"Edinburgh",
    "sg:classifiers":[
        {
            "category":"Government",
            "subcategory":"City Hall",
            "type":"Public Place"
        },
        {
            "category":"Community Center",
            "type":"Public Place"
        }
    ],
    "sg:phone":"+44 131 669 5800",
    "sg:postcode":"EH15 1AF",
    "sg:province":"City of Edinburgh",
    "sg:tags":[
        "centre"
    ],
    "wof:name":"Portobello Town Hall",
    "wof:placetype":"venue"
},
  "geometry": {"coordinates":[-3.113959,55.952625],"type":"Point"}
}