{
  "type": "Feature",
  "properties": {
    "addr:full":"20 Howard Rd Wellington Devon TA21 8RU",
    "addr:housenumber":"20",
    "addr:postcode":"ta21 8ru",
    "addr:street":"Howard Rd",
    "iso:country":"GB",
    "sg:address":"20 Howard Rd",
    "sg:city":"Wellington",
    "sg:classifiers":[
        {
            "category":"Food & Beverages",
            "subcategory":"Groceries & Convenience Stores",
            "type":"Retail Goods"
        }
    ],
    "sg:phone":"+44 1823 661081",
    "sg:postcode":"TA21 8RU",
    "sg:province":"Devon",
    "wof:name":"Mini Market The",
    "wof:placetype":"venue"
},
  "geometry": {"coordinates":[-3.230342,50.982758],"type":"Point"}
}