{
  "type": "Feature",
  "properties": {
    "addr:full":"58 West Street, Tollesbury Maldon Essex CM9 8RJ",
    "addr:housenumber":"58",
    "addr:postcode":"cm9 8rj",
    "addr:street":"West Street",
    "iso:country":"GB",
    "sg:address":"58 West Street, Tollesbury",
    "sg:city":"Maldon",
    "sg:classifiers":[
        {
            "category":"Building & Trades",
            "subcategory":"Plumbing",
            "type":"Services"
        }
    ],
    "sg:phone":"+44 1621 869326",
    "sg:postcode":"CM9 8RJ",
    "sg:province":"Essex",
    "sg:tags":[
        "repair",
        "heating",
        "servicing",
        "boiler"
    ],
    "wof:name":"Tollesbury Boiler Maintenance Service Ltd",
    "wof:placetype":"venue"
},
  "geometry": {"coordinates":[0.82527,51.758873],"type":"Point"}
}