{
  "type": "Feature",
  "properties": {
    "addr:full":"Freight Terminal, Lydden Hill Dover Kent CT15 7JW",
    "addr:postcode":"ct15 7jw",
    "addr:street":"Lydden Hill Dover",
    "iso:country":"GB",
    "sg:address":"Freight Terminal, Lydden Hill",
    "sg:city":"Dover",
    "sg:classifiers":[
        {
            "category":"Freight",
            "type":"Transportation"
        }
    ],
    "sg:phone":"+44 1304 831883",
    "sg:postcode":"CT15 7JW",
    "sg:province":"Kent",
    "sg:tags":[
        "haulage",
        "road"
    ],
    "wof:name":"Comfret U K Ltd.",
    "wof:placetype":"venue"
},
  "geometry": {"coordinates":[1.236498,51.165634],"type":"Point"}
}