{
  "type": "Feature",
  "properties": {
    "addr:full":"224a Stroud Rd, Tuffley Gloucester Gloucestershire GL4 0AU",
    "addr:housenumber":"224a",
    "addr:postcode":"gl4 0au",
    "addr:street":"Stroud Rd",
    "iso:country":"GB",
    "sg:address":"224a Stroud Rd, Tuffley",
    "sg:city":"Gloucester",
    "sg:classifiers":[
        {
            "category":"Home & Garden",
            "subcategory":"Furniture",
            "type":"Retail Goods"
        }
    ],
    "sg:postcode":"GL4 0AU",
    "sg:province":"Gloucestershire",
    "wof:name":"Johnston,Barbara,",
    "wof:placetype":"venue"
},
  "geometry": {"coordinates":[-2.242611,51.839664],"type":"Point"}
}