{
  "type": "Feature",
  "properties": {
    "addr:full":"Front Street, Craghead Stanley Durham DH9 6DS",
    "addr:postcode":"dh9 6ds",
    "addr:street":"Front Street;Stanley",
    "iso:country":"GB",
    "sg:address":"Front Street, Craghead",
    "sg:city":"Stanley",
    "sg:classifiers":[
        {
            "category":"Organizations",
            "subcategory":"Membership Organization",
            "type":"Services"
        }
    ],
    "sg:phone":"+44 1207 232813",
    "sg:postcode":"DH9 6DS",
    "sg:province":"Durham",
    "sg:tags":[
        "club"
    ],
    "wof:name":"Victory Workmen's Social Club & Institute Ltd.",
    "wof:placetype":"venue"
},
  "geometry": {"coordinates":[-1.668289,54.851929],"type":"Point"}
}