{
  "type": "Feature",
  "properties": {
    "iso:country":"GB",
    "sg:address":"131 Clifton St",
    "sg:city":"Cardiff",
    "sg:classifiers":[
        {
            "category":"Personal",
            "subcategory":"Beauty Salon",
            "type":"Services"
        }
    ],
    "sg:postcode":"CF24 1LX",
    "sg:province":"Cardiff",
    "sg:tags":[
        "unisex",
        "hairdresser"
    ],
    "wof:name":"White,Leanne,",
    "wof:placetype":"venue"
},
  "geometry": {"coordinates":[-3.1583459377,51.4857292175],"type":"Point"}
}