{
  "type": "Feature",
  "properties": {
    "iso:country":"GB",
    "sg:address":"The Conifers Calford Rd, Ingham",
    "sg:city":"Bury St Edmunds",
    "sg:classifiers":[
        {
            "category":"Banks & Credit Unions",
            "subcategory":"Financial Services",
            "type":"Services"
        }
    ],
    "sg:postcode":"IP31 1NP",
    "sg:province":"Suffolk",
    "sg:tags":[
        "agent",
        "tied"
    ],
    "wof:name":"Gilliat,Joseph,& Co",
    "wof:placetype":"venue"
},
  "geometry": {"coordinates":[0.71557,52.304668],"type":"Point"}
}