{
  "type": "Feature",
  "properties": {
    "iso:country":"GB",
    "sg:address":"16 Channel Park Avenue, Efford",
    "sg:city":"Plymouth",
    "sg:classifiers":[
        {
            "category":"Arena",
            "subcategory":"Sports Club",
            "type":"Entertainment"
        }
    ],
    "sg:phone":"+44 1752 662075",
    "sg:postcode":"PL3 6LQ",
    "sg:province":"Devon",
    "wof:name":"Beacon Castle Sports & Social Club",
    "wof:placetype":"venue"
},
  "geometry": {"coordinates":[-4.1144900322,50.3854598999],"type":"Point"}
}