{
  "type": "Feature",
  "properties": {
    "iso:country":"GB",
    "sg:address":"Mentone, Vicarage Road",
    "sg:city":"Sidmouth",
    "sg:classifiers":[
        {
            "category":"Building & Trades",
            "subcategory":"Construction",
            "type":"Services"
        }
    ],
    "sg:phone":"+44 1395 512698",
    "sg:postcode":"EX10 8TS",
    "sg:province":"Devon",
    "sg:tags":[
        "glazier"
    ],
    "wof:name":"R Titherington",
    "wof:placetype":"venue"
},
  "geometry": {"coordinates":[-3.238259,50.683392],"type":"Point"}
}