{
  "type": "Feature",
  "properties": {
    "addr:full":"Crabtree Farm, Park Lane, Colton Rugeley Staffordshire WS15 3LX",
    "addr:postcode":"ws15 3lx",
    "addr:street":"Park Lane",
    "iso:country":"GB",
    "sg:address":"Crabtree Farm, Park Lane, Colton",
    "sg:city":"Rugeley",
    "sg:classifiers":[
        {
            "category":"Farming",
            "subcategory":"Dairy Farm",
            "type":"Manufacturing & Wholesale Goods"
        }
    ],
    "sg:postcode":"WS15 3LX",
    "sg:province":"Staffordshire",
    "wof:name":"W E Knight & Son",
    "wof:placetype":"venue"
},
  "geometry": {"coordinates":[-1.937324,52.78326],"type":"Point"}
}