{
  "type": "Feature",
  "properties": {
    "iso:country":"GB",
    "sg:address":"37 Hall Lane, Hindley",
    "sg:city":"Wigan",
    "sg:classifiers":[
        {
            "category":"Professional",
            "subcategory":"Accounting & Tax Preparation",
            "type":"Services"
        }
    ],
    "sg:phone":"+44 1942 255331",
    "sg:postcode":"WN2 2SA",
    "sg:province":"Lancashire",
    "sg:tags":[
        "accountant"
    ],
    "wof:name":"Myers Business Services",
    "wof:placetype":"venue"
},
  "geometry": {"coordinates":[-2.576535,53.54425],"type":"Point"}
}