{
  "type": "Feature",
  "properties": {
    "iso:country":"GB",
    "sg:address":"Villa Joyosa, Orby Road, Addlethorpe",
    "sg:city":"Skegness",
    "sg:classifiers":[
        {
            "category":"Military Area",
            "subcategory":"Air Force Base",
            "type":"Public Place"
        }
    ],
    "sg:phone":"+44 1754 871871",
    "sg:postcode":"PE24 4TR",
    "sg:province":"Lincolnshire",
    "sg:tags":[
        "taxi",
        "hire",
        "private"
    ],
    "wof:name":"Ingoldmells Taxis",
    "wof:placetype":"venue"
},
  "geometry": {"coordinates":[0.3181799948,53.1951942444],"type":"Point"}
}