{
  "type": "Feature",
  "properties": {
    "addr:full":"Units 1, 2 +3 County House Wickford Essex SS11 8BR",
    "addr:housenumber":"units 1 2 + 3 county",
    "addr:postcode":"ss11 8br",
    "iso:country":"GB",
    "sg:address":"Units 1, 2 +3 County House",
    "sg:city":"Wickford",
    "sg:classifiers":[
        {
            "category":"Retail",
            "subcategory":"Storage",
            "type":"Services"
        }
    ],
    "sg:phone":"+44 1268 573232",
    "sg:postcode":"SS11 8BR",
    "sg:province":"Essex",
    "sg:tags":[
        "household",
        "removal"
    ],
    "wof:name":"Bridger Removals",
    "wof:placetype":"venue"
},
  "geometry": {"coordinates":[0.53631,51.6077],"type":"Point"}
}