{
  "type": "Feature",
  "properties": {
    "addr:full":"74b Warrington Rd Warrington Cheshire WA3 5NH",
    "addr:housenumber":"74b",
    "addr:postcode":"wa3 5nh",
    "addr:street":"Warrington Rd",
    "iso:country":"GB",
    "sg:address":"74b Warrington Rd",
    "sg:city":"Warrington",
    "sg:classifiers":[
        {
            "category":"Manufacturing",
            "subcategory":"Metals",
            "type":"Manufacturing & Wholesale Goods"
        }
    ],
    "sg:phone":"+44 1925 791500",
    "sg:postcode":"WA3 5NH",
    "sg:province":"Cheshire",
    "sg:tags":[
        "work",
        "sheet"
    ],
    "wof:name":"Steve Lycett",
    "wof:placetype":"venue"
},
  "geometry": {"coordinates":[-2.495296,53.471996],"type":"Point"}
}