{
  "type": "Feature",
  "properties": {
    "addr:full":"Bluestem Road, Ransomes Industrial Estate Ipswich Suffolk IP3 9RR",
    "addr:postcode":"ip3 9rr",
    "addr:street":"Bluestem Road Ransomes Industrial Estate",
    "iso:country":"GB",
    "sg:address":"Bluestem Road, Ransomes Industrial Estate",
    "sg:city":"Ipswich",
    "sg:classifiers":[
        {
            "category":"Professional",
            "subcategory":"Business Services",
            "type":"Services"
        }
    ],
    "sg:postcode":"IP3 9RR",
    "sg:province":"Suffolk",
    "sg:tags":[
        "import",
        "export",
        "agent"
    ],
    "wof:name":"Ocean World Lines Europe",
    "wof:placetype":"venue"
},
  "geometry": {"coordinates":[1.2028579712,52.0301971436],"type":"Point"}
}