{
  "type": "Feature",
  "properties": {
    "addr:full":"4 Beechfield Road Bromley Kent BR1 3BU",
    "addr:housenumber":"4",
    "addr:postcode":"br1 3bu",
    "addr:street":"Beechfield Road",
    "iso:country":"GB",
    "sg:address":"4 Beechfield Road",
    "sg:city":"Bromley",
    "sg:classifiers":[
        {
            "category":"Building & Trades",
            "subcategory":"Pest Control",
            "type":"Services"
        }
    ],
    "sg:postcode":"BR1 3BU",
    "sg:province":"Kent",
    "sg:tags":[
        "vermin"
    ],
    "wof:name":"Wasp Busters",
    "wof:placetype":"venue"
},
  "geometry": {"coordinates":[0.03231,51.404549],"type":"Point"}
}