{
  "type": "Feature",
  "properties": {
    "addr:full":"21 Morrison Drive Dunfermline Fife KY11 8DJ",
    "addr:housenumber":"21",
    "addr:postcode":"ky11 8dj",
    "addr:street":"Morrison Drive",
    "iso:country":"GB",
    "sg:address":"21 Morrison Drive",
    "sg:city":"Dunfermline",
    "sg:classifiers":[
        {
            "category":"Organizations",
            "subcategory":"Non-profit Organization",
            "type":"Services"
        }
    ],
    "sg:phone":"+44 1383 736084",
    "sg:postcode":"KY11 8DJ",
    "sg:province":"Fife",
    "sg:tags":[
        "organisation",
        "voluntary",
        "charity"
    ],
    "wof:name":"Congenital Muscular Dystrophy",
    "wof:placetype":"venue"
},
  "geometry": {"coordinates":[-3.4178988934,56.0582733154],"type":"Point"}
}