{
  "type": "Feature",
  "properties": {
    "iso:country":"GB",
    "sg:address":"Filmer Road",
    "sg:city":"London",
    "sg:classifiers":[
        {
            "category":"Education",
            "subcategory":"School",
            "type":"Public Place"
        }
    ],
    "sg:phone":"+44 20 7731 5454",
    "sg:postcode":"SW6 6AS",
    "sg:province":"Greater London",
    "sg:tags":[
        "local",
        "authority"
    ],
    "wof:name":"St John's C of E Primary School",
    "wof:placetype":"venue"
},
  "geometry": {"coordinates":[-0.208851,51.476997],"type":"Point"}
}