{
  "type": "Feature",
  "properties": {
    "addr:full":"4 Crescent West Thornton-cleveleys Lancashire FY5 1AD",
    "addr:housenumber":"4",
    "addr:postcode":"fy5 1ad",
    "addr:street":"Crescent West Thornton-Cleveleys",
    "iso:country":"GB",
    "sg:address":"4 Crescent West",
    "sg:city":"Thornton-cleveleys",
    "sg:classifiers":[
        {
            "category":"Shopping",
            "subcategory":"Discount & Variety Stores",
            "type":"Retail Goods"
        }
    ],
    "sg:phone":"+44 1253 852020",
    "sg:postcode":"FY5 1AD",
    "sg:province":"Lancashire",
    "sg:tags":[
        "centre"
    ],
    "wof:name":"Adorn Discount Cosmetics",
    "wof:placetype":"venue"
},
  "geometry": {"coordinates":[-3.040927,53.876865],"type":"Point"}
}