{
  "type": "Feature",
  "properties": {
    "iso:country":"GB",
    "sg:address":"18 The Downs",
    "sg:city":"Altrincham",
    "sg:classifiers":[
        {
            "category":"Professional",
            "subcategory":"Lawyer & Legal Services",
            "type":"Services"
        }
    ],
    "sg:phone":"+44 161 929 8107",
    "sg:postcode":"WA14 2PU",
    "sg:province":"Cheshire",
    "sg:tags":[
        "solicitor"
    ],
    "wof:name":"Hamiltons Solicitors",
    "wof:placetype":"venue"
},
  "geometry": {"coordinates":[-2.352944,53.384354],"type":"Point"}
}