{
  "type": "Feature",
  "properties": {
    "addr:full":"Kent Street Leicester Leicestershire LE2 0AY",
    "addr:postcode":"le2 0ay",
    "addr:street":"Kent Street",
    "iso:country":"GB",
    "sg:address":"Kent Street",
    "sg:city":"Leicester",
    "sg:classifiers":[
        {
            "category":"Home & Garden",
            "subcategory":"Kitchen Supply",
            "type":"Retail Goods"
        }
    ],
    "sg:phone":"+44 116 251 3217",
    "sg:postcode":"LE2 0AY",
    "sg:province":"Leicestershire",
    "sg:tags":[
        "confectioner",
        "baker",
        "bakery",
        "equipment"
    ],
    "wof:name":"Leicester Bakery Ltd",
    "wof:placetype":"venue"
},
  "geometry": {"coordinates":[-1.1176439524,52.6371116638],"type":"Point"}
}