{
  "type": "Feature",
  "properties": {
    "iso:country":"GB",
    "sg:address":"Warrington Road, Rainhill",
    "sg:city":"Prescot",
    "sg:classifiers":[
        {
            "category":"Education",
            "subcategory":"School",
            "type":"Public Place"
        },
        {
            "category":"Government",
            "subcategory":"Office",
            "type":"Public Place"
        }
    ],
    "sg:phone":"+44 1744 677205",
    "sg:postcode":"L35 6NY",
    "sg:province":"Cheshire",
    "sg:tags":[
        "local",
        "authority"
    ],
    "wof:name":"Rainhill High School",
    "wof:placetype":"venue"
},
  "geometry": {"coordinates":[-2.750623,53.40493],"type":"Point"}
}