{
  "type": "Feature",
  "properties": {
    "iso:country":"GB",
    "sg:address":"Unit 32 Hobbs Indstl Est",
    "sg:city":"Lingfield",
    "sg:classifiers":[
        {
            "category":"Professional",
            "subcategory":"Printing & Photocopies",
            "type":"Services"
        }
    ],
    "sg:postcode":"RH7 6HL",
    "sg:province":"Surrey",
    "sg:tags":[
        "printer"
    ],
    "wof:name":"Broad,Arthur,Associates",
    "wof:placetype":"venue"
},
  "geometry": {"coordinates":[-0.019686,51.17482],"type":"Point"}
}