{
  "type": "Feature",
  "properties": {
    "iso:country":"GB",
    "sg:address":"Unit 9 Rumer Hill Business Estate",
    "sg:city":"Cannock",
    "sg:classifiers":[
        {
            "category":"Social Services",
            "type":"Services"
        }
    ],
    "sg:phone":"+44 1543 570341",
    "sg:postcode":"WS11 3ET",
    "sg:province":"Staffordshire",
    "sg:tags":[
        "disability"
    ],
    "wof:name":"Disabled Aids",
    "wof:placetype":"venue"
},
  "geometry": {"coordinates":[-2.023437,52.682632],"type":"Point"}
}