{
  "type": "Feature",
  "properties": {
    "addr:full":"Elvingston Tranent East Lothian EH33 1EH",
    "addr:postcode":"eh33 1eh",
    "iso:country":"GB",
    "sg:address":"Elvingston",
    "sg:city":"Tranent",
    "sg:classifiers":[
        {
            "category":"Professional",
            "subcategory":"Business Services",
            "type":"Services"
        },
        {
            "category":"Military Area",
            "subcategory":"Air Force Base",
            "type":"Public Place"
        }
    ],
    "sg:phone":"+44 1875 408000",
    "sg:postcode":"EH33 1EH",
    "sg:province":"East Lothian",
    "sg:tags":[
        "manufacture",
        "accomodation",
        "component",
        "electronic",
        "equipment"
    ],
    "wof:name":"ELVINGSTON SCIENCE CENTRE",
    "wof:placetype":"venue"
},
  "geometry": {"coordinates":[-2.953759,55.944515],"type":"Point"}
}