{
  "type": "Feature",
  "properties": {
    "addr:full":"2 Hendford Yeovil Somerset BA20 1TN",
    "addr:housenumber":"2",
    "addr:postcode":"ba20 1tn",
    "addr:street":"Hendford",
    "iso:country":"GB",
    "sg:address":"2 Hendford",
    "sg:city":"Yeovil",
    "sg:classifiers":[
        {
            "category":"Banks & Credit Unions",
            "subcategory":"Bank",
            "type":"Services"
        }
    ],
    "sg:phone":"+44 23 8022 6443",
    "sg:postcode":"BA20 1TN",
    "sg:province":"Somerset",
    "sg:tags":[
        "financial",
        "institution"
    ],
    "wof:name":"National Westminster Bank Plc",
    "wof:placetype":"venue"
},
  "geometry": {"coordinates":[-2.634171,50.941307],"type":"Point"}
}