{
  "type": "Feature",
  "properties": {
    "addr:full":"Froghall Terrace Aberdeen Aberdeen City AB24 3JN",
    "addr:postcode":"ab24 3jn",
    "addr:street":"Froghall Terrace",
    "iso:country":"GB",
    "sg:address":"Froghall Terrace",
    "sg:city":"Aberdeen",
    "sg:classifiers":[
        {
            "category":"Home & Garden",
            "subcategory":"Building Materials",
            "type":"Retail Goods"
        },
        {
            "category":"Home & Garden",
            "subcategory":"Hardware",
            "type":"Retail Goods"
        }
    ],
    "sg:phone":"+44 1224 788400",
    "sg:postcode":"AB24 3JN",
    "sg:province":"Aberdeen City",
    "sg:tags":[
        "paint",
        "manufacturer"
    ],
    "wof:name":"Spencer Coatings Ltd",
    "wof:placetype":"venue"
},
  "geometry": {"coordinates":[-2.100644,57.158176],"type":"Point"}
}