{
  "type": "Feature",
  "properties": {
    "addr:full":"The Scout Hall, Linden Park Littlehampton West Sussex BN17 7BH",
    "addr:postcode":"bn17 7bh",
    "addr:street":"Park",
    "iso:country":"GB",
    "sg:address":"The Scout Hall, Linden Park",
    "sg:city":"Littlehampton",
    "sg:classifiers":[
        {
            "category":"Organizations",
            "subcategory":"Membership Organization",
            "type":"Services"
        }
    ],
    "sg:phone":"+44 1903 731536",
    "sg:postcode":"BN17 7BH",
    "sg:province":"West Sussex",
    "sg:tags":[
        "club"
    ],
    "wof:name":"4th Littlehampton Scouts",
    "wof:placetype":"venue"
},
  "geometry": {"coordinates":[-0.5389590263,50.8210296631],"type":"Point"}
}