{
  "type": "Feature",
  "properties": {
    "addr:full":"14 Teanlowe Centre Poulton-le-fylde Lancashire FY6 7DF",
    "addr:housenumber":"14",
    "addr:postcode":"fy6 7df",
    "addr:street":"Teanlowe;Poulton-Le-Fylde",
    "iso:country":"GB",
    "sg:address":"14 Teanlowe Centre",
    "sg:city":"Poulton-le-fylde",
    "sg:classifiers":[
        {
            "category":"Shopping",
            "subcategory":"Shoes",
            "type":"Retail Goods"
        }
    ],
    "sg:phone":"+44 1253 883435",
    "sg:postcode":"FY6 7DF",
    "sg:province":"Lancashire",
    "sg:tags":[
        "shop",
        "retailer",
        "footwear"
    ],
    "sg:website":"http://www.clarks.co.uk",
    "wof:name":"Clarks Shoes Ltd",
    "wof:placetype":"venue"
},
  "geometry": {"coordinates":[-2.994658947,53.8480796814],"type":"Point"}
}