{
  "type": "Feature",
  "properties": {
    "iso:country":"GB",
    "sg:address":"Sun Alliance House, 166-167 St Helens Road",
    "sg:city":"Swansea",
    "sg:classifiers":[
        {
            "category":"Professional",
            "subcategory":"Lawyer & Legal Services",
            "type":"Services"
        }
    ],
    "sg:phone":"+44 1792 463111",
    "sg:postcode":"SA1 4DQ",
    "sg:province":"Neath Port Talbot",
    "sg:tags":[
        "solicitor"
    ],
    "wof:name":"Kearns & Co.",
    "wof:placetype":"venue"
},
  "geometry": {"coordinates":[-3.951218,51.619102],"type":"Point"}
}