{
  "type": "Feature",
  "properties": {
    "iso:country":"GB",
    "sg:address":"13 Gelliwastad Road",
    "sg:city":"Pontypridd",
    "sg:classifiers":[
        {
            "category":"Real Estate",
            "subcategory":"Surveying",
            "type":"Services"
        }
    ],
    "sg:phone":"+44 1443 491800",
    "sg:postcode":"CF37 2BW",
    "sg:province":"Caerphilly",
    "sg:tags":[
        "surveyor",
        "valuer"
    ],
    "wof:name":"Peter Simmons",
    "wof:placetype":"venue"
},
  "geometry": {"coordinates":[-3.3409678936,51.6039581299],"type":"Point"}
}