{
  "type": "Feature",
  "properties": {
    "addr:full":"Elm Grove, Wimbledon London Greater London SW19 4HE",
    "addr:postcode":"sw19 4he",
    "addr:street":"Elm Grove",
    "iso:country":"GB",
    "sg:address":"Elm Grove, Wimbledon",
    "sg:city":"London",
    "sg:classifiers":[
        {
            "category":"Retail",
            "subcategory":"Auto Repair",
            "type":"Services"
        }
    ],
    "sg:phone":"+44 20 8947 0234",
    "sg:postcode":"SW19 4HE",
    "sg:province":"Greater London",
    "sg:tags":[
        "modification",
        "garage"
    ],
    "wof:name":"Elm Autosales Ltd.",
    "wof:placetype":"venue"
},
  "geometry": {"coordinates":[-0.21514,51.4168701172],"type":"Point"}
}