{
  "type": "Feature",
  "properties": {
    "iso:country":"GB",
    "sg:address":"4 Turberville Rd",
    "sg:city":"Wareham",
    "sg:classifiers":[
        {
            "category":"Building & Trades",
            "subcategory":"Construction",
            "type":"Services"
        }
    ],
    "sg:postcode":"BH20 7HA",
    "sg:province":"Dorset",
    "sg:tags":[
        "builder"
    ],
    "wof:name":"Burry,John,",
    "wof:placetype":"venue"
},
  "geometry": {"coordinates":[-2.218726,50.752991],"type":"Point"}
}