{
  "type": "Feature",
  "properties": {
    "addr:full":"West End Rd Ruislip Greater London HA4 6QX",
    "addr:postcode":"ha4 6qx",
    "addr:street":"West End Rd",
    "iso:country":"GB",
    "sg:address":"West End Rd",
    "sg:city":"Ruislip",
    "sg:classifiers":[
        {
            "category":"Government",
            "subcategory":"City Hall",
            "type":"Public Place"
        }
    ],
    "sg:phone":"+44 20 8841 2468",
    "sg:postcode":"HA4 6QX",
    "sg:province":"Greater London",
    "wof:name":"Emerald Rooms Ltd The",
    "wof:placetype":"venue"
},
  "geometry": {"coordinates":[-0.4142239988,51.5633850098],"type":"Point"}
}