{
  "type": "Feature",
  "properties": {
    "addr:full":"4 Quarry Road Street Somerset BA16 0RB",
    "addr:housenumber":"4",
    "addr:postcode":"ba16 0rb",
    "addr:street":"Quarry Road Street",
    "iso:country":"GB",
    "sg:address":"4 Quarry Road",
    "sg:city":"Street",
    "sg:classifiers":[
        {
            "category":"Building & Trades",
            "subcategory":"Plumbing",
            "type":"Services"
        }
    ],
    "sg:phone":"+44 1458 443019",
    "sg:postcode":"BA16 0RB",
    "sg:province":"Somerset",
    "sg:tags":[
        "plumber",
        "heating"
    ],
    "wof:name":"D T Foley Plumbing & Heating",
    "wof:placetype":"venue"
},
  "geometry": {"coordinates":[-2.74718,51.118137],"type":"Point"}
}