{
  "type": "Feature",
  "properties": {
    "iso:country":"GB",
    "sg:address":"Free Methodist Church, Aldermans Green Rd",
    "sg:city":"Coventry",
    "sg:classifiers":[
        {
            "category":"Organizations",
            "subcategory":"Religious Organization",
            "type":"Services"
        }
    ],
    "sg:phone":"+44 24 7658 1800",
    "sg:postcode":"CV2 1PP",
    "sg:province":"Warwickshire",
    "sg:tags":[
        "organisation"
    ],
    "wof:name":"B.A.M Gospel Trust",
    "wof:placetype":"venue"
},
  "geometry": {"coordinates":[-1.47315,52.4454],"type":"Point"}
}