{
  "type": "Feature",
  "properties": {
    "addr:full":"Queens Road Freshwater Isle of Wight PO40 9ES",
    "addr:postcode":"po40 9es",
    "addr:street":"Queens Road",
    "iso:country":"GB",
    "sg:address":"Queens Road",
    "sg:city":"Freshwater",
    "sg:classifiers":[
        {
            "category":"Organizations",
            "subcategory":"Political Organization",
            "type":"Services"
        },
        {
            "category":"Organizations",
            "subcategory":"Membership Organization",
            "type":"Services"
        }
    ],
    "sg:phone":"+44 1983 752988",
    "sg:postcode":"PO40 9ES",
    "sg:province":"Isle of Wight",
    "sg:tags":[
        "club",
        "party",
        "social"
    ],
    "wof:name":"Freshwater Conservative Club",
    "wof:placetype":"venue"
},
  "geometry": {"coordinates":[-1.526069,50.682549],"type":"Point"}
}