{
  "type": "Feature",
  "properties": {
    "iso:country":"GB",
    "sg:address":"363 Chipperfield Road",
    "sg:city":"Orpington",
    "sg:classifiers":[
        {
            "category":"Food & Beverages",
            "subcategory":"Meat & Fish",
            "type":"Retail Goods"
        }
    ],
    "sg:phone":"+44 1689 827174",
    "sg:postcode":"BR5 2LJ",
    "sg:province":"Kent",
    "sg:tags":[
        "chip"
    ],
    "wof:name":"Gundee's Place",
    "wof:placetype":"venue"
},
  "geometry": {"coordinates":[0.10684,51.397911],"type":"Point"}
}