{
  "type": "Feature",
  "properties": {
    "addr:full":"418-420 Cranbrook Road, Gants Hill Ilford Essex IG2 6HW",
    "addr:housenumber":"418-420",
    "addr:postcode":"ig2 6hw",
    "addr:street":"Cranbrook Road",
    "iso:country":"GB",
    "sg:address":"418-420 Cranbrook Road, Gants Hill",
    "sg:city":"Ilford",
    "sg:classifiers":[
        {
            "category":"Professional",
            "subcategory":"Accounting & Tax Preparation",
            "type":"Services"
        }
    ],
    "sg:postcode":"IG2 6HW",
    "sg:province":"Essex",
    "sg:tags":[
        "accountant"
    ],
    "wof:name":"Edwin K Frederick & Co.",
    "wof:placetype":"venue"
},
  "geometry": {"coordinates":[0.0664080009,51.5760345459],"type":"Point"}
}