{
  "type": "Feature",
  "properties": {
    "addr:full":"70 Portway Didcot Oxfordshire OX11 0AZ",
    "addr:housenumber":"70",
    "addr:postcode":"ox11 0az",
    "addr:street":"Portway Didcot",
    "iso:country":"GB",
    "sg:address":"70 Portway",
    "sg:city":"Didcot",
    "sg:classifiers":[
        {
            "category":"Building & Trades",
            "subcategory":"Landscaping Services",
            "type":"Services"
        }
    ],
    "sg:phone":"+44 1235 815038",
    "sg:postcode":"OX11 0AZ",
    "sg:province":"Oxfordshire",
    "sg:tags":[
        "gardening"
    ],
    "wof:name":"C Mortlock",
    "wof:placetype":"venue"
},
  "geometry": {"coordinates":[-1.2605090141,51.6006317139],"type":"Point"}
}