{
  "type": "Feature",
  "properties": {
    "addr:full":"2 Oakley Villas Stockport Cheshire SK4 3LJ",
    "addr:housenumber":"2",
    "addr:postcode":"sk4 3lj",
    "addr:street":"Oakley Villas",
    "iso:country":"GB",
    "sg:address":"2 Oakley Villas",
    "sg:city":"Stockport",
    "sg:classifiers":[
        {
            "category":"Landmark",
            "subcategory":"Tourist Information",
            "type":"Public Place"
        }
    ],
    "sg:phone":"+44 161 431 9663",
    "sg:postcode":"SK4 3LJ",
    "sg:province":"Cheshire",
    "sg:tags":[
        "tour",
        "guide",
        "sightseeing"
    ],
    "wof:name":"Christian Holidays & Tours",
    "wof:placetype":"venue"
},
  "geometry": {"coordinates":[-2.185152,53.416908],"type":"Point"}
}