{
  "type": "Feature",
  "properties": {
    "addr:full":"13 Bedford Close, Chenies Rickmansworth Hertfordshire WD3 6EJ",
    "addr:housenumber":"13",
    "addr:postcode":"chenies;wd3 6ej",
    "addr:street":"Bedford Close",
    "iso:country":"GB",
    "sg:address":"13 Bedford Close, Chenies",
    "sg:city":"Rickmansworth",
    "sg:classifiers":[
        {
            "category":"Professional",
            "subcategory":"Art Services",
            "type":"Services"
        }
    ],
    "sg:phone":"+44 1494 764127",
    "sg:postcode":"WD3 6EJ",
    "sg:province":"Hertfordshire",
    "sg:tags":[
        "graphic",
        "designer"
    ],
    "wof:name":"Viv Bernard",
    "wof:placetype":"venue"
},
  "geometry": {"coordinates":[-0.5306400061,51.6725540161],"type":"Point"}
}