{
  "type": "Feature",
  "properties": {
    "addr:full":"Unit 24, Melmerby Industrial Estate Ripon North Yorkshire HG4 5HP",
    "addr:housenumber":"unit 24 melmerby",
    "addr:postcode":"hg4 5hp",
    "addr:street":"Industrial Estate",
    "iso:country":"GB",
    "sg:address":"Unit 24, Melmerby Industrial Estate",
    "sg:city":"Ripon",
    "sg:classifiers":[
        {
            "category":"Retail",
            "subcategory":"Auto Repair",
            "type":"Services"
        }
    ],
    "sg:phone":"+44 1765 640667",
    "sg:postcode":"HG4 5HP",
    "sg:province":"North Yorkshire",
    "sg:tags":[
        "modification",
        "garage"
    ],
    "wof:name":"Roger Clarke",
    "wof:placetype":"venue"
},
  "geometry": {"coordinates":[-1.4724010229,54.1704750061],"type":"Point"}
}