{
  "type": "Feature",
  "properties": {
    "addr:full":"185 Front Street Chester-le-street Durham DH3 3AX",
    "addr:housenumber":"185",
    "addr:postcode":"dh3 3ax",
    "addr:street":"Front Street",
    "iso:country":"GB",
    "sg:address":"185 Front Street",
    "sg:city":"Chester-le-street",
    "sg:classifiers":[
        {
            "category":"Fast Food",
            "type":"Food & Drink"
        }
    ],
    "sg:phone":"+44 191 389 1079",
    "sg:postcode":"DH3 3AX",
    "sg:province":"Durham",
    "sg:tags":[
        "away",
        "take"
    ],
    "wof:name":"Happy Garden",
    "wof:placetype":"venue"
},
  "geometry": {"coordinates":[-1.573619,54.853161],"type":"Point"}
}