{
  "type": "Feature",
  "properties": {
    "addr:full":"Island House, Priestland Place Lymington Hampshire SO41 9GA",
    "addr:postcode":"so41 9ga",
    "addr:street":"Priestland Place",
    "iso:country":"GB",
    "sg:address":"Island House, Priestland Place",
    "sg:city":"Lymington",
    "sg:classifiers":[
        {
            "category":"Government",
            "subcategory":"Office",
            "type":"Public Place"
        }
    ],
    "sg:phone":"+44 1590 673107",
    "sg:postcode":"SO41 9GA",
    "sg:province":"Hampshire",
    "sg:tags":[
        "central"
    ],
    "wof:name":"National Probation Service for England & Wales",
    "wof:placetype":"venue"
},
  "geometry": {"coordinates":[-1.538911,50.758938],"type":"Point"}
}