{
  "type": "Feature",
  "properties": {
    "addr:full":"50 Albert Street Dundee Dundee City DD4 6QQ",
    "addr:housenumber":"50",
    "addr:postcode":"dd4 6qq",
    "addr:street":"Albert Street",
    "iso:country":"GB",
    "sg:address":"50 Albert Street",
    "sg:city":"Dundee",
    "sg:classifiers":[
        {
            "category":"Professional",
            "subcategory":"Business Services",
            "type":"Services"
        },
        {
            "category":"Professional",
            "subcategory":"Printing & Photocopies",
            "type":"Services"
        }
    ],
    "sg:postcode":"DD4 6QQ",
    "sg:province":"Dundee City",
    "sg:tags":[
        "trophy",
        "import",
        "export",
        "agent"
    ],
    "wof:name":"Trophy World",
    "wof:placetype":"venue"
},
  "geometry": {"coordinates":[-2.957846,56.469353],"type":"Point"}
}