{
  "type": "Feature",
  "properties": {
    "addr:full":"69 Coutts Road Newcastle-upon-tyne Tyne and Wear NE6 4RA",
    "addr:housenumber":"69",
    "addr:postcode":"ne6 4ra",
    "addr:street":"Coutts Road",
    "iso:country":"GB",
    "sg:address":"69 Coutts Road",
    "sg:city":"Newcastle-upon-tyne",
    "sg:classifiers":[
        {
            "category":"Food & Beverages",
            "subcategory":"Fruits & Vegetables",
            "type":"Retail Goods"
        }
    ],
    "sg:phone":"+44 191 276 6610",
    "sg:postcode":"NE6 4RA",
    "sg:province":"Tyne and Wear",
    "sg:tags":[
        "greengrocer"
    ],
    "wof:name":"Ali Store",
    "wof:placetype":"venue"
},
  "geometry": {"coordinates":[-1.5577219725,54.9836425781],"type":"Point"}
}