{
  "type": "Feature",
  "properties": {
    "addr:full":"Treetop Cottage, Ovington Alresford Hampshire SO24 0RB",
    "addr:postcode":"so24 0rb",
    "iso:country":"GB",
    "sg:address":"Treetop Cottage, Ovington",
    "sg:city":"Alresford",
    "sg:classifiers":[
        {
            "category":"Professional",
            "subcategory":"Management & Consulting",
            "type":"Services"
        }
    ],
    "sg:phone":"+44 1962 736683",
    "sg:postcode":"SO24 0RB",
    "sg:province":"Hampshire",
    "sg:tags":[
        "consultant",
        "business"
    ],
    "wof:name":"Scanmost Ltd",
    "wof:placetype":"venue"
},
  "geometry": {"coordinates":[-1.200759,51.082031],"type":"Point"}
}