{
  "type": "Feature",
  "properties": {
    "addr:full":"4 Davies Street London Greater London W1K 3DW",
    "addr:housenumber":"4",
    "addr:postcode":"w1k 3dw",
    "addr:street":"Davies Street",
    "iso:country":"GB",
    "sg:address":"4 Davies Street",
    "sg:city":"London",
    "sg:classifiers":[
        {
            "category":"Shopping",
            "subcategory":"Department Store",
            "type":"Retail Goods"
        },
        {
            "category":"Arts & Performance",
            "subcategory":"Art Gallery",
            "type":"Entertainment"
        }
    ],
    "sg:phone":"+44 20 7491 3435",
    "sg:postcode":"W1K 3DW",
    "sg:province":"Greater London",
    "wof:name":"Mayfair Galleries Ltd.",
    "wof:placetype":"venue"
},
  "geometry": {"coordinates":[-0.1474319994,51.5110321045],"type":"Point"}
}