{
  "type": "Feature",
  "properties": {
    "addr:full":"17 Foundry Street Dewsbury West Yorkshire WF13 1QL",
    "addr:housenumber":"17",
    "addr:postcode":"wf13 1ql",
    "addr:street":"Foundry Street",
    "iso:country":"GB",
    "sg:address":"17 Foundry Street",
    "sg:city":"Dewsbury",
    "sg:classifiers":[
        {
            "category":"Banks & Credit Unions",
            "subcategory":"Financial Services",
            "type":"Services"
        }
    ],
    "sg:phone":"+44 1924 469206",
    "sg:postcode":"WF13 1QL",
    "sg:province":"West Yorkshire",
    "sg:tags":[
        "building",
        "society"
    ],
    "wof:name":"Leeds & Holbeck Building Society",
    "wof:placetype":"venue"
},
  "geometry": {"coordinates":[-1.6289809942,53.6929321289],"type":"Point"}
}