{
  "type": "Feature",
  "properties": {
    "iso:country":"GB",
    "sg:address":"32 Ferney Court, Ferney Road, Byfleet",
    "sg:city":"West Byfleet",
    "sg:classifiers":[
        {
            "category":"Social Services",
            "subcategory":"Adult Care",
            "type":"Services"
        },
        {
            "category":"Government",
            "subcategory":"Office",
            "type":"Public Place"
        }
    ],
    "sg:phone":"+44 1932 344713",
    "sg:postcode":"KT14 7BB",
    "sg:province":"Surrey",
    "sg:tags":[
        "housing",
        "local",
        "sheltered"
    ],
    "wof:name":"Ferney Court Sheltered Housing",
    "wof:placetype":"venue"
},
  "geometry": {"coordinates":[-0.481902,51.3428],"type":"Point"}
}