{
  "type": "Feature",
  "properties": {
    "addr:full":"80 Bottesford Road Scunthorpe Lincolnshire DN16 3HN",
    "addr:housenumber":"80",
    "addr:postcode":"dn16 3hn",
    "addr:street":"Bottesford Road",
    "iso:country":"GB",
    "sg:address":"80 Bottesford Road",
    "sg:city":"Scunthorpe",
    "sg:classifiers":[
        {
            "category":"Utilities",
            "subcategory":"Fuel Oil & Lpg",
            "type":"Services"
        }
    ],
    "sg:phone":"+44 1724 271911",
    "sg:postcode":"DN16 3HN",
    "sg:province":"Lincolnshire",
    "sg:tags":[
        "coal",
        "smokeless"
    ],
    "wof:name":"W R Drury & Son",
    "wof:placetype":"venue"
},
  "geometry": {"coordinates":[-0.64678,53.562065],"type":"Point"}
}