{
  "type": "Feature",
  "properties": {
    "iso:country":"GB",
    "sg:address":"Green Farm, Barton Le Willows",
    "sg:city":"York",
    "sg:classifiers":[
        {
            "category":"Farming",
            "subcategory":"Farm",
            "type":"Manufacturing & Wholesale Goods"
        }
    ],
    "sg:phone":"+44 1653 618387",
    "sg:postcode":"YO60 7PD",
    "sg:province":"North Yorkshire",
    "sg:tags":[
        "mixed",
        "crop"
    ],
    "wof:name":"K H Hudson",
    "wof:placetype":"venue"
},
  "geometry": {"coordinates":[-0.911344,54.061539],"type":"Point"}
}