{
  "type": "Feature",
  "properties": {
    "addr:full":"Pontefract Road, Ackworth Pontefract West Yorkshire WF7 5AA",
    "addr:postcode":"wf7 5aa",
    "addr:street":"Pontefract Road;Pontefract West",
    "iso:country":"GB",
    "sg:address":"Pontefract Road, Ackworth",
    "sg:city":"Pontefract",
    "sg:classifiers":[
        {
            "category":"Bars & Pubs",
            "type":"Food & Drink"
        }
    ],
    "sg:phone":"+44 1977 704735",
    "sg:postcode":"WF7 5AA",
    "sg:province":"West Yorkshire",
    "sg:tags":[
        "pubs",
        "inn"
    ],
    "wof:name":"Tibsco Ltd.",
    "wof:placetype":"venue"
},
  "geometry": {"coordinates":[-1.3372440338,53.6792831421],"type":"Point"}
}