{
  "type": "Feature",
  "properties": {
    "iso:country":"GB",
    "sg:address":"38 Southside Street, The Barbican",
    "sg:city":"Plymouth",
    "sg:classifiers":[
        {
            "category":"Food & Beverages",
            "subcategory":"Bakery",
            "type":"Retail Goods"
        }
    ],
    "sg:postcode":"PL1 2LE",
    "sg:province":"Devon",
    "sg:tags":[
        "baker"
    ],
    "wof:name":"F H Jacka",
    "wof:placetype":"venue"
},
  "geometry": {"coordinates":[-4.135347,50.367249],"type":"Point"}
}