{
  "type": "Feature",
  "properties": {
    "iso:country":"GB",
    "sg:address":"79 - 81 Euston Road",
    "sg:city":"London",
    "sg:classifiers":[
        {
            "category":"Travel",
            "subcategory":"Hostel",
            "type":"Entertainment"
        }
    ],
    "sg:phone":"+44 20 7388 9998",
    "sg:postcode":"NW1 2QS",
    "sg:province":"Greater London",
    "sg:tags":[
        "youth"
    ],
    "wof:name":"Youth Hostels Association",
    "wof:placetype":"venue"
},
  "geometry": {"coordinates":[-0.1309249997,51.5271644592],"type":"Point"}
}