{
  "type": "Feature",
  "properties": {
    "addr:full":"112 New Bond St London Greater London W1S 1DP",
    "addr:housenumber":"112",
    "addr:postcode":"w1s 1dp",
    "addr:street":"New Bond St",
    "iso:country":"GB",
    "sg:address":"112 New Bond St",
    "sg:city":"London",
    "sg:classifiers":[
        {
            "category":"Shopping",
            "subcategory":"Antiques",
            "type":"Retail Goods"
        }
    ],
    "sg:postcode":"W1S 1DP",
    "sg:province":"Greater London",
    "wof:name":"Ewart,Adrian,",
    "wof:placetype":"venue"
},
  "geometry": {"coordinates":[-0.1453240067,51.5129165649],"type":"Point"}
}