{
  "type": "Feature",
  "properties": {
    "iso:country":"GB",
    "sg:address":"84 Valentines Way",
    "sg:city":"Romford",
    "sg:classifiers":[
        {
            "category":"Building & Trades",
            "subcategory":"Construction",
            "type":"Services"
        }
    ],
    "sg:phone":"+44 20 8517 6074",
    "sg:postcode":"RM7 0YH",
    "sg:province":"Essex",
    "sg:tags":[
        "resurfacing",
        "laying",
        "floor"
    ],
    "wof:name":"Bottone Flooring",
    "wof:placetype":"venue"
},
  "geometry": {"coordinates":[0.1772170067,51.5574684143],"type":"Point"}
}