{
  "type": "Feature",
  "properties": {
    "addr:full":"320-323 Marine Road Central Morecambe Lancashire LA4 5AA",
    "addr:housenumber":"320-323",
    "addr:postcode":"la4 5aa",
    "addr:street":"Marine Road Central Morecambe",
    "iso:country":"GB",
    "sg:address":"320-323 Marine Road Central",
    "sg:city":"Morecambe",
    "sg:classifiers":[
        {
            "category":"Travel",
            "subcategory":"Hotels & Motels",
            "type":"Entertainment"
        }
    ],
    "sg:phone":"+44 1524 416404",
    "sg:postcode":"LA4 5AA",
    "sg:province":"Lancashire",
    "wof:name":"Lothersdale Hotel",
    "wof:placetype":"venue"
},
  "geometry": {"coordinates":[-2.862124,54.075317],"type":"Point"}
}