{
  "type": "Feature",
  "properties": {
    "addr:full":"Borth Golf Club Borth Ceredigion SY24 5JS",
    "addr:postcode":"sy24 5js",
    "iso:country":"GB",
    "sg:address":"Borth Golf Club",
    "sg:city":"Borth",
    "sg:classifiers":[
        {
            "category":"Sports & Exercise",
            "subcategory":"Golf",
            "type":"Entertainment"
        }
    ],
    "sg:phone":"+44 1970 871557",
    "sg:postcode":"SY24 5JS",
    "sg:province":"Ceredigion",
    "sg:tags":[
        "equipment"
    ],
    "wof:name":"Borth Golf Club Golf Shop",
    "wof:placetype":"venue"
},
  "geometry": {"coordinates":[-4.0513691902,52.490524292],"type":"Point"}
}