{
  "type": "Feature",
  "properties": {
    "iso:country":"GB",
    "sg:address":"37 Woodside Rd",
    "sg:city":"Amersham",
    "sg:classifiers":[
        {
            "category":"Shopping",
            "subcategory":"Stationery & Office Supplies",
            "type":"Retail Goods"
        }
    ],
    "sg:phone":"+44 1494 432565",
    "sg:postcode":"HP6 6AA",
    "sg:province":"Buckinghamshire",
    "sg:tags":[
        "printers'"
    ],
    "wof:name":"Heidelberg Harris S A",
    "wof:placetype":"venue"
},
  "geometry": {"coordinates":[-0.6036779881,51.6780815125],"type":"Point"}
}