{
  "type": "Feature",
  "properties": {
    "iso:country":"GB",
    "sg:address":"11 Fish Street",
    "sg:city":"Northampton",
    "sg:classifiers":[
        {
            "category":"Bars & Pubs",
            "type":"Food & Drink"
        }
    ],
    "sg:phone":"+44 1604 234040",
    "sg:postcode":"NN1 2AA",
    "sg:province":"Northamptonshire",
    "sg:tags":[
        "pubs",
        "inn"
    ],
    "wof:name":"Fish Inn",
    "wof:placetype":"venue"
},
  "geometry": {"coordinates":[-0.893424,52.237591],"type":"Point"}
}