{
  "type": "Feature",
  "properties": {
    "addr:full":"1 Coronation Avenue, Keynsham Bristol City of Bristol BS31 2PT",
    "addr:housenumber":"1",
    "addr:postcode":"bs31 2pt",
    "addr:street":"Coronation Avenue",
    "iso:country":"GB",
    "sg:address":"1 Coronation Avenue, Keynsham",
    "sg:city":"Bristol",
    "sg:classifiers":[
        {
            "category":"Manufacturing",
            "subcategory":"Petroleum Products",
            "type":"Manufacturing & Wholesale Goods"
        }
    ],
    "sg:phone":"+44 117 985 5004",
    "sg:postcode":"BS31 2PT",
    "sg:province":"City of Bristol",
    "sg:tags":[
        "double",
        "glazing"
    ],
    "wof:name":"Homesafe",
    "wof:placetype":"venue"
},
  "geometry": {"coordinates":[-2.500822,51.408302],"type":"Point"}
}