{
  "type": "Feature",
  "properties": {
    "addr:full":"Empire House Chelmsford Essex CM1 1PE",
    "addr:postcode":"cm1 1pe",
    "iso:country":"GB",
    "sg:address":"Empire House",
    "sg:city":"Chelmsford",
    "sg:classifiers":[
        {
            "category":"Manufacturing",
            "subcategory":"Signs",
            "type":"Manufacturing & Wholesale Goods"
        }
    ],
    "sg:phone":"+44 1245 350450",
    "sg:postcode":"CM1 1PE",
    "sg:province":"Essex",
    "sg:tags":[
        "nameplate"
    ],
    "wof:name":"Fastsigns",
    "wof:placetype":"venue"
},
  "geometry": {"coordinates":[0.4778999984,51.7380905151],"type":"Point"}
}