{
  "type": "Feature",
  "properties": {
    "addr:full":"108 Seymour Road, West Bridgford Nottingham Nottinghamshire NG2 5EF",
    "addr:housenumber":"108",
    "addr:postcode":"ng2 5ef",
    "addr:street":"Seymour Road",
    "iso:country":"GB",
    "sg:address":"108 Seymour Road, West Bridgford",
    "sg:city":"Nottingham",
    "sg:classifiers":[
        {
            "category":"Organizations",
            "subcategory":"Non-profit Organization",
            "type":"Services"
        }
    ],
    "sg:postcode":"NG2 5EF",
    "sg:province":"Nottinghamshire",
    "sg:tags":[
        "organisation",
        "voluntary",
        "charity"
    ],
    "wof:name":"R N L I Lifeboat Service",
    "wof:placetype":"venue"
},
  "geometry": {"coordinates":[-1.114443,52.934269],"type":"Point"}
}