{
  "type": "Feature",
  "properties": {
    "addr:full":"Bryn Farm Port Talbot Neath Port Talbot SA13 2RP",
    "addr:postcode":"sa13 2rp",
    "addr:street":"Bryn",
    "iso:country":"GB",
    "sg:address":"Bryn Farm",
    "sg:city":"Port Talbot",
    "sg:classifiers":[
        {
            "category":"Taxi",
            "type":"Transportation"
        }
    ],
    "sg:phone":"+44 1639 894888",
    "sg:postcode":"SA13 2RP",
    "sg:province":"Neath Port Talbot",
    "sg:tags":[
        "mini",
        "hire",
        "cab",
        "private",
        "vehicle"
    ],
    "wof:name":"Bryn Private Hire",
    "wof:placetype":"venue"
},
  "geometry": {"coordinates":[-3.7114779949,51.6151847839],"type":"Point"}
}