{
  "type": "Feature",
  "properties": {
    "addr:full":"Folkestone Rd Dover Kent CT17 9JG",
    "addr:postcode":"ct17 9jg",
    "addr:street":"Folkestone Rd",
    "iso:country":"GB",
    "sg:address":"Folkestone Rd",
    "sg:city":"Dover",
    "sg:classifiers":[
        {
            "category":"Place Of Worship",
            "type":"Public Place"
        }
    ],
    "sg:phone":"+44 1304 205391",
    "sg:postcode":"CT17 9JG",
    "sg:province":"Kent",
    "wof:name":"St Martin Of Tours C Of E Church",
    "wof:placetype":"venue"
},
  "geometry": {"coordinates":[1.308713,51.125889],"type":"Point"}
}