{
  "type": "Feature",
  "properties": {
    "iso:country":"GB",
    "sg:address":"Unit 16, Harcourt Field",
    "sg:city":"Wallington",
    "sg:classifiers":[
        {
            "category":"Shopping",
            "subcategory":"Stationery & Office Supplies",
            "type":"Retail Goods"
        },
        {
            "category":"Manufacturing",
            "subcategory":"Wood Products",
            "type":"Manufacturing & Wholesale Goods"
        }
    ],
    "sg:phone":"+44 20 8395 2401",
    "sg:postcode":"SM6 8BA",
    "sg:province":"Surrey",
    "sg:tags":[
        "packaging",
        "equipment",
        "crate",
        "pallets"
    ],
    "wof:name":"Target Display Pack Ltd",
    "wof:placetype":"venue"
},
  "geometry": {"coordinates":[-0.150609,51.367226],"type":"Point"}
}