{
  "type": "Feature",
  "properties": {
    "addr:full":"Unit 6 Tudor Wks, Beaconsfield Rd Hayes Greater London UB4 0SL",
    "addr:housenumber":"unit 6",
    "addr:postcode":"ub4 0sl",
    "addr:street":"Tudor Wks Beaconsfield Rd",
    "iso:country":"GB",
    "sg:address":"Unit 6 Tudor Wks, Beaconsfield Rd",
    "sg:city":"Hayes",
    "sg:classifiers":[
        {
            "category":"Manufacturing",
            "subcategory":"Petroleum Products",
            "type":"Manufacturing & Wholesale Goods"
        }
    ],
    "sg:phone":"+44 181 561 5574",
    "sg:postcode":"UB4 0SL",
    "sg:province":"Greater London",
    "sg:tags":[
        "double",
        "glazing"
    ],
    "wof:name":"Carebright Ltd",
    "wof:placetype":"venue"
},
  "geometry": {"coordinates":[-0.3971459866,51.5091629028],"type":"Point"}
}