{
  "type": "Feature",
  "properties": {
    "iso:country":"GB",
    "sg:address":"2 Kirkwood Road",
    "sg:city":"London",
    "sg:classifiers":[
        {
            "category":"Food & Beverages",
            "subcategory":"Supermarket",
            "type":"Retail Goods"
        }
    ],
    "sg:phone":"+44 20 7277 5520",
    "sg:postcode":"SE15 3XX",
    "sg:province":"Greater London",
    "wof:name":"Nun Head Express Supermarket",
    "wof:placetype":"venue"
},
  "geometry": {"coordinates":[-0.0578190014,51.4659805298],"type":"Point"}
}