{
  "type": "Feature",
  "properties": {
    "addr:full":"Health Visitors Only, Askern Rd Doncaster South Yorkshire DN5 0JX",
    "addr:postcode":"dn5 0jx",
    "addr:street":"Askern Rd",
    "iso:country":"GB",
    "sg:address":"Health Visitors Only, Askern Rd",
    "sg:city":"Doncaster",
    "sg:classifiers":[
        {
            "category":"Health Services",
            "subcategory":"Clinic",
            "type":"Services"
        }
    ],
    "sg:phone":"+44 1302 873031",
    "sg:postcode":"DN5 0JX",
    "sg:province":"South Yorkshire",
    "sg:tags":[
        "nh"
    ],
    "wof:name":"Bentley Health Centre",
    "wof:placetype":"venue"
},
  "geometry": {"coordinates":[-1.14848,53.55101],"type":"Point"}
}