{
  "type": "Feature",
  "properties": {
    "addr:full":"5 Malthouse Meadows Liphook Hampshire GU30 7BD",
    "addr:housenumber":"5",
    "addr:postcode":"gu30 7bd",
    "addr:street":"Malthouse Meadows",
    "iso:country":"GB",
    "sg:address":"5 Malthouse Meadows",
    "sg:city":"Liphook",
    "sg:classifiers":[
        {
            "category":"Organizations",
            "subcategory":"Political Organization",
            "type":"Services"
        }
    ],
    "sg:phone":"+44 1428 724173",
    "sg:postcode":"GU30 7BD",
    "sg:province":"Hampshire",
    "sg:tags":[
        "party"
    ],
    "wof:name":"East Hampshire Green Party",
    "wof:placetype":"venue"
},
  "geometry": {"coordinates":[-0.797545,51.078705],"type":"Point"}
}