{
  "type": "Feature",
  "properties": {
    "iso:country":"GB",
    "sg:address":"222 Station Rd",
    "sg:city":"Solihull",
    "sg:classifiers":[
        {
            "category":"Health Services",
            "subcategory":"Dentist",
            "type":"Services"
        }
    ],
    "sg:phone":"+44 1564 770053",
    "sg:postcode":"B93 0ER",
    "sg:province":"Warwickshire",
    "wof:name":"A Philpott",
    "wof:placetype":"venue"
},
  "geometry": {"coordinates":[-1.742501,52.382988],"type":"Point"}
}