{
  "type": "Feature",
  "properties": {
    "addr:full":"83 Main St Bellshill North Lanarkshire ML4 3DU",
    "addr:housenumber":"83",
    "addr:postcode":"ml4 3du",
    "addr:street":"Main St",
    "iso:country":"GB",
    "sg:address":"83 Main St",
    "sg:city":"Bellshill",
    "sg:classifiers":[
        {
            "category":"Autos & Motor Vehicles",
            "subcategory":"Automobile Sales",
            "type":"Retail Goods"
        }
    ],
    "sg:postcode":"ML4 3DU",
    "sg:province":"North Lanarkshire",
    "sg:tags":[
        "car"
    ],
    "wof:name":"Campbell Fairfull Car Sales",
    "wof:placetype":"venue"
},
  "geometry": {"coordinates":[-4.0299048424,55.8191566467],"type":"Point"}
}