{
  "type": "Feature",
  "properties": {
    "addr:full":"Unit 8/10 Mount Farm, Junction Road Chipping Norton Gloucestershire OX7 6NP",
    "addr:housenumber":"unit 8 / 10",
    "addr:postcode":"ox7 6np",
    "addr:street":"Mount Farm Junction Road",
    "iso:country":"GB",
    "sg:address":"Unit 8/10 Mount Farm, Junction Road",
    "sg:city":"Chipping Norton",
    "sg:classifiers":[
        {
            "category":"Health Services",
            "subcategory":"Clinic",
            "type":"Services"
        }
    ],
    "sg:phone":"+44 1608 659544",
    "sg:postcode":"OX7 6NP",
    "sg:province":"Gloucestershire",
    "sg:tags":[
        "aromatherapy"
    ],
    "wof:name":"Essentially Oils Ltd",
    "wof:placetype":"venue"
},
  "geometry": {"coordinates":[-1.545912981,51.9404067993],"type":"Point"}
}