{
  "type": "Feature",
  "properties": {
    "addr:full":"95 Queen St Peterhead Aberdeenshire AB42 6UA",
    "addr:housenumber":"95",
    "addr:postcode":"ab42 6ua",
    "addr:street":"Queen St",
    "iso:country":"GB",
    "sg:address":"95 Queen St",
    "sg:city":"Peterhead",
    "sg:classifiers":[
        {
            "category":"Health Services",
            "subcategory":"Dentist",
            "type":"Services"
        }
    ],
    "sg:phone":"+44 1779 473222",
    "sg:postcode":"AB42 6UA",
    "sg:province":"Aberdeenshire",
    "wof:name":"Dentist The",
    "wof:placetype":"venue"
},
  "geometry": {"coordinates":[-1.79731,57.506531],"type":"Point"}
}