{
  "type": "Feature",
  "properties": {
    "addr:full":"Crichton Royal Farm, Mid Park House Dumfries Dumfries and Galloway DG1 4SZ",
    "addr:postcode":"dg1 4sz",
    "addr:street":"Mid",
    "iso:country":"GB",
    "sg:address":"Crichton Royal Farm, Mid Park House",
    "sg:city":"Dumfries",
    "sg:classifiers":[
        {
            "category":"Education",
            "subcategory":"College",
            "type":"Public Place"
        },
        {
            "category":"Education",
            "subcategory":"Vocational School",
            "type":"Public Place"
        }
    ],
    "sg:phone":"+44 1387 263961",
    "sg:postcode":"DG1 4SZ",
    "sg:province":"Dumfries and Galloway",
    "sg:tags":[
        "technical",
        "agricultural"
    ],
    "wof:name":"The Scottish Agricultural College Ltd",
    "wof:placetype":"venue"
},
  "geometry": {"coordinates":[-3.586949,55.042709],"type":"Point"}
}