{
  "type": "Feature",
  "properties": {
    "addr:full":"5 Steele House, High Street, Dovercourt Harwich Essex CO12 3PN",
    "addr:housenumber":"5;house",
    "addr:postcode":"co12 3pn",
    "addr:street":"High Street",
    "iso:country":"GB",
    "sg:address":"5 Steele House, High Street, Dovercourt",
    "sg:city":"Harwich",
    "sg:classifiers":[
        {
            "category":"Retail",
            "subcategory":"Repair Shop",
            "type":"Services"
        },
        {
            "category":"Home & Garden",
            "subcategory":"Carpets & Floor Coverings",
            "type":"Retail Goods"
        }
    ],
    "sg:phone":"+44 1255 241428",
    "sg:postcode":"CO12 3PN",
    "sg:province":"Essex",
    "sg:tags":[
        "carpets",
        "rug",
        "floorcoverings",
        "matting"
    ],
    "wof:name":"Persha Carpets",
    "wof:placetype":"venue"
},
  "geometry": {"coordinates":[1.2811570168,51.9372673035],"type":"Point"}
}