{
  "type": "Feature",
  "properties": {
    "iso:country":"GB",
    "sg:address":"65 Kirk Street",
    "sg:city":"Strathaven",
    "sg:classifiers":[
        {
            "category":"Real Estate",
            "subcategory":"Architect",
            "type":"Services"
        }
    ],
    "sg:postcode":"ML10 6BA",
    "sg:province":"South Lanarkshire",
    "wof:name":"Peter Halliday",
    "wof:placetype":"venue"
},
  "geometry": {"coordinates":[-4.0674490929,55.6746864319],"type":"Point"}
}