{
  "type": "Feature",
  "properties": {
    "addr:full":"25 Sea Rd Westgate On Sea Kent CT8 8SB",
    "addr:housenumber":"25",
    "addr:postcode":"ct8 8sb",
    "addr:street":"Sea Rd Westgate",
    "iso:country":"GB",
    "sg:address":"25 Sea Rd",
    "sg:city":"Westgate On Sea",
    "sg:classifiers":[
        {
            "category":"Travel",
            "subcategory":"Hotels & Motels",
            "type":"Entertainment"
        }
    ],
    "sg:phone":"+44 1843 831082",
    "sg:postcode":"CT8 8SB",
    "sg:province":"Kent",
    "wof:name":"Ivyside Hotel",
    "wof:placetype":"venue"
},
  "geometry": {"coordinates":[1.3391749859,51.3844223022],"type":"Point"}
}