{
  "type": "Feature",
  "properties": {
    "iso:country":"GB",
    "sg:address":"6 Harvest Court, Harvest Drive",
    "sg:city":"Lowestoft",
    "sg:classifiers":[
        {
            "category":"Mining & Drilling",
            "type":"Manufacturing & Wholesale Goods"
        }
    ],
    "sg:phone":"+44 1502 566500",
    "sg:postcode":"NR33 7NB",
    "sg:province":"Suffolk",
    "sg:tags":[
        "contractor"
    ],
    "wof:name":"Diamond Drilling",
    "wof:placetype":"venue"
},
  "geometry": {"coordinates":[1.718944,52.447659],"type":"Point"}
}