{
  "type": "Feature",
  "properties": {
    "addr:full":"66 Victoria Rd Swindon Wiltshire SN1 3BB",
    "addr:housenumber":"66",
    "addr:postcode":"sn1 3bb",
    "addr:street":"Victoria Rd",
    "iso:country":"GB",
    "sg:address":"66 Victoria Rd",
    "sg:city":"Swindon",
    "sg:classifiers":[
        {
            "category":"Place Of Worship",
            "type":"Public Place"
        }
    ],
    "sg:phone":"+44 1793 491889",
    "sg:postcode":"SN1 3BB",
    "sg:province":"Wiltshire",
    "wof:name":"Christian Science Society",
    "wof:placetype":"venue"
},
  "geometry": {"coordinates":[-1.777271986,51.5550422668],"type":"Point"}
}