{
  "type": "Feature",
  "properties": {
    "addr:full":"35 Knowsley Rd Bolton Lancashire BL1 6HN",
    "addr:housenumber":"35",
    "addr:postcode":"bl1 6hn",
    "addr:street":"Knowsley Rd",
    "iso:country":"GB",
    "sg:address":"35 Knowsley Rd",
    "sg:city":"Bolton",
    "sg:classifiers":[
        {
            "category":"Building & Trades",
            "subcategory":"Construction",
            "type":"Services"
        }
    ],
    "sg:phone":"+44 1204 494560",
    "sg:postcode":"BL1 6HN",
    "sg:province":"Lancashire",
    "sg:tags":[
        "roofing"
    ],
    "wof:name":"John Marsden Roofing Contractors",
    "wof:placetype":"venue"
},
  "geometry": {"coordinates":[-2.4560289383,53.5931358337],"type":"Point"}
}