{
  "type": "Feature",
  "properties": {
    "iso:country":"GB",
    "sg:address":"Redcar Rd",
    "sg:city":"Redcar",
    "sg:classifiers":[
        {
            "category":"Restaurant",
            "type":"Food & Drink"
        }
    ],
    "sg:phone":"+44 1642 483163",
    "sg:postcode":"TS11 6EX",
    "sg:province":"North Yorkshire",
    "wof:name":"Mermaid Hotel",
    "wof:placetype":"venue"
},
  "geometry": {"coordinates":[-1.035958,54.593559],"type":"Point"}
}