{
  "type": "Feature",
  "properties": {
    "addr:full":"10 Windermere Avenue Ramsgate Kent CT11 0PA",
    "addr:housenumber":"10",
    "addr:postcode":"ct11 0pa",
    "addr:street":"Windermere Avenue Ramsgate",
    "iso:country":"GB",
    "sg:address":"10 Windermere Avenue",
    "sg:city":"Ramsgate",
    "sg:classifiers":[
        {
            "category":"Building & Trades",
            "subcategory":"Cleaning & Sanitation",
            "type":"Services"
        },
        {
            "category":"Building & Trades",
            "subcategory":"Construction",
            "type":"Services"
        }
    ],
    "sg:postcode":"CT11 0PA",
    "sg:province":"Kent",
    "sg:tags":[
        "builder",
        "steam"
    ],
    "wof:name":"Bowman Maintenance Contracting",
    "wof:placetype":"venue"
},
  "geometry": {"coordinates":[1.3955880404,51.3389587402],"type":"Point"}
}