{
  "type": "Feature",
  "properties": {
    "addr:full":"Stand C8 Fruit Market, Blochairn Road Glasgow East Dunbartonshire G21 2SU",
    "addr:postcode":"g21 2su",
    "addr:street":"Blochairn Road",
    "iso:country":"GB",
    "sg:address":"Stand C8 Fruit Market, Blochairn Road",
    "sg:city":"Glasgow",
    "sg:classifiers":[
        {
            "category":"Shopping",
            "subcategory":"Florist",
            "type":"Retail Goods"
        }
    ],
    "sg:phone":"+44 141 552 1281",
    "sg:postcode":"G21 2SU",
    "sg:province":"East Dunbartonshire",
    "wof:name":"James Taylor Flowers",
    "wof:placetype":"venue"
},
  "geometry": {"coordinates":[-4.21675,55.872681],"type":"Point"}
}