{
  "type": "Feature",
  "properties": {
    "iso:country":"GB",
    "sg:address":"Gardeners Cottage, Croft Bank, Croft",
    "sg:city":"Skegness",
    "sg:classifiers":[
        {
            "category":"Transit Center",
            "subcategory":"Passenger",
            "type":"Transportation"
        }
    ],
    "sg:postcode":"PE24 4AW",
    "sg:province":"Lincolnshire",
    "sg:tags":[
        "boarding",
        "kennel",
        "catteries"
    ],
    "wof:name":"Cosy Cat",
    "wof:placetype":"venue"
},
  "geometry": {"coordinates":[0.254115,53.129601],"type":"Point"}
}