{
  "type": "Feature",
  "properties": {
    "addr:full":"21 Poplar Hill Stowmarket Suffolk IP14 2AS",
    "addr:housenumber":"21",
    "addr:postcode":"ip14 2as",
    "iso:country":"GB",
    "sg:address":"21 Poplar Hill",
    "sg:city":"Stowmarket",
    "sg:classifiers":[
        {
            "category":"Food & Beverages",
            "subcategory":"Meat & Fish",
            "type":"Retail Goods"
        }
    ],
    "sg:phone":"+44 1449 612832",
    "sg:postcode":"IP14 2AS",
    "sg:province":"Suffolk",
    "sg:tags":[
        "butcher"
    ],
    "wof:name":"R C Hubbard",
    "wof:placetype":"venue"
},
  "geometry": {"coordinates":[0.997214,52.17902],"type":"Point"}
}