{
  "type": "Feature",
  "properties": {
    "iso:country":"GB",
    "sg:address":"Hema Works, Station Lane, Old Whittington",
    "sg:city":"Chesterfield",
    "sg:classifiers":[
        {
            "category":"Military Area",
            "subcategory":"Air Force Base",
            "type":"Public Place"
        }
    ],
    "sg:phone":"+44 1246 452387",
    "sg:postcode":"S41 9QX",
    "sg:province":"Derbyshire",
    "sg:tags":[
        "water",
        "treatment"
    ],
    "wof:name":"Arcrite Process Systems (U K) Ltd.",
    "wof:placetype":"venue"
},
  "geometry": {"coordinates":[-1.4269989729,53.2666664124],"type":"Point"}
}