{
  "type": "Feature",
  "properties": {
    "iso:country":"GB",
    "sg:address":"Unit 3d Heapham Road Industrial Estate",
    "sg:city":"Gainsborough",
    "sg:classifiers":[
        {
            "category":"Wholesale",
            "subcategory":"Meat",
            "type":"Manufacturing & Wholesale Goods"
        },
        {
            "category":"Farming",
            "subcategory":"Farm",
            "type":"Manufacturing & Wholesale Goods"
        }
    ],
    "sg:phone":"+44 1427 810171",
    "sg:postcode":"DN21 1RZ",
    "sg:province":"Lincolnshire",
    "sg:tags":[
        "egg",
        "-",
        "producer"
    ],
    "wof:name":"Fieldson Farm Eggs",
    "wof:placetype":"venue"
},
  "geometry": {"coordinates":[-0.762829,53.399132],"type":"Point"}
}