{
  "type": "Feature",
  "properties": {
    "iso:country":"GB",
    "sg:address":"Smokeacre, Norton Lane",
    "sg:city":"Bristol",
    "sg:classifiers":[
        {
            "category":"Organizations",
            "subcategory":"Professional Association",
            "type":"Services"
        }
    ],
    "sg:phone":"+44 1275 332404",
    "sg:postcode":"BS40 8RX",
    "sg:province":"Somerset",
    "sg:tags":[
        "specialist",
        "calendar"
    ],
    "wof:name":"Edition Boiselle",
    "wof:placetype":"venue"
},
  "geometry": {"coordinates":[-2.598569,51.372456],"type":"Point"}
}