{
  "type": "Feature",
  "properties": {
    "addr:full":"Mersey House, 1 Church St Bootle Merseyside L20 1AF",
    "addr:housenumber":"1",
    "addr:postcode":"l20 1af",
    "addr:street":"Church St",
    "iso:country":"GB",
    "sg:address":"Mersey House, 1 Church St",
    "sg:city":"Bootle",
    "sg:classifiers":[
        {
            "category":"Freight",
            "type":"Transportation"
        }
    ],
    "sg:phone":"+44 151 933 7828",
    "sg:postcode":"L20 1AF",
    "sg:province":"Merseyside",
    "sg:tags":[
        "haulage",
        "road"
    ],
    "wof:name":"P & E Norris Haulage",
    "wof:placetype":"venue"
},
  "geometry": {"coordinates":[-3.0043570995,53.4484863281],"type":"Point"}
}