{
  "type": "Feature",
  "properties": {
    "addr:full":"1 Waldegrave Street Hastings East Sussex TN34 1SJ",
    "addr:housenumber":"1",
    "addr:postcode":"tn34 1sj",
    "addr:street":"Waldegrave Street",
    "iso:country":"GB",
    "sg:address":"1 Waldegrave Street",
    "sg:city":"Hastings",
    "sg:classifiers":[
        {
            "category":"Home & Garden",
            "subcategory":"Garden Supply",
            "type":"Retail Goods"
        },
        {
            "category":"Farming",
            "subcategory":"Livestock Farm",
            "type":"Manufacturing & Wholesale Goods"
        }
    ],
    "sg:phone":"+44 1424 429176",
    "sg:postcode":"TN34 1SJ",
    "sg:province":"East Sussex",
    "sg:tags":[
        "breeder",
        "flower",
        "shrub"
    ],
    "wof:name":"Everfresh",
    "wof:placetype":"venue"
},
  "geometry": {"coordinates":[0.582119,50.857956],"type":"Point"}
}