{
  "type": "Feature",
  "properties": {
    "addr:full":"24 Derwent Drive Hayes Greater London UB4 8DR",
    "addr:housenumber":"24",
    "addr:postcode":"ub4 8dr",
    "addr:street":"Derwent Drive",
    "iso:country":"GB",
    "sg:address":"24 Derwent Drive",
    "sg:city":"Hayes",
    "sg:classifiers":[
        {
            "category":"Health Services",
            "subcategory":"Podiatrist",
            "type":"Services"
        }
    ],
    "sg:postcode":"UB4 8DR",
    "sg:province":"Greater London",
    "sg:tags":[
        "podiatrists",
        "chiropodist"
    ],
    "wof:name":"Fiona Gilchrist",
    "wof:placetype":"venue"
},
  "geometry": {"coordinates":[-0.427899,51.525272],"type":"Point"}
}