{
  "type": "Feature",
  "properties": {
    "iso:country":"GB",
    "sg:address":"19 High Street",
    "sg:city":"Shefford",
    "sg:classifiers":[
        {
            "category":"Recreation",
            "subcategory":"Fishing",
            "type":"Entertainment"
        }
    ],
    "sg:postcode":"SG17 5DD",
    "sg:province":"Bedfordshire",
    "sg:tags":[
        "angling"
    ],
    "wof:name":"Andy's Angling Centre",
    "wof:placetype":"venue"
},
  "geometry": {"coordinates":[-0.334818989,52.0381317139],"type":"Point"}
}