{
  "type": "Feature",
  "properties": {
    "iso:country":"GB",
    "sg:address":"201 Shuna St",
    "sg:city":"Glasgow",
    "sg:classifiers":[
        {
            "category":"Community Center",
            "type":"Public Place"
        }
    ],
    "sg:phone":"+44 141 946 5675",
    "sg:postcode":"G20 9EY",
    "sg:province":"Glasgow City",
    "sg:tags":[
        "centre"
    ],
    "wof:name":"Ruchill Unemployed & Community Resource Centre",
    "wof:placetype":"venue"
},
  "geometry": {"coordinates":[-4.281429,55.888397],"type":"Point"}
}