{
  "type": "Feature",
  "properties": {
    "addr:full":"St James The Less School, Moreton Street, Pimlico London Greater London SW1V 2PT",
    "addr:postcode":"sw1v 2pt",
    "addr:street":"Moreton Street",
    "iso:country":"GB",
    "sg:address":"St James The Less School, Moreton Street, Pimlico",
    "sg:city":"London",
    "sg:classifiers":[
        {
            "category":"Farming",
            "subcategory":"Nursery",
            "type":"Manufacturing & Wholesale Goods"
        }
    ],
    "sg:phone":"+44 20 7931 7978",
    "sg:postcode":"SW1V 2PT",
    "sg:province":"Greater London",
    "sg:tags":[
        "creche"
    ],
    "wof:name":"Daisies Day Nursery",
    "wof:placetype":"venue"
},
  "geometry": {"coordinates":[-0.13575,51.489841],"type":"Point"}
}