{
  "type": "Feature",
  "properties": {
    "iso:country":"GB",
    "sg:address":"Unit 8 Block D, Triumph Trading Park, 26-32 Spitfire Road",
    "sg:city":"Liverpool",
    "sg:classifiers":[
        {
            "category":"Professional",
            "subcategory":"Business Services",
            "type":"Services"
        }
    ],
    "sg:phone":"+44 151 486 1888",
    "sg:postcode":"L24 9GQ",
    "sg:province":"Merseyside",
    "sg:tags":[
        "import",
        "export",
        "agent"
    ],
    "wof:name":"Rayware Ltd.",
    "wof:placetype":"venue"
},
  "geometry": {"coordinates":[-2.8742399216,53.3567810059],"type":"Point"}
}