{
  "type": "Feature",
  "properties": {
    "iso:country":"GB",
    "sg:address":"28 Lappin St",
    "sg:city":"Clydebank",
    "sg:classifiers":[
        {
            "category":"Banks & Credit Unions",
            "subcategory":"Financial Services",
            "type":"Services"
        }
    ],
    "sg:phone":"+44 141 941 3202",
    "sg:postcode":"G81 1AH",
    "sg:province":"East Dunbartonshire",
    "sg:tags":[
        "consultant"
    ],
    "wof:name":"East Clydebank Credit Union Ltd",
    "wof:placetype":"venue"
},
  "geometry": {"coordinates":[-4.3864030838,55.8982429504],"type":"Point"}
}