{
  "type": "Feature",
  "properties": {
    "iso:country":"GB",
    "sg:address":"Unit 16, Bassetts Manor, Butcherfield Lane",
    "sg:city":"Hartfield",
    "sg:classifiers":[
        {
            "category":"Shopping",
            "subcategory":"Books",
            "type":"Retail Goods"
        }
    ],
    "sg:phone":"+44 1892 770074",
    "sg:postcode":"TN7 4LA",
    "sg:province":"East Sussex",
    "wof:name":"Martlet Publishing Co",
    "wof:placetype":"venue"
},
  "geometry": {"coordinates":[0.111161,51.103489],"type":"Point"}
}