{
  "type": "Feature",
  "properties": {
    "iso:country":"GB",
    "sg:address":"118 St Marys Rd",
    "sg:city":"Sheffield",
    "sg:classifiers":[
        {
            "category":"Autos & Motor Vehicles",
            "subcategory":"Automobile Sales",
            "type":"Retail Goods"
        }
    ],
    "sg:postcode":"S2 4AW",
    "sg:province":"South Yorkshire",
    "sg:tags":[
        "commercial"
    ],
    "wof:name":"Webster,Peter,",
    "wof:placetype":"venue"
},
  "geometry": {"coordinates":[-1.4672299623,53.373790741],"type":"Point"}
}