{
  "type": "Feature",
  "properties": {
    "addr:full":"Auchendoon Rd Newton Stewart Dumfries and Galloway DG8 6HD",
    "addr:postcode":"dg8 6hd",
    "addr:street":"Auchendoon Rd",
    "iso:country":"GB",
    "sg:address":"Auchendoon Rd",
    "sg:city":"Newton Stewart",
    "sg:classifiers":[
        {
            "category":"Social Services",
            "subcategory":"Retirement Home",
            "type":"Services"
        },
        {
            "category":"Government",
            "subcategory":"Office",
            "type":"Public Place"
        }
    ],
    "sg:postcode":"DG8 6HD",
    "sg:province":"Dumfries and Galloway",
    "sg:tags":[
        "residential",
        "local",
        "care"
    ],
    "wof:name":"Dumfries & Galloway Council",
    "wof:placetype":"venue"
},
  "geometry": {"coordinates":[-4.4872279167,54.958026886],"type":"Point"}
}