{
  "type": "Feature",
  "properties": {
    "iso:country":"GB",
    "sg:address":"158 Gorringe Park Avenue",
    "sg:city":"Mitcham",
    "sg:classifiers":[
        {
            "category":"Professional",
            "subcategory":"Engineering",
            "type":"Services"
        },
        {
            "category":"Building & Trades",
            "subcategory":"Electrical",
            "type":"Services"
        }
    ],
    "sg:postcode":"CR4 2DX",
    "sg:province":"Greater London",
    "sg:tags":[
        "engineer",
        "electrician",
        "contractor"
    ],
    "wof:name":"R A B ELECTRICAL",
    "wof:placetype":"venue"
},
  "geometry": {"coordinates":[-0.15472,51.415241],"type":"Point"}
}