{
  "type": "Feature",
  "properties": {
    "addr:full":"20 The Bull Ring Ludlow Herefordshire SY8 1AA",
    "addr:housenumber":"20",
    "addr:postcode":"sy8 1aa",
    "addr:street":"The Bull Ring",
    "iso:country":"GB",
    "sg:address":"20 The Bull Ring",
    "sg:city":"Ludlow",
    "sg:classifiers":[
        {
            "category":"Arts & Performance",
            "subcategory":"Art Gallery",
            "type":"Entertainment"
        }
    ],
    "sg:phone":"+44 1584 875390",
    "sg:postcode":"SY8 1AA",
    "sg:province":"Herefordshire",
    "wof:name":"Feathers Gallery",
    "wof:placetype":"venue"
},
  "geometry": {"coordinates":[-2.717788,52.368992],"type":"Point"}
}