{
  "type": "Feature",
  "properties": {
    "iso:country":"GB",
    "sg:address":"131 Mowbray Dr",
    "sg:city":"Blackpool",
    "sg:classifiers":[
        {
            "category":"Home & Garden",
            "subcategory":"Carpets & Floor Coverings",
            "type":"Retail Goods"
        }
    ],
    "sg:phone":"+44 1253 302164",
    "sg:postcode":"FY3 7UN",
    "sg:province":"Lancashire",
    "sg:tags":[
        "cleaner",
        "upholstery"
    ],
    "wof:name":"Chem-Dry Fylde",
    "wof:placetype":"venue"
},
  "geometry": {"coordinates":[-3.022472,53.837666],"type":"Point"}
}