{
  "type": "Feature",
  "properties": {
    "addr:full":"36/38 Piccadilly London Greater London W1J 0DP",
    "addr:housenumber":"36 / 38",
    "addr:postcode":"w1j 0dp",
    "addr:street":"Piccadilly",
    "iso:country":"GB",
    "sg:address":"36/38 Piccadilly",
    "sg:city":"London",
    "sg:classifiers":[
        {
            "category":"Real Estate",
            "subcategory":"Real Estate Agent",
            "type":"Services"
        }
    ],
    "sg:phone":"+44 20 7734 5599",
    "sg:postcode":"W1J 0DP",
    "sg:province":"Greater London",
    "wof:name":"London & General Property Ltd.",
    "wof:placetype":"venue"
},
  "geometry": {"coordinates":[-0.136768,51.509102],"type":"Point"}
}