{
  "type": "Feature",
  "properties": {
    "addr:full":"Green La, Burghfield Bridge Reading Berkshire RG30 3XN",
    "addr:postcode":"rg30 3xn",
    "addr:street":"Green;Burghfield Bridge",
    "iso:country":"GB",
    "sg:address":"Green La, Burghfield Bridge",
    "sg:city":"Reading",
    "sg:classifiers":[
        {
            "category":"Retail",
            "subcategory":"Auto Repair",
            "type":"Services"
        }
    ],
    "sg:postcode":"RG30 3XN",
    "sg:province":"Berkshire",
    "sg:tags":[
        "modification",
        "garage"
    ],
    "wof:name":"Eggleton,Colin,",
    "wof:placetype":"venue"
},
  "geometry": {"coordinates":[-1.0431480408,51.4108734131],"type":"Point"}
}