{
  "type": "Feature",
  "properties": {
    "iso:country":"GB",
    "sg:address":"30 Ascot Gardens",
    "sg:city":"Southall",
    "sg:classifiers":[
        {
            "category":"Retail",
            "subcategory":"Driving School",
            "type":"Services"
        }
    ],
    "sg:postcode":"UB1 2RZ",
    "sg:province":"Greater London",
    "wof:name":"G S Flora",
    "wof:placetype":"venue"
},
  "geometry": {"coordinates":[-0.3728480041,51.522151947],"type":"Point"}
}