{
  "type": "Feature",
  "properties": {
    "iso:country":"GB",
    "sg:address":"6b Union Street",
    "sg:city":"Stratford-upon-avon",
    "sg:classifiers":[
        {
            "category":"Shopping",
            "subcategory":"Clothing, Apparel, & Fashions",
            "type":"Retail Goods"
        }
    ],
    "sg:phone":"+44 1789 267788",
    "sg:postcode":"CV37 6QT",
    "sg:province":"Warwickshire",
    "sg:tags":[
        "lingerie",
        "hosiery"
    ],
    "wof:name":"Camille",
    "wof:placetype":"venue"
},
  "geometry": {"coordinates":[-1.705811,52.193584],"type":"Point"}
}