{
  "type": "Feature",
  "properties": {
    "iso:country":"GB",
    "sg:address":"Accrington Rd",
    "sg:city":"Burnley",
    "sg:classifiers":[
        {
            "category":"Restaurant",
            "type":"Food & Drink"
        }
    ],
    "sg:phone":"+44 1282 457881",
    "sg:postcode":"BB11 5QH",
    "sg:province":"Lancashire",
    "wof:name":"Bentley Wood Farm",
    "wof:placetype":"venue"
},
  "geometry": {"coordinates":[-2.261829,53.787991],"type":"Point"}
}