{
  "type": "Feature",
  "properties": {
    "iso:country":"GB",
    "sg:address":"209 Preston Road",
    "sg:city":"Brighton",
    "sg:classifiers":[
        {
            "category":"Shopping",
            "subcategory":"Pharmacy",
            "type":"Retail Goods"
        }
    ],
    "sg:phone":"+44 1273 552815",
    "sg:postcode":"BN1 6SA",
    "sg:province":"East Sussex",
    "sg:tags":[
        "pharmacist",
        "chemist"
    ],
    "wof:name":"Preston Park Pharmacy",
    "wof:placetype":"venue"
},
  "geometry": {"coordinates":[-0.1514900029,50.8429679871],"type":"Point"}
}