{
  "type": "Feature",
  "properties": {
    "iso:country":"GB",
    "sg:address":"117 Lawton Rd, Alsager",
    "sg:city":"Stoke-on-trent",
    "sg:classifiers":[
        {
            "category":"Building & Trades",
            "subcategory":"Construction",
            "type":"Services"
        }
    ],
    "sg:phone":"+44 1270 882114",
    "sg:postcode":"ST7 2DD",
    "sg:province":"Cheshire",
    "sg:tags":[
        "builder"
    ],
    "wof:name":"D S B Building Ltd",
    "wof:placetype":"venue"
},
  "geometry": {"coordinates":[-2.2923688889,53.0983505249],"type":"Point"}
}