{
  "type": "Feature",
  "properties": {
    "addr:full":"Unit 25-27, Reginald Road Industrial Park, Brindley Road St Helens Cheshire WA9 4HY",
    "addr:housenumber":"unit 25-27",
    "addr:postcode":"wa9 4hy",
    "addr:street":"Reginald Road Industrial Park Brindley Road",
    "iso:country":"GB",
    "sg:address":"Unit 25-27, Reginald Road Industrial Park, Brindley Road",
    "sg:city":"St Helens",
    "sg:classifiers":[
        {
            "category":"Professional",
            "subcategory":"Testing Lab",
            "type":"Services"
        }
    ],
    "sg:phone":"+44 1744 816225",
    "sg:postcode":"WA9 4HY",
    "sg:province":"Cheshire",
    "sg:tags":[
        "inspection",
        "calibration"
    ],
    "wof:name":"Format N D E",
    "wof:placetype":"venue"
},
  "geometry": {"coordinates":[-2.708939,53.428951],"type":"Point"}
}