{
  "type": "Feature",
  "properties": {
    "iso:country":"GB",
    "sg:address":"142 Lodge Road",
    "sg:city":"Southampton",
    "sg:classifiers":[
        {
            "category":"Real Estate",
            "subcategory":"Developer",
            "type":"Services"
        }
    ],
    "sg:phone":"+44 23 8033 2288",
    "sg:postcode":"SO14 6QR",
    "sg:province":"Hampshire",
    "sg:tags":[
        "property"
    ],
    "wof:name":"Roxan Construction Ltd.",
    "wof:placetype":"venue"
},
  "geometry": {"coordinates":[-1.403111,50.918953],"type":"Point"}
}