{
  "type": "Feature",
  "properties": {
    "addr:full":"2 The Farthings, North Pentwyn Cardiff Cardiff CF23 8ET",
    "addr:housenumber":"2",
    "addr:postcode":"cf23 8et",
    "addr:street":"The;North Pentwyn",
    "iso:country":"GB",
    "sg:address":"2 The Farthings, North Pentwyn",
    "sg:city":"Cardiff",
    "sg:classifiers":[
        {
            "category":"Professional",
            "type":"Services"
        },
        {
            "category":"Building & Trades",
            "subcategory":"Cleaning & Sanitation",
            "type":"Services"
        }
    ],
    "sg:phone":"+44 29 2073 3888",
    "sg:postcode":"CF23 8ET",
    "sg:province":"Cardiff",
    "sg:tags":[
        "dry",
        "control",
        "damp",
        "rot",
        "preservation"
    ],
    "wof:name":"Damp Proofing 2000",
    "wof:placetype":"venue"
},
  "geometry": {"coordinates":[-3.1415839195,51.5324630737],"type":"Point"}
}