{
  "type": "Feature",
  "properties": {
    "addr:full":"245 High Street Exeter Devon EX4 3NZ",
    "addr:housenumber":"245",
    "addr:postcode":"ex4 3nz",
    "addr:street":"High Street",
    "iso:country":"GB",
    "sg:address":"245 High Street",
    "sg:city":"Exeter",
    "sg:classifiers":[
        {
            "category":"Shopping",
            "subcategory":"Tobacco",
            "type":"Retail Goods"
        }
    ],
    "sg:phone":"+44 1392 496111",
    "sg:postcode":"EX4 3NZ",
    "sg:province":"Devon",
    "sg:tags":[
        "tobacconist"
    ],
    "wof:name":"McGahey the Tobacconist",
    "wof:placetype":"venue"
},
  "geometry": {"coordinates":[-3.528414011,50.7250938416],"type":"Point"}
}