{
  "type": "Feature",
  "properties": {
    "addr:full":"Marlin House, 2 Boocoppice Close, The Street Bishops Stortford Essex CM22 6QB",
    "addr:housenumber":"2",
    "addr:postcode":"cm22 6qb",
    "addr:street":"Boocoppice Close The Street",
    "iso:country":"GB",
    "sg:address":"Marlin House, 2 Boocoppice Close, The Street",
    "sg:city":"Bishops Stortford",
    "sg:classifiers":[
        {
            "category":"Education",
            "subcategory":"Special Training",
            "type":"Public Place"
        }
    ],
    "sg:phone":"+44 1279 873494",
    "sg:postcode":"CM22 6QB",
    "sg:province":"Essex",
    "sg:tags":[
        "product",
        "centre"
    ],
    "wof:name":"Marlin Management Training & Conference Services Ltd.",
    "wof:placetype":"venue"
},
  "geometry": {"coordinates":[0.1619500071,51.8723297119],"type":"Point"}
}