{
  "type": "Feature",
  "properties": {
    "addr:full":"Winterbourne Way Worthing West Sussex BN13 3QH",
    "addr:postcode":"bn13 3qh",
    "addr:street":"Winterbourne Way",
    "iso:country":"GB",
    "sg:address":"Winterbourne Way",
    "sg:city":"Worthing",
    "sg:classifiers":[
        {
            "category":"Education",
            "subcategory":"School",
            "type":"Public Place"
        }
    ],
    "sg:phone":"+44 1903 830901",
    "sg:postcode":"BN13 3QH",
    "sg:province":"West Sussex",
    "sg:tags":[
        "local",
        "authority"
    ],
    "wof:name":"The Laurels County First School",
    "wof:placetype":"venue"
},
  "geometry": {"coordinates":[-0.426793,50.829056],"type":"Point"}
}