{
  "type": "Feature",
  "properties": {
    "iso:country":"GB",
    "sg:address":"46 Sheen Lane",
    "sg:city":"London",
    "sg:classifiers":[
        {
            "category":"Shopping",
            "subcategory":"Stationery & Office Supplies",
            "type":"Retail Goods"
        }
    ],
    "sg:phone":"+44 20 8878 7887",
    "sg:postcode":"SW14 8LP",
    "sg:province":"Greater London",
    "sg:tags":[
        "item",
        "promotional"
    ],
    "wof:name":"Cool Million Ltd.",
    "wof:placetype":"venue"
},
  "geometry": {"coordinates":[-0.2671160102,51.4662742615],"type":"Point"}
}