{
  "type": "Feature",
  "properties": {
    "addr:full":"Church Farm, Baldhu Truro Cornwall TR3 6EG",
    "addr:postcode":"tr3 6eg",
    "addr:street":"Baldhu",
    "iso:country":"GB",
    "sg:address":"Church Farm, Baldhu",
    "sg:city":"Truro",
    "sg:classifiers":[
        {
            "category":"Farming",
            "subcategory":"Livestock Farm",
            "type":"Manufacturing & Wholesale Goods"
        }
    ],
    "sg:phone":"+44 1872 560210",
    "sg:postcode":"TR3 6EG",
    "sg:province":"Cornwall",
    "sg:tags":[
        "others"
    ],
    "wof:name":"T J & C J Ham",
    "wof:placetype":"venue"
},
  "geometry": {"coordinates":[-5.1256341934,50.2479782104],"type":"Point"}
}