{
  "type": "Feature",
  "properties": {
    "iso:country":"GB",
    "sg:address":"Unit 8 Station Lane Industrial E, State Station Lan, Old Whittington",
    "sg:city":"Chesterfield",
    "sg:classifiers":[
        {
            "category":"Manufacturing",
            "subcategory":"Electronics",
            "type":"Manufacturing & Wholesale Goods"
        }
    ],
    "sg:phone":"+44 1246 450854",
    "sg:postcode":"S41 9QX",
    "sg:province":"Derbyshire",
    "sg:tags":[
        "control",
        "component",
        "-",
        "electronic"
    ],
    "wof:name":"Sinmet Ltd.",
    "wof:placetype":"venue"
},
  "geometry": {"coordinates":[-1.4254390001,53.2690200806],"type":"Point"}
}