{
  "type": "Feature",
  "properties": {
    "addr:full":"1 Harbour Exchange Sq Poplar Greater London E14 9GE",
    "addr:housenumber":"1",
    "addr:postcode":"e14 9ge",
    "addr:street":"Harbour Exchange Sq",
    "iso:country":"GB",
    "sg:address":"1 Harbour Exchange Sq",
    "sg:city":"Poplar",
    "sg:classifiers":[
        {
            "category":"Health Services",
            "subcategory":"Clinic",
            "type":"Services"
        }
    ],
    "sg:phone":"+44 20 7512 2440",
    "sg:postcode":"E14 9GE",
    "sg:province":"Greater London",
    "sg:tags":[
        "private"
    ],
    "wof:name":"Multicare International",
    "wof:placetype":"venue"
},
  "geometry": {"coordinates":[-0.014494,51.499256],"type":"Point"}
}