{
  "type": "Feature",
  "properties": {
    "iso:country":"GB",
    "sg:address":"Unit 15-16, Chadwick Industrial Estate",
    "sg:city":"Stourport-on-severn",
    "sg:classifiers":[
        {
            "category":"Autos & Motor Vehicles",
            "subcategory":"Boat Sales",
            "type":"Retail Goods"
        },
        {
            "category":"Manufacturing",
            "subcategory":"Watercraft",
            "type":"Manufacturing & Wholesale Goods"
        }
    ],
    "sg:phone":"+44 1299 251471",
    "sg:postcode":"DY13 9QW",
    "sg:province":"Worcestershire",
    "sg:tags":[
        "boatbuilder",
        "repair",
        "builder"
    ],
    "wof:name":"ALEXANDER BOAT BUILDERS",
    "wof:placetype":"venue"
},
  "geometry": {"coordinates":[-2.2811670303,52.3389968872],"type":"Point"}
}