{
  "type": "Feature",
  "properties": {
    "iso:country":"GB",
    "sg:address":"7 Grampian Ct, Beveridges Sq",
    "sg:city":"Livingston",
    "sg:classifiers":[
        {
            "category":"Professional",
            "subcategory":"Printing & Photocopies",
            "type":"Services"
        }
    ],
    "sg:phone":"+44 1506 633123",
    "sg:postcode":"EH54 6QF",
    "sg:province":"West Lothian",
    "sg:tags":[
        "printer"
    ],
    "wof:name":"Murrie Thomson Ltd",
    "wof:placetype":"venue"
},
  "geometry": {"coordinates":[-3.5098340511,55.8862457275],"type":"Point"}
}