{
  "type": "Feature",
  "properties": {
    "addr:full":"Dental Surgery, 12 Woods Terrace East Seaham Durham SR7 9AA",
    "addr:housenumber":"12",
    "addr:postcode":"sr7 9aa",
    "addr:street":"Woods Terrace East",
    "iso:country":"GB",
    "sg:address":"Dental Surgery, 12 Woods Terrace East",
    "sg:city":"Seaham",
    "sg:classifiers":[
        {
            "category":"Health Services",
            "subcategory":"Dentist",
            "type":"Services"
        }
    ],
    "sg:phone":"+44 191 526 0562",
    "sg:postcode":"SR7 9AA",
    "sg:province":"Durham",
    "wof:name":"S Kuverlker",
    "wof:placetype":"venue"
},
  "geometry": {"coordinates":[-1.3420790434,54.8375701904],"type":"Point"}
}