{
  "type": "Feature",
  "properties": {
    "addr:full":"9 De Lane Warr Mews, Station Road Bexhill-on-sea East Sussex TN40 1RD",
    "addr:housenumber":"9",
    "addr:postcode":"tn40 1rd",
    "addr:street":"De Lane Warr Mews Station Road",
    "iso:country":"GB",
    "sg:address":"9 De Lane Warr Mews, Station Road",
    "sg:city":"Bexhill-on-sea",
    "sg:classifiers":[
        {
            "category":"Autos & Motor Vehicles",
            "subcategory":"Motorcycle Sales",
            "type":"Retail Goods"
        }
    ],
    "sg:phone":"+44 1424 211843",
    "sg:postcode":"TN40 1RD",
    "sg:province":"East Sussex",
    "wof:name":"Moton Motor Cycles",
    "wof:placetype":"venue"
},
  "geometry": {"coordinates":[0.478731,50.844955],"type":"Point"}
}