{
  "type": "Feature",
  "properties": {
    "iso:country":"GB",
    "sg:address":"15 Lilycroft Rd",
    "sg:city":"Bradford",
    "sg:classifiers":[
        {
            "category":"Food & Beverages",
            "subcategory":"Meat & Fish",
            "type":"Retail Goods"
        }
    ],
    "sg:postcode":"BD9 5AD",
    "sg:province":"West Yorkshire",
    "sg:tags":[
        "chip"
    ],
    "wof:name":"Akram,Mohad,",
    "wof:placetype":"venue"
},
  "geometry": {"coordinates":[-1.780287981,53.8071098328],"type":"Point"}
}