{
  "type": "Feature",
  "properties": {
    "iso:country":"GB",
    "sg:address":"Harvies Showbar, 234 Main Street",
    "sg:city":"Wishaw",
    "sg:classifiers":[
        {
            "category":"Bars & Pubs",
            "type":"Food & Drink"
        }
    ],
    "sg:phone":"+44 1698 375546",
    "sg:postcode":"ML2 7ND",
    "sg:province":"North Lanarkshire",
    "sg:tags":[
        "pubs",
        "inn"
    ],
    "wof:name":"Harvies Bar Diner",
    "wof:placetype":"venue"
},
  "geometry": {"coordinates":[-3.920879,55.774391],"type":"Point"}
}