{
  "type": "Feature",
  "properties": {
    "addr:full":"37 West Malling Ave Plymouth Devon PL5 2SS",
    "addr:housenumber":"37",
    "addr:postcode":"pl5 2ss",
    "addr:street":"West Malling Ave",
    "iso:country":"GB",
    "sg:address":"37 West Malling Ave",
    "sg:city":"Plymouth",
    "sg:classifiers":[
        {
            "category":"Home & Garden",
            "subcategory":"Home Furnishings",
            "type":"Retail Goods"
        }
    ],
    "sg:postcode":"PL5 2SS",
    "sg:province":"Devon",
    "sg:tags":[
        "furnishers",
        "planner",
        "kitchen"
    ],
    "wof:name":"Harding,L E,",
    "wof:placetype":"venue"
},
  "geometry": {"coordinates":[-4.1784639359,50.4207458496],"type":"Point"}
}