{
  "type": "Feature",
  "properties": {
    "addr:full":"4 Boileau Parade, Boileau Road London Greater London W5 3HQ",
    "addr:housenumber":"4",
    "addr:postcode":"w5 3hq",
    "addr:street":"Boileau Parade Boileau Road",
    "iso:country":"GB",
    "sg:address":"4 Boileau Parade, Boileau Road",
    "sg:city":"London",
    "sg:classifiers":[
        {
            "category":"Fast Food",
            "type":"Food & Drink"
        }
    ],
    "sg:postcode":"W5 3HQ",
    "sg:province":"Greater London",
    "sg:tags":[
        "away",
        "take"
    ],
    "wof:name":"Hopewell",
    "wof:placetype":"venue"
},
  "geometry": {"coordinates":[-0.2896179855,51.5175552368],"type":"Point"}
}