{
  "type": "Feature",
  "properties": {
    "iso:country":"GB",
    "sg:address":"20 Lichfield Street",
    "sg:city":"Bilston",
    "sg:classifiers":[
        {
            "category":"Bars & Pubs",
            "type":"Food & Drink"
        }
    ],
    "sg:phone":"+44 1902 498339",
    "sg:postcode":"WV14 0AG",
    "sg:province":"West Midlands",
    "sg:tags":[
        "pubs",
        "inn"
    ],
    "wof:name":"Olde White Rose Inn",
    "wof:placetype":"venue"
},
  "geometry": {"coordinates":[-2.0738589764,52.5660514832],"type":"Point"}
}