{
  "type": "Feature",
  "properties": {
    "iso:country":"GB",
    "sg:address":"3 Monmouth Place",
    "sg:city":"Bath",
    "sg:classifiers":[
        {
            "category":"Recreation",
            "subcategory":"Gun Range",
            "type":"Entertainment"
        }
    ],
    "sg:phone":"+44 1225 469508",
    "sg:postcode":"BA1 2AT",
    "sg:province":"Bath and North East Somerset",
    "sg:tags":[
        "operator",
        "tour"
    ],
    "wof:name":"European Connoisseurs Travel B V",
    "wof:placetype":"venue"
},
  "geometry": {"coordinates":[-2.3671209812,51.383014679],"type":"Point"}
}