{
  "type": "Feature",
  "properties": {
    "iso:country":"GB",
    "sg:address":"228 Gleadless Road",
    "sg:city":"Sheffield",
    "sg:classifiers":[
        {
            "category":"Organizations",
            "subcategory":"Labor Organization",
            "type":"Services"
        },
        {
            "category":"Personal",
            "subcategory":"Sauna",
            "type":"Services"
        }
    ],
    "sg:phone":"+44 114 255 3583",
    "sg:postcode":"S2 3AF",
    "sg:province":"South Yorkshire",
    "sg:tags":[
        "activity"
    ],
    "sg:website":"http://www.parlor.co.uk",
    "wof:name":"Cameo",
    "wof:placetype":"venue"
},
  "geometry": {"coordinates":[-1.465845,53.359592],"type":"Point"}
}