{
  "type": "Feature",
  "properties": {
    "iso:country":"GB",
    "sg:address":"Brown & Illingworth Ford 5-5, Hoults Estate Walker Road",
    "sg:city":"Newcastle-upon-tyne",
    "sg:classifiers":[
        {
            "category":"Retail",
            "subcategory":"Storage",
            "type":"Services"
        }
    ],
    "sg:phone":"+44 191 265 3860",
    "sg:postcode":"NE6 1AB",
    "sg:province":"Tyne and Wear",
    "sg:tags":[
        "household",
        "removal"
    ],
    "wof:name":"Brown & Illingworth",
    "wof:placetype":"venue"
},
  "geometry": {"coordinates":[-1.58204,54.97065],"type":"Point"}
}