{
  "type": "Feature",
  "properties": {
    "addr:full":"159-161 West Street Sheffield South Yorkshire S1 4EW",
    "addr:housenumber":"159-161",
    "addr:postcode":"s1 4ew",
    "addr:street":"West Street",
    "iso:country":"GB",
    "sg:address":"159-161 West Street",
    "sg:city":"Sheffield",
    "sg:classifiers":[
        {
            "category":"Sports & Exercise",
            "subcategory":"Sports Center",
            "type":"Entertainment"
        }
    ],
    "sg:postcode":"S1 4EW",
    "sg:province":"South Yorkshire",
    "sg:tags":[
        "shop",
        "good"
    ],
    "wof:name":"Darlows Sports Ltd.",
    "wof:placetype":"venue"
},
  "geometry": {"coordinates":[-1.479263,53.380054],"type":"Point"}
}