{
  "type": "Feature",
  "properties": {
    "iso:country":"GB",
    "sg:address":"Townfield Lane",
    "sg:city":"Wirral",
    "sg:classifiers":[
        {
            "category":"Education",
            "subcategory":"School",
            "type":"Public Place"
        }
    ],
    "sg:phone":"+44 151 645 7782",
    "sg:postcode":"CH63 7NL",
    "sg:province":"Merseyside",
    "sg:tags":[
        "local",
        "authority"
    ],
    "wof:name":"St Andrew's C of E Primary School",
    "wof:placetype":"venue"
},
  "geometry": {"coordinates":[-3.008783,53.355461],"type":"Point"}
}