{
  "type": "Feature",
  "properties": {
    "addr:full":"Love Lane Mayfield East Sussex TN20 6EN",
    "addr:postcode":"tn20 6en",
    "addr:street":"Love Lane",
    "iso:country":"GB",
    "sg:address":"Love Lane",
    "sg:city":"Mayfield",
    "sg:classifiers":[
        {
            "category":"Freight",
            "type":"Transportation"
        }
    ],
    "sg:phone":"+44 1435 873160",
    "sg:postcode":"TN20 6EN",
    "sg:province":"East Sussex",
    "sg:tags":[
        "haulage",
        "transport",
        "road"
    ],
    "wof:name":"Wincanton Group Ltd.",
    "wof:placetype":"venue"
},
  "geometry": {"coordinates":[0.251698,51.021358],"type":"Point"}
}