{
  "type": "Feature",
  "properties": {
    "addr:full":"Hanwell Cottage, Swainshill Hereford Herefordshire HR4 7QB",
    "addr:postcode":"hr4 7qb",
    "addr:street":"Swainshill",
    "iso:country":"GB",
    "sg:address":"Hanwell Cottage, Swainshill",
    "sg:city":"Hereford",
    "sg:classifiers":[
        {
            "category":"Building & Trades",
            "subcategory":"Construction",
            "type":"Services"
        }
    ],
    "sg:phone":"+44 1981 590475",
    "sg:postcode":"HR4 7QB",
    "sg:province":"Herefordshire",
    "sg:tags":[
        "builder"
    ],
    "wof:name":"T W Welch",
    "wof:placetype":"venue"
},
  "geometry": {"coordinates":[-2.790829,52.072987],"type":"Point"}
}