{
  "type": "Feature",
  "properties": {
    "addr:full":"Caenby Corner Estate, Hemswell Cliff Gainsborough Lincolnshire DN21 5TH",
    "addr:housenumber":"caenby",
    "addr:postcode":"dn21 5th",
    "iso:country":"GB",
    "sg:address":"Caenby Corner Estate, Hemswell Cliff",
    "sg:city":"Gainsborough",
    "sg:classifiers":[
        {
            "category":"Home & Garden",
            "subcategory":"Furniture",
            "type":"Retail Goods"
        }
    ],
    "sg:phone":"+44 1427 667228",
    "sg:postcode":"DN21 5TH",
    "sg:province":"Lincolnshire",
    "wof:name":"Tops Light Fabrics",
    "wof:placetype":"venue"
},
  "geometry": {"coordinates":[-0.5719490051,53.3951911926],"type":"Point"}
}