{
  "type": "Feature",
  "properties": {
    "addr:full":"31 Surrey St Croydon Surrey CR0 1RG",
    "addr:housenumber":"31",
    "addr:postcode":"cr0 1rg",
    "addr:street":"Surrey St",
    "iso:country":"GB",
    "sg:address":"31 Surrey St",
    "sg:city":"Croydon",
    "sg:classifiers":[
        {
            "category":"Shopping",
            "subcategory":"Comic Books",
            "type":"Retail Goods"
        }
    ],
    "sg:phone":"+44 20 8686 2035",
    "sg:postcode":"CR0 1RG",
    "sg:province":"Surrey",
    "sg:tags":[
        "jeweller"
    ],
    "wof:name":"Tiffanys Jewellers",
    "wof:placetype":"venue"
},
  "geometry": {"coordinates":[-0.1013899967,51.3729019165],"type":"Point"}
}