{
  "type": "Feature",
  "properties": {
    "addr:full":"1 Durrance Courtyard, Berry Lane, Upton Warren Bromsgrove Worcestershire B61 9EL",
    "addr:housenumber":"1",
    "addr:postcode":"b61 9el",
    "addr:street":"Durrance Courtyard Berry Lane",
    "iso:country":"GB",
    "sg:address":"1 Durrance Courtyard, Berry Lane, Upton Warren",
    "sg:city":"Bromsgrove",
    "sg:classifiers":[
        {
            "category":"Real Estate",
            "subcategory":"Real Estate Operator",
            "type":"Services"
        },
        {
            "category":"Real Estate",
            "subcategory":"Developer",
            "type":"Services"
        }
    ],
    "sg:phone":"+44 1562 777747",
    "sg:postcode":"B61 9EL",
    "sg:province":"Worcestershire",
    "sg:tags":[
        "letting",
        "property",
        "agent"
    ],
    "wof:name":"Worcester & Regional Properties Ltd.",
    "wof:placetype":"venue"
},
  "geometry": {"coordinates":[-2.0581119061,52.3365936279],"type":"Point"}
}