{
  "type": "Feature",
  "properties": {
    "iso:country":"GB",
    "sg:address":"7a Newgate Street",
    "sg:city":"Morpeth",
    "sg:classifiers":[
        {
            "category":"Personal",
            "subcategory":"Beauty Salon",
            "type":"Services"
        },
        {
            "category":"Personal",
            "subcategory":"Barber",
            "type":"Services"
        }
    ],
    "sg:phone":"+44 1670 512011",
    "sg:postcode":"NE61 1AL",
    "sg:province":"Northumberland",
    "sg:tags":[
        "unisex",
        "hairdresser"
    ],
    "wof:name":"Lynnes",
    "wof:placetype":"venue"
},
  "geometry": {"coordinates":[-1.690958,55.167858],"type":"Point"}
}