{
  "type": "Feature",
  "properties": {
    "addr:full":"64 Lancaster Road Preston Lancashire PR1 1DD",
    "addr:housenumber":"64",
    "addr:postcode":"pr1 1dd",
    "addr:street":"Lancaster Road",
    "iso:country":"GB",
    "sg:address":"64 Lancaster Road",
    "sg:city":"Preston",
    "sg:classifiers":[
        {
            "category":"Shopping",
            "subcategory":"Florist",
            "type":"Retail Goods"
        }
    ],
    "sg:postcode":"PR1 1DD",
    "sg:province":"Lancashire",
    "wof:name":"Forshaws Flower Shop",
    "wof:placetype":"venue"
},
  "geometry": {"coordinates":[-2.6983671188,53.7605361938],"type":"Point"}
}