{
  "type": "Feature",
  "properties": {
    "iso:country":"GB",
    "sg:address":"54 Moore Lane",
    "sg:city":"Chesterfield",
    "sg:classifiers":[
        {
            "category":"Shopping",
            "subcategory":"Department Store",
            "type":"Retail Goods"
        }
    ],
    "sg:phone":"+44 1246 823966",
    "sg:postcode":"S44 6EW",
    "sg:province":"Derbyshire",
    "wof:name":"Moore Lane General Store",
    "wof:placetype":"venue"
},
  "geometry": {"coordinates":[-1.283662,53.227695],"type":"Point"}
}