{
  "type": "Feature",
  "properties": {
    "iso:country":"GB",
    "sg:address":"2 Saxon Court, High Street, Bidford On Avon",
    "sg:city":"Alcester",
    "sg:classifiers":[
        {
            "category":"Personal",
            "subcategory":"Beauty Salon",
            "type":"Services"
        }
    ],
    "sg:phone":"+44 1789 778997",
    "sg:postcode":"B50 4AB",
    "sg:province":"Warwickshire",
    "sg:tags":[
        "ladies",
        "lady",
        "hairdresser"
    ],
    "wof:name":"Hair By Chris",
    "wof:placetype":"venue"
},
  "geometry": {"coordinates":[-1.856308,52.164665],"type":"Point"}
}