{
  "type": "Feature",
  "properties": {
    "addr:full":"194 Lower Rd Sth Bermondsey Greater London SE16 2UN",
    "addr:housenumber":"194",
    "addr:postcode":"se16 2un",
    "addr:street":"Lower Rd",
    "iso:country":"GB",
    "sg:address":"194 Lower Rd",
    "sg:city":"Sth Bermondsey",
    "sg:classifiers":[
        {
            "category":"Retail",
            "subcategory":"Laundry & Dry Cleaning",
            "type":"Services"
        }
    ],
    "sg:phone":"+44 20 7237 3725",
    "sg:postcode":"SE16 2UN",
    "sg:province":"Greater London",
    "sg:tags":[
        "alteration"
    ],
    "wof:name":"Four Hour Clean-In",
    "wof:placetype":"venue"
},
  "geometry": {"coordinates":[-0.045832,51.492256],"type":"Point"}
}