{
  "type": "Feature",
  "properties": {
    "addr:full":"17 Edleston Road Crewe Cheshire CW2 7HJ",
    "addr:housenumber":"17",
    "addr:postcode":"cw2 7hj",
    "addr:street":"Edleston Road",
    "iso:country":"GB",
    "sg:address":"17 Edleston Road",
    "sg:city":"Crewe",
    "sg:classifiers":[
        {
            "category":"Shopping",
            "subcategory":"Bicycles & Sporting Goods",
            "type":"Retail Goods"
        }
    ],
    "sg:phone":"+44 1270 255672",
    "sg:postcode":"CW2 7HJ",
    "sg:province":"Cheshire",
    "sg:tags":[
        "cycle",
        "accessory"
    ],
    "wof:name":"J E Williams & Son",
    "wof:placetype":"venue"
},
  "geometry": {"coordinates":[-2.4410350323,53.0890083313],"type":"Point"}
}