{
  "type": "Feature",
  "properties": {
    "addr:full":"10 Castle Place, Castle Street High Wycombe Buckinghamshire HP13 6RF",
    "addr:housenumber":"10",
    "addr:postcode":"hp13 6rf",
    "addr:street":"Castle Place Castle Street",
    "iso:country":"GB",
    "sg:address":"10 Castle Place, Castle Street",
    "sg:city":"High Wycombe",
    "sg:classifiers":[
        {
            "category":"Professional",
            "subcategory":"Employment Agencies",
            "type":"Services"
        }
    ],
    "sg:phone":"+44 1494 450312",
    "sg:postcode":"HP13 6RF",
    "sg:province":"Buckinghamshire",
    "sg:tags":[
        "consultant"
    ],
    "wof:name":"Adecco Alfred Marks",
    "wof:placetype":"venue"
},
  "geometry": {"coordinates":[-0.749419,51.630405],"type":"Point"}
}