{
  "type": "Feature",
  "properties": {
    "addr:full":"17 The Garages, Ellesmere Avenue London Greater London NW7 3EX",
    "addr:housenumber":"17",
    "addr:postcode":"nw7 3ex",
    "addr:street":"The Garages Ellesmere Avenue",
    "iso:country":"GB",
    "sg:address":"17 The Garages, Ellesmere Avenue",
    "sg:city":"London",
    "sg:classifiers":[
        {
            "category":"Shopping",
            "type":"Retail Goods"
        }
    ],
    "sg:phone":"+44 20 8959 2230",
    "sg:postcode":"NW7 3EX",
    "sg:province":"Greater London",
    "sg:tags":[
        "part",
        "accessory"
    ],
    "wof:name":"Nissan Spares",
    "wof:placetype":"venue"
},
  "geometry": {"coordinates":[-0.2567000091,51.6224403381],"type":"Point"}
}