{
  "type": "Feature",
  "properties": {
    "addr:full":"New Close Farm, Bar Rd, Lolworth Cambridge Cambridgeshire CB3 8DS",
    "addr:postcode":"cb3 8ds",
    "addr:street":"New Close;Bar Rd",
    "iso:country":"GB",
    "sg:address":"New Close Farm, Bar Rd, Lolworth",
    "sg:city":"Cambridge",
    "sg:classifiers":[
        {
            "category":"Building & Trades",
            "subcategory":"Construction",
            "type":"Services"
        }
    ],
    "sg:phone":"+44 1954 789810",
    "sg:postcode":"CB3 8DS",
    "sg:province":"Cambridgeshire",
    "sg:tags":[
        "joiner",
        "carpenter"
    ],
    "wof:name":"C.J Warner",
    "wof:placetype":"venue"
},
  "geometry": {"coordinates":[0.00126,52.25819],"type":"Point"}
}