{
  "type": "Feature",
  "properties": {
    "iso:country":"GB",
    "sg:address":"55 Church Road, Rainford",
    "sg:city":"St Helens",
    "sg:classifiers":[
        {
            "category":"Autos & Motor Vehicles",
            "subcategory":"Automobile Sales",
            "type":"Retail Goods"
        }
    ],
    "sg:postcode":"WA11 8EZ",
    "sg:province":"Lancashire",
    "sg:tags":[
        "car"
    ],
    "wof:name":"S C S Car Sales",
    "wof:placetype":"venue"
},
  "geometry": {"coordinates":[-2.78448,53.498386],"type":"Point"}
}