{
  "type": "Feature",
  "properties": {
    "addr:full":"Anchorhill Gordon Scottish Borders TD3 6JU",
    "addr:postcode":"td3 6ju",
    "iso:country":"GB",
    "sg:address":"Anchorhill",
    "sg:city":"Gordon",
    "sg:classifiers":[
        {
            "category":"Banks & Credit Unions",
            "subcategory":"Financial Services",
            "type":"Services"
        }
    ],
    "sg:phone":"+44 1573 410581",
    "sg:postcode":"TD3 6JU",
    "sg:province":"Scottish Borders",
    "sg:tags":[
        "adviser",
        "independent"
    ],
    "wof:name":"David G Livingstone",
    "wof:placetype":"venue"
},
  "geometry": {"coordinates":[-2.560988903,55.6804504395],"type":"Point"}
}