{
  "type": "Feature",
  "properties": {
    "addr:full":"25 Pasture Road Goole East Riding of Yorkshire DN14 6BP",
    "addr:housenumber":"25",
    "addr:postcode":"dn14 6bp",
    "addr:street":"Pasture Road",
    "iso:country":"GB",
    "sg:address":"25 Pasture Road",
    "sg:city":"Goole",
    "sg:classifiers":[
        {
            "category":"Home & Garden",
            "subcategory":"Household Appliances",
            "type":"Retail Goods"
        },
        {
            "category":"Utilities",
            "subcategory":"Natural Gas",
            "type":"Services"
        }
    ],
    "sg:phone":"+44 1405 760395",
    "sg:postcode":"DN14 6BP",
    "sg:province":"East Riding of Yorkshire",
    "sg:tags":[
        "sale"
    ],
    "wof:name":"Gas Corner",
    "wof:placetype":"venue"
},
  "geometry": {"coordinates":[-0.875205,53.706059],"type":"Point"}
}