{
  "type": "Feature",
  "properties": {
    "iso:country":"GB",
    "sg:address":"7 Summerhill Gro",
    "sg:city":"Newcastle Upon Tyne",
    "sg:classifiers":[
        {
            "category":"Organizations",
            "subcategory":"Religious Organization",
            "type":"Services"
        }
    ],
    "sg:phone":"+44 191 232 0942",
    "sg:postcode":"NE4 6EE",
    "sg:province":"Tyne and Wear",
    "sg:tags":[
        "organisation",
        "place",
        "worship"
    ],
    "wof:name":"St Anne's Convent",
    "wof:placetype":"venue"
},
  "geometry": {"coordinates":[-1.629198,54.971348],"type":"Point"}
}