{
  "type": "Feature",
  "properties": {
    "addr:full":"P O Box 1 Battle East Sussex TN33 0YB",
    "addr:housenumber":"1",
    "addr:postcode":"tn33 0yb",
    "addr:street":"P O Box;Battle",
    "iso:country":"GB",
    "sg:address":"P O Box 1",
    "sg:city":"Battle",
    "sg:classifiers":[
        {
            "category":"Professional",
            "subcategory":"Management & Consulting",
            "type":"Services"
        }
    ],
    "sg:phone":"+44 1424 775100",
    "sg:postcode":"TN33 0YB",
    "sg:province":"East Sussex",
    "sg:tags":[
        "consultant",
        "business"
    ],
    "wof:name":"Herrmann Institute The",
    "wof:placetype":"venue"
},
  "geometry": {"coordinates":[0.5020679832,50.9174690247],"type":"Point"}
}