{
  "type": "Feature",
  "properties": {
    "addr:full":"40 Burwell Avenue Greenford Greater London UB6 0NU",
    "addr:housenumber":"40",
    "addr:postcode":"ub6 0nu",
    "addr:street":"Burwell Avenue",
    "iso:country":"GB",
    "sg:address":"40 Burwell Avenue",
    "sg:city":"Greenford",
    "sg:classifiers":[
        {
            "category":"Retail",
            "subcategory":"Auto Repair",
            "type":"Services"
        }
    ],
    "sg:phone":"+44 20 8423 2245",
    "sg:postcode":"UB6 0NU",
    "sg:province":"Greater London",
    "sg:tags":[
        "engine",
        "car",
        "specialist"
    ],
    "wof:name":"In Tune",
    "wof:placetype":"venue"
},
  "geometry": {"coordinates":[-0.3379899859,51.5499801636],"type":"Point"}
}