{
  "type": "Feature",
  "properties": {
    "addr:full":"Jennycliffe Plymouth Devon PL9 9TU",
    "addr:postcode":"pl9 9tu",
    "addr:street":"Jennycliffe",
    "iso:country":"GB",
    "sg:address":"Jennycliffe",
    "sg:city":"Plymouth",
    "sg:classifiers":[
        {
            "category":"Sports & Exercise",
            "subcategory":"Gym",
            "type":"Entertainment"
        }
    ],
    "sg:phone":"+44 1752 402576",
    "sg:postcode":"PL9 9TU",
    "sg:province":"Devon",
    "sg:tags":[
        "fitness",
        "health",
        "centre"
    ],
    "wof:name":"Fort Stamford Squash & Fitness Centre",
    "wof:placetype":"venue"
},
  "geometry": {"coordinates":[-4.1164059639,50.353427887],"type":"Point"}
}