{
  "type": "Feature",
  "properties": {
    "iso:country":"GB",
    "sg:address":"Gordano Service Area, M5 Motorway, Portbury",
    "sg:city":"Bristol",
    "sg:classifiers":[
        {
            "category":"Autos & Motor Vehicles",
            "subcategory":"Fuel & Gas Station",
            "type":"Retail Goods"
        }
    ],
    "sg:phone":"+44 1275 375885",
    "sg:postcode":"BS20 7XG",
    "sg:province":"Somerset",
    "sg:tags":[
        "hr",
        "petrol"
    ],
    "wof:name":"Meridien Holdings Ltd.",
    "wof:placetype":"venue"
},
  "geometry": {"coordinates":[-2.7173190117,51.4746360779],"type":"Point"}
}