{
  "type": "Feature",
  "properties": {
    "addr:full":"37 The Foregate Kilmarnock East Ayrshire KA1 1LU",
    "addr:housenumber":"37",
    "addr:postcode":"ka1 1lu",
    "addr:street":"The Foregate",
    "iso:country":"GB",
    "sg:address":"37 The Foregate",
    "sg:city":"Kilmarnock",
    "sg:classifiers":[
        {
            "category":"Food & Beverages",
            "subcategory":"Bakery",
            "type":"Retail Goods"
        }
    ],
    "sg:phone":"+44 1563 536792",
    "sg:postcode":"KA1 1LU",
    "sg:province":"East Ayrshire",
    "sg:tags":[
        "baker"
    ],
    "wof:name":"Grays the Country Bakers",
    "wof:placetype":"venue"
},
  "geometry": {"coordinates":[-4.5097298622,55.6088943481],"type":"Point"}
}