{
  "type": "Feature",
  "properties": {
    "addr:full":"Unit 43-44 Market Gate Shopping, Centre Wigan Lancashire WN1 1HX",
    "addr:housenumber":"unit 43-44",
    "addr:postcode":"wn1 1hx",
    "addr:street":"Market Gate Shopping",
    "iso:country":"GB",
    "sg:address":"Unit 43-44 Market Gate Shopping, Centre",
    "sg:city":"Wigan",
    "sg:classifiers":[
        {
            "category":"Shopping",
            "subcategory":"Shoes",
            "type":"Retail Goods"
        }
    ],
    "sg:phone":"+44 1942 324989",
    "sg:postcode":"WN1 1HX",
    "sg:province":"Lancashire",
    "sg:tags":[
        "shop"
    ],
    "wof:name":"Instep Sports",
    "wof:placetype":"venue"
},
  "geometry": {"coordinates":[-2.631393,53.546745],"type":"Point"}
}