{
  "type": "Feature",
  "properties": {
    "iso:country":"GB",
    "sg:address":"Westerleigh",
    "sg:city":"Bristol",
    "sg:classifiers":[
        {
            "category":"Sports & Exercise",
            "subcategory":"Stables",
            "type":"Entertainment"
        }
    ],
    "sg:phone":"+44 1454 318458",
    "sg:postcode":"BS37 8QU",
    "sg:province":"Gloucestershire",
    "sg:tags":[
        "education",
        "equestrian"
    ],
    "wof:name":"Westerleigh Livery Stables",
    "wof:placetype":"venue"
},
  "geometry": {"coordinates":[-2.427243948,51.5112838745],"type":"Point"}
}