{
  "type": "Feature",
  "properties": {
    "iso:country":"GB",
    "sg:address":"99 Bute Street",
    "sg:city":"Treorchy",
    "sg:classifiers":[
        {
            "category":"Professional",
            "subcategory":"Accounting & Tax Preparation",
            "type":"Services"
        }
    ],
    "sg:postcode":"CF42 5NY",
    "sg:province":"Rhondda, Cynon, Taff",
    "sg:tags":[
        "accountant"
    ],
    "wof:name":"Searle Sons & Co.",
    "wof:placetype":"venue"
},
  "geometry": {"coordinates":[-3.5307939053,51.6717758179],"type":"Point"}
}