{
  "type": "Feature",
  "properties": {
    "addr:full":"99 Bute Street Treorchy Rhondda, Cynon, Taff CF42 5NY",
    "addr:housenumber":"99",
    "addr:postcode":"cf42 5ny",
    "addr:street":"Bute Street;Cynon Taff",
    "iso:country":"GB",
    "sg:address":"99 Bute Street",
    "sg:city":"Treorchy",
    "sg:classifiers":[
        {
            "category":"Professional",
            "subcategory":"Accounting & Tax Preparation",
            "type":"Services"
        }
    ],
    "sg:postcode":"CF42 5NY",
    "sg:province":"Rhondda, Cynon, Taff",
    "sg:tags":[
        "accountant"
    ],
    "wof:name":"Searle Sons & Co.",
    "wof:placetype":"venue"
},
  "geometry": {"coordinates":[-3.5307939053,51.6717758179],"type":"Point"}
}