{
  "type": "Feature",
  "properties": {
    "addr:full":"469 Otley Rd Bradford West Yorkshire BD2 4QF",
    "addr:housenumber":"469",
    "addr:postcode":"bd2 4qf",
    "addr:street":"Otley Rd",
    "iso:country":"GB",
    "sg:address":"469 Otley Rd",
    "sg:city":"Bradford",
    "sg:classifiers":[
        {
            "category":"Wholesale",
            "subcategory":"Apparel",
            "type":"Manufacturing & Wholesale Goods"
        }
    ],
    "sg:phone":"+44 1274 626383",
    "sg:postcode":"BD2 4QF",
    "sg:province":"West Yorkshire",
    "sg:tags":[
        "babywear",
        "childrens"
    ],
    "wof:name":"Under Age Childrens Wear",
    "wof:placetype":"venue"
},
  "geometry": {"coordinates":[-1.731241,53.808121],"type":"Point"}
}