{
  "type": "Feature",
  "properties": {
    "iso:country":"GB",
    "sg:address":"40 Upper Church Rd",
    "sg:city":"Weston Super Mare",
    "sg:classifiers":[
        {
            "category":"Home & Garden",
            "subcategory":"Garden Supply",
            "type":"Retail Goods"
        }
    ],
    "sg:phone":"+44 1934 635557",
    "sg:postcode":"BS23 2DX",
    "sg:province":"Somerset",
    "sg:tags":[
        "nursery",
        "centre"
    ],
    "wof:name":"All Seasons",
    "wof:placetype":"venue"
},
  "geometry": {"coordinates":[-2.985601,51.353317],"type":"Point"}
}