{
  "type": "Feature",
  "properties": {
    "iso:country":"GB",
    "sg:address":"Unit 11 Amethyst Road, Newcastle Business Park",
    "sg:city":"Newcastle-upon-tyne",
    "sg:classifiers":[
        {
            "category":"Professional",
            "subcategory":"Management & Consulting",
            "type":"Services"
        }
    ],
    "sg:phone":"+44 191 273 0741",
    "sg:postcode":"NE4 7YL",
    "sg:province":"Tyne and Wear",
    "sg:tags":[
        "marketing",
        "consultant"
    ],
    "wof:name":"Willow Marketing",
    "wof:placetype":"venue"
},
  "geometry": {"coordinates":[-1.645145,54.961391],"type":"Point"}
}