{
  "type": "Feature",
  "properties": {
    "iso:country":"GB",
    "sg:address":"37 Castle St",
    "sg:city":"Dover",
    "sg:classifiers":[
        {
            "category":"Shopping",
            "subcategory":"Clothing, Apparel, & Fashions",
            "type":"Retail Goods"
        }
    ],
    "sg:phone":"+44 1304 211091",
    "sg:postcode":"CT16 1PT",
    "sg:province":"Kent",
    "sg:tags":[
        "dresswear"
    ],
    "wof:name":"Mary Sewing & Alterations",
    "wof:placetype":"venue"
},
  "geometry": {"coordinates":[1.314788,51.125931],"type":"Point"}
}