{
  "type": "Feature",
  "properties": {
    "addr:full":"Mossley Hill Hospital Liverpool Merseyside L18 8BU",
    "addr:postcode":"l18 8bu",
    "iso:country":"GB",
    "sg:address":"Mossley Hill Hospital",
    "sg:city":"Liverpool",
    "sg:classifiers":[
        {
            "category":"Wholesale",
            "subcategory":"Medical Equipment & Supplies",
            "type":"Manufacturing & Wholesale Goods"
        }
    ],
    "sg:postcode":"L18 8BU",
    "sg:province":"Merseyside",
    "sg:tags":[
        "hospital"
    ],
    "wof:name":"N H S Supplies N W Division",
    "wof:placetype":"venue"
},
  "geometry": {"coordinates":[-2.9208300114,53.3752441406],"type":"Point"}
}