{
  "type": "Feature",
  "properties": {
    "addr:full":"13 Duke Street Glossop Derbyshire SK13 8JD",
    "addr:housenumber":"13",
    "addr:postcode":"sk13 8jd",
    "addr:street":"Duke Street",
    "iso:country":"GB",
    "sg:address":"13 Duke Street",
    "sg:city":"Glossop",
    "sg:classifiers":[
        {
            "category":"Professional",
            "type":"Services"
        }
    ],
    "sg:postcode":"SK13 8JD",
    "sg:province":"Derbyshire",
    "sg:tags":[
        "repair",
        "tech",
        "maintenance"
    ],
    "wof:name":"Total Business I.T. Solutions Ltd",
    "wof:placetype":"venue"
},
  "geometry": {"coordinates":[-1.9550689459,53.4397506714],"type":"Point"}
}