{
  "type": "Feature",
  "properties": {
    "addr:full":"43 High Street, Meadowhall Centre Sheffield South Yorkshire S9 1EN",
    "addr:housenumber":"43",
    "addr:postcode":"s9 1en",
    "addr:street":"High Street",
    "iso:country":"GB",
    "sg:address":"43 High Street, Meadowhall Centre",
    "sg:city":"Sheffield",
    "sg:classifiers":[
        {
            "category":"Banks & Credit Unions",
            "subcategory":"Bank",
            "type":"Services"
        }
    ],
    "sg:phone":"+44 114 256 8381",
    "sg:postcode":"S9 1EN",
    "sg:province":"South Yorkshire",
    "wof:name":"Lloyds Tsb Bank Plc",
    "wof:placetype":"venue"
},
  "geometry": {"coordinates":[-1.392555,53.412415],"type":"Point"}
}