{
  "type": "Feature",
  "properties": {
    "iso:country":"GB",
    "sg:address":"73 Portree Drive, Holmes Chapel",
    "sg:city":"Crewe",
    "sg:classifiers":[
        {
            "category":"Professional",
            "subcategory":"Business Services",
            "type":"Services"
        },
        {
            "category":"Wholesale",
            "subcategory":"Computers",
            "type":"Manufacturing & Wholesale Goods"
        }
    ],
    "sg:phone":"+44 1477 534273",
    "sg:postcode":"CW4 7JB",
    "sg:province":"Cheshire",
    "sg:tags":[
        "supplier",
        "information",
        "consumables"
    ],
    "wof:name":"B J B International Ltd.",
    "wof:placetype":"venue"
},
  "geometry": {"coordinates":[-2.3604640961,53.1962928772],"type":"Point"}
}