{
  "type": "Feature",
  "properties": {
    "iso:country":"GB",
    "sg:address":"Sterling House",
    "sg:city":"London",
    "sg:classifiers":[
        {
            "category":"Real Estate",
            "subcategory":"Real Estate Agent",
            "type":"Services"
        }
    ],
    "sg:phone":"+44 20 8348 5555",
    "sg:postcode":"E17 4EE",
    "sg:province":"Greater London",
    "wof:name":"Junita Ltd.",
    "wof:placetype":"venue"
},
  "geometry": {"coordinates":[0.017715,51.530567],"type":"Point"}
}