{
  "type": "Feature",
  "properties": {
    "iso:country":"GB",
    "sg:address":"24 Runswick Drive",
    "sg:city":"Nottingham",
    "sg:classifiers":[
        {
            "category":"Building & Trades",
            "subcategory":"Construction",
            "type":"Services"
        }
    ],
    "sg:phone":"+44 115 913 9657",
    "sg:postcode":"NG8 1JD",
    "sg:province":"Nottinghamshire",
    "sg:tags":[
        "roofing"
    ],
    "wof:name":"A & A Roofing",
    "wof:placetype":"venue"
},
  "geometry": {"coordinates":[-1.201653,52.956581],"type":"Point"}
}