{
  "type": "Feature",
  "properties": {
    "addr:full":"The Rectory Corby Northamptonshire NN17 3DY",
    "addr:postcode":"nn17 3dy",
    "iso:country":"GB",
    "sg:address":"The Rectory",
    "sg:city":"Corby",
    "sg:classifiers":[
        {
            "category":"Place Of Worship",
            "type":"Public Place"
        }
    ],
    "sg:phone":"+44 1780 450249",
    "sg:postcode":"NN17 3DY",
    "sg:province":"Northamptonshire",
    "wof:name":"All Saints Laxton",
    "wof:placetype":"venue"
},
  "geometry": {"coordinates":[-0.63169,52.496387],"type":"Point"}
}