{
  "type": "Feature",
  "properties": {
    "addr:full":"Rear Of Preston Lancashire PR2 2SU",
    "addr:housenumber":"rear of preston",
    "addr:postcode":"pr2 2su",
    "iso:country":"GB",
    "sg:address":"Rear Of",
    "sg:city":"Preston",
    "sg:classifiers":[
        {
            "category":"Building & Trades",
            "subcategory":"Construction",
            "type":"Services"
        }
    ],
    "sg:phone":"+44 1772 725706",
    "sg:postcode":"PR2 2SU",
    "sg:province":"Lancashire",
    "sg:tags":[
        "decorator",
        "painter"
    ],
    "wof:name":"Brian Parry Ltd.",
    "wof:placetype":"venue"
},
  "geometry": {"coordinates":[-2.7226688862,53.7658691406],"type":"Point"}
}