{
  "type": "Feature",
  "properties": {
    "iso:country":"GB",
    "sg:address":"2 Glen Road, Boscombe",
    "sg:city":"Bournemouth",
    "sg:classifiers":[
        {
            "category":"Travel",
            "subcategory":"Hotels & Motels",
            "type":"Entertainment"
        }
    ],
    "sg:phone":"+44 1202 460269",
    "sg:postcode":"BH5 1HR",
    "sg:province":"Dorset",
    "wof:name":"Silver Fern Hotel",
    "wof:placetype":"venue"
},
  "geometry": {"coordinates":[-1.839704,50.723328],"type":"Point"}
}