{
  "type": "Feature",
  "properties": {
    "addr:full":"4 Cairns Road, Westbury Park Bristol City of Bristol BS6 7TZ",
    "addr:housenumber":"4",
    "addr:postcode":"bs6 7tz",
    "addr:street":"Cairns Road;Park",
    "iso:country":"GB",
    "sg:address":"4 Cairns Road, Westbury Park",
    "sg:city":"Bristol",
    "sg:classifiers":[
        {
            "category":"Professional",
            "subcategory":"Computer Services",
            "type":"Services"
        }
    ],
    "sg:postcode":"BS6 7TZ",
    "sg:province":"City of Bristol",
    "sg:tags":[
        "system",
        "software"
    ],
    "wof:name":"Dartview Ltd.",
    "wof:placetype":"venue"
},
  "geometry": {"coordinates":[-2.60696,51.481506],"type":"Point"}
}