{
  "type": "Feature",
  "properties": {
    "iso:country":"GB",
    "sg:address":"4 Broomlands Street",
    "sg:city":"Paisley",
    "sg:classifiers":[
        {
            "category":"Building & Trades",
            "subcategory":"Cleaning & Sanitation",
            "type":"Services"
        },
        {
            "category":"Professional",
            "subcategory":"Business Services",
            "type":"Services"
        }
    ],
    "sg:phone":"+44 141 848 7535",
    "sg:postcode":"PA1 2LR",
    "sg:province":"Renfrewshire",
    "sg:tags":[
        "shop",
        "commercial",
        "premise"
    ],
    "wof:name":"Carlyle Cleaning Services",
    "wof:placetype":"venue"
},
  "geometry": {"coordinates":[-4.437848,55.844246],"type":"Point"}
}