{
  "type": "Feature",
  "properties": {
    "addr:full":"North Road Darlington Durham DL1 2EQ",
    "addr:postcode":"dl1 2eq",
    "addr:street":"North Road",
    "iso:country":"GB",
    "sg:address":"North Road",
    "sg:city":"Darlington",
    "sg:classifiers":[
        {
            "category":"Shopping",
            "subcategory":"Clothing, Apparel, & Fashions",
            "type":"Retail Goods"
        }
    ],
    "sg:phone":"+44 1325 361018",
    "sg:postcode":"DL1 2EQ",
    "sg:province":"Durham",
    "sg:tags":[
        "ladieswear"
    ],
    "wof:name":"Transforming You Transvestite Clothing",
    "wof:placetype":"venue"
},
  "geometry": {"coordinates":[-1.547779,54.545841],"type":"Point"}
}