{
  "type": "Feature",
  "properties": {
    "iso:country":"GB",
    "sg:address":"7 Holmwood Rd",
    "sg:city":"Ilford",
    "sg:classifiers":[
        {
            "category":"Building & Trades",
            "subcategory":"Construction",
            "type":"Services"
        }
    ],
    "sg:phone":"+44 20 8220 2367",
    "sg:postcode":"IG3 9XY",
    "sg:province":"Essex",
    "sg:tags":[
        "decorator",
        "painter"
    ],
    "wof:name":"A D Jines & Sons",
    "wof:placetype":"venue"
},
  "geometry": {"coordinates":[0.09635,51.560032],"type":"Point"}
}