{
  "type": "Feature",
  "properties": {
    "iso:country":"GB",
    "sg:address":"Unit 3 10 Theed St",
    "sg:city":"Southwark",
    "sg:classifiers":[
        {
            "category":"Professional",
            "subcategory":"Computer Services",
            "type":"Services"
        }
    ],
    "sg:phone":"+44 20 7928 6200",
    "sg:postcode":"SE1 8ST",
    "sg:province":"Greater London",
    "sg:tags":[
        "information"
    ],
    "wof:name":"Association Of International Marathons,The",
    "wof:placetype":"venue"
},
  "geometry": {"coordinates":[-0.109143,51.505066],"type":"Point"}
}