{
  "type": "Feature",
  "properties": {
    "addr:full":"Sturtridge Pavilion, Franklin`s Gardens, Weedon Road Northampton Northamptonshire NN5 5BG",
    "addr:postcode":"nn5 5bg",
    "addr:street":"Weedon Road",
    "iso:country":"GB",
    "sg:address":"Sturtridge Pavilion, Franklin`s Gardens, Weedon Road",
    "sg:city":"Northampton",
    "sg:classifiers":[
        {
            "category":"Arena",
            "subcategory":"Sports Club",
            "type":"Entertainment"
        }
    ],
    "sg:phone":"+44 1604 751543",
    "sg:postcode":"NN5 5BG",
    "sg:province":"Northamptonshire",
    "wof:name":"Northampton Rugby Football Club Ltd.",
    "wof:placetype":"venue"
},
  "geometry": {"coordinates":[-0.91923,52.240849],"type":"Point"}
}