{
  "type": "Feature",
  "properties": {
    "addr:full":"52 Station Lane, Seaton Carew Hartlepool Durham TS25 1BG",
    "addr:housenumber":"52",
    "addr:postcode":"ts25 1bg",
    "addr:street":"Station Lane",
    "iso:country":"GB",
    "sg:address":"52 Station Lane, Seaton Carew",
    "sg:city":"Hartlepool",
    "sg:classifiers":[
        {
            "category":"Building & Trades",
            "subcategory":"Construction",
            "type":"Services"
        }
    ],
    "sg:phone":"+44 1429 274197",
    "sg:postcode":"TS25 1BG",
    "sg:province":"Durham",
    "sg:tags":[
        "builder"
    ],
    "wof:name":"G W Morter & Son",
    "wof:placetype":"venue"
},
  "geometry": {"coordinates":[-1.1933380365,54.6609115601],"type":"Point"}
}