{
  "type": "Feature",
  "properties": {
    "addr:full":"43 Gladstone Street, Long Eaton Nottingham Derbyshire NG10 1DG",
    "addr:housenumber":"43",
    "addr:postcode":"ng10 1dg",
    "addr:street":"Gladstone Street",
    "iso:country":"GB",
    "sg:address":"43 Gladstone Street, Long Eaton",
    "sg:city":"Nottingham",
    "sg:classifiers":[
        {
            "category":"Building & Trades",
            "subcategory":"Construction",
            "type":"Services"
        }
    ],
    "sg:phone":"+44 1332 872725",
    "sg:postcode":"NG10 1DG",
    "sg:province":"Derbyshire",
    "sg:tags":[
        "builder"
    ],
    "wof:name":"J C Joinery Building Contractors",
    "wof:placetype":"venue"
},
  "geometry": {"coordinates":[-1.277149,52.892059],"type":"Point"}
}