{
  "type": "Feature",
  "properties": {
    "iso:country":"GB",
    "sg:address":"5-6 Old Market Pl",
    "sg:city":"Grimsby",
    "sg:classifiers":[
        {
            "category":"Bars & Pubs",
            "type":"Food & Drink"
        }
    ],
    "sg:phone":"+44 1472 246901",
    "sg:postcode":"DN31 1DT",
    "sg:province":"Lincolnshire",
    "sg:tags":[
        "pubs",
        "inn"
    ],
    "wof:name":"Pestle & Mortar",
    "wof:placetype":"venue"
},
  "geometry": {"coordinates":[-0.087994,53.564465],"type":"Point"}
}