{
  "type": "Feature",
  "properties": {
    "addr:full":"Strickland Tenement, Crosthwaite Kendal Cumbria LA8 8BU",
    "addr:postcode":"la8 8bu",
    "addr:street":"Crosthwaite Kendal",
    "iso:country":"GB",
    "sg:address":"Strickland Tenement, Crosthwaite",
    "sg:city":"Kendal",
    "sg:classifiers":[
        {
            "category":"Retail",
            "subcategory":"Animal Services",
            "type":"Services"
        }
    ],
    "sg:postcode":"LA8 8BU",
    "sg:province":"Cumbria",
    "sg:tags":[
        "carrier",
        "transportation"
    ],
    "wof:name":"R H Walling",
    "wof:placetype":"venue"
},
  "geometry": {"coordinates":[-2.85748,54.314781],"type":"Point"}
}