{
  "type": "Feature",
  "properties": {
    "addr:full":"34 Thicket Rd Penge Greater London SE20 8DD",
    "addr:housenumber":"34",
    "addr:postcode":"se20 8dd",
    "addr:street":"Thicket Rd",
    "iso:country":"GB",
    "sg:address":"34 Thicket Rd",
    "sg:city":"Penge",
    "sg:classifiers":[
        {
            "category":"Building & Trades",
            "subcategory":"Construction",
            "type":"Services"
        }
    ],
    "sg:phone":"+44 20 8659 1704",
    "sg:postcode":"SE20 8DD",
    "sg:province":"Greater London",
    "sg:tags":[
        "joiner",
        "carpenter"
    ],
    "wof:name":"Woodlatch Carpentry",
    "wof:placetype":"venue"
},
  "geometry": {"coordinates":[-0.0672620013,51.4162216187],"type":"Point"}
}