{
  "type": "Feature",
  "properties": {
    "addr:full":"Broomfields, Welbury Northallerton North Yorkshire DL6 2SB",
    "addr:postcode":"dl6 2sb",
    "iso:country":"GB",
    "sg:address":"Broomfields, Welbury",
    "sg:city":"Northallerton",
    "sg:classifiers":[
        {
            "category":"Freight",
            "type":"Transportation"
        }
    ],
    "sg:postcode":"DL6 2SB",
    "sg:province":"North Yorkshire",
    "sg:tags":[
        "haulage",
        "road"
    ],
    "wof:name":"D W & A Stainthorpe",
    "wof:placetype":"venue"
},
  "geometry": {"coordinates":[-1.3886630535,54.4155311584],"type":"Point"}
}