{
  "type": "Feature",
  "properties": {
    "addr:full":"Unit 11 Groveley Road Christchurch Dorset BH23 3HB",
    "addr:housenumber":"unit 11",
    "addr:postcode":"bh23 3hb",
    "addr:street":"Groveley Road",
    "iso:country":"GB",
    "sg:address":"Unit 11 Groveley Road",
    "sg:city":"Christchurch",
    "sg:classifiers":[
        {
            "category":"Professional",
            "subcategory":"Printing & Photocopies",
            "type":"Services"
        }
    ],
    "sg:postcode":"BH23 3HB",
    "sg:province":"Dorset",
    "sg:tags":[
        "printer"
    ],
    "wof:name":"Impress Print & Design",
    "wof:placetype":"venue"
},
  "geometry": {"coordinates":[-1.7577940226,50.735824585],"type":"Point"}
}