{
  "type": "Feature",
  "properties": {
    "addr:full":"213 High Rd Benfleet Essex SS7 5HZ",
    "addr:housenumber":"213",
    "addr:postcode":"ss7 5hz",
    "addr:street":"High Rd",
    "iso:country":"GB",
    "sg:address":"213 High Rd",
    "sg:city":"Benfleet",
    "sg:classifiers":[
        {
            "category":"Shopping",
            "subcategory":"Thrift Store",
            "type":"Retail Goods"
        }
    ],
    "sg:phone":"+44 1268 756344",
    "sg:postcode":"SS7 5HZ",
    "sg:province":"Essex",
    "sg:tags":[
        "shop",
        "charity"
    ],
    "wof:name":"RSPCA",
    "wof:placetype":"venue"
},
  "geometry": {"coordinates":[0.561215,51.552731],"type":"Point"}
}