{
  "type": "Feature",
  "properties": {
    "iso:country":"GB",
    "sg:address":"1 Newbiggin Road, North Seaton",
    "sg:city":"Ashington",
    "sg:classifiers":[
        {
            "category":"Manufacturing",
            "subcategory":"Petroleum Products",
            "type":"Manufacturing & Wholesale Goods"
        },
        {
            "category":"Building & Trades",
            "subcategory":"Construction",
            "type":"Services"
        }
    ],
    "sg:phone":"+44 1670 813385",
    "sg:postcode":"NE63 0TB",
    "sg:province":"Northumberland",
    "sg:tags":[
        "double",
        "glazing",
        "installers"
    ],
    "wof:name":"Whites of Ashington",
    "wof:placetype":"venue"
},
  "geometry": {"coordinates":[-1.565351,55.168629],"type":"Point"}
}