{
  "type": "Feature",
  "properties": {
    "iso:country":"GB",
    "sg:address":"Unit 122 West Block, Westminster Business Square, Durham Street",
    "sg:city":"London",
    "sg:classifiers":[
        {
            "category":"Retail",
            "subcategory":"Photofinishing",
            "type":"Services"
        }
    ],
    "sg:phone":"+44 20 7793 1110",
    "sg:postcode":"SE11 5JH",
    "sg:province":"Greater London",
    "sg:tags":[
        "photographic",
        "processor"
    ],
    "wof:name":"Lynn Driscoll Colour Processing",
    "wof:placetype":"venue"
},
  "geometry": {"coordinates":[-0.11837,51.485931],"type":"Point"}
}