{
  "type": "Feature",
  "properties": {
    "iso:country":"GB",
    "sg:address":"34 G & H Aston Road",
    "sg:city":"Waterlooville",
    "sg:classifiers":[
        {
            "category":"Manufacturing",
            "subcategory":"Printing",
            "type":"Manufacturing & Wholesale Goods"
        },
        {
            "category":"Building & Trades",
            "subcategory":"Plumbing",
            "type":"Services"
        }
    ],
    "sg:phone":"+44 23 9226 5031",
    "sg:postcode":"PO7 7XQ",
    "sg:province":"Hampshire",
    "sg:tags":[
        "joint",
        "seal",
        "manufacturer"
    ],
    "sg:website":"http://www.flowseal.co.uk",
    "wof:name":"Flowseal Ltd",
    "wof:placetype":"venue"
},
  "geometry": {"coordinates":[-1.03654,50.88633],"type":"Point"}
}