{
  "type": "Feature",
  "properties": {
    "addr:full":"Brentwood, Marton Road, Birdingbury Rugby Northamptonshire CV23 8EH",
    "addr:postcode":"cv23 8eh",
    "addr:street":"Marton Road",
    "iso:country":"GB",
    "sg:address":"Brentwood, Marton Road, Birdingbury",
    "sg:city":"Rugby",
    "sg:classifiers":[
        {
            "category":"Retail",
            "subcategory":"Auto Rental",
            "type":"Services"
        }
    ],
    "sg:phone":"+44 1926 633000",
    "sg:postcode":"CV23 8EH",
    "sg:province":"Northamptonshire",
    "sg:tags":[
        "car",
        "hire",
        "truck"
    ],
    "wof:name":"Vixen",
    "wof:placetype":"venue"
},
  "geometry": {"coordinates":[-1.368104,52.311649],"type":"Point"}
}