{
  "type": "Feature",
  "properties": {
    "addr:full":"Woodlands Road, Thornliebank Glasgow East Renfrewshire G46 7SU",
    "addr:postcode":"g46 7su",
    "addr:street":"Woodlands Road",
    "iso:country":"GB",
    "sg:address":"Woodlands Road, Thornliebank",
    "sg:city":"Glasgow",
    "sg:classifiers":[
        {
            "category":"Travel",
            "subcategory":"Hostel",
            "type":"Entertainment"
        },
        {
            "category":"Government",
            "subcategory":"Office",
            "type":"Public Place"
        }
    ],
    "sg:phone":"+44 141 638 6572",
    "sg:postcode":"G46 7SU",
    "sg:province":"East Renfrewshire",
    "sg:tags":[
        "local"
    ],
    "wof:name":"Atholl House",
    "wof:placetype":"venue"
},
  "geometry": {"coordinates":[-4.3099741936,55.8068008423],"type":"Point"}
}