{
  "type": "Feature",
  "properties": {
    "addr:full":"Kenyon Road, Standish Wigan Lancashire WN6 0NX",
    "addr:postcode":"wn6 0nx",
    "addr:street":"Kenyon Road",
    "iso:country":"GB",
    "sg:address":"Kenyon Road, Standish",
    "sg:city":"Wigan",
    "sg:classifiers":[
        {
            "category":"Education",
            "subcategory":"School",
            "type":"Public Place"
        }
    ],
    "sg:phone":"+44 1257 422265",
    "sg:postcode":"WN6 0NX",
    "sg:province":"Lancashire",
    "sg:tags":[
        "local",
        "authority"
    ],
    "wof:name":"Standish Communicty High School",
    "wof:placetype":"venue"
},
  "geometry": {"coordinates":[-2.6734259129,53.593006134],"type":"Point"}
}