{
  "type": "Feature",
  "properties": {
    "addr:full":"75a High Street Dunmow Essex CM6 1AE",
    "addr:housenumber":"75a",
    "addr:postcode":"cm6 1ae",
    "addr:street":"High Street",
    "iso:country":"GB",
    "sg:address":"75a High Street",
    "sg:city":"Dunmow",
    "sg:classifiers":[
        {
            "category":"Health Services",
            "subcategory":"Podiatrist",
            "type":"Services"
        }
    ],
    "sg:phone":"+44 1371 872332",
    "sg:postcode":"CM6 1AE",
    "sg:province":"Essex",
    "sg:tags":[
        "podiatrists",
        "chiropodist"
    ],
    "wof:name":"David Culverhouse",
    "wof:placetype":"venue"
},
  "geometry": {"coordinates":[0.365632,51.870373],"type":"Point"}
}