{
  "type": "Feature",
  "properties": {
    "addr:full":"44 North Road, Ponteland Newcastle-upon-tyne Northumberland NE20 9UR",
    "addr:housenumber":"44",
    "addr:postcode":"ne20 9ur",
    "addr:street":"North Road",
    "iso:country":"GB",
    "sg:address":"44 North Road, Ponteland",
    "sg:city":"Newcastle-upon-tyne",
    "sg:classifiers":[
        {
            "category":"Shopping",
            "subcategory":"Books",
            "type":"Retail Goods"
        },
        {
            "category":"Wholesale",
            "subcategory":"Books, Periodicals, & Newspapers",
            "type":"Manufacturing & Wholesale Goods"
        }
    ],
    "sg:phone":"+44 1661 822316",
    "sg:postcode":"NE20 9UR",
    "sg:province":"Northumberland",
    "sg:tags":[
        "publisher"
    ],
    "wof:name":"Stass Publications",
    "wof:placetype":"venue"
},
  "geometry": {"coordinates":[-1.7438850403,55.0560340881],"type":"Point"}
}