{
  "type": "Feature",
  "properties": {
    "iso:country":"GB",
    "sg:address":"Hanovia House, 28-29 Eastman Rd",
    "sg:city":"Acton",
    "sg:classifiers":[
        {
            "category":"Social Services",
            "subcategory":"Job Training",
            "type":"Services"
        }
    ],
    "sg:phone":"+44 20 8743 4232",
    "sg:postcode":"W3 7YG",
    "sg:province":"Greater London",
    "sg:tags":[
        "translator",
        "interpreter"
    ],
    "wof:name":"A Harb Arabic Translations",
    "wof:placetype":"venue"
},
  "geometry": {"coordinates":[-0.260188,51.505493],"type":"Point"}
}