{
  "type": "Feature",
  "properties": {
    "addr:full":"The Willows Monmouth Gloucestershire NP25 4JP",
    "addr:postcode":"np25 4jp",
    "iso:country":"GB",
    "sg:address":"The Willows",
    "sg:city":"Monmouth",
    "sg:classifiers":[
        {
            "category":"Building & Trades",
            "subcategory":"Plumbing",
            "type":"Services"
        }
    ],
    "sg:postcode":"NP25 4JP",
    "sg:province":"Gloucestershire",
    "sg:tags":[
        "heating"
    ],
    "wof:name":"Gerald Payne Heating",
    "wof:placetype":"venue"
},
  "geometry": {"coordinates":[-2.7124109268,51.8207855225],"type":"Point"}
}