{
  "type": "Feature",
  "properties": {
    "iso:country":"GB",
    "sg:address":"Unit 6b Park Lane Trading Estate, Park Lane",
    "sg:city":"Corsham",
    "sg:classifiers":[
        {
            "category":"Professional",
            "subcategory":"Engineering",
            "type":"Services"
        }
    ],
    "sg:postcode":"SN13 9LG",
    "sg:province":"Wiltshire",
    "sg:tags":[
        "precision",
        "engineer"
    ],
    "wof:name":"Payne Engineering Developments",
    "wof:placetype":"venue"
},
  "geometry": {"coordinates":[-2.2015450001,51.4331512451],"type":"Point"}
}