{
  "type": "Feature",
  "properties": {
    "addr:full":"236 South Street Romford Essex RM1 2AD",
    "addr:housenumber":"236",
    "addr:postcode":"rm1 2ad",
    "addr:street":"South Street",
    "iso:country":"GB",
    "sg:address":"236 South Street",
    "sg:city":"Romford",
    "sg:classifiers":[
        {
            "category":"Building & Trades",
            "subcategory":"Construction",
            "type":"Services"
        }
    ],
    "sg:phone":"+44 1708 741595",
    "sg:postcode":"RM1 2AD",
    "sg:province":"Essex",
    "sg:tags":[
        "builder"
    ],
    "wof:name":"R J Carter",
    "wof:placetype":"venue"
},
  "geometry": {"coordinates":[0.1846559942,51.5712242126],"type":"Point"}
}