{
  "type": "Feature",
  "properties": {
    "addr:full":"74-78 The Broadway London Greater London SW19 1RQ",
    "addr:housenumber":"74-78",
    "addr:postcode":"sw19 1rq",
    "addr:street":"The Broadway",
    "iso:country":"GB",
    "sg:address":"74-78 The Broadway",
    "sg:city":"London",
    "sg:classifiers":[
        {
            "category":"Bars & Pubs",
            "type":"Food & Drink"
        }
    ],
    "sg:phone":"+44 20 8543 8624",
    "sg:postcode":"SW19 1RQ",
    "sg:province":"Greater London",
    "sg:tags":[
        "pubs",
        "inn"
    ],
    "wof:name":"Chumleys",
    "wof:placetype":"venue"
},
  "geometry": {"coordinates":[-0.202195,51.419716],"type":"Point"}
}