{
  "type": "Feature",
  "properties": {
    "addr:full":"Cost Cutters Supermarket, Ivy Cross Shaftesbury Dorset SP7 8DS",
    "addr:housenumber":"supermarket",
    "addr:postcode":"sp7 8ds",
    "addr:street":"Ivy Cross",
    "iso:country":"GB",
    "sg:address":"Cost Cutters Supermarket, Ivy Cross",
    "sg:city":"Shaftesbury",
    "sg:classifiers":[
        {
            "category":"Cinema",
            "subcategory":"Movie Rental",
            "type":"Entertainment"
        }
    ],
    "sg:phone":"+44 1747 855666",
    "sg:postcode":"SP7 8DS",
    "sg:province":"Dorset",
    "sg:tags":[
        "video",
        "library"
    ],
    "wof:name":"Top Tips Video",
    "wof:placetype":"venue"
},
  "geometry": {"coordinates":[-2.1871240139,51.0057640076],"type":"Point"}
}