{
  "type": "Feature",
  "properties": {
    "addr:full":"East Witheridge, Penn Rd Beaconsfield Buckinghamshire HP9 2TW",
    "addr:postcode":"hp9 2tw",
    "addr:street":"East;Penn Rd",
    "iso:country":"GB",
    "sg:address":"East Witheridge, Penn Rd",
    "sg:city":"Beaconsfield",
    "sg:classifiers":[
        {
            "category":"Real Estate",
            "subcategory":"Surveying",
            "type":"Services"
        }
    ],
    "sg:phone":"+44 1494 676913",
    "sg:postcode":"HP9 2TW",
    "sg:province":"Buckinghamshire",
    "sg:tags":[
        "building",
        "surveyor"
    ],
    "wof:name":"Alan Oliver",
    "wof:placetype":"venue"
},
  "geometry": {"coordinates":[-0.647023,51.61187],"type":"Point"}
}