{
  "type": "Feature",
  "properties": {
    "iso:country":"GB",
    "sg:address":"85 Eastwoodmains Road, Clarkston",
    "sg:city":"Glasgow",
    "sg:classifiers":[
        {
            "category":"Organizations",
            "subcategory":"Non-profit Organization",
            "type":"Services"
        }
    ],
    "sg:phone":"+44 141 621 2121",
    "sg:postcode":"G76 7HG",
    "sg:province":"East Renfrewshire",
    "sg:tags":[
        "charitable",
        "organisation",
        "voluntary",
        "charity"
    ],
    "wof:name":"Radio Amateurs' Emergency Network",
    "wof:placetype":"venue"
},
  "geometry": {"coordinates":[-4.2835597992,55.7927398682],"type":"Point"}
}