{
  "type": "Feature",
  "properties": {
    "addr:full":"West Benhar Rd Shotts North Lanarkshire ML7 5PG",
    "addr:postcode":"ml7 5pg",
    "addr:street":"West Benhar Rd",
    "iso:country":"GB",
    "sg:address":"West Benhar Rd",
    "sg:city":"Shotts",
    "sg:classifiers":[
        {
            "category":"Government",
            "subcategory":"Office",
            "type":"Public Place"
        }
    ],
    "sg:phone":"+44 1501 751044",
    "sg:postcode":"ML7 5PG",
    "sg:province":"North Lanarkshire",
    "sg:tags":[
        "project",
        "gov",
        "community"
    ],
    "wof:name":"Eastfield Community Action Group",
    "wof:placetype":"venue"
},
  "geometry": {"coordinates":[-3.770989,55.853886],"type":"Point"}
}