{
  "type": "Feature",
  "properties": {
    "iso:country":"GB",
    "sg:address":"490 Blandford Road, Hamworthy",
    "sg:city":"Poole",
    "sg:classifiers":[
        {
            "category":"Retail",
            "subcategory":"Auto Repair",
            "type":"Services"
        }
    ],
    "sg:phone":"+44 1202 623636",
    "sg:postcode":"BH16 5BN",
    "sg:province":"Dorset",
    "sg:tags":[
        "modification",
        "garage"
    ],
    "wof:name":"Wyatt Citroen",
    "wof:placetype":"venue"
},
  "geometry": {"coordinates":[-2.019938,50.729752],"type":"Point"}
}