{
  "type": "Feature",
  "properties": {
    "addr:full":"123 King Street, Hammersmith London Greater London W6 9JG",
    "addr:housenumber":"123",
    "addr:postcode":"w6 9jg",
    "addr:street":"King Street",
    "iso:country":"GB",
    "sg:address":"123 King Street, Hammersmith",
    "sg:city":"London",
    "sg:classifiers":[
        {
            "category":"Education",
            "subcategory":"Special Training",
            "type":"Public Place"
        }
    ],
    "sg:phone":"+44 20 8563 0850",
    "sg:postcode":"W6 9JG",
    "sg:province":"Greater London",
    "sg:tags":[
        "product",
        "centre"
    ],
    "wof:name":"Arab Women Group (Uk) Ltd.",
    "wof:placetype":"venue"
},
  "geometry": {"coordinates":[-0.2302239984,51.4924430847],"type":"Point"}
}