{
  "type": "Feature",
  "properties": {
    "iso:country":"GB",
    "sg:address":"55 Oxford Rd",
    "sg:city":"Altrincham",
    "sg:classifiers":[
        {
            "category":"Professional",
            "subcategory":"Management & Consulting",
            "type":"Services"
        }
    ],
    "sg:phone":"+44 161 929 6302",
    "sg:postcode":"WA14 2ED",
    "sg:province":"Cheshire",
    "sg:tags":[
        "marketing",
        "consultant"
    ],
    "wof:name":"B Direct",
    "wof:placetype":"venue"
},
  "geometry": {"coordinates":[-2.350382,53.382378],"type":"Point"}
}