{
  "type": "Feature",
  "properties": {
    "addr:full":"54 Damson Lane Solihull West Midlands B91 2RF",
    "addr:housenumber":"54",
    "addr:postcode":"b91 2rf",
    "addr:street":"Damson Lane",
    "iso:country":"GB",
    "sg:address":"54 Damson Lane",
    "sg:city":"Solihull",
    "sg:classifiers":[
        {
            "category":"Food & Beverages",
            "subcategory":"Groceries & Convenience Stores",
            "type":"Retail Goods"
        }
    ],
    "sg:phone":"+44 121 705 2978",
    "sg:postcode":"B91 2RF",
    "sg:province":"West Midlands",
    "wof:name":"Dillons",
    "wof:placetype":"venue"
},
  "geometry": {"coordinates":[-1.7652449608,52.4242973328],"type":"Point"}
}