{
  "type": "Feature",
  "properties": {
    "iso:country":"GB",
    "sg:address":"Unit 4 Great Honeyborough, Neyland",
    "sg:city":"Milford Haven",
    "sg:classifiers":[
        {
            "category":"Manufacturing",
            "subcategory":"Buildings",
            "type":"Manufacturing & Wholesale Goods"
        }
    ],
    "sg:phone":"+44 1646 600724",
    "sg:postcode":"SA73 1SE",
    "sg:province":"Pembrokeshire",
    "sg:tags":[
        "framed",
        "timber"
    ],
    "wof:name":"Firwood Homes Ltd.",
    "wof:placetype":"venue"
},
  "geometry": {"coordinates":[-4.949875,51.709881],"type":"Point"}
}