{
  "type": "Feature",
  "properties": {
    "addr:full":"4 Belvoir Close, Market Deeping Peterborough Cambridgeshire PE6 8SS",
    "addr:housenumber":"4",
    "addr:postcode":"pe6 8ss",
    "addr:street":"Belvoir Close Market Deeping Peterborough",
    "iso:country":"GB",
    "sg:address":"4 Belvoir Close, Market Deeping",
    "sg:city":"Peterborough",
    "sg:classifiers":[
        {
            "category":"Banks & Credit Unions",
            "subcategory":"Bank",
            "type":"Services"
        }
    ],
    "sg:postcode":"PE6 8SS",
    "sg:province":"Cambridgeshire",
    "sg:tags":[
        "broker",
        "mortgage"
    ],
    "wof:name":"Belvoir Financial",
    "wof:placetype":"venue"
},
  "geometry": {"coordinates":[-0.3293780088,52.6800117493],"type":"Point"}
}