{
  "type": "Feature",
  "properties": {
    "addr:full":"51 Methuen Rd Edgware Greater London HA8 6EU",
    "addr:housenumber":"51",
    "addr:postcode":"ha8 6eu",
    "addr:street":"Methuen Rd",
    "iso:country":"GB",
    "sg:address":"51 Methuen Rd",
    "sg:city":"Edgware",
    "sg:classifiers":[
        {
            "category":"Professional",
            "subcategory":"Research",
            "type":"Services"
        }
    ],
    "sg:phone":"+44 20 8952 8752",
    "sg:postcode":"HA8 6EU",
    "sg:province":"Greater London",
    "sg:tags":[
        "market"
    ],
    "wof:name":"Lozowick Market Research",
    "wof:placetype":"venue"
},
  "geometry": {"coordinates":[-0.280633,51.606407],"type":"Point"}
}