{
  "type": "Feature",
  "properties": {
    "iso:country":"GB",
    "sg:address":"3 Victoria Rd",
    "sg:city":"Lytham St. Annes",
    "sg:classifiers":[
        {
            "category":"Food & Beverages",
            "subcategory":"Specialty",
            "type":"Retail Goods"
        }
    ],
    "sg:phone":"+44 1253 721001",
    "sg:postcode":"FY8 1LE",
    "sg:province":"Lancashire",
    "sg:tags":[
        "product",
        "health"
    ],
    "wof:name":"MSM National Helpline",
    "wof:placetype":"venue"
},
  "geometry": {"coordinates":[-3.023389,53.747204],"type":"Point"}
}