{
  "type": "Feature",
  "properties": {
    "addr:full":"Cross St Lynton Devon EX35 6HG",
    "addr:postcode":"ex35 6hg",
    "addr:street":"Cross St",
    "iso:country":"GB",
    "sg:address":"Cross St",
    "sg:city":"Lynton",
    "sg:classifiers":[
        {
            "category":"Building & Trades",
            "subcategory":"Cleaning & Sanitation",
            "type":"Services"
        }
    ],
    "sg:phone":"+44 1598 752363",
    "sg:postcode":"EX35 6HG",
    "sg:province":"Devon",
    "sg:tags":[
        "blast"
    ],
    "wof:name":"Atticus Abrasive Blasting",
    "wof:placetype":"venue"
},
  "geometry": {"coordinates":[-3.8362441063,51.2295188904],"type":"Point"}
}