{
  "type": "Feature",
  "properties": {
    "iso:country":"GB",
    "sg:address":"Fox's Lane, Five Ways",
    "sg:city":"Wolverhampton",
    "sg:classifiers":[
        {
            "category":"Shopping",
            "type":"Retail Goods"
        }
    ],
    "sg:phone":"+44 1902 423091",
    "sg:postcode":"WV1 1PB",
    "sg:province":"West Midlands",
    "sg:tags":[
        "part",
        "accessory"
    ],
    "wof:name":"Halfords Garage Servicing",
    "wof:placetype":"venue"
},
  "geometry": {"coordinates":[-2.1281,52.596409],"type":"Point"}
}