{
  "type": "Feature",
  "properties": {
    "addr:full":"68 Percy Road, Stourvale York East Riding of Yorkshire YO42 2LX",
    "addr:housenumber":"68",
    "addr:postcode":"yo42 2lx",
    "addr:street":"Percy Road",
    "iso:country":"GB",
    "sg:address":"68 Percy Road, Stourvale",
    "sg:city":"York",
    "sg:classifiers":[
        {
            "category":"Building & Trades",
            "subcategory":"Plumbing",
            "type":"Services"
        }
    ],
    "sg:postcode":"YO42 2LX",
    "sg:province":"East Riding of Yorkshire",
    "sg:tags":[
        "heating"
    ],
    "wof:name":"Steve Johnson Plumbing & Heating",
    "wof:placetype":"venue"
},
  "geometry": {"coordinates":[-0.771148026,53.9327392578],"type":"Point"}
}