{
  "type": "Feature",
  "properties": {
    "addr:full":"Giblet Farm, Heol Las, Coity Bridgend Bridgend CF35 6BS",
    "addr:postcode":"cf35 6bs",
    "addr:street":"Heol Las Coity",
    "iso:country":"GB",
    "sg:address":"Giblet Farm, Heol Las, Coity",
    "sg:city":"Bridgend",
    "sg:classifiers":[
        {
            "category":"Farming",
            "subcategory":"Livestock Farm",
            "type":"Manufacturing & Wholesale Goods"
        }
    ],
    "sg:phone":"+44 1656 652558",
    "sg:postcode":"CF35 6BS",
    "sg:province":"Bridgend",
    "sg:tags":[
        "others"
    ],
    "wof:name":"G.H Williams",
    "wof:placetype":"venue"
},
  "geometry": {"coordinates":[-3.5545639992,51.5218086243],"type":"Point"}
}