{
  "type": "Feature",
  "properties": {
    "iso:country":"GB",
    "sg:address":"Shurdington",
    "sg:city":"Cheltenham",
    "sg:classifiers":[
        {
            "category":"Travel",
            "subcategory":"Hotels & Motels",
            "type":"Entertainment"
        }
    ],
    "sg:phone":"+44 1242 862352",
    "sg:postcode":"GL51 4UG",
    "sg:province":"Gloucestershire",
    "wof:name":"Greenway Hotel",
    "wof:placetype":"venue"
},
  "geometry": {"coordinates":[-2.1178,51.858879],"type":"Point"}
}