{
  "type": "Feature",
  "properties": {
    "addr:full":"8 East Towers Pinner Greater London HA5 1TL",
    "addr:housenumber":"8",
    "addr:postcode":"ha5 1tl",
    "addr:street":"East Towers",
    "iso:country":"GB",
    "sg:address":"8 East Towers",
    "sg:city":"Pinner",
    "sg:classifiers":[
        {
            "category":"Shopping",
            "subcategory":"Clothing, Apparel, & Fashions",
            "type":"Retail Goods"
        },
        {
            "category":"Banks & Credit Unions",
            "subcategory":"Investment Brokerage",
            "type":"Services"
        }
    ],
    "sg:phone":"+44 20 8868 2018",
    "sg:postcode":"HA5 1TL",
    "sg:province":"Greater London",
    "sg:tags":[
        "hire",
        "dresswear"
    ],
    "wof:name":"Butterfly Ball Designer Wear",
    "wof:placetype":"venue"
},
  "geometry": {"coordinates":[-0.3888779879,51.5848731995],"type":"Point"}
}