{
  "type": "Feature",
  "properties": {
    "addr:full":"3 Newbury Street Wantage Berkshire OX12 8BX",
    "addr:housenumber":"3",
    "addr:postcode":"ox12 8bx",
    "addr:street":"Newbury Street",
    "iso:country":"GB",
    "sg:address":"3 Newbury Street",
    "sg:city":"Wantage",
    "sg:classifiers":[
        {
            "category":"Banks & Credit Unions",
            "subcategory":"Bank",
            "type":"Services"
        }
    ],
    "sg:phone":"+44 845 604 1604",
    "sg:postcode":"OX12 8BX",
    "sg:province":"Berkshire",
    "wof:name":"National Westminster Bank Plc",
    "wof:placetype":"venue"
},
  "geometry": {"coordinates":[-1.4256210327,51.5881233215],"type":"Point"}
}