{
  "type": "Feature",
  "properties": {
    "addr:full":"3 St. Elizabeth Walk, Woodham Village Newton Aycliffe Durham DL5 4TJ",
    "addr:housenumber":"3",
    "addr:postcode":"dl5 4tj",
    "addr:street":"St. Elizabeth Walk",
    "iso:country":"GB",
    "sg:address":"3 St. Elizabeth Walk, Woodham Village",
    "sg:city":"Newton Aycliffe",
    "sg:classifiers":[
        {
            "category":"Personal",
            "subcategory":"Beauty Salon",
            "type":"Services"
        }
    ],
    "sg:phone":"+44 1325 310357",
    "sg:postcode":"DL5 4TJ",
    "sg:province":"Durham",
    "sg:tags":[
        "unisex",
        "hairdresser"
    ],
    "wof:name":"Hers & Sirs",
    "wof:placetype":"venue"
},
  "geometry": {"coordinates":[-1.5663820505,54.6339645386],"type":"Point"}
}