{
  "type": "Feature",
  "properties": {
    "addr:full":"Swift Lane Bagshot Berkshire GU19 5NJ",
    "addr:postcode":"gu19 5nj",
    "addr:street":"Swift Lane",
    "iso:country":"GB",
    "sg:address":"Swift Lane",
    "sg:city":"Bagshot",
    "sg:classifiers":[
        {
            "category":"Utilities",
            "subcategory":"Refuse",
            "type":"Services"
        },
        {
            "category":"Government",
            "subcategory":"Office",
            "type":"Public Place"
        }
    ],
    "sg:phone":"+44 1276 474470",
    "sg:postcode":"GU19 5NJ",
    "sg:province":"Berkshire",
    "sg:tags":[
        "disposal",
        "waste",
        "local"
    ],
    "wof:name":"Swift Lane Waste Amenity Site",
    "wof:placetype":"venue"
},
  "geometry": {"coordinates":[-0.6846690178,51.3598098755],"type":"Point"}
}