{
  "type": "Feature",
  "properties": {
    "iso:country":"GB",
    "sg:address":"351 Goldington Rd",
    "sg:city":"Bedford",
    "sg:classifiers":[
        {
            "category":"Building & Trades",
            "subcategory":"Construction",
            "type":"Services"
        }
    ],
    "sg:phone":"+44 1234 359595",
    "sg:postcode":"MK41 9NX",
    "sg:province":"Bedfordshire",
    "sg:tags":[
        "builder"
    ],
    "wof:name":"Polycote UK",
    "wof:placetype":"venue"
},
  "geometry": {"coordinates":[-0.431088,52.142448],"type":"Point"}
}