{
  "type": "Feature",
  "properties": {
    "iso:country":"GB",
    "sg:address":"Glasgow Road, Hardgate",
    "sg:city":"Clydebank",
    "sg:classifiers":[
        {
            "category":"Bars & Pubs",
            "type":"Food & Drink"
        },
        {
            "category":"Community Center",
            "subcategory":"Social",
            "type":"Public Place"
        }
    ],
    "sg:phone":"+44 1389 873287",
    "sg:postcode":"G81 6AX",
    "sg:province":"East Dunbartonshire",
    "sg:tags":[
        "pubs",
        "house",
        "inn",
        "activity"
    ],
    "wof:name":"THE GOLDENHILL",
    "wof:placetype":"venue"
},
  "geometry": {"coordinates":[-4.405809,55.925076],"type":"Point"}
}