{
  "type": "Feature",
  "properties": {
    "addr:full":"Trafalagar House, 110 Manchester Road Altrincham Cheshire WA14 1NU",
    "addr:housenumber":"110",
    "addr:postcode":"wa14 1nu",
    "addr:street":"Manchester Road",
    "iso:country":"GB",
    "sg:address":"Trafalagar House, 110 Manchester Road",
    "sg:city":"Altrincham",
    "sg:classifiers":[
        {
            "category":"Manufacturing",
            "subcategory":"Tools & Machinery",
            "type":"Manufacturing & Wholesale Goods"
        }
    ],
    "sg:phone":"+44 161 927 2424",
    "sg:postcode":"WA14 1NU",
    "sg:province":"Cheshire",
    "sg:tags":[
        "society",
        "friendly"
    ],
    "wof:name":"Carole Nash Insurance Consultants Ltd.",
    "wof:placetype":"venue"
},
  "geometry": {"coordinates":[-2.351964,53.396957],"type":"Point"}
}