{
  "type": "Feature",
  "properties": {
    "addr:full":"373 London Road, Hazel Gro Stockport Cheshire SK7 6AA",
    "addr:housenumber":"373",
    "addr:postcode":"sk7 6aa",
    "addr:street":"London Road",
    "iso:country":"GB",
    "sg:address":"373 London Road, Hazel Gro",
    "sg:city":"Stockport",
    "sg:classifiers":[
        {
            "category":"Retail",
            "subcategory":"Veterinary Services",
            "type":"Services"
        }
    ],
    "sg:postcode":"SK7 6AA",
    "sg:province":"Cheshire",
    "sg:tags":[
        "surgeon"
    ],
    "wof:name":"Torkington Park Vets",
    "wof:placetype":"venue"
},
  "geometry": {"coordinates":[-2.114676,53.376324],"type":"Point"}
}