{
  "type": "Feature",
  "properties": {
    "addr:full":"Po Box 45 Evesham Gloucestershire WR11 7YP",
    "addr:housenumber":"po box 45",
    "addr:postcode":"wr11 7yp",
    "iso:country":"GB",
    "sg:address":"Po Box 45",
    "sg:city":"Evesham",
    "sg:classifiers":[
        {
            "category":"Shopping",
            "subcategory":"Florist",
            "type":"Retail Goods"
        }
    ],
    "sg:postcode":"WR11 7YP",
    "sg:province":"Gloucestershire",
    "wof:name":"First Class Flowers",
    "wof:placetype":"venue"
},
  "geometry": {"coordinates":[-1.900889039,52.0729789734],"type":"Point"}
}