{
  "type": "Feature",
  "properties": {
    "iso:country":"GB",
    "sg:address":"Caldway Drive",
    "sg:city":"Liverpool",
    "sg:classifiers":[
        {
            "category":"Sports & Exercise",
            "subcategory":"Golf",
            "type":"Entertainment"
        }
    ],
    "sg:phone":"+44 151 487 3744",
    "sg:postcode":"L27 7AR",
    "sg:province":"Merseyside",
    "sg:tags":[
        "club",
        "course"
    ],
    "wof:name":"Horton Group Ltd.",
    "wof:placetype":"venue"
},
  "geometry": {"coordinates":[-2.843168,53.390358],"type":"Point"}
}