{
  "type": "Feature",
  "properties": {
    "iso:country":"GB",
    "sg:address":"3 St Johns Road, Cudworth",
    "sg:city":"Barnsley",
    "sg:classifiers":[
        {
            "category":"Commercial Area",
            "type":"Public Place"
        }
    ],
    "sg:postcode":"S72 8BY",
    "sg:province":"South Yorkshire",
    "sg:tags":[
        "shop",
        "centre"
    ],
    "wof:name":"Wholesale Direct",
    "wof:placetype":"venue"
},
  "geometry": {"coordinates":[-1.418212,53.575706],"type":"Point"}
}