{
  "type": "Feature",
  "properties": {
    "iso:country":"GB",
    "sg:address":"Hillcrest, Andrew Rd",
    "sg:city":"Penarth",
    "sg:classifiers":[
        {
            "category":"Military Area",
            "subcategory":"Air Force Base",
            "type":"Public Place"
        }
    ],
    "sg:phone":"+44 29 2070 9822",
    "sg:postcode":"CF64 2NS",
    "sg:province":"The Vale of Glamorgan",
    "sg:tags":[
        "taxi",
        "hire",
        "private"
    ],
    "wof:name":"B Line Taxis Of Penarth",
    "wof:placetype":"venue"
},
  "geometry": {"coordinates":[-3.193329,51.442329],"type":"Point"}
}