{
  "type": "Feature",
  "properties": {
    "addr:full":"Chetwynd Street Stoke-on-trent Staffordshire ST6 1PP",
    "addr:postcode":"st6 1pp",
    "addr:street":"Chetwynd Street",
    "iso:country":"GB",
    "sg:address":"Chetwynd Street",
    "sg:city":"Stoke-on-trent",
    "sg:classifiers":[
        {
            "category":"Organizations",
            "subcategory":"Membership Organization",
            "type":"Services"
        }
    ],
    "sg:phone":"+44 1782 834695",
    "sg:postcode":"ST6 1PP",
    "sg:province":"Staffordshire",
    "sg:tags":[
        "club"
    ],
    "wof:name":"Smallthorne Pioneer Club & Institute",
    "wof:placetype":"venue"
},
  "geometry": {"coordinates":[-2.170559,53.053616],"type":"Point"}
}