{
  "type": "Feature",
  "properties": {
    "addr:full":"2 Sundon Park Parade Luton Bedfordshire LU3 3BH",
    "addr:housenumber":"2",
    "addr:postcode":"lu3 3bh",
    "addr:street":"Sundon Park Parade",
    "iso:country":"GB",
    "sg:address":"2 Sundon Park Parade",
    "sg:city":"Luton",
    "sg:classifiers":[
        {
            "category":"Cafe",
            "type":"Food & Drink"
        }
    ],
    "sg:phone":"+44 1582 560025",
    "sg:postcode":"LU3 3BH",
    "sg:province":"Bedfordshire",
    "sg:tags":[
        "tea",
        "room"
    ],
    "wof:name":"Toni's Diner",
    "wof:placetype":"venue"
},
  "geometry": {"coordinates":[-0.466049,51.910389],"type":"Point"}
}