{
  "type": "Feature",
  "properties": {
    "addr:full":"The Chapels Worcester Herefordshire WR6 5EH",
    "addr:postcode":"wr6 5eh",
    "iso:country":"GB",
    "sg:address":"The Chapels",
    "sg:city":"Worcester",
    "sg:classifiers":[
        {
            "category":"Retail",
            "subcategory":"Auto Repair",
            "type":"Services"
        }
    ],
    "sg:phone":"+44 1886 884460",
    "sg:postcode":"WR6 5EH",
    "sg:province":"Herefordshire",
    "sg:tags":[
        "modification",
        "garage"
    ],
    "wof:name":"D N Griffiths",
    "wof:placetype":"venue"
},
  "geometry": {"coordinates":[-2.3026530743,52.1646461487],"type":"Point"}
}