{
  "type": "Feature",
  "properties": {
    "iso:country":"GB",
    "sg:address":"Unit 9 Greenhill Business Centre",
    "sg:city":"Coatbridge",
    "sg:classifiers":[
        {
            "category":"Building & Trades",
            "subcategory":"Construction",
            "type":"Services"
        }
    ],
    "sg:postcode":"ML5 3AA",
    "sg:province":"North Lanarkshire",
    "sg:tags":[
        "decorator",
        "painter"
    ],
    "wof:name":"Artisan Decorating",
    "wof:placetype":"venue"
},
  "geometry": {"coordinates":[-4.035839,55.858753],"type":"Point"}
}