{
  "type": "Feature",
  "properties": {
    "addr:full":"37 Victoria Street Burnham-on-sea Somerset TA8 1AN",
    "addr:housenumber":"37",
    "addr:postcode":"ta8 1an",
    "addr:street":"Victoria Street",
    "iso:country":"GB",
    "sg:address":"37 Victoria Street",
    "sg:city":"Burnham-on-sea",
    "sg:classifiers":[
        {
            "category":"Home & Garden",
            "subcategory":"Furniture",
            "type":"Retail Goods"
        }
    ],
    "sg:phone":"+44 1278 780296",
    "sg:postcode":"TA8 1AN",
    "sg:province":"Somerset",
    "wof:name":"Stylish Ways",
    "wof:placetype":"venue"
},
  "geometry": {"coordinates":[-2.997392,51.23838],"type":"Point"}
}