{
  "type": "Feature",
  "properties": {
    "addr:full":"31 Albert Street Dundee Dundee City DD4 6NS",
    "addr:housenumber":"31",
    "addr:postcode":"dd4 6ns",
    "addr:street":"Albert Street",
    "iso:country":"GB",
    "sg:address":"31 Albert Street",
    "sg:city":"Dundee",
    "sg:classifiers":[
        {
            "category":"Fast Food",
            "type":"Food & Drink"
        }
    ],
    "sg:phone":"+44 1382 453426",
    "sg:postcode":"DD4 6NS",
    "sg:province":"Dundee City",
    "sg:tags":[
        "away",
        "take"
    ],
    "wof:name":"Punjab Tandoori",
    "wof:placetype":"venue"
},
  "geometry": {"coordinates":[-2.957785,56.468857],"type":"Point"}
}