{
  "type": "Feature",
  "properties": {
    "iso:country":"GB",
    "sg:address":"Tudor House, 47 High Street, Wem",
    "sg:city":"Shrewsbury",
    "sg:classifiers":[
        {
            "category":"Professional",
            "subcategory":"Lawyer & Legal Services",
            "type":"Services"
        }
    ],
    "sg:phone":"+44 1939 232775",
    "sg:postcode":"SY4 5DG",
    "sg:province":"Shropshire",
    "sg:tags":[
        "solicitor"
    ],
    "wof:name":"Paul F Harfitt & Co",
    "wof:placetype":"venue"
},
  "geometry": {"coordinates":[-2.7252910137,52.8552780151],"type":"Point"}
}