{
  "type": "Feature",
  "properties": {
    "addr:full":"51 Castlefields Main Centre Derby Derbyshire DE1 2PE",
    "addr:housenumber":"51",
    "addr:postcode":"de1 2pe",
    "addr:street":"Castlefields Main Centre",
    "iso:country":"GB",
    "sg:address":"51 Castlefields Main Centre",
    "sg:city":"Derby",
    "sg:classifiers":[
        {
            "category":"Home & Garden",
            "subcategory":"Household Appliances",
            "type":"Retail Goods"
        }
    ],
    "sg:postcode":"DE1 2PE",
    "sg:province":"Derbyshire",
    "sg:tags":[
        "electrical"
    ],
    "wof:name":"Powdrill,Tony,",
    "wof:placetype":"venue"
},
  "geometry": {"coordinates":[-1.4836839437,52.9251708984],"type":"Point"}
}