{
  "type": "Feature",
  "properties": {
    "addr:full":"42-43 Royal Mail House, Terminus Terrace Southampton Hampshire SO14 3FD",
    "addr:housenumber":"42-43",
    "addr:postcode":"so14 3fd",
    "addr:street":"Royal;Terminus Terrace",
    "iso:country":"GB",
    "sg:address":"42-43 Royal Mail House, Terminus Terrace",
    "sg:city":"Southampton",
    "sg:classifiers":[
        {
            "category":"Home & Garden",
            "subcategory":"Building Materials",
            "type":"Retail Goods"
        }
    ],
    "sg:postcode":"SO14 3FD",
    "sg:province":"Hampshire",
    "sg:tags":[
        "stairlifts"
    ],
    "wof:name":"Curti Lifts (Southern) Ltd.",
    "wof:placetype":"venue"
},
  "geometry": {"coordinates":[-1.3973200321,50.8975296021],"type":"Point"}
}