{
  "type": "Feature",
  "properties": {
    "iso:country":"GB",
    "sg:address":"9 Belwood Drive",
    "sg:city":"Doncaster",
    "sg:classifiers":[
        {
            "category":"Manufacturing",
            "subcategory":"Wood Products",
            "type":"Manufacturing & Wholesale Goods"
        },
        {
            "category":"Building & Trades",
            "subcategory":"Construction",
            "type":"Services"
        }
    ],
    "sg:postcode":"DN9 1TA",
    "sg:province":"Lincolnshire",
    "sg:tags":[
        "joinery",
        "sawmill",
        "shaving"
    ],
    "wof:name":"Leggott Joinery",
    "wof:placetype":"venue"
},
  "geometry": {"coordinates":[-0.8111,53.551941],"type":"Point"}
}