{
  "type": "Feature",
  "properties": {
    "addr:full":"Carr La Rotherham South Yorkshire S66 8NB",
    "addr:postcode":"s66 8nb",
    "addr:street":"Carr La Rotherham South",
    "iso:country":"GB",
    "sg:address":"Carr La",
    "sg:city":"Rotherham",
    "sg:classifiers":[
        {
            "category":"Home & Garden",
            "subcategory":"Building Materials",
            "type":"Retail Goods"
        }
    ],
    "sg:phone":"+44 1709 813555",
    "sg:postcode":"S66 8NB",
    "sg:province":"South Yorkshire",
    "sg:tags":[
        "ironwork",
        "diy",
        "wrought"
    ],
    "wof:name":"D & B Fencing & Ironworks",
    "wof:placetype":"venue"
},
  "geometry": {"coordinates":[-1.220354,53.419476],"type":"Point"}
}