{
  "type": "Feature",
  "properties": {
    "addr:full":"15 Kentish Town Rd Camden Greater London NW1 8NH",
    "addr:housenumber":"15",
    "addr:postcode":"nw1 8nh",
    "addr:street":"Kentish Town Rd",
    "iso:country":"GB",
    "sg:address":"15 Kentish Town Rd",
    "sg:city":"Camden",
    "sg:classifiers":[
        {
            "category":"Professional",
            "subcategory":"Business Services",
            "type":"Services"
        }
    ],
    "sg:phone":"+44 20 7482 4455",
    "sg:postcode":"NW1 8NH",
    "sg:province":"Greater London",
    "sg:tags":[
        "shop",
        "cleaning"
    ],
    "wof:name":"Promite Ltd",
    "wof:placetype":"venue"
},
  "geometry": {"coordinates":[-0.1421049982,51.5397758484],"type":"Point"}
}