{
  "type": "Feature",
  "properties": {
    "iso:country":"GB",
    "sg:address":"Manor Business Centre, Manor Way",
    "sg:city":"Rainham",
    "sg:classifiers":[
        {
            "category":"Building & Trades",
            "subcategory":"Construction",
            "type":"Services"
        }
    ],
    "sg:phone":"+44 1780 525200",
    "sg:postcode":"RM13 8RH",
    "sg:province":"Essex",
    "sg:tags":[
        "pipework",
        "contractor"
    ],
    "wof:name":"Anglo Standard Pipework Ltd: Unit 10",
    "wof:placetype":"venue"
},
  "geometry": {"coordinates":[0.1904260069,51.5179138184],"type":"Point"}
}