{
  "type": "Feature",
  "properties": {
    "addr:full":"Birds Farm, Haslingfield Road Cambridge Cambridgeshire CB3 7AG",
    "addr:postcode":"cb3 7ag",
    "addr:street":"Haslingfield Road",
    "iso:country":"GB",
    "sg:address":"Birds Farm, Haslingfield Road",
    "sg:city":"Cambridge",
    "sg:classifiers":[
        {
            "category":"Professional",
            "subcategory":"Management & Consulting",
            "type":"Services"
        }
    ],
    "sg:postcode":"CB3 7AG",
    "sg:province":"Cambridgeshire",
    "sg:tags":[
        "conservation"
    ],
    "wof:name":"The Countryside Restoration Trust Ltd.",
    "wof:placetype":"venue"
},
  "geometry": {"coordinates":[0.0582199991,52.1502914429],"type":"Point"}
}