{
  "type": "Feature",
  "properties": {
    "addr:full":"8 St. Kilda Rd West Ealing Greater London W13 9DE",
    "addr:housenumber":"8",
    "addr:postcode":"w13 9de",
    "addr:street":"St. Kilda Rd",
    "iso:country":"GB",
    "sg:address":"8 St. Kilda Rd",
    "sg:city":"West Ealing",
    "sg:classifiers":[
        {
            "category":"Health Services",
            "subcategory":"Doctor",
            "type":"Services"
        }
    ],
    "sg:phone":"+44 20 8567 5721",
    "sg:postcode":"W13 9DE",
    "sg:province":"Greater London",
    "sg:tags":[
        "practitioners"
    ],
    "wof:name":"Dr P Gupta",
    "wof:placetype":"venue"
},
  "geometry": {"coordinates":[-0.325802,51.507401],"type":"Point"}
}