{
  "type": "Feature",
  "properties": {
    "iso:country":"GB",
    "sg:address":"94 Renfield Street",
    "sg:city":"Glasgow",
    "sg:classifiers":[
        {
            "category":"Recreation",
            "subcategory":"Amusement Park",
            "type":"Entertainment"
        }
    ],
    "sg:phone":"+44 141 331 2052",
    "sg:postcode":"G2 1NH",
    "sg:province":"Glasgow City",
    "sg:tags":[
        "arcade"
    ],
    "wof:name":"Scotia Pubs & Leisure Ltd.",
    "wof:placetype":"venue"
},
  "geometry": {"coordinates":[-4.255665,55.863846],"type":"Point"}
}