{
  "type": "Feature",
  "properties": {
    "iso:country":"GB",
    "sg:address":"9 Park Road",
    "sg:city":"Harrogate",
    "sg:classifiers":[
        {
            "category":"Health Services",
            "subcategory":"Nursing And Care Facility",
            "type":"Services"
        },
        {
            "category":"Social Services",
            "subcategory":"Retirement Home",
            "type":"Services"
        }
    ],
    "sg:phone":"+44 1423 521014",
    "sg:postcode":"HG2 9BH",
    "sg:province":"North Yorkshire",
    "sg:tags":[
        "residential"
    ],
    "wof:name":"Insight Homes Ltd.",
    "wof:placetype":"venue"
},
  "geometry": {"coordinates":[-1.5442609787,53.9846534729],"type":"Point"}
}