{
  "type": "Feature",
  "properties": {
    "addr:full":"20 Penmon Drive Wirral Merseyside CH61 5UJ",
    "addr:housenumber":"20",
    "addr:postcode":"ch61 5uj",
    "addr:street":"Penmon Drive",
    "iso:country":"GB",
    "sg:address":"20 Penmon Drive",
    "sg:city":"Wirral",
    "sg:classifiers":[
        {
            "category":"Personal",
            "type":"Services"
        }
    ],
    "sg:phone":"+44 151 342 8148",
    "sg:postcode":"CH61 5UJ",
    "sg:province":"Merseyside",
    "sg:tags":[
        "wedding"
    ],
    "wof:name":"Harmony Bridal Hire",
    "wof:placetype":"venue"
},
  "geometry": {"coordinates":[-3.098841,53.341049],"type":"Point"}
}