{
  "type": "Feature",
  "properties": {
    "addr:full":"Unit 15 Ingoldmells Court, Edinburgh Way Corsham Wiltshire SN13 9XN",
    "addr:housenumber":"unit 15 ingoldmells",
    "addr:postcode":"sn13 9xn",
    "addr:street":"Court Edinburgh Way",
    "iso:country":"GB",
    "sg:address":"Unit 15 Ingoldmells Court, Edinburgh Way",
    "sg:city":"Corsham",
    "sg:classifiers":[
        {
            "category":"Professional",
            "subcategory":"Management & Consulting",
            "type":"Services"
        },
        {
            "category":"Sports & Exercise",
            "subcategory":"Sports Center",
            "type":"Entertainment"
        }
    ],
    "sg:phone":"+44 1225 810818",
    "sg:postcode":"SN13 9XN",
    "sg:province":"Wiltshire",
    "sg:tags":[
        "consultant",
        "investigation",
        "site"
    ],
    "wof:name":"Ground Restoration Ltd",
    "wof:placetype":"venue"
},
  "geometry": {"coordinates":[-2.197803,51.421249],"type":"Point"}
}