{
  "type": "Feature",
  "properties": {
    "addr:full":"Unit 22, Atlantic Trading Estate Barry The Vale of Glamorgan CF63 3RF",
    "addr:housenumber":"unit 22;estate",
    "addr:postcode":"cf63 3rf",
    "addr:street":"Trading;Barry The Vale",
    "iso:country":"GB",
    "sg:address":"Unit 22, Atlantic Trading Estate",
    "sg:city":"Barry",
    "sg:classifiers":[
        {
            "category":"Wholesale",
            "subcategory":"Scrap",
            "type":"Manufacturing & Wholesale Goods"
        }
    ],
    "sg:phone":"+44 1446 744441",
    "sg:postcode":"CF63 3RF",
    "sg:province":"The Vale of Glamorgan",
    "sg:tags":[
        "car",
        "breaker",
        "dismantlers"
    ],
    "wof:name":"Atlantic Salvage",
    "wof:placetype":"venue"
},
  "geometry": {"coordinates":[-3.2487089634,51.4039115906],"type":"Point"}
}