{
  "type": "Feature",
  "properties": {
    "addr:full":"Cary Lane Brigg Lincolnshire DN20 8EY",
    "addr:postcode":"dn20 8ey",
    "iso:country":"GB",
    "sg:address":"Cary Lane",
    "sg:city":"Brigg",
    "sg:classifiers":[
        {
            "category":"Food & Beverages",
            "subcategory":"Meat & Fish",
            "type":"Retail Goods"
        }
    ],
    "sg:phone":"+44 1652 650760",
    "sg:postcode":"DN20 8EY",
    "sg:province":"Lincolnshire",
    "sg:tags":[
        "butcher"
    ],
    "wof:name":"Spelman Family Butchers",
    "wof:placetype":"venue"
},
  "geometry": {"coordinates":[-0.492956996,53.5533790588],"type":"Point"}
}