{
  "type": "Feature",
  "properties": {
    "iso:country":"GB",
    "sg:address":"932 Ringwood Road",
    "sg:city":"Bournemouth",
    "sg:classifiers":[
        {
            "category":"Shopping",
            "subcategory":"Florist",
            "type":"Retail Goods"
        }
    ],
    "sg:postcode":"BH11 8NL",
    "sg:province":"Dorset",
    "wof:name":"Debbies Florists",
    "wof:placetype":"venue"
},
  "geometry": {"coordinates":[-1.926109,50.758976],"type":"Point"}
}