{
  "type": "Feature",
  "properties": {
    "addr:full":"4 Lydford Court, 29a Lydford Road Willesden Green London Greater London NW2 5QZ",
    "addr:housenumber":"4;29a",
    "addr:postcode":"nw2 5qz",
    "addr:street":"Lydford Court;Lydford Road",
    "iso:country":"GB",
    "sg:address":"4 Lydford Court, 29a Lydford Road Willesden Green",
    "sg:city":"London",
    "sg:classifiers":[
        {
            "category":"Travel",
            "subcategory":"Travel Agent",
            "type":"Entertainment"
        }
    ],
    "sg:postcode":"NW2 5QZ",
    "sg:province":"Greater London",
    "wof:name":"Travelling (Uk) Ltd",
    "wof:placetype":"venue"
},
  "geometry": {"coordinates":[-0.221157,51.548958],"type":"Point"}
}