{
  "type": "Feature",
  "properties": {
    "iso:country":"GB",
    "sg:address":"36 Poulton Street, Kirkham",
    "sg:city":"Preston",
    "sg:classifiers":[
        {
            "category":"Banks & Credit Unions",
            "subcategory":"Bank",
            "type":"Services"
        }
    ],
    "sg:phone":"+44 845 765 4321",
    "sg:postcode":"PR4 2AH",
    "sg:province":"Lancashire",
    "wof:name":"Abbey National Plc",
    "wof:placetype":"venue"
},
  "geometry": {"coordinates":[-2.873637,53.78241],"type":"Point"}
}