{
  "type": "Feature",
  "properties": {
    "iso:country":"GB",
    "sg:address":"139 High Street, Tibshelf",
    "sg:city":"Alfreton",
    "sg:classifiers":[
        {
            "category":"Home & Garden",
            "subcategory":"Furniture",
            "type":"Retail Goods"
        }
    ],
    "sg:postcode":"DE55 5PP",
    "sg:province":"Derbyshire",
    "wof:name":"Johns of Tibshelf",
    "wof:placetype":"venue"
},
  "geometry": {"coordinates":[-1.339188,53.144981],"type":"Point"}
}