{
  "type": "Feature",
  "properties": {
    "iso:country":"GB",
    "sg:address":"449-451 Hoylake Road",
    "sg:city":"Wirral",
    "sg:classifiers":[
        {
            "category":"Shopping",
            "subcategory":"News",
            "type":"Retail Goods"
        }
    ],
    "sg:phone":"+44 151 677 8101",
    "sg:postcode":"CH46 6DQ",
    "sg:province":"Merseyside",
    "sg:tags":[
        "newsagent"
    ],
    "wof:name":"Londis",
    "wof:placetype":"venue"
},
  "geometry": {"coordinates":[-3.12533,53.396259],"type":"Point"}
}