{
  "type": "Feature",
  "properties": {
    "addr:full":"60 Albert Road Eyemouth Scottish Borders TD14 5EN",
    "addr:housenumber":"60",
    "addr:postcode":"td14 5en",
    "addr:street":"Albert Road",
    "iso:country":"GB",
    "sg:address":"60 Albert Road",
    "sg:city":"Eyemouth",
    "sg:classifiers":[
        {
            "category":"Organizations",
            "subcategory":"Community Association",
            "type":"Services"
        },
        {
            "category":"Organizations",
            "subcategory":"Membership Organization",
            "type":"Services"
        }
    ],
    "sg:phone":"+44 1890 750482",
    "sg:postcode":"TD14 5EN",
    "sg:province":"Scottish Borders",
    "sg:tags":[
        "club",
        "social"
    ],
    "wof:name":"The Royal British Legion",
    "wof:placetype":"venue"
},
  "geometry": {"coordinates":[-2.0913519859,55.8724555969],"type":"Point"}
}