{
  "type": "Feature",
  "properties": {
    "addr:full":"151 Somers Road Southsea Hampshire PO5 4PT",
    "addr:housenumber":"151",
    "addr:postcode":"po5 4pt",
    "addr:street":"Somers Road",
    "iso:country":"GB",
    "sg:address":"151 Somers Road",
    "sg:city":"Southsea",
    "sg:classifiers":[
        {
            "category":"Military Area",
            "subcategory":"Air Force Base",
            "type":"Public Place"
        }
    ],
    "sg:phone":"+44 23 9281 8123",
    "sg:postcode":"PO5 4PT",
    "sg:province":"Hampshire",
    "sg:tags":[
        "taxi",
        "hire",
        "private"
    ],
    "wof:name":"Aqua Cars Ltd.",
    "wof:placetype":"venue"
},
  "geometry": {"coordinates":[-1.0829410553,50.795211792],"type":"Point"}
}