{
  "type": "Feature",
  "properties": {
    "iso:country":"GB",
    "sg:address":"66 Victoria Rd",
    "sg:city":"Ferndown",
    "sg:classifiers":[
        {
            "category":"Real Estate",
            "subcategory":"Real Estate Agent",
            "type":"Services"
        }
    ],
    "sg:phone":"+44 1202 876565",
    "sg:postcode":"BH22 9JA",
    "sg:province":"Dorset",
    "wof:name":"Halifax Property Services",
    "wof:placetype":"venue"
},
  "geometry": {"coordinates":[-1.8904149532,50.8025550842],"type":"Point"}
}