{
  "type": "Feature",
  "properties": {
    "addr:full":"The Old Barn, 52 East Fen Common, Soham Ely Cambridgeshire CB7 5JJ",
    "addr:housenumber":"52",
    "addr:postcode":"cb7 5jj",
    "addr:street":"East Fen Common",
    "iso:country":"GB",
    "sg:address":"The Old Barn, 52 East Fen Common, Soham",
    "sg:city":"Ely",
    "sg:classifiers":[
        {
            "category":"Banks & Credit Unions",
            "subcategory":"Financial Services",
            "type":"Services"
        }
    ],
    "sg:phone":"+44 1353 723007",
    "sg:postcode":"CB7 5JJ",
    "sg:province":"Cambridgeshire",
    "sg:tags":[
        "adviser"
    ],
    "wof:name":"Edgar Brooks & Co",
    "wof:placetype":"venue"
},
  "geometry": {"coordinates":[0.3569400012,52.3179893494],"type":"Point"}
}