{
  "type": "Feature",
  "properties": {
    "iso:country":"GB",
    "sg:address":"Broad Oak Rd",
    "sg:city":"Canterbury",
    "sg:classifiers":[
        {
            "category":"Retail",
            "subcategory":"Auto Repair",
            "type":"Services"
        }
    ],
    "sg:postcode":"CT2 7RB",
    "sg:province":"Kent",
    "sg:tags":[
        "modification",
        "garage"
    ],
    "wof:name":"Driveline Ltd",
    "wof:placetype":"venue"
},
  "geometry": {"coordinates":[1.088605,51.290176],"type":"Point"}
}