{
  "type": "Feature",
  "properties": {
    "addr:full":"North Deeside Road, Pitfodels Aberdeen Aberdeen City AB15 9PN",
    "addr:postcode":"ab15 9pn",
    "addr:street":"North Deeside Road Pitfodels",
    "iso:country":"GB",
    "sg:address":"North Deeside Road, Pitfodels",
    "sg:city":"Aberdeen",
    "sg:classifiers":[
        {
            "category":"Education",
            "subcategory":"School",
            "type":"Public Place"
        }
    ],
    "sg:postcode":"AB15 9PN",
    "sg:province":"Aberdeen City",
    "sg:tags":[
        "local",
        "authority"
    ],
    "wof:name":"Pitfodels School",
    "wof:placetype":"venue"
},
  "geometry": {"coordinates":[-2.208361,57.110577],"type":"Point"}
}