{
  "type": "Feature",
  "properties": {
    "addr:full":"96 Keighley Road Colne Lancashire BB8 0PH",
    "addr:housenumber":"96",
    "addr:postcode":"bb8 0ph",
    "addr:street":"Keighley Road",
    "iso:country":"GB",
    "sg:address":"96 Keighley Road",
    "sg:city":"Colne",
    "sg:classifiers":[
        {
            "category":"Manufacturing",
            "subcategory":"Petroleum Products",
            "type":"Manufacturing & Wholesale Goods"
        },
        {
            "category":"Manufacturing",
            "subcategory":"Lumber",
            "type":"Manufacturing & Wholesale Goods"
        }
    ],
    "sg:phone":"+44 1282 868889",
    "sg:postcode":"BB8 0PH",
    "sg:province":"Lancashire",
    "sg:tags":[
        "merchants",
        "glazing",
        "double",
        "agent",
        "importer",
        "timber"
    ],
    "wof:name":"Normandy Glass",
    "wof:placetype":"venue"
},
  "geometry": {"coordinates":[-2.1572918892,53.8579864502],"type":"Point"}
}