{
  "type": "Feature",
  "properties": {
    "addr:full":"Werran Ho, Kenterton Rd Bedford Bedfordshire MK41 0YA",
    "addr:postcode":"mk41 0ya",
    "addr:street":"Kenterton Rd",
    "iso:country":"GB",
    "sg:address":"Werran Ho, Kenterton Rd",
    "sg:city":"Bedford",
    "sg:classifiers":[
        {
            "category":"Shopping",
            "subcategory":"Bicycles & Sporting Goods",
            "type":"Retail Goods"
        },
        {
            "category":"Autos & Motor Vehicles",
            "subcategory":"Boat Sales",
            "type":"Retail Goods"
        }
    ],
    "sg:postcode":"MK41 0YA",
    "sg:province":"Bedfordshire",
    "sg:tags":[
        "equipment",
        "repair",
        "builder",
        "marine",
        "supply"
    ],
    "wof:name":"Compass Inflatables Ltd",
    "wof:placetype":"venue"
},
  "geometry": {"coordinates":[-0.4195599854,52.1461181641],"type":"Point"}
}