{
  "type": "Feature",
  "properties": {
    "iso:country":"GB",
    "sg:address":"147 Ravensworth Rd",
    "sg:city":"Gateshead",
    "sg:classifiers":[
        {
            "category":"Home & Garden",
            "subcategory":"Hardware",
            "type":"Retail Goods"
        }
    ],
    "sg:phone":"+44 191 460 6749",
    "sg:postcode":"NE11 9AE",
    "sg:province":"Tyne and Wear",
    "wof:name":"Cattericks Hardware",
    "wof:placetype":"venue"
},
  "geometry": {"coordinates":[-1.6394439936,54.9551849365],"type":"Point"}
}