{
  "type": "Feature",
  "properties": {
    "addr:full":"The Wynd Glasgow Falkirk G67 2ST",
    "addr:postcode":"g67 2st",
    "addr:street":"The Wynd",
    "iso:country":"GB",
    "sg:address":"The Wynd",
    "sg:city":"Glasgow",
    "sg:classifiers":[
        {
            "category":"Museum",
            "subcategory":"Art Museum",
            "type":"Entertainment"
        }
    ],
    "sg:phone":"+44 1236 730513",
    "sg:postcode":"G67 2ST",
    "sg:province":"Falkirk",
    "sg:tags":[
        "gallery"
    ],
    "wof:name":"Ardenlea House Museum",
    "wof:placetype":"venue"
},
  "geometry": {"coordinates":[-3.975174,55.963055],"type":"Point"}
}