{
  "type": "Feature",
  "properties": {
    "addr:full":"9 Moorside Road, Heaton Moor Stockport Cheshire SK4 4DT",
    "addr:housenumber":"9",
    "addr:postcode":"sk4 4dt",
    "addr:street":"Moorside Road",
    "iso:country":"GB",
    "sg:address":"9 Moorside Road, Heaton Moor",
    "sg:city":"Stockport",
    "sg:classifiers":[
        {
            "category":"Shopping",
            "subcategory":"Gifts & Souvenirs",
            "type":"Retail Goods"
        }
    ],
    "sg:postcode":"SK4 4DT",
    "sg:province":"Cheshire",
    "sg:tags":[
        "shop"
    ],
    "wof:name":"Rivendell",
    "wof:placetype":"venue"
},
  "geometry": {"coordinates":[-2.189538002,53.4166183472],"type":"Point"}
}