{
  "type": "Feature",
  "properties": {
    "addr:full":"38 Mill La Billingham Durham TS23 1HF",
    "addr:housenumber":"38",
    "addr:postcode":"ts23 1hf",
    "addr:street":"Mill La Billingham",
    "iso:country":"GB",
    "sg:address":"38 Mill La",
    "sg:city":"Billingham",
    "sg:classifiers":[
        {
            "category":"Retail",
            "subcategory":"Laundry & Dry Cleaning",
            "type":"Services"
        }
    ],
    "sg:phone":"+44 1642 554141",
    "sg:postcode":"TS23 1HF",
    "sg:province":"Durham",
    "sg:tags":[
        "launderette"
    ],
    "wof:name":"R W & M Rowell",
    "wof:placetype":"venue"
},
  "geometry": {"coordinates":[-1.289307,54.591991],"type":"Point"}
}