{
  "type": "Feature",
  "properties": {
    "iso:country":"GB",
    "sg:address":"11 Wardens Walk, Leicester Forest East",
    "sg:city":"Leicester",
    "sg:classifiers":[
        {
            "category":"Cinema",
            "subcategory":"Movie Rental",
            "type":"Entertainment"
        }
    ],
    "sg:phone":"+44 116 289 0000",
    "sg:postcode":"LE3 3GF",
    "sg:province":"Leicestershire",
    "sg:tags":[
        "video",
        "library"
    ],
    "wof:name":"Andy Kim's Moviezone",
    "wof:placetype":"venue"
},
  "geometry": {"coordinates":[-1.200582,52.624104],"type":"Point"}
}