{
  "type": "Feature",
  "properties": {
    "iso:country":"GB",
    "sg:address":"35 Charlotte Dundas Ct",
    "sg:city":"Grangemouth",
    "sg:classifiers":[
        {
            "category":"Shopping",
            "subcategory":"Thrift Store",
            "type":"Retail Goods"
        }
    ],
    "sg:postcode":"FK3 9EA",
    "sg:province":"Falkirk",
    "sg:tags":[
        "shop",
        "charity"
    ],
    "wof:name":"New 2 You",
    "wof:placetype":"venue"
},
  "geometry": {"coordinates":[-3.723894,56.009331],"type":"Point"}
}