{
  "type": "Feature",
  "properties": {
    "addr:full":"26 Henson Way Hinckley Leicestershire LE10 3PN",
    "addr:housenumber":"26",
    "addr:postcode":"le10 3pn",
    "addr:street":"Henson Way",
    "iso:country":"GB",
    "sg:address":"26 Henson Way",
    "sg:city":"Hinckley",
    "sg:classifiers":[
        {
            "category":"Professional",
            "subcategory":"Art Services",
            "type":"Services"
        }
    ],
    "sg:phone":"+44 1455 274230",
    "sg:postcode":"LE10 3PN",
    "sg:province":"Leicestershire",
    "sg:tags":[
        "photographer"
    ],
    "wof:name":"Dimension",
    "wof:placetype":"venue"
},
  "geometry": {"coordinates":[-1.2940609455,52.5246696472],"type":"Point"}
}