{
  "type": "Feature",
  "properties": {
    "addr:full":"12 Redwood Crescent, Peel Park Camp Glasgow South Lanarkshire G74 5PA",
    "addr:housenumber":"12",
    "addr:postcode":"g74 5pa",
    "addr:street":"Redwood Crescent Peel Park",
    "iso:country":"GB",
    "sg:address":"12 Redwood Crescent, Peel Park Camp",
    "sg:city":"Glasgow",
    "sg:classifiers":[
        {
            "category":"Shopping",
            "subcategory":"Computers & Home Electronics",
            "type":"Retail Goods"
        }
    ],
    "sg:postcode":"G74 5PA",
    "sg:province":"South Lanarkshire",
    "wof:name":"Simple Technology Ltd.",
    "wof:placetype":"venue"
},
  "geometry": {"coordinates":[-4.2293839455,55.7654380798],"type":"Point"}
}