{
  "type": "Feature",
  "properties": {
    "iso:country":"GB",
    "sg:address":"13 Northfield Place, Shavington",
    "sg:city":"Crewe",
    "sg:classifiers":[
        {
            "category":"Retail",
            "subcategory":"Veterinary Services",
            "type":"Services"
        }
    ],
    "sg:postcode":"CW2 5BL",
    "sg:province":"Cheshire",
    "sg:tags":[
        "surgeon"
    ],
    "wof:name":"Moneague Ltd",
    "wof:placetype":"venue"
},
  "geometry": {"coordinates":[-2.4488170147,53.0669708252],"type":"Point"}
}