{
  "type": "Feature",
  "properties": {
    "addr:full":"1 Whaley Road Potters Bar Greater London EN6 2RA",
    "addr:housenumber":"1",
    "addr:postcode":"en6 2ra",
    "addr:street":"Whaley Road",
    "iso:country":"GB",
    "sg:address":"1 Whaley Road",
    "sg:city":"Potters Bar",
    "sg:classifiers":[
        {
            "category":"Retail",
            "subcategory":"Auto Repair",
            "type":"Services"
        }
    ],
    "sg:phone":"+44 1707 656281",
    "sg:postcode":"EN6 2RA",
    "sg:province":"Greater London",
    "sg:tags":[
        "body",
        "garage",
        "modification",
        "car"
    ],
    "wof:name":"Newton Motors",
    "wof:placetype":"venue"
},
  "geometry": {"coordinates":[-0.178494,51.690254],"type":"Point"}
}