{
  "type": "Feature",
  "properties": {
    "addr:full":"79 Cowley Mill Rd Uxbridge Buckinghamshire UB8 2QE",
    "addr:housenumber":"79",
    "addr:postcode":"ub8 2qe",
    "addr:street":"Cowley Mill Rd",
    "iso:country":"GB",
    "sg:address":"79 Cowley Mill Rd",
    "sg:city":"Uxbridge",
    "sg:classifiers":[
        {
            "category":"Utilities",
            "subcategory":"Fuel Oil & Lpg",
            "type":"Services"
        }
    ],
    "sg:phone":"+44 1895 812607",
    "sg:postcode":"UB8 2QE",
    "sg:province":"Buckinghamshire",
    "sg:tags":[
        "cosmetic"
    ],
    "wof:name":"Vernon Charles",
    "wof:placetype":"venue"
},
  "geometry": {"coordinates":[-0.488975,51.538342],"type":"Point"}
}