{
  "type": "Feature",
  "properties": {
    "iso:country":"GB",
    "sg:address":"The Morgan Centre, Lower Road, Little Hallingbury",
    "sg:city":"Bishops Stortford",
    "sg:classifiers":[
        {
            "category":"Shopping",
            "subcategory":"Stationery & Office Supplies",
            "type":"Retail Goods"
        }
    ],
    "sg:postcode":"CM22 7RA",
    "sg:province":"Essex",
    "sg:tags":[
        "equipment"
    ],
    "wof:name":"Laser Office Equipment",
    "wof:placetype":"venue"
},
  "geometry": {"coordinates":[0.1752829999,51.8372154236],"type":"Point"}
}