{
  "type": "Feature",
  "properties": {
    "addr:full":"25 St Mary Street Bridgwater Somerset TA6 3LX",
    "addr:housenumber":"25",
    "addr:postcode":"ta6 3lx",
    "addr:street":"St Mary Street",
    "iso:country":"GB",
    "sg:address":"25 St Mary Street",
    "sg:city":"Bridgwater",
    "sg:classifiers":[
        {
            "category":"Shopping",
            "subcategory":"Comic Books",
            "type":"Retail Goods"
        }
    ],
    "sg:phone":"+44 1278 422075",
    "sg:postcode":"TA6 3LX",
    "sg:province":"Somerset",
    "sg:tags":[
        "jeweller"
    ],
    "wof:name":"Austin Warner",
    "wof:placetype":"venue"
},
  "geometry": {"coordinates":[-3.003491,51.127201],"type":"Point"}
}