{
  "type": "Feature",
  "properties": {
    "addr:full":"Unit 2-3a Perseverance Mills, Lockwood Scar Huddersfield West Yorkshire HD4 6BW",
    "addr:housenumber":"unit 2-3a",
    "addr:postcode":"hd4 6bw",
    "addr:street":"Scar",
    "iso:country":"GB",
    "sg:address":"Unit 2-3a Perseverance Mills, Lockwood Scar",
    "sg:city":"Huddersfield",
    "sg:classifiers":[
        {
            "category":"Depot",
            "subcategory":"Train",
            "type":"Transportation"
        },
        {
            "category":"Military Area",
            "subcategory":"Restricted Area",
            "type":"Public Place"
        }
    ],
    "sg:phone":"+44 1484 451760",
    "sg:postcode":"HD4 6BW",
    "sg:province":"West Yorkshire",
    "sg:tags":[
        "mnfrs",
        "repair",
        "servicing",
        "caravan"
    ],
    "wof:name":"West Riding Leisure",
    "wof:placetype":"venue"
},
  "geometry": {"coordinates":[-1.7853089571,53.6356010437],"type":"Point"}
}