{
  "type": "Feature",
  "properties": {
    "addr:full":"Unit 3, 28 Plantation Road Amersham Buckinghamshire HP6 6HJ",
    "addr:housenumber":"unit;28",
    "addr:postcode":"hp6 6hj",
    "addr:street":"Plantation Road",
    "iso:country":"GB",
    "sg:address":"Unit 3, 28 Plantation Road",
    "sg:city":"Amersham",
    "sg:classifiers":[
        {
            "category":"Autos & Motor Vehicles",
            "subcategory":"Automobile Sales",
            "type":"Retail Goods"
        },
        {
            "category":"Retail",
            "subcategory":"Auto Repair",
            "type":"Services"
        }
    ],
    "sg:phone":"+44 1494 721491",
    "sg:postcode":"HP6 6HJ",
    "sg:province":"Buckinghamshire",
    "sg:tags":[
        "modification",
        "garage",
        "car"
    ],
    "wof:name":"A & J Cars",
    "wof:placetype":"venue"
},
  "geometry": {"coordinates":[-0.591339,51.67878],"type":"Point"}
}