{
  "type": "Feature",
  "properties": {
    "addr:full":"Westacre, Smithy Lane, Holmswood Ormskirk Lancashire L40 1UH",
    "addr:postcode":"l40 1uh",
    "addr:street":"Smithy Lane",
    "iso:country":"GB",
    "sg:address":"Westacre, Smithy Lane, Holmswood",
    "sg:city":"Ormskirk",
    "sg:classifiers":[
        {
            "category":"Building & Trades",
            "subcategory":"Plumbing",
            "type":"Services"
        }
    ],
    "sg:phone":"+44 1704 822310",
    "sg:postcode":"L40 1UH",
    "sg:province":"Lancashire",
    "sg:tags":[
        "central",
        "heating"
    ],
    "wof:name":"Dandy Heating Services",
    "wof:placetype":"venue"
},
  "geometry": {"coordinates":[-2.8611400127,53.6455116272],"type":"Point"}
}