{
  "type": "Feature",
  "properties": {
    "addr:full":"44 Coventry Road St Leonards-on-sea East Sussex TN38 9ET",
    "addr:housenumber":"44",
    "addr:postcode":"leonards-on-sea;tn38 9et",
    "addr:street":"Coventry Road St",
    "iso:country":"GB",
    "sg:address":"44 Coventry Road",
    "sg:city":"St Leonards-on-sea",
    "sg:classifiers":[
        {
            "category":"Professional",
            "subcategory":"Detective & Security Services",
            "type":"Services"
        }
    ],
    "sg:postcode":"TN38 9ET",
    "sg:province":"East Sussex",
    "sg:tags":[
        "alarm",
        "burglar",
        "system"
    ],
    "wof:name":"All Safe 'N' Sound Security Systems",
    "wof:placetype":"venue"
},
  "geometry": {"coordinates":[0.549668,50.872974],"type":"Point"}
}