{
  "type": "Feature",
  "properties": {
    "addr:full":"2 Guildhall Walk Portsmouth Hampshire PO1 2DD",
    "addr:housenumber":"2",
    "addr:postcode":"hampshire po1 2dd",
    "addr:street":"Guildhall Walk",
    "iso:country":"GB",
    "sg:address":"2 Guildhall Walk",
    "sg:city":"Portsmouth",
    "sg:classifiers":[
        {
            "category":"Bars & Pubs",
            "type":"Food & Drink"
        }
    ],
    "sg:phone":"+44 23 9229 5112",
    "sg:postcode":"PO1 2DD",
    "sg:province":"Hampshire",
    "sg:tags":[
        "pubs",
        "inn"
    ],
    "wof:name":"Wetherspoons",
    "wof:placetype":"venue"
},
  "geometry": {"coordinates":[-1.092427969,50.7967948914],"type":"Point"}
}