{
  "type": "Feature",
  "properties": {
    "addr:full":"245a Coldharbour Lane London Greater London SW9 8RR",
    "addr:housenumber":"245a",
    "addr:postcode":"sw9 8rr",
    "addr:street":"Coldharbour Lane",
    "iso:country":"GB",
    "sg:address":"245a Coldharbour Lane",
    "sg:city":"London",
    "sg:classifiers":[
        {
            "category":"Building & Trades",
            "subcategory":"Cleaning & Sanitation",
            "type":"Services"
        }
    ],
    "sg:postcode":"SW9 8RR",
    "sg:province":"Greater London",
    "sg:tags":[
        "contracting",
        "commercial"
    ],
    "wof:name":"E N K O",
    "wof:placetype":"venue"
},
  "geometry": {"coordinates":[-0.103018,51.46479],"type":"Point"}
}