{
  "type": "Feature",
  "properties": {
    "addr:full":"4 Stanhope Road Deal Kent CT14 6AB",
    "addr:housenumber":"4",
    "addr:postcode":"ct14 6ab",
    "addr:street":"Stanhope Road Deal",
    "iso:country":"GB",
    "sg:address":"4 Stanhope Road",
    "sg:city":"Deal",
    "sg:classifiers":[
        {
            "category":"Food & Beverages",
            "subcategory":"Fruits & Vegetables",
            "type":"Retail Goods"
        }
    ],
    "sg:phone":"+44 1304 368699",
    "sg:postcode":"CT14 6AB",
    "sg:province":"Kent",
    "sg:tags":[
        "greengrocer"
    ],
    "wof:name":"Alison Flowers",
    "wof:placetype":"venue"
},
  "geometry": {"coordinates":[1.40224,51.225021],"type":"Point"}
}