{
  "type": "Feature",
  "properties": {
    "iso:country":"GB",
    "sg:address":"19 Rannoch Drive, Bearsden",
    "sg:city":"Glasgow",
    "sg:classifiers":[
        {
            "category":"Personal",
            "subcategory":"Beauty Salon",
            "type":"Services"
        }
    ],
    "sg:postcode":"G61 2JW",
    "sg:province":"East Dunbartonshire",
    "sg:tags":[
        "unisex",
        "hairdresser"
    ],
    "wof:name":"Hair by Shapes",
    "wof:placetype":"venue"
},
  "geometry": {"coordinates":[-4.3142251968,55.9078941345],"type":"Point"}
}