{
  "type": "Feature",
  "properties": {
    "iso:country":"GB",
    "sg:address":"71 Laithes Lane",
    "sg:city":"Barnsley",
    "sg:classifiers":[
        {
            "category":"Professional",
            "subcategory":"Art Services",
            "type":"Services"
        }
    ],
    "sg:postcode":"S71 3AQ",
    "sg:province":"South Yorkshire",
    "sg:tags":[
        "graphic",
        "designer"
    ],
    "wof:name":"Wilson Design House",
    "wof:placetype":"venue"
},
  "geometry": {"coordinates":[-1.4717619419,53.5802574158],"type":"Point"}
}