{
  "type": "Feature",
  "properties": {
    "iso:country":"GB",
    "sg:address":"Brays Lane",
    "sg:city":"Coventry",
    "sg:classifiers":[
        {
            "category":"Health Services",
            "subcategory":"Nursing And Care Facility",
            "type":"Services"
        },
        {
            "category":"Social Services",
            "subcategory":"Retirement Home",
            "type":"Services"
        }
    ],
    "sg:phone":"+44 24 7644 5514",
    "sg:postcode":"CV2 4DS",
    "sg:province":"Warwickshire",
    "sg:tags":[
        "residential"
    ],
    "wof:name":"Victoria Park",
    "wof:placetype":"venue"
},
  "geometry": {"coordinates":[-1.4809499979,52.4105567932],"type":"Point"}
}