{
  "type": "Feature",
  "properties": {
    "iso:country":"GB",
    "sg:address":"Unit 1, The Gate House, Gorleston-on-sea",
    "sg:city":"Great Yarmouth",
    "sg:classifiers":[
        {
            "category":"Shopping",
            "subcategory":"Mobile Phones",
            "type":"Retail Goods"
        }
    ],
    "sg:phone":"+44 1493 655429",
    "sg:postcode":"NR31 6BE",
    "sg:province":"Norfolk",
    "wof:name":"Starcom Rentals Ltd.",
    "wof:placetype":"venue"
},
  "geometry": {"coordinates":[1.7265150547,52.5690307617],"type":"Point"}
}