{
  "type": "Feature",
  "properties": {
    "addr:full":"Barrow Farm, Bearwood Leominster Herefordshire HR6 9EQ",
    "addr:postcode":"hr6 9eq",
    "addr:street":"Bearwood",
    "iso:country":"GB",
    "sg:address":"Barrow Farm, Bearwood",
    "sg:city":"Leominster",
    "sg:classifiers":[
        {
            "category":"Farming",
            "subcategory":"Livestock Farm",
            "type":"Manufacturing & Wholesale Goods"
        }
    ],
    "sg:phone":"+44 1544 388272",
    "sg:postcode":"HR6 9EQ",
    "sg:province":"Herefordshire",
    "sg:tags":[
        "others"
    ],
    "wof:name":"John K Morgan",
    "wof:placetype":"venue"
},
  "geometry": {"coordinates":[-2.905704,52.200634],"type":"Point"}
}