{
  "type": "Feature",
  "properties": {
    "addr:full":"Hereford Rd, Bayston Hill Shrewsbury Shropshire SY3 0AD",
    "addr:postcode":"sy3 0ad",
    "addr:street":"Hereford Rd",
    "iso:country":"GB",
    "sg:address":"Hereford Rd, Bayston Hill",
    "sg:city":"Shrewsbury",
    "sg:classifiers":[
        {
            "category":"Fast Food",
            "type":"Food & Drink"
        }
    ],
    "sg:phone":"+44 1743 874041",
    "sg:postcode":"SY3 0AD",
    "sg:province":"Shropshire",
    "sg:tags":[
        "away",
        "take"
    ],
    "wof:name":"Burger King",
    "wof:placetype":"venue"
},
  "geometry": {"coordinates":[-2.758274,52.681969],"type":"Point"}
}