{
  "type": "Feature",
  "properties": {
    "addr:full":"Queens Chambers, North Street Newport Newport NP20 1TE",
    "addr:postcode":"np20 1te",
    "addr:street":"North Street",
    "iso:country":"GB",
    "sg:address":"Queens Chambers, North Street",
    "sg:city":"Newport",
    "sg:classifiers":[
        {
            "category":"Professional",
            "subcategory":"Lawyer & Legal Services",
            "type":"Services"
        }
    ],
    "sg:postcode":"NP20 1TE",
    "sg:province":"Newport",
    "sg:tags":[
        "solicitor"
    ],
    "wof:name":"Harding Evans",
    "wof:placetype":"venue"
},
  "geometry": {"coordinates":[-2.9983799458,51.5872993469],"type":"Point"}
}