{
  "type": "Feature",
  "properties": {
    "iso:country":"GB",
    "sg:address":"4 Cherry Close",
    "sg:city":"Canvey Island",
    "sg:classifiers":[
        {
            "category":"Personal",
            "type":"Services"
        }
    ],
    "sg:phone":"+44 1268 682981",
    "sg:postcode":"SS8 9HT",
    "sg:province":"Essex",
    "sg:tags":[
        "kiss-o-grams"
    ],
    "wof:name":"Heart-Throbkissograms",
    "wof:placetype":"venue"
},
  "geometry": {"coordinates":[0.5720229745,51.5229988098],"type":"Point"}
}