{
  "type": "Feature",
  "properties": {
    "iso:country":"GB",
    "sg:address":"33 West Sunniside",
    "sg:city":"Sunderland",
    "sg:classifiers":[
        {
            "category":"Real Estate",
            "subcategory":"Real Estate Agent",
            "type":"Services"
        }
    ],
    "sg:phone":"+44 191 565 7691",
    "sg:postcode":"SR1 1BU",
    "sg:province":"Tyne and Wear",
    "wof:name":"William Dean & Co",
    "wof:placetype":"venue"
},
  "geometry": {"coordinates":[-1.378428,54.906143],"type":"Point"}
}