{
  "type": "Feature",
  "properties": {
    "addr:full":"Garthdee Rd Aberdeen Aberdeen City AB10 7AP",
    "addr:postcode":"ab10 7ap",
    "addr:street":"Garthdee Rd",
    "iso:country":"GB",
    "sg:address":"Garthdee Rd",
    "sg:city":"Aberdeen",
    "sg:classifiers":[
        {
            "category":"Bars & Pubs",
            "type":"Food & Drink"
        },
        {
            "category":"Community Center",
            "subcategory":"Social",
            "type":"Public Place"
        }
    ],
    "sg:phone":"+44 1224 321720",
    "sg:postcode":"AB10 7AP",
    "sg:province":"Aberdeen City",
    "sg:tags":[
        "pubs",
        "house",
        "inn",
        "activity"
    ],
    "wof:name":"ALLOA PUBS & RESTAURANTS LTD",
    "wof:placetype":"venue"
},
  "geometry": {"coordinates":[-2.1280601025,57.1204299927],"type":"Point"}
}