{
  "type": "Feature",
  "properties": {
    "addr:full":"First Floor, Ashford House Ashford Kent TN23 1YB",
    "addr:postcode":"tn23 1yb",
    "iso:country":"GB",
    "sg:address":"First Floor, Ashford House",
    "sg:city":"Ashford",
    "sg:classifiers":[
        {
            "category":"Government",
            "subcategory":"Court House",
            "type":"Public Place"
        }
    ],
    "sg:phone":"+44 1233 621346",
    "sg:postcode":"TN23 1YB",
    "sg:province":"Kent",
    "wof:name":"Employment Tribunals Services",
    "wof:placetype":"venue"
},
  "geometry": {"coordinates":[0.876037,51.146633],"type":"Point"}
}