{
  "type": "Feature",
  "properties": {
    "addr:full":"95 High Street Teddington Greater London TW11 8HG",
    "addr:housenumber":"95",
    "addr:postcode":"tw11 8hg",
    "addr:street":"High Street",
    "iso:country":"GB",
    "sg:address":"95 High Street",
    "sg:city":"Teddington",
    "sg:classifiers":[
        {
            "category":"Personal",
            "subcategory":"Nail Salon",
            "type":"Services"
        }
    ],
    "sg:phone":"+44 20 8977 7749",
    "sg:postcode":"TW11 8HG",
    "sg:province":"Greater London",
    "sg:tags":[
        "solarium",
        "tanning"
    ],
    "wof:name":"The Tanning Centre",
    "wof:placetype":"venue"
},
  "geometry": {"coordinates":[-0.329317987,51.4273948669],"type":"Point"}
}