{
  "type": "Feature",
  "properties": {
    "iso:country":"GB",
    "sg:address":"49 Keyford",
    "sg:city":"Frome",
    "sg:classifiers":[
        {
            "category":"Manufacturing",
            "subcategory":"Wood Products",
            "type":"Manufacturing & Wholesale Goods"
        }
    ],
    "sg:postcode":"BA11 1LB",
    "sg:province":"Somerset",
    "sg:tags":[
        "maker",
        "cabinet"
    ],
    "wof:name":"Copperfield Interiors",
    "wof:placetype":"venue"
},
  "geometry": {"coordinates":[-2.321597,51.225056],"type":"Point"}
}