{
  "type": "Feature",
  "properties": {
    "addr:full":"4/5 Fowlers Arcade, 11 Connaught Avenue Frinton-on-sea Essex CO13 9PN",
    "addr:housenumber":"4 / 5 fowlers;11",
    "addr:postcode":"co13 9pn",
    "addr:street":"Connaught Avenue",
    "iso:country":"GB",
    "sg:address":"4/5 Fowlers Arcade, 11 Connaught Avenue",
    "sg:city":"Frinton-on-sea",
    "sg:classifiers":[
        {
            "category":"Personal",
            "type":"Services"
        },
        {
            "category":"Autos & Motor Vehicles",
            "subcategory":"Auto Supplies",
            "type":"Retail Goods"
        }
    ],
    "sg:phone":"+44 1255 672290",
    "sg:postcode":"CO13 9PN",
    "sg:province":"Essex",
    "sg:tags":[
        "dressmaker",
        "audio",
        "car"
    ],
    "wof:name":"Xclusive",
    "wof:placetype":"venue"
},
  "geometry": {"coordinates":[1.2419110537,51.8380317688],"type":"Point"}
}