{
  "type": "Feature",
  "properties": {
    "addr:full":"Townsend Lane Harpenden Hertfordshire AL5 2RH",
    "addr:postcode":"al5 2rh",
    "addr:street":"Townsend Lane",
    "iso:country":"GB",
    "sg:address":"Townsend Lane",
    "sg:city":"Harpenden",
    "sg:classifiers":[
        {
            "category":"Home & Garden",
            "subcategory":"Garden Supply",
            "type":"Retail Goods"
        }
    ],
    "sg:phone":"+44 1582 713083",
    "sg:postcode":"AL5 2RH",
    "sg:province":"Hertfordshire",
    "sg:tags":[
        "nursery",
        "centre"
    ],
    "wof:name":"Townsend Nursery & Mowers",
    "wof:placetype":"venue"
},
  "geometry": {"coordinates":[-0.359864,51.819107],"type":"Point"}
}