{
  "type": "Feature",
  "properties": {
    "addr:full":"90 Camden High Street London Greater London NW1 0LT",
    "addr:housenumber":"90",
    "addr:postcode":"nw1 0lt",
    "addr:street":"Camden High Street",
    "iso:country":"GB",
    "sg:address":"90 Camden High Street",
    "sg:city":"London",
    "sg:classifiers":[
        {
            "category":"Shopping",
            "subcategory":"Pawn Shop",
            "type":"Retail Goods"
        }
    ],
    "sg:phone":"+44 20 7388 7175",
    "sg:postcode":"NW1 0LT",
    "sg:province":"Greater London",
    "sg:tags":[
        "pawnbroker"
    ],
    "wof:name":"Mybond Pawnbrokers Ltd.",
    "wof:placetype":"venue"
},
  "geometry": {"coordinates":[-0.140647,51.536987],"type":"Point"}
}