{
  "type": "Feature",
  "properties": {
    "iso:country":"GB",
    "sg:address":"15 Stafford Leys, Leicester Forest East",
    "sg:city":"Leicester",
    "sg:classifiers":[
        {
            "category":"Building & Trades",
            "subcategory":"Construction",
            "type":"Services"
        }
    ],
    "sg:phone":"+44 116 299 8648",
    "sg:postcode":"LE3 3LJ",
    "sg:province":"Leicestershire",
    "sg:tags":[
        "guttering"
    ],
    "wof:name":"House Martin Plastics",
    "wof:placetype":"venue"
},
  "geometry": {"coordinates":[-1.2212510109,52.6227874756],"type":"Point"}
}