{
  "type": "Feature",
  "properties": {
    "iso:country":"GB",
    "sg:address":"Fairfax Rd",
    "sg:city":"Leeds",
    "sg:classifiers":[
        {
            "category":"Retail",
            "subcategory":"Funeral Services",
            "type":"Services"
        }
    ],
    "sg:phone":"+44 113 267 3188",
    "sg:postcode":"LS11 8SY",
    "sg:province":"West Yorkshire",
    "sg:tags":[
        "cemetery",
        "crematorium"
    ],
    "wof:name":"Holbeck Cemetery",
    "wof:placetype":"venue"
},
  "geometry": {"coordinates":[-1.559339,53.778278],"type":"Point"}
}