{
  "type": "Feature",
  "properties": {
    "iso:country":"GB",
    "sg:address":"The Thatch Cottage, Honeypot Lane",
    "sg:city":"Manningtree",
    "sg:classifiers":[
        {
            "category":"Farming",
            "subcategory":"Livestock Farm",
            "type":"Manufacturing & Wholesale Goods"
        }
    ],
    "sg:phone":"+44 1255 870665",
    "sg:postcode":"CO11 2RL",
    "sg:province":"Essex",
    "sg:tags":[
        "others"
    ],
    "wof:name":"J R A Cooper",
    "wof:placetype":"venue"
},
  "geometry": {"coordinates":[1.0630400181,51.9453811646],"type":"Point"}
}