{
  "type": "Feature",
  "properties": {
    "addr:full":"Blairnyle Farm, Gartocharn Alexandria Argyll and Bute G83 8RR",
    "addr:postcode":"g83 8rr",
    "iso:country":"GB",
    "sg:address":"Blairnyle Farm, Gartocharn",
    "sg:city":"Alexandria",
    "sg:classifiers":[
        {
            "category":"Farming",
            "subcategory":"Livestock Farm",
            "type":"Manufacturing & Wholesale Goods"
        }
    ],
    "sg:phone":"+44 1389 752677",
    "sg:postcode":"G83 8RR",
    "sg:province":"Argyll and Bute",
    "sg:tags":[
        "others"
    ],
    "wof:name":"A J Allan (Blairnyle) Ltd.",
    "wof:placetype":"venue"
},
  "geometry": {"coordinates":[-4.5308089256,56.0404052734],"type":"Point"}
}