{
  "type": "Feature",
  "properties": {
    "addr:full":"41-51 High Bridge Newcastle Upon Tyne Tyne and Wear NE1 1EW",
    "addr:housenumber":"41-51",
    "addr:postcode":"ne1 1ew",
    "addr:street":"High Bridge",
    "iso:country":"GB",
    "sg:address":"41-51 High Bridge",
    "sg:city":"Newcastle Upon Tyne",
    "sg:classifiers":[
        {
            "category":"Bars & Pubs",
            "type":"Food & Drink"
        }
    ],
    "sg:phone":"+44 191 261 1374",
    "sg:postcode":"NE1 1EW",
    "sg:province":"Tyne and Wear",
    "sg:tags":[
        "pubs",
        "inn"
    ],
    "wof:name":"Rat & Parrot",
    "wof:placetype":"venue"
},
  "geometry": {"coordinates":[-1.612612009,54.9720726013],"type":"Point"}
}