{
  "type": "Feature",
  "properties": {
    "iso:country":"GB",
    "sg:address":"64 Salisbury Road, Wavertree",
    "sg:city":"Liverpool",
    "sg:classifiers":[
        {
            "category":"Social Services",
            "subcategory":"Retirement Home",
            "type":"Services"
        }
    ],
    "sg:phone":"+44 151 482 1088",
    "sg:postcode":"L15 1HW",
    "sg:province":"Merseyside",
    "sg:tags":[
        "residential",
        "care"
    ],
    "wof:name":"Robinson Tyrrell",
    "wof:placetype":"venue"
},
  "geometry": {"coordinates":[-2.9381039143,53.3992424011],"type":"Point"}
}