{
  "type": "Feature",
  "properties": {
    "addr:full":"52 New Inn Hall St Oxford Oxfordshire OX1 2QA",
    "addr:housenumber":"52",
    "addr:postcode":"ox1 2qa",
    "addr:street":"New Inn Hall St",
    "iso:country":"GB",
    "sg:address":"52 New Inn Hall St",
    "sg:city":"Oxford",
    "sg:classifiers":[
        {
            "category":"Professional",
            "subcategory":"Lawyer & Legal Services",
            "type":"Services"
        }
    ],
    "sg:phone":"+44 1865 247294",
    "sg:postcode":"OX1 2QA",
    "sg:province":"Oxfordshire",
    "sg:tags":[
        "solicitor"
    ],
    "wof:name":"Darbys",
    "wof:placetype":"venue"
},
  "geometry": {"coordinates":[-1.26064,51.753426],"type":"Point"}
}