{
  "type": "Feature",
  "properties": {
    "iso:country":"GB",
    "sg:address":"18 Somerford Pl",
    "sg:city":"Willenhall",
    "sg:classifiers":[
        {
            "category":"Building & Trades",
            "subcategory":"Plumbing",
            "type":"Services"
        }
    ],
    "sg:phone":"+44 1902 608128",
    "sg:postcode":"WV13 3DT",
    "sg:province":"West Midlands",
    "sg:tags":[
        "heating"
    ],
    "wof:name":"N Cope",
    "wof:placetype":"venue"
},
  "geometry": {"coordinates":[-2.065045,52.583195],"type":"Point"}
}