{
  "type": "Feature",
  "properties": {
    "iso:country":"GB",
    "sg:address":"High Sunbrick Farm, Sunbrick",
    "sg:city":"Ulverston",
    "sg:classifiers":[
        {
            "category":"Farming",
            "subcategory":"Dairy Farm",
            "type":"Manufacturing & Wholesale Goods"
        },
        {
            "category":"Farming",
            "subcategory":"Farm",
            "type":"Manufacturing & Wholesale Goods"
        }
    ],
    "sg:phone":"+44 1229 869303",
    "sg:postcode":"LA12 9RE",
    "sg:province":"Cumbria",
    "sg:tags":[
        "mixed",
        "crop"
    ],
    "wof:name":"R J Parker",
    "wof:placetype":"venue"
},
  "geometry": {"coordinates":[-3.092257,54.155155],"type":"Point"}
}