{
  "type": "Feature",
  "properties": {
    "addr:full":"245 High Road Chigwell Essex IG7 5BL",
    "addr:housenumber":"245",
    "addr:postcode":"ig7 5bl",
    "addr:street":"High Road",
    "iso:country":"GB",
    "sg:address":"245 High Road",
    "sg:city":"Chigwell",
    "sg:classifiers":[
        {
            "category":"Home & Garden",
            "subcategory":"Garden Supply",
            "type":"Retail Goods"
        }
    ],
    "sg:phone":"+44 20 8500 2690",
    "sg:postcode":"IG7 5BL",
    "sg:province":"Essex",
    "sg:tags":[
        "nursery",
        "centre"
    ],
    "wof:name":"Chigwell Nursery",
    "wof:placetype":"venue"
},
  "geometry": {"coordinates":[0.067479,51.612595],"type":"Point"}
}