{
  "type": "Feature",
  "properties": {
    "addr:full":"14 Bassett Wood Dr Southampton Hampshire SO16 3PT",
    "addr:housenumber":"14",
    "addr:postcode":"so16 3pt",
    "addr:street":"Bassett Wood Dr",
    "iso:country":"GB",
    "sg:address":"14 Bassett Wood Dr",
    "sg:city":"Southampton",
    "sg:classifiers":[
        {
            "category":"Real Estate",
            "subcategory":"Surveying",
            "type":"Services"
        }
    ],
    "sg:phone":"+44 23 8076 8620",
    "sg:postcode":"SO16 3PT",
    "sg:province":"Hampshire",
    "sg:tags":[
        "surveyor",
        "valuer"
    ],
    "wof:name":"Michael Horton",
    "wof:placetype":"venue"
},
  "geometry": {"coordinates":[-1.403651,50.948547],"type":"Point"}
}