{
  "type": "Feature",
  "properties": {
    "iso:country":"GB",
    "sg:address":"55 Gurney Court Road",
    "sg:city":"St Albans",
    "sg:classifiers":[
        {
            "category":"Education",
            "subcategory":"Music School",
            "type":"Public Place"
        }
    ],
    "sg:phone":"+44 1727 858307",
    "sg:postcode":"AL1 4QU",
    "sg:province":"Hertfordshire",
    "sg:tags":[
        "teacher"
    ],
    "wof:name":"Phyllis Swindlehurst",
    "wof:placetype":"venue"
},
  "geometry": {"coordinates":[-0.321026,51.761215],"type":"Point"}
}