{
  "type": "Feature",
  "properties": {
    "addr:full":"345 Green Lane Ilford Essex IG3 9TH",
    "addr:housenumber":"345",
    "addr:postcode":"ig3 9th",
    "addr:street":"Green Lane",
    "iso:country":"GB",
    "sg:address":"345 Green Lane",
    "sg:city":"Ilford",
    "sg:classifiers":[
        {
            "category":"Government",
            "subcategory":"Customs House",
            "type":"Public Place"
        }
    ],
    "sg:postcode":"IG3 9TH",
    "sg:province":"Essex",
    "sg:tags":[
        "clearance"
    ],
    "wof:name":"Past Present & Future",
    "wof:placetype":"venue"
},
  "geometry": {"coordinates":[0.098851,51.561035],"type":"Point"}
}