{
  "type": "Feature",
  "properties": {
    "addr:full":"Dick Lane, Tyersal Bradford West Yorkshire BD4 8LA",
    "addr:postcode":"bd4 8la",
    "addr:street":"Dick Lane Tyersal Bradford West",
    "iso:country":"GB",
    "sg:address":"Dick Lane, Tyersal",
    "sg:city":"Bradford",
    "sg:classifiers":[
        {
            "category":"Autos & Motor Vehicles",
            "subcategory":"Fuel & Gas Station",
            "type":"Retail Goods"
        }
    ],
    "sg:phone":"+44 1274 660536",
    "sg:postcode":"BD4 8LA",
    "sg:province":"West Yorkshire",
    "sg:tags":[
        "petrol",
        "filling"
    ],
    "wof:name":"Save Service Station",
    "wof:placetype":"venue"
},
  "geometry": {"coordinates":[-1.711444,53.790726],"type":"Point"}
}