{
  "type": "Feature",
  "properties": {
    "iso:country":"GB",
    "sg:address":"Walshaw Street",
    "sg:city":"Oldham",
    "sg:classifiers":[
        {
            "category":"Bus Charters",
            "type":"Transportation"
        }
    ],
    "sg:phone":"+44 161 627 7255",
    "sg:postcode":"OL1 3TR",
    "sg:province":"Lancashire",
    "sg:tags":[
        "coach"
    ],
    "wof:name":"First Manchester Ltd.",
    "wof:placetype":"venue"
},
  "geometry": {"coordinates":[-2.106159,53.545235],"type":"Point"}
}