{
  "type": "Feature",
  "properties": {
    "addr:full":"102 St. Helens Link Way St. Helens Cheshire WA9 5DT",
    "addr:housenumber":"102",
    "addr:postcode":"wa9 5dt",
    "addr:street":"St. Helens Link Way",
    "iso:country":"GB",
    "sg:address":"102 St. Helens Link Way",
    "sg:city":"St. Helens",
    "sg:classifiers":[
        {
            "category":"Autos & Motor Vehicles",
            "subcategory":"Fuel & Gas Station",
            "type":"Retail Goods"
        }
    ],
    "sg:phone":"+44 1744 454977",
    "sg:postcode":"WA9 5DT",
    "sg:province":"Cheshire",
    "sg:tags":[
        "hr",
        "petrol"
    ],
    "wof:name":"Sherdley Park Service Station",
    "wof:placetype":"venue"
},
  "geometry": {"coordinates":[-2.73350811,53.4398269653],"type":"Point"}
}