{
  "type": "Feature",
  "properties": {
    "addr:full":"28 New Road, Rufford Ormskirk Lancashire L40 1SR",
    "addr:housenumber":"28",
    "addr:postcode":"l40 1sr",
    "addr:street":"New Road",
    "iso:country":"GB",
    "sg:address":"28 New Road, Rufford",
    "sg:city":"Ormskirk",
    "sg:classifiers":[
        {
            "category":"Building & Trades",
            "subcategory":"Landscaping Services",
            "type":"Services"
        }
    ],
    "sg:postcode":"L40 1SR",
    "sg:province":"Lancashire",
    "sg:tags":[
        "forestry",
        "tree"
    ],
    "wof:name":"Rufford Tree Services",
    "wof:placetype":"venue"
},
  "geometry": {"coordinates":[-2.820037,53.633411],"type":"Point"}
}