{
  "type": "Feature",
  "properties": {
    "iso:country":"GB",
    "sg:address":"The Old Mill,litcham Rd, Gayton",
    "sg:city":"King's Lynn",
    "sg:classifiers":[
        {
            "category":"Professional",
            "subcategory":"Detective & Security Services",
            "type":"Services"
        }
    ],
    "sg:postcode":"PE32 1PQ",
    "sg:province":"Norfolk",
    "wof:name":"Hysec",
    "wof:placetype":"venue"
},
  "geometry": {"coordinates":[0.5648800135,52.7433204651],"type":"Point"}
}