{
  "type": "Feature",
  "properties": {
    "iso:country":"GB",
    "sg:address":"The Warehouse Studio, Glaziers Lane, Culcheth",
    "sg:city":"Warrington",
    "sg:classifiers":[
        {
            "category":"Professional",
            "subcategory":"Employment Agencies",
            "type":"Services"
        }
    ],
    "sg:phone":"+44 1925 767574",
    "sg:postcode":"WA3 4AQ",
    "sg:province":"Cheshire",
    "sg:tags":[
        "modelling"
    ],
    "wof:name":"Euro Kids & Adult International Casting & Model Ag",
    "wof:placetype":"venue"
},
  "geometry": {"coordinates":[-2.522873,53.453735],"type":"Point"}
}