{
  "type": "Feature",
  "properties": {
    "iso:country":"GB",
    "sg:address":"50 Selly Hill Rd",
    "sg:city":"Birmingham",
    "sg:classifiers":[
        {
            "category":"Autos & Motor Vehicles",
            "subcategory":"Auto Supplies",
            "type":"Retail Goods"
        }
    ],
    "sg:phone":"+44 121 471 4702",
    "sg:postcode":"B29 7DL",
    "sg:province":"West Midlands",
    "sg:tags":[
        "tyre"
    ],
    "wof:name":"Longbridge Tyres",
    "wof:placetype":"venue"
},
  "geometry": {"coordinates":[-1.920391,52.443451],"type":"Point"}
}