{
  "type": "Feature",
  "properties": {
    "iso:country":"GB",
    "sg:address":"King John Bank, Walpole St Andrew",
    "sg:city":"Wisbech",
    "sg:classifiers":[
        {
            "category":"Building & Trades",
            "subcategory":"Cleaning & Sanitation",
            "type":"Services"
        }
    ],
    "sg:postcode":"PE14 7JT",
    "sg:province":"Cambridgeshire",
    "sg:tags":[
        "commercial"
    ],
    "wof:name":"Sureclean Chemical & Hygiene Services",
    "wof:placetype":"venue"
},
  "geometry": {"coordinates":[0.203665,52.745731],"type":"Point"}
}