{
  "type": "Feature",
  "properties": {
    "addr:full":"58 Lodge Lane Liverpool Merseyside L8 0QL",
    "addr:housenumber":"58",
    "addr:postcode":"l8 0ql",
    "addr:street":"Lodge Lane",
    "iso:country":"GB",
    "sg:address":"58 Lodge Lane",
    "sg:city":"Liverpool",
    "sg:classifiers":[
        {
            "category":"Bars & Pubs",
            "type":"Food & Drink"
        }
    ],
    "sg:phone":"+44 151 709 1381",
    "sg:postcode":"L8 0QL",
    "sg:province":"Merseyside",
    "sg:tags":[
        "pubs",
        "inn"
    ],
    "wof:name":"Grapes Hotel",
    "wof:placetype":"venue"
},
  "geometry": {"coordinates":[-2.9497139454,53.3956565857],"type":"Point"}
}