{
  "type": "Feature",
  "properties": {
    "addr:full":"31 Swanley Centre Swanley Kent BR8 7TL",
    "addr:housenumber":"31",
    "addr:postcode":"br8 7tl",
    "addr:street":"Swanley Centre",
    "iso:country":"GB",
    "sg:address":"31 Swanley Centre",
    "sg:city":"Swanley",
    "sg:classifiers":[
        {
            "category":"Health Services",
            "subcategory":"Optometrist",
            "type":"Services"
        }
    ],
    "sg:postcode":"BR8 7TL",
    "sg:province":"Kent",
    "sg:tags":[
        "optician"
    ],
    "wof:name":"Robert Murrell Opticians",
    "wof:placetype":"venue"
},
  "geometry": {"coordinates":[0.1781450063,51.3970832825],"type":"Point"}
}