{
  "type": "Feature",
  "properties": {
    "addr:full":"Alexandra House, 5 Blyth Road Bromley Kent BR1 3RS",
    "addr:housenumber":"5",
    "addr:postcode":"br1 3rs",
    "addr:street":"Blyth Road",
    "iso:country":"GB",
    "sg:address":"Alexandra House, 5 Blyth Road",
    "sg:city":"Bromley",
    "sg:classifiers":[
        {
            "category":"Professional",
            "subcategory":"Management & Consulting",
            "type":"Services"
        }
    ],
    "sg:phone":"+44 20 8290 5629",
    "sg:postcode":"BR1 3RS",
    "sg:province":"Kent",
    "sg:tags":[
        "environmental",
        "consultant"
    ],
    "wof:name":"D & H Shah",
    "wof:placetype":"venue"
},
  "geometry": {"coordinates":[0.0091110002,51.4091339111],"type":"Point"}
}