{
  "type": "Feature",
  "properties": {
    "iso:country":"GB",
    "sg:address":"102 Loyd Road",
    "sg:city":"Didcot",
    "sg:classifiers":[
        {
            "category":"Building & Trades",
            "subcategory":"Plumbing",
            "type":"Services"
        }
    ],
    "sg:phone":"+44 1235 814180",
    "sg:postcode":"OX11 8JS",
    "sg:province":"Oxfordshire",
    "sg:tags":[
        "central",
        "heating"
    ],
    "wof:name":"A.C. Heating",
    "wof:placetype":"venue"
},
  "geometry": {"coordinates":[-1.251184,51.596565],"type":"Point"}
}