{
  "type": "Feature",
  "properties": {
    "addr:full":"29 Poplar Drive, Witton Birmingham West Midlands B6 7AD",
    "addr:housenumber":"29",
    "addr:postcode":"b6 7ad",
    "addr:street":"Poplar Drive",
    "iso:country":"GB",
    "sg:address":"29 Poplar Drive, Witton",
    "sg:city":"Birmingham",
    "sg:classifiers":[
        {
            "category":"Manufacturing",
            "subcategory":"Tools & Machinery",
            "type":"Manufacturing & Wholesale Goods"
        },
        {
            "category":"Professional",
            "subcategory":"Engineering",
            "type":"Services"
        }
    ],
    "sg:phone":"+44 121 356 3378",
    "sg:postcode":"B6 7AD",
    "sg:province":"West Midlands",
    "sg:tags":[
        "manufacturer"
    ],
    "wof:name":"G & D Vickers (Engineering) Ltd.",
    "wof:placetype":"venue"
},
  "geometry": {"coordinates":[-1.880706,52.514698],"type":"Point"}
}