{
  "type": "Feature",
  "properties": {
    "addr:full":"250 Milkwood Rd Herne Hill Greater London SE24 0HG",
    "addr:housenumber":"250",
    "addr:postcode":"se24 0hg",
    "addr:street":"Milkwood Rd",
    "iso:country":"GB",
    "sg:address":"250 Milkwood Rd",
    "sg:city":"Herne Hill",
    "sg:classifiers":[
        {
            "category":"Communications",
            "type":"Services"
        }
    ],
    "sg:phone":"+44 20 7738 5599",
    "sg:postcode":"SE24 0HG",
    "sg:province":"Greater London",
    "sg:tags":[
        "telecommunication"
    ],
    "wof:name":"Digital Transmission Cabling Ltd",
    "wof:placetype":"venue"
},
  "geometry": {"coordinates":[-0.1025300026,51.4589958191],"type":"Point"}
}