{
  "type": "Feature",
  "properties": {
    "iso:country":"GB",
    "sg:address":"32 Bell Hill, Finedon",
    "sg:city":"Wellingborough",
    "sg:classifiers":[
        {
            "category":"Bars & Pubs",
            "type":"Food & Drink"
        },
        {
            "category":"Community Center",
            "subcategory":"Social",
            "type":"Public Place"
        }
    ],
    "sg:phone":"+44 1933 680332",
    "sg:postcode":"NN9 5ND",
    "sg:province":"Northamptonshire",
    "sg:tags":[
        "pubs",
        "house",
        "inn",
        "activity"
    ],
    "wof:name":"Bell Inn",
    "wof:placetype":"venue"
},
  "geometry": {"coordinates":[-0.6589609981,52.3360748291],"type":"Point"}
}