{
  "type": "Feature",
  "properties": {
    "iso:country":"GB",
    "sg:address":"73 Abbey Rd",
    "sg:city":"St John's Wood",
    "sg:classifiers":[
        {
            "category":"Travel",
            "subcategory":"Travel Agent",
            "type":"Entertainment"
        }
    ],
    "sg:phone":"+44 20 7328 3399",
    "sg:postcode":"NW8 0AE",
    "sg:province":"Greater London",
    "wof:name":"Airtraders Travel",
    "wof:placetype":"venue"
},
  "geometry": {"coordinates":[-0.183961,51.537308],"type":"Point"}
}