{
  "type": "Feature",
  "properties": {
    "iso:country":"GB",
    "sg:address":"The Old Granary Ct. Lodge Farm, Darenth Hill",
    "sg:city":"Dartford",
    "sg:classifiers":[
        {
            "category":"Home & Garden",
            "subcategory":"Kitchen Supply",
            "type":"Retail Goods"
        }
    ],
    "sg:phone":"+44 1322 291188",
    "sg:postcode":"DA2 7QY",
    "sg:province":"Kent",
    "sg:tags":[
        "equipment",
        "catering"
    ],
    "wof:name":"Kccj Ltd",
    "wof:placetype":"venue"
},
  "geometry": {"coordinates":[0.2434500009,51.4184608459],"type":"Point"}
}