{
  "type": "Feature",
  "properties": {
    "addr:full":"Quay Accounting, 7a Milburn Road Bournemouth Dorset BH4 9HJ",
    "addr:housenumber":"7a",
    "addr:postcode":"bh4 9hj",
    "addr:street":"Milburn Road",
    "iso:country":"GB",
    "sg:address":"Quay Accounting, 7a Milburn Road",
    "sg:city":"Bournemouth",
    "sg:classifiers":[
        {
            "category":"Professional",
            "subcategory":"Computer Services",
            "type":"Services"
        }
    ],
    "sg:phone":"+44 1202 571157",
    "sg:postcode":"BH4 9HJ",
    "sg:province":"Dorset",
    "sg:tags":[
        "system",
        "software"
    ],
    "wof:name":"P C Tech Co. Ltd.",
    "wof:placetype":"venue"
},
  "geometry": {"coordinates":[-1.9015799761,50.7233200073],"type":"Point"}
}