{
  "type": "Feature",
  "properties": {
    "iso:country":"GB",
    "sg:address":"31 Northumberland Road, Tweedmouth",
    "sg:city":"Berwick-upon-tweed",
    "sg:classifiers":[
        {
            "category":"Building & Trades",
            "subcategory":"Construction",
            "type":"Services"
        }
    ],
    "sg:phone":"+44 1289 304014",
    "sg:postcode":"TD15 2AS",
    "sg:province":"Northumberland",
    "sg:tags":[
        "joinery"
    ],
    "wof:name":"W R M Joinery",
    "wof:placetype":"venue"
},
  "geometry": {"coordinates":[-2.0089,55.759968],"type":"Point"}
}