{
  "type": "Feature",
  "properties": {
    "iso:country":"GB",
    "sg:address":"4 Hunters Ride, Caston",
    "sg:city":"Attleborough",
    "sg:classifiers":[
        {
            "category":"Professional",
            "subcategory":"Computer Services",
            "type":"Services"
        }
    ],
    "sg:phone":"+44 1953 483615",
    "sg:postcode":"NR17 1DE",
    "sg:province":"Norfolk",
    "sg:tags":[
        "consultant"
    ],
    "wof:name":"Professional Computer Support",
    "wof:placetype":"venue"
},
  "geometry": {"coordinates":[0.888042,52.541168],"type":"Point"}
}