{
  "type": "Feature",
  "properties": {
    "iso:country":"GB",
    "sg:address":"Beacon Hill House, Bealings Road, Martlesham",
    "sg:city":"Woodbridge",
    "sg:classifiers":[
        {
            "category":"Real Estate",
            "subcategory":"Real Estate Agent",
            "type":"Services"
        }
    ],
    "sg:postcode":"IP12 4RP",
    "sg:province":"Suffolk",
    "wof:name":"Legrys Property Management",
    "wof:placetype":"venue"
},
  "geometry": {"coordinates":[1.278699,52.071705],"type":"Point"}
}