{
  "type": "Feature",
  "properties": {
    "addr:full":"8 Griffon Centre, Vale Of Leven Indstl Est Dumbarton Argyll and Bute G82 3PD",
    "addr:housenumber":"8",
    "addr:postcode":"g82 3pd",
    "addr:street":"Griffon Centre Vale",
    "iso:country":"GB",
    "sg:address":"8 Griffon Centre, Vale Of Leven Indstl Est",
    "sg:city":"Dumbarton",
    "sg:classifiers":[
        {
            "category":"Manufacturing",
            "subcategory":"Signs",
            "type":"Manufacturing & Wholesale Goods"
        }
    ],
    "sg:phone":"+44 1389 755521",
    "sg:postcode":"G82 3PD",
    "sg:province":"Argyll and Bute",
    "sg:tags":[
        "maker"
    ],
    "wof:name":"Nexen International Ltd",
    "wof:placetype":"venue"
},
  "geometry": {"coordinates":[-4.570166,55.94323],"type":"Point"}
}