{
  "type": "Feature",
  "properties": {
    "iso:country":"GB",
    "sg:address":"51 Fairlands Avenue",
    "sg:city":"Guildford",
    "sg:classifiers":[
        {
            "category":"Personal",
            "subcategory":"Beauty Salon",
            "type":"Services"
        }
    ],
    "sg:phone":"+44 1483 232769",
    "sg:postcode":"GU3 3NB",
    "sg:province":"Surrey",
    "sg:tags":[
        "unisex",
        "hairdresser"
    ],
    "wof:name":"The Hair Inn",
    "wof:placetype":"venue"
},
  "geometry": {"coordinates":[-0.620656,51.262901],"type":"Point"}
}