{
  "type": "Feature",
  "properties": {
    "addr:full":"Ann Posnansky Ct, 311-315 Green Lanes London Greater London N4 2ES",
    "addr:housenumber":"311-315",
    "addr:postcode":"n4 2es",
    "addr:street":"Ct;Green Lanes",
    "iso:country":"GB",
    "sg:address":"Ann Posnansky Ct, 311-315 Green Lanes",
    "sg:city":"London",
    "sg:classifiers":[
        {
            "category":"Social Services",
            "subcategory":"Retirement Home",
            "type":"Services"
        }
    ],
    "sg:phone":"+44 20 8802 0594",
    "sg:postcode":"N4 2ES",
    "sg:province":"Greater London",
    "sg:tags":[
        "residential",
        "care"
    ],
    "wof:name":"J B G Housing Society Ltd",
    "wof:placetype":"venue"
},
  "geometry": {"coordinates":[-0.09492,51.568771],"type":"Point"}
}