{
  "type": "Feature",
  "properties": {
    "addr:full":"127-129 Chester Rd, Streetly Sutton Coldfield Staffordshire B74 2HE",
    "addr:housenumber":"127-129",
    "addr:postcode":"b74 2he",
    "addr:street":"Chester Rd",
    "iso:country":"GB",
    "sg:address":"127-129 Chester Rd, Streetly",
    "sg:city":"Sutton Coldfield",
    "sg:classifiers":[
        {
            "category":"Autos & Motor Vehicles",
            "subcategory":"Automobile Sales",
            "type":"Retail Goods"
        }
    ],
    "sg:postcode":"B74 2HE",
    "sg:province":"Staffordshire",
    "sg:tags":[
        "car"
    ],
    "wof:name":"Meads Garage",
    "wof:placetype":"venue"
},
  "geometry": {"coordinates":[-1.883917,52.577148],"type":"Point"}
}