{
  "type": "Feature",
  "properties": {
    "addr:full":"31 Albion Road Edinburgh City of Edinburgh EH7 5QJ",
    "addr:housenumber":"31",
    "addr:postcode":"eh7 5qj",
    "addr:street":"Albion Road",
    "iso:country":"GB",
    "sg:address":"31 Albion Road",
    "sg:city":"Edinburgh",
    "sg:classifiers":[
        {
            "category":"Building & Trades",
            "subcategory":"Construction",
            "type":"Services"
        }
    ],
    "sg:phone":"+44 131 661 9203",
    "sg:postcode":"EH7 5QJ",
    "sg:province":"City of Edinburgh",
    "sg:tags":[
        "builder"
    ],
    "wof:name":"Alexander M Davidson",
    "wof:placetype":"venue"
},
  "geometry": {"coordinates":[-3.165538,55.960732],"type":"Point"}
}