{
  "type": "Feature",
  "properties": {
    "iso:country":"GB",
    "sg:address":"Commercial Quay, Hope Square",
    "sg:city":"Weymouth",
    "sg:classifiers":[
        {
            "category":"Education",
            "subcategory":"Special Training",
            "type":"Public Place"
        }
    ],
    "sg:phone":"+44 1305 786999",
    "sg:postcode":"DT4 8TR",
    "sg:province":"Dorset",
    "sg:tags":[
        "product",
        "centre"
    ],
    "wof:name":"Paragon Training (Dorset) Ltd.",
    "wof:placetype":"venue"
},
  "geometry": {"coordinates":[-2.456251,50.611012],"type":"Point"}
}