{
  "type": "Feature",
  "properties": {
    "addr:full":"Bakehouse Close, 146 Canongate Edinburgh City of Edinburgh EH8 8DD",
    "addr:housenumber":"146",
    "addr:postcode":"eh8 8dd",
    "addr:street":"Bakehouse Close;Canongate",
    "iso:country":"GB",
    "sg:address":"Bakehouse Close, 146 Canongate",
    "sg:city":"Edinburgh",
    "sg:classifiers":[
        {
            "category":"Banks & Credit Unions",
            "subcategory":"Bureau De Change",
            "type":"Services"
        }
    ],
    "sg:phone":"+44 131 556 6699",
    "sg:postcode":"EH8 8DD",
    "sg:province":"City of Edinburgh",
    "sg:tags":[
        "town",
        "consultant",
        "planning"
    ],
    "wof:name":"Royal Fine Art Commission for Scotland",
    "wof:placetype":"venue"
},
  "geometry": {"coordinates":[-3.18006,55.95126],"type":"Point"}
}