{
  "type": "Feature",
  "properties": {
    "addr:full":"Fitzwarren St Salford Greater Manchester M6 5JF",
    "addr:postcode":"m6 5jf",
    "addr:street":"Fitzwarren St",
    "iso:country":"GB",
    "sg:address":"Fitzwarren St",
    "sg:city":"Salford",
    "sg:classifiers":[
        {
            "category":"Farming",
            "subcategory":"Farm & Veterinary Services",
            "type":"Manufacturing & Wholesale Goods"
        }
    ],
    "sg:phone":"+44 161 745 8282",
    "sg:postcode":"M6 5JF",
    "sg:province":"Greater Manchester",
    "sg:tags":[
        "lampshade",
        "mnfs",
        "distributor"
    ],
    "wof:name":"Sueray Lighting Ltd",
    "wof:placetype":"venue"
},
  "geometry": {"coordinates":[-2.2906739712,53.4877090454],"type":"Point"}
}