{
  "type": "Feature",
  "properties": {
    "iso:country":"GB",
    "sg:address":"Pickford Street",
    "sg:city":"Macclesfield",
    "sg:classifiers":[
        {
            "category":"Sports & Exercise",
            "subcategory":"Gym",
            "type":"Entertainment"
        }
    ],
    "sg:phone":"+44 1625 616125",
    "sg:postcode":"SK11 6HX",
    "sg:province":"Cheshire",
    "sg:tags":[
        "fitness",
        "health",
        "centre"
    ],
    "wof:name":"Dave's Gym and Fitness Centre",
    "wof:placetype":"venue"
},
  "geometry": {"coordinates":[-2.122799,53.257599],"type":"Point"}
}