{
  "type": "Feature",
  "properties": {
    "iso:country":"GB",
    "sg:address":"Knapton Grange, Main Street, Knapton",
    "sg:city":"York",
    "sg:classifiers":[
        {
            "category":"Shopping",
            "subcategory":"Computers & Home Electronics",
            "type":"Retail Goods"
        },
        {
            "category":"Building & Trades",
            "subcategory":"Construction",
            "type":"Services"
        }
    ],
    "sg:phone":"+44 1904 785148",
    "sg:postcode":"YO26 6QG",
    "sg:province":"North Yorkshire",
    "sg:tags":[
        "supplier",
        "radio",
        "television",
        "erectors",
        "aerial"
    ],
    "wof:name":"A A Quick Fix",
    "wof:placetype":"venue"
},
  "geometry": {"coordinates":[-1.1455,53.960674],"type":"Point"}
}