{
  "type": "Feature",
  "properties": {
    "addr:full":"5 Eccleston Street London Greater London SW1W 9LY",
    "addr:housenumber":"5",
    "addr:postcode":"sw1w 9ly",
    "addr:street":"Eccleston Street",
    "iso:country":"GB",
    "sg:address":"5 Eccleston Street",
    "sg:city":"London",
    "sg:classifiers":[
        {
            "category":"Real Estate",
            "subcategory":"Architect",
            "type":"Services"
        }
    ],
    "sg:phone":"+44 20 7730 9633",
    "sg:postcode":"SW1W 9LY",
    "sg:province":"Greater London",
    "wof:name":"Clifford Tee & Gale",
    "wof:placetype":"venue"
},
  "geometry": {"coordinates":[-0.14747,51.494308],"type":"Point"}
}