{
  "type": "Feature",
  "properties": {
    "addr:full":"Glanrafon, Pont Rug Caernarfon Gwynedd LL55 1UB",
    "addr:postcode":"ll55 1ub",
    "iso:country":"GB",
    "sg:address":"Glanrafon, Pont Rug",
    "sg:city":"Caernarfon",
    "sg:classifiers":[
        {
            "category":"Farming",
            "subcategory":"Farm",
            "type":"Manufacturing & Wholesale Goods"
        }
    ],
    "sg:phone":"+44 1286 673207",
    "sg:postcode":"LL55 1UB",
    "sg:province":"Gwynedd",
    "sg:tags":[
        "mixed",
        "crop"
    ],
    "wof:name":"R & E M Pierce",
    "wof:placetype":"venue"
},
  "geometry": {"coordinates":[-4.2718091011,53.1425933838],"type":"Point"}
}