{
  "type": "Feature",
  "properties": {
    "addr:full":"32 Shearman Road, Blackheath London Greater London SE3 9HX",
    "addr:housenumber":"32",
    "addr:postcode":"se3 9hx",
    "addr:street":"Shearman Road",
    "iso:country":"GB",
    "sg:address":"32 Shearman Road, Blackheath",
    "sg:city":"London",
    "sg:classifiers":[
        {
            "category":"Taxi",
            "type":"Transportation"
        }
    ],
    "sg:phone":"+44 20 8852 4621",
    "sg:postcode":"SE3 9HX",
    "sg:province":"Greater London",
    "sg:tags":[
        "toastmaster"
    ],
    "wof:name":"Robert Grosse",
    "wof:placetype":"venue"
},
  "geometry": {"coordinates":[0.008792,51.460751],"type":"Point"}
}