{
  "type": "Feature",
  "properties": {
    "iso:country":"GB",
    "sg:address":"222-226 The Balcony, Central Market",
    "sg:city":"Cardiff",
    "sg:classifiers":[
        {
            "category":"Shopping",
            "subcategory":"Department Store",
            "type":"Retail Goods"
        },
        {
            "category":"Shopping",
            "subcategory":"Music",
            "type":"Retail Goods"
        }
    ],
    "sg:phone":"+44 29 2037 7355",
    "sg:postcode":"CF10 2AU",
    "sg:province":"Cardiff",
    "sg:tags":[
        "record",
        "tape",
        "cd"
    ],
    "wof:name":"Kellys Records",
    "wof:placetype":"venue"
},
  "geometry": {"coordinates":[-3.180669,51.481258],"type":"Point"}
}