{
  "type": "Feature",
  "properties": {
    "iso:country":"GB",
    "sg:address":"24 Sandown Rd",
    "sg:city":"Sandown",
    "sg:classifiers":[
        {
            "category":"Shopping",
            "subcategory":"Florist",
            "type":"Retail Goods"
        }
    ],
    "sg:phone":"+44 1983 403439",
    "sg:postcode":"PO36 9JP",
    "sg:province":"Isle of Wight",
    "wof:name":"Gina's Flower Box",
    "wof:placetype":"venue"
},
  "geometry": {"coordinates":[-1.168102026,50.6480751038],"type":"Point"}
}