{
  "type": "Feature",
  "properties": {
    "iso:country":"GB",
    "sg:address":"Whitworth Rd",
    "sg:city":"London",
    "sg:classifiers":[
        {
            "category":"Education",
            "subcategory":"School",
            "type":"Public Place"
        },
        {
            "category":"Government",
            "subcategory":"Office",
            "type":"Public Place"
        }
    ],
    "sg:phone":"+44 20 8854 3802",
    "sg:postcode":"SE18 3SX",
    "sg:province":"Greater London",
    "sg:tags":[
        "local",
        "authority"
    ],
    "wof:name":"London Borough of Greenwich",
    "wof:placetype":"venue"
},
  "geometry": {"coordinates":[0.06314,51.478378],"type":"Point"}
}