{
  "type": "Feature",
  "properties": {
    "addr:full":"155a Wilmington Gardens Barking Essex IG11 9TT",
    "addr:housenumber":"155a",
    "addr:postcode":"ig11 9tt",
    "addr:street":"Wilmington Gardens",
    "iso:country":"GB",
    "sg:address":"155a Wilmington Gardens",
    "sg:city":"Barking",
    "sg:classifiers":[
        {
            "category":"Building & Trades",
            "subcategory":"Construction",
            "type":"Services"
        }
    ],
    "sg:postcode":"IG11 9TT",
    "sg:province":"Essex",
    "sg:tags":[
        "builder"
    ],
    "wof:name":"A.J. Painters & Decorators Ltd",
    "wof:placetype":"venue"
},
  "geometry": {"coordinates":[0.092701003,51.5385398865],"type":"Point"}
}