{
  "type": "Feature",
  "properties": {
    "iso:country":"GB",
    "sg:address":"16 Westbourne Mansions, Westbourne Crescent",
    "sg:city":"Southampton",
    "sg:classifiers":[
        {
            "category":"Professional",
            "subcategory":"Accounting & Tax Preparation",
            "type":"Services"
        }
    ],
    "sg:phone":"+44 23 8067 2895",
    "sg:postcode":"SO17 1UW",
    "sg:province":"Hampshire",
    "sg:tags":[
        "accountant"
    ],
    "wof:name":"Graeme Anderson",
    "wof:placetype":"venue"
},
  "geometry": {"coordinates":[-1.40337,50.927151],"type":"Point"}
}