{
  "type": "Feature",
  "properties": {
    "addr:full":"55 Eden St Kingston Upon Thames Greater London KT1 1BW",
    "addr:housenumber":"55",
    "addr:postcode":"kt1 1bw",
    "addr:street":"Eden St",
    "iso:country":"GB",
    "sg:address":"55 Eden St",
    "sg:city":"Kingston Upon Thames",
    "sg:classifiers":[
        {
            "category":"Communications",
            "type":"Services"
        }
    ],
    "sg:phone":"+44 20 8549 5415",
    "sg:postcode":"KT1 1BW",
    "sg:province":"Greater London",
    "sg:tags":[
        "audio-visual"
    ],
    "wof:name":"Jordan UK Ltd",
    "wof:placetype":"venue"
},
  "geometry": {"coordinates":[-0.3022840023,51.410533905],"type":"Point"}
}