{
  "type": "Feature",
  "properties": {
    "addr:full":"Unit 2 The Old Dairy, Hazlemere Cross Roads, Hazlemere High Wycombe Buckinghamshire HP15 7LG",
    "addr:housenumber":"unit 2",
    "addr:postcode":"hp15 7lg",
    "addr:street":"The Old;Hazlemere Cross Roads Hazlemere",
    "iso:country":"GB",
    "sg:address":"Unit 2 The Old Dairy, Hazlemere Cross Roads, Hazlemere",
    "sg:city":"High Wycombe",
    "sg:classifiers":[
        {
            "category":"Home & Garden",
            "subcategory":"Hardware",
            "type":"Retail Goods"
        },
        {
            "category":"Building & Trades",
            "subcategory":"Construction",
            "type":"Services"
        }
    ],
    "sg:postcode":"HP15 7LG",
    "sg:province":"Buckinghamshire",
    "sg:tags":[
        "tiling",
        "retailer",
        "diy",
        "contractor"
    ],
    "wof:name":"Alghero Tilecrafts",
    "wof:placetype":"venue"
},
  "geometry": {"coordinates":[-0.708729,51.651031],"type":"Point"}
}