{
  "type": "Feature",
  "properties": {
    "iso:country":"GB",
    "sg:address":"74 Kingsland Rd",
    "sg:city":"Worthing",
    "sg:classifiers":[
        {
            "category":"Retail",
            "subcategory":"Storage",
            "type":"Services"
        }
    ],
    "sg:phone":"+44 1903 215572",
    "sg:postcode":"BN14 9ED",
    "sg:province":"West Sussex",
    "sg:tags":[
        "household",
        "removal"
    ],
    "wof:name":"Fords Removals",
    "wof:placetype":"venue"
},
  "geometry": {"coordinates":[-0.368593,50.829056],"type":"Point"}
}