{
  "type": "Feature",
  "properties": {
    "iso:country":"GB",
    "sg:address":"Long Meadows, West Monkton",
    "sg:city":"Taunton",
    "sg:classifiers":[
        {
            "category":"Utilities",
            "subcategory":"Cable",
            "type":"Services"
        },
        {
            "category":"Military Area",
            "subcategory":"Air Force Base",
            "type":"Public Place"
        }
    ],
    "sg:phone":"+44 1823 412232",
    "sg:postcode":"TA2 8QT",
    "sg:province":"Somerset",
    "sg:tags":[
        "rope",
        "hawser"
    ],
    "wof:name":"G B Nowell",
    "wof:placetype":"venue"
},
  "geometry": {"coordinates":[-3.054035,51.05233],"type":"Point"}
}