{
  "type": "Feature",
  "properties": {
    "addr:full":"25 Marshall Place Perth Perth and Kinross PH2 8AG",
    "addr:housenumber":"25",
    "addr:postcode":"ph2 8ag",
    "addr:street":"Marshall Place",
    "iso:country":"GB",
    "sg:address":"25 Marshall Place",
    "sg:city":"Perth",
    "sg:classifiers":[
        {
            "category":"Travel",
            "subcategory":"Hotels & Motels",
            "type":"Entertainment"
        }
    ],
    "sg:phone":"+44 1738 629610",
    "sg:postcode":"PH2 8AG",
    "sg:province":"Perth and Kinross",
    "sg:tags":[
        "house",
        "guest"
    ],
    "wof:name":"A & A R Young",
    "wof:placetype":"venue"
},
  "geometry": {"coordinates":[-3.4317889214,56.3922843933],"type":"Point"}
}