{
  "type": "Feature",
  "properties": {
    "iso:country":"GB",
    "sg:address":"35 Hathaway Court, Esplanade",
    "sg:city":"Rochester",
    "sg:classifiers":[
        {
            "category":"Professional",
            "subcategory":"Computer Services",
            "type":"Services"
        }
    ],
    "sg:phone":"+44 1634 818324",
    "sg:postcode":"ME1 1QX",
    "sg:province":"Kent",
    "sg:tags":[
        "system",
        "software"
    ],
    "wof:name":"G & K Systems",
    "wof:placetype":"venue"
},
  "geometry": {"coordinates":[0.497481,51.386696],"type":"Point"}
}