{
  "type": "Feature",
  "properties": {
    "iso:country":"GB",
    "sg:address":"45 Silver Road",
    "sg:city":"Street",
    "sg:classifiers":[
        {
            "category":"Food & Beverages",
            "subcategory":"Meat & Fish",
            "type":"Retail Goods"
        },
        {
            "category":"Food & Beverages",
            "subcategory":"Groceries & Convenience Stores",
            "type":"Retail Goods"
        }
    ],
    "sg:phone":"+44 1456 486284",
    "sg:postcode":"BA16 0JR",
    "sg:province":"Somerset",
    "sg:tags":[
        "shop",
        "chip"
    ],
    "wof:name":"The Park Fish Bar",
    "wof:placetype":"venue"
},
  "geometry": {"coordinates":[-2.74228,51.122612],"type":"Point"}
}