{
  "type": "Feature",
  "properties": {
    "addr:full":"139 Kidderminster Road Bewdley Shropshire DY12 1JE",
    "addr:housenumber":"139",
    "addr:postcode":"dy12 1je",
    "addr:street":"Kidderminster Road",
    "iso:country":"GB",
    "sg:address":"139 Kidderminster Road",
    "sg:city":"Bewdley",
    "sg:classifiers":[
        {
            "category":"Bars & Pubs",
            "type":"Food & Drink"
        },
        {
            "category":"Community Center",
            "subcategory":"Social",
            "type":"Public Place"
        }
    ],
    "sg:phone":"+44 1299 404177",
    "sg:postcode":"DY12 1JE",
    "sg:province":"Shropshire",
    "sg:tags":[
        "pubs",
        "house",
        "inn",
        "activity"
    ],
    "wof:name":"Rising Sun Inn",
    "wof:placetype":"venue"
},
  "geometry": {"coordinates":[-2.298646,52.380714],"type":"Point"}
}