{
  "type": "Feature",
  "properties": {
    "addr:full":"34-35 The Mint Rye East Sussex TN31 7EN",
    "addr:housenumber":"34-35",
    "addr:postcode":"tn31 7en",
    "addr:street":"The Mint",
    "iso:country":"GB",
    "sg:address":"34-35 The Mint",
    "sg:city":"Rye",
    "sg:classifiers":[
        {
            "category":"Restaurant",
            "type":"Food & Drink"
        }
    ],
    "sg:postcode":"TN31 7EN",
    "sg:province":"East Sussex",
    "wof:name":"The Copper Kettle",
    "wof:placetype":"venue"
},
  "geometry": {"coordinates":[0.730763,50.950481],"type":"Point"}
}