{
  "type": "Feature",
  "properties": {
    "addr:full":"1 Medway Parade Greenford Greater London UB6 8HN",
    "addr:housenumber":"1",
    "addr:postcode":"ub6 8hn",
    "addr:street":"Medway Parade",
    "iso:country":"GB",
    "sg:address":"1 Medway Parade",
    "sg:city":"Greenford",
    "sg:classifiers":[
        {
            "category":"Fast Food",
            "type":"Food & Drink"
        }
    ],
    "sg:phone":"+44 20 8998 9933",
    "sg:postcode":"UB6 8HN",
    "sg:province":"Greater London",
    "sg:tags":[
        "away",
        "take"
    ],
    "wof:name":"Door to Door Pizza",
    "wof:placetype":"venue"
},
  "geometry": {"coordinates":[-0.333287,51.534401],"type":"Point"}
}