{
  "type": "Feature",
  "properties": {
    "iso:country":"GB",
    "sg:address":"4 Haverstock Rd",
    "sg:city":"Bournemouth",
    "sg:classifiers":[
        {
            "category":"Professional",
            "subcategory":"Advertising",
            "type":"Services"
        }
    ],
    "sg:phone":"+44 1202 523168",
    "sg:postcode":"BH9 3HE",
    "sg:province":"Dorset",
    "sg:tags":[
        "telemarketing"
    ],
    "wof:name":"Tele-direct",
    "wof:placetype":"venue"
},
  "geometry": {"coordinates":[-1.863022,50.752266],"type":"Point"}
}