{
  "type": "Feature",
  "properties": {
    "iso:country":"GB",
    "sg:address":"The Lilacs, Botany Bay, Grangewood",
    "sg:city":"Swadlincote",
    "sg:classifiers":[
        {
            "category":"Home & Garden",
            "subcategory":"Garden Supply",
            "type":"Retail Goods"
        }
    ],
    "sg:phone":"+44 1283 761371",
    "sg:postcode":"DE12 8DY",
    "sg:province":"Derbyshire",
    "sg:tags":[
        "bulb",
        "grower"
    ],
    "wof:name":"John R Goodall",
    "wof:placetype":"venue"
},
  "geometry": {"coordinates":[-1.5866910219,52.7265777588],"type":"Point"}
}