{
  "type": "Feature",
  "properties": {
    "addr:full":"Liquorice Way Pontefract North Yorkshire WF8 1DR",
    "addr:postcode":"wf8 1dr",
    "addr:street":"Liquorice Way",
    "iso:country":"GB",
    "sg:address":"Liquorice Way",
    "sg:city":"Pontefract",
    "sg:classifiers":[
        {
            "category":"Museum",
            "subcategory":"Art Museum",
            "type":"Entertainment"
        },
        {
            "category":"Professional",
            "subcategory":"Art Services",
            "type":"Services"
        }
    ],
    "sg:phone":"+44 1977 795009",
    "sg:postcode":"WF8 1DR",
    "sg:province":"North Yorkshire",
    "sg:tags":[
        "picture",
        "framing",
        "gallery"
    ],
    "wof:name":"Pomfret Gallery",
    "wof:placetype":"venue"
},
  "geometry": {"coordinates":[-1.3131610155,53.6909484863],"type":"Point"}
}