{
  "type": "Feature",
  "properties": {
    "addr:full":"Unit 1, Toll Bar Business Park, Newchurch Road Bacup Lancashire OL13 0NA",
    "addr:housenumber":"unit 1",
    "addr:postcode":"ol13 0na",
    "addr:street":"Toll;Business Park Newchurch Road",
    "iso:country":"GB",
    "sg:address":"Unit 1, Toll Bar Business Park, Newchurch Road",
    "sg:city":"Bacup",
    "sg:classifiers":[
        {
            "category":"Manufacturing",
            "subcategory":"Textiles",
            "type":"Manufacturing & Wholesale Goods"
        }
    ],
    "sg:postcode":"OL13 0NA",
    "sg:province":"Lancashire",
    "sg:tags":[
        "merchant",
        "agent"
    ],
    "wof:name":"Trentham-Cameo Ltd.",
    "wof:placetype":"venue"
},
  "geometry": {"coordinates":[-2.201104,53.702717],"type":"Point"}
}