{
  "type": "Feature",
  "properties": {
    "addr:full":"10 Woodlands Rd Reading Berkshire RG4 9JR",
    "addr:housenumber":"10",
    "addr:postcode":"rg4 9jr",
    "addr:street":"Woodlands Rd",
    "iso:country":"GB",
    "sg:address":"10 Woodlands Rd",
    "sg:city":"Reading",
    "sg:classifiers":[
        {
            "category":"Professional",
            "type":"Services"
        }
    ],
    "sg:phone":"+44 118 972 2184",
    "sg:postcode":"RG4 9JR",
    "sg:province":"Berkshire",
    "sg:tags":[
        "repair",
        "tech",
        "maintenance"
    ],
    "wof:name":"Boulton Electronic Computer Services",
    "wof:placetype":"venue"
},
  "geometry": {"coordinates":[-0.9829649925,51.5186424255],"type":"Point"}
}