{
  "type": "Feature",
  "properties": {
    "iso:country":"GB",
    "sg:address":"Dukesmead House, 39 High Street",
    "sg:city":"Chelmsford",
    "sg:classifiers":[
        {
            "category":"Professional",
            "subcategory":"Business Services",
            "type":"Services"
        }
    ],
    "sg:postcode":"CM1 1DE",
    "sg:province":"Essex",
    "sg:tags":[
        "registrar"
    ],
    "wof:name":"Opus International Group Plc",
    "wof:placetype":"venue"
},
  "geometry": {"coordinates":[0.47379,51.733597],"type":"Point"}
}