{
  "type": "Feature",
  "properties": {
    "addr:full":"54 Helen Street Glasgow Glasgow City G51 3HQ",
    "addr:housenumber":"54",
    "addr:postcode":"g51 3hq",
    "addr:street":"Helen Street",
    "iso:country":"GB",
    "sg:address":"54 Helen Street",
    "sg:city":"Glasgow",
    "sg:classifiers":[
        {
            "category":"Building & Trades",
            "subcategory":"Construction",
            "type":"Services"
        }
    ],
    "sg:phone":"+44 141 425 1133",
    "sg:postcode":"G51 3HQ",
    "sg:province":"Glasgow City",
    "sg:tags":[
        "builder"
    ],
    "wof:name":"Trowel Trades Ltd.",
    "wof:placetype":"venue"
},
  "geometry": {"coordinates":[-4.313108,55.861698],"type":"Point"}
}