{
  "type": "Feature",
  "properties": {
    "iso:country":"GB",
    "sg:address":"12 Englishcombe Lane",
    "sg:city":"Bath",
    "sg:classifiers":[
        {
            "category":"Building & Trades",
            "subcategory":"Construction",
            "type":"Services"
        }
    ],
    "sg:phone":"+44 1225 420154",
    "sg:postcode":"BA2 2ED",
    "sg:province":"Somerset",
    "sg:tags":[
        "builder"
    ],
    "wof:name":"T J Cockle",
    "wof:placetype":"venue"
},
  "geometry": {"coordinates":[-2.3699491024,51.3678016663],"type":"Point"}
}