{
  "type": "Feature",
  "properties": {
    "addr:full":"Birmingham Road, Great Barr Birmingham West Midlands B43 7AG",
    "addr:postcode":"b43 7ag",
    "addr:street":"Birmingham Road",
    "iso:country":"GB",
    "sg:address":"Birmingham Road, Great Barr",
    "sg:city":"Birmingham",
    "sg:classifiers":[
        {
            "category":"Bars & Pubs",
            "type":"Food & Drink"
        },
        {
            "category":"Restaurant",
            "type":"Food & Drink"
        }
    ],
    "sg:phone":"+44 121 357 2567",
    "sg:postcode":"B43 7AG",
    "sg:province":"West Midlands",
    "sg:tags":[
        "pubs",
        "inn"
    ],
    "wof:name":"Beacon Harvester",
    "wof:placetype":"venue"
},
  "geometry": {"coordinates":[-1.937844,52.558727],"type":"Point"}
}