{
  "type": "Feature",
  "properties": {
    "iso:country":"GB",
    "sg:address":"2 Bridge Street",
    "sg:city":"Dunfermline",
    "sg:classifiers":[
        {
            "category":"Shopping",
            "subcategory":"Shoes",
            "type":"Retail Goods"
        }
    ],
    "sg:phone":"+44 1383 620172",
    "sg:postcode":"KY12 8DA",
    "sg:province":"Fife",
    "sg:tags":[
        "shop"
    ],
    "wof:name":"Feet & Co. (Scotland) Ltd.",
    "wof:placetype":"venue"
},
  "geometry": {"coordinates":[-3.4641180038,56.0713539124],"type":"Point"}
}