{
  "type": "Feature",
  "properties": {
    "iso:country":"GB",
    "sg:address":"Woodview, Challacombe",
    "sg:city":"Barnstaple",
    "sg:classifiers":[
        {
            "category":"Home & Garden",
            "subcategory":"Garden Supply",
            "type":"Retail Goods"
        },
        {
            "category":"Farming",
            "subcategory":"Farm",
            "type":"Manufacturing & Wholesale Goods"
        }
    ],
    "sg:phone":"+44 1598 763214",
    "sg:postcode":"EX31 4TS",
    "sg:province":"Devon",
    "sg:tags":[
        "mixed",
        "bulb",
        "crop",
        "grower"
    ],
    "wof:name":"John F Clark",
    "wof:placetype":"venue"
},
  "geometry": {"coordinates":[-3.8697431087,51.1536636353],"type":"Point"}
}