{
  "type": "Feature",
  "properties": {
    "iso:country":"GB",
    "sg:address":"Melton Road",
    "sg:city":"Oakham",
    "sg:classifiers":[
        {
            "category":"Autos & Motor Vehicles",
            "subcategory":"Auto Supplies",
            "type":"Retail Goods"
        }
    ],
    "sg:phone":"+44 1572 723604",
    "sg:postcode":"LE15 6AY",
    "sg:province":"Leicestershire",
    "sg:tags":[
        "towing",
        "eqpt",
        "trailer"
    ],
    "wof:name":"Healey Trailers",
    "wof:placetype":"venue"
},
  "geometry": {"coordinates":[-0.733269,52.670906],"type":"Point"}
}