{
  "type": "Feature",
  "properties": {
    "iso:country":"GB",
    "sg:address":"26b Parsons Street",
    "sg:city":"Banbury",
    "sg:classifiers":[
        {
            "category":"Military Area",
            "subcategory":"Air Force Base",
            "type":"Public Place"
        }
    ],
    "sg:phone":"+44 1295 272020",
    "sg:postcode":"OX16 5LY",
    "sg:province":"Oxfordshire",
    "sg:tags":[
        "taxi",
        "hire",
        "private"
    ],
    "wof:name":"A 1 Taxis",
    "wof:placetype":"venue"
},
  "geometry": {"coordinates":[-1.3359620571,52.0620498657],"type":"Point"}
}