{
  "type": "Feature",
  "properties": {
    "addr:full":"Troupers Lodge Filling Statione, Bourton On The Hill Moreton-in-marsh Gloucestershire GL56 9TE",
    "addr:postcode":"gl56 9te",
    "iso:country":"GB",
    "sg:address":"Troupers Lodge Filling Statione, Bourton On The Hill",
    "sg:city":"Moreton-in-marsh",
    "sg:classifiers":[
        {
            "category":"Autos & Motor Vehicles",
            "subcategory":"Automobile Sales",
            "type":"Retail Goods"
        }
    ],
    "sg:postcode":"GL56 9TE",
    "sg:province":"Gloucestershire",
    "sg:tags":[
        "car"
    ],
    "wof:name":"Cotswold Car Sales",
    "wof:placetype":"venue"
},
  "geometry": {"coordinates":[-1.746314,51.991055],"type":"Point"}
}