{
  "type": "Feature",
  "properties": {
    "addr:full":"1-2 Exchange Arcade, 175 Bishopsgate London Greater London EC2M 3WA",
    "addr:housenumber":"1-2;175",
    "addr:postcode":"ec2m 3wa",
    "addr:street":"Exchange Arcade;Bishopsgate",
    "iso:country":"GB",
    "sg:address":"1-2 Exchange Arcade, 175 Bishopsgate",
    "sg:city":"London",
    "sg:classifiers":[
        {
            "category":"Health Services",
            "subcategory":"Optometrist",
            "type":"Services"
        }
    ],
    "sg:postcode":"EC2M 3WA",
    "sg:province":"Greater London",
    "sg:tags":[
        "optician"
    ],
    "wof:name":"Optix At Broadgate",
    "wof:placetype":"venue"
},
  "geometry": {"coordinates":[-0.08051,51.517521],"type":"Point"}
}