{
  "type": "Feature",
  "properties": {
    "addr:full":"Stocka House Farm, Stocka Houses Bingley West Yorkshire BD16 1UQ",
    "addr:postcode":"bd16 1uq",
    "addr:street":"Stocka;West",
    "iso:country":"GB",
    "sg:address":"Stocka House Farm, Stocka Houses",
    "sg:city":"Bingley",
    "sg:classifiers":[
        {
            "category":"Professional",
            "subcategory":"Engineering",
            "type":"Services"
        }
    ],
    "sg:phone":"+44 1274 498853",
    "sg:postcode":"BD16 1UQ",
    "sg:province":"West Yorkshire",
    "wof:name":"J Proctor & Son",
    "wof:placetype":"venue"
},
  "geometry": {"coordinates":[-1.8389270306,53.8492584229],"type":"Point"}
}