{
  "type": "Feature",
  "properties": {
    "addr:full":"213 Grange Road London Greater London SE1 3AA",
    "addr:housenumber":"213",
    "addr:postcode":"se1 3aa",
    "addr:street":"Grange Road",
    "iso:country":"GB",
    "sg:address":"213 Grange Road",
    "sg:city":"London",
    "sg:classifiers":[
        {
            "category":"Fast Food",
            "type":"Food & Drink"
        }
    ],
    "sg:phone":"+44 20 7237 6388",
    "sg:postcode":"SE1 3AA",
    "sg:province":"Greater London",
    "sg:tags":[
        "away",
        "take"
    ],
    "wof:name":"Chauwah Cheung",
    "wof:placetype":"venue"
},
  "geometry": {"coordinates":[-0.0801720023,51.496383667],"type":"Point"}
}