{
  "type": "Feature",
  "properties": {
    "addr:full":"14 High Street Edinburgh City of Edinburgh EH1 1TE",
    "addr:housenumber":"14",
    "addr:postcode":"eh1 1te",
    "addr:street":"High Street",
    "iso:country":"GB",
    "sg:address":"14 High Street",
    "sg:city":"Edinburgh",
    "sg:classifiers":[
        {
            "category":"Communications",
            "subcategory":"Newspaper",
            "type":"Services"
        }
    ],
    "sg:phone":"+44 131 558 1191",
    "sg:postcode":"EH1 1TE",
    "sg:province":"City of Edinburgh",
    "sg:tags":[
        "magazine"
    ],
    "wof:name":"The List Ltd.",
    "wof:placetype":"venue"
},
  "geometry": {"coordinates":[-3.1846621037,55.9505462646],"type":"Point"}
}