{
  "type": "Feature",
  "properties": {
    "addr:full":"32 Maule Street, Monifieth Dundee Angus DD5 4NR",
    "addr:housenumber":"32",
    "addr:postcode":"dd5 4nr",
    "addr:street":"Maule Street",
    "iso:country":"GB",
    "sg:address":"32 Maule Street, Monifieth",
    "sg:city":"Dundee",
    "sg:classifiers":[
        {
            "category":"Health Services",
            "subcategory":"Dentist",
            "type":"Services"
        }
    ],
    "sg:phone":"+44 1382 532382",
    "sg:postcode":"DD5 4NR",
    "sg:province":"Angus",
    "wof:name":"Mary George",
    "wof:placetype":"venue"
},
  "geometry": {"coordinates":[-2.8232069016,56.4794654846],"type":"Point"}
}