{
  "type": "Feature",
  "properties": {
    "addr:full":"Woodmuir Ho, Breich West Calder South Lanarkshire EH55 8JW",
    "addr:postcode":"eh55 8jw",
    "addr:street":"West",
    "iso:country":"GB",
    "sg:address":"Woodmuir Ho, Breich",
    "sg:city":"West Calder",
    "sg:classifiers":[
        {
            "category":"Manufacturing",
            "subcategory":"Wood Products",
            "type":"Manufacturing & Wholesale Goods"
        }
    ],
    "sg:postcode":"EH55 8JW",
    "sg:province":"South Lanarkshire",
    "sg:tags":[
        "sawmill",
        "shaving"
    ],
    "wof:name":"Woodmuir Saw Mill",
    "wof:placetype":"venue"
},
  "geometry": {"coordinates":[-3.572372,55.851124],"type":"Point"}
}