{
  "type": "Feature",
  "properties": {
    "addr:full":"Station Road North Ferriby East Riding of Yorkshire HU14 3DJ",
    "addr:postcode":"hu14 3dj",
    "addr:street":"Station Road",
    "iso:country":"GB",
    "sg:address":"Station Road",
    "sg:city":"North Ferriby",
    "sg:classifiers":[
        {
            "category":"Retail",
            "subcategory":"Funeral Services",
            "type":"Services"
        }
    ],
    "sg:phone":"+44 1482 631740",
    "sg:postcode":"HU14 3DJ",
    "sg:province":"East Riding of Yorkshire",
    "wof:name":"Ronald Cogan & Sons",
    "wof:placetype":"venue"
},
  "geometry": {"coordinates":[-0.506799,53.720631],"type":"Point"}
}