{
  "type": "Feature",
  "properties": {
    "addr:full":"Spittalhill Works, Ayr Road Kilmarnock East Ayrshire KA1 5NX",
    "addr:postcode":"ka1 5nx",
    "addr:street":"Ayr Road",
    "iso:country":"GB",
    "sg:address":"Spittalhill Works, Ayr Road",
    "sg:city":"Kilmarnock",
    "sg:classifiers":[
        {
            "category":"Manufacturing",
            "subcategory":"Metals",
            "type":"Manufacturing & Wholesale Goods"
        }
    ],
    "sg:phone":"+44 1563 830198",
    "sg:postcode":"KA1 5NX",
    "sg:province":"East Ayrshire",
    "sg:tags":[
        "product",
        "fabricated"
    ],
    "wof:name":"Kilmarnock Engineers",
    "wof:placetype":"venue"
},
  "geometry": {"coordinates":[-4.5097298622,55.6088943481],"type":"Point"}
}