{
  "type": "Feature",
  "properties": {
    "addr:full":"306 Harrow Road Wembley Greater London HA9 6LL",
    "addr:housenumber":"306",
    "addr:postcode":"ha9 6ll",
    "addr:street":"Harrow Road",
    "iso:country":"GB",
    "sg:address":"306 Harrow Road",
    "sg:city":"Wembley",
    "sg:classifiers":[
        {
            "category":"Food & Beverages",
            "subcategory":"Groceries & Convenience Stores",
            "type":"Retail Goods"
        }
    ],
    "sg:postcode":"HA9 6LL",
    "sg:province":"Greater London",
    "wof:name":"M SUBEE",
    "wof:placetype":"venue"
},
  "geometry": {"coordinates":[-0.284792,51.552681],"type":"Point"}
}