{
  "type": "Feature",
  "properties": {
    "addr:full":"Argyle Street Swindon Wiltshire SN2 8AR",
    "addr:postcode":"sn2 8ar",
    "addr:street":"Argyle Street",
    "iso:country":"GB",
    "sg:address":"Argyle Street",
    "sg:city":"Swindon",
    "sg:classifiers":[
        {
            "category":"Home & Garden",
            "subcategory":"Garden Supply",
            "type":"Retail Goods"
        }
    ],
    "sg:phone":"+44 1793 520827",
    "sg:postcode":"SN2 8AR",
    "sg:province":"Wiltshire",
    "sg:tags":[
        "nursery",
        "centre"
    ],
    "wof:name":"Argyle Garden Supplies",
    "wof:placetype":"venue"
},
  "geometry": {"coordinates":[-1.774599,51.574554],"type":"Point"}
}