{
  "type": "Feature",
  "properties": {
    "addr:full":"50 High St, Willingham Cambridge Cambridgeshire CB4 5ES",
    "addr:housenumber":"50",
    "addr:postcode":"cb4 5es",
    "addr:street":"High St",
    "iso:country":"GB",
    "sg:address":"50 High St, Willingham",
    "sg:city":"Cambridge",
    "sg:classifiers":[
        {
            "category":"Building & Trades",
            "subcategory":"Construction",
            "type":"Services"
        }
    ],
    "sg:postcode":"CB4 5ES",
    "sg:province":"Cambridgeshire",
    "sg:tags":[
        "roofing"
    ],
    "wof:name":"Mumford,Mark,",
    "wof:placetype":"venue"
},
  "geometry": {"coordinates":[0.0450539999,52.2818069458],"type":"Point"}
}