{
  "type": "Feature",
  "properties": {
    "addr:full":"40 Barrington Road Altrincham Cheshire WA14 1HJ",
    "addr:housenumber":"40",
    "addr:postcode":"wa14 1hj",
    "addr:street":"Barrington Road",
    "iso:country":"GB",
    "sg:address":"40 Barrington Road",
    "sg:city":"Altrincham",
    "sg:classifiers":[
        {
            "category":"Organizations",
            "subcategory":"Non-profit Organization",
            "type":"Services"
        }
    ],
    "sg:postcode":"WA14 1HJ",
    "sg:province":"Cheshire",
    "sg:tags":[
        "organisation",
        "animal",
        "welfare"
    ],
    "wof:name":"C J & P M Hanson",
    "wof:placetype":"venue"
},
  "geometry": {"coordinates":[-2.3478059769,53.3916244507],"type":"Point"}
}