{
  "type": "Feature",
  "properties": {
    "addr:full":"1a Seymour Rd, Eastwood Nottingham Derbyshire NG16 3ND",
    "addr:housenumber":"1a",
    "addr:postcode":"ng16 3nd",
    "addr:street":"Seymour Rd",
    "iso:country":"GB",
    "sg:address":"1a Seymour Rd, Eastwood",
    "sg:city":"Nottingham",
    "sg:classifiers":[
        {
            "category":"Organizations",
            "subcategory":"Non-profit Organization",
            "type":"Services"
        }
    ],
    "sg:phone":"+44 1773 535839",
    "sg:postcode":"NG16 3ND",
    "sg:province":"Derbyshire",
    "sg:tags":[
        "organisation",
        "voluntary",
        "charity"
    ],
    "wof:name":"The Eastwood Drop In",
    "wof:placetype":"venue"
},
  "geometry": {"coordinates":[-1.299914,53.012592],"type":"Point"}
}