{
  "type": "Feature",
  "properties": {
    "addr:full":"303 Manchester Road, Ince Wigan Lancashire WN2 2ED",
    "addr:housenumber":"303",
    "addr:postcode":"wn2 2ed",
    "addr:street":"Manchester Road",
    "iso:country":"GB",
    "sg:address":"303 Manchester Road, Ince",
    "sg:city":"Wigan",
    "sg:classifiers":[
        {
            "category":"Professional",
            "subcategory":"Testing Lab",
            "type":"Services"
        }
    ],
    "sg:phone":"+44 1942 324881",
    "sg:postcode":"WN2 2ED",
    "sg:province":"Lancashire",
    "sg:tags":[
        "mot"
    ],
    "wof:name":"Phenoix Motors",
    "wof:placetype":"venue"
},
  "geometry": {"coordinates":[-2.5985190868,53.5409812927],"type":"Point"}
}