{
  "type": "Feature",
  "properties": {
    "addr:full":"Estate Office, Shawdene Newbury Berkshire RG14 3AJ",
    "addr:postcode":"rg14 3aj",
    "addr:street":"Newbury",
    "iso:country":"GB",
    "sg:address":"Estate Office, Shawdene",
    "sg:city":"Newbury",
    "sg:classifiers":[
        {
            "category":"Farming",
            "subcategory":"Livestock Farm",
            "type":"Manufacturing & Wholesale Goods"
        }
    ],
    "sg:postcode":"RG14 3AJ",
    "sg:province":"Berkshire",
    "sg:tags":[
        "others"
    ],
    "wof:name":"Fairhurst Estates",
    "wof:placetype":"venue"
},
  "geometry": {"coordinates":[-1.3258719444,51.405872345],"type":"Point"}
}