{
  "type": "Feature",
  "properties": {
    "iso:country":"GB",
    "sg:address":"62 Madeira Road",
    "sg:city":"London",
    "sg:classifiers":[
        {
            "category":"Professional",
            "subcategory":"Art Services",
            "type":"Services"
        }
    ],
    "sg:phone":"+44 20 8677 1694",
    "sg:postcode":"SW16 2DE",
    "sg:province":"Greater London",
    "sg:tags":[
        "consultant",
        "design"
    ],
    "wof:name":"The Design Works",
    "wof:placetype":"venue"
},
  "geometry": {"coordinates":[-0.127475,51.4268],"type":"Point"}
}