{
  "type": "Feature",
  "properties": {
    "addr:full":"4 High Street Auchterarder Perth and Kinross PH3 1DF",
    "addr:housenumber":"4",
    "addr:postcode":"ph3 1df",
    "addr:street":"High Street",
    "iso:country":"GB",
    "sg:address":"4 High Street",
    "sg:city":"Auchterarder",
    "sg:classifiers":[
        {
            "category":"Professional",
            "subcategory":"Art Services",
            "type":"Services"
        }
    ],
    "sg:phone":"+44 1764 664073",
    "sg:postcode":"PH3 1DF",
    "sg:province":"Perth and Kinross",
    "sg:tags":[
        "decorating",
        "painting"
    ],
    "wof:name":"Iona Designs",
    "wof:placetype":"venue"
},
  "geometry": {"coordinates":[-3.701528,56.297588],"type":"Point"}
}