{
  "type": "Feature",
  "properties": {
    "addr:full":"Highgate Business Centre, Greenwood Pl, Kentish Town London Greater London NW5 1LB",
    "addr:postcode":"nw5 1lb",
    "addr:street":"Highgate;Greenwood Pl",
    "iso:country":"GB",
    "sg:address":"Highgate Business Centre, Greenwood Pl, Kentish Town",
    "sg:city":"London",
    "sg:classifiers":[
        {
            "category":"Home & Garden",
            "subcategory":"Home Furnishings",
            "type":"Retail Goods"
        }
    ],
    "sg:phone":"+44 20 7267 9299",
    "sg:postcode":"NW5 1LB",
    "sg:province":"Greater London",
    "sg:tags":[
        "candle"
    ],
    "wof:name":"Angelic Candles Ltd",
    "wof:placetype":"venue"
},
  "geometry": {"coordinates":[-0.1423300058,51.5523986816],"type":"Point"}
}