{
  "type": "Feature",
  "properties": {
    "addr:full":"9 Yewtree Drive, Bayston Hill Shrewsbury Shropshire SY3 0PP",
    "addr:housenumber":"9",
    "addr:postcode":"sy3 0pp",
    "addr:street":"Yewtree Drive Bayston Hill",
    "iso:country":"GB",
    "sg:address":"9 Yewtree Drive, Bayston Hill",
    "sg:city":"Shrewsbury",
    "sg:classifiers":[
        {
            "category":"Building & Trades",
            "subcategory":"Construction",
            "type":"Services"
        }
    ],
    "sg:postcode":"SY3 0PP",
    "sg:province":"Shropshire",
    "sg:tags":[
        "joiner",
        "carpenter"
    ],
    "wof:name":"John Davies Carpentry",
    "wof:placetype":"venue"
},
  "geometry": {"coordinates":[-2.7751030922,52.671787262],"type":"Point"}
}