{
  "type": "Feature",
  "properties": {
    "addr:full":"4 Roneo Corner Hornchurch Essex RM12 4TN",
    "addr:housenumber":"4",
    "addr:postcode":"rm12 4tn",
    "addr:street":"Roneo Corner",
    "iso:country":"GB",
    "sg:address":"4 Roneo Corner",
    "sg:city":"Hornchurch",
    "sg:classifiers":[
        {
            "category":"Fast Food",
            "type":"Food & Drink"
        }
    ],
    "sg:phone":"+44 1708 472020",
    "sg:postcode":"RM12 4TN",
    "sg:province":"Essex",
    "sg:tags":[
        "away",
        "take"
    ],
    "wof:name":"Ma Mone",
    "wof:placetype":"venue"
},
  "geometry": {"coordinates":[0.188154,51.565235],"type":"Point"}
}