{
  "type": "Feature",
  "properties": {
    "addr:full":"51 Barnsley Road, South Elmsall Pontefract West Yorkshire WF9 2RP",
    "addr:housenumber":"51",
    "addr:postcode":"wf9 2rp",
    "addr:street":"Barnsley Road South;Pontefract West",
    "iso:country":"GB",
    "sg:address":"51 Barnsley Road, South Elmsall",
    "sg:city":"Pontefract",
    "sg:classifiers":[
        {
            "category":"Cinema",
            "subcategory":"Movie Rental",
            "type":"Entertainment"
        }
    ],
    "sg:phone":"+44 1977 646430",
    "sg:postcode":"WF9 2RP",
    "sg:province":"West Yorkshire",
    "sg:tags":[
        "video",
        "library"
    ],
    "wof:name":"Blockbuster Video",
    "wof:placetype":"venue"
},
  "geometry": {"coordinates":[-1.292886,53.594707],"type":"Point"}
}