{
  "type": "Feature",
  "properties": {
    "iso:country":"GB",
    "sg:address":"1 Oxford Road",
    "sg:city":"Rochford",
    "sg:classifiers":[
        {
            "category":"Organizations",
            "subcategory":"Membership Organization",
            "type":"Services"
        }
    ],
    "sg:phone":"+44 1702 530933",
    "sg:postcode":"SS4 1TG",
    "sg:province":"Essex",
    "sg:tags":[
        "club"
    ],
    "wof:name":"W D Greenhill Ltd.",
    "wof:placetype":"venue"
},
  "geometry": {"coordinates":[0.697776,51.594608],"type":"Point"}
}