{
  "type": "Feature",
  "properties": {
    "addr:full":"Radley Road Newark Nottinghamshire NG22 8AH",
    "addr:postcode":"ng22 8ah",
    "addr:street":"Radley Road",
    "iso:country":"GB",
    "sg:address":"Radley Road",
    "sg:city":"Newark",
    "sg:classifiers":[
        {
            "category":"Government",
            "subcategory":"Post Office",
            "type":"Public Place"
        }
    ],
    "sg:phone":"+44 1636 812963",
    "sg:postcode":"NG22 8AH",
    "sg:province":"Nottinghamshire",
    "wof:name":"Halan Sub Post Office",
    "wof:placetype":"venue"
},
  "geometry": {"coordinates":[-0.9891170263,53.0830535889],"type":"Point"}
}