{
  "type": "Feature",
  "properties": {
    "addr:full":"Aldridge Rd, Great Barr Birmingham West Midlands B44 8NE",
    "addr:postcode":"b44 8ne",
    "addr:street":"Aldridge Rd",
    "iso:country":"GB",
    "sg:address":"Aldridge Rd, Great Barr",
    "sg:city":"Birmingham",
    "sg:classifiers":[
        {
            "category":"Sports & Exercise",
            "subcategory":"Gym",
            "type":"Entertainment"
        }
    ],
    "sg:phone":"+44 121 360 3939",
    "sg:postcode":"B44 8NE",
    "sg:province":"West Midlands",
    "sg:tags":[
        "fitness",
        "health",
        "centre"
    ],
    "wof:name":"Time Health & Fitness",
    "wof:placetype":"venue"
},
  "geometry": {"coordinates":[-1.907785058,52.5521774292],"type":"Point"}
}