{
  "type": "Feature",
  "properties": {
    "addr:full":"Atlas Road, Hermitage Industrial Estate Coalville Leicestershire LE67 3FQ",
    "addr:postcode":"le67 3fq",
    "addr:street":"Atlas Road Hermitage Industrial Estate",
    "iso:country":"GB",
    "sg:address":"Atlas Road, Hermitage Industrial Estate",
    "sg:city":"Coalville",
    "sg:classifiers":[
        {
            "category":"Wholesale",
            "subcategory":"Construction Materials",
            "type":"Manufacturing & Wholesale Goods"
        }
    ],
    "sg:phone":"+44 1530 839696",
    "sg:postcode":"LE67 3FQ",
    "sg:province":"Leicestershire",
    "sg:tags":[
        "elastic"
    ],
    "wof:name":"Charnwood Elastics Ltd.",
    "wof:placetype":"venue"
},
  "geometry": {"coordinates":[-1.3686109781,52.7290420532],"type":"Point"}
}