{
  "type": "Feature",
  "properties": {
    "addr:full":"16 Lower Bond St Hinckley Leicestershire LE10 1QU",
    "addr:housenumber":"16",
    "addr:postcode":"le10 1qu",
    "addr:street":"Lower Bond St",
    "iso:country":"GB",
    "sg:address":"16 Lower Bond St",
    "sg:city":"Hinckley",
    "sg:classifiers":[
        {
            "category":"Home & Garden",
            "subcategory":"Furniture",
            "type":"Retail Goods"
        }
    ],
    "sg:postcode":"LE10 1QU",
    "sg:province":"Leicestershire",
    "wof:name":"Morris,Michelle,",
    "wof:placetype":"venue"
},
  "geometry": {"coordinates":[-1.3738349676,52.5430145264],"type":"Point"}
}