{
  "type": "Feature",
  "properties": {
    "iso:country":"GB",
    "sg:address":"527 Bearwood Road",
    "sg:city":"Smethwick",
    "sg:classifiers":[
        {
            "category":"Home & Garden",
            "subcategory":"Carpets & Floor Coverings",
            "type":"Retail Goods"
        }
    ],
    "sg:phone":"+44 121 429 7691",
    "sg:postcode":"B66 4BE",
    "sg:province":"West Midlands",
    "sg:tags":[
        "carpets",
        "rug",
        "matting"
    ],
    "wof:name":"M & M Carpets",
    "wof:placetype":"venue"
},
  "geometry": {"coordinates":[-1.969493,52.476028],"type":"Point"}
}