{
  "type": "Feature",
  "properties": {
    "addr:full":"Croasdale Avenue, Ribbleton Preston Lancashire PR2 6UB",
    "addr:postcode":"pr2 6ub",
    "addr:street":"Croasdale Avenue",
    "iso:country":"GB",
    "sg:address":"Croasdale Avenue, Ribbleton",
    "sg:city":"Preston",
    "sg:classifiers":[
        {
            "category":"Travel",
            "subcategory":"Hotels & Motels",
            "type":"Entertainment"
        },
        {
            "category":"Travel",
            "subcategory":"Hostel",
            "type":"Entertainment"
        }
    ],
    "sg:phone":"+44 1772 700664",
    "sg:postcode":"PR2 6UB",
    "sg:province":"Lancashire",
    "wof:name":"17-19 Malham Place",
    "wof:placetype":"venue"
},
  "geometry": {"coordinates":[-2.6649041176,53.7820014954],"type":"Point"}
}