{
  "type": "Feature",
  "properties": {
    "iso:country":"GB",
    "sg:address":"Great Western Road",
    "sg:city":"Clydebank",
    "sg:classifiers":[
        {
            "category":"Retail",
            "subcategory":"Funeral Services",
            "type":"Services"
        },
        {
            "category":"Government",
            "subcategory":"Office",
            "type":"Public Place"
        }
    ],
    "sg:phone":"+44 1389 874318",
    "sg:postcode":"G81 4SL",
    "sg:province":"East Dunbartonshire",
    "sg:tags":[
        "cemetery",
        "local",
        "crematorium"
    ],
    "wof:name":"Clydebank Crematorium",
    "wof:placetype":"venue"
},
  "geometry": {"coordinates":[-4.444644,55.924557],"type":"Point"}
}