{
  "type": "Feature",
  "properties": {
    "addr:full":"102 Rushton Drive, Bramhall Stockport Cheshire SK7 3LE",
    "addr:housenumber":"102",
    "addr:postcode":"sk7 3le",
    "addr:street":"Rushton Drive",
    "iso:country":"GB",
    "sg:address":"102 Rushton Drive, Bramhall",
    "sg:city":"Stockport",
    "sg:classifiers":[
        {
            "category":"Home & Garden",
            "subcategory":"Building Materials",
            "type":"Retail Goods"
        }
    ],
    "sg:phone":"+44 161 439 4427",
    "sg:postcode":"SK7 3LE",
    "sg:province":"Cheshire",
    "sg:tags":[
        "gate",
        "door",
        "barrier"
    ],
    "wof:name":"Branhall Fencing",
    "wof:placetype":"venue"
},
  "geometry": {"coordinates":[-2.167515,53.380898],"type":"Point"}
}