{
  "type": "Feature",
  "properties": {
    "iso:country":"GB",
    "sg:address":"2 Seaside Lane, Easington Colliery",
    "sg:city":"Peterlee",
    "sg:classifiers":[
        {
            "category":"Shopping",
            "subcategory":"News",
            "type":"Retail Goods"
        }
    ],
    "sg:phone":"+44 191 527 0257",
    "sg:postcode":"SR8 3PF",
    "sg:province":"Durham",
    "sg:tags":[
        "newsagent"
    ],
    "wof:name":"Henry's Newsagents",
    "wof:placetype":"venue"
},
  "geometry": {"coordinates":[-1.324591,54.788258],"type":"Point"}
}