{
  "type": "Feature",
  "properties": {
    "addr:full":"88 High Street, Barkingside Ilford Essex IG6 2DR",
    "addr:housenumber":"88",
    "addr:postcode":"ig6 2dr",
    "addr:street":"High Street",
    "iso:country":"GB",
    "sg:address":"88 High Street, Barkingside",
    "sg:city":"Ilford",
    "sg:classifiers":[
        {
            "category":"Home & Garden",
            "subcategory":"Carpets & Floor Coverings",
            "type":"Retail Goods"
        }
    ],
    "sg:phone":"+44 20 8550 0078",
    "sg:postcode":"IG6 2DR",
    "sg:province":"Essex",
    "sg:tags":[
        "carpets",
        "retailer",
        "rug",
        "matting"
    ],
    "wof:name":"P V Barnes Carpets Ltd",
    "wof:placetype":"venue"
},
  "geometry": {"coordinates":[0.082857,51.590897],"type":"Point"}
}