{
  "type": "Feature",
  "properties": {
    "addr:full":"Sandy Lane Prestatyn Denbighshire LL19 7SG",
    "addr:postcode":"ll19 7sg",
    "addr:street":"Sandy Lane",
    "iso:country":"GB",
    "sg:address":"Sandy Lane",
    "sg:city":"Prestatyn",
    "sg:classifiers":[
        {
            "category":"Bars & Pubs",
            "type":"Food & Drink"
        },
        {
            "category":"Community Center",
            "subcategory":"Social",
            "type":"Public Place"
        }
    ],
    "sg:phone":"+44 1745 854670",
    "sg:postcode":"LL19 7SG",
    "sg:province":"Denbighshire",
    "sg:tags":[
        "pubs",
        "house",
        "inn",
        "activity"
    ],
    "wof:name":"Royal Victoria",
    "wof:placetype":"venue"
},
  "geometry": {"coordinates":[-3.410956,53.33606],"type":"Point"}
}