{
  "type": "Feature",
  "properties": {
    "iso:country":"GB",
    "sg:address":"307 Kingston Rd",
    "sg:city":"Epsom",
    "sg:classifiers":[
        {
            "category":"Place Of Worship",
            "type":"Public Place"
        }
    ],
    "sg:phone":"+44 20 8393 5572",
    "sg:postcode":"KT19 0BW",
    "sg:province":"Surrey",
    "wof:name":"St Clements R C Church",
    "wof:placetype":"venue"
},
  "geometry": {"coordinates":[-0.2597439885,51.3647956848],"type":"Point"}
}