{
  "type": "Feature",
  "properties": {
    "iso:country":"GB",
    "sg:address":"Second Avenue, Llay",
    "sg:city":"Wrexham",
    "sg:classifiers":[
        {
            "category":"Social Services",
            "subcategory":"Adult Care",
            "type":"Services"
        },
        {
            "category":"Government",
            "subcategory":"Office",
            "type":"Public Place"
        }
    ],
    "sg:phone":"+44 1978 856159",
    "sg:postcode":"LL12 0TJ",
    "sg:province":"Wrexham",
    "sg:tags":[
        "housing",
        "local",
        "sheltered"
    ],
    "wof:name":"Y Tir Capel",
    "wof:placetype":"venue"
},
  "geometry": {"coordinates":[-3.000814,53.093639],"type":"Point"}
}