{
  "type": "Feature",
  "properties": {
    "iso:country":"GB",
    "sg:address":"5 Winsford Av",
    "sg:city":"Eastleigh",
    "sg:classifiers":[
        {
            "category":"Retail",
            "subcategory":"Laundry & Dry Cleaning",
            "type":"Services"
        }
    ],
    "sg:phone":"+44 23 8060 0833",
    "sg:postcode":"SO50 8JJ",
    "sg:province":"Hampshire",
    "sg:tags":[
        "home",
        "ironing"
    ],
    "wof:name":"Hard Pressed",
    "wof:placetype":"venue"
},
  "geometry": {"coordinates":[-1.315656,50.961136],"type":"Point"}
}