{
  "type": "Feature",
  "properties": {
    "addr:full":"Unit 1, 137 Shawbridge Street, Pollockshaws Glasgow Glasgow City G43 1QQ",
    "addr:housenumber":"unit 1",
    "addr:postcode":"137;g43 1qq",
    "addr:street":"Shawbridge Street",
    "iso:country":"GB",
    "sg:address":"Unit 1, 137 Shawbridge Street, Pollockshaws",
    "sg:city":"Glasgow",
    "sg:classifiers":[
        {
            "category":"Building & Trades",
            "subcategory":"Construction",
            "type":"Services"
        }
    ],
    "sg:phone":"+44 141 649 9272",
    "sg:postcode":"G43 1QQ",
    "sg:province":"Glasgow City",
    "sg:tags":[
        "decorator",
        "painter"
    ],
    "wof:name":"Brawley Brothers Ltd.",
    "wof:placetype":"venue"
},
  "geometry": {"coordinates":[-4.297109127,55.8229408264],"type":"Point"}
}