{
  "type": "Feature",
  "properties": {
    "addr:full":"Blackbrook Business Park Taunton Somerset TA1 2RW",
    "addr:postcode":"ta1 2rw",
    "addr:street":"Park",
    "iso:country":"GB",
    "sg:address":"Blackbrook Business Park",
    "sg:city":"Taunton",
    "sg:classifiers":[
        {
            "category":"Travel",
            "subcategory":"Hotels & Motels",
            "type":"Entertainment"
        }
    ],
    "sg:phone":"+44 1823 624000",
    "sg:postcode":"TA1 2RW",
    "sg:province":"Somerset",
    "wof:name":"Holiday Inn Express",
    "wof:placetype":"venue"
},
  "geometry": {"coordinates":[-3.0669589043,51.0168914795],"type":"Point"}
}