{
  "type": "Feature",
  "properties": {
    "addr:full":"Unit 6, 5-19 Holland Street Aberdeen Aberdeen City AB25 3UJ",
    "addr:housenumber":"unit 6 5-19",
    "addr:postcode":"ab25 3uj",
    "addr:street":"Holland Street",
    "iso:country":"GB",
    "sg:address":"Unit 6, 5-19 Holland Street",
    "sg:city":"Aberdeen",
    "sg:classifiers":[
        {
            "category":"Professional",
            "subcategory":"Management & Consulting",
            "type":"Services"
        },
        {
            "category":"Organizations",
            "subcategory":"Community Association",
            "type":"Services"
        }
    ],
    "sg:phone":"+44 1224 626232",
    "sg:postcode":"AB25 3UJ",
    "sg:province":"Aberdeen City",
    "sg:tags":[
        "fire",
        "consultant",
        "alarm",
        "protection",
        "system"
    ],
    "wof:name":"Fire Protection Alliance Ltd.",
    "wof:placetype":"venue"
},
  "geometry": {"coordinates":[-2.1096599102,57.1536903381],"type":"Point"}
}