{
  "type": "Feature",
  "properties": {
    "iso:country":"GB",
    "sg:address":"687 Chepstow Road",
    "sg:city":"Newport",
    "sg:classifiers":[
        {
            "category":"Organizations",
            "subcategory":"Non-profit Organization",
            "type":"Services"
        }
    ],
    "sg:phone":"+44 1633 276969",
    "sg:postcode":"NP19 9BY",
    "sg:province":"Newport",
    "sg:tags":[
        "charitable",
        "organisation",
        "voluntary",
        "charity"
    ],
    "wof:name":"Multiple Sclerosis Society of Great Britain & Northern Ireland",
    "wof:placetype":"venue"
},
  "geometry": {"coordinates":[-2.9476270676,51.5930252075],"type":"Point"}
}