{
  "type": "Feature",
  "properties": {
    "iso:country":"GB",
    "sg:address":"24 Treebank Cres",
    "sg:city":"Ayr",
    "sg:classifiers":[
        {
            "category":"Arts & Performance",
            "subcategory":"Music",
            "type":"Entertainment"
        }
    ],
    "sg:phone":"+44 1292 281462",
    "sg:postcode":"KA7 3NF",
    "sg:province":"South Ayrshire",
    "sg:tags":[
        "mobile",
        "disco"
    ],
    "wof:name":"Sound Moves",
    "wof:placetype":"venue"
},
  "geometry": {"coordinates":[-4.6024198532,55.450050354],"type":"Point"}
}