{
  "type": "Feature",
  "properties": {
    "iso:country":"GB",
    "sg:address":"45a Southbourne Grove",
    "sg:city":"Bournemouth",
    "sg:classifiers":[
        {
            "category":"Home & Garden",
            "subcategory":"Furniture",
            "type":"Retail Goods"
        }
    ],
    "sg:postcode":"BH6 3QT",
    "sg:province":"Dorset",
    "wof:name":"Etceteras",
    "wof:placetype":"venue"
},
  "geometry": {"coordinates":[-1.8160309792,50.7260894775],"type":"Point"}
}