{
  "type": "Feature",
  "properties": {
    "addr:full":"46a Maddox St West End Hampshire W1R 9PB",
    "addr:housenumber":"46a",
    "addr:postcode":"w1r 9pb",
    "addr:street":"Maddox St",
    "iso:country":"GB",
    "sg:address":"46a Maddox St",
    "sg:city":"West End",
    "sg:classifiers":[
        {
            "category":"Professional",
            "subcategory":"Art Services",
            "type":"Services"
        }
    ],
    "sg:phone":"+44 20 7629 7585",
    "sg:postcode":"W1R 9PB",
    "sg:province":"Hampshire",
    "sg:tags":[
        "photographer"
    ],
    "wof:name":"A C Cooper Ltd",
    "wof:placetype":"venue"
},
  "geometry": {"coordinates":[-0.143484,51.512699],"type":"Point"}
}