{
  "type": "Feature",
  "properties": {
    "iso:country":"GB",
    "sg:address":"Hoelands, Billingshurst Road, Wisborough Green",
    "sg:city":"Billingshurst",
    "sg:classifiers":[
        {
            "category":"Manufacturing",
            "subcategory":"Lumber",
            "type":"Manufacturing & Wholesale Goods"
        }
    ],
    "sg:phone":"+44 1403 700208",
    "sg:postcode":"RH14 0DZ",
    "sg:province":"West Sussex",
    "sg:tags":[
        "merchant",
        "merchants",
        "importer",
        "agent",
        "timber"
    ],
    "wof:name":"Gordon J Hamblin",
    "wof:placetype":"venue"
},
  "geometry": {"coordinates":[-0.4524280131,51.0211830139],"type":"Point"}
}