{
  "type": "Feature",
  "properties": {
    "addr:full":"4 Holmebank Cotts, Birgham Coldstream Northumberland TD12 4ND",
    "addr:housenumber":"4;cotts birgham",
    "addr:postcode":"td12 4nd",
    "addr:street":"Holmebank",
    "iso:country":"GB",
    "sg:address":"4 Holmebank Cotts, Birgham",
    "sg:city":"Coldstream",
    "sg:classifiers":[
        {
            "category":"Professional",
            "subcategory":"Advertising",
            "type":"Services"
        }
    ],
    "sg:phone":"+44 1890 830247",
    "sg:postcode":"TD12 4ND",
    "sg:province":"Northumberland",
    "sg:tags":[
        "agency"
    ],
    "wof:name":"J M & D B Hicks",
    "wof:placetype":"venue"
},
  "geometry": {"coordinates":[-2.2080740929,55.6359481812],"type":"Point"}
}