{
  "type": "Feature",
  "properties": {
    "addr:full":"6 Dean Park St Edinburgh City of Edinburgh EH4 1JW",
    "addr:housenumber":"6",
    "addr:postcode":"eh4 1jw",
    "addr:street":"Dean Park St",
    "iso:country":"GB",
    "sg:address":"6 Dean Park St",
    "sg:city":"Edinburgh",
    "sg:classifiers":[
        {
            "category":"Professional",
            "type":"Services"
        }
    ],
    "sg:phone":"+44 131 332 8423",
    "sg:postcode":"EH4 1JW",
    "sg:province":"City of Edinburgh",
    "sg:tags":[
        "caterer"
    ],
    "wof:name":"Tuck In Outside Catering",
    "wof:placetype":"venue"
},
  "geometry": {"coordinates":[-3.2102088928,55.9585609436],"type":"Point"}
}