{
  "type": "Feature",
  "properties": {
    "iso:country":"GB",
    "sg:address":"17 Cannon Grove, Fetcham",
    "sg:city":"Leatherhead",
    "sg:classifiers":[
        {
            "category":"Shopping",
            "subcategory":"Pharmacy",
            "type":"Retail Goods"
        }
    ],
    "sg:postcode":"KT22 9LG",
    "sg:province":"Surrey",
    "sg:tags":[
        "pharmacist",
        "chemist"
    ],
    "wof:name":"Cannon Court Pharmacy",
    "wof:placetype":"venue"
},
  "geometry": {"coordinates":[-0.3484990001,51.2973327637],"type":"Point"}
}