{
  "type": "Feature",
  "properties": {
    "addr:full":"The Surgery, Bunbury Tarporley Cheshire CW6 9PJ",
    "addr:postcode":"cw6 9pj",
    "addr:street":"Tarporley",
    "iso:country":"GB",
    "sg:address":"The Surgery, Bunbury",
    "sg:city":"Tarporley",
    "sg:classifiers":[
        {
            "category":"Health Services",
            "subcategory":"Doctor",
            "type":"Services"
        },
        {
            "category":"Health Services",
            "subcategory":"Clinic",
            "type":"Services"
        }
    ],
    "sg:phone":"+44 1829 260218",
    "sg:postcode":"CW6 9PJ",
    "sg:province":"Cheshire",
    "sg:tags":[
        "nh",
        "practitioners"
    ],
    "wof:name":"Bunbury Medical Practice",
    "wof:placetype":"venue"
},
  "geometry": {"coordinates":[-2.661644,53.121246],"type":"Point"}
}