{
  "type": "Feature",
  "properties": {
    "iso:country":"GB",
    "sg:address":"27 Cambridge Road",
    "sg:city":"Kingston-upon-thames",
    "sg:classifiers":[
        {
            "category":"Fast Food",
            "type":"Food & Drink"
        }
    ],
    "sg:phone":"+44 20 8541 4380",
    "sg:postcode":"KT1 3NQ",
    "sg:province":"Greater London",
    "sg:tags":[
        "away",
        "take"
    ],
    "wof:name":"Hing Long Fish & Chips",
    "wof:placetype":"venue"
},
  "geometry": {"coordinates":[-0.28936,51.409805],"type":"Point"}
}