{
  "type": "Feature",
  "properties": {
    "addr:full":"Wellingborough Road Post Office, 179 Wellingborough Road Northampton Northamptonshire NN1 4DY",
    "addr:housenumber":"179",
    "addr:postcode":"nn1 4dy",
    "addr:street":"Wellingborough;Wellingborough Road",
    "iso:country":"GB",
    "sg:address":"Wellingborough Road Post Office, 179 Wellingborough Road",
    "sg:city":"Northampton",
    "sg:classifiers":[
        {
            "category":"Food & Beverages",
            "subcategory":"Candy",
            "type":"Retail Goods"
        }
    ],
    "sg:postcode":"NN1 4DY",
    "sg:province":"Northamptonshire",
    "sg:tags":[
        "confectioner"
    ],
    "wof:name":"Amrit Enterprises",
    "wof:placetype":"venue"
},
  "geometry": {"coordinates":[-0.868904,52.247845],"type":"Point"}
}