{
  "type": "Feature",
  "properties": {
    "iso:country":"GB",
    "sg:address":"Rose Bower Garage, Thirsk Road, Easingwold",
    "sg:city":"York",
    "sg:classifiers":[
        {
            "category":"Autos & Motor Vehicles",
            "subcategory":"Automobile Sales",
            "type":"Retail Goods"
        }
    ],
    "sg:phone":"+44 1347 822423",
    "sg:postcode":"YO61 3HN",
    "sg:province":"North Yorkshire",
    "sg:tags":[
        "car"
    ],
    "wof:name":"G C Motors New & Used",
    "wof:placetype":"venue"
},
  "geometry": {"coordinates":[-1.19231,54.121414],"type":"Point"}
}