{
  "type": "Feature",
  "properties": {
    "addr:full":"55 Lidget Street Huddersfield West Yorkshire HD3 3JP",
    "addr:housenumber":"55",
    "addr:postcode":"hd3 3jp",
    "addr:street":"Lidget Street",
    "iso:country":"GB",
    "sg:address":"55 Lidget Street",
    "sg:city":"Huddersfield",
    "sg:classifiers":[
        {
            "category":"Health Services",
            "subcategory":"Optometrist",
            "type":"Services"
        },
        {
            "category":"Shopping",
            "subcategory":"Optician",
            "type":"Retail Goods"
        }
    ],
    "sg:phone":"+44 1484 643692",
    "sg:postcode":"HD3 3JP",
    "sg:province":"West Yorkshire",
    "sg:tags":[
        "ophthalmic"
    ],
    "wof:name":"Bottomley & Ramsden",
    "wof:placetype":"venue"
},
  "geometry": {"coordinates":[-1.8237190247,53.6612205505],"type":"Point"}
}