{
  "type": "Feature",
  "properties": {
    "addr:full":"Radway Road Swindon Wiltshire SN3 4FH",
    "addr:postcode":"sn3 4fh",
    "addr:street":"Radway Road",
    "iso:country":"GB",
    "sg:address":"Radway Road",
    "sg:city":"Swindon",
    "sg:classifiers":[
        {
            "category":"Professional",
            "subcategory":"Printing & Photocopies",
            "type":"Services"
        }
    ],
    "sg:phone":"+44 1793 820900",
    "sg:postcode":"SN3 4FH",
    "sg:province":"Wiltshire",
    "sg:tags":[
        "plate",
        "lithographic",
        "maker"
    ],
    "wof:name":"Wace Corporate Print Ltd.",
    "wof:placetype":"venue"
},
  "geometry": {"coordinates":[-1.7576309443,51.5823822021],"type":"Point"}
}