{
  "type": "Feature",
  "properties": {
    "iso:country":"GB",
    "sg:address":"35 Bingen Road",
    "sg:city":"Hitchin",
    "sg:classifiers":[
        {
            "category":"Personal",
            "type":"Services"
        }
    ],
    "sg:phone":"+44 1462 453793",
    "sg:postcode":"SG5 2PP",
    "sg:province":"Bedfordshire",
    "sg:tags":[
        "wedding"
    ],
    "wof:name":"Sheila's Wedding Hire",
    "wof:placetype":"venue"
},
  "geometry": {"coordinates":[-0.294383,51.957966],"type":"Point"}
}