{
  "type": "Feature",
  "properties": {
    "addr:full":"Kyrimar Lodge Lower Way, Upper Longdon Rugeley Staffordshire WS15 1QG",
    "addr:postcode":"ws15 1qg",
    "addr:street":"Lower Way",
    "iso:country":"GB",
    "sg:address":"Kyrimar Lodge Lower Way, Upper Longdon",
    "sg:city":"Rugeley",
    "sg:classifiers":[
        {
            "category":"Professional",
            "subcategory":"Management & Consulting",
            "type":"Services"
        }
    ],
    "sg:postcode":"WS15 1QG",
    "sg:province":"Staffordshire",
    "sg:tags":[
        "consultant"
    ],
    "wof:name":"Co View Ltd",
    "wof:placetype":"venue"
},
  "geometry": {"coordinates":[-1.907332,52.729259],"type":"Point"}
}