{
  "type": "Feature",
  "properties": {
    "addr:full":"Walmer Road Lowestoft Suffolk NR32 1HS",
    "addr:postcode":"nr32 1hs",
    "addr:street":"Walmer Road",
    "iso:country":"GB",
    "sg:address":"Walmer Road",
    "sg:city":"Lowestoft",
    "sg:classifiers":[
        {
            "category":"Arena",
            "subcategory":"Sports Club",
            "type":"Entertainment"
        }
    ],
    "sg:phone":"+44 1502 565495",
    "sg:postcode":"NR32 1HS",
    "sg:province":"Suffolk",
    "sg:tags":[
        "ground"
    ],
    "wof:name":"Kirkley Recreation Ground",
    "wof:placetype":"venue"
},
  "geometry": {"coordinates":[1.72806,52.460773],"type":"Point"}
}