{
  "type": "Feature",
  "properties": {
    "addr:full":"22 Twisden Road, East Malling West Malling Kent ME19 6SA",
    "addr:housenumber":"22",
    "addr:postcode":"me19 6sa",
    "addr:street":"Twisden Road East",
    "iso:country":"GB",
    "sg:address":"22 Twisden Road, East Malling",
    "sg:city":"West Malling",
    "sg:classifiers":[
        {
            "category":"Fast Food",
            "type":"Food & Drink"
        }
    ],
    "sg:phone":"+44 1732 849356",
    "sg:postcode":"ME19 6SA",
    "sg:province":"Kent",
    "sg:tags":[
        "away",
        "meal",
        "outlet",
        "take"
    ],
    "wof:name":"Ho Lap House",
    "wof:placetype":"venue"
},
  "geometry": {"coordinates":[0.435083,51.293854],"type":"Point"}
}