{
  "type": "Feature",
  "properties": {
    "iso:country":"GB",
    "sg:address":"428 Denby Dale Road East, Durkar",
    "sg:city":"Wakefield",
    "sg:classifiers":[
        {
            "category":"Retail",
            "subcategory":"Auto Repair",
            "type":"Services"
        }
    ],
    "sg:postcode":"WF4 3AD",
    "sg:province":"West Yorkshire",
    "sg:tags":[
        "body",
        "car"
    ],
    "wof:name":"Roger H Lloyd Pancell Motors",
    "wof:placetype":"venue"
},
  "geometry": {"coordinates":[-1.524353981,53.6511726379],"type":"Point"}
}