{
  "type": "Feature",
  "properties": {
    "addr:full":"114 Duke Street Barrow-in-furness Cumbria LA14 1LW",
    "addr:housenumber":"114",
    "addr:postcode":"la14 1lw",
    "addr:street":"Duke Street",
    "iso:country":"GB",
    "sg:address":"114 Duke Street",
    "sg:city":"Barrow-in-furness",
    "sg:classifiers":[
        {
            "category":"Travel",
            "subcategory":"Chalets",
            "type":"Entertainment"
        },
        {
            "category":"Travel",
            "subcategory":"Travel Agent",
            "type":"Entertainment"
        }
    ],
    "sg:phone":"+44 1229 845701",
    "sg:postcode":"LA14 1LW",
    "sg:province":"Cumbria",
    "sg:tags":[
        "cruiselines"
    ],
    "wof:name":"Cumbria Cruise",
    "wof:placetype":"venue"
},
  "geometry": {"coordinates":[-3.2306780815,54.11378479],"type":"Point"}
}