{
  "type": "Feature",
  "properties": {
    "iso:country":"GB",
    "sg:address":"4 Brunel Plaza, Brunel Centre",
    "sg:city":"Swindon",
    "sg:classifiers":[
        {
            "category":"Food & Beverages",
            "subcategory":"Supermarket",
            "type":"Retail Goods"
        }
    ],
    "sg:phone":"+44 1793 530477",
    "sg:postcode":"SN1 1LF",
    "sg:province":"Wiltshire",
    "wof:name":"J Sainsbury",
    "wof:placetype":"venue"
},
  "geometry": {"coordinates":[-1.781814,51.561764],"type":"Point"}
}