{
  "type": "Feature",
  "properties": {
    "addr:full":"7 Kingston Rd Wilmslow Cheshire SK9 3JN",
    "addr:housenumber":"7",
    "addr:postcode":"sk9 3jn",
    "addr:street":"Kingston Rd",
    "iso:country":"GB",
    "sg:address":"7 Kingston Rd",
    "sg:city":"Wilmslow",
    "sg:classifiers":[
        {
            "category":"Building & Trades",
            "subcategory":"Construction",
            "type":"Services"
        }
    ],
    "sg:phone":"+44 1625 524557",
    "sg:postcode":"SK9 3JN",
    "sg:province":"Cheshire",
    "sg:tags":[
        "joiner",
        "carpenter"
    ],
    "wof:name":"T Dale",
    "wof:placetype":"venue"
},
  "geometry": {"coordinates":[-2.2176420689,53.353427887],"type":"Point"}
}