{
  "type": "Feature",
  "properties": {
    "iso:country":"GB",
    "sg:address":"60 Fore Street",
    "sg:city":"Totnes",
    "sg:classifiers":[
        {
            "category":"Banks & Credit Unions",
            "subcategory":"Financial Services",
            "type":"Services"
        }
    ],
    "sg:phone":"+44 1803 864658",
    "sg:postcode":"TQ9 5RU",
    "sg:province":"Devon",
    "sg:tags":[
        "building",
        "society"
    ],
    "wof:name":"Alliance & Leicester",
    "wof:placetype":"venue"
},
  "geometry": {"coordinates":[-3.686299,50.431171],"type":"Point"}
}