{
  "type": "Feature",
  "properties": {
    "iso:country":"GB",
    "sg:address":"20 Caerleon Road",
    "sg:city":"Newport",
    "sg:classifiers":[
        {
            "category":"Autos & Motor Vehicles",
            "subcategory":"Fuel & Gas Station",
            "type":"Retail Goods"
        }
    ],
    "sg:postcode":"NP19 7BX",
    "sg:province":"Newport",
    "sg:tags":[
        "petrol",
        "filling"
    ],
    "wof:name":"A J Gambarini & Co. Ltd.",
    "wof:placetype":"venue"
},
  "geometry": {"coordinates":[-2.985794,51.593521],"type":"Point"}
}