{
  "type": "Feature",
  "properties": {
    "iso:country":"GB",
    "sg:address":"9 Beverley Clo",
    "sg:city":"Broxbourne",
    "sg:classifiers":[
        {
            "category":"Building & Trades",
            "subcategory":"Landscaping Services",
            "type":"Services"
        }
    ],
    "sg:phone":"+44 1992 424567",
    "sg:postcode":"EN10 7HF",
    "sg:province":"Essex",
    "sg:tags":[
        "landscape",
        "contractor"
    ],
    "wof:name":"A Hatton",
    "wof:placetype":"venue"
},
  "geometry": {"coordinates":[-0.024559,51.742771],"type":"Point"}
}