{
  "type": "Feature",
  "properties": {
    "iso:country":"GB",
    "sg:address":"Shire Court, 25 Richmond Road",
    "sg:city":"Towcester",
    "sg:classifiers":[
        {
            "category":"Health Services",
            "subcategory":"Dentist",
            "type":"Services"
        }
    ],
    "sg:phone":"+44 1327 352146",
    "sg:postcode":"NN12 6EX",
    "sg:province":"Buckinghamshire",
    "wof:name":"M Langdon-Jones",
    "wof:placetype":"venue"
},
  "geometry": {"coordinates":[-0.9905120134,52.1308937073],"type":"Point"}
}