{
  "type": "Feature",
  "properties": {
    "addr:full":"All Saints Vicarage, 21 View Rd Keighley North Yorkshire BD20 6JN",
    "addr:housenumber":"21",
    "addr:postcode":"bd20 6jn",
    "addr:street":"View Rd",
    "iso:country":"GB",
    "sg:address":"All Saints Vicarage, 21 View Rd",
    "sg:city":"Keighley",
    "sg:classifiers":[
        {
            "category":"Place Of Worship",
            "type":"Public Place"
        }
    ],
    "sg:phone":"+44 1535 607002",
    "sg:postcode":"BD20 6JN",
    "sg:province":"North Yorkshire",
    "wof:name":"Churches",
    "wof:placetype":"venue"
},
  "geometry": {"coordinates":[-1.9194699526,53.8732795715],"type":"Point"}
}