{
  "type": "Feature",
  "properties": {
    "iso:country":"GB",
    "sg:address":"Station Road",
    "sg:city":"Oakham",
    "sg:classifiers":[
        {
            "category":"Place Of Worship",
            "type":"Public Place"
        }
    ],
    "sg:phone":"+44 1572 722308",
    "sg:postcode":"LE15 6QU",
    "sg:province":"Leicestershire",
    "wof:name":"St Josephs Catholic Church",
    "wof:placetype":"venue"
},
  "geometry": {"coordinates":[-0.72911,52.672581],"type":"Point"}
}