{
  "type": "Feature",
  "properties": {
    "iso:country":"GB",
    "sg:address":"Hill Top Farm, Hill Top Lane, Hunshelf Green Moor",
    "sg:city":"Sheffield",
    "sg:classifiers":[
        {
            "category":"Farming",
            "subcategory":"Livestock Farm",
            "type":"Manufacturing & Wholesale Goods"
        }
    ],
    "sg:phone":"+44 114 288 2581",
    "sg:postcode":"S30 4DQ",
    "sg:province":"Derbyshire",
    "sg:tags":[
        "others"
    ],
    "wof:name":"G Godley",
    "wof:placetype":"venue"
},
  "geometry": {"coordinates":[-1.57507,53.48843],"type":"Point"}
}