{
  "type": "Feature",
  "properties": {
    "addr:full":"7 Harrow Close Ipswich Suffolk IP4 5DX",
    "addr:housenumber":"7",
    "addr:postcode":"ip4 5dx",
    "addr:street":"Harrow Close",
    "iso:country":"GB",
    "sg:address":"7 Harrow Close",
    "sg:city":"Ipswich",
    "sg:classifiers":[
        {
            "category":"Professional",
            "subcategory":"Engineering",
            "type":"Services"
        },
        {
            "category":"Building & Trades",
            "subcategory":"Electrical",
            "type":"Services"
        }
    ],
    "sg:phone":"+44 1473 272949",
    "sg:postcode":"IP4 5DX",
    "sg:province":"Suffolk",
    "sg:tags":[
        "engineer",
        "electrician",
        "contractor"
    ],
    "wof:name":"Eastbury Electrical",
    "wof:placetype":"venue"
},
  "geometry": {"coordinates":[1.1854020357,52.0539283752],"type":"Point"}
}