{
  "type": "Feature",
  "properties": {
    "addr:full":"268 Perth Road Dundee Dundee City DD2 1AE",
    "addr:housenumber":"268",
    "addr:postcode":"dd2 1ae",
    "addr:street":"Perth Road",
    "iso:country":"GB",
    "sg:address":"268 Perth Road",
    "sg:city":"Dundee",
    "sg:classifiers":[
        {
            "category":"Shopping",
            "subcategory":"Thrift Store",
            "type":"Retail Goods"
        }
    ],
    "sg:phone":"+44 1382 665094",
    "sg:postcode":"DD2 1AE",
    "sg:province":"Dundee City",
    "sg:tags":[
        "shop",
        "charity"
    ],
    "wof:name":"Shelter Shops",
    "wof:placetype":"venue"
},
  "geometry": {"coordinates":[-2.99252,56.456005],"type":"Point"}
}