{
  "type": "Feature",
  "properties": {
    "iso:country":"GB",
    "sg:address":"1 Beastfair",
    "sg:city":"Pontefract",
    "sg:classifiers":[
        {
            "category":"Retail",
            "subcategory":"Photofinishing",
            "type":"Services"
        }
    ],
    "sg:phone":"+44 1977 798072",
    "sg:postcode":"WF8 1AL",
    "sg:province":"North Yorkshire",
    "sg:tags":[
        "photographic",
        "processor"
    ],
    "wof:name":"Klick Photopoint",
    "wof:placetype":"venue"
},
  "geometry": {"coordinates":[-1.312399,53.69138],"type":"Point"}
}