{
  "type": "Feature",
  "properties": {
    "addr:full":"231 Longwood Road, Longwood Huddersfield West Yorkshire HD3 4EL",
    "addr:housenumber":"231",
    "addr:postcode":"hd3 4el",
    "addr:street":"Longwood Road;West",
    "iso:country":"GB",
    "sg:address":"231 Longwood Road, Longwood",
    "sg:city":"Huddersfield",
    "sg:classifiers":[
        {
            "category":"Home & Garden",
            "subcategory":"Building Materials",
            "type":"Retail Goods"
        }
    ],
    "sg:postcode":"HD3 4EL",
    "sg:province":"West Yorkshire",
    "sg:tags":[
        "fencing"
    ],
    "wof:name":"Phil Jones Fencing",
    "wof:placetype":"venue"
},
  "geometry": {"coordinates":[-1.822614,53.643562],"type":"Point"}
}