{
  "type": "Feature",
  "properties": {
    "iso:country":"GB",
    "sg:address":"19 Bedford Dr",
    "sg:city":"Leicester",
    "sg:classifiers":[
        {
            "category":"Freight",
            "type":"Transportation"
        }
    ],
    "sg:phone":"+44 116 231 3121",
    "sg:postcode":"LE6 0YB",
    "sg:province":"Leicestershire",
    "sg:tags":[
        "haulage",
        "road"
    ],
    "wof:name":"A N P Logistics",
    "wof:placetype":"venue"
},
  "geometry": {"coordinates":[-1.220797,52.655598],"type":"Point"}
}