{
  "type": "Feature",
  "properties": {
    "addr:full":"Red Cross Garage Works Stoke-on-trent Staffordshire ST8 7AA",
    "addr:postcode":"staffordshire st8 7aa",
    "iso:country":"GB",
    "sg:address":"Red Cross Garage Works",
    "sg:city":"Stoke-on-trent",
    "sg:classifiers":[
        {
            "category":"Retail",
            "subcategory":"Auto Repair",
            "type":"Services"
        }
    ],
    "sg:phone":"+44 1782 518631",
    "sg:postcode":"ST8 7AA",
    "sg:province":"Staffordshire",
    "sg:tags":[
        "modification",
        "garage"
    ],
    "wof:name":"Rally & Competition Equipment",
    "wof:placetype":"venue"
},
  "geometry": {"coordinates":[-2.1793000698,53.1090087891],"type":"Point"}
}