{
  "type": "Feature",
  "properties": {
    "addr:full":"29 Carr Hill La, Briggswath Whitby North Yorkshire YO21 1RS",
    "addr:housenumber":"29",
    "addr:postcode":"yo21 1rs",
    "addr:street":"Carr Hill La Briggswath",
    "iso:country":"GB",
    "sg:address":"29 Carr Hill La, Briggswath",
    "sg:city":"Whitby",
    "sg:classifiers":[
        {
            "category":"Real Estate",
            "subcategory":"Architect",
            "type":"Services"
        }
    ],
    "sg:postcode":"YO21 1RS",
    "sg:province":"North Yorkshire",
    "wof:name":"Cole,J C,Captain,",
    "wof:placetype":"venue"
},
  "geometry": {"coordinates":[-0.615053,54.485233],"type":"Point"}
}