{
  "type": "Feature",
  "properties": {
    "addr:full":"9 St Leonards Square Wallingford Oxfordshire OX10 0AR",
    "addr:housenumber":"9",
    "addr:postcode":"ox10 0ar",
    "addr:street":"St;Square",
    "iso:country":"GB",
    "sg:address":"9 St Leonards Square",
    "sg:city":"Wallingford",
    "sg:classifiers":[
        {
            "category":"Health Services",
            "subcategory":"Clinic",
            "type":"Services"
        },
        {
            "category":"Shopping",
            "subcategory":"Pharmacy",
            "type":"Retail Goods"
        }
    ],
    "sg:phone":"+44 1491 824724",
    "sg:postcode":"OX10 0AR",
    "sg:province":"Oxfordshire",
    "sg:tags":[
        "medicine",
        "therapy",
        "private"
    ],
    "wof:name":"Wallingford Therapy Clinic",
    "wof:placetype":"venue"
},
  "geometry": {"coordinates":[-1.123453021,51.5974349976],"type":"Point"}
}