{
  "type": "Feature",
  "properties": {
    "addr:full":"54 Lambs Conduit Street London Greater London WC1N 3LW",
    "addr:housenumber":"54",
    "addr:postcode":"wc1n 3lw",
    "addr:street":"Lambs Conduit Street",
    "iso:country":"GB",
    "sg:address":"54 Lambs Conduit Street",
    "sg:city":"London",
    "sg:classifiers":[
        {
            "category":"Restaurant",
            "type":"Food & Drink"
        }
    ],
    "sg:phone":"+44 20 7405 1717",
    "sg:postcode":"WC1N 3LW",
    "sg:province":"Greater London",
    "sg:tags":[
        "french"
    ],
    "wof:name":"Brasserie Du Coin",
    "wof:placetype":"venue"
},
  "geometry": {"coordinates":[-0.118376,51.52195],"type":"Point"}
}