{
  "type": "Feature",
  "properties": {
    "addr:full":"21d Strathearn Road Edinburgh City of Edinburgh EH9 2AB",
    "addr:housenumber":"21d",
    "addr:postcode":"eh9 2ab",
    "addr:street":"Strathearn Road",
    "iso:country":"GB",
    "sg:address":"21d Strathearn Road",
    "sg:city":"Edinburgh",
    "sg:classifiers":[
        {
            "category":"Food & Beverages",
            "subcategory":"Fruits & Vegetables",
            "type":"Retail Goods"
        },
        {
            "category":"Food & Beverages",
            "subcategory":"Groceries & Convenience Stores",
            "type":"Retail Goods"
        }
    ],
    "sg:phone":"+44 131 447 3333",
    "sg:postcode":"EH9 2AB",
    "sg:province":"City of Edinburgh",
    "sg:tags":[
        "grocer",
        "greengrocer"
    ],
    "wof:name":"W D McGregor",
    "wof:placetype":"venue"
},
  "geometry": {"coordinates":[-3.1943790913,55.9348754883],"type":"Point"}
}