{
  "type": "Feature",
  "properties": {
    "addr:full":"7th Floor, 78 Cannon Street London Greater London EC1V 2NA",
    "addr:housenumber":"7th floor 78",
    "addr:postcode":"ec1v 2na",
    "addr:street":"Cannon Street",
    "iso:country":"GB",
    "sg:address":"7th Floor, 78 Cannon Street",
    "sg:city":"London",
    "sg:classifiers":[
        {
            "category":"Professional",
            "subcategory":"Business Services",
            "type":"Services"
        }
    ],
    "sg:phone":"+44 20 7750 0000",
    "sg:postcode":"EC1V 2NA",
    "sg:province":"Greater London",
    "sg:tags":[
        "answering"
    ],
    "wof:name":"M C I Worldcom Ltd.",
    "wof:placetype":"venue"
},
  "geometry": {"coordinates":[-0.0895709991,51.5114212036],"type":"Point"}
}