{
  "type": "Feature",
  "properties": {
    "iso:country":"GB",
    "sg:address":"20 Bradford Street",
    "sg:city":"Shifnal",
    "sg:classifiers":[
        {
            "category":"Professional",
            "subcategory":"Employment Agencies",
            "type":"Services"
        }
    ],
    "sg:postcode":"TF11 8AU",
    "sg:province":"Shropshire",
    "sg:tags":[
        "consultant"
    ],
    "wof:name":"Sherpa Services Ltd.",
    "wof:placetype":"venue"
},
  "geometry": {"coordinates":[-2.372681,52.667179],"type":"Point"}
}