{
  "type": "Feature",
  "properties": {
    "addr:full":"Corkscrew Hill West Wickham Kent BR4 9BA",
    "addr:postcode":"br4 9ba",
    "addr:street":"Corkscrew Hill",
    "iso:country":"GB",
    "sg:address":"Corkscrew Hill",
    "sg:city":"West Wickham",
    "sg:classifiers":[
        {
            "category":"Education",
            "subcategory":"School",
            "type":"Public Place"
        }
    ],
    "sg:postcode":"BR4 9BA",
    "sg:province":"Kent",
    "sg:tags":[
        "independent",
        "preparatory"
    ],
    "wof:name":"Greenhayes School for Boys",
    "wof:placetype":"venue"
},
  "geometry": {"coordinates":[-0.010638,51.371532],"type":"Point"}
}