{
  "type": "Feature",
  "properties": {
    "iso:country":"GB",
    "sg:address":"34 Gateford Rd",
    "sg:city":"Worksop",
    "sg:classifiers":[
        {
            "category":"Home & Garden",
            "subcategory":"Furniture",
            "type":"Retail Goods"
        }
    ],
    "sg:postcode":"S80 1EB",
    "sg:province":"Nottinghamshire",
    "wof:name":"Second Choice Furnishings",
    "wof:placetype":"venue"
},
  "geometry": {"coordinates":[-1.1228699684,53.3077507019],"type":"Point"}
}