{
  "type": "Feature",
  "properties": {
    "addr:full":"18 West Street Horsham West Sussex RH12 1PB",
    "addr:housenumber":"18",
    "addr:postcode":"rh12 1pb",
    "addr:street":"West Street",
    "iso:country":"GB",
    "sg:address":"18 West Street",
    "sg:city":"Horsham",
    "sg:classifiers":[
        {
            "category":"Shopping",
            "subcategory":"Bicycles & Sporting Goods",
            "type":"Retail Goods"
        }
    ],
    "sg:phone":"+44 1403 262851",
    "sg:postcode":"RH12 1PB",
    "sg:province":"West Sussex",
    "sg:tags":[
        "equipment",
        "camping"
    ],
    "wof:name":"Millets Leisure",
    "wof:placetype":"venue"
},
  "geometry": {"coordinates":[-0.3302870095,51.0626106262],"type":"Point"}
}