{
  "type": "Feature",
  "properties": {
    "iso:country":"GB",
    "sg:address":"260 Canterbury Street",
    "sg:city":"Gillingham",
    "sg:classifiers":[
        {
            "category":"Social Services",
            "subcategory":"Retirement Home",
            "type":"Services"
        }
    ],
    "sg:phone":"+44 1634 852903",
    "sg:postcode":"ME7 5XR",
    "sg:province":"Kent",
    "sg:tags":[
        "residential",
        "care"
    ],
    "wof:name":"Maraval",
    "wof:placetype":"venue"
},
  "geometry": {"coordinates":[0.54831,51.379055],"type":"Point"}
}