{
  "type": "Feature",
  "properties": {
    "addr:full":"386 High Street Cheltenham Gloucestershire GL50 3JD",
    "addr:housenumber":"386",
    "addr:postcode":"gl50 3jd",
    "addr:street":"High Street",
    "iso:country":"GB",
    "sg:address":"386 High Street",
    "sg:city":"Cheltenham",
    "sg:classifiers":[
        {
            "category":"Bars & Pubs",
            "type":"Food & Drink"
        }
    ],
    "sg:phone":"+44 1242 690128",
    "sg:postcode":"GL50 3JD",
    "sg:province":"Gloucestershire",
    "sg:tags":[
        "pubs",
        "inn"
    ],
    "wof:name":"The Shakespeare Inn",
    "wof:placetype":"venue"
},
  "geometry": {"coordinates":[-2.082273,51.904312],"type":"Point"}
}