{
  "type": "Feature",
  "properties": {
    "iso:country":"GB",
    "sg:address":"22 Island Crescent",
    "sg:city":"Newquay",
    "sg:classifiers":[
        {
            "category":"Travel",
            "subcategory":"Hotels & Motels",
            "type":"Entertainment"
        }
    ],
    "sg:phone":"+44 1637 873121",
    "sg:postcode":"TR7 1DZ",
    "sg:province":"Cornwall",
    "wof:name":"Bartrip Hotel",
    "wof:placetype":"venue"
},
  "geometry": {"coordinates":[-5.08125,50.41523],"type":"Point"}
}