{
  "type": "Feature",
  "properties": {
    "addr:full":"257 Upper Woodlands Rd Bradford West Yorkshire BD8 9JQ",
    "addr:housenumber":"257",
    "addr:postcode":"bd8 9jq",
    "addr:street":"Upper Woodlands Rd",
    "iso:country":"GB",
    "sg:address":"257 Upper Woodlands Rd",
    "sg:city":"Bradford",
    "sg:classifiers":[
        {
            "category":"Food & Beverages",
            "subcategory":"Fruits & Vegetables",
            "type":"Retail Goods"
        }
    ],
    "sg:phone":"+44 1274 484459",
    "sg:postcode":"BD8 9JQ",
    "sg:province":"West Yorkshire",
    "sg:tags":[
        "greengrocer"
    ],
    "wof:name":"Rajah Spice Land",
    "wof:placetype":"venue"
},
  "geometry": {"coordinates":[-1.7864890099,53.8059043884],"type":"Point"}
}