{
  "type": "Feature",
  "properties": {
    "addr:full":"17 Charlotte Dundas Court Grangemouth Falkirk FK3 9EA",
    "addr:housenumber":"17",
    "addr:postcode":"fk3 9ea",
    "addr:street":"Charlotte Dundas Court",
    "iso:country":"GB",
    "sg:address":"17 Charlotte Dundas Court",
    "sg:city":"Grangemouth",
    "sg:classifiers":[
        {
            "category":"Food & Beverages",
            "subcategory":"Groceries & Convenience Stores",
            "type":"Retail Goods"
        }
    ],
    "sg:phone":"+44 1324 474829",
    "sg:postcode":"FK3 9EA",
    "sg:province":"Falkirk",
    "wof:name":"Argee C Stores Ltd.",
    "wof:placetype":"venue"
},
  "geometry": {"coordinates":[-3.723894,56.009331],"type":"Point"}
}