{
  "type": "Feature",
  "properties": {
    "iso:country":"GB",
    "sg:address":"The Green, Barlaston",
    "sg:city":"Stoke-on-trent",
    "sg:classifiers":[
        {
            "category":"Education",
            "subcategory":"Library",
            "type":"Public Place"
        }
    ],
    "sg:phone":"+44 1782 372703",
    "sg:postcode":"ST12 9AB",
    "sg:province":"Staffordshire",
    "sg:tags":[
        "book"
    ],
    "wof:name":"Barlaston Library",
    "wof:placetype":"venue"
},
  "geometry": {"coordinates":[-2.175069,53.029369],"type":"Point"}
}