{
  "type": "Feature",
  "properties": {
    "addr:full":"Sharston Rd, Sharston Industrial Area Manchester Greater Manchester M22 4RA",
    "addr:postcode":"m22 4ra",
    "addr:street":"Sharston Rd Sharston Industrial",
    "iso:country":"GB",
    "sg:address":"Sharston Rd, Sharston Industrial Area",
    "sg:city":"Manchester",
    "sg:classifiers":[
        {
            "category":"Shopping",
            "subcategory":"Computers & Home Electronics",
            "type":"Retail Goods"
        }
    ],
    "sg:phone":"+44 161 998 5454",
    "sg:postcode":"M22 4RA",
    "sg:province":"Greater Manchester",
    "sg:tags":[
        "electrical"
    ],
    "wof:name":"Wylex Ltd",
    "wof:placetype":"venue"
},
  "geometry": {"coordinates":[-2.254031,53.40089],"type":"Point"}
}