{
  "type": "Feature",
  "properties": {
    "iso:country":"GB",
    "sg:address":"Vine Park Farm, Thursford Road",
    "sg:city":"Fakenham",
    "sg:classifiers":[
        {
            "category":"Farming",
            "subcategory":"Livestock Farm",
            "type":"Manufacturing & Wholesale Goods"
        }
    ],
    "sg:postcode":"NR21 0PF",
    "sg:province":"Norfolk",
    "sg:tags":[
        "others"
    ],
    "wof:name":"W J & M M Bushell & Sons",
    "wof:placetype":"venue"
},
  "geometry": {"coordinates":[0.93873,52.870834],"type":"Point"}
}