{
  "type": "Feature",
  "properties": {
    "addr:full":"5 Rosemount Terr Crook Durham DL15 9EN",
    "addr:housenumber":"5",
    "addr:postcode":"dl15 9en",
    "addr:street":"Rosemount Terr",
    "iso:country":"GB",
    "sg:address":"5 Rosemount Terr",
    "sg:city":"Crook",
    "sg:classifiers":[
        {
            "category":"Retail",
            "subcategory":"Repair Shop",
            "type":"Services"
        }
    ],
    "sg:phone":"+44 1388 767883",
    "sg:postcode":"DL15 9EN",
    "sg:province":"Durham",
    "sg:tags":[
        "radio",
        "television",
        "video"
    ],
    "wof:name":"Bowdene",
    "wof:placetype":"venue"
},
  "geometry": {"coordinates":[-1.746534,54.717266],"type":"Point"}
}