{
  "type": "Feature",
  "properties": {
    "addr:full":"122 Baker Street London Greater London W1U 6TU",
    "addr:housenumber":"122",
    "addr:postcode":"w1u 6tu",
    "addr:street":"Baker Street",
    "iso:country":"GB",
    "sg:address":"122 Baker Street",
    "sg:city":"London",
    "sg:classifiers":[
        {
            "category":"Fast Food",
            "type":"Food & Drink"
        }
    ],
    "sg:phone":"+44 20 7487 4003",
    "sg:postcode":"W1U 6TU",
    "sg:province":"Greater London",
    "sg:tags":[
        "away",
        "take"
    ],
    "wof:name":"McDonalds Restaurants Ltd.",
    "wof:placetype":"venue"
},
  "geometry": {"coordinates":[-0.156960994,51.5213813782],"type":"Point"}
}