{
  "type": "Feature",
  "properties": {
    "iso:country":"GB",
    "sg:address":"20 Gladstone Rd",
    "sg:city":"Horsham",
    "sg:classifiers":[
        {
            "category":"Shopping",
            "subcategory":"Mobile Phones",
            "type":"Retail Goods"
        }
    ],
    "sg:phone":"+44 1403 273858",
    "sg:postcode":"RH12 2NN",
    "sg:province":"West Sussex",
    "wof:name":"G R Communications",
    "wof:placetype":"venue"
},
  "geometry": {"coordinates":[-0.319393,51.067432],"type":"Point"}
}