{
  "type": "Feature",
  "properties": {
    "addr:full":"16 Woodstock Street London Greater London W1C 2AJ",
    "addr:housenumber":"16",
    "addr:postcode":"w1c 2aj",
    "addr:street":"Woodstock Street",
    "iso:country":"GB",
    "sg:address":"16 Woodstock Street",
    "sg:city":"London",
    "sg:classifiers":[
        {
            "category":"Shopping",
            "subcategory":"Party Supplies",
            "type":"Retail Goods"
        }
    ],
    "sg:postcode":"W1C 2AJ",
    "sg:province":"Greater London",
    "sg:tags":[
        "novelty"
    ],
    "wof:name":"American Party Store",
    "wof:placetype":"venue"
},
  "geometry": {"coordinates":[-0.147439003,51.5140533447],"type":"Point"}
}