{
  "type": "Feature",
  "properties": {
    "iso:country":"GB",
    "sg:address":"12 Queens Parade",
    "sg:city":"Lancing",
    "sg:classifiers":[
        {
            "category":"Shopping",
            "subcategory":"Comic Books",
            "type":"Retail Goods"
        }
    ],
    "sg:postcode":"BN15 9BA",
    "sg:province":"West Sussex",
    "sg:tags":[
        "jeweller"
    ],
    "wof:name":"The Jewellers Workshop",
    "wof:placetype":"venue"
},
  "geometry": {"coordinates":[-0.313749,50.823738],"type":"Point"}
}