{
  "type": "Feature",
  "properties": {
    "addr:full":"Whitefriars, Chesterton Cambridge Cambridgeshire CB4 1NN",
    "addr:postcode":"cb4 1nn",
    "addr:street":"Whitefriars",
    "iso:country":"GB",
    "sg:address":"Whitefriars, Chesterton",
    "sg:city":"Cambridge",
    "sg:classifiers":[
        {
            "category":"Social Services",
            "subcategory":"Adult Care",
            "type":"Services"
        },
        {
            "category":"Government",
            "subcategory":"Office",
            "type":"Public Place"
        }
    ],
    "sg:postcode":"CB4 1NN",
    "sg:province":"Cambridgeshire",
    "sg:tags":[
        "housing",
        "local",
        "sheltered"
    ],
    "wof:name":"Whitefriars Sheltered Housing",
    "wof:placetype":"venue"
},
  "geometry": {"coordinates":[0.1411650032,52.2249717712],"type":"Point"}
}