{
  "type": "Feature",
  "properties": {
    "addr:full":"Anfield House, Southburgh Thetford Norfolk IP25 7TJ",
    "addr:postcode":"ip25 7tj",
    "addr:street":"Southburgh",
    "iso:country":"GB",
    "sg:address":"Anfield House, Southburgh",
    "sg:city":"Thetford",
    "sg:classifiers":[
        {
            "category":"Professional",
            "subcategory":"Engineering",
            "type":"Services"
        }
    ],
    "sg:phone":"+44 1953 851437",
    "sg:postcode":"IP25 7TJ",
    "sg:province":"Norfolk",
    "sg:tags":[
        "contractor",
        "electrical",
        "engineer"
    ],
    "wof:name":"T.J Price",
    "wof:placetype":"venue"
},
  "geometry": {"coordinates":[0.9478210211,52.6034851074],"type":"Point"}
}