{
  "type": "Feature",
  "properties": {
    "addr:full":"Hothfield Works, Station Rd Ashford Kent TN23 1PP",
    "addr:housenumber":"hothfield",
    "addr:postcode":"tn23 1pp",
    "addr:street":"Station Rd",
    "iso:country":"GB",
    "sg:address":"Hothfield Works, Station Rd",
    "sg:city":"Ashford",
    "sg:classifiers":[
        {
            "category":"Manufacturing",
            "subcategory":"Building Materials",
            "type":"Manufacturing & Wholesale Goods"
        }
    ],
    "sg:phone":"+44 1233 611611",
    "sg:postcode":"TN23 1PP",
    "sg:province":"Kent",
    "sg:tags":[
        "tarmac",
        "asphalt"
    ],
    "wof:name":"Tarmac Quarry Products (Southern) Ltd",
    "wof:placetype":"venue"
},
  "geometry": {"coordinates":[0.876037,51.146633],"type":"Point"}
}