{
  "type": "Feature",
  "properties": {
    "iso:country":"GB",
    "sg:address":"185 Crayford Road, Crayford",
    "sg:city":"Dartford",
    "sg:classifiers":[
        {
            "category":"Food & Beverages",
            "subcategory":"Bakery",
            "type":"Retail Goods"
        }
    ],
    "sg:phone":"+44 1322 523189",
    "sg:postcode":"DA1 4HA",
    "sg:province":"Kent",
    "sg:tags":[
        "baker"
    ],
    "wof:name":"The Bakers Oven",
    "wof:placetype":"venue"
},
  "geometry": {"coordinates":[0.179225,51.451363],"type":"Point"}
}