{
  "type": "Feature",
  "properties": {
    "addr:full":"15 Merrion Way Leeds West Yorkshire LS2 8BT",
    "addr:housenumber":"15",
    "addr:postcode":"ls2 8bt",
    "addr:street":"Merrion Way",
    "iso:country":"GB",
    "sg:address":"15 Merrion Way",
    "sg:city":"Leeds",
    "sg:classifiers":[
        {
            "category":"Fast Food",
            "type":"Food & Drink"
        }
    ],
    "sg:phone":"+44 113 244 2752",
    "sg:postcode":"LS2 8BT",
    "sg:province":"West Yorkshire",
    "sg:tags":[
        "away",
        "meal",
        "outlet",
        "take"
    ],
    "wof:name":"Sheila's Sandwiches",
    "wof:placetype":"venue"
},
  "geometry": {"coordinates":[-1.543474,53.802357],"type":"Point"}
}