{
  "type": "Feature",
  "properties": {
    "addr:full":"2 Milford Ho, 7 Queen Anne St West End Hampshire W1M 9FD",
    "addr:housenumber":"2;7",
    "addr:postcode":"w1m 9fd",
    "addr:street":"Milford Ho;Queen Anne St",
    "iso:country":"GB",
    "sg:address":"2 Milford Ho, 7 Queen Anne St",
    "sg:city":"West End",
    "sg:classifiers":[
        {
            "category":"Travel",
            "subcategory":"Travel Agent",
            "type":"Entertainment"
        }
    ],
    "sg:phone":"+44 20 7323 1220",
    "sg:postcode":"W1M 9FD",
    "sg:province":"Hampshire",
    "wof:name":"Vacations International",
    "wof:placetype":"venue"
},
  "geometry": {"coordinates":[-0.13899,51.50758],"type":"Point"}
}