{
  "type": "Feature",
  "properties": {
    "addr:full":"83 Tottenham Lane London Greater London N8 9BE",
    "addr:housenumber":"83",
    "addr:postcode":"n8 9be",
    "addr:street":"Tottenham Lane",
    "iso:country":"GB",
    "sg:address":"83 Tottenham Lane",
    "sg:city":"London",
    "sg:classifiers":[
        {
            "category":"Personal",
            "subcategory":"Barber",
            "type":"Services"
        }
    ],
    "sg:phone":"+44 20 8348 0455",
    "sg:postcode":"N8 9BE",
    "sg:province":"Greater London",
    "sg:tags":[
        "men's",
        "gents",
        "hairdresser"
    ],
    "wof:name":"Simon's Hair Fashions",
    "wof:placetype":"venue"
},
  "geometry": {"coordinates":[-0.1162929982,51.5837059021],"type":"Point"}
}