{
  "type": "Feature",
  "properties": {
    "addr:full":"9 Granville Lane Newport Newport NP20 2AL",
    "addr:housenumber":"9",
    "addr:postcode":"np20 2al",
    "addr:street":"Granville Lane",
    "iso:country":"GB",
    "sg:address":"9 Granville Lane",
    "sg:city":"Newport",
    "sg:classifiers":[
        {
            "category":"Wholesale",
            "subcategory":"Construction Materials",
            "type":"Manufacturing & Wholesale Goods"
        }
    ],
    "sg:postcode":"NP20 2AL",
    "sg:province":"Newport",
    "sg:tags":[
        "merchant",
        "glass"
    ],
    "wof:name":"The Glass Shop",
    "wof:placetype":"venue"
},
  "geometry": {"coordinates":[-2.9885339737,51.5833435059],"type":"Point"}
}