{
  "type": "Feature",
  "properties": {
    "iso:country":"GB",
    "sg:address":"11 Rubislaw Terrace",
    "sg:city":"Aberdeen",
    "sg:classifiers":[
        {
            "category":"Mining & Drilling",
            "type":"Manufacturing & Wholesale Goods"
        }
    ],
    "sg:phone":"+44 1224 636002",
    "sg:postcode":"AB10 1XE",
    "sg:province":"Aberdeen City",
    "sg:tags":[
        "oil",
        "petroleum"
    ],
    "wof:name":"Dove Energy Ltd.",
    "wof:placetype":"venue"
},
  "geometry": {"coordinates":[-2.1168909073,57.1434555054],"type":"Point"}
}