{
  "type": "Feature",
  "properties": {
    "iso:country":"GB",
    "sg:address":"North Street, Wiveliscombe",
    "sg:city":"Taunton",
    "sg:classifiers":[
        {
            "category":"Education",
            "subcategory":"School",
            "type":"Public Place"
        },
        {
            "category":"Government",
            "subcategory":"Office",
            "type":"Public Place"
        }
    ],
    "sg:phone":"+44 1984 623325",
    "sg:postcode":"TA4 2LA",
    "sg:province":"Devon",
    "sg:tags":[
        "local",
        "authority"
    ],
    "wof:name":"Wiveliscombe County Primary School",
    "wof:placetype":"venue"
},
  "geometry": {"coordinates":[-3.3088541031,51.0414581299],"type":"Point"}
}