{
  "type": "Feature",
  "properties": {
    "addr:full":"14 St Mary Street Kirkcudbright Dumfries and Galloway DG6 4DN",
    "addr:housenumber":"14",
    "addr:postcode":"dg6 4dn",
    "addr:street":"St Mary Street",
    "iso:country":"GB",
    "sg:address":"14 St Mary Street",
    "sg:city":"Kirkcudbright",
    "sg:classifiers":[
        {
            "category":"Food & Beverages",
            "subcategory":"Liquor & Beverages",
            "type":"Retail Goods"
        },
        {
            "category":"Food & Beverages",
            "subcategory":"Fruits & Vegetables",
            "type":"Retail Goods"
        }
    ],
    "sg:phone":"+44 1557 330417",
    "sg:postcode":"DG6 4DN",
    "sg:province":"Dumfries and Galloway",
    "sg:tags":[
        "beer",
        "greengrocer",
        "spirit",
        "wines"
    ],
    "wof:name":"William Ross",
    "wof:placetype":"venue"
},
  "geometry": {"coordinates":[-4.044148922,54.8412361145],"type":"Point"}
}