{
  "type": "Feature",
  "properties": {
    "addr:full":"79 Cheetham Hill Rd Manchester Greater Manchester M4 4ER",
    "addr:housenumber":"79",
    "addr:postcode":"m4 4er",
    "addr:street":"Cheetham Hill Rd",
    "iso:country":"GB",
    "sg:address":"79 Cheetham Hill Rd",
    "sg:city":"Manchester",
    "sg:classifiers":[
        {
            "category":"Manufacturing",
            "subcategory":"Textiles",
            "type":"Manufacturing & Wholesale Goods"
        }
    ],
    "sg:phone":"+44 161 832 6964",
    "sg:postcode":"M4 4ER",
    "sg:province":"Greater Manchester",
    "sg:tags":[
        "made-up"
    ],
    "wof:name":"Jane Louise Curtains",
    "wof:placetype":"venue"
},
  "geometry": {"coordinates":[-2.2402489185,53.4928092957],"type":"Point"}
}