{
  "type": "Feature",
  "properties": {
    "iso:country":"GB",
    "sg:address":"Unit 2, Habat Enterprise Park, Clovelley Road I E",
    "sg:city":"Bideford",
    "sg:classifiers":[
        {
            "category":"Home & Garden",
            "subcategory":"Building Materials",
            "type":"Retail Goods"
        }
    ],
    "sg:postcode":"EX39 3HN",
    "sg:province":"Devon",
    "sg:tags":[
        "garage",
        "door"
    ],
    "wof:name":"Garage Doors Direct (S W)",
    "wof:placetype":"venue"
},
  "geometry": {"coordinates":[-4.21272,51.01545],"type":"Point"}
}