{
  "type": "Feature",
  "properties": {
    "iso:country":"GB",
    "sg:address":"97-107 Southampton Row",
    "sg:city":"London",
    "sg:classifiers":[
        {
            "category":"Insurance",
            "subcategory":"Insurance Agent",
            "type":"Services"
        }
    ],
    "sg:phone":"+44 20 7436 4451",
    "sg:postcode":"WC1B 4AG",
    "sg:province":"Greater London",
    "wof:name":"Endsleigh Insurance Services Ltd.",
    "wof:placetype":"venue"
},
  "geometry": {"coordinates":[-0.123651,51.520893],"type":"Point"}
}