{
  "type": "Feature",
  "properties": {
    "addr:full":"3 South Street Crook Durham DL15 8NE",
    "addr:housenumber":"3",
    "addr:postcode":"dl15 8ne",
    "addr:street":"South Street",
    "iso:country":"GB",
    "sg:address":"3 South Street",
    "sg:city":"Crook",
    "sg:classifiers":[
        {
            "category":"Manufacturing",
            "subcategory":"Tools & Machinery",
            "type":"Manufacturing & Wholesale Goods"
        },
        {
            "category":"Insurance",
            "subcategory":"Insurance Agent",
            "type":"Services"
        }
    ],
    "sg:phone":"+44 1388 766048",
    "sg:postcode":"DL15 8NE",
    "sg:province":"Durham",
    "sg:tags":[
        "society",
        "friendly"
    ],
    "wof:name":"Langley Insurance Agents",
    "wof:placetype":"venue"
},
  "geometry": {"coordinates":[-1.745282,54.714573],"type":"Point"}
}