{
  "type": "Feature",
  "properties": {
    "iso:country":"GB",
    "sg:address":"7 Church Street, Twyford",
    "sg:city":"Reading",
    "sg:classifiers":[
        {
            "category":"Health Services",
            "subcategory":"Optometrist",
            "type":"Services"
        }
    ],
    "sg:phone":"+44 118 934 5566",
    "sg:postcode":"RG10 9DN",
    "sg:province":"Berkshire",
    "sg:tags":[
        "optician"
    ],
    "wof:name":"Batemans (Opticians) Ltd.",
    "wof:placetype":"venue"
},
  "geometry": {"coordinates":[-0.86639,51.477448],"type":"Point"}
}