{
  "type": "Feature",
  "properties": {
    "addr:full":"Dunkeswell Honiton Devon EX14 4RH",
    "addr:housenumber":"dunkeswell",
    "addr:postcode":"ex14 4rh",
    "iso:country":"GB",
    "sg:address":"Dunkeswell",
    "sg:city":"Honiton",
    "sg:classifiers":[
        {
            "category":"Retail",
            "subcategory":"Repair Shop",
            "type":"Services"
        }
    ],
    "sg:phone":"+44 1404 891682",
    "sg:postcode":"EX14 4RH",
    "sg:province":"Devon",
    "sg:tags":[
        "upholstering",
        "upholsterer"
    ],
    "wof:name":"Badgers Holt Upholstery",
    "wof:placetype":"venue"
},
  "geometry": {"coordinates":[-3.1956589222,50.8475914001],"type":"Point"}
}