{
  "type": "Feature",
  "properties": {
    "iso:country":"GB",
    "sg:address":"12 Featherbed Lane",
    "sg:city":"Croydon",
    "sg:classifiers":[
        {
            "category":"Retail",
            "subcategory":"Event Space",
            "type":"Services"
        }
    ],
    "sg:postcode":"CR0 9AE",
    "sg:province":"Surrey",
    "sg:tags":[
        "exhibition",
        "organiser"
    ],
    "wof:name":"J A C Business Services",
    "wof:placetype":"venue"
},
  "geometry": {"coordinates":[-0.036594,51.350849],"type":"Point"}
}