{
  "type": "Feature",
  "properties": {
    "addr:full":"297 New Kings Rd, Fulham Fulham Greater London SW6 4RE",
    "addr:housenumber":"297",
    "addr:postcode":"sw6 4re",
    "addr:street":"New Kings Rd",
    "iso:country":"GB",
    "sg:address":"297 New Kings Rd, Fulham",
    "sg:city":"Fulham",
    "sg:classifiers":[
        {
            "category":"Shopping",
            "subcategory":"Thrift Store",
            "type":"Retail Goods"
        }
    ],
    "sg:phone":"+44 20 7736 2833",
    "sg:postcode":"SW6 4RE",
    "sg:province":"Greater London",
    "sg:tags":[
        "shop",
        "charity"
    ],
    "wof:name":"FARA Charity Shops",
    "wof:placetype":"venue"
},
  "geometry": {"coordinates":[-0.202998,51.472145],"type":"Point"}
}