{
  "type": "Feature",
  "properties": {
    "addr:full":"123 Station Road Ashington Northumberland NE63 8HQ",
    "addr:housenumber":"123",
    "addr:postcode":"ne63 8hq",
    "addr:street":"Station Road;Northumberland",
    "iso:country":"GB",
    "sg:address":"123 Station Road",
    "sg:city":"Ashington",
    "sg:classifiers":[
        {
            "category":"Home & Garden",
            "subcategory":"Furniture",
            "type":"Retail Goods"
        }
    ],
    "sg:phone":"+44 1670 520082",
    "sg:postcode":"NE63 8HQ",
    "sg:province":"Northumberland",
    "wof:name":"The Repro Centre",
    "wof:placetype":"venue"
},
  "geometry": {"coordinates":[-1.5795149803,55.1829185486],"type":"Point"}
}