{
  "type": "Feature",
  "properties": {
    "addr:full":"15 Lancaster Way Nottingham Nottinghamshire NG8 6PH",
    "addr:housenumber":"15",
    "addr:postcode":"ng8 6ph",
    "addr:street":"Lancaster Way",
    "iso:country":"GB",
    "sg:address":"15 Lancaster Way",
    "sg:city":"Nottingham",
    "sg:classifiers":[
        {
            "category":"Building & Trades",
            "subcategory":"Plumbing",
            "type":"Services"
        }
    ],
    "sg:phone":"+44 115 945 9797",
    "sg:postcode":"NG8 6PH",
    "sg:province":"Nottinghamshire",
    "sg:tags":[
        "heating"
    ],
    "wof:name":"Andrew Westbury",
    "wof:placetype":"venue"
},
  "geometry": {"coordinates":[-1.2332969904,52.9791183472],"type":"Point"}
}