{
  "type": "Feature",
  "properties": {
    "addr:full":"2 Stuart Place, East Twerton Bath Somerset BA2 3RQ",
    "addr:housenumber":"2",
    "addr:postcode":"ba2 3rq",
    "addr:street":"Stuart Place East",
    "iso:country":"GB",
    "sg:address":"2 Stuart Place, East Twerton",
    "sg:city":"Bath",
    "sg:classifiers":[
        {
            "category":"Building & Trades",
            "subcategory":"Construction",
            "type":"Services"
        }
    ],
    "sg:postcode":"BA2 3RQ",
    "sg:province":"Somerset",
    "sg:tags":[
        "roofing"
    ],
    "wof:name":"J P Cousins",
    "wof:placetype":"venue"
},
  "geometry": {"coordinates":[-2.3792030811,51.380153656],"type":"Point"}
}