{
  "type": "Feature",
  "properties": {
    "addr:full":"Crowland House, Vicarage Farm Rd Peterborough Cambridgeshire PE1 5TP",
    "addr:postcode":"pe1 5tp",
    "addr:street":"Farm Rd",
    "iso:country":"GB",
    "sg:address":"Crowland House, Vicarage Farm Rd",
    "sg:city":"Peterborough",
    "sg:classifiers":[
        {
            "category":"Manufacturing",
            "subcategory":"Signs",
            "type":"Manufacturing & Wholesale Goods"
        }
    ],
    "sg:phone":"+44 1733 897877",
    "sg:postcode":"PE1 5TP",
    "sg:province":"Cambridgeshire",
    "sg:tags":[
        "nameplate"
    ],
    "wof:name":"Crowland Ltd",
    "wof:placetype":"venue"
},
  "geometry": {"coordinates":[-0.2054090053,52.5797691345],"type":"Point"}
}