{
  "type": "Feature",
  "properties": {
    "addr:full":"Woodlands Special Needs Nursery, Woodlands Road Gillingham Kent ME7 2BX",
    "addr:postcode":"me7 2bx",
    "addr:street":"Woodlands Road",
    "iso:country":"GB",
    "sg:address":"Woodlands Special Needs Nursery, Woodlands Road",
    "sg:city":"Gillingham",
    "sg:classifiers":[
        {
            "category":"Health Services",
            "subcategory":"Clinic",
            "type":"Services"
        }
    ],
    "sg:phone":"+44 1634 854452",
    "sg:postcode":"ME7 2BX",
    "sg:province":"Kent",
    "sg:tags":[
        "nh"
    ],
    "wof:name":"Medway N H S Trust",
    "wof:placetype":"venue"
},
  "geometry": {"coordinates":[0.549543,51.386459],"type":"Point"}
}