{
  "type": "Feature",
  "properties": {
    "iso:country":"GB",
    "sg:address":"22 Soho Square",
    "sg:city":"West End",
    "sg:classifiers":[
        {
            "category":"Utilities",
            "type":"Services"
        }
    ],
    "sg:phone":"+44 20 7434 0408",
    "sg:postcode":"W1V 5FJ",
    "sg:province":"Hampshire",
    "sg:tags":[
        "internet"
    ],
    "wof:name":"cScape",
    "wof:placetype":"venue"
},
  "geometry": {"coordinates":[-0.13899,51.50758],"type":"Point"}
}