{
  "type": "Feature",
  "properties": {
    "addr:full":"50 High Street, Bushey Watford Hertfordshire WD2 3DN",
    "addr:housenumber":"50",
    "addr:postcode":"wd2 3dn",
    "addr:street":"High Street",
    "iso:country":"GB",
    "sg:address":"50 High Street, Bushey",
    "sg:city":"Watford",
    "sg:classifiers":[
        {
            "category":"Bars & Pubs",
            "type":"Food & Drink"
        }
    ],
    "sg:phone":"+44 20 8421 9051",
    "sg:postcode":"WD2 3DN",
    "sg:province":"Hertfordshire",
    "sg:tags":[
        "pubs",
        "inn"
    ],
    "wof:name":"Red Lion",
    "wof:placetype":"venue"
},
  "geometry": {"coordinates":[-0.36307,51.644341],"type":"Point"}
}