{
  "type": "Feature",
  "properties": {
    "addr:full":"216 Hilltown Dundee Dundee City DD3 7AU",
    "addr:housenumber":"216",
    "addr:postcode":"dd3 7au",
    "addr:street":"Hilltown",
    "iso:country":"GB",
    "sg:address":"216 Hilltown",
    "sg:city":"Dundee",
    "sg:classifiers":[
        {
            "category":"Professional",
            "subcategory":"Management & Consulting",
            "type":"Services"
        }
    ],
    "sg:phone":"+44 1382 227963",
    "sg:postcode":"DD3 7AU",
    "sg:province":"Dundee City",
    "sg:tags":[
        "consultant",
        "training"
    ],
    "wof:name":"Gas Training Consultants",
    "wof:placetype":"venue"
},
  "geometry": {"coordinates":[-2.9742660522,56.4686164856],"type":"Point"}
}