{
  "type": "Feature",
  "properties": {
    "addr:full":"21 Alexandra Road Swadlincote Derbyshire DE11 9SP",
    "addr:housenumber":"21",
    "addr:postcode":"de11 9sp",
    "addr:street":"Alexandra Road",
    "iso:country":"GB",
    "sg:address":"21 Alexandra Road",
    "sg:city":"Swadlincote",
    "sg:classifiers":[
        {
            "category":"Personal",
            "subcategory":"Barber",
            "type":"Services"
        }
    ],
    "sg:phone":"+44 1283 552221",
    "sg:postcode":"DE11 9SP",
    "sg:province":"Derbyshire",
    "sg:tags":[
        "men's",
        "hairdresser"
    ],
    "wof:name":"The Barber Shop",
    "wof:placetype":"venue"
},
  "geometry": {"coordinates":[-1.559568,52.7719],"type":"Point"}
}