{
  "type": "Feature",
  "properties": {
    "addr:full":"41 Portland Road, Hucknall Nottingham Nottinghamshire NG15 7SL",
    "addr:housenumber":"41",
    "addr:postcode":"ng15 7sl",
    "addr:street":"Portland Road",
    "iso:country":"GB",
    "sg:address":"41 Portland Road, Hucknall",
    "sg:city":"Nottingham",
    "sg:classifiers":[
        {
            "category":"Professional",
            "subcategory":"Art Services",
            "type":"Services"
        }
    ],
    "sg:phone":"+44 115 963 7158",
    "sg:postcode":"NG15 7SL",
    "sg:province":"Nottinghamshire",
    "sg:tags":[
        "photographer"
    ],
    "wof:name":"Great Occasions",
    "wof:placetype":"venue"
},
  "geometry": {"coordinates":[-1.1987320185,53.0356292725],"type":"Point"}
}