{
  "type": "Feature",
  "properties": {
    "addr:full":"1a Sandwich St, Walkden Manchester Greater Manchester M28 3XN",
    "addr:housenumber":"1a",
    "addr:postcode":"m28 3xn",
    "addr:street":"Sandwich St",
    "iso:country":"GB",
    "sg:address":"1a Sandwich St, Walkden",
    "sg:city":"Manchester",
    "sg:classifiers":[
        {
            "category":"Building & Trades",
            "subcategory":"Construction",
            "type":"Services"
        }
    ],
    "sg:phone":"+44 161 703 7203",
    "sg:postcode":"M28 3XN",
    "sg:province":"Greater Manchester",
    "sg:tags":[
        "roofing"
    ],
    "wof:name":"A.A Roofing",
    "wof:placetype":"venue"
},
  "geometry": {"coordinates":[-2.393548,53.522369],"type":"Point"}
}