{
  "type": "Feature",
  "properties": {
    "addr:full":"12 Frinton Road, Holland-on-sea Clacton-on-sea Essex CO15 5UL",
    "addr:housenumber":"12",
    "addr:postcode":"co15 5ul",
    "addr:street":"Frinton Road",
    "iso:country":"GB",
    "sg:address":"12 Frinton Road, Holland-on-sea",
    "sg:city":"Clacton-on-sea",
    "sg:classifiers":[
        {
            "category":"Shopping",
            "subcategory":"Jewelry",
            "type":"Retail Goods"
        },
        {
            "category":"Shopping",
            "subcategory":"Comic Books",
            "type":"Retail Goods"
        }
    ],
    "sg:phone":"+44 1255 813113",
    "sg:postcode":"CO15 5UL",
    "sg:province":"Essex",
    "sg:tags":[
        "jeweller",
        "sale",
        "jewellery"
    ],
    "wof:name":"Holland Jewellers",
    "wof:placetype":"venue"
},
  "geometry": {"coordinates":[1.182609,51.802917],"type":"Point"}
}