{
  "type": "Feature",
  "properties": {
    "iso:country":"GB",
    "sg:address":"Stansted Airport",
    "sg:city":"Stansted",
    "sg:classifiers":[
        {
            "category":"Travel",
            "subcategory":"Travel Agent",
            "type":"Entertainment"
        }
    ],
    "sg:phone":"+44 1279 680350",
    "sg:postcode":"CM24 1QN",
    "sg:province":"Essex",
    "wof:name":"Tour Operators Study Group",
    "wof:placetype":"venue"
},
  "geometry": {"coordinates":[0.2197999954,51.8838310242],"type":"Point"}
}