{
  "type": "Feature",
  "properties": {
    "addr:full":"40 Bells Lane, Hoo Rochester Kent ME3 9HU",
    "addr:housenumber":"40",
    "addr:postcode":"me3 9hu",
    "addr:street":"Bells Lane",
    "iso:country":"GB",
    "sg:address":"40 Bells Lane, Hoo",
    "sg:city":"Rochester",
    "sg:classifiers":[
        {
            "category":"Retail",
            "subcategory":"Driving School",
            "type":"Services"
        }
    ],
    "sg:phone":"+44 1634 251670",
    "sg:postcode":"ME3 9HU",
    "sg:province":"Kent",
    "wof:name":"Broadway Driving School",
    "wof:placetype":"venue"
},
  "geometry": {"coordinates":[0.5630429983,51.4224624634],"type":"Point"}
}