{
  "type": "Feature",
  "properties": {
    "addr:full":"Unit D 14 Dukes Walk, Chequers Centre Maidstone Kent ME15 6AS",
    "addr:housenumber":"unit d 14",
    "addr:postcode":"me15 6as",
    "addr:street":"Dukes Walk",
    "iso:country":"GB",
    "sg:address":"Unit D 14 Dukes Walk, Chequers Centre",
    "sg:city":"Maidstone",
    "sg:classifiers":[
        {
            "category":"Shopping",
            "subcategory":"Discount & Variety Stores",
            "type":"Retail Goods"
        }
    ],
    "sg:phone":"+44 1622 691558",
    "sg:postcode":"ME15 6AS",
    "sg:province":"Kent",
    "sg:tags":[
        "centre"
    ],
    "wof:name":"Poundland",
    "wof:placetype":"venue"
},
  "geometry": {"coordinates":[0.5253,51.272579],"type":"Point"}
}