{
  "type": "Feature",
  "properties": {
    "addr:full":"121 Moffat Street Glasgow Glasgow City G5 0NG",
    "addr:housenumber":"121",
    "addr:postcode":"g5 0ng",
    "addr:street":"Moffat Street",
    "iso:country":"GB",
    "sg:address":"121 Moffat Street",
    "sg:city":"Glasgow",
    "sg:classifiers":[
        {
            "category":"Home & Garden",
            "subcategory":"Home Furnishings",
            "type":"Retail Goods"
        },
        {
            "category":"Manufacturing",
            "subcategory":"Textiles",
            "type":"Manufacturing & Wholesale Goods"
        }
    ],
    "sg:phone":"+44 141 429 1124",
    "sg:postcode":"G5 0NG",
    "sg:province":"Glasgow City",
    "sg:tags":[
        "made-up",
        "fitted",
        "furniture"
    ],
    "wof:name":"Elite Bedding Co Ltd",
    "wof:placetype":"venue"
},
  "geometry": {"coordinates":[-4.24187994,55.847278595],"type":"Point"}
}