{
  "type": "Feature",
  "properties": {
    "iso:country":"GB",
    "sg:address":"Stephen House Edinburgh Road, 16 Edinburgh Road",
    "sg:city":"Perth",
    "sg:classifiers":[
        {
            "category":"Building & Trades",
            "subcategory":"Construction",
            "type":"Services"
        }
    ],
    "sg:postcode":"PH2 8BS",
    "sg:province":"Perth and Kinross",
    "sg:tags":[
        "builder"
    ],
    "wof:name":"Castle Homes (Scotland) Ltd.",
    "wof:placetype":"venue"
},
  "geometry": {"coordinates":[-3.4324140549,56.3960533142],"type":"Point"}
}