{
  "type": "Feature",
  "properties": {
    "iso:country":"GB",
    "sg:address":"5-11 Hartington Pl",
    "sg:city":"Eastbourne",
    "sg:classifiers":[
        {
            "category":"Organizations",
            "subcategory":"Non-profit Organization",
            "type":"Services"
        }
    ],
    "sg:phone":"+44 1323 721828",
    "sg:postcode":"BN21 3BS",
    "sg:province":"East Sussex",
    "sg:tags":[
        "organisation",
        "voluntary",
        "charity"
    ],
    "wof:name":"Royal Alfred Seafarers Housing Associati",
    "wof:placetype":"venue"
},
  "geometry": {"coordinates":[0.287521,50.766247],"type":"Point"}
}