{
  "type": "Feature",
  "properties": {
    "addr:full":"181 Newtown Road Carlisle Cumbria CA2 7LN",
    "addr:housenumber":"181",
    "addr:postcode":"ca2 7ln",
    "addr:street":"Newtown Road",
    "iso:country":"GB",
    "sg:address":"181 Newtown Road",
    "sg:city":"Carlisle",
    "sg:classifiers":[
        {
            "category":"Shopping",
            "subcategory":"Florist",
            "type":"Retail Goods"
        }
    ],
    "sg:postcode":"CA2 7LN",
    "sg:province":"Cumbria",
    "wof:name":"W Lees Florist",
    "wof:placetype":"venue"
},
  "geometry": {"coordinates":[-2.9650681019,54.8952255249],"type":"Point"}
}