{
  "type": "Feature",
  "properties": {
    "iso:country":"GB",
    "sg:address":"9b Ladbroke Gro, Holland Park",
    "sg:city":"London",
    "sg:classifiers":[
        {
            "category":"Professional",
            "subcategory":"Advertising",
            "type":"Services"
        }
    ],
    "sg:phone":"+44 20 7727 5752",
    "sg:postcode":"W11 3BD",
    "sg:province":"Greater London",
    "wof:name":"E C M Trustees Ltd.",
    "wof:placetype":"venue"
},
  "geometry": {"coordinates":[-0.2035319954,51.5081863403],"type":"Point"}
}