{
  "type": "Feature",
  "properties": {
    "addr:full":"P O Box 1181 Bristol City of Bristol BS99 2PZ",
    "addr:housenumber":"p o;1181",
    "addr:postcode":"bs99 2pz",
    "iso:country":"GB",
    "sg:address":"P O Box 1181",
    "sg:city":"Bristol",
    "sg:classifiers":[
        {
            "category":"Professional",
            "subcategory":"Accounting & Tax Preparation",
            "type":"Services"
        }
    ],
    "sg:phone":"+44 117 907 9631",
    "sg:postcode":"BS99 2PZ",
    "sg:province":"City of Bristol",
    "sg:tags":[
        "herb",
        "spice"
    ],
    "wof:name":"Resurrection Drinks Ltd.",
    "wof:placetype":"venue"
},
  "geometry": {"coordinates":[-2.58545,51.45026],"type":"Point"}
}