{
  "type": "Feature",
  "properties": {
    "iso:country":"GB",
    "sg:address":"66 Fordham Road, Soham",
    "sg:city":"Ely",
    "sg:classifiers":[
        {
            "category":"Bars & Pubs",
            "type":"Food & Drink"
        }
    ],
    "sg:phone":"+44 1353 720405",
    "sg:postcode":"CB7 5AH",
    "sg:province":"Cambridgeshire",
    "sg:tags":[
        "pubs",
        "inn"
    ],
    "wof:name":"Cherrytree Public House",
    "wof:placetype":"venue"
},
  "geometry": {"coordinates":[0.351535,52.323631],"type":"Point"}
}