{
  "type": "Feature",
  "properties": {
    "addr:full":"83 Bettesworth Road Ryde Isle of Wight PO33 3EN",
    "addr:housenumber":"83",
    "addr:postcode":"po33 3en",
    "addr:street":"Bettesworth Road",
    "iso:country":"GB",
    "sg:address":"83 Bettesworth Road",
    "sg:city":"Ryde",
    "sg:classifiers":[
        {
            "category":"Manufacturing",
            "subcategory":"Aerospace",
            "type":"Manufacturing & Wholesale Goods"
        }
    ],
    "sg:postcode":"PO33 3EN",
    "sg:province":"Isle of Wight",
    "sg:tags":[
        "aircraft",
        "furnishing",
        "fitting"
    ],
    "wof:name":"Premier Aviation Ltd",
    "wof:placetype":"venue"
},
  "geometry": {"coordinates":[-1.170443058,50.7175331116],"type":"Point"}
}