{
  "type": "Feature",
  "properties": {
    "addr:full":"Sunmeadow Road, Hempsted Lane, Hempsted Gloucester Gloucestershire GL2 5HG",
    "addr:postcode":"gl2 5hg",
    "addr:street":"Sunmeadow Road Hempsted Lane",
    "iso:country":"GB",
    "sg:address":"Sunmeadow Road, Hempsted Lane, Hempsted",
    "sg:city":"Gloucester",
    "sg:classifiers":[
        {
            "category":"Wholesale",
            "subcategory":"Scrap",
            "type":"Manufacturing & Wholesale Goods"
        }
    ],
    "sg:phone":"+44 1452 527133",
    "sg:postcode":"GL2 5HG",
    "sg:province":"Gloucestershire",
    "sg:tags":[
        "waste",
        "metal"
    ],
    "wof:name":"Phelps Bros",
    "wof:placetype":"venue"
},
  "geometry": {"coordinates":[-2.2602651119,51.860824585],"type":"Point"}
}