{
  "type": "Feature",
  "properties": {
    "addr:full":"Unit 3 William Road London Greater London NW1 3EN",
    "addr:housenumber":"unit 3",
    "addr:postcode":"nw1 3en",
    "addr:street":"William Road",
    "iso:country":"GB",
    "sg:address":"Unit 3 William Road",
    "sg:city":"London",
    "sg:classifiers":[
        {
            "category":"Professional",
            "subcategory":"Printing & Photocopies",
            "type":"Services"
        }
    ],
    "sg:phone":"+44 20 7387 6071",
    "sg:postcode":"NW1 3EN",
    "sg:province":"Greater London",
    "sg:tags":[
        "printer"
    ],
    "wof:name":"Sarkpoint Reprographics Ltd.",
    "wof:placetype":"venue"
},
  "geometry": {"coordinates":[-0.139744,51.527168],"type":"Point"}
}