{
  "type": "Feature",
  "properties": {
    "iso:country":"GB",
    "sg:address":"Barbush Farm, Barochan Rd",
    "sg:city":"Johnstone",
    "sg:classifiers":[
        {
            "category":"Farming",
            "subcategory":"Farm",
            "type":"Manufacturing & Wholesale Goods"
        }
    ],
    "sg:postcode":"PA5 8YR",
    "sg:province":"Renfrewshire",
    "sg:tags":[
        "mixed",
        "crop"
    ],
    "wof:name":"Craig,John & Anne,",
    "wof:placetype":"venue"
},
  "geometry": {"coordinates":[-4.508344,55.836109],"type":"Point"}
}