{
  "type": "Feature",
  "properties": {
    "iso:country":"GB",
    "sg:address":"Clay Street",
    "sg:city":"Sheffield",
    "sg:classifiers":[
        {
            "category":"Banks & Credit Unions",
            "subcategory":"Financial Services",
            "type":"Services"
        },
        {
            "category":"Organizations",
            "subcategory":"Non-profit Organization",
            "type":"Services"
        }
    ],
    "sg:phone":"+44 114 242 4294",
    "sg:postcode":"S9 2PE",
    "sg:province":"South Yorkshire",
    "sg:tags":[
        "voluntary",
        "loan",
        "organisation",
        "charity"
    ],
    "wof:name":"South Yorkshire Community Foundation",
    "wof:placetype":"venue"
},
  "geometry": {"coordinates":[-1.430256,53.398022],"type":"Point"}
}