{
  "type": "Feature",
  "properties": {
    "addr:full":"297 Uttoxeter Rd Stoke-on-trent Staffordshire ST3 5LQ",
    "addr:housenumber":"297",
    "addr:postcode":"st3 5lq",
    "addr:street":"Uttoxeter Rd",
    "iso:country":"GB",
    "sg:address":"297 Uttoxeter Rd",
    "sg:city":"Stoke-on-trent",
    "sg:classifiers":[
        {
            "category":"Personal",
            "subcategory":"Beauty Salon",
            "type":"Services"
        }
    ],
    "sg:postcode":"ST3 5LQ",
    "sg:province":"Staffordshire",
    "sg:tags":[
        "unisex",
        "hairdresser"
    ],
    "wof:name":"Gunn,Angela,",
    "wof:placetype":"venue"
},
  "geometry": {"coordinates":[-2.120294,52.982681],"type":"Point"}
}