{
  "type": "Feature",
  "properties": {
    "addr:full":"Duke St Yard, Near Police Station Tredegar Blaenau Gwent NP22 3AG",
    "addr:postcode":"np22 3ag",
    "addr:street":"Duke St Yard Near Police;Tredegar Blaenau Gwent",
    "iso:country":"GB",
    "sg:address":"Duke St Yard, Near Police Station",
    "sg:city":"Tredegar",
    "sg:classifiers":[
        {
            "category":"Wholesale",
            "subcategory":"Scrap",
            "type":"Manufacturing & Wholesale Goods"
        }
    ],
    "sg:postcode":"NP22 3AG",
    "sg:province":"Blaenau Gwent",
    "sg:tags":[
        "breaker",
        "dismantlers"
    ],
    "wof:name":"Tredegar Car Dismantlers",
    "wof:placetype":"venue"
},
  "geometry": {"coordinates":[-3.2453370094,51.7728271484],"type":"Point"}
}