{
  "type": "Feature",
  "properties": {
    "addr:full":"Stanton Road, Barnes London Greater London SW13 0EY",
    "addr:postcode":"sw13 0ey",
    "addr:street":"Stanton Road",
    "iso:country":"GB",
    "sg:address":"Stanton Road, Barnes",
    "sg:city":"London",
    "sg:classifiers":[
        {
            "category":"Professional",
            "type":"Services"
        }
    ],
    "sg:phone":"+44 20 8876 5216",
    "sg:postcode":"SW13 0EY",
    "sg:province":"Greater London",
    "sg:tags":[
        "shopfitters"
    ],
    "wof:name":"Colson Shopfitting Ltd.",
    "wof:placetype":"venue"
},
  "geometry": {"coordinates":[-0.249216,51.472675],"type":"Point"}
}