{
  "type": "Feature",
  "properties": {
    "iso:country":"GB",
    "sg:address":"61-63 Waterside, Brightlingsea",
    "sg:city":"Colchester",
    "sg:classifiers":[
        {
            "category":"Social Services",
            "subcategory":"Job Training",
            "type":"Services"
        },
        {
            "category":"Military Area",
            "subcategory":"Coast Guard Base",
            "type":"Public Place"
        }
    ],
    "sg:phone":"+44 1206 302133",
    "sg:postcode":"CO7 0AX",
    "sg:province":"Essex",
    "sg:tags":[
        "engine",
        "engineering",
        "marine"
    ],
    "wof:name":"French Marine Motors Ltd",
    "wof:placetype":"venue"
},
  "geometry": {"coordinates":[1.02438,51.811169],"type":"Point"}
}