{
  "type": "Feature",
  "properties": {
    "addr:full":"Bungalow Farm, Station Road, Ashcott Bridgwater Somerset TA7 9QP",
    "addr:postcode":"ta7 9qp",
    "addr:street":"Station Road",
    "iso:country":"GB",
    "sg:address":"Bungalow Farm, Station Road, Ashcott",
    "sg:city":"Bridgwater",
    "sg:classifiers":[
        {
            "category":"Farming",
            "subcategory":"Livestock Farm",
            "type":"Manufacturing & Wholesale Goods"
        }
    ],
    "sg:phone":"+44 1458 210221",
    "sg:postcode":"TA7 9QP",
    "sg:province":"Somerset",
    "sg:tags":[
        "others"
    ],
    "wof:name":"N C Baker",
    "wof:placetype":"venue"
},
  "geometry": {"coordinates":[-2.8101129532,51.1289901733],"type":"Point"}
}