{
  "type": "Feature",
  "properties": {
    "iso:country":"GB",
    "sg:address":"68 Sheephousehill, Fauldhouse",
    "sg:city":"Bathgate",
    "sg:classifiers":[
        {
            "category":"Professional",
            "subcategory":"Computer Services",
            "type":"Services"
        }
    ],
    "sg:postcode":"EH47 9EE",
    "sg:province":"North Lanarkshire",
    "sg:tags":[
        "aided",
        "design"
    ],
    "wof:name":"G M Computer Graphics",
    "wof:placetype":"venue"
},
  "geometry": {"coordinates":[-3.705289,55.827961],"type":"Point"}
}