{
  "type": "Feature",
  "properties": {
    "iso:country":"GB",
    "sg:address":"The Homoeopathic Practice, The Street",
    "sg:city":"Sittingbourne",
    "sg:classifiers":[
        {
            "category":"Health Services",
            "subcategory":"Health Practitioner",
            "type":"Services"
        }
    ],
    "sg:postcode":"ME9 7TL",
    "sg:province":"Kent",
    "sg:tags":[
        "homoeopathic"
    ],
    "wof:name":"Virgina Yonge",
    "wof:placetype":"venue"
},
  "geometry": {"coordinates":[0.64041,51.347881],"type":"Point"}
}