{
  "type": "Feature",
  "properties": {
    "addr:full":"8 Mansel St Swansea Neath Port Talbot SA1 5SF",
    "addr:housenumber":"8",
    "addr:postcode":"sa1 5sf",
    "addr:street":"Mansel St",
    "iso:country":"GB",
    "sg:address":"8 Mansel St",
    "sg:city":"Swansea",
    "sg:classifiers":[
        {
            "category":"Travel",
            "subcategory":"Travel Agent",
            "type":"Entertainment"
        }
    ],
    "sg:phone":"+44 1792 476060",
    "sg:postcode":"SA1 5SF",
    "sg:province":"Neath Port Talbot",
    "wof:name":"Escape Tv",
    "wof:placetype":"venue"
},
  "geometry": {"coordinates":[-3.9481749535,51.6209640503],"type":"Point"}
}