{
  "type": "Feature",
  "properties": {
    "iso:country":"GB",
    "sg:address":"360 Icknield Way",
    "sg:city":"Luton",
    "sg:classifiers":[
        {
            "category":"Health Services",
            "subcategory":"Health Practitioner",
            "type":"Services"
        }
    ],
    "sg:phone":"+44 1582 595058",
    "sg:postcode":"LU3 2JU",
    "sg:province":"Bedfordshire",
    "sg:tags":[
        "physiotherapist"
    ],
    "wof:name":"Dave Kirby",
    "wof:placetype":"venue"
},
  "geometry": {"coordinates":[-0.441946,51.910091],"type":"Point"}
}