{
  "type": "Feature",
  "properties": {
    "addr:full":"8 Picardy Place Edinburgh City of Edinburgh EH1 3JT",
    "addr:housenumber":"8",
    "addr:postcode":"eh1 3jt",
    "addr:street":"Picardy Place Edinburgh",
    "iso:country":"GB",
    "sg:address":"8 Picardy Place",
    "sg:city":"Edinburgh",
    "sg:classifiers":[
        {
            "category":"Professional",
            "subcategory":"Employment Agencies",
            "type":"Services"
        }
    ],
    "sg:postcode":"EH1 3JT",
    "sg:province":"City of Edinburgh",
    "sg:tags":[
        "consultant",
        "recruitment"
    ],
    "wof:name":"ANDERSEN ELLIS FINANCIAL RECRUITMENT",
    "wof:placetype":"venue"
},
  "geometry": {"coordinates":[-3.1869859695,55.9570274353],"type":"Point"}
}