{
  "type": "Feature",
  "properties": {
    "addr:full":"West Surrey Estate, Spelthorne La Ashford Greater London TW15 1UJ",
    "addr:postcode":"tw15 1uj",
    "addr:street":"West Surrey;Spelthorne",
    "iso:country":"GB",
    "sg:address":"West Surrey Estate, Spelthorne La",
    "sg:city":"Ashford",
    "sg:classifiers":[
        {
            "category":"Shopping",
            "type":"Retail Goods"
        },
        {
            "category":"Retail",
            "subcategory":"Auto Repair",
            "type":"Services"
        }
    ],
    "sg:phone":"+44 1784 420361",
    "sg:postcode":"TW15 1UJ",
    "sg:province":"Greater London",
    "sg:tags":[
        "modification",
        "garage",
        "part",
        "accessory"
    ],
    "wof:name":"Peacock Motor Group (Ashford) Ltd (The)",
    "wof:placetype":"venue"
},
  "geometry": {"coordinates":[-0.4624440074,51.432975769],"type":"Point"}
}