{
  "type": "Feature",
  "properties": {
    "addr:full":"11 Kensal Avenue Bristol City of Bristol BS3 4QY",
    "addr:housenumber":"11",
    "addr:postcode":"bs3 4qy",
    "addr:street":"Kensal Avenue",
    "iso:country":"GB",
    "sg:address":"11 Kensal Avenue",
    "sg:city":"Bristol",
    "sg:classifiers":[
        {
            "category":"Building & Trades",
            "subcategory":"Construction",
            "type":"Services"
        }
    ],
    "sg:phone":"+44 7799 406067",
    "sg:postcode":"BS3 4QY",
    "sg:province":"City of Bristol",
    "sg:tags":[
        "builder"
    ],
    "wof:name":"Stonegrate 70",
    "wof:placetype":"venue"
},
  "geometry": {"coordinates":[-2.5896890163,51.4369277954],"type":"Point"}
}