{
  "type": "Feature",
  "properties": {
    "addr:full":"Unit 43 Gelli Indstl Est Tonypandy Rhondda, Cynon, Taff CF40 1DB",
    "addr:housenumber":"unit 43",
    "addr:postcode":"cf40 1db",
    "addr:street":"Gelli Indstl Est;Cynon Taff",
    "iso:country":"GB",
    "sg:address":"Unit 43 Gelli Indstl Est",
    "sg:city":"Tonypandy",
    "sg:classifiers":[
        {
            "category":"Building & Trades",
            "subcategory":"Construction",
            "type":"Services"
        }
    ],
    "sg:phone":"+44 1443 434305",
    "sg:postcode":"CF40 1DB",
    "sg:province":"Rhondda, Cynon, Taff",
    "sg:tags":[
        "welder"
    ],
    "wof:name":"J L M (Welding & Fabrications) Ltd",
    "wof:placetype":"venue"
},
  "geometry": {"coordinates":[-3.456164,51.620121],"type":"Point"}
}