{
  "type": "Feature",
  "properties": {
    "addr:full":"248 Meanwood Road Leeds West Yorkshire LS7 2HZ",
    "addr:housenumber":"248",
    "addr:postcode":"ls7 2hz",
    "addr:street":"Meanwood Road",
    "iso:country":"GB",
    "sg:address":"248 Meanwood Road",
    "sg:city":"Leeds",
    "sg:classifiers":[
        {
            "category":"Communications",
            "type":"Services"
        }
    ],
    "sg:phone":"+44 113 262 3342",
    "sg:postcode":"LS7 2HZ",
    "sg:province":"West Yorkshire",
    "sg:tags":[
        "audio-visual"
    ],
    "wof:name":"Stuart Joseph Associates",
    "wof:placetype":"venue"
},
  "geometry": {"coordinates":[-1.545218,53.815063],"type":"Point"}
}