{
  "type": "Feature",
  "properties": {
    "addr:full":"203-205 Maryhill Road Glasgow Glasgow City G20 7XJ",
    "addr:housenumber":"203-205",
    "addr:postcode":"g20 7xj",
    "addr:street":"Maryhill Road",
    "iso:country":"GB",
    "sg:address":"203-205 Maryhill Road",
    "sg:city":"Glasgow",
    "sg:classifiers":[
        {
            "category":"Home & Garden",
            "subcategory":"Kitchen Supply",
            "type":"Retail Goods"
        }
    ],
    "sg:phone":"+44 141 332 7730",
    "sg:postcode":"G20 7XJ",
    "sg:province":"Glasgow City",
    "sg:tags":[
        "equipment",
        "catering"
    ],
    "wof:name":"Barrack Cake Decorations",
    "wof:placetype":"venue"
},
  "geometry": {"coordinates":[-4.270782,55.874336],"type":"Point"}
}