{
  "type": "Feature",
  "properties": {
    "addr:full":"1st Floor Corner House, Ringwood Road, Bransgore Christchurch Dorset BH23 8AA",
    "addr:postcode":"bh23 8aa",
    "addr:street":"Ringwood Road",
    "iso:country":"GB",
    "sg:address":"1st Floor Corner House, Ringwood Road, Bransgore",
    "sg:city":"Christchurch",
    "sg:classifiers":[
        {
            "category":"Building & Trades",
            "subcategory":"Construction",
            "type":"Services"
        }
    ],
    "sg:phone":"+44 1425 674464",
    "sg:postcode":"BH23 8AA",
    "sg:province":"Dorset",
    "sg:tags":[
        "builder"
    ],
    "wof:name":"Pm Homes Ltd.",
    "wof:placetype":"venue"
},
  "geometry": {"coordinates":[-1.74042,50.782654],"type":"Point"}
}