{
  "type": "Feature",
  "properties": {
    "addr:full":"Watersmead, White Horse Way Westbury Wiltshire BA13 3AH",
    "addr:postcode":"ba13 3ah",
    "addr:street":"White Horse Way",
    "iso:country":"GB",
    "sg:address":"Watersmead, White Horse Way",
    "sg:city":"Westbury",
    "sg:classifiers":[
        {
            "category":"Health Services",
            "subcategory":"Nursing And Care Facility",
            "type":"Services"
        }
    ],
    "sg:phone":"+44 1373 826503",
    "sg:postcode":"BA13 3AH",
    "sg:province":"Wiltshire",
    "sg:tags":[
        "home"
    ],
    "wof:name":"Orders of St. John Trust Care Homes-wiltshire",
    "wof:placetype":"venue"
},
  "geometry": {"coordinates":[-2.1851289272,51.2574768066],"type":"Point"}
}