{
  "type": "Feature",
  "properties": {
    "addr:full":"7 Mansell St Stratford Upon Avon Warwickshire CV37 6NR",
    "addr:housenumber":"7",
    "addr:postcode":"cv37 6nr",
    "addr:street":"Mansell St",
    "iso:country":"GB",
    "sg:address":"7 Mansell St",
    "sg:city":"Stratford Upon Avon",
    "sg:classifiers":[
        {
            "category":"Real Estate",
            "subcategory":"Architect",
            "type":"Services"
        }
    ],
    "sg:phone":"+44 1789 295908",
    "sg:postcode":"CV37 6NR",
    "sg:province":"Warwickshire",
    "wof:name":"Robert Humber Associates",
    "wof:placetype":"venue"
},
  "geometry": {"coordinates":[-1.7103780508,52.1939468384],"type":"Point"}
}