{
  "type": "Feature",
  "properties": {
    "addr:full":"54 Chase Side London Greater London N14 5PA",
    "addr:housenumber":"54",
    "addr:postcode":"n14 5pa",
    "addr:street":"Chase",
    "iso:country":"GB",
    "sg:address":"54 Chase Side",
    "sg:city":"London",
    "sg:classifiers":[
        {
            "category":"Real Estate",
            "subcategory":"Real Estate Agent",
            "type":"Services"
        }
    ],
    "sg:phone":"+44 20 8882 2112",
    "sg:postcode":"N14 5PA",
    "sg:province":"Greater London",
    "wof:name":"A & E ESTATES LTD",
    "wof:placetype":"venue"
},
  "geometry": {"coordinates":[-0.130188,51.633232],"type":"Point"}
}