{
  "type": "Feature",
  "properties": {
    "iso:country":"GB",
    "sg:address":"8-10 Headingley Lane",
    "sg:city":"Leeds",
    "sg:classifiers":[
        {
            "category":"Home & Garden",
            "subcategory":"Hardware",
            "type":"Retail Goods"
        },
        {
            "category":"Home & Garden",
            "subcategory":"Furniture",
            "type":"Retail Goods"
        }
    ],
    "sg:phone":"+44 113 278 2653",
    "sg:postcode":"LS6 2AS",
    "sg:province":"West Yorkshire",
    "sg:tags":[
        "retailer",
        "lighting"
    ],
    "wof:name":"Christopher Wray Lighting",
    "wof:placetype":"venue"
},
  "geometry": {"coordinates":[-1.5617630482,53.8149528503],"type":"Point"}
}