{
  "type": "Feature",
  "properties": {
    "iso:country":"GB",
    "sg:address":"1 Redclose Avenue",
    "sg:city":"Morden",
    "sg:classifiers":[
        {
            "category":"Building & Trades",
            "subcategory":"Plumbing",
            "type":"Services"
        }
    ],
    "sg:phone":"+44 20 8648 5320",
    "sg:postcode":"SM4 5RD",
    "sg:province":"Surrey",
    "sg:tags":[
        "central",
        "heating"
    ],
    "wof:name":"Underwood Plumbing & Heating",
    "wof:placetype":"venue"
},
  "geometry": {"coordinates":[-0.200945,51.39439],"type":"Point"}
}