{
  "type": "Feature",
  "properties": {
    "iso:country":"GB",
    "sg:address":"9 The Square, Torphin",
    "sg:city":"Banchory",
    "sg:classifiers":[
        {
            "category":"Food & Beverages",
            "subcategory":"Meat & Fish",
            "type":"Retail Goods"
        }
    ],
    "sg:postcode":"AB31 4GP",
    "sg:province":"Aberdeen City",
    "sg:tags":[
        "butcher"
    ],
    "wof:name":"George & Dorothy Sinclair",
    "wof:placetype":"venue"
},
  "geometry": {"coordinates":[-2.622513,57.105793],"type":"Point"}
}