{
  "type": "Feature",
  "properties": {
    "addr:full":"24 Railway Street Chatham Kent ME4 4JT",
    "addr:housenumber":"24",
    "addr:postcode":"me4 4jt",
    "addr:street":"Railway Street",
    "iso:country":"GB",
    "sg:address":"24 Railway Street",
    "sg:city":"Chatham",
    "sg:classifiers":[
        {
            "category":"Shopping",
            "subcategory":"Thrift Store",
            "type":"Retail Goods"
        }
    ],
    "sg:phone":"+44 1634 826709",
    "sg:postcode":"ME4 4JT",
    "sg:province":"Kent",
    "sg:tags":[
        "shop",
        "charity"
    ],
    "wof:name":"Shelter Trading Ltd.",
    "wof:placetype":"venue"
},
  "geometry": {"coordinates":[0.522203,51.381905],"type":"Point"}
}