{
  "type": "Feature",
  "properties": {
    "iso:country":"GB",
    "sg:address":"348 Burnley Road",
    "sg:city":"Colne",
    "sg:classifiers":[
        {
            "category":"Bars & Pubs",
            "type":"Food & Drink"
        },
        {
            "category":"Community Center",
            "subcategory":"Social",
            "type":"Public Place"
        }
    ],
    "sg:phone":"+44 1282 861862",
    "sg:postcode":"BB8 8LF",
    "sg:province":"Lancashire",
    "sg:tags":[
        "pubs",
        "house",
        "inn",
        "activity"
    ],
    "wof:name":"Golden Ball",
    "wof:placetype":"venue"
},
  "geometry": {"coordinates":[-2.183094,53.852638],"type":"Point"}
}