{
  "type": "Feature",
  "properties": {
    "addr:full":"39 Long Rd Bristol City of Bristol BS16 9HW",
    "addr:housenumber":"39",
    "addr:postcode":"bs16 9hw",
    "addr:street":"Long Rd",
    "iso:country":"GB",
    "sg:address":"39 Long Rd",
    "sg:city":"Bristol",
    "sg:classifiers":[
        {
            "category":"Personal",
            "type":"Services"
        }
    ],
    "sg:phone":"+44 117 949 9958",
    "sg:postcode":"BS16 9HW",
    "sg:province":"City of Bristol",
    "sg:tags":[
        "wedding"
    ],
    "wof:name":"T F C Limousine Hire",
    "wof:placetype":"venue"
},
  "geometry": {"coordinates":[-2.5914289951,51.453666687],"type":"Point"}
}