{
  "type": "Feature",
  "properties": {
    "iso:country":"GB",
    "sg:address":"24 Ewhurst House, Jamaica Street",
    "sg:city":"London",
    "sg:classifiers":[
        {
            "category":"Professional",
            "subcategory":"Detective & Security Services",
            "type":"Services"
        }
    ],
    "sg:postcode":"E1 3HS",
    "sg:province":"Greater London",
    "sg:tags":[
        "car"
    ],
    "wof:name":"Major",
    "wof:placetype":"venue"
},
  "geometry": {"coordinates":[-0.0500399992,51.5171890259],"type":"Point"}
}