{
  "type": "Feature",
  "properties": {
    "iso:country":"GB",
    "sg:address":"P O Box 184",
    "sg:city":"Ashford",
    "sg:classifiers":[
        {
            "category":"Professional",
            "subcategory":"Business Services",
            "type":"Services"
        }
    ],
    "sg:phone":"+44 1233 612022",
    "sg:postcode":"TN24 0ZS",
    "sg:province":"Kent",
    "sg:tags":[
        "distribution"
    ],
    "wof:name":"One Stop Music Distribution Ltd",
    "wof:placetype":"venue"
},
  "geometry": {"coordinates":[0.8985300064,51.1366500854],"type":"Point"}
}