{
  "type": "Feature",
  "properties": {
    "iso:country":"GB",
    "sg:address":"Unit 1c Deacon Estate, Forstal Road",
    "sg:city":"Aylesford",
    "sg:classifiers":[
        {
            "category":"Manufacturing",
            "subcategory":"Rubber & Plastics",
            "type":"Manufacturing & Wholesale Goods"
        }
    ],
    "sg:phone":"+44 1622 718449",
    "sg:postcode":"ME20 7SP",
    "sg:province":"Kent",
    "sg:tags":[
        "product"
    ],
    "wof:name":"Haddonway Ltd",
    "wof:placetype":"venue"
},
  "geometry": {"coordinates":[0.48037,51.303631],"type":"Point"}
}