{
  "type": "Feature",
  "properties": {
    "addr:full":"69 Alcombe Road Minehead Somerset TA24 6BD",
    "addr:housenumber":"69",
    "addr:postcode":"ta24 6bd",
    "addr:street":"Alcombe Road",
    "iso:country":"GB",
    "sg:address":"69 Alcombe Road",
    "sg:city":"Minehead",
    "sg:classifiers":[
        {
            "category":"Government",
            "subcategory":"Post Office",
            "type":"Public Place"
        }
    ],
    "sg:phone":"+44 1643 702049",
    "sg:postcode":"TA24 6BD",
    "sg:province":"Somerset",
    "wof:name":"Alcombe Post Office",
    "wof:placetype":"venue"
},
  "geometry": {"coordinates":[-3.4671440125,51.1971435547],"type":"Point"}
}