{
  "type": "Feature",
  "properties": {
    "addr:full":"11 Stryd Womanby Cardiff Cardiff CF10 1BR",
    "addr:housenumber":"11",
    "addr:postcode":"cf10 1br",
    "addr:street":"Stryd Womanby",
    "iso:country":"GB",
    "sg:address":"11 Stryd Womanby",
    "sg:city":"Cardiff",
    "sg:classifiers":[
        {
            "category":"Bars & Pubs",
            "subcategory":"Nightclub",
            "type":"Food & Drink"
        },
        {
            "category":"Organizations",
            "subcategory":"Membership Organization",
            "type":"Services"
        }
    ],
    "sg:phone":"+44 29 2023 2199",
    "sg:postcode":"CF10 1BR",
    "sg:province":"Cardiff",
    "sg:tags":[
        "club",
        "activity"
    ],
    "wof:name":"CLWB Ifor Bach",
    "wof:placetype":"venue"
},
  "geometry": {"coordinates":[-3.181552,51.480434],"type":"Point"}
}