{
  "type": "Feature",
  "properties": {
    "addr:full":"Montagu Square Mexborough South Yorkshire S64 9AJ",
    "addr:postcode":"s64 9aj",
    "addr:street":"Montagu Square Mexborough South",
    "iso:country":"GB",
    "sg:address":"Montagu Square",
    "sg:city":"Mexborough",
    "sg:classifiers":[
        {
            "category":"Shopping",
            "subcategory":"Clothing, Apparel, & Fashions",
            "type":"Retail Goods"
        }
    ],
    "sg:phone":"+44 1709 582359",
    "sg:postcode":"S64 9AJ",
    "sg:province":"South Yorkshire",
    "sg:tags":[
        "shop"
    ],
    "wof:name":"Madame Florence Ltd.",
    "wof:placetype":"venue"
},
  "geometry": {"coordinates":[-1.299808979,53.4953536987],"type":"Point"}
}