{
  "type": "Feature",
  "properties": {
    "addr:full":"199 Regent Street London Greater London W1R 7WA",
    "addr:housenumber":"199",
    "addr:postcode":"w1r",
    "addr:street":"Regent Street;7Wa",
    "iso:country":"GB",
    "sg:address":"199 Regent Street",
    "sg:city":"London",
    "sg:classifiers":[
        {
            "category":"Shopping",
            "subcategory":"Stationery & Office Supplies",
            "type":"Retail Goods"
        }
    ],
    "sg:phone":"+44 20 7734 4088",
    "sg:postcode":"W1R 7WA",
    "sg:province":"Greater London",
    "wof:name":"The Pen Shop",
    "wof:placetype":"venue"
},
  "geometry": {"coordinates":[-0.140702,51.512951],"type":"Point"}
}