{
  "type": "Feature",
  "properties": {
    "iso:country":"GB",
    "sg:address":"Green Lane Cotts, Beehive Lane",
    "sg:city":"Newtown",
    "sg:classifiers":[
        {
            "category":"Professional",
            "subcategory":"Engineering",
            "type":"Services"
        }
    ],
    "sg:phone":"+44 1686 628931",
    "sg:postcode":"SY16 2NA",
    "sg:province":"Powys",
    "sg:tags":[
        "civil",
        "engineer"
    ],
    "wof:name":"Ann H P Thomas",
    "wof:placetype":"venue"
},
  "geometry": {"coordinates":[-3.314603,52.519958],"type":"Point"}
}