{
  "type": "Feature",
  "properties": {
    "addr:full":"76 Heathfield Park, Upton Rock Widnes Cheshire WA8 9WX",
    "addr:housenumber":"76",
    "addr:postcode":"wa8 9wx",
    "addr:street":"Heathfield Park",
    "iso:country":"GB",
    "sg:address":"76 Heathfield Park, Upton Rock",
    "sg:city":"Widnes",
    "sg:classifiers":[
        {
            "category":"Retail",
            "subcategory":"Driving School",
            "type":"Services"
        }
    ],
    "sg:postcode":"WA8 9WX",
    "sg:province":"Cheshire",
    "wof:name":"Keith Williams",
    "wof:placetype":"venue"
},
  "geometry": {"coordinates":[-2.7332439423,53.3740310669],"type":"Point"}
}