{
  "type": "Feature",
  "properties": {
    "addr:full":"3 Alwins Court, Warmley Bristol Gloucestershire BS30 7AP",
    "addr:housenumber":"3",
    "addr:postcode":"bs30 7ap",
    "addr:street":"Alwins Court",
    "iso:country":"GB",
    "sg:address":"3 Alwins Court, Warmley",
    "sg:city":"Bristol",
    "sg:classifiers":[
        {
            "category":"Organizations",
            "subcategory":"Non-profit Organization",
            "type":"Services"
        }
    ],
    "sg:phone":"+44 117 960 1962",
    "sg:postcode":"BS30 7AP",
    "sg:province":"Gloucestershire",
    "sg:tags":[
        "organisation",
        "animal",
        "welfare"
    ],
    "wof:name":"Bristol Feline Welfare",
    "wof:placetype":"venue"
},
  "geometry": {"coordinates":[-2.4918339252,51.4449539185],"type":"Point"}
}