{
  "type": "Feature",
  "properties": {
    "addr:full":"Units 7 & 8, The Boundry, Wheatley Road Oxford Oxfordshire OX44 9EJ",
    "addr:housenumber":"units 7 & 8",
    "addr:postcode":"ox44 9ej",
    "addr:street":"The Boundry Wheatley Road",
    "iso:country":"GB",
    "sg:address":"Units 7 & 8, The Boundry, Wheatley Road",
    "sg:city":"Oxford",
    "sg:classifiers":[
        {
            "category":"Shopping",
            "subcategory":"Computers & Home Electronics",
            "type":"Retail Goods"
        }
    ],
    "sg:phone":"+44 1865 361000",
    "sg:postcode":"OX44 9EJ",
    "sg:province":"Oxfordshire",
    "sg:tags":[
        "tape",
        "video"
    ],
    "wof:name":"The Vault Search Service",
    "wof:placetype":"venue"
},
  "geometry": {"coordinates":[-1.1529999971,51.726940155],"type":"Point"}
}