{
  "type": "Feature",
  "properties": {
    "iso:country":"GB",
    "sg:address":"Central Music Centre, Redgate",
    "sg:city":"Liverpool",
    "sg:classifiers":[
        {
            "category":"Education",
            "subcategory":"Music School",
            "type":"Public Place"
        }
    ],
    "sg:postcode":"L37 4EW",
    "sg:province":"Lancashire",
    "sg:tags":[
        "teacher"
    ],
    "wof:name":"Music Support Service",
    "wof:placetype":"venue"
},
  "geometry": {"coordinates":[-3.05019,53.552761],"type":"Point"}
}