{
  "type": "Feature",
  "properties": {
    "addr:full":"Grindlay Street Edinburgh City of Edinburgh EH3 9AR",
    "addr:postcode":"eh3 9ar",
    "addr:street":"Grindlay Street",
    "iso:country":"GB",
    "sg:address":"Grindlay Street",
    "sg:city":"Edinburgh",
    "sg:classifiers":[
        {
            "category":"Social Services",
            "type":"Services"
        }
    ],
    "sg:phone":"+44 131 229 7941",
    "sg:postcode":"EH3 9AR",
    "sg:province":"City of Edinburgh",
    "wof:name":"Grindlay Court Adult Training & Resource Centre",
    "wof:placetype":"venue"
},
  "geometry": {"coordinates":[-3.204626,55.946827],"type":"Point"}
}