{
  "type": "Feature",
  "properties": {
    "addr:full":"517-519 Barking Road, Plaistow London Greater London E13 8PT",
    "addr:postcode":"517-519;e13 8pt",
    "addr:street":"Barking Road",
    "iso:country":"GB",
    "sg:address":"517-519 Barking Road, Plaistow",
    "sg:city":"London",
    "sg:classifiers":[
        {
            "category":"Professional",
            "subcategory":"Lawyer & Legal Services",
            "type":"Services"
        }
    ],
    "sg:phone":"+44 20 8514 9000",
    "sg:postcode":"E13 8PT",
    "sg:province":"Greater London",
    "sg:tags":[
        "solicitor"
    ],
    "wof:name":"Edwards Duthie",
    "wof:placetype":"venue"
},
  "geometry": {"coordinates":[0.0290660001,51.5259590149],"type":"Point"}
}