{
  "type": "Feature",
  "properties": {
    "iso:country":"GB",
    "sg:address":"Ashby Cres",
    "sg:city":"Leeds",
    "sg:classifiers":[
        {
            "category":"Retail",
            "subcategory":"Funeral Services",
            "type":"Services"
        }
    ],
    "sg:phone":"+44 113 236 0673",
    "sg:postcode":"LS13 3AE",
    "sg:province":"West Yorkshire",
    "wof:name":"The Lawns Funeral Home",
    "wof:placetype":"venue"
},
  "geometry": {"coordinates":[-1.627169,53.806293],"type":"Point"}
}