{
  "type": "Feature",
  "properties": {
    "iso:country":"GB",
    "sg:address":"25 Shore Street",
    "sg:city":"Macduff",
    "sg:classifiers":[
        {
            "category":"Banks & Credit Unions",
            "subcategory":"Bank",
            "type":"Services"
        }
    ],
    "sg:phone":"+44 1261 832324",
    "sg:postcode":"AB44 1TX",
    "sg:province":"Aberdeenshire",
    "sg:tags":[
        "financial",
        "institution"
    ],
    "wof:name":"Bank of Scotland plc",
    "wof:placetype":"venue"
},
  "geometry": {"coordinates":[-2.497857,57.670082],"type":"Point"}
}