{
  "type": "Feature",
  "properties": {
    "addr:full":"4-6 Falsgrave Road Scarborough North Yorkshire YO12 5AT",
    "addr:housenumber":"4-6",
    "addr:postcode":"yo12 5at",
    "addr:street":"Falsgrave Road",
    "iso:country":"GB",
    "sg:address":"4-6 Falsgrave Road",
    "sg:city":"Scarborough",
    "sg:classifiers":[
        {
            "category":"Social Services",
            "type":"Services"
        },
        {
            "category":"Manufacturing",
            "subcategory":"Tobacco Products",
            "type":"Manufacturing & Wholesale Goods"
        }
    ],
    "sg:phone":"+44 1723 355122",
    "sg:postcode":"YO12 5AT",
    "sg:province":"North Yorkshire",
    "sg:tags":[
        "equipment",
        "suppliers",
        "disability",
        "manufacturers"
    ],
    "wof:name":"Active Mobility Centre Ltd.",
    "wof:placetype":"venue"
},
  "geometry": {"coordinates":[-0.4105589986,54.2778816223],"type":"Point"}
}