{
  "type": "Feature",
  "properties": {
    "iso:country":"GB",
    "sg:address":"Mulberry Ho, Kells La",
    "sg:city":"Gateshead",
    "sg:classifiers":[
        {
            "category":"Manufacturing",
            "subcategory":"Petroleum Products",
            "type":"Manufacturing & Wholesale Goods"
        }
    ],
    "sg:postcode":"NE9 5SJ",
    "sg:province":"Tyne and Wear",
    "sg:tags":[
        "double",
        "glazing"
    ],
    "wof:name":"Century Home Improvements",
    "wof:placetype":"venue"
},
  "geometry": {"coordinates":[-1.5916800499,54.9403495789],"type":"Point"}
}