{
  "type": "Feature",
  "properties": {
    "iso:country":"GB",
    "sg:address":"Old Organ Hall, Worcester Road",
    "sg:city":"Malvern",
    "sg:classifiers":[
        {
            "category":"Professional",
            "subcategory":"Printing & Photocopies",
            "type":"Services"
        }
    ],
    "sg:phone":"+44 1684 576061",
    "sg:postcode":"WR14 1SS",
    "sg:province":"Herefordshire",
    "sg:tags":[
        "printer"
    ],
    "wof:name":"Brownes the Printers",
    "wof:placetype":"venue"
},
  "geometry": {"coordinates":[-2.31586,52.126949],"type":"Point"}
}