{
  "type": "Feature",
  "properties": {
    "iso:country":"GB",
    "sg:address":"Danny Garage, Mearclough Rd",
    "sg:city":"Sowerby Bridge",
    "sg:classifiers":[
        {
            "category":"Utilities",
            "subcategory":"Natural Gas",
            "type":"Services"
        }
    ],
    "sg:phone":"+44 1422 832129",
    "sg:postcode":"HX6 3LD",
    "sg:province":"West Yorkshire",
    "sg:tags":[
        "injector",
        "diesel"
    ],
    "wof:name":"Sowerby Bridge Diesel Centre",
    "wof:placetype":"venue"
},
  "geometry": {"coordinates":[-1.9139339924,53.7065391541],"type":"Point"}
}