{
  "type": "Feature",
  "properties": {
    "addr:full":"59 Bayham Place London Greater London NW1 0ET",
    "addr:housenumber":"59",
    "addr:postcode":"nw1 0et",
    "addr:street":"Bayham Place",
    "iso:country":"GB",
    "sg:address":"59 Bayham Place",
    "sg:city":"London",
    "sg:classifiers":[
        {
            "category":"Shopping",
            "subcategory":"Clothing, Apparel, & Fashions",
            "type":"Retail Goods"
        }
    ],
    "sg:phone":"+44 20 7383 3949",
    "sg:postcode":"NW1 0ET",
    "sg:province":"Greater London",
    "sg:tags":[
        "clothing",
        "fabric"
    ],
    "wof:name":"Scruffs International Ltd.",
    "wof:placetype":"venue"
},
  "geometry": {"coordinates":[-0.1371860057,51.5350914001],"type":"Point"}
}