{
  "type": "Feature",
  "properties": {
    "iso:country":"GB",
    "sg:address":"54-62 Grey Eagle St",
    "sg:city":"Whitechapel",
    "sg:classifiers":[
        {
            "category":"Freight",
            "type":"Transportation"
        }
    ],
    "sg:phone":"+44 20 7375 2541",
    "sg:postcode":"E1 6SL",
    "sg:province":"Greater London",
    "sg:tags":[
        "forwarders"
    ],
    "wof:name":"Major Port Cargo Express",
    "wof:placetype":"venue"
},
  "geometry": {"coordinates":[-0.073089,51.522297],"type":"Point"}
}