{
  "type": "Feature",
  "properties": {
    "iso:country":"GB",
    "sg:address":"Wharf Road",
    "sg:city":"Rugeley",
    "sg:classifiers":[
        {
            "category":"Military Area",
            "subcategory":"Air Force Base",
            "type":"Public Place"
        }
    ],
    "sg:phone":"+44 1889 586061",
    "sg:postcode":"WS15 1BL",
    "sg:province":"Staffordshire",
    "sg:tags":[
        "taxi",
        "hire",
        "private"
    ],
    "wof:name":"60-61 Cars",
    "wof:placetype":"venue"
},
  "geometry": {"coordinates":[-1.93462,52.755192],"type":"Point"}
}