{
  "type": "Feature",
  "properties": {
    "addr:full":"5 Yorkshire Street Bacup Lancashire OL13 9AE",
    "addr:housenumber":"5",
    "addr:postcode":"ol13 9ae",
    "addr:street":"Yorkshire Street",
    "iso:country":"GB",
    "sg:address":"5 Yorkshire Street",
    "sg:city":"Bacup",
    "sg:classifiers":[
        {
            "category":"Fast Food",
            "type":"Food & Drink"
        }
    ],
    "sg:phone":"+44 1706 877077",
    "sg:postcode":"OL13 9AE",
    "sg:province":"Lancashire",
    "sg:tags":[
        "away",
        "meal",
        "outlet",
        "take"
    ],
    "wof:name":"Pizza & Kebab House",
    "wof:placetype":"venue"
},
  "geometry": {"coordinates":[-2.2005240917,53.7035369873],"type":"Point"}
}