{
  "type": "Feature",
  "properties": {
    "iso:country":"GB",
    "sg:address":"Unit 1 Back Grantley Street",
    "sg:city":"Wakefield",
    "sg:classifiers":[
        {
            "category":"Parking",
            "type":"Transportation"
        }
    ],
    "sg:phone":"+44 1924 201565",
    "sg:postcode":"WF1 4LG",
    "sg:province":"West Yorkshire",
    "sg:tags":[
        "car",
        "valet"
    ],
    "wof:name":"Elite Valeting",
    "wof:placetype":"venue"
},
  "geometry": {"coordinates":[-1.490499,53.68428],"type":"Point"}
}