{
  "type": "Feature",
  "properties": {
    "addr:full":"White Houses, London Road Retford Nottinghamshire DN22 7JS",
    "addr:postcode":"dn22 7js",
    "addr:street":"White;London Road",
    "iso:country":"GB",
    "sg:address":"White Houses, London Road",
    "sg:city":"Retford",
    "sg:classifiers":[
        {
            "category":"Community Center",
            "type":"Public Place"
        }
    ],
    "sg:postcode":"DN22 7JS",
    "sg:province":"Nottinghamshire",
    "sg:tags":[
        "nursery",
        "centre"
    ],
    "wof:name":"T J Barker & Sons",
    "wof:placetype":"venue"
},
  "geometry": {"coordinates":[-0.9344660044,53.3073654175],"type":"Point"}
}