{
  "type": "Feature",
  "properties": {
    "addr:full":"Priors Hall, Colne Road Colchester Essex CO6 1SX",
    "addr:postcode":"co6 1sx",
    "addr:street":"Colne Road Colchester",
    "iso:country":"GB",
    "sg:address":"Priors Hall, Colne Road",
    "sg:city":"Colchester",
    "sg:classifiers":[
        {
            "category":"Government",
            "subcategory":"Post Office",
            "type":"Public Place"
        }
    ],
    "sg:phone":"+44 1376 565216",
    "sg:postcode":"CO6 1SX",
    "sg:province":"Essex",
    "sg:tags":[
        "print",
        "typesetter"
    ],
    "wof:name":"Facsimile Graphics Ltd.",
    "wof:placetype":"venue"
},
  "geometry": {"coordinates":[0.6926199794,51.8773384094],"type":"Point"}
}