{
  "type": "Feature",
  "properties": {
    "addr:full":"Unit 2, 175 Rolfe Street Smethwick West Midlands B66 2AS",
    "addr:housenumber":"unit 2 175",
    "addr:postcode":"b66 2as",
    "addr:street":"Rolfe Street",
    "iso:country":"GB",
    "sg:address":"Unit 2, 175 Rolfe Street",
    "sg:city":"Smethwick",
    "sg:classifiers":[
        {
            "category":"Shopping",
            "subcategory":"Clothing, Apparel, & Fashions",
            "type":"Retail Goods"
        }
    ],
    "sg:postcode":"B66 2AS",
    "sg:province":"West Midlands",
    "sg:tags":[
        "clothing",
        "fabric"
    ],
    "wof:name":"Outer Limits",
    "wof:placetype":"venue"
},
  "geometry": {"coordinates":[-1.966484,52.496922],"type":"Point"}
}