{
  "type": "Feature",
  "properties": {
    "iso:country":"GB",
    "sg:address":"Old Cockburn Foundry Estate, Gowan Avenue",
    "sg:city":"Falkirk",
    "sg:classifiers":[
        {
            "category":"Government",
            "subcategory":"Post Office",
            "type":"Public Place"
        }
    ],
    "sg:postcode":"FK2 7HL",
    "sg:province":"Falkirk",
    "sg:tags":[
        "messenger",
        "courier"
    ],
    "wof:name":"Fast Forward Couriers",
    "wof:placetype":"venue"
},
  "geometry": {"coordinates":[-3.78444,56.007179],"type":"Point"}
}