{
  "type": "Feature",
  "properties": {
    "iso:country":"GB",
    "sg:address":"425 Cheetham Hill Road",
    "sg:city":"Manchester",
    "sg:classifiers":[
        {
            "category":"Community Center",
            "type":"Public Place"
        },
        {
            "category":"Organizations",
            "subcategory":"Non-profit Organization",
            "type":"Services"
        }
    ],
    "sg:phone":"+44 161 205 6662",
    "sg:postcode":"M8 0PF",
    "sg:province":"Greater Manchester",
    "sg:tags":[
        "charitable",
        "organisation",
        "charity",
        "voluntary",
        "centre"
    ],
    "wof:name":"Cheetham Al-Hilal Community Project",
    "wof:placetype":"venue"
},
  "geometry": {"coordinates":[-2.237108,53.505424],"type":"Point"}
}