{
  "type": "Feature",
  "properties": {
    "iso:country":"GB",
    "sg:address":"Hurricane Way, Woodley",
    "sg:city":"Reading",
    "sg:classifiers":[
        {
            "category":"Shopping",
            "subcategory":"Pharmacy",
            "type":"Retail Goods"
        }
    ],
    "sg:phone":"+44 118 944 1036",
    "sg:postcode":"RG5 4UX",
    "sg:province":"Berkshire",
    "sg:tags":[
        "pharmacist",
        "chemist"
    ],
    "wof:name":"Rankin Chemist",
    "wof:placetype":"venue"
},
  "geometry": {"coordinates":[-0.882464,51.459606],"type":"Point"}
}