{
  "type": "Feature",
  "properties": {
    "addr:full":"50 Mansfield Road Ilford Essex IG1 3BD",
    "addr:housenumber":"50",
    "addr:postcode":"ig1 3bd",
    "addr:street":"Mansfield Road",
    "iso:country":"GB",
    "sg:address":"50 Mansfield Road",
    "sg:city":"Ilford",
    "sg:classifiers":[
        {
            "category":"Travel",
            "subcategory":"Hotels & Motels",
            "type":"Entertainment"
        }
    ],
    "sg:phone":"+44 20 8554 7351",
    "sg:postcode":"IG1 3BD",
    "sg:province":"Essex",
    "sg:tags":[
        "house",
        "guest"
    ],
    "wof:name":"Alfirdo's Guest House",
    "wof:placetype":"venue"
},
  "geometry": {"coordinates":[0.0669229999,51.5624008179],"type":"Point"}
}