{
  "type": "Feature",
  "properties": {
    "addr:full":"Silver Birch, St Asaph Avenue Rhyl Conwy LL18 5HA",
    "addr:postcode":"ll18 5ha",
    "addr:street":"Silver Birch St Asaph Avenue",
    "iso:country":"GB",
    "sg:address":"Silver Birch, St Asaph Avenue",
    "sg:city":"Rhyl",
    "sg:classifiers":[
        {
            "category":"Home & Garden",
            "subcategory":"Garden Supply",
            "type":"Retail Goods"
        }
    ],
    "sg:phone":"+44 1745 351366",
    "sg:postcode":"LL18 5HA",
    "sg:province":"Conwy",
    "sg:tags":[
        "nursery",
        "centre"
    ],
    "wof:name":"D & B J Overthrow",
    "wof:placetype":"venue"
},
  "geometry": {"coordinates":[-3.5197780132,53.3105583191],"type":"Point"}
}