{
  "type": "Feature",
  "properties": {
    "iso:country":"GB",
    "sg:address":"113 Frodingham Road",
    "sg:city":"Scunthorpe",
    "sg:classifiers":[
        {
            "category":"Real Estate",
            "subcategory":"Real Estate Services",
            "type":"Services"
        },
        {
            "category":"Building & Trades",
            "subcategory":"Equipment Rental",
            "type":"Services"
        }
    ],
    "sg:phone":"+44 1724 845727",
    "sg:postcode":"DN15 7JT",
    "sg:province":"Lincolnshire",
    "sg:tags":[
        "hire",
        "leasing",
        "plant",
        "machinery"
    ],
    "wof:name":"Crosby Plant & Tool Hire",
    "wof:placetype":"venue"
},
  "geometry": {"coordinates":[-0.654615,53.59219],"type":"Point"}
}