{
  "type": "Feature",
  "properties": {
    "iso:country":"GB",
    "sg:address":"Gurnos Road, Ystradgynlais",
    "sg:city":"Swansea",
    "sg:classifiers":[
        {
            "category":"Food & Beverages",
            "subcategory":"Supermarket",
            "type":"Retail Goods"
        }
    ],
    "sg:phone":"+44 1639 844712",
    "sg:postcode":"SA9 2JP",
    "sg:province":"Carmarthenshire",
    "wof:name":"Co-Operative Pioneer",
    "wof:placetype":"venue"
},
  "geometry": {"coordinates":[-3.776819,51.768631],"type":"Point"}
}