{
  "type": "Feature",
  "properties": {
    "addr:full":"20 Culver Street Newent Gloucestershire GL18 1DA",
    "addr:housenumber":"20",
    "addr:postcode":"gl18 1da",
    "addr:street":"Culver Street",
    "iso:country":"GB",
    "sg:address":"20 Culver Street",
    "sg:city":"Newent",
    "sg:classifiers":[
        {
            "category":"Professional",
            "subcategory":"Printing & Photocopies",
            "type":"Services"
        }
    ],
    "sg:phone":"+44 1531 820816",
    "sg:postcode":"GL18 1DA",
    "sg:province":"Gloucestershire",
    "sg:tags":[
        "printer"
    ],
    "wof:name":"Perpetua Press",
    "wof:placetype":"venue"
},
  "geometry": {"coordinates":[-2.4059309959,51.9298934937],"type":"Point"}
}