{
  "type": "Feature",
  "properties": {
    "iso:country":"GB",
    "sg:address":"41 Whitehill Rd",
    "sg:city":"Coalville",
    "sg:classifiers":[
        {
            "category":"Building & Trades",
            "subcategory":"Construction",
            "type":"Services"
        }
    ],
    "sg:postcode":"LE67 1EN",
    "sg:province":"Leicestershire",
    "sg:tags":[
        "builder"
    ],
    "wof:name":"Cartwright,Lee",
    "wof:placetype":"venue"
},
  "geometry": {"coordinates":[-1.363784,52.693935],"type":"Point"}
}