{
  "type": "Feature",
  "properties": {
    "iso:country":"GB",
    "sg:address":"147 Marlowes",
    "sg:city":"Hemel Hempstead",
    "sg:classifiers":[
        {
            "category":"Food & Beverages",
            "subcategory":"Supermarket",
            "type":"Retail Goods"
        }
    ],
    "sg:phone":"+44 1442 236100",
    "sg:postcode":"HP1 1BB",
    "sg:province":"Hertfordshire",
    "wof:name":"J Sainsbury PLC",
    "wof:placetype":"venue"
},
  "geometry": {"coordinates":[-0.472257,51.751221],"type":"Point"}
}