{
  "type": "Feature",
  "properties": {
    "iso:country":"GB",
    "sg:address":"11a School Lane, Quedgeley",
    "sg:city":"Gloucester",
    "sg:classifiers":[
        {
            "category":"Real Estate",
            "subcategory":"Real Estate Agent",
            "type":"Services"
        }
    ],
    "sg:phone":"+44 1452 721396",
    "sg:postcode":"GL2 4PJ",
    "sg:province":"Gloucestershire",
    "wof:name":"Parkers",
    "wof:placetype":"venue"
},
  "geometry": {"coordinates":[-2.278627,51.825611],"type":"Point"}
}