{
  "type": "Feature",
  "properties": {
    "addr:full":"London Road Garage Halesworth Suffolk IP19 8LR",
    "addr:postcode":"ip19 8lr",
    "addr:street":"London",
    "iso:country":"GB",
    "sg:address":"London Road Garage",
    "sg:city":"Halesworth",
    "sg:classifiers":[
        {
            "category":"Autos & Motor Vehicles",
            "subcategory":"Automobile Sales",
            "type":"Retail Goods"
        }
    ],
    "sg:phone":"+44 1986 872138",
    "sg:postcode":"IP19 8LR",
    "sg:province":"Suffolk",
    "sg:tags":[
        "car"
    ],
    "wof:name":"Kerridge (Halesworth) Ltd.",
    "wof:placetype":"venue"
},
  "geometry": {"coordinates":[1.503773,52.344131],"type":"Point"}
}