{
  "type": "Feature",
  "properties": {
    "addr:full":"229-231 St Helens Road Bolton Lancashire BL3 3PY",
    "addr:housenumber":"229-231",
    "addr:postcode":"bl3 3py",
    "addr:street":"St Helens Road",
    "iso:country":"GB",
    "sg:address":"229-231 St Helens Road",
    "sg:city":"Bolton",
    "sg:classifiers":[
        {
            "category":"Shopping",
            "subcategory":"Bicycles & Sporting Goods",
            "type":"Retail Goods"
        }
    ],
    "sg:phone":"+44 1204 653509",
    "sg:postcode":"BL3 3PY",
    "sg:province":"Lancashire",
    "sg:tags":[
        "cycle",
        "accessory"
    ],
    "wof:name":"Geoff Smith Cycles",
    "wof:placetype":"venue"
},
  "geometry": {"coordinates":[-2.453105,53.562065],"type":"Point"}
}