{
  "type": "Feature",
  "properties": {
    "addr:full":"Pinewood, Chieneham Business Park, Crockford Lane Basingstoke Hampshire RG24 8AL",
    "addr:postcode":"rg24 8al",
    "addr:street":"Business Park Crockford Lane",
    "iso:country":"GB",
    "sg:address":"Pinewood, Chieneham Business Park, Crockford Lane",
    "sg:city":"Basingstoke",
    "sg:classifiers":[
        {
            "category":"Professional",
            "subcategory":"Accounting & Tax Preparation",
            "type":"Services"
        }
    ],
    "sg:phone":"+44 1256 698022",
    "sg:postcode":"RG24 8AL",
    "sg:province":"Hampshire",
    "sg:tags":[
        "payroll"
    ],
    "wof:name":"The Compliance Group Ltd.",
    "wof:placetype":"venue"
},
  "geometry": {"coordinates":[-1.0693600178,51.291759491],"type":"Point"}
}