{
  "type": "Feature",
  "properties": {
    "addr:full":"1 City Arc Coventry West Midlands CV1 3HX",
    "addr:housenumber":"1",
    "addr:postcode":"cv1 3hx",
    "addr:street":"City Arc",
    "iso:country":"GB",
    "sg:address":"1 City Arc",
    "sg:city":"Coventry",
    "sg:classifiers":[
        {
            "category":"Shopping",
            "subcategory":"Pets & Pet Supplies",
            "type":"Retail Goods"
        }
    ],
    "sg:phone":"+44 24 7655 0675",
    "sg:postcode":"CV1 3HX",
    "sg:province":"West Midlands",
    "wof:name":"Martins Pet Supplies",
    "wof:placetype":"venue"
},
  "geometry": {"coordinates":[-1.514587,52.405922],"type":"Point"}
}