{
  "type": "Feature",
  "properties": {
    "addr:full":"47 Ropergate Pontefract North Yorkshire WF8 1JY",
    "addr:housenumber":"47",
    "addr:postcode":"wf8 1jy",
    "addr:street":"Ropergate Pontefract",
    "iso:country":"GB",
    "sg:address":"47 Ropergate",
    "sg:city":"Pontefract",
    "sg:classifiers":[
        {
            "category":"Health Services",
            "subcategory":"Dentist",
            "type":"Services"
        }
    ],
    "sg:phone":"+44 1977 703413",
    "sg:postcode":"WF8 1JY",
    "sg:province":"North Yorkshire",
    "wof:name":"Ropergate Dental Practice",
    "wof:placetype":"venue"
},
  "geometry": {"coordinates":[-1.313695,53.689655],"type":"Point"}
}