{
  "type": "Feature",
  "properties": {
    "iso:country":"GB",
    "sg:address":"340 Hastilar Road South",
    "sg:city":"Sheffield",
    "sg:classifiers":[
        {
            "category":"Building & Trades",
            "subcategory":"Plumbing",
            "type":"Services"
        }
    ],
    "sg:phone":"+44 114 239 5367",
    "sg:postcode":"S13 8LE",
    "sg:province":"South Yorkshire",
    "sg:tags":[
        "plumber",
        "central",
        "heating"
    ],
    "wof:name":"D C HEATING & PLUMBING",
    "wof:placetype":"venue"
},
  "geometry": {"coordinates":[-1.4041340351,53.3608627319],"type":"Point"}
}