{
  "type": "Feature",
  "properties": {
    "iso:country":"GB",
    "sg:address":"35 Northgate",
    "sg:city":"Canterbury",
    "sg:classifiers":[
        {
            "category":"Retail",
            "subcategory":"Repair Shop",
            "type":"Services"
        }
    ],
    "sg:postcode":"CT1 1BL",
    "sg:province":"Kent",
    "sg:tags":[
        "radio",
        "television",
        "video"
    ],
    "wof:name":"Securatel Communications",
    "wof:placetype":"venue"
},
  "geometry": {"coordinates":[1.0848369598,51.2832603455],"type":"Point"}
}