{
  "type": "Feature",
  "properties": {
    "addr:full":"Coldwells Road, Munstone Hereford Herefordshire HR1 1LH",
    "addr:postcode":"hr1 1lh",
    "addr:street":"Coldwells Road Munstone",
    "iso:country":"GB",
    "sg:address":"Coldwells Road, Munstone",
    "sg:city":"Hereford",
    "sg:classifiers":[
        {
            "category":"Bars & Pubs",
            "type":"Food & Drink"
        }
    ],
    "sg:phone":"+44 1432 267803",
    "sg:postcode":"HR1 1LH",
    "sg:province":"Herefordshire",
    "sg:tags":[
        "pubs",
        "inn"
    ],
    "wof:name":"The Rose Gardens Inn",
    "wof:placetype":"venue"
},
  "geometry": {"coordinates":[-2.719432,52.078121],"type":"Point"}
}