{
  "type": "Feature",
  "properties": {
    "iso:country":"GB",
    "sg:address":"Mount Pleasant Avenue, Llanrumney",
    "sg:city":"Cardiff",
    "sg:classifiers":[
        {
            "category":"Autos & Motor Vehicles",
            "subcategory":"Fuel & Gas Station",
            "type":"Retail Goods"
        }
    ],
    "sg:postcode":"CF3 5SZ",
    "sg:province":"Caerphilly",
    "sg:tags":[
        "petrol",
        "filling"
    ],
    "wof:name":"Richard Mery",
    "wof:placetype":"venue"
},
  "geometry": {"coordinates":[-3.123403,51.521492],"type":"Point"}
}