{
  "type": "Feature",
  "properties": {
    "iso:country":"GB",
    "sg:address":"Tisbury Pharmacy, High St, Tisbury",
    "sg:city":"Salisbury",
    "sg:classifiers":[
        {
            "category":"Professional",
            "subcategory":"Art Services",
            "type":"Services"
        }
    ],
    "sg:postcode":"SP3 6LD",
    "sg:province":"Wiltshire",
    "sg:tags":[
        "photographer"
    ],
    "wof:name":"Kirby,Idris,",
    "wof:placetype":"venue"
},
  "geometry": {"coordinates":[-2.080324,51.066849],"type":"Point"}
}