{
  "type": "Feature",
  "properties": {
    "iso:country":"GB",
    "sg:address":"High St",
    "sg:city":"Polegate",
    "sg:classifiers":[
        {
            "category":"Travel",
            "subcategory":"Hotels & Motels",
            "type":"Entertainment"
        }
    ],
    "sg:postcode":"BN26 5TA",
    "sg:province":"East Sussex",
    "wof:name":"Reed,A R,",
    "wof:placetype":"venue"
},
  "geometry": {"coordinates":[0.156761,50.806946],"type":"Point"}
}