{
  "type": "Feature",
  "properties": {
    "addr:full":"58 High Street Grays Essex RM17 6NA",
    "addr:housenumber":"58",
    "addr:postcode":"rm17 6na",
    "addr:street":"High Street",
    "iso:country":"GB",
    "sg:address":"58 High Street",
    "sg:city":"Grays",
    "sg:classifiers":[
        {
            "category":"Home & Garden",
            "subcategory":"Home Furnishings",
            "type":"Retail Goods"
        }
    ],
    "sg:phone":"+44 1375 392358",
    "sg:postcode":"RM17 6NA",
    "sg:province":"Essex",
    "sg:tags":[
        "blind",
        "curtain",
        "fitting"
    ],
    "wof:name":"Curtains Babe",
    "wof:placetype":"venue"
},
  "geometry": {"coordinates":[0.3225330114,51.4755821228],"type":"Point"}
}