{
  "type": "Feature",
  "properties": {
    "addr:full":"4 York Street Stourport-on-severn Worcestershire DY13 9EQ",
    "addr:housenumber":"4",
    "addr:postcode":"dy13 9eq",
    "addr:street":"York Street",
    "iso:country":"GB",
    "sg:address":"4 York Street",
    "sg:city":"Stourport-on-severn",
    "sg:classifiers":[
        {
            "category":"Food & Beverages",
            "subcategory":"Meat & Fish",
            "type":"Retail Goods"
        }
    ],
    "sg:phone":"+44 1299 823493",
    "sg:postcode":"DY13 9EQ",
    "sg:province":"Worcestershire",
    "sg:tags":[
        "butcher"
    ],
    "wof:name":"M M Freeman Butcher",
    "wof:placetype":"venue"
},
  "geometry": {"coordinates":[-2.278671,52.338787],"type":"Point"}
}