{
  "type": "Feature",
  "properties": {
    "addr:full":"1 Seafield St Buckie Moray AB56 2SG",
    "addr:housenumber":"1",
    "addr:postcode":"ab56 2sg",
    "addr:street":"Seafield St",
    "iso:country":"GB",
    "sg:address":"1 Seafield St",
    "sg:city":"Buckie",
    "sg:classifiers":[
        {
            "category":"Professional",
            "subcategory":"Lawyer & Legal Services",
            "type":"Services"
        }
    ],
    "sg:phone":"+44 1542 840408",
    "sg:postcode":"AB56 2SG",
    "sg:province":"Moray",
    "sg:tags":[
        "solicitor"
    ],
    "wof:name":"Kings",
    "wof:placetype":"venue"
},
  "geometry": {"coordinates":[-2.96522,57.676811],"type":"Point"}
}