{
  "type": "Feature",
  "properties": {
    "addr:full":"Burwood House, High St, Drayton Abingdon Oxfordshire OX14 4SX",
    "addr:postcode":"ox14 4sx",
    "addr:street":"High St",
    "iso:country":"GB",
    "sg:address":"Burwood House, High St, Drayton",
    "sg:city":"Abingdon",
    "sg:classifiers":[
        {
            "category":"Professional",
            "subcategory":"Management & Consulting",
            "type":"Services"
        },
        {
            "category":"Sports & Exercise",
            "subcategory":"Sports Center",
            "type":"Entertainment"
        }
    ],
    "sg:phone":"+44 1235 555411",
    "sg:postcode":"OX14 4SX",
    "sg:province":"Oxfordshire",
    "sg:tags":[
        "technician",
        "adviser",
        "safety",
        "environmental",
        "consultant"
    ],
    "wof:name":"Oxford Safety & Risk Management",
    "wof:placetype":"venue"
},
  "geometry": {"coordinates":[-1.303014,51.644051],"type":"Point"}
}