{
  "type": "Feature",
  "properties": {
    "iso:country":"GB",
    "sg:address":"107 Lower Lickhill Road",
    "sg:city":"Stourport-on-severn",
    "sg:classifiers":[
        {
            "category":"Shopping",
            "subcategory":"Department Store",
            "type":"Retail Goods"
        }
    ],
    "sg:postcode":"DY13 8UQ",
    "sg:province":"Worcestershire",
    "wof:name":"Lickhill Stores",
    "wof:placetype":"venue"
},
  "geometry": {"coordinates":[-2.2929120064,52.3467750549],"type":"Point"}
}