{
  "type": "Feature",
  "properties": {
    "addr:full":"Second Floor, 14 The Broadway Stanmore Greater London HA7 4DW",
    "addr:housenumber":"second floor 14",
    "addr:postcode":"ha7 4dw",
    "addr:street":"The Broadway",
    "iso:country":"GB",
    "sg:address":"Second Floor, 14 The Broadway",
    "sg:city":"Stanmore",
    "sg:classifiers":[
        {
            "category":"Professional",
            "subcategory":"Business Services",
            "type":"Services"
        }
    ],
    "sg:phone":"+44 20 8954 0297",
    "sg:postcode":"HA7 4DW",
    "sg:province":"Greater London",
    "sg:tags":[
        "import",
        "export",
        "agent"
    ],
    "wof:name":"Dandee International",
    "wof:placetype":"venue"
},
  "geometry": {"coordinates":[-0.311082989,51.6178131104],"type":"Point"}
}