{
  "type": "Feature",
  "properties": {
    "iso:country":"GB",
    "sg:address":"5 Shire Parade, The Ridings, Worth",
    "sg:city":"Crawley",
    "sg:classifiers":[
        {
            "category":"Food & Beverages",
            "subcategory":"Groceries & Convenience Stores",
            "type":"Retail Goods"
        }
    ],
    "sg:phone":"+44 1293 888238",
    "sg:postcode":"RH10 7XR",
    "sg:province":"Surrey",
    "wof:name":"Circle C",
    "wof:placetype":"venue"
},
  "geometry": {"coordinates":[-0.1448110044,51.1199798584],"type":"Point"}
}