{
  "type": "Feature",
  "properties": {
    "iso:country":"GB",
    "sg:address":"24 Croydon Street, Domestic Street Industrial Estate",
    "sg:city":"Leeds",
    "sg:classifiers":[
        {
            "category":"Professional",
            "subcategory":"Printing & Photocopies",
            "type":"Services"
        }
    ],
    "sg:phone":"+44 113 245 3246",
    "sg:postcode":"LS11 9RT",
    "sg:province":"West Yorkshire",
    "sg:tags":[
        "printer"
    ],
    "wof:name":"A W Angus & Co. Ltd.",
    "wof:placetype":"venue"
},
  "geometry": {"coordinates":[-1.5656150579,53.7884216309],"type":"Point"}
}