{
  "type": "Feature",
  "properties": {
    "addr:full":"9 Willenhall Clo Luton Bedfordshire LU3 3XX",
    "addr:housenumber":"9",
    "addr:postcode":"lu3 3xx",
    "addr:street":"Willenhall Clo",
    "iso:country":"GB",
    "sg:address":"9 Willenhall Clo",
    "sg:city":"Luton",
    "sg:classifiers":[
        {
            "category":"Food & Beverages",
            "subcategory":"Specialty",
            "type":"Retail Goods"
        }
    ],
    "sg:phone":"+44 1582 591906",
    "sg:postcode":"LU3 3XX",
    "sg:province":"Bedfordshire",
    "sg:tags":[
        "product",
        "health"
    ],
    "wof:name":"Herbalife Independent Distributor",
    "wof:placetype":"venue"
},
  "geometry": {"coordinates":[-0.439926,51.916477],"type":"Point"}
}