{
  "type": "Feature",
  "properties": {
    "addr:full":"The Hamlet Centre Norwich Norfolk NR1 4BP",
    "addr:postcode":"nr1 4bp",
    "addr:street":"Norwich Norfolk",
    "iso:country":"GB",
    "sg:address":"The Hamlet Centre",
    "sg:city":"Norwich",
    "sg:classifiers":[
        {
            "category":"Education",
            "subcategory":"Library",
            "type":"Public Place"
        },
        {
            "category":"Organizations",
            "subcategory":"Non-profit Organization",
            "type":"Services"
        }
    ],
    "sg:phone":"+44 1603 616094",
    "sg:postcode":"NR1 4BP",
    "sg:province":"Norfolk",
    "sg:tags":[
        "charitable",
        "organisation",
        "book",
        "charity"
    ],
    "wof:name":"The Hamlet Centre Trust",
    "wof:placetype":"venue"
},
  "geometry": {"coordinates":[1.2949,52.622494],"type":"Point"}
}