{
  "type": "Feature",
  "properties": {
    "iso:country":"GB",
    "sg:address":"Warden, Common Road, Stock",
    "sg:city":"Ingatestone",
    "sg:classifiers":[
        {
            "category":"Social Services",
            "subcategory":"Adult Care",
            "type":"Services"
        }
    ],
    "sg:phone":"+44 1277 841323",
    "sg:postcode":"CM4 9NF",
    "sg:province":"Essex",
    "sg:tags":[
        "housing",
        "sheltered"
    ],
    "wof:name":"Shaftesbury Housing Association Ltd.",
    "wof:placetype":"venue"
},
  "geometry": {"coordinates":[0.383585006,51.669921875],"type":"Point"}
}