{
  "type": "Feature",
  "properties": {
    "addr:full":"27 Mooreland Road Bromley Kent BR1 3RD",
    "addr:housenumber":"27",
    "addr:postcode":"br1 3rd",
    "addr:street":"Mooreland Road",
    "iso:country":"GB",
    "sg:address":"27 Mooreland Road",
    "sg:city":"Bromley",
    "sg:classifiers":[
        {
            "category":"Professional",
            "subcategory":"Engineering",
            "type":"Services"
        }
    ],
    "sg:phone":"+44 20 8466 7348",
    "sg:postcode":"BR1 3RD",
    "sg:province":"Kent",
    "sg:tags":[
        "contractor",
        "electrical",
        "engineer"
    ],
    "wof:name":"Wayforward",
    "wof:placetype":"venue"
},
  "geometry": {"coordinates":[0.0115040001,51.4115409851],"type":"Point"}
}