{
  "type": "Feature",
  "properties": {
    "addr:full":"233 High Street Hornchurch Essex RM11 3XU",
    "addr:housenumber":"233",
    "addr:postcode":"rm11 3xu",
    "addr:street":"High Street",
    "iso:country":"GB",
    "sg:address":"233 High Street",
    "sg:city":"Hornchurch",
    "sg:classifiers":[
        {
            "category":"Education",
            "subcategory":"University",
            "type":"Public Place"
        }
    ],
    "sg:phone":"+44 1708 449538",
    "sg:postcode":"RM11 3XU",
    "sg:province":"Essex",
    "sg:tags":[
        "adult"
    ],
    "wof:name":"Robert Beard Centre",
    "wof:placetype":"venue"
},
  "geometry": {"coordinates":[0.2241030037,51.5613212585],"type":"Point"}
}