{
  "type": "Feature",
  "properties": {
    "iso:country":"GB",
    "sg:address":"85 Savoy Road",
    "sg:city":"Bristol",
    "sg:classifiers":[
        {
            "category":"Personal",
            "type":"Services"
        }
    ],
    "sg:phone":"+44 117 972 4356",
    "sg:postcode":"BS4 3SZ",
    "sg:province":"City of Bristol",
    "sg:tags":[
        "delivery"
    ],
    "wof:name":"T & M Deliveries",
    "wof:placetype":"venue"
},
  "geometry": {"coordinates":[-2.5519659519,51.4464874268],"type":"Point"}
}