{
  "type": "Feature",
  "properties": {
    "iso:country":"GB",
    "sg:address":"3 Llewelyn Avenue",
    "sg:city":"Llandudno",
    "sg:classifiers":[
        {
            "category":"Shopping",
            "subcategory":"Pets & Pet Supplies",
            "type":"Retail Goods"
        }
    ],
    "sg:phone":"+44 1492 878791",
    "sg:postcode":"LL30 2ER",
    "sg:province":"Conwy",
    "sg:tags":[
        "shop"
    ],
    "wof:name":"The Pet Centre",
    "wof:placetype":"venue"
},
  "geometry": {"coordinates":[-3.8330750465,53.3263473511],"type":"Point"}
}