{
  "type": "Feature",
  "properties": {
    "addr:full":"Diamond House, 36-38 Hatton Garden London Greater London EC1N 8EB",
    "addr:housenumber":"36-38",
    "addr:postcode":"ec1n 8eb",
    "addr:street":"Hatton Garden",
    "iso:country":"GB",
    "sg:address":"Diamond House, 36-38 Hatton Garden",
    "sg:city":"London",
    "sg:classifiers":[
        {
            "category":"Airline",
            "type":"Transportation"
        }
    ],
    "sg:phone":"+44 20 7242 9501",
    "sg:postcode":"EC1N 8EB",
    "sg:province":"Greater London",
    "sg:tags":[
        "aircraft",
        "charter"
    ],
    "wof:name":"International Skycharter Ltd.",
    "wof:placetype":"venue"
},
  "geometry": {"coordinates":[-0.1081520021,51.5201416016],"type":"Point"}
}