{
  "type": "Feature",
  "properties": {
    "iso:country":"GB",
    "sg:address":"27 Praed Street",
    "sg:city":"London",
    "sg:classifiers":[
        {
            "category":"Shopping",
            "subcategory":"Clothing, Apparel, & Fashions",
            "type":"Retail Goods"
        }
    ],
    "sg:postcode":"W2 1NJ",
    "sg:province":"Greater London",
    "sg:tags":[
        "lingerie",
        "hosiery"
    ],
    "wof:name":"Honour",
    "wof:placetype":"venue"
},
  "geometry": {"coordinates":[-0.169949,51.518574],"type":"Point"}
}