{
  "type": "Feature",
  "properties": {
    "iso:country":"GB",
    "sg:address":"1 Abbey Gate Court, Stockett Lane",
    "sg:city":"Maidstone",
    "sg:classifiers":[
        {
            "category":"Manufacturing",
            "subcategory":"Paper Products",
            "type":"Manufacturing & Wholesale Goods"
        }
    ],
    "sg:phone":"+44 1622 355140",
    "sg:postcode":"ME15 0PP",
    "sg:province":"Kent",
    "sg:tags":[
        "board"
    ],
    "wof:name":"James McNaughton Paper Merchants Ltd.",
    "wof:placetype":"venue"
},
  "geometry": {"coordinates":[0.51262,51.25354],"type":"Point"}
}