{
  "type": "Feature",
  "properties": {
    "iso:country":"GB",
    "sg:address":"68 Whifflet Street",
    "sg:city":"Coatbridge",
    "sg:classifiers":[
        {
            "category":"Bars & Pubs",
            "type":"Food & Drink"
        }
    ],
    "sg:phone":"+44 1236 438841",
    "sg:postcode":"ML5 4EJ",
    "sg:province":"North Lanarkshire",
    "sg:tags":[
        "pubs",
        "inn"
    ],
    "wof:name":"The Whifflet Arms",
    "wof:placetype":"venue"
},
  "geometry": {"coordinates":[-4.020664,55.852245],"type":"Point"}
}