{
  "type": "Feature",
  "properties": {
    "addr:full":"48 Springfield Drive Thornton-cleveleys Lancashire FY5 4LN",
    "addr:housenumber":"48",
    "addr:postcode":"fy5 4ln",
    "addr:street":"Springfield Drive Thornton-Cleveleys",
    "iso:country":"GB",
    "sg:address":"48 Springfield Drive",
    "sg:city":"Thornton-cleveleys",
    "sg:classifiers":[
        {
            "category":"Building & Trades",
            "subcategory":"Plumbing",
            "type":"Services"
        }
    ],
    "sg:phone":"+44 1253 868418",
    "sg:postcode":"FY5 4LN",
    "sg:province":"Lancashire",
    "sg:tags":[
        "heating"
    ],
    "wof:name":"First Choice Plumbing",
    "wof:placetype":"venue"
},
  "geometry": {"coordinates":[-3.011044,53.884048],"type":"Point"}
}