{
  "type": "Feature",
  "properties": {
    "addr:full":"15 Wilton Parade Feltham Greater London TW13 4BU",
    "addr:housenumber":"15",
    "addr:postcode":"tw13 4bu",
    "addr:street":"Wilton Parade",
    "iso:country":"GB",
    "sg:address":"15 Wilton Parade",
    "sg:city":"Feltham",
    "sg:classifiers":[
        {
            "category":"Travel",
            "subcategory":"Travel Agent",
            "type":"Entertainment"
        }
    ],
    "sg:phone":"+44 20 8844 1892",
    "sg:postcode":"TW13 4BU",
    "sg:province":"Greater London",
    "wof:name":"Cook.Thomas",
    "wof:placetype":"venue"
},
  "geometry": {"coordinates":[-0.4106500149,51.445110321],"type":"Point"}
}