{
  "type": "Feature",
  "properties": {
    "iso:country":"GB",
    "sg:address":"Winchelsea St",
    "sg:city":"Dover",
    "sg:classifiers":[
        {
            "category":"Social Services",
            "type":"Services"
        }
    ],
    "sg:phone":"+44 1304 225881",
    "sg:postcode":"CT17 9ST",
    "sg:province":"Kent",
    "wof:name":"Orange Badge Scheme",
    "wof:placetype":"venue"
},
  "geometry": {"coordinates":[1.29806,51.124531],"type":"Point"}
}