{
  "type": "Feature",
  "properties": {
    "addr:full":"Stockbridge Shop, 39-41 Deanhaugh Street Edinburgh City of Edinburgh EH4 1LR",
    "addr:housenumber":"39-41",
    "addr:postcode":"eh4 1lr",
    "addr:street":"Deanhaugh Street",
    "iso:country":"GB",
    "sg:address":"Stockbridge Shop, 39-41 Deanhaugh Street",
    "sg:city":"Edinburgh",
    "sg:classifiers":[
        {
            "category":"Organizations",
            "subcategory":"Non-profit Organization",
            "type":"Services"
        }
    ],
    "sg:postcode":"EH4 1LR",
    "sg:province":"City of Edinburgh",
    "sg:tags":[
        "organisation",
        "voluntary",
        "charity"
    ],
    "wof:name":"Capability Scotland",
    "wof:placetype":"venue"
},
  "geometry": {"coordinates":[-3.2097198963,55.9586906433],"type":"Point"}
}