{
  "type": "Feature",
  "properties": {
    "addr:full":"245 Skipton Road Harrogate North Yorkshire HG1 3EY",
    "addr:housenumber":"245",
    "addr:postcode":"hg1 3ey",
    "addr:street":"Skipton Road",
    "iso:country":"GB",
    "sg:address":"245 Skipton Road",
    "sg:city":"Harrogate",
    "sg:classifiers":[
        {
            "category":"Personal",
            "subcategory":"Beauty Salon",
            "type":"Services"
        }
    ],
    "sg:phone":"+44 1423 560079",
    "sg:postcode":"HG1 3EY",
    "sg:province":"North Yorkshire",
    "sg:tags":[
        "unisex",
        "hairdresser"
    ],
    "wof:name":"Frizz-Bizz",
    "wof:placetype":"venue"
},
  "geometry": {"coordinates":[-1.5427019596,54.0054855347],"type":"Point"}
}