{
  "type": "Feature",
  "properties": {
    "iso:country":"GB",
    "sg:address":"1 Speke Blvd",
    "sg:city":"Liverpool",
    "sg:classifiers":[
        {
            "category":"Shopping",
            "subcategory":"News",
            "type":"Retail Goods"
        }
    ],
    "sg:phone":"+44 151 448 9531",
    "sg:postcode":"L24 9HZ",
    "sg:province":"Merseyside",
    "sg:tags":[
        "newsagent"
    ],
    "wof:name":"Horsley & Son",
    "wof:placetype":"venue"
},
  "geometry": {"coordinates":[-2.8500959873,53.3486404419],"type":"Point"}
}