{
  "type": "Feature",
  "properties": {
    "iso:country":"GB",
    "sg:address":"Southend Farm, Southend Road",
    "sg:city":"Billericay",
    "sg:classifiers":[
        {
            "category":"Building & Trades",
            "subcategory":"Construction",
            "type":"Services"
        }
    ],
    "sg:postcode":"CM11 2PP",
    "sg:province":"Essex",
    "sg:tags":[
        "contractor"
    ],
    "wof:name":"Nugent & Hills",
    "wof:placetype":"venue"
},
  "geometry": {"coordinates":[0.4618,51.588799],"type":"Point"}
}