{
  "type": "Feature",
  "properties": {
    "iso:country":"GB",
    "sg:address":"90 Commercial Road",
    "sg:city":"Grantham",
    "sg:classifiers":[
        {
            "category":"Professional",
            "type":"Services"
        }
    ],
    "sg:postcode":"NG31 6DB",
    "sg:province":"Lincolnshire",
    "sg:tags":[
        "reflexologists"
    ],
    "wof:name":"Derbyshire John 'S Clinic of Natural Therapies",
    "wof:placetype":"venue"
},
  "geometry": {"coordinates":[-0.641025,52.908733],"type":"Point"}
}