{
  "type": "Feature",
  "properties": {
    "addr:full":"High Beech Nurseries, Avey Lane Waltham Abbey Essex EN9 3QJ",
    "addr:postcode":"en9 3qj",
    "addr:street":"Avey Lane",
    "iso:country":"GB",
    "sg:address":"High Beech Nurseries, Avey Lane",
    "sg:city":"Waltham Abbey",
    "sg:classifiers":[
        {
            "category":"Shopping",
            "subcategory":"Florist",
            "type":"Retail Goods"
        }
    ],
    "sg:phone":"+44 20 8508 3755",
    "sg:postcode":"EN9 3QJ",
    "sg:province":"Essex",
    "wof:name":"A J Mason Ltd.",
    "wof:placetype":"venue"
},
  "geometry": {"coordinates":[0.0332310013,51.6716041565],"type":"Point"}
}