{
  "type": "Feature",
  "properties": {
    "iso:country":"GB",
    "sg:address":"39 The Broadway, Cheam",
    "sg:city":"Sutton",
    "sg:classifiers":[
        {
            "category":"Shopping",
            "subcategory":"Clothing, Apparel, & Fashions",
            "type":"Retail Goods"
        },
        {
            "category":"Banks & Credit Unions",
            "subcategory":"Investment Brokerage",
            "type":"Services"
        }
    ],
    "sg:postcode":"SM3 8BL",
    "sg:province":"Surrey",
    "sg:tags":[
        "agency",
        "dress",
        "dresswear"
    ],
    "wof:name":"The Frock Exchange",
    "wof:placetype":"venue"
},
  "geometry": {"coordinates":[-0.216933,51.358883],"type":"Point"}
}