{
  "type": "Feature",
  "properties": {
    "addr:full":"1 Market Passage Stoke-on-trent Staffordshire ST6 3AQ",
    "addr:housenumber":"1",
    "addr:postcode":"st6 3aq",
    "addr:street":"Market Passage",
    "iso:country":"GB",
    "sg:address":"1 Market Passage",
    "sg:city":"Stoke-on-trent",
    "sg:classifiers":[
        {
            "category":"Communications",
            "type":"Services"
        }
    ],
    "sg:postcode":"ST6 3AQ",
    "sg:province":"Staffordshire",
    "sg:tags":[
        "tv",
        "video",
        "radio"
    ],
    "wof:name":"T P Services",
    "wof:placetype":"venue"
},
  "geometry": {"coordinates":[-2.19688797,53.0455551147],"type":"Point"}
}