{
  "type": "Feature",
  "properties": {
    "iso:country":"GB",
    "sg:address":"16-20 Market Street",
    "sg:city":"Sandwich",
    "sg:classifiers":[
        {
            "category":"Food & Beverages",
            "subcategory":"Groceries & Convenience Stores",
            "type":"Retail Goods"
        }
    ],
    "sg:phone":"+44 1304 612233",
    "sg:postcode":"CT13 9DA",
    "sg:province":"Kent",
    "wof:name":"Spar Store",
    "wof:placetype":"venue"
},
  "geometry": {"coordinates":[1.340125,51.275269],"type":"Point"}
}