{
  "type": "Feature",
  "properties": {
    "iso:country":"GB",
    "sg:address":"29-31 High St",
    "sg:city":"Dorking",
    "sg:classifiers":[
        {
            "category":"Travel",
            "subcategory":"Travel Agent",
            "type":"Entertainment"
        }
    ],
    "sg:phone":"+44 1306 740554",
    "sg:postcode":"RH4 1AR",
    "sg:province":"Surrey",
    "wof:name":"Lunn Poly Ltd",
    "wof:placetype":"venue"
},
  "geometry": {"coordinates":[-0.3323400021,51.2318534851],"type":"Point"}
}