{
  "type": "Feature",
  "properties": {
    "iso:country":"GB",
    "sg:address":"124-126 Roman Rd",
    "sg:city":"Bethnal Green",
    "sg:classifiers":[
        {
            "category":"Home & Garden",
            "subcategory":"Carpets & Floor Coverings",
            "type":"Retail Goods"
        }
    ],
    "sg:phone":"+44 20 8279 4517",
    "sg:postcode":"E2 0RN",
    "sg:province":"Greater London",
    "sg:tags":[
        "carpets",
        "rug",
        "matting"
    ],
    "wof:name":"M & K Carpets",
    "wof:placetype":"venue"
},
  "geometry": {"coordinates":[-0.062569,51.526684],"type":"Point"}
}