{
  "type": "Feature",
  "properties": {
    "addr:full":"138a Wright Street, Horwich Bolton Lancashire BL6 7HU",
    "addr:housenumber":"138a",
    "addr:postcode":"bl6 7hu",
    "addr:street":"Wright Street",
    "iso:country":"GB",
    "sg:address":"138a Wright Street, Horwich",
    "sg:city":"Bolton",
    "sg:classifiers":[
        {
            "category":"Shopping",
            "subcategory":"Hobbies, Toys, & Games",
            "type":"Retail Goods"
        }
    ],
    "sg:phone":"+44 1204 669782",
    "sg:postcode":"BL6 7HU",
    "sg:province":"Lancashire",
    "sg:tags":[
        "collectors'",
        "item"
    ],
    "wof:name":"The Toy Shop",
    "wof:placetype":"venue"
},
  "geometry": {"coordinates":[-2.547411,53.600124],"type":"Point"}
}