{
  "type": "Feature",
  "properties": {
    "addr:full":"26 Meadow Walk Whitstable Kent CT5 4PW",
    "addr:housenumber":"26",
    "addr:postcode":"ct5 4pw",
    "addr:street":"Meadow Walk Whitstable",
    "iso:country":"GB",
    "sg:address":"26 Meadow Walk",
    "sg:city":"Whitstable",
    "sg:classifiers":[
        {
            "category":"Professional",
            "subcategory":"Art Services",
            "type":"Services"
        }
    ],
    "sg:phone":"+44 1227 275058",
    "sg:postcode":"CT5 4PW",
    "sg:province":"Kent",
    "sg:tags":[
        "photographer"
    ],
    "wof:name":"Barry Duffield",
    "wof:placetype":"venue"
},
  "geometry": {"coordinates":[1.019026041,51.3451347351],"type":"Point"}
}