{
  "type": "Feature",
  "properties": {
    "addr:full":"82 Bishops Bridge Road London Greater London W2 6BB",
    "addr:housenumber":"82",
    "addr:postcode":"w2 6bb",
    "addr:street":"Bishops Bridge Road",
    "iso:country":"GB",
    "sg:address":"82 Bishops Bridge Road",
    "sg:city":"London",
    "sg:classifiers":[
        {
            "category":"Utilities",
            "type":"Services"
        }
    ],
    "sg:phone":"+44 20 7792 6200",
    "sg:postcode":"W2 6BB",
    "sg:province":"Greater London",
    "sg:tags":[
        "internet"
    ],
    "wof:name":"Simply Internet Ltd.",
    "wof:placetype":"venue"
},
  "geometry": {"coordinates":[-0.185999006,51.5164794922],"type":"Point"}
}