{
  "type": "Feature",
  "properties": {
    "iso:country":"GB",
    "sg:address":"St Andrews Way",
    "sg:city":"Slough",
    "sg:classifiers":[
        {
            "category":"Shopping",
            "subcategory":"Department Store",
            "type":"Retail Goods"
        },
        {
            "category":"Food & Beverages",
            "subcategory":"Groceries & Convenience Stores",
            "type":"Retail Goods"
        }
    ],
    "sg:phone":"+44 1628 661457",
    "sg:postcode":"SL1 5LJ",
    "sg:province":"Berkshire",
    "wof:name":"SAHANS FOOD STORE",
    "wof:placetype":"venue"
},
  "geometry": {"coordinates":[-0.6503340006,51.5197067261],"type":"Point"}
}