{
  "type": "Feature",
  "properties": {
    "addr:full":"6 Fairland Street Wymondham Norfolk NR18 0AN",
    "addr:housenumber":"6",
    "addr:postcode":"nr18 0an",
    "addr:street":"Fairland Street",
    "iso:country":"GB",
    "sg:address":"6 Fairland Street",
    "sg:city":"Wymondham",
    "sg:classifiers":[
        {
            "category":"Fast Food",
            "type":"Food & Drink"
        }
    ],
    "sg:phone":"+44 1953 606365",
    "sg:postcode":"NR18 0AN",
    "sg:province":"Norfolk",
    "sg:tags":[
        "away",
        "take"
    ],
    "wof:name":"Peking Dragon",
    "wof:placetype":"venue"
},
  "geometry": {"coordinates":[1.1136740446,52.5696182251],"type":"Point"}
}