{
  "type": "Feature",
  "properties": {
    "addr:full":"Orchard Lea, Greenhill Way Crickhowell Monmouthshire NP8 1AF",
    "addr:postcode":"np8 1af",
    "addr:street":"Greenhill Way",
    "iso:country":"GB",
    "sg:address":"Orchard Lea, Greenhill Way",
    "sg:city":"Crickhowell",
    "sg:classifiers":[
        {
            "category":"Organizations",
            "subcategory":"Non-profit Organization",
            "type":"Services"
        }
    ],
    "sg:phone":"+44 1873 811172",
    "sg:postcode":"NP8 1AF",
    "sg:province":"Monmouthshire",
    "sg:tags":[
        "organisation",
        "voluntary",
        "charity"
    ],
    "wof:name":"S S A F A Forces Help",
    "wof:placetype":"venue"
},
  "geometry": {"coordinates":[-3.1381220818,51.8616256714],"type":"Point"}
}