{
  "type": "Feature",
  "properties": {
    "iso:country":"GB",
    "sg:address":"1 Mill Wynd",
    "sg:city":"Yarm",
    "sg:classifiers":[
        {
            "category":"Real Estate",
            "subcategory":"Developer",
            "type":"Services"
        }
    ],
    "sg:phone":"+44 1642 785385",
    "sg:postcode":"TS15 9AF",
    "sg:province":"North Yorkshire",
    "sg:tags":[
        "property"
    ],
    "wof:name":"Newham Properties Ltd.",
    "wof:placetype":"venue"
},
  "geometry": {"coordinates":[-1.3537230492,54.5084037781],"type":"Point"}
}