{
  "type": "Feature",
  "properties": {
    "addr:full":"The Estate Office, Lackford Bury St Edmunds Cambridgeshire IP28 6HW",
    "addr:postcode":"ip28 6hw",
    "addr:street":"Lackford;St",
    "iso:country":"GB",
    "sg:address":"The Estate Office, Lackford",
    "sg:city":"Bury St Edmunds",
    "sg:classifiers":[
        {
            "category":"Farming",
            "subcategory":"Farm",
            "type":"Manufacturing & Wholesale Goods"
        }
    ],
    "sg:postcode":"IP28 6HW",
    "sg:province":"Cambridgeshire",
    "sg:tags":[
        "mixed",
        "crop"
    ],
    "wof:name":"D W P Gough & Co. Ltd.",
    "wof:placetype":"venue"
},
  "geometry": {"coordinates":[0.626045,52.301311],"type":"Point"}
}