{
  "type": "Feature",
  "properties": {
    "iso:country":"GB",
    "sg:address":"Telesales, Roving Bridge, Whixall",
    "sg:city":"Whitchurch",
    "sg:classifiers":[
        {
            "category":"Wholesale",
            "subcategory":"Scrap",
            "type":"Manufacturing & Wholesale Goods"
        }
    ],
    "sg:phone":"+44 1948 880019",
    "sg:postcode":"SY13 2RT",
    "sg:province":"Cheshire",
    "sg:tags":[
        "breaker",
        "dismantlers"
    ],
    "wof:name":"William J Furber",
    "wof:placetype":"venue"
},
  "geometry": {"coordinates":[-2.720931,52.905739],"type":"Point"}
}