{
  "type": "Feature",
  "properties": {
    "iso:country":"GB",
    "sg:address":"Poland Street",
    "sg:city":"London",
    "sg:classifiers":[
        {
            "category":"Parking",
            "type":"Transportation"
        }
    ],
    "sg:phone":"+44 20 7437 7660",
    "sg:postcode":"W1F 7NB",
    "sg:province":"Greater London",
    "sg:tags":[
        "car",
        "park"
    ],
    "wof:name":"Poland Street Car Parking",
    "wof:placetype":"venue"
},
  "geometry": {"coordinates":[-0.1370290071,51.5145835876],"type":"Point"}
}