{
  "type": "Feature",
  "properties": {
    "addr:full":"44 Dilbridge Road West Colchester Essex CO4 0BJ",
    "addr:housenumber":"44",
    "addr:postcode":"co4 0bj",
    "addr:street":"Dilbridge Road West Colchester",
    "iso:country":"GB",
    "sg:address":"44 Dilbridge Road West",
    "sg:city":"Colchester",
    "sg:classifiers":[
        {
            "category":"Retail",
            "subcategory":"Auto Repair",
            "type":"Services"
        }
    ],
    "sg:phone":"+44 1206 869612",
    "sg:postcode":"CO4 0BJ",
    "sg:province":"Essex",
    "sg:tags":[
        "modification",
        "garage"
    ],
    "wof:name":"Is Autos",
    "wof:placetype":"venue"
},
  "geometry": {"coordinates":[0.919295,51.895679],"type":"Point"}
}