{
  "type": "Feature",
  "properties": {
    "iso:country":"GB",
    "sg:address":"Penuwch Fach",
    "sg:city":"Aberystwyth",
    "sg:classifiers":[
        {
            "category":"Farming",
            "subcategory":"Livestock Farm",
            "type":"Manufacturing & Wholesale Goods"
        }
    ],
    "sg:phone":"+44 1970 880253",
    "sg:postcode":"SY23 4ND",
    "sg:province":"Ceredigion",
    "sg:tags":[
        "others"
    ],
    "wof:name":"Owen Branwen",
    "wof:placetype":"venue"
},
  "geometry": {"coordinates":[-4.003329,52.346901],"type":"Point"}
}