{
  "type": "Feature",
  "properties": {
    "addr:full":"142 Wardour St West End Hampshire W1V 3AU",
    "addr:housenumber":"142",
    "addr:postcode":"w1v 3au",
    "addr:street":"Wardour St",
    "iso:country":"GB",
    "sg:address":"142 Wardour St",
    "sg:city":"West End",
    "sg:classifiers":[
        {
            "category":"Communications",
            "type":"Services"
        }
    ],
    "sg:phone":"+44 20 7878 7884",
    "sg:postcode":"W1V 3AU",
    "sg:province":"Hampshire",
    "sg:tags":[
        "audio-visual"
    ],
    "wof:name":"Stream",
    "wof:placetype":"venue"
},
  "geometry": {"coordinates":[-0.1347659975,51.514793396],"type":"Point"}
}