{
  "type": "Feature",
  "properties": {
    "addr:full":"297 Perth Road Dundee Dundee City DD2 1JS",
    "addr:housenumber":"297",
    "addr:postcode":"dd2 1js",
    "addr:street":"Perth Road",
    "iso:country":"GB",
    "sg:address":"297 Perth Road",
    "sg:city":"Dundee",
    "sg:classifiers":[
        {
            "category":"Arena",
            "subcategory":"Sports Club",
            "type":"Entertainment"
        }
    ],
    "sg:phone":"+44 1382 665699",
    "sg:postcode":"DD2 1JS",
    "sg:province":"Dundee City",
    "wof:name":"Dundee Bridge Club Ltd",
    "wof:placetype":"venue"
},
  "geometry": {"coordinates":[-3.0041189194,56.4567489624],"type":"Point"}
}