{
  "type": "Feature",
  "properties": {
    "iso:country":"GB",
    "sg:address":"Po Box 38",
    "sg:city":"Wakefield",
    "sg:classifiers":[
        {
            "category":"Home & Garden",
            "subcategory":"Hardware",
            "type":"Retail Goods"
        }
    ],
    "sg:phone":"+44 1924 780000",
    "sg:postcode":"WF1 5PF",
    "sg:province":"West Yorkshire",
    "sg:tags":[
        "heat",
        "mech",
        "exchanger"
    ],
    "wof:name":"Thermal Engineering International Ltd.",
    "wof:placetype":"venue"
},
  "geometry": {"coordinates":[-1.474839,53.67001],"type":"Point"}
}