{
  "type": "Feature",
  "properties": {
    "addr:full":"399 Edgware Road London Greater London W2 1BT",
    "addr:housenumber":"399",
    "addr:postcode":"w2 1bt",
    "addr:street":"Edgware Road",
    "iso:country":"GB",
    "sg:address":"399 Edgware Road",
    "sg:city":"London",
    "sg:classifiers":[
        {
            "category":"Food & Beverages",
            "subcategory":"Supermarket",
            "type":"Retail Goods"
        }
    ],
    "sg:postcode":"W2 1BT",
    "sg:province":"Greater London",
    "wof:name":"Nasa Supermarket",
    "wof:placetype":"venue"
},
  "geometry": {"coordinates":[-0.1747439951,51.5231056213],"type":"Point"}
}