{
  "type": "Feature",
  "properties": {
    "iso:country":"GB",
    "sg:address":"470 Wolverhampton Road",
    "sg:city":"Walsall",
    "sg:classifiers":[
        {
            "category":"Manufacturing",
            "subcategory":"Wood Products",
            "type":"Manufacturing & Wholesale Goods"
        }
    ],
    "sg:phone":"+44 1922 641306",
    "sg:postcode":"WS2 8TD",
    "sg:province":"West Midlands",
    "sg:tags":[
        "maker",
        "cabinet"
    ],
    "wof:name":"D & C Enterprises Ltd.",
    "wof:placetype":"venue"
},
  "geometry": {"coordinates":[-2.012246,52.587212],"type":"Point"}
}