{
  "type": "Feature",
  "properties": {
    "addr:full":"1 Wheelwright Lane Burgess Hill East Sussex RH15 0QS",
    "addr:housenumber":"1",
    "addr:postcode":"rh15 0qs",
    "addr:street":"Wheelwright Lane",
    "iso:country":"GB",
    "sg:address":"1 Wheelwright Lane",
    "sg:city":"Burgess Hill",
    "sg:classifiers":[
        {
            "category":"Professional",
            "subcategory":"Computer Services",
            "type":"Services"
        }
    ],
    "sg:postcode":"RH15 0QS",
    "sg:province":"East Sussex",
    "sg:tags":[
        "system",
        "software"
    ],
    "wof:name":"Pandarus Systems Ltd.",
    "wof:placetype":"venue"
},
  "geometry": {"coordinates":[-0.1124640033,50.9492530823],"type":"Point"}
}