{
  "type": "Feature",
  "properties": {
    "addr:full":"56 Westgate Cleckheaton West Yorkshire BD19 5HB",
    "addr:housenumber":"56",
    "addr:postcode":"bd19 5hb",
    "addr:street":"Westgate Cleckheaton West",
    "iso:country":"GB",
    "sg:address":"56 Westgate",
    "sg:city":"Cleckheaton",
    "sg:classifiers":[
        {
            "category":"Building & Trades",
            "subcategory":"Construction",
            "type":"Services"
        }
    ],
    "sg:phone":"+44 1274 851684",
    "sg:postcode":"BD19 5HB",
    "sg:province":"West Yorkshire",
    "sg:tags":[
        "builder"
    ],
    "wof:name":"Permatex",
    "wof:placetype":"venue"
},
  "geometry": {"coordinates":[-1.7257889509,53.7223510742],"type":"Point"}
}