{
  "type": "Feature",
  "properties": {
    "addr:full":"99 Flat 22 Mcculloch St Glasgow Glasgow City G41 1NT",
    "addr:housenumber":"99 flat 22",
    "addr:postcode":"g41 1nt",
    "addr:street":"Mcculloch St",
    "iso:country":"GB",
    "sg:address":"99 Flat 22 Mcculloch St",
    "sg:city":"Glasgow",
    "sg:classifiers":[
        {
            "category":"Organizations",
            "subcategory":"Non-profit Organization",
            "type":"Services"
        }
    ],
    "sg:phone":"+44 141 418 0000",
    "sg:postcode":"G41 1NT",
    "sg:province":"Glasgow City",
    "sg:tags":[
        "organisation",
        "voluntary",
        "charity"
    ],
    "wof:name":"Glasgow Braendam Link",
    "wof:placetype":"venue"
},
  "geometry": {"coordinates":[-4.2731800079,55.8449707031],"type":"Point"}
}