{
  "type": "Feature",
  "properties": {
    "iso:country":"GB",
    "sg:address":"Oak House, Holywell Street",
    "sg:city":"Flint",
    "sg:classifiers":[
        {
            "category":"Retail",
            "subcategory":"Funeral Services",
            "type":"Services"
        }
    ],
    "sg:phone":"+44 1352 763137",
    "sg:postcode":"CH6 5NS",
    "sg:province":"Flintshire",
    "wof:name":"John Sibeon & Sons",
    "wof:placetype":"venue"
},
  "geometry": {"coordinates":[-3.134479,53.250309],"type":"Point"}
}