{
  "type": "Feature",
  "properties": {
    "addr:full":"27 Newton Pl Glasgow Glasgow City G3 7PY",
    "addr:housenumber":"27",
    "addr:postcode":"g3 7py",
    "addr:street":"Newton Pl",
    "iso:country":"GB",
    "sg:address":"27 Newton Pl",
    "sg:city":"Glasgow",
    "sg:classifiers":[
        {
            "category":"Real Estate",
            "subcategory":"Surveying",
            "type":"Services"
        }
    ],
    "sg:phone":"+44 141 353 0433",
    "sg:postcode":"G3 7PY",
    "sg:province":"Glasgow City",
    "sg:tags":[
        "surveyor",
        "land"
    ],
    "wof:name":"RBJ Land Surveys Ltd",
    "wof:placetype":"venue"
},
  "geometry": {"coordinates":[-4.2727799416,55.8666915894],"type":"Point"}
}