{
  "type": "Feature",
  "properties": {
    "addr:full":"15 Canada Close Banbury Oxfordshire OX16 7RT",
    "addr:housenumber":"15",
    "addr:postcode":"ox16 7rt",
    "addr:street":"Canada Close",
    "iso:country":"GB",
    "sg:address":"15 Canada Close",
    "sg:city":"Banbury",
    "sg:classifiers":[
        {
            "category":"Professional",
            "subcategory":"Business Services",
            "type":"Services"
        }
    ],
    "sg:phone":"+44 1295 270488",
    "sg:postcode":"OX16 7RT",
    "sg:province":"Oxfordshire",
    "sg:tags":[
        "publishers'"
    ],
    "wof:name":"The Red Group Ltd",
    "wof:placetype":"venue"
},
  "geometry": {"coordinates":[-1.3363000154,52.0691070557],"type":"Point"}
}