{
  "type": "Feature",
  "properties": {
    "addr:full":"92 Bondfield Crescent, Wombwell Barnsley South Yorkshire S73 8TL",
    "addr:housenumber":"92",
    "addr:postcode":"s73 8tl",
    "addr:street":"Bondfield Crescent;Yorkshire",
    "iso:country":"GB",
    "sg:address":"92 Bondfield Crescent, Wombwell",
    "sg:city":"Barnsley",
    "sg:classifiers":[
        {
            "category":"Communications",
            "type":"Services"
        }
    ],
    "sg:postcode":"S73 8TL",
    "sg:province":"South Yorkshire",
    "sg:tags":[
        "audio-visual"
    ],
    "wof:name":"Dan Ace Television Ltd.",
    "wof:placetype":"venue"
},
  "geometry": {"coordinates":[-1.406915,53.522392],"type":"Point"}
}