{
  "type": "Feature",
  "properties": {
    "iso:country":"GB",
    "sg:address":"The Square, Hardway",
    "sg:city":"Gosport",
    "sg:classifiers":[
        {
            "category":"Building & Trades",
            "subcategory":"Landscaping Services",
            "type":"Services"
        }
    ],
    "sg:phone":"+44 23 9252 8312",
    "sg:postcode":"PO12 4LH",
    "sg:province":"Hampshire",
    "sg:tags":[
        "landscape",
        "contractor"
    ],
    "wof:name":"Pleasant Surroundings",
    "wof:placetype":"venue"
},
  "geometry": {"coordinates":[-1.139084,50.807255],"type":"Point"}
}