{
  "type": "Feature",
  "properties": {
    "addr:full":"Station Lane, Holme On Spalding Moor York East Riding of Yorkshire YO43 4AL",
    "addr:postcode":"yo43 4al",
    "addr:street":"Station Lane;Moor",
    "iso:country":"GB",
    "sg:address":"Station Lane, Holme On Spalding Moor",
    "sg:city":"York",
    "sg:classifiers":[
        {
            "category":"Personal",
            "subcategory":"Adult",
            "type":"Services"
        }
    ],
    "sg:phone":"+44 1430 861165",
    "sg:postcode":"YO43 4AL",
    "sg:province":"East Riding of Yorkshire",
    "sg:tags":[
        "equestrian"
    ],
    "wof:name":"Paradise Paddocks",
    "wof:placetype":"venue"
},
  "geometry": {"coordinates":[-0.788854,53.839272],"type":"Point"}
}