{
  "type": "Feature",
  "properties": {
    "addr:full":"18 Rodenhurst Road, Clapham Park London Greater London SW4 8AR",
    "addr:housenumber":"18",
    "addr:postcode":"sw4 8ar",
    "addr:street":"Rodenhurst Road Clapham Park",
    "iso:country":"GB",
    "sg:address":"18 Rodenhurst Road, Clapham Park",
    "sg:city":"London",
    "sg:classifiers":[
        {
            "category":"Building & Trades",
            "subcategory":"Landscaping Services",
            "type":"Services"
        }
    ],
    "sg:phone":"+44 20 8671 3274",
    "sg:postcode":"SW4 8AR",
    "sg:province":"Greater London",
    "sg:tags":[
        "gardening"
    ],
    "wof:name":"Pollination",
    "wof:placetype":"venue"
},
  "geometry": {"coordinates":[-0.1321859956,51.4551734924],"type":"Point"}
}