{
  "type": "Feature",
  "properties": {
    "addr:full":"Burcroft Hill Garage, Burcroft Hill, Conisbrough Doncaster South Yorkshire DN12 3EF",
    "addr:postcode":"dn12 3ef",
    "addr:street":"Burcroft",
    "iso:country":"GB",
    "sg:address":"Burcroft Hill Garage, Burcroft Hill, Conisbrough",
    "sg:city":"Doncaster",
    "sg:classifiers":[
        {
            "category":"Retail",
            "subcategory":"Auto Repair",
            "type":"Services"
        }
    ],
    "sg:phone":"+44 1709 860999",
    "sg:postcode":"DN12 3EF",
    "sg:province":"South Yorkshire",
    "sg:tags":[
        "modification",
        "garage",
        "related"
    ],
    "wof:name":"K P's Autos",
    "wof:placetype":"venue"
},
  "geometry": {"coordinates":[-1.2238839865,53.485710144],"type":"Point"}
}