{
  "type": "Feature",
  "properties": {
    "iso:country":"GB",
    "sg:address":"Market Square House, 22 Market Square",
    "sg:city":"Westerham",
    "sg:classifiers":[
        {
            "category":"Real Estate",
            "subcategory":"Architect",
            "type":"Services"
        }
    ],
    "sg:postcode":"TN16 1SR",
    "sg:province":"Kent",
    "wof:name":"Woodward Ambrose Architects Ltd.",
    "wof:placetype":"venue"
},
  "geometry": {"coordinates":[0.070428,51.267097],"type":"Point"}
}