{
  "type": "Feature",
  "properties": {
    "addr:full":"Higher Manor Road Brixham Devon TQ5 8HA",
    "addr:postcode":"tq5 8ha",
    "addr:street":"Manor Road",
    "iso:country":"GB",
    "sg:address":"Higher Manor Road",
    "sg:city":"Brixham",
    "sg:classifiers":[
        {
            "category":"Travel",
            "subcategory":"Hotels & Motels",
            "type":"Entertainment"
        }
    ],
    "sg:phone":"+44 1803 882391",
    "sg:postcode":"TQ5 8HA",
    "sg:province":"Devon",
    "sg:tags":[
        "house",
        "guest"
    ],
    "wof:name":"Richmond House",
    "wof:placetype":"venue"
},
  "geometry": {"coordinates":[-3.517116,50.39492],"type":"Point"}
}