{
  "type": "Feature",
  "properties": {
    "addr:full":"Old Hall Farm, Thetford Rd, Griston Thetford Norfolk IP25 6PR",
    "addr:postcode":"ip25 6pr",
    "addr:street":"Thetford Rd",
    "iso:country":"GB",
    "sg:address":"Old Hall Farm, Thetford Rd, Griston",
    "sg:city":"Thetford",
    "sg:classifiers":[
        {
            "category":"Shopping",
            "subcategory":"Pets & Pet Supplies",
            "type":"Retail Goods"
        }
    ],
    "sg:phone":"+44 1953 883131",
    "sg:postcode":"IP25 6PR",
    "sg:province":"Norfolk",
    "sg:tags":[
        "feed",
        "food",
        "animal"
    ],
    "wof:name":"Norfolk Pastures",
    "wof:placetype":"venue"
},
  "geometry": {"coordinates":[0.8621739745,52.5511512756],"type":"Point"}
}