{
  "type": "Feature",
  "properties": {
    "addr:full":"10 Church Fields Bordon Hampshire GU35 8PE",
    "addr:housenumber":"10",
    "addr:postcode":"gu35 8pe",
    "addr:street":"Church Fields",
    "iso:country":"GB",
    "sg:address":"10 Church Fields",
    "sg:city":"Bordon",
    "sg:classifiers":[
        {
            "category":"Professional",
            "subcategory":"Art Services",
            "type":"Services"
        }
    ],
    "sg:phone":"+44 1428 714984",
    "sg:postcode":"GU35 8PE",
    "sg:province":"Hampshire",
    "sg:tags":[
        "photographer"
    ],
    "wof:name":"Gillian Richmond Photography",
    "wof:placetype":"venue"
},
  "geometry": {"coordinates":[-0.830838,51.120045],"type":"Point"}
}