{
  "type": "Feature",
  "properties": {
    "addr:full":"Nicholls Road, Coytrahen Bridgend Bridgend CF32 0EP",
    "addr:postcode":"cf32 0ep",
    "addr:street":"Nicholls Road Coytrahen",
    "iso:country":"GB",
    "sg:address":"Nicholls Road, Coytrahen",
    "sg:city":"Bridgend",
    "sg:classifiers":[
        {
            "category":"Bars & Pubs",
            "type":"Food & Drink"
        }
    ],
    "sg:phone":"+44 1656 724680",
    "sg:postcode":"CF32 0EP",
    "sg:province":"Bridgend",
    "sg:tags":[
        "pubs",
        "inn"
    ],
    "wof:name":"A C Birbeck",
    "wof:placetype":"venue"
},
  "geometry": {"coordinates":[-3.602156,51.557758],"type":"Point"}
}