{
  "type": "Feature",
  "properties": {
    "addr:full":"3 George St, Wickham Newcastle Upon Tyne Durham NE16 4AS",
    "addr:housenumber":"3",
    "addr:postcode":"ne16 4as",
    "addr:street":"George St",
    "iso:country":"GB",
    "sg:address":"3 George St, Wickham",
    "sg:city":"Newcastle Upon Tyne",
    "sg:classifiers":[
        {
            "category":"Professional",
            "subcategory":"Secretarial Services",
            "type":"Services"
        }
    ],
    "sg:phone":"+44 191 488 8322",
    "sg:postcode":"NE16 4AS",
    "sg:province":"Durham",
    "wof:name":"D.J.S Complete Typing Service",
    "wof:placetype":"venue"
},
  "geometry": {"coordinates":[-1.685924,54.945969],"type":"Point"}
}