{
  "type": "Feature",
  "properties": {
    "iso:country":"GB",
    "sg:address":"6-8 Nunn Brook Rise",
    "sg:city":"Sutton-in-ashfield",
    "sg:classifiers":[
        {
            "category":"Manufacturing",
            "subcategory":"Signs",
            "type":"Manufacturing & Wholesale Goods"
        }
    ],
    "sg:phone":"+44 1623 555383",
    "sg:postcode":"NG17 2PD",
    "sg:province":"Nottinghamshire",
    "sg:tags":[
        "nameplate"
    ],
    "wof:name":"Positive Signs",
    "wof:placetype":"venue"
},
  "geometry": {"coordinates":[-1.306542,53.122021],"type":"Point"}
}