{
  "type": "Feature",
  "properties": {
    "addr:full":"59-61 Reevy Road Bradford West Yorkshire BD6 1TQ",
    "addr:housenumber":"59-61",
    "addr:postcode":"bd6 1tq",
    "addr:street":"Reevy Road",
    "iso:country":"GB",
    "sg:address":"59-61 Reevy Road",
    "sg:city":"Bradford",
    "sg:classifiers":[
        {
            "category":"Professional",
            "subcategory":"Printing & Photocopies",
            "type":"Services"
        }
    ],
    "sg:phone":"+44 1274 602862",
    "sg:postcode":"BD6 1TQ",
    "sg:province":"West Yorkshire",
    "sg:tags":[
        "computer",
        "tag",
        "label"
    ],
    "wof:name":"Universal Pricing Systems",
    "wof:placetype":"venue"
},
  "geometry": {"coordinates":[-1.780078,53.765251],"type":"Point"}
}