{
  "type": "Feature",
  "properties": {
    "addr:full":"5 Vyvyan Rd Bristol City of Bristol BS8 3AD",
    "addr:housenumber":"5",
    "addr:postcode":"bs8 3ad",
    "addr:street":"Vyvyan Rd",
    "iso:country":"GB",
    "sg:address":"5 Vyvyan Rd",
    "sg:city":"Bristol",
    "sg:classifiers":[
        {
            "category":"Professional",
            "type":"Services"
        }
    ],
    "sg:phone":"+44 117 973 8265",
    "sg:postcode":"BS8 3AD",
    "sg:province":"City of Bristol",
    "sg:tags":[
        "entertainer"
    ],
    "wof:name":"Robert Smith Agency",
    "wof:placetype":"venue"
},
  "geometry": {"coordinates":[-2.646159,51.45504],"type":"Point"}
}