{
  "type": "Feature",
  "properties": {
    "iso:country":"GB",
    "sg:address":"13 Hall Drive, Cropwell Bishop",
    "sg:city":"Nottingham",
    "sg:classifiers":[
        {
            "category":"Communications",
            "subcategory":"Film & Video Production",
            "type":"Services"
        }
    ],
    "sg:phone":"+44 115 989 3875",
    "sg:postcode":"NG12 3DT",
    "sg:province":"Nottinghamshire",
    "sg:tags":[
        "illustrator",
        "artist"
    ],
    "wof:name":"Mart'sart",
    "wof:placetype":"venue"
},
  "geometry": {"coordinates":[-0.9832909703,52.9153022766],"type":"Point"}
}