{
  "type": "Feature",
  "properties": {
    "iso:country":"GB",
    "sg:address":"37 Broomlands Street",
    "sg:city":"Paisley",
    "sg:classifiers":[
        {
            "category":"Bars & Pubs",
            "type":"Food & Drink"
        }
    ],
    "sg:phone":"+44 141 889 9244",
    "sg:postcode":"PA1 2NG",
    "sg:province":"Renfrewshire",
    "sg:tags":[
        "pubs",
        "inn"
    ],
    "wof:name":"The Crown Bar",
    "wof:placetype":"venue"
},
  "geometry": {"coordinates":[-4.4413070679,55.8429412842],"type":"Point"}
}