{
  "type": "Feature",
  "properties": {
    "addr:full":"55 Stanworth Street London Greater London SE1 3NY",
    "addr:housenumber":"55",
    "addr:postcode":"se1 3ny",
    "addr:street":"Stanworth Street",
    "iso:country":"GB",
    "sg:address":"55 Stanworth Street",
    "sg:city":"London",
    "sg:classifiers":[
        {
            "category":"Utilities",
            "subcategory":"Telephone",
            "type":"Services"
        }
    ],
    "sg:phone":"+44 20 7394 0420",
    "sg:postcode":"SE1 3NY",
    "sg:province":"Greater London",
    "sg:tags":[
        "telecommunication"
    ],
    "wof:name":"Linx Supplies Ltd.",
    "wof:placetype":"venue"
},
  "geometry": {"coordinates":[-0.074666,51.498451],"type":"Point"}
}