{
  "type": "Feature",
  "properties": {
    "addr:full":"55 St Marys Road Manchester Greater Manchester M40 3AR",
    "addr:housenumber":"55",
    "addr:postcode":"m40 3ar",
    "addr:street":"St Marys Road",
    "iso:country":"GB",
    "sg:address":"55 St Marys Road",
    "sg:city":"Manchester",
    "sg:classifiers":[
        {
            "category":"Autos & Motor Vehicles",
            "subcategory":"Fuel & Gas Station",
            "type":"Retail Goods"
        }
    ],
    "sg:phone":"+44 161 681 5116",
    "sg:postcode":"M40 3AR",
    "sg:province":"Greater Manchester",
    "sg:tags":[
        "petrol",
        "filling"
    ],
    "wof:name":"Murco Petroleum Ltd.",
    "wof:placetype":"venue"
},
  "geometry": {"coordinates":[-2.1689488888,53.5170783997],"type":"Point"}
}