{
  "type": "Feature",
  "properties": {
    "addr:full":"37 Broadhurst Gdns London Greater London NW6 3QT",
    "addr:housenumber":"37",
    "addr:postcode":"nw6 3qt",
    "addr:street":"Broadhurst Gdns",
    "iso:country":"GB",
    "sg:address":"37 Broadhurst Gdns",
    "sg:city":"London",
    "sg:classifiers":[
        {
            "category":"Professional",
            "subcategory":"Computer Services",
            "type":"Services"
        }
    ],
    "sg:postcode":"NW6 3QT",
    "sg:province":"Greater London",
    "sg:tags":[
        "system",
        "software"
    ],
    "wof:name":"Check Point Software Technologies (Uk) L",
    "wof:placetype":"venue"
},
  "geometry": {"coordinates":[-0.1816720068,51.546661377],"type":"Point"}
}