{
  "type": "Feature",
  "properties": {
    "iso:country":"GB",
    "sg:address":"14/6 Royston Mains Street, Granton",
    "sg:city":"Edinburgh",
    "sg:classifiers":[
        {
            "category":"Building & Trades",
            "subcategory":"Construction",
            "type":"Services"
        }
    ],
    "sg:postcode":"EH5 1LB",
    "sg:province":"City of Edinburgh",
    "sg:tags":[
        "decorator",
        "painter"
    ],
    "wof:name":"A McArthur Painter & Decorator",
    "wof:placetype":"venue"
},
  "geometry": {"coordinates":[-3.2368140221,55.9768333435],"type":"Point"}
}