{
  "type": "Feature",
  "properties": {
    "addr:full":"Clifton Cottage, Old Rickerscote Lane Stafford Staffordshire ST17 4HG",
    "addr:postcode":"st17 4hg",
    "addr:street":"Old Rickerscote Lane",
    "iso:country":"GB",
    "sg:address":"Clifton Cottage, Old Rickerscote Lane",
    "sg:city":"Stafford",
    "sg:classifiers":[
        {
            "category":"Professional",
            "subcategory":"Accounting & Tax Preparation",
            "type":"Services"
        }
    ],
    "sg:postcode":"ST17 4HG",
    "sg:province":"Staffordshire",
    "sg:tags":[
        "accountant"
    ],
    "wof:name":"Paul Beasley Services",
    "wof:placetype":"venue"
},
  "geometry": {"coordinates":[-2.1049799919,52.7810287476],"type":"Point"}
}