{
  "type": "Feature",
  "properties": {
    "iso:country":"GB",
    "sg:address":"Regimental Hq, 37 Signal Regiment, Kohima House",
    "sg:city":"Redditch",
    "sg:classifiers":[
        {
            "category":"Military Area",
            "subcategory":"Coast Guard Base",
            "type":"Public Place"
        },
        {
            "category":"Government",
            "subcategory":"Office",
            "type":"Public Place"
        }
    ],
    "sg:phone":"+44 1527 68989",
    "sg:postcode":"B98 9PJ",
    "sg:province":"Warwickshire",
    "sg:tags":[
        "force",
        "armed",
        "reserve"
    ],
    "wof:name":"Territorial Auxiliary & Volunteer Reserve Association",
    "wof:placetype":"venue"
},
  "geometry": {"coordinates":[-1.89773,52.312618],"type":"Point"}
}