{
  "type": "Feature",
  "properties": {
    "addr:full":"82 Pit Lane Widnes Cheshire WA8 9HW",
    "addr:housenumber":"82",
    "addr:postcode":"wa8 9hw",
    "addr:street":"Pit Lane",
    "iso:country":"GB",
    "sg:address":"82 Pit Lane",
    "sg:city":"Widnes",
    "sg:classifiers":[
        {
            "category":"Shopping",
            "subcategory":"News",
            "type":"Retail Goods"
        }
    ],
    "sg:phone":"+44 151 424 5627",
    "sg:postcode":"WA8 9HW",
    "sg:province":"Cheshire",
    "sg:tags":[
        "newsagent"
    ],
    "wof:name":"Valentine Jones",
    "wof:placetype":"venue"
},
  "geometry": {"coordinates":[-2.7323920727,53.3837165833],"type":"Point"}
}