{
  "type": "Feature",
  "properties": {
    "iso:country":"GB",
    "sg:address":"67 Elland Road, Churwell, Morley",
    "sg:city":"Leeds",
    "sg:classifiers":[
        {
            "category":"Health Services",
            "subcategory":"Clinic",
            "type":"Services"
        },
        {
            "category":"Organizations",
            "subcategory":"Non-profit Organization",
            "type":"Services"
        }
    ],
    "sg:phone":"+44 113 252 6561",
    "sg:postcode":"LS27 7QS",
    "sg:province":"West Yorkshire",
    "sg:tags":[
        "organisation",
        "voluntary",
        "private",
        "charity"
    ],
    "wof:name":"Northern Life Care Ltd.",
    "wof:placetype":"venue"
},
  "geometry": {"coordinates":[-1.590114,53.760719],"type":"Point"}
}