{
  "type": "Feature",
  "properties": {
    "addr:full":"29 Chequer Lane, Ash Canterbury Kent CT3 2AX",
    "addr:housenumber":"29",
    "addr:postcode":"ct3 2ax",
    "addr:street":"Chequer Lane",
    "iso:country":"GB",
    "sg:address":"29 Chequer Lane, Ash",
    "sg:city":"Canterbury",
    "sg:classifiers":[
        {
            "category":"Building & Trades",
            "subcategory":"Construction",
            "type":"Services"
        }
    ],
    "sg:phone":"+44 1304 812214",
    "sg:postcode":"CT3 2AX",
    "sg:province":"Kent",
    "sg:tags":[
        "heating",
        "contractor"
    ],
    "wof:name":"A Greenhalgh Plumbing & Heating",
    "wof:placetype":"venue"
},
  "geometry": {"coordinates":[1.2775520086,51.2808418274],"type":"Point"}
}