{
  "type": "Feature",
  "properties": {
    "iso:country":"GB",
    "sg:address":"29-31 Collegiate Crescent",
    "sg:city":"Sheffield",
    "sg:classifiers":[
        {
            "category":"Health Services",
            "subcategory":"Clinic",
            "type":"Services"
        }
    ],
    "sg:phone":"+44 114 267 0640",
    "sg:postcode":"S10 2BJ",
    "sg:province":"South Yorkshire",
    "sg:tags":[
        "abuse",
        "drug"
    ],
    "wof:name":"Phoenix House Family Centre",
    "wof:placetype":"venue"
},
  "geometry": {"coordinates":[-1.491384,53.374065],"type":"Point"}
}