{
  "type": "Feature",
  "properties": {
    "iso:country":"GB",
    "sg:address":"40 High Street",
    "sg:city":"Ross-on-wye",
    "sg:classifiers":[
        {
            "category":"Fast Food",
            "type":"Food & Drink"
        },
        {
            "category":"Cafe",
            "type":"Food & Drink"
        }
    ],
    "sg:postcode":"HR9 5HD",
    "sg:province":"Gloucestershire",
    "sg:tags":[
        "tea",
        "away",
        "room",
        "take"
    ],
    "wof:name":"The Antique Tea Shop",
    "wof:placetype":"venue"
},
  "geometry": {"coordinates":[-2.584499,51.91412],"type":"Point"}
}