{
  "type": "Feature",
  "properties": {
    "iso:country":"GB",
    "sg:address":"Castledore Road, Tywardreath",
    "sg:city":"Par",
    "sg:classifiers":[
        {
            "category":"Health Services",
            "subcategory":"Nursing And Care Facility",
            "type":"Services"
        }
    ],
    "sg:phone":"+44 1726 813588",
    "sg:postcode":"PL24 2TR",
    "sg:province":"Cornwall",
    "sg:tags":[
        "home"
    ],
    "wof:name":"Trecarrel Nursing Home",
    "wof:placetype":"venue"
},
  "geometry": {"coordinates":[-4.6680788994,50.3611183167],"type":"Point"}
}