{
  "type": "Feature",
  "properties": {
    "iso:country":"GB",
    "sg:address":"349 Delgatie Avenue",
    "sg:city":"Glenrothes",
    "sg:classifiers":[
        {
            "category":"Building & Trades",
            "subcategory":"Construction",
            "type":"Services"
        }
    ],
    "sg:phone":"+44 1592 771926",
    "sg:postcode":"KY7 4QD",
    "sg:province":"Fife",
    "sg:tags":[
        "decorator",
        "painter"
    ],
    "wof:name":"Dennis Sheach & Son",
    "wof:placetype":"venue"
},
  "geometry": {"coordinates":[-3.155873,56.182873],"type":"Point"}
}