{
  "type": "Feature",
  "properties": {
    "iso:country":"GB",
    "sg:address":"Aefen, Corwen Road, Pontybodkin",
    "sg:city":"Mold",
    "sg:classifiers":[
        {
            "category":"Utilities",
            "subcategory":"Fuel Oil & Lpg",
            "type":"Services"
        },
        {
            "category":"Professional",
            "subcategory":"Business Services",
            "type":"Services"
        }
    ],
    "sg:phone":"+44 1352 771391",
    "sg:postcode":"CH7 4TG",
    "sg:province":"Denbighshire",
    "sg:tags":[
        "export",
        "gas",
        "agent",
        "import"
    ],
    "wof:name":"Etonpark Logistics",
    "wof:placetype":"venue"
},
  "geometry": {"coordinates":[-3.089885,53.126804],"type":"Point"}
}