{
  "type": "Feature",
  "properties": {
    "iso:country":"GB",
    "sg:address":"P O Box 244",
    "sg:city":"Manchester",
    "sg:classifiers":[
        {
            "category":"Real Estate",
            "subcategory":"Real Estate Operator",
            "type":"Services"
        }
    ],
    "sg:phone":"+44 161 237 9226",
    "sg:postcode":"M60 1AJ",
    "sg:province":"Greater Manchester",
    "sg:tags":[
        "letting",
        "agent"
    ],
    "wof:name":"Manlets",
    "wof:placetype":"venue"
},
  "geometry": {"coordinates":[-2.24137,53.479599],"type":"Point"}
}