{
  "type": "Feature",
  "properties": {
    "addr:full":"Northbrook College, Littlehampton Road, Goring By Sea Worthing West Sussex BN12 6NU",
    "addr:postcode":"bn12 6nu",
    "addr:street":"Littlehampton Road",
    "iso:country":"GB",
    "sg:address":"Northbrook College, Littlehampton Road, Goring By Sea",
    "sg:city":"Worthing",
    "sg:classifiers":[
        {
            "category":"Arts & Performance",
            "subcategory":"Theater",
            "type":"Entertainment"
        }
    ],
    "sg:phone":"+44 1903 606162",
    "sg:postcode":"BN12 6NU",
    "sg:province":"West Sussex",
    "sg:tags":[
        "hall",
        "theatre",
        "concert"
    ],
    "wof:name":"Northbrook Theatre",
    "wof:placetype":"venue"
},
  "geometry": {"coordinates":[-0.4319700003,50.823059082],"type":"Point"}
}