{
  "type": "Feature",
  "properties": {
    "iso:country":"GB",
    "sg:address":"16 Stafford Street, Eccleshall",
    "sg:city":"Stafford",
    "sg:classifiers":[
        {
            "category":"Education",
            "subcategory":"School",
            "type":"Public Place"
        }
    ],
    "sg:postcode":"ST21 6BF",
    "sg:province":"Staffordshire",
    "sg:tags":[
        "local",
        "authority"
    ],
    "wof:name":"School of Garden Design Ltd.",
    "wof:placetype":"venue"
},
  "geometry": {"coordinates":[-2.251663,52.859135],"type":"Point"}
}