{
  "type": "Feature",
  "properties": {
    "iso:country":"GB",
    "sg:address":"Bank St",
    "sg:city":"Newquay",
    "sg:classifiers":[
        {
            "category":"Bus Charters",
            "type":"Transportation"
        }
    ],
    "sg:phone":"+44 1637 872432",
    "sg:postcode":"TR7 1AX",
    "sg:province":"Cornwall",
    "sg:tags":[
        "hire",
        "coach"
    ],
    "wof:name":"Wheal Britain Coaches",
    "wof:placetype":"venue"
},
  "geometry": {"coordinates":[-5.0838418007,50.4136276245],"type":"Point"}
}