{
  "type": "Feature",
  "properties": {
    "iso:country":"GB",
    "sg:address":"Unit 160, Lydney Industrial Estate, Harbour Road",
    "sg:city":"Lydney",
    "sg:classifiers":[
        {
            "category":"Manufacturing",
            "subcategory":"Chemicals & Compounds",
            "type":"Manufacturing & Wholesale Goods"
        }
    ],
    "sg:phone":"+44 1594 842688",
    "sg:postcode":"GL15 4EJ",
    "sg:province":"Gloucestershire",
    "sg:tags":[
        "pesticide"
    ],
    "wof:name":"Hy-Clene Chemicals Ltd.",
    "wof:placetype":"venue"
},
  "geometry": {"coordinates":[-2.517624,51.710091],"type":"Point"}
}