{
  "type": "Feature",
  "properties": {
    "addr:full":"580 Woodbridge Road Ipswich Suffolk IP4 4PH",
    "addr:housenumber":"580",
    "addr:postcode":"ip4 4ph",
    "addr:street":"Woodbridge Road",
    "iso:country":"GB",
    "sg:address":"580 Woodbridge Road",
    "sg:city":"Ipswich",
    "sg:classifiers":[
        {
            "category":"Autos & Motor Vehicles",
            "subcategory":"Auto Supplies",
            "type":"Retail Goods"
        }
    ],
    "sg:phone":"+44 1473 724431",
    "sg:postcode":"IP4 4PH",
    "sg:province":"Suffolk",
    "sg:tags":[
        "tyre"
    ],
    "wof:name":"Hi-Q Tyre Services",
    "wof:placetype":"venue"
},
  "geometry": {"coordinates":[1.18954,52.0606],"type":"Point"}
}