{
  "type": "Feature",
  "properties": {
    "iso:country":"GB",
    "sg:address":"Ty Wrth Y Glwyd, Trallong",
    "sg:city":"Brecon",
    "sg:classifiers":[
        {
            "category":"Professional",
            "subcategory":"Engineering",
            "type":"Services"
        }
    ],
    "sg:phone":"+44 1874 636682",
    "sg:postcode":"LD3 8HW",
    "sg:province":"Powys",
    "sg:tags":[
        "contractor",
        "electrical",
        "engineer"
    ],
    "wof:name":"M J & A M Roberts",
    "wof:placetype":"venue"
},
  "geometry": {"coordinates":[-3.505059,51.955608],"type":"Point"}
}