{
  "type": "Feature",
  "properties": {
    "addr:full":"Earlham Road Norwich Norfolk NR4 7TJ",
    "addr:postcode":"nr4 7tj",
    "addr:street":"Earlham Road Norwich Norfolk",
    "iso:country":"GB",
    "sg:address":"Earlham Road",
    "sg:city":"Norwich",
    "sg:classifiers":[
        {
            "category":"Education",
            "subcategory":"University",
            "type":"Public Place"
        },
        {
            "category":"Community Center",
            "type":"Public Place"
        },
        {
            "category":"Communications",
            "type":"Services"
        }
    ],
    "sg:phone":"+44 1603 456161",
    "sg:postcode":"NR4 7TJ",
    "sg:province":"Norfolk",
    "sg:tags":[
        "recreation",
        "centre",
        "medical",
        "school",
        "leisure",
        "broadcasting"
    ],
    "wof:name":"University of East Anglia",
    "wof:placetype":"venue"
},
  "geometry": {"coordinates":[1.257,52.629318],"type":"Point"}
}