{
  "type": "Feature",
  "properties": {
    "addr:full":"2 High Street Bordon Hampshire GU35 0AY",
    "addr:housenumber":"2",
    "addr:postcode":"gu35 0ay",
    "addr:street":"High Street",
    "iso:country":"GB",
    "sg:address":"2 High Street",
    "sg:city":"Bordon",
    "sg:classifiers":[
        {
            "category":"Shopping",
            "subcategory":"Computers & Home Electronics",
            "type":"Retail Goods"
        }
    ],
    "sg:phone":"+44 1420 474684",
    "sg:postcode":"GU35 0AY",
    "sg:province":"Hampshire",
    "sg:tags":[
        "equipment",
        "radio"
    ],
    "wof:name":"Breakers World",
    "wof:placetype":"venue"
},
  "geometry": {"coordinates":[-0.8635010123,51.1112976074],"type":"Point"}
}