{
  "type": "Feature",
  "properties": {
    "addr:full":"Venture House, Fifth Avenue Letchworth Hertfordshire SG6 2HW",
    "addr:postcode":"sg6 2hw",
    "addr:street":"Fifth Avenue Letchworth",
    "iso:country":"GB",
    "sg:address":"Venture House, Fifth Avenue",
    "sg:city":"Letchworth",
    "sg:classifiers":[
        {
            "category":"Professional",
            "subcategory":"Management & Consulting",
            "type":"Services"
        }
    ],
    "sg:phone":"+44 1462 483307",
    "sg:postcode":"SG6 2HW",
    "sg:province":"Hertfordshire",
    "sg:tags":[
        "consultant",
        "business"
    ],
    "wof:name":"Allied Strategy Ltd.",
    "wof:placetype":"venue"
},
  "geometry": {"coordinates":[-0.2057339996,51.9800338745],"type":"Point"}
}