{
  "type": "Feature",
  "properties": {
    "addr:full":"213-215 Park Rd Stanley Durham DH9 7QF",
    "addr:housenumber":"213-215",
    "addr:postcode":"dh9 7qf",
    "addr:street":"Park Rd",
    "iso:country":"GB",
    "sg:address":"213-215 Park Rd",
    "sg:city":"Stanley",
    "sg:classifiers":[
        {
            "category":"Food & Beverages",
            "subcategory":"Supermarket",
            "type":"Retail Goods"
        }
    ],
    "sg:phone":"+44 1207 233378",
    "sg:postcode":"DH9 7QF",
    "sg:province":"Durham",
    "wof:name":"Happy Shopper Everyday Supermarket",
    "wof:placetype":"venue"
},
  "geometry": {"coordinates":[-1.7062,54.861771],"type":"Point"}
}