{
  "type": "Feature",
  "properties": {
    "addr:full":"34-40 Soho Hill, Hockley Birmingham West Midlands B19 1AA",
    "addr:housenumber":"34-40",
    "addr:postcode":"b19 1aa",
    "addr:street":"Soho Hill Hockley",
    "iso:country":"GB",
    "sg:address":"34-40 Soho Hill, Hockley",
    "sg:city":"Birmingham",
    "sg:classifiers":[
        {
            "category":"Shopping",
            "subcategory":"Clothing, Apparel, & Fashions",
            "type":"Retail Goods"
        }
    ],
    "sg:postcode":"B19 1AA",
    "sg:province":"West Midlands",
    "sg:tags":[
        "clothing"
    ],
    "wof:name":"Associated Stockbuyers",
    "wof:placetype":"venue"
},
  "geometry": {"coordinates":[-1.916018,52.496296],"type":"Point"}
}