{
  "type": "Feature",
  "properties": {
    "addr:full":"31 Palace View Bromley Kent BR1 3EJ",
    "addr:housenumber":"31",
    "addr:postcode":"br1 3ej",
    "addr:street":"Palace View",
    "iso:country":"GB",
    "sg:address":"31 Palace View",
    "sg:city":"Bromley",
    "sg:classifiers":[
        {
            "category":"Building & Trades",
            "subcategory":"Cleaning & Sanitation",
            "type":"Services"
        }
    ],
    "sg:phone":"+44 20 8464 1194",
    "sg:postcode":"BR1 3EJ",
    "sg:province":"Kent",
    "sg:tags":[
        "cleaner",
        "window"
    ],
    "wof:name":"Lee Cleaning Co",
    "wof:placetype":"venue"
},
  "geometry": {"coordinates":[0.021308,51.400932],"type":"Point"}
}