{
  "type": "Feature",
  "properties": {
    "iso:country":"GB",
    "sg:address":"3 Greenhill, Wirksworth",
    "sg:city":"Matlock",
    "sg:classifiers":[
        {
            "category":"Real Estate",
            "subcategory":"Surveying",
            "type":"Services"
        }
    ],
    "sg:phone":"+44 1629 824170",
    "sg:postcode":"DE4 4EN",
    "sg:province":"Derbyshire",
    "sg:tags":[
        "surveyor",
        "quantity"
    ],
    "wof:name":"Roger Rawlinson Associates",
    "wof:placetype":"venue"
},
  "geometry": {"coordinates":[-1.548274,53.135616],"type":"Point"}
}