{
  "type": "Feature",
  "properties": {
    "addr:full":"45 St Augustine Road, Griffithstown Pontypool Monmouthshire NP4 5EZ",
    "addr:housenumber":"45",
    "addr:postcode":"np4 5ez",
    "addr:street":"St Augustine Road",
    "iso:country":"GB",
    "sg:address":"45 St Augustine Road, Griffithstown",
    "sg:city":"Pontypool",
    "sg:classifiers":[
        {
            "category":"Autos & Motor Vehicles",
            "subcategory":"Auto Supplies",
            "type":"Retail Goods"
        }
    ],
    "sg:phone":"+44 1495 763366",
    "sg:postcode":"NP4 5EZ",
    "sg:province":"Monmouthshire",
    "sg:tags":[
        "windscreen"
    ],
    "wof:name":"Autoglazers",
    "wof:placetype":"venue"
},
  "geometry": {"coordinates":[-3.0319509506,51.6836204529],"type":"Point"}
}