{
  "type": "Feature",
  "properties": {
    "addr:full":"Alma Road Suregery, Alma Rd Romsey Hampshire SO51 8ED",
    "addr:postcode":"so51 8ed",
    "addr:street":"Alma Road Suregery Alma Rd",
    "iso:country":"GB",
    "sg:address":"Alma Road Suregery, Alma Rd",
    "sg:city":"Romsey",
    "sg:classifiers":[
        {
            "category":"Health Services",
            "subcategory":"Doctor",
            "type":"Services"
        }
    ],
    "sg:phone":"+44 1795 511794",
    "sg:postcode":"SO51 8ED",
    "sg:province":"Hampshire",
    "sg:tags":[
        "practitioners"
    ],
    "wof:name":"Keith, I A",
    "wof:placetype":"venue"
},
  "geometry": {"coordinates":[-1.4941689968,50.9914512634],"type":"Point"}
}