{
  "type": "Feature",
  "properties": {
    "addr:full":"27 Brunel Gro, Perton Wolverhampton Shropshire WV6 7YD",
    "addr:housenumber":"27",
    "addr:postcode":"wv6 7yd",
    "addr:street":"Brunel Gro",
    "iso:country":"GB",
    "sg:address":"27 Brunel Gro, Perton",
    "sg:city":"Wolverhampton",
    "sg:classifiers":[
        {
            "category":"Professional",
            "subcategory":"Engineering",
            "type":"Services"
        }
    ],
    "sg:phone":"+44 1902 743673",
    "sg:postcode":"WV6 7YD",
    "sg:province":"Shropshire",
    "sg:tags":[
        "consulting",
        "engineer"
    ],
    "wof:name":"Halcyon Environmental",
    "wof:placetype":"venue"
},
  "geometry": {"coordinates":[-2.20637393,52.6026153564],"type":"Point"}
}