{
  "type": "Feature",
  "properties": {
    "iso:country":"GB",
    "sg:address":"66 Old Church Rd, Bell Grn",
    "sg:city":"Coventry",
    "sg:classifiers":[
        {
            "category":"Building & Trades",
            "subcategory":"Cleaning & Sanitation",
            "type":"Services"
        }
    ],
    "sg:postcode":"CV6 7BY",
    "sg:province":"Warwickshire",
    "sg:tags":[
        "dry",
        "control",
        "damp",
        "rot"
    ],
    "wof:name":"Johnson,G R,& Son",
    "wof:placetype":"venue"
},
  "geometry": {"coordinates":[-1.477379,52.437756],"type":"Point"}
}