{
  "type": "Feature",
  "properties": {
    "iso:country":"GB",
    "sg:address":"Unit 3, K D O Business Park",
    "sg:city":"Worcester",
    "sg:classifiers":[
        {
            "category":"Retail",
            "subcategory":"Auto Repair",
            "type":"Services"
        }
    ],
    "sg:phone":"+44 1299 896754",
    "sg:postcode":"WR6 6LR",
    "sg:province":"Herefordshire",
    "sg:tags":[
        "bodybuilder",
        "repairer"
    ],
    "wof:name":"Oakland Horse Boxes",
    "wof:placetype":"venue"
},
  "geometry": {"coordinates":[-2.32128,52.26897],"type":"Point"}
}