{
  "type": "Feature",
  "properties": {
    "addr:full":"8 River View Close Colyton Devon EX24 6PX",
    "addr:housenumber":"8",
    "addr:postcode":"ex24 6px",
    "addr:street":"River View Close",
    "iso:country":"GB",
    "sg:address":"8 River View Close",
    "sg:city":"Colyton",
    "sg:classifiers":[
        {
            "category":"Home & Garden",
            "subcategory":"Household Appliances",
            "type":"Retail Goods"
        },
        {
            "category":"Retail",
            "subcategory":"Repair Shop",
            "type":"Services"
        }
    ],
    "sg:phone":"+44 1297 553749",
    "sg:postcode":"EX24 6PX",
    "sg:province":"Devon",
    "sg:tags":[
        "refrigerator",
        "electrical",
        "servicing",
        "freezer"
    ],
    "wof:name":"Diamond Refrigeration",
    "wof:placetype":"venue"
},
  "geometry": {"coordinates":[-3.0682590008,50.7352409363],"type":"Point"}
}