{
  "type": "Feature",
  "properties": {
    "addr:full":"10 Acres Berry Hill, Taplow Maidenhead Berkshire SL6 0DA",
    "addr:housenumber":"10",
    "addr:postcode":"sl6 0da",
    "addr:street":"Acres",
    "iso:country":"GB",
    "sg:address":"10 Acres Berry Hill, Taplow",
    "sg:city":"Maidenhead",
    "sg:classifiers":[
        {
            "category":"Arena",
            "subcategory":"Sports Club",
            "type":"Entertainment"
        }
    ],
    "sg:phone":"+44 1628 632951",
    "sg:postcode":"SL6 0DA",
    "sg:province":"Berkshire",
    "wof:name":"Taplow Cricket Club",
    "wof:placetype":"venue"
},
  "geometry": {"coordinates":[-0.6871489882,51.532169342],"type":"Point"}
}