{
  "type": "Feature",
  "properties": {
    "addr:full":"Unit 8 Advance Business Park, Burdock Close, Hawkes Grn Cannock Staffordshire WS11 2GF",
    "addr:housenumber":"unit 8",
    "addr:postcode":"ws11 2gf",
    "addr:street":"Advance Business Park Burdock Close Hawkes Grn",
    "iso:country":"GB",
    "sg:address":"Unit 8 Advance Business Park, Burdock Close, Hawkes Grn",
    "sg:city":"Cannock",
    "sg:classifiers":[
        {
            "category":"Wholesale",
            "subcategory":"Construction Materials",
            "type":"Manufacturing & Wholesale Goods"
        }
    ],
    "sg:phone":"+44 1543 466666",
    "sg:postcode":"WS11 2GF",
    "sg:province":"Staffordshire",
    "sg:tags":[
        "cladding"
    ],
    "wof:name":"Cannock Fascia & Cladding Ltd.",
    "wof:placetype":"venue"
},
  "geometry": {"coordinates":[-2.033145,52.690952],"type":"Point"}
}