{
  "type": "Feature",
  "properties": {
    "addr:full":"162-166 Upper New Walk Leicester Leicestershire LE1 7QA",
    "addr:housenumber":"162-166",
    "addr:postcode":"le1 7qa",
    "addr:street":"Upper New Walk",
    "iso:country":"GB",
    "sg:address":"162-166 Upper New Walk",
    "sg:city":"Leicester",
    "sg:classifiers":[
        {
            "category":"Professional",
            "subcategory":"Management & Consulting",
            "type":"Services"
        },
        {
            "category":"Professional",
            "subcategory":"Computer Services",
            "type":"Services"
        }
    ],
    "sg:postcode":"LE1 7QA",
    "sg:province":"Leicestershire",
    "sg:tags":[
        "consultant",
        "business",
        "information"
    ],
    "wof:name":"BROCH HOLDINGS LTD",
    "wof:placetype":"venue"
},
  "geometry": {"coordinates":[-1.1201610565,52.6267089844],"type":"Point"}
}