{
  "type": "Feature",
  "properties": {
    "addr:full":"Po Box 6947 Clacton-on-sea Essex CO15 6ZE",
    "addr:housenumber":"po",
    "addr:postcode":"6947;co15 6ze",
    "addr:street":"Box",
    "iso:country":"GB",
    "sg:address":"Po Box 6947",
    "sg:city":"Clacton-on-sea",
    "sg:classifiers":[
        {
            "category":"Banks & Credit Unions",
            "subcategory":"Bank",
            "type":"Services"
        },
        {
            "category":"Banks & Credit Unions",
            "subcategory":"Financial Services",
            "type":"Services"
        }
    ],
    "sg:phone":"+44 1255 474047",
    "sg:postcode":"CO15 6ZE",
    "sg:province":"Essex",
    "sg:tags":[
        "adviser",
        "broker",
        "mortgage"
    ],
    "wof:name":"BURNDEN FINANCIAL SERVICES",
    "wof:placetype":"venue"
},
  "geometry": {"coordinates":[1.15327,51.801826],"type":"Point"}
}