{
  "type": "Feature",
  "properties": {
    "addr:full":"115 Middleton Blvd Nottingham Nottinghamshire NG8 1FW",
    "addr:housenumber":"115",
    "addr:postcode":"ng8 1fw",
    "addr:street":"Middleton Blvd",
    "iso:country":"GB",
    "sg:address":"115 Middleton Blvd",
    "sg:city":"Nottingham",
    "sg:classifiers":[
        {
            "category":"Health Services",
            "subcategory":"Optometrist",
            "type":"Services"
        }
    ],
    "sg:phone":"+44 115 928 2572",
    "sg:postcode":"NG8 1FW",
    "sg:province":"Nottinghamshire",
    "sg:tags":[
        "optician"
    ],
    "wof:name":"Duffy Optometrist",
    "wof:placetype":"venue"
},
  "geometry": {"coordinates":[-1.1931450367,52.9542732239],"type":"Point"}
}