{
  "type": "Feature",
  "properties": {
    "iso:country":"GB",
    "sg:address":"Unit 61c Lord Avenue",
    "sg:city":"Stockton-on-tees",
    "sg:classifiers":[
        {
            "category":"Professional",
            "type":"Services"
        }
    ],
    "sg:postcode":"TS17 9JX",
    "sg:province":"Durham",
    "sg:tags":[
        "control",
        "system"
    ],
    "wof:name":"A S Lingtech Ltd.",
    "wof:placetype":"venue"
},
  "geometry": {"coordinates":[-1.292034,54.524841],"type":"Point"}
}