{
  "type": "Feature",
  "properties": {
    "iso:country":"GB",
    "sg:address":"280/290 Cleveland Street",
    "sg:city":"Birkenhead",
    "sg:classifiers":[
        {
            "category":"Retail",
            "subcategory":"Auto Rental",
            "type":"Services"
        }
    ],
    "sg:postcode":"L41 4JN",
    "sg:province":"Merseyside",
    "sg:tags":[
        "car"
    ],
    "wof:name":"R. & H. Motor Co. Ltd",
    "wof:placetype":"venue"
},
  "geometry": {"coordinates":[-3.0318889618,53.3989257812],"type":"Point"}
}