{
  "type": "Feature",
  "properties": {
    "iso:country":"GB",
    "sg:address":"Rear Of, 22 Stannington Road",
    "sg:city":"Sheffield",
    "sg:classifiers":[
        {
            "category":"Retail",
            "subcategory":"Auto Repair",
            "type":"Services"
        }
    ],
    "sg:phone":"+44 114 234 3659",
    "sg:postcode":"S6 5FL",
    "sg:province":"South Yorkshire",
    "sg:tags":[
        "modification",
        "garage"
    ],
    "wof:name":"S & T Motors",
    "wof:placetype":"venue"
},
  "geometry": {"coordinates":[-1.51376,53.398411],"type":"Point"}
}