{
  "type": "Feature",
  "properties": {
    "addr:full":"106 High Street, Earls Colne Colchester Essex CO6 2QX",
    "addr:housenumber":"106",
    "addr:postcode":"co6 2qx",
    "addr:street":"High Street",
    "iso:country":"GB",
    "sg:address":"106 High Street, Earls Colne",
    "sg:city":"Colchester",
    "sg:classifiers":[
        {
            "category":"Health Services",
            "subcategory":"Optometrist",
            "type":"Services"
        }
    ],
    "sg:phone":"+44 1787 223213",
    "sg:postcode":"CO6 2QX",
    "sg:province":"Essex",
    "sg:tags":[
        "optician"
    ],
    "wof:name":"S Kleyn",
    "wof:placetype":"venue"
},
  "geometry": {"coordinates":[0.7033789754,51.9269638062],"type":"Point"}
}