{
  "type": "Feature",
  "properties": {
    "addr:full":"Sheephouse Wood, Stocksbridge Sheffield South Yorkshire S36 4GS",
    "addr:postcode":"s36 4gs",
    "iso:country":"GB",
    "sg:address":"Sheephouse Wood, Stocksbridge",
    "sg:city":"Sheffield",
    "sg:classifiers":[
        {
            "category":"Manufacturing",
            "subcategory":"Tools & Machinery",
            "type":"Manufacturing & Wholesale Goods"
        },
        {
            "category":"Home & Garden",
            "subcategory":"Hardware",
            "type":"Retail Goods"
        }
    ],
    "sg:phone":"+44 114 288 4207",
    "sg:postcode":"S36 4GS",
    "sg:province":"South Yorkshire",
    "sg:tags":[
        "product",
        "wire",
        "electrical",
        "manufacturer"
    ],
    "wof:name":"Bridon Wire Special Steels Division",
    "wof:placetype":"venue"
},
  "geometry": {"coordinates":[-1.59107,53.481972],"type":"Point"}
}