{
  "type": "Feature",
  "properties": {
    "addr:full":"Charnwood Road, Shepshed Loughborough Leicestershire LE12 9QE",
    "addr:postcode":"le12 9qe",
    "addr:street":"Charnwood Road",
    "iso:country":"GB",
    "sg:address":"Charnwood Road, Shepshed",
    "sg:city":"Loughborough",
    "sg:classifiers":[
        {
            "category":"Arena",
            "subcategory":"Sports Club",
            "type":"Entertainment"
        }
    ],
    "sg:phone":"+44 1509 502130",
    "sg:postcode":"LE12 9QE",
    "sg:province":"Leicestershire",
    "wof:name":"Shepshed Town Bowls Club",
    "wof:placetype":"venue"
},
  "geometry": {"coordinates":[-1.2913479805,52.7708358765],"type":"Point"}
}