{
  "type": "Feature",
  "properties": {
    "addr:full":"2 Homecroft Road, Goldthorpe Rotherham South Yorkshire S63 9DX",
    "addr:housenumber":"2",
    "addr:postcode":"s63 9dx",
    "addr:street":"Homecroft Road",
    "iso:country":"GB",
    "sg:address":"2 Homecroft Road, Goldthorpe",
    "sg:city":"Rotherham",
    "sg:classifiers":[
        {
            "category":"Fast Food",
            "type":"Food & Drink"
        }
    ],
    "sg:phone":"+44 1709 896321",
    "sg:postcode":"S63 9DX",
    "sg:province":"South Yorkshire",
    "sg:tags":[
        "away",
        "meal",
        "outlet",
        "take"
    ],
    "wof:name":"Hayley's Sandwich Shop",
    "wof:placetype":"venue"
},
  "geometry": {"coordinates":[-1.3073370457,53.5311965942],"type":"Point"}
}