{
  "type": "Feature",
  "properties": {
    "iso:country":"GB",
    "sg:address":"22 Hayston Avenue, Hakin",
    "sg:city":"Milford Haven",
    "sg:classifiers":[
        {
            "category":"Home & Garden",
            "subcategory":"Home Furnishings",
            "type":"Retail Goods"
        }
    ],
    "sg:phone":"+44 1646 694461",
    "sg:postcode":"SA73 3EB",
    "sg:province":"Pembrokeshire",
    "sg:tags":[
        "furnishers",
        "planner",
        "kitchen"
    ],
    "wof:name":"Zenith Installation",
    "wof:placetype":"venue"
},
  "geometry": {"coordinates":[-5.046378,51.7089],"type":"Point"}
}