{
  "type": "Feature",
  "properties": {
    "iso:country":"GB",
    "sg:address":"Mary Ward House, 5 Tavistock Place",
    "sg:city":"London",
    "sg:classifiers":[
        {
            "category":"Education",
            "subcategory":"Special Training",
            "type":"Public Place"
        }
    ],
    "sg:phone":"+44 20 7387 9681",
    "sg:postcode":"WC1H 9SN",
    "sg:province":"Greater London",
    "sg:tags":[
        "product",
        "centre"
    ],
    "wof:name":"National Institute for Social Work",
    "wof:placetype":"venue"
},
  "geometry": {"coordinates":[-0.13007,51.525471],"type":"Point"}
}