{
  "type": "Feature",
  "properties": {
    "addr:full":"Wylams Scrap Yard, Monkton Honiton Devon EX14 9QQ",
    "addr:postcode":"ex14 9qq",
    "iso:country":"GB",
    "sg:address":"Wylams Scrap Yard, Monkton",
    "sg:city":"Honiton",
    "sg:classifiers":[
        {
            "category":"Wholesale",
            "subcategory":"Scrap",
            "type":"Manufacturing & Wholesale Goods"
        }
    ],
    "sg:postcode":"EX14 9QQ",
    "sg:province":"Devon",
    "sg:tags":[
        "waste",
        "metal"
    ],
    "wof:name":"M D Corbin",
    "wof:placetype":"venue"
},
  "geometry": {"coordinates":[-3.152688,50.823734],"type":"Point"}
}