{
  "type": "Feature",
  "properties": {
    "iso:country":"GB",
    "sg:address":"Cider Mill Lane",
    "sg:city":"Chipping Campden",
    "sg:classifiers":[
        {
            "category":"Community Center",
            "subcategory":"Youth",
            "type":"Public Place"
        },
        {
            "category":"Community Center",
            "type":"Public Place"
        }
    ],
    "sg:phone":"+44 1386 841595",
    "sg:postcode":"GL55 6HU",
    "sg:province":"Gloucestershire",
    "sg:tags":[
        "recreation",
        "organisation",
        "leisure",
        "centre"
    ],
    "wof:name":"Chipping Campden Sports Centre",
    "wof:placetype":"venue"
},
  "geometry": {"coordinates":[-1.77642,52.05368],"type":"Point"}
}