{
  "type": "Feature",
  "properties": {
    "addr:full":"17a Beach Rd South Shields Tyne and Wear NE33 2QA",
    "addr:housenumber":"17a",
    "addr:postcode":"ne33 2qa",
    "addr:street":"Beach Rd",
    "iso:country":"GB",
    "sg:address":"17a Beach Rd",
    "sg:city":"South Shields",
    "sg:classifiers":[
        {
            "category":"Health Services",
            "subcategory":"Medical Lab",
            "type":"Services"
        }
    ],
    "sg:phone":"+44 191 456 0851",
    "sg:postcode":"NE33 2QA",
    "sg:province":"Tyne and Wear",
    "sg:tags":[
        "dental"
    ],
    "wof:name":"Dentures Direct",
    "wof:placetype":"venue"
},
  "geometry": {"coordinates":[-1.4288300276,54.9957618713],"type":"Point"}
}