{
  "type": "Feature",
  "properties": {
    "addr:full":"50 Leys Avenue Letchworth Hertfordshire SG6 3EQ",
    "addr:housenumber":"50",
    "addr:postcode":"sg6 3eq",
    "addr:street":"Leys Avenue Letchworth",
    "iso:country":"GB",
    "sg:address":"50 Leys Avenue",
    "sg:city":"Letchworth",
    "sg:classifiers":[
        {
            "category":"Professional",
            "subcategory":"Art Services",
            "type":"Services"
        }
    ],
    "sg:phone":"+44 1462 685790",
    "sg:postcode":"SG6 3EQ",
    "sg:province":"Hertfordshire",
    "sg:tags":[
        "framing"
    ],
    "wof:name":"Tuscany Fine Arts",
    "wof:placetype":"venue"
},
  "geometry": {"coordinates":[-0.22534,51.978733],"type":"Point"}
}