{
  "type": "Feature",
  "properties": {
    "addr:full":"Pleasant View, Station Rd, Elmesthorpe Leicester Leicestershire LE9 7SG",
    "addr:postcode":"le9 7sg",
    "addr:street":"Station Rd",
    "iso:country":"GB",
    "sg:address":"Pleasant View, Station Rd, Elmesthorpe",
    "sg:city":"Leicester",
    "sg:classifiers":[
        {
            "category":"Shopping",
            "subcategory":"Computers & Home Electronics",
            "type":"Retail Goods"
        }
    ],
    "sg:phone":"+44 116 254 6663",
    "sg:postcode":"LE9 7SG",
    "sg:province":"Leicestershire",
    "sg:tags":[
        "aerial",
        "television",
        "radio"
    ],
    "wof:name":"Leicester Aerial Installations",
    "wof:placetype":"venue"
},
  "geometry": {"coordinates":[-1.3090189695,52.559841156],"type":"Point"}
}