{
  "type": "Feature",
  "properties": {
    "iso:country":"GB",
    "sg:address":"7 The Windmills, St Marys Close",
    "sg:city":"Alton",
    "sg:classifiers":[
        {
            "category":"Professional",
            "subcategory":"Management & Consulting",
            "type":"Services"
        },
        {
            "category":"Communications",
            "type":"Services"
        }
    ],
    "sg:phone":"+44 1420 548100",
    "sg:postcode":"GU34 1EF",
    "sg:province":"Hampshire",
    "sg:tags":[
        "consultant",
        "telecommunication"
    ],
    "wof:name":"Intelcom Consultants Ltd.",
    "wof:placetype":"venue"
},
  "geometry": {"coordinates":[-0.9743289948,51.1475601196],"type":"Point"}
}