{
  "type": "Feature",
  "properties": {
    "iso:country":"GB",
    "sg:address":"11 Radcliffe St, Wolverton",
    "sg:city":"Milton Keynes",
    "sg:classifiers":[
        {
            "category":"Sports & Exercise",
            "subcategory":"Sports Center",
            "type":"Entertainment"
        }
    ],
    "sg:postcode":"MK12 5DQ",
    "sg:province":"Buckinghamshire",
    "sg:tags":[
        "shop",
        "good"
    ],
    "wof:name":"Personal Best Athletic Services Ltd",
    "wof:placetype":"venue"
},
  "geometry": {"coordinates":[-0.8096370101,52.061214447],"type":"Point"}
}