{
  "type": "Feature",
  "properties": {
    "iso:country":"GB",
    "sg:address":"Long Buckby Wharf, Long Buckby",
    "sg:city":"Northampton",
    "sg:classifiers":[
        {
            "category":"Bars & Pubs",
            "type":"Food & Drink"
        }
    ],
    "sg:phone":"+44 1327 844747",
    "sg:postcode":"NN6 7PW",
    "sg:province":"Northamptonshire",
    "sg:tags":[
        "pubs",
        "inn"
    ],
    "wof:name":"The New Inn",
    "wof:placetype":"venue"
},
  "geometry": {"coordinates":[-1.11095,52.28447],"type":"Point"}
}