{
  "type": "Feature",
  "properties": {
    "iso:country":"GB",
    "sg:address":"5 High Street",
    "sg:city":"Stamford",
    "sg:classifiers":[
        {
            "category":"Recreation",
            "type":"Entertainment"
        }
    ],
    "sg:phone":"+44 1780 752641",
    "sg:postcode":"PE9 2AL",
    "sg:province":"Cambridgeshire",
    "sg:tags":[
        "snooker",
        "billiards",
        "hall",
        "pool"
    ],
    "wof:name":"Stamford Snooker Club",
    "wof:placetype":"venue"
},
  "geometry": {"coordinates":[-0.4796600044,52.6520881653],"type":"Point"}
}