{
  "type": "Feature",
  "properties": {
    "addr:full":"1326 Greenford Road Greenford Greater London UB6 0HL",
    "addr:housenumber":"1326",
    "addr:postcode":"ub6 0hl",
    "addr:street":"Greenford Road",
    "iso:country":"GB",
    "sg:address":"1326 Greenford Road",
    "sg:city":"Greenford",
    "sg:classifiers":[
        {
            "category":"Retail",
            "subcategory":"Laundry & Dry Cleaning",
            "type":"Services"
        }
    ],
    "sg:phone":"+44 20 8864 0176",
    "sg:postcode":"UB6 0HL",
    "sg:province":"Greater London",
    "sg:tags":[
        "launderette"
    ],
    "wof:name":"Pearl Laundrette & Dry Cleaning",
    "wof:placetype":"venue"
},
  "geometry": {"coordinates":[-0.3390200138,51.5516929626],"type":"Point"}
}