{
  "type": "Feature",
  "properties": {
    "addr:full":"15 Thornhill Crescent London Greater London N1 1BL",
    "addr:housenumber":"15",
    "addr:postcode":"n1 1bl",
    "addr:street":"Thornhill Crescent",
    "iso:country":"GB",
    "sg:address":"15 Thornhill Crescent",
    "sg:city":"London",
    "sg:classifiers":[
        {
            "category":"Professional",
            "subcategory":"Art Services",
            "type":"Services"
        },
        {
            "category":"Building & Trades",
            "subcategory":"Construction",
            "type":"Services"
        }
    ],
    "sg:phone":"+44 20 7609 2438",
    "sg:postcode":"N1 1BL",
    "sg:province":"Greater London",
    "sg:tags":[
        "decorator",
        "painter"
    ],
    "wof:name":"Terry Liddon",
    "wof:placetype":"venue"
},
  "geometry": {"coordinates":[-0.1155389994,51.5415344238],"type":"Point"}
}