{
  "type": "Feature",
  "properties": {
    "iso:country":"GB",
    "sg:address":"34 Olympia, Town Centre",
    "sg:city":"Glasgow",
    "sg:classifiers":[
        {
            "category":"Home & Garden",
            "subcategory":"Household Appliances",
            "type":"Retail Goods"
        }
    ],
    "sg:phone":"+44 1355 261606",
    "sg:postcode":"G74 1PG",
    "sg:province":"South Lanarkshire",
    "sg:tags":[
        "electrical",
        "domestic"
    ],
    "wof:name":"ScottishPower Sound & Vision",
    "wof:placetype":"venue"
},
  "geometry": {"coordinates":[-4.181969,55.76614],"type":"Point"}
}