{
  "type": "Feature",
  "properties": {
    "addr:full":"Shern-well Building, Fen Farm, Newport Road Milton Keynes Bedfordshire MK17 8AA",
    "addr:postcode":"mk17 8aa",
    "addr:street":"Fen;Newport Road",
    "iso:country":"GB",
    "sg:address":"Shern-well Building, Fen Farm, Newport Road",
    "sg:city":"Milton Keynes",
    "sg:classifiers":[
        {
            "category":"Building & Trades",
            "subcategory":"Construction",
            "type":"Services"
        }
    ],
    "sg:phone":"+44 1908 585737",
    "sg:postcode":"MK17 8AA",
    "sg:province":"Bedfordshire",
    "sg:tags":[
        "fork",
        "lift",
        "truck"
    ],
    "wof:name":"Liftek Forktruck Hire",
    "wof:placetype":"venue"
},
  "geometry": {"coordinates":[-0.727749,52.005856],"type":"Point"}
}