{
  "type": "Feature",
  "properties": {
    "addr:full":"47 Nelson Avenue Downham Market Cambridgeshire PE38 9JL",
    "addr:housenumber":"47",
    "addr:postcode":"pe38 9jl",
    "addr:street":"Nelson Avenue",
    "iso:country":"GB",
    "sg:address":"47 Nelson Avenue",
    "sg:city":"Downham Market",
    "sg:classifiers":[
        {
            "category":"Building & Trades",
            "subcategory":"Construction",
            "type":"Services"
        }
    ],
    "sg:postcode":"PE38 9JL",
    "sg:province":"Cambridgeshire",
    "sg:tags":[
        "decorator",
        "painter"
    ],
    "wof:name":"David A Daw",
    "wof:placetype":"venue"
},
  "geometry": {"coordinates":[0.3712329865,52.6051826477],"type":"Point"}
}