{
  "type": "Feature",
  "properties": {
    "addr:full":"25 Bardsey Avenue, Blaenymaes Swansea Swansea SA5 5PR",
    "addr:housenumber":"25",
    "addr:postcode":"sa5 5pr",
    "addr:street":"Bardsey Avenue Blaenymaes",
    "iso:country":"GB",
    "sg:address":"25 Bardsey Avenue, Blaenymaes",
    "sg:city":"Swansea",
    "sg:classifiers":[
        {
            "category":"Bars & Pubs",
            "type":"Food & Drink"
        }
    ],
    "sg:phone":"+44 1792 581880",
    "sg:postcode":"SA5 5PR",
    "sg:province":"Swansea",
    "sg:tags":[
        "pubs",
        "inn"
    ],
    "wof:name":"A Smith",
    "wof:placetype":"venue"
},
  "geometry": {"coordinates":[-3.978271,51.657078],"type":"Point"}
}