{
  "type": "Feature",
  "properties": {
    "iso:country":"GB",
    "sg:address":"169 Drake Street",
    "sg:city":"Rochdale",
    "sg:classifiers":[
        {
            "category":"Health Services",
            "subcategory":"Health Practitioner",
            "type":"Services"
        }
    ],
    "sg:phone":"+44 1706 633169",
    "sg:postcode":"OL11 1EF",
    "sg:province":"Lancashire",
    "sg:tags":[
        "osteopath"
    ],
    "wof:name":"G Owen",
    "wof:placetype":"venue"
},
  "geometry": {"coordinates":[-2.1584839821,53.6121635437],"type":"Point"}
}