{
  "type": "Feature",
  "properties": {
    "iso:country":"GB",
    "sg:address":"175 West George Street",
    "sg:city":"Glasgow",
    "sg:classifiers":[
        {
            "category":"Real Estate",
            "subcategory":"Surveying",
            "type":"Services"
        }
    ],
    "sg:phone":"+44 141 221 4930",
    "sg:postcode":"G2 2LB",
    "sg:province":"Glasgow City",
    "sg:tags":[
        "building",
        "surveyor"
    ],
    "wof:name":"Ross Moore Ltd.",
    "wof:placetype":"venue"
},
  "geometry": {"coordinates":[-4.258253,55.862442],"type":"Point"}
}