{
  "type": "Feature",
  "properties": {
    "iso:country":"GB",
    "sg:address":"36 High Street, Dawley",
    "sg:city":"Telford",
    "sg:classifiers":[
        {
            "category":"Home & Garden",
            "subcategory":"Hardware",
            "type":"Retail Goods"
        }
    ],
    "sg:phone":"+44 1952 630248",
    "sg:postcode":"TF4 2EX",
    "sg:province":"Shropshire",
    "sg:tags":[
        "retailer",
        "diy"
    ],
    "wof:name":"Second To None",
    "wof:placetype":"venue"
},
  "geometry": {"coordinates":[-2.467744,52.664013],"type":"Point"}
}