{
  "type": "Feature",
  "properties": {
    "iso:country":"GB",
    "sg:address":"Rose Cottage, Oxenton",
    "sg:city":"Cheltenham",
    "sg:classifiers":[
        {
            "category":"Building & Trades",
            "subcategory":"Construction",
            "type":"Services"
        }
    ],
    "sg:phone":"+44 1242 672246",
    "sg:postcode":"GL52 9SE",
    "sg:province":"Gloucestershire",
    "sg:tags":[
        "builder"
    ],
    "wof:name":"R W Tibbles",
    "wof:placetype":"venue"
},
  "geometry": {"coordinates":[-2.0702650547,51.9797286987],"type":"Point"}
}