{
  "type": "Feature",
  "properties": {
    "addr:full":"Vale Road Weybridge Surrey KT13 9NR",
    "addr:postcode":"kt13 9nr",
    "addr:street":"Vale Road",
    "iso:country":"GB",
    "sg:address":"Vale Road",
    "sg:city":"Weybridge",
    "sg:classifiers":[
        {
            "category":"Building & Trades",
            "subcategory":"Construction",
            "type":"Services"
        }
    ],
    "sg:phone":"+44 1932 846878",
    "sg:postcode":"KT13 9NR",
    "sg:province":"Surrey",
    "sg:tags":[
        "glazier"
    ],
    "wof:name":"Oatlands Glass & Glazing Services Ltd.",
    "wof:placetype":"venue"
},
  "geometry": {"coordinates":[-0.4408490062,51.3759803772],"type":"Point"}
}