{
  "type": "Feature",
  "properties": {
    "addr:full":"Victoria Road, Off Bradford Road Dewsbury West Yorkshire WF13 2AB",
    "addr:postcode":"wf13 2ab",
    "addr:street":"Victoria Road Off Bradford Road",
    "iso:country":"GB",
    "sg:address":"Victoria Road, Off Bradford Road",
    "sg:city":"Dewsbury",
    "sg:classifiers":[
        {
            "category":"Manufacturing",
            "subcategory":"Furniture",
            "type":"Manufacturing & Wholesale Goods"
        }
    ],
    "sg:phone":"+44 1924 507050",
    "sg:postcode":"WF13 2AB",
    "sg:province":"West Yorkshire",
    "sg:tags":[
        "retail"
    ],
    "wof:name":"H S L (U K) Ltd.",
    "wof:placetype":"venue"
},
  "geometry": {"coordinates":[-1.6341990232,53.6959342957],"type":"Point"}
}