{
  "type": "Feature",
  "properties": {
    "addr:full":"110 Thurrock Lakeside Shop Cntr, West Thurrock Grays Essex RM20 2ZG",
    "addr:housenumber":"110",
    "addr:postcode":"rm20 2zg",
    "addr:street":"Thurrock;West",
    "iso:country":"GB",
    "sg:address":"110 Thurrock Lakeside Shop Cntr, West Thurrock",
    "sg:city":"Grays",
    "sg:classifiers":[
        {
            "category":"Shopping",
            "subcategory":"Gifts & Souvenirs",
            "type":"Retail Goods"
        }
    ],
    "sg:phone":"+44 1708 890916",
    "sg:postcode":"RM20 2ZG",
    "sg:province":"Essex",
    "sg:tags":[
        "shop"
    ],
    "wof:name":"The Disney Store Ltd.",
    "wof:placetype":"venue"
},
  "geometry": {"coordinates":[0.2837899923,51.4875984192],"type":"Point"}
}