{
  "type": "Feature",
  "properties": {
    "addr:full":"20 Salisbury Street Blandford Forum Dorset DT11 7AR",
    "addr:housenumber":"20",
    "addr:postcode":"dt11 7ar",
    "addr:street":"Salisbury Street",
    "iso:country":"GB",
    "sg:address":"20 Salisbury Street",
    "sg:city":"Blandford Forum",
    "sg:classifiers":[
        {
            "category":"Real Estate",
            "subcategory":"Real Estate Agent",
            "type":"Services"
        }
    ],
    "sg:phone":"+44 1258 452327",
    "sg:postcode":"DT11 7AR",
    "sg:province":"Dorset",
    "sg:website":"http://www.connells.co.uk",
    "wof:name":"Connell Estate Agents",
    "wof:placetype":"venue"
},
  "geometry": {"coordinates":[-2.1651399136,50.8566474915],"type":"Point"}
}