{
  "type": "Feature",
  "properties": {
    "addr:full":"9 New Heston Road, Heston Hounslow Greater London TW5 0NA",
    "addr:housenumber":"9",
    "addr:postcode":"tw5 0na",
    "addr:street":"New Heston Road",
    "iso:country":"GB",
    "sg:address":"9 New Heston Road, Heston",
    "sg:city":"Hounslow",
    "sg:classifiers":[
        {
            "category":"Shopping",
            "subcategory":"Department Store",
            "type":"Retail Goods"
        }
    ],
    "sg:phone":"+44 20 8577 2096",
    "sg:postcode":"TW5 0NA",
    "sg:province":"Greater London",
    "wof:name":"Heston Grocers",
    "wof:placetype":"venue"
},
  "geometry": {"coordinates":[-0.3740270138,51.4854774475],"type":"Point"}
}