{
  "type": "Feature",
  "properties": {
    "addr:full":"Clevedon Hall, Victoria Rd Clevedon Somerset BS21 7RQ",
    "addr:postcode":"bs21 7rq",
    "addr:street":"Victoria Rd",
    "iso:country":"GB",
    "sg:address":"Clevedon Hall, Victoria Rd",
    "sg:city":"Clevedon",
    "sg:classifiers":[
        {
            "category":"Communications",
            "type":"Services"
        }
    ],
    "sg:phone":"+44 1275 344333",
    "sg:postcode":"BS21 7RQ",
    "sg:province":"Somerset",
    "sg:tags":[
        "telecommunication"
    ],
    "wof:name":"Voice Solutions",
    "wof:placetype":"venue"
},
  "geometry": {"coordinates":[-2.8550388813,51.43592453],"type":"Point"}
}