{
  "type": "Feature",
  "properties": {
    "addr:full":"1 Mount Pleasant Crewkerne Dorset TA18 7AH",
    "addr:housenumber":"1",
    "addr:postcode":"ta18 7ah",
    "addr:street":"Mount Pleasant",
    "iso:country":"GB",
    "sg:address":"1 Mount Pleasant",
    "sg:city":"Crewkerne",
    "sg:classifiers":[
        {
            "category":"Freight",
            "type":"Transportation"
        }
    ],
    "sg:phone":"+44 1460 76421",
    "sg:postcode":"TA18 7AH",
    "sg:province":"Dorset",
    "sg:tags":[
        "haulage",
        "road"
    ],
    "wof:name":"Wills B R Mobile Welding & Steel Structure",
    "wof:placetype":"venue"
},
  "geometry": {"coordinates":[-2.7897570133,50.8858337402],"type":"Point"}
}