{
  "type": "Feature",
  "properties": {
    "addr:full":"1 King Street Dronfield Derbyshire S18 1RW",
    "addr:housenumber":"1",
    "addr:postcode":"s18 1rw",
    "addr:street":"King Street",
    "iso:country":"GB",
    "sg:address":"1 King Street",
    "sg:city":"Dronfield",
    "sg:classifiers":[
        {
            "category":"Building & Trades",
            "subcategory":"Construction",
            "type":"Services"
        }
    ],
    "sg:postcode":"S18 1RW",
    "sg:province":"Derbyshire",
    "sg:tags":[
        "contractor",
        "paving",
        "driveway"
    ],
    "wof:name":"David Bacon",
    "wof:placetype":"venue"
},
  "geometry": {"coordinates":[-1.4694240093,53.3047294617],"type":"Point"}
}