{
  "type": "Feature",
  "properties": {
    "addr:full":"73 Derby Road, Long Eaton Nottingham Derbyshire NG10 1LU",
    "addr:housenumber":"73",
    "addr:postcode":"ng10 1lu",
    "addr:street":"Derby Road",
    "iso:country":"GB",
    "sg:address":"73 Derby Road, Long Eaton",
    "sg:city":"Nottingham",
    "sg:classifiers":[
        {
            "category":"Shopping",
            "subcategory":"Pets & Pet Supplies",
            "type":"Retail Goods"
        }
    ],
    "sg:postcode":"NG10 1LU",
    "sg:province":"Derbyshire",
    "sg:tags":[
        "shop"
    ],
    "wof:name":"Pets Choice",
    "wof:placetype":"venue"
},
  "geometry": {"coordinates":[-1.273966,52.900009],"type":"Point"}
}