{
  "type": "Feature",
  "properties": {
    "addr:full":"31 Castle Street Banff Aberdeenshire AB45 1DH",
    "addr:housenumber":"31",
    "addr:postcode":"ab45 1dh",
    "addr:street":"Castle Street",
    "iso:country":"GB",
    "sg:address":"31 Castle Street",
    "sg:city":"Banff",
    "sg:classifiers":[
        {
            "category":"Shopping",
            "type":"Retail Goods"
        }
    ],
    "sg:postcode":"AB45 1DH",
    "sg:province":"Aberdeenshire",
    "sg:tags":[
        "part",
        "accessory"
    ],
    "wof:name":"Spin Off Car Spares",
    "wof:placetype":"venue"
},
  "geometry": {"coordinates":[-2.523751,57.666744],"type":"Point"}
}