{
  "type": "Feature",
  "properties": {
    "addr:full":"Canal Street, Longport Stoke-on-trent Staffordshire ST6 4LU",
    "addr:postcode":"staffordshire st6 4lu",
    "addr:street":"Canal Street",
    "iso:country":"GB",
    "sg:address":"Canal Street, Longport",
    "sg:city":"Stoke-on-trent",
    "sg:classifiers":[
        {
            "category":"Organizations",
            "subcategory":"Non-profit Organization",
            "type":"Services"
        }
    ],
    "sg:phone":"+44 1782 811722",
    "sg:postcode":"ST6 4LU",
    "sg:province":"Staffordshire",
    "sg:tags":[
        "organisation",
        "voluntary",
        "charity"
    ],
    "wof:name":"Westport Wildlife Rescue",
    "wof:placetype":"venue"
},
  "geometry": {"coordinates":[-2.214574,53.045006],"type":"Point"}
}