{
  "type": "Feature",
  "properties": {
    "addr:full":"425 Ash Bank Road, Werrington Stoke-on-trent Staffordshire ST9 0DU",
    "addr:housenumber":"425",
    "addr:postcode":"staffordshire st9 0du",
    "addr:street":"Ash Bank Road",
    "iso:country":"GB",
    "sg:address":"425 Ash Bank Road, Werrington",
    "sg:city":"Stoke-on-trent",
    "sg:classifiers":[
        {
            "category":"Personal",
            "subcategory":"Beauty Salon",
            "type":"Services"
        }
    ],
    "sg:postcode":"ST9 0DU",
    "sg:province":"Staffordshire",
    "sg:tags":[
        "unisex",
        "hairdresser"
    ],
    "wof:name":"Exclusive Hair Studio",
    "wof:placetype":"venue"
},
  "geometry": {"coordinates":[-2.0875020027,53.0247306824],"type":"Point"}
}