{
  "type": "Feature",
  "properties": {
    "iso:country":"GB",
    "sg:address":"161 Whitfield Street",
    "sg:city":"London",
    "sg:classifiers":[
        {
            "category":"Real Estate",
            "subcategory":"Architect",
            "type":"Services"
        }
    ],
    "sg:phone":"+44 20 7380 1199",
    "sg:postcode":"W1T 5ER",
    "sg:province":"Greater London",
    "wof:name":"Mark Guard Ltd.",
    "wof:placetype":"venue"
},
  "geometry": {"coordinates":[-0.139286,51.524101],"type":"Point"}
}