{
  "type": "Feature",
  "properties": {
    "addr:full":"1-5 Station Road North Egham Surrey TW20 9LD",
    "addr:housenumber":"1-5",
    "addr:postcode":"tw20 9ld",
    "addr:street":"Station Road North Egham",
    "iso:country":"GB",
    "sg:address":"1-5 Station Road North",
    "sg:city":"Egham",
    "sg:classifiers":[
        {
            "category":"Food & Beverages",
            "subcategory":"Supermarket",
            "type":"Retail Goods"
        }
    ],
    "sg:phone":"+44 1784 439100",
    "sg:postcode":"TW20 9LD",
    "sg:province":"Surrey",
    "wof:name":"Budgens",
    "wof:placetype":"venue"
},
  "geometry": {"coordinates":[-0.5485870242,51.4315490723],"type":"Point"}
}