{
  "type": "Feature",
  "properties": {
    "addr:full":"Leeds Road, Pannal Harrogate North Yorkshire HG3 1ER",
    "addr:postcode":"hg3 1er",
    "addr:street":"Leeds Road",
    "iso:country":"GB",
    "sg:address":"Leeds Road, Pannal",
    "sg:city":"Harrogate",
    "sg:classifiers":[
        {
            "category":"Autos & Motor Vehicles",
            "subcategory":"Fuel & Gas Station",
            "type":"Retail Goods"
        }
    ],
    "sg:phone":"+44 1423 873269",
    "sg:postcode":"HG3 1ER",
    "sg:province":"North Yorkshire",
    "sg:tags":[
        "hr",
        "petrol"
    ],
    "wof:name":"Eagle Three Filling Station",
    "wof:placetype":"venue"
},
  "geometry": {"coordinates":[-1.529371,53.960205],"type":"Point"}
}