{
  "type": "Feature",
  "properties": {
    "addr:full":"47 Broad Street Ross-on-wye Gloucestershire HR9 7DY",
    "addr:housenumber":"47",
    "addr:postcode":"hr9 7dy",
    "addr:street":"Broad Street",
    "iso:country":"GB",
    "sg:address":"47 Broad Street",
    "sg:city":"Ross-on-wye",
    "sg:classifiers":[
        {
            "category":"Food & Beverages",
            "subcategory":"Specialty",
            "type":"Retail Goods"
        }
    ],
    "sg:phone":"+44 1989 566271",
    "sg:postcode":"HR9 7DY",
    "sg:province":"Gloucestershire",
    "sg:tags":[
        "vegetarian"
    ],
    "wof:name":"Oat Cuisine",
    "wof:placetype":"venue"
},
  "geometry": {"coordinates":[-2.582543,51.915154],"type":"Point"}
}