{
  "type": "Feature",
  "properties": {
    "addr:full":"103 Preston Street, Kirkham Preston Lancashire PR4 2XA",
    "addr:housenumber":"103",
    "addr:postcode":"pr4 2xa",
    "addr:street":"Preston Street",
    "iso:country":"GB",
    "sg:address":"103 Preston Street, Kirkham",
    "sg:city":"Preston",
    "sg:classifiers":[
        {
            "category":"Building & Trades",
            "subcategory":"Construction",
            "type":"Services"
        }
    ],
    "sg:phone":"+44 1772 687333",
    "sg:postcode":"PR4 2XA",
    "sg:province":"Lancashire",
    "sg:tags":[
        "joinery",
        "joiner",
        "carpenter",
        "carpentry"
    ],
    "wof:name":"Bob Moss",
    "wof:placetype":"venue"
},
  "geometry": {"coordinates":[-2.8666810989,53.7817993164],"type":"Point"}
}