{
  "type": "Feature",
  "properties": {
    "iso:country":"GB",
    "sg:address":"Lidgetts Close, Scawby",
    "sg:city":"Brigg",
    "sg:classifiers":[
        {
            "category":"Military Area",
            "subcategory":"Air Force Base",
            "type":"Public Place"
        }
    ],
    "sg:postcode":"DN20 9AW",
    "sg:province":"Lincolnshire",
    "sg:tags":[
        "taxi",
        "hire",
        "private"
    ],
    "wof:name":"F & A Proctor",
    "wof:placetype":"venue"
},
  "geometry": {"coordinates":[-0.539929,53.535534],"type":"Point"}
}