{
  "type": "Feature",
  "properties": {
    "addr:full":"Albion Heat Treatment Building, Kingsfield Road Coventry West Midlands CV1 4NG",
    "addr:postcode":"cv1 4ng",
    "addr:street":"Kingsfield Road",
    "iso:country":"GB",
    "sg:address":"Albion Heat Treatment Building, Kingsfield Road",
    "sg:city":"Coventry",
    "sg:classifiers":[
        {
            "category":"Professional",
            "type":"Services"
        }
    ],
    "sg:phone":"+44 24 7655 0882",
    "sg:postcode":"CV1 4NG",
    "sg:province":"West Midlands",
    "sg:tags":[
        "specialist",
        "coating"
    ],
    "wof:name":"Plasma Coated Services Ltd.",
    "wof:placetype":"venue"
},
  "geometry": {"coordinates":[-1.507768,52.406986],"type":"Point"}
}