{
  "type": "Feature",
  "properties": {
    "iso:country":"GB",
    "sg:address":"A371 Next To Castle Cary Station",
    "sg:city":"Castle Cary",
    "sg:classifiers":[
        {
            "category":"Home & Garden",
            "subcategory":"Building Materials",
            "type":"Retail Goods"
        }
    ],
    "sg:phone":"+44 1963 351731",
    "sg:postcode":"BA7 7PE",
    "sg:province":"Somerset",
    "sg:tags":[
        "ready",
        "mixed",
        "concrete"
    ],
    "wof:name":"Evercreech Building Supplies Ltd.",
    "wof:placetype":"venue"
},
  "geometry": {"coordinates":[-2.507074,51.090046],"type":"Point"}
}