{
  "type": "Feature",
  "properties": {
    "iso:country":"GB",
    "sg:address":"18 Purbeck Road",
    "sg:city":"Bournemouth",
    "sg:classifiers":[
        {
            "category":"Travel",
            "subcategory":"Hotels & Motels",
            "type":"Entertainment"
        }
    ],
    "sg:phone":"+44 1202 292865",
    "sg:postcode":"BH2 5EF",
    "sg:province":"Dorset",
    "wof:name":"Aaron House",
    "wof:placetype":"venue"
},
  "geometry": {"coordinates":[-1.885322,50.718559],"type":"Point"}
}