{
  "type": "Feature",
  "properties": {
    "iso:country":"GB",
    "sg:address":"4 Quay Walls",
    "sg:city":"Berwick-upon-tweed",
    "sg:classifiers":[
        {
            "category":"Professional",
            "subcategory":"Lawyer & Legal Services",
            "type":"Services"
        }
    ],
    "sg:phone":"+44 1289 306724",
    "sg:postcode":"TD15 1HD",
    "sg:province":"Northumberland",
    "sg:tags":[
        "solicitor"
    ],
    "sg:website":"http://www.sm-e.co.uk",
    "wof:name":"Sanderson McCreath & Edney",
    "wof:placetype":"venue"
},
  "geometry": {"coordinates":[-2.004362,55.767578],"type":"Point"}
}