{
  "type": "Feature",
  "properties": {
    "iso:country":"GB",
    "sg:address":"Thimbleby Hill, Stanhope",
    "sg:city":"Bishop Auckland",
    "sg:classifiers":[
        {
            "category":"Farming",
            "subcategory":"Farm",
            "type":"Manufacturing & Wholesale Goods"
        }
    ],
    "sg:postcode":"DL13 2PN",
    "sg:province":"Durham",
    "sg:tags":[
        "mixed",
        "crop"
    ],
    "wof:name":"B T Bell",
    "wof:placetype":"venue"
},
  "geometry": {"coordinates":[-2.0055539608,54.746925354],"type":"Point"}
}