{
  "type": "Feature",
  "properties": {
    "iso:country":"GB",
    "sg:address":"73 Coronation Road, Southville",
    "sg:city":"Bristol",
    "sg:classifiers":[
        {
            "category":"Professional",
            "subcategory":"Computer Services",
            "type":"Services"
        }
    ],
    "sg:postcode":"BS3 1AT",
    "sg:province":"City of Bristol",
    "sg:tags":[
        "system",
        "software"
    ],
    "wof:name":"Subplot Ltd",
    "wof:placetype":"venue"
},
  "geometry": {"coordinates":[-2.600322,51.445564],"type":"Point"}
}