{
  "type": "Feature",
  "properties": {
    "addr:full":"Enterprise House, Ocean Village Southampton Hampshire SO14 3XB",
    "addr:postcode":"so14 3xb",
    "addr:street":"Ocean Village",
    "iso:country":"GB",
    "sg:address":"Enterprise House, Ocean Village",
    "sg:city":"Southampton",
    "sg:classifiers":[
        {
            "category":"Professional",
            "subcategory":"Business Services",
            "type":"Services"
        }
    ],
    "sg:phone":"+44 23 8033 1666",
    "sg:postcode":"SO14 3XB",
    "sg:province":"Hampshire",
    "sg:tags":[
        "accomodation"
    ],
    "wof:name":"First Base Southampton Ltd.",
    "wof:placetype":"venue"
},
  "geometry": {"coordinates":[-1.392996,50.896118],"type":"Point"}
}