{
  "type": "Feature",
  "properties": {
    "iso:country":"GB",
    "sg:address":"9 Woodview",
    "sg:city":"Grays",
    "sg:classifiers":[
        {
            "category":"Building & Trades",
            "subcategory":"Construction",
            "type":"Services"
        }
    ],
    "sg:phone":"+44 1375 393839",
    "sg:postcode":"RM16 2WJ",
    "sg:province":"Essex",
    "sg:tags":[
        "roofing"
    ],
    "wof:name":"Roofing Contracting",
    "wof:placetype":"venue"
},
  "geometry": {"coordinates":[0.345582,51.487965],"type":"Point"}
}