{
  "type": "Feature",
  "properties": {
    "addr:full":"Unit 5, Cluster Industrial Estate, Rodney Road Southsea Hampshire PO4 8ST",
    "addr:housenumber":"unit 5",
    "addr:postcode":"po4 8st",
    "addr:street":"Cluster Industrial;Rodney Road",
    "iso:country":"GB",
    "sg:address":"Unit 5, Cluster Industrial Estate, Rodney Road",
    "sg:city":"Southsea",
    "sg:classifiers":[
        {
            "category":"Bars & Pubs",
            "type":"Food & Drink"
        },
        {
            "category":"Building & Trades",
            "subcategory":"Construction",
            "type":"Services"
        }
    ],
    "sg:phone":"+44 23 9229 8600",
    "sg:postcode":"PO4 8ST",
    "sg:province":"Hampshire",
    "sg:tags":[
        "house",
        "glazier",
        "public",
        "activity"
    ],
    "wof:name":"Colin Paul & Ken Ltd",
    "wof:placetype":"venue"
},
  "geometry": {"coordinates":[-1.06358,50.798759],"type":"Point"}
}