{
  "type": "Feature",
  "properties": {
    "addr:full":"47 Market Place Uttoxeter Derbyshire ST14 8HF",
    "addr:housenumber":"47",
    "addr:postcode":"st14 8hf",
    "addr:street":"Market Place",
    "iso:country":"GB",
    "sg:address":"47 Market Place",
    "sg:city":"Uttoxeter",
    "sg:classifiers":[
        {
            "category":"Professional",
            "type":"Services"
        }
    ],
    "sg:phone":"+44 1889 567788",
    "sg:postcode":"ST14 8HF",
    "sg:province":"Derbyshire",
    "sg:tags":[
        "notary",
        "public"
    ],
    "wof:name":"A P H Peach & Co",
    "wof:placetype":"venue"
},
  "geometry": {"coordinates":[-1.864714,52.898205],"type":"Point"}
}