{
  "type": "Feature",
  "properties": {
    "iso:country":"GB",
    "sg:address":"9 Westbury Close, Elmwood Padgate",
    "sg:city":"Warrington",
    "sg:classifiers":[
        {
            "category":"Professional",
            "subcategory":"Engineering",
            "type":"Services"
        }
    ],
    "sg:phone":"+44 1663 747678",
    "sg:postcode":"WA1 4JU",
    "sg:province":"Cheshire",
    "sg:tags":[
        "engineer"
    ],
    "wof:name":"Control Specialists Ltd.",
    "wof:placetype":"venue"
},
  "geometry": {"coordinates":[-2.55319,53.404831],"type":"Point"}
}