{
  "type": "Feature",
  "properties": {
    "addr:full":"3 Glebe Cottages, Church End, Sheriff Hutton York North Yorkshire YO60 6SY",
    "addr:housenumber":"3",
    "addr:postcode":"yo60 6sy",
    "addr:street":"Glebe;Church End",
    "iso:country":"GB",
    "sg:address":"3 Glebe Cottages, Church End, Sheriff Hutton",
    "sg:city":"York",
    "sg:classifiers":[
        {
            "category":"Social Services",
            "subcategory":"Job Training",
            "type":"Services"
        }
    ],
    "sg:phone":"+44 1347 878779",
    "sg:postcode":"YO60 6SY",
    "sg:province":"North Yorkshire",
    "sg:tags":[
        "translator",
        "interpreter"
    ],
    "wof:name":"Ryedale Language Services",
    "wof:placetype":"venue"
},
  "geometry": {"coordinates":[-1.0078910589,54.0880355835],"type":"Point"}
}