{
  "type": "Feature",
  "properties": {
    "addr:full":"49 High Street Billingshurst West Sussex RH14 9PP",
    "addr:housenumber":"49",
    "addr:postcode":"rh14 9pp",
    "addr:street":"High Street",
    "iso:country":"GB",
    "sg:address":"49 High Street",
    "sg:city":"Billingshurst",
    "sg:classifiers":[
        {
            "category":"Shopping",
            "subcategory":"Pets & Pet Supplies",
            "type":"Retail Goods"
        }
    ],
    "sg:phone":"+44 1403 784123",
    "sg:postcode":"RH14 9PP",
    "sg:province":"West Sussex",
    "wof:name":"Petstop",
    "wof:placetype":"venue"
},
  "geometry": {"coordinates":[-0.451097995,51.0232620239],"type":"Point"}
}