{
  "type": "Feature",
  "properties": {
    "addr:full":"29 Shrewsbury Rd, Edgmond Newport Shropshire TF10 8HU",
    "addr:housenumber":"29",
    "addr:postcode":"tf10 8hu",
    "addr:street":"Shrewsbury Rd",
    "iso:country":"GB",
    "sg:address":"29 Shrewsbury Rd, Edgmond",
    "sg:city":"Newport",
    "sg:classifiers":[
        {
            "category":"Bars & Pubs",
            "type":"Food & Drink"
        }
    ],
    "sg:phone":"+44 1952 810421",
    "sg:postcode":"TF10 8HU",
    "sg:province":"Shropshire",
    "sg:tags":[
        "pubs",
        "inn"
    ],
    "wof:name":"The Lamb Inn",
    "wof:placetype":"venue"
},
  "geometry": {"coordinates":[-2.412250042,52.7771224976],"type":"Point"}
}