{
  "type": "Feature",
  "properties": {
    "iso:country":"GB",
    "sg:address":"19a Langham Place",
    "sg:city":"Egham",
    "sg:classifiers":[
        {
            "category":"Shopping",
            "subcategory":"Gifts & Souvenirs",
            "type":"Retail Goods"
        }
    ],
    "sg:postcode":"TW20 9EB",
    "sg:province":"Surrey",
    "sg:tags":[
        "ducting"
    ],
    "wof:name":"Fresh Vent Services",
    "wof:placetype":"venue"
},
  "geometry": {"coordinates":[-0.5529260039,51.4326057434],"type":"Point"}
}