{
  "type": "Feature",
  "properties": {
    "iso:country":"GB",
    "sg:address":"Exeter Laboratory, Bridge Road, Countess Weir",
    "sg:city":"Exeter",
    "sg:classifiers":[
        {
            "category":"Professional",
            "subcategory":"Testing Lab",
            "type":"Services"
        },
        {
            "category":"Health Services",
            "subcategory":"Medical Lab",
            "type":"Services"
        }
    ],
    "sg:phone":"+44 1392 434136",
    "sg:postcode":"EX2 7AA",
    "sg:province":"Devon",
    "sg:tags":[
        "laboratory",
        "activity",
        "based",
        "research"
    ],
    "wof:name":"South West Water Ltd",
    "wof:placetype":"venue"
},
  "geometry": {"coordinates":[-3.49558,50.697338],"type":"Point"}
}