{
  "type": "Feature",
  "properties": {
    "iso:country":"GB",
    "sg:address":"108 High Street",
    "sg:city":"Godstone",
    "sg:classifiers":[
        {
            "category":"Personal",
            "subcategory":"Beauty Salon",
            "type":"Services"
        }
    ],
    "sg:phone":"+44 1883 742208",
    "sg:postcode":"RH9 8DR",
    "sg:province":"Surrey",
    "sg:tags":[
        "unisex",
        "hairdresser"
    ],
    "wof:name":"Rapunzel's Hair Salon",
    "wof:placetype":"venue"
},
  "geometry": {"coordinates":[-0.0670439973,51.2480201721],"type":"Point"}
}