{
  "type": "Feature",
  "properties": {
    "addr:full":"7 Brook Hey, Parkgate Wirral Cheshire CH64 6TH",
    "addr:housenumber":"7",
    "addr:postcode":"ch64 6th",
    "addr:street":"Brook Hey Parkgate",
    "iso:country":"GB",
    "sg:address":"7 Brook Hey, Parkgate",
    "sg:city":"Wirral",
    "sg:classifiers":[
        {
            "category":"Professional",
            "subcategory":"Business Services",
            "type":"Services"
        },
        {
            "category":"Recreation",
            "subcategory":"Playground",
            "type":"Entertainment"
        }
    ],
    "sg:phone":"+44 151 336 6545",
    "sg:postcode":"CH64 6TH",
    "sg:province":"Cheshire",
    "sg:tags":[
        "hospitality",
        "corporate"
    ],
    "wof:name":"Concept Corporate Events",
    "wof:placetype":"venue"
},
  "geometry": {"coordinates":[-3.074782,53.301132],"type":"Point"}
}