{
  "type": "Feature",
  "properties": {
    "iso:country":"GB",
    "sg:address":"110 Coronation Road",
    "sg:city":"Wednesbury",
    "sg:classifiers":[
        {
            "category":"Shopping",
            "subcategory":"News",
            "type":"Retail Goods"
        }
    ],
    "sg:phone":"+44 121 556 2665",
    "sg:postcode":"WS10 0TJ",
    "sg:province":"West Midlands",
    "sg:tags":[
        "newsagent"
    ],
    "wof:name":"Stars News Shops",
    "wof:placetype":"venue"
},
  "geometry": {"coordinates":[-1.996093,52.559261],"type":"Point"}
}