{
  "type": "Feature",
  "properties": {
    "iso:country":"GB",
    "sg:address":"Prospect House, 38-40 Barmby Road, Pocklington",
    "sg:city":"York",
    "sg:classifiers":[
        {
            "category":"Manufacturing",
            "subcategory":"Electronics",
            "type":"Manufacturing & Wholesale Goods"
        }
    ],
    "sg:phone":"+44 1759 303068",
    "sg:postcode":"YO42 2DP",
    "sg:province":"East Riding of Yorkshire",
    "sg:tags":[
        "control",
        "component",
        "-",
        "electronic"
    ],
    "wof:name":"Charles Hyde & Son Ltd.",
    "wof:placetype":"venue"
},
  "geometry": {"coordinates":[-0.7853829861,53.9318122864],"type":"Point"}
}