{
  "type": "Feature",
  "properties": {
    "addr:full":"273 Bury New Road, Whitefield Manchester Lancashire M45 8QP",
    "addr:housenumber":"273",
    "addr:postcode":"m45 8qp",
    "addr:street":"Bury New Road",
    "iso:country":"GB",
    "sg:address":"273 Bury New Road, Whitefield",
    "sg:city":"Manchester",
    "sg:classifiers":[
        {
            "category":"Manufacturing",
            "subcategory":"Lumber",
            "type":"Manufacturing & Wholesale Goods"
        }
    ],
    "sg:postcode":"M45 8QP",
    "sg:province":"Lancashire",
    "sg:tags":[
        "importer",
        "merchants",
        "agent",
        "timber"
    ],
    "wof:name":"Quickframe Ltd",
    "wof:placetype":"venue"
},
  "geometry": {"coordinates":[-2.2968308926,53.5524559021],"type":"Point"}
}