{
  "type": "Feature",
  "properties": {
    "iso:country":"GB",
    "sg:address":"25 High Street",
    "sg:city":"Sevenoaks",
    "sg:classifiers":[
        {
            "category":"Personal",
            "subcategory":"Beauty Salon",
            "type":"Services"
        }
    ],
    "sg:postcode":"TN13 1JD",
    "sg:province":"Kent",
    "wof:name":"Clinique Belle",
    "wof:placetype":"venue"
},
  "geometry": {"coordinates":[0.1936720014,51.2679977417],"type":"Point"}
}