{
  "type": "Feature",
  "properties": {
    "addr:full":"2 The Parade, Blackbridge Road Woking Surrey GU22 0DH",
    "addr:housenumber":"2",
    "addr:postcode":"gu22 0dh",
    "addr:street":"The Parade Blackbridge Road",
    "iso:country":"GB",
    "sg:address":"2 The Parade, Blackbridge Road",
    "sg:city":"Woking",
    "sg:classifiers":[
        {
            "category":"Shopping",
            "subcategory":"News",
            "type":"Retail Goods"
        }
    ],
    "sg:phone":"+44 1483 714599",
    "sg:postcode":"GU22 0DH",
    "sg:province":"Surrey",
    "sg:tags":[
        "newsagent"
    ],
    "wof:name":"Rayburn News",
    "wof:placetype":"venue"
},
  "geometry": {"coordinates":[-0.572946,51.309021],"type":"Point"}
}