{
  "type": "Feature",
  "properties": {
    "addr:full":"61 Brunswick Road Buckley Denbighshire CH7 2EH",
    "addr:housenumber":"61",
    "addr:postcode":"ch7 2eh",
    "addr:street":"Brunswick Road",
    "iso:country":"GB",
    "sg:address":"61 Brunswick Road",
    "sg:city":"Buckley",
    "sg:classifiers":[
        {
            "category":"Shopping",
            "subcategory":"Clothing, Apparel, & Fashions",
            "type":"Retail Goods"
        }
    ],
    "sg:postcode":"CH7 2EH",
    "sg:province":"Denbighshire",
    "sg:tags":[
        "shop"
    ],
    "wof:name":"Ladyfayre",
    "wof:placetype":"venue"
},
  "geometry": {"coordinates":[-3.0755419731,53.1678657532],"type":"Point"}
}