{
  "type": "Feature",
  "properties": {
    "addr:full":"Mill Road Wellingborough Northamptonshire NN8 1PE",
    "addr:postcode":"nn8 1pe",
    "addr:street":"Mill Road",
    "iso:country":"GB",
    "sg:address":"Mill Road",
    "sg:city":"Wellingborough",
    "sg:classifiers":[
        {
            "category":"Banks & Credit Unions",
            "subcategory":"Financial Services",
            "type":"Services"
        }
    ],
    "sg:phone":"+44 1933 276767",
    "sg:postcode":"NN8 1PE",
    "sg:province":"Northamptonshire",
    "sg:tags":[
        "consultant"
    ],
    "wof:name":"Mutual Clothing & Supply Co. Ltd.",
    "wof:placetype":"venue"
},
  "geometry": {"coordinates":[-0.6772559881,52.3062896729],"type":"Point"}
}