{
  "type": "Feature",
  "properties": {
    "iso:country":"GB",
    "sg:address":"23 Honey Street",
    "sg:city":"Bodmin",
    "sg:classifiers":[
        {
            "category":"Shopping",
            "subcategory":"Department Store",
            "type":"Retail Goods"
        }
    ],
    "sg:phone":"+44 1208 76612",
    "sg:postcode":"PL31 2DL",
    "sg:province":"Cornwall",
    "wof:name":"The Lighthouse Discount Centre",
    "wof:placetype":"venue"
},
  "geometry": {"coordinates":[-4.71827,50.471268],"type":"Point"}
}