{
  "type": "Feature",
  "properties": {
    "addr:full":"8 Sawston Close, Radbrook Grn Shrewsbury Shropshire SY3 6AY",
    "addr:housenumber":"8",
    "addr:postcode":"sy3 6ay",
    "addr:street":"Sawston Close Radbrook Grn",
    "iso:country":"GB",
    "sg:address":"8 Sawston Close, Radbrook Grn",
    "sg:city":"Shrewsbury",
    "sg:classifiers":[
        {
            "category":"Retail",
            "subcategory":"Storage",
            "type":"Services"
        }
    ],
    "sg:phone":"+44 1743 242947",
    "sg:postcode":"SY3 6AY",
    "sg:province":"Shropshire",
    "sg:tags":[
        "household",
        "removal"
    ],
    "wof:name":"Executive Moves",
    "wof:placetype":"venue"
},
  "geometry": {"coordinates":[-2.775103,52.698605],"type":"Point"}
}