{
  "type": "Feature",
  "properties": {
    "addr:full":"82 Mansfield Street, Sherwood Nottingham Nottinghamshire NG5 4BN",
    "addr:housenumber":"82",
    "addr:postcode":"ng5 4bn",
    "addr:street":"Mansfield Street",
    "iso:country":"GB",
    "sg:address":"82 Mansfield Street, Sherwood",
    "sg:city":"Nottingham",
    "sg:classifiers":[
        {
            "category":"Building & Trades",
            "subcategory":"Construction",
            "type":"Services"
        }
    ],
    "sg:phone":"+44 115 985 6611",
    "sg:postcode":"NG5 4BN",
    "sg:province":"Nottinghamshire",
    "sg:tags":[
        "decorator",
        "painter"
    ],
    "wof:name":"Trent Decorators Ltd.",
    "wof:placetype":"venue"
},
  "geometry": {"coordinates":[-1.145266,52.980412],"type":"Point"}
}