{
  "type": "Feature",
  "properties": {
    "addr:full":"82b Chesterton Lane Cirencester Gloucestershire GL7 1YD",
    "addr:housenumber":"82b",
    "addr:postcode":"gl7 1yd",
    "addr:street":"Chesterton Lane",
    "iso:country":"GB",
    "sg:address":"82b Chesterton Lane",
    "sg:city":"Cirencester",
    "sg:classifiers":[
        {
            "category":"Retail",
            "subcategory":"Car Wash",
            "type":"Services"
        },
        {
            "category":"Retail",
            "subcategory":"Auto Repair",
            "type":"Services"
        }
    ],
    "sg:phone":"+44 1285 657410",
    "sg:postcode":"GL7 1YD",
    "sg:province":"Gloucestershire",
    "sg:tags":[
        "upholsterer",
        "trimmer"
    ],
    "wof:name":"John Skinner Manufacturing Ltd",
    "wof:placetype":"venue"
},
  "geometry": {"coordinates":[-1.964478,51.70755],"type":"Point"}
}