{
  "type": "Feature",
  "properties": {
    "addr:full":"47 Newcastle Street Swindon Wiltshire SN1 2LQ",
    "addr:housenumber":"47",
    "addr:postcode":"sn1 2lq",
    "addr:street":"Newcastle Street",
    "iso:country":"GB",
    "sg:address":"47 Newcastle Street",
    "sg:city":"Swindon",
    "sg:classifiers":[
        {
            "category":"Personal",
            "subcategory":"Tanning Parlor",
            "type":"Services"
        }
    ],
    "sg:postcode":"SN1 2LQ",
    "sg:province":"Wiltshire",
    "sg:tags":[
        "sunbeds"
    ],
    "wof:name":"Deb's Sunbed Hire",
    "wof:placetype":"venue"
},
  "geometry": {"coordinates":[-1.7758239508,51.5617904663],"type":"Point"}
}