{
  "type": "Feature",
  "properties": {
    "addr:full":"9 Mount Mews Hampton Greater London TW12 2SH",
    "addr:housenumber":"9",
    "addr:postcode":"tw12 2sh",
    "addr:street":"Mount Mews",
    "iso:country":"GB",
    "sg:address":"9 Mount Mews",
    "sg:city":"Hampton",
    "sg:classifiers":[
        {
            "category":"Professional",
            "subcategory":"Computer Services",
            "type":"Services"
        }
    ],
    "sg:phone":"+44 20 8255 5511",
    "sg:postcode":"TW12 2SH",
    "sg:province":"Greater London",
    "sg:tags":[
        "system",
        "software"
    ],
    "wof:name":"Imagin Associates Ltd",
    "wof:placetype":"venue"
},
  "geometry": {"coordinates":[-0.362569,51.413815],"type":"Point"}
}