{
  "type": "Feature",
  "properties": {
    "addr:full":"10 Stonefield Road, Blantyre Glasgow South Lanarkshire G72 9PQ",
    "addr:housenumber":"10",
    "addr:postcode":"g72 9pq",
    "addr:street":"Stonefield Road",
    "iso:country":"GB",
    "sg:address":"10 Stonefield Road, Blantyre",
    "sg:city":"Glasgow",
    "sg:classifiers":[
        {
            "category":"Food & Beverages",
            "subcategory":"Groceries & Convenience Stores",
            "type":"Retail Goods"
        }
    ],
    "sg:phone":"+44 1698 823135",
    "sg:postcode":"G72 9PQ",
    "sg:province":"South Lanarkshire",
    "wof:name":"Botterills",
    "wof:placetype":"venue"
},
  "geometry": {"coordinates":[-4.0962710381,55.7943000793],"type":"Point"}
}