{
  "type": "Feature",
  "properties": {
    "addr:full":"3 Clarendon Drive, Wymbush Milton Keynes Buckinghamshire MK8 8DA",
    "addr:housenumber":"3",
    "addr:postcode":"mk8 8da",
    "addr:street":"Clarendon Drive",
    "iso:country":"GB",
    "sg:address":"3 Clarendon Drive, Wymbush",
    "sg:city":"Milton Keynes",
    "sg:classifiers":[
        {
            "category":"Shopping",
            "subcategory":"Computers & Home Electronics",
            "type":"Retail Goods"
        }
    ],
    "sg:phone":"+44 1908 568192",
    "sg:postcode":"MK8 8DA",
    "sg:province":"Buckinghamshire",
    "wof:name":"Radix Micro Devices Plc",
    "wof:placetype":"venue"
},
  "geometry": {"coordinates":[-0.7935990095,52.041519165],"type":"Point"}
}