{
  "type": "Feature",
  "properties": {
    "addr:full":"33 Tor Bryan Ingatestone Essex CM4 9JZ",
    "addr:housenumber":"33",
    "addr:postcode":"cm4 9jz",
    "addr:street":"Tor Bryan",
    "iso:country":"GB",
    "sg:address":"33 Tor Bryan",
    "sg:city":"Ingatestone",
    "sg:classifiers":[
        {
            "category":"Retail",
            "subcategory":"Driving School",
            "type":"Services"
        }
    ],
    "sg:phone":"+44 1277 353472",
    "sg:postcode":"CM4 9JZ",
    "sg:province":"Essex",
    "wof:name":"Hutton School of Motoring",
    "wof:placetype":"venue"
},
  "geometry": {"coordinates":[0.377626,51.663956],"type":"Point"}
}