{
  "type": "Feature",
  "properties": {
    "addr:full":"7 Oakham Court Preston Lancashire PR1 3XP",
    "addr:housenumber":"7",
    "addr:postcode":"pr1 3xp",
    "addr:street":"Oakham Court",
    "iso:country":"GB",
    "sg:address":"7 Oakham Court",
    "sg:city":"Preston",
    "sg:classifiers":[
        {
            "category":"Wholesale",
            "subcategory":"Machinery & Supplies",
            "type":"Manufacturing & Wholesale Goods"
        }
    ],
    "sg:postcode":"PR1 3XP",
    "sg:province":"Lancashire",
    "sg:tags":[
        "industrial",
        "commercial"
    ],
    "wof:name":"Eisbar (U K) Ltd.",
    "wof:placetype":"venue"
},
  "geometry": {"coordinates":[-2.693885,53.757477],"type":"Point"}
}