{
  "type": "Feature",
  "properties": {
    "addr:full":"Stores Road Derby Derbyshire DE21 4BD",
    "addr:postcode":"de21 4bd",
    "addr:street":"Stores Road",
    "iso:country":"GB",
    "sg:address":"Stores Road",
    "sg:city":"Derby",
    "sg:classifiers":[
        {
            "category":"Wholesale",
            "subcategory":"Non-durable Goods",
            "type":"Manufacturing & Wholesale Goods"
        }
    ],
    "sg:phone":"+44 1332 361761",
    "sg:postcode":"DE21 4BD",
    "sg:province":"Derbyshire",
    "sg:tags":[
        "carry",
        "wholesaler",
        "cash"
    ],
    "wof:name":"Special Offer Supplies",
    "wof:placetype":"venue"
},
  "geometry": {"coordinates":[-1.4664510489,52.9302444458],"type":"Point"}
}