{
  "type": "Feature",
  "properties": {
    "addr:full":"82 Derby Road Nottingham Nottinghamshire NG1 5FD",
    "addr:housenumber":"82",
    "addr:postcode":"ng1 5fd",
    "addr:street":"Derby Road",
    "iso:country":"GB",
    "sg:address":"82 Derby Road",
    "sg:city":"Nottingham",
    "sg:classifiers":[
        {
            "category":"Shopping",
            "subcategory":"Comic Books",
            "type":"Retail Goods"
        }
    ],
    "sg:phone":"+44 115 947 3472",
    "sg:postcode":"NG1 5FD",
    "sg:province":"Nottinghamshire",
    "sg:tags":[
        "jeweller"
    ],
    "wof:name":"Woodwards Jewellers",
    "wof:placetype":"venue"
},
  "geometry": {"coordinates":[-1.1590729952,52.9555664062],"type":"Point"}
}