{
  "type": "Feature",
  "properties": {
    "addr:full":"7 Chapel Rd Worthing West Sussex BN11 1EG",
    "addr:housenumber":"7",
    "addr:postcode":"bn11 1eg",
    "addr:street":"Chapel Rd",
    "iso:country":"GB",
    "sg:address":"7 Chapel Rd",
    "sg:city":"Worthing",
    "sg:classifiers":[
        {
            "category":"Professional",
            "subcategory":"Employment Agencies",
            "type":"Services"
        }
    ],
    "sg:phone":"+44 1903 239933",
    "sg:postcode":"BN11 1EG",
    "sg:province":"West Sussex",
    "sg:tags":[
        "consultant"
    ],
    "wof:name":"Grovetex Trading Ltd",
    "wof:placetype":"venue"
},
  "geometry": {"coordinates":[-0.3704380095,50.8118133545],"type":"Point"}
}