{
  "type": "Feature",
  "properties": {
    "iso:country":"GB",
    "sg:address":"All Saints Indust Est",
    "sg:city":"Margate",
    "sg:classifiers":[
        {
            "category":"Retail",
            "subcategory":"Auto Repair",
            "type":"Services"
        }
    ],
    "sg:phone":"+44 1843 220016",
    "sg:postcode":"CT9 1XB",
    "sg:province":"Kent",
    "sg:tags":[
        "modification",
        "garage"
    ],
    "wof:name":"Wings Austin Rover Service & Repairs",
    "wof:placetype":"venue"
},
  "geometry": {"coordinates":[1.3792469501,51.3866615295],"type":"Point"}
}