{
  "type": "Feature",
  "properties": {
    "iso:country":"GB",
    "sg:address":"2 Esther La",
    "sg:city":"Haverfordwest",
    "sg:classifiers":[
        {
            "category":"Shopping",
            "subcategory":"Pets & Pet Supplies",
            "type":"Retail Goods"
        }
    ],
    "sg:phone":"+44 1437 891278",
    "sg:postcode":"SA62 4JH",
    "sg:province":"Pembrokeshire",
    "sg:tags":[
        "food"
    ],
    "wof:name":"Trophy Pet Food",
    "wof:placetype":"venue"
},
  "geometry": {"coordinates":[-4.912231,51.745766],"type":"Point"}
}