{
  "type": "Feature",
  "properties": {
    "addr:full":"Oak Cottage, Lower Froyle Alton Hampshire GU34 4LL",
    "addr:postcode":"gu34 4ll",
    "addr:street":"Lower Froyle",
    "iso:country":"GB",
    "sg:address":"Oak Cottage, Lower Froyle",
    "sg:city":"Alton",
    "sg:classifiers":[
        {
            "category":"Real Estate",
            "subcategory":"Architect",
            "type":"Services"
        }
    ],
    "sg:phone":"+44 1420 22662",
    "sg:postcode":"GU34 4LL",
    "sg:province":"Hampshire",
    "wof:name":"A E J Morris Associates",
    "wof:placetype":"venue"
},
  "geometry": {"coordinates":[-0.913737,51.192112],"type":"Point"}
}