{
  "type": "Feature",
  "properties": {
    "addr:full":"432 Putney High Street London Greater London SW15 2LB",
    "addr:housenumber":"432",
    "addr:postcode":"sw15 2lb",
    "addr:street":"Putney High Street",
    "iso:country":"GB",
    "sg:address":"432 Putney High Street",
    "sg:city":"London",
    "sg:classifiers":[
        {
            "category":"Personal",
            "type":"Services"
        }
    ],
    "sg:phone":"+44 20 8785 7022",
    "sg:postcode":"SW15 2LB",
    "sg:province":"Greater London",
    "sg:tags":[
        "kiss-o-grams"
    ],
    "wof:name":"Ardvark Grams",
    "wof:placetype":"venue"
},
  "geometry": {"coordinates":[-0.21467,51.463612],"type":"Point"}
}