{
  "type": "Feature",
  "properties": {
    "addr:full":"463 Bearwood Road Smethwick West Midlands B66 4DH",
    "addr:housenumber":"463",
    "addr:postcode":"b66 4dh",
    "addr:street":"Bearwood Road",
    "iso:country":"GB",
    "sg:address":"463 Bearwood Road",
    "sg:city":"Smethwick",
    "sg:classifiers":[
        {
            "category":"Shopping",
            "subcategory":"Florist",
            "type":"Retail Goods"
        }
    ],
    "sg:phone":"+44 121 429 9490",
    "sg:postcode":"B66 4DH",
    "sg:province":"West Midlands",
    "wof:name":"Maureens Florist",
    "wof:placetype":"venue"
},
  "geometry": {"coordinates":[-1.969808,52.477394],"type":"Point"}
}