{
  "type": "Feature",
  "properties": {
    "addr:full":"67 Walton Road East Molesey Greater London KT8 0DP",
    "addr:housenumber":"67",
    "addr:postcode":"kt8 0dp",
    "addr:street":"Walton Road",
    "iso:country":"GB",
    "sg:address":"67 Walton Road",
    "sg:city":"East Molesey",
    "sg:classifiers":[
        {
            "category":"Professional",
            "subcategory":"Business Services",
            "type":"Services"
        }
    ],
    "sg:phone":"+44 20 8941 9936",
    "sg:postcode":"KT8 0DP",
    "sg:province":"Greater London",
    "sg:tags":[
        "shop",
        "cleaning"
    ],
    "wof:name":"Minster Cleaning Services",
    "wof:placetype":"venue"
},
  "geometry": {"coordinates":[-0.354072988,51.4000434875],"type":"Point"}
}