{
  "type": "Feature",
  "properties": {
    "addr:full":"Sundial Ho, 111 Queens Rd Brighton East Sussex BN1 3XF",
    "addr:housenumber":"111",
    "addr:postcode":"bn1 3xf",
    "addr:street":"Queens Rd",
    "iso:country":"GB",
    "sg:address":"Sundial Ho, 111 Queens Rd",
    "sg:city":"Brighton",
    "sg:classifiers":[
        {
            "category":"Health Services",
            "subcategory":"Chiropractor",
            "type":"Services"
        }
    ],
    "sg:phone":"+44 1273 774114",
    "sg:postcode":"BN1 3XF",
    "sg:province":"East Sussex",
    "wof:name":"Dianne Hole",
    "wof:placetype":"venue"
},
  "geometry": {"coordinates":[-0.14208,50.826401],"type":"Point"}
}