{
  "type": "Feature",
  "properties": {
    "addr:full":"15 The Green, Southwick Brighton West Sussex BN42 4DE",
    "addr:housenumber":"15",
    "addr:postcode":"bn42 4de",
    "addr:street":"The Green",
    "iso:country":"GB",
    "sg:address":"15 The Green, Southwick",
    "sg:city":"Brighton",
    "sg:classifiers":[
        {
            "category":"Home & Garden",
            "subcategory":"Home Furnishings",
            "type":"Retail Goods"
        }
    ],
    "sg:postcode":"BN42 4DE",
    "sg:province":"West Sussex",
    "sg:tags":[
        "homefurnishings"
    ],
    "wof:name":"J M  Furniture Ltd.",
    "wof:placetype":"venue"
},
  "geometry": {"coordinates":[-0.2381410003,50.8364181519],"type":"Point"}
}