{
  "type": "Feature",
  "properties": {
    "iso:country":"GB",
    "sg:address":"33 Fore Street",
    "sg:city":"St Ives",
    "sg:classifiers":[
        {
            "category":"Arts & Performance",
            "subcategory":"Art Gallery",
            "type":"Entertainment"
        }
    ],
    "sg:phone":"+44 1736 793147",
    "sg:postcode":"TR26 1HE",
    "sg:province":"Cornwall",
    "wof:name":"African Connection Ltd.",
    "wof:placetype":"venue"
},
  "geometry": {"coordinates":[-5.480365,50.2136],"type":"Point"}
}