{
  "type": "Feature",
  "properties": {
    "addr:full":"P O Box 100 Princes Risborough Buckinghamshire HP27 0NJ",
    "addr:housenumber":"100",
    "addr:postcode":"hp27 0nj",
    "addr:street":"P O Box",
    "iso:country":"GB",
    "sg:address":"P O Box 100",
    "sg:city":"Princes Risborough",
    "sg:classifiers":[
        {
            "category":"Shopping",
            "subcategory":"Stationery & Office Supplies",
            "type":"Retail Goods"
        }
    ],
    "sg:phone":"+44 1844 275515",
    "sg:postcode":"HP27 0NJ",
    "sg:province":"Buckinghamshire",
    "wof:name":"Action Stationery",
    "wof:placetype":"venue"
},
  "geometry": {"coordinates":[-0.832952,51.721622],"type":"Point"}
}