{
  "type": "Feature",
  "properties": {
    "addr:full":"35 Alexandra Road Morecambe Lancashire LA3 1TQ",
    "addr:housenumber":"35",
    "addr:postcode":"la3 1tq",
    "addr:street":"Alexandra Road",
    "iso:country":"GB",
    "sg:address":"35 Alexandra Road",
    "sg:city":"Morecambe",
    "sg:classifiers":[
        {
            "category":"Retail",
            "subcategory":"Laundry & Dry Cleaning",
            "type":"Services"
        }
    ],
    "sg:phone":"+44 1524 414142",
    "sg:postcode":"LA3 1TQ",
    "sg:province":"Lancashire",
    "sg:tags":[
        "launderette",
        "alteration"
    ],
    "wof:name":"E Johnson",
    "wof:placetype":"venue"
},
  "geometry": {"coordinates":[-2.8827409744,54.0642089844],"type":"Point"}
}