{
  "type": "Feature",
  "properties": {
    "addr:full":"Usk Way Newport Newport NP20 2BU",
    "addr:postcode":"np20 2bu",
    "addr:street":"Usk Way",
    "iso:country":"GB",
    "sg:address":"Usk Way",
    "sg:city":"Newport",
    "sg:classifiers":[
        {
            "category":"Professional",
            "subcategory":"Engineering",
            "type":"Services"
        }
    ],
    "sg:phone":"+44 1633 246921",
    "sg:postcode":"NP20 2BU",
    "sg:province":"Newport",
    "sg:tags":[
        "precision",
        "engineer"
    ],
    "wof:name":"Melmec Engineering",
    "wof:placetype":"venue"
},
  "geometry": {"coordinates":[-2.989394,51.584896],"type":"Point"}
}