{
  "type": "Feature",
  "properties": {
    "addr:full":"Worthing Depot, Meadow Road Indust Est Worthing West Sussex BN11 2RU",
    "addr:postcode":"bn11 2ru",
    "addr:street":"Meadow Road",
    "iso:country":"GB",
    "sg:address":"Worthing Depot, Meadow Road Indust Est",
    "sg:city":"Worthing",
    "sg:classifiers":[
        {
            "category":"Utilities",
            "subcategory":"Refuse",
            "type":"Services"
        }
    ],
    "sg:phone":"+44 1903 230901",
    "sg:postcode":"BN11 2RU",
    "sg:province":"West Sussex",
    "sg:tags":[
        "disposal",
        "waste"
    ],
    "wof:name":"UK Waste",
    "wof:placetype":"venue"
},
  "geometry": {"coordinates":[-0.3754239976,50.8136253357],"type":"Point"}
}