{
  "type": "Feature",
  "properties": {
    "addr:full":"Newbiggin High Farm, Aislaby Whitby North Yorkshire YO21 1SX",
    "addr:postcode":"yo21 1sx",
    "iso:country":"GB",
    "sg:address":"Newbiggin High Farm, Aislaby",
    "sg:city":"Whitby",
    "sg:classifiers":[
        {
            "category":"Farming",
            "subcategory":"Livestock Farm",
            "type":"Manufacturing & Wholesale Goods"
        }
    ],
    "sg:phone":"+44 1947 810324",
    "sg:postcode":"YO21 1SX",
    "sg:province":"North Yorkshire",
    "sg:tags":[
        "others"
    ],
    "wof:name":"P Dowson",
    "wof:placetype":"venue"
},
  "geometry": {"coordinates":[-0.615053,54.485233],"type":"Point"}
}