{
  "type": "Feature",
  "properties": {
    "addr:full":"City Financial Centre, 88 Borough High Street London Greater London SE1 1ST",
    "addr:housenumber":"88",
    "addr:postcode":"se1 1st",
    "addr:street":"Borough High Street",
    "iso:country":"GB",
    "sg:address":"City Financial Centre, 88 Borough High Street",
    "sg:city":"London",
    "sg:classifiers":[
        {
            "category":"Banks & Credit Unions",
            "subcategory":"Financial Services",
            "type":"Services"
        }
    ],
    "sg:phone":"+44 20 7556 8800",
    "sg:postcode":"SE1 1ST",
    "sg:province":"Greater London",
    "sg:tags":[
        "consultant"
    ],
    "wof:name":"Capita Financial Managers Ltd.",
    "wof:placetype":"venue"
},
  "geometry": {"coordinates":[-0.09177,51.503502],"type":"Point"}
}