{
  "type": "Feature",
  "properties": {
    "addr:full":"31 Roman Way, Thrapston Kettering Northamptonshire NN14 4TE",
    "addr:housenumber":"31",
    "addr:postcode":"nn14 4te",
    "addr:street":"Roman Way",
    "iso:country":"GB",
    "sg:address":"31 Roman Way, Thrapston",
    "sg:city":"Kettering",
    "sg:classifiers":[
        {
            "category":"Taxi",
            "type":"Transportation"
        },
        {
            "category":"Bus Stop",
            "subcategory":"None",
            "type":"Transportation"
        }
    ],
    "sg:phone":"+44 1832 734666",
    "sg:postcode":"NN14 4TE",
    "sg:province":"Northamptonshire",
    "sg:tags":[
        "mini",
        "hire",
        "cab",
        "min"
    ],
    "wof:name":"MICHAEL & A STARSMORE",
    "wof:placetype":"venue"
},
  "geometry": {"coordinates":[-0.529317975,52.4022636414],"type":"Point"}
}