{
  "type": "Feature",
  "properties": {
    "addr:full":"198 Ashby Rd Scunthorpe Lincolnshire DN16 2AR",
    "addr:housenumber":"198",
    "addr:postcode":"dn16 2ar",
    "addr:street":"Ashby Rd",
    "iso:country":"GB",
    "sg:address":"198 Ashby Rd",
    "sg:city":"Scunthorpe",
    "sg:classifiers":[
        {
            "category":"Shopping",
            "type":"Retail Goods"
        }
    ],
    "sg:phone":"+44 1724 858698",
    "sg:postcode":"DN16 2AR",
    "sg:province":"Lincolnshire",
    "sg:tags":[
        "merchant"
    ],
    "wof:name":"J R Haslehurst",
    "wof:placetype":"venue"
},
  "geometry": {"coordinates":[-0.655312,53.573524],"type":"Point"}
}