{
  "type": "Feature",
  "properties": {
    "iso:country":"GB",
    "sg:address":"4 Station Road, Sutton",
    "sg:city":"Ely",
    "sg:classifiers":[
        {
            "category":"Building & Trades",
            "subcategory":"Construction",
            "type":"Services"
        }
    ],
    "sg:postcode":"CB6 2RL",
    "sg:province":"Cambridgeshire",
    "sg:tags":[
        "builder"
    ],
    "wof:name":"Therlex Ltd.",
    "wof:placetype":"venue"
},
  "geometry": {"coordinates":[0.129209,52.38921],"type":"Point"}
}