{
  "type": "Feature",
  "properties": {
    "iso:country":"GB",
    "sg:address":"Po Box 62",
    "sg:city":"Ormskirk",
    "sg:classifiers":[
        {
            "category":"Food & Beverages",
            "subcategory":"Liquor & Beverages",
            "type":"Retail Goods"
        }
    ],
    "sg:phone":"+44 1704 889060",
    "sg:postcode":"L40 9SJ",
    "sg:province":"Lancashire",
    "sg:tags":[
        "beer",
        "spirit",
        "wines"
    ],
    "wof:name":"Corkpoppers Collective Wines",
    "wof:placetype":"venue"
},
  "geometry": {"coordinates":[-2.909999,53.61985],"type":"Point"}
}