{
  "type": "Feature",
  "properties": {
    "addr:full":"South Quay, Fishmart Wick Highland KW1 5HA",
    "addr:postcode":"kw1 5ha",
    "addr:street":"South Quay Fishmart Wick",
    "iso:country":"GB",
    "sg:address":"South Quay, Fishmart",
    "sg:city":"Wick",
    "sg:classifiers":[
        {
            "category":"Building & Trades",
            "subcategory":"Equipment Rental",
            "type":"Services"
        }
    ],
    "sg:phone":"+44 1955 604444",
    "sg:postcode":"KW1 5HA",
    "sg:province":"Highland",
    "sg:tags":[
        "plant",
        "machinery"
    ],
    "wof:name":"Hugh Simpson (Contractors) Ltd.",
    "wof:placetype":"venue"
},
  "geometry": {"coordinates":[-3.094143,58.433956],"type":"Point"}
}