{
  "type": "Feature",
  "properties": {
    "addr:full":"12 Newland Gardens London Greater London W13 9TR",
    "addr:housenumber":"12",
    "addr:postcode":"w13 9tr",
    "addr:street":"Newland Gardens",
    "iso:country":"GB",
    "sg:address":"12 Newland Gardens",
    "sg:city":"London",
    "sg:classifiers":[
        {
            "category":"Professional",
            "subcategory":"Lawyer & Legal Services",
            "type":"Services"
        }
    ],
    "sg:postcode":"W13 9TR",
    "sg:province":"Greater London",
    "wof:name":"Just Wills of Ealing",
    "wof:placetype":"venue"
},
  "geometry": {"coordinates":[-0.325531,51.503639],"type":"Point"}
}