{
  "type": "Feature",
  "properties": {
    "iso:country":"GB",
    "sg:address":"92-94 Linden Rd",
    "sg:city":"Gloucester",
    "sg:classifiers":[
        {
            "category":"Government",
            "subcategory":"Post Office",
            "type":"Public Place"
        }
    ],
    "sg:phone":"+44 1452 522812",
    "sg:postcode":"GL1 5HE",
    "sg:province":"Gloucestershire",
    "wof:name":"Linden Road Stores",
    "wof:placetype":"venue"
},
  "geometry": {"coordinates":[-2.25181,51.850693],"type":"Point"}
}