{
  "type": "Feature",
  "properties": {
    "iso:country":"GB",
    "sg:address":"25 South Parade",
    "sg:city":"Whitley Bay",
    "sg:classifiers":[
        {
            "category":"Travel",
            "subcategory":"Hotels & Motels",
            "type":"Entertainment"
        }
    ],
    "sg:phone":"+44 191 251 3653",
    "sg:postcode":"NE26 2RE",
    "sg:province":"Northumberland",
    "sg:tags":[
        "house",
        "guest"
    ],
    "wof:name":"Mayfair Guest House",
    "wof:placetype":"venue"
},
  "geometry": {"coordinates":[-1.442827,55.043045],"type":"Point"}
}