{
  "type": "Feature",
  "properties": {
    "addr:full":"Vandyke Road Leighton Buzzard Bedfordshire LU7 3HS",
    "addr:postcode":"lu7 3hs",
    "addr:street":"Vandyke Road",
    "iso:country":"GB",
    "sg:address":"Vandyke Road",
    "sg:city":"Leighton Buzzard",
    "sg:classifiers":[
        {
            "category":"Education",
            "subcategory":"School",
            "type":"Public Place"
        },
        {
            "category":"Government",
            "subcategory":"Office",
            "type":"Public Place"
        }
    ],
    "sg:phone":"+44 1525 372266",
    "sg:postcode":"LU7 3HS",
    "sg:province":"Bedfordshire",
    "sg:tags":[
        "local",
        "authority"
    ],
    "wof:name":"Gilbert Inglefield Middle School",
    "wof:placetype":"venue"
},
  "geometry": {"coordinates":[-0.6496220231,51.9250144958],"type":"Point"}
}