{
  "type": "Feature",
  "properties": {
    "addr:full":"12 Cornmarket Thame Buckinghamshire OX9 2BL",
    "addr:housenumber":"12",
    "addr:postcode":"ox9 2bl",
    "addr:street":"Cornmarket Thame",
    "iso:country":"GB",
    "sg:address":"12 Cornmarket",
    "sg:city":"Thame",
    "sg:classifiers":[
        {
            "category":"Shopping",
            "subcategory":"Discount & Variety Stores",
            "type":"Retail Goods"
        }
    ],
    "sg:phone":"+44 1844 217277",
    "sg:postcode":"OX9 2BL",
    "sg:province":"Buckinghamshire",
    "sg:tags":[
        "centre"
    ],
    "wof:name":"The Money Spinner",
    "wof:placetype":"venue"
},
  "geometry": {"coordinates":[-0.977363,51.74667],"type":"Point"}
}