{
  "type": "Feature",
  "properties": {
    "addr:full":"30 Pemberton Street Blackburn Lancashire BB1 9AB",
    "addr:housenumber":"30",
    "addr:postcode":"bb1 9ab",
    "addr:street":"Pemberton Street",
    "iso:country":"GB",
    "sg:address":"30 Pemberton Street",
    "sg:city":"Blackburn",
    "sg:classifiers":[
        {
            "category":"Professional",
            "subcategory":"Printing & Photocopies",
            "type":"Services"
        }
    ],
    "sg:phone":"+44 1254 664266",
    "sg:postcode":"BB1 9AB",
    "sg:province":"Lancashire",
    "sg:tags":[
        "printer"
    ],
    "wof:name":"Shaw Corporation (uk) Ltd",
    "wof:placetype":"venue"
},
  "geometry": {"coordinates":[-2.47985,53.767796],"type":"Point"}
}