{
  "type": "Feature",
  "properties": {
    "iso:country":"GB",
    "sg:address":"54 Humperey Lane",
    "sg:city":"Manchester",
    "sg:classifiers":[
        {
            "category":"Professional",
            "subcategory":"Art Services",
            "type":"Services"
        }
    ],
    "sg:postcode":"M41 9PS",
    "sg:province":"Cheshire",
    "sg:tags":[
        "photographer"
    ],
    "wof:name":"G C L Photography",
    "wof:placetype":"venue"
},
  "geometry": {"coordinates":[-2.332053,53.44923],"type":"Point"}
}