{
  "type": "Feature",
  "properties": {
    "iso:country":"GB",
    "sg:address":"Unit 3, Padden Brook",
    "sg:city":"Stockport",
    "sg:classifiers":[
        {
            "category":"Autos & Motor Vehicles",
            "subcategory":"Automobile Sales",
            "type":"Retail Goods"
        }
    ],
    "sg:phone":"+44 161 406 9446",
    "sg:postcode":"SK6 3AN",
    "sg:province":"Cheshire",
    "sg:tags":[
        "car"
    ],
    "wof:name":"Clarks of Cheshire Ltd.",
    "wof:placetype":"venue"
},
  "geometry": {"coordinates":[-2.099004,53.412685],"type":"Point"}
}