{
  "type": "Feature",
  "properties": {
    "addr:full":"10a Wareham Road, Corfe Mullen Wimborne Dorset BH21 3LE",
    "addr:housenumber":"10a",
    "addr:postcode":"bh21 3le",
    "addr:street":"Wareham Road",
    "iso:country":"GB",
    "sg:address":"10a Wareham Road, Corfe Mullen",
    "sg:city":"Wimborne",
    "sg:classifiers":[
        {
            "category":"Shopping",
            "subcategory":"Stationery & Office Supplies",
            "type":"Retail Goods"
        }
    ],
    "sg:phone":"+44 1202 602757",
    "sg:postcode":"BH21 3LE",
    "sg:province":"Dorset",
    "sg:tags":[
        "equipment"
    ],
    "wof:name":"Clarity Copiers 9DORSET) & Co",
    "wof:placetype":"venue"
},
  "geometry": {"coordinates":[-2.0159459114,50.7767944336],"type":"Point"}
}