{
  "type": "Feature",
  "properties": {
    "addr:full":"154 Avon Street Coventry Warwickshire CV2 3GP",
    "addr:housenumber":"154",
    "addr:postcode":"cv2 3gp",
    "addr:street":"Avon Street",
    "iso:country":"GB",
    "sg:address":"154 Avon Street",
    "sg:city":"Coventry",
    "sg:classifiers":[
        {
            "category":"Retail",
            "subcategory":"Driving School",
            "type":"Services"
        }
    ],
    "sg:postcode":"CV2 3GP",
    "sg:province":"Warwickshire",
    "wof:name":"Malcan Driving School",
    "wof:placetype":"venue"
},
  "geometry": {"coordinates":[-1.472425,52.418308],"type":"Point"}
}