{
  "type": "Feature",
  "properties": {
    "addr:full":"Transmer Ho, Byrons La Macclesfield Cheshire SK11 7JW",
    "addr:postcode":"sk11 7jw",
    "addr:street":"La Macclesfield",
    "iso:country":"GB",
    "sg:address":"Transmer Ho, Byrons La",
    "sg:city":"Macclesfield",
    "sg:classifiers":[
        {
            "category":"Manufacturing",
            "subcategory":"Paper Products",
            "type":"Manufacturing & Wholesale Goods"
        }
    ],
    "sg:postcode":"SK11 7JW",
    "sg:province":"Cheshire",
    "sg:tags":[
        "board"
    ],
    "wof:name":"Greystone Packaging Ltd",
    "wof:placetype":"venue"
},
  "geometry": {"coordinates":[-2.125756,53.255669],"type":"Point"}
}