{
  "type": "Feature",
  "properties": {
    "addr:full":"Daisy Bank, Borras Road, Borras Wrexham Wrexham LL13 9TG",
    "addr:postcode":"ll13 9tg",
    "addr:street":"Borras Road Borras",
    "iso:country":"GB",
    "sg:address":"Daisy Bank, Borras Road, Borras",
    "sg:city":"Wrexham",
    "sg:classifiers":[
        {
            "category":"Farming",
            "subcategory":"Livestock Farm",
            "type":"Manufacturing & Wholesale Goods"
        }
    ],
    "sg:postcode":"LL13 9TG",
    "sg:province":"Wrexham",
    "sg:tags":[
        "others"
    ],
    "wof:name":"E Chadwick & Son",
    "wof:placetype":"venue"
},
  "geometry": {"coordinates":[-2.966882,53.062408],"type":"Point"}
}