{
  "type": "Feature",
  "properties": {
    "addr:full":"112 Feltham Road Ashford Greater London TW15 1DS",
    "addr:housenumber":"112",
    "addr:postcode":"tw15 1ds",
    "addr:street":"Feltham Road",
    "iso:country":"GB",
    "sg:address":"112 Feltham Road",
    "sg:city":"Ashford",
    "sg:classifiers":[
        {
            "category":"Building & Trades",
            "subcategory":"Construction",
            "type":"Services"
        }
    ],
    "sg:phone":"+44 1784 259362",
    "sg:postcode":"TW15 1DS",
    "sg:province":"Greater London",
    "sg:tags":[
        "roofing"
    ],
    "wof:name":"Roofcare Services",
    "wof:placetype":"venue"
},
  "geometry": {"coordinates":[-0.448998,51.432617],"type":"Point"}
}