{
  "type": "Feature",
  "properties": {
    "iso:country":"GB",
    "sg:address":"Chestnut Farm, Vole Road, Mark",
    "sg:city":"Highbridge",
    "sg:classifiers":[
        {
            "category":"Farming",
            "subcategory":"Dairy Farm",
            "type":"Manufacturing & Wholesale Goods"
        }
    ],
    "sg:phone":"+44 1278 760684",
    "sg:postcode":"TA9 4PD",
    "sg:province":"Somerset",
    "sg:tags":[
        "farmer"
    ],
    "wof:name":"G A Durston & Son",
    "wof:placetype":"venue"
},
  "geometry": {"coordinates":[-2.892619,51.227337],"type":"Point"}
}