{
  "type": "Feature",
  "properties": {
    "iso:country":"GB",
    "sg:address":"77 Haydn Road",
    "sg:city":"Nottingham",
    "sg:classifiers":[
        {
            "category":"Fast Food",
            "type":"Food & Drink"
        }
    ],
    "sg:phone":"+44 115 969 3583",
    "sg:postcode":"NG5 2LA",
    "sg:province":"Nottinghamshire",
    "sg:tags":[
        "away",
        "take"
    ],
    "wof:name":"The Dragon Palace",
    "wof:placetype":"venue"
},
  "geometry": {"coordinates":[-1.152999,52.979752],"type":"Point"}
}