{
  "type": "Feature",
  "properties": {
    "iso:country":"GB",
    "sg:address":"Baltic House, Kingston Crescent, North End",
    "sg:city":"Portsmouth",
    "sg:classifiers":[
        {
            "category":"Manufacturing",
            "subcategory":"Tools & Machinery",
            "type":"Manufacturing & Wholesale Goods"
        },
        {
            "category":"Insurance",
            "subcategory":"Insurance Agent",
            "type":"Services"
        }
    ],
    "sg:postcode":"PO2 8QL",
    "sg:province":"Hampshire",
    "sg:tags":[
        "society",
        "friendly"
    ],
    "wof:name":"B D M L Connect Ltd.",
    "wof:placetype":"venue"
},
  "geometry": {"coordinates":[-1.0840599537,50.8135414124],"type":"Point"}
}