{
  "type": "Feature",
  "properties": {
    "iso:country":"GB",
    "sg:address":"Blair Athall",
    "sg:city":"Pitlochry",
    "sg:classifiers":[
        {
            "category":"Shopping",
            "subcategory":"Department Store",
            "type":"Retail Goods"
        }
    ],
    "sg:phone":"+44 1796 481206",
    "sg:postcode":"PH18 5SX",
    "sg:province":"Perth and Kinross",
    "wof:name":"Tilt Stores",
    "wof:placetype":"venue"
},
  "geometry": {"coordinates":[-3.8362801075,56.7658996582],"type":"Point"}
}