{
  "type": "Feature",
  "properties": {
    "addr:full":"Westfields, New Road Shaftesbury Dorset SP7 8QH",
    "addr:postcode":"sp7 8qh",
    "addr:street":"New Road",
    "iso:country":"GB",
    "sg:address":"Westfields, New Road",
    "sg:city":"Shaftesbury",
    "sg:classifiers":[
        {
            "category":"Health Services",
            "subcategory":"Dentist",
            "type":"Services"
        }
    ],
    "sg:phone":"+44 1747 852055",
    "sg:postcode":"SP7 8QH",
    "sg:province":"Dorset",
    "wof:name":"A P Rhodes",
    "wof:placetype":"venue"
},
  "geometry": {"coordinates":[-2.187124,51.005764],"type":"Point"}
}