{
  "type": "Feature",
  "properties": {
    "addr:full":"120 Derby Road, Long Eaton Nottingham Derbyshire NG10 4LS",
    "addr:housenumber":"120",
    "addr:postcode":"ng10 4ls",
    "addr:street":"Derby Road",
    "iso:country":"GB",
    "sg:address":"120 Derby Road, Long Eaton",
    "sg:city":"Nottingham",
    "sg:classifiers":[
        {
            "category":"Real Estate",
            "subcategory":"Surveying",
            "type":"Services"
        }
    ],
    "sg:phone":"+44 115 972 5163",
    "sg:postcode":"NG10 4LS",
    "sg:province":"Derbyshire",
    "sg:tags":[
        "building",
        "surveyor"
    ],
    "wof:name":"Monitor Environmental Ltd.",
    "wof:placetype":"venue"
},
  "geometry": {"coordinates":[-1.2823339701,52.9019737244],"type":"Point"}
}