{
  "type": "Feature",
  "properties": {
    "addr:full":"32 Clive Road, Cowley Oxford Oxfordshire OX4 3EJ",
    "addr:housenumber":"32",
    "addr:postcode":"ox4 3ej",
    "addr:street":"Clive Road",
    "iso:country":"GB",
    "sg:address":"32 Clive Road, Cowley",
    "sg:city":"Oxford",
    "sg:classifiers":[
        {
            "category":"Manufacturing",
            "subcategory":"Signs",
            "type":"Manufacturing & Wholesale Goods"
        }
    ],
    "sg:postcode":"OX4 3EJ",
    "sg:province":"Oxfordshire",
    "sg:tags":[
        "writer"
    ],
    "wof:name":"N C Signs",
    "wof:placetype":"venue"
},
  "geometry": {"coordinates":[-1.2186239958,51.7348594666],"type":"Point"}
}