{
  "type": "Feature",
  "properties": {
    "addr:full":"147a High Park Road Southport Lancashire PR9 7BY",
    "addr:housenumber":"147a",
    "addr:postcode":"pr9 7by",
    "addr:street":"High Park Road",
    "iso:country":"GB",
    "sg:address":"147a High Park Road",
    "sg:city":"Southport",
    "sg:classifiers":[
        {
            "category":"Retail",
            "subcategory":"Auto Repair",
            "type":"Services"
        }
    ],
    "sg:phone":"+44 1704 229217",
    "sg:postcode":"PR9 7BY",
    "sg:province":"Lancashire",
    "sg:tags":[
        "modification",
        "garage",
        "related"
    ],
    "wof:name":"Wilson Healy Automobile Engineering",
    "wof:placetype":"venue"
},
  "geometry": {"coordinates":[-2.964725,53.64867],"type":"Point"}
}