{
  "type": "Feature",
  "properties": {
    "addr:full":"The Cedars Hotel Kidderminster Staffordshire DY11 6AG",
    "addr:postcode":"dy11 6ag",
    "iso:country":"GB",
    "sg:address":"The Cedars Hotel",
    "sg:city":"Kidderminster",
    "sg:classifiers":[
        {
            "category":"Travel",
            "subcategory":"Hotels & Motels",
            "type":"Entertainment"
        }
    ],
    "sg:phone":"+44 1562 515595",
    "sg:postcode":"DY11 6AG",
    "sg:province":"Staffordshire",
    "wof:name":"Courtford Inns Ltd.",
    "wof:placetype":"venue"
},
  "geometry": {"coordinates":[-2.26374,52.390228],"type":"Point"}
}