{
  "type": "Feature",
  "properties": {
    "addr:full":"Leasow Farm, Highfield Lane, Mugginton Derby Derbyshire DE6 4PQ",
    "addr:postcode":"de6 4pq",
    "addr:street":"Leasow;Highfield Lane",
    "iso:country":"GB",
    "sg:address":"Leasow Farm, Highfield Lane, Mugginton",
    "sg:city":"Derby",
    "sg:classifiers":[
        {
            "category":"Farming",
            "subcategory":"Livestock Farm",
            "type":"Manufacturing & Wholesale Goods"
        }
    ],
    "sg:postcode":"DE6 4PQ",
    "sg:province":"Derbyshire",
    "sg:tags":[
        "others"
    ],
    "wof:name":"D J Metcalf & Co.",
    "wof:placetype":"venue"
},
  "geometry": {"coordinates":[-1.57859,52.983181],"type":"Point"}
}