{
  "type": "Feature",
  "properties": {
    "iso:country":"GB",
    "sg:address":"77 Southern Road",
    "sg:city":"Basingstoke",
    "sg:classifiers":[
        {
            "category":"Fast Food",
            "type":"Food & Drink"
        }
    ],
    "sg:phone":"+44 1256 321336",
    "sg:postcode":"RG21 3DY",
    "sg:province":"Hampshire",
    "sg:tags":[
        "away",
        "take"
    ],
    "wof:name":"Wok Inn",
    "wof:placetype":"venue"
},
  "geometry": {"coordinates":[-1.087478,51.260643],"type":"Point"}
}