{
  "type": "Feature",
  "properties": {
    "addr:full":"13 Bridge Street Stafford Staffordshire ST16 2HL",
    "addr:housenumber":"13",
    "addr:postcode":"st16 2hl",
    "addr:street":"Bridge Street",
    "iso:country":"GB",
    "sg:address":"13 Bridge Street",
    "sg:city":"Stafford",
    "sg:classifiers":[
        {
            "category":"Recreation",
            "subcategory":"Amusement Park",
            "type":"Entertainment"
        }
    ],
    "sg:phone":"+44 1785 244407",
    "sg:postcode":"ST16 2HL",
    "sg:province":"Staffordshire",
    "sg:tags":[
        "arcade"
    ],
    "wof:name":"Shipleys Amusement Arcade",
    "wof:placetype":"venue"
},
  "geometry": {"coordinates":[-2.1163349152,52.8049621582],"type":"Point"}
}