{
  "type": "Feature",
  "properties": {
    "iso:country":"GB",
    "sg:address":"206 Childwall Rd, Childwall Fiveways",
    "sg:city":"Liverpool",
    "sg:classifiers":[
        {
            "category":"Real Estate",
            "subcategory":"Developer",
            "type":"Services"
        }
    ],
    "sg:phone":"+44 151 738 1586",
    "sg:postcode":"L15 6UY",
    "sg:province":"Merseyside",
    "sg:tags":[
        "property"
    ],
    "wof:name":"Greg Ormesher",
    "wof:placetype":"venue"
},
  "geometry": {"coordinates":[-2.898786,53.39687],"type":"Point"}
}