{
  "type": "Feature",
  "properties": {
    "addr:full":"71 High Street, Norton Stockton-on-tees Durham TS20 1AQ",
    "addr:housenumber":"71",
    "addr:postcode":"ts20 1aq",
    "addr:street":"High Street",
    "iso:country":"GB",
    "sg:address":"71 High Street, Norton",
    "sg:city":"Stockton-on-tees",
    "sg:classifiers":[
        {
            "category":"Professional",
            "type":"Services"
        }
    ],
    "sg:phone":"+44 1642 556687",
    "sg:postcode":"TS20 1AQ",
    "sg:province":"Durham",
    "sg:tags":[
        "caterer"
    ],
    "wof:name":"Cleveland Caterers",
    "wof:placetype":"venue"
},
  "geometry": {"coordinates":[-1.3109639883,54.5884780884],"type":"Point"}
}