{
  "type": "Feature",
  "properties": {
    "iso:country":"GB",
    "sg:address":"244 /246kingston Road",
    "sg:city":"Portsmouth",
    "sg:classifiers":[
        {
            "category":"Professional",
            "subcategory":"Printing & Photocopies",
            "type":"Services"
        }
    ],
    "sg:phone":"+44 23 9269 5652",
    "sg:postcode":"PO2 7LR",
    "sg:province":"Hampshire",
    "sg:tags":[
        "trophy"
    ],
    "wof:name":"Victory Trophies",
    "wof:placetype":"venue"
},
  "geometry": {"coordinates":[-1.0638890266,50.8098297119],"type":"Point"}
}