{
  "type": "Feature",
  "properties": {
    "addr:full":"17 London Road Tonbridge Kent TN10 3AB",
    "addr:housenumber":"17",
    "addr:postcode":"tn10 3ab",
    "addr:street":"London Road",
    "iso:country":"GB",
    "sg:address":"17 London Road",
    "sg:city":"Tonbridge",
    "sg:classifiers":[
        {
            "category":"Health Services",
            "subcategory":"Nursing And Care Facility",
            "type":"Services"
        }
    ],
    "sg:phone":"+44 1732 355231",
    "sg:postcode":"TN10 3AB",
    "sg:province":"Kent",
    "sg:tags":[
        "agency"
    ],
    "wof:name":"Consultus Care & Nursing Agency Ltd.",
    "wof:placetype":"venue"
},
  "geometry": {"coordinates":[0.2760800123,51.2016296387],"type":"Point"}
}