{
  "type": "Feature",
  "properties": {
    "addr:full":"Unit 4, Miller Court, Alloa Business Park Alloa Clackmannanshire FK10 3SA",
    "addr:housenumber":"unit 4",
    "addr:postcode":"fk10 3sa",
    "addr:street":"Miller Court;Business Park",
    "iso:country":"GB",
    "sg:address":"Unit 4, Miller Court, Alloa Business Park",
    "sg:city":"Alloa",
    "sg:classifiers":[
        {
            "category":"Home & Garden",
            "subcategory":"Kitchen Supply",
            "type":"Retail Goods"
        }
    ],
    "sg:phone":"+44 1259 218121",
    "sg:postcode":"FK10 3SA",
    "sg:province":"Clackmannanshire",
    "sg:tags":[
        "equipment",
        "catering"
    ],
    "wof:name":"Plus Minus Ltd.",
    "wof:placetype":"venue"
},
  "geometry": {"coordinates":[-3.7951939106,56.1163215637],"type":"Point"}
}