{
  "type": "Feature",
  "properties": {
    "addr:full":"13 Hillside Cres Bury Lancashire BL9 6PZ",
    "addr:housenumber":"13",
    "addr:postcode":"bl9 6pz",
    "addr:street":"Hillside Cres",
    "iso:country":"GB",
    "sg:address":"13 Hillside Cres",
    "sg:city":"Bury",
    "sg:classifiers":[
        {
            "category":"Building & Trades",
            "subcategory":"Construction",
            "type":"Services"
        }
    ],
    "sg:phone":"+44 161 761 2106",
    "sg:postcode":"BL9 6PZ",
    "sg:province":"Lancashire",
    "sg:tags":[
        "decorator",
        "painter"
    ],
    "wof:name":"P Bertwistle",
    "wof:placetype":"venue"
},
  "geometry": {"coordinates":[-2.2920041084,53.6116943359],"type":"Point"}
}