{
  "type": "Feature",
  "properties": {
    "addr:full":"13 Waverley Road Southsea Hampshire PO5 2PH",
    "addr:housenumber":"13",
    "addr:postcode":"po5 2ph",
    "addr:street":"Waverley Road",
    "iso:country":"GB",
    "sg:address":"13 Waverley Road",
    "sg:city":"Southsea",
    "sg:classifiers":[
        {
            "category":"Cafe",
            "type":"Food & Drink"
        }
    ],
    "sg:phone":"+44 23 9235 1722",
    "sg:postcode":"PO5 2PH",
    "sg:province":"Hampshire",
    "sg:tags":[
        "tea",
        "room"
    ],
    "wof:name":"The Waverley Cafe",
    "wof:placetype":"venue"
},
  "geometry": {"coordinates":[-1.079938,50.781773],"type":"Point"}
}