{
  "type": "Feature",
  "properties": {
    "addr:full":"Ellifoot Lane, Burstwick Industrial Estate Hull East Riding of Yorkshire HU12 9EF",
    "addr:postcode":"hu12 9ef",
    "addr:street":"Ellifoot Lane;Industrial Estate",
    "iso:country":"GB",
    "sg:address":"Ellifoot Lane, Burstwick Industrial Estate",
    "sg:city":"Hull",
    "sg:classifiers":[
        {
            "category":"Building & Trades",
            "subcategory":"Construction",
            "type":"Services"
        }
    ],
    "sg:phone":"+44 1964 670818",
    "sg:postcode":"HU12 9EF",
    "sg:province":"East Riding of Yorkshire",
    "sg:tags":[
        "joiner",
        "carpenter"
    ],
    "wof:name":"Brian Fawcett Joinery",
    "wof:placetype":"venue"
},
  "geometry": {"coordinates":[-0.131877,53.741196],"type":"Point"}
}