{
  "type": "Feature",
  "properties": {
    "addr:full":"Alma Street, Brynmawr Ebbw Vale Blaenau Gwent NP23 4DZ",
    "addr:postcode":"np23 4dz",
    "addr:street":"Alma Street",
    "iso:country":"GB",
    "sg:address":"Alma Street, Brynmawr",
    "sg:city":"Ebbw Vale",
    "sg:classifiers":[
        {
            "category":"Home & Garden",
            "subcategory":"Furniture",
            "type":"Retail Goods"
        }
    ],
    "sg:phone":"+44 1495 312173",
    "sg:postcode":"NP23 4DZ",
    "sg:province":"Blaenau Gwent",
    "wof:name":"Planet Pine Ltd.",
    "wof:placetype":"venue"
},
  "geometry": {"coordinates":[-3.1763939857,51.8000488281],"type":"Point"}
}