{
  "type": "Feature",
  "properties": {
    "addr:full":"Churnetside Business Park, Station Road, Cheddleton Leek Staffordshire ST13 7EE",
    "addr:postcode":"st13 7ee",
    "addr:street":"Station Road",
    "iso:country":"GB",
    "sg:address":"Churnetside Business Park, Station Road, Cheddleton",
    "sg:city":"Leek",
    "sg:classifiers":[
        {
            "category":"Home & Garden",
            "subcategory":"Hardware",
            "type":"Retail Goods"
        }
    ],
    "sg:phone":"+44 1538 361633",
    "sg:postcode":"ST13 7EE",
    "sg:province":"Staffordshire",
    "sg:tags":[
        "sealant",
        "glue",
        "adhesives"
    ],
    "wof:name":"F Ball & Co. Ltd.",
    "wof:placetype":"venue"
},
  "geometry": {"coordinates":[-2.0432031155,53.0643424988],"type":"Point"}
}