{
  "type": "Feature",
  "properties": {
    "addr:full":"35 Bank Street Aberdeen Aberdeen City AB11 7TA",
    "addr:housenumber":"35",
    "addr:postcode":"ab11 7ta",
    "addr:street":"Bank Street",
    "iso:country":"GB",
    "sg:address":"35 Bank Street",
    "sg:city":"Aberdeen",
    "sg:classifiers":[
        {
            "category":"Shopping",
            "subcategory":"News",
            "type":"Retail Goods"
        }
    ],
    "sg:phone":"+44 1224 582000",
    "sg:postcode":"AB11 7TA",
    "sg:province":"Aberdeen City",
    "sg:tags":[
        "newsagent"
    ],
    "wof:name":"Simpson's Newsagency",
    "wof:placetype":"venue"
},
  "geometry": {"coordinates":[-2.100653,57.137989],"type":"Point"}
}