{
  "type": "Feature",
  "properties": {
    "addr:full":"9 High Street Shaftesbury Dorset SP7 8JB",
    "addr:housenumber":"9",
    "addr:postcode":"sp7 8jb",
    "addr:street":"High Street",
    "iso:country":"GB",
    "sg:address":"9 High Street",
    "sg:city":"Shaftesbury",
    "sg:classifiers":[
        {
            "category":"Real Estate",
            "subcategory":"Real Estate Agent",
            "type":"Services"
        }
    ],
    "sg:phone":"+44 1747 852400",
    "sg:postcode":"SP7 8JB",
    "sg:province":"Dorset",
    "wof:name":"Chapman Moore & Mugford",
    "wof:placetype":"venue"
},
  "geometry": {"coordinates":[-2.1979219913,51.0060119629],"type":"Point"}
}