{
  "type": "Feature",
  "properties": {
    "iso:country":"GB",
    "sg:address":"With Penn Hospital, Penn Rd",
    "sg:city":"Wolverhampton",
    "sg:classifiers":[
        {
            "category":"Health Services",
            "subcategory":"Hospital",
            "type":"Services"
        }
    ],
    "sg:phone":"+44 1902 444019",
    "sg:postcode":"WV4 5HN",
    "sg:province":"Staffordshire",
    "wof:name":"Groves Day Hospital",
    "wof:placetype":"venue"
},
  "geometry": {"coordinates":[-2.15919,52.558609],"type":"Point"}
}