{
  "type": "Feature",
  "properties": {
    "iso:country":"GB",
    "sg:address":"106 Highfield Road",
    "sg:city":"Wellingborough",
    "sg:classifiers":[
        {
            "category":"Building & Trades",
            "subcategory":"Landscaping Services",
            "type":"Services"
        }
    ],
    "sg:phone":"+44 1933 278805",
    "sg:postcode":"NN8 1PL",
    "sg:province":"Northamptonshire",
    "sg:tags":[
        "landscape",
        "contractor"
    ],
    "wof:name":"Kingsnorth Landscapes",
    "wof:placetype":"venue"
},
  "geometry": {"coordinates":[-0.683231,52.305786],"type":"Point"}
}