{
  "type": "Feature",
  "properties": {
    "addr:full":"13 Grange Road West Birkenhead Merseyside CH41 4BY",
    "addr:housenumber":"13",
    "addr:postcode":"ch41 4by",
    "addr:street":"Grange Road West",
    "iso:country":"GB",
    "sg:address":"13 Grange Road West",
    "sg:city":"Birkenhead",
    "sg:classifiers":[
        {
            "category":"Home & Garden",
            "subcategory":"Hardware",
            "type":"Retail Goods"
        }
    ],
    "sg:phone":"+44 151 650 1531",
    "sg:postcode":"CH41 4BY",
    "sg:province":"Merseyside",
    "sg:tags":[
        "retailer",
        "lighting"
    ],
    "wof:name":"Grange West Lighting",
    "wof:placetype":"venue"
},
  "geometry": {"coordinates":[-3.031934,53.388836],"type":"Point"}
}