{
  "type": "Feature",
  "properties": {
    "addr:full":"Richmond Court Business Centre, 216 Capstone Rd Bournemouth Dorset BH8 8RX",
    "addr:housenumber":"216",
    "addr:postcode":"bh8 8rx",
    "addr:street":"Richmond;Capstone Rd",
    "iso:country":"GB",
    "sg:address":"Richmond Court Business Centre, 216 Capstone Rd",
    "sg:city":"Bournemouth",
    "sg:classifiers":[
        {
            "category":"Real Estate",
            "subcategory":"Developer",
            "type":"Services"
        }
    ],
    "sg:phone":"+44 1202 776633",
    "sg:postcode":"BH8 8RX",
    "sg:province":"Dorset",
    "sg:tags":[
        "property"
    ],
    "wof:name":"Richmond Court",
    "wof:placetype":"venue"
},
  "geometry": {"coordinates":[-1.8651100397,50.7365493774],"type":"Point"}
}