{
  "type": "Feature",
  "properties": {
    "addr:full":"86 Walkley Road Sheffield South Yorkshire S6 2XP",
    "addr:housenumber":"86",
    "addr:postcode":"s6 2xp",
    "addr:street":"Walkley Road",
    "iso:country":"GB",
    "sg:address":"86 Walkley Road",
    "sg:city":"Sheffield",
    "sg:classifiers":[
        {
            "category":"Building & Trades",
            "subcategory":"Construction",
            "type":"Services"
        }
    ],
    "sg:postcode":"S6 2XP",
    "sg:province":"South Yorkshire",
    "sg:tags":[
        "decorator",
        "painter"
    ],
    "wof:name":"F J Prior & Sons",
    "wof:placetype":"venue"
},
  "geometry": {"coordinates":[-1.498142004,53.3959159851],"type":"Point"}
}