{
  "type": "Feature",
  "properties": {
    "addr:full":"127-129 Portland Road, Hucknall Nottingham Nottinghamshire NG15 7SB",
    "addr:housenumber":"127-129",
    "addr:postcode":"ng15 7sb",
    "addr:street":"Portland Road",
    "iso:country":"GB",
    "sg:address":"127-129 Portland Road, Hucknall",
    "sg:city":"Nottingham",
    "sg:classifiers":[
        {
            "category":"Food & Beverages",
            "subcategory":"Groceries & Convenience Stores",
            "type":"Retail Goods"
        }
    ],
    "sg:phone":"+44 115 956 5701",
    "sg:postcode":"NG15 7SB",
    "sg:province":"Nottinghamshire",
    "wof:name":"R T'S FAMILY SUPERSTORE",
    "wof:placetype":"venue"
},
  "geometry": {"coordinates":[-1.1961380243,53.032207489],"type":"Point"}
}