{
  "type": "Feature",
  "properties": {
    "addr:full":"41a Fore St St Austell Cornwall PL25 5PY",
    "addr:housenumber":"41a",
    "addr:postcode":"pl25 5py",
    "addr:street":"Fore St",
    "iso:country":"GB",
    "sg:address":"41a Fore St",
    "sg:city":"St Austell",
    "sg:classifiers":[
        {
            "category":"Bakery",
            "type":"Food & Drink"
        }
    ],
    "sg:phone":"+44 1726 75805",
    "sg:postcode":"PL25 5PY",
    "sg:province":"Cornwall",
    "sg:tags":[
        "cake",
        "maker"
    ],
    "wof:name":"The Thin End",
    "wof:placetype":"venue"
},
  "geometry": {"coordinates":[-4.794927,50.338123],"type":"Point"}
}