{
  "type": "Feature",
  "properties": {
    "iso:country":"GB",
    "sg:address":"43 Merstow Grn",
    "sg:city":"Evesham",
    "sg:classifiers":[
        {
            "category":"Banks & Credit Unions",
            "subcategory":"Financial Services",
            "type":"Services"
        }
    ],
    "sg:phone":"+44 1386 49900",
    "sg:postcode":"WR11 4BB",
    "sg:province":"Gloucestershire",
    "sg:tags":[
        "adviser"
    ],
    "wof:name":"Fraser Anderson & Partners",
    "wof:placetype":"venue"
},
  "geometry": {"coordinates":[-1.951226,52.092079],"type":"Point"}
}