{
  "type": "Feature",
  "properties": {
    "iso:country":"GB",
    "sg:address":"126 Auckland, Waldridge",
    "sg:city":"Chester-le-street",
    "sg:classifiers":[
        {
            "category":"Building & Trades",
            "subcategory":"Landscaping Services",
            "type":"Services"
        }
    ],
    "sg:postcode":"DH2 2TZ",
    "sg:province":"Durham",
    "sg:tags":[
        "landscape",
        "contractor"
    ],
    "wof:name":"Untidy Gardens",
    "wof:placetype":"venue"
},
  "geometry": {"coordinates":[-1.595702,54.851383],"type":"Point"}
}