{
  "type": "Feature",
  "properties": {
    "iso:country":"GB",
    "sg:address":"Unit 1, 12 Verney Road",
    "sg:city":"London",
    "sg:classifiers":[
        {
            "category":"Retail",
            "subcategory":"Auto Repair",
            "type":"Services"
        }
    ],
    "sg:phone":"+44 20 7394 8599",
    "sg:postcode":"SE16 3DH",
    "sg:province":"Greater London",
    "sg:tags":[
        "modification",
        "garage"
    ],
    "wof:name":"The South London Mot Centre Ltd.",
    "wof:placetype":"venue"
},
  "geometry": {"coordinates":[-0.06307,51.485519],"type":"Point"}
}