{
  "type": "Feature",
  "properties": {
    "iso:country":"GB",
    "sg:address":"Cardross Rd",
    "sg:city":"Dumbarton",
    "sg:classifiers":[
        {
            "category":"Place Of Worship",
            "type":"Public Place"
        }
    ],
    "sg:phone":"+44 1389 732894",
    "sg:postcode":"G82 4JG",
    "sg:province":"Argyll and Bute",
    "wof:name":"St Michaels Church Hall",
    "wof:placetype":"venue"
},
  "geometry": {"coordinates":[-4.586694,55.947868],"type":"Point"}
}