{
  "type": "Feature",
  "properties": {
    "addr:full":"48 Lorne Road, Forest Gate London Greater London E7 0LJ",
    "addr:housenumber":"48",
    "addr:postcode":"e7 0lj",
    "addr:street":"Lorne Road",
    "iso:country":"GB",
    "sg:address":"48 Lorne Road, Forest Gate",
    "sg:city":"London",
    "sg:classifiers":[
        {
            "category":"Shopping",
            "subcategory":"Musical Instruments",
            "type":"Retail Goods"
        }
    ],
    "sg:postcode":"E7 0LJ",
    "sg:province":"Greater London",
    "wof:name":"Philip Ridaut",
    "wof:placetype":"venue"
},
  "geometry": {"coordinates":[0.0327979997,51.5527076721],"type":"Point"}
}