{
  "type": "Feature",
  "properties": {
    "iso:country":"GB",
    "sg:address":"1 Moore Rd, Baglan Indstl Pk, Port Talbot",
    "sg:city":"Swansea",
    "sg:classifiers":[
        {
            "category":"Professional",
            "subcategory":"Computer Services",
            "type":"Services"
        }
    ],
    "sg:phone":"+44 1639 822222",
    "sg:postcode":"SA12 7BJ",
    "sg:province":"Neath Port Talbot",
    "sg:tags":[
        "system",
        "software"
    ],
    "wof:name":"Atlantic Business Systems Ltd",
    "wof:placetype":"venue"
},
  "geometry": {"coordinates":[-3.810688,51.607609],"type":"Point"}
}