{
  "type": "Feature",
  "properties": {
    "addr:full":"Usher Walker House, Datapoint Business Cent, 6 South Crescent London Greater London E16 4TL",
    "addr:housenumber":"6",
    "addr:postcode":"e16 4tl",
    "addr:street":"Walker;Datapoint;Cent;South Crescent",
    "iso:country":"GB",
    "sg:address":"Usher Walker House, Datapoint Business Cent, 6 South Crescent",
    "sg:city":"London",
    "sg:classifiers":[
        {
            "category":"Shopping",
            "subcategory":"Stationery & Office Supplies",
            "type":"Retail Goods"
        }
    ],
    "sg:phone":"+44 20 7712 7121",
    "sg:postcode":"E16 4TL",
    "sg:province":"Greater London",
    "sg:tags":[
        "printers'"
    ],
    "wof:name":"Usher-Walker Ltd.",
    "wof:placetype":"venue"
},
  "geometry": {"coordinates":[-0.00176,51.5205802917],"type":"Point"}
}