{
  "type": "Feature",
  "properties": {
    "addr:full":"15 Nantwich Road Crewe Cheshire CW2 6AF",
    "addr:housenumber":"15",
    "addr:postcode":"cw2 6af",
    "addr:street":"Nantwich Road",
    "iso:country":"GB",
    "sg:address":"15 Nantwich Road",
    "sg:city":"Crewe",
    "sg:classifiers":[
        {
            "category":"Professional",
            "subcategory":"Detective & Security Services",
            "type":"Services"
        }
    ],
    "sg:phone":"+44 1270 583199",
    "sg:postcode":"CW2 6AF",
    "sg:province":"Cheshire",
    "sg:tags":[
        "alarm",
        "burglar",
        "system"
    ],
    "wof:name":"E P G Security Systems",
    "wof:placetype":"venue"
},
  "geometry": {"coordinates":[-2.4368929863,53.08934021],"type":"Point"}
}