{
  "type": "Feature",
  "properties": {
    "addr:full":"116 Dunstable Road Luton Bedfordshire LU1 1EW",
    "addr:housenumber":"116",
    "addr:postcode":"lu1 1ew",
    "addr:street":"Dunstable Road",
    "iso:country":"GB",
    "sg:address":"116 Dunstable Road",
    "sg:city":"Luton",
    "sg:classifiers":[
        {
            "category":"Food & Beverages",
            "subcategory":"Groceries & Convenience Stores",
            "type":"Retail Goods"
        }
    ],
    "sg:phone":"+44 1582 721184",
    "sg:postcode":"LU1 1EW",
    "sg:province":"Bedfordshire",
    "wof:name":"Alhalal Food Store",
    "wof:placetype":"venue"
},
  "geometry": {"coordinates":[-0.4279940128,51.8852386475],"type":"Point"}
}