{
  "type": "Feature",
  "properties": {
    "addr:full":"Stanhope House, Highgate High Street London Greater London N6 5JL",
    "addr:postcode":"n6 5jl",
    "addr:street":"Highgate High Street",
    "iso:country":"GB",
    "sg:address":"Stanhope House, Highgate High Street",
    "sg:city":"London",
    "sg:classifiers":[
        {
            "category":"Shopping",
            "type":"Retail Goods"
        }
    ],
    "sg:phone":"+44 20 8341 7070",
    "sg:postcode":"N6 5JL",
    "sg:province":"Greater London",
    "sg:tags":[
        "bag"
    ],
    "wof:name":"Skyman Sacks & Bags Ltd.",
    "wof:placetype":"venue"
},
  "geometry": {"coordinates":[-0.14533,51.57037],"type":"Point"}
}