{
  "type": "Feature",
  "properties": {
    "iso:country":"GB",
    "sg:address":"23 Castle Road",
    "sg:city":"Falkirk",
    "sg:classifiers":[
        {
            "category":"Professional",
            "subcategory":"Computer Services",
            "type":"Services"
        }
    ],
    "sg:phone":"+44 1324 635081",
    "sg:postcode":"FK2 7XL",
    "sg:province":"Falkirk",
    "sg:tags":[
        "bureau",
        "facility"
    ],
    "wof:name":"Datapoint (U K) Ltd.",
    "wof:placetype":"venue"
},
  "geometry": {"coordinates":[-3.776237,56.012955],"type":"Point"}
}