{
  "type": "Feature",
  "properties": {
    "addr:full":"2 Oxford Close, Greasbrough Rotherham South Yorkshire S61 4PJ",
    "addr:housenumber":"2",
    "addr:postcode":"s61 4pj",
    "addr:street":"Oxford Close",
    "iso:country":"GB",
    "sg:address":"2 Oxford Close, Greasbrough",
    "sg:city":"Rotherham",
    "sg:classifiers":[
        {
            "category":"Retail",
            "subcategory":"Auto Repair",
            "type":"Services"
        }
    ],
    "sg:postcode":"S61 4PJ",
    "sg:province":"South Yorkshire",
    "sg:tags":[
        "modification",
        "garage"
    ],
    "wof:name":"D V Draisey Mobile Mechanic",
    "wof:placetype":"venue"
},
  "geometry": {"coordinates":[-1.366911,53.453377],"type":"Point"}
}