{
  "type": "Feature",
  "properties": {
    "addr:full":"5 Church Terrace Wisbech Cambridgeshire PE13 1BJ",
    "addr:housenumber":"5",
    "addr:postcode":"pe13 1bj",
    "addr:street":"Church Terrace",
    "iso:country":"GB",
    "sg:address":"5 Church Terrace",
    "sg:city":"Wisbech",
    "sg:classifiers":[
        {
            "category":"Real Estate",
            "subcategory":"Real Estate Agent",
            "type":"Services"
        }
    ],
    "sg:phone":"+44 1945 581234",
    "sg:postcode":"PE13 1BJ",
    "sg:province":"Cambridgeshire",
    "wof:name":"Principal Estate Agents Ltd.",
    "wof:placetype":"venue"
},
  "geometry": {"coordinates":[0.1622419953,52.6644439697],"type":"Point"}
}