{
  "type": "Feature",
  "properties": {
    "addr:full":"Royal Crest Ho, 22-26 Upr Mulgrave Rd Sutton Surrey SM2 7AZ",
    "addr:housenumber":"22-26",
    "addr:postcode":"sm2 7az",
    "addr:street":"Royal;Upr Mulgrave Rd",
    "iso:country":"GB",
    "sg:address":"Royal Crest Ho, 22-26 Upr Mulgrave Rd",
    "sg:city":"Sutton",
    "sg:classifiers":[
        {
            "category":"Shopping",
            "subcategory":"Stationery & Office Supplies",
            "type":"Retail Goods"
        }
    ],
    "sg:postcode":"SM2 7AZ",
    "sg:province":"Surrey",
    "wof:name":"J & S Print (Surrey) Ltd",
    "wof:placetype":"venue"
},
  "geometry": {"coordinates":[-0.2156199962,51.3542404175],"type":"Point"}
}