{
  "type": "Feature",
  "properties": {
    "addr:full":"Glovers Lane, Netherton Bootle Merseyside L30 3TL",
    "addr:postcode":"l30 3tl",
    "addr:street":"Glovers Lane",
    "iso:country":"GB",
    "sg:address":"Glovers Lane, Netherton",
    "sg:city":"Bootle",
    "sg:classifiers":[
        {
            "category":"Arts & Performance",
            "subcategory":"Arts Center",
            "type":"Entertainment"
        }
    ],
    "sg:phone":"+44 151 525 0417",
    "sg:postcode":"L30 3TL",
    "sg:province":"Merseyside",
    "sg:tags":[
        "centre"
    ],
    "wof:name":"Netherton Arts Centre",
    "wof:placetype":"venue"
},
  "geometry": {"coordinates":[-2.975839,53.489475],"type":"Point"}
}