{
  "type": "Feature",
  "properties": {
    "addr:full":"Newbiggin Library, Gibson Street Newbiggin-by-the-sea Northumberland NE64 6UZ",
    "addr:postcode":"ne64 6uz",
    "addr:street":"Gibson Street;Northumberland",
    "iso:country":"GB",
    "sg:address":"Newbiggin Library, Gibson Street",
    "sg:city":"Newbiggin-by-the-sea",
    "sg:classifiers":[
        {
            "category":"Education",
            "subcategory":"Library",
            "type":"Public Place"
        }
    ],
    "sg:phone":"+44 1670 818277",
    "sg:postcode":"NE64 6UZ",
    "sg:province":"Northumberland",
    "sg:tags":[
        "book"
    ],
    "wof:name":"Newbiggin By The Sea Library",
    "wof:placetype":"venue"
},
  "geometry": {"coordinates":[-1.5164840221,55.1826667786],"type":"Point"}
}