{
  "type": "Feature",
  "properties": {
    "addr:full":"The Grn, Bearsted Maidstone Kent ME14 4DN",
    "addr:postcode":"me14 4dn",
    "iso:country":"GB",
    "sg:address":"The Grn, Bearsted",
    "sg:city":"Maidstone",
    "sg:classifiers":[
        {
            "category":"Education",
            "subcategory":"Library",
            "type":"Public Place"
        }
    ],
    "sg:phone":"+44 1622 739774",
    "sg:postcode":"ME14 4DN",
    "sg:province":"Kent",
    "sg:tags":[
        "book"
    ],
    "wof:name":"Bearsted Library",
    "wof:placetype":"venue"
},
  "geometry": {"coordinates":[0.5740839839,51.2672576904],"type":"Point"}
}