{
  "type": "Feature",
  "properties": {
    "iso:country":"GB",
    "sg:address":"2a High Street",
    "sg:city":"Yeovil",
    "sg:classifiers":[
        {
            "category":"Shopping",
            "subcategory":"Jewelry",
            "type":"Retail Goods"
        },
        {
            "category":"Shopping",
            "subcategory":"Comic Books",
            "type":"Retail Goods"
        }
    ],
    "sg:phone":"+44 1935 411113",
    "sg:postcode":"BA20 1RE",
    "sg:province":"Somerset",
    "sg:tags":[
        "jeweller",
        "sale",
        "jewellery"
    ],
    "wof:name":"Delor Jewellers",
    "wof:placetype":"venue"
},
  "geometry": {"coordinates":[-2.633425,50.941521],"type":"Point"}
}