{
  "type": "Feature",
  "properties": {
    "iso:country":"GB",
    "sg:address":"37 Middleborough Road, Spon End",
    "sg:city":"Coventry",
    "sg:classifiers":[
        {
            "category":"Shopping",
            "subcategory":"Computers & Home Electronics",
            "type":"Retail Goods"
        },
        {
            "category":"Building & Trades",
            "subcategory":"Construction",
            "type":"Services"
        }
    ],
    "sg:phone":"+44 24 7622 8614",
    "sg:postcode":"CV1 4DG",
    "sg:province":"West Midlands",
    "sg:tags":[
        "supplier",
        "radio",
        "television",
        "erectors",
        "aerial"
    ],
    "wof:name":"C D F Aerial Services",
    "wof:placetype":"venue"
},
  "geometry": {"coordinates":[-1.517406,52.412682],"type":"Point"}
}