{
  "type": "Feature",
  "properties": {
    "iso:country":"GB",
    "sg:address":"42 Hassall Road, Winterley",
    "sg:city":"Sandbach",
    "sg:classifiers":[
        {
            "category":"Home & Garden",
            "subcategory":"Garden Supply",
            "type":"Retail Goods"
        }
    ],
    "sg:phone":"+44 1270 767215",
    "sg:postcode":"CW11 4RJ",
    "sg:province":"Cheshire",
    "sg:tags":[
        "nursery",
        "centre"
    ],
    "wof:name":"Winterley Nursery & Garden Centre",
    "wof:placetype":"venue"
},
  "geometry": {"coordinates":[-2.373776,53.113892],"type":"Point"}
}