{
  "type": "Feature",
  "properties": {
    "addr:full":"Unit 6 Saltley Business Park, Dorset Rd Birmingham West Midlands B8 1BG",
    "addr:housenumber":"unit 6",
    "addr:postcode":"b8 1bg",
    "addr:street":"Saltley Business Park Dorset Rd",
    "iso:country":"GB",
    "sg:address":"Unit 6 Saltley Business Park, Dorset Rd",
    "sg:city":"Birmingham",
    "sg:classifiers":[
        {
            "category":"Shopping",
            "subcategory":"Baby Store",
            "type":"Retail Goods"
        }
    ],
    "sg:phone":"+44 121 327 1422",
    "sg:postcode":"B8 1BG",
    "sg:province":"West Midlands",
    "sg:tags":[
        "nursery",
        "accessory"
    ],
    "wof:name":"Jeenay Ltd",
    "wof:placetype":"venue"
},
  "geometry": {"coordinates":[-1.857419,52.495636],"type":"Point"}
}