{
  "type": "Feature",
  "properties": {
    "iso:country":"GB",
    "sg:address":"3 Byker Bridge",
    "sg:city":"Newcastle Upon Tyne",
    "sg:classifiers":[
        {
            "category":"Taxi",
            "type":"Transportation"
        }
    ],
    "sg:phone":"+44 191 261 2413",
    "sg:postcode":"NE1 2NS",
    "sg:province":"Tyne and Wear",
    "sg:tags":[
        "mini",
        "cab"
    ],
    "wof:name":"Cabmaster",
    "wof:placetype":"venue"
},
  "geometry": {"coordinates":[-1.5942410231,54.9753112793],"type":"Point"}
}