{
  "type": "Feature",
  "properties": {
    "addr:full":"Castle Road Invergordon Highland IV18 0LW",
    "addr:postcode":"iv18 0lw",
    "addr:street":"Castle Road",
    "iso:country":"GB",
    "sg:address":"Castle Road",
    "sg:city":"Invergordon",
    "sg:classifiers":[
        {
            "category":"Professional",
            "subcategory":"Printing & Photocopies",
            "type":"Services"
        }
    ],
    "sg:phone":"+44 1349 853934",
    "sg:postcode":"IV18 0LW",
    "sg:province":"Highland",
    "sg:tags":[
        "printer"
    ],
    "wof:name":"Gospel Truth Press",
    "wof:placetype":"venue"
},
  "geometry": {"coordinates":[-4.1698179245,57.6896820068],"type":"Point"}
}