{
  "type": "Feature",
  "properties": {
    "iso:country":"GB",
    "sg:address":"Clynnog Service Station, Clynnogfawr",
    "sg:city":"Caernarfon",
    "sg:classifiers":[
        {
            "category":"Autos & Motor Vehicles",
            "subcategory":"Automobile Sales",
            "type":"Retail Goods"
        },
        {
            "category":"Retail",
            "subcategory":"Auto Repair",
            "type":"Services"
        }
    ],
    "sg:postcode":"LL54 5PF",
    "sg:province":"Gwynedd",
    "sg:tags":[
        "modification",
        "garage",
        "car"
    ],
    "wof:name":"Swift Motors",
    "wof:placetype":"venue"
},
  "geometry": {"coordinates":[-4.365201,53.020428],"type":"Point"}
}