{
  "type": "Feature",
  "properties": {
    "addr:full":"14 Kipling Close Lowestoft Suffolk NR33 7NZ",
    "addr:housenumber":"14",
    "addr:postcode":"nr33 7nz",
    "addr:street":"Kipling Close",
    "iso:country":"GB",
    "sg:address":"14 Kipling Close",
    "sg:city":"Lowestoft",
    "sg:classifiers":[
        {
            "category":"Professional",
            "subcategory":"Art Services",
            "type":"Services"
        }
    ],
    "sg:postcode":"NR33 7NZ",
    "sg:province":"Suffolk",
    "sg:tags":[
        "photographer"
    ],
    "wof:name":"The Brian Davies Studio",
    "wof:placetype":"venue"
},
  "geometry": {"coordinates":[1.7268879414,52.4200515747],"type":"Point"}
}