{
  "type": "Feature",
  "properties": {
    "iso:country":"GB",
    "sg:address":"Unit 1, Hither Green Industrial Estate",
    "sg:city":"Clevedon",
    "sg:classifiers":[
        {
            "category":"Professional",
            "subcategory":"Engineering",
            "type":"Services"
        }
    ],
    "sg:phone":"+44 1275 793150",
    "sg:postcode":"BS21 6XT",
    "sg:province":"Somerset",
    "sg:tags":[
        "electronic",
        "engineer"
    ],
    "wof:name":"Serco Ltd.",
    "wof:placetype":"venue"
},
  "geometry": {"coordinates":[-2.8400809765,51.4334449768],"type":"Point"}
}