{
  "type": "Feature",
  "properties": {
    "iso:country":"GB",
    "sg:address":"278 Bethnal Green Road",
    "sg:city":"London",
    "sg:classifiers":[
        {
            "category":"Restaurant",
            "type":"Food & Drink"
        }
    ],
    "sg:phone":"+44 20 7739 2140",
    "sg:postcode":"E2 0AG",
    "sg:province":"Greater London",
    "sg:tags":[
        "chinese"
    ],
    "wof:name":"SEA PALACE CHINESE RESTAURANT",
    "wof:placetype":"venue"
},
  "geometry": {"coordinates":[-0.0654959977,51.526222229],"type":"Point"}
}