{
  "type": "Feature",
  "properties": {
    "iso:country":"GB",
    "sg:address":"17 Tansley Hill Road",
    "sg:city":"Dudley",
    "sg:classifiers":[
        {
            "category":"Freight",
            "type":"Transportation"
        }
    ],
    "sg:postcode":"DY2 7EP",
    "sg:province":"West Midlands",
    "sg:tags":[
        "haulage",
        "road"
    ],
    "wof:name":"C J Holland Contracting",
    "wof:placetype":"venue"
},
  "geometry": {"coordinates":[-2.069079,52.504517],"type":"Point"}
}