{
  "type": "Feature",
  "properties": {
    "addr:full":"The Square, High Street, Welton Daventry Northamptonshire NN11 5JP",
    "addr:postcode":"nn11 5jp",
    "addr:street":"The;High Street",
    "iso:country":"GB",
    "sg:address":"The Square, High Street, Welton",
    "sg:city":"Daventry",
    "sg:classifiers":[
        {
            "category":"Retail",
            "subcategory":"Event Space",
            "type":"Services"
        }
    ],
    "sg:phone":"+44 1327 705040",
    "sg:postcode":"NN11 5JP",
    "sg:province":"Northamptonshire",
    "sg:tags":[
        "exhibition",
        "organiser"
    ],
    "wof:name":"Solway Exhibitions Europe Ltd.",
    "wof:placetype":"venue"
},
  "geometry": {"coordinates":[-1.1622389555,52.260433197],"type":"Point"}
}