{
  "type": "Feature",
  "properties": {
    "addr:full":"Thakeham Road, Storrington Pulborough West Sussex RH20 3PP",
    "addr:postcode":"rh20 3pp",
    "addr:street":"Thakeham Road",
    "iso:country":"GB",
    "sg:address":"Thakeham Road, Storrington",
    "sg:city":"Pulborough",
    "sg:classifiers":[
        {
            "category":"Food & Beverages",
            "subcategory":"Fruits & Vegetables",
            "type":"Retail Goods"
        },
        {
            "category":"Food & Beverages",
            "subcategory":"Groceries & Convenience Stores",
            "type":"Retail Goods"
        }
    ],
    "sg:phone":"+44 1903 742424",
    "sg:postcode":"RH20 3PP",
    "sg:province":"West Sussex",
    "sg:tags":[
        "grocer",
        "greengrocer"
    ],
    "wof:name":"Marley Way Stores",
    "wof:placetype":"venue"
},
  "geometry": {"coordinates":[-0.426565,50.945549],"type":"Point"}
}