{
  "type": "Feature",
  "properties": {
    "iso:country":"GB",
    "sg:address":"2 Meadowland",
    "sg:city":"Chichester",
    "sg:classifiers":[
        {
            "category":"Building & Trades",
            "subcategory":"Construction",
            "type":"Services"
        }
    ],
    "sg:phone":"+44 1243 606535",
    "sg:postcode":"PO20 0LA",
    "sg:province":"West Sussex",
    "sg:tags":[
        "builder"
    ],
    "wof:name":"Chapman Associates",
    "wof:placetype":"venue"
},
  "geometry": {"coordinates":[-0.792053,50.729446],"type":"Point"}
}