{
  "type": "Feature",
  "properties": {
    "addr:full":"Brownberrie Lane, Horsforth Leeds West Yorkshire LS18 5SB",
    "addr:postcode":"ls18 5sb",
    "addr:street":"Brownberrie Lane",
    "iso:country":"GB",
    "sg:address":"Brownberrie Lane, Horsforth",
    "sg:city":"Leeds",
    "sg:classifiers":[
        {
            "category":"Arena",
            "subcategory":"Sports Club",
            "type":"Entertainment"
        }
    ],
    "sg:phone":"+44 113 258 1246",
    "sg:postcode":"LS18 5SB",
    "sg:province":"West Yorkshire",
    "wof:name":"Horsforth Cricket Club",
    "wof:placetype":"venue"
},
  "geometry": {"coordinates":[-1.6400289536,53.8490905762],"type":"Point"}
}