{
  "type": "Feature",
  "properties": {
    "addr:full":"Illieston Broxburn City of Edinburgh EH52 5PD",
    "addr:postcode":"eh52 5pd",
    "addr:street":"Illieston",
    "iso:country":"GB",
    "sg:address":"Illieston",
    "sg:city":"Broxburn",
    "sg:classifiers":[
        {
            "category":"Communications",
            "subcategory":"Film & Video Production",
            "type":"Services"
        },
        {
            "category":"Professional",
            "subcategory":"Art Services",
            "type":"Services"
        }
    ],
    "sg:postcode":"EH52 5PD",
    "sg:province":"City of Edinburgh",
    "sg:tags":[
        "illustrator",
        "artist"
    ],
    "wof:name":"COACH HOUSE STUDIO",
    "wof:placetype":"venue"
},
  "geometry": {"coordinates":[-3.4718840122,55.9342346191],"type":"Point"}
}