{
  "type": "Feature",
  "properties": {
    "addr:full":"Bupton, Hilmarton Calne Wiltshire SN11 8SZ",
    "addr:postcode":"sn11 8sz",
    "addr:street":"Hilmarton",
    "iso:country":"GB",
    "sg:address":"Bupton, Hilmarton",
    "sg:city":"Calne",
    "sg:classifiers":[
        {
            "category":"Recreation",
            "subcategory":"Dog Park",
            "type":"Entertainment"
        }
    ],
    "sg:phone":"+44 1249 760360",
    "sg:postcode":"SN11 8SZ",
    "sg:province":"Wiltshire",
    "wof:name":"P V Swadden Greyhound Trainer",
    "wof:placetype":"venue"
},
  "geometry": {"coordinates":[-1.9733769894,51.4774475098],"type":"Point"}
}