{
  "type": "Feature",
  "properties": {
    "iso:country":"GB",
    "sg:address":"156 Steade Road",
    "sg:city":"Sheffield",
    "sg:classifiers":[
        {
            "category":"Education",
            "subcategory":"Library",
            "type":"Public Place"
        },
        {
            "category":"Home & Garden",
            "subcategory":"Furniture",
            "type":"Retail Goods"
        }
    ],
    "sg:phone":"+44 114 255 3139",
    "sg:postcode":"S7 1DU",
    "sg:province":"South Yorkshire",
    "sg:tags":[
        "outlet",
        "reproduction"
    ],
    "wof:name":"Linkdeep Ltd.",
    "wof:placetype":"venue"
},
  "geometry": {"coordinates":[-1.47907,53.361206],"type":"Point"}
}