{
  "type": "Feature",
  "properties": {
    "iso:country":"GB",
    "sg:address":"Nestleton Woodside Farm, Intakes Lane, Turnditch",
    "sg:city":"Belper",
    "sg:classifiers":[
        {
            "category":"Building & Trades",
            "subcategory":"Landscaping Services",
            "type":"Services"
        },
        {
            "category":"Professional",
            "subcategory":"Engineering",
            "type":"Services"
        }
    ],
    "sg:phone":"+44 1335 370491",
    "sg:postcode":"DE56 2LU",
    "sg:province":"Derbyshire",
    "sg:tags":[
        "forestry",
        "design",
        "surgeon",
        "tree",
        "engineer"
    ],
    "wof:name":"Midland Tree Management",
    "wof:placetype":"venue"
},
  "geometry": {"coordinates":[-1.4759819508,53.0286102295],"type":"Point"}
}