{
  "type": "Feature",
  "properties": {
    "iso:country":"GB",
    "sg:address":"2 Castle Of Auchry Cottages, Cuminestown",
    "sg:city":"Turriff",
    "sg:classifiers":[
        {
            "category":"Farming",
            "subcategory":"Farm",
            "type":"Manufacturing & Wholesale Goods"
        }
    ],
    "sg:phone":"+44 1888 544300",
    "sg:postcode":"AB53 5UR",
    "sg:province":"Aberdeenshire",
    "sg:tags":[
        "mixed",
        "crop"
    ],
    "wof:name":"Brian Gordon Pirie & Co.",
    "wof:placetype":"venue"
},
  "geometry": {"coordinates":[-2.33822,57.54361],"type":"Point"}
}