{
  "type": "Feature",
  "properties": {
    "addr:full":"18 Middle March Daventry Northamptonshire NN11 4PQ",
    "addr:housenumber":"18",
    "addr:postcode":"nn11 4pq",
    "addr:street":"Middle March",
    "iso:country":"GB",
    "sg:address":"18 Middle March",
    "sg:city":"Daventry",
    "sg:classifiers":[
        {
            "category":"Professional",
            "subcategory":"Engineering",
            "type":"Services"
        }
    ],
    "sg:phone":"+44 1327 310240",
    "sg:postcode":"NN11 4PQ",
    "sg:province":"Northamptonshire",
    "sg:tags":[
        "precision",
        "engineer"
    ],
    "wof:name":"Central Carbide Tooling",
    "wof:placetype":"venue"
},
  "geometry": {"coordinates":[-1.1545139551,52.25],"type":"Point"}
}