{
  "type": "Feature",
  "properties": {
    "addr:full":"Tarmac Ho, Bournemouth Rd Southampton Hampshire SO53 3ZH",
    "addr:postcode":"so53 3zh",
    "addr:street":"Bournemouth Rd",
    "iso:country":"GB",
    "sg:address":"Tarmac Ho, Bournemouth Rd",
    "sg:city":"Southampton",
    "sg:classifiers":[
        {
            "category":"Professional",
            "subcategory":"Engineering",
            "type":"Services"
        }
    ],
    "sg:phone":"+44 23 8025 2211",
    "sg:postcode":"SO53 3ZH",
    "sg:province":"Hampshire",
    "sg:tags":[
        "contractor",
        "electrical",
        "engineer"
    ],
    "wof:name":"Crown House Engineering",
    "wof:placetype":"venue"
},
  "geometry": {"coordinates":[-1.3904399872,50.9701004028],"type":"Point"}
}