{
  "type": "Feature",
  "properties": {
    "addr:full":"Old Manse Gallery, Victiora Blgs, Clynder Helensburgh Argyll and Bute G84 0QB",
    "addr:postcode":"g84 0qb",
    "iso:country":"GB",
    "sg:address":"Old Manse Gallery, Victiora Blgs, Clynder",
    "sg:city":"Helensburgh",
    "sg:classifiers":[
        {
            "category":"Professional",
            "subcategory":"Art Services",
            "type":"Services"
        }
    ],
    "sg:postcode":"G84 0QB",
    "sg:province":"Argyll and Bute",
    "sg:tags":[
        "picture",
        "restoration",
        "framing"
    ],
    "wof:name":"Camsail Frames",
    "wof:placetype":"venue"
},
  "geometry": {"coordinates":[-4.813109,56.01968],"type":"Point"}
}