{
  "type": "Feature",
  "properties": {
    "addr:full":"Hatfield House Tennis Court, Fore Street Lodge Hatfield Hertfordshire AL9 5NF",
    "addr:postcode":"al9 5nf",
    "addr:street":"Tennis Court Fore Street",
    "iso:country":"GB",
    "sg:address":"Hatfield House Tennis Court, Fore Street Lodge",
    "sg:city":"Hatfield",
    "sg:classifiers":[
        {
            "category":"Arena",
            "subcategory":"Sports Club",
            "type":"Entertainment"
        },
        {
            "category":"Sports & Exercise",
            "subcategory":"Golf",
            "type":"Entertainment"
        }
    ],
    "sg:phone":"+44 1707 273391",
    "sg:postcode":"AL9 5NF",
    "sg:province":"Hertfordshire",
    "wof:name":"Hatfield House Tennis Club Ltd.",
    "wof:placetype":"venue"
},
  "geometry": {"coordinates":[-0.212433,51.762005],"type":"Point"}
}