{
  "type": "Feature",
  "properties": {
    "iso:country":"GB",
    "sg:address":"57 North Parade",
    "sg:city":"Whitley Bay",
    "sg:classifiers":[
        {
            "category":"Bars & Pubs",
            "type":"Food & Drink"
        }
    ],
    "sg:phone":"+44 191 251 5780",
    "sg:postcode":"NE26 1NX",
    "sg:province":"Northumberland",
    "sg:tags":[
        "pubs",
        "inn"
    ],
    "wof:name":"Rio",
    "wof:placetype":"venue"
},
  "geometry": {"coordinates":[-1.4424190521,55.0450210571],"type":"Point"}
}