{
  "type": "Feature",
  "properties": {
    "addr:full":"65-66 Fore Bondgate Bishop Auckland Durham DL14 7PE",
    "addr:housenumber":"65-66",
    "addr:postcode":"dl14 7pe",
    "addr:street":"Fore Bondgate;Auckland",
    "iso:country":"GB",
    "sg:address":"65-66 Fore Bondgate",
    "sg:city":"Bishop Auckland",
    "sg:classifiers":[
        {
            "category":"Bars & Pubs",
            "type":"Food & Drink"
        }
    ],
    "sg:phone":"+44 1388 451606",
    "sg:postcode":"DL14 7PE",
    "sg:province":"Durham",
    "sg:tags":[
        "pubs",
        "inn"
    ],
    "wof:name":"Barmondo",
    "wof:placetype":"venue"
},
  "geometry": {"coordinates":[-1.6748839617,54.6656112671],"type":"Point"}
}