{
  "type": "Feature",
  "properties": {
    "addr:full":"69-70 High Street Oxford Oxfordshire OX1 4BD",
    "addr:housenumber":"69-70",
    "addr:postcode":"ox1 4bd",
    "addr:street":"High Street",
    "iso:country":"GB",
    "sg:address":"69-70 High Street",
    "sg:city":"Oxford",
    "sg:classifiers":[
        {
            "category":"Shopping",
            "subcategory":"Stationery & Office Supplies",
            "type":"Retail Goods"
        },
        {
            "category":"Wholesale",
            "subcategory":"Stationery",
            "type":"Manufacturing & Wholesale Goods"
        }
    ],
    "sg:phone":"+44 1865 241174",
    "sg:postcode":"OX1 4BD",
    "sg:province":"Oxfordshire",
    "sg:tags":[
        "supplier"
    ],
    "sg:website":"http://www.pensplus.co.uk",
    "wof:name":"Pens Plus",
    "wof:placetype":"venue"
},
  "geometry": {"coordinates":[-1.2490149736,51.7522697449],"type":"Point"}
}