{
  "type": "Feature",
  "properties": {
    "addr:full":"23 Broom Road, Shirley Croydon Surrey CR0 8NG",
    "addr:housenumber":"23",
    "addr:postcode":"cr0 8ng",
    "addr:street":"Broom Road",
    "iso:country":"GB",
    "sg:address":"23 Broom Road, Shirley",
    "sg:city":"Croydon",
    "sg:classifiers":[
        {
            "category":"Health Services",
            "subcategory":"Doctor",
            "type":"Services"
        }
    ],
    "sg:postcode":"CR0 8NG",
    "sg:province":"Surrey",
    "sg:tags":[
        "practitioners"
    ],
    "wof:name":"Win T & Singh R Drs",
    "wof:placetype":"venue"
},
  "geometry": {"coordinates":[-0.029407,51.369232],"type":"Point"}
}