{
  "type": "Feature",
  "properties": {
    "iso:country":"GB",
    "sg:address":"Elm House",
    "sg:city":"London",
    "sg:classifiers":[
        {
            "category":"Professional",
            "subcategory":"Management & Consulting",
            "type":"Services"
        }
    ],
    "sg:postcode":"WC2E 9DT",
    "sg:province":"Greater London",
    "sg:tags":[
        "consultant",
        "promotion",
        "direct",
        "sale"
    ],
    "wof:name":"Mercier Gray Ltd.",
    "wof:placetype":"venue"
},
  "geometry": {"coordinates":[-0.087914,51.50737],"type":"Point"}
}