{
  "type": "Feature",
  "properties": {
    "addr:full":"235 Bridge Street West, Newtown Birmingham West Midlands B19 2YU",
    "addr:housenumber":"235",
    "addr:postcode":"b19 2yu",
    "addr:street":"Bridge Street West",
    "iso:country":"GB",
    "sg:address":"235 Bridge Street West, Newtown",
    "sg:city":"Birmingham",
    "sg:classifiers":[
        {
            "category":"Professional",
            "subcategory":"Business Services",
            "type":"Services"
        }
    ],
    "sg:postcode":"B19 2YU",
    "sg:province":"West Midlands",
    "sg:tags":[
        "import",
        "export",
        "agent"
    ],
    "wof:name":"Jain Bros",
    "wof:placetype":"venue"
},
  "geometry": {"coordinates":[-1.900766,52.49419],"type":"Point"}
}