{
  "type": "Feature",
  "properties": {
    "addr:full":"Stonecheck Hall Farm, Crook Gate Lane, Out Rawcliffe Preston Lancashire PR3 6BH",
    "addr:postcode":"pr3 6bh",
    "addr:street":"Crook Gate Lane",
    "iso:country":"GB",
    "sg:address":"Stonecheck Hall Farm, Crook Gate Lane, Out Rawcliffe",
    "sg:city":"Preston",
    "sg:classifiers":[
        {
            "category":"Farming",
            "subcategory":"Livestock Farm",
            "type":"Manufacturing & Wholesale Goods"
        }
    ],
    "sg:postcode":"PR3 6BH",
    "sg:province":"Lancashire",
    "sg:tags":[
        "others"
    ],
    "wof:name":"Austin J & Elizabeth Hollinhurst",
    "wof:placetype":"venue"
},
  "geometry": {"coordinates":[-2.9130818844,53.8711395264],"type":"Point"}
}