{
  "type": "Feature",
  "properties": {
    "addr:full":"Lombard House, 145 Great Charles Street Birmingham West Midlands B3 3JR",
    "addr:housenumber":"145",
    "addr:postcode":"b3 3jr",
    "addr:street":"Great Charles Street",
    "iso:country":"GB",
    "sg:address":"Lombard House, 145 Great Charles Street",
    "sg:city":"Birmingham",
    "sg:classifiers":[
        {
            "category":"Education",
            "subcategory":"Special Training",
            "type":"Public Place"
        }
    ],
    "sg:phone":"+44 121 200 1140",
    "sg:postcode":"B3 3JR",
    "sg:province":"West Midlands",
    "sg:tags":[
        "product",
        "centre"
    ],
    "wof:name":"The Training & Business Group Ltd.",
    "wof:placetype":"venue"
},
  "geometry": {"coordinates":[-1.90437603,52.4820251465],"type":"Point"}
}