{
  "type": "Feature",
  "properties": {
    "iso:country":"GB",
    "sg:address":"Dental Surgery, Eastwood Copse, Aviation Way",
    "sg:city":"Southend On Sea",
    "sg:classifiers":[
        {
            "category":"Health Services",
            "subcategory":"Dentist",
            "type":"Services"
        }
    ],
    "sg:phone":"+44 1702 549595",
    "sg:postcode":"SS2 6UN",
    "sg:province":"Essex",
    "wof:name":"S Chopra",
    "wof:placetype":"venue"
},
  "geometry": {"coordinates":[0.6833900213,51.5731315613],"type":"Point"}
}