{
  "type": "Feature",
  "properties": {
    "addr:full":"Farrar Mill, Farrar Mill Lane, Salterhebble Halifax West Yorkshire HX3 9EU",
    "addr:postcode":"hx3 9eu",
    "addr:street":"Farrar;Farrar Mill Lane",
    "iso:country":"GB",
    "sg:address":"Farrar Mill, Farrar Mill Lane, Salterhebble",
    "sg:city":"Halifax",
    "sg:classifiers":[
        {
            "category":"Retail",
            "subcategory":"Auto Repair",
            "type":"Services"
        },
        {
            "category":"Shopping Center",
            "type":"Public Place"
        }
    ],
    "sg:phone":"+44 1422 340876",
    "sg:postcode":"HX3 9EU",
    "sg:province":"West Yorkshire",
    "sg:tags":[
        "centre",
        "clutch",
        "commercial",
        "brake",
        "vehicle",
        "car"
    ],
    "wof:name":"S A Motors",
    "wof:placetype":"venue"
},
  "geometry": {"coordinates":[-1.8536499739,53.7074813843],"type":"Point"}
}