{
  "type": "Feature",
  "properties": {
    "iso:country":"GB",
    "sg:address":"Sycamore Gardens",
    "sg:city":"Hammersmith",
    "sg:classifiers":[
        {
            "category":"Social Services",
            "subcategory":"Adult Care",
            "type":"Services"
        }
    ],
    "sg:phone":"+44 20 8743 0710",
    "sg:postcode":"W6 0AR",
    "sg:province":"Greater London",
    "sg:tags":[
        "housing",
        "sheltered"
    ],
    "wof:name":"Underwood House Sheltered Housing Unit",
    "wof:placetype":"venue"
},
  "geometry": {"coordinates":[-0.2294200063,51.4961509705],"type":"Point"}
}