{
  "type": "Feature",
  "properties": {
    "addr:full":"28 Tweed Crescent Renfrew Renfrewshire PA4 0UF",
    "addr:housenumber":"28",
    "addr:postcode":"pa4 0uf",
    "addr:street":"Tweed Crescent",
    "iso:country":"GB",
    "sg:address":"28 Tweed Crescent",
    "sg:city":"Renfrew",
    "sg:classifiers":[
        {
            "category":"Building & Trades",
            "subcategory":"Construction",
            "type":"Services"
        }
    ],
    "sg:phone":"+44 141 886 5527",
    "sg:postcode":"PA4 0UF",
    "sg:province":"Renfrewshire",
    "sg:tags":[
        "dry",
        "plastering",
        "plasterers",
        "lining",
        "related",
        "screeders"
    ],
    "wof:name":"A Menzies Plastering",
    "wof:placetype":"venue"
},
  "geometry": {"coordinates":[-4.378309,55.872284],"type":"Point"}
}