{
  "type": "Feature",
  "properties": {
    "iso:country":"GB",
    "sg:address":"10 Sagar Street",
    "sg:city":"Castleford",
    "sg:classifiers":[
        {
            "category":"Home & Garden",
            "subcategory":"Carpets & Floor Coverings",
            "type":"Retail Goods"
        }
    ],
    "sg:phone":"+44 1977 558808",
    "sg:postcode":"WF10 1AF",
    "sg:province":"West Yorkshire",
    "sg:tags":[
        "carpets",
        "rug",
        "matting"
    ],
    "wof:name":"Hales Carpets & Curtains",
    "wof:placetype":"venue"
},
  "geometry": {"coordinates":[-1.351735,53.726711],"type":"Point"}
}