{
  "type": "Feature",
  "properties": {
    "iso:country":"GB",
    "sg:address":"48 Wheel La, Grenoside",
    "sg:city":"Sheffield",
    "sg:classifiers":[
        {
            "category":"Communications",
            "type":"Services"
        }
    ],
    "sg:phone":"+44 114 245 1750",
    "sg:postcode":"S30 3RN",
    "sg:province":"Derbyshire",
    "sg:tags":[
        "telecommunication"
    ],
    "wof:name":"Malscot Ltd",
    "wof:placetype":"venue"
},
  "geometry": {"coordinates":[-1.49555,53.438969],"type":"Point"}
}