{
  "type": "Feature",
  "properties": {
    "addr:full":"25 North Lane Canterbury Kent CT2 7EE",
    "addr:housenumber":"25",
    "addr:postcode":"ct2 7ee",
    "addr:street":"North Lane",
    "iso:country":"GB",
    "sg:address":"25 North Lane",
    "sg:city":"Canterbury",
    "sg:classifiers":[
        {
            "category":"Restaurant",
            "type":"Food & Drink"
        }
    ],
    "sg:postcode":"CT2 7EE",
    "sg:province":"Kent",
    "wof:name":"Anchor House",
    "wof:placetype":"venue"
},
  "geometry": {"coordinates":[1.07709,51.282982],"type":"Point"}
}