{
  "type": "Feature",
  "properties": {
    "addr:full":"22 Main Av Enfield Greater London EN1 1DA",
    "addr:housenumber":"22",
    "addr:postcode":"en1 1da",
    "addr:street":"Main Av",
    "iso:country":"GB",
    "sg:address":"22 Main Av",
    "sg:city":"Enfield",
    "sg:classifiers":[
        {
            "category":"Fast Food",
            "type":"Food & Drink"
        }
    ],
    "sg:phone":"+44 20 8367 5999",
    "sg:postcode":"EN1 1DA",
    "sg:province":"Greater London",
    "sg:tags":[
        "away",
        "take"
    ],
    "wof:name":"Dial A Curry",
    "wof:placetype":"venue"
},
  "geometry": {"coordinates":[-0.069151,51.64518],"type":"Point"}
}