{
  "type": "Feature",
  "properties": {
    "addr:full":"36 Beardsley Road, Edwinstowe Mansfield Nottinghamshire NG21 9LN",
    "addr:housenumber":"36",
    "addr:postcode":"ng21 9ln",
    "addr:street":"Beardsley Road",
    "iso:country":"GB",
    "sg:address":"36 Beardsley Road, Edwinstowe",
    "sg:city":"Mansfield",
    "sg:classifiers":[
        {
            "category":"Building & Trades",
            "subcategory":"Construction",
            "type":"Services"
        }
    ],
    "sg:phone":"+44 1623 823855",
    "sg:postcode":"NG21 9LN",
    "sg:province":"Nottinghamshire",
    "sg:tags":[
        "builder"
    ],
    "wof:name":"Cockayne Builders",
    "wof:placetype":"venue"
},
  "geometry": {"coordinates":[-1.0571609735,53.1869239807],"type":"Point"}
}