{
  "type": "Feature",
  "properties": {
    "addr:full":"Bright Road, Eccles Manchester Greater Manchester M30 0WG",
    "addr:postcode":"m30 0wg",
    "addr:street":"Bright Road",
    "iso:country":"GB",
    "sg:address":"Bright Road, Eccles",
    "sg:city":"Manchester",
    "sg:classifiers":[
        {
            "category":"Organizations",
            "subcategory":"Non-profit Organization",
            "type":"Services"
        }
    ],
    "sg:phone":"+44 161 787 8219",
    "sg:postcode":"M30 0WG",
    "sg:province":"Greater Manchester",
    "sg:tags":[
        "organisation",
        "voluntary",
        "charity"
    ],
    "wof:name":"Salford Link Community Care Project",
    "wof:placetype":"venue"
},
  "geometry": {"coordinates":[-2.3450040817,53.485080719],"type":"Point"}
}