{
  "type": "Feature",
  "properties": {
    "iso:country":"GB",
    "sg:address":"36-40 Upper Manor Road",
    "sg:city":"Paignton",
    "sg:classifiers":[
        {
            "category":"Home & Garden",
            "subcategory":"Building Materials",
            "type":"Retail Goods"
        }
    ],
    "sg:postcode":"TQ3 2TL",
    "sg:province":"Devon",
    "sg:tags":[
        "furnishers",
        "bathroom",
        "planner"
    ],
    "wof:name":"T H S Coral Bathrooms & Kitchens",
    "wof:placetype":"venue"
},
  "geometry": {"coordinates":[-3.563099,50.444565],"type":"Point"}
}