{
  "type": "Feature",
  "properties": {
    "iso:country":"GB",
    "sg:address":"83-85 Crane St",
    "sg:city":"Salisbury",
    "sg:classifiers":[
        {
            "category":"Transit Center",
            "subcategory":"Freight",
            "type":"Transportation"
        }
    ],
    "sg:postcode":"SP1 2PU",
    "sg:province":"Wiltshire",
    "sg:tags":[
        "shop",
        "craft",
        "centre"
    ],
    "wof:name":"Mole Hole Craft Shop",
    "wof:placetype":"venue"
},
  "geometry": {"coordinates":[-1.797904,51.06741],"type":"Point"}
}