{
  "type": "Feature",
  "properties": {
    "iso:country":"GB",
    "sg:address":"Lyons Court",
    "sg:city":"Chatteris",
    "sg:classifiers":[
        {
            "category":"Government",
            "subcategory":"Office",
            "type":"Public Place"
        },
        {
            "category":"Social Services",
            "subcategory":"Adult Care",
            "type":"Services"
        },
        {
            "category":"Social Services",
            "subcategory":"Retirement Home",
            "type":"Services"
        }
    ],
    "sg:phone":"+44 1354 692696",
    "sg:postcode":"PE16 6NJ",
    "sg:province":"Cambridgeshire",
    "sg:tags":[
        "housing",
        "local",
        "accommodation",
        "sheltered"
    ],
    "wof:name":"Sheltered Housing Scheme",
    "wof:placetype":"venue"
},
  "geometry": {"coordinates":[0.048666,52.453632],"type":"Point"}
}