{
  "type": "Feature",
  "properties": {
    "addr:full":"55a Huntspill Road Highbridge Somerset TA9 3DQ",
    "addr:housenumber":"55a",
    "addr:postcode":"ta9 3dq",
    "addr:street":"Huntspill Road",
    "iso:country":"GB",
    "sg:address":"55a Huntspill Road",
    "sg:city":"Highbridge",
    "sg:classifiers":[
        {
            "category":"Autos & Motor Vehicles",
            "subcategory":"Automobile Sales",
            "type":"Retail Goods"
        }
    ],
    "sg:phone":"+44 1278 794200",
    "sg:postcode":"TA9 3DQ",
    "sg:province":"Somerset",
    "sg:tags":[
        "car"
    ],
    "wof:name":"Highbridge Car Centre",
    "wof:placetype":"venue"
},
  "geometry": {"coordinates":[-2.981262,51.2178],"type":"Point"}
}