{
  "type": "Feature",
  "properties": {
    "iso:country":"GB",
    "sg:address":"146 New Cavendish Street",
    "sg:city":"London",
    "sg:classifiers":[
        {
            "category":"Manufacturing",
            "subcategory":"Apparel",
            "type":"Manufacturing & Wholesale Goods"
        }
    ],
    "sg:phone":"+44 20 7323 4535",
    "sg:postcode":"W1W 6YQ",
    "sg:province":"Greater London",
    "sg:tags":[
        "garment",
        "designer"
    ],
    "wof:name":"Modernmove Ltd.",
    "wof:placetype":"venue"
},
  "geometry": {"coordinates":[-0.140158,51.520439],"type":"Point"}
}