{
  "type": "Feature",
  "properties": {
    "addr:full":"18 Newlands Close Brighouse West Yorkshire HD6 3RJ",
    "addr:housenumber":"18",
    "addr:postcode":"hd6 3rj",
    "addr:street":"Newlands Close",
    "iso:country":"GB",
    "sg:address":"18 Newlands Close",
    "sg:city":"Brighouse",
    "sg:classifiers":[
        {
            "category":"Personal",
            "type":"Services"
        }
    ],
    "sg:postcode":"HD6 3RJ",
    "sg:province":"West Yorkshire",
    "sg:tags":[
        "dating",
        "friendship",
        "agency"
    ],
    "wof:name":"Cupid Dating Service",
    "wof:placetype":"venue"
},
  "geometry": {"coordinates":[-1.7775529623,53.6971092224],"type":"Point"}
}