{
  "type": "Feature",
  "properties": {
    "addr:full":"32 Dover St West End Hampshire W1X 3RA",
    "addr:housenumber":"32",
    "addr:postcode":"w1x 3ra",
    "addr:street":"Dover St",
    "iso:country":"GB",
    "sg:address":"32 Dover St",
    "sg:city":"West End",
    "sg:classifiers":[
        {
            "category":"Wholesale",
            "subcategory":"Books, Periodicals, & Newspapers",
            "type":"Manufacturing & Wholesale Goods"
        }
    ],
    "sg:phone":"+44 20 7409 1165",
    "sg:postcode":"W1X 3RA",
    "sg:province":"Hampshire",
    "sg:tags":[
        "publishing"
    ],
    "wof:name":"Jeremy Hunt",
    "wof:placetype":"venue"
},
  "geometry": {"coordinates":[-0.1430760026,51.5090293884],"type":"Point"}
}