{
  "type": "Feature",
  "properties": {
    "addr:full":"71 Willow Road Bromsgrove Worcestershire B61 8PU",
    "addr:housenumber":"71",
    "addr:postcode":"b61 8pu",
    "addr:street":"Willow Road",
    "iso:country":"GB",
    "sg:address":"71 Willow Road",
    "sg:city":"Bromsgrove",
    "sg:classifiers":[
        {
            "category":"Professional",
            "subcategory":"Accounting & Tax Preparation",
            "type":"Services"
        }
    ],
    "sg:postcode":"B61 8PU",
    "sg:province":"Worcestershire",
    "sg:tags":[
        "accountant"
    ],
    "wof:name":"Graham R Brickstock & Associates",
    "wof:placetype":"venue"
},
  "geometry": {"coordinates":[-2.07006,52.336338],"type":"Point"}
}