{
  "type": "Feature",
  "properties": {
    "iso:country":"GB",
    "sg:address":"134 Wick Street, Wick",
    "sg:city":"Littlehampton",
    "sg:classifiers":[
        {
            "category":"Fast Food",
            "type":"Food & Drink"
        }
    ],
    "sg:phone":"+44 1903 716453",
    "sg:postcode":"BN17 7JT",
    "sg:province":"West Sussex",
    "sg:tags":[
        "away",
        "meal",
        "outlet",
        "take"
    ],
    "wof:name":"Sun Wah",
    "wof:placetype":"venue"
},
  "geometry": {"coordinates":[-0.543721,50.819984],"type":"Point"}
}