{
  "type": "Feature",
  "properties": {
    "iso:country":"GB",
    "sg:address":"47 Marlborough Road, Irlam",
    "sg:city":"Manchester",
    "sg:classifiers":[
        {
            "category":"Building & Trades",
            "subcategory":"Construction",
            "type":"Services"
        }
    ],
    "sg:postcode":"M44 6HH",
    "sg:province":"Greater Manchester",
    "sg:tags":[
        "decorator",
        "painter"
    ],
    "wof:name":"J S Ravenscroft",
    "wof:placetype":"venue"
},
  "geometry": {"coordinates":[-2.4102270603,53.454914093],"type":"Point"}
}