{
  "type": "Feature",
  "properties": {
    "iso:country":"GB",
    "sg:address":"177a Sunderland Road",
    "sg:city":"South Shields",
    "sg:classifiers":[
        {
            "category":"Food & Beverages",
            "subcategory":"Fruits & Vegetables",
            "type":"Retail Goods"
        }
    ],
    "sg:postcode":"NE34 6AD",
    "sg:province":"Tyne and Wear",
    "sg:tags":[
        "greengrocer"
    ],
    "wof:name":"M & J Tomas",
    "wof:placetype":"venue"
},
  "geometry": {"coordinates":[-1.41328,54.977478],"type":"Point"}
}