{
  "type": "Feature",
  "properties": {
    "addr:full":"Flint Barns, Ham Farm, Main Road, Bosham Chichester West Sussex PO18 8EH",
    "addr:postcode":"po18 8eh",
    "addr:street":"Main Road",
    "iso:country":"GB",
    "sg:address":"Flint Barns, Ham Farm, Main Road, Bosham",
    "sg:city":"Chichester",
    "sg:classifiers":[
        {
            "category":"Real Estate",
            "subcategory":"Architect",
            "type":"Services"
        }
    ],
    "sg:phone":"+44 1243 576611",
    "sg:postcode":"PO18 8EH",
    "sg:province":"West Sussex",
    "wof:name":"Douglas Briggs Partnership",
    "wof:placetype":"venue"
},
  "geometry": {"coordinates":[-0.8361,50.838421],"type":"Point"}
}