{
  "type": "Feature",
  "properties": {
    "addr:full":"30 Shifford Cres Maidenhead Berkshire SL6 7UW",
    "addr:housenumber":"30",
    "addr:postcode":"sl6 7uw",
    "addr:street":"Shifford Cres",
    "iso:country":"GB",
    "sg:address":"30 Shifford Cres",
    "sg:city":"Maidenhead",
    "sg:classifiers":[
        {
            "category":"Retail",
            "subcategory":"Driving School",
            "type":"Services"
        }
    ],
    "sg:phone":"+44 1628 639093",
    "sg:postcode":"SL6 7UW",
    "sg:province":"Berkshire",
    "wof:name":"Ken Smith's Driving School",
    "wof:placetype":"venue"
},
  "geometry": {"coordinates":[-0.7278349996,51.5404167175],"type":"Point"}
}