{
  "type": "Feature",
  "properties": {
    "iso:country":"GB",
    "sg:address":"1249 Govan Road",
    "sg:city":"Glasgow",
    "sg:classifiers":[
        {
            "category":"Autos & Motor Vehicles",
            "subcategory":"Fuel & Gas Station",
            "type":"Retail Goods"
        }
    ],
    "sg:phone":"+44 141 445 5701",
    "sg:postcode":"G51 4PL",
    "sg:province":"Glasgow City",
    "sg:tags":[
        "petrol",
        "filling"
    ],
    "wof:name":"Save Service Station Ltd.",
    "wof:placetype":"venue"
},
  "geometry": {"coordinates":[-4.3339099884,55.8644180298],"type":"Point"}
}