{
  "type": "Feature",
  "properties": {
    "iso:country":"GB",
    "sg:address":"Unit 31, Station Arcade, Vicarage Fields",
    "sg:city":"Barking",
    "sg:classifiers":[
        {
            "category":"Shopping",
            "subcategory":"Beauty & Cosmetics",
            "type":"Retail Goods"
        }
    ],
    "sg:phone":"+44 20 8594 1604",
    "sg:postcode":"IG11 8DQ",
    "sg:province":"Essex",
    "wof:name":"James Leigh Ltd.",
    "wof:placetype":"venue"
},
  "geometry": {"coordinates":[0.0816849992,51.5395698547],"type":"Point"}
}