{
  "type": "Feature",
  "properties": {
    "addr:full":"9 Coundon Road Coventry West Midlands CV1 4AR",
    "addr:housenumber":"9",
    "addr:postcode":"cv1 4ar",
    "addr:street":"Coundon Road",
    "iso:country":"GB",
    "sg:address":"9 Coundon Road",
    "sg:city":"Coventry",
    "sg:classifiers":[
        {
            "category":"Travel",
            "subcategory":"Hotels & Motels",
            "type":"Entertainment"
        }
    ],
    "sg:phone":"+44 24 7622 5998",
    "sg:postcode":"CV1 4AR",
    "sg:province":"West Midlands",
    "sg:tags":[
        "house",
        "guest"
    ],
    "wof:name":"Mount Guest House",
    "wof:placetype":"venue"
},
  "geometry": {"coordinates":[-1.5200409889,52.411441803],"type":"Point"}
}