{
  "type": "Feature",
  "properties": {
    "addr:full":"26 Brixton Water Lane London Greater London SW2 1PE",
    "addr:housenumber":"26",
    "addr:postcode":"sw2 1pe",
    "addr:street":"Brixton Water Lane",
    "iso:country":"GB",
    "sg:address":"26 Brixton Water Lane",
    "sg:city":"London",
    "sg:classifiers":[
        {
            "category":"Bars & Pubs",
            "type":"Food & Drink"
        }
    ],
    "sg:phone":"+44 20 7501 9133",
    "sg:postcode":"SW2 1PE",
    "sg:province":"Greater London",
    "sg:tags":[
        "pubs",
        "inn"
    ],
    "wof:name":"J S Off Licence",
    "wof:placetype":"venue"
},
  "geometry": {"coordinates":[-0.113462,51.455063],"type":"Point"}
}