{
  "type": "Feature",
  "properties": {
    "iso:country":"GB",
    "sg:address":"18 Queen Anne St",
    "sg:city":"London",
    "sg:classifiers":[
        {
            "category":"Building & Trades",
            "subcategory":"Construction",
            "type":"Services"
        }
    ],
    "sg:postcode":"W1G 8HZ",
    "sg:province":"Greater London",
    "sg:tags":[
        "glazier"
    ],
    "wof:name":"Oaklodge Ltd",
    "wof:placetype":"venue"
},
  "geometry": {"coordinates":[-0.146719,51.517986],"type":"Point"}
}