{
  "type": "Feature",
  "properties": {
    "addr:full":"1897 Leek Road Stoke-on-trent Staffordshire ST2 7AQ",
    "addr:housenumber":"1897",
    "addr:postcode":"st2 7aq",
    "addr:street":"Leek Road",
    "iso:country":"GB",
    "sg:address":"1897 Leek Road",
    "sg:city":"Stoke-on-trent",
    "sg:classifiers":[
        {
            "category":"Shopping",
            "subcategory":"Pets & Pet Supplies",
            "type":"Retail Goods"
        }
    ],
    "sg:phone":"+44 1782 536826",
    "sg:postcode":"ST2 7AQ",
    "sg:province":"Staffordshire",
    "wof:name":"Milton Pet Store",
    "wof:placetype":"venue"
},
  "geometry": {"coordinates":[-2.140344,53.049007],"type":"Point"}
}