{
  "type": "Feature",
  "properties": {
    "addr:full":"27 Shales Rd Southampton Hampshire SO18 6NQ",
    "addr:housenumber":"27",
    "addr:postcode":"so18 6nq",
    "addr:street":"Shales Rd",
    "iso:country":"GB",
    "sg:address":"27 Shales Rd",
    "sg:city":"Southampton",
    "sg:classifiers":[
        {
            "category":"Place Of Worship",
            "type":"Public Place"
        },
        {
            "category":"Organizations",
            "subcategory":"Religious Organization",
            "type":"Services"
        }
    ],
    "sg:phone":"+44 23 8046 3219",
    "sg:postcode":"SO18 6NQ",
    "sg:province":"Hampshire",
    "sg:tags":[
        "organisation"
    ],
    "wof:name":"Sisters Of Charity",
    "wof:placetype":"venue"
},
  "geometry": {"coordinates":[-1.3518300056,50.91771698],"type":"Point"}
}