{
  "type": "Feature",
  "properties": {
    "iso:country":"GB",
    "sg:address":"449 Foleshill Road",
    "sg:city":"Coventry",
    "sg:classifiers":[
        {
            "category":"Professional",
            "subcategory":"Lawyer & Legal Services",
            "type":"Services"
        }
    ],
    "sg:phone":"+44 24 7668 6123",
    "sg:postcode":"CV6 5AQ",
    "sg:province":"Warwickshire",
    "sg:tags":[
        "advice",
        "counselling"
    ],
    "wof:name":"Foleshill Information & Advice Centre",
    "wof:placetype":"venue"
},
  "geometry": {"coordinates":[-1.500623,52.427212],"type":"Point"}
}