{
  "type": "Feature",
  "properties": {
    "iso:country":"GB",
    "sg:address":"Unit 3, 160 Chapel Street",
    "sg:city":"Tiverton",
    "sg:classifiers":[
        {
            "category":"Retail",
            "subcategory":"Auto Repair",
            "type":"Services"
        }
    ],
    "sg:postcode":"EX16 6DF",
    "sg:province":"Devon",
    "sg:tags":[
        "modification",
        "garage"
    ],
    "wof:name":"W Radford",
    "wof:placetype":"venue"
},
  "geometry": {"coordinates":[-3.4792220592,50.9072952271],"type":"Point"}
}