{
  "type": "Feature",
  "properties": {
    "iso:country":"GB",
    "sg:address":"1 Chapleton Mains Farm",
    "sg:city":"West Kilbride",
    "sg:classifiers":[
        {
            "category":"Freight",
            "type":"Transportation"
        }
    ],
    "sg:phone":"+44 1294 823202",
    "sg:postcode":"KA23 9LU",
    "sg:province":"North Ayrshire",
    "sg:tags":[
        "haulage",
        "road"
    ],
    "wof:name":"John Young & Son",
    "wof:placetype":"venue"
},
  "geometry": {"coordinates":[-4.861939,55.685421],"type":"Point"}
}