{
  "type": "Feature",
  "properties": {
    "addr:full":"South Mill House, Amesbury Salisbury Hampshire SP4 7HR",
    "addr:postcode":"sp4 7hr",
    "addr:street":"South Mill House Amesbury",
    "iso:country":"GB",
    "sg:address":"South Mill House, Amesbury",
    "sg:city":"Salisbury",
    "sg:classifiers":[
        {
            "category":"Health Services",
            "subcategory":"Health Practitioner",
            "type":"Services"
        }
    ],
    "sg:phone":"+44 1980 622051",
    "sg:postcode":"SP4 7HR",
    "sg:province":"Hampshire",
    "sg:tags":[
        "physiotherapist"
    ],
    "wof:name":"Mrs C Thompson MCSP SRP",
    "wof:placetype":"venue"
},
  "geometry": {"coordinates":[-1.765319,51.171021],"type":"Point"}
}