{
  "type": "Feature",
  "properties": {
    "iso:country":"GB",
    "sg:address":"The Drive",
    "sg:city":"Northwood",
    "sg:classifiers":[
        {
            "category":"Sports & Exercise",
            "subcategory":"Golf",
            "type":"Entertainment"
        }
    ],
    "sg:phone":"+44 1923 825224",
    "sg:postcode":"HA6 1HN",
    "sg:province":"Greater London",
    "sg:tags":[
        "club",
        "course"
    ],
    "wof:name":"Haste Hill Golf Course",
    "wof:placetype":"venue"
},
  "geometry": {"coordinates":[-0.420484,51.604397],"type":"Point"}
}