{
  "type": "Feature",
  "properties": {
    "iso:country":"GB",
    "sg:address":"Bright Street Garage, Bright Street",
    "sg:city":"Bury",
    "sg:classifiers":[
        {
            "category":"Retail",
            "subcategory":"Auto Repair",
            "type":"Services"
        }
    ],
    "sg:phone":"+44 161 763 1712",
    "sg:postcode":"BL9 6AQ",
    "sg:province":"Lancashire",
    "sg:tags":[
        "modification",
        "garage"
    ],
    "wof:name":"C C Motors",
    "wof:placetype":"venue"
},
  "geometry": {"coordinates":[-2.2839939594,53.598865509],"type":"Point"}
}