{
  "type": "Feature",
  "properties": {
    "addr:full":"27 Romford Road, Stratford London Greater London E15 4LJ",
    "addr:housenumber":"27",
    "addr:postcode":"e15 4lj",
    "addr:street":"Romford Road",
    "iso:country":"GB",
    "sg:address":"27 Romford Road, Stratford",
    "sg:city":"London",
    "sg:classifiers":[
        {
            "category":"Real Estate",
            "subcategory":"Real Estate Agent",
            "type":"Services"
        }
    ],
    "sg:postcode":"E15 4LJ",
    "sg:province":"Greater London",
    "wof:name":"Dovedale Property Management Limited",
    "wof:placetype":"venue"
},
  "geometry": {"coordinates":[0.006266,51.542381],"type":"Point"}
}