{
  "type": "Feature",
  "properties": {
    "addr:full":"6 Royal Parade Harrogate North Yorkshire HG1 2SZ",
    "addr:housenumber":"6",
    "addr:postcode":"hg1 2sz",
    "addr:street":"Royal Parade",
    "iso:country":"GB",
    "sg:address":"6 Royal Parade",
    "sg:city":"Harrogate",
    "sg:classifiers":[
        {
            "category":"Restaurant",
            "type":"Food & Drink"
        }
    ],
    "sg:phone":"+44 1423 507930",
    "sg:postcode":"HG1 2SZ",
    "sg:province":"North Yorkshire",
    "wof:name":"Market Town Taverns",
    "wof:placetype":"venue"
},
  "geometry": {"coordinates":[-1.545884,53.993214],"type":"Point"}
}