{
  "type": "Feature",
  "properties": {
    "iso:country":"GB",
    "sg:address":"The Workshop, 9 High Street, Collingham",
    "sg:city":"Newark",
    "sg:classifiers":[
        {
            "category":"Professional",
            "subcategory":"Engineering",
            "type":"Services"
        }
    ],
    "sg:postcode":"NG23 7LA",
    "sg:province":"Lincolnshire",
    "sg:tags":[
        "engineer",
        "mechanical"
    ],
    "wof:name":"Fine-Align Ltd.",
    "wof:placetype":"venue"
},
  "geometry": {"coordinates":[-0.7602030039,53.1459388733],"type":"Point"}
}