{
  "type": "Feature",
  "properties": {
    "iso:country":"GB",
    "sg:address":"14 High St",
    "sg:city":"Loughborough",
    "sg:classifiers":[
        {
            "category":"Home & Garden",
            "subcategory":"Building Materials",
            "type":"Retail Goods"
        }
    ],
    "sg:phone":"+44 1509 815512",
    "sg:postcode":"LE12 7RX",
    "sg:province":"Leicestershire",
    "sg:tags":[
        "garage",
        "door"
    ],
    "wof:name":"Amber Royal Doors",
    "wof:placetype":"venue"
},
  "geometry": {"coordinates":[-1.110977,52.730228],"type":"Point"}
}