{
  "type": "Feature",
  "properties": {
    "iso:country":"GB",
    "sg:address":"Newington Enterprise Centre, Wardwell Lane, Lower Halstow",
    "sg:city":"Sittingbourne",
    "sg:classifiers":[
        {
            "category":"Building & Trades",
            "subcategory":"Construction",
            "type":"Services"
        }
    ],
    "sg:postcode":"ME9 7ER",
    "sg:province":"Kent",
    "sg:tags":[
        "worker",
        "metal"
    ],
    "wof:name":"K V Fabrication",
    "wof:placetype":"venue"
},
  "geometry": {"coordinates":[0.6686099768,51.373790741],"type":"Point"}
}