{
  "type": "Feature",
  "properties": {
    "iso:country":"GB",
    "sg:address":"Baten Bush Farm Bungalow",
    "sg:city":"Carlisle",
    "sg:classifiers":[
        {
            "category":"Farming",
            "subcategory":"Dairy Farm",
            "type":"Manufacturing & Wholesale Goods"
        }
    ],
    "sg:phone":"+44 1228 791258",
    "sg:postcode":"CA6 5NW",
    "sg:province":"Cumbria",
    "wof:name":"Glenzier Estate",
    "wof:placetype":"venue"
},
  "geometry": {"coordinates":[-2.98944,55.036049],"type":"Point"}
}