{
  "type": "Feature",
  "properties": {
    "addr:full":"51 High Street, Chobham Woking Surrey GU24 8AF",
    "addr:housenumber":"51",
    "addr:postcode":"gu24 8af",
    "addr:street":"High Street",
    "iso:country":"GB",
    "sg:address":"51 High Street, Chobham",
    "sg:city":"Woking",
    "sg:classifiers":[
        {
            "category":"Building & Trades",
            "subcategory":"Construction",
            "type":"Services"
        }
    ],
    "sg:phone":"+44 1276 855282",
    "sg:postcode":"GU24 8AF",
    "sg:province":"Surrey",
    "sg:tags":[
        "builder"
    ],
    "wof:name":"William Davies Ltd.",
    "wof:placetype":"venue"
},
  "geometry": {"coordinates":[-0.60386,51.346458],"type":"Point"}
}