{
  "type": "Feature",
  "properties": {
    "addr:full":"350a Ashley Road Poole Dorset BH14 0AR",
    "addr:housenumber":"350a",
    "addr:postcode":"bh14 0ar",
    "addr:street":"Ashley Road",
    "iso:country":"GB",
    "sg:address":"350a Ashley Road",
    "sg:city":"Poole",
    "sg:classifiers":[
        {
            "category":"Recreation",
            "type":"Entertainment"
        }
    ],
    "sg:phone":"+44 1202 777147",
    "sg:postcode":"BH14 0AR",
    "sg:province":"Dorset",
    "sg:tags":[
        "snooker",
        "billiards",
        "pool"
    ],
    "wof:name":"Parkstone Snooker Club",
    "wof:placetype":"venue"
},
  "geometry": {"coordinates":[-1.93688,50.728828],"type":"Point"}
}