{
  "type": "Feature",
  "properties": {
    "iso:country":"GB",
    "sg:address":"Street House Farm, Great North Road, Sinderby",
    "sg:city":"Thirsk",
    "sg:classifiers":[
        {
            "category":"Banks & Credit Unions",
            "subcategory":"Bank",
            "type":"Services"
        }
    ],
    "sg:postcode":"YO7 4LQ",
    "sg:province":"North Yorkshire",
    "sg:tags":[
        "broker",
        "mortgage"
    ],
    "wof:name":"Howard Pickersgill",
    "wof:placetype":"venue"
},
  "geometry": {"coordinates":[-1.4731919765,54.2315292358],"type":"Point"}
}