{
  "type": "Feature",
  "properties": {
    "addr:full":"Unit 1, The Kilshaw Centre, Lamberhead Industrial Estate Wigan Lancashire WN5 8EA",
    "addr:housenumber":"unit 1",
    "addr:postcode":"wn5 8ea",
    "addr:street":"The Kilshaw;Industrial Estate",
    "iso:country":"GB",
    "sg:address":"Unit 1, The Kilshaw Centre, Lamberhead Industrial Estate",
    "sg:city":"Wigan",
    "sg:classifiers":[
        {
            "category":"Professional",
            "subcategory":"Engineering",
            "type":"Services"
        }
    ],
    "sg:phone":"+44 1942 227257",
    "sg:postcode":"WN5 8EA",
    "sg:province":"Lancashire",
    "wof:name":"Projects Procurement & Services Ltd.",
    "wof:placetype":"venue"
},
  "geometry": {"coordinates":[-2.675549984,53.5343894958],"type":"Point"}
}