{
  "type": "Feature",
  "properties": {
    "addr:full":"10-14 Hainton Av Grimsby Lincolnshire DN32 9BB",
    "addr:housenumber":"10-14",
    "addr:postcode":"dn32 9bb",
    "addr:street":"Hainton Av",
    "iso:country":"GB",
    "sg:address":"10-14 Hainton Av",
    "sg:city":"Grimsby",
    "sg:classifiers":[
        {
            "category":"Government",
            "subcategory":"Office",
            "type":"Public Place"
        }
    ],
    "sg:phone":"+44 1472 342981",
    "sg:postcode":"DN32 9BB",
    "sg:province":"Lincolnshire",
    "sg:tags":[
        "chamber",
        "commerce"
    ],
    "wof:name":"Chamber Of Commerce & Shipping",
    "wof:placetype":"venue"
},
  "geometry": {"coordinates":[-0.07524,53.566322],"type":"Point"}
}