{
  "type": "Feature",
  "properties": {
    "addr:full":"Unit 9/10 Llanelli Workshops, Trostre Industrial Park Llanelli Carmarthenshire SA14 9UU",
    "addr:housenumber":"unit 9 / 10",
    "addr:postcode":"sa14 9uu",
    "addr:street":"Llanelli Workshops Trostre Industrial Park",
    "iso:country":"GB",
    "sg:address":"Unit 9/10 Llanelli Workshops, Trostre Industrial Park",
    "sg:city":"Llanelli",
    "sg:classifiers":[
        {
            "category":"Sports & Exercise",
            "subcategory":"Sports Center",
            "type":"Entertainment"
        }
    ],
    "sg:phone":"+44 1554 754662",
    "sg:postcode":"SA14 9UU",
    "sg:province":"Carmarthenshire",
    "sg:tags":[
        "shop",
        "good"
    ],
    "wof:name":"Picton Sports",
    "wof:placetype":"venue"
},
  "geometry": {"coordinates":[-4.1462,51.678478],"type":"Point"}
}