{
  "type": "Feature",
  "properties": {
    "addr:full":"2 - 18 Glasgow Road, Blantyre Glasgow South Lanarkshire G72 0LE",
    "addr:housenumber":"18",
    "addr:postcode":"g72 0le",
    "addr:street":"2;Glasgow Road",
    "iso:country":"GB",
    "sg:address":"2 - 18 Glasgow Road, Blantyre",
    "sg:city":"Glasgow",
    "sg:classifiers":[
        {
            "category":"Wholesale",
            "subcategory":"Scrap",
            "type":"Manufacturing & Wholesale Goods"
        }
    ],
    "sg:phone":"+44 1698 823126",
    "sg:postcode":"G72 0LE",
    "sg:province":"South Lanarkshire",
    "sg:tags":[
        "waste",
        "metal"
    ],
    "wof:name":"Duncan Brothers",
    "wof:placetype":"venue"
},
  "geometry": {"coordinates":[-4.0770788193,55.7887191772],"type":"Point"}
}