{
  "type": "Feature",
  "properties": {
    "addr:full":"Biwater House, Station Approach Dorking Surrey RH4 1TZ",
    "addr:postcode":"rh4 1tz",
    "addr:street":"Station Approach",
    "iso:country":"GB",
    "sg:address":"Biwater House, Station Approach",
    "sg:city":"Dorking",
    "sg:classifiers":[
        {
            "category":"Utilities",
            "subcategory":"Water",
            "type":"Services"
        },
        {
            "category":"Military Area",
            "subcategory":"Air Force Base",
            "type":"Public Place"
        }
    ],
    "sg:phone":"+44 1306 740740",
    "sg:postcode":"RH4 1TZ",
    "sg:province":"Surrey",
    "sg:tags":[
        "treatment"
    ],
    "wof:name":"Biwater Plc",
    "wof:placetype":"venue"
},
  "geometry": {"coordinates":[-0.3288139999,51.233341217],"type":"Point"}
}