{
  "type": "Feature",
  "properties": {
    "addr:full":"34 Spear Road, Portswood Southampton Hampshire SO14 6UH",
    "addr:housenumber":"34",
    "addr:postcode":"so14 6uh",
    "addr:street":"Spear Road",
    "iso:country":"GB",
    "sg:address":"34 Spear Road, Portswood",
    "sg:city":"Southampton",
    "sg:classifiers":[
        {
            "category":"Professional",
            "subcategory":"Engineering",
            "type":"Services"
        }
    ],
    "sg:phone":"+44 23 8032 2650",
    "sg:postcode":"SO14 6UH",
    "sg:province":"Hampshire",
    "sg:tags":[
        "contractor",
        "electrical",
        "engineer"
    ],
    "wof:name":"L C Kittow & Co. Ltd.",
    "wof:placetype":"venue"
},
  "geometry": {"coordinates":[-1.3971149921,50.9209632874],"type":"Point"}
}