{
  "type": "Feature",
  "properties": {
    "iso:country":"GB",
    "sg:address":"1 College Road",
    "sg:city":"Harrogate",
    "sg:classifiers":[
        {
            "category":"Building & Trades",
            "subcategory":"Cleaning & Sanitation",
            "type":"Services"
        }
    ],
    "sg:postcode":"HG2 0AQ",
    "sg:province":"North Yorkshire",
    "sg:tags":[
        "cleaner",
        "window"
    ],
    "wof:name":"Interclean",
    "wof:placetype":"venue"
},
  "geometry": {"coordinates":[-1.5575489998,53.9817810059],"type":"Point"}
}