{
  "type": "Feature",
  "properties": {
    "iso:country":"GB",
    "sg:address":"229 Wrythe Lane",
    "sg:city":"Carshalton",
    "sg:classifiers":[
        {
            "category":"Building & Trades",
            "subcategory":"Construction",
            "type":"Services"
        }
    ],
    "sg:postcode":"SM5 1UA",
    "sg:province":"Surrey",
    "sg:tags":[
        "decorator",
        "painter"
    ],
    "wof:name":"C J Webb",
    "wof:placetype":"venue"
},
  "geometry": {"coordinates":[-0.179585,51.378925],"type":"Point"}
}