{
  "type": "Feature",
  "properties": {
    "iso:country":"GB",
    "sg:address":"52 Dorchester Park, Sandymoor",
    "sg:city":"Runcorn",
    "sg:classifiers":[
        {
            "category":"Communications",
            "type":"Services"
        }
    ],
    "sg:postcode":"WA7 1QB",
    "sg:province":"Cheshire",
    "sg:tags":[
        "data",
        "network"
    ],
    "wof:name":"Obitex Data Services Ltd",
    "wof:placetype":"venue"
},
  "geometry": {"coordinates":[-2.660776,53.34399],"type":"Point"}
}