{
  "type": "Feature",
  "properties": {
    "addr:full":"Roding La Buckhurst Hill Essex IG9 6BJ",
    "addr:postcode":"ig9 6bj",
    "addr:street":"Roding La Buckhurst Hill",
    "iso:country":"GB",
    "sg:address":"Roding La",
    "sg:city":"Buckhurst Hill",
    "sg:classifiers":[
        {
            "category":"Personal",
            "subcategory":"Day Spa",
            "type":"Services"
        }
    ],
    "sg:phone":"+44 20 8500 8324",
    "sg:postcode":"IG9 6BJ",
    "sg:province":"Essex",
    "sg:tags":[
        "whirlpool"
    ],
    "wof:name":"Sanctuary Spar",
    "wof:placetype":"venue"
},
  "geometry": {"coordinates":[0.053135,51.627312],"type":"Point"}
}