{
  "type": "Feature",
  "properties": {
    "addr:full":"82-84 Charles Street Milford Haven Pembrokeshire SA73 2HE",
    "addr:housenumber":"82-84",
    "addr:postcode":"sa73 2he",
    "addr:street":"Charles Street",
    "iso:country":"GB",
    "sg:address":"82-84 Charles Street",
    "sg:city":"Milford Haven",
    "sg:classifiers":[
        {
            "category":"Shopping",
            "subcategory":"Gifts & Souvenirs",
            "type":"Retail Goods"
        }
    ],
    "sg:phone":"+44 1646 697111",
    "sg:postcode":"SA73 2HE",
    "sg:province":"Pembrokeshire",
    "sg:tags":[
        "shop"
    ],
    "wof:name":"Foster-Powell (Milford Haven) Ltd.",
    "wof:placetype":"venue"
},
  "geometry": {"coordinates":[-5.0348510742,51.7127952576],"type":"Point"}
}