{
  "type": "Feature",
  "properties": {
    "addr:full":"19 Stanley Way Orpington Kent BR5 2HE",
    "addr:housenumber":"19",
    "addr:postcode":"br5 2he",
    "addr:street":"Stanley Way",
    "iso:country":"GB",
    "sg:address":"19 Stanley Way",
    "sg:city":"Orpington",
    "sg:classifiers":[
        {
            "category":"Retail",
            "subcategory":"Laundry & Dry Cleaning",
            "type":"Services"
        }
    ],
    "sg:phone":"+44 1689 834209",
    "sg:postcode":"BR5 2HE",
    "sg:province":"Kent",
    "sg:tags":[
        "alteration"
    ],
    "wof:name":"Savage,Michael,",
    "wof:placetype":"venue"
},
  "geometry": {"coordinates":[0.106584,51.390438],"type":"Point"}
}