{
  "type": "Feature",
  "properties": {
    "addr:full":"116 Hackney Road London Greater London E2 7QL",
    "addr:housenumber":"116",
    "addr:postcode":"e2 7ql",
    "addr:street":"Hackney Road",
    "iso:country":"GB",
    "sg:address":"116 Hackney Road",
    "sg:city":"London",
    "sg:classifiers":[
        {
            "category":"Bars & Pubs",
            "type":"Food & Drink"
        },
        {
            "category":"Community Center",
            "subcategory":"Social",
            "type":"Public Place"
        }
    ],
    "sg:phone":"+44 20 7739 9397",
    "sg:postcode":"E2 7QL",
    "sg:province":"Greater London",
    "sg:tags":[
        "pubs",
        "house",
        "inn",
        "activity"
    ],
    "wof:name":"The Joiners Arms",
    "wof:placetype":"venue"
},
  "geometry": {"coordinates":[-0.074723,51.52953],"type":"Point"}
}