{
  "type": "Feature",
  "properties": {
    "iso:country":"GB",
    "sg:address":"10 Brent Lane",
    "sg:city":"Dartford",
    "sg:classifiers":[
        {
            "category":"Personal",
            "type":"Services"
        }
    ],
    "sg:phone":"+44 1322 274691",
    "sg:postcode":"DA1 1QW",
    "sg:province":"Kent",
    "sg:tags":[
        "wedding"
    ],
    "wof:name":"Fabrics For Brides",
    "wof:placetype":"venue"
},
  "geometry": {"coordinates":[0.2247390002,51.4409751892],"type":"Point"}
}