{
  "type": "Feature",
  "properties": {
    "iso:country":"GB",
    "sg:address":"Newhaven, Forest Road, Whitehill",
    "sg:city":"Bordon",
    "sg:classifiers":[
        {
            "category":"Home & Garden",
            "subcategory":"Furniture",
            "type":"Retail Goods"
        }
    ],
    "sg:postcode":"GU35 9BA",
    "sg:province":"Hampshire",
    "wof:name":"Richard Eade & Son",
    "wof:placetype":"venue"
},
  "geometry": {"coordinates":[-0.865114,51.108856],"type":"Point"}
}