{
  "type": "Feature",
  "properties": {
    "addr:full":"76 Newton Road, Mumbles Swansea Swansea SA3 4BE",
    "addr:housenumber":"76",
    "addr:postcode":"sa3 4be",
    "addr:street":"Newton Road",
    "iso:country":"GB",
    "sg:address":"76 Newton Road, Mumbles",
    "sg:city":"Swansea",
    "sg:classifiers":[
        {
            "category":"Real Estate",
            "subcategory":"Real Estate Agent",
            "type":"Services"
        }
    ],
    "sg:phone":"+44 1792 360060",
    "sg:postcode":"SA3 4BE",
    "sg:province":"Swansea",
    "wof:name":"John Francis Property Services",
    "wof:placetype":"venue"
},
  "geometry": {"coordinates":[-4.0038928986,51.575466156],"type":"Point"}
}