{
  "type": "Feature",
  "properties": {
    "addr:full":"123 Kingsway, Church Accrington Lancashire BB5 5EL",
    "addr:housenumber":"123",
    "addr:postcode":"bb5 5el",
    "addr:street":"Kingsway Church Accrington",
    "iso:country":"GB",
    "sg:address":"123 Kingsway, Church",
    "sg:city":"Accrington",
    "sg:classifiers":[
        {
            "category":"Building & Trades",
            "subcategory":"Construction",
            "type":"Services"
        }
    ],
    "sg:phone":"+44 1254 399624",
    "sg:postcode":"BB5 5EL",
    "sg:province":"Lancashire",
    "sg:tags":[
        "builder"
    ],
    "wof:name":"Stephen Whittaker",
    "wof:placetype":"venue"
},
  "geometry": {"coordinates":[-2.3750081062,53.7640037537],"type":"Point"}
}