{
  "type": "Feature",
  "properties": {
    "addr:full":"17 Woodyard Close, Mulbarton Norwich Norfolk NR14 8AS",
    "addr:housenumber":"17",
    "addr:postcode":"nr14 8as",
    "addr:street":"Woodyard Close;Norwich",
    "iso:country":"GB",
    "sg:address":"17 Woodyard Close, Mulbarton",
    "sg:city":"Norwich",
    "sg:classifiers":[
        {
            "category":"Professional",
            "subcategory":"Credit Reporting & Collection",
            "type":"Services"
        }
    ],
    "sg:phone":"+44 1508 570069",
    "sg:postcode":"NR14 8AS",
    "sg:province":"Norfolk",
    "sg:tags":[
        "collecting",
        "agency"
    ],
    "wof:name":"K & K Recoveries",
    "wof:placetype":"venue"
},
  "geometry": {"coordinates":[1.238514,52.55798],"type":"Point"}
}