{
  "type": "Feature",
  "properties": {
    "iso:country":"GB",
    "sg:address":"Brandlehow Road",
    "sg:city":"London",
    "sg:classifiers":[
        {
            "category":"Education",
            "subcategory":"School",
            "type":"Public Place"
        }
    ],
    "sg:phone":"+44 20 8874 5429",
    "sg:postcode":"SW15 2ED",
    "sg:province":"Greater London",
    "sg:tags":[
        "local",
        "authority"
    ],
    "wof:name":"Brandlehow School",
    "wof:placetype":"venue"
},
  "geometry": {"coordinates":[-0.207152,51.46146],"type":"Point"}
}