{
  "type": "Feature",
  "properties": {
    "iso:country":"GB",
    "sg:address":"25 Glentworth Avenue",
    "sg:city":"Coventry",
    "sg:classifiers":[
        {
            "category":"Health Services",
            "subcategory":"Health Practitioner",
            "type":"Services"
        }
    ],
    "sg:postcode":"CV6 2HU",
    "sg:province":"Warwickshire",
    "sg:tags":[
        "psychotherapist"
    ],
    "wof:name":"Cynthia Sunderland",
    "wof:placetype":"venue"
},
  "geometry": {"coordinates":[-1.523648,52.442684],"type":"Point"}
}