{
  "type": "Feature",
  "properties": {
    "addr:full":"Norwood House, Low Lane Keighley North Yorkshire BD22 0LE",
    "addr:postcode":"bd22 0le",
    "addr:street":"Low Lane",
    "iso:country":"GB",
    "sg:address":"Norwood House, Low Lane",
    "sg:city":"Keighley",
    "sg:classifiers":[
        {
            "category":"Personal",
            "subcategory":"Skin Care",
            "type":"Services"
        }
    ],
    "sg:phone":"+44 1535 632418",
    "sg:postcode":"BD22 0LE",
    "sg:province":"North Yorkshire",
    "sg:tags":[
        "leather",
        "merchant"
    ],
    "wof:name":"J Woods Leather",
    "wof:placetype":"venue"
},
  "geometry": {"coordinates":[-2.0476379395,53.9017829895],"type":"Point"}
}