{
  "type": "Feature",
  "properties": {
    "iso:country":"GB",
    "sg:address":"Peter Pal House, High Street, Oadby",
    "sg:city":"Leicester",
    "sg:classifiers":[
        {
            "category":"Home & Garden",
            "subcategory":"Carpets & Floor Coverings",
            "type":"Retail Goods"
        },
        {
            "category":"Military Area",
            "subcategory":"Air Force Base",
            "type":"Public Place"
        }
    ],
    "sg:phone":"+44 116 271 4923",
    "sg:postcode":"LE2 5DE",
    "sg:province":"Leicestershire",
    "sg:tags":[
        "mnfr",
        "trimming",
        "trimmer"
    ],
    "wof:name":"The Neo Knitting Co. Ltd.",
    "wof:placetype":"venue"
},
  "geometry": {"coordinates":[-1.0799889565,52.5988197327],"type":"Point"}
}