{
  "type": "Feature",
  "properties": {
    "iso:country":"GB",
    "sg:address":"14 High Cross Street",
    "sg:city":"St. Austell",
    "sg:classifiers":[
        {
            "category":"Organizations",
            "subcategory":"Non-profit Organization",
            "type":"Services"
        }
    ],
    "sg:phone":"+44 1726 63770",
    "sg:postcode":"PL25 4AN",
    "sg:province":"Cornwall",
    "sg:tags":[
        "organisation",
        "voluntary",
        "charity"
    ],
    "wof:name":"Womens Royal Voluntary Service",
    "wof:placetype":"venue"
},
  "geometry": {"coordinates":[-4.790342,50.338558],"type":"Point"}
}