{
  "type": "Feature",
  "properties": {
    "addr:full":"Phoenix Business Centre, Bow Common La London Greater London E3 4AX",
    "addr:postcode":"e3 4ax",
    "iso:country":"GB",
    "sg:address":"Phoenix Business Centre, Bow Common La",
    "sg:city":"London",
    "sg:classifiers":[
        {
            "category":"Personal",
            "type":"Services"
        }
    ],
    "sg:phone":"+44 171 538 4003",
    "sg:postcode":"E3 4AX",
    "sg:province":"Greater London",
    "sg:tags":[
        "tailor"
    ],
    "wof:name":"Liberty Fashions Ltd",
    "wof:placetype":"venue"
},
  "geometry": {"coordinates":[-0.0219930001,51.5168762207],"type":"Point"}
}