{
  "type": "Feature",
  "properties": {
    "addr:full":"4 King Edward Terrace, Gisburn Road Barrowford Nelson Lancashire BB9 8NJ",
    "addr:housenumber":"4",
    "addr:postcode":"bb9 8nj",
    "addr:street":"King Edward Terrace Gisburn Road",
    "iso:country":"GB",
    "sg:address":"4 King Edward Terrace, Gisburn Road Barrowford",
    "sg:city":"Nelson",
    "sg:classifiers":[
        {
            "category":"Retail",
            "subcategory":"Storage",
            "type":"Services"
        }
    ],
    "sg:postcode":"BB9 8NJ",
    "sg:province":"Lancashire",
    "sg:tags":[
        "vault",
        "safe"
    ],
    "wof:name":"Barrowford Safe & Lock Services",
    "wof:placetype":"venue"
},
  "geometry": {"coordinates":[-2.218169,53.84687],"type":"Point"}
}