{
  "type": "Feature",
  "properties": {
    "iso:country":"GB",
    "sg:address":"48 Heath Road, Holmewood",
    "sg:city":"Chesterfield",
    "sg:classifiers":[
        {
            "category":"Health Services",
            "subcategory":"Nursing And Care Facility",
            "type":"Services"
        }
    ],
    "sg:postcode":"S42 5SW",
    "sg:province":"Derbyshire",
    "sg:tags":[
        "home"
    ],
    "wof:name":"Westlea",
    "wof:placetype":"venue"
},
  "geometry": {"coordinates":[-1.355462,53.187984],"type":"Point"}
}