{
  "type": "Feature",
  "properties": {
    "iso:country":"GB",
    "sg:address":"Unit 4-6, Old Tannery Buildings, Haverigg",
    "sg:city":"Millom",
    "sg:classifiers":[
        {
            "category":"Arena",
            "subcategory":"Sports Club",
            "type":"Entertainment"
        }
    ],
    "sg:phone":"+44 1229 775149",
    "sg:postcode":"LA18 4NA",
    "sg:province":"Cumbria",
    "wof:name":"Millom Gymnastic Club",
    "wof:placetype":"venue"
},
  "geometry": {"coordinates":[-3.291439,54.197498],"type":"Point"}
}