{
  "type": "Feature",
  "properties": {
    "iso:country":"GB",
    "sg:address":"Kenbridge Road, New Galloway",
    "sg:city":"Castle Douglas",
    "sg:classifiers":[
        {
            "category":"Banks & Credit Unions",
            "subcategory":"Bank",
            "type":"Services"
        }
    ],
    "sg:phone":"+44 1556 502999",
    "sg:postcode":"DG7 3RP",
    "sg:province":"Dumfries and Galloway",
    "wof:name":"Clydesdale Bank Plc",
    "wof:placetype":"venue"
},
  "geometry": {"coordinates":[-4.141488,55.07592],"type":"Point"}
}