{
  "type": "Feature",
  "properties": {
    "addr:full":"Kings Nympton Umberleigh Devon EX37 9ST",
    "addr:postcode":"ex37 9st",
    "iso:country":"GB",
    "sg:address":"Kings Nympton",
    "sg:city":"Umberleigh",
    "sg:classifiers":[
        {
            "category":"Bars & Pubs",
            "type":"Food & Drink"
        }
    ],
    "sg:postcode":"EX37 9ST",
    "sg:province":"Devon",
    "sg:tags":[
        "pubs",
        "inn"
    ],
    "wof:name":"Grove Inn",
    "wof:placetype":"venue"
},
  "geometry": {"coordinates":[-3.9853448868,50.9958152771],"type":"Point"}
}