{
  "type": "Feature",
  "properties": {
    "iso:country":"GB",
    "sg:address":"Annan Careers Office, Ednam Street",
    "sg:city":"Annan",
    "sg:classifiers":[
        {
            "category":"Professional",
            "subcategory":"Employment Agencies",
            "type":"Services"
        }
    ],
    "sg:phone":"+44 1461 204916",
    "sg:postcode":"DG12 6EF",
    "sg:province":"Dumfries and Galloway",
    "sg:tags":[
        "career",
        "guidance"
    ],
    "wof:name":"Career Development Services",
    "wof:placetype":"venue"
},
  "geometry": {"coordinates":[-3.256819,54.987034],"type":"Point"}
}