{
  "type": "Feature",
  "properties": {
    "iso:country":"GB",
    "sg:address":"24 Blendon Drive",
    "sg:city":"Andover",
    "sg:classifiers":[
        {
            "category":"Professional",
            "subcategory":"Management & Consulting",
            "type":"Services"
        },
        {
            "category":"Organizations",
            "subcategory":"Community Association",
            "type":"Services"
        }
    ],
    "sg:phone":"+44 1264 352450",
    "sg:postcode":"SP10 3NQ",
    "sg:province":"Hampshire",
    "sg:tags":[
        "consultant",
        "relation",
        "public",
        "business"
    ],
    "wof:name":"Two Shires Marketing",
    "wof:placetype":"venue"
},
  "geometry": {"coordinates":[-1.506086,51.214088],"type":"Point"}
}