{
  "type": "Feature",
  "properties": {
    "iso:country":"GB",
    "sg:address":"44 St Annes Crescent",
    "sg:city":"Lewes",
    "sg:classifiers":[
        {
            "category":"Education",
            "subcategory":"Library",
            "type":"Public Place"
        }
    ],
    "sg:phone":"+44 1273 481538",
    "sg:postcode":"BN7 1SQ",
    "sg:province":"East Sussex",
    "sg:tags":[
        "book"
    ],
    "wof:name":"County Library Headquarters",
    "wof:placetype":"venue"
},
  "geometry": {"coordinates":[-0.001044,50.872425],"type":"Point"}
}