{
  "type": "Feature",
  "properties": {
    "iso:country":"GB",
    "sg:address":"1 Bridgend",
    "sg:city":"Looe",
    "sg:classifiers":[
        {
            "category":"Military Area",
            "subcategory":"Air Force Base",
            "type":"Public Place"
        }
    ],
    "sg:phone":"+44 1503 262405",
    "sg:postcode":"PL13 2AD",
    "sg:province":"Cornwall",
    "sg:tags":[
        "taxi",
        "hire",
        "private"
    ],
    "wof:name":"Looe Taxis",
    "wof:placetype":"venue"
},
  "geometry": {"coordinates":[-4.516562,50.356358],"type":"Point"}
}