{
  "type": "Feature",
  "properties": {
    "addr:full":"Northway, Queens Rd Newbury Berkshire RG14 7NF",
    "addr:postcode":"rg14 7nf",
    "addr:street":"Northway Queens Rd",
    "iso:country":"GB",
    "sg:address":"Northway, Queens Rd",
    "sg:city":"Newbury",
    "sg:classifiers":[
        {
            "category":"Autos & Motor Vehicles",
            "subcategory":"Fuel & Gas Station",
            "type":"Retail Goods"
        }
    ],
    "sg:phone":"+44 1635 40348",
    "sg:postcode":"RG14 7NF",
    "sg:province":"Berkshire",
    "sg:tags":[
        "petrol",
        "filling"
    ],
    "wof:name":"Davies & Co",
    "wof:placetype":"venue"
},
  "geometry": {"coordinates":[-1.316659,51.396992],"type":"Point"}
}