{
  "type": "Feature",
  "properties": {
    "iso:country":"GB",
    "sg:address":"26 New Street",
    "sg:city":"Dudley",
    "sg:classifiers":[
        {
            "category":"Fast Food",
            "type":"Food & Drink"
        }
    ],
    "sg:phone":"+44 1384 236271",
    "sg:postcode":"DY1 1LP",
    "sg:province":"West Midlands",
    "sg:tags":[
        "away",
        "take"
    ],
    "wof:name":"Pars Pizza",
    "wof:placetype":"venue"
},
  "geometry": {"coordinates":[-2.082556,52.511539],"type":"Point"}
}