{
  "type": "Feature",
  "properties": {
    "addr:full":"155-157a Clapham High Street London Greater London SW4 7SY",
    "addr:housenumber":"155-157a",
    "addr:postcode":"sw4 7sy",
    "addr:street":"Clapham High Street",
    "iso:country":"GB",
    "sg:address":"155-157a Clapham High Street",
    "sg:city":"London",
    "sg:classifiers":[
        {
            "category":"Autos & Motor Vehicles",
            "subcategory":"Fuel & Gas Station",
            "type":"Retail Goods"
        }
    ],
    "sg:postcode":"SW4 7SY",
    "sg:province":"Greater London",
    "sg:tags":[
        "petrol",
        "filling"
    ],
    "wof:name":"Goodstone Limited",
    "wof:placetype":"venue"
},
  "geometry": {"coordinates":[-0.1373939961,51.462020874],"type":"Point"}
}