{
  "type": "Feature",
  "properties": {
    "addr:full":"Ithon View Llandrindod Wells Powys LD1 6SF",
    "addr:postcode":"ld1 6sf",
    "iso:country":"GB",
    "sg:address":"Ithon View",
    "sg:city":"Llandrindod Wells",
    "sg:classifiers":[
        {
            "category":"Recreation",
            "type":"Entertainment"
        }
    ],
    "sg:phone":"+44 1597 851221",
    "sg:postcode":"LD1 6SF",
    "sg:province":"Powys",
    "sg:tags":[
        "outdoor",
        "pursuit"
    ],
    "wof:name":"British Outdoor Professionals Association",
    "wof:placetype":"venue"
},
  "geometry": {"coordinates":[-3.3658390045,52.2908210754],"type":"Point"}
}