{
  "type": "Feature",
  "properties": {
    "addr:full":"39 Morton Way, Southgate London Greater London N14 7HS",
    "addr:housenumber":"39",
    "addr:postcode":"n14 7hs",
    "addr:street":"Morton Way",
    "iso:country":"GB",
    "sg:address":"39 Morton Way, Southgate",
    "sg:city":"London",
    "sg:classifiers":[
        {
            "category":"Building & Trades",
            "subcategory":"Electrical",
            "type":"Services"
        }
    ],
    "sg:postcode":"N14 7HS",
    "sg:province":"Greater London",
    "sg:tags":[
        "lighting"
    ],
    "wof:name":"K A S Lighting Services Ltd.",
    "wof:placetype":"venue"
},
  "geometry": {"coordinates":[-0.126583,51.61898],"type":"Point"}
}