{
  "type": "Feature",
  "properties": {
    "addr:full":"1 Chatsworth Road Morecambe Lancashire LA4 4JF",
    "addr:housenumber":"1",
    "addr:postcode":"la4 4jf",
    "addr:street":"Chatsworth Road",
    "iso:country":"GB",
    "sg:address":"1 Chatsworth Road",
    "sg:city":"Morecambe",
    "sg:classifiers":[
        {
            "category":"Travel",
            "subcategory":"Hotels & Motels",
            "type":"Entertainment"
        }
    ],
    "sg:phone":"+44 1524 412845",
    "sg:postcode":"LA4 4JF",
    "sg:province":"Lancashire",
    "wof:name":"Harwood House Hotel",
    "wof:placetype":"venue"
},
  "geometry": {"coordinates":[-2.875180006,54.0670547485],"type":"Point"}
}