{
  "type": "Feature",
  "properties": {
    "iso:country":"GB",
    "sg:address":"90 Palmerston Road",
    "sg:city":"London",
    "sg:classifiers":[
        {
            "category":"Fast Food",
            "type":"Food & Drink"
        }
    ],
    "sg:postcode":"E17 6PZ",
    "sg:province":"Greater London",
    "sg:tags":[
        "away",
        "take"
    ],
    "wof:name":"Brucies Takeaway",
    "wof:placetype":"venue"
},
  "geometry": {"coordinates":[-0.029182,51.586212],"type":"Point"}
}