{
  "type": "Feature",
  "properties": {
    "addr:full":"16 High Street, Kincardine Clackmannan Clackmannanshire FK10 4JG",
    "addr:housenumber":"16",
    "addr:postcode":"fk10 4jg",
    "addr:street":"High Street",
    "iso:country":"GB",
    "sg:address":"16 High Street, Kincardine",
    "sg:city":"Clackmannan",
    "sg:classifiers":[
        {
            "category":"Farming",
            "subcategory":"Livestock Farm",
            "type":"Manufacturing & Wholesale Goods"
        }
    ],
    "sg:phone":"+44 1259 731405",
    "sg:postcode":"FK10 4JG",
    "sg:province":"Clackmannanshire",
    "sg:tags":[
        "breeder"
    ],
    "wof:name":"Fay Miller",
    "wof:placetype":"venue"
},
  "geometry": {"coordinates":[-3.75407,56.107471],"type":"Point"}
}