{
  "type": "Feature",
  "properties": {
    "addr:full":"Causeway End, Felsted Dunmow Essex CM6 3EY",
    "addr:housenumber":"felsted",
    "addr:postcode":"cm6 3ey",
    "addr:street":"Causeway;Dunmow",
    "iso:country":"GB",
    "sg:address":"Causeway End, Felsted",
    "sg:city":"Dunmow",
    "sg:classifiers":[
        {
            "category":"Bars & Pubs",
            "type":"Food & Drink"
        }
    ],
    "sg:phone":"+44 1371 820998",
    "sg:postcode":"CM6 3EY",
    "sg:province":"Essex",
    "sg:tags":[
        "pubs",
        "inn"
    ],
    "wof:name":"Yew Tree Inn",
    "wof:placetype":"venue"
},
  "geometry": {"coordinates":[0.43375,51.855976],"type":"Point"}
}