{
  "type": "Feature",
  "properties": {
    "addr:full":"The Whitwick Business Centre, Stenson Road Coalville Leicestershire LE67 4JP",
    "addr:postcode":"le67 4jp",
    "addr:street":"Stenson Road",
    "iso:country":"GB",
    "sg:address":"The Whitwick Business Centre, Stenson Road",
    "sg:city":"Coalville",
    "sg:classifiers":[
        {
            "category":"Banks & Credit Unions",
            "subcategory":"Financial Services",
            "type":"Services"
        }
    ],
    "sg:phone":"+44 1530 276174",
    "sg:postcode":"LE67 4JP",
    "sg:province":"Leicestershire",
    "sg:tags":[
        "consultant"
    ],
    "wof:name":"H S Finance Ltd.",
    "wof:placetype":"venue"
},
  "geometry": {"coordinates":[-1.3723059893,52.7187843323],"type":"Point"}
}