{
  "type": "Feature",
  "properties": {
    "addr:full":"Information Bureau One, Bee North St Martock Somerset TA12 6DH",
    "addr:postcode":"ta12 6dh",
    "addr:street":"North St",
    "iso:country":"GB",
    "sg:address":"Information Bureau One, Bee North St",
    "sg:city":"Martock",
    "sg:classifiers":[
        {
            "category":"Professional",
            "subcategory":"Computer Services",
            "type":"Services"
        }
    ],
    "sg:postcode":"TA12 6DH",
    "sg:province":"Somerset",
    "sg:tags":[
        "information"
    ],
    "wof:name":"Callaghan,Lynn,",
    "wof:placetype":"venue"
},
  "geometry": {"coordinates":[-2.7706689835,50.9672470093],"type":"Point"}
}