{
  "type": "Feature",
  "properties": {
    "addr:full":"1 Retreat Rd Richmond Greater London TW9 1NN",
    "addr:housenumber":"1",
    "addr:postcode":"tw9 1nn",
    "addr:street":"Retreat Rd",
    "iso:country":"GB",
    "sg:address":"1 Retreat Rd",
    "sg:city":"Richmond",
    "sg:classifiers":[
        {
            "category":"Place Of Worship",
            "type":"Public Place"
        }
    ],
    "sg:phone":"+44 20 8878 2809",
    "sg:postcode":"TW9 1NN",
    "sg:province":"Greater London",
    "wof:name":"Religious Society Of Friends Quakers",
    "wof:placetype":"venue"
},
  "geometry": {"coordinates":[-0.308687,51.459881],"type":"Point"}
}