{
  "type": "Feature",
  "properties": {
    "addr:full":"Woodland Road, Cockerton Green Darlington Durham DL3 9AA",
    "addr:postcode":"dl3 9aa",
    "addr:street":"Woodland Road Cockerton Green",
    "iso:country":"GB",
    "sg:address":"Woodland Road, Cockerton Green",
    "sg:city":"Darlington",
    "sg:classifiers":[
        {
            "category":"Education",
            "subcategory":"Library",
            "type":"Public Place"
        }
    ],
    "sg:phone":"+44 1325 461320",
    "sg:postcode":"DL3 9AA",
    "sg:province":"Durham",
    "sg:tags":[
        "book"
    ],
    "wof:name":"Cockerton Library",
    "wof:placetype":"venue"
},
  "geometry": {"coordinates":[-1.5736190081,54.53125],"type":"Point"}
}