{
  "type": "Feature",
  "properties": {
    "addr:full":"Denbigh Street Llanrwst Conwy LL26 0LL",
    "addr:postcode":"ll26 0ll",
    "addr:street":"Denbigh Street",
    "iso:country":"GB",
    "sg:address":"Denbigh Street",
    "sg:city":"Llanrwst",
    "sg:classifiers":[
        {
            "category":"Bars & Pubs",
            "type":"Food & Drink"
        },
        {
            "category":"Community Center",
            "subcategory":"Social",
            "type":"Public Place"
        },
        {
            "category":"Travel",
            "subcategory":"Hotels & Motels",
            "type":"Entertainment"
        }
    ],
    "sg:phone":"+44 1492 640272",
    "sg:postcode":"LL26 0LL",
    "sg:province":"Conwy",
    "sg:tags":[
        "pubs",
        "house",
        "inn",
        "activity"
    ],
    "wof:name":"Albion Hotel",
    "wof:placetype":"venue"
},
  "geometry": {"coordinates":[-3.796854,53.139015],"type":"Point"}
}