{
  "type": "Feature",
  "properties": {
    "iso:country":"GB",
    "sg:address":"Unit 34, Britten Road",
    "sg:city":"Reading",
    "sg:classifiers":[
        {
            "category":"Manufacturing",
            "subcategory":"Building Materials",
            "type":"Manufacturing & Wholesale Goods"
        }
    ],
    "sg:phone":"+44 118 975 3377",
    "sg:postcode":"RG2 0AU",
    "sg:province":"Berkshire",
    "sg:tags":[
        "merchant",
        "builder"
    ],
    "wof:name":"S P Dorsey Specialist Construction Materials Ltd.",
    "wof:placetype":"venue"
},
  "geometry": {"coordinates":[-0.9702200294,51.4430389404],"type":"Point"}
}