{
  "type": "Feature",
  "properties": {
    "addr:full":"Unit 6 Ambley Grn, Gillingham Business Park Gillingham Kent ME8 0NJ",
    "addr:housenumber":"unit 6",
    "addr:postcode":"me8 0nj",
    "addr:street":"Ambley Grn Gillingham Business Park",
    "iso:country":"GB",
    "sg:address":"Unit 6 Ambley Grn, Gillingham Business Park",
    "sg:city":"Gillingham",
    "sg:classifiers":[
        {
            "category":"Health Services",
            "subcategory":"Clinic",
            "type":"Services"
        }
    ],
    "sg:phone":"+44 1634 360044",
    "sg:postcode":"ME8 0NJ",
    "sg:province":"Kent",
    "sg:tags":[
        "medical"
    ],
    "wof:name":"Micro Medical Ltd.",
    "wof:placetype":"venue"
},
  "geometry": {"coordinates":[0.574228,51.364487],"type":"Point"}
}