{
  "type": "Feature",
  "properties": {
    "addr:full":"Unit 7, Monmore Park Industrial Estate, Ettingshall Road Wolverhampton West Midlands WV2 2LQ",
    "addr:housenumber":"unit 7",
    "addr:postcode":"wv2 2lq",
    "addr:street":"Monmore Park Industrial;Ettingshall Road",
    "iso:country":"GB",
    "sg:address":"Unit 7, Monmore Park Industrial Estate, Ettingshall Road",
    "sg:city":"Wolverhampton",
    "sg:classifiers":[
        {
            "category":"Retail",
            "subcategory":"Auto Repair",
            "type":"Services"
        }
    ],
    "sg:phone":"+44 1902 498222",
    "sg:postcode":"WV2 2LQ",
    "sg:province":"West Midlands",
    "sg:tags":[
        "body",
        "car"
    ],
    "wof:name":"Whitehall Car Bodies Ltd.",
    "wof:placetype":"venue"
},
  "geometry": {"coordinates":[-2.1029140949,52.5706214905],"type":"Point"}
}