{
  "type": "Feature",
  "properties": {
    "iso:country":"GB",
    "sg:address":"54 Mayes Lane, Ramsey",
    "sg:city":"Harwich",
    "sg:classifiers":[
        {
            "category":"Health Services",
            "subcategory":"Nursing And Care Facility",
            "type":"Services"
        }
    ],
    "sg:phone":"+44 1255 880751",
    "sg:postcode":"CO12 5EJ",
    "sg:province":"Essex",
    "sg:tags":[
        "home"
    ],
    "wof:name":"Tendring Premier Care",
    "wof:placetype":"venue"
},
  "geometry": {"coordinates":[1.2284400463,51.9262237549],"type":"Point"}
}