{
  "type": "Feature",
  "properties": {
    "iso:country":"GB",
    "sg:address":"1 Wentworth Street",
    "sg:city":"London",
    "sg:classifiers":[
        {
            "category":"Shopping",
            "subcategory":"Luggage & Leather Goods",
            "type":"Retail Goods"
        }
    ],
    "sg:phone":"+44 20 7247 9166",
    "sg:postcode":"E1 7TB",
    "sg:province":"Greater London",
    "sg:tags":[
        "shop",
        "leathergoods"
    ],
    "wof:name":"Amir's",
    "wof:placetype":"venue"
},
  "geometry": {"coordinates":[-0.0763849989,51.516330719],"type":"Point"}
}