{
  "type": "Feature",
  "properties": {
    "iso:country":"GB",
    "sg:address":"Windy Harbour Holiday Centre, Singleton",
    "sg:city":"Poulton-le-fylde",
    "sg:classifiers":[
        {
            "category":"Building & Trades",
            "subcategory":"Equipment Rental",
            "type":"Services"
        }
    ],
    "sg:phone":"+44 1253 893794",
    "sg:postcode":"FY6 8NB",
    "sg:province":"Lancashire",
    "sg:tags":[
        "hire",
        "centre"
    ],
    "wof:name":"The Hire & Leisure Shop",
    "wof:placetype":"venue"
},
  "geometry": {"coordinates":[-2.9419839382,53.8369750977],"type":"Point"}
}