{
  "type": "Feature",
  "properties": {
    "iso:country":"GB",
    "sg:address":"8 Broad St",
    "sg:city":"Wokingham",
    "sg:classifiers":[
        {
            "category":"Manufacturing",
            "subcategory":"Tools & Machinery",
            "type":"Manufacturing & Wholesale Goods"
        }
    ],
    "sg:postcode":"RG40 1AB",
    "sg:province":"Berkshire",
    "sg:tags":[
        "society",
        "friendly"
    ],
    "wof:name":"Gay,James,& Partner",
    "wof:placetype":"venue"
},
  "geometry": {"coordinates":[-0.835589,51.411076],"type":"Point"}
}