{
  "type": "Feature",
  "properties": {
    "iso:country":"GB",
    "sg:address":"14 Bourne Court, Southend Road",
    "sg:city":"Woodford Green",
    "sg:classifiers":[
        {
            "category":"Home & Garden",
            "subcategory":"Home Furnishings",
            "type":"Retail Goods"
        }
    ],
    "sg:postcode":"IG8 8HD",
    "sg:province":"Essex",
    "sg:tags":[
        "furnishers",
        "planner",
        "kitchen"
    ],
    "wof:name":"C D C",
    "wof:placetype":"venue"
},
  "geometry": {"coordinates":[0.028982,51.604389],"type":"Point"}
}