{
  "type": "Feature",
  "properties": {
    "addr:full":"Sherwood House, Gadbrook Business Centre Northwich Cheshire CW9 7TN",
    "addr:postcode":"cw9 7tn",
    "addr:street":"Gadbrook",
    "iso:country":"GB",
    "sg:address":"Sherwood House, Gadbrook Business Centre",
    "sg:city":"Northwich",
    "sg:classifiers":[
        {
            "category":"Manufacturing",
            "subcategory":"Electronics",
            "type":"Manufacturing & Wholesale Goods"
        }
    ],
    "sg:phone":"+44 1606 815400",
    "sg:postcode":"CW9 7TN",
    "sg:province":"Cheshire",
    "sg:tags":[
        "control",
        "component",
        "-",
        "electronic"
    ],
    "wof:name":"Motorola Ltd.",
    "wof:placetype":"venue"
},
  "geometry": {"coordinates":[-2.4851369858,53.2480392456],"type":"Point"}
}