{
  "type": "Feature",
  "properties": {
    "iso:country":"GB",
    "sg:address":"2 Brooks Court, Kirtling Street",
    "sg:city":"London",
    "sg:classifiers":[
        {
            "category":"Professional",
            "subcategory":"Management & Consulting",
            "type":"Services"
        },
        {
            "category":"Professional",
            "subcategory":"Art Services",
            "type":"Services"
        }
    ],
    "sg:phone":"+44 20 7801 8900",
    "sg:postcode":"SW8 5BX",
    "sg:province":"Greater London",
    "sg:tags":[
        "consultant",
        "design",
        "marketing"
    ],
    "wof:name":"Manifest",
    "wof:placetype":"venue"
},
  "geometry": {"coordinates":[-0.14024,51.480751],"type":"Point"}
}