{
  "type": "Feature",
  "properties": {
    "addr:full":"Grove Street, Raunds Wellingborough Northamptonshire NN9 6ED",
    "addr:postcode":"nn9 6ed",
    "addr:street":"Grove Street",
    "iso:country":"GB",
    "sg:address":"Grove Street, Raunds",
    "sg:city":"Wellingborough",
    "sg:classifiers":[
        {
            "category":"Manufacturing",
            "subcategory":"Rubber & Plastics",
            "type":"Manufacturing & Wholesale Goods"
        }
    ],
    "sg:phone":"+44 1933 623311",
    "sg:postcode":"NN9 6ED",
    "sg:province":"Northamptonshire",
    "sg:tags":[
        "product"
    ],
    "wof:name":"R P C Containers Rushden",
    "wof:placetype":"venue"
},
  "geometry": {"coordinates":[-0.5468440056,52.3433532715],"type":"Point"}
}