{
  "type": "Feature",
  "properties": {
    "addr:full":"Challenger Quay Falmouth Cornwall TR11 3YL",
    "addr:postcode":"tr11 3yl",
    "addr:street":"Challenger Quay",
    "iso:country":"GB",
    "sg:address":"Challenger Quay",
    "sg:city":"Falmouth",
    "sg:classifiers":[
        {
            "category":"Recreation",
            "subcategory":"Marina",
            "type":"Entertainment"
        }
    ],
    "sg:phone":"+44 1326 311113",
    "sg:postcode":"TR11 3YL",
    "sg:province":"Cornwall",
    "wof:name":"Port Pendennis Marina",
    "wof:placetype":"venue"
},
  "geometry": {"coordinates":[-5.0800328255,50.1522064209],"type":"Point"}
}