{
  "type": "Feature",
  "properties": {
    "iso:country":"GB",
    "sg:address":"P O Box 30",
    "sg:city":"Newark",
    "sg:classifiers":[
        {
            "category":"Professional",
            "subcategory":"Business Services",
            "type":"Services"
        },
        {
            "category":"Organizations",
            "subcategory":"Professional Association",
            "type":"Services"
        }
    ],
    "sg:phone":"+44 1400 282192",
    "sg:postcode":"NG23 5AX",
    "sg:province":"Lincolnshire",
    "sg:tags":[
        "limited",
        "registrar",
        "registration"
    ],
    "wof:name":"Selby A & M Business Services",
    "wof:placetype":"venue"
},
  "geometry": {"coordinates":[-0.81494,53.02261],"type":"Point"}
}