{
  "type": "Feature",
  "properties": {
    "addr:full":"Guyscliff, 31-33 Doncaster Gate Rotherham South Yorkshire S65 1DF",
    "addr:housenumber":"31-33",
    "addr:postcode":"s65 1df",
    "addr:street":"Doncaster Gate",
    "iso:country":"GB",
    "sg:address":"Guyscliff, 31-33 Doncaster Gate",
    "sg:city":"Rotherham",
    "sg:classifiers":[
        {
            "category":"Professional",
            "subcategory":"Lawyer & Legal Services",
            "type":"Services"
        }
    ],
    "sg:phone":"+44 1709 365531",
    "sg:postcode":"S65 1DF",
    "sg:province":"South Yorkshire",
    "sg:tags":[
        "solicitor"
    ],
    "sg:website":"http://www.gichard.com",
    "wof:name":"Gichard & Co",
    "wof:placetype":"venue"
},
  "geometry": {"coordinates":[-1.35292,53.430908],"type":"Point"}
}