{
  "type": "Feature",
  "properties": {
    "addr:full":"68 Watergate Street, Factory Road, Handicroft Chester Cheshire CH1 2LA",
    "addr:housenumber":"68",
    "addr:postcode":"ch1 2la",
    "addr:street":"Watergate Street Factory Road Handicroft",
    "iso:country":"GB",
    "sg:address":"68 Watergate Street, Factory Road, Handicroft",
    "sg:city":"Chester",
    "sg:classifiers":[
        {
            "category":"Mining & Drilling",
            "type":"Manufacturing & Wholesale Goods"
        }
    ],
    "sg:postcode":"CH1 2LA",
    "sg:province":"Cheshire",
    "sg:tags":[
        "quarry"
    ],
    "wof:name":"Mansfield & Sons Ltd.",
    "wof:placetype":"venue"
},
  "geometry": {"coordinates":[-2.894226,53.189999],"type":"Point"}
}