{
  "type": "Feature",
  "properties": {
    "iso:country":"GB",
    "sg:address":"Robin Hood Meadow",
    "sg:city":"Hemel Hempstead",
    "sg:classifiers":[
        {
            "category":"Organizations",
            "subcategory":"Community Association",
            "type":"Services"
        },
        {
            "category":"Organizations",
            "subcategory":"Membership Organization",
            "type":"Services"
        }
    ],
    "sg:phone":"+44 1442 241513",
    "sg:postcode":"HP2 6NH",
    "sg:province":"Hertfordshire",
    "sg:tags":[
        "club",
        "social"
    ],
    "wof:name":"Robin Sports & Social Club",
    "wof:placetype":"venue"
},
  "geometry": {"coordinates":[-0.456242,51.77441],"type":"Point"}
}