{
  "type": "Feature",
  "properties": {
    "addr:full":"2 Rosslyn Street, Clifton York North Yorkshire YO30 6LG",
    "addr:housenumber":"2",
    "addr:postcode":"yo30 6lg",
    "addr:street":"Rosslyn Street",
    "iso:country":"GB",
    "sg:address":"2 Rosslyn Street, Clifton",
    "sg:city":"York",
    "sg:classifiers":[
        {
            "category":"Building & Trades",
            "subcategory":"Construction",
            "type":"Services"
        }
    ],
    "sg:phone":"+44 1904 643819",
    "sg:postcode":"YO30 6LG",
    "sg:province":"North Yorkshire",
    "sg:tags":[
        "window",
        "replacement"
    ],
    "wof:name":"D G M S",
    "wof:placetype":"venue"
},
  "geometry": {"coordinates":[-1.096688,53.968437],"type":"Point"}
}