{
  "type": "Feature",
  "properties": {
    "iso:country":"GB",
    "sg:address":"1 Market Close",
    "sg:city":"Poole",
    "sg:classifiers":[
        {
            "category":"Organizations",
            "subcategory":"Community Association",
            "type":"Services"
        }
    ],
    "sg:phone":"+44 1202 669244",
    "sg:postcode":"BH15 1NQ",
    "sg:province":"Dorset",
    "sg:tags":[
        "relation",
        "public"
    ],
    "wof:name":"B M C Public Relations",
    "wof:placetype":"venue"
},
  "geometry": {"coordinates":[-1.987027,50.715256],"type":"Point"}
}