{
  "type": "Feature",
  "properties": {
    "iso:country":"GB",
    "sg:address":"Upper Barr Farm",
    "sg:city":"Newton Stewart",
    "sg:classifiers":[
        {
            "category":"Farming",
            "subcategory":"Farm",
            "type":"Manufacturing & Wholesale Goods"
        }
    ],
    "sg:postcode":"DG8 6AU",
    "sg:province":"Dumfries and Galloway",
    "sg:tags":[
        "mixed",
        "crop"
    ],
    "wof:name":"Upr Barr Farming Co",
    "wof:placetype":"venue"
},
  "geometry": {"coordinates":[-4.482984,54.954784],"type":"Point"}
}