{
  "type": "Feature",
  "properties": {
    "addr:full":"Greenwood Close Prescot Merseyside L34 2SL",
    "addr:postcode":"l34 2sl",
    "addr:street":"Greenwood Close",
    "iso:country":"GB",
    "sg:address":"Greenwood Close",
    "sg:city":"Prescot",
    "sg:classifiers":[
        {
            "category":"Social Services",
            "subcategory":"Adult Care",
            "type":"Services"
        }
    ],
    "sg:phone":"+44 151 426 3398",
    "sg:postcode":"L34 2SL",
    "sg:province":"Merseyside",
    "sg:tags":[
        "housing",
        "sheltered"
    ],
    "wof:name":"Greenwood Close Sheltered Housing",
    "wof:placetype":"venue"
},
  "geometry": {"coordinates":[-2.7953751087,53.4306983948],"type":"Point"}
}