{
  "type": "Feature",
  "properties": {
    "addr:full":"Jersey Farm Surgery, 2 St Brelades Pl St Albans Hertfordshire AL4 9RG",
    "addr:housenumber":"2",
    "addr:postcode":"al4 9rg",
    "addr:street":"St Brelades Pl",
    "iso:country":"GB",
    "sg:address":"Jersey Farm Surgery, 2 St Brelades Pl",
    "sg:city":"St Albans",
    "sg:classifiers":[
        {
            "category":"Health Services",
            "subcategory":"Doctor",
            "type":"Services"
        }
    ],
    "sg:phone":"+44 1727 837498",
    "sg:postcode":"AL4 9RG",
    "sg:province":"Hertfordshire",
    "sg:tags":[
        "practitioners"
    ],
    "wof:name":"Clegg, J P",
    "wof:placetype":"venue"
},
  "geometry": {"coordinates":[-0.29778,51.76973],"type":"Point"}
}