{
  "type": "Feature",
  "properties": {
    "addr:full":"64 Corstorphine Rd Edinburgh City of Edinburgh EH12 6JQ",
    "addr:housenumber":"64",
    "addr:postcode":"eh12 6jq",
    "addr:street":"Corstorphine Rd",
    "iso:country":"GB",
    "sg:address":"64 Corstorphine Rd",
    "sg:city":"Edinburgh",
    "sg:classifiers":[
        {
            "category":"Sports & Exercise",
            "subcategory":"Sports Center",
            "type":"Entertainment"
        }
    ],
    "sg:phone":"+44 131 337 1255",
    "sg:postcode":"EH12 6JQ",
    "sg:province":"City of Edinburgh",
    "sg:tags":[
        "shop",
        "good"
    ],
    "wof:name":"Sports Stock",
    "wof:placetype":"venue"
},
  "geometry": {"coordinates":[-3.277949,55.942371],"type":"Point"}
}