{
  "type": "Feature",
  "properties": {
    "addr:full":"Unit 7 Rivermead Industrial Estate, Bishops Hall Lane Chelmsford Essex CM1 1PD",
    "addr:housenumber":"unit 7",
    "addr:postcode":"cm1 1pd",
    "addr:street":"Rivermead Industrial Estate;Hall Lane",
    "iso:country":"GB",
    "sg:address":"Unit 7 Rivermead Industrial Estate, Bishops Hall Lane",
    "sg:city":"Chelmsford",
    "sg:classifiers":[
        {
            "category":"Shopping",
            "subcategory":"Beauty & Cosmetics",
            "type":"Retail Goods"
        }
    ],
    "sg:phone":"+44 1245 358324",
    "sg:postcode":"CM1 1PD",
    "sg:province":"Essex",
    "sg:tags":[
        "equipment",
        "supply",
        "hairdressing"
    ],
    "wof:name":"M Kaye Hairdressers Supplies",
    "wof:placetype":"venue"
},
  "geometry": {"coordinates":[0.4736799896,51.7432861328],"type":"Point"}
}