{
  "type": "Feature",
  "properties": {
    "addr:full":"Wakeman Road Bourne End Berkshire SL8 5SX",
    "addr:postcode":"sl8 5sx",
    "addr:street":"Wakeman Road Bourne",
    "iso:country":"GB",
    "sg:address":"Wakeman Road",
    "sg:city":"Bourne End",
    "sg:classifiers":[
        {
            "category":"Social Services",
            "subcategory":"Child Care",
            "type":"Services"
        },
        {
            "category":"Social Services",
            "subcategory":"Adult Care",
            "type":"Services"
        }
    ],
    "sg:phone":"+44 1628 530264",
    "sg:postcode":"SL8 5SX",
    "sg:province":"Berkshire",
    "sg:tags":[
        "day",
        "centre"
    ],
    "wof:name":"Bourne End Red Cross Day Centre",
    "wof:placetype":"venue"
},
  "geometry": {"coordinates":[-0.7112089992,51.5789031982],"type":"Point"}
}