{
  "type": "Feature",
  "properties": {
    "addr:full":"17 Richmond Street Ashton-under-lyne Greater Manchester OL6 7TX",
    "addr:housenumber":"17",
    "addr:postcode":"ol6 7tx",
    "addr:street":"Richmond Street",
    "iso:country":"GB",
    "sg:address":"17 Richmond Street",
    "sg:city":"Ashton-under-lyne",
    "sg:classifiers":[
        {
            "category":"Travel",
            "subcategory":"Hotels & Motels",
            "type":"Entertainment"
        }
    ],
    "sg:phone":"+44 161 330 0248",
    "sg:postcode":"OL6 7TX",
    "sg:province":"Greater Manchester",
    "wof:name":"Lancaster House Hotel",
    "wof:placetype":"venue"
},
  "geometry": {"coordinates":[-2.105069,53.485519],"type":"Point"}
}