{
  "type": "Feature",
  "properties": {
    "addr:full":"Oxford House, Oxford Road Macclesfield Cheshire SK11 8HP",
    "addr:postcode":"sk11 8hp",
    "addr:street":"Oxford Road",
    "iso:country":"GB",
    "sg:address":"Oxford House, Oxford Road",
    "sg:city":"Macclesfield",
    "sg:classifiers":[
        {
            "category":"Banks & Credit Unions",
            "subcategory":"Financial Services",
            "type":"Services"
        }
    ],
    "sg:phone":"+44 1625 511005",
    "sg:postcode":"SK11 8HP",
    "sg:province":"Cheshire",
    "sg:tags":[
        "consultant"
    ],
    "wof:name":"H F S Loans Ltd.",
    "wof:placetype":"venue"
},
  "geometry": {"coordinates":[-2.1374340057,53.2593002319],"type":"Point"}
}