{
  "type": "Feature",
  "properties": {
    "addr:full":"Pitland St, Holmbury St. Mary Dorking Surrey RH5 6NP",
    "addr:postcode":"rh5 6np",
    "addr:street":"Pitland St Holmbury St. Mary Dorking",
    "iso:country":"GB",
    "sg:address":"Pitland St, Holmbury St. Mary",
    "sg:city":"Dorking",
    "sg:classifiers":[
        {
            "category":"Bars & Pubs",
            "type":"Food & Drink"
        }
    ],
    "sg:phone":"+44 1306 730282",
    "sg:postcode":"RH5 6NP",
    "sg:province":"Surrey",
    "sg:tags":[
        "pubs",
        "inn"
    ],
    "wof:name":"Kings Head",
    "wof:placetype":"venue"
},
  "geometry": {"coordinates":[-0.4103940129,51.1850967407],"type":"Point"}
}