{
  "type": "Feature",
  "properties": {
    "iso:country":"GB",
    "sg:address":"Lennig House, 2 Masons Avenue",
    "sg:city":"Croydon",
    "sg:classifiers":[
        {
            "category":"Manufacturing",
            "subcategory":"Tools & Machinery",
            "type":"Manufacturing & Wholesale Goods"
        }
    ],
    "sg:phone":"+44 20 8688 0054",
    "sg:postcode":"CR0 9XS",
    "sg:province":"Surrey",
    "sg:tags":[
        "society",
        "friendly"
    ],
    "wof:name":"Co-Operative Insurance Society Ltd.",
    "wof:placetype":"venue"
},
  "geometry": {"coordinates":[-0.098669,51.3687477112],"type":"Point"}
}