{
  "type": "Feature",
  "properties": {
    "addr:full":"27 Elizabeth Street London Greater London SW1W 9RP",
    "addr:housenumber":"27",
    "addr:postcode":"sw1w 9rp",
    "addr:street":"Elizabeth Street",
    "iso:country":"GB",
    "sg:address":"27 Elizabeth Street",
    "sg:city":"London",
    "sg:classifiers":[
        {
            "category":"Cafe",
            "type":"Food & Drink"
        }
    ],
    "sg:phone":"+44 20 7259 9597",
    "sg:postcode":"SW1W 9RP",
    "sg:province":"Greater London",
    "sg:tags":[
        "tea",
        "room"
    ],
    "wof:name":"Osys Cafe",
    "wof:placetype":"venue"
},
  "geometry": {"coordinates":[-0.149507001,51.4928855896],"type":"Point"}
}