{
  "type": "Feature",
  "properties": {
    "addr:full":"Station Rd Cannock Staffordshire WS12 4DH",
    "addr:postcode":"ws12 4dh",
    "addr:street":"Station Rd",
    "iso:country":"GB",
    "sg:address":"Station Rd",
    "sg:city":"Cannock",
    "sg:classifiers":[
        {
            "category":"Place Of Worship",
            "type":"Public Place"
        }
    ],
    "sg:phone":"+44 1543 425588",
    "sg:postcode":"WS12 4DH",
    "sg:province":"Staffordshire",
    "wof:name":"Trinity Church",
    "wof:placetype":"venue"
},
  "geometry": {"coordinates":[-1.9954589605,52.7169952393],"type":"Point"}
}