{
  "type": "Feature",
  "properties": {
    "addr:full":"14 Westrick Walk, Prestwood Great Missenden Buckinghamshire HP16 0RZ",
    "addr:housenumber":"14",
    "addr:postcode":"hp16 0rz",
    "addr:street":"Westrick Walk Prestwood",
    "iso:country":"GB",
    "sg:address":"14 Westrick Walk, Prestwood",
    "sg:city":"Great Missenden",
    "sg:classifiers":[
        {
            "category":"Building & Trades",
            "subcategory":"Plumbing",
            "type":"Services"
        }
    ],
    "sg:phone":"+44 1494 865687",
    "sg:postcode":"HP16 0RZ",
    "sg:province":"Buckinghamshire",
    "sg:tags":[
        "plumber",
        "heating"
    ],
    "wof:name":"DAVID H CLEMENTS",
    "wof:placetype":"venue"
},
  "geometry": {"coordinates":[-0.7373239994,51.6942558289],"type":"Point"}
}