{
  "type": "Feature",
  "properties": {
    "addr:full":"11 Thames Road Barking Essex IG11 0HG",
    "addr:housenumber":"11",
    "addr:postcode":"ig11 0hg",
    "addr:street":"Thames Road",
    "iso:country":"GB",
    "sg:address":"11 Thames Road",
    "sg:city":"Barking",
    "sg:classifiers":[
        {
            "category":"Autos & Motor Vehicles",
            "subcategory":"Auto Supplies",
            "type":"Retail Goods"
        }
    ],
    "sg:phone":"+44 20 8591 3030",
    "sg:postcode":"IG11 0HG",
    "sg:province":"Essex",
    "sg:tags":[
        "electric"
    ],
    "wof:name":"Brownings Electric Co. Ltd.",
    "wof:placetype":"venue"
},
  "geometry": {"coordinates":[0.0994609967,51.5253753662],"type":"Point"}
}