{
  "type": "Feature",
  "properties": {
    "iso:country":"GB",
    "sg:address":"11-13 Braeval Street",
    "sg:city":"Cardiff",
    "sg:classifiers":[
        {
            "category":"Retail",
            "subcategory":"Auto Repair",
            "type":"Services"
        }
    ],
    "sg:phone":"+44 29 2047 1802",
    "sg:postcode":"CF24 4SJ",
    "sg:province":"Cardiff",
    "sg:tags":[
        "engine",
        "specialist",
        "garage",
        "related",
        "car"
    ],
    "wof:name":"A Gallo",
    "wof:placetype":"venue"
},
  "geometry": {"coordinates":[-3.173401,51.49445],"type":"Point"}
}