{
  "type": "Feature",
  "properties": {
    "addr:full":"Longmead School, Laurel Lane West Drayton Greater London UB7 7TX",
    "addr:postcode":"ub7 7tx",
    "addr:street":"Laurel Lane",
    "iso:country":"GB",
    "sg:address":"Longmead School, Laurel Lane",
    "sg:city":"West Drayton",
    "sg:classifiers":[
        {
            "category":"Shopping",
            "subcategory":"Department Store",
            "type":"Retail Goods"
        },
        {
            "category":"Professional",
            "subcategory":"Engineering",
            "type":"Services"
        }
    ],
    "sg:phone":"+44 1895 449191",
    "sg:postcode":"UB7 7TX",
    "sg:province":"Greater London",
    "sg:tags":[
        "electronic",
        "engineer"
    ],
    "wof:name":"G & J Instrument Repairs & Supplies Ltd.",
    "wof:placetype":"venue"
},
  "geometry": {"coordinates":[-0.47399,51.509117],"type":"Point"}
}