{
  "type": "Feature",
  "properties": {
    "addr:full":"Eirene Garage, Mulberry Lane, Goring-by-sea Worthing West Sussex BN12 4RD",
    "addr:postcode":"bn12 4rd",
    "addr:street":"Mulberry Lane",
    "iso:country":"GB",
    "sg:address":"Eirene Garage, Mulberry Lane, Goring-by-sea",
    "sg:city":"Worthing",
    "sg:classifiers":[
        {
            "category":"Retail",
            "subcategory":"Auto Repair",
            "type":"Services"
        }
    ],
    "sg:phone":"+44 1903 211212",
    "sg:postcode":"BN12 4RD",
    "sg:province":"West Sussex",
    "sg:tags":[
        "modification",
        "garage"
    ],
    "wof:name":"John Haynes Auto Technics",
    "wof:placetype":"venue"
},
  "geometry": {"coordinates":[-0.424129,50.815079],"type":"Point"}
}