{
  "type": "Feature",
  "properties": {
    "addr:full":"Unit C & D Feathers Yard Holt Norfolk NR25 6BF",
    "addr:housenumber":"unit",
    "addr:postcode":"nr25 6bf",
    "iso:country":"GB",
    "sg:address":"Unit C & D Feathers Yard",
    "sg:city":"Holt",
    "sg:classifiers":[
        {
            "category":"Autos & Motor Vehicles",
            "subcategory":"Fuel & Gas Station",
            "type":"Retail Goods"
        },
        {
            "category":"Military Area",
            "subcategory":"Air Force Base",
            "type":"Public Place"
        }
    ],
    "sg:phone":"+44 1263 713722",
    "sg:postcode":"NR25 6BF",
    "sg:province":"Norfolk",
    "sg:tags":[
        "sale",
        "aga",
        "cooker"
    ],
    "wof:name":"The Aga Shop Ltd",
    "wof:placetype":"venue"
},
  "geometry": {"coordinates":[1.0870900154,52.9055480957],"type":"Point"}
}