{
  "type": "Feature",
  "properties": {
    "addr:full":"46 Fairways Avenue, Maddiston Falkirk Falkirk FK2 0NY",
    "addr:housenumber":"46",
    "addr:postcode":"fk2 0ny",
    "addr:street":"Fairways Avenue Maddiston",
    "iso:country":"GB",
    "sg:address":"46 Fairways Avenue, Maddiston",
    "sg:city":"Falkirk",
    "sg:classifiers":[
        {
            "category":"Shopping",
            "subcategory":"Department Store",
            "type":"Retail Goods"
        }
    ],
    "sg:postcode":"FK2 0NY",
    "sg:province":"Falkirk",
    "wof:name":"Home Show Interior Accessories",
    "wof:placetype":"venue"
},
  "geometry": {"coordinates":[-3.706876,55.971729],"type":"Point"}
}