{
  "type": "Feature",
  "properties": {
    "iso:country":"GB",
    "sg:address":"Anfield, Longcoombe Lane",
    "sg:city":"Looe",
    "sg:classifiers":[
        {
            "category":"Building & Trades",
            "subcategory":"Construction",
            "type":"Services"
        }
    ],
    "sg:postcode":"PL13 2PL",
    "sg:province":"Cornwall",
    "sg:tags":[
        "builder"
    ],
    "wof:name":"Terence J Lewis",
    "wof:placetype":"venue"
},
  "geometry": {"coordinates":[-4.462355,50.356121],"type":"Point"}
}