{
  "type": "Feature",
  "properties": {
    "addr:full":"460 Caerleon Road Newport Newport NP19 7LW",
    "addr:housenumber":"460",
    "addr:postcode":"np19 7lw",
    "addr:street":"Caerleon Road",
    "iso:country":"GB",
    "sg:address":"460 Caerleon Road",
    "sg:city":"Newport",
    "sg:classifiers":[
        {
            "category":"Shopping",
            "subcategory":"Baby Store",
            "type":"Retail Goods"
        }
    ],
    "sg:postcode":"NP19 7LW",
    "sg:province":"Newport",
    "sg:tags":[
        "nursery",
        "accessory"
    ],
    "wof:name":"Baby Castaways",
    "wof:placetype":"venue"
},
  "geometry": {"coordinates":[-2.9742019176,51.6037101746],"type":"Point"}
}