{
  "type": "Feature",
  "properties": {
    "iso:country":"GB",
    "sg:address":"58 Grove Road",
    "sg:city":"Eastbourne",
    "sg:classifiers":[
        {
            "category":"Home & Garden",
            "subcategory":"Building Materials",
            "type":"Retail Goods"
        }
    ],
    "sg:postcode":"BN21 4UD",
    "sg:province":"East Sussex",
    "sg:tags":[
        "furnishers",
        "bathroom",
        "planner"
    ],
    "wof:name":"Cascade Bathrooms",
    "wof:placetype":"venue"
},
  "geometry": {"coordinates":[0.278803,50.767139],"type":"Point"}
}