{
  "type": "Feature",
  "properties": {
    "addr:full":"Imperial House, 1a Standen Avenue Hornchurch Essex RM12 6AA",
    "addr:housenumber":"1a",
    "addr:postcode":"rm12 6aa",
    "addr:street":"Standen Avenue",
    "iso:country":"GB",
    "sg:address":"Imperial House, 1a Standen Avenue",
    "sg:city":"Hornchurch",
    "sg:classifiers":[
        {
            "category":"Communications",
            "type":"Services"
        }
    ],
    "sg:phone":"+44 1708 476235",
    "sg:postcode":"RM12 6AA",
    "sg:province":"Essex",
    "sg:tags":[
        "data",
        "network"
    ],
    "wof:name":"Vala Services Ltd.",
    "wof:placetype":"venue"
},
  "geometry": {"coordinates":[0.2191630006,51.5532684326],"type":"Point"}
}