{
  "type": "Feature",
  "properties": {
    "iso:country":"GB",
    "sg:address":"89 Eastfield Rd",
    "sg:city":"Louth",
    "sg:classifiers":[
        {
            "category":"Manufacturing",
            "subcategory":"Signs",
            "type":"Manufacturing & Wholesale Goods"
        }
    ],
    "sg:phone":"+44 1507 607747",
    "sg:postcode":"LN11 7AP",
    "sg:province":"Lincolnshire",
    "sg:tags":[
        "writer"
    ],
    "wof:name":"Lee Crosskill the Signwiter",
    "wof:placetype":"venue"
},
  "geometry": {"coordinates":[0.0137980003,53.3724746704],"type":"Point"}
}