{
  "type": "Feature",
  "properties": {
    "iso:country":"GB",
    "sg:address":"Upper Street, Defford",
    "sg:city":"Worcester",
    "sg:classifiers":[
        {
            "category":"Shopping",
            "subcategory":"Pets & Pet Supplies",
            "type":"Retail Goods"
        },
        {
            "category":"Retail",
            "subcategory":"Animal Services",
            "type":"Services"
        }
    ],
    "sg:phone":"+44 1386 750615",
    "sg:postcode":"WR8 9AB",
    "sg:province":"Gloucestershire",
    "sg:tags":[
        "training",
        "dog"
    ],
    "wof:name":"The Pet Behaviour Centre",
    "wof:placetype":"venue"
},
  "geometry": {"coordinates":[-2.1172189713,52.0867004395],"type":"Point"}
}