{
  "type": "Feature",
  "properties": {
    "addr:full":"11 St Andrews Road South Lytham St Annes Lancashire FY8 1SX",
    "addr:housenumber":"11",
    "addr:postcode":"fy8 1sx",
    "addr:street":"St Andrews Road South;St",
    "iso:country":"GB",
    "sg:address":"11 St Andrews Road South",
    "sg:city":"Lytham St Annes",
    "sg:classifiers":[
        {
            "category":"Shopping",
            "subcategory":"Antiques",
            "type":"Retail Goods"
        },
        {
            "category":"Shopping",
            "subcategory":"Used Merchandise",
            "type":"Retail Goods"
        }
    ],
    "sg:postcode":"FY8 1SX",
    "sg:province":"Lancashire",
    "sg:tags":[
        "shop",
        "second-hand"
    ],
    "wof:name":"St. Annes Antique Centre",
    "wof:placetype":"venue"
},
  "geometry": {"coordinates":[-3.028108,53.752205],"type":"Point"}
}