{
  "type": "Feature",
  "properties": {
    "addr:full":"Glebe Farm, Gidding Road Huntingdon Bedfordshire PE28 5UJ",
    "addr:postcode":"pe28 5uj",
    "addr:street":"Gidding Road",
    "iso:country":"GB",
    "sg:address":"Glebe Farm, Gidding Road",
    "sg:city":"Huntingdon",
    "sg:classifiers":[
        {
            "category":"Farming",
            "subcategory":"Farm",
            "type":"Manufacturing & Wholesale Goods"
        }
    ],
    "sg:postcode":"PE28 5UJ",
    "sg:province":"Bedfordshire",
    "sg:tags":[
        "mixed",
        "crop"
    ],
    "wof:name":"M J Elliot",
    "wof:placetype":"venue"
},
  "geometry": {"coordinates":[-0.289583,52.439335],"type":"Point"}
}