{
  "type": "Feature",
  "properties": {
    "iso:country":"GB",
    "sg:address":"Anchorage Lane",
    "sg:city":"Northallerton",
    "sg:classifiers":[
        {
            "category":"Manufacturing",
            "subcategory":"Wood Products",
            "type":"Manufacturing & Wholesale Goods"
        }
    ],
    "sg:phone":"+44 1609 774935",
    "sg:postcode":"DL7 8DX",
    "sg:province":"North Yorkshire",
    "sg:tags":[
        "maker",
        "cabinet"
    ],
    "wof:name":"David  Gardener",
    "wof:placetype":"venue"
},
  "geometry": {"coordinates":[-1.4391390085,54.3436698914],"type":"Point"}
}