{
  "type": "Feature",
  "properties": {
    "addr:full":"103 Pinner Road, Northwwood Hill Northwood Greater London HA6 1QN",
    "addr:housenumber":"103",
    "addr:postcode":"ha6 1qn",
    "addr:street":"Pinner Road Northwwood Hill",
    "iso:country":"GB",
    "sg:address":"103 Pinner Road, Northwwood Hill",
    "sg:city":"Northwood",
    "sg:classifiers":[
        {
            "category":"Health Services",
            "subcategory":"Dentist",
            "type":"Services"
        }
    ],
    "sg:phone":"+44 20 8868 2083",
    "sg:postcode":"HA6 1QN",
    "sg:province":"Greater London",
    "sg:tags":[
        "technician",
        "dental"
    ],
    "wof:name":"Hartsbourne Ceramic Laboratory",
    "wof:placetype":"venue"
},
  "geometry": {"coordinates":[-0.408214,51.602173],"type":"Point"}
}