{
  "type": "Feature",
  "properties": {
    "addr:full":"Cartref, Maesycwmmer Hengoed Caerphilly CF82 7SN",
    "addr:postcode":"cf82 7sn",
    "iso:country":"GB",
    "sg:address":"Cartref, Maesycwmmer",
    "sg:city":"Hengoed",
    "sg:classifiers":[
        {
            "category":"Recreation",
            "subcategory":"Dog Park",
            "type":"Entertainment"
        }
    ],
    "sg:phone":"+44 1443 813356",
    "sg:postcode":"CF82 7SN",
    "sg:province":"Caerphilly",
    "wof:name":"Mistism Grooming",
    "wof:placetype":"venue"
},
  "geometry": {"coordinates":[-3.231799,51.648319],"type":"Point"}
}