{
  "type": "Feature",
  "properties": {
    "iso:country":"GB",
    "sg:address":"52 Broadway",
    "sg:city":"York",
    "sg:classifiers":[
        {
            "category":"Home & Garden",
            "subcategory":"Hardware",
            "type":"Retail Goods"
        }
    ],
    "sg:phone":"+44 1904 673080",
    "sg:postcode":"YO10 4JX",
    "sg:province":"North Yorkshire",
    "sg:tags":[
        "part",
        "accessory"
    ],
    "wof:name":"Northern Trail Bikes",
    "wof:placetype":"venue"
},
  "geometry": {"coordinates":[-1.0696710348,53.9409751892],"type":"Point"}
}