{
  "type": "Feature",
  "properties": {
    "iso:country":"GB",
    "sg:address":"P O Box 95",
    "sg:city":"Ipswich",
    "sg:classifiers":[
        {
            "category":"Social Services",
            "subcategory":"Adult Care",
            "type":"Services"
        }
    ],
    "sg:phone":"+44 1473 689926",
    "sg:postcode":"IP9 2BH",
    "sg:province":"Suffolk",
    "sg:tags":[
        "domestic",
        "cleaning"
    ],
    "wof:name":"Crystal Cleaning Services",
    "wof:placetype":"venue"
},
  "geometry": {"coordinates":[1.10175,51.99926],"type":"Point"}
}