{
  "type": "Feature",
  "properties": {
    "addr:full":"3 Cromwell Avenue Cheadle Cheshire SK8 4BS",
    "addr:housenumber":"3",
    "addr:postcode":"sk8 4bs",
    "addr:street":"Cromwell Avenue Cheadle",
    "iso:country":"GB",
    "sg:address":"3 Cromwell Avenue",
    "sg:city":"Cheadle",
    "sg:classifiers":[
        {
            "category":"Personal",
            "type":"Services"
        }
    ],
    "sg:postcode":"SK8 4BS",
    "sg:province":"Cheshire",
    "sg:tags":[
        "wedding"
    ],
    "wof:name":"Society Weddings",
    "wof:placetype":"venue"
},
  "geometry": {"coordinates":[-2.234349966,53.3972511292],"type":"Point"}
}