{
  "type": "Feature",
  "properties": {
    "addr:full":"29 St Martins Street Peterborough Cambridgeshire PE1 3BB",
    "addr:housenumber":"29",
    "addr:postcode":"pe1 3bb",
    "addr:street":"St Martins Street",
    "iso:country":"GB",
    "sg:address":"29 St Martins Street",
    "sg:city":"Peterborough",
    "sg:classifiers":[
        {
            "category":"Professional",
            "subcategory":"Art Services",
            "type":"Services"
        }
    ],
    "sg:phone":"+44 1733 567303",
    "sg:postcode":"PE1 3BB",
    "sg:province":"Cambridgeshire",
    "sg:tags":[
        "graphic",
        "designer"
    ],
    "wof:name":"S & M DESIGN",
    "wof:placetype":"venue"
},
  "geometry": {"coordinates":[-0.2429430038,52.5857620239],"type":"Point"}
}