{
  "type": "Feature",
  "properties": {
    "iso:country":"GB",
    "sg:address":"Unit 3, Park Lane Industrial Estate",
    "sg:city":"Oldbury",
    "sg:classifiers":[
        {
            "category":"Manufacturing",
            "subcategory":"Metals",
            "type":"Manufacturing & Wholesale Goods"
        },
        {
            "category":"Home & Garden",
            "subcategory":"Home Furnishings",
            "type":"Retail Goods"
        }
    ],
    "sg:phone":"+44 121 544 4666",
    "sg:postcode":"B69 4JX",
    "sg:province":"West Midlands",
    "sg:tags":[
        "steel",
        "mnfrs",
        "fitting",
        "tubing"
    ],
    "wof:name":"Star Tubes (U K) Ltd.",
    "wof:placetype":"venue"
},
  "geometry": {"coordinates":[-2.0152881145,52.4948577881],"type":"Point"}
}