{
  "type": "Feature",
  "properties": {
    "addr:full":"Leeholme Rd Billingham Durham TS23 3TA",
    "addr:postcode":"ts23 3ta",
    "addr:street":"Leeholme Rd",
    "iso:country":"GB",
    "sg:address":"Leeholme Rd",
    "sg:city":"Billingham",
    "sg:classifiers":[
        {
            "category":"Building & Trades",
            "subcategory":"Construction",
            "type":"Services"
        }
    ],
    "sg:phone":"+44 1642 560086",
    "sg:postcode":"TS23 3TA",
    "sg:province":"Durham",
    "sg:tags":[
        "heating",
        "contractor"
    ],
    "wof:name":"Associated Heat Services Emstar Ltd",
    "wof:placetype":"venue"
},
  "geometry": {"coordinates":[-1.2818000317,54.6068000793],"type":"Point"}
}