{
  "type": "Feature",
  "properties": {
    "addr:full":"17 Brancepeth Chare Peterlee Durham SR8 1LU",
    "addr:housenumber":"17",
    "addr:postcode":"sr8 1lu",
    "addr:street":"Brancepeth Chare",
    "iso:country":"GB",
    "sg:address":"17 Brancepeth Chare",
    "sg:city":"Peterlee",
    "sg:classifiers":[
        {
            "category":"Freight",
            "type":"Transportation"
        }
    ],
    "sg:postcode":"SR8 1LU",
    "sg:province":"Durham",
    "sg:tags":[
        "haulage",
        "road"
    ],
    "wof:name":"G Race & Sons",
    "wof:placetype":"venue"
},
  "geometry": {"coordinates":[-1.3492219448,54.7454032898],"type":"Point"}
}