{
  "type": "Feature",
  "properties": {
    "addr:full":"Higher Lane, Whitefield Manchester Lancashire M45 7FX",
    "addr:postcode":"m45 7fx",
    "addr:street":"Higher Lane",
    "iso:country":"GB",
    "sg:address":"Higher Lane, Whitefield",
    "sg:city":"Manchester",
    "sg:classifiers":[
        {
            "category":"Education",
            "subcategory":"University",
            "type":"Public Place"
        },
        {
            "category":"Government",
            "subcategory":"Office",
            "type":"Public Place"
        }
    ],
    "sg:phone":"+44 161 766 5118",
    "sg:postcode":"M45 7FX",
    "sg:province":"Lancashire",
    "sg:tags":[
        "local",
        "adult"
    ],
    "wof:name":"Bury Metropolitan Borough Council",
    "wof:placetype":"venue"
},
  "geometry": {"coordinates":[-2.300928,53.549236],"type":"Point"}
}