{
  "type": "Feature",
  "properties": {
    "iso:country":"GB",
    "sg:address":"Downey Street, Hanley",
    "sg:city":"Stoke-on-trent",
    "sg:classifiers":[
        {
            "category":"Farming",
            "subcategory":"Nursery",
            "type":"Manufacturing & Wholesale Goods"
        }
    ],
    "sg:phone":"+44 1782 286360",
    "sg:postcode":"ST1 3BY",
    "sg:province":"Staffordshire",
    "sg:tags":[
        "creche"
    ],
    "wof:name":"Happy Days Nursery",
    "wof:placetype":"venue"
},
  "geometry": {"coordinates":[-2.173429,53.021404],"type":"Point"}
}