{
  "type": "Feature",
  "properties": {
    "addr:full":"Victoria Place, Victoria Road Ripley Derbyshire DE5 3FW",
    "addr:postcode":"de5 3fw",
    "addr:street":"Place Victoria Road",
    "iso:country":"GB",
    "sg:address":"Victoria Place, Victoria Road",
    "sg:city":"Ripley",
    "sg:classifiers":[
        {
            "category":"Shopping",
            "subcategory":"Clothing, Apparel, & Fashions",
            "type":"Retail Goods"
        },
        {
            "category":"Social Services",
            "subcategory":"Adult Care",
            "type":"Services"
        }
    ],
    "sg:phone":"+44 1773 571200",
    "sg:postcode":"DE5 3FW",
    "sg:province":"Derbyshire",
    "sg:tags":[
        "industrial",
        "protective",
        "clothing"
    ],
    "wof:name":"Jamtiln Ltd.",
    "wof:placetype":"venue"
},
  "geometry": {"coordinates":[-1.4108389616,53.0505371094],"type":"Point"}
}