{
  "type": "Feature",
  "properties": {
    "iso:country":"GB",
    "sg:address":"40 Albert Road",
    "sg:city":"Rayleigh",
    "sg:classifiers":[
        {
            "category":"Retail",
            "subcategory":"Auto Rental",
            "type":"Services"
        }
    ],
    "sg:phone":"+44 1268 745695",
    "sg:postcode":"SS6 8HN",
    "sg:province":"Essex",
    "sg:tags":[
        "car",
        "hire",
        "truck"
    ],
    "wof:name":"Citygate",
    "wof:placetype":"venue"
},
  "geometry": {"coordinates":[0.623800993,51.5900993347],"type":"Point"}
}