{
  "type": "Feature",
  "properties": {
    "addr:full":"Unit D1 Raceview Business Centre, Hambridge Road Newbury Berkshire RG14 5SA",
    "addr:postcode":"rg14 5sa",
    "addr:street":"Hambridge Road",
    "iso:country":"GB",
    "sg:address":"Unit D1 Raceview Business Centre, Hambridge Road",
    "sg:city":"Newbury",
    "sg:classifiers":[
        {
            "category":"Fast Food",
            "type":"Food & Drink"
        }
    ],
    "sg:phone":"+44 1635 551133",
    "sg:postcode":"RG14 5SA",
    "sg:province":"Berkshire",
    "sg:tags":[
        "delivery"
    ],
    "wof:name":"Heroes Pizza Ltd.",
    "wof:placetype":"venue"
},
  "geometry": {"coordinates":[-1.3258719444,51.405872345],"type":"Point"}
}