{
  "type": "Feature",
  "properties": {
    "iso:country":"GB",
    "sg:address":"Unit E5 & E6, Clyde Shopping No 1, 36 Sylvania Way South",
    "sg:city":"Clydebank",
    "sg:classifiers":[
        {
            "category":"Professional",
            "subcategory":"Printing & Photocopies",
            "type":"Services"
        }
    ],
    "sg:phone":"+44 141 952 4544",
    "sg:postcode":"G81 1EA",
    "sg:province":"East Dunbartonshire",
    "sg:tags":[
        "printer"
    ],
    "wof:name":"Photo-Graphix",
    "wof:placetype":"venue"
},
  "geometry": {"coordinates":[-4.4049201012,55.9019508362],"type":"Point"}
}