{
  "type": "Feature",
  "properties": {
    "addr:full":"Preston Grange House Prestonpans East Lothian EH32 9RP",
    "addr:postcode":"eh32 9rp",
    "addr:street":"Preston;Prestonpans",
    "iso:country":"GB",
    "sg:address":"Preston Grange House",
    "sg:city":"Prestonpans",
    "sg:classifiers":[
        {
            "category":"Sports & Exercise",
            "subcategory":"Golf",
            "type":"Entertainment"
        }
    ],
    "sg:phone":"+44 1875 810139",
    "sg:postcode":"EH32 9RP",
    "sg:province":"East Lothian",
    "sg:tags":[
        "equipment"
    ],
    "wof:name":"John Henderson Proffesional Shop",
    "wof:placetype":"venue"
},
  "geometry": {"coordinates":[-2.982527,55.95834],"type":"Point"}
}