{
  "type": "Feature",
  "properties": {
    "addr:full":"20 Rowan Drive, Shaw Newbury Berkshire RG14 1LY",
    "addr:housenumber":"20",
    "addr:postcode":"rg14 1ly",
    "addr:street":"Rowan Drive",
    "iso:country":"GB",
    "sg:address":"20 Rowan Drive, Shaw",
    "sg:city":"Newbury",
    "sg:classifiers":[
        {
            "category":"Home & Garden",
            "subcategory":"Household Appliances",
            "type":"Retail Goods"
        },
        {
            "category":"Retail",
            "subcategory":"Repair Shop",
            "type":"Services"
        }
    ],
    "sg:phone":"+44 1635 528058",
    "sg:postcode":"RG14 1LY",
    "sg:province":"Berkshire",
    "sg:tags":[
        "machine",
        "electrical",
        "washing"
    ],
    "wof:name":"Brown & Clemens",
    "wof:placetype":"venue"
},
  "geometry": {"coordinates":[-1.32304,51.40958],"type":"Point"}
}