{
  "type": "Feature",
  "properties": {
    "iso:country":"GB",
    "sg:address":"Amersham Road",
    "sg:city":"Chesham",
    "sg:classifiers":[
        {
            "category":"Health Services",
            "subcategory":"Nursing And Care Facility",
            "type":"Services"
        }
    ],
    "sg:phone":"+44 1494 783194",
    "sg:postcode":"HP5 1NE",
    "sg:province":"Buckinghamshire",
    "sg:tags":[
        "home",
        "residential"
    ],
    "wof:name":"Chesham Bois Manor",
    "wof:placetype":"venue"
},
  "geometry": {"coordinates":[-0.6110479832,51.7015113831],"type":"Point"}
}