{
  "type": "Feature",
  "properties": {
    "addr:full":"234 Dumbarton Road, Old Kilpatrick Glasgow West Dunbartonshire G60 5LJ",
    "addr:housenumber":"234",
    "addr:postcode":"g60 5lj",
    "addr:street":"Dumbarton Road",
    "iso:country":"GB",
    "sg:address":"234 Dumbarton Road, Old Kilpatrick",
    "sg:city":"Glasgow",
    "sg:classifiers":[
        {
            "category":"Food & Beverages",
            "subcategory":"Groceries & Convenience Stores",
            "type":"Retail Goods"
        }
    ],
    "sg:phone":"+44 1389 878523",
    "sg:postcode":"G60 5LJ",
    "sg:province":"West Dunbartonshire",
    "wof:name":"Village Store",
    "wof:placetype":"venue"
},
  "geometry": {"coordinates":[-4.455903,55.922535],"type":"Point"}
}