{
  "type": "Feature",
  "properties": {
    "iso:country":"GB",
    "sg:address":"Orbital House, 85-87 Croydon Road",
    "sg:city":"Caterham",
    "sg:classifiers":[
        {
            "category":"Shopping",
            "subcategory":"Stationery & Office Supplies",
            "type":"Retail Goods"
        }
    ],
    "sg:phone":"+44 1883 346440",
    "sg:postcode":"CR3 6PD",
    "sg:province":"Surrey",
    "sg:tags":[
        "merchant",
        "paper"
    ],
    "wof:name":"Frank Crossley & Sons Ltd",
    "wof:placetype":"venue"
},
  "geometry": {"coordinates":[-0.079085,51.286091],"type":"Point"}
}