{
  "type": "Feature",
  "properties": {
    "addr:full":"Abbey Flatts Farm, Calderbridge Seascale Cumbria CA20 1DY",
    "addr:postcode":"ca20 1dy",
    "iso:country":"GB",
    "sg:address":"Abbey Flatts Farm, Calderbridge",
    "sg:city":"Seascale",
    "sg:classifiers":[
        {
            "category":"Home & Garden",
            "subcategory":"Garden Supply",
            "type":"Retail Goods"
        }
    ],
    "sg:postcode":"CA20 1DY",
    "sg:province":"Cumbria",
    "sg:tags":[
        "bulb",
        "grower"
    ],
    "wof:name":"N & R W Huck",
    "wof:placetype":"venue"
},
  "geometry": {"coordinates":[-3.48462,54.394821],"type":"Point"}
}