{
  "type": "Feature",
  "properties": {
    "iso:country":"GB",
    "sg:address":"Straglethorpe, Radcliffe On Trent",
    "sg:city":"Nottingham",
    "sg:classifiers":[
        {
            "category":"Sports & Exercise",
            "subcategory":"Golf",
            "type":"Entertainment"
        }
    ],
    "sg:phone":"+44 115 933 3344",
    "sg:postcode":"NG12 3HB",
    "sg:province":"Nottinghamshire",
    "sg:tags":[
        "club",
        "course"
    ],
    "wof:name":"Cotgrave Place Golf & Country Club",
    "wof:placetype":"venue"
},
  "geometry": {"coordinates":[-1.143924,52.949226],"type":"Point"}
}