{
  "type": "Feature",
  "properties": {
    "addr:full":"St Peters Rd Maidenhead Berkshire SL6 7QU",
    "addr:postcode":"sl6 7qu",
    "addr:street":"St Peters Rd",
    "iso:country":"GB",
    "sg:address":"St Peters Rd",
    "sg:city":"Maidenhead",
    "sg:classifiers":[
        {
            "category":"Place Of Worship",
            "type":"Public Place"
        }
    ],
    "sg:phone":"+44 1628 784053",
    "sg:postcode":"SL6 7QU",
    "sg:province":"Berkshire",
    "wof:name":"St Peters First Platt Maidenhead",
    "wof:placetype":"venue"
},
  "geometry": {"coordinates":[-0.7348009944,51.5356292725],"type":"Point"}
}