{
  "type": "Feature",
  "properties": {
    "iso:country":"GB",
    "sg:address":"64 Natland Road",
    "sg:city":"Kendal",
    "sg:classifiers":[
        {
            "category":"Building & Trades",
            "subcategory":"Construction",
            "type":"Services"
        }
    ],
    "sg:phone":"+44 1539 724986",
    "sg:postcode":"LA9 7LT",
    "sg:province":"Cumbria",
    "sg:tags":[
        "joiner",
        "carpenter"
    ],
    "wof:name":"Jonathon R Waller",
    "wof:placetype":"venue"
},
  "geometry": {"coordinates":[-2.7415020466,54.3135375977],"type":"Point"}
}