{
  "type": "Feature",
  "properties": {
    "addr:full":"Haggstones Road, Oughtibridge Sheffield South Yorkshire S35 0LP",
    "addr:postcode":"s35 0lp",
    "addr:street":"Haggstones Road",
    "iso:country":"GB",
    "sg:address":"Haggstones Road, Oughtibridge",
    "sg:city":"Sheffield",
    "sg:classifiers":[
        {
            "category":"Farming",
            "subcategory":"Livestock Farm",
            "type":"Manufacturing & Wholesale Goods"
        }
    ],
    "sg:phone":"+44 114 286 2458",
    "sg:postcode":"S35 0LP",
    "sg:province":"South Yorkshire",
    "sg:tags":[
        "others"
    ],
    "wof:name":"B A & B Perkins",
    "wof:placetype":"venue"
},
  "geometry": {"coordinates":[-1.541128993,53.4356155396],"type":"Point"}
}