{
  "type": "Feature",
  "properties": {
    "addr:full":"Lowbrook Lane Solihull West Midlands B90 1QR",
    "addr:postcode":"b90 1qr",
    "addr:street":"Lowbrook Lane",
    "iso:country":"GB",
    "sg:address":"Lowbrook Lane",
    "sg:city":"Solihull",
    "sg:classifiers":[
        {
            "category":"Autos & Motor Vehicles",
            "subcategory":"Automobile Sales",
            "type":"Retail Goods"
        }
    ],
    "sg:phone":"+44 1564 822261",
    "sg:postcode":"B90 1QR",
    "sg:province":"West Midlands",
    "sg:tags":[
        "car"
    ],
    "wof:name":"Steve Lane Cars Ltd.",
    "wof:placetype":"venue"
},
  "geometry": {"coordinates":[-1.8573759794,52.3796882629],"type":"Point"}
}