{
  "type": "Feature",
  "properties": {
    "iso:country":"GB",
    "sg:address":"Redland Green Road",
    "sg:city":"Bristol",
    "sg:classifiers":[
        {
            "category":"Place Of Worship",
            "type":"Public Place"
        },
        {
            "category":"Community Center",
            "subcategory":"Youth",
            "type":"Public Place"
        }
    ],
    "sg:phone":"+44 117 973 7423",
    "sg:postcode":"BS6 7HE",
    "sg:province":"City of Bristol",
    "sg:tags":[
        "organisation",
        "centre"
    ],
    "wof:name":"Redland Parish Church",
    "wof:placetype":"venue"
},
  "geometry": {"coordinates":[-2.603574,51.470814],"type":"Point"}
}