{
  "type": "Feature",
  "properties": {
    "iso:country":"GB",
    "sg:address":"48 The Parade, Oadby",
    "sg:city":"Leicester",
    "sg:classifiers":[
        {
            "category":"Food & Beverages",
            "subcategory":"Candy",
            "type":"Retail Goods"
        },
        {
            "category":"Food & Beverages",
            "subcategory":"Bakery",
            "type":"Retail Goods"
        }
    ],
    "sg:postcode":"LE2 5BF",
    "sg:province":"Leicestershire",
    "sg:tags":[
        "confectioner",
        "baker"
    ],
    "wof:name":"BIRDS (DERBY) LTD",
    "wof:placetype":"venue"
},
  "geometry": {"coordinates":[-1.083968,52.599483],"type":"Point"}
}