{
  "type": "Feature",
  "properties": {
    "iso:country":"GB",
    "sg:address":"Hilton Farm",
    "sg:city":"Perth",
    "sg:classifiers":[
        {
            "category":"Retail",
            "subcategory":"Auto Repair",
            "type":"Services"
        }
    ],
    "sg:phone":"+44 1738 812009",
    "sg:postcode":"PH2 8PY",
    "sg:province":"Perth and Kinross",
    "sg:tags":[
        "modification",
        "garage"
    ],
    "wof:name":"Hilton Classics",
    "wof:placetype":"venue"
},
  "geometry": {"coordinates":[-3.4324140549,56.3960533142],"type":"Point"}
}