{
  "type": "Feature",
  "properties": {
    "iso:country":"GB",
    "sg:address":"7 Katherine St",
    "sg:city":"Livingston",
    "sg:classifiers":[
        {
            "category":"Home & Garden",
            "subcategory":"Carpets & Floor Coverings",
            "type":"Retail Goods"
        }
    ],
    "sg:phone":"+44 1506 496518",
    "sg:postcode":"EH54 5HJ",
    "sg:province":"West Lothian",
    "sg:tags":[
        "cleaner",
        "upholstery"
    ],
    "wof:name":"A1 Deep Clean",
    "wof:placetype":"venue"
},
  "geometry": {"coordinates":[-3.501372,55.896767],"type":"Point"}
}