{
  "type": "Feature",
  "properties": {
    "iso:country":"GB",
    "sg:address":"25 Agar Gro",
    "sg:city":"London",
    "sg:classifiers":[
        {
            "category":"Bars & Pubs",
            "type":"Food & Drink"
        }
    ],
    "sg:phone":"+44 20 7485 2484",
    "sg:postcode":"NW1 9SL",
    "sg:province":"Greater London",
    "sg:tags":[
        "pubs",
        "inn"
    ],
    "wof:name":"Murray Arms",
    "wof:placetype":"venue"
},
  "geometry": {"coordinates":[-0.131731,51.543022],"type":"Point"}
}