{
  "type": "Feature",
  "properties": {
    "addr:full":"466 Bowes Road London Greater London N11 1NL",
    "addr:housenumber":"466",
    "addr:postcode":"n11 1nl",
    "addr:street":"Bowes Road",
    "iso:country":"GB",
    "sg:address":"466 Bowes Road",
    "sg:city":"London",
    "sg:classifiers":[
        {
            "category":"Personal",
            "subcategory":"Beauty Salon",
            "type":"Services"
        },
        {
            "category":"Personal",
            "subcategory":"Barber",
            "type":"Services"
        }
    ],
    "sg:phone":"+44 20 8368 1450",
    "sg:postcode":"N11 1NL",
    "sg:province":"Greater London",
    "sg:tags":[
        "unisex",
        "hairdresser"
    ],
    "wof:name":"Michael's",
    "wof:placetype":"venue"
},
  "geometry": {"coordinates":[-0.1405110061,51.6167793274],"type":"Point"}
}