{
  "type": "Feature",
  "properties": {
    "iso:country":"GB",
    "sg:address":", Iping",
    "sg:city":"Midhurst",
    "sg:classifiers":[
        {
            "category":"Travel",
            "subcategory":"Hotels & Motels",
            "type":"Entertainment"
        }
    ],
    "sg:phone":"+44 1730 813634",
    "sg:postcode":"GU29 0JP",
    "sg:province":"West Sussex",
    "sg:tags":[
        "house",
        "guest"
    ],
    "wof:name":"Fitzhall Guest House",
    "wof:placetype":"venue"
},
  "geometry": {"coordinates":[-0.7856529951,50.9987373352],"type":"Point"}
}