{
  "type": "Feature",
  "properties": {
    "iso:country":"GB",
    "sg:address":"Haverhill House, 13 Bond Street",
    "sg:city":"Cromer",
    "sg:classifiers":[
        {
            "category":"Military Area",
            "subcategory":"Air Force Base",
            "type":"Public Place"
        }
    ],
    "sg:phone":"+44 1263 512645",
    "sg:postcode":"NR27 9DA",
    "sg:province":"Norfolk",
    "sg:tags":[
        "taxi",
        "hire",
        "private"
    ],
    "wof:name":"Blue Star Taxis",
    "wof:placetype":"venue"
},
  "geometry": {"coordinates":[1.301337,52.930313],"type":"Point"}
}