{
  "type": "Feature",
  "properties": {
    "iso:country":"GB",
    "sg:address":"Market Place, Middlam",
    "sg:city":"Leyburn",
    "sg:classifiers":[
        {
            "category":"Restaurant",
            "type":"Food & Drink"
        }
    ],
    "sg:phone":"+44 1969 623568",
    "sg:postcode":"DL8 4NP",
    "sg:province":"North Yorkshire",
    "wof:name":"The Stable Door Restaurant",
    "wof:placetype":"venue"
},
  "geometry": {"coordinates":[-1.8044689894,54.2854766846],"type":"Point"}
}