{
  "type": "Feature",
  "properties": {
    "addr:full":"Hubberston Dairy Milford Haven Pembrokeshire SA73 3PU",
    "addr:postcode":"sa73 3pu",
    "iso:country":"GB",
    "sg:address":"Hubberston Dairy",
    "sg:city":"Milford Haven",
    "sg:classifiers":[
        {
            "category":"Farming",
            "subcategory":"Dairy Farm",
            "type":"Manufacturing & Wholesale Goods"
        }
    ],
    "sg:phone":"+44 1646 692253",
    "sg:postcode":"SA73 3PU",
    "sg:province":"Pembrokeshire",
    "wof:name":"D Charles & Son",
    "wof:placetype":"venue"
},
  "geometry": {"coordinates":[-5.04843,51.717262],"type":"Point"}
}