{
  "type": "Feature",
  "properties": {
    "iso:country":"GB",
    "sg:address":"1 Roman Villas",
    "sg:city":"Shepton Mallet",
    "sg:classifiers":[
        {
            "category":"Autos & Motor Vehicles",
            "subcategory":"Auto Supplies",
            "type":"Retail Goods"
        }
    ],
    "sg:postcode":"BA4 4TU",
    "sg:province":"Somerset",
    "sg:tags":[
        "towing",
        "eqpt",
        "trailer"
    ],
    "wof:name":"South-West Trailer Hire Ltd",
    "wof:placetype":"venue"
},
  "geometry": {"coordinates":[-2.5299699306,51.1846351624],"type":"Point"}
}