{
  "type": "Feature",
  "properties": {
    "addr:full":"19 Sidney Road Walton-on-thames Surrey KT12 2NA",
    "addr:housenumber":"19",
    "addr:postcode":"kt12 2na",
    "addr:street":"Sidney Road",
    "iso:country":"GB",
    "sg:address":"19 Sidney Road",
    "sg:city":"Walton-on-thames",
    "sg:classifiers":[
        {
            "category":"Retail",
            "subcategory":"Veterinary Services",
            "type":"Services"
        }
    ],
    "sg:phone":"+44 1932 228915",
    "sg:postcode":"KT12 2NA",
    "sg:province":"Surrey",
    "sg:tags":[
        "surgeon"
    ],
    "wof:name":"Andrew J Manfield",
    "wof:placetype":"venue"
},
  "geometry": {"coordinates":[-0.4130089879,51.3874053955],"type":"Point"}
}