{
  "type": "Feature",
  "properties": {
    "iso:country":"GB",
    "sg:address":"7 London Rd",
    "sg:city":"Sandbach",
    "sg:classifiers":[
        {
            "category":"Organizations",
            "subcategory":"Non-profit Organization",
            "type":"Services"
        }
    ],
    "sg:phone":"+44 1270 759190",
    "sg:postcode":"CW11 3BB",
    "sg:province":"Cheshire",
    "sg:tags":[
        "organisation",
        "voluntary",
        "charity"
    ],
    "wof:name":"Hilary House",
    "wof:placetype":"venue"
},
  "geometry": {"coordinates":[-2.3929820061,53.1514015198],"type":"Point"}
}