{
  "type": "Feature",
  "properties": {
    "addr:full":"121/123 Praed Street London Greater London W2 1RL",
    "addr:housenumber":"121 / 123",
    "addr:postcode":"w2 1rl",
    "addr:street":"Praed Street",
    "iso:country":"GB",
    "sg:address":"121/123 Praed Street",
    "sg:city":"London",
    "sg:classifiers":[
        {
            "category":"Professional",
            "subcategory":"Detective & Security Services",
            "type":"Services"
        }
    ],
    "sg:phone":"+44 20 7262 2450",
    "sg:postcode":"W2 1RL",
    "sg:province":"Greater London",
    "sg:tags":[
        "alarm",
        "burglar",
        "system"
    ],
    "wof:name":"Barry Bros (Security Devices)",
    "wof:placetype":"venue"
},
  "geometry": {"coordinates":[-0.17318,51.516762],"type":"Point"}
}