{
  "type": "Feature",
  "properties": {
    "addr:full":"20 Deanery Way Stockport Cheshire SK1 1PY",
    "addr:housenumber":"20",
    "addr:postcode":"sk1 1py",
    "addr:street":"Deanery Way",
    "iso:country":"GB",
    "sg:address":"20 Deanery Way",
    "sg:city":"Stockport",
    "sg:classifiers":[
        {
            "category":"Banks & Credit Unions",
            "subcategory":"Financial Services",
            "type":"Services"
        }
    ],
    "sg:phone":"+44 161 480 3920",
    "sg:postcode":"SK1 1PY",
    "sg:province":"Cheshire",
    "sg:tags":[
        "building",
        "society"
    ],
    "wof:name":"Bradford & Bingley Plc",
    "wof:placetype":"venue"
},
  "geometry": {"coordinates":[-2.1588249207,53.4113235474],"type":"Point"}
}