{
  "type": "Feature",
  "properties": {
    "addr:full":"13 Muirhall Road Larbert Falkirk FK5 4RF",
    "addr:housenumber":"13",
    "addr:postcode":"fk5 4rf",
    "addr:street":"Muirhall Road",
    "iso:country":"GB",
    "sg:address":"13 Muirhall Road",
    "sg:city":"Larbert",
    "sg:classifiers":[
        {
            "category":"Autos & Motor Vehicles",
            "subcategory":"Automobile Sales",
            "type":"Retail Goods"
        },
        {
            "category":"Retail",
            "subcategory":"Auto Repair",
            "type":"Services"
        }
    ],
    "sg:phone":"+44 1324 552209",
    "sg:postcode":"FK5 4RF",
    "sg:province":"Falkirk",
    "sg:tags":[
        "body",
        "car"
    ],
    "wof:name":"Millers Coachworks",
    "wof:placetype":"venue"
},
  "geometry": {"coordinates":[-3.830373,56.029442],"type":"Point"}
}