{
  "type": "Feature",
  "properties": {
    "addr:full":"14 Ack Lane East, Bramhall Stockport Cheshire SK7 2BY",
    "addr:housenumber":"14",
    "addr:postcode":"sk7 2by",
    "addr:street":"Ack Lane East",
    "iso:country":"GB",
    "sg:address":"14 Ack Lane East, Bramhall",
    "sg:city":"Stockport",
    "sg:classifiers":[
        {
            "category":"Professional",
            "subcategory":"Accounting & Tax Preparation",
            "type":"Services"
        }
    ],
    "sg:postcode":"SK7 2BY",
    "sg:province":"Cheshire",
    "sg:tags":[
        "accountant"
    ],
    "wof:name":"Griffith Wilson & Co.",
    "wof:placetype":"venue"
},
  "geometry": {"coordinates":[-2.167256,53.35878],"type":"Point"}
}