{
  "type": "Feature",
  "properties": {
    "addr:full":"10-16 Brook Road Benfleet Essex SS7 5JA",
    "addr:housenumber":"10-16",
    "addr:postcode":"ss7 5ja",
    "addr:street":"Brook Road",
    "iso:country":"GB",
    "sg:address":"10-16 Brook Road",
    "sg:city":"Benfleet",
    "sg:classifiers":[
        {
            "category":"Health Services",
            "subcategory":"Nursing And Care Facility",
            "type":"Services"
        }
    ],
    "sg:phone":"+44 1268 752327",
    "sg:postcode":"SS7 5JA",
    "sg:province":"Essex",
    "sg:tags":[
        "home"
    ],
    "wof:name":"Hopes Green Care Centre",
    "wof:placetype":"venue"
},
  "geometry": {"coordinates":[0.5506700277,51.5617790222],"type":"Point"}
}