{
  "type": "Feature",
  "properties": {
    "iso:country":"GB",
    "sg:address":"387 Alfred St North",
    "sg:city":"Nottingham",
    "sg:classifiers":[
        {
            "category":"Home & Garden",
            "subcategory":"Carpets & Floor Coverings",
            "type":"Retail Goods"
        }
    ],
    "sg:phone":"+44 115 958 9580",
    "sg:postcode":"NG3 1AA",
    "sg:province":"Nottinghamshire",
    "sg:tags":[
        "carpets",
        "rug",
        "matting"
    ],
    "wof:name":"B J M Flooring & Supplies",
    "wof:placetype":"venue"
},
  "geometry": {"coordinates":[-1.15009,52.96299],"type":"Point"}
}