{
  "type": "Feature",
  "properties": {
    "addr:full":"7 Swindlers Drove Spalding Cambridgeshire PE12 6BS",
    "addr:housenumber":"7",
    "addr:postcode":"pe12 6bs",
    "addr:street":"Swindlers Drove Spalding",
    "iso:country":"GB",
    "sg:address":"7 Swindlers Drove",
    "sg:city":"Spalding",
    "sg:classifiers":[
        {
            "category":"Home & Garden",
            "subcategory":"Garden Supply",
            "type":"Retail Goods"
        }
    ],
    "sg:phone":"+44 1775 712170",
    "sg:postcode":"PE12 6BS",
    "sg:province":"Cambridgeshire",
    "sg:tags":[
        "nursery",
        "centre"
    ],
    "wof:name":"J Cunnington",
    "wof:placetype":"venue"
},
  "geometry": {"coordinates":[-0.1104620025,52.7843933105],"type":"Point"}
}