{
  "type": "Feature",
  "properties": {
    "iso:country":"GB",
    "sg:address":"24 Cowell Street",
    "sg:city":"Llanelli",
    "sg:classifiers":[
        {
            "category":"Food & Beverages",
            "subcategory":"Bakery",
            "type":"Retail Goods"
        }
    ],
    "sg:postcode":"SA15 1UU",
    "sg:province":"Carmarthenshire",
    "sg:tags":[
        "baker"
    ],
    "wof:name":"The Rolypoly",
    "wof:placetype":"venue"
},
  "geometry": {"coordinates":[-4.162051,51.68161],"type":"Point"}
}