{
  "type": "Feature",
  "properties": {
    "addr:full":"Plas Coch, Lower Denbigh Road St Asaph Conwy LL17 0EP",
    "addr:postcode":"ll17 0ep",
    "addr:street":"Plas Coch Lower Denbigh Road St",
    "iso:country":"GB",
    "sg:address":"Plas Coch, Lower Denbigh Road",
    "sg:city":"St Asaph",
    "sg:classifiers":[
        {
            "category":"Farming",
            "subcategory":"Livestock Farm",
            "type":"Manufacturing & Wholesale Goods"
        }
    ],
    "sg:phone":"+44 1745 730201",
    "sg:postcode":"LL17 0EP",
    "sg:province":"Conwy",
    "sg:tags":[
        "others"
    ],
    "wof:name":"E O Jones",
    "wof:placetype":"venue"
},
  "geometry": {"coordinates":[-3.448719,53.256153],"type":"Point"}
}