{
  "type": "Feature",
  "properties": {
    "iso:country":"GB",
    "sg:address":"3 Main St, Douglas",
    "sg:city":"Lanark",
    "sg:classifiers":[
        {
            "category":"Shopping",
            "subcategory":"Clothing, Apparel, & Fashions",
            "type":"Retail Goods"
        }
    ],
    "sg:postcode":"ML11 0QW",
    "sg:province":"South Lanarkshire",
    "sg:tags":[
        "ladieswear"
    ],
    "wof:name":"Taylor & McLeod",
    "wof:placetype":"venue"
},
  "geometry": {"coordinates":[-3.848421,55.555752],"type":"Point"}
}