{
  "type": "Feature",
  "properties": {
    "iso:country":"GB",
    "sg:address":"Biggin Hill Garage, Leaves Grn Road",
    "sg:city":"Keston",
    "sg:classifiers":[
        {
            "category":"Shopping",
            "subcategory":"Bicycles & Sporting Goods",
            "type":"Retail Goods"
        }
    ],
    "sg:phone":"+44 1959 570958",
    "sg:postcode":"BR2 6DQ",
    "sg:province":"Kent",
    "sg:tags":[
        "cycle",
        "accessory"
    ],
    "wof:name":"Biggin Bikes",
    "wof:placetype":"venue"
},
  "geometry": {"coordinates":[0.0281700008,51.3614654541],"type":"Point"}
}