{
  "type": "Feature",
  "properties": {
    "iso:country":"GB",
    "sg:address":"2 Church Rd, Snape",
    "sg:city":"Saxmundham",
    "sg:classifiers":[
        {
            "category":"Communications",
            "type":"Services"
        }
    ],
    "sg:postcode":"IP17 1SZ",
    "sg:province":"Suffolk",
    "sg:tags":[
        "system",
        "music",
        "public",
        "address"
    ],
    "wof:name":"Cotton,Andrew,",
    "wof:placetype":"venue"
},
  "geometry": {"coordinates":[1.500842,52.170677],"type":"Point"}
}