{
  "type": "Feature",
  "properties": {
    "iso:country":"GB",
    "sg:address":"33 Chichester Road",
    "sg:city":"South Shields",
    "sg:classifiers":[
        {
            "category":"Shopping",
            "subcategory":"Bicycles & Sporting Goods",
            "type":"Retail Goods"
        },
        {
            "category":"Sports & Exercise",
            "subcategory":"Sports Center",
            "type":"Entertainment"
        }
    ],
    "sg:phone":"+44 191 456 1678",
    "sg:postcode":"NE33 4AA",
    "sg:province":"Tyne and Wear",
    "sg:tags":[
        "shop",
        "retailer"
    ],
    "wof:name":"Leisure World",
    "wof:placetype":"venue"
},
  "geometry": {"coordinates":[-1.431213,54.987267],"type":"Point"}
}