{
  "type": "Feature",
  "properties": {
    "iso:country":"GB",
    "sg:address":"137a Station Rd",
    "sg:city":"Nottingham",
    "sg:classifiers":[
        {
            "category":"Professional",
            "subcategory":"Printing & Photocopies",
            "type":"Services"
        }
    ],
    "sg:phone":"+44 115 922 0603",
    "sg:postcode":"NG9 2AZ",
    "sg:province":"Nottinghamshire",
    "sg:tags":[
        "duplicating",
        "copying"
    ],
    "wof:name":"Photofax & Co",
    "wof:placetype":"venue"
},
  "geometry": {"coordinates":[-1.2113829851,52.9246749878],"type":"Point"}
}