{
  "type": "Feature",
  "properties": {
    "iso:country":"GB",
    "sg:address":"Martells Barn, Flough Lane",
    "sg:city":"Colchester",
    "sg:classifiers":[
        {
            "category":"Home & Garden",
            "subcategory":"Building Materials",
            "type":"Retail Goods"
        }
    ],
    "sg:postcode":"CO7 7RU",
    "sg:province":"Essex",
    "sg:tags":[
        "insulation",
        "installers"
    ],
    "wof:name":"Malcolm H Cater",
    "wof:placetype":"venue"
},
  "geometry": {"coordinates":[0.9789800048,51.9159393311],"type":"Point"}
}