{
  "type": "Feature",
  "properties": {
    "addr:full":"42 Frys Lane, Everton Lymington Hampshire SO41 0JY",
    "addr:housenumber":"42",
    "addr:postcode":"so41 0jy",
    "addr:street":"Frys Lane",
    "iso:country":"GB",
    "sg:address":"42 Frys Lane, Everton",
    "sg:city":"Lymington",
    "sg:classifiers":[
        {
            "category":"Professional",
            "subcategory":"Art Services",
            "type":"Services"
        }
    ],
    "sg:phone":"+44 1590 642676",
    "sg:postcode":"SO41 0JY",
    "sg:province":"Hampshire",
    "sg:tags":[
        "graphic",
        "designer"
    ],
    "wof:name":"Cooper Johnson Ltd",
    "wof:placetype":"venue"
},
  "geometry": {"coordinates":[-1.595612,50.747467],"type":"Point"}
}