{
  "type": "Feature",
  "properties": {
    "iso:country":"GB",
    "sg:address":"Defford Mill, Dunstall",
    "sg:city":"Worcester",
    "sg:classifiers":[
        {
            "category":"Shopping",
            "subcategory":"Department Store",
            "type":"Retail Goods"
        },
        {
            "category":"Shopping",
            "type":"Retail Goods"
        }
    ],
    "sg:phone":"+44 1386 757300",
    "sg:postcode":"WR8 9DF",
    "sg:province":"Gloucestershire",
    "sg:tags":[
        "merchant"
    ],
    "wof:name":"Countrywide Farmers Plc",
    "wof:placetype":"venue"
},
  "geometry": {"coordinates":[-2.117219,52.0867],"type":"Point"}
}