{
  "type": "Feature",
  "properties": {
    "addr:full":"6 Cordingley Street Bradford West Yorkshire BD4 0PP",
    "addr:housenumber":"6",
    "addr:postcode":"bd4 0pp",
    "addr:street":"Cordingley Street",
    "iso:country":"GB",
    "sg:address":"6 Cordingley Street",
    "sg:city":"Bradford",
    "sg:classifiers":[
        {
            "category":"Autos & Motor Vehicles",
            "subcategory":"Automobile Sales",
            "type":"Retail Goods"
        }
    ],
    "sg:postcode":"BD4 0PP",
    "sg:province":"West Yorkshire",
    "sg:tags":[
        "car",
        "commercial"
    ],
    "wof:name":"N & J Blamires",
    "wof:placetype":"venue"
},
  "geometry": {"coordinates":[-1.7097320557,53.7686042786],"type":"Point"}
}