{
  "type": "Feature",
  "properties": {
    "addr:full":"10 Ely Place London Greater London EC1N 6RY",
    "addr:housenumber":"10",
    "addr:postcode":"ec1n 6ry",
    "addr:street":"Ely Place",
    "iso:country":"GB",
    "sg:address":"10 Ely Place",
    "sg:city":"London",
    "sg:classifiers":[
        {
            "category":"Freight",
            "type":"Transportation"
        }
    ],
    "sg:postcode":"EC1N 6RY",
    "sg:province":"Greater London",
    "sg:tags":[
        "overseas",
        "shipping",
        "removal"
    ],
    "wof:name":"Lyras Shipping Ltd.",
    "wof:placetype":"venue"
},
  "geometry": {"coordinates":[-0.107232,51.518486],"type":"Point"}
}