{
  "type": "Feature",
  "properties": {
    "addr:full":"95 London Road Sawbridgeworth Essex CM21 9JJ",
    "addr:housenumber":"95",
    "addr:postcode":"cm21 9jj",
    "addr:street":"London Road",
    "iso:country":"GB",
    "sg:address":"95 London Road",
    "sg:city":"Sawbridgeworth",
    "sg:classifiers":[
        {
            "category":"Building & Trades",
            "subcategory":"Landscaping Services",
            "type":"Services"
        }
    ],
    "sg:phone":"+44 1279 429904",
    "sg:postcode":"CM21 9JJ",
    "sg:province":"Essex",
    "sg:tags":[
        "landscape",
        "contractor"
    ],
    "wof:name":"Noel Landscapes",
    "wof:placetype":"venue"
},
  "geometry": {"coordinates":[0.147586,51.814091],"type":"Point"}
}