{
  "type": "Feature",
  "properties": {
    "addr:full":"Collane 261 Hatherley Road Cheltenham Gloucestershire GL51 6HF",
    "addr:housenumber":"261",
    "addr:postcode":"gl51 6hf",
    "addr:street":"Hatherley Road",
    "iso:country":"GB",
    "sg:address":"Collane 261 Hatherley Road",
    "sg:city":"Cheltenham",
    "sg:classifiers":[
        {
            "category":"Shopping",
            "subcategory":"Bicycles & Sporting Goods",
            "type":"Retail Goods"
        }
    ],
    "sg:postcode":"GL51 6HF",
    "sg:province":"Gloucestershire",
    "sg:tags":[
        "dance",
        "balletwear"
    ],
    "wof:name":"Heroes & Villains Ltd",
    "wof:placetype":"venue"
},
  "geometry": {"coordinates":[-2.11395,51.890171],"type":"Point"}
}