{
  "type": "Feature",
  "properties": {
    "addr:full":"25 Cheriton Parade, Queens Crescent London Greater London NW5 4EZ",
    "addr:housenumber":"25",
    "addr:postcode":"nw5 4ez",
    "addr:street":"Cheriton Parade Queens Crescent",
    "iso:country":"GB",
    "sg:address":"25 Cheriton Parade, Queens Crescent",
    "sg:city":"London",
    "sg:classifiers":[
        {
            "category":"Real Estate",
            "subcategory":"Architect",
            "type":"Services"
        }
    ],
    "sg:postcode":"NW5 4EZ",
    "sg:province":"Greater London",
    "wof:name":"Art of Living Architects & Interior Design",
    "wof:placetype":"venue"
},
  "geometry": {"coordinates":[-0.15327,51.54858],"type":"Point"}
}