{
  "type": "Feature",
  "properties": {
    "addr:full":"Laundry Cottage, Twineham Lane Hassocks East Sussex BN6 9JF",
    "addr:postcode":"bn6 9jf",
    "addr:street":"Twineham Lane",
    "iso:country":"GB",
    "sg:address":"Laundry Cottage, Twineham Lane",
    "sg:city":"Hassocks",
    "sg:classifiers":[
        {
            "category":"Autos & Motor Vehicles",
            "subcategory":"Automobile Sales",
            "type":"Retail Goods"
        }
    ],
    "sg:postcode":"BN6 9JF",
    "sg:province":"East Sussex",
    "sg:tags":[
        "car",
        "specialist",
        "sales",
        "classic"
    ],
    "wof:name":"Mid Sussex Minors",
    "wof:placetype":"venue"
},
  "geometry": {"coordinates":[-0.1402689964,50.9239959717],"type":"Point"}
}