{
  "type": "Feature",
  "properties": {
    "addr:full":"107 High St Hungerford Berkshire RG17 0ND",
    "addr:housenumber":"107",
    "addr:postcode":"rg17 0nd",
    "addr:street":"High St",
    "iso:country":"GB",
    "sg:address":"107 High St",
    "sg:city":"Hungerford",
    "sg:classifiers":[
        {
            "category":"Banks & Credit Unions",
            "subcategory":"Investment Brokerage",
            "type":"Services"
        }
    ],
    "sg:postcode":"RG17 0ND",
    "sg:province":"Berkshire",
    "sg:tags":[
        "contractor"
    ],
    "wof:name":"Radbourne,Tim,(Agricultural Contracting)",
    "wof:placetype":"venue"
},
  "geometry": {"coordinates":[-1.515665,51.41399],"type":"Point"}
}