{
  "type": "Feature",
  "properties": {
    "addr:full":"2 North, Cray Road Bexley Kent DA5 3LZ",
    "addr:housenumber":"2",
    "addr:postcode":"da5 3lz",
    "addr:street":"North Cray Road",
    "iso:country":"GB",
    "sg:address":"2 North, Cray Road",
    "sg:city":"Bexley",
    "sg:classifiers":[
        {
            "category":"Professional",
            "subcategory":"Business Services",
            "type":"Services"
        }
    ],
    "sg:phone":"+44 1322 522201",
    "sg:postcode":"DA5 3LZ",
    "sg:province":"Kent",
    "sg:tags":[
        "answering"
    ],
    "wof:name":"Healthcall Ltd.",
    "wof:placetype":"venue"
},
  "geometry": {"coordinates":[0.15317,51.439915],"type":"Point"}
}