{
  "type": "Feature",
  "properties": {
    "addr:full":"12 Clytha Park Road Newport Newport NP20 4PB",
    "addr:housenumber":"12",
    "addr:postcode":"np20 4pb",
    "addr:street":"Clytha Park Road",
    "iso:country":"GB",
    "sg:address":"12 Clytha Park Road",
    "sg:city":"Newport",
    "sg:classifiers":[
        {
            "category":"Professional",
            "subcategory":"Lawyer & Legal Services",
            "type":"Services"
        }
    ],
    "sg:phone":"+44 1633 267403",
    "sg:postcode":"NP20 4PB",
    "sg:province":"Newport",
    "sg:tags":[
        "barrister"
    ],
    "wof:name":"Temple Chambers",
    "wof:placetype":"venue"
},
  "geometry": {"coordinates":[-3.0045089722,51.5873222351],"type":"Point"}
}