{
  "type": "Feature",
  "properties": {
    "iso:country":"GB",
    "sg:address":"68 Mill Lane, Newbold Verdon",
    "sg:city":"Leicester",
    "sg:classifiers":[
        {
            "category":"Wholesale",
            "subcategory":"Construction Materials",
            "type":"Manufacturing & Wholesale Goods"
        }
    ],
    "sg:phone":"+44 1455 822830",
    "sg:postcode":"LE9 9PU",
    "sg:province":"Leicestershire",
    "sg:tags":[
        "refractory"
    ],
    "wof:name":"Magna Industrials Ltd.",
    "wof:placetype":"venue"
},
  "geometry": {"coordinates":[-1.339316,52.631908],"type":"Point"}
}