{
  "type": "Feature",
  "properties": {
    "iso:country":"GB",
    "sg:address":"47 Esplanade",
    "sg:city":"Burnham-on-sea",
    "sg:classifiers":[
        {
            "category":"Communications",
            "subcategory":"Film & Video Production",
            "type":"Services"
        }
    ],
    "sg:postcode":"TA8 2AQ",
    "sg:province":"Somerset",
    "sg:tags":[
        "illustrator",
        "artist"
    ],
    "wof:name":"Ceramic Images & Prints",
    "wof:placetype":"venue"
},
  "geometry": {"coordinates":[-2.998827,51.23991],"type":"Point"}
}