{
  "type": "Feature",
  "properties": {
    "iso:country":"GB",
    "sg:address":"4 Lower Rock Gardens",
    "sg:city":"Brighton",
    "sg:classifiers":[
        {
            "category":"Travel",
            "subcategory":"Hotels & Motels",
            "type":"Entertainment"
        }
    ],
    "sg:phone":"+44 1273 604686",
    "sg:postcode":"BN2 1PG",
    "sg:province":"East Sussex",
    "wof:name":"Suffolk House Hotel",
    "wof:placetype":"venue"
},
  "geometry": {"coordinates":[-0.130579,50.819523],"type":"Point"}
}