{
  "type": "Feature",
  "properties": {
    "addr:full":"Environmental Health Dept, Cleansing Division, Station La Wymondham Norfolk NR18 9RS",
    "addr:postcode":"nr18 9rs",
    "addr:street":"La",
    "iso:country":"GB",
    "sg:address":"Environmental Health Dept, Cleansing Division, Station La",
    "sg:city":"Wymondham",
    "sg:classifiers":[
        {
            "category":"Government",
            "subcategory":"Office",
            "type":"Public Place"
        }
    ],
    "sg:phone":"+44 1603 810441",
    "sg:postcode":"NR18 9RS",
    "sg:province":"Norfolk",
    "sg:tags":[
        "local"
    ],
    "wof:name":"South Norfolk Council",
    "wof:placetype":"venue"
},
  "geometry": {"coordinates":[1.1160639524,52.5702285767],"type":"Point"}
}