{
  "type": "Feature",
  "properties": {
    "addr:full":"38 Shuttlewood Road Chesterfield Derbyshire S44 6NU",
    "addr:housenumber":"38",
    "addr:postcode":"s44 6nu",
    "addr:street":"Shuttlewood Road",
    "iso:country":"GB",
    "sg:address":"38 Shuttlewood Road",
    "sg:city":"Chesterfield",
    "sg:classifiers":[
        {
            "category":"Building & Trades",
            "subcategory":"Plumbing",
            "type":"Services"
        }
    ],
    "sg:phone":"+44 1246 824723",
    "sg:postcode":"S44 6NU",
    "sg:province":"Derbyshire",
    "sg:tags":[
        "central",
        "heating"
    ],
    "wof:name":"K Davison Plumbing & Heating",
    "wof:placetype":"venue"
},
  "geometry": {"coordinates":[-1.2936110497,53.2383842468],"type":"Point"}
}