{
  "type": "Feature",
  "properties": {
    "iso:country":"GB",
    "sg:address":"45 Shakespeare Road",
    "sg:city":"Exeter",
    "sg:classifiers":[
        {
            "category":"Shopping",
            "subcategory":"Party Supplies",
            "type":"Retail Goods"
        },
        {
            "category":"Recreation",
            "subcategory":"Dance Hall",
            "type":"Entertainment"
        }
    ],
    "sg:phone":"+44 1392 434698",
    "sg:postcode":"EX2 6BU",
    "sg:province":"Devon",
    "sg:tags":[
        "mobile",
        "operator",
        "disco"
    ],
    "wof:name":"M Double Disco & Karoake",
    "wof:placetype":"venue"
},
  "geometry": {"coordinates":[-3.508671,50.711338],"type":"Point"}
}