{
  "type": "Feature",
  "properties": {
    "addr:full":"Broad Farm, The Terrace York North Yorkshire YO62 5XZ",
    "addr:postcode":"yo62 5xz",
    "addr:street":"The Terrace",
    "iso:country":"GB",
    "sg:address":"Broad Farm, The Terrace",
    "sg:city":"York",
    "sg:classifiers":[
        {
            "category":"Banks & Credit Unions",
            "subcategory":"Investment Brokerage",
            "type":"Services"
        }
    ],
    "sg:phone":"+44 1439 788532",
    "sg:postcode":"YO62 5XZ",
    "sg:province":"North Yorkshire",
    "sg:tags":[
        "contractor"
    ],
    "wof:name":"Paul F Hogarth",
    "wof:placetype":"venue"
},
  "geometry": {"coordinates":[-1.04189,54.2038],"type":"Point"}
}