{
  "type": "Feature",
  "properties": {
    "addr:full":"40 Sweet Briar Rd, Stanway Colchester Essex CO3 5HJ",
    "addr:housenumber":"40",
    "addr:postcode":"co3 5hj",
    "addr:street":"Sweet Briar Rd",
    "iso:country":"GB",
    "sg:address":"40 Sweet Briar Rd, Stanway",
    "sg:city":"Colchester",
    "sg:classifiers":[
        {
            "category":"Health Services",
            "subcategory":"Podiatrist",
            "type":"Services"
        }
    ],
    "sg:phone":"+44 1206 765934",
    "sg:postcode":"CO3 5HJ",
    "sg:province":"Essex",
    "sg:tags":[
        "podiatrists",
        "chiropodist"
    ],
    "wof:name":"Mr Terence Barfield",
    "wof:placetype":"venue"
},
  "geometry": {"coordinates":[0.84286,51.883598],"type":"Point"}
}