{
  "type": "Feature",
  "properties": {
    "iso:country":"GB",
    "sg:address":"107 Norwich Road",
    "sg:city":"Wisbech",
    "sg:classifiers":[
        {
            "category":"Professional",
            "subcategory":"Accounting & Tax Preparation",
            "type":"Services"
        }
    ],
    "sg:phone":"+44 1945 464679",
    "sg:postcode":"PE13 2BB",
    "sg:province":"Cambridgeshire",
    "sg:tags":[
        "payroll"
    ],
    "wof:name":"Wisbech Payroll Services",
    "wof:placetype":"venue"
},
  "geometry": {"coordinates":[0.1674569994,52.6640853882],"type":"Point"}
}