{
  "type": "Feature",
  "properties": {
    "iso:country":"GB",
    "sg:address":"Unit 9 Prospect Industrial Centre, Platt La",
    "sg:city":"Wigan",
    "sg:classifiers":[
        {
            "category":"Government",
            "subcategory":"Office",
            "type":"Public Place"
        }
    ],
    "sg:phone":"+44 1942 521127",
    "sg:postcode":"WN2 3PA",
    "sg:province":"Lancashire",
    "sg:tags":[
        "local"
    ],
    "wof:name":"Hi Security",
    "wof:placetype":"venue"
},
  "geometry": {"coordinates":[-2.5778930187,53.5339851379],"type":"Point"}
}