{
  "type": "Feature",
  "properties": {
    "addr:full":"19 Upper Mall London Greater London W6 9TA",
    "addr:housenumber":"19",
    "addr:postcode":"w6 9ta",
    "addr:street":"Upper Mall",
    "iso:country":"GB",
    "sg:address":"19 Upper Mall",
    "sg:city":"London",
    "sg:classifiers":[
        {
            "category":"Bars & Pubs",
            "type":"Food & Drink"
        }
    ],
    "sg:phone":"+44 20 8748 5405",
    "sg:postcode":"W6 9TA",
    "sg:province":"Greater London",
    "sg:tags":[
        "pubs",
        "inn"
    ],
    "wof:name":"The Dove",
    "wof:placetype":"venue"
},
  "geometry": {"coordinates":[-0.2352209985,51.4903907776],"type":"Point"}
}