{
  "type": "Feature",
  "properties": {
    "iso:country":"GB",
    "sg:address":"London Centre, 7 Brechin Place",
    "sg:city":"South Kensington",
    "sg:classifiers":[
        {
            "category":"Education",
            "subcategory":"University",
            "type":"Public Place"
        }
    ],
    "sg:phone":"+44 20 7373 6413",
    "sg:postcode":"SW7 4QB",
    "sg:province":"Greater London",
    "sg:tags":[
        "medical",
        "school"
    ],
    "wof:name":"Lawrence University",
    "wof:placetype":"venue"
},
  "geometry": {"coordinates":[-0.18095,51.49139],"type":"Point"}
}