{
  "type": "Feature",
  "properties": {
    "addr:full":"200 Woodlands Court, Ash Ridge Road, Almondsbury Bristol Gloucestershire BS32 4LB",
    "addr:housenumber":"200",
    "addr:postcode":"bs32 4lb",
    "addr:street":"Woodlands Court Ash Ridge Road",
    "iso:country":"GB",
    "sg:address":"200 Woodlands Court, Ash Ridge Road, Almondsbury",
    "sg:city":"Bristol",
    "sg:classifiers":[
        {
            "category":"Professional",
            "subcategory":"Computer Services",
            "type":"Services"
        }
    ],
    "sg:phone":"+44 1454 619700",
    "sg:postcode":"BS32 4LB",
    "sg:province":"Gloucestershire",
    "sg:tags":[
        "consultant"
    ],
    "wof:name":"Admiral Management",
    "wof:placetype":"venue"
},
  "geometry": {"coordinates":[-2.564619,51.556526],"type":"Point"}
}