{
  "type": "Feature",
  "properties": {
    "iso:country":"GB",
    "sg:address":"7 & 8 Charlotte Road",
    "sg:city":"London",
    "sg:classifiers":[
        {
            "category":"Real Estate",
            "subcategory":"Developer",
            "type":"Services"
        }
    ],
    "sg:phone":"+44 20 7033 0494",
    "sg:postcode":"EC2A 3DH",
    "sg:province":"Greater London",
    "sg:tags":[
        "calligrapher"
    ],
    "wof:name":"Alphabet Soup",
    "wof:placetype":"venue"
},
  "geometry": {"coordinates":[-0.08137,51.526691],"type":"Point"}
}