{
  "type": "Feature",
  "properties": {
    "iso:country":"GB",
    "sg:address":"Surgery, Fairweather Ho, Parkhurst Rd",
    "sg:city":"Holloway",
    "sg:classifiers":[
        {
            "category":"Health Services",
            "subcategory":"Doctor",
            "type":"Services"
        }
    ],
    "sg:phone":"+44 20 7607 1339",
    "sg:postcode":"N7 0NS",
    "sg:province":"Greater London",
    "sg:tags":[
        "practitioners"
    ],
    "wof:name":"Rosenthal, D",
    "wof:placetype":"venue"
},
  "geometry": {"coordinates":[-0.12308,51.554722],"type":"Point"}
}