{
  "type": "Feature",
  "properties": {
    "iso:country":"GB",
    "sg:address":"Stevenage Indoor Market",
    "sg:city":"Stevenage",
    "sg:classifiers":[
        {
            "category":"Shopping",
            "subcategory":"Pets & Pet Supplies",
            "type":"Retail Goods"
        }
    ],
    "sg:phone":"+44 1438 368720",
    "sg:postcode":"SG1 1EP",
    "sg:province":"Hertfordshire",
    "wof:name":"Stevenage Pet Stall",
    "wof:placetype":"venue"
},
  "geometry": {"coordinates":[-0.18868,51.905609],"type":"Point"}
}