{
  "type": "Feature",
  "properties": {
    "iso:country":"GB",
    "sg:address":"50 Wooteys Way",
    "sg:city":"Alton",
    "sg:classifiers":[
        {
            "category":"Place Of Worship",
            "type":"Public Place"
        }
    ],
    "sg:phone":"+44 1420 85325",
    "sg:postcode":"GU34 2JZ",
    "sg:province":"Hampshire",
    "wof:name":"St Nicholas Church",
    "wof:placetype":"venue"
},
  "geometry": {"coordinates":[-0.9771389961,51.158405304],"type":"Point"}
}