{
  "type": "Feature",
  "properties": {
    "addr:full":"23a Parsons St Banbury Oxfordshire OX16 5LY",
    "addr:housenumber":"23a",
    "addr:postcode":"ox16 5ly",
    "addr:street":"Parsons St",
    "iso:country":"GB",
    "sg:address":"23a Parsons St",
    "sg:city":"Banbury",
    "sg:classifiers":[
        {
            "category":"Professional",
            "subcategory":"Business Services",
            "type":"Services"
        }
    ],
    "sg:phone":"+44 1295 277050",
    "sg:postcode":"OX16 5LY",
    "sg:province":"Oxfordshire",
    "sg:tags":[
        "accomodation"
    ],
    "wof:name":"23A Parsons St",
    "wof:placetype":"venue"
},
  "geometry": {"coordinates":[-1.3362059593,52.0621833801],"type":"Point"}
}