{
  "type": "Feature",
  "properties": {
    "addr:full":"153-155 Broadhurst Gardens London Greater London NW6 3AU",
    "addr:housenumber":"153-155",
    "addr:postcode":"nw6 3au",
    "addr:street":"Broadhurst Gardens",
    "iso:country":"GB",
    "sg:address":"153-155 Broadhurst Gardens",
    "sg:city":"London",
    "sg:classifiers":[
        {
            "category":"Restaurant",
            "type":"Food & Drink"
        }
    ],
    "sg:phone":"+44 20 7625 5827",
    "sg:postcode":"NW6 3AU",
    "sg:province":"Greater London",
    "sg:tags":[
        "greek"
    ],
    "wof:name":"Marios Restuarant",
    "wof:placetype":"venue"
},
  "geometry": {"coordinates":[-0.19001,51.546314],"type":"Point"}
}