{
  "type": "Feature",
  "properties": {
    "addr:full":"Caton Road Lancaster Lancashire LA1 3PE",
    "addr:postcode":"la1 3pe",
    "addr:street":"Caton Road",
    "iso:country":"GB",
    "sg:address":"Caton Road",
    "sg:city":"Lancaster",
    "sg:classifiers":[
        {
            "category":"Autos & Motor Vehicles",
            "subcategory":"Fuel & Gas Station",
            "type":"Retail Goods"
        }
    ],
    "sg:phone":"+44 1524 590900",
    "sg:postcode":"LA1 3PE",
    "sg:province":"Lancashire",
    "sg:tags":[
        "hr",
        "petrol"
    ],
    "wof:name":"Shell Lancaster",
    "wof:placetype":"venue"
},
  "geometry": {"coordinates":[-2.788207,54.06205],"type":"Point"}
}