{
  "type": "Feature",
  "properties": {
    "addr:full":"18 Church Street Crook Durham DL15 9BG",
    "addr:housenumber":"18",
    "addr:postcode":"dl15 9bg",
    "addr:street":"Church Street",
    "iso:country":"GB",
    "sg:address":"18 Church Street",
    "sg:city":"Crook",
    "sg:classifiers":[
        {
            "category":"Fast Food",
            "type":"Food & Drink"
        }
    ],
    "sg:phone":"+44 1388 768471",
    "sg:postcode":"DL15 9BG",
    "sg:province":"Durham",
    "sg:tags":[
        "away",
        "take"
    ],
    "wof:name":"The Indian Cottage",
    "wof:placetype":"venue"
},
  "geometry": {"coordinates":[-1.744791,54.714825],"type":"Point"}
}