{
  "type": "Feature",
  "properties": {
    "addr:full":"Po Box 37 Walsall West Midlands WS1 2EF",
    "addr:housenumber":"po box 37",
    "addr:postcode":"ws1 2ef",
    "iso:country":"GB",
    "sg:address":"Po Box 37",
    "sg:city":"Walsall",
    "sg:classifiers":[
        {
            "category":"Shopping",
            "subcategory":"Pets & Pet Supplies",
            "type":"Retail Goods"
        }
    ],
    "sg:phone":"+44 1922 622043",
    "sg:postcode":"WS1 2EF",
    "sg:province":"West Midlands",
    "sg:tags":[
        "cemetery",
        "crematorium"
    ],
    "wof:name":"Longwood Pet Cemetery",
    "wof:placetype":"venue"
},
  "geometry": {"coordinates":[-1.9761040211,52.5852890015],"type":"Point"}
}