{
  "type": "Feature",
  "properties": {
    "iso:country":"GB",
    "sg:address":"8 Seaside La South",
    "sg:city":"Peterlee",
    "sg:classifiers":[
        {
            "category":"Health Services",
            "subcategory":"Clinic",
            "type":"Services"
        }
    ],
    "sg:phone":"+44 191 527 0796",
    "sg:postcode":"SR8 3PN",
    "sg:province":"Durham",
    "sg:tags":[
        "nh"
    ],
    "wof:name":"Durham Area Health Authority",
    "wof:placetype":"venue"
},
  "geometry": {"coordinates":[-1.325671,54.788235],"type":"Point"}
}