{
  "type": "Feature",
  "properties": {
    "addr:full":"56 Duke Street Windsor Berkshire SL4 1SQ",
    "addr:housenumber":"56",
    "addr:postcode":"sl4 1sq",
    "addr:street":"Duke Street",
    "iso:country":"GB",
    "sg:address":"56 Duke Street",
    "sg:city":"Windsor",
    "sg:classifiers":[
        {
            "category":"Building & Trades",
            "subcategory":"Construction",
            "type":"Services"
        }
    ],
    "sg:phone":"+44 1753 771912",
    "sg:postcode":"SL4 1SQ",
    "sg:province":"Berkshire",
    "sg:tags":[
        "conversion",
        "property",
        "loft",
        "converter"
    ],
    "wof:name":"Graham Parfoot",
    "wof:placetype":"venue"
},
  "geometry": {"coordinates":[-0.618332,51.484608],"type":"Point"}
}