{
  "type": "Feature",
  "properties": {
    "addr:full":"272 High Street Waltham Cross Essex EN8 7EA",
    "addr:housenumber":"272",
    "addr:postcode":"en8 7ea",
    "addr:street":"High Street",
    "iso:country":"GB",
    "sg:address":"272 High Street",
    "sg:city":"Waltham Cross",
    "sg:classifiers":[
        {
            "category":"Personal",
            "subcategory":"Beauty Salon",
            "type":"Services"
        }
    ],
    "sg:phone":"+44 1992 633277",
    "sg:postcode":"EN8 7EA",
    "sg:province":"Essex",
    "sg:tags":[
        "unisex",
        "hairdresser"
    ],
    "wof:name":"The Clip Joint",
    "wof:placetype":"venue"
},
  "geometry": {"coordinates":[-0.033879,51.691364],"type":"Point"}
}