{
  "type": "Feature",
  "properties": {
    "iso:country":"GB",
    "sg:address":"94 Academy Street",
    "sg:city":"Inverness",
    "sg:classifiers":[
        {
            "category":"Professional",
            "subcategory":"Art Services",
            "type":"Services"
        },
        {
            "category":"Professional",
            "subcategory":"Printing & Photocopies",
            "type":"Services"
        }
    ],
    "sg:phone":"+44 1463 239052",
    "sg:postcode":"IV1 1LU",
    "sg:province":"Highland",
    "sg:tags":[
        "designer",
        "graphic",
        "printer"
    ],
    "wof:name":"Medway Graphics",
    "wof:placetype":"venue"
},
  "geometry": {"coordinates":[-4.227025032,57.4804573059],"type":"Point"}
}