{
  "type": "Feature",
  "properties": {
    "addr:full":"Golf Course Road Southampton Hampshire SO16 7LE",
    "addr:postcode":"so16 7le",
    "addr:street":"Golf Course Road",
    "iso:country":"GB",
    "sg:address":"Golf Course Road",
    "sg:city":"Southampton",
    "sg:classifiers":[
        {
            "category":"Bars & Pubs",
            "type":"Food & Drink"
        },
        {
            "category":"Restaurant",
            "type":"Food & Drink"
        }
    ],
    "sg:phone":"+44 23 8076 7996",
    "sg:postcode":"SO16 7LE",
    "sg:province":"Hampshire",
    "sg:tags":[
        "-"
    ],
    "wof:name":"Bowlers Restaurant Ltd",
    "wof:placetype":"venue"
},
  "geometry": {"coordinates":[-1.4079099894,50.9465866089],"type":"Point"}
}