{
  "type": "Feature",
  "properties": {
    "addr:full":"11 Romsey Road Southampton Hampshire SO16 4BY",
    "addr:housenumber":"11",
    "addr:postcode":"so16 4by",
    "addr:street":"Romsey Road",
    "iso:country":"GB",
    "sg:address":"11 Romsey Road",
    "sg:city":"Southampton",
    "sg:classifiers":[
        {
            "category":"Shopping",
            "subcategory":"Used Merchandise",
            "type":"Retail Goods"
        }
    ],
    "sg:phone":"+44 23 8077 2046",
    "sg:postcode":"SO16 4BY",
    "sg:province":"Hampshire",
    "sg:tags":[
        "shop",
        "second-hand"
    ],
    "wof:name":"John Kershaw",
    "wof:placetype":"venue"
},
  "geometry": {"coordinates":[-1.435555,50.924107],"type":"Point"}
}