{
  "type": "Feature",
  "properties": {
    "addr:full":"Unit 10a, New Rock Ind Est, New Rock Rd, Chilcompton Bath Somerset BA3 4JE",
    "addr:housenumber":"unit 10a",
    "addr:postcode":"ba3 4je",
    "addr:street":"New Rock;Est New Rock Rd",
    "iso:country":"GB",
    "sg:address":"Unit 10a, New Rock Ind Est, New Rock Rd, Chilcompton",
    "sg:city":"Bath",
    "sg:classifiers":[
        {
            "category":"Home & Garden",
            "subcategory":"Home Furnishings",
            "type":"Retail Goods"
        }
    ],
    "sg:phone":"+44 1761 232181",
    "sg:postcode":"BA3 4JE",
    "sg:province":"Somerset",
    "sg:tags":[
        "homefurnishings"
    ],
    "wof:name":"Scott Appleton  Furniture Solutions Ltd",
    "wof:placetype":"venue"
},
  "geometry": {"coordinates":[-2.508267,51.259113],"type":"Point"}
}