{
  "type": "Feature",
  "properties": {
    "addr:full":"23-25 Church Road Bolton Lancashire BL1 6HE",
    "addr:housenumber":"23-25",
    "addr:postcode":"bl1 6he",
    "addr:street":"Church Road",
    "iso:country":"GB",
    "sg:address":"23-25 Church Road",
    "sg:city":"Bolton",
    "sg:classifiers":[
        {
            "category":"Food & Beverages",
            "subcategory":"Candy",
            "type":"Retail Goods"
        }
    ],
    "sg:phone":"+44 1204 840608",
    "sg:postcode":"BL1 6HE",
    "sg:province":"Lancashire",
    "sg:tags":[
        "confectioner"
    ],
    "wof:name":"B Hunter",
    "wof:placetype":"venue"
},
  "geometry": {"coordinates":[-2.4533319473,53.5922546387],"type":"Point"}
}