{
  "type": "Feature",
  "properties": {
    "iso:country":"GB",
    "sg:address":"32 Grosvenor Rd",
    "sg:city":"Prescot",
    "sg:classifiers":[
        {
            "category":"Health Services",
            "subcategory":"Health Practitioner",
            "type":"Services"
        }
    ],
    "sg:phone":"+44 151 430 6483",
    "sg:postcode":"L34 6HZ",
    "sg:province":"Merseyside",
    "sg:tags":[
        "herbalist"
    ],
    "wof:name":"H A Davies",
    "wof:placetype":"venue"
},
  "geometry": {"coordinates":[-2.799736,53.430618],"type":"Point"}
}