{
  "type": "Feature",
  "properties": {
    "addr:full":"Monthermer Road Garage, Monthermer Road Cardiff Cardiff CF24 4QY",
    "addr:postcode":"cf24 4qy",
    "addr:street":"Monthermer;Monthermer Road",
    "iso:country":"GB",
    "sg:address":"Monthermer Road Garage, Monthermer Road",
    "sg:city":"Cardiff",
    "sg:classifiers":[
        {
            "category":"Retail",
            "subcategory":"Auto Repair",
            "type":"Services"
        }
    ],
    "sg:postcode":"CF24 4QY",
    "sg:province":"Cardiff",
    "sg:tags":[
        "modification",
        "garage"
    ],
    "wof:name":"C N Thomas",
    "wof:placetype":"venue"
},
  "geometry": {"coordinates":[-3.176629,51.498844],"type":"Point"}
}