{
  "type": "Feature",
  "properties": {
    "addr:full":"2 Church Street Newbury Berkshire RG17 9TR",
    "addr:housenumber":"2",
    "addr:postcode":"rg17 9tr",
    "addr:street":"Church Street",
    "iso:country":"GB",
    "sg:address":"2 Church Street",
    "sg:city":"Newbury",
    "sg:classifiers":[
        {
            "category":"Food & Beverages",
            "subcategory":"Meat & Fish",
            "type":"Retail Goods"
        }
    ],
    "sg:postcode":"RG17 9TR",
    "sg:province":"Berkshire",
    "sg:tags":[
        "butcher"
    ],
    "wof:name":"Thatchers Butchers",
    "wof:placetype":"venue"
},
  "geometry": {"coordinates":[-1.3771250248,51.3807487488],"type":"Point"}
}