{
  "type": "Feature",
  "properties": {
    "addr:full":"14 Niddrie Mains Road Edinburgh City of Edinburgh EH16 4BG",
    "addr:housenumber":"14",
    "addr:postcode":"eh16 4bg",
    "addr:street":"Niddrie Mains Road",
    "iso:country":"GB",
    "sg:address":"14 Niddrie Mains Road",
    "sg:city":"Edinburgh",
    "sg:classifiers":[
        {
            "category":"Shopping",
            "subcategory":"Clothing, Apparel, & Fashions",
            "type":"Retail Goods"
        }
    ],
    "sg:phone":"+44 131 661 3140",
    "sg:postcode":"EH16 4BG",
    "sg:province":"City of Edinburgh",
    "sg:tags":[
        "lady",
        "fashionwear",
        "ladieswear"
    ],
    "wof:name":"Alan Cunningham",
    "wof:placetype":"venue"
},
  "geometry": {"coordinates":[-3.140355,55.93259],"type":"Point"}
}