{
  "type": "Feature",
  "properties": {
    "addr:full":"51 Parkside Carlisle Cumbria CA3 9SF",
    "addr:housenumber":"51",
    "addr:postcode":"ca3 9sf",
    "addr:street":"Parkside",
    "iso:country":"GB",
    "sg:address":"51 Parkside",
    "sg:city":"Carlisle",
    "sg:classifiers":[
        {
            "category":"Food & Beverages",
            "subcategory":"Meat & Fish",
            "type":"Retail Goods"
        }
    ],
    "sg:postcode":"CA3 9SF",
    "sg:province":"Cumbria",
    "sg:tags":[
        "chip"
    ],
    "wof:name":"Belah Fish Bar",
    "wof:placetype":"venue"
},
  "geometry": {"coordinates":[-2.9482591152,54.9102897644],"type":"Point"}
}