{
  "type": "Feature",
  "properties": {
    "iso:country":"GB",
    "sg:address":"Century House, Westcott Venture Park",
    "sg:city":"Aylesbury",
    "sg:classifiers":[
        {
            "category":"Professional",
            "subcategory":"Computer Services",
            "type":"Services"
        }
    ],
    "sg:phone":"+44 1296 658947",
    "sg:postcode":"HP18 0XB",
    "sg:province":"Buckinghamshire",
    "sg:tags":[
        "system",
        "software"
    ],
    "wof:name":"Computers Plus",
    "wof:placetype":"venue"
},
  "geometry": {"coordinates":[-0.957499,51.846924],"type":"Point"}
}