{
  "type": "Feature",
  "properties": {
    "addr:full":"82 The Broadway Loughton Essex IG10 3ST",
    "addr:housenumber":"82",
    "addr:postcode":"ig10 3st",
    "addr:street":"The Broadway",
    "iso:country":"GB",
    "sg:address":"82 The Broadway",
    "sg:city":"Loughton",
    "sg:classifiers":[
        {
            "category":"Cafe",
            "type":"Food & Drink"
        }
    ],
    "sg:phone":"+44 20 8508 7113",
    "sg:postcode":"IG10 3ST",
    "sg:province":"Essex",
    "sg:tags":[
        "tea",
        "snack",
        "bar",
        "room"
    ],
    "wof:name":"T & J Kelly",
    "wof:placetype":"venue"
},
  "geometry": {"coordinates":[0.0826499984,51.6465797424],"type":"Point"}
}