{
  "type": "Feature",
  "properties": {
    "iso:country":"GB",
    "sg:address":"8 Cresswell Lane",
    "sg:city":"Glasgow",
    "sg:classifiers":[
        {
            "category":"Shopping",
            "subcategory":"Clothing, Apparel, & Fashions",
            "type":"Retail Goods"
        }
    ],
    "sg:phone":"+44 141 334 8002",
    "sg:postcode":"G12 8AA",
    "sg:province":"Glasgow City",
    "sg:tags":[
        "shop"
    ],
    "wof:name":"Mumbo Jumbo Designs",
    "wof:placetype":"venue"
},
  "geometry": {"coordinates":[-4.2898540497,55.8761405945],"type":"Point"}
}