{
  "type": "Feature",
  "properties": {
    "addr:full":"54 Westminster Rd Wrexham Wrexham LL11 6DH",
    "addr:housenumber":"54",
    "addr:postcode":"ll11 6dh",
    "addr:street":"Westminster Rd",
    "iso:country":"GB",
    "sg:address":"54 Westminster Rd",
    "sg:city":"Wrexham",
    "sg:classifiers":[
        {
            "category":"Bus Charters",
            "type":"Transportation"
        }
    ],
    "sg:phone":"+44 1978 758047",
    "sg:postcode":"LL11 6DH",
    "sg:province":"Wrexham",
    "sg:tags":[
        "hire",
        "coach"
    ],
    "wof:name":"Terrys Coaches",
    "wof:placetype":"venue"
},
  "geometry": {"coordinates":[-3.0347940922,53.0715522766],"type":"Point"}
}