{
  "type": "Feature",
  "properties": {
    "iso:country":"GB",
    "sg:address":"49-50 King Edwards Road",
    "sg:city":"Swansea",
    "sg:classifiers":[
        {
            "category":"Building & Trades",
            "subcategory":"Plumbing",
            "type":"Services"
        }
    ],
    "sg:postcode":"SA1 4LN",
    "sg:province":"Neath Port Talbot",
    "sg:tags":[
        "merchant",
        "plumbers'"
    ],
    "wof:name":"F G Trew & Son Ltd.",
    "wof:placetype":"venue"
},
  "geometry": {"coordinates":[-3.9606239796,51.6161766052],"type":"Point"}
}