{
  "type": "Feature",
  "properties": {
    "addr:full":"The White Ho, 12 Standishgate Wigan Lancashire WN1 1UE",
    "addr:housenumber":"12",
    "addr:postcode":"wn1 1ue",
    "addr:street":"Standishgate Wigan",
    "iso:country":"GB",
    "sg:address":"The White Ho, 12 Standishgate",
    "sg:city":"Wigan",
    "sg:classifiers":[
        {
            "category":"Health Services",
            "subcategory":"Dentist",
            "type":"Services"
        }
    ],
    "sg:phone":"+44 1942 243136",
    "sg:postcode":"WN1 1UE",
    "sg:province":"Lancashire",
    "wof:name":"Randall J G",
    "wof:placetype":"venue"
},
  "geometry": {"coordinates":[-2.6335320473,53.5441551208],"type":"Point"}
}