{
  "type": "Feature",
  "properties": {
    "addr:full":"Bryn Gwyddan, Llangadfan Welshpool Shropshire SY21 0NW",
    "addr:postcode":"sy21 0nw",
    "iso:country":"GB",
    "sg:address":"Bryn Gwyddan, Llangadfan",
    "sg:city":"Welshpool",
    "sg:classifiers":[
        {
            "category":"Farming",
            "subcategory":"Livestock Farm",
            "type":"Manufacturing & Wholesale Goods"
        }
    ],
    "sg:phone":"+44 1938 820385",
    "sg:postcode":"SY21 0NW",
    "sg:province":"Shropshire",
    "sg:tags":[
        "others"
    ],
    "wof:name":"E J Jones",
    "wof:placetype":"venue"
},
  "geometry": {"coordinates":[-3.463512,52.685905],"type":"Point"}
}