{
  "type": "Feature",
  "properties": {
    "iso:country":"GB",
    "sg:address":"Tennis Court Rd",
    "sg:city":"Cambridge",
    "sg:classifiers":[
        {
            "category":"Education",
            "subcategory":"University",
            "type":"Public Place"
        }
    ],
    "sg:phone":"+44 1223 334088",
    "sg:postcode":"CB2 1QR",
    "sg:province":"Cambridgeshire",
    "sg:tags":[
        "medical",
        "school"
    ],
    "wof:name":"Wellcome CRC Institute",
    "wof:placetype":"venue"
},
  "geometry": {"coordinates":[0.121535,52.201134],"type":"Point"}
}