{
  "type": "Feature",
  "properties": {
    "addr:full":"Unit 2, Bryson Street Industrial Estate Falkirk Falkirk FK2 7BT",
    "addr:housenumber":"unit 2;estate",
    "addr:postcode":"fk2 7bt",
    "addr:street":"Bryson Street Industrial",
    "iso:country":"GB",
    "sg:address":"Unit 2, Bryson Street Industrial Estate",
    "sg:city":"Falkirk",
    "sg:classifiers":[
        {
            "category":"Shopping",
            "subcategory":"Beauty & Cosmetics",
            "type":"Retail Goods"
        }
    ],
    "sg:phone":"+44 1324 624576",
    "sg:postcode":"FK2 7BT",
    "sg:province":"Falkirk",
    "sg:tags":[
        "equipment",
        "supply",
        "hairdressing"
    ],
    "wof:name":"Salon Services (Hair & Beauty Supplies) Ltd.",
    "wof:placetype":"venue"
},
  "geometry": {"coordinates":[-3.785399,56.00811],"type":"Point"}
}