{
  "type": "Feature",
  "properties": {
    "addr:full":"56 Hanbury Rd Bargoed Caerphilly CF81 8QW",
    "addr:housenumber":"56",
    "addr:postcode":"cf81 8qw",
    "addr:street":"Hanbury Rd",
    "iso:country":"GB",
    "sg:address":"56 Hanbury Rd",
    "sg:city":"Bargoed",
    "sg:classifiers":[
        {
            "category":"Real Estate",
            "subcategory":"Real Estate Agent",
            "type":"Services"
        }
    ],
    "sg:phone":"+44 1443 834856",
    "sg:postcode":"CF81 8QW",
    "sg:province":"Caerphilly",
    "wof:name":"Halifax Property Services",
    "wof:placetype":"venue"
},
  "geometry": {"coordinates":[-3.2291579247,51.689781189],"type":"Point"}
}