{
  "type": "Feature",
  "properties": {
    "addr:full":"55 Station Road Westgate-on-sea Kent CT8 8QY",
    "addr:housenumber":"55",
    "addr:postcode":"ct8 8qy",
    "addr:street":"Station Road Westgate-On-Sea",
    "iso:country":"GB",
    "sg:address":"55 Station Road",
    "sg:city":"Westgate-on-sea",
    "sg:classifiers":[
        {
            "category":"Food & Beverages",
            "subcategory":"Liquor & Beverages",
            "type":"Retail Goods"
        }
    ],
    "sg:postcode":"CT8 8QY",
    "sg:province":"Kent",
    "sg:tags":[
        "beer",
        "spirit",
        "wines"
    ],
    "wof:name":"Corkscrew",
    "wof:placetype":"venue"
},
  "geometry": {"coordinates":[1.3376790285,51.3815345764],"type":"Point"}
}