{
  "type": "Feature",
  "properties": {
    "addr:full":"Brockhall Village Blackburn Lancashire BB6 8BB",
    "addr:postcode":"bb6 8bb",
    "addr:street":"Brockhall Village",
    "iso:country":"GB",
    "sg:address":"Brockhall Village",
    "sg:city":"Blackburn",
    "sg:classifiers":[
        {
            "category":"Food & Beverages",
            "subcategory":"Specialty",
            "type":"Retail Goods"
        }
    ],
    "sg:phone":"+44 1254 246624",
    "sg:postcode":"BB6 8BB",
    "sg:province":"Lancashire",
    "sg:tags":[
        "product",
        "health"
    ],
    "wof:name":"Podium Sport Ltd.",
    "wof:placetype":"venue"
},
  "geometry": {"coordinates":[-2.4529399872,53.8286399841],"type":"Point"}
}