{
  "type": "Feature",
  "properties": {
    "iso:country":"GB",
    "sg:address":"57 Charlotte Dundas Court",
    "sg:city":"Grangemouth",
    "sg:classifiers":[
        {
            "category":"Shopping",
            "subcategory":"News",
            "type":"Retail Goods"
        }
    ],
    "sg:phone":"+44 1324 483350",
    "sg:postcode":"FK3 9EB",
    "sg:province":"Falkirk",
    "sg:tags":[
        "newsagent"
    ],
    "wof:name":"W & S Frew",
    "wof:placetype":"venue"
},
  "geometry": {"coordinates":[-3.723894,56.009331],"type":"Point"}
}