{
  "type": "Feature",
  "properties": {
    "addr:full":"St Johns Hall, Halesworth Road Beccles Norfolk NR34 8JQ",
    "addr:postcode":"nr34 8jq",
    "addr:street":"Halesworth Road",
    "iso:country":"GB",
    "sg:address":"St Johns Hall, Halesworth Road",
    "sg:city":"Beccles",
    "sg:classifiers":[
        {
            "category":"Retail",
            "subcategory":"Storage",
            "type":"Services"
        }
    ],
    "sg:phone":"+44 1986 781694",
    "sg:postcode":"NR34 8JQ",
    "sg:province":"Norfolk",
    "sg:tags":[
        "household",
        "removal",
        "operation",
        "facility"
    ],
    "wof:name":"St John's Hall Storage",
    "wof:placetype":"venue"
},
  "geometry": {"coordinates":[1.567245,52.453667],"type":"Point"}
}