{
  "type": "Feature",
  "properties": {
    "iso:country":"GB",
    "sg:address":"1 Bridge Street",
    "sg:city":"Sturminster Newton",
    "sg:classifiers":[
        {
            "category":"Fast Food",
            "type":"Food & Drink"
        }
    ],
    "sg:phone":"+44 1258 473982",
    "sg:postcode":"DT10 1AP",
    "sg:province":"Dorset",
    "sg:tags":[
        "away",
        "take"
    ],
    "wof:name":"Star Tandoori",
    "wof:placetype":"venue"
},
  "geometry": {"coordinates":[-2.3056271076,50.9251670837],"type":"Point"}
}