{
  "type": "Feature",
  "properties": {
    "addr:full":"Cuffley Gate, Sopers Road Potters Bar Greater London EN6 4RY",
    "addr:postcode":"en6 4ry",
    "addr:street":"Cuffley Gate Sopers Road",
    "iso:country":"GB",
    "sg:address":"Cuffley Gate, Sopers Road",
    "sg:city":"Potters Bar",
    "sg:classifiers":[
        {
            "category":"Manufacturing",
            "subcategory":"Metals",
            "type":"Manufacturing & Wholesale Goods"
        }
    ],
    "sg:phone":"+44 1707 872655",
    "sg:postcode":"EN6 4RY",
    "sg:province":"Greater London",
    "sg:tags":[
        "steel",
        "fabricator",
        "erectors"
    ],
    "wof:name":"Brooksby Engineering",
    "wof:placetype":"venue"
},
  "geometry": {"coordinates":[-0.1784240007,51.6930122375],"type":"Point"}
}