{
  "type": "Feature",
  "properties": {
    "iso:country":"GB",
    "sg:address":"Manor House Hospital, Bierton Road",
    "sg:city":"Aylesbury",
    "sg:classifiers":[
        {
            "category":"Organizations",
            "subcategory":"Non-profit Organization",
            "type":"Services"
        }
    ],
    "sg:postcode":"HP20 1EG",
    "sg:province":"Buckinghamshire",
    "sg:tags":[
        "organisation",
        "voluntary",
        "charity"
    ],
    "wof:name":"Bucks Association for Mental Health",
    "wof:placetype":"venue"
},
  "geometry": {"coordinates":[-0.8118640184,51.8187789917],"type":"Point"}
}