{
  "type": "Feature",
  "properties": {
    "addr:full":"321-323 Sauchiehall Street Glasgow Glasgow City G2 3HW",
    "addr:housenumber":"321-323",
    "addr:postcode":"g2 3hw",
    "addr:street":"Sauchiehall Street",
    "iso:country":"GB",
    "sg:address":"321-323 Sauchiehall Street",
    "sg:city":"Glasgow",
    "sg:classifiers":[
        {
            "category":"Restaurant",
            "type":"Food & Drink"
        }
    ],
    "sg:phone":"+44 141 332 4180",
    "sg:postcode":"G2 3HW",
    "sg:province":"Glasgow City",
    "sg:tags":[
        "indian",
        "-"
    ],
    "wof:name":"Rawalpindi",
    "wof:placetype":"venue"
},
  "geometry": {"coordinates":[-4.2652921677,55.8654823303],"type":"Point"}
}