{
  "type": "Feature",
  "properties": {
    "addr:full":"2 Birchetts Avenue, Langton Grn Tunbridge Wells East Sussex TN3 0EH",
    "addr:housenumber":"2",
    "addr:postcode":"tn3 0eh",
    "addr:street":"Birchetts Avenue Langton Grn;Wells",
    "iso:country":"GB",
    "sg:address":"2 Birchetts Avenue, Langton Grn",
    "sg:city":"Tunbridge Wells",
    "sg:classifiers":[
        {
            "category":"Professional",
            "type":"Services"
        }
    ],
    "sg:phone":"+44 1892 862396",
    "sg:postcode":"TN3 0EH",
    "sg:province":"East Sussex",
    "sg:tags":[
        "entertainer"
    ],
    "wof:name":"Band Matters",
    "wof:placetype":"venue"
},
  "geometry": {"coordinates":[0.2061450034,51.1312522888],"type":"Point"}
}