{
  "type": "Feature",
  "properties": {
    "iso:country":"GB",
    "sg:address":"73 Norwich Road, New Costess",
    "sg:city":"Norwich",
    "sg:classifiers":[
        {
            "category":"Shopping",
            "subcategory":"Computers & Home Electronics",
            "type":"Retail Goods"
        }
    ],
    "sg:phone":"+44 1603 743589",
    "sg:postcode":"NR5 0EN",
    "sg:province":"Norfolk",
    "sg:tags":[
        "aerial",
        "television",
        "radio"
    ],
    "wof:name":"Zenith Aerials",
    "wof:placetype":"venue"
},
  "geometry": {"coordinates":[1.234424,52.646824],"type":"Point"}
}