{
  "type": "Feature",
  "properties": {
    "iso:country":"GB",
    "sg:address":"10 East Street, Crowland",
    "sg:city":"Peterborough",
    "sg:classifiers":[
        {
            "category":"Organizations",
            "subcategory":"Non-profit Organization",
            "type":"Services"
        }
    ],
    "sg:phone":"+44 1733 211797",
    "sg:postcode":"PE6 0EN",
    "sg:province":"Cambridgeshire",
    "sg:tags":[
        "organisation",
        "voluntary",
        "charity"
    ],
    "wof:name":"Crowland Care",
    "wof:placetype":"venue"
},
  "geometry": {"coordinates":[-0.167999,52.676041],"type":"Point"}
}