{
  "type": "Feature",
  "properties": {
    "iso:country":"GB",
    "sg:address":"Ormerod St",
    "sg:city":"Accrington",
    "sg:classifiers":[
        {
            "category":"Professional",
            "subcategory":"Printing & Photocopies",
            "type":"Services"
        }
    ],
    "sg:postcode":"BB5 0PF",
    "sg:province":"Lancashire",
    "sg:tags":[
        "trophy"
    ],
    "wof:name":"S D L Trophies Ltd",
    "wof:placetype":"venue"
},
  "geometry": {"coordinates":[-2.3691339493,53.750125885],"type":"Point"}
}