{
  "type": "Feature",
  "properties": {
    "iso:country":"GB",
    "sg:address":"13 Kempton Close, Shotley Bridge",
    "sg:city":"Consett",
    "sg:classifiers":[
        {
            "category":"Home & Garden",
            "subcategory":"Building Materials",
            "type":"Retail Goods"
        },
        {
            "category":"Building & Trades",
            "subcategory":"Construction",
            "type":"Services"
        }
    ],
    "sg:phone":"+44 1207 508371",
    "sg:postcode":"DH8 0UB",
    "sg:province":"Durham",
    "sg:tags":[
        "roofing"
    ],
    "wof:name":"J H Allon Roofing RFG Contractor",
    "wof:placetype":"venue"
},
  "geometry": {"coordinates":[-1.846671,54.8731],"type":"Point"}
}