{
  "type": "Feature",
  "properties": {
    "iso:country":"GB",
    "sg:address":"49 Buxton Road, Aylsham",
    "sg:city":"Norwich",
    "sg:classifiers":[
        {
            "category":"Place Of Worship",
            "type":"Public Place"
        }
    ],
    "sg:phone":"+44 1263 732102",
    "sg:postcode":"NR11 6UB",
    "sg:province":"Norfolk",
    "wof:name":"Aylsham Methodist Church",
    "wof:placetype":"venue"
},
  "geometry": {"coordinates":[1.261029,52.78838],"type":"Point"}
}