{
  "type": "Feature",
  "properties": {
    "iso:country":"GB",
    "sg:address":"278 Victoria Rd East",
    "sg:city":"Leicester",
    "sg:classifiers":[
        {
            "category":"Shopping",
            "subcategory":"Computers & Home Electronics",
            "type":"Retail Goods"
        }
    ],
    "sg:phone":"+44 116 212 3070",
    "sg:postcode":"LE5 0LF",
    "sg:province":"Leicestershire",
    "sg:tags":[
        "sound",
        "equipment",
        "system"
    ],
    "wof:name":"Aptec",
    "wof:placetype":"venue"
},
  "geometry": {"coordinates":[-1.0955510139,52.648021698],"type":"Point"}
}