{
  "type": "Feature",
  "properties": {
    "addr:full":"23 Drygate Glasgow Glasgow City G4 0XY",
    "addr:housenumber":"23",
    "addr:postcode":"g4 0xy",
    "addr:street":"Drygate",
    "iso:country":"GB",
    "sg:address":"23 Drygate",
    "sg:city":"Glasgow",
    "sg:classifiers":[
        {
            "category":"Shopping",
            "subcategory":"News",
            "type":"Retail Goods"
        }
    ],
    "sg:phone":"+44 141 552 3302",
    "sg:postcode":"G4 0XY",
    "sg:province":"Glasgow City",
    "sg:tags":[
        "newsagent"
    ],
    "wof:name":"Asima Newsagents",
    "wof:placetype":"venue"
},
  "geometry": {"coordinates":[-4.2356109619,55.8605804443],"type":"Point"}
}