{
  "type": "Feature",
  "properties": {
    "iso:country":"GB",
    "sg:address":"Second Floor, 4-5 Union Terr",
    "sg:city":"Aberdeen",
    "sg:classifiers":[
        {
            "category":"Travel",
            "subcategory":"Travel Agent",
            "type":"Entertainment"
        }
    ],
    "sg:phone":"+44 1224 641050",
    "sg:postcode":"AB10 1NJ",
    "sg:province":"Aberdeen City",
    "wof:name":"American Express Travel Agents",
    "wof:placetype":"venue"
},
  "geometry": {"coordinates":[-2.102684,57.145702],"type":"Point"}
}