{
  "type": "Feature",
  "properties": {
    "addr:full":"Heugh House West, Haydon Bridge Hexham Northumberland NE47 6ND",
    "addr:postcode":"ne47 6nd",
    "addr:street":"West",
    "iso:country":"GB",
    "sg:address":"Heugh House West, Haydon Bridge",
    "sg:city":"Hexham",
    "sg:classifiers":[
        {
            "category":"Social Services",
            "subcategory":"Job Training",
            "type":"Services"
        },
        {
            "category":"Professional",
            "subcategory":"Engineering",
            "type":"Services"
        }
    ],
    "sg:phone":"+44 1434 688001",
    "sg:postcode":"NE47 6ND",
    "sg:province":"Northumberland",
    "sg:tags":[
        "draughtsman",
        "consulting",
        "drawing",
        "engineer"
    ],
    "wof:name":"L J Yare Associates",
    "wof:placetype":"venue"
},
  "geometry": {"coordinates":[-2.2578,54.979092],"type":"Point"}
}