{
  "type": "Feature",
  "properties": {
    "addr:full":"Unit 1 Holly Park, Spitfire Road Birmingham West Midlands B24 9PB",
    "addr:housenumber":"unit 1",
    "addr:postcode":"b24 9pb",
    "addr:street":"Spitfire Road",
    "iso:country":"GB",
    "sg:address":"Unit 1 Holly Park, Spitfire Road",
    "sg:city":"Birmingham",
    "sg:classifiers":[
        {
            "category":"Building & Trades",
            "subcategory":"Construction",
            "type":"Services"
        }
    ],
    "sg:phone":"+44 121 382 5444",
    "sg:postcode":"B24 9PB",
    "sg:province":"West Midlands",
    "sg:tags":[
        "decorator",
        "painter"
    ],
    "wof:name":"Ian Williams Ltd.",
    "wof:placetype":"venue"
},
  "geometry": {"coordinates":[-1.821144,52.515942],"type":"Point"}
}