{
  "type": "Feature",
  "properties": {
    "iso:country":"GB",
    "sg:address":"Sussex Street",
    "sg:city":"Middlesbrough",
    "sg:classifiers":[
        {
            "category":"Bars & Pubs",
            "type":"Food & Drink"
        }
    ],
    "sg:phone":"+44 1642 243167",
    "sg:postcode":"TS2 1BH",
    "sg:province":"Durham",
    "sg:tags":[
        "pubs",
        "inn"
    ],
    "wof:name":"The Glass Barrel",
    "wof:placetype":"venue"
},
  "geometry": {"coordinates":[-1.2362610102,54.5807685852],"type":"Point"}
}