{
  "type": "Feature",
  "properties": {
    "iso:country":"GB",
    "sg:address":"51 Heol Y Meinciau",
    "sg:city":"Llanelli",
    "sg:classifiers":[
        {
            "category":"Food & Beverages",
            "subcategory":"Bakery",
            "type":"Retail Goods"
        }
    ],
    "sg:postcode":"SA15 5RT",
    "sg:province":"Carmarthenshire",
    "sg:tags":[
        "baker"
    ],
    "wof:name":"The Iscoed Bakery",
    "wof:placetype":"venue"
},
  "geometry": {"coordinates":[-4.221457,51.756027],"type":"Point"}
}