{
  "type": "Feature",
  "properties": {
    "addr:full":"Southfield, Thornfield Road Grange-over-sands Cumbria LA11 6ES",
    "addr:postcode":"la11 6es",
    "addr:street":"Thornfield Road",
    "iso:country":"GB",
    "sg:address":"Southfield, Thornfield Road",
    "sg:city":"Grange-over-sands",
    "sg:classifiers":[
        {
            "category":"Building & Trades",
            "subcategory":"Construction",
            "type":"Services"
        }
    ],
    "sg:postcode":"LA11 6ES",
    "sg:province":"Cumbria",
    "sg:tags":[
        "glazier"
    ],
    "wof:name":"David Hodgson",
    "wof:placetype":"venue"
},
  "geometry": {"coordinates":[-2.9216399193,54.1841583252],"type":"Point"}
}