{
  "type": "Feature",
  "properties": {
    "addr:full":"Waenfawr Caernarfon Gwynedd LL55 4AQ",
    "addr:postcode":"ll55 4aq",
    "addr:street":"Waenfawr",
    "iso:country":"GB",
    "sg:address":"Waenfawr",
    "sg:city":"Caernarfon",
    "sg:classifiers":[
        {
            "category":"Bars & Pubs",
            "type":"Food & Drink"
        }
    ],
    "sg:postcode":"LL55 4AQ",
    "sg:province":"Gwynedd",
    "sg:tags":[
        "pubs",
        "inn"
    ],
    "wof:name":"K C Humphreys",
    "wof:placetype":"venue"
},
  "geometry": {"coordinates":[-4.2307639122,53.1269721985],"type":"Point"}
}