{
  "type": "Feature",
  "properties": {
    "addr:full":"30 Holmfield Road Walton-on-thames Surrey KT12 3RD",
    "addr:housenumber":"30",
    "addr:postcode":"kt12 3rd",
    "addr:street":"Holmfield Road",
    "iso:country":"GB",
    "sg:address":"30 Holmfield Road",
    "sg:city":"Walton-on-thames",
    "sg:classifiers":[
        {
            "category":"Home & Garden",
            "subcategory":"Garden Supply",
            "type":"Retail Goods"
        }
    ],
    "sg:phone":"+44 1932 225790",
    "sg:postcode":"KT12 3RD",
    "sg:province":"Surrey",
    "sg:tags":[
        "turfing"
    ],
    "wof:name":"Surrey Turf",
    "wof:placetype":"venue"
},
  "geometry": {"coordinates":[-0.384506,51.387447],"type":"Point"}
}