{
  "type": "Feature",
  "properties": {
    "addr:full":"Pennypot Industrial Estate, Dymchurch Road Hythe Kent CT21 6PE",
    "addr:postcode":"ct21 6pe",
    "addr:street":"Estate Dymchurch Road",
    "iso:country":"GB",
    "sg:address":"Pennypot Industrial Estate, Dymchurch Road",
    "sg:city":"Hythe",
    "sg:classifiers":[
        {
            "category":"Home & Garden",
            "subcategory":"Hardware",
            "type":"Retail Goods"
        }
    ],
    "sg:postcode":"CT21 6PE",
    "sg:province":"Kent",
    "sg:tags":[
        "fixing",
        "nuts",
        "bolt"
    ],
    "wof:name":"R S R Fasteners",
    "wof:placetype":"venue"
},
  "geometry": {"coordinates":[1.0804810524,51.0708274841],"type":"Point"}
}