{
  "type": "Feature",
  "properties": {
    "iso:country":"GB",
    "sg:address":"1 Hall Flat Lane, Balby",
    "sg:city":"Doncaster",
    "sg:classifiers":[
        {
            "category":"Education",
            "subcategory":"School",
            "type":"Public Place"
        }
    ],
    "sg:phone":"+44 1302 856800",
    "sg:postcode":"DN4 8PT",
    "sg:province":"South Yorkshire",
    "sg:tags":[
        "independent",
        "preparatory"
    ],
    "wof:name":"Sycamore Hall Preparatory School",
    "wof:placetype":"venue"
},
  "geometry": {"coordinates":[-1.1553549767,53.5042724609],"type":"Point"}
}