{
  "type": "Feature",
  "properties": {
    "addr:full":"33 Sheep St Stratford Upon Avon Warwickshire CV37 6EE",
    "addr:housenumber":"33",
    "addr:postcode":"cv37 6ee",
    "addr:street":"Sheep St",
    "iso:country":"GB",
    "sg:address":"33 Sheep St",
    "sg:city":"Stratford Upon Avon",
    "sg:classifiers":[
        {
            "category":"Shopping",
            "subcategory":"Gifts & Souvenirs",
            "type":"Retail Goods"
        }
    ],
    "sg:phone":"+44 1789 293810",
    "sg:postcode":"CV37 6EE",
    "sg:province":"Warwickshire",
    "sg:tags":[
        "shop"
    ],
    "wof:name":"Serendipity",
    "wof:placetype":"venue"
},
  "geometry": {"coordinates":[-1.7048369646,52.1914253235],"type":"Point"}
}