{
  "type": "Feature",
  "properties": {
    "addr:full":"Healthcall Ho, Langstone Park Newport East Riding of Yorkshire NP6 2LX",
    "addr:postcode":"np6 2lx",
    "addr:street":"Park",
    "iso:country":"GB",
    "sg:address":"Healthcall Ho, Langstone Park",
    "sg:city":"Newport",
    "sg:classifiers":[
        {
            "category":"Banks & Credit Unions",
            "subcategory":"Financial Services",
            "type":"Services"
        }
    ],
    "sg:phone":"+44 1633 411222",
    "sg:postcode":"NP6 2LX",
    "sg:province":"East Riding of Yorkshire",
    "sg:tags":[
        "adviser"
    ],
    "wof:name":"Anglo Celtic",
    "wof:placetype":"venue"
},
  "geometry": {"coordinates":[-2.90721,51.603882],"type":"Point"}
}