{
  "type": "Feature",
  "properties": {
    "iso:country":"GB",
    "sg:address":"2 Alder Way, West Cross",
    "sg:city":"Swansea",
    "sg:classifiers":[
        {
            "category":"Shopping",
            "subcategory":"Computers & Home Electronics",
            "type":"Retail Goods"
        }
    ],
    "sg:postcode":"SA3 5PD",
    "sg:province":"Swansea",
    "sg:tags":[
        "equipment",
        "radio"
    ],
    "wof:name":"Gemini Digital Broadcast",
    "wof:placetype":"venue"
},
  "geometry": {"coordinates":[-4.0136327744,51.5846710205],"type":"Point"}
}