{
  "type": "Feature",
  "properties": {
    "iso:country":"GB",
    "sg:address":"Alexander House, Christy Court, Southfields Business Park",
    "sg:city":"Basildon",
    "sg:classifiers":[
        {
            "category":"Professional",
            "subcategory":"Engineering",
            "type":"Services"
        }
    ],
    "sg:phone":"+44 1268 542242",
    "sg:postcode":"SS15 6TL",
    "sg:province":"Essex",
    "sg:tags":[
        "design",
        "engineer"
    ],
    "wof:name":"G E Polymer Design Associates Ltd.",
    "wof:placetype":"venue"
},
  "geometry": {"coordinates":[0.3990139961,51.5777778625],"type":"Point"}
}