{
  "type": "Feature",
  "properties": {
    "iso:country":"GB",
    "sg:address":"Sudehill Mills, Newmill",
    "sg:city":"Huddersfield",
    "sg:classifiers":[
        {
            "category":"Shopping",
            "subcategory":"Clothing, Apparel, & Fashions",
            "type":"Retail Goods"
        }
    ],
    "sg:phone":"+44 1484 686444",
    "sg:postcode":"HD7 7BX",
    "sg:province":"West Yorkshire",
    "sg:tags":[
        "clothing",
        "fabric"
    ],
    "wof:name":"Newmill Knitting Co. Ltd.",
    "wof:placetype":"venue"
},
  "geometry": {"coordinates":[-1.78268,53.64695],"type":"Point"}
}