{
  "type": "Feature",
  "properties": {
    "addr:full":"103 Fitzwalter Road Sheffield South Yorkshire S2 2SP",
    "addr:housenumber":"103",
    "addr:postcode":"s2 2sp",
    "addr:street":"Fitzwalter Road",
    "iso:country":"GB",
    "sg:address":"103 Fitzwalter Road",
    "sg:city":"Sheffield",
    "sg:classifiers":[
        {
            "category":"Retail",
            "subcategory":"Funeral Services",
            "type":"Services"
        }
    ],
    "sg:phone":"+44 114 272 3928",
    "sg:postcode":"S2 2SP",
    "sg:province":"South Yorkshire",
    "wof:name":"W Simpson & Son",
    "wof:placetype":"venue"
},
  "geometry": {"coordinates":[-1.4525489807,53.3759689331],"type":"Point"}
}