{
  "type": "Feature",
  "properties": {
    "iso:country":"GB",
    "sg:address":"15 Piece Hall",
    "sg:city":"Halifax",
    "sg:classifiers":[
        {
            "category":"Shopping",
            "subcategory":"Gifts & Souvenirs",
            "type":"Retail Goods"
        }
    ],
    "sg:postcode":"HX1 1RE",
    "sg:province":"West Yorkshire",
    "sg:tags":[
        "shop"
    ],
    "wof:name":"C B G B's",
    "wof:placetype":"venue"
},
  "geometry": {"coordinates":[-1.8575639725,53.7223968506],"type":"Point"}
}