{
  "type": "Feature",
  "properties": {
    "addr:full":"278 Bluebell Road Norwich Norfolk NR4 7LW",
    "addr:housenumber":"278",
    "addr:postcode":"nr4 7lw",
    "addr:street":"Bluebell Road Norwich Norfolk",
    "iso:country":"GB",
    "sg:address":"278 Bluebell Road",
    "sg:city":"Norwich",
    "sg:classifiers":[
        {
            "category":"Building & Trades",
            "subcategory":"Landscaping Services",
            "type":"Services"
        },
        {
            "category":"Building & Trades",
            "subcategory":"Construction",
            "type":"Services"
        }
    ],
    "sg:phone":"+44 1603 501998",
    "sg:postcode":"NR4 7LW",
    "sg:province":"Norfolk",
    "sg:tags":[
        "joiner",
        "carpenter",
        "preservation",
        "timber"
    ],
    "wof:name":"Gordon H Mallett",
    "wof:placetype":"venue"
},
  "geometry": {"coordinates":[1.248555,52.628418],"type":"Point"}
}