{
  "type": "Feature",
  "properties": {
    "iso:country":"GB",
    "sg:address":"1 Guardian Estate, Eldon Street",
    "sg:city":"Greenock",
    "sg:classifiers":[
        {
            "category":"Wholesale",
            "subcategory":"Non-durable Goods",
            "type":"Manufacturing & Wholesale Goods"
        }
    ],
    "sg:phone":"+44 1475 721326",
    "sg:postcode":"PA16 7QJ",
    "sg:province":"Inverclyde",
    "sg:tags":[
        "carry",
        "cash"
    ],
    "wof:name":"Booker Cash & Carry",
    "wof:placetype":"venue"
},
  "geometry": {"coordinates":[-4.78706,55.95237],"type":"Point"}
}