{
  "type": "Feature",
  "properties": {
    "iso:country":"GB",
    "sg:address":"Spring Field Mount, Shawbury",
    "sg:city":"Shrewsbury",
    "sg:classifiers":[
        {
            "category":"Health Services",
            "subcategory":"Nursing And Care Facility",
            "type":"Services"
        }
    ],
    "sg:postcode":"SY4 4EL",
    "sg:province":"Shropshire",
    "sg:tags":[
        "home"
    ],
    "wof:name":"The River Meadows Nursing Home Ltd.",
    "wof:placetype":"venue"
},
  "geometry": {"coordinates":[-2.656574,52.787674],"type":"Point"}
}