{
  "type": "Feature",
  "properties": {
    "addr:full":"Oak House, Cliff End Lane, Pett Level Hastings East Sussex TN35 4EF",
    "addr:postcode":"tn35 4ef",
    "addr:street":"Cliff End Lane",
    "iso:country":"GB",
    "sg:address":"Oak House, Cliff End Lane, Pett Level",
    "sg:city":"Hastings",
    "sg:classifiers":[
        {
            "category":"Manufacturing",
            "subcategory":"Buildings",
            "type":"Manufacturing & Wholesale Goods"
        }
    ],
    "sg:phone":"+44 1424 814100",
    "sg:postcode":"TN35 4EF",
    "sg:province":"East Sussex",
    "sg:tags":[
        "mobile",
        "home"
    ],
    "wof:name":"Motorhome Holidays",
    "wof:placetype":"venue"
},
  "geometry": {"coordinates":[0.679365,50.88747],"type":"Point"}
}