{
  "type": "Feature",
  "properties": {
    "iso:country":"GB",
    "sg:address":"Katheleen Ho, James Rd",
    "sg:city":"Birmingham",
    "sg:classifiers":[
        {
            "category":"Professional",
            "subcategory":"Detective & Security Services",
            "type":"Services"
        }
    ],
    "sg:phone":"+44 121 765 4448",
    "sg:postcode":"B11 2BA",
    "sg:province":"West Midlands",
    "wof:name":"Central Security",
    "wof:placetype":"venue"
},
  "geometry": {"coordinates":[-1.908604,52.478596],"type":"Point"}
}