{
  "type": "Feature",
  "properties": {
    "addr:full":"4 The Royals, High Street Southend-on-sea Essex SS1 1DQ",
    "addr:housenumber":"4",
    "addr:postcode":"ss1 1dq",
    "addr:street":"The;High Street",
    "iso:country":"GB",
    "sg:address":"4 The Royals, High Street",
    "sg:city":"Southend-on-sea",
    "sg:classifiers":[
        {
            "category":"Home & Garden",
            "subcategory":"Home Furnishings",
            "type":"Retail Goods"
        }
    ],
    "sg:phone":"+44 1702 618912",
    "sg:postcode":"SS1 1DQ",
    "sg:province":"Essex",
    "sg:tags":[
        "furnishers",
        "planner",
        "kitchen"
    ],
    "wof:name":"Moben Kitchens",
    "wof:placetype":"venue"
},
  "geometry": {"coordinates":[0.70516,51.540386],"type":"Point"}
}