{
  "type": "Feature",
  "properties": {
    "addr:full":"Cavendish Avenue London Greater London W13 0JG",
    "addr:postcode":"w13 0jg",
    "addr:street":"Cavendish Avenue",
    "iso:country":"GB",
    "sg:address":"Cavendish Avenue",
    "sg:city":"London",
    "sg:classifiers":[
        {
            "category":"Education",
            "subcategory":"Special Training",
            "type":"Public Place"
        },
        {
            "category":"Government",
            "subcategory":"Office",
            "type":"Public Place"
        }
    ],
    "sg:phone":"+44 20 8998 2700",
    "sg:postcode":"W13 0JG",
    "sg:province":"Greater London",
    "sg:tags":[
        "school",
        "local"
    ],
    "wof:name":"Springhallow Special School",
    "wof:placetype":"venue"
},
  "geometry": {"coordinates":[-0.32894,51.521587],"type":"Point"}
}