{
  "type": "Feature",
  "properties": {
    "addr:full":"12 Swanage Grn, Clifford Pk,walsgrave Coventry Warwickshire CV2 2JP",
    "addr:housenumber":"12",
    "addr:postcode":"cv2 2jp",
    "addr:street":"Swanage Grn Clifford Pk Walsgrave",
    "iso:country":"GB",
    "sg:address":"12 Swanage Grn, Clifford Pk,walsgrave",
    "sg:city":"Coventry",
    "sg:classifiers":[
        {
            "category":"Sports & Exercise",
            "subcategory":"Golf",
            "type":"Entertainment"
        }
    ],
    "sg:postcode":"CV2 2JP",
    "sg:province":"Warwickshire",
    "sg:tags":[
        "club",
        "course",
        "equipment"
    ],
    "wof:name":"European Golf Services Ltd",
    "wof:placetype":"venue"
},
  "geometry": {"coordinates":[-1.4420419931,52.4163208008],"type":"Point"}
}