{
  "type": "Feature",
  "properties": {
    "iso:country":"GB",
    "sg:address":"21 Criterion Arcade",
    "sg:city":"Bournemouth",
    "sg:classifiers":[
        {
            "category":"Shopping",
            "subcategory":"Department Store",
            "type":"Retail Goods"
        },
        {
            "category":"Shopping",
            "subcategory":"Photographic Equipment",
            "type":"Retail Goods"
        }
    ],
    "sg:postcode":"BH1 1BU",
    "sg:province":"Dorset",
    "sg:tags":[
        "supply"
    ],
    "wof:name":"Victor Cameras",
    "wof:placetype":"venue"
},
  "geometry": {"coordinates":[-1.8776,50.720661],"type":"Point"}
}