{
  "type": "Feature",
  "properties": {
    "iso:country":"GB",
    "sg:address":"53 Imperial Road",
    "sg:city":"Exmouth",
    "sg:classifiers":[
        {
            "category":"Health Services",
            "subcategory":"Chiropractor",
            "type":"Services"
        }
    ],
    "sg:phone":"+44 1395 222656",
    "sg:postcode":"EX8 1DQ",
    "sg:province":"Devon",
    "wof:name":"M Martineau",
    "wof:placetype":"venue"
},
  "geometry": {"coordinates":[-3.416488,50.619637],"type":"Point"}
}