{
  "type": "Feature",
  "properties": {
    "iso:country":"GB",
    "sg:address":"17-21 Patterson Road, Finedon Road Industrial Estate",
    "sg:city":"Wellingborough",
    "sg:classifiers":[
        {
            "category":"Manufacturing",
            "subcategory":"Metals",
            "type":"Manufacturing & Wholesale Goods"
        },
        {
            "category":"Home & Garden",
            "subcategory":"Kitchen Supply",
            "type":"Retail Goods"
        }
    ],
    "sg:phone":"+44 1933 440573",
    "sg:postcode":"NN8 4BZ",
    "sg:province":"Northamptonshire",
    "sg:tags":[
        "equipment",
        "work",
        "sheet",
        "catering"
    ],
    "wof:name":"Metal Craft Industries UK Ltd",
    "wof:placetype":"venue"
},
  "geometry": {"coordinates":[-0.696296,52.302422],"type":"Point"}
}