{
  "type": "Feature",
  "properties": {
    "iso:country":"GB",
    "sg:address":"109 Granby St",
    "sg:city":"Leicester",
    "sg:classifiers":[
        {
            "category":"Professional",
            "type":"Services"
        }
    ],
    "sg:phone":"+44 116 233 0064",
    "sg:postcode":"LE1 6FD",
    "sg:province":"Leicestershire",
    "sg:tags":[
        "caterer"
    ],
    "wof:name":"Toy Catering",
    "wof:placetype":"venue"
},
  "geometry": {"coordinates":[-1.128362,52.632595],"type":"Point"}
}