{
  "type": "Feature",
  "properties": {
    "iso:country":"GB",
    "sg:address":"80 Stourport Road",
    "sg:city":"Kidderminster",
    "sg:classifiers":[
        {
            "category":"Cinema",
            "subcategory":"Movie Rental",
            "type":"Entertainment"
        }
    ],
    "sg:phone":"+44 1562 743970",
    "sg:postcode":"DY11 7BQ",
    "sg:province":"Staffordshire",
    "sg:tags":[
        "video",
        "library"
    ],
    "sg:website":"http://www.choicesuk.com",
    "wof:name":"Choices Video Ltd",
    "wof:placetype":"venue"
},
  "geometry": {"coordinates":[-2.259809,52.375816],"type":"Point"}
}