{
  "type": "Feature",
  "properties": {
    "addr:full":"23/24 Maelfa, Llanedeyrn Cardiff Cardiff CF23 9PL",
    "addr:housenumber":"23 / 24",
    "addr:postcode":"cf23 9pl",
    "addr:street":"Maelfa Llanedeyrn",
    "iso:country":"GB",
    "sg:address":"23/24 Maelfa, Llanedeyrn",
    "sg:city":"Cardiff",
    "sg:classifiers":[
        {
            "category":"Shopping",
            "subcategory":"Gifts & Souvenirs",
            "type":"Retail Goods"
        }
    ],
    "sg:phone":"+44 29 2021 8808",
    "sg:postcode":"CF23 9PL",
    "sg:province":"Cardiff",
    "sg:tags":[
        "poster",
        "card"
    ],
    "wof:name":"Maelfa Cards",
    "wof:placetype":"venue"
},
  "geometry": {"coordinates":[-3.149116,51.50742],"type":"Point"}
}