{
  "type": "Feature",
  "properties": {
    "addr:full":"27 St Anns Road, Holland Park London Greater London W11 4ST",
    "addr:housenumber":"27",
    "addr:postcode":"w11 4st",
    "addr:street":"St Anns Road",
    "iso:country":"GB",
    "sg:address":"27 St Anns Road, Holland Park",
    "sg:city":"London",
    "sg:classifiers":[
        {
            "category":"Building & Trades",
            "subcategory":"Construction",
            "type":"Services"
        }
    ],
    "sg:phone":"+44 20 7603 1808",
    "sg:postcode":"W11 4ST",
    "sg:province":"Greater London",
    "sg:tags":[
        "flooring"
    ],
    "wof:name":"London Carpets",
    "wof:placetype":"venue"
},
  "geometry": {"coordinates":[-0.215812,51.508541],"type":"Point"}
}