{
  "type": "Feature",
  "properties": {
    "addr:full":"Post Office, Llanbedrog Pwllheli Gwynedd LL53 7PF",
    "addr:postcode":"ll53 7pf",
    "iso:country":"GB",
    "sg:address":"Post Office, Llanbedrog",
    "sg:city":"Pwllheli",
    "sg:classifiers":[
        {
            "category":"Government",
            "subcategory":"Post Office",
            "type":"Public Place"
        }
    ],
    "sg:phone":"+44 1758 740937",
    "sg:postcode":"LL53 7PF",
    "sg:province":"Gwynedd",
    "wof:name":"Llanbedrog Post Office",
    "wof:placetype":"venue"
},
  "geometry": {"coordinates":[-4.4851088524,52.8581123352],"type":"Point"}
}