{
  "type": "Feature",
  "properties": {
    "iso:country":"GB",
    "sg:address":"38 Yorkshire Street",
    "sg:city":"Rochdale",
    "sg:classifiers":[
        {
            "category":"Sports & Exercise",
            "subcategory":"Sports Center",
            "type":"Entertainment"
        }
    ],
    "sg:phone":"+44 1706 712828",
    "sg:postcode":"OL16 1JN",
    "sg:province":"Lancashire",
    "sg:tags":[
        "shop",
        "good"
    ],
    "wof:name":"J D Sports",
    "wof:placetype":"venue"
},
  "geometry": {"coordinates":[-2.1573219299,53.6181755066],"type":"Point"}
}