{
  "type": "Feature",
  "properties": {
    "addr:full":"Astmans Farm, Lassington Lane, Highnam Gloucester Gloucestershire GL2 8DH",
    "addr:postcode":"gl2 8dh",
    "addr:street":"Lassington Lane",
    "iso:country":"GB",
    "sg:address":"Astmans Farm, Lassington Lane, Highnam",
    "sg:city":"Gloucester",
    "sg:classifiers":[
        {
            "category":"Farming",
            "subcategory":"Livestock Farm",
            "type":"Manufacturing & Wholesale Goods"
        }
    ],
    "sg:postcode":"GL2 8DH",
    "sg:province":"Gloucestershire",
    "sg:tags":[
        "others"
    ],
    "wof:name":"G M Smith & Son",
    "wof:placetype":"venue"
},
  "geometry": {"coordinates":[-2.298154,51.877087],"type":"Point"}
}