{
  "type": "Feature",
  "properties": {
    "iso:country":"GB",
    "sg:address":"Stoneleigh, Bexhill Road",
    "sg:city":"Battle",
    "sg:classifiers":[
        {
            "category":"Building & Trades",
            "subcategory":"Construction",
            "type":"Services"
        }
    ],
    "sg:phone":"+44 1424 892257",
    "sg:postcode":"TN33 9EE",
    "sg:province":"East Sussex",
    "sg:tags":[
        "roofing"
    ],
    "wof:name":"Haffendens Roofing",
    "wof:placetype":"venue"
},
  "geometry": {"coordinates":[0.489025,50.914616],"type":"Point"}
}