{
  "type": "Feature",
  "properties": {
    "addr:full":"2 Warren Cottages, Micheldever Station Winchester Hampshire SO21 3AS",
    "addr:housenumber":"2",
    "addr:postcode":"so21 3as",
    "addr:street":"Warren Cottages",
    "iso:country":"GB",
    "sg:address":"2 Warren Cottages, Micheldever Station",
    "sg:city":"Winchester",
    "sg:classifiers":[
        {
            "category":"Professional",
            "subcategory":"Detective & Security Services",
            "type":"Services"
        }
    ],
    "sg:postcode":"SO21 3AS",
    "sg:province":"Hampshire",
    "sg:tags":[
        "video",
        "cctv"
    ],
    "wof:name":"Kamtek Surveys",
    "wof:placetype":"venue"
},
  "geometry": {"coordinates":[-1.2655949593,51.1485671997],"type":"Point"}
}