{
  "type": "Feature",
  "properties": {
    "addr:full":"36 Moat Sole Sandwich Kent CT13 9AU",
    "addr:housenumber":"36",
    "addr:postcode":"ct13 9au",
    "addr:street":"Moat Sole",
    "iso:country":"GB",
    "sg:address":"36 Moat Sole",
    "sg:city":"Sandwich",
    "sg:classifiers":[
        {
            "category":"Retail",
            "subcategory":"Auto Repair",
            "type":"Services"
        }
    ],
    "sg:phone":"+44 1304 620469",
    "sg:postcode":"CT13 9AU",
    "sg:province":"Kent",
    "sg:tags":[
        "engine",
        "car",
        "specialist"
    ],
    "wof:name":"Hometune Motoring Services",
    "wof:placetype":"venue"
},
  "geometry": {"coordinates":[1.3364429474,51.2739372253],"type":"Point"}
}