{
  "type": "Feature",
  "properties": {
    "iso:country":"GB",
    "sg:address":"Victoria Close",
    "sg:city":"Rickmansworth",
    "sg:classifiers":[
        {
            "category":"Travel",
            "subcategory":"Hotels & Motels",
            "type":"Entertainment"
        }
    ],
    "sg:phone":"+44 1923 779466",
    "sg:postcode":"WD3 4EQ",
    "sg:province":"Hertfordshire",
    "wof:name":"Long Island Exchange",
    "wof:placetype":"venue"
},
  "geometry": {"coordinates":[-0.473713,51.641323],"type":"Point"}
}