{
  "type": "Feature",
  "properties": {
    "addr:full":"Gun Meadow, Salisbury Road, Walmer Deal Kent CT14 7QJ",
    "addr:postcode":"ct14 7qj",
    "addr:street":"Gun Meadow Salisbury Road",
    "iso:country":"GB",
    "sg:address":"Gun Meadow, Salisbury Road, Walmer",
    "sg:city":"Deal",
    "sg:classifiers":[
        {
            "category":"Arena",
            "subcategory":"Sports Club",
            "type":"Entertainment"
        }
    ],
    "sg:phone":"+44 1304 368738",
    "sg:postcode":"CT14 7QJ",
    "sg:province":"Kent",
    "wof:name":"Deal Victoria & Barns Close Cricket Club",
    "wof:placetype":"venue"
},
  "geometry": {"coordinates":[1.391783,51.203434],"type":"Point"}
}