{
  "type": "Feature",
  "properties": {
    "iso:country":"GB",
    "sg:address":"P O Box 55",
    "sg:city":"Hounslow",
    "sg:classifiers":[
        {
            "category":"Professional",
            "subcategory":"Lawyer & Legal Services",
            "type":"Services"
        }
    ],
    "sg:phone":"+44 7956 116117",
    "sg:postcode":"W5 2WW",
    "sg:province":"Greater London",
    "sg:tags":[
        "advice",
        "counselling"
    ],
    "wof:name":"Man In Crisis",
    "wof:placetype":"venue"
},
  "geometry": {"coordinates":[-0.30294,51.517799],"type":"Point"}
}