{
  "type": "Feature",
  "properties": {
    "iso:country":"GB",
    "sg:address":"6a Park Drive, Sandiacre",
    "sg:city":"Nottingham",
    "sg:classifiers":[
        {
            "category":"Shopping",
            "subcategory":"Computers & Home Electronics",
            "type":"Retail Goods"
        }
    ],
    "sg:phone":"+44 115 973 3689",
    "sg:postcode":"NG10 5NB",
    "sg:province":"Derbyshire",
    "sg:tags":[
        "aerial",
        "television",
        "radio"
    ],
    "wof:name":"Action Tv Aerial Specialists",
    "wof:placetype":"venue"
},
  "geometry": {"coordinates":[-1.294605,52.912369],"type":"Point"}
}