{
  "type": "Feature",
  "properties": {
    "addr:full":"118 Broadway, Treforest Pontypridd Caerphilly CF37 1BE",
    "addr:housenumber":"118",
    "addr:postcode":"cf37 1be",
    "addr:street":"Broadway",
    "iso:country":"GB",
    "sg:address":"118 Broadway, Treforest",
    "sg:city":"Pontypridd",
    "sg:classifiers":[
        {
            "category":"Shopping",
            "subcategory":"Event Tickets",
            "type":"Retail Goods"
        }
    ],
    "sg:postcode":"CF37 1BE",
    "sg:province":"Caerphilly",
    "sg:tags":[
        "agency"
    ],
    "wof:name":"Essential Tickets & Travel Ltd",
    "wof:placetype":"venue"
},
  "geometry": {"coordinates":[-3.3359589577,51.5989494324],"type":"Point"}
}