{
  "type": "Feature",
  "properties": {
    "iso:country":"GB",
    "sg:address":"James St",
    "sg:city":"York",
    "sg:classifiers":[
        {
            "category":"Manufacturing",
            "subcategory":"Building Materials",
            "type":"Manufacturing & Wholesale Goods"
        }
    ],
    "sg:phone":"+44 1904 430044",
    "sg:postcode":"YO1 3DW",
    "sg:province":"North Yorkshire",
    "sg:tags":[
        "merchant",
        "builder"
    ],
    "wof:name":"Hall & Co Ltd",
    "wof:placetype":"venue"
},
  "geometry": {"coordinates":[-1.067674,53.955662],"type":"Point"}
}