{
  "type": "Feature",
  "properties": {
    "iso:country":"GB",
    "sg:address":"142 Haughton Green Rd, Denton",
    "sg:city":"Manchester",
    "sg:classifiers":[
        {
            "category":"Bars & Pubs",
            "type":"Food & Drink"
        },
        {
            "category":"Community Center",
            "subcategory":"Social",
            "type":"Public Place"
        }
    ],
    "sg:phone":"+44 161 336 6380",
    "sg:postcode":"M34 7GQ",
    "sg:province":"Greater Manchester",
    "sg:tags":[
        "pubs",
        "house",
        "inn",
        "activity"
    ],
    "wof:name":"Bay Horse",
    "wof:placetype":"venue"
},
  "geometry": {"coordinates":[-2.0984549522,53.4410743713],"type":"Point"}
}