{
  "type": "Feature",
  "properties": {
    "iso:country":"GB",
    "sg:address":"201 Main Street",
    "sg:city":"Prestwick",
    "sg:classifiers":[
        {
            "category":"Professional",
            "subcategory":"Computer Services",
            "type":"Services"
        }
    ],
    "sg:postcode":"KA9 1LH",
    "sg:province":"South Ayrshire",
    "sg:tags":[
        "system",
        "software"
    ],
    "wof:name":"P C Solutions",
    "wof:placetype":"venue"
},
  "geometry": {"coordinates":[-4.612646,55.496616],"type":"Point"}
}