{
  "type": "Feature",
  "properties": {
    "iso:country":"GB",
    "sg:address":"345 High St",
    "sg:city":"Lincoln",
    "sg:classifiers":[
        {
            "category":"Travel",
            "subcategory":"Travel Agent",
            "type":"Entertainment"
        }
    ],
    "sg:phone":"+44 1522 520972",
    "sg:postcode":"LN5 7DQ",
    "sg:province":"Lincolnshire",
    "wof:name":"L S G Newspapers Reader Holiday Lincs",
    "wof:placetype":"venue"
},
  "geometry": {"coordinates":[-0.5421100259,53.2256584167],"type":"Point"}
}