{
  "type": "Feature",
  "properties": {
    "iso:country":"GB",
    "sg:address":"Mill Hill Farm, Chatton",
    "sg:city":"Alnwick",
    "sg:classifiers":[
        {
            "category":"Farming",
            "subcategory":"Farm",
            "type":"Manufacturing & Wholesale Goods"
        }
    ],
    "sg:phone":"+44 1668 215246",
    "sg:postcode":"NE66 5PR",
    "sg:province":"Northumberland",
    "sg:tags":[
        "mixed",
        "crop"
    ],
    "wof:name":"J A Douglas",
    "wof:placetype":"venue"
},
  "geometry": {"coordinates":[-1.9103300571,55.5492897034],"type":"Point"}
}