{
  "type": "Feature",
  "properties": {
    "addr:full":"2 South John Street New Quay Ceredigion SA45 9NG",
    "addr:housenumber":"2",
    "addr:postcode":"sa45 9ng",
    "addr:street":"South John Street",
    "iso:country":"GB",
    "sg:address":"2 South John Street",
    "sg:city":"New Quay",
    "sg:classifiers":[
        {
            "category":"Restaurant",
            "type":"Food & Drink"
        }
    ],
    "sg:phone":"+44 1545 560680",
    "sg:postcode":"SA45 9NG",
    "sg:province":"Ceredigion",
    "wof:name":"The Hungry Trout Restaurant",
    "wof:placetype":"venue"
},
  "geometry": {"coordinates":[-4.358208,52.215309],"type":"Point"}
}