{
  "type": "Feature",
  "properties": {
    "iso:country":"GB",
    "sg:address":"Wattons La",
    "sg:city":"Leamington Spa",
    "sg:classifiers":[
        {
            "category":"Building & Trades",
            "subcategory":"Equipment Rental",
            "type":"Services"
        }
    ],
    "sg:phone":"+44 1926 814770",
    "sg:postcode":"CV33 0HX",
    "sg:province":"Warwickshire",
    "sg:tags":[
        "hire",
        "centre"
    ],
    "wof:name":"Priory Tool Hire",
    "wof:placetype":"venue"
},
  "geometry": {"coordinates":[-1.3925089836,52.2529602051],"type":"Point"}
}