{
  "type": "Feature",
  "properties": {
    "addr:full":"7 Addy Close, Netherthorpe Sheffield South Yorkshire S6 3GS",
    "addr:housenumber":"7",
    "addr:postcode":"s6 3gs",
    "addr:street":"Addy Close",
    "iso:country":"GB",
    "sg:address":"7 Addy Close, Netherthorpe",
    "sg:city":"Sheffield",
    "sg:classifiers":[
        {
            "category":"Building & Trades",
            "subcategory":"Construction",
            "type":"Services"
        }
    ],
    "sg:postcode":"S6 3GS",
    "sg:province":"South Yorkshire",
    "sg:tags":[
        "builder"
    ],
    "wof:name":"Fabix Construction Ltd.",
    "wof:placetype":"venue"
},
  "geometry": {"coordinates":[-1.489331,53.388695],"type":"Point"}
}