{
  "type": "Feature",
  "properties": {
    "addr:full":"13 Tonning St Lowestoft Suffolk NR32 2AL",
    "addr:housenumber":"13",
    "addr:postcode":"nr32 2al",
    "addr:street":"Tonning St",
    "iso:country":"GB",
    "sg:address":"13 Tonning St",
    "sg:city":"Lowestoft",
    "sg:classifiers":[
        {
            "category":"Home & Garden",
            "subcategory":"Home Furnishings",
            "type":"Retail Goods"
        }
    ],
    "sg:phone":"+44 1502 537603",
    "sg:postcode":"NR32 2AL",
    "sg:province":"Suffolk",
    "sg:tags":[
        "homefurnishings"
    ],
    "wof:name":"Waveney Wardrobes",
    "wof:placetype":"venue"
},
  "geometry": {"coordinates":[1.748463,52.475277],"type":"Point"}
}