{
  "type": "Feature",
  "properties": {
    "addr:full":"6 Highbridge Street Waltham Abbey Essex EN9 1DG",
    "addr:housenumber":"6",
    "addr:postcode":"en9 1dg",
    "addr:street":"Highbridge Street",
    "iso:country":"GB",
    "sg:address":"6 Highbridge Street",
    "sg:city":"Waltham Abbey",
    "sg:classifiers":[
        {
            "category":"Banks & Credit Unions",
            "subcategory":"Financial Services",
            "type":"Services"
        }
    ],
    "sg:phone":"+44 1992 788993",
    "sg:postcode":"EN9 1DG",
    "sg:province":"Essex",
    "sg:tags":[
        "adviser"
    ],
    "wof:name":"Huson Biggs & Co.",
    "wof:placetype":"venue"
},
  "geometry": {"coordinates":[-0.004096,51.6874351501],"type":"Point"}
}