{
  "type": "Feature",
  "properties": {
    "addr:full":"6 Western Rd Billericay Essex CM12 9DZ",
    "addr:housenumber":"6",
    "addr:postcode":"cm12 9dz",
    "addr:street":"Western Rd",
    "iso:country":"GB",
    "sg:address":"6 Western Rd",
    "sg:city":"Billericay",
    "sg:classifiers":[
        {
            "category":"Retail",
            "subcategory":"Laundry & Dry Cleaning",
            "type":"Services"
        }
    ],
    "sg:phone":"+44 1277 626274",
    "sg:postcode":"CM12 9DZ",
    "sg:province":"Essex",
    "sg:tags":[
        "cleaner",
        "alteration"
    ],
    "wof:name":"Presstigue Dry Cleaners",
    "wof:placetype":"venue"
},
  "geometry": {"coordinates":[0.4187819958,51.6277236938],"type":"Point"}
}