{
  "type": "Feature",
  "properties": {
    "iso:country":"GB",
    "sg:address":"Bradford House, Droitwich Road, Hartlebury",
    "sg:city":"Kidderminster",
    "sg:classifiers":[
        {
            "category":"Farming",
            "subcategory":"Livestock Farm",
            "type":"Manufacturing & Wholesale Goods"
        }
    ],
    "sg:phone":"+44 1299 250325",
    "sg:postcode":"DY10 4EA",
    "sg:province":"Staffordshire",
    "sg:tags":[
        "others"
    ],
    "wof:name":"T G Cartridge",
    "wof:placetype":"venue"
},
  "geometry": {"coordinates":[-2.2146179676,52.348072052],"type":"Point"}
}