{
  "type": "Feature",
  "properties": {
    "iso:country":"GB",
    "sg:address":"Croftronan",
    "sg:city":"Boat Of Garten",
    "sg:classifiers":[
        {
            "category":"Professional",
            "subcategory":"Art Services",
            "type":"Services"
        }
    ],
    "sg:postcode":"PH24 3BY",
    "sg:province":"Highland",
    "sg:tags":[
        "photographer"
    ],
    "wof:name":"Wildlife Images",
    "wof:placetype":"venue"
},
  "geometry": {"coordinates":[-3.762189,57.249279],"type":"Point"}
}