{
  "type": "Feature",
  "properties": {
    "addr:full":"Care Of Forte Post Ho Northampton Northamptonshire NN6 7XR",
    "addr:postcode":"nn6 7xr",
    "iso:country":"GB",
    "sg:address":"Care Of Forte Post Ho",
    "sg:city":"Northampton",
    "sg:classifiers":[
        {
            "category":"Professional",
            "subcategory":"Business Services",
            "type":"Services"
        }
    ],
    "sg:phone":"+44 1788 824000",
    "sg:postcode":"NN6 7XR",
    "sg:province":"Northamptonshire",
    "sg:tags":[
        "distribution"
    ],
    "wof:name":"Dirft Ltd",
    "wof:placetype":"venue"
},
  "geometry": {"coordinates":[-1.14773,52.351871],"type":"Point"}
}