{
  "type": "Feature",
  "properties": {
    "addr:full":"182 Station Rd, Rolleston On Dove Burton-on-trent Derbyshire DE13 9AB",
    "addr:housenumber":"182",
    "addr:postcode":"de13 9ab",
    "addr:street":"Station Rd",
    "iso:country":"GB",
    "sg:address":"182 Station Rd, Rolleston On Dove",
    "sg:city":"Burton-on-trent",
    "sg:classifiers":[
        {
            "category":"Banks & Credit Unions",
            "subcategory":"Investment Brokerage",
            "type":"Services"
        }
    ],
    "sg:postcode":"DE13 9AB",
    "sg:province":"Derbyshire",
    "sg:tags":[
        "message",
        "greeting"
    ],
    "wof:name":"Ariss,Alan,",
    "wof:placetype":"venue"
},
  "geometry": {"coordinates":[-1.6366590261,52.8466644287],"type":"Point"}
}