{
  "type": "Feature",
  "properties": {
    "addr:full":"18 Highbury Gro Highbury Greater London N5 2EA",
    "addr:housenumber":"18",
    "addr:postcode":"n5 2ea",
    "addr:street":"Highbury Gro",
    "iso:country":"GB",
    "sg:address":"18 Highbury Gro",
    "sg:city":"Highbury",
    "sg:classifiers":[
        {
            "category":"Organizations",
            "subcategory":"Non-profit Organization",
            "type":"Services"
        }
    ],
    "sg:phone":"+44 20 7288 1051",
    "sg:postcode":"N5 2EA",
    "sg:province":"Greater London",
    "sg:tags":[
        "organisation",
        "voluntary",
        "charity"
    ],
    "wof:name":"The Haven",
    "wof:placetype":"venue"
},
  "geometry": {"coordinates":[-0.0954200029,51.5546722412],"type":"Point"}
}