{
  "type": "Feature",
  "properties": {
    "addr:full":"160 Leigh Road Leigh Lancashire WN7 1SJ",
    "addr:housenumber":"160",
    "addr:postcode":"wn7 1sj",
    "addr:street":"Leigh Road Leigh",
    "iso:country":"GB",
    "sg:address":"160 Leigh Road",
    "sg:city":"Leigh",
    "sg:classifiers":[
        {
            "category":"Food & Beverages",
            "subcategory":"Liquor & Beverages",
            "type":"Retail Goods"
        }
    ],
    "sg:phone":"+44 1942 672098",
    "sg:postcode":"WN7 1SJ",
    "sg:province":"Lancashire",
    "sg:tags":[
        "beer",
        "spirit",
        "wines"
    ],
    "wof:name":"Booze Buster",
    "wof:placetype":"venue"
},
  "geometry": {"coordinates":[-2.518093,53.504288],"type":"Point"}
}