{
  "type": "Feature",
  "properties": {
    "addr:full":"Ashland Ho, 20 Moxon St West End Hampshire W1M 3JE",
    "addr:housenumber":"20",
    "addr:postcode":"w1m 3je",
    "addr:street":"Moxon St",
    "iso:country":"GB",
    "sg:address":"Ashland Ho, 20 Moxon St",
    "sg:city":"West End",
    "sg:classifiers":[
        {
            "category":"Building & Trades",
            "subcategory":"Construction",
            "type":"Services"
        }
    ],
    "sg:phone":"+44 20 7935 7712",
    "sg:postcode":"W1M 3JE",
    "sg:province":"Hampshire",
    "sg:tags":[
        "restoration",
        "refurbishment"
    ],
    "wof:name":"Renovation Group Ltd The",
    "wof:placetype":"venue"
},
  "geometry": {"coordinates":[-0.1523080021,51.5199546814],"type":"Point"}
}