{
  "type": "Feature",
  "properties": {
    "iso:country":"GB",
    "sg:address":"Skegness Area Office, Town Hall, North Parade",
    "sg:city":"Skegness",
    "sg:classifiers":[
        {
            "category":"Education",
            "subcategory":"Special Training",
            "type":"Public Place"
        }
    ],
    "sg:phone":"+44 1754 610381",
    "sg:postcode":"PE25 1DA",
    "sg:province":"Lincolnshire",
    "sg:tags":[
        "product",
        "centre"
    ],
    "wof:name":"Manby Park Training Centre",
    "wof:placetype":"venue"
},
  "geometry": {"coordinates":[0.343417,53.187164],"type":"Point"}
}