{
  "type": "Feature",
  "properties": {
    "iso:country":"GB",
    "sg:address":"Highway Depot, Station Road East, Whittlesford",
    "sg:city":"Cambridge",
    "sg:classifiers":[
        {
            "category":"Building & Trades",
            "subcategory":"Construction",
            "type":"Services"
        }
    ],
    "sg:phone":"+44 1223 837651",
    "sg:postcode":"CB2 4NL",
    "sg:province":"Cambridgeshire",
    "sg:tags":[
        "surfacing",
        "road"
    ],
    "wof:name":"Ringway Highway Services",
    "wof:placetype":"venue"
},
  "geometry": {"coordinates":[0.1479309946,52.1121940613],"type":"Point"}
}