{
  "type": "Feature",
  "properties": {
    "iso:country":"GB",
    "sg:address":"1 Amesbury Rd",
    "sg:city":"Birmingham",
    "sg:classifiers":[
        {
            "category":"Social Services",
            "subcategory":"Adult Care",
            "type":"Services"
        }
    ],
    "sg:postcode":"B13 8LD",
    "sg:province":"West Midlands",
    "sg:tags":[
        "day",
        "centre"
    ],
    "wof:name":"Moseley Day Centre",
    "wof:placetype":"venue"
},
  "geometry": {"coordinates":[-1.89509,52.448444],"type":"Point"}
}