{
  "type": "Feature",
  "properties": {
    "iso:country":"GB",
    "sg:address":"2 Denmark Road",
    "sg:city":"Reading",
    "sg:classifiers":[
        {
            "category":"Professional",
            "subcategory":"Art Services",
            "type":"Services"
        }
    ],
    "sg:phone":"+44 118 986 1672",
    "sg:postcode":"RG1 5PA",
    "sg:province":"Berkshire",
    "sg:tags":[
        "graphic",
        "designer"
    ],
    "wof:name":"Indent Designers",
    "wof:placetype":"venue"
},
  "geometry": {"coordinates":[-0.954983,51.451763],"type":"Point"}
}