{
  "type": "Feature",
  "properties": {
    "addr:full":"56 Washington Gro, Bentley Doncaster South Yorkshire DN5 9RL",
    "addr:housenumber":"56",
    "addr:postcode":"dn5 9rl",
    "addr:street":"Washington Gro",
    "iso:country":"GB",
    "sg:address":"56 Washington Gro, Bentley",
    "sg:city":"Doncaster",
    "sg:classifiers":[
        {
            "category":"Professional",
            "subcategory":"Detective & Security Services",
            "type":"Services"
        }
    ],
    "sg:phone":"+44 1302 874728",
    "sg:postcode":"DN5 9RL",
    "sg:province":"South Yorkshire",
    "sg:tags":[
        "alarm",
        "burglar",
        "system"
    ],
    "wof:name":"Active Alarms",
    "wof:placetype":"venue"
},
  "geometry": {"coordinates":[-1.1519140005,53.5397377014],"type":"Point"}
}