{
  "type": "Feature",
  "properties": {
    "iso:country":"GB",
    "sg:address":"Calthorpe Cottage, Ingham",
    "sg:city":"Norwich",
    "sg:classifiers":[
        {
            "category":"Social Services",
            "subcategory":"Job Training",
            "type":"Services"
        }
    ],
    "sg:postcode":"NR12 9TF",
    "sg:province":"Norfolk",
    "sg:tags":[
        "translator",
        "interpreter"
    ],
    "wof:name":"Lingua-Franca Ltd.",
    "wof:placetype":"venue"
},
  "geometry": {"coordinates":[1.535964,52.778652],"type":"Point"}
}