{
  "type": "Feature",
  "properties": {
    "addr:full":"37 Annesley Rd Sheffield Derbyshire S8 7SD",
    "addr:housenumber":"37",
    "addr:postcode":"s8 7sd",
    "addr:street":"Annesley Rd",
    "iso:country":"GB",
    "sg:address":"37 Annesley Rd",
    "sg:city":"Sheffield",
    "sg:classifiers":[
        {
            "category":"Building & Trades",
            "subcategory":"Construction",
            "type":"Services"
        }
    ],
    "sg:phone":"+44 114 274 6994",
    "sg:postcode":"S8 7SD",
    "sg:province":"Derbyshire",
    "sg:tags":[
        "decorator",
        "painter"
    ],
    "wof:name":"R W Claxton",
    "wof:placetype":"venue"
},
  "geometry": {"coordinates":[-1.4824310541,53.3292160034],"type":"Point"}
}