{
  "type": "Feature",
  "properties": {
    "iso:country":"GB",
    "sg:address":"5 Leypark Walk",
    "sg:city":"Plymouth",
    "sg:classifiers":[
        {
            "category":"Personal",
            "subcategory":"Beauty Salon",
            "type":"Services"
        }
    ],
    "sg:postcode":"PL6 8UE",
    "sg:province":"Devon",
    "sg:tags":[
        "unisex",
        "hairdresser"
    ],
    "wof:name":"The Attic Hair Salon",
    "wof:placetype":"venue"
},
  "geometry": {"coordinates":[-4.095085,50.409828],"type":"Point"}
}