{
  "type": "Feature",
  "properties": {
    "iso:country":"GB",
    "sg:address":"102 Featherby Road",
    "sg:city":"Gillingham",
    "sg:classifiers":[
        {
            "category":"Shopping",
            "type":"Retail Goods"
        }
    ],
    "sg:phone":"+44 1634 363303",
    "sg:postcode":"ME8 6BB",
    "sg:province":"Kent",
    "sg:tags":[
        "part",
        "accessory"
    ],
    "wof:name":"Drive in (Silencers) Ltd.",
    "wof:placetype":"venue"
},
  "geometry": {"coordinates":[0.573538,51.374176],"type":"Point"}
}