{
  "type": "Feature",
  "properties": {
    "iso:country":"GB",
    "sg:address":"83-87 Crawford Street",
    "sg:city":"London",
    "sg:classifiers":[
        {
            "category":"Professional",
            "subcategory":"Business Services",
            "type":"Services"
        }
    ],
    "sg:phone":"+44 20 7724 9693",
    "sg:postcode":"W1H 2HB",
    "sg:province":"Greater London",
    "sg:tags":[
        "trade"
    ],
    "wof:name":"Corporation of Professional Loss Assessors",
    "wof:placetype":"venue"
},
  "geometry": {"coordinates":[-0.162643,51.519073],"type":"Point"}
}