{
  "type": "Feature",
  "properties": {
    "iso:country":"GB",
    "sg:address":"97 Kingsdown Road, Chase Terrace",
    "sg:city":"Walsall",
    "sg:classifiers":[
        {
            "category":"Building & Trades",
            "subcategory":"Construction",
            "type":"Services"
        }
    ],
    "sg:phone":"+44 1543 270074",
    "sg:postcode":"WS7 8PZ",
    "sg:province":"Staffordshire",
    "sg:tags":[
        "builder"
    ],
    "wof:name":"Viscount Construction",
    "wof:placetype":"venue"
},
  "geometry": {"coordinates":[-1.938786,52.691242],"type":"Point"}
}