{
  "type": "Feature",
  "properties": {
    "addr:full":"3 Tangier Street Whitehaven Cumbria CA28 7UZ",
    "addr:housenumber":"3",
    "addr:postcode":"ca28 7uz",
    "addr:street":"Tangier Street",
    "iso:country":"GB",
    "sg:address":"3 Tangier Street",
    "sg:city":"Whitehaven",
    "sg:classifiers":[
        {
            "category":"Restaurant",
            "type":"Food & Drink"
        }
    ],
    "sg:phone":"+44 1946 691171",
    "sg:postcode":"CA28 7UZ",
    "sg:province":"Cumbria",
    "sg:tags":[
        "indian"
    ],
    "wof:name":"Akash Tandoori Restaurant",
    "wof:placetype":"venue"
},
  "geometry": {"coordinates":[-3.5878210068,54.5502357483],"type":"Point"}
}