{
  "type": "Feature",
  "properties": {
    "addr:full":"Kirkmahoe, Duncow Dumfries Dumfries and Galloway DG1 1TA",
    "addr:postcode":"dg1 1ta",
    "iso:country":"GB",
    "sg:address":"Kirkmahoe, Duncow",
    "sg:city":"Dumfries",
    "sg:classifiers":[
        {
            "category":"Education",
            "subcategory":"School",
            "type":"Public Place"
        }
    ],
    "sg:phone":"+44 1387 710305",
    "sg:postcode":"DG1 1TA",
    "sg:province":"Dumfries and Galloway",
    "sg:tags":[
        "local",
        "authority"
    ],
    "sg:website":"http://www.aem.dumgal.net",
    "wof:name":"Duncow Primary School",
    "wof:placetype":"venue"
},
  "geometry": {"coordinates":[-3.624454,55.133945],"type":"Point"}
}