{
  "type": "Feature",
  "properties": {
    "addr:full":"91 Bannister St Withernsea East Riding of Yorkshire HU19 2DT",
    "addr:housenumber":"91",
    "addr:postcode":"hu19 2dt",
    "addr:street":"Bannister St",
    "iso:country":"GB",
    "sg:address":"91 Bannister St",
    "sg:city":"Withernsea",
    "sg:classifiers":[
        {
            "category":"Place Of Worship",
            "type":"Public Place"
        }
    ],
    "sg:phone":"+44 1964 612204",
    "sg:postcode":"HU19 2DT",
    "sg:province":"East Riding of Yorkshire",
    "wof:name":"St Peter & John Fisher",
    "wof:placetype":"venue"
},
  "geometry": {"coordinates":[0.0327600017,53.7249298096],"type":"Point"}
}