{
  "type": "Feature",
  "properties": {
    "addr:full":"Manor Farm, Pulford Chester Cheshire CH4 9DP",
    "addr:postcode":"ch4 9dp",
    "addr:street":"Manor",
    "iso:country":"GB",
    "sg:address":"Manor Farm, Pulford",
    "sg:city":"Chester",
    "sg:classifiers":[
        {
            "category":"Education",
            "subcategory":"Special Training",
            "type":"Public Place"
        }
    ],
    "sg:postcode":"CH4 9DP",
    "sg:province":"Cheshire",
    "sg:tags":[
        "school",
        "flying"
    ],
    "wof:name":"Deltair Ltd.",
    "wof:placetype":"venue"
},
  "geometry": {"coordinates":[-2.9338140488,53.1236763],"type":"Point"}
}