{
  "type": "Feature",
  "properties": {
    "iso:country":"GB",
    "sg:address":"39 Manor Pl",
    "sg:city":"Edinburgh",
    "sg:classifiers":[
        {
            "category":"Building & Trades",
            "subcategory":"Equipment Rental",
            "type":"Services"
        }
    ],
    "sg:phone":"+44 131 226 1122",
    "sg:postcode":"EH3 7EB",
    "sg:province":"City of Edinburgh",
    "sg:tags":[
        "supply"
    ],
    "wof:name":"Assay Office Edinburgh",
    "wof:placetype":"venue"
},
  "geometry": {"coordinates":[-3.214981,55.952438],"type":"Point"}
}