{
  "type": "Feature",
  "properties": {
    "addr:full":"3 Mark La Eastbourne East Sussex BN21 4RJ",
    "addr:housenumber":"3",
    "addr:postcode":"bn21 4rj",
    "addr:street":"Mark La Eastbourne",
    "iso:country":"GB",
    "sg:address":"3 Mark La",
    "sg:city":"Eastbourne",
    "sg:classifiers":[
        {
            "category":"Shopping",
            "subcategory":"Clothing, Apparel, & Fashions",
            "type":"Retail Goods"
        }
    ],
    "sg:phone":"+44 1323 639890",
    "sg:postcode":"BN21 4RJ",
    "sg:province":"East Sussex",
    "sg:tags":[
        "dresswear"
    ],
    "wof:name":"A Touch Of Class",
    "wof:placetype":"venue"
},
  "geometry": {"coordinates":[0.281892,50.76823],"type":"Point"}
}