{
  "type": "Feature",
  "properties": {
    "addr:full":"614 Bloxwich Road Walsall Staffordshire WS3 2BA",
    "addr:housenumber":"614",
    "addr:postcode":"ws3 2ba",
    "addr:street":"Bloxwich Road",
    "iso:country":"GB",
    "sg:address":"614 Bloxwich Road",
    "sg:city":"Walsall",
    "sg:classifiers":[
        {
            "category":"Bars & Pubs",
            "type":"Food & Drink"
        }
    ],
    "sg:phone":"+44 1922 476475",
    "sg:postcode":"WS3 2BA",
    "sg:province":"Staffordshire",
    "sg:tags":[
        "pubs",
        "inn"
    ],
    "wof:name":"Butler Arms",
    "wof:placetype":"venue"
},
  "geometry": {"coordinates":[-1.994693,52.608307],"type":"Point"}
}