{
  "type": "Feature",
  "properties": {
    "iso:country":"GB",
    "sg:address":"157 Middleton Park Road",
    "sg:city":"Leeds",
    "sg:classifiers":[
        {
            "category":"Travel",
            "subcategory":"Hotels & Motels",
            "type":"Entertainment"
        }
    ],
    "sg:postcode":"LS10 4LZ",
    "sg:province":"West Yorkshire",
    "sg:tags":[
        "house",
        "guest"
    ],
    "wof:name":"The White House",
    "wof:placetype":"venue"
},
  "geometry": {"coordinates":[-1.55361,53.748634],"type":"Point"}
}