{
  "type": "Feature",
  "properties": {
    "addr:full":"25 Park Street St Albans Hertfordshire AL4 9QL",
    "addr:housenumber":"25",
    "addr:postcode":"al4 9ql",
    "addr:street":"Park Street",
    "iso:country":"GB",
    "sg:address":"25 Park Street",
    "sg:city":"St Albans",
    "sg:classifiers":[
        {
            "category":"Education",
            "subcategory":"Dance Studio",
            "type":"Public Place"
        }
    ],
    "sg:postcode":"AL4 9QL",
    "sg:province":"Hertfordshire",
    "sg:tags":[
        "school",
        "dancing"
    ],
    "wof:name":"Lets Dance",
    "wof:placetype":"venue"
},
  "geometry": {"coordinates":[-0.318086,51.755455],"type":"Point"}
}