{
  "type": "Feature",
  "properties": {
    "iso:country":"GB",
    "sg:address":"37 Saxon Street, Stapenhill",
    "sg:city":"Burton-on-trent",
    "sg:classifiers":[
        {
            "category":"Building & Trades",
            "subcategory":"Cleaning & Sanitation",
            "type":"Services"
        }
    ],
    "sg:phone":"+44 1283 537125",
    "sg:postcode":"DE15 9RL",
    "sg:province":"Derbyshire",
    "sg:tags":[
        "dry",
        "control",
        "damp",
        "rot"
    ],
    "wof:name":"Burton Damproofing & Wood Preservation Services Ltd.",
    "wof:placetype":"venue"
},
  "geometry": {"coordinates":[-1.619759,52.789665],"type":"Point"}
}