{
  "type": "Feature",
  "properties": {
    "addr:full":"1 Shrivenham Hundred Business Pa, Rk Majors Road, Watchfield Swindon Gloucestershire SN6 8TZ",
    "addr:housenumber":"1;rk",
    "addr:postcode":"sn6 8tz",
    "addr:street":"Shrivenham Hundred;Majors Road",
    "iso:country":"GB",
    "sg:address":"1 Shrivenham Hundred Business Pa, Rk Majors Road, Watchfield",
    "sg:city":"Swindon",
    "sg:classifiers":[
        {
            "category":"Shopping",
            "subcategory":"Computers & Home Electronics",
            "type":"Retail Goods"
        }
    ],
    "sg:phone":"+44 1793 784377",
    "sg:postcode":"SN6 8TZ",
    "sg:province":"Gloucestershire",
    "sg:tags":[
        "equipment",
        "video",
        "cctv"
    ],
    "wof:name":"A M T V Ltd.",
    "wof:placetype":"venue"
},
  "geometry": {"coordinates":[-1.6466089487,51.6137313843],"type":"Point"}
}