{
  "type": "Feature",
  "properties": {
    "addr:full":"Bentley School, Bentle Lane Leeds West Yorkshire LS6 4AJ",
    "addr:postcode":"ls6 4aj",
    "addr:street":"Bentle Lane",
    "iso:country":"GB",
    "sg:address":"Bentley School, Bentle Lane",
    "sg:city":"Leeds",
    "sg:classifiers":[
        {
            "category":"Education",
            "subcategory":"Library",
            "type":"Public Place"
        },
        {
            "category":"Government",
            "subcategory":"Office",
            "type":"Public Place"
        }
    ],
    "sg:phone":"+44 113 214 4530",
    "sg:postcode":"LS6 4AJ",
    "sg:province":"West Yorkshire",
    "sg:tags":[
        "book",
        "local"
    ],
    "wof:name":"Meanwood Library",
    "wof:placetype":"venue"
},
  "geometry": {"coordinates":[-1.5664989948,53.8260192871],"type":"Point"}
}