{
  "type": "Feature",
  "properties": {
    "iso:country":"GB",
    "sg:address":"32 Cathedral Road",
    "sg:city":"Cardiff",
    "sg:classifiers":[
        {
            "category":"Building & Trades",
            "subcategory":"Construction",
            "type":"Services"
        }
    ],
    "sg:phone":"+44 29 2022 1002",
    "sg:postcode":"CF11 9UQ",
    "sg:province":"Cardiff",
    "sg:tags":[
        "builder"
    ],
    "wof:name":"E Turner & Sons",
    "wof:placetype":"venue"
},
  "geometry": {"coordinates":[-3.1922729015,51.4844398499],"type":"Point"}
}