{
  "type": "Feature",
  "properties": {
    "addr:full":"63 Newbegin Hornsea East Riding of Yorkshire HU18 1AA",
    "addr:housenumber":"63",
    "addr:postcode":"hu18 1aa",
    "addr:street":"Newbegin Hornsea",
    "iso:country":"GB",
    "sg:address":"63 Newbegin",
    "sg:city":"Hornsea",
    "sg:classifiers":[
        {
            "category":"Government",
            "subcategory":"Post Office",
            "type":"Public Place"
        }
    ],
    "sg:phone":"+44 1964 532880",
    "sg:postcode":"HU18 1AA",
    "sg:province":"East Riding of Yorkshire",
    "wof:name":"Hornsea Post Office",
    "wof:placetype":"venue"
},
  "geometry": {"coordinates":[-0.1685290039,53.9117431641],"type":"Point"}
}