{
  "type": "Feature",
  "properties": {
    "addr:full":"23 St Peters Street, Radford Nottingham Nottinghamshire NG7 3EN",
    "addr:housenumber":"23",
    "addr:postcode":"ng7 3en",
    "addr:street":"St Peters Street",
    "iso:country":"GB",
    "sg:address":"23 St Peters Street, Radford",
    "sg:city":"Nottingham",
    "sg:classifiers":[
        {
            "category":"Manufacturing",
            "subcategory":"Wood Products",
            "type":"Manufacturing & Wholesale Goods"
        }
    ],
    "sg:phone":"+44 115 970 5051",
    "sg:postcode":"NG7 3EN",
    "sg:province":"Nottinghamshire",
    "sg:tags":[
        "maker",
        "cabinet"
    ],
    "wof:name":"Davenport Cabinetworks Ltd.",
    "wof:placetype":"venue"
},
  "geometry": {"coordinates":[-1.181032,52.956505],"type":"Point"}
}