{
  "type": "Feature",
  "properties": {
    "addr:full":"Larghan Park, Coupar Angus Blairgowrie Angus PH13 9ES",
    "addr:postcode":"ph13 9es",
    "iso:country":"GB",
    "sg:address":"Larghan Park, Coupar Angus",
    "sg:city":"Blairgowrie",
    "sg:classifiers":[
        {
            "category":"Community Center",
            "type":"Public Place"
        }
    ],
    "sg:phone":"+44 1828 627394",
    "sg:postcode":"PH13 9ES",
    "sg:province":"Angus",
    "sg:tags":[
        "nursery",
        "centre"
    ],
    "wof:name":"Shelley's Corner",
    "wof:placetype":"venue"
},
  "geometry": {"coordinates":[-3.266429,56.546135],"type":"Point"}
}