{
  "type": "Feature",
  "properties": {
    "addr:full":"105 Boldon Lane South Shields Tyne and Wear NE34 0AS",
    "addr:housenumber":"105",
    "addr:postcode":"ne34 0as",
    "addr:street":"Boldon Lane",
    "iso:country":"GB",
    "sg:address":"105 Boldon Lane",
    "sg:city":"South Shields",
    "sg:classifiers":[
        {
            "category":"Personal",
            "subcategory":"Beauty Salon",
            "type":"Services"
        },
        {
            "category":"Personal",
            "subcategory":"Barber",
            "type":"Services"
        }
    ],
    "sg:phone":"+44 191 455 7903",
    "sg:postcode":"NE34 0AS",
    "sg:province":"Tyne and Wear",
    "sg:tags":[
        "unisex",
        "hairdresser"
    ],
    "wof:name":"Cutz",
    "wof:placetype":"venue"
},
  "geometry": {"coordinates":[-1.439665,54.972553],"type":"Point"}
}