{
  "type": "Feature",
  "properties": {
    "addr:full":"261 Nottingham Rd Nottingham Nottinghamshire NG7 7DA",
    "addr:housenumber":"261",
    "addr:postcode":"ng7 7da",
    "addr:street":"Nottingham Rd",
    "iso:country":"GB",
    "sg:address":"261 Nottingham Rd",
    "sg:city":"Nottingham",
    "sg:classifiers":[
        {
            "category":"Health Services",
            "subcategory":"Dentist",
            "type":"Services"
        }
    ],
    "sg:phone":"+44 115 979 1994",
    "sg:postcode":"NG7 7DA",
    "sg:province":"Nottinghamshire",
    "wof:name":"Family Dental Care Centre",
    "wof:placetype":"venue"
},
  "geometry": {"coordinates":[-1.1673289537,52.9771461487],"type":"Point"}
}