{
  "type": "Feature",
  "properties": {
    "iso:country":"GB",
    "sg:address":"55 Seabourne Road",
    "sg:city":"Bournemouth",
    "sg:classifiers":[
        {
            "category":"Food & Beverages",
            "subcategory":"Meat & Fish",
            "type":"Retail Goods"
        }
    ],
    "sg:phone":"+44 1202 423621",
    "sg:postcode":"BH5 2HA",
    "sg:province":"Dorset",
    "sg:tags":[
        "chip"
    ],
    "wof:name":"Smithson's",
    "wof:placetype":"venue"
},
  "geometry": {"coordinates":[-1.823443,50.729832],"type":"Point"}
}