{
  "type": "Feature",
  "properties": {
    "addr:full":"124 Stamford Hill London Greater London N16 6QT",
    "addr:housenumber":"124",
    "addr:postcode":"n16 6qt",
    "addr:street":"Stamford Hill",
    "iso:country":"GB",
    "sg:address":"124 Stamford Hill",
    "sg:city":"London",
    "sg:classifiers":[
        {
            "category":"Community Center",
            "subcategory":"Youth",
            "type":"Public Place"
        }
    ],
    "sg:phone":"+44 20 8802 8414",
    "sg:postcode":"N16 6QT",
    "sg:province":"Greater London",
    "sg:tags":[
        "organisation",
        "centre"
    ],
    "wof:name":"Stamford Hill Youth Club",
    "wof:placetype":"venue"
},
  "geometry": {"coordinates":[-0.072819002,51.5710906982],"type":"Point"}
}