{
  "type": "Feature",
  "properties": {
    "addr:full":"477 Newark Road Lincoln Lincolnshire LN6 8RT",
    "addr:housenumber":"477",
    "addr:postcode":"ln6 8rt",
    "addr:street":"Newark Road",
    "iso:country":"GB",
    "sg:address":"477 Newark Road",
    "sg:city":"Lincoln",
    "sg:classifiers":[
        {
            "category":"Building & Trades",
            "subcategory":"Construction",
            "type":"Services"
        }
    ],
    "sg:phone":"+44 1522 523709",
    "sg:postcode":"LN6 8RT",
    "sg:province":"Lincolnshire",
    "sg:tags":[
        "glazier"
    ],
    "wof:name":"James Harkness",
    "wof:placetype":"venue"
},
  "geometry": {"coordinates":[-0.562652,53.201473],"type":"Point"}
}