{
  "type": "Feature",
  "properties": {
    "iso:country":"GB",
    "sg:address":"Berkeley Place, Lower Clifton Hill",
    "sg:city":"Bristol",
    "sg:classifiers":[
        {
            "category":"Autos & Motor Vehicles",
            "subcategory":"Automobile Sales",
            "type":"Retail Goods"
        }
    ],
    "sg:phone":"+44 117 927 7355",
    "sg:postcode":"BS8 1EH",
    "sg:province":"City of Bristol",
    "sg:tags":[
        "car"
    ],
    "wof:name":"Lex Volvo",
    "wof:placetype":"venue"
},
  "geometry": {"coordinates":[-2.609065,51.455685],"type":"Point"}
}