{
  "type": "Feature",
  "properties": {
    "iso:country":"GB",
    "sg:address":"121 Sutton Rd",
    "sg:city":"Southend On Sea",
    "sg:classifiers":[
        {
            "category":"Food & Beverages",
            "subcategory":"Meat & Fish",
            "type":"Retail Goods"
        }
    ],
    "sg:phone":"+44 1702 300038",
    "sg:postcode":"SS2 5PB",
    "sg:province":"Essex",
    "sg:tags":[
        "chip"
    ],
    "wof:name":"Kingfisher",
    "wof:placetype":"venue"
},
  "geometry": {"coordinates":[0.718365,51.543137],"type":"Point"}
}