{
  "type": "Feature",
  "properties": {
    "iso:country":"GB",
    "sg:address":"23 Hymers Avenue",
    "sg:city":"Hull",
    "sg:classifiers":[
        {
            "category":"Home & Garden",
            "subcategory":"Hardware",
            "type":"Retail Goods"
        }
    ],
    "sg:phone":"+44 1482 441759",
    "sg:postcode":"HU3 1LJ",
    "sg:province":"East Riding of Yorkshire",
    "sg:tags":[
        "lawnmowers",
        "machinery"
    ],
    "wof:name":"Garden Machinery Engineers",
    "wof:placetype":"venue"
},
  "geometry": {"coordinates":[-0.362912,53.750816],"type":"Point"}
}