{
  "type": "Feature",
  "properties": {
    "addr:full":"17a Garston Park Parade Watford Hertfordshire WD25 9LQ",
    "addr:housenumber":"17a",
    "addr:postcode":"wd25 9lq",
    "addr:street":"Garston Park Parade",
    "iso:country":"GB",
    "sg:address":"17a Garston Park Parade",
    "sg:city":"Watford",
    "sg:classifiers":[
        {
            "category":"Building & Trades",
            "subcategory":"Plumbing",
            "type":"Services"
        }
    ],
    "sg:phone":"+44 1923 661098",
    "sg:postcode":"WD25 9LQ",
    "sg:province":"Hertfordshire",
    "sg:tags":[
        "heating"
    ],
    "wof:name":"Olivers Plumbing & Heating",
    "wof:placetype":"venue"
},
  "geometry": {"coordinates":[-0.385662,51.689491],"type":"Point"}
}