{
  "type": "Feature",
  "properties": {
    "iso:country":"GB",
    "sg:address":"Milan Surgery, 2 Milan St",
    "sg:city":"Leeds",
    "sg:classifiers":[
        {
            "category":"Health Services",
            "subcategory":"Doctor",
            "type":"Services"
        }
    ],
    "sg:phone":"+44 113 249 0598",
    "sg:postcode":"LS8 5JW",
    "sg:province":"West Yorkshire",
    "sg:tags":[
        "practitioners"
    ],
    "wof:name":"Nazir, N",
    "wof:placetype":"venue"
},
  "geometry": {"coordinates":[-1.51406,53.814098],"type":"Point"}
}