{
  "type": "Feature",
  "properties": {
    "iso:country":"GB",
    "sg:address":"76 Randolph Drive",
    "sg:city":"Glasgow",
    "sg:classifiers":[
        {
            "category":"Shopping",
            "subcategory":"Musical Instruments",
            "type":"Retail Goods"
        },
        {
            "category":"Professional",
            "subcategory":"Employment Agencies",
            "type":"Services"
        }
    ],
    "sg:phone":"+44 141 637 5576",
    "sg:postcode":"G76 8AP",
    "sg:province":"East Renfrewshire",
    "sg:tags":[
        "sale",
        "organ",
        "accessory"
    ],
    "wof:name":"J A Mackenzie",
    "wof:placetype":"venue"
},
  "geometry": {"coordinates":[-4.268375,55.79702],"type":"Point"}
}