{
  "type": "Feature",
  "properties": {
    "addr:full":"1 Wilkinson Walk Market Drayton Shropshire TF9 1PW",
    "addr:housenumber":"1",
    "addr:postcode":"tf9 1pw",
    "addr:street":"Wilkinson Walk",
    "iso:country":"GB",
    "sg:address":"1 Wilkinson Walk",
    "sg:city":"Market Drayton",
    "sg:classifiers":[
        {
            "category":"Food & Beverages",
            "subcategory":"Specialty",
            "type":"Retail Goods"
        }
    ],
    "sg:phone":"+44 1630 655155",
    "sg:postcode":"TF9 1PW",
    "sg:province":"Shropshire",
    "sg:tags":[
        "retailer",
        "product",
        "health"
    ],
    "wof:name":"Sherwood Wholefoods",
    "wof:placetype":"venue"
},
  "geometry": {"coordinates":[-2.4861719608,52.9040908813],"type":"Point"}
}