{
  "type": "Feature",
  "properties": {
    "addr:full":"Abacus House, Station Yard, Needham Market Ipswich Suffolk IP6 8AS",
    "addr:postcode":"ip6 8as",
    "addr:street":"Station",
    "iso:country":"GB",
    "sg:address":"Abacus House, Station Yard, Needham Market",
    "sg:city":"Ipswich",
    "sg:classifiers":[
        {
            "category":"Manufacturing",
            "subcategory":"Food",
            "type":"Manufacturing & Wholesale Goods"
        }
    ],
    "sg:postcode":"IP6 8AS",
    "sg:province":"Suffolk",
    "sg:tags":[
        "processing"
    ],
    "wof:name":"S T B Process Systems Ltd.",
    "wof:placetype":"venue"
},
  "geometry": {"coordinates":[1.054115,52.15213],"type":"Point"}
}