{
  "type": "Feature",
  "properties": {
    "addr:full":"123 London Road Sawbridgeworth Essex CM21 9JJ",
    "addr:housenumber":"123",
    "addr:postcode":"cm21 9jj",
    "addr:street":"London Road",
    "iso:country":"GB",
    "sg:address":"123 London Road",
    "sg:city":"Sawbridgeworth",
    "sg:classifiers":[
        {
            "category":"Banks & Credit Unions",
            "subcategory":"Bank",
            "type":"Services"
        }
    ],
    "sg:postcode":"CM21 9JJ",
    "sg:province":"Essex",
    "sg:tags":[
        "broker",
        "mortgage"
    ],
    "wof:name":"C B Mortgages",
    "wof:placetype":"venue"
},
  "geometry": {"coordinates":[0.147316,51.813305],"type":"Point"}
}