{
  "type": "Feature",
  "properties": {
    "addr:full":"Central Library, The Wellgate Dundee Dundee City DD1 1DB",
    "addr:postcode":"dd1 1db",
    "addr:street":"The Wellgate",
    "iso:country":"GB",
    "sg:address":"Central Library, The Wellgate",
    "sg:city":"Dundee",
    "sg:classifiers":[
        {
            "category":"Education",
            "subcategory":"Library",
            "type":"Public Place"
        },
        {
            "category":"Government",
            "subcategory":"Office",
            "type":"Public Place"
        }
    ],
    "sg:phone":"+44 1382 434025",
    "sg:postcode":"DD1 1DB",
    "sg:province":"Dundee City",
    "sg:tags":[
        "book",
        "local"
    ],
    "wof:name":"Business Information Uint",
    "wof:placetype":"venue"
},
  "geometry": {"coordinates":[-2.967609,56.461376],"type":"Point"}
}