{
  "type": "Feature",
  "properties": {
    "addr:full":"44 Fog La Manchester Greater Manchester M20 6AG",
    "addr:housenumber":"44",
    "addr:postcode":"m20 6ag",
    "addr:street":"Fog La Manchester",
    "iso:country":"GB",
    "sg:address":"44 Fog La",
    "sg:city":"Manchester",
    "sg:classifiers":[
        {
            "category":"Autos & Motor Vehicles",
            "subcategory":"Fuel & Gas Station",
            "type":"Retail Goods"
        }
    ],
    "sg:phone":"+44 161 445 3388",
    "sg:postcode":"M20 6AG",
    "sg:province":"Greater Manchester",
    "sg:tags":[
        "petrol",
        "filling"
    ],
    "wof:name":"Priory Filling Station",
    "wof:placetype":"venue"
},
  "geometry": {"coordinates":[-2.227836,53.421116],"type":"Point"}
}