{
  "type": "Feature",
  "properties": {
    "addr:full":"Amtest Ho, 75-79 Guildford St Chertsey Surrey KT16 9AS",
    "addr:housenumber":"75-79",
    "addr:postcode":"kt16 9as",
    "addr:street":"Guildford St",
    "iso:country":"GB",
    "sg:address":"Amtest Ho, 75-79 Guildford St",
    "sg:city":"Chertsey",
    "sg:classifiers":[
        {
            "category":"Communications",
            "type":"Services"
        }
    ],
    "sg:phone":"+44 1932 566899",
    "sg:postcode":"KT16 9AS",
    "sg:province":"Surrey",
    "sg:tags":[
        "telecommunication"
    ],
    "wof:name":"Mediacom Tele Facilities",
    "wof:placetype":"venue"
},
  "geometry": {"coordinates":[-0.5082539916,51.3881988525],"type":"Point"}
}