{
  "type": "Feature",
  "properties": {
    "addr:full":"Mt Pleasant Farm, Farm Rd Bridgend Bridgend CF32 0HA",
    "addr:postcode":"cf32 0ha",
    "addr:street":"Mt;Farm Rd",
    "iso:country":"GB",
    "sg:address":"Mt Pleasant Farm, Farm Rd",
    "sg:city":"Bridgend",
    "sg:classifiers":[
        {
            "category":"Shopping",
            "subcategory":"Computers & Home Electronics",
            "type":"Retail Goods"
        }
    ],
    "sg:postcode":"CF32 0HA",
    "sg:province":"Bridgend",
    "wof:name":"Millfields Upholstery",
    "wof:placetype":"venue"
},
  "geometry": {"coordinates":[-3.6296899319,51.53150177],"type":"Point"}
}