{
  "type": "Feature",
  "properties": {
    "addr:full":"3 Portland Street Southampton Hampshire SO14 7EB",
    "addr:housenumber":"3",
    "addr:postcode":"so14 7eb",
    "addr:street":"Portland Street",
    "iso:country":"GB",
    "sg:address":"3 Portland Street",
    "sg:city":"Southampton",
    "sg:classifiers":[
        {
            "category":"Health Services",
            "subcategory":"Dentist",
            "type":"Services"
        }
    ],
    "sg:phone":"+44 23 8033 5156",
    "sg:postcode":"SO14 7EB",
    "sg:province":"Hampshire",
    "wof:name":"Portland Street Dental Practice",
    "wof:placetype":"venue"
},
  "geometry": {"coordinates":[-1.404914,50.904766],"type":"Point"}
}