{
  "type": "Feature",
  "properties": {
    "addr:full":"44a High Street Lampeter Carmarthenshire SA48 7BB",
    "addr:housenumber":"44a",
    "addr:postcode":"sa48 7bb",
    "addr:street":"High Street",
    "iso:country":"GB",
    "sg:address":"44a High Street",
    "sg:city":"Lampeter",
    "sg:classifiers":[
        {
            "category":"Shopping",
            "subcategory":"Thrift Store",
            "type":"Retail Goods"
        }
    ],
    "sg:phone":"+44 1570 423116",
    "sg:postcode":"SA48 7BB",
    "sg:province":"Carmarthenshire",
    "sg:tags":[
        "shop",
        "charity"
    ],
    "wof:name":"Tenovus Cancer Charity",
    "wof:placetype":"venue"
},
  "geometry": {"coordinates":[-4.0800800323,52.1130905151],"type":"Point"}
}