{
  "type": "Feature",
  "properties": {
    "addr:full":"Smeeth Road, Marshland St James Wisbech Cambridgeshire PE14 8JF",
    "addr:postcode":"pe14 8jf",
    "addr:street":"Smeeth Road",
    "iso:country":"GB",
    "sg:address":"Smeeth Road, Marshland St James",
    "sg:city":"Wisbech",
    "sg:classifiers":[
        {
            "category":"Food & Beverages",
            "subcategory":"Supermarket",
            "type":"Retail Goods"
        }
    ],
    "sg:phone":"+44 1945 430226",
    "sg:postcode":"PE14 8JF",
    "sg:province":"Cambridgeshire",
    "sg:tags":[
        "frozen"
    ],
    "wof:name":"Fenland Fruits Ltd.",
    "wof:placetype":"venue"
},
  "geometry": {"coordinates":[0.2389370054,52.6519317627],"type":"Point"}
}