{
  "type": "Feature",
  "properties": {
    "addr:full":"Unit F2 Maybird Centre, Birmingham Road Stratford-upon-avon Warwickshire CV37 0AZ",
    "addr:housenumber":"f2",
    "addr:postcode":"cv37 0az",
    "addr:street":"Centre Birmingham Road",
    "iso:country":"GB",
    "sg:address":"Unit F2 Maybird Centre, Birmingham Road",
    "sg:city":"Stratford-upon-avon",
    "sg:classifiers":[
        {
            "category":"Shopping",
            "subcategory":"Pets & Pet Supplies",
            "type":"Retail Goods"
        }
    ],
    "sg:phone":"+44 1789 261889",
    "sg:postcode":"CV37 0AZ",
    "sg:province":"Warwickshire",
    "sg:tags":[
        "food"
    ],
    "wof:name":"L F Jollyes Pet Foods",
    "wof:placetype":"venue"
},
  "geometry": {"coordinates":[-1.707269,52.194134],"type":"Point"}
}