{
  "type": "Feature",
  "properties": {
    "addr:full":"11 St Marks Ho, Phelp St Elephant And Castle Greater London SE17 2PP",
    "addr:housenumber":"11",
    "addr:postcode":"se17 2pp",
    "addr:street":"St Marks Ho Phelp St",
    "iso:country":"GB",
    "sg:address":"11 St Marks Ho, Phelp St",
    "sg:city":"Elephant And Castle",
    "sg:classifiers":[
        {
            "category":"Manufacturing",
            "subcategory":"Signs",
            "type":"Manufacturing & Wholesale Goods"
        }
    ],
    "sg:phone":"+44 20 7701 8128",
    "sg:postcode":"SE17 2PP",
    "sg:province":"Greater London",
    "sg:tags":[
        "writer"
    ],
    "wof:name":"Zenith Signs",
    "wof:placetype":"venue"
},
  "geometry": {"coordinates":[-0.090216,51.484577],"type":"Point"}
}