{
  "type": "Feature",
  "properties": {
    "addr:full":"2 Princes Avenue, Mayland Chelmsford Essex CM3 6BA",
    "addr:housenumber":"2",
    "addr:postcode":"cm3 6ba",
    "addr:street":"Princes Avenue",
    "iso:country":"GB",
    "sg:address":"2 Princes Avenue, Mayland",
    "sg:city":"Chelmsford",
    "sg:classifiers":[
        {
            "category":"Building & Trades",
            "subcategory":"Plumbing",
            "type":"Services"
        }
    ],
    "sg:postcode":"CM3 6BA",
    "sg:province":"Essex",
    "sg:tags":[
        "consultant",
        "heating"
    ],
    "wof:name":"Essex Flues",
    "wof:placetype":"venue"
},
  "geometry": {"coordinates":[0.761644,51.682598],"type":"Point"}
}