{
  "type": "Feature",
  "properties": {
    "addr:full":"41 Oakhill Road Sheffield South Yorkshire S7 1SJ",
    "addr:housenumber":"41",
    "addr:postcode":"s7 1sj",
    "addr:street":"Oakhill Road",
    "iso:country":"GB",
    "sg:address":"41 Oakhill Road",
    "sg:city":"Sheffield",
    "sg:classifiers":[
        {
            "category":"Education",
            "subcategory":"School",
            "type":"Public Place"
        }
    ],
    "sg:postcode":"S7 1SJ",
    "sg:province":"South Yorkshire",
    "sg:tags":[
        "local",
        "authority"
    ],
    "wof:name":"Schools And Homes Energy Education Project",
    "wof:placetype":"venue"
},
  "geometry": {"coordinates":[-1.4911049604,53.3568840027],"type":"Point"}
}