{
  "type": "Feature",
  "properties": {
    "addr:full":"36 Dorian Road Hornchurch Essex RM12 4AL",
    "addr:housenumber":"36",
    "addr:postcode":"rm12 4al",
    "addr:street":"Dorian Road",
    "iso:country":"GB",
    "sg:address":"36 Dorian Road",
    "sg:city":"Hornchurch",
    "sg:classifiers":[
        {
            "category":"Home & Garden",
            "subcategory":"Household Appliances",
            "type":"Retail Goods"
        }
    ],
    "sg:postcode":"RM12 4AL",
    "sg:province":"Essex",
    "sg:tags":[
        "electrical"
    ],
    "wof:name":"Advance Domestics",
    "wof:placetype":"venue"
},
  "geometry": {"coordinates":[0.1973949969,51.5617370605],"type":"Point"}
}