{
  "type": "Feature",
  "properties": {
    "iso:country":"GB",
    "sg:address":"United Reform Church, High Street",
    "sg:city":"Hampton",
    "sg:classifiers":[
        {
            "category":"Farming",
            "subcategory":"Nursery",
            "type":"Manufacturing & Wholesale Goods"
        },
        {
            "category":"Education",
            "subcategory":"Preschool",
            "type":"Public Place"
        }
    ],
    "sg:phone":"+44 20 8941 3447",
    "sg:postcode":"TW12 1NB",
    "sg:province":"Greater London",
    "sg:tags":[
        "playgroups",
        "pre-school",
        "creche"
    ],
    "wof:name":"The Ivytree Nursery Group",
    "wof:placetype":"venue"
},
  "geometry": {"coordinates":[-0.3623139858,51.4307098389],"type":"Point"}
}