{
  "type": "Feature",
  "properties": {
    "iso:country":"GB",
    "sg:address":"Unit 16 Abbey Court, Wallingford Road, Corporation Road",
    "sg:city":"Leicester",
    "sg:classifiers":[
        {
            "category":"Professional",
            "subcategory":"Engineering",
            "type":"Services"
        }
    ],
    "sg:phone":"+44 116 261 1220",
    "sg:postcode":"LE4 5PW",
    "sg:province":"Leicestershire",
    "sg:tags":[
        "engineer"
    ],
    "wof:name":"T I S Tooling Ltd.",
    "wof:placetype":"venue"
},
  "geometry": {"coordinates":[-1.131544,52.655251],"type":"Point"}
}