{
  "type": "Feature",
  "properties": {
    "iso:country":"GB",
    "sg:address":"27 Easby Road, Middleton",
    "sg:city":"Manchester",
    "sg:classifiers":[
        {
            "category":"Shopping",
            "subcategory":"Party Supplies",
            "type":"Retail Goods"
        },
        {
            "category":"Arts & Performance",
            "subcategory":"Music",
            "type":"Entertainment"
        }
    ],
    "sg:phone":"+44 161 345 0227",
    "sg:postcode":"M24 6FT",
    "sg:province":"Greater Manchester",
    "sg:tags":[
        "mobile",
        "operator",
        "disco"
    ],
    "wof:name":"Dial-A-Dj",
    "wof:placetype":"venue"
},
  "geometry": {"coordinates":[-2.199499,53.561516],"type":"Point"}
}