{
  "type": "Feature",
  "properties": {
    "iso:country":"GB",
    "sg:address":"Alexandra Road",
    "sg:city":"Lowestoft",
    "sg:classifiers":[
        {
            "category":"Health Services",
            "subcategory":"Doctor",
            "type":"Services"
        },
        {
            "category":"Health Services",
            "subcategory":"Clinic",
            "type":"Services"
        }
    ],
    "sg:phone":"+44 1502 574524",
    "sg:postcode":"NR32 1PL",
    "sg:province":"Suffolk",
    "sg:tags":[
        "nh",
        "practitioners"
    ],
    "wof:name":"The Surgery",
    "wof:placetype":"venue"
},
  "geometry": {"coordinates":[1.752783,52.481068],"type":"Point"}
}