{
  "type": "Feature",
  "properties": {
    "addr:full":"Parsonage Farm, Berners Roding Ongar Essex CM5 0SZ",
    "addr:postcode":"cm5 0sz",
    "addr:street":"Berners;Ongar",
    "iso:country":"GB",
    "sg:address":"Parsonage Farm, Berners Roding",
    "sg:city":"Ongar",
    "sg:classifiers":[
        {
            "category":"Insurance",
            "subcategory":"Insurance Agent",
            "type":"Services"
        }
    ],
    "sg:phone":"+44 1245 231014",
    "sg:postcode":"CM5 0SZ",
    "sg:province":"Essex",
    "wof:name":"B J Stratton Associates",
    "wof:placetype":"venue"
},
  "geometry": {"coordinates":[0.31955,51.764977],"type":"Point"}
}