{
  "type": "Feature",
  "properties": {
    "addr:full":"195a Drumry Road East, Drumchapel Glasgow Glasgow City G15 8NS",
    "addr:housenumber":"195a",
    "addr:postcode":"g15 8ns",
    "addr:street":"Drumry Road East",
    "iso:country":"GB",
    "sg:address":"195a Drumry Road East, Drumchapel",
    "sg:city":"Glasgow",
    "sg:classifiers":[
        {
            "category":"Community Center",
            "type":"Public Place"
        }
    ],
    "sg:phone":"+44 141 944 7276",
    "sg:postcode":"G15 8NS",
    "sg:province":"Glasgow City",
    "sg:tags":[
        "recreation",
        "leisure",
        "centre"
    ],
    "wof:name":"Drumchapel Sports Centre",
    "wof:placetype":"venue"
},
  "geometry": {"coordinates":[-4.376928,55.908497],"type":"Point"}
}