{
  "type": "Feature",
  "properties": {
    "iso:country":"GB",
    "sg:address":"23 Knoll Avenue, Uplands",
    "sg:city":"Swansea",
    "sg:classifiers":[
        {
            "category":"Professional",
            "subcategory":"Art Services",
            "type":"Services"
        }
    ],
    "sg:phone":"+44 1792 298386",
    "sg:postcode":"SA2 0JE",
    "sg:province":"Swansea",
    "sg:tags":[
        "graphic",
        "designer"
    ],
    "wof:name":"Llew Thomas Design",
    "wof:placetype":"venue"
},
  "geometry": {"coordinates":[-3.973012,51.616619],"type":"Point"}
}