{
  "type": "Feature",
  "properties": {
    "addr:full":"Metnor Ho, Mylord Cres Newcastle Upon Tyne Tyne and Wear NE12 0YD",
    "addr:postcode":"ne12 0yd",
    "addr:street":"Mylord Cres",
    "iso:country":"GB",
    "sg:address":"Metnor Ho, Mylord Cres",
    "sg:city":"Newcastle Upon Tyne",
    "sg:classifiers":[
        {
            "category":"Professional",
            "subcategory":"Engineering",
            "type":"Services"
        }
    ],
    "sg:phone":"+44 191 268 4000",
    "sg:postcode":"NE12 0YD",
    "sg:province":"Tyne and Wear",
    "wof:name":"Metnor Tyne Tees Ltd",
    "wof:placetype":"venue"
},
  "geometry": {"coordinates":[-1.5819749832,55.04088974],"type":"Point"}
}