{
  "type": "Feature",
  "properties": {
    "addr:full":"P.o Box 54 New House Lodge Perth Perth and Kinross PH1 1QF",
    "addr:housenumber":"54",
    "addr:postcode":"ph1 1qf",
    "addr:street":"P.O Box",
    "iso:country":"GB",
    "sg:address":"P.o Box 54 New House Lodge",
    "sg:city":"Perth",
    "sg:classifiers":[
        {
            "category":"Professional",
            "subcategory":"Management & Consulting",
            "type":"Services"
        }
    ],
    "sg:phone":"+44 1738 441302",
    "sg:postcode":"PH1 1QF",
    "sg:province":"Perth and Kinross",
    "sg:tags":[
        "consultant",
        "business"
    ],
    "wof:name":"J.J.I Bakery Consultancy Services",
    "wof:placetype":"venue"
},
  "geometry": {"coordinates":[-3.4909799099,56.402759552],"type":"Point"}
}