{
  "type": "Feature",
  "properties": {
    "iso:country":"GB",
    "sg:address":"38-40 Market Place",
    "sg:city":"Dewsbury",
    "sg:classifiers":[
        {
            "category":"Shopping",
            "subcategory":"Discount & Variety Stores",
            "type":"Retail Goods"
        }
    ],
    "sg:phone":"+44 1924 461130",
    "sg:postcode":"WF13 1DW",
    "sg:province":"West Yorkshire",
    "sg:tags":[
        "centre"
    ],
    "wof:name":"Quality Save",
    "wof:placetype":"venue"
},
  "geometry": {"coordinates":[-1.628452,53.691692],"type":"Point"}
}