{
  "type": "Feature",
  "properties": {
    "iso:country":"GB",
    "sg:address":"25 Lyneham Road",
    "sg:city":"Luton",
    "sg:classifiers":[
        {
            "category":"Retail",
            "subcategory":"Laundry & Dry Cleaning",
            "type":"Services"
        },
        {
            "category":"Retail",
            "subcategory":"Repair Shop",
            "type":"Services"
        }
    ],
    "sg:phone":"+44 1582 412414",
    "sg:postcode":"LU2 9JS",
    "sg:province":"Bedfordshire",
    "sg:tags":[
        "clothing",
        "alteration"
    ],
    "wof:name":"Maria's Cut & Sew",
    "wof:placetype":"venue"
},
  "geometry": {"coordinates":[-0.382916,51.887096],"type":"Point"}
}