{
  "type": "Feature",
  "properties": {
    "iso:country":"GB",
    "sg:address":"56 Rydal Road",
    "sg:city":"Lancaster",
    "sg:classifiers":[
        {
            "category":"Health Services",
            "subcategory":"Nursing And Care Facility",
            "type":"Services"
        },
        {
            "category":"Social Services",
            "subcategory":"Retirement Home",
            "type":"Services"
        }
    ],
    "sg:postcode":"LA1 3HA",
    "sg:province":"Lancashire",
    "sg:tags":[
        "residential"
    ],
    "wof:name":"RYDAL VILLA CARE CENTRE",
    "wof:placetype":"venue"
},
  "geometry": {"coordinates":[-2.788296,54.048737],"type":"Point"}
}