{
  "type": "Feature",
  "properties": {
    "iso:country":"GB",
    "sg:address":"74-76 Duke Street, Mayfair",
    "sg:city":"London",
    "sg:classifiers":[
        {
            "category":"Restaurant",
            "type":"Food & Drink"
        }
    ],
    "sg:phone":"+44 20 7629 6097",
    "sg:postcode":"W1M 5DS",
    "sg:province":"Greater London",
    "sg:tags":[
        "italian"
    ],
    "wof:name":"Spaghetti House Restaurants Ltd.",
    "wof:placetype":"venue"
},
  "geometry": {"coordinates":[-0.15121,51.513474],"type":"Point"}
}