{
  "type": "Feature",
  "properties": {
    "iso:country":"GB",
    "sg:address":"74 Avenue Road",
    "sg:city":"Torquay",
    "sg:classifiers":[
        {
            "category":"Professional",
            "subcategory":"Management & Consulting",
            "type":"Services"
        }
    ],
    "sg:phone":"+44 1803 294185",
    "sg:postcode":"TQ2 5LF",
    "sg:province":"Devon",
    "sg:tags":[
        "consultant",
        "specialist"
    ],
    "wof:name":"Nirvana",
    "wof:placetype":"venue"
},
  "geometry": {"coordinates":[-3.544213,50.468258],"type":"Point"}
}