{
  "type": "Feature",
  "properties": {
    "addr:full":"Bridge Street, New Byth Turriff Aberdeenshire AB53 5XB",
    "addr:postcode":"ab53 5xb",
    "addr:street":"Bridge Street",
    "iso:country":"GB",
    "sg:address":"Bridge Street, New Byth",
    "sg:city":"Turriff",
    "sg:classifiers":[
        {
            "category":"Government",
            "subcategory":"Post Office",
            "type":"Public Place"
        }
    ],
    "sg:phone":"+44 1888 544214",
    "sg:postcode":"AB53 5XB",
    "sg:province":"Aberdeenshire",
    "wof:name":"New Byth Post Office",
    "wof:placetype":"venue"
},
  "geometry": {"coordinates":[-2.2982389927,57.5734786987],"type":"Point"}
}