{
  "type": "Feature",
  "properties": {
    "addr:full":"199 Bishopsgate London Greater London EC2M 3TY",
    "addr:housenumber":"199",
    "addr:postcode":"ec2m 3ty",
    "addr:street":"Bishopsgate",
    "iso:country":"GB",
    "sg:address":"199 Bishopsgate",
    "sg:city":"London",
    "sg:classifiers":[
        {
            "category":"Professional",
            "subcategory":"Lawyer & Legal Services",
            "type":"Services"
        }
    ],
    "sg:postcode":"EC2M 3TY",
    "sg:province":"Greater London",
    "sg:tags":[
        "solicitor"
    ],
    "wof:name":"Langley & Co",
    "wof:placetype":"venue"
},
  "geometry": {"coordinates":[-0.080959,51.516972],"type":"Point"}
}