{
  "type": "Feature",
  "properties": {
    "addr:full":"The Heads Keswick Cumbria CA12 5ER",
    "addr:postcode":"ca12 5er",
    "iso:country":"GB",
    "sg:address":"The Heads",
    "sg:city":"Keswick",
    "sg:classifiers":[
        {
            "category":"Travel",
            "subcategory":"Hotels & Motels",
            "type":"Entertainment"
        }
    ],
    "sg:phone":"+44 17687 72208",
    "sg:postcode":"CA12 5ER",
    "sg:province":"Cumbria",
    "sg:website":"http://www.crowpark.co.uk",
    "wof:name":"Crow Park Hotel",
    "wof:placetype":"venue"
},
  "geometry": {"coordinates":[-3.138767,54.59935],"type":"Point"}
}