{
  "type": "Feature",
  "properties": {
    "iso:country":"GB",
    "sg:address":"Newport Industrial Estate",
    "sg:city":"Launceston",
    "sg:classifiers":[
        {
            "category":"Home & Garden",
            "subcategory":"Home Furnishings",
            "type":"Retail Goods"
        }
    ],
    "sg:phone":"+44 1566 777500",
    "sg:postcode":"PL15 8EX",
    "sg:province":"Cornwall",
    "sg:tags":[
        "blind",
        "curtain",
        "fitting"
    ],
    "wof:name":"Touch of Class",
    "wof:placetype":"venue"
},
  "geometry": {"coordinates":[-4.365059,50.641071],"type":"Point"}
}