{
  "type": "Feature",
  "properties": {
    "addr:full":"278 Foxhall Road Ipswich Suffolk IP3 8HT",
    "addr:housenumber":"278",
    "addr:postcode":"ip3 8ht",
    "addr:street":"Foxhall Road",
    "iso:country":"GB",
    "sg:address":"278 Foxhall Road",
    "sg:city":"Ipswich",
    "sg:classifiers":[
        {
            "category":"Real Estate",
            "subcategory":"Developer",
            "type":"Services"
        }
    ],
    "sg:postcode":"IP3 8HT",
    "sg:province":"Suffolk",
    "sg:tags":[
        "property"
    ],
    "wof:name":"K W T Bean Properties",
    "wof:placetype":"venue"
},
  "geometry": {"coordinates":[1.183023,52.052258],"type":"Point"}
}