{
  "type": "Feature",
  "properties": {
    "addr:full":"Plot 1 St Markas Church, Ystrad Terrace Pentre Rhondda, Cynon, Taff CF41 7UA",
    "addr:housenumber":"plot 1",
    "addr:postcode":"cf41 7ua",
    "addr:street":"St;Ystrad Terrace Pentre;Cynon Taff",
    "iso:country":"GB",
    "sg:address":"Plot 1 St Markas Church, Ystrad Terrace",
    "sg:city":"Pentre",
    "sg:classifiers":[
        {
            "category":"Bus Charters",
            "type":"Transportation"
        },
        {
            "category":"Bus Stop",
            "subcategory":"None",
            "type":"Transportation"
        }
    ],
    "sg:phone":"+44 1443 430125",
    "sg:postcode":"CF41 7UA",
    "sg:province":"Rhondda, Cynon, Taff",
    "sg:tags":[
        "mini",
        "hire",
        "leasing",
        "min"
    ],
    "wof:name":"Roberts Taxis",
    "wof:placetype":"venue"
},
  "geometry": {"coordinates":[-3.492894,51.655327],"type":"Point"}
}