{
  "type": "Feature",
  "properties": {
    "addr:full":"109 The Business Village London Greater London SW18 4JQ",
    "addr:housenumber":"109",
    "addr:postcode":"sw18 4jq",
    "addr:street":"The Business Village",
    "iso:country":"GB",
    "sg:address":"109 The Business Village",
    "sg:city":"London",
    "sg:classifiers":[
        {
            "category":"Shopping",
            "subcategory":"Music",
            "type":"Retail Goods"
        }
    ],
    "sg:postcode":"SW18 4JQ",
    "sg:province":"Greater London",
    "sg:tags":[
        "record",
        "tape",
        "cd"
    ],
    "wof:name":"Chain Reaction",
    "wof:placetype":"venue"
},
  "geometry": {"coordinates":[-0.19831,51.45686],"type":"Point"}
}