{
  "type": "Feature",
  "properties": {
    "iso:country":"GB",
    "sg:address":"Unit 4 Cutters Clo",
    "sg:city":"Leicester",
    "sg:classifiers":[
        {
            "category":"Shopping",
            "subcategory":"Stationery & Office Supplies",
            "type":"Retail Goods"
        }
    ],
    "sg:phone":"+44 116 284 9292",
    "sg:postcode":"LE9 5FY",
    "sg:province":"Leicestershire",
    "sg:tags":[
        "merchant",
        "paper"
    ],
    "wof:name":"Wigston Paper & Board",
    "wof:placetype":"venue"
},
  "geometry": {"coordinates":[-1.209994,52.571091],"type":"Point"}
}