{
  "type": "Feature",
  "properties": {
    "addr:full":"33 Benedict Square, Werrington Peterborough Cambridgeshire PE4 6ZE",
    "addr:housenumber":"33",
    "addr:postcode":"pe4 6ze",
    "addr:street":"Benedict Square",
    "iso:country":"GB",
    "sg:address":"33 Benedict Square, Werrington",
    "sg:city":"Peterborough",
    "sg:classifiers":[
        {
            "category":"Retail",
            "subcategory":"Auto Repair",
            "type":"Services"
        }
    ],
    "sg:phone":"+44 1733 324252",
    "sg:postcode":"PE4 6ZE",
    "sg:province":"Cambridgeshire",
    "sg:tags":[
        "modification",
        "garage"
    ],
    "wof:name":"Skoda Specialist",
    "wof:placetype":"venue"
},
  "geometry": {"coordinates":[-0.2826069891,52.610370636],"type":"Point"}
}