{
  "type": "Feature",
  "properties": {
    "addr:full":"27 Barassie Street Troon South Ayrshire KA10 6LX",
    "addr:housenumber":"27",
    "addr:postcode":"ka10 6lx",
    "addr:street":"Barassie Street",
    "iso:country":"GB",
    "sg:address":"27 Barassie Street",
    "sg:city":"Troon",
    "sg:classifiers":[
        {
            "category":"Education",
            "subcategory":"School",
            "type":"Public Place"
        },
        {
            "category":"Government",
            "subcategory":"Office",
            "type":"Public Place"
        }
    ],
    "sg:phone":"+44 1292 312166",
    "sg:postcode":"KA10 6LX",
    "sg:province":"South Ayrshire",
    "sg:tags":[
        "local",
        "authority"
    ],
    "wof:name":"Troon Primary School",
    "wof:placetype":"venue"
},
  "geometry": {"coordinates":[-4.659819,55.54517],"type":"Point"}
}