{
  "type": "Feature",
  "properties": {
    "addr:full":"2291 Coventry Rd, Sheldon Birmingham West Midlands B26 3PD",
    "addr:housenumber":"2291",
    "addr:postcode":"b26 3pd",
    "addr:street":"Coventry Rd",
    "iso:country":"GB",
    "sg:address":"2291 Coventry Rd, Sheldon",
    "sg:city":"Birmingham",
    "sg:classifiers":[
        {
            "category":"Shopping",
            "subcategory":"Computers & Home Electronics",
            "type":"Retail Goods"
        }
    ],
    "sg:phone":"+44 121 722 2526",
    "sg:postcode":"B26 3PD",
    "sg:province":"West Midlands",
    "sg:tags":[
        "system",
        "automation"
    ],
    "wof:name":"ADAC",
    "wof:placetype":"venue"
},
  "geometry": {"coordinates":[-1.7789690495,52.4514884949],"type":"Point"}
}