{
  "type": "Feature",
  "properties": {
    "addr:full":"22 Swan Street Brechin Aberdeenshire DD9 6EH",
    "addr:housenumber":"22",
    "addr:postcode":"dd9 6eh",
    "addr:street":"Swan Street",
    "iso:country":"GB",
    "sg:address":"22 Swan Street",
    "sg:city":"Brechin",
    "sg:classifiers":[
        {
            "category":"Professional",
            "subcategory":"Accounting & Tax Preparation",
            "type":"Services"
        }
    ],
    "sg:phone":"+44 1356 623929",
    "sg:postcode":"DD9 6EH",
    "sg:province":"Aberdeenshire",
    "sg:tags":[
        "accountant"
    ],
    "wof:name":"R B Cessford",
    "wof:placetype":"venue"
},
  "geometry": {"coordinates":[-2.65945,56.732239],"type":"Point"}
}