{
  "type": "Feature",
  "properties": {
    "iso:country":"GB",
    "sg:address":"2 Compton Place Business Cntr, Surrey Avenue",
    "sg:city":"Camberley",
    "sg:classifiers":[
        {
            "category":"Professional",
            "subcategory":"Computer Services",
            "type":"Services"
        }
    ],
    "sg:phone":"+44 1276 675577",
    "sg:postcode":"GU15 3DX",
    "sg:province":"Berkshire",
    "sg:tags":[
        "system",
        "software"
    ],
    "wof:name":"C P & I Ltd.",
    "wof:placetype":"venue"
},
  "geometry": {"coordinates":[-0.73423,51.336216],"type":"Point"}
}