{
  "type": "Feature",
  "properties": {
    "addr:full":"49 South Clerk Street Edinburgh City of Edinburgh EH8 9PB",
    "addr:housenumber":"49",
    "addr:postcode":"eh8 9pb",
    "addr:street":"South Clerk Street",
    "iso:country":"GB",
    "sg:address":"49 South Clerk Street",
    "sg:city":"Edinburgh",
    "sg:classifiers":[
        {
            "category":"Fast Food",
            "type":"Food & Drink"
        }
    ],
    "sg:phone":"+44 131 667 4432",
    "sg:postcode":"EH8 9PB",
    "sg:province":"City of Edinburgh",
    "sg:tags":[
        "away",
        "take"
    ],
    "wof:name":"A Ghafoor",
    "wof:placetype":"venue"
},
  "geometry": {"coordinates":[-3.1806910038,55.9408111572],"type":"Point"}
}