{
  "type": "Feature",
  "properties": {
    "addr:full":"303-305 Charminster Road Bournemouth Dorset BH8 9QP",
    "addr:housenumber":"303-305",
    "addr:postcode":"bh8 9qp",
    "addr:street":"Charminster Road",
    "iso:country":"GB",
    "sg:address":"303-305 Charminster Road",
    "sg:city":"Bournemouth",
    "sg:classifiers":[
        {
            "category":"Deli",
            "type":"Food & Drink"
        }
    ],
    "sg:postcode":"BH8 9QP",
    "sg:province":"Dorset",
    "sg:tags":[
        "delicatessen"
    ],
    "wof:name":"The Charminster Deli",
    "wof:placetype":"venue"
},
  "geometry": {"coordinates":[-1.8629250526,50.7412261963],"type":"Point"}
}