{
  "type": "Feature",
  "properties": {
    "addr:full":"Church Farm, Bunton Lane, Marston Road Leicester Leicestershire LE9 3GX",
    "addr:postcode":"le9 3gx",
    "addr:street":"Bunton Lane Marston Road",
    "iso:country":"GB",
    "sg:address":"Church Farm, Bunton Lane, Marston Road",
    "sg:city":"Leicester",
    "sg:classifiers":[
        {
            "category":"Farming",
            "subcategory":"Farm",
            "type":"Manufacturing & Wholesale Goods"
        }
    ],
    "sg:phone":"+44 1455 282263",
    "sg:postcode":"LE9 3GX",
    "sg:province":"Leicestershire",
    "sg:tags":[
        "mixed",
        "crop"
    ],
    "wof:name":"J R & R C Holt",
    "wof:placetype":"venue"
},
  "geometry": {"coordinates":[-1.25225,52.560921],"type":"Point"}
}