{
  "type": "Feature",
  "properties": {
    "iso:country":"GB",
    "sg:address":"Brockton",
    "sg:city":"Much Wenlock",
    "sg:classifiers":[
        {
            "category":"Education",
            "subcategory":"School",
            "type":"Public Place"
        }
    ],
    "sg:phone":"+44 1746 785671",
    "sg:postcode":"TF13 6JR",
    "sg:province":"Shropshire",
    "sg:tags":[
        "local",
        "authority"
    ],
    "wof:name":"Brockton Ce Primary School",
    "wof:placetype":"venue"
},
  "geometry": {"coordinates":[-2.559925,52.594009],"type":"Point"}
}