{
  "type": "Feature",
  "properties": {
    "iso:country":"GB",
    "sg:address":"17 Park St",
    "sg:city":"York",
    "sg:classifiers":[
        {
            "category":"Professional",
            "type":"Services"
        }
    ],
    "sg:phone":"+44 1904 645185",
    "sg:postcode":"YO24 1BQ",
    "sg:province":"North Yorkshire",
    "sg:tags":[
        "shopfitters"
    ],
    "wof:name":"Steve Charlton Building & Joinery",
    "wof:placetype":"venue"
},
  "geometry": {"coordinates":[-1.092837,53.953094],"type":"Point"}
}