{
  "type": "Feature",
  "properties": {
    "addr:full":"3 Moulton Street Manchester Greater Manchester M8 8FQ",
    "addr:housenumber":"3",
    "addr:postcode":"m8 8fq",
    "addr:street":"Moulton Street",
    "iso:country":"GB",
    "sg:address":"3 Moulton Street",
    "sg:city":"Manchester",
    "sg:classifiers":[
        {
            "category":"Wholesale",
            "subcategory":"Non-durable Goods",
            "type":"Manufacturing & Wholesale Goods"
        }
    ],
    "sg:phone":"+44 161 834 0830",
    "sg:postcode":"M8 8FQ",
    "sg:province":"Greater Manchester",
    "sg:tags":[
        "carry",
        "cash"
    ],
    "wof:name":"Vicway Ltd.",
    "wof:placetype":"venue"
},
  "geometry": {"coordinates":[-2.2512450218,53.4941711426],"type":"Point"}
}