{
  "type": "Feature",
  "properties": {
    "addr:full":"Suffolk Road, South Norwood London Greater London SE25 6ES",
    "addr:postcode":"se25 6es",
    "addr:street":"Suffolk Road",
    "iso:country":"GB",
    "sg:address":"Suffolk Road, South Norwood",
    "sg:city":"London",
    "sg:classifiers":[
        {
            "category":"Organizations",
            "subcategory":"Non-profit Organization",
            "type":"Services"
        }
    ],
    "sg:phone":"+44 20 8771 7417",
    "sg:postcode":"SE25 6ES",
    "sg:province":"Greater London",
    "sg:tags":[
        "organisation",
        "voluntary",
        "charity"
    ],
    "wof:name":"Sukyo Mahikari",
    "wof:placetype":"venue"
},
  "geometry": {"coordinates":[-0.0759840012,51.3995094299],"type":"Point"}
}