{
  "type": "Feature",
  "properties": {
    "addr:full":"11 Gally Hill Rd, Church Crookham Fleet Dorset GU13 0LH",
    "addr:housenumber":"11",
    "addr:postcode":"gu13 0lh",
    "addr:street":"Gally Hill Rd",
    "iso:country":"GB",
    "sg:address":"11 Gally Hill Rd, Church Crookham",
    "sg:city":"Fleet",
    "sg:classifiers":[
        {
            "category":"Autos & Motor Vehicles",
            "subcategory":"Automobile Sales",
            "type":"Retail Goods"
        }
    ],
    "sg:phone":"+44 1252 810440",
    "sg:postcode":"GU13 0LH",
    "sg:province":"Dorset",
    "sg:tags":[
        "commercial"
    ],
    "wof:name":"COURT CAR SALES",
    "wof:placetype":"venue"
},
  "geometry": {"coordinates":[-0.8322899938,51.267829895],"type":"Point"}
}