{
  "type": "Feature",
  "properties": {
    "iso:country":"GB",
    "sg:address":"Unit 1b Chilbolton Down Farm",
    "sg:city":"Stockbridge",
    "sg:classifiers":[
        {
            "category":"Building & Trades",
            "subcategory":"Construction",
            "type":"Services"
        }
    ],
    "sg:phone":"+44 1264 811600",
    "sg:postcode":"SO20 6BU",
    "sg:province":"Hampshire",
    "sg:tags":[
        "contractor"
    ],
    "wof:name":"Sarum Hardwood Structures Ltd.",
    "wof:placetype":"venue"
},
  "geometry": {"coordinates":[-1.4876489639,51.1125984192],"type":"Point"}
}