{
  "type": "Feature",
  "properties": {
    "addr:full":"Balgownie Tech Cntr, Campus 3science & Technology Aberdeen Aberdeen City AB22 8GW",
    "addr:postcode":"ab22 8gw",
    "iso:country":"GB",
    "sg:address":"Balgownie Tech Cntr, Campus 3science & Technology",
    "sg:city":"Aberdeen",
    "sg:classifiers":[
        {
            "category":"Professional",
            "subcategory":"Research",
            "type":"Services"
        },
        {
            "category":"Professional",
            "subcategory":"Computer Services",
            "type":"Services"
        }
    ],
    "sg:phone":"+44 1224 357290",
    "sg:postcode":"AB22 8GW",
    "sg:province":"Aberdeen City",
    "sg:tags":[
        "information",
        "market"
    ],
    "wof:name":"Petrodata Ltd.",
    "wof:placetype":"venue"
},
  "geometry": {"coordinates":[-2.1173000336,57.1787605286],"type":"Point"}
}