{
  "type": "Feature",
  "properties": {
    "addr:full":"179 Inverkip Road Greenock Inverclyde PA16 9EU",
    "addr:housenumber":"179",
    "addr:postcode":"pa16 9eu",
    "addr:street":"Inverkip Road",
    "iso:country":"GB",
    "sg:address":"179 Inverkip Road",
    "sg:city":"Greenock",
    "sg:classifiers":[
        {
            "category":"Retail",
            "subcategory":"Auto Repair",
            "type":"Services"
        }
    ],
    "sg:phone":"+44 1475 724753",
    "sg:postcode":"PA16 9EU",
    "sg:province":"Inverclyde",
    "sg:tags":[
        "modification",
        "garage",
        "related"
    ],
    "wof:name":"John S Phillips (Garages) Ltd",
    "wof:placetype":"venue"
},
  "geometry": {"coordinates":[-4.792636,55.940178],"type":"Point"}
}