{
  "type": "Feature",
  "properties": {
    "addr:full":"6 High Street, Sedgley Dudley Staffordshire DY3 1RW",
    "addr:housenumber":"6",
    "addr:postcode":"dy3 1rw",
    "addr:street":"High Street",
    "iso:country":"GB",
    "sg:address":"6 High Street, Sedgley",
    "sg:city":"Dudley",
    "sg:classifiers":[
        {
            "category":"Building & Trades",
            "subcategory":"Plumbing",
            "type":"Services"
        }
    ],
    "sg:postcode":"DY3 1RW",
    "sg:province":"Staffordshire",
    "sg:tags":[
        "central",
        "heating"
    ],
    "wof:name":"The Gas Shop",
    "wof:placetype":"venue"
},
  "geometry": {"coordinates":[-2.1220750809,52.541595459],"type":"Point"}
}