{
  "type": "Feature",
  "properties": {
    "addr:full":"105 Dartford Road March Cambridgeshire PE15 8BQ",
    "addr:housenumber":"105",
    "addr:postcode":"pe15 8bq",
    "addr:street":"Dartford Road",
    "iso:country":"GB",
    "sg:address":"105 Dartford Road",
    "sg:city":"March",
    "sg:classifiers":[
        {
            "category":"Professional",
            "subcategory":"Business Services",
            "type":"Services"
        }
    ],
    "sg:phone":"+44 1354 653802",
    "sg:postcode":"PE15 8BQ",
    "sg:province":"Cambridgeshire",
    "sg:tags":[
        "shop",
        "cleaning"
    ],
    "wof:name":"Roy Richards",
    "wof:placetype":"venue"
},
  "geometry": {"coordinates":[0.080903,52.553104],"type":"Point"}
}