{
  "type": "Feature",
  "properties": {
    "addr:full":"9 Llandudno Rd, Rhos On Sea Colwyn Bay Conwy LL28 4TR",
    "addr:housenumber":"9",
    "addr:postcode":"ll28 4tr",
    "addr:street":"Llandudno Rd",
    "iso:country":"GB",
    "sg:address":"9 Llandudno Rd, Rhos On Sea",
    "sg:city":"Colwyn Bay",
    "sg:classifiers":[
        {
            "category":"Restaurant",
            "type":"Food & Drink"
        }
    ],
    "sg:phone":"+44 1492 540198",
    "sg:postcode":"LL28 4TR",
    "sg:province":"Conwy",
    "wof:name":"The Ship Hotel",
    "wof:placetype":"venue"
},
  "geometry": {"coordinates":[-3.7519569397,53.3086166382],"type":"Point"}
}