{
  "type": "Feature",
  "properties": {
    "addr:full":"36 Parliament Street Harrogate North Yorkshire HG1 2RL",
    "addr:housenumber":"36",
    "addr:postcode":"hg1 2rl",
    "addr:street":"Parliament Street",
    "iso:country":"GB",
    "sg:address":"36 Parliament Street",
    "sg:city":"Harrogate",
    "sg:classifiers":[
        {
            "category":"Personal",
            "subcategory":"Beauty Salon",
            "type":"Services"
        }
    ],
    "sg:phone":"+44 1423 504301",
    "sg:postcode":"HG1 2RL",
    "sg:province":"North Yorkshire",
    "sg:tags":[
        "lady",
        "hairdresser"
    ],
    "wof:name":"Peter Gotthard",
    "wof:placetype":"venue"
},
  "geometry": {"coordinates":[-1.5433670282,53.9941444397],"type":"Point"}
}