{
  "type": "Feature",
  "properties": {
    "addr:full":"78 Tennyson Av Grantham Lincolnshire NG31 9NH",
    "addr:housenumber":"78",
    "addr:postcode":"ng31 9nh",
    "addr:street":"Tennyson Av Grantham",
    "iso:country":"GB",
    "sg:address":"78 Tennyson Av",
    "sg:city":"Grantham",
    "sg:classifiers":[
        {
            "category":"Professional",
            "subcategory":"Advertising",
            "type":"Services"
        }
    ],
    "sg:phone":"+44 1476 591851",
    "sg:postcode":"NG31 9NH",
    "sg:province":"Lincolnshire",
    "sg:tags":[
        "agency"
    ],
    "wof:name":"Pixie Advertising Agency",
    "wof:placetype":"venue"
},
  "geometry": {"coordinates":[-0.613537,52.918308],"type":"Point"}
}