{
  "type": "Feature",
  "properties": {
    "iso:country":"GB",
    "sg:address":"255 Marston Road, Marston",
    "sg:city":"Oxford",
    "sg:classifiers":[
        {
            "category":"Utilities",
            "subcategory":"Water",
            "type":"Services"
        },
        {
            "category":"Military Area",
            "subcategory":"Air Force Base",
            "type":"Public Place"
        }
    ],
    "sg:phone":"+44 1865 721901",
    "sg:postcode":"OX3 0EN",
    "sg:province":"Oxfordshire",
    "sg:tags":[
        "treatment"
    ],
    "wof:name":"Oxford Water Care",
    "wof:placetype":"venue"
},
  "geometry": {"coordinates":[-1.235909,51.759865],"type":"Point"}
}