{
  "type": "Feature",
  "properties": {
    "addr:full":"41 New Street Thornhill Dumfries and Galloway DG3 5NJ",
    "addr:housenumber":"41",
    "addr:postcode":"dg3 5nj",
    "addr:street":"New Street",
    "iso:country":"GB",
    "sg:address":"41 New Street",
    "sg:city":"Thornhill",
    "sg:classifiers":[
        {
            "category":"Building & Trades",
            "subcategory":"Construction",
            "type":"Services"
        }
    ],
    "sg:phone":"+44 1848 330270",
    "sg:postcode":"DG3 5NJ",
    "sg:province":"Dumfries and Galloway",
    "sg:tags":[
        "joiner",
        "carpenter"
    ],
    "wof:name":"Mitchell & Edgar",
    "wof:placetype":"venue"
},
  "geometry": {"coordinates":[-3.766359,55.241035],"type":"Point"}
}