{
  "type": "Feature",
  "properties": {
    "iso:country":"GB",
    "sg:address":"25a Church Street, Frodsham",
    "sg:city":"Warrington",
    "sg:classifiers":[
        {
            "category":"Retail",
            "subcategory":"Laundry & Dry Cleaning",
            "type":"Services"
        }
    ],
    "sg:phone":"+44 1928 734200",
    "sg:postcode":"WA6 6PN",
    "sg:province":"Cheshire",
    "sg:tags":[
        "alteration"
    ],
    "wof:name":"Sterling Dry Cleaners",
    "wof:placetype":"venue"
},
  "geometry": {"coordinates":[-2.7239809036,53.2947158813],"type":"Point"}
}