{
  "type": "Feature",
  "properties": {
    "iso:country":"GB",
    "sg:address":"81 Town St, Pinxton",
    "sg:city":"Nottingham",
    "sg:classifiers":[
        {
            "category":"Manufacturing",
            "subcategory":"Petroleum Products",
            "type":"Manufacturing & Wholesale Goods"
        }
    ],
    "sg:phone":"+44 1773 863050",
    "sg:postcode":"NG16 6JN",
    "sg:province":"Derbyshire",
    "sg:tags":[
        "double",
        "glazing"
    ],
    "wof:name":"Select Windows",
    "wof:placetype":"venue"
},
  "geometry": {"coordinates":[-1.317955,53.095806],"type":"Point"}
}