{
  "type": "Feature",
  "properties": {
    "iso:country":"GB",
    "sg:address":"Container Way",
    "sg:city":"Greenock",
    "sg:classifiers":[
        {
            "category":"Organizations",
            "subcategory":"Membership Organization",
            "type":"Services"
        }
    ],
    "sg:phone":"+44 1475 721194",
    "sg:postcode":"PA15 1PX",
    "sg:province":"Inverclyde",
    "sg:tags":[
        "club"
    ],
    "wof:name":"Mecca Social Club",
    "wof:placetype":"venue"
},
  "geometry": {"coordinates":[-4.756839,55.949776],"type":"Point"}
}