{
  "type": "Feature",
  "properties": {
    "iso:country":"GB",
    "sg:address":"High Street, Great Gonerby",
    "sg:city":"Grantham",
    "sg:classifiers":[
        {
            "category":"Education",
            "subcategory":"School",
            "type":"Public Place"
        },
        {
            "category":"Government",
            "subcategory":"Office",
            "type":"Public Place"
        }
    ],
    "sg:phone":"+44 1476 565896",
    "sg:postcode":"NG31 8LB",
    "sg:province":"Lincolnshire",
    "sg:tags":[
        "local",
        "authority"
    ],
    "wof:name":"St. Sebastian's C of E Primary School",
    "wof:placetype":"venue"
},
  "geometry": {"coordinates":[-0.666949,52.936539],"type":"Point"}
}