{
  "type": "Feature",
  "properties": {
    "iso:country":"GB",
    "sg:address":"Unit G & H, Markeaton Craft Village",
    "sg:city":"Derby",
    "sg:classifiers":[
        {
            "category":"Shopping",
            "subcategory":"Baby Store",
            "type":"Retail Goods"
        }
    ],
    "sg:phone":"+44 1332 207465",
    "sg:postcode":"DE22 3BG",
    "sg:province":"Derbyshire",
    "sg:tags":[
        "babywear",
        "childrens"
    ],
    "wof:name":"Village Co.",
    "wof:placetype":"venue"
},
  "geometry": {"coordinates":[-1.50544,52.93507],"type":"Point"}
}