{
  "type": "Feature",
  "properties": {
    "addr:full":"David Street, Bridgend Industrial Estate Bridgend Bridgend CF31 3SA",
    "addr:postcode":"cf31 3sa",
    "addr:street":"David Street;Industrial Estate",
    "iso:country":"GB",
    "sg:address":"David Street, Bridgend Industrial Estate",
    "sg:city":"Bridgend",
    "sg:classifiers":[
        {
            "category":"Wholesale",
            "subcategory":"Construction Materials",
            "type":"Manufacturing & Wholesale Goods"
        },
        {
            "category":"Building & Trades",
            "subcategory":"Construction",
            "type":"Services"
        }
    ],
    "sg:phone":"+44 1656 648444",
    "sg:postcode":"CF31 3SA",
    "sg:province":"Bridgend",
    "sg:tags":[
        "fork",
        "lift",
        "truck"
    ],
    "wof:name":"Eddison Lift Truck Services",
    "wof:placetype":"venue"
},
  "geometry": {"coordinates":[-3.5399138927,51.5031890869],"type":"Point"}
}