{
  "type": "Feature",
  "properties": {
    "addr:full":"Church Road, Seaforth Liverpool Merseyside L21 4LW",
    "addr:postcode":"l21 4lw",
    "addr:street":"Church Road",
    "iso:country":"GB",
    "sg:address":"Church Road, Seaforth",
    "sg:city":"Liverpool",
    "sg:classifiers":[
        {
            "category":"Farming",
            "subcategory":"Nursery",
            "type":"Manufacturing & Wholesale Goods"
        }
    ],
    "sg:phone":"+44 151 928 8557",
    "sg:postcode":"L21 4LW",
    "sg:province":"Merseyside",
    "sg:tags":[
        "creche"
    ],
    "wof:name":"Seaforth Nursery Centre",
    "wof:placetype":"venue"
},
  "geometry": {"coordinates":[-3.00928,53.463051],"type":"Point"}
}