{
  "type": "Feature",
  "properties": {
    "addr:full":"135 Green Lanes Epsom Surrey KT19 9TN",
    "addr:housenumber":"135",
    "addr:postcode":"kt19 9tn",
    "addr:street":"Green Lanes",
    "iso:country":"GB",
    "sg:address":"135 Green Lanes",
    "sg:city":"Epsom",
    "sg:classifiers":[
        {
            "category":"Retail",
            "subcategory":"Driving School",
            "type":"Services"
        }
    ],
    "sg:postcode":"KT19 9TN",
    "sg:province":"Surrey",
    "wof:name":"Colin School of Driving",
    "wof:placetype":"venue"
},
  "geometry": {"coordinates":[-0.25957,51.354248],"type":"Point"}
}