{
  "type": "Feature",
  "properties": {
    "addr:full":"Renny's Lane, Dragonville Industrial Estate, Gilesgate Durham Durham DH1 2RF",
    "addr:postcode":"dh1 2rf",
    "addr:street":"Renny'S Lane;Industrial Estate Gilesgate",
    "iso:country":"GB",
    "sg:address":"Renny's Lane, Dragonville Industrial Estate, Gilesgate",
    "sg:city":"Durham",
    "sg:classifiers":[
        {
            "category":"Home & Garden",
            "subcategory":"Building Materials",
            "type":"Retail Goods"
        }
    ],
    "sg:phone":"+44 191 386 9502",
    "sg:postcode":"DH1 2RF",
    "sg:province":"Durham",
    "sg:tags":[
        "ironwork",
        "diy",
        "wrought"
    ],
    "wof:name":"Armthorpe Fabrication",
    "wof:placetype":"venue"
},
  "geometry": {"coordinates":[-1.53894,54.7789],"type":"Point"}
}