{
  "type": "Feature",
  "properties": {
    "addr:full":"County Chambers, 6-8 Chestergate Macclesfield Cheshire SK11 6BA",
    "addr:housenumber":"6-8",
    "addr:postcode":"sk11 6ba",
    "addr:street":"County Chambers;Chestergate Macclesfield",
    "iso:country":"GB",
    "sg:address":"County Chambers, 6-8 Chestergate",
    "sg:city":"Macclesfield",
    "sg:classifiers":[
        {
            "category":"Professional",
            "subcategory":"Lawyer & Legal Services",
            "type":"Services"
        }
    ],
    "sg:phone":"+44 1625 431311",
    "sg:postcode":"SK11 6BA",
    "sg:province":"Cheshire",
    "sg:tags":[
        "solicitor"
    ],
    "wof:name":"Daniels Solicitors",
    "wof:placetype":"venue"
},
  "geometry": {"coordinates":[-2.1267249584,53.2570228577],"type":"Point"}
}