{
  "type": "Feature",
  "properties": {
    "iso:country":"GB",
    "sg:address":"Halifax Road, Hurstead",
    "sg:city":"Rochdale",
    "sg:classifiers":[
        {
            "category":"Government",
            "subcategory":"Post Office",
            "type":"Public Place"
        }
    ],
    "sg:phone":"+44 1706 378162",
    "sg:postcode":"OL12 9PY",
    "sg:province":"Lancashire",
    "wof:name":"Hursted Sub Post Office",
    "wof:placetype":"venue"
},
  "geometry": {"coordinates":[-2.1245720387,53.6383018494],"type":"Point"}
}