{
  "type": "Feature",
  "properties": {
    "iso:country":"GB",
    "sg:address":"Norwood Rd",
    "sg:city":"March",
    "sg:classifiers":[
        {
            "category":"Professional",
            "type":"Services"
        },
        {
            "category":"Government",
            "subcategory":"Customs House",
            "type":"Public Place"
        }
    ],
    "sg:postcode":"PE15 8QD",
    "sg:province":"Cambridgeshire",
    "sg:tags":[
        "clearance",
        "auctioneer"
    ],
    "wof:name":"Cannon,Andrew,",
    "wof:placetype":"venue"
},
  "geometry": {"coordinates":[0.09155,52.561985],"type":"Point"}
}