{
  "type": "Feature",
  "properties": {
    "addr:full":"5 Monument View, Sycamore Avenue, Polesworth Tamworth Staffordshire B78 1NF",
    "addr:housenumber":"5",
    "addr:postcode":"b78 1nf",
    "addr:street":"Monument View Sycamore Avenue",
    "iso:country":"GB",
    "sg:address":"5 Monument View, Sycamore Avenue, Polesworth",
    "sg:city":"Tamworth",
    "sg:classifiers":[
        {
            "category":"Shopping",
            "subcategory":"Department Store",
            "type":"Retail Goods"
        },
        {
            "category":"Food & Beverages",
            "subcategory":"Supermarket",
            "type":"Retail Goods"
        },
        {
            "category":"Food & Beverages",
            "subcategory":"Groceries & Convenience Stores",
            "type":"Retail Goods"
        }
    ],
    "sg:phone":"+44 1827 894735",
    "sg:postcode":"B78 1NF",
    "sg:province":"Staffordshire",
    "wof:name":"Monument Foodstore",
    "wof:placetype":"venue"
},
  "geometry": {"coordinates":[-1.6114599705,52.6127700806],"type":"Point"}
}