{
  "type": "Feature",
  "properties": {
    "addr:full":"Dudhope Street Dundee Dundee City DD1 1JT",
    "addr:postcode":"dd1 1jt",
    "addr:street":"Dudhope Street",
    "iso:country":"GB",
    "sg:address":"Dudhope Street",
    "sg:city":"Dundee",
    "sg:classifiers":[
        {
            "category":"Place Of Worship",
            "type":"Public Place"
        },
        {
            "category":"Organizations",
            "subcategory":"Non-profit Organization",
            "type":"Services"
        }
    ],
    "sg:postcode":"DD1 1JT",
    "sg:province":"Dundee City",
    "sg:tags":[
        "charitable",
        "organisation",
        "charity"
    ],
    "wof:name":"Unitarian Church",
    "wof:placetype":"venue"
},
  "geometry": {"coordinates":[-2.9729440212,56.4650115967],"type":"Point"}
}