{
  "type": "Feature",
  "properties": {
    "iso:country":"GB",
    "sg:address":"Great North Road, Middleton Tyas",
    "sg:city":"Richmond",
    "sg:classifiers":[
        {
            "category":"Health Services",
            "subcategory":"Nursing And Care Facility",
            "type":"Services"
        }
    ],
    "sg:phone":"+44 1748 826266",
    "sg:postcode":"DL10 6NX",
    "sg:province":"North Yorkshire",
    "sg:tags":[
        "home"
    ],
    "wof:name":"The Morris Grange Private Nursing Home",
    "wof:placetype":"venue"
},
  "geometry": {"coordinates":[-1.650018,54.447056],"type":"Point"}
}