{
  "type": "Feature",
  "properties": {
    "addr:full":"The Shareware Village, Station Road Colyton Devon EX24 6HA",
    "addr:postcode":"ex24 6ha",
    "addr:street":"Station Road",
    "iso:country":"GB",
    "sg:address":"The Shareware Village, Station Road",
    "sg:city":"Colyton",
    "sg:classifiers":[
        {
            "category":"Professional",
            "subcategory":"Computer Services",
            "type":"Services"
        }
    ],
    "sg:phone":"+44 1297 552222",
    "sg:postcode":"EX24 6HA",
    "sg:province":"Devon",
    "sg:tags":[
        "system",
        "software"
    ],
    "wof:name":"Atlantic Coast Plc",
    "wof:placetype":"venue"
},
  "geometry": {"coordinates":[-3.0702440739,50.7403373718],"type":"Point"}
}