{
  "type": "Feature",
  "properties": {
    "iso:country":"GB",
    "sg:address":"86 High Street",
    "sg:city":"Ayr",
    "sg:classifiers":[
        {
            "category":"Shopping",
            "subcategory":"Department Store",
            "type":"Retail Goods"
        }
    ],
    "sg:phone":"+44 1292 281669",
    "sg:postcode":"KA7 1PQ",
    "sg:province":"South Ayrshire",
    "wof:name":"Camerons Cards & Gifts",
    "wof:placetype":"venue"
},
  "geometry": {"coordinates":[-4.630151,55.463589],"type":"Point"}
}