{
  "type": "Feature",
  "properties": {
    "addr:full":"26 St Lukes Drive, Orrell Wigan Lancashire WN5 7AU",
    "addr:housenumber":"26",
    "addr:postcode":"wn5 7au",
    "addr:street":"St Lukes Drive",
    "iso:country":"GB",
    "sg:address":"26 St Lukes Drive, Orrell",
    "sg:city":"Wigan",
    "sg:classifiers":[
        {
            "category":"Building & Trades",
            "subcategory":"Construction",
            "type":"Services"
        }
    ],
    "sg:postcode":"WN5 7AU",
    "sg:province":"Lancashire",
    "sg:tags":[
        "joiner",
        "carpenter"
    ],
    "wof:name":"Alan Winstanley",
    "wof:placetype":"venue"
},
  "geometry": {"coordinates":[-2.711079,53.528484],"type":"Point"}
}