{
  "type": "Feature",
  "properties": {
    "iso:country":"GB",
    "sg:address":"350 Bradford Road",
    "sg:city":"Birmingham",
    "sg:classifiers":[
        {
            "category":"Health Services",
            "subcategory":"Optometrist",
            "type":"Services"
        }
    ],
    "sg:phone":"+44 121 747 2115",
    "sg:postcode":"B36 9AD",
    "sg:province":"West Midlands",
    "sg:tags":[
        "optician"
    ],
    "wof:name":"J Ellis Opticians Ltd.",
    "wof:placetype":"venue"
},
  "geometry": {"coordinates":[-1.772869,52.502151],"type":"Point"}
}