{
  "type": "Feature",
  "properties": {
    "iso:country":"GB",
    "sg:address":"13-15 West Street, Old Market",
    "sg:city":"Bristol",
    "sg:classifiers":[
        {
            "category":"Wholesale",
            "subcategory":"Furniture",
            "type":"Manufacturing & Wholesale Goods"
        }
    ],
    "sg:phone":"+44 117 955 7031",
    "sg:postcode":"BS2 0DF",
    "sg:province":"City of Bristol",
    "sg:tags":[
        "shop",
        "fitting"
    ],
    "wof:name":"Stayfast Ltd.",
    "wof:placetype":"venue"
},
  "geometry": {"coordinates":[-2.579497,51.456741],"type":"Point"}
}