{
  "type": "Feature",
  "properties": {
    "addr:full":"Ivybridge Road, Ermington Ivybridge Devon PL21 9NT",
    "addr:postcode":"pl21 9nt",
    "addr:street":"Ivybridge Road",
    "iso:country":"GB",
    "sg:address":"Ivybridge Road, Ermington",
    "sg:city":"Ivybridge",
    "sg:classifiers":[
        {
            "category":"Professional",
            "subcategory":"Employment Agencies",
            "type":"Services"
        }
    ],
    "sg:phone":"+44 1548 830410",
    "sg:postcode":"PL21 9NT",
    "sg:province":"Devon",
    "sg:tags":[
        "agricultural",
        "advice"
    ],
    "wof:name":"Erme Valley Farmers",
    "wof:placetype":"venue"
},
  "geometry": {"coordinates":[-3.929039,50.387264],"type":"Point"}
}