{
  "type": "Feature",
  "properties": {
    "iso:country":"GB",
    "sg:address":"Alpha Unit 3 Orchard Indust Est",
    "sg:city":"Cheltenham",
    "sg:classifiers":[
        {
            "category":"Shopping",
            "subcategory":"Pets & Pet Supplies",
            "type":"Retail Goods"
        }
    ],
    "sg:phone":"+44 1242 620080",
    "sg:postcode":"GL54 5EB",
    "sg:province":"Gloucestershire",
    "wof:name":"Pedigree Pens",
    "wof:placetype":"venue"
},
  "geometry": {"coordinates":[-1.9715,51.955681],"type":"Point"}
}