{
  "type": "Feature",
  "properties": {
    "iso:country":"GB",
    "sg:address":"4 Top Common, Warfield",
    "sg:city":"Bracknell",
    "sg:classifiers":[
        {
            "category":"Professional",
            "subcategory":"Detective & Security Services",
            "type":"Services"
        }
    ],
    "sg:postcode":"RG42 3SJ",
    "sg:province":"Berkshire",
    "wof:name":"G & G Alarms Ltd.",
    "wof:placetype":"venue"
},
  "geometry": {"coordinates":[-0.738468,51.425995],"type":"Point"}
}