{
  "type": "Feature",
  "properties": {
    "addr:full":"8 Swanside Avenue Liverpool Merseyside L14 7NR",
    "addr:housenumber":"8",
    "addr:postcode":"l14 7nr",
    "addr:street":"Swanside Avenue",
    "iso:country":"GB",
    "sg:address":"8 Swanside Avenue",
    "sg:city":"Liverpool",
    "sg:classifiers":[
        {
            "category":"Bus Charters",
            "type":"Transportation"
        }
    ],
    "sg:phone":"+44 151 289 3481",
    "sg:postcode":"L14 7NR",
    "sg:province":"Merseyside",
    "sg:tags":[
        "mini",
        "hire",
        "leasing"
    ],
    "wof:name":"Moores Chauffeur Services",
    "wof:placetype":"venue"
},
  "geometry": {"coordinates":[-2.882141,53.415363],"type":"Point"}
}