{
  "type": "Feature",
  "properties": {
    "addr:full":"20-22 Forest Road Loughton Essex IG10 1DX",
    "addr:housenumber":"20-22",
    "addr:postcode":"ig10 1dx",
    "addr:street":"Forest Road",
    "iso:country":"GB",
    "sg:address":"20-22 Forest Road",
    "sg:city":"Loughton",
    "sg:classifiers":[
        {
            "category":"Home & Garden",
            "subcategory":"Hardware",
            "type":"Retail Goods"
        }
    ],
    "sg:phone":"+44 20 8508 2637",
    "sg:postcode":"IG10 1DX",
    "sg:province":"Essex",
    "sg:tags":[
        "shop",
        "retailer",
        "diy"
    ],
    "wof:name":"The Tool Shop",
    "wof:placetype":"venue"
},
  "geometry": {"coordinates":[0.053514,51.646629],"type":"Point"}
}