{
  "type": "Feature",
  "properties": {
    "iso:country":"GB",
    "sg:address":"51 Main Street",
    "sg:city":"Pembroke",
    "sg:classifiers":[
        {
            "category":"Restaurant",
            "type":"Food & Drink"
        }
    ],
    "sg:phone":"+44 1646 682419",
    "sg:postcode":"SA71 4DA",
    "sg:province":"Pembrokeshire",
    "wof:name":"Brown's Restaurant",
    "wof:placetype":"venue"
},
  "geometry": {"coordinates":[-4.915627,51.675404],"type":"Point"}
}