{
  "type": "Feature",
  "properties": {
    "addr:full":"46 Hamilton Street Saltcoats North Ayrshire KA21 5DS",
    "addr:housenumber":"46",
    "addr:postcode":"ka21 5ds",
    "addr:street":"Hamilton Street",
    "iso:country":"GB",
    "sg:address":"46 Hamilton Street",
    "sg:city":"Saltcoats",
    "sg:classifiers":[
        {
            "category":"Cinema",
            "subcategory":"Movie Rental",
            "type":"Entertainment"
        }
    ],
    "sg:phone":"+44 1294 468163",
    "sg:postcode":"KA21 5DS",
    "sg:province":"North Ayrshire",
    "sg:tags":[
        "video",
        "library"
    ],
    "wof:name":"Global Video (Uk) Ltd.",
    "wof:placetype":"venue"
},
  "geometry": {"coordinates":[-4.7911200523,55.6347808838],"type":"Point"}
}