{
  "type": "Feature",
  "properties": {
    "addr:full":"Studio 2, 70 Ransom Rd, Mapperley Nottingham Nottinghamshire NG3 3LJ",
    "addr:housenumber":"70",
    "addr:postcode":"ng3 3lj",
    "addr:street":"Ransom Rd",
    "iso:country":"GB",
    "sg:address":"Studio 2, 70 Ransom Rd, Mapperley",
    "sg:city":"Nottingham",
    "sg:classifiers":[
        {
            "category":"Professional",
            "subcategory":"Art Services",
            "type":"Services"
        }
    ],
    "sg:phone":"+44 115 955 5110",
    "sg:postcode":"NG3 3LJ",
    "sg:province":"Nottinghamshire",
    "sg:tags":[
        "graphic",
        "designer"
    ],
    "wof:name":"Liquid Design",
    "wof:placetype":"venue"
},
  "geometry": {"coordinates":[-1.1311999559,52.9697113037],"type":"Point"}
}