{
  "type": "Feature",
  "properties": {
    "addr:full":"7 -15 Pink Lane Newcastle-upon-tyne Tyne and Wear NE1 5DW",
    "addr:housenumber":"-15",
    "addr:postcode":"ne1 5dw",
    "addr:street":"7;Pink Lane",
    "iso:country":"GB",
    "sg:address":"7 -15 Pink Lane",
    "sg:city":"Newcastle-upon-tyne",
    "sg:classifiers":[
        {
            "category":"Communications",
            "type":"Services"
        }
    ],
    "sg:postcode":"NE1 5DW",
    "sg:province":"Tyne and Wear",
    "sg:tags":[
        "audio-visual"
    ],
    "wof:name":"Oddfish Films",
    "wof:placetype":"venue"
},
  "geometry": {"coordinates":[-1.619017,54.969658],"type":"Point"}
}