{
  "type": "Feature",
  "properties": {
    "addr:full":"60 Woodgates Lane North Ferriby East Riding of Yorkshire HU14 3JY",
    "addr:housenumber":"60",
    "addr:postcode":"hu14 3jy",
    "addr:street":"Woodgates Lane",
    "iso:country":"GB",
    "sg:address":"60 Woodgates Lane",
    "sg:city":"North Ferriby",
    "sg:classifiers":[
        {
            "category":"Real Estate",
            "subcategory":"Real Estate Agent",
            "type":"Services"
        }
    ],
    "sg:postcode":"HU14 3JY",
    "sg:province":"East Riding of Yorkshire",
    "wof:name":"Ian Loncaster",
    "wof:placetype":"venue"
},
  "geometry": {"coordinates":[-0.506718,53.728138],"type":"Point"}
}