{
  "type": "Feature",
  "properties": {
    "iso:country":"GB",
    "sg:address":"75 Cemetery Rd",
    "sg:city":"Stourbridge",
    "sg:classifiers":[
        {
            "category":"Shopping",
            "subcategory":"Stationery & Office Supplies",
            "type":"Retail Goods"
        }
    ],
    "sg:phone":"+44 1384 422230",
    "sg:postcode":"DY9 8AD",
    "sg:province":"West Midlands",
    "sg:tags":[
        "box",
        "carton"
    ],
    "wof:name":"Ron Davies & Son",
    "wof:placetype":"venue"
},
  "geometry": {"coordinates":[-2.1177270412,52.4551963806],"type":"Point"}
}