{
  "type": "Feature",
  "properties": {
    "addr:full":"Daymans Farm, St Mawgan Newquay Cornwall TR8 4HF",
    "addr:postcode":"tr8 4hf",
    "addr:street":"St",
    "iso:country":"GB",
    "sg:address":"Daymans Farm, St Mawgan",
    "sg:city":"Newquay",
    "sg:classifiers":[
        {
            "category":"Farming",
            "subcategory":"Livestock Farm",
            "type":"Manufacturing & Wholesale Goods"
        }
    ],
    "sg:phone":"+44 1637 860341",
    "sg:postcode":"TR8 4HF",
    "sg:province":"Cornwall",
    "sg:tags":[
        "others"
    ],
    "wof:name":"June Dunstan",
    "wof:placetype":"venue"
},
  "geometry": {"coordinates":[-4.98526,50.468182],"type":"Point"}
}