{
  "type": "Feature",
  "properties": {
    "addr:full":"Units 5 & 6 Talisman House, 47 Bath St Walsall West Midlands WS1 3BX",
    "addr:housenumber":"units 5 & 6 talisman house 47",
    "addr:postcode":"ws1 3bx",
    "addr:street":"Bath St",
    "iso:country":"GB",
    "sg:address":"Units 5 & 6 Talisman House, 47 Bath St",
    "sg:city":"Walsall",
    "sg:classifiers":[
        {
            "category":"Education",
            "subcategory":"Music School",
            "type":"Public Place"
        }
    ],
    "sg:phone":"+44 1922 642123",
    "sg:postcode":"WS1 3BX",
    "sg:province":"West Midlands",
    "wof:name":"M.P.M Records",
    "wof:placetype":"venue"
},
  "geometry": {"coordinates":[-1.980574,52.578579],"type":"Point"}
}