{
  "type": "Feature",
  "properties": {
    "addr:full":"22-24 Market St Dalton In Furness Cumbria LA15 8AA",
    "addr:housenumber":"22-24",
    "addr:postcode":"la15 8aa",
    "addr:street":"Market St;Furness",
    "iso:country":"GB",
    "sg:address":"22-24 Market St",
    "sg:city":"Dalton In Furness",
    "sg:classifiers":[
        {
            "category":"Professional",
            "subcategory":"Management & Consulting",
            "type":"Services"
        }
    ],
    "sg:phone":"+44 1229 462837",
    "sg:postcode":"LA15 8AA",
    "sg:province":"Cumbria",
    "sg:tags":[
        "consultant",
        "investigation",
        "site"
    ],
    "wof:name":"Fabtex",
    "wof:placetype":"venue"
},
  "geometry": {"coordinates":[-3.1840400696,54.1558647156],"type":"Point"}
}