{
  "type": "Feature",
  "properties": {
    "iso:country":"GB",
    "sg:address":"1a Tamar Park, Cox Park",
    "sg:city":"Gunnislake",
    "sg:classifiers":[
        {
            "category":"Building & Trades",
            "subcategory":"Construction",
            "type":"Services"
        }
    ],
    "sg:phone":"+44 1822 832536",
    "sg:postcode":"PL18 9BD",
    "sg:province":"Cornwall",
    "sg:tags":[
        "builder"
    ],
    "wof:name":"Brian Cummings",
    "wof:placetype":"venue"
},
  "geometry": {"coordinates":[-4.2136640549,50.523891449],"type":"Point"}
}