{
  "type": "Feature",
  "properties": {
    "iso:country":"GB",
    "sg:address":"The Rookery, Heningby",
    "sg:city":"Horncastle",
    "sg:classifiers":[
        {
            "category":"Shopping",
            "subcategory":"Antiques",
            "type":"Retail Goods"
        }
    ],
    "sg:phone":"+44 1507 578490",
    "sg:postcode":"LN9 5QF",
    "sg:province":"Lincolnshire",
    "wof:name":"Ceramic Repair by Roger Carter",
    "wof:placetype":"venue"
},
  "geometry": {"coordinates":[-0.1147650033,53.2085227966],"type":"Point"}
}