{
  "type": "Feature",
  "properties": {
    "addr:full":"Enfield Road Enfield Greater London EN2 7HL",
    "addr:postcode":"en2 7hl",
    "addr:street":"Enfield Road",
    "iso:country":"GB",
    "sg:address":"Enfield Road",
    "sg:city":"Enfield",
    "sg:classifiers":[
        {
            "category":"Education",
            "subcategory":"Library",
            "type":"Public Place"
        },
        {
            "category":"Government",
            "subcategory":"Office",
            "type":"Public Place"
        }
    ],
    "sg:phone":"+44 20 8379 1711",
    "sg:postcode":"EN2 7HL",
    "sg:province":"Greater London",
    "sg:tags":[
        "book",
        "local"
    ],
    "wof:name":"Merryhills Library",
    "wof:placetype":"venue"
},
  "geometry": {"coordinates":[-0.1112489998,51.6545257568],"type":"Point"}
}