{
  "type": "Feature",
  "properties": {
    "addr:full":"78 Lake Road Portsmouth Hampshire PO1 4HF",
    "addr:housenumber":"78",
    "addr:postcode":"hampshire po1 4hf",
    "addr:street":"Lake Road",
    "iso:country":"GB",
    "sg:address":"78 Lake Road",
    "sg:city":"Portsmouth",
    "sg:classifiers":[
        {
            "category":"Building & Trades",
            "subcategory":"Construction",
            "type":"Services"
        }
    ],
    "sg:postcode":"PO1 4HF",
    "sg:province":"Hampshire",
    "sg:tags":[
        "builder"
    ],
    "wof:name":"Accurate Building Services",
    "wof:placetype":"venue"
},
  "geometry": {"coordinates":[-1.08349,50.80344],"type":"Point"}
}