{
  "type": "Feature",
  "properties": {
    "addr:full":"2 Radnor Chambers Folkestone Kent CT20 2BB",
    "addr:housenumber":"2",
    "addr:postcode":"ct20 2bb",
    "iso:country":"GB",
    "sg:address":"2 Radnor Chambers",
    "sg:city":"Folkestone",
    "sg:classifiers":[
        {
            "category":"Shopping",
            "subcategory":"Clothing, Apparel, & Fashions",
            "type":"Retail Goods"
        }
    ],
    "sg:phone":"+44 1303 241078",
    "sg:postcode":"CT20 2BB",
    "sg:province":"Kent",
    "sg:tags":[
        "shop"
    ],
    "wof:name":"Bamba Boutique",
    "wof:placetype":"venue"
},
  "geometry": {"coordinates":[1.177945,51.084431],"type":"Point"}
}