{
  "type": "Feature",
  "properties": {
    "addr:full":"61-62 Royal Parade Eastbourne East Sussex BN22 7AQ",
    "addr:housenumber":"61-62",
    "addr:postcode":"bn22 7aq",
    "addr:street":"Royal Parade",
    "iso:country":"GB",
    "sg:address":"61-62 Royal Parade",
    "sg:city":"Eastbourne",
    "sg:classifiers":[
        {
            "category":"Travel",
            "subcategory":"Hotels & Motels",
            "type":"Entertainment"
        }
    ],
    "sg:postcode":"BN22 7AQ",
    "sg:province":"East Sussex",
    "wof:name":"Bay Lodge Hotel",
    "wof:placetype":"venue"
},
  "geometry": {"coordinates":[0.299174,50.773788],"type":"Point"}
}