{
  "type": "Feature",
  "properties": {
    "iso:country":"GB",
    "sg:address":"Station House, Old Station Court, Blunham",
    "sg:city":"Bedford",
    "sg:classifiers":[
        {
            "category":"Organizations",
            "subcategory":"Membership Organization",
            "type":"Services"
        }
    ],
    "sg:phone":"+44 1767 641294",
    "sg:postcode":"MK44 3PN",
    "sg:province":"Bedfordshire",
    "sg:tags":[
        "club"
    ],
    "wof:name":"Links",
    "wof:placetype":"venue"
},
  "geometry": {"coordinates":[-0.326395005,52.1386032104],"type":"Point"}
}