{
  "type": "Feature",
  "properties": {
    "addr:full":"19 Ridley Place, Newcastle Newcastle Upon Tyne Tyne and Wear NE1 8JN",
    "addr:housenumber":"19",
    "addr:postcode":"ne1 8jn",
    "addr:street":"Ridley Place",
    "iso:country":"GB",
    "sg:address":"19 Ridley Place, Newcastle",
    "sg:city":"Newcastle Upon Tyne",
    "sg:classifiers":[
        {
            "category":"Professional",
            "subcategory":"Business Services",
            "type":"Services"
        }
    ],
    "sg:phone":"+44 191 230 2414",
    "sg:postcode":"NE1 8JN",
    "sg:province":"Tyne and Wear",
    "sg:tags":[
        "transfer",
        "agent",
        "broking"
    ],
    "wof:name":"Wharton Carpenter",
    "wof:placetype":"venue"
},
  "geometry": {"coordinates":[-1.6121770144,54.9773368835],"type":"Point"}
}