{
  "type": "Feature",
  "properties": {
    "iso:country":"GB",
    "sg:address":"132 London Road",
    "sg:city":"Rayleigh",
    "sg:classifiers":[
        {
            "category":"Food & Beverages",
            "subcategory":"Liquor & Beverages",
            "type":"Retail Goods"
        }
    ],
    "sg:phone":"+44 1268 785230",
    "sg:postcode":"SS6 9BN",
    "sg:province":"Essex",
    "sg:tags":[
        "beer",
        "spirit",
        "wines"
    ],
    "wof:name":"Victoria Wine Co",
    "wof:placetype":"venue"
},
  "geometry": {"coordinates":[0.593978,51.594345],"type":"Point"}
}