{
  "type": "Feature",
  "properties": {
    "addr:full":"Arlington House, Arlington Street London Greater London SW1A 1RJ",
    "addr:postcode":"sw1a 1rj",
    "addr:street":"Arlington Street",
    "iso:country":"GB",
    "sg:address":"Arlington House, Arlington Street",
    "sg:city":"London",
    "sg:classifiers":[
        {
            "category":"Restaurant",
            "type":"Food & Drink"
        }
    ],
    "sg:phone":"+44 20 7629 2239",
    "sg:postcode":"SW1A 1RJ",
    "sg:province":"Greater London",
    "sg:tags":[
        "french"
    ],
    "wof:name":"le Caprice",
    "wof:placetype":"venue"
},
  "geometry": {"coordinates":[-0.1412999928,51.5061912537],"type":"Point"}
}