{
  "type": "Feature",
  "properties": {
    "addr:full":"Teybrook Farm, Brook Road Colchester Essex CO6 1JE",
    "addr:postcode":"co6 1je",
    "addr:street":"Brook Road Colchester",
    "iso:country":"GB",
    "sg:address":"Teybrook Farm, Brook Road",
    "sg:city":"Colchester",
    "sg:classifiers":[
        {
            "category":"Manufacturing",
            "subcategory":"Wood Products",
            "type":"Manufacturing & Wholesale Goods"
        }
    ],
    "sg:postcode":"CO6 1JE",
    "sg:province":"Essex",
    "sg:tags":[
        "maker",
        "cabinet"
    ],
    "wof:name":"Tey Brook Cabinets",
    "wof:placetype":"venue"
},
  "geometry": {"coordinates":[0.7485799789,51.8898200989],"type":"Point"}
}