{
  "type": "Feature",
  "properties": {
    "iso:country":"GB",
    "sg:address":"10 School Wynd",
    "sg:city":"Kirriemuir",
    "sg:classifiers":[
        {
            "category":"Banks & Credit Unions",
            "subcategory":"Financial Services",
            "type":"Services"
        }
    ],
    "sg:phone":"+44 1575 575411",
    "sg:postcode":"DD8 4BQ",
    "sg:province":"Angus",
    "sg:tags":[
        "consultant"
    ],
    "wof:name":"Camerons",
    "wof:placetype":"venue"
},
  "geometry": {"coordinates":[-3.011468,56.691925],"type":"Point"}
}