{
  "type": "Feature",
  "properties": {
    "iso:country":"GB",
    "sg:address":"87-89 Cholmondeley Road",
    "sg:city":"Salford",
    "sg:classifiers":[
        {
            "category":"Cinema",
            "subcategory":"Movie Rental",
            "type":"Entertainment"
        }
    ],
    "sg:phone":"+44 161 745 7645",
    "sg:postcode":"M6 8PU",
    "sg:province":"Greater Manchester",
    "sg:tags":[
        "video",
        "library"
    ],
    "wof:name":"Global Video (Uk)",
    "wof:placetype":"venue"
},
  "geometry": {"coordinates":[-2.3199589252,53.4936408997],"type":"Point"}
}