{
  "type": "Feature",
  "properties": {
    "iso:country":"GB",
    "sg:address":"117 Lordship Lane",
    "sg:city":"London",
    "sg:classifiers":[
        {
            "category":"Professional",
            "subcategory":"Detective & Security Services",
            "type":"Services"
        }
    ],
    "sg:phone":"+44 20 8299 4737",
    "sg:postcode":"SE22 8HU",
    "sg:province":"Greater London",
    "sg:tags":[
        "locksmith"
    ],
    "wof:name":"Callow Locksmiths",
    "wof:placetype":"venue"
},
  "geometry": {"coordinates":[-0.0754999965,51.4570770264],"type":"Point"}
}