{
  "type": "Feature",
  "properties": {
    "addr:full":"Compton House, Upper South Street Mold Denbighshire CH7 5AL",
    "addr:postcode":"ch7 5al",
    "addr:street":"Upper South Street",
    "iso:country":"GB",
    "sg:address":"Compton House, Upper South Street",
    "sg:city":"Mold",
    "sg:classifiers":[
        {
            "category":"Shopping",
            "subcategory":"Department Store",
            "type":"Retail Goods"
        }
    ],
    "sg:phone":"+44 1352 720221",
    "sg:postcode":"CH7 5AL",
    "sg:province":"Denbighshire",
    "wof:name":"J E & M Falshaw & Sons",
    "wof:placetype":"venue"
},
  "geometry": {"coordinates":[-3.3073790073,53.2457847595],"type":"Point"}
}