{
  "type": "Feature",
  "properties": {
    "addr:full":"27 Church Road, Bebington Wirral Merseyside CH63 7PG",
    "addr:housenumber":"27",
    "addr:postcode":"ch63 7pg",
    "addr:street":"Church Road",
    "iso:country":"GB",
    "sg:address":"27 Church Road, Bebington",
    "sg:city":"Wirral",
    "sg:classifiers":[
        {
            "category":"Communications",
            "type":"Services"
        }
    ],
    "sg:postcode":"CH63 7PG",
    "sg:province":"Merseyside",
    "sg:tags":[
        "tv",
        "video",
        "radio"
    ],
    "wof:name":"H C Smith & Co.",
    "wof:placetype":"venue"
},
  "geometry": {"coordinates":[-3.002684,53.349144],"type":"Point"}
}