{
  "type": "Feature",
  "properties": {
    "addr:full":"Porta Cabin, Rowborough Farm, South Marston Swindon Wiltshire SN3 4SL",
    "addr:housenumber":"south",
    "addr:postcode":"sn3 4sl",
    "addr:street":"Porta;Marston Swindon",
    "iso:country":"GB",
    "sg:address":"Porta Cabin, Rowborough Farm, South Marston",
    "sg:city":"Swindon",
    "sg:classifiers":[
        {
            "category":"Building & Trades",
            "subcategory":"Construction",
            "type":"Services"
        }
    ],
    "sg:postcode":"SN3 4SL",
    "sg:province":"Wiltshire",
    "sg:tags":[
        "builder"
    ],
    "wof:name":"Boundry Scaffolding",
    "wof:placetype":"venue"
},
  "geometry": {"coordinates":[-1.723333,51.591125],"type":"Point"}
}