{
  "type": "Feature",
  "properties": {
    "iso:country":"GB",
    "sg:address":"8 Palmerston Centre, Palmerston Road",
    "sg:city":"Harrow",
    "sg:classifiers":[
        {
            "category":"Shopping",
            "subcategory":"Computers & Home Electronics",
            "type":"Retail Goods"
        }
    ],
    "sg:postcode":"HA3 7RG",
    "sg:province":"Greater London",
    "sg:tags":[
        "electrical"
    ],
    "wof:name":"Dynamic Electric Co. Ltd.",
    "wof:placetype":"venue"
},
  "geometry": {"coordinates":[-0.3310100138,51.5929107666],"type":"Point"}
}