{
  "type": "Feature",
  "properties": {
    "addr:full":"Crag House, Cliff Avenue, Summerseat Bury Lancashire BL9 5NT",
    "addr:postcode":"bl9 5nt",
    "addr:street":"Cliff Avenue",
    "iso:country":"GB",
    "sg:address":"Crag House, Cliff Avenue, Summerseat",
    "sg:city":"Bury",
    "sg:classifiers":[
        {
            "category":"Building & Trades",
            "subcategory":"Construction",
            "type":"Services"
        }
    ],
    "sg:phone":"+44 1706 823601",
    "sg:postcode":"BL9 5NT",
    "sg:province":"Lancashire",
    "sg:tags":[
        "builder"
    ],
    "wof:name":"G P Hartley Builders",
    "wof:placetype":"venue"
},
  "geometry": {"coordinates":[-2.3133640289,53.6309509277],"type":"Point"}
}