{
  "type": "Feature",
  "properties": {
    "addr:full":"21 Neville Dr Thornton Cleveleys Lancashire FY5 5EY",
    "addr:housenumber":"21",
    "addr:postcode":"fy5 5ey",
    "addr:street":"Neville Dr",
    "iso:country":"GB",
    "sg:address":"21 Neville Dr",
    "sg:city":"Thornton Cleveleys",
    "sg:classifiers":[
        {
            "category":"Professional",
            "subcategory":"Engineering",
            "type":"Services"
        }
    ],
    "sg:phone":"+44 1253 862512",
    "sg:postcode":"FY5 5EY",
    "sg:province":"Lancashire",
    "sg:tags":[
        "contractor",
        "electrical",
        "engineer"
    ],
    "wof:name":"Bateson Security & Electrical",
    "wof:placetype":"venue"
},
  "geometry": {"coordinates":[-3.0080769062,53.8670578003],"type":"Point"}
}