{
  "type": "Feature",
  "properties": {
    "iso:country":"GB",
    "sg:address":"Ecovert House, 2 Bartholomews",
    "sg:city":"Brighton",
    "sg:classifiers":[
        {
            "category":"Professional",
            "subcategory":"Business Services",
            "type":"Services"
        }
    ],
    "sg:phone":"+44 1273 778772",
    "sg:postcode":"BN1 1HG",
    "sg:province":"East Sussex",
    "sg:tags":[
        "hospitality",
        "corporate"
    ],
    "wof:name":"Reflex Event Management Ltd.",
    "wof:placetype":"venue"
},
  "geometry": {"coordinates":[-0.1397600025,50.8205337524],"type":"Point"}
}