{
  "type": "Feature",
  "properties": {
    "addr:full":"98 Station Road Horsham West Sussex RH13 5EU",
    "addr:housenumber":"98",
    "addr:postcode":"rh13 5eu",
    "addr:street":"Station Road",
    "iso:country":"GB",
    "sg:address":"98 Station Road",
    "sg:city":"Horsham",
    "sg:classifiers":[
        {
            "category":"Shopping",
            "subcategory":"Stationery & Office Supplies",
            "type":"Retail Goods"
        }
    ],
    "sg:phone":"+44 1403 262453",
    "sg:postcode":"RH13 5EU",
    "sg:province":"West Sussex",
    "sg:tags":[
        "item",
        "promotional"
    ],
    "wof:name":"R J Osborne Ltd.",
    "wof:placetype":"venue"
},
  "geometry": {"coordinates":[-0.3159379959,51.0676040649],"type":"Point"}
}