{
  "type": "Feature",
  "properties": {
    "iso:country":"GB",
    "sg:address":"Newport Road, Rumney",
    "sg:city":"Cardiff",
    "sg:classifiers":[
        {
            "category":"Education",
            "subcategory":"School",
            "type":"Public Place"
        },
        {
            "category":"Government",
            "subcategory":"Office",
            "type":"Public Place"
        }
    ],
    "sg:phone":"+44 29 2079 2751",
    "sg:postcode":"CF3 3XG",
    "sg:province":"Caerphilly",
    "sg:tags":[
        "local",
        "authority"
    ],
    "wof:name":"Rumney High School",
    "wof:placetype":"venue"
},
  "geometry": {"coordinates":[-3.124594,51.513786],"type":"Point"}
}