{
  "type": "Feature",
  "properties": {
    "iso:country":"GB",
    "sg:address":"43 Hillsborough Road, Glen Parva",
    "sg:city":"Leicester",
    "sg:classifiers":[
        {
            "category":"Building & Trades",
            "subcategory":"Plumbing",
            "type":"Services"
        }
    ],
    "sg:postcode":"LE2 9PS",
    "sg:province":"Leicestershire",
    "sg:tags":[
        "heating"
    ],
    "wof:name":"J S Cartwright",
    "wof:placetype":"venue"
},
  "geometry": {"coordinates":[-1.1561479568,52.5857467651],"type":"Point"}
}