{
  "type": "Feature",
  "properties": {
    "addr:full":"22 Monks Kirby Rd Sutton Coldfield Warwickshire B76 2UN",
    "addr:housenumber":"22",
    "addr:postcode":"b76 2un",
    "addr:street":"Monks Kirby Rd",
    "iso:country":"GB",
    "sg:address":"22 Monks Kirby Rd",
    "sg:city":"Sutton Coldfield",
    "sg:classifiers":[
        {
            "category":"Arts & Performance",
            "subcategory":"Music",
            "type":"Entertainment"
        }
    ],
    "sg:phone":"+44 121 240 8411",
    "sg:postcode":"B76 2UN",
    "sg:province":"Warwickshire",
    "sg:tags":[
        "mobile",
        "disco"
    ],
    "wof:name":"D.J 2000 Roadshow",
    "wof:placetype":"venue"
},
  "geometry": {"coordinates":[-1.799466,52.556286],"type":"Point"}
}