{
  "type": "Feature",
  "properties": {
    "iso:country":"GB",
    "sg:address":"10 Cloverdale Square",
    "sg:city":"Bolton",
    "sg:classifiers":[
        {
            "category":"Building & Trades",
            "subcategory":"Cleaning & Sanitation",
            "type":"Services"
        }
    ],
    "sg:phone":"+44 1204 842117",
    "sg:postcode":"BL1 6AU",
    "sg:province":"Lancashire",
    "sg:tags":[
        "commercial"
    ],
    "wof:name":"C.G Cleaning",
    "wof:placetype":"venue"
},
  "geometry": {"coordinates":[-2.463467,53.589497],"type":"Point"}
}