{
  "type": "Feature",
  "properties": {
    "iso:country":"GB",
    "sg:address":"21 New Bridge Street",
    "sg:city":"Truro",
    "sg:classifiers":[
        {
            "category":"Arts & Performance",
            "subcategory":"Art Gallery",
            "type":"Entertainment"
        }
    ],
    "sg:postcode":"TR1 2AA",
    "sg:province":"Cornwall",
    "wof:name":"New Bridge Gallery",
    "wof:placetype":"venue"
},
  "geometry": {"coordinates":[-5.049067,50.263531],"type":"Point"}
}