{
  "type": "Feature",
  "properties": {
    "addr:full":"Clint Green Farm Dereham Norfolk NR19 1RX",
    "addr:postcode":"nr19 1rx",
    "addr:street":"Clint;Dereham",
    "iso:country":"GB",
    "sg:address":"Clint Green Farm",
    "sg:city":"Dereham",
    "sg:classifiers":[
        {
            "category":"Building & Trades",
            "subcategory":"Construction",
            "type":"Services"
        }
    ],
    "sg:phone":"+44 1362 696724",
    "sg:postcode":"NR19 1RX",
    "sg:province":"Norfolk",
    "sg:tags":[
        "joinery"
    ],
    "wof:name":"J Cheetham",
    "wof:placetype":"venue"
},
  "geometry": {"coordinates":[0.9455890059,52.6801681519],"type":"Point"}
}