{
  "type": "Feature",
  "properties": {
    "addr:full":"Highway Farm, Ash Martock Somerset TA12 6NT",
    "addr:postcode":"ta12 6nt",
    "addr:street":"Highway;Ash",
    "iso:country":"GB",
    "sg:address":"Highway Farm, Ash",
    "sg:city":"Martock",
    "sg:classifiers":[
        {
            "category":"Professional",
            "type":"Services"
        }
    ],
    "sg:phone":"+44 1935 823261",
    "sg:postcode":"TA12 6NT",
    "sg:province":"Somerset",
    "sg:tags":[
        "valuer",
        "auctioneer"
    ],
    "wof:name":"Vickery's Auction",
    "wof:placetype":"venue"
},
  "geometry": {"coordinates":[-2.770669,50.967247],"type":"Point"}
}