{
  "type": "Feature",
  "properties": {
    "iso:country":"GB",
    "sg:address":"23 Banbury Road",
    "sg:city":"Oxford",
    "sg:classifiers":[
        {
            "category":"Health Services",
            "subcategory":"Hospital",
            "type":"Services"
        }
    ],
    "sg:phone":"+44 1865 404142",
    "sg:postcode":"OX2 6PD",
    "sg:province":"Oxfordshire",
    "wof:name":"The Acland Hospital",
    "wof:placetype":"venue"
},
  "geometry": {"coordinates":[-1.260481,51.76104],"type":"Point"}
}