{
  "type": "Feature",
  "properties": {
    "iso:country":"GB",
    "sg:address":"34 Knighton Park, Sea Rd",
    "sg:city":"New Milton",
    "sg:classifiers":[
        {
            "category":"Professional",
            "subcategory":"Secretarial Services",
            "type":"Services"
        }
    ],
    "sg:phone":"+44 1425 610287",
    "sg:postcode":"BH25 7PG",
    "sg:province":"Hampshire",
    "wof:name":"Phrasers Manuscripts",
    "wof:placetype":"venue"
},
  "geometry": {"coordinates":[-1.673104,50.743565],"type":"Point"}
}