{
  "type": "Feature",
  "properties": {
    "addr:full":"7 Bellevue Rd Tooting Greater London SW17 7EG",
    "addr:housenumber":"7",
    "addr:postcode":"sw17 7eg",
    "addr:street":"Bellevue Rd",
    "iso:country":"GB",
    "sg:address":"7 Bellevue Rd",
    "sg:city":"Tooting",
    "sg:classifiers":[
        {
            "category":"Food & Beverages",
            "subcategory":"Bakery",
            "type":"Retail Goods"
        }
    ],
    "sg:phone":"+44 20 8672 7252",
    "sg:postcode":"SW17 7EG",
    "sg:province":"Greater London",
    "sg:tags":[
        "confectionery"
    ],
    "wof:name":"Amandine Patisserie",
    "wof:placetype":"venue"
},
  "geometry": {"coordinates":[-0.1656299978,51.4459648132],"type":"Point"}
}