{
  "type": "Feature",
  "properties": {
    "iso:country":"GB",
    "sg:address":"Main Street",
    "sg:city":"Grange-over-sands",
    "sg:classifiers":[
        {
            "category":"Shopping",
            "subcategory":"Antiques",
            "type":"Retail Goods"
        }
    ],
    "sg:postcode":"LA11 6DP",
    "sg:province":"Cumbria",
    "wof:name":"THE OLD CURIOSITY SHOP",
    "wof:placetype":"venue"
},
  "geometry": {"coordinates":[-2.908149004,54.1940307617],"type":"Point"}
}