{
  "type": "Feature",
  "properties": {
    "addr:full":"90 The Broadway Mill Hill Greater London NW7 3TB",
    "addr:housenumber":"90",
    "addr:postcode":"nw7 3tb",
    "addr:street":"The Broadway",
    "iso:country":"GB",
    "sg:address":"90 The Broadway",
    "sg:city":"Mill Hill",
    "sg:classifiers":[
        {
            "category":"Shopping",
            "subcategory":"News",
            "type":"Retail Goods"
        }
    ],
    "sg:phone":"+44 20 8959 0490",
    "sg:postcode":"NW7 3TB",
    "sg:province":"Greater London",
    "sg:tags":[
        "newsagent"
    ],
    "wof:name":"Andrews",
    "wof:placetype":"venue"
},
  "geometry": {"coordinates":[-0.2448109984,51.6158866882],"type":"Point"}
}