{
  "type": "Feature",
  "properties": {
    "addr:full":"The Reeds, Frensham Farnham Hampshire GU10 3BP",
    "addr:postcode":"gu10 3bp",
    "iso:country":"GB",
    "sg:address":"The Reeds, Frensham",
    "sg:city":"Farnham",
    "sg:classifiers":[
        {
            "category":"Shopping",
            "subcategory":"Department Store",
            "type":"Retail Goods"
        },
        {
            "category":"Shopping",
            "subcategory":"Gifts & Souvenirs",
            "type":"Retail Goods"
        }
    ],
    "sg:phone":"+44 1252 793365",
    "sg:postcode":"GU10 3BP",
    "sg:province":"Hampshire",
    "sg:tags":[
        "shop"
    ],
    "wof:name":"Dorian Craft",
    "wof:placetype":"venue"
},
  "geometry": {"coordinates":[-0.795544,51.165733],"type":"Point"}
}