{
  "type": "Feature",
  "properties": {
    "addr:full":"Unit 1-2, Hampstead Mill Stockport Cheshire SK2 7NU",
    "addr:housenumber":"unit 1-2",
    "addr:postcode":"sk2 7nu",
    "addr:street":"Hampstead Mill",
    "iso:country":"GB",
    "sg:address":"Unit 1-2, Hampstead Mill",
    "sg:city":"Stockport",
    "sg:classifiers":[
        {
            "category":"Retail",
            "subcategory":"Repair Shop",
            "type":"Services"
        }
    ],
    "sg:phone":"+44 161 456 9013",
    "sg:postcode":"SK2 7NU",
    "sg:province":"Cheshire",
    "sg:tags":[
        "upholsterer"
    ],
    "wof:name":"VOGUE INTERIORS",
    "wof:placetype":"venue"
},
  "geometry": {"coordinates":[-2.1356151104,53.3912239075],"type":"Point"}
}