{
  "type": "Feature",
  "properties": {
    "addr:full":"58 Shrivenham Hundred, Watchfield Swindon Gloucestershire SN6 8TZ",
    "addr:housenumber":"58",
    "addr:postcode":"sn6 8tz",
    "addr:street":"Shrivenham Hundred",
    "iso:country":"GB",
    "sg:address":"58 Shrivenham Hundred, Watchfield",
    "sg:city":"Swindon",
    "sg:classifiers":[
        {
            "category":"Professional",
            "subcategory":"Business Services",
            "type":"Services"
        }
    ],
    "sg:postcode":"SN6 8TZ",
    "sg:province":"Gloucestershire",
    "sg:tags":[
        "import",
        "export",
        "agent"
    ],
    "wof:name":"Cubicom Sweetoy Ltd.",
    "wof:placetype":"venue"
},
  "geometry": {"coordinates":[-1.6901739836,51.6182785034],"type":"Point"}
}