{
  "type": "Feature",
  "properties": {
    "addr:full":"Lyde Rd Yeovil Somerset BA21 5DW",
    "addr:postcode":"ba21 5dw",
    "addr:street":"Lyde Rd",
    "iso:country":"GB",
    "sg:address":"Lyde Rd",
    "sg:city":"Yeovil",
    "sg:classifiers":[
        {
            "category":"Food & Beverages",
            "subcategory":"Supermarket",
            "type":"Retail Goods"
        }
    ],
    "sg:phone":"+44 1455 555000",
    "sg:postcode":"BA21 5DW",
    "sg:province":"Somerset",
    "wof:name":"Lidl UK GMBH",
    "wof:placetype":"venue"
},
  "geometry": {"coordinates":[-2.609872,50.954418],"type":"Point"}
}