{
  "type": "Feature",
  "properties": {
    "addr:full":"286 North Road Cardiff Cardiff CF14 3BN",
    "addr:housenumber":"286",
    "addr:postcode":"cf14 3bn",
    "addr:street":"North Road",
    "iso:country":"GB",
    "sg:address":"286 North Road",
    "sg:city":"Cardiff",
    "sg:classifiers":[
        {
            "category":"Professional",
            "subcategory":"Art Services",
            "type":"Services"
        }
    ],
    "sg:phone":"+44 29 2069 4100",
    "sg:postcode":"CF14 3BN",
    "sg:province":"Cardiff",
    "sg:tags":[
        "consultant",
        "design"
    ],
    "wof:name":"D T B Design",
    "wof:placetype":"venue"
},
  "geometry": {"coordinates":[-3.1971390247,51.5025405884],"type":"Point"}
}