{
  "type": "Feature",
  "properties": {
    "addr:full":"21 Weardale Lane, Queenslie Industrial Estate Glasgow Glasgow City G33 4JJ",
    "addr:housenumber":"21",
    "addr:postcode":"g33 4jj",
    "addr:street":"Weardale Lane Queenslie Industrial Estate",
    "iso:country":"GB",
    "sg:address":"21 Weardale Lane, Queenslie Industrial Estate",
    "sg:city":"Glasgow",
    "sg:classifiers":[
        {
            "category":"Retail",
            "subcategory":"Auto Repair",
            "type":"Services"
        }
    ],
    "sg:postcode":"G33 4JJ",
    "sg:province":"Glasgow City",
    "sg:tags":[
        "modification",
        "garage"
    ],
    "wof:name":"A & J's Autos",
    "wof:placetype":"venue"
},
  "geometry": {"coordinates":[-4.1533989906,55.8660316467],"type":"Point"}
}