{
  "type": "Feature",
  "properties": {
    "iso:country":"GB",
    "sg:address":"1/2 Lemon Villas",
    "sg:city":"Truro",
    "sg:classifiers":[
        {
            "category":"Real Estate",
            "subcategory":"Surveying",
            "type":"Services"
        }
    ],
    "sg:phone":"+44 1872 274646",
    "sg:postcode":"TR1 2NU",
    "sg:province":"Cornwall",
    "sg:tags":[
        "surveyor",
        "valuer"
    ],
    "wof:name":"Stratton & Holborow Ltd.",
    "wof:placetype":"venue"
},
  "geometry": {"coordinates":[-5.050914,50.262341],"type":"Point"}
}