{
  "type": "Feature",
  "properties": {
    "addr:full":"23 Caedelyn Road Cardiff Cardiff CF14 1BH",
    "addr:housenumber":"23",
    "addr:postcode":"cf14 1bh",
    "addr:street":"Caedelyn Road",
    "iso:country":"GB",
    "sg:address":"23 Caedelyn Road",
    "sg:city":"Cardiff",
    "sg:classifiers":[
        {
            "category":"Personal",
            "type":"Services"
        }
    ],
    "sg:phone":"+44 29 2061 6875",
    "sg:postcode":"CF14 1BH",
    "sg:province":"Cardiff",
    "sg:tags":[
        "consultant",
        "fitness"
    ],
    "wof:name":"Rugby Science",
    "wof:placetype":"venue"
},
  "geometry": {"coordinates":[-3.2209420204,51.5202713013],"type":"Point"}
}