{
  "type": "Feature",
  "properties": {
    "addr:full":"374a-474f Richmond Road Twickenham Greater London TW1 2DX",
    "addr:postcode":"tw1 2dx",
    "addr:street":"374A-474F Richmond Road",
    "iso:country":"GB",
    "sg:address":"374a-474f Richmond Road",
    "sg:city":"Twickenham",
    "sg:classifiers":[
        {
            "category":"Restaurant",
            "type":"Food & Drink"
        }
    ],
    "sg:phone":"+44 20 8255 0000",
    "sg:postcode":"TW1 2DX",
    "sg:province":"Greater London",
    "wof:name":"Annabells Brasserie",
    "wof:placetype":"venue"
},
  "geometry": {"coordinates":[-0.3104040027,51.4553451538],"type":"Point"}
}