{
  "type": "Feature",
  "properties": {
    "iso:country":"GB",
    "sg:address":"Holmlea, Main Street",
    "sg:city":"Northallerton",
    "sg:classifiers":[
        {
            "category":"Professional",
            "subcategory":"Management & Consulting",
            "type":"Services"
        },
        {
            "category":"Real Estate",
            "subcategory":"Architect",
            "type":"Services"
        }
    ],
    "sg:phone":"+44 1609 770017",
    "sg:postcode":"DL7 9DN",
    "sg:province":"North Yorkshire",
    "sg:tags":[
        "consultant",
        "business",
        "architectural"
    ],
    "wof:name":"William J Stockdale",
    "wof:placetype":"venue"
},
  "geometry": {"coordinates":[-1.4011900425,54.2869491577],"type":"Point"}
}