{
  "type": "Feature",
  "properties": {
    "iso:country":"GB",
    "sg:address":"Whittington Hall, Whittington Road",
    "sg:city":"Worcester",
    "sg:classifiers":[
        {
            "category":"Real Estate",
            "subcategory":"Real Estate Agent",
            "type":"Services"
        }
    ],
    "sg:phone":"+44 1905 354444",
    "sg:postcode":"WR5 2ZX",
    "sg:province":"Worcestershire",
    "wof:name":"Pemberstone Commercial Ltd.",
    "wof:placetype":"venue"
},
  "geometry": {"coordinates":[-2.1856970787,52.1720733643],"type":"Point"}
}