{
  "type": "Feature",
  "properties": {
    "iso:country":"GB",
    "sg:address":"Main Car Park, Main Street, Hawkshead",
    "sg:city":"Ambleside",
    "sg:classifiers":[
        {
            "category":"Cafe",
            "type":"Food & Drink"
        }
    ],
    "sg:phone":"+44 15394 36274",
    "sg:postcode":"LA22 0NT",
    "sg:province":"Cumbria",
    "sg:tags":[
        "tea",
        "snack",
        "bar",
        "room"
    ],
    "wof:name":"THE COFFEE SHOP",
    "wof:placetype":"venue"
},
  "geometry": {"coordinates":[-2.9996109009,54.3760719299],"type":"Point"}
}