{
  "type": "Feature",
  "properties": {
    "addr:full":"19 Barrie Court Livingston West Lothian EH54 5NJ",
    "addr:housenumber":"19",
    "addr:postcode":"eh54 5nj",
    "addr:street":"Barrie Court",
    "iso:country":"GB",
    "sg:address":"19 Barrie Court",
    "sg:city":"Livingston",
    "sg:classifiers":[
        {
            "category":"Parking",
            "type":"Transportation"
        }
    ],
    "sg:phone":"+44 1506 497088",
    "sg:postcode":"EH54 5NJ",
    "sg:province":"West Lothian",
    "sg:tags":[
        "car",
        "park"
    ],
    "wof:name":"Scotpark",
    "wof:placetype":"venue"
},
  "geometry": {"coordinates":[-3.483845,55.897408],"type":"Point"}
}