{
  "type": "Feature",
  "properties": {
    "iso:country":"GB",
    "sg:address":"76 High Street",
    "sg:city":"Ipswich",
    "sg:classifiers":[
        {
            "category":"Banks & Credit Unions",
            "subcategory":"Financial Services",
            "type":"Services"
        }
    ],
    "sg:postcode":"IP7 5EF",
    "sg:province":"Suffolk",
    "sg:tags":[
        "consultant"
    ],
    "wof:name":"Hadleigh Financial Planning",
    "wof:placetype":"venue"
},
  "geometry": {"coordinates":[0.9534080029,52.0444564819],"type":"Point"}
}