{
  "type": "Feature",
  "properties": {
    "addr:full":"The Forge, Main Road, Dorrington Shrewsbury Shropshire SY5 7JE",
    "addr:postcode":"sy5 7je",
    "addr:street":"Main Road",
    "iso:country":"GB",
    "sg:address":"The Forge, Main Road, Dorrington",
    "sg:city":"Shrewsbury",
    "sg:classifiers":[
        {
            "category":"Building & Trades",
            "subcategory":"Equipment Rental",
            "type":"Services"
        }
    ],
    "sg:phone":"+44 1743 718777",
    "sg:postcode":"SY5 7JE",
    "sg:province":"Shropshire",
    "sg:tags":[
        "plant",
        "machinery"
    ],
    "wof:name":"Wildes Plant Hire Ltd.",
    "wof:placetype":"venue"
},
  "geometry": {"coordinates":[-2.773399,52.622414],"type":"Point"}
}