{
  "type": "Feature",
  "properties": {
    "iso:country":"GB",
    "sg:address":"116 Holland Rd",
    "sg:city":"Clacton On Sea",
    "sg:classifiers":[
        {
            "category":"Retail",
            "subcategory":"Auto Repair",
            "type":"Services"
        }
    ],
    "sg:phone":"+44 1255 474145",
    "sg:postcode":"CO15 6ND",
    "sg:province":"Essex",
    "sg:tags":[
        "modification",
        "garage"
    ],
    "wof:name":"Ron Brown",
    "wof:placetype":"venue"
},
  "geometry": {"coordinates":[1.170582,51.798473],"type":"Point"}
}