{
  "type": "Feature",
  "properties": {
    "iso:country":"GB",
    "sg:address":"Greendyke House, Low Mill Lane, Darley",
    "sg:city":"Ilkley",
    "sg:classifiers":[
        {
            "category":"Professional",
            "subcategory":"Management & Consulting",
            "type":"Services"
        },
        {
            "category":"Organizations",
            "subcategory":"Community Association",
            "type":"Services"
        }
    ],
    "sg:phone":"+44 1943 830626",
    "sg:postcode":"LS29 0QP",
    "sg:province":"North Yorkshire",
    "sg:tags":[
        "consultant",
        "training",
        "relation",
        "public"
    ],
    "wof:name":"Lexicon",
    "wof:placetype":"venue"
},
  "geometry": {"coordinates":[-1.866188,53.94157],"type":"Point"}
}