{
  "type": "Feature",
  "properties": {
    "addr:full":"Clove Building, 4 Maguire St Southwark Greater London SE1 2NQ",
    "addr:postcode":"se1 2nq",
    "addr:street":"Maguire St",
    "iso:country":"GB",
    "sg:address":"Clove Building, 4 Maguire St",
    "sg:city":"Southwark",
    "sg:classifiers":[
        {
            "category":"Shopping",
            "subcategory":"Stationery & Office Supplies",
            "type":"Retail Goods"
        }
    ],
    "sg:phone":"+44 20 7403 6993",
    "sg:postcode":"SE1 2NQ",
    "sg:province":"Greater London",
    "sg:tags":[
        "equipment"
    ],
    "wof:name":"Bulo Office Furniture",
    "wof:placetype":"venue"
},
  "geometry": {"coordinates":[-0.07248,51.502411],"type":"Point"}
}