{
  "type": "Feature",
  "properties": {
    "addr:full":"124 Finchley Rd London Greater London NW3 5JS",
    "addr:housenumber":"124",
    "addr:postcode":"nw3 5js",
    "addr:street":"Finchley Rd",
    "iso:country":"GB",
    "sg:address":"124 Finchley Rd",
    "sg:city":"London",
    "sg:classifiers":[
        {
            "category":"Communications",
            "subcategory":"Film & Video Production",
            "type":"Services"
        }
    ],
    "sg:postcode":"NW3 5JS",
    "sg:province":"Greater London",
    "sg:tags":[
        "tv",
        "studio"
    ],
    "wof:name":"N F H Ltd",
    "wof:placetype":"venue"
},
  "geometry": {"coordinates":[-0.179852,51.547523],"type":"Point"}
}