{
  "type": "Feature",
  "properties": {
    "iso:country":"GB",
    "sg:address":"30 Great George Street",
    "sg:city":"Liverpool",
    "sg:classifiers":[
        {
            "category":"Home & Garden",
            "subcategory":"Household Appliances",
            "type":"Retail Goods"
        },
        {
            "category":"Retail",
            "subcategory":"Repair Shop",
            "type":"Services"
        }
    ],
    "sg:phone":"+44 151 708 6218",
    "sg:postcode":"L1 5EP",
    "sg:province":"Merseyside",
    "sg:tags":[
        "machine",
        "electrical",
        "washing"
    ],
    "wof:name":"Machine Medics",
    "wof:placetype":"venue"
},
  "geometry": {"coordinates":[-2.976457,53.397717],"type":"Point"}
}