{
  "type": "Feature",
  "properties": {
    "addr:full":"25 Lambcroft Road, Pinxton Nottingham Derbyshire NG16 6QL",
    "addr:housenumber":"25",
    "addr:postcode":"ng16 6ql",
    "addr:street":"Lambcroft Road",
    "iso:country":"GB",
    "sg:address":"25 Lambcroft Road, Pinxton",
    "sg:city":"Nottingham",
    "sg:classifiers":[
        {
            "category":"Autos & Motor Vehicles",
            "subcategory":"Auto Supplies",
            "type":"Retail Goods"
        },
        {
            "category":"Home & Garden",
            "subcategory":"Hardware",
            "type":"Retail Goods"
        }
    ],
    "sg:phone":"+44 1773 860030",
    "sg:postcode":"NG16 6QL",
    "sg:province":"Derbyshire",
    "sg:tags":[
        "equipment",
        "caravan",
        "heating",
        "accessory"
    ],
    "wof:name":"Detroit Solar",
    "wof:placetype":"venue"
},
  "geometry": {"coordinates":[-1.3206199408,53.0943870544],"type":"Point"}
}