{
  "type": "Feature",
  "properties": {
    "addr:full":"2 Pevensey Court, Eastbourne Road, Pevensey Bay Eastbourne East Sussex BN21 4XB",
    "addr:housenumber":"2",
    "addr:postcode":"bn21 4xb",
    "addr:street":"Pevensey Court Eastbourne Road",
    "iso:country":"GB",
    "sg:address":"2 Pevensey Court, Eastbourne Road, Pevensey Bay",
    "sg:city":"Eastbourne",
    "sg:classifiers":[
        {
            "category":"Home & Garden",
            "subcategory":"Home Furnishings",
            "type":"Retail Goods"
        }
    ],
    "sg:postcode":"BN21 4XB",
    "sg:province":"East Sussex",
    "sg:tags":[
        "blind",
        "curtain",
        "fitting"
    ],
    "wof:name":"Ann Morrow",
    "wof:placetype":"venue"
},
  "geometry": {"coordinates":[0.2803600132,50.7663116455],"type":"Point"}
}