{
  "type": "Feature",
  "properties": {
    "addr:full":"105 Sheepscar St North Leeds West Yorkshire LS7 2RS",
    "addr:housenumber":"105",
    "addr:postcode":"ls7 2rs",
    "addr:street":"Sheepscar St",
    "iso:country":"GB",
    "sg:address":"105 Sheepscar St North",
    "sg:city":"Leeds",
    "sg:classifiers":[
        {
            "category":"Food & Beverages",
            "subcategory":"Supermarket",
            "type":"Retail Goods"
        }
    ],
    "sg:phone":"+44 113 262 1068",
    "sg:postcode":"LS7 2RS",
    "sg:province":"West Yorkshire",
    "sg:tags":[
        "frozen"
    ],
    "wof:name":"Brays Foods Ltd.",
    "wof:placetype":"venue"
},
  "geometry": {"coordinates":[-1.538381,53.812176],"type":"Point"}
}