{
  "type": "Feature",
  "properties": {
    "iso:country":"GB",
    "sg:address":"132 Queens Road",
    "sg:city":"Nuneaton",
    "sg:classifiers":[
        {
            "category":"Food & Beverages",
            "subcategory":"Liquor & Beverages",
            "type":"Retail Goods"
        }
    ],
    "sg:phone":"+44 24 7638 2268",
    "sg:postcode":"CV11 5LG",
    "sg:province":"Leicestershire",
    "sg:tags":[
        "beer",
        "spirit",
        "wines"
    ],
    "wof:name":"M P Stores",
    "wof:placetype":"venue"
},
  "geometry": {"coordinates":[-1.476954,52.522156],"type":"Point"}
}