{
  "type": "Feature",
  "properties": {
    "addr:full":"Mottram St Stockport Cheshire SK1 3PA",
    "addr:postcode":"sk1 3pa",
    "addr:street":"Mottram St",
    "iso:country":"GB",
    "sg:address":"Mottram St",
    "sg:city":"Stockport",
    "sg:classifiers":[
        {
            "category":"Place Of Worship",
            "type":"Public Place"
        }
    ],
    "sg:phone":"+44 161 429 6947",
    "sg:postcode":"SK1 3PA",
    "sg:province":"Cheshire",
    "wof:name":"Elim Pentecostal Church",
    "wof:placetype":"venue"
},
  "geometry": {"coordinates":[-2.15509,53.405682],"type":"Point"}
}