{
  "type": "Feature",
  "properties": {
    "addr:full":"129 Bayswater Road London Greater London W2 4RJ",
    "addr:housenumber":"129",
    "addr:postcode":"w2 4rj",
    "addr:street":"Bayswater Road",
    "iso:country":"GB",
    "sg:address":"129 Bayswater Road",
    "sg:city":"London",
    "sg:classifiers":[
        {
            "category":"Travel",
            "subcategory":"Hotels & Motels",
            "type":"Entertainment"
        }
    ],
    "sg:phone":"+44 20 7221 2217",
    "sg:postcode":"W2 4RJ",
    "sg:province":"Greater London",
    "wof:name":"Stakis Coburg Hotel",
    "wof:placetype":"venue"
},
  "geometry": {"coordinates":[-0.188461,51.510303],"type":"Point"}
}