{
  "type": "Feature",
  "properties": {
    "addr:full":"15 Greatcoat Place London Greater London SW1P 1SB",
    "addr:housenumber":"15",
    "addr:postcode":"sw1p 1sb",
    "addr:street":"Greatcoat Place",
    "iso:country":"GB",
    "sg:address":"15 Greatcoat Place",
    "sg:city":"London",
    "sg:classifiers":[
        {
            "category":"Professional",
            "subcategory":"Management & Consulting",
            "type":"Services"
        }
    ],
    "sg:postcode":"SW1P 1SB",
    "sg:province":"Greater London",
    "sg:tags":[
        "consultant",
        "business"
    ],
    "wof:name":"Pacific Consultancy Services Ltd",
    "wof:placetype":"venue"
},
  "geometry": {"coordinates":[-0.13495,51.496288],"type":"Point"}
}