{
  "type": "Feature",
  "properties": {
    "addr:full":"22 High Street Westerham Kent TN16 1RG",
    "addr:housenumber":"22",
    "addr:postcode":"tn16 1rg",
    "addr:street":"High Street",
    "iso:country":"GB",
    "sg:address":"22 High Street",
    "sg:city":"Westerham",
    "sg:classifiers":[
        {
            "category":"Real Estate",
            "subcategory":"Surveying",
            "type":"Services"
        }
    ],
    "sg:phone":"+44 1959 563800",
    "sg:postcode":"TN16 1RG",
    "sg:province":"Kent",
    "sg:tags":[
        "surveyor",
        "valuer"
    ],
    "wof:name":"Karrison Ltd.",
    "wof:placetype":"venue"
},
  "geometry": {"coordinates":[0.067682,51.265743],"type":"Point"}
}