{
  "type": "Feature",
  "properties": {
    "iso:country":"GB",
    "sg:address":"19 Victory Road",
    "sg:city":"Coventry",
    "sg:classifiers":[
        {
            "category":"Food & Beverages",
            "subcategory":"Supermarket",
            "type":"Retail Goods"
        }
    ],
    "sg:phone":"+44 24 7668 8478",
    "sg:postcode":"CV6 5JF",
    "sg:province":"Warwickshire",
    "wof:name":"Victory Stores",
    "wof:placetype":"venue"
},
  "geometry": {"coordinates":[-1.499283,52.435085],"type":"Point"}
}