{
  "type": "Feature",
  "properties": {
    "addr:full":"11 Middle Row London Greater London W10 5AT",
    "addr:housenumber":"11",
    "addr:postcode":"w10 5at",
    "addr:street":"Middle Row",
    "iso:country":"GB",
    "sg:address":"11 Middle Row",
    "sg:city":"London",
    "sg:classifiers":[
        {
            "category":"Organizations",
            "subcategory":"Non-profit Organization",
            "type":"Services"
        }
    ],
    "sg:phone":"+44 20 8969 9493",
    "sg:postcode":"W10 5AT",
    "sg:province":"Greater London",
    "sg:tags":[
        "organisation",
        "voluntary",
        "charity"
    ],
    "wof:name":"India Investments Plc",
    "wof:placetype":"venue"
},
  "geometry": {"coordinates":[-0.2117010057,51.5249328613],"type":"Point"}
}