{
  "type": "Feature",
  "properties": {
    "iso:country":"GB",
    "sg:address":"1 Highgate West Hill",
    "sg:city":"London",
    "sg:classifiers":[
        {
            "category":"Cafe",
            "type":"Food & Drink"
        }
    ],
    "sg:phone":"+44 20 8342 8355",
    "sg:postcode":"N6 6JS",
    "sg:province":"Greater London",
    "sg:tags":[
        "tea",
        "room"
    ],
    "wof:name":"Sansiro Restaurant & Snack Bar",
    "wof:placetype":"venue"
},
  "geometry": {"coordinates":[-0.144389,51.576363],"type":"Point"}
}