{
  "type": "Feature",
  "properties": {
    "addr:full":"Deer Park Tenby Pembrokeshire SA70 7LE",
    "addr:postcode":"sa70 7le",
    "iso:country":"GB",
    "sg:address":"Deer Park",
    "sg:city":"Tenby",
    "sg:classifiers":[
        {
            "category":"Building & Trades",
            "subcategory":"Construction",
            "type":"Services"
        }
    ],
    "sg:phone":"+44 1834 844962",
    "sg:postcode":"SA70 7LE",
    "sg:province":"Pembrokeshire",
    "sg:tags":[
        "welder"
    ],
    "wof:name":"Pembrokeshire Engineering & Steel Fabrication",
    "wof:placetype":"venue"
},
  "geometry": {"coordinates":[-4.7066540718,51.6718215942],"type":"Point"}
}