{
  "type": "Feature",
  "properties": {
    "iso:country":"GB",
    "sg:address":"30 Church Street",
    "sg:city":"Bishops Castle",
    "sg:classifiers":[
        {
            "category":"Insurance",
            "subcategory":"Insurance Agent",
            "type":"Services"
        }
    ],
    "sg:phone":"+44 1588 638778",
    "sg:postcode":"SY9 5AE",
    "sg:province":"Shropshire",
    "sg:tags":[
        "broker"
    ],
    "wof:name":"P Harris",
    "wof:placetype":"venue"
},
  "geometry": {"coordinates":[-2.997847,52.491638],"type":"Point"}
}