{
  "type": "Feature",
  "properties": {
    "addr:full":"5 Robert St Rushden Bedfordshire NN10 0NG",
    "addr:housenumber":"5",
    "addr:postcode":"nn10 0ng",
    "addr:street":"Robert St",
    "iso:country":"GB",
    "sg:address":"5 Robert St",
    "sg:city":"Rushden",
    "sg:classifiers":[
        {
            "category":"Building & Trades",
            "subcategory":"Construction",
            "type":"Services"
        }
    ],
    "sg:phone":"+44 1933 413159",
    "sg:postcode":"NN10 0NG",
    "sg:province":"Bedfordshire",
    "sg:tags":[
        "builder"
    ],
    "wof:name":"P A Davies Builders",
    "wof:placetype":"venue"
},
  "geometry": {"coordinates":[-0.5915769935,52.2885665894],"type":"Point"}
}