{
  "type": "Feature",
  "properties": {
    "addr:full":"28 East Charles St Camborne Cornwall TR14 8JF",
    "addr:housenumber":"28",
    "addr:postcode":"tr14 8jf",
    "addr:street":"East Charles St",
    "iso:country":"GB",
    "sg:address":"28 East Charles St",
    "sg:city":"Camborne",
    "sg:classifiers":[
        {
            "category":"Building & Trades",
            "subcategory":"Construction",
            "type":"Services"
        }
    ],
    "sg:phone":"+44 1209 710391",
    "sg:postcode":"TR14 8JF",
    "sg:province":"Cornwall",
    "sg:tags":[
        "builder"
    ],
    "wof:name":"R Paull",
    "wof:placetype":"venue"
},
  "geometry": {"coordinates":[-5.2951111794,50.2115516663],"type":"Point"}
}