{
  "type": "Feature",
  "properties": {
    "addr:full":"127-129 Great Suffolk Street London Greater London SE1 1PP",
    "addr:housenumber":"127-129",
    "addr:postcode":"se1 1pp",
    "addr:street":"Great Suffolk Street",
    "iso:country":"GB",
    "sg:address":"127-129 Great Suffolk Street",
    "sg:city":"London",
    "sg:classifiers":[
        {
            "category":"Professional",
            "subcategory":"Engineering",
            "type":"Services"
        }
    ],
    "sg:phone":"+44 20 7407 6847",
    "sg:postcode":"SE1 1PP",
    "sg:province":"Greater London",
    "sg:tags":[
        "consulting",
        "engineer"
    ],
    "wof:name":"Ian Mackay & Associates",
    "wof:placetype":"venue"
},
  "geometry": {"coordinates":[-0.0964630023,51.5002670288],"type":"Point"}
}