{
  "type": "Feature",
  "properties": {
    "addr:full":"Creeton Road, Little Bytham Grantham Leicestershire NG33 4PX",
    "addr:postcode":"ng33 4px",
    "addr:street":"Creeton Road",
    "iso:country":"GB",
    "sg:address":"Creeton Road, Little Bytham",
    "sg:city":"Grantham",
    "sg:classifiers":[
        {
            "category":"Education",
            "subcategory":"School",
            "type":"Public Place"
        },
        {
            "category":"Government",
            "subcategory":"Office",
            "type":"Public Place"
        }
    ],
    "sg:phone":"+44 1780 410275",
    "sg:postcode":"NG33 4PX",
    "sg:province":"Leicestershire",
    "sg:tags":[
        "local",
        "authority"
    ],
    "wof:name":"The Bythams County Primary School",
    "wof:placetype":"venue"
},
  "geometry": {"coordinates":[-0.5034890175,52.7659950256],"type":"Point"}
}