{
  "type": "Feature",
  "properties": {
    "addr:full":"15 Kingston Lane, Southwick Brighton West Sussex BN42 4SJ",
    "addr:housenumber":"15",
    "addr:postcode":"bn42 4sj",
    "addr:street":"Kingston Lane",
    "iso:country":"GB",
    "sg:address":"15 Kingston Lane, Southwick",
    "sg:city":"Brighton",
    "sg:classifiers":[
        {
            "category":"Building & Trades",
            "subcategory":"Construction",
            "type":"Services"
        }
    ],
    "sg:postcode":"BN42 4SJ",
    "sg:province":"West Sussex",
    "sg:tags":[
        "builder"
    ],
    "wof:name":"A C Neville Services",
    "wof:placetype":"venue"
},
  "geometry": {"coordinates":[-0.2438019961,50.8395729065],"type":"Point"}
}