{
  "type": "Feature",
  "properties": {
    "iso:country":"GB",
    "sg:address":"631 Fulham Rd",
    "sg:city":"Fulham",
    "sg:classifiers":[
        {
            "category":"Utilities",
            "type":"Services"
        }
    ],
    "sg:phone":"+44 20 7384 6900",
    "sg:postcode":"SW6 5UQ",
    "sg:province":"Greater London",
    "sg:tags":[
        "internet"
    ],
    "wof:name":"Bibliotech",
    "wof:placetype":"venue"
},
  "geometry": {"coordinates":[-0.1987639964,51.4796218872],"type":"Point"}
}