{
  "type": "Feature",
  "properties": {
    "iso:country":"GB",
    "sg:address":"27 The Burges",
    "sg:city":"Coventry",
    "sg:classifiers":[
        {
            "category":"Shopping",
            "subcategory":"Department Store",
            "type":"Retail Goods"
        }
    ],
    "sg:phone":"+44 24 7622 4020",
    "sg:postcode":"CV1 1HL",
    "sg:province":"West Midlands",
    "wof:name":"J S Nagra",
    "wof:placetype":"venue"
},
  "geometry": {"coordinates":[-1.510802,52.410091],"type":"Point"}
}