{
  "type": "Feature",
  "properties": {
    "iso:country":"GB",
    "sg:address":"52d Cowick Street, St Thomas",
    "sg:city":"Exeter",
    "sg:classifiers":[
        {
            "category":"Parking",
            "type":"Transportation"
        }
    ],
    "sg:phone":"+44 1392 425559",
    "sg:postcode":"EX4 1AP",
    "sg:province":"Devon",
    "sg:tags":[
        "car",
        "valet"
    ],
    "wof:name":"Dream Clean Valeting Service",
    "wof:placetype":"venue"
},
  "geometry": {"coordinates":[-3.54318,50.715405],"type":"Point"}
}