{
  "type": "Feature",
  "properties": {
    "iso:country":"GB",
    "sg:address":"Wellington Drive",
    "sg:city":"Rugeley",
    "sg:classifiers":[
        {
            "category":"Bus Charters",
            "type":"Transportation"
        },
        {
            "category":"Military Area",
            "subcategory":"Air Force Base",
            "type":"Public Place"
        }
    ],
    "sg:phone":"+44 1889 577777",
    "sg:postcode":"WS15 2JX",
    "sg:province":"Staffordshire",
    "sg:tags":[
        "taxi",
        "hire",
        "coach",
        "private"
    ],
    "wof:name":"Maple Motors",
    "wof:placetype":"venue"
},
  "geometry": {"coordinates":[-1.934936,52.758308],"type":"Point"}
}