{
  "type": "Feature",
  "properties": {
    "addr:full":"43 Strouden Road, Charminster Bournemouth Dorset BH9 1QL",
    "addr:housenumber":"43",
    "addr:postcode":"bh9 1ql",
    "addr:street":"Strouden Road",
    "iso:country":"GB",
    "sg:address":"43 Strouden Road, Charminster",
    "sg:city":"Bournemouth",
    "sg:classifiers":[
        {
            "category":"Personal",
            "subcategory":"Tanning Parlor",
            "type":"Services"
        },
        {
            "category":"Shopping",
            "subcategory":"Party Supplies",
            "type":"Retail Goods"
        },
        {
            "category":"Home & Garden",
            "subcategory":"Carpets & Floor Coverings",
            "type":"Retail Goods"
        }
    ],
    "sg:postcode":"BH9 1QL",
    "sg:province":"Dorset",
    "sg:tags":[
        "cleaner",
        "upholstery",
        "sunbeds",
        "bouncy",
        "inflatables",
        "castle",
        "marquees",
        "tent"
    ],
    "wof:name":"Bouncy Fun Hire",
    "wof:placetype":"venue"
},
  "geometry": {"coordinates":[-1.865473,50.745964],"type":"Point"}
}