{
  "type": "Feature",
  "properties": {
    "iso:country":"GB",
    "sg:address":"38 High Street, Puckeridge",
    "sg:city":"Ware",
    "sg:classifiers":[
        {
            "category":"Professional",
            "subcategory":"Lawyer & Legal Services",
            "type":"Services"
        }
    ],
    "sg:phone":"+44 1920 823453",
    "sg:postcode":"SG9 9AG",
    "sg:province":"Hertfordshire",
    "sg:tags":[
        "solicitor"
    ],
    "wof:name":"Norman Macleod",
    "wof:placetype":"venue"
},
  "geometry": {"coordinates":[-0.01908,51.94685],"type":"Point"}
}