{
  "type": "Feature",
  "properties": {
    "iso:country":"GB",
    "sg:address":"70 Clough Road, Hoyland",
    "sg:city":"Barnsley",
    "sg:classifiers":[
        {
            "category":"Building & Trades",
            "subcategory":"Construction",
            "type":"Services"
        }
    ],
    "sg:phone":"+44 1226 743528",
    "sg:postcode":"S74 9DZ",
    "sg:province":"South Yorkshire",
    "sg:tags":[
        "builder",
        "joiner",
        "carpenter"
    ],
    "wof:name":"Ian Cutts",
    "wof:placetype":"venue"
},
  "geometry": {"coordinates":[-1.4481060505,53.4986495972],"type":"Point"}
}