{
  "type": "Feature",
  "properties": {
    "iso:country":"GB",
    "sg:address":"Monarch House, Smyth Road",
    "sg:city":"Bristol",
    "sg:classifiers":[
        {
            "category":"Shopping",
            "subcategory":"Florist",
            "type":"Retail Goods"
        }
    ],
    "sg:phone":"+44 117 953 0345",
    "sg:postcode":"BS3 2BX",
    "sg:province":"City of Bristol",
    "wof:name":"Plants Enhance",
    "wof:placetype":"venue"
},
  "geometry": {"coordinates":[-2.616568,51.438557],"type":"Point"}
}