{
  "type": "Feature",
  "properties": {
    "iso:country":"GB",
    "sg:address":"Grange Terrace, Shotton Colliery",
    "sg:city":"Durham",
    "sg:classifiers":[
        {
            "category":"Education",
            "subcategory":"School",
            "type":"Public Place"
        },
        {
            "category":"Government",
            "subcategory":"Office",
            "type":"Public Place"
        }
    ],
    "sg:phone":"+44 191 526 2006",
    "sg:postcode":"DH6 2JP",
    "sg:province":"Durham",
    "sg:tags":[
        "local",
        "authority"
    ],
    "wof:name":"Shotton Primary School",
    "wof:placetype":"venue"
},
  "geometry": {"coordinates":[-1.394204,54.75983],"type":"Point"}
}