{
  "type": "Feature",
  "properties": {
    "iso:country":"GB",
    "sg:address":"24 Champneys Walk",
    "sg:city":"Cambridge",
    "sg:classifiers":[
        {
            "category":"Banks & Credit Unions",
            "subcategory":"Financial Services",
            "type":"Services"
        }
    ],
    "sg:postcode":"CB3 9AW",
    "sg:province":"Cambridgeshire",
    "sg:tags":[
        "adviser"
    ],
    "wof:name":"Granta Financial Services",
    "wof:placetype":"venue"
},
  "geometry": {"coordinates":[0.1064610034,52.1983337402],"type":"Point"}
}