{
  "type": "Feature",
  "properties": {
    "addr:full":"Unit 4 Kingsthorpe Business Cent, Re Studland Road Northampton Northamptonshire NN2 6NE",
    "addr:housenumber":"unit 4",
    "addr:postcode":"nn2 6ne",
    "addr:street":"Studland Road",
    "iso:country":"GB",
    "sg:address":"Unit 4 Kingsthorpe Business Cent, Re Studland Road",
    "sg:city":"Northampton",
    "sg:classifiers":[
        {
            "category":"Professional",
            "type":"Services"
        }
    ],
    "sg:phone":"+44 1604 791050",
    "sg:postcode":"NN2 6NE",
    "sg:province":"Northamptonshire",
    "sg:tags":[
        "shopfitters"
    ],
    "wof:name":"Pps Shopfitters Ltd.",
    "wof:placetype":"venue"
},
  "geometry": {"coordinates":[-0.9071900249,52.2559318542],"type":"Point"}
}