{
  "type": "Feature",
  "properties": {
    "iso:country":"GB",
    "sg:address":"Lytham Road, Warton",
    "sg:city":"Preston",
    "sg:classifiers":[
        {
            "category":"Professional",
            "subcategory":"Engineering",
            "type":"Services"
        }
    ],
    "sg:phone":"+44 1772 634042",
    "sg:postcode":"PR4 1AH",
    "sg:province":"Lancashire",
    "sg:tags":[
        "agricultural",
        "engineer"
    ],
    "wof:name":"A C P Engineering",
    "wof:placetype":"venue"
},
  "geometry": {"coordinates":[-2.865069,53.75526],"type":"Point"}
}