{
  "type": "Feature",
  "properties": {
    "iso:country":"GB",
    "sg:address":"Unit 1-8, College Park",
    "sg:city":"Cambridge",
    "sg:classifiers":[
        {
            "category":"Communications",
            "type":"Services"
        }
    ],
    "sg:phone":"+44 1223 414101",
    "sg:postcode":"CB1 3HD",
    "sg:province":"Cambridgeshire",
    "sg:tags":[
        "broadcasting"
    ],
    "wof:name":"Megahertz Communications Ltd.",
    "wof:placetype":"venue"
},
  "geometry": {"coordinates":[0.1080949977,52.241065979],"type":"Point"}
}