{
  "type": "Feature",
  "properties": {
    "iso:country":"GB",
    "sg:address":"Lubbecke Way",
    "sg:city":"Dorchester",
    "sg:classifiers":[
        {
            "category":"Organizations",
            "subcategory":"Membership Organization",
            "type":"Services"
        },
        {
            "category":"Organizations",
            "subcategory":"Non-profit Organization",
            "type":"Services"
        }
    ],
    "sg:phone":"+44 1305 262440",
    "sg:postcode":"DT1 1QL",
    "sg:province":"Dorset",
    "sg:tags":[
        "club",
        "charitable",
        "organisation",
        "charity"
    ],
    "wof:name":"DORSET YOUTH ASSOCIATION",
    "wof:placetype":"venue"
},
  "geometry": {"coordinates":[-2.423211,50.712551],"type":"Point"}
}