{
  "type": "Feature",
  "properties": {
    "iso:country":"GB",
    "sg:address":"27 Tabard Road, Eggborough",
    "sg:city":"Goole",
    "sg:classifiers":[
        {
            "category":"Professional",
            "subcategory":"Management & Consulting",
            "type":"Services"
        }
    ],
    "sg:postcode":"DN14 0UP",
    "sg:province":"East Riding of Yorkshire",
    "sg:tags":[
        "consultant",
        "business"
    ],
    "wof:name":"Korea Connections Ltd",
    "wof:placetype":"venue"
},
  "geometry": {"coordinates":[-1.154851,53.703655],"type":"Point"}
}