{
  "type": "Feature",
  "properties": {
    "iso:country":"GB",
    "sg:address":"18 Town Gate, Calverley",
    "sg:city":"Pudsey",
    "sg:classifiers":[
        {
            "category":"Bars & Pubs",
            "type":"Food & Drink"
        }
    ],
    "sg:phone":"+44 113 256 5492",
    "sg:postcode":"LS28 5NF",
    "sg:province":"West Yorkshire",
    "sg:tags":[
        "pubs",
        "house",
        "inn",
        "public",
        "activity"
    ],
    "wof:name":"The Thornhill Arms",
    "wof:placetype":"venue"
},
  "geometry": {"coordinates":[-1.6848649979,53.8288841248],"type":"Point"}
}