{
  "type": "Feature",
  "properties": {
    "iso:country":"GB",
    "sg:address":"94 Hill Top Drive",
    "sg:city":"Rochdale",
    "sg:classifiers":[
        {
            "category":"Organizations",
            "subcategory":"Non-profit Organization",
            "type":"Services"
        }
    ],
    "sg:phone":"+44 1706 345600",
    "sg:postcode":"OL11 2RL",
    "sg:province":"Lancashire",
    "sg:tags":[
        "organisation",
        "voluntary",
        "charity"
    ],
    "wof:name":"The Childrens Society",
    "wof:placetype":"venue"
},
  "geometry": {"coordinates":[-2.1594181061,53.5918006897],"type":"Point"}
}