{
  "type": "Feature",
  "properties": {
    "iso:country":"GB",
    "sg:address":"Trefloyne Park, Trefloyne Lane, Penally",
    "sg:city":"Tenby",
    "sg:classifiers":[
        {
            "category":"Sports & Exercise",
            "subcategory":"Golf",
            "type":"Entertainment"
        }
    ],
    "sg:phone":"+44 1834 842165",
    "sg:postcode":"SA70 7RG",
    "sg:province":"Pembrokeshire",
    "sg:tags":[
        "club",
        "course"
    ],
    "wof:name":"Trefloyne Golf Course",
    "wof:placetype":"venue"
},
  "geometry": {"coordinates":[-4.728238,51.668468],"type":"Point"}
}