{
  "type": "Feature",
  "properties": {
    "addr:full":"137 East Barnet Rd Barnet Hertfordshire EN4 8QZ",
    "addr:housenumber":"137",
    "addr:postcode":"en4 8qz",
    "addr:street":"East Barnet Rd",
    "iso:country":"GB",
    "sg:address":"137 East Barnet Rd",
    "sg:city":"Barnet",
    "sg:classifiers":[
        {
            "category":"Home & Garden",
            "subcategory":"Furniture",
            "type":"Retail Goods"
        }
    ],
    "sg:phone":"+44 20 8449 1491",
    "sg:postcode":"EN4 8QZ",
    "sg:province":"Hertfordshire",
    "wof:name":"Fineworld Pine Furniture",
    "wof:placetype":"venue"
},
  "geometry": {"coordinates":[-0.167195,51.647247],"type":"Point"}
}