{
  "type": "Feature",
  "properties": {
    "iso:country":"GB",
    "sg:address":"1 Lorenzo Street",
    "sg:city":"London",
    "sg:classifiers":[
        {
            "category":"Professional",
            "subcategory":"Business Services",
            "type":"Services"
        }
    ],
    "sg:phone":"+44 20 7278 8111",
    "sg:postcode":"WC1X 9DJ",
    "sg:province":"Greater London",
    "sg:tags":[
        "import",
        "export",
        "agent"
    ],
    "wof:name":"M A Y Trading (U K) Ltd.",
    "wof:placetype":"venue"
},
  "geometry": {"coordinates":[-0.1172029972,51.5305213928],"type":"Point"}
}