{
  "type": "Feature",
  "properties": {
    "addr:full":"Madyn Road Amlwch Isle of Anglesey LL68 9DL",
    "addr:postcode":"ll68 9dl",
    "addr:street":"Madyn Road",
    "iso:country":"GB",
    "sg:address":"Madyn Road",
    "sg:city":"Amlwch",
    "sg:classifiers":[
        {
            "category":"Fast Food",
            "type":"Food & Drink"
        }
    ],
    "sg:phone":"+44 1407 831911",
    "sg:postcode":"LL68 9DL",
    "sg:province":"Isle of Anglesey",
    "sg:tags":[
        "away",
        "meal",
        "outlet",
        "take"
    ],
    "wof:name":"Anglesey Balti House",
    "wof:placetype":"venue"
},
  "geometry": {"coordinates":[-4.3463768959,53.4091033936],"type":"Point"}
}