{
  "type": "Feature",
  "properties": {
    "iso:country":"GB",
    "sg:address":"Chaucer House, Biscot Road",
    "sg:city":"Luton",
    "sg:classifiers":[
        {
            "category":"Sports & Exercise",
            "subcategory":"Sports Center",
            "type":"Entertainment"
        }
    ],
    "sg:postcode":"LU3 1AX",
    "sg:province":"Bedfordshire",
    "sg:tags":[
        "shop",
        "good"
    ],
    "wof:name":"Fitness Factors",
    "wof:placetype":"venue"
},
  "geometry": {"coordinates":[-0.432328999,51.8954658508],"type":"Point"}
}