{
  "type": "Feature",
  "properties": {
    "iso:country":"GB",
    "sg:address":"Binders Industrial Estate, Cryers Hill Road, Cryers Hill",
    "sg:city":"High Wycombe",
    "sg:classifiers":[
        {
            "category":"Autos & Motor Vehicles",
            "subcategory":"Automobile Sales",
            "type":"Retail Goods"
        },
        {
            "category":"Retail",
            "subcategory":"Auto Repair",
            "type":"Services"
        }
    ],
    "sg:phone":"+44 1494 716727",
    "sg:postcode":"HP15 6LJ",
    "sg:province":"Buckinghamshire",
    "sg:tags":[
        "modification",
        "garage",
        "car"
    ],
    "wof:name":"Martin Jones Workshops",
    "wof:placetype":"venue"
},
  "geometry": {"coordinates":[-0.733873,51.662415],"type":"Point"}
}