{
  "type": "Feature",
  "properties": {
    "iso:country":"GB",
    "sg:address":"Main Road, Langrick",
    "sg:city":"Boston",
    "sg:classifiers":[
        {
            "category":"Bars & Pubs",
            "type":"Food & Drink"
        }
    ],
    "sg:postcode":"PE22 7AJ",
    "sg:province":"Lincolnshire",
    "sg:tags":[
        "pubs",
        "inn"
    ],
    "wof:name":"The Ferry Boat Inn",
    "wof:placetype":"venue"
},
  "geometry": {"coordinates":[-0.1071270034,53.0221481323],"type":"Point"}
}