{
  "type": "Feature",
  "properties": {
    "addr:full":"9 Market Place Chorley Lancashire PR7 1DA",
    "addr:housenumber":"9",
    "addr:postcode":"pr7 1da",
    "addr:street":"Market Place",
    "iso:country":"GB",
    "sg:address":"9 Market Place",
    "sg:city":"Chorley",
    "sg:classifiers":[
        {
            "category":"Shopping",
            "subcategory":"Department Store",
            "type":"Retail Goods"
        },
        {
            "category":"Shopping",
            "subcategory":"Comic Books",
            "type":"Retail Goods"
        }
    ],
    "sg:phone":"+44 1257 261050",
    "sg:postcode":"PR7 1DA",
    "sg:province":"Lancashire",
    "sg:tags":[
        "sale",
        "jewellery"
    ],
    "wof:name":"Krishan'S Jewellers",
    "wof:placetype":"venue"
},
  "geometry": {"coordinates":[-2.6325879097,53.653793335],"type":"Point"}
}