{
  "type": "Feature",
  "properties": {
    "addr:full":"1-3 Nelson Street Widnes Cheshire WA8 0QD",
    "addr:housenumber":"1-3",
    "addr:postcode":"wa8 0qd",
    "addr:street":"Nelson Street",
    "iso:country":"GB",
    "sg:address":"1-3 Nelson Street",
    "sg:city":"Widnes",
    "sg:classifiers":[
        {
            "category":"Government",
            "subcategory":"Department Of Motor Vehicles",
            "type":"Public Place"
        }
    ],
    "sg:phone":"+44 1254 693000",
    "sg:postcode":"WA8 0QD",
    "sg:province":"Cheshire",
    "sg:tags":[
        "engine",
        "component"
    ],
    "wof:name":"The Exhaust Agency",
    "wof:placetype":"venue"
},
  "geometry": {"coordinates":[-2.7357990742,53.356338501],"type":"Point"}
}