{
  "type": "Feature",
  "properties": {
    "addr:full":"27 Castle Street Inverness Highland IV2 3DU",
    "addr:housenumber":"27",
    "addr:postcode":"iv2 3du",
    "addr:street":"Castle Street",
    "iso:country":"GB",
    "sg:address":"27 Castle Street",
    "sg:city":"Inverness",
    "sg:classifiers":[
        {
            "category":"Bars & Pubs",
            "type":"Food & Drink"
        },
        {
            "category":"Community Center",
            "subcategory":"Social",
            "type":"Public Place"
        }
    ],
    "sg:phone":"+44 1463 241999",
    "sg:postcode":"IV2 3DU",
    "sg:province":"Highland",
    "sg:tags":[
        "pubs",
        "house",
        "inn",
        "activity"
    ],
    "wof:name":"Blaven Ltd.",
    "wof:placetype":"venue"
},
  "geometry": {"coordinates":[-4.2241392136,57.4769515991],"type":"Point"}
}