{
  "type": "Feature",
  "properties": {
    "addr:full":"Carrog, Noke Oxford Oxfordshire OX3 9TX",
    "addr:postcode":"ox3 9tx",
    "iso:country":"GB",
    "sg:address":"Carrog, Noke",
    "sg:city":"Oxford",
    "sg:classifiers":[
        {
            "category":"Building & Trades",
            "subcategory":"Construction",
            "type":"Services"
        }
    ],
    "sg:postcode":"OX3 9TX",
    "sg:province":"Oxfordshire",
    "sg:tags":[
        "builder"
    ],
    "wof:name":"R.M.R. Construction Ltd",
    "wof:placetype":"venue"
},
  "geometry": {"coordinates":[-1.211984,51.814419],"type":"Point"}
}