{
  "type": "Feature",
  "properties": {
    "iso:country":"GB",
    "sg:address":"153 Quill Street",
    "sg:city":"London",
    "sg:classifiers":[
        {
            "category":"Building & Trades",
            "subcategory":"Construction",
            "type":"Services"
        }
    ],
    "sg:postcode":"N4 2AE",
    "sg:province":"Greater London",
    "sg:tags":[
        "joinery",
        "joiner",
        "carpenter",
        "carpentry"
    ],
    "wof:name":"Vanessa Lake",
    "wof:placetype":"venue"
},
  "geometry": {"coordinates":[-0.105257,51.560165],"type":"Point"}
}