{
  "type": "Feature",
  "properties": {
    "iso:country":"GB",
    "sg:address":"25-27 Oxford Street",
    "sg:city":"Workington",
    "sg:classifiers":[
        {
            "category":"Shopping",
            "subcategory":"Pharmacy",
            "type":"Retail Goods"
        }
    ],
    "sg:phone":"+44 1900 603258",
    "sg:postcode":"CA14 2AL",
    "sg:province":"Cumbria",
    "sg:tags":[
        "pharmacist",
        "chemist"
    ],
    "wof:name":"Gourlays Chemist",
    "wof:placetype":"venue"
},
  "geometry": {"coordinates":[-3.551034,54.64365],"type":"Point"}
}