{
  "type": "Feature",
  "properties": {
    "iso:country":"GB",
    "sg:address":"12 Felstead Close",
    "sg:city":"Benfleet",
    "sg:classifiers":[
        {
            "category":"Building & Trades",
            "subcategory":"Construction",
            "type":"Services"
        }
    ],
    "sg:postcode":"SS7 1BX",
    "sg:province":"Essex",
    "sg:tags":[
        "heating",
        "contractor"
    ],
    "wof:name":"Hackforth Heating",
    "wof:placetype":"venue"
},
  "geometry": {"coordinates":[0.5622829795,51.560218811],"type":"Point"}
}