{
  "type": "Feature",
  "properties": {
    "addr:full":"345 Burnley Road East Rossendale Lancashire BB4 9JR",
    "addr:housenumber":"345",
    "addr:postcode":"bb4 9jr",
    "addr:street":"Burnley Road East",
    "iso:country":"GB",
    "sg:address":"345 Burnley Road East",
    "sg:city":"Rossendale",
    "sg:classifiers":[
        {
            "category":"Organizations",
            "subcategory":"Community Association",
            "type":"Services"
        },
        {
            "category":"Organizations",
            "subcategory":"Membership Organization",
            "type":"Services"
        }
    ],
    "sg:phone":"+44 1706 213067",
    "sg:postcode":"BB4 9JR",
    "sg:province":"Lancashire",
    "sg:tags":[
        "club",
        "social"
    ],
    "wof:name":"R A O B SOCIAL CLUB",
    "wof:placetype":"venue"
},
  "geometry": {"coordinates":[-2.2495100498,53.7049980164],"type":"Point"}
}