{
  "type": "Feature",
  "properties": {
    "addr:full":"78 George Street Perth Perth and Kinross PH1 5LB",
    "addr:housenumber":"78",
    "addr:postcode":"ph1 5lb",
    "addr:street":"George Street",
    "iso:country":"GB",
    "sg:address":"78 George Street",
    "sg:city":"Perth",
    "sg:classifiers":[
        {
            "category":"Museum",
            "type":"Entertainment"
        },
        {
            "category":"Museum",
            "subcategory":"Art Museum",
            "type":"Entertainment"
        },
        {
            "category":"Government",
            "subcategory":"Office",
            "type":"Public Place"
        }
    ],
    "sg:phone":"+44 1738 632488",
    "sg:postcode":"PH1 5LB",
    "sg:province":"Perth and Kinross",
    "sg:tags":[
        "local",
        "gallery"
    ],
    "wof:name":"Perth Museum & Art Gallery",
    "wof:placetype":"venue"
},
  "geometry": {"coordinates":[-3.4278550148,56.3982696533],"type":"Point"}
}