{
  "type": "Feature",
  "properties": {
    "addr:full":"12 Ormonde Avenue Salford Greater Manchester M6 8LP",
    "addr:housenumber":"12",
    "addr:postcode":"m6 8lp",
    "addr:street":"Ormonde Avenue",
    "iso:country":"GB",
    "sg:address":"12 Ormonde Avenue",
    "sg:city":"Salford",
    "sg:classifiers":[
        {
            "category":"Building & Trades",
            "subcategory":"Construction",
            "type":"Services"
        }
    ],
    "sg:phone":"+44 161 789 2470",
    "sg:postcode":"M6 8LP",
    "sg:province":"Greater Manchester",
    "sg:tags":[
        "decorator",
        "painter"
    ],
    "wof:name":"Stephen Mawdsley",
    "wof:placetype":"venue"
},
  "geometry": {"coordinates":[-2.3236529827,53.4950942993],"type":"Point"}
}