{
  "type": "Feature",
  "properties": {
    "addr:full":"9 Market St Leicester Leicestershire LE1 6DN",
    "addr:housenumber":"9",
    "addr:postcode":"le1 6dn",
    "addr:street":"Market St",
    "iso:country":"GB",
    "sg:address":"9 Market St",
    "sg:city":"Leicester",
    "sg:classifiers":[
        {
            "category":"Home & Garden",
            "subcategory":"Household Appliances",
            "type":"Retail Goods"
        }
    ],
    "sg:phone":"+44 116 254 8595",
    "sg:postcode":"LE1 6DN",
    "sg:province":"Leicestershire",
    "sg:tags":[
        "gas"
    ],
    "wof:name":"British Gas Energy Centre",
    "wof:placetype":"venue"
},
  "geometry": {"coordinates":[-1.133683,52.633244],"type":"Point"}
}