{
  "type": "Feature",
  "properties": {
    "addr:full":"295 Fleet Road Fleet Hampshire GU51 3BT",
    "addr:housenumber":"295",
    "addr:postcode":"gu51 3bt",
    "addr:street":"Fleet Road",
    "iso:country":"GB",
    "sg:address":"295 Fleet Road",
    "sg:city":"Fleet",
    "sg:classifiers":[
        {
            "category":"Food & Beverages",
            "subcategory":"Bakery",
            "type":"Retail Goods"
        }
    ],
    "sg:phone":"+44 1252 615051",
    "sg:postcode":"GU51 3BT",
    "sg:province":"Hampshire",
    "sg:tags":[
        "baker"
    ],
    "wof:name":"D R Wright & Sons",
    "wof:placetype":"venue"
},
  "geometry": {"coordinates":[-0.8375689983,51.2850112915],"type":"Point"}
}