{
  "type": "Feature",
  "properties": {
    "iso:country":"GB",
    "sg:address":"73 Ferniehill Rd",
    "sg:city":"Edinburgh",
    "sg:classifiers":[
        {
            "category":"Bars & Pubs",
            "type":"Food & Drink"
        }
    ],
    "sg:phone":"+44 131 666 0822",
    "sg:postcode":"EH17 7BN",
    "sg:province":"City of Edinburgh",
    "sg:tags":[
        "pubs",
        "inn"
    ],
    "wof:name":"Fernie Hill Inn",
    "wof:placetype":"venue"
},
  "geometry": {"coordinates":[-3.129971,55.910969],"type":"Point"}
}