{
  "type": "Feature",
  "properties": {
    "iso:country":"GB",
    "sg:address":"5 Keith Street",
    "sg:city":"Hamilton",
    "sg:classifiers":[
        {
            "category":"Professional",
            "subcategory":"Testing Lab",
            "type":"Services"
        }
    ],
    "sg:phone":"+44 1698 285914",
    "sg:postcode":"ML3 7BL",
    "sg:province":"South Lanarkshire",
    "sg:tags":[
        "inspection",
        "calibration"
    ],
    "wof:name":"N D T Kenged",
    "wof:placetype":"venue"
},
  "geometry": {"coordinates":[-4.0332422256,55.7763061523],"type":"Point"}
}