{
  "type": "Feature",
  "properties": {
    "iso:country":"GB",
    "sg:address":"11 West End",
    "sg:city":"Grantham",
    "sg:classifiers":[
        {
            "category":"Freight",
            "type":"Transportation"
        }
    ],
    "sg:phone":"+44 1476 594470",
    "sg:postcode":"NG32 1HE",
    "sg:province":"Leicestershire",
    "sg:tags":[
        "haulage",
        "road"
    ],
    "wof:name":"Mercury Transport UK",
    "wof:placetype":"venue"
},
  "geometry": {"coordinates":[-0.693798,52.883018],"type":"Point"}
}