{
  "type": "Feature",
  "properties": {
    "iso:country":"GB",
    "sg:address":"Rear, 119 Liverpool Road",
    "sg:city":"Preston",
    "sg:classifiers":[
        {
            "category":"Farming",
            "subcategory":"Nursery",
            "type":"Manufacturing & Wholesale Goods"
        },
        {
            "category":"Education",
            "subcategory":"Preschool",
            "type":"Public Place"
        }
    ],
    "sg:phone":"+44 1772 611233",
    "sg:postcode":"PR4 5AA",
    "sg:province":"Lancashire",
    "sg:tags":[
        "school",
        "creche"
    ],
    "wof:name":"Sunshine Nursery",
    "wof:placetype":"venue"
},
  "geometry": {"coordinates":[-2.758331,53.735889],"type":"Point"}
}