{
  "type": "Feature",
  "properties": {
    "addr:full":"Durham Office, County Hall Durham Durham DH1 5UE",
    "addr:postcode":"dh1 5ue",
    "iso:country":"GB",
    "sg:address":"Durham Office, County Hall",
    "sg:city":"Durham",
    "sg:classifiers":[
        {
            "category":"Communications",
            "type":"Services"
        },
        {
            "category":"Communications",
            "subcategory":"Television Station",
            "type":"Services"
        }
    ],
    "sg:phone":"+44 191 384 0199",
    "sg:postcode":"DH1 5UE",
    "sg:province":"Durham",
    "sg:tags":[
        "operator",
        "broadcasting",
        "radio"
    ],
    "wof:name":"B B C Radio Newcastle & Cleveland",
    "wof:placetype":"venue"
},
  "geometry": {"coordinates":[-1.574608,54.777534],"type":"Point"}
}