{
  "type": "Feature",
  "properties": {
    "iso:country":"GB",
    "sg:address":"70 Coxmoor Church, Cookham",
    "sg:city":"Fleet",
    "sg:classifiers":[
        {
            "category":"Professional",
            "subcategory":"Management & Consulting",
            "type":"Services"
        }
    ],
    "sg:postcode":"GU52 6ET",
    "sg:province":"Hampshire",
    "sg:tags":[
        "consultant",
        "business"
    ],
    "wof:name":"Virtual Learning Co Ltd",
    "wof:placetype":"venue"
},
  "geometry": {"coordinates":[-0.8254550099,51.2653465271],"type":"Point"}
}