{
  "type": "Feature",
  "properties": {
    "addr:full":"26 Wilfred St London Greater London SW1E 6PL",
    "addr:housenumber":"26",
    "addr:postcode":"sw1e 6pl",
    "addr:street":"Wilfred St",
    "iso:country":"GB",
    "sg:address":"26 Wilfred St",
    "sg:city":"London",
    "sg:classifiers":[
        {
            "category":"Real Estate",
            "subcategory":"Real Estate Agent",
            "type":"Services"
        }
    ],
    "sg:postcode":"SW1E 6PL",
    "sg:province":"Greater London",
    "wof:name":"Sawyer Properties Ltd",
    "wof:placetype":"venue"
},
  "geometry": {"coordinates":[-0.140301,51.498539],"type":"Point"}
}