{
  "type": "Feature",
  "properties": {
    "addr:full":"Guildford Road Trading Estate Farnham Surrey GU9 9PZ",
    "addr:postcode":"gu9 9pz",
    "addr:street":"Guildford Road Trading Estate",
    "iso:country":"GB",
    "sg:address":"Guildford Road Trading Estate",
    "sg:city":"Farnham",
    "sg:classifiers":[
        {
            "category":"Home & Garden",
            "subcategory":"Hardware",
            "type":"Retail Goods"
        }
    ],
    "sg:phone":"+44 1252 717180",
    "sg:postcode":"GU9 9PZ",
    "sg:province":"Surrey",
    "sg:tags":[
        "retailer",
        "diy"
    ],
    "wof:name":"Homebase Ltd.",
    "wof:placetype":"venue"
},
  "geometry": {"coordinates":[-0.7848039865,51.2190666199],"type":"Point"}
}