{
  "type": "Feature",
  "properties": {
    "addr:full":"Unit 18, Walton Business Centre Walton-on-thames Surrey KT12 2SD",
    "addr:housenumber":"unit 18;business",
    "addr:postcode":"kt12 2sd",
    "addr:street":"Walton;Walton-On-Thames",
    "iso:country":"GB",
    "sg:address":"Unit 18, Walton Business Centre",
    "sg:city":"Walton-on-thames",
    "sg:classifiers":[
        {
            "category":"Professional",
            "subcategory":"Business Services",
            "type":"Services"
        }
    ],
    "sg:phone":"+44 20 8428 0111",
    "sg:postcode":"KT12 2SD",
    "sg:province":"Surrey",
    "sg:tags":[
        "import",
        "export",
        "agent"
    ],
    "wof:name":"Wotek Corp",
    "wof:placetype":"venue"
},
  "geometry": {"coordinates":[-0.4207040071,51.3843460083],"type":"Point"}
}