{
  "type": "Feature",
  "properties": {
    "iso:country":"GB",
    "sg:address":"11 Berkeley Square",
    "sg:city":"Bristol",
    "sg:classifiers":[
        {
            "category":"Professional",
            "subcategory":"Lawyer & Legal Services",
            "type":"Services"
        }
    ],
    "sg:postcode":"BS8 1HG",
    "sg:province":"City of Bristol",
    "sg:tags":[
        "conveyancing"
    ],
    "wof:name":"Roy Coles & Co",
    "wof:placetype":"venue"
},
  "geometry": {"coordinates":[-2.606664,51.455082],"type":"Point"}
}