{
  "type": "Feature",
  "properties": {
    "iso:country":"GB",
    "sg:address":"192 Kilburn High Road",
    "sg:city":"London",
    "sg:classifiers":[
        {
            "category":"Shopping",
            "subcategory":"Clothing, Apparel, & Fashions",
            "type":"Retail Goods"
        }
    ],
    "sg:postcode":"NW6 4JD",
    "sg:province":"Greater London",
    "sg:tags":[
        "menswear"
    ],
    "wof:name":"Charmingchance Ltd.",
    "wof:placetype":"venue"
},
  "geometry": {"coordinates":[-0.196319,51.540539],"type":"Point"}
}