{
  "type": "Feature",
  "properties": {
    "addr:full":"Unit 3 Little Shellwood Farm, Clayhill Road Reigate Surrey RH2 8PA",
    "addr:housenumber":"unit 3;farm",
    "addr:postcode":"rh2 8pa",
    "addr:street":"Little Shellwood;Clayhill Road",
    "iso:country":"GB",
    "sg:address":"Unit 3 Little Shellwood Farm, Clayhill Road",
    "sg:city":"Reigate",
    "sg:classifiers":[
        {
            "category":"Professional",
            "type":"Services"
        }
    ],
    "sg:phone":"+44 1306 611100",
    "sg:postcode":"RH2 8PA",
    "sg:province":"Surrey",
    "sg:tags":[
        "marine"
    ],
    "sg:website":"http://www.plancraft.co.uk",
    "wof:name":"Plancraft Marine Ltd",
    "wof:placetype":"venue"
},
  "geometry": {"coordinates":[-0.204779,51.235744],"type":"Point"}
}