{
  "type": "Feature",
  "properties": {
    "addr:full":"2 Meadow Cotts Rochdale Lancashire OL12 8LH",
    "addr:housenumber":"2;cotts",
    "addr:postcode":"ol12 8lh",
    "addr:street":"Meadow",
    "iso:country":"GB",
    "sg:address":"2 Meadow Cotts",
    "sg:city":"Rochdale",
    "sg:classifiers":[
        {
            "category":"Food & Beverages",
            "subcategory":"Meat & Fish",
            "type":"Retail Goods"
        }
    ],
    "sg:phone":"+44 1706 853098",
    "sg:postcode":"OL12 8LH",
    "sg:province":"Lancashire",
    "sg:tags":[
        "chip"
    ],
    "wof:name":"Half Way Chippy",
    "wof:placetype":"venue"
},
  "geometry": {"coordinates":[-2.1707510948,53.6685752869],"type":"Point"}
}