{
  "type": "Feature",
  "properties": {
    "addr:full":"1071 South St Glasgow Glasgow City G14 0DW",
    "addr:housenumber":"1071",
    "addr:postcode":"g14 0dw",
    "addr:street":"South St",
    "iso:country":"GB",
    "sg:address":"1071 South St",
    "sg:city":"Glasgow",
    "sg:classifiers":[
        {
            "category":"Manufacturing",
            "subcategory":"Tools & Machinery",
            "type":"Manufacturing & Wholesale Goods"
        }
    ],
    "sg:phone":"+44 141 958 1000",
    "sg:postcode":"G14 0DW",
    "sg:province":"Glasgow City",
    "wof:name":"Govan Machine Tool Co",
    "wof:placetype":"venue"
},
  "geometry": {"coordinates":[-4.350504,55.876259],"type":"Point"}
}