{
  "type": "Feature",
  "properties": {
    "addr:full":"30 Heath Road, Hortle New Milton Hampshire SO41 0GG",
    "addr:housenumber":"30",
    "addr:postcode":"so41 0gg",
    "addr:street":"Heath Road",
    "iso:country":"GB",
    "sg:address":"30 Heath Road, Hortle",
    "sg:city":"New Milton",
    "sg:classifiers":[
        {
            "category":"Retail",
            "subcategory":"Storage",
            "type":"Services"
        }
    ],
    "sg:phone":"+44 1425 619074",
    "sg:postcode":"SO41 0GG",
    "sg:province":"Hampshire",
    "sg:tags":[
        "household",
        "removal"
    ],
    "wof:name":"Fairfreight Newforest Removals",
    "wof:placetype":"venue"
},
  "geometry": {"coordinates":[-1.6243699789,50.7553405762],"type":"Point"}
}