{
  "type": "Feature",
  "properties": {
    "addr:full":"Unit 2 Live Wire Business Centre, Ysgubo, Cwmbwrla Swansea Neath Port Talbot SA1 2DD",
    "addr:housenumber":"unit 2",
    "addr:postcode":"sa1 2dd",
    "iso:country":"GB",
    "sg:address":"Unit 2 Live Wire Business Centre, Ysgubo, Cwmbwrla",
    "sg:city":"Swansea",
    "sg:classifiers":[
        {
            "category":"Building & Trades",
            "subcategory":"Plumbing",
            "type":"Services"
        }
    ],
    "sg:postcode":"SA1 2DD",
    "sg:province":"Neath Port Talbot",
    "sg:tags":[
        "heating"
    ],
    "wof:name":"Harris,P C,",
    "wof:placetype":"venue"
},
  "geometry": {"coordinates":[-3.940928936,51.6231536865],"type":"Point"}
}