{
  "type": "Feature",
  "properties": {
    "iso:country":"GB",
    "sg:address":"Kinswood Farm, Lackenhurst Lane, Brooks Grn",
    "sg:city":"Horsham",
    "sg:classifiers":[
        {
            "category":"Farming",
            "subcategory":"Farm",
            "type":"Manufacturing & Wholesale Goods"
        }
    ],
    "sg:phone":"+44 1403 741559",
    "sg:postcode":"RH13 0JL",
    "sg:province":"West Sussex",
    "sg:tags":[
        "egg",
        "producer"
    ],
    "wof:name":"Kinswood Eggs Ltd.",
    "wof:placetype":"venue"
},
  "geometry": {"coordinates":[-0.3883999884,51.0103683472],"type":"Point"}
}