{
  "type": "Feature",
  "properties": {
    "iso:country":"GB",
    "sg:address":"3 Tubwell Road",
    "sg:city":"Slough",
    "sg:classifiers":[
        {
            "category":"Building & Trades",
            "subcategory":"Plumbing",
            "type":"Services"
        }
    ],
    "sg:postcode":"SL2 4JT",
    "sg:province":"Berkshire",
    "sg:tags":[
        "central",
        "heating"
    ],
    "wof:name":"M K Heating Engineers",
    "wof:placetype":"venue"
},
  "geometry": {"coordinates":[-0.574029,51.542805],"type":"Point"}
}