{
  "type": "Feature",
  "properties": {
    "addr:full":"Caretakerosmond House Flats, Croscombe Walk Bradford West Yorkshire BD5 0RR",
    "addr:housenumber":"flats",
    "addr:postcode":"bd5 0rr",
    "addr:street":"Croscombe Walk",
    "iso:country":"GB",
    "sg:address":"Caretakerosmond House Flats, Croscombe Walk",
    "sg:city":"Bradford",
    "sg:classifiers":[
        {
            "category":"Government",
            "subcategory":"Office",
            "type":"Public Place"
        }
    ],
    "sg:phone":"+44 1274 725398",
    "sg:postcode":"BD5 0RR",
    "sg:province":"West Yorkshire",
    "sg:tags":[
        "local"
    ],
    "wof:name":"Bradford Metropolitan District Council",
    "wof:placetype":"venue"
},
  "geometry": {"coordinates":[-1.7564640045,53.786819458],"type":"Point"}
}