{
  "type": "Feature",
  "properties": {
    "addr:full":"Care Of Cherwell District Council, Bodicote Ho Banbury Oxfordshire OX15 4AA",
    "addr:postcode":"ox15 4aa",
    "iso:country":"GB",
    "sg:address":"Care Of Cherwell District Council, Bodicote Ho",
    "sg:city":"Banbury",
    "sg:classifiers":[
        {
            "category":"Professional",
            "subcategory":"Computer Services",
            "type":"Services"
        }
    ],
    "sg:phone":"+44 1295 250655",
    "sg:postcode":"OX15 4AA",
    "sg:province":"Oxfordshire",
    "sg:tags":[
        "information"
    ],
    "wof:name":"Bretchill Community Association",
    "wof:placetype":"venue"
},
  "geometry": {"coordinates":[-1.322803,52.038479],"type":"Point"}
}