{
  "type": "Feature",
  "properties": {
    "iso:country":"GB",
    "sg:address":"41 Britannia Square",
    "sg:city":"Worcester",
    "sg:classifiers":[
        {
            "category":"Food & Beverages",
            "subcategory":"Groceries & Convenience Stores",
            "type":"Retail Goods"
        }
    ],
    "sg:phone":"+44 1905 724990",
    "sg:postcode":"WR1 3DN",
    "sg:province":"Worcestershire",
    "wof:name":"West Mercia Convenience Stores",
    "wof:placetype":"venue"
},
  "geometry": {"coordinates":[-2.2267599106,52.1996841431],"type":"Point"}
}