{
  "type": "Feature",
  "properties": {
    "addr:full":"226 Nantwich Road Crewe Cheshire CW2 6BP",
    "addr:housenumber":"226",
    "addr:postcode":"cw2 6bp",
    "addr:street":"Nantwich Road",
    "iso:country":"GB",
    "sg:address":"226 Nantwich Road",
    "sg:city":"Crewe",
    "sg:classifiers":[
        {
            "category":"Real Estate",
            "subcategory":"Real Estate Agent",
            "type":"Services"
        }
    ],
    "sg:phone":"+44 1270 500833",
    "sg:postcode":"CW2 6BP",
    "sg:province":"Cheshire",
    "wof:name":"Beresford Adams",
    "wof:placetype":"venue"
},
  "geometry": {"coordinates":[-2.4468650818,53.0870399475],"type":"Point"}
}