{
  "type": "Feature",
  "properties": {
    "addr:full":"10 Coronation Rd Newcastle-upon-tyne Tyne and Wear NE5 1PU",
    "addr:housenumber":"10",
    "addr:postcode":"ne5 1pu",
    "addr:street":"Coronation Rd",
    "iso:country":"GB",
    "sg:address":"10 Coronation Rd",
    "sg:city":"Newcastle-upon-tyne",
    "sg:classifiers":[
        {
            "category":"Building & Trades",
            "subcategory":"Construction",
            "type":"Services"
        }
    ],
    "sg:postcode":"NE5 1PU",
    "sg:province":"Tyne and Wear",
    "sg:tags":[
        "builder"
    ],
    "wof:name":"R M B Builders",
    "wof:placetype":"venue"
},
  "geometry": {"coordinates":[-1.724586,55.000816],"type":"Point"}
}