{
  "type": "Feature",
  "properties": {
    "addr:full":"7 Windmill Way Reigate Surrey RH2 0JB",
    "addr:housenumber":"7",
    "addr:postcode":"rh2 0jb",
    "addr:street":"Windmill Way",
    "iso:country":"GB",
    "sg:address":"7 Windmill Way",
    "sg:city":"Reigate",
    "sg:classifiers":[
        {
            "category":"Building & Trades",
            "subcategory":"Construction",
            "type":"Services"
        }
    ],
    "sg:postcode":"RH2 0JB",
    "sg:province":"Surrey",
    "sg:tags":[
        "builder"
    ],
    "wof:name":"The Oaks Building Co.",
    "wof:placetype":"venue"
},
  "geometry": {"coordinates":[-0.183812,51.246758],"type":"Point"}
}