{
  "type": "Feature",
  "properties": {
    "addr:full":"Chute House, Church Street Basingstoke Hampshire RG21 7QT",
    "addr:postcode":"rg21 7qt",
    "addr:street":"Church Street",
    "iso:country":"GB",
    "sg:address":"Chute House, Church Street",
    "sg:city":"Basingstoke",
    "sg:classifiers":[
        {
            "category":"Organizations",
            "subcategory":"Non-profit Organization",
            "type":"Services"
        }
    ],
    "sg:phone":"+44 1256 473350",
    "sg:postcode":"RG21 7QT",
    "sg:province":"Hampshire",
    "sg:tags":[
        "organisation",
        "voluntary",
        "charity"
    ],
    "wof:name":"Wel-Care",
    "wof:placetype":"venue"
},
  "geometry": {"coordinates":[-1.088735,51.265869],"type":"Point"}
}