{
  "type": "Feature",
  "properties": {
    "iso:country":"GB",
    "sg:address":"1 Main Street, Kilsyth",
    "sg:city":"Glasgow",
    "sg:classifiers":[
        {
            "category":"Food & Beverages",
            "subcategory":"Meat & Fish",
            "type":"Retail Goods"
        }
    ],
    "sg:phone":"+44 1236 821211",
    "sg:postcode":"G65 0AH",
    "sg:province":"East Dunbartonshire",
    "sg:tags":[
        "butcher"
    ],
    "wof:name":"The Cross Butchers Ltd.",
    "wof:placetype":"venue"
},
  "geometry": {"coordinates":[-4.057229,55.97784],"type":"Point"}
}