{
  "type": "Feature",
  "properties": {
    "addr:full":"4 Charles St, Higher Hill Gate Stockport Cheshire SK1 3JR",
    "addr:housenumber":"4",
    "addr:postcode":"sk1 3jr",
    "addr:street":"Charles St Higher Hill Gate",
    "iso:country":"GB",
    "sg:address":"4 Charles St, Higher Hill Gate",
    "sg:city":"Stockport",
    "sg:classifiers":[
        {
            "category":"Manufacturing",
            "subcategory":"Metals",
            "type":"Manufacturing & Wholesale Goods"
        }
    ],
    "sg:phone":"+44 161 429 0832",
    "sg:postcode":"SK1 3JR",
    "sg:province":"Cheshire",
    "sg:tags":[
        "steel",
        "fabricator",
        "erectors"
    ],
    "wof:name":"Falco Pipe & Steel Fabrication",
    "wof:placetype":"venue"
},
  "geometry": {"coordinates":[-2.1517999172,53.4006271362],"type":"Point"}
}