{
  "type": "Feature",
  "properties": {
    "addr:full":"25 Orchard Close Presteigne Herefordshire LD8 2HF",
    "addr:housenumber":"25",
    "addr:postcode":"ld8 2hf",
    "addr:street":"Orchard Close",
    "iso:country":"GB",
    "sg:address":"25 Orchard Close",
    "sg:city":"Presteigne",
    "sg:classifiers":[
        {
            "category":"Home & Garden",
            "subcategory":"Carpets & Floor Coverings",
            "type":"Retail Goods"
        }
    ],
    "sg:phone":"+44 1544 260070",
    "sg:postcode":"LD8 2HF",
    "sg:province":"Herefordshire",
    "sg:tags":[
        "textile",
        "floorcoverings"
    ],
    "wof:name":"Chase Flooring",
    "wof:placetype":"venue"
},
  "geometry": {"coordinates":[-3.0015890598,52.2711410522],"type":"Point"}
}