{
  "type": "Feature",
  "properties": {
    "iso:country":"GB",
    "sg:address":"Penrhos Industrial Estate, Penrhos",
    "sg:city":"Holyhead",
    "sg:classifiers":[
        {
            "category":"Food & Beverages",
            "subcategory":"Supermarket",
            "type":"Retail Goods"
        }
    ],
    "sg:phone":"+44 845 677 9356",
    "sg:postcode":"LL65 2UH",
    "sg:province":"Isle of Anglesey",
    "sg:website":"http://www.tesco.com",
    "wof:name":"Tesco Stores Ltd.",
    "wof:placetype":"venue"
},
  "geometry": {"coordinates":[-4.630714,53.30637],"type":"Point"}
}