{
  "type": "Feature",
  "properties": {
    "iso:country":"GB",
    "sg:address":"Skeyton Road Studio, Skeyton Road",
    "sg:city":"North Walsham",
    "sg:classifiers":[
        {
            "category":"Professional",
            "type":"Services"
        }
    ],
    "sg:postcode":"NR28 0JG",
    "sg:province":"Norfolk",
    "sg:tags":[
        "interior",
        "furnishers",
        "designer"
    ],
    "wof:name":"Skeyton Road Studio",
    "wof:placetype":"venue"
},
  "geometry": {"coordinates":[1.376447,52.818729],"type":"Point"}
}