{
  "type": "Feature",
  "properties": {
    "iso:country":"GB",
    "sg:address":"Unit 8, Acorn Business Centre, Wing",
    "sg:city":"Leighton Buzzard",
    "sg:classifiers":[
        {
            "category":"Home & Garden",
            "subcategory":"Home Furnishings",
            "type":"Retail Goods"
        }
    ],
    "sg:phone":"+44 1296 681965",
    "sg:postcode":"LU7 0LB",
    "sg:province":"Bedfordshire",
    "sg:tags":[
        "blind",
        "curtain",
        "fitting"
    ],
    "wof:name":"Polonaise",
    "wof:placetype":"venue"
},
  "geometry": {"coordinates":[-0.714999,51.897835],"type":"Point"}
}