{
  "type": "Feature",
  "properties": {
    "iso:country":"GB",
    "sg:address":"Grovewood Business Centre, Strathclyde Business Park",
    "sg:city":"Bellshill",
    "sg:classifiers":[
        {
            "category":"Retail",
            "subcategory":"Repair Shop",
            "type":"Services"
        }
    ],
    "sg:phone":"+44 1698 843117",
    "sg:postcode":"ML4 3NQ",
    "sg:province":"North Lanarkshire",
    "sg:tags":[
        "sharpening",
        "tool"
    ],
    "wof:name":"Leitz Tooling (Uk)",
    "wof:placetype":"venue"
},
  "geometry": {"coordinates":[-4.0358009338,55.8203048706],"type":"Point"}
}