{
  "type": "Feature",
  "properties": {
    "addr:full":"30 Newbery Road, Slade Grn Erith Kent DA8 2BY",
    "addr:housenumber":"30",
    "addr:postcode":"da8 2by",
    "addr:street":"Newbery Road",
    "iso:country":"GB",
    "sg:address":"30 Newbery Road, Slade Grn",
    "sg:city":"Erith",
    "sg:classifiers":[
        {
            "category":"Building & Trades",
            "subcategory":"Cleaning & Sanitation",
            "type":"Services"
        }
    ],
    "sg:phone":"+44 1322 332024",
    "sg:postcode":"DA8 2BY",
    "sg:province":"Kent",
    "sg:tags":[
        "dry",
        "control",
        "damp",
        "rot"
    ],
    "wof:name":"Dampcheck",
    "wof:placetype":"venue"
},
  "geometry": {"coordinates":[0.183126,51.470181],"type":"Point"}
}