{
  "type": "Feature",
  "properties": {
    "addr:full":"Thurstaston Road, Heswall Wirral Merseyside CH60 3SL",
    "addr:postcode":"ch60 3sl",
    "addr:street":"Thurstaston Road",
    "iso:country":"GB",
    "sg:address":"Thurstaston Road, Heswall",
    "sg:city":"Wirral",
    "sg:classifiers":[
        {
            "category":"Education",
            "subcategory":"Preschool",
            "type":"Public Place"
        }
    ],
    "sg:phone":"+44 151 342 9909",
    "sg:postcode":"CH60 3SL",
    "sg:province":"Merseyside",
    "sg:tags":[
        "pre-school",
        "playgroups"
    ],
    "wof:name":"St.Peters Church of England Pre School Playgroup",
    "wof:placetype":"venue"
},
  "geometry": {"coordinates":[-3.0793199539,53.3172988892],"type":"Point"}
}