{
  "type": "Feature",
  "properties": {
    "iso:country":"GB",
    "sg:address":"188-192 Saltash Road, Keyham",
    "sg:city":"Plymouth",
    "sg:classifiers":[
        {
            "category":"Bars & Pubs",
            "type":"Food & Drink"
        }
    ],
    "sg:phone":"+44 1752 562143",
    "sg:postcode":"PL2 2BD",
    "sg:province":"Devon",
    "sg:tags":[
        "pubs",
        "inn"
    ],
    "wof:name":"The Royal Naval Arms",
    "wof:placetype":"venue"
},
  "geometry": {"coordinates":[-4.1801347733,50.3895378113],"type":"Point"}
}