{
  "type": "Feature",
  "properties": {
    "iso:country":"GB",
    "sg:address":"47 Newington Green Road",
    "sg:city":"London",
    "sg:classifiers":[
        {
            "category":"Personal",
            "subcategory":"Barber",
            "type":"Services"
        }
    ],
    "sg:phone":"+44 20 7226 8763",
    "sg:postcode":"N1 4QT",
    "sg:province":"Greater London",
    "sg:tags":[
        "men's",
        "gents",
        "hairdresser"
    ],
    "wof:name":"Serens Hair Gents Hair Stylist",
    "wof:placetype":"venue"
},
  "geometry": {"coordinates":[-0.087579,51.54834],"type":"Point"}
}