{
  "type": "Feature",
  "properties": {
    "addr:full":"19 Aughton Street Ormskirk Lancashire L39 3BH",
    "addr:housenumber":"19",
    "addr:postcode":"l39 3bh",
    "addr:street":"Aughton Street",
    "iso:country":"GB",
    "sg:address":"19 Aughton Street",
    "sg:city":"Ormskirk",
    "sg:classifiers":[
        {
            "category":"Community Center",
            "subcategory":"Social",
            "type":"Public Place"
        }
    ],
    "sg:phone":"+44 1695 577797",
    "sg:postcode":"L39 3BH",
    "sg:province":"Lancashire",
    "sg:tags":[
        "frozen",
        "food",
        "freezer",
        "centre"
    ],
    "wof:name":"Iceland Foods Plc",
    "wof:placetype":"venue"
},
  "geometry": {"coordinates":[-2.886491,53.566692],"type":"Point"}
}