{
  "type": "Feature",
  "properties": {
    "iso:country":"GB",
    "sg:address":"21 East Barnet Road",
    "sg:city":"Barnet",
    "sg:classifiers":[
        {
            "category":"Shopping",
            "subcategory":"News",
            "type":"Retail Goods"
        }
    ],
    "sg:phone":"+44 20 8449 2816",
    "sg:postcode":"EN4 8RN",
    "sg:province":"Hertfordshire",
    "sg:tags":[
        "newsagent"
    ],
    "wof:name":"Aldertons",
    "wof:placetype":"venue"
},
  "geometry": {"coordinates":[-0.172005,51.65015],"type":"Point"}
}