{
  "type": "Feature",
  "properties": {
    "addr:full":"269a London Road, Leftwhich Northwich Cheshire CW9 8HD",
    "addr:housenumber":"269a",
    "addr:postcode":"cw9 8hd",
    "addr:street":"London Road Leftwhich",
    "iso:country":"GB",
    "sg:address":"269a London Road, Leftwhich",
    "sg:city":"Northwich",
    "sg:classifiers":[
        {
            "category":"Social Services",
            "subcategory":"Adult Care",
            "type":"Services"
        },
        {
            "category":"Government",
            "subcategory":"Office",
            "type":"Public Place"
        }
    ],
    "sg:phone":"+44 1606 46040",
    "sg:postcode":"CW9 8HD",
    "sg:province":"Cheshire",
    "sg:tags":[
        "housing",
        "local",
        "sheltered"
    ],
    "wof:name":"Sheltered Housing Control Centre",
    "wof:placetype":"venue"
},
  "geometry": {"coordinates":[-2.5100638866,53.246547699],"type":"Point"}
}