{
  "type": "Feature",
  "properties": {
    "addr:full":"Hemsby Holliday Village, Beach Rd Great Yarmouth Norfolk NR29 4HL",
    "addr:housenumber":"hemsby",
    "addr:postcode":"nr29 4hl",
    "addr:street":"Village Beach Rd",
    "iso:country":"GB",
    "sg:address":"Hemsby Holliday Village, Beach Rd",
    "sg:city":"Great Yarmouth",
    "sg:classifiers":[
        {
            "category":"Recreation",
            "subcategory":"Campground",
            "type":"Entertainment"
        }
    ],
    "sg:phone":"+44 870 601 0478",
    "sg:postcode":"NR29 4HL",
    "sg:province":"Norfolk",
    "sg:tags":[
        "holiday",
        "centre",
        "camp"
    ],
    "wof:name":"Pontins",
    "wof:placetype":"venue"
},
  "geometry": {"coordinates":[1.6921299696,52.6979560852],"type":"Point"}
}