{
  "type": "Feature",
  "properties": {
    "addr:full":"88 High St Devizes Wiltshire SN10 5RU",
    "addr:housenumber":"88",
    "addr:postcode":"sn10 5ru",
    "addr:street":"High St",
    "iso:country":"GB",
    "sg:address":"88 High St",
    "sg:city":"Devizes",
    "sg:classifiers":[
        {
            "category":"Shopping",
            "subcategory":"Department Store",
            "type":"Retail Goods"
        }
    ],
    "sg:phone":"+44 1380 722393",
    "sg:postcode":"SN10 5RU",
    "sg:province":"Wiltshire",
    "wof:name":"Village Store",
    "wof:placetype":"venue"
},
  "geometry": {"coordinates":[-2.0241379738,51.2887496948],"type":"Point"}
}