{
  "type": "Feature",
  "properties": {
    "iso:country":"GB",
    "sg:address":"53 Silver Street",
    "sg:city":"Lyme Regis",
    "sg:classifiers":[
        {
            "category":"Personal",
            "subcategory":"Beauty Salon",
            "type":"Services"
        }
    ],
    "sg:phone":"+44 1297 442918",
    "sg:postcode":"DT7 3HR",
    "sg:province":"Devon",
    "sg:tags":[
        "unisex",
        "hairdresser"
    ],
    "wof:name":"Hair by Julie",
    "wof:placetype":"venue"
},
  "geometry": {"coordinates":[-2.937042,50.725513],"type":"Point"}
}