{
  "type": "Feature",
  "properties": {
    "addr:full":"136 High Street, Porthadoc Porthmadog Gwynedd LL49 9NU",
    "addr:housenumber":"136",
    "addr:postcode":"ll49 9nu",
    "addr:street":"High Street;Porthmadog",
    "iso:country":"GB",
    "sg:address":"136 High Street, Porthadoc",
    "sg:city":"Porthmadog",
    "sg:classifiers":[
        {
            "category":"Food & Beverages",
            "subcategory":"Liquor & Beverages",
            "type":"Retail Goods"
        }
    ],
    "sg:phone":"+44 1766 512834",
    "sg:postcode":"LL49 9NU",
    "sg:province":"Gwynedd",
    "sg:tags":[
        "beer",
        "spirit",
        "wines"
    ],
    "wof:name":"Thresher Wine Shop",
    "wof:placetype":"venue"
},
  "geometry": {"coordinates":[-4.139729023,52.9402503967],"type":"Point"}
}