{
  "type": "Feature",
  "properties": {
    "addr:full":"60 Nile St North Shields Tyne and Wear NE29 0BG",
    "addr:housenumber":"60",
    "addr:postcode":"ne29 0bg",
    "addr:street":"Nile St",
    "iso:country":"GB",
    "sg:address":"60 Nile St",
    "sg:city":"North Shields",
    "sg:classifiers":[
        {
            "category":"Bars & Pubs",
            "type":"Food & Drink"
        }
    ],
    "sg:phone":"+44 191 257 5905",
    "sg:postcode":"NE29 0BG",
    "sg:province":"Tyne and Wear",
    "sg:tags":[
        "pubs",
        "inn"
    ],
    "wof:name":"Royal Arms",
    "wof:placetype":"venue"
},
  "geometry": {"coordinates":[-1.448546052,55.0090141296],"type":"Point"}
}