{
  "type": "Feature",
  "properties": {
    "addr:full":"10 Church Street Spalding Cambridgeshire PE12 7LL",
    "addr:housenumber":"10",
    "addr:postcode":"pe12 7ll",
    "addr:street":"Church Street Spalding",
    "iso:country":"GB",
    "sg:address":"10 Church Street",
    "sg:city":"Spalding",
    "sg:classifiers":[
        {
            "category":"Food & Beverages",
            "subcategory":"Meat & Fish",
            "type":"Retail Goods"
        }
    ],
    "sg:postcode":"PE12 7LL",
    "sg:province":"Cambridgeshire",
    "sg:tags":[
        "chip"
    ],
    "wof:name":"Barries Fish Bar",
    "wof:placetype":"venue"
},
  "geometry": {"coordinates":[0.0134779997,52.8036193848],"type":"Point"}
}