{
  "type": "Feature",
  "properties": {
    "iso:country":"GB",
    "sg:address":"27a Boothtown Rd",
    "sg:city":"Halifax",
    "sg:classifiers":[
        {
            "category":"Retail",
            "subcategory":"Laundry & Dry Cleaning",
            "type":"Services"
        }
    ],
    "sg:postcode":"HX3 6EU",
    "sg:province":"West Yorkshire",
    "sg:tags":[
        "launderette"
    ],
    "wof:name":"Beavers,Graham,",
    "wof:placetype":"venue"
},
  "geometry": {"coordinates":[-1.865127,53.733372],"type":"Point"}
}