{
  "type": "Feature",
  "properties": {
    "addr:full":"30 West King St Helensburgh Argyll and Bute G84 8EB",
    "addr:housenumber":"30",
    "addr:postcode":"g84 8eb",
    "addr:street":"West King St",
    "iso:country":"GB",
    "sg:address":"30 West King St",
    "sg:city":"Helensburgh",
    "sg:classifiers":[
        {
            "category":"Utilities",
            "subcategory":"Refuse",
            "type":"Services"
        }
    ],
    "sg:phone":"+44 1436 672070",
    "sg:postcode":"G84 8EB",
    "sg:province":"Argyll and Bute",
    "sg:tags":[
        "skip",
        "hire"
    ],
    "wof:name":"John Caldwell",
    "wof:placetype":"venue"
},
  "geometry": {"coordinates":[-4.7597560883,56.0175247192],"type":"Point"}
}