{
  "type": "Feature",
  "properties": {
    "addr:full":"Northlands Park, Felmores Basildon Essex SS13 1SD",
    "addr:postcode":"ss13 1sd",
    "addr:street":"Northlands;Felmores",
    "iso:country":"GB",
    "sg:address":"Northlands Park, Felmores",
    "sg:city":"Basildon",
    "sg:classifiers":[
        {
            "category":"Community Center",
            "type":"Public Place"
        }
    ],
    "sg:phone":"+44 1268 583430",
    "sg:postcode":"SS13 1SD",
    "sg:province":"Essex",
    "sg:tags":[
        "centre"
    ],
    "wof:name":"Northlands Park Community Centre",
    "wof:placetype":"venue"
},
  "geometry": {"coordinates":[0.49922,51.57914],"type":"Point"}
}