{
  "type": "Feature",
  "properties": {
    "iso:country":"GB",
    "sg:address":"Shepherds Farm, Middleton Rd",
    "sg:city":"Rickmansworth",
    "sg:classifiers":[
        {
            "category":"Farming",
            "subcategory":"Dairy Farm",
            "type":"Manufacturing & Wholesale Goods"
        }
    ],
    "sg:phone":"+44 1923 775791",
    "sg:postcode":"WD3 8JD",
    "sg:province":"Hertfordshire",
    "wof:name":"Express Dairy Ltd",
    "wof:placetype":"venue"
},
  "geometry": {"coordinates":[-0.468275,51.641438],"type":"Point"}
}