{
  "type": "Feature",
  "properties": {
    "addr:full":"35 Hendford Road Bournemouth Dorset BH10 5AU",
    "addr:housenumber":"35",
    "addr:postcode":"bh10 5au",
    "addr:street":"Hendford Road",
    "iso:country":"GB",
    "sg:address":"35 Hendford Road",
    "sg:city":"Bournemouth",
    "sg:classifiers":[
        {
            "category":"Retail",
            "subcategory":"Auto Repair",
            "type":"Services"
        }
    ],
    "sg:phone":"+44 1202 519060",
    "sg:postcode":"BH10 5AU",
    "sg:province":"Dorset",
    "sg:tags":[
        "electrical",
        "centre"
    ],
    "wof:name":"Auto-Lec",
    "wof:placetype":"venue"
},
  "geometry": {"coordinates":[-1.8911099434,50.7541046143],"type":"Point"}
}