{
  "type": "Feature",
  "properties": {
    "iso:country":"GB",
    "sg:address":"102 Fountain Crescent, Inchinnan Business Park, Inchinnan",
    "sg:city":"Renfrew",
    "sg:classifiers":[
        {
            "category":"Professional",
            "type":"Services"
        }
    ],
    "sg:phone":"+44 141 812 8008",
    "sg:postcode":"PA4 9RE",
    "sg:province":"Renfrewshire",
    "sg:tags":[
        "repair",
        "tech",
        "maintenance"
    ],
    "wof:name":"Inventec (Scotland) Corporation Ltd.",
    "wof:placetype":"venue"
},
  "geometry": {"coordinates":[-4.4475269318,55.8835983276],"type":"Point"}
}