{
  "type": "Feature",
  "properties": {
    "addr:full":"Torliath House, Drumchork Achnasheen Highland IV22 2HU",
    "addr:postcode":"iv22 2hu",
    "iso:country":"GB",
    "sg:address":"Torliath House, Drumchork",
    "sg:city":"Achnasheen",
    "sg:classifiers":[
        {
            "category":"Travel",
            "subcategory":"Hotels & Motels",
            "type":"Entertainment"
        }
    ],
    "sg:phone":"+44 1445 731268",
    "sg:postcode":"IV22 2HU",
    "sg:province":"Highland",
    "sg:tags":[
        "self",
        "catering"
    ],
    "wof:name":"Aultbea Lodges",
    "wof:placetype":"venue"
},
  "geometry": {"coordinates":[-5.5710911751,57.7480201721],"type":"Point"}
}