{
  "type": "Feature",
  "properties": {
    "addr:full":"18 Mallard Close Worcester Worcestershire WR2 4BB",
    "addr:housenumber":"18",
    "addr:postcode":"wr2 4bb",
    "addr:street":"Mallard Close",
    "iso:country":"GB",
    "sg:address":"18 Mallard Close",
    "sg:city":"Worcester",
    "sg:classifiers":[
        {
            "category":"Building & Trades",
            "subcategory":"Construction",
            "type":"Services"
        }
    ],
    "sg:postcode":"WR2 4BB",
    "sg:province":"Worcestershire",
    "sg:tags":[
        "roofing"
    ],
    "wof:name":"Nigel C Green",
    "wof:placetype":"venue"
},
  "geometry": {"coordinates":[-2.232948,52.175045],"type":"Point"}
}