{
  "type": "Feature",
  "properties": {
    "addr:full":"72 Epping New Road Buckhurst Hill Essex IG9 5TX",
    "addr:housenumber":"72",
    "addr:postcode":"ig9 5tx",
    "addr:street":"Epping New Road",
    "iso:country":"GB",
    "sg:address":"72 Epping New Road",
    "sg:city":"Buckhurst Hill",
    "sg:classifiers":[
        {
            "category":"Arena",
            "subcategory":"Sports Club",
            "type":"Entertainment"
        }
    ],
    "sg:phone":"+44 20 8504 0780",
    "sg:postcode":"IG9 5TX",
    "sg:province":"Essex",
    "wof:name":"Buckhurst Hill Bowling & Lawn Tennis Club",
    "wof:placetype":"venue"
},
  "geometry": {"coordinates":[0.030593,51.630589],"type":"Point"}
}