{
  "type": "Feature",
  "properties": {
    "iso:country":"GB",
    "sg:address":"Willowgarth Newbiggin, Askrigg",
    "sg:city":"Leyburn",
    "sg:classifiers":[
        {
            "category":"Utilities",
            "subcategory":"Fuel Oil & Lpg",
            "type":"Services"
        }
    ],
    "sg:phone":"+44 1969 650414",
    "sg:postcode":"DL8 3JA",
    "sg:province":"North Yorkshire",
    "wof:name":"Wensley Coal & Coke Co",
    "wof:placetype":"venue"
},
  "geometry": {"coordinates":[-2.0784399509,54.3161697388],"type":"Point"}
}