{
  "type": "Feature",
  "properties": {
    "addr:full":"Victor Wharf, Roden St Ilford Essex IG1 2AD",
    "addr:postcode":"ig1 2ad",
    "addr:street":"Victor Wharf Roden St",
    "iso:country":"GB",
    "sg:address":"Victor Wharf, Roden St",
    "sg:city":"Ilford",
    "sg:classifiers":[
        {
            "category":"Manufacturing",
            "subcategory":"Rubber & Plastics",
            "type":"Manufacturing & Wholesale Goods"
        }
    ],
    "sg:postcode":"IG1 2AD",
    "sg:province":"Essex",
    "sg:tags":[
        "injection",
        "moulding"
    ],
    "wof:name":"Curtis,Ross,",
    "wof:placetype":"venue"
},
  "geometry": {"coordinates":[0.067115,51.563751],"type":"Point"}
}