{
  "type": "Feature",
  "properties": {
    "addr:full":"6 Buckhurst Clo East Grinstead East Sussex RH19 2AG",
    "addr:housenumber":"6",
    "addr:postcode":"rh19 2ag",
    "addr:street":"Buckhurst Clo",
    "iso:country":"GB",
    "sg:address":"6 Buckhurst Clo",
    "sg:city":"East Grinstead",
    "sg:classifiers":[
        {
            "category":"Food & Beverages",
            "subcategory":"Specialty",
            "type":"Retail Goods"
        }
    ],
    "sg:phone":"+44 1342 314728",
    "sg:postcode":"RH19 2AG",
    "sg:province":"East Sussex",
    "sg:tags":[
        "organic"
    ],
    "wof:name":"Organic Express",
    "wof:placetype":"venue"
},
  "geometry": {"coordinates":[-0.024487,51.1354904175],"type":"Point"}
}