{
  "type": "Feature",
  "properties": {
    "addr:full":"22 Stirling Street Denny Falkirk FK6 6AZ",
    "addr:housenumber":"22",
    "addr:postcode":"fk6 6az",
    "addr:street":"Stirling Street",
    "iso:country":"GB",
    "sg:address":"22 Stirling Street",
    "sg:city":"Denny",
    "sg:classifiers":[
        {
            "category":"Professional",
            "subcategory":"Lawyer & Legal Services",
            "type":"Services"
        }
    ],
    "sg:phone":"+44 1324 822194",
    "sg:postcode":"FK6 6AZ",
    "sg:province":"Falkirk",
    "sg:tags":[
        "solicitor"
    ],
    "wof:name":"Russell & Aitken",
    "wof:placetype":"venue"
},
  "geometry": {"coordinates":[-3.9076640606,56.0235099792],"type":"Point"}
}