{
  "type": "Feature",
  "properties": {
    "addr:full":"West Bay Bridport Dorset DT6 4EN",
    "addr:postcode":"dt6 4en",
    "iso:country":"GB",
    "sg:address":"West Bay",
    "sg:city":"Bridport",
    "sg:classifiers":[
        {
            "category":"Shopping",
            "subcategory":"News",
            "type":"Retail Goods"
        }
    ],
    "sg:phone":"+44 1308 423828",
    "sg:postcode":"DT6 4EN",
    "sg:province":"Dorset",
    "sg:tags":[
        "newsagent"
    ],
    "wof:name":"Harbour News",
    "wof:placetype":"venue"
},
  "geometry": {"coordinates":[-2.76138,50.710369],"type":"Point"}
}