{
  "type": "Feature",
  "properties": {
    "iso:country":"GB",
    "sg:address":"Suite 2b Gilbert Wakefield House, 67 Bewsey Street",
    "sg:city":"Warrington",
    "sg:classifiers":[
        {
            "category":"Communications",
            "type":"Services"
        }
    ],
    "sg:phone":"+44 1925 415177",
    "sg:postcode":"WA2 7JQ",
    "sg:province":"Cheshire",
    "sg:tags":[
        "telecommunication"
    ],
    "wof:name":"Amm Services",
    "wof:placetype":"venue"
},
  "geometry": {"coordinates":[-2.596447,53.392353],"type":"Point"}
}