{
  "type": "Feature",
  "properties": {
    "addr:full":"736 London Road, Larkfield Aylesford Kent ME20 6BG",
    "addr:housenumber":"736",
    "addr:postcode":"me20 6bg",
    "addr:street":"London Road",
    "iso:country":"GB",
    "sg:address":"736 London Road, Larkfield",
    "sg:city":"Aylesford",
    "sg:classifiers":[
        {
            "category":"Professional",
            "subcategory":"Testing Lab",
            "type":"Services"
        }
    ],
    "sg:phone":"+44 1732 870368",
    "sg:postcode":"ME20 6BG",
    "sg:province":"Kent",
    "sg:tags":[
        "mot"
    ],
    "wof:name":"Ace Mot Centre",
    "wof:placetype":"venue"
},
  "geometry": {"coordinates":[0.4433760047,51.2987251282],"type":"Point"}
}