{
  "type": "Feature",
  "properties": {
    "addr:full":"Stoneleigh Hall, Cranston Road East Grinstead East Sussex RH19 3HN",
    "addr:postcode":"rh19 3hn",
    "addr:street":"Cranston Road",
    "iso:country":"GB",
    "sg:address":"Stoneleigh Hall, Cranston Road",
    "sg:city":"East Grinstead",
    "sg:classifiers":[
        {
            "category":"Professional",
            "subcategory":"Advertising",
            "type":"Services"
        }
    ],
    "sg:phone":"+44 1342 324963",
    "sg:postcode":"RH19 3HN",
    "sg:province":"East Sussex",
    "sg:tags":[
        "medium"
    ],
    "wof:name":"D & P King",
    "wof:placetype":"venue"
},
  "geometry": {"coordinates":[-0.007568,51.123981],"type":"Point"}
}