{
  "type": "Feature",
  "properties": {
    "addr:full":"16 New Street Worcester Worcestershire WR1 2DP",
    "addr:housenumber":"16",
    "addr:postcode":"wr1 2dp",
    "addr:street":"New Street",
    "iso:country":"GB",
    "sg:address":"16 New Street",
    "sg:city":"Worcester",
    "sg:classifiers":[
        {
            "category":"Shopping",
            "subcategory":"Musical Instruments",
            "type":"Retail Goods"
        }
    ],
    "sg:postcode":"WR1 2DP",
    "sg:province":"Worcestershire",
    "sg:tags":[
        "music",
        "sheet"
    ],
    "wof:name":"Mike Bowley",
    "wof:placetype":"venue"
},
  "geometry": {"coordinates":[-2.218606,52.191822],"type":"Point"}
}