{
  "type": "Feature",
  "properties": {
    "iso:country":"GB",
    "sg:address":"193 Oak Road",
    "sg:city":"West Bromwich",
    "sg:classifiers":[
        {
            "category":"Building & Trades",
            "subcategory":"Construction",
            "type":"Services"
        }
    ],
    "sg:phone":"+44 121 553 0234",
    "sg:postcode":"B70 8HW",
    "sg:province":"West Midlands",
    "sg:tags":[
        "builder"
    ],
    "wof:name":"D J & R Dixon",
    "wof:placetype":"venue"
},
  "geometry": {"coordinates":[-2.0097789764,52.5160942078],"type":"Point"}
}