{
  "type": "Feature",
  "properties": {
    "iso:country":"GB",
    "sg:address":"West Tankerness Lane",
    "sg:city":"Kirkwall",
    "sg:classifiers":[
        {
            "category":"Taxi",
            "type":"Transportation"
        },
        {
            "category":"Military Area",
            "subcategory":"Air Force Base",
            "type":"Public Place"
        }
    ],
    "sg:phone":"+44 1856 878787",
    "sg:postcode":"KW15 1AL",
    "sg:province":"Orkney Islands",
    "sg:tags":[
        "hire",
        "private"
    ],
    "wof:name":"Craigie's Taxis",
    "wof:placetype":"venue"
},
  "geometry": {"coordinates":[-2.963739,58.981434],"type":"Point"}
}