{
  "type": "Feature",
  "properties": {
    "iso:country":"GB",
    "sg:address":"Ecomonic Regeneration, Bailey Ho, Rawmarsh Rd",
    "sg:city":"Rotherham",
    "sg:classifiers":[
        {
            "category":"Government",
            "subcategory":"Office",
            "type":"Public Place"
        }
    ],
    "sg:phone":"+44 1709 823806",
    "sg:postcode":"S60 1TX",
    "sg:province":"South Yorkshire",
    "sg:tags":[
        "local"
    ],
    "wof:name":"Rotherham Metropolitan Borough Council",
    "wof:placetype":"venue"
},
  "geometry": {"coordinates":[-1.3542430401,53.4298744202],"type":"Point"}
}