{
  "type": "Feature",
  "properties": {
    "addr:full":"R A F Henlow Henlow Bedfordshire SG16 6DN",
    "addr:postcode":"sg16 6dn",
    "addr:street":"R A F Henlow",
    "iso:country":"GB",
    "sg:address":"R A F Henlow",
    "sg:city":"Henlow",
    "sg:classifiers":[
        {
            "category":"Organizations",
            "subcategory":"Non-profit Organization",
            "type":"Services"
        }
    ],
    "sg:phone":"+44 1462 851515",
    "sg:postcode":"SG16 6DN",
    "sg:province":"Bedfordshire",
    "sg:tags":[
        "organisation",
        "voluntary",
        "charity"
    ],
    "wof:name":"The Royal Air Forces Association",
    "wof:placetype":"venue"
},
  "geometry": {"coordinates":[-0.285839,52.030876],"type":"Point"}
}