{
  "type": "Feature",
  "properties": {
    "addr:full":"Sussex Lodge, 44 Station Road Taunton Somerset TA1 1NS",
    "addr:housenumber":"44",
    "addr:postcode":"ta1 1ns",
    "addr:street":"Station Road",
    "iso:country":"GB",
    "sg:address":"Sussex Lodge, 44 Station Road",
    "sg:city":"Taunton",
    "sg:classifiers":[
        {
            "category":"Fast Food",
            "type":"Food & Drink"
        }
    ],
    "sg:phone":"+44 1823 331346",
    "sg:postcode":"TA1 1NS",
    "sg:province":"Somerset",
    "sg:tags":[
        "away",
        "meal",
        "outlet",
        "take"
    ],
    "wof:name":"Crystal Kebabs",
    "wof:placetype":"venue"
},
  "geometry": {"coordinates":[-3.104838,51.020184],"type":"Point"}
}