{
  "type": "Feature",
  "properties": {
    "addr:full":"Unit I68 Queensway, Team Valley Industrial Estate Gateshead Tyne and Wear NE11 0NX",
    "addr:housenumber":"estate",
    "addr:postcode":"ne11 0nx",
    "addr:street":"Queensway;Industrial",
    "iso:country":"GB",
    "sg:address":"Unit I68 Queensway, Team Valley Industrial Estate",
    "sg:city":"Gateshead",
    "sg:phone":"+44 191 491 0771",
    "sg:postcode":"NE11 0NX",
    "sg:province":"Tyne and Wear",
    "wof:name":"Van Bedaff P J",
    "wof:placetype":"venue"
},
  "geometry": {"coordinates":[-1.62211,54.941631],"type":"Point"}
}