{
  "type": "Feature",
  "properties": {
    "addr:full":"181 Daventry Road, Cheylesmore Coventry Warwickshire CV3 5HF",
    "addr:housenumber":"181",
    "addr:postcode":"cv3 5hf",
    "addr:street":"Daventry Road Cheylesmore",
    "iso:country":"GB",
    "sg:address":"181 Daventry Road, Cheylesmore",
    "sg:city":"Coventry",
    "sg:classifiers":[
        {
            "category":"Food & Beverages",
            "subcategory":"Liquor & Beverages",
            "type":"Retail Goods"
        }
    ],
    "sg:phone":"+44 24 7650 2680",
    "sg:postcode":"CV3 5HF",
    "sg:province":"Warwickshire",
    "sg:tags":[
        "beer",
        "wine",
        "spirit",
        "wines"
    ],
    "wof:name":"Victoria Wine",
    "wof:placetype":"venue"
},
  "geometry": {"coordinates":[-1.505259,52.394501],"type":"Point"}
}