{
  "type": "Feature",
  "properties": {
    "addr:full":"Segars Farm, Segars Lane, Twyford Winchester Hampshire SO21 1QJ",
    "addr:postcode":"so21 1qj",
    "addr:street":"Segars Lane",
    "iso:country":"GB",
    "sg:address":"Segars Farm, Segars Lane, Twyford",
    "sg:city":"Winchester",
    "sg:classifiers":[
        {
            "category":"Shopping",
            "subcategory":"Antiques",
            "type":"Retail Goods"
        }
    ],
    "sg:phone":"+44 1962 713401",
    "sg:postcode":"SO21 1QJ",
    "sg:province":"Hampshire",
    "wof:name":"Frearson & Hewlett",
    "wof:placetype":"venue"
},
  "geometry": {"coordinates":[-1.3127390146,51.0235900879],"type":"Point"}
}