{
  "type": "Feature",
  "properties": {
    "addr:full":"Unit 1 William James Ho, Towley Rd Cambridge Cambridgeshire CB1 7WX",
    "addr:housenumber":"unit 1",
    "addr:postcode":"cb1 7wx",
    "addr:street":"William James;Towley Rd",
    "iso:country":"GB",
    "sg:address":"Unit 1 William James Ho, Towley Rd",
    "sg:city":"Cambridge",
    "sg:classifiers":[
        {
            "category":"Professional",
            "subcategory":"Accounting & Tax Preparation",
            "type":"Services"
        }
    ],
    "sg:postcode":"CB1 7WX",
    "sg:province":"Cambridgeshire",
    "sg:tags":[
        "accountant"
    ],
    "wof:name":"Reardon & Co Ltd",
    "wof:placetype":"venue"
},
  "geometry": {"coordinates":[0.14498,52.185501],"type":"Point"}
}