{
  "type": "Feature",
  "properties": {
    "addr:full":"94 Stoneleigh Avenue Enfield Greater London EN1 4HQ",
    "addr:housenumber":"94",
    "addr:postcode":"en1 4hq",
    "addr:street":"Stoneleigh Avenue",
    "iso:country":"GB",
    "sg:address":"94 Stoneleigh Avenue",
    "sg:city":"Enfield",
    "sg:classifiers":[
        {
            "category":"Building & Trades",
            "subcategory":"Construction",
            "type":"Services"
        }
    ],
    "sg:phone":"+44 20 8364 7676",
    "sg:postcode":"EN1 4HQ",
    "sg:province":"Greater London",
    "sg:tags":[
        "roofing"
    ],
    "wof:name":"Secure Roofing & Construction",
    "wof:placetype":"venue"
},
  "geometry": {"coordinates":[-0.0530649982,51.6646003723],"type":"Point"}
}