{
  "type": "Feature",
  "properties": {
    "iso:country":"GB",
    "sg:address":"20 Kilmarnock Road",
    "sg:city":"Mauchline",
    "sg:classifiers":[
        {
            "category":"Home & Garden",
            "subcategory":"Hardware",
            "type":"Retail Goods"
        }
    ],
    "sg:postcode":"KA5 5DF",
    "sg:province":"East Ayrshire",
    "wof:name":"Iain  Cowan",
    "wof:placetype":"venue"
},
  "geometry": {"coordinates":[-4.380975,55.517502],"type":"Point"}
}