{
  "type": "Feature",
  "properties": {
    "iso:country":"GB",
    "sg:address":"10 Tribune Drive, Trinity Trading Estate",
    "sg:city":"Sittingbourne",
    "sg:classifiers":[
        {
            "category":"Professional",
            "subcategory":"Engineering",
            "type":"Services"
        }
    ],
    "sg:phone":"+44 1795 431301",
    "sg:postcode":"ME10 2PG",
    "sg:province":"Kent",
    "sg:tags":[
        "engineer",
        "mechanical"
    ],
    "wof:name":"Bmc (Control Equipment) Ltd.",
    "wof:placetype":"venue"
},
  "geometry": {"coordinates":[0.7379099727,51.3408203125],"type":"Point"}
}