{
  "type": "Feature",
  "properties": {
    "iso:country":"GB",
    "sg:address":"2 Harvills Hawthorn",
    "sg:city":"West Bromwich",
    "sg:classifiers":[
        {
            "category":"Food & Beverages",
            "subcategory":"Meat & Fish",
            "type":"Retail Goods"
        },
        {
            "category":"Food & Beverages",
            "subcategory":"Groceries & Convenience Stores",
            "type":"Retail Goods"
        }
    ],
    "sg:phone":"+44 121 532 7255",
    "sg:postcode":"B70 0UH",
    "sg:province":"West Midlands",
    "sg:tags":[
        "shop",
        "chip"
    ],
    "wof:name":"Ocean Fish Bar",
    "wof:placetype":"venue"
},
  "geometry": {"coordinates":[-2.01594,52.537338],"type":"Point"}
}