{
  "type": "Feature",
  "properties": {
    "addr:full":"Ninth Avenue East, Team Valley Trading Est Gateshead Tyne and Wear NE11 0EH",
    "addr:postcode":"ne11 0eh",
    "addr:street":"Ninth Avenue East;Est",
    "iso:country":"GB",
    "sg:address":"Ninth Avenue East, Team Valley Trading Est",
    "sg:city":"Gateshead",
    "sg:classifiers":[
        {
            "category":"Wholesale",
            "subcategory":"Non-durable Goods",
            "type":"Manufacturing & Wholesale Goods"
        }
    ],
    "sg:phone":"+44 191 482 6340",
    "sg:postcode":"NE11 0EH",
    "sg:province":"Tyne and Wear",
    "sg:tags":[
        "carry",
        "wholesaler",
        "cash"
    ],
    "wof:name":"Ray & Co Ltd",
    "wof:placetype":"venue"
},
  "geometry": {"coordinates":[-1.61095,54.927448],"type":"Point"}
}