{
  "type": "Feature",
  "properties": {
    "iso:country":"GB",
    "sg:address":"20 Craigielea Pl",
    "sg:city":"Dundee",
    "sg:classifiers":[
        {
            "category":"Organizations",
            "subcategory":"Religious Organization",
            "type":"Services"
        }
    ],
    "sg:phone":"+44 1382 509206",
    "sg:postcode":"DD4 8HL",
    "sg:province":"Dundee City",
    "sg:tags":[
        "organisation"
    ],
    "wof:name":"Order Of The Holy Paraclete Scottish Episcopal Church",
    "wof:placetype":"venue"
},
  "geometry": {"coordinates":[-2.932854,56.479485],"type":"Point"}
}