{
  "type": "Feature",
  "properties": {
    "addr:full":"2 Park Place, Clifton Bristol City of Bristol BS8 1JW",
    "addr:housenumber":"2",
    "addr:postcode":"bs8 1jw",
    "addr:street":"Park Place",
    "iso:country":"GB",
    "sg:address":"2 Park Place, Clifton",
    "sg:city":"Bristol",
    "sg:classifiers":[
        {
            "category":"Bars & Pubs",
            "type":"Food & Drink"
        }
    ],
    "sg:phone":"+44 117 907 7858",
    "sg:postcode":"BS8 1JW",
    "sg:province":"City of Bristol",
    "sg:tags":[
        "pubs",
        "inn"
    ],
    "wof:name":"Quinton Ho",
    "wof:placetype":"venue"
},
  "geometry": {"coordinates":[-2.60889,51.457172],"type":"Point"}
}