{
  "type": "Feature",
  "properties": {
    "iso:country":"GB",
    "sg:address":"31 Quintrell Gardens, Quintrell Downs",
    "sg:city":"Newquay",
    "sg:classifiers":[
        {
            "category":"Retail",
            "subcategory":"Driving School",
            "type":"Services"
        }
    ],
    "sg:phone":"+44 1637 876967",
    "sg:postcode":"TR8 4LH",
    "sg:province":"Cornwall",
    "wof:name":"Quintrell School Of Motoring",
    "wof:placetype":"venue"
},
  "geometry": {"coordinates":[-5.0222730637,50.4028663635],"type":"Point"}
}