{
  "type": "Feature",
  "properties": {
    "addr:full":"57 Garstang Rd Preston Lancashire PR1 1LB",
    "addr:housenumber":"57",
    "addr:postcode":"pr1 1lb",
    "addr:street":"Garstang Rd",
    "iso:country":"GB",
    "sg:address":"57 Garstang Rd",
    "sg:city":"Preston",
    "sg:classifiers":[
        {
            "category":"Professional",
            "subcategory":"Management & Consulting",
            "type":"Services"
        }
    ],
    "sg:phone":"+44 1772 259612",
    "sg:postcode":"PR1 1LB",
    "sg:province":"Lancashire",
    "sg:tags":[
        "consultant",
        "energy",
        "conservation"
    ],
    "wof:name":"Remco (Northern) Ltd",
    "wof:placetype":"venue"
},
  "geometry": {"coordinates":[-2.7056090832,53.7709503174],"type":"Point"}
}