{
  "type": "Feature",
  "properties": {
    "iso:country":"GB",
    "sg:address":"Unit 37 Albion Mills, Miry Lane",
    "sg:city":"Huddersfield",
    "sg:classifiers":[
        {
            "category":"Retail",
            "subcategory":"Auto Repair",
            "type":"Services"
        }
    ],
    "sg:phone":"+44 1484 681651",
    "sg:postcode":"HD9 7HP",
    "sg:province":"South Yorkshire",
    "sg:tags":[
        "modification",
        "garage"
    ],
    "wof:name":"C T M Motor Engineers",
    "wof:placetype":"venue"
},
  "geometry": {"coordinates":[-1.77735,53.583778],"type":"Point"}
}