{
  "type": "Feature",
  "properties": {
    "addr:full":"50a Queens Road Buckhurst Hill Essex IG9 5DD",
    "addr:housenumber":"50a",
    "addr:postcode":"ig9 5dd",
    "addr:street":"Queens Road",
    "iso:country":"GB",
    "sg:address":"50a Queens Road",
    "sg:city":"Buckhurst Hill",
    "sg:classifiers":[
        {
            "category":"Communications",
            "subcategory":"Newspaper",
            "type":"Services"
        }
    ],
    "sg:phone":"+44 20 8506 0163",
    "sg:postcode":"IG9 5DD",
    "sg:province":"Essex",
    "sg:tags":[
        "magazine"
    ],
    "wof:name":"Plant World Journal",
    "wof:placetype":"venue"
},
  "geometry": {"coordinates":[0.04384,51.625183],"type":"Point"}
}