{
  "type": "Feature",
  "properties": {
    "addr:full":"Unit 4 Derby Derbyshire DE21 7BH",
    "addr:housenumber":"unit 4",
    "addr:postcode":"de21 7bh",
    "addr:street":"Derby Derbyshire",
    "iso:country":"GB",
    "sg:address":"Unit 4",
    "sg:city":"Derby",
    "sg:classifiers":[
        {
            "category":"Manufacturing",
            "subcategory":"Metals",
            "type":"Manufacturing & Wholesale Goods"
        },
        {
            "category":"Home & Garden",
            "subcategory":"Hardware",
            "type":"Retail Goods"
        }
    ],
    "sg:postcode":"DE21 7BH",
    "sg:province":"Derbyshire",
    "sg:tags":[
        "equipment",
        "welding"
    ],
    "wof:name":"Arc Machines (U K) Ltd.",
    "wof:placetype":"venue"
},
  "geometry": {"coordinates":[-1.409139,52.917141],"type":"Point"}
}