{
  "type": "Feature",
  "properties": {
    "addr:full":"1 Bridge Chambers, The Sqaure Barnstaple Devon EX31 1HB",
    "addr:housenumber":"1;chambers",
    "addr:postcode":"ex31 1hb",
    "addr:street":"The Sqaure",
    "iso:country":"GB",
    "sg:address":"1 Bridge Chambers, The Sqaure",
    "sg:city":"Barnstaple",
    "sg:classifiers":[
        {
            "category":"Real Estate",
            "subcategory":"Architect",
            "type":"Services"
        }
    ],
    "sg:phone":"+44 1271 321321",
    "sg:postcode":"EX31 1HB",
    "sg:province":"Devon",
    "wof:name":"John Shardelow Architecture & Planning",
    "wof:placetype":"venue"
},
  "geometry": {"coordinates":[-4.0616002083,51.0795783997],"type":"Point"}
}