{
  "type": "Feature",
  "properties": {
    "iso:country":"GB",
    "sg:address":"343 Strathmartine Road",
    "sg:city":"Dundee",
    "sg:classifiers":[
        {
            "category":"Building & Trades",
            "subcategory":"Plumbing",
            "type":"Services"
        }
    ],
    "sg:phone":"+44 1382 827790",
    "sg:postcode":"DD3 8NE",
    "sg:province":"Dundee City",
    "sg:tags":[
        "plumber",
        "heating"
    ],
    "wof:name":"J Grant & Sons",
    "wof:placetype":"venue"
},
  "geometry": {"coordinates":[-2.993026,56.488091],"type":"Point"}
}