{
  "type": "Feature",
  "properties": {
    "addr:full":"16 Carwinshoch View Ayr South Ayrshire KA7 4AZ",
    "addr:housenumber":"16",
    "addr:postcode":"ka7 4az",
    "addr:street":"Carwinshoch View",
    "iso:country":"GB",
    "sg:address":"16 Carwinshoch View",
    "sg:city":"Ayr",
    "sg:classifiers":[
        {
            "category":"Building & Trades",
            "subcategory":"Construction",
            "type":"Services"
        }
    ],
    "sg:postcode":"KA7 4AZ",
    "sg:province":"South Ayrshire",
    "sg:tags":[
        "monumental",
        "mason"
    ],
    "wof:name":"William Armour",
    "wof:placetype":"venue"
},
  "geometry": {"coordinates":[-4.6445269585,55.4460983276],"type":"Point"}
}