{
  "type": "Feature",
  "properties": {
    "iso:country":"GB",
    "sg:address":"Europa Dr",
    "sg:city":"Sheffield",
    "sg:classifiers":[
        {
            "category":"Wholesale",
            "subcategory":"Books, Periodicals, & Newspapers",
            "type":"Manufacturing & Wholesale Goods"
        }
    ],
    "sg:phone":"+44 114 220 0777",
    "sg:postcode":"S9 1XT",
    "sg:province":"South Yorkshire",
    "sg:tags":[
        "newsagent"
    ],
    "wof:name":"Turners Information Services Ltd",
    "wof:placetype":"venue"
},
  "geometry": {"coordinates":[-1.4044430256,53.3999786377],"type":"Point"}
}