{
  "type": "Feature",
  "properties": {
    "addr:full":"35 Red Lane Coventry Warwickshire CV6 5EE",
    "addr:housenumber":"35",
    "addr:postcode":"cv6 5ee",
    "addr:street":"Red Lane",
    "iso:country":"GB",
    "sg:address":"35 Red Lane",
    "sg:city":"Coventry",
    "sg:classifiers":[
        {
            "category":"Banks & Credit Unions",
            "subcategory":"Bureau De Change",
            "type":"Services"
        },
        {
            "category":"Food & Beverages",
            "subcategory":"Liquor & Beverages",
            "type":"Retail Goods"
        }
    ],
    "sg:phone":"+44 24 7668 9762",
    "sg:postcode":"CV6 5EE",
    "sg:province":"Warwickshire",
    "sg:tags":[
        "beer",
        "wine",
        "spirit",
        "wines"
    ],
    "wof:name":"Hasmukh Vara",
    "wof:placetype":"venue"
},
  "geometry": {"coordinates":[-1.494252,52.420238],"type":"Point"}
}