{
  "type": "Feature",
  "properties": {
    "iso:country":"GB",
    "sg:address":"School Lane",
    "sg:city":"Liverpool",
    "sg:classifiers":[
        {
            "category":"Farming",
            "subcategory":"Dairy Farm",
            "type":"Manufacturing & Wholesale Goods"
        }
    ],
    "sg:phone":"+44 151 428 3627",
    "sg:postcode":"L25 7UA",
    "sg:province":"Merseyside",
    "wof:name":"Liverpool Dairy Products Ltd.",
    "wof:placetype":"venue"
},
  "geometry": {"coordinates":[-2.863606,53.370163],"type":"Point"}
}