{
  "type": "Feature",
  "properties": {
    "iso:country":"GB",
    "sg:address":"52-58 Main Street, Cambuslang",
    "sg:city":"Glasgow",
    "sg:classifiers":[
        {
            "category":"Organizations",
            "subcategory":"Membership Organization",
            "type":"Services"
        }
    ],
    "sg:phone":"+44 141 641 3558",
    "sg:postcode":"G72 7EP",
    "sg:province":"South Lanarkshire",
    "sg:tags":[
        "club"
    ],
    "wof:name":"Savoy Bingo Club",
    "wof:placetype":"venue"
},
  "geometry": {"coordinates":[-4.165922,55.818642],"type":"Point"}
}