{
  "type": "Feature",
  "properties": {
    "addr:full":"17 The Old Maltings, Hockerill Street Bishops Stortford Essex CM23 2ED",
    "addr:housenumber":"17",
    "addr:postcode":"cm23 2ed",
    "addr:street":"The Old Maltings Hockerill Street",
    "iso:country":"GB",
    "sg:address":"17 The Old Maltings, Hockerill Street",
    "sg:city":"Bishops Stortford",
    "sg:classifiers":[
        {
            "category":"Professional",
            "subcategory":"Lawyer & Legal Services",
            "type":"Services"
        }
    ],
    "sg:phone":"+44 1279 466206",
    "sg:postcode":"CM23 2ED",
    "sg:province":"Essex",
    "wof:name":"M B Kain & Co",
    "wof:placetype":"venue"
},
  "geometry": {"coordinates":[0.161956,51.872356],"type":"Point"}
}