{
  "type": "Feature",
  "properties": {
    "iso:country":"GB",
    "sg:address":"Spinney Estates, Hoddesdon Road, Stanstead Abbots",
    "sg:city":"Ware",
    "sg:classifiers":[
        {
            "category":"Professional",
            "subcategory":"Engineering",
            "type":"Services"
        }
    ],
    "sg:phone":"+44 1920 871734",
    "sg:postcode":"SG12 8EJ",
    "sg:province":"Hertfordshire",
    "sg:tags":[
        "consulting",
        "engineer"
    ],
    "wof:name":"Istec Services Ltd.",
    "wof:placetype":"venue"
},
  "geometry": {"coordinates":[0.0110950004,51.787071228],"type":"Point"}
}