{
  "type": "Feature",
  "properties": {
    "addr:full":"Middle Farm, Hatton Church Stretton Shropshire SY6 6QP",
    "addr:housenumber":"hatton",
    "addr:postcode":"sy6 6qp",
    "addr:street":"Middle",
    "iso:country":"GB",
    "sg:address":"Middle Farm, Hatton",
    "sg:city":"Church Stretton",
    "sg:classifiers":[
        {
            "category":"Farming",
            "subcategory":"Farm",
            "type":"Manufacturing & Wholesale Goods"
        }
    ],
    "sg:postcode":"SY6 6QP",
    "sg:province":"Shropshire",
    "sg:tags":[
        "mixed",
        "crop"
    ],
    "wof:name":"C Perkins",
    "wof:placetype":"venue"
},
  "geometry": {"coordinates":[-2.7851989269,52.5079612732],"type":"Point"}
}