{
  "type": "Feature",
  "properties": {
    "addr:full":"Hammetts Farm, Mildenhall Road, West Row Bury St Edmunds Cambridgeshire IP28 8NT",
    "addr:postcode":"ip28 8nt",
    "addr:street":"Mildenhall Road West;St",
    "iso:country":"GB",
    "sg:address":"Hammetts Farm, Mildenhall Road, West Row",
    "sg:city":"Bury St Edmunds",
    "sg:classifiers":[
        {
            "category":"Farming",
            "subcategory":"Livestock Farm",
            "type":"Manufacturing & Wholesale Goods"
        }
    ],
    "sg:phone":"+44 1638 715778",
    "sg:postcode":"IP28 8NT",
    "sg:province":"Cambridgeshire",
    "sg:tags":[
        "others"
    ],
    "wof:name":"David E Shipp",
    "wof:placetype":"venue"
},
  "geometry": {"coordinates":[0.452419,52.323612],"type":"Point"}
}