{
  "type": "Feature",
  "properties": {
    "iso:country":"GB",
    "sg:address":"Ffordd-yr-afon, Trefin",
    "sg:city":"Haverfordwest",
    "sg:classifiers":[
        {
            "category":"Travel",
            "subcategory":"Hostel",
            "type":"Entertainment"
        }
    ],
    "sg:phone":"+44 1348 831414",
    "sg:postcode":"SA62 5AU",
    "sg:province":"Pembrokeshire",
    "sg:tags":[
        "youth"
    ],
    "wof:name":"Trefin Youth Hostel",
    "wof:placetype":"venue"
},
  "geometry": {"coordinates":[-5.145729,51.948994],"type":"Point"}
}