{
  "type": "Feature",
  "properties": {
    "iso:country":"GB",
    "sg:address":"20 Vittoria Street",
    "sg:city":"Birmingham",
    "sg:classifiers":[
        {
            "category":"Communications",
            "type":"Services"
        }
    ],
    "sg:phone":"+44 121 233 3233",
    "sg:postcode":"B1 3PE",
    "sg:province":"West Midlands",
    "sg:tags":[
        "broadcasting"
    ],
    "wof:name":"Graffiti Post Productions",
    "wof:placetype":"venue"
},
  "geometry": {"coordinates":[-1.910647,52.484619],"type":"Point"}
}