{
  "type": "Feature",
  "properties": {
    "iso:country":"GB",
    "sg:address":"Health Centre, Wynne Rd",
    "sg:city":"Blaenau Ffestiniog",
    "sg:classifiers":[
        {
            "category":"Health Services",
            "subcategory":"Doctor",
            "type":"Services"
        }
    ],
    "sg:phone":"+44 1766 830261",
    "sg:postcode":"LL41 3DW",
    "sg:province":"Gwynedd",
    "sg:tags":[
        "practitioners"
    ],
    "wof:name":"Jones, H R",
    "wof:placetype":"venue"
},
  "geometry": {"coordinates":[-3.940505,52.995342],"type":"Point"}
}