{
  "type": "Feature",
  "properties": {
    "addr:full":"125 College Street Dumbarton Argyll and Bute G82 1NH",
    "addr:housenumber":"125",
    "addr:postcode":"g82 1nh",
    "addr:street":"College Street",
    "iso:country":"GB",
    "sg:address":"125 College Street",
    "sg:city":"Dumbarton",
    "sg:classifiers":[
        {
            "category":"Government",
            "subcategory":"Office",
            "type":"Public Place"
        }
    ],
    "sg:postcode":"G82 1NH",
    "sg:province":"Argyll and Bute",
    "sg:tags":[
        "local"
    ],
    "wof:name":"The Dumbarton Project",
    "wof:placetype":"venue"
},
  "geometry": {"coordinates":[-4.568749,55.946217],"type":"Point"}
}