{
  "type": "Feature",
  "properties": {
    "addr:full":"49 Sussex Road South Croydon Surrey CR2 7DB",
    "addr:housenumber":"49",
    "addr:postcode":"cr2 7db",
    "addr:street":"Sussex Road",
    "iso:country":"GB",
    "sg:address":"49 Sussex Road",
    "sg:city":"South Croydon",
    "sg:classifiers":[
        {
            "category":"Professional",
            "subcategory":"Detective & Security Services",
            "type":"Services"
        }
    ],
    "sg:postcode":"CR2 7DB",
    "sg:province":"Surrey",
    "sg:tags":[
        "alarm",
        "burglar",
        "system"
    ],
    "wof:name":"Knight Security Alarms",
    "wof:placetype":"venue"
},
  "geometry": {"coordinates":[-0.093069,51.358383],"type":"Point"}
}