{
  "type": "Feature",
  "properties": {
    "addr:full":"Daneby Hall, The Lane Tunbridge Wells East Sussex TN3 0RP",
    "addr:postcode":"tn3 0rp",
    "addr:street":"The Lane",
    "iso:country":"GB",
    "sg:address":"Daneby Hall, The Lane",
    "sg:city":"Tunbridge Wells",
    "sg:classifiers":[
        {
            "category":"Personal",
            "type":"Services"
        }
    ],
    "sg:phone":"+44 1892 740235",
    "sg:postcode":"TN3 0RP",
    "sg:province":"East Sussex",
    "sg:tags":[
        "wedding"
    ],
    "wof:name":"The Black Cat Music Agency",
    "wof:placetype":"venue"
},
  "geometry": {"coordinates":[0.18561,51.141621],"type":"Point"}
}