{
  "type": "Feature",
  "properties": {
    "iso:country":"GB",
    "sg:address":"Kipson Bank Farm, 4 Dukes Court, Bognor Road",
    "sg:city":"Chichester",
    "sg:classifiers":[
        {
            "category":"Professional",
            "subcategory":"Accounting & Tax Preparation",
            "type":"Services"
        },
        {
            "category":"Farming",
            "subcategory":"Crops",
            "type":"Manufacturing & Wholesale Goods"
        }
    ],
    "sg:phone":"+44 1243 789031",
    "sg:postcode":"PO19 8FX",
    "sg:province":"West Sussex",
    "sg:tags":[
        "accountant",
        "arable"
    ],
    "wof:name":"Kipson Bank Farm",
    "wof:placetype":"venue"
},
  "geometry": {"coordinates":[-0.7754290104,50.8361663818],"type":"Point"}
}