{
  "type": "Feature",
  "properties": {
    "iso:country":"GB",
    "sg:address":"5-6 Shepherd St",
    "sg:city":"Preston",
    "sg:classifiers":[
        {
            "category":"Community Center",
            "type":"Public Place"
        }
    ],
    "sg:phone":"+44 1772 825665",
    "sg:postcode":"PR1 3YD",
    "sg:province":"Lancashire",
    "sg:tags":[
        "centre"
    ],
    "wof:name":"Unity Community Centre",
    "wof:placetype":"venue"
},
  "geometry": {"coordinates":[-2.6947,53.757896],"type":"Point"}
}