{
  "type": "Feature",
  "properties": {
    "iso:country":"GB",
    "sg:address":"11 Priory Park, Thurgarton",
    "sg:city":"Nottingham",
    "sg:classifiers":[
        {
            "category":"Recreation",
            "subcategory":"Amusement Park",
            "type":"Entertainment"
        }
    ],
    "sg:phone":"+44 1636 830558",
    "sg:postcode":"NG14 7HE",
    "sg:province":"Nottinghamshire",
    "sg:tags":[
        "arcade",
        "activity"
    ],
    "wof:name":"TOTALMOVE LTD",
    "wof:placetype":"venue"
},
  "geometry": {"coordinates":[-0.96096,53.034039],"type":"Point"}
}