{
  "type": "Feature",
  "properties": {
    "iso:country":"GB",
    "sg:address":"151 Weston Road",
    "sg:city":"Stafford",
    "sg:classifiers":[
        {
            "category":"Banks & Credit Unions",
            "subcategory":"Investment Brokerage",
            "type":"Services"
        }
    ],
    "sg:phone":"+44 1785 247297",
    "sg:postcode":"ST16 3RS",
    "sg:province":"Staffordshire",
    "wof:name":"The Inglewood Investment Co. Ltd.",
    "wof:placetype":"venue"
},
  "geometry": {"coordinates":[-2.096427,52.809219],"type":"Point"}
}