{
  "type": "Feature",
  "properties": {
    "addr:full":"3 Cramer Road, West Meadows Industrial Estate Derby Derbyshire DE21 6WU",
    "addr:housenumber":"3;estate",
    "addr:postcode":"de21 6wu",
    "addr:street":"Cramer Road West;Industrial",
    "iso:country":"GB",
    "sg:address":"3 Cramer Road, West Meadows Industrial Estate",
    "sg:city":"Derby",
    "sg:classifiers":[
        {
            "category":"Manufacturing",
            "subcategory":"Motor Vehicles & Parts",
            "type":"Manufacturing & Wholesale Goods"
        }
    ],
    "sg:phone":"+44 1332 349457",
    "sg:postcode":"DE21 6WU",
    "sg:province":"Derbyshire",
    "sg:tags":[
        "bearing"
    ],
    "wof:name":"B S L Ltd.",
    "wof:placetype":"venue"
},
  "geometry": {"coordinates":[-1.4604439735,52.9240036011],"type":"Point"}
}