{
  "type": "Feature",
  "properties": {
    "addr:full":"14 Bond Street Wakefield West Yorkshire WF1 2QP",
    "addr:housenumber":"14",
    "addr:postcode":"wf1 2qp",
    "addr:street":"Bond Street",
    "iso:country":"GB",
    "sg:address":"14 Bond Street",
    "sg:city":"Wakefield",
    "sg:classifiers":[
        {
            "category":"Professional",
            "subcategory":"Lawyer & Legal Services",
            "type":"Services"
        }
    ],
    "sg:phone":"+44 1924 201122",
    "sg:postcode":"WF1 2QP",
    "sg:province":"West Yorkshire",
    "sg:tags":[
        "solicitor"
    ],
    "wof:name":"Gartonshire Solicitors",
    "wof:placetype":"venue"
},
  "geometry": {"coordinates":[-1.5030809641,53.6857032776],"type":"Point"}
}