{
  "type": "Feature",
  "properties": {
    "iso:country":"GB",
    "sg:address":"Old Grammar School, Church View",
    "sg:city":"Bampton",
    "sg:classifiers":[
        {
            "category":"Education",
            "subcategory":"Library",
            "type":"Public Place"
        }
    ],
    "sg:phone":"+44 1993 850076",
    "sg:postcode":"OX18 2NE",
    "sg:province":"Gloucestershire",
    "sg:tags":[
        "book"
    ],
    "wof:name":"Bampton Library",
    "wof:placetype":"venue"
},
  "geometry": {"coordinates":[-1.5467580557,51.7279243469],"type":"Point"}
}