{
  "type": "Feature",
  "properties": {
    "addr:full":"7 Marham Gardens London Greater London SW18 3JZ",
    "addr:housenumber":"7",
    "addr:postcode":"sw18 3jz",
    "addr:street":"Marham Gardens",
    "iso:country":"GB",
    "sg:address":"7 Marham Gardens",
    "sg:city":"London",
    "sg:classifiers":[
        {
            "category":"Retail",
            "subcategory":"Event Space",
            "type":"Services"
        }
    ],
    "sg:postcode":"SW18 3JZ",
    "sg:province":"Greater London",
    "sg:tags":[
        "exhibition",
        "organiser"
    ],
    "wof:name":"Force 10 Events",
    "wof:placetype":"venue"
},
  "geometry": {"coordinates":[-0.172398,51.441746],"type":"Point"}
}