{
  "type": "Feature",
  "properties": {
    "addr:full":"10 Queen Alexandra Road North Shields Tyne and Wear NE29 9AR",
    "addr:housenumber":"10",
    "addr:postcode":"ne29 9ar",
    "addr:street":"Queen Alexandra Road",
    "iso:country":"GB",
    "sg:address":"10 Queen Alexandra Road",
    "sg:city":"North Shields",
    "sg:classifiers":[
        {
            "category":"Professional",
            "type":"Services"
        }
    ],
    "sg:phone":"+44 191 258 0035",
    "sg:postcode":"NE29 9AR",
    "sg:province":"Tyne and Wear",
    "sg:tags":[
        "caterer"
    ],
    "wof:name":"Just A Snack",
    "wof:placetype":"venue"
},
  "geometry": {"coordinates":[-1.4507889748,55.0146102905],"type":"Point"}
}