{
  "type": "Feature",
  "properties": {
    "addr:full":"21a George Street Luton Bedfordshire LU1 2AF",
    "addr:housenumber":"21a",
    "addr:postcode":"lu1 2af",
    "addr:street":"George Street",
    "iso:country":"GB",
    "sg:address":"21a George Street",
    "sg:city":"Luton",
    "sg:classifiers":[
        {
            "category":"Personal",
            "subcategory":"Barber",
            "type":"Services"
        }
    ],
    "sg:phone":"+44 1582 451188",
    "sg:postcode":"LU1 2AF",
    "sg:province":"Bedfordshire",
    "sg:tags":[
        "men's",
        "gents",
        "hairdresser"
    ],
    "wof:name":"Bryans Hairdressing",
    "wof:placetype":"venue"
},
  "geometry": {"coordinates":[-0.4148119986,51.8782310486],"type":"Point"}
}