{
  "type": "Feature",
  "properties": {
    "addr:full":"Sands Lane, Badsey Evesham Gloucestershire WR11 7EZ",
    "addr:postcode":"wr11 7ez",
    "addr:street":"Sands Lane",
    "iso:country":"GB",
    "sg:address":"Sands Lane, Badsey",
    "sg:city":"Evesham",
    "sg:classifiers":[
        {
            "category":"Home & Garden",
            "subcategory":"Garden Supply",
            "type":"Retail Goods"
        }
    ],
    "sg:postcode":"WR11 7EZ",
    "sg:province":"Gloucestershire",
    "sg:tags":[
        "nursery",
        "centre"
    ],
    "wof:name":"Cotswold Garden Flowers",
    "wof:placetype":"venue"
},
  "geometry": {"coordinates":[-1.898144,52.09103],"type":"Point"}
}