{
  "type": "Feature",
  "properties": {
    "addr:full":"29 West St, Shelf Halifax West Yorkshire HX3 7LN",
    "addr:housenumber":"29",
    "addr:postcode":"hx3 7ln",
    "addr:street":"West St",
    "iso:country":"GB",
    "sg:address":"29 West St, Shelf",
    "sg:city":"Halifax",
    "sg:classifiers":[
        {
            "category":"Personal",
            "subcategory":"Beauty Salon",
            "type":"Services"
        }
    ],
    "sg:phone":"+44 1422 206004",
    "sg:postcode":"HX3 7LN",
    "sg:province":"West Yorkshire",
    "sg:tags":[
        "unisex",
        "hairdresser"
    ],
    "wof:name":"The Review",
    "wof:placetype":"venue"
},
  "geometry": {"coordinates":[-1.8227770329,53.7481498718],"type":"Point"}
}