{
  "type": "Feature",
  "properties": {
    "iso:country":"GB",
    "sg:address":"23 Rosslyn Hill",
    "sg:city":"London",
    "sg:classifiers":[
        {
            "category":"Real Estate",
            "subcategory":"Developer",
            "type":"Services"
        }
    ],
    "sg:phone":"+44 20 7433 1400",
    "sg:postcode":"NW3 5UJ",
    "sg:province":"Greater London",
    "sg:tags":[
        "property"
    ],
    "wof:name":"Central & Provincial Estates Ltd.",
    "wof:placetype":"venue"
},
  "geometry": {"coordinates":[-0.170607,51.553734],"type":"Point"}
}