{
  "type": "Feature",
  "properties": {
    "addr:full":"West Bay Dunoon Argyll and Bute PA23 7HN",
    "addr:postcode":"pa23 7hn",
    "iso:country":"GB",
    "sg:address":"West Bay",
    "sg:city":"Dunoon",
    "sg:classifiers":[
        {
            "category":"Cafe",
            "type":"Food & Drink"
        }
    ],
    "sg:phone":"+44 1369 702508",
    "sg:postcode":"PA23 7HN",
    "sg:province":"Argyll and Bute",
    "sg:tags":[
        "tea",
        "snack",
        "bar",
        "room"
    ],
    "wof:name":"Rock Cafe",
    "wof:placetype":"venue"
},
  "geometry": {"coordinates":[-4.980709,55.868526],"type":"Point"}
}