{
  "type": "Feature",
  "properties": {
    "addr:full":"46 Redbraes Place Edinburgh City of Edinburgh EH7 4LH",
    "addr:housenumber":"46",
    "addr:postcode":"eh7 4lh",
    "addr:street":"Redbraes Place Edinburgh",
    "iso:country":"GB",
    "sg:address":"46 Redbraes Place",
    "sg:city":"Edinburgh",
    "sg:classifiers":[
        {
            "category":"Building & Trades",
            "subcategory":"Construction",
            "type":"Services"
        }
    ],
    "sg:phone":"+44 131 554 6418",
    "sg:postcode":"EH7 4LH",
    "sg:province":"City of Edinburgh",
    "sg:tags":[
        "builder"
    ],
    "wof:name":"J Smart & Co (Contractors)",
    "wof:placetype":"venue"
},
  "geometry": {"coordinates":[-3.189119,55.969818],"type":"Point"}
}