{
  "type": "Feature",
  "properties": {
    "iso:country":"GB",
    "sg:address":"10 Balmoral Close, Thurlstone",
    "sg:city":"Sheffield",
    "sg:classifiers":[
        {
            "category":"Professional",
            "subcategory":"Secretarial Services",
            "type":"Services"
        }
    ],
    "sg:phone":"+44 1226 370030",
    "sg:postcode":"S36 9RT",
    "sg:province":"South Yorkshire",
    "wof:name":"M B Secretarial Services",
    "wof:placetype":"venue"
},
  "geometry": {"coordinates":[-1.651502,53.530544],"type":"Point"}
}