{
  "type": "Feature",
  "properties": {
    "iso:country":"GB",
    "sg:address":"77 Compton Road",
    "sg:city":"Wolverhampton",
    "sg:classifiers":[
        {
            "category":"Professional",
            "subcategory":"Management & Consulting",
            "type":"Services"
        }
    ],
    "sg:phone":"+44 1902 717789",
    "sg:postcode":"WV3 9QH",
    "sg:province":"Staffordshire",
    "sg:tags":[
        "marketing",
        "consultant"
    ],
    "wof:name":"Ray Symons Associates",
    "wof:placetype":"venue"
},
  "geometry": {"coordinates":[-2.15376091,52.5864143372],"type":"Point"}
}