{
  "type": "Feature",
  "properties": {
    "iso:country":"GB",
    "sg:address":"Unit C, Horton Close",
    "sg:city":"West Drayton",
    "sg:classifiers":[
        {
            "category":"Manufacturing",
            "subcategory":"Metals",
            "type":"Manufacturing & Wholesale Goods"
        }
    ],
    "sg:phone":"+44 1895 443194",
    "sg:postcode":"UB7 8EB",
    "sg:province":"Greater London",
    "sg:tags":[
        "fab",
        "foundry"
    ],
    "wof:name":"New Pro Foundries Ltd.",
    "wof:placetype":"venue"
},
  "geometry": {"coordinates":[-0.4596480131,51.5103797913],"type":"Point"}
}