{
  "type": "Feature",
  "properties": {
    "iso:country":"GB",
    "sg:address":"233 Royal College St",
    "sg:city":"Camden",
    "sg:classifiers":[
        {
            "category":"Freight",
            "type":"Transportation"
        }
    ],
    "sg:phone":"+44 20 7267 3958",
    "sg:postcode":"NW1 9LT",
    "sg:province":"Greater London",
    "sg:tags":[
        "overseas",
        "shipping",
        "removal"
    ],
    "wof:name":"Parcelworld Ltd",
    "wof:placetype":"venue"
},
  "geometry": {"coordinates":[-0.139081,51.542294],"type":"Point"}
}