{
  "type": "Feature",
  "properties": {
    "iso:country":"GB",
    "sg:address":"P O Box 146",
    "sg:city":"Northwich",
    "sg:classifiers":[
        {
            "category":"Social Services",
            "subcategory":"Adult Care",
            "type":"Services"
        }
    ],
    "sg:phone":"+44 1606 892419",
    "sg:postcode":"CW9 6RS",
    "sg:province":"Cheshire",
    "sg:tags":[
        "home",
        "help",
        "private"
    ],
    "wof:name":"Freedom Home Care Services",
    "wof:placetype":"venue"
},
  "geometry": {"coordinates":[-2.503409,53.294182],"type":"Point"}
}