{
  "type": "Feature",
  "properties": {
    "addr:full":"Unit 16 Broughton Business Centre, Broughton La Manchester Greater Manchester M7 1UF",
    "addr:housenumber":"unit 16",
    "addr:postcode":"m7 1uf",
    "addr:street":"Broughton Business Centre Broughton La Manchester",
    "iso:country":"GB",
    "sg:address":"Unit 16 Broughton Business Centre, Broughton La",
    "sg:city":"Manchester",
    "sg:classifiers":[
        {
            "category":"Cinema",
            "subcategory":"Movie Rental",
            "type":"Entertainment"
        },
        {
            "category":"Shopping",
            "subcategory":"Computers & Home Electronics",
            "type":"Retail Goods"
        }
    ],
    "sg:phone":"+44 161 832 4923",
    "sg:postcode":"M7 1UF",
    "sg:province":"Greater Manchester",
    "sg:tags":[
        "tape",
        "video",
        "library"
    ],
    "wof:name":"Orbit Video",
    "wof:placetype":"venue"
},
  "geometry": {"coordinates":[-2.2560501099,53.4957618713],"type":"Point"}
}