{
  "type": "Feature",
  "properties": {
    "iso:country":"GB",
    "sg:address":"Sundon Pk Service Station, Sundon Pk Rd",
    "sg:city":"Luton",
    "sg:classifiers":[
        {
            "category":"Autos & Motor Vehicles",
            "subcategory":"Automobile Sales",
            "type":"Retail Goods"
        }
    ],
    "sg:postcode":"LU3 3AA",
    "sg:province":"Bedfordshire",
    "sg:tags":[
        "car"
    ],
    "wof:name":"Sundon Auto's",
    "wof:placetype":"venue"
},
  "geometry": {"coordinates":[-0.477329,51.931274],"type":"Point"}
}