{
  "type": "Feature",
  "properties": {
    "addr:full":"61 Edinburgh Road, Baillieston Glasgow East Dunbartonshire G69 6RS",
    "addr:housenumber":"61",
    "addr:postcode":"g69 6rs",
    "addr:street":"Edinburgh Road",
    "iso:country":"GB",
    "sg:address":"61 Edinburgh Road, Baillieston",
    "sg:city":"Glasgow",
    "sg:classifiers":[
        {
            "category":"Autos & Motor Vehicles",
            "subcategory":"Fuel & Gas Station",
            "type":"Retail Goods"
        }
    ],
    "sg:phone":"+44 141 773 5110",
    "sg:postcode":"G69 6RS",
    "sg:province":"East Dunbartonshire",
    "sg:tags":[
        "hr",
        "petrol"
    ],
    "wof:name":"Shell Garrowhill",
    "wof:placetype":"venue"
},
  "geometry": {"coordinates":[-4.1120090485,55.8544387817],"type":"Point"}
}