{
  "type": "Feature",
  "properties": {
    "iso:country":"GB",
    "sg:address":"4 Market Place",
    "sg:city":"Whitby",
    "sg:classifiers":[
        {
            "category":"Transit Center",
            "subcategory":"Freight",
            "type":"Transportation"
        }
    ],
    "sg:postcode":"YO22 4DD",
    "sg:province":"North Yorkshire",
    "sg:tags":[
        "shop",
        "craft",
        "centre"
    ],
    "wof:name":"Sheila Sawyer Decoupage Centre",
    "wof:placetype":"venue"
},
  "geometry": {"coordinates":[-0.6121069789,54.4880142212],"type":"Point"}
}