{
  "type": "Feature",
  "properties": {
    "addr:full":"Top Farm, Fryston Lane Knottingley North Yorkshire WF11 8SF",
    "addr:postcode":"wf11 8sf",
    "addr:street":"Fryston Lane",
    "iso:country":"GB",
    "sg:address":"Top Farm, Fryston Lane",
    "sg:city":"Knottingley",
    "sg:classifiers":[
        {
            "category":"Recreation",
            "subcategory":"Campground",
            "type":"Entertainment"
        }
    ],
    "sg:postcode":"WF11 8SF",
    "sg:province":"North Yorkshire",
    "sg:tags":[
        "caravan",
        "park"
    ],
    "wof:name":"Holmfield Caravan Pk",
    "wof:placetype":"venue"
},
  "geometry": {"coordinates":[-1.259354949,53.7076072693],"type":"Point"}
}