{
  "type": "Feature",
  "properties": {
    "addr:full":"Rossmere Way Hartlepool Durham TS25 5EB",
    "addr:postcode":"ts25 5eb",
    "addr:street":"Rossmere Way",
    "iso:country":"GB",
    "sg:address":"Rossmere Way",
    "sg:city":"Hartlepool",
    "sg:classifiers":[
        {
            "category":"Community Center",
            "subcategory":"Youth",
            "type":"Public Place"
        },
        {
            "category":"Government",
            "subcategory":"Office",
            "type":"Public Place"
        }
    ],
    "sg:phone":"+44 1429 273741",
    "sg:postcode":"TS25 5EB",
    "sg:province":"Durham",
    "sg:tags":[
        "organisation",
        "local",
        "centre"
    ],
    "wof:name":"Rossmere Youth Centre",
    "wof:placetype":"venue"
},
  "geometry": {"coordinates":[-1.22861,54.662045],"type":"Point"}
}