{
  "type": "Feature",
  "properties": {
    "addr:full":"2 Three Tuns Pde, Stafford Rd Wolverhampton Staffordshire WV10 6BA",
    "addr:housenumber":"2",
    "addr:postcode":"wv10 6ba",
    "addr:street":"Three Tuns;Stafford Rd",
    "iso:country":"GB",
    "sg:address":"2 Three Tuns Pde, Stafford Rd",
    "sg:city":"Wolverhampton",
    "sg:classifiers":[
        {
            "category":"Banks & Credit Unions",
            "subcategory":"Bank",
            "type":"Services"
        }
    ],
    "sg:phone":"+44 1902 783325",
    "sg:postcode":"WV10 6BA",
    "sg:province":"Staffordshire",
    "wof:name":"NatWest",
    "wof:placetype":"venue"
},
  "geometry": {"coordinates":[-2.1285760403,52.6206588745],"type":"Point"}
}