{
  "type": "Feature",
  "properties": {
    "iso:country":"GB",
    "sg:address":"16 Hallamgate Road",
    "sg:city":"Sheffield",
    "sg:classifiers":[
        {
            "category":"Social Services",
            "subcategory":"Adult Care",
            "type":"Services"
        }
    ],
    "sg:phone":"+44 114 266 3134",
    "sg:postcode":"S10 5BT",
    "sg:province":"South Yorkshire",
    "sg:tags":[
        "day",
        "centre"
    ],
    "wof:name":"Hallamgate",
    "wof:placetype":"venue"
},
  "geometry": {"coordinates":[-1.506092,53.379738],"type":"Point"}
}