{
  "type": "Feature",
  "properties": {
    "addr:full":"Priory Meadow Hastings East Sussex TN34 1PH",
    "addr:postcode":"tn34 1ph",
    "addr:street":"Priory Meadow Hastings",
    "iso:country":"GB",
    "sg:address":"Priory Meadow",
    "sg:city":"Hastings",
    "sg:classifiers":[
        {
            "category":"Organizations",
            "subcategory":"Non-profit Organization",
            "type":"Services"
        }
    ],
    "sg:phone":"+44 1424 219295",
    "sg:postcode":"TN34 1PH",
    "sg:province":"East Sussex",
    "sg:tags":[
        "organisation",
        "voluntary",
        "charity"
    ],
    "wof:name":"Bexhill & Hastings Parkinsons Disease Society",
    "wof:placetype":"venue"
},
  "geometry": {"coordinates":[0.578698,50.85619],"type":"Point"}
}