{
  "type": "Feature",
  "properties": {
    "addr:full":"50a Sighthill Crescent Edinburgh City of Edinburgh EH11 4QB",
    "addr:housenumber":"50a",
    "addr:postcode":"eh11 4qb",
    "addr:street":"Sighthill Crescent",
    "iso:country":"GB",
    "sg:address":"50a Sighthill Crescent",
    "sg:city":"Edinburgh",
    "sg:classifiers":[
        {
            "category":"Manufacturing",
            "subcategory":"Tools & Machinery",
            "type":"Manufacturing & Wholesale Goods"
        }
    ],
    "sg:phone":"+44 131 458 3886",
    "sg:postcode":"EH11 4QB",
    "sg:province":"City of Edinburgh",
    "sg:tags":[
        "design",
        "maker"
    ],
    "wof:name":"Saw & Tooling Services",
    "wof:placetype":"venue"
},
  "geometry": {"coordinates":[-3.282677,55.920635],"type":"Point"}
}