{
  "type": "Feature",
  "properties": {
    "addr:full":"29 Kilburn Lane London Greater London W10 4AE",
    "addr:housenumber":"29",
    "addr:postcode":"w10 4ae",
    "addr:street":"Kilburn Lane",
    "iso:country":"GB",
    "sg:address":"29 Kilburn Lane",
    "sg:city":"London",
    "sg:classifiers":[
        {
            "category":"Autos & Motor Vehicles",
            "subcategory":"Auto Supplies",
            "type":"Retail Goods"
        }
    ],
    "sg:phone":"+44 20 8964 5052",
    "sg:postcode":"W10 4AE",
    "sg:province":"Greater London",
    "sg:tags":[
        "tyre"
    ],
    "wof:name":"D A T Tyre Supplies Ltd.",
    "wof:placetype":"venue"
},
  "geometry": {"coordinates":[-0.2162149996,51.5292778015],"type":"Point"}
}