{
  "type": "Feature",
  "properties": {
    "addr:full":"Greasehayes Farm, Stockland Honiton Devon EX14 9LL",
    "addr:housenumber":"farm stockland",
    "addr:postcode":"ex14 9ll",
    "iso:country":"GB",
    "sg:address":"Greasehayes Farm, Stockland",
    "sg:city":"Honiton",
    "sg:classifiers":[
        {
            "category":"Farming",
            "subcategory":"Dairy Farm",
            "type":"Manufacturing & Wholesale Goods"
        }
    ],
    "sg:phone":"+44 1404 881295",
    "sg:postcode":"EX14 9LL",
    "sg:province":"Devon",
    "wof:name":"O.V Moore",
    "wof:placetype":"venue"
},
  "geometry": {"coordinates":[-3.0731759071,50.8371047974],"type":"Point"}
}