{
  "type": "Feature",
  "properties": {
    "iso:country":"GB",
    "sg:address":"25 Church Street",
    "sg:city":"Kidderminster",
    "sg:classifiers":[
        {
            "category":"Professional",
            "subcategory":"Accounting & Tax Preparation",
            "type":"Services"
        },
        {
            "category":"Health Services",
            "subcategory":"Nursing And Care Facility",
            "type":"Services"
        }
    ],
    "sg:phone":"+44 1562 822138",
    "sg:postcode":"DY10 2AW",
    "sg:province":"Staffordshire",
    "sg:tags":[
        "home",
        "accountant"
    ],
    "wof:name":"The Hawthorns Ltd.",
    "wof:placetype":"venue"
},
  "geometry": {"coordinates":[-2.249772,52.389263],"type":"Point"}
}