{
  "type": "Feature",
  "properties": {
    "addr:full":"Torc High School, Silver Link Road Tamworth Staffordshire B77 2EA",
    "addr:postcode":"b77 2ea",
    "addr:street":"Silver Link Road",
    "iso:country":"GB",
    "sg:address":"Torc High School, Silver Link Road",
    "sg:city":"Tamworth",
    "sg:classifiers":[
        {
            "category":"Community Center",
            "subcategory":"Youth",
            "type":"Public Place"
        }
    ],
    "sg:phone":"+44 1827 289745",
    "sg:postcode":"B77 2EA",
    "sg:province":"Staffordshire",
    "sg:tags":[
        "organisation",
        "centre"
    ],
    "wof:name":"Area Office Youth Community Centre",
    "wof:placetype":"venue"
},
  "geometry": {"coordinates":[-1.66036,52.623631],"type":"Point"}
}