{
  "type": "Feature",
  "properties": {
    "addr:full":"41 Black Prince Avenue Peterborough Cambridgeshire PE6 8LR",
    "addr:housenumber":"41",
    "addr:postcode":"pe6 8lr",
    "addr:street":"Black Prince Avenue",
    "iso:country":"GB",
    "sg:address":"41 Black Prince Avenue",
    "sg:city":"Peterborough",
    "sg:classifiers":[
        {
            "category":"Autos & Motor Vehicles",
            "subcategory":"Motorcycle Sales",
            "type":"Retail Goods"
        }
    ],
    "sg:phone":"+44 1778 346681",
    "sg:postcode":"PE6 8LR",
    "sg:province":"Cambridgeshire",
    "sg:tags":[
        "chauffeur",
        "driven",
        "car"
    ],
    "wof:name":"Executive Travel",
    "wof:placetype":"venue"
},
  "geometry": {"coordinates":[-0.317339,52.68306],"type":"Point"}
}