{
  "type": "Feature",
  "properties": {
    "iso:country":"GB",
    "sg:address":"Elland Road, Brierfield",
    "sg:city":"Nelson",
    "sg:classifiers":[
        {
            "category":"Education",
            "subcategory":"School",
            "type":"Public Place"
        }
    ],
    "sg:phone":"+44 1282 614640",
    "sg:postcode":"BB9 5RX",
    "sg:province":"Lancashire",
    "sg:tags":[
        "local",
        "authority"
    ],
    "wof:name":"Mansfield High School",
    "wof:placetype":"venue"
},
  "geometry": {"coordinates":[-2.228207,53.827435],"type":"Point"}
}