{
  "type": "Feature",
  "properties": {
    "addr:full":"Dunleven, Spencers Pl Horsham West Sussex RH12 2EZ",
    "addr:postcode":"rh12 2ez",
    "addr:street":"Spencers Pl",
    "iso:country":"GB",
    "sg:address":"Dunleven, Spencers Pl",
    "sg:city":"Horsham",
    "sg:classifiers":[
        {
            "category":"Building & Trades",
            "subcategory":"Plumbing",
            "type":"Services"
        }
    ],
    "sg:phone":"+44 1403 267296",
    "sg:postcode":"RH12 2EZ",
    "sg:province":"West Sussex",
    "sg:tags":[
        "heating"
    ],
    "wof:name":"G Snooks",
    "wof:placetype":"venue"
},
  "geometry": {"coordinates":[-0.3354389966,51.0735855103],"type":"Point"}
}