{
  "type": "Feature",
  "properties": {
    "addr:full":"438 Greenford Avenue, Hanwell London Greater London W7 3DD",
    "addr:housenumber":"438",
    "addr:postcode":"w7 3dd",
    "addr:street":"Greenford Avenue",
    "iso:country":"GB",
    "sg:address":"438 Greenford Avenue, Hanwell",
    "sg:city":"London",
    "sg:classifiers":[
        {
            "category":"Health Services",
            "subcategory":"Doctor",
            "type":"Services"
        }
    ],
    "sg:phone":"+44 20 8578 1430",
    "sg:postcode":"W7 3DD",
    "sg:province":"Greater London",
    "sg:tags":[
        "practitioners"
    ],
    "wof:name":"Bipin R Patel",
    "wof:placetype":"venue"
},
  "geometry": {"coordinates":[-0.3417800069,51.5254478455],"type":"Point"}
}