{
  "type": "Feature",
  "properties": {
    "addr:full":"12-16 Westland Place London Greater London N1 7LP",
    "addr:housenumber":"12-16",
    "addr:postcode":"n1 7lp",
    "addr:street":"Westland Place",
    "iso:country":"GB",
    "sg:address":"12-16 Westland Place",
    "sg:city":"London",
    "sg:classifiers":[
        {
            "category":"Professional",
            "subcategory":"Computer Services",
            "type":"Services"
        }
    ],
    "sg:phone":"+44 20 7490 7977",
    "sg:postcode":"N1 7LP",
    "sg:province":"Greater London",
    "sg:tags":[
        "system",
        "software"
    ],
    "wof:name":"A V T Systems Ltd.",
    "wof:placetype":"venue"
},
  "geometry": {"coordinates":[-0.090279,51.52845],"type":"Point"}
}