{
  "type": "Feature",
  "properties": {
    "addr:full":"Molly Millers La Wokingham Berkshire RG41 2PX",
    "addr:postcode":"rg41 2px",
    "addr:street":"La",
    "iso:country":"GB",
    "sg:address":"Molly Millers La",
    "sg:city":"Wokingham",
    "sg:classifiers":[
        {
            "category":"Professional",
            "subcategory":"Engineering",
            "type":"Services"
        }
    ],
    "sg:postcode":"RG41 2PX",
    "sg:province":"Berkshire",
    "sg:tags":[
        "precision",
        "engineer"
    ],
    "wof:name":"A D M Electrodes Ltd",
    "wof:placetype":"venue"
},
  "geometry": {"coordinates":[-0.847959,51.407104],"type":"Point"}
}