{
  "type": "Feature",
  "properties": {
    "addr:full":"45 Craven Road London Greater London W2 3BX",
    "addr:housenumber":"45",
    "addr:postcode":"w2 3bx",
    "addr:street":"Craven Road",
    "iso:country":"GB",
    "sg:address":"45 Craven Road",
    "sg:city":"London",
    "sg:classifiers":[
        {
            "category":"Shopping",
            "subcategory":"Pharmacy",
            "type":"Retail Goods"
        }
    ],
    "sg:phone":"+44 20 7723 1633",
    "sg:postcode":"W2 3BX",
    "sg:province":"Greater London",
    "sg:tags":[
        "pharmacist",
        "chemist"
    ],
    "wof:name":"Jerseylodge Ltd.",
    "wof:placetype":"venue"
},
  "geometry": {"coordinates":[-0.179316,51.51339],"type":"Point"}
}