{
  "type": "Feature",
  "properties": {
    "addr:full":"1 Belvedere Parade Bridlington East Riding of Yorkshire YO15 3LX",
    "addr:housenumber":"1",
    "addr:postcode":"yo15 3lx",
    "addr:street":"Belvedere Parade",
    "iso:country":"GB",
    "sg:address":"1 Belvedere Parade",
    "sg:city":"Bridlington",
    "sg:classifiers":[
        {
            "category":"Building & Trades",
            "subcategory":"Cleaning & Sanitation",
            "type":"Services"
        }
    ],
    "sg:phone":"+44 1262 400066",
    "sg:postcode":"YO15 3LX",
    "sg:province":"East Riding of Yorkshire",
    "sg:tags":[
        "contracting",
        "commercial"
    ],
    "wof:name":"Bob Webster & Sons",
    "wof:placetype":"venue"
},
  "geometry": {"coordinates":[-0.2041379958,54.0715904236],"type":"Point"}
}