{
  "type": "Feature",
  "properties": {
    "iso:country":"GB",
    "sg:address":"100 Cobham Road, Ferndown Industrial Estate, Stapehill",
    "sg:city":"Wimborne",
    "sg:classifiers":[
        {
            "category":"Manufacturing",
            "subcategory":"Metals",
            "type":"Manufacturing & Wholesale Goods"
        }
    ],
    "sg:phone":"+44 1202 876270",
    "sg:postcode":"BH21 7PQ",
    "sg:province":"Dorset",
    "sg:tags":[
        "foundry"
    ],
    "wof:name":"D & H Castings Ltd.",
    "wof:placetype":"venue"
},
  "geometry": {"coordinates":[-1.912977,50.814011],"type":"Point"}
}