{
  "type": "Feature",
  "properties": {
    "addr:full":"Portland Road Colchester Essex CO2 7EQ",
    "addr:postcode":"co2 7eq",
    "addr:street":"Portland Road Colchester",
    "iso:country":"GB",
    "sg:address":"Portland Road",
    "sg:city":"Colchester",
    "sg:classifiers":[
        {
            "category":"Food & Beverages",
            "subcategory":"Groceries & Convenience Stores",
            "type":"Retail Goods"
        }
    ],
    "sg:phone":"+44 1206 572922",
    "sg:postcode":"CO2 7EQ",
    "sg:province":"Essex",
    "sg:tags":[
        "merchant",
        "potato"
    ],
    "wof:name":"H & E Edwards (Colchester) Ltd.",
    "wof:placetype":"venue"
},
  "geometry": {"coordinates":[0.904254,51.885532],"type":"Point"}
}