{
  "type": "Feature",
  "properties": {
    "addr:full":"29 Evelyn Terr, Mountain Bradford West Yorkshire BD13 1LF",
    "addr:housenumber":"29",
    "addr:postcode":"bd13 1lf",
    "addr:street":"Evelyn Terr",
    "iso:country":"GB",
    "sg:address":"29 Evelyn Terr, Mountain",
    "sg:city":"Bradford",
    "sg:classifiers":[
        {
            "category":"Building & Trades",
            "subcategory":"Plumbing",
            "type":"Services"
        }
    ],
    "sg:postcode":"BD13 1LF",
    "sg:province":"West Yorkshire",
    "sg:tags":[
        "heating"
    ],
    "wof:name":"Gray,Rodney,",
    "wof:placetype":"venue"
},
  "geometry": {"coordinates":[-1.860294,53.774666],"type":"Point"}
}