{
  "type": "Feature",
  "properties": {
    "iso:country":"GB",
    "sg:address":"Marshwood Close",
    "sg:city":"Canterbury",
    "sg:classifiers":[
        {
            "category":"Retail",
            "subcategory":"Storage",
            "type":"Services"
        }
    ],
    "sg:phone":"+44 1227 463075",
    "sg:postcode":"CT1 1DX",
    "sg:province":"Kent",
    "sg:tags":[
        "household",
        "removal"
    ],
    "wof:name":"Jordan & Jarrett Ltd",
    "wof:placetype":"venue"
},
  "geometry": {"coordinates":[1.0984239578,51.2909355164],"type":"Point"}
}