{
  "type": "Feature",
  "properties": {
    "iso:country":"GB",
    "sg:address":"11 Wooler Road",
    "sg:city":"Hartlepool",
    "sg:classifiers":[
        {
            "category":"Government",
            "subcategory":"Office",
            "type":"Public Place"
        }
    ],
    "sg:phone":"+44 1429 274381",
    "sg:postcode":"TS26 0HB",
    "sg:province":"Durham",
    "sg:tags":[
        "local"
    ],
    "wof:name":"Hazelhurst Hostel",
    "wof:placetype":"venue"
},
  "geometry": {"coordinates":[-1.2347910404,54.6874313354],"type":"Point"}
}