{
  "type": "Feature",
  "properties": {
    "iso:country":"GB",
    "sg:address":"124 Meriden Avenue, Wollaston",
    "sg:city":"Stourbridge",
    "sg:classifiers":[
        {
            "category":"Building & Trades",
            "subcategory":"Landscaping Services",
            "type":"Services"
        }
    ],
    "sg:postcode":"DY8 4QR",
    "sg:province":"Staffordshire",
    "sg:tags":[
        "forestry",
        "tree"
    ],
    "wof:name":"John Blackwell Tree Surgery",
    "wof:placetype":"venue"
},
  "geometry": {"coordinates":[-2.168238,52.460426],"type":"Point"}
}