{
  "type": "Feature",
  "properties": {
    "iso:country":"GB",
    "sg:address":"417 Chorley Rd",
    "sg:city":"Manchester",
    "sg:classifiers":[
        {
            "category":"Health Services",
            "subcategory":"Doctor",
            "type":"Services"
        }
    ],
    "sg:phone":"+44 161 281 4111",
    "sg:postcode":"M27 9UQ",
    "sg:province":"Greater Manchester",
    "sg:tags":[
        "practitioners"
    ],
    "wof:name":"A K L De Silva",
    "wof:placetype":"venue"
},
  "geometry": {"coordinates":[-2.347702,53.515747],"type":"Point"}
}