{
  "type": "Feature",
  "properties": {
    "addr:full":"15 Craven Park Road London Greater London NW10 8SE",
    "addr:housenumber":"15",
    "addr:postcode":"nw10 8se",
    "addr:street":"Craven Park Road",
    "iso:country":"GB",
    "sg:address":"15 Craven Park Road",
    "sg:city":"London",
    "sg:classifiers":[
        {
            "category":"Fast Food",
            "type":"Food & Drink"
        }
    ],
    "sg:phone":"+44 20 8965 1657",
    "sg:postcode":"NW10 8SE",
    "sg:province":"Greater London",
    "sg:tags":[
        "away",
        "take"
    ],
    "wof:name":"Golden Duck Chinese Take Away",
    "wof:placetype":"venue"
},
  "geometry": {"coordinates":[-0.2558149993,51.5409812927],"type":"Point"}
}