{
  "type": "Feature",
  "properties": {
    "addr:full":"Po Box 222 Barnet Hertfordshire EN5 5BD",
    "addr:housenumber":"po",
    "addr:postcode":"en5 5bd",
    "addr:street":"Box 222",
    "iso:country":"GB",
    "sg:address":"Po Box 222",
    "sg:city":"Barnet",
    "sg:classifiers":[
        {
            "category":"Professional",
            "subcategory":"Management & Consulting",
            "type":"Services"
        }
    ],
    "sg:postcode":"EN5 5BD",
    "sg:province":"Hertfordshire",
    "sg:tags":[
        "music"
    ],
    "wof:name":"Ferocious Music",
    "wof:placetype":"venue"
},
  "geometry": {"coordinates":[-0.18658,51.652901],"type":"Point"}
}