{
  "type": "Feature",
  "properties": {
    "iso:country":"GB",
    "sg:address":"Liverpool Free Port, 80 Regent Road",
    "sg:city":"Liverpool",
    "sg:classifiers":[
        {
            "category":"Freight",
            "type":"Transportation"
        }
    ],
    "sg:phone":"+44 151 287 7553",
    "sg:postcode":"L20 1BL",
    "sg:province":"Merseyside",
    "sg:tags":[
        "haulage",
        "road"
    ],
    "wof:name":"B A T Transport Ltd.",
    "wof:placetype":"venue"
},
  "geometry": {"coordinates":[-3.0027201176,53.445110321],"type":"Point"}
}