{
  "type": "Feature",
  "properties": {
    "iso:country":"GB",
    "sg:address":"West Hill",
    "sg:city":"Wincanton",
    "sg:classifiers":[
        {
            "category":"Education",
            "subcategory":"School",
            "type":"Public Place"
        },
        {
            "category":"Government",
            "subcategory":"Office",
            "type":"Public Place"
        }
    ],
    "sg:phone":"+44 1963 32368",
    "sg:postcode":"BA9 9BX",
    "sg:province":"Somerset",
    "sg:tags":[
        "local",
        "authority"
    ],
    "wof:name":"King Arthur's Community School",
    "wof:placetype":"venue"
},
  "geometry": {"coordinates":[-2.417954,51.05616],"type":"Point"}
}