{
  "type": "Feature",
  "properties": {
    "iso:country":"GB",
    "sg:address":"Creek Haven, Wharf Road, Fobbing",
    "sg:city":"Stanford-le-hope",
    "sg:classifiers":[
        {
            "category":"Building & Trades",
            "subcategory":"Construction",
            "type":"Services"
        }
    ],
    "sg:phone":"+44 1375 672977",
    "sg:postcode":"SS17 9JL",
    "sg:province":"Essex",
    "sg:tags":[
        "decorator",
        "painter"
    ],
    "wof:name":"F J Merrison & Son Ltd",
    "wof:placetype":"venue"
},
  "geometry": {"coordinates":[0.473696,51.528828],"type":"Point"}
}