{
  "type": "Feature",
  "properties": {
    "addr:full":"The Surgery, Hodgson Centre, Hodgson Avenue Peterborough Cambridgeshire PE4 5EG",
    "addr:postcode":"pe4 5eg",
    "addr:street":"Hodgson;Hodgson Avenue",
    "iso:country":"GB",
    "sg:address":"The Surgery, Hodgson Centre, Hodgson Avenue",
    "sg:city":"Peterborough",
    "sg:classifiers":[
        {
            "category":"Health Services",
            "subcategory":"Doctor",
            "type":"Services"
        }
    ],
    "sg:phone":"+44 1733 573232",
    "sg:postcode":"PE4 5EG",
    "sg:province":"Cambridgeshire",
    "sg:tags":[
        "practitioners"
    ],
    "wof:name":"V S Iyer",
    "wof:placetype":"venue"
},
  "geometry": {"coordinates":[-0.27933,52.628479],"type":"Point"}
}