{
  "type": "Feature",
  "properties": {
    "iso:country":"GB",
    "sg:address":"38-39 Market Hall, Low Street",
    "sg:city":"Keighley",
    "sg:classifiers":[
        {
            "category":"Shopping",
            "subcategory":"Luggage & Leather Goods",
            "type":"Retail Goods"
        }
    ],
    "sg:postcode":"BD21 3PQ",
    "sg:province":"West Yorkshire",
    "sg:tags":[
        "shop",
        "leathergoods"
    ],
    "wof:name":"Franklin Handbags",
    "wof:placetype":"venue"
},
  "geometry": {"coordinates":[-1.9096740484,53.8663635254],"type":"Point"}
}