{
  "type": "Feature",
  "properties": {
    "addr:full":"15 Old Palace Rd Norwich Norfolk NR2 4JE",
    "addr:housenumber":"15",
    "addr:postcode":"nr2 4je",
    "addr:street":"Old Palace Rd",
    "iso:country":"GB",
    "sg:address":"15 Old Palace Rd",
    "sg:city":"Norwich",
    "sg:classifiers":[
        {
            "category":"Autos & Motor Vehicles",
            "subcategory":"Auto Supplies",
            "type":"Retail Goods"
        }
    ],
    "sg:phone":"+44 1603 614940",
    "sg:postcode":"NR2 4JE",
    "sg:province":"Norfolk",
    "sg:tags":[
        "tyre"
    ],
    "wof:name":"Holburn Tyre & Exhaust Centre",
    "wof:placetype":"venue"
},
  "geometry": {"coordinates":[1.278464,52.634144],"type":"Point"}
}