{
  "type": "Feature",
  "properties": {
    "addr:full":"Building H1, Westcott Venture Park, Westcott Aylesbury Buckinghamshire HP18 0XB",
    "addr:housenumber":"h1",
    "addr:postcode":"hp18 0xb",
    "addr:street":"Westcott Venture Park",
    "iso:country":"GB",
    "sg:address":"Building H1, Westcott Venture Park, Westcott",
    "sg:city":"Aylesbury",
    "sg:classifiers":[
        {
            "category":"Retail",
            "subcategory":"Storage",
            "type":"Services"
        }
    ],
    "sg:phone":"+44 1296 655864",
    "sg:postcode":"HP18 0XB",
    "sg:province":"Buckinghamshire",
    "sg:tags":[
        "household",
        "removal"
    ],
    "wof:name":"Fentonwharfe Ltd.",
    "wof:placetype":"venue"
},
  "geometry": {"coordinates":[-0.957499,51.846924],"type":"Point"}
}