{
  "type": "Feature",
  "properties": {
    "addr:full":"6 West Main St Bathgate North Lanarkshire EH47 0QZ",
    "addr:housenumber":"6",
    "addr:postcode":"eh47 0qz",
    "addr:street":"West Main St Bathgate",
    "iso:country":"GB",
    "sg:address":"6 West Main St",
    "sg:city":"Bathgate",
    "sg:classifiers":[
        {
            "category":"Home & Garden",
            "subcategory":"Home Furnishings",
            "type":"Retail Goods"
        }
    ],
    "sg:phone":"+44 1501 740337",
    "sg:postcode":"EH47 0QZ",
    "sg:province":"North Lanarkshire",
    "sg:tags":[
        "blind",
        "curtain",
        "fitting"
    ],
    "wof:name":"Warrens",
    "wof:placetype":"venue"
},
  "geometry": {"coordinates":[-3.6852519512,55.8668136597],"type":"Point"}
}