{
  "type": "Feature",
  "properties": {
    "addr:full":"Pennine House Newcastle-upon-tyne Tyne and Wear NE2 1NE",
    "addr:postcode":"ne2 1ne",
    "iso:country":"GB",
    "sg:address":"Pennine House",
    "sg:city":"Newcastle-upon-tyne",
    "sg:classifiers":[
        {
            "category":"Professional",
            "subcategory":"Credit Reporting & Collection",
            "type":"Services"
        }
    ],
    "sg:postcode":"NE2 1NE",
    "sg:province":"Tyne and Wear",
    "sg:tags":[
        "collecting",
        "agency"
    ],
    "wof:name":"Logic Group Plc",
    "wof:placetype":"venue"
},
  "geometry": {"coordinates":[-1.60419,54.982159],"type":"Point"}
}