{
  "type": "Feature",
  "properties": {
    "addr:full":"398 London Road South Lowestoft Suffolk NR33 0BQ",
    "addr:housenumber":"398",
    "addr:postcode":"nr33 0bq",
    "addr:street":"London Road South",
    "iso:country":"GB",
    "sg:address":"398 London Road South",
    "sg:city":"Lowestoft",
    "sg:classifiers":[
        {
            "category":"Travel",
            "subcategory":"Hotels & Motels",
            "type":"Entertainment"
        }
    ],
    "sg:phone":"+44 1502 572659",
    "sg:postcode":"NR33 0BQ",
    "sg:province":"Suffolk",
    "sg:tags":[
        "house",
        "guest"
    ],
    "wof:name":"Fairways Guest House",
    "wof:placetype":"venue"
},
  "geometry": {"coordinates":[1.738841,52.460999],"type":"Point"}
}