{
  "type": "Feature",
  "properties": {
    "iso:country":"GB",
    "sg:address":"Gloucester Rd",
    "sg:city":"Bath",
    "sg:classifiers":[
        {
            "category":"Fast Food",
            "type":"Food & Drink"
        }
    ],
    "sg:postcode":"BA1 8AD",
    "sg:province":"Bath and North East Somerset",
    "sg:tags":[
        "away",
        "take"
    ],
    "wof:name":"Swainswick Heights",
    "wof:placetype":"venue"
},
  "geometry": {"coordinates":[-2.3681368828,51.4367904663],"type":"Point"}
}