{
  "type": "Feature",
  "properties": {
    "addr:full":"52 Stanhope Rd Jarrow Tyne and Wear NE32 3UB",
    "addr:housenumber":"52",
    "addr:postcode":"ne32 3ub",
    "addr:street":"Stanhope Rd",
    "iso:country":"GB",
    "sg:address":"52 Stanhope Rd",
    "sg:city":"Jarrow",
    "sg:classifiers":[
        {
            "category":"Shopping",
            "subcategory":"News",
            "type":"Retail Goods"
        }
    ],
    "sg:phone":"+44 191 489 7439",
    "sg:postcode":"NE32 3UB",
    "sg:province":"Tyne and Wear",
    "sg:tags":[
        "newsagent"
    ],
    "wof:name":"Collins News",
    "wof:placetype":"venue"
},
  "geometry": {"coordinates":[-1.4726929665,54.9693260193],"type":"Point"}
}