{
  "type": "Feature",
  "properties": {
    "addr:full":"24 Oliver Street Leicester Leicestershire LE2 7PD",
    "addr:housenumber":"24",
    "addr:postcode":"le2 7pd",
    "addr:street":"Oliver Street",
    "iso:country":"GB",
    "sg:address":"24 Oliver Street",
    "sg:city":"Leicester",
    "sg:classifiers":[
        {
            "category":"Government",
            "subcategory":"Office",
            "type":"Public Place"
        },
        {
            "category":"Social Services",
            "subcategory":"Adult Care",
            "type":"Services"
        },
        {
            "category":"Social Services",
            "subcategory":"Retirement Home",
            "type":"Services"
        }
    ],
    "sg:phone":"+44 116 283 9291",
    "sg:postcode":"LE2 7PD",
    "sg:province":"Leicestershire",
    "sg:tags":[
        "housing",
        "local",
        "accommodation",
        "sheltered"
    ],
    "wof:name":"Cromwell House",
    "wof:placetype":"venue"
},
  "geometry": {"coordinates":[-1.137435,52.612049],"type":"Point"}
}