{
  "type": "Feature",
  "properties": {
    "addr:full":"Guy Thornycroft Court, Toll Gate Road Ludlow Herefordshire SY8 1TL",
    "addr:postcode":"sy8 1tl",
    "addr:street":"Court Toll Gate Road",
    "iso:country":"GB",
    "sg:address":"Guy Thornycroft Court, Toll Gate Road",
    "sg:city":"Ludlow",
    "sg:classifiers":[
        {
            "category":"Health Services",
            "subcategory":"Nursing And Care Facility",
            "type":"Services"
        }
    ],
    "sg:phone":"+44 1584 872348",
    "sg:postcode":"SY8 1TL",
    "sg:province":"Herefordshire",
    "sg:tags":[
        "home"
    ],
    "wof:name":"Housing 21",
    "wof:placetype":"venue"
},
  "geometry": {"coordinates":[-2.700961,52.366356],"type":"Point"}
}