{
  "type": "Feature",
  "properties": {
    "iso:country":"GB",
    "sg:address":"74 Cranbrook Road",
    "sg:city":"Ilford",
    "sg:classifiers":[
        {
            "category":"Bars & Pubs",
            "type":"Food & Drink"
        }
    ],
    "sg:phone":"+44 20 8478 7645",
    "sg:postcode":"IG1 4NH",
    "sg:province":"Essex",
    "sg:tags":[
        "pubs",
        "inn"
    ],
    "wof:name":"Whitbread Group Plc",
    "wof:placetype":"venue"
},
  "geometry": {"coordinates":[0.069716,51.560658],"type":"Point"}
}