{
  "type": "Feature",
  "properties": {
    "addr:full":"Lancaster Ho, 70 Blackburn St Radcliffe Manchester Greater Manchester M26 2JW",
    "addr:housenumber":"70",
    "addr:postcode":"m26 2jw",
    "addr:street":"Blackburn St",
    "iso:country":"GB",
    "sg:address":"Lancaster Ho, 70 Blackburn St Radcliffe",
    "sg:city":"Manchester",
    "sg:classifiers":[
        {
            "category":"Education",
            "subcategory":"Special Training",
            "type":"Public Place"
        }
    ],
    "sg:postcode":"M26 2JW",
    "sg:province":"Greater Manchester",
    "sg:tags":[
        "product",
        "centre"
    ],
    "wof:name":"Effishency Training Ltd",
    "wof:placetype":"venue"
},
  "geometry": {"coordinates":[-2.3280301094,53.56224823],"type":"Point"}
}