{
  "type": "Feature",
  "properties": {
    "addr:full":"Unit 3/4 Richer House, Gallery Court London Greater London SE1 4BB",
    "addr:housenumber":"unit 3 / 4 richer",
    "addr:postcode":"se1 4bb",
    "addr:street":"Gallery Court",
    "iso:country":"GB",
    "sg:address":"Unit 3/4 Richer House, Gallery Court",
    "sg:city":"London",
    "sg:classifiers":[
        {
            "category":"Manufacturing",
            "subcategory":"Electronics",
            "type":"Manufacturing & Wholesale Goods"
        }
    ],
    "sg:phone":"+44 20 7940 2200",
    "sg:postcode":"SE1 4BB",
    "sg:province":"Greater London",
    "sg:tags":[
        "control",
        "component",
        "-",
        "electronic"
    ],
    "wof:name":"Audio Partnership Plc",
    "wof:placetype":"venue"
},
  "geometry": {"coordinates":[-0.0887999982,51.4999084473],"type":"Point"}
}