{
  "type": "Feature",
  "properties": {
    "iso:country":"GB",
    "sg:address":"Howshoots Farm, Knutsford Road, Grappenhall",
    "sg:city":"Warrington",
    "sg:classifiers":[
        {
            "category":"Retail",
            "subcategory":"Auto Repair",
            "type":"Services"
        }
    ],
    "sg:postcode":"WA4 4SJ",
    "sg:province":"Cheshire",
    "sg:tags":[
        "car",
        "upholsterer"
    ],
    "wof:name":"Cheshire Coachtrimmers",
    "wof:placetype":"venue"
},
  "geometry": {"coordinates":[-2.51224,53.36084],"type":"Point"}
}