{
  "type": "Feature",
  "properties": {
    "addr:full":"36a Freeman Street Grimsby Lincolnshire DN32 7AG",
    "addr:housenumber":"36a",
    "addr:postcode":"dn32 7ag",
    "addr:street":"Freeman Street",
    "iso:country":"GB",
    "sg:address":"36a Freeman Street",
    "sg:city":"Grimsby",
    "sg:classifiers":[
        {
            "category":"Shopping",
            "subcategory":"Antiques",
            "type":"Retail Goods"
        }
    ],
    "sg:phone":"+44 1472 355668",
    "sg:postcode":"DN32 7AG",
    "sg:province":"Lincolnshire",
    "wof:name":"Adrian J Black",
    "wof:placetype":"venue"
},
  "geometry": {"coordinates":[-0.07327,53.573833],"type":"Point"}
}