{
  "type": "Feature",
  "properties": {
    "iso:country":"GB",
    "sg:address":"304 Colne Road",
    "sg:city":"Burnley",
    "sg:classifiers":[
        {
            "category":"Food & Beverages",
            "subcategory":"Fruits & Vegetables",
            "type":"Retail Goods"
        }
    ],
    "sg:phone":"+44 1282 420930",
    "sg:postcode":"BB10 1DZ",
    "sg:province":"Lancashire",
    "sg:tags":[
        "greengrocer"
    ],
    "wof:name":"Katherine Isherwood",
    "wof:placetype":"venue"
},
  "geometry": {"coordinates":[-2.2343239784,53.8055419922],"type":"Point"}
}