{
  "type": "Feature",
  "properties": {
    "iso:country":"GB",
    "sg:address":"Coombe Lodge, Farnborough",
    "sg:city":"Banbury",
    "sg:classifiers":[
        {
            "category":"Professional",
            "subcategory":"Management & Consulting",
            "type":"Services"
        }
    ],
    "sg:postcode":"OX12 8NP",
    "sg:province":"Berkshire",
    "sg:tags":[
        "consultant",
        "business"
    ],
    "wof:name":"Dacre Lacy Associates Ltd.",
    "wof:placetype":"venue"
},
  "geometry": {"coordinates":[-1.377489,51.535416],"type":"Point"}
}