{
  "type": "Feature",
  "properties": {
    "addr:full":"Riverside Industrial Estate Littlehampton West Sussex BN17 5DR",
    "addr:postcode":"bn17 5dr",
    "iso:country":"GB",
    "sg:address":"Riverside Industrial Estate",
    "sg:city":"Littlehampton",
    "sg:classifiers":[
        {
            "category":"Manufacturing",
            "subcategory":"Metals",
            "type":"Manufacturing & Wholesale Goods"
        }
    ],
    "sg:postcode":"BN17 5DR",
    "sg:province":"West Sussex",
    "sg:tags":[
        "blacksmith",
        "forgemasters"
    ],
    "wof:name":"Robert Shane Fuller",
    "wof:placetype":"venue"
},
  "geometry": {"coordinates":[-0.5389590263,50.8210296631],"type":"Point"}
}