{
  "type": "Feature",
  "properties": {
    "iso:country":"GB",
    "sg:address":"10 Greenwood",
    "sg:city":"Newcastle Upon Tyne",
    "sg:classifiers":[
        {
            "category":"Home & Garden",
            "subcategory":"Household Appliances",
            "type":"Retail Goods"
        }
    ],
    "sg:phone":"+44 191 268 3515",
    "sg:postcode":"NE12 0FE",
    "sg:province":"Tyne and Wear",
    "sg:tags":[
        "electrical"
    ],
    "wof:name":"B Chambers",
    "wof:placetype":"venue"
},
  "geometry": {"coordinates":[-1.550011,55.033073],"type":"Point"}
}