{
  "type": "Feature",
  "properties": {
    "iso:country":"GB",
    "sg:address":"New Road, Cambuslang",
    "sg:city":"Glasgow",
    "sg:classifiers":[
        {
            "category":"Community Center",
            "type":"Public Place"
        },
        {
            "category":"Government",
            "subcategory":"Office",
            "type":"Public Place"
        }
    ],
    "sg:phone":"+44 141 641 4158",
    "sg:postcode":"G72 7PU",
    "sg:province":"South Lanarkshire",
    "sg:tags":[
        "recreation",
        "local",
        "leisure",
        "centre"
    ],
    "wof:name":"Halfway Recreation Centre",
    "wof:placetype":"venue"
},
  "geometry": {"coordinates":[-4.137732,55.812347],"type":"Point"}
}