{
  "type": "Feature",
  "properties": {
    "addr:full":"9 Furmston Ct Letchworth Hertfordshire SG6 1UJ",
    "addr:housenumber":"9",
    "addr:postcode":"sg6 1uj",
    "addr:street":"Furmston Ct Letchworth",
    "iso:country":"GB",
    "sg:address":"9 Furmston Ct",
    "sg:city":"Letchworth",
    "sg:classifiers":[
        {
            "category":"Professional",
            "subcategory":"Engineering",
            "type":"Services"
        }
    ],
    "sg:phone":"+44 1462 682467",
    "sg:postcode":"SG6 1UJ",
    "sg:province":"Hertfordshire",
    "sg:tags":[
        "precision",
        "engineer"
    ],
    "wof:name":"Imagik Ltd",
    "wof:placetype":"venue"
},
  "geometry": {"coordinates":[-0.220626995,51.9848670959],"type":"Point"}
}