{
  "type": "Feature",
  "properties": {
    "addr:full":"South Suffolk Business Centre, Alexandra Sudbury Essex CO10 2PX",
    "addr:postcode":"co10 2px",
    "addr:street":"South Suffolk;Alexandra Sudbury",
    "iso:country":"GB",
    "sg:address":"South Suffolk Business Centre, Alexandra",
    "sg:city":"Sudbury",
    "sg:classifiers":[
        {
            "category":"Autos & Motor Vehicles",
            "subcategory":"Automobile Sales",
            "type":"Retail Goods"
        }
    ],
    "sg:postcode":"CO10 2PX",
    "sg:province":"Essex",
    "sg:tags":[
        "car",
        "commercial"
    ],
    "wof:name":"Barn,Patrick,",
    "wof:placetype":"venue"
},
  "geometry": {"coordinates":[0.73439,52.038605],"type":"Point"}
}