{
  "type": "Feature",
  "properties": {
    "iso:country":"GB",
    "sg:address":"Unit 4, Hunstanton Commercial Park",
    "sg:city":"Hunstanton",
    "sg:classifiers":[
        {
            "category":"Home & Garden",
            "subcategory":"Carpets & Floor Coverings",
            "type":"Retail Goods"
        }
    ],
    "sg:phone":"+44 1485 534027",
    "sg:postcode":"PE36 5JQ",
    "sg:province":"Norfolk",
    "sg:tags":[
        "carpets",
        "rug",
        "matting"
    ],
    "wof:name":"Carpet Sellers",
    "wof:placetype":"venue"
},
  "geometry": {"coordinates":[0.4944050014,52.9371604919],"type":"Point"}
}