{
  "type": "Feature",
  "properties": {
    "addr:full":"99 Carmarthen Clo Farnborough Hampshire GU14 8TH",
    "addr:housenumber":"99",
    "addr:postcode":"gu14 8th",
    "iso:country":"GB",
    "sg:address":"99 Carmarthen Clo",
    "sg:city":"Farnborough",
    "sg:classifiers":[
        {
            "category":"Building & Trades",
            "subcategory":"Construction",
            "type":"Services"
        }
    ],
    "sg:postcode":"GU14 8TH",
    "sg:province":"Hampshire",
    "sg:tags":[
        "glazier"
    ],
    "wof:name":"Chilton,W H,",
    "wof:placetype":"venue"
},
  "geometry": {"coordinates":[-0.7661740184,51.3064308167],"type":"Point"}
}