{
  "type": "Feature",
  "properties": {
    "iso:country":"GB",
    "sg:address":"34 Park Parade, Hazlemere",
    "sg:city":"High Wycombe",
    "sg:classifiers":[
        {
            "category":"Shopping",
            "subcategory":"Florist",
            "type":"Retail Goods"
        }
    ],
    "sg:postcode":"HP15 7AA",
    "sg:province":"Buckinghamshire",
    "wof:name":"Pinks Florist",
    "wof:placetype":"venue"
},
  "geometry": {"coordinates":[-0.710464,51.654922],"type":"Point"}
}