{
  "type": "Feature",
  "properties": {
    "iso:country":"GB",
    "sg:address":"Tollgate Rd",
    "sg:city":"Hatfield",
    "sg:classifiers":[
        {
            "category":"Place Of Worship",
            "type":"Public Place"
        }
    ],
    "sg:phone":"+44 1727 822062",
    "sg:postcode":"AL9 7TN",
    "sg:province":"Hertfordshire",
    "wof:name":"St Mary C Of E Church",
    "wof:placetype":"venue"
},
  "geometry": {"coordinates":[-0.2297530025,51.7275047302],"type":"Point"}
}