{
  "type": "Feature",
  "properties": {
    "iso:country":"GB",
    "sg:address":"8 Elm Crescent",
    "sg:city":"Bridgend",
    "sg:classifiers":[
        {
            "category":"Food & Beverages",
            "subcategory":"Supermarket",
            "type":"Retail Goods"
        }
    ],
    "sg:phone":"+44 1656 653120",
    "sg:postcode":"CF31 4EA",
    "sg:province":"Bridgend",
    "wof:name":"Nisa Supermarkets",
    "wof:placetype":"venue"
},
  "geometry": {"coordinates":[-3.607354,51.508171],"type":"Point"}
}