{
  "type": "Feature",
  "properties": {
    "addr:full":"Lomeshaye Bridge Mill, St. Marys St Nelson Lancashire BB9 7BA",
    "addr:postcode":"bb9 7ba",
    "addr:street":"Bridge Mill;Marys St",
    "iso:country":"GB",
    "sg:address":"Lomeshaye Bridge Mill, St. Marys St",
    "sg:city":"Nelson",
    "sg:classifiers":[
        {
            "category":"Utilities",
            "subcategory":"Cable",
            "type":"Services"
        }
    ],
    "sg:phone":"+44 1282 695557",
    "sg:postcode":"BB9 7BA",
    "sg:province":"Lancashire",
    "sg:tags":[
        "rope",
        "hawser"
    ],
    "wof:name":"Michael Crabtree & Sons",
    "wof:placetype":"venue"
},
  "geometry": {"coordinates":[-2.21334,53.835968],"type":"Point"}
}