{
  "type": "Feature",
  "properties": {
    "addr:full":"Norman House, Kettering Terrace Portsmouth Hampshire PO2 7AE",
    "addr:postcode":"hampshire po2 7ae",
    "addr:street":"Kettering Terrace",
    "iso:country":"GB",
    "sg:address":"Norman House, Kettering Terrace",
    "sg:city":"Portsmouth",
    "sg:classifiers":[
        {
            "category":"Social Services",
            "subcategory":"Job Training",
            "type":"Services"
        }
    ],
    "sg:phone":"+44 23 9287 5277",
    "sg:postcode":"PO2 7AE",
    "sg:province":"Hampshire",
    "sg:tags":[
        "engineering",
        "marine"
    ],
    "wof:name":"Hart Fenton & Co. (Portsmouth) Ltd.",
    "wof:placetype":"venue"
},
  "geometry": {"coordinates":[-1.0879989862,50.8097763062],"type":"Point"}
}