{
  "type": "Feature",
  "properties": {
    "addr:full":"4a Emery Lane Boston Lincolnshire PE21 8QA",
    "addr:housenumber":"4a",
    "addr:postcode":"pe21 8qa",
    "addr:street":"Emery Lane",
    "iso:country":"GB",
    "sg:address":"4a Emery Lane",
    "sg:city":"Boston",
    "sg:classifiers":[
        {
            "category":"Shopping",
            "subcategory":"Mobile Phones",
            "type":"Retail Goods"
        }
    ],
    "sg:phone":"+44 1205 311135",
    "sg:postcode":"PE21 8QA",
    "sg:province":"Lincolnshire",
    "wof:name":"Air 7 Ltd",
    "wof:placetype":"venue"
},
  "geometry": {"coordinates":[-0.025274,52.976669],"type":"Point"}
}