{
  "type": "Feature",
  "properties": {
    "iso:country":"GB",
    "sg:address":"Beach Road",
    "sg:city":"Perranporth",
    "sg:classifiers":[
        {
            "category":"Cafe",
            "type":"Food & Drink"
        }
    ],
    "sg:phone":"+44 1872 573817",
    "sg:postcode":"TR6 0JL",
    "sg:province":"Cornwall",
    "sg:tags":[
        "tea",
        "snack",
        "bar",
        "room"
    ],
    "wof:name":"Dolphin Cafe",
    "wof:placetype":"venue"
},
  "geometry": {"coordinates":[-5.154774,50.345455],"type":"Point"}
}