{
  "type": "Feature",
  "properties": {
    "iso:country":"GB",
    "sg:address":"21 Market Place",
    "sg:city":"Pickering",
    "sg:classifiers":[
        {
            "category":"Food & Beverages",
            "subcategory":"Liquor & Beverages",
            "type":"Retail Goods"
        }
    ],
    "sg:phone":"+44 1751 472221",
    "sg:postcode":"YO18 7AE",
    "sg:province":"North Yorkshire",
    "sg:tags":[
        "beer",
        "spirit",
        "wines"
    ],
    "wof:name":"Victoria Wine Company",
    "wof:placetype":"venue"
},
  "geometry": {"coordinates":[-0.7779020071,54.2458267212],"type":"Point"}
}