{
  "type": "Feature",
  "properties": {
    "addr:full":"Prisk Farm Clynderwen Carmarthenshire SA66 7XS",
    "addr:housenumber":"clynderwen",
    "addr:postcode":"sa66 7xs",
    "addr:street":"Carmarthenshire",
    "iso:country":"GB",
    "sg:address":"Prisk Farm",
    "sg:city":"Clynderwen",
    "sg:classifiers":[
        {
            "category":"Farming",
            "subcategory":"Dairy Farm",
            "type":"Manufacturing & Wholesale Goods"
        }
    ],
    "sg:phone":"+44 1437 532295",
    "sg:postcode":"SA66 7XS",
    "sg:province":"Carmarthenshire",
    "wof:name":"W D T Lewis",
    "wof:placetype":"venue"
},
  "geometry": {"coordinates":[-4.750082,51.885559],"type":"Point"}
}