{
  "type": "Feature",
  "properties": {
    "iso:country":"GB",
    "sg:address":"47 Links Av",
    "sg:city":"Felixstowe",
    "sg:classifiers":[
        {
            "category":"Building & Trades",
            "subcategory":"Construction",
            "type":"Services"
        }
    ],
    "sg:phone":"+44 1394 286554",
    "sg:postcode":"IP11 9HD",
    "sg:province":"Suffolk",
    "sg:tags":[
        "decorator",
        "painter"
    ],
    "wof:name":"G Siegel",
    "wof:placetype":"venue"
},
  "geometry": {"coordinates":[1.3563070297,51.9726905823],"type":"Point"}
}