{
  "type": "Feature",
  "properties": {
    "addr:full":"18 Leas Road, Otterton Budleigh Salterton Devon EX9 7JH",
    "addr:housenumber":"18",
    "addr:postcode":"ex9 7jh",
    "addr:street":"Leas Road",
    "iso:country":"GB",
    "sg:address":"18 Leas Road, Otterton",
    "sg:city":"Budleigh Salterton",
    "sg:classifiers":[
        {
            "category":"Building & Trades",
            "subcategory":"Construction",
            "type":"Services"
        }
    ],
    "sg:phone":"+44 1395 568459",
    "sg:postcode":"EX9 7JH",
    "sg:province":"Devon",
    "sg:tags":[
        "decorator",
        "painter"
    ],
    "wof:name":"Graham Dabrowiecki",
    "wof:placetype":"venue"
},
  "geometry": {"coordinates":[-3.2969288826,50.6591758728],"type":"Point"}
}