{
  "type": "Feature",
  "properties": {
    "addr:full":"Providence Way Baldock Bedfordshire SG7 6TT",
    "addr:postcode":"sg7 6tt",
    "addr:street":"Providence Way",
    "iso:country":"GB",
    "sg:address":"Providence Way",
    "sg:city":"Baldock",
    "sg:classifiers":[
        {
            "category":"Education",
            "subcategory":"School",
            "type":"Public Place"
        }
    ],
    "sg:phone":"+44 1462 892478",
    "sg:postcode":"SG7 6TT",
    "sg:province":"Bedfordshire",
    "sg:tags":[
        "local",
        "authority"
    ],
    "wof:name":"St Johns R C Primary School",
    "wof:placetype":"venue"
},
  "geometry": {"coordinates":[-0.1821310073,51.9831542969],"type":"Point"}
}