{
  "type": "Feature",
  "properties": {
    "addr:full":"3c High Street Alcester Warwickshire B49 5AE",
    "addr:housenumber":"3c",
    "addr:postcode":"b49 5ae",
    "addr:street":"High Street",
    "iso:country":"GB",
    "sg:address":"3c High Street",
    "sg:city":"Alcester",
    "sg:classifiers":[
        {
            "category":"Professional",
            "subcategory":"Computer Services",
            "type":"Services"
        }
    ],
    "sg:phone":"+44 1789 400193",
    "sg:postcode":"B49 5AE",
    "sg:province":"Warwickshire",
    "sg:tags":[
        "system",
        "software"
    ],
    "wof:name":"Perrywell Computer Services Ltd.",
    "wof:placetype":"venue"
},
  "geometry": {"coordinates":[-1.869545,52.214909],"type":"Point"}
}