{
  "type": "Feature",
  "properties": {
    "iso:country":"GB",
    "sg:address":"P & A House, Alma Road",
    "sg:city":"Chesham",
    "sg:classifiers":[
        {
            "category":"Professional",
            "subcategory":"Management & Consulting",
            "type":"Services"
        }
    ],
    "sg:phone":"+44 1494 771734",
    "sg:postcode":"HP5 3HB",
    "sg:province":"Buckinghamshire",
    "sg:tags":[
        "marketing",
        "consultant"
    ],
    "sg:website":"http://www.cmsinfo.com",
    "wof:name":"Chiltern Magazine Services Ltd.",
    "wof:placetype":"venue"
},
  "geometry": {"coordinates":[-0.6087499857,51.7137184143],"type":"Point"}
}