{
  "type": "Feature",
  "properties": {
    "addr:full":"46a Pennyacre Rd Teignmouth Devon TQ14 8LB",
    "addr:housenumber":"46a",
    "addr:postcode":"tq14 8lb",
    "addr:street":"Pennyacre Rd",
    "iso:country":"GB",
    "sg:address":"46a Pennyacre Rd",
    "sg:city":"Teignmouth",
    "sg:classifiers":[
        {
            "category":"Building & Trades",
            "subcategory":"Construction",
            "type":"Services"
        }
    ],
    "sg:phone":"+44 1626 770377",
    "sg:postcode":"TQ14 8LB",
    "sg:province":"Devon",
    "sg:tags":[
        "conservation",
        "craft",
        "thatching"
    ],
    "wof:name":"J Singleton",
    "wof:placetype":"venue"
},
  "geometry": {"coordinates":[-3.494677,50.553242],"type":"Point"}
}