{
  "type": "Feature",
  "properties": {
    "addr:full":"236/238 Ruislip Road Greenford Greater London UB6 9RS",
    "addr:housenumber":"236 / 238",
    "addr:postcode":"ub6 9rs",
    "addr:street":"Ruislip Road",
    "iso:country":"GB",
    "sg:address":"236/238 Ruislip Road",
    "sg:city":"Greenford",
    "sg:classifiers":[
        {
            "category":"Building & Trades",
            "subcategory":"Construction",
            "type":"Services"
        }
    ],
    "sg:phone":"+44 20 8566 6665",
    "sg:postcode":"UB6 9RS",
    "sg:province":"Greater London",
    "sg:tags":[
        "equipment"
    ],
    "wof:name":"Fordpower Tool Hire & Sales Ltd.",
    "wof:placetype":"venue"
},
  "geometry": {"coordinates":[-0.3679580092,51.5325202942],"type":"Point"}
}