{
  "type": "Feature",
  "properties": {
    "addr:full":"Bridge House Farm, Harrogate Road, North Rigton Leeds North Yorkshire LS17 0DA",
    "addr:postcode":"ls17 0da",
    "addr:street":"Harrogate Road North",
    "iso:country":"GB",
    "sg:address":"Bridge House Farm, Harrogate Road, North Rigton",
    "sg:city":"Leeds",
    "sg:classifiers":[
        {
            "category":"Farming",
            "subcategory":"Livestock Farm",
            "type":"Manufacturing & Wholesale Goods"
        }
    ],
    "sg:phone":"+44 113 288 6681",
    "sg:postcode":"LS17 0DA",
    "sg:province":"North Yorkshire",
    "sg:tags":[
        "others"
    ],
    "wof:name":"R J H Cobbald & Sons",
    "wof:placetype":"venue"
},
  "geometry": {"coordinates":[-1.565844059,53.935760498],"type":"Point"}
}