{
  "type": "Feature",
  "properties": {
    "iso:country":"GB",
    "sg:address":"1 Sunningdale Drive",
    "sg:city":"Swansea",
    "sg:classifiers":[
        {
            "category":"Professional",
            "subcategory":"Engineering",
            "type":"Services"
        }
    ],
    "sg:phone":"+44 1792 894599",
    "sg:postcode":"SA4 4LZ",
    "sg:province":"Carmarthenshire",
    "sg:tags":[
        "contractor",
        "electrical",
        "engineer"
    ],
    "wof:name":"Electrical Mechanical Services (Penllergaer) Ltd.",
    "wof:placetype":"venue"
},
  "geometry": {"coordinates":[-4.0416097641,51.6792602539],"type":"Point"}
}