{
  "type": "Feature",
  "properties": {
    "addr:full":"2 Fleming Way Isleworth Greater London TW7 6EU",
    "addr:housenumber":"2",
    "addr:postcode":"tw7 6eu",
    "addr:street":"Fleming Way",
    "iso:country":"GB",
    "sg:address":"2 Fleming Way",
    "sg:city":"Isleworth",
    "sg:classifiers":[
        {
            "category":"Professional",
            "subcategory":"Business Services",
            "type":"Services"
        }
    ],
    "sg:phone":"+44 20 8232 8180",
    "sg:postcode":"TW7 6EU",
    "sg:province":"Greater London",
    "sg:tags":[
        "holding"
    ],
    "wof:name":"Chanticleer (Holdings) Ltd",
    "wof:placetype":"venue"
},
  "geometry": {"coordinates":[-0.3361989856,51.4669342041],"type":"Point"}
}