{
  "type": "Feature",
  "properties": {
    "iso:country":"GB",
    "sg:address":"63 Sunground, Avening",
    "sg:city":"Tetbury",
    "sg:classifiers":[
        {
            "category":"Home & Garden",
            "subcategory":"Building Materials",
            "type":"Retail Goods"
        },
        {
            "category":"Building & Trades",
            "subcategory":"Construction",
            "type":"Services"
        }
    ],
    "sg:phone":"+44 1453 833239",
    "sg:postcode":"GL8 8NW",
    "sg:province":"Gloucestershire",
    "sg:tags":[
        "fencing",
        "contractor"
    ],
    "wof:name":"Peter Savage",
    "wof:placetype":"venue"
},
  "geometry": {"coordinates":[-2.175975,51.642689],"type":"Point"}
}