{
  "type": "Feature",
  "properties": {
    "addr:full":"45 Jaunty Way Sheffield Derbyshire S12 3DZ",
    "addr:housenumber":"45",
    "addr:postcode":"s12 3dz",
    "addr:street":"Jaunty Way",
    "iso:country":"GB",
    "sg:address":"45 Jaunty Way",
    "sg:city":"Sheffield",
    "sg:classifiers":[
        {
            "category":"Food & Beverages",
            "subcategory":"Meat & Fish",
            "type":"Retail Goods"
        }
    ],
    "sg:phone":"+44 114 239 9305",
    "sg:postcode":"S12 3DZ",
    "sg:province":"Derbyshire",
    "sg:tags":[
        "chip"
    ],
    "wof:name":"Basegreen Fisheries",
    "wof:placetype":"venue"
},
  "geometry": {"coordinates":[-1.418088,53.347931],"type":"Point"}
}