{
  "type": "Feature",
  "properties": {
    "iso:country":"GB",
    "sg:address":"Bridgnorth Medical Practice, Northgate Ho, 7 High St",
    "sg:city":"Bridgnorth",
    "sg:classifiers":[
        {
            "category":"Health Services",
            "subcategory":"Doctor",
            "type":"Services"
        }
    ],
    "sg:phone":"+44 1746 767121",
    "sg:postcode":"WV16 4BU",
    "sg:province":"Shropshire",
    "sg:tags":[
        "practitioners"
    ],
    "wof:name":"McDowell, D",
    "wof:placetype":"venue"
},
  "geometry": {"coordinates":[-2.420479,52.536819],"type":"Point"}
}