{
  "type": "Feature",
  "properties": {
    "iso:country":"GB",
    "sg:address":"1 White Horse La",
    "sg:city":"Maldon",
    "sg:classifiers":[
        {
            "category":"Retail",
            "subcategory":"Auto Repair",
            "type":"Services"
        }
    ],
    "sg:phone":"+44 1621 853366",
    "sg:postcode":"CM9 6AH",
    "sg:province":"Essex",
    "sg:tags":[
        "modification",
        "garage"
    ],
    "wof:name":"Orth,R L,& Sons Ltd",
    "wof:placetype":"venue"
},
  "geometry": {"coordinates":[0.675249,51.731377],"type":"Point"}
}