{
  "type": "Feature",
  "properties": {
    "iso:country":"GB",
    "sg:address":"Beech Park, Brandon",
    "sg:city":"Durham",
    "sg:classifiers":[
        {
            "category":"Fast Food",
            "type":"Food & Drink"
        }
    ],
    "sg:postcode":"DH7 8TL",
    "sg:province":"Durham",
    "sg:tags":[
        "away",
        "take"
    ],
    "wof:name":"Brandon's",
    "wof:placetype":"venue"
},
  "geometry": {"coordinates":[-1.621559,54.750031],"type":"Point"}
}