{
  "type": "Feature",
  "properties": {
    "iso:country":"GB",
    "sg:address":"42-48 Great Western Road",
    "sg:city":"Aberdeen",
    "sg:classifiers":[
        {
            "category":"Home & Garden",
            "subcategory":"Kitchen Supply",
            "type":"Retail Goods"
        }
    ],
    "sg:phone":"+44 1224 596981",
    "sg:postcode":"AB10 6PY",
    "sg:province":"Aberdeen City",
    "sg:tags":[
        "equipment",
        "catering"
    ],
    "wof:name":"The Ashvale Fish Restaurant Ltd.",
    "wof:placetype":"venue"
},
  "geometry": {"coordinates":[-2.115573,57.139923],"type":"Point"}
}