{
  "type": "Feature",
  "properties": {
    "iso:country":"GB",
    "sg:address":"178 Whiteleas Way",
    "sg:city":"South Shields",
    "sg:classifiers":[
        {
            "category":"Food & Beverages",
            "subcategory":"Candy",
            "type":"Retail Goods"
        }
    ],
    "sg:phone":"+44 191 536 7690",
    "sg:postcode":"NE34 8HF",
    "sg:province":"Tyne and Wear",
    "sg:tags":[
        "confectioner"
    ],
    "wof:name":"Swainstons Sweet Shop",
    "wof:placetype":"venue"
},
  "geometry": {"coordinates":[-1.4311950207,54.9587287903],"type":"Point"}
}