{
  "type": "Feature",
  "properties": {
    "addr:full":"101 Broad Town Swindon Wiltshire SN4 7RU",
    "addr:housenumber":"101",
    "addr:postcode":"sn4 7ru",
    "addr:street":"Broad",
    "iso:country":"GB",
    "sg:address":"101 Broad Town",
    "sg:city":"Swindon",
    "sg:classifiers":[
        {
            "category":"Professional",
            "subcategory":"Computer Services",
            "type":"Services"
        }
    ],
    "sg:phone":"+44 1793 731364",
    "sg:postcode":"SN4 7RU",
    "sg:province":"Wiltshire",
    "sg:tags":[
        "development",
        "consultant",
        "software"
    ],
    "wof:name":"Scopus Ltd",
    "wof:placetype":"venue"
},
  "geometry": {"coordinates":[-1.87706,51.496078],"type":"Point"}
}