{
  "type": "Feature",
  "properties": {
    "addr:full":"Firth Mill, Firth Street Skipton Lancashire BD23 2PT",
    "addr:postcode":"bd23 2pt",
    "addr:street":"Firth Mill Firth Street",
    "iso:country":"GB",
    "sg:address":"Firth Mill, Firth Street",
    "sg:city":"Skipton",
    "sg:classifiers":[
        {
            "category":"Communications",
            "type":"Services"
        },
        {
            "category":"Communications",
            "subcategory":"Television Station",
            "type":"Services"
        }
    ],
    "sg:phone":"+44 1756 799991",
    "sg:postcode":"BD23 2PT",
    "sg:province":"Lancashire",
    "sg:tags":[
        "operator",
        "broadcasting",
        "radio"
    ],
    "wof:name":"FRESH RADIO LTD",
    "wof:placetype":"venue"
},
  "geometry": {"coordinates":[-2.018514,53.960201],"type":"Point"}
}