{
  "type": "Feature",
  "properties": {
    "addr:full":"The Court Pontefract West Yorkshire WF7 7LX",
    "addr:postcode":"wf7 7lx",
    "addr:street":"West",
    "iso:country":"GB",
    "sg:address":"The Court",
    "sg:city":"Pontefract",
    "sg:classifiers":[
        {
            "category":"Real Estate",
            "subcategory":"Developer",
            "type":"Services"
        }
    ],
    "sg:postcode":"WF7 7LX",
    "sg:province":"West Yorkshire",
    "sg:tags":[
        "property"
    ],
    "wof:name":"Sarkfern Ltd.",
    "wof:placetype":"venue"
},
  "geometry": {"coordinates":[-1.322875,53.652969],"type":"Point"}
}