{
  "type": "Feature",
  "properties": {
    "addr:full":"Penruddock Close Salisbury Wiltshire SP2 9HH",
    "addr:postcode":"sp2 9hh",
    "addr:street":"Penruddock Close",
    "iso:country":"GB",
    "sg:address":"Penruddock Close",
    "sg:city":"Salisbury",
    "sg:classifiers":[
        {
            "category":"Education",
            "subcategory":"School",
            "type":"Public Place"
        },
        {
            "category":"Government",
            "subcategory":"Office",
            "type":"Public Place"
        }
    ],
    "sg:phone":"+44 1722 324050",
    "sg:postcode":"SP2 9HH",
    "sg:province":"Wiltshire",
    "sg:tags":[
        "local",
        "authority"
    ],
    "wof:name":"Pembroke Park County First School",
    "wof:placetype":"venue"
},
  "geometry": {"coordinates":[-1.8255970478,51.0796699524],"type":"Point"}
}