{
  "type": "Feature",
  "properties": {
    "addr:full":"Unit 10c, Dawkins Road Poole Dorset BH15 4JD",
    "addr:housenumber":"unit 10c",
    "addr:postcode":"bh15 4jd",
    "addr:street":"Dawkins Road",
    "iso:country":"GB",
    "sg:address":"Unit 10c, Dawkins Road",
    "sg:city":"Poole",
    "sg:classifiers":[
        {
            "category":"Retail",
            "subcategory":"Auto Repair",
            "type":"Services"
        }
    ],
    "sg:phone":"+44 1202 672486",
    "sg:postcode":"BH15 4JD",
    "sg:province":"Dorset",
    "sg:tags":[
        "modification",
        "garage",
        "related"
    ],
    "wof:name":"Watson Motors",
    "wof:placetype":"venue"
},
  "geometry": {"coordinates":[-2.0148539543,50.7235984802],"type":"Point"}
}