{
  "type": "Feature",
  "properties": {
    "addr:full":"Holme Street Hebden Bridge West Yorkshire HX7 8EE",
    "addr:postcode":"hx7 8ee",
    "addr:street":"Holme Street",
    "iso:country":"GB",
    "sg:address":"Holme Street",
    "sg:city":"Hebden Bridge",
    "sg:classifiers":[
        {
            "category":"Education",
            "subcategory":"School",
            "type":"Public Place"
        },
        {
            "category":"Government",
            "subcategory":"Office",
            "type":"Public Place"
        }
    ],
    "sg:phone":"+44 1422 842154",
    "sg:postcode":"HX7 8EE",
    "sg:province":"West Yorkshire",
    "sg:tags":[
        "local",
        "authority"
    ],
    "wof:name":"Riverside Junior School",
    "wof:placetype":"venue"
},
  "geometry": {"coordinates":[-2.0141839981,53.7407493591],"type":"Point"}
}