{
  "type": "Feature",
  "properties": {
    "addr:full":"Federation Ho, Station Rd Stoke-on-trent Staffordshire ST4 2RT",
    "addr:postcode":"st4 2rt",
    "addr:street":"Station Rd",
    "iso:country":"GB",
    "sg:address":"Federation Ho, Station Rd",
    "sg:city":"Stoke-on-trent",
    "sg:classifiers":[
        {
            "category":"Professional",
            "subcategory":"Business Services",
            "type":"Services"
        }
    ],
    "sg:postcode":"ST4 2RT",
    "sg:province":"Staffordshire",
    "sg:tags":[
        "trade"
    ],
    "wof:name":"British Bathroom Council",
    "wof:placetype":"venue"
},
  "geometry": {"coordinates":[-2.1811699867,53.0088500977],"type":"Point"}
}