{
  "type": "Feature",
  "properties": {
    "iso:country":"GB",
    "sg:address":"36 Longfield Avenue",
    "sg:city":"Wallington",
    "sg:classifiers":[
        {
            "category":"Professional",
            "subcategory":"Management & Consulting",
            "type":"Services"
        }
    ],
    "sg:phone":"+44 20 8644 8276",
    "sg:postcode":"SM6 7BA",
    "sg:province":"Surrey",
    "sg:tags":[
        "fire",
        "consultant",
        "protection"
    ],
    "wof:name":"Independent Fire Protection",
    "wof:placetype":"venue"
},
  "geometry": {"coordinates":[-0.158045,51.379799],"type":"Point"}
}