{
  "type": "Feature",
  "properties": {
    "addr:full":"2 The Rise Amersham Buckinghamshire HP7 9AG",
    "addr:housenumber":"2",
    "addr:postcode":"hp7 9ag",
    "addr:street":"The Rise",
    "iso:country":"GB",
    "sg:address":"2 The Rise",
    "sg:city":"Amersham",
    "sg:classifiers":[
        {
            "category":"Parking",
            "type":"Transportation"
        },
        {
            "category":"Building & Trades",
            "subcategory":"Cleaning & Sanitation",
            "type":"Services"
        }
    ],
    "sg:phone":"+44 1494 792800",
    "sg:postcode":"HP7 9AG",
    "sg:province":"Buckinghamshire",
    "sg:tags":[
        "car",
        "hygiene",
        "valet"
    ],
    "wof:name":"Fleet Clean Services",
    "wof:placetype":"venue"
},
  "geometry": {"coordinates":[-0.6071500182,51.6719589233],"type":"Point"}
}