{
  "type": "Feature",
  "properties": {
    "addr:full":"50 Bonscale Crescent, Middleton Manchester Greater Manchester M24 5LY",
    "addr:housenumber":"50",
    "addr:postcode":"m24 5ly",
    "addr:street":"Bonscale Crescent",
    "iso:country":"GB",
    "sg:address":"50 Bonscale Crescent, Middleton",
    "sg:city":"Manchester",
    "sg:classifiers":[
        {
            "category":"Government",
            "subcategory":"Post Office",
            "type":"Public Place"
        }
    ],
    "sg:phone":"+44 161 643 6050",
    "sg:postcode":"M24 5LY",
    "sg:province":"Greater Manchester",
    "sg:tags":[
        "messenger",
        "courier"
    ],
    "wof:name":"Woods Corporation Ltd.",
    "wof:placetype":"venue"
},
  "geometry": {"coordinates":[-2.205845,53.56361],"type":"Point"}
}