{
  "type": "Feature",
  "properties": {
    "addr:full":"604 Oldham Road, Failsworth Manchester Lancashire M35 9DQ",
    "addr:housenumber":"604",
    "addr:postcode":"m35 9dq",
    "addr:street":"Oldham Road",
    "iso:country":"GB",
    "sg:address":"604 Oldham Road, Failsworth",
    "sg:city":"Manchester",
    "sg:classifiers":[
        {
            "category":"Bars & Pubs",
            "type":"Food & Drink"
        }
    ],
    "sg:phone":"+44 161 681 1314",
    "sg:postcode":"M35 9DQ",
    "sg:province":"Lancashire",
    "sg:tags":[
        "pubs",
        "inn"
    ],
    "wof:name":"The Sun Inn",
    "wof:placetype":"venue"
},
  "geometry": {"coordinates":[-2.151332,53.514336],"type":"Point"}
}