{
  "type": "Feature",
  "properties": {
    "iso:country":"GB",
    "sg:address":"59 William Street",
    "sg:city":"Swindon",
    "sg:classifiers":[
        {
            "category":"Building & Trades",
            "subcategory":"Plumbing",
            "type":"Services"
        }
    ],
    "sg:postcode":"SN1 5LB",
    "sg:province":"Wiltshire",
    "sg:tags":[
        "heating"
    ],
    "wof:name":"A M B",
    "wof:placetype":"venue"
},
  "geometry": {"coordinates":[-1.794778,51.555592],"type":"Point"}
}