{
  "type": "Feature",
  "properties": {
    "iso:country":"GB",
    "sg:address":"162 Queensway, Bletchley",
    "sg:city":"Milton Keynes",
    "sg:classifiers":[
        {
            "category":"Food & Beverages",
            "subcategory":"Liquor & Beverages",
            "type":"Retail Goods"
        }
    ],
    "sg:phone":"+44 1908 277118",
    "sg:postcode":"MK2 2SW",
    "sg:province":"Buckinghamshire",
    "sg:tags":[
        "beer",
        "spirit",
        "wines"
    ],
    "wof:name":"Victoria Wine Company",
    "wof:placetype":"venue"
},
  "geometry": {"coordinates":[-0.7282029986,51.9949226379],"type":"Point"}
}