{
  "type": "Feature",
  "properties": {
    "addr:full":"7 South Acomb Farm Stocksfield Northumberland NE43 7AQ",
    "addr:housenumber":"7;stocksfield",
    "addr:postcode":"ne43 7aq",
    "addr:street":"South Acomb;Northumberland",
    "iso:country":"GB",
    "sg:address":"7 South Acomb Farm",
    "sg:city":"Stocksfield",
    "sg:classifiers":[
        {
            "category":"Health Services",
            "subcategory":"Dentist",
            "type":"Services"
        }
    ],
    "sg:phone":"+44 1661 844088",
    "sg:postcode":"NE43 7AQ",
    "sg:province":"Northumberland",
    "sg:tags":[
        "technician",
        "dental"
    ],
    "wof:name":"Winn Dental Ceramics",
    "wof:placetype":"venue"
},
  "geometry": {"coordinates":[-1.9158940315,54.946685791],"type":"Point"}
}