{
  "type": "Feature",
  "properties": {
    "addr:full":"4 Queensgate Arc Inverness Highland IV1 1PQ",
    "addr:housenumber":"4",
    "addr:postcode":"iv1 1pq",
    "addr:street":"Queensgate Arc Inverness",
    "iso:country":"GB",
    "sg:address":"4 Queensgate Arc",
    "sg:city":"Inverness",
    "sg:classifiers":[
        {
            "category":"Food & Beverages",
            "subcategory":"Liquor & Beverages",
            "type":"Retail Goods"
        }
    ],
    "sg:phone":"+44 1463 715252",
    "sg:postcode":"IV1 1PQ",
    "sg:province":"Highland",
    "sg:tags":[
        "beer",
        "spirit",
        "wines"
    ],
    "wof:name":"Victoria Wine",
    "wof:placetype":"venue"
},
  "geometry": {"coordinates":[-4.225361,57.479546],"type":"Point"}
}