{
  "type": "Feature",
  "properties": {
    "iso:country":"GB",
    "sg:address":"10 Lindow Parade",
    "sg:city":"Wilmslow",
    "sg:classifiers":[
        {
            "category":"Shopping",
            "subcategory":"Clothing, Apparel, & Fashions",
            "type":"Retail Goods"
        }
    ],
    "sg:phone":"+44 1625 525402",
    "sg:postcode":"SK9 5JL",
    "sg:province":"Cheshire",
    "sg:tags":[
        "shop"
    ],
    "wof:name":"New Extra Elegance",
    "wof:placetype":"venue"
},
  "geometry": {"coordinates":[-2.255037,53.325657],"type":"Point"}
}