{
  "type": "Feature",
  "properties": {
    "addr:full":"Unit 6 Oddington Grange Farm Industrial, Ustries Weston-on Bicester Oxfordshire OX25 3QW",
    "addr:housenumber":"unit 6 oddington",
    "addr:postcode":"ox25 3qw",
    "addr:street":"Grange Farm Industrial Ustries Weston-On",
    "iso:country":"GB",
    "sg:address":"Unit 6 Oddington Grange Farm Industrial, Ustries Weston-on",
    "sg:city":"Bicester",
    "sg:classifiers":[
        {
            "category":"Professional",
            "subcategory":"Engineering",
            "type":"Services"
        }
    ],
    "sg:phone":"+44 1865 331619",
    "sg:postcode":"OX25 3QW",
    "sg:province":"Oxfordshire",
    "sg:tags":[
        "precision",
        "engineer"
    ],
    "wof:name":"S J S Precision Engineering",
    "wof:placetype":"venue"
},
  "geometry": {"coordinates":[-1.211109,51.845928],"type":"Point"}
}