{
  "type": "Feature",
  "properties": {
    "iso:country":"GB",
    "sg:address":"Kent Cottage, Mill Lane, Stratford-sub-castlelane",
    "sg:city":"Salisbury",
    "sg:classifiers":[
        {
            "category":"Building & Trades",
            "subcategory":"Construction",
            "type":"Services"
        }
    ],
    "sg:phone":"+44 1722 321575",
    "sg:postcode":"SP1 3LJ",
    "sg:province":"Wiltshire",
    "sg:tags":[
        "builder"
    ],
    "wof:name":"Philip A Coggan",
    "wof:placetype":"venue"
},
  "geometry": {"coordinates":[-1.81405,51.08934],"type":"Point"}
}