{
  "type": "Feature",
  "properties": {
    "addr:full":"Church Farm, Moulsoe Newport Pagnell Buckinghamshire MK16 0HW",
    "addr:postcode":"mk16 0hw",
    "iso:country":"GB",
    "sg:address":"Church Farm, Moulsoe",
    "sg:city":"Newport Pagnell",
    "sg:classifiers":[
        {
            "category":"Farming",
            "subcategory":"Livestock Farm",
            "type":"Manufacturing & Wholesale Goods"
        }
    ],
    "sg:postcode":"MK16 0HW",
    "sg:province":"Buckinghamshire",
    "sg:tags":[
        "others"
    ],
    "wof:name":"Kingham & Son",
    "wof:placetype":"venue"
},
  "geometry": {"coordinates":[-0.6731889844,52.0688285828],"type":"Point"}
}