{
  "type": "Feature",
  "properties": {
    "iso:country":"GB",
    "sg:address":"Unit 73 Industrial Estate, Mccalls Avenue",
    "sg:city":"Ayr",
    "sg:classifiers":[
        {
            "category":"Retail",
            "subcategory":"Auto Repair",
            "type":"Services"
        }
    ],
    "sg:phone":"+44 1292 269522",
    "sg:postcode":"KA8 9AG",
    "sg:province":"South Ayrshire",
    "sg:tags":[
        "body",
        "car"
    ],
    "wof:name":"Ingram Motoring Group Ltd.",
    "wof:placetype":"venue"
},
  "geometry": {"coordinates":[-4.6191802025,55.4719581604],"type":"Point"}
}