{
  "type": "Feature",
  "properties": {
    "addr:full":"24 Ashby High St Scunthorpe Lincolnshire DN16 2NL",
    "addr:housenumber":"24",
    "addr:postcode":"dn16 2nl",
    "addr:street":"Ashby High St",
    "iso:country":"GB",
    "sg:address":"24 Ashby High St",
    "sg:city":"Scunthorpe",
    "sg:classifiers":[
        {
            "category":"Building & Trades",
            "subcategory":"Plumbing",
            "type":"Services"
        }
    ],
    "sg:phone":"+44 1724 863883",
    "sg:postcode":"DN16 2NL",
    "sg:province":"Lincolnshire",
    "sg:tags":[
        "heating"
    ],
    "wof:name":"Howsam & Mee",
    "wof:placetype":"venue"
},
  "geometry": {"coordinates":[-0.633725,53.566475],"type":"Point"}
}