{
  "type": "Feature",
  "properties": {
    "iso:country":"GB",
    "sg:address":"Unit E1 Fareham Heights, Standard Way",
    "sg:city":"Fareham",
    "sg:classifiers":[
        {
            "category":"Professional",
            "subcategory":"Engineering",
            "type":"Services"
        }
    ],
    "sg:phone":"+44 1329 233223",
    "sg:postcode":"PO16 8XT",
    "sg:province":"Hampshire",
    "sg:tags":[
        "contractor",
        "electrical",
        "engineer"
    ],
    "wof:name":"Hills Electrical & Mechanical Plc",
    "wof:placetype":"venue"
},
  "geometry": {"coordinates":[-1.1740989685,50.8527336121],"type":"Point"}
}