{
  "type": "Feature",
  "properties": {
    "addr:full":"Brittannica Wks, Clavering Saffron Walden Essex CB11 4QZ",
    "addr:postcode":"cb11 4qz",
    "iso:country":"GB",
    "sg:address":"Brittannica Wks, Clavering",
    "sg:city":"Saffron Walden",
    "sg:classifiers":[
        {
            "category":"Military Area",
            "subcategory":"Air Force Base",
            "type":"Public Place"
        }
    ],
    "sg:phone":"+44 1799 550811",
    "sg:postcode":"CB11 4QZ",
    "sg:province":"Essex",
    "sg:tags":[
        "water",
        "treatment"
    ],
    "wof:name":"Fernox Manufacturing Co Ltd",
    "wof:placetype":"venue"
},
  "geometry": {"coordinates":[0.1444569975,51.965839386],"type":"Point"}
}