{
  "type": "Feature",
  "properties": {
    "addr:full":"54 Cambridge Grove London Greater London W6 0LA",
    "addr:housenumber":"54",
    "addr:postcode":"w6 0la",
    "addr:street":"Cambridge Grove",
    "iso:country":"GB",
    "sg:address":"54 Cambridge Grove",
    "sg:city":"London",
    "sg:classifiers":[
        {
            "category":"Bars & Pubs",
            "type":"Food & Drink"
        }
    ],
    "sg:phone":"+44 20 8748 1397",
    "sg:postcode":"W6 0LA",
    "sg:province":"Greater London",
    "sg:tags":[
        "pubs",
        "house",
        "inn",
        "public",
        "activity"
    ],
    "wof:name":"The Stonemasons Arms",
    "wof:placetype":"venue"
},
  "geometry": {"coordinates":[-0.230159,51.494259],"type":"Point"}
}