{
  "type": "Feature",
  "properties": {
    "iso:country":"GB",
    "sg:address":"1 Summer Place, Llansamlet",
    "sg:city":"Swansea",
    "sg:classifiers":[
        {
            "category":"Autos & Motor Vehicles",
            "subcategory":"Auto Supplies",
            "type":"Retail Goods"
        }
    ],
    "sg:phone":"+44 1792 794853",
    "sg:postcode":"SA7 9SB",
    "sg:province":"Neath Port Talbot",
    "sg:tags":[
        "machine",
        "laundry",
        "washing"
    ],
    "wof:name":"C Morgan & Son",
    "wof:placetype":"venue"
},
  "geometry": {"coordinates":[-3.887432,51.656422],"type":"Point"}
}