{
  "type": "Feature",
  "properties": {
    "addr:full":"2 Picardy Road Belvedere Kent DA17 5QH",
    "addr:housenumber":"2",
    "addr:postcode":"da17 5qh",
    "addr:street":"Picardy Road",
    "iso:country":"GB",
    "sg:address":"2 Picardy Road",
    "sg:city":"Belvedere",
    "sg:classifiers":[
        {
            "category":"Bars & Pubs",
            "type":"Food & Drink"
        }
    ],
    "sg:phone":"+44 1322 432310",
    "sg:postcode":"DA17 5QH",
    "sg:province":"Kent",
    "sg:tags":[
        "pubs",
        "inn"
    ],
    "wof:name":"Punch Retail (Holdings) Ltd.",
    "wof:placetype":"venue"
},
  "geometry": {"coordinates":[0.1514859945,51.4906311035],"type":"Point"}
}