{
  "type": "Feature",
  "properties": {
    "iso:country":"GB",
    "sg:address":"Unit A15, Monmouth St",
    "sg:city":"Bridgwater",
    "sg:classifiers":[
        {
            "category":"Professional",
            "type":"Services"
        }
    ],
    "sg:phone":"+44 1278 431188",
    "sg:postcode":"TA6 5EQ",
    "sg:province":"Somerset",
    "sg:tags":[
        "auctioneer"
    ],
    "wof:name":"Monmouth Street Auction Rooms",
    "wof:placetype":"venue"
},
  "geometry": {"coordinates":[-2.996673,51.129868],"type":"Point"}
}