{
  "type": "Feature",
  "properties": {
    "addr:full":"P.o Box 30 New Town House, Buttermarket St Warrington Cheshire WA1 2QG",
    "addr:housenumber":"30",
    "addr:postcode":"wa1 2qg",
    "addr:street":"P.O Box;Town;Buttermarket St",
    "iso:country":"GB",
    "sg:address":"P.o Box 30 New Town House, Buttermarket St",
    "sg:city":"Warrington",
    "sg:classifiers":[
        {
            "category":"Organizations",
            "subcategory":"Non-profit Organization",
            "type":"Services"
        }
    ],
    "sg:phone":"+44 1925 239625",
    "sg:postcode":"WA1 2QG",
    "sg:province":"Cheshire",
    "sg:tags":[
        "organisation",
        "voluntary",
        "charity"
    ],
    "wof:name":"Business in the Community",
    "wof:placetype":"venue"
},
  "geometry": {"coordinates":[-2.5838499069,53.3886184692],"type":"Point"}
}