{
  "type": "Feature",
  "properties": {
    "iso:country":"GB",
    "sg:address":"Hurst Farm, Wyre Road",
    "sg:city":"Pershore",
    "sg:classifiers":[
        {
            "category":"Retail",
            "subcategory":"Auto Repair",
            "type":"Services"
        }
    ],
    "sg:postcode":"WR10 2JP",
    "sg:province":"Worcestershire",
    "sg:tags":[
        "modification",
        "garage"
    ],
    "wof:name":"Wychavon Garage",
    "wof:placetype":"venue"
},
  "geometry": {"coordinates":[-2.0793390274,52.1137657166],"type":"Point"}
}