{
  "type": "Feature",
  "properties": {
    "addr:full":"59 Lambert Road London Greater London SW2 5BB",
    "addr:housenumber":"59",
    "addr:postcode":"sw2 5bb",
    "addr:street":"Lambert Road",
    "iso:country":"GB",
    "sg:address":"59 Lambert Road",
    "sg:city":"London",
    "sg:classifiers":[
        {
            "category":"Professional",
            "subcategory":"Accounting & Tax Preparation",
            "type":"Services"
        }
    ],
    "sg:phone":"+44 870 366 9608",
    "sg:postcode":"SW2 5BB",
    "sg:province":"Greater London",
    "sg:tags":[
        "consultant"
    ],
    "wof:name":"United States Tax Services",
    "wof:placetype":"venue"
},
  "geometry": {"coordinates":[-0.1243970022,51.4556236267],"type":"Point"}
}