{
  "type": "Feature",
  "properties": {
    "addr:full":"4 Lower Craigo Street Montrose Aberdeenshire DD10 8AU",
    "addr:housenumber":"4",
    "addr:postcode":"dd10 8au",
    "addr:street":"Lower Craigo Street",
    "iso:country":"GB",
    "sg:address":"4 Lower Craigo Street",
    "sg:city":"Montrose",
    "sg:classifiers":[
        {
            "category":"Food & Beverages",
            "subcategory":"Supermarket",
            "type":"Retail Goods"
        }
    ],
    "sg:phone":"+44 1674 673202",
    "sg:postcode":"DD10 8AU",
    "sg:province":"Aberdeenshire",
    "wof:name":"Costcutter",
    "wof:placetype":"venue"
},
  "geometry": {"coordinates":[-2.4712710381,56.7078666687],"type":"Point"}
}