{
  "type": "Feature",
  "properties": {
    "addr:full":"57 Wigan Road, Euxton Chorley Lancashire PR7 6JU",
    "addr:housenumber":"57",
    "addr:postcode":"pr7 6ju",
    "addr:street":"Wigan Road",
    "iso:country":"GB",
    "sg:address":"57 Wigan Road, Euxton",
    "sg:city":"Chorley",
    "sg:classifiers":[
        {
            "category":"Retail",
            "subcategory":"Auto Repair",
            "type":"Services"
        }
    ],
    "sg:phone":"+44 1257 263518",
    "sg:postcode":"PR7 6JU",
    "sg:province":"Lancashire",
    "sg:tags":[
        "modification",
        "garage"
    ],
    "wof:name":"Felton's Service Station",
    "wof:placetype":"venue"
},
  "geometry": {"coordinates":[-2.677216,53.673912],"type":"Point"}
}