{
  "type": "Feature",
  "properties": {
    "addr:full":"252 Crow Road, Broom Hill Glasgow Glasgow City G11 7LA",
    "addr:housenumber":"252",
    "addr:postcode":"g11 7la",
    "addr:street":"Crow Road Broom Hill",
    "iso:country":"GB",
    "sg:address":"252 Crow Road, Broom Hill",
    "sg:city":"Glasgow",
    "sg:classifiers":[
        {
            "category":"Shopping",
            "subcategory":"News",
            "type":"Retail Goods"
        }
    ],
    "sg:phone":"+44 141 334 6227",
    "sg:postcode":"G11 7LA",
    "sg:province":"Glasgow City",
    "sg:tags":[
        "newsagent"
    ],
    "wof:name":"Sanjay",
    "wof:placetype":"venue"
},
  "geometry": {"coordinates":[-4.3199601173,55.8760757446],"type":"Point"}
}