{
  "type": "Feature",
  "properties": {
    "addr:full":"Foxley Works, Redhills Road, Milton Stoke-on-trent Staffordshire ST2 7PE",
    "addr:postcode":"staffordshire st2 7pe",
    "addr:street":"Redhills Road",
    "iso:country":"GB",
    "sg:address":"Foxley Works, Redhills Road, Milton",
    "sg:city":"Stoke-on-trent",
    "sg:classifiers":[
        {
            "category":"Professional",
            "subcategory":"Engineering",
            "type":"Services"
        }
    ],
    "sg:phone":"+44 1782 541024",
    "sg:postcode":"ST2 7PE",
    "sg:province":"Staffordshire",
    "wof:name":"Baddeley Green Engineers Ltd.",
    "wof:placetype":"venue"
},
  "geometry": {"coordinates":[-2.15171,53.04504],"type":"Point"}
}