{
  "type": "Feature",
  "properties": {
    "addr:full":"Nethershaugh Farm, Shaugh Prior Plymouth Devon PL7 5HF",
    "addr:postcode":"pl7 5hf",
    "iso:country":"GB",
    "sg:address":"Nethershaugh Farm, Shaugh Prior",
    "sg:city":"Plymouth",
    "sg:classifiers":[
        {
            "category":"Farming",
            "subcategory":"Livestock Farm",
            "type":"Manufacturing & Wholesale Goods"
        }
    ],
    "sg:postcode":"PL7 5HF",
    "sg:province":"Devon",
    "sg:tags":[
        "others"
    ],
    "wof:name":"E T & M Elliott",
    "wof:placetype":"venue"
},
  "geometry": {"coordinates":[-4.053194,50.449379],"type":"Point"}
}