{
  "type": "Feature",
  "properties": {
    "iso:country":"GB",
    "sg:address":"49 Norbreck Road",
    "sg:city":"Thornton-cleveleys",
    "sg:classifiers":[
        {
            "category":"Retail",
            "subcategory":"Laundry & Dry Cleaning",
            "type":"Services"
        }
    ],
    "sg:phone":"+44 1253 353225",
    "sg:postcode":"FY5 1RR",
    "sg:province":"Lancashire",
    "sg:tags":[
        "alteration"
    ],
    "wof:name":"Dazzles Dry Cleaning",
    "wof:placetype":"venue"
},
  "geometry": {"coordinates":[-3.0472590923,53.8579788208],"type":"Point"}
}