{
  "type": "Feature",
  "properties": {
    "addr:full":"15 Kilroyd Avenue Cleckheaton West Yorkshire BD19 4ED",
    "addr:housenumber":"15",
    "addr:postcode":"bd19 4ed",
    "addr:street":"Kilroyd Avenue",
    "iso:country":"GB",
    "sg:address":"15 Kilroyd Avenue",
    "sg:city":"Cleckheaton",
    "sg:classifiers":[
        {
            "category":"Building & Trades",
            "subcategory":"Landscaping Services",
            "type":"Services"
        }
    ],
    "sg:phone":"+44 1274 870751",
    "sg:postcode":"BD19 4ED",
    "sg:province":"West Yorkshire",
    "sg:tags":[
        "landscape",
        "contractor"
    ],
    "wof:name":"R J Garden Maintenance",
    "wof:placetype":"venue"
},
  "geometry": {"coordinates":[-1.713062,53.736187],"type":"Point"}
}