{
  "type": "Feature",
  "properties": {
    "iso:country":"GB",
    "sg:address":"8 The Broadway",
    "sg:city":"Woking",
    "sg:classifiers":[
        {
            "category":"Fast Food",
            "type":"Food & Drink"
        }
    ],
    "sg:phone":"+44 1483 766250",
    "sg:postcode":"GU21 5AP",
    "sg:province":"Surrey",
    "sg:tags":[
        "away",
        "take"
    ],
    "wof:name":"Swidges",
    "wof:placetype":"venue"
},
  "geometry": {"coordinates":[-0.556389,51.31921],"type":"Point"}
}