{
  "type": "Feature",
  "properties": {
    "addr:full":"Units 49-51, Brunswick Centre, Russell S London Greater London WC1N 1AF",
    "addr:housenumber":"units 49-51",
    "addr:postcode":"wc1n 1af",
    "addr:street":"Brunswick Centre",
    "iso:country":"GB",
    "sg:address":"Units 49-51, Brunswick Centre, Russell S",
    "sg:city":"London",
    "sg:classifiers":[
        {
            "category":"Retail",
            "subcategory":"Laundry & Dry Cleaning",
            "type":"Services"
        }
    ],
    "sg:postcode":"WC1N 1AF",
    "sg:province":"Greater London",
    "sg:tags":[
        "launderette"
    ],
    "wof:name":"Nicell,Gerard,",
    "wof:placetype":"venue"
},
  "geometry": {"coordinates":[-0.12351,51.52422],"type":"Point"}
}