{
  "type": "Feature",
  "properties": {
    "iso:country":"GB",
    "sg:address":"23 Stephenson Rd",
    "sg:city":"Huntingdon",
    "sg:classifiers":[
        {
            "category":"Shopping",
            "subcategory":"Computers & Home Electronics",
            "type":"Retail Goods"
        }
    ],
    "sg:phone":"+44 1480 495496",
    "sg:postcode":"PE17 4WJ",
    "sg:province":"Cambridgeshire",
    "sg:tags":[
        "equipment",
        "video",
        "cctv"
    ],
    "wof:name":"Crimewatch Systems",
    "wof:placetype":"venue"
},
  "geometry": {"coordinates":[-0.1893000007,52.3351402283],"type":"Point"}
}