{
  "type": "Feature",
  "properties": {
    "addr:full":"The Stables, Dyson Road Halifax West Yorkshire HX1 4RL",
    "addr:postcode":"hx1 4rl",
    "addr:street":"Dyson Road",
    "iso:country":"GB",
    "sg:address":"The Stables, Dyson Road",
    "sg:city":"Halifax",
    "sg:classifiers":[
        {
            "category":"Professional",
            "subcategory":"Engineering",
            "type":"Services"
        }
    ],
    "sg:phone":"+44 1422 367411",
    "sg:postcode":"HX1 4RL",
    "sg:province":"West Yorkshire",
    "wof:name":"The Calder Pressing & Lighting Co",
    "wof:placetype":"venue"
},
  "geometry": {"coordinates":[-1.862224,53.721233],"type":"Point"}
}