{
  "type": "Feature",
  "properties": {
    "addr:full":"Rowan Garth, Ripon Road, Killinghall Harrogate North Yorkshire HG3 2DH",
    "addr:postcode":"hg3 2dh",
    "addr:street":"Garth Ripon Road",
    "iso:country":"GB",
    "sg:address":"Rowan Garth, Ripon Road, Killinghall",
    "sg:city":"Harrogate",
    "sg:classifiers":[
        {
            "category":"Professional",
            "subcategory":"Engineering",
            "type":"Services"
        },
        {
            "category":"Building & Trades",
            "subcategory":"Electrical",
            "type":"Services"
        }
    ],
    "sg:phone":"+44 1423 525406",
    "sg:postcode":"HG3 2DH",
    "sg:province":"North Yorkshire",
    "sg:tags":[
        "engineer",
        "electrician",
        "contractor"
    ],
    "wof:name":"Paul Fender",
    "wof:placetype":"venue"
},
  "geometry": {"coordinates":[-1.5642559528,54.024055481],"type":"Point"}
}