{
  "type": "Feature",
  "properties": {
    "iso:country":"GB",
    "sg:address":"The Old Garage, Albert Rd, Bollington",
    "sg:city":"Macclesfield",
    "sg:classifiers":[
        {
            "category":"Retail",
            "subcategory":"Auto Repair",
            "type":"Services"
        }
    ],
    "sg:phone":"+44 1625 573330",
    "sg:postcode":"SK10 5HS",
    "sg:province":"Cheshire",
    "sg:tags":[
        "modification",
        "garage"
    ],
    "wof:name":"D S E Landrover Services",
    "wof:placetype":"venue"
},
  "geometry": {"coordinates":[-2.1103689671,53.2933883667],"type":"Point"}
}