{
  "type": "Feature",
  "properties": {
    "iso:country":"GB",
    "sg:address":"Wenlock Edge, Hill Top",
    "sg:city":"Much Wenlock",
    "sg:classifiers":[
        {
            "category":"Bars & Pubs",
            "type":"Food & Drink"
        }
    ],
    "sg:phone":"+44 1746 785678",
    "sg:postcode":"TF13 6DJ",
    "sg:province":"Shropshire",
    "sg:tags":[
        "pubs",
        "inn"
    ],
    "wof:name":"The Wenlock Edge Inn",
    "wof:placetype":"venue"
},
  "geometry": {"coordinates":[-2.5599250793,52.5940093994],"type":"Point"}
}