{
  "type": "Feature",
  "properties": {
    "iso:country":"GB",
    "sg:address":"742 High Road",
    "sg:city":"Ilford",
    "sg:classifiers":[
        {
            "category":"Wholesale",
            "subcategory":"Machinery & Supplies",
            "type":"Manufacturing & Wholesale Goods"
        }
    ],
    "sg:postcode":"IG3 8SX",
    "sg:province":"Essex",
    "sg:tags":[
        "equipment",
        "handling",
        "lifting"
    ],
    "wof:name":"Autos First Ltd",
    "wof:placetype":"venue"
},
  "geometry": {"coordinates":[0.107507,51.566025],"type":"Point"}
}