{
  "type": "Feature",
  "properties": {
    "addr:full":"Strawberry Hill Farm, Lamphey Pembroke Pembrokeshire SA71 5PG",
    "addr:housenumber":"lamphey",
    "addr:postcode":"sa71 5pg",
    "addr:street":"Hill;Pembroke Pembrokeshire",
    "iso:country":"GB",
    "sg:address":"Strawberry Hill Farm, Lamphey",
    "sg:city":"Pembroke",
    "sg:classifiers":[
        {
            "category":"Freight",
            "type":"Transportation"
        }
    ],
    "sg:phone":"+44 1646 672393",
    "sg:postcode":"SA71 5PG",
    "sg:province":"Pembrokeshire",
    "sg:tags":[
        "haulage",
        "road"
    ],
    "wof:name":"DAVID SAUNDERS",
    "wof:placetype":"venue"
},
  "geometry": {"coordinates":[-4.8719539642,51.6668243408],"type":"Point"}
}