{
  "type": "Feature",
  "properties": {
    "addr:full":"Clarence Road Cardiff Cardiff CF10 5FA",
    "addr:postcode":"cf10 5fa",
    "addr:street":"Clarence Road",
    "iso:country":"GB",
    "sg:address":"Clarence Road",
    "sg:city":"Cardiff",
    "sg:classifiers":[
        {
            "category":"Real Estate",
            "subcategory":"Architect",
            "type":"Services"
        }
    ],
    "sg:phone":"+44 29 2046 0662",
    "sg:postcode":"CF10 5FA",
    "sg:province":"Cardiff",
    "wof:name":"Noel Architects",
    "wof:placetype":"venue"
},
  "geometry": {"coordinates":[-3.174347,51.465195],"type":"Point"}
}