{
  "type": "Feature",
  "properties": {
    "addr:full":"Moor Park, Chester Moor Chester-le-street Durham DH2 3RW",
    "addr:postcode":"dh2 3rw",
    "addr:street":"Moor Park Chester Moor Chester-Le-Street",
    "iso:country":"GB",
    "sg:address":"Moor Park, Chester Moor",
    "sg:city":"Chester-le-street",
    "sg:classifiers":[
        {
            "category":"Arena",
            "subcategory":"Sports Club",
            "type":"Entertainment"
        }
    ],
    "sg:phone":"+44 191 388 3363",
    "sg:postcode":"DH2 3RW",
    "sg:province":"Durham",
    "wof:name":"Chester le Street Town Football Club",
    "wof:placetype":"venue"
},
  "geometry": {"coordinates":[-1.5880999565,54.8359603882],"type":"Point"}
}