{
  "type": "Feature",
  "properties": {
    "addr:full":"Maitland Road Ipswich Suffolk IP6 8NZ",
    "addr:postcode":"ip6 8nz",
    "addr:street":"Maitland Road",
    "iso:country":"GB",
    "sg:address":"Maitland Road",
    "sg:city":"Ipswich",
    "sg:classifiers":[
        {
            "category":"Autos & Motor Vehicles",
            "subcategory":"Auto Supplies",
            "type":"Retail Goods"
        }
    ],
    "sg:phone":"+44 1449 721731",
    "sg:postcode":"IP6 8NZ",
    "sg:province":"Suffolk",
    "sg:tags":[
        "tyre"
    ],
    "wof:name":"Needham Tyre Supplies",
    "wof:placetype":"venue"
},
  "geometry": {"coordinates":[1.062909,52.147018],"type":"Point"}
}