{
  "type": "Feature",
  "properties": {
    "addr:full":"Hylas Lane, Rhuddlan Rhyl Conwy LL18 5AG",
    "addr:postcode":"ll18 5ag",
    "addr:street":"Hylas Lane",
    "iso:country":"GB",
    "sg:address":"Hylas Lane, Rhuddlan",
    "sg:city":"Rhyl",
    "sg:classifiers":[
        {
            "category":"Education",
            "subcategory":"School",
            "type":"Public Place"
        }
    ],
    "sg:phone":"+44 1745 590545",
    "sg:postcode":"LL18 5AG",
    "sg:province":"Conwy",
    "sg:tags":[
        "local",
        "authority"
    ],
    "wof:name":"Ysgol Y Castell",
    "wof:placetype":"venue"
},
  "geometry": {"coordinates":[-3.462467,53.289478],"type":"Point"}
}