{
  "type": "Feature",
  "properties": {
    "iso:country":"GB",
    "sg:address":"Phoenix Business Park, John Nike Way",
    "sg:city":"Bracknell",
    "sg:classifiers":[
        {
            "category":"Professional",
            "subcategory":"Printing & Photocopies",
            "type":"Services"
        }
    ],
    "sg:phone":"+44 1344 789500",
    "sg:postcode":"RG12 8TN",
    "sg:province":"Berkshire",
    "sg:tags":[
        "printer"
    ],
    "wof:name":"RAINBOW COLOUR PRINT LTD",
    "wof:placetype":"venue"
},
  "geometry": {"coordinates":[-0.7867799997,51.4153785706],"type":"Point"}
}