{
  "type": "Feature",
  "properties": {
    "iso:country":"GB",
    "sg:address":"55 Melbourne Street",
    "sg:city":"Stalybridge",
    "sg:classifiers":[
        {
            "category":"Personal",
            "subcategory":"Beauty Salon",
            "type":"Services"
        }
    ],
    "sg:phone":"+44 161 304 9636",
    "sg:postcode":"SK15 2JJ",
    "sg:province":"Greater Manchester",
    "sg:tags":[
        "unisex",
        "hairdresser"
    ],
    "wof:name":"Cream Hairdressing-Mama Appointed Salon",
    "wof:placetype":"venue"
},
  "geometry": {"coordinates":[-2.057553,53.482761],"type":"Point"}
}