{
  "type": "Feature",
  "properties": {
    "iso:country":"GB",
    "sg:address":"Plot B Unit 4 Clifton Trading Est",
    "sg:city":"Newbridge",
    "sg:classifiers":[
        {
            "category":"Government",
            "subcategory":"Post Office",
            "type":"Public Place"
        }
    ],
    "sg:phone":"+44 131 333 3944",
    "sg:postcode":"EH28 8TP",
    "sg:province":"City of Edinburgh",
    "sg:tags":[
        "messenger",
        "courier"
    ],
    "wof:name":"World Xpress",
    "wof:placetype":"venue"
},
  "geometry": {"coordinates":[-3.409335,55.940845],"type":"Point"}
}