{
  "type": "Feature",
  "properties": {
    "addr:full":"102 Princes Avenue Chatham Kent ME5 8AH",
    "addr:housenumber":"102",
    "addr:postcode":"me5 8ah",
    "addr:street":"Princes Avenue",
    "iso:country":"GB",
    "sg:address":"102 Princes Avenue",
    "sg:city":"Chatham",
    "sg:classifiers":[
        {
            "category":"Building & Trades",
            "subcategory":"Construction",
            "type":"Services"
        }
    ],
    "sg:phone":"+44 1634 684382",
    "sg:postcode":"ME5 8AH",
    "sg:province":"Kent",
    "sg:tags":[
        "builder"
    ],
    "wof:name":"G & G Builders & Contractors",
    "wof:placetype":"venue"
},
  "geometry": {"coordinates":[0.530353,51.344406],"type":"Point"}
}