{
  "type": "Feature",
  "properties": {
    "addr:full":"Unit 24 Thurnscoe Business Centr, E Princess Drive, Thurnscoe Rotherham South Yorkshire S63 0BL",
    "addr:housenumber":"unit 24",
    "addr:postcode":"s63 0bl",
    "addr:street":"Thurnscoe Business Centr E Princess Drive",
    "iso:country":"GB",
    "sg:address":"Unit 24 Thurnscoe Business Centr, E Princess Drive, Thurnscoe",
    "sg:city":"Rotherham",
    "sg:classifiers":[
        {
            "category":"Food & Beverages",
            "subcategory":"Candy",
            "type":"Retail Goods"
        }
    ],
    "sg:phone":"+44 1709 891453",
    "sg:postcode":"S63 0BL",
    "sg:province":"South Yorkshire",
    "sg:tags":[
        "confectioner"
    ],
    "wof:name":"Pearson Pre Pack",
    "wof:placetype":"venue"
},
  "geometry": {"coordinates":[-1.299559,53.542591],"type":"Point"}
}