{
  "type": "Feature",
  "properties": {
    "iso:country":"GB",
    "sg:address":"2 Bridge St",
    "sg:city":"Sheffield",
    "sg:classifiers":[
        {
            "category":"Home & Garden",
            "subcategory":"Building Materials",
            "type":"Retail Goods"
        }
    ],
    "sg:phone":"+44 1226 763313",
    "sg:postcode":"S36 6AJ",
    "sg:province":"South Yorkshire",
    "sg:tags":[
        "fencing"
    ],
    "wof:name":"Z N D (UK) Ltd",
    "wof:placetype":"venue"
},
  "geometry": {"coordinates":[-1.631614,53.527023],"type":"Point"}
}