{
  "type": "Feature",
  "properties": {
    "iso:country":"GB",
    "sg:address":"2a Church Road, Bishops Cleeve",
    "sg:city":"Cheltenham",
    "sg:classifiers":[
        {
            "category":"Shopping",
            "subcategory":"Florist",
            "type":"Retail Goods"
        }
    ],
    "sg:phone":"+44 1242 678733",
    "sg:postcode":"GL52 8LR",
    "sg:province":"Gloucestershire",
    "wof:name":"Variete",
    "wof:placetype":"venue"
},
  "geometry": {"coordinates":[-2.0619699955,51.9473342896],"type":"Point"}
}