{
  "type": "Feature",
  "properties": {
    "addr:full":"23 Westover Road Bournemouth Dorset BH1 2BZ",
    "addr:housenumber":"23",
    "addr:postcode":"bh1 2bz",
    "addr:street":"Westover Road",
    "iso:country":"GB",
    "sg:address":"23 Westover Road",
    "sg:city":"Bournemouth",
    "sg:classifiers":[
        {
            "category":"Shopping",
            "subcategory":"Department Store",
            "type":"Retail Goods"
        },
        {
            "category":"Shopping",
            "subcategory":"Jewelry",
            "type":"Retail Goods"
        },
        {
            "category":"Shopping",
            "subcategory":"Comic Books",
            "type":"Retail Goods"
        }
    ],
    "sg:phone":"+44 1202 558928",
    "sg:postcode":"BH1 2BZ",
    "sg:province":"Dorset",
    "sg:tags":[
        "jeweller",
        "sale",
        "jewellery"
    ],
    "wof:name":"J Franses & Son Jewellers",
    "wof:placetype":"venue"
},
  "geometry": {"coordinates":[-1.875217,50.71883],"type":"Point"}
}