{
  "type": "Feature",
  "properties": {
    "addr:full":"14 Stansfield Clo Halifax West Yorkshire HX1 5QF",
    "addr:housenumber":"14",
    "addr:postcode":"hx1 5qf",
    "addr:street":"Stansfield Clo",
    "iso:country":"GB",
    "sg:address":"14 Stansfield Clo",
    "sg:city":"Halifax",
    "sg:classifiers":[
        {
            "category":"Social Services",
            "subcategory":"Adult Care",
            "type":"Services"
        }
    ],
    "sg:phone":"+44 1422 368441",
    "sg:postcode":"HX1 5QF",
    "sg:province":"West Yorkshire",
    "sg:tags":[
        "housing",
        "sheltered"
    ],
    "wof:name":"Stansfield Close",
    "wof:placetype":"venue"
},
  "geometry": {"coordinates":[-1.87395,53.725266],"type":"Point"}
}