{
  "type": "Feature",
  "properties": {
    "iso:country":"GB",
    "sg:address":"90 Warley Rd",
    "sg:city":"Blackpool",
    "sg:classifiers":[
        {
            "category":"Travel",
            "subcategory":"Hotels & Motels",
            "type":"Entertainment"
        }
    ],
    "sg:phone":"+44 1253 355216",
    "sg:postcode":"FY1 2RP",
    "sg:province":"Lancashire",
    "sg:tags":[
        "house",
        "guest"
    ],
    "wof:name":"Windsor Guest House",
    "wof:placetype":"venue"
},
  "geometry": {"coordinates":[-3.049026,53.830929],"type":"Point"}
}