{
  "type": "Feature",
  "properties": {
    "addr:full":"31 Waterloo Road Norwich Norfolk NR3 1EG",
    "addr:housenumber":"31",
    "addr:postcode":"nr3 1eg",
    "addr:street":"Waterloo Road Norwich Norfolk",
    "iso:country":"GB",
    "sg:address":"31 Waterloo Road",
    "sg:city":"Norwich",
    "sg:classifiers":[
        {
            "category":"Personal",
            "subcategory":"Tanning Parlor",
            "type":"Services"
        },
        {
            "category":"Building & Trades",
            "subcategory":"Cleaning & Sanitation",
            "type":"Services"
        }
    ],
    "sg:phone":"+44 1603 410313",
    "sg:postcode":"NR3 1EG",
    "sg:province":"Norfolk",
    "sg:tags":[
        "dry",
        "control",
        "damp",
        "rot",
        "sunbeds"
    ],
    "wof:name":"Ambertan Sunbeds",
    "wof:placetype":"venue"
},
  "geometry": {"coordinates":[1.2955800295,52.6430854797],"type":"Point"}
}