{
  "type": "Feature",
  "properties": {
    "iso:country":"GB",
    "sg:address":"Green End Lane, Great Holland",
    "sg:city":"Frinton-on-sea",
    "sg:classifiers":[
        {
            "category":"Retail",
            "subcategory":"Auto Repair",
            "type":"Services"
        }
    ],
    "sg:phone":"+44 1255 675466",
    "sg:postcode":"CO13 0JA",
    "sg:province":"Essex",
    "sg:tags":[
        "modification",
        "garage",
        "related"
    ],
    "wof:name":"Green End Garage",
    "wof:placetype":"venue"
},
  "geometry": {"coordinates":[1.21433,51.834949],"type":"Point"}
}