{
  "type": "Feature",
  "properties": {
    "addr:full":"213 Grangehill Rd Eltham Greater London SE9 1SR",
    "addr:housenumber":"213",
    "addr:postcode":"se9 1sr",
    "addr:street":"Grangehill Rd",
    "iso:country":"GB",
    "sg:address":"213 Grangehill Rd",
    "sg:city":"Eltham",
    "sg:classifiers":[
        {
            "category":"Arts & Performance",
            "subcategory":"Theater",
            "type":"Entertainment"
        }
    ],
    "sg:phone":"+44 20 8859 5552",
    "sg:postcode":"SE9 1SR",
    "sg:province":"Greater London",
    "sg:tags":[
        "theatrical",
        "agency"
    ],
    "wof:name":"D & B Management",
    "wof:placetype":"venue"
},
  "geometry": {"coordinates":[0.0559469983,51.4624061584],"type":"Point"}
}