{
  "type": "Feature",
  "properties": {
    "addr:full":"538 Manchester Road Bury Lancashire BL9 9PA",
    "addr:housenumber":"538",
    "addr:postcode":"bl9 9pa",
    "addr:street":"Manchester Road",
    "iso:country":"GB",
    "sg:address":"538 Manchester Road",
    "sg:city":"Bury",
    "sg:classifiers":[
        {
            "category":"Building & Trades",
            "subcategory":"Plumbing",
            "type":"Services"
        }
    ],
    "sg:postcode":"BL9 9PA",
    "sg:province":"Lancashire",
    "sg:tags":[
        "central",
        "heating"
    ],
    "wof:name":"Anglo Heating & Maintenance",
    "wof:placetype":"venue"
},
  "geometry": {"coordinates":[-2.295024,53.571957],"type":"Point"}
}