{
  "type": "Feature",
  "properties": {
    "addr:full":"69 Heronswood Rd, Rednal Birmingham West Midlands B45 8QT",
    "addr:housenumber":"69",
    "addr:postcode":"b45 8qt",
    "addr:street":"Heronswood Rd",
    "iso:country":"GB",
    "sg:address":"69 Heronswood Rd, Rednal",
    "sg:city":"Birmingham",
    "sg:classifiers":[
        {
            "category":"Building & Trades",
            "subcategory":"Construction",
            "type":"Services"
        }
    ],
    "sg:postcode":"B45 8QT",
    "sg:province":"West Midlands",
    "sg:tags":[
        "decorator",
        "painter"
    ],
    "wof:name":"Stewart,John W,",
    "wof:placetype":"venue"
},
  "geometry": {"coordinates":[-2.002674,52.386871],"type":"Point"}
}