{
  "type": "Feature",
  "properties": {
    "iso:country":"GB",
    "sg:address":"Unit 5 Brookfield Industrial Estate, Brookfield Road",
    "sg:city":"Cheadle",
    "sg:classifiers":[
        {
            "category":"Shopping",
            "subcategory":"Clothing, Apparel, & Fashions",
            "type":"Retail Goods"
        }
    ],
    "sg:phone":"+44 161 428 1933",
    "sg:postcode":"SK8 2PN",
    "sg:province":"Cheshire",
    "sg:tags":[
        "t-shirt"
    ],
    "wof:name":"The Bagging Co",
    "wof:placetype":"venue"
},
  "geometry": {"coordinates":[-2.212272,53.395248],"type":"Point"}
}