{
  "type": "Feature",
  "properties": {
    "iso:country":"GB",
    "sg:address":"45 Eliotts Drive",
    "sg:city":"Yeovil",
    "sg:classifiers":[
        {
            "category":"Wholesale",
            "subcategory":"Computers",
            "type":"Manufacturing & Wholesale Goods"
        },
        {
            "category":"Professional",
            "subcategory":"Computer Services",
            "type":"Services"
        }
    ],
    "sg:phone":"+44 1935 473450",
    "sg:postcode":"BA21 3NN",
    "sg:province":"Somerset",
    "sg:tags":[
        "supplier",
        "consumables",
        "system",
        "software"
    ],
    "wof:name":"Designer Software",
    "wof:placetype":"venue"
},
  "geometry": {"coordinates":[-2.651641,50.952999],"type":"Point"}
}