{
  "type": "Feature",
  "properties": {
    "addr:full":"250 Ferndale Road London Greater London SW9 8BQ",
    "addr:housenumber":"250",
    "addr:postcode":"sw9 8bq",
    "addr:street":"Ferndale Road",
    "iso:country":"GB",
    "sg:address":"250 Ferndale Road",
    "sg:city":"London",
    "sg:classifiers":[
        {
            "category":"Government",
            "subcategory":"Post Office",
            "type":"Public Place"
        }
    ],
    "sg:phone":"+44 20 7274 1503",
    "sg:postcode":"SW9 8BQ",
    "sg:province":"Greater London",
    "wof:name":"Post Office Counters Ltd.",
    "wof:placetype":"venue"
},
  "geometry": {"coordinates":[-0.11563,51.464081],"type":"Point"}
}