{
  "type": "Feature",
  "properties": {
    "iso:country":"GB",
    "sg:address":"114 Sutton Park Rd",
    "sg:city":"Kidderminster",
    "sg:classifiers":[
        {
            "category":"Building & Trades",
            "subcategory":"Construction",
            "type":"Services"
        }
    ],
    "sg:phone":"+44 1562 746771",
    "sg:postcode":"DY11 6JG",
    "sg:province":"Staffordshire",
    "sg:tags":[
        "builder"
    ],
    "wof:name":"Worcestershire Building Services",
    "wof:placetype":"venue"
},
  "geometry": {"coordinates":[-2.2754359245,52.3818588257],"type":"Point"}
}