{
  "type": "Feature",
  "properties": {
    "addr:full":"5 Helena Pl, Church St Hemel Hempstead Hertfordshire HP2 5AD",
    "addr:housenumber":"5",
    "addr:postcode":"hp2 5ad",
    "addr:street":"Helena Pl Church St",
    "iso:country":"GB",
    "sg:address":"5 Helena Pl, Church St",
    "sg:city":"Hemel Hempstead",
    "sg:classifiers":[
        {
            "category":"Manufacturing",
            "subcategory":"Buildings",
            "type":"Manufacturing & Wholesale Goods"
        }
    ],
    "sg:phone":"+44 1442 250669",
    "sg:postcode":"HP2 5AD",
    "sg:province":"Hertfordshire",
    "sg:tags":[
        "system",
        "air conditioning"
    ],
    "wof:name":"A & S Car Air-Con Services",
    "wof:placetype":"venue"
},
  "geometry": {"coordinates":[-0.454764,51.75761],"type":"Point"}
}