{
  "type": "Feature",
  "properties": {
    "iso:country":"GB",
    "sg:address":"5 Ullswater Close",
    "sg:city":"Biggleswade",
    "sg:classifiers":[
        {
            "category":"Building & Trades",
            "subcategory":"Construction",
            "type":"Services"
        }
    ],
    "sg:phone":"+44 1767 316035",
    "sg:postcode":"SG18 8LX",
    "sg:province":"Bedfordshire",
    "sg:tags":[
        "joiner",
        "carpenter"
    ],
    "wof:name":"B A Wilson & Son",
    "wof:placetype":"venue"
},
  "geometry": {"coordinates":[-0.2562600076,52.0780181885],"type":"Point"}
}