{
  "type": "Feature",
  "properties": {
    "addr:full":"12 Brown Ave, Mansfield Woodhouse Mansfield Derbyshire NG19 8HG",
    "addr:housenumber":"12",
    "addr:postcode":"ng19 8hg",
    "addr:street":"Brown Ave",
    "iso:country":"GB",
    "sg:address":"12 Brown Ave, Mansfield Woodhouse",
    "sg:city":"Mansfield",
    "sg:classifiers":[
        {
            "category":"Shopping",
            "subcategory":"News",
            "type":"Retail Goods"
        }
    ],
    "sg:postcode":"NG19 8HG",
    "sg:province":"Derbyshire",
    "sg:tags":[
        "newsagent"
    ],
    "wof:name":"Rayner,J M & Y A,",
    "wof:placetype":"venue"
},
  "geometry": {"coordinates":[-1.1967400312,53.1711921692],"type":"Point"}
}