{
  "type": "Feature",
  "properties": {
    "addr:full":"Suite 3 Claridge Ho, 32 Davies St West End Hampshire W1Y 1LG",
    "addr:housenumber":"suite 3;32",
    "addr:postcode":"w1y 1lg",
    "addr:street":"Claridge Ho;Davies St",
    "iso:country":"GB",
    "sg:address":"Suite 3 Claridge Ho, 32 Davies St",
    "sg:city":"West End",
    "sg:classifiers":[
        {
            "category":"Real Estate",
            "subcategory":"Real Estate Operator",
            "type":"Services"
        }
    ],
    "sg:phone":"+44 20 7935 3521",
    "sg:postcode":"W1Y 1LG",
    "sg:province":"Hampshire",
    "sg:tags":[
        "letting",
        "agent"
    ],
    "wof:name":"West Trend Apartments",
    "wof:placetype":"venue"
},
  "geometry": {"coordinates":[-0.1389899999,51.5075798035],"type":"Point"}
}