{
  "type": "Feature",
  "properties": {
    "iso:country":"GB",
    "sg:address":"157 Walton Rd",
    "sg:city":"East Molesey",
    "sg:classifiers":[
        {
            "category":"Food & Beverages",
            "subcategory":"Supermarket",
            "type":"Retail Goods"
        }
    ],
    "sg:phone":"+44 20 8979 2203",
    "sg:postcode":"KT8 0DX",
    "sg:province":"Greater London",
    "wof:name":"b2",
    "wof:placetype":"venue"
},
  "geometry": {"coordinates":[-0.3593170047,51.4008483887],"type":"Point"}
}