{
  "type": "Feature",
  "properties": {
    "addr:full":"Yalberton Road Paignton Devon TQ4 7PJ",
    "addr:postcode":"tq4 7pj",
    "addr:street":"Yalberton Road",
    "iso:country":"GB",
    "sg:address":"Yalberton Road",
    "sg:city":"Paignton",
    "sg:classifiers":[
        {
            "category":"Wholesale",
            "subcategory":"Scrap",
            "type":"Manufacturing & Wholesale Goods"
        }
    ],
    "sg:phone":"+44 1803 555953",
    "sg:postcode":"TQ4 7PJ",
    "sg:province":"Devon",
    "sg:tags":[
        "breaker",
        "dismantlers"
    ],
    "wof:name":"Quarry Breakers",
    "wof:placetype":"venue"
},
  "geometry": {"coordinates":[-3.5999200344,50.4203605652],"type":"Point"}
}