{
  "type": "Feature",
  "properties": {
    "iso:country":"GB",
    "sg:address":"124 London Road",
    "sg:city":"Leicester",
    "sg:classifiers":[
        {
            "category":"Personal",
            "subcategory":"Beauty Salon",
            "type":"Services"
        }
    ],
    "sg:phone":"+44 116 254 7787",
    "sg:postcode":"LE2 0QS",
    "sg:province":"Leicestershire",
    "wof:name":"Venus Beauty Salon",
    "wof:placetype":"venue"
},
  "geometry": {"coordinates":[-1.1201430559,52.6276741028],"type":"Point"}
}