{
  "type": "Feature",
  "properties": {
    "addr:full":"Cromdale Road Grantown-on-spey Highland PH26 3HU",
    "addr:postcode":"ph26 3hu",
    "addr:street":"Cromdale Road Grantown-On-Spey",
    "iso:country":"GB",
    "sg:address":"Cromdale Road",
    "sg:city":"Grantown-on-spey",
    "sg:classifiers":[
        {
            "category":"Education",
            "subcategory":"School",
            "type":"Public Place"
        },
        {
            "category":"Government",
            "subcategory":"Office",
            "type":"Public Place"
        }
    ],
    "sg:phone":"+44 1479 872649",
    "sg:postcode":"PH26 3HU",
    "sg:province":"Highland",
    "sg:tags":[
        "local",
        "authority"
    ],
    "wof:name":"Grantown Grammar School",
    "wof:placetype":"venue"
},
  "geometry": {"coordinates":[-3.6067790985,57.3320007324],"type":"Point"}
}