{
  "type": "Feature",
  "properties": {
    "addr:full":"Stow Park Road, Stow Lincoln Lincolnshire LN1 2DD",
    "addr:postcode":"ln1 2dd",
    "addr:street":"Park Road",
    "iso:country":"GB",
    "sg:address":"Stow Park Road, Stow",
    "sg:city":"Lincoln",
    "sg:classifiers":[
        {
            "category":"Retail",
            "subcategory":"Auto Repair",
            "type":"Services"
        }
    ],
    "sg:phone":"+44 1427 788321",
    "sg:postcode":"LN1 2DD",
    "sg:province":"Lincolnshire",
    "sg:tags":[
        "modification",
        "garage"
    ],
    "wof:name":"Williams Garage",
    "wof:placetype":"venue"
},
  "geometry": {"coordinates":[-0.6773030162,53.3269424438],"type":"Point"}
}