{
  "type": "Feature",
  "properties": {
    "iso:country":"GB",
    "sg:address":"Wansford",
    "sg:city":"Peterborough",
    "sg:classifiers":[
        {
            "category":"Organizations",
            "subcategory":"Community Association",
            "type":"Services"
        },
        {
            "category":"Organizations",
            "subcategory":"Non-profit Organization",
            "type":"Services"
        }
    ],
    "sg:phone":"+44 1780 783331",
    "sg:postcode":"PE8 6NN",
    "sg:province":"Cambridgeshire",
    "sg:tags":[
        "organisation",
        "care",
        "animal",
        "welfare"
    ],
    "wof:name":"Animal Helpline",
    "wof:placetype":"venue"
},
  "geometry": {"coordinates":[-0.458310008,52.5918617249],"type":"Point"}
}