{
  "type": "Feature",
  "properties": {
    "addr:full":"Crump Farm, Tawney Common Epping Essex CM16 7PU",
    "addr:postcode":"cm16 7pu",
    "addr:street":"Tawney Common",
    "iso:country":"GB",
    "sg:address":"Crump Farm, Tawney Common",
    "sg:city":"Epping",
    "sg:classifiers":[
        {
            "category":"Home & Garden",
            "subcategory":"Garden Supply",
            "type":"Retail Goods"
        }
    ],
    "sg:postcode":"CM16 7PU",
    "sg:province":"Essex",
    "sg:tags":[
        "bulb",
        "grower"
    ],
    "wof:name":"W P Power & Son",
    "wof:placetype":"venue"
},
  "geometry": {"coordinates":[0.1116589978,51.6992988586],"type":"Point"}
}