{
  "type": "Feature",
  "properties": {
    "addr:full":"42 Church Road, Formby Liverpool Lancashire L37 3NF",
    "addr:housenumber":"42",
    "addr:postcode":"l37 3nf",
    "addr:street":"Church Road",
    "iso:country":"GB",
    "sg:address":"42 Church Road, Formby",
    "sg:city":"Liverpool",
    "sg:classifiers":[
        {
            "category":"Personal",
            "subcategory":"Beauty Salon",
            "type":"Services"
        }
    ],
    "sg:postcode":"L37 3NF",
    "sg:province":"Lancashire",
    "sg:tags":[
        "unisex",
        "hairdresser"
    ],
    "wof:name":"Joan Harris",
    "wof:placetype":"venue"
},
  "geometry": {"coordinates":[-3.0565679073,53.558631897],"type":"Point"}
}