{
  "type": "Feature",
  "properties": {
    "iso:country":"GB",
    "sg:address":"61 Cove Road",
    "sg:city":"Farnborough",
    "sg:classifiers":[
        {
            "category":"Food & Beverages",
            "subcategory":"Meat & Fish",
            "type":"Retail Goods"
        }
    ],
    "sg:phone":"+44 1252 541742",
    "sg:postcode":"GU14 0EX",
    "sg:province":"Hampshire",
    "sg:tags":[
        "chip"
    ],
    "wof:name":"Elite Fisheries",
    "wof:placetype":"venue"
},
  "geometry": {"coordinates":[-0.767372,51.292122],"type":"Point"}
}