{
  "type": "Feature",
  "properties": {
    "iso:country":"GB",
    "sg:address":"14 Old London Road, Badgers Mount",
    "sg:city":"Sevenoaks",
    "sg:classifiers":[
        {
            "category":"Government",
            "subcategory":"Post Office",
            "type":"Public Place"
        }
    ],
    "sg:phone":"+44 1959 534283",
    "sg:postcode":"TN14 7AE",
    "sg:province":"Kent",
    "wof:name":"Badgers Mount Sub Post Office",
    "wof:placetype":"venue"
},
  "geometry": {"coordinates":[0.12648,51.317921],"type":"Point"}
}