{
  "type": "Feature",
  "properties": {
    "iso:country":"GB",
    "sg:address":"365 Fulham Road",
    "sg:city":"London",
    "sg:classifiers":[
        {
            "category":"Personal",
            "subcategory":"Nail Salon",
            "type":"Services"
        }
    ],
    "sg:phone":"+44 20 7351 3693",
    "sg:postcode":"SW10 9TN",
    "sg:province":"Greater London",
    "sg:tags":[
        "solarium",
        "tanning"
    ],
    "wof:name":"Electric Beach",
    "wof:placetype":"venue"
},
  "geometry": {"coordinates":[-0.18178,51.485359],"type":"Point"}
}