{
  "type": "Feature",
  "properties": {
    "addr:full":"82 Toen Road Welwyn Garden City Hertfordshire AL7 1BD",
    "addr:housenumber":"82",
    "addr:postcode":"al7 1bd",
    "addr:street":"Toen Road",
    "iso:country":"GB",
    "sg:address":"82 Toen Road",
    "sg:city":"Welwyn Garden City",
    "sg:classifiers":[
        {
            "category":"Manufacturing",
            "subcategory":"Tools & Machinery",
            "type":"Manufacturing & Wholesale Goods"
        }
    ],
    "sg:postcode":"AL7 1BD",
    "sg:province":"Hertfordshire",
    "sg:tags":[
        "design",
        "maker"
    ],
    "wof:name":"Lingwood Tools",
    "wof:placetype":"venue"
},
  "geometry": {"coordinates":[-0.1905609965,51.8056945801],"type":"Point"}
}