{
  "type": "Feature",
  "properties": {
    "iso:country":"GB",
    "sg:address":"6-8 Upper Green East",
    "sg:city":"Mitcham",
    "sg:classifiers":[
        {
            "category":"Restaurant",
            "type":"Food & Drink"
        }
    ],
    "sg:phone":"+44 20 8648 9555",
    "sg:postcode":"CR4 2PA",
    "sg:province":"Greater London",
    "wof:name":"Cavotoro Greek & International Restaurant",
    "wof:placetype":"venue"
},
  "geometry": {"coordinates":[-0.1629679948,51.4048233032],"type":"Point"}
}