{
  "type": "Feature",
  "properties": {
    "iso:country":"GB",
    "sg:address":"285 West Street",
    "sg:city":"Crewe",
    "sg:classifiers":[
        {
            "category":"Personal",
            "subcategory":"Beauty Salon",
            "type":"Services"
        }
    ],
    "sg:postcode":"CW1 3HU",
    "sg:province":"Cheshire",
    "sg:tags":[
        "unisex",
        "hairdresser"
    ],
    "wof:name":"Just Jane Hair Design",
    "wof:placetype":"venue"
},
  "geometry": {"coordinates":[-2.4610579014,53.1025276184],"type":"Point"}
}