{
  "type": "Feature",
  "properties": {
    "addr:full":"Penwyn Garage, Hendra Road St Austell Cornwall PL26 8EQ",
    "addr:postcode":"pl26 8eq",
    "addr:street":"Hendra Road",
    "iso:country":"GB",
    "sg:address":"Penwyn Garage, Hendra Road",
    "sg:city":"St Austell",
    "sg:classifiers":[
        {
            "category":"Retail",
            "subcategory":"Auto Repair",
            "type":"Services"
        }
    ],
    "sg:phone":"+44 1726 822329",
    "sg:postcode":"PL26 8EQ",
    "sg:province":"Cornwall",
    "sg:tags":[
        "modification",
        "garage"
    ],
    "wof:name":"E G Brokenshire & Sons",
    "wof:placetype":"venue"
},
  "geometry": {"coordinates":[-4.8837199211,50.3796005249],"type":"Point"}
}