{
  "type": "Feature",
  "properties": {
    "addr:full":"Unit 1 Castings Road, Middlefield Industrial Centre Falkirk Falkirk FK2 9HQ",
    "addr:housenumber":"unit 1",
    "addr:postcode":"fk2 9hq",
    "addr:street":"Castings Road;Centre",
    "iso:country":"GB",
    "sg:address":"Unit 1 Castings Road, Middlefield Industrial Centre",
    "sg:city":"Falkirk",
    "sg:classifiers":[
        {
            "category":"Manufacturing",
            "subcategory":"Building Materials",
            "type":"Manufacturing & Wholesale Goods"
        }
    ],
    "sg:phone":"+44 1324 638383",
    "sg:postcode":"FK2 9HQ",
    "sg:province":"Falkirk",
    "sg:tags":[
        "merchant",
        "builder"
    ],
    "wof:name":"Graham Builders Merchants",
    "wof:placetype":"venue"
},
  "geometry": {"coordinates":[-3.7660338879,56.0082511902],"type":"Point"}
}