{
  "type": "Feature",
  "properties": {
    "addr:full":"15 St Helens Rd Ormskirk Lancashire L39 4QJ",
    "addr:housenumber":"15",
    "addr:postcode":"l39 4qj",
    "addr:street":"St Helens Rd",
    "iso:country":"GB",
    "sg:address":"15 St Helens Rd",
    "sg:city":"Ormskirk",
    "sg:classifiers":[
        {
            "category":"Shopping",
            "subcategory":"Clothing, Apparel, & Fashions",
            "type":"Retail Goods"
        }
    ],
    "sg:phone":"+44 1695 576800",
    "sg:postcode":"L39 4QJ",
    "sg:province":"Lancashire",
    "sg:tags":[
        "t-shirt"
    ],
    "wof:name":"O'Malley",
    "wof:placetype":"venue"
},
  "geometry": {"coordinates":[-2.883147,53.565971],"type":"Point"}
}