{
  "type": "Feature",
  "properties": {
    "iso:country":"GB",
    "sg:address":"30 Mill Street",
    "sg:city":"Bedford",
    "sg:classifiers":[
        {
            "category":"Real Estate",
            "subcategory":"Architect",
            "type":"Services"
        }
    ],
    "sg:phone":"+44 1234 350716",
    "sg:postcode":"MK40 3HD",
    "sg:province":"Bedfordshire",
    "sg:tags":[
        "architectural"
    ],
    "wof:name":"Simic Associates",
    "wof:placetype":"venue"
},
  "geometry": {"coordinates":[-0.464562,52.13707],"type":"Point"}
}