{
  "type": "Feature",
  "properties": {
    "addr:full":"15 Meon Rd Acton Greater London W3 8AN",
    "addr:housenumber":"15",
    "addr:postcode":"w3 8an",
    "addr:street":"Meon Rd",
    "iso:country":"GB",
    "sg:address":"15 Meon Rd",
    "sg:city":"Acton",
    "sg:classifiers":[
        {
            "category":"Building & Trades",
            "subcategory":"Plumbing",
            "type":"Services"
        }
    ],
    "sg:phone":"+44 20 8248 8154",
    "sg:postcode":"W3 8AN",
    "sg:province":"Greater London",
    "sg:tags":[
        "heating"
    ],
    "wof:name":"D J Haran",
    "wof:placetype":"venue"
},
  "geometry": {"coordinates":[-0.26806,51.504032],"type":"Point"}
}