{
  "type": "Feature",
  "properties": {
    "addr:full":"1a-1b Unit, Guildford Road Industrial Estate Hayle Cornwall TR27 4QZ",
    "addr:housenumber":"1a-1b unit",
    "addr:postcode":"tr27 4qz",
    "addr:street":"Guildford Road Industrial Estate",
    "iso:country":"GB",
    "sg:address":"1a-1b Unit, Guildford Road Industrial Estate",
    "sg:city":"Hayle",
    "sg:classifiers":[
        {
            "category":"Home & Garden",
            "subcategory":"Hardware",
            "type":"Retail Goods"
        }
    ],
    "sg:phone":"+44 1736 754415",
    "sg:postcode":"TR27 4QZ",
    "sg:province":"Cornwall",
    "sg:tags":[
        "equipment",
        "welding"
    ],
    "wof:name":"D J W Engineering & Welding Supplies",
    "wof:placetype":"venue"
},
  "geometry": {"coordinates":[-5.407609,50.192036],"type":"Point"}
}