{
  "type": "Feature",
  "properties": {
    "iso:country":"GB",
    "sg:address":"Harbour Road",
    "sg:city":"Seaton",
    "sg:classifiers":[
        {
            "category":"Professional",
            "type":"Services"
        }
    ],
    "sg:phone":"+44 1297 22453",
    "sg:postcode":"EX12 2NA",
    "sg:province":"Devon",
    "sg:tags":[
        "auctioneer"
    ],
    "wof:name":"Lyme Bay Auction Galleries",
    "wof:placetype":"venue"
},
  "geometry": {"coordinates":[-3.0652339458,50.7043685913],"type":"Point"}
}