{
  "type": "Feature",
  "properties": {
    "iso:country":"GB",
    "sg:address":"6 Larch Close, Kings Worthy",
    "sg:city":"Winchester",
    "sg:classifiers":[
        {
            "category":"Professional",
            "subcategory":"Business Services",
            "type":"Services"
        }
    ],
    "sg:postcode":"SO23 7NE",
    "sg:province":"Hampshire",
    "sg:tags":[
        "import",
        "export",
        "agent"
    ],
    "wof:name":"Gm Financial Services Ltd.",
    "wof:placetype":"venue"
},
  "geometry": {"coordinates":[-1.305912,51.103195],"type":"Point"}
}