{
  "type": "Feature",
  "properties": {
    "addr:full":"Chester Market Hall, Princess Street Chester Cheshire CH1 2HH",
    "addr:postcode":"ch1 2hh",
    "addr:street":"Princess Street",
    "iso:country":"GB",
    "sg:address":"Chester Market Hall, Princess Street",
    "sg:city":"Chester",
    "sg:classifiers":[
        {
            "category":"Manufacturing",
            "subcategory":"Food",
            "type":"Manufacturing & Wholesale Goods"
        }
    ],
    "sg:phone":"+44 1244 325458",
    "sg:postcode":"CH1 2HH",
    "sg:province":"Cheshire",
    "sg:tags":[
        "cheese",
        "producer"
    ],
    "wof:name":"The Cheese Wedge",
    "wof:placetype":"venue"
},
  "geometry": {"coordinates":[-2.894369,53.188129],"type":"Point"}
}