{
  "type": "Feature",
  "properties": {
    "addr:full":"Unit 2a, 168 Breck Rd, Everton Liverpool Merseyside L5 6PX",
    "addr:housenumber":"unit 2a 168",
    "addr:postcode":"l5 6px",
    "addr:street":"Breck Rd",
    "iso:country":"GB",
    "sg:address":"Unit 2a, 168 Breck Rd, Everton",
    "sg:city":"Liverpool",
    "sg:classifiers":[
        {
            "category":"Home & Garden",
            "subcategory":"Home Furnishings",
            "type":"Retail Goods"
        },
        {
            "category":"Manufacturing",
            "subcategory":"Textiles",
            "type":"Manufacturing & Wholesale Goods"
        }
    ],
    "sg:phone":"+44 151 260 1162",
    "sg:postcode":"L5 6PX",
    "sg:province":"Merseyside",
    "sg:tags":[
        "made-up",
        "bedding",
        "bed"
    ],
    "wof:name":"Home Sweet Homes",
    "wof:placetype":"venue"
},
  "geometry": {"coordinates":[-2.9593930244,53.4227027893],"type":"Point"}
}