{
  "type": "Feature",
  "properties": {
    "addr:full":"43 Stephenson Way, Formby Business Park, Formby Liverpool Lancashire L37 8EG",
    "addr:housenumber":"43",
    "addr:postcode":"l37 8eg",
    "addr:street":"Stephenson Way",
    "iso:country":"GB",
    "sg:address":"43 Stephenson Way, Formby Business Park, Formby",
    "sg:city":"Liverpool",
    "sg:classifiers":[
        {
            "category":"Professional",
            "subcategory":"Engineering",
            "type":"Services"
        }
    ],
    "sg:phone":"+44 1704 872143",
    "sg:postcode":"L37 8EG",
    "sg:province":"Lancashire",
    "sg:tags":[
        "engineer"
    ],
    "wof:name":"Asco Precision Engineering Ltd.",
    "wof:placetype":"venue"
},
  "geometry": {"coordinates":[-3.041312,53.554176],"type":"Point"}
}