{
  "type": "Feature",
  "properties": {
    "addr:full":"Unit 7, Burfield Park Industrial Estate Hailsham East Sussex BN27 3JL",
    "addr:housenumber":"unit 7",
    "addr:postcode":"bn27 3jl",
    "addr:street":"Burfield Park Industrial",
    "iso:country":"GB",
    "sg:address":"Unit 7, Burfield Park Industrial Estate",
    "sg:city":"Hailsham",
    "sg:classifiers":[
        {
            "category":"Wholesale",
            "subcategory":"Scrap",
            "type":"Manufacturing & Wholesale Goods"
        }
    ],
    "sg:phone":"+44 1323 440366",
    "sg:postcode":"BN27 3JL",
    "sg:province":"East Sussex",
    "sg:tags":[
        "breaker",
        "dismantlers"
    ],
    "wof:name":"Burfield Breakers Vauxhall & Austin Rover Specialists",
    "wof:placetype":"venue"
},
  "geometry": {"coordinates":[0.25652,50.865383],"type":"Point"}
}