{
  "type": "Feature",
  "properties": {
    "iso:country":"GB",
    "sg:address":"70 Eyre Place",
    "sg:city":"Edinburgh",
    "sg:classifiers":[
        {
            "category":"Community Center",
            "subcategory":"Youth",
            "type":"Public Place"
        }
    ],
    "sg:phone":"+44 131 476 4506",
    "sg:postcode":"EH3 5EJ",
    "sg:province":"City of Edinburgh",
    "sg:tags":[
        "organisation",
        "centre"
    ],
    "wof:name":"Scotland Yard Adventure Centre Ltd",
    "wof:placetype":"venue"
},
  "geometry": {"coordinates":[-3.197331,55.962101],"type":"Point"}
}