{
  "type": "Feature",
  "properties": {
    "addr:full":"2nd Floor, Baird House London Greater London EC1N 8UW",
    "addr:housenumber":"2nd floor baird house",
    "addr:postcode":"ec1n 8uw",
    "iso:country":"GB",
    "sg:address":"2nd Floor, Baird House",
    "sg:city":"London",
    "sg:classifiers":[
        {
            "category":"Professional",
            "subcategory":"Lawyer & Legal Services",
            "type":"Services"
        }
    ],
    "sg:phone":"+44 20 7404 4604",
    "sg:postcode":"EC1N 8UW",
    "sg:province":"Greater London",
    "sg:tags":[
        "solicitor"
    ],
    "wof:name":"Interlace 4 D Ltd.",
    "wof:placetype":"venue"
},
  "geometry": {"coordinates":[-0.10802,51.520821],"type":"Point"}
}