{
  "type": "Feature",
  "properties": {
    "addr:full":"23 Royston Road, Firswood Manchester Cheshire M16 0EU",
    "addr:housenumber":"23",
    "addr:postcode":"m16 0eu",
    "addr:street":"Royston Road",
    "iso:country":"GB",
    "sg:address":"23 Royston Road, Firswood",
    "sg:city":"Manchester",
    "sg:classifiers":[
        {
            "category":"Freight",
            "type":"Transportation"
        }
    ],
    "sg:postcode":"M16 0EU",
    "sg:province":"Cheshire",
    "sg:tags":[
        "haulage",
        "road"
    ],
    "wof:name":"Norman Jones Haulage",
    "wof:placetype":"venue"
},
  "geometry": {"coordinates":[-2.2786080837,53.4530639648],"type":"Point"}
}