{
  "type": "Feature",
  "properties": {
    "addr:full":"2 Broomhill Ave, Broomhill Glasgow Glasgow City G11 7AE",
    "addr:housenumber":"2",
    "addr:postcode":"g11 7ae",
    "addr:street":"Broomhill Ave",
    "iso:country":"GB",
    "sg:address":"2 Broomhill Ave, Broomhill",
    "sg:city":"Glasgow",
    "sg:classifiers":[
        {
            "category":"Building & Trades",
            "subcategory":"Construction",
            "type":"Services"
        }
    ],
    "sg:postcode":"G11 7AE",
    "sg:province":"Glasgow City",
    "sg:tags":[
        "joiner",
        "carpenter"
    ],
    "wof:name":"B F Joiners & Builders",
    "wof:placetype":"venue"
},
  "geometry": {"coordinates":[-4.323961,55.872929],"type":"Point"}
}