{
  "type": "Feature",
  "properties": {
    "iso:country":"GB",
    "sg:address":"77 West Street",
    "sg:city":"Tavistock",
    "sg:classifiers":[
        {
            "category":"Shopping",
            "subcategory":"Stationery & Office Supplies",
            "type":"Retail Goods"
        },
        {
            "category":"Shopping",
            "subcategory":"Gifts & Souvenirs",
            "type":"Retail Goods"
        }
    ],
    "sg:phone":"+44 1822 610800",
    "sg:postcode":"PL19 8AQ",
    "sg:province":"Devon",
    "sg:tags":[
        "shop",
        "poster",
        "card"
    ],
    "wof:name":"The Shambles",
    "wof:placetype":"venue"
},
  "geometry": {"coordinates":[-4.147224,50.549625],"type":"Point"}
}