{
  "type": "Feature",
  "properties": {
    "iso:country":"GB",
    "sg:address":"Twickenham Trad Est, Rugby Rd",
    "sg:city":"Twickenham",
    "sg:classifiers":[
        {
            "category":"Food & Beverages",
            "subcategory":"Groceries & Convenience Stores",
            "type":"Retail Goods"
        }
    ],
    "sg:phone":"+44 20 8892 2612",
    "sg:postcode":"TW1 1DS",
    "sg:province":"Greater London",
    "wof:name":"Friendly Water Ltd",
    "wof:placetype":"venue"
},
  "geometry": {"coordinates":[-0.338681,51.456169],"type":"Point"}
}