{
  "type": "Feature",
  "properties": {
    "iso:country":"GB",
    "sg:address":"C/o Homebase, Alban Park, Hatfield Road",
    "sg:city":"St Albans",
    "sg:classifiers":[
        {
            "category":"Home & Garden",
            "subcategory":"Furniture",
            "type":"Retail Goods"
        }
    ],
    "sg:phone":"+44 1727 837452",
    "sg:postcode":"AL4 0JJ",
    "sg:province":"Hertfordshire",
    "wof:name":"Laura Ashley",
    "wof:placetype":"venue"
},
  "geometry": {"coordinates":[-0.27967,51.7505],"type":"Point"}
}