{
  "type": "Feature",
  "properties": {
    "addr:full":"223 Canongate Edinburgh City of Edinburgh EH8 8BJ",
    "addr:housenumber":"223",
    "addr:postcode":"eh8 8bj",
    "addr:street":"Canongate",
    "iso:country":"GB",
    "sg:address":"223 Canongate",
    "sg:city":"Edinburgh",
    "sg:classifiers":[
        {
            "category":"Fast Food",
            "type":"Food & Drink"
        },
        {
            "category":"Food & Beverages",
            "subcategory":"Supermarket",
            "type":"Retail Goods"
        }
    ],
    "sg:phone":"+44 131 556 6077",
    "sg:postcode":"EH8 8BJ",
    "sg:province":"City of Edinburgh",
    "sg:tags":[
        "frozen",
        "away",
        "take"
    ],
    "wof:name":"Fresco",
    "wof:placetype":"venue"
},
  "geometry": {"coordinates":[-3.1821360588,55.9509963989],"type":"Point"}
}