{
  "type": "Feature",
  "properties": {
    "iso:country":"GB",
    "sg:address":"Unit 5 Ome Indust Est, Cargo Fleet Rd",
    "sg:city":"Middlesbrough",
    "sg:classifiers":[
        {
            "category":"Professional",
            "subcategory":"Engineering",
            "type":"Services"
        }
    ],
    "sg:phone":"+44 1642 219998",
    "sg:postcode":"TS3 6AF",
    "sg:province":"North Yorkshire",
    "wof:name":"Nu-Town Fabrications",
    "wof:placetype":"venue"
},
  "geometry": {"coordinates":[-1.21255,54.575359],"type":"Point"}
}