{
  "type": "Feature",
  "properties": {
    "addr:full":"Hadleigh Rd Sunderland Tyne and Wear SR4 8DG",
    "addr:postcode":"sr4 8dg",
    "addr:street":"Hadleigh Rd",
    "iso:country":"GB",
    "sg:address":"Hadleigh Rd",
    "sg:city":"Sunderland",
    "sg:classifiers":[
        {
            "category":"Government",
            "subcategory":"Post Office",
            "type":"Public Place"
        }
    ],
    "sg:phone":"+44 191 551 8133",
    "sg:postcode":"SR4 8DG",
    "sg:province":"Tyne and Wear",
    "sg:tags":[
        "messenger",
        "courier"
    ],
    "wof:name":"Ascend Courier Services",
    "wof:placetype":"venue"
},
  "geometry": {"coordinates":[-1.42542,54.901329],"type":"Point"}
}