{
  "type": "Feature",
  "properties": {
    "addr:full":"479 Herringthorpe Valley Road Rotherham South Yorkshire S65 3AD",
    "addr:housenumber":"479",
    "addr:postcode":"s65 3ad",
    "addr:street":"Herringthorpe Valley Road",
    "iso:country":"GB",
    "sg:address":"479 Herringthorpe Valley Road",
    "sg:city":"Rotherham",
    "sg:classifiers":[
        {
            "category":"Insurance",
            "subcategory":"Insurance Agent",
            "type":"Services"
        }
    ],
    "sg:phone":"+44 1709 378828",
    "sg:postcode":"S65 3AD",
    "sg:province":"South Yorkshire",
    "wof:name":"Page Insurance",
    "wof:placetype":"venue"
},
  "geometry": {"coordinates":[-1.322571,53.419865],"type":"Point"}
}