{
  "type": "Feature",
  "properties": {
    "iso:country":"GB",
    "sg:address":"Orchard View, Martley Road, Lower Broadheath",
    "sg:city":"Worcester",
    "sg:classifiers":[
        {
            "category":"Shopping",
            "subcategory":"Pharmacy",
            "type":"Retail Goods"
        }
    ],
    "sg:phone":"+44 1905 640133",
    "sg:postcode":"WR2 6QG",
    "sg:province":"Worcestershire",
    "sg:tags":[
        "medicine",
        "therapy"
    ],
    "wof:name":"Graham J Roberts",
    "wof:placetype":"venue"
},
  "geometry": {"coordinates":[-2.278581,52.212254],"type":"Point"}
}