{
  "type": "Feature",
  "properties": {
    "addr:full":"16 Meadowfield, Penwortham Preston Lancashire PR1 9ER",
    "addr:housenumber":"16;penwortham",
    "addr:postcode":"pr1 9er",
    "addr:street":"Meadowfield;Preston",
    "iso:country":"GB",
    "sg:address":"16 Meadowfield, Penwortham",
    "sg:city":"Preston",
    "sg:classifiers":[
        {
            "category":"Building & Trades",
            "subcategory":"Construction",
            "type":"Services"
        }
    ],
    "sg:phone":"+44 1772 750067",
    "sg:postcode":"PR1 9ER",
    "sg:province":"Lancashire",
    "sg:tags":[
        "decorator",
        "painter"
    ],
    "wof:name":"Neil C Gardner",
    "wof:placetype":"venue"
},
  "geometry": {"coordinates":[-2.7057290077,53.7579612732],"type":"Point"}
}