{
  "type": "Feature",
  "properties": {
    "addr:full":"51 Dawley Road Telford Shropshire TF1 2HW",
    "addr:housenumber":"51",
    "addr:postcode":"tf1 2hw",
    "addr:street":"Dawley Road",
    "iso:country":"GB",
    "sg:address":"51 Dawley Road",
    "sg:city":"Telford",
    "sg:classifiers":[
        {
            "category":"Autos & Motor Vehicles",
            "subcategory":"Auto Supplies",
            "type":"Retail Goods"
        }
    ],
    "sg:phone":"+44 1952 246507",
    "sg:postcode":"TF1 2HW",
    "sg:province":"Shropshire",
    "sg:tags":[
        "component"
    ],
    "wof:name":"T & M Parts & Tools",
    "wof:placetype":"venue"
},
  "geometry": {"coordinates":[-2.5044178963,52.694770813],"type":"Point"}
}