{
  "type": "Feature",
  "properties": {
    "addr:full":"Hole Farm, Old Hall Green Ware Hertfordshire SG11 1DZ",
    "addr:postcode":"sg11 1dz",
    "iso:country":"GB",
    "sg:address":"Hole Farm, Old Hall Green",
    "sg:city":"Ware",
    "sg:classifiers":[
        {
            "category":"Farming",
            "subcategory":"Livestock Farm",
            "type":"Manufacturing & Wholesale Goods"
        }
    ],
    "sg:phone":"+44 1920 821645",
    "sg:postcode":"SG11 1DZ",
    "sg:province":"Hertfordshire",
    "sg:tags":[
        "others"
    ],
    "wof:name":"A C Johnson",
    "wof:placetype":"venue"
},
  "geometry": {"coordinates":[0.0123439999,51.8924942017],"type":"Point"}
}