{
  "type": "Feature",
  "properties": {
    "addr:full":"18 Nethermains Rd Glasgow East Dunbartonshire G62 6NL",
    "addr:housenumber":"18",
    "addr:postcode":"g62 6nl",
    "addr:street":"Nethermains Rd",
    "iso:country":"GB",
    "sg:address":"18 Nethermains Rd",
    "sg:city":"Glasgow",
    "sg:classifiers":[
        {
            "category":"Place Of Worship",
            "type":"Public Place"
        }
    ],
    "sg:phone":"+44 141 956 3052",
    "sg:postcode":"G62 6NL",
    "sg:province":"East Dunbartonshire",
    "wof:name":"United Free Church of Scotland",
    "wof:placetype":"venue"
},
  "geometry": {"coordinates":[-4.3196959496,55.9346694946],"type":"Point"}
}