{
  "type": "Feature",
  "properties": {
    "addr:full":"Windsmore, Taylors Lane, Holmes Preston Lancashire PR4 6JE",
    "addr:postcode":"pr4 6je",
    "addr:street":"Taylors Lane",
    "iso:country":"GB",
    "sg:address":"Windsmore, Taylors Lane, Holmes",
    "sg:city":"Preston",
    "sg:classifiers":[
        {
            "category":"Food & Beverages",
            "subcategory":"Farmers Market",
            "type":"Retail Goods"
        }
    ],
    "sg:postcode":"PR4 6JE",
    "sg:province":"Lancashire",
    "sg:tags":[
        "gardener"
    ],
    "wof:name":"Conway Nurseries",
    "wof:placetype":"venue"
},
  "geometry": {"coordinates":[-2.8528900146,53.6668510437],"type":"Point"}
}