{
  "type": "Feature",
  "properties": {
    "iso:country":"GB",
    "sg:address":"150 Birkenhead Rd",
    "sg:city":"Wallasey",
    "sg:classifiers":[
        {
            "category":"Home & Garden",
            "subcategory":"Furniture",
            "type":"Retail Goods"
        }
    ],
    "sg:phone":"+44 151 630 7300",
    "sg:postcode":"L44 7JN",
    "sg:province":"Merseyside",
    "wof:name":"Ellis And Company Ltd",
    "wof:placetype":"venue"
},
  "geometry": {"coordinates":[-3.020914,53.405266],"type":"Point"}
}