{
  "type": "Feature",
  "properties": {
    "addr:full":"6 Alexandra Rd St Austell Cornwall PL25 4QP",
    "addr:housenumber":"6",
    "addr:postcode":"pl25 4qp",
    "addr:street":"Alexandra Rd",
    "iso:country":"GB",
    "sg:address":"6 Alexandra Rd",
    "sg:city":"St Austell",
    "sg:classifiers":[
        {
            "category":"Shopping",
            "subcategory":"Florist",
            "type":"Retail Goods"
        }
    ],
    "sg:phone":"+44 1726 65333",
    "sg:postcode":"PL25 4QP",
    "sg:province":"Cornwall",
    "wof:name":"Petal Florist",
    "wof:placetype":"venue"
},
  "geometry": {"coordinates":[-4.78618,50.337852],"type":"Point"}
}