{
  "type": "Feature",
  "properties": {
    "iso:country":"GB",
    "sg:address":"Muchall Gro, Muchall Rd",
    "sg:city":"Wolverhampton",
    "sg:classifiers":[
        {
            "category":"Government",
            "subcategory":"Office",
            "type":"Public Place"
        }
    ],
    "sg:phone":"+44 1902 558078",
    "sg:postcode":"WV4 5SE",
    "sg:province":"Staffordshire",
    "sg:tags":[
        "local"
    ],
    "wof:name":"Wolverhampton Borough Council",
    "wof:placetype":"venue"
},
  "geometry": {"coordinates":[-2.146784,52.562103],"type":"Point"}
}