{
  "type": "Feature",
  "properties": {
    "addr:full":"25 English Street Dumfries Dumfries and Galloway DG1 2BU",
    "addr:housenumber":"25",
    "addr:postcode":"dg1 2bu",
    "addr:street":"English Street",
    "iso:country":"GB",
    "sg:address":"25 English Street",
    "sg:city":"Dumfries",
    "sg:classifiers":[
        {
            "category":"Food & Beverages",
            "subcategory":"Bakery",
            "type":"Retail Goods"
        }
    ],
    "sg:phone":"+44 1387 253148",
    "sg:postcode":"DG1 2BU",
    "sg:province":"Dumfries and Galloway",
    "sg:tags":[
        "baker"
    ],
    "wof:name":"J R Birkett & Sons",
    "wof:placetype":"venue"
},
  "geometry": {"coordinates":[-3.609364,55.068623],"type":"Point"}
}