{
  "type": "Feature",
  "properties": {
    "iso:country":"GB",
    "sg:address":"15 Spittal St",
    "sg:city":"Marlow",
    "sg:classifiers":[
        {
            "category":"Bars & Pubs",
            "type":"Food & Drink"
        }
    ],
    "sg:phone":"+44 1628 473649",
    "sg:postcode":"SL7 3HJ",
    "sg:province":"Berkshire",
    "sg:tags":[
        "pubs",
        "inn"
    ],
    "wof:name":"Carpenters Arms",
    "wof:placetype":"venue"
},
  "geometry": {"coordinates":[-0.776901,51.572453],"type":"Point"}
}