{
  "type": "Feature",
  "properties": {
    "addr:full":"101 Wellingborough Road Rushden Bedfordshire NN10 9YL",
    "addr:housenumber":"101",
    "addr:postcode":"nn10 9yl",
    "addr:street":"Wellingborough Road",
    "iso:country":"GB",
    "sg:address":"101 Wellingborough Road",
    "sg:city":"Rushden",
    "sg:classifiers":[
        {
            "category":"Organizations",
            "subcategory":"Community Association",
            "type":"Services"
        }
    ],
    "sg:phone":"+44 1933 411400",
    "sg:postcode":"NN10 9YL",
    "sg:province":"Bedfordshire",
    "sg:tags":[
        "co-operatives",
        "society",
        "housing",
        "trust"
    ],
    "wof:name":"Rockingham Forest Housing Association Ltd.",
    "wof:placetype":"venue"
},
  "geometry": {"coordinates":[-0.6025099754,52.290397644],"type":"Point"}
}