{
  "type": "Feature",
  "properties": {
    "addr:full":"6 Lichfield Road Stafford Staffordshire ST17 4JY",
    "addr:housenumber":"6",
    "addr:postcode":"st17 4jy",
    "addr:street":"Lichfield Road",
    "iso:country":"GB",
    "sg:address":"6 Lichfield Road",
    "sg:city":"Stafford",
    "sg:classifiers":[
        {
            "category":"Professional",
            "subcategory":"Lawyer & Legal Services",
            "type":"Services"
        }
    ],
    "sg:phone":"+44 1785 251382",
    "sg:postcode":"ST17 4JY",
    "sg:province":"Staffordshire",
    "sg:tags":[
        "solicitor"
    ],
    "wof:name":"Lloyd & Robinson",
    "wof:placetype":"venue"
},
  "geometry": {"coordinates":[-2.1146249771,52.8038482666],"type":"Point"}
}