{
  "type": "Feature",
  "properties": {
    "addr:full":"40 Bowling Green Lane London Greater London EC1R 0NE",
    "addr:housenumber":"40",
    "addr:postcode":"ec1r 0ne",
    "addr:street":"Bowling Green Lane",
    "iso:country":"GB",
    "sg:address":"40 Bowling Green Lane",
    "sg:city":"London",
    "sg:classifiers":[
        {
            "category":"Communications",
            "type":"Services"
        }
    ],
    "sg:phone":"+44 20 7638 2344",
    "sg:postcode":"EC1R 0NE",
    "sg:province":"Greater London",
    "sg:tags":[
        "telecommunication"
    ],
    "wof:name":"National Telecable Ltd.",
    "wof:placetype":"venue"
},
  "geometry": {"coordinates":[-0.107357,51.524773],"type":"Point"}
}