{
  "type": "Feature",
  "properties": {
    "iso:country":"GB",
    "sg:address":"Mitre Street",
    "sg:city":"Bolton",
    "sg:classifiers":[
        {
            "category":"Education",
            "subcategory":"School",
            "type":"Public Place"
        },
        {
            "category":"Government",
            "subcategory":"Office",
            "type":"Public Place"
        }
    ],
    "sg:phone":"+44 1204 301175",
    "sg:postcode":"BL1 6QJ",
    "sg:province":"Lancashire",
    "sg:tags":[
        "local",
        "authority"
    ],
    "wof:name":"Holy Infants Primary School",
    "wof:placetype":"venue"
},
  "geometry": {"coordinates":[-2.436349,53.602501],"type":"Point"}
}