{
  "type": "Feature",
  "properties": {
    "iso:country":"GB",
    "sg:address":"56 Park Road",
    "sg:city":"Bristol",
    "sg:classifiers":[
        {
            "category":"Building & Trades",
            "subcategory":"Construction",
            "type":"Services"
        }
    ],
    "sg:postcode":"BS16 1AY",
    "sg:province":"City of Bristol",
    "sg:tags":[
        "builder"
    ],
    "wof:name":"Badger Construction",
    "wof:placetype":"venue"
},
  "geometry": {"coordinates":[-2.553174,51.483192],"type":"Point"}
}