{
  "type": "Feature",
  "properties": {
    "iso:country":"GB",
    "sg:address":"Wickworth St",
    "sg:city":"Nelson",
    "sg:classifiers":[
        {
            "category":"Arena",
            "subcategory":"Sports Club",
            "type":"Entertainment"
        }
    ],
    "sg:postcode":"BB9 0LQ",
    "sg:province":"Lancashire",
    "wof:name":"Laycock,Keith,",
    "wof:placetype":"venue"
},
  "geometry": {"coordinates":[-2.198759079,53.8316383362],"type":"Point"}
}