{
  "type": "Feature",
  "properties": {
    "iso:country":"GB",
    "sg:address":"80 Woodville Rd",
    "sg:city":"Cardiff",
    "sg:classifiers":[
        {
            "category":"Community Center",
            "subcategory":"Youth",
            "type":"Public Place"
        }
    ],
    "sg:phone":"+44 29 2022 6668",
    "sg:postcode":"CF2 4ED",
    "sg:province":"Cardiff",
    "sg:tags":[
        "organisation",
        "centre"
    ],
    "wof:name":"The Boys Brigade",
    "wof:placetype":"venue"
},
  "geometry": {"coordinates":[-3.177926,51.492783],"type":"Point"}
}