{
  "type": "Feature",
  "properties": {
    "addr:full":"1 Lodore Gro, Acklam Middlesbrough North Yorkshire TS5 8PA",
    "addr:housenumber":"1",
    "addr:postcode":"ts5 8pa",
    "addr:street":"Lodore Gro",
    "iso:country":"GB",
    "sg:address":"1 Lodore Gro, Acklam",
    "sg:city":"Middlesbrough",
    "sg:classifiers":[
        {
            "category":"Retail",
            "subcategory":"Auto Repair",
            "type":"Services"
        }
    ],
    "sg:postcode":"TS5 8PA",
    "sg:province":"North Yorkshire",
    "sg:tags":[
        "modification",
        "garage"
    ],
    "wof:name":"Linthorpe Mobile Mechanic",
    "wof:placetype":"venue"
},
  "geometry": {"coordinates":[-1.258544,54.544884],"type":"Point"}
}