{
  "type": "Feature",
  "properties": {
    "addr:full":"76 Gladstone Street Bedford Bedfordshire MK41 7RT",
    "addr:housenumber":"76",
    "addr:postcode":"mk41 7rt",
    "addr:street":"Gladstone Street",
    "iso:country":"GB",
    "sg:address":"76 Gladstone Street",
    "sg:city":"Bedford",
    "sg:classifiers":[
        {
            "category":"Building & Trades",
            "subcategory":"Construction",
            "type":"Services"
        }
    ],
    "sg:phone":"+44 1234 271899",
    "sg:postcode":"MK41 7RT",
    "sg:province":"Bedfordshire",
    "sg:tags":[
        "decorator",
        "painter"
    ],
    "wof:name":"Goldthorp Ltd.",
    "wof:placetype":"venue"
},
  "geometry": {"coordinates":[-0.472574,52.145653],"type":"Point"}
}