{
  "type": "Feature",
  "properties": {
    "addr:full":"Derby Road Burton-on-trent Derbyshire DE13 0BH",
    "addr:postcode":"de13 0bh",
    "addr:street":"Derby Road",
    "iso:country":"GB",
    "sg:address":"Derby Road",
    "sg:city":"Burton-on-trent",
    "sg:classifiers":[
        {
            "category":"Wholesale",
            "subcategory":"Auto Parts",
            "type":"Manufacturing & Wholesale Goods"
        }
    ],
    "sg:phone":"+44 870 205 6515",
    "sg:postcode":"DE13 0BH",
    "sg:province":"Derbyshire",
    "sg:tags":[
        "wholesaler",
        "tyre"
    ],
    "wof:name":"C P K Auto Products Ltd.",
    "wof:placetype":"venue"
},
  "geometry": {"coordinates":[-1.613441,52.833363],"type":"Point"}
}