{
  "type": "Feature",
  "properties": {
    "addr:full":"C/o 1 Yelneh Villas, Newlands St Helens Ryde Isle of Wight PO33 1TU",
    "addr:housenumber":"1",
    "addr:postcode":"po33 1tu",
    "addr:street":"C / O;Villas Newlands",
    "iso:country":"GB",
    "sg:address":"C/o 1 Yelneh Villas, Newlands St Helens",
    "sg:city":"Ryde",
    "sg:classifiers":[
        {
            "category":"Organizations",
            "subcategory":"Membership Organization",
            "type":"Services"
        }
    ],
    "sg:postcode":"PO33 1TU",
    "sg:province":"Isle of Wight",
    "sg:tags":[
        "club"
    ],
    "wof:name":"St Helens Village Hall Association Ltd",
    "wof:placetype":"venue"
},
  "geometry": {"coordinates":[-1.1686660051,50.7275657654],"type":"Point"}
}