{
  "type": "Feature",
  "properties": {
    "iso:country":"GB",
    "sg:address":"Templeborough Works, Sheffield Road, Tinsley",
    "sg:city":"Sheffield",
    "sg:classifiers":[
        {
            "category":"Autos & Motor Vehicles",
            "subcategory":"Automobile Sales",
            "type":"Retail Goods"
        }
    ],
    "sg:phone":"+44 114 244 4831",
    "sg:postcode":"S9 1RT",
    "sg:province":"South Yorkshire",
    "sg:tags":[
        "commercial"
    ],
    "wof:name":"N W T Sales & Service",
    "wof:placetype":"venue"
},
  "geometry": {"coordinates":[-1.398739,53.413036],"type":"Point"}
}