{
  "type": "Feature",
  "properties": {
    "addr:full":"Mill Hill, The Ridgeway Mill Hill Greater London NW7 1AA",
    "addr:postcode":"nw7 1aa",
    "addr:street":"The Ridgeway;Hill",
    "iso:country":"GB",
    "sg:address":"Mill Hill, The Ridgeway",
    "sg:city":"Mill Hill",
    "sg:classifiers":[
        {
            "category":"Professional",
            "subcategory":"Research",
            "type":"Services"
        }
    ],
    "sg:phone":"+44 20 8959 3666",
    "sg:postcode":"NW7 1AA",
    "sg:province":"Greater London",
    "sg:tags":[
        "organisation"
    ],
    "wof:name":"Medical Research Council",
    "wof:placetype":"venue"
},
  "geometry": {"coordinates":[-0.219750002,51.6175994873],"type":"Point"}
}