{
  "type": "Feature",
  "properties": {
    "iso:country":"GB",
    "sg:address":"204-206 Hewlett Rd",
    "sg:city":"Cheltenham",
    "sg:classifiers":[
        {
            "category":"Autos & Motor Vehicles",
            "subcategory":"Automobile Sales",
            "type":"Retail Goods"
        }
    ],
    "sg:postcode":"GL52 6UQ",
    "sg:province":"Gloucestershire",
    "sg:tags":[
        "car"
    ],
    "wof:name":"Cheltenham Trade Centre",
    "wof:placetype":"venue"
},
  "geometry": {"coordinates":[-2.0558969975,51.9012413025],"type":"Point"}
}