{
  "type": "Feature",
  "properties": {
    "iso:country":"GB",
    "sg:address":"38 Benjamin Road",
    "sg:city":"High Wycombe",
    "sg:classifiers":[
        {
            "category":"Building & Trades",
            "subcategory":"Construction",
            "type":"Services"
        }
    ],
    "sg:postcode":"HP13 6SR",
    "sg:province":"Buckinghamshire",
    "sg:tags":[
        "decorator",
        "painter"
    ],
    "wof:name":"M Little",
    "wof:placetype":"venue"
},
  "geometry": {"coordinates":[-0.749251,51.634129],"type":"Point"}
}