{
  "type": "Feature",
  "properties": {
    "addr:full":"Cadwell Farm Hitchin Bedfordshire SG5 3UA",
    "addr:postcode":"sg5 3ua",
    "iso:country":"GB",
    "sg:address":"Cadwell Farm",
    "sg:city":"Hitchin",
    "sg:classifiers":[
        {
            "category":"Farming",
            "subcategory":"Livestock Farm",
            "type":"Manufacturing & Wholesale Goods"
        }
    ],
    "sg:postcode":"SG5 3UA",
    "sg:province":"Bedfordshire",
    "sg:tags":[
        "others"
    ],
    "wof:name":"Wallace Farms Ltd.",
    "wof:placetype":"venue"
},
  "geometry": {"coordinates":[-0.2844080031,51.9524345398],"type":"Point"}
}