{
  "type": "Feature",
  "properties": {
    "iso:country":"GB",
    "sg:address":"124 Cleveland Road",
    "sg:city":"Sunderland",
    "sg:classifiers":[
        {
            "category":"Professional",
            "subcategory":"Management & Consulting",
            "type":"Services"
        }
    ],
    "sg:phone":"+44 191 528 8484",
    "sg:postcode":"SR4 7JT",
    "sg:province":"Tyne and Wear",
    "sg:tags":[
        "consultant",
        "business"
    ],
    "wof:name":"Paul Sturgess Consultancy Services",
    "wof:placetype":"venue"
},
  "geometry": {"coordinates":[-1.407052,54.898678],"type":"Point"}
}