{
  "type": "Feature",
  "properties": {
    "addr:full":"Moorside Farm, Brandesburton Driffield East Riding of Yorkshire YO25 8EP",
    "addr:postcode":"yo25 8ep",
    "addr:street":"Brandesburton",
    "iso:country":"GB",
    "sg:address":"Moorside Farm, Brandesburton",
    "sg:city":"Driffield",
    "sg:classifiers":[
        {
            "category":"Home & Garden",
            "subcategory":"Garden Supply",
            "type":"Retail Goods"
        },
        {
            "category":"Farming",
            "subcategory":"Farm",
            "type":"Manufacturing & Wholesale Goods"
        }
    ],
    "sg:phone":"+44 1262 488218",
    "sg:postcode":"YO25 8EP",
    "sg:province":"East Riding of Yorkshire",
    "sg:tags":[
        "mixed",
        "bulb",
        "crop",
        "grower"
    ],
    "wof:name":"W E A & P Copeland",
    "wof:placetype":"venue"
},
  "geometry": {"coordinates":[-0.302119,53.910999],"type":"Point"}
}