{
  "type": "Feature",
  "properties": {
    "addr:full":"18 High Street Crediton Devon EX17 3AH",
    "addr:housenumber":"18",
    "addr:postcode":"ex17 3ah",
    "addr:street":"High Street",
    "iso:country":"GB",
    "sg:address":"18 High Street",
    "sg:city":"Crediton",
    "sg:classifiers":[
        {
            "category":"Shopping",
            "subcategory":"Pharmacy",
            "type":"Retail Goods"
        }
    ],
    "sg:phone":"+44 1363 773030",
    "sg:postcode":"EX17 3AH",
    "sg:province":"Devon",
    "sg:tags":[
        "pharmacist",
        "chemist"
    ],
    "wof:name":"Edwards Chemist",
    "wof:placetype":"venue"
},
  "geometry": {"coordinates":[-3.658707,50.790497],"type":"Point"}
}