{
  "type": "Feature",
  "properties": {
    "addr:full":"163 Butt Lane, Allesley Coventry West Midlands CV5 9FD",
    "addr:housenumber":"163",
    "addr:postcode":"cv5 9fd",
    "addr:street":"Butt Lane",
    "iso:country":"GB",
    "sg:address":"163 Butt Lane, Allesley",
    "sg:city":"Coventry",
    "sg:classifiers":[
        {
            "category":"Professional",
            "subcategory":"Detective & Security Services",
            "type":"Services"
        },
        {
            "category":"Building & Trades",
            "subcategory":"Construction",
            "type":"Services"
        }
    ],
    "sg:phone":"+44 24 7640 2645",
    "sg:postcode":"CV5 9FD",
    "sg:province":"West Midlands",
    "sg:tags":[
        "builder",
        "locksmith"
    ],
    "wof:name":"Allin Building Maintenance",
    "wof:placetype":"venue"
},
  "geometry": {"coordinates":[-1.566735,52.429768],"type":"Point"}
}