{
  "type": "Feature",
  "properties": {
    "iso:country":"GB",
    "sg:address":"20-22 Gransden Av, London Fields",
    "sg:city":"Hackney",
    "sg:classifiers":[
        {
            "category":"Real Estate",
            "subcategory":"Architect",
            "type":"Services"
        }
    ],
    "sg:phone":"+44 20 8533 9630",
    "sg:postcode":"E8 3QA",
    "sg:province":"Greater London",
    "wof:name":"Architecture For The Arts",
    "wof:placetype":"venue"
},
  "geometry": {"coordinates":[-0.057016,51.541138],"type":"Point"}
}