{
  "type": "Feature",
  "properties": {
    "iso:country":"GB",
    "sg:address":"61 Rumbridge Street, Totton",
    "sg:city":"Southampton",
    "sg:classifiers":[
        {
            "category":"Health Services",
            "subcategory":"Dentist",
            "type":"Services"
        }
    ],
    "sg:phone":"+44 23 8086 8833",
    "sg:postcode":"SO40 9DT",
    "sg:province":"Hampshire",
    "wof:name":"Bridgeways Dental Practice",
    "wof:placetype":"venue"
},
  "geometry": {"coordinates":[-1.488105,50.914665],"type":"Point"}
}