{
  "type": "Feature",
  "properties": {
    "iso:country":"GB",
    "sg:address":"29 Hill Street",
    "sg:city":"Wisbech",
    "sg:classifiers":[
        {
            "category":"Organizations",
            "subcategory":"Community Association",
            "type":"Services"
        },
        {
            "category":"Organizations",
            "subcategory":"Membership Organization",
            "type":"Services"
        }
    ],
    "sg:phone":"+44 1945 583746",
    "sg:postcode":"PE13 1BD",
    "sg:province":"Cambridgeshire",
    "sg:tags":[
        "club",
        "social"
    ],
    "wof:name":"Wisbech Working Men's Conservative Club",
    "wof:placetype":"venue"
},
  "geometry": {"coordinates":[0.1605080068,52.6659355164],"type":"Point"}
}