{
  "type": "Feature",
  "properties": {
    "addr:full":"Unit 52b Symondscliffe Way Caldicot Monmouthshire NP26 5PW",
    "addr:housenumber":"unit 52b",
    "addr:postcode":"np26 5pw",
    "addr:street":"Symondscliffe Way",
    "iso:country":"GB",
    "sg:address":"Unit 52b Symondscliffe Way",
    "sg:city":"Caldicot",
    "sg:classifiers":[
        {
            "category":"Professional",
            "subcategory":"Engineering",
            "type":"Services"
        }
    ],
    "sg:phone":"+44 1291 437020",
    "sg:postcode":"NP26 5PW",
    "sg:province":"Monmouthshire",
    "sg:tags":[
        "contractor",
        "electrical",
        "engineer"
    ],
    "wof:name":"C I E International Ltd.",
    "wof:placetype":"venue"
},
  "geometry": {"coordinates":[-2.733109,51.589176],"type":"Point"}
}