{
  "type": "Feature",
  "properties": {
    "iso:country":"GB",
    "sg:address":"32 Campbell Street",
    "sg:city":"Hamilton",
    "sg:classifiers":[
        {
            "category":"Real Estate",
            "subcategory":"Surveying",
            "type":"Services"
        }
    ],
    "sg:phone":"+44 1698 891400",
    "sg:postcode":"ML3 6AS",
    "sg:province":"South Lanarkshire",
    "sg:tags":[
        "surveyor",
        "valuer"
    ],
    "wof:name":"Whyte & Barrie",
    "wof:placetype":"venue"
},
  "geometry": {"coordinates":[-4.035419,55.776543],"type":"Point"}
}