{
  "type": "Feature",
  "properties": {
    "addr:full":"3 Sedgefield Close, Totton Southampton Hampshire SO40 8GP",
    "addr:housenumber":"3",
    "addr:postcode":"so40 8gp",
    "addr:street":"Sedgefield Close",
    "iso:country":"GB",
    "sg:address":"3 Sedgefield Close, Totton",
    "sg:city":"Southampton",
    "sg:classifiers":[
        {
            "category":"Shopping",
            "subcategory":"Pharmacy",
            "type":"Retail Goods"
        }
    ],
    "sg:postcode":"SO40 8GP",
    "sg:province":"Hampshire",
    "sg:tags":[
        "medicine",
        "therapy"
    ],
    "wof:name":"Harmony Indian Head Massage & Stress Counselling",
    "wof:placetype":"venue"
},
  "geometry": {"coordinates":[-1.510871,50.921463],"type":"Point"}
}