{
  "type": "Feature",
  "properties": {
    "addr:full":"Holly House Farm, Flagg Buxton Derbyshire SK17 9QT",
    "addr:housenumber":"flagg",
    "addr:postcode":"sk17 9qt",
    "iso:country":"GB",
    "sg:address":"Holly House Farm, Flagg",
    "sg:city":"Buxton",
    "sg:classifiers":[
        {
            "category":"Farming",
            "subcategory":"Farm",
            "type":"Manufacturing & Wholesale Goods"
        }
    ],
    "sg:phone":"+44 1298 85393",
    "sg:postcode":"SK17 9QT",
    "sg:province":"Derbyshire",
    "sg:tags":[
        "mixed",
        "crop"
    ],
    "wof:name":"J H & S J Mycock",
    "wof:placetype":"venue"
},
  "geometry": {"coordinates":[-1.797518,53.212219],"type":"Point"}
}