{
  "type": "Feature",
  "properties": {
    "addr:full":"25 Manor Close Ely Cambridgeshire CB6 2JB",
    "addr:housenumber":"25",
    "addr:postcode":"cb6 2jb",
    "addr:street":"Manor Close",
    "iso:country":"GB",
    "sg:address":"25 Manor Close",
    "sg:city":"Ely",
    "sg:classifiers":[
        {
            "category":"Building & Trades",
            "subcategory":"Construction",
            "type":"Services"
        }
    ],
    "sg:phone":"+44 1353 667216",
    "sg:postcode":"CB6 2JB",
    "sg:province":"Cambridgeshire",
    "sg:tags":[
        "builder"
    ],
    "wof:name":"R H Day",
    "wof:placetype":"venue"
},
  "geometry": {"coordinates":[0.2081699967,52.38804245],"type":"Point"}
}