{
  "type": "Feature",
  "properties": {
    "iso:country":"GB",
    "sg:address":"55 Bondgate Within",
    "sg:city":"Alnwick",
    "sg:classifiers":[
        {
            "category":"Food & Beverages",
            "subcategory":"Bakery",
            "type":"Retail Goods"
        }
    ],
    "sg:phone":"+44 1665 602684",
    "sg:postcode":"NE66 1HZ",
    "sg:province":"Northumberland",
    "sg:tags":[
        "shop",
        "baker"
    ],
    "wof:name":"Trotters Family Bakers",
    "wof:placetype":"venue"
},
  "geometry": {"coordinates":[-1.706384,55.413559],"type":"Point"}
}