{
  "type": "Feature",
  "properties": {
    "addr:full":"98 Queensgate Centre Peterborough Cambridgeshire PE1 1XJ",
    "addr:housenumber":"98",
    "addr:postcode":"pe1 1xj",
    "addr:street":"Queensgate Centre Peterborough",
    "iso:country":"GB",
    "sg:address":"98 Queensgate Centre",
    "sg:city":"Peterborough",
    "sg:classifiers":[
        {
            "category":"Communications",
            "type":"Services"
        }
    ],
    "sg:phone":"+44 1733 460460",
    "sg:postcode":"PE1 1XJ",
    "sg:province":"Cambridgeshire",
    "sg:tags":[
        "broadcasting"
    ],
    "wof:name":"Mid Anglia Radio Plc",
    "wof:placetype":"venue"
},
  "geometry": {"coordinates":[-0.2465150058,52.5738983154],"type":"Point"}
}