{
  "type": "Feature",
  "properties": {
    "iso:country":"GB",
    "sg:address":"Childeritch Hall Drive, Little Warley",
    "sg:city":"Brentwood",
    "sg:classifiers":[
        {
            "category":"Manufacturing",
            "subcategory":"Petroleum Products",
            "type":"Manufacturing & Wholesale Goods"
        }
    ],
    "sg:phone":"+44 1277 810009",
    "sg:postcode":"CM13 3HD",
    "sg:province":"Essex",
    "sg:tags":[
        "double",
        "glazing"
    ],
    "wof:name":"Weatherseal Window Systems",
    "wof:placetype":"venue"
},
  "geometry": {"coordinates":[0.31526,51.590801],"type":"Point"}
}