{
  "type": "Feature",
  "properties": {
    "addr:full":"Hill Street Elgin Moray IV30 1AL",
    "addr:postcode":"iv30 1al",
    "addr:street":"Hill Street",
    "iso:country":"GB",
    "sg:address":"Hill Street",
    "sg:city":"Elgin",
    "sg:classifiers":[
        {
            "category":"Taxi",
            "type":"Transportation"
        },
        {
            "category":"Military Area",
            "subcategory":"Air Force Base",
            "type":"Public Place"
        }
    ],
    "sg:phone":"+44 1343 550440",
    "sg:postcode":"IV30 1AL",
    "sg:province":"Moray",
    "sg:tags":[
        "mini",
        "hire",
        "private",
        "cab"
    ],
    "wof:name":"Ladyhill Taxis",
    "wof:placetype":"venue"
},
  "geometry": {"coordinates":[-3.324478,57.648315],"type":"Point"}
}