{
  "type": "Feature",
  "properties": {
    "addr:full":"Llanwnnen, Lampeteren Lampeter Carmarthenshire SA40 9SP",
    "addr:postcode":"sa40 9sp",
    "addr:street":"Carmarthenshire",
    "iso:country":"GB",
    "sg:address":"Llanwnnen, Lampeteren",
    "sg:city":"Lampeter",
    "sg:classifiers":[
        {
            "category":"Manufacturing",
            "subcategory":"Building Materials",
            "type":"Manufacturing & Wholesale Goods"
        }
    ],
    "sg:phone":"+44 1570 480381",
    "sg:postcode":"SA40 9SP",
    "sg:province":"Carmarthenshire",
    "sg:tags":[
        "concrete",
        "product"
    ],
    "wof:name":"Teifi Concrete Products Ltd.",
    "wof:placetype":"venue"
},
  "geometry": {"coordinates":[-4.1822690964,52.0781898499],"type":"Point"}
}