{
  "type": "Feature",
  "properties": {
    "iso:country":"GB",
    "sg:address":"Unit 10, Adam Smith Street",
    "sg:city":"Grimsby",
    "sg:classifiers":[
        {
            "category":"Autos & Motor Vehicles",
            "subcategory":"Auto Supplies",
            "type":"Retail Goods"
        }
    ],
    "sg:postcode":"DN31 1SJ",
    "sg:province":"Lincolnshire",
    "sg:tags":[
        "car",
        "audio"
    ],
    "wof:name":"Motorsound",
    "wof:placetype":"venue"
},
  "geometry": {"coordinates":[-0.091524,53.573826],"type":"Point"}
}