{
  "type": "Feature",
  "properties": {
    "addr:full":"Wheatacre Road, Clifton Estate Nottingham Nottinghamshire NG11 8LE",
    "addr:postcode":"ng11 8le",
    "addr:street":"Wheatacre Road;Estate",
    "iso:country":"GB",
    "sg:address":"Wheatacre Road, Clifton Estate",
    "sg:city":"Nottingham",
    "sg:classifiers":[
        {
            "category":"Wholesale",
            "subcategory":"Home Furnishings",
            "type":"Manufacturing & Wholesale Goods"
        }
    ],
    "sg:phone":"+44 115 984 5050",
    "sg:postcode":"NG11 8LE",
    "sg:province":"Nottinghamshire",
    "sg:tags":[
        "wsale",
        "rug",
        "carpet"
    ],
    "wof:name":"Decor Style Floors Ltd.",
    "wof:placetype":"venue"
},
  "geometry": {"coordinates":[-1.185204,52.908642],"type":"Point"}
}