{
  "type": "Feature",
  "properties": {
    "addr:full":"Cranmer Gardens Leeds North Yorkshire LS17 5LA",
    "addr:postcode":"ls17 5la",
    "addr:street":"Cranmer Gardens Leeds",
    "iso:country":"GB",
    "sg:address":"Cranmer Gardens",
    "sg:city":"Leeds",
    "sg:classifiers":[
        {
            "category":"Social Services",
            "subcategory":"Retirement Home",
            "type":"Services"
        }
    ],
    "sg:phone":"+44 113 268 6800",
    "sg:postcode":"LS17 5LA",
    "sg:province":"North Yorkshire",
    "sg:tags":[
        "residential",
        "care"
    ],
    "wof:name":"Moorhaven",
    "wof:placetype":"venue"
},
  "geometry": {"coordinates":[-1.5535529852,53.8489341736],"type":"Point"}
}