{
  "type": "Feature",
  "properties": {
    "iso:country":"GB",
    "sg:address":"3 Brook Lane",
    "sg:city":"Chester",
    "sg:classifiers":[
        {
            "category":"Fast Food",
            "type":"Food & Drink"
        }
    ],
    "sg:postcode":"CH2 2EB",
    "sg:province":"Cheshire",
    "sg:tags":[
        "away",
        "take"
    ],
    "wof:name":"Newton Park Sandwich Bar",
    "wof:placetype":"venue"
},
  "geometry": {"coordinates":[-2.892948,53.200912],"type":"Point"}
}