{
  "type": "Feature",
  "properties": {
    "iso:country":"GB",
    "sg:address":"Pole Farm, Lochgoilhead",
    "sg:city":"Cairndow",
    "sg:classifiers":[
        {
            "category":"Farming",
            "subcategory":"Livestock Farm",
            "type":"Manufacturing & Wholesale Goods"
        }
    ],
    "sg:phone":"+44 1301 703221",
    "sg:postcode":"PA24 8AN",
    "sg:province":"Argyll and Bute",
    "sg:tags":[
        "others"
    ],
    "wof:name":"JAMES & DAVID JACKSON",
    "wof:placetype":"venue"
},
  "geometry": {"coordinates":[-4.9026989937,56.1724662781],"type":"Point"}
}