{
  "type": "Feature",
  "properties": {
    "iso:country":"GB",
    "sg:address":"25 Windmill Street",
    "sg:city":"Peterhead",
    "sg:classifiers":[
        {
            "category":"Farming",
            "subcategory":"Nursery",
            "type":"Manufacturing & Wholesale Goods"
        },
        {
            "category":"Social Services",
            "subcategory":"Child Care",
            "type":"Services"
        }
    ],
    "sg:phone":"+44 1779 474156",
    "sg:postcode":"AB42 1LH",
    "sg:province":"Aberdeenshire",
    "sg:tags":[
        "creche"
    ],
    "wof:name":"Jack & Jill Nursery",
    "wof:placetype":"venue"
},
  "geometry": {"coordinates":[-1.781299,57.508724],"type":"Point"}
}