{
  "type": "Feature",
  "properties": {
    "iso:country":"GB",
    "sg:address":"C/o 9 Stanford Way, Walton",
    "sg:city":"Chesterfield",
    "sg:classifiers":[
        {
            "category":"Organizations",
            "subcategory":"Professional Association",
            "type":"Services"
        }
    ],
    "sg:postcode":"S42 7NH",
    "sg:province":"Derbyshire",
    "sg:tags":[
        "organisation",
        "motoring"
    ],
    "wof:name":"Chesterfield Group of Advanced Motorists",
    "wof:placetype":"venue"
},
  "geometry": {"coordinates":[-1.4636039734,53.224571228],"type":"Point"}
}