{
  "type": "Feature",
  "properties": {
    "addr:full":"Saltcoats Road Gullane East Lothian EH31 2AQ",
    "addr:postcode":"eh31 2aq",
    "addr:street":"Saltcoats Road",
    "iso:country":"GB",
    "sg:address":"Saltcoats Road",
    "sg:city":"Gullane",
    "sg:classifiers":[
        {
            "category":"Building & Trades",
            "subcategory":"Construction",
            "type":"Services"
        }
    ],
    "sg:phone":"+44 1620 843180",
    "sg:postcode":"EH31 2AQ",
    "sg:province":"East Lothian",
    "sg:tags":[
        "joiner",
        "carpenter"
    ],
    "wof:name":"J & R Hay",
    "wof:placetype":"venue"
},
  "geometry": {"coordinates":[-2.8323540688,56.0341415405],"type":"Point"}
}