{
  "type": "Feature",
  "properties": {
    "addr:full":"3 Elm La, Sheffield Lane Top Sheffield South Yorkshire S5 7TR",
    "addr:housenumber":"3",
    "addr:postcode":"s5 7tr",
    "addr:street":"Elm La Sheffield Lane",
    "iso:country":"GB",
    "sg:address":"3 Elm La, Sheffield Lane Top",
    "sg:city":"Sheffield",
    "sg:classifiers":[
        {
            "category":"Shopping",
            "subcategory":"Florist",
            "type":"Retail Goods"
        }
    ],
    "sg:phone":"+44 114 246 0150",
    "sg:postcode":"S5 7TR",
    "sg:province":"South Yorkshire",
    "wof:name":"Elm Lane",
    "wof:placetype":"venue"
},
  "geometry": {"coordinates":[-1.4551359415,53.4219818115],"type":"Point"}
}