{
  "type": "Feature",
  "properties": {
    "addr:full":"8-10 Mansion House Place London Greater London EC4N 8LB",
    "addr:housenumber":"8-10",
    "addr:postcode":"ec4n 8lb",
    "addr:street":"Mansion House Place",
    "iso:country":"GB",
    "sg:address":"8-10 Mansion House Place",
    "sg:city":"London",
    "sg:classifiers":[
        {
            "category":"Professional",
            "subcategory":"Lawyer & Legal Services",
            "type":"Services"
        }
    ],
    "sg:phone":"+44 20 7375 9770",
    "sg:postcode":"EC4N 8LB",
    "sg:province":"Greater London",
    "wof:name":"Bingham Dana",
    "wof:placetype":"venue"
},
  "geometry": {"coordinates":[-0.0892100036,51.512588501],"type":"Point"}
}