{
  "type": "Feature",
  "properties": {
    "iso:country":"GB",
    "sg:address":"6 Chandos Gardens",
    "sg:city":"Leeds",
    "sg:classifiers":[
        {
            "category":"Sports & Exercise",
            "subcategory":"Sports Center",
            "type":"Entertainment"
        }
    ],
    "sg:phone":"+44 113 237 1799",
    "sg:postcode":"LS8 1LW",
    "sg:province":"West Yorkshire",
    "sg:tags":[
        "shop",
        "good"
    ],
    "wof:name":"Roundhay Sports",
    "wof:placetype":"venue"
},
  "geometry": {"coordinates":[-1.520645,53.834641],"type":"Point"}
}