{
  "type": "Feature",
  "properties": {
    "addr:full":"51 Pier Avenue Clacton-on-sea Essex CO15 1QQ",
    "addr:housenumber":"51",
    "addr:postcode":"co15 1qq",
    "addr:street":"Pier Avenue",
    "iso:country":"GB",
    "sg:address":"51 Pier Avenue",
    "sg:city":"Clacton-on-sea",
    "sg:classifiers":[
        {
            "category":"Shopping",
            "subcategory":"Books",
            "type":"Retail Goods"
        }
    ],
    "sg:phone":"+44 1255 423295",
    "sg:postcode":"CO15 1QQ",
    "sg:province":"Essex",
    "sg:tags":[
        "bookseller"
    ],
    "wof:name":"W H Smith",
    "wof:placetype":"venue"
},
  "geometry": {"coordinates":[1.15209,51.788929],"type":"Point"}
}