{
  "type": "Feature",
  "properties": {
    "addr:full":"456-458 Bury Old Road, Prestwich Manchester Greater Manchester M25 1NL",
    "addr:housenumber":"456-458",
    "addr:postcode":"m25 1nl",
    "addr:street":"Bury Old Road",
    "iso:country":"GB",
    "sg:address":"456-458 Bury Old Road, Prestwich",
    "sg:city":"Manchester",
    "sg:classifiers":[
        {
            "category":"Retail",
            "subcategory":"Auto Rental",
            "type":"Services"
        }
    ],
    "sg:phone":"+44 161 798 6868",
    "sg:postcode":"M25 1NL",
    "sg:province":"Greater Manchester",
    "sg:tags":[
        "car"
    ],
    "wof:name":"Thrifty Car Rental",
    "wof:placetype":"venue"
},
  "geometry": {"coordinates":[-2.2753899097,53.5374641418],"type":"Point"}
}