{
  "type": "Feature",
  "properties": {
    "iso:country":"GB",
    "sg:address":"160 Hadleigh Road",
    "sg:city":"Ipswich",
    "sg:classifiers":[
        {
            "category":"Building & Trades",
            "subcategory":"Construction",
            "type":"Services"
        }
    ],
    "sg:phone":"+44 1473 255931",
    "sg:postcode":"IP2 0HJ",
    "sg:province":"Suffolk",
    "sg:tags":[
        "builder"
    ],
    "wof:name":"A M E C Construction Ltd.",
    "wof:placetype":"venue"
},
  "geometry": {"coordinates":[1.1237800121,52.057849884],"type":"Point"}
}