{
  "type": "Feature",
  "properties": {
    "iso:country":"GB",
    "sg:address":"8 St Anns Square",
    "sg:city":"Manchester",
    "sg:classifiers":[
        {
            "category":"Shopping",
            "subcategory":"Shoes",
            "type":"Retail Goods"
        }
    ],
    "sg:postcode":"M2 7HW",
    "sg:province":"Greater Manchester",
    "sg:tags":[
        "shop"
    ],
    "wof:name":"Danielle Footwear",
    "wof:placetype":"venue"
},
  "geometry": {"coordinates":[-2.245642,53.482197],"type":"Point"}
}