{
  "type": "Feature",
  "properties": {
    "iso:country":"GB",
    "sg:address":"8b Paikes Street",
    "sg:city":"Alnwick",
    "sg:classifiers":[
        {
            "category":"Food & Beverages",
            "subcategory":"Meat & Fish",
            "type":"Retail Goods"
        }
    ],
    "sg:phone":"+44 1665 510441",
    "sg:postcode":"NE66 1HX",
    "sg:province":"Northumberland",
    "sg:tags":[
        "butcher"
    ],
    "wof:name":"J H Hunter (Butchers) Ltd.",
    "wof:placetype":"venue"
},
  "geometry": {"coordinates":[-1.70755,55.413857],"type":"Point"}
}