{
  "type": "Feature",
  "properties": {
    "addr:full":"3 King Street Halifax West Yorkshire HX1 1SR",
    "addr:housenumber":"3",
    "addr:postcode":"hx1 1sr",
    "addr:street":"King Street",
    "iso:country":"GB",
    "sg:address":"3 King Street",
    "sg:city":"Halifax",
    "sg:classifiers":[
        {
            "category":"Autos & Motor Vehicles",
            "subcategory":"Automobile Sales",
            "type":"Retail Goods"
        }
    ],
    "sg:phone":"+44 1422 321111",
    "sg:postcode":"HX1 1SR",
    "sg:province":"West Yorkshire",
    "sg:tags":[
        "car"
    ],
    "wof:name":"Hepworth Honda",
    "wof:placetype":"venue"
},
  "geometry": {"coordinates":[-1.854497,53.72403],"type":"Point"}
}