{
  "type": "Feature",
  "properties": {
    "addr:full":"3-7 Clayton House, Vaughan Road Harpenden Hertfordshire AL5 4EF",
    "addr:housenumber":"3-7",
    "addr:postcode":"al5 4ef",
    "addr:street":"Clayton House Vaughan Road",
    "iso:country":"GB",
    "sg:address":"3-7 Clayton House, Vaughan Road",
    "sg:city":"Harpenden",
    "sg:classifiers":[
        {
            "category":"Shopping",
            "subcategory":"Music",
            "type":"Retail Goods"
        }
    ],
    "sg:phone":"+44 1582 766794",
    "sg:postcode":"AL5 4EF",
    "sg:province":"Hertfordshire",
    "sg:tags":[
        "record",
        "tape",
        "cd"
    ],
    "wof:name":"Impulse Entertainment Ltd.",
    "wof:placetype":"venue"
},
  "geometry": {"coordinates":[-0.356559,51.816216],"type":"Point"}
}