{
  "type": "Feature",
  "properties": {
    "addr:full":"9 Towngate, Highburton Huddersfield South Yorkshire HD8 0QP",
    "addr:housenumber":"9",
    "addr:postcode":"hd8 0qp",
    "addr:street":"Towngate Highburton",
    "iso:country":"GB",
    "sg:address":"9 Towngate, Highburton",
    "sg:city":"Huddersfield",
    "sg:classifiers":[
        {
            "category":"Shopping",
            "subcategory":"News",
            "type":"Retail Goods"
        }
    ],
    "sg:postcode":"HD8 0QP",
    "sg:province":"South Yorkshire",
    "sg:tags":[
        "newsagent"
    ],
    "wof:name":"Highburton News",
    "wof:placetype":"venue"
},
  "geometry": {"coordinates":[-1.7110999823,53.6179084778],"type":"Point"}
}