{
  "type": "Feature",
  "properties": {
    "addr:full":"15 Argie Rd Leeds West Yorkshire LS4 2RD",
    "addr:housenumber":"15",
    "addr:postcode":"ls4 2rd",
    "addr:street":"Argie Rd",
    "iso:country":"GB",
    "sg:address":"15 Argie Rd",
    "sg:city":"Leeds",
    "sg:classifiers":[
        {
            "category":"Food & Beverages",
            "subcategory":"Bakery",
            "type":"Retail Goods"
        }
    ],
    "sg:phone":"+44 113 278 8151",
    "sg:postcode":"LS4 2RD",
    "sg:province":"West Yorkshire",
    "sg:tags":[
        "baker"
    ],
    "wof:name":"John & Fionas Kitchen",
    "wof:placetype":"venue"
},
  "geometry": {"coordinates":[-1.586226,53.808952],"type":"Point"}
}