{
  "type": "Feature",
  "properties": {
    "iso:country":"GB",
    "sg:address":"72 St John's Road",
    "sg:city":"Bootle",
    "sg:classifiers":[
        {
            "category":"Retail",
            "subcategory":"Storage",
            "type":"Services"
        }
    ],
    "sg:phone":"+44 151 922 0522",
    "sg:postcode":"L20 8BH",
    "sg:province":"Merseyside",
    "sg:tags":[
        "hire",
        "container"
    ],
    "wof:name":"Container Movements Ltd.",
    "wof:placetype":"venue"
},
  "geometry": {"coordinates":[-3.028051,53.474148],"type":"Point"}
}