{
  "type": "Feature",
  "properties": {
    "iso:country":"GB",
    "sg:address":"32c Ellesmere Court, Leechmere Industrial Estate",
    "sg:city":"Sunderland",
    "sg:classifiers":[
        {
            "category":"Professional",
            "subcategory":"Management & Consulting",
            "type":"Services"
        }
    ],
    "sg:phone":"+44 191 521 4316",
    "sg:postcode":"SR2 9UA",
    "sg:province":"Tyne and Wear",
    "sg:tags":[
        "consultant",
        "safety"
    ],
    "wof:name":"Calmtoken Ltd.",
    "wof:placetype":"venue"
},
  "geometry": {"coordinates":[-1.376641,54.881191],"type":"Point"}
}