{
  "type": "Feature",
  "properties": {
    "iso:country":"GB",
    "sg:address":"Sandwich Drive",
    "sg:city":"Macclesfield",
    "sg:classifiers":[
        {
            "category":"Place Of Worship",
            "type":"Public Place"
        }
    ],
    "sg:phone":"+44 1625 615195",
    "sg:postcode":"SK10 2UD",
    "sg:province":"Cheshire",
    "wof:name":"Tytherington Family Worship Church",
    "wof:placetype":"venue"
},
  "geometry": {"coordinates":[-2.134894,53.276459],"type":"Point"}
}