{
  "type": "Feature",
  "properties": {
    "addr:full":"73 Southwark Park Road, Bermondsey London Greater London SE16 3TY",
    "addr:housenumber":"73",
    "addr:postcode":"se16 3ty",
    "addr:street":"Southwark Park Road",
    "iso:country":"GB",
    "sg:address":"73 Southwark Park Road, Bermondsey",
    "sg:city":"London",
    "sg:classifiers":[
        {
            "category":"Building & Trades",
            "subcategory":"Landscaping Services",
            "type":"Services"
        }
    ],
    "sg:postcode":"SE16 3TY",
    "sg:province":"Greater London",
    "sg:tags":[
        "pond",
        "aquarium"
    ],
    "wof:name":"Dissington",
    "wof:placetype":"venue"
},
  "geometry": {"coordinates":[-0.098559998,51.5052642822],"type":"Point"}
}