{
  "type": "Feature",
  "properties": {
    "iso:country":"GB",
    "sg:address":"2 Kingsway House, Smithfield Street, Amesbury",
    "sg:city":"Salisbury",
    "sg:classifiers":[
        {
            "category":"Shopping",
            "subcategory":"Bicycles & Sporting Goods",
            "type":"Retail Goods"
        }
    ],
    "sg:phone":"+44 1980 622705",
    "sg:postcode":"SP4 7AL",
    "sg:province":"Hampshire",
    "sg:tags":[
        "cycle",
        "accessory"
    ],
    "wof:name":"Hills",
    "wof:placetype":"venue"
},
  "geometry": {"coordinates":[-1.77721,51.169476],"type":"Point"}
}