{
  "type": "Feature",
  "properties": {
    "iso:country":"GB",
    "sg:address":"31 Heathside",
    "sg:city":"Esher",
    "sg:classifiers":[
        {
            "category":"Travel",
            "subcategory":"Travel Agent",
            "type":"Entertainment"
        }
    ],
    "sg:phone":"+44 1869 337339",
    "sg:postcode":"KT10 9TD",
    "sg:province":"Surrey",
    "sg:tags":[
        "agency",
        "activity"
    ],
    "wof:name":"Alto Aragon Ltd",
    "wof:placetype":"venue"
},
  "geometry": {"coordinates":[-0.345156,51.373325],"type":"Point"}
}