{
  "type": "Feature",
  "properties": {
    "iso:country":"GB",
    "sg:address":"9 Commercial Road, Totton",
    "sg:city":"Southampton",
    "sg:classifiers":[
        {
            "category":"Food & Beverages",
            "subcategory":"Supermarket",
            "type":"Retail Goods"
        }
    ],
    "sg:phone":"+44 23 8086 8836",
    "sg:postcode":"SO40 3BX",
    "sg:province":"Hampshire",
    "wof:name":"T M Stores",
    "wof:placetype":"venue"
},
  "geometry": {"coordinates":[-1.488364,50.918999],"type":"Point"}
}