{
  "type": "Feature",
  "properties": {
    "iso:country":"GB",
    "sg:address":"Hartford Way, Sealand Indust Est",
    "sg:city":"Chester",
    "sg:classifiers":[
        {
            "category":"Home & Garden",
            "subcategory":"Building Materials",
            "type":"Retail Goods"
        }
    ],
    "sg:phone":"+44 1244 390174",
    "sg:postcode":"CH1 4NT",
    "sg:province":"Cheshire",
    "sg:tags":[
        "ready",
        "mixed",
        "concrete"
    ],
    "wof:name":"Readymix Concrete (North West) Ltd",
    "wof:placetype":"venue"
},
  "geometry": {"coordinates":[-2.910549,53.194675],"type":"Point"}
}