{
  "type": "Feature",
  "properties": {
    "iso:country":"GB",
    "sg:address":"19 Milnefield Avenue",
    "sg:city":"Elgin",
    "sg:classifiers":[
        {
            "category":"Real Estate",
            "subcategory":"Architect",
            "type":"Services"
        }
    ],
    "sg:phone":"+44 1343 543262",
    "sg:postcode":"IV30 6EJ",
    "sg:province":"Moray",
    "sg:tags":[
        "architectural"
    ],
    "wof:name":"Kenneth J King",
    "wof:placetype":"venue"
},
  "geometry": {"coordinates":[-3.299455,57.64064],"type":"Point"}
}