{
  "type": "Feature",
  "properties": {
    "addr:full":"485-489 Kingsland Rd Hackney Greater London E8 4AU",
    "addr:housenumber":"485-489",
    "addr:postcode":"e8 4au",
    "addr:street":"Kingsland Rd",
    "iso:country":"GB",
    "sg:address":"485-489 Kingsland Rd",
    "sg:city":"Hackney",
    "sg:classifiers":[
        {
            "category":"Health Services",
            "subcategory":"Nursing And Care Facility",
            "type":"Services"
        }
    ],
    "sg:phone":"+44 20 7503 1521",
    "sg:postcode":"E8 4AU",
    "sg:province":"Greater London",
    "sg:tags":[
        "agency"
    ],
    "wof:name":"Amazing Grace Nursing Agency",
    "wof:placetype":"venue"
},
  "geometry": {"coordinates":[-0.0762740001,51.5443191528],"type":"Point"}
}