{
  "type": "Feature",
  "properties": {
    "addr:full":"145 Four Acres Bristol City of Bristol BS13 8RA",
    "addr:housenumber":"145",
    "addr:postcode":"bs13 8ra",
    "addr:street":"Four Acres",
    "iso:country":"GB",
    "sg:address":"145 Four Acres",
    "sg:city":"Bristol",
    "sg:classifiers":[
        {
            "category":"Shopping",
            "subcategory":"Baby Store",
            "type":"Retail Goods"
        },
        {
            "category":"Government",
            "subcategory":"Post Office",
            "type":"Public Place"
        }
    ],
    "sg:phone":"+44 117 964 5196",
    "sg:postcode":"BS13 8RA",
    "sg:province":"City of Bristol",
    "sg:tags":[
        "childrens",
        "babywear"
    ],
    "wof:name":"Withywood Post Office",
    "wof:placetype":"venue"
},
  "geometry": {"coordinates":[-2.626313,51.406414],"type":"Point"}
}