{
  "type": "Feature",
  "properties": {
    "addr:full":"100-104 Upper Richmond Road London Greater London SW15 2SP",
    "addr:housenumber":"100-104",
    "addr:postcode":"sw15 2sp",
    "addr:street":"Upper Richmond Road",
    "iso:country":"GB",
    "sg:address":"100-104 Upper Richmond Road",
    "sg:city":"London",
    "sg:classifiers":[
        {
            "category":"Professional",
            "subcategory":"Employment Agencies",
            "type":"Services"
        }
    ],
    "sg:phone":"+44 20 8780 3000",
    "sg:postcode":"SW15 2SP",
    "sg:province":"Greater London",
    "sg:tags":[
        "consultant"
    ],
    "wof:name":"Petrosearch Ltd.",
    "wof:placetype":"venue"
},
  "geometry": {"coordinates":[-0.2109159976,51.4595832825],"type":"Point"}
}