{
  "type": "Feature",
  "properties": {
    "addr:full":"45 Briton Street Leicester Leicestershire LE3 0AB",
    "addr:housenumber":"45",
    "addr:postcode":"le3 0ab",
    "addr:street":"Briton Street",
    "iso:country":"GB",
    "sg:address":"45 Briton Street",
    "sg:city":"Leicester",
    "sg:classifiers":[
        {
            "category":"Shopping",
            "subcategory":"Clothing, Apparel, & Fashions",
            "type":"Retail Goods"
        }
    ],
    "sg:postcode":"LE3 0AB",
    "sg:province":"Leicestershire",
    "sg:tags":[
        "clothing"
    ],
    "wof:name":"Supreme Jeans & Casualwear Ltd.",
    "wof:placetype":"venue"
},
  "geometry": {"coordinates":[-1.147577,52.628017],"type":"Point"}
}