{
  "type": "Feature",
  "properties": {
    "iso:country":"GB",
    "sg:address":"Park Sidings, High Street",
    "sg:city":"Boston",
    "sg:classifiers":[
        {
            "category":"Retail",
            "subcategory":"Auto Repair",
            "type":"Services"
        }
    ],
    "sg:postcode":"PE21 8TJ",
    "sg:province":"Lincolnshire",
    "sg:tags":[
        "modification",
        "garage"
    ],
    "wof:name":"M A Barsley",
    "wof:placetype":"venue"
},
  "geometry": {"coordinates":[-0.029124,52.974697],"type":"Point"}
}