{
  "type": "Feature",
  "properties": {
    "addr:full":"1 Ambleside Road Lancing West Sussex BN15 9SE",
    "addr:housenumber":"1",
    "addr:postcode":"bn15 9se",
    "addr:street":"Ambleside Road",
    "iso:country":"GB",
    "sg:address":"1 Ambleside Road",
    "sg:city":"Lancing",
    "sg:classifiers":[
        {
            "category":"Building & Trades",
            "subcategory":"Construction",
            "type":"Services"
        }
    ],
    "sg:postcode":"BN15 9SE",
    "sg:province":"West Sussex",
    "sg:tags":[
        "decorator",
        "painter"
    ],
    "wof:name":"Cockrill & Braiden",
    "wof:placetype":"venue"
},
  "geometry": {"coordinates":[-0.339089,50.827969],"type":"Point"}
}