{
  "type": "Feature",
  "properties": {
    "addr:full":"33 Mendip Avenue Eastbourne East Sussex BN23 8HP",
    "addr:housenumber":"33",
    "addr:postcode":"bn23 8hp",
    "addr:street":"Mendip Avenue",
    "iso:country":"GB",
    "sg:address":"33 Mendip Avenue",
    "sg:city":"Eastbourne",
    "sg:classifiers":[
        {
            "category":"Professional",
            "subcategory":"Management & Consulting",
            "type":"Services"
        }
    ],
    "sg:phone":"+44 1323 740453",
    "sg:postcode":"BN23 8HP",
    "sg:province":"East Sussex",
    "sg:tags":[
        "consultant"
    ],
    "wof:name":"DNA Distribution",
    "wof:placetype":"venue"
},
  "geometry": {"coordinates":[0.305939,50.806446],"type":"Point"}
}