{
  "type": "Feature",
  "properties": {
    "iso:country":"GB",
    "sg:address":"Unit 501a Platts Eyot, Lower Sunbury Road",
    "sg:city":"Hampton",
    "sg:classifiers":[
        {
            "category":"Professional",
            "subcategory":"Art Services",
            "type":"Services"
        }
    ],
    "sg:phone":"+44 20 8941 8382",
    "sg:postcode":"TW12 2HG",
    "sg:province":"Greater London",
    "sg:tags":[
        "model",
        "maker"
    ],
    "wof:name":"Enterprise Models",
    "wof:placetype":"venue"
},
  "geometry": {"coordinates":[-0.376788,51.410049],"type":"Point"}
}