{
  "type": "Feature",
  "properties": {
    "iso:country":"GB",
    "sg:address":"Power House, Waterloo Road",
    "sg:city":"Shepton Mallet",
    "sg:classifiers":[
        {
            "category":"Recreation",
            "type":"Entertainment"
        }
    ],
    "sg:postcode":"BA4 5DH",
    "sg:province":"Somerset",
    "sg:tags":[
        "outdoor",
        "pursuit"
    ],
    "wof:name":"Dave Hockey",
    "wof:placetype":"venue"
},
  "geometry": {"coordinates":[-2.545408,51.195026],"type":"Point"}
}