{
  "type": "Feature",
  "properties": {
    "addr:full":"Bookham Lodge, Stoke D'abernon Cobham Surrey KT11 3QJ",
    "addr:postcode":"kt11 3qj",
    "iso:country":"GB",
    "sg:address":"Bookham Lodge, Stoke D'abernon",
    "sg:city":"Cobham",
    "sg:classifiers":[
        {
            "category":"Airport",
            "subcategory":"General Aviation",
            "type":"Transportation"
        }
    ],
    "sg:postcode":"KT11 3QJ",
    "sg:province":"Surrey",
    "wof:name":"Fitzroy Aviation Ltd",
    "wof:placetype":"venue"
},
  "geometry": {"coordinates":[-0.3822999895,51.3041000366],"type":"Point"}
}