{
  "type": "Feature",
  "properties": {
    "iso:country":"GB",
    "sg:address":"5 Duncan Mcintosh Rd, Wardpark North",
    "sg:city":"Glasgow",
    "sg:classifiers":[
        {
            "category":"Communications",
            "type":"Services"
        }
    ],
    "sg:phone":"+44 1236 738625",
    "sg:postcode":"G68 0HH",
    "sg:province":"East Dunbartonshire",
    "sg:tags":[
        "data",
        "network"
    ],
    "wof:name":"Effective Cabling Systems",
    "wof:placetype":"venue"
},
  "geometry": {"coordinates":[-3.9714500904,55.9740638733],"type":"Point"}
}