{
  "type": "Feature",
  "properties": {
    "addr:full":"Hartland House Church Street Reigate Surrey RH2 0AD",
    "addr:postcode":"rh2 0ad",
    "addr:street":"Church Street",
    "iso:country":"GB",
    "sg:address":"Hartland House Church Street",
    "sg:city":"Reigate",
    "sg:classifiers":[
        {
            "category":"Professional",
            "subcategory":"Detective & Security Services",
            "type":"Services"
        }
    ],
    "sg:postcode":"RH2 0AD",
    "sg:province":"Surrey",
    "wof:name":"White Lion Aviation Security Ltd",
    "wof:placetype":"venue"
},
  "geometry": {"coordinates":[-0.2020519972,51.2385444641],"type":"Point"}
}