{
  "type": "Feature",
  "properties": {
    "addr:full":"7 Woodlands Road Camberley Berkshire GU15 3LZ",
    "addr:housenumber":"7",
    "addr:postcode":"gu15 3lz",
    "addr:street":"Woodlands Road",
    "iso:country":"GB",
    "sg:address":"7 Woodlands Road",
    "sg:city":"Camberley",
    "sg:classifiers":[
        {
            "category":"Health Services",
            "subcategory":"Dentist",
            "type":"Services"
        }
    ],
    "sg:phone":"+44 1276 21463",
    "sg:postcode":"GU15 3LZ",
    "sg:province":"Berkshire",
    "wof:name":"Oatlands Dental Centre",
    "wof:placetype":"venue"
},
  "geometry": {"coordinates":[-0.7579669952,51.3346633911],"type":"Point"}
}