{
  "type": "Feature",
  "properties": {
    "addr:full":"92 -93 Queens Arcade Wolverhampton West Midlands WV1 3NL",
    "addr:housenumber":"-93;arcade",
    "addr:postcode":"wv1 3nl",
    "addr:street":"Queens",
    "iso:country":"GB",
    "sg:address":"92 -93 Queens Arcade",
    "sg:city":"Wolverhampton",
    "sg:classifiers":[
        {
            "category":"Shopping",
            "subcategory":"Luggage & Leather Goods",
            "type":"Retail Goods"
        }
    ],
    "sg:phone":"+44 1902 421803",
    "sg:postcode":"WV1 3NL",
    "sg:province":"West Midlands",
    "wof:name":"Hudsons Leather Shop",
    "wof:placetype":"venue"
},
  "geometry": {"coordinates":[-2.128844,52.585114],"type":"Point"}
}