{
  "type": "Feature",
  "properties": {
    "iso:country":"GB",
    "sg:address":"Market Hall, Morley",
    "sg:city":"Leeds",
    "sg:classifiers":[
        {
            "category":"Home & Garden",
            "subcategory":"Carpets & Floor Coverings",
            "type":"Retail Goods"
        }
    ],
    "sg:postcode":"LS27 8DS",
    "sg:province":"West Yorkshire",
    "sg:tags":[
        "carpets",
        "rug",
        "matting"
    ],
    "wof:name":"D L M Carpets",
    "wof:placetype":"venue"
},
  "geometry": {"coordinates":[-1.60034,53.745449],"type":"Point"}
}