{
  "type": "Feature",
  "properties": {
    "addr:full":"Cil Faen Farm, Felindre Swansea Swansea SA5 7NA",
    "addr:postcode":"sa5 7na",
    "iso:country":"GB",
    "sg:address":"Cil Faen Farm, Felindre",
    "sg:city":"Swansea",
    "sg:classifiers":[
        {
            "category":"Farming",
            "subcategory":"Livestock Farm",
            "type":"Manufacturing & Wholesale Goods"
        }
    ],
    "sg:phone":"+44 1792 772993",
    "sg:postcode":"SA5 7NA",
    "sg:province":"Swansea",
    "sg:tags":[
        "others"
    ],
    "wof:name":"A W G Stone",
    "wof:placetype":"venue"
},
  "geometry": {"coordinates":[-3.986621,51.706844],"type":"Point"}
}