{
  "type": "Feature",
  "properties": {
    "addr:full":"Chapel Farm Salisbury Dorset SP5 5QY",
    "addr:postcode":"sp5 5qy",
    "addr:street":"Dorset",
    "iso:country":"GB",
    "sg:address":"Chapel Farm",
    "sg:city":"Salisbury",
    "sg:classifiers":[
        {
            "category":"Farming",
            "subcategory":"Livestock Farm",
            "type":"Manufacturing & Wholesale Goods"
        }
    ],
    "sg:phone":"+44 1725 552202",
    "sg:postcode":"SP5 5QY",
    "sg:province":"Dorset",
    "sg:tags":[
        "stud"
    ],
    "wof:name":"D R C Elsworth",
    "wof:placetype":"venue"
},
  "geometry": {"coordinates":[-1.9607599974,50.9740409851],"type":"Point"}
}