{
  "type": "Feature",
  "properties": {
    "addr:full":"Stafford Road Cannock Staffordshire WS11 2AL",
    "addr:postcode":"ws11 2al",
    "addr:street":"Stafford Road",
    "iso:country":"GB",
    "sg:address":"Stafford Road",
    "sg:city":"Cannock",
    "sg:classifiers":[
        {
            "category":"Retail",
            "subcategory":"Auto Rental",
            "type":"Services"
        }
    ],
    "sg:phone":"+44 1543 469111",
    "sg:postcode":"WS11 2AL",
    "sg:province":"Staffordshire",
    "sg:tags":[
        "car",
        "hire",
        "truck"
    ],
    "wof:name":"Total Fleet Services Ltd.",
    "wof:placetype":"venue"
},
  "geometry": {"coordinates":[-2.031519,52.690456],"type":"Point"}
}