{
  "type": "Feature",
  "properties": {
    "iso:country":"GB",
    "sg:address":"Camelot Cottage, Woolston, North Cadbury",
    "sg:city":"Yeovil",
    "sg:classifiers":[
        {
            "category":"Shopping",
            "subcategory":"Hobbies, Toys, & Games",
            "type":"Retail Goods"
        },
        {
            "category":"Military Area",
            "subcategory":"Air Force Base",
            "type":"Public Place"
        }
    ],
    "sg:phone":"+44 1963 440025",
    "sg:postcode":"BA22 7BJ",
    "sg:province":"Dorset",
    "sg:tags":[
        "balloon",
        "toy",
        "novelty"
    ],
    "wof:name":"Balloonworks",
    "wof:placetype":"venue"
},
  "geometry": {"coordinates":[-2.522895,51.045921],"type":"Point"}
}