{
  "type": "Feature",
  "properties": {
    "addr:full":"77 Lower Blandford Road Broadstone Dorset BH18 8NS",
    "addr:housenumber":"77",
    "addr:postcode":"bh18 8ns",
    "addr:street":"Lower Blandford Road",
    "iso:country":"GB",
    "sg:address":"77 Lower Blandford Road",
    "sg:city":"Broadstone",
    "sg:classifiers":[
        {
            "category":"Building & Trades",
            "subcategory":"Construction",
            "type":"Services"
        }
    ],
    "sg:phone":"+44 1202 600987",
    "sg:postcode":"BH18 8NS",
    "sg:province":"Dorset",
    "sg:tags":[
        "builder"
    ],
    "wof:name":"Grade One Services",
    "wof:placetype":"venue"
},
  "geometry": {"coordinates":[-1.988451004,50.7538452148],"type":"Point"}
}