{
  "type": "Feature",
  "properties": {
    "addr:full":"1st Floor Transport Ho, Apsley St Ashford Kent TN23 1LF",
    "addr:postcode":"tn23 1lf",
    "addr:street":"Apsley St",
    "iso:country":"GB",
    "sg:address":"1st Floor Transport Ho, Apsley St",
    "sg:city":"Ashford",
    "sg:classifiers":[
        {
            "category":"Organizations",
            "subcategory":"Political Organization",
            "type":"Services"
        }
    ],
    "sg:phone":"+44 1233 663668",
    "sg:postcode":"TN23 1LF",
    "sg:province":"Kent",
    "sg:tags":[
        "party"
    ],
    "wof:name":"Mark Watts",
    "wof:placetype":"venue"
},
  "geometry": {"coordinates":[0.8760370016,51.1466331482],"type":"Point"}
}