{
  "type": "Feature",
  "properties": {
    "iso:country":"GB",
    "sg:address":"Spinglane",
    "sg:city":"Malvern",
    "sg:classifiers":[
        {
            "category":"Retail",
            "subcategory":"Auto Repair",
            "type":"Services"
        }
    ],
    "sg:phone":"+44 1684 562532",
    "sg:postcode":"WR14 1BU",
    "sg:province":"Herefordshire",
    "sg:tags":[
        "modification",
        "garage"
    ],
    "wof:name":"J & P Motors",
    "wof:placetype":"venue"
},
  "geometry": {"coordinates":[-2.3083701134,52.1282196045],"type":"Point"}
}