{
  "type": "Feature",
  "properties": {
    "iso:country":"GB",
    "sg:address":"4 The Precinct, Romiley",
    "sg:city":"Stockport",
    "sg:classifiers":[
        {
            "category":"Real Estate",
            "subcategory":"Real Estate Agent",
            "type":"Services"
        }
    ],
    "sg:phone":"+44 161 430 7519",
    "sg:postcode":"SK6 4EA",
    "sg:province":"Cheshire",
    "wof:name":"Edward Mellor",
    "wof:placetype":"venue"
},
  "geometry": {"coordinates":[-2.08596,53.413799],"type":"Point"}
}