{
  "type": "Feature",
  "properties": {
    "addr:full":"165 King St Ramsgate Kent CT11 8PN",
    "addr:housenumber":"165",
    "addr:postcode":"ct11 8pn",
    "addr:street":"King St",
    "iso:country":"GB",
    "sg:address":"165 King St",
    "sg:city":"Ramsgate",
    "sg:classifiers":[
        {
            "category":"Government",
            "subcategory":"Customs House",
            "type":"Public Place"
        }
    ],
    "sg:phone":"+44 1843 599900",
    "sg:postcode":"CT11 8PN",
    "sg:province":"Kent",
    "sg:tags":[
        "clearance"
    ],
    "wof:name":"Humpers",
    "wof:placetype":"venue"
},
  "geometry": {"coordinates":[1.423025012,51.3373794556],"type":"Point"}
}