{
  "type": "Feature",
  "properties": {
    "addr:full":"Station Road Clitheroe Lancashire BB7 2JT",
    "addr:postcode":"bb7 2jt",
    "addr:street":"Station Road",
    "iso:country":"GB",
    "sg:address":"Station Road",
    "sg:city":"Clitheroe",
    "sg:classifiers":[
        {
            "category":"Bars & Pubs",
            "type":"Food & Drink"
        },
        {
            "category":"Community Center",
            "subcategory":"Social",
            "type":"Public Place"
        }
    ],
    "sg:phone":"+44 1200 442280",
    "sg:postcode":"BB7 2JT",
    "sg:province":"Lancashire",
    "sg:tags":[
        "pubs",
        "house",
        "inn",
        "activity"
    ],
    "wof:name":"The Castle",
    "wof:placetype":"venue"
},
  "geometry": {"coordinates":[-2.3944509029,53.8724517822],"type":"Point"}
}