{
  "type": "Feature",
  "properties": {
    "addr:full":"89 Wash Lane Clacton-on-sea Essex CO15 1DA",
    "addr:housenumber":"89",
    "addr:postcode":"co15 1da",
    "addr:street":"Wash Lane",
    "iso:country":"GB",
    "sg:address":"89 Wash Lane",
    "sg:city":"Clacton-on-sea",
    "sg:classifiers":[
        {
            "category":"Health Services",
            "subcategory":"Doctor",
            "type":"Services"
        },
        {
            "category":"Health Services",
            "subcategory":"Clinic",
            "type":"Services"
        }
    ],
    "sg:phone":"+44 1255 222121",
    "sg:postcode":"CO15 1DA",
    "sg:province":"Essex",
    "sg:tags":[
        "nh",
        "practitioners"
    ],
    "wof:name":"St James Surgery",
    "wof:placetype":"venue"
},
  "geometry": {"coordinates":[1.14701,51.787544],"type":"Point"}
}