{
  "type": "Feature",
  "properties": {
    "iso:country":"GB",
    "sg:address":"18 Laburnum Gro",
    "sg:city":"Eastleigh",
    "sg:classifiers":[
        {
            "category":"Personal",
            "type":"Services"
        }
    ],
    "sg:phone":"+44 23 8061 5153",
    "sg:postcode":"SO50 9DJ",
    "sg:province":"Hampshire",
    "sg:tags":[
        "wedding"
    ],
    "wof:name":"Stuart's Caterers",
    "wof:placetype":"venue"
},
  "geometry": {"coordinates":[-1.357742,50.972366],"type":"Point"}
}