{
  "type": "Feature",
  "properties": {
    "addr:full":"29 Jubilee Close Pinner Greater London HA5 3TB",
    "addr:housenumber":"29",
    "addr:postcode":"ha5 3tb",
    "addr:street":"Jubilee Close",
    "iso:country":"GB",
    "sg:address":"29 Jubilee Close",
    "sg:city":"Pinner",
    "sg:classifiers":[
        {
            "category":"Travel",
            "subcategory":"Travel Agent",
            "type":"Entertainment"
        }
    ],
    "sg:phone":"+44 20 8866 4030",
    "sg:postcode":"HA5 3TB",
    "sg:province":"Greater London",
    "wof:name":"Planet Scan Travel",
    "wof:placetype":"venue"
},
  "geometry": {"coordinates":[-0.393798,51.601757],"type":"Point"}
}