{
  "type": "Feature",
  "properties": {
    "addr:full":"Sibco House Stoke-on-trent Staffordshire ST4 2ST",
    "addr:postcode":"staffordshire st4 2st",
    "iso:country":"GB",
    "sg:address":"Sibco House",
    "sg:city":"Stoke-on-trent",
    "sg:classifiers":[
        {
            "category":"Manufacturing",
            "subcategory":"Petroleum Products",
            "type":"Manufacturing & Wholesale Goods"
        }
    ],
    "sg:phone":"+44 1782 845999",
    "sg:postcode":"ST4 2ST",
    "sg:province":"Staffordshire",
    "sg:tags":[
        "double",
        "glazing"
    ],
    "wof:name":"Excel Conservatories & Windows Ltd.",
    "wof:placetype":"venue"
},
  "geometry": {"coordinates":[-2.1832289696,53.0128898621],"type":"Point"}
}