{
  "type": "Feature",
  "properties": {
    "addr:full":"1 Gateshead Close, Middlefield Industrial Estate Sandy Bedfordshire SG19 1RS",
    "addr:housenumber":"1",
    "addr:postcode":"sg19 1rs",
    "addr:street":"Gateshead Close;Industrial Estate",
    "iso:country":"GB",
    "sg:address":"1 Gateshead Close, Middlefield Industrial Estate",
    "sg:city":"Sandy",
    "sg:classifiers":[
        {
            "category":"Professional",
            "subcategory":"Business Services",
            "type":"Services"
        }
    ],
    "sg:phone":"+44 1767 680097",
    "sg:postcode":"SG19 1RS",
    "sg:province":"Bedfordshire",
    "sg:tags":[
        "information"
    ],
    "wof:name":"Business to Business Associates Ltd.",
    "wof:placetype":"venue"
},
  "geometry": {"coordinates":[-0.2866309881,52.1396713257],"type":"Point"}
}