{
  "type": "Feature",
  "properties": {
    "iso:country":"GB",
    "sg:address":"The Broyle, Ringmer",
    "sg:city":"Lewes",
    "sg:classifiers":[
        {
            "category":"Manufacturing",
            "subcategory":"Rubber & Plastics",
            "type":"Manufacturing & Wholesale Goods"
        }
    ],
    "sg:phone":"+44 1273 813456",
    "sg:postcode":"BN8 5NP",
    "sg:province":"East Sussex",
    "sg:tags":[
        "forming",
        "vacuum"
    ],
    "wof:name":"Advanced Mouldings",
    "wof:placetype":"venue"
},
  "geometry": {"coordinates":[0.0590789989,50.894077301],"type":"Point"}
}