{
  "type": "Feature",
  "properties": {
    "addr:full":"60-64 High Street Uttoxeter Derbyshire ST14 7JD",
    "addr:housenumber":"60-64",
    "addr:postcode":"st14 7jd",
    "addr:street":"High Street",
    "iso:country":"GB",
    "sg:address":"60-64 High Street",
    "sg:city":"Uttoxeter",
    "sg:classifiers":[
        {
            "category":"Recreation",
            "subcategory":"Fishing",
            "type":"Entertainment"
        }
    ],
    "sg:phone":"+44 1889 569787",
    "sg:postcode":"ST14 7JD",
    "sg:province":"Derbyshire",
    "sg:tags":[
        "angling"
    ],
    "wof:name":"J E Massey Ltd.",
    "wof:placetype":"venue"
},
  "geometry": {"coordinates":[-1.865738,52.900421],"type":"Point"}
}