{
  "type": "Feature",
  "properties": {
    "addr:full":"164 High Street Dumfries Dumfries and Galloway DG1 2BA",
    "addr:housenumber":"164",
    "addr:postcode":"dg1 2ba",
    "addr:street":"High Street",
    "iso:country":"GB",
    "sg:address":"164 High Street",
    "sg:city":"Dumfries",
    "sg:classifiers":[
        {
            "category":"Shopping",
            "subcategory":"Stationery & Office Supplies",
            "type":"Retail Goods"
        },
        {
            "category":"Wholesale",
            "subcategory":"Stationery",
            "type":"Manufacturing & Wholesale Goods"
        }
    ],
    "sg:phone":"+44 1387 253529",
    "sg:postcode":"DG1 2BA",
    "sg:province":"Dumfries and Galloway",
    "sg:tags":[
        "supplier"
    ],
    "wof:name":"Stationery Box Ltd",
    "wof:placetype":"venue"
},
  "geometry": {"coordinates":[-3.6113960743,55.0695457458],"type":"Point"}
}