{
  "type": "Feature",
  "properties": {
    "addr:full":"3 Cadman Court, Chartists Way Leeds West Yorkshire LS27 0RX",
    "addr:housenumber":"3",
    "addr:postcode":"ls27 0rx",
    "addr:street":"Cadman Court Chartists Way",
    "iso:country":"GB",
    "sg:address":"3 Cadman Court, Chartists Way",
    "sg:city":"Leeds",
    "sg:classifiers":[
        {
            "category":"Structure",
            "subcategory":"Warehouse",
            "type":"Public Place"
        }
    ],
    "sg:phone":"+44 113 252 7744",
    "sg:postcode":"LS27 0RX",
    "sg:province":"West Yorkshire",
    "wof:name":"Kaymar Finance Co. Ltd.",
    "wof:placetype":"venue"
},
  "geometry": {"coordinates":[-1.6025840044,53.7411003113],"type":"Point"}
}