{
  "type": "Feature",
  "properties": {
    "addr:full":"65 Station Road, Alsager Stoke-on-trent Cheshire ST7 2PD",
    "addr:housenumber":"65",
    "addr:postcode":"st7 2pd",
    "addr:street":"Station Road",
    "iso:country":"GB",
    "sg:address":"65 Station Road, Alsager",
    "sg:city":"Stoke-on-trent",
    "sg:classifiers":[
        {
            "category":"Professional",
            "subcategory":"Art Services",
            "type":"Services"
        }
    ],
    "sg:postcode":"ST7 2PD",
    "sg:province":"Cheshire",
    "sg:tags":[
        "carver",
        "sculptor"
    ],
    "wof:name":"A E Munslow",
    "wof:placetype":"venue"
},
  "geometry": {"coordinates":[-2.305994,53.094616],"type":"Point"}
}