{
  "type": "Feature",
  "properties": {
    "addr:full":"1 Eastgate Business Centre, Southernhay Basildon Essex SS14 1EB",
    "addr:housenumber":"1",
    "addr:postcode":"ss14 1eb",
    "addr:street":"Eastgate Business Centre Southernhay",
    "iso:country":"GB",
    "sg:address":"1 Eastgate Business Centre, Southernhay",
    "sg:city":"Basildon",
    "sg:classifiers":[
        {
            "category":"Insurance",
            "subcategory":"Insurance Agent",
            "type":"Services"
        }
    ],
    "sg:phone":"+44 1268 531010",
    "sg:postcode":"SS14 1EB",
    "sg:province":"Essex",
    "wof:name":"Swift Direct Ltd.",
    "wof:placetype":"venue"
},
  "geometry": {"coordinates":[0.4614900053,51.5698204041],"type":"Point"}
}