{
  "type": "Feature",
  "properties": {
    "addr:full":"127 Portsmouth Rd, Frimley Camberley Hampshire GU16 5AA",
    "addr:housenumber":"127",
    "addr:postcode":"gu16 5aa",
    "addr:street":"Portsmouth Rd",
    "iso:country":"GB",
    "sg:address":"127 Portsmouth Rd, Frimley",
    "sg:city":"Camberley",
    "sg:classifiers":[
        {
            "category":"Retail",
            "subcategory":"Auto Repair",
            "type":"Services"
        }
    ],
    "sg:phone":"+44 1276 22079",
    "sg:postcode":"GU16 5AA",
    "sg:province":"Hampshire",
    "sg:tags":[
        "car",
        "specialist",
        "customizing"
    ],
    "wof:name":"Roper's Battery & Tyre Sales Ltd",
    "wof:placetype":"venue"
},
  "geometry": {"coordinates":[-0.7142999768,51.3039398193],"type":"Point"}
}