{
  "type": "Feature",
  "properties": {
    "iso:country":"GB",
    "sg:address":"8a Abbey Foregate",
    "sg:city":"Shrewsbury",
    "sg:classifiers":[
        {
            "category":"Food & Beverages",
            "subcategory":"Meat & Fish",
            "type":"Retail Goods"
        }
    ],
    "sg:phone":"+44 1743 236399",
    "sg:postcode":"SY2 6AD",
    "sg:province":"Shropshire",
    "sg:tags":[
        "chip"
    ],
    "wof:name":"The Abbey Fish Bar",
    "wof:placetype":"venue"
},
  "geometry": {"coordinates":[-2.7457909584,52.7071990967],"type":"Point"}
}