{
  "type": "Feature",
  "properties": {
    "addr:full":"Unit 7, South East Quadrant Warrington Cheshire WA2 8AS",
    "addr:housenumber":"unit 7",
    "addr:postcode":"wa2 8as",
    "iso:country":"GB",
    "sg:address":"Unit 7, South East Quadrant",
    "sg:city":"Warrington",
    "sg:classifiers":[
        {
            "category":"Home & Garden",
            "subcategory":"Household Appliances",
            "type":"Retail Goods"
        }
    ],
    "sg:phone":"+44 1925 415296",
    "sg:postcode":"WA2 8AS",
    "sg:province":"Cheshire",
    "sg:tags":[
        "electrical",
        "domestic"
    ],
    "wof:name":"Tandy",
    "wof:placetype":"venue"
},
  "geometry": {"coordinates":[-2.5912139416,53.4039497375],"type":"Point"}
}