{
  "type": "Feature",
  "properties": {
    "addr:full":"21 Crouch Street Colchester Essex CO3 3EN",
    "addr:housenumber":"21",
    "addr:postcode":"co3 3en",
    "addr:street":"Crouch Street",
    "iso:country":"GB",
    "sg:address":"21 Crouch Street",
    "sg:city":"Colchester",
    "sg:classifiers":[
        {
            "category":"Personal",
            "subcategory":"Beauty Salon",
            "type":"Services"
        }
    ],
    "sg:postcode":"CO3 3EN",
    "sg:province":"Essex",
    "sg:tags":[
        "unisex",
        "hairdresser"
    ],
    "wof:name":"Hair by Claire",
    "wof:placetype":"venue"
},
  "geometry": {"coordinates":[0.89142,51.887806],"type":"Point"}
}