{
  "type": "Feature",
  "properties": {
    "addr:full":"6 St George Road Chepstow Gloucestershire NP16 5LA",
    "addr:housenumber":"6",
    "addr:postcode":"np16 5la",
    "addr:street":"St George Road",
    "iso:country":"GB",
    "sg:address":"6 St George Road",
    "sg:city":"Chepstow",
    "sg:classifiers":[
        {
            "category":"Professional",
            "subcategory":"Engineering",
            "type":"Services"
        }
    ],
    "sg:phone":"+44 1291 623270",
    "sg:postcode":"NP16 5LA",
    "sg:province":"Gloucestershire",
    "sg:tags":[
        "electrical",
        "engineer"
    ],
    "wof:name":"Lightdetail Ltd.",
    "wof:placetype":"venue"
},
  "geometry": {"coordinates":[-2.675948,51.635708],"type":"Point"}
}