{
  "type": "Feature",
  "properties": {
    "iso:country":"GB",
    "sg:address":"102 Queens Drive",
    "sg:city":"Bedford",
    "sg:classifiers":[
        {
            "category":"Shopping",
            "subcategory":"News",
            "type":"Retail Goods"
        }
    ],
    "sg:phone":"+44 1234 353572",
    "sg:postcode":"MK41 9BS",
    "sg:province":"Bedfordshire",
    "sg:tags":[
        "newsagent"
    ],
    "wof:name":"Forbuoys Ltd.",
    "wof:placetype":"venue"
},
  "geometry": {"coordinates":[-0.439665,52.149174],"type":"Point"}
}