{
  "type": "Feature",
  "properties": {
    "addr:full":"Unit F 9 The Mayford Centre, Mayford Grn Woking Surrey GU22 0PP",
    "addr:housenumber":"9",
    "addr:postcode":"gu22 0pp",
    "addr:street":"The;Mayford Grn",
    "iso:country":"GB",
    "sg:address":"Unit F 9 The Mayford Centre, Mayford Grn",
    "sg:city":"Woking",
    "sg:classifiers":[
        {
            "category":"Shopping",
            "subcategory":"Musical Instruments",
            "type":"Retail Goods"
        }
    ],
    "sg:postcode":"GU22 0PP",
    "sg:province":"Surrey",
    "sg:tags":[
        "music",
        "sheet"
    ],
    "wof:name":"The Drummers Workshop",
    "wof:placetype":"venue"
},
  "geometry": {"coordinates":[-0.572559,51.296757],"type":"Point"}
}