{
  "type": "Feature",
  "properties": {
    "addr:full":"16 High Street Billericay Essex CM12 9BQ",
    "addr:housenumber":"16",
    "addr:postcode":"cm12 9bq",
    "addr:street":"High Street",
    "iso:country":"GB",
    "sg:address":"16 High Street",
    "sg:city":"Billericay",
    "sg:classifiers":[
        {
            "category":"Professional",
            "subcategory":"Employment Agencies",
            "type":"Services"
        }
    ],
    "sg:phone":"+44 1277 632394",
    "sg:postcode":"CM12 9BQ",
    "sg:province":"Essex",
    "sg:tags":[
        "consultant"
    ],
    "wof:name":"Supported Employment & Training",
    "wof:placetype":"venue"
},
  "geometry": {"coordinates":[0.419118,51.627071],"type":"Point"}
}