{
  "type": "Feature",
  "properties": {
    "addr:full":"The Podium, Northgate Street Bath Bath and North East Somerset BA1 5AL",
    "addr:postcode":"ba1 5al",
    "addr:street":"Northgate Street",
    "iso:country":"GB",
    "sg:address":"The Podium, Northgate Street",
    "sg:city":"Bath",
    "sg:classifiers":[
        {
            "category":"Food & Beverages",
            "subcategory":"Supermarket",
            "type":"Retail Goods"
        }
    ],
    "sg:phone":"+44 1225 442550",
    "sg:postcode":"BA1 5AL",
    "sg:province":"Bath and North East Somerset",
    "wof:name":"Waitrose Ltd.",
    "wof:placetype":"venue"
},
  "geometry": {"coordinates":[-2.361166954,51.3850708008],"type":"Point"}
}