{
  "type": "Feature",
  "properties": {
    "iso:country":"GB",
    "sg:address":"4a Fourth Drove, Little Downham",
    "sg:city":"Ely",
    "sg:classifiers":[
        {
            "category":"Farming",
            "subcategory":"Livestock Farm",
            "type":"Manufacturing & Wholesale Goods"
        },
        {
            "category":"Farming",
            "subcategory":"Farm",
            "type":"Manufacturing & Wholesale Goods"
        }
    ],
    "sg:phone":"+44 1353 699338",
    "sg:postcode":"CB6 2ES",
    "sg:province":"Cambridgeshire",
    "sg:tags":[
        "mixed",
        "others"
    ],
    "wof:name":"W I Butcher & Sons",
    "wof:placetype":"venue"
},
  "geometry": {"coordinates":[0.241555,52.43325],"type":"Point"}
}