{
  "type": "Feature",
  "properties": {
    "iso:country":"GB",
    "sg:address":"All Saints Church, Oakleigh Road North",
    "sg:city":"Totteridge",
    "sg:classifiers":[
        {
            "category":"Community Center",
            "subcategory":"Youth",
            "type":"Public Place"
        }
    ],
    "sg:phone":"+44 20 8361 9796",
    "sg:postcode":"N20 9EZ",
    "sg:province":"Greater London",
    "sg:tags":[
        "organisation",
        "centre"
    ],
    "wof:name":"6th Friern Barnet Scout Group",
    "wof:placetype":"venue"
},
  "geometry": {"coordinates":[-0.16947,51.629662],"type":"Point"}
}