{
  "type": "Feature",
  "properties": {
    "addr:full":"Grange Farm Primary School, Dewsbury Avenue Coventry Warwickshire CV3 6NF",
    "addr:postcode":"cv3 6nf",
    "addr:street":"Dewsbury Avenue",
    "iso:country":"GB",
    "sg:address":"Grange Farm Primary School, Dewsbury Avenue",
    "sg:city":"Coventry",
    "sg:classifiers":[
        {
            "category":"Education",
            "subcategory":"School",
            "type":"Public Place"
        },
        {
            "category":"Government",
            "subcategory":"Office",
            "type":"Public Place"
        }
    ],
    "sg:phone":"+44 24 7641 1098",
    "sg:postcode":"CV3 6NF",
    "sg:province":"Warwickshire",
    "sg:tags":[
        "local",
        "authority"
    ],
    "wof:name":"Grange Farm Primary School",
    "wof:placetype":"venue"
},
  "geometry": {"coordinates":[-1.520866,52.385513],"type":"Point"}
}