{
  "type": "Feature",
  "properties": {
    "addr:full":"297 All Saints Road Wolverhampton West Midlands WV2 1EG",
    "addr:housenumber":"297",
    "addr:postcode":"wv2 1eg",
    "addr:street":"All Saints Road",
    "iso:country":"GB",
    "sg:address":"297 All Saints Road",
    "sg:city":"Wolverhampton",
    "sg:classifiers":[
        {
            "category":"Building & Trades",
            "subcategory":"Construction",
            "type":"Services"
        }
    ],
    "sg:phone":"+44 1902 451296",
    "sg:postcode":"WV2 1EG",
    "sg:province":"West Midlands",
    "sg:tags":[
        "joiner",
        "carpenter"
    ],
    "wof:name":"Wolverhampton Shopfitting Accessories",
    "wof:placetype":"venue"
},
  "geometry": {"coordinates":[-2.1244080067,52.5780754089],"type":"Point"}
}