{
  "type": "Feature",
  "properties": {
    "iso:country":"GB",
    "sg:address":"Newlyn Market, Newlyn",
    "sg:city":"Penzance",
    "sg:classifiers":[
        {
            "category":"Food & Beverages",
            "subcategory":"Meat & Fish",
            "type":"Retail Goods"
        }
    ],
    "sg:phone":"+44 1736 350000",
    "sg:postcode":"TR18 5HW",
    "sg:province":"Cornwall",
    "sg:tags":[
        "merchant"
    ],
    "wof:name":"Smarts Prime Fish",
    "wof:placetype":"venue"
},
  "geometry": {"coordinates":[-5.5524082184,50.1017608643],"type":"Point"}
}