{
  "type": "Feature",
  "properties": {
    "iso:country":"GB",
    "sg:address":"319 Colne Road",
    "sg:city":"Burnley",
    "sg:classifiers":[
        {
            "category":"Social Services",
            "subcategory":"Adult Care",
            "type":"Services"
        }
    ],
    "sg:phone":"+44 1282 420798",
    "sg:postcode":"BB10 1XU",
    "sg:province":"Lancashire",
    "sg:tags":[
        "day",
        "centre"
    ],
    "wof:name":"Rokeby Centre",
    "wof:placetype":"venue"
},
  "geometry": {"coordinates":[-2.234214,53.81012],"type":"Point"}
}