{
  "type": "Feature",
  "properties": {
    "iso:country":"GB",
    "sg:address":"45 Churchgate",
    "sg:city":"Retford",
    "sg:classifiers":[
        {
            "category":"Food & Beverages",
            "subcategory":"Meat & Fish",
            "type":"Retail Goods"
        }
    ],
    "sg:postcode":"DN22 6PA",
    "sg:province":"Nottinghamshire",
    "sg:tags":[
        "butcher"
    ],
    "wof:name":"George Burton Butchers",
    "wof:placetype":"venue"
},
  "geometry": {"coordinates":[-0.9409809709,53.3247756958],"type":"Point"}
}