{
  "type": "Feature",
  "properties": {
    "addr:full":"8 Warren Street London Greater London W1T 5LG",
    "addr:housenumber":"8",
    "addr:postcode":"w1t 5lg",
    "addr:street":"Warren Street",
    "iso:country":"GB",
    "sg:address":"8 Warren Street",
    "sg:city":"London",
    "sg:classifiers":[
        {
            "category":"Bars & Pubs",
            "type":"Food & Drink"
        }
    ],
    "sg:phone":"+44 20 7255 9911",
    "sg:postcode":"W1T 5LG",
    "sg:province":"Greater London",
    "sg:tags":[
        "pubs",
        "inn"
    ],
    "wof:name":"Prince of Wales Feathers",
    "wof:placetype":"venue"
},
  "geometry": {"coordinates":[-0.138639003,51.5241851807],"type":"Point"}
}