{
  "type": "Feature",
  "properties": {
    "iso:country":"GB",
    "sg:address":"7 Rye View",
    "sg:city":"High Wycombe",
    "sg:classifiers":[
        {
            "category":"Retail",
            "subcategory":"Auto Rental",
            "type":"Services"
        },
        {
            "category":"Shopping",
            "subcategory":"News",
            "type":"Retail Goods"
        },
        {
            "category":"Organizations",
            "subcategory":"Religious Organization",
            "type":"Services"
        }
    ],
    "sg:phone":"+44 1494 439132",
    "sg:postcode":"HP13 6HL",
    "sg:province":"Buckinghamshire",
    "sg:tags":[
        "chauffeur",
        "hire",
        "car",
        "organisation",
        "newsagent",
        "driven"
    ],
    "wof:name":"ANDREW M PEDDLE",
    "wof:placetype":"venue"
},
  "geometry": {"coordinates":[-0.742873,51.632141],"type":"Point"}
}