{
  "type": "Feature",
  "properties": {
    "addr:full":"122 Sheriffs Highway Gateshead Tyne and Wear NE9 5SD",
    "addr:housenumber":"122",
    "addr:postcode":"ne9 5sd",
    "addr:street":"Sheriffs Highway",
    "iso:country":"GB",
    "sg:address":"122 Sheriffs Highway",
    "sg:city":"Gateshead",
    "sg:classifiers":[
        {
            "category":"Shopping",
            "subcategory":"Used Merchandise",
            "type":"Retail Goods"
        }
    ],
    "sg:phone":"+44 191 482 1604",
    "sg:postcode":"NE9 5SD",
    "sg:province":"Tyne and Wear",
    "sg:tags":[
        "furniture"
    ],
    "wof:name":"Low Sell Furnishers",
    "wof:placetype":"venue"
},
  "geometry": {"coordinates":[-1.5901190042,54.9431762695],"type":"Point"}
}