{
  "type": "Feature",
  "properties": {
    "iso:country":"GB",
    "sg:address":"13 Richmond Hill, Clifton",
    "sg:city":"Bristol",
    "sg:classifiers":[
        {
            "category":"Professional",
            "type":"Services"
        }
    ],
    "sg:phone":"+44 117 973 0620",
    "sg:postcode":"BS8 1AT",
    "sg:province":"City of Bristol",
    "sg:tags":[
        "interior",
        "furnishers",
        "designer"
    ],
    "wof:name":"Anthony Richard Interiors",
    "wof:placetype":"venue"
},
  "geometry": {"coordinates":[-2.610537,51.457268],"type":"Point"}
}