{
  "type": "Feature",
  "properties": {
    "iso:country":"GB",
    "sg:address":"Mackintosh Road, Rackheath Industrial Estate",
    "sg:city":"Norwich",
    "sg:classifiers":[
        {
            "category":"Professional",
            "subcategory":"Engineering",
            "type":"Services"
        }
    ],
    "sg:postcode":"NR13 6LJ",
    "sg:province":"Norfolk",
    "sg:tags":[
        "precision",
        "engineer"
    ],
    "wof:name":"Centec Engineering",
    "wof:placetype":"venue"
},
  "geometry": {"coordinates":[1.373136,52.67194],"type":"Point"}
}