{
  "type": "Feature",
  "properties": {
    "addr:full":"Newlands Community Hall, 226 Stroud Crescent London Greater London SW15 3EQ",
    "addr:housenumber":"226",
    "addr:postcode":"sw15 3eq",
    "addr:street":"Stroud Crescent",
    "iso:country":"GB",
    "sg:address":"Newlands Community Hall, 226 Stroud Crescent",
    "sg:city":"London",
    "sg:classifiers":[
        {
            "category":"Education",
            "subcategory":"Preschool",
            "type":"Public Place"
        }
    ],
    "sg:phone":"+44 20 8780 5050",
    "sg:postcode":"SW15 3EQ",
    "sg:province":"Greater London",
    "sg:tags":[
        "pre-school",
        "playgroups"
    ],
    "wof:name":"Putney Vale Tiny Tots",
    "wof:placetype":"venue"
},
  "geometry": {"coordinates":[-0.2436,51.437019],"type":"Point"}
}