{
  "type": "Feature",
  "properties": {
    "iso:country":"GB",
    "sg:address":"42a John Street",
    "sg:city":"Penicuik",
    "sg:classifiers":[
        {
            "category":"Shopping",
            "subcategory":"Florist",
            "type":"Retail Goods"
        }
    ],
    "sg:phone":"+44 1968 672909",
    "sg:postcode":"EH26 8AB",
    "sg:province":"Midlothian",
    "wof:name":"Tommy G's",
    "wof:placetype":"venue"
},
  "geometry": {"coordinates":[-3.223409,55.829529],"type":"Point"}
}