{
  "type": "Feature",
  "properties": {
    "iso:country":"GB",
    "sg:address":"31 Monks Ave",
    "sg:city":"West Molesey",
    "sg:classifiers":[
        {
            "category":"Building & Trades",
            "subcategory":"Construction",
            "type":"Services"
        }
    ],
    "sg:postcode":"KT8 2HD",
    "sg:province":"Greater London",
    "sg:tags":[
        "builder"
    ],
    "wof:name":"Harris,Jeffrey,",
    "wof:placetype":"venue"
},
  "geometry": {"coordinates":[-0.3824200034,51.3970527649],"type":"Point"}
}