{
  "type": "Feature",
  "properties": {
    "addr:full":"Middleton Street Llandrindod Wells Powys LD1 5ET",
    "addr:postcode":"ld1 5et",
    "addr:street":"Middleton Street",
    "iso:country":"GB",
    "sg:address":"Middleton Street",
    "sg:city":"Llandrindod Wells",
    "sg:classifiers":[
        {
            "category":"Food & Beverages",
            "subcategory":"Specialty",
            "type":"Retail Goods"
        },
        {
            "category":"Food & Beverages",
            "subcategory":"Supermarket",
            "type":"Retail Goods"
        }
    ],
    "sg:phone":"+44 1597 823074",
    "sg:postcode":"LD1 5ET",
    "sg:province":"Powys",
    "sg:tags":[
        "health",
        "product",
        "retailer"
    ],
    "wof:name":"Vans Good Food Shops",
    "wof:placetype":"venue"
},
  "geometry": {"coordinates":[-3.379399,52.240181],"type":"Point"}
}