{
  "type": "Feature",
  "properties": {
    "addr:full":"Kingscote Tetbury Gloucestershire GL8 8XZ",
    "addr:postcode":"gl8 8xz",
    "iso:country":"GB",
    "sg:address":"Kingscote",
    "sg:city":"Tetbury",
    "sg:classifiers":[
        {
            "category":"Travel",
            "subcategory":"Hotels & Motels",
            "type":"Entertainment"
        }
    ],
    "sg:phone":"+44 1453 860393",
    "sg:postcode":"GL8 8XZ",
    "sg:province":"Gloucestershire",
    "wof:name":"Hunters Hall Inn",
    "wof:placetype":"venue"
},
  "geometry": {"coordinates":[-2.1609759331,51.6378593445],"type":"Point"}
}