{
  "type": "Feature",
  "properties": {
    "addr:full":"56 Grosvenor Rd Romford Essex RM7 0QT",
    "addr:housenumber":"56",
    "addr:postcode":"rm7 0qt",
    "addr:street":"Grosvenor Rd",
    "iso:country":"GB",
    "sg:address":"56 Grosvenor Rd",
    "sg:city":"Romford",
    "sg:classifiers":[
        {
            "category":"Professional",
            "type":"Services"
        }
    ],
    "sg:phone":"+44 1708 708676",
    "sg:postcode":"RM7 0QT",
    "sg:province":"Essex",
    "sg:tags":[
        "entertainer"
    ],
    "wof:name":"Tonioke's Party Mania",
    "wof:placetype":"venue"
},
  "geometry": {"coordinates":[0.1730560064,51.5667228699],"type":"Point"}
}