{
  "type": "Feature",
  "properties": {
    "iso:country":"GB",
    "sg:address":"23 Tooting Market, Tooting High Street",
    "sg:city":"London",
    "sg:classifiers":[
        {
            "category":"Food & Beverages",
            "subcategory":"Meat & Fish",
            "type":"Retail Goods"
        }
    ],
    "sg:phone":"+44 20 8672 8381",
    "sg:postcode":"SW17 0RH",
    "sg:province":"Greater London",
    "sg:tags":[
        "butcher"
    ],
    "wof:name":"Stannards",
    "wof:placetype":"venue"
},
  "geometry": {"coordinates":[-0.1721359938,51.4258270264],"type":"Point"}
}