{
  "type": "Feature",
  "properties": {
    "iso:country":"GB",
    "sg:address":"29 Dychurch Lane, Bozeat",
    "sg:city":"Wellingborough",
    "sg:classifiers":[
        {
            "category":"Professional",
            "subcategory":"Art Services",
            "type":"Services"
        }
    ],
    "sg:phone":"+44 1933 665617",
    "sg:postcode":"NN29 7JP",
    "sg:province":"Bedfordshire",
    "sg:tags":[
        "graphic",
        "designer"
    ],
    "wof:name":"Pollard Creativity",
    "wof:placetype":"venue"
},
  "geometry": {"coordinates":[-0.6682689786,52.2232780457],"type":"Point"}
}