{
  "type": "Feature",
  "properties": {
    "addr:full":"P O Box 497 Bristol City of Bristol BS99 7DB",
    "addr:housenumber":"497",
    "addr:postcode":"bs99 7db",
    "addr:street":"P O Box",
    "iso:country":"GB",
    "sg:address":"P O Box 497",
    "sg:city":"Bristol",
    "sg:classifiers":[
        {
            "category":"Professional",
            "subcategory":"Computer Services",
            "type":"Services"
        }
    ],
    "sg:phone":"+44 117 973 1004",
    "sg:postcode":"BS99 7DB",
    "sg:province":"City of Bristol",
    "sg:tags":[
        "system",
        "software"
    ],
    "wof:name":"Intellegents 2 B Ltd",
    "wof:placetype":"venue"
},
  "geometry": {"coordinates":[-2.59569,51.451481],"type":"Point"}
}