{
  "type": "Feature",
  "properties": {
    "iso:country":"GB",
    "sg:address":"10 High St",
    "sg:city":"Honiton",
    "sg:classifiers":[
        {
            "category":"Real Estate",
            "subcategory":"Surveying",
            "type":"Services"
        }
    ],
    "sg:phone":"+44 1404 45415",
    "sg:postcode":"EX14 1PU",
    "sg:province":"Devon",
    "sg:tags":[
        "surveyor",
        "valuer"
    ],
    "wof:name":"Keith Luxton",
    "wof:placetype":"venue"
},
  "geometry": {"coordinates":[-3.1835839748,50.8010978699],"type":"Point"}
}