{
  "type": "Feature",
  "properties": {
    "addr:full":"4 St James Square Bath Bath and North East Somerset BA1 2TR",
    "addr:housenumber":"4",
    "addr:postcode":"ba1 2tr",
    "addr:street":"St James Square",
    "iso:country":"GB",
    "sg:address":"4 St James Square",
    "sg:city":"Bath",
    "sg:classifiers":[
        {
            "category":"Organizations",
            "subcategory":"Membership Organization",
            "type":"Services"
        }
    ],
    "sg:phone":"+44 1225 331663",
    "sg:postcode":"BA1 2TR",
    "sg:province":"Bath and North East Somerset",
    "sg:tags":[
        "club"
    ],
    "wof:name":"4 St James Square Bath Management Limite",
    "wof:placetype":"venue"
},
  "geometry": {"coordinates":[-2.368889,51.388931],"type":"Point"}
}