{
  "type": "Feature",
  "properties": {
    "iso:country":"GB",
    "sg:address":"49 Kynaston Rd",
    "sg:city":"Stoke Newington",
    "sg:classifiers":[
        {
            "category":"Shopping",
            "subcategory":"News",
            "type":"Retail Goods"
        }
    ],
    "sg:phone":"+44 20 7254 0339",
    "sg:postcode":"N16 0EB",
    "sg:province":"Greater London",
    "sg:tags":[
        "newsagent"
    ],
    "wof:name":"D Barnard",
    "wof:placetype":"venue"
},
  "geometry": {"coordinates":[-0.07775,51.560131],"type":"Point"}
}