{
  "type": "Feature",
  "properties": {
    "addr:full":"12 Park Pl Leeds West Yorkshire LS1 2RU",
    "addr:housenumber":"12",
    "addr:postcode":"ls1 2ru",
    "addr:street":"Park Pl",
    "iso:country":"GB",
    "sg:address":"12 Park Pl",
    "sg:city":"Leeds",
    "sg:classifiers":[
        {
            "category":"Real Estate",
            "subcategory":"Surveying",
            "type":"Services"
        },
        {
            "category":"Building & Trades",
            "subcategory":"Construction",
            "type":"Services"
        }
    ],
    "sg:postcode":"LS1 2RU",
    "sg:province":"West Yorkshire",
    "sg:tags":[
        "surveyor",
        "builder",
        "quantity"
    ],
    "wof:name":"Schofield Kendall Ltd",
    "wof:placetype":"venue"
},
  "geometry": {"coordinates":[-1.5519,53.797768],"type":"Point"}
}