{
  "type": "Feature",
  "properties": {
    "addr:full":"Leverton House, 461-463 London Road Sheffield South Yorkshire S2 4HL",
    "addr:housenumber":"leverton;461-463",
    "addr:postcode":"s2 4hl",
    "addr:street":"London Road",
    "iso:country":"GB",
    "sg:address":"Leverton House, 461-463 London Road",
    "sg:city":"Sheffield",
    "sg:classifiers":[
        {
            "category":"Professional",
            "subcategory":"Accounting & Tax Preparation",
            "type":"Services"
        }
    ],
    "sg:phone":"+44 114 258 0305",
    "sg:postcode":"S2 4HL",
    "sg:province":"South Yorkshire",
    "sg:tags":[
        "accountant"
    ],
    "wof:name":"Altman Smith & Co",
    "wof:placetype":"venue"
},
  "geometry": {"coordinates":[-1.4723709822,53.3638725281],"type":"Point"}
}