{
  "type": "Feature",
  "properties": {
    "iso:country":"GB",
    "sg:address":"Fountain Mill, 81 High Street",
    "sg:city":"Uxbridge",
    "sg:classifiers":[
        {
            "category":"Professional",
            "subcategory":"Lawyer & Legal Services",
            "type":"Services"
        }
    ],
    "sg:phone":"+44 1895 250414",
    "sg:postcode":"UB8 1JR",
    "sg:province":"Buckinghamshire",
    "sg:tags":[
        "advice",
        "counselling"
    ],
    "wof:name":"Trust Community Drugs & Alcohol Team",
    "wof:placetype":"venue"
},
  "geometry": {"coordinates":[-0.474536,51.544071],"type":"Point"}
}