{
  "type": "Feature",
  "properties": {
    "iso:country":"GB",
    "sg:address":"Springfield Farm Wheel Lane, Pilling",
    "sg:city":"Preston",
    "sg:classifiers":[
        {
            "category":"Farming",
            "subcategory":"Livestock Farm",
            "type":"Manufacturing & Wholesale Goods"
        }
    ],
    "sg:phone":"+44 1253 790498",
    "sg:postcode":"PR3 6HL",
    "sg:province":"Lancashire",
    "sg:tags":[
        "others"
    ],
    "wof:name":"P W Roskell",
    "wof:placetype":"venue"
},
  "geometry": {"coordinates":[-2.910156,53.930977],"type":"Point"}
}