{
  "type": "Feature",
  "properties": {
    "addr:full":"5-9 Greenhill Road Paisley Renfrewshire PA3 1RJ",
    "addr:housenumber":"5-9",
    "addr:postcode":"pa3 1rj",
    "addr:street":"Greenhill Road",
    "iso:country":"GB",
    "sg:address":"5-9 Greenhill Road",
    "sg:city":"Paisley",
    "sg:classifiers":[
        {
            "category":"Home & Garden",
            "subcategory":"Hardware",
            "type":"Retail Goods"
        }
    ],
    "sg:phone":"+44 141 889 1608",
    "sg:postcode":"PA3 1RJ",
    "sg:province":"Renfrewshire",
    "sg:tags":[
        "merchant",
        "ironmonger"
    ],
    "wof:name":"J K M Industrial Supply Merchants Ltd",
    "wof:placetype":"venue"
},
  "geometry": {"coordinates":[-4.4391322136,55.8481140137],"type":"Point"}
}