{
  "type": "Feature",
  "properties": {
    "addr:full":"69 Kings Park Road Glasgow East Renfrewshire G44 4SX",
    "addr:housenumber":"69",
    "addr:postcode":"g44 4sx",
    "addr:street":"Kings Park Road",
    "iso:country":"GB",
    "sg:address":"69 Kings Park Road",
    "sg:city":"Glasgow",
    "sg:classifiers":[
        {
            "category":"Building & Trades",
            "subcategory":"Construction",
            "type":"Services"
        }
    ],
    "sg:postcode":"G44 4SX",
    "sg:province":"East Renfrewshire",
    "sg:tags":[
        "builder"
    ],
    "wof:name":"Robert Gerard Poole",
    "wof:placetype":"venue"
},
  "geometry": {"coordinates":[-4.256611,55.821499],"type":"Point"}
}