{
  "type": "Feature",
  "properties": {
    "iso:country":"GB",
    "sg:address":"3 Loddon View, Hurst Road",
    "sg:city":"Reading",
    "sg:classifiers":[
        {
            "category":"Building & Trades",
            "subcategory":"Construction",
            "type":"Services"
        }
    ],
    "sg:phone":"+44 118 934 3100",
    "sg:postcode":"RG10 0AW",
    "sg:province":"Berkshire",
    "sg:tags":[
        "builder"
    ],
    "wof:name":"Anthony Harding",
    "wof:placetype":"venue"
},
  "geometry": {"coordinates":[-0.8528860211,51.4585494995],"type":"Point"}
}