{
  "type": "Feature",
  "properties": {
    "iso:country":"GB",
    "sg:address":"Orton Malborne",
    "sg:city":"Peterborough",
    "sg:classifiers":[
        {
            "category":"Education",
            "subcategory":"School",
            "type":"Public Place"
        }
    ],
    "sg:phone":"+44 1733 232949",
    "sg:postcode":"PE2 5PL",
    "sg:province":"Cambridgeshire",
    "sg:tags":[
        "local",
        "authority"
    ],
    "wof:name":"Leighton County Primary School",
    "wof:placetype":"venue"
},
  "geometry": {"coordinates":[-0.27008,52.547371],"type":"Point"}
}