{
  "type": "Feature",
  "properties": {
    "addr:full":"The Heldite Centre, Bristow Road Hounslow Greater London TW3 1UP",
    "addr:postcode":"tw3 1up",
    "addr:street":"Bristow Road",
    "iso:country":"GB",
    "sg:address":"The Heldite Centre, Bristow Road",
    "sg:city":"Hounslow",
    "sg:classifiers":[
        {
            "category":"Organizations",
            "subcategory":"Non-profit Organization",
            "type":"Services"
        }
    ],
    "sg:phone":"+44 20 8570 6702",
    "sg:postcode":"TW3 1UP",
    "sg:province":"Greater London",
    "sg:tags":[
        "organisation",
        "voluntary",
        "charity"
    ],
    "wof:name":"Victims Support Schemes in London",
    "wof:placetype":"venue"
},
  "geometry": {"coordinates":[-0.352207,51.472843],"type":"Point"}
}