{
  "type": "Feature",
  "properties": {
    "addr:full":"York Street, Dufftown Keith Moray AB55 4AU",
    "addr:postcode":"ab55 4au",
    "addr:street":"York Street",
    "iso:country":"GB",
    "sg:address":"York Street, Dufftown",
    "sg:city":"Keith",
    "sg:classifiers":[
        {
            "category":"Education",
            "subcategory":"School",
            "type":"Public Place"
        }
    ],
    "sg:phone":"+44 1340 820268",
    "sg:postcode":"AB55 4AU",
    "sg:province":"Moray",
    "sg:tags":[
        "local",
        "authority"
    ],
    "wof:name":"Mortlach Primary School",
    "wof:placetype":"venue"
},
  "geometry": {"coordinates":[-3.1265668869,57.4448738098],"type":"Point"}
}