{
  "type": "Feature",
  "properties": {
    "addr:full":"156 Wellingborough Road Rushden Bedfordshire NN10 9ST",
    "addr:housenumber":"156",
    "addr:postcode":"nn10 9st",
    "addr:street":"Wellingborough Road",
    "iso:country":"GB",
    "sg:address":"156 Wellingborough Road",
    "sg:city":"Rushden",
    "sg:classifiers":[
        {
            "category":"Cinema",
            "subcategory":"Movie Rental",
            "type":"Entertainment"
        }
    ],
    "sg:phone":"+44 1933 411117",
    "sg:postcode":"NN10 9ST",
    "sg:province":"Bedfordshire",
    "sg:tags":[
        "video",
        "library"
    ],
    "wof:name":"Video Knights",
    "wof:placetype":"venue"
},
  "geometry": {"coordinates":[-0.606106,52.292122],"type":"Point"}
}