{
  "type": "Feature",
  "properties": {
    "addr:full":"81 Hockers Lane, Detling Maidstone Kent ME14 3JW",
    "addr:housenumber":"81",
    "addr:postcode":"me14 3jw",
    "addr:street":"Hockers Lane",
    "iso:country":"GB",
    "sg:address":"81 Hockers Lane, Detling",
    "sg:city":"Maidstone",
    "sg:classifiers":[
        {
            "category":"Home & Garden",
            "subcategory":"Building Materials",
            "type":"Retail Goods"
        },
        {
            "category":"Building & Trades",
            "subcategory":"Construction",
            "type":"Services"
        }
    ],
    "sg:postcode":"ME14 3JW",
    "sg:province":"Kent",
    "sg:tags":[
        "contracting",
        "fencing",
        "roofing"
    ],
    "wof:name":"Detling Fencing",
    "wof:placetype":"venue"
},
  "geometry": {"coordinates":[0.5671250224,51.288608551],"type":"Point"}
}