{
  "type": "Feature",
  "properties": {
    "addr:full":"54 High St Maidstone Kent ME14 1SY",
    "addr:housenumber":"54",
    "addr:postcode":"me14 1sy",
    "addr:street":"High St",
    "iso:country":"GB",
    "sg:address":"54 High St",
    "sg:city":"Maidstone",
    "sg:classifiers":[
        {
            "category":"Fast Food",
            "type":"Food & Drink"
        }
    ],
    "sg:phone":"+44 1622 691665",
    "sg:postcode":"ME14 1SY",
    "sg:province":"Kent",
    "sg:tags":[
        "away",
        "take"
    ],
    "wof:name":"Babs Take Away",
    "wof:placetype":"venue"
},
  "geometry": {"coordinates":[0.519568,51.272461],"type":"Point"}
}