{
  "type": "Feature",
  "properties": {
    "addr:full":"85 Belmont Avenue Wickford Essex SS12 0HG",
    "addr:housenumber":"85",
    "addr:postcode":"ss12 0hg",
    "addr:street":"Belmont Avenue Wickford",
    "iso:country":"GB",
    "sg:address":"85 Belmont Avenue",
    "sg:city":"Wickford",
    "sg:classifiers":[
        {
            "category":"Bus Charters",
            "type":"Transportation"
        }
    ],
    "sg:phone":"+44 1268 733746",
    "sg:postcode":"SS12 0HG",
    "sg:province":"Essex",
    "sg:tags":[
        "hire",
        "coach"
    ],
    "wof:name":"Bob's Mini Coaches",
    "wof:placetype":"venue"
},
  "geometry": {"coordinates":[0.50348,51.608753],"type":"Point"}
}