{
  "type": "Feature",
  "properties": {
    "iso:country":"GB",
    "sg:address":"25 Eastside, Kirkintilloch",
    "sg:city":"Glasgow",
    "sg:classifiers":[
        {
            "category":"Shopping",
            "subcategory":"Florist",
            "type":"Retail Goods"
        }
    ],
    "sg:phone":"+44 141 776 8266",
    "sg:postcode":"G66 1QA",
    "sg:province":"East Dunbartonshire",
    "wof:name":"Campsie Flowers",
    "wof:placetype":"venue"
},
  "geometry": {"coordinates":[-4.1538500786,55.9421577454],"type":"Point"}
}