{
  "type": "Feature",
  "properties": {
    "addr:full":"38 Main Street, Willoughby On The Wolds Loughborough Leicestershire LE12 6SZ",
    "addr:housenumber":"38",
    "addr:postcode":"le12 6sz",
    "addr:street":"Main Street",
    "iso:country":"GB",
    "sg:address":"38 Main Street, Willoughby On The Wolds",
    "sg:city":"Loughborough",
    "sg:classifiers":[
        {
            "category":"Building & Trades",
            "subcategory":"Construction",
            "type":"Services"
        }
    ],
    "sg:phone":"+44 1509 880925",
    "sg:postcode":"LE12 6SZ",
    "sg:province":"Leicestershire",
    "sg:tags":[
        "builder"
    ],
    "wof:name":"Derry Thornalley",
    "wof:placetype":"venue"
},
  "geometry": {"coordinates":[-1.151257,52.831635],"type":"Point"}
}