{
  "type": "Feature",
  "properties": {
    "iso:country":"GB",
    "sg:address":"31 Upper Dalton Way",
    "sg:city":"Newton Aycliffe",
    "sg:classifiers":[
        {
            "category":"Professional",
            "subcategory":"Accounting & Tax Preparation",
            "type":"Services"
        }
    ],
    "sg:phone":"+44 1325 300466",
    "sg:postcode":"DL5 4DJ",
    "sg:province":"Durham",
    "sg:tags":[
        "accountant"
    ],
    "wof:name":"Mitchell Gordon",
    "wof:placetype":"venue"
},
  "geometry": {"coordinates":[-1.57169,54.62112],"type":"Point"}
}