{
  "type": "Feature",
  "properties": {
    "addr:full":"13 Towngate Ossett West Yorkshire WF5 9BL",
    "addr:housenumber":"13;ossett",
    "addr:postcode":"wf5 9bl",
    "addr:street":"Towngate",
    "iso:country":"GB",
    "sg:address":"13 Towngate",
    "sg:city":"Ossett",
    "sg:classifiers":[
        {
            "category":"Shopping",
            "subcategory":"Books",
            "type":"Retail Goods"
        }
    ],
    "sg:phone":"+44 1924 267772",
    "sg:postcode":"WF5 9BL",
    "sg:province":"West Yorkshire",
    "sg:tags":[
        "bookseller"
    ],
    "wof:name":"Ossett Books Ltd.",
    "wof:placetype":"venue"
},
  "geometry": {"coordinates":[-1.5770889521,53.6799201965],"type":"Point"}
}