{
  "type": "Feature",
  "properties": {
    "addr:full":"The Old Vicarage, St Johns Road Ilkeston Derbyshire DE7 5PA",
    "addr:postcode":"de7 5pa",
    "addr:street":"St Johns Road",
    "iso:country":"GB",
    "sg:address":"The Old Vicarage, St Johns Road",
    "sg:city":"Ilkeston",
    "sg:classifiers":[
        {
            "category":"Wholesale",
            "subcategory":"Vending Machines",
            "type":"Manufacturing & Wholesale Goods"
        }
    ],
    "sg:phone":"+44 115 930 8550",
    "sg:postcode":"DE7 5PA",
    "sg:province":"Derbyshire",
    "sg:tags":[
        "content"
    ],
    "wof:name":"Local Vending Ltd",
    "wof:placetype":"venue"
},
  "geometry": {"coordinates":[-1.3101890087,52.9786109924],"type":"Point"}
}