{
  "type": "Feature",
  "properties": {
    "addr:full":"162 Vernon Road Nottingham Nottinghamshire NG6 0AD",
    "addr:housenumber":"162",
    "addr:postcode":"ng6 0ad",
    "addr:street":"Vernon Road",
    "iso:country":"GB",
    "sg:address":"162 Vernon Road",
    "sg:city":"Nottingham",
    "sg:classifiers":[
        {
            "category":"Fast Food",
            "type":"Food & Drink"
        }
    ],
    "sg:phone":"+44 115 942 2992",
    "sg:postcode":"NG6 0AD",
    "sg:province":"Nottinghamshire",
    "sg:tags":[
        "delivery"
    ],
    "wof:name":"Best Pizza",
    "wof:placetype":"venue"
},
  "geometry": {"coordinates":[-1.1780669689,52.9820251465],"type":"Point"}
}