{
  "type": "Feature",
  "properties": {
    "addr:full":"525 Cranbrook Road Ilford Essex IG2 6HA",
    "addr:housenumber":"525",
    "addr:postcode":"ig2 6ha",
    "addr:street":"Cranbrook Road",
    "iso:country":"GB",
    "sg:address":"525 Cranbrook Road",
    "sg:city":"Ilford",
    "sg:classifiers":[
        {
            "category":"Fast Food",
            "type":"Food & Drink"
        },
        {
            "category":"Restaurant",
            "type":"Food & Drink"
        }
    ],
    "sg:postcode":"IG2 6HA",
    "sg:province":"Essex",
    "sg:tags":[
        "away",
        "take"
    ],
    "wof:name":"CHAMPAGNE RESTAURANT",
    "wof:placetype":"venue"
},
  "geometry": {"coordinates":[0.0660969988,51.5753936768],"type":"Point"}
}