{
  "type": "Feature",
  "properties": {
    "addr:full":"177 Wood St, Walthamstow Walthamstow Greater London E17 3NU",
    "addr:housenumber":"177",
    "addr:postcode":"e17 3nu",
    "addr:street":"Wood St",
    "iso:country":"GB",
    "sg:address":"177 Wood St, Walthamstow",
    "sg:city":"Walthamstow",
    "sg:classifiers":[
        {
            "category":"Taxi",
            "type":"Transportation"
        }
    ],
    "sg:phone":"+44 20 8520 8585",
    "sg:postcode":"E17 3NU",
    "sg:province":"Greater London",
    "sg:tags":[
        "mini",
        "cab"
    ],
    "wof:name":"Wood Street Car Service",
    "wof:placetype":"venue"
},
  "geometry": {"coordinates":[-0.002119,51.58622],"type":"Point"}
}