{
  "type": "Feature",
  "properties": {
    "iso:country":"GB",
    "sg:address":"177 Wood St, Walthamstow",
    "sg:city":"Walthamstow",
    "sg:classifiers":[
        {
            "category":"Taxi",
            "type":"Transportation"
        }
    ],
    "sg:phone":"+44 20 8520 8585",
    "sg:postcode":"E17 3NU",
    "sg:province":"Greater London",
    "sg:tags":[
        "mini",
        "cab"
    ],
    "wof:name":"Wood Street Car Service",
    "wof:placetype":"venue"
},
  "geometry": {"coordinates":[-0.002119,51.58622],"type":"Point"}
}