{
  "type": "Feature",
  "properties": {
    "iso:country":"GB",
    "sg:address":"St Anthonys R C Primary School, Lochaber Dr",
    "sg:city":"Glasgow",
    "sg:classifiers":[
        {
            "category":"Farming",
            "subcategory":"Nursery",
            "type":"Manufacturing & Wholesale Goods"
        }
    ],
    "sg:phone":"+44 141 630 0005",
    "sg:postcode":"G73 5HX",
    "sg:province":"Glasgow City",
    "sg:tags":[
        "creche"
    ],
    "wof:name":"Weans World Afterschool Care Ltd",
    "wof:placetype":"venue"
},
  "geometry": {"coordinates":[-4.185613,55.807327],"type":"Point"}
}