{
  "type": "Feature",
  "properties": {
    "addr:full":"Updown Hill Windlesham Surrey GU20 6DL",
    "addr:postcode":"gu20 6dl",
    "addr:street":"Updown Hill",
    "iso:country":"GB",
    "sg:address":"Updown Hill",
    "sg:city":"Windlesham",
    "sg:classifiers":[
        {
            "category":"Government",
            "subcategory":"Post Office",
            "type":"Public Place"
        }
    ],
    "sg:phone":"+44 1276 472213",
    "sg:postcode":"GU20 6DL",
    "sg:province":"Surrey",
    "wof:name":"Updown Hill Post Office",
    "wof:placetype":"venue"
},
  "geometry": {"coordinates":[-0.6574890018,51.3661727905],"type":"Point"}
}