{
  "type": "Feature",
  "properties": {
    "iso:country":"GB",
    "sg:address":"11 Fitzroy Place",
    "sg:city":"Glasgow",
    "sg:classifiers":[
        {
            "category":"Brewery",
            "type":"Food & Drink"
        }
    ],
    "sg:phone":"+44 141 221 0707",
    "sg:postcode":"G3 7RW",
    "sg:province":"Glasgow City",
    "sg:tags":[
        "brewer"
    ],
    "wof:name":"Wm  Lundie & Co.",
    "wof:placetype":"venue"
},
  "geometry": {"coordinates":[-4.280479,55.86581],"type":"Point"}
}