{
  "type": "Feature",
  "properties": {
    "addr:full":"3 Beatrice Walk Bexhill-on-sea East Sussex TN39 4EW",
    "addr:housenumber":"3",
    "addr:postcode":"tn39 4ew",
    "addr:street":"Beatrice Walk",
    "iso:country":"GB",
    "sg:address":"3 Beatrice Walk",
    "sg:city":"Bexhill-on-sea",
    "sg:classifiers":[
        {
            "category":"Professional",
            "subcategory":"Art Services",
            "type":"Services"
        }
    ],
    "sg:postcode":"TN39 4EW",
    "sg:province":"East Sussex",
    "sg:tags":[
        "graphic",
        "designer"
    ],
    "wof:name":"Teamwork Design",
    "wof:placetype":"venue"
},
  "geometry": {"coordinates":[0.460339,50.850716],"type":"Point"}
}