{
  "type": "Feature",
  "properties": {
    "addr:full":"191 High Street London Greater London W3 9DD",
    "addr:housenumber":"191",
    "addr:postcode":"w3 9dd",
    "addr:street":"High Street",
    "iso:country":"GB",
    "sg:address":"191 High Street",
    "sg:city":"London",
    "sg:classifiers":[
        {
            "category":"Fast Food",
            "type":"Food & Drink"
        }
    ],
    "sg:phone":"+44 20 8992 3929",
    "sg:postcode":"W3 9DD",
    "sg:province":"Greater London",
    "sg:tags":[
        "away",
        "take"
    ],
    "wof:name":"Mings Take Away",
    "wof:placetype":"venue"
},
  "geometry": {"coordinates":[-0.272378,51.507355],"type":"Point"}
}