{
  "type": "Feature",
  "properties": {
    "addr:full":"192-200 Pensby Road, Heswall Wirral Merseyside CH60 7RJ",
    "addr:postcode":"192-200;ch60 7rj",
    "addr:street":"Pensby Road",
    "iso:country":"GB",
    "sg:address":"192-200 Pensby Road, Heswall",
    "sg:city":"Wirral",
    "sg:classifiers":[
        {
            "category":"Professional",
            "subcategory":"Accounting & Tax Preparation",
            "type":"Services"
        }
    ],
    "sg:postcode":"CH60 7RJ",
    "sg:province":"Merseyside",
    "sg:tags":[
        "accountant"
    ],
    "wof:name":"Malkin & Co",
    "wof:placetype":"venue"
},
  "geometry": {"coordinates":[-3.0968620777,53.3352165222],"type":"Point"}
}