{
  "type": "Feature",
  "properties": {
    "iso:country":"GB",
    "sg:address":"High Street",
    "sg:city":"Alfreton",
    "sg:classifiers":[
        {
            "category":"Bars & Pubs",
            "type":"Food & Drink"
        }
    ],
    "sg:phone":"+44 1773 811289",
    "sg:postcode":"DE55 2BP",
    "sg:province":"Derbyshire",
    "sg:tags":[
        "pubs",
        "inn"
    ],
    "wof:name":"Concorde Inns Ltd.",
    "wof:placetype":"venue"
},
  "geometry": {"coordinates":[-1.3411389589,53.1076850891],"type":"Point"}
}