{
  "type": "Feature",
  "properties": {
    "iso:country":"GB",
    "sg:address":"Park House, 15-19 Greenhill Crescent",
    "sg:city":"Watford",
    "sg:classifiers":[
        {
            "category":"Professional",
            "subcategory":"Printing & Photocopies",
            "type":"Services"
        }
    ],
    "sg:phone":"+44 1923 230675",
    "sg:postcode":"WD18 8PH",
    "sg:province":"Hertfordshire",
    "sg:tags":[
        "process",
        "screen",
        "printer"
    ],
    "wof:name":"Personal Print",
    "wof:placetype":"venue"
},
  "geometry": {"coordinates":[-0.425391,51.645702],"type":"Point"}
}