{
  "type": "Feature",
  "properties": {
    "iso:country":"GB",
    "sg:address":"16 Farne Road, Spittal",
    "sg:city":"Berwick-upon-tweed",
    "sg:classifiers":[
        {
            "category":"Retail",
            "subcategory":"Driving School",
            "type":"Services"
        }
    ],
    "sg:postcode":"TD15 2DW",
    "sg:province":"Northumberland",
    "wof:name":"Ian Virtue",
    "wof:placetype":"venue"
},
  "geometry": {"coordinates":[-2.002763,55.757767],"type":"Point"}
}