{
  "type": "Feature",
  "properties": {
    "addr:full":"Birks Farm, Long Lane, Garstang Preston Lancashire PR3 1RN",
    "addr:postcode":"pr3 1rn",
    "addr:street":"Long Lane",
    "iso:country":"GB",
    "sg:address":"Birks Farm, Long Lane, Garstang",
    "sg:city":"Preston",
    "sg:classifiers":[
        {
            "category":"Farming",
            "subcategory":"Crops",
            "type":"Manufacturing & Wholesale Goods"
        },
        {
            "category":"Farming",
            "subcategory":"Dairy Farm",
            "type":"Manufacturing & Wholesale Goods"
        }
    ],
    "sg:phone":"+44 1995 603252",
    "sg:postcode":"PR3 1RN",
    "sg:province":"Lancashire",
    "sg:tags":[
        "arable"
    ],
    "wof:name":"H L Proctor & Son",
    "wof:placetype":"venue"
},
  "geometry": {"coordinates":[-2.773784,53.907307],"type":"Point"}
}