{
  "type": "Feature",
  "properties": {
    "addr:full":"19 York Place Edinburgh City of Edinburgh EH1 3EB",
    "addr:housenumber":"19",
    "addr:postcode":"eh1 3eb",
    "addr:street":"York Place Edinburgh",
    "iso:country":"GB",
    "sg:address":"19 York Place",
    "sg:city":"Edinburgh",
    "sg:classifiers":[
        {
            "category":"Professional",
            "subcategory":"Art Services",
            "type":"Services"
        }
    ],
    "sg:phone":"+44 131 225 7232",
    "sg:postcode":"EH1 3EB",
    "sg:province":"City of Edinburgh",
    "sg:tags":[
        "graphic",
        "designer"
    ],
    "wof:name":"The Graphics Co. Ltd.",
    "wof:placetype":"venue"
},
  "geometry": {"coordinates":[-3.191092968,55.9559936523],"type":"Point"}
}