{
  "type": "Feature",
  "properties": {
    "addr:full":"3-5 Thorpe Clo London Greater London W10 5XL",
    "addr:housenumber":"3-5",
    "addr:postcode":"w10 5xl",
    "addr:street":"Thorpe Clo",
    "iso:country":"GB",
    "sg:address":"3-5 Thorpe Clo",
    "sg:city":"London",
    "sg:classifiers":[
        {
            "category":"Utilities",
            "type":"Services"
        }
    ],
    "sg:phone":"+44 20 8964 5484",
    "sg:postcode":"W10 5XL",
    "sg:province":"Greater London",
    "sg:tags":[
        "internet"
    ],
    "wof:name":"Dot Com Internet Cafe & Bars Ltd",
    "wof:placetype":"venue"
},
  "geometry": {"coordinates":[-0.209326,51.517956],"type":"Point"}
}