{
  "type": "Feature",
  "properties": {
    "iso:country":"GB",
    "sg:address":"Woodhouse Farm, Blithbury",
    "sg:city":"Rugeley",
    "sg:classifiers":[
        {
            "category":"Farming",
            "subcategory":"Farm",
            "type":"Manufacturing & Wholesale Goods"
        }
    ],
    "sg:phone":"+44 1889 504206",
    "sg:postcode":"WS15 3JL",
    "sg:province":"Staffordshire",
    "sg:tags":[
        "mixed",
        "crop"
    ],
    "wof:name":"Mavis & Michael James Daw",
    "wof:placetype":"venue"
},
  "geometry": {"coordinates":[-1.879249,52.778404],"type":"Point"}
}