{
  "type": "Feature",
  "properties": {
    "iso:country":"GB",
    "sg:address":"High Street, Goring-on-thames",
    "sg:city":"Reading",
    "sg:classifiers":[
        {
            "category":"Food & Beverages",
            "subcategory":"Groceries & Convenience Stores",
            "type":"Retail Goods"
        }
    ],
    "sg:phone":"+44 1491 872626",
    "sg:postcode":"RG8 9AR",
    "sg:province":"Berkshire",
    "wof:name":"W H Napper",
    "wof:placetype":"venue"
},
  "geometry": {"coordinates":[-1.137341,51.522671],"type":"Point"}
}