{
  "type": "Feature",
  "properties": {
    "addr:full":"22 Townsed Way, Folksworth Peterborough Cambridgeshire PE7 3TU",
    "addr:housenumber":"22",
    "addr:postcode":"pe7 3tu",
    "addr:street":"Townsed Way",
    "iso:country":"GB",
    "sg:address":"22 Townsed Way, Folksworth",
    "sg:city":"Peterborough",
    "sg:classifiers":[
        {
            "category":"Communications",
            "subcategory":"Film & Video Production",
            "type":"Services"
        }
    ],
    "sg:phone":"+44 1733 241850",
    "sg:postcode":"PE7 3TU",
    "sg:province":"Cambridgeshire",
    "sg:tags":[
        "survey",
        "aerial",
        "photographer"
    ],
    "wof:name":"Photoair",
    "wof:placetype":"venue"
},
  "geometry": {"coordinates":[-0.3086520135,52.4929008484],"type":"Point"}
}