{
  "type": "Feature",
  "properties": {
    "iso:country":"GB",
    "sg:address":"71-72 John Street Market",
    "sg:city":"Bradford",
    "sg:classifiers":[
        {
            "category":"Shopping",
            "subcategory":"Luggage & Leather Goods",
            "type":"Retail Goods"
        }
    ],
    "sg:phone":"+44 1274 370004",
    "sg:postcode":"BD1 3SS",
    "sg:province":"West Yorkshire",
    "wof:name":"Bags & Baggage",
    "wof:placetype":"venue"
},
  "geometry": {"coordinates":[-1.757259,53.79586],"type":"Point"}
}