{
  "type": "Feature",
  "properties": {
    "addr:full":"Junction Road Dorking Surrey RH4 3HB",
    "addr:postcode":"rh4 3hb",
    "addr:street":"Junction Road",
    "iso:country":"GB",
    "sg:address":"Junction Road",
    "sg:city":"Dorking",
    "sg:classifiers":[
        {
            "category":"Restaurant",
            "type":"Food & Drink"
        }
    ],
    "sg:phone":"+44 1306 742448",
    "sg:postcode":"RH4 3HB",
    "sg:province":"Surrey",
    "wof:name":"Highland Cottage",
    "wof:placetype":"venue"
},
  "geometry": {"coordinates":[-0.335384,51.231026],"type":"Point"}
}