{
  "type": "Feature",
  "properties": {
    "iso:country":"GB",
    "sg:address":"Unit 22, Okus Trading Estate Okus Rd",
    "sg:city":"Swindon",
    "sg:classifiers":[
        {
            "category":"Retail",
            "subcategory":"Auto Repair",
            "type":"Services"
        }
    ],
    "sg:phone":"+44 1793 491700",
    "sg:postcode":"SN1 4JH",
    "sg:province":"Wiltshire",
    "sg:tags":[
        "car",
        "specialist",
        "customizing"
    ],
    "wof:name":"Tamesvsall Tryres",
    "wof:placetype":"venue"
},
  "geometry": {"coordinates":[-1.781814,51.561764],"type":"Point"}
}