{
  "type": "Feature",
  "properties": {
    "iso:country":"GB",
    "sg:address":"654 Sutton Road",
    "sg:city":"Southend-on-sea",
    "sg:classifiers":[
        {
            "category":"Autos & Motor Vehicles",
            "subcategory":"Automobile Sales",
            "type":"Retail Goods"
        }
    ],
    "sg:phone":"+44 1702 602042",
    "sg:postcode":"SS2 5PX",
    "sg:province":"Essex",
    "sg:tags":[
        "car"
    ],
    "wof:name":"Cliffsea Cars (Hadleigh) Ltd.",
    "wof:placetype":"venue"
},
  "geometry": {"coordinates":[0.716531992,51.5575904846],"type":"Point"}
}