{
  "type": "Feature",
  "properties": {
    "iso:country":"GB",
    "sg:address":"Cynflex, Highfield Street",
    "sg:city":"Nottingham",
    "sg:classifiers":[
        {
            "category":"Real Estate",
            "subcategory":"Real Estate Agent",
            "type":"Services"
        }
    ],
    "sg:postcode":"NG10 4GY",
    "sg:province":"Derbyshire",
    "wof:name":"Hardwycke Estates Ltd.",
    "wof:placetype":"venue"
},
  "geometry": {"coordinates":[-1.282659,52.905861],"type":"Point"}
}