{
  "type": "Feature",
  "properties": {
    "addr:full":"58 Holywell Hill St Albans Hertfordshire AL1 1BX",
    "addr:housenumber":"58",
    "addr:postcode":"al1 1bx",
    "addr:street":"Holywell Hill",
    "iso:country":"GB",
    "sg:address":"58 Holywell Hill",
    "sg:city":"St Albans",
    "sg:classifiers":[
        {
            "category":"Home & Garden",
            "subcategory":"Furniture",
            "type":"Retail Goods"
        }
    ],
    "sg:postcode":"AL1 1BX",
    "sg:province":"Hertfordshire",
    "wof:name":"St. Albans Pine",
    "wof:placetype":"venue"
},
  "geometry": {"coordinates":[-0.341036,51.749016],"type":"Point"}
}