{
  "type": "Feature",
  "properties": {
    "iso:country":"GB",
    "sg:address":"15 Newnham Parade, College Road, Cheshunt",
    "sg:city":"Waltham Cross",
    "sg:classifiers":[
        {
            "category":"Food & Beverages",
            "subcategory":"Bakery",
            "type":"Retail Goods"
        }
    ],
    "sg:phone":"+44 1992 622229",
    "sg:postcode":"EN8 7NU",
    "sg:province":"Essex",
    "sg:tags":[
        "pizza"
    ],
    "wof:name":"Pizza Hut",
    "wof:placetype":"venue"
},
  "geometry": {"coordinates":[-0.033814,51.69051],"type":"Point"}
}