{
  "type": "Feature",
  "properties": {
    "iso:country":"GB",
    "sg:address":"37 Simpson Road, East Mains Industrial Estate",
    "sg:city":"Broxburn",
    "sg:classifiers":[
        {
            "category":"Home & Garden",
            "subcategory":"Kitchen Supply",
            "type":"Retail Goods"
        }
    ],
    "sg:phone":"+44 1506 852566",
    "sg:postcode":"EH52 5AU",
    "sg:province":"City of Edinburgh",
    "sg:tags":[
        "glassware",
        "china"
    ],
    "wof:name":"Gleneagles of Edinburgh Ltd.",
    "wof:placetype":"venue"
},
  "geometry": {"coordinates":[-3.471884,55.934235],"type":"Point"}
}