{
  "type": "Feature",
  "properties": {
    "iso:country":"GB",
    "sg:address":"81-83 High Street",
    "sg:city":"Bagshot",
    "sg:classifiers":[
        {
            "category":"Professional",
            "subcategory":"Accounting & Tax Preparation",
            "type":"Services"
        }
    ],
    "sg:phone":"+44 1276 451511",
    "sg:postcode":"GU19 5AH",
    "sg:province":"Berkshire",
    "sg:tags":[
        "accountant"
    ],
    "wof:name":"Lovesey & Co",
    "wof:placetype":"venue"
},
  "geometry": {"coordinates":[-0.6913759708,51.3623313904],"type":"Point"}
}