{
  "type": "Feature",
  "properties": {
    "addr:full":"56 Howard Rd Bromley Kent BR1 3QJ",
    "addr:housenumber":"56",
    "addr:postcode":"br1 3qj",
    "addr:street":"Howard Rd",
    "iso:country":"GB",
    "sg:address":"56 Howard Rd",
    "sg:city":"Bromley",
    "sg:classifiers":[
        {
            "category":"Building & Trades",
            "subcategory":"Construction",
            "type":"Services"
        }
    ],
    "sg:postcode":"BR1 3QJ",
    "sg:province":"Kent",
    "sg:tags":[
        "builder"
    ],
    "wof:name":"Hobdell,Peter,",
    "wof:placetype":"venue"
},
  "geometry": {"coordinates":[0.0122239999,51.41248703],"type":"Point"}
}