{
  "type": "Feature",
  "properties": {
    "addr:full":"34 Priory Gro, Bitton Aylesford Kent ME20 6BB",
    "addr:housenumber":"34",
    "addr:postcode":"me20 6bb",
    "addr:street":"Priory Gro Bitton",
    "iso:country":"GB",
    "sg:address":"34 Priory Gro, Bitton",
    "sg:city":"Aylesford",
    "sg:classifiers":[
        {
            "category":"Professional",
            "subcategory":"Engineering",
            "type":"Services"
        }
    ],
    "sg:postcode":"ME20 6BB",
    "sg:province":"Kent",
    "sg:tags":[
        "consulting",
        "engineer"
    ],
    "wof:name":"A Rawlingson",
    "wof:placetype":"venue"
},
  "geometry": {"coordinates":[0.4617469907,51.3000907898],"type":"Point"}
}