{
  "type": "Feature",
  "properties": {
    "iso:country":"GB",
    "sg:address":"Silesbourne Farm, Salters Lane, Wootton Wawen",
    "sg:city":"Solihull",
    "sg:classifiers":[
        {
            "category":"Farming",
            "subcategory":"Livestock Farm",
            "type":"Manufacturing & Wholesale Goods"
        },
        {
            "category":"Farming",
            "subcategory":"Farm",
            "type":"Manufacturing & Wholesale Goods"
        }
    ],
    "sg:postcode":"B95 6LA",
    "sg:province":"Warwickshire",
    "sg:tags":[
        "mixed",
        "crop",
        "others"
    ],
    "wof:name":"M A & J A Cleeton",
    "wof:placetype":"venue"
},
  "geometry": {"coordinates":[-1.7774089575,52.2667312622],"type":"Point"}
}