{
  "type": "Feature",
  "properties": {
    "addr:full":"5 High Street Wellingborough Northamptonshire NN8 4HR",
    "addr:housenumber":"5",
    "addr:postcode":"nn8 4hr",
    "addr:street":"High Street",
    "iso:country":"GB",
    "sg:address":"5 High Street",
    "sg:city":"Wellingborough",
    "sg:classifiers":[
        {
            "category":"Shopping",
            "subcategory":"Music",
            "type":"Retail Goods"
        }
    ],
    "sg:postcode":"NN8 4HR",
    "sg:province":"Northamptonshire",
    "sg:tags":[
        "record",
        "tape",
        "cd"
    ],
    "wof:name":"Record & Cassette Mart",
    "wof:placetype":"venue"
},
  "geometry": {"coordinates":[-0.696496,52.302353],"type":"Point"}
}