{
  "type": "Feature",
  "properties": {
    "addr:full":"Unit 24-25 In Shops, Monmouth Square Cwmbran Monmouthshire NP44 1PE",
    "addr:housenumber":"unit 24-25",
    "addr:postcode":"np44 1pe",
    "addr:street":"Monmouth Square",
    "iso:country":"GB",
    "sg:address":"Unit 24-25 In Shops, Monmouth Square",
    "sg:city":"Cwmbran",
    "sg:classifiers":[
        {
            "category":"Fast Food",
            "type":"Food & Drink"
        }
    ],
    "sg:phone":"+44 1633 864494",
    "sg:postcode":"NP44 1PE",
    "sg:province":"Monmouthshire",
    "sg:tags":[
        "away",
        "take"
    ],
    "wof:name":"Castaldo's Takeaway",
    "wof:placetype":"venue"
},
  "geometry": {"coordinates":[-3.0258638859,51.6574668884],"type":"Point"}
}