{
  "type": "Feature",
  "properties": {
    "iso:country":"GB",
    "sg:address":"15 Unity Street",
    "sg:city":"Sheerness",
    "sg:classifiers":[
        {
            "category":"Insurance",
            "subcategory":"Insurance Agent",
            "type":"Services"
        }
    ],
    "sg:postcode":"ME12 2PR",
    "sg:province":"Kent",
    "wof:name":"Kemp Services Ltd",
    "wof:placetype":"venue"
},
  "geometry": {"coordinates":[0.7737399936,51.437538147],"type":"Point"}
}