{
  "type": "Feature",
  "properties": {
    "addr:full":"98 Ovenden Road Halifax West Yorkshire HX3 5QG",
    "addr:housenumber":"98",
    "addr:postcode":"hx3 5qg",
    "addr:street":"Ovenden Road",
    "iso:country":"GB",
    "sg:address":"98 Ovenden Road",
    "sg:city":"Halifax",
    "sg:classifiers":[
        {
            "category":"Personal",
            "subcategory":"Beauty Salon",
            "type":"Services"
        }
    ],
    "sg:phone":"+44 1422 354728",
    "sg:postcode":"HX3 5QG",
    "sg:province":"West Yorkshire",
    "sg:tags":[
        "unisex",
        "hairdresser"
    ],
    "wof:name":"Deb-N-Hair",
    "wof:placetype":"venue"
},
  "geometry": {"coordinates":[-1.8742419481,53.7370948792],"type":"Point"}
}