{
  "type": "Feature",
  "properties": {
    "iso:country":"GB",
    "sg:address":"63 High St",
    "sg:city":"Reading",
    "sg:classifiers":[
        {
            "category":"Professional",
            "subcategory":"Lawyer & Legal Services",
            "type":"Services"
        }
    ],
    "sg:phone":"+44 118 940 4052",
    "sg:postcode":"RG10 8BU",
    "sg:province":"Berkshire",
    "sg:tags":[
        "advice",
        "counselling"
    ],
    "wof:name":"Catherine Clarke & Jennifer Davies",
    "wof:placetype":"venue"
},
  "geometry": {"coordinates":[-0.869591,51.501102],"type":"Point"}
}