{
  "type": "Feature",
  "properties": {
    "iso:country":"GB",
    "sg:address":"Fenix House, 2 New Kirkgate",
    "sg:city":"Shipley",
    "sg:classifiers":[
        {
            "category":"Professional",
            "subcategory":"Lawyer & Legal Services",
            "type":"Services"
        }
    ],
    "sg:phone":"+44 1274 584305",
    "sg:postcode":"BD18 3QY",
    "sg:province":"West Yorkshire",
    "sg:tags":[
        "solicitor"
    ],
    "wof:name":"Atkinson & Firth Solicitors",
    "wof:placetype":"venue"
},
  "geometry": {"coordinates":[-1.778614,53.834202],"type":"Point"}
}