{
  "type": "Feature",
  "properties": {
    "iso:country":"GB",
    "sg:address":"P O Box 37601",
    "sg:city":"London",
    "sg:classifiers":[
        {
            "category":"Shopping",
            "subcategory":"Hobbies, Toys, & Games",
            "type":"Retail Goods"
        }
    ],
    "sg:phone":"+44 20 8349 8048",
    "sg:postcode":"NW7 2YL",
    "sg:province":"Greater London",
    "sg:tags":[
        "stamp"
    ],
    "wof:name":"Ross-Shiells Ltd.",
    "wof:placetype":"venue"
},
  "geometry": {"coordinates":[-0.2411600053,51.615398407],"type":"Point"}
}