{
  "type": "Feature",
  "properties": {
    "iso:country":"GB",
    "sg:address":"105 Altcar Road, Formby",
    "sg:city":"Liverpool",
    "sg:classifiers":[
        {
            "category":"Parking",
            "type":"Transportation"
        }
    ],
    "sg:postcode":"L37 8DW",
    "sg:province":"Lancashire",
    "sg:tags":[
        "car",
        "valet"
    ],
    "wof:name":"Moores Professional Valeting Service",
    "wof:placetype":"venue"
},
  "geometry": {"coordinates":[-3.042485,53.553795],"type":"Point"}
}