{
  "type": "Feature",
  "properties": {
    "iso:country":"GB",
    "sg:address":"1 Alston Road, Pattinson North",
    "sg:city":"Washington",
    "sg:classifiers":[
        {
            "category":"Professional",
            "subcategory":"Engineering",
            "type":"Services"
        }
    ],
    "sg:phone":"+44 191 416 7786",
    "sg:postcode":"NE38 8QH",
    "sg:province":"Durham",
    "sg:tags":[
        "engineer"
    ],
    "wof:name":"Armour Plastics Ltd.",
    "wof:placetype":"venue"
},
  "geometry": {"coordinates":[-1.493949,54.902748],"type":"Point"}
}