{
  "type": "Feature",
  "properties": {
    "addr:full":"46 High Street Lowestoft Suffolk NR32 1HZ",
    "addr:housenumber":"46",
    "addr:postcode":"nr32 1hz",
    "addr:street":"High Street",
    "iso:country":"GB",
    "sg:address":"46 High Street",
    "sg:city":"Lowestoft",
    "sg:classifiers":[
        {
            "category":"Home & Garden",
            "subcategory":"Furniture",
            "type":"Retail Goods"
        }
    ],
    "sg:phone":"+44 1502 514300",
    "sg:postcode":"NR32 1HZ",
    "sg:province":"Suffolk",
    "wof:name":"Inspired by Stencil Art",
    "wof:placetype":"venue"
},
  "geometry": {"coordinates":[1.7564979792,52.4830741882],"type":"Point"}
}