{
  "type": "Feature",
  "properties": {
    "iso:country":"GB",
    "sg:address":"Argoed Farm, Cenarth",
    "sg:city":"Newcastle Emlyn",
    "sg:classifiers":[
        {
            "category":"Farming",
            "subcategory":"Dairy Farm",
            "type":"Manufacturing & Wholesale Goods"
        }
    ],
    "sg:postcode":"SA38 9JL",
    "sg:province":"Carmarthenshire",
    "wof:name":"T A & R Owens",
    "wof:placetype":"venue"
},
  "geometry": {"coordinates":[-4.467984,52.035919],"type":"Point"}
}