{
  "type": "Feature",
  "properties": {
    "addr:full":"36 Lombard Road London Greater London SW11 3RP",
    "addr:housenumber":"36",
    "addr:postcode":"sw11 3rp",
    "addr:street":"Lombard Road",
    "iso:country":"GB",
    "sg:address":"36 Lombard Road",
    "sg:city":"London",
    "sg:classifiers":[
        {
            "category":"Manufacturing",
            "subcategory":"Lumber",
            "type":"Manufacturing & Wholesale Goods"
        }
    ],
    "sg:phone":"+44 20 7564 2300",
    "sg:postcode":"SW11 3RP",
    "sg:province":"Greater London",
    "sg:tags":[
        "merchant",
        "merchants",
        "importer",
        "agent",
        "timber"
    ],
    "sg:website":"http://www.castleonline.co.uk",
    "wof:name":"Castle Timber & Building Materials Ltd",
    "wof:placetype":"venue"
},
  "geometry": {"coordinates":[-0.17764,51.471088],"type":"Point"}
}