{
  "type": "Feature",
  "properties": {
    "iso:country":"GB",
    "sg:address":"Norfolk Road",
    "sg:city":"Gravesend",
    "sg:classifiers":[
        {
            "category":"Bars & Pubs",
            "type":"Food & Drink"
        }
    ],
    "sg:phone":"+44 1474 359158",
    "sg:postcode":"DA12 2PS",
    "sg:province":"Kent",
    "sg:tags":[
        "pubs",
        "inn"
    ],
    "wof:name":"Margaret King & Colin Thomson",
    "wof:placetype":"venue"
},
  "geometry": {"coordinates":[0.38208,51.440964],"type":"Point"}
}