{
  "type": "Feature",
  "properties": {
    "addr:full":"158 Fulham Palace Road London Greater London W6 9ER",
    "addr:housenumber":"158",
    "addr:postcode":"w6 9er",
    "addr:street":"Fulham Palace Road",
    "iso:country":"GB",
    "sg:address":"158 Fulham Palace Road",
    "sg:city":"London",
    "sg:classifiers":[
        {
            "category":"Organizations",
            "subcategory":"Labor Organization",
            "type":"Services"
        }
    ],
    "sg:phone":"+44 20 8741 5999",
    "sg:postcode":"W6 9ER",
    "sg:province":"Greater London",
    "sg:tags":[
        "oil"
    ],
    "wof:name":"Almeana Ltd.",
    "wof:placetype":"venue"
},
  "geometry": {"coordinates":[-0.220777,51.486031],"type":"Point"}
}