{
  "type": "Feature",
  "properties": {
    "iso:country":"GB",
    "sg:address":"10 Audrey St",
    "sg:city":"Ossett",
    "sg:classifiers":[
        {
            "category":"Building & Trades",
            "subcategory":"Equipment Rental",
            "type":"Services"
        }
    ],
    "sg:phone":"+44 1924 265630",
    "sg:postcode":"WF5 0JL",
    "sg:province":"West Yorkshire",
    "sg:tags":[
        "plant",
        "machinery"
    ],
    "wof:name":"J C Daniel",
    "wof:placetype":"venue"
},
  "geometry": {"coordinates":[-1.570705,53.673298],"type":"Point"}
}