{
  "type": "Feature",
  "properties": {
    "addr:full":"9 Stonehills Mansions, 8 Streatham High Rd Streatham Greater London SW16 1DD",
    "addr:housenumber":"9;8",
    "addr:postcode":"sw16 1dd",
    "addr:street":"Streatham High Rd",
    "iso:country":"GB",
    "sg:address":"9 Stonehills Mansions, 8 Streatham High Rd",
    "sg:city":"Streatham",
    "sg:classifiers":[
        {
            "category":"Health Services",
            "subcategory":"Health Practitioner",
            "type":"Services"
        }
    ],
    "sg:phone":"+44 20 8769 2118",
    "sg:postcode":"SW16 1DD",
    "sg:province":"Greater London",
    "sg:tags":[
        "hypnotherapists"
    ],
    "wof:name":"Joseph Perrins",
    "wof:placetype":"venue"
},
  "geometry": {"coordinates":[-0.130089,51.430126],"type":"Point"}
}