{
  "type": "Feature",
  "properties": {
    "addr:full":"73a Nuxley Road Belvedere Kent DA17 5JN",
    "addr:housenumber":"73a",
    "addr:postcode":"da17 5jn",
    "addr:street":"Nuxley Road",
    "iso:country":"GB",
    "sg:address":"73a Nuxley Road",
    "sg:city":"Belvedere",
    "sg:classifiers":[
        {
            "category":"Professional",
            "subcategory":"Accounting & Tax Preparation",
            "type":"Services"
        }
    ],
    "sg:phone":"+44 1322 449063",
    "sg:postcode":"DA17 5JN",
    "sg:province":"Kent",
    "sg:tags":[
        "accountant",
        "activity"
    ],
    "wof:name":"K J Watkin",
    "wof:placetype":"venue"
},
  "geometry": {"coordinates":[0.1451350003,51.4815330505],"type":"Point"}
}