{
  "type": "Feature",
  "properties": {
    "addr:full":"Beech Hill Cotts, Beech Hill Road Bordon Hampshire GU35 8DW",
    "addr:postcode":"gu35 8dw",
    "addr:street":"Beech Hill Road",
    "iso:country":"GB",
    "sg:address":"Beech Hill Cotts, Beech Hill Road",
    "sg:city":"Bordon",
    "sg:classifiers":[
        {
            "category":"Building & Trades",
            "subcategory":"Construction",
            "type":"Services"
        }
    ],
    "sg:phone":"+44 1428 713431",
    "sg:postcode":"GU35 8DW",
    "sg:province":"Hampshire",
    "sg:tags":[
        "builder"
    ],
    "wof:name":"Roger W Smith",
    "wof:placetype":"venue"
},
  "geometry": {"coordinates":[-0.8054339886,51.1224250793],"type":"Point"}
}