{
  "type": "Feature",
  "properties": {
    "addr:full":"32 Church Street, Haslingfield Cambridge Cambridgeshire CB3 7JE",
    "addr:housenumber":"32",
    "addr:postcode":"cb3 7je",
    "addr:street":"Church Street",
    "iso:country":"GB",
    "sg:address":"32 Church Street, Haslingfield",
    "sg:city":"Cambridge",
    "sg:classifiers":[
        {
            "category":"Building & Trades",
            "subcategory":"Construction",
            "type":"Services"
        }
    ],
    "sg:postcode":"CB3 7JE",
    "sg:province":"Cambridgeshire",
    "sg:tags":[
        "bricklaying"
    ],
    "wof:name":"Lambert Constructions (Cambridge) Ltd.",
    "wof:placetype":"venue"
},
  "geometry": {"coordinates":[0.0481400006,52.1513366699],"type":"Point"}
}