{
  "type": "Feature",
  "properties": {
    "addr:full":"142 Mill Hill Deal Kent CT14 9HZ",
    "addr:housenumber":"142",
    "addr:postcode":"ct14 9hz",
    "addr:street":"Mill Hill Deal",
    "iso:country":"GB",
    "sg:address":"142 Mill Hill",
    "sg:city":"Deal",
    "sg:classifiers":[
        {
            "category":"Retail",
            "subcategory":"Auto Repair",
            "type":"Services"
        }
    ],
    "sg:phone":"+44 1304 362537",
    "sg:postcode":"CT14 9HZ",
    "sg:province":"Kent",
    "sg:tags":[
        "modification",
        "garage"
    ],
    "wof:name":"Mobile Repair Services",
    "wof:placetype":"venue"
},
  "geometry": {"coordinates":[1.3814419508,51.2097396851],"type":"Point"}
}