{
  "type": "Feature",
  "properties": {
    "addr:full":"284 Ecclesall Road Sheffield Derbyshire S11 8PE",
    "addr:housenumber":"284",
    "addr:postcode":"s11 8pe",
    "addr:street":"Ecclesall Road",
    "iso:country":"GB",
    "sg:address":"284 Ecclesall Road",
    "sg:city":"Sheffield",
    "sg:classifiers":[
        {
            "category":"Personal",
            "subcategory":"Beauty Salon",
            "type":"Services"
        },
        {
            "category":"Personal",
            "subcategory":"Barber",
            "type":"Services"
        }
    ],
    "sg:phone":"+44 114 266 4045",
    "sg:postcode":"S11 8PE",
    "sg:province":"Derbyshire",
    "sg:tags":[
        "unisex",
        "hairdresser"
    ],
    "wof:name":"284 Hair",
    "wof:placetype":"venue"
},
  "geometry": {"coordinates":[-1.48896,53.37149],"type":"Point"}
}