{
  "type": "Feature",
  "properties": {
    "addr:full":"28 Camberwell Gro London Greater London SE5 8RE",
    "addr:housenumber":"28",
    "addr:postcode":"se5 8re",
    "addr:street":"Camberwell Gro",
    "iso:country":"GB",
    "sg:address":"28 Camberwell Gro",
    "sg:city":"London",
    "sg:classifiers":[
        {
            "category":"Shopping",
            "subcategory":"Books",
            "type":"Retail Goods"
        }
    ],
    "sg:postcode":"SE5 8RE",
    "sg:province":"Greater London",
    "sg:tags":[
        "second-hand"
    ],
    "wof:name":"The Camberwell Book Shop",
    "wof:placetype":"venue"
},
  "geometry": {"coordinates":[-0.08913,51.473427],"type":"Point"}
}