{
  "type": "Feature",
  "properties": {
    "addr:full":"Dutch Court Farm, Dutch Road, Mark Highbridge Somerset TA9 4QR",
    "addr:postcode":"ta9 4qr",
    "addr:street":"Dutch Court;Dutch Road",
    "iso:country":"GB",
    "sg:address":"Dutch Court Farm, Dutch Road, Mark",
    "sg:city":"Highbridge",
    "sg:classifiers":[
        {
            "category":"Farming",
            "subcategory":"Livestock Farm",
            "type":"Manufacturing & Wholesale Goods"
        },
        {
            "category":"Retail",
            "subcategory":"Animal Services",
            "type":"Services"
        }
    ],
    "sg:phone":"+44 1278 783474",
    "sg:postcode":"TA9 4QR",
    "sg:province":"Somerset",
    "sg:tags":[
        "breeder",
        "others"
    ],
    "wof:name":"G Hares",
    "wof:placetype":"venue"
},
  "geometry": {"coordinates":[-2.930711,51.228313],"type":"Point"}
}