{
  "type": "Feature",
  "properties": {
    "addr:full":"Corner Of St Andrews Rd, Watery La Birmingham West Midlands B9 4HF",
    "addr:postcode":"b9 4hf",
    "addr:street":"Corner Of St Andrews Rd;La Birmingham",
    "iso:country":"GB",
    "sg:address":"Corner Of St Andrews Rd, Watery La",
    "sg:city":"Birmingham",
    "sg:classifiers":[
        {
            "category":"Autos & Motor Vehicles",
            "subcategory":"Fuel & Gas Station",
            "type":"Retail Goods"
        }
    ],
    "sg:phone":"+44 121 771 2672",
    "sg:postcode":"B9 4HF",
    "sg:province":"West Midlands",
    "sg:tags":[
        "hr",
        "petrol"
    ],
    "wof:name":"St Andrews Filling Station",
    "wof:placetype":"venue"
},
  "geometry": {"coordinates":[-1.871589,52.477085],"type":"Point"}
}