{
  "type": "Feature",
  "properties": {
    "addr:full":"10 Abeles Way, Holly Lane Industrial Estate Atherstone Leicestershire CV9 2QZ",
    "addr:housenumber":"10",
    "addr:postcode":"cv9 2qz",
    "addr:street":"Abeles Way Holly Lane Industrial Estate",
    "iso:country":"GB",
    "sg:address":"10 Abeles Way, Holly Lane Industrial Estate",
    "sg:city":"Atherstone",
    "sg:classifiers":[
        {
            "category":"Retail",
            "subcategory":"Auto Repair",
            "type":"Services"
        }
    ],
    "sg:phone":"+44 1827 712097",
    "sg:postcode":"CV9 2QZ",
    "sg:province":"Leicestershire",
    "sg:tags":[
        "electrician",
        "electrical",
        "centre"
    ],
    "wof:name":"K J Cox Auto Electrical",
    "wof:placetype":"venue"
},
  "geometry": {"coordinates":[-1.554234,52.584053],"type":"Point"}
}