{
  "type": "Feature",
  "properties": {
    "iso:country":"GB",
    "sg:address":"Unit 10 Friendship Mill Whalley, Road, Padiham",
    "sg:city":"Burnley",
    "sg:classifiers":[
        {
            "category":"Farming",
            "subcategory":"Farm",
            "type":"Manufacturing & Wholesale Goods"
        }
    ],
    "sg:phone":"+44 1282 776475",
    "sg:postcode":"BB12 7PN",
    "sg:province":"Lancashire",
    "sg:tags":[
        "agricultural"
    ],
    "wof:name":"Keith Roberts",
    "wof:placetype":"venue"
},
  "geometry": {"coordinates":[-2.3566699028,53.8063316345],"type":"Point"}
}