{
  "type": "Feature",
  "properties": {
    "iso:country":"GB",
    "sg:address":"115 Leam Terrace",
    "sg:city":"Leamington Spa",
    "sg:classifiers":[
        {
            "category":"Professional",
            "subcategory":"Printing & Photocopies",
            "type":"Services"
        },
        {
            "category":"Wholesale",
            "subcategory":"Books, Periodicals, & Newspapers",
            "type":"Manufacturing & Wholesale Goods"
        }
    ],
    "sg:phone":"+44 1926 831030",
    "sg:postcode":"CV31 1DF",
    "sg:province":"Warwickshire",
    "sg:tags":[
        "top",
        "publishing",
        "desk"
    ],
    "wof:name":"Bespoke Communications",
    "wof:placetype":"venue"
},
  "geometry": {"coordinates":[-1.520503,52.287498],"type":"Point"}
}