{
  "type": "Feature",
  "properties": {
    "addr:full":"24 Hills Road Cambridge Cambridgeshire CB2 1JW",
    "addr:housenumber":"24",
    "addr:postcode":"cb2 1jw",
    "addr:street":"Hills Road",
    "iso:country":"GB",
    "sg:address":"24 Hills Road",
    "sg:city":"Cambridge",
    "sg:classifiers":[
        {
            "category":"Banks & Credit Unions",
            "subcategory":"Financial Services",
            "type":"Services"
        }
    ],
    "sg:phone":"+44 1223 464146",
    "sg:postcode":"CB2 1JW",
    "sg:province":"Cambridgeshire",
    "sg:tags":[
        "adviser"
    ],
    "wof:name":"Bradford & Bingley Dormant 29 Ltd.",
    "wof:placetype":"venue"
},
  "geometry": {"coordinates":[0.1287010014,52.19764328],"type":"Point"}
}