{
  "type": "Feature",
  "properties": {
    "iso:country":"GB",
    "sg:address":"7c Spring Hill Industrial Estate, Colliers Way Arley",
    "sg:city":"Coventry",
    "sg:classifiers":[
        {
            "category":"Professional",
            "subcategory":"Engineering",
            "type":"Services"
        }
    ],
    "sg:phone":"+44 1676 542128",
    "sg:postcode":"CV7 8HN",
    "sg:province":"Warwickshire",
    "sg:tags":[
        "precision",
        "engineer"
    ],
    "wof:name":"P & G Engineering",
    "wof:placetype":"venue"
},
  "geometry": {"coordinates":[-1.5827089548,52.5031204224],"type":"Point"}
}