{
  "type": "Feature",
  "properties": {
    "addr:full":"243 Ryebank Road, Chorlton-cum-hardy Manchester Cheshire M21 9LX",
    "addr:housenumber":"243",
    "addr:postcode":"m21 9lx",
    "addr:street":"Ryebank Road",
    "iso:country":"GB",
    "sg:address":"243 Ryebank Road, Chorlton-cum-hardy",
    "sg:city":"Manchester",
    "sg:classifiers":[
        {
            "category":"Building & Trades",
            "subcategory":"Construction",
            "type":"Services"
        }
    ],
    "sg:phone":"+44 161 881 3971",
    "sg:postcode":"M21 9LX",
    "sg:province":"Cheshire",
    "sg:tags":[
        "decorator",
        "painter"
    ],
    "wof:name":"E Davies",
    "wof:placetype":"venue"
},
  "geometry": {"coordinates":[-2.288779,53.445068],"type":"Point"}
}