{
  "type": "Feature",
  "properties": {
    "iso:country":"GB",
    "sg:address":"7 Sapley Square",
    "sg:city":"Huntingdon",
    "sg:classifiers":[
        {
            "category":"Food & Beverages",
            "subcategory":"Fruits & Vegetables",
            "type":"Retail Goods"
        }
    ],
    "sg:postcode":"PE29 7LB",
    "sg:province":"Cambridgeshire",
    "sg:tags":[
        "greengrocer"
    ],
    "wof:name":"H P Samani",
    "wof:placetype":"venue"
},
  "geometry": {"coordinates":[-0.176560998,52.3456192017],"type":"Point"}
}