{
  "type": "Feature",
  "properties": {
    "iso:country":"GB",
    "sg:address":"Ty Gwyn, Manor Park",
    "sg:city":"Newport",
    "sg:classifiers":[
        {
            "category":"Building & Trades",
            "subcategory":"Construction",
            "type":"Services"
        }
    ],
    "sg:postcode":"NP11 4RT",
    "sg:province":"Blaenau Gwent",
    "sg:tags":[
        "joiner",
        "carpenter"
    ],
    "wof:name":"D Morgan Carpentry",
    "wof:placetype":"venue"
},
  "geometry": {"coordinates":[-3.1433999538,51.6738014221],"type":"Point"}
}