{
  "type": "Feature",
  "properties": {
    "addr:full":"Livesey Road, Ludborough Grimsby Lincolnshire DN36 5SF",
    "addr:postcode":"dn36 5sf",
    "addr:street":"Livesey Road",
    "iso:country":"GB",
    "sg:address":"Livesey Road, Ludborough",
    "sg:city":"Grimsby",
    "sg:classifiers":[
        {
            "category":"Bars & Pubs",
            "type":"Food & Drink"
        }
    ],
    "sg:phone":"+44 1472 840993",
    "sg:postcode":"DN36 5SF",
    "sg:province":"Lincolnshire",
    "sg:tags":[
        "pubs",
        "inn"
    ],
    "wof:name":"Livesey Arms",
    "wof:placetype":"venue"
},
  "geometry": {"coordinates":[-0.0506439991,53.4452781677],"type":"Point"}
}