{
  "type": "Feature",
  "properties": {
    "iso:country":"GB",
    "sg:address":"116 Malden Road, Kentish Town",
    "sg:city":"London",
    "sg:classifiers":[
        {
            "category":"Shopping",
            "subcategory":"Bicycles & Sporting Goods",
            "type":"Retail Goods"
        }
    ],
    "sg:phone":"+44 20 7485 1706",
    "sg:postcode":"NW5 4BY",
    "sg:province":"Greater London",
    "sg:tags":[
        "cycle",
        "accessory"
    ],
    "wof:name":"Simpsons Cycles",
    "wof:placetype":"venue"
},
  "geometry": {"coordinates":[-0.153339,51.549622],"type":"Point"}
}