{
  "type": "Feature",
  "properties": {
    "addr:full":"10 The Sq North Tawton Devon EX20 2EP",
    "addr:housenumber":"10;tawton",
    "addr:postcode":"ex20 2ep",
    "addr:street":"The Sq North",
    "iso:country":"GB",
    "sg:address":"10 The Sq",
    "sg:city":"North Tawton",
    "sg:classifiers":[
        {
            "category":"Real Estate",
            "subcategory":"Real Estate Agent",
            "type":"Services"
        }
    ],
    "sg:postcode":"EX20 2EP",
    "sg:province":"Devon",
    "wof:name":"N A Ramsay",
    "wof:placetype":"venue"
},
  "geometry": {"coordinates":[-3.897569,50.799332],"type":"Point"}
}