{
  "type": "Feature",
  "properties": {
    "iso:country":"GB",
    "sg:address":"36 Calton Avenue",
    "sg:city":"Hertford",
    "sg:classifiers":[
        {
            "category":"Social Services",
            "subcategory":"Adult Care",
            "type":"Services"
        },
        {
            "category":"Organizations",
            "subcategory":"Community Association",
            "type":"Services"
        }
    ],
    "sg:phone":"+44 1992 509385",
    "sg:postcode":"SG14 2ES",
    "sg:province":"Hertfordshire",
    "sg:tags":[
        "society",
        "housing",
        "sheltered"
    ],
    "wof:name":"Calton House",
    "wof:placetype":"venue"
},
  "geometry": {"coordinates":[-0.102578,51.800114],"type":"Point"}
}