{
  "type": "Feature",
  "properties": {
    "iso:country":"GB",
    "sg:address":"1166 Rochdale Road, Blackley",
    "sg:city":"Manchester",
    "sg:classifiers":[
        {
            "category":"Insurance",
            "subcategory":"Insurance Agent",
            "type":"Services"
        }
    ],
    "sg:phone":"+44 161 740 1558",
    "sg:postcode":"M9 6ER",
    "sg:province":"Greater Manchester",
    "wof:name":"Budget Retail Ltd.",
    "wof:placetype":"venue"
},
  "geometry": {"coordinates":[-2.208314,53.53194],"type":"Point"}
}