{
  "type": "Feature",
  "properties": {
    "addr:full":"Park View, Shibdon Road Blaydon-on-tyne Tyne and Wear NE21 5LU",
    "addr:postcode":"ne21 5lu",
    "addr:street":"Shibdon Road",
    "iso:country":"GB",
    "sg:address":"Park View, Shibdon Road",
    "sg:city":"Blaydon-on-tyne",
    "sg:classifiers":[
        {
            "category":"Farming",
            "subcategory":"Nursery",
            "type":"Manufacturing & Wholesale Goods"
        }
    ],
    "sg:postcode":"NE21 5LU",
    "sg:province":"Tyne and Wear",
    "sg:tags":[
        "creche"
    ],
    "wof:name":"Lakeside Children's Day Nursery",
    "wof:placetype":"venue"
},
  "geometry": {"coordinates":[-1.707943,54.963013],"type":"Point"}
}