{
  "type": "Feature",
  "properties": {
    "addr:full":"29-33 Battersea Rise London Greater London SW11 1HG",
    "addr:housenumber":"29-33",
    "addr:postcode":"sw11 1hg",
    "addr:street":"Battersea Rise",
    "iso:country":"GB",
    "sg:address":"29-33 Battersea Rise",
    "sg:city":"London",
    "sg:classifiers":[
        {
            "category":"Food & Beverages",
            "subcategory":"Groceries & Convenience Stores",
            "type":"Retail Goods"
        }
    ],
    "sg:phone":"+44 20 7924 3124",
    "sg:postcode":"SW11 1HG",
    "sg:province":"Greater London",
    "wof:name":"Cullens",
    "wof:placetype":"venue"
},
  "geometry": {"coordinates":[-0.16339,51.460892],"type":"Point"}
}