{
  "type": "Feature",
  "properties": {
    "addr:full":"211 Barton Street Gloucester Gloucestershire GL1 4HY",
    "addr:housenumber":"211",
    "addr:postcode":"gl1 4hy",
    "addr:street":"Barton Street",
    "iso:country":"GB",
    "sg:address":"211 Barton Street",
    "sg:city":"Gloucester",
    "sg:classifiers":[
        {
            "category":"Fast Food",
            "type":"Food & Drink"
        },
        {
            "category":"Restaurant",
            "type":"Food & Drink"
        }
    ],
    "sg:phone":"+44 1452 331246",
    "sg:postcode":"GL1 4HY",
    "sg:province":"Gloucestershire",
    "sg:tags":[
        "away",
        "indian",
        "-",
        "take"
    ],
    "wof:name":"Bengal Tandoori",
    "wof:placetype":"venue"
},
  "geometry": {"coordinates":[-2.233965,51.859352],"type":"Point"}
}