{
  "type": "Feature",
  "properties": {
    "iso:country":"GB",
    "sg:address":"Leicester Rd, Blaby",
    "sg:city":"Leicester",
    "sg:classifiers":[
        {
            "category":"Arena",
            "subcategory":"Sports Club",
            "type":"Entertainment"
        }
    ],
    "sg:phone":"+44 116 277 1210",
    "sg:postcode":"LE8 4GQ",
    "sg:province":"Leicestershire",
    "wof:name":"Blaby Bowling Club",
    "wof:placetype":"venue"
},
  "geometry": {"coordinates":[-1.163734,52.579407],"type":"Point"}
}