{
  "type": "Feature",
  "properties": {
    "iso:country":"GB",
    "sg:address":"Trinity College, Newent Close",
    "sg:city":"London",
    "sg:classifiers":[
        {
            "category":"Community Center",
            "subcategory":"Youth",
            "type":"Public Place"
        }
    ],
    "sg:postcode":"SE15 6EF",
    "sg:province":"Greater London",
    "sg:tags":[
        "children's",
        "activity"
    ],
    "wof:name":"Kingfisher Project",
    "wof:placetype":"venue"
},
  "geometry": {"coordinates":[-0.08296,51.4795],"type":"Point"}
}