{
  "type": "Feature",
  "properties": {
    "addr:full":"91 Grasmere Road Blackpool Lancashire FY1 5LU",
    "addr:housenumber":"91",
    "addr:postcode":"fy1 5lu",
    "addr:street":"Grasmere Road",
    "iso:country":"GB",
    "sg:address":"91 Grasmere Road",
    "sg:city":"Blackpool",
    "sg:classifiers":[
        {
            "category":"Home & Garden",
            "subcategory":"Hardware",
            "type":"Retail Goods"
        },
        {
            "category":"Building & Trades",
            "subcategory":"Construction",
            "type":"Services"
        }
    ],
    "sg:phone":"+44 1253 694637",
    "sg:postcode":"FY1 5LU",
    "sg:province":"Lancashire",
    "sg:tags":[
        "window",
        "retailer",
        "diy",
        "replacement"
    ],
    "wof:name":"Design Centre Diy",
    "wof:placetype":"venue"
},
  "geometry": {"coordinates":[-3.0403139591,53.8062210083],"type":"Point"}
}