{
  "type": "Feature",
  "properties": {
    "addr:full":"55 Bruntsfield Place Edinburgh City of Edinburgh EH10 4HQ",
    "addr:housenumber":"55",
    "addr:postcode":"eh10 4hq",
    "addr:street":"Bruntsfield Place Edinburgh",
    "iso:country":"GB",
    "sg:address":"55 Bruntsfield Place",
    "sg:city":"Edinburgh",
    "sg:classifiers":[
        {
            "category":"Retail",
            "subcategory":"Veterinary Services",
            "type":"Services"
        }
    ],
    "sg:postcode":"EH10 4HQ",
    "sg:province":"City of Edinburgh",
    "sg:tags":[
        "surgeon"
    ],
    "wof:name":"Kerr Henderson J G",
    "wof:placetype":"venue"
},
  "geometry": {"coordinates":[-3.2091770172,55.9360237122],"type":"Point"}
}