{
  "type": "Feature",
  "properties": {
    "addr:full":"24a Front St Stanley Durham DH9 6DS",
    "addr:housenumber":"24a",
    "addr:postcode":"dh9 6ds",
    "addr:street":"Front St",
    "iso:country":"GB",
    "sg:address":"24a Front St",
    "sg:city":"Stanley",
    "sg:classifiers":[
        {
            "category":"Manufacturing",
            "subcategory":"Petroleum Products",
            "type":"Manufacturing & Wholesale Goods"
        }
    ],
    "sg:phone":"+44 1207 234542",
    "sg:postcode":"DH9 6DS",
    "sg:province":"Durham",
    "sg:tags":[
        "double",
        "glazing"
    ],
    "wof:name":"View Windows & Property Repairs",
    "wof:placetype":"venue"
},
  "geometry": {"coordinates":[-1.66775,54.853642],"type":"Point"}
}