{
  "type": "Feature",
  "properties": {
    "addr:full":"210 Long La London Greater London SE1 4QB",
    "addr:housenumber":"210",
    "addr:postcode":"se1 4qb",
    "addr:street":"Long La",
    "iso:country":"GB",
    "sg:address":"210 Long La",
    "sg:city":"London",
    "sg:classifiers":[
        {
            "category":"Retail",
            "subcategory":"Auto Rental",
            "type":"Services"
        }
    ],
    "sg:postcode":"SE1 4QB",
    "sg:province":"Greater London",
    "sg:tags":[
        "truck",
        "hire",
        "van"
    ],
    "wof:name":"Evans,Andrew J,",
    "wof:placetype":"venue"
},
  "geometry": {"coordinates":[-0.084464,51.49852],"type":"Point"}
}