{
  "type": "Feature",
  "properties": {
    "addr:full":"61 Stone Road Broadstairs Kent CT10 1EB",
    "addr:housenumber":"61",
    "addr:postcode":"ct10 1eb",
    "addr:street":"Stone Road",
    "iso:country":"GB",
    "sg:address":"61 Stone Road",
    "sg:city":"Broadstairs",
    "sg:classifiers":[
        {
            "category":"Professional",
            "subcategory":"Art Services",
            "type":"Services"
        }
    ],
    "sg:phone":"+44 1843 867630",
    "sg:postcode":"CT10 1EB",
    "sg:province":"Kent",
    "sg:tags":[
        "photographer"
    ],
    "wof:name":"Starlight Studios",
    "wof:placetype":"venue"
},
  "geometry": {"coordinates":[1.4429359436,51.3658332825],"type":"Point"}
}