{
  "type": "Feature",
  "properties": {
    "addr:full":"Grincrete Ho, Whittle Rd Cardiff Cardiff CF1 8AT",
    "addr:postcode":"cf1 8at",
    "addr:street":"Whittle Rd",
    "iso:country":"GB",
    "sg:address":"Grincrete Ho, Whittle Rd",
    "sg:city":"Cardiff",
    "sg:classifiers":[
        {
            "category":"Professional",
            "subcategory":"Engineering",
            "type":"Services"
        }
    ],
    "sg:phone":"+44 29 2030 6000",
    "sg:postcode":"CF1 8AT",
    "sg:province":"Cardiff",
    "sg:tags":[
        "civil",
        "engineer"
    ],
    "wof:name":"M & N Group Of Companies",
    "wof:placetype":"venue"
},
  "geometry": {"coordinates":[-3.18067,51.481258],"type":"Point"}
}