{
  "type": "Feature",
  "properties": {
    "addr:full":"51h Middleshot Square Prestonpans East Lothian EH32 9RJ",
    "addr:postcode":"eh32 9rj",
    "addr:street":"Square Prestonpans",
    "iso:country":"GB",
    "sg:address":"51h Middleshot Square",
    "sg:city":"Prestonpans",
    "sg:classifiers":[
        {
            "category":"Building & Trades",
            "subcategory":"Construction",
            "type":"Services"
        }
    ],
    "sg:postcode":"EH32 9RJ",
    "sg:province":"East Lothian",
    "sg:tags":[
        "roofing"
    ],
    "wof:name":"Gourlay Construction Ltd.",
    "wof:placetype":"venue"
},
  "geometry": {"coordinates":[-2.967261,55.960213],"type":"Point"}
}