{
  "type": "Feature",
  "properties": {
    "iso:country":"GB",
    "sg:address":"Scotmid Catering Castle Rooms, 65 Old Mill Road",
    "sg:city":"Glasgow",
    "sg:classifiers":[
        {
            "category":"Food & Beverages",
            "subcategory":"Supermarket",
            "type":"Retail Goods"
        }
    ],
    "sg:phone":"+44 1698 810889",
    "sg:postcode":"G71 7PE",
    "sg:province":"Glasgow City",
    "wof:name":"Scotmid Co-Operative Society",
    "wof:placetype":"venue"
},
  "geometry": {"coordinates":[-4.08151,55.82048],"type":"Point"}
}