{
  "type": "Feature",
  "properties": {
    "iso:country":"GB",
    "sg:address":"303-305 Great Western Road",
    "sg:city":"Glasgow",
    "sg:classifiers":[
        {
            "category":"Shopping",
            "subcategory":"Department Store",
            "type":"Retail Goods"
        },
        {
            "category":"Food & Beverages",
            "subcategory":"Meat & Fish",
            "type":"Retail Goods"
        }
    ],
    "sg:phone":"+44 141 334 8133",
    "sg:postcode":"G4 9HR",
    "sg:province":"Glasgow City",
    "sg:tags":[
        "butcher"
    ],
    "wof:name":"Oriental Foods",
    "wof:placetype":"venue"
},
  "geometry": {"coordinates":[-4.2748188972,55.8731613159],"type":"Point"}
}