{
  "type": "Feature",
  "properties": {
    "addr:full":"72 Cornwall Street Plymouth Devon PL1 1LR",
    "addr:housenumber":"72",
    "addr:postcode":"pl1 1lr",
    "addr:street":"Cornwall Street",
    "iso:country":"GB",
    "sg:address":"72 Cornwall Street",
    "sg:city":"Plymouth",
    "sg:classifiers":[
        {
            "category":"Restaurant",
            "type":"Food & Drink"
        }
    ],
    "sg:phone":"+44 1752 660541",
    "sg:postcode":"PL1 1LR",
    "sg:province":"Devon",
    "wof:name":"Wimpy International Ltd.",
    "wof:placetype":"venue"
},
  "geometry": {"coordinates":[-4.1439170837,50.3724937439],"type":"Point"}
}