{
  "type": "Feature",
  "properties": {
    "addr:full":"1 Albert Street Kirkwall Orkney Islands KW15 1HP",
    "addr:housenumber":"1",
    "addr:postcode":"kw15 1hp",
    "addr:street":"Albert Street",
    "iso:country":"GB",
    "sg:address":"1 Albert Street",
    "sg:city":"Kirkwall",
    "sg:classifiers":[
        {
            "category":"Shopping",
            "subcategory":"Department Store",
            "type":"Retail Goods"
        }
    ],
    "sg:postcode":"KW15 1HP",
    "sg:province":"Orkney Islands",
    "wof:name":"Leonards",
    "wof:placetype":"venue"
},
  "geometry": {"coordinates":[-2.958057,58.98362],"type":"Point"}
}