{
  "type": "Feature",
  "properties": {
    "addr:full":"52 High Street Swanage Dorset BH19 2NX",
    "addr:housenumber":"52",
    "addr:postcode":"bh19 2nx",
    "addr:street":"High Street",
    "iso:country":"GB",
    "sg:address":"52 High Street",
    "sg:city":"Swanage",
    "sg:classifiers":[
        {
            "category":"Bars & Pubs",
            "subcategory":"Wine Bar",
            "type":"Food & Drink"
        }
    ],
    "sg:phone":"+44 1929 422781",
    "sg:postcode":"BH19 2NX",
    "sg:province":"Dorset",
    "wof:name":"Tawny's Wine Bar",
    "wof:placetype":"venue"
},
  "geometry": {"coordinates":[-1.958527,50.608444],"type":"Point"}
}