{
  "type": "Feature",
  "properties": {
    "addr:full":"16 Gordon St Edinburgh City of Edinburgh EH6 8NA",
    "addr:housenumber":"16",
    "addr:postcode":"eh6 8na",
    "addr:street":"Gordon St Edinburgh",
    "iso:country":"GB",
    "sg:address":"16 Gordon St",
    "sg:city":"Edinburgh",
    "sg:classifiers":[
        {
            "category":"Retail",
            "subcategory":"Auto Repair",
            "type":"Services"
        }
    ],
    "sg:postcode":"EH6 8NA",
    "sg:province":"City of Edinburgh",
    "sg:tags":[
        "modification",
        "garage"
    ],
    "wof:name":"Flockhart,Graeme,",
    "wof:placetype":"venue"
},
  "geometry": {"coordinates":[-3.1708459854,55.9683418274],"type":"Point"}
}