{
  "type": "Feature",
  "properties": {
    "addr:full":"Bedford Heights, Brickhill Drive Bedford Bedfordshire MK41 7PH",
    "addr:postcode":"mk41 7ph",
    "addr:street":"Heights Brickhill Drive",
    "iso:country":"GB",
    "sg:address":"Bedford Heights, Brickhill Drive",
    "sg:city":"Bedford",
    "sg:classifiers":[
        {
            "category":"Professional",
            "subcategory":"Printing & Photocopies",
            "type":"Services"
        }
    ],
    "sg:phone":"+44 1234 218642",
    "sg:postcode":"MK41 7PH",
    "sg:province":"Bedfordshire",
    "sg:tags":[
        "printer"
    ],
    "wof:name":"Sapphire Print Services Ltd.",
    "wof:placetype":"venue"
},
  "geometry": {"coordinates":[-0.48589,52.146622],"type":"Point"}
}