{
  "type": "Feature",
  "properties": {
    "iso:country":"GB",
    "sg:address":"588 Warwick Rd, Tyseley",
    "sg:city":"Birmingham",
    "sg:classifiers":[
        {
            "category":"Professional",
            "subcategory":"Computer Services",
            "type":"Services"
        }
    ],
    "sg:phone":"+44 121 707 4594",
    "sg:postcode":"B11 2HR",
    "sg:province":"West Midlands",
    "sg:tags":[
        "system",
        "software"
    ],
    "wof:name":"P & S Communications",
    "wof:placetype":"venue"
},
  "geometry": {"coordinates":[-1.84856,52.453449],"type":"Point"}
}