{
  "type": "Feature",
  "properties": {
    "addr:full":"Albert Rd, Bollington Macclesfield Cheshire SK10 5HS",
    "addr:postcode":"sk10 5hs",
    "addr:street":"Albert Rd",
    "iso:country":"GB",
    "sg:address":"Albert Rd, Bollington",
    "sg:city":"Macclesfield",
    "sg:classifiers":[
        {
            "category":"Education",
            "subcategory":"School",
            "type":"Public Place"
        }
    ],
    "sg:phone":"+44 1625 572767",
    "sg:postcode":"SK10 5HS",
    "sg:province":"Cheshire",
    "sg:tags":[
        "local",
        "authority"
    ],
    "wof:name":"Dean Valley Primary School",
    "wof:placetype":"venue"
},
  "geometry": {"coordinates":[-2.1103689671,53.2933883667],"type":"Point"}
}