{
  "type": "Feature",
  "properties": {
    "addr:full":"10 Friar Street Worcester Worcestershire WR1 2LZ",
    "addr:housenumber":"10",
    "addr:postcode":"wr1 2lz",
    "addr:street":"Friar Street",
    "iso:country":"GB",
    "sg:address":"10 Friar Street",
    "sg:city":"Worcester",
    "sg:classifiers":[
        {
            "category":"Sports & Exercise",
            "subcategory":"Sports Center",
            "type":"Entertainment"
        }
    ],
    "sg:phone":"+44 1905 726058",
    "sg:postcode":"WR1 2LZ",
    "sg:province":"Worcestershire",
    "sg:tags":[
        "shop",
        "good"
    ],
    "wof:name":"Dirty Habits Clothing Co",
    "wof:placetype":"venue"
},
  "geometry": {"coordinates":[-2.2191340923,52.1906738281],"type":"Point"}
}