{
  "type": "Feature",
  "properties": {
    "addr:full":"58 Churchill Close Bristol Gloucestershire BS30 7BW",
    "addr:housenumber":"58",
    "addr:postcode":"bs30 7bw",
    "addr:street":"Churchill Close",
    "iso:country":"GB",
    "sg:address":"58 Churchill Close",
    "sg:city":"Bristol",
    "sg:classifiers":[
        {
            "category":"Building & Trades",
            "subcategory":"Plumbing",
            "type":"Services"
        }
    ],
    "sg:phone":"+44 117 960 0304",
    "sg:postcode":"BS30 7BW",
    "sg:province":"Gloucestershire",
    "sg:tags":[
        "heating"
    ],
    "wof:name":"R Lane & Son",
    "wof:placetype":"venue"
},
  "geometry": {"coordinates":[-2.489798,51.448414],"type":"Point"}
}