{
  "type": "Feature",
  "properties": {
    "addr:full":"232-234 London Road Sheffield South Yorkshire S2 4LW",
    "addr:housenumber":"232-234",
    "addr:postcode":"s2 4lw",
    "addr:street":"London Road",
    "iso:country":"GB",
    "sg:address":"232-234 London Road",
    "sg:city":"Sheffield",
    "sg:classifiers":[
        {
            "category":"Home & Garden",
            "subcategory":"Furniture",
            "type":"Retail Goods"
        }
    ],
    "sg:postcode":"S2 4LW",
    "sg:province":"South Yorkshire",
    "wof:name":"Furnishings Direct",
    "wof:placetype":"venue"
},
  "geometry": {"coordinates":[-1.476148963,53.3678894043],"type":"Point"}
}