{
  "type": "Feature",
  "properties": {
    "addr:full":"Uxbridge Scout Hall, Gatting Way, Off Park Road Uxbridge Buckinghamshire UB8 1ES",
    "addr:postcode":"ub8 1es",
    "addr:street":"Gatting Way Off Park Road",
    "iso:country":"GB",
    "sg:address":"Uxbridge Scout Hall, Gatting Way, Off Park Road",
    "sg:city":"Uxbridge",
    "sg:classifiers":[
        {
            "category":"Farming",
            "subcategory":"Nursery",
            "type":"Manufacturing & Wholesale Goods"
        }
    ],
    "sg:phone":"+44 1895 274206",
    "sg:postcode":"UB8 1ES",
    "sg:province":"Buckinghamshire",
    "sg:tags":[
        "creche"
    ],
    "wof:name":"Activity Day Nursery",
    "wof:placetype":"venue"
},
  "geometry": {"coordinates":[-0.4745360017,51.5440711975],"type":"Point"}
}