{
  "type": "Feature",
  "properties": {
    "addr:full":"36 King Street Bathgate West Lothian EH48 1AX",
    "addr:housenumber":"36",
    "addr:postcode":"eh48 1ax",
    "addr:street":"King Street Bathgate",
    "iso:country":"GB",
    "sg:address":"36 King Street",
    "sg:city":"Bathgate",
    "sg:classifiers":[
        {
            "category":"Education",
            "subcategory":"Special Training",
            "type":"Public Place"
        }
    ],
    "sg:postcode":"EH48 1AX",
    "sg:province":"West Lothian",
    "sg:tags":[
        "product",
        "centre"
    ],
    "wof:name":"Bathgate Employment Rights Group",
    "wof:placetype":"venue"
},
  "geometry": {"coordinates":[-3.639654,55.899685],"type":"Point"}
}