{
  "type": "Feature",
  "properties": {
    "addr:full":"4 Chapel Street, Rutherglen Glasgow Glasgow City G73 1JE",
    "addr:housenumber":"4",
    "addr:postcode":"g73 1je",
    "addr:street":"Chapel Street",
    "iso:country":"GB",
    "sg:address":"4 Chapel Street, Rutherglen",
    "sg:city":"Glasgow",
    "sg:classifiers":[
        {
            "category":"Personal",
            "subcategory":"Beauty Salon",
            "type":"Services"
        }
    ],
    "sg:phone":"+44 141 647 9245",
    "sg:postcode":"G73 1JE",
    "sg:province":"Glasgow City",
    "sg:tags":[
        "unisex",
        "hairdresser"
    ],
    "wof:name":"Silki Salon",
    "wof:placetype":"venue"
},
  "geometry": {"coordinates":[-4.220787,55.828854],"type":"Point"}
}