{
  "type": "Feature",
  "properties": {
    "addr:full":"12 Station Rd Manchester Cheshire M41 9JN",
    "addr:housenumber":"12",
    "addr:postcode":"m41 9jn",
    "addr:street":"Station Rd",
    "iso:country":"GB",
    "sg:address":"12 Station Rd",
    "sg:city":"Manchester",
    "sg:classifiers":[
        {
            "category":"Food & Beverages",
            "subcategory":"Meat & Fish",
            "type":"Retail Goods"
        }
    ],
    "sg:phone":"+44 161 747 8206",
    "sg:postcode":"M41 9JN",
    "sg:province":"Cheshire",
    "sg:tags":[
        "chip"
    ],
    "wof:name":"Seaking",
    "wof:placetype":"venue"
},
  "geometry": {"coordinates":[-2.3531289101,53.4476203918],"type":"Point"}
}