{
  "type": "Feature",
  "properties": {
    "iso:country":"GB",
    "sg:address":"37 Medway Drive, Kearsley",
    "sg:city":"Bolton",
    "sg:classifiers":[
        {
            "category":"Manufacturing",
            "subcategory":"Building Materials",
            "type":"Manufacturing & Wholesale Goods"
        }
    ],
    "sg:phone":"+44 1204 862070",
    "sg:postcode":"BL4 8PJ",
    "sg:province":"Lancashire",
    "sg:tags":[
        "tarmac",
        "asphalt"
    ],
    "wof:name":"Farnworth Asphalt",
    "wof:placetype":"venue"
},
  "geometry": {"coordinates":[-2.3695559502,53.5361747742],"type":"Point"}
}