{
  "type": "Feature",
  "properties": {
    "addr:full":"45 Station Road Clacton-on-sea Essex CO15 1SD",
    "addr:housenumber":"45",
    "addr:postcode":"co15 1sd",
    "addr:street":"Station Road",
    "iso:country":"GB",
    "sg:address":"45 Station Road",
    "sg:city":"Clacton-on-sea",
    "sg:classifiers":[
        {
            "category":"Real Estate",
            "subcategory":"Real Estate Agent",
            "type":"Services"
        }
    ],
    "sg:phone":"+44 1255 222882",
    "sg:postcode":"CO15 1SD",
    "sg:province":"Essex",
    "wof:name":"Omega Property Services",
    "wof:placetype":"venue"
},
  "geometry": {"coordinates":[1.1534429789,51.7905273438],"type":"Point"}
}