{
  "type": "Feature",
  "properties": {
    "addr:full":"Shawlands Arcade, Kilmarnock Road Glasgow Glasgow City G41 3NN",
    "addr:postcode":"g41 3nn",
    "addr:street":"Kilmarnock Road",
    "iso:country":"GB",
    "sg:address":"Shawlands Arcade, Kilmarnock Road",
    "sg:city":"Glasgow",
    "sg:classifiers":[
        {
            "category":"Bars & Pubs",
            "type":"Food & Drink"
        },
        {
            "category":"Community Center",
            "subcategory":"Social",
            "type":"Public Place"
        }
    ],
    "sg:phone":"+44 141 636 9024",
    "sg:postcode":"G41 3NN",
    "sg:province":"Glasgow City",
    "sg:tags":[
        "pubs",
        "house",
        "inn",
        "activity"
    ],
    "wof:name":"The Sir John Stirling Maxwell",
    "wof:placetype":"venue"
},
  "geometry": {"coordinates":[-4.2841801643,55.8278999329],"type":"Point"}
}