{
  "type": "Feature",
  "properties": {
    "iso:country":"GB",
    "sg:address":"6 Oakdene, Killay",
    "sg:city":"Swansea",
    "sg:classifiers":[
        {
            "category":"Banks & Credit Unions",
            "subcategory":"Financial Services",
            "type":"Services"
        }
    ],
    "sg:phone":"+44 1792 299341",
    "sg:postcode":"SA2 7RX",
    "sg:province":"Swansea",
    "sg:tags":[
        "consultant"
    ],
    "wof:name":"Oakdene Finance Ltd.",
    "wof:placetype":"venue"
},
  "geometry": {"coordinates":[-4.0309200287,51.6203536987],"type":"Point"}
}