{
  "type": "Feature",
  "properties": {
    "addr:full":"79 Falsgrave Road Scarborough North Yorkshire YO12 5EA",
    "addr:housenumber":"79",
    "addr:postcode":"yo12 5ea",
    "addr:street":"Falsgrave Road",
    "iso:country":"GB",
    "sg:address":"79 Falsgrave Road",
    "sg:city":"Scarborough",
    "sg:classifiers":[
        {
            "category":"Personal",
            "type":"Services"
        }
    ],
    "sg:phone":"+44 1723 363851",
    "sg:postcode":"YO12 5EA",
    "sg:province":"North Yorkshire",
    "sg:tags":[
        "tailor"
    ],
    "wof:name":"Proles Ladies & Gents Tailoring",
    "wof:placetype":"venue"
},
  "geometry": {"coordinates":[-0.4126139879,54.2772407532],"type":"Point"}
}