{
  "type": "Feature",
  "properties": {
    "addr:full":"Unit 4 Linthwaite Business Centr, E Huddersfield West Yorkshire HD7 5QS",
    "addr:housenumber":"unit 4",
    "addr:postcode":"hd7 5qs",
    "addr:street":"Linthwaite Business Centr E Huddersfield West",
    "iso:country":"GB",
    "sg:address":"Unit 4 Linthwaite Business Centr, E",
    "sg:city":"Huddersfield",
    "sg:classifiers":[
        {
            "category":"Retail",
            "subcategory":"Auto Repair",
            "type":"Services"
        }
    ],
    "sg:postcode":"HD7 5QS",
    "sg:province":"West Yorkshire",
    "sg:tags":[
        "modification",
        "garage"
    ],
    "wof:name":"J N H Autos",
    "wof:placetype":"venue"
},
  "geometry": {"coordinates":[-1.8524099588,53.6281890869],"type":"Point"}
}