{
  "type": "Feature",
  "properties": {
    "iso:country":"GB",
    "sg:address":"Braevail, Lethen",
    "sg:city":"Nairn",
    "sg:classifiers":[
        {
            "category":"Professional",
            "type":"Services"
        },
        {
            "category":"Banks & Credit Unions",
            "subcategory":"Investment Brokerage",
            "type":"Services"
        }
    ],
    "sg:phone":"+44 1667 452719",
    "sg:postcode":"IV12 5LD",
    "sg:province":"Highland",
    "sg:tags":[
        "farm",
        "agricultural",
        "contractor"
    ],
    "wof:name":"Peter Murray Smart",
    "wof:placetype":"venue"
},
  "geometry": {"coordinates":[-3.8767089844,57.5832138062],"type":"Point"}
}