{
  "type": "Feature",
  "properties": {
    "addr:full":"117-118 Western Road Hove East Sussex BN3 1DB",
    "addr:housenumber":"117-118",
    "addr:postcode":"bn3 1db",
    "addr:street":"Western Road",
    "iso:country":"GB",
    "sg:address":"117-118 Western Road",
    "sg:city":"Hove",
    "sg:classifiers":[
        {
            "category":"Professional",
            "subcategory":"Employment Agencies",
            "type":"Services"
        }
    ],
    "sg:phone":"+44 1273 777844",
    "sg:postcode":"BN3 1DB",
    "sg:province":"East Sussex",
    "sg:tags":[
        "modelling"
    ],
    "wof:name":"Cyber Stars Model Agency",
    "wof:placetype":"venue"
},
  "geometry": {"coordinates":[-0.1572850049,50.8255195618],"type":"Point"}
}