{
  "type": "Feature",
  "properties": {
    "iso:country":"GB",
    "sg:address":"16 Fleet Street",
    "sg:city":"London",
    "sg:classifiers":[
        {
            "category":"Shopping",
            "subcategory":"Books",
            "type":"Retail Goods"
        }
    ],
    "sg:phone":"+44 20 7353 3907",
    "sg:postcode":"EC4Y 1AU",
    "sg:province":"Greater London",
    "sg:tags":[
        "bookseller"
    ],
    "wof:name":"Wildy & Sons Ltd.",
    "wof:placetype":"venue"
},
  "geometry": {"coordinates":[-0.108331,51.514153],"type":"Point"}
}