{
  "type": "Feature",
  "properties": {
    "iso:country":"GB",
    "sg:address":"66 Percival Road",
    "sg:city":"Eastbourne",
    "sg:classifiers":[
        {
            "category":"Building & Trades",
            "subcategory":"Construction",
            "type":"Services"
        }
    ],
    "sg:postcode":"BN22 9JN",
    "sg:province":"East Sussex",
    "sg:tags":[
        "decorator",
        "painter"
    ],
    "wof:name":"E W Decorations",
    "wof:placetype":"venue"
},
  "geometry": {"coordinates":[0.277737,50.803131],"type":"Point"}
}