{
  "type": "Feature",
  "properties": {
    "iso:country":"GB",
    "sg:address":"277 Staines Rd",
    "sg:city":"Hounslow",
    "sg:classifiers":[
        {
            "category":"Arts & Performance",
            "subcategory":"Music",
            "type":"Entertainment"
        }
    ],
    "sg:phone":"+44 20 8569 4203",
    "sg:postcode":"TW3 3JJ",
    "sg:province":"Greater London",
    "sg:tags":[
        "mobile",
        "disco"
    ],
    "wof:name":"Rapid Sounds",
    "wof:placetype":"venue"
},
  "geometry": {"coordinates":[-0.378083,51.46537],"type":"Point"}
}