{
  "type": "Feature",
  "properties": {
    "iso:country":"GB",
    "sg:address":"Longfield Shopping Centre, Prestwich",
    "sg:city":"Manchester",
    "sg:classifiers":[
        {
            "category":"Food & Beverages",
            "subcategory":"Supermarket",
            "type":"Retail Goods"
        }
    ],
    "sg:phone":"+44 161 798 8068",
    "sg:postcode":"M25 5AY",
    "sg:province":"Greater Manchester",
    "wof:name":"Sainsbury's Supermarkets Ltd.",
    "wof:placetype":"venue"
},
  "geometry": {"coordinates":[-2.2730801105,53.5354804993],"type":"Point"}
}