{
  "type": "Feature",
  "properties": {
    "addr:full":"46 The Bdwy Haywards Heath East Sussex RH16 3AL",
    "addr:housenumber":"46",
    "addr:postcode":"rh16 3al",
    "addr:street":"The Bdwy",
    "iso:country":"GB",
    "sg:address":"46 The Bdwy",
    "sg:city":"Haywards Heath",
    "sg:classifiers":[
        {
            "category":"Banks & Credit Unions",
            "subcategory":"Financial Services",
            "type":"Services"
        }
    ],
    "sg:phone":"+44 1444 412334",
    "sg:postcode":"RH16 3AL",
    "sg:province":"East Sussex",
    "sg:tags":[
        "building",
        "society"
    ],
    "wof:name":"Yorkshire Building Society",
    "wof:placetype":"venue"
},
  "geometry": {"coordinates":[-0.1057389975,51.0004043579],"type":"Point"}
}