{
  "type": "Feature",
  "properties": {
    "addr:full":"61 London Rd, Blackwater Camberley Hampshire GU17 0AB",
    "addr:housenumber":"61",
    "addr:postcode":"gu17 0ab",
    "addr:street":"London Rd",
    "iso:country":"GB",
    "sg:address":"61 London Rd, Blackwater",
    "sg:city":"Camberley",
    "sg:classifiers":[
        {
            "category":"Shopping",
            "subcategory":"Used Merchandise",
            "type":"Retail Goods"
        }
    ],
    "sg:postcode":"GU17 0AB",
    "sg:province":"Hampshire",
    "sg:tags":[
        "shop",
        "second-hand"
    ],
    "wof:name":"Caruana,Tony,",
    "wof:placetype":"venue"
},
  "geometry": {"coordinates":[-0.7817559838,51.3303184509],"type":"Point"}
}