{
  "type": "Feature",
  "properties": {
    "addr:full":"Unit 1 Acton Place Industrial Estate, Acton Sudbury Essex CO10 0BB",
    "addr:housenumber":"unit 1",
    "addr:postcode":"co10 0bb",
    "addr:street":"Acton Place Industrial Estate",
    "iso:country":"GB",
    "sg:address":"Unit 1 Acton Place Industrial Estate, Acton",
    "sg:city":"Sudbury",
    "sg:classifiers":[
        {
            "category":"Retail",
            "subcategory":"Auto Repair",
            "type":"Services"
        }
    ],
    "sg:postcode":"CO10 0BB",
    "sg:province":"Essex",
    "sg:tags":[
        "modification",
        "garage"
    ],
    "wof:name":"K & K Car Repairs",
    "wof:placetype":"venue"
},
  "geometry": {"coordinates":[0.7453650236,52.0618667603],"type":"Point"}
}