{
  "type": "Feature",
  "properties": {
    "iso:country":"GB",
    "sg:address":"27a Giles Close",
    "sg:city":"Birmingham",
    "sg:classifiers":[
        {
            "category":"Shopping",
            "subcategory":"Department Store",
            "type":"Retail Goods"
        }
    ],
    "sg:phone":"+44 121 783 7638",
    "sg:postcode":"B33 8DU",
    "sg:province":"West Midlands",
    "wof:name":"Jabbar & Sons",
    "wof:placetype":"venue"
},
  "geometry": {"coordinates":[-1.8040790558,52.481918335],"type":"Point"}
}