{
  "type": "Feature",
  "properties": {
    "addr:full":"52 Regent Quay Aberdeen Aberdeen City AB11 5AQ",
    "addr:housenumber":"52",
    "addr:postcode":"ab11 5aq",
    "addr:street":"Regent Quay",
    "iso:country":"GB",
    "sg:address":"52 Regent Quay",
    "sg:city":"Aberdeen",
    "sg:classifiers":[
        {
            "category":"Utilities",
            "subcategory":"Fuel Oil & Lpg",
            "type":"Services"
        }
    ],
    "sg:phone":"+44 1224 585009",
    "sg:postcode":"AB11 5AQ",
    "sg:province":"Aberdeen City",
    "sg:tags":[
        "gas"
    ],
    "wof:name":"Asset Geoscience",
    "wof:placetype":"venue"
},
  "geometry": {"coordinates":[-2.08945,57.146687],"type":"Point"}
}