{
  "type": "Feature",
  "properties": {
    "iso:country":"GB",
    "sg:address":"32 Hamilton Street",
    "sg:city":"Birkenhead",
    "sg:classifiers":[
        {
            "category":"Professional",
            "subcategory":"Computer Services",
            "type":"Services"
        }
    ],
    "sg:phone":"+44 151 647 4251",
    "sg:postcode":"CH41 5AD",
    "sg:province":"Merseyside",
    "sg:tags":[
        "information"
    ],
    "wof:name":"Wirral Community Health Council",
    "wof:placetype":"venue"
},
  "geometry": {"coordinates":[-3.015667,53.392544],"type":"Point"}
}