{
  "type": "Feature",
  "properties": {
    "iso:country":"GB",
    "sg:address":"131 Aldridge Road, Perry Barr",
    "sg:city":"Birmingham",
    "sg:classifiers":[
        {
            "category":"Travel",
            "subcategory":"Hotels & Motels",
            "type":"Entertainment"
        }
    ],
    "sg:phone":"+44 121 356 0707",
    "sg:postcode":"B42 2ET",
    "sg:province":"West Midlands",
    "wof:name":"Park Hotel",
    "wof:placetype":"venue"
},
  "geometry": {"coordinates":[-1.897142,52.522705],"type":"Point"}
}