{
  "type": "Feature",
  "properties": {
    "addr:full":"Norwich Road, Stonham Parva Stowmarket Suffolk IP14 5JY",
    "addr:postcode":"ip14 5jy",
    "addr:street":"Norwich Road",
    "iso:country":"GB",
    "sg:address":"Norwich Road, Stonham Parva",
    "sg:city":"Stowmarket",
    "sg:classifiers":[
        {
            "category":"Bars & Pubs",
            "type":"Food & Drink"
        },
        {
            "category":"Community Center",
            "subcategory":"Social",
            "type":"Public Place"
        }
    ],
    "sg:phone":"+44 1449 711287",
    "sg:postcode":"IP14 5JY",
    "sg:province":"Suffolk",
    "sg:tags":[
        "pubs",
        "house",
        "inn",
        "activity"
    ],
    "wof:name":"Magpie Inn",
    "wof:placetype":"venue"
},
  "geometry": {"coordinates":[0.996769,52.188625],"type":"Point"}
}