{
  "type": "Feature",
  "properties": {
    "addr:full":"Gwaefi Farm Carmarthen Carmarthenshire SA33 4EW",
    "addr:housenumber":"carmarthen",
    "addr:postcode":"sa33 4ew",
    "addr:street":"Carmarthenshire",
    "iso:country":"GB",
    "sg:address":"Gwaefi Farm",
    "sg:city":"Carmarthen",
    "sg:classifiers":[
        {
            "category":"Professional",
            "subcategory":"Engineering",
            "type":"Services"
        }
    ],
    "sg:phone":"+44 1994 230347",
    "sg:postcode":"SA33 4EW",
    "sg:province":"Carmarthenshire",
    "wof:name":"H J Lodwig",
    "wof:placetype":"venue"
},
  "geometry": {"coordinates":[-4.4943699837,51.8101806641],"type":"Point"}
}