{
  "type": "Feature",
  "properties": {
    "iso:country":"GB",
    "sg:address":"Millers Yard",
    "sg:city":"Market Harborough",
    "sg:classifiers":[
        {
            "category":"Retail",
            "subcategory":"Repair Shop",
            "type":"Services"
        }
    ],
    "sg:postcode":"LE16 7PW",
    "sg:province":"Leicestershire",
    "sg:tags":[
        "equipment",
        "catering"
    ],
    "wof:name":"Great Eastern Services",
    "wof:placetype":"venue"
},
  "geometry": {"coordinates":[-0.9419609904,52.4751243591],"type":"Point"}
}