{
  "type": "Feature",
  "properties": {
    "addr:full":"Jute Lane Enfield Greater London EN3 7PJ",
    "addr:postcode":"en3 7pj",
    "addr:street":"Jute Lane",
    "iso:country":"GB",
    "sg:address":"Jute Lane",
    "sg:city":"Enfield",
    "sg:classifiers":[
        {
            "category":"Freight",
            "type":"Transportation"
        }
    ],
    "sg:phone":"+44 20 8805 2535",
    "sg:postcode":"EN3 7PJ",
    "sg:province":"Greater London",
    "sg:tags":[
        "haulage",
        "transport",
        "road"
    ],
    "wof:name":"Foxton Roadway Services Ltd.",
    "wof:placetype":"venue"
},
  "geometry": {"coordinates":[-0.0299200006,51.6551399231],"type":"Point"}
}