{
  "type": "Feature",
  "properties": {
    "addr:full":"253 Victoria Road Lowestoft Suffolk NR33 9LP",
    "addr:housenumber":"253",
    "addr:postcode":"nr33 9lp",
    "addr:street":"Victoria Road",
    "iso:country":"GB",
    "sg:address":"253 Victoria Road",
    "sg:city":"Lowestoft",
    "sg:classifiers":[
        {
            "category":"Shopping",
            "subcategory":"Department Store",
            "type":"Retail Goods"
        }
    ],
    "sg:phone":"+44 1502 514503",
    "sg:postcode":"NR33 9LP",
    "sg:province":"Suffolk",
    "wof:name":"Vvt Victoria Superstore",
    "wof:placetype":"venue"
},
  "geometry": {"coordinates":[1.718134,52.471169],"type":"Point"}
}