{
  "type": "Feature",
  "properties": {
    "addr:full":"105 Brownhill Road, Catford London Greater London SE6 2HF",
    "addr:housenumber":"105",
    "addr:postcode":"se6 2hf",
    "addr:street":"Brownhill Road",
    "iso:country":"GB",
    "sg:address":"105 Brownhill Road, Catford",
    "sg:city":"London",
    "sg:classifiers":[
        {
            "category":"Shopping",
            "subcategory":"Computers & Home Electronics",
            "type":"Retail Goods"
        },
        {
            "category":"Communications",
            "type":"Services"
        }
    ],
    "sg:phone":"+44 20 8697 2644",
    "sg:postcode":"SE6 2HF",
    "sg:province":"Greater London",
    "sg:tags":[
        "tv",
        "radio",
        "television",
        "video",
        "sale"
    ],
    "wof:name":"B & E Hardman Ltd",
    "wof:placetype":"venue"
},
  "geometry": {"coordinates":[-0.0136019997,51.4455528259],"type":"Point"}
}