{
  "type": "Feature",
  "properties": {
    "addr:full":"14 Moor Centre Brierley Hill West Midlands DY5 3AH",
    "addr:housenumber":"14",
    "addr:postcode":"dy5 3ah",
    "addr:street":"Moor Centre Brierley Hill",
    "iso:country":"GB",
    "sg:address":"14 Moor Centre",
    "sg:city":"Brierley Hill",
    "sg:classifiers":[
        {
            "category":"Shopping",
            "subcategory":"Baby Store",
            "type":"Retail Goods"
        }
    ],
    "sg:phone":"+44 1384 483111",
    "sg:postcode":"DY5 3AH",
    "sg:province":"West Midlands",
    "sg:tags":[
        "babywear",
        "childrens"
    ],
    "wof:name":"Ethel Austin",
    "wof:placetype":"venue"
},
  "geometry": {"coordinates":[-2.1213009357,52.48204422],"type":"Point"}
}