{
  "type": "Feature",
  "properties": {
    "addr:full":"Chorley Road, Standish Wigan Lancashire WN1 2XN",
    "addr:postcode":"wn1 2xn",
    "addr:street":"Chorley Road",
    "iso:country":"GB",
    "sg:address":"Chorley Road, Standish",
    "sg:city":"Wigan",
    "sg:classifiers":[
        {
            "category":"Restaurant",
            "type":"Food & Drink"
        }
    ],
    "sg:phone":"+44 1257 472100",
    "sg:postcode":"WN1 2XN",
    "sg:province":"Lancashire",
    "wof:name":"Kilhey Court Hotel",
    "wof:placetype":"venue"
},
  "geometry": {"coordinates":[-2.637629,53.585636],"type":"Point"}
}