{
  "type": "Feature",
  "properties": {
    "iso:country":"GB",
    "sg:address":"17 Tangier Street",
    "sg:city":"Whitehaven",
    "sg:classifiers":[
        {
            "category":"Personal",
            "subcategory":"Beauty Salon",
            "type":"Services"
        }
    ],
    "sg:phone":"+44 1946 691834",
    "sg:postcode":"CA28 7UX",
    "sg:province":"Cumbria",
    "wof:name":"The Beauty Spot",
    "wof:placetype":"venue"
},
  "geometry": {"coordinates":[-3.5884540081,54.5497703552],"type":"Point"}
}