{
  "type": "Feature",
  "properties": {
    "iso:country":"GB",
    "sg:address":"149 Draycott Road, Breaston",
    "sg:city":"Derby",
    "sg:classifiers":[
        {
            "category":"Professional",
            "subcategory":"Engineering",
            "type":"Services"
        }
    ],
    "sg:phone":"+44 1332 873721",
    "sg:postcode":"DE72 3DB",
    "sg:province":"Derbyshire",
    "wof:name":"Harry Steer Engineering",
    "wof:placetype":"venue"
},
  "geometry": {"coordinates":[-1.331481,52.895775],"type":"Point"}
}