{
  "type": "Feature",
  "properties": {
    "addr:full":"Dolly Garth, Reeth Richmond Durham DL11 6QX",
    "addr:postcode":"dl11 6qx",
    "addr:street":"Dolly;Reeth",
    "iso:country":"GB",
    "sg:address":"Dolly Garth, Reeth",
    "sg:city":"Richmond",
    "sg:classifiers":[
        {
            "category":"Professional",
            "subcategory":"Testing Lab",
            "type":"Services"
        }
    ],
    "sg:phone":"+44 1748 884781",
    "sg:postcode":"DL11 6QX",
    "sg:province":"Durham",
    "sg:tags":[
        "inspection",
        "calibration"
    ],
    "wof:name":"David Skinner & Partners",
    "wof:placetype":"venue"
},
  "geometry": {"coordinates":[-1.942514,54.389191],"type":"Point"}
}