{
  "type": "Feature",
  "properties": {
    "addr:full":"93 Walkergate Beverley East Riding of Yorkshire HU17 9BP",
    "addr:housenumber":"93",
    "addr:postcode":"hu17 9bp",
    "addr:street":"Walkergate Beverley",
    "iso:country":"GB",
    "sg:address":"93 Walkergate",
    "sg:city":"Beverley",
    "sg:classifiers":[
        {
            "category":"Personal",
            "subcategory":"Beauty Salon",
            "type":"Services"
        }
    ],
    "sg:phone":"+44 1482 882689",
    "sg:postcode":"HU17 9BP",
    "sg:province":"East Riding of Yorkshire",
    "sg:tags":[
        "unisex",
        "hairdresser"
    ],
    "wof:name":"Rootz",
    "wof:placetype":"venue"
},
  "geometry": {"coordinates":[-0.4290159941,53.8425636292],"type":"Point"}
}