{
  "type": "Feature",
  "properties": {
    "iso:country":"GB",
    "sg:address":"42 Camdan St, Hockley",
    "sg:city":"Birmingham",
    "sg:classifiers":[
        {
            "category":"Retail",
            "subcategory":"Auto Repair",
            "type":"Services"
        }
    ],
    "sg:postcode":"B1 3BN",
    "sg:province":"West Midlands",
    "sg:tags":[
        "modification",
        "garage"
    ],
    "wof:name":"Morrell,Alan,",
    "wof:placetype":"venue"
},
  "geometry": {"coordinates":[-1.9128890038,52.483127594],"type":"Point"}
}