{
  "type": "Feature",
  "properties": {
    "addr:full":"Malton Industrial Estate, Showfield Lane Malton North Yorkshire YO17 6BT",
    "addr:postcode":"yo17 6bt",
    "addr:street":"Estate Showfield Lane",
    "iso:country":"GB",
    "sg:address":"Malton Industrial Estate, Showfield Lane",
    "sg:city":"Malton",
    "sg:classifiers":[
        {
            "category":"Building & Trades",
            "subcategory":"Cleaning & Sanitation",
            "type":"Services"
        }
    ],
    "sg:postcode":"YO17 6BT",
    "sg:province":"North Yorkshire",
    "sg:tags":[
        "hygiene",
        "cleansing"
    ],
    "wof:name":"B & W (Hygiene Services) Ltd.",
    "wof:placetype":"venue"
},
  "geometry": {"coordinates":[-0.788043,54.146866],"type":"Point"}
}