{
  "type": "Feature",
  "properties": {
    "addr:full":"Wharf House, Wharf Street Newbury Berkshire RG14 5AP",
    "addr:postcode":"rg14 5ap",
    "addr:street":"Wharf Street",
    "iso:country":"GB",
    "sg:address":"Wharf House, Wharf Street",
    "sg:city":"Newbury",
    "sg:classifiers":[
        {
            "category":"Professional",
            "subcategory":"Computer Services",
            "type":"Services"
        }
    ],
    "sg:phone":"+44 1635 41100",
    "sg:postcode":"RG14 5AP",
    "sg:province":"Berkshire",
    "sg:tags":[
        "system",
        "software"
    ],
    "wof:name":"Hyperformix Ltd.",
    "wof:placetype":"venue"
},
  "geometry": {"coordinates":[-1.3258719444,51.405872345],"type":"Point"}
}