{
  "type": "Feature",
  "properties": {
    "addr:full":"370 Green Lanes London Greater London N13 5PE",
    "addr:housenumber":"370",
    "addr:postcode":"n13 5pe",
    "addr:street":"Green Lanes",
    "iso:country":"GB",
    "sg:address":"370 Green Lanes",
    "sg:city":"London",
    "sg:classifiers":[
        {
            "category":"Shopping",
            "subcategory":"Florist",
            "type":"Retail Goods"
        }
    ],
    "sg:phone":"+44 20 8882 4660",
    "sg:postcode":"N13 5PE",
    "sg:province":"Greater London",
    "wof:name":"Flowerzone",
    "wof:placetype":"venue"
},
  "geometry": {"coordinates":[-0.106011,51.620758],"type":"Point"}
}