{
  "type": "Feature",
  "properties": {
    "addr:full":"11 Crown Street Hebden Bridge West Yorkshire HX7 8EL",
    "addr:housenumber":"11",
    "addr:postcode":"hx7 8el",
    "addr:street":"Crown Street",
    "iso:country":"GB",
    "sg:address":"11 Crown Street",
    "sg:city":"Hebden Bridge",
    "sg:classifiers":[
        {
            "category":"Shopping",
            "subcategory":"Gifts & Souvenirs",
            "type":"Retail Goods"
        }
    ],
    "sg:phone":"+44 1422 845620",
    "sg:postcode":"HX7 8EL",
    "sg:province":"West Yorkshire",
    "sg:tags":[
        "shop"
    ],
    "wof:name":"Past & Present Gifts",
    "wof:placetype":"venue"
},
  "geometry": {"coordinates":[-2.0129380226,53.7415084839],"type":"Point"}
}