{
  "type": "Feature",
  "properties": {
    "iso:country":"GB",
    "sg:address":"Selecta Post 6, Ring Road - Middleton",
    "sg:city":"Leeds",
    "sg:classifiers":[
        {
            "category":"Education",
            "subcategory":"University",
            "type":"Public Place"
        }
    ],
    "sg:phone":"+44 113 247 6360",
    "sg:postcode":"LS10 4AX",
    "sg:province":"West Yorkshire",
    "sg:tags":[
        "higher"
    ],
    "wof:name":"Dept. of Highways & Transport",
    "wof:placetype":"venue"
},
  "geometry": {"coordinates":[-1.5478240252,53.7483139038],"type":"Point"}
}