{
  "type": "Feature",
  "properties": {
    "addr:full":"2 Cannon Street Hull East Riding of Yorkshire HU2 0AB",
    "addr:housenumber":"2",
    "addr:postcode":"hu2 0ab",
    "addr:street":"Cannon Street",
    "iso:country":"GB",
    "sg:address":"2 Cannon Street",
    "sg:city":"Hull",
    "sg:classifiers":[
        {
            "category":"Farming",
            "subcategory":"Farm",
            "type":"Manufacturing & Wholesale Goods"
        }
    ],
    "sg:phone":"+44 1482 223446",
    "sg:postcode":"HU2 0AB",
    "sg:province":"East Riding of Yorkshire",
    "sg:tags":[
        "agricultural"
    ],
    "wof:name":"M & D Jenkins Industrial Suppliers",
    "wof:placetype":"venue"
},
  "geometry": {"coordinates":[-0.337927,53.751244],"type":"Point"}
}