{
  "type": "Feature",
  "properties": {
    "addr:full":"Grange Primary School, Grange Road, Monifieth Dundee Angus DD5 4LU",
    "addr:postcode":"dd5 4lu",
    "addr:street":"Grange Road",
    "iso:country":"GB",
    "sg:address":"Grange Primary School, Grange Road, Monifieth",
    "sg:city":"Dundee",
    "sg:classifiers":[
        {
            "category":"Social Services",
            "subcategory":"Child Care",
            "type":"Services"
        }
    ],
    "sg:phone":"+44 1382 533996",
    "sg:postcode":"DD5 4LU",
    "sg:province":"Angus",
    "sg:tags":[
        "childminders"
    ],
    "wof:name":"Monifieth Out of School Care Club",
    "wof:placetype":"venue"
},
  "geometry": {"coordinates":[-2.8200309277,56.4804039001],"type":"Point"}
}