{
  "type": "Feature",
  "properties": {
    "iso:country":"GB",
    "sg:address":"21 Milford Road",
    "sg:city":"Reading",
    "sg:classifiers":[
        {
            "category":"Retail",
            "subcategory":"Auto Repair",
            "type":"Services"
        }
    ],
    "sg:phone":"+44 118 967 7799",
    "sg:postcode":"RG1 8LG",
    "sg:province":"Berkshire",
    "sg:tags":[
        "engine",
        "specialist",
        "diagnostic",
        "tuning",
        "car"
    ],
    "wof:name":"Clifford Cox Engineering",
    "wof:placetype":"venue"
},
  "geometry": {"coordinates":[-0.981164,51.463554],"type":"Point"}
}