{
  "type": "Feature",
  "properties": {
    "addr:full":"The Sheiling, The Camps Kirknewton City of Edinburgh EH27 8DN",
    "addr:postcode":"eh27 8dn",
    "iso:country":"GB",
    "sg:address":"The Sheiling, The Camps",
    "sg:city":"Kirknewton",
    "sg:classifiers":[
        {
            "category":"Professional",
            "subcategory":"Engineering",
            "type":"Services"
        }
    ],
    "sg:phone":"+44 1506 881253",
    "sg:postcode":"EH27 8DN",
    "sg:province":"City of Edinburgh",
    "wof:name":"R H Young Engineering",
    "wof:placetype":"venue"
},
  "geometry": {"coordinates":[-3.424299,55.88784],"type":"Point"}
}