{
  "type": "Feature",
  "properties": {
    "iso:country":"GB",
    "sg:address":"47 Burleigh Road",
    "sg:city":"Sutton",
    "sg:classifiers":[
        {
            "category":"Home & Garden",
            "subcategory":"Carpets & Floor Coverings",
            "type":"Retail Goods"
        }
    ],
    "sg:phone":"+44 20 8641 2610",
    "sg:postcode":"SM3 9NE",
    "sg:province":"Surrey",
    "sg:tags":[
        "carpets",
        "rug",
        "matting"
    ],
    "wof:name":"Daniel Butler",
    "wof:placetype":"venue"
},
  "geometry": {"coordinates":[-0.2121389955,51.3813552856],"type":"Point"}
}