{
  "type": "Feature",
  "properties": {
    "addr:full":"Suite B, Basilica House Wickford Essex SS11 8QS",
    "addr:housenumber":"suite b basilica house wickford",
    "addr:postcode":"ss11 8qs",
    "iso:country":"GB",
    "sg:address":"Suite B, Basilica House",
    "sg:city":"Wickford",
    "sg:classifiers":[
        {
            "category":"Banks & Credit Unions",
            "subcategory":"Financial Services",
            "type":"Services"
        }
    ],
    "sg:postcode":"SS11 8QS",
    "sg:province":"Essex",
    "sg:tags":[
        "agent",
        "tied"
    ],
    "wof:name":"Synergy Financial Management",
    "wof:placetype":"venue"
},
  "geometry": {"coordinates":[0.574755013,51.6114692688],"type":"Point"}
}