{
  "type": "Feature",
  "properties": {
    "iso:country":"GB",
    "sg:address":"15 Roath Road, Portishead",
    "sg:city":"Bristol",
    "sg:classifiers":[
        {
            "category":"Professional",
            "subcategory":"Lawyer & Legal Services",
            "type":"Services"
        }
    ],
    "sg:phone":"+44 1275 845223",
    "sg:postcode":"BS20 6AW",
    "sg:province":"Somerset",
    "sg:tags":[
        "solicitor"
    ],
    "wof:name":"Wards Solicitors",
    "wof:placetype":"venue"
},
  "geometry": {"coordinates":[-2.769833,51.481556],"type":"Point"}
}