{
  "type": "Feature",
  "properties": {
    "addr:full":"47 Birchington Avenue, Grange Town Middlesbrough North Yorkshire TS6 7HX",
    "addr:housenumber":"47",
    "addr:postcode":"ts6 7hx",
    "addr:street":"Birchington Avenue",
    "iso:country":"GB",
    "sg:address":"47 Birchington Avenue, Grange Town",
    "sg:city":"Middlesbrough",
    "sg:classifiers":[
        {
            "category":"Government",
            "subcategory":"Post Office",
            "type":"Public Place"
        }
    ],
    "sg:phone":"+44 1642 453064",
    "sg:postcode":"TS6 7HX",
    "sg:province":"North Yorkshire",
    "wof:name":"Birchington Avenue Post Office",
    "wof:placetype":"venue"
},
  "geometry": {"coordinates":[-1.1465309858,54.5762557983],"type":"Point"}
}