{
  "type": "Feature",
  "properties": {
    "iso:country":"GB",
    "sg:address":"City Road",
    "sg:city":"Derby",
    "sg:classifiers":[
        {
            "category":"Autos & Motor Vehicles",
            "subcategory":"Auto Supplies",
            "type":"Retail Goods"
        }
    ],
    "sg:phone":"+44 1332 290007",
    "sg:postcode":"DE1 3QY",
    "sg:province":"Derbyshire",
    "sg:tags":[
        "exhaust",
        "absorber",
        "shock"
    ],
    "wof:name":"Q E D",
    "wof:placetype":"venue"
},
  "geometry": {"coordinates":[-1.475164,52.930195],"type":"Point"}
}