{
  "type": "Feature",
  "properties": {
    "iso:country":"GB",
    "sg:address":"Threeway Ho, 40-44 Clipstone St",
    "sg:city":"London",
    "sg:classifiers":[
        {
            "category":"Shopping",
            "subcategory":"Clothing, Apparel, & Fashions",
            "type":"Retail Goods"
        }
    ],
    "sg:phone":"+44 20 8492 0133",
    "sg:postcode":"W1W 5DW",
    "sg:province":"Greater London",
    "sg:tags":[
        "clothing"
    ],
    "wof:name":"Nc Agencies Ltd",
    "wof:placetype":"venue"
},
  "geometry": {"coordinates":[-0.1422600001,51.521030426],"type":"Point"}
}