{
  "type": "Feature",
  "properties": {
    "addr:full":"56 High Street, Hemingford Grey Huntingdon Bedfordshire PE28 9BJ",
    "addr:housenumber":"56",
    "addr:postcode":"pe28 9bj",
    "addr:street":"High Street",
    "iso:country":"GB",
    "sg:address":"56 High Street, Hemingford Grey",
    "sg:city":"Huntingdon",
    "sg:classifiers":[
        {
            "category":"Real Estate",
            "subcategory":"Architect",
            "type":"Services"
        }
    ],
    "sg:phone":"+44 1480 461101",
    "sg:postcode":"PE28 9BJ",
    "sg:province":"Bedfordshire",
    "wof:name":"Marshall Sisson Architect",
    "wof:placetype":"venue"
},
  "geometry": {"coordinates":[-0.104901,52.31868],"type":"Point"}
}