{
  "type": "Feature",
  "properties": {
    "addr:full":"16 Parry Street Leicester Leicestershire LE5 3NL",
    "addr:housenumber":"16",
    "addr:postcode":"le5 3nl",
    "addr:street":"Parry Street",
    "iso:country":"GB",
    "sg:address":"16 Parry Street",
    "sg:city":"Leicester",
    "sg:classifiers":[
        {
            "category":"Professional",
            "subcategory":"Printing & Photocopies",
            "type":"Services"
        }
    ],
    "sg:phone":"+44 116 253 7122",
    "sg:postcode":"LE5 3NL",
    "sg:province":"Leicestershire",
    "sg:tags":[
        "printer"
    ],
    "wof:name":"Swan Print",
    "wof:placetype":"venue"
},
  "geometry": {"coordinates":[-1.1072380543,52.6414909363],"type":"Point"}
}