{
  "type": "Feature",
  "properties": {
    "iso:country":"GB",
    "sg:address":"Market Place",
    "sg:city":"Evesham",
    "sg:classifiers":[
        {
            "category":"Shopping",
            "subcategory":"Used Merchandise",
            "type":"Retail Goods"
        }
    ],
    "sg:phone":"+44 1386 45191",
    "sg:postcode":"WR11 4BG",
    "sg:province":"Gloucestershire",
    "sg:tags":[
        "shop",
        "second-hand"
    ],
    "wof:name":"A G Stanley Ltd.",
    "wof:placetype":"venue"
},
  "geometry": {"coordinates":[-1.947957,52.091877],"type":"Point"}
}