{
  "type": "Feature",
  "properties": {
    "addr:full":"58 Melrose Road Gainsborough Lincolnshire DN21 2SD",
    "addr:housenumber":"58",
    "addr:postcode":"dn21 2sd",
    "addr:street":"Melrose Road",
    "iso:country":"GB",
    "sg:address":"58 Melrose Road",
    "sg:city":"Gainsborough",
    "sg:classifiers":[
        {
            "category":"Food & Beverages",
            "subcategory":"Meat & Fish",
            "type":"Retail Goods"
        }
    ],
    "sg:phone":"+44 1427 616700",
    "sg:postcode":"DN21 2SD",
    "sg:province":"Lincolnshire",
    "sg:tags":[
        "butcher"
    ],
    "wof:name":"Oxleys Butchers",
    "wof:placetype":"venue"
},
  "geometry": {"coordinates":[-0.779877007,53.4077186584],"type":"Point"}
}