{
  "type": "Feature",
  "properties": {
    "iso:country":"GB",
    "sg:address":"15 Invicta Road",
    "sg:city":"Dartford",
    "sg:classifiers":[
        {
            "category":"Professional",
            "subcategory":"Accounting & Tax Preparation",
            "type":"Services"
        }
    ],
    "sg:phone":"+44 1322 284091",
    "sg:postcode":"DA2 6AY",
    "sg:province":"Kent",
    "sg:tags":[
        "accountant"
    ],
    "wof:name":"Grimes & King",
    "wof:placetype":"venue"
},
  "geometry": {"coordinates":[0.2427960038,51.4433097839],"type":"Point"}
}