{
  "type": "Feature",
  "properties": {
    "addr:full":"Unit 3 Broad Lane, Norris Grn Liverpool Merseyside L11 1AD",
    "addr:housenumber":"unit 3",
    "addr:postcode":"l11 1ad",
    "addr:street":"Broad Lane;Grn",
    "iso:country":"GB",
    "sg:address":"Unit 3 Broad Lane, Norris Grn",
    "sg:city":"Liverpool",
    "sg:classifiers":[
        {
            "category":"Shopping",
            "subcategory":"Discount & Variety Stores",
            "type":"Retail Goods"
        }
    ],
    "sg:phone":"+44 151 256 7222",
    "sg:postcode":"L11 1AD",
    "sg:province":"Merseyside",
    "sg:tags":[
        "centre"
    ],
    "wof:name":"Poundstretcher Ltd.",
    "wof:placetype":"venue"
},
  "geometry": {"coordinates":[-2.924634,53.440475],"type":"Point"}
}