{
  "type": "Feature",
  "properties": {
    "addr:full":"9 Coventry Coventry West Midlands CV1 1EA",
    "addr:housenumber":"9",
    "addr:postcode":"cv1 1ea",
    "addr:street":"Coventry Coventry West",
    "iso:country":"GB",
    "sg:address":"9 Coventry",
    "sg:city":"Coventry",
    "sg:classifiers":[
        {
            "category":"Government",
            "subcategory":"Office",
            "type":"Public Place"
        }
    ],
    "sg:phone":"+44 24 7622 6707",
    "sg:postcode":"CV1 1EA",
    "sg:province":"West Midlands",
    "sg:tags":[
        "mp",
        "meps"
    ],
    "wof:name":"Member of Parliament",
    "wof:placetype":"venue"
},
  "geometry": {"coordinates":[-1.49733603,52.3726463318],"type":"Point"}
}