{
  "type": "Feature",
  "properties": {
    "addr:full":"17 Nestor Close Andover Hampshire SP10 3JX",
    "addr:housenumber":"17",
    "addr:postcode":"sp10 3jx",
    "addr:street":"Nestor Close",
    "iso:country":"GB",
    "sg:address":"17 Nestor Close",
    "sg:city":"Andover",
    "sg:classifiers":[
        {
            "category":"Home & Garden",
            "subcategory":"Home Furnishings",
            "type":"Retail Goods"
        }
    ],
    "sg:phone":"+44 1264 333477",
    "sg:postcode":"SP10 3JX",
    "sg:province":"Hampshire",
    "sg:tags":[
        "mantelpiece",
        "fireplace"
    ],
    "wof:name":"Andover Fireplace Supplies",
    "wof:placetype":"venue"
},
  "geometry": {"coordinates":[-1.492773,51.215504],"type":"Point"}
}