{
  "type": "Feature",
  "properties": {
    "iso:country":"GB",
    "sg:address":"Unit 1 Telford Road, Gorse Lane Industrial Estate",
    "sg:city":"Clacton-on-sea",
    "sg:classifiers":[
        {
            "category":"Retail",
            "subcategory":"Auto Repair",
            "type":"Services"
        }
    ],
    "sg:phone":"+44 1255 473647",
    "sg:postcode":"CO15 4LP",
    "sg:province":"Essex",
    "sg:tags":[
        "car",
        "sprayer",
        "painter"
    ],
    "wof:name":"Autospray Graphics",
    "wof:placetype":"venue"
},
  "geometry": {"coordinates":[1.17646,51.815266],"type":"Point"}
}