{
  "type": "Feature",
  "properties": {
    "iso:country":"GB",
    "sg:address":"28a Headley Road, Grayshott",
    "sg:city":"Hindhead",
    "sg:classifiers":[
        {
            "category":"Food & Beverages",
            "subcategory":"Liquor & Beverages",
            "type":"Retail Goods"
        }
    ],
    "sg:phone":"+44 1428 604234",
    "sg:postcode":"GU26 6LB",
    "sg:province":"Hampshire",
    "sg:tags":[
        "beer",
        "spirit",
        "wines"
    ],
    "wof:name":"Wine Rack",
    "wof:placetype":"venue"
},
  "geometry": {"coordinates":[-0.751223,51.110622],"type":"Point"}
}