{
  "type": "Feature",
  "properties": {
    "iso:country":"GB",
    "sg:address":"Higher Listock, Wrantage",
    "sg:city":"Taunton",
    "sg:classifiers":[
        {
            "category":"Utilities",
            "type":"Services"
        }
    ],
    "sg:phone":"+44 1823 490808",
    "sg:postcode":"TA3 6DP",
    "sg:province":"Devon",
    "sg:tags":[
        "internet"
    ],
    "wof:name":"Interface Website Design",
    "wof:placetype":"venue"
},
  "geometry": {"coordinates":[-2.98811,50.997101],"type":"Point"}
}