{
  "type": "Feature",
  "properties": {
    "addr:full":"4 May Tree Dr Wigan Lancashire WN1 2PB",
    "addr:housenumber":"4",
    "addr:postcode":"wn1 2pb",
    "addr:street":"May Tree Dr",
    "iso:country":"GB",
    "sg:address":"4 May Tree Dr",
    "sg:city":"Wigan",
    "sg:classifiers":[
        {
            "category":"Government",
            "subcategory":"Post Office",
            "type":"Public Place"
        }
    ],
    "sg:phone":"+44 1942 324773",
    "sg:postcode":"WN1 2PB",
    "sg:province":"Lancashire",
    "sg:tags":[
        "messenger",
        "courier"
    ],
    "wof:name":"C D Couriers",
    "wof:placetype":"venue"
},
  "geometry": {"coordinates":[-2.638915062,53.5628318787],"type":"Point"}
}