{
  "type": "Feature",
  "properties": {
    "addr:full":"20 Academy Rd Rothesay Argyll and Bute PA20 0BG",
    "addr:housenumber":"20",
    "addr:postcode":"pa20 0bg",
    "addr:street":"Academy Rd",
    "iso:country":"GB",
    "sg:address":"20 Academy Rd",
    "sg:city":"Rothesay",
    "sg:classifiers":[
        {
            "category":"Professional",
            "subcategory":"Business Services",
            "type":"Services"
        }
    ],
    "sg:phone":"+44 1700 505477",
    "sg:postcode":"PA20 0BG",
    "sg:province":"Argyll and Bute",
    "sg:tags":[
        "trade"
    ],
    "wof:name":"Scottish Livestock Services Ltd",
    "wof:placetype":"venue"
},
  "geometry": {"coordinates":[-5.0636529922,55.8403358459],"type":"Point"}
}