{
  "type": "Feature",
  "properties": {
    "addr:full":"12b High Street Tonbridge Kent TN9 1EJ",
    "addr:housenumber":"12b",
    "addr:postcode":"tn9 1ej",
    "addr:street":"High Street",
    "iso:country":"GB",
    "sg:address":"12b High Street",
    "sg:city":"Tonbridge",
    "sg:classifiers":[
        {
            "category":"Personal",
            "subcategory":"Beauty Salon",
            "type":"Services"
        }
    ],
    "sg:phone":"+44 1732 360998",
    "sg:postcode":"TN9 1EJ",
    "sg:province":"Kent",
    "sg:tags":[
        "unisex",
        "hairdresser"
    ],
    "wof:name":"Starkuts",
    "wof:placetype":"venue"
},
  "geometry": {"coordinates":[0.2721630037,51.1927680969],"type":"Point"}
}