{
  "type": "Feature",
  "properties": {
    "iso:country":"GB",
    "sg:address":"2425 The Crescent, Birmingham Business Park",
    "sg:city":"Birmingham",
    "sg:classifiers":[
        {
            "category":"Professional",
            "subcategory":"Computer Services",
            "type":"Services"
        }
    ],
    "sg:phone":"+44 121 717 4300",
    "sg:postcode":"B37 7YE",
    "sg:province":"West Midlands",
    "sg:tags":[
        "aided",
        "design"
    ],
    "wof:name":"Eds Unigraphics Ltd",
    "wof:placetype":"venue"
},
  "geometry": {"coordinates":[-1.718793,52.471451],"type":"Point"}
}