{
  "type": "Feature",
  "properties": {
    "addr:full":"123/125 Charles St Nelson Lancashire BB9 8SP",
    "addr:housenumber":"123 / 125",
    "addr:postcode":"bb9 8sp",
    "addr:street":"Charles St",
    "iso:country":"GB",
    "sg:address":"123/125 Charles St",
    "sg:city":"Nelson",
    "sg:classifiers":[
        {
            "category":"Personal",
            "type":"Services"
        }
    ],
    "sg:phone":"+44 1282 716282",
    "sg:postcode":"BB9 8SP",
    "sg:province":"Lancashire",
    "sg:tags":[
        "delivery"
    ],
    "wof:name":"U K Euro Chilled Express Ltd",
    "wof:placetype":"venue"
},
  "geometry": {"coordinates":[-2.20904,53.846783],"type":"Point"}
}