{
  "type": "Feature",
  "properties": {
    "iso:country":"GB",
    "sg:address":"Venn Lane, Chideock",
    "sg:city":"Bridport",
    "sg:classifiers":[
        {
            "category":"Farming",
            "subcategory":"Livestock Farm",
            "type":"Manufacturing & Wholesale Goods"
        }
    ],
    "sg:phone":"+44 1297 489495",
    "sg:postcode":"DT6 6JY",
    "sg:province":"Dorset",
    "sg:tags":[
        "others"
    ],
    "wof:name":"David Lyall",
    "wof:placetype":"venue"
},
  "geometry": {"coordinates":[-2.81787,50.731972],"type":"Point"}
}