{
  "type": "Feature",
  "properties": {
    "iso:country":"GB",
    "sg:address":"22 Norris Way, Riland Industrial Estate",
    "sg:city":"Sutton Coldfield",
    "sg:classifiers":[
        {
            "category":"Professional",
            "subcategory":"Engineering",
            "type":"Services"
        }
    ],
    "sg:phone":"+44 121 378 4207",
    "sg:postcode":"B75 7BB",
    "sg:province":"Staffordshire",
    "sg:tags":[
        "contractor",
        "electrical",
        "engineer"
    ],
    "wof:name":"Tool Protection Techniques Ltd.",
    "wof:placetype":"venue"
},
  "geometry": {"coordinates":[-1.815528,52.562428],"type":"Point"}
}