{
  "type": "Feature",
  "properties": {
    "iso:country":"GB",
    "sg:address":"Pearl Centre, Lynch Wood",
    "sg:city":"Peterborough",
    "sg:classifiers":[
        {
            "category":"Insurance",
            "subcategory":"Insurance Agent",
            "type":"Services"
        }
    ],
    "sg:phone":"+44 845 882 5673",
    "sg:postcode":"PE2 6FY",
    "sg:province":"Cambridgeshire",
    "wof:name":"Pearl Assurance Plc",
    "wof:placetype":"venue"
},
  "geometry": {"coordinates":[-0.32026,52.55463],"type":"Point"}
}