{
  "type": "Feature",
  "properties": {
    "iso:country":"GB",
    "sg:address":"40 Altcross Rd",
    "sg:city":"Liverpool",
    "sg:classifiers":[
        {
            "category":"Health Services",
            "subcategory":"Clinic",
            "type":"Services"
        }
    ],
    "sg:phone":"+44 151 546 6777",
    "sg:postcode":"L11 4SU",
    "sg:province":"Merseyside",
    "sg:tags":[
        "nh"
    ],
    "wof:name":"Croxteth Family Health Clinic",
    "wof:placetype":"venue"
},
  "geometry": {"coordinates":[-2.901697,53.453148],"type":"Point"}
}