{
  "type": "Feature",
  "properties": {
    "addr:full":"62 Breck Road, Anfield Liverpool Merseyside L4 2RD",
    "addr:housenumber":"62",
    "addr:postcode":"l4 2rd",
    "addr:street":"Breck Road Anfield",
    "iso:country":"GB",
    "sg:address":"62 Breck Road, Anfield",
    "sg:city":"Liverpool",
    "sg:classifiers":[
        {
            "category":"Building & Trades",
            "subcategory":"Construction",
            "type":"Services"
        }
    ],
    "sg:phone":"+44 151 263 5733",
    "sg:postcode":"L4 2RD",
    "sg:province":"Merseyside",
    "sg:tags":[
        "glazier"
    ],
    "wof:name":"J O'Neil",
    "wof:placetype":"venue"
},
  "geometry": {"coordinates":[-2.95248,53.42617],"type":"Point"}
}