{
  "type": "Feature",
  "properties": {
    "addr:full":"Angel Street Bridgend Bridgend CF31 4AD",
    "addr:postcode":"cf31 4ad",
    "addr:street":"Angel Street",
    "iso:country":"GB",
    "sg:address":"Angel Street",
    "sg:city":"Bridgend",
    "sg:classifiers":[
        {
            "category":"Government",
            "subcategory":"City Hall",
            "type":"Public Place"
        },
        {
            "category":"Retail",
            "subcategory":"Event Space",
            "type":"Services"
        }
    ],
    "sg:phone":"+44 1656 661822",
    "sg:postcode":"CF31 4AD",
    "sg:province":"Bridgend",
    "sg:tags":[
        "function",
        "hire",
        "room"
    ],
    "wof:name":"Evergreen Hall",
    "wof:placetype":"venue"
},
  "geometry": {"coordinates":[-3.5806388855,51.5064582825],"type":"Point"}
}