{
  "type": "Feature",
  "properties": {
    "addr:full":"Brittania Ho, High St, Oldland Common Bristol Gloucestershire BS30 9QF",
    "addr:postcode":"bs30 9qf",
    "addr:street":"High St",
    "iso:country":"GB",
    "sg:address":"Brittania Ho, High St, Oldland Common",
    "sg:city":"Bristol",
    "sg:classifiers":[
        {
            "category":"Retail",
            "subcategory":"Auto Rental",
            "type":"Services"
        }
    ],
    "sg:postcode":"BS30 9QF",
    "sg:province":"Gloucestershire",
    "sg:tags":[
        "car"
    ],
    "wof:name":"Arrow Car Hire",
    "wof:placetype":"venue"
},
  "geometry": {"coordinates":[-2.4700388908,51.4403457642],"type":"Point"}
}