{
  "type": "Feature",
  "properties": {
    "iso:country":"GB",
    "sg:address":"Ivydene",
    "sg:city":"Worcester Park",
    "sg:classifiers":[
        {
            "category":"Organizations",
            "subcategory":"Membership Organization",
            "type":"Services"
        }
    ],
    "sg:postcode":"KT4 7PX",
    "sg:province":"Surrey",
    "sg:tags":[
        "club"
    ],
    "wof:name":"Maouri Club",
    "wof:placetype":"venue"
},
  "geometry": {"coordinates":[-0.258427,51.371639],"type":"Point"}
}