{
  "type": "Feature",
  "properties": {
    "addr:full":"58 Church Road Aldershot Hampshire GU11 3PS",
    "addr:housenumber":"58",
    "addr:postcode":"gu11 3ps",
    "addr:street":"Church Road",
    "iso:country":"GB",
    "sg:address":"58 Church Road",
    "sg:city":"Aldershot",
    "sg:classifiers":[
        {
            "category":"Food & Beverages",
            "subcategory":"Meat & Fish",
            "type":"Retail Goods"
        }
    ],
    "sg:phone":"+44 1252 314045",
    "sg:postcode":"GU11 3PS",
    "sg:province":"Hampshire",
    "sg:tags":[
        "butcher"
    ],
    "wof:name":"Mark Turner & Daughters Family Butchers",
    "wof:placetype":"venue"
},
  "geometry": {"coordinates":[-0.7524229884,51.2378387451],"type":"Point"}
}