{
  "type": "Feature",
  "properties": {
    "iso:country":"GB",
    "sg:address":"Sunnyvale Road",
    "sg:city":"Sheffield",
    "sg:classifiers":[
        {
            "category":"Education",
            "subcategory":"School",
            "type":"Public Place"
        },
        {
            "category":"Government",
            "subcategory":"Office",
            "type":"Public Place"
        }
    ],
    "sg:phone":"+44 114 236 4482",
    "sg:postcode":"S17 4FB",
    "sg:province":"Derbyshire",
    "sg:tags":[
        "local",
        "authority"
    ],
    "wof:name":"Totley Primary School",
    "wof:placetype":"venue"
},
  "geometry": {"coordinates":[-1.537569046,53.3132019043],"type":"Point"}
}