{
  "type": "Feature",
  "properties": {
    "iso:country":"GB",
    "sg:address":"30 Limbrick",
    "sg:city":"Blackburn",
    "sg:classifiers":[
        {
            "category":"Manufacturing",
            "subcategory":"Textiles",
            "type":"Manufacturing & Wholesale Goods"
        }
    ],
    "sg:phone":"+44 1254 680102",
    "sg:postcode":"BB1 8AB",
    "sg:province":"Lancashire",
    "sg:tags":[
        "knitwear"
    ],
    "wof:name":"Lancashire Trimmings",
    "wof:placetype":"venue"
},
  "geometry": {"coordinates":[-2.486214,53.751766],"type":"Point"}
}