{
  "type": "Feature",
  "properties": {
    "iso:country":"GB",
    "sg:address":"Hook, Warsash",
    "sg:city":"Southampton",
    "sg:classifiers":[
        {
            "category":"Retail",
            "subcategory":"Auto Repair",
            "type":"Services"
        }
    ],
    "sg:postcode":"SO31 9HH",
    "sg:province":"Hampshire",
    "sg:tags":[
        "body",
        "car"
    ],
    "wof:name":"Forge Body Repair Shop",
    "wof:placetype":"venue"
},
  "geometry": {"coordinates":[-1.299124,50.853233],"type":"Point"}
}