{
  "type": "Feature",
  "properties": {
    "addr:full":"3 The Wynd Redcar North Yorkshire TS11 7LD",
    "addr:housenumber":"3",
    "addr:postcode":"ts11 7ld",
    "addr:street":"The Wynd",
    "iso:country":"GB",
    "sg:address":"3 The Wynd",
    "sg:city":"Redcar",
    "sg:classifiers":[
        {
            "category":"Food & Beverages",
            "subcategory":"Fruits & Vegetables",
            "type":"Retail Goods"
        }
    ],
    "sg:phone":"+44 1642 490391",
    "sg:postcode":"TS11 7LD",
    "sg:province":"North Yorkshire",
    "sg:tags":[
        "greengrocer"
    ],
    "wof:name":"D Wadsworth & Sons",
    "wof:placetype":"venue"
},
  "geometry": {"coordinates":[-1.0183550119,54.5921020508],"type":"Point"}
}