{
  "type": "Feature",
  "properties": {
    "iso:country":"GB",
    "sg:address":"Church Rd, Seacombe",
    "sg:city":"Wallasey",
    "sg:classifiers":[
        {
            "category":"Travel",
            "subcategory":"Hotels & Motels",
            "type":"Entertainment"
        },
        {
            "category":"Social Services",
            "subcategory":"Retirement Home",
            "type":"Services"
        }
    ],
    "sg:phone":"+44 151 639 5723",
    "sg:postcode":"CH44 7BA",
    "sg:province":"Merseyside",
    "sg:tags":[
        "residential",
        "care"
    ],
    "wof:name":"The Russell Hotel",
    "wof:placetype":"venue"
},
  "geometry": {"coordinates":[-3.0199489594,53.4094963074],"type":"Point"}
}