{
  "type": "Feature",
  "properties": {
    "iso:country":"GB",
    "sg:address":"Suite 102 Charter House, Lord Montgomery Way",
    "sg:city":"Portsmouth",
    "sg:classifiers":[
        {
            "category":"Building & Trades",
            "subcategory":"Cleaning & Sanitation",
            "type":"Services"
        }
    ],
    "sg:phone":"+44 23 9275 1202",
    "sg:postcode":"PO1 2SB",
    "sg:province":"Hampshire",
    "sg:tags":[
        "commercial"
    ],
    "wof:name":"Henrys Contract Cleaning",
    "wof:placetype":"venue"
},
  "geometry": {"coordinates":[-1.095306,50.794834],"type":"Point"}
}