{
  "type": "Feature",
  "properties": {
    "iso:country":"GB",
    "sg:address":"150 Clay Hill Road",
    "sg:city":"Basildon",
    "sg:classifiers":[
        {
            "category":"Food & Beverages",
            "subcategory":"Liquor & Beverages",
            "type":"Retail Goods"
        }
    ],
    "sg:phone":"+44 1268 520476",
    "sg:postcode":"SS16 5DF",
    "sg:province":"Essex",
    "sg:tags":[
        "beer",
        "spirit",
        "wines"
    ],
    "wof:name":"High Spirits",
    "wof:placetype":"venue"
},
  "geometry": {"coordinates":[0.463564,51.563721],"type":"Point"}
}