{
  "type": "Feature",
  "properties": {
    "addr:full":"Unit 1, Birchwood La Alfreton Derbyshire DE55 4NE",
    "addr:housenumber":"unit 1",
    "addr:postcode":"de55 4ne",
    "iso:country":"GB",
    "sg:address":"Unit 1, Birchwood La",
    "sg:city":"Alfreton",
    "sg:classifiers":[
        {
            "category":"Autos & Motor Vehicles",
            "subcategory":"Automobile Sales",
            "type":"Retail Goods"
        }
    ],
    "sg:postcode":"DE55 4NE",
    "sg:province":"Derbyshire",
    "sg:tags":[
        "car"
    ],
    "wof:name":"Chapman,John,",
    "wof:placetype":"venue"
},
  "geometry": {"coordinates":[-1.3561580181,53.0816192627],"type":"Point"}
}