{
  "type": "Feature",
  "properties": {
    "addr:full":"32 Hazelhurst Gro, Queensbury Bradford West Yorkshire BD13 2LU",
    "addr:housenumber":"32",
    "addr:postcode":"bd13 2lu",
    "addr:street":"Hazelhurst Gro;Bradford West",
    "iso:country":"GB",
    "sg:address":"32 Hazelhurst Gro, Queensbury",
    "sg:city":"Bradford",
    "sg:classifiers":[
        {
            "category":"Building & Trades",
            "subcategory":"Construction",
            "type":"Services"
        }
    ],
    "sg:postcode":"BD13 2LU",
    "sg:province":"West Yorkshire",
    "sg:tags":[
        "builder"
    ],
    "wof:name":"Paul Alderson",
    "wof:placetype":"venue"
},
  "geometry": {"coordinates":[-1.8536590338,53.7612915039],"type":"Point"}
}