{
  "type": "Feature",
  "properties": {
    "addr:full":"25 Park Av Watford Hertfordshire WD1 7HR",
    "addr:housenumber":"25",
    "addr:postcode":"wd1 7hr",
    "addr:street":"Park Av",
    "iso:country":"GB",
    "sg:address":"25 Park Av",
    "sg:city":"Watford",
    "sg:classifiers":[
        {
            "category":"Professional",
            "subcategory":"Secretarial Services",
            "type":"Services"
        }
    ],
    "sg:phone":"+44 1923 218661",
    "sg:postcode":"WD1 7HR",
    "sg:province":"Hertfordshire",
    "wof:name":"Acme Business Centre",
    "wof:placetype":"venue"
},
  "geometry": {"coordinates":[-0.405947,51.654816],"type":"Point"}
}