{
  "type": "Feature",
  "properties": {
    "addr:full":"Oak Lea, The Avenue, Collingham Wetherby North Yorkshire LS22 5BU",
    "addr:postcode":"ls22 5bu",
    "addr:street":"The Avenue",
    "iso:country":"GB",
    "sg:address":"Oak Lea, The Avenue, Collingham",
    "sg:city":"Wetherby",
    "sg:classifiers":[
        {
            "category":"Utilities",
            "subcategory":"Fuel Oil & Lpg",
            "type":"Services"
        }
    ],
    "sg:postcode":"LS22 5BU",
    "sg:province":"North Yorkshire",
    "wof:name":"J F L Fuels",
    "wof:placetype":"venue"
},
  "geometry": {"coordinates":[-1.4142129421,53.9063987732],"type":"Point"}
}