{
  "type": "Feature",
  "properties": {
    "addr:full":"78-90 Glasgow Street Dumfries Dumfries and Galloway DG2 9AQ",
    "addr:housenumber":"78-90",
    "addr:postcode":"dg2 9aq",
    "addr:street":"Glasgow Street",
    "iso:country":"GB",
    "sg:address":"78-90 Glasgow Street",
    "sg:city":"Dumfries",
    "sg:classifiers":[
        {
            "category":"Retail",
            "subcategory":"Auto Repair",
            "type":"Services"
        }
    ],
    "sg:postcode":"DG2 9AQ",
    "sg:province":"Dumfries and Galloway",
    "sg:tags":[
        "modification",
        "garage"
    ],
    "wof:name":"Central Car Sales",
    "wof:placetype":"venue"
},
  "geometry": {"coordinates":[-3.619765,55.070404],"type":"Point"}
}