{
  "type": "Feature",
  "properties": {
    "addr:full":"Union Place Worthing West Sussex BN11 1LG",
    "addr:postcode":"bn11 1lg",
    "addr:street":"Union Place",
    "iso:country":"GB",
    "sg:address":"Union Place",
    "sg:city":"Worthing",
    "sg:classifiers":[
        {
            "category":"Parking",
            "type":"Transportation"
        }
    ],
    "sg:phone":"+44 20 7499 7050",
    "sg:postcode":"BN11 1LG",
    "sg:province":"West Sussex",
    "sg:tags":[
        "car",
        "park"
    ],
    "wof:name":"National Car Parks Ltd.",
    "wof:placetype":"venue"
},
  "geometry": {"coordinates":[-0.369675,50.813889],"type":"Point"}
}