{
  "type": "Feature",
  "properties": {
    "addr:full":"18 The Square, Letham Forfar Angus DD8 2PZ",
    "addr:housenumber":"18",
    "addr:postcode":"dd8 2pz",
    "addr:street":"The Square Letham",
    "iso:country":"GB",
    "sg:address":"18 The Square, Letham",
    "sg:city":"Forfar",
    "sg:classifiers":[
        {
            "category":"Personal",
            "subcategory":"Beauty Salon",
            "type":"Services"
        }
    ],
    "sg:phone":"+44 1307 818814",
    "sg:postcode":"DD8 2PZ",
    "sg:province":"Angus",
    "sg:tags":[
        "unisex",
        "hairdresser"
    ],
    "wof:name":"Snip Salon",
    "wof:placetype":"venue"
},
  "geometry": {"coordinates":[-2.7694380283,56.6288833618],"type":"Point"}
}