{
  "type": "Feature",
  "properties": {
    "addr:full":"191 Heathfield Rd, Handsworth Birmingham West Midlands B19 1JD",
    "addr:housenumber":"191",
    "addr:postcode":"b19 1jd",
    "addr:street":"Heathfield Rd",
    "iso:country":"GB",
    "sg:address":"191 Heathfield Rd, Handsworth",
    "sg:city":"Birmingham",
    "sg:classifiers":[
        {
            "category":"Health Services",
            "subcategory":"Dentist",
            "type":"Services"
        }
    ],
    "sg:phone":"+44 121 523 3749",
    "sg:postcode":"B19 1JD",
    "sg:province":"West Midlands",
    "wof:name":"Dental Emergencies",
    "wof:placetype":"venue"
},
  "geometry": {"coordinates":[-1.906479001,52.5080413818],"type":"Point"}
}