{
  "type": "Feature",
  "properties": {
    "addr:full":"21 St. John St Manchester Greater Manchester M3 4DT",
    "addr:housenumber":"21",
    "addr:postcode":"m3 4dt",
    "addr:street":"St. John St",
    "iso:country":"GB",
    "sg:address":"21 St. John St",
    "sg:city":"Manchester",
    "sg:classifiers":[
        {
            "category":"Health Services",
            "subcategory":"Doctor",
            "type":"Services"
        }
    ],
    "sg:phone":"+44 161 834 4131",
    "sg:postcode":"M3 4DT",
    "sg:province":"Greater Manchester",
    "sg:tags":[
        "practitioners"
    ],
    "wof:name":"A.W Hargreaves",
    "wof:placetype":"venue"
},
  "geometry": {"coordinates":[-2.251802,53.47768],"type":"Point"}
}