{
  "type": "Feature",
  "properties": {
    "iso:country":"GB",
    "sg:address":"6 The Derwent Centre",
    "sg:city":"Consett",
    "sg:classifiers":[
        {
            "category":"Food & Beverages",
            "subcategory":"Bakery",
            "type":"Retail Goods"
        }
    ],
    "sg:phone":"+44 1207 501796",
    "sg:postcode":"DH8 5SD",
    "sg:province":"Durham",
    "sg:tags":[
        "baker"
    ],
    "wof:name":"Peters Cathedral Bakers Ltd.",
    "wof:placetype":"venue"
},
  "geometry": {"coordinates":[-1.8333109617,54.8593292236],"type":"Point"}
}