{
  "type": "Feature",
  "properties": {
    "iso:country":"GB",
    "sg:address":"Front Street, Sacriston",
    "sg:city":"Durham",
    "sg:classifiers":[
        {
            "category":"Autos & Motor Vehicles",
            "subcategory":"Automobile Sales",
            "type":"Retail Goods"
        }
    ],
    "sg:postcode":"DH7 6JP",
    "sg:province":"Durham",
    "sg:tags":[
        "car"
    ],
    "wof:name":"Cathedral City Cars Ltd.",
    "wof:placetype":"venue"
},
  "geometry": {"coordinates":[-1.626584,54.81773],"type":"Point"}
}