{
  "type": "Feature",
  "properties": {
    "addr:full":"4 Westbury Street Hyde Cheshire SK14 4QP",
    "addr:housenumber":"4",
    "addr:postcode":"sk14 4qp",
    "addr:street":"Westbury Street",
    "iso:country":"GB",
    "sg:address":"4 Westbury Street",
    "sg:city":"Hyde",
    "sg:classifiers":[
        {
            "category":"Retail",
            "subcategory":"Storage",
            "type":"Services"
        }
    ],
    "sg:phone":"+44 161 368 2723",
    "sg:postcode":"SK14 4QP",
    "sg:province":"Cheshire",
    "sg:tags":[
        "household",
        "removal"
    ],
    "wof:name":"Allotts Removals & Storage",
    "wof:placetype":"venue"
},
  "geometry": {"coordinates":[-2.0884950161,53.4646759033],"type":"Point"}
}