{
  "type": "Feature",
  "properties": {
    "iso:country":"GB",
    "sg:address":"Pattinson Court, Pattinson Drive",
    "sg:city":"Plymouth",
    "sg:classifiers":[
        {
            "category":"Organizations",
            "subcategory":"Community Association",
            "type":"Services"
        }
    ],
    "sg:postcode":"PL6 8RU",
    "sg:province":"Devon",
    "sg:tags":[
        "society",
        "housing"
    ],
    "wof:name":"Pattison Ct",
    "wof:placetype":"venue"
},
  "geometry": {"coordinates":[-4.092343,50.410545],"type":"Point"}
}