{
  "type": "Feature",
  "properties": {
    "addr:full":"Combe Hay Lane Bath Somerset BA2 8PA",
    "addr:postcode":"ba2 8pa",
    "addr:street":"Combe Hay Lane",
    "iso:country":"GB",
    "sg:address":"Combe Hay Lane",
    "sg:city":"Bath",
    "sg:classifiers":[
        {
            "category":"Education",
            "subcategory":"School",
            "type":"Public Place"
        }
    ],
    "sg:phone":"+44 1225 832873",
    "sg:postcode":"BA2 8PA",
    "sg:province":"Somerset",
    "sg:tags":[
        "local",
        "authority"
    ],
    "wof:name":"St Gregorys R C Comprehensive School",
    "wof:placetype":"venue"
},
  "geometry": {"coordinates":[-2.3838059902,51.3510818481],"type":"Point"}
}