{
  "type": "Feature",
  "properties": {
    "iso:country":"GB",
    "sg:address":"5 East Park",
    "sg:city":"Crawley",
    "sg:classifiers":[
        {
            "category":"Utilities",
            "type":"Services"
        }
    ],
    "sg:phone":"+44 1293 619932",
    "sg:postcode":"RH10 6AN",
    "sg:province":"Surrey",
    "sg:tags":[
        "internet"
    ],
    "wof:name":"Ict Strategies Ltd.",
    "wof:placetype":"venue"
},
  "geometry": {"coordinates":[-0.18913,51.111732],"type":"Point"}
}