{
  "type": "Feature",
  "properties": {
    "addr:full":"Northern Regional Office, 2d The Wynd Glasgow Falkirk G67 2SU",
    "addr:housenumber":"2d",
    "addr:postcode":"g67 2su",
    "addr:street":"The Wynd",
    "iso:country":"GB",
    "sg:address":"Northern Regional Office, 2d The Wynd",
    "sg:city":"Glasgow",
    "sg:classifiers":[
        {
            "category":"Shopping",
            "subcategory":"Pharmacy",
            "type":"Retail Goods"
        }
    ],
    "sg:phone":"+44 1236 734585",
    "sg:postcode":"G67 2SU",
    "sg:province":"Falkirk",
    "sg:tags":[
        "pharmacist",
        "chemist"
    ],
    "wof:name":"Co-Op Pharmacy",
    "wof:placetype":"venue"
},
  "geometry": {"coordinates":[-3.97499,55.963032],"type":"Point"}
}