{
  "type": "Feature",
  "properties": {
    "addr:full":"15 Old Street London Greater London EC1V 9HL",
    "addr:housenumber":"15",
    "addr:postcode":"ec1v 9hl",
    "addr:street":"Old Street",
    "iso:country":"GB",
    "sg:address":"15 Old Street",
    "sg:city":"London",
    "sg:classifiers":[
        {
            "category":"Manufacturing",
            "subcategory":"Textiles",
            "type":"Manufacturing & Wholesale Goods"
        }
    ],
    "sg:phone":"+44 20 7729 3755",
    "sg:postcode":"EC1V 9HL",
    "sg:province":"Greater London",
    "sg:tags":[
        "designer"
    ],
    "wof:name":"Alison Hume 101",
    "wof:placetype":"venue"
},
  "geometry": {"coordinates":[-0.1045570001,51.4984474182],"type":"Point"}
}