{
  "type": "Feature",
  "properties": {
    "addr:full":"32 Lewis Road St Leonards-on-sea East Sussex TN38 9EJ",
    "addr:housenumber":"32",
    "addr:postcode":"leonards-on-sea;tn38 9ej",
    "addr:street":"Lewis Road St",
    "iso:country":"GB",
    "sg:address":"32 Lewis Road",
    "sg:city":"St Leonards-on-sea",
    "sg:classifiers":[
        {
            "category":"Building & Trades",
            "subcategory":"Construction",
            "type":"Services"
        }
    ],
    "sg:phone":"+44 1424 719712",
    "sg:postcode":"TN38 9EJ",
    "sg:province":"East Sussex",
    "sg:tags":[
        "decorator",
        "painter"
    ],
    "wof:name":"G Eldridge",
    "wof:placetype":"venue"
},
  "geometry": {"coordinates":[0.547343,50.872009],"type":"Point"}
}