{
  "type": "Feature",
  "properties": {
    "addr:full":"Unit 1, 11 Fieldings Road Waltham Cross Essex EN8 9TL",
    "addr:housenumber":"unit;11",
    "addr:postcode":"en8 9tl",
    "addr:street":"Fieldings Road",
    "iso:country":"GB",
    "sg:address":"Unit 1, 11 Fieldings Road",
    "sg:city":"Waltham Cross",
    "sg:classifiers":[
        {
            "category":"Professional",
            "subcategory":"Printing & Photocopies",
            "type":"Services"
        }
    ],
    "sg:postcode":"EN8 9TL",
    "sg:province":"Essex",
    "sg:tags":[
        "print",
        "finisher"
    ],
    "wof:name":"Karen Murphy",
    "wof:placetype":"venue"
},
  "geometry": {"coordinates":[-0.024209,51.70813],"type":"Point"}
}