{
  "type": "Feature",
  "properties": {
    "addr:full":"Godswell Stables, Church St Banbury Oxfordshire OX15 4ES",
    "addr:postcode":"ox15 4es",
    "addr:street":"St",
    "iso:country":"GB",
    "sg:address":"Godswell Stables, Church St",
    "sg:city":"Banbury",
    "sg:classifiers":[
        {
            "category":"Health Services",
            "subcategory":"Dentist",
            "type":"Services"
        }
    ],
    "sg:phone":"+44 1295 721030",
    "sg:postcode":"OX15 4ES",
    "sg:province":"Oxfordshire",
    "wof:name":"Catherine Brady",
    "wof:placetype":"venue"
},
  "geometry": {"coordinates":[-1.3750400543,52.0186080933],"type":"Point"}
}