{
  "type": "Feature",
  "properties": {
    "iso:country":"GB",
    "sg:address":"Unit3, Carlisle Business Park, 1 Chambers Lane",
    "sg:city":"Sheffield",
    "sg:classifiers":[
        {
            "category":"Retail",
            "subcategory":"Auto Repair",
            "type":"Services"
        }
    ],
    "sg:phone":"+44 114 261 1732",
    "sg:postcode":"S4 8DA",
    "sg:province":"South Yorkshire",
    "sg:tags":[
        "modification",
        "garage",
        "related"
    ],
    "wof:name":"C L Autos",
    "wof:placetype":"venue"
},
  "geometry": {"coordinates":[-1.437701,53.405952],"type":"Point"}
}