{
  "type": "Feature",
  "properties": {
    "addr:full":"Chester Street Mold Denbighshire CH7 1EG",
    "addr:postcode":"ch7 1eg",
    "addr:street":"Chester Street",
    "iso:country":"GB",
    "sg:address":"Chester Street",
    "sg:city":"Mold",
    "sg:classifiers":[
        {
            "category":"Professional",
            "subcategory":"Printing & Photocopies",
            "type":"Services"
        }
    ],
    "sg:postcode":"CH7 1EG",
    "sg:province":"Denbighshire",
    "sg:tags":[
        "printer"
    ],
    "wof:name":"Info Cards",
    "wof:placetype":"venue"
},
  "geometry": {"coordinates":[-3.138173,53.168125],"type":"Point"}
}