{
  "type": "Feature",
  "properties": {
    "iso:country":"GB",
    "sg:address":"70-74 Green Lanes",
    "sg:city":"London",
    "sg:classifiers":[
        {
            "category":"Travel",
            "subcategory":"Hostel",
            "type":"Entertainment"
        }
    ],
    "sg:postcode":"N13 6BE",
    "sg:province":"Greater London",
    "wof:name":"FOREST HOUSE HOSTEL",
    "wof:placetype":"venue"
},
  "geometry": {"coordinates":[-0.1093389988,51.6117935181],"type":"Point"}
}