{
  "type": "Feature",
  "properties": {
    "iso:country":"GB",
    "sg:address":"Unit 8 & 9, Block 7, Rosebury Lane",
    "sg:city":"Airdrie",
    "sg:classifiers":[
        {
            "category":"Wholesale",
            "subcategory":"Fruits & Vegetables",
            "type":"Manufacturing & Wholesale Goods"
        }
    ],
    "sg:phone":"+44 1236 762091",
    "sg:postcode":"ML6 8QY",
    "sg:province":"North Lanarkshire",
    "wof:name":"Craig Miller Fruit & Veg",
    "wof:placetype":"venue"
},
  "geometry": {"coordinates":[-3.9493401051,55.8481216431],"type":"Point"}
}