{
  "type": "Feature",
  "properties": {
    "addr:full":"112 High Road London Greater London N22 6HE",
    "addr:housenumber":"112",
    "addr:postcode":"n22 6he",
    "addr:street":"High Road",
    "iso:country":"GB",
    "sg:address":"112 High Road",
    "sg:city":"London",
    "sg:classifiers":[
        {
            "category":"Home & Garden",
            "subcategory":"Furniture",
            "type":"Retail Goods"
        }
    ],
    "sg:phone":"+44 20 8889 0296",
    "sg:postcode":"N22 6HE",
    "sg:province":"Greater London",
    "wof:name":"Harveys Furnishing Ltd.",
    "wof:placetype":"venue"
},
  "geometry": {"coordinates":[-0.108018,51.59425],"type":"Point"}
}