{
  "type": "Feature",
  "properties": {
    "addr:full":"The Warehouse, Moy Road, Roath Cardiff Cardiff CF24 4TE",
    "addr:postcode":"cf24 4te",
    "addr:street":"Moy Road",
    "iso:country":"GB",
    "sg:address":"The Warehouse, Moy Road, Roath",
    "sg:city":"Cardiff",
    "sg:classifiers":[
        {
            "category":"Autos & Motor Vehicles",
            "subcategory":"Auto Supplies",
            "type":"Retail Goods"
        }
    ],
    "sg:phone":"+44 29 2046 5583",
    "sg:postcode":"CF24 4TE",
    "sg:province":"Cardiff",
    "sg:tags":[
        "component"
    ],
    "wof:name":"Japanese Parts South Wales",
    "wof:placetype":"venue"
},
  "geometry": {"coordinates":[-3.1704499722,51.4946899414],"type":"Point"}
}