{
  "type": "Feature",
  "properties": {
    "iso:country":"GB",
    "sg:address":"56 Newington Rd",
    "sg:city":"Annan",
    "sg:classifiers":[
        {
            "category":"Building & Trades",
            "subcategory":"Construction",
            "type":"Services"
        }
    ],
    "sg:phone":"+44 1461 205645",
    "sg:postcode":"DG12 5JB",
    "sg:province":"Dumfries and Galloway",
    "sg:tags":[
        "builder"
    ],
    "wof:name":"J & R Builders",
    "wof:placetype":"venue"
},
  "geometry": {"coordinates":[-3.25518,54.991657],"type":"Point"}
}