{
  "type": "Feature",
  "properties": {
    "addr:full":"Corner House Street Aberdare Neath Port Talbot CF44 0YA",
    "addr:postcode":"cf44 0ya",
    "addr:street":"Corner House Street",
    "iso:country":"GB",
    "sg:address":"Corner House Street",
    "sg:city":"Aberdare",
    "sg:classifiers":[
        {
            "category":"Bars & Pubs",
            "type":"Food & Drink"
        }
    ],
    "sg:phone":"+44 1685 879739",
    "sg:postcode":"CF44 0YA",
    "sg:province":"Neath Port Talbot",
    "sg:tags":[
        "pubs",
        "inn"
    ],
    "wof:name":"Corner House Inn",
    "wof:placetype":"venue"
},
  "geometry": {"coordinates":[-3.458518,51.734802],"type":"Point"}
}