{
  "type": "Feature",
  "properties": {
    "addr:full":"185 Fore Street Exeter Devon EX4 3AX",
    "addr:housenumber":"185",
    "addr:postcode":"ex4 3ax",
    "addr:street":"Fore Street",
    "iso:country":"GB",
    "sg:address":"185 Fore Street",
    "sg:city":"Exeter",
    "sg:classifiers":[
        {
            "category":"Retail",
            "subcategory":"Photofinishing",
            "type":"Services"
        }
    ],
    "sg:phone":"+44 1392 490102",
    "sg:postcode":"EX4 3AX",
    "sg:province":"Devon",
    "sg:tags":[
        "photographic",
        "processor"
    ],
    "wof:name":"Snappy Snaps",
    "wof:placetype":"venue"
},
  "geometry": {"coordinates":[-3.533479,50.721909],"type":"Point"}
}