{
  "type": "Feature",
  "properties": {
    "iso:country":"GB",
    "sg:address":"Bromyard Road, St Johns",
    "sg:city":"Worcester",
    "sg:classifiers":[
        {
            "category":"Personal",
            "subcategory":"Beauty Salon",
            "type":"Services"
        }
    ],
    "sg:phone":"+44 1905 748361",
    "sg:postcode":"WR2 5HP",
    "sg:province":"Worcestershire",
    "wof:name":"Beauty Box",
    "wof:placetype":"venue"
},
  "geometry": {"coordinates":[-2.234994,52.188519],"type":"Point"}
}