{
  "type": "Feature",
  "properties": {
    "addr:full":"1 Plas Glen Rosa Penarth The Vale of Glamorgan CF64 1TS",
    "addr:housenumber":"1",
    "addr:postcode":"cf64 1ts",
    "addr:street":"Plas Glen Rosa;Vale",
    "iso:country":"GB",
    "sg:address":"1 Plas Glen Rosa",
    "sg:city":"Penarth",
    "sg:classifiers":[
        {
            "category":"Professional",
            "subcategory":"Management & Consulting",
            "type":"Services"
        }
    ],
    "sg:phone":"+44 29 2070 7442",
    "sg:postcode":"CF64 1TS",
    "sg:province":"The Vale of Glamorgan",
    "sg:tags":[
        "consultant",
        "business"
    ],
    "wof:name":"The Laird Consultancy",
    "wof:placetype":"venue"
},
  "geometry": {"coordinates":[-3.1761090755,51.4442405701],"type":"Point"}
}