{
  "type": "Feature",
  "properties": {
    "iso:country":"GB",
    "sg:address":"London Road",
    "sg:city":"Wellingborough",
    "sg:classifiers":[
        {
            "category":"Shopping",
            "subcategory":"Clothing, Apparel, & Fashions",
            "type":"Retail Goods"
        }
    ],
    "sg:phone":"+44 1933 225666",
    "sg:postcode":"NN8 2QX",
    "sg:province":"Northamptonshire",
    "sg:tags":[
        "clothing",
        "fabric"
    ],
    "wof:name":"Gloverall Plc",
    "wof:placetype":"venue"
},
  "geometry": {"coordinates":[-0.689837,52.299042],"type":"Point"}
}