{
  "type": "Feature",
  "properties": {
    "addr:full":"35 Woodhedge Drive, Thorneywood Nottingham Nottinghamshire NG3 6LU",
    "addr:housenumber":"35",
    "addr:postcode":"ng3 6lu",
    "addr:street":"Woodhedge Drive",
    "iso:country":"GB",
    "sg:address":"35 Woodhedge Drive, Thorneywood",
    "sg:city":"Nottingham",
    "sg:classifiers":[
        {
            "category":"Professional",
            "subcategory":"Engineering",
            "type":"Services"
        }
    ],
    "sg:phone":"+44 115 958 5601",
    "sg:postcode":"NG3 6LU",
    "sg:province":"Nottinghamshire",
    "sg:tags":[
        "contractor",
        "electrical",
        "engineer"
    ],
    "wof:name":"H S T Electrical & Security",
    "wof:placetype":"venue"
},
  "geometry": {"coordinates":[-1.120919,52.972134],"type":"Point"}
}