{
  "type": "Feature",
  "properties": {
    "iso:country":"GB",
    "sg:address":"50 Cowick Street, St Thomas",
    "sg:city":"Exeter",
    "sg:classifiers":[
        {
            "category":"Professional",
            "subcategory":"Accounting & Tax Preparation",
            "type":"Services"
        }
    ],
    "sg:postcode":"EX4 1AP",
    "sg:province":"Devon",
    "sg:tags":[
        "accountant",
        "chartered"
    ],
    "wof:name":"Alexander Maitland Ltd",
    "wof:placetype":"venue"
},
  "geometry": {"coordinates":[-3.542913,50.715527],"type":"Point"}
}