{
  "type": "Feature",
  "properties": {
    "iso:country":"GB",
    "sg:address":"119 London Rd, Headington",
    "sg:city":"Oxford",
    "sg:classifiers":[
        {
            "category":"Shopping",
            "subcategory":"Thrift Store",
            "type":"Retail Goods"
        }
    ],
    "sg:phone":"+44 1865 764400",
    "sg:postcode":"OX3 9HZ",
    "sg:province":"Oxfordshire",
    "sg:tags":[
        "shop",
        "charity"
    ],
    "wof:name":"Sobell House Hospice Charity",
    "wof:placetype":"venue"
},
  "geometry": {"coordinates":[-1.210581,51.760414],"type":"Point"}
}