{
  "type": "Feature",
  "properties": {
    "addr:full":"24 Ellison St Gateshead Tyne and Wear NE8 1AY",
    "addr:housenumber":"24",
    "addr:postcode":"ne8 1ay",
    "addr:street":"Ellison St",
    "iso:country":"GB",
    "sg:address":"24 Ellison St",
    "sg:city":"Gateshead",
    "sg:classifiers":[
        {
            "category":"Personal",
            "type":"Services"
        }
    ],
    "sg:phone":"+44 191 477 0004",
    "sg:postcode":"NE8 1AY",
    "sg:province":"Tyne and Wear",
    "sg:tags":[
        "wedding"
    ],
    "wof:name":"Blushing Brides",
    "wof:placetype":"venue"
},
  "geometry": {"coordinates":[-1.6018669605,54.963306427],"type":"Point"}
}