{
  "type": "Feature",
  "properties": {
    "addr:full":"4 Pier La, Arnside Carnforth Cumbria LA5 0DA",
    "addr:housenumber":"4",
    "addr:postcode":"la5 0da",
    "addr:street":"Pier La Arnside",
    "iso:country":"GB",
    "sg:address":"4 Pier La, Arnside",
    "sg:city":"Carnforth",
    "sg:classifiers":[
        {
            "category":"Real Estate",
            "subcategory":"Real Estate Agent",
            "type":"Services"
        }
    ],
    "sg:postcode":"LA5 0DA",
    "sg:province":"Cumbria",
    "wof:name":"Home & Property Link",
    "wof:placetype":"venue"
},
  "geometry": {"coordinates":[-2.834194,54.20211],"type":"Point"}
}