{
  "type": "Feature",
  "properties": {
    "iso:country":"GB",
    "sg:address":"17-19 Long La",
    "sg:city":"Uxbridge",
    "sg:classifiers":[
        {
            "category":"Parking",
            "type":"Transportation"
        }
    ],
    "sg:phone":"+44 1895 676767",
    "sg:postcode":"UB10 8QU",
    "sg:province":"Greater London",
    "sg:tags":[
        "car",
        "valet"
    ],
    "wof:name":"Diamond Car Valeting",
    "wof:placetype":"venue"
},
  "geometry": {"coordinates":[-0.444114,51.562794],"type":"Point"}
}