{
  "type": "Feature",
  "properties": {
    "addr:full":"The Dairy, Loseley Park Guildford Surrey GU3 1HS",
    "addr:postcode":"gu3 1hs",
    "iso:country":"GB",
    "sg:address":"The Dairy, Loseley Park",
    "sg:city":"Guildford",
    "sg:classifiers":[
        {
            "category":"Professional",
            "type":"Services"
        }
    ],
    "sg:postcode":"GU3 1HS",
    "sg:province":"Surrey",
    "sg:tags":[
        "caterer"
    ],
    "wof:name":"Creative Catering",
    "wof:placetype":"venue"
},
  "geometry": {"coordinates":[-0.6327069998,51.220703125],"type":"Point"}
}