{
  "type": "Feature",
  "properties": {
    "addr:full":"Bank Street Congleton Cheshire CW12 1ES",
    "addr:postcode":"cw12 1es",
    "addr:street":"Bank Street",
    "iso:country":"GB",
    "sg:address":"Bank Street",
    "sg:city":"Congleton",
    "sg:classifiers":[
        {
            "category":"Wholesale",
            "subcategory":"Scrap",
            "type":"Manufacturing & Wholesale Goods"
        }
    ],
    "sg:postcode":"CW12 1ES",
    "sg:province":"Cheshire",
    "sg:tags":[
        "breaker",
        "dismantlers"
    ],
    "wof:name":"Lacey's Auto Spares",
    "wof:placetype":"venue"
},
  "geometry": {"coordinates":[-2.208965,53.163513],"type":"Point"}
}