{
  "type": "Feature",
  "properties": {
    "iso:country":"GB",
    "sg:address":"87 High Street South",
    "sg:city":"Dunstable",
    "sg:classifiers":[
        {
            "category":"Professional",
            "subcategory":"Computer Services",
            "type":"Services"
        }
    ],
    "sg:phone":"+44 1582 478877",
    "sg:postcode":"LU6 3SF",
    "sg:province":"Bedfordshire",
    "sg:tags":[
        "consultant"
    ],
    "wof:name":"Corporate Solutions",
    "wof:placetype":"venue"
},
  "geometry": {"coordinates":[-0.51684,51.883636],"type":"Point"}
}