{
  "type": "Feature",
  "properties": {
    "addr:full":"4 Lonesome Depot, Leonards Rd, Stretham Vale London Greater London SW16 2HN",
    "addr:housenumber":"4",
    "addr:postcode":"sw16 2hn",
    "addr:street":"Lonesome Depot Leonards Rd",
    "iso:country":"GB",
    "sg:address":"4 Lonesome Depot, Leonards Rd, Stretham Vale",
    "sg:city":"London",
    "sg:classifiers":[
        {
            "category":"Building & Trades",
            "subcategory":"Construction",
            "type":"Services"
        }
    ],
    "sg:postcode":"SW16 2HN",
    "sg:province":"Greater London",
    "sg:tags":[
        "guttering"
    ],
    "wof:name":"Davies,G,",
    "wof:placetype":"venue"
},
  "geometry": {"coordinates":[-0.12498,51.42667],"type":"Point"}
}