{
  "type": "Feature",
  "properties": {
    "addr:full":"26 Swanston Rd Edinburgh City of Edinburgh EH10 7BB",
    "addr:housenumber":"26",
    "addr:postcode":"eh10 7bb",
    "addr:street":"Swanston Rd",
    "iso:country":"GB",
    "sg:address":"26 Swanston Rd",
    "sg:city":"Edinburgh",
    "sg:classifiers":[
        {
            "category":"Retail",
            "subcategory":"Driving School",
            "type":"Services"
        }
    ],
    "sg:phone":"+44 131 445 5212",
    "sg:postcode":"EH10 7BB",
    "sg:province":"City of Edinburgh",
    "wof:name":"Susan Kidston",
    "wof:placetype":"venue"
},
  "geometry": {"coordinates":[-3.2022590637,55.9008560181],"type":"Point"}
}