{
  "type": "Feature",
  "properties": {
    "addr:full":"Citi Aeron Lampeter Carmarthenshire SA48 8DD",
    "addr:postcode":"sa48 8dd",
    "addr:street":"Carmarthenshire",
    "iso:country":"GB",
    "sg:address":"Citi Aeron",
    "sg:city":"Lampeter",
    "sg:classifiers":[
        {
            "category":"Travel",
            "subcategory":"Hotels & Motels",
            "type":"Entertainment"
        }
    ],
    "sg:phone":"+44 1570 470625",
    "sg:postcode":"SA48 8DD",
    "sg:province":"Carmarthenshire",
    "wof:name":"Tyglyn Aeron Country Hotel",
    "wof:placetype":"venue"
},
  "geometry": {"coordinates":[-4.1952390671,52.2107009888],"type":"Point"}
}