{
  "type": "Feature",
  "properties": {
    "addr:full":"31 Eaton Crescent Swansea Neath Port Talbot SA1 4QL",
    "addr:housenumber":"31",
    "addr:postcode":"sa1 4ql",
    "addr:street":"Eaton Crescent",
    "iso:country":"GB",
    "sg:address":"31 Eaton Crescent",
    "sg:city":"Swansea",
    "sg:classifiers":[
        {
            "category":"Health Services",
            "subcategory":"Nursing And Care Facility",
            "type":"Services"
        }
    ],
    "sg:postcode":"SA1 4QL",
    "sg:province":"Neath Port Talbot",
    "sg:tags":[
        "home"
    ],
    "wof:name":"St Anne's Nursing Home",
    "wof:placetype":"venue"
},
  "geometry": {"coordinates":[-3.9648559093,51.6169662476],"type":"Point"}
}