{
  "type": "Feature",
  "properties": {
    "iso:country":"GB",
    "sg:address":"40 Ivanhoe Road, Southwark",
    "sg:city":"London",
    "sg:classifiers":[
        {
            "category":"Farming",
            "subcategory":"Nursery",
            "type":"Manufacturing & Wholesale Goods"
        }
    ],
    "sg:phone":"+44 20 7737 1719",
    "sg:postcode":"SE5 8DJ",
    "sg:province":"Greater London",
    "sg:tags":[
        "creche"
    ],
    "wof:name":"South East Montessori Nursery",
    "wof:placetype":"venue"
},
  "geometry": {"coordinates":[-0.0794780031,51.4652786255],"type":"Point"}
}