{
  "type": "Feature",
  "properties": {
    "addr:full":"Unit 9, Peverel Drive, Granby, Bletchley Milton Keynes Buckinghamshire MK1 1NL",
    "addr:housenumber":"unit 9",
    "addr:postcode":"mk1 1nl",
    "addr:street":"Peverel Drive",
    "iso:country":"GB",
    "sg:address":"Unit 9, Peverel Drive, Granby, Bletchley",
    "sg:city":"Milton Keynes",
    "sg:classifiers":[
        {
            "category":"Manufacturing",
            "subcategory":"Rubber & Plastics",
            "type":"Manufacturing & Wholesale Goods"
        }
    ],
    "sg:phone":"+44 1908 642578",
    "sg:postcode":"MK1 1NL",
    "sg:province":"Buckinghamshire",
    "sg:tags":[
        "product"
    ],
    "wof:name":"Plastics Fabrication & Printing Ltd",
    "wof:placetype":"venue"
},
  "geometry": {"coordinates":[-0.7379009724,52.0082931519],"type":"Point"}
}