{
  "type": "Feature",
  "properties": {
    "addr:full":"Little Sunnyside Farm Larkhall South Lanarkshire ML9 1RB",
    "addr:postcode":"ml9 1rb",
    "iso:country":"GB",
    "sg:address":"Little Sunnyside Farm",
    "sg:city":"Larkhall",
    "sg:classifiers":[
        {
            "category":"Farming",
            "subcategory":"Farm",
            "type":"Manufacturing & Wholesale Goods"
        }
    ],
    "sg:postcode":"ML9 1RB",
    "sg:province":"South Lanarkshire",
    "sg:tags":[
        "mixed",
        "crop"
    ],
    "wof:name":"Robert Moore",
    "wof:placetype":"venue"
},
  "geometry": {"coordinates":[-3.973058939,55.7384796143],"type":"Point"}
}