{
  "type": "Feature",
  "properties": {
    "iso:country":"GB",
    "sg:address":"183-185 Charlestown Road",
    "sg:city":"St Austell",
    "sg:classifiers":[
        {
            "category":"Real Estate",
            "subcategory":"Surveying",
            "type":"Services"
        }
    ],
    "sg:phone":"+44 1726 65663",
    "sg:postcode":"PL25 3NP",
    "sg:province":"Cornwall",
    "sg:tags":[
        "surveyor",
        "valuer"
    ],
    "wof:name":"Keith A Redfern",
    "wof:placetype":"venue"
},
  "geometry": {"coordinates":[-4.7627987862,50.3358421326],"type":"Point"}
}