{
  "type": "Feature",
  "properties": {
    "iso:country":"GB",
    "sg:address":"4 Cadham Centre",
    "sg:city":"Glenrothes",
    "sg:classifiers":[
        {
            "category":"Fast Food",
            "type":"Food & Drink"
        }
    ],
    "sg:phone":"+44 1592 622433",
    "sg:postcode":"KY7 6RU",
    "sg:province":"Fife",
    "sg:tags":[
        "away",
        "meal",
        "outlet",
        "take"
    ],
    "wof:name":"Red Star Chinese Carry Out",
    "wof:placetype":"venue"
},
  "geometry": {"coordinates":[-3.1685490608,56.2079811096],"type":"Point"}
}