{
  "type": "Feature",
  "properties": {
    "iso:country":"GB",
    "sg:address":"Prince Of Wales Dock, Langdon Road",
    "sg:city":"Swansea",
    "sg:classifiers":[
        {
            "category":"Home & Garden",
            "subcategory":"Building Materials",
            "type":"Retail Goods"
        }
    ],
    "sg:phone":"+44 1792 654949",
    "sg:postcode":"SA1 8QY",
    "sg:province":"Neath Port Talbot",
    "sg:tags":[
        "ready",
        "mixed",
        "concrete"
    ],
    "wof:name":"Arc-Powell Duffryn",
    "wof:placetype":"venue"
},
  "geometry": {"coordinates":[-3.940929,51.623154],"type":"Point"}
}