{
  "type": "Feature",
  "properties": {
    "iso:country":"GB",
    "sg:address":"Unit 33 Cibyn Industrial Estate",
    "sg:city":"Caernarfon",
    "sg:classifiers":[
        {
            "category":"Professional",
            "subcategory":"Lawyer & Legal Services",
            "type":"Services"
        },
        {
            "category":"Communications",
            "type":"Services"
        }
    ],
    "sg:phone":"+44 1286 671167",
    "sg:postcode":"LL55 2BD",
    "sg:province":"Gwynedd",
    "sg:tags":[
        "broadcasting",
        "solicitor"
    ],
    "wof:name":"Tonfedd Cyf",
    "wof:placetype":"venue"
},
  "geometry": {"coordinates":[-4.2528247833,53.1405830383],"type":"Point"}
}