{
  "type": "Feature",
  "properties": {
    "iso:country":"GB",
    "sg:address":"Alexandra Ho, Alexandra Terr",
    "sg:city":"Guildford",
    "sg:classifiers":[
        {
            "category":"Social Services",
            "subcategory":"Job Training",
            "type":"Services"
        }
    ],
    "sg:phone":"+44 1483 456486",
    "sg:postcode":"GU1 3DA",
    "sg:province":"Surrey",
    "sg:tags":[
        "translator",
        "interpreter"
    ],
    "wof:name":"Association Of Translation Companies The",
    "wof:placetype":"venue"
},
  "geometry": {"coordinates":[-0.560789,51.234959],"type":"Point"}
}