{
  "type": "Feature",
  "properties": {
    "iso:country":"GB",
    "sg:address":"25 Woodside Green, Woodside",
    "sg:city":"South Norwood",
    "sg:classifiers":[
        {
            "category":"Fast Food",
            "type":"Food & Drink"
        }
    ],
    "sg:phone":"+44 20 8654 4100",
    "sg:postcode":"SE25 5EY",
    "sg:province":"Greater London",
    "sg:tags":[
        "away",
        "take"
    ],
    "wof:name":"Sali Tandoori",
    "wof:placetype":"venue"
},
  "geometry": {"coordinates":[-0.06652,51.390839],"type":"Point"}
}