{
  "type": "Feature",
  "properties": {
    "addr:full":"13 Wesley St Otley North Yorkshire LS21 1AZ",
    "addr:housenumber":"13",
    "addr:postcode":"ls21 1az",
    "addr:street":"Wesley St",
    "iso:country":"GB",
    "sg:address":"13 Wesley St",
    "sg:city":"Otley",
    "sg:classifiers":[
        {
            "category":"Autos & Motor Vehicles",
            "subcategory":"Motorcycle Sales",
            "type":"Retail Goods"
        }
    ],
    "sg:phone":"+44 1943 463874",
    "sg:postcode":"LS21 1AZ",
    "sg:province":"North Yorkshire",
    "sg:tags":[
        "chauffeur",
        "driven",
        "car"
    ],
    "wof:name":"Otley Taxis",
    "wof:placetype":"venue"
},
  "geometry": {"coordinates":[-1.6918350458,53.9061584473],"type":"Point"}
}