{
  "type": "Feature",
  "properties": {
    "addr:full":"Lodge Farm, Kineton Warwick Warwickshire CV35 0JH",
    "addr:postcode":"cv35 0jh",
    "addr:street":"Lodge",
    "iso:country":"GB",
    "sg:address":"Lodge Farm, Kineton",
    "sg:city":"Warwick",
    "sg:classifiers":[
        {
            "category":"Manufacturing",
            "subcategory":"Wood Products",
            "type":"Manufacturing & Wholesale Goods"
        }
    ],
    "sg:postcode":"CV35 0JH",
    "sg:province":"Warwickshire",
    "sg:tags":[
        "maker",
        "cabinet"
    ],
    "wof:name":"Robins",
    "wof:placetype":"venue"
},
  "geometry": {"coordinates":[-1.5106090307,52.1565742493],"type":"Point"}
}