{
  "type": "Feature",
  "properties": {
    "addr:full":"52-54 Lower Breck Road Liverpool Merseyside L6 4BZ",
    "addr:housenumber":"52-54",
    "addr:postcode":"l6 4bz",
    "addr:street":"Lower Breck Road",
    "iso:country":"GB",
    "sg:address":"52-54 Lower Breck Road",
    "sg:city":"Liverpool",
    "sg:classifiers":[
        {
            "category":"Real Estate",
            "subcategory":"Real Estate Agent",
            "type":"Services"
        }
    ],
    "sg:phone":"+44 151 263 0332",
    "sg:postcode":"L6 4BZ",
    "sg:province":"Merseyside",
    "wof:name":"Lancashire Property Services (1997) Ltd.",
    "wof:placetype":"venue"
},
  "geometry": {"coordinates":[-2.9423971176,53.4244995117],"type":"Point"}
}