{
  "type": "Feature",
  "properties": {
    "iso:country":"GB",
    "sg:address":"10 Ardgowan Street",
    "sg:city":"Port Glasgow",
    "sg:classifiers":[
        {
            "category":"Retail",
            "subcategory":"Auto Repair",
            "type":"Services"
        }
    ],
    "sg:phone":"+44 1475 744555",
    "sg:postcode":"PA14 5DG",
    "sg:province":"Inverclyde",
    "sg:tags":[
        "body",
        "car",
        "modification",
        "related",
        "garage"
    ],
    "wof:name":"Blackhawk Equipment Services",
    "wof:placetype":"venue"
},
  "geometry": {"coordinates":[-4.680089,55.93224],"type":"Point"}
}