{
  "type": "Feature",
  "properties": {
    "addr:full":"307 Regents Park Road London Greater London N3 1DP",
    "addr:housenumber":"307",
    "addr:postcode":"n3 1dp",
    "addr:street":"Regents Park Road",
    "iso:country":"GB",
    "sg:address":"307 Regents Park Road",
    "sg:city":"London",
    "sg:classifiers":[
        {
            "category":"Insurance",
            "subcategory":"Insurance Agent",
            "type":"Services"
        }
    ],
    "sg:phone":"+44 20 8349 1996",
    "sg:postcode":"N3 1DP",
    "sg:province":"Greater London",
    "sg:tags":[
        "broker"
    ],
    "wof:name":"Bradstock Ltd.",
    "wof:placetype":"venue"
},
  "geometry": {"coordinates":[-0.196403,51.599289],"type":"Point"}
}