{
  "type": "Feature",
  "properties": {
    "addr:full":"Unit 3 Seymour Pl, St Johns Hill Wareham Dorset BH20 4NA",
    "addr:housenumber":"unit 3",
    "addr:postcode":"bh20 4na",
    "addr:street":"Seymour Pl St Johns Hill",
    "iso:country":"GB",
    "sg:address":"Unit 3 Seymour Pl, St Johns Hill",
    "sg:city":"Wareham",
    "sg:classifiers":[
        {
            "category":"Taxi",
            "type":"Transportation"
        }
    ],
    "sg:postcode":"BH20 4NA",
    "sg:province":"Dorset",
    "sg:tags":[
        "mini",
        "cab"
    ],
    "wof:name":"Astral Cars & Viceroy Taxis",
    "wof:placetype":"venue"
},
  "geometry": {"coordinates":[-2.108365,50.685326],"type":"Point"}
}