{
  "type": "Feature",
  "properties": {
    "addr:full":"The Hive Garage, Garsdale Sedbergh Cumbria LA10 5PQ",
    "addr:postcode":"la10 5pq",
    "iso:country":"GB",
    "sg:address":"The Hive Garage, Garsdale",
    "sg:city":"Sedbergh",
    "sg:classifiers":[
        {
            "category":"Retail",
            "subcategory":"Auto Repair",
            "type":"Services"
        }
    ],
    "sg:postcode":"LA10 5PQ",
    "sg:province":"Cumbria",
    "sg:tags":[
        "modification",
        "garage"
    ],
    "wof:name":"T P & A M Davenport",
    "wof:placetype":"venue"
},
  "geometry": {"coordinates":[-2.527837,54.321945],"type":"Point"}
}