{
  "type": "Feature",
  "properties": {
    "addr:full":"183 Paradise Shopping Precinct, Pasture Lane Bradford West Yorkshire BD7 2SB",
    "addr:housenumber":"183",
    "addr:postcode":"bd7 2sb",
    "addr:street":"Paradise;Pasture Lane",
    "iso:country":"GB",
    "sg:address":"183 Paradise Shopping Precinct, Pasture Lane",
    "sg:city":"Bradford",
    "sg:classifiers":[
        {
            "category":"Real Estate",
            "subcategory":"Real Estate Agent",
            "type":"Services"
        }
    ],
    "sg:phone":"+44 1274 521410",
    "sg:postcode":"BD7 2SB",
    "sg:province":"West Yorkshire",
    "wof:name":"Pitcliffe Properties Ltd.",
    "wof:placetype":"venue"
},
  "geometry": {"coordinates":[-1.80064,53.782551],"type":"Point"}
}