{
  "type": "Feature",
  "properties": {
    "addr:full":"2 Victoria Park, Alexander Street Dunoon Argyll and Bute PA23 7PP",
    "addr:housenumber":"2",
    "addr:postcode":"pa23 7pp",
    "addr:street":"Victoria Park Alexander Street",
    "iso:country":"GB",
    "sg:address":"2 Victoria Park, Alexander Street",
    "sg:city":"Dunoon",
    "sg:classifiers":[
        {
            "category":"Wholesale",
            "subcategory":"Non-durable Goods",
            "type":"Manufacturing & Wholesale Goods"
        }
    ],
    "sg:phone":"+44 1369 702756",
    "sg:postcode":"PA23 7PP",
    "sg:province":"Argyll and Bute",
    "sg:tags":[
        "carry",
        "cash"
    ],
    "wof:name":"Cowal Cash & Carry",
    "wof:placetype":"venue"
},
  "geometry": {"coordinates":[-4.9340219498,55.942111969],"type":"Point"}
}