{
  "type": "Feature",
  "properties": {
    "addr:full":"Liphook Road, Whitehall Bordon Hampshire GU35 9AF",
    "addr:postcode":"gu35 9af",
    "addr:street":"Liphook Road",
    "iso:country":"GB",
    "sg:address":"Liphook Road, Whitehall",
    "sg:city":"Bordon",
    "sg:classifiers":[
        {
            "category":"Building & Trades",
            "subcategory":"Equipment Rental",
            "type":"Services"
        }
    ],
    "sg:phone":"+44 1428 751555",
    "sg:postcode":"GU35 9AF",
    "sg:province":"Hampshire",
    "sg:tags":[
        "plant",
        "machinery"
    ],
    "wof:name":"J Devine Plant Hire Ltd.",
    "wof:placetype":"venue"
},
  "geometry": {"coordinates":[-0.8651139736,51.1088562012],"type":"Point"}
}