{
  "type": "Feature",
  "properties": {
    "iso:country":"GB",
    "sg:address":"42 Wates Way, Willow Lane Industrial Estate",
    "sg:city":"Mitcham",
    "sg:classifiers":[
        {
            "category":"Professional",
            "subcategory":"Printing & Photocopies",
            "type":"Services"
        }
    ],
    "sg:phone":"+44 20 8685 0440",
    "sg:postcode":"CR4 4TA",
    "sg:province":"Greater London",
    "sg:tags":[
        "printer"
    ],
    "wof:name":"Rephoto Litho Ltd.",
    "wof:placetype":"venue"
},
  "geometry": {"coordinates":[-0.165116,51.388603],"type":"Point"}
}