{
  "type": "Feature",
  "properties": {
    "addr:full":"Spearcey Farm, Spearcey Lane, Trull Taunton Devon TA3 7HW",
    "addr:postcode":"ta3 7hw",
    "addr:street":"Spearcey Lane",
    "iso:country":"GB",
    "sg:address":"Spearcey Farm, Spearcey Lane, Trull",
    "sg:city":"Taunton",
    "sg:classifiers":[
        {
            "category":"Farming",
            "subcategory":"Farm",
            "type":"Manufacturing & Wholesale Goods"
        }
    ],
    "sg:phone":"+44 1823 275868",
    "sg:postcode":"TA3 7HW",
    "sg:province":"Devon",
    "sg:tags":[
        "mixed",
        "crop"
    ],
    "wof:name":"Charles French & Son",
    "wof:placetype":"venue"
},
  "geometry": {"coordinates":[-3.1198570728,50.9940414429],"type":"Point"}
}