{
  "type": "Feature",
  "properties": {
    "addr:full":"Gwynfa Llanbedr Gwynedd LL45 2LE",
    "addr:postcode":"ll45 2le",
    "addr:street":"Llanbedr",
    "iso:country":"GB",
    "sg:address":"Gwynfa",
    "sg:city":"Llanbedr",
    "sg:classifiers":[
        {
            "category":"Social Services",
            "subcategory":"Retirement Home",
            "type":"Services"
        }
    ],
    "sg:phone":"+44 1766 512768",
    "sg:postcode":"LL45 2LE",
    "sg:province":"Gwynedd",
    "sg:tags":[
        "residential",
        "care"
    ],
    "wof:name":"Gofal Cader Care Ltd.",
    "wof:placetype":"venue"
},
  "geometry": {"coordinates":[-4.0971450806,52.8246917725],"type":"Point"}
}