{
  "type": "Feature",
  "properties": {
    "iso:country":"GB",
    "sg:address":"Town Hall Chambers, Barkers Pool",
    "sg:city":"Sheffield",
    "sg:classifiers":[
        {
            "category":"Government",
            "subcategory":"Office",
            "type":"Public Place"
        }
    ],
    "sg:phone":"+44 114 273 4610",
    "sg:postcode":"S1 1EN",
    "sg:province":"South Yorkshire",
    "sg:tags":[
        "local"
    ],
    "wof:name":"Sheffield Centre for Ecology & Environmental Manag",
    "wof:placetype":"venue"
},
  "geometry": {"coordinates":[-1.4719200134,53.3824806213],"type":"Point"}
}