{
  "type": "Feature",
  "properties": {
    "addr:full":"Unit 3 Kimpton Trade & Business, Centre 40 Kimpton Sutton Surrey SM3 9QP",
    "addr:housenumber":"unit 3 kimpton;40",
    "addr:postcode":"sm3 9qp",
    "addr:street":"Kimpton Sutton",
    "iso:country":"GB",
    "sg:address":"Unit 3 Kimpton Trade & Business, Centre 40 Kimpton",
    "sg:city":"Sutton",
    "sg:classifiers":[
        {
            "category":"Manufacturing",
            "subcategory":"Tools & Machinery",
            "type":"Manufacturing & Wholesale Goods"
        },
        {
            "category":"Insurance",
            "subcategory":"Insurance Agent",
            "type":"Services"
        }
    ],
    "sg:phone":"+44 20 8644 8494",
    "sg:postcode":"SM3 9QP",
    "sg:province":"Surrey",
    "sg:tags":[
        "society",
        "friendly"
    ],
    "wof:name":"James Insurance Services",
    "wof:placetype":"venue"
},
  "geometry": {"coordinates":[-0.2082419991,51.3745880127],"type":"Point"}
}