{
  "type": "Feature",
  "properties": {
    "iso:country":"GB",
    "sg:address":"22 Southernhay Avenue",
    "sg:city":"Bristol",
    "sg:classifiers":[
        {
            "category":"Building & Trades",
            "subcategory":"Plumbing",
            "type":"Services"
        }
    ],
    "sg:postcode":"BS8 4TJ",
    "sg:province":"City of Bristol",
    "sg:tags":[
        "heating"
    ],
    "wof:name":"Pauls Plumbing Services",
    "wof:placetype":"venue"
},
  "geometry": {"coordinates":[-2.609995,51.450687],"type":"Point"}
}