{
  "type": "Feature",
  "properties": {
    "iso:country":"GB",
    "sg:address":"196 Barnardo Street",
    "sg:city":"London",
    "sg:classifiers":[
        {
            "category":"Retail",
            "subcategory":"Storage",
            "type":"Services"
        }
    ],
    "sg:phone":"+44 20 7790 1563",
    "sg:postcode":"E1 0LH",
    "sg:province":"Greater London",
    "sg:tags":[
        "household",
        "removal"
    ],
    "wof:name":"T S Transport Removals & Storage Services",
    "wof:placetype":"venue"
},
  "geometry": {"coordinates":[-0.048019,51.51173],"type":"Point"}
}