{
  "type": "Feature",
  "properties": {
    "iso:country":"GB",
    "sg:address":"The Street",
    "sg:city":"Bury St Edmunds",
    "sg:classifiers":[
        {
            "category":"Retail",
            "subcategory":"Auto Repair",
            "type":"Services"
        }
    ],
    "sg:phone":"+44 1284 810022",
    "sg:postcode":"IP29 5AP",
    "sg:province":"Suffolk",
    "sg:tags":[
        "body",
        "car"
    ],
    "wof:name":"M & P Motor Services",
    "wof:placetype":"venue"
},
  "geometry": {"coordinates":[0.580745,52.243404],"type":"Point"}
}