{
  "type": "Feature",
  "properties": {
    "iso:country":"GB",
    "sg:address":"Unit 27, Carlton Lanes",
    "sg:city":"Castleford",
    "sg:classifiers":[
        {
            "category":"Sports & Exercise",
            "subcategory":"Sports Center",
            "type":"Entertainment"
        }
    ],
    "sg:phone":"+44 1977 604765",
    "sg:postcode":"WF10 1AD",
    "sg:province":"West Yorkshire",
    "sg:tags":[
        "shop",
        "good"
    ],
    "wof:name":"Allsports (Retail) Ltd.",
    "wof:placetype":"venue"
},
  "geometry": {"coordinates":[-1.350429,53.726501],"type":"Point"}
}