{
  "type": "Feature",
  "properties": {
    "addr:full":"Maitland Ho, Maitland St Preston Lancashire PR1 5XR",
    "addr:postcode":"pr1 5xr",
    "addr:street":"Maitland St",
    "iso:country":"GB",
    "sg:address":"Maitland Ho, Maitland St",
    "sg:city":"Preston",
    "sg:classifiers":[
        {
            "category":"Professional",
            "subcategory":"Business Services",
            "type":"Services"
        }
    ],
    "sg:phone":"+44 1772 655223",
    "sg:postcode":"PR1 5XR",
    "sg:province":"Lancashire",
    "sg:tags":[
        "hospitality",
        "corporate"
    ],
    "wof:name":"R G C L Ltd",
    "wof:placetype":"venue"
},
  "geometry": {"coordinates":[-2.6784939766,53.7633247375],"type":"Point"}
}