{
  "type": "Feature",
  "properties": {
    "addr:full":"Coton Hill Shrewsbury Shropshire SY1 2DZ",
    "addr:postcode":"sy1 2dz",
    "addr:street":"Coton Hill",
    "iso:country":"GB",
    "sg:address":"Coton Hill",
    "sg:city":"Shrewsbury",
    "sg:classifiers":[
        {
            "category":"Bars & Pubs",
            "type":"Food & Drink"
        }
    ],
    "sg:phone":"+44 1743 344338",
    "sg:postcode":"SY1 2DZ",
    "sg:province":"Shropshire",
    "sg:tags":[
        "pubs",
        "inn"
    ],
    "wof:name":"The Royal Oak",
    "wof:placetype":"venue"
},
  "geometry": {"coordinates":[-2.7532699108,52.7159042358],"type":"Point"}
}