{
  "type": "Feature",
  "properties": {
    "addr:full":"15 Chapel Lane Poole Dorset BH15 1NU",
    "addr:housenumber":"15",
    "addr:postcode":"bh15 1nu",
    "addr:street":"Chapel Lane",
    "iso:country":"GB",
    "sg:address":"15 Chapel Lane",
    "sg:city":"Poole",
    "sg:classifiers":[
        {
            "category":"Retail",
            "subcategory":"Repair Shop",
            "type":"Services"
        }
    ],
    "sg:phone":"+44 1202 682176",
    "sg:postcode":"BH15 1NU",
    "sg:province":"Dorset",
    "sg:tags":[
        "clocks",
        "watch"
    ],
    "wof:name":"Bacons Watch Repairs Service",
    "wof:placetype":"venue"
},
  "geometry": {"coordinates":[-1.984187,50.716],"type":"Point"}
}