{
  "type": "Feature",
  "properties": {
    "addr:full":"94a London Road Leicester Leicestershire LE2 0QW",
    "addr:housenumber":"94a",
    "addr:postcode":"le2 0qw",
    "addr:street":"London Road",
    "iso:country":"GB",
    "sg:address":"94a London Road",
    "sg:city":"Leicester",
    "sg:classifiers":[
        {
            "category":"Banks & Credit Unions",
            "subcategory":"Bank",
            "type":"Services"
        }
    ],
    "sg:phone":"+44 845 740 4404",
    "sg:postcode":"LE2 0QW",
    "sg:province":"Leicestershire",
    "wof:name":"Hsbc Bank Plc",
    "wof:placetype":"venue"
},
  "geometry": {"coordinates":[-1.121765,52.628693],"type":"Point"}
}