{
  "type": "Feature",
  "properties": {
    "iso:country":"GB",
    "sg:address":"35 Chastilian Road",
    "sg:city":"Dartford",
    "sg:classifiers":[
        {
            "category":"Personal",
            "subcategory":"Beauty Salon",
            "type":"Services"
        },
        {
            "category":"Personal",
            "subcategory":"Barber",
            "type":"Services"
        }
    ],
    "sg:phone":"+44 1322 275171",
    "sg:postcode":"DA1 3JP",
    "sg:province":"Kent",
    "sg:tags":[
        "unisex",
        "hairdresser"
    ],
    "wof:name":"Hi-Lites Hairdressers",
    "wof:placetype":"venue"
},
  "geometry": {"coordinates":[0.191271,51.443481],"type":"Point"}
}