{
  "type": "Feature",
  "properties": {
    "iso:country":"GB",
    "sg:address":"170 High Street",
    "sg:city":"Rochester",
    "sg:classifiers":[
        {
            "category":"Home & Garden",
            "subcategory":"Furniture",
            "type":"Retail Goods"
        }
    ],
    "sg:phone":"+44 1634 832010",
    "sg:postcode":"ME1 1EX",
    "sg:province":"Kent",
    "wof:name":"City Covers",
    "wof:placetype":"venue"
},
  "geometry": {"coordinates":[0.458813,51.350735],"type":"Point"}
}