{
  "type": "Feature",
  "properties": {
    "iso:country":"GB",
    "sg:address":"Whitcombe Manor",
    "sg:city":"Dorchester",
    "sg:classifiers":[
        {
            "category":"Farming",
            "subcategory":"Livestock Farm",
            "type":"Manufacturing & Wholesale Goods"
        }
    ],
    "sg:phone":"+44 1305 251298",
    "sg:postcode":"DT2 8NY",
    "sg:province":"Dorset",
    "sg:tags":[
        "others"
    ],
    "wof:name":"Whitcombe Manor Farms",
    "wof:placetype":"venue"
},
  "geometry": {"coordinates":[-2.40343,50.693424],"type":"Point"}
}