{
  "type": "Feature",
  "properties": {
    "addr:full":"34 High Street King's Langley Hertfordshire WD4 9HT",
    "addr:housenumber":"34",
    "addr:postcode":"wd4 9ht",
    "addr:street":"High Street",
    "iso:country":"GB",
    "sg:address":"34 High Street",
    "sg:city":"King's Langley",
    "sg:classifiers":[
        {
            "category":"Health Services",
            "subcategory":"Health Practitioner",
            "type":"Services"
        }
    ],
    "sg:phone":"+44 1923 261974",
    "sg:postcode":"WD4 9HT",
    "sg:province":"Hertfordshire",
    "sg:tags":[
        "physiotherapist"
    ],
    "wof:name":"Kings Langley Physiotherapy Clinic",
    "wof:placetype":"venue"
},
  "geometry": {"coordinates":[-0.449884,51.712326],"type":"Point"}
}