{
  "type": "Feature",
  "properties": {
    "iso:country":"GB",
    "sg:address":"414 Preston Old Road",
    "sg:city":"Blackburn",
    "sg:classifiers":[
        {
            "category":"Professional",
            "type":"Services"
        }
    ],
    "sg:phone":"+44 1254 200225",
    "sg:postcode":"BB2 5LP",
    "sg:province":"Lancashire",
    "sg:tags":[
        "caterer"
    ],
    "wof:name":"Nibbles Sandwich Bar",
    "wof:placetype":"venue"
},
  "geometry": {"coordinates":[-2.5203950405,53.7328720093],"type":"Point"}
}