{
  "type": "Feature",
  "properties": {
    "addr:full":"Vitalia House, Paradise Hemel Hempstead Hertfordshire HP2 4TF",
    "addr:postcode":"hp2 4tf",
    "addr:street":"Hemel Hempstead",
    "iso:country":"GB",
    "sg:address":"Vitalia House, Paradise",
    "sg:city":"Hemel Hempstead",
    "sg:classifiers":[
        {
            "category":"Professional",
            "subcategory":"Printing & Photocopies",
            "type":"Services"
        }
    ],
    "sg:phone":"+44 1442 230761",
    "sg:postcode":"HP2 4TF",
    "sg:province":"Hertfordshire",
    "sg:tags":[
        "printer"
    ],
    "wof:name":"E K Print",
    "wof:placetype":"venue"
},
  "geometry": {"coordinates":[-0.4685739875,51.7491455078],"type":"Point"}
}