{
  "type": "Feature",
  "properties": {
    "addr:full":"Cortry Close Poole Dorset BH12 4BQ",
    "addr:postcode":"bh12 4bq",
    "addr:street":"Cortry Close",
    "iso:country":"GB",
    "sg:address":"Cortry Close",
    "sg:city":"Poole",
    "sg:classifiers":[
        {
            "category":"Manufacturing",
            "subcategory":"Motor Vehicles & Parts",
            "type":"Manufacturing & Wholesale Goods"
        }
    ],
    "sg:phone":"+44 1202 743222",
    "sg:postcode":"BH12 4BQ",
    "sg:province":"Dorset",
    "sg:tags":[
        "bearing"
    ],
    "wof:name":"Moore International Ltd.",
    "wof:placetype":"venue"
},
  "geometry": {"coordinates":[-1.9150710106,50.7373847961],"type":"Point"}
}