{
  "type": "Feature",
  "properties": {
    "addr:full":"194-196 Fratton Road Portsmouth Hampshire PO1 5HD",
    "addr:postcode":"194-196;hampshire po1 5hd",
    "addr:street":"Fratton Road",
    "iso:country":"GB",
    "sg:address":"194-196 Fratton Road",
    "sg:city":"Portsmouth",
    "sg:classifiers":[
        {
            "category":"Communications",
            "subcategory":"Film & Video Production",
            "type":"Services"
        }
    ],
    "sg:phone":"+44 23 9273 0200",
    "sg:postcode":"PO1 5HD",
    "sg:province":"Hampshire",
    "sg:tags":[
        "tv",
        "studio"
    ],
    "wof:name":"A1 Electrics",
    "wof:placetype":"venue"
},
  "geometry": {"coordinates":[-1.0771189928,50.8009223938],"type":"Point"}
}