{
  "type": "Feature",
  "properties": {
    "addr:full":"64 Bloomfield Dr Bath Somerset BA2 2BG",
    "addr:housenumber":"64",
    "addr:postcode":"ba2 2bg",
    "addr:street":"Bloomfield Dr",
    "iso:country":"GB",
    "sg:address":"64 Bloomfield Dr",
    "sg:city":"Bath",
    "sg:classifiers":[
        {
            "category":"Professional",
            "subcategory":"Management & Consulting",
            "type":"Services"
        },
        {
            "category":"Arena",
            "subcategory":"Sports Club",
            "type":"Entertainment"
        }
    ],
    "sg:postcode":"BA2 2BG",
    "sg:province":"Somerset",
    "sg:tags":[
        "ground"
    ],
    "wof:name":"Matthews,Graham,",
    "wof:placetype":"venue"
},
  "geometry": {"coordinates":[-2.381732,51.363651],"type":"Point"}
}