{
  "type": "Feature",
  "properties": {
    "addr:full":"Clark Way, Motherwell Food Park Bellshill North Lanarkshire ML4 3NX",
    "addr:postcode":"ml4 3nx",
    "addr:street":"Clark Way;Food Park Bellshill",
    "iso:country":"GB",
    "sg:address":"Clark Way, Motherwell Food Park",
    "sg:city":"Bellshill",
    "sg:classifiers":[
        {
            "category":"Autos & Motor Vehicles",
            "subcategory":"Automobile Sales",
            "type":"Retail Goods"
        }
    ],
    "sg:phone":"+44 1698 327328",
    "sg:postcode":"ML4 3NX",
    "sg:province":"North Lanarkshire",
    "sg:tags":[
        "commercial"
    ],
    "wof:name":"M A N Central Scotland",
    "wof:placetype":"venue"
},
  "geometry": {"coordinates":[-4.0347337723,55.8267784119],"type":"Point"}
}