{
  "type": "Feature",
  "properties": {
    "addr:full":"46 Gipsy Lane, Earley Reading Berkshire RG6 7HD",
    "addr:housenumber":"46",
    "addr:postcode":"rg6 7hd",
    "addr:street":"Gipsy Lane",
    "iso:country":"GB",
    "sg:address":"46 Gipsy Lane, Earley",
    "sg:city":"Reading",
    "sg:classifiers":[
        {
            "category":"Health Services",
            "subcategory":"Optometrist",
            "type":"Services"
        }
    ],
    "sg:phone":"+44 118 935 1975",
    "sg:postcode":"RG6 7HD",
    "sg:province":"Berkshire",
    "sg:tags":[
        "optician"
    ],
    "wof:name":"Stephen Abery BSc MCOptom",
    "wof:placetype":"venue"
},
  "geometry": {"coordinates":[-0.910414,51.43293],"type":"Point"}
}