{
  "type": "Feature",
  "properties": {
    "iso:country":"GB",
    "sg:address":"Crosby Court, 28 George Street",
    "sg:city":"Birmingham",
    "sg:classifiers":[
        {
            "category":"Food & Beverages",
            "subcategory":"Meat & Fish",
            "type":"Retail Goods"
        }
    ],
    "sg:postcode":"B3 1QG",
    "sg:province":"West Midlands",
    "sg:tags":[
        "butcher"
    ],
    "wof:name":"Walter Smith (Birmingham) Ltd.",
    "wof:placetype":"venue"
},
  "geometry": {"coordinates":[-1.908092,52.48418],"type":"Point"}
}