{
  "type": "Feature",
  "properties": {
    "addr:full":"25 High Street, Pateley Bridge Harrogate North Yorkshire HG3 5AL",
    "addr:housenumber":"25",
    "addr:postcode":"hg3 5al",
    "addr:street":"High Street",
    "iso:country":"GB",
    "sg:address":"25 High Street, Pateley Bridge",
    "sg:city":"Harrogate",
    "sg:classifiers":[
        {
            "category":"Shopping",
            "subcategory":"Pharmacy",
            "type":"Retail Goods"
        }
    ],
    "sg:postcode":"HG3 5AL",
    "sg:province":"North Yorkshire",
    "sg:tags":[
        "pharmacist",
        "store",
        "drug",
        "chemist"
    ],
    "wof:name":"A Stebbing",
    "wof:placetype":"venue"
},
  "geometry": {"coordinates":[-1.759307,54.086414],"type":"Point"}
}