{
  "type": "Feature",
  "properties": {
    "iso:country":"GB",
    "sg:address":"Secretary, 38 Elizabeth St",
    "sg:city":"Workington",
    "sg:classifiers":[
        {
            "category":"Place Of Worship",
            "type":"Public Place"
        }
    ],
    "sg:phone":"+44 1900 602462",
    "sg:postcode":"CA14 4DB",
    "sg:province":"Cumbria",
    "wof:name":"Workington United Reformed Church",
    "wof:placetype":"venue"
},
  "geometry": {"coordinates":[-3.5500020981,54.6389808655],"type":"Point"}
}