{
  "type": "Feature",
  "properties": {
    "addr:full":"Dental Surgery Old Sick Bay Balm, Acara Road, Acara Road Kyle Highland IV40 8AE",
    "addr:postcode":"iv40 8ae",
    "addr:street":"Old Sick Bay Balm Acara Road Acara Road",
    "iso:country":"GB",
    "sg:address":"Dental Surgery Old Sick Bay Balm, Acara Road, Acara Road",
    "sg:city":"Kyle",
    "sg:classifiers":[
        {
            "category":"Health Services",
            "subcategory":"Dentist",
            "type":"Services"
        }
    ],
    "sg:phone":"+44 1599 534726",
    "sg:postcode":"IV40 8AE",
    "sg:province":"Highland",
    "wof:name":"L B Parsons",
    "wof:placetype":"venue"
},
  "geometry": {"coordinates":[-5.714052,57.280945],"type":"Point"}
}