{
  "type": "Feature",
  "properties": {
    "addr:full":"Oak Farm, Jill Lane, Sambourne Redditch Warwickshire B96 6ES",
    "addr:postcode":"b96 6es",
    "addr:street":"Oak;Jill Lane",
    "iso:country":"GB",
    "sg:address":"Oak Farm, Jill Lane, Sambourne",
    "sg:city":"Redditch",
    "sg:classifiers":[
        {
            "category":"Transit Center",
            "subcategory":"Passenger",
            "type":"Transportation"
        },
        {
            "category":"Retail",
            "subcategory":"Pet Boarding",
            "type":"Services"
        }
    ],
    "sg:phone":"+44 1527 893054",
    "sg:postcode":"B96 6ES",
    "sg:province":"Warwickshire",
    "sg:tags":[
        "kennel",
        "catteries"
    ],
    "wof:name":"The Kennels",
    "wof:placetype":"venue"
},
  "geometry": {"coordinates":[-1.913721,52.254528],"type":"Point"}
}