{
  "type": "Feature",
  "properties": {
    "addr:full":"38b Birley Moor Road Sheffield Derbyshire S12 4WD",
    "addr:housenumber":"38b",
    "addr:postcode":"s12 4wd",
    "addr:street":"Birley Moor Road",
    "iso:country":"GB",
    "sg:address":"38b Birley Moor Road",
    "sg:city":"Sheffield",
    "sg:classifiers":[
        {
            "category":"Food & Beverages",
            "subcategory":"Fruits & Vegetables",
            "type":"Retail Goods"
        }
    ],
    "sg:phone":"+44 114 239 8449",
    "sg:postcode":"S12 4WD",
    "sg:province":"Derbyshire",
    "sg:tags":[
        "greengrocer"
    ],
    "wof:name":"S & C Heathcote",
    "wof:placetype":"venue"
},
  "geometry": {"coordinates":[-1.4026739597,53.3498458862],"type":"Point"}
}