{
  "type": "Feature",
  "properties": {
    "addr:full":"5a Cleveland St Wolverhampton West Midlands WV1 3HL",
    "addr:housenumber":"5a",
    "addr:postcode":"wv1 3hl",
    "addr:street":"Cleveland St",
    "iso:country":"GB",
    "sg:address":"5a Cleveland St",
    "sg:city":"Wolverhampton",
    "sg:classifiers":[
        {
            "category":"Health Services",
            "subcategory":"Health Practitioner",
            "type":"Services"
        }
    ],
    "sg:phone":"+44 1902 428558",
    "sg:postcode":"WV1 3HL",
    "sg:province":"West Midlands",
    "sg:tags":[
        "acupuncture"
    ],
    "wof:name":"Chinese Medicine Centre",
    "wof:placetype":"venue"
},
  "geometry": {"coordinates":[-2.1292099953,52.5832023621],"type":"Point"}
}