{
  "type": "Feature",
  "properties": {
    "addr:full":"82 Seaside Eastbourne East Sussex BN22 7QP",
    "addr:housenumber":"82",
    "addr:postcode":"bn22 7qp",
    "addr:street":"Seaside",
    "iso:country":"GB",
    "sg:address":"82 Seaside",
    "sg:city":"Eastbourne",
    "sg:classifiers":[
        {
            "category":"Shopping",
            "subcategory":"Pharmacy",
            "type":"Retail Goods"
        }
    ],
    "sg:phone":"+44 1323 725860",
    "sg:postcode":"BN22 7QP",
    "sg:province":"East Sussex",
    "sg:tags":[
        "pharmacist",
        "chemist"
    ],
    "wof:name":"G E Newman Ltd.",
    "wof:placetype":"venue"
},
  "geometry": {"coordinates":[0.294904,50.771702],"type":"Point"}
}