{
  "type": "Feature",
  "properties": {
    "addr:full":"147 Port & Reclamation Co, Cottage Beck Road Scunthorpe Lincolnshire DN16 1TY",
    "addr:housenumber":"147",
    "addr:postcode":"dn16 1ty",
    "addr:street":"Port & Reclamation;Beck Road",
    "iso:country":"GB",
    "sg:address":"147 Port & Reclamation Co, Cottage Beck Road",
    "sg:city":"Scunthorpe",
    "sg:classifiers":[
        {
            "category":"Government",
            "subcategory":"Office",
            "type":"Public Place"
        }
    ],
    "sg:phone":"+44 1724 869159",
    "sg:postcode":"DN16 1TY",
    "sg:province":"Lincolnshire",
    "sg:tags":[
        "armed",
        "reserve"
    ],
    "wof:name":"Territorial Auxiliary & Volunteer Reserve Associat",
    "wof:placetype":"venue"
},
  "geometry": {"coordinates":[-0.6384999752,53.5844993591],"type":"Point"}
}