{
  "type": "Feature",
  "properties": {
    "iso:country":"GB",
    "sg:address":"Parrett Works",
    "sg:city":"Martock",
    "sg:classifiers":[
        {
            "category":"Wholesale",
            "subcategory":"Machinery & Supplies",
            "type":"Manufacturing & Wholesale Goods"
        }
    ],
    "sg:postcode":"TA12 6AE",
    "sg:province":"Somerset",
    "sg:tags":[
        "industrial",
        "commercial"
    ],
    "wof:name":"Amotec Product Engineers",
    "wof:placetype":"venue"
},
  "geometry": {"coordinates":[-2.7706689835,50.9672470093],"type":"Point"}
}