{
  "type": "Feature",
  "properties": {
    "iso:country":"GB",
    "sg:address":"Gorton Road, Openshaw",
    "sg:city":"Manchester",
    "sg:classifiers":[
        {
            "category":"Professional",
            "subcategory":"Printing & Photocopies",
            "type":"Services"
        }
    ],
    "sg:phone":"+44 161 223 8833",
    "sg:postcode":"M11 2DZ",
    "sg:province":"Greater Manchester",
    "sg:tags":[
        "printer"
    ],
    "wof:name":"Armin & Butler (Printers) Ltd.",
    "wof:placetype":"venue"
},
  "geometry": {"coordinates":[-2.1809539795,53.4734611511],"type":"Point"}
}