{
  "type": "Feature",
  "properties": {
    "iso:country":"GB",
    "sg:address":"27 Bell Alley",
    "sg:city":"Leighton Buzzard",
    "sg:classifiers":[
        {
            "category":"Farming",
            "subcategory":"Livestock Farm",
            "type":"Manufacturing & Wholesale Goods"
        },
        {
            "category":"Shopping",
            "subcategory":"Florist",
            "type":"Retail Goods"
        }
    ],
    "sg:postcode":"LU7 1DG",
    "sg:province":"Bedfordshire",
    "sg:tags":[
        "breeder"
    ],
    "wof:name":"Stacey,Janet,",
    "wof:placetype":"venue"
},
  "geometry": {"coordinates":[-0.660904,51.916294],"type":"Point"}
}