{
  "type": "Feature",
  "properties": {
    "addr:full":"5 Gossops Parade Crawley West Sussex RH11 8HH",
    "addr:housenumber":"5",
    "addr:postcode":"rh11 8hh",
    "addr:street":"Gossops Parade",
    "iso:country":"GB",
    "sg:address":"5 Gossops Parade",
    "sg:city":"Crawley",
    "sg:classifiers":[
        {
            "category":"Retail",
            "subcategory":"Laundry & Dry Cleaning",
            "type":"Services"
        }
    ],
    "sg:phone":"+44 1293 544033",
    "sg:postcode":"RH11 8HH",
    "sg:province":"West Sussex",
    "sg:tags":[
        "launderette"
    ],
    "wof:name":"Gatwick Laundries",
    "wof:placetype":"venue"
},
  "geometry": {"coordinates":[-0.2102150023,51.1129112244],"type":"Point"}
}