{
  "type": "Feature",
  "properties": {
    "iso:country":"GB",
    "sg:address":"Home Farm, Chapel Lane, Little Hadham",
    "sg:city":"Ware",
    "sg:classifiers":[
        {
            "category":"Farming",
            "subcategory":"Crops",
            "type":"Manufacturing & Wholesale Goods"
        },
        {
            "category":"Farming",
            "subcategory":"Livestock Farm",
            "type":"Manufacturing & Wholesale Goods"
        }
    ],
    "sg:phone":"+44 1279 771223",
    "sg:postcode":"SG11 2AB",
    "sg:province":"Hertfordshire",
    "sg:tags":[
        "arable",
        "others"
    ],
    "wof:name":"S A & C H Stigwood",
    "wof:placetype":"venue"
},
  "geometry": {"coordinates":[0.0898979977,51.8844528198],"type":"Point"}
}