{
  "type": "Feature",
  "properties": {
    "iso:country":"GB",
    "sg:address":"Broomhill",
    "sg:city":"Downham Market",
    "sg:classifiers":[
        {
            "category":"Autos & Motor Vehicles",
            "subcategory":"Fuel & Gas Station",
            "type":"Retail Goods"
        }
    ],
    "sg:phone":"+44 1366 386700",
    "sg:postcode":"PE38 9QY",
    "sg:province":"Cambridgeshire",
    "sg:tags":[
        "petrol",
        "filling"
    ],
    "wof:name":"Downham Petroleum Co. Ltd.",
    "wof:placetype":"venue"
},
  "geometry": {"coordinates":[0.387425,52.609852],"type":"Point"}
}