{
  "type": "Feature",
  "properties": {
    "iso:country":"GB",
    "sg:address":"10 St Georges Terrace",
    "sg:city":"Millom",
    "sg:classifiers":[
        {
            "category":"Shopping",
            "subcategory":"Florist",
            "type":"Retail Goods"
        }
    ],
    "sg:phone":"+44 1229 774367",
    "sg:postcode":"LA18 4DB",
    "sg:province":"Cumbria",
    "wof:name":"I Spy",
    "wof:placetype":"venue"
},
  "geometry": {"coordinates":[-3.269436,54.209518],"type":"Point"}
}