{
  "type": "Feature",
  "properties": {
    "iso:country":"GB",
    "sg:address":"33 Westfied Gardens",
    "sg:city":"Harrow",
    "sg:classifiers":[
        {
            "category":"Retail",
            "subcategory":"Auto Rental",
            "type":"Services"
        },
        {
            "category":"Autos & Motor Vehicles",
            "subcategory":"Motorcycle Sales",
            "type":"Retail Goods"
        }
    ],
    "sg:phone":"+44 20 8883 2991",
    "sg:postcode":"HA3 9EH",
    "sg:province":"Greater London",
    "sg:tags":[
        "chauffeur",
        "driven",
        "hire",
        "car"
    ],
    "wof:name":"Alexandra Chauffeur Hire",
    "wof:placetype":"venue"
},
  "geometry": {"coordinates":[-0.301235,51.589382],"type":"Point"}
}