{
  "type": "Feature",
  "properties": {
    "addr:full":"Ala Cottage, Ala Rd Pwllheli Gwynedd LL53 5BU",
    "addr:postcode":"ll53 5bu",
    "addr:street":"Ala Rd",
    "iso:country":"GB",
    "sg:address":"Ala Cottage, Ala Rd",
    "sg:city":"Pwllheli",
    "sg:classifiers":[
        {
            "category":"Retail",
            "subcategory":"Veterinary Services",
            "type":"Services"
        }
    ],
    "sg:phone":"+44 1758 701816",
    "sg:postcode":"LL53 5BU",
    "sg:province":"Gwynedd",
    "sg:tags":[
        "surgeon"
    ],
    "wof:name":"Milfeddygon Deufor",
    "wof:placetype":"venue"
},
  "geometry": {"coordinates":[-4.4143137932,52.8898468018],"type":"Point"}
}