{
  "type": "Feature",
  "properties": {
    "addr:full":"Rear Off 7 Market St Garage, Adlington Chorley Lancashire PR7 4HE",
    "addr:housenumber":"rear;7",
    "addr:postcode":"pr7 4he",
    "addr:street":"Off;Market",
    "iso:country":"GB",
    "sg:address":"Rear Off 7 Market St Garage, Adlington",
    "sg:city":"Chorley",
    "sg:classifiers":[
        {
            "category":"Bus Charters",
            "type":"Transportation"
        }
    ],
    "sg:postcode":"PR7 4HE",
    "sg:province":"Lancashire",
    "sg:tags":[
        "mini",
        "hire",
        "leasing"
    ],
    "wof:name":"White Bear Mini Coaches",
    "wof:placetype":"venue"
},
  "geometry": {"coordinates":[-2.6048800945,53.6119918823],"type":"Point"}
}