{
  "type": "Feature",
  "properties": {
    "iso:country":"GB",
    "sg:address":"1 Willie Snaith Road",
    "sg:city":"Newmarket",
    "sg:classifiers":[
        {
            "category":"Building & Trades",
            "subcategory":"Construction",
            "type":"Services"
        },
        {
            "category":"Utilities",
            "subcategory":"Natural Gas",
            "type":"Services"
        }
    ],
    "sg:phone":"+44 1638 665000",
    "sg:postcode":"CB8 7GG",
    "sg:province":"Cambridgeshire",
    "sg:tags":[
        "valve",
        "manufacturer"
    ],
    "wof:name":"International Valves Ltd.",
    "wof:placetype":"venue"
},
  "geometry": {"coordinates":[0.396596998,52.2594909668],"type":"Point"}
}