{
  "type": "Feature",
  "properties": {
    "addr:full":"5 Torrens St Clerkenwell Greater London EC1V 1NQ",
    "addr:housenumber":"5",
    "addr:postcode":"ec1v 1nq",
    "addr:street":"Torrens St",
    "iso:country":"GB",
    "sg:address":"5 Torrens St",
    "sg:city":"Clerkenwell",
    "sg:classifiers":[
        {
            "category":"Professional",
            "subcategory":"Art Services",
            "type":"Services"
        }
    ],
    "sg:phone":"+44 20 7833 5626",
    "sg:postcode":"EC1V 1NQ",
    "sg:province":"Greater London",
    "sg:tags":[
        "graphic",
        "designer"
    ],
    "wof:name":"Struktur Design",
    "wof:placetype":"venue"
},
  "geometry": {"coordinates":[-0.10523,51.532269],"type":"Point"}
}