{
  "type": "Feature",
  "properties": {
    "addr:full":"2nd Floor St Mathews House Sheffield South Yorkshire S1 4FT",
    "addr:housenumber":"2nd floor",
    "addr:postcode":"s1 4ft",
    "addr:street":"St",
    "iso:country":"GB",
    "sg:address":"2nd Floor St Mathews House",
    "sg:city":"Sheffield",
    "sg:classifiers":[
        {
            "category":"Organizations",
            "subcategory":"Non-profit Organization",
            "type":"Services"
        }
    ],
    "sg:phone":"+44 114 272 2220",
    "sg:postcode":"S1 4FT",
    "sg:province":"South Yorkshire",
    "sg:tags":[
        "organisation",
        "voluntary",
        "charity"
    ],
    "wof:name":"Uncaged Ltd.",
    "wof:placetype":"venue"
},
  "geometry": {"coordinates":[-1.477639,53.381615],"type":"Point"}
}