{
  "type": "Feature",
  "properties": {
    "iso:country":"GB",
    "sg:address":"St Nicholas House, 14 The Mount",
    "sg:city":"Guildford",
    "sg:classifiers":[
        {
            "category":"Banks & Credit Unions",
            "subcategory":"Financial Services",
            "type":"Services"
        }
    ],
    "sg:phone":"+44 1483 569998",
    "sg:postcode":"GU2 4HN",
    "sg:province":"Surrey",
    "sg:tags":[
        "consultant"
    ],
    "wof:name":"Marlborough Park Investments Ltd.",
    "wof:placetype":"venue"
},
  "geometry": {"coordinates":[-0.579147,51.23457],"type":"Point"}
}