{
  "type": "Feature",
  "properties": {
    "addr:full":"Rodenhurst Farm, Timberhonger Lane Bromsgrove Worcestershire B61 9DP",
    "addr:postcode":"b61 9dp",
    "addr:street":"Timberhonger Lane",
    "iso:country":"GB",
    "sg:address":"Rodenhurst Farm, Timberhonger Lane",
    "sg:city":"Bromsgrove",
    "sg:classifiers":[
        {
            "category":"Farming",
            "subcategory":"Farm",
            "type":"Manufacturing & Wholesale Goods"
        }
    ],
    "sg:postcode":"B61 9DP",
    "sg:province":"Worcestershire",
    "sg:tags":[
        "mixed",
        "crop"
    ],
    "wof:name":"P J & M E Powell",
    "wof:placetype":"venue"
},
  "geometry": {"coordinates":[-2.0581119061,52.3365936279],"type":"Point"}
}