{
  "type": "Feature",
  "properties": {
    "addr:full":"101 Hennings Park Rd Poole Dorset BH15 3QY",
    "addr:housenumber":"101",
    "addr:postcode":"bh15 3qy",
    "addr:street":"Hennings Park Rd",
    "iso:country":"GB",
    "sg:address":"101 Hennings Park Rd",
    "sg:city":"Poole",
    "sg:classifiers":[
        {
            "category":"Retail",
            "subcategory":"Repair Shop",
            "type":"Services"
        }
    ],
    "sg:phone":"+44 1202 673476",
    "sg:postcode":"BH15 3QY",
    "sg:province":"Dorset",
    "sg:tags":[
        "maintenance"
    ],
    "wof:name":"M E Brown",
    "wof:placetype":"venue"
},
  "geometry": {"coordinates":[-1.969819,50.731785],"type":"Point"}
}