{
  "type": "Feature",
  "properties": {
    "iso:country":"GB",
    "sg:address":"3 St. Martins Square",
    "sg:city":"Leicester",
    "sg:classifiers":[
        {
            "category":"Restaurant",
            "type":"Food & Drink"
        }
    ],
    "sg:phone":"+44 116 253 3977",
    "sg:postcode":"LE1 5DF",
    "sg:province":"Leicestershire",
    "wof:name":"Joe Rigatoni Restaurant",
    "wof:placetype":"venue"
},
  "geometry": {"coordinates":[-1.135161,52.634506],"type":"Point"}
}