{
  "type": "Feature",
  "properties": {
    "addr:full":"3 St. Martins Square Leicester Leicestershire LE1 5DF",
    "addr:housenumber":"3",
    "addr:postcode":"le1 5df",
    "addr:street":"St. Martins Square",
    "iso:country":"GB",
    "sg:address":"3 St. Martins Square",
    "sg:city":"Leicester",
    "sg:classifiers":[
        {
            "category":"Restaurant",
            "type":"Food & Drink"
        }
    ],
    "sg:phone":"+44 116 253 3977",
    "sg:postcode":"LE1 5DF",
    "sg:province":"Leicestershire",
    "wof:name":"Joe Rigatoni Restaurant",
    "wof:placetype":"venue"
},
  "geometry": {"coordinates":[-1.135161,52.634506],"type":"Point"}
}