{
  "type": "Feature",
  "properties": {
    "addr:full":"12 Lidsey Road Banbury Oxfordshire OX16 0ND",
    "addr:housenumber":"12",
    "addr:postcode":"ox16 0nd",
    "addr:street":"Lidsey Road",
    "iso:country":"GB",
    "sg:address":"12 Lidsey Road",
    "sg:city":"Banbury",
    "sg:classifiers":[
        {
            "category":"Building & Trades",
            "subcategory":"Construction",
            "type":"Services"
        }
    ],
    "sg:phone":"+44 1295 256164",
    "sg:postcode":"OX16 0ND",
    "sg:province":"Oxfordshire",
    "sg:tags":[
        "builder"
    ],
    "wof:name":"M L S Builders",
    "wof:placetype":"venue"
},
  "geometry": {"coordinates":[-1.3581299782,52.0592498779],"type":"Point"}
}