{
  "type": "Feature",
  "properties": {
    "addr:full":"29 Richard Street Chatham Kent ME4 4AH",
    "addr:housenumber":"29",
    "addr:postcode":"me4 4ah",
    "addr:street":"Richard Street",
    "iso:country":"GB",
    "sg:address":"29 Richard Street",
    "sg:city":"Chatham",
    "sg:classifiers":[
        {
            "category":"Bars & Pubs",
            "type":"Food & Drink"
        }
    ],
    "sg:phone":"+44 1634 813684",
    "sg:postcode":"ME4 4AH",
    "sg:province":"Kent",
    "sg:tags":[
        "pubs",
        "inn"
    ],
    "wof:name":"Shipwrights Arms",
    "wof:placetype":"venue"
},
  "geometry": {"coordinates":[0.5273510218,51.380859375],"type":"Point"}
}