{
  "type": "Feature",
  "properties": {
    "addr:full":"High Street, Bloxwich Walsall Staffordshire WS3 3JT",
    "addr:postcode":"ws3 3jt",
    "addr:street":"High Street",
    "iso:country":"GB",
    "sg:address":"High Street, Bloxwich",
    "sg:city":"Walsall",
    "sg:classifiers":[
        {
            "category":"Government",
            "subcategory":"Fire Station",
            "type":"Public Place"
        }
    ],
    "sg:phone":"+44 1922 475000",
    "sg:postcode":"WS3 3JT",
    "sg:province":"Staffordshire",
    "wof:name":"West Midlands Fire Service",
    "wof:placetype":"venue"
},
  "geometry": {"coordinates":[-2.0043148994,52.6176376343],"type":"Point"}
}