{
  "type": "Feature",
  "properties": {
    "addr:full":"20 Raglan Gardens, Oxhey Hall Watford Hertfordshire WD19 4LL",
    "addr:housenumber":"20",
    "addr:postcode":"wd19 4ll",
    "addr:street":"Raglan Gardens",
    "iso:country":"GB",
    "sg:address":"20 Raglan Gardens, Oxhey Hall",
    "sg:city":"Watford",
    "sg:classifiers":[
        {
            "category":"Building & Trades",
            "subcategory":"Construction",
            "type":"Services"
        }
    ],
    "sg:phone":"+44 1923 235650",
    "sg:postcode":"WD19 4LL",
    "sg:province":"Hertfordshire",
    "sg:tags":[
        "roofing"
    ],
    "wof:name":"A Flanagan & Son Roofing Contractors",
    "wof:placetype":"venue"
},
  "geometry": {"coordinates":[-0.400323987,51.6373672485],"type":"Point"}
}