{
  "type": "Feature",
  "properties": {
    "iso:country":"GB",
    "sg:address":"2 Mercantile House",
    "sg:city":"Colchester",
    "sg:classifiers":[
        {
            "category":"Shopping",
            "subcategory":"Gifts & Souvenirs",
            "type":"Retail Goods"
        }
    ],
    "sg:phone":"+44 1206 575159",
    "sg:postcode":"CO1 1JJ",
    "sg:province":"Essex",
    "sg:tags":[
        "shop"
    ],
    "wof:name":"Tim Costello",
    "wof:placetype":"venue"
},
  "geometry": {"coordinates":[0.89781,51.887829],"type":"Point"}
}