{
  "type": "Feature",
  "properties": {
    "iso:country":"GB",
    "sg:address":"26 Babbacombe Rd",
    "sg:city":"Torquay",
    "sg:classifiers":[
        {
            "category":"Social Services",
            "subcategory":"Retirement Home",
            "type":"Services"
        }
    ],
    "sg:phone":"+44 1803 328902",
    "sg:postcode":"TQ1 3SN",
    "sg:province":"Devon",
    "sg:tags":[
        "residential",
        "care"
    ],
    "wof:name":"Landscove",
    "wof:placetype":"venue"
},
  "geometry": {"coordinates":[-3.516501,50.479481],"type":"Point"}
}