{
  "type": "Feature",
  "properties": {
    "iso:country":"GB",
    "sg:address":"Hales Court, Stourbridge Road",
    "sg:city":"Halesowen",
    "sg:classifiers":[
        {
            "category":"Professional",
            "subcategory":"Computer Services",
            "type":"Services"
        }
    ],
    "sg:phone":"+44 121 585 7227",
    "sg:postcode":"B63 3TT",
    "sg:province":"West Midlands",
    "sg:tags":[
        "system",
        "software"
    ],
    "wof:name":"Photonic",
    "wof:placetype":"venue"
},
  "geometry": {"coordinates":[-2.06886,52.454948],"type":"Point"}
}