{
  "type": "Feature",
  "properties": {
    "addr:full":"Samuel House, St Chad Street Manchester Greater Manchester M8 8QA",
    "addr:postcode":"m8 8qa",
    "addr:street":"St Chad Street",
    "iso:country":"GB",
    "sg:address":"Samuel House, St Chad Street",
    "sg:city":"Manchester",
    "sg:classifiers":[
        {
            "category":"Building & Trades",
            "subcategory":"Equipment Rental",
            "type":"Services"
        }
    ],
    "sg:phone":"+44 161 834 7940",
    "sg:postcode":"M8 8QA",
    "sg:province":"Greater Manchester",
    "sg:tags":[
        "supply"
    ],
    "wof:name":"Ben David Samuel  Ltd.",
    "wof:placetype":"venue"
},
  "geometry": {"coordinates":[-2.238376,53.492157],"type":"Point"}
}