{
  "type": "Feature",
  "properties": {
    "addr:full":"35 Church Street Flint Flintshire CH6 5AD",
    "addr:housenumber":"35",
    "addr:postcode":"ch6 5ad",
    "addr:street":"Church Street",
    "iso:country":"GB",
    "sg:address":"35 Church Street",
    "sg:city":"Flint",
    "sg:classifiers":[
        {
            "category":"Real Estate",
            "subcategory":"Real Estate Agent",
            "type":"Services"
        }
    ],
    "sg:phone":"+44 1352 732331",
    "sg:postcode":"CH6 5AD",
    "sg:province":"Flintshire",
    "wof:name":"David W Pearse",
    "wof:placetype":"venue"
},
  "geometry": {"coordinates":[-3.1366689205,53.2482452393],"type":"Point"}
}