{
  "type": "Feature",
  "properties": {
    "addr:full":"10 High Street Dorking Surrey RH4 1AT",
    "addr:housenumber":"10",
    "addr:postcode":"rh4 1at",
    "addr:street":"High Street",
    "iso:country":"GB",
    "sg:address":"10 High Street",
    "sg:city":"Dorking",
    "sg:classifiers":[
        {
            "category":"Shopping",
            "subcategory":"Clothing, Apparel, & Fashions",
            "type":"Retail Goods"
        }
    ],
    "sg:phone":"+44 1306 882270",
    "sg:postcode":"RH4 1AT",
    "sg:province":"Surrey",
    "sg:tags":[
        "menswear"
    ],
    "wof:name":"Ian Munro",
    "wof:placetype":"venue"
},
  "geometry": {"coordinates":[-0.3327890038,51.2315711975],"type":"Point"}
}