{
  "type": "Feature",
  "properties": {
    "iso:country":"GB",
    "sg:address":"The Butts, Hulse Road",
    "sg:city":"Salisbury",
    "sg:classifiers":[
        {
            "category":"Community Center",
            "type":"Public Place"
        }
    ],
    "sg:phone":"+44 1722 339966",
    "sg:postcode":"SP1 3NR",
    "sg:province":"Wiltshire",
    "sg:tags":[
        "recreation",
        "leisure",
        "centre"
    ],
    "wof:name":"Salisbury Leisure Centre",
    "wof:placetype":"venue"
},
  "geometry": {"coordinates":[-1.798248,51.077633],"type":"Point"}
}