{
  "type": "Feature",
  "properties": {
    "iso:country":"GB",
    "sg:address":"4 Early Road",
    "sg:city":"Witney",
    "sg:classifiers":[
        {
            "category":"Shopping",
            "subcategory":"Shoes",
            "type":"Retail Goods"
        },
        {
            "category":"Home & Garden",
            "subcategory":"Carpets & Floor Coverings",
            "type":"Retail Goods"
        }
    ],
    "sg:phone":"+44 1993 703199",
    "sg:postcode":"OX28 1EN",
    "sg:province":"Oxfordshire",
    "sg:tags":[
        "carpets",
        "retailer",
        "rug",
        "matting",
        "footwear"
    ],
    "wof:name":"Terry May",
    "wof:placetype":"venue"
},
  "geometry": {"coordinates":[-1.474807,51.793934],"type":"Point"}
}