{
  "type": "Feature",
  "properties": {
    "addr:full":"Unit C, Field Street Wolverhampton West Midlands WV13 2NX",
    "addr:housenumber":"unit c",
    "addr:postcode":"wv13 2nx",
    "addr:street":"Field Street",
    "iso:country":"GB",
    "sg:address":"Unit C, Field Street",
    "sg:city":"Wolverhampton",
    "sg:classifiers":[
        {
            "category":"Manufacturing",
            "subcategory":"Metals",
            "type":"Manufacturing & Wholesale Goods"
        }
    ],
    "sg:phone":"+44 1902 635406",
    "sg:postcode":"WV13 2NX",
    "sg:province":"West Midlands",
    "sg:tags":[
        "fabricator",
        "aluminium",
        "mnfrs"
    ],
    "wof:name":"G V Aluminium Systems Ltd.",
    "wof:placetype":"venue"
},
  "geometry": {"coordinates":[-2.121669054,52.5886497498],"type":"Point"}
}