{
  "type": "Feature",
  "properties": {
    "addr:full":"New Line Road, Kirkby-in-ashfield Nottingham Nottinghamshire NG17 8JQ",
    "addr:postcode":"ng17 8jq",
    "addr:street":"Road",
    "iso:country":"GB",
    "sg:address":"New Line Road, Kirkby-in-ashfield",
    "sg:city":"Nottingham",
    "sg:classifiers":[
        {
            "category":"Shopping",
            "subcategory":"Clothing, Apparel, & Fashions",
            "type":"Retail Goods"
        }
    ],
    "sg:phone":"+44 1623 757748",
    "sg:postcode":"NG17 8JQ",
    "sg:province":"Nottinghamshire",
    "sg:tags":[
        "lingerie"
    ],
    "wof:name":"Lorien Textile Agency Ltd.",
    "wof:placetype":"venue"
},
  "geometry": {"coordinates":[-1.263517,53.099388],"type":"Point"}
}