{
  "type": "Feature",
  "properties": {
    "addr:full":"Unit 38, Unity Road, Lowmoor Business Park Nottingham Nottinghamshire NG17 7LE",
    "addr:housenumber":"unit 38",
    "addr:postcode":"park;ng17 7le",
    "addr:street":"Unity Road Lowmoor Business",
    "iso:country":"GB",
    "sg:address":"Unit 38, Unity Road, Lowmoor Business Park",
    "sg:city":"Nottingham",
    "sg:classifiers":[
        {
            "category":"Home & Garden",
            "subcategory":"Home Furnishings",
            "type":"Retail Goods"
        },
        {
            "category":"Shopping",
            "subcategory":"Crafts & Fabrics",
            "type":"Retail Goods"
        }
    ],
    "sg:phone":"+44 1623 722290",
    "sg:postcode":"NG17 7LE",
    "sg:province":"Nottinghamshire",
    "sg:tags":[
        "blind",
        "curtain",
        "fitting",
        "netting"
    ],
    "wof:name":"White Angel Curtain Co. Ltd.",
    "wof:placetype":"venue"
},
  "geometry": {"coordinates":[-1.2406740189,53.1096839905],"type":"Point"}
}