{
  "type": "Feature",
  "properties": {
    "addr:full":"16 West Row Stockton-on-tees Durham TS18 1BT",
    "addr:housenumber":"16",
    "addr:postcode":"ts18 1bt",
    "addr:street":"West Row",
    "iso:country":"GB",
    "sg:address":"16 West Row",
    "sg:city":"Stockton-on-tees",
    "sg:classifiers":[
        {
            "category":"Home & Garden",
            "subcategory":"Home Furnishings",
            "type":"Retail Goods"
        },
        {
            "category":"Manufacturing",
            "subcategory":"Textiles",
            "type":"Manufacturing & Wholesale Goods"
        }
    ],
    "sg:phone":"+44 1642 678394",
    "sg:postcode":"TS18 1BT",
    "sg:province":"Durham",
    "sg:tags":[
        "blind",
        "made-up",
        "fitting",
        "curtain"
    ],
    "wof:name":"Discount Curtains",
    "wof:placetype":"venue"
},
  "geometry": {"coordinates":[-1.3143789768,54.5636558533],"type":"Point"}
}