{
  "type": "Feature",
  "properties": {
    "iso:country":"GB",
    "sg:address":"47a Shibdon Road",
    "sg:city":"Blaydon-on-tyne",
    "sg:classifiers":[
        {
            "category":"Shopping",
            "subcategory":"News",
            "type":"Retail Goods"
        }
    ],
    "sg:phone":"+44 191 420 0848",
    "sg:postcode":"NE21 5LX",
    "sg:province":"Tyne and Wear",
    "sg:tags":[
        "newsagent"
    ],
    "wof:name":"Parkland Stores",
    "wof:placetype":"venue"
},
  "geometry": {"coordinates":[-1.701788,54.958347],"type":"Point"}
}