{
  "type": "Feature",
  "properties": {
    "iso:country":"GB",
    "sg:address":"1 Ash Hill Close, Bushey Heath",
    "sg:city":"Bushey",
    "sg:classifiers":[
        {
            "category":"Real Estate",
            "subcategory":"Real Estate Agent",
            "type":"Services"
        }
    ],
    "sg:postcode":"WD2 1BW",
    "sg:province":"Hertfordshire",
    "wof:name":"Rosemont Properties Ltd.",
    "wof:placetype":"venue"
},
  "geometry": {"coordinates":[-0.34032,51.633389],"type":"Point"}
}