{
  "type": "Feature",
  "properties": {
    "iso:country":"GB",
    "sg:address":"Auriol Close",
    "sg:city":"Worcester Park",
    "sg:classifiers":[
        {
            "category":"Professional",
            "type":"Services"
        }
    ],
    "sg:postcode":"KT4 7DR",
    "sg:province":"Surrey",
    "sg:tags":[
        "entertainer"
    ],
    "wof:name":"Mr Trickey Childrens Entertainer",
    "wof:placetype":"venue"
},
  "geometry": {"coordinates":[-0.257664,51.371769],"type":"Point"}
}