{
  "type": "Feature",
  "properties": {
    "iso:country":"GB",
    "sg:address":"Boclair Road, Milngavie",
    "sg:city":"Glasgow",
    "sg:classifiers":[
        {
            "category":"Home & Garden",
            "subcategory":"Garden Supply",
            "type":"Retail Goods"
        }
    ],
    "sg:phone":"+44 131 663 6778",
    "sg:postcode":"G62 6EP",
    "sg:province":"East Dunbartonshire",
    "sg:tags":[
        "nursery",
        "centre"
    ],
    "wof:name":"Findlay Clark Ltd.",
    "wof:placetype":"venue"
},
  "geometry": {"coordinates":[-4.3171238899,55.9368286133],"type":"Point"}
}