{
  "type": "Feature",
  "properties": {
    "iso:country":"GB",
    "sg:address":"6a Hargreaves St",
    "sg:city":"Burnley",
    "sg:classifiers":[
        {
            "category":"Professional",
            "subcategory":"Lawyer & Legal Services",
            "type":"Services"
        }
    ],
    "sg:phone":"+44 1282 427601",
    "sg:postcode":"BB11 1ES",
    "sg:province":"Lancashire",
    "sg:tags":[
        "solicitor"
    ],
    "wof:name":"Cooper Smith & Williams",
    "wof:placetype":"venue"
},
  "geometry": {"coordinates":[-2.2441020012,53.7883033752],"type":"Point"}
}