{
  "type": "Feature",
  "properties": {
    "iso:country":"GB",
    "sg:address":"Main Street",
    "sg:city":"Bridge Of Weir",
    "sg:classifiers":[
        {
            "category":"Education",
            "subcategory":"Library",
            "type":"Public Place"
        },
        {
            "category":"Government",
            "subcategory":"Office",
            "type":"Public Place"
        }
    ],
    "sg:phone":"+44 1505 612220",
    "sg:postcode":"PA11 3NR",
    "sg:province":"Inverclyde",
    "sg:tags":[
        "book",
        "local"
    ],
    "wof:name":"Bridge of Weir Community Library",
    "wof:placetype":"venue"
},
  "geometry": {"coordinates":[-4.582529,55.85672],"type":"Point"}
}