{
  "type": "Feature",
  "properties": {
    "iso:country":"GB",
    "sg:address":"C/o Jenner & Co, 31-33 The Brunel Centre, Bletchley",
    "sg:city":"Milton Keynes",
    "sg:classifiers":[
        {
            "category":"Building & Trades",
            "subcategory":"Cleaning & Sanitation",
            "type":"Services"
        }
    ],
    "sg:postcode":"MK2 2ES",
    "sg:province":"Buckinghamshire",
    "sg:tags":[
        "commercial"
    ],
    "wof:name":"Newpin Cleaning Services Ltd",
    "wof:placetype":"venue"
},
  "geometry": {"coordinates":[-0.7333599925,51.9940414429],"type":"Point"}
}