{
  "type": "Feature",
  "properties": {
    "iso:country":"GB",
    "sg:address":"126 Colindale Av",
    "sg:city":"Colindale",
    "sg:classifiers":[
        {
            "category":"Professional",
            "subcategory":"Computer Services",
            "type":"Services"
        }
    ],
    "sg:phone":"+44 20 8938 1000",
    "sg:postcode":"NW9 5HD",
    "sg:province":"Greater London",
    "sg:tags":[
        "system",
        "software"
    ],
    "wof:name":"Grey Cell Systems Ltd",
    "wof:placetype":"venue"
},
  "geometry": {"coordinates":[-0.252361,51.593861],"type":"Point"}
}