{
  "type": "Feature",
  "properties": {
    "iso:country":"GB",
    "sg:address":"Unit 10-12 Kilburn Square",
    "sg:city":"London",
    "sg:classifiers":[
        {
            "category":"Shopping",
            "subcategory":"Pharmacy",
            "type":"Retail Goods"
        }
    ],
    "sg:phone":"+44 20 7625 9354",
    "sg:postcode":"NW6 6PP",
    "sg:province":"Greater London",
    "sg:tags":[
        "toiletry"
    ],
    "wof:name":"J & A Toiletries",
    "wof:placetype":"venue"
},
  "geometry": {"coordinates":[-0.192663,51.537304],"type":"Point"}
}