{
  "type": "Feature",
  "properties": {
    "addr:full":"116 Church Rd Hove East Sussex BN3 2EA",
    "addr:housenumber":"116",
    "addr:postcode":"bn3 2ea",
    "addr:street":"Church Rd",
    "iso:country":"GB",
    "sg:address":"116 Church Rd",
    "sg:city":"Hove",
    "sg:classifiers":[
        {
            "category":"Professional",
            "type":"Services"
        },
        {
            "category":"Bars & Pubs",
            "subcategory":"Wine Bar",
            "type":"Food & Drink"
        }
    ],
    "sg:postcode":"BN3 2EA",
    "sg:province":"East Sussex",
    "sg:tags":[
        "caterer"
    ],
    "wof:name":"Barnfield,Angela,",
    "wof:placetype":"venue"
},
  "geometry": {"coordinates":[-0.1740020066,50.8279762268],"type":"Point"}
}