{
  "type": "Feature",
  "properties": {
    "addr:full":"39a Ock Street Abingdon Oxfordshire OX14 5AG",
    "addr:housenumber":"39a",
    "addr:postcode":"ox14 5ag",
    "addr:street":"Ock Street",
    "iso:country":"GB",
    "sg:address":"39a Ock Street",
    "sg:city":"Abingdon",
    "sg:classifiers":[
        {
            "category":"Retail",
            "subcategory":"Repair Shop",
            "type":"Services"
        }
    ],
    "sg:phone":"+44 1235 524209",
    "sg:postcode":"OX14 5AG",
    "sg:province":"Oxfordshire",
    "sg:tags":[
        "upholstering",
        "upholsterer"
    ],
    "wof:name":"PETER J PRATT",
    "wof:placetype":"venue"
},
  "geometry": {"coordinates":[-1.2860549688,51.6701202393],"type":"Point"}
}