{
  "type": "Feature",
  "properties": {
    "addr:full":"Cleveland House, 34 Edleston Road Crewe Cheshire CW2 7HD",
    "addr:housenumber":"34",
    "addr:postcode":"cw2 7hd",
    "addr:street":"Edleston Road",
    "iso:country":"GB",
    "sg:address":"Cleveland House, 34 Edleston Road",
    "sg:city":"Crewe",
    "sg:classifiers":[
        {
            "category":"Professional",
            "subcategory":"Employment Agencies",
            "type":"Services"
        }
    ],
    "sg:phone":"+44 1270 253397",
    "sg:postcode":"CW2 7HD",
    "sg:province":"Cheshire",
    "sg:tags":[
        "consultant"
    ],
    "wof:name":"Central Recruitment Services",
    "wof:placetype":"venue"
},
  "geometry": {"coordinates":[-2.4414420128,53.0893135071],"type":"Point"}
}