{
  "type": "Feature",
  "properties": {
    "iso:country":"GB",
    "sg:address":"Penbach Farm, Llanboidy",
    "sg:city":"Whitland",
    "sg:classifiers":[
        {
            "category":"Farming",
            "subcategory":"Livestock Farm",
            "type":"Manufacturing & Wholesale Goods"
        }
    ],
    "sg:phone":"+44 1994 448351",
    "sg:postcode":"SA34 0LN",
    "sg:province":"Carmarthenshire",
    "sg:tags":[
        "others"
    ],
    "wof:name":"Scourfield Brothers",
    "wof:placetype":"venue"
},
  "geometry": {"coordinates":[-4.612054,51.819256],"type":"Point"}
}