{
  "type": "Feature",
  "properties": {
    "addr:full":"81a Marians Drive Ormskirk Lancashire L39 1LG",
    "addr:housenumber":"81a",
    "addr:postcode":"l39 1lg",
    "addr:street":"Marians Drive",
    "iso:country":"GB",
    "sg:address":"81a Marians Drive",
    "sg:city":"Ormskirk",
    "sg:classifiers":[
        {
            "category":"Health Services",
            "subcategory":"Nursing And Care Facility",
            "type":"Services"
        }
    ],
    "sg:phone":"+44 1695 570581",
    "sg:postcode":"L39 1LG",
    "sg:province":"Lancashire",
    "sg:tags":[
        "home"
    ],
    "wof:name":"Courtfield Lodge",
    "wof:placetype":"venue"
},
  "geometry": {"coordinates":[-2.891036,53.576927],"type":"Point"}
}