{
  "type": "Feature",
  "properties": {
    "addr:full":"200 Hangleton Road Hove East Sussex BN3 7LT",
    "addr:housenumber":"200",
    "addr:postcode":"bn3 7lt",
    "addr:street":"Hangleton Road",
    "iso:country":"GB",
    "sg:address":"200 Hangleton Road",
    "sg:city":"Hove",
    "sg:classifiers":[
        {
            "category":"Bars & Pubs",
            "type":"Food & Drink"
        }
    ],
    "sg:postcode":"BN3 7LT",
    "sg:province":"East Sussex",
    "sg:tags":[
        "pubs",
        "inn"
    ],
    "wof:name":"The Grenadier Public House",
    "wof:placetype":"venue"
},
  "geometry": {"coordinates":[-0.194723,50.844601],"type":"Point"}
}