{
  "type": "Feature",
  "properties": {
    "addr:full":"Vernon Station, Lincoln Street, Basford Nottingham Nottinghamshire NG6 0FU",
    "addr:postcode":"ng6 0fu",
    "addr:street":"Lincoln Street",
    "iso:country":"GB",
    "sg:address":"Vernon Station, Lincoln Street, Basford",
    "sg:city":"Nottingham",
    "sg:classifiers":[
        {
            "category":"Professional",
            "subcategory":"Engineering",
            "type":"Services"
        }
    ],
    "sg:phone":"+44 115 978 5568",
    "sg:postcode":"NG6 0FU",
    "sg:province":"Nottinghamshire",
    "sg:tags":[
        "contractor",
        "electrical",
        "engineer"
    ],
    "wof:name":"C & I (Electrical Engineers) Ltd.",
    "wof:placetype":"venue"
},
  "geometry": {"coordinates":[-1.182369,52.99007],"type":"Point"}
}