{
  "type": "Feature",
  "properties": {
    "addr:full":"Princes Ct, Barony Employment Pk Nantwich Cheshire CW5 6PQ",
    "addr:postcode":"cw5 6pq",
    "addr:street":"Princes Ct;Employment Pk",
    "iso:country":"GB",
    "sg:address":"Princes Ct, Barony Employment Pk",
    "sg:city":"Nantwich",
    "sg:classifiers":[
        {
            "category":"Professional",
            "subcategory":"Printing & Photocopies",
            "type":"Services"
        }
    ],
    "sg:postcode":"CW5 6PQ",
    "sg:province":"Cheshire",
    "sg:tags":[
        "printer"
    ],
    "wof:name":"Minshull Oak Ltd",
    "wof:placetype":"venue"
},
  "geometry": {"coordinates":[-2.5081989765,53.0702667236],"type":"Point"}
}