{
  "type": "Feature",
  "properties": {
    "addr:full":"107 Shirley High Street Southampton Hampshire SO16 4EY",
    "addr:housenumber":"107",
    "addr:postcode":"so16 4ey",
    "addr:street":"Shirley High Street",
    "iso:country":"GB",
    "sg:address":"107 Shirley High Street",
    "sg:city":"Southampton",
    "sg:classifiers":[
        {
            "category":"Travel",
            "subcategory":"Travel Agent",
            "type":"Entertainment"
        }
    ],
    "sg:phone":"+44 23 8078 9133",
    "sg:postcode":"SO16 4EY",
    "sg:province":"Hampshire",
    "wof:name":"Javelin World Travel",
    "wof:placetype":"venue"
},
  "geometry": {"coordinates":[-1.4348629713,50.9235801697],"type":"Point"}
}