{
  "type": "Feature",
  "properties": {
    "iso:country":"GB",
    "sg:address":"Speedgate Farm, Speedgate",
    "sg:city":"Longfield",
    "sg:classifiers":[
        {
            "category":"Shopping",
            "subcategory":"Bicycles & Sporting Goods",
            "type":"Retail Goods"
        }
    ],
    "sg:phone":"+44 1474 872313",
    "sg:postcode":"DA3 8NJ",
    "sg:province":"Kent",
    "sg:tags":[
        "riding",
        "saddlery",
        "wear"
    ],
    "wof:name":"Speedgate Saddlery",
    "wof:placetype":"venue"
},
  "geometry": {"coordinates":[0.2727949917,51.3692932129],"type":"Point"}
}