{
  "type": "Feature",
  "properties": {
    "iso:country":"GB",
    "sg:address":"13 Malvern Avenue, Frenchwood",
    "sg:city":"Preston",
    "sg:classifiers":[
        {
            "category":"Building & Trades",
            "subcategory":"Construction",
            "type":"Services"
        }
    ],
    "sg:postcode":"PR1 4PL",
    "sg:province":"Lancashire",
    "sg:tags":[
        "decorator",
        "painter"
    ],
    "wof:name":"Cyril Jones",
    "wof:placetype":"venue"
},
  "geometry": {"coordinates":[-2.683797,53.751743],"type":"Point"}
}