{
  "type": "Feature",
  "properties": {
    "addr:full":"15 New Cottages, The Coombe Betchworth Surrey RH3 7BU",
    "addr:housenumber":"15",
    "addr:postcode":"rh3 7bu",
    "addr:street":"New Cottages The Coombe",
    "iso:country":"GB",
    "sg:address":"15 New Cottages, The Coombe",
    "sg:city":"Betchworth",
    "sg:classifiers":[
        {
            "category":"Building & Trades",
            "subcategory":"Construction",
            "type":"Services"
        }
    ],
    "sg:phone":"+44 1737 844889",
    "sg:postcode":"RH3 7BU",
    "sg:province":"Surrey",
    "sg:tags":[
        "builder"
    ],
    "wof:name":"Temple Plant & Construction",
    "wof:placetype":"venue"
},
  "geometry": {"coordinates":[-0.2677980065,51.235206604],"type":"Point"}
}