{
  "type": "Feature",
  "properties": {
    "iso:country":"GB",
    "sg:address":"33-48 Charles Henry Street",
    "sg:city":"Birmingham",
    "sg:classifiers":[
        {
            "category":"Wholesale",
            "subcategory":"Non-durable Goods",
            "type":"Manufacturing & Wholesale Goods"
        }
    ],
    "sg:phone":"+44 121 622 4984",
    "sg:postcode":"B12 0JD",
    "sg:province":"West Midlands",
    "sg:tags":[
        "carry",
        "cash"
    ],
    "wof:name":"M Sharif Cash & Carry Ltd.",
    "wof:placetype":"venue"
},
  "geometry": {"coordinates":[-1.891743,52.468273],"type":"Point"}
}