{
  "type": "Feature",
  "properties": {
    "iso:country":"GB",
    "sg:address":"15 Kingsway",
    "sg:city":"Exeter",
    "sg:classifiers":[
        {
            "category":"Professional",
            "subcategory":"Engineering",
            "type":"Services"
        }
    ],
    "sg:phone":"+44 1392 210949",
    "sg:postcode":"EX2 5EN",
    "sg:province":"Devon",
    "sg:tags":[
        "contractor",
        "electrical",
        "engineer"
    ],
    "wof:name":"Pete Wreyford Electrical",
    "wof:placetype":"venue"
},
  "geometry": {"coordinates":[-3.502979,50.719772],"type":"Point"}
}