{
  "type": "Feature",
  "properties": {
    "iso:country":"GB",
    "sg:address":"Sherwood Lawn",
    "sg:city":"Bonnyrigg",
    "sg:classifiers":[
        {
            "category":"Military Area",
            "subcategory":"Air Force Base",
            "type":"Public Place"
        }
    ],
    "sg:phone":"+44 131 663 0118",
    "sg:postcode":"EH19 3NF",
    "sg:province":"Midlothian",
    "sg:tags":[
        "taxi",
        "hire",
        "private"
    ],
    "wof:name":"Zac's Premier Taxis",
    "wof:placetype":"venue"
},
  "geometry": {"coordinates":[-3.1040699482,55.8740348816],"type":"Point"}
}