{
  "type": "Feature",
  "properties": {
    "iso:country":"GB",
    "sg:address":"The Osiers Pk, Laversall Way",
    "sg:city":"Leicester",
    "sg:classifiers":[
        {
            "category":"Utilities",
            "type":"Services"
        }
    ],
    "sg:phone":"+44 116 202 2000",
    "sg:postcode":"LE3 2DX",
    "sg:province":"Leicestershire",
    "sg:tags":[
        "internet"
    ],
    "wof:name":"Fol Networks Ltd",
    "wof:placetype":"venue"
},
  "geometry": {"coordinates":[-1.1789770126,52.6052474976],"type":"Point"}
}