{
  "type": "Feature",
  "properties": {
    "addr:full":"2 Broompark West Menstrie Clackmannanshire FK11 7AL",
    "addr:housenumber":"2",
    "addr:postcode":"fk11 7al",
    "addr:street":"Broompark West Menstrie",
    "iso:country":"GB",
    "sg:address":"2 Broompark West",
    "sg:city":"Menstrie",
    "sg:classifiers":[
        {
            "category":"Personal",
            "subcategory":"Tanning Parlor",
            "type":"Services"
        }
    ],
    "sg:postcode":"FK11 7AL",
    "sg:province":"Clackmannanshire",
    "sg:tags":[
        "sunbeds"
    ],
    "wof:name":"Tanfastique Sunbeds",
    "wof:placetype":"venue"
},
  "geometry": {"coordinates":[-3.851799,56.152409],"type":"Point"}
}