{
  "type": "Feature",
  "properties": {
    "addr:full":"Unit 16, Charles Industrial Estate Stowmarket Suffolk IP14 5AH",
    "addr:housenumber":"unit 16",
    "addr:postcode":"ip14 5ah",
    "addr:street":"Charles Industrial Estate",
    "iso:country":"GB",
    "sg:address":"Unit 16, Charles Industrial Estate",
    "sg:city":"Stowmarket",
    "sg:classifiers":[
        {
            "category":"Home & Garden",
            "subcategory":"Home Furnishings",
            "type":"Retail Goods"
        },
        {
            "category":"Building & Trades",
            "subcategory":"Construction",
            "type":"Services"
        }
    ],
    "sg:phone":"+44 1449 678659",
    "sg:postcode":"IP14 5AH",
    "sg:province":"Suffolk",
    "sg:tags":[
        "mantelpiece",
        "fireplace"
    ],
    "wof:name":"Classic Stoves & Fireplaces",
    "wof:placetype":"venue"
},
  "geometry": {"coordinates":[0.996769011,52.1886253357],"type":"Point"}
}