{
  "type": "Feature",
  "properties": {
    "iso:country":"GB",
    "sg:address":"250 Morrison Street",
    "sg:city":"Edinburgh",
    "sg:classifiers":[
        {
            "category":"Communications",
            "type":"Services"
        },
        {
            "category":"Shopping",
            "subcategory":"Computers & Home Electronics",
            "type":"Retail Goods"
        },
        {
            "category":"Shopping",
            "subcategory":"Photographic Equipment",
            "type":"Retail Goods"
        }
    ],
    "sg:phone":"+44 131 229 6601",
    "sg:postcode":"EH3 8DT",
    "sg:province":"City of Edinburgh",
    "sg:tags":[
        "television",
        "supply",
        "tv",
        "sale",
        "radio",
        "video"
    ],
    "wof:name":"Edinburgh Photo Centre Ltd.",
    "wof:placetype":"venue"
},
  "geometry": {"coordinates":[-3.214634,55.946255],"type":"Point"}
}