{
  "type": "Feature",
  "properties": {
    "addr:full":"128 Corporation Road Newport Newport NP19 0BH",
    "addr:housenumber":"128",
    "addr:postcode":"np19 0bh",
    "addr:street":"Corporation Road",
    "iso:country":"GB",
    "sg:address":"128 Corporation Road",
    "sg:city":"Newport",
    "sg:classifiers":[
        {
            "category":"Autos & Motor Vehicles",
            "subcategory":"Motorcycle Sales",
            "type":"Retail Goods"
        }
    ],
    "sg:phone":"+44 1633 840450",
    "sg:postcode":"NP19 0BH",
    "sg:province":"Newport",
    "wof:name":"Taffspeed Racing",
    "wof:placetype":"venue"
},
  "geometry": {"coordinates":[-2.985321,51.587723],"type":"Point"}
}