{
  "type": "Feature",
  "properties": {
    "iso:country":"GB",
    "sg:address":"115 Crown Street",
    "sg:city":"Aberdeen",
    "sg:classifiers":[
        {
            "category":"Travel",
            "subcategory":"Hotels & Motels",
            "type":"Entertainment"
        }
    ],
    "sg:postcode":"AB11 6HN",
    "sg:province":"Aberdeen City",
    "sg:tags":[
        "house",
        "guest"
    ],
    "wof:name":"Carron Guest House",
    "wof:placetype":"venue"
},
  "geometry": {"coordinates":[-2.101393,57.142498],"type":"Point"}
}