{
  "type": "Feature",
  "properties": {
    "addr:full":"Unit 13 Morrison Yard, 551a High Rd Tottenham Greater London N17 6SB",
    "addr:housenumber":"unit 13;551a",
    "addr:postcode":"n17 6sb",
    "addr:street":"Morrison Yard;High Rd",
    "iso:country":"GB",
    "sg:address":"Unit 13 Morrison Yard, 551a High Rd",
    "sg:city":"Tottenham",
    "sg:classifiers":[
        {
            "category":"Food & Beverages",
            "subcategory":"Supermarket",
            "type":"Retail Goods"
        }
    ],
    "sg:phone":"+44 20 8808 2234",
    "sg:postcode":"N17 6SB",
    "sg:province":"Greater London",
    "sg:tags":[
        "frozen"
    ],
    "wof:name":"Toyo Seimen Ltd",
    "wof:placetype":"venue"
},
  "geometry": {"coordinates":[-0.06885,51.595871],"type":"Point"}
}