{
  "type": "Feature",
  "properties": {
    "addr:full":"52 Deanburn Road Linlithgow Falkirk EH49 6EY",
    "addr:housenumber":"52",
    "addr:postcode":"eh49 6ey",
    "addr:street":"Deanburn Road",
    "iso:country":"GB",
    "sg:address":"52 Deanburn Road",
    "sg:city":"Linlithgow",
    "sg:classifiers":[
        {
            "category":"Professional",
            "subcategory":"Computer Services",
            "type":"Services"
        }
    ],
    "sg:phone":"+44 1506 846500",
    "sg:postcode":"EH49 6EY",
    "sg:province":"Falkirk",
    "sg:tags":[
        "consultant"
    ],
    "wof:name":"I T Freeway Ltd.",
    "wof:placetype":"venue"
},
  "geometry": {"coordinates":[-3.609811,55.969765],"type":"Point"}
}