{
  "type": "Feature",
  "properties": {
    "iso:country":"GB",
    "sg:address":"The Esplanade",
    "sg:city":"Watchet",
    "sg:classifiers":[
        {
            "category":"Communications",
            "type":"Services"
        },
        {
            "category":"Government",
            "subcategory":"Post Office",
            "type":"Public Place"
        }
    ],
    "sg:phone":"+44 1984 634900",
    "sg:postcode":"TA23 0AJ",
    "sg:province":"Somerset",
    "sg:tags":[
        "broadcasting"
    ],
    "wof:name":"QUAY WEST RADIO LTD",
    "wof:placetype":"venue"
},
  "geometry": {"coordinates":[-3.330244,51.180626],"type":"Point"}
}