{
  "type": "Feature",
  "properties": {
    "iso:country":"GB",
    "sg:address":"Hungerford Delivery Office, 126 High Street",
    "sg:city":"Hungerford",
    "sg:classifiers":[
        {
            "category":"Personal",
            "type":"Services"
        }
    ],
    "sg:phone":"+44 1488 682826",
    "sg:postcode":"RG17 0DP",
    "sg:province":"Berkshire",
    "sg:tags":[
        "delivery"
    ],
    "wof:name":"Royal Mail",
    "wof:placetype":"venue"
},
  "geometry": {"coordinates":[-1.5161559582,51.4131965637],"type":"Point"}
}