{
  "type": "Feature",
  "properties": {
    "iso:country":"GB",
    "sg:address":"Stoneleigh, Southwaite",
    "sg:city":"Carlisle",
    "sg:classifiers":[
        {
            "category":"Shopping",
            "subcategory":"Pharmacy",
            "type":"Retail Goods"
        }
    ],
    "sg:postcode":"CA4 0NA",
    "sg:province":"Cumbria",
    "sg:tags":[
        "medicine",
        "therapy"
    ],
    "wof:name":"Hilary Norman Aromatherapy",
    "wof:placetype":"venue"
},
  "geometry": {"coordinates":[-2.856182,54.797813],"type":"Point"}
}