{
  "type": "Feature",
  "properties": {
    "addr:full":"Binghams House, Church Street, Bowerchalke Salisbury Dorset SP5 5BN",
    "addr:postcode":"sp5 5bn",
    "addr:street":"Church Street",
    "iso:country":"GB",
    "sg:address":"Binghams House, Church Street, Bowerchalke",
    "sg:city":"Salisbury",
    "sg:classifiers":[
        {
            "category":"Home & Garden",
            "subcategory":"Garden Supply",
            "type":"Retail Goods"
        }
    ],
    "sg:phone":"+44 1722 780999",
    "sg:postcode":"SP5 5BN",
    "sg:province":"Dorset",
    "sg:tags":[
        "nursery",
        "centre"
    ],
    "wof:name":"Templeton Walker",
    "wof:placetype":"venue"
},
  "geometry": {"coordinates":[-1.9708880186,51.0099601746],"type":"Point"}
}