{
  "type": "Feature",
  "properties": {
    "addr:full":"127b Denbydale Way, Royton Oldham Lancashire OL2 5TE",
    "addr:housenumber":"127b",
    "addr:postcode":"ol2 5te",
    "addr:street":"Denbydale Way",
    "iso:country":"GB",
    "sg:address":"127b Denbydale Way, Royton",
    "sg:city":"Oldham",
    "sg:classifiers":[
        {
            "category":"Building & Trades",
            "subcategory":"Construction",
            "type":"Services"
        }
    ],
    "sg:phone":"+44 161 626 7134",
    "sg:postcode":"OL2 5TE",
    "sg:province":"Lancashire",
    "sg:tags":[
        "dry",
        "lining",
        "plasterers",
        "screeders"
    ],
    "wof:name":"Les Meredith Plastering Contractors",
    "wof:placetype":"venue"
},
  "geometry": {"coordinates":[-2.134613,53.56831],"type":"Point"}
}