{
  "type": "Feature",
  "properties": {
    "iso:country":"GB",
    "sg:address":"55 Conholt Road",
    "sg:city":"Andover",
    "sg:classifiers":[
        {
            "category":"Shopping",
            "subcategory":"Clothing, Apparel, & Fashions",
            "type":"Retail Goods"
        }
    ],
    "sg:phone":"+44 1264 361107",
    "sg:postcode":"SP10 2HS",
    "sg:province":"Hampshire",
    "sg:tags":[
        "shop",
        "hat"
    ],
    "wof:name":"Headlines Hat Hire",
    "wof:placetype":"venue"
},
  "geometry": {"coordinates":[-1.483213,51.195339],"type":"Point"}
}