{
  "type": "Feature",
  "properties": {
    "addr:full":"Moss Bay Rd Workington Cumbria CA14 3TL",
    "addr:postcode":"ca14 3tl",
    "addr:street":"Moss Bay Rd",
    "iso:country":"GB",
    "sg:address":"Moss Bay Rd",
    "sg:city":"Workington",
    "sg:classifiers":[
        {
            "category":"Home & Garden",
            "subcategory":"Furniture",
            "type":"Retail Goods"
        }
    ],
    "sg:phone":"+44 1900 68800",
    "sg:postcode":"CA14 3TL",
    "sg:province":"Cumbria",
    "wof:name":"Costs Less",
    "wof:placetype":"venue"
},
  "geometry": {"coordinates":[-3.556824,54.635418],"type":"Point"}
}