{
  "type": "Feature",
  "properties": {
    "addr:full":"59 Colchester Road, Humberstone Leicester Leicestershire LE5 2DH",
    "addr:housenumber":"59",
    "addr:postcode":"le5 2dh",
    "addr:street":"Colchester Road",
    "iso:country":"GB",
    "sg:address":"59 Colchester Road, Humberstone",
    "sg:city":"Leicester",
    "sg:classifiers":[
        {
            "category":"Professional",
            "type":"Services"
        }
    ],
    "sg:postcode":"LE5 2DH",
    "sg:province":"Leicestershire",
    "sg:tags":[
        "caterer"
    ],
    "wof:name":"Two Chefs Caterers",
    "wof:placetype":"venue"
},
  "geometry": {"coordinates":[-1.0720180273,52.6402282715],"type":"Point"}
}