{
  "type": "Feature",
  "properties": {
    "addr:full":"182a Station Rd Burton-on-trent Derbyshire DE14 1BN",
    "addr:housenumber":"182a",
    "addr:postcode":"de14 1bn",
    "addr:street":"Station Rd",
    "iso:country":"GB",
    "sg:address":"182a Station Rd",
    "sg:city":"Burton-on-trent",
    "sg:classifiers":[
        {
            "category":"Personal",
            "subcategory":"Beauty Salon",
            "type":"Services"
        }
    ],
    "sg:postcode":"DE14 1BN",
    "sg:province":"Derbyshire",
    "sg:tags":[
        "unisex",
        "hairdresser"
    ],
    "wof:name":"Foy,Kay,",
    "wof:placetype":"venue"
},
  "geometry": {"coordinates":[-1.63756001,52.8053283691],"type":"Point"}
}