{
  "type": "Feature",
  "properties": {
    "addr:full":"16 Weeton Avenue Blackpool Lancashire FY4 3QW",
    "addr:housenumber":"16",
    "addr:postcode":"fy4 3qw",
    "addr:street":"Weeton Avenue",
    "iso:country":"GB",
    "sg:address":"16 Weeton Avenue",
    "sg:city":"Blackpool",
    "sg:classifiers":[
        {
            "category":"Professional",
            "subcategory":"Engineering",
            "type":"Services"
        },
        {
            "category":"Shopping",
            "subcategory":"Computers & Home Electronics",
            "type":"Retail Goods"
        }
    ],
    "sg:postcode":"FY4 3QW",
    "sg:province":"Lancashire",
    "sg:tags":[
        "television",
        "aerial",
        "contractor",
        "electrical",
        "radio",
        "engineer"
    ],
    "wof:name":"Eastham,Garry,",
    "wof:placetype":"venue"
},
  "geometry": {"coordinates":[-3.031624,53.782032],"type":"Point"}
}