{
  "type": "Feature",
  "properties": {
    "iso:country":"GB",
    "sg:address":"Lower Buckland Road",
    "sg:city":"Lymington",
    "sg:classifiers":[
        {
            "category":"Shopping",
            "subcategory":"Department Store",
            "type":"Retail Goods"
        }
    ],
    "sg:postcode":"SO41 9DN",
    "sg:province":"Hampshire",
    "wof:name":"Lower Buckland Stores",
    "wof:placetype":"venue"
},
  "geometry": {"coordinates":[-1.549099,50.765919],"type":"Point"}
}