{
  "type": "Feature",
  "properties": {
    "addr:full":"Lower Buckland Road Lymington Hampshire SO41 9DN",
    "addr:postcode":"so41 9dn",
    "addr:street":"Lower Buckland Road",
    "iso:country":"GB",
    "sg:address":"Lower Buckland Road",
    "sg:city":"Lymington",
    "sg:classifiers":[
        {
            "category":"Shopping",
            "subcategory":"Department Store",
            "type":"Retail Goods"
        }
    ],
    "sg:postcode":"SO41 9DN",
    "sg:province":"Hampshire",
    "wof:name":"Lower Buckland Stores",
    "wof:placetype":"venue"
},
  "geometry": {"coordinates":[-1.549099,50.765919],"type":"Point"}
}