{
  "type": "Feature",
  "properties": {
    "addr:full":"Unit E2, East Wittering Business Centre, Church Road East Chichester West Sussex PO20 8RL",
    "addr:housenumber":"e2",
    "addr:postcode":"po20 8rl",
    "addr:street":"Church Road East",
    "iso:country":"GB",
    "sg:address":"Unit E2, East Wittering Business Centre, Church Road East",
    "sg:city":"Chichester",
    "sg:classifiers":[
        {
            "category":"Manufacturing",
            "subcategory":"Rubber & Plastics",
            "type":"Manufacturing & Wholesale Goods"
        }
    ],
    "sg:phone":"+44 1243 671072",
    "sg:postcode":"PO20 8RL",
    "sg:province":"West Sussex",
    "sg:tags":[
        "coating"
    ],
    "wof:name":"Safecoat Ltd.",
    "wof:placetype":"venue"
},
  "geometry": {"coordinates":[-0.8643500209,50.7738418579],"type":"Point"}
}