{
  "type": "Feature",
  "properties": {
    "addr:full":"64-66 Bickerstaffe St St. Helens Merseyside WA10 1DS",
    "addr:housenumber":"64-66",
    "addr:postcode":"wa10 1ds",
    "addr:street":"Bickerstaffe St",
    "iso:country":"GB",
    "sg:address":"64-66 Bickerstaffe St",
    "sg:city":"St. Helens",
    "sg:classifiers":[
        {
            "category":"Shopping",
            "subcategory":"Thrift Store",
            "type":"Retail Goods"
        }
    ],
    "sg:phone":"+44 1744 22707",
    "sg:postcode":"WA10 1DS",
    "sg:province":"Merseyside",
    "sg:tags":[
        "shop",
        "charity"
    ],
    "wof:name":"Allsorts Charity Shop",
    "wof:placetype":"venue"
},
  "geometry": {"coordinates":[-2.7341239452,53.4534378052],"type":"Point"}
}