{
  "type": "Feature",
  "properties": {
    "addr:full":"64 Shortmead Street Biggleswade Bedfordshire SG18 0AP",
    "addr:housenumber":"64",
    "addr:postcode":"sg18 0ap",
    "addr:street":"Shortmead Street",
    "iso:country":"GB",
    "sg:address":"64 Shortmead Street",
    "sg:city":"Biggleswade",
    "sg:classifiers":[
        {
            "category":"Shopping",
            "subcategory":"Baby Store",
            "type":"Retail Goods"
        }
    ],
    "sg:postcode":"SG18 0AP",
    "sg:province":"Bedfordshire",
    "sg:tags":[
        "nursery",
        "accessory"
    ],
    "wof:name":"Baby Bows",
    "wof:placetype":"venue"
},
  "geometry": {"coordinates":[-0.267088,52.088772],"type":"Point"}
}