{
  "type": "Feature",
  "properties": {
    "addr:full":"Firby House Farm Bedale North Yorkshire DL8 2PW",
    "addr:postcode":"dl8 2pw",
    "iso:country":"GB",
    "sg:address":"Firby House Farm",
    "sg:city":"Bedale",
    "sg:classifiers":[
        {
            "category":"Farming",
            "subcategory":"Livestock Farm",
            "type":"Manufacturing & Wholesale Goods"
        }
    ],
    "sg:phone":"+44 1677 422102",
    "sg:postcode":"DL8 2PW",
    "sg:province":"North Yorkshire",
    "sg:tags":[
        "others"
    ],
    "wof:name":"C W J Fall & Sons Ltd.",
    "wof:placetype":"venue"
},
  "geometry": {"coordinates":[-1.592346,54.288811],"type":"Point"}
}