{
  "type": "Feature",
  "properties": {
    "addr:full":"134a South Ealing Road London Greater London W5 4QJ",
    "addr:housenumber":"134a",
    "addr:postcode":"w5 4qj",
    "addr:street":"South Ealing Road",
    "iso:country":"GB",
    "sg:address":"134a South Ealing Road",
    "sg:city":"London",
    "sg:classifiers":[
        {
            "category":"Personal",
            "subcategory":"Beauty Salon",
            "type":"Services"
        },
        {
            "category":"Personal",
            "subcategory":"Barber",
            "type":"Services"
        }
    ],
    "sg:phone":"+44 20 8567 7597",
    "sg:postcode":"W5 4QJ",
    "sg:province":"Greater London",
    "sg:tags":[
        "unisex",
        "lady",
        "hairdresser"
    ],
    "wof:name":"Raffles",
    "wof:placetype":"venue"
},
  "geometry": {"coordinates":[-0.3064039946,51.4994087219],"type":"Point"}
}