{
  "type": "Feature",
  "properties": {
    "addr:full":"Rauter House, 1 Sybron Way Crowborough East Sussex TN6 3DZ",
    "addr:housenumber":"1",
    "addr:postcode":"tn6 3dz",
    "addr:street":"Sybron Way",
    "iso:country":"GB",
    "sg:address":"Rauter House, 1 Sybron Way",
    "sg:city":"Crowborough",
    "sg:classifiers":[
        {
            "category":"Professional",
            "subcategory":"Management & Consulting",
            "type":"Services"
        },
        {
            "category":"Education",
            "subcategory":"Special Training",
            "type":"Public Place"
        }
    ],
    "sg:phone":"+44 1892 610060",
    "sg:postcode":"TN6 3DZ",
    "sg:province":"East Sussex",
    "sg:tags":[
        "consultant",
        "product",
        "business",
        "centre"
    ],
    "sg:website":"http://www.right-training.com",
    "wof:name":"Right Training Ltd.",
    "wof:placetype":"venue"
},
  "geometry": {"coordinates":[0.193629995,51.0463485718],"type":"Point"}
}