{
  "type": "Feature",
  "properties": {
    "addr:full":"136a Casterton Road Stamford Cambridgeshire PE9 2UQ",
    "addr:housenumber":"136a",
    "addr:postcode":"pe9 2uq",
    "addr:street":"Casterton Road",
    "iso:country":"GB",
    "sg:address":"136a Casterton Road",
    "sg:city":"Stamford",
    "sg:classifiers":[
        {
            "category":"Professional",
            "subcategory":"Management & Consulting",
            "type":"Services"
        }
    ],
    "sg:phone":"+44 1780 766610",
    "sg:postcode":"PE9 2UQ",
    "sg:province":"Cambridgeshire",
    "sg:tags":[
        "consultant",
        "business",
        "transport"
    ],
    "wof:name":"P J P Management Systems",
    "wof:placetype":"venue"
},
  "geometry": {"coordinates":[-0.4995099902,52.6580657959],"type":"Point"}
}