{
  "type": "Feature",
  "properties": {
    "iso:country":"GB",
    "sg:address":"828 Bristol Road South, Northfield",
    "sg:city":"Birmingham",
    "sg:classifiers":[
        {
            "category":"Food & Beverages",
            "subcategory":"Liquor & Beverages",
            "type":"Retail Goods"
        }
    ],
    "sg:phone":"+44 121 475 1812",
    "sg:postcode":"B31 2NS",
    "sg:province":"West Midlands",
    "sg:tags":[
        "beer",
        "spirit",
        "wines"
    ],
    "wof:name":"Drinks Cabin",
    "wof:placetype":"venue"
},
  "geometry": {"coordinates":[-1.971719,52.414185],"type":"Point"}
}