{
  "type": "Feature",
  "properties": {
    "addr:full":"39 High Street, Hemingford Grey Huntingdon Bedfordshire PE28 9BJ",
    "addr:housenumber":"39",
    "addr:postcode":"pe28 9bj",
    "addr:street":"High Street",
    "iso:country":"GB",
    "sg:address":"39 High Street, Hemingford Grey",
    "sg:city":"Huntingdon",
    "sg:classifiers":[
        {
            "category":"Professional",
            "subcategory":"Accounting & Tax Preparation",
            "type":"Services"
        }
    ],
    "sg:phone":"+44 1480 467106",
    "sg:postcode":"PE28 9BJ",
    "sg:province":"Bedfordshire",
    "sg:tags":[
        "accountant",
        "bookkeeping",
        "primarily",
        "activity"
    ],
    "wof:name":"Gordon Brown",
    "wof:placetype":"venue"
},
  "geometry": {"coordinates":[-0.069113,52.297466],"type":"Point"}
}