{
  "type": "Feature",
  "properties": {
    "iso:country":"GB",
    "sg:address":"The Clock House, Kempshott Park",
    "sg:city":"Basingstoke",
    "sg:classifiers":[
        {
            "category":"Professional",
            "subcategory":"Computer Services",
            "type":"Services"
        }
    ],
    "sg:phone":"+44 1256 698888",
    "sg:postcode":"RG23 7LP",
    "sg:province":"Hampshire",
    "sg:tags":[
        "system",
        "software"
    ],
    "wof:name":"Vega Solutions Ltd.",
    "wof:placetype":"venue"
},
  "geometry": {"coordinates":[-1.141686,51.243465],"type":"Point"}
}