{
  "type": "Feature",
  "properties": {
    "iso:country":"GB",
    "sg:address":"Rochdale Road",
    "sg:city":"Oldham",
    "sg:classifiers":[
        {
            "category":"Education",
            "subcategory":"School",
            "type":"Public Place"
        },
        {
            "category":"Government",
            "subcategory":"Office",
            "type":"Public Place"
        }
    ],
    "sg:phone":"+44 161 652 2428",
    "sg:postcode":"OL9 6DY",
    "sg:province":"Lancashire",
    "sg:tags":[
        "local",
        "authority"
    ],
    "wof:name":"Grange Secondary School",
    "wof:placetype":"venue"
},
  "geometry": {"coordinates":[-2.118759,53.542],"type":"Point"}
}