{
  "type": "Feature",
  "properties": {
    "addr:full":"Bradford Ct, 123-131 Bradford St Birmingham West Midlands B12 0NS",
    "addr:housenumber":"123-131",
    "addr:postcode":"b12 0ns",
    "addr:street":"Bradford Ct;Bradford St",
    "iso:country":"GB",
    "sg:address":"Bradford Ct, 123-131 Bradford St",
    "sg:city":"Birmingham",
    "sg:classifiers":[
        {
            "category":"Banks & Credit Unions",
            "subcategory":"Financial Services",
            "type":"Services"
        },
        {
            "category":"Real Estate",
            "subcategory":"Real Estate Agent",
            "type":"Services"
        }
    ],
    "sg:phone":"+44 121 693 9192",
    "sg:postcode":"B12 0NS",
    "sg:province":"West Midlands",
    "sg:tags":[
        "adviser"
    ],
    "wof:name":"Chamberlains",
    "wof:placetype":"venue"
},
  "geometry": {"coordinates":[-1.908604,52.478596],"type":"Point"}
}