{
  "type": "Feature",
  "properties": {
    "iso:country":"GB",
    "sg:address":"Flat 3 2 Lafone Street, Butlers Wharf",
    "sg:city":"London",
    "sg:classifiers":[
        {
            "category":"Banks & Credit Unions",
            "subcategory":"Financial Services",
            "type":"Services"
        }
    ],
    "sg:postcode":"SE1 2LT",
    "sg:province":"Greater London",
    "sg:tags":[
        "consultant"
    ],
    "wof:name":"Iceberg Investments Ltd",
    "wof:placetype":"venue"
},
  "geometry": {"coordinates":[-0.0756800026,51.5021781921],"type":"Point"}
}