{
  "type": "Feature",
  "properties": {
    "addr:full":"2-4 Springfield Grange Wakefield West Yorkshire WF2 9QA",
    "addr:housenumber":"2-4",
    "addr:postcode":"wf2 9qa",
    "addr:street":"Springfield Grange",
    "iso:country":"GB",
    "sg:address":"2-4 Springfield Grange",
    "sg:city":"Wakefield",
    "sg:classifiers":[
        {
            "category":"Social Services",
            "type":"Services"
        }
    ],
    "sg:phone":"+44 1924 302195",
    "sg:postcode":"WF2 9QA",
    "sg:province":"West Yorkshire",
    "wof:name":"Flanshaw Community Team",
    "wof:placetype":"venue"
},
  "geometry": {"coordinates":[-1.532968998,53.6822357178],"type":"Point"}
}