{
  "type": "Feature",
  "properties": {
    "addr:full":"84a Main Road, Radcliffe-on-trent Nottingham Nottinghamshire NG12 2BQ",
    "addr:housenumber":"84a",
    "addr:postcode":"ng12 2bq",
    "addr:street":"Main Road",
    "iso:country":"GB",
    "sg:address":"84a Main Road, Radcliffe-on-trent",
    "sg:city":"Nottingham",
    "sg:classifiers":[
        {
            "category":"Social Services",
            "subcategory":"Retirement Home",
            "type":"Services"
        }
    ],
    "sg:postcode":"NG12 2BQ",
    "sg:province":"Nottinghamshire",
    "sg:tags":[
        "residential",
        "care"
    ],
    "wof:name":"Rosewood House",
    "wof:placetype":"venue"
},
  "geometry": {"coordinates":[-1.0471559763,52.9464454651],"type":"Point"}
}