{
  "type": "Feature",
  "properties": {
    "addr:full":"17a Church Street, Wellington Telford Shropshire TF1 1DD",
    "addr:housenumber":"17a",
    "addr:postcode":"tf1 1dd",
    "addr:street":"Church Street",
    "iso:country":"GB",
    "sg:address":"17a Church Street, Wellington",
    "sg:city":"Telford",
    "sg:classifiers":[
        {
            "category":"Professional",
            "subcategory":"Lawyer & Legal Services",
            "type":"Services"
        }
    ],
    "sg:phone":"+44 1952 245700",
    "sg:postcode":"TF1 1DD",
    "sg:province":"Shropshire",
    "sg:tags":[
        "solicitor"
    ],
    "wof:name":"Carol Dixon & Co",
    "wof:placetype":"venue"
},
  "geometry": {"coordinates":[-2.519148,52.702026],"type":"Point"}
}