{
  "type": "Feature",
  "properties": {
    "addr:full":"Erw Road Llanelli Carmarthenshire SA15 2TE",
    "addr:postcode":"sa15 2te",
    "addr:street":"Erw Road",
    "iso:country":"GB",
    "sg:address":"Erw Road",
    "sg:city":"Llanelli",
    "sg:classifiers":[
        {
            "category":"Bars & Pubs",
            "type":"Food & Drink"
        }
    ],
    "sg:phone":"+44 1554 741189",
    "sg:postcode":"SA15 2TE",
    "sg:province":"Carmarthenshire",
    "sg:tags":[
        "pubs",
        "house",
        "inn",
        "public",
        "activity"
    ],
    "wof:name":"The Greenfield Inn",
    "wof:placetype":"venue"
},
  "geometry": {"coordinates":[-4.166007,51.678978],"type":"Point"}
}