{
  "type": "Feature",
  "properties": {
    "addr:full":"Cambridge Road, High Cross Ware Hertfordshire SG11 1AP",
    "addr:postcode":"sg11 1ap",
    "addr:street":"Cambridge Road High Cross Ware",
    "iso:country":"GB",
    "sg:address":"Cambridge Road, High Cross",
    "sg:city":"Ware",
    "sg:classifiers":[
        {
            "category":"Banks & Credit Unions",
            "subcategory":"Investment Brokerage",
            "type":"Services"
        }
    ],
    "sg:phone":"+44 1920 466781",
    "sg:postcode":"SG11 1AP",
    "sg:province":"Hertfordshire",
    "sg:tags":[
        "equipment",
        "transport"
    ],
    "wof:name":"Oakley Coach Builders",
    "wof:placetype":"venue"
},
  "geometry": {"coordinates":[-0.0232820008,51.8481941223],"type":"Point"}
}