{
  "type": "Feature",
  "properties": {
    "iso:country":"GB",
    "sg:address":"Rheidol Avenue, Clase",
    "sg:city":"Swansea",
    "sg:classifiers":[
        {
            "category":"Education",
            "subcategory":"School",
            "type":"Public Place"
        }
    ],
    "sg:phone":"+44 1792 781747",
    "sg:postcode":"SA6 7JX",
    "sg:province":"Swansea",
    "sg:tags":[
        "local",
        "authority"
    ],
    "wof:name":"Clase Primary School",
    "wof:placetype":"venue"
},
  "geometry": {"coordinates":[-3.9419438839,51.6622581482],"type":"Point"}
}