{
  "type": "Feature",
  "properties": {
    "iso:country":"GB",
    "sg:address":"Sheffield Technology Park, 60 Shirland Lane",
    "sg:city":"Sheffield",
    "sg:classifiers":[
        {
            "category":"Health Services",
            "subcategory":"Medical Lab",
            "type":"Services"
        }
    ],
    "sg:phone":"+44 114 243 5400",
    "sg:postcode":"S9 3SP",
    "sg:province":"South Yorkshire",
    "sg:tags":[
        "dental"
    ],
    "wof:name":"Archform 2000 Ltd.",
    "wof:placetype":"venue"
},
  "geometry": {"coordinates":[-1.42995,53.39278],"type":"Point"}
}