{
  "type": "Feature",
  "properties": {
    "iso:country":"GB",
    "sg:address":"Owls Hall, Blackmore End",
    "sg:city":"Braintree",
    "sg:classifiers":[
        {
            "category":"Recreation",
            "subcategory":"Fishing",
            "type":"Entertainment"
        }
    ],
    "sg:phone":"+44 1371 850360",
    "sg:postcode":"CM7 4DF",
    "sg:province":"Essex",
    "sg:tags":[
        "angling"
    ],
    "wof:name":"Kingfisher Aquaculture",
    "wof:placetype":"venue"
},
  "geometry": {"coordinates":[0.553242,51.877758],"type":"Point"}
}