{
  "type": "Feature",
  "properties": {
    "addr:full":"Unit 182, Bradkirk Place, Walton Summit Centre Preston Lancashire PR5 8AJ",
    "addr:housenumber":"182",
    "addr:postcode":"pr5 8aj",
    "addr:street":"Bradkirk Place",
    "iso:country":"GB",
    "sg:address":"Unit 182, Bradkirk Place, Walton Summit Centre",
    "sg:city":"Preston",
    "sg:classifiers":[
        {
            "category":"Home & Garden",
            "subcategory":"Building Materials",
            "type":"Retail Goods"
        }
    ],
    "sg:phone":"+44 1772 311593",
    "sg:postcode":"PR5 8AJ",
    "sg:province":"Lancashire",
    "sg:tags":[
        "polythene",
        "plastic"
    ],
    "wof:name":"Michael Jackson (Paper) Ltd.",
    "wof:placetype":"venue"
},
  "geometry": {"coordinates":[-2.6485140324,53.7241783142],"type":"Point"}
}