{
  "type": "Feature",
  "properties": {
    "addr:full":"45 High Street Egham Surrey TW20 9DP",
    "addr:housenumber":"45",
    "addr:postcode":"tw20 9dp",
    "addr:street":"High Street",
    "iso:country":"GB",
    "sg:address":"45 High Street",
    "sg:city":"Egham",
    "sg:classifiers":[
        {
            "category":"Professional",
            "subcategory":"Computer Services",
            "type":"Services"
        }
    ],
    "sg:phone":"+44 1224 242288",
    "sg:postcode":"TW20 9DP",
    "sg:province":"Surrey",
    "sg:tags":[
        "information"
    ],
    "wof:name":"Kerr-McGee Pigments (Europe) Ltd.",
    "wof:placetype":"venue"
},
  "geometry": {"coordinates":[-0.544734,51.43264],"type":"Point"}
}