{
  "type": "Feature",
  "properties": {
    "iso:country":"GB",
    "sg:address":"31 Whipton Lane",
    "sg:city":"Exeter",
    "sg:classifiers":[
        {
            "category":"Personal",
            "type":"Services"
        },
        {
            "category":"Retail",
            "subcategory":"Laundry & Dry Cleaning",
            "type":"Services"
        }
    ],
    "sg:phone":"+44 1392 435829",
    "sg:postcode":"EX1 3DN",
    "sg:province":"Devon",
    "sg:tags":[
        "dressmaker",
        "alteration"
    ],
    "wof:name":"Taffeta & Lace",
    "wof:placetype":"venue"
},
  "geometry": {"coordinates":[-3.49632,50.724087],"type":"Point"}
}