{
  "type": "Feature",
  "properties": {
    "iso:country":"GB",
    "sg:address":"Copper Beech, Efailwen",
    "sg:city":"Clynderwen",
    "sg:classifiers":[
        {
            "category":"Building & Trades",
            "subcategory":"Equipment Rental",
            "type":"Services"
        }
    ],
    "sg:phone":"+44 1994 419529",
    "sg:postcode":"SA66 7UX",
    "sg:province":"Carmarthenshire",
    "sg:tags":[
        "plant",
        "machinery"
    ],
    "wof:name":"Russell Thomas",
    "wof:placetype":"venue"
},
  "geometry": {"coordinates":[-4.7292199135,51.8399734497],"type":"Point"}
}