{
  "type": "Feature",
  "properties": {
    "addr:full":"31-33 Kew Rd Richmond Greater London TW9 2NQ",
    "addr:housenumber":"31-33",
    "addr:postcode":"tw9 2nq",
    "addr:street":"Kew Rd",
    "iso:country":"GB",
    "sg:address":"31-33 Kew Rd",
    "sg:city":"Richmond",
    "sg:classifiers":[
        {
            "category":"Restaurant",
            "type":"Food & Drink"
        }
    ],
    "sg:phone":"+44 20 8948 2159",
    "sg:postcode":"TW9 2NQ",
    "sg:province":"Greater London",
    "wof:name":"Captains Table The",
    "wof:placetype":"venue"
},
  "geometry": {"coordinates":[-0.3018009961,51.463924408],"type":"Point"}
}