{
  "type": "Feature",
  "properties": {
    "iso:country":"GB",
    "sg:address":"374a Wandsworth Rd",
    "sg:city":"South Lambeth",
    "sg:classifiers":[
        {
            "category":"Retail",
            "subcategory":"Auto Repair",
            "type":"Services"
        }
    ],
    "sg:phone":"+44 20 7622 6200",
    "sg:postcode":"SW8 4TE",
    "sg:province":"Greater London",
    "sg:tags":[
        "modification",
        "garage"
    ],
    "wof:name":"South Bank Motor Co",
    "wof:placetype":"venue"
},
  "geometry": {"coordinates":[-0.1376399994,51.4711380005],"type":"Point"}
}