{
  "type": "Feature",
  "properties": {
    "addr:full":"9a Devonshire Road, Chiswick London Greater London W4 2EU",
    "addr:housenumber":"9a",
    "addr:postcode":"w4 2eu",
    "addr:street":"Devonshire Road",
    "iso:country":"GB",
    "sg:address":"9a Devonshire Road, Chiswick",
    "sg:city":"London",
    "sg:classifiers":[
        {
            "category":"Fast Food",
            "type":"Food & Drink"
        }
    ],
    "sg:postcode":"W4 2EU",
    "sg:province":"Greater London",
    "sg:tags":[
        "away",
        "take"
    ],
    "wof:name":"Diplomat Restaurants Ltd",
    "wof:placetype":"venue"
},
  "geometry": {"coordinates":[-0.2561889887,51.4921913147],"type":"Point"}
}