{
  "type": "Feature",
  "properties": {
    "addr:full":"16 Harcourt Estate, Kibworth Leicester Leicestershire LE8 0NE",
    "addr:housenumber":"16",
    "addr:postcode":"le8 0ne",
    "addr:street":"Harcourt Estate",
    "iso:country":"GB",
    "sg:address":"16 Harcourt Estate, Kibworth",
    "sg:city":"Leicester",
    "sg:classifiers":[
        {
            "category":"Shopping",
            "subcategory":"Antiques",
            "type":"Retail Goods"
        }
    ],
    "sg:phone":"+44 116 279 3475",
    "sg:postcode":"LE8 0NE",
    "sg:province":"Leicestershire",
    "wof:name":"Kibworth Pine Co.",
    "wof:placetype":"venue"
},
  "geometry": {"coordinates":[-0.993731,52.542805],"type":"Point"}
}