{
  "type": "Feature",
  "properties": {
    "iso:country":"GB",
    "sg:address":"8 Compton Av",
    "sg:city":"Reading",
    "sg:classifiers":[
        {
            "category":"Communications",
            "subcategory":"Film & Video Production",
            "type":"Services"
        }
    ],
    "sg:phone":"+44 118 942 8869",
    "sg:postcode":"RG31 5LH",
    "sg:province":"Berkshire",
    "sg:tags":[
        "illustrator",
        "artist"
    ],
    "wof:name":"Katherine Baxter",
    "wof:placetype":"venue"
},
  "geometry": {"coordinates":[-1.051921,51.456196],"type":"Point"}
}