{
  "type": "Feature",
  "properties": {
    "addr:full":"89 Brighton Road Purley Surrey CR8 4HD",
    "addr:housenumber":"89",
    "addr:postcode":"cr8 4hd",
    "addr:street":"Brighton Road",
    "iso:country":"GB",
    "sg:address":"89 Brighton Road",
    "sg:city":"Purley",
    "sg:classifiers":[
        {
            "category":"Health Services",
            "subcategory":"Doctor",
            "type":"Services"
        },
        {
            "category":"Health Services",
            "subcategory":"Health Practitioner",
            "type":"Services"
        }
    ],
    "sg:phone":"+44 20 8660 6632",
    "sg:postcode":"CR8 4HD",
    "sg:province":"Surrey",
    "sg:tags":[
        "osteopath"
    ],
    "wof:name":"JOHN & HAZEL SILVERSTONE",
    "wof:placetype":"venue"
},
  "geometry": {"coordinates":[-0.123535,51.332462],"type":"Point"}
}