{
  "type": "Feature",
  "properties": {
    "addr:full":"1 Green Street London Greater London W1K 6RG",
    "addr:housenumber":"1",
    "addr:postcode":"w1k 6rg",
    "addr:street":"Green Street",
    "iso:country":"GB",
    "sg:address":"1 Green Street",
    "sg:city":"London",
    "sg:classifiers":[
        {
            "category":"Professional",
            "subcategory":"Lawyer & Legal Services",
            "type":"Services"
        }
    ],
    "sg:phone":"+44 20 7499 0944",
    "sg:postcode":"W1K 6RG",
    "sg:province":"Greater London",
    "sg:tags":[
        "solicitor"
    ],
    "wof:name":"Owen Thomas",
    "wof:placetype":"venue"
},
  "geometry": {"coordinates":[-0.1536359936,51.5130615234],"type":"Point"}
}