{
  "type": "Feature",
  "properties": {
    "iso:country":"GB",
    "sg:address":"67 High St",
    "sg:city":"Ilfracombe",
    "sg:classifiers":[
        {
            "category":"Real Estate",
            "subcategory":"Real Estate Agent",
            "type":"Services"
        }
    ],
    "sg:phone":"+44 1271 863408",
    "sg:postcode":"EX34 9QE",
    "sg:province":"Devon",
    "wof:name":"Stevens,Timothy J,",
    "wof:placetype":"venue"
},
  "geometry": {"coordinates":[-4.1257171631,51.2066078186],"type":"Point"}
}