{
  "type": "Feature",
  "properties": {
    "addr:full":"10 Wellington Parade, Blackfen Road Sidcup Kent DA15 9NB",
    "addr:housenumber":"10",
    "addr:postcode":"da15 9nb",
    "addr:street":"Wellington Parade Blackfen Road",
    "iso:country":"GB",
    "sg:address":"10 Wellington Parade, Blackfen Road",
    "sg:city":"Sidcup",
    "sg:classifiers":[
        {
            "category":"Health Services",
            "subcategory":"Optometrist",
            "type":"Services"
        },
        {
            "category":"Health Services",
            "subcategory":"Doctor",
            "type":"Services"
        }
    ],
    "sg:phone":"+44 20 8303 3935",
    "sg:postcode":"DA15 9NB",
    "sg:province":"Kent",
    "sg:tags":[
        "optician"
    ],
    "wof:name":"Gothelf S Associates",
    "wof:placetype":"venue"
},
  "geometry": {"coordinates":[0.1027019992,51.4500694275],"type":"Point"}
}