{
  "type": "Feature",
  "properties": {
    "iso:country":"GB",
    "sg:address":"Moor Farm, Moor Lane, Shobrooke",
    "sg:city":"Crediton",
    "sg:classifiers":[
        {
            "category":"Home & Garden",
            "subcategory":"Garden Supply",
            "type":"Retail Goods"
        },
        {
            "category":"Farming",
            "subcategory":"Livestock Farm",
            "type":"Manufacturing & Wholesale Goods"
        }
    ],
    "sg:postcode":"EX17 1AY",
    "sg:province":"Devon",
    "sg:tags":[
        "bulb",
        "grower",
        "others"
    ],
    "wof:name":"D P Ward",
    "wof:placetype":"venue"
},
  "geometry": {"coordinates":[-3.617874,50.798553],"type":"Point"}
}