{
  "type": "Feature",
  "properties": {
    "addr:full":"137a Hankinson Rd, Charminster Bournemouth Dorset BH9 1HR",
    "addr:housenumber":"137a",
    "addr:postcode":"bh9 1hr",
    "addr:street":"Hankinson Rd",
    "iso:country":"GB",
    "sg:address":"137a Hankinson Rd, Charminster",
    "sg:city":"Bournemouth",
    "sg:classifiers":[
        {
            "category":"Retail",
            "subcategory":"Auto Repair",
            "type":"Services"
        }
    ],
    "sg:phone":"+44 1202 251315",
    "sg:postcode":"BH9 1HR",
    "sg:province":"Dorset",
    "sg:tags":[
        "body",
        "car"
    ],
    "wof:name":"AJS Body Works",
    "wof:placetype":"venue"
},
  "geometry": {"coordinates":[-1.863924,50.740883],"type":"Point"}
}