{
  "type": "Feature",
  "properties": {
    "iso:country":"GB",
    "sg:address":"12 Tower Road",
    "sg:city":"Washington",
    "sg:classifiers":[
        {
            "category":"Professional",
            "subcategory":"Printing & Photocopies",
            "type":"Services"
        }
    ],
    "sg:postcode":"NE37 2SH",
    "sg:province":"Tyne and Wear",
    "sg:tags":[
        "printer"
    ],
    "wof:name":"Jasprint",
    "wof:placetype":"venue"
},
  "geometry": {"coordinates":[-1.511522,54.907722],"type":"Point"}
}