{
  "type": "Feature",
  "properties": {
    "addr:full":"2a Albert Pl Woodbridge Suffolk IP13 9DX",
    "addr:housenumber":"2a",
    "addr:postcode":"ip13 9dx",
    "addr:street":"Albert Pl",
    "iso:country":"GB",
    "sg:address":"2a Albert Pl",
    "sg:city":"Woodbridge",
    "sg:classifiers":[
        {
            "category":"Manufacturing",
            "subcategory":"Tools & Machinery",
            "type":"Manufacturing & Wholesale Goods"
        }
    ],
    "sg:phone":"+44 1728 724169",
    "sg:postcode":"IP13 9DX",
    "sg:province":"Suffolk",
    "sg:tags":[
        "society",
        "friendly"
    ],
    "wof:name":"Bernard Whiting",
    "wof:placetype":"venue"
},
  "geometry": {"coordinates":[1.3415640593,52.2213516235],"type":"Point"}
}