{
  "type": "Feature",
  "properties": {
    "addr:full":"Suite A, Berkley Court, St Mary's Street Huntingdon Bedfordshire PE19 4TU",
    "addr:housenumber":"suite a",
    "addr:postcode":"pe19 4tu",
    "addr:street":"Berkley Court St Mary'S Street",
    "iso:country":"GB",
    "sg:address":"Suite A, Berkley Court, St Mary's Street",
    "sg:city":"Huntingdon",
    "sg:classifiers":[
        {
            "category":"Building & Trades",
            "subcategory":"Construction",
            "type":"Services"
        }
    ],
    "sg:phone":"+44 1480 477233",
    "sg:postcode":"PE19 4TU",
    "sg:province":"Bedfordshire",
    "sg:tags":[
        "dry",
        "lining",
        "plasterers",
        "screeders"
    ],
    "wof:name":"Tuffwall Plastering",
    "wof:placetype":"venue"
},
  "geometry": {"coordinates":[-0.269346,52.227684],"type":"Point"}
}