{
  "type": "Feature",
  "properties": {
    "addr:full":"Paget Road Barry The Vale of Glamorgan CF62 5TQ",
    "addr:postcode":"cf62 5tq",
    "addr:street":"Paget Road;Vale",
    "iso:country":"GB",
    "sg:address":"Paget Road",
    "sg:city":"Barry",
    "sg:classifiers":[
        {
            "category":"Food & Beverages",
            "subcategory":"Candy",
            "type":"Retail Goods"
        }
    ],
    "sg:postcode":"CF62 5TQ",
    "sg:province":"The Vale of Glamorgan",
    "sg:tags":[
        "confectioner"
    ],
    "wof:name":"The Rock Shop",
    "wof:placetype":"venue"
},
  "geometry": {"coordinates":[-3.2780721188,51.3905029297],"type":"Point"}
}