{
  "type": "Feature",
  "properties": {
    "addr:full":"After Hours Office, 5 Jade Clo Cardiff Cardiff CF4 5GE",
    "addr:housenumber":"5",
    "addr:postcode":"cf4 5ge",
    "addr:street":"Jade Clo",
    "iso:country":"GB",
    "sg:address":"After Hours Office, 5 Jade Clo",
    "sg:city":"Cardiff",
    "sg:classifiers":[
        {
            "category":"Utilities",
            "subcategory":"Electric",
            "type":"Services"
        }
    ],
    "sg:phone":"+44 29 2074 7002",
    "sg:postcode":"CF4 5GE",
    "sg:province":"Cardiff",
    "sg:tags":[
        "vehicle"
    ],
    "wof:name":"Mobile Electrics",
    "wof:placetype":"venue"
},
  "geometry": {"coordinates":[-3.180670023,51.4812583923],"type":"Point"}
}