{
  "type": "Feature",
  "properties": {
    "addr:full":"25 St Georges Rd Cheltenham Gloucestershire GL50 3DT",
    "addr:housenumber":"25",
    "addr:postcode":"gl50 3dt",
    "addr:street":"St Georges Rd",
    "iso:country":"GB",
    "sg:address":"25 St Georges Rd",
    "sg:city":"Cheltenham",
    "sg:classifiers":[
        {
            "category":"Professional",
            "subcategory":"Art Services",
            "type":"Services"
        }
    ],
    "sg:phone":"+44 1242 255831",
    "sg:postcode":"GL50 3DT",
    "sg:province":"Gloucestershire",
    "sg:tags":[
        "graphic",
        "designer"
    ],
    "wof:name":"Accorde Group Ltd The",
    "wof:placetype":"venue"
},
  "geometry": {"coordinates":[-2.080392,51.898891],"type":"Point"}
}