{
  "type": "Feature",
  "properties": {
    "addr:full":"Unit 2, Usk Way Industrial Estate, Old Town Dock Newport Newport NP20 2HZ",
    "addr:housenumber":"unit 2;estate",
    "addr:postcode":"np20 2hz",
    "addr:street":"Usk Way Industrial;Dock Newport",
    "iso:country":"GB",
    "sg:address":"Unit 2, Usk Way Industrial Estate, Old Town Dock",
    "sg:city":"Newport",
    "sg:classifiers":[
        {
            "category":"Wholesale",
            "subcategory":"Machinery & Supplies",
            "type":"Manufacturing & Wholesale Goods"
        },
        {
            "category":"Arts & Performance",
            "subcategory":"Theater",
            "type":"Entertainment"
        }
    ],
    "sg:phone":"+44 1633 262728",
    "sg:postcode":"NP20 2HZ",
    "sg:province":"Newport",
    "sg:tags":[
        "theatrical",
        "presentation"
    ],
    "wof:name":"Scenic & Property Hire",
    "wof:placetype":"venue"
},
  "geometry": {"coordinates":[-2.9893939495,51.5848960876],"type":"Point"}
}