{
  "type": "Feature",
  "properties": {
    "addr:full":"684 High Road London Greater London N12 9PT",
    "addr:housenumber":"684",
    "addr:postcode":"n12 9pt",
    "addr:street":"High Road",
    "iso:country":"GB",
    "sg:address":"684 High Road",
    "sg:city":"London",
    "sg:classifiers":[
        {
            "category":"Shopping",
            "subcategory":"Clothing, Apparel, & Fashions",
            "type":"Retail Goods"
        }
    ],
    "sg:phone":"+44 20 8343 7930",
    "sg:postcode":"N12 9PT",
    "sg:province":"Greater London",
    "sg:tags":[
        "ladieswear"
    ],
    "wof:name":"New Image",
    "wof:placetype":"venue"
},
  "geometry": {"coordinates":[-0.1757539958,51.6128387451],"type":"Point"}
}