{
  "type": "Feature",
  "properties": {
    "addr:full":"Unit 41, Walton Business Centre, 44-46 Terrace Road Walton-on-thames Surrey KT12 2SD",
    "addr:housenumber":"unit 41;business;44-46",
    "addr:postcode":"kt12 2sd",
    "addr:street":"Walton;Terrace Road",
    "iso:country":"GB",
    "sg:address":"Unit 41, Walton Business Centre, 44-46 Terrace Road",
    "sg:city":"Walton-on-thames",
    "sg:classifiers":[
        {
            "category":"Professional",
            "subcategory":"Art Services",
            "type":"Services"
        }
    ],
    "sg:phone":"+44 1932 230364",
    "sg:postcode":"KT12 2SD",
    "sg:province":"Surrey",
    "sg:tags":[
        "picture",
        "restoration",
        "cleaning"
    ],
    "wof:name":"Concept Art & Design Ltd.",
    "wof:placetype":"venue"
},
  "geometry": {"coordinates":[-0.4207040071,51.3843460083],"type":"Point"}
}