{
  "type": "Feature",
  "properties": {
    "addr:full":"31 Brunswick Road Shoreham-by-sea West Sussex BN43 5WA",
    "addr:housenumber":"31",
    "addr:postcode":"bn43 5wa",
    "addr:street":"Brunswick Road",
    "iso:country":"GB",
    "sg:address":"31 Brunswick Road",
    "sg:city":"Shoreham-by-sea",
    "sg:classifiers":[
        {
            "category":"Real Estate",
            "subcategory":"Real Estate Agent",
            "type":"Services"
        }
    ],
    "sg:phone":"+44 1273 441341",
    "sg:postcode":"BN43 5WA",
    "sg:province":"West Sussex",
    "wof:name":"Jacobs Steel & Co.",
    "wof:placetype":"venue"
},
  "geometry": {"coordinates":[-0.272728,50.833969],"type":"Point"}
}