{
  "type": "Feature",
  "properties": {
    "iso:country":"GB",
    "sg:address":"Suite 1 Town Hall",
    "sg:city":"Matlock",
    "sg:classifiers":[
        {
            "category":"Shopping",
            "subcategory":"Stationery & Office Supplies",
            "type":"Retail Goods"
        }
    ],
    "sg:phone":"+44 1629 825845",
    "sg:postcode":"DE4 4EU",
    "sg:province":"Derbyshire",
    "wof:name":"Pegasus Partners Ltd",
    "wof:placetype":"venue"
},
  "geometry": {"coordinates":[-1.654337,53.082943],"type":"Point"}
}