{
  "type": "Feature",
  "properties": {
    "addr:full":"252 Berkhamstead Road Chesham Buckinghamshire HP5 3ET",
    "addr:housenumber":"252",
    "addr:postcode":"hp5 3et",
    "addr:street":"Berkhamstead Road",
    "iso:country":"GB",
    "sg:address":"252 Berkhamstead Road",
    "sg:city":"Chesham",
    "sg:classifiers":[
        {
            "category":"Home & Garden",
            "subcategory":"Carpets & Floor Coverings",
            "type":"Retail Goods"
        }
    ],
    "sg:phone":"+44 1494 786307",
    "sg:postcode":"HP5 3ET",
    "sg:province":"Buckinghamshire",
    "sg:tags":[
        "carpets",
        "retailer",
        "rug",
        "matting"
    ],
    "wof:name":"SUMMERLING CARPETS & CURTAINS LTD",
    "wof:placetype":"venue"
},
  "geometry": {"coordinates":[-0.608129,51.712551],"type":"Point"}
}