{
  "type": "Feature",
  "properties": {
    "iso:country":"GB",
    "sg:address":"21 Cherry Lane, Wootton",
    "sg:city":"Ulceby",
    "sg:classifiers":[
        {
            "category":"Building & Trades",
            "subcategory":"Construction",
            "type":"Services"
        }
    ],
    "sg:phone":"+44 1469 588336",
    "sg:postcode":"DN39 6RL",
    "sg:province":"Lincolnshire",
    "sg:tags":[
        "joinery",
        "joiner",
        "carpenter",
        "carpentry"
    ],
    "wof:name":"D R Staves",
    "wof:placetype":"venue"
},
  "geometry": {"coordinates":[-0.360754,53.629169],"type":"Point"}
}