{
  "type": "Feature",
  "properties": {
    "iso:country":"GB",
    "sg:address":"Fen Rd",
    "sg:city":"Lincoln",
    "sg:classifiers":[
        {
            "category":"Community Center",
            "type":"Public Place"
        }
    ],
    "sg:phone":"+44 1522 792816",
    "sg:postcode":"LN4 1AE",
    "sg:province":"Lincolnshire",
    "sg:tags":[
        "centre"
    ],
    "wof:name":"Washingborough Community Centre",
    "wof:placetype":"venue"
},
  "geometry": {"coordinates":[-0.451039,53.211933],"type":"Point"}
}