{
  "type": "Feature",
  "properties": {
    "addr:full":"6 Crossway Bracknell Berkshire RG12 1AF",
    "addr:housenumber":"6",
    "addr:postcode":"rg12 1af",
    "addr:street":"Crossway",
    "iso:country":"GB",
    "sg:address":"6 Crossway",
    "sg:city":"Bracknell",
    "sg:classifiers":[
        {
            "category":"Shopping",
            "subcategory":"Discount & Variety Stores",
            "type":"Retail Goods"
        }
    ],
    "sg:postcode":"RG12 1AF",
    "sg:province":"Berkshire",
    "sg:tags":[
        "centre"
    ],
    "wof:name":"Cost to Cost",
    "wof:placetype":"venue"
},
  "geometry": {"coordinates":[-0.7487699986,51.4169387817],"type":"Point"}
}