{
  "type": "Feature",
  "properties": {
    "iso:country":"GB",
    "sg:address":"The Drill Hall, Grove Rd",
    "sg:city":"Hastings",
    "sg:classifiers":[
        {
            "category":"Manufacturing",
            "subcategory":"Lumber",
            "type":"Manufacturing & Wholesale Goods"
        }
    ],
    "sg:phone":"+44 1424 428601",
    "sg:postcode":"TN35 4JS",
    "sg:province":"East Sussex",
    "sg:tags":[
        "importer",
        "merchants",
        "agent",
        "timber"
    ],
    "wof:name":"Hi-Tec Plant & Building Supplies Ltd",
    "wof:placetype":"venue"
},
  "geometry": {"coordinates":[0.60883,50.875439],"type":"Point"}
}