{
  "type": "Feature",
  "properties": {
    "addr:full":"20 West End, Costessey Norwich Norfolk NR8 5AG",
    "addr:housenumber":"20",
    "addr:postcode":"nr8 5ag",
    "addr:street":"West End;Norwich Norfolk",
    "iso:country":"GB",
    "sg:address":"20 West End, Costessey",
    "sg:city":"Norwich",
    "sg:classifiers":[
        {
            "category":"Recreation",
            "type":"Entertainment"
        }
    ],
    "sg:phone":"+44 1603 747876",
    "sg:postcode":"NR8 5AG",
    "sg:province":"Norfolk",
    "sg:tags":[
        "snooker",
        "billiards",
        "pool"
    ],
    "wof:name":"West End Cue Club",
    "wof:placetype":"venue"
},
  "geometry": {"coordinates":[1.20801,52.658859],"type":"Point"}
}