{
  "type": "Feature",
  "properties": {
    "iso:country":"GB",
    "sg:address":"11 Shaw Road, Heaton Moor",
    "sg:city":"Stockport",
    "sg:classifiers":[
        {
            "category":"Shopping",
            "subcategory":"Clothing, Apparel, & Fashions",
            "type":"Retail Goods"
        }
    ],
    "sg:postcode":"SK4 4AG",
    "sg:province":"Cheshire",
    "sg:tags":[
        "menswear"
    ],
    "wof:name":"A Walmsley & Co. Ltd.",
    "wof:placetype":"venue"
},
  "geometry": {"coordinates":[-2.1848089695,53.423034668],"type":"Point"}
}