{
  "type": "Feature",
  "properties": {
    "iso:country":"GB",
    "sg:address":"32 Bell Street",
    "sg:city":"Henley-on-thames",
    "sg:classifiers":[
        {
            "category":"Shopping",
            "subcategory":"Pharmacy",
            "type":"Retail Goods"
        }
    ],
    "sg:phone":"+44 1491 414333",
    "sg:postcode":"RG9 2BG",
    "sg:province":"Berkshire",
    "sg:tags":[
        "pharmaceutical"
    ],
    "wof:name":"Orphan Europe (U K) Ltd.",
    "wof:placetype":"venue"
},
  "geometry": {"coordinates":[-0.904559,51.538441],"type":"Point"}
}