{
  "type": "Feature",
  "properties": {
    "addr:full":"Lyndhurst Hall, Warden Road London Greater London NW5 4RE",
    "addr:postcode":"nw5 4re",
    "addr:street":"Warden Road",
    "iso:country":"GB",
    "sg:address":"Lyndhurst Hall, Warden Road",
    "sg:city":"London",
    "sg:classifiers":[
        {
            "category":"Organizations",
            "subcategory":"Membership Organization",
            "type":"Services"
        }
    ],
    "sg:phone":"+44 20 7284 3939",
    "sg:postcode":"NW5 4RE",
    "sg:province":"Greater London",
    "sg:tags":[
        "club"
    ],
    "wof:name":"Camden Workers Social Club",
    "wof:placetype":"venue"
},
  "geometry": {"coordinates":[-0.148249,51.548244],"type":"Point"}
}