{
  "type": "Feature",
  "properties": {
    "iso:country":"GB",
    "sg:address":"The Workshop, Moss Lane, Heversham",
    "sg:city":"Milnthorpe",
    "sg:classifiers":[
        {
            "category":"Building & Trades",
            "subcategory":"Construction",
            "type":"Services"
        }
    ],
    "sg:phone":"+44 15395 63791",
    "sg:postcode":"LA7 7EN",
    "sg:province":"Cumbria",
    "sg:tags":[
        "joiner",
        "carpenter"
    ],
    "wof:name":"William Gott",
    "wof:placetype":"venue"
},
  "geometry": {"coordinates":[-2.772592,54.226864],"type":"Point"}
}