{
  "type": "Feature",
  "properties": {
    "iso:country":"GB",
    "sg:address":"67 York Road, Acomb",
    "sg:city":"York",
    "sg:classifiers":[
        {
            "category":"Banks & Credit Unions",
            "subcategory":"Bank",
            "type":"Services"
        }
    ],
    "sg:phone":"+44 1904 798277",
    "sg:postcode":"YO24 4LN",
    "sg:province":"North Yorkshire",
    "sg:tags":[
        "financial",
        "institution"
    ],
    "sg:website":"http://www.lloydstsb.com",
    "wof:name":"Lloyds TSB Bank plc",
    "wof:placetype":"venue"
},
  "geometry": {"coordinates":[-1.1231869459,53.9558792114],"type":"Point"}
}