{
  "type": "Feature",
  "properties": {
    "addr:full":"Unit 2a Roundthorn House, Roundthorn Industrial Estate, Floats Road Manchester Cheshire M23 9LJ",
    "addr:housenumber":"unit 2a roundthorn house",
    "addr:postcode":"m23 9lj",
    "addr:street":"Roundthorn Industrial Estate Floats Road",
    "iso:country":"GB",
    "sg:address":"Unit 2a Roundthorn House, Roundthorn Industrial Estate, Floats Road",
    "sg:city":"Manchester",
    "sg:classifiers":[
        {
            "category":"Organizations",
            "subcategory":"Non-profit Organization",
            "type":"Services"
        }
    ],
    "sg:phone":"+44 161 945 3415",
    "sg:postcode":"M23 9LJ",
    "sg:province":"Cheshire",
    "sg:tags":[
        "organisation",
        "voluntary",
        "charity"
    ],
    "wof:name":"Ymca",
    "wof:placetype":"venue"
},
  "geometry": {"coordinates":[-2.2964799404,53.3892250061],"type":"Point"}
}