{
  "type": "Feature",
  "properties": {
    "iso:country":"GB",
    "sg:address":"Belle Vue Terrace",
    "sg:city":"Newport",
    "sg:classifiers":[
        {
            "category":"Shopping",
            "subcategory":"Pharmacy",
            "type":"Retail Goods"
        }
    ],
    "sg:phone":"+44 1633 264291",
    "sg:postcode":"NP20 2LB",
    "sg:province":"Newport",
    "sg:tags":[
        "dispensing",
        "store",
        "drug",
        "chemist"
    ],
    "wof:name":"J D S Evans",
    "wof:placetype":"venue"
},
  "geometry": {"coordinates":[-2.997234,51.577332],"type":"Point"}
}