{
  "type": "Feature",
  "properties": {
    "iso:country":"GB",
    "sg:address":"Hays Chemical Ltd, Booth Lane",
    "sg:city":"Sandbach",
    "sg:classifiers":[
        {
            "category":"Professional",
            "subcategory":"Business Services",
            "type":"Services"
        }
    ],
    "sg:postcode":"CW11 3PZ",
    "sg:province":"Cheshire",
    "sg:tags":[
        "distribution"
    ],
    "wof:name":"Hagan Ltd.",
    "wof:placetype":"venue"
},
  "geometry": {"coordinates":[-2.363648,53.142208],"type":"Point"}
}