{
  "type": "Feature",
  "properties": {
    "addr:full":"3 Alexandra Parade, Northolt Road Harrow Greater London HA2 8HE",
    "addr:housenumber":"3",
    "addr:postcode":"ha2 8he",
    "addr:street":"Alexandra Parade Northolt Road",
    "iso:country":"GB",
    "sg:address":"3 Alexandra Parade, Northolt Road",
    "sg:city":"Harrow",
    "sg:classifiers":[
        {
            "category":"Fast Food",
            "type":"Food & Drink"
        }
    ],
    "sg:phone":"+44 20 8422 8055",
    "sg:postcode":"HA2 8HE",
    "sg:province":"Greater London",
    "sg:tags":[
        "away",
        "meal",
        "outlet",
        "take"
    ],
    "wof:name":"Spicy Nights",
    "wof:placetype":"venue"
},
  "geometry": {"coordinates":[-0.3629780114,51.5581741333],"type":"Point"}
}