{
  "type": "Feature",
  "properties": {
    "iso:country":"GB",
    "sg:address":"Bridge St",
    "sg:city":"Lampeter",
    "sg:classifiers":[
        {
            "category":"Health Services",
            "subcategory":"Dentist",
            "type":"Services"
        }
    ],
    "sg:phone":"+44 1570 423459",
    "sg:postcode":"SA48 7AA",
    "sg:province":"Carmarthenshire",
    "wof:name":"Lampeter Dental Clinic",
    "wof:placetype":"venue"
},
  "geometry": {"coordinates":[-4.077894,52.112694],"type":"Point"}
}