{
  "type": "Feature",
  "properties": {
    "addr:full":"Roseneath, Wallcote Road, South Kilworth Lutterworth Leicestershire LE17 6EQ",
    "addr:postcode":"le17 6eq",
    "addr:street":"Wallcote Road South",
    "iso:country":"GB",
    "sg:address":"Roseneath, Wallcote Road, South Kilworth",
    "sg:city":"Lutterworth",
    "sg:classifiers":[
        {
            "category":"Freight",
            "type":"Transportation"
        }
    ],
    "sg:postcode":"LE17 6EQ",
    "sg:province":"Leicestershire",
    "sg:tags":[
        "haulage",
        "road"
    ],
    "wof:name":"John Berry Haulage Ltd.",
    "wof:placetype":"venue"
},
  "geometry": {"coordinates":[-1.1119170189,52.431350708],"type":"Point"}
}