{
  "type": "Feature",
  "properties": {
    "addr:full":"53 Waites Lane, Fairlight Hastings East Sussex TN35 4AX",
    "addr:housenumber":"53",
    "addr:postcode":"tn35 4ax",
    "addr:street":"Waites Lane",
    "iso:country":"GB",
    "sg:address":"53 Waites Lane, Fairlight",
    "sg:city":"Hastings",
    "sg:classifiers":[
        {
            "category":"Bars & Pubs",
            "type":"Food & Drink"
        }
    ],
    "sg:phone":"+44 1424 812110",
    "sg:postcode":"TN35 4AX",
    "sg:province":"East Sussex",
    "sg:tags":[
        "pubs",
        "inn"
    ],
    "wof:name":"The Cove",
    "wof:placetype":"venue"
},
  "geometry": {"coordinates":[0.663413,50.876842],"type":"Point"}
}