{
  "type": "Feature",
  "properties": {
    "addr:full":"Glebe Farm, Harp Rd, Mark Highbridge Somerset TA9 4QW",
    "addr:postcode":"ta9 4qw",
    "addr:street":"Harp Rd",
    "iso:country":"GB",
    "sg:address":"Glebe Farm, Harp Rd, Mark",
    "sg:city":"Highbridge",
    "sg:classifiers":[
        {
            "category":"Building & Trades",
            "subcategory":"Construction",
            "type":"Services"
        }
    ],
    "sg:phone":"+44 1278 760274",
    "sg:postcode":"TA9 4QW",
    "sg:province":"Somerset",
    "sg:tags":[
        "joinery",
        "contractor",
        "fencing"
    ],
    "wof:name":"Glebe Fencing",
    "wof:placetype":"venue"
},
  "geometry": {"coordinates":[-2.892619,51.227337],"type":"Point"}
}