{
  "type": "Feature",
  "properties": {
    "addr:full":"58 Upper Orwell St Ipswich Suffolk IP4 1HR",
    "addr:housenumber":"58",
    "addr:postcode":"ip4 1hr",
    "addr:street":"Upper Orwell St",
    "iso:country":"GB",
    "sg:address":"58 Upper Orwell St",
    "sg:city":"Ipswich",
    "sg:classifiers":[
        {
            "category":"Personal",
            "subcategory":"Beauty Salon",
            "type":"Services"
        }
    ],
    "sg:phone":"+44 1473 281718",
    "sg:postcode":"IP4 1HR",
    "sg:province":"Suffolk",
    "wof:name":"Que Sera",
    "wof:placetype":"venue"
},
  "geometry": {"coordinates":[1.159395,52.055874],"type":"Point"}
}