{
  "type": "Feature",
  "properties": {
    "iso:country":"GB",
    "sg:address":"Wentworth Drive",
    "sg:city":"Broadstone",
    "sg:classifiers":[
        {
            "category":"Sports & Exercise",
            "subcategory":"Golf",
            "type":"Entertainment"
        }
    ],
    "sg:phone":"+44 1202 692835",
    "sg:postcode":"BH18 8DQ",
    "sg:province":"Dorset",
    "sg:tags":[
        "equipment"
    ],
    "wof:name":"Nigel Tokely",
    "wof:placetype":"venue"
},
  "geometry": {"coordinates":[-1.9936239719,50.7673797607],"type":"Point"}
}