{
  "type": "Feature",
  "properties": {
    "iso:country":"GB",
    "sg:address":"79 High St, Wavertree",
    "sg:city":"Liverpool",
    "sg:classifiers":[
        {
            "category":"Shopping",
            "subcategory":"Pharmacy",
            "type":"Retail Goods"
        }
    ],
    "sg:phone":"+44 151 733 7020",
    "sg:postcode":"L15 8HF",
    "sg:province":"Merseyside",
    "sg:tags":[
        "pharmacist",
        "dispensing",
        "chemist"
    ],
    "wof:name":"Wattersons Pharmacy",
    "wof:placetype":"venue"
},
  "geometry": {"coordinates":[-2.918324,53.39867],"type":"Point"}
}