{
  "type": "Feature",
  "properties": {
    "addr:full":"Newton Manor, Newton Manor Lane, Newton Rugby Northamptonshire CV23 0DW",
    "addr:postcode":"cv23 0dw",
    "addr:street":"Newton;Newton Manor Lane",
    "iso:country":"GB",
    "sg:address":"Newton Manor, Newton Manor Lane, Newton",
    "sg:city":"Rugby",
    "sg:classifiers":[
        {
            "category":"Retail",
            "subcategory":"Auto Repair",
            "type":"Services"
        }
    ],
    "sg:phone":"+44 1788 551349",
    "sg:postcode":"CV23 0DW",
    "sg:province":"Northamptonshire",
    "sg:tags":[
        "body",
        "car"
    ],
    "wof:name":"Automotive Bodycraft & Coachbuilders",
    "wof:placetype":"venue"
},
  "geometry": {"coordinates":[-1.2254730463,52.3931388855],"type":"Point"}
}