{
  "type": "Feature",
  "properties": {
    "addr:full":"12 The Idlewells Sutton-in-ashfield Nottinghamshire NG17 1BL",
    "addr:housenumber":"12",
    "addr:postcode":"ng17 1bl",
    "addr:street":"The Idlewells Sutton-In-Ashfield",
    "iso:country":"GB",
    "sg:address":"12 The Idlewells",
    "sg:city":"Sutton-in-ashfield",
    "sg:classifiers":[
        {
            "category":"Retail",
            "subcategory":"Photofinishing",
            "type":"Services"
        }
    ],
    "sg:phone":"+44 1623 441514",
    "sg:postcode":"NG17 1BL",
    "sg:province":"Nottinghamshire",
    "sg:tags":[
        "processing",
        "photographic",
        "processor"
    ],
    "wof:name":"Quick Snap Photo Lab",
    "wof:placetype":"venue"
},
  "geometry": {"coordinates":[-1.2770889997,53.1218414307],"type":"Point"}
}