{
  "type": "Feature",
  "properties": {
    "addr:full":"18 Melbourne Grove London Greater London SE22 8RA",
    "addr:housenumber":"18",
    "addr:postcode":"se22 8ra",
    "addr:street":"Melbourne Grove",
    "iso:country":"GB",
    "sg:address":"18 Melbourne Grove",
    "sg:city":"London",
    "sg:classifiers":[
        {
            "category":"Banks & Credit Unions",
            "subcategory":"Financial Services",
            "type":"Services"
        }
    ],
    "sg:postcode":"SE22 8RA",
    "sg:province":"Greater London",
    "sg:tags":[
        "consultant"
    ],
    "wof:name":"Elmtree Investments Limited",
    "wof:placetype":"venue"
},
  "geometry": {"coordinates":[-0.0798780024,51.4601211548],"type":"Point"}
}