{
  "type": "Feature",
  "properties": {
    "iso:country":"GB",
    "sg:address":"259 Ashford Road",
    "sg:city":"Staines",
    "sg:classifiers":[
        {
            "category":"Bakery",
            "type":"Food & Drink"
        }
    ],
    "sg:phone":"+44 1784 481441",
    "sg:postcode":"TW18 1QR",
    "sg:province":"Berkshire",
    "sg:tags":[
        "cake",
        "maker"
    ],
    "wof:name":"Cakes Unlimited",
    "wof:placetype":"venue"
},
  "geometry": {"coordinates":[-0.479861,51.420498],"type":"Point"}
}