{
  "type": "Feature",
  "properties": {
    "iso:country":"GB",
    "sg:address":"Old Foundry",
    "sg:city":"Brigg",
    "sg:classifiers":[
        {
            "category":"Professional",
            "subcategory":"Engineering",
            "type":"Services"
        }
    ],
    "sg:phone":"+44 1652 600200",
    "sg:postcode":"DN20 8NR",
    "sg:province":"Lincolnshire",
    "wof:name":"Peacock & Binnington Holdings Ltd.",
    "wof:placetype":"venue"
},
  "geometry": {"coordinates":[-0.484879,53.552986],"type":"Point"}
}