{
  "type": "Feature",
  "properties": {
    "addr:full":"4-6 Horsemarket Darlington Durham DL1 5PW",
    "addr:housenumber":"4-6",
    "addr:postcode":"dl1 5pw",
    "addr:street":"Horsemarket Darlington",
    "iso:country":"GB",
    "sg:address":"4-6 Horsemarket",
    "sg:city":"Darlington",
    "sg:classifiers":[
        {
            "category":"Sports & Exercise",
            "subcategory":"Gym",
            "type":"Entertainment"
        }
    ],
    "sg:phone":"+44 1325 369409",
    "sg:postcode":"DL1 5PW",
    "sg:province":"Durham",
    "sg:tags":[
        "fitness",
        "health",
        "centre"
    ],
    "wof:name":"Image",
    "wof:placetype":"venue"
},
  "geometry": {"coordinates":[-1.548894,54.524502],"type":"Point"}
}