{
  "type": "Feature",
  "properties": {
    "addr:full":"Victory Hall, Stockcroft Road, Balcombe Haywards Heath East Sussex RH17 6HP",
    "addr:postcode":"rh17 6hp",
    "addr:street":"Stockcroft Road",
    "iso:country":"GB",
    "sg:address":"Victory Hall, Stockcroft Road, Balcombe",
    "sg:city":"Haywards Heath",
    "sg:classifiers":[
        {
            "category":"Organizations",
            "subcategory":"Membership Organization",
            "type":"Services"
        }
    ],
    "sg:phone":"+44 1444 811226",
    "sg:postcode":"RH17 6HP",
    "sg:province":"East Sussex",
    "sg:tags":[
        "club",
        "social"
    ],
    "wof:name":"Balcombe Social Club",
    "wof:placetype":"venue"
},
  "geometry": {"coordinates":[-0.1346240044,51.0590362549],"type":"Point"}
}