{
  "type": "Feature",
  "properties": {
    "iso:country":"GB",
    "sg:address":"54 Leopold Road",
    "sg:city":"Felixstowe",
    "sg:classifiers":[
        {
            "category":"Retail",
            "subcategory":"Driving School",
            "type":"Services"
        }
    ],
    "sg:phone":"+44 1394 272248",
    "sg:postcode":"IP11 7NP",
    "sg:province":"Suffolk",
    "wof:name":"A D Harris",
    "wof:placetype":"venue"
},
  "geometry": {"coordinates":[1.3489220142,51.961517334],"type":"Point"}
}