{
  "type": "Feature",
  "properties": {
    "addr:full":"Silver Street, Chew Magna Bristol Somerset BS40 8RE",
    "addr:postcode":"bs40 8re",
    "addr:street":"Silver Street",
    "iso:country":"GB",
    "sg:address":"Silver Street, Chew Magna",
    "sg:city":"Bristol",
    "sg:classifiers":[
        {
            "category":"Government",
            "subcategory":"Office",
            "type":"Public Place"
        }
    ],
    "sg:phone":"+44 1275 856024",
    "sg:postcode":"BS40 8RE",
    "sg:province":"Somerset",
    "sg:tags":[
        "local"
    ],
    "wof:name":"North Somerset Council",
    "wof:placetype":"venue"
},
  "geometry": {"coordinates":[-2.611749,51.3657],"type":"Point"}
}