{
  "type": "Feature",
  "properties": {
    "addr:full":"Thornthwaite Close, Rubery, Rednal Birmingham West Midlands B45 0DS",
    "addr:postcode":"b45 0ds",
    "addr:street":"Thornthwaite Close;Rednal",
    "iso:country":"GB",
    "sg:address":"Thornthwaite Close, Rubery, Rednal",
    "sg:city":"Birmingham",
    "sg:classifiers":[
        {
            "category":"Education",
            "subcategory":"School",
            "type":"Public Place"
        }
    ],
    "sg:phone":"+44 121 453 8634",
    "sg:postcode":"B45 0DS",
    "sg:province":"West Midlands",
    "sg:tags":[
        "local",
        "authority"
    ],
    "wof:name":"The Beeches Infant & Nursery School",
    "wof:placetype":"venue"
},
  "geometry": {"coordinates":[-2.0067939758,52.4065132141],"type":"Point"}
}