{
  "type": "Feature",
  "properties": {
    "iso:country":"GB",
    "sg:address":"8 Congleton Road",
    "sg:city":"Stoke-on-trent",
    "sg:classifiers":[
        {
            "category":"Restaurant",
            "type":"Food & Drink"
        }
    ],
    "sg:phone":"+44 1782 775654",
    "sg:postcode":"ST7 1NE",
    "sg:province":"Cheshire",
    "wof:name":"Mrs B's Victorian Supper Rooms",
    "wof:placetype":"venue"
},
  "geometry": {"coordinates":[-2.257881,53.089432],"type":"Point"}
}