{
  "type": "Feature",
  "properties": {
    "addr:full":"Poplars Farm, Icknield Street, Beoley Redditch Warwickshire B98 9AP",
    "addr:postcode":"b98 9ap",
    "addr:street":"Icknield Street",
    "iso:country":"GB",
    "sg:address":"Poplars Farm, Icknield Street, Beoley",
    "sg:city":"Redditch",
    "sg:classifiers":[
        {
            "category":"Farming",
            "subcategory":"Livestock Farm",
            "type":"Manufacturing & Wholesale Goods"
        }
    ],
    "sg:phone":"+44 1527 62592",
    "sg:postcode":"B98 9AP",
    "sg:province":"Warwickshire",
    "sg:tags":[
        "others"
    ],
    "wof:name":"V Boffey & Son",
    "wof:placetype":"venue"
},
  "geometry": {"coordinates":[-1.906234026,52.3238983154],"type":"Point"}
}