{
  "type": "Feature",
  "properties": {
    "addr:full":"38 North Street Jarrow Tyne and Wear NE32 3PG",
    "addr:housenumber":"38",
    "addr:postcode":"ne32 3pg",
    "addr:street":"North Street",
    "iso:country":"GB",
    "sg:address":"38 North Street",
    "sg:city":"Jarrow",
    "sg:classifiers":[
        {
            "category":"Home & Garden",
            "subcategory":"Household Appliances",
            "type":"Retail Goods"
        }
    ],
    "sg:postcode":"NE32 3PG",
    "sg:province":"Tyne and Wear",
    "sg:tags":[
        "electrical"
    ],
    "wof:name":"C & K Appliances",
    "wof:placetype":"venue"
},
  "geometry": {"coordinates":[-1.4876439571,54.9824981689],"type":"Point"}
}