{
  "type": "Feature",
  "properties": {
    "addr:full":"Sovereign Enterprise Park, King William Street Salford Greater Manchester M5 2UP",
    "addr:postcode":"m5 2up",
    "addr:street":"King William Street",
    "iso:country":"GB",
    "sg:address":"Sovereign Enterprise Park, King William Street",
    "sg:city":"Salford",
    "sg:classifiers":[
        {
            "category":"Professional",
            "subcategory":"Engineering",
            "type":"Services"
        }
    ],
    "sg:phone":"+44 161 873 7311",
    "sg:postcode":"M5 2UP",
    "sg:province":"Greater Manchester",
    "sg:tags":[
        "electronic",
        "engineer"
    ],
    "wof:name":"McMillan & Co",
    "wof:placetype":"venue"
},
  "geometry": {"coordinates":[-2.2843,53.489731],"type":"Point"}
}