{
  "type": "Feature",
  "properties": {
    "iso:country":"GB",
    "sg:address":"4a Old Lodge Lane",
    "sg:city":"Purley",
    "sg:classifiers":[
        {
            "category":"Building & Trades",
            "subcategory":"Construction",
            "type":"Services"
        }
    ],
    "sg:phone":"+44 20 8660 3300",
    "sg:postcode":"CR8 4DE",
    "sg:province":"Surrey",
    "sg:tags":[
        "ceiling",
        "suspended",
        "contractor"
    ],
    "sg:website":"http://www.acoustilux.com",
    "wof:name":"Acoustilux Suspended Ceilings",
    "wof:placetype":"venue"
},
  "geometry": {"coordinates":[-0.1245979965,51.3307991028],"type":"Point"}
}