{
  "type": "Feature",
  "properties": {
    "addr:full":"1b Link Road, Carters Grn West Bromwich West Midlands B70 9QP",
    "addr:housenumber":"1b",
    "addr:postcode":"b70 9qp",
    "addr:street":"Link Road Carters Grn",
    "iso:country":"GB",
    "sg:address":"1b Link Road, Carters Grn",
    "sg:city":"West Bromwich",
    "sg:classifiers":[
        {
            "category":"Fast Food",
            "type":"Food & Drink"
        }
    ],
    "sg:phone":"+44 121 553 6772",
    "sg:postcode":"B70 9QP",
    "sg:province":"West Midlands",
    "sg:tags":[
        "away",
        "take"
    ],
    "wof:name":"Burger King",
    "wof:placetype":"venue"
},
  "geometry": {"coordinates":[-2.0043699741,52.5244903564],"type":"Point"}
}