{
  "type": "Feature",
  "properties": {
    "iso:country":"GB",
    "sg:address":"Milligans Yard, Westgate",
    "sg:city":"Otley",
    "sg:classifiers":[
        {
            "category":"Retail",
            "subcategory":"Auto Repair",
            "type":"Services"
        }
    ],
    "sg:postcode":"LS21 3AS",
    "sg:province":"North Yorkshire",
    "sg:tags":[
        "body",
        "car"
    ],
    "wof:name":"Howard Hughes Body Shop",
    "wof:placetype":"venue"
},
  "geometry": {"coordinates":[-1.694953,53.90572],"type":"Point"}
}