{
  "type": "Feature",
  "properties": {
    "iso:country":"GB",
    "sg:address":"P O Box 31",
    "sg:city":"Borehamwood",
    "sg:classifiers":[
        {
            "category":"Shopping",
            "subcategory":"Catalog Store",
            "type":"Retail Goods"
        }
    ],
    "sg:phone":"+44 20 8207 5919",
    "sg:postcode":"WD6 3TF",
    "sg:province":"Hertfordshire",
    "sg:tags":[
        "mail",
        "order"
    ],
    "wof:name":"Camisa Direct",
    "wof:placetype":"venue"
},
  "geometry": {"coordinates":[-0.298539,51.644291],"type":"Point"}
}