{
  "type": "Feature",
  "properties": {
    "addr:full":"Station Road North Great Yarmouth Norfolk NR31 9NF",
    "addr:postcode":"nr31 9nf",
    "addr:street":"Station Road North Great",
    "iso:country":"GB",
    "sg:address":"Station Road North",
    "sg:city":"Great Yarmouth",
    "sg:classifiers":[
        {
            "category":"Shopping",
            "subcategory":"Department Store",
            "type":"Retail Goods"
        }
    ],
    "sg:phone":"+44 1493 780242",
    "sg:postcode":"NR31 9NF",
    "sg:province":"Norfolk",
    "wof:name":"Berrys Of Belton",
    "wof:placetype":"venue"
},
  "geometry": {"coordinates":[1.654663,52.570412],"type":"Point"}
}