{
  "type": "Feature",
  "properties": {
    "addr:full":"11 Leys Avenue Letchworth Hertfordshire SG6 3EA",
    "addr:housenumber":"11",
    "addr:postcode":"sg6 3ea",
    "addr:street":"Leys Avenue Letchworth",
    "iso:country":"GB",
    "sg:address":"11 Leys Avenue",
    "sg:city":"Letchworth",
    "sg:classifiers":[
        {
            "category":"Food & Beverages",
            "subcategory":"Specialty",
            "type":"Retail Goods"
        }
    ],
    "sg:phone":"+44 1462 678289",
    "sg:postcode":"SG6 3EA",
    "sg:province":"Hertfordshire",
    "sg:tags":[
        "product",
        "health"
    ],
    "wof:name":"Holland & Barrett",
    "wof:placetype":"venue"
},
  "geometry": {"coordinates":[-0.227158,51.979034],"type":"Point"}
}