{
  "type": "Feature",
  "properties": {
    "addr:full":"288 Gloucester Road, Horfield Bristol City of Bristol BS7 8PD",
    "addr:housenumber":"288",
    "addr:postcode":"bs7 8pd",
    "addr:street":"Gloucester Road",
    "iso:country":"GB",
    "sg:address":"288 Gloucester Road, Horfield",
    "sg:city":"Bristol",
    "sg:classifiers":[
        {
            "category":"Banks & Credit Unions",
            "subcategory":"Bank",
            "type":"Services"
        },
        {
            "category":"Banks & Credit Unions",
            "subcategory":"Financial Services",
            "type":"Services"
        }
    ],
    "sg:phone":"+44 117 942 6611",
    "sg:postcode":"BS7 8PD",
    "sg:province":"City of Bristol",
    "sg:tags":[
        "adviser",
        "broker",
        "mortgage"
    ],
    "wof:name":"Grosvenor Consultancy Ltd.",
    "wof:placetype":"venue"
},
  "geometry": {"coordinates":[-2.5882360935,51.4814033508],"type":"Point"}
}