{
  "type": "Feature",
  "properties": {
    "addr:full":"Thorning Farm, Marros, Pendine Carmarthen Carmarthenshire SA33 4PN",
    "addr:postcode":"sa33 4pn",
    "addr:street":"Pendine;Carmarthenshire",
    "iso:country":"GB",
    "sg:address":"Thorning Farm, Marros, Pendine",
    "sg:city":"Carmarthen",
    "sg:classifiers":[
        {
            "category":"Home & Garden",
            "subcategory":"Garden Supply",
            "type":"Retail Goods"
        }
    ],
    "sg:phone":"+44 1994 453475",
    "sg:postcode":"SA33 4PN",
    "sg:province":"Carmarthenshire",
    "sg:tags":[
        "turfing"
    ],
    "wof:name":"Pendine Turf",
    "wof:placetype":"venue"
},
  "geometry": {"coordinates":[-4.6001200676,51.7464103699],"type":"Point"}
}