{
  "type": "Feature",
  "properties": {
    "addr:full":"3 Clearmount Burrow Hill, Chobham Woking Surrey GU24 8TP",
    "addr:housenumber":"3",
    "addr:postcode":"gu24 8tp",
    "addr:street":"Clearmount Burrow Hill",
    "iso:country":"GB",
    "sg:address":"3 Clearmount Burrow Hill, Chobham",
    "sg:city":"Woking",
    "sg:classifiers":[
        {
            "category":"Building & Trades",
            "subcategory":"Construction",
            "type":"Services"
        }
    ],
    "sg:phone":"+44 1276 858865",
    "sg:postcode":"GU24 8TP",
    "sg:province":"Surrey",
    "sg:tags":[
        "decorator",
        "painter"
    ],
    "wof:name":"T.H Spong",
    "wof:placetype":"venue"
},
  "geometry": {"coordinates":[-0.6061800122,51.3536567688],"type":"Point"}
}