{
  "type": "Feature",
  "properties": {
    "addr:full":"66 Newstead Avenue Orpington Kent BR6 9RN",
    "addr:housenumber":"66",
    "addr:postcode":"br6 9rn",
    "addr:street":"Newstead Avenue",
    "iso:country":"GB",
    "sg:address":"66 Newstead Avenue",
    "sg:city":"Orpington",
    "sg:classifiers":[
        {
            "category":"Health Services",
            "subcategory":"Health Practitioner",
            "type":"Services"
        }
    ],
    "sg:phone":"+44 1689 898787",
    "sg:postcode":"BR6 9RN",
    "sg:province":"Kent",
    "sg:tags":[
        "homoeopathic"
    ],
    "wof:name":"Sandra Baker",
    "wof:placetype":"venue"
},
  "geometry": {"coordinates":[0.0813300014,51.3697662354],"type":"Point"}
}