{
  "type": "Feature",
  "properties": {
    "addr:full":"40 Market Place, Bolsover Chesterfield Derbyshire S44 6PN",
    "addr:housenumber":"40",
    "addr:postcode":"s44 6pn",
    "addr:street":"Market Place",
    "iso:country":"GB",
    "sg:address":"40 Market Place, Bolsover",
    "sg:city":"Chesterfield",
    "sg:classifiers":[
        {
            "category":"Food & Beverages",
            "subcategory":"Meat & Fish",
            "type":"Retail Goods"
        }
    ],
    "sg:phone":"+44 1246 240279",
    "sg:postcode":"S44 6PN",
    "sg:province":"Derbyshire",
    "sg:tags":[
        "butcher"
    ],
    "wof:name":"Elliott Meats",
    "wof:placetype":"venue"
},
  "geometry": {"coordinates":[-1.292319,53.22934],"type":"Point"}
}