{
  "type": "Feature",
  "properties": {
    "iso:country":"GB",
    "sg:address":"17 Fowlds Street",
    "sg:city":"Kilmarnock",
    "sg:classifiers":[
        {
            "category":"Bars & Pubs",
            "type":"Food & Drink"
        }
    ],
    "sg:phone":"+44 1563 572946",
    "sg:postcode":"KA1 3DG",
    "sg:province":"East Ayrshire",
    "sg:tags":[
        "pubs",
        "inn"
    ],
    "wof:name":"Gordons Lounge Bar",
    "wof:placetype":"venue"
},
  "geometry": {"coordinates":[-4.497095108,55.606678009],"type":"Point"}
}