{
  "type": "Feature",
  "properties": {
    "addr:full":"Keighley Railway Stn, Station Bridge Keighley West Yorkshire BD21 4HP",
    "addr:postcode":"bd21 4hp",
    "addr:street":"Keighley Railway Stn Station Bridge",
    "iso:country":"GB",
    "sg:address":"Keighley Railway Stn, Station Bridge",
    "sg:city":"Keighley",
    "sg:classifiers":[
        {
            "category":"Professional",
            "type":"Services"
        },
        {
            "category":"Personal",
            "type":"Services"
        }
    ],
    "sg:phone":"+44 1535 600216",
    "sg:postcode":"BD21 4HP",
    "sg:province":"West Yorkshire",
    "sg:tags":[
        "delivery",
        "good"
    ],
    "wof:name":"Red Star Parcels Ltd",
    "wof:placetype":"venue"
},
  "geometry": {"coordinates":[-1.909674,53.866364],"type":"Point"}
}