{
  "type": "Feature",
  "properties": {
    "addr:full":"17 Sadler Gate Derby Derbyshire DE1 3NH",
    "addr:housenumber":"17",
    "addr:postcode":"de1 3nh",
    "addr:street":"Sadler Gate",
    "iso:country":"GB",
    "sg:address":"17 Sadler Gate",
    "sg:city":"Derby",
    "sg:classifiers":[
        {
            "category":"Professional",
            "subcategory":"Business Services",
            "type":"Services"
        },
        {
            "category":"Wholesale",
            "subcategory":"Photographic Equipment",
            "type":"Manufacturing & Wholesale Goods"
        },
        {
            "category":"Shopping",
            "subcategory":"Photographic Equipment",
            "type":"Retail Goods"
        }
    ],
    "sg:phone":"+44 1332 348644",
    "sg:postcode":"DE1 3NH",
    "sg:province":"Derbyshire",
    "sg:tags":[
        "holding",
        "supply"
    ],
    "wof:name":"London Camera Exchange Ltd",
    "wof:placetype":"venue"
},
  "geometry": {"coordinates":[-1.4786510468,52.9233856201],"type":"Point"}
}