{
  "type": "Feature",
  "properties": {
    "iso:country":"GB",
    "sg:address":"Bridgeway",
    "sg:city":"St Leonards-on-sea",
    "sg:classifiers":[
        {
            "category":"Manufacturing",
            "subcategory":"Metals",
            "type":"Manufacturing & Wholesale Goods"
        },
        {
            "category":"Government",
            "subcategory":"Office",
            "type":"Public Place"
        }
    ],
    "sg:phone":"+44 1424 444888",
    "sg:postcode":"TN38 8AP",
    "sg:province":"East Sussex",
    "sg:tags":[
        "steel",
        "local",
        "stockholder"
    ],
    "wof:name":"Rother Steel Services Ltd.",
    "wof:placetype":"venue"
},
  "geometry": {"coordinates":[0.519345,50.848976],"type":"Point"}
}