{
  "type": "Feature",
  "properties": {
    "iso:country":"GB",
    "sg:address":"6 Queen's Crescent",
    "sg:city":"Edinburgh",
    "sg:classifiers":[
        {
            "category":"Communications",
            "subcategory":"Film & Video Production",
            "type":"Services"
        }
    ],
    "sg:phone":"+44 131 662 1983",
    "sg:postcode":"EH9 2AZ",
    "sg:province":"City of Edinburgh",
    "sg:tags":[
        "illustrator",
        "artist"
    ],
    "wof:name":"Arkitekt",
    "wof:placetype":"venue"
},
  "geometry": {"coordinates":[-3.1859738827,55.947555542],"type":"Point"}
}