{
  "type": "Feature",
  "properties": {
    "iso:country":"GB",
    "sg:address":"5 Wharfedale Cres",
    "sg:city":"Leeds",
    "sg:classifiers":[
        {
            "category":"Professional",
            "subcategory":"Advertising",
            "type":"Services"
        }
    ],
    "sg:phone":"+44 113 286 2560",
    "sg:postcode":"LS25 1LD",
    "sg:province":"North Yorkshire",
    "wof:name":"Vernon Wood Associates",
    "wof:placetype":"venue"
},
  "geometry": {"coordinates":[-1.3838449717,53.7884407043],"type":"Point"}
}