{
  "type": "Feature",
  "properties": {
    "iso:country":"GB",
    "sg:address":"63 Main Road, Fenwick",
    "sg:city":"Kilmarnock",
    "sg:classifiers":[
        {
            "category":"Shopping",
            "subcategory":"Computers & Home Electronics",
            "type":"Retail Goods"
        }
    ],
    "sg:phone":"+44 1560 600800",
    "sg:postcode":"KA3 6DU",
    "sg:province":"East Ayrshire",
    "wof:name":"David Lewis Designs",
    "wof:placetype":"venue"
},
  "geometry": {"coordinates":[-4.445325,55.659622],"type":"Point"}
}