{
  "type": "Feature",
  "properties": {
    "iso:country":"GB",
    "sg:address":"9-11 Market Street",
    "sg:city":"Alton",
    "sg:classifiers":[
        {
            "category":"Fast Food",
            "type":"Food & Drink"
        }
    ],
    "sg:phone":"+44 1420 549086",
    "sg:postcode":"GU34 1HA",
    "sg:province":"Hampshire",
    "sg:tags":[
        "away",
        "take"
    ],
    "wof:name":"Balti House",
    "wof:placetype":"venue"
},
  "geometry": {"coordinates":[-0.976465,51.148796],"type":"Point"}
}