{
  "type": "Feature",
  "properties": {
    "iso:country":"GB",
    "sg:address":"9 The Georgian Village, 30-31 Islington Green",
    "sg:city":"Islington",
    "sg:classifiers":[
        {
            "category":"Shopping",
            "subcategory":"Antiques",
            "type":"Retail Goods"
        }
    ],
    "sg:phone":"+44 20 7226 9907",
    "sg:postcode":"N1 8NR",
    "sg:province":"Greater London",
    "wof:name":"Pottle Sue",
    "wof:placetype":"venue"
},
  "geometry": {"coordinates":[-0.10286,51.53587],"type":"Point"}
}