{
  "type": "Feature",
  "properties": {
    "addr:full":"121 High Street Forres Moray IV36 1AB",
    "addr:housenumber":"121",
    "addr:postcode":"iv36 1ab",
    "addr:street":"High Street",
    "iso:country":"GB",
    "sg:address":"121 High Street",
    "sg:city":"Forres",
    "sg:classifiers":[
        {
            "category":"Education",
            "subcategory":"School",
            "type":"Public Place"
        },
        {
            "category":"Government",
            "subcategory":"Office",
            "type":"Public Place"
        }
    ],
    "sg:phone":"+44 1309 672887",
    "sg:postcode":"IV36 1AB",
    "sg:province":"Moray",
    "sg:tags":[
        "local",
        "authority"
    ],
    "wof:name":"Moray Chamber of Commerce",
    "wof:placetype":"venue"
},
  "geometry": {"coordinates":[-3.6141269207,57.6097221375],"type":"Point"}
}