{
  "type": "Feature",
  "properties": {
    "iso:country":"GB",
    "sg:address":"9 Yew Tree Drive, Bovingdon",
    "sg:city":"Hemel Hempstead",
    "sg:classifiers":[
        {
            "category":"Professional",
            "subcategory":"Management & Consulting",
            "type":"Services"
        }
    ],
    "sg:phone":"+44 1442 834613",
    "sg:postcode":"HP3 0TA",
    "sg:province":"Hertfordshire",
    "sg:tags":[
        "consultant",
        "transport"
    ],
    "wof:name":"Jay Services",
    "wof:placetype":"venue"
},
  "geometry": {"coordinates":[-0.528958,51.720894],"type":"Point"}
}