{
  "type": "Feature",
  "properties": {
    "iso:country":"GB",
    "sg:address":"23 Castle Street",
    "sg:city":"Bishops Stortford",
    "sg:classifiers":[
        {
            "category":"Retail",
            "subcategory":"Photofinishing",
            "type":"Services"
        },
        {
            "category":"Retail",
            "subcategory":"Portrait Studio",
            "type":"Services"
        }
    ],
    "sg:phone":"+44 1279 654723",
    "sg:postcode":"CM23 3TG",
    "sg:province":"Essex",
    "sg:tags":[
        "photographic",
        "photographer",
        "commercial",
        "processor"
    ],
    "wof:name":"Images",
    "wof:placetype":"venue"
},
  "geometry": {"coordinates":[0.1592029929,51.8672027588],"type":"Point"}
}