{
  "type": "Feature",
  "properties": {
    "iso:country":"GB",
    "sg:address":"8a South Road",
    "sg:city":"Southall",
    "sg:classifiers":[
        {
            "category":"Professional",
            "subcategory":"Lawyer & Legal Services",
            "type":"Services"
        }
    ],
    "sg:phone":"+44 20 8571 6001",
    "sg:postcode":"UB1 1RT",
    "sg:province":"Greater London",
    "sg:tags":[
        "conveyancing",
        "solicitor"
    ],
    "wof:name":"David Shine & Satish Karbanda",
    "wof:placetype":"venue"
},
  "geometry": {"coordinates":[-0.3759059906,51.5108375549],"type":"Point"}
}