{
  "type": "Feature",
  "properties": {
    "iso:country":"GB",
    "sg:address":"19 Broad St, Brinklow",
    "sg:city":"Rugby",
    "sg:classifiers":[
        {
            "category":"Shopping",
            "subcategory":"Antiques",
            "type":"Retail Goods"
        }
    ],
    "sg:phone":"+44 1788 832673",
    "sg:postcode":"CV23 0LS",
    "sg:province":"Northamptonshire",
    "wof:name":"Cottage Pine",
    "wof:placetype":"venue"
},
  "geometry": {"coordinates":[-1.362331,52.41016],"type":"Point"}
}