{
  "type": "Feature",
  "properties": {
    "iso:country":"GB",
    "sg:address":"139 Walmley Road",
    "sg:city":"Sutton Coldfield",
    "sg:classifiers":[
        {
            "category":"Home & Garden",
            "subcategory":"Carpets & Floor Coverings",
            "type":"Retail Goods"
        }
    ],
    "sg:postcode":"B76 1QL",
    "sg:province":"Warwickshire",
    "sg:tags":[
        "cleaner",
        "upholstery"
    ],
    "wof:name":"Safeclean (West Midlands) Ltd.",
    "wof:placetype":"venue"
},
  "geometry": {"coordinates":[-1.7990560532,52.5458641052],"type":"Point"}
}