{
  "type": "Feature",
  "properties": {
    "addr:full":"4 Marlingford Rd, Easton Norwich Norfolk NR9 5AD",
    "addr:housenumber":"4",
    "addr:postcode":"nr9 5ad",
    "addr:street":"Marlingford Rd;Norwich Norfolk",
    "iso:country":"GB",
    "sg:address":"4 Marlingford Rd, Easton",
    "sg:city":"Norwich",
    "sg:classifiers":[
        {
            "category":"Government",
            "subcategory":"Post Office",
            "type":"Public Place"
        }
    ],
    "sg:phone":"+44 1603 880850",
    "sg:postcode":"NR9 5AD",
    "sg:province":"Norfolk",
    "wof:name":"Easton Post Office Stores",
    "wof:placetype":"venue"
},
  "geometry": {"coordinates":[1.1552250385,52.6536064148],"type":"Point"}
}