{
  "type": "Feature",
  "properties": {
    "addr:full":"Park Lane, Harefield Uxbridge Buckinghamshire UB9 6BJ",
    "addr:postcode":"ub9 6bj",
    "addr:street":"Park Lane",
    "iso:country":"GB",
    "sg:address":"Park Lane, Harefield",
    "sg:city":"Uxbridge",
    "sg:classifiers":[
        {
            "category":"Education",
            "subcategory":"Library",
            "type":"Public Place"
        },
        {
            "category":"Government",
            "subcategory":"Office",
            "type":"Public Place"
        }
    ],
    "sg:phone":"+44 1895 822171",
    "sg:postcode":"UB9 6BJ",
    "sg:province":"Buckinghamshire",
    "sg:tags":[
        "book",
        "local"
    ],
    "wof:name":"Harefield Library",
    "wof:placetype":"venue"
},
  "geometry": {"coordinates":[-0.4820719957,51.604019165],"type":"Point"}
}