{
  "type": "Feature",
  "properties": {
    "addr:full":"Dorner House, Hammersley Lane, Penn High Wycombe Buckinghamshire HP10 8HF",
    "addr:postcode":"hp10 8hf",
    "addr:street":"Hammersley Lane",
    "iso:country":"GB",
    "sg:address":"Dorner House, Hammersley Lane, Penn",
    "sg:city":"High Wycombe",
    "sg:classifiers":[
        {
            "category":"Real Estate",
            "subcategory":"Architect",
            "type":"Services"
        }
    ],
    "sg:phone":"+44 1372 270900",
    "sg:postcode":"HP10 8HF",
    "sg:province":"Buckinghamshire",
    "sg:tags":[
        "architectural"
    ],
    "wof:name":"Woodiwiss & Martin",
    "wof:placetype":"venue"
},
  "geometry": {"coordinates":[-0.695587,51.634968],"type":"Point"}
}