{
  "type": "Feature",
  "properties": {
    "iso:country":"GB",
    "sg:address":"23 Bowrons Ave",
    "sg:city":"Wembley",
    "sg:classifiers":[
        {
            "category":"Shopping",
            "subcategory":"Clothing, Apparel, & Fashions",
            "type":"Retail Goods"
        }
    ],
    "sg:postcode":"HA0 4QS",
    "sg:province":"Greater London",
    "sg:tags":[
        "ladieswear"
    ],
    "wof:name":"Kris Ltd",
    "wof:placetype":"venue"
},
  "geometry": {"coordinates":[-0.2985599935,51.5448074341],"type":"Point"}
}