{
  "type": "Feature",
  "properties": {
    "iso:country":"GB",
    "sg:address":"Furniture Factors, Off York Road, Arkwright Road",
    "sg:city":"Doncaster",
    "sg:classifiers":[
        {
            "category":"Home & Garden",
            "subcategory":"Carpets & Floor Coverings",
            "type":"Retail Goods"
        }
    ],
    "sg:phone":"+44 1302 781727",
    "sg:postcode":"DN5 8PT",
    "sg:province":"South Yorkshire",
    "sg:tags":[
        "carpets",
        "rug",
        "matting"
    ],
    "wof:name":"S & D Carpets",
    "wof:placetype":"venue"
},
  "geometry": {"coordinates":[-1.1592400074,53.5315704346],"type":"Point"}
}