{
  "type": "Feature",
  "properties": {
    "iso:country":"GB",
    "sg:address":"Hallwood Hospital Health Centre",
    "sg:city":"Runcorn",
    "sg:classifiers":[
        {
            "category":"Shopping",
            "subcategory":"Pharmacy",
            "type":"Retail Goods"
        }
    ],
    "sg:phone":"+44 1928 719088",
    "sg:postcode":"WA7 2UT",
    "sg:province":"Cheshire",
    "sg:tags":[
        "pharmacist",
        "chemist"
    ],
    "wof:name":"Boots the Chemists Ltd.",
    "wof:placetype":"venue"
},
  "geometry": {"coordinates":[-2.702632,53.320744],"type":"Point"}
}