{
  "type": "Feature",
  "properties": {
    "addr:full":"Kiosk 1 Eastgate Shopp Centre, Southernhay Basildon Essex SS14 1EB",
    "addr:housenumber":"1",
    "addr:postcode":"ss14 1eb",
    "addr:street":"Eastgate Shopp Centre Southernhay",
    "iso:country":"GB",
    "sg:address":"Kiosk 1 Eastgate Shopp Centre, Southernhay",
    "sg:city":"Basildon",
    "sg:classifiers":[
        {
            "category":"Fast Food",
            "type":"Food & Drink"
        }
    ],
    "sg:postcode":"SS14 1EB",
    "sg:province":"Essex",
    "sg:tags":[
        "away",
        "take"
    ],
    "wof:name":"Hendersons Catering",
    "wof:placetype":"venue"
},
  "geometry": {"coordinates":[0.4614900053,51.5698204041],"type":"Point"}
}