{
  "type": "Feature",
  "properties": {
    "addr:full":"229 Derby Road, Spondon Derby Derbyshire DE21 7LW",
    "addr:housenumber":"229",
    "addr:postcode":"de21 7lw",
    "addr:street":"Derby Road",
    "iso:country":"GB",
    "sg:address":"229 Derby Road, Spondon",
    "sg:city":"Derby",
    "sg:classifiers":[
        {
            "category":"Bus Charters",
            "type":"Transportation"
        }
    ],
    "sg:phone":"+44 1332 721232",
    "sg:postcode":"DE21 7LW",
    "sg:province":"Derbyshire",
    "sg:tags":[
        "mini",
        "hire",
        "leasing"
    ],
    "wof:name":"Direct Airport Services",
    "wof:placetype":"venue"
},
  "geometry": {"coordinates":[-1.4219590425,52.918510437],"type":"Point"}
}