{
  "type": "Feature",
  "properties": {
    "addr:full":"15 Anchor Rd Walsall Staffordshire WS9 8PT",
    "addr:housenumber":"15",
    "addr:postcode":"ws9 8pt",
    "addr:street":"Anchor Rd",
    "iso:country":"GB",
    "sg:address":"15 Anchor Rd",
    "sg:city":"Walsall",
    "sg:classifiers":[
        {
            "category":"Home & Garden",
            "subcategory":"Household Appliances",
            "type":"Retail Goods"
        }
    ],
    "sg:postcode":"WS9 8PT",
    "sg:province":"Staffordshire",
    "sg:tags":[
        "electrical",
        "domestic"
    ],
    "wof:name":"Antika Retail Ltd",
    "wof:placetype":"venue"
},
  "geometry": {"coordinates":[-1.919462,52.603291],"type":"Point"}
}