{
  "type": "Feature",
  "properties": {
    "addr:full":"Moor Lane Weston-super-mare Somerset BS24 7LA",
    "addr:postcode":"bs24 7la",
    "addr:street":"Moor Lane",
    "iso:country":"GB",
    "sg:address":"Moor Lane",
    "sg:city":"Weston-super-mare",
    "sg:classifiers":[
        {
            "category":"Travel",
            "subcategory":"Hotels & Motels",
            "type":"Entertainment"
        }
    ],
    "sg:postcode":"BS24 7LA",
    "sg:province":"Somerset",
    "sg:tags":[
        "self",
        "catering"
    ],
    "wof:name":"Airport View Caravan Park",
    "wof:placetype":"venue"
},
  "geometry": {"coordinates":[-2.9313440323,51.3456687927],"type":"Point"}
}