{
  "type": "Feature",
  "properties": {
    "iso:country":"GB",
    "sg:address":"Millers Road",
    "sg:city":"Warwick",
    "sg:classifiers":[
        {
            "category":"Building & Trades",
            "subcategory":"Equipment Rental",
            "type":"Services"
        }
    ],
    "sg:postcode":"CV34 5AN",
    "sg:province":"Warwickshire",
    "sg:tags":[
        "hire",
        "centre"
    ],
    "wof:name":"Plantool Hire & Sales",
    "wof:placetype":"venue"
},
  "geometry": {"coordinates":[-1.59104,52.290745],"type":"Point"}
}