{
  "type": "Feature",
  "properties": {
    "addr:full":"42 Laverockbank Road Edinburgh City of Edinburgh EH5 3BZ",
    "addr:housenumber":"42",
    "addr:postcode":"eh5 3bz",
    "addr:street":"Laverockbank Road",
    "iso:country":"GB",
    "sg:address":"42 Laverockbank Road",
    "sg:city":"Edinburgh",
    "sg:classifiers":[
        {
            "category":"Travel",
            "subcategory":"Hotels & Motels",
            "type":"Entertainment"
        }
    ],
    "sg:phone":"+44 131 552 4866",
    "sg:postcode":"EH5 3BZ",
    "sg:province":"City of Edinburgh",
    "sg:tags":[
        "house",
        "guest"
    ],
    "wof:name":"Rose Villa",
    "wof:placetype":"venue"
},
  "geometry": {"coordinates":[-3.201668,55.97868],"type":"Point"}
}