{
  "type": "Feature",
  "properties": {
    "addr:full":"60 Grange Rd Durham Durham DH1 1AL",
    "addr:housenumber":"60",
    "addr:postcode":"dh1 1al",
    "addr:street":"Grange Rd",
    "iso:country":"GB",
    "sg:address":"60 Grange Rd",
    "sg:city":"Durham",
    "sg:classifiers":[
        {
            "category":"Building & Trades",
            "subcategory":"Construction",
            "type":"Services"
        }
    ],
    "sg:phone":"+44 1740 620734",
    "sg:postcode":"DH1 1AL",
    "sg:province":"Durham",
    "sg:tags":[
        "joiner",
        "carpenter"
    ],
    "wof:name":"Carville Windows & Cladding Services",
    "wof:placetype":"venue"
},
  "geometry": {"coordinates":[-1.528871,54.789684],"type":"Point"}
}