{
  "type": "Feature",
  "properties": {
    "addr:full":"Fairgardens, Plant Centre, Stn Rd, Kirton Lindsey Gainsborough Lincolnshire DN21 4JR",
    "addr:postcode":"dn21 4jr",
    "addr:street":"Stn Rd",
    "iso:country":"GB",
    "sg:address":"Fairgardens, Plant Centre, Stn Rd, Kirton Lindsey",
    "sg:city":"Gainsborough",
    "sg:classifiers":[
        {
            "category":"Home & Garden",
            "subcategory":"Garden Supply",
            "type":"Retail Goods"
        }
    ],
    "sg:postcode":"DN21 4JR",
    "sg:province":"Lincolnshire",
    "sg:tags":[
        "flower",
        "shrub"
    ],
    "wof:name":"Flowerjoy",
    "wof:placetype":"venue"
},
  "geometry": {"coordinates":[-0.587453,53.475845],"type":"Point"}
}