{
  "type": "Feature",
  "properties": {
    "addr:full":"71 Greencroft Street Salisbury Wiltshire SP1 1JF",
    "addr:housenumber":"71",
    "addr:postcode":"sp1 1jf",
    "addr:street":"Greencroft Street",
    "iso:country":"GB",
    "sg:address":"71 Greencroft Street",
    "sg:city":"Salisbury",
    "sg:classifiers":[
        {
            "category":"Bars & Pubs",
            "type":"Food & Drink"
        }
    ],
    "sg:postcode":"SP1 1JF",
    "sg:province":"Wiltshire",
    "sg:tags":[
        "pubs",
        "inn"
    ],
    "wof:name":"The Barley Mow",
    "wof:placetype":"venue"
},
  "geometry": {"coordinates":[-1.7912089825,51.0711784363],"type":"Point"}
}