{
  "type": "Feature",
  "properties": {
    "addr:full":"145 St Margarets Road Twickenham Greater London TW1 1RG",
    "addr:housenumber":"145",
    "addr:postcode":"tw1 1rg",
    "addr:street":"St Margarets Road",
    "iso:country":"GB",
    "sg:address":"145 St Margarets Road",
    "sg:city":"Twickenham",
    "sg:classifiers":[
        {
            "category":"Manufacturing",
            "subcategory":"Tools & Machinery",
            "type":"Manufacturing & Wholesale Goods"
        }
    ],
    "sg:phone":"+44 20 8560 1111",
    "sg:postcode":"TW1 1RG",
    "sg:province":"Greater London",
    "sg:tags":[
        "society",
        "friendly"
    ],
    "wof:name":"McGinn & Associates Ltd.",
    "wof:placetype":"venue"
},
  "geometry": {"coordinates":[-0.3210099936,51.4560089111],"type":"Point"}
}