{
  "type": "Feature",
  "properties": {
    "iso:country":"GB",
    "sg:address":"12 Buckmore Avenue",
    "sg:city":"Petersfield",
    "sg:classifiers":[
        {
            "category":"Shopping",
            "subcategory":"Party Supplies",
            "type":"Retail Goods"
        }
    ],
    "sg:postcode":"GU32 2EG",
    "sg:province":"Hampshire",
    "sg:tags":[
        "inflatables",
        "bouncy",
        "castle"
    ],
    "wof:name":"Crooked Cottage Castles",
    "wof:placetype":"venue"
},
  "geometry": {"coordinates":[-0.947144,51.010162],"type":"Point"}
}