{
  "type": "Feature",
  "properties": {
    "addr:full":"206 Great Bridge Street West Bromwich West Midlands B70 0BZ",
    "addr:housenumber":"206",
    "addr:postcode":"b70 0bz",
    "addr:street":"Great Bridge Street",
    "iso:country":"GB",
    "sg:address":"206 Great Bridge Street",
    "sg:city":"West Bromwich",
    "sg:classifiers":[
        {
            "category":"Manufacturing",
            "subcategory":"Rubber & Plastics",
            "type":"Manufacturing & Wholesale Goods"
        }
    ],
    "sg:phone":"+44 121 557 0585",
    "sg:postcode":"B70 0BZ",
    "sg:province":"West Midlands",
    "sg:tags":[
        "injection",
        "moulding"
    ],
    "wof:name":"Thurlestone Engineering Ltd.",
    "wof:placetype":"venue"
},
  "geometry": {"coordinates":[-2.0252180099,52.5284576416],"type":"Point"}
}