{
  "type": "Feature",
  "properties": {
    "iso:country":"GB",
    "sg:address":"First Floor St Swithins House, Trinity Street",
    "sg:city":"Worcester",
    "sg:classifiers":[
        {
            "category":"Professional",
            "subcategory":"Employment Agencies",
            "type":"Services"
        }
    ],
    "sg:postcode":"WR1 2PW",
    "sg:province":"Worcestershire",
    "sg:tags":[
        "consultant"
    ],
    "wof:name":"Select Recruitment Services",
    "wof:placetype":"venue"
},
  "geometry": {"coordinates":[-2.220114,52.19355],"type":"Point"}
}