{
  "type": "Feature",
  "properties": {
    "iso:country":"GB",
    "sg:address":"Elizabeth Ho, 1554 Ashton Old Rd",
    "sg:city":"Manchester",
    "sg:classifiers":[
        {
            "category":"Building & Trades",
            "subcategory":"Construction",
            "type":"Services"
        }
    ],
    "sg:phone":"+44 161 301 1060",
    "sg:postcode":"M11 1HW",
    "sg:province":"Greater Manchester",
    "sg:tags":[
        "joinery"
    ],
    "wof:name":"Maurame Ltd",
    "wof:placetype":"venue"
},
  "geometry": {"coordinates":[-2.2488100529,53.4796218872],"type":"Point"}
}