{
  "type": "Feature",
  "properties": {
    "addr:full":"Hop Gardens Haverfordwest Pembrokeshire SA62 4ES",
    "addr:postcode":"sa62 4es",
    "addr:street":"Hop Gardens",
    "iso:country":"GB",
    "sg:address":"Hop Gardens",
    "sg:city":"Haverfordwest",
    "sg:classifiers":[
        {
            "category":"Building & Trades",
            "subcategory":"Cleaning & Sanitation",
            "type":"Services"
        }
    ],
    "sg:phone":"+44 1437 765374",
    "sg:postcode":"SA62 4ES",
    "sg:province":"Pembrokeshire",
    "sg:tags":[
        "commercial"
    ],
    "wof:name":"C G Pearce",
    "wof:placetype":"venue"
},
  "geometry": {"coordinates":[-4.9468398094,51.7846908569],"type":"Point"}
}