{
  "type": "Feature",
  "properties": {
    "addr:full":"1 Queens Road Penarth The Vale of Glamorgan CF64 1DH",
    "addr:housenumber":"1",
    "addr:postcode":"cf64 1dh",
    "addr:street":"Queens Road;Vale",
    "iso:country":"GB",
    "sg:address":"1 Queens Road",
    "sg:city":"Penarth",
    "sg:classifiers":[
        {
            "category":"Bars & Pubs",
            "type":"Food & Drink"
        }
    ],
    "sg:phone":"+44 29 2025 6888",
    "sg:postcode":"CF64 1DH",
    "sg:province":"The Vale of Glamorgan",
    "sg:tags":[
        "pubs",
        "inn"
    ],
    "wof:name":"The Royal Hotel",
    "wof:placetype":"venue"
},
  "geometry": {"coordinates":[-3.175259,51.442848],"type":"Point"}
}