{
  "type": "Feature",
  "properties": {
    "addr:full":"Newbold Terrace East Leamington Spa Warwickshire CV32 4EU",
    "addr:postcode":"cv32 4eu",
    "addr:street":"Newbold Terrace East",
    "iso:country":"GB",
    "sg:address":"Newbold Terrace East",
    "sg:city":"Leamington Spa",
    "sg:classifiers":[
        {
            "category":"Bars & Pubs",
            "type":"Food & Drink"
        }
    ],
    "sg:phone":"+44 1926 338810",
    "sg:postcode":"CV32 4EU",
    "sg:province":"Warwickshire",
    "sg:tags":[
        "pubs",
        "inn"
    ],
    "wof:name":"Newbold Comyn Arms",
    "wof:placetype":"venue"
},
  "geometry": {"coordinates":[-1.522044,52.290661],"type":"Point"}
}