{
  "type": "Feature",
  "properties": {
    "addr:full":"164 Industry Street Sheffield South Yorkshire S6 2WX",
    "addr:housenumber":"164",
    "addr:postcode":"s6 2wx",
    "addr:street":"Industry Street",
    "iso:country":"GB",
    "sg:address":"164 Industry Street",
    "sg:city":"Sheffield",
    "sg:classifiers":[
        {
            "category":"Utilities",
            "type":"Services"
        }
    ],
    "sg:phone":"+44 114 221 2374",
    "sg:postcode":"S6 2WX",
    "sg:province":"South Yorkshire",
    "sg:tags":[
        "internet"
    ],
    "wof:name":"Cyberspace Web Services",
    "wof:placetype":"venue"
},
  "geometry": {"coordinates":[-1.4996320009,53.3932151794],"type":"Point"}
}