{
  "type": "Feature",
  "properties": {
    "iso:country":"GB",
    "sg:address":"59 South Parade, Speke",
    "sg:city":"Liverpool",
    "sg:classifiers":[
        {
            "category":"Food & Beverages",
            "subcategory":"Fruits & Vegetables",
            "type":"Retail Goods"
        }
    ],
    "sg:phone":"+44 151 475 0271",
    "sg:postcode":"L24 2SF",
    "sg:province":"Merseyside",
    "sg:tags":[
        "greengrocer"
    ],
    "wof:name":"Fruit Line",
    "wof:placetype":"venue"
},
  "geometry": {"coordinates":[-2.8396310806,53.3409614563],"type":"Point"}
}