{
  "type": "Feature",
  "properties": {
    "addr:full":"Knighton Factory, Knighton Stafford Staffordshire ST20 0QJ",
    "addr:postcode":"st20 0qj",
    "iso:country":"GB",
    "sg:address":"Knighton Factory, Knighton",
    "sg:city":"Stafford",
    "sg:classifiers":[
        {
            "category":"Food & Beverages",
            "subcategory":"Supermarket",
            "type":"Retail Goods"
        }
    ],
    "sg:phone":"+44 1785 280215",
    "sg:postcode":"ST20 0QJ",
    "sg:province":"Staffordshire",
    "sg:tags":[
        "frozen"
    ],
    "wof:name":"Premier Beverages",
    "wof:placetype":"venue"
},
  "geometry": {"coordinates":[-2.3761270046,52.8404388428],"type":"Point"}
}