{
  "type": "Feature",
  "properties": {
    "addr:full":"Burtons Yard, Weston Lane Totland Bay Isle of Wight PO39 0HE",
    "addr:postcode":"po39 0he",
    "addr:street":"Weston Lane",
    "iso:country":"GB",
    "sg:address":"Burtons Yard, Weston Lane",
    "sg:city":"Totland Bay",
    "sg:classifiers":[
        {
            "category":"Manufacturing",
            "subcategory":"Building Materials",
            "type":"Manufacturing & Wholesale Goods"
        }
    ],
    "sg:phone":"+44 1983 756655",
    "sg:postcode":"PO39 0HE",
    "sg:province":"Isle of Wight",
    "sg:tags":[
        "merchant",
        "builder"
    ],
    "wof:name":"R V N Building Supplies",
    "wof:placetype":"venue"
},
  "geometry": {"coordinates":[-1.5465209484,50.6787872314],"type":"Point"}
}