{
  "type": "Feature",
  "properties": {
    "addr:full":"19 Belvoir Street Leicester Leicestershire LE1 6SL",
    "addr:housenumber":"19",
    "addr:postcode":"le1 6sl",
    "addr:street":"Belvoir Street",
    "iso:country":"GB",
    "sg:address":"19 Belvoir Street",
    "sg:city":"Leicester",
    "sg:classifiers":[
        {
            "category":"Food & Beverages",
            "subcategory":"Specialty",
            "type":"Retail Goods"
        }
    ],
    "sg:postcode":"LE1 6SL",
    "sg:province":"Leicestershire",
    "sg:tags":[
        "vegetarian"
    ],
    "wof:name":"The Whole Truth Cafe",
    "wof:placetype":"venue"
},
  "geometry": {"coordinates":[-1.1307229996,52.6332855225],"type":"Point"}
}