{
  "type": "Feature",
  "properties": {
    "addr:full":"Kinness House, 35 Largo Road St Andrews Fife KY16 8NJ",
    "addr:housenumber":"35",
    "addr:postcode":"ky16 8nj",
    "addr:street":"Largo Road",
    "iso:country":"GB",
    "sg:address":"Kinness House, 35 Largo Road",
    "sg:city":"St Andrews",
    "sg:classifiers":[
        {
            "category":"Real Estate",
            "subcategory":"Developer",
            "type":"Services"
        }
    ],
    "sg:phone":"+44 1334 477913",
    "sg:postcode":"KY16 8NJ",
    "sg:province":"Fife",
    "sg:tags":[
        "property"
    ],
    "sg:website":"http://www.headon-dev.com",
    "wof:name":"Pollpledge Ltd",
    "wof:placetype":"venue"
},
  "geometry": {"coordinates":[-2.805498,56.33028],"type":"Point"}
}