{
  "type": "Feature",
  "properties": {
    "addr:full":"St. Stephens Ho, Arthur Rd Windsor Berkshire SL4 1RY",
    "addr:postcode":"sl4 1ry",
    "addr:street":"St.;Arthur Rd",
    "iso:country":"GB",
    "sg:address":"St. Stephens Ho, Arthur Rd",
    "sg:city":"Windsor",
    "sg:classifiers":[
        {
            "category":"Building & Trades",
            "subcategory":"Cleaning & Sanitation",
            "type":"Services"
        }
    ],
    "sg:postcode":"SL4 1RY",
    "sg:province":"Berkshire",
    "sg:tags":[
        "cleaner",
        "window"
    ],
    "wof:name":"Fenestra Clean",
    "wof:placetype":"venue"
},
  "geometry": {"coordinates":[-0.612228,51.481735],"type":"Point"}
}