{
  "type": "Feature",
  "properties": {
    "addr:full":"101 Main Road, Newport Brough East Riding of Yorkshire HU15 2QS",
    "addr:housenumber":"101",
    "addr:postcode":"hu15 2qs",
    "addr:street":"Main Road",
    "iso:country":"GB",
    "sg:address":"101 Main Road, Newport",
    "sg:city":"Brough",
    "sg:classifiers":[
        {
            "category":"Fast Food",
            "type":"Food & Drink"
        }
    ],
    "sg:phone":"+44 1430 440177",
    "sg:postcode":"HU15 2QS",
    "sg:province":"East Riding of Yorkshire",
    "sg:tags":[
        "away",
        "take"
    ],
    "wof:name":"Royal Fast Food",
    "wof:placetype":"venue"
},
  "geometry": {"coordinates":[-0.7014719844,53.762008667],"type":"Point"}
}