{
  "type": "Feature",
  "properties": {
    "addr:full":"Field Farm, Ringland Lane, Weston Longville Norwich Norfolk NR9 5JT",
    "addr:postcode":"nr9 5jt",
    "addr:street":"Ringland Lane",
    "iso:country":"GB",
    "sg:address":"Field Farm, Ringland Lane, Weston Longville",
    "sg:city":"Norwich",
    "sg:classifiers":[
        {
            "category":"Farming",
            "subcategory":"Farm",
            "type":"Manufacturing & Wholesale Goods"
        }
    ],
    "sg:postcode":"NR9 5JT",
    "sg:province":"Norfolk",
    "sg:tags":[
        "mixed",
        "crop"
    ],
    "wof:name":"D A Wales",
    "wof:placetype":"venue"
},
  "geometry": {"coordinates":[1.1318999529,52.7008666992],"type":"Point"}
}