{
  "type": "Feature",
  "properties": {
    "addr:full":"Custom House, Merfeyton Road Ellesmere Port Cheshire CH65 3AD",
    "addr:postcode":"ch65 3ad",
    "addr:street":"Merfeyton Road",
    "iso:country":"GB",
    "sg:address":"Custom House, Merfeyton Road",
    "sg:city":"Ellesmere Port",
    "sg:classifiers":[
        {
            "category":"Sports & Exercise",
            "subcategory":"Sports Center",
            "type":"Entertainment"
        }
    ],
    "sg:postcode":"CH65 3AD",
    "sg:province":"Cheshire",
    "sg:tags":[
        "coaching"
    ],
    "wof:name":"British Self Defence Governing Body Ltd.",
    "wof:placetype":"venue"
},
  "geometry": {"coordinates":[-2.905574,53.277199],"type":"Point"}
}