{
  "type": "Feature",
  "properties": {
    "iso:country":"GB",
    "sg:address":"336a Hoylake Road, Moreton",
    "sg:city":"Wirral",
    "sg:classifiers":[
        {
            "category":"Banks & Credit Unions",
            "subcategory":"Financial Services",
            "type":"Services"
        }
    ],
    "sg:postcode":"CH46 6DF",
    "sg:province":"Merseyside",
    "sg:tags":[
        "consultant"
    ],
    "wof:name":"Harvest Financial Management",
    "wof:placetype":"venue"
},
  "geometry": {"coordinates":[-3.119426012,53.3984489441],"type":"Point"}
}