{
  "type": "Feature",
  "properties": {
    "addr:full":"13-15 St. Huberts St, Great Harwood Blackburn Lancashire BB6 7BE",
    "addr:housenumber":"13-15",
    "addr:postcode":"bb6 7be",
    "addr:street":"St. Huberts St",
    "iso:country":"GB",
    "sg:address":"13-15 St. Huberts St, Great Harwood",
    "sg:city":"Blackburn",
    "sg:classifiers":[
        {
            "category":"Farming",
            "subcategory":"Nursery",
            "type":"Manufacturing & Wholesale Goods"
        }
    ],
    "sg:phone":"+44 1254 876707",
    "sg:postcode":"BB6 7BE",
    "sg:province":"Lancashire",
    "sg:tags":[
        "creche"
    ],
    "wof:name":"Hubbles Day Nursery",
    "wof:placetype":"venue"
},
  "geometry": {"coordinates":[-2.4004080296,53.7845191956],"type":"Point"}
}