{
  "type": "Feature",
  "properties": {
    "iso:country":"GB",
    "sg:address":"Unit 6 Wainstones Court, Stokesley Indst, Stokesley",
    "sg:city":"Middlesbrough",
    "sg:classifiers":[
        {
            "category":"Wholesale",
            "subcategory":"Fruits & Vegetables",
            "type":"Manufacturing & Wholesale Goods"
        }
    ],
    "sg:postcode":"TS9 5JY",
    "sg:province":"North Yorkshire",
    "wof:name":"Whitehead,Ross,",
    "wof:placetype":"venue"
},
  "geometry": {"coordinates":[-1.18879,54.470703],"type":"Point"}
}