{
  "type": "Feature",
  "properties": {
    "iso:country":"GB",
    "sg:address":"59 Alfred Street",
    "sg:city":"Stromness",
    "sg:classifiers":[
        {
            "category":"Organizations",
            "subcategory":"Non-profit Organization",
            "type":"Services"
        }
    ],
    "sg:phone":"+44 1856 850683",
    "sg:postcode":"KW16 3DF",
    "sg:province":"Orkney Islands",
    "sg:tags":[
        "charitable",
        "organisation",
        "voluntary",
        "charity"
    ],
    "wof:name":"Lifeboats-Royal National Lifeboat Institution",
    "wof:placetype":"venue"
},
  "geometry": {"coordinates":[-3.301419,58.957741],"type":"Point"}
}