{
  "type": "Feature",
  "properties": {
    "addr:full":"Unit 7 & 8 Metro Centre, Kangley Bridge Road London Greater London SE26 5BW",
    "addr:housenumber":"unit 7 & 8",
    "addr:postcode":"se26 5bw",
    "addr:street":"Kangley Bridge Road",
    "iso:country":"GB",
    "sg:address":"Unit 7 & 8 Metro Centre, Kangley Bridge Road",
    "sg:city":"London",
    "sg:classifiers":[
        {
            "category":"Home & Garden",
            "subcategory":"Carpets & Floor Coverings",
            "type":"Retail Goods"
        }
    ],
    "sg:postcode":"SE26 5BW",
    "sg:province":"Greater London",
    "sg:tags":[
        "trimming",
        "trimmer"
    ],
    "wof:name":"Trimont Furnishings Trimmings",
    "wof:placetype":"venue"
},
  "geometry": {"coordinates":[-0.03504,51.421371],"type":"Point"}
}