{
  "type": "Feature",
  "properties": {
    "addr:full":"22 Callart Rd Aviemore Highland PH22 1SR",
    "addr:housenumber":"22",
    "addr:postcode":"ph22 1sr",
    "addr:street":"Callart Rd",
    "iso:country":"GB",
    "sg:address":"22 Callart Rd",
    "sg:city":"Aviemore",
    "sg:classifiers":[
        {
            "category":"Taxi",
            "type":"Transportation"
        }
    ],
    "sg:phone":"+44 1479 811520",
    "sg:postcode":"PH22 1SR",
    "sg:province":"Highland",
    "sg:tags":[
        "mini",
        "cab"
    ],
    "wof:name":"J G A's Taxis",
    "wof:placetype":"venue"
},
  "geometry": {"coordinates":[-3.8164548874,57.200252533],"type":"Point"}
}