{
  "type": "Feature",
  "properties": {
    "iso:country":"GB",
    "sg:address":"45 St Edward Street",
    "sg:city":"Leek",
    "sg:classifiers":[
        {
            "category":"Banks & Credit Unions",
            "subcategory":"Bank",
            "type":"Services"
        }
    ],
    "sg:postcode":"ST13 5DN",
    "sg:province":"Staffordshire",
    "sg:tags":[
        "belt",
        "conveyor"
    ],
    "wof:name":"Humbert & Pol Uk Ltd.",
    "wof:placetype":"venue"
},
  "geometry": {"coordinates":[-2.025989,53.104935],"type":"Point"}
}