{
  "type": "Feature",
  "properties": {
    "iso:country":"GB",
    "sg:address":"1 Kenworthy Street",
    "sg:city":"Stalybridge",
    "sg:classifiers":[
        {
            "category":"Professional",
            "subcategory":"Engineering",
            "type":"Services"
        }
    ],
    "sg:phone":"+44 161 303 9950",
    "sg:postcode":"SK15 2DX",
    "sg:province":"Greater Manchester",
    "sg:tags":[
        "consulting",
        "engineer"
    ],
    "wof:name":"J Pedley Associates Ltd.",
    "wof:placetype":"venue"
},
  "geometry": {"coordinates":[-2.057022,53.481197],"type":"Point"}
}