{
  "type": "Feature",
  "properties": {
    "addr:full":"Unit 11 The Hollies, Graiseley Row Wolverhampton West Midlands WV2 4HJ",
    "addr:housenumber":"unit 11",
    "addr:postcode":"wv2 4hj",
    "addr:street":"The Hollies Graiseley Row",
    "iso:country":"GB",
    "sg:address":"Unit 11 The Hollies, Graiseley Row",
    "sg:city":"Wolverhampton",
    "sg:classifiers":[
        {
            "category":"Retail",
            "subcategory":"Auto Repair",
            "type":"Services"
        }
    ],
    "sg:postcode":"WV2 4HJ",
    "sg:province":"West Midlands",
    "sg:tags":[
        "modification",
        "garage"
    ],
    "wof:name":"D H Whitehall & Sons",
    "wof:placetype":"venue"
},
  "geometry": {"coordinates":[-2.1329410076,52.5776138306],"type":"Point"}
}