{
  "type": "Feature",
  "properties": {
    "iso:country":"GB",
    "sg:address":"Glebelands Road",
    "sg:city":"Wokingham",
    "sg:classifiers":[
        {
            "category":"Health Services",
            "subcategory":"Clinic",
            "type":"Services"
        },
        {
            "category":"Health Services",
            "subcategory":"Nursing And Care Facility",
            "type":"Services"
        },
        {
            "category":"Social Services",
            "subcategory":"Retirement Home",
            "type":"Services"
        }
    ],
    "sg:phone":"+44 118 979 0669",
    "sg:postcode":"RG40 1DU",
    "sg:province":"Berkshire",
    "sg:tags":[
        "residential",
        "private"
    ],
    "wof:name":"Glebelands Residential Home",
    "wof:placetype":"venue"
},
  "geometry": {"coordinates":[-0.836516,51.415112],"type":"Point"}
}