{
  "type": "Feature",
  "properties": {
    "addr:full":"1 Pleasant View, Knowle Ludlow Herefordshire SY8 3NL",
    "addr:housenumber":"1",
    "addr:postcode":"sy8 3nl",
    "iso:country":"GB",
    "sg:address":"1 Pleasant View, Knowle",
    "sg:city":"Ludlow",
    "sg:classifiers":[
        {
            "category":"Bus Charters",
            "type":"Transportation"
        }
    ],
    "sg:phone":"+44 1584 890770",
    "sg:postcode":"SY8 3NL",
    "sg:province":"Herefordshire",
    "sg:tags":[
        "hire",
        "coach"
    ],
    "wof:name":"R & B Travel",
    "wof:placetype":"venue"
},
  "geometry": {"coordinates":[-2.7190139294,52.3705940247],"type":"Point"}
}