{
  "type": "Feature",
  "properties": {
    "iso:country":"GB",
    "sg:address":"86 Southampton Rd",
    "sg:city":"Salisbury",
    "sg:classifiers":[
        {
            "category":"Autos & Motor Vehicles",
            "subcategory":"Auto Supplies",
            "type":"Retail Goods"
        }
    ],
    "sg:phone":"+44 1722 334954",
    "sg:postcode":"SP1 2LE",
    "sg:province":"Wiltshire",
    "sg:tags":[
        "car",
        "audio"
    ],
    "wof:name":"Contact",
    "wof:placetype":"venue"
},
  "geometry": {"coordinates":[-1.783618,51.063492],"type":"Point"}
}