{
  "type": "Feature",
  "properties": {
    "addr:full":"520-522 Watford Way London Greater London NW7 2PT",
    "addr:housenumber":"520-522",
    "addr:postcode":"nw7 2pt",
    "addr:street":"Watford Way",
    "iso:country":"GB",
    "sg:address":"520-522 Watford Way",
    "sg:city":"London",
    "sg:classifiers":[
        {
            "category":"Autos & Motor Vehicles",
            "subcategory":"Fuel & Gas Station",
            "type":"Retail Goods"
        }
    ],
    "sg:phone":"+44 20 8959 2277",
    "sg:postcode":"NW7 2PT",
    "sg:province":"Greater London",
    "sg:tags":[
        "hr",
        "petrol"
    ],
    "wof:name":"Observatory Service Station",
    "wof:placetype":"venue"
},
  "geometry": {"coordinates":[-0.2363090068,51.6024894714],"type":"Point"}
}