{
  "type": "Feature",
  "properties": {
    "iso:country":"GB",
    "sg:address":"68 Dudley Road",
    "sg:city":"Wolverhampton",
    "sg:classifiers":[
        {
            "category":"Manufacturing",
            "subcategory":"Textiles",
            "type":"Manufacturing & Wholesale Goods"
        }
    ],
    "sg:phone":"+44 1902 458205",
    "sg:postcode":"WV2 3BY",
    "sg:province":"West Midlands",
    "sg:tags":[
        "merchant",
        "agent"
    ],
    "wof:name":"D K Warehouse",
    "wof:placetype":"venue"
},
  "geometry": {"coordinates":[-2.126079,52.576431],"type":"Point"}
}