{
  "type": "Feature",
  "properties": {
    "addr:full":"Spout Lane, Caldmore Walsall West Midlands WS1 4HU",
    "addr:postcode":"ws1 4hu",
    "addr:street":"Spout Lane",
    "iso:country":"GB",
    "sg:address":"Spout Lane, Caldmore",
    "sg:city":"Walsall",
    "sg:classifiers":[
        {
            "category":"Government",
            "subcategory":"Office",
            "type":"Public Place"
        }
    ],
    "sg:phone":"+44 1922 720728",
    "sg:postcode":"WS1 4HU",
    "sg:province":"West Midlands",
    "sg:tags":[
        "local"
    ],
    "wof:name":"Walsall Mbc Neighbourhood Offices",
    "wof:placetype":"venue"
},
  "geometry": {"coordinates":[-1.9827970266,52.5757064819],"type":"Point"}
}