{
  "type": "Feature",
  "properties": {
    "iso:country":"GB",
    "sg:address":"2 Broomknowes Road",
    "sg:city":"Glasgow",
    "sg:classifiers":[
        {
            "category":"Food & Beverages",
            "subcategory":"Groceries & Convenience Stores",
            "type":"Retail Goods"
        }
    ],
    "sg:phone":"+44 141 558 9826",
    "sg:postcode":"G21 4YE",
    "sg:province":"East Dunbartonshire",
    "wof:name":"The Premier",
    "wof:placetype":"venue"
},
  "geometry": {"coordinates":[-4.221589,55.883053],"type":"Point"}
}