{
  "type": "Feature",
  "properties": {
    "iso:country":"GB",
    "sg:address":"Terrace Road South, Binfield",
    "sg:city":"Bracknell",
    "sg:classifiers":[
        {
            "category":"Social Services",
            "subcategory":"Adult Care",
            "type":"Services"
        },
        {
            "category":"Social Services",
            "subcategory":"Retirement Home",
            "type":"Services"
        }
    ],
    "sg:phone":"+44 1344 861557",
    "sg:postcode":"RG42 4BQ",
    "sg:province":"Berkshire",
    "sg:tags":[
        "housing",
        "sheltered",
        "accommodation"
    ],
    "wof:name":"Haddenhurst Court",
    "wof:placetype":"venue"
},
  "geometry": {"coordinates":[-0.788429,51.428215],"type":"Point"}
}