{
  "type": "Feature",
  "properties": {
    "iso:country":"GB",
    "sg:address":"Unit 14, Quay Lane, Hardway",
    "sg:city":"Gosport",
    "sg:classifiers":[
        {
            "category":"Autos & Motor Vehicles",
            "subcategory":"Fuel & Gas Station",
            "type":"Retail Goods"
        },
        {
            "category":"Manufacturing",
            "subcategory":"Tools & Machinery",
            "type":"Manufacturing & Wholesale Goods"
        }
    ],
    "sg:phone":"+44 23 9251 1666",
    "sg:postcode":"PO12 4LJ",
    "sg:province":"Hampshire",
    "sg:tags":[
        "machine"
    ],
    "sg:website":"http://www.mtes.co.uk",
    "wof:name":"Machine Tool & Engineering Services Ltd",
    "wof:placetype":"venue"
},
  "geometry": {"coordinates":[-1.1396080256,50.815246582],"type":"Point"}
}