{
  "type": "Feature",
  "properties": {
    "addr:full":"Sale Hearing Centre, 39-41 Poplar Grove Sale Cheshire M33 3AX",
    "addr:housenumber":"39-41",
    "addr:postcode":"m33 3ax",
    "iso:country":"GB",
    "sg:address":"Sale Hearing Centre, 39-41 Poplar Grove",
    "sg:city":"Sale",
    "sg:classifiers":[
        {
            "category":"Wholesale",
            "subcategory":"Medical Equipment & Supplies",
            "type":"Manufacturing & Wholesale Goods"
        },
        {
            "category":"Health Services",
            "subcategory":"Nursing And Care Facility",
            "type":"Services"
        }
    ],
    "sg:phone":"+44 161 969 2461",
    "sg:postcode":"M33 3AX",
    "sg:province":"Cheshire",
    "sg:tags":[
        "aid",
        "agency",
        "hearing"
    ],
    "wof:name":"THE HEARING CARE PARTNERSHIP LTD",
    "wof:placetype":"venue"
},
  "geometry": {"coordinates":[-2.3190789223,53.4156494141],"type":"Point"}
}