{
  "type": "Feature",
  "properties": {
    "addr:full":"30 New Park Road London Greater London SW2 4UN",
    "addr:housenumber":"30",
    "addr:postcode":"sw2 4un",
    "addr:street":"New Park Road",
    "iso:country":"GB",
    "sg:address":"30 New Park Road",
    "sg:city":"London",
    "sg:classifiers":[
        {
            "category":"Shopping",
            "subcategory":"Florist",
            "type":"Retail Goods"
        }
    ],
    "sg:phone":"+44 20 8671 8165",
    "sg:postcode":"SW2 4UN",
    "sg:province":"Greater London",
    "wof:name":"The Flower Box",
    "wof:placetype":"venue"
},
  "geometry": {"coordinates":[-0.125356,51.448627],"type":"Point"}
}