{
  "type": "Feature",
  "properties": {
    "addr:full":"1 Tylers Way, Sedbury Chepstow Gloucestershire NP16 7AB",
    "addr:housenumber":"1",
    "addr:postcode":"np16 7ab",
    "addr:street":"Tylers Way Sedbury",
    "iso:country":"GB",
    "sg:address":"1 Tylers Way, Sedbury",
    "sg:city":"Chepstow",
    "sg:classifiers":[
        {
            "category":"Retail",
            "subcategory":"Driving School",
            "type":"Services"
        }
    ],
    "sg:postcode":"NP16 7AB",
    "sg:province":"Gloucestershire",
    "wof:name":"Sue's School of Motoring",
    "wof:placetype":"venue"
},
  "geometry": {"coordinates":[-2.6582229137,51.639995575],"type":"Point"}
}