{
  "type": "Feature",
  "properties": {
    "addr:full":"188 Holbrook Lane Coventry Warwickshire CV6 4BY",
    "addr:housenumber":"188",
    "addr:postcode":"cv6 4by",
    "addr:street":"Holbrook Lane",
    "iso:country":"GB",
    "sg:address":"188 Holbrook Lane",
    "sg:city":"Coventry",
    "sg:classifiers":[
        {
            "category":"Home & Garden",
            "subcategory":"Building Materials",
            "type":"Retail Goods"
        }
    ],
    "sg:phone":"+44 24 7666 7829",
    "sg:postcode":"CV6 4BY",
    "sg:province":"Warwickshire",
    "sg:tags":[
        "plaster",
        "ware"
    ],
    "wof:name":"Anthony Paul Molloy",
    "wof:placetype":"venue"
},
  "geometry": {"coordinates":[-1.507159,52.437428],"type":"Point"}
}