{
  "type": "Feature",
  "properties": {
    "addr:full":"108 Ashgate Road Chesterfield Derbyshire S40 4AQ",
    "addr:housenumber":"108",
    "addr:postcode":"s40 4aq",
    "addr:street":"Ashgate Road",
    "iso:country":"GB",
    "sg:address":"108 Ashgate Road",
    "sg:city":"Chesterfield",
    "sg:classifiers":[
        {
            "category":"Autos & Motor Vehicles",
            "subcategory":"Fuel & Gas Station",
            "type":"Retail Goods"
        },
        {
            "category":"Professional",
            "subcategory":"Testing Lab",
            "type":"Services"
        },
        {
            "category":"Shopping",
            "subcategory":"News",
            "type":"Retail Goods"
        }
    ],
    "sg:phone":"+44 1246 279631",
    "sg:postcode":"S40 4AQ",
    "sg:province":"Derbyshire",
    "sg:tags":[
        "petrol",
        "filling",
        "newsagent",
        "mot"
    ],
    "wof:name":"Jack Loggin Ltd.",
    "wof:placetype":"venue"
},
  "geometry": {"coordinates":[-1.445146,53.239162],"type":"Point"}
}