{
  "type": "Feature",
  "properties": {
    "iso:country":"GB",
    "sg:address":"96 Barnsley Road",
    "sg:city":"Wakefield",
    "sg:classifiers":[
        {
            "category":"Military Area",
            "subcategory":"Air Force Base",
            "type":"Public Place"
        }
    ],
    "sg:phone":"+44 1924 242000",
    "sg:postcode":"WF1 5NP",
    "sg:province":"West Yorkshire",
    "sg:tags":[
        "taxi",
        "hire",
        "private"
    ],
    "wof:name":"Walton Cars",
    "wof:placetype":"venue"
},
  "geometry": {"coordinates":[-1.487305,53.667534],"type":"Point"}
}