{
  "type": "Feature",
  "properties": {
    "addr:full":"196-198 Foleshill Road Coventry West Midlands CV1 4JH",
    "addr:postcode":"196-198;cv1 4jh",
    "addr:street":"Foleshill Road",
    "iso:country":"GB",
    "sg:address":"196-198 Foleshill Road",
    "sg:city":"Coventry",
    "sg:classifiers":[
        {
            "category":"Fast Food",
            "type":"Food & Drink"
        },
        {
            "category":"Restaurant",
            "type":"Food & Drink"
        }
    ],
    "sg:phone":"+44 24 7663 3414",
    "sg:postcode":"CV1 4JH",
    "sg:province":"West Midlands",
    "sg:tags":[
        "away",
        "indian",
        "take"
    ],
    "wof:name":"Moonlight Balti Restaurant",
    "wof:placetype":"venue"
},
  "geometry": {"coordinates":[-1.506681,52.419552],"type":"Point"}
}