{
  "type": "Feature",
  "properties": {
    "addr:full":"314a Collier Row Lane Romford Essex RM5 3NL",
    "addr:housenumber":"314a",
    "addr:postcode":"rm5 3nl",
    "addr:street":"Collier Row Lane",
    "iso:country":"GB",
    "sg:address":"314a Collier Row Lane",
    "sg:city":"Romford",
    "sg:classifiers":[
        {
            "category":"Personal",
            "subcategory":"Tattoo Parlor",
            "type":"Services"
        }
    ],
    "sg:phone":"+44 1708 739330",
    "sg:postcode":"RM5 3NL",
    "sg:province":"Essex",
    "sg:tags":[
        "tattooing",
        "piercing"
    ],
    "wof:name":"The Tattoo Shack",
    "wof:placetype":"venue"
},
  "geometry": {"coordinates":[0.1633539945,51.5989303589],"type":"Point"}
}