{
  "type": "Feature",
  "properties": {
    "iso:country":"GB",
    "sg:address":"Bramble Cottage, Moor Lane, Westfield",
    "sg:city":"Woking",
    "sg:classifiers":[
        {
            "category":"Building & Trades",
            "subcategory":"Landscaping Services",
            "type":"Services"
        }
    ],
    "sg:phone":"+44 1483 767410",
    "sg:postcode":"GU22 9RB",
    "sg:province":"Surrey",
    "sg:tags":[
        "landscape",
        "contractor"
    ],
    "wof:name":"Surrey Scapes",
    "wof:placetype":"venue"
},
  "geometry": {"coordinates":[-0.5558000207,51.2949905396],"type":"Point"}
}