{
  "type": "Feature",
  "properties": {
    "addr:full":"Unit C Marten Park, Marten Lane Ashford Kent TN26 3JP",
    "addr:housenumber":"unit c",
    "addr:postcode":"tn26 3jp",
    "addr:street":"Marten Park Marten Lane",
    "iso:country":"GB",
    "sg:address":"Unit C Marten Park, Marten Lane",
    "sg:city":"Ashford",
    "sg:classifiers":[
        {
            "category":"Building & Trades",
            "subcategory":"Equipment Rental",
            "type":"Services"
        }
    ],
    "sg:phone":"+44 1239 881389",
    "sg:postcode":"TN26 3JP",
    "sg:province":"Kent",
    "sg:tags":[
        "hotel",
        "restaurant"
    ],
    "wof:name":"la Kitchen Equipment Supplies Ltd.",
    "wof:placetype":"venue"
},
  "geometry": {"coordinates":[0.74083,51.10603],"type":"Point"}
}