{
  "type": "Feature",
  "properties": {
    "iso:country":"GB",
    "sg:address":"Windmill Road, Weald",
    "sg:city":"Sevenoaks",
    "sg:classifiers":[
        {
            "category":"Government",
            "subcategory":"Post Office",
            "type":"Public Place"
        }
    ],
    "sg:phone":"+44 1732 463201",
    "sg:postcode":"TN14 6PH",
    "sg:province":"Kent",
    "wof:name":"Weald Post Office",
    "wof:placetype":"venue"
},
  "geometry": {"coordinates":[0.18773,51.237644],"type":"Point"}
}