{
  "type": "Feature",
  "properties": {
    "addr:full":"Second Floor, 115 Commercial Rd Swindon Wiltshire SN1 5PL",
    "addr:housenumber":"second;115",
    "addr:postcode":"sn1 5pl",
    "addr:street":"Commercial Rd",
    "iso:country":"GB",
    "sg:address":"Second Floor, 115 Commercial Rd",
    "sg:city":"Swindon",
    "sg:classifiers":[
        {
            "category":"Sports & Exercise",
            "subcategory":"Sports Center",
            "type":"Entertainment"
        }
    ],
    "sg:phone":"+44 1793 616313",
    "sg:postcode":"SN1 5PL",
    "sg:province":"Wiltshire",
    "sg:tags":[
        "shop",
        "good"
    ],
    "wof:name":"EDT",
    "wof:placetype":"venue"
},
  "geometry": {"coordinates":[-1.78391397,51.558807373],"type":"Point"}
}