{
  "type": "Feature",
  "properties": {
    "addr:full":"Fiveways House, Five Ways, Wolvey Hinckley Leicestershire LE10 3HG",
    "addr:postcode":"le10 3hg",
    "addr:street":"Five Ways",
    "iso:country":"GB",
    "sg:address":"Fiveways House, Five Ways, Wolvey",
    "sg:city":"Hinckley",
    "sg:classifiers":[
        {
            "category":"Retail",
            "subcategory":"Auto Repair",
            "type":"Services"
        }
    ],
    "sg:postcode":"LE10 3HG",
    "sg:province":"Leicestershire",
    "sg:tags":[
        "modification",
        "garage"
    ],
    "wof:name":"Gunter's Truck Centre",
    "wof:placetype":"venue"
},
  "geometry": {"coordinates":[-1.369322,52.485638],"type":"Point"}
}