{
  "type": "Feature",
  "properties": {
    "addr:full":"58-59 South Side St Plymouth Devon PL1 2LA",
    "addr:housenumber":"58-59",
    "addr:postcode":"pl1 2la",
    "addr:street":"South Side St",
    "iso:country":"GB",
    "sg:address":"58-59 South Side St",
    "sg:city":"Plymouth",
    "sg:classifiers":[
        {
            "category":"Health Services",
            "subcategory":"Clinic",
            "type":"Services"
        }
    ],
    "sg:phone":"+44 1752 255577",
    "sg:postcode":"PL1 2LA",
    "sg:province":"Devon",
    "sg:tags":[
        "aromatherapy"
    ],
    "wof:name":"Heavenly Aromas",
    "wof:placetype":"venue"
},
  "geometry": {"coordinates":[-4.1374950409,50.3676452637],"type":"Point"}
}