{
  "type": "Feature",
  "properties": {
    "iso:country":"GB",
    "sg:address":"19 The Avenue",
    "sg:city":"Newmarket",
    "sg:classifiers":[
        {
            "category":"Building & Trades",
            "subcategory":"Construction",
            "type":"Services"
        }
    ],
    "sg:phone":"+44 1638 663151",
    "sg:postcode":"CB8 9AA",
    "sg:province":"Cambridgeshire",
    "sg:tags":[
        "roofing"
    ],
    "wof:name":"B T Pettit Roofing",
    "wof:placetype":"venue"
},
  "geometry": {"coordinates":[0.404927,52.241623],"type":"Point"}
}