{
  "type": "Feature",
  "properties": {
    "iso:country":"GB",
    "sg:address":"6 Mount Street",
    "sg:city":"Bridgwater",
    "sg:classifiers":[
        {
            "category":"Retail",
            "subcategory":"Auto Repair",
            "type":"Services"
        }
    ],
    "sg:phone":"+44 1278 453496",
    "sg:postcode":"TA6 3ER",
    "sg:province":"Somerset",
    "sg:tags":[
        "modification",
        "garage"
    ],
    "wof:name":"R & N Auto Repairs",
    "wof:placetype":"venue"
},
  "geometry": {"coordinates":[-3.00646,51.129375],"type":"Point"}
}