{
  "type": "Feature",
  "properties": {
    "iso:country":"GB",
    "sg:address":"38 Linden Rd",
    "sg:city":"Luton",
    "sg:classifiers":[
        {
            "category":"Food & Beverages",
            "subcategory":"Supermarket",
            "type":"Retail Goods"
        }
    ],
    "sg:postcode":"LU4 9QZ",
    "sg:province":"Bedfordshire",
    "wof:name":"George's Off Licence",
    "wof:placetype":"venue"
},
  "geometry": {"coordinates":[-0.458851,51.900902],"type":"Point"}
}