{
  "type": "Feature",
  "properties": {
    "addr:full":"Baird Ho, 15-17 St Cross St London Greater London EC1N 8UN",
    "addr:housenumber":"15-17",
    "addr:postcode":"ec1n 8un",
    "addr:street":"Baird;St Cross St",
    "iso:country":"GB",
    "sg:address":"Baird Ho, 15-17 St Cross St",
    "sg:city":"London",
    "sg:classifiers":[
        {
            "category":"Professional",
            "subcategory":"Printing & Photocopies",
            "type":"Services"
        }
    ],
    "sg:phone":"+44 204308200",
    "sg:postcode":"EC1N 8UN",
    "sg:province":"Greater London",
    "sg:tags":[
        "top",
        "publishing",
        "desk"
    ],
    "wof:name":"Concept D T P Ltd",
    "wof:placetype":"venue"
},
  "geometry": {"coordinates":[-0.108139,51.520824],"type":"Point"}
}