{
  "type": "Feature",
  "properties": {
    "addr:full":"Rooley Avenue Bradford West Yorkshire BD6 1EZ",
    "addr:postcode":"bd6 1ez",
    "addr:street":"Avenue Bradford West",
    "iso:country":"GB",
    "sg:address":"Rooley Avenue",
    "sg:city":"Bradford",
    "sg:classifiers":[
        {
            "category":"Arena",
            "subcategory":"Sports Club",
            "type":"Entertainment"
        },
        {
            "category":"Sports & Exercise",
            "subcategory":"Gym",
            "type":"Entertainment"
        },
        {
            "category":"Government",
            "subcategory":"Office",
            "type":"Public Place"
        }
    ],
    "sg:phone":"+44 1274 307822",
    "sg:postcode":"BD6 1EZ",
    "sg:province":"West Yorkshire",
    "sg:tags":[
        "ground",
        "local",
        "fitness",
        "health",
        "centre"
    ],
    "wof:name":"Images Fitness Centre",
    "wof:placetype":"venue"
},
  "geometry": {"coordinates":[-1.750552,53.768288],"type":"Point"}
}