{
  "type": "Feature",
  "properties": {
    "addr:full":"34 Hanover Street Edinburgh City of Edinburgh EH2 2DR",
    "addr:housenumber":"34",
    "addr:postcode":"eh2 2dr",
    "addr:street":"Hanover Street",
    "iso:country":"GB",
    "sg:address":"34 Hanover Street",
    "sg:city":"Edinburgh",
    "sg:classifiers":[
        {
            "category":"Food & Beverages",
            "subcategory":"Bakery",
            "type":"Retail Goods"
        }
    ],
    "sg:phone":"+44 131 226 3652",
    "sg:postcode":"EH2 2DR",
    "sg:province":"City of Edinburgh",
    "sg:tags":[
        "pizza"
    ],
    "wof:name":"Pizza Hut",
    "wof:placetype":"venue"
},
  "geometry": {"coordinates":[-3.197214,55.952953],"type":"Point"}
}