{
  "type": "Feature",
  "properties": {
    "addr:full":"Netherhall School Maryport Cumbria CA15 6NT",
    "addr:postcode":"ca15 6nt",
    "iso:country":"GB",
    "sg:address":"Netherhall School",
    "sg:city":"Maryport",
    "sg:classifiers":[
        {
            "category":"Education",
            "subcategory":"University",
            "type":"Public Place"
        }
    ],
    "sg:phone":"+44 1900 815765",
    "sg:postcode":"CA15 6NT",
    "sg:province":"Cumbria",
    "sg:tags":[
        "adult"
    ],
    "wof:name":"Netherhall Adult Education Centre",
    "wof:placetype":"venue"
},
  "geometry": {"coordinates":[-3.4965350628,54.7123908997],"type":"Point"}
}