{
  "type": "Feature",
  "properties": {
    "iso:country":"GB",
    "sg:address":"7 Macbeth Court",
    "sg:city":"Bracknell",
    "sg:classifiers":[
        {
            "category":"Home & Garden",
            "subcategory":"Home Furnishings",
            "type":"Retail Goods"
        }
    ],
    "sg:phone":"+44 1344 305369",
    "sg:postcode":"RG42 3EQ",
    "sg:province":"Berkshire",
    "sg:tags":[
        "furnishers",
        "planner",
        "kitchen"
    ],
    "wof:name":"Sunninghill Kitchen Co",
    "wof:placetype":"venue"
},
  "geometry": {"coordinates":[-0.7327160239,51.4215736389],"type":"Point"}
}