{
  "type": "Feature",
  "properties": {
    "addr:full":"Dunkery Road Manchester Greater Manchester M22 0NT",
    "addr:postcode":"m22 0nt",
    "addr:street":"Dunkery Road",
    "iso:country":"GB",
    "sg:address":"Dunkery Road",
    "sg:city":"Manchester",
    "sg:classifiers":[
        {
            "category":"Organizations",
            "subcategory":"Membership Organization",
            "type":"Services"
        }
    ],
    "sg:phone":"+44 161 437 6588",
    "sg:postcode":"M22 0NT",
    "sg:province":"Greater Manchester",
    "sg:tags":[
        "club"
    ],
    "wof:name":"St.Anthony's Parish Centre",
    "wof:placetype":"venue"
},
  "geometry": {"coordinates":[-2.260224,53.372978],"type":"Point"}
}