{
  "type": "Feature",
  "properties": {
    "iso:country":"GB",
    "sg:address":"Collymoon Farm, Port Of Menteith",
    "sg:city":"Stirling",
    "sg:classifiers":[
        {
            "category":"Farming",
            "subcategory":"Farm",
            "type":"Manufacturing & Wholesale Goods"
        }
    ],
    "sg:phone":"+44 1360 850268",
    "sg:postcode":"FK8 3JY",
    "sg:province":"Stirling",
    "sg:tags":[
        "mixed",
        "crop"
    ],
    "wof:name":"H D Fotheringham",
    "wof:placetype":"venue"
},
  "geometry": {"coordinates":[-4.283714,56.18504],"type":"Point"}
}