{
  "type": "Feature",
  "properties": {
    "iso:country":"GB",
    "sg:address":"15 High Street",
    "sg:city":"Olney",
    "sg:classifiers":[
        {
            "category":"Food & Beverages",
            "subcategory":"Groceries & Convenience Stores",
            "type":"Retail Goods"
        }
    ],
    "sg:postcode":"MK46 4EB",
    "sg:province":"Buckinghamshire",
    "wof:name":"Lavendon Post Office & Stores",
    "wof:placetype":"venue"
},
  "geometry": {"coordinates":[-0.7019469738,52.1544113159],"type":"Point"}
}