{
  "type": "Feature",
  "properties": {
    "addr:full":"5 Upperhead Row Huddersfield West Yorkshire HD1 2JL",
    "addr:housenumber":"5",
    "addr:postcode":"hd1 2jl",
    "addr:street":"Upperhead Row",
    "iso:country":"GB",
    "sg:address":"5 Upperhead Row",
    "sg:city":"Huddersfield",
    "sg:classifiers":[
        {
            "category":"Real Estate",
            "subcategory":"Real Estate Agent",
            "type":"Services"
        }
    ],
    "sg:phone":"+44 1484 452200",
    "sg:postcode":"HD1 2JL",
    "sg:province":"West Yorkshire",
    "wof:name":"Chainmakers",
    "wof:placetype":"venue"
},
  "geometry": {"coordinates":[-1.7859710455,53.6463432312],"type":"Point"}
}