{
  "type": "Feature",
  "properties": {
    "iso:country":"GB",
    "sg:address":"17 Ashley Gardens",
    "sg:city":"Tunbridge Wells",
    "sg:classifiers":[
        {
            "category":"Retail",
            "subcategory":"Driving School",
            "type":"Services"
        }
    ],
    "sg:phone":"+44 1892 543544",
    "sg:postcode":"TN4 8TY",
    "sg:province":"Kent",
    "wof:name":"Mike Bassett Driving Tuition",
    "wof:placetype":"venue"
},
  "geometry": {"coordinates":[0.230091,51.138039],"type":"Point"}
}