{
  "type": "Feature",
  "properties": {
    "addr:full":"Strathaven Road Lanark South Lanarkshire ML11 9RN",
    "addr:postcode":"ml11 9rn",
    "addr:street":"Strathaven Road",
    "iso:country":"GB",
    "sg:address":"Strathaven Road",
    "sg:city":"Lanark",
    "sg:classifiers":[
        {
            "category":"Autos & Motor Vehicles",
            "subcategory":"Fuel & Gas Station",
            "type":"Retail Goods"
        }
    ],
    "sg:phone":"+44 1555 893498",
    "sg:postcode":"ML11 9RN",
    "sg:province":"South Lanarkshire",
    "sg:tags":[
        "petrol",
        "filling"
    ],
    "wof:name":"Fourways Service Station Ltd.",
    "wof:placetype":"venue"
},
  "geometry": {"coordinates":[-3.781384,55.673866],"type":"Point"}
}