{
  "type": "Feature",
  "properties": {
    "addr:full":"37a Kidbrooke Gro, Blackheath London Greater London SE3 0LJ",
    "addr:housenumber":"37a",
    "addr:postcode":"se3 0lj",
    "addr:street":"Kidbrooke Gro Blackheath",
    "iso:country":"GB",
    "sg:address":"37a Kidbrooke Gro, Blackheath",
    "sg:city":"London",
    "sg:classifiers":[
        {
            "category":"Real Estate",
            "subcategory":"Developer",
            "type":"Services"
        }
    ],
    "sg:phone":"+44 20 8858 7751",
    "sg:postcode":"SE3 0LJ",
    "sg:province":"Greater London",
    "sg:tags":[
        "property"
    ],
    "wof:name":"Mulberry Building Developers & Contractors",
    "wof:placetype":"venue"
},
  "geometry": {"coordinates":[0.021251,51.470764],"type":"Point"}
}