{
  "type": "Feature",
  "properties": {
    "iso:country":"GB",
    "sg:address":"99 Kenningknowes Rd",
    "sg:city":"Stirling",
    "sg:classifiers":[
        {
            "category":"Professional",
            "subcategory":"Computer Services",
            "type":"Services"
        }
    ],
    "sg:phone":"+44 1786 465632",
    "sg:postcode":"FK7 9JF",
    "sg:province":"Falkirk",
    "sg:tags":[
        "consultant"
    ],
    "wof:name":"Quality Training Ltd",
    "wof:placetype":"venue"
},
  "geometry": {"coordinates":[-3.955793,56.109711],"type":"Point"}
}