{
  "type": "Feature",
  "properties": {
    "iso:country":"GB",
    "sg:address":"Netherplace Farm",
    "sg:city":"Lockerbie",
    "sg:phone":"+44 1576 202727",
    "sg:postcode":"DG11 2DQ",
    "sg:province":"Dumfries and Galloway",
    "wof:name":"Messrs Charles Marshall Kirkpatrick",
    "wof:placetype":"venue"
},
  "geometry": {"coordinates":[-3.3545689583,55.1217765808],"type":"Point"}
}