{
  "type": "Feature",
  "properties": {
    "addr:full":"Po Box 1921 Slough Berkshire SL2 3NU",
    "addr:housenumber":"po",
    "addr:postcode":"sl2 3nu",
    "addr:street":"Box 1921",
    "iso:country":"GB",
    "sg:address":"Po Box 1921",
    "sg:city":"Slough",
    "sg:classifiers":[
        {
            "category":"Real Estate",
            "subcategory":"Developer",
            "type":"Services"
        }
    ],
    "sg:phone":"+44 1753 647619",
    "sg:postcode":"SL2 3NU",
    "sg:province":"Berkshire",
    "sg:tags":[
        "property"
    ],
    "wof:name":"Trident Holdings Plc",
    "wof:placetype":"venue"
},
  "geometry": {"coordinates":[-0.6186689734,51.5520210266],"type":"Point"}
}