{
  "type": "Feature",
  "properties": {
    "iso:country":"GB",
    "sg:address":"Rixlade Stoke Hill",
    "sg:city":"Exeter",
    "sg:classifiers":[
        {
            "category":"Travel",
            "subcategory":"Hotels & Motels",
            "type":"Entertainment"
        }
    ],
    "sg:postcode":"EX4 9JN",
    "sg:province":"Devon",
    "sg:tags":[
        "self",
        "catering"
    ],
    "wof:name":"Rixlade Farm Self Catering Cottages",
    "wof:placetype":"venue"
},
  "geometry": {"coordinates":[-3.50574,50.75029],"type":"Point"}
}