{
  "type": "Feature",
  "properties": {
    "addr:full":"Park Farm Dalbeattie Dumfries and Galloway DG5 4NE",
    "addr:postcode":"dg5 4ne",
    "iso:country":"GB",
    "sg:address":"Park Farm",
    "sg:city":"Dalbeattie",
    "sg:classifiers":[
        {
            "category":"Recreation",
            "subcategory":"Campground",
            "type":"Entertainment"
        }
    ],
    "sg:phone":"+44 1556 611393",
    "sg:postcode":"DG5 4NE",
    "sg:province":"Dumfries and Galloway",
    "sg:tags":[
        "caravan",
        "park"
    ],
    "wof:name":"Glenearly Caravan Park Ltd.",
    "wof:placetype":"venue"
},
  "geometry": {"coordinates":[-3.823039,54.933456],"type":"Point"}
}