{
  "type": "Feature",
  "properties": {
    "addr:full":"25 St Thomas Place, Penkhull Stoke-on-trent Staffordshire ST4 7LA",
    "addr:housenumber":"25",
    "addr:postcode":"st4 7la",
    "addr:street":"St Thomas;Penkhull",
    "iso:country":"GB",
    "sg:address":"25 St Thomas Place, Penkhull",
    "sg:city":"Stoke-on-trent",
    "sg:classifiers":[
        {
            "category":"Professional",
            "subcategory":"Engineering",
            "type":"Services"
        }
    ],
    "sg:postcode":"ST4 7LA",
    "sg:province":"Staffordshire",
    "sg:tags":[
        "contractor",
        "electrical",
        "engineer"
    ],
    "wof:name":"Penkhull Electrical",
    "wof:placetype":"venue"
},
  "geometry": {"coordinates":[-2.195809,53.002609],"type":"Point"}
}