{
  "type": "Feature",
  "properties": {
    "iso:country":"GB",
    "sg:address":"2-4 Maddox Street",
    "sg:city":"London",
    "sg:classifiers":[
        {
            "category":"Fast Food",
            "type":"Food & Drink"
        }
    ],
    "sg:phone":"+44 20 7499 7687",
    "sg:postcode":"W1S 1PF",
    "sg:province":"Greater London",
    "sg:tags":[
        "away",
        "take"
    ],
    "wof:name":"Soup Works Plc",
    "wof:placetype":"venue"
},
  "geometry": {"coordinates":[-0.1414110065,51.5137062073],"type":"Point"}
}