{
  "type": "Feature",
  "properties": {
    "iso:country":"GB",
    "sg:address":"1st Floor Viking House, Swallowdale Lane",
    "sg:city":"Hemel Hempstead",
    "sg:classifiers":[
        {
            "category":"Professional",
            "subcategory":"Management & Consulting",
            "type":"Services"
        }
    ],
    "sg:phone":"+44 1442 232124",
    "sg:postcode":"HP2 7PU",
    "sg:province":"Hertfordshire",
    "sg:tags":[
        "consultant",
        "business"
    ],
    "wof:name":"Genesis Development International",
    "wof:placetype":"venue"
},
  "geometry": {"coordinates":[-0.4375660121,51.7694816589],"type":"Point"}
}