{
  "type": "Feature",
  "properties": {
    "addr:full":"22 Maureen Close Poole Dorset BH12 3HG",
    "addr:housenumber":"22",
    "addr:postcode":"bh12 3hg",
    "addr:street":"Maureen Close",
    "iso:country":"GB",
    "sg:address":"22 Maureen Close",
    "sg:city":"Poole",
    "sg:classifiers":[
        {
            "category":"Home & Garden",
            "subcategory":"Household Appliances",
            "type":"Retail Goods"
        },
        {
            "category":"Shopping",
            "subcategory":"Crafts & Fabrics",
            "type":"Retail Goods"
        },
        {
            "category":"Communications",
            "type":"Services"
        }
    ],
    "sg:postcode":"BH12 3HG",
    "sg:province":"Dorset",
    "sg:tags":[
        "knitting",
        "tv",
        "sewing",
        "domestic",
        "microwave",
        "machine",
        "video",
        "oven",
        "radio"
    ],
    "wof:name":"Wessex Microwaves",
    "wof:placetype":"venue"
},
  "geometry": {"coordinates":[-1.9448080063,50.7410736084],"type":"Point"}
}