{
  "type": "Feature",
  "properties": {
    "addr:full":"15 Westfield Gro, Finchfield Wolverhampton Staffordshire WV3 8EX",
    "addr:housenumber":"15",
    "addr:postcode":"wv3 8ex",
    "addr:street":"Westfield Gro Finchfield",
    "iso:country":"GB",
    "sg:address":"15 Westfield Gro, Finchfield",
    "sg:city":"Wolverhampton",
    "sg:classifiers":[
        {
            "category":"Wholesale",
            "subcategory":"Chemicals & Plastics",
            "type":"Manufacturing & Wholesale Goods"
        }
    ],
    "sg:phone":"+44 1902 373699",
    "sg:postcode":"WV3 8EX",
    "sg:province":"Staffordshire",
    "sg:tags":[
        "ind"
    ],
    "wof:name":"Jayward Systems (U K) Ltd.",
    "wof:placetype":"venue"
},
  "geometry": {"coordinates":[-2.1711690426,52.5805015564],"type":"Point"}
}