{
  "type": "Feature",
  "properties": {
    "addr:full":"67 Laygate South Shields Tyne and Wear NE33 5RW",
    "addr:housenumber":"67",
    "addr:postcode":"ne33 5rw",
    "addr:street":"Laygate",
    "iso:country":"GB",
    "sg:address":"67 Laygate",
    "sg:city":"South Shields",
    "sg:classifiers":[
        {
            "category":"Building & Trades",
            "subcategory":"Cleaning & Sanitation",
            "type":"Services"
        }
    ],
    "sg:phone":"+44 191 454 5191",
    "sg:postcode":"NE33 5RW",
    "sg:province":"Tyne and Wear",
    "sg:tags":[
        "polishing",
        "floor"
    ],
    "wof:name":"Cleaneasy",
    "wof:placetype":"venue"
},
  "geometry": {"coordinates":[-1.438444972,54.9900093079],"type":"Point"}
}