{
  "type": "Feature",
  "properties": {
    "addr:full":"North Dr Beaconsfield Buckinghamshire HP9 1TZ",
    "addr:postcode":"hp9 1tz",
    "addr:street":"North Dr",
    "iso:country":"GB",
    "sg:address":"North Dr",
    "sg:city":"Beaconsfield",
    "sg:classifiers":[
        {
            "category":"Government",
            "subcategory":"Post Office",
            "type":"Public Place"
        }
    ],
    "sg:phone":"+44 1494 672997",
    "sg:postcode":"HP9 1TZ",
    "sg:province":"Buckinghamshire",
    "wof:name":"Holtspur Post Office",
    "wof:placetype":"venue"
},
  "geometry": {"coordinates":[-0.6649489999,51.5997810364],"type":"Point"}
}