{
  "type": "Feature",
  "properties": {
    "addr:full":"38 Peel St Wrexham Wrexham LL13 7TR",
    "addr:housenumber":"38",
    "addr:postcode":"ll13 7tr",
    "addr:street":"Peel St",
    "iso:country":"GB",
    "sg:address":"38 Peel St",
    "sg:city":"Wrexham",
    "sg:classifiers":[
        {
            "category":"Military Area",
            "subcategory":"Air Force Base",
            "type":"Public Place"
        }
    ],
    "sg:phone":"+44 1978 358366",
    "sg:postcode":"LL13 7TR",
    "sg:province":"Wrexham",
    "sg:tags":[
        "taxi",
        "hire",
        "private"
    ],
    "wof:name":"A & M Cars",
    "wof:placetype":"venue"
},
  "geometry": {"coordinates":[-3.003849,53.044277],"type":"Point"}
}