{
  "type": "Feature",
  "properties": {
    "iso:country":"GB",
    "sg:address":"15 Garrick Way",
    "sg:city":"Ipswich",
    "sg:classifiers":[
        {
            "category":"Food & Beverages",
            "subcategory":"Supermarket",
            "type":"Retail Goods"
        }
    ],
    "sg:phone":"+44 1473 741119",
    "sg:postcode":"IP1 6NF",
    "sg:province":"Suffolk",
    "wof:name":"Ipswich & Norwich Co-Operative Society",
    "wof:placetype":"venue"
},
  "geometry": {"coordinates":[1.138028,52.080025],"type":"Point"}
}