{
  "type": "Feature",
  "properties": {
    "iso:country":"GB",
    "sg:address":"Thornecliffe Ho, Wistaston Rd",
    "sg:city":"Nantwich",
    "sg:classifiers":[
        {
            "category":"Professional",
            "subcategory":"Management & Consulting",
            "type":"Services"
        }
    ],
    "sg:phone":"+44 1270 669249",
    "sg:postcode":"CW5 6QP",
    "sg:province":"Cheshire",
    "sg:tags":[
        "consultant",
        "safety"
    ],
    "wof:name":"Crosbie P",
    "wof:placetype":"venue"
},
  "geometry": {"coordinates":[-2.484447,53.071682],"type":"Point"}
}