{
  "type": "Feature",
  "properties": {
    "addr:full":"114 Blackstock Road London Greater London N4 2DR",
    "addr:housenumber":"114",
    "addr:postcode":"n4 2dr",
    "addr:street":"Blackstock Road",
    "iso:country":"GB",
    "sg:address":"114 Blackstock Road",
    "sg:city":"London",
    "sg:classifiers":[
        {
            "category":"Real Estate",
            "subcategory":"Real Estate Agent",
            "type":"Services"
        }
    ],
    "sg:phone":"+44 20 7226 0711",
    "sg:postcode":"N4 2DR",
    "sg:province":"Greater London",
    "wof:name":"Anthony Garfield & Co",
    "wof:placetype":"venue"
},
  "geometry": {"coordinates":[-0.1001809984,51.5619049072],"type":"Point"}
}