{
  "type": "Feature",
  "properties": {
    "iso:country":"GB",
    "sg:address":"Units 1 & 2 Sidings Road",
    "sg:city":"Fleetwood",
    "sg:classifiers":[
        {
            "category":"Manufacturing",
            "subcategory":"Metals",
            "type":"Manufacturing & Wholesale Goods"
        }
    ],
    "sg:phone":"+44 1253 777074",
    "sg:postcode":"FY7 6NS",
    "sg:province":"Lancashire",
    "sg:tags":[
        "work",
        "sheet"
    ],
    "wof:name":"D Strickland Ltd.",
    "wof:placetype":"venue"
},
  "geometry": {"coordinates":[-3.01667,53.91856],"type":"Point"}
}