{
  "type": "Feature",
  "properties": {
    "addr:full":"Rookery Farm, East End, North Crawley Newport Pagnell Buckinghamshire MK16 9HW",
    "addr:postcode":"mk16 9hw",
    "iso:country":"GB",
    "sg:address":"Rookery Farm, East End, North Crawley",
    "sg:city":"Newport Pagnell",
    "sg:classifiers":[
        {
            "category":"Transit Center",
            "subcategory":"Passenger",
            "type":"Transportation"
        }
    ],
    "sg:phone":"+44 1234 391219",
    "sg:postcode":"MK16 9HW",
    "sg:province":"Buckinghamshire",
    "sg:tags":[
        "boarding",
        "kennel",
        "catteries"
    ],
    "wof:name":"Rookery Farm Kennels Ltd",
    "wof:placetype":"venue"
},
  "geometry": {"coordinates":[-0.62535,52.092739],"type":"Point"}
}