{
  "type": "Feature",
  "properties": {
    "addr:full":"Lords Meadow Industrial Estate, Marsh End Crediton Devon EX17 1DN",
    "addr:housenumber":"estate",
    "addr:postcode":"ex17 1dn",
    "addr:street":"Lords Meadow Industrial;Marsh End",
    "iso:country":"GB",
    "sg:address":"Lords Meadow Industrial Estate, Marsh End",
    "sg:city":"Crediton",
    "sg:classifiers":[
        {
            "category":"Manufacturing",
            "subcategory":"Metals",
            "type":"Manufacturing & Wholesale Goods"
        }
    ],
    "sg:phone":"+44 1363 773562",
    "sg:postcode":"EX17 1DN",
    "sg:province":"Devon",
    "sg:tags":[
        "blacksmith",
        "forgemasters"
    ],
    "wof:name":"Phoenix Forge",
    "wof:placetype":"venue"
},
  "geometry": {"coordinates":[-3.661404,50.790836],"type":"Point"}
}