{
  "type": "Feature",
  "properties": {
    "addr:full":"Unit 14, Northpoint Business Estate, Enterprise Close, Medway City Estate Rochester Kent ME2 4LX",
    "addr:housenumber":"unit 14",
    "addr:postcode":"me2 4lx",
    "addr:street":"Enterprise Close",
    "iso:country":"GB",
    "sg:address":"Unit 14, Northpoint Business Estate, Enterprise Close, Medway City Estate",
    "sg:city":"Rochester",
    "sg:classifiers":[
        {
            "category":"Retail",
            "subcategory":"Repair Shop",
            "type":"Services"
        },
        {
            "category":"Manufacturing",
            "subcategory":"Retail Goods",
            "type":"Manufacturing & Wholesale Goods"
        }
    ],
    "sg:phone":"+44 1634 295233",
    "sg:postcode":"ME2 4LX",
    "sg:province":"Kent",
    "sg:tags":[
        "ship",
        "chandler"
    ],
    "wof:name":"Pirates Cave Ltd",
    "wof:placetype":"venue"
},
  "geometry": {"coordinates":[0.4887830019,51.3963699341],"type":"Point"}
}