{
  "type": "Feature",
  "properties": {
    "iso:country":"GB",
    "sg:address":"11 Goodwin Street",
    "sg:city":"London",
    "sg:classifiers":[
        {
            "category":"Organizations",
            "subcategory":"Non-profit Organization",
            "type":"Services"
        }
    ],
    "sg:phone":"+44 20 7281 0297",
    "sg:postcode":"N4 3HQ",
    "sg:province":"Greater London",
    "sg:tags":[
        "organisation",
        "voluntary",
        "charity"
    ],
    "wof:name":"Trust for Research Into Arms Trade",
    "wof:placetype":"venue"
},
  "geometry": {"coordinates":[-0.1079899967,51.5641059875],"type":"Point"}
}