{
  "type": "Feature",
  "properties": {
    "iso:country":"GB",
    "sg:address":"Flat2-23 Haven Bank",
    "sg:city":"Boston",
    "sg:classifiers":[
        {
            "category":"Building & Trades",
            "subcategory":"Construction",
            "type":"Services"
        }
    ],
    "sg:postcode":"PE21 8SB",
    "sg:province":"Lincolnshire",
    "sg:tags":[
        "builder"
    ],
    "wof:name":"T A Hall",
    "wof:placetype":"venue"
},
  "geometry": {"coordinates":[-0.0291239992,52.974697113],"type":"Point"}
}