{
  "type": "Feature",
  "properties": {
    "addr:full":"Grange Farm, Little Houghton Northampton Buckinghamshire NN7 1AJ",
    "addr:postcode":"nn7 1aj",
    "iso:country":"GB",
    "sg:address":"Grange Farm, Little Houghton",
    "sg:city":"Northampton",
    "sg:classifiers":[
        {
            "category":"Farming",
            "subcategory":"Farm",
            "type":"Manufacturing & Wholesale Goods"
        }
    ],
    "sg:phone":"+44 1604 890271",
    "sg:postcode":"NN7 1AJ",
    "sg:province":"Buckinghamshire",
    "sg:tags":[
        "mixed",
        "crop"
    ],
    "wof:name":"J Arrowsmith",
    "wof:placetype":"venue"
},
  "geometry": {"coordinates":[-0.8249890208,52.2294235229],"type":"Point"}
}