{
  "type": "Feature",
  "properties": {
    "iso:country":"GB",
    "sg:address":"173b Spring Hall Lane",
    "sg:city":"Halifax",
    "sg:classifiers":[
        {
            "category":"Shopping",
            "subcategory":"Pharmacy",
            "type":"Retail Goods"
        }
    ],
    "sg:phone":"+44 1422 354616",
    "sg:postcode":"HX1 4JG",
    "sg:province":"West Yorkshire",
    "sg:tags":[
        "pharmacist",
        "chemist"
    ],
    "wof:name":"T W Leach Ltd.",
    "wof:placetype":"venue"
},
  "geometry": {"coordinates":[-1.89260602,53.7216148376],"type":"Point"}
}