{
  "type": "Feature",
  "properties": {
    "iso:country":"GB",
    "sg:address":"7 Market Street",
    "sg:city":"Hexham",
    "sg:classifiers":[
        {
            "category":"Shopping",
            "subcategory":"Comic Books",
            "type":"Retail Goods"
        }
    ],
    "sg:postcode":"NE46 3NS",
    "sg:province":"Northumberland",
    "sg:tags":[
        "jeweller"
    ],
    "wof:name":"Harris Jewellers Hexham",
    "wof:placetype":"venue"
},
  "geometry": {"coordinates":[-2.1020350456,54.9723892212],"type":"Point"}
}