{
  "type": "Feature",
  "properties": {
    "addr:full":"12 Upper Hollingdean Road Brighton East Sussex BN1 7GA",
    "addr:housenumber":"12",
    "addr:postcode":"bn1 7ga",
    "addr:street":"Upper Hollingdean Road",
    "iso:country":"GB",
    "sg:address":"12 Upper Hollingdean Road",
    "sg:city":"Brighton",
    "sg:classifiers":[
        {
            "category":"Banks & Credit Unions",
            "subcategory":"Atm",
            "type":"Services"
        }
    ],
    "sg:phone":"+44 1273 551379",
    "sg:postcode":"BN1 7GA",
    "sg:province":"East Sussex",
    "sg:tags":[
        "carburettor"
    ],
    "wof:name":"Formula One",
    "wof:placetype":"venue"
},
  "geometry": {"coordinates":[-0.1325020045,50.840259552],"type":"Point"}
}