{
  "type": "Feature",
  "properties": {
    "addr:full":"Birmingham Road, Pathlow Stratford-upon-avon Warwickshire CV37 0ES",
    "addr:postcode":"cv37 0es",
    "addr:street":"Birmingham Road",
    "iso:country":"GB",
    "sg:address":"Birmingham Road, Pathlow",
    "sg:city":"Stratford-upon-avon",
    "sg:classifiers":[
        {
            "category":"Bars & Pubs",
            "type":"Food & Drink"
        }
    ],
    "sg:phone":"+44 1789 297057",
    "sg:postcode":"CV37 0ES",
    "sg:province":"Warwickshire",
    "sg:tags":[
        "pubs",
        "inn"
    ],
    "wof:name":"The Dun Cow",
    "wof:placetype":"venue"
},
  "geometry": {"coordinates":[-1.739289,52.224915],"type":"Point"}
}