{
  "type": "Feature",
  "properties": {
    "addr:full":"Unit 2 Tir Llwyd Enterprise Park Rhyl Conwy LL18 5JA",
    "addr:housenumber":"unit 2",
    "addr:postcode":"ll18 5ja",
    "addr:street":"Tir Llwyd Enterprise Park",
    "iso:country":"GB",
    "sg:address":"Unit 2 Tir Llwyd Enterprise Park",
    "sg:city":"Rhyl",
    "sg:classifiers":[
        {
            "category":"Professional",
            "subcategory":"Business Services",
            "type":"Services"
        }
    ],
    "sg:phone":"+44 1745 360366",
    "sg:postcode":"LL18 5JA",
    "sg:province":"Conwy",
    "sg:tags":[
        "distribution"
    ],
    "wof:name":"Ravenscroft & Thackeray",
    "wof:placetype":"venue"
},
  "geometry": {"coordinates":[-3.5161790848,53.2976417542],"type":"Point"}
}