{
  "type": "Feature",
  "properties": {
    "addr:full":"144 Avenue Rd, Portswood Southampton Hampshire SO14 6UA",
    "addr:housenumber":"144",
    "addr:postcode":"so14 6ua",
    "addr:street":"Avenue Rd",
    "iso:country":"GB",
    "sg:address":"144 Avenue Rd, Portswood",
    "sg:city":"Southampton",
    "sg:classifiers":[
        {
            "category":"Professional",
            "subcategory":"Engineering",
            "type":"Services"
        }
    ],
    "sg:phone":"+44 23 8034 8000",
    "sg:postcode":"SO14 6UA",
    "sg:province":"Hampshire",
    "sg:tags":[
        "contractor",
        "electrical",
        "engineer"
    ],
    "wof:name":"D.P Lighting Supplies",
    "wof:placetype":"venue"
},
  "geometry": {"coordinates":[-1.3957480192,50.9210891724],"type":"Point"}
}