{
  "type": "Feature",
  "properties": {
    "addr:full":"7 Abbots Terrace, Parkgate Rd Chester Cheshire CH1 4AZ",
    "addr:housenumber":"7",
    "addr:postcode":"ch1 4az",
    "addr:street":"Abbots Terrace Parkgate Rd",
    "iso:country":"GB",
    "sg:address":"7 Abbots Terrace, Parkgate Rd",
    "sg:city":"Chester",
    "sg:classifiers":[
        {
            "category":"Retail",
            "subcategory":"Auto Rental",
            "type":"Services"
        }
    ],
    "sg:phone":"+44 1244 375537",
    "sg:postcode":"CH1 4AZ",
    "sg:province":"Cheshire",
    "sg:tags":[
        "car"
    ],
    "wof:name":"Jasmor Rent A Car",
    "wof:placetype":"venue"
},
  "geometry": {"coordinates":[-2.8970799446,53.2028541565],"type":"Point"}
}