{
  "type": "Feature",
  "properties": {
    "addr:full":"20 Bellevue Park Bristol City of Bristol BS4 4JR",
    "addr:housenumber":"20",
    "addr:postcode":"bs4 4jr",
    "addr:street":"Bellevue Park",
    "iso:country":"GB",
    "sg:address":"20 Bellevue Park",
    "sg:city":"Bristol",
    "sg:classifiers":[
        {
            "category":"Shopping",
            "subcategory":"Musical Instruments",
            "type":"Retail Goods"
        }
    ],
    "sg:phone":"+44 117 972 4160",
    "sg:postcode":"BS4 4JR",
    "sg:province":"City of Bristol",
    "wof:name":"A Bryant",
    "wof:placetype":"venue"
},
  "geometry": {"coordinates":[-2.5487220287,51.4359741211],"type":"Point"}
}