{
  "type": "Feature",
  "properties": {
    "iso:country":"GB",
    "sg:address":"30 Gordon Street",
    "sg:city":"Huntly",
    "sg:classifiers":[
        {
            "category":"Personal",
            "subcategory":"Barber",
            "type":"Services"
        }
    ],
    "sg:phone":"+44 1466 793900",
    "sg:postcode":"AB54 8EQ",
    "sg:province":"Aberdeenshire",
    "sg:tags":[
        "men's",
        "hairdresser"
    ],
    "wof:name":"Chaps",
    "wof:placetype":"venue"
},
  "geometry": {"coordinates":[-2.7874701023,57.446231842],"type":"Point"}
}