{
  "type": "Feature",
  "properties": {
    "addr:full":"105 Town Street, Stanningley Pudsey West Yorkshire LS28 6ES",
    "addr:housenumber":"105",
    "addr:postcode":"ls28 6es",
    "addr:street":"Town Street;West",
    "iso:country":"GB",
    "sg:address":"105 Town Street, Stanningley",
    "sg:city":"Pudsey",
    "sg:classifiers":[
        {
            "category":"Real Estate",
            "subcategory":"Real Estate Services",
            "type":"Services"
        },
        {
            "category":"Building & Trades",
            "subcategory":"Construction",
            "type":"Services"
        }
    ],
    "sg:phone":"+44 113 256 4890",
    "sg:postcode":"LS28 6ES",
    "sg:province":"West Yorkshire",
    "sg:tags":[
        "equipment",
        "plant",
        "leasing",
        "hire"
    ],
    "wof:name":"Moat Plant Hire Ltd",
    "wof:placetype":"venue"
},
  "geometry": {"coordinates":[-1.6637250185,53.8063621521],"type":"Point"}
}