{
  "type": "Feature",
  "properties": {
    "addr:full":"249 Albert Road Southsea Hampshire PO4 0JR",
    "addr:housenumber":"249",
    "addr:postcode":"po4 0jr",
    "addr:street":"Albert Road",
    "iso:country":"GB",
    "sg:address":"249 Albert Road",
    "sg:city":"Southsea",
    "sg:classifiers":[
        {
            "category":"Government",
            "subcategory":"Customs House",
            "type":"Public Place"
        }
    ],
    "sg:postcode":"PO4 0JR",
    "sg:province":"Hampshire",
    "sg:tags":[
        "clearance"
    ],
    "wof:name":"Jims",
    "wof:placetype":"venue"
},
  "geometry": {"coordinates":[-1.0709760189,50.7864646912],"type":"Point"}
}