{
  "type": "Feature",
  "properties": {
    "iso:country":"GB",
    "sg:address":"Hillsborough Road",
    "sg:city":"Ilfracombe",
    "sg:classifiers":[
        {
            "category":"Real Estate",
            "subcategory":"Real Estate Agent",
            "type":"Services"
        },
        {
            "category":"Retail",
            "subcategory":"Auto Repair",
            "type":"Services"
        }
    ],
    "sg:phone":"+44 1271 862717",
    "sg:postcode":"EX34 9NW",
    "sg:province":"Devon",
    "sg:tags":[
        "modification",
        "garage"
    ],
    "wof:name":"Scarlet Pimpernel Cars Ltd.",
    "wof:placetype":"venue"
},
  "geometry": {"coordinates":[-4.109302,51.206535],"type":"Point"}
}