{
  "type": "Feature",
  "properties": {
    "addr:full":"84 Dunlin Road Hemel Hempstead Hertfordshire HP2 6LX",
    "addr:housenumber":"84",
    "addr:postcode":"hp2 6lx",
    "addr:street":"Dunlin Road",
    "iso:country":"GB",
    "sg:address":"84 Dunlin Road",
    "sg:city":"Hemel Hempstead",
    "sg:classifiers":[
        {
            "category":"Autos & Motor Vehicles",
            "subcategory":"Motorcycle Sales",
            "type":"Retail Goods"
        }
    ],
    "sg:postcode":"HP2 6LX",
    "sg:province":"Hertfordshire",
    "sg:tags":[
        "chauffeur",
        "driven",
        "car"
    ],
    "wof:name":"Executive Car Hire",
    "wof:placetype":"venue"
},
  "geometry": {"coordinates":[-0.464632,51.775253],"type":"Point"}
}