{
  "type": "Feature",
  "properties": {
    "iso:country":"GB",
    "sg:address":"20 Le Brun Road",
    "sg:city":"Eastbourne",
    "sg:classifiers":[
        {
            "category":"Social Services",
            "subcategory":"Retirement Home",
            "type":"Services"
        }
    ],
    "sg:postcode":"BN21 2HZ",
    "sg:province":"East Sussex",
    "sg:tags":[
        "residential",
        "care"
    ],
    "wof:name":"A Ferguson",
    "wof:placetype":"venue"
},
  "geometry": {"coordinates":[0.277567,50.777996],"type":"Point"}
}