{
  "type": "Feature",
  "properties": {
    "addr:full":"73 Church Street, Cogeshall Colchester Essex CO6 1UB",
    "addr:housenumber":"73",
    "addr:postcode":"co6 1ub",
    "addr:street":"Church Street;Colchester",
    "iso:country":"GB",
    "sg:address":"73 Church Street, Cogeshall",
    "sg:city":"Colchester",
    "sg:classifiers":[
        {
            "category":"Shopping",
            "subcategory":"Clothing, Apparel, & Fashions",
            "type":"Retail Goods"
        }
    ],
    "sg:phone":"+44 1376 561211",
    "sg:postcode":"CO6 1UB",
    "sg:province":"Essex",
    "sg:tags":[
        "shop",
        "menswear"
    ],
    "wof:name":"Hollington Brothers Ltd.",
    "wof:placetype":"venue"
},
  "geometry": {"coordinates":[0.6898009777,51.8734664917],"type":"Point"}
}