{
  "type": "Feature",
  "properties": {
    "addr:full":"15 Branch Road, Armley Leeds West Yorkshire LS12 3AQ",
    "addr:housenumber":"15",
    "addr:postcode":"ls12 3aq",
    "addr:street":"Branch Road",
    "iso:country":"GB",
    "sg:address":"15 Branch Road, Armley",
    "sg:city":"Leeds",
    "sg:classifiers":[
        {
            "category":"Recreation",
            "subcategory":"Fishing",
            "type":"Entertainment"
        }
    ],
    "sg:phone":"+44 113 279 0738",
    "sg:postcode":"LS12 3AQ",
    "sg:province":"West Yorkshire",
    "sg:tags":[
        "angling"
    ],
    "wof:name":"Armley Angling Centre",
    "wof:placetype":"venue"
},
  "geometry": {"coordinates":[-1.587651968,53.7977104187],"type":"Point"}
}