{
  "type": "Feature",
  "properties": {
    "iso:country":"GB",
    "sg:address":"10 John St",
    "sg:city":"Willenhall",
    "sg:classifiers":[
        {
            "category":"Home & Garden",
            "subcategory":"Building Materials",
            "type":"Retail Goods"
        }
    ],
    "sg:phone":"+44 1902 607576",
    "sg:postcode":"WV13 1PW",
    "sg:province":"West Midlands",
    "sg:tags":[
        "shutter",
        "door"
    ],
    "wof:name":"F And S Doors",
    "wof:placetype":"venue"
},
  "geometry": {"coordinates":[-2.052498,52.584312],"type":"Point"}
}