{
  "type": "Feature",
  "properties": {
    "addr:full":"Colonsay Road, Glenburn Paisley East Renfrewshire PA2 8HH",
    "addr:postcode":"pa2 8hh",
    "addr:street":"Colonsay Road;Paisley East",
    "iso:country":"GB",
    "sg:address":"Colonsay Road, Glenburn",
    "sg:city":"Paisley",
    "sg:classifiers":[
        {
            "category":"Farming",
            "subcategory":"Nursery",
            "type":"Manufacturing & Wholesale Goods"
        },
        {
            "category":"Government",
            "subcategory":"Office",
            "type":"Public Place"
        }
    ],
    "sg:phone":"+44 141 884 2020",
    "sg:postcode":"PA2 8HH",
    "sg:province":"East Renfrewshire",
    "sg:tags":[
        "local",
        "creche"
    ],
    "wof:name":"Glenburn Nursery",
    "wof:placetype":"venue"
},
  "geometry": {"coordinates":[-4.4317288399,55.822101593],"type":"Point"}
}