{
  "type": "Feature",
  "properties": {
    "iso:country":"GB",
    "sg:address":"224 - 236 Walworth Road",
    "sg:city":"London",
    "sg:classifiers":[
        {
            "category":"Organizations",
            "subcategory":"Non-profit Organization",
            "type":"Services"
        }
    ],
    "sg:phone":"+44 20 7701 9700",
    "sg:postcode":"SE17 1JE",
    "sg:province":"Greater London",
    "sg:tags":[
        "organisation",
        "voluntary",
        "charity"
    ],
    "wof:name":"Age Concern Southwark Services Ltd.",
    "wof:placetype":"venue"
},
  "geometry": {"coordinates":[-0.096119,51.488567],"type":"Point"}
}