{
  "type": "Feature",
  "properties": {
    "iso:country":"GB",
    "sg:address":"140 Old Church Road, Little Heath",
    "sg:city":"Coventry",
    "sg:classifiers":[
        {
            "category":"Health Services",
            "subcategory":"Nursing And Care Facility",
            "type":"Services"
        }
    ],
    "sg:phone":"+44 24 7663 8602",
    "sg:postcode":"CV6 7ED",
    "sg:province":"Warwickshire",
    "sg:tags":[
        "home"
    ],
    "wof:name":"Ultima Care Ltd.",
    "wof:placetype":"venue"
},
  "geometry": {"coordinates":[-1.4813710451,52.4392356873],"type":"Point"}
}