{
  "type": "Feature",
  "properties": {
    "iso:country":"GB",
    "sg:address":"Unit 6 Sunnyside Road North",
    "sg:city":"Weston Super Mare",
    "sg:classifiers":[
        {
            "category":"Wholesale",
            "subcategory":"Sporting Goods",
            "type":"Manufacturing & Wholesale Goods"
        }
    ],
    "sg:phone":"+44 1934 626560",
    "sg:postcode":"BS23 3PZ",
    "sg:province":"Somerset",
    "sg:tags":[
        "wholesaler",
        "mnfrs",
        "cycle"
    ],
    "wof:name":"Split Second Imports",
    "wof:placetype":"venue"
},
  "geometry": {"coordinates":[-2.972291,51.341442],"type":"Point"}
}