{
  "type": "Feature",
  "properties": {
    "addr:full":"76 Church La Stoke On Trent Staffordshire ST4 4QD",
    "addr:housenumber":"76",
    "addr:postcode":"st4 4qd",
    "addr:street":"Church La Stoke",
    "iso:country":"GB",
    "sg:address":"76 Church La",
    "sg:city":"Stoke On Trent",
    "sg:classifiers":[
        {
            "category":"Place Of Worship",
            "type":"Public Place"
        }
    ],
    "sg:phone":"+44 1782 657848",
    "sg:postcode":"ST4 4QD",
    "sg:province":"Staffordshire",
    "wof:name":"St Matthias C Of E Church",
    "wof:placetype":"venue"
},
  "geometry": {"coordinates":[-2.194883,52.980453],"type":"Point"}
}