{
  "type": "Feature",
  "properties": {
    "addr:full":"19 Moxon Gr Wakefield West Yorkshire WF1 2JF",
    "addr:housenumber":"19",
    "addr:postcode":"wf1 2jf",
    "addr:street":"Moxon Gr",
    "iso:country":"GB",
    "sg:address":"19 Moxon Gr",
    "sg:city":"Wakefield",
    "sg:classifiers":[
        {
            "category":"Building & Trades",
            "subcategory":"Construction",
            "type":"Services"
        }
    ],
    "sg:postcode":"WF1 2JF",
    "sg:province":"West Yorkshire",
    "sg:tags":[
        "builder"
    ],
    "wof:name":"Gary Melling Building Services",
    "wof:placetype":"venue"
},
  "geometry": {"coordinates":[-1.5053290129,53.7032394409],"type":"Point"}
}