{
  "type": "Feature",
  "properties": {
    "iso:country":"GB",
    "sg:address":"Units 1& 2 Merridian Centre, Belvoir Way",
    "sg:city":"Louth",
    "sg:classifiers":[
        {
            "category":"Manufacturing",
            "subcategory":"Tools & Machinery",
            "type":"Manufacturing & Wholesale Goods"
        }
    ],
    "sg:phone":"+44 1507 608880",
    "sg:postcode":"LN11 0LQ",
    "sg:province":"Lincolnshire",
    "sg:tags":[
        "machine",
        "cutting"
    ],
    "wof:name":"Container Technics Euro-Forme Ltd.",
    "wof:placetype":"venue"
},
  "geometry": {"coordinates":[-0.00439,53.37859],"type":"Point"}
}