{
  "type": "Feature",
  "properties": {
    "iso:country":"GB",
    "sg:address":"49 Brampton Road",
    "sg:city":"Cambridge",
    "sg:classifiers":[
        {
            "category":"Building & Trades",
            "subcategory":"Plumbing",
            "type":"Services"
        }
    ],
    "sg:postcode":"CB1 3HJ",
    "sg:province":"Cambridgeshire",
    "sg:tags":[
        "heating"
    ],
    "wof:name":"A Hughes",
    "wof:placetype":"venue"
},
  "geometry": {"coordinates":[0.1497640014,52.2044677734],"type":"Point"}
}