{
  "type": "Feature",
  "properties": {
    "iso:country":"GB",
    "sg:address":"Main Road, Frithville",
    "sg:city":"Boston",
    "sg:classifiers":[
        {
            "category":"Autos & Motor Vehicles",
            "subcategory":"Motorcycle Sales",
            "type":"Retail Goods"
        }
    ],
    "sg:phone":"+44 1205 750266",
    "sg:postcode":"PE22 7DT",
    "sg:province":"Lincolnshire",
    "wof:name":"Sam Coupland Motor Cycles Ltd.",
    "wof:placetype":"venue"
},
  "geometry": {"coordinates":[-0.031014,53.034698],"type":"Point"}
}