{
  "type": "Feature",
  "properties": {
    "addr:full":"Lord Wandsworth College, Long Sutton Hook Hampshire RG29 1TB",
    "addr:postcode":"rg29 1tb",
    "addr:street":"Lord",
    "iso:country":"GB",
    "sg:address":"Lord Wandsworth College, Long Sutton",
    "sg:city":"Hook",
    "sg:classifiers":[
        {
            "category":"Organizations",
            "subcategory":"Membership Organization",
            "type":"Services"
        }
    ],
    "sg:phone":"+44 1256 860356",
    "sg:postcode":"RG29 1TB",
    "sg:province":"Hampshire",
    "sg:tags":[
        "club"
    ],
    "wof:name":"The Sternians Association",
    "wof:placetype":"venue"
},
  "geometry": {"coordinates":[-0.9428160191,51.2206001282],"type":"Point"}
}