{
  "type": "Feature",
  "properties": {
    "addr:full":"86 Babbacombe Rd Torquay Devon TQ1 3SW",
    "addr:housenumber":"86",
    "addr:postcode":"tq1 3sw",
    "addr:street":"Babbacombe Rd",
    "iso:country":"GB",
    "sg:address":"86 Babbacombe Rd",
    "sg:city":"Torquay",
    "sg:classifiers":[
        {
            "category":"Health Services",
            "subcategory":"Podiatrist",
            "type":"Services"
        }
    ],
    "sg:phone":"+44 1803 325657",
    "sg:postcode":"TQ1 3SW",
    "sg:province":"Devon",
    "sg:tags":[
        "podiatrists",
        "chiropodist"
    ],
    "wof:name":"E Forrest",
    "wof:placetype":"venue"
},
  "geometry": {"coordinates":[-3.513075,50.477627],"type":"Point"}
}