{
  "type": "Feature",
  "properties": {
    "addr:full":"93b Whetstone Rd Farnborough Hampshire GU14 9SX",
    "addr:housenumber":"93b",
    "addr:postcode":"gu14 9sx",
    "addr:street":"Whetstone Rd",
    "iso:country":"GB",
    "sg:address":"93b Whetstone Rd",
    "sg:city":"Farnborough",
    "sg:classifiers":[
        {
            "category":"Shopping",
            "subcategory":"Used Merchandise",
            "type":"Retail Goods"
        }
    ],
    "sg:postcode":"GU14 9SX",
    "sg:province":"Hampshire",
    "sg:tags":[
        "furniture"
    ],
    "wof:name":"Seconds Out",
    "wof:placetype":"venue"
},
  "geometry": {"coordinates":[-0.7901970148,51.2967567444],"type":"Point"}
}