{
  "type": "Feature",
  "properties": {
    "addr:full":"23 Herbert Road Bexleyheath Kent DA7 4QE",
    "addr:housenumber":"23",
    "addr:postcode":"da7 4qe",
    "addr:street":"Herbert Road",
    "iso:country":"GB",
    "sg:address":"23 Herbert Road",
    "sg:city":"Bexleyheath",
    "sg:classifiers":[
        {
            "category":"Building & Trades",
            "subcategory":"Construction",
            "type":"Services"
        }
    ],
    "sg:phone":"+44 20 8298 0081",
    "sg:postcode":"DA7 4QE",
    "sg:province":"Kent",
    "sg:tags":[
        "bricklayer",
        "bricklaying"
    ],
    "wof:name":"John Gillespie",
    "wof:placetype":"venue"
},
  "geometry": {"coordinates":[0.13649,51.465916],"type":"Point"}
}