{
  "type": "Feature",
  "properties": {
    "addr:full":"Church House, Church Lane, Climping Littlehampton West Sussex BN17 5RB",
    "addr:postcode":"bn17 5rb",
    "addr:street":"Church Lane",
    "iso:country":"GB",
    "sg:address":"Church House, Church Lane, Climping",
    "sg:city":"Littlehampton",
    "sg:classifiers":[
        {
            "category":"Shopping",
            "subcategory":"Bicycles & Sporting Goods",
            "type":"Retail Goods"
        }
    ],
    "sg:postcode":"BN17 5RB",
    "sg:province":"West Sussex",
    "sg:tags":[
        "equipment",
        "marine",
        "supply"
    ],
    "wof:name":"M E S Ltd.",
    "wof:placetype":"venue"
},
  "geometry": {"coordinates":[-0.5765910149,50.8101043701],"type":"Point"}
}