{
  "type": "Feature",
  "properties": {
    "addr:full":"Unit 1 Faulkner Lane, College Farm Industrial Estate Sandown Isle of Wight PO36 9AZ",
    "addr:housenumber":"unit 1;industrial estate",
    "addr:postcode":"po36 9az",
    "addr:street":"Faulkner Lane College",
    "iso:country":"GB",
    "sg:address":"Unit 1 Faulkner Lane, College Farm Industrial Estate",
    "sg:city":"Sandown",
    "sg:classifiers":[
        {
            "category":"Food & Beverages",
            "subcategory":"Bakery",
            "type":"Retail Goods"
        }
    ],
    "sg:postcode":"PO36 9AZ",
    "sg:province":"Isle of Wight",
    "sg:tags":[
        "confectionery"
    ],
    "wof:name":"Pema Bakery",
    "wof:placetype":"venue"
},
  "geometry": {"coordinates":[-1.1503330469,50.6624794006],"type":"Point"}
}