{
  "type": "Feature",
  "properties": {
    "iso:country":"GB",
    "sg:address":"16 Tamar Clo",
    "sg:city":"High Wycombe",
    "sg:classifiers":[
        {
            "category":"Education",
            "subcategory":"Music School",
            "type":"Public Place"
        }
    ],
    "sg:phone":"+44 1494 813542",
    "sg:postcode":"HP13 7BG",
    "sg:province":"Buckinghamshire",
    "sg:tags":[
        "conservatory"
    ],
    "wof:name":"Tamar Conservatories & Windows",
    "wof:placetype":"venue"
},
  "geometry": {"coordinates":[-0.7028579712,51.6176528931],"type":"Point"}
}