{
  "type": "Feature",
  "properties": {
    "addr:full":"19 Alice Lane, Burnham Slough Berkshire SL1 7AY",
    "addr:housenumber":"19",
    "addr:postcode":"sl1 7ay",
    "addr:street":"Alice Lane",
    "iso:country":"GB",
    "sg:address":"19 Alice Lane, Burnham",
    "sg:city":"Slough",
    "sg:classifiers":[
        {
            "category":"Autos & Motor Vehicles",
            "subcategory":"Auto Supplies",
            "type":"Retail Goods"
        }
    ],
    "sg:phone":"+44 1753 825085",
    "sg:postcode":"SL1 7AY",
    "sg:province":"Berkshire",
    "sg:tags":[
        "tyre"
    ],
    "wof:name":"Tyred Out",
    "wof:placetype":"venue"
},
  "geometry": {"coordinates":[-0.665666,51.531586],"type":"Point"}
}