{
  "type": "Feature",
  "properties": {
    "addr:full":"15 Victoria Ave Saffron Walden Essex CB11 3AD",
    "addr:housenumber":"15",
    "addr:postcode":"cb11 3ad",
    "addr:street":"Victoria Ave",
    "iso:country":"GB",
    "sg:address":"15 Victoria Ave",
    "sg:city":"Saffron Walden",
    "sg:classifiers":[
        {
            "category":"Building & Trades",
            "subcategory":"Construction",
            "type":"Services"
        }
    ],
    "sg:postcode":"CB11 3AD",
    "sg:province":"Essex",
    "sg:tags":[
        "decorator",
        "painter"
    ],
    "wof:name":"Purkiss,Neil,",
    "wof:placetype":"venue"
},
  "geometry": {"coordinates":[0.2464890033,52.0190010071],"type":"Point"}
}