{
  "type": "Feature",
  "properties": {
    "addr:full":"151b High Street, Kings Heath Birmingham West Midlands B14 7DG",
    "addr:housenumber":"151b",
    "addr:postcode":"b14 7dg",
    "addr:street":"High Street",
    "iso:country":"GB",
    "sg:address":"151b High Street, Kings Heath",
    "sg:city":"Birmingham",
    "sg:classifiers":[
        {
            "category":"Fast Food",
            "type":"Food & Drink"
        }
    ],
    "sg:phone":"+44 121 444 1994",
    "sg:postcode":"B14 7DG",
    "sg:province":"West Midlands",
    "sg:tags":[
        "away",
        "take"
    ],
    "wof:name":"MCDONALDS RESTAURANTS LTD",
    "wof:placetype":"venue"
},
  "geometry": {"coordinates":[-1.892779,52.43409],"type":"Point"}
}