{
  "type": "Feature",
  "properties": {
    "iso:country":"GB",
    "sg:address":"80 Outram St",
    "sg:city":"Sutton In Ashfield",
    "sg:classifiers":[
        {
            "category":"Home & Garden",
            "subcategory":"Home Furnishings",
            "type":"Retail Goods"
        }
    ],
    "sg:phone":"+44 1623 557750",
    "sg:postcode":"NG17 4FS",
    "sg:province":"Nottinghamshire",
    "sg:tags":[
        "homefurnishings"
    ],
    "wof:name":"JWS Fitted Bedrooms",
    "wof:placetype":"venue"
},
  "geometry": {"coordinates":[-1.25605,53.128498],"type":"Point"}
}