{
  "type": "Feature",
  "properties": {
    "addr:full":"417-419 New Cross Road London Greater London SE14 6TA",
    "addr:housenumber":"417-419",
    "addr:postcode":"se14 6ta",
    "addr:street":"New Cross Road",
    "iso:country":"GB",
    "sg:address":"417-419 New Cross Road",
    "sg:city":"London",
    "sg:classifiers":[
        {
            "category":"Building & Trades",
            "subcategory":"Construction",
            "type":"Services"
        }
    ],
    "sg:phone":"+44 20 8692 4443",
    "sg:postcode":"SE14 6TA",
    "sg:province":"Greater London",
    "sg:tags":[
        "builder"
    ],
    "wof:name":"Sames Holdings Ltd.",
    "wof:placetype":"venue"
},
  "geometry": {"coordinates":[-0.031528,51.475903],"type":"Point"}
}