{
  "type": "Feature",
  "properties": {
    "addr:full":"69 Ruxley Lane Epsom Surrey KT19 0JG",
    "addr:housenumber":"69",
    "addr:postcode":"kt19 0jg",
    "addr:street":"Ruxley Lane",
    "iso:country":"GB",
    "sg:address":"69 Ruxley Lane",
    "sg:city":"Epsom",
    "sg:classifiers":[
        {
            "category":"Home & Garden",
            "subcategory":"Household Appliances",
            "type":"Retail Goods"
        }
    ],
    "sg:postcode":"KT19 0JG",
    "sg:province":"Surrey",
    "sg:tags":[
        "electrical"
    ],
    "wof:name":"Robinson's Vacuum Cleaner Services",
    "wof:placetype":"venue"
},
  "geometry": {"coordinates":[-0.2691789865,51.3643112183],"type":"Point"}
}