{
  "type": "Feature",
  "properties": {
    "addr:full":"Pathbrae Industrial Estate, New Cumnock Cumnock East Ayrshire KA18 4DF",
    "addr:postcode":"ka18 4df",
    "addr:street":"Estate;Cumnock Cumnock East",
    "iso:country":"GB",
    "sg:address":"Pathbrae Industrial Estate, New Cumnock",
    "sg:city":"Cumnock",
    "sg:classifiers":[
        {
            "category":"Freight",
            "type":"Transportation"
        }
    ],
    "sg:postcode":"KA18 4DF",
    "sg:province":"East Ayrshire",
    "sg:tags":[
        "haulage",
        "road"
    ],
    "wof:name":"Watson Haulage",
    "wof:placetype":"venue"
},
  "geometry": {"coordinates":[-4.1835689545,55.3990058899],"type":"Point"}
}