{
  "type": "Feature",
  "properties": {
    "addr:full":"42 Stockport Road Ashton-under-lyne Greater Manchester OL7 0LD",
    "addr:housenumber":"42",
    "addr:postcode":"ol7 0ld",
    "addr:street":"Stockport Road",
    "iso:country":"GB",
    "sg:address":"42 Stockport Road",
    "sg:city":"Ashton-under-lyne",
    "sg:classifiers":[
        {
            "category":"Retail",
            "subcategory":"Repair Shop",
            "type":"Services"
        }
    ],
    "sg:phone":"+44 161 344 5616",
    "sg:postcode":"OL7 0LD",
    "sg:province":"Greater Manchester",
    "sg:tags":[
        "upholsterer"
    ],
    "wof:name":"G K Furnishings",
    "wof:placetype":"venue"
},
  "geometry": {"coordinates":[-2.107054,53.481567],"type":"Point"}
}