{
  "type": "Feature",
  "properties": {
    "addr:full":"45 The Shires Trowbridge Wiltshire BA14 8AT",
    "addr:housenumber":"45",
    "addr:postcode":"ba14 8at",
    "addr:street":"The Shires",
    "iso:country":"GB",
    "sg:address":"45 The Shires",
    "sg:city":"Trowbridge",
    "sg:classifiers":[
        {
            "category":"Shopping",
            "subcategory":"Hobbies, Toys, & Games",
            "type":"Retail Goods"
        }
    ],
    "sg:phone":"+44 1225 774223",
    "sg:postcode":"BA14 8AT",
    "sg:province":"Wiltshire",
    "sg:tags":[
        "shop",
        "toy",
        "sale"
    ],
    "sg:website":"http://www.elc.co.uk",
    "wof:name":"EARLY LEARNING CENTRE LTD",
    "wof:placetype":"venue"
},
  "geometry": {"coordinates":[-2.208231926,51.3202781677],"type":"Point"}
}