{
  "type": "Feature",
  "properties": {
    "addr:full":"Springfield, Rectory Road, Orsett Grays Essex RM16 3JU",
    "addr:postcode":"rm16 3ju",
    "addr:street":"Rectory Road",
    "iso:country":"GB",
    "sg:address":"Springfield, Rectory Road, Orsett",
    "sg:city":"Grays",
    "sg:classifiers":[
        {
            "category":"Real Estate",
            "subcategory":"Surveying",
            "type":"Services"
        }
    ],
    "sg:postcode":"RM16 3JU",
    "sg:province":"Essex",
    "sg:tags":[
        "surveyor",
        "valuer"
    ],
    "wof:name":"Barnetts Chartered Surveyors",
    "wof:placetype":"venue"
},
  "geometry": {"coordinates":[0.3667750061,51.5123214722],"type":"Point"}
}