{
  "type": "Feature",
  "properties": {
    "addr:full":"56a Bensham Gro Thornton Heath Surrey CR7 8DA",
    "addr:housenumber":"56a",
    "addr:postcode":"cr7 8da",
    "addr:street":"Bensham Gro",
    "iso:country":"GB",
    "sg:address":"56a Bensham Gro",
    "sg:city":"Thornton Heath",
    "sg:classifiers":[
        {
            "category":"Professional",
            "subcategory":"Engineering",
            "type":"Services"
        }
    ],
    "sg:postcode":"CR7 8DA",
    "sg:province":"Surrey",
    "sg:tags":[
        "precision",
        "engineer"
    ],
    "wof:name":"Beckenham Engineering",
    "wof:placetype":"venue"
},
  "geometry": {"coordinates":[-0.100972,51.405739],"type":"Point"}
}