{
  "type": "Feature",
  "properties": {
    "iso:country":"GB",
    "sg:address":"Saughton Goods Yd, Saughton Mains St",
    "sg:city":"Edinburgh",
    "sg:classifiers":[
        {
            "category":"Retail",
            "subcategory":"Auto Repair",
            "type":"Services"
        }
    ],
    "sg:postcode":"EH11 3QX",
    "sg:province":"City of Edinburgh",
    "sg:tags":[
        "modification",
        "garage"
    ],
    "wof:name":"G B Car Breakers",
    "wof:placetype":"venue"
},
  "geometry": {"coordinates":[-3.249994,55.938126],"type":"Point"}
}