{
  "type": "Feature",
  "properties": {
    "addr:full":"52 St Helens Street Derby Derbyshire DE1 1HT",
    "addr:housenumber":"52",
    "addr:postcode":"de1 1ht",
    "addr:street":"St Helens Street",
    "iso:country":"GB",
    "sg:address":"52 St Helens Street",
    "sg:city":"Derby",
    "sg:classifiers":[
        {
            "category":"Organizations",
            "subcategory":"Non-profit Organization",
            "type":"Services"
        }
    ],
    "sg:phone":"+44 1332 366780",
    "sg:postcode":"DE1 1HT",
    "sg:province":"Derbyshire",
    "sg:tags":[
        "organisation",
        "voluntary",
        "charity"
    ],
    "wof:name":"Padley Recycling",
    "wof:placetype":"venue"
},
  "geometry": {"coordinates":[-1.48147,52.926849],"type":"Point"}
}