{
  "type": "Feature",
  "properties": {
    "iso:country":"GB",
    "sg:address":"L21b Waverley Shopping Centre, Waverley Bridge",
    "sg:city":"Edinburgh",
    "sg:classifiers":[
        {
            "category":"Shopping",
            "subcategory":"Clothing, Apparel, & Fashions",
            "type":"Retail Goods"
        }
    ],
    "sg:phone":"+44 131 558 8898",
    "sg:postcode":"EH1 1BQ",
    "sg:province":"City of Edinburgh",
    "sg:tags":[
        "shop",
        "ladieswear"
    ],
    "wof:name":"Xile Woman",
    "wof:placetype":"venue"
},
  "geometry": {"coordinates":[-3.19198,55.952579],"type":"Point"}
}