{
  "type": "Feature",
  "properties": {
    "addr:full":"34 Brinkhall Way, Welton Lincoln Lincolnshire LN2 3NS",
    "addr:housenumber":"34",
    "addr:postcode":"ln2 3ns",
    "addr:street":"Brinkhall Way",
    "iso:country":"GB",
    "sg:address":"34 Brinkhall Way, Welton",
    "sg:city":"Lincoln",
    "sg:classifiers":[
        {
            "category":"Retail",
            "subcategory":"Driving School",
            "type":"Services"
        }
    ],
    "sg:phone":"+44 1673 862710",
    "sg:postcode":"LN2 3NS",
    "sg:province":"Lincolnshire",
    "wof:name":"Ted Gant",
    "wof:placetype":"venue"
},
  "geometry": {"coordinates":[-0.480091989,53.3093986511],"type":"Point"}
}