{
  "type": "Feature",
  "properties": {
    "iso:country":"GB",
    "sg:address":"Unit 18 Shopping Precinct, Rochdale Road, Royton",
    "sg:city":"Oldham",
    "sg:classifiers":[
        {
            "category":"Food & Beverages",
            "subcategory":"Meat & Fish",
            "type":"Retail Goods"
        }
    ],
    "sg:phone":"+44 161 624 2786",
    "sg:postcode":"OL2 6QJ",
    "sg:province":"Lancashire",
    "sg:tags":[
        "butcher"
    ],
    "wof:name":"The Quality Meat Shop",
    "wof:placetype":"venue"
},
  "geometry": {"coordinates":[-2.09683,53.579021],"type":"Point"}
}