{
  "type": "Feature",
  "properties": {
    "addr:full":"Hobson Moor Road, Mottram Hyde Cheshire SK14 6SG",
    "addr:postcode":"sk14 6sg",
    "addr:street":"Hobson Moor Road",
    "iso:country":"GB",
    "sg:address":"Hobson Moor Road, Mottram",
    "sg:city":"Hyde",
    "sg:classifiers":[
        {
            "category":"Travel",
            "subcategory":"Hotels & Motels",
            "type":"Entertainment"
        }
    ],
    "sg:phone":"+44 1457 766188",
    "sg:postcode":"SK14 6SG",
    "sg:province":"Cheshire",
    "sg:tags":[
        "self",
        "catering"
    ],
    "wof:name":"Hollingworth Hall",
    "wof:placetype":"venue"
},
  "geometry": {"coordinates":[-2.010145,53.469955],"type":"Point"}
}