{
  "type": "Feature",
  "properties": {
    "iso:country":"GB",
    "sg:address":"Engineering Works, Bankhead Indust Estate, Bucksburn",
    "sg:city":"Aberdeen",
    "sg:classifiers":[
        {
            "category":"Farming",
            "subcategory":"Farm",
            "type":"Manufacturing & Wholesale Goods"
        }
    ],
    "sg:phone":"+44 1224 716222",
    "sg:postcode":"AB21 9ET",
    "sg:province":"Aberdeen City",
    "sg:tags":[
        "agricultural"
    ],
    "wof:name":"R S Machine Tools",
    "wof:placetype":"venue"
},
  "geometry": {"coordinates":[-2.1816599369,57.1781387329],"type":"Point"}
}