{
  "type": "Feature",
  "properties": {
    "iso:country":"GB",
    "sg:address":"Upper Ashwood Park Farm",
    "sg:city":"Leominster",
    "sg:classifiers":[
        {
            "category":"Farming",
            "subcategory":"Poultry Farm",
            "type":"Manufacturing & Wholesale Goods"
        }
    ],
    "sg:phone":"+44 1584 711276",
    "sg:postcode":"HR6 0DN",
    "sg:province":"Herefordshire",
    "sg:tags":[
        "game"
    ],
    "wof:name":"Sun Valley Foods Ltd.",
    "wof:placetype":"venue"
},
  "geometry": {"coordinates":[-2.71242,52.276649],"type":"Point"}
}