{
  "type": "Feature",
  "properties": {
    "addr:full":"41 Meadow Road Kettering Northamptonshire NN16 8TN",
    "addr:housenumber":"41",
    "addr:postcode":"nn16 8tn",
    "addr:street":"Meadow Road",
    "iso:country":"GB",
    "sg:address":"41 Meadow Road",
    "sg:city":"Kettering",
    "sg:classifiers":[
        {
            "category":"Professional",
            "subcategory":"Lawyer & Legal Services",
            "type":"Services"
        }
    ],
    "sg:postcode":"NN16 8TN",
    "sg:province":"Northamptonshire",
    "sg:tags":[
        "solicitor"
    ],
    "wof:name":"Wilson Browne",
    "wof:placetype":"venue"
},
  "geometry": {"coordinates":[-0.8065159917,52.4181098938],"type":"Point"}
}