{
  "type": "Feature",
  "properties": {
    "iso:country":"GB",
    "sg:address":"5-6 Bankside",
    "sg:city":"Kidlington",
    "sg:classifiers":[
        {
            "category":"Retail",
            "subcategory":"Auto Repair",
            "type":"Services"
        }
    ],
    "sg:phone":"+44 1865 375262",
    "sg:postcode":"OX5 1JE",
    "sg:province":"Buckinghamshire",
    "sg:tags":[
        "body",
        "car"
    ],
    "wof:name":"A J L Body Repairs",
    "wof:placetype":"venue"
},
  "geometry": {"coordinates":[-1.301229,51.829983],"type":"Point"}
}