{
  "type": "Feature",
  "properties": {
    "iso:country":"GB",
    "sg:address":"P O Box 135",
    "sg:city":"Tring",
    "sg:classifiers":[
        {
            "category":"Professional",
            "subcategory":"Management & Consulting",
            "type":"Services"
        }
    ],
    "sg:postcode":"HP23 5QH",
    "sg:province":"Buckinghamshire",
    "sg:tags":[
        "consultant",
        "promotion",
        "direct",
        "sale"
    ],
    "wof:name":"Barnes,Anthony,Associates",
    "wof:placetype":"venue"
},
  "geometry": {"coordinates":[-0.6025000215,51.8011016846],"type":"Point"}
}