{
  "type": "Feature",
  "properties": {
    "addr:full":"120 Chippenham Road London Greater London W9 2AD",
    "addr:housenumber":"120",
    "addr:postcode":"w9 2ad",
    "addr:street":"Chippenham Road",
    "iso:country":"GB",
    "sg:address":"120 Chippenham Road",
    "sg:city":"London",
    "sg:classifiers":[
        {
            "category":"Fast Food",
            "type":"Food & Drink"
        }
    ],
    "sg:phone":"+44 20 7266 3311",
    "sg:postcode":"W9 2AD",
    "sg:province":"Greater London",
    "sg:tags":[
        "away",
        "meal",
        "outlet",
        "take"
    ],
    "wof:name":"Dominos Pizza",
    "wof:placetype":"venue"
},
  "geometry": {"coordinates":[-0.1974299997,51.5273895264],"type":"Point"}
}