{
  "type": "Feature",
  "properties": {
    "iso:country":"GB",
    "sg:address":"20 Nelson St",
    "sg:city":"Kilmarnock",
    "sg:classifiers":[
        {
            "category":"Cafe",
            "type":"Food & Drink"
        }
    ],
    "sg:phone":"+44 1563 550021",
    "sg:postcode":"KA1 1BD",
    "sg:province":"East Ayrshire",
    "sg:tags":[
        "tea",
        "room"
    ],
    "wof:name":"Tea Parlour The",
    "wof:placetype":"venue"
},
  "geometry": {"coordinates":[-4.4994602203,55.6087684631],"type":"Point"}
}