{
  "type": "Feature",
  "properties": {
    "addr:full":"1/2 Rutland Buildings Bakewell Derbyshire DE45 1BZ",
    "addr:housenumber":"1 / 2;buildings",
    "addr:postcode":"de45 1bz",
    "addr:street":"Rutland",
    "iso:country":"GB",
    "sg:address":"1/2 Rutland Buildings",
    "sg:city":"Bakewell",
    "sg:classifiers":[
        {
            "category":"Shopping",
            "subcategory":"News",
            "type":"Retail Goods"
        }
    ],
    "sg:phone":"+44 1629 813025",
    "sg:postcode":"DE45 1BZ",
    "sg:province":"Derbyshire",
    "sg:tags":[
        "newsagent"
    ],
    "wof:name":"Bakewell Newsagents",
    "wof:placetype":"venue"
},
  "geometry": {"coordinates":[-1.6711109877,53.2136573792],"type":"Point"}
}