{
  "type": "Feature",
  "properties": {
    "iso:country":"GB",
    "sg:address":"The Fields Farm, Back Lane, Lower Peover",
    "sg:city":"Knutsford",
    "sg:classifiers":[
        {
            "category":"Transit Center",
            "subcategory":"Passenger",
            "type":"Transportation"
        }
    ],
    "sg:postcode":"WA16 9SG",
    "sg:province":"Cheshire",
    "sg:tags":[
        "boarding",
        "kennel",
        "catteries"
    ],
    "wof:name":"Peover Kennels",
    "wof:placetype":"venue"
},
  "geometry": {"coordinates":[-2.390905,53.263615],"type":"Point"}
}