{
  "type": "Feature",
  "properties": {
    "addr:full":"The Street, Bradfield Manningtree Essex CO11 2US",
    "addr:postcode":"co11 2us",
    "addr:street":"The Street",
    "iso:country":"GB",
    "sg:address":"The Street, Bradfield",
    "sg:city":"Manningtree",
    "sg:classifiers":[
        {
            "category":"Bars & Pubs",
            "type":"Food & Drink"
        }
    ],
    "sg:phone":"+44 1255 870304",
    "sg:postcode":"CO11 2US",
    "sg:province":"Essex",
    "sg:tags":[
        "pubs",
        "inn"
    ],
    "wof:name":"The Strangers Home",
    "wof:placetype":"venue"
},
  "geometry": {"coordinates":[1.116603,51.930923],"type":"Point"}
}