{
  "type": "Feature",
  "properties": {
    "iso:country":"GB",
    "sg:address":"19 Ospringe Place",
    "sg:city":"Faversham",
    "sg:classifiers":[
        {
            "category":"Manufacturing",
            "subcategory":"Paper Products",
            "type":"Manufacturing & Wholesale Goods"
        }
    ],
    "sg:postcode":"ME13 8TB",
    "sg:province":"Kent",
    "sg:tags":[
        "board"
    ],
    "wof:name":"Qualitas (Paper & Boards) Ltd.",
    "wof:placetype":"venue"
},
  "geometry": {"coordinates":[0.8779609799,51.3099937439],"type":"Point"}
}