{
  "type": "Feature",
  "properties": {
    "iso:country":"GB",
    "sg:address":"Unit 71 Centenary Market Hall, Howard Street",
    "sg:city":"Rotherham",
    "sg:classifiers":[
        {
            "category":"Shopping",
            "subcategory":"Clothing, Apparel, & Fashions",
            "type":"Retail Goods"
        }
    ],
    "sg:postcode":"S65 1EL",
    "sg:province":"South Yorkshire",
    "sg:tags":[
        "accessory"
    ],
    "wof:name":"The Sock Bar",
    "wof:placetype":"venue"
},
  "geometry": {"coordinates":[-1.354062,53.434685],"type":"Point"}
}