{
  "type": "Feature",
  "properties": {
    "addr:full":"South Dale, Caistor Market Rasen Lincolnshire LN7 6LX",
    "addr:postcode":"ln7 6lx",
    "addr:street":"South Dale Caistor Market Rasen",
    "iso:country":"GB",
    "sg:address":"South Dale, Caistor",
    "sg:city":"Market Rasen",
    "sg:classifiers":[
        {
            "category":"Sports & Exercise",
            "subcategory":"Sports Center",
            "type":"Entertainment"
        }
    ],
    "sg:phone":"+44 1472 852877",
    "sg:postcode":"LN7 6LX",
    "sg:province":"Lincolnshire",
    "sg:tags":[
        "coaching"
    ],
    "wof:name":"Nld-Rfu Youth Development",
    "wof:placetype":"venue"
},
  "geometry": {"coordinates":[-0.3157519996,53.4948310852],"type":"Point"}
}