{
  "type": "Feature",
  "properties": {
    "addr:full":"3 Fronheulog, Cemmaes Machynlleth Ceredigion SY20 9PU",
    "addr:housenumber":"3",
    "addr:postcode":"sy20 9pu",
    "addr:street":"Fronheulog Cemmaes",
    "iso:country":"GB",
    "sg:address":"3 Fronheulog, Cemmaes",
    "sg:city":"Machynlleth",
    "sg:classifiers":[
        {
            "category":"Professional",
            "subcategory":"Computer Services",
            "type":"Services"
        }
    ],
    "sg:phone":"+44 1650 511897",
    "sg:postcode":"SY20 9PU",
    "sg:province":"Ceredigion",
    "sg:tags":[
        "system",
        "software"
    ],
    "wof:name":"Nouveau Entertainment & Ticketing",
    "wof:placetype":"venue"
},
  "geometry": {"coordinates":[-3.8467230797,52.5909614563],"type":"Point"}
}