{
  "type": "Feature",
  "properties": {
    "addr:full":"Hill House, 43 Cheltenham Road Cirencester Gloucestershire GL7 2HU",
    "addr:housenumber":"43",
    "addr:postcode":"gl7 2hu",
    "addr:street":"Cheltenham Road",
    "iso:country":"GB",
    "sg:address":"Hill House, 43 Cheltenham Road",
    "sg:city":"Cirencester",
    "sg:classifiers":[
        {
            "category":"Building & Trades",
            "subcategory":"Construction",
            "type":"Services"
        }
    ],
    "sg:phone":"+44 1285 658535",
    "sg:postcode":"GL7 2HU",
    "sg:province":"Gloucestershire",
    "sg:tags":[
        "joinery",
        "joiner",
        "carpenter",
        "carpentry"
    ],
    "wof:name":"MARK B A CLAYTON",
    "wof:placetype":"venue"
},
  "geometry": {"coordinates":[-1.975542,51.728737],"type":"Point"}
}