{
  "type": "Feature",
  "properties": {
    "addr:full":"7 Staion Road, Urmston Manchester Cheshire M41 9JG",
    "addr:housenumber":"7",
    "addr:postcode":"m41 9jg",
    "addr:street":"Staion Road",
    "iso:country":"GB",
    "sg:address":"7 Staion Road, Urmston",
    "sg:city":"Manchester",
    "sg:classifiers":[
        {
            "category":"Professional",
            "subcategory":"Printing & Photocopies",
            "type":"Services"
        }
    ],
    "sg:phone":"+44 161 748 5959",
    "sg:postcode":"M41 9JG",
    "sg:province":"Cheshire",
    "sg:tags":[
        "printer"
    ],
    "wof:name":"Roberts & Longden (Printers)",
    "wof:placetype":"venue"
},
  "geometry": {"coordinates":[-2.3526899815,53.447807312],"type":"Point"}
}