{
  "type": "Feature",
  "properties": {
    "iso:country":"GB",
    "sg:address":"8 New Road, Belton In Rutland",
    "sg:city":"Oakham",
    "sg:classifiers":[
        {
            "category":"Shopping",
            "subcategory":"Bicycles & Sporting Goods",
            "type":"Retail Goods"
        },
        {
            "category":"Farming",
            "subcategory":"Livestock Farm",
            "type":"Manufacturing & Wholesale Goods"
        }
    ],
    "sg:phone":"+44 1572 717294",
    "sg:postcode":"LE15 9LE",
    "sg:province":"Leicestershire",
    "sg:tags":[
        "riding",
        "saddlery",
        "wear",
        "stud"
    ],
    "wof:name":"Kings Lodge Stables",
    "wof:placetype":"venue"
},
  "geometry": {"coordinates":[-0.799004,52.600323],"type":"Point"}
}