{
  "type": "Feature",
  "properties": {
    "addr:full":"27 Wargrave Rd Reading Berkshire RG10 9PB",
    "addr:housenumber":"27",
    "addr:postcode":"rg10 9pb",
    "addr:street":"Wargrave Rd",
    "iso:country":"GB",
    "sg:address":"27 Wargrave Rd",
    "sg:city":"Reading",
    "sg:classifiers":[
        {
            "category":"Professional",
            "subcategory":"Accounting & Tax Preparation",
            "type":"Services"
        }
    ],
    "sg:phone":"+44 118 932 1421",
    "sg:postcode":"RG10 9PB",
    "sg:province":"Berkshire",
    "sg:tags":[
        "accountant"
    ],
    "wof:name":"B Bennett & Co",
    "wof:placetype":"venue"
},
  "geometry": {"coordinates":[-0.86826998,51.4787368774],"type":"Point"}
}