{
  "type": "Feature",
  "properties": {
    "addr:full":"297 Poulton Road Wallasey Merseyside CH44 4BT",
    "addr:housenumber":"297",
    "addr:postcode":"ch44 4bt",
    "addr:street":"Poulton Road",
    "iso:country":"GB",
    "sg:address":"297 Poulton Road",
    "sg:city":"Wallasey",
    "sg:classifiers":[
        {
            "category":"Shopping",
            "subcategory":"Hobbies, Toys, & Games",
            "type":"Retail Goods"
        }
    ],
    "sg:phone":"+44 151 653 3753",
    "sg:postcode":"CH44 4BT",
    "sg:province":"Merseyside",
    "sg:tags":[
        "toy"
    ],
    "wof:name":"G Day & Co. Ltd.",
    "wof:placetype":"venue"
},
  "geometry": {"coordinates":[-3.0408689976,53.4121513367],"type":"Point"}
}