{
  "type": "Feature",
  "properties": {
    "addr:full":"348 Burgess Road Southampton Hampshire SO16 3BJ",
    "addr:housenumber":"348",
    "addr:postcode":"so16 3bj",
    "addr:street":"Burgess Road",
    "iso:country":"GB",
    "sg:address":"348 Burgess Road",
    "sg:city":"Southampton",
    "sg:classifiers":[
        {
            "category":"Retail",
            "subcategory":"Auto Repair",
            "type":"Services"
        }
    ],
    "sg:postcode":"SO16 3BJ",
    "sg:province":"Hampshire",
    "sg:tags":[
        "modification",
        "garage"
    ],
    "wof:name":"Keith Newton",
    "wof:placetype":"venue"
},
  "geometry": {"coordinates":[-1.38062,50.939114],"type":"Point"}
}