{
  "type": "Feature",
  "properties": {
    "addr:full":"4 Dixon Terrace, Cockfield Bishop Auckland Durham DL13 5EU",
    "addr:housenumber":"4",
    "addr:postcode":"dl13 5eu",
    "addr:street":"Dixon Terrace;Auckland",
    "iso:country":"GB",
    "sg:address":"4 Dixon Terrace, Cockfield",
    "sg:city":"Bishop Auckland",
    "sg:classifiers":[
        {
            "category":"Building & Trades",
            "subcategory":"Construction",
            "type":"Services"
        }
    ],
    "sg:phone":"+44 1388 718415",
    "sg:postcode":"DL13 5EU",
    "sg:province":"Durham",
    "sg:tags":[
        "builder"
    ],
    "wof:name":"A.l Colegrove",
    "wof:placetype":"venue"
},
  "geometry": {"coordinates":[-1.807329,54.613029],"type":"Point"}
}