{
  "type": "Feature",
  "properties": {
    "addr:full":"Ravenside Retail & Leisure Park Bexhill On Sea East Sussex TN40 2JS",
    "addr:postcode":"tn40 2js",
    "addr:street":"Park",
    "iso:country":"GB",
    "sg:address":"Ravenside Retail & Leisure Park",
    "sg:city":"Bexhill On Sea",
    "sg:classifiers":[
        {
            "category":"Community Center",
            "type":"Public Place"
        }
    ],
    "sg:phone":"+44 1424 731508",
    "sg:postcode":"TN40 2JS",
    "sg:province":"East Sussex",
    "sg:tags":[
        "recreation",
        "leisure",
        "centre"
    ],
    "wof:name":"Bexhill Leisure Pool",
    "wof:placetype":"venue"
},
  "geometry": {"coordinates":[0.49957,50.844341],"type":"Point"}
}