{
  "type": "Feature",
  "properties": {
    "addr:full":"2 Lydiard Green, Lydiard Millicent Swindon Wiltshire SN5 3LP",
    "addr:housenumber":"2",
    "addr:postcode":"sn5 3lp",
    "addr:street":"Lydiard Green",
    "iso:country":"GB",
    "sg:address":"2 Lydiard Green, Lydiard Millicent",
    "sg:city":"Swindon",
    "sg:classifiers":[
        {
            "category":"Social Services",
            "subcategory":"Job Training",
            "type":"Services"
        },
        {
            "category":"Education",
            "subcategory":"Special Training",
            "type":"Public Place"
        }
    ],
    "sg:phone":"+44 1793 771748",
    "sg:postcode":"SN5 3LP",
    "sg:province":"Wiltshire",
    "sg:tags":[
        "product",
        "centre"
    ],
    "wof:name":"Q I Training Ltd.",
    "wof:placetype":"venue"
},
  "geometry": {"coordinates":[-1.862928,51.570961],"type":"Point"}
}