{
  "type": "Feature",
  "properties": {
    "addr:full":"182-186 Walsgrave Rd Coventry Warwickshire CV2 4AX",
    "addr:postcode":"182-186;cv2 4ax",
    "addr:street":"Walsgrave Rd",
    "iso:country":"GB",
    "sg:address":"182-186 Walsgrave Rd",
    "sg:city":"Coventry",
    "sg:classifiers":[
        {
            "category":"Retail",
            "subcategory":"Auto Repair",
            "type":"Services"
        }
    ],
    "sg:phone":"+44 24 7665 0602",
    "sg:postcode":"CV2 4AX",
    "sg:province":"Warwickshire",
    "sg:tags":[
        "car",
        "upholsterer"
    ],
    "wof:name":"Wash N Go",
    "wof:placetype":"venue"
},
  "geometry": {"coordinates":[-1.479468,52.411324],"type":"Point"}
}