{
  "type": "Feature",
  "properties": {
    "addr:full":"32 Stamford Rd Nottingham Nottinghamshire NG2 6GE",
    "addr:housenumber":"32",
    "addr:postcode":"ng2 6ge",
    "addr:street":"Stamford Rd",
    "iso:country":"GB",
    "sg:address":"32 Stamford Rd",
    "sg:city":"Nottingham",
    "sg:classifiers":[
        {
            "category":"Personal",
            "type":"Services"
        }
    ],
    "sg:postcode":"NG2 6GE",
    "sg:province":"Nottinghamshire",
    "sg:tags":[
        "wedding"
    ],
    "wof:name":"S K Photographic",
    "wof:placetype":"venue"
},
  "geometry": {"coordinates":[-1.120299,52.922787],"type":"Point"}
}