{
  "type": "Feature",
  "properties": {
    "addr:full":"Ditton Nursery, Summerfield Lane Surbiton Surrey KT6 5DZ",
    "addr:postcode":"kt6 5dz",
    "addr:street":"Summerfield Lane",
    "iso:country":"GB",
    "sg:address":"Ditton Nursery, Summerfield Lane",
    "sg:city":"Surbiton",
    "sg:classifiers":[
        {
            "category":"Shopping",
            "subcategory":"Florist",
            "type":"Retail Goods"
        }
    ],
    "sg:phone":"+44 20 8398 8813",
    "sg:postcode":"KT6 5DZ",
    "sg:province":"Surrey",
    "wof:name":"The Plant People Ltd.",
    "wof:placetype":"venue"
},
  "geometry": {"coordinates":[-0.3069489896,51.3920593262],"type":"Point"}
}