{
  "type": "Feature",
  "properties": {
    "iso:country":"GB",
    "sg:address":"Clan Ho, Turners La",
    "sg:city":"Sheffield",
    "sg:classifiers":[
        {
            "category":"Professional",
            "subcategory":"Advertising",
            "type":"Services"
        }
    ],
    "sg:postcode":"S10 1BP",
    "sg:province":"South Yorkshire",
    "sg:tags":[
        "agency"
    ],
    "wof:name":"Glover,Martin,",
    "wof:placetype":"venue"
},
  "geometry": {"coordinates":[-1.500124,53.378265],"type":"Point"}
}