{
  "type": "Feature",
  "properties": {
    "addr:full":"229 Coventry Rd Nuneaton Leicestershire CV10 7AX",
    "addr:housenumber":"229",
    "addr:postcode":"cv10 7ax",
    "addr:street":"Coventry Rd",
    "iso:country":"GB",
    "sg:address":"229 Coventry Rd",
    "sg:city":"Nuneaton",
    "sg:classifiers":[
        {
            "category":"Professional",
            "subcategory":"Engineering",
            "type":"Services"
        }
    ],
    "sg:phone":"+44 24 7638 6171",
    "sg:postcode":"CV10 7AX",
    "sg:province":"Leicestershire",
    "wof:name":"T I Sanderson",
    "wof:placetype":"venue"
},
  "geometry": {"coordinates":[-1.468701005,52.5037651062],"type":"Point"}
}