{
  "type": "Feature",
  "properties": {
    "addr:full":"Unit 1, Hurstwood Court Bolton Lancashire BL3 2NP",
    "addr:housenumber":"unit 1",
    "addr:postcode":"bl3 2np",
    "addr:street":"Hurstwood Court",
    "iso:country":"GB",
    "sg:address":"Unit 1, Hurstwood Court",
    "sg:city":"Bolton",
    "sg:classifiers":[
        {
            "category":"Autos & Motor Vehicles",
            "subcategory":"Automobile Sales",
            "type":"Retail Goods"
        }
    ],
    "sg:phone":"+44 1204 385855",
    "sg:postcode":"BL3 2NP",
    "sg:province":"Lancashire",
    "sg:tags":[
        "car"
    ],
    "wof:name":"Jaycar Ltd.",
    "wof:placetype":"venue"
},
  "geometry": {"coordinates":[-2.43966,53.606449],"type":"Point"}
}