{
  "type": "Feature",
  "properties": {
    "addr:full":"Canwick Road, Canwick Lincoln Lincolnshire LN4 2RF",
    "addr:postcode":"ln4 2rf",
    "addr:street":"Canwick Road",
    "iso:country":"GB",
    "sg:address":"Canwick Road, Canwick",
    "sg:city":"Lincoln",
    "sg:classifiers":[
        {
            "category":"Autos & Motor Vehicles",
            "subcategory":"Fuel & Gas Station",
            "type":"Retail Goods"
        },
        {
            "category":"Retail",
            "subcategory":"Auto Repair",
            "type":"Services"
        }
    ],
    "sg:phone":"+44 1522 533665",
    "sg:postcode":"LN4 2RF",
    "sg:province":"Lincolnshire",
    "sg:tags":[
        "petrol",
        "garage",
        "modification"
    ],
    "wof:name":"Pitstop (U K) Ltd",
    "wof:placetype":"venue"
},
  "geometry": {"coordinates":[-0.529911,53.216671],"type":"Point"}
}