{
  "type": "Feature",
  "properties": {
    "addr:full":"1 Sutton Street Birmingham West Midlands B1 1PE",
    "addr:housenumber":"1",
    "addr:postcode":"b1 1pe",
    "addr:street":"Sutton Street",
    "iso:country":"GB",
    "sg:address":"1 Sutton Street",
    "sg:city":"Birmingham",
    "sg:classifiers":[
        {
            "category":"Professional",
            "type":"Services"
        },
        {
            "category":"Conference Center",
            "type":"Public Place"
        }
    ],
    "sg:phone":"+44 121 666 6266",
    "sg:postcode":"B1 1PE",
    "sg:province":"West Midlands",
    "sg:tags":[
        "related"
    ],
    "wof:name":"Clockwork Communications Ltd.",
    "wof:placetype":"venue"
},
  "geometry": {"coordinates":[-1.9039900303,52.4724960327],"type":"Point"}
}