{
  "type": "Feature",
  "properties": {
    "iso:country":"GB",
    "sg:address":"Church Lane, Walney",
    "sg:city":"Barrow-in-furness",
    "sg:classifiers":[
        {
            "category":"Education",
            "subcategory":"School",
            "type":"Public Place"
        }
    ],
    "sg:phone":"+44 1229 471522",
    "sg:postcode":"LA14 3AD",
    "sg:province":"Cumbria",
    "sg:tags":[
        "local",
        "authority"
    ],
    "wof:name":"St Columbas C School",
    "wof:placetype":"venue"
},
  "geometry": {"coordinates":[-3.249744,54.105759],"type":"Point"}
}