{
  "type": "Feature",
  "properties": {
    "addr:full":"166 Old Shoreham Road Hove East Sussex BN3 7AP",
    "addr:housenumber":"166",
    "addr:postcode":"bn3 7ap",
    "addr:street":"Old Shoreham Road",
    "iso:country":"GB",
    "sg:address":"166 Old Shoreham Road",
    "sg:city":"Hove",
    "sg:classifiers":[
        {
            "category":"Shopping",
            "subcategory":"News",
            "type":"Retail Goods"
        }
    ],
    "sg:postcode":"BN3 7AP",
    "sg:province":"East Sussex",
    "sg:tags":[
        "newsagent"
    ],
    "wof:name":"Jay's of Hove",
    "wof:placetype":"venue"
},
  "geometry": {"coordinates":[-0.182184,50.839081],"type":"Point"}
}