{
  "type": "Feature",
  "properties": {
    "addr:full":"53 North St Wareham Dorset BH20 4AD",
    "addr:housenumber":"53",
    "addr:postcode":"bh20 4ad",
    "addr:street":"North St",
    "iso:country":"GB",
    "sg:address":"53 North St",
    "sg:city":"Wareham",
    "sg:classifiers":[
        {
            "category":"Cinema",
            "subcategory":"Movie Rental",
            "type":"Entertainment"
        }
    ],
    "sg:phone":"+44 1929 554766",
    "sg:postcode":"BH20 4AD",
    "sg:province":"Dorset",
    "sg:tags":[
        "video",
        "library"
    ],
    "wof:name":"Revolutions",
    "wof:placetype":"venue"
},
  "geometry": {"coordinates":[-2.1113400459,50.6880874634],"type":"Point"}
}