{
  "type": "Feature",
  "properties": {
    "iso:country":"GB",
    "sg:address":"Oakdale Trading Estate, Ham Lane",
    "sg:city":"Brierley Hill",
    "sg:classifiers":[
        {
            "category":"Brewery",
            "type":"Food & Drink"
        }
    ],
    "sg:phone":"+44 800 454984",
    "sg:postcode":"DY6 7JH",
    "sg:province":"Staffordshire",
    "sg:tags":[
        "brewer"
    ],
    "wof:name":"Anheuser-Busch Europe Ltd.",
    "wof:placetype":"venue"
},
  "geometry": {"coordinates":[-2.16266,52.50819],"type":"Point"}
}