{
  "type": "Feature",
  "properties": {
    "addr:full":"73-74 High Street, Station Road Banbury Oxfordshire OX16 5JG",
    "addr:housenumber":"73-74",
    "addr:postcode":"ox16 5jg",
    "addr:street":"High;Station Road",
    "iso:country":"GB",
    "sg:address":"73-74 High Street, Station Road",
    "sg:city":"Banbury",
    "sg:classifiers":[
        {
            "category":"Professional",
            "subcategory":"Management & Consulting",
            "type":"Services"
        }
    ],
    "sg:postcode":"OX16 5JG",
    "sg:province":"Oxfordshire",
    "sg:tags":[
        "consultant",
        "business"
    ],
    "wof:name":"Crif Decision Solutions Ltd.",
    "wof:placetype":"venue"
},
  "geometry": {"coordinates":[-1.3364050388,52.0616226196],"type":"Point"}
}