{
  "type": "Feature",
  "properties": {
    "iso:country":"GB",
    "sg:address":"Provincial House, Albion Street",
    "sg:city":"Leeds",
    "sg:classifiers":[
        {
            "category":"Professional",
            "subcategory":"Employment Agencies",
            "type":"Services"
        }
    ],
    "sg:phone":"+44 113 231 4545",
    "sg:postcode":"LS1 6HX",
    "sg:province":"West Yorkshire",
    "sg:tags":[
        "consultant",
        "recruitment"
    ],
    "wof:name":"Badenoch & Clark Ltd",
    "wof:placetype":"venue"
},
  "geometry": {"coordinates":[-1.545114994,53.7980918884],"type":"Point"}
}