{
  "type": "Feature",
  "properties": {
    "addr:full":"Church Farm, Hatherton Cannock Staffordshire WS11 1RR",
    "addr:postcode":"ws11 1rr",
    "iso:country":"GB",
    "sg:address":"Church Farm, Hatherton",
    "sg:city":"Cannock",
    "sg:classifiers":[
        {
            "category":"Farming",
            "subcategory":"Farm",
            "type":"Manufacturing & Wholesale Goods"
        }
    ],
    "sg:phone":"+44 1543 571406",
    "sg:postcode":"WS11 1RR",
    "sg:province":"Staffordshire",
    "sg:tags":[
        "mixed",
        "crop"
    ],
    "wof:name":"Church Farm Eggs Ltd.",
    "wof:placetype":"venue"
},
  "geometry": {"coordinates":[-2.062184,52.690559],"type":"Point"}
}