{
  "type": "Feature",
  "properties": {
    "iso:country":"GB",
    "sg:address":"78 Kesteven Rd",
    "sg:city":"Stamford",
    "sg:classifiers":[
        {
            "category":"Building & Trades",
            "subcategory":"Construction",
            "type":"Services"
        }
    ],
    "sg:phone":"+44 1780 481740",
    "sg:postcode":"PE9 1SR",
    "sg:province":"Cambridgeshire",
    "sg:tags":[
        "roofing"
    ],
    "wof:name":"Woodward Roofing",
    "wof:placetype":"venue"
},
  "geometry": {"coordinates":[-0.476249,52.662491],"type":"Point"}
}