{
  "type": "Feature",
  "properties": {
    "addr:full":"23 Teak Drive, Kearsley Bolton Lancashire BL4 8RR",
    "addr:housenumber":"23",
    "addr:postcode":"bl4 8rr",
    "addr:street":"Teak Drive",
    "iso:country":"GB",
    "sg:address":"23 Teak Drive, Kearsley",
    "sg:city":"Bolton",
    "sg:classifiers":[
        {
            "category":"Professional",
            "subcategory":"Engineering",
            "type":"Services"
        }
    ],
    "sg:postcode":"BL4 8RR",
    "sg:province":"Lancashire",
    "sg:tags":[
        "contractor",
        "electrical",
        "engineer"
    ],
    "wof:name":"Thomas B Fish",
    "wof:placetype":"venue"
},
  "geometry": {"coordinates":[-2.3555119038,53.530544281],"type":"Point"}
}