{
  "type": "Feature",
  "properties": {
    "iso:country":"GB",
    "sg:address":"23 Calder Place, Hallglen",
    "sg:city":"Falkirk",
    "sg:classifiers":[
        {
            "category":"Professional",
            "subcategory":"Secretarial Services",
            "type":"Services"
        }
    ],
    "sg:phone":"+44 1324 617465",
    "sg:postcode":"FK1 2QZ",
    "sg:province":"Falkirk",
    "wof:name":"W.P.E",
    "wof:placetype":"venue"
},
  "geometry": {"coordinates":[-3.7717568874,55.9857788086],"type":"Point"}
}