{
  "type": "Feature",
  "properties": {
    "iso:country":"GB",
    "sg:address":"11-19 Vyner Street",
    "sg:city":"London",
    "sg:classifiers":[
        {
            "category":"Shopping",
            "subcategory":"Stationery & Office Supplies",
            "type":"Retail Goods"
        }
    ],
    "sg:postcode":"E2 9DG",
    "sg:province":"Greater London",
    "sg:tags":[
        "printers'"
    ],
    "wof:name":"King Repro",
    "wof:placetype":"venue"
},
  "geometry": {"coordinates":[-0.0567290001,51.5344581604],"type":"Point"}
}