{
  "type": "Feature",
  "properties": {
    "addr:full":"37 Goldentan Rd Bedford Bedfordshire MK40 3LH",
    "addr:housenumber":"37",
    "addr:postcode":"mk40 3lh",
    "addr:street":"Goldentan Rd",
    "iso:country":"GB",
    "sg:address":"37 Goldentan Rd",
    "sg:city":"Bedford",
    "sg:classifiers":[
        {
            "category":"Health Services",
            "subcategory":"Dentist",
            "type":"Services"
        }
    ],
    "sg:phone":"+44 1234 359594",
    "sg:postcode":"MK40 3LH",
    "sg:province":"Bedfordshire",
    "wof:name":"S Barnes",
    "wof:placetype":"venue"
},
  "geometry": {"coordinates":[-0.4597029984,52.1396408081],"type":"Point"}
}