{
  "type": "Feature",
  "properties": {
    "addr:full":"48 Keresley Brook Road Coventry Warwickshire CV6 2FW",
    "addr:housenumber":"48",
    "addr:postcode":"cv6 2fw",
    "addr:street":"Keresley Brook Road",
    "iso:country":"GB",
    "sg:address":"48 Keresley Brook Road",
    "sg:city":"Coventry",
    "sg:classifiers":[
        {
            "category":"Building & Trades",
            "subcategory":"Plumbing",
            "type":"Services"
        }
    ],
    "sg:phone":"+44 24 7633 4003",
    "sg:postcode":"CV6 2FW",
    "sg:province":"Warwickshire",
    "sg:tags":[
        "plumber",
        "heating"
    ],
    "wof:name":"Coventry Plumbing & Gas Services",
    "wof:placetype":"venue"
},
  "geometry": {"coordinates":[-1.5274629593,52.4419059753],"type":"Point"}
}