{
  "type": "Feature",
  "properties": {
    "iso:country":"GB",
    "sg:address":"5 Palmer Road, South West Industrial Estate",
    "sg:city":"Peterlee",
    "sg:classifiers":[
        {
            "category":"Professional",
            "type":"Services"
        }
    ],
    "sg:phone":"+44 191 518 1088",
    "sg:postcode":"SR8 2HU",
    "sg:province":"Durham",
    "sg:tags":[
        "specialist",
        "coating"
    ],
    "wof:name":"Euro Decorative Boards Ltd.",
    "wof:placetype":"venue"
},
  "geometry": {"coordinates":[-1.3612020016,54.7576026917],"type":"Point"}
}