{
  "type": "Feature",
  "properties": {
    "iso:country":"GB",
    "sg:address":"Tavistock House, 5 Rodney Road",
    "sg:city":"Cheltenham",
    "sg:classifiers":[
        {
            "category":"Professional",
            "subcategory":"Engineering",
            "type":"Services"
        }
    ],
    "sg:phone":"+44 1242 517222",
    "sg:postcode":"GL50 1HX",
    "sg:province":"Gloucestershire",
    "sg:tags":[
        "engineer",
        "structural"
    ],
    "wof:name":"Nomad A E D Ltd",
    "wof:placetype":"venue"
},
  "geometry": {"coordinates":[-2.0734019279,51.8996086121],"type":"Point"}
}