{
  "type": "Feature",
  "properties": {
    "addr:full":"6 High Street Romford Essex RM1 1HR",
    "addr:housenumber":"6",
    "addr:postcode":"rm1 1hr",
    "addr:street":"High Street",
    "iso:country":"GB",
    "sg:address":"6 High Street",
    "sg:city":"Romford",
    "sg:classifiers":[
        {
            "category":"Shopping",
            "subcategory":"Clothing, Apparel, & Fashions",
            "type":"Retail Goods"
        }
    ],
    "sg:phone":"+44 1708 727162",
    "sg:postcode":"RM1 1HR",
    "sg:province":"Essex",
    "sg:tags":[
        "shop"
    ],
    "wof:name":"Primark Stores Ltd.",
    "wof:placetype":"venue"
},
  "geometry": {"coordinates":[0.1797650009,51.578327179],"type":"Point"}
}