{
  "type": "Feature",
  "properties": {
    "addr:full":"Unit 7/8 Clocktower Workspace, 4 Shearling Way London Greater London N7 9TH",
    "addr:housenumber":"unit 7 / 8;4",
    "addr:postcode":"n7 9th",
    "addr:street":"Clocktower Workspace;Shearling Way",
    "iso:country":"GB",
    "sg:address":"Unit 7/8 Clocktower Workspace, 4 Shearling Way",
    "sg:city":"London",
    "sg:classifiers":[
        {
            "category":"Professional",
            "subcategory":"Printing & Photocopies",
            "type":"Services"
        }
    ],
    "sg:postcode":"N7 9TH",
    "sg:province":"Greater London",
    "sg:tags":[
        "printer"
    ],
    "wof:name":"Galactic Press",
    "wof:placetype":"venue"
},
  "geometry": {"coordinates":[-0.1220199987,51.5480918884],"type":"Point"}
}