{
  "type": "Feature",
  "properties": {
    "iso:country":"GB",
    "sg:address":"57 Rede Way, Great Cornard",
    "sg:city":"Sudbury",
    "sg:classifiers":[
        {
            "category":"Building & Trades",
            "subcategory":"Landscaping Services",
            "type":"Services"
        },
        {
            "category":"Autos & Motor Vehicles",
            "subcategory":"Auto Supplies",
            "type":"Retail Goods"
        }
    ],
    "sg:postcode":"CO10 0LQ",
    "sg:province":"Essex",
    "sg:tags":[
        "horticultural",
        "towbars",
        "consultant"
    ],
    "wof:name":"C & C Towing",
    "wof:placetype":"venue"
},
  "geometry": {"coordinates":[0.756023,52.032375],"type":"Point"}
}