{
  "type": "Feature",
  "properties": {
    "iso:country":"GB",
    "sg:address":"7 Smalley Place",
    "sg:city":"Kenilworth",
    "sg:classifiers":[
        {
            "category":"Real Estate",
            "subcategory":"Real Estate Agent",
            "type":"Services"
        }
    ],
    "sg:phone":"+44 1926 409070",
    "sg:postcode":"CV8 1QG",
    "sg:province":"Warwickshire",
    "wof:name":"Maxwell Heppell & Co.",
    "wof:placetype":"venue"
},
  "geometry": {"coordinates":[-1.580632,52.34338],"type":"Point"}
}