{
  "type": "Feature",
  "properties": {
    "addr:full":"18a Lynton Rd Kilburn Greater London NW6 6BL",
    "addr:housenumber":"18a",
    "addr:postcode":"nw6 6bl",
    "addr:street":"Lynton Rd",
    "iso:country":"GB",
    "sg:address":"18a Lynton Rd",
    "sg:city":"Kilburn",
    "sg:classifiers":[
        {
            "category":"Professional",
            "subcategory":"Business Services",
            "type":"Services"
        }
    ],
    "sg:phone":"+44 20 7372 6803",
    "sg:postcode":"NW6 6BL",
    "sg:province":"Greater London",
    "sg:tags":[
        "import",
        "export",
        "agent"
    ],
    "wof:name":"Magyfoz Co.Ltd",
    "wof:placetype":"venue"
},
  "geometry": {"coordinates":[-0.2022709996,51.5365104675],"type":"Point"}
}