{
  "type": "Feature",
  "properties": {
    "addr:full":"Westmorland Avenue Leicester Leicestershire LE4 6SB",
    "addr:postcode":"le4 6sb",
    "addr:street":"Westmorland Avenue",
    "iso:country":"GB",
    "sg:address":"Westmorland Avenue",
    "sg:city":"Leicester",
    "sg:classifiers":[
        {
            "category":"Freight",
            "type":"Transportation"
        }
    ],
    "sg:phone":"+44 116 266 7229",
    "sg:postcode":"LE4 6SB",
    "sg:province":"Leicestershire",
    "sg:tags":[
        "haulage",
        "road"
    ],
    "wof:name":"P K Transport",
    "wof:placetype":"venue"
},
  "geometry": {"coordinates":[-1.111409,52.654732],"type":"Point"}
}