{
  "type": "Feature",
  "properties": {
    "addr:full":"17 Medway Close Sittingbourne Kent ME10 1LP",
    "addr:housenumber":"17",
    "addr:postcode":"me10 1lp",
    "addr:street":"Medway Close",
    "iso:country":"GB",
    "sg:address":"17 Medway Close",
    "sg:city":"Sittingbourne",
    "sg:classifiers":[
        {
            "category":"Building & Trades",
            "subcategory":"Construction",
            "type":"Services"
        }
    ],
    "sg:phone":"+44 1795 425164",
    "sg:postcode":"ME10 1LP",
    "sg:province":"Kent",
    "sg:tags":[
        "repair",
        "window",
        "replacement"
    ],
    "wof:name":"Tom Marks",
    "wof:placetype":"venue"
},
  "geometry": {"coordinates":[0.7252789736,51.3387908936],"type":"Point"}
}