{
  "type": "Feature",
  "properties": {
    "iso:country":"GB",
    "sg:address":"Spalding Road",
    "sg:city":"Bourne",
    "sg:classifiers":[
        {
            "category":"Autos & Motor Vehicles",
            "subcategory":"Auto Supplies",
            "type":"Retail Goods"
        }
    ],
    "sg:phone":"+44 1778 394400",
    "sg:postcode":"PE10 9LE",
    "sg:province":"Lincolnshire",
    "sg:tags":[
        "tyre"
    ],
    "wof:name":"Rapid Fit",
    "wof:placetype":"venue"
},
  "geometry": {"coordinates":[-0.3688639998,52.7660255432],"type":"Point"}
}