{
  "type": "Feature",
  "properties": {
    "iso:country":"GB",
    "sg:address":"20 West Street",
    "sg:city":"Berwick-upon-tweed",
    "sg:classifiers":[
        {
            "category":"Communications",
            "subcategory":"Newspaper",
            "type":"Services"
        }
    ],
    "sg:phone":"+44 1289 308995",
    "sg:postcode":"TD15 1AS",
    "sg:province":"Northumberland",
    "sg:tags":[
        "magazine"
    ],
    "wof:name":"Berwick & Borders Gazette",
    "wof:placetype":"venue"
},
  "geometry": {"coordinates":[-2.00472,55.769821],"type":"Point"}
}