{
  "type": "Feature",
  "properties": {
    "iso:country":"GB",
    "sg:address":"29 Main Street, Carnaby",
    "sg:city":"Bridlington",
    "sg:classifiers":[
        {
            "category":"Travel",
            "subcategory":"Hotels & Motels",
            "type":"Entertainment"
        }
    ],
    "sg:phone":"+44 1262 678961",
    "sg:postcode":"YO16 4UJ",
    "sg:province":"East Riding of Yorkshire",
    "wof:name":"Ferns Farm Hotel",
    "wof:placetype":"venue"
},
  "geometry": {"coordinates":[-0.248418,54.072552],"type":"Point"}
}