{
  "type": "Feature",
  "properties": {
    "iso:country":"GB",
    "sg:address":"1-3 Whitehouse Road",
    "sg:city":"Swindon",
    "sg:classifiers":[
        {
            "category":"Autos & Motor Vehicles",
            "subcategory":"Auto Supplies",
            "type":"Retail Goods"
        }
    ],
    "sg:phone":"+44 1793 490119",
    "sg:postcode":"SN2 1BZ",
    "sg:province":"Wiltshire",
    "sg:tags":[
        "part",
        "motorcycle",
        "accessory"
    ],
    "wof:name":"Cobra Leathers",
    "wof:placetype":"venue"
},
  "geometry": {"coordinates":[-1.7836560011,51.5684242249],"type":"Point"}
}