{
  "type": "Feature",
  "properties": {
    "addr:full":"P O Box 53, Hanover St Manchester Greater Manchester M60 4ES",
    "addr:housenumber":"box 53",
    "addr:postcode":"m60 4es",
    "addr:street":"P O;Hanover St",
    "iso:country":"GB",
    "sg:address":"P O Box 53, Hanover St",
    "sg:city":"Manchester",
    "sg:classifiers":[
        {
            "category":"Government",
            "subcategory":"Office",
            "type":"Public Place"
        }
    ],
    "sg:postcode":"M60 4ES",
    "sg:province":"Greater Manchester",
    "sg:tags":[
        "education",
        "agency",
        "authority"
    ],
    "wof:name":"Manchester Education Business Partnershi",
    "wof:placetype":"venue"
},
  "geometry": {"coordinates":[-2.239180088,53.4822616577],"type":"Point"}
}