{
  "type": "Feature",
  "properties": {
    "addr:full":"Old Goods Yard Pontypridd Caerphilly CF37 2BP",
    "addr:postcode":"cf37 2bp",
    "addr:street":"Yard",
    "iso:country":"GB",
    "sg:address":"Old Goods Yard",
    "sg:city":"Pontypridd",
    "sg:classifiers":[
        {
            "category":"Sports & Exercise",
            "subcategory":"Bowling",
            "type":"Entertainment"
        }
    ],
    "sg:phone":"+44 1443 485051",
    "sg:postcode":"CF37 2BP",
    "sg:province":"Caerphilly",
    "wof:name":"Taff-Ely Indoor Bowls Club",
    "wof:placetype":"venue"
},
  "geometry": {"coordinates":[-3.330959,51.597549],"type":"Point"}
}