{
  "type": "Feature",
  "properties": {
    "addr:full":"Low Road Leeds West Yorkshire LS10 1QR",
    "addr:postcode":"ls10 1qr",
    "addr:street":"Low Road",
    "iso:country":"GB",
    "sg:address":"Low Road",
    "sg:city":"Leeds",
    "sg:classifiers":[
        {
            "category":"Retail",
            "subcategory":"Auto Rental",
            "type":"Services"
        }
    ],
    "sg:phone":"+44 113 277 9455",
    "sg:postcode":"LS10 1QR",
    "sg:province":"West Yorkshire",
    "sg:tags":[
        "truck",
        "hire",
        "van"
    ],
    "wof:name":"Anchor Self Drive Ltd.",
    "wof:placetype":"venue"
},
  "geometry": {"coordinates":[-1.5276399851,53.7816925049],"type":"Point"}
}