{
  "type": "Feature",
  "properties": {
    "iso:country":"GB",
    "sg:address":"124 Cowley Road",
    "sg:city":"Oxford",
    "sg:classifiers":[
        {
            "category":"Personal",
            "subcategory":"Tattoo Parlor",
            "type":"Services"
        }
    ],
    "sg:phone":"+44 1865 200651",
    "sg:postcode":"OX4 1JE",
    "sg:province":"Oxfordshire",
    "sg:tags":[
        "tattooing",
        "piercing"
    ],
    "wof:name":"Eagle Tattoo",
    "wof:placetype":"venue"
},
  "geometry": {"coordinates":[-1.2382910252,51.748046875],"type":"Point"}
}