{
  "type": "Feature",
  "properties": {
    "addr:full":"34 Wagg Street Congleton Cheshire CW12 4BA",
    "addr:housenumber":"34",
    "addr:postcode":"cw12 4ba",
    "addr:street":"Wagg Street",
    "iso:country":"GB",
    "sg:address":"34 Wagg Street",
    "sg:city":"Congleton",
    "sg:classifiers":[
        {
            "category":"Home & Garden",
            "subcategory":"Home Furnishings",
            "type":"Retail Goods"
        }
    ],
    "sg:phone":"+44 1260 299866",
    "sg:postcode":"CW12 4BA",
    "sg:province":"Cheshire",
    "sg:tags":[
        "blind",
        "awning",
        "canopy",
        "blinds"
    ],
    "wof:name":"Blinds by Design Limited",
    "wof:placetype":"venue"
},
  "geometry": {"coordinates":[-2.2150700092,53.1615791321],"type":"Point"}
}