{
  "type": "Feature",
  "properties": {
    "addr:full":"8 Witch Close Gillingham Dorset SP8 5LB",
    "addr:housenumber":"8",
    "addr:postcode":"sp8 5lb",
    "addr:street":"Witch Close",
    "iso:country":"GB",
    "sg:address":"8 Witch Close",
    "sg:city":"Gillingham",
    "sg:classifiers":[
        {
            "category":"Building & Trades",
            "subcategory":"Construction",
            "type":"Services"
        }
    ],
    "sg:postcode":"SP8 5LB",
    "sg:province":"Dorset",
    "sg:tags":[
        "decorator",
        "painter"
    ],
    "wof:name":"P & E Taylor",
    "wof:placetype":"venue"
},
  "geometry": {"coordinates":[-2.2871079445,51.0085411072],"type":"Point"}
}