{
  "type": "Feature",
  "properties": {
    "iso:country":"GB",
    "sg:address":"5 John Street",
    "sg:city":"Birmingham",
    "sg:classifiers":[
        {
            "category":"Shopping",
            "subcategory":"Clothing, Apparel, & Fashions",
            "type":"Retail Goods"
        }
    ],
    "sg:phone":"+44 121 681 6892",
    "sg:postcode":"B19 1NT",
    "sg:province":"West Midlands",
    "sg:tags":[
        "clothing",
        "fabric"
    ],
    "wof:name":"Case Consultants",
    "wof:placetype":"venue"
},
  "geometry": {"coordinates":[-1.9161399603,52.5006904602],"type":"Point"}
}