{
  "type": "Feature",
  "properties": {
    "addr:full":"Bredon House, Hospital Lane, Powick Worcester Worcestershire WR2 4SQ",
    "addr:postcode":"wr2 4sq",
    "addr:street":"Hospital Lane",
    "iso:country":"GB",
    "sg:address":"Bredon House, Hospital Lane, Powick",
    "sg:city":"Worcester",
    "sg:classifiers":[
        {
            "category":"Professional",
            "subcategory":"Engineering",
            "type":"Services"
        }
    ],
    "sg:postcode":"WR2 4SQ",
    "sg:province":"Worcestershire",
    "sg:tags":[
        "civil",
        "engineer"
    ],
    "wof:name":"Laser Civil Engineering Ltd",
    "wof:placetype":"venue"
},
  "geometry": {"coordinates":[-2.2620809078,52.157245636],"type":"Point"}
}