{
  "type": "Feature",
  "properties": {
    "addr:full":"84 Stn Rd Ellon Aberdeenshire AB41 9AY",
    "addr:housenumber":"84",
    "addr:postcode":"ab41 9ay",
    "addr:street":"Stn Rd",
    "iso:country":"GB",
    "sg:address":"84 Stn Rd",
    "sg:city":"Ellon",
    "sg:classifiers":[
        {
            "category":"Building & Trades",
            "subcategory":"Construction",
            "type":"Services"
        }
    ],
    "sg:postcode":"AB41 9AY",
    "sg:province":"Aberdeenshire",
    "sg:tags":[
        "builder"
    ],
    "wof:name":"Reid,Ian,",
    "wof:placetype":"venue"
},
  "geometry": {"coordinates":[-2.080139,57.366402],"type":"Point"}
}