{
  "type": "Feature",
  "properties": {
    "iso:country":"GB",
    "sg:address":"Lemington Lakes, Lower Lemington",
    "sg:city":"Moreton-in-marsh",
    "sg:classifiers":[
        {
            "category":"Farming",
            "subcategory":"Fish & Marine Products",
            "type":"Manufacturing & Wholesale Goods"
        },
        {
            "category":"Building & Trades",
            "subcategory":"Construction",
            "type":"Services"
        }
    ],
    "sg:postcode":"GL56 9NP",
    "sg:province":"Gloucestershire",
    "sg:tags":[
        "excavation",
        "groundwork",
        "builder",
        "fisherman",
        "contractor"
    ],
    "wof:name":"Maurice William Gadsby",
    "wof:placetype":"venue"
},
  "geometry": {"coordinates":[-1.6851240396,52.0060081482],"type":"Point"}
}