{
  "type": "Feature",
  "properties": {
    "iso:country":"GB",
    "sg:address":"5 Alder Avenue, Ashton In Makerfield",
    "sg:city":"Wigan",
    "sg:classifiers":[
        {
            "category":"Building & Trades",
            "subcategory":"Construction",
            "type":"Services"
        }
    ],
    "sg:phone":"+44 1942 716738",
    "sg:postcode":"WN4 0LS",
    "sg:province":"Lancashire",
    "sg:tags":[
        "decorator",
        "painter"
    ],
    "wof:name":"Ashfield Homes",
    "wof:placetype":"venue"
},
  "geometry": {"coordinates":[-2.654106,53.498974],"type":"Point"}
}