{
  "type": "Feature",
  "properties": {
    "iso:country":"GB",
    "sg:address":"15 Liverpool Road, Islington",
    "sg:city":"London",
    "sg:classifiers":[
        {
            "category":"Shopping",
            "subcategory":"Clothing, Apparel, & Fashions",
            "type":"Retail Goods"
        },
        {
            "category":"Shopping",
            "subcategory":"Used Merchandise",
            "type":"Retail Goods"
        }
    ],
    "sg:phone":"+44 20 7837 9717",
    "sg:postcode":"N1 0RW",
    "sg:province":"Greater London",
    "sg:tags":[
        "shop",
        "lingerie",
        "second-hand"
    ],
    "wof:name":"Icondeal Ltd.",
    "wof:placetype":"venue"
},
  "geometry": {"coordinates":[-0.107271,51.536369],"type":"Point"}
}