{
  "type": "Feature",
  "properties": {
    "iso:country":"GB",
    "sg:address":"Oakley Farm, Dinton",
    "sg:city":"Salisbury",
    "sg:classifiers":[
        {
            "category":"Retail",
            "subcategory":"Auto Repair",
            "type":"Services"
        }
    ],
    "sg:postcode":"SP3 5EU",
    "sg:province":"Wiltshire",
    "sg:tags":[
        "modification",
        "garage"
    ],
    "wof:name":"Oakley Motors",
    "wof:placetype":"venue"
},
  "geometry": {"coordinates":[-1.979668,51.083214],"type":"Point"}
}