{
  "type": "Feature",
  "properties": {
    "addr:full":"Lathkill Dale Craft Centre Bakewell Derbyshire DE45 1JE",
    "addr:postcode":"de45 1je",
    "iso:country":"GB",
    "sg:address":"Lathkill Dale Craft Centre",
    "sg:city":"Bakewell",
    "sg:classifiers":[
        {
            "category":"Home & Garden",
            "subcategory":"Building Materials",
            "type":"Retail Goods"
        }
    ],
    "sg:postcode":"DE45 1JE",
    "sg:province":"Derbyshire",
    "sg:tags":[
        "roofing",
        "rafter",
        "beams"
    ],
    "wof:name":"Smith,Malcolm D,",
    "wof:placetype":"venue"
},
  "geometry": {"coordinates":[-1.675119,53.213329],"type":"Point"}
}