{
  "type": "Feature",
  "properties": {
    "iso:country":"GB",
    "sg:address":"2-4 Rowntree Avenue, Burton Stone Lane",
    "sg:city":"York",
    "sg:classifiers":[
        {
            "category":"Home & Garden",
            "subcategory":"Household Appliances",
            "type":"Retail Goods"
        }
    ],
    "sg:postcode":"YO30 6HD",
    "sg:province":"North Yorkshire",
    "sg:tags":[
        "electrical"
    ],
    "wof:name":"G T Washing Machines",
    "wof:placetype":"venue"
},
  "geometry": {"coordinates":[-1.0841200352,53.9743843079],"type":"Point"}
}