{
  "type": "Feature",
  "properties": {
    "iso:country":"GB",
    "sg:address":"Anvers, Lower Dicker",
    "sg:city":"Hailsham",
    "sg:classifiers":[
        {
            "category":"Building & Trades",
            "subcategory":"Construction",
            "type":"Services"
        }
    ],
    "sg:phone":"+44 1323 449361",
    "sg:postcode":"BN27 4AY",
    "sg:province":"East Sussex",
    "sg:tags":[
        "joinery"
    ],
    "wof:name":"J Lancaster Fencing Supplies",
    "wof:placetype":"venue"
},
  "geometry": {"coordinates":[0.2123199999,50.8828887939],"type":"Point"}
}