{
  "type": "Feature",
  "properties": {
    "addr:full":"Coppenhall Garage, 1 Remer Street Crewe Cheshire CW1 4LS",
    "addr:housenumber":"1",
    "addr:postcode":"cw1 4ls",
    "addr:street":"Remer Street",
    "iso:country":"GB",
    "sg:address":"Coppenhall Garage, 1 Remer Street",
    "sg:city":"Crewe",
    "sg:classifiers":[
        {
            "category":"Retail",
            "subcategory":"Auto Repair",
            "type":"Services"
        }
    ],
    "sg:postcode":"CW1 4LS",
    "sg:province":"Cheshire",
    "sg:tags":[
        "modification",
        "garage"
    ],
    "wof:name":"D C Cook",
    "wof:placetype":"venue"
},
  "geometry": {"coordinates":[-2.446105,53.100578],"type":"Point"}
}