{
  "type": "Feature",
  "properties": {
    "iso:country":"GB",
    "sg:address":"128 London Road, Shardlow",
    "sg:city":"Derby",
    "sg:classifiers":[
        {
            "category":"Professional",
            "subcategory":"Accounting & Tax Preparation",
            "type":"Services"
        }
    ],
    "sg:phone":"+44 1332 792446",
    "sg:postcode":"DE72 2GP",
    "sg:province":"Derbyshire",
    "sg:tags":[
        "stove",
        "woodburning"
    ],
    "wof:name":"G D Harrison (Heating) Ltd.",
    "wof:placetype":"venue"
},
  "geometry": {"coordinates":[-1.3481030464,52.8685150146],"type":"Point"}
}