{
  "type": "Feature",
  "properties": {
    "iso:country":"GB",
    "sg:address":"31 Portland Road, Selston",
    "sg:city":"Nottingham",
    "sg:classifiers":[
        {
            "category":"Retail",
            "subcategory":"Repair Shop",
            "type":"Services"
        }
    ],
    "sg:postcode":"NG16 6AS",
    "sg:province":"Derbyshire",
    "sg:tags":[
        "upholsterer"
    ],
    "wof:name":"A H Naylor & Son",
    "wof:placetype":"venue"
},
  "geometry": {"coordinates":[-1.2944560051,53.0749664307],"type":"Point"}
}