{
  "type": "Feature",
  "properties": {
    "addr:full":"1a Coventry Road Market Harborough Leicestershire LE16 9BX",
    "addr:housenumber":"1a",
    "addr:postcode":"le16 9bx",
    "addr:street":"Coventry Road",
    "iso:country":"GB",
    "sg:address":"1a Coventry Road",
    "sg:city":"Market Harborough",
    "sg:classifiers":[
        {
            "category":"Personal",
            "subcategory":"Barber",
            "type":"Services"
        }
    ],
    "sg:phone":"+44 1858 463707",
    "sg:postcode":"LE16 9BX",
    "sg:province":"Leicestershire",
    "sg:tags":[
        "men's",
        "hairdresser"
    ],
    "wof:name":"L C Brazier",
    "wof:placetype":"venue"
},
  "geometry": {"coordinates":[-0.921127975,52.4777603149],"type":"Point"}
}