{
  "type": "Feature",
  "properties": {
    "iso:country":"GB",
    "sg:address":"Derby Rd",
    "sg:city":"Heanor",
    "sg:classifiers":[
        {
            "category":"Home & Garden",
            "subcategory":"Home Furnishings",
            "type":"Retail Goods"
        }
    ],
    "sg:phone":"+44 1773 713371",
    "sg:postcode":"DE75 7YH",
    "sg:province":"Derbyshire",
    "sg:tags":[
        "blind",
        "curtain",
        "fitting"
    ],
    "wof:name":"Basford Home Fashions",
    "wof:placetype":"venue"
},
  "geometry": {"coordinates":[-1.3611459732,53.0131835938],"type":"Point"}
}