{
  "type": "Feature",
  "properties": {
    "addr:full":"90 High Street, Eastchurch Sheerness Kent ME12 4DF",
    "addr:housenumber":"90",
    "addr:postcode":"me12 4df",
    "addr:street":"High Street",
    "iso:country":"GB",
    "sg:address":"90 High Street, Eastchurch",
    "sg:city":"Sheerness",
    "sg:classifiers":[
        {
            "category":"Building & Trades",
            "subcategory":"Plumbing",
            "type":"Services"
        },
        {
            "category":"Retail",
            "subcategory":"Auto Repair",
            "type":"Services"
        }
    ],
    "sg:phone":"+44 1795 880594",
    "sg:postcode":"ME12 4DF",
    "sg:province":"Kent",
    "sg:tags":[
        "body",
        "car",
        "heating"
    ],
    "wof:name":"Eastchurch Coachworks",
    "wof:placetype":"venue"
},
  "geometry": {"coordinates":[0.8567370176,51.4066886902],"type":"Point"}
}