{
  "type": "Feature",
  "properties": {
    "iso:country":"GB",
    "sg:address":"18 St Andrews Rd",
    "sg:city":"Liverpool",
    "sg:classifiers":[
        {
            "category":"Health Services",
            "subcategory":"Doctor",
            "type":"Services"
        }
    ],
    "sg:phone":"+44 151 924 2065",
    "sg:postcode":"L23 7UR",
    "sg:province":"Merseyside",
    "sg:tags":[
        "practitioners"
    ],
    "wof:name":"Sonia Goldrein",
    "wof:placetype":"venue"
},
  "geometry": {"coordinates":[-3.041225,53.498497],"type":"Point"}
}