{
  "type": "Feature",
  "properties": {
    "addr:full":"49 Rivington Crescent, Mill Hill London Greater London NW7 2LF",
    "addr:housenumber":"49",
    "addr:postcode":"nw7 2lf",
    "addr:street":"Rivington Crescent",
    "iso:country":"GB",
    "sg:address":"49 Rivington Crescent, Mill Hill",
    "sg:city":"London",
    "sg:classifiers":[
        {
            "category":"Professional",
            "subcategory":"Business Services",
            "type":"Services"
        }
    ],
    "sg:postcode":"NW7 2LF",
    "sg:province":"Greater London",
    "sg:tags":[
        "import",
        "export",
        "agent"
    ],
    "wof:name":"Ghina Aqua International Ltd",
    "wof:placetype":"venue"
},
  "geometry": {"coordinates":[-0.244885996,51.6068382263],"type":"Point"}
}