{
  "type": "Feature",
  "properties": {
    "addr:full":"6 Sunnyside Terrace Sherborne Dorset DT9 3JT",
    "addr:housenumber":"6",
    "addr:postcode":"dt9 3jt",
    "addr:street":"Sunnyside Terrace",
    "iso:country":"GB",
    "sg:address":"6 Sunnyside Terrace",
    "sg:city":"Sherborne",
    "sg:classifiers":[
        {
            "category":"Professional",
            "subcategory":"Art Services",
            "type":"Services"
        },
        {
            "category":"Building & Trades",
            "subcategory":"Construction",
            "type":"Services"
        }
    ],
    "sg:phone":"+44 1935 814166",
    "sg:postcode":"DT9 3JT",
    "sg:province":"Dorset",
    "sg:tags":[
        "decorator",
        "painter"
    ],
    "wof:name":"John Wisdom Painters & Decorators",
    "wof:placetype":"venue"
},
  "geometry": {"coordinates":[-2.5130860806,50.9512557983],"type":"Point"}
}