{
  "type": "Feature",
  "properties": {
    "addr:full":"Parks Cottage, New Road Uttoxeter Derbyshire ST14 5DS",
    "addr:postcode":"st14 5ds",
    "addr:street":"New Road",
    "iso:country":"GB",
    "sg:address":"Parks Cottage, New Road",
    "sg:city":"Uttoxeter",
    "sg:classifiers":[
        {
            "category":"Building & Trades",
            "subcategory":"Construction",
            "type":"Services"
        }
    ],
    "sg:phone":"+44 1889 567189",
    "sg:postcode":"ST14 5DS",
    "sg:province":"Derbyshire",
    "sg:tags":[
        "heating",
        "contractor"
    ],
    "wof:name":"D H Morley Plumbing & Heating",
    "wof:placetype":"venue"
},
  "geometry": {"coordinates":[-1.869644,52.896523],"type":"Point"}
}