{
  "type": "Feature",
  "properties": {
    "iso:country":"GB",
    "sg:address":"20a Hampden Square",
    "sg:city":"Southgate",
    "sg:classifiers":[
        {
            "category":"Shopping",
            "subcategory":"Party Supplies",
            "type":"Retail Goods"
        }
    ],
    "sg:phone":"+44 20 8361 4242",
    "sg:postcode":"N14 5JR",
    "sg:province":"Greater London",
    "sg:tags":[
        "marquees",
        "floor",
        "tent"
    ],
    "wof:name":"K & G Marquee Hire",
    "wof:placetype":"venue"
},
  "geometry": {"coordinates":[-0.1427589953,51.6313285828],"type":"Point"}
}