{
  "type": "Feature",
  "properties": {
    "addr:full":"155 Newcastle Street Stoke-on-trent Staffordshire ST6 3QJ",
    "addr:housenumber":"155",
    "addr:postcode":"st6 3qj",
    "addr:street":"Newcastle Street",
    "iso:country":"GB",
    "sg:address":"155 Newcastle Street",
    "sg:city":"Stoke-on-trent",
    "sg:classifiers":[
        {
            "category":"Fast Food",
            "type":"Food & Drink"
        }
    ],
    "sg:phone":"+44 1782 825448",
    "sg:postcode":"ST6 3QJ",
    "sg:province":"Staffordshire",
    "sg:tags":[
        "away",
        "take"
    ],
    "wof:name":"Lee's Chinese Take Away",
    "wof:placetype":"venue"
},
  "geometry": {"coordinates":[-2.204288,53.043201],"type":"Point"}
}