{
  "type": "Feature",
  "properties": {
    "addr:full":"17 The Terrace, Creigiau Cardiff Caerphilly CF15 9NG",
    "addr:housenumber":"17",
    "addr:postcode":"cf15 9ng",
    "addr:street":"The Terrace Creigiau",
    "iso:country":"GB",
    "sg:address":"17 The Terrace, Creigiau",
    "sg:city":"Cardiff",
    "sg:classifiers":[
        {
            "category":"Building & Trades",
            "subcategory":"Construction",
            "type":"Services"
        }
    ],
    "sg:phone":"+44 29 2089 1620",
    "sg:postcode":"CF15 9NG",
    "sg:province":"Caerphilly",
    "sg:tags":[
        "erectors",
        "platform",
        "scaffold",
        "work",
        "scaffolding"
    ],
    "wof:name":"Ace Scaffolding",
    "wof:placetype":"venue"
},
  "geometry": {"coordinates":[-3.323945,51.525669],"type":"Point"}
}