{
  "type": "Feature",
  "properties": {
    "addr:full":"33-34 Pontmorlais Merthyr Tydfil Merthyr Tydfil CF47 8UN",
    "addr:housenumber":"33-34",
    "addr:postcode":"cf47 8un",
    "addr:street":"Pontmorlais Merthyr Tydfil",
    "iso:country":"GB",
    "sg:address":"33-34 Pontmorlais",
    "sg:city":"Merthyr Tydfil",
    "sg:classifiers":[
        {
            "category":"Shopping",
            "subcategory":"Used Merchandise",
            "type":"Retail Goods"
        }
    ],
    "sg:phone":"+44 1685 377059",
    "sg:postcode":"CF47 8UN",
    "sg:province":"Merthyr Tydfil",
    "sg:tags":[
        "furniture"
    ],
    "wof:name":"A B C Exchange & Mart",
    "wof:placetype":"venue"
},
  "geometry": {"coordinates":[-3.379349,51.74905],"type":"Point"}
}