{
  "type": "Feature",
  "properties": {
    "addr:full":"7a Castle House, Castle Meadow Norwich Norfolk NR1 3DH",
    "addr:housenumber":"7a",
    "addr:postcode":"nr1 3dh",
    "addr:street":"Castle House Castle Meadow Norwich Norfolk",
    "iso:country":"GB",
    "sg:address":"7a Castle House, Castle Meadow",
    "sg:city":"Norwich",
    "sg:classifiers":[
        {
            "category":"Manufacturing",
            "subcategory":"Electronics",
            "type":"Manufacturing & Wholesale Goods"
        }
    ],
    "sg:phone":"+44 1603 630044",
    "sg:postcode":"NR1 3DH",
    "sg:province":"Norfolk",
    "sg:tags":[
        "mnfr",
        "component",
        "electronic"
    ],
    "wof:name":"Maplin Electronics Ltd.",
    "wof:placetype":"venue"
},
  "geometry": {"coordinates":[1.2948999405,52.6224937439],"type":"Point"}
}