{
  "type": "Feature",
  "properties": {
    "addr:full":"14 Edzell Drive, Newton Mearns Glasgow East Ayrshire G77 5QU",
    "addr:housenumber":"14",
    "addr:postcode":"g77 5qu",
    "addr:street":"Edzell Drive",
    "iso:country":"GB",
    "sg:address":"14 Edzell Drive, Newton Mearns",
    "sg:city":"Glasgow",
    "sg:classifiers":[
        {
            "category":"Retail",
            "subcategory":"Driving School",
            "type":"Services"
        }
    ],
    "sg:postcode":"G77 5QU",
    "sg:province":"East Ayrshire",
    "wof:name":"Motovation Driving School",
    "wof:placetype":"venue"
},
  "geometry": {"coordinates":[-4.325189,55.772083],"type":"Point"}
}