{
  "type": "Feature",
  "properties": {
    "iso:country":"GB",
    "sg:address":"Brackenber Moor",
    "sg:city":"Appleby-in-westmorland",
    "sg:classifiers":[
        {
            "category":"Sports & Exercise",
            "subcategory":"Golf",
            "type":"Entertainment"
        }
    ],
    "sg:phone":"+44 17683 51432",
    "sg:postcode":"CA16 6LP",
    "sg:province":"Cumbria",
    "sg:tags":[
        "club",
        "course"
    ],
    "wof:name":"Appleby Golf Club",
    "wof:placetype":"venue"
},
  "geometry": {"coordinates":[-2.48743,54.577309],"type":"Point"}
}