{
  "type": "Feature",
  "properties": {
    "addr:full":"10 Pop In Commercial Centre, South Way Wembley Greater London HA9 0HF",
    "addr:housenumber":"10",
    "addr:postcode":"ha9 0hf",
    "addr:street":"Pop In Commercial Centre South Way",
    "iso:country":"GB",
    "sg:address":"10 Pop In Commercial Centre, South Way",
    "sg:city":"Wembley",
    "sg:classifiers":[
        {
            "category":"Retail",
            "subcategory":"Auto Repair",
            "type":"Services"
        }
    ],
    "sg:phone":"+44 20 8900 0619",
    "sg:postcode":"HA9 0HF",
    "sg:province":"Greater London",
    "sg:tags":[
        "body",
        "car",
        "repairer",
        "modification",
        "garage"
    ],
    "wof:name":"C & R Motors",
    "wof:placetype":"venue"
},
  "geometry": {"coordinates":[-0.2955389917,51.5529632568],"type":"Point"}
}