{
  "type": "Feature",
  "properties": {
    "addr:full":"Unit 3, Pallion Centre, 33 Woodbine Terrace Sunderland Tyne and Wear SR4 6TY",
    "addr:housenumber":"unit 3;33",
    "addr:postcode":"sr4 6ty",
    "addr:street":"Woodbine Terrace",
    "iso:country":"GB",
    "sg:address":"Unit 3, Pallion Centre, 33 Woodbine Terrace",
    "sg:city":"Sunderland",
    "sg:classifiers":[
        {
            "category":"Community Center",
            "subcategory":"Social",
            "type":"Public Place"
        }
    ],
    "sg:phone":"+44 191 514 7026",
    "sg:postcode":"SR4 6TY",
    "sg:province":"Tyne and Wear",
    "sg:tags":[
        "frozen",
        "food",
        "freezer",
        "centre"
    ],
    "wof:name":"Iceland Frozen Foods",
    "wof:placetype":"venue"
},
  "geometry": {"coordinates":[-1.42018,54.913681],"type":"Point"}
}