{
  "type": "Feature",
  "properties": {
    "addr:full":"Mansel House, 99 Mansel Street Swansea Neath Port Talbot SA1 5UE",
    "addr:housenumber":"99",
    "addr:postcode":"sa1 5ue",
    "addr:street":"Mansel Street",
    "iso:country":"GB",
    "sg:address":"Mansel House, 99 Mansel Street",
    "sg:city":"Swansea",
    "sg:classifiers":[
        {
            "category":"Health Services",
            "subcategory":"Health Practitioner",
            "type":"Services"
        }
    ],
    "sg:phone":"+44 1792 462001",
    "sg:postcode":"SA1 5UE",
    "sg:province":"Neath Port Talbot",
    "sg:tags":[
        "osteopath"
    ],
    "wof:name":"G F Stephens",
    "wof:placetype":"venue"
},
  "geometry": {"coordinates":[-3.948211,51.62125],"type":"Point"}
}