{
  "type": "Feature",
  "properties": {
    "addr:full":"1-2 Browning Street, Easington Peterlee Durham SR8 3RY",
    "addr:housenumber":"1-2",
    "addr:postcode":"sr8 3ry",
    "addr:street":"Browning Street",
    "iso:country":"GB",
    "sg:address":"1-2 Browning Street, Easington",
    "sg:city":"Peterlee",
    "sg:classifiers":[
        {
            "category":"Organizations",
            "subcategory":"Membership Organization",
            "type":"Services"
        }
    ],
    "sg:phone":"+44 191 527 0708",
    "sg:postcode":"SR8 3RY",
    "sg:province":"Durham",
    "sg:tags":[
        "club"
    ],
    "wof:name":"Easington Colliery Officials Club",
    "wof:placetype":"venue"
},
  "geometry": {"coordinates":[-1.3219079971,54.7877464294],"type":"Point"}
}