{
  "type": "Feature",
  "properties": {
    "addr:full":"42 Kemerton Road London Greater London SE5 9AR",
    "addr:housenumber":"42",
    "addr:postcode":"se5 9ar",
    "addr:street":"Kemerton Road",
    "iso:country":"GB",
    "sg:address":"42 Kemerton Road",
    "sg:city":"London",
    "sg:classifiers":[
        {
            "category":"Freight",
            "type":"Transportation"
        }
    ],
    "sg:phone":"+44 20 7274 0920",
    "sg:postcode":"SE5 9AR",
    "sg:province":"Greater London",
    "sg:tags":[
        "haulage",
        "road"
    ],
    "wof:name":"A G M Transport",
    "wof:placetype":"venue"
},
  "geometry": {"coordinates":[-0.098376,51.464386],"type":"Point"}
}