{
  "type": "Feature",
  "properties": {
    "iso:country":"GB",
    "sg:address":"Unit 167 Boughton Industrial Estate, Boughton",
    "sg:city":"Newark",
    "sg:classifiers":[
        {
            "category":"Home & Garden",
            "subcategory":"Building Materials",
            "type":"Retail Goods"
        }
    ],
    "sg:postcode":"NG22 9LD",
    "sg:province":"Nottinghamshire",
    "sg:tags":[
        "gate",
        "door",
        "barrier"
    ],
    "wof:name":"Inter-Fence",
    "wof:placetype":"venue"
},
  "geometry": {"coordinates":[-0.9759089947,53.2042312622],"type":"Point"}
}