{
  "type": "Feature",
  "properties": {
    "iso:country":"GB",
    "sg:address":"Alexander House",
    "sg:city":"London",
    "sg:classifiers":[
        {
            "category":"Professional",
            "subcategory":"Accounting & Tax Preparation",
            "type":"Services"
        }
    ],
    "sg:phone":"+44 20 8346 7272",
    "sg:postcode":"N3 1XE",
    "sg:province":"Greater London",
    "sg:tags":[
        "accountant"
    ],
    "wof:name":"Jackson Feldman & Co. Ltd.",
    "wof:placetype":"venue"
},
  "geometry": {"coordinates":[-0.1953870058,51.6071891785],"type":"Point"}
}