{
  "type": "Feature",
  "properties": {
    "iso:country":"GB",
    "sg:address":"2 The Market, Pentrebane St",
    "sg:city":"Caerphilly",
    "sg:classifiers":[
        {
            "category":"Food & Beverages",
            "subcategory":"Meat & Fish",
            "type":"Retail Goods"
        }
    ],
    "sg:phone":"+44 29 2088 6124",
    "sg:postcode":"CF83 1FU",
    "sg:province":"Caerphilly",
    "sg:tags":[
        "butcher"
    ],
    "wof:name":"R Butler Butcher",
    "wof:placetype":"venue"
},
  "geometry": {"coordinates":[-3.220264,51.573074],"type":"Point"}
}