{
  "type": "Feature",
  "properties": {
    "iso:country":"GB",
    "sg:address":"4-6 Charlton Road",
    "sg:city":"Bristol",
    "sg:classifiers":[
        {
            "category":"Shopping",
            "type":"Retail Goods"
        }
    ],
    "sg:phone":"+44 117 986 9669",
    "sg:postcode":"BS31 2JA",
    "sg:province":"City of Bristol",
    "sg:tags":[
        "part",
        "accessory"
    ],
    "wof:name":"Carquip",
    "wof:placetype":"venue"
},
  "geometry": {"coordinates":[-2.4993,51.41629],"type":"Point"}
}