{
  "type": "Feature",
  "properties": {
    "addr:full":"Richmonds House, White Rose Wy Doncaster South Yorkshire DN4 5JH",
    "addr:postcode":"dn4 5jh",
    "addr:street":"White Rose Wy",
    "iso:country":"GB",
    "sg:address":"Richmonds House, White Rose Wy",
    "sg:city":"Doncaster",
    "sg:classifiers":[
        {
            "category":"Mining & Drilling",
            "type":"Manufacturing & Wholesale Goods"
        }
    ],
    "sg:postcode":"DN4 5JH",
    "sg:province":"South Yorkshire",
    "sg:tags":[
        "coal"
    ],
    "wof:name":"Aardvark T M C Ltd.",
    "wof:placetype":"venue"
},
  "geometry": {"coordinates":[-1.1149890423,53.501209259],"type":"Point"}
}