{
  "type": "Feature",
  "properties": {
    "addr:full":"15 Clevedon Craft Centre, Moor Lane Clevedon Somerset BS21 6TD",
    "addr:housenumber":"15;craft centre",
    "addr:postcode":"bs21 6td",
    "addr:street":"Clevedon;Moor Lane",
    "iso:country":"GB",
    "sg:address":"15 Clevedon Craft Centre, Moor Lane",
    "sg:city":"Clevedon",
    "sg:classifiers":[
        {
            "category":"Transit Center",
            "subcategory":"Freight",
            "type":"Transportation"
        }
    ],
    "sg:postcode":"BS21 6TD",
    "sg:province":"Somerset",
    "sg:tags":[
        "shop",
        "craft",
        "centre"
    ],
    "wof:name":"Aeolian",
    "wof:placetype":"venue"
},
  "geometry": {"coordinates":[-2.8550388813,51.43592453],"type":"Point"}
}