{
  "type": "Feature",
  "properties": {
    "iso:country":"GB",
    "sg:address":"158a Llantarnam Road, Llantarnam",
    "sg:city":"Cwmbran",
    "sg:classifiers":[
        {
            "category":"Shopping",
            "subcategory":"News",
            "type":"Retail Goods"
        }
    ],
    "sg:phone":"+44 1633 871367",
    "sg:postcode":"NP44 3BD",
    "sg:province":"Monmouthshire",
    "sg:tags":[
        "newsagent"
    ],
    "wof:name":"Cyril H Barter",
    "wof:placetype":"venue"
},
  "geometry": {"coordinates":[-3.015425,51.64204],"type":"Point"}
}