{
  "type": "Feature",
  "properties": {
    "addr:full":"Unit 3, Woodland Drive, Alma Park Ind Est Grantham Lincolnshire NG31 9DJ",
    "addr:housenumber":"unit 3",
    "addr:postcode":"ng31 9dj",
    "addr:street":"Woodland Drive;Park Ind Est",
    "iso:country":"GB",
    "sg:address":"Unit 3, Woodland Drive, Alma Park Ind Est",
    "sg:city":"Grantham",
    "sg:classifiers":[
        {
            "category":"Professional",
            "subcategory":"Engineering",
            "type":"Services"
        }
    ],
    "sg:phone":"+44 1476 577177",
    "sg:postcode":"NG31 9DJ",
    "sg:province":"Lincolnshire",
    "sg:tags":[
        "contractor",
        "electrical",
        "engineer"
    ],
    "wof:name":"Castle Contracts",
    "wof:placetype":"venue"
},
  "geometry": {"coordinates":[-0.6039950252,52.9258422852],"type":"Point"}
}