{
  "type": "Feature",
  "properties": {
    "iso:country":"GB",
    "sg:address":"24 Staithe Street",
    "sg:city":"Wells-next-the-sea",
    "sg:classifiers":[
        {
            "category":"Food & Beverages",
            "subcategory":"Meat & Fish",
            "type":"Retail Goods"
        }
    ],
    "sg:phone":"+44 1328 710228",
    "sg:postcode":"NR23 1AF",
    "sg:province":"Norfolk",
    "sg:tags":[
        "butcher"
    ],
    "wof:name":"Arthur Howell",
    "wof:placetype":"venue"
},
  "geometry": {"coordinates":[0.852348,52.954468],"type":"Point"}
}