{
  "type": "Feature",
  "properties": {
    "iso:country":"GB",
    "sg:address":"Fountainhall Rd",
    "sg:city":"Edinburgh",
    "sg:classifiers":[
        {
            "category":"Professional",
            "subcategory":"Advertising",
            "type":"Services"
        }
    ],
    "sg:phone":"+44 131 667 7770",
    "sg:postcode":"EH9 2NL",
    "sg:province":"City of Edinburgh",
    "sg:tags":[
        "agency"
    ],
    "wof:name":"Osprey Scotland",
    "wof:placetype":"venue"
},
  "geometry": {"coordinates":[-3.178514,55.93298],"type":"Point"}
}