{
  "type": "Feature",
  "properties": {
    "iso:country":"GB",
    "sg:address":"Old George St, Derrys Cross",
    "sg:city":"Plymouth",
    "sg:classifiers":[
        {
            "category":"Bars & Pubs",
            "type":"Food & Drink"
        }
    ],
    "sg:postcode":"PL1 2TG",
    "sg:province":"Devon",
    "sg:tags":[
        "pubs",
        "inn"
    ],
    "wof:name":"Bank Public House (The)",
    "wof:placetype":"venue"
},
  "geometry": {"coordinates":[-4.144924,50.369362],"type":"Point"}
}