{
  "type": "Feature",
  "properties": {
    "iso:country":"GB",
    "sg:address":"Pavilion Road",
    "sg:city":"Aldershot",
    "sg:classifiers":[
        {
            "category":"Shopping",
            "type":"Retail Goods"
        }
    ],
    "sg:phone":"+44 1252 317701",
    "sg:postcode":"GU11 3NX",
    "sg:province":"Hampshire",
    "sg:tags":[
        "part",
        "accessory"
    ],
    "wof:name":"Express Factors",
    "wof:placetype":"venue"
},
  "geometry": {"coordinates":[-0.7810029984,51.2467269897],"type":"Point"}
}