{
  "type": "Feature",
  "properties": {
    "iso:country":"GB",
    "sg:address":"38 Gun La",
    "sg:city":"Knebworth",
    "sg:classifiers":[
        {
            "category":"Professional",
            "subcategory":"Research",
            "type":"Services"
        }
    ],
    "sg:postcode":"SG3 6BH",
    "sg:province":"Hertfordshire",
    "sg:tags":[
        "market"
    ],
    "wof:name":"Wilson,Susan,",
    "wof:placetype":"venue"
},
  "geometry": {"coordinates":[-0.1868779957,51.8638687134],"type":"Point"}
}