{
  "type": "Feature",
  "properties": {
    "addr:full":"Netherton Lane, Netherton Wakefield West Yorkshire WF4 4HQ",
    "addr:postcode":"wf4 4hq",
    "addr:street":"Netherton Lane;West",
    "iso:country":"GB",
    "sg:address":"Netherton Lane, Netherton",
    "sg:city":"Wakefield",
    "sg:classifiers":[
        {
            "category":"Education",
            "subcategory":"School",
            "type":"Public Place"
        },
        {
            "category":"Government",
            "subcategory":"Office",
            "type":"Public Place"
        }
    ],
    "sg:phone":"+44 1924 302885",
    "sg:postcode":"WF4 4HQ",
    "sg:province":"West Yorkshire",
    "sg:tags":[
        "local",
        "authority"
    ],
    "wof:name":"Netherton Junior & Infants School",
    "wof:placetype":"venue"
},
  "geometry": {"coordinates":[-1.581668973,53.6431388855],"type":"Point"}
}