{
  "type": "Feature",
  "properties": {
    "iso:country":"GB",
    "sg:address":"Crewe Road South",
    "sg:city":"Edinburgh",
    "sg:classifiers":[
        {
            "category":"Autos & Motor Vehicles",
            "subcategory":"Fuel & Gas Station",
            "type":"Retail Goods"
        }
    ],
    "sg:phone":"+44 131 315 0910",
    "sg:postcode":"EH4 2NT",
    "sg:province":"City of Edinburgh",
    "sg:tags":[
        "hr",
        "petrol"
    ],
    "wof:name":"Shell Circle",
    "wof:placetype":"venue"
},
  "geometry": {"coordinates":[-3.236742,55.970654],"type":"Point"}
}