{
  "type": "Feature",
  "properties": {
    "addr:full":"8-18 Station Road, Chellaston Derby Derbyshire DE73 1SU",
    "addr:housenumber":"8-18",
    "addr:postcode":"de73 1su",
    "addr:street":"Station Road",
    "iso:country":"GB",
    "sg:address":"8-18 Station Road, Chellaston",
    "sg:city":"Derby",
    "sg:classifiers":[
        {
            "category":"Shopping",
            "subcategory":"Party Supplies",
            "type":"Retail Goods"
        }
    ],
    "sg:phone":"+44 1332 701171",
    "sg:postcode":"DE73 1SU",
    "sg:province":"Derbyshire",
    "sg:tags":[
        "marquees",
        "floor",
        "tent"
    ],
    "wof:name":"Crocker Bros Ltd.",
    "wof:placetype":"venue"
},
  "geometry": {"coordinates":[-1.4264270067,52.8253822327],"type":"Point"}
}