{
  "type": "Feature",
  "properties": {
    "addr:full":"97 Penybank Road Ammanford Carmarthenshire SA18 3QP",
    "addr:housenumber":"97",
    "addr:postcode":"sa18 3qp",
    "addr:street":"Penybank Road",
    "iso:country":"GB",
    "sg:address":"97 Penybank Road",
    "sg:city":"Ammanford",
    "sg:classifiers":[
        {
            "category":"Travel",
            "subcategory":"Hotels & Motels",
            "type":"Entertainment"
        }
    ],
    "sg:phone":"+44 1269 592280",
    "sg:postcode":"SA18 3QP",
    "sg:province":"Carmarthenshire",
    "wof:name":"Golden Lion Hotel",
    "wof:placetype":"venue"
},
  "geometry": {"coordinates":[-3.9889450073,51.7923965454],"type":"Point"}
}