{
  "type": "Feature",
  "properties": {
    "iso:country":"GB",
    "sg:address":"Unit 20 Sheet Rd",
    "sg:city":"Ludlow",
    "sg:classifiers":[
        {
            "category":"Autos & Motor Vehicles",
            "subcategory":"Auto Supplies",
            "type":"Retail Goods"
        }
    ],
    "sg:phone":"+44 1584 877100",
    "sg:postcode":"SY8 1LR",
    "sg:province":"Herefordshire",
    "sg:tags":[
        "windscreen"
    ],
    "wof:name":"Templar Automotive",
    "wof:placetype":"venue"
},
  "geometry": {"coordinates":[-2.699349,52.365116],"type":"Point"}
}