{
  "type": "Feature",
  "properties": {
    "iso:country":"GB",
    "sg:address":"Woolwich House, 3rd Floor, 43 George Street",
    "sg:city":"Croydon",
    "sg:classifiers":[
        {
            "category":"Professional",
            "subcategory":"Employment Agencies",
            "type":"Services"
        }
    ],
    "sg:phone":"+44 20 8286 9393",
    "sg:postcode":"CR9 1EY",
    "sg:province":"Surrey",
    "sg:tags":[
        "consultant"
    ],
    "wof:name":"M D S It Ltd.",
    "wof:placetype":"venue"
},
  "geometry": {"coordinates":[-0.097508,51.374222],"type":"Point"}
}