{
  "type": "Feature",
  "properties": {
    "addr:full":"27 Stanton Road, Wimbledon London Greater London SW20 8RW",
    "addr:housenumber":"27",
    "addr:postcode":"sw20 8rw",
    "addr:street":"Stanton Road",
    "iso:country":"GB",
    "sg:address":"27 Stanton Road, Wimbledon",
    "sg:city":"London",
    "sg:classifiers":[
        {
            "category":"Professional",
            "subcategory":"Computer Services",
            "type":"Services"
        }
    ],
    "sg:phone":"+44 20 8715 2222",
    "sg:postcode":"SW20 8RW",
    "sg:province":"Greater London",
    "sg:tags":[
        "system",
        "software"
    ],
    "wof:name":"Gridfile Developments Ltd.",
    "wof:placetype":"venue"
},
  "geometry": {"coordinates":[-0.2225890011,51.4117584229],"type":"Point"}
}