{
  "type": "Feature",
  "properties": {
    "addr:full":"Grange St Burton On Trent Derbyshire DE14 2ER",
    "addr:postcode":"trent derbyshire de14 2er",
    "addr:street":"Grange St",
    "iso:country":"GB",
    "sg:address":"Grange St",
    "sg:city":"Burton On Trent",
    "sg:classifiers":[
        {
            "category":"Education",
            "subcategory":"School",
            "type":"Public Place"
        }
    ],
    "sg:phone":"+44 1283 563014",
    "sg:postcode":"DE14 2ER",
    "sg:province":"Derbyshire",
    "sg:tags":[
        "local",
        "authority"
    ],
    "wof:name":"Burton Education Centre",
    "wof:placetype":"venue"
},
  "geometry": {"coordinates":[-1.647524,52.810345],"type":"Point"}
}