{
  "type": "Feature",
  "properties": {
    "iso:country":"GB",
    "sg:address":"124 Park Road, Spixworth",
    "sg:city":"Norwich",
    "sg:classifiers":[
        {
            "category":"Building & Trades",
            "subcategory":"Plumbing",
            "type":"Services"
        }
    ],
    "sg:phone":"+44 1603 890057",
    "sg:postcode":"NR10 3NP",
    "sg:province":"Norfolk",
    "sg:tags":[
        "heating"
    ],
    "wof:name":"Knud H Pederson",
    "wof:placetype":"venue"
},
  "geometry": {"coordinates":[1.324818,52.685299],"type":"Point"}
}