{
  "type": "Feature",
  "properties": {
    "addr:full":"Unit 7 Kiln Hill Industrial Esta, Te Kiln Hill Huddersfield West Yorkshire HD7 5JS",
    "addr:housenumber":"unit 7",
    "addr:postcode":"hd7 5js",
    "addr:street":"Kiln Hill Industrial Esta Te;West",
    "iso:country":"GB",
    "sg:address":"Unit 7 Kiln Hill Industrial Esta, Te Kiln Hill",
    "sg:city":"Huddersfield",
    "sg:classifiers":[
        {
            "category":"Shopping",
            "subcategory":"Computers & Home Electronics",
            "type":"Retail Goods"
        },
        {
            "category":"Manufacturing",
            "subcategory":"Building Materials",
            "type":"Manufacturing & Wholesale Goods"
        }
    ],
    "sg:phone":"+44 1484 844969",
    "sg:postcode":"HD7 5JS",
    "sg:province":"West Yorkshire",
    "sg:tags":[
        "tube",
        "manipulator",
        "bender"
    ],
    "wof:name":"Fabtec Manufacturing Ltd",
    "wof:placetype":"venue"
},
  "geometry": {"coordinates":[-1.879808,53.621216],"type":"Point"}
}