{
  "type": "Feature",
  "properties": {
    "addr:full":"Unit 1 Gambles Factory, Newdigate St Nottingham Nottinghamshire NG7 4FD",
    "addr:housenumber":"unit 1",
    "addr:postcode":"ng7 4fd",
    "addr:street":"Gambles Factory Newdigate St",
    "iso:country":"GB",
    "sg:address":"Unit 1 Gambles Factory, Newdigate St",
    "sg:city":"Nottingham",
    "sg:classifiers":[
        {
            "category":"Professional",
            "subcategory":"Printing & Photocopies",
            "type":"Services"
        }
    ],
    "sg:phone":"+44 115 942 0768",
    "sg:postcode":"NG7 4FD",
    "sg:province":"Nottinghamshire",
    "sg:tags":[
        "computer",
        "tag",
        "label"
    ],
    "wof:name":"Tutin Garment Labels",
    "wof:placetype":"venue"
},
  "geometry": {"coordinates":[-1.1642299891,52.9580612183],"type":"Point"}
}