{
  "type": "Feature",
  "properties": {
    "iso:country":"GB",
    "sg:address":"2 Oakfield",
    "sg:city":"Newton Aycliffe",
    "sg:classifiers":[
        {
            "category":"Retail",
            "subcategory":"Storage",
            "type":"Services"
        }
    ],
    "sg:phone":"+44 1325 308580",
    "sg:postcode":"DL5 7AS",
    "sg:province":"Durham",
    "sg:tags":[
        "household",
        "activity",
        "domestic",
        "removal"
    ],
    "wof:name":"Rapid Removals",
    "wof:placetype":"venue"
},
  "geometry": {"coordinates":[-1.582844,54.615131],"type":"Point"}
}