{
  "type": "Feature",
  "properties": {
    "addr:full":"1 Millersneuk Road Glasgow East Dunbartonshire G66 5JD",
    "addr:housenumber":"1",
    "addr:postcode":"g66 5jd",
    "addr:street":"Millersneuk Road",
    "iso:country":"GB",
    "sg:address":"1 Millersneuk Road",
    "sg:city":"Glasgow",
    "sg:classifiers":[
        {
            "category":"Food & Beverages",
            "subcategory":"Bakery",
            "type":"Retail Goods"
        }
    ],
    "sg:phone":"+44 141 776 5323",
    "sg:postcode":"G66 5JD",
    "sg:province":"East Dunbartonshire",
    "sg:tags":[
        "baker"
    ],
    "wof:name":"Connor J S",
    "wof:placetype":"venue"
},
  "geometry": {"coordinates":[-4.1426668167,55.9226608276],"type":"Point"}
}