{
  "type": "Feature",
  "properties": {
    "iso:country":"GB",
    "sg:address":"Brookside Lane, High Lane",
    "sg:city":"Stockport",
    "sg:classifiers":[
        {
            "category":"Arena",
            "subcategory":"Sports Club",
            "type":"Entertainment"
        }
    ],
    "sg:phone":"+44 1663 764218",
    "sg:postcode":"SK6 8HL",
    "sg:province":"Cheshire",
    "wof:name":"Woodside Tennis Club",
    "wof:placetype":"venue"
},
  "geometry": {"coordinates":[-2.0695340633,53.3638114929],"type":"Point"}
}