{
  "type": "Feature",
  "properties": {
    "addr:full":"56 Cotham Hill Bristol City of Bristol BS6 6JX",
    "addr:housenumber":"56",
    "addr:postcode":"bs6 6jx",
    "addr:street":"Cotham Hill",
    "iso:country":"GB",
    "sg:address":"56 Cotham Hill",
    "sg:city":"Bristol",
    "sg:classifiers":[
        {
            "category":"Shopping",
            "subcategory":"News",
            "type":"Retail Goods"
        }
    ],
    "sg:phone":"+44 117 973 5791",
    "sg:postcode":"BS6 6JX",
    "sg:province":"City of Bristol",
    "sg:tags":[
        "newsagent"
    ],
    "wof:name":"N & S News",
    "wof:placetype":"venue"
},
  "geometry": {"coordinates":[-2.607102,51.463451],"type":"Point"}
}