{
  "type": "Feature",
  "properties": {
    "iso:country":"GB",
    "sg:address":"15 Casketgate",
    "sg:city":"Lincoln",
    "sg:classifiers":[
        {
            "category":"Shopping",
            "subcategory":"Clothing, Apparel, & Fashions",
            "type":"Retail Goods"
        }
    ],
    "sg:phone":"+44 1522 532616",
    "sg:postcode":"LN2 1JJ",
    "sg:province":"Lincolnshire",
    "sg:tags":[
        "menswear"
    ],
    "wof:name":"Gere Ltd.",
    "wof:placetype":"venue"
},
  "geometry": {"coordinates":[-0.538967,53.230614],"type":"Point"}
}