{
  "type": "Feature",
  "properties": {
    "addr:full":"4 Hill View Road Whitstable Kent CT5 4HX",
    "addr:housenumber":"4",
    "addr:postcode":"ct5 4hx",
    "addr:street":"Hill View Road",
    "iso:country":"GB",
    "sg:address":"4 Hill View Road",
    "sg:city":"Whitstable",
    "sg:classifiers":[
        {
            "category":"Shopping",
            "subcategory":"Stationery & Office Supplies",
            "type":"Retail Goods"
        }
    ],
    "sg:phone":"+44 1227 273138",
    "sg:postcode":"CT5 4HX",
    "sg:province":"Kent",
    "sg:tags":[
        "printers'"
    ],
    "wof:name":"Medway Cutters",
    "wof:placetype":"venue"
},
  "geometry": {"coordinates":[1.02777,51.351685],"type":"Point"}
}