{
  "type": "Feature",
  "properties": {
    "addr:full":"1 Clayhall Road Gosport Hampshire PO12 2BY",
    "addr:housenumber":"1",
    "addr:postcode":"po12 2by",
    "addr:street":"Clayhall Road",
    "iso:country":"GB",
    "sg:address":"1 Clayhall Road",
    "sg:city":"Gosport",
    "sg:classifiers":[
        {
            "category":"Social Services",
            "subcategory":"Retirement Home",
            "type":"Services"
        }
    ],
    "sg:phone":"+44 23 9258 1103",
    "sg:postcode":"PO12 2BY",
    "sg:province":"Hampshire",
    "sg:tags":[
        "rest"
    ],
    "wof:name":"Brookfield Retirement Residence",
    "wof:placetype":"venue"
},
  "geometry": {"coordinates":[-1.143068,50.783886],"type":"Point"}
}