{
  "type": "Feature",
  "properties": {
    "addr:full":"38a East Street Havant Hampshire PO9 1AQ",
    "addr:housenumber":"38a",
    "addr:postcode":"po9 1aq",
    "addr:street":"East Street",
    "iso:country":"GB",
    "sg:address":"38a East Street",
    "sg:city":"Havant",
    "sg:classifiers":[
        {
            "category":"Food & Beverages",
            "subcategory":"Bakery",
            "type":"Retail Goods"
        }
    ],
    "sg:phone":"+44 23 9248 3176",
    "sg:postcode":"PO9 1AQ",
    "sg:province":"Hampshire",
    "sg:tags":[
        "baker"
    ],
    "wof:name":"Tudor Rose",
    "wof:placetype":"venue"
},
  "geometry": {"coordinates":[-0.979391,50.850735],"type":"Point"}
}