{
  "type": "Feature",
  "properties": {
    "addr:full":"Cayton Bay Holiday Centre Scarborough North Yorkshire YO11 3NJ",
    "addr:postcode":"yo11 3nj",
    "addr:street":"Cayton",
    "iso:country":"GB",
    "sg:address":"Cayton Bay Holiday Centre",
    "sg:city":"Scarborough",
    "sg:classifiers":[
        {
            "category":"Travel",
            "subcategory":"Hotels & Motels",
            "type":"Entertainment"
        }
    ],
    "sg:phone":"+44 1723 583111",
    "sg:postcode":"YO11 3NJ",
    "sg:province":"North Yorkshire",
    "sg:tags":[
        "self",
        "catering"
    ],
    "wof:name":"Haven Holidays",
    "wof:placetype":"venue"
},
  "geometry": {"coordinates":[-0.3657599986,54.2427101135],"type":"Point"}
}