{
  "type": "Feature",
  "properties": {
    "iso:country":"GB",
    "sg:address":"38 Chester Road West, Shotton",
    "sg:city":"Deeside",
    "sg:classifiers":[
        {
            "category":"Professional",
            "subcategory":"Employment Agencies",
            "type":"Services"
        }
    ],
    "sg:phone":"+44 1925 265158",
    "sg:postcode":"CH5 1BY",
    "sg:province":"Flintshire",
    "sg:tags":[
        "consultant"
    ],
    "wof:name":"The Industrial Connection",
    "wof:placetype":"venue"
},
  "geometry": {"coordinates":[-3.022927,53.205189],"type":"Point"}
}