{
  "type": "Feature",
  "properties": {
    "iso:country":"GB",
    "sg:address":"13 Albion Road",
    "sg:city":"Edinburgh",
    "sg:classifiers":[
        {
            "category":"Personal",
            "subcategory":"Barber",
            "type":"Services"
        }
    ],
    "sg:phone":"+44 131 467 7507",
    "sg:postcode":"EH7 5QJ",
    "sg:province":"City of Edinburgh",
    "sg:tags":[
        "men's",
        "gents",
        "hairdresser"
    ],
    "wof:name":"Clippers",
    "wof:placetype":"venue"
},
  "geometry": {"coordinates":[-3.169754,55.962025],"type":"Point"}
}