{
  "type": "Feature",
  "properties": {
    "addr:full":"Winklebury Way Basingstoke Hampshire RG23 8BU",
    "addr:postcode":"rg23 8bu",
    "addr:street":"Winklebury Way",
    "iso:country":"GB",
    "sg:address":"Winklebury Way",
    "sg:city":"Basingstoke",
    "sg:classifiers":[
        {
            "category":"Bars & Pubs",
            "type":"Food & Drink"
        }
    ],
    "sg:phone":"+44 1256 354180",
    "sg:postcode":"RG23 8BU",
    "sg:province":"Hampshire",
    "sg:tags":[
        "pubs",
        "inn"
    ],
    "wof:name":"The Three Barrels",
    "wof:placetype":"venue"
},
  "geometry": {"coordinates":[-1.1309390068,51.2673110962],"type":"Point"}
}