{
  "type": "Feature",
  "properties": {
    "addr:full":"61 Woodgrange Road London Greater London E7 0EL",
    "addr:housenumber":"61",
    "addr:postcode":"e7 0el",
    "addr:street":"Woodgrange Road",
    "iso:country":"GB",
    "sg:address":"61 Woodgrange Road",
    "sg:city":"London",
    "sg:classifiers":[
        {
            "category":"Restaurant",
            "type":"Food & Drink"
        }
    ],
    "sg:postcode":"E7 0EL",
    "sg:province":"Greater London",
    "wof:name":"Star Express",
    "wof:placetype":"venue"
},
  "geometry": {"coordinates":[0.024621,51.548882],"type":"Point"}
}