{
  "type": "Feature",
  "properties": {
    "addr:full":"98 Pendle Road, Streatham London Greater London SW16 6RY",
    "addr:housenumber":"98",
    "addr:postcode":"sw16 6ry",
    "addr:street":"Pendle Road",
    "iso:country":"GB",
    "sg:address":"98 Pendle Road, Streatham",
    "sg:city":"London",
    "sg:classifiers":[
        {
            "category":"Utilities",
            "subcategory":"Natural Gas",
            "type":"Services"
        }
    ],
    "sg:phone":"+44 20 8869 5580",
    "sg:postcode":"SW16 6RY",
    "sg:province":"Greater London",
    "sg:tags":[
        "control",
        "energy",
        "management",
        "system"
    ],
    "wof:name":"On Tap Plumbing & Heating",
    "wof:placetype":"venue"
},
  "geometry": {"coordinates":[-0.1475030035,51.4231872559],"type":"Point"}
}