{
  "type": "Feature",
  "properties": {
    "iso:country":"GB",
    "sg:address":"6 Littleham Rd",
    "sg:city":"Exmouth",
    "sg:classifiers":[
        {
            "category":"Personal",
            "subcategory":"Beauty Salon",
            "type":"Services"
        },
        {
            "category":"Personal",
            "subcategory":"Barber",
            "type":"Services"
        }
    ],
    "sg:phone":"+44 1395 269710",
    "sg:postcode":"EX8 2QG",
    "sg:province":"Devon",
    "sg:tags":[
        "unisex",
        "hairdresser"
    ],
    "wof:name":"The Hair & Beauty Shoppe",
    "wof:placetype":"venue"
},
  "geometry": {"coordinates":[-3.3889029026,50.624370575],"type":"Point"}
}