{
  "type": "Feature",
  "properties": {
    "iso:country":"GB",
    "sg:address":"8 Westcliffe Drive",
    "sg:city":"Blackpool",
    "sg:classifiers":[
        {
            "category":"Health Services",
            "subcategory":"Optometrist",
            "type":"Services"
        }
    ],
    "sg:phone":"+44 1253 393377",
    "sg:postcode":"FY3 7HG",
    "sg:province":"Lancashire",
    "sg:tags":[
        "optician"
    ],
    "wof:name":"Jim Procter",
    "wof:placetype":"venue"
},
  "geometry": {"coordinates":[-3.0313830376,53.8282432556],"type":"Point"}
}