{
  "type": "Feature",
  "properties": {
    "iso:country":"GB",
    "sg:address":"Sidley Community Centre, 121 Ninfield Road",
    "sg:city":"Bexhill-on-sea",
    "sg:classifiers":[
        {
            "category":"Community Center",
            "type":"Public Place"
        },
        {
            "category":"Organizations",
            "subcategory":"Non-profit Organization",
            "type":"Services"
        }
    ],
    "sg:phone":"+44 1424 212789",
    "sg:postcode":"TN39 5BD",
    "sg:province":"East Sussex",
    "sg:tags":[
        "charitable",
        "organisation",
        "charity",
        "centre"
    ],
    "sg:website":"http://www.sidleyca.com",
    "wof:name":"Sidley Community Association",
    "wof:placetype":"venue"
},
  "geometry": {"coordinates":[0.46283,50.85939],"type":"Point"}
}