{
  "type": "Feature",
  "properties": {
    "addr:full":"32 Cromwell Road Luton Bedfordshire LU3 1DN",
    "addr:housenumber":"32",
    "addr:postcode":"lu3 1dn",
    "addr:street":"Cromwell Road",
    "iso:country":"GB",
    "sg:address":"32 Cromwell Road",
    "sg:city":"Luton",
    "sg:classifiers":[
        {
            "category":"Food & Beverages",
            "subcategory":"Meat & Fish",
            "type":"Retail Goods"
        }
    ],
    "sg:phone":"+44 7956 371553",
    "sg:postcode":"LU3 1DN",
    "sg:province":"Bedfordshire",
    "sg:tags":[
        "merchant"
    ],
    "wof:name":"Bari & Sons Ltd.",
    "wof:placetype":"venue"
},
  "geometry": {"coordinates":[-0.422473,51.886795],"type":"Point"}
}