{
  "type": "Feature",
  "properties": {
    "addr:full":"2 Station Rd North Egham Surrey TW20 9LE",
    "addr:housenumber":"2",
    "addr:postcode":"tw20 9le",
    "addr:street":"Station Rd",
    "iso:country":"GB",
    "sg:address":"2 Station Rd North",
    "sg:city":"Egham",
    "sg:classifiers":[
        {
            "category":"Personal",
            "subcategory":"Beauty Salon",
            "type":"Services"
        }
    ],
    "sg:phone":"+44 1784 436146",
    "sg:postcode":"TW20 9LE",
    "sg:province":"Surrey",
    "sg:tags":[
        "unisex",
        "hairdresser"
    ],
    "wof:name":"The Hair Emporium",
    "wof:placetype":"venue"
},
  "geometry": {"coordinates":[-0.5487909913,51.4314689636],"type":"Point"}
}