{
  "type": "Feature",
  "properties": {
    "iso:country":"GB",
    "sg:address":"104 Victoria Road",
    "sg:city":"Scarborough",
    "sg:classifiers":[
        {
            "category":"Food & Beverages",
            "subcategory":"Fruits & Vegetables",
            "type":"Retail Goods"
        }
    ],
    "sg:phone":"+44 1723 500335",
    "sg:postcode":"YO11 1SL",
    "sg:province":"North Yorkshire",
    "sg:tags":[
        "greengrocer"
    ],
    "wof:name":"Kerry's",
    "wof:placetype":"venue"
},
  "geometry": {"coordinates":[-0.406643,54.281033],"type":"Point"}
}