{
  "type": "Feature",
  "properties": {
    "iso:country":"GB",
    "sg:address":"9 Market Square",
    "sg:city":"Lytham St Annes",
    "sg:classifiers":[
        {
            "category":"Restaurant",
            "type":"Food & Drink"
        }
    ],
    "sg:phone":"+44 1253 736492",
    "sg:postcode":"FY8 5LW",
    "sg:province":"Lancashire",
    "sg:tags":[
        "-",
        "english"
    ],
    "wof:name":"The Lytham Kitchen",
    "wof:placetype":"venue"
},
  "geometry": {"coordinates":[-2.964363,53.737007],"type":"Point"}
}