{
  "type": "Feature",
  "properties": {
    "addr:full":"70 High Street Pewsey Wiltshire SN9 5AQ",
    "addr:housenumber":"70",
    "addr:postcode":"sn9 5aq",
    "addr:street":"High Street",
    "iso:country":"GB",
    "sg:address":"70 High Street",
    "sg:city":"Pewsey",
    "sg:classifiers":[
        {
            "category":"Bars & Pubs",
            "type":"Food & Drink"
        }
    ],
    "sg:phone":"+44 1672 563414",
    "sg:postcode":"SN9 5AQ",
    "sg:province":"Wiltshire",
    "sg:tags":[
        "pubs",
        "inn"
    ],
    "wof:name":"Alfreds",
    "wof:placetype":"venue"
},
  "geometry": {"coordinates":[-1.760966,51.340275],"type":"Point"}
}