{
  "type": "Feature",
  "properties": {
    "iso:country":"GB",
    "sg:address":"83 Lawley Middleway",
    "sg:city":"Birmingham",
    "sg:classifiers":[
        {
            "category":"Retail",
            "subcategory":"Auto Repair",
            "type":"Services"
        }
    ],
    "sg:postcode":"B4 7XH",
    "sg:province":"West Midlands",
    "sg:tags":[
        "engine",
        "car",
        "specialist"
    ],
    "wof:name":"E M C",
    "wof:placetype":"venue"
},
  "geometry": {"coordinates":[-1.881976,52.48558],"type":"Point"}
}