{
  "type": "Feature",
  "properties": {
    "addr:full":"Unit 3 Hawthorn Ho Forth Banks Newcastle-upon-tyne Tyne and Wear NE1 3SG",
    "addr:housenumber":"unit 3",
    "addr:postcode":"ne1 3sg",
    "addr:street":"Hawthorn Ho",
    "iso:country":"GB",
    "sg:address":"Unit 3 Hawthorn Ho Forth Banks",
    "sg:city":"Newcastle-upon-tyne",
    "sg:classifiers":[
        {
            "category":"Professional",
            "subcategory":"Engineering",
            "type":"Services"
        }
    ],
    "sg:postcode":"NE1 3SG",
    "sg:province":"Tyne and Wear",
    "sg:tags":[
        "consulting",
        "engineer"
    ],
    "wof:name":"Association of Independant Management Ma",
    "wof:placetype":"venue"
},
  "geometry": {"coordinates":[-1.61657,54.965881],"type":"Point"}
}