{
  "type": "Feature",
  "properties": {
    "iso:country":"GB",
    "sg:address":"2b Franklin Rd",
    "sg:city":"Watford",
    "sg:classifiers":[
        {
            "category":"Health Services",
            "subcategory":"Chiropractor",
            "type":"Services"
        }
    ],
    "sg:phone":"+44 1923 241199",
    "sg:postcode":"WD1 1QD",
    "sg:province":"Hertfordshire",
    "wof:name":"Watford Chiropractic Clinic",
    "wof:placetype":"venue"
},
  "geometry": {"coordinates":[-0.399445,51.661648],"type":"Point"}
}