{
  "type": "Feature",
  "properties": {
    "iso:country":"GB",
    "sg:address":"Lythe Avenue",
    "sg:city":"Hull",
    "sg:classifiers":[
        {
            "category":"Manufacturing",
            "subcategory":"Wood Products",
            "type":"Manufacturing & Wholesale Goods"
        },
        {
            "category":"Manufacturing",
            "subcategory":"Petroleum Products",
            "type":"Manufacturing & Wholesale Goods"
        },
        {
            "category":"Building & Trades",
            "subcategory":"Construction",
            "type":"Services"
        }
    ],
    "sg:postcode":"HU5 4TE",
    "sg:province":"East Riding of Yorkshire",
    "sg:tags":[
        "double",
        "shaving",
        "glazing",
        "sawmill",
        "joinery"
    ],
    "wof:name":"Marshall Joinery",
    "wof:placetype":"venue"
},
  "geometry": {"coordinates":[-0.3935639858,53.7703094482],"type":"Point"}
}