{
  "type": "Feature",
  "properties": {
    "iso:country":"GB",
    "sg:address":"Lower Barn, Shop Lane",
    "sg:city":"Northampton",
    "sg:classifiers":[
        {
            "category":"Real Estate",
            "subcategory":"Developer",
            "type":"Services"
        }
    ],
    "sg:postcode":"NN7 1EJ",
    "sg:province":"Buckinghamshire",
    "sg:tags":[
        "property"
    ],
    "wof:name":"Orderkind Ltd.",
    "wof:placetype":"venue"
},
  "geometry": {"coordinates":[-0.73496,52.20422],"type":"Point"}
}