{
  "type": "Feature",
  "properties": {
    "iso:country":"GB",
    "sg:address":"17 High Street",
    "sg:city":"Manningtree",
    "sg:classifiers":[
        {
            "category":"Professional",
            "subcategory":"Art Services",
            "type":"Services"
        }
    ],
    "sg:postcode":"CO11 1AG",
    "sg:province":"Essex",
    "sg:tags":[
        "photographer"
    ],
    "wof:name":"Lantern Photographic Studios",
    "wof:placetype":"venue"
},
  "geometry": {"coordinates":[1.0632059574,51.9455223083],"type":"Point"}
}