{
  "type": "Feature",
  "properties": {
    "addr:full":"221 High Street Arbroath Angus DD11 1DZ",
    "addr:housenumber":"221",
    "addr:postcode":"dd11 1dz",
    "addr:street":"High Street",
    "iso:country":"GB",
    "sg:address":"221 High Street",
    "sg:city":"Arbroath",
    "sg:classifiers":[
        {
            "category":"Shopping",
            "subcategory":"Department Store",
            "type":"Retail Goods"
        },
        {
            "category":"Shopping",
            "subcategory":"Gifts & Souvenirs",
            "type":"Retail Goods"
        }
    ],
    "sg:phone":"+44 1241 872493",
    "sg:postcode":"DD11 1DZ",
    "sg:province":"Angus",
    "sg:tags":[
        "shop"
    ],
    "wof:name":"Loretta McTavish",
    "wof:placetype":"venue"
},
  "geometry": {"coordinates":[-2.5831079483,56.5615234375],"type":"Point"}
}