{
  "type": "Feature",
  "properties": {
    "addr:full":"3 Newbrook Road, Over-hulton Bolton Lancashire BL5 1EL",
    "addr:housenumber":"3",
    "addr:postcode":"bl5 1el",
    "addr:street":"Newbrook Road Over-Hulton",
    "iso:country":"GB",
    "sg:address":"3 Newbrook Road, Over-hulton",
    "sg:city":"Bolton",
    "sg:classifiers":[
        {
            "category":"Travel",
            "subcategory":"Travel Agent",
            "type":"Entertainment"
        }
    ],
    "sg:phone":"+44 1204 654711",
    "sg:postcode":"BL5 1EL",
    "sg:province":"Lancashire",
    "wof:name":"Scopeedge Ltd.",
    "wof:placetype":"venue"
},
  "geometry": {"coordinates":[-2.4689559937,53.5476112366],"type":"Point"}
}