{
  "type": "Feature",
  "properties": {
    "iso:country":"GB",
    "sg:address":"65 King Street",
    "sg:city":"Belper",
    "sg:classifiers":[
        {
            "category":"Professional",
            "subcategory":"Lawyer & Legal Services",
            "type":"Services"
        }
    ],
    "sg:phone":"+44 1773 821771",
    "sg:postcode":"DE56 1QA",
    "sg:province":"Derbyshire",
    "sg:tags":[
        "solicitor"
    ],
    "wof:name":"Alan Kerry & Co",
    "wof:placetype":"venue"
},
  "geometry": {"coordinates":[-1.479742,53.023491],"type":"Point"}
}