{
  "type": "Feature",
  "properties": {
    "iso:country":"GB",
    "sg:address":"Clayton Works, Pontardlulais",
    "sg:city":"Swansea",
    "sg:classifiers":[
        {
            "category":"Manufacturing",
            "subcategory":"Metals",
            "type":"Manufacturing & Wholesale Goods"
        }
    ],
    "sg:phone":"+44 1792 882301",
    "sg:postcode":"SA4 8SJ",
    "sg:province":"Carmarthenshire",
    "sg:tags":[
        "steel",
        "stockholder"
    ],
    "wof:name":"Morgan E Rees & Co. (Steel) Ltd.",
    "wof:placetype":"venue"
},
  "geometry": {"coordinates":[-4.0436301231,51.7163009644],"type":"Point"}
}