{
  "type": "Feature",
  "properties": {
    "addr:full":"12 Stanley Road Sheffield Derbyshire S8 9JB",
    "addr:housenumber":"12",
    "addr:postcode":"s8 9jb",
    "addr:street":"Stanley Road",
    "iso:country":"GB",
    "sg:address":"12 Stanley Road",
    "sg:city":"Sheffield",
    "sg:classifiers":[
        {
            "category":"Health Services",
            "subcategory":"Health Practitioner",
            "type":"Services"
        }
    ],
    "sg:phone":"+44 114 250 7767",
    "sg:postcode":"S8 9JB",
    "sg:province":"Derbyshire",
    "sg:tags":[
        "homoeopathic"
    ],
    "wof:name":"Susan Hartley",
    "wof:placetype":"venue"
},
  "geometry": {"coordinates":[-1.4623179436,53.3553161621],"type":"Point"}
}