{
  "type": "Feature",
  "properties": {
    "addr:full":"Riverside Works, Cropredy Banbury Northamptonshire OX17 1PQ",
    "addr:housenumber":"cropredy",
    "addr:postcode":"ox17 1pq",
    "iso:country":"GB",
    "sg:address":"Riverside Works, Cropredy",
    "sg:city":"Banbury",
    "sg:classifiers":[
        {
            "category":"Professional",
            "subcategory":"Engineering",
            "type":"Services"
        }
    ],
    "sg:phone":"+44 1295 758911",
    "sg:postcode":"OX17 1PQ",
    "sg:province":"Northamptonshire",
    "sg:tags":[
        "contractor",
        "electrical",
        "engineer"
    ],
    "wof:name":"C J Swain Electrical Ltd.",
    "wof:placetype":"venue"
},
  "geometry": {"coordinates":[-1.3196979761,52.1168708801],"type":"Point"}
}