{
  "type": "Feature",
  "properties": {
    "addr:full":"Unit 4, Station Road Industrial Estate, Great Harwood Blackburn Lancashire BB6 7BB",
    "addr:housenumber":"unit 4",
    "addr:postcode":"bb6 7bb",
    "addr:street":"Station Road Industrial Estate Great",
    "iso:country":"GB",
    "sg:address":"Unit 4, Station Road Industrial Estate, Great Harwood",
    "sg:city":"Blackburn",
    "sg:classifiers":[
        {
            "category":"Professional",
            "subcategory":"Engineering",
            "type":"Services"
        }
    ],
    "sg:phone":"+44 1254 888009",
    "sg:postcode":"BB6 7BB",
    "sg:province":"Lancashire",
    "sg:tags":[
        "precision",
        "engineer"
    ],
    "wof:name":"Equinox Precision Engineering",
    "wof:placetype":"venue"
},
  "geometry": {"coordinates":[-2.3974480629,53.7856941223],"type":"Point"}
}