{
  "type": "Feature",
  "properties": {
    "iso:country":"GB",
    "sg:address":"10 New Street",
    "sg:city":"Porthmadog",
    "sg:classifiers":[
        {
            "category":"Cinema",
            "subcategory":"Movie Rental",
            "type":"Entertainment"
        }
    ],
    "sg:phone":"+44 1766 514251",
    "sg:postcode":"LL49 9ED",
    "sg:province":"Gwynedd",
    "sg:tags":[
        "video",
        "library"
    ],
    "wof:name":"Video Llyn",
    "wof:placetype":"venue"
},
  "geometry": {"coordinates":[-4.131324,52.929119],"type":"Point"}
}