{
  "type": "Feature",
  "properties": {
    "addr:full":"14 Beaumont Close Walton-on-the-naze Essex CO14 8TX",
    "addr:housenumber":"14",
    "addr:postcode":"co14 8tx",
    "addr:street":"Beaumont Close",
    "iso:country":"GB",
    "sg:address":"14 Beaumont Close",
    "sg:city":"Walton-on-the-naze",
    "sg:classifiers":[
        {
            "category":"Retail",
            "subcategory":"Driving School",
            "type":"Services"
        }
    ],
    "sg:postcode":"CO14 8TX",
    "sg:province":"Essex",
    "wof:name":"A Lillistone",
    "wof:placetype":"venue"
},
  "geometry": {"coordinates":[1.2501809597,51.8472709656],"type":"Point"}
}