{
  "type": "Feature",
  "properties": {
    "addr:full":"Jamieson Drive Stornoway Eilean Siar HS1 2LF",
    "addr:postcode":"hs1 2lf",
    "addr:street":"Jamieson Drive",
    "iso:country":"GB",
    "sg:address":"Jamieson Drive",
    "sg:city":"Stornoway",
    "sg:classifiers":[
        {
            "category":"Education",
            "subcategory":"School",
            "type":"Public Place"
        }
    ],
    "sg:phone":"+44 1851 703418",
    "sg:postcode":"HS1 2LF",
    "sg:province":"Eilean Siar",
    "sg:tags":[
        "local",
        "authority"
    ],
    "wof:name":"Stornoway Primary School",
    "wof:placetype":"venue"
},
  "geometry": {"coordinates":[-6.3794841766,58.2161712646],"type":"Point"}
}