{
  "type": "Feature",
  "properties": {
    "iso:country":"GB",
    "sg:address":"18th Floor, Royex Ho",
    "sg:city":"London",
    "sg:classifiers":[
        {
            "category":"Fast Food",
            "type":"Food & Drink"
        }
    ],
    "sg:postcode":"EC2V 7HR",
    "sg:province":"Greater London",
    "sg:tags":[
        "away",
        "take"
    ],
    "wof:name":"Novored Ltd",
    "wof:placetype":"venue"
},
  "geometry": {"coordinates":[-0.09329,51.517071],"type":"Point"}
}