{
  "type": "Feature",
  "properties": {
    "iso:country":"GB",
    "sg:address":"26-31 Back Goldspink Lane, Newcastle",
    "sg:city":"Newcastle Upon Tyne",
    "sg:classifiers":[
        {
            "category":"Professional",
            "subcategory":"Art Services",
            "type":"Services"
        }
    ],
    "sg:phone":"+44 191 222 1419",
    "sg:postcode":"NE2 1NU",
    "sg:province":"Tyne and Wear",
    "sg:tags":[
        "graphic",
        "designer"
    ],
    "wof:name":"Red Square Design",
    "wof:placetype":"venue"
},
  "geometry": {"coordinates":[-1.596128,54.983143],"type":"Point"}
}