{
  "type": "Feature",
  "properties": {
    "addr:full":"Fishing Cottage, Lower Brook, Kings Somborne Stockbridge Hampshire SO20 6QR",
    "addr:postcode":"so20 6qr",
    "addr:street":"Lower Brook",
    "iso:country":"GB",
    "sg:address":"Fishing Cottage, Lower Brook, Kings Somborne",
    "sg:city":"Stockbridge",
    "sg:classifiers":[
        {
            "category":"Farming",
            "subcategory":"Farm",
            "type":"Manufacturing & Wholesale Goods"
        }
    ],
    "sg:phone":"+44 1794 388677",
    "sg:postcode":"SO20 6QR",
    "sg:province":"Hampshire",
    "sg:tags":[
        "hatchery"
    ],
    "wof:name":"Wester Ross Salmon Ltd.",
    "wof:placetype":"venue"
},
  "geometry": {"coordinates":[-1.4941020012,51.1142807007],"type":"Point"}
}