{
  "type": "Feature",
  "properties": {
    "addr:full":"338-346 Goswell Road London Greater London EC1V 7QP",
    "addr:housenumber":"338-346",
    "addr:postcode":"ec1v 7qp",
    "addr:street":"Goswell Road",
    "iso:country":"GB",
    "sg:address":"338-346 Goswell Road",
    "sg:city":"London",
    "sg:classifiers":[
        {
            "category":"Retail",
            "subcategory":"Event Space",
            "type":"Services"
        }
    ],
    "sg:phone":"+44 20 7520 1540",
    "sg:postcode":"EC1V 7QP",
    "sg:province":"Greater London",
    "sg:tags":[
        "exhibition",
        "organiser"
    ],
    "wof:name":"40 Degrees",
    "wof:placetype":"venue"
},
  "geometry": {"coordinates":[-0.103798002,51.5308609009],"type":"Point"}
}