{
  "type": "Feature",
  "properties": {
    "addr:full":"Goat Mill Rd Merthyr Tydfil Caerphilly CF48 3TD",
    "addr:postcode":"cf48 3td",
    "addr:street":"Goat Mill Rd",
    "iso:country":"GB",
    "sg:address":"Goat Mill Rd",
    "sg:city":"Merthyr Tydfil",
    "sg:classifiers":[
        {
            "category":"Manufacturing",
            "subcategory":"Building Materials",
            "type":"Manufacturing & Wholesale Goods"
        }
    ],
    "sg:phone":"+44 1685 376908",
    "sg:postcode":"CF48 3TD",
    "sg:province":"Caerphilly",
    "sg:tags":[
        "concrete",
        "product"
    ],
    "wof:name":"Merthyr Patio Centre",
    "wof:placetype":"venue"
},
  "geometry": {"coordinates":[-3.3534290791,51.7589530945],"type":"Point"}
}