{
  "type": "Feature",
  "properties": {
    "iso:country":"GB",
    "sg:address":"86 High Street, Gorseinon",
    "sg:city":"Swansea",
    "sg:classifiers":[
        {
            "category":"Banks & Credit Unions",
            "subcategory":"Financial Services",
            "type":"Services"
        }
    ],
    "sg:phone":"+44 1792 896389",
    "sg:postcode":"SA4 4BL",
    "sg:province":"Carmarthenshire",
    "sg:tags":[
        "building",
        "society"
    ],
    "wof:name":"Principality Building Society",
    "wof:placetype":"venue"
},
  "geometry": {"coordinates":[-4.041495,51.669308],"type":"Point"}
}