{
  "type": "Feature",
  "properties": {
    "addr:full":"84 Holden Close Dagenham Essex RM8 2QT",
    "addr:housenumber":"84",
    "addr:postcode":"rm8 2qt",
    "addr:street":"Holden Close",
    "iso:country":"GB",
    "sg:address":"84 Holden Close",
    "sg:city":"Dagenham",
    "sg:classifiers":[
        {
            "category":"Building & Trades",
            "subcategory":"Construction",
            "type":"Services"
        }
    ],
    "sg:phone":"+44 20 8599 3416",
    "sg:postcode":"RM8 2QT",
    "sg:province":"Essex",
    "sg:tags":[
        "builder"
    ],
    "wof:name":"F & R Construction",
    "wof:placetype":"venue"
},
  "geometry": {"coordinates":[0.1154190004,51.5569419861],"type":"Point"}
}