{
  "type": "Feature",
  "properties": {
    "iso:country":"GB",
    "sg:address":"57 Lacrosse Avenue",
    "sg:city":"Oldham",
    "sg:classifiers":[
        {
            "category":"Banks & Credit Unions",
            "subcategory":"Financial Services",
            "type":"Services"
        }
    ],
    "sg:phone":"+44 161 624 0174",
    "sg:postcode":"OL8 4LU",
    "sg:province":"Lancashire",
    "sg:tags":[
        "adviser"
    ],
    "wof:name":"M.A Corless Financial Broker",
    "wof:placetype":"venue"
},
  "geometry": {"coordinates":[-2.130388,53.529251],"type":"Point"}
}