{
  "type": "Feature",
  "properties": {
    "addr:full":"68 Mossdale Rd Leicester Leicestershire LE3 2US",
    "addr:housenumber":"68",
    "addr:postcode":"le3 2us",
    "addr:street":"Mossdale Rd",
    "iso:country":"GB",
    "sg:address":"68 Mossdale Rd",
    "sg:city":"Leicester",
    "sg:classifiers":[
        {
            "category":"Building & Trades",
            "subcategory":"Construction",
            "type":"Services"
        }
    ],
    "sg:phone":"+44 116 289 0096",
    "sg:postcode":"LE3 2US",
    "sg:province":"Leicestershire",
    "sg:tags":[
        "flooring"
    ],
    "wof:name":"Blockpavers",
    "wof:placetype":"venue"
},
  "geometry": {"coordinates":[-1.1828459501,52.6119270325],"type":"Point"}
}