{
  "type": "Feature",
  "properties": {
    "iso:country":"GB",
    "sg:address":", Beazley End",
    "sg:city":"Braintree",
    "sg:classifiers":[
        {
            "category":"Bars & Pubs",
            "type":"Food & Drink"
        }
    ],
    "sg:phone":"+44 1371 850566",
    "sg:postcode":"CM7 5JH",
    "sg:province":"Essex",
    "sg:tags":[
        "pubs",
        "inn"
    ],
    "wof:name":"The Cock Inn",
    "wof:placetype":"venue"
},
  "geometry": {"coordinates":[0.5532420278,51.8777580261],"type":"Point"}
}