{
  "type": "Feature",
  "properties": {
    "iso:country":"GB",
    "sg:address":"Home Farm, Nottingham Rd, Nuthall",
    "sg:city":"Nottingham",
    "sg:classifiers":[
        {
            "category":"Farming",
            "subcategory":"Farm",
            "type":"Manufacturing & Wholesale Goods"
        }
    ],
    "sg:postcode":"NG16 1DP",
    "sg:province":"Derbyshire",
    "sg:tags":[
        "mixed",
        "crop"
    ],
    "wof:name":"Steeples,Robert Stuart,",
    "wof:placetype":"venue"
},
  "geometry": {"coordinates":[-1.231074,52.995167],"type":"Point"}
}