{
  "type": "Feature",
  "properties": {
    "iso:country":"GB",
    "sg:address":"Newcastle Technopole, Kings Manor",
    "sg:city":"Newcastle Upon Tyne",
    "sg:classifiers":[
        {
            "category":"Professional",
            "subcategory":"Engineering",
            "type":"Services"
        }
    ],
    "sg:phone":"+44 191 201 2127",
    "sg:postcode":"NE1 6PA",
    "sg:province":"Tyne and Wear",
    "sg:tags":[
        "consultant",
        "structural"
    ],
    "wof:name":"Beattie Watkinson",
    "wof:placetype":"venue"
},
  "geometry": {"coordinates":[-1.6061099768,54.9734382629],"type":"Point"}
}