{
  "type": "Feature",
  "properties": {
    "iso:country":"GB",
    "sg:address":"Rectory Lane, Glinton",
    "sg:city":"Peterborough",
    "sg:classifiers":[
        {
            "category":"Shopping",
            "subcategory":"Department Store",
            "type":"Retail Goods"
        }
    ],
    "sg:phone":"+44 1733 253433",
    "sg:postcode":"PE6 7LR",
    "sg:province":"Cambridgeshire",
    "wof:name":"Rectory Stores",
    "wof:placetype":"venue"
},
  "geometry": {"coordinates":[-0.296139,52.638981],"type":"Point"}
}