{
  "type": "Feature",
  "properties": {
    "addr:full":"102b Mytchett Road, Mytchett Camberley Hampshire GU16 6ET",
    "addr:housenumber":"102b",
    "addr:postcode":"gu16 6et",
    "addr:street":"Mytchett Road",
    "iso:country":"GB",
    "sg:address":"102b Mytchett Road, Mytchett",
    "sg:city":"Camberley",
    "sg:classifiers":[
        {
            "category":"Home & Garden",
            "subcategory":"Household Appliances",
            "type":"Retail Goods"
        }
    ],
    "sg:postcode":"GU16 6ET",
    "sg:province":"Hampshire",
    "sg:tags":[
        "electrical"
    ],
    "wof:name":"R Tavenor",
    "wof:placetype":"venue"
},
  "geometry": {"coordinates":[-0.726209,51.291809],"type":"Point"}
}