{
  "type": "Feature",
  "properties": {
    "addr:full":"53 Lwr Olland St Bungay Norfolk NR35 1BY",
    "addr:housenumber":"53",
    "addr:postcode":"nr35 1by",
    "addr:street":"Lwr Olland St",
    "iso:country":"GB",
    "sg:address":"53 Lwr Olland St",
    "sg:city":"Bungay",
    "sg:classifiers":[
        {
            "category":"Bars & Pubs",
            "type":"Food & Drink"
        }
    ],
    "sg:postcode":"NR35 1BY",
    "sg:province":"Norfolk",
    "sg:tags":[
        "pubs",
        "inn"
    ],
    "wof:name":"Smith,Joseph Michael,",
    "wof:placetype":"venue"
},
  "geometry": {"coordinates":[1.440471,52.452991],"type":"Point"}
}