{
  "type": "Feature",
  "properties": {
    "addr:full":"20 Hurst Street Birmingham West Midlands B5 4BN",
    "addr:housenumber":"20",
    "addr:postcode":"b5 4bn",
    "addr:street":"Hurst Street",
    "iso:country":"GB",
    "sg:address":"20 Hurst Street",
    "sg:city":"Birmingham",
    "sg:classifiers":[
        {
            "category":"Shopping",
            "subcategory":"Mobile Phones",
            "type":"Retail Goods"
        }
    ],
    "sg:postcode":"B5 4BN",
    "sg:province":"West Midlands",
    "wof:name":"Wah Communications",
    "wof:placetype":"venue"
},
  "geometry": {"coordinates":[-1.8980679512,52.4754104614],"type":"Point"}
}