{
  "type": "Feature",
  "properties": {
    "addr:full":"Bradbourne House, Stable Block, East Malling West Malling Kent ME19 6DZ",
    "addr:postcode":"me19 6dz",
    "addr:street":"Malling West",
    "iso:country":"GB",
    "sg:address":"Bradbourne House, Stable Block, East Malling",
    "sg:city":"West Malling",
    "sg:classifiers":[
        {
            "category":"Government",
            "subcategory":"Post Office",
            "type":"Public Place"
        }
    ],
    "sg:phone":"+44 1732 845115",
    "sg:postcode":"ME19 6DZ",
    "sg:province":"Kent",
    "sg:tags":[
        "organisation",
        "soc",
        "research"
    ],
    "wof:name":"The Apple & Pear Research Council",
    "wof:placetype":"venue"
},
  "geometry": {"coordinates":[0.41294,51.293709],"type":"Point"}
}