{
  "type": "Feature",
  "properties": {
    "iso:country":"GB",
    "sg:address":"Pentreheylin",
    "sg:city":"Llanymynech",
    "sg:classifiers":[
        {
            "category":"Farming",
            "subcategory":"Farm",
            "type":"Manufacturing & Wholesale Goods"
        }
    ],
    "sg:phone":"+44 1691 830310",
    "sg:postcode":"SY22 6PG",
    "sg:province":"Shropshire",
    "sg:tags":[
        "mixed",
        "crop"
    ],
    "wof:name":"G H & C M Savage",
    "wof:placetype":"venue"
},
  "geometry": {"coordinates":[-3.0893540382,52.7808532715],"type":"Point"}
}