{
  "type": "Feature",
  "properties": {
    "addr:full":"16 High Street Hailsham East Sussex BN27 1BJ",
    "addr:housenumber":"16",
    "addr:postcode":"bn27 1bj",
    "addr:street":"High Street",
    "iso:country":"GB",
    "sg:address":"16 High Street",
    "sg:city":"Hailsham",
    "sg:classifiers":[
        {
            "category":"Shopping",
            "subcategory":"Gifts & Souvenirs",
            "type":"Retail Goods"
        }
    ],
    "sg:phone":"+44 1323 449032",
    "sg:postcode":"BN27 1BJ",
    "sg:province":"East Sussex",
    "sg:tags":[
        "shop"
    ],
    "wof:name":"Smiles",
    "wof:placetype":"venue"
},
  "geometry": {"coordinates":[0.259721,50.863178],"type":"Point"}
}