{
  "type": "Feature",
  "properties": {
    "iso:country":"GB",
    "sg:address":"31 St Thomas Street",
    "sg:city":"Weymouth",
    "sg:classifiers":[
        {
            "category":"Real Estate",
            "subcategory":"Real Estate Agent",
            "type":"Services"
        }
    ],
    "sg:phone":"+44 1305 783488",
    "sg:postcode":"DT4 8EJ",
    "sg:province":"Dorset",
    "wof:name":"Fox & Sons Estate Agents",
    "wof:placetype":"venue"
},
  "geometry": {"coordinates":[-2.4546279907,50.6092224121],"type":"Point"}
}