{
  "type": "Feature",
  "properties": {
    "iso:country":"GB",
    "sg:address":"120 Grenville St",
    "sg:city":"Stockport",
    "sg:classifiers":[
        {
            "category":"Shopping",
            "subcategory":"News",
            "type":"Retail Goods"
        }
    ],
    "sg:phone":"+44 161 477 1346",
    "sg:postcode":"SK3 9ET",
    "sg:province":"Cheshire",
    "sg:tags":[
        "newsagent"
    ],
    "wof:name":"S J & J D Cooke",
    "wof:placetype":"venue"
},
  "geometry": {"coordinates":[-2.170729,53.402912],"type":"Point"}
}