{
  "type": "Feature",
  "properties": {
    "addr:full":"Stoke Road Hinckley Leicestershire LE10 3EA",
    "addr:postcode":"le10 3ea",
    "addr:street":"Stoke Road",
    "iso:country":"GB",
    "sg:address":"Stoke Road",
    "sg:city":"Hinckley",
    "sg:classifiers":[
        {
            "category":"Education",
            "subcategory":"School",
            "type":"Public Place"
        }
    ],
    "sg:phone":"+44 1455 637266",
    "sg:postcode":"LE10 3EA",
    "sg:province":"Leicestershire",
    "sg:tags":[
        "local",
        "authority"
    ],
    "wof:name":"Hinckley Richmond Primary School",
    "wof:placetype":"venue"
},
  "geometry": {"coordinates":[-1.390515,52.559303],"type":"Point"}
}