{
  "type": "Feature",
  "properties": {
    "addr:full":"Fairview Industrial Estate, Marsh Way Rainham Essex RM13 8UH",
    "addr:housenumber":"estate",
    "addr:postcode":"rm13 8uh",
    "addr:street":"Marsh Way",
    "iso:country":"GB",
    "sg:address":"Fairview Industrial Estate, Marsh Way",
    "sg:city":"Rainham",
    "sg:classifiers":[
        {
            "category":"Freight",
            "type":"Transportation"
        }
    ],
    "sg:phone":"+44 1708 526622",
    "sg:postcode":"RM13 8UH",
    "sg:province":"Essex",
    "sg:tags":[
        "cargo",
        "handling",
        "forwarders"
    ],
    "wof:name":"de Georgio Transport (U K) Ltd.",
    "wof:placetype":"venue"
},
  "geometry": {"coordinates":[0.1904260069,51.5179138184],"type":"Point"}
}