{
  "type": "Feature",
  "properties": {
    "addr:full":"21 Cowgate Peterborough Cambridgeshire PE1 1LZ",
    "addr:housenumber":"21",
    "addr:postcode":"pe1 1lz",
    "addr:street":"Cowgate Peterborough",
    "iso:country":"GB",
    "sg:address":"21 Cowgate",
    "sg:city":"Peterborough",
    "sg:classifiers":[
        {
            "category":"Professional",
            "subcategory":"Employment Agencies",
            "type":"Services"
        }
    ],
    "sg:phone":"+44 1733 558877",
    "sg:postcode":"PE1 1LZ",
    "sg:province":"Cambridgeshire",
    "sg:tags":[
        "consultant",
        "recruitment"
    ],
    "wof:name":"INTERACTION RECRUITMENT PLC",
    "wof:placetype":"venue"
},
  "geometry": {"coordinates":[-0.246049,52.573002],"type":"Point"}
}