{
  "type": "Feature",
  "properties": {
    "iso:country":"GB",
    "sg:address":"2 Glebe Road",
    "sg:city":"Huntingdon",
    "sg:classifiers":[
        {
            "category":"Professional",
            "subcategory":"Engineering",
            "type":"Services"
        },
        {
            "category":"Professional",
            "subcategory":"Testing Lab",
            "type":"Services"
        }
    ],
    "sg:phone":"+44 1480 412451",
    "sg:postcode":"PE29 7DR",
    "sg:province":"Cambridgeshire",
    "sg:tags":[
        "engineer",
        "inspection",
        "calibration"
    ],
    "wof:name":"THURLBY THANDAR INSTRUMENTS LTD",
    "wof:placetype":"venue"
},
  "geometry": {"coordinates":[-0.182324,52.347126],"type":"Point"}
}