{
  "type": "Feature",
  "properties": {
    "iso:country":"GB",
    "sg:address":"8 Sussex Av",
    "sg:city":"Hailsham",
    "sg:classifiers":[
        {
            "category":"Building & Trades",
            "subcategory":"Construction",
            "type":"Services"
        }
    ],
    "sg:phone":"+44 1323 440073",
    "sg:postcode":"BN27 3EA",
    "sg:province":"East Sussex",
    "sg:tags":[
        "builder"
    ],
    "wof:name":"D Toms",
    "wof:placetype":"venue"
},
  "geometry": {"coordinates":[0.2514449954,50.863822937],"type":"Point"}
}