{
  "type": "Feature",
  "properties": {
    "addr:full":"6 Warwick Ct Bloomsbury Greater London WC1R 5DJ",
    "addr:housenumber":"6",
    "addr:postcode":"wc1r 5dj",
    "addr:street":"Warwick Ct",
    "iso:country":"GB",
    "sg:address":"6 Warwick Ct",
    "sg:city":"Bloomsbury",
    "sg:classifiers":[
        {
            "category":"Building & Trades",
            "subcategory":"Construction",
            "type":"Services"
        }
    ],
    "sg:phone":"+44 20 7584 6334",
    "sg:postcode":"WC1R 5DJ",
    "sg:province":"Greater London",
    "sg:tags":[
        "decorator",
        "painter"
    ],
    "wof:name":"James Lipinsky Co Ltd",
    "wof:placetype":"venue"
},
  "geometry": {"coordinates":[-0.1143309996,51.5186157227],"type":"Point"}
}