{
  "type": "Feature",
  "properties": {
    "addr:full":"11 Mkt Place Prescot Merseyside L34 5SB",
    "addr:housenumber":"11",
    "addr:postcode":"l34 5sb",
    "addr:street":"Mkt Place",
    "iso:country":"GB",
    "sg:address":"11 Mkt Place",
    "sg:city":"Prescot",
    "sg:classifiers":[
        {
            "category":"Sports & Exercise",
            "subcategory":"Gym",
            "type":"Entertainment"
        }
    ],
    "sg:postcode":"L34 5SB",
    "sg:province":"Merseyside",
    "sg:tags":[
        "fitness",
        "health",
        "centre"
    ],
    "wof:name":"Elegant Sunbeds Ltd",
    "wof:placetype":"venue"
},
  "geometry": {"coordinates":[-2.804989,53.428341],"type":"Point"}
}