{
  "type": "Feature",
  "properties": {
    "iso:country":"GB",
    "sg:address":"5 Eastgate",
    "sg:city":"Lincoln",
    "sg:classifiers":[
        {
            "category":"Shopping",
            "subcategory":"Clothing, Apparel, & Fashions",
            "type":"Retail Goods"
        }
    ],
    "sg:phone":"+44 1522 512141",
    "sg:postcode":"LN2 1QA",
    "sg:province":"Lincolnshire",
    "sg:tags":[
        "menswear"
    ],
    "wof:name":"Chesters Exclusive Menswear",
    "wof:placetype":"venue"
},
  "geometry": {"coordinates":[-0.5381749868,53.2351341248],"type":"Point"}
}