{
  "type": "Feature",
  "properties": {
    "addr:full":"Unit 2 Newmill Rd Keith Moray AB55 3BT",
    "addr:housenumber":"unit 2",
    "addr:postcode":"ab55 3bt",
    "addr:street":"Newmill Rd",
    "iso:country":"GB",
    "sg:address":"Unit 2 Newmill Rd",
    "sg:city":"Keith",
    "sg:classifiers":[
        {
            "category":"Retail",
            "subcategory":"Auto Repair",
            "type":"Services"
        }
    ],
    "sg:postcode":"AB55 3BT",
    "sg:province":"Moray",
    "sg:tags":[
        "modification",
        "garage"
    ],
    "wof:name":"Jeffiman,A F,",
    "wof:placetype":"venue"
},
  "geometry": {"coordinates":[-2.953014,57.550255],"type":"Point"}
}