{
  "type": "Feature",
  "properties": {
    "addr:full":"Off Wyndham St Cleator Moor Cumbria CA25 5AN",
    "addr:postcode":"ca25 5an",
    "addr:street":"Moor",
    "iso:country":"GB",
    "sg:address":"Off Wyndham St",
    "sg:city":"Cleator Moor",
    "sg:classifiers":[
        {
            "category":"Sports & Exercise",
            "subcategory":"Bowling",
            "type":"Entertainment"
        }
    ],
    "sg:phone":"+44 1946 815419",
    "sg:postcode":"CA25 5AN",
    "sg:province":"Cumbria",
    "wof:name":"Copeland Indoor Bowls Centre",
    "wof:placetype":"venue"
},
  "geometry": {"coordinates":[-3.515809,54.52137],"type":"Point"}
}