{
  "type": "Feature",
  "properties": {
    "addr:full":"Granby Avenue Birmingham West Midlands B33 0TJ",
    "addr:postcode":"b33 0tj",
    "addr:street":"Granby Avenue",
    "iso:country":"GB",
    "sg:address":"Granby Avenue",
    "sg:city":"Birmingham",
    "sg:classifiers":[
        {
            "category":"Professional",
            "subcategory":"Engineering",
            "type":"Services"
        }
    ],
    "sg:postcode":"B33 0TJ",
    "sg:province":"West Midlands",
    "sg:tags":[
        "civil",
        "engineer"
    ],
    "wof:name":"Brennan & Murphy Ltd.",
    "wof:placetype":"venue"
},
  "geometry": {"coordinates":[-1.7754640579,52.4740791321],"type":"Point"}
}