{
  "type": "Feature",
  "properties": {
    "iso:country":"GB",
    "sg:address":"Preston Street",
    "sg:city":"Bradford",
    "sg:classifiers":[
        {
            "category":"Autos & Motor Vehicles",
            "subcategory":"Auto Supplies",
            "type":"Retail Goods"
        }
    ],
    "sg:phone":"+44 1274 308000",
    "sg:postcode":"BD1 2JY",
    "sg:province":"West Yorkshire",
    "sg:tags":[
        "component"
    ],
    "wof:name":"B M F Autoparts",
    "wof:placetype":"venue"
},
  "geometry": {"coordinates":[-1.7704839706,53.7964515686],"type":"Point"}
}