{
  "type": "Feature",
  "properties": {
    "addr:full":"68 Saxon Rd, Whittlesley Peterborough Cambridgeshire PE7 1NP",
    "addr:housenumber":"68",
    "addr:postcode":"pe7 1np",
    "addr:street":"Saxon Rd Whittlesley Peterborough",
    "iso:country":"GB",
    "sg:address":"68 Saxon Rd, Whittlesley",
    "sg:city":"Peterborough",
    "sg:classifiers":[
        {
            "category":"Government",
            "subcategory":"Customs House",
            "type":"Public Place"
        }
    ],
    "sg:phone":"+44 1733 202646",
    "sg:postcode":"PE7 1NP",
    "sg:province":"Cambridgeshire",
    "sg:tags":[
        "clearance"
    ],
    "wof:name":"Past Era",
    "wof:placetype":"venue"
},
  "geometry": {"coordinates":[-0.1413879991,52.5597267151],"type":"Point"}
}