{
  "type": "Feature",
  "properties": {
    "addr:full":"Reigate Road Epsom Surrey KT17 3LA",
    "addr:postcode":"kt17 3la",
    "addr:street":"Reigate Road",
    "iso:country":"GB",
    "sg:address":"Reigate Road",
    "sg:city":"Epsom",
    "sg:classifiers":[
        {
            "category":"Autos & Motor Vehicles",
            "subcategory":"Automobile Sales",
            "type":"Retail Goods"
        }
    ],
    "sg:phone":"+44 1737 360111",
    "sg:postcode":"KT17 3LA",
    "sg:province":"Surrey",
    "sg:tags":[
        "car"
    ],
    "wof:name":"Drift Bridge Garage Ltd.",
    "wof:placetype":"venue"
},
  "geometry": {"coordinates":[-0.2436019927,51.338722229],"type":"Point"}
}