{
  "type": "Feature",
  "properties": {
    "iso:country":"GB",
    "sg:address":"Central Chambers, 109 Hope St",
    "sg:city":"Glasgow",
    "sg:classifiers":[
        {
            "category":"Professional",
            "subcategory":"Employment Agencies",
            "type":"Services"
        }
    ],
    "sg:phone":"+44 141 221 5313",
    "sg:postcode":"G2 6LL",
    "sg:province":"Glasgow City",
    "sg:tags":[
        "consultant"
    ],
    "wof:name":"Reed First Direct",
    "wof:placetype":"venue"
},
  "geometry": {"coordinates":[-4.25882,55.860619],"type":"Point"}
}