{
  "type": "Feature",
  "properties": {
    "addr:full":"5 Brewer Street London Greater London W1F 0RE",
    "addr:housenumber":"5",
    "addr:postcode":"w1f 0re",
    "addr:street":"Brewer Street",
    "iso:country":"GB",
    "sg:address":"5 Brewer Street",
    "sg:city":"London",
    "sg:classifiers":[
        {
            "category":"Real Estate",
            "subcategory":"Real Estate Agent",
            "type":"Services"
        }
    ],
    "sg:phone":"+44 20 7734 9274",
    "sg:postcode":"W1F 0RE",
    "sg:province":"Greater London",
    "wof:name":"Alan Poulton Ltd.",
    "wof:placetype":"venue"
},
  "geometry": {"coordinates":[-0.133546,51.512367],"type":"Point"}
}