{
  "type": "Feature",
  "properties": {
    "addr:full":"121 Clare Street Northampton Northamptonshire NN1 3JA",
    "addr:housenumber":"121",
    "addr:postcode":"nn1 3ja",
    "addr:street":"Clare Street",
    "iso:country":"GB",
    "sg:address":"121 Clare Street",
    "sg:city":"Northampton",
    "sg:classifiers":[
        {
            "category":"Manufacturing",
            "subcategory":"Metals",
            "type":"Manufacturing & Wholesale Goods"
        },
        {
            "category":"Wholesale",
            "subcategory":"Metals & Minerals",
            "type":"Manufacturing & Wholesale Goods"
        }
    ],
    "sg:phone":"+44 1604 636845",
    "sg:postcode":"NN1 3JA",
    "sg:province":"Northamptonshire",
    "sg:tags":[
        "fabricator",
        "work",
        "sheet"
    ],
    "wof:name":"F Brinklow & Co. Ltd.",
    "wof:placetype":"venue"
},
  "geometry": {"coordinates":[-0.885156,52.244267],"type":"Point"}
}