{
  "type": "Feature",
  "properties": {
    "iso:country":"GB",
    "sg:address":"3 Clifton Road",
    "sg:city":"London",
    "sg:classifiers":[
        {
            "category":"Retail",
            "subcategory":"Laundry & Dry Cleaning",
            "type":"Services"
        }
    ],
    "sg:phone":"+44 20 7286 6400",
    "sg:postcode":"W9 1SZ",
    "sg:province":"Greater London",
    "sg:tags":[
        "alteration"
    ],
    "wof:name":"Johnson Cleaners U K Ltd.",
    "wof:placetype":"venue"
},
  "geometry": {"coordinates":[-0.178519,51.525761],"type":"Point"}
}