{
  "type": "Feature",
  "properties": {
    "addr:full":"Salisbury Street London Greater London W3 8NW",
    "addr:postcode":"w3 8nw",
    "addr:street":"Salisbury Street",
    "iso:country":"GB",
    "sg:address":"Salisbury Street",
    "sg:city":"London",
    "sg:classifiers":[
        {
            "category":"Sports & Exercise",
            "subcategory":"Swimming Pool",
            "type":"Entertainment"
        }
    ],
    "sg:phone":"+44 20 8992 8877",
    "sg:postcode":"W3 8NW",
    "sg:province":"Greater London",
    "wof:name":"Acton Swimming Pool",
    "wof:placetype":"venue"
},
  "geometry": {"coordinates":[-0.267167,51.506008],"type":"Point"}
}