{
  "type": "Feature",
  "properties": {
    "addr:full":"The Red House, 5 Swindon Rd, Stratton St Margaret Swindon Wiltshire SN3 4PU",
    "addr:housenumber":"5",
    "addr:postcode":"sn3 4pu",
    "addr:street":"Swindon Rd;St",
    "iso:country":"GB",
    "sg:address":"The Red House, 5 Swindon Rd, Stratton St Margaret",
    "sg:city":"Swindon",
    "sg:classifiers":[
        {
            "category":"Professional",
            "subcategory":"Art Services",
            "type":"Services"
        }
    ],
    "sg:phone":"+44 1793 821662",
    "sg:postcode":"SN3 4PU",
    "sg:province":"Wiltshire",
    "sg:tags":[
        "graphic",
        "designer"
    ],
    "wof:name":"WOW Creative Services",
    "wof:placetype":"venue"
},
  "geometry": {"coordinates":[-1.752229,51.578629],"type":"Point"}
}