{
  "type": "Feature",
  "properties": {
    "iso:country":"GB",
    "sg:address":"123 Friday Wood Green",
    "sg:city":"Colchester",
    "sg:classifiers":[
        {
            "category":"Building & Trades",
            "subcategory":"Construction",
            "type":"Services"
        }
    ],
    "sg:phone":"+44 1206 564775",
    "sg:postcode":"CO2 8XF",
    "sg:province":"Essex",
    "sg:tags":[
        "builder"
    ],
    "wof:name":"Friday Wood Green Construction",
    "wof:placetype":"venue"
},
  "geometry": {"coordinates":[0.902506,51.857586],"type":"Point"}
}