{
  "type": "Feature",
  "properties": {
    "addr:full":"Drove Farm, Andersea, Weston Zoyland Bridgwater Somerset TA7 0LU",
    "addr:housenumber":"andersea",
    "addr:postcode":"ta7 0lu",
    "addr:street":"Drove;Zoyland",
    "iso:country":"GB",
    "sg:address":"Drove Farm, Andersea, Weston Zoyland",
    "sg:city":"Bridgwater",
    "sg:classifiers":[
        {
            "category":"Farming",
            "subcategory":"Poultry Farm",
            "type":"Manufacturing & Wholesale Goods"
        }
    ],
    "sg:phone":"+44 1278 691866",
    "sg:postcode":"TA7 0LU",
    "sg:province":"Somerset",
    "sg:tags":[
        "game"
    ],
    "wof:name":"Philip C Binder",
    "wof:placetype":"venue"
},
  "geometry": {"coordinates":[-2.95494,51.097019],"type":"Point"}
}