{
  "type": "Feature",
  "properties": {
    "addr:full":"1 Marlborough Square Coalville Leicestershire LE67 3WD",
    "addr:housenumber":"1",
    "addr:postcode":"le67 3wd",
    "addr:street":"Marlborough Square",
    "iso:country":"GB",
    "sg:address":"1 Marlborough Square",
    "sg:city":"Coalville",
    "sg:classifiers":[
        {
            "category":"Banks & Credit Unions",
            "subcategory":"Bank",
            "type":"Services"
        }
    ],
    "sg:phone":"+44 116 262 5205",
    "sg:postcode":"LE67 3WD",
    "sg:province":"Leicestershire",
    "wof:name":"Lloyds Tsb Bank Plc",
    "wof:placetype":"venue"
},
  "geometry": {"coordinates":[-1.3746759892,52.7235527039],"type":"Point"}
}