{
  "type": "Feature",
  "properties": {
    "addr:full":"347 Cardiff Rd, Aberaman Aberdare Neath Port Talbot CF44 6TP",
    "addr:housenumber":"347",
    "addr:postcode":"cf44 6tp",
    "addr:street":"Cardiff Rd",
    "iso:country":"GB",
    "sg:address":"347 Cardiff Rd, Aberaman",
    "sg:city":"Aberdare",
    "sg:classifiers":[
        {
            "category":"Professional",
            "type":"Services"
        },
        {
            "category":"Professional",
            "subcategory":"Printing & Photocopies",
            "type":"Services"
        }
    ],
    "sg:postcode":"CF44 6TP",
    "sg:province":"Neath Port Talbot",
    "sg:tags":[
        "directory",
        "printer",
        "pub"
    ],
    "wof:name":"Mehmet,Nedim,",
    "wof:placetype":"venue"
},
  "geometry": {"coordinates":[-3.434099,51.705528],"type":"Point"}
}