{
  "type": "Feature",
  "properties": {
    "addr:full":"741 High Road London Greater London N12 0BQ",
    "addr:housenumber":"741",
    "addr:postcode":"n12 0bq",
    "addr:street":"High Road",
    "iso:country":"GB",
    "sg:address":"741 High Road",
    "sg:city":"London",
    "sg:classifiers":[
        {
            "category":"Government",
            "subcategory":"Office",
            "type":"Public Place"
        }
    ],
    "sg:phone":"+44 20 8446 8109",
    "sg:postcode":"N12 0BQ",
    "sg:province":"Greater London",
    "sg:tags":[
        "education",
        "agency",
        "authority"
    ],
    "wof:name":"Hebrew Hotline Jewish Agency",
    "wof:placetype":"venue"
},
  "geometry": {"coordinates":[-0.17647,51.614101],"type":"Point"}
}