{
  "type": "Feature",
  "properties": {
    "addr:full":"Po Box 140 High Wycombe Buckinghamshire HP13 6YF",
    "addr:housenumber":"po;140",
    "addr:postcode":"hp13 6yf",
    "addr:street":"Box",
    "iso:country":"GB",
    "sg:address":"Po Box 140",
    "sg:city":"High Wycombe",
    "sg:classifiers":[
        {
            "category":"Home & Garden",
            "subcategory":"Home Furnishings",
            "type":"Retail Goods"
        },
        {
            "category":"Manufacturing",
            "subcategory":"Building Materials",
            "type":"Manufacturing & Wholesale Goods"
        }
    ],
    "sg:phone":"+44 1494 471226",
    "sg:postcode":"HP13 6YF",
    "sg:province":"Buckinghamshire",
    "sg:tags":[
        "mnfr",
        "loose",
        "cover"
    ],
    "wof:name":"Loose Cover Co",
    "wof:placetype":"venue"
},
  "geometry": {"coordinates":[-0.7477890253,51.628944397],"type":"Point"}
}