{
  "type": "Feature",
  "properties": {
    "iso:country":"GB",
    "sg:address":"Invicta Works, Chalk Pit Av",
    "sg:city":"Orpington",
    "sg:classifiers":[
        {
            "category":"Government",
            "subcategory":"Post Office",
            "type":"Public Place"
        }
    ],
    "sg:phone":"+44 1689 827229",
    "sg:postcode":"BR5 3JP",
    "sg:province":"Kent",
    "sg:tags":[
        "messenger",
        "courier"
    ],
    "wof:name":"NCN Kent",
    "wof:placetype":"venue"
},
  "geometry": {"coordinates":[0.11743,51.400768],"type":"Point"}
}