{
  "type": "Feature",
  "properties": {
    "addr:full":"3 Bowstoke Road Birmingham West Midlands B43 5EB",
    "addr:housenumber":"3",
    "addr:postcode":"b43 5eb",
    "addr:street":"Bowstoke Road",
    "iso:country":"GB",
    "sg:address":"3 Bowstoke Road",
    "sg:city":"Birmingham",
    "sg:classifiers":[
        {
            "category":"Fast Food",
            "type":"Food & Drink"
        }
    ],
    "sg:phone":"+44 121 357 4467",
    "sg:postcode":"B43 5EB",
    "sg:province":"West Midlands",
    "sg:tags":[
        "away",
        "meal",
        "outlet",
        "take"
    ],
    "wof:name":"Good Year",
    "wof:placetype":"venue"
},
  "geometry": {"coordinates":[-1.9553740025,52.5426025391],"type":"Point"}
}