{
  "type": "Feature",
  "properties": {
    "iso:country":"GB",
    "sg:address":"93 Wendover Road",
    "sg:city":"Manchester",
    "sg:classifiers":[
        {
            "category":"Food & Beverages",
            "subcategory":"Bakery",
            "type":"Retail Goods"
        }
    ],
    "sg:phone":"+44 161 998 3559",
    "sg:postcode":"M23 9EG",
    "sg:province":"Cheshire",
    "sg:tags":[
        "shop",
        "baker"
    ],
    "wof:name":"Country Bakery",
    "wof:placetype":"venue"
},
  "geometry": {"coordinates":[-2.29648,53.389225],"type":"Point"}
}