{
  "type": "Feature",
  "properties": {
    "addr:full":"Lordshire Farm, 38 Armshead Road, Werrington Stoke-on-trent Staffordshire ST9 0HJ",
    "addr:housenumber":"38",
    "addr:postcode":"staffordshire st9 0hj",
    "addr:street":"Armshead Road",
    "iso:country":"GB",
    "sg:address":"Lordshire Farm, 38 Armshead Road, Werrington",
    "sg:city":"Stoke-on-trent",
    "sg:classifiers":[
        {
            "category":"Retail",
            "subcategory":"Storage",
            "type":"Services"
        }
    ],
    "sg:phone":"+44 1782 304410",
    "sg:postcode":"ST9 0HJ",
    "sg:province":"Staffordshire",
    "sg:tags":[
        "household",
        "removal"
    ],
    "wof:name":"Peck's Removals",
    "wof:placetype":"venue"
},
  "geometry": {"coordinates":[-2.0896298885,53.0243453979],"type":"Point"}
}