{
  "type": "Feature",
  "properties": {
    "addr:full":"80 Nethergate Dundee Dundee City DD1 4ER",
    "addr:housenumber":"80",
    "addr:postcode":"dd1 4er",
    "addr:street":"Nethergate",
    "iso:country":"GB",
    "sg:address":"80 Nethergate",
    "sg:city":"Dundee",
    "sg:classifiers":[
        {
            "category":"Health Services",
            "subcategory":"Dentist",
            "type":"Services"
        }
    ],
    "sg:phone":"+44 1382 224808",
    "sg:postcode":"DD1 4ER",
    "sg:province":"Dundee City",
    "wof:name":"John A Vardy",
    "wof:placetype":"venue"
},
  "geometry": {"coordinates":[-2.9723410606,56.4589996338],"type":"Point"}
}