{
  "type": "Feature",
  "properties": {
    "addr:full":"224 West End Lane, Horsforth Leeds West Yorkshire LS18 5RU",
    "addr:housenumber":"224",
    "addr:postcode":"ls18 5ru",
    "addr:street":"West End Lane",
    "iso:country":"GB",
    "sg:address":"224 West End Lane, Horsforth",
    "sg:city":"Leeds",
    "sg:classifiers":[
        {
            "category":"Home & Garden",
            "subcategory":"Home Furnishings",
            "type":"Retail Goods"
        },
        {
            "category":"Home & Garden",
            "subcategory":"Carpets & Floor Coverings",
            "type":"Retail Goods"
        }
    ],
    "sg:phone":"+44 113 258 4981",
    "sg:postcode":"LS18 5RU",
    "sg:province":"West Yorkshire",
    "sg:tags":[
        "fitting",
        "rug",
        "matting",
        "carpets"
    ],
    "wof:name":"W Brown & Co",
    "wof:placetype":"venue"
},
  "geometry": {"coordinates":[-1.6492389441,53.8396682739],"type":"Point"}
}