{
  "type": "Feature",
  "properties": {
    "addr:full":"The Temple, Eastgate Sleaford Lincolnshire NG34 7DR",
    "addr:postcode":"ng34 7dr",
    "addr:street":"Eastgate Sleaford",
    "iso:country":"GB",
    "sg:address":"The Temple, Eastgate",
    "sg:city":"Sleaford",
    "sg:classifiers":[
        {
            "category":"Transit Center",
            "subcategory":"Freight",
            "type":"Transportation"
        },
        {
            "category":"Manufacturing",
            "subcategory":"Musical Instruments",
            "type":"Manufacturing & Wholesale Goods"
        }
    ],
    "sg:phone":"+44 1529 302037",
    "sg:postcode":"NG34 7DR",
    "sg:province":"Lincolnshire",
    "sg:tags":[
        "piano",
        "accessory"
    ],
    "wof:name":"White & Sentance",
    "wof:placetype":"venue"
},
  "geometry": {"coordinates":[-0.4118689895,52.9945869446],"type":"Point"}
}