{
  "type": "Feature",
  "properties": {
    "iso:country":"GB",
    "sg:address":"Unit 7 Brassmill Enterprise Ctre, Brassmill Lane",
    "sg:city":"Bath",
    "sg:classifiers":[
        {
            "category":"Communications",
            "subcategory":"Newspaper",
            "type":"Services"
        },
        {
            "category":"Wholesale",
            "subcategory":"Books, Periodicals, & Newspapers",
            "type":"Manufacturing & Wholesale Goods"
        }
    ],
    "sg:phone":"+44 1225 445046",
    "sg:postcode":"BA1 3JN",
    "sg:province":"Bath and North East Somerset",
    "sg:tags":[
        "publisher",
        "magazine",
        "book"
    ],
    "sg:website":"http://www.geolsoc.org.uk",
    "wof:name":"Geological Society Publishing House",
    "wof:placetype":"venue"
},
  "geometry": {"coordinates":[-2.402769,51.38649],"type":"Point"}
}