{
  "type": "Feature",
  "properties": {
    "addr:full":"85 Rose Green Rd Bristol City of Bristol BS5 7UT",
    "addr:housenumber":"85",
    "addr:postcode":"bs5 7ut",
    "addr:street":"Rose Green Rd",
    "iso:country":"GB",
    "sg:address":"85 Rose Green Rd",
    "sg:city":"Bristol",
    "sg:classifiers":[
        {
            "category":"Professional",
            "subcategory":"Art Services",
            "type":"Services"
        }
    ],
    "sg:phone":"+44 117 952 2438",
    "sg:postcode":"BS5 7UT",
    "sg:province":"City of Bristol",
    "sg:tags":[
        "photographer"
    ],
    "wof:name":"Avon Studios",
    "wof:placetype":"venue"
},
  "geometry": {"coordinates":[-2.549024,51.469429],"type":"Point"}
}