{
  "type": "Feature",
  "properties": {
    "iso:country":"GB",
    "sg:address":"57 Chapel Road",
    "sg:city":"Worthing",
    "sg:classifiers":[
        {
            "category":"Cinema",
            "subcategory":"Movie Rental",
            "type":"Entertainment"
        }
    ],
    "sg:phone":"+44 1903 200006",
    "sg:postcode":"BN11 1HW",
    "sg:province":"West Sussex",
    "sg:tags":[
        "video",
        "library"
    ],
    "wof:name":"Blockbuster Video",
    "wof:placetype":"venue"
},
  "geometry": {"coordinates":[-0.3716059923,50.8146591187],"type":"Point"}
}