{
  "type": "Feature",
  "properties": {
    "addr:full":"Castlefield Road Reigate Surrey RH2 0SD",
    "addr:postcode":"rh2 0sd",
    "addr:street":"Castlefield Road",
    "iso:country":"GB",
    "sg:address":"Castlefield Road",
    "sg:city":"Reigate",
    "sg:classifiers":[
        {
            "category":"Social Services",
            "type":"Services"
        },
        {
            "category":"Education",
            "subcategory":"University",
            "type":"Public Place"
        }
    ],
    "sg:phone":"+44 1737 221118",
    "sg:postcode":"RH2 0SD",
    "sg:province":"Surrey",
    "sg:tags":[
        "higher"
    ],
    "wof:name":"Reigate Sixth Form College",
    "wof:placetype":"venue"
},
  "geometry": {"coordinates":[-0.204584,51.238922],"type":"Point"}
}