{
  "type": "Feature",
  "properties": {
    "addr:full":"187 Scrogg Road, Walkerville Newcastle-upon-tyne Tyne and Wear NE6 3EN",
    "addr:housenumber":"187",
    "addr:postcode":"ne6 3en",
    "addr:street":"Scrogg Road",
    "iso:country":"GB",
    "sg:address":"187 Scrogg Road, Walkerville",
    "sg:city":"Newcastle-upon-tyne",
    "sg:classifiers":[
        {
            "category":"Home & Garden",
            "subcategory":"Hardware",
            "type":"Retail Goods"
        }
    ],
    "sg:phone":"+44 191 262 9555",
    "sg:postcode":"NE6 3EN",
    "sg:province":"Tyne and Wear",
    "sg:tags":[
        "lawnmowers",
        "machinery"
    ],
    "wof:name":"Barry Davison & Richard Laydon & Ivon Huwitt",
    "wof:placetype":"venue"
},
  "geometry": {"coordinates":[-1.549663,54.968742],"type":"Point"}
}