{
  "type": "Feature",
  "properties": {
    "addr:full":"Town Farm 48 High Street, Cloughton Scarborough North Yorkshire YO13 0AE",
    "addr:housenumber":"48",
    "addr:postcode":"yo13 0ae",
    "addr:street":"High Street",
    "iso:country":"GB",
    "sg:address":"Town Farm 48 High Street, Cloughton",
    "sg:city":"Scarborough",
    "sg:classifiers":[
        {
            "category":"Farming",
            "subcategory":"Farm",
            "type":"Manufacturing & Wholesale Goods"
        }
    ],
    "sg:postcode":"YO13 0AE",
    "sg:province":"North Yorkshire",
    "sg:tags":[
        "mixed",
        "crop"
    ],
    "wof:name":"George Green Farms Ltd.",
    "wof:placetype":"venue"
},
  "geometry": {"coordinates":[-0.4490660131,54.3358306885],"type":"Point"}
}