{
  "type": "Feature",
  "properties": {
    "addr:full":"8 The Drive Northampton Northamptonshire NN1 4SA",
    "addr:housenumber":"8",
    "addr:postcode":"nn1 4sa",
    "addr:street":"The Drive",
    "iso:country":"GB",
    "sg:address":"8 The Drive",
    "sg:city":"Northampton",
    "sg:classifiers":[
        {
            "category":"Health Services",
            "subcategory":"Nursing And Care Facility",
            "type":"Services"
        }
    ],
    "sg:phone":"+44 1604 713098",
    "sg:postcode":"NN1 4SA",
    "sg:province":"Northamptonshire",
    "sg:tags":[
        "home"
    ],
    "wof:name":"Oakwood",
    "wof:placetype":"venue"
},
  "geometry": {"coordinates":[-0.876561,52.251446],"type":"Point"}
}