{
  "type": "Feature",
  "properties": {
    "iso:country":"GB",
    "sg:address":"Unit 6, Newbridge Industrial Estate",
    "sg:city":"Keighley",
    "sg:classifiers":[
        {
            "category":"Manufacturing",
            "subcategory":"Metals",
            "type":"Manufacturing & Wholesale Goods"
        },
        {
            "category":"Mining & Drilling",
            "type":"Manufacturing & Wholesale Goods"
        }
    ],
    "sg:phone":"+44 1535 680400",
    "sg:postcode":"BD21 4PQ",
    "sg:province":"West Yorkshire",
    "sg:tags":[
        "product",
        "fabricated"
    ],
    "wof:name":"WORTH MINING",
    "wof:placetype":"venue"
},
  "geometry": {"coordinates":[-1.8978149891,53.8665809631],"type":"Point"}
}