{
  "type": "Feature",
  "properties": {
    "addr:full":"226 Portland Road London Greater London SE25 4SL",
    "addr:housenumber":"226",
    "addr:postcode":"se25 4sl",
    "addr:street":"Portland Road",
    "iso:country":"GB",
    "sg:address":"226 Portland Road",
    "sg:city":"London",
    "sg:classifiers":[
        {
            "category":"Professional",
            "subcategory":"Lawyer & Legal Services",
            "type":"Services"
        }
    ],
    "sg:phone":"+44 20 8656 8318",
    "sg:postcode":"SE25 4SL",
    "sg:province":"Greater London",
    "sg:tags":[
        "solicitor"
    ],
    "wof:name":"Barrington Charles Edwards & Co",
    "wof:placetype":"venue"
},
  "geometry": {"coordinates":[-0.0668610036,51.3938140869],"type":"Point"}
}