{
  "type": "Feature",
  "properties": {
    "addr:full":"63 Lansdowne Pl Hove East Sussex BN3 1FL",
    "addr:housenumber":"63",
    "addr:postcode":"bn3 1fl",
    "addr:street":"Lansdowne Pl",
    "iso:country":"GB",
    "sg:address":"63 Lansdowne Pl",
    "sg:city":"Hove",
    "sg:classifiers":[
        {
            "category":"Communications",
            "type":"Services"
        }
    ],
    "sg:phone":"+44 1273 203572",
    "sg:postcode":"BN3 1FL",
    "sg:province":"East Sussex",
    "sg:tags":[
        "telecommunication"
    ],
    "wof:name":"Rendezvous",
    "wof:placetype":"venue"
},
  "geometry": {"coordinates":[-0.160504,50.826241],"type":"Point"}
}