{
  "type": "Feature",
  "properties": {
    "addr:full":"Olton Court, 10 Warwick Road Solihull West Midlands B92 7HX",
    "addr:housenumber":"10",
    "addr:postcode":"b92 7hx",
    "addr:street":"Olton;Warwick Road",
    "iso:country":"GB",
    "sg:address":"Olton Court, 10 Warwick Road",
    "sg:city":"Solihull",
    "sg:classifiers":[
        {
            "category":"Building & Trades",
            "subcategory":"Construction",
            "type":"Services"
        }
    ],
    "sg:phone":"+44 121 707 7429",
    "sg:postcode":"B92 7HX",
    "sg:province":"West Midlands",
    "sg:tags":[
        "installers",
        "gas"
    ],
    "wof:name":"Lattice Energy Services Ltd.",
    "wof:placetype":"venue"
},
  "geometry": {"coordinates":[-1.810122,52.440765],"type":"Point"}
}