{
  "type": "Feature",
  "properties": {
    "iso:country":"GB",
    "sg:address":"83 Acre La",
    "sg:city":"Brixton",
    "sg:classifiers":[
        {
            "category":"Real Estate",
            "subcategory":"Real Estate Agent",
            "type":"Services"
        }
    ],
    "sg:phone":"+44 20 8569 1616",
    "sg:postcode":"SW2 5TN",
    "sg:province":"Greater London",
    "wof:name":"Century Residential Sales",
    "wof:placetype":"venue"
},
  "geometry": {"coordinates":[-0.124424,51.459457],"type":"Point"}
}