{
  "type": "Feature",
  "properties": {
    "addr:full":"20 Greville Road London Greater London NW6 5JA",
    "addr:housenumber":"20",
    "addr:postcode":"nw6 5ja",
    "addr:street":"Greville Road",
    "iso:country":"GB",
    "sg:address":"20 Greville Road",
    "sg:city":"London",
    "sg:classifiers":[
        {
            "category":"Professional",
            "subcategory":"Business Services",
            "type":"Services"
        }
    ],
    "sg:phone":"+44 20 7681 7180",
    "sg:postcode":"NW6 5JA",
    "sg:province":"Greater London",
    "sg:tags":[
        "planning",
        "design"
    ],
    "wof:name":"Projects International",
    "wof:placetype":"venue"
},
  "geometry": {"coordinates":[-0.1882369965,51.5362930298],"type":"Point"}
}