{
  "type": "Feature",
  "properties": {
    "iso:country":"GB",
    "sg:address":"Care Of Homebase, Pines Way",
    "sg:city":"Bath",
    "sg:classifiers":[
        {
            "category":"Home & Garden",
            "subcategory":"Furniture",
            "type":"Retail Goods"
        }
    ],
    "sg:postcode":"BA2 3ET",
    "sg:province":"Somerset",
    "wof:name":"Harveys Furnishing Group Ltd",
    "wof:placetype":"venue"
},
  "geometry": {"coordinates":[-2.3699400425,51.3805198669],"type":"Point"}
}