{
  "type": "Feature",
  "properties": {
    "iso:country":"GB",
    "sg:address":"Whitehill Farm",
    "sg:city":"Denny",
    "sg:classifiers":[
        {
            "category":"Wholesale",
            "subcategory":"Scrap",
            "type":"Manufacturing & Wholesale Goods"
        },
        {
            "category":"Wholesale",
            "subcategory":"Auto Parts",
            "type":"Manufacturing & Wholesale Goods"
        }
    ],
    "sg:phone":"+44 1324 841636",
    "sg:postcode":"FK6 5NA",
    "sg:province":"Falkirk",
    "sg:tags":[
        "car",
        "breaker",
        "dismantlers"
    ],
    "wof:name":"Headswood Garage",
    "wof:placetype":"venue"
},
  "geometry": {"coordinates":[-3.916404,56.014584],"type":"Point"}
}