{
  "type": "Feature",
  "properties": {
    "addr:full":"16 Liverpool Gardens Worthing West Sussex BN11 1RY",
    "addr:housenumber":"16",
    "addr:postcode":"bn11 1ry",
    "addr:street":"Liverpool Gardens",
    "iso:country":"GB",
    "sg:address":"16 Liverpool Gardens",
    "sg:city":"Worthing",
    "sg:classifiers":[
        {
            "category":"Health Services",
            "subcategory":"Health Practitioner",
            "type":"Services"
        }
    ],
    "sg:phone":"+44 1903 820672",
    "sg:postcode":"BN11 1RY",
    "sg:province":"West Sussex",
    "sg:tags":[
        "psychologist"
    ],
    "wof:name":"Psychology Services Worthing Priority Healthcare",
    "wof:placetype":"venue"
},
  "geometry": {"coordinates":[-0.3718099892,50.8120079041],"type":"Point"}
}