{
  "type": "Feature",
  "properties": {
    "iso:country":"GB",
    "sg:address":"Linkwood Industrial Estate",
    "sg:city":"Elgin",
    "sg:classifiers":[
        {
            "category":"Freight",
            "type":"Transportation"
        }
    ],
    "sg:phone":"+44 1343 555312",
    "sg:postcode":"IV30 1HZ",
    "sg:province":"Moray",
    "sg:tags":[
        "haulage",
        "road"
    ],
    "wof:name":"Baillie Bros (Contractors) Ltd.",
    "wof:placetype":"venue"
},
  "geometry": {"coordinates":[-3.317868948,57.6493682861],"type":"Point"}
}