{
  "type": "Feature",
  "properties": {
    "addr:full":"2a The Grn, Little Neston Wirral Cheshire CH64 4BZ",
    "addr:housenumber":"2a",
    "addr:postcode":"ch64 4bz",
    "addr:street":"The Grn Little",
    "iso:country":"GB",
    "sg:address":"2a The Grn, Little Neston",
    "sg:city":"Wirral",
    "sg:classifiers":[
        {
            "category":"Banks & Credit Unions",
            "subcategory":"Financial Services",
            "type":"Services"
        }
    ],
    "sg:phone":"+44 151 336 6161",
    "sg:postcode":"CH64 4BZ",
    "sg:province":"Cheshire",
    "sg:tags":[
        "adviser",
        "agent",
        "tied",
        "independent"
    ],
    "wof:name":"Oakley Financial Services",
    "wof:placetype":"venue"
},
  "geometry": {"coordinates":[-3.0578238964,53.2837181091],"type":"Point"}
}