{
  "type": "Feature",
  "properties": {
    "addr:full":"21 Wide Bargate Boston Lincolnshire PE21 6SR",
    "addr:housenumber":"21",
    "addr:postcode":"pe21 6sr",
    "addr:street":"Wide Bargate",
    "iso:country":"GB",
    "sg:address":"21 Wide Bargate",
    "sg:city":"Boston",
    "sg:classifiers":[
        {
            "category":"Food & Beverages",
            "subcategory":"Bakery",
            "type":"Retail Goods"
        }
    ],
    "sg:phone":"+44 1205 362796",
    "sg:postcode":"PE21 6SR",
    "sg:province":"Lincolnshire",
    "sg:tags":[
        "baker"
    ],
    "wof:name":"Shephards (Bakers) Ltd.",
    "wof:placetype":"venue"
},
  "geometry": {"coordinates":[-0.021127,52.979725],"type":"Point"}
}