{
  "type": "Feature",
  "properties": {
    "addr:full":"188 Southwick Rd Sunderland Tyne and Wear SR5 2AG",
    "addr:housenumber":"188",
    "addr:postcode":"sr5 2ag",
    "addr:street":"Southwick Rd",
    "iso:country":"GB",
    "sg:address":"188 Southwick Rd",
    "sg:city":"Sunderland",
    "sg:classifiers":[
        {
            "category":"Building & Trades",
            "subcategory":"Construction",
            "type":"Services"
        }
    ],
    "sg:phone":"+44 191 549 1474",
    "sg:postcode":"SR5 2AG",
    "sg:province":"Tyne and Wear",
    "sg:tags":[
        "glazier"
    ],
    "wof:name":"J D I Glaziers",
    "wof:placetype":"venue"
},
  "geometry": {"coordinates":[-1.3986330032,54.9197845459],"type":"Point"}
}