{
  "type": "Feature",
  "properties": {
    "iso:country":"GB",
    "sg:address":"18 Byron Road, Holway",
    "sg:city":"Taunton",
    "sg:classifiers":[
        {
            "category":"Building & Trades",
            "subcategory":"Construction",
            "type":"Services"
        }
    ],
    "sg:postcode":"TA1 2JD",
    "sg:province":"Somerset",
    "sg:tags":[
        "decorator",
        "painter"
    ],
    "wof:name":"Colin A Savage",
    "wof:placetype":"venue"
},
  "geometry": {"coordinates":[-3.083243,51.011696],"type":"Point"}
}