{
  "type": "Feature",
  "properties": {
    "iso:country":"GB",
    "sg:address":"60 Ackhurst Park Industrial Estate, Foxhole Road",
    "sg:city":"Chorley",
    "sg:classifiers":[
        {
            "category":"Taxi",
            "type":"Transportation"
        },
        {
            "category":"Military Area",
            "subcategory":"Air Force Base",
            "type":"Public Place"
        }
    ],
    "sg:phone":"+44 1257 261666",
    "sg:postcode":"PR7 1NW",
    "sg:province":"Lancashire",
    "sg:tags":[
        "hire",
        "private",
        "vehicle"
    ],
    "wof:name":"Cooper'S Taxis",
    "wof:placetype":"venue"
},
  "geometry": {"coordinates":[-2.65396,53.655384],"type":"Point"}
}