{
  "type": "Feature",
  "properties": {
    "iso:country":"GB",
    "sg:address":"Higher Doggaport, Langtree",
    "sg:city":"Torrington",
    "sg:classifiers":[
        {
            "category":"Home & Garden",
            "subcategory":"Garden Supply",
            "type":"Retail Goods"
        },
        {
            "category":"Farming",
            "subcategory":"Farm",
            "type":"Manufacturing & Wholesale Goods"
        }
    ],
    "sg:postcode":"EX38 8NJ",
    "sg:province":"Devon",
    "sg:tags":[
        "mixed",
        "bulb",
        "crop",
        "grower"
    ],
    "wof:name":"K J & E H Beer & Son",
    "wof:placetype":"venue"
},
  "geometry": {"coordinates":[-4.142255,50.953152],"type":"Point"}
}