{
  "type": "Feature",
  "properties": {
    "addr:full":"Stanley Place, Talbot Street Nottingham Nottinghamshire NG1 5GG",
    "addr:postcode":"ng1 5gg",
    "addr:street":"Stanley Place Talbot Street",
    "iso:country":"GB",
    "sg:address":"Stanley Place, Talbot Street",
    "sg:city":"Nottingham",
    "sg:classifiers":[
        {
            "category":"Parking",
            "type":"Transportation"
        }
    ],
    "sg:phone":"+44 115 941 5553",
    "sg:postcode":"NG1 5GG",
    "sg:province":"Nottinghamshire",
    "sg:tags":[
        "car",
        "park"
    ],
    "wof:name":"The Talbot Street Car Park",
    "wof:placetype":"venue"
},
  "geometry": {"coordinates":[-1.154748,52.956207],"type":"Point"}
}