{
  "type": "Feature",
  "properties": {
    "iso:country":"GB",
    "sg:address":"Boarfold Campsite, Chisworth",
    "sg:city":"Hyde",
    "sg:classifiers":[
        {
            "category":"Recreation",
            "subcategory":"Campground",
            "type":"Entertainment"
        }
    ],
    "sg:phone":"+44 1457 862246",
    "sg:postcode":"SK14 6RT",
    "sg:province":"Cheshire",
    "sg:tags":[
        "site",
        "camping"
    ],
    "wof:name":"Hyde District Scout Council",
    "wof:placetype":"venue"
},
  "geometry": {"coordinates":[-2.080884,53.454311],"type":"Point"}
}