{
  "type": "Feature",
  "properties": {
    "iso:country":"GB",
    "sg:address":"7 Parkstone Rd",
    "sg:city":"Leicester",
    "sg:classifiers":[
        {
            "category":"Cafe",
            "type":"Food & Drink"
        }
    ],
    "sg:phone":"+44 116 243 3334",
    "sg:postcode":"LE5 1NP",
    "sg:province":"Leicestershire",
    "sg:tags":[
        "tea",
        "room"
    ],
    "wof:name":"M's Pantry",
    "wof:placetype":"venue"
},
  "geometry": {"coordinates":[-1.059167,52.643925],"type":"Point"}
}