{
  "type": "Feature",
  "properties": {
    "iso:country":"GB",
    "sg:address":"The Limes, North Square",
    "sg:city":"Newport Pagnell",
    "sg:classifiers":[
        {
            "category":"Travel",
            "subcategory":"Hotels & Motels",
            "type":"Entertainment"
        }
    ],
    "sg:phone":"+44 1908 617041",
    "sg:postcode":"MK16 8EP",
    "sg:province":"Buckinghamshire",
    "sg:tags":[
        "house",
        "guest"
    ],
    "wof:name":"The Limes Guest House",
    "wof:placetype":"venue"
},
  "geometry": {"coordinates":[-0.723019,52.086697],"type":"Point"}
}