{
  "type": "Feature",
  "properties": {
    "addr:full":"29 St James Street Bacup Lancashire OL13 9NJ",
    "addr:housenumber":"29",
    "addr:postcode":"ol13 9nj",
    "addr:street":"St James Street",
    "iso:country":"GB",
    "sg:address":"29 St James Street",
    "sg:city":"Bacup",
    "sg:classifiers":[
        {
            "category":"Food & Beverages",
            "subcategory":"Fruits & Vegetables",
            "type":"Retail Goods"
        }
    ],
    "sg:phone":"+44 1706 874640",
    "sg:postcode":"OL13 9NJ",
    "sg:province":"Lancashire",
    "sg:tags":[
        "greengrocer"
    ],
    "wof:name":"Graham's Fruit & Veg",
    "wof:placetype":"venue"
},
  "geometry": {"coordinates":[-2.1998078823,53.7025260925],"type":"Point"}
}