{
  "type": "Feature",
  "properties": {
    "iso:country":"GB",
    "sg:address":"Peregrine Road, Westhill Business Park, Skene",
    "sg:city":"Westhill",
    "sg:classifiers":[
        {
            "category":"Building & Trades",
            "subcategory":"Construction",
            "type":"Services"
        }
    ],
    "sg:phone":"+44 1224 744555",
    "sg:postcode":"AB32 6JL",
    "sg:province":"Aberdeen City",
    "sg:tags":[
        "builder"
    ],
    "wof:name":"Cameron Chisholm Dawson Partnership",
    "wof:placetype":"venue"
},
  "geometry": {"coordinates":[-2.299517,57.149876],"type":"Point"}
}