{
  "type": "Feature",
  "properties": {
    "iso:country":"GB",
    "sg:address":"Blue Anchor Bay",
    "sg:city":"Minehead",
    "sg:classifiers":[
        {
            "category":"Bars & Pubs",
            "type":"Food & Drink"
        },
        {
            "category":"Community Center",
            "subcategory":"Social",
            "type":"Public Place"
        }
    ],
    "sg:phone":"+44 1984 640239",
    "sg:postcode":"TA24 6JP",
    "sg:province":"Somerset",
    "sg:tags":[
        "pubs",
        "house",
        "inn",
        "activity"
    ],
    "wof:name":"Blue Anchor Hotel",
    "wof:placetype":"venue"
},
  "geometry": {"coordinates":[-3.479969,51.205406],"type":"Point"}
}