{
  "type": "Feature",
  "properties": {
    "iso:country":"GB",
    "sg:address":"79a Allhallowgate",
    "sg:city":"Ripon",
    "sg:classifiers":[
        {
            "category":"Health Services",
            "subcategory":"Podiatrist",
            "type":"Services"
        }
    ],
    "sg:postcode":"HG4 1LE",
    "sg:province":"North Yorkshire",
    "sg:tags":[
        "podiatrists",
        "chiropodist"
    ],
    "wof:name":"J Waterworth",
    "wof:placetype":"venue"
},
  "geometry": {"coordinates":[-1.523248,54.13821],"type":"Point"}
}