{
  "type": "Feature",
  "properties": {
    "iso:country":"GB",
    "sg:address":"Unit 1 & 2 Candle Works Yard, Off Station Rd",
    "sg:city":"Otley",
    "sg:classifiers":[
        {
            "category":"Autos & Motor Vehicles",
            "subcategory":"Auto Supplies",
            "type":"Retail Goods"
        }
    ],
    "sg:phone":"+44 1943 467282",
    "sg:postcode":"LS21 3HX",
    "sg:province":"North Yorkshire",
    "sg:tags":[
        "tyre"
    ],
    "wof:name":"Direct Motor Cycle Tyres",
    "wof:placetype":"venue"
},
  "geometry": {"coordinates":[-1.6931,53.90173],"type":"Point"}
}