{
  "type": "Feature",
  "properties": {
    "iso:country":"GB",
    "sg:address":"212 Nantgarw Rd",
    "sg:city":"Caerphilly",
    "sg:classifiers":[
        {
            "category":"Building & Trades",
            "subcategory":"Construction",
            "type":"Services"
        }
    ],
    "sg:postcode":"CF83 1AQ",
    "sg:province":"Caerphilly",
    "sg:tags":[
        "roofing"
    ],
    "wof:name":"Smith,Bryan,",
    "wof:placetype":"venue"
},
  "geometry": {"coordinates":[-3.2292859554,51.5760726929],"type":"Point"}
}