{
  "type": "Feature",
  "properties": {
    "iso:country":"GB",
    "sg:address":"33 Dukes Close, Thurmaston",
    "sg:city":"Leicester",
    "sg:classifiers":[
        {
            "category":"Manufacturing",
            "subcategory":"Electronics",
            "type":"Manufacturing & Wholesale Goods"
        },
        {
            "category":"Shopping",
            "subcategory":"Computers & Home Electronics",
            "type":"Retail Goods"
        }
    ],
    "sg:phone":"+44 116 269 7636",
    "sg:postcode":"LE4 8EY",
    "sg:province":"Leicestershire",
    "sg:tags":[
        "sound",
        "equipment",
        "system",
        "manufacturer"
    ],
    "wof:name":"Midland Sound & Lighting",
    "wof:placetype":"venue"
},
  "geometry": {"coordinates":[-1.087082,52.677914],"type":"Point"}
}