{
  "type": "Feature",
  "properties": {
    "iso:country":"GB",
    "sg:address":"171a Chorley Rd",
    "sg:city":"Chorley",
    "sg:classifiers":[
        {
            "category":"Shopping",
            "subcategory":"Florist",
            "type":"Retail Goods"
        }
    ],
    "sg:phone":"+44 1257 474351",
    "sg:postcode":"PR6 9LP",
    "sg:province":"Lancashire",
    "wof:name":"Cabin Flowers",
    "wof:placetype":"venue"
},
  "geometry": {"coordinates":[-2.597886,53.617786],"type":"Point"}
}