{
  "type": "Feature",
  "properties": {
    "addr:full":"Marsh Farm, 8 Purley Centre Luton Bedfordshire LU3 3SR",
    "addr:housenumber":"8",
    "addr:postcode":"lu3 3sr",
    "addr:street":"Purley Centre",
    "iso:country":"GB",
    "sg:address":"Marsh Farm, 8 Purley Centre",
    "sg:city":"Luton",
    "sg:classifiers":[
        {
            "category":"Farming",
            "subcategory":"Fish & Marine Products",
            "type":"Manufacturing & Wholesale Goods"
        },
        {
            "category":"Food & Beverages",
            "subcategory":"Meat & Fish",
            "type":"Retail Goods"
        }
    ],
    "sg:postcode":"LU3 3SR",
    "sg:province":"Bedfordshire",
    "sg:tags":[
        "fishmonger",
        "butcher"
    ],
    "wof:name":"R J Jarvis Quality Meats",
    "wof:placetype":"venue"
},
  "geometry": {"coordinates":[-0.45423,51.916939],"type":"Point"}
}