{
  "type": "Feature",
  "properties": {
    "addr:full":"15 Talbot Rd Lyme Regis Devon DT7 3BA",
    "addr:housenumber":"15",
    "addr:postcode":"dt7 3ba",
    "addr:street":"Talbot Rd",
    "iso:country":"GB",
    "sg:address":"15 Talbot Rd",
    "sg:city":"Lyme Regis",
    "sg:classifiers":[
        {
            "category":"Conference Center",
            "type":"Public Place"
        }
    ],
    "sg:phone":"+44 1297 445886",
    "sg:postcode":"DT7 3BA",
    "sg:province":"Devon",
    "wof:name":"Conference Connections",
    "wof:placetype":"venue"
},
  "geometry": {"coordinates":[-2.937205,50.734402],"type":"Point"}
}