{
  "type": "Feature",
  "properties": {
    "addr:full":"Unit 2 Concrete Works, Wellthorne Lane Sheffield South Yorkshire S36 7GJ",
    "addr:housenumber":"unit",
    "addr:postcode":"s36 7gj",
    "addr:street":"Wellthorne Lane",
    "iso:country":"GB",
    "sg:address":"Unit 2 Concrete Works, Wellthorne Lane",
    "sg:city":"Sheffield",
    "sg:classifiers":[
        {
            "category":"Manufacturing",
            "subcategory":"Building Materials",
            "type":"Manufacturing & Wholesale Goods"
        }
    ],
    "sg:phone":"+44 1226 761000",
    "sg:postcode":"S36 7GJ",
    "sg:province":"South Yorkshire",
    "sg:tags":[
        "concrete",
        "product"
    ],
    "wof:name":"Bespoke Precast Ltd.",
    "wof:placetype":"venue"
},
  "geometry": {"coordinates":[-1.6708600521,53.5520591736],"type":"Point"}
}