{
  "type": "Feature",
  "properties": {
    "iso:country":"GB",
    "sg:address":"14 Upper Street, Quainton",
    "sg:city":"Aylesbury",
    "sg:classifiers":[
        {
            "category":"Home & Garden",
            "subcategory":"Carpets & Floor Coverings",
            "type":"Retail Goods"
        }
    ],
    "sg:phone":"+44 1296 655208",
    "sg:postcode":"HP22 4AY",
    "sg:province":"Buckinghamshire",
    "sg:tags":[
        "carpets",
        "retailer",
        "rug",
        "matting"
    ],
    "wof:name":"Quainton Carpets",
    "wof:placetype":"venue"
},
  "geometry": {"coordinates":[-0.918715,51.875389],"type":"Point"}
}