{
  "type": "Feature",
  "properties": {
    "iso:country":"GB",
    "sg:address":"16 Red Bank",
    "sg:city":"Manchester",
    "sg:classifiers":[
        {
            "category":"Professional",
            "subcategory":"Business Services",
            "type":"Services"
        }
    ],
    "sg:phone":"+44 161 831 9588",
    "sg:postcode":"M4 4HF",
    "sg:province":"Greater Manchester",
    "sg:tags":[
        "import",
        "export",
        "agent"
    ],
    "wof:name":"Global City Ltd",
    "wof:placetype":"venue"
},
  "geometry": {"coordinates":[-2.237084,53.492348],"type":"Point"}
}