{
  "type": "Feature",
  "properties": {
    "iso:country":"GB",
    "sg:address":"The North Suite, 4 Holme Street",
    "sg:city":"Glasgow",
    "sg:classifiers":[
        {
            "category":"Professional",
            "subcategory":"Secretarial Services",
            "type":"Services"
        }
    ],
    "sg:phone":"+44 141 221 3074",
    "sg:postcode":"G2 6SW",
    "sg:province":"Glasgow City",
    "sg:tags":[
        "processing",
        "word"
    ],
    "wof:name":"J J Kennedy Office Equipment",
    "wof:placetype":"venue"
},
  "geometry": {"coordinates":[-4.26031,55.859112],"type":"Point"}
}