{
  "type": "Feature",
  "properties": {
    "iso:country":"GB",
    "sg:address":"560 Market Way",
    "sg:city":"Wembley",
    "sg:classifiers":[
        {
            "category":"Professional",
            "subcategory":"Printing & Photocopies",
            "type":"Services"
        }
    ],
    "sg:phone":"+44 20 8903 3478",
    "sg:postcode":"HA0 2BT",
    "sg:province":"Greater London",
    "sg:tags":[
        "printer"
    ],
    "wof:name":"Lotus Press",
    "wof:placetype":"venue"
},
  "geometry": {"coordinates":[-0.298037,51.552197],"type":"Point"}
}