{
  "type": "Feature",
  "properties": {
    "iso:country":"GB",
    "sg:address":"10 King Edwards Buildings, Bury Old Road Salford",
    "sg:city":"Manchester",
    "sg:classifiers":[
        {
            "category":"Food & Beverages",
            "subcategory":"Specialty",
            "type":"Retail Goods"
        }
    ],
    "sg:postcode":"M7 4QJ",
    "sg:province":"Greater Manchester",
    "sg:tags":[
        "product",
        "health"
    ],
    "wof:name":"The Laughing Lental",
    "wof:placetype":"venue"
},
  "geometry": {"coordinates":[-2.246254,53.513554],"type":"Point"}
}