{
  "type": "Feature",
  "properties": {
    "addr:full":"34 Tame Street, Denton Manchester Greater Manchester M34 3HW",
    "addr:housenumber":"34",
    "addr:postcode":"m34 3hw",
    "addr:street":"Tame Street",
    "iso:country":"GB",
    "sg:address":"34 Tame Street, Denton",
    "sg:city":"Manchester",
    "sg:classifiers":[
        {
            "category":"Communications",
            "subcategory":"Film & Video Production",
            "type":"Services"
        }
    ],
    "sg:postcode":"M34 3HW",
    "sg:province":"Greater Manchester",
    "sg:tags":[
        "illustrator",
        "artist"
    ],
    "wof:name":"Animal Portraits",
    "wof:placetype":"venue"
},
  "geometry": {"coordinates":[-2.1111409664,53.4605903625],"type":"Point"}
}