{
  "type": "Feature",
  "properties": {
    "addr:full":"Newlands Farm, Newlands Road Mansfield Derbyshire NG19 0HU",
    "addr:postcode":"ng19 0hu",
    "addr:street":"Newlands Road",
    "iso:country":"GB",
    "sg:address":"Newlands Farm, Newlands Road",
    "sg:city":"Mansfield",
    "sg:classifiers":[
        {
            "category":"Building & Trades",
            "subcategory":"Landscaping Services",
            "type":"Services"
        },
        {
            "category":"Professional",
            "subcategory":"Engineering",
            "type":"Services"
        }
    ],
    "sg:phone":"+44 1623 621449",
    "sg:postcode":"NG19 0HU",
    "sg:province":"Derbyshire",
    "sg:tags":[
        "horticultural"
    ],
    "wof:name":"J E D & E M Cowpe",
    "wof:placetype":"venue"
},
  "geometry": {"coordinates":[-1.141479,53.160854],"type":"Point"}
}