{
  "type": "Feature",
  "properties": {
    "addr:full":"46 Station Road East Oxted Surrey RH8 0PG",
    "addr:housenumber":"46",
    "addr:postcode":"rh8 0pg",
    "addr:street":"Station Road East",
    "iso:country":"GB",
    "sg:address":"46 Station Road East",
    "sg:city":"Oxted",
    "sg:classifiers":[
        {
            "category":"Shopping",
            "subcategory":"Clothing, Apparel, & Fashions",
            "type":"Retail Goods"
        }
    ],
    "sg:phone":"+44 1883 730860",
    "sg:postcode":"RH8 0PG",
    "sg:province":"Surrey",
    "sg:tags":[
        "menswear"
    ],
    "wof:name":"County Clothing Co",
    "wof:placetype":"venue"
},
  "geometry": {"coordinates":[-0.002197,51.257713],"type":"Point"}
}