{
  "type": "Feature",
  "properties": {
    "addr:full":"Colebrook Road, Plympton Plymouth Devon PL7 4AA",
    "addr:postcode":"pl7 4aa",
    "addr:street":"Colebrook Road",
    "iso:country":"GB",
    "sg:address":"Colebrook Road, Plympton",
    "sg:city":"Plymouth",
    "sg:classifiers":[
        {
            "category":"Shopping",
            "subcategory":"Pets & Pet Supplies",
            "type":"Retail Goods"
        }
    ],
    "sg:phone":"+44 1752 337334",
    "sg:postcode":"PL7 4AA",
    "sg:province":"Devon",
    "sg:tags":[
        "food"
    ],
    "wof:name":"T G Willcocks",
    "wof:placetype":"venue"
},
  "geometry": {"coordinates":[-4.054077,50.394093],"type":"Point"}
}