{
  "type": "Feature",
  "properties": {
    "iso:country":"GB",
    "sg:address":"The Willows, Lakeview, Alsager",
    "sg:city":"Stoke-on-trent",
    "sg:classifiers":[
        {
            "category":"Professional",
            "subcategory":"Computer Services",
            "type":"Services"
        }
    ],
    "sg:phone":"+44 1270 878552",
    "sg:postcode":"ST7 2FY",
    "sg:province":"Cheshire",
    "sg:tags":[
        "system",
        "software"
    ],
    "wof:name":"Datamore Ltd.",
    "wof:placetype":"venue"
},
  "geometry": {"coordinates":[-2.3023540974,53.0966262817],"type":"Point"}
}