{
  "type": "Feature",
  "properties": {
    "iso:country":"GB",
    "sg:address":"Abercorn Ind Est, Abercorn St",
    "sg:city":"Paisley",
    "sg:classifiers":[
        {
            "category":"Building & Trades",
            "subcategory":"Construction",
            "type":"Services"
        }
    ],
    "sg:phone":"+44 141 840 4404",
    "sg:postcode":"PA3 4AT",
    "sg:province":"Renfrewshire",
    "sg:tags":[
        "builder"
    ],
    "wof:name":"Ace Home Improvements",
    "wof:placetype":"venue"
},
  "geometry": {"coordinates":[-4.421379,55.852905],"type":"Point"}
}