{
  "type": "Feature",
  "properties": {
    "iso:country":"GB",
    "sg:address":"17 New Broadway, Uxbridge Road, Hillingdon",
    "sg:city":"Uxbridge",
    "sg:classifiers":[
        {
            "category":"Shopping",
            "subcategory":"Computers & Home Electronics",
            "type":"Retail Goods"
        }
    ],
    "sg:phone":"+44 1895 233036",
    "sg:postcode":"UB10 0LJ",
    "sg:province":"Greater London",
    "sg:tags":[
        "electrical"
    ],
    "wof:name":"T & R Electrical",
    "wof:placetype":"venue"
},
  "geometry": {"coordinates":[-0.449564,51.531376],"type":"Point"}
}