{
  "type": "Feature",
  "properties": {
    "addr:full":"899 Walsall Road, Great Barr Birmingham West Midlands B42 1TN",
    "addr:housenumber":"899",
    "addr:postcode":"b42 1tn",
    "addr:street":"Walsall Road",
    "iso:country":"GB",
    "sg:address":"899 Walsall Road, Great Barr",
    "sg:city":"Birmingham",
    "sg:classifiers":[
        {
            "category":"Food & Beverages",
            "subcategory":"Liquor & Beverages",
            "type":"Retail Goods"
        }
    ],
    "sg:phone":"+44 121 357 2089",
    "sg:postcode":"B42 1TN",
    "sg:province":"West Midlands",
    "sg:tags":[
        "beer",
        "spirit",
        "wines"
    ],
    "wof:name":"Victoria Wine",
    "wof:placetype":"venue"
},
  "geometry": {"coordinates":[-1.9306010008,52.5443382263],"type":"Point"}
}