{
  "type": "Feature",
  "properties": {
    "iso:country":"GB",
    "sg:address":"Dock Meadow Dr",
    "sg:city":"Wolverhampton",
    "sg:classifiers":[
        {
            "category":"Building & Trades",
            "subcategory":"Cleaning & Sanitation",
            "type":"Services"
        }
    ],
    "sg:postcode":"WV4 6LE",
    "sg:province":"Staffordshire",
    "sg:tags":[
        "blast"
    ],
    "wof:name":"Lowe,Alan,",
    "wof:placetype":"venue"
},
  "geometry": {"coordinates":[-2.099174,52.55777],"type":"Point"}
}