{
  "type": "Feature",
  "properties": {
    "addr:full":"8 Clapham Terrace, Forge Side, Blaenavon Pontypool Monmouthshire NP4 9DE",
    "addr:housenumber":"8",
    "addr:postcode":"np4 9de",
    "addr:street":"Clapham Terrace Forge Side",
    "iso:country":"GB",
    "sg:address":"8 Clapham Terrace, Forge Side, Blaenavon",
    "sg:city":"Pontypool",
    "sg:classifiers":[
        {
            "category":"Government",
            "subcategory":"Post Office",
            "type":"Public Place"
        }
    ],
    "sg:phone":"+44 1495 790291",
    "sg:postcode":"NP4 9DE",
    "sg:province":"Monmouthshire",
    "wof:name":"Forge Side Sub Post Office",
    "wof:placetype":"venue"
},
  "geometry": {"coordinates":[-3.095102,51.770145],"type":"Point"}
}