{
  "type": "Feature",
  "properties": {
    "addr:full":"3 & 4 Griffin Industrial Mall Aylesbury Buckinghamshire HP19 8BP",
    "addr:housenumber":"3 & 4",
    "addr:postcode":"hp19 8bp",
    "addr:street":"Griffin Industrial Mall",
    "iso:country":"GB",
    "sg:address":"3 & 4 Griffin Industrial Mall",
    "sg:city":"Aylesbury",
    "sg:classifiers":[
        {
            "category":"Professional",
            "subcategory":"Printing & Photocopies",
            "type":"Services"
        }
    ],
    "sg:phone":"+44 1296 484552",
    "sg:postcode":"HP19 8BP",
    "sg:province":"Buckinghamshire",
    "sg:tags":[
        "printer"
    ],
    "wof:name":"Crysacol Ltd",
    "wof:placetype":"venue"
},
  "geometry": {"coordinates":[-0.83133,51.82119],"type":"Point"}
}