{
  "type": "Feature",
  "properties": {
    "addr:full":"29 Hackett St Tipton West Midlands DY4 0JJ",
    "addr:housenumber":"29",
    "addr:postcode":"dy4 0jj",
    "addr:street":"Hackett St",
    "iso:country":"GB",
    "sg:address":"29 Hackett St",
    "sg:city":"Tipton",
    "sg:classifiers":[
        {
            "category":"Wholesale",
            "subcategory":"Construction Materials",
            "type":"Manufacturing & Wholesale Goods"
        }
    ],
    "sg:phone":"+44 121 557 1728",
    "sg:postcode":"DY4 0JJ",
    "sg:province":"West Midlands",
    "sg:tags":[
        "distributor",
        "spring"
    ],
    "wof:name":"T T E Road Springs Ltd",
    "wof:placetype":"venue"
},
  "geometry": {"coordinates":[-2.0411710739,52.5354766846],"type":"Point"}
}