{
  "type": "Feature",
  "properties": {
    "iso:country":"GB",
    "sg:address":"63 Deere Avenue",
    "sg:city":"Rainham",
    "sg:classifiers":[
        {
            "category":"Shopping",
            "subcategory":"Pharmacy",
            "type":"Retail Goods"
        }
    ],
    "sg:phone":"+44 1708 523304",
    "sg:postcode":"RM13 7JD",
    "sg:province":"Essex",
    "sg:tags":[
        "medicine",
        "therapy"
    ],
    "wof:name":"Kabworks",
    "wof:placetype":"venue"
},
  "geometry": {"coordinates":[0.19616,51.541672],"type":"Point"}
}