{
  "type": "Feature",
  "properties": {
    "iso:country":"GB",
    "sg:address":"31 Street Lane",
    "sg:city":"Leeds",
    "sg:classifiers":[
        {
            "category":"Health Services",
            "subcategory":"Nursing And Care Facility",
            "type":"Services"
        }
    ],
    "sg:phone":"+44 113 266 4381",
    "sg:postcode":"LS8 1BW",
    "sg:province":"West Yorkshire",
    "sg:tags":[
        "home",
        "residential"
    ],
    "wof:name":"Ashcroft Lodge",
    "wof:placetype":"venue"
},
  "geometry": {"coordinates":[-1.505609,53.842957],"type":"Point"}
}