{
  "type": "Feature",
  "properties": {
    "addr:full":"52 St Enoch Square Glasgow Glasgow City G1 4AA",
    "addr:housenumber":"52",
    "addr:postcode":"g1 4aa",
    "addr:street":"St Enoch Square",
    "iso:country":"GB",
    "sg:address":"52 St Enoch Square",
    "sg:city":"Glasgow",
    "sg:classifiers":[
        {
            "category":"Personal",
            "type":"Services"
        },
        {
            "category":"Retail",
            "subcategory":"Laundry & Dry Cleaning",
            "type":"Services"
        }
    ],
    "sg:phone":"+44 141 248 8127",
    "sg:postcode":"G1 4AA",
    "sg:province":"Glasgow City",
    "sg:tags":[
        "tailor",
        "alteration"
    ],
    "wof:name":"Mellisa",
    "wof:placetype":"venue"
},
  "geometry": {"coordinates":[-4.2557721138,55.8575057983],"type":"Point"}
}