{
  "type": "Feature",
  "properties": {
    "iso:country":"GB",
    "sg:address":"3b Westgate",
    "sg:city":"Oxford",
    "sg:classifiers":[
        {
            "category":"Shopping",
            "subcategory":"Clothing, Apparel, & Fashions",
            "type":"Retail Goods"
        }
    ],
    "sg:phone":"+44 1865 790174",
    "sg:postcode":"OX1 1NU",
    "sg:province":"Oxfordshire",
    "sg:tags":[
        "shop"
    ],
    "wof:name":"Pilot Clothing Ltd.",
    "wof:placetype":"venue"
},
  "geometry": {"coordinates":[-1.259489,51.756207],"type":"Point"}
}