{
  "type": "Feature",
  "properties": {
    "addr:full":"Unit 2 The Wallows Indust Est, Fens Pool Av Brierley Hill West Midlands DY5 1QA",
    "addr:housenumber":"unit 2",
    "addr:postcode":"dy5 1qa",
    "addr:street":"The Wallows Indust Est;Av Brierley Hill",
    "iso:country":"GB",
    "sg:address":"Unit 2 The Wallows Indust Est, Fens Pool Av",
    "sg:city":"Brierley Hill",
    "sg:classifiers":[
        {
            "category":"Retail",
            "subcategory":"Auto Repair",
            "type":"Services"
        }
    ],
    "sg:phone":"+44 1384 352352",
    "sg:postcode":"DY5 1QA",
    "sg:province":"West Midlands",
    "sg:tags":[
        "engine",
        "car",
        "specialist"
    ],
    "wof:name":"Japanese Engine Traders",
    "wof:placetype":"venue"
},
  "geometry": {"coordinates":[-2.121301,52.482044],"type":"Point"}
}