{
  "type": "Feature",
  "properties": {
    "addr:full":"Manston Road Ramsgate Kent CT12 6HW",
    "addr:postcode":"ct12 6hw",
    "addr:street":"Manston Road Ramsgate",
    "iso:country":"GB",
    "sg:address":"Manston Road",
    "sg:city":"Ramsgate",
    "sg:classifiers":[
        {
            "category":"Manufacturing",
            "subcategory":"Rubber & Plastics",
            "type":"Manufacturing & Wholesale Goods"
        }
    ],
    "sg:phone":"+44 1843 854000",
    "sg:postcode":"CT12 6HW",
    "sg:province":"Kent",
    "sg:tags":[
        "product",
        "manufacturer"
    ],
    "wof:name":"Flambeau Europlast Ltd.",
    "wof:placetype":"venue"
},
  "geometry": {"coordinates":[1.3472319841,51.349395752],"type":"Point"}
}