{
  "type": "Feature",
  "properties": {
    "addr:full":"1 North Hill St Liverpool Merseyside L8 8BG",
    "addr:housenumber":"1",
    "addr:postcode":"l8 8bg",
    "addr:street":"North Hill St",
    "iso:country":"GB",
    "sg:address":"1 North Hill St",
    "sg:city":"Liverpool",
    "sg:classifiers":[
        {
            "category":"Bars & Pubs",
            "type":"Food & Drink"
        }
    ],
    "sg:postcode":"L8 8BG",
    "sg:province":"Merseyside",
    "sg:tags":[
        "pubs",
        "inn"
    ],
    "wof:name":"Phillips,A,",
    "wof:placetype":"venue"
},
  "geometry": {"coordinates":[-2.9674780369,53.3865127563],"type":"Point"}
}