{
  "type": "Feature",
  "properties": {
    "iso:country":"GB",
    "sg:address":"149 Finchley Road",
    "sg:city":"London",
    "sg:classifiers":[
        {
            "category":"Food & Beverages",
            "subcategory":"Bakery",
            "type":"Retail Goods"
        }
    ],
    "sg:phone":"+44 20 7722 8182",
    "sg:postcode":"NW3 6JH",
    "sg:province":"Greater London",
    "sg:tags":[
        "pizza"
    ],
    "wof:name":"Pizza Hut",
    "wof:placetype":"venue"
},
  "geometry": {"coordinates":[-0.180686,51.548416],"type":"Point"}
}