{
  "type": "Feature",
  "properties": {
    "iso:country":"GB",
    "sg:address":"14 Telford House, Moorfields Rd",
    "sg:city":"Bath",
    "sg:classifiers":[
        {
            "category":"Communications",
            "subcategory":"Film & Video Production",
            "type":"Services"
        }
    ],
    "sg:phone":"+44 1225 355936",
    "sg:postcode":"BA2 2HT",
    "sg:province":"Somerset",
    "sg:tags":[
        "illustrator",
        "artist"
    ],
    "wof:name":"J.C.M Parry",
    "wof:placetype":"venue"
},
  "geometry": {"coordinates":[-2.3796300888,51.3692893982],"type":"Point"}
}