{
  "type": "Feature",
  "properties": {
    "iso:country":"GB",
    "sg:address":"Unit 28-33, The Forum, Independent Place",
    "sg:city":"Hackney",
    "sg:classifiers":[
        {
            "category":"Professional",
            "subcategory":"Computer Services",
            "type":"Services"
        }
    ],
    "sg:phone":"+44 20 7275 8195",
    "sg:postcode":"E8 2HE",
    "sg:province":"Greater London",
    "sg:tags":[
        "consultant"
    ],
    "wof:name":"Hoxton Bibliotech",
    "wof:placetype":"venue"
},
  "geometry": {"coordinates":[-0.071054,51.552174],"type":"Point"}
}