{
  "type": "Feature",
  "properties": {
    "addr:full":"164 Milton Rd Southsea Hampshire PO4 8PN",
    "addr:housenumber":"164",
    "addr:postcode":"po4 8pn",
    "addr:street":"Milton Rd",
    "iso:country":"GB",
    "sg:address":"164 Milton Rd",
    "sg:city":"Southsea",
    "sg:classifiers":[
        {
            "category":"Home & Garden",
            "subcategory":"Home Furnishings",
            "type":"Retail Goods"
        }
    ],
    "sg:phone":"+44 23 9287 3444",
    "sg:postcode":"PO4 8PN",
    "sg:province":"Hampshire",
    "sg:tags":[
        "beds",
        "bedding",
        "blanket",
        "bed"
    ],
    "wof:name":"High & Dry Waterbeds",
    "wof:placetype":"venue"
},
  "geometry": {"coordinates":[-1.059379,50.795979],"type":"Point"}
}