{
  "type": "Feature",
  "properties": {
    "addr:full":"Wildacre Collytown, Bere Alston Yelverton Devon PL20 7ED",
    "addr:postcode":"pl20 7ed",
    "iso:country":"GB",
    "sg:address":"Wildacre Collytown, Bere Alston",
    "sg:city":"Yelverton",
    "sg:classifiers":[
        {
            "category":"Professional",
            "type":"Services"
        },
        {
            "category":"Building & Trades",
            "subcategory":"Cleaning & Sanitation",
            "type":"Services"
        }
    ],
    "sg:phone":"+44 1822 841005",
    "sg:postcode":"PL20 7ED",
    "sg:province":"Devon",
    "sg:tags":[
        "dry",
        "control",
        "damp",
        "rot",
        "preservation"
    ],
    "wof:name":"Active Services",
    "wof:placetype":"venue"
},
  "geometry": {"coordinates":[-4.189649,50.480156],"type":"Point"}
}