{
  "type": "Feature",
  "properties": {
    "addr:full":"Poplar Gro, South Bank Middlesbrough North Yorkshire TS6 6SU",
    "addr:postcode":"ts6 6su",
    "addr:street":"Gro South Bank",
    "iso:country":"GB",
    "sg:address":"Poplar Gro, South Bank",
    "sg:city":"Middlesbrough",
    "sg:classifiers":[
        {
            "category":"Education",
            "subcategory":"School",
            "type":"Public Place"
        }
    ],
    "sg:phone":"+44 1642 453451",
    "sg:postcode":"TS6 6SU",
    "sg:province":"North Yorkshire",
    "sg:tags":[
        "local",
        "authority"
    ],
    "wof:name":"Beech Grove Primary School",
    "wof:placetype":"venue"
},
  "geometry": {"coordinates":[-1.1731740236,54.5778045654],"type":"Point"}
}