{
  "type": "Feature",
  "properties": {
    "addr:full":"Unit 45, Evelyn St, Beeston Nottingham Nottinghamshire NG9 2EU",
    "addr:housenumber":"unit 45",
    "addr:postcode":"ng9 2eu",
    "addr:street":"Evelyn St",
    "iso:country":"GB",
    "sg:address":"Unit 45, Evelyn St, Beeston",
    "sg:city":"Nottingham",
    "sg:classifiers":[
        {
            "category":"Manufacturing",
            "subcategory":"Tobacco Products",
            "type":"Manufacturing & Wholesale Goods"
        }
    ],
    "sg:phone":"+44 115 967 7766",
    "sg:postcode":"NG9 2EU",
    "sg:province":"Nottinghamshire",
    "sg:tags":[
        "ind",
        "plastic"
    ],
    "wof:name":"Double Quick Supplyline",
    "wof:placetype":"venue"
},
  "geometry": {"coordinates":[-1.2043449879,52.9282951355],"type":"Point"}
}