{
  "type": "Feature",
  "properties": {
    "addr:full":"Meadow Walk, South Woodford London Greater London E18 2EN",
    "addr:postcode":"e18 2en",
    "addr:street":"Meadow Walk",
    "iso:country":"GB",
    "sg:address":"Meadow Walk, South Woodford",
    "sg:city":"London",
    "sg:classifiers":[
        {
            "category":"Education",
            "subcategory":"School",
            "type":"Public Place"
        },
        {
            "category":"Government",
            "subcategory":"Office",
            "type":"Public Place"
        }
    ],
    "sg:phone":"+44 20 8989 9975",
    "sg:postcode":"E18 2EN",
    "sg:province":"Greater London",
    "sg:tags":[
        "local",
        "authority"
    ],
    "wof:name":"Snaresbrook Primary School",
    "wof:placetype":"venue"
},
  "geometry": {"coordinates":[0.02306,51.585884],"type":"Point"}
}