{
  "type": "Feature",
  "properties": {
    "iso:country":"GB",
    "sg:address":"220 Frimley Rd",
    "sg:city":"Camberley",
    "sg:classifiers":[
        {
            "category":"Restaurant",
            "type":"Food & Drink"
        }
    ],
    "sg:phone":"+44 1276 22578",
    "sg:postcode":"GU15 2QJ",
    "sg:province":"Berkshire",
    "wof:name":"The Crab & Dragon",
    "wof:placetype":"venue"
},
  "geometry": {"coordinates":[-0.753635,51.322315],"type":"Point"}
}