{
  "type": "Feature",
  "properties": {
    "iso:country":"GB",
    "sg:address":"35 Stainland Road, Greetland",
    "sg:city":"Halifax",
    "sg:classifiers":[
        {
            "category":"Community Center",
            "subcategory":"Social",
            "type":"Public Place"
        }
    ],
    "sg:phone":"+44 1422 370857",
    "sg:postcode":"HX4 8AD",
    "sg:province":"West Yorkshire",
    "sg:tags":[
        "frozen",
        "food",
        "freezer",
        "centre"
    ],
    "wof:name":"Chillie Willie S Frozen Foods",
    "wof:placetype":"venue"
},
  "geometry": {"coordinates":[-1.855447,53.687191],"type":"Point"}
}