{
  "type": "Feature",
  "properties": {
    "iso:country":"GB",
    "sg:address":"5 Worthele Close",
    "sg:city":"Ivybridge",
    "sg:classifiers":[
        {
            "category":"Personal",
            "type":"Services"
        }
    ],
    "sg:postcode":"PL21 9UQ",
    "sg:province":"Devon",
    "sg:tags":[
        "wedding"
    ],
    "wof:name":"The Finishing Touch",
    "wof:placetype":"venue"
},
  "geometry": {"coordinates":[-3.94155,50.387642],"type":"Point"}
}