{
  "type": "Feature",
  "properties": {
    "iso:country":"GB",
    "sg:address":"116 Frederick Road",
    "sg:city":"Rainham",
    "sg:classifiers":[
        {
            "category":"Professional",
            "subcategory":"Lawyer & Legal Services",
            "type":"Services"
        }
    ],
    "sg:postcode":"RM13 8NS",
    "sg:province":"Essex",
    "sg:tags":[
        "solicitor"
    ],
    "wof:name":"M & B Law Consultants Ltd",
    "wof:placetype":"venue"
},
  "geometry": {"coordinates":[0.1741659939,51.5286598206],"type":"Point"}
}