{
  "type": "Feature",
  "properties": {
    "iso:country":"GB",
    "sg:address":"70a High Street",
    "sg:city":"Ingatestone",
    "sg:classifiers":[
        {
            "category":"Banks & Credit Unions",
            "subcategory":"Financial Services",
            "type":"Services"
        }
    ],
    "sg:phone":"+44 1277 355775",
    "sg:postcode":"CM4 9DW",
    "sg:province":"Essex",
    "sg:tags":[
        "agent",
        "tied"
    ],
    "wof:name":"David Charles Financial Services",
    "wof:placetype":"venue"
},
  "geometry": {"coordinates":[0.385894,51.671425],"type":"Point"}
}