{
  "type": "Feature",
  "properties": {
    "iso:country":"GB",
    "sg:address":"154 Thelwall Lane",
    "sg:city":"Warrington",
    "sg:classifiers":[
        {
            "category":"Personal",
            "subcategory":"Beauty Salon",
            "type":"Services"
        }
    ],
    "sg:phone":"+44 1925 634771",
    "sg:postcode":"WA4 1LU",
    "sg:province":"Cheshire",
    "sg:tags":[
        "lady",
        "hairdresser"
    ],
    "wof:name":"Robert Anderson Salon",
    "wof:placetype":"venue"
},
  "geometry": {"coordinates":[-2.5576,53.381554],"type":"Point"}
}