{
  "type": "Feature",
  "properties": {
    "iso:country":"GB",
    "sg:address":"30 Clarence Rd",
    "sg:city":"Grays",
    "sg:classifiers":[
        {
            "category":"Travel",
            "subcategory":"Travel Agent",
            "type":"Entertainment"
        }
    ],
    "sg:phone":"+44 1375 399000",
    "sg:postcode":"RM17 6QJ",
    "sg:province":"Essex",
    "wof:name":"Grays Travelcommunications",
    "wof:placetype":"venue"
},
  "geometry": {"coordinates":[0.3260110021,51.4776573181],"type":"Point"}
}