{
  "type": "Feature",
  "properties": {
    "iso:country":"GB",
    "sg:address":"145 Handley Road, New Whittington",
    "sg:city":"Chesterfield",
    "sg:classifiers":[
        {
            "category":"Social Services",
            "subcategory":"Retirement Home",
            "type":"Services"
        }
    ],
    "sg:phone":"+44 1246 454051",
    "sg:postcode":"S43 2EP",
    "sg:province":"Derbyshire",
    "sg:tags":[
        "residential",
        "care"
    ],
    "wof:name":"Ingledene Residential Care Home",
    "wof:placetype":"venue"
},
  "geometry": {"coordinates":[-1.4039119482,53.2795295715],"type":"Point"}
}