{
  "type": "Feature",
  "properties": {
    "addr:full":"Norwich Road Dereham Norfolk NR20 3PX",
    "addr:postcode":"nr20 3px",
    "addr:street":"Norwich Road",
    "iso:country":"GB",
    "sg:address":"Norwich Road",
    "sg:city":"Dereham",
    "sg:classifiers":[
        {
            "category":"Train Station",
            "subcategory":"Rail",
            "type":"Transportation"
        }
    ],
    "sg:phone":"+44 1362 696434",
    "sg:postcode":"NR20 3PX",
    "sg:province":"Norfolk",
    "sg:tags":[
        "caravan"
    ],
    "wof:name":"Greentree Caravans",
    "wof:placetype":"venue"
},
  "geometry": {"coordinates":[0.9678549767,52.6804161072],"type":"Point"}
}