{
  "type": "Feature",
  "properties": {
    "iso:country":"GB",
    "sg:address":"57 Ann Rd",
    "sg:city":"Birmingham",
    "sg:classifiers":[
        {
            "category":"Social Services",
            "subcategory":"Adult Care",
            "type":"Services"
        }
    ],
    "sg:phone":"+44 1564 822076",
    "sg:postcode":"B47 6EP",
    "sg:province":"Worcestershire",
    "sg:tags":[
        "domestic",
        "cleaning"
    ],
    "wof:name":"Finishing Touches",
    "wof:placetype":"venue"
},
  "geometry": {"coordinates":[-1.881563,52.376331],"type":"Point"}
}