{
  "type": "Feature",
  "properties": {
    "addr:full":"22 Fair Leas Chesham Buckinghamshire HP5 2QW",
    "addr:housenumber":"22",
    "addr:postcode":"hp5 2qw",
    "addr:street":"Fair Leas",
    "iso:country":"GB",
    "sg:address":"22 Fair Leas",
    "sg:city":"Chesham",
    "sg:classifiers":[
        {
            "category":"Place Of Worship",
            "type":"Public Place"
        }
    ],
    "sg:phone":"+44 845 644 2370",
    "sg:postcode":"HP5 2QW",
    "sg:province":"Buckinghamshire",
    "wof:name":"South Bucks Jewish Community",
    "wof:placetype":"venue"
},
  "geometry": {"coordinates":[-0.6220459938,51.7145805359],"type":"Point"}
}