{
  "type": "Feature",
  "properties": {
    "iso:country":"GB",
    "sg:address":"P O Box 157, Radley",
    "sg:city":"Abingdon",
    "sg:classifiers":[
        {
            "category":"Shopping",
            "subcategory":"Clothing, Apparel, & Fashions",
            "type":"Retail Goods"
        }
    ],
    "sg:postcode":"OX14 2HR",
    "sg:province":"Oxfordshire",
    "sg:tags":[
        "t-shirt"
    ],
    "wof:name":"Rock the Boat",
    "wof:placetype":"venue"
},
  "geometry": {"coordinates":[-1.247432,51.690105],"type":"Point"}
}