{
  "type": "Feature",
  "properties": {
    "addr:full":"10 Chelsham Road Warlingham Kent CR6 9EQ",
    "addr:housenumber":"10",
    "addr:postcode":"cr6 9eq",
    "addr:street":"Chelsham Road",
    "iso:country":"GB",
    "sg:address":"10 Chelsham Road",
    "sg:city":"Warlingham",
    "sg:classifiers":[
        {
            "category":"Retail",
            "subcategory":"Funeral Services",
            "type":"Services"
        }
    ],
    "sg:phone":"+44 1883 624484",
    "sg:postcode":"CR6 9EQ",
    "sg:province":"Kent",
    "sg:tags":[
        "cemetery",
        "crematorium"
    ],
    "wof:name":"Greenlawn Memorial Park",
    "wof:placetype":"venue"
},
  "geometry": {"coordinates":[-0.040956,51.308956],"type":"Point"}
}