{
  "type": "Feature",
  "properties": {
    "iso:country":"GB",
    "sg:address":"29 Wentworth Street",
    "sg:city":"London",
    "sg:classifiers":[
        {
            "category":"Shopping",
            "subcategory":"Clothing, Apparel, & Fashions",
            "type":"Retail Goods"
        }
    ],
    "sg:phone":"+44 20 7247 4845",
    "sg:postcode":"E1 7TB",
    "sg:province":"Greater London",
    "sg:tags":[
        "menswear"
    ],
    "wof:name":"Frank G Fisher Group Companies Ltd.",
    "wof:placetype":"venue"
},
  "geometry": {"coordinates":[-0.0753939971,51.5166969299],"type":"Point"}
}