{
  "type": "Feature",
  "properties": {
    "addr:full":"3 St Andrews Pl Camden Greater London NW1 4LB",
    "addr:housenumber":"3",
    "addr:postcode":"nw1 4lb",
    "addr:street":"St Andrews Pl",
    "iso:country":"GB",
    "sg:address":"3 St Andrews Pl",
    "sg:city":"Camden",
    "sg:classifiers":[
        {
            "category":"Organizations",
            "subcategory":"Non-profit Organization",
            "type":"Services"
        }
    ],
    "sg:phone":"+44 20 7486 0341",
    "sg:postcode":"NW1 4LB",
    "sg:province":"Greater London",
    "sg:tags":[
        "organisation",
        "voluntary",
        "charity"
    ],
    "wof:name":"British Digestive Foundation",
    "wof:placetype":"venue"
},
  "geometry": {"coordinates":[-0.252402,51.514301],"type":"Point"}
}