{
  "type": "Feature",
  "properties": {
    "addr:full":"63 The Brambles Crowthorne Berkshire RG11 6EF",
    "addr:housenumber":"63",
    "addr:postcode":"rg11 6ef",
    "addr:street":"The Brambles",
    "iso:country":"GB",
    "sg:address":"63 The Brambles",
    "sg:city":"Crowthorne",
    "sg:classifiers":[
        {
            "category":"Professional",
            "subcategory":"Management & Consulting",
            "type":"Services"
        }
    ],
    "sg:phone":"+44 1344 751119",
    "sg:postcode":"RG11 6EF",
    "sg:province":"Berkshire",
    "sg:tags":[
        "marketing",
        "consultant"
    ],
    "wof:name":"Trilobyte Services",
    "wof:placetype":"venue"
},
  "geometry": {"coordinates":[-0.826308012,51.3767127991],"type":"Point"}
}