{
  "type": "Feature",
  "properties": {
    "iso:country":"GB",
    "sg:address":"Titheban St",
    "sg:city":"Keswick",
    "sg:classifiers":[
        {
            "category":"Food & Beverages",
            "subcategory":"Supermarket",
            "type":"Retail Goods"
        }
    ],
    "sg:postcode":"CA12 5EA",
    "sg:province":"Cumbria",
    "wof:name":"Freshchoice Lakeland Ltd",
    "wof:placetype":"venue"
},
  "geometry": {"coordinates":[-3.138964,54.60173],"type":"Point"}
}