{
  "type": "Feature",
  "properties": {
    "iso:country":"GB",
    "sg:address":"Whiteyetts",
    "sg:city":"Alloa",
    "sg:classifiers":[
        {
            "category":"Professional",
            "subcategory":"Engineering",
            "type":"Services"
        }
    ],
    "sg:phone":"+44 1259 722073",
    "sg:postcode":"FK10 3AQ",
    "sg:province":"Clackmannanshire",
    "sg:tags":[
        "contractor",
        "electrical",
        "engineer"
    ],
    "wof:name":"Devon Electrical & Rewinding Services",
    "wof:placetype":"venue"
},
  "geometry": {"coordinates":[-3.7738549709,56.133769989],"type":"Point"}
}