{
  "type": "Feature",
  "properties": {
    "addr:full":"Unit, Unit 47, Mayfield Industrial Estate Dalkeith City of Edinburgh EH22 4AD",
    "addr:housenumber":"unit 47",
    "addr:postcode":"eh22 4ad",
    "addr:street":"Mayfield Industrial Estate",
    "iso:country":"GB",
    "sg:address":"Unit, Unit 47, Mayfield Industrial Estate",
    "sg:city":"Dalkeith",
    "sg:classifiers":[
        {
            "category":"Building & Trades",
            "subcategory":"Plumbing",
            "type":"Services"
        }
    ],
    "sg:phone":"+44 131 663 5441",
    "sg:postcode":"EH22 4AD",
    "sg:province":"City of Edinburgh",
    "sg:tags":[
        "central",
        "installation",
        "system",
        "servicing",
        "heating"
    ],
    "wof:name":"Silvatye Heating (Scotland) Ltd",
    "wof:placetype":"venue"
},
  "geometry": {"coordinates":[-3.052009,55.868851],"type":"Point"}
}