{
  "type": "Feature",
  "properties": {
    "iso:country":"GB",
    "sg:address":"33 Caister Avenue, Chapeltown",
    "sg:city":"Sheffield",
    "sg:classifiers":[
        {
            "category":"Arts & Performance",
            "subcategory":"Music",
            "type":"Entertainment"
        }
    ],
    "sg:phone":"+44 114 240 0420",
    "sg:postcode":"S35 2ZN",
    "sg:province":"South Yorkshire",
    "sg:tags":[
        "mobile",
        "disco"
    ],
    "wof:name":"K L M Mobile Disco",
    "wof:placetype":"venue"
},
  "geometry": {"coordinates":[-1.481285,53.463657],"type":"Point"}
}