{
  "type": "Feature",
  "properties": {
    "addr:full":"Ashcroft, Dalbury Lees Ashbourne Ashbourne Derbyshire DE6 5BE",
    "addr:postcode":"de6 5be",
    "addr:street":"Lees",
    "iso:country":"GB",
    "sg:address":"Ashcroft, Dalbury Lees Ashbourne",
    "sg:city":"Ashbourne",
    "sg:classifiers":[
        {
            "category":"Real Estate",
            "subcategory":"Architect",
            "type":"Services"
        }
    ],
    "sg:phone":"+44 1332 824840",
    "sg:postcode":"DE6 5BE",
    "sg:province":"Derbyshire",
    "wof:name":"Penn-smith & Weston",
    "wof:placetype":"venue"
},
  "geometry": {"coordinates":[-1.609056,52.905807],"type":"Point"}
}