{
  "type": "Feature",
  "properties": {
    "addr:full":"116b Bow Road London Greater London E3 3AA",
    "addr:housenumber":"116b",
    "addr:postcode":"e3 3aa",
    "addr:street":"Bow Road",
    "iso:country":"GB",
    "sg:address":"116b Bow Road",
    "sg:city":"London",
    "sg:classifiers":[
        {
            "category":"Retail",
            "subcategory":"Funeral Services",
            "type":"Services"
        }
    ],
    "sg:phone":"+44 20 8980 3034",
    "sg:postcode":"E3 3AA",
    "sg:province":"Greater London",
    "sg:tags":[
        "director"
    ],
    "sg:website":"http://www.dignity.co.uk",
    "wof:name":"C Selby & Son",
    "wof:placetype":"venue"
},
  "geometry": {"coordinates":[-0.0194300003,51.5279998779],"type":"Point"}
}