{
  "type": "Feature",
  "properties": {
    "iso:country":"GB",
    "sg:address":"56 Lingfield Avenue",
    "sg:city":"Sale",
    "sg:classifiers":[
        {
            "category":"Food & Beverages",
            "subcategory":"Supermarket",
            "type":"Retail Goods"
        }
    ],
    "sg:phone":"+44 161 973 6736",
    "sg:postcode":"M33 4QY",
    "sg:province":"Cheshire",
    "wof:name":"Manor Supermarket",
    "wof:placetype":"venue"
},
  "geometry": {"coordinates":[-2.3626220226,53.4121284485],"type":"Point"}
}