{
  "type": "Feature",
  "properties": {
    "addr:full":"69 High Street Knaresborough North Yorkshire HG5 0HB",
    "addr:housenumber":"69",
    "addr:postcode":"hg5 0hb",
    "addr:street":"High Street",
    "iso:country":"GB",
    "sg:address":"69 High Street",
    "sg:city":"Knaresborough",
    "sg:classifiers":[
        {
            "category":"Government",
            "subcategory":"Post Office",
            "type":"Public Place"
        }
    ],
    "sg:phone":"+44 1423 860414",
    "sg:postcode":"HG5 0HB",
    "sg:province":"North Yorkshire",
    "wof:name":"Knaresborough Post Office",
    "wof:placetype":"venue"
},
  "geometry": {"coordinates":[-1.469624,54.010208],"type":"Point"}
}