{
  "type": "Feature",
  "properties": {
    "addr:full":"26 Bagthorpe Road, East Rudham King's Lynn Norfolk PE31 8RA",
    "addr:housenumber":"26",
    "addr:postcode":"pe31 8ra",
    "addr:street":"Bagthorpe Road;Lynn",
    "iso:country":"GB",
    "sg:address":"26 Bagthorpe Road, East Rudham",
    "sg:city":"King's Lynn",
    "sg:classifiers":[
        {
            "category":"Professional",
            "subcategory":"Engineering",
            "type":"Services"
        }
    ],
    "sg:phone":"+44 1485 528269",
    "sg:postcode":"PE31 8RA",
    "sg:province":"Norfolk",
    "sg:tags":[
        "engineer"
    ],
    "wof:name":"Payne & Son Engineers",
    "wof:placetype":"venue"
},
  "geometry": {"coordinates":[0.71056,52.82299],"type":"Point"}
}