{
  "type": "Feature",
  "properties": {
    "iso:country":"GB",
    "sg:address":"Becontree Av",
    "sg:city":"Dagenham",
    "sg:classifiers":[
        {
            "category":"Place Of Worship",
            "type":"Public Place"
        }
    ],
    "sg:phone":"+44 20 8593 2782",
    "sg:postcode":"RM8 3JR",
    "sg:province":"Essex",
    "wof:name":"Becontree Avenue Baptist Church",
    "wof:placetype":"venue"
},
  "geometry": {"coordinates":[0.14281,51.559155],"type":"Point"}
}