{
  "type": "Feature",
  "properties": {
    "addr:full":"14 Weekin Works, Park Hill Rd Birmingham West Midlands B17 9HD",
    "addr:housenumber":"14",
    "addr:postcode":"b17 9hd",
    "addr:street":"Weekin Works Park Hill Rd",
    "iso:country":"GB",
    "sg:address":"14 Weekin Works, Park Hill Rd",
    "sg:city":"Birmingham",
    "sg:classifiers":[
        {
            "category":"Professional",
            "subcategory":"Advertising",
            "type":"Services"
        }
    ],
    "sg:phone":"+44 121 684 8485",
    "sg:postcode":"B17 9HD",
    "sg:province":"West Midlands",
    "wof:name":"Chameleon Advertising & Design Consultants",
    "wof:placetype":"venue"
},
  "geometry": {"coordinates":[-1.9086040258,52.4785957336],"type":"Point"}
}