{
  "type": "Feature",
  "properties": {
    "addr:full":"3 Kinsgway Hall, Bagshaw Rd, Dovercourt Harwich Essex CO12 3AB",
    "addr:housenumber":"3",
    "addr:postcode":"co12 3ab",
    "addr:street":"Kinsgway Hall Bagshaw Rd;Harwich",
    "iso:country":"GB",
    "sg:address":"3 Kinsgway Hall, Bagshaw Rd, Dovercourt",
    "sg:city":"Harwich",
    "sg:classifiers":[
        {
            "category":"Shopping",
            "subcategory":"Thrift Store",
            "type":"Retail Goods"
        }
    ],
    "sg:phone":"+44 1255 240959",
    "sg:postcode":"CO12 3AB",
    "sg:province":"Essex",
    "sg:tags":[
        "shop",
        "charity"
    ],
    "wof:name":"St. Helena Hospice Shops",
    "wof:placetype":"venue"
},
  "geometry": {"coordinates":[1.2811570168,51.9372673035],"type":"Point"}
}