{
  "type": "Feature",
  "properties": {
    "addr:full":"Eastlake, Lewdown Okehampton Devon EX20 4QS",
    "addr:postcode":"ex20 4qs",
    "addr:street":"Lewdown",
    "iso:country":"GB",
    "sg:address":"Eastlake, Lewdown",
    "sg:city":"Okehampton",
    "sg:classifiers":[
        {
            "category":"Farming",
            "subcategory":"Dairy Farm",
            "type":"Manufacturing & Wholesale Goods"
        }
    ],
    "sg:postcode":"EX20 4QS",
    "sg:province":"Devon",
    "wof:name":"S Baker & Son",
    "wof:placetype":"venue"
},
  "geometry": {"coordinates":[-4.1965141296,50.6587867737],"type":"Point"}
}