{
  "type": "Feature",
  "properties": {
    "iso:country":"GB",
    "sg:address":"11-13 West Colinade, Euston Station",
    "sg:city":"London",
    "sg:classifiers":[
        {
            "category":"Shopping",
            "subcategory":"Bicycles & Sporting Goods",
            "type":"Retail Goods"
        }
    ],
    "sg:postcode":"NW1 2DY",
    "sg:province":"Greater London",
    "sg:tags":[
        "equipment",
        "camping"
    ],
    "wof:name":"The Survival Shop",
    "wof:placetype":"venue"
},
  "geometry": {"coordinates":[-0.13328,51.52861],"type":"Point"}
}