{
  "type": "Feature",
  "properties": {
    "addr:full":"2 Ormond Avenue Richmond Greater London TW10 6TN",
    "addr:housenumber":"2",
    "addr:postcode":"tw10 6tn",
    "addr:street":"Ormond Avenue",
    "iso:country":"GB",
    "sg:address":"2 Ormond Avenue",
    "sg:city":"Richmond",
    "sg:classifiers":[
        {
            "category":"Communications",
            "type":"Services"
        }
    ],
    "sg:phone":"+44 20 7888 9792",
    "sg:postcode":"TW10 6TN",
    "sg:province":"Greater London",
    "sg:tags":[
        "data",
        "network"
    ],
    "wof:name":"Ageless Data Ltd.",
    "wof:placetype":"venue"
},
  "geometry": {"coordinates":[-0.304327,51.458767],"type":"Point"}
}