{
  "type": "Feature",
  "properties": {
    "addr:full":"Windsor House London Greater London SW1H 0NW",
    "addr:postcode":"sw1h 0nw",
    "iso:country":"GB",
    "sg:address":"Windsor House",
    "sg:city":"London",
    "sg:classifiers":[
        {
            "category":"Fast Food",
            "type":"Food & Drink"
        }
    ],
    "sg:postcode":"SW1H 0NW",
    "sg:province":"Greater London",
    "sg:tags":[
        "away",
        "take"
    ],
    "wof:name":"Dalgreave (Byrons) Ltd.",
    "wof:placetype":"venue"
},
  "geometry": {"coordinates":[-0.13517,51.497822],"type":"Point"}
}