{
  "type": "Feature",
  "properties": {
    "addr:full":"Osmaston House Leicester Leicestershire LE5 5JG",
    "addr:postcode":"le5 5jg",
    "iso:country":"GB",
    "sg:address":"Osmaston House",
    "sg:city":"Leicester",
    "sg:classifiers":[
        {
            "category":"Shopping",
            "subcategory":"Computers & Home Electronics",
            "type":"Retail Goods"
        }
    ],
    "sg:postcode":"LE5 5JG",
    "sg:province":"Leicestershire",
    "wof:name":"Advanced New Technologies Corp Ltd.",
    "wof:placetype":"venue"
},
  "geometry": {"coordinates":[-1.1053099632,52.6261787415],"type":"Point"}
}