{
  "type": "Feature",
  "properties": {
    "addr:full":"21 Lacey Grn Wilmslow Cheshire SK9 4BA",
    "addr:housenumber":"21",
    "addr:postcode":"sk9 4ba",
    "addr:street":"Lacey Grn",
    "iso:country":"GB",
    "sg:address":"21 Lacey Grn",
    "sg:city":"Wilmslow",
    "sg:classifiers":[
        {
            "category":"Retail",
            "subcategory":"Driving School",
            "type":"Services"
        }
    ],
    "sg:postcode":"SK9 4BA",
    "sg:province":"Cheshire",
    "wof:name":"Phillip's Driving School",
    "wof:placetype":"venue"
},
  "geometry": {"coordinates":[-2.23019,53.334427],"type":"Point"}
}