{
  "type": "Feature",
  "properties": {
    "addr:full":"180 Mayals Road, Mayals Swansea Swansea SA3 5HF",
    "addr:housenumber":"180",
    "addr:postcode":"sa3 5hf",
    "addr:street":"Mayals Road",
    "iso:country":"GB",
    "sg:address":"180 Mayals Road, Mayals",
    "sg:city":"Swansea",
    "sg:classifiers":[
        {
            "category":"Building & Trades",
            "subcategory":"Construction",
            "type":"Services"
        }
    ],
    "sg:postcode":"SA3 5HF",
    "sg:province":"Swansea",
    "sg:tags":[
        "glazier",
        "decorator",
        "painter"
    ],
    "wof:name":"David H Bennett",
    "wof:placetype":"venue"
},
  "geometry": {"coordinates":[-4.0138921738,51.5919075012],"type":"Point"}
}