{
  "type": "Feature",
  "properties": {
    "iso:country":"GB",
    "sg:address":"18-20 Bevan Road, Lovedean",
    "sg:city":"Waterlooville",
    "sg:classifiers":[
        {
            "category":"Social Services",
            "subcategory":"Retirement Home",
            "type":"Services"
        }
    ],
    "sg:phone":"+44 23 9259 7388",
    "sg:postcode":"PO8 9QH",
    "sg:province":"Hampshire",
    "sg:tags":[
        "rest"
    ],
    "wof:name":"Bayith Rest Home",
    "wof:placetype":"venue"
},
  "geometry": {"coordinates":[-1.019253,50.904861],"type":"Point"}
}