{
  "type": "Feature",
  "properties": {
    "addr:full":"44 Soulis Street Kilmarnock East Ayrshire KA3 1AP",
    "addr:housenumber":"44",
    "addr:postcode":"ka3 1ap",
    "addr:street":"Soulis Street",
    "iso:country":"GB",
    "sg:address":"44 Soulis Street",
    "sg:city":"Kilmarnock",
    "sg:classifiers":[
        {
            "category":"Home & Garden",
            "subcategory":"Home Furnishings",
            "type":"Retail Goods"
        }
    ],
    "sg:phone":"+44 1563 520230",
    "sg:postcode":"KA3 1AP",
    "sg:province":"East Ayrshire",
    "sg:tags":[
        "blind",
        "curtain",
        "fitting"
    ],
    "wof:name":"The Curtain Workshop",
    "wof:placetype":"venue"
},
  "geometry": {"coordinates":[-4.49404,55.612453],"type":"Point"}
}