{
  "type": "Feature",
  "properties": {
    "iso:country":"GB",
    "sg:address":"Pitts Farm, Woodbank Lane, Woodbank",
    "sg:city":"Chester",
    "sg:classifiers":[
        {
            "category":"Farming",
            "subcategory":"Livestock Farm",
            "type":"Manufacturing & Wholesale Goods"
        }
    ],
    "sg:phone":"+44 1244 881040",
    "sg:postcode":"CH1 6EZ",
    "sg:province":"Cheshire",
    "sg:tags":[
        "others"
    ],
    "wof:name":"R B & J Jones & Sons",
    "wof:placetype":"venue"
},
  "geometry": {"coordinates":[-2.967279911,53.2501945496],"type":"Point"}
}