{
  "type": "Feature",
  "properties": {
    "addr:full":"24 Warren Avenue, Stapleford Nottingham Nottinghamshire NG9 8EY",
    "addr:housenumber":"24",
    "addr:postcode":"ng9 8ey",
    "addr:street":"Warren Avenue",
    "iso:country":"GB",
    "sg:address":"24 Warren Avenue, Stapleford",
    "sg:city":"Nottingham",
    "sg:classifiers":[
        {
            "category":"Professional",
            "type":"Services"
        }
    ],
    "sg:postcode":"NG9 8EY",
    "sg:province":"Nottinghamshire",
    "sg:tags":[
        "services",
        "belt",
        "conveyor"
    ],
    "wof:name":"Phoenix Conveyor Products",
    "wof:placetype":"venue"
},
  "geometry": {"coordinates":[-1.2782919407,52.9304847717],"type":"Point"}
}