{
  "type": "Feature",
  "properties": {
    "addr:full":"52 St Pauls Square Birmingham West Midlands B3 1QS",
    "addr:housenumber":"52",
    "addr:postcode":"b3 1qs",
    "addr:street":"St Pauls Square",
    "iso:country":"GB",
    "sg:address":"52 St Pauls Square",
    "sg:city":"Birmingham",
    "sg:classifiers":[
        {
            "category":"Building & Trades",
            "subcategory":"Construction",
            "type":"Services"
        }
    ],
    "sg:phone":"+44 121 212 0223",
    "sg:postcode":"B3 1QS",
    "sg:province":"West Midlands",
    "sg:tags":[
        "contractor"
    ],
    "wof:name":"Z V I Construction (U K) Ltd.",
    "wof:placetype":"venue"
},
  "geometry": {"coordinates":[-1.906266,52.484528],"type":"Point"}
}