{
  "type": "Feature",
  "properties": {
    "iso:country":"GB",
    "sg:address":"Unit 1/3, Metro Business Centre",
    "sg:city":"London",
    "sg:classifiers":[
        {
            "category":"Manufacturing",
            "subcategory":"Tools & Machinery",
            "type":"Manufacturing & Wholesale Goods"
        }
    ],
    "sg:phone":"+44 20 8778 1420",
    "sg:postcode":"SE26 5BW",
    "sg:province":"Greater London",
    "sg:tags":[
        "stone",
        "cutting"
    ],
    "wof:name":"Laserdie Ltd.",
    "wof:placetype":"venue"
},
  "geometry": {"coordinates":[-0.035131,51.42157],"type":"Point"}
}