{
  "type": "Feature",
  "properties": {
    "iso:country":"GB",
    "sg:address":"48 Kempock Street",
    "sg:city":"Gourock",
    "sg:classifiers":[
        {
            "category":"Professional",
            "subcategory":"Engineering",
            "type":"Services"
        },
        {
            "category":"Shopping",
            "subcategory":"Computers & Home Electronics",
            "type":"Retail Goods"
        }
    ],
    "sg:phone":"+44 1475 632174",
    "sg:postcode":"PA19 1ND",
    "sg:province":"Inverclyde",
    "sg:tags":[
        "television",
        "engineer",
        "electrical",
        "sale",
        "contractor"
    ],
    "sg:website":"http://www.gourockweb.com",
    "wof:name":"J & J McMorland Ltd.",
    "wof:placetype":"venue"
},
  "geometry": {"coordinates":[-4.820144,55.96196],"type":"Point"}
}