{
  "type": "Feature",
  "properties": {
    "addr:full":"68 Chorley Old Road Bolton Lancashire BL1 3AE",
    "addr:housenumber":"68",
    "addr:postcode":"bl1 3ae",
    "addr:street":"Chorley Old Road",
    "iso:country":"GB",
    "sg:address":"68 Chorley Old Road",
    "sg:city":"Bolton",
    "sg:classifiers":[
        {
            "category":"Wholesale",
            "subcategory":"Electrical",
            "type":"Manufacturing & Wholesale Goods"
        },
        {
            "category":"Shopping",
            "subcategory":"Computers & Home Electronics",
            "type":"Retail Goods"
        }
    ],
    "sg:phone":"+44 1204 362959",
    "sg:postcode":"BL1 3AE",
    "sg:province":"Lancashire",
    "sg:tags":[
        "wholesaler"
    ],
    "sg:website":"http://www.electricalsupplies.com",
    "wof:name":"Electrical Supplies Bolton Ltd",
    "wof:placetype":"venue"
},
  "geometry": {"coordinates":[-2.444234,53.583725],"type":"Point"}
}