{
  "type": "Feature",
  "properties": {
    "iso:country":"GB",
    "sg:address":"Murdock House, Murdock Road",
    "sg:city":"Bedford",
    "sg:classifiers":[
        {
            "category":"Building & Trades",
            "subcategory":"Construction",
            "type":"Services"
        }
    ],
    "sg:phone":"+44 1234 328161",
    "sg:postcode":"MK41 7PD",
    "sg:province":"Bedfordshire",
    "sg:tags":[
        "glazier"
    ],
    "wof:name":"Mduk Bedrooms & Kitchens Ltd.",
    "wof:placetype":"venue"
},
  "geometry": {"coordinates":[-0.473625,52.154575],"type":"Point"}
}