{
  "type": "Feature",
  "properties": {
    "addr:full":"Hurstwood House Chillies Lane, High Hurstwood Uckfield East Sussex TN22 4AD",
    "addr:postcode":"tn22 4ad",
    "addr:street":"Chillies Lane",
    "iso:country":"GB",
    "sg:address":"Hurstwood House Chillies Lane, High Hurstwood",
    "sg:city":"Uckfield",
    "sg:classifiers":[
        {
            "category":"Social Services",
            "subcategory":"Retirement Home",
            "type":"Services"
        }
    ],
    "sg:phone":"+44 1825 732453",
    "sg:postcode":"TN22 4AD",
    "sg:province":"East Sussex",
    "sg:tags":[
        "residential",
        "care"
    ],
    "wof:name":"The Care Estates Ltd.",
    "wof:placetype":"venue"
},
  "geometry": {"coordinates":[0.133001,51.029121],"type":"Point"}
}