{
  "type": "Feature",
  "properties": {
    "iso:country":"GB",
    "sg:address":"23 Rawson Market",
    "sg:city":"Bradford",
    "sg:classifiers":[
        {
            "category":"Food & Beverages",
            "subcategory":"Meat & Fish",
            "type":"Retail Goods"
        }
    ],
    "sg:phone":"+44 1274 728481",
    "sg:postcode":"BD1 3QF",
    "sg:province":"West Yorkshire",
    "sg:tags":[
        "butcher"
    ],
    "wof:name":"J Holland & Sons",
    "wof:placetype":"venue"
},
  "geometry": {"coordinates":[-1.755951,53.795891],"type":"Point"}
}