{
  "type": "Feature",
  "properties": {
    "addr:full":"19 George Street Bicester Oxfordshire OX26 2EB",
    "addr:housenumber":"19",
    "addr:postcode":"ox26 2eb",
    "addr:street":"George Street",
    "iso:country":"GB",
    "sg:address":"19 George Street",
    "sg:city":"Bicester",
    "sg:classifiers":[
        {
            "category":"Professional",
            "subcategory":"Art Services",
            "type":"Services"
        },
        {
            "category":"Building & Trades",
            "subcategory":"Construction",
            "type":"Services"
        }
    ],
    "sg:phone":"+44 1869 253830",
    "sg:postcode":"OX26 2EB",
    "sg:province":"Oxfordshire",
    "sg:tags":[
        "decorator",
        "painter"
    ],
    "wof:name":"David John Kavanagh",
    "wof:placetype":"venue"
},
  "geometry": {"coordinates":[-1.1627540588,51.9032058716],"type":"Point"}
}