{
  "type": "Feature",
  "properties": {
    "iso:country":"GB",
    "sg:address":"252a London Road",
    "sg:city":"Waterlooville",
    "sg:classifiers":[
        {
            "category":"Organizations",
            "subcategory":"Non-profit Organization",
            "type":"Services"
        }
    ],
    "sg:phone":"+44 23 9226 9961",
    "sg:postcode":"PO7 7HG",
    "sg:province":"Hampshire",
    "sg:tags":[
        "organisation",
        "voluntary",
        "charity"
    ],
    "wof:name":"Anthony B King",
    "wof:placetype":"venue"
},
  "geometry": {"coordinates":[-1.033037,50.878426],"type":"Point"}
}