{
  "type": "Feature",
  "properties": {
    "iso:country":"GB",
    "sg:address":"1 Breckside Close",
    "sg:city":"Poulton-le-fylde",
    "sg:classifiers":[
        {
            "category":"Insurance",
            "subcategory":"Insurance Agent",
            "type":"Services"
        }
    ],
    "sg:phone":"+44 1253 885595",
    "sg:postcode":"FY6 7AJ",
    "sg:province":"Lancashire",
    "sg:tags":[
        "broker"
    ],
    "wof:name":"Geoffrey W Rose",
    "wof:placetype":"venue"
},
  "geometry": {"coordinates":[-2.982241,53.854057],"type":"Point"}
}