{
  "type": "Feature",
  "properties": {
    "addr:full":"1 The Broadway Swanley Kent BR8 8JH",
    "addr:housenumber":"1",
    "addr:postcode":"br8 8jh",
    "addr:street":"The Broadway",
    "iso:country":"GB",
    "sg:address":"1 The Broadway",
    "sg:city":"Swanley",
    "sg:classifiers":[
        {
            "category":"Food & Beverages",
            "subcategory":"Meat & Fish",
            "type":"Retail Goods"
        }
    ],
    "sg:postcode":"BR8 8JH",
    "sg:province":"Kent",
    "sg:tags":[
        "butcher"
    ],
    "wof:name":"H Willard",
    "wof:placetype":"venue"
},
  "geometry": {"coordinates":[0.161135,51.383686],"type":"Point"}
}