{
  "type": "Feature",
  "properties": {
    "iso:country":"GB",
    "sg:address":"17 Broad Street",
    "sg:city":"Bromyard",
    "sg:classifiers":[
        {
            "category":"Health Services",
            "subcategory":"Podiatrist",
            "type":"Services"
        }
    ],
    "sg:phone":"+44 1885 488608",
    "sg:postcode":"HR7 4BT",
    "sg:province":"Herefordshire",
    "sg:tags":[
        "podiatrists",
        "chiropodist"
    ],
    "wof:name":"J Potts",
    "wof:placetype":"venue"
},
  "geometry": {"coordinates":[-2.5059330463,52.1887931824],"type":"Point"}
}