{
  "type": "Feature",
  "properties": {
    "iso:country":"GB",
    "sg:address":"34 Pincheon Street",
    "sg:city":"Wakefield",
    "sg:classifiers":[
        {
            "category":"Bus Charters",
            "type":"Transportation"
        }
    ],
    "sg:phone":"+44 1924 374404",
    "sg:postcode":"WF1 4DT",
    "sg:province":"West Yorkshire",
    "sg:tags":[
        "coach"
    ],
    "wof:name":"Illingworth Coaches",
    "wof:placetype":"venue"
},
  "geometry": {"coordinates":[-1.491863966,53.6832542419],"type":"Point"}
}