{
  "type": "Feature",
  "properties": {
    "iso:country":"GB",
    "sg:address":"102 Lydney Indust Estate, Harbour Road",
    "sg:city":"Lydney",
    "sg:classifiers":[
        {
            "category":"Professional",
            "subcategory":"Engineering",
            "type":"Services"
        }
    ],
    "sg:phone":"+44 1594 843255",
    "sg:postcode":"GL15 4EN",
    "sg:province":"Gloucestershire",
    "wof:name":"C Manns",
    "wof:placetype":"venue"
},
  "geometry": {"coordinates":[-2.517624,51.710091],"type":"Point"}
}