{
  "type": "Feature",
  "properties": {
    "addr:full":"23 Charlton Rise Ludlow Herefordshire SY8 1ND",
    "addr:housenumber":"23",
    "addr:postcode":"sy8 1nd",
    "addr:street":"Charlton Rise",
    "iso:country":"GB",
    "sg:address":"23 Charlton Rise",
    "sg:city":"Ludlow",
    "sg:classifiers":[
        {
            "category":"Real Estate",
            "subcategory":"Architect",
            "type":"Services"
        }
    ],
    "sg:phone":"+44 1584 874717",
    "sg:postcode":"SY8 1ND",
    "sg:province":"Herefordshire",
    "sg:tags":[
        "architectural"
    ],
    "wof:name":"Davies David R (Consulting & Architectural Enginee",
    "wof:placetype":"venue"
},
  "geometry": {"coordinates":[-2.704444,52.367577],"type":"Point"}
}