{
  "type": "Feature",
  "properties": {
    "addr:full":"12a Heybridge Way London Greater London E10 7NQ",
    "addr:housenumber":"12a",
    "addr:postcode":"e10 7nq",
    "addr:street":"Heybridge Way",
    "iso:country":"GB",
    "sg:address":"12a Heybridge Way",
    "sg:city":"London",
    "sg:classifiers":[
        {
            "category":"Shopping",
            "subcategory":"Crafts & Fabrics",
            "type":"Retail Goods"
        }
    ],
    "sg:phone":"+44 20 8558 7273",
    "sg:postcode":"E10 7NQ",
    "sg:province":"Greater London",
    "sg:tags":[
        "machine",
        "sewing",
        "knitting"
    ],
    "wof:name":"Burkett Automation",
    "wof:placetype":"venue"
},
  "geometry": {"coordinates":[-0.031149,51.569256],"type":"Point"}
}