{
  "type": "Feature",
  "properties": {
    "iso:country":"GB",
    "sg:address":"10 Forfield Place",
    "sg:city":"Leamington Spa",
    "sg:classifiers":[
        {
            "category":"Building & Trades",
            "subcategory":"Construction",
            "type":"Services"
        }
    ],
    "sg:phone":"+44 1926 339834",
    "sg:postcode":"CV31 1HG",
    "sg:province":"Warwickshire",
    "sg:tags":[
        "roofing"
    ],
    "wof:name":"J P Marshall Roofing Co",
    "wof:placetype":"venue"
},
  "geometry": {"coordinates":[-1.529061,52.284393],"type":"Point"}
}