{
  "type": "Feature",
  "properties": {
    "addr:full":"42 High St Uttoxeter Derbyshire ST14 7HT",
    "addr:housenumber":"42",
    "addr:postcode":"st14 7ht",
    "addr:street":"High St",
    "iso:country":"GB",
    "sg:address":"42 High St",
    "sg:city":"Uttoxeter",
    "sg:classifiers":[
        {
            "category":"Sports & Exercise",
            "subcategory":"Sports Center",
            "type":"Entertainment"
        }
    ],
    "sg:postcode":"ST14 7HT",
    "sg:province":"Derbyshire",
    "sg:tags":[
        "shop",
        "good"
    ],
    "wof:name":"Sportsland Ltd",
    "wof:placetype":"venue"
},
  "geometry": {"coordinates":[-1.865452,52.899708],"type":"Point"}
}