{
  "type": "Feature",
  "properties": {
    "addr:full":"Blurton Grange Farm, Cocknage Stoke On Trent Staffordshire ST3 4AN",
    "addr:postcode":"st3 4an",
    "iso:country":"GB",
    "sg:address":"Blurton Grange Farm, Cocknage",
    "sg:city":"Stoke On Trent",
    "sg:classifiers":[
        {
            "category":"Farming",
            "subcategory":"Dairy Farm",
            "type":"Manufacturing & Wholesale Goods"
        }
    ],
    "sg:phone":"+44 1782 312152",
    "sg:postcode":"ST3 4AN",
    "sg:province":"Staffordshire",
    "wof:name":"John Anthony Hooley",
    "wof:placetype":"venue"
},
  "geometry": {"coordinates":[-2.14304,52.972519],"type":"Point"}
}