{
  "type": "Feature",
  "properties": {
    "addr:full":"Ross Rd Gloucester Gloucestershire GL19 3EG",
    "addr:postcode":"gl19 3eg",
    "addr:street":"Ross Rd",
    "iso:country":"GB",
    "sg:address":"Ross Rd",
    "sg:city":"Gloucester",
    "sg:classifiers":[
        {
            "category":"Retail",
            "subcategory":"Auto Repair",
            "type":"Services"
        }
    ],
    "sg:phone":"+44 1452 750726",
    "sg:postcode":"GL19 3EG",
    "sg:province":"Gloucestershire",
    "sg:tags":[
        "modification",
        "garage"
    ],
    "wof:name":"St Michaels Garages Ltd",
    "wof:placetype":"venue"
},
  "geometry": {"coordinates":[-2.2496240139,51.8638114929],"type":"Point"}
}