{
  "type": "Feature",
  "properties": {
    "addr:full":"26 Grosvenor Street London Greater London W1K 4DB",
    "addr:housenumber":"26",
    "addr:postcode":"w1k 4db",
    "addr:street":"Grosvenor Street",
    "iso:country":"GB",
    "sg:address":"26 Grosvenor Street",
    "sg:city":"London",
    "sg:classifiers":[
        {
            "category":"Professional",
            "subcategory":"Lawyer & Legal Services",
            "type":"Services"
        }
    ],
    "sg:phone":"+44 20 7629 3304",
    "sg:postcode":"W1K 4DB",
    "sg:province":"Greater London",
    "sg:tags":[
        "solicitor"
    ],
    "wof:name":"Gentle Jayes",
    "wof:placetype":"venue"
},
  "geometry": {"coordinates":[-0.147809,51.5116],"type":"Point"}
}