{
  "type": "Feature",
  "properties": {
    "addr:full":"49 Kilburn High Road London Greater London NW6 5SB",
    "addr:housenumber":"49",
    "addr:postcode":"nw6 5sb",
    "addr:street":"Kilburn High Road",
    "iso:country":"GB",
    "sg:address":"49 Kilburn High Road",
    "sg:city":"London",
    "sg:classifiers":[
        {
            "category":"Wholesale",
            "subcategory":"Meat",
            "type":"Manufacturing & Wholesale Goods"
        }
    ],
    "sg:postcode":"NW6 5SB",
    "sg:province":"Greater London",
    "sg:tags":[
        "-"
    ],
    "wof:name":"A1 Fresh Meats",
    "wof:placetype":"venue"
},
  "geometry": {"coordinates":[-0.191903,51.536469],"type":"Point"}
}