{
  "type": "Feature",
  "properties": {
    "addr:full":"Dale Street, New Marske Redcar North Yorkshire TS11 8EJ",
    "addr:postcode":"ts11 8ej",
    "addr:street":"Dale Street",
    "iso:country":"GB",
    "sg:address":"Dale Street, New Marske",
    "sg:city":"Redcar",
    "sg:classifiers":[
        {
            "category":"Government",
            "subcategory":"Post Office",
            "type":"Public Place"
        }
    ],
    "sg:postcode":"TS11 8EJ",
    "sg:province":"North Yorkshire",
    "wof:name":"New Marske Post Office",
    "wof:placetype":"venue"
},
  "geometry": {"coordinates":[-1.0428980589,54.5808067322],"type":"Point"}
}