{
  "type": "Feature",
  "properties": {
    "iso:country":"GB",
    "sg:address":"21 Lower Street",
    "sg:city":"Dartmouth",
    "sg:classifiers":[
        {
            "category":"Health Services",
            "subcategory":"Optometrist",
            "type":"Services"
        }
    ],
    "sg:phone":"+44 1803 832664",
    "sg:postcode":"TQ6 9AN",
    "sg:province":"Devon",
    "sg:tags":[
        "optician"
    ],
    "wof:name":"Dart Optical",
    "wof:placetype":"venue"
},
  "geometry": {"coordinates":[-3.5779259205,50.348903656],"type":"Point"}
}