{
  "type": "Feature",
  "properties": {
    "addr:full":"306b Fulham Road London Greater London SW10 9ER",
    "addr:housenumber":"306b",
    "addr:postcode":"sw10 9er",
    "addr:street":"Fulham Road",
    "iso:country":"GB",
    "sg:address":"306b Fulham Road",
    "sg:city":"London",
    "sg:classifiers":[
        {
            "category":"Restaurant",
            "type":"Food & Drink"
        }
    ],
    "sg:phone":"+44 20 7565 8183",
    "sg:postcode":"SW10 9ER",
    "sg:province":"Greater London",
    "sg:tags":[
        "indian",
        "-"
    ],
    "wof:name":"Saffron Indian Restaurant",
    "wof:placetype":"venue"
},
  "geometry": {"coordinates":[-0.1858049929,51.483291626],"type":"Point"}
}