{
  "type": "Feature",
  "properties": {
    "addr:full":"Unit 11 Rassau Industrial Estate, Rassau Ebbw Vale Blaenau Gwent NP23 5SD",
    "addr:housenumber":"unit 11",
    "addr:postcode":"np23 5sd",
    "addr:street":"Rassau Industrial Estate",
    "iso:country":"GB",
    "sg:address":"Unit 11 Rassau Industrial Estate, Rassau",
    "sg:city":"Ebbw Vale",
    "sg:classifiers":[
        {
            "category":"Shopping",
            "subcategory":"Computers & Home Electronics",
            "type":"Retail Goods"
        }
    ],
    "sg:phone":"+44 1495 307341",
    "sg:postcode":"NP23 5SD",
    "sg:province":"Blaenau Gwent",
    "sg:tags":[
        "tape",
        "video"
    ],
    "wof:name":"Archmagic Ltd.",
    "wof:placetype":"venue"
},
  "geometry": {"coordinates":[-3.2255589962,51.8072357178],"type":"Point"}
}