{
  "type": "Feature",
  "properties": {
    "iso:country":"GB",
    "sg:address":"Crayford Mill",
    "sg:city":"Dartford",
    "sg:classifiers":[
        {
            "category":"Building & Trades",
            "subcategory":"Construction",
            "type":"Services"
        },
        {
            "category":"Building & Trades",
            "subcategory":"Pest Control",
            "type":"Services"
        }
    ],
    "sg:phone":"+44 1322 555050",
    "sg:postcode":"DA1 4QH",
    "sg:province":"Kent",
    "sg:tags":[
        "equipment",
        "hire",
        "crane",
        "sales"
    ],
    "wof:name":"Bronzeshield Lifting Ltd.",
    "wof:placetype":"venue"
},
  "geometry": {"coordinates":[0.177534,51.452374],"type":"Point"}
}