{
  "type": "Feature",
  "properties": {
    "addr:full":"5 Saracen Street Bath Bath and North East Somerset BA1 5BR",
    "addr:housenumber":"5",
    "addr:postcode":"ba1 5br",
    "addr:street":"Saracen Street",
    "iso:country":"GB",
    "sg:address":"5 Saracen Street",
    "sg:city":"Bath",
    "sg:classifiers":[
        {
            "category":"Shopping",
            "subcategory":"Gifts & Souvenirs",
            "type":"Retail Goods"
        },
        {
            "category":"Retail",
            "subcategory":"Event Space",
            "type":"Services"
        }
    ],
    "sg:postcode":"BA1 5BR",
    "sg:province":"Bath and North East Somerset",
    "sg:tags":[
        "shop",
        "product",
        "electrical",
        "sales"
    ],
    "wof:name":"ONCE A TREE LTD",
    "wof:placetype":"venue"
},
  "geometry": {"coordinates":[-2.360012,51.384605],"type":"Point"}
}