{
  "type": "Feature",
  "properties": {
    "iso:country":"GB",
    "sg:address":"Seaton Mill, Seaton",
    "sg:city":"Oakham",
    "sg:classifiers":[
        {
            "category":"Professional",
            "subcategory":"Art Services",
            "type":"Services"
        }
    ],
    "sg:postcode":"LE15 9HX",
    "sg:province":"Leicestershire",
    "sg:tags":[
        "graphic",
        "designer"
    ],
    "wof:name":"Oakley,Paul,",
    "wof:placetype":"venue"
},
  "geometry": {"coordinates":[-0.668824,52.57523],"type":"Point"}
}