{
  "type": "Feature",
  "properties": {
    "addr:full":"7 Stanley Street Southsea Hampshire PO5 2DS",
    "addr:housenumber":"7",
    "addr:postcode":"po5 2ds",
    "addr:street":"Stanley Street",
    "iso:country":"GB",
    "sg:address":"7 Stanley Street",
    "sg:city":"Southsea",
    "sg:classifiers":[
        {
            "category":"Bars & Pubs",
            "subcategory":"Wine Bar",
            "type":"Food & Drink"
        }
    ],
    "sg:postcode":"PO5 2DS",
    "sg:province":"Hampshire",
    "wof:name":"Steinbecks Wine Bar",
    "wof:placetype":"venue"
},
  "geometry": {"coordinates":[-1.0881149769,50.7854537964],"type":"Point"}
}