{
  "type": "Feature",
  "properties": {
    "iso:country":"GB",
    "sg:address":"3 Eastry Pk, Eastry",
    "sg:city":"Sandwich",
    "sg:classifiers":[
        {
            "category":"Real Estate",
            "subcategory":"Developer",
            "type":"Services"
        }
    ],
    "sg:postcode":"CT13 0JL",
    "sg:province":"Kent",
    "sg:tags":[
        "property"
    ],
    "wof:name":"Jerrygreen & Co",
    "wof:placetype":"venue"
},
  "geometry": {"coordinates":[1.3092050552,51.2485542297],"type":"Point"}
}