{
  "type": "Feature",
  "properties": {
    "addr:full":"16 Northfields Prospect Business, Centre London Greater London SW18 1PE",
    "addr:housenumber":"16",
    "addr:postcode":"sw18 1pe",
    "addr:street":"Northfields",
    "iso:country":"GB",
    "sg:address":"16 Northfields Prospect Business, Centre",
    "sg:city":"London",
    "sg:classifiers":[
        {
            "category":"Professional",
            "subcategory":"Art Services",
            "type":"Services"
        }
    ],
    "sg:phone":"+44 20 8870 1045",
    "sg:postcode":"SW18 1PE",
    "sg:province":"Greater London",
    "sg:tags":[
        "photographer"
    ],
    "wof:name":"Gold & Goose Photography",
    "wof:placetype":"venue"
},
  "geometry": {"coordinates":[-0.200492993,51.4613952637],"type":"Point"}
}