{
  "type": "Feature",
  "properties": {
    "iso:country":"GB",
    "sg:address":"Dittons Road",
    "sg:city":"Polegate",
    "sg:classifiers":[
        {
            "category":"Building & Trades",
            "subcategory":"Construction",
            "type":"Services"
        }
    ],
    "sg:postcode":"BN26 6HX",
    "sg:province":"East Sussex",
    "sg:tags":[
        "builder"
    ],
    "wof:name":"West Ham Building Services",
    "wof:placetype":"venue"
},
  "geometry": {"coordinates":[0.26488,50.820961],"type":"Point"}
}