{
  "type": "Feature",
  "properties": {
    "addr:full":"George St Johnstone Renfrewshire PA5 8SL",
    "addr:postcode":"pa5 8sl",
    "addr:street":"George",
    "iso:country":"GB",
    "sg:address":"George St",
    "sg:city":"Johnstone",
    "sg:classifiers":[
        {
            "category":"Military Area",
            "subcategory":"Air Force Base",
            "type":"Public Place"
        }
    ],
    "sg:phone":"+44 1505 325222",
    "sg:postcode":"PA5 8SL",
    "sg:province":"Renfrewshire",
    "sg:tags":[
        "taxi",
        "hire",
        "private"
    ],
    "wof:name":"J H K Radio Taxis",
    "wof:placetype":"venue"
},
  "geometry": {"coordinates":[-4.5083441734,55.8361091614],"type":"Point"}
}