{
  "type": "Feature",
  "properties": {
    "iso:country":"GB",
    "sg:address":"119 Gregson Lane, Hoghton",
    "sg:city":"Preston",
    "sg:classifiers":[
        {
            "category":"Building & Trades",
            "subcategory":"Electrical",
            "type":"Services"
        }
    ],
    "sg:phone":"+44 1772 313799",
    "sg:postcode":"PR5 0LB",
    "sg:province":"Lancashire",
    "sg:tags":[
        "lighting"
    ],
    "wof:name":"Gregory's Ltd.",
    "wof:placetype":"venue"
},
  "geometry": {"coordinates":[-2.629928,53.737022],"type":"Point"}
}