{
  "type": "Feature",
  "properties": {
    "iso:country":"GB",
    "sg:address":"59 West End",
    "sg:city":"Redruth",
    "sg:classifiers":[
        {
            "category":"Professional",
            "subcategory":"Accounting & Tax Preparation",
            "type":"Services"
        }
    ],
    "sg:phone":"+44 1209 215063",
    "sg:postcode":"TR15 2SQ",
    "sg:province":"Cornwall",
    "sg:tags":[
        "accountant"
    ],
    "wof:name":"Paul Harris & Co",
    "wof:placetype":"venue"
},
  "geometry": {"coordinates":[-5.232036,50.232327],"type":"Point"}
}