{
  "type": "Feature",
  "properties": {
    "iso:country":"GB",
    "sg:address":"Potters Yard, Severn Road",
    "sg:city":"Welshpool",
    "sg:classifiers":[
        {
            "category":"Autos & Motor Vehicles",
            "subcategory":"Auto Supplies",
            "type":"Retail Goods"
        }
    ],
    "sg:phone":"+44 1938 554523",
    "sg:postcode":"SY21 7YE",
    "sg:province":"Shropshire",
    "sg:tags":[
        "tyre"
    ],
    "wof:name":"G F & J E Potter Garages Ltd.",
    "wof:placetype":"venue"
},
  "geometry": {"coordinates":[-3.145203,52.66119],"type":"Point"}
}