{
  "type": "Feature",
  "properties": {
    "iso:country":"GB",
    "sg:address":"19a London Road",
    "sg:city":"Southampton",
    "sg:classifiers":[
        {
            "category":"Real Estate",
            "subcategory":"Real Estate Operator",
            "type":"Services"
        },
        {
            "category":"Building & Trades",
            "subcategory":"Plumbing",
            "type":"Services"
        }
    ],
    "sg:phone":"+44 23 8036 6555",
    "sg:postcode":"SO15 2AE",
    "sg:province":"Hampshire",
    "sg:tags":[
        "letting",
        "heating",
        "agent"
    ],
    "wof:name":"Tenant Link",
    "wof:placetype":"venue"
},
  "geometry": {"coordinates":[-1.4047989845,50.9111633301],"type":"Point"}
}