{
  "type": "Feature",
  "properties": {
    "addr:full":"Nutfield House, Eyre Street Stanley Durham DH9 7AF",
    "addr:postcode":"dh9 7af",
    "addr:street":"Eyre Street",
    "iso:country":"GB",
    "sg:address":"Nutfield House, Eyre Street",
    "sg:city":"Stanley",
    "sg:classifiers":[
        {
            "category":"Food & Beverages",
            "subcategory":"Candy",
            "type":"Retail Goods"
        }
    ],
    "sg:phone":"+44 1207 299290",
    "sg:postcode":"DH9 7AF",
    "sg:province":"Durham",
    "sg:tags":[
        "confectioner"
    ],
    "wof:name":"Daisy Galore",
    "wof:placetype":"venue"
},
  "geometry": {"coordinates":[-1.7058639526,54.8627357483],"type":"Point"}
}