{
  "type": "Feature",
  "properties": {
    "addr:full":"14 The Oaklands Rugeley Staffordshire WS15 2SD",
    "addr:housenumber":"14",
    "addr:postcode":"ws15 2sd",
    "addr:street":"The",
    "iso:country":"GB",
    "sg:address":"14 The Oaklands",
    "sg:city":"Rugeley",
    "sg:classifiers":[
        {
            "category":"Retail",
            "subcategory":"Driving School",
            "type":"Services"
        }
    ],
    "sg:phone":"+44 1889 583683",
    "sg:postcode":"WS15 2SD",
    "sg:province":"Staffordshire",
    "wof:name":"Courtney Motoring School",
    "wof:placetype":"venue"
},
  "geometry": {"coordinates":[-1.9555120468,52.76121521],"type":"Point"}
}