{
  "type": "Feature",
  "properties": {
    "iso:country":"GB",
    "sg:address":"Church Hill Cottage, Church Hill",
    "sg:city":"Ashford",
    "sg:classifiers":[
        {
            "category":"Home & Garden",
            "subcategory":"Garden Supply",
            "type":"Retail Goods"
        }
    ],
    "sg:phone":"+44 1233 712522",
    "sg:postcode":"TN27 0BU",
    "sg:province":"Kent",
    "sg:tags":[
        "nursery",
        "centre"
    ],
    "wof:name":"Church Hill Cottage Gardens",
    "wof:placetype":"venue"
},
  "geometry": {"coordinates":[0.7534819841,51.2107620239],"type":"Point"}
}