{
  "type": "Feature",
  "properties": {
    "addr:full":"191 Hagley Road, Oldswinford Stourbridge Staffordshire DY8 2JJ",
    "addr:housenumber":"191",
    "addr:postcode":"dy8 2jj",
    "addr:street":"Hagley Road",
    "iso:country":"GB",
    "sg:address":"191 Hagley Road, Oldswinford",
    "sg:city":"Stourbridge",
    "sg:classifiers":[
        {
            "category":"Building & Trades",
            "subcategory":"Construction",
            "type":"Services"
        }
    ],
    "sg:phone":"+44 1384 396719",
    "sg:postcode":"DY8 2JJ",
    "sg:province":"Staffordshire",
    "sg:tags":[
        "heating",
        "contractor"
    ],
    "wof:name":"R B Porter Ltd.",
    "wof:placetype":"venue"
},
  "geometry": {"coordinates":[-2.1399490833,52.4459648132],"type":"Point"}
}