{
  "type": "Feature",
  "properties": {
    "addr:full":"8 Telford Close Norwich Norfolk NR3 2BN",
    "addr:housenumber":"8",
    "addr:postcode":"nr3 2bn",
    "addr:street":"Telford Close",
    "iso:country":"GB",
    "sg:address":"8 Telford Close",
    "sg:city":"Norwich",
    "sg:classifiers":[
        {
            "category":"Manufacturing",
            "subcategory":"Lumber",
            "type":"Manufacturing & Wholesale Goods"
        }
    ],
    "sg:postcode":"NR3 2BN",
    "sg:province":"Norfolk",
    "sg:tags":[
        "importer",
        "merchants",
        "agent",
        "timber"
    ],
    "wof:name":"Solaglas",
    "wof:placetype":"venue"
},
  "geometry": {"coordinates":[1.2649489641,52.6459236145],"type":"Point"}
}