{
  "type": "Feature",
  "properties": {
    "addr:full":"1 Waldeck Rd Luton Bedfordshire LU1 1HG",
    "addr:housenumber":"1",
    "addr:postcode":"lu1 1hg",
    "addr:street":"Waldeck Rd",
    "iso:country":"GB",
    "sg:address":"1 Waldeck Rd",
    "sg:city":"Luton",
    "sg:classifiers":[
        {
            "category":"Shopping",
            "subcategory":"Department Store",
            "type":"Retail Goods"
        }
    ],
    "sg:postcode":"LU1 1HG",
    "sg:province":"Bedfordshire",
    "wof:name":"Sylhet Store",
    "wof:placetype":"venue"
},
  "geometry": {"coordinates":[-0.426134,51.885464],"type":"Point"}
}