{
  "type": "Feature",
  "properties": {
    "iso:country":"GB",
    "sg:address":"14 Bellfield Road",
    "sg:city":"Aberdeen",
    "sg:classifiers":[
        {
            "category":"Retail",
            "subcategory":"Driving School",
            "type":"Services"
        }
    ],
    "sg:postcode":"AB16 6QB",
    "sg:province":"Aberdeen City",
    "wof:name":"Dyce School of Motoring",
    "wof:placetype":"venue"
},
  "geometry": {"coordinates":[-2.1720559597,57.1563415527],"type":"Point"}
}