{
  "type": "Feature",
  "properties": {
    "iso:country":"GB",
    "sg:address":"Gardenni, Llangwyryfon",
    "sg:city":"Aberystwyth",
    "sg:classifiers":[
        {
            "category":"Farming",
            "subcategory":"Livestock Farm",
            "type":"Manufacturing & Wholesale Goods"
        }
    ],
    "sg:phone":"+44 1974 241279",
    "sg:postcode":"SY23 4PQ",
    "sg:province":"Ceredigion",
    "sg:tags":[
        "others"
    ],
    "wof:name":"M I & D M Evans",
    "wof:placetype":"venue"
},
  "geometry": {"coordinates":[-4.0563941002,52.3159942627],"type":"Point"}
}