{
  "type": "Feature",
  "properties": {
    "iso:country":"GB",
    "sg:address":"Gooshays Dr",
    "sg:city":"Romford",
    "sg:classifiers":[
        {
            "category":"Health Services",
            "subcategory":"Doctor",
            "type":"Services"
        }
    ],
    "sg:phone":"+44 1708 343991",
    "sg:postcode":"RM3 9SU",
    "sg:province":"Essex",
    "sg:tags":[
        "practitioners"
    ],
    "wof:name":"Kuchhai, N",
    "wof:placetype":"venue"
},
  "geometry": {"coordinates":[0.2240449935,51.6067237854],"type":"Point"}
}