{
  "type": "Feature",
  "properties": {
    "iso:country":"GB",
    "sg:address":"188 192 Grooch Street",
    "sg:city":"Birmingham",
    "sg:classifiers":[
        {
            "category":"Professional",
            "subcategory":"Accounting & Tax Preparation",
            "type":"Services"
        }
    ],
    "sg:phone":"+44 121 622 1369",
    "sg:postcode":"B5 7HE",
    "sg:province":"West Midlands",
    "sg:tags":[
        "accountant"
    ],
    "wof:name":"M Hasnain & Co.",
    "wof:placetype":"venue"
},
  "geometry": {"coordinates":[-1.89464,52.469028],"type":"Point"}
}