{
  "type": "Feature",
  "properties": {
    "addr:full":"33 Broadmead Ave Worcester Park Surrey KT4 7SN",
    "addr:housenumber":"33",
    "addr:postcode":"kt4 7sn",
    "addr:street":"Broadmead Ave",
    "iso:country":"GB",
    "sg:address":"33 Broadmead Ave",
    "sg:city":"Worcester Park",
    "sg:classifiers":[
        {
            "category":"Retail",
            "subcategory":"Driving School",
            "type":"Services"
        }
    ],
    "sg:phone":"+44 20 8255 9896",
    "sg:postcode":"KT4 7SN",
    "sg:province":"Surrey",
    "wof:name":"Drivewell",
    "wof:placetype":"venue"
},
  "geometry": {"coordinates":[-0.245027,51.385471],"type":"Point"}
}