{
  "type": "Feature",
  "properties": {
    "iso:country":"GB",
    "sg:address":"41 Market Street",
    "sg:city":"Rugeley",
    "sg:classifiers":[
        {
            "category":"Retail",
            "subcategory":"Auto Repair",
            "type":"Services"
        }
    ],
    "sg:phone":"+44 1889 575345",
    "sg:postcode":"WS15 2JH",
    "sg:province":"Staffordshire",
    "sg:tags":[
        "modification",
        "garage"
    ],
    "wof:name":"Market St Garage",
    "wof:placetype":"venue"
},
  "geometry": {"coordinates":[-1.934053,52.762405],"type":"Point"}
}