{
  "type": "Feature",
  "properties": {
    "addr:full":"Robinson Road, Immingham Dock Grimsby Lincolnshire DN40 2QN",
    "addr:postcode":"dn40 2qn",
    "addr:street":"Robinson Road;Dock Grimsby",
    "iso:country":"GB",
    "sg:address":"Robinson Road, Immingham Dock",
    "sg:city":"Grimsby",
    "sg:classifiers":[
        {
            "category":"Freight",
            "type":"Transportation"
        }
    ],
    "sg:phone":"+44 1469 577018",
    "sg:postcode":"DN40 2QN",
    "sg:province":"Lincolnshire",
    "sg:tags":[
        "haulage",
        "road"
    ],
    "wof:name":"Benhaul (Immingham) Ltd.",
    "wof:placetype":"venue"
},
  "geometry": {"coordinates":[-0.2289270014,53.633731842],"type":"Point"}
}