{
  "type": "Feature",
  "properties": {
    "addr:full":"Sowerby New Rd, Sowerby Sowerby Bridge West Yorkshire HX6 1JZ",
    "addr:postcode":"hx6 1jz",
    "addr:street":"New Rd;West",
    "iso:country":"GB",
    "sg:address":"Sowerby New Rd, Sowerby",
    "sg:city":"Sowerby Bridge",
    "sg:classifiers":[
        {
            "category":"Bars & Pubs",
            "type":"Food & Drink"
        }
    ],
    "sg:postcode":"HX6 1JZ",
    "sg:province":"West Yorkshire",
    "sg:tags":[
        "pubs",
        "inn"
    ],
    "wof:name":"Binns,Cecilia,",
    "wof:placetype":"venue"
},
  "geometry": {"coordinates":[-1.9420039654,53.7056350708],"type":"Point"}
}