{
  "type": "Feature",
  "properties": {
    "addr:full":"374 High Road, Tottenham London Greater London N17 9HY",
    "addr:housenumber":"374",
    "addr:postcode":"n17 9hy",
    "addr:street":"High Road",
    "iso:country":"GB",
    "sg:address":"374 High Road, Tottenham",
    "sg:city":"London",
    "sg:classifiers":[
        {
            "category":"Autos & Motor Vehicles",
            "subcategory":"Auto Supplies",
            "type":"Retail Goods"
        },
        {
            "category":"Shopping",
            "type":"Retail Goods"
        }
    ],
    "sg:phone":"+44 20 8808 2407",
    "sg:postcode":"N17 9HY",
    "sg:province":"Greater London",
    "sg:tags":[
        "car",
        "part",
        "accessory"
    ],
    "wof:name":"Aashish Motors",
    "wof:placetype":"venue"
},
  "geometry": {"coordinates":[-0.0699400008,51.5902099609],"type":"Point"}
}