{
  "type": "Feature",
  "properties": {
    "iso:country":"GB",
    "sg:address":"201-207 Tooting High St",
    "sg:city":"Tooting",
    "sg:classifiers":[
        {
            "category":"Manufacturing",
            "subcategory":"Wood Products",
            "type":"Manufacturing & Wholesale Goods"
        }
    ],
    "sg:phone":"+44 20 8682 2190",
    "sg:postcode":"SW17 0SZ",
    "sg:province":"Greater London",
    "sg:tags":[
        "maker",
        "cabinet"
    ],
    "wof:name":"Norema Scandinavian Design Centre",
    "wof:placetype":"venue"
},
  "geometry": {"coordinates":[-0.1716119945,51.4241790771],"type":"Point"}
}