{
  "type": "Feature",
  "properties": {
    "iso:country":"GB",
    "sg:address":"63 High Street",
    "sg:city":"Arundel",
    "sg:classifiers":[
        {
            "category":"Travel",
            "subcategory":"Hotels & Motels",
            "type":"Entertainment"
        }
    ],
    "sg:phone":"+44 1903 883029",
    "sg:postcode":"BN18 9AJ",
    "sg:province":"West Sussex",
    "sg:tags":[
        "house",
        "guest"
    ],
    "wof:name":"The Absolute Pub Co",
    "wof:placetype":"venue"
},
  "geometry": {"coordinates":[-0.554884,50.854839],"type":"Point"}
}