{
  "type": "Feature",
  "properties": {
    "iso:country":"GB",
    "sg:address":"27 Eskdale Rise, Allerton",
    "sg:city":"Bradford",
    "sg:classifiers":[
        {
            "category":"Building & Trades",
            "subcategory":"Construction",
            "type":"Services"
        }
    ],
    "sg:postcode":"BD15 7UG",
    "sg:province":"West Yorkshire",
    "sg:tags":[
        "joinery",
        "joiner",
        "carpenter",
        "carpentry"
    ],
    "wof:name":"BERNARD MALLORY",
    "wof:placetype":"venue"
},
  "geometry": {"coordinates":[-1.8184059858,53.7983322144],"type":"Point"}
}