{
  "type": "Feature",
  "properties": {
    "addr:full":"34 Queen Road Reading Berkshire RG1 4BA",
    "addr:housenumber":"34",
    "addr:postcode":"rg1 4ba",
    "addr:street":"Queen Road",
    "iso:country":"GB",
    "sg:address":"34 Queen Road",
    "sg:city":"Reading",
    "sg:classifiers":[
        {
            "category":"Shopping",
            "subcategory":"Photographic Equipment",
            "type":"Retail Goods"
        }
    ],
    "sg:phone":"+44 118 944 2524",
    "sg:postcode":"RG1 4BA",
    "sg:province":"Berkshire",
    "wof:name":"Photo Technical Ltd.",
    "wof:placetype":"venue"
},
  "geometry": {"coordinates":[-0.9666339755,51.4533538818],"type":"Point"}
}