{
  "type": "Feature",
  "properties": {
    "iso:country":"GB",
    "sg:address":"7 Lydyett Lane, Barnton",
    "sg:city":"Northwich",
    "sg:classifiers":[
        {
            "category":"Building & Trades",
            "subcategory":"Construction",
            "type":"Services"
        }
    ],
    "sg:postcode":"CW8 4JP",
    "sg:province":"Cheshire",
    "sg:tags":[
        "joiner",
        "carpenter"
    ],
    "wof:name":"D P Garnett Joinery",
    "wof:placetype":"venue"
},
  "geometry": {"coordinates":[-2.5482990742,53.2710647583],"type":"Point"}
}