{
  "type": "Feature",
  "properties": {
    "addr:full":"81 September Way Stanmore Greater London HA7 2SE",
    "addr:housenumber":"81",
    "addr:postcode":"ha7 2se",
    "addr:street":"September Way",
    "iso:country":"GB",
    "sg:address":"81 September Way",
    "sg:city":"Stanmore",
    "sg:classifiers":[
        {
            "category":"Professional",
            "subcategory":"Computer Services",
            "type":"Services"
        }
    ],
    "sg:phone":"+44 20 8954 0573",
    "sg:postcode":"HA7 2SE",
    "sg:province":"Greater London",
    "sg:tags":[
        "consultant"
    ],
    "wof:name":"Hana Services Ltd",
    "wof:placetype":"venue"
},
  "geometry": {"coordinates":[-0.3129140139,51.6121711731],"type":"Point"}
}