{
  "type": "Feature",
  "properties": {
    "addr:full":"Grange Lane Winsford Cheshire CW7 2PT",
    "addr:postcode":"cw7 2pt",
    "addr:street":"Grange Lane",
    "iso:country":"GB",
    "sg:address":"Grange Lane",
    "sg:city":"Winsford",
    "sg:classifiers":[
        {
            "category":"Restaurant",
            "type":"Food & Drink"
        },
        {
            "category":"Community Center",
            "type":"Public Place"
        },
        {
            "category":"Government",
            "subcategory":"Office",
            "type":"Public Place"
        }
    ],
    "sg:phone":"+44 1606 552780",
    "sg:postcode":"CW7 2PT",
    "sg:province":"Cheshire",
    "sg:tags":[
        "recreation",
        "local",
        "leisure",
        "centre"
    ],
    "wof:name":"Knights Grange Sports Complex & Golf Course",
    "wof:placetype":"venue"
},
  "geometry": {"coordinates":[-2.5379729271,53.2012138367],"type":"Point"}
}