{
  "type": "Feature",
  "properties": {
    "addr:full":"25 Randalls Park Avenue Leatherhead Surrey KT22 7NS",
    "addr:housenumber":"25",
    "addr:postcode":"kt22 7ns",
    "addr:street":"Randalls Park Avenue",
    "iso:country":"GB",
    "sg:address":"25 Randalls Park Avenue",
    "sg:city":"Leatherhead",
    "sg:classifiers":[
        {
            "category":"Building & Trades",
            "subcategory":"Plumbing",
            "type":"Services"
        }
    ],
    "sg:phone":"+44 1372 379676",
    "sg:postcode":"KT22 7NS",
    "sg:province":"Surrey",
    "sg:tags":[
        "central",
        "installation",
        "heating",
        "servicing",
        "system"
    ],
    "wof:name":"R L Wigley Plumbing & Heating",
    "wof:placetype":"venue"
},
  "geometry": {"coordinates":[-0.33206,51.304241],"type":"Point"}
}