{
  "type": "Feature",
  "properties": {
    "iso:country":"GB",
    "sg:address":"172 Canongate (royal Mile)",
    "sg:city":"Edinburgh",
    "sg:classifiers":[
        {
            "category":"Food & Beverages",
            "subcategory":"Liquor & Beverages",
            "type":"Retail Goods"
        }
    ],
    "sg:postcode":"EH8 8BN",
    "sg:province":"City of Edinburgh",
    "sg:tags":[
        "beer",
        "spirit",
        "wines"
    ],
    "wof:name":"Cadenshead Whisky Shop",
    "wof:placetype":"venue"
},
  "geometry": {"coordinates":[-3.180997,55.951092],"type":"Point"}
}