{
  "type": "Feature",
  "properties": {
    "addr:full":"Lodge Road Croydon Surrey CR0 2PL",
    "addr:postcode":"cr0 2pl",
    "addr:street":"Lodge Road",
    "iso:country":"GB",
    "sg:address":"Lodge Road",
    "sg:city":"Croydon",
    "sg:classifiers":[
        {
            "category":"Education",
            "subcategory":"School",
            "type":"Public Place"
        }
    ],
    "sg:phone":"+44 20 8689 7681",
    "sg:postcode":"CR0 2PL",
    "sg:province":"Surrey",
    "sg:tags":[
        "local",
        "authority"
    ],
    "wof:name":"Elmwood Infants School",
    "wof:placetype":"venue"
},
  "geometry": {"coordinates":[-0.1050940007,51.3870048523],"type":"Point"}
}