{
  "type": "Feature",
  "properties": {
    "iso:country":"GB",
    "sg:address":"Unit 10a New Haden Works, Draycott Crossroads",
    "sg:city":"Stoke-on-trent",
    "sg:classifiers":[
        {
            "category":"Retail",
            "subcategory":"Auto Repair",
            "type":"Services"
        }
    ],
    "sg:phone":"+44 1538 750788",
    "sg:postcode":"ST10 2NW",
    "sg:province":"Staffordshire",
    "sg:tags":[
        "electrician"
    ],
    "wof:name":"Airfawn Consultants Ltd.",
    "wof:placetype":"venue"
},
  "geometry": {"coordinates":[-2.00665,52.981178],"type":"Point"}
}