{
  "type": "Feature",
  "properties": {
    "addr:full":"3 Brunwin Road, Rayne Braintree Essex CM77 6BU",
    "addr:housenumber":"3",
    "addr:postcode":"cm77 6bu",
    "addr:street":"Brunwin Road",
    "iso:country":"GB",
    "sg:address":"3 Brunwin Road, Rayne",
    "sg:city":"Braintree",
    "sg:classifiers":[
        {
            "category":"Building & Trades",
            "subcategory":"Construction",
            "type":"Services"
        }
    ],
    "sg:phone":"+44 1376 324054",
    "sg:postcode":"CM77 6BU",
    "sg:province":"Essex",
    "sg:tags":[
        "builder"
    ],
    "wof:name":"Smith Bros (Rayne) Ltd.",
    "wof:placetype":"venue"
},
  "geometry": {"coordinates":[0.5098959804,51.8785247803],"type":"Point"}
}