{
  "type": "Feature",
  "properties": {
    "iso:country":"GB",
    "sg:address":"143 Neil Armstrong Way",
    "sg:city":"Leigh On Sea",
    "sg:classifiers":[
        {
            "category":"Professional",
            "subcategory":"Detective & Security Services",
            "type":"Services"
        }
    ],
    "sg:phone":"+44 1702 526194",
    "sg:postcode":"SS9 5UF",
    "sg:province":"Essex",
    "sg:tags":[
        "agency"
    ],
    "wof:name":"U.N.I.F.O.R.M.S.",
    "wof:placetype":"venue"
},
  "geometry": {"coordinates":[0.670106,51.568851],"type":"Point"}
}