{
  "type": "Feature",
  "properties": {
    "iso:country":"GB",
    "sg:address":"6 Underdown Road, Southwick",
    "sg:city":"Brighton",
    "sg:classifiers":[
        {
            "category":"Professional",
            "subcategory":"Engineering",
            "type":"Services"
        },
        {
            "category":"Shopping",
            "subcategory":"Computers & Home Electronics",
            "type":"Retail Goods"
        }
    ],
    "sg:phone":"+44 1273 594506",
    "sg:postcode":"BN42 4HL",
    "sg:province":"West Sussex",
    "sg:tags":[
        "television",
        "aerial",
        "contractor",
        "electrical",
        "radio",
        "engineer"
    ],
    "wof:name":"Grants Television Aerial Service",
    "wof:placetype":"venue"
},
  "geometry": {"coordinates":[-0.23908,50.838112],"type":"Point"}
}