{
  "type": "Feature",
  "properties": {
    "addr:full":"5 Alexandria Drive Lytham St Annes Lancashire FY8 1NL",
    "addr:housenumber":"5",
    "addr:postcode":"fy8 1nl",
    "addr:street":"Alexandria Drive",
    "iso:country":"GB",
    "sg:address":"5 Alexandria Drive",
    "sg:city":"Lytham St Annes",
    "sg:classifiers":[
        {
            "category":"Food & Beverages",
            "subcategory":"Meat & Fish",
            "type":"Retail Goods"
        }
    ],
    "sg:phone":"+44 1253 725711",
    "sg:postcode":"FY8 1NL",
    "sg:province":"Lancashire",
    "sg:tags":[
        "butcher"
    ],
    "wof:name":"Booth's Butchers",
    "wof:placetype":"venue"
},
  "geometry": {"coordinates":[-3.0240409374,53.7457427979],"type":"Point"}
}