{
  "type": "Feature",
  "properties": {
    "iso:country":"GB",
    "sg:address":"66 Church Road, Soundwell",
    "sg:city":"Bristol",
    "sg:classifiers":[
        {
            "category":"Retail",
            "subcategory":"Repair Shop",
            "type":"Services"
        }
    ],
    "sg:postcode":"BS16 4RQ",
    "sg:province":"City of Bristol",
    "sg:tags":[
        "maintenance"
    ],
    "wof:name":"Lee C Brasier",
    "wof:placetype":"venue"
},
  "geometry": {"coordinates":[-2.503516,51.473984],"type":"Point"}
}