{
  "type": "Feature",
  "properties": {
    "addr:full":"11 Livingstone Court, Nimrod Drive, Rowner Gosport Hampshire PO13 8AG",
    "addr:housenumber":"11",
    "addr:postcode":"po13 8ag",
    "addr:street":"Livingstone Court Nimrod Drive",
    "iso:country":"GB",
    "sg:address":"11 Livingstone Court, Nimrod Drive, Rowner",
    "sg:city":"Gosport",
    "sg:classifiers":[
        {
            "category":"Health Services",
            "subcategory":"Doctor",
            "type":"Services"
        }
    ],
    "sg:phone":"+44 23 9258 0831",
    "sg:postcode":"PO13 8AG",
    "sg:province":"Hampshire",
    "sg:tags":[
        "practitioners"
    ],
    "wof:name":"Drs Reid Evans Cavanagh & Burlein",
    "wof:placetype":"venue"
},
  "geometry": {"coordinates":[-1.1664760113,50.8032531738],"type":"Point"}
}