{
  "type": "Feature",
  "properties": {
    "addr:full":"74b Jubilee Road Waterlooville Hampshire PO7 7RE",
    "addr:housenumber":"74b",
    "addr:postcode":"po7 7re",
    "addr:street":"Jubilee Road",
    "iso:country":"GB",
    "sg:address":"74b Jubilee Road",
    "sg:city":"Waterlooville",
    "sg:classifiers":[
        {
            "category":"Professional",
            "subcategory":"Printing & Photocopies",
            "type":"Services"
        }
    ],
    "sg:phone":"+44 23 9226 2114",
    "sg:postcode":"PO7 7RE",
    "sg:province":"Hampshire",
    "sg:tags":[
        "embroiderer"
    ],
    "wof:name":"Freelance",
    "wof:placetype":"venue"
},
  "geometry": {"coordinates":[-1.0327390432,50.8860473633],"type":"Point"}
}