{
  "type": "Feature",
  "properties": {
    "iso:country":"GB",
    "sg:address":"Black Hill Farm",
    "sg:city":"Ilkley",
    "sg:classifiers":[
        {
            "category":"Home & Garden",
            "subcategory":"Carpets & Floor Coverings",
            "type":"Retail Goods"
        }
    ],
    "sg:phone":"+44 1943 602668",
    "sg:postcode":"LS29 0ET",
    "sg:province":"North Yorkshire",
    "sg:tags":[
        "textile",
        "floorcoverings"
    ],
    "wof:name":"R Lawson (Floorcovering) Ltd",
    "wof:placetype":"venue"
},
  "geometry": {"coordinates":[-1.821754,53.924461],"type":"Point"}
}