{
  "type": "Feature",
  "properties": {
    "addr:full":"14 Mander Square, Mander Centre Wolverhampton West Midlands WV1 3NN",
    "addr:housenumber":"14",
    "addr:postcode":"wv1 3nn",
    "addr:street":"Mander Square Mander",
    "iso:country":"GB",
    "sg:address":"14 Mander Square, Mander Centre",
    "sg:city":"Wolverhampton",
    "sg:classifiers":[
        {
            "category":"Travel",
            "subcategory":"Travel Agent",
            "type":"Entertainment"
        }
    ],
    "sg:phone":"+44 1902 379100",
    "sg:postcode":"WV1 3NN",
    "sg:province":"West Midlands",
    "wof:name":"Going Places Leisure Travel Ltd.",
    "wof:placetype":"venue"
},
  "geometry": {"coordinates":[-2.129489,52.584213],"type":"Point"}
}