{
  "type": "Feature",
  "properties": {
    "addr:full":"226 North La Aldershot Hampshire GU12 4TH",
    "addr:housenumber":"226",
    "addr:postcode":"gu12 4th",
    "addr:street":"North La Aldershot",
    "iso:country":"GB",
    "sg:address":"226 North La",
    "sg:city":"Aldershot",
    "sg:classifiers":[
        {
            "category":"Shopping",
            "subcategory":"Florist",
            "type":"Retail Goods"
        }
    ],
    "sg:phone":"+44 1252 342625",
    "sg:postcode":"GU12 4TH",
    "sg:province":"Hampshire",
    "wof:name":"Flowers By Jan",
    "wof:placetype":"venue"
},
  "geometry": {"coordinates":[-0.7426620126,51.2501106262],"type":"Point"}
}