{
  "type": "Feature",
  "properties": {
    "addr:full":"103 King Street Castle Douglas Dumfries and Galloway DG7 1LZ",
    "addr:housenumber":"103",
    "addr:postcode":"dg7 1lz",
    "addr:street":"King Street",
    "iso:country":"GB",
    "sg:address":"103 King Street",
    "sg:city":"Castle Douglas",
    "sg:classifiers":[
        {
            "category":"Shopping",
            "subcategory":"Clothing, Apparel, & Fashions",
            "type":"Retail Goods"
        }
    ],
    "sg:phone":"+44 1556 503579",
    "sg:postcode":"DG7 1LZ",
    "sg:province":"Dumfries and Galloway",
    "sg:tags":[
        "shop"
    ],
    "wof:name":"Lynsey Stewart",
    "wof:placetype":"venue"
},
  "geometry": {"coordinates":[-3.9294769764,54.9408111572],"type":"Point"}
}