{
  "type": "Feature",
  "properties": {
    "addr:full":"89 Great Western Designer, Outlet Village, Kemble Drive Swindon Wiltshire SN2 2DY",
    "addr:housenumber":"89",
    "addr:postcode":"sn2 2dy",
    "addr:street":"Great;Kemble Drive",
    "iso:country":"GB",
    "sg:address":"89 Great Western Designer, Outlet Village, Kemble Drive",
    "sg:city":"Swindon",
    "sg:classifiers":[
        {
            "category":"Shopping",
            "subcategory":"Clothing, Apparel, & Fashions",
            "type":"Retail Goods"
        }
    ],
    "sg:phone":"+44 1793 531070",
    "sg:postcode":"SN2 2DY",
    "sg:province":"Wiltshire",
    "sg:tags":[
        "tie",
        "neckwear"
    ],
    "wof:name":"Tie Rack Ltd.",
    "wof:placetype":"venue"
},
  "geometry": {"coordinates":[-1.7981200218,51.562538147],"type":"Point"}
}