{
  "type": "Feature",
  "properties": {
    "iso:country":"GB",
    "sg:address":"72 Margate Road",
    "sg:city":"Ramsgate",
    "sg:classifiers":[
        {
            "category":"Bars & Pubs",
            "type":"Food & Drink"
        }
    ],
    "sg:phone":"+44 1843 593586",
    "sg:postcode":"CT11 7SG",
    "sg:province":"Kent",
    "sg:tags":[
        "pubs",
        "inn"
    ],
    "wof:name":"Derby Arms",
    "wof:placetype":"venue"
},
  "geometry": {"coordinates":[1.410581,51.342312],"type":"Point"}
}