{
  "type": "Feature",
  "properties": {
    "addr:full":"9 Field Street Willenhall West Midlands WV13 2NY",
    "addr:housenumber":"9",
    "addr:postcode":"wv13 2ny",
    "addr:street":"Field Street",
    "iso:country":"GB",
    "sg:address":"9 Field Street",
    "sg:city":"Willenhall",
    "sg:classifiers":[
        {
            "category":"Home & Garden",
            "subcategory":"Hardware",
            "type":"Retail Goods"
        }
    ],
    "sg:postcode":"WV13 2NY",
    "sg:province":"West Midlands",
    "sg:tags":[
        "retailer",
        "diy"
    ],
    "wof:name":"Jeffreys D I Y Stores",
    "wof:placetype":"venue"
},
  "geometry": {"coordinates":[-2.0593039989,52.5841178894],"type":"Point"}
}