{
  "type": "Feature",
  "properties": {
    "iso:country":"GB",
    "sg:address":"Unit 52, Old Mill Industrial Estate",
    "sg:city":"Exeter",
    "sg:classifiers":[
        {
            "category":"Military Area",
            "subcategory":"Coast Guard Base",
            "type":"Public Place"
        },
        {
            "category":"Wholesale",
            "subcategory":"Construction Materials",
            "type":"Manufacturing & Wholesale Goods"
        }
    ],
    "sg:phone":"+44 1392 841446",
    "sg:postcode":"EX5 4RJ",
    "sg:province":"Devon",
    "sg:tags":[
        "supplier",
        "flow",
        "system",
        "meter",
        "measurement"
    ],
    "wof:name":"Flotec (U K) Ltd.",
    "wof:placetype":"venue"
},
  "geometry": {"coordinates":[-3.508591,50.764526],"type":"Point"}
}