{
  "type": "Feature",
  "properties": {
    "addr:full":"Hanging Hill Farm, Rawdon Road, Moira Swadlincote Derbyshire DE12 6DQ",
    "addr:postcode":"de12 6dq",
    "addr:street":"Hanging Hill Farm Rawdon Road",
    "iso:country":"GB",
    "sg:address":"Hanging Hill Farm, Rawdon Road, Moira",
    "sg:city":"Swadlincote",
    "sg:classifiers":[
        {
            "category":"Farming",
            "subcategory":"Livestock Farm",
            "type":"Manufacturing & Wholesale Goods"
        },
        {
            "category":"Farming",
            "subcategory":"Farm",
            "type":"Manufacturing & Wholesale Goods"
        }
    ],
    "sg:phone":"+44 1283 214010",
    "sg:postcode":"DE12 6DQ",
    "sg:province":"Derbyshire",
    "sg:tags":[
        "mixed",
        "crop",
        "others"
    ],
    "wof:name":"Robert S Betteridge",
    "wof:placetype":"venue"
},
  "geometry": {"coordinates":[-1.5147689581,52.7451438904],"type":"Point"}
}