{
  "type": "Feature",
  "properties": {
    "iso:country":"GB",
    "sg:address":"Arch 20-21, Lionel Street",
    "sg:city":"Birmingham",
    "sg:classifiers":[
        {
            "category":"Autos & Motor Vehicles",
            "subcategory":"Auto Supplies",
            "type":"Retail Goods"
        }
    ],
    "sg:phone":"+44 121 236 5584",
    "sg:postcode":"B3 1AQ",
    "sg:province":"West Midlands",
    "sg:tags":[
        "tyre"
    ],
    "wof:name":"Mr Tyre Ltd.",
    "wof:placetype":"venue"
},
  "geometry": {"coordinates":[-1.90194,52.485062],"type":"Point"}
}