{
  "type": "Feature",
  "properties": {
    "addr:full":"16 Gordon Road Great Yarmouth Norfolk NR31 0EW",
    "addr:housenumber":"16",
    "addr:postcode":"nr31 0ew",
    "addr:street":"Gordon Road",
    "iso:country":"GB",
    "sg:address":"16 Gordon Road",
    "sg:city":"Great Yarmouth",
    "sg:classifiers":[
        {
            "category":"Bakery",
            "type":"Food & Drink"
        }
    ],
    "sg:phone":"+44 1493 658186",
    "sg:postcode":"NR31 0EW",
    "sg:province":"Norfolk",
    "sg:tags":[
        "cake",
        "maker"
    ],
    "wof:name":"The Cake Box",
    "wof:placetype":"venue"
},
  "geometry": {"coordinates":[1.721195,52.599449],"type":"Point"}
}