{
  "type": "Feature",
  "properties": {
    "addr:full":"Queens Park Health Centre London Greater London W10 4LD",
    "addr:postcode":"w10 4ld",
    "addr:street":"Queens",
    "iso:country":"GB",
    "sg:address":"Queens Park Health Centre",
    "sg:city":"London",
    "sg:classifiers":[
        {
            "category":"Health Services",
            "subcategory":"Clinic",
            "type":"Services"
        },
        {
            "category":"Health Services",
            "subcategory":"Dentist",
            "type":"Services"
        }
    ],
    "sg:phone":"+44 20 8960 9007",
    "sg:postcode":"W10 4LD",
    "sg:province":"Greater London",
    "sg:tags":[
        "nh"
    ],
    "wof:name":"Indian Medical Association (Uk)",
    "wof:placetype":"venue"
},
  "geometry": {"coordinates":[-0.20762,51.530529],"type":"Point"}
}