{
  "type": "Feature",
  "properties": {
    "addr:full":"272 Manchester Road Warrington Cheshire WA1 3RB",
    "addr:housenumber":"272",
    "addr:postcode":"wa1 3rb",
    "addr:street":"Manchester Road",
    "iso:country":"GB",
    "sg:address":"272 Manchester Road",
    "sg:city":"Warrington",
    "sg:classifiers":[
        {
            "category":"Professional",
            "subcategory":"Engineering",
            "type":"Services"
        }
    ],
    "sg:phone":"+44 1925 655495",
    "sg:postcode":"WA1 3RB",
    "sg:province":"Cheshire",
    "sg:tags":[
        "consultant",
        "structural"
    ],
    "wof:name":"Structural Design & Draughting",
    "wof:placetype":"venue"
},
  "geometry": {"coordinates":[-2.57158494,53.3966445923],"type":"Point"}
}