{
  "type": "Feature",
  "properties": {
    "addr:full":"14 High Street Potters Bar Greater London EN6 5AW",
    "addr:housenumber":"14",
    "addr:postcode":"en6 5aw",
    "addr:street":"High Street",
    "iso:country":"GB",
    "sg:address":"14 High Street",
    "sg:city":"Potters Bar",
    "sg:classifiers":[
        {
            "category":"Home & Garden",
            "subcategory":"Furniture",
            "type":"Retail Goods"
        }
    ],
    "sg:phone":"+44 1707 647945",
    "sg:postcode":"EN6 5AW",
    "sg:province":"Greater London",
    "wof:name":"Bedroom Design Studios",
    "wof:placetype":"venue"
},
  "geometry": {"coordinates":[-0.178647,51.693012],"type":"Point"}
}