{
  "type": "Feature",
  "properties": {
    "addr:full":"34 Station Road, Scholes Leeds West Yorkshire LS15 4BN",
    "addr:housenumber":"34",
    "addr:postcode":"ls15 4bn",
    "addr:street":"Station Road",
    "iso:country":"GB",
    "sg:address":"34 Station Road, Scholes",
    "sg:city":"Leeds",
    "sg:classifiers":[
        {
            "category":"Shopping",
            "subcategory":"News",
            "type":"Retail Goods"
        },
        {
            "category":"Government",
            "subcategory":"Post Office",
            "type":"Public Place"
        }
    ],
    "sg:phone":"+44 113 273 5866",
    "sg:postcode":"LS15 4BN",
    "sg:province":"West Yorkshire",
    "sg:tags":[
        "newsagent"
    ],
    "wof:name":"Pennocks Newsagents",
    "wof:placetype":"venue"
},
  "geometry": {"coordinates":[-1.4297289848,53.8280296326],"type":"Point"}
}