{
  "type": "Feature",
  "properties": {
    "addr:full":"Cutenhoe Road Luton Bedfordshire LU1 3NB",
    "addr:postcode":"lu1 3nb",
    "addr:street":"Cutenhoe Road",
    "iso:country":"GB",
    "sg:address":"Cutenhoe Road",
    "sg:city":"Luton",
    "sg:classifiers":[
        {
            "category":"Place Of Worship",
            "type":"Public Place"
        },
        {
            "category":"Social Services",
            "subcategory":"Retirement Home",
            "type":"Services"
        }
    ],
    "sg:phone":"+44 1582 482234",
    "sg:postcode":"LU1 3NB",
    "sg:province":"Bedfordshire",
    "sg:tags":[
        "historian",
        "family"
    ],
    "wof:name":"Family History Centre",
    "wof:placetype":"venue"
},
  "geometry": {"coordinates":[-0.406109,51.870316],"type":"Point"}
}