{
  "type": "Feature",
  "properties": {
    "iso:country":"GB",
    "sg:address":"Chamberlain Walk,high St, Coleshill",
    "sg:city":"Birmingham",
    "sg:classifiers":[
        {
            "category":"Shopping",
            "subcategory":"Florist",
            "type":"Retail Goods"
        }
    ],
    "sg:postcode":"B46 3BL",
    "sg:province":"Warwickshire",
    "wof:name":"Florist of Coleshill (The)",
    "wof:placetype":"venue"
},
  "geometry": {"coordinates":[-1.7068,52.498611],"type":"Point"}
}