{
  "type": "Feature",
  "properties": {
    "iso:country":"GB",
    "sg:address":"Po Box 416",
    "sg:city":"Woking",
    "sg:classifiers":[
        {
            "category":"Utilities",
            "type":"Services"
        }
    ],
    "sg:phone":"+44 1276 855165",
    "sg:postcode":"GU24 9XY",
    "sg:province":"Surrey",
    "sg:tags":[
        "internet"
    ],
    "wof:name":"Wondrex Promotions",
    "wof:placetype":"venue"
},
  "geometry": {"coordinates":[-0.641029,51.33556],"type":"Point"}
}