{
  "type": "Feature",
  "properties": {
    "addr:full":"Standens Barn Local, Standens Barn Northampton Northamptonshire NN3 9DE",
    "addr:postcode":"nn3 9de",
    "iso:country":"GB",
    "sg:address":"Standens Barn Local, Standens Barn",
    "sg:city":"Northampton",
    "sg:classifiers":[
        {
            "category":"Bars & Pubs",
            "type":"Food & Drink"
        }
    ],
    "sg:phone":"+44 1604 408743",
    "sg:postcode":"NN3 9DE",
    "sg:province":"Northamptonshire",
    "sg:tags":[
        "pubs",
        "inn"
    ],
    "wof:name":"The Standens Inn",
    "wof:placetype":"venue"
},
  "geometry": {"coordinates":[-0.830787003,52.2522201538],"type":"Point"}
}