{
  "type": "Feature",
  "properties": {
    "addr:full":"21 Walverden Rd Nelson Lancashire BB9 0PJ",
    "addr:housenumber":"21",
    "addr:postcode":"bb9 0pj",
    "addr:street":"Walverden Rd",
    "iso:country":"GB",
    "sg:address":"21 Walverden Rd",
    "sg:city":"Nelson",
    "sg:classifiers":[
        {
            "category":"Organizations",
            "subcategory":"Religious Organization",
            "type":"Services"
        }
    ],
    "sg:phone":"+44 1282 613776",
    "sg:postcode":"BB9 0PJ",
    "sg:province":"Lancashire",
    "sg:tags":[
        "organisation"
    ],
    "wof:name":"Quakers",
    "wof:placetype":"venue"
},
  "geometry": {"coordinates":[-2.219618,53.824463],"type":"Point"}
}