{
  "type": "Feature",
  "properties": {
    "addr:full":"10 New Road, Armigage Rugeley Staffordshire WS15 4BN",
    "addr:housenumber":"10",
    "addr:postcode":"ws15 4bn",
    "addr:street":"New Road Armigage",
    "iso:country":"GB",
    "sg:address":"10 New Road, Armigage",
    "sg:city":"Rugeley",
    "sg:classifiers":[
        {
            "category":"Organizations",
            "subcategory":"Membership Organization",
            "type":"Services"
        }
    ],
    "sg:phone":"+44 1543 490038",
    "sg:postcode":"WS15 4BN",
    "sg:province":"Staffordshire",
    "sg:tags":[
        "club"
    ],
    "wof:name":"The Royal British Legion Scotland",
    "wof:placetype":"venue"
},
  "geometry": {"coordinates":[-1.879634,52.741783],"type":"Point"}
}