{
  "type": "Feature",
  "properties": {
    "addr:full":"1 Jubilee Terrace, Langho Blackburn Lancashire BB6 8DA",
    "addr:housenumber":"1",
    "addr:postcode":"bb6 8da",
    "addr:street":"Jubilee Terrace Langho",
    "iso:country":"GB",
    "sg:address":"1 Jubilee Terrace, Langho",
    "sg:city":"Blackburn",
    "sg:classifiers":[
        {
            "category":"Fast Food",
            "type":"Food & Drink"
        }
    ],
    "sg:phone":"+44 1254 247881",
    "sg:postcode":"BB6 8DA",
    "sg:province":"Lancashire",
    "sg:tags":[
        "away",
        "meal",
        "outlet",
        "take"
    ],
    "wof:name":"Good Taste Chinese Take Away",
    "wof:placetype":"venue"
},
  "geometry": {"coordinates":[-2.448534,53.804184],"type":"Point"}
}