{
  "type": "Feature",
  "properties": {
    "addr:full":"Pen Bryn Isaf Farm, Talybont Bangor Gwynedd LL57 3YE",
    "addr:postcode":"ll57 3ye",
    "addr:street":"Talybont",
    "iso:country":"GB",
    "sg:address":"Pen Bryn Isaf Farm, Talybont",
    "sg:city":"Bangor",
    "sg:classifiers":[
        {
            "category":"Farming",
            "subcategory":"Livestock Farm",
            "type":"Manufacturing & Wholesale Goods"
        },
        {
            "category":"Farming",
            "subcategory":"Farm",
            "type":"Manufacturing & Wholesale Goods"
        }
    ],
    "sg:phone":"+44 1248 364482",
    "sg:postcode":"LL57 3YE",
    "sg:province":"Gwynedd",
    "sg:tags":[
        "mixed",
        "crop",
        "others"
    ],
    "wof:name":"Jones S & J",
    "wof:placetype":"venue"
},
  "geometry": {"coordinates":[-4.091026783,53.2148971558],"type":"Point"}
}