{
  "type": "Feature",
  "properties": {
    "addr:full":"8 Barnes Street, Clayton Le Moors Accrington Lancashire BB5 5PF",
    "addr:housenumber":"8",
    "addr:postcode":"bb5 5pf",
    "addr:street":"Barnes Street",
    "iso:country":"GB",
    "sg:address":"8 Barnes Street, Clayton Le Moors",
    "sg:city":"Accrington",
    "sg:classifiers":[
        {
            "category":"Professional",
            "subcategory":"Business Services",
            "type":"Services"
        }
    ],
    "sg:postcode":"BB5 5PF",
    "sg:province":"Lancashire",
    "sg:tags":[
        "bookmaker"
    ],
    "wof:name":"B & B Racing",
    "wof:placetype":"venue"
},
  "geometry": {"coordinates":[-2.3854999542,53.7751998901],"type":"Point"}
}