{
  "type": "Feature",
  "properties": {
    "addr:full":"Malcolm House, 581-583 Moseley Road Birmingham West Midlands B12 9BL",
    "addr:housenumber":"581-583",
    "addr:postcode":"b12 9bl",
    "addr:street":"Moseley Road",
    "iso:country":"GB",
    "sg:address":"Malcolm House, 581-583 Moseley Road",
    "sg:city":"Birmingham",
    "sg:classifiers":[
        {
            "category":"Communications",
            "subcategory":"Newspaper",
            "type":"Services"
        }
    ],
    "sg:postcode":"B12 9BL",
    "sg:province":"West Midlands",
    "sg:tags":[
        "magazine"
    ],
    "wof:name":"Simon Baker",
    "wof:placetype":"venue"
},
  "geometry": {"coordinates":[-1.886499,52.455078],"type":"Point"}
}