{
  "type": "Feature",
  "properties": {
    "addr:full":"113 Hoddern Avenue Peacehaven East Sussex BN10 7QT",
    "addr:housenumber":"113",
    "addr:postcode":"bn10 7qt",
    "addr:street":"Hoddern Avenue Peacehaven",
    "iso:country":"GB",
    "sg:address":"113 Hoddern Avenue",
    "sg:city":"Peacehaven",
    "sg:classifiers":[
        {
            "category":"Building & Trades",
            "subcategory":"Construction",
            "type":"Services"
        }
    ],
    "sg:postcode":"BN10 7QT",
    "sg:province":"East Sussex",
    "sg:tags":[
        "decorator",
        "painter"
    ],
    "wof:name":"Peter Therin",
    "wof:placetype":"venue"
},
  "geometry": {"coordinates":[-0.002754,50.799313],"type":"Point"}
}