{
  "type": "Feature",
  "properties": {
    "addr:full":"Crossing Gate Farm, Thorpe Lane Lincoln Lincolnshire LN6 9DY",
    "addr:postcode":"ln6 9dy",
    "addr:street":"Crossing Gate;Thorpe Lane",
    "iso:country":"GB",
    "sg:address":"Crossing Gate Farm, Thorpe Lane",
    "sg:city":"Lincoln",
    "sg:classifiers":[
        {
            "category":"Farming",
            "subcategory":"Dairy Farm",
            "type":"Manufacturing & Wholesale Goods"
        }
    ],
    "sg:phone":"+44 1522 868641",
    "sg:postcode":"LN6 9DY",
    "sg:province":"Lincolnshire",
    "wof:name":"J & L Wood",
    "wof:placetype":"venue"
},
  "geometry": {"coordinates":[-0.66713,53.185398],"type":"Point"}
}