{
  "type": "Feature",
  "properties": {
    "addr:full":"57 Broad Street Bromsgrove Worcestershire B61 8LL",
    "addr:housenumber":"57",
    "addr:postcode":"b61 8ll",
    "addr:street":"Broad Street",
    "iso:country":"GB",
    "sg:address":"57 Broad Street",
    "sg:city":"Bromsgrove",
    "sg:classifiers":[
        {
            "category":"Building & Trades",
            "subcategory":"Plumbing",
            "type":"Services"
        }
    ],
    "sg:postcode":"B61 8LL",
    "sg:province":"Worcestershire",
    "sg:tags":[
        "heating"
    ],
    "wof:name":"Carter,Stephen,",
    "wof:placetype":"venue"
},
  "geometry": {"coordinates":[-2.0669460297,52.3411407471],"type":"Point"}
}