{
  "type": "Feature",
  "properties": {
    "addr:full":"47 Garth Close, Lower Morden Morden Surrey SM4 4NN",
    "addr:housenumber":"47",
    "addr:postcode":"sm4 4nn",
    "addr:street":"Garth Close",
    "iso:country":"GB",
    "sg:address":"47 Garth Close, Lower Morden",
    "sg:city":"Morden",
    "sg:classifiers":[
        {
            "category":"Professional",
            "subcategory":"Management & Consulting",
            "type":"Services"
        }
    ],
    "sg:phone":"+44 20 8395 7385",
    "sg:postcode":"SM4 4NN",
    "sg:province":"Surrey",
    "sg:tags":[
        "project"
    ],
    "wof:name":"The Peter Forsdike Consultancy",
    "wof:placetype":"venue"
},
  "geometry": {"coordinates":[-0.225146994,51.3864326477],"type":"Point"}
}