{
  "type": "Feature",
  "properties": {
    "iso:country":"GB",
    "sg:address":"92 Warburton Road, Canford Heath",
    "sg:city":"Poole",
    "sg:classifiers":[
        {
            "category":"Building & Trades",
            "subcategory":"Construction",
            "type":"Services"
        }
    ],
    "sg:postcode":"BH17 8SF",
    "sg:province":"Dorset",
    "sg:tags":[
        "builder"
    ],
    "wof:name":"Datalec Installations Ltd.",
    "wof:placetype":"venue"
},
  "geometry": {"coordinates":[-1.9656610489,50.7460670471],"type":"Point"}
}