{
  "type": "Feature",
  "properties": {
    "addr:full":"17 Mountjoy Close Wimborne Dorset BH21 3AX",
    "addr:housenumber":"17",
    "addr:postcode":"bh21 3ax",
    "addr:street":"Mountjoy Close",
    "iso:country":"GB",
    "sg:address":"17 Mountjoy Close",
    "sg:city":"Wimborne",
    "sg:classifiers":[
        {
            "category":"Professional",
            "subcategory":"Engineering",
            "type":"Services"
        },
        {
            "category":"Building & Trades",
            "subcategory":"Electrical",
            "type":"Services"
        }
    ],
    "sg:phone":"+44 1202 889368",
    "sg:postcode":"BH21 3AX",
    "sg:province":"Dorset",
    "sg:tags":[
        "engineer",
        "electrician",
        "contractor"
    ],
    "wof:name":"Inte-Lectrical Services",
    "wof:placetype":"venue"
},
  "geometry": {"coordinates":[-1.959041,50.786182],"type":"Point"}
}