{
  "type": "Feature",
  "properties": {
    "addr:full":"71 St Kilda Road London Greater London W13 9DF",
    "addr:housenumber":"71",
    "addr:postcode":"w13 9df",
    "addr:street":"St Kilda Road",
    "iso:country":"GB",
    "sg:address":"71 St Kilda Road",
    "sg:city":"London",
    "sg:classifiers":[
        {
            "category":"Manufacturing",
            "subcategory":"Signs",
            "type":"Manufacturing & Wholesale Goods"
        }
    ],
    "sg:phone":"+44 20 8567 6081",
    "sg:postcode":"W13 9DF",
    "sg:province":"Greater London",
    "sg:tags":[
        "writer"
    ],
    "wof:name":"George E Pull",
    "wof:placetype":"venue"
},
  "geometry": {"coordinates":[-0.324458003,51.5057868958],"type":"Point"}
}