{
  "type": "Feature",
  "properties": {
    "iso:country":"GB",
    "sg:address":"167 Huddersfield Road",
    "sg:city":"Oldham",
    "sg:classifiers":[
        {
            "category":"Government",
            "subcategory":"Post Office",
            "type":"Public Place"
        }
    ],
    "sg:phone":"+44 161 624 3206",
    "sg:postcode":"OL1 3PA",
    "sg:province":"Lancashire",
    "wof:name":"Huddersfield Road P O",
    "wof:placetype":"venue"
},
  "geometry": {"coordinates":[-2.0908970833,53.5468215942],"type":"Point"}
}