{
  "type": "Feature",
  "properties": {
    "iso:country":"GB",
    "sg:address":"24 Scarr Av",
    "sg:city":"Manchester",
    "sg:classifiers":[
        {
            "category":"Building & Trades",
            "subcategory":"Construction",
            "type":"Services"
        }
    ],
    "sg:phone":"+44 161 723 2828",
    "sg:postcode":"M26 1WA",
    "sg:province":"Greater Manchester",
    "sg:tags":[
        "builder"
    ],
    "wof:name":"Direct Building Services",
    "wof:placetype":"venue"
},
  "geometry": {"coordinates":[-2.316092,53.554573],"type":"Point"}
}