{
  "type": "Feature",
  "properties": {
    "addr:full":"Family Support Worker Town Hall, Great Georges Road Liverpool Merseyside L22 1RB",
    "addr:postcode":"l22 1rb",
    "addr:street":"Great Georges Road",
    "iso:country":"GB",
    "sg:address":"Family Support Worker Town Hall, Great Georges Road",
    "sg:city":"Liverpool",
    "sg:classifiers":[
        {
            "category":"Organizations",
            "subcategory":"Non-profit Organization",
            "type":"Services"
        }
    ],
    "sg:phone":"+44 151 928 1044",
    "sg:postcode":"L22 1RB",
    "sg:province":"Merseyside",
    "sg:tags":[
        "organisation",
        "voluntary",
        "charity"
    ],
    "wof:name":"Making Spaces",
    "wof:placetype":"venue"
},
  "geometry": {"coordinates":[-3.0252699852,53.4718513489],"type":"Point"}
}