{
  "type": "Feature",
  "properties": {
    "iso:country":"GB",
    "sg:address":"1 Park Homes",
    "sg:city":"Forfar",
    "sg:classifiers":[
        {
            "category":"Health Services",
            "subcategory":"Nursing And Care Facility",
            "type":"Services"
        },
        {
            "category":"Social Services",
            "subcategory":"Retirement Home",
            "type":"Services"
        }
    ],
    "sg:phone":"+44 1307 468656",
    "sg:postcode":"DD8 1BT",
    "sg:province":"Angus",
    "sg:tags":[
        "residential"
    ],
    "wof:name":"Ark Housing Association",
    "wof:placetype":"venue"
},
  "geometry": {"coordinates":[-2.93007,56.62722],"type":"Point"}
}