{
  "type": "Feature",
  "properties": {
    "iso:country":"GB",
    "sg:address":"20-24 South Parade",
    "sg:city":"Whitley Bay",
    "sg:classifiers":[
        {
            "category":"Social Services",
            "subcategory":"Retirement Home",
            "type":"Services"
        }
    ],
    "sg:postcode":"NE26 2RG",
    "sg:province":"Northumberland",
    "sg:tags":[
        "rest"
    ],
    "wof:name":"Brynestyn",
    "wof:placetype":"venue"
},
  "geometry": {"coordinates":[-1.443264,55.043159],"type":"Point"}
}