{
  "type": "Feature",
  "properties": {
    "iso:country":"GB",
    "sg:address":"Unit 5, Cranmere Road",
    "sg:city":"Okehampton",
    "sg:classifiers":[
        {
            "category":"Shopping",
            "subcategory":"Computers & Home Electronics",
            "type":"Retail Goods"
        }
    ],
    "sg:postcode":"EX20 1UE",
    "sg:province":"Devon",
    "sg:tags":[
        "equipment",
        "video",
        "cctv"
    ],
    "wof:name":"The C C T V Servicing Centre",
    "wof:placetype":"venue"
},
  "geometry": {"coordinates":[-3.9823689461,50.7425346375],"type":"Point"}
}