{
  "type": "Feature",
  "properties": {
    "iso:country":"GB",
    "sg:address":"6 Woolwell Crescent",
    "sg:city":"Plymouth",
    "sg:classifiers":[
        {
            "category":"Shopping",
            "subcategory":"News",
            "type":"Retail Goods"
        }
    ],
    "sg:phone":"+44 1752 791632",
    "sg:postcode":"PL6 7RB",
    "sg:province":"Devon",
    "sg:tags":[
        "newsagent"
    ],
    "wof:name":"Merretts",
    "wof:placetype":"venue"
},
  "geometry": {"coordinates":[-4.10839,50.435619],"type":"Point"}
}