{
  "type": "Feature",
  "properties": {
    "addr:full":"97 Dixons Green Road Dudley West Midlands DY2 7DJ",
    "addr:housenumber":"97",
    "addr:postcode":"dy2 7dj",
    "addr:street":"Dixons Green Road",
    "iso:country":"GB",
    "sg:address":"97 Dixons Green Road",
    "sg:city":"Dudley",
    "sg:classifiers":[
        {
            "category":"Travel",
            "subcategory":"Hotels & Motels",
            "type":"Entertainment"
        },
        {
            "category":"Travel",
            "subcategory":"Hostel",
            "type":"Entertainment"
        },
        {
            "category":"Organizations",
            "subcategory":"Non-profit Organization",
            "type":"Services"
        }
    ],
    "sg:phone":"+44 1384 237555",
    "sg:postcode":"DY2 7DJ",
    "sg:province":"West Midlands",
    "sg:tags":[
        "charitable",
        "organisation",
        "charity"
    ],
    "wof:name":"Church Housing Association For Dudley & District",
    "wof:placetype":"venue"
},
  "geometry": {"coordinates":[-2.0748,52.506199],"type":"Point"}
}