{
  "type": "Feature",
  "properties": {
    "addr:full":"114 Front Street, Arnold Nottingham Nottinghamshire NG5 7EG",
    "addr:housenumber":"114",
    "addr:postcode":"ng5 7eg",
    "addr:street":"Front Street",
    "iso:country":"GB",
    "sg:address":"114 Front Street, Arnold",
    "sg:city":"Nottingham",
    "sg:classifiers":[
        {
            "category":"Shopping",
            "subcategory":"Department Store",
            "type":"Retail Goods"
        }
    ],
    "sg:phone":"+44 115 926 3005",
    "sg:postcode":"NG5 7EG",
    "sg:province":"Nottinghamshire",
    "wof:name":"Dee's Carpets",
    "wof:placetype":"venue"
},
  "geometry": {"coordinates":[-1.1269550323,53.0047492981],"type":"Point"}
}