{
  "type": "Feature",
  "properties": {
    "addr:full":"64 Denmark Hill London Greater London SE5 8RZ",
    "addr:housenumber":"64",
    "addr:postcode":"se5 8rz",
    "addr:street":"Denmark Hill",
    "iso:country":"GB",
    "sg:address":"64 Denmark Hill",
    "sg:city":"London",
    "sg:classifiers":[
        {
            "category":"Shopping",
            "subcategory":"Department Store",
            "type":"Retail Goods"
        }
    ],
    "sg:phone":"+44 20 7737 5813",
    "sg:postcode":"SE5 8RZ",
    "sg:province":"Greater London",
    "wof:name":"E T C General Stores",
    "wof:placetype":"venue"
},
  "geometry": {"coordinates":[-0.0933429971,51.4726066589],"type":"Point"}
}