{
  "type": "Feature",
  "properties": {
    "addr:full":"26 Francis Street Wolverhampton West Midlands WV1 4RN",
    "addr:housenumber":"26",
    "addr:postcode":"wv1 4rn",
    "addr:street":"Francis Street",
    "iso:country":"GB",
    "sg:address":"26 Francis Street",
    "sg:city":"Wolverhampton",
    "sg:classifiers":[
        {
            "category":"Food & Beverages",
            "subcategory":"Candy",
            "type":"Retail Goods"
        }
    ],
    "sg:postcode":"WV1 4RN",
    "sg:province":"West Midlands",
    "sg:tags":[
        "confectioner"
    ],
    "wof:name":"Staveley Road Post Office",
    "wof:placetype":"venue"
},
  "geometry": {"coordinates":[-2.1330749989,52.5941123962],"type":"Point"}
}