{
  "type": "Feature",
  "properties": {
    "addr:full":"17 Rookery Close, Bodicote Banbury Oxfordshire OX15 4BA",
    "addr:housenumber":"17",
    "addr:postcode":"ox15 4ba",
    "addr:street":"Rookery Close",
    "iso:country":"GB",
    "sg:address":"17 Rookery Close, Bodicote",
    "sg:city":"Banbury",
    "sg:classifiers":[
        {
            "category":"Professional",
            "subcategory":"Business Services",
            "type":"Services"
        },
        {
            "category":"Government",
            "subcategory":"Post Office",
            "type":"Public Place"
        }
    ],
    "sg:phone":"+44 7860 322735",
    "sg:postcode":"OX15 4BA",
    "sg:province":"Oxfordshire",
    "sg:tags":[
        "messenger",
        "courier"
    ],
    "wof:name":"P G S Express Delivery",
    "wof:placetype":"venue"
},
  "geometry": {"coordinates":[-1.3249930143,52.035785675],"type":"Point"}
}