{
  "type": "Feature",
  "properties": {
    "addr:full":"Nelson Street, Hyde Park Industrial Estate Doncaster South Yorkshire DN4 5AD",
    "addr:housenumber":"estate",
    "addr:postcode":"dn4 5ad",
    "addr:street":"Nelson Street",
    "iso:country":"GB",
    "sg:address":"Nelson Street, Hyde Park Industrial Estate",
    "sg:city":"Doncaster",
    "sg:classifiers":[
        {
            "category":"Retail",
            "subcategory":"Auto Repair",
            "type":"Services"
        }
    ],
    "sg:phone":"+44 1302 321238",
    "sg:postcode":"DN4 5AD",
    "sg:province":"South Yorkshire",
    "sg:tags":[
        "modification",
        "garage"
    ],
    "wof:name":"Jock Sergison",
    "wof:placetype":"venue"
},
  "geometry": {"coordinates":[-1.128034,53.514397],"type":"Point"}
}