{
  "type": "Feature",
  "properties": {
    "addr:full":"14 Granada Road Southsea Hampshire PO4 0RH",
    "addr:housenumber":"14",
    "addr:postcode":"po4 0rh",
    "addr:street":"Granada Road",
    "iso:country":"GB",
    "sg:address":"14 Granada Road",
    "sg:city":"Southsea",
    "sg:classifiers":[
        {
            "category":"Fast Food",
            "type":"Food & Drink"
        }
    ],
    "sg:phone":"+44 23 9275 3504",
    "sg:postcode":"PO4 0RH",
    "sg:province":"Hampshire",
    "sg:tags":[
        "away",
        "take"
    ],
    "wof:name":"Mandarin",
    "wof:placetype":"venue"
},
  "geometry": {"coordinates":[-1.078924,50.780918],"type":"Point"}
}