{
  "type": "Feature",
  "properties": {
    "addr:full":"3 Windermere Road Chesterfield Derbyshire S41 8DU",
    "addr:housenumber":"3",
    "addr:postcode":"s41 8du",
    "addr:street":"Windermere Road",
    "iso:country":"GB",
    "sg:address":"3 Windermere Road",
    "sg:city":"Chesterfield",
    "sg:classifiers":[
        {
            "category":"Health Services",
            "subcategory":"Doctor",
            "type":"Services"
        }
    ],
    "sg:postcode":"S41 8DU",
    "sg:province":"Derbyshire",
    "sg:tags":[
        "practitioners"
    ],
    "wof:name":"Dr D Elmore",
    "wof:placetype":"venue"
},
  "geometry": {"coordinates":[-1.4482289553,53.2561683655],"type":"Point"}
}