{
  "type": "Feature",
  "properties": {
    "iso:country":"GB",
    "sg:address":"Chenoweth Garage, Ruan High Las",
    "sg:city":"Truro",
    "sg:classifiers":[
        {
            "category":"Home & Garden",
            "subcategory":"Garden Supply",
            "type":"Retail Goods"
        }
    ],
    "sg:phone":"+44 1726 891666",
    "sg:postcode":"TR2 5JT",
    "sg:province":"Cornwall",
    "sg:tags":[
        "sand",
        "gravel"
    ],
    "wof:name":"Aggregates & Minerals Ltd.",
    "wof:placetype":"venue"
},
  "geometry": {"coordinates":[-4.9420437813,50.2215957642],"type":"Point"}
}