{
  "type": "Feature",
  "properties": {
    "iso:country":"GB",
    "sg:address":"Westhead Avenue",
    "sg:city":"Liverpool",
    "sg:classifiers":[
        {
            "category":"Professional",
            "subcategory":"Lawyer & Legal Services",
            "type":"Services"
        }
    ],
    "sg:phone":"+44 151 548 0001",
    "sg:postcode":"L33 0XN",
    "sg:province":"Lancashire",
    "sg:tags":[
        "advice",
        "counselling"
    ],
    "wof:name":"Kirkby Unemployed Centre",
    "wof:placetype":"venue"
},
  "geometry": {"coordinates":[-2.880753994,53.4825515747],"type":"Point"}
}