{
  "type": "Feature",
  "properties": {
    "addr:full":"2 Recorder Road Norwich Norfolk NR1 1NR",
    "addr:housenumber":"2",
    "addr:postcode":"nr1 1nr",
    "addr:street":"Recorder Road Norwich Norfolk",
    "iso:country":"GB",
    "sg:address":"2 Recorder Road",
    "sg:city":"Norwich",
    "sg:classifiers":[
        {
            "category":"Social Services",
            "subcategory":"Job Training",
            "type":"Services"
        },
        {
            "category":"Education",
            "subcategory":"Special Training",
            "type":"Public Place"
        }
    ],
    "sg:phone":"+44 1603 619769",
    "sg:postcode":"NR1 1NR",
    "sg:province":"Norfolk",
    "sg:tags":[
        "product",
        "centre"
    ],
    "wof:name":"Pitman Training Centre Ltd",
    "wof:placetype":"venue"
},
  "geometry": {"coordinates":[1.3057080507,52.6287078857],"type":"Point"}
}