{
  "type": "Feature",
  "properties": {
    "addr:full":"13 Victoria Rd Shifnal Shropshire TF11 8AF",
    "addr:housenumber":"13",
    "addr:postcode":"tf11 8af",
    "addr:street":"Victoria Rd",
    "iso:country":"GB",
    "sg:address":"13 Victoria Rd",
    "sg:city":"Shifnal",
    "sg:classifiers":[
        {
            "category":"Home & Garden",
            "subcategory":"Kitchen Supply",
            "type":"Retail Goods"
        }
    ],
    "sg:phone":"+44 1952 463333",
    "sg:postcode":"TF11 8AF",
    "sg:province":"Shropshire",
    "sg:tags":[
        "equipment",
        "catering"
    ],
    "wof:name":"Seymour Systems Ltd",
    "wof:placetype":"venue"
},
  "geometry": {"coordinates":[-2.3742699623,52.66639328],"type":"Point"}
}