{
  "type": "Feature",
  "properties": {
    "addr:full":"139-141 Portland Road Hove East Sussex BN3 5QJ",
    "addr:housenumber":"139-141",
    "addr:postcode":"bn3 5qj",
    "addr:street":"Portland Road",
    "iso:country":"GB",
    "sg:address":"139-141 Portland Road",
    "sg:city":"Hove",
    "sg:classifiers":[
        {
            "category":"Shopping",
            "subcategory":"Florist",
            "type":"Retail Goods"
        }
    ],
    "sg:phone":"+44 1273 736949",
    "sg:postcode":"BN3 5QJ",
    "sg:province":"East Sussex",
    "wof:name":"Seymour & Dench Hove",
    "wof:placetype":"venue"
},
  "geometry": {"coordinates":[-0.1856160015,50.8334655762],"type":"Point"}
}