{
  "type": "Feature",
  "properties": {
    "addr:full":"Glenbarr Avenue Leicester Leicestershire LE4 0AE",
    "addr:postcode":"le4 0ae",
    "addr:street":"Glenbarr Avenue",
    "iso:country":"GB",
    "sg:address":"Glenbarr Avenue",
    "sg:city":"Leicester",
    "sg:classifiers":[
        {
            "category":"Manufacturing",
            "subcategory":"Textiles",
            "type":"Manufacturing & Wholesale Goods"
        }
    ],
    "sg:postcode":"LE4 0AE",
    "sg:province":"Leicestershire",
    "sg:tags":[
        "made-up"
    ],
    "wof:name":"The Midland Paper Co",
    "wof:placetype":"venue"
},
  "geometry": {"coordinates":[-1.1447839737,52.6449050903],"type":"Point"}
}