{
  "type": "Feature",
  "properties": {
    "addr:full":"54 Greenvale Drive, Timsbury Bath Somerset BA2 0HP",
    "addr:housenumber":"54",
    "addr:postcode":"ba2 0hp",
    "addr:street":"Greenvale Drive",
    "iso:country":"GB",
    "sg:address":"54 Greenvale Drive, Timsbury",
    "sg:city":"Bath",
    "sg:classifiers":[
        {
            "category":"Retail",
            "subcategory":"Driving School",
            "type":"Services"
        }
    ],
    "sg:phone":"+44 1761 471680",
    "sg:postcode":"BA2 0HP",
    "sg:province":"Somerset",
    "wof:name":"Nigel Kirby",
    "wof:placetype":"venue"
},
  "geometry": {"coordinates":[-2.479852,51.321983],"type":"Point"}
}