{
  "type": "Feature",
  "properties": {
    "addr:full":"4 Ashford Road, Topsham Exeter Devon EX3 0LA",
    "addr:housenumber":"4",
    "addr:postcode":"ex3 0la",
    "addr:street":"Ashford Road",
    "iso:country":"GB",
    "sg:address":"4 Ashford Road, Topsham",
    "sg:city":"Exeter",
    "sg:classifiers":[
        {
            "category":"Banks & Credit Unions",
            "subcategory":"Bank",
            "type":"Services"
        }
    ],
    "sg:postcode":"EX3 0LA",
    "sg:province":"Devon",
    "sg:tags":[
        "stocktaking",
        "inventory"
    ],
    "wof:name":"Isca Stocktaking Services",
    "wof:placetype":"venue"
},
  "geometry": {"coordinates":[-3.468991,50.687473],"type":"Point"}
}