{
  "type": "Feature",
  "properties": {
    "iso:country":"GB",
    "sg:address":"31 Southgate",
    "sg:city":"Chichester",
    "sg:classifiers":[
        {
            "category":"Fast Food",
            "type":"Food & Drink"
        }
    ],
    "sg:phone":"+44 1243 781613",
    "sg:postcode":"PO19 1DP",
    "sg:province":"West Sussex",
    "sg:tags":[
        "away",
        "meal",
        "outlet",
        "take"
    ],
    "wof:name":"Lucky House",
    "wof:placetype":"venue"
},
  "geometry": {"coordinates":[-0.779892,50.833431],"type":"Point"}
}