{
  "type": "Feature",
  "properties": {
    "iso:country":"GB",
    "sg:address":"51 Plane Street",
    "sg:city":"Blackburn",
    "sg:classifiers":[
        {
            "category":"Food & Beverages",
            "subcategory":"Meat & Fish",
            "type":"Retail Goods"
        },
        {
            "category":"Food & Beverages",
            "subcategory":"Groceries & Convenience Stores",
            "type":"Retail Goods"
        }
    ],
    "sg:phone":"+44 1254 675899",
    "sg:postcode":"BB1 6LR",
    "sg:province":"Lancashire",
    "sg:tags":[
        "shop",
        "chip"
    ],
    "wof:name":"K2 Taj Chippery",
    "wof:placetype":"venue"
},
  "geometry": {"coordinates":[-2.469539,53.758003],"type":"Point"}
}