{
  "type": "Feature",
  "properties": {
    "iso:country":"GB",
    "sg:address":"24 Southgate Street",
    "sg:city":"Gloucester",
    "sg:classifiers":[
        {
            "category":"Professional",
            "subcategory":"Employment Agencies",
            "type":"Services"
        }
    ],
    "sg:phone":"+44 1452 420700",
    "sg:postcode":"GL1 2DP",
    "sg:province":"Gloucestershire",
    "sg:tags":[
        "consultant",
        "recruitment"
    ],
    "sg:website":"http://www.925.co.uk",
    "wof:name":"Travail Employment Group Ltd",
    "wof:placetype":"venue"
},
  "geometry": {"coordinates":[-2.247889,51.863831],"type":"Point"}
}