{
  "type": "Feature",
  "properties": {
    "iso:country":"GB",
    "sg:address":"Bluntisham Service Station, Station Road, Bluntisham",
    "sg:city":"Huntingdon",
    "sg:classifiers":[
        {
            "category":"Autos & Motor Vehicles",
            "subcategory":"Automobile Sales",
            "type":"Retail Goods"
        }
    ],
    "sg:phone":"+44 1487 741741",
    "sg:postcode":"PE28 3PA",
    "sg:province":"Bedfordshire",
    "sg:tags":[
        "car"
    ],
    "wof:name":"Bluntisham Car Sales",
    "wof:placetype":"venue"
},
  "geometry": {"coordinates":[0.009525,52.351082],"type":"Point"}
}