{
  "type": "Feature",
  "properties": {
    "iso:country":"GB",
    "sg:address":"11 Windrush, Highworth",
    "sg:city":"Swindon",
    "sg:classifiers":[
        {
            "category":"Building & Trades",
            "subcategory":"Pest Control",
            "type":"Services"
        }
    ],
    "sg:postcode":"SN6 7DS",
    "sg:province":"Gloucestershire",
    "sg:tags":[
        "vermin"
    ],
    "wof:name":"Bryant,Rebecca,",
    "wof:placetype":"venue"
},
  "geometry": {"coordinates":[-1.7104690075,51.6376495361],"type":"Point"}
}