{
  "type": "Feature",
  "properties": {
    "addr:full":"9-10 Shardlow Road, Alvaston Derby Derbyshire DE24 0JH",
    "addr:housenumber":"9-10",
    "addr:postcode":"de24 0jh",
    "addr:street":"Shardlow Road",
    "iso:country":"GB",
    "sg:address":"9-10 Shardlow Road, Alvaston",
    "sg:city":"Derby",
    "sg:classifiers":[
        {
            "category":"Shopping",
            "subcategory":"Thrift Store",
            "type":"Retail Goods"
        }
    ],
    "sg:phone":"+44 1332 752058",
    "sg:postcode":"DE24 0JH",
    "sg:province":"Derbyshire",
    "sg:tags":[
        "shop",
        "charity"
    ],
    "wof:name":"Help The Aged",
    "wof:placetype":"venue"
},
  "geometry": {"coordinates":[-1.414809,52.88842],"type":"Point"}
}