{
  "type": "Feature",
  "properties": {
    "iso:country":"GB",
    "sg:address":"Bonnetts Lane, Ifield",
    "sg:city":"Crawley",
    "sg:classifiers":[
        {
            "category":"Transit Center",
            "subcategory":"Passenger",
            "type":"Transportation"
        },
        {
            "category":"Retail",
            "subcategory":"Pet Boarding",
            "type":"Services"
        }
    ],
    "sg:phone":"+44 845 130 0460",
    "sg:postcode":"RH11 0NY",
    "sg:province":"West Sussex",
    "sg:tags":[
        "kennel",
        "catteries"
    ],
    "sg:website":"http://www.ifield-park.co.uk",
    "wof:name":"Ifield Park Cattery & Kennels",
    "wof:placetype":"venue"
},
  "geometry": {"coordinates":[-0.2123969942,51.1333503723],"type":"Point"}
}