{
  "type": "Feature",
  "properties": {
    "iso:country":"GB",
    "sg:address":"Pontdolgoch Saw Mills, Pontdolgoch",
    "sg:city":"Caersws",
    "sg:classifiers":[
        {
            "category":"Retail",
            "subcategory":"Funeral Services",
            "type":"Services"
        }
    ],
    "sg:phone":"+44 1686 688351",
    "sg:postcode":"SY17 5NJ",
    "sg:province":"Powys",
    "wof:name":"Edward Owen & Son",
    "wof:placetype":"venue"
},
  "geometry": {"coordinates":[-3.4303290844,52.5167350769],"type":"Point"}
}