{
  "type": "Feature",
  "properties": {
    "addr:full":"School Lane, Storrington Pulborough West Sussex RH20 4LL",
    "addr:postcode":"rh20 4ll",
    "addr:street":"School Lane",
    "iso:country":"GB",
    "sg:address":"School Lane, Storrington",
    "sg:city":"Pulborough",
    "sg:classifiers":[
        {
            "category":"Government",
            "subcategory":"City Hall",
            "type":"Public Place"
        }
    ],
    "sg:postcode":"RH20 4LL",
    "sg:province":"West Sussex",
    "wof:name":"Storrington Parish Council",
    "wof:placetype":"venue"
},
  "geometry": {"coordinates":[-0.4580749869,50.916217804],"type":"Point"}
}