{
  "type": "Feature",
  "properties": {
    "addr:full":"364-366 Chorley Old Road Bolton Lancashire BL1 6AG",
    "addr:housenumber":"364-366",
    "addr:postcode":"bl1 6ag",
    "addr:street":"Chorley Old Road",
    "iso:country":"GB",
    "sg:address":"364-366 Chorley Old Road",
    "sg:city":"Bolton",
    "sg:classifiers":[
        {
            "category":"Shopping",
            "subcategory":"Clothing, Apparel, & Fashions",
            "type":"Retail Goods"
        }
    ],
    "sg:postcode":"BL1 6AG",
    "sg:province":"Lancashire",
    "sg:tags":[
        "ladieswear"
    ],
    "wof:name":"Rebecca C International",
    "wof:placetype":"venue"
},
  "geometry": {"coordinates":[-2.455327034,53.5878067017],"type":"Point"}
}