{
  "type": "Feature",
  "properties": {
    "iso:country":"GB",
    "sg:address":"7 Centre Court, The Oval, Brookfield",
    "sg:city":"Middlesbrough",
    "sg:classifiers":[
        {
            "category":"Personal",
            "subcategory":"Beauty Salon",
            "type":"Services"
        }
    ],
    "sg:phone":"+44 1642 593394",
    "sg:postcode":"TS5 8HP",
    "sg:province":"North Yorkshire",
    "sg:tags":[
        "unisex",
        "hairdresser"
    ],
    "wof:name":"Classics Hair Salon",
    "wof:placetype":"venue"
},
  "geometry": {"coordinates":[-1.2522000074,54.5315589905],"type":"Point"}
}