{
  "type": "Feature",
  "properties": {
    "iso:country":"GB",
    "sg:address":"47 Gainsborough Street",
    "sg:city":"Sudbury",
    "sg:classifiers":[
        {
            "category":"Professional",
            "subcategory":"Business Services",
            "type":"Services"
        }
    ],
    "sg:phone":"+44 1787 882171",
    "sg:postcode":"CO10 2ET",
    "sg:province":"Essex",
    "sg:tags":[
        "broker",
        "commodity"
    ],
    "wof:name":"Rossmarsh Ltd.",
    "wof:placetype":"venue"
},
  "geometry": {"coordinates":[0.728392005,52.0382461548],"type":"Point"}
}