{
  "type": "Feature",
  "properties": {
    "addr:full":"South Stack Road, South Stack Holyhead Isle of Anglesey LL65 1YH",
    "addr:postcode":"ll65 1yh",
    "addr:street":"South Stack Road South Stack Holyhead",
    "iso:country":"GB",
    "sg:address":"South Stack Road, South Stack",
    "sg:city":"Holyhead",
    "sg:classifiers":[
        {
            "category":"Restaurant",
            "type":"Food & Drink"
        }
    ],
    "sg:phone":"+44 1407 762181",
    "sg:postcode":"LL65 1YH",
    "sg:province":"Isle of Anglesey",
    "wof:name":"South Stack Kitchen",
    "wof:placetype":"venue"
},
  "geometry": {"coordinates":[-4.6416702271,53.3110466003],"type":"Point"}
}