{
  "type": "Feature",
  "properties": {
    "addr:full":"Saltergate Chesterfield Derbyshire S40 1UJ",
    "addr:postcode":"s40 1uj",
    "addr:street":"Saltergate",
    "iso:country":"GB",
    "sg:address":"Saltergate",
    "sg:city":"Chesterfield",
    "sg:classifiers":[
        {
            "category":"Parking",
            "type":"Transportation"
        }
    ],
    "sg:phone":"+44 1246 235898",
    "sg:postcode":"S40 1UJ",
    "sg:province":"Derbyshire",
    "sg:tags":[
        "car",
        "park"
    ],
    "wof:name":"Multi-Storey Car Park",
    "wof:placetype":"venue"
},
  "geometry": {"coordinates":[-1.42925,53.237572],"type":"Point"}
}