{
  "type": "Feature",
  "properties": {
    "addr:full":"The Lanes Medical Practice, Plough La Slough Berkshire SL2 4JW",
    "addr:postcode":"sl2 4jw",
    "addr:street":"La",
    "iso:country":"GB",
    "sg:address":"The Lanes Medical Practice, Plough La",
    "sg:city":"Slough",
    "sg:classifiers":[
        {
            "category":"Health Services",
            "subcategory":"Clinic",
            "type":"Services"
        }
    ],
    "sg:phone":"+44 1753 662243",
    "sg:postcode":"SL2 4JW",
    "sg:province":"Berkshire",
    "sg:tags":[
        "private"
    ],
    "wof:name":"British Airways Travel Clinic",
    "wof:placetype":"venue"
},
  "geometry": {"coordinates":[-0.57483,51.544418],"type":"Point"}
}