{
  "type": "Feature",
  "properties": {
    "addr:full":"East Hampstead Road Wokingham Berkshire RG11 2EH",
    "addr:postcode":"rg11 2eh",
    "addr:street":"East Hampstead Road",
    "iso:country":"GB",
    "sg:address":"East Hampstead Road",
    "sg:city":"Wokingham",
    "sg:classifiers":[
        {
            "category":"Cinema",
            "subcategory":"Movie Rental",
            "type":"Entertainment"
        }
    ],
    "sg:phone":"+44 118 989 0264",
    "sg:postcode":"RG11 2EH",
    "sg:province":"Berkshire",
    "sg:tags":[
        "video",
        "library"
    ],
    "wof:name":"Blockbuster Video",
    "wof:placetype":"venue"
},
  "geometry": {"coordinates":[-0.829946,51.410652],"type":"Point"}
}