{
  "type": "Feature",
  "properties": {
    "iso:country":"GB",
    "sg:address":"508 London Rd",
    "sg:city":"Thornton Heath",
    "sg:classifiers":[
        {
            "category":"Health Services",
            "subcategory":"Optometrist",
            "type":"Services"
        }
    ],
    "sg:phone":"+44 20 8683 0570",
    "sg:postcode":"CR7 7HQ",
    "sg:province":"Surrey",
    "sg:tags":[
        "optician"
    ],
    "wof:name":"Optique-Mayday",
    "wof:placetype":"venue"
},
  "geometry": {"coordinates":[-0.114491,51.39468],"type":"Point"}
}