{
  "type": "Feature",
  "properties": {
    "addr:full":"323a Lower Addiscombe Road Croydon Surrey CR0 6RF",
    "addr:housenumber":"323a",
    "addr:postcode":"cr0 6rf",
    "addr:street":"Lower Addiscombe Road",
    "iso:country":"GB",
    "sg:address":"323a Lower Addiscombe Road",
    "sg:city":"Croydon",
    "sg:classifiers":[
        {
            "category":"Utilities",
            "type":"Services"
        }
    ],
    "sg:postcode":"CR0 6RF",
    "sg:province":"Surrey",
    "sg:tags":[
        "internet"
    ],
    "wof:name":"Pathway Computers Ltd.",
    "wof:placetype":"venue"
},
  "geometry": {"coordinates":[-0.06953,51.382122],"type":"Point"}
}