{
  "type": "Feature",
  "properties": {
    "iso:country":"GB",
    "sg:address":"25 Grieves Row, Dudley",
    "sg:city":"Cramlington",
    "sg:classifiers":[
        {
            "category":"Fast Food",
            "type":"Food & Drink"
        }
    ],
    "sg:phone":"+44 191 250 0661",
    "sg:postcode":"NE23 7PX",
    "sg:province":"Northumberland",
    "sg:tags":[
        "away",
        "meal",
        "outlet",
        "take"
    ],
    "wof:name":"New Horizon Chinese Take Away",
    "wof:placetype":"venue"
},
  "geometry": {"coordinates":[-1.5933500528,55.0605964661],"type":"Point"}
}