{
  "type": "Feature",
  "properties": {
    "addr:full":"103w Aviation Park West Christchurch Dorset BH23 6NW",
    "addr:housenumber":"103w",
    "addr:postcode":"bh23 6nw",
    "addr:street":"Aviation Park",
    "iso:country":"GB",
    "sg:address":"103w Aviation Park West",
    "sg:city":"Christchurch",
    "sg:classifiers":[
        {
            "category":"Freight",
            "type":"Transportation"
        }
    ],
    "sg:phone":"+44 1202 593555",
    "sg:postcode":"BH23 6NW",
    "sg:province":"Dorset",
    "sg:tags":[
        "haulage",
        "road"
    ],
    "wof:name":"Shears Brothers (Transport) Ltd.",
    "wof:placetype":"venue"
},
  "geometry": {"coordinates":[-1.8527350426,50.7840118408],"type":"Point"}
}