{
  "type": "Feature",
  "properties": {
    "iso:country":"GB",
    "sg:address":"Railway Road",
    "sg:city":"Ilkley",
    "sg:classifiers":[
        {
            "category":"Shopping",
            "subcategory":"Department Store",
            "type":"Retail Goods"
        }
    ],
    "sg:phone":"+44 1943 602666",
    "sg:postcode":"LS29 8HA",
    "sg:province":"North Yorkshire",
    "wof:name":"Sunwin House",
    "wof:placetype":"venue"
},
  "geometry": {"coordinates":[-1.822749,53.925186],"type":"Point"}
}