{
  "type": "Feature",
  "properties": {
    "iso:country":"GB",
    "sg:address":"16 South Street",
    "sg:city":"Braunton",
    "sg:classifiers":[
        {
            "category":"Food & Beverages",
            "subcategory":"Meat & Fish",
            "type":"Retail Goods"
        }
    ],
    "sg:phone":"+44 1271 816445",
    "sg:postcode":"EX33 2AA",
    "sg:province":"Devon",
    "sg:tags":[
        "chip"
    ],
    "wof:name":"J & F Thorn",
    "wof:placetype":"venue"
},
  "geometry": {"coordinates":[-4.1484088898,51.1044845581],"type":"Point"}
}