{
  "type": "Feature",
  "properties": {
    "addr:full":"48 Tytton Lane East Boston Lincolnshire PE21 7HW",
    "addr:housenumber":"48",
    "addr:postcode":"pe21 7hw",
    "addr:street":"Tytton Lane",
    "iso:country":"GB",
    "sg:address":"48 Tytton Lane East",
    "sg:city":"Boston",
    "sg:classifiers":[
        {
            "category":"Building & Trades",
            "subcategory":"Construction",
            "type":"Services"
        }
    ],
    "sg:postcode":"PE21 7HW",
    "sg:province":"Lincolnshire",
    "sg:tags":[
        "joiner",
        "carpenter"
    ],
    "wof:name":"N J Taylor",
    "wof:placetype":"venue"
},
  "geometry": {"coordinates":[-0.0339320004,52.9579467773],"type":"Point"}
}