{
  "type": "Feature",
  "properties": {
    "iso:country":"GB",
    "sg:address":"42-44 Olivet Rd",
    "sg:city":"Sheffield",
    "sg:classifiers":[
        {
            "category":"Building & Trades",
            "subcategory":"Construction",
            "type":"Services"
        }
    ],
    "sg:phone":"+44 114 258 0578",
    "sg:postcode":"S8 8QS",
    "sg:province":"Derbyshire",
    "sg:tags":[
        "roofing"
    ],
    "wof:name":"Point To Point Roofing & Building Ltd",
    "wof:placetype":"venue"
},
  "geometry": {"coordinates":[-1.475941,53.343014],"type":"Point"}
}