{
  "type": "Feature",
  "properties": {
    "iso:country":"GB",
    "sg:address":"The Manse, East St, Crowland",
    "sg:city":"Peterborough",
    "sg:classifiers":[
        {
            "category":"Professional",
            "subcategory":"Management & Consulting",
            "type":"Services"
        }
    ],
    "sg:phone":"+44 1733 211987",
    "sg:postcode":"PE6 0EN",
    "sg:province":"Cambridgeshire",
    "sg:tags":[
        "consultant",
        "business"
    ],
    "wof:name":"Alverton & Co",
    "wof:placetype":"venue"
},
  "geometry": {"coordinates":[-0.167112,52.675121],"type":"Point"}
}