{
  "type": "Feature",
  "properties": {
    "iso:country":"GB",
    "sg:address":"C13 H R S House, Garretts Green Lane",
    "sg:city":"Birmingham",
    "sg:classifiers":[
        {
            "category":"Professional",
            "type":"Services"
        },
        {
            "category":"Fast Food",
            "type":"Food & Drink"
        }
    ],
    "sg:phone":"+44 121 604 5335",
    "sg:postcode":"B33 0UE",
    "sg:province":"West Midlands",
    "sg:tags":[
        "away",
        "take",
        "caterer"
    ],
    "wof:name":"The Real Sandwich Co",
    "wof:placetype":"venue"
},
  "geometry": {"coordinates":[-1.77943,52.473888],"type":"Point"}
}