{
  "type": "Feature",
  "properties": {
    "iso:country":"GB",
    "sg:address":"The Manse, Gold St",
    "sg:city":"Sturminster Newton",
    "sg:classifiers":[
        {
            "category":"Shopping",
            "subcategory":"Musical Instruments",
            "type":"Retail Goods"
        }
    ],
    "sg:phone":"+44 1963 362285",
    "sg:postcode":"DT10 2LX",
    "sg:province":"Dorset",
    "sg:tags":[
        "music",
        "sheet"
    ],
    "wof:name":"John Dike",
    "wof:placetype":"venue"
},
  "geometry": {"coordinates":[-2.312842,50.919811],"type":"Point"}
}