{
  "type": "Feature",
  "properties": {
    "addr:full":"10 Bedford St, Egerton Bolton Lancashire BL7 9SZ",
    "addr:housenumber":"10",
    "addr:postcode":"bl7 9sz",
    "addr:street":"Bedford St",
    "iso:country":"GB",
    "sg:address":"10 Bedford St, Egerton",
    "sg:city":"Bolton",
    "sg:classifiers":[
        {
            "category":"Personal",
            "subcategory":"Beauty Salon",
            "type":"Services"
        }
    ],
    "sg:postcode":"BL7 9SZ",
    "sg:province":"Lancashire",
    "sg:tags":[
        "unisex",
        "hairdresser"
    ],
    "wof:name":"Conway,Dominic,",
    "wof:placetype":"venue"
},
  "geometry": {"coordinates":[-2.4359910488,53.6238861084],"type":"Point"}
}