{
  "type": "Feature",
  "properties": {
    "addr:full":"Miller Farm, Outwell Road, Stow Bridge King's Lynn Lincolnshire PE34 3NT",
    "addr:postcode":"pe34 3nt",
    "addr:street":"Outwell Road",
    "iso:country":"GB",
    "sg:address":"Miller Farm, Outwell Road, Stow Bridge",
    "sg:city":"King's Lynn",
    "sg:classifiers":[
        {
            "category":"Home & Garden",
            "subcategory":"Garden Supply",
            "type":"Retail Goods"
        },
        {
            "category":"Farming",
            "subcategory":"Livestock Farm",
            "type":"Manufacturing & Wholesale Goods"
        }
    ],
    "sg:phone":"+44 1366 382472",
    "sg:postcode":"PE34 3NT",
    "sg:province":"Lincolnshire",
    "sg:tags":[
        "bulb",
        "grower",
        "others"
    ],
    "wof:name":"Jack Mervyn Bywater",
    "wof:placetype":"venue"
},
  "geometry": {"coordinates":[0.3147799969,52.6189918518],"type":"Point"}
}