{
  "type": "Feature",
  "properties": {
    "addr:full":"Masonic Hall, 57 Hardgate Haddington East Lothian EH41 3JN",
    "addr:housenumber":"57",
    "addr:postcode":"eh41 3jn",
    "addr:street":"Hardgate Haddington",
    "iso:country":"GB",
    "sg:address":"Masonic Hall, 57 Hardgate",
    "sg:city":"Haddington",
    "sg:classifiers":[
        {
            "category":"Organizations",
            "subcategory":"Community Association",
            "type":"Services"
        },
        {
            "category":"Organizations",
            "subcategory":"Membership Organization",
            "type":"Services"
        }
    ],
    "sg:phone":"+44 1620 826088",
    "sg:postcode":"EH41 3JN",
    "sg:province":"East Lothian",
    "sg:tags":[
        "club",
        "social"
    ],
    "wof:name":"Lodge St John Kilwinning 57",
    "wof:placetype":"venue"
},
  "geometry": {"coordinates":[-2.7816689014,55.9606513977],"type":"Point"}
}