{
  "type": "Feature",
  "properties": {
    "iso:country":"GB",
    "sg:address":"2 Hythe Street",
    "sg:city":"Dartford",
    "sg:classifiers":[
        {
            "category":"Real Estate",
            "subcategory":"Real Estate Agent",
            "type":"Services"
        }
    ],
    "sg:phone":"+44 1322 224436",
    "sg:postcode":"DA1 1BX",
    "sg:province":"Kent",
    "wof:name":"Halifax Property Services",
    "wof:placetype":"venue"
},
  "geometry": {"coordinates":[0.216636,51.444603],"type":"Point"}
}