{
  "type": "Feature",
  "properties": {
    "iso:country":"GB",
    "sg:address":"Middlebank, Doncaster Carr Industrial Estate",
    "sg:city":"Doncaster",
    "sg:classifiers":[
        {
            "category":"Autos & Motor Vehicles",
            "subcategory":"Automobile Sales",
            "type":"Retail Goods"
        }
    ],
    "sg:phone":"+44 1302 363544",
    "sg:postcode":"DN4 5JJ",
    "sg:province":"South Yorkshire",
    "sg:tags":[
        "car"
    ],
    "wof:name":"Doncaster Hyundai Centre",
    "wof:placetype":"venue"
},
  "geometry": {"coordinates":[-1.128379941,53.5105895996],"type":"Point"}
}