{
  "type": "Feature",
  "properties": {
    "iso:country":"GB",
    "sg:address":"Hardmannor House, Newhallhey Road",
    "sg:city":"Rossendale",
    "sg:classifiers":[
        {
            "category":"Building & Trades",
            "subcategory":"Construction",
            "type":"Services"
        }
    ],
    "sg:phone":"+44 1706 214192",
    "sg:postcode":"BB4 6HL",
    "sg:province":"Lancashire",
    "sg:tags":[
        "builder",
        "carpenter"
    ],
    "wof:name":"A & H Hargreaves",
    "wof:placetype":"venue"
},
  "geometry": {"coordinates":[-2.290951,53.698154],"type":"Point"}
}