{
  "type": "Feature",
  "properties": {
    "iso:country":"GB",
    "sg:address":"The Shop, The Street, Sutton Waldron",
    "sg:city":"Blandford Forum",
    "sg:classifiers":[
        {
            "category":"Building & Trades",
            "subcategory":"Landscaping Services",
            "type":"Services"
        }
    ],
    "sg:phone":"+44 1747 811778",
    "sg:postcode":"DT11 8NZ",
    "sg:province":"Dorset",
    "sg:tags":[
        "horticultural",
        "consultant"
    ],
    "wof:name":"Really Wild Flowers",
    "wof:placetype":"venue"
},
  "geometry": {"coordinates":[-2.194778,50.943165],"type":"Point"}
}