{
  "type": "Feature",
  "properties": {
    "addr:full":"8 Urswick Court, Tudor Grange Newcastle-upon-tyne Tyne and Wear NE3 2FN",
    "addr:housenumber":"8",
    "addr:postcode":"ne3 2fn",
    "addr:street":"Urswick Court",
    "iso:country":"GB",
    "sg:address":"8 Urswick Court, Tudor Grange",
    "sg:city":"Newcastle-upon-tyne",
    "sg:classifiers":[
        {
            "category":"Building & Trades",
            "subcategory":"Construction",
            "type":"Services"
        }
    ],
    "sg:phone":"+44 191 214 5202",
    "sg:postcode":"NE3 2FN",
    "sg:province":"Tyne and Wear",
    "sg:tags":[
        "fork",
        "lift",
        "truck"
    ],
    "wof:name":"E M B",
    "wof:placetype":"venue"
},
  "geometry": {"coordinates":[-1.6735080481,55.0103988647],"type":"Point"}
}