{
  "type": "Feature",
  "properties": {
    "iso:country":"GB",
    "sg:address":"8 Union St",
    "sg:city":"Bacup",
    "sg:classifiers":[
        {
            "category":"Manufacturing",
            "subcategory":"Tools & Machinery",
            "type":"Manufacturing & Wholesale Goods"
        }
    ],
    "sg:phone":"+44 1706 877314",
    "sg:postcode":"OL13 0AA",
    "sg:province":"Lancashire",
    "sg:tags":[
        "society",
        "friendly"
    ],
    "wof:name":"M T M Insurance Brokers Ltd",
    "wof:placetype":"venue"
},
  "geometry": {"coordinates":[-2.200189,53.702335],"type":"Point"}
}