{
  "type": "Feature",
  "properties": {
    "addr:full":"Maypole Lane, Yapton Arundel West Sussex BN18 0DP",
    "addr:postcode":"bn18 0dp",
    "addr:street":"Maypole Lane",
    "iso:country":"GB",
    "sg:address":"Maypole Lane, Yapton",
    "sg:city":"Arundel",
    "sg:classifiers":[
        {
            "category":"Bars & Pubs",
            "type":"Food & Drink"
        }
    ],
    "sg:phone":"+44 1243 551417",
    "sg:postcode":"BN18 0DP",
    "sg:province":"West Sussex",
    "sg:tags":[
        "pubs",
        "inn"
    ],
    "wof:name":"Maypole Inn",
    "wof:placetype":"venue"
},
  "geometry": {"coordinates":[-0.6105149984,50.819694519],"type":"Point"}
}