{
  "type": "Feature",
  "properties": {
    "iso:country":"GB",
    "sg:address":"2 Holt Road",
    "sg:city":"Poole",
    "sg:classifiers":[
        {
            "category":"Professional",
            "subcategory":"Art Services",
            "type":"Services"
        },
        {
            "category":"Building & Trades",
            "subcategory":"Construction",
            "type":"Services"
        }
    ],
    "sg:phone":"+44 1202 742841",
    "sg:postcode":"BH12 1JQ",
    "sg:province":"Dorset",
    "sg:tags":[
        "glazier",
        "decorator",
        "painter"
    ],
    "wof:name":"Melvin Jones",
    "wof:placetype":"venue"
},
  "geometry": {"coordinates":[-1.9174040556,50.7331695557],"type":"Point"}
}