{
  "type": "Feature",
  "properties": {
    "iso:country":"GB",
    "sg:address":"2 Town Street, Stanningley",
    "sg:city":"Pudsey",
    "sg:classifiers":[
        {
            "category":"Autos & Motor Vehicles",
            "subcategory":"Automobile Sales",
            "type":"Retail Goods"
        }
    ],
    "sg:phone":"+44 113 257 1811",
    "sg:postcode":"LS28 6LQ",
    "sg:province":"West Yorkshire",
    "sg:tags":[
        "car"
    ],
    "wof:name":"Sunwynns of Stanningley",
    "wof:placetype":"venue"
},
  "geometry": {"coordinates":[-1.657786,53.808479],"type":"Point"}
}