{
  "type": "Feature",
  "properties": {
    "addr:full":"Lower Gwerneirion Farm Llandinam Powys SY17 5DD",
    "addr:postcode":"sy17 5dd",
    "iso:country":"GB",
    "sg:address":"Lower Gwerneirion Farm",
    "sg:city":"Llandinam",
    "sg:classifiers":[
        {
            "category":"Travel",
            "subcategory":"Hotels & Motels",
            "type":"Entertainment"
        }
    ],
    "sg:postcode":"SY17 5DD",
    "sg:province":"Powys",
    "sg:tags":[
        "house",
        "guest"
    ],
    "wof:name":"Lower Gwerneirin Farm",
    "wof:placetype":"venue"
},
  "geometry": {"coordinates":[-3.4367959499,52.4833641052],"type":"Point"}
}