{
  "type": "Feature",
  "properties": {
    "addr:full":"Offwell Honiton Devon EX14 9UZ",
    "addr:housenumber":"offwell",
    "addr:postcode":"ex14 9uz",
    "iso:country":"GB",
    "sg:address":"Offwell",
    "sg:city":"Honiton",
    "sg:classifiers":[
        {
            "category":"Farming",
            "subcategory":"Livestock Farm",
            "type":"Manufacturing & Wholesale Goods"
        }
    ],
    "sg:phone":"+44 1404 43150",
    "sg:postcode":"EX14 9UZ",
    "sg:province":"Devon",
    "sg:tags":[
        "others"
    ],
    "wof:name":"Dean R J Laramy",
    "wof:placetype":"venue"
},
  "geometry": {"coordinates":[-3.143849,50.790367],"type":"Point"}
}