{
  "type": "Feature",
  "properties": {
    "addr:full":"Cansfield Street, Off Shaw Street St Helens Merseyside WA10 1EN",
    "addr:postcode":"wa10 1en",
    "addr:street":"Cansfield Street Off Shaw Street",
    "iso:country":"GB",
    "sg:address":"Cansfield Street, Off Shaw Street",
    "sg:city":"St Helens",
    "sg:classifiers":[
        {
            "category":"Retail",
            "subcategory":"Auto Repair",
            "type":"Services"
        }
    ],
    "sg:phone":"+44 1744 24967",
    "sg:postcode":"WA10 1EN",
    "sg:province":"Merseyside",
    "sg:tags":[
        "body",
        "car"
    ],
    "wof:name":"John Burns Auto Body Repairs",
    "wof:placetype":"venue"
},
  "geometry": {"coordinates":[-2.732669,53.455601],"type":"Point"}
}