{
  "type": "Feature",
  "properties": {
    "addr:full":"1 Dale Road Rotherham South Yorkshire S62 5AE",
    "addr:housenumber":"1",
    "addr:postcode":"s62 5ae",
    "addr:street":"Dale Road",
    "iso:country":"GB",
    "sg:address":"1 Dale Road",
    "sg:city":"Rotherham",
    "sg:classifiers":[
        {
            "category":"Food & Beverages",
            "subcategory":"Meat & Fish",
            "type":"Retail Goods"
        }
    ],
    "sg:phone":"+44 1709 527860",
    "sg:postcode":"S62 5AE",
    "sg:province":"South Yorkshire",
    "sg:tags":[
        "chip"
    ],
    "wof:name":"M & D Elestheriades",
    "wof:placetype":"venue"
},
  "geometry": {"coordinates":[-1.3416680098,53.4612312317],"type":"Point"}
}