{
  "type": "Feature",
  "properties": {
    "addr:full":"102 Bellshill Clo Wallsend Tyne and Wear NE28 9XF",
    "addr:housenumber":"102",
    "addr:postcode":"ne28 9xf",
    "addr:street":"Bellshill Clo",
    "iso:country":"GB",
    "sg:address":"102 Bellshill Clo",
    "sg:city":"Wallsend",
    "sg:classifiers":[
        {
            "category":"Retail",
            "subcategory":"Auto Repair",
            "type":"Services"
        }
    ],
    "sg:phone":"+44 191 262 3189",
    "sg:postcode":"NE28 9XF",
    "sg:province":"Tyne and Wear",
    "sg:tags":[
        "modification",
        "garage"
    ],
    "wof:name":"Tweedy,Eric,",
    "wof:placetype":"venue"
},
  "geometry": {"coordinates":[-1.508963,55.012798],"type":"Point"}
}