{
  "type": "Feature",
  "properties": {
    "addr:full":"16b Midworth St Mansfield Nottinghamshire NG18 1AT",
    "addr:housenumber":"16b",
    "addr:postcode":"ng18 1at",
    "addr:street":"Midworth St",
    "iso:country":"GB",
    "sg:address":"16b Midworth St",
    "sg:city":"Mansfield",
    "sg:classifiers":[
        {
            "category":"Retail",
            "subcategory":"Auto Repair",
            "type":"Services"
        }
    ],
    "sg:postcode":"NG18 1AT",
    "sg:province":"Nottinghamshire",
    "sg:tags":[
        "modification",
        "garage"
    ],
    "wof:name":"Davidson,M A,",
    "wof:placetype":"venue"
},
  "geometry": {"coordinates":[-1.1950390339,53.1426010132],"type":"Point"}
}