{
  "type": "Feature",
  "properties": {
    "addr:full":"34 St. Georges Close Wednesbury West Midlands WS10 8UU",
    "addr:housenumber":"34",
    "addr:postcode":"ws10 8uu",
    "addr:street":"St. Georges Close",
    "iso:country":"GB",
    "sg:address":"34 St. Georges Close",
    "sg:city":"Wednesbury",
    "sg:classifiers":[
        {
            "category":"Building & Trades",
            "subcategory":"Cleaning & Sanitation",
            "type":"Services"
        }
    ],
    "sg:phone":"+44 121 526 3654",
    "sg:postcode":"WS10 8UU",
    "sg:province":"West Midlands",
    "sg:tags":[
        "cleaner",
        "window"
    ],
    "wof:name":"A.D Cleaning",
    "wof:placetype":"venue"
},
  "geometry": {"coordinates":[-2.0347309113,52.5727424622],"type":"Point"}
}