{
  "type": "Feature",
  "properties": {
    "addr:full":"66 Lea Way Wellingborough Northamptonshire NN8 3NG",
    "addr:housenumber":"66",
    "addr:postcode":"nn8 3ng",
    "addr:street":"Lea Way",
    "iso:country":"GB",
    "sg:address":"66 Lea Way",
    "sg:city":"Wellingborough",
    "sg:classifiers":[
        {
            "category":"Retail",
            "subcategory":"Laundry & Dry Cleaning",
            "type":"Services"
        }
    ],
    "sg:postcode":"NN8 3NG",
    "sg:province":"Northamptonshire",
    "sg:tags":[
        "launderette"
    ],
    "wof:name":"Lea Way Launderette",
    "wof:placetype":"venue"
},
  "geometry": {"coordinates":[-0.7155910134,52.2989845276],"type":"Point"}
}