{
  "type": "Feature",
  "properties": {
    "addr:full":"20 Chapel Street, Woodhouse Sheffield South Yorkshire S13 7JN",
    "addr:housenumber":"20",
    "addr:postcode":"s13 7jn",
    "addr:street":"Chapel Street",
    "iso:country":"GB",
    "sg:address":"20 Chapel Street, Woodhouse",
    "sg:city":"Sheffield",
    "sg:classifiers":[
        {
            "category":"Manufacturing",
            "subcategory":"Metals",
            "type":"Manufacturing & Wholesale Goods"
        }
    ],
    "sg:phone":"+44 114 269 3341",
    "sg:postcode":"S13 7JN",
    "sg:province":"South Yorkshire",
    "sg:tags":[
        "steel",
        "fabricator",
        "erectors"
    ],
    "wof:name":"ANTHONY H HAMPTON",
    "wof:placetype":"venue"
},
  "geometry": {"coordinates":[-1.372386,53.359566],"type":"Point"}
}