{
  "type": "Feature",
  "properties": {
    "addr:full":"White Street, Walker Newcastle-upon-tyne Tyne and Wear NE6 3PJ",
    "addr:postcode":"ne6 3pj",
    "addr:street":"White Street",
    "iso:country":"GB",
    "sg:address":"White Street, Walker",
    "sg:city":"Newcastle-upon-tyne",
    "sg:classifiers":[
        {
            "category":"Freight",
            "type":"Transportation"
        }
    ],
    "sg:phone":"+44 191 262 9614",
    "sg:postcode":"NE6 3PJ",
    "sg:province":"Tyne and Wear",
    "sg:tags":[
        "haulage",
        "road"
    ],
    "wof:name":"Fruit & General Transport Ltd.",
    "wof:placetype":"venue"
},
  "geometry": {"coordinates":[-1.5387170315,54.9735527039],"type":"Point"}
}