{
  "type": "Feature",
  "properties": {
    "addr:full":"Unit 3, Holm Farm, Stonehouse Larkhall South Lanarkshire ML9 3PQ",
    "addr:housenumber":"unit 3",
    "addr:postcode":"ml9 3pq",
    "addr:street":"Holm Farm",
    "iso:country":"GB",
    "sg:address":"Unit 3, Holm Farm, Stonehouse",
    "sg:city":"Larkhall",
    "sg:classifiers":[
        {
            "category":"Building & Trades",
            "subcategory":"Construction",
            "type":"Services"
        }
    ],
    "sg:phone":"+44 1698 791888",
    "sg:postcode":"ML9 3PQ",
    "sg:province":"South Lanarkshire",
    "sg:tags":[
        "joiner",
        "carpenter"
    ],
    "wof:name":"Industrial Joinery",
    "wof:placetype":"venue"
},
  "geometry": {"coordinates":[-3.9690480232,55.7028999329],"type":"Point"}
}