{
  "type": "Feature",
  "properties": {
    "iso:country":"GB",
    "sg:address":"39 Catherine Street",
    "sg:city":"Salisbury",
    "sg:classifiers":[
        {
            "category":"Restaurant",
            "type":"Food & Drink"
        }
    ],
    "sg:phone":"+44 1722 326063",
    "sg:postcode":"SP1 2DH",
    "sg:province":"Wiltshire",
    "wof:name":"Chef Peking",
    "wof:placetype":"venue"
},
  "geometry": {"coordinates":[-1.79360497,51.0675697327],"type":"Point"}
}