{
  "type": "Feature",
  "properties": {
    "iso:country":"GB",
    "sg:address":"125 Liverpool Road",
    "sg:city":"Newcastle",
    "sg:classifiers":[
        {
            "category":"Home & Garden",
            "subcategory":"Home Furnishings",
            "type":"Retail Goods"
        }
    ],
    "sg:phone":"+44 1782 626429",
    "sg:postcode":"ST5 9ER",
    "sg:province":"Staffordshire",
    "sg:tags":[
        "beds",
        "bedding",
        "blanket"
    ],
    "wof:name":"Bedtime",
    "wof:placetype":"venue"
},
  "geometry": {"coordinates":[-2.230887,53.018795],"type":"Point"}
}