{
  "type": "Feature",
  "properties": {
    "addr:full":"Skate Pk, Lockoford La Chesterfield Derbyshire S41 7JB",
    "addr:postcode":"s41 7jb",
    "addr:street":"Skate;La Chesterfield",
    "iso:country":"GB",
    "sg:address":"Skate Pk, Lockoford La",
    "sg:city":"Chesterfield",
    "sg:classifiers":[
        {
            "category":"Community Center",
            "type":"Public Place"
        }
    ],
    "sg:phone":"+44 1246 231133",
    "sg:postcode":"S41 7JB",
    "sg:province":"Derbyshire",
    "sg:tags":[
        "recreation",
        "leisure",
        "centre"
    ],
    "wof:name":"Unit 1",
    "wof:placetype":"venue"
},
  "geometry": {"coordinates":[-1.4255759716,53.2509994507],"type":"Point"}
}