{
  "type": "Feature",
  "properties": {
    "addr:full":"Chester Rd Buckley Denbighshire CH7 3AQ",
    "addr:postcode":"ch7 3aq",
    "addr:street":"Chester Rd",
    "iso:country":"GB",
    "sg:address":"Chester Rd",
    "sg:city":"Buckley",
    "sg:classifiers":[
        {
            "category":"Arena",
            "subcategory":"Sports Club",
            "type":"Entertainment"
        }
    ],
    "sg:phone":"+44 1244 548868",
    "sg:postcode":"CH7 3AQ",
    "sg:province":"Denbighshire",
    "wof:name":"Buckley Cricket Club",
    "wof:placetype":"venue"
},
  "geometry": {"coordinates":[-3.066631,53.166538],"type":"Point"}
}