{
  "type": "Feature",
  "properties": {
    "addr:full":"Unit 1a Empress Park, 179 Empress Road Southampton Hampshire SO14 0JX",
    "addr:housenumber":"unit 1a;179",
    "addr:postcode":"so14 0jx",
    "addr:street":"Empress Park;Empress Road",
    "iso:country":"GB",
    "sg:address":"Unit 1a Empress Park, 179 Empress Road",
    "sg:city":"Southampton",
    "sg:classifiers":[
        {
            "category":"Manufacturing",
            "subcategory":"Metals",
            "type":"Manufacturing & Wholesale Goods"
        },
        {
            "category":"Wholesale",
            "subcategory":"Metals & Minerals",
            "type":"Manufacturing & Wholesale Goods"
        }
    ],
    "sg:phone":"+44 23 8022 3880",
    "sg:postcode":"SO14 0JX",
    "sg:province":"Hampshire",
    "sg:tags":[
        "fabricator",
        "work",
        "sheet"
    ],
    "wof:name":"S W Asgood Engineering Ltd.",
    "wof:placetype":"venue"
},
  "geometry": {"coordinates":[-1.3923200369,50.9180107117],"type":"Point"}
}