{
  "type": "Feature",
  "properties": {
    "addr:full":"Ridgewood, Woodland Grange, Fence Houses Houghton-le-spring Durham DH4 6AF",
    "addr:postcode":"dh4 6af",
    "iso:country":"GB",
    "sg:address":"Ridgewood, Woodland Grange, Fence Houses",
    "sg:city":"Houghton-le-spring",
    "sg:classifiers":[
        {
            "category":"Building & Trades",
            "subcategory":"Plumbing",
            "type":"Services"
        }
    ],
    "sg:phone":"+44 191 385 2726",
    "sg:postcode":"DH4 6AF",
    "sg:province":"Durham",
    "sg:tags":[
        "drain",
        "clearance",
        "sewer"
    ],
    "wof:name":"David Gaines Contracting",
    "wof:placetype":"venue"
},
  "geometry": {"coordinates":[-1.50911,54.846439],"type":"Point"}
}