{
  "type": "Feature",
  "properties": {
    "addr:full":"R W F House, 5 Renfield Street Glasgow Glasgow City G2 5EZ",
    "addr:housenumber":"5",
    "addr:postcode":"g2 5ez",
    "addr:street":"W;Renfield Street",
    "iso:country":"GB",
    "sg:address":"R W F House, 5 Renfield Street",
    "sg:city":"Glasgow",
    "sg:classifiers":[
        {
            "category":"Professional",
            "subcategory":"Employment Agencies",
            "type":"Services"
        }
    ],
    "sg:phone":"+44 141 221 8866",
    "sg:postcode":"G2 5EZ",
    "sg:province":"Glasgow City",
    "sg:tags":[
        "consultant"
    ],
    "wof:name":"Cavendish Partners Ltd.",
    "wof:placetype":"venue"
},
  "geometry": {"coordinates":[-4.2568688393,55.8609199524],"type":"Point"}
}