{
  "type": "Feature",
  "properties": {
    "iso:country":"GB",
    "sg:address":"Dunstable Ho, Dunstable Rd",
    "sg:city":"Luton",
    "sg:classifiers":[
        {
            "category":"Professional",
            "subcategory":"Employment Agencies",
            "type":"Services"
        }
    ],
    "sg:phone":"+44 1582 721501",
    "sg:postcode":"LU1 1EF",
    "sg:province":"Bedfordshire",
    "sg:tags":[
        "career",
        "guidance"
    ],
    "wof:name":"Naval Establishments",
    "wof:placetype":"venue"
},
  "geometry": {"coordinates":[-0.429294,51.885948],"type":"Point"}
}