{
  "type": "Feature",
  "properties": {
    "addr:full":"72-74 Ashburner Street Bolton Lancashire BL1 1TN",
    "addr:housenumber":"72-74",
    "addr:postcode":"bl1 1tn",
    "addr:street":"Ashburner Street",
    "iso:country":"GB",
    "sg:address":"72-74 Ashburner Street",
    "sg:city":"Bolton",
    "sg:classifiers":[
        {
            "category":"Organizations",
            "subcategory":"Non-profit Organization",
            "type":"Services"
        }
    ],
    "sg:phone":"+44 1204 382411",
    "sg:postcode":"BL1 1TN",
    "sg:province":"Lancashire",
    "sg:tags":[
        "organisation",
        "voluntary",
        "charity"
    ],
    "wof:name":"Age Concern England (National Council of Ageing)",
    "wof:placetype":"venue"
},
  "geometry": {"coordinates":[-2.4337830544,53.5767097473],"type":"Point"}
}