{
  "type": "Feature",
  "properties": {
    "addr:full":"Leywood House, Woodside Road Amersham Buckinghamshire HP6 6AA",
    "addr:postcode":"hp6 6aa",
    "addr:street":"Woodside Road",
    "iso:country":"GB",
    "sg:address":"Leywood House, Woodside Road",
    "sg:city":"Amersham",
    "sg:classifiers":[
        {
            "category":"Shopping",
            "subcategory":"Pharmacy",
            "type":"Retail Goods"
        }
    ],
    "sg:phone":"+44 1494 432606",
    "sg:postcode":"HP6 6AA",
    "sg:province":"Buckinghamshire",
    "sg:tags":[
        "pharmaceutical"
    ],
    "wof:name":"Galderma (U K) Ltd.",
    "wof:placetype":"venue"
},
  "geometry": {"coordinates":[-0.6045039892,51.6786651611],"type":"Point"}
}