{
  "type": "Feature",
  "properties": {
    "addr:full":"Temple Bar Farm, Wallhill Road Oldham Lancashire OL3 5BH",
    "addr:postcode":"ol3 5bh",
    "addr:street":"Wallhill Road",
    "iso:country":"GB",
    "sg:address":"Temple Bar Farm, Wallhill Road",
    "sg:city":"Oldham",
    "sg:classifiers":[
        {
            "category":"Home & Garden",
            "subcategory":"Home Furnishings",
            "type":"Retail Goods"
        }
    ],
    "sg:phone":"+44 1457 872003",
    "sg:postcode":"OL3 5BH",
    "sg:province":"Lancashire",
    "sg:tags":[
        "furnishers",
        "planner",
        "kitchen"
    ],
    "wof:name":"B Howarth",
    "wof:placetype":"venue"
},
  "geometry": {"coordinates":[-2.02805,53.55521],"type":"Point"}
}