{
  "type": "Feature",
  "properties": {
    "addr:full":"Unitek House, Oxford Road, Tatling End Gerrards Cross Buckinghamshire SL9 7BB",
    "addr:postcode":"sl9 7bb",
    "addr:street":"Oxford Road Tatling End",
    "iso:country":"GB",
    "sg:address":"Unitek House, Oxford Road, Tatling End",
    "sg:city":"Gerrards Cross",
    "sg:classifiers":[
        {
            "category":"Manufacturing",
            "subcategory":"Signs",
            "type":"Manufacturing & Wholesale Goods"
        },
        {
            "category":"Communications",
            "type":"Services"
        }
    ],
    "sg:phone":"+44 1753 890500",
    "sg:postcode":"SL9 7BB",
    "sg:province":"Buckinghamshire",
    "sg:tags":[
        "nameplate",
        "audio-visual"
    ],
    "wof:name":"Unitek Displays Ltd.",
    "wof:placetype":"venue"
},
  "geometry": {"coordinates":[-0.5311840177,51.5739135742],"type":"Point"}
}