{
  "type": "Feature",
  "properties": {
    "addr:full":"52 Battleton Dulverton Devon TA22 9HU",
    "addr:housenumber":"52",
    "addr:postcode":"ta22 9hu",
    "addr:street":"Battleton",
    "iso:country":"GB",
    "sg:address":"52 Battleton",
    "sg:city":"Dulverton",
    "sg:classifiers":[
        {
            "category":"Professional",
            "subcategory":"Engineering",
            "type":"Services"
        }
    ],
    "sg:phone":"+44 1398 323518",
    "sg:postcode":"TA22 9HU",
    "sg:province":"Devon",
    "sg:tags":[
        "contractor",
        "electrical",
        "engineer"
    ],
    "wof:name":"Alan Hobbs Electrical Services",
    "wof:placetype":"venue"
},
  "geometry": {"coordinates":[-3.5477600098,51.0339584351],"type":"Point"}
}