{
  "type": "Feature",
  "properties": {
    "addr:full":"Stonehouse Lane, Quinton Birmingham West Midlands B32 3DX",
    "addr:postcode":"b32 3dx",
    "addr:street":"Stonehouse Lane",
    "iso:country":"GB",
    "sg:address":"Stonehouse Lane, Quinton",
    "sg:city":"Birmingham",
    "sg:classifiers":[
        {
            "category":"Farming",
            "subcategory":"Nursery",
            "type":"Manufacturing & Wholesale Goods"
        }
    ],
    "sg:phone":"+44 121 427 9056",
    "sg:postcode":"B32 3DX",
    "sg:province":"West Midlands",
    "sg:tags":[
        "creche"
    ],
    "wof:name":"The First Steps Childrens Nursery",
    "wof:placetype":"venue"
},
  "geometry": {"coordinates":[-1.9750519991,52.4453926086],"type":"Point"}
}