{
  "type": "Feature",
  "properties": {
    "addr:full":"146 Brookdale Avenue South, Greasby Wirral Merseyside CH49 1SS",
    "addr:housenumber":"146",
    "addr:postcode":"ch49 1ss",
    "addr:street":"Brookdale Avenue South",
    "iso:country":"GB",
    "sg:address":"146 Brookdale Avenue South, Greasby",
    "sg:city":"Wirral",
    "sg:classifiers":[
        {
            "category":"Building & Trades",
            "subcategory":"Construction",
            "type":"Services"
        }
    ],
    "sg:postcode":"CH49 1SS",
    "sg:province":"Merseyside",
    "sg:tags":[
        "builder"
    ],
    "wof:name":"Leachim Builders",
    "wof:placetype":"venue"
},
  "geometry": {"coordinates":[-3.107467,53.375916],"type":"Point"}
}