{
  "type": "Feature",
  "properties": {
    "addr:full":"Unit 10 Castings Rd, Sir Francis Ley Indstl Est Derby Derbyshire DE23 8XA",
    "addr:housenumber":"unit 10",
    "addr:postcode":"de23 8xa",
    "addr:street":"Castings Rd Sir Francis Ley Indstl Est",
    "iso:country":"GB",
    "sg:address":"Unit 10 Castings Rd, Sir Francis Ley Indstl Est",
    "sg:city":"Derby",
    "sg:classifiers":[
        {
            "category":"Shopping",
            "subcategory":"Clothing, Apparel, & Fashions",
            "type":"Retail Goods"
        }
    ],
    "sg:postcode":"DE23 8XA",
    "sg:province":"Derbyshire",
    "sg:tags":[
        "clothing",
        "fabric"
    ],
    "wof:name":"Shergill Clothing Co  Ltd",
    "wof:placetype":"venue"
},
  "geometry": {"coordinates":[-1.4701579809,52.9017066956],"type":"Point"}
}