{
  "type": "Feature",
  "properties": {
    "iso:country":"GB",
    "sg:address":"37 Regent Street",
    "sg:city":"Shanklin",
    "sg:classifiers":[
        {
            "category":"Shopping",
            "subcategory":"Clothing, Apparel, & Fashions",
            "type":"Retail Goods"
        }
    ],
    "sg:postcode":"PO37 7AF",
    "sg:province":"Isle of Wight",
    "sg:tags":[
        "shop"
    ],
    "wof:name":"Just",
    "wof:placetype":"venue"
},
  "geometry": {"coordinates":[-1.178138,50.630779],"type":"Point"}
}