{
  "type": "Feature",
  "properties": {
    "addr:full":"57 London Road, Stockton Heath Warrington Cheshire WA4 6SG",
    "addr:housenumber":"57",
    "addr:postcode":"wa4 6sg",
    "addr:street":"London Road",
    "iso:country":"GB",
    "sg:address":"57 London Road, Stockton Heath",
    "sg:city":"Warrington",
    "sg:classifiers":[
        {
            "category":"Food & Beverages",
            "subcategory":"Bakery",
            "type":"Retail Goods"
        }
    ],
    "sg:phone":"+44 1925 262532",
    "sg:postcode":"WA4 6SG",
    "sg:province":"Cheshire",
    "sg:tags":[
        "baker"
    ],
    "wof:name":"Waterfield",
    "wof:placetype":"venue"
},
  "geometry": {"coordinates":[-2.5814499855,53.372089386],"type":"Point"}
}