{
  "type": "Feature",
  "properties": {
    "iso:country":"GB",
    "sg:address":"49a High Street",
    "sg:city":"Broseley",
    "sg:classifiers":[
        {
            "category":"Food & Beverages",
            "subcategory":"Fruits & Vegetables",
            "type":"Retail Goods"
        }
    ],
    "sg:postcode":"TF12 5EZ",
    "sg:province":"Shropshire",
    "sg:tags":[
        "greengrocer"
    ],
    "wof:name":"Downes Greengrocers",
    "wof:placetype":"venue"
},
  "geometry": {"coordinates":[-2.483361,52.613476],"type":"Point"}
}