{
  "type": "Feature",
  "properties": {
    "addr:full":"21 Hawkhurst Road, Maypole Birmingham West Midlands B14 5HS",
    "addr:housenumber":"21",
    "addr:postcode":"b14 5hs",
    "addr:street":"Hawkhurst Road",
    "iso:country":"GB",
    "sg:address":"21 Hawkhurst Road, Maypole",
    "sg:city":"Birmingham",
    "sg:classifiers":[
        {
            "category":"Professional",
            "type":"Services"
        }
    ],
    "sg:postcode":"B14 5HS",
    "sg:province":"West Midlands",
    "sg:tags":[
        "entertainer"
    ],
    "wof:name":"Abracadabra It's Magic",
    "wof:placetype":"venue"
},
  "geometry": {"coordinates":[-1.8871860504,52.4069976807],"type":"Point"}
}