{
  "type": "Feature",
  "properties": {
    "addr:full":"Croston Road, Leyland Preston Lancashire PR26 6LZ",
    "addr:postcode":"pr26 6lz",
    "addr:street":"Croston Road",
    "iso:country":"GB",
    "sg:address":"Croston Road, Leyland",
    "sg:city":"Preston",
    "sg:classifiers":[
        {
            "category":"Autos & Motor Vehicles",
            "subcategory":"Automobile Sales",
            "type":"Retail Goods"
        },
        {
            "category":"Manufacturing",
            "subcategory":"Motor Vehicles & Parts",
            "type":"Manufacturing & Wholesale Goods"
        }
    ],
    "sg:phone":"+44 1772 621400",
    "sg:postcode":"PR26 6LZ",
    "sg:province":"Lancashire",
    "sg:tags":[
        "commercial",
        "van",
        "truck",
        "manufacturer"
    ],
    "sg:website":"http://www.leyland-trucks.co.uk",
    "wof:name":"Leyland Trucks Ltd",
    "wof:placetype":"venue"
},
  "geometry": {"coordinates":[-2.7015590668,53.718044281],"type":"Point"}
}