{
  "type": "Feature",
  "properties": {
    "iso:country":"GB",
    "sg:address":"81 Kings Road",
    "sg:city":"Reading",
    "sg:classifiers":[
        {
            "category":"Building & Trades",
            "subcategory":"Construction",
            "type":"Services"
        },
        {
            "category":"Organizations",
            "subcategory":"Professional Association",
            "type":"Services"
        }
    ],
    "sg:phone":"+44 118 959 4128",
    "sg:postcode":"RG1 3DD",
    "sg:province":"Berkshire",
    "sg:tags":[
        "union",
        "activity"
    ],
    "wof:name":"Gmb",
    "wof:placetype":"venue"
},
  "geometry": {"coordinates":[-0.96410501,51.4549255371],"type":"Point"}
}