{
  "type": "Feature",
  "properties": {
    "addr:full":"36 Heol-y-nant, Clydach Swansea Swansea SA6 5HB",
    "addr:housenumber":"36",
    "addr:postcode":"sa6 5hb",
    "addr:street":"Heol-Y-Nant Clydach",
    "iso:country":"GB",
    "sg:address":"36 Heol-y-nant, Clydach",
    "sg:city":"Swansea",
    "sg:classifiers":[
        {
            "category":"Retail",
            "subcategory":"Funeral Services",
            "type":"Services"
        }
    ],
    "sg:phone":"+44 1792 843373",
    "sg:postcode":"SA6 5HB",
    "sg:province":"Swansea",
    "wof:name":"Brian E Duggan & Sons",
    "wof:placetype":"venue"
},
  "geometry": {"coordinates":[-3.891829,51.69585],"type":"Point"}
}