{
  "type": "Feature",
  "properties": {
    "addr:full":"44 Lozells Rd Birmingham West Midlands B19 2TH",
    "addr:housenumber":"44;b19",
    "addr:postcode":"2th",
    "addr:street":"Lozells Rd",
    "iso:country":"GB",
    "sg:address":"44 Lozells Rd",
    "sg:city":"Birmingham",
    "sg:classifiers":[
        {
            "category":"Retail",
            "subcategory":"Storage",
            "type":"Services"
        }
    ],
    "sg:phone":"+44 121 523 8875",
    "sg:postcode":"B19 2TH",
    "sg:province":"West Midlands",
    "sg:tags":[
        "household",
        "removal"
    ],
    "wof:name":"Aston Removals",
    "wof:placetype":"venue"
},
  "geometry": {"coordinates":[-1.9017169476,52.5024681091],"type":"Point"}
}