{
  "type": "Feature",
  "properties": {
    "addr:full":"27 High Street, Theale Reading Berkshire RG7 5AH",
    "addr:housenumber":"27",
    "addr:postcode":"rg7 5ah",
    "addr:street":"High Street",
    "iso:country":"GB",
    "sg:address":"27 High Street, Theale",
    "sg:city":"Reading",
    "sg:classifiers":[
        {
            "category":"Shopping",
            "subcategory":"Pharmacy",
            "type":"Retail Goods"
        }
    ],
    "sg:phone":"+44 118 930 2542",
    "sg:postcode":"RG7 5AH",
    "sg:province":"Berkshire",
    "sg:tags":[
        "pharmacist",
        "store",
        "drug",
        "chemist"
    ],
    "wof:name":"Theale Pharmacy",
    "wof:placetype":"venue"
},
  "geometry": {"coordinates":[-1.075168,51.437729],"type":"Point"}
}