{
  "type": "Feature",
  "properties": {
    "addr:full":"10 Howland House, Leigham Avenue London Greater London SW16 2TG",
    "addr:housenumber":"10",
    "addr:postcode":"sw16 2tg",
    "addr:street":"Howland House Leigham Avenue",
    "iso:country":"GB",
    "sg:address":"10 Howland House, Leigham Avenue",
    "sg:city":"London",
    "sg:classifiers":[
        {
            "category":"Communications",
            "type":"Services"
        }
    ],
    "sg:postcode":"SW16 2TG",
    "sg:province":"Greater London",
    "sg:tags":[
        "audio-visual"
    ],
    "wof:name":"Latv Production Ltd",
    "wof:placetype":"venue"
},
  "geometry": {"coordinates":[-0.12611,51.433861],"type":"Point"}
}