{
  "type": "Feature",
  "properties": {
    "addr:full":"The Old Slaughter Ho Carterton Gloucestershire OX18 3AD",
    "addr:postcode":"ox18 3ad",
    "iso:country":"GB",
    "sg:address":"The Old Slaughter Ho",
    "sg:city":"Carterton",
    "sg:classifiers":[
        {
            "category":"Health Services",
            "subcategory":"Dentist",
            "type":"Services"
        }
    ],
    "sg:phone":"+44 1993 850095",
    "sg:postcode":"OX18 3AD",
    "sg:province":"Gloucestershire",
    "wof:name":"A P Sykes",
    "wof:placetype":"venue"
},
  "geometry": {"coordinates":[-1.5903840065,51.7606239319],"type":"Point"}
}