{
  "type": "Feature",
  "properties": {
    "iso:country":"GB",
    "sg:address":"Gemini House, Bartholomues Walk",
    "sg:city":"Ely",
    "sg:classifiers":[
        {
            "category":"Government",
            "subcategory":"Post Office",
            "type":"Public Place"
        }
    ],
    "sg:phone":"+44 1353 668339",
    "sg:postcode":"CB7 4EA",
    "sg:province":"Cambridgeshire",
    "sg:tags":[
        "organisation",
        "soc",
        "research"
    ],
    "wof:name":"Harrison Clinical Research Ltd.",
    "wof:placetype":"venue"
},
  "geometry": {"coordinates":[0.2621450126,52.3900146484],"type":"Point"}
}