{
  "type": "Feature",
  "properties": {
    "addr:full":"21 Market Street Wotton-under-edge Gloucestershire GL12 7AE",
    "addr:housenumber":"21",
    "addr:postcode":"gl12 7ae",
    "addr:street":"Market Street",
    "iso:country":"GB",
    "sg:address":"21 Market Street",
    "sg:city":"Wotton-under-edge",
    "sg:classifiers":[
        {
            "category":"Bars & Pubs",
            "type":"Food & Drink"
        }
    ],
    "sg:phone":"+44 1453 844651",
    "sg:postcode":"GL12 7AE",
    "sg:province":"Gloucestershire",
    "sg:tags":[
        "pubs",
        "inn"
    ],
    "wof:name":"Star Inn",
    "wof:placetype":"venue"
},
  "geometry": {"coordinates":[-2.353909,51.63699],"type":"Point"}
}