{
  "type": "Feature",
  "properties": {
    "addr:full":"Cleveland Road North Shields Tyne and Wear NE29 0NW",
    "addr:postcode":"ne29 0nw",
    "addr:street":"Cleveland Road",
    "iso:country":"GB",
    "sg:address":"Cleveland Road",
    "sg:city":"North Shields",
    "sg:classifiers":[
        {
            "category":"Health Services",
            "subcategory":"Nursing And Care Facility",
            "type":"Services"
        }
    ],
    "sg:phone":"+44 191 258 5500",
    "sg:postcode":"NE29 0NW",
    "sg:province":"Tyne and Wear",
    "sg:tags":[
        "home"
    ],
    "wof:name":"Cleveland Park Nursing Home",
    "wof:placetype":"venue"
},
  "geometry": {"coordinates":[-1.450349,55.01321],"type":"Point"}
}