{
  "type": "Feature",
  "properties": {
    "addr:full":"Unit 14 Bassington Industrial Estate Cramlington Northumberland NE23 8AD",
    "addr:housenumber":"unit 14",
    "addr:postcode":"ne23 8ad",
    "addr:street":"Bassington Industrial Estate;Northumberland",
    "iso:country":"GB",
    "sg:address":"Unit 14 Bassington Industrial Estate",
    "sg:city":"Cramlington",
    "sg:classifiers":[
        {
            "category":"Home & Garden",
            "subcategory":"Building Materials",
            "type":"Retail Goods"
        }
    ],
    "sg:phone":"+44 1670 737645",
    "sg:postcode":"NE23 8AD",
    "sg:province":"Northumberland",
    "sg:tags":[
        "gate",
        "door",
        "barrier"
    ],
    "wof:name":"Bft Northern",
    "wof:placetype":"venue"
},
  "geometry": {"coordinates":[-1.6165989637,55.0921669006],"type":"Point"}
}