{
  "type": "Feature",
  "properties": {
    "iso:country":"GB",
    "sg:address":"3a Marsh Lane",
    "sg:city":"Lowestoft",
    "sg:classifiers":[
        {
            "category":"Building & Trades",
            "subcategory":"Construction",
            "type":"Services"
        }
    ],
    "sg:phone":"+44 1502 516123",
    "sg:postcode":"NR33 8BW",
    "sg:province":"Suffolk",
    "sg:tags":[
        "builder"
    ],
    "wof:name":"Kirvy & Godbold",
    "wof:placetype":"venue"
},
  "geometry": {"coordinates":[1.6851719618,52.4574890137],"type":"Point"}
}