{
  "type": "Feature",
  "properties": {
    "iso:country":"GB",
    "sg:address":"Lee Mill Bridge, Lee Mill",
    "sg:city":"Ivybridge",
    "sg:classifiers":[
        {
            "category":"Wholesale",
            "subcategory":"Chemicals & Plastics",
            "type":"Manufacturing & Wholesale Goods"
        }
    ],
    "sg:phone":"+44 1752 893142",
    "sg:postcode":"PL21 9EF",
    "sg:province":"Devon",
    "sg:tags":[
        "retail",
        "freezer",
        "refrigerator"
    ],
    "wof:name":"P L Bowker & Co. Ltd.",
    "wof:placetype":"venue"
},
  "geometry": {"coordinates":[-3.97279,50.384739],"type":"Point"}
}