{
  "type": "Feature",
  "properties": {
    "iso:country":"GB",
    "sg:address":"14-16 Portland Road",
    "sg:city":"Worthing",
    "sg:classifiers":[
        {
            "category":"Shopping",
            "subcategory":"Clothing, Apparel, & Fashions",
            "type":"Retail Goods"
        }
    ],
    "sg:phone":"+44 1903 210397",
    "sg:postcode":"BN11 1QN",
    "sg:province":"West Sussex",
    "sg:tags":[
        "shop"
    ],
    "wof:name":"Q S Plc",
    "wof:placetype":"venue"
},
  "geometry": {"coordinates":[-0.3726679981,50.8104362488],"type":"Point"}
}