{
  "type": "Feature",
  "properties": {
    "iso:country":"GB",
    "sg:address":"53 Hawcliffe Road, Mountsorrel",
    "sg:city":"Loughborough",
    "sg:classifiers":[
        {
            "category":"Transit Center",
            "subcategory":"Passenger",
            "type":"Transportation"
        }
    ],
    "sg:postcode":"LE12 7AQ",
    "sg:province":"Leicestershire",
    "sg:tags":[
        "boarding",
        "kennel",
        "catteries"
    ],
    "wof:name":"Woo's Willow Cattery",
    "wof:placetype":"venue"
},
  "geometry": {"coordinates":[-1.1521680355,52.7335777283],"type":"Point"}
}