{
  "type": "Feature",
  "properties": {
    "addr:full":"Oxford Street, Millbrook Stalybridge Greater Manchester SK15 3JJ",
    "addr:postcode":"sk15 3jj",
    "addr:street":"Oxford Street",
    "iso:country":"GB",
    "sg:address":"Oxford Street, Millbrook",
    "sg:city":"Stalybridge",
    "sg:classifiers":[
        {
            "category":"Arena",
            "subcategory":"Sports Club",
            "type":"Entertainment"
        }
    ],
    "sg:phone":"+44 161 338 5298",
    "sg:postcode":"SK15 3JJ",
    "sg:province":"Greater Manchester",
    "wof:name":"Staley Millbrook Cricket Club",
    "wof:placetype":"venue"
},
  "geometry": {"coordinates":[-2.0316040516,53.4948616028],"type":"Point"}
}