{
  "type": "Feature",
  "properties": {
    "iso:country":"GB",
    "sg:address":"L15a The Merry Hill Centre",
    "sg:city":"Brierley Hill",
    "sg:classifiers":[
        {
            "category":"Recreation",
            "subcategory":"Amusement Park",
            "type":"Entertainment"
        },
        {
            "category":"Recreation",
            "subcategory":"Dance Hall",
            "type":"Entertainment"
        }
    ],
    "sg:phone":"+44 1384 79379",
    "sg:postcode":"DY5 1SY",
    "sg:province":"West Midlands",
    "sg:tags":[
        "bingo",
        "arcade"
    ],
    "wof:name":"Shipleys Amusements Centre",
    "wof:placetype":"venue"
},
  "geometry": {"coordinates":[-2.1114099026,52.4777984619],"type":"Point"}
}