{
  "type": "Feature",
  "properties": {
    "addr:full":"24 Cosheston Road Cardiff Cardiff CF5 3NR",
    "addr:housenumber":"24",
    "addr:postcode":"cf5 3nr",
    "addr:street":"Cosheston Road",
    "iso:country":"GB",
    "sg:address":"24 Cosheston Road",
    "sg:city":"Cardiff",
    "sg:classifiers":[
        {
            "category":"Home & Garden",
            "subcategory":"Carpets & Floor Coverings",
            "type":"Retail Goods"
        }
    ],
    "sg:phone":"+44 29 2079 8047",
    "sg:postcode":"CF5 3NR",
    "sg:province":"Cardiff",
    "sg:tags":[
        "wall",
        "tie",
        "replacement"
    ],
    "wof:name":"Drum Structural Services",
    "wof:placetype":"venue"
},
  "geometry": {"coordinates":[-3.2419939041,51.4987297058],"type":"Point"}
}