{
  "type": "Feature",
  "properties": {
    "addr:full":"58 Union Street Ryde Isle of Wight PO33 2LG",
    "addr:housenumber":"58",
    "addr:postcode":"po33 2lg",
    "addr:street":"Union Street",
    "iso:country":"GB",
    "sg:address":"58 Union Street",
    "sg:city":"Ryde",
    "sg:classifiers":[
        {
            "category":"Shopping",
            "subcategory":"Clothing, Apparel, & Fashions",
            "type":"Retail Goods"
        }
    ],
    "sg:phone":"+44 1983 615464",
    "sg:postcode":"PO33 2LG",
    "sg:province":"Isle of Wight",
    "sg:tags":[
        "shop"
    ],
    "wof:name":"Gladrags",
    "wof:placetype":"venue"
},
  "geometry": {"coordinates":[-1.162104,50.731388],"type":"Point"}
}