{
  "type": "Feature",
  "properties": {
    "addr:full":"9 Edleston Grove Wilmslow Cheshire SK9 2PB",
    "addr:housenumber":"9",
    "addr:postcode":"sk9 2pb",
    "addr:street":"Edleston Grove",
    "iso:country":"GB",
    "sg:address":"9 Edleston Grove",
    "sg:city":"Wilmslow",
    "sg:classifiers":[
        {
            "category":"Military Area",
            "subcategory":"Air Force Base",
            "type":"Public Place"
        }
    ],
    "sg:phone":"+44 1625 539012",
    "sg:postcode":"SK9 2PB",
    "sg:province":"Cheshire",
    "sg:tags":[
        "taxi",
        "hire",
        "private"
    ],
    "wof:name":"R-tax Taxis",
    "wof:placetype":"venue"
},
  "geometry": {"coordinates":[-2.208036,53.338177],"type":"Point"}
}