{
  "type": "Feature",
  "properties": {
    "addr:full":"Mill Lane, Tottington Rd Bury Lancashire BL8 1TB",
    "addr:postcode":"bl8 1tb",
    "addr:street":"Mill Lane Tottington Rd",
    "iso:country":"GB",
    "sg:address":"Mill Lane, Tottington Rd",
    "sg:city":"Bury",
    "sg:classifiers":[
        {
            "category":"Health Services",
            "subcategory":"Dentist",
            "type":"Services"
        }
    ],
    "sg:phone":"+44 161 797 5621",
    "sg:postcode":"BL8 1TB",
    "sg:province":"Lancashire",
    "sg:tags":[
        "technician",
        "instrument",
        "dental"
    ],
    "wof:name":"Filippini & Gray",
    "wof:placetype":"venue"
},
  "geometry": {"coordinates":[-2.320694,53.602566],"type":"Point"}
}