{
  "type": "Feature",
  "properties": {
    "iso:country":"GB",
    "sg:address":"Maple Heys Hall, Abnalls Lane",
    "sg:city":"Lichfield",
    "sg:classifiers":[
        {
            "category":"Education",
            "subcategory":"School",
            "type":"Public Place"
        }
    ],
    "sg:phone":"+44 1543 264387",
    "sg:postcode":"WS13 8BL",
    "sg:province":"Staffordshire",
    "sg:tags":[
        "independent",
        "preparatory"
    ],
    "wof:name":"Maples Hayes Dyslexia School",
    "wof:placetype":"venue"
},
  "geometry": {"coordinates":[-1.81966,52.684029],"type":"Point"}
}