{
  "type": "Feature",
  "properties": {
    "addr:full":"Deavalls Farm, Hawks Green Lane Cannock Staffordshire WS11 2LP",
    "addr:postcode":"ws11 2lp",
    "addr:street":"Hawks Green Lane",
    "iso:country":"GB",
    "sg:address":"Deavalls Farm, Hawks Green Lane",
    "sg:city":"Cannock",
    "sg:classifiers":[
        {
            "category":"Government",
            "subcategory":"Office",
            "type":"Public Place"
        }
    ],
    "sg:phone":"+44 1543 450018",
    "sg:postcode":"WS11 2LP",
    "sg:province":"Staffordshire",
    "sg:tags":[
        "local"
    ],
    "wof:name":"Cannock Chase District Rangers",
    "wof:placetype":"venue"
},
  "geometry": {"coordinates":[-2.0331449509,52.690952301],"type":"Point"}
}