{
  "type": "Feature",
  "properties": {
    "addr:full":"Crown Park, Caroline Street Llanelli Carmarthenshire SA15 2PB",
    "addr:postcode":"sa15 2pb",
    "addr:street":"Crown Park Caroline Street",
    "iso:country":"GB",
    "sg:address":"Crown Park, Caroline Street",
    "sg:city":"Llanelli",
    "sg:classifiers":[
        {
            "category":"Arena",
            "subcategory":"Sports Club",
            "type":"Entertainment"
        }
    ],
    "sg:postcode":"SA15 2PB",
    "sg:province":"Carmarthenshire",
    "wof:name":"South Llanelli Cricket Club",
    "wof:placetype":"venue"
},
  "geometry": {"coordinates":[-4.1342988014,51.6826820374],"type":"Point"}
}