{
  "type": "Feature",
  "properties": {
    "addr:full":"Club House, Langford Road Biggleswade Bedfordshire SG18 9RA",
    "addr:postcode":"sg18 9ra",
    "addr:street":"Club;Langford Road",
    "iso:country":"GB",
    "sg:address":"Club House, Langford Road",
    "sg:city":"Biggleswade",
    "sg:classifiers":[
        {
            "category":"Arena",
            "subcategory":"Sports Club",
            "type":"Entertainment"
        }
    ],
    "sg:phone":"+44 1767 312463",
    "sg:postcode":"SG18 9RA",
    "sg:province":"Bedfordshire",
    "wof:name":"Biggleswade Rugby & Squash Club",
    "wof:placetype":"venue"
},
  "geometry": {"coordinates":[-0.2665289938,52.0730209351],"type":"Point"}
}