{
  "type": "Feature",
  "properties": {
    "addr:full":"Spring Croft Well Hill Orpington Kent BR6 7PR",
    "addr:postcode":"br6 7pr",
    "addr:street":"Spring Croft Well Hill Orpington",
    "iso:country":"GB",
    "sg:address":"Spring Croft Well Hill",
    "sg:city":"Orpington",
    "sg:classifiers":[
        {
            "category":"Banks & Credit Unions",
            "subcategory":"Financial Services",
            "type":"Services"
        }
    ],
    "sg:phone":"+44 1959 532500",
    "sg:postcode":"BR6 7PR",
    "sg:province":"Kent",
    "sg:tags":[
        "claim",
        "assessor"
    ],
    "wof:name":"G J G Assessor",
    "wof:placetype":"venue"
},
  "geometry": {"coordinates":[0.1010800004,51.3780403137],"type":"Point"}
}