{
  "type": "Feature",
  "properties": {
    "iso:country":"GB",
    "sg:address":"21 Diss Business Centre, Dark Lane, Scole",
    "sg:city":"Diss",
    "sg:classifiers":[
        {
            "category":"Professional",
            "subcategory":"Lawyer & Legal Services",
            "type":"Services"
        }
    ],
    "sg:phone":"+44 1379 644311",
    "sg:postcode":"IP21 4HD",
    "sg:province":"Norfolk",
    "sg:tags":[
        "solicitor"
    ],
    "wof:name":"Ian Comer Injury Claims Specilaists",
    "wof:placetype":"venue"
},
  "geometry": {"coordinates":[1.153705,52.365952],"type":"Point"}
}