{
  "type": "Feature",
  "properties": {
    "addr:full":"54 Broadway Leigh-on-sea Essex SS9 1AQ",
    "addr:housenumber":"54",
    "addr:postcode":"ss9 1aq",
    "addr:street":"Broadway",
    "iso:country":"GB",
    "sg:address":"54 Broadway",
    "sg:city":"Leigh-on-sea",
    "sg:classifiers":[
        {
            "category":"Real Estate",
            "subcategory":"Surveying",
            "type":"Services"
        }
    ],
    "sg:phone":"+44 1702 470055",
    "sg:postcode":"SS9 1AQ",
    "sg:province":"Essex",
    "sg:tags":[
        "surveyor",
        "valuer"
    ],
    "wof:name":"Fredk G Hair & Son",
    "wof:placetype":"venue"
},
  "geometry": {"coordinates":[0.6581540108,51.5414085388],"type":"Point"}
}