{
  "type": "Feature",
  "properties": {
    "addr:full":"Control Horndon Industrial Park, West Horndon Brentwood Essex CM13 3XE",
    "addr:postcode":"cm13 3xe",
    "addr:street":"Industrial Park;Horndon",
    "iso:country":"GB",
    "sg:address":"Control Horndon Industrial Park, West Horndon",
    "sg:city":"Brentwood",
    "sg:classifiers":[
        {
            "category":"Sports & Exercise",
            "subcategory":"Tennis Court",
            "type":"Entertainment"
        }
    ],
    "sg:phone":"+44 1277 812182",
    "sg:postcode":"CM13 3XE",
    "sg:province":"Essex",
    "sg:tags":[
        "breakdown",
        "recovery"
    ],
    "wof:name":"Ontime (Service Garage) Rescue & Recover",
    "wof:placetype":"venue"
},
  "geometry": {"coordinates":[0.3428199887,51.5689239502],"type":"Point"}
}