{
  "type": "Feature",
  "properties": {
    "addr:full":"Pitt St West Stoke-on-trent Staffordshire ST6 3JW",
    "addr:postcode":"staffordshire st6 3jw",
    "addr:street":"Pitt St",
    "iso:country":"GB",
    "sg:address":"Pitt St West",
    "sg:city":"Stoke-on-trent",
    "sg:classifiers":[
        {
            "category":"Bars & Pubs",
            "type":"Food & Drink"
        }
    ],
    "sg:postcode":"ST6 3JW",
    "sg:province":"Staffordshire",
    "sg:tags":[
        "pubs",
        "inn"
    ],
    "wof:name":"The Mitre",
    "wof:placetype":"venue"
},
  "geometry": {"coordinates":[-2.1945440769,53.0427093506],"type":"Point"}
}