{
  "type": "Feature",
  "properties": {
    "iso:country":"GB",
    "sg:address":"Bongate",
    "sg:city":"Appleby-in-westmorland",
    "sg:classifiers":[
        {
            "category":"Travel",
            "subcategory":"Hotels & Motels",
            "type":"Entertainment"
        }
    ],
    "sg:postcode":"CA16 6UE",
    "sg:province":"Cumbria",
    "sg:tags":[
        "house",
        "guest"
    ],
    "wof:name":"Bongate House",
    "wof:placetype":"venue"
},
  "geometry": {"coordinates":[-2.4844579697,54.5764389038],"type":"Point"}
}