{
  "type": "Feature",
  "properties": {
    "addr:full":"Horton House, Atlantic Court, Exchange Flags Liverpool Merseyside L2 3YL",
    "addr:postcode":"l2 3yl",
    "addr:street":"Atlantic Court",
    "iso:country":"GB",
    "sg:address":"Horton House, Atlantic Court, Exchange Flags",
    "sg:city":"Liverpool",
    "sg:classifiers":[
        {
            "category":"Real Estate",
            "subcategory":"Developer",
            "type":"Services"
        }
    ],
    "sg:phone":"+44 151 236 6915",
    "sg:postcode":"L2 3YL",
    "sg:province":"Merseyside",
    "sg:tags":[
        "property"
    ],
    "wof:name":"Walton Group Plc",
    "wof:placetype":"venue"
},
  "geometry": {"coordinates":[-2.992254,53.40736],"type":"Point"}
}