{
  "type": "Feature",
  "properties": {
    "addr:full":"Ecl House, Lake Street Leighton Buzzard Bedfordshire LU7 1RT",
    "addr:postcode":"lu7 1rt",
    "addr:street":"Lake Street",
    "iso:country":"GB",
    "sg:address":"Ecl House, Lake Street",
    "sg:city":"Leighton Buzzard",
    "sg:classifiers":[
        {
            "category":"Organizations",
            "subcategory":"Membership Organization",
            "type":"Services"
        }
    ],
    "sg:postcode":"LU7 1RT",
    "sg:province":"Bedfordshire",
    "sg:tags":[
        "club"
    ],
    "wof:name":"Cotsmoor Management Co  Ltd",
    "wof:placetype":"venue"
},
  "geometry": {"coordinates":[-0.658915,51.915291],"type":"Point"}
}