{
  "type": "Feature",
  "properties": {
    "iso:country":"GB",
    "sg:address":"3a Bridge Street",
    "sg:city":"Horncastle",
    "sg:classifiers":[
        {
            "category":"Autos & Motor Vehicles",
            "subcategory":"Auto Supplies",
            "type":"Retail Goods"
        },
        {
            "category":"Shopping",
            "type":"Retail Goods"
        }
    ],
    "sg:phone":"+44 1507 527644",
    "sg:postcode":"LN9 5HZ",
    "sg:province":"Lincolnshire",
    "sg:tags":[
        "car",
        "part",
        "accessory"
    ],
    "wof:name":"Motor Accessories Horncastle",
    "wof:placetype":"venue"
},
  "geometry": {"coordinates":[-0.117205,53.208652],"type":"Point"}
}