{
  "type": "Feature",
  "properties": {
    "iso:country":"GB",
    "sg:address":"Vicarage, 28 Buxton Rd",
    "sg:city":"Stockport",
    "sg:classifiers":[
        {
            "category":"Place Of Worship",
            "type":"Public Place"
        }
    ],
    "sg:phone":"+44 161 480 2453",
    "sg:postcode":"SK2 6NU",
    "sg:province":"Cheshire",
    "wof:name":"St Georges C of E Church",
    "wof:placetype":"venue"
},
  "geometry": {"coordinates":[-2.1524500847,53.398109436],"type":"Point"}
}