{
  "type": "Feature",
  "properties": {
    "addr:full":"16 Kingswood Terrace Bradford West Yorkshire BD7 3DT",
    "addr:housenumber":"16",
    "addr:postcode":"bd7 3dt",
    "addr:street":"Kingswood Terrace",
    "iso:country":"GB",
    "sg:address":"16 Kingswood Terrace",
    "sg:city":"Bradford",
    "sg:classifiers":[
        {
            "category":"Manufacturing",
            "subcategory":"Tools & Machinery",
            "type":"Manufacturing & Wholesale Goods"
        },
        {
            "category":"Shopping",
            "subcategory":"Optical Goods",
            "type":"Retail Goods"
        }
    ],
    "sg:phone":"+44 1274 570495",
    "sg:postcode":"BD7 3DT",
    "sg:province":"West Yorkshire",
    "sg:tags":[
        "product",
        "manufacturer"
    ],
    "wof:name":"Bradford Optical Co. Ltd.",
    "wof:placetype":"venue"
},
  "geometry": {"coordinates":[-1.784084,53.780735],"type":"Point"}
}