{
  "type": "Feature",
  "properties": {
    "addr:full":"26 Mason Rd Norwich Norfolk NR6 6RF",
    "addr:housenumber":"26",
    "addr:postcode":"nr6 6rf",
    "addr:street":"Mason Rd",
    "iso:country":"GB",
    "sg:address":"26 Mason Rd",
    "sg:city":"Norwich",
    "sg:classifiers":[
        {
            "category":"Professional",
            "subcategory":"Engineering",
            "type":"Services"
        }
    ],
    "sg:postcode":"NR6 6RF",
    "sg:province":"Norfolk",
    "wof:name":"Patten,Steve,",
    "wof:placetype":"venue"
},
  "geometry": {"coordinates":[1.2816699743,52.6547584534],"type":"Point"}
}