{
  "type": "Feature",
  "properties": {
    "addr:full":"53 Tower Street Harrogate North Yorkshire HG1 1HS",
    "addr:housenumber":"53",
    "addr:postcode":"hg1 1hs",
    "addr:street":"Tower Street",
    "iso:country":"GB",
    "sg:address":"53 Tower Street",
    "sg:city":"Harrogate",
    "sg:classifiers":[
        {
            "category":"Shopping",
            "subcategory":"Clothing, Apparel, & Fashions",
            "type":"Retail Goods"
        },
        {
            "category":"Banks & Credit Unions",
            "subcategory":"Investment Brokerage",
            "type":"Services"
        }
    ],
    "sg:phone":"+44 1423 509849",
    "sg:postcode":"HG1 1HS",
    "sg:province":"North Yorkshire",
    "sg:tags":[
        "agency",
        "dress",
        "dresswear"
    ],
    "wof:name":"2nd Time Around",
    "wof:placetype":"venue"
},
  "geometry": {"coordinates":[-1.5384889841,53.9893341064],"type":"Point"}
}