{
  "type": "Feature",
  "properties": {
    "iso:country":"GB",
    "sg:address":"3 Gloucester Road, Andoversford",
    "sg:city":"Cheltenham",
    "sg:classifiers":[
        {
            "category":"Home & Garden",
            "subcategory":"Household Appliances",
            "type":"Retail Goods"
        }
    ],
    "sg:phone":"+44 1242 820857",
    "sg:postcode":"GL54 4HR",
    "sg:province":"Gloucestershire",
    "sg:tags":[
        "electrical"
    ],
    "wof:name":"Basil Messenger",
    "wof:placetype":"venue"
},
  "geometry": {"coordinates":[-1.968106,51.873642],"type":"Point"}
}