{
  "type": "Feature",
  "properties": {
    "addr:full":"20 Gainsford St Southwark Greater London SE1 2NE",
    "addr:housenumber":"20",
    "addr:postcode":"se1 2ne",
    "addr:street":"Gainsford St",
    "iso:country":"GB",
    "sg:address":"20 Gainsford St",
    "sg:city":"Southwark",
    "sg:classifiers":[
        {
            "category":"Utilities",
            "type":"Services"
        }
    ],
    "sg:phone":"+44 20 7681 1852",
    "sg:postcode":"SE1 2NE",
    "sg:province":"Greater London",
    "sg:tags":[
        "internet"
    ],
    "wof:name":"Compu Solve",
    "wof:placetype":"venue"
},
  "geometry": {"coordinates":[-0.075762,51.503212],"type":"Point"}
}