{
  "type": "Feature",
  "properties": {
    "addr:full":"525 Staines Road Feltham Greater London TW14 8BP",
    "addr:housenumber":"525",
    "addr:postcode":"tw14 8bp",
    "addr:street":"Staines Road",
    "iso:country":"GB",
    "sg:address":"525 Staines Road",
    "sg:city":"Feltham",
    "sg:classifiers":[
        {
            "category":"Fast Food",
            "type":"Food & Drink"
        }
    ],
    "sg:phone":"+44 20 8890 5008",
    "sg:postcode":"TW14 8BP",
    "sg:province":"Greater London",
    "sg:tags":[
        "away",
        "meal",
        "outlet",
        "take"
    ],
    "wof:name":"Just Burgers Plus",
    "wof:placetype":"venue"
},
  "geometry": {"coordinates":[-0.430555,51.452866],"type":"Point"}
}