{
  "type": "Feature",
  "properties": {
    "addr:full":"169 Farringdon Road London Greater London EC1R 3AL",
    "addr:housenumber":"169",
    "addr:postcode":"ec1r 3al",
    "addr:street":"Farringdon Road",
    "iso:country":"GB",
    "sg:address":"169 Farringdon Road",
    "sg:city":"London",
    "sg:classifiers":[
        {
            "category":"Deli",
            "type":"Food & Drink"
        }
    ],
    "sg:phone":"+44 20 7837 1586",
    "sg:postcode":"EC1R 3AL",
    "sg:province":"Greater London",
    "sg:tags":[
        "delicatessen"
    ],
    "wof:name":"G Gazzano & Son",
    "wof:placetype":"venue"
},
  "geometry": {"coordinates":[-0.1098200008,51.5242385864],"type":"Point"}
}