{
  "type": "Feature",
  "properties": {
    "iso:country":"GB",
    "sg:address":"Way Hill, Minster",
    "sg:city":"Ramsgate",
    "sg:classifiers":[
        {
            "category":"Banks & Credit Unions",
            "subcategory":"Investment Brokerage",
            "type":"Services"
        },
        {
            "category":"Autos & Motor Vehicles",
            "subcategory":"Recreational Vehicle Sales",
            "type":"Retail Goods"
        },
        {
            "category":"Military Area",
            "subcategory":"Air Force Base",
            "type":"Public Place"
        }
    ],
    "sg:phone":"+44 1843 821272",
    "sg:postcode":"CT12 4HW",
    "sg:province":"Kent",
    "sg:tags":[
        "taxi",
        "hire",
        "caravan",
        "private",
        "caravans",
        "motorhomes",
        "trailer"
    ],
    "wof:name":"Wayside Caravan Park",
    "wof:placetype":"venue"
},
  "geometry": {"coordinates":[1.340865,51.340984],"type":"Point"}
}