{
  "type": "Feature",
  "properties": {
    "addr:full":"145 Halesowen Road, Netherton Dudley West Midlands DY2 9PY",
    "addr:housenumber":"145",
    "addr:postcode":"dy2 9py",
    "addr:street":"Halesowen Road",
    "iso:country":"GB",
    "sg:address":"145 Halesowen Road, Netherton",
    "sg:city":"Dudley",
    "sg:classifiers":[
        {
            "category":"Shopping",
            "subcategory":"Pharmacy",
            "type":"Retail Goods"
        }
    ],
    "sg:phone":"+44 1384 230079",
    "sg:postcode":"DY2 9PY",
    "sg:province":"West Midlands",
    "sg:tags":[
        "pharmacist",
        "dispensing",
        "chemist"
    ],
    "sg:website":"http://www.lloydspharmacy.co.uk",
    "wof:name":"Lloyds Pharmacy Ltd",
    "wof:placetype":"venue"
},
  "geometry": {"coordinates":[-2.0815980434,52.4893951416],"type":"Point"}
}