{
  "type": "Feature",
  "properties": {
    "addr:full":"Unit 3 Rear Of, 18 King Street Honiton Devon EX14 1AF",
    "addr:housenumber":"unit 3 rear of 18",
    "addr:postcode":"ex14 1af",
    "addr:street":"King Street",
    "iso:country":"GB",
    "sg:address":"Unit 3 Rear Of, 18 King Street",
    "sg:city":"Honiton",
    "sg:classifiers":[
        {
            "category":"Home & Garden",
            "subcategory":"Carpets & Floor Coverings",
            "type":"Retail Goods"
        }
    ],
    "sg:phone":"+44 1404 43783",
    "sg:postcode":"EX14 1AF",
    "sg:province":"Devon",
    "sg:tags":[
        "carpets",
        "retailer",
        "rug",
        "matting"
    ],
    "wof:name":"R & S Carpets",
    "wof:placetype":"venue"
},
  "geometry": {"coordinates":[-3.196906,50.797386],"type":"Point"}
}