{
  "type": "Feature",
  "properties": {
    "iso:country":"GB",
    "sg:address":"6 Harcourt House, 19a Cavendish Square",
    "sg:city":"London",
    "sg:classifiers":[
        {
            "category":"Health Services",
            "subcategory":"Dentist",
            "type":"Services"
        }
    ],
    "sg:phone":"+44 20 7580 1017",
    "sg:postcode":"W1G 0PN",
    "sg:province":"Greater London",
    "wof:name":"Andrew A Macdonald",
    "wof:placetype":"venue"
},
  "geometry": {"coordinates":[-0.146044,51.516571],"type":"Point"}
}