{
  "type": "Feature",
  "properties": {
    "addr:full":"1 King Street Mews London Greater London N2 8EA",
    "addr:housenumber":"1",
    "addr:postcode":"n2 8ea",
    "addr:street":"King Street Mews",
    "iso:country":"GB",
    "sg:address":"1 King Street Mews",
    "sg:city":"London",
    "sg:classifiers":[
        {
            "category":"Communications",
            "subcategory":"Newspaper",
            "type":"Services"
        }
    ],
    "sg:postcode":"N2 8EA",
    "sg:province":"Greater London",
    "sg:tags":[
        "magazine"
    ],
    "wof:name":"Shalom Publications Ltd",
    "wof:placetype":"venue"
},
  "geometry": {"coordinates":[-0.171182,51.594036],"type":"Point"}
}