{
  "type": "Feature",
  "properties": {
    "addr:full":"2 Broad Lane, Cawood Selby East Riding of Yorkshire YO8 3SQ",
    "addr:housenumber":"2",
    "addr:postcode":"yo8 3sq",
    "addr:street":"Broad Lane",
    "iso:country":"GB",
    "sg:address":"2 Broad Lane, Cawood",
    "sg:city":"Selby",
    "sg:classifiers":[
        {
            "category":"Professional",
            "subcategory":"Art Services",
            "type":"Services"
        }
    ],
    "sg:phone":"+44 1757 269222",
    "sg:postcode":"YO8 3SQ",
    "sg:province":"East Riding of Yorkshire",
    "sg:tags":[
        "graphic",
        "designer"
    ],
    "wof:name":"M D P Graphics",
    "wof:placetype":"venue"
},
  "geometry": {"coordinates":[-1.1272189617,53.8305053711],"type":"Point"}
}