{
  "type": "Feature",
  "properties": {
    "addr:full":"St Stephens Place Trowbridge Wiltshire BA14 8AH",
    "addr:postcode":"ba14 8ah",
    "addr:street":"St Stephens Place",
    "iso:country":"GB",
    "sg:address":"St Stephens Place",
    "sg:city":"Trowbridge",
    "sg:classifiers":[
        {
            "category":"Community Center",
            "type":"Public Place"
        },
        {
            "category":"Government",
            "subcategory":"Office",
            "type":"Public Place"
        }
    ],
    "sg:phone":"+44 1225 762439",
    "sg:postcode":"BA14 8AH",
    "sg:province":"Wiltshire",
    "sg:tags":[
        "conference",
        "local",
        "room",
        "centre"
    ],
    "wof:name":"Trowbridge Civic Hall",
    "wof:placetype":"venue"
},
  "geometry": {"coordinates":[-2.2071290016,51.3184394836],"type":"Point"}
}