{
  "type": "Feature",
  "properties": {
    "addr:full":"Deans Ct, 1-3 London Rd Bicester Oxfordshire OX26 6BU",
    "addr:housenumber":"1-3",
    "addr:postcode":"ox26 6bu",
    "addr:street":"Deans Ct;London Rd",
    "iso:country":"GB",
    "sg:address":"Deans Ct, 1-3 London Rd",
    "sg:city":"Bicester",
    "sg:classifiers":[
        {
            "category":"Professional",
            "subcategory":"Management & Consulting",
            "type":"Services"
        }
    ],
    "sg:postcode":"OX26 6BU",
    "sg:province":"Oxfordshire",
    "sg:tags":[
        "consultant",
        "business"
    ],
    "wof:name":"J. Woodman Partners (U K) Ltd",
    "wof:placetype":"venue"
},
  "geometry": {"coordinates":[-1.15354,51.898026],"type":"Point"}
}