{
  "type": "Feature",
  "properties": {
    "addr:full":"4 School House, 2nd Avenue, Trafford Park Manchester Cheshire M17 1DZ",
    "addr:housenumber":"4",
    "addr:postcode":"m17 1dz",
    "addr:street":"School House 2Nd Avenue",
    "iso:country":"GB",
    "sg:address":"4 School House, 2nd Avenue, Trafford Park",
    "sg:city":"Manchester",
    "sg:classifiers":[
        {
            "category":"Wholesale",
            "subcategory":"Books, Periodicals, & Newspapers",
            "type":"Manufacturing & Wholesale Goods"
        }
    ],
    "sg:phone":"+44 161 872 6667",
    "sg:postcode":"M17 1DZ",
    "sg:province":"Cheshire",
    "sg:tags":[
        "publisher",
        "publishing"
    ],
    "wof:name":"Lansdowne Publishing Partnership Ltd.",
    "wof:placetype":"venue"
},
  "geometry": {"coordinates":[-2.308359,53.46814],"type":"Point"}
}