{
  "type": "Feature",
  "properties": {
    "addr:full":"20 Wellmeadow Blairgowrie Perth and Kinross PH10 6AS",
    "addr:housenumber":"20",
    "addr:postcode":"ph10 6as",
    "addr:street":"Wellmeadow Blairgowrie",
    "iso:country":"GB",
    "sg:address":"20 Wellmeadow",
    "sg:city":"Blairgowrie",
    "sg:classifiers":[
        {
            "category":"Shopping",
            "subcategory":"Clothing, Apparel, & Fashions",
            "type":"Retail Goods"
        }
    ],
    "sg:phone":"+44 1250 873463",
    "sg:postcode":"PH10 6AS",
    "sg:province":"Perth and Kinross",
    "sg:tags":[
        "shop",
        "lady",
        "fashionwear"
    ],
    "sg:website":"http://www.ewm.co.uk",
    "wof:name":"Edinburgh Woollen Mill Ltd",
    "wof:placetype":"venue"
},
  "geometry": {"coordinates":[-3.337839,56.591991],"type":"Point"}
}