{
  "type": "Feature",
  "properties": {
    "addr:full":"Unit C, Bedewell Indstl Pk Hebburn Tyne and Wear NE31 2HQ",
    "addr:housenumber":"unit c",
    "addr:postcode":"ne31 2hq",
    "addr:street":"Indstl Pk",
    "iso:country":"GB",
    "sg:address":"Unit C, Bedewell Indstl Pk",
    "sg:city":"Hebburn",
    "sg:classifiers":[
        {
            "category":"Building & Trades",
            "subcategory":"Cleaning & Sanitation",
            "type":"Services"
        }
    ],
    "sg:phone":"+44 191 483 9660",
    "sg:postcode":"NE31 2HQ",
    "sg:province":"Tyne and Wear",
    "sg:tags":[
        "blast"
    ],
    "wof:name":"Coastline Shot Blasting Co  Ltd",
    "wof:placetype":"venue"
},
  "geometry": {"coordinates":[-1.51118,54.957981],"type":"Point"}
}