{
  "type": "Feature",
  "properties": {
    "iso:country":"GB",
    "sg:address":"34 Maxton Terrace",
    "sg:city":"Glasgow",
    "sg:classifiers":[
        {
            "category":"Organizations",
            "subcategory":"Community Association",
            "type":"Services"
        }
    ],
    "sg:phone":"+44 141 641 3484",
    "sg:postcode":"G72 8LX",
    "sg:province":"South Lanarkshire",
    "sg:tags":[
        "co-operatives",
        "society",
        "housing",
        "trust"
    ],
    "wof:name":"East Whitlawburn Tenant Management Co-Operative",
    "wof:placetype":"venue"
},
  "geometry": {"coordinates":[-4.177112,55.80777],"type":"Point"}
}