{
  "type": "Feature",
  "properties": {
    "addr:full":"776 Alum Rock Road, Ward End Birmingham West Midlands B8 2TE",
    "addr:housenumber":"776",
    "addr:postcode":"b8 2te",
    "addr:street":"Alum Rock Road",
    "iso:country":"GB",
    "sg:address":"776 Alum Rock Road, Ward End",
    "sg:city":"Birmingham",
    "sg:classifiers":[
        {
            "category":"Building & Trades",
            "subcategory":"Equipment Rental",
            "type":"Services"
        }
    ],
    "sg:phone":"+44 121 327 6017",
    "sg:postcode":"B8 2TE",
    "sg:province":"West Midlands",
    "sg:tags":[
        "hire",
        "centre"
    ],
    "wof:name":"The Hire Shop (Birmingham) Ltd.",
    "wof:placetype":"venue"
},
  "geometry": {"coordinates":[-1.8304200172,52.4893760681],"type":"Point"}
}