{
  "type": "Feature",
  "properties": {
    "addr:full":"The Sycamores, Boothferry Road, Howden Goole East Riding of Yorkshire DN14 7TA",
    "addr:postcode":"dn14 7ta",
    "addr:street":"Boothferry Road",
    "iso:country":"GB",
    "sg:address":"The Sycamores, Boothferry Road, Howden",
    "sg:city":"Goole",
    "sg:classifiers":[
        {
            "category":"Sports & Exercise",
            "subcategory":"Skate Park",
            "type":"Entertainment"
        }
    ],
    "sg:postcode":"DN14 7TA",
    "sg:province":"East Riding of Yorkshire",
    "sg:tags":[
        "mushroom"
    ],
    "wof:name":"Frank Batty",
    "wof:placetype":"venue"
},
  "geometry": {"coordinates":[-0.8610560298,53.7476654053],"type":"Point"}
}