{
  "type": "Feature",
  "properties": {
    "iso:country":"GB",
    "sg:address":"Butt Dyke House, 33 Park Row",
    "sg:city":"Nottingham",
    "sg:classifiers":[
        {
            "category":"Government",
            "subcategory":"Office",
            "type":"Public Place"
        }
    ],
    "sg:phone":"+44 115 941 4288",
    "sg:postcode":"NG1 6GR",
    "sg:province":"Nottinghamshire",
    "sg:tags":[
        "central"
    ],
    "wof:name":"Probate Registry",
    "wof:placetype":"venue"
},
  "geometry": {"coordinates":[-1.15545,52.953022],"type":"Point"}
}