{
  "type": "Feature",
  "properties": {
    "iso:country":"GB",
    "sg:address":"20 Bracken Close, Warsop",
    "sg:city":"Mansfield",
    "sg:classifiers":[
        {
            "category":"Building & Trades",
            "subcategory":"Plumbing",
            "type":"Services"
        }
    ],
    "sg:postcode":"NG20 0QQ",
    "sg:province":"Derbyshire",
    "sg:tags":[
        "central",
        "installation",
        "heating",
        "servicing",
        "system"
    ],
    "wof:name":"G K & R J PARKER",
    "wof:placetype":"venue"
},
  "geometry": {"coordinates":[-1.1449619532,53.199886322],"type":"Point"}
}