{
  "type": "Feature",
  "properties": {
    "iso:country":"GB",
    "sg:address":"Unit 3 & 5 Lapthorne Farm, Totnes Road, Ipplepen",
    "sg:city":"Newton Abbot",
    "sg:classifiers":[
        {
            "category":"Autos & Motor Vehicles",
            "subcategory":"Automobile Sales",
            "type":"Retail Goods"
        }
    ],
    "sg:postcode":"TQ12 5TU",
    "sg:province":"Devon",
    "sg:tags":[
        "car"
    ],
    "wof:name":"Lapthorne Motors",
    "wof:placetype":"venue"
},
  "geometry": {"coordinates":[-3.62724,50.491348],"type":"Point"}
}