{
  "type": "Feature",
  "properties": {
    "addr:full":"P O Box 73 Bury Lancashire BL9 7FW",
    "addr:housenumber":"box 73",
    "addr:postcode":"bl9 7fw",
    "addr:street":"P O",
    "iso:country":"GB",
    "sg:address":"P O Box 73",
    "sg:city":"Bury",
    "sg:classifiers":[
        {
            "category":"Organizations",
            "subcategory":"Non-profit Organization",
            "type":"Services"
        }
    ],
    "sg:phone":"+44 161 763 1500",
    "sg:postcode":"BL9 7FW",
    "sg:province":"Lancashire",
    "sg:tags":[
        "organisation",
        "voluntary",
        "charity"
    ],
    "wof:name":"Chinese Church Support Ministries",
    "wof:placetype":"venue"
},
  "geometry": {"coordinates":[-2.2705891132,53.5956115723],"type":"Point"}
}