{
  "type": "Feature",
  "properties": {
    "iso:country":"GB",
    "sg:address":"8 London Road, Twyford",
    "sg:city":"Reading",
    "sg:classifiers":[
        {
            "category":"Professional",
            "subcategory":"Printing & Photocopies",
            "type":"Services"
        }
    ],
    "sg:phone":"+44 118 934 4003",
    "sg:postcode":"RG10 9ER",
    "sg:province":"Berkshire",
    "sg:tags":[
        "duplicating",
        "copying"
    ],
    "wof:name":"Elite Business Systems",
    "wof:placetype":"venue"
},
  "geometry": {"coordinates":[-0.866280973,51.4775009155],"type":"Point"}
}