{
  "type": "Feature",
  "properties": {
    "iso:country":"GB",
    "sg:address":"Unit 6, Station Road, Keadby",
    "sg:city":"Scunthorpe",
    "sg:classifiers":[
        {
            "category":"Retail",
            "subcategory":"Repair Shop",
            "type":"Services"
        }
    ],
    "sg:phone":"+44 1724 783022",
    "sg:postcode":"DN17 3BN",
    "sg:province":"Lincolnshire",
    "sg:tags":[
        "radio",
        "television",
        "video"
    ],
    "wof:name":"A & B Television Services",
    "wof:placetype":"venue"
},
  "geometry": {"coordinates":[-0.733868,53.577671],"type":"Point"}
}