{
  "type": "Feature",
  "properties": {
    "addr:full":"19 Dundonald Street Dundee Dundee City DD3 7QA",
    "addr:housenumber":"19",
    "addr:postcode":"dd3 7qa",
    "addr:street":"Dundonald Street",
    "iso:country":"GB",
    "sg:address":"19 Dundonald Street",
    "sg:city":"Dundee",
    "sg:classifiers":[
        {
            "category":"Shopping",
            "subcategory":"Department Store",
            "type":"Retail Goods"
        },
        {
            "category":"Shopping",
            "subcategory":"Crafts & Fabrics",
            "type":"Retail Goods"
        }
    ],
    "sg:phone":"+44 1382 456560",
    "sg:postcode":"DD3 7QA",
    "sg:province":"Dundee City",
    "sg:tags":[
        "retailer"
    ],
    "wof:name":"Universal Fabrics",
    "wof:placetype":"venue"
},
  "geometry": {"coordinates":[-2.964891,56.471951],"type":"Point"}
}