{
  "type": "Feature",
  "properties": {
    "addr:full":"The Old Gardens, Blackhorse Road Woking Surrey GU22 0QT",
    "addr:postcode":"gu22 0qt",
    "addr:street":"Blackhorse Road",
    "iso:country":"GB",
    "sg:address":"The Old Gardens, Blackhorse Road",
    "sg:city":"Woking",
    "sg:classifiers":[
        {
            "category":"Home & Garden",
            "subcategory":"Hardware",
            "type":"Retail Goods"
        }
    ],
    "sg:phone":"+44 1483 797446",
    "sg:postcode":"GU22 0QT",
    "sg:province":"Surrey",
    "sg:tags":[
        "lawnmowers",
        "machinery"
    ],
    "wof:name":"Ashley Services",
    "wof:placetype":"venue"
},
  "geometry": {"coordinates":[-0.60963,51.303089],"type":"Point"}
}