{
  "type": "Feature",
  "properties": {
    "iso:country":"GB",
    "sg:address":"Foxhall Road",
    "sg:city":"Ipswich",
    "sg:classifiers":[
        {
            "category":"Health Services",
            "subcategory":"Hospital",
            "type":"Services"
        }
    ],
    "sg:phone":"+44 1473 279100",
    "sg:postcode":"IP4 5SW",
    "sg:province":"Suffolk",
    "wof:name":"The Suffolk Nuffield Hospital",
    "wof:placetype":"venue"
},
  "geometry": {"coordinates":[1.22481,52.04937],"type":"Point"}
}