{
  "type": "Feature",
  "properties": {
    "addr:full":"Bridge Cottage, Brisley Lane, Ruckinge Ashford Kent TN26 2PN",
    "addr:postcode":"tn26 2pn",
    "addr:street":"Brisley Lane",
    "iso:country":"GB",
    "sg:address":"Bridge Cottage, Brisley Lane, Ruckinge",
    "sg:city":"Ashford",
    "sg:classifiers":[
        {
            "category":"Wholesale",
            "subcategory":"Scrap",
            "type":"Manufacturing & Wholesale Goods"
        }
    ],
    "sg:phone":"+44 1233 733881",
    "sg:postcode":"TN26 2PN",
    "sg:province":"Kent",
    "sg:tags":[
        "car",
        "breaker",
        "dismantlers"
    ],
    "wof:name":"Ashfords Auto Salvage",
    "wof:placetype":"venue"
},
  "geometry": {"coordinates":[0.8895900249,51.0661697388],"type":"Point"}
}