{
  "type": "Feature",
  "properties": {
    "addr:full":"Boulton Road, Pin Green Industrial Estate Stevenage Hertfordshire SG1 4QX",
    "addr:housenumber":"estate",
    "addr:postcode":"sg1 4qx",
    "addr:street":"Boulton Road Pin Green Industrial",
    "iso:country":"GB",
    "sg:address":"Boulton Road, Pin Green Industrial Estate",
    "sg:city":"Stevenage",
    "sg:classifiers":[
        {
            "category":"Professional",
            "subcategory":"Engineering",
            "type":"Services"
        }
    ],
    "sg:phone":"+44 1438 743400",
    "sg:postcode":"SG1 4QX",
    "sg:province":"Hertfordshire",
    "sg:tags":[
        "precision",
        "engineer"
    ],
    "wof:name":"Belmont Precision Engineering Co. Ltd.",
    "wof:placetype":"venue"
},
  "geometry": {"coordinates":[-0.1686040014,51.9264373779],"type":"Point"}
}