{
  "type": "Feature",
  "properties": {
    "iso:country":"GB",
    "sg:address":"Bdwy Business Park, Bdwy, Chadderton",
    "sg:city":"Oldham",
    "sg:classifiers":[
        {
            "category":"Shopping",
            "subcategory":"Computers & Home Electronics",
            "type":"Retail Goods"
        }
    ],
    "sg:phone":"+44 161 681 6922",
    "sg:postcode":"OL9 0JA",
    "sg:province":"Lancashire",
    "sg:tags":[
        "electrical"
    ],
    "wof:name":"Power Supply Cords",
    "wof:placetype":"venue"
},
  "geometry": {"coordinates":[-2.13881,53.546051],"type":"Point"}
}