{
  "type": "Feature",
  "properties": {
    "addr:full":"Albert Street, Chesterton Newcastle Staffordshire ST5 7JF",
    "addr:postcode":"st5 7jf",
    "addr:street":"Albert Street",
    "iso:country":"GB",
    "sg:address":"Albert Street, Chesterton",
    "sg:city":"Newcastle",
    "sg:classifiers":[
        {
            "category":"Shopping",
            "subcategory":"Bicycles & Sporting Goods",
            "type":"Retail Goods"
        }
    ],
    "sg:phone":"+44 1782 561966",
    "sg:postcode":"ST5 7JF",
    "sg:province":"Staffordshire",
    "sg:tags":[
        "cycle",
        "accessory"
    ],
    "wof:name":"Longstaff Cycles",
    "wof:placetype":"venue"
},
  "geometry": {"coordinates":[-2.250059,53.041046],"type":"Point"}
}