{
  "type": "Feature",
  "properties": {
    "addr:full":"1 East Lane, Shipton By Beningbrough York North Yorkshire YO30 1AH",
    "addr:housenumber":"1",
    "addr:postcode":"yo30 1ah",
    "addr:street":"East Lane",
    "iso:country":"GB",
    "sg:address":"1 East Lane, Shipton By Beningbrough",
    "sg:city":"York",
    "sg:classifiers":[
        {
            "category":"Health Services",
            "subcategory":"Nursing And Care Facility",
            "type":"Services"
        }
    ],
    "sg:phone":"+44 1904 470644",
    "sg:postcode":"YO30 1AH",
    "sg:province":"North Yorkshire",
    "sg:tags":[
        "home"
    ],
    "wof:name":"St Catherines",
    "wof:placetype":"venue"
},
  "geometry": {"coordinates":[-1.1545740366,54.0233840942],"type":"Point"}
}