{
  "type": "Feature",
  "properties": {
    "addr:full":"4 Daisy Lea Lane, Lindley Huddersfield West Yorkshire HD3 3JA",
    "addr:housenumber":"4",
    "addr:postcode":"hd3 3ja",
    "addr:street":"Daisy Lea Lane;West",
    "iso:country":"GB",
    "sg:address":"4 Daisy Lea Lane, Lindley",
    "sg:city":"Huddersfield",
    "sg:classifiers":[
        {
            "category":"Professional",
            "subcategory":"Engineering",
            "type":"Services"
        }
    ],
    "sg:postcode":"HD3 3JA",
    "sg:province":"West Yorkshire",
    "sg:tags":[
        "contractor",
        "electrical",
        "engineer"
    ],
    "wof:name":"Fleetwood Electrical Contractors",
    "wof:placetype":"venue"
},
  "geometry": {"coordinates":[-1.8209739923,53.6587257385],"type":"Point"}
}