{
  "type": "Feature",
  "properties": {
    "iso:country":"GB",
    "sg:address":"Unit1, Coundon Industrial Estate, Coundon",
    "sg:city":"Bishop Auckland",
    "sg:classifiers":[
        {
            "category":"Professional",
            "subcategory":"Detective & Security Services",
            "type":"Services"
        },
        {
            "category":"Home & Garden",
            "subcategory":"Building Materials",
            "type":"Retail Goods"
        }
    ],
    "sg:phone":"+44 1388 458794",
    "sg:postcode":"DL14 8NR",
    "sg:province":"Durham",
    "sg:tags":[
        "installers",
        "gate",
        "door",
        "barrier",
        "equipment"
    ],
    "wof:name":"Hercules Security Fabrications Ltd.",
    "wof:placetype":"venue"
},
  "geometry": {"coordinates":[-1.628616,54.664146],"type":"Point"}
}