{
  "type": "Feature",
  "properties": {
    "addr:full":"The Firs, Hogspudding Lane, Newdigate Dorking Surrey RH5 5DS",
    "addr:postcode":"rh5 5ds",
    "addr:street":"Hogspudding Lane",
    "iso:country":"GB",
    "sg:address":"The Firs, Hogspudding Lane, Newdigate",
    "sg:city":"Dorking",
    "sg:classifiers":[
        {
            "category":"Building & Trades",
            "subcategory":"Construction",
            "type":"Services"
        }
    ],
    "sg:phone":"+44 1306 631649",
    "sg:postcode":"RH5 5DS",
    "sg:province":"Surrey",
    "sg:tags":[
        "builder"
    ],
    "wof:name":"David Weller & Sons",
    "wof:placetype":"venue"
},
  "geometry": {"coordinates":[-0.283625,51.171135],"type":"Point"}
}