{
  "type": "Feature",
  "properties": {
    "iso:country":"GB",
    "sg:address":"Dorchester Road, Great Sankey",
    "sg:city":"Warrington",
    "sg:classifiers":[
        {
            "category":"Education",
            "subcategory":"School",
            "type":"Public Place"
        },
        {
            "category":"Government",
            "subcategory":"Office",
            "type":"Public Place"
        }
    ],
    "sg:phone":"+44 1925 659307",
    "sg:postcode":"WA5 1XZ",
    "sg:province":"Cheshire",
    "sg:tags":[
        "local",
        "authority"
    ],
    "wof:name":"Hood Manor County Primary School",
    "wof:placetype":"venue"
},
  "geometry": {"coordinates":[-2.629714,53.394169],"type":"Point"}
}