{
  "type": "Feature",
  "properties": {
    "iso:country":"GB",
    "sg:address":"47 Whiteladies Road",
    "sg:city":"Bristol",
    "sg:classifiers":[
        {
            "category":"Autos & Motor Vehicles",
            "subcategory":"Automobile Sales",
            "type":"Retail Goods"
        }
    ],
    "sg:phone":"+44 117 973 7199",
    "sg:postcode":"BS8 2LS",
    "sg:province":"City of Bristol",
    "sg:tags":[
        "car"
    ],
    "wof:name":"Slade Cars",
    "wof:placetype":"venue"
},
  "geometry": {"coordinates":[-2.6084499359,51.4616355896],"type":"Point"}
}