{
  "type": "Feature",
  "properties": {
    "addr:full":"493 Huddersfield Road Oldham Lancashire OL4 2JG",
    "addr:housenumber":"493",
    "addr:postcode":"ol4 2jg",
    "addr:street":"Huddersfield Road",
    "iso:country":"GB",
    "sg:address":"493 Huddersfield Road",
    "sg:city":"Oldham",
    "sg:classifiers":[
        {
            "category":"Food & Beverages",
            "subcategory":"Meat & Fish",
            "type":"Retail Goods"
        }
    ],
    "sg:phone":"+44 161 624 6336",
    "sg:postcode":"OL4 2JG",
    "sg:province":"Lancashire",
    "sg:tags":[
        "butcher"
    ],
    "wof:name":"Taylors Butchers",
    "wof:placetype":"venue"
},
  "geometry": {"coordinates":[-2.073281,53.54974],"type":"Point"}
}