{
  "type": "Feature",
  "properties": {
    "iso:country":"GB",
    "sg:address":"38 Throwley Way",
    "sg:city":"Sutton",
    "sg:classifiers":[
        {
            "category":"Health Services",
            "subcategory":"Dentist",
            "type":"Services"
        }
    ],
    "sg:phone":"+44 20 8642 1169",
    "sg:postcode":"SM1 4AF",
    "sg:province":"Surrey",
    "wof:name":"J K Farquharson",
    "wof:placetype":"venue"
},
  "geometry": {"coordinates":[-0.1915310025,51.3634529114],"type":"Point"}
}