{
  "type": "Feature",
  "properties": {
    "addr:full":"Room 201-202 Building 308, World Freight Terminal, Manchester Airport Manchester Greater Manchester M90 5PZ",
    "addr:housenumber":"201-202;308",
    "addr:postcode":"m90 5pz",
    "iso:country":"GB",
    "sg:address":"Room 201-202 Building 308, World Freight Terminal, Manchester Airport",
    "sg:city":"Manchester",
    "sg:classifiers":[
        {
            "category":"Freight",
            "type":"Transportation"
        }
    ],
    "sg:phone":"+44 161 436 5656",
    "sg:postcode":"M90 5PZ",
    "sg:province":"Greater Manchester",
    "sg:tags":[
        "forwarders"
    ],
    "wof:name":"World Cargo Ltd.",
    "wof:placetype":"venue"
},
  "geometry": {"coordinates":[-2.288599968,53.361869812],"type":"Point"}
}