{
  "type": "Feature",
  "properties": {
    "addr:full":"Unit 6 Gravelly Indstl Pk Birmingham West Midlands B24 8HZ",
    "addr:housenumber":"unit 6",
    "addr:postcode":"b24 8hz",
    "addr:street":"Gravelly Indstl Pk",
    "iso:country":"GB",
    "sg:address":"Unit 6 Gravelly Indstl Pk",
    "sg:city":"Birmingham",
    "sg:classifiers":[
        {
            "category":"Professional",
            "subcategory":"Engineering",
            "type":"Services"
        }
    ],
    "sg:postcode":"B24 8HZ",
    "sg:province":"West Midlands",
    "wof:name":"Set Fast Engineering",
    "wof:placetype":"venue"
},
  "geometry": {"coordinates":[-1.846864,52.508915],"type":"Point"}
}