{
  "type": "Feature",
  "properties": {
    "iso:country":"GB",
    "sg:address":"Metropolitan Police (imber Ct) S, Ports Club, Ember Lane",
    "sg:city":"East Molesey",
    "sg:classifiers":[
        {
            "category":"Organizations",
            "subcategory":"Membership Organization",
            "type":"Services"
        },
        {
            "category":"Arena",
            "subcategory":"Sports Club",
            "type":"Entertainment"
        }
    ],
    "sg:phone":"+44 20 8398 1267",
    "sg:postcode":"KT8 0BT",
    "sg:province":"Greater London",
    "wof:name":"Metropolitan Police (Imber Ct) Sports Club",
    "wof:placetype":"venue"
},
  "geometry": {"coordinates":[-0.344541,51.401962],"type":"Point"}
}