{
  "type": "Feature",
  "properties": {
    "addr:full":"247-253 North Sherwood St Nottingham Nottinghamshire NG1 4EQ",
    "addr:housenumber":"247-253",
    "addr:postcode":"ng1 4eq",
    "addr:street":"North Sherwood St",
    "iso:country":"GB",
    "sg:address":"247-253 North Sherwood St",
    "sg:city":"Nottingham",
    "sg:classifiers":[
        {
            "category":"Retail",
            "subcategory":"Auto Rental",
            "type":"Services"
        }
    ],
    "sg:phone":"+44 115 941 4841",
    "sg:postcode":"NG1 4EQ",
    "sg:province":"Nottinghamshire",
    "sg:tags":[
        "car"
    ],
    "wof:name":"Century Self Drive",
    "wof:placetype":"venue"
},
  "geometry": {"coordinates":[-1.153241,52.964142],"type":"Point"}
}