{
  "type": "Feature",
  "properties": {
    "addr:full":"70 Hartslock Drive, Abbey Wood London Greater London SE2 9UU",
    "addr:housenumber":"70",
    "addr:postcode":"se2 9uu",
    "addr:street":"Hartslock Drive",
    "iso:country":"GB",
    "sg:address":"70 Hartslock Drive, Abbey Wood",
    "sg:city":"London",
    "sg:classifiers":[
        {
            "category":"Retail",
            "subcategory":"Storage",
            "type":"Services"
        }
    ],
    "sg:postcode":"SE2 9UU",
    "sg:province":"Greater London",
    "sg:tags":[
        "hire",
        "container"
    ],
    "wof:name":"Tigress Containers",
    "wof:placetype":"venue"
},
  "geometry": {"coordinates":[0.12124,51.492447],"type":"Point"}
}