{
  "type": "Feature",
  "properties": {
    "addr:full":"28-32 Heaton Road Bradford West Yorkshire BD8 8RA",
    "addr:housenumber":"28-32",
    "addr:postcode":"bd8 8ra",
    "addr:street":"Heaton Road",
    "iso:country":"GB",
    "sg:address":"28-32 Heaton Road",
    "sg:city":"Bradford",
    "sg:classifiers":[
        {
            "category":"Autos & Motor Vehicles",
            "subcategory":"Auto Supplies",
            "type":"Retail Goods"
        },
        {
            "category":"Shopping",
            "type":"Retail Goods"
        }
    ],
    "sg:phone":"+44 1274 493458",
    "sg:postcode":"BD8 8RA",
    "sg:province":"West Yorkshire",
    "sg:tags":[
        "car",
        "part",
        "accessory"
    ],
    "wof:name":"S S Motortech",
    "wof:placetype":"venue"
},
  "geometry": {"coordinates":[-1.77606,53.806908],"type":"Point"}
}