{
  "type": "Feature",
  "properties": {
    "iso:country":"GB",
    "sg:address":"62 Pyle Street",
    "sg:city":"Newport",
    "sg:classifiers":[
        {
            "category":"Shopping",
            "subcategory":"Department Store",
            "type":"Retail Goods"
        },
        {
            "category":"Food & Beverages",
            "subcategory":"Groceries & Convenience Stores",
            "type":"Retail Goods"
        }
    ],
    "sg:phone":"+44 1983 523228",
    "sg:postcode":"PO30 1UL",
    "sg:province":"Isle of Wight",
    "sg:website":"http://www.easyweighiow.co.uk",
    "wof:name":"Easy Weigh",
    "wof:placetype":"venue"
},
  "geometry": {"coordinates":[-1.295598,50.698944],"type":"Point"}
}