{
  "type": "Feature",
  "properties": {
    "addr:full":"205 Cowley Road Oxford Oxfordshire OX4 1XA",
    "addr:housenumber":"205",
    "addr:postcode":"ox4 1xa",
    "addr:street":"Cowley Road",
    "iso:country":"GB",
    "sg:address":"205 Cowley Road",
    "sg:city":"Oxford",
    "sg:classifiers":[
        {
            "category":"Organizations",
            "subcategory":"Non-profit Organization",
            "type":"Services"
        }
    ],
    "sg:phone":"+44 1865 243539",
    "sg:postcode":"OX4 1XA",
    "sg:province":"Oxfordshire",
    "sg:tags":[
        "organisation",
        "voluntary",
        "charity"
    ],
    "wof:name":"Smart Criminal Justice Services",
    "wof:placetype":"venue"
},
  "geometry": {"coordinates":[-1.2337360382,51.7468147278],"type":"Point"}
}