{
  "type": "Feature",
  "properties": {
    "iso:country":"GB",
    "sg:address":"3 Browning Circle",
    "sg:city":"Derby",
    "sg:classifiers":[
        {
            "category":"Food & Beverages",
            "subcategory":"Meat & Fish",
            "type":"Retail Goods"
        }
    ],
    "sg:phone":"+44 1332 743899",
    "sg:postcode":"DE23 8AR",
    "sg:province":"Derbyshire",
    "sg:tags":[
        "chip"
    ],
    "wof:name":"Circle Fish Bar",
    "wof:placetype":"venue"
},
  "geometry": {"coordinates":[-1.485734,52.898403],"type":"Point"}
}