{
  "type": "Feature",
  "properties": {
    "addr:full":"127 Bridge Street Warrington Cheshire WA1 2HS",
    "addr:housenumber":"127",
    "addr:postcode":"wa1 2hs",
    "addr:street":"Bridge Street",
    "iso:country":"GB",
    "sg:address":"127 Bridge Street",
    "sg:city":"Warrington",
    "sg:classifiers":[
        {
            "category":"Fast Food",
            "type":"Food & Drink"
        }
    ],
    "sg:phone":"+44 1925 633988",
    "sg:postcode":"WA1 2HS",
    "sg:province":"Cheshire",
    "sg:tags":[
        "away",
        "take"
    ],
    "wof:name":"Bridgecourt Chinese Take Away",
    "wof:placetype":"venue"
},
  "geometry": {"coordinates":[-2.591629982,53.3865127563],"type":"Point"}
}