{
  "type": "Feature",
  "properties": {
    "iso:country":"GB",
    "sg:address":"P O Box 160",
    "sg:city":"Northampton",
    "sg:classifiers":[
        {
            "category":"Professional",
            "subcategory":"Accounting & Tax Preparation",
            "type":"Services"
        }
    ],
    "sg:phone":"+44 1604 603083",
    "sg:postcode":"NN1 1AA",
    "sg:province":"Northamptonshire",
    "sg:tags":[
        "accountant"
    ],
    "wof:name":"Errington Smith & Co",
    "wof:placetype":"venue"
},
  "geometry": {"coordinates":[-0.897679,52.234859],"type":"Point"}
}