{
  "type": "Feature",
  "properties": {
    "addr:full":"Firbrooks, Houghton Lane, North Pickenham Swaffham Norfolk PE37 8LF",
    "addr:postcode":"pe37 8lf",
    "addr:street":"Firbrooks Houghton Lane",
    "iso:country":"GB",
    "sg:address":"Firbrooks, Houghton Lane, North Pickenham",
    "sg:city":"Swaffham",
    "sg:classifiers":[
        {
            "category":"Building & Trades",
            "subcategory":"Construction",
            "type":"Services"
        }
    ],
    "sg:phone":"+44 1760 440641",
    "sg:postcode":"PE37 8LF",
    "sg:province":"Norfolk",
    "sg:tags":[
        "builder"
    ],
    "wof:name":"John Lucas",
    "wof:placetype":"venue"
},
  "geometry": {"coordinates":[0.756099999,52.6251602173],"type":"Point"}
}