{
  "type": "Feature",
  "properties": {
    "addr:full":"Trevarnon Farm, 20 Prosper Hill, Gwithian Hayle Cornwall TR27 5EB",
    "addr:housenumber":"20",
    "addr:postcode":"tr27 5eb",
    "addr:street":"Prosper Hill",
    "iso:country":"GB",
    "sg:address":"Trevarnon Farm, 20 Prosper Hill, Gwithian",
    "sg:city":"Hayle",
    "sg:classifiers":[
        {
            "category":"Home & Garden",
            "subcategory":"Garden Supply",
            "type":"Retail Goods"
        },
        {
            "category":"Farming",
            "subcategory":"Livestock Farm",
            "type":"Manufacturing & Wholesale Goods"
        }
    ],
    "sg:phone":"+44 1736 753316",
    "sg:postcode":"TR27 5EB",
    "sg:province":"Cornwall",
    "sg:tags":[
        "bulb",
        "grower",
        "others"
    ],
    "wof:name":"S H Hosking & Son",
    "wof:placetype":"venue"
},
  "geometry": {"coordinates":[-5.385478,50.221153],"type":"Point"}
}