{
  "type": "Feature",
  "properties": {
    "iso:country":"GB",
    "sg:address":"Old Mills, Trewern",
    "sg:city":"Welshpool",
    "sg:classifiers":[
        {
            "category":"Farming",
            "subcategory":"Livestock Farm",
            "type":"Manufacturing & Wholesale Goods"
        }
    ],
    "sg:phone":"+44 1938 570275",
    "sg:postcode":"SY21 8ED",
    "sg:province":"Shropshire",
    "sg:tags":[
        "others"
    ],
    "wof:name":"Alan M Bebb",
    "wof:placetype":"venue"
},
  "geometry": {"coordinates":[-3.060437,52.696793],"type":"Point"}
}