{
  "type": "Feature",
  "properties": {
    "addr:full":"35 Craven Terrace, Lancaster Gate London Greater London W2 3EL",
    "addr:housenumber":"35",
    "addr:postcode":"w2 3el",
    "addr:street":"Craven Terrace Lancaster Gate",
    "iso:country":"GB",
    "sg:address":"35 Craven Terrace, Lancaster Gate",
    "sg:city":"London",
    "sg:classifiers":[
        {
            "category":"Travel",
            "subcategory":"Hotels & Motels",
            "type":"Entertainment"
        }
    ],
    "sg:phone":"+44 20 7723 9276",
    "sg:postcode":"W2 3EL",
    "sg:province":"Greater London",
    "wof:name":"Lancaster Hall Hotel Ltd.",
    "wof:placetype":"venue"
},
  "geometry": {"coordinates":[-0.179113999,51.5132865906],"type":"Point"}
}