{
  "type": "Feature",
  "properties": {
    "addr:full":"11 Palmerston Rd, Sutton Surrey SM1 4QL",
    "addr:housenumber":"11",
    "addr:postcode":"sm1 4ql",
    "addr:street":"Palmerston Rd",
    "iso:country":"GB",
    "sg:address":"11 Palmerston Rd,",
    "sg:city":"Sutton",
    "sg:classifiers":[
        {
            "category":"Real Estate",
            "subcategory":"Architect",
            "type":"Services"
        }
    ],
    "sg:postcode":"SM1 4QL",
    "sg:province":"Surrey",
    "wof:name":"Wilgate (Engineering) Ltd",
    "wof:placetype":"venue"
},
  "geometry": {"coordinates":[-0.185603,51.365108],"type":"Point"}
}