{
  "type": "Feature",
  "properties": {
    "iso:country":"GB",
    "sg:address":"28 Sycamore Ave, Chandlers Ford",
    "sg:city":"Southampton",
    "sg:classifiers":[
        {
            "category":"Building & Trades",
            "subcategory":"Construction",
            "type":"Services"
        }
    ],
    "sg:phone":"+44 23 8090 7139",
    "sg:postcode":"SO53 5RH",
    "sg:province":"Hampshire",
    "sg:tags":[
        "roofing"
    ],
    "wof:name":"Banbury,Alan,",
    "wof:placetype":"venue"
},
  "geometry": {"coordinates":[-1.3825900555,50.9994812012],"type":"Point"}
}