{
  "type": "Feature",
  "properties": {
    "iso:country":"GB",
    "sg:address":"7 Paxton Terrace",
    "sg:city":"Eyemouth",
    "sg:classifiers":[
        {
            "category":"Building & Trades",
            "subcategory":"Plumbing",
            "type":"Services"
        }
    ],
    "sg:phone":"+44 1890 750210",
    "sg:postcode":"TD14 5EL",
    "sg:province":"Scottish Borders",
    "sg:tags":[
        "heating"
    ],
    "wof:name":"J G & H Collin",
    "wof:placetype":"venue"
},
  "geometry": {"coordinates":[-2.0916171074,55.8719863892],"type":"Point"}
}