{
  "type": "Feature",
  "properties": {
    "addr:full":"2 Nelson Street Congleton Cheshire CW12 4BS",
    "addr:housenumber":"2",
    "addr:postcode":"cw12 4bs",
    "addr:street":"Nelson Street",
    "iso:country":"GB",
    "sg:address":"2 Nelson Street",
    "sg:city":"Congleton",
    "sg:classifiers":[
        {
            "category":"Education",
            "subcategory":"Special Training",
            "type":"Public Place"
        }
    ],
    "sg:phone":"+44 1260 271685",
    "sg:postcode":"CW12 4BS",
    "sg:province":"Cheshire",
    "sg:tags":[
        "school",
        "language"
    ],
    "wof:name":"Eurolingua Institute",
    "wof:placetype":"venue"
},
  "geometry": {"coordinates":[-2.2165958881,53.1610374451],"type":"Point"}
}