{
  "type": "Feature",
  "properties": {
    "iso:country":"GB",
    "sg:address":"135 Stroud Green Rd",
    "sg:city":"Finsbury Park",
    "sg:classifiers":[
        {
            "category":"Shopping",
            "subcategory":"Clothing, Apparel, & Fashions",
            "type":"Retail Goods"
        }
    ],
    "sg:phone":"+44 20 7263 5010",
    "sg:postcode":"N4 3PX",
    "sg:province":"Greater London",
    "sg:tags":[
        "shop"
    ],
    "wof:name":"Fresh",
    "wof:placetype":"venue"
},
  "geometry": {"coordinates":[-0.112958,51.569489],"type":"Point"}
}