{
  "type": "Feature",
  "properties": {
    "iso:country":"GB",
    "sg:address":"7 Main Street",
    "sg:city":"Milnthorpe",
    "sg:classifiers":[
        {
            "category":"Food & Beverages",
            "subcategory":"Fruits & Vegetables",
            "type":"Retail Goods"
        }
    ],
    "sg:phone":"+44 15395 64615",
    "sg:postcode":"LA7 7PN",
    "sg:province":"Cumbria",
    "sg:tags":[
        "greengrocer"
    ],
    "wof:name":"Grisedale Fruit & Veg",
    "wof:placetype":"venue"
},
  "geometry": {"coordinates":[-2.7726809978,54.2269973755],"type":"Point"}
}