{
  "type": "Feature",
  "properties": {
    "addr:full":"175 Almond Road, Abronhill Glasgow Falkirk G67 3AL",
    "addr:housenumber":"175",
    "addr:postcode":"g67 3al",
    "addr:street":"Almond Road",
    "iso:country":"GB",
    "sg:address":"175 Almond Road, Abronhill",
    "sg:city":"Glasgow",
    "sg:classifiers":[
        {
            "category":"Home & Garden",
            "subcategory":"Building Materials",
            "type":"Retail Goods"
        }
    ],
    "sg:postcode":"G67 3AL",
    "sg:province":"Falkirk",
    "sg:tags":[
        "fencing"
    ],
    "wof:name":"J D Engineering",
    "wof:placetype":"venue"
},
  "geometry": {"coordinates":[-3.9456479549,55.9614715576],"type":"Point"}
}