{
  "type": "Feature",
  "properties": {
    "iso:country":"GB",
    "sg:address":"43 Stirling Close, North Yate",
    "sg:city":"Bristol",
    "sg:classifiers":[
        {
            "category":"Building & Trades",
            "subcategory":"Construction",
            "type":"Services"
        }
    ],
    "sg:phone":"+44 1454 882840",
    "sg:postcode":"BS37 5UJ",
    "sg:province":"Gloucestershire",
    "sg:tags":[
        "surfacing",
        "road"
    ],
    "wof:name":"Advance Markings",
    "wof:placetype":"venue"
},
  "geometry": {"coordinates":[-2.419448,51.550758],"type":"Point"}
}