{
  "type": "Feature",
  "properties": {
    "iso:country":"GB",
    "sg:address":"P O Box 28",
    "sg:city":"Aldershot",
    "sg:classifiers":[
        {
            "category":"Recreation",
            "subcategory":"Fishing",
            "type":"Entertainment"
        }
    ],
    "sg:phone":"+44 1252 336048",
    "sg:postcode":"GU11 3YG",
    "sg:province":"Hampshire",
    "sg:tags":[
        "equipment",
        "angling"
    ],
    "wof:name":"Cloth Tag Originals Ltd.",
    "wof:placetype":"venue"
},
  "geometry": {"coordinates":[-0.759346,51.249603],"type":"Point"}
}