{
  "type": "Feature",
  "properties": {
    "iso:country":"GB",
    "sg:address":"71 Hobs Moat Road",
    "sg:city":"Solihull",
    "sg:classifiers":[
        {
            "category":"Home & Garden",
            "subcategory":"Hardware",
            "type":"Retail Goods"
        }
    ],
    "sg:phone":"+44 121 743 4798",
    "sg:postcode":"B92 8JJ",
    "sg:province":"West Midlands",
    "wof:name":"Martins Hardware",
    "wof:placetype":"venue"
},
  "geometry": {"coordinates":[-1.784922,52.443352],"type":"Point"}
}