{
  "type": "Feature",
  "properties": {
    "addr:full":"8-9 Upper Grn Wolverhampton Shropshire WV6 8QQ",
    "addr:housenumber":"8-9",
    "addr:postcode":"wv6 8qq",
    "addr:street":"Upper Grn",
    "iso:country":"GB",
    "sg:address":"8-9 Upper Grn",
    "sg:city":"Wolverhampton",
    "sg:classifiers":[
        {
            "category":"Food & Beverages",
            "subcategory":"Fruits & Vegetables",
            "type":"Retail Goods"
        }
    ],
    "sg:phone":"+44 1902 751216",
    "sg:postcode":"WV6 8QQ",
    "sg:province":"Shropshire",
    "sg:tags":[
        "greengrocer"
    ],
    "wof:name":"Jim Gough Ltd.",
    "wof:placetype":"venue"
},
  "geometry": {"coordinates":[-2.1682379246,52.5982208252],"type":"Point"}
}