{
  "type": "Feature",
  "properties": {
    "addr:full":"39 Newtoft Street Edinburgh City of Edinburgh EH17 8RB",
    "addr:housenumber":"39",
    "addr:postcode":"eh17 8rb",
    "addr:street":"Newtoft Street",
    "iso:country":"GB",
    "sg:address":"39 Newtoft Street",
    "sg:city":"Edinburgh",
    "sg:classifiers":[
        {
            "category":"Fast Food",
            "type":"Food & Drink"
        },
        {
            "category":"Restaurant",
            "type":"Food & Drink"
        }
    ],
    "sg:phone":"+44 131 664 8552",
    "sg:postcode":"EH17 8RB",
    "sg:province":"City of Edinburgh",
    "sg:tags":[
        "away",
        "take"
    ],
    "wof:name":"HALOMAN CARRY OUT",
    "wof:placetype":"venue"
},
  "geometry": {"coordinates":[-3.1353189945,55.9048118591],"type":"Point"}
}