{
  "type": "Feature",
  "properties": {
    "addr:full":"26-28 Midmoor Rd Sunderland Tyne and Wear SR4 6LU",
    "addr:housenumber":"26-28",
    "addr:postcode":"sr4 6lu",
    "addr:street":"Midmoor Rd",
    "iso:country":"GB",
    "sg:address":"26-28 Midmoor Rd",
    "sg:city":"Sunderland",
    "sg:classifiers":[
        {
            "category":"Ice Cream",
            "type":"Food & Drink"
        }
    ],
    "sg:postcode":"SR4 6LU",
    "sg:province":"Tyne and Wear",
    "sg:tags":[
        "mnfr"
    ],
    "wof:name":"Geraldi,J,",
    "wof:placetype":"venue"
},
  "geometry": {"coordinates":[-1.416638,54.907471],"type":"Point"}
}