{
  "type": "Feature",
  "properties": {
    "addr:full":"Blooms Farm Cottage, Delvin End, Sible Hedingham Halstead Essex CO9 3LN",
    "addr:postcode":"co9 3ln",
    "addr:street":"Delvin End",
    "iso:country":"GB",
    "sg:address":"Blooms Farm Cottage, Delvin End, Sible Hedingham",
    "sg:city":"Halstead",
    "sg:classifiers":[
        {
            "category":"Retail",
            "subcategory":"Animal Services",
            "type":"Services"
        },
        {
            "category":"Personal",
            "subcategory":"Adult",
            "type":"Services"
        }
    ],
    "sg:phone":"+44 1787 462473",
    "sg:postcode":"CO9 3LN",
    "sg:province":"Essex",
    "sg:tags":[
        "farrier",
        "equestrian"
    ],
    "wof:name":"KEVIN J BELL",
    "wof:placetype":"venue"
},
  "geometry": {"coordinates":[0.592345,51.978249],"type":"Point"}
}