{
  "type": "Feature",
  "properties": {
    "iso:country":"GB",
    "sg:address":"Wamil Court, Wamil Way, Mildenhall",
    "sg:city":"Bury St Edmunds",
    "sg:classifiers":[
        {
            "category":"Social Services",
            "subcategory":"Retirement Home",
            "type":"Services"
        },
        {
            "category":"Government",
            "subcategory":"Office",
            "type":"Public Place"
        }
    ],
    "sg:phone":"+44 1638 714751",
    "sg:postcode":"IP28 7JU",
    "sg:province":"Cambridgeshire",
    "sg:tags":[
        "residential",
        "local",
        "care"
    ],
    "wof:name":"Wamil Court",
    "wof:placetype":"venue"
},
  "geometry": {"coordinates":[0.50519,52.343491],"type":"Point"}
}