{
  "type": "Feature",
  "properties": {
    "iso:country":"GB",
    "sg:address":"Mains Of Kilravock, Croy",
    "sg:city":"Inverness",
    "sg:classifiers":[
        {
            "category":"Professional",
            "type":"Services"
        },
        {
            "category":"Banks & Credit Unions",
            "subcategory":"Investment Brokerage",
            "type":"Services"
        },
        {
            "category":"Farming",
            "subcategory":"Dairy Farm",
            "type":"Manufacturing & Wholesale Goods"
        }
    ],
    "sg:phone":"+44 1667 493286",
    "sg:postcode":"IV2 7PJ",
    "sg:province":"Highland",
    "sg:tags":[
        "agricultural",
        "contractor"
    ],
    "wof:name":"William John Lean",
    "wof:placetype":"venue"
},
  "geometry": {"coordinates":[-3.98159,57.518909],"type":"Point"}
}