{
  "type": "Feature",
  "properties": {
    "addr:full":"6a Mounthooly Street, Lerwick Lerwick Shetland Islands ZE1 0BJ",
    "addr:housenumber":"6a",
    "addr:postcode":"ze1 0bj",
    "addr:street":"Mounthooly Street",
    "iso:country":"GB",
    "sg:address":"6a Mounthooly Street, Lerwick",
    "sg:city":"Lerwick",
    "sg:classifiers":[
        {
            "category":"Social Services",
            "subcategory":"Job Training",
            "type":"Services"
        },
        {
            "category":"Education",
            "subcategory":"Special Training",
            "type":"Public Place"
        }
    ],
    "sg:phone":"+44 1595 695026",
    "sg:postcode":"ZE1 0BJ",
    "sg:province":"Shetland Islands",
    "sg:tags":[
        "product",
        "centre"
    ],
    "wof:name":"Support Training Ltd",
    "wof:placetype":"venue"
},
  "geometry": {"coordinates":[-1.143286,60.152794],"type":"Point"}
}