{
  "type": "Feature",
  "properties": {
    "addr:full":"Earsby Street London Greater London W14 8SH",
    "addr:postcode":"w14 8sh",
    "addr:street":"Earsby Street",
    "iso:country":"GB",
    "sg:address":"Earsby Street",
    "sg:city":"London",
    "sg:classifiers":[
        {
            "category":"Education",
            "subcategory":"School",
            "type":"Public Place"
        },
        {
            "category":"Government",
            "subcategory":"Office",
            "type":"Public Place"
        }
    ],
    "sg:phone":"+44 20 7603 9750",
    "sg:postcode":"W14 8SH",
    "sg:province":"Greater London",
    "sg:tags":[
        "local",
        "authority"
    ],
    "wof:name":"Avonmore Primary School",
    "wof:placetype":"venue"
},
  "geometry": {"coordinates":[-0.2092839926,51.4956169128],"type":"Point"}
}