{
  "type": "Feature",
  "properties": {
    "addr:full":"Buckingham House, West St Congleton Cheshire CW12 1JN",
    "addr:postcode":"cw12 1jn",
    "addr:street":"West St",
    "iso:country":"GB",
    "sg:address":"Buckingham House, West St",
    "sg:city":"Congleton",
    "sg:classifiers":[
        {
            "category":"Freight",
            "type":"Transportation"
        }
    ],
    "sg:phone":"+44 1260 290430",
    "sg:postcode":"CW12 1JN",
    "sg:province":"Cheshire",
    "sg:tags":[
        "haulage",
        "road"
    ],
    "wof:name":"Dettendorfer Ltd",
    "wof:placetype":"venue"
},
  "geometry": {"coordinates":[-2.2205140591,53.1645393372],"type":"Point"}
}