{
  "type": "Feature",
  "properties": {
    "addr:full":"9 Princeton Court, 53-55 Felsham Road, Putney London Greater London SW15 1AZ",
    "addr:housenumber":"9;53-55",
    "addr:postcode":"sw15 1az",
    "addr:street":"Princeton Court;Felsham Road",
    "iso:country":"GB",
    "sg:address":"9 Princeton Court, 53-55 Felsham Road, Putney",
    "sg:city":"London",
    "sg:classifiers":[
        {
            "category":"Professional",
            "type":"Services"
        }
    ],
    "sg:phone":"+44 20 8788 5008",
    "sg:postcode":"SW15 1AZ",
    "sg:province":"Greater London",
    "sg:tags":[
        "interior",
        "furnishers",
        "designer"
    ],
    "wof:name":"Howard & Horsfield",
    "wof:placetype":"venue"
},
  "geometry": {"coordinates":[-0.2156240046,51.4636535645],"type":"Point"}
}