{
  "type": "Feature",
  "properties": {
    "addr:full":"306 Charminster Road Bournemouth Dorset BH8 9RT",
    "addr:housenumber":"306",
    "addr:postcode":"bh8 9rt",
    "addr:street":"Charminster Road",
    "iso:country":"GB",
    "sg:address":"306 Charminster Road",
    "sg:city":"Bournemouth",
    "sg:classifiers":[
        {
            "category":"Shopping",
            "subcategory":"Florist",
            "type":"Retail Goods"
        }
    ],
    "sg:postcode":"BH8 9RT",
    "sg:province":"Dorset",
    "wof:name":"Children Wish (U K) Ltd",
    "wof:placetype":"venue"
},
  "geometry": {"coordinates":[-1.8629590273,50.7408447266],"type":"Point"}
}