{
  "type": "Feature",
  "properties": {
    "iso:country":"GB",
    "sg:address":"132/138 Charnwood Street",
    "sg:city":"Leicester",
    "sg:classifiers":[
        {
            "category":"Wholesale",
            "subcategory":"Non-durable Goods",
            "type":"Manufacturing & Wholesale Goods"
        },
        {
            "category":"Food & Beverages",
            "subcategory":"Supermarket",
            "type":"Retail Goods"
        }
    ],
    "sg:phone":"+44 116 251 0950",
    "sg:postcode":"LE2 0BG",
    "sg:province":"Leicestershire",
    "sg:tags":[
        "frozen",
        "animal",
        "by-product"
    ],
    "wof:name":"Euro-Worldwide Associates Ltd.",
    "wof:placetype":"venue"
},
  "geometry": {"coordinates":[-1.114118,52.638741],"type":"Point"}
}