{
  "type": "Feature",
  "properties": {
    "addr:full":"Unit 4 Southfields Indust Est, Delling La Chichester West Sussex PO18 8NW",
    "addr:housenumber":"unit 4",
    "addr:postcode":"po18 8nw",
    "addr:street":"Indust;Delling La Chichester",
    "iso:country":"GB",
    "sg:address":"Unit 4 Southfields Indust Est, Delling La",
    "sg:city":"Chichester",
    "sg:classifiers":[
        {
            "category":"Wholesale",
            "subcategory":"Fruits & Vegetables",
            "type":"Manufacturing & Wholesale Goods"
        }
    ],
    "sg:phone":"+44 1243 572661",
    "sg:postcode":"PO18 8NW",
    "sg:province":"West Sussex",
    "wof:name":"Runner Bean",
    "wof:placetype":"venue"
},
  "geometry": {"coordinates":[-0.85138,50.837551],"type":"Point"}
}