{
  "type": "Feature",
  "properties": {
    "addr:full":"1 Wilton Road London Greater London SE2 9RH",
    "addr:housenumber":"1",
    "addr:postcode":"se2 9rh",
    "addr:street":"Wilton Road",
    "iso:country":"GB",
    "sg:address":"1 Wilton Road",
    "sg:city":"London",
    "sg:classifiers":[
        {
            "category":"Real Estate",
            "subcategory":"Real Estate Agent",
            "type":"Services"
        }
    ],
    "sg:phone":"+44 20 8311 0102",
    "sg:postcode":"SE2 9RH",
    "sg:province":"Greater London",
    "wof:name":"Halifax Property Services",
    "wof:placetype":"venue"
},
  "geometry": {"coordinates":[0.121206,51.489864],"type":"Point"}
}