{
  "type": "Feature",
  "properties": {
    "iso:country":"GB",
    "sg:address":"Railway Street, Ramsbottom",
    "sg:city":"Bury",
    "sg:classifiers":[
        {
            "category":"Freight",
            "type":"Transportation"
        },
        {
            "category":"Professional",
            "subcategory":"Credit Reporting & Collection",
            "type":"Services"
        }
    ],
    "sg:phone":"+44 1706 824291",
    "sg:postcode":"BL0 9AL",
    "sg:province":"Lancashire",
    "sg:tags":[
        "collecting",
        "haulage",
        "agency",
        "road",
        "transport"
    ],
    "wof:name":"Equity Credit Services Ltd",
    "wof:placetype":"venue"
},
  "geometry": {"coordinates":[-2.315044,53.647449],"type":"Point"}
}