{
  "type": "Feature",
  "properties": {
    "iso:country":"GB",
    "sg:address":"7 York Place, Agar Nook",
    "sg:city":"Coalville",
    "sg:classifiers":[
        {
            "category":"Building & Trades",
            "subcategory":"Construction",
            "type":"Services"
        }
    ],
    "sg:postcode":"LE67 4TH",
    "sg:province":"Leicestershire",
    "sg:tags":[
        "decorator",
        "painter"
    ],
    "wof:name":"Highland Decorators Ltd",
    "wof:placetype":"venue"
},
  "geometry": {"coordinates":[-1.324948,52.72514],"type":"Point"}
}