{
  "type": "Feature",
  "properties": {
    "iso:country":"GB",
    "sg:address":"86 Bell Street",
    "sg:city":"Dundee",
    "sg:classifiers":[
        {
            "category":"Professional",
            "subcategory":"Lawyer & Legal Services",
            "type":"Services"
        }
    ],
    "sg:phone":"+44 1382 201010",
    "sg:postcode":"DD1 1JQ",
    "sg:province":"Dundee City",
    "sg:tags":[
        "solicitor"
    ],
    "wof:name":"Ross Strachan & Co.",
    "wof:placetype":"venue"
},
  "geometry": {"coordinates":[-2.9716980457,56.4638290405],"type":"Point"}
}