{
  "type": "Feature",
  "properties": {
    "iso:country":"GB",
    "sg:address":"Unit 93, Old Mill Lane Industrial Estate, Mansfield Woodhouse",
    "sg:city":"Mansfield",
    "sg:classifiers":[
        {
            "category":"Shopping",
            "subcategory":"Stationery & Office Supplies",
            "type":"Retail Goods"
        }
    ],
    "sg:phone":"+44 1623 635482",
    "sg:postcode":"NG19 9BG",
    "sg:province":"Derbyshire",
    "wof:name":"Connect",
    "wof:placetype":"venue"
},
  "geometry": {"coordinates":[-1.188625,53.158104],"type":"Point"}
}