{
  "type": "Feature",
  "properties": {
    "iso:country":"GB",
    "sg:address":"The Old Mill, Hicks Mill",
    "sg:city":"Truro",
    "sg:classifiers":[
        {
            "category":"Travel",
            "subcategory":"Hotels & Motels",
            "type":"Entertainment"
        }
    ],
    "sg:phone":"+44 1872 865480",
    "sg:postcode":"TR4 8RB",
    "sg:province":"Cornwall",
    "sg:tags":[
        "self",
        "catering"
    ],
    "wof:name":"Bawden R.B.T",
    "wof:placetype":"venue"
},
  "geometry": {"coordinates":[-5.12974,50.227669],"type":"Point"}
}