{
  "type": "Feature",
  "properties": {
    "iso:country":"GB",
    "sg:address":"17 Bedford Row",
    "sg:city":"London",
    "sg:classifiers":[
        {
            "category":"Professional",
            "subcategory":"Lawyer & Legal Services",
            "type":"Services"
        }
    ],
    "sg:phone":"+44 20 7831 7314",
    "sg:postcode":"WC1R 4EB",
    "sg:province":"Greater London",
    "sg:tags":[
        "barrister"
    ],
    "wof:name":"F Raffray",
    "wof:placetype":"venue"
},
  "geometry": {"coordinates":[-0.116059,51.520271],"type":"Point"}
}