{
  "type": "Feature",
  "properties": {
    "iso:country":"GB",
    "sg:address":"371 Banbury Road",
    "sg:city":"Oxford",
    "sg:classifiers":[
        {
            "category":"Real Estate",
            "subcategory":"Developer",
            "type":"Services"
        }
    ],
    "sg:phone":"+44 1865 316787",
    "sg:postcode":"OX2 7RE",
    "sg:province":"Oxfordshire",
    "sg:tags":[
        "property"
    ],
    "wof:name":"Henaud Developments",
    "wof:placetype":"venue"
},
  "geometry": {"coordinates":[-1.269641,51.785473],"type":"Point"}
}