{
  "type": "Feature",
  "properties": {
    "addr:full":"110-116 Ormside Street London Greater London SE15 1TF",
    "addr:housenumber":"110-116",
    "addr:postcode":"se15 1tf",
    "addr:street":"Ormside Street",
    "iso:country":"GB",
    "sg:address":"110-116 Ormside Street",
    "sg:city":"London",
    "sg:classifiers":[
        {
            "category":"Building & Trades",
            "subcategory":"Construction",
            "type":"Services"
        }
    ],
    "sg:phone":"+44 20 7277 5661",
    "sg:postcode":"SE15 1TF",
    "sg:province":"Greater London",
    "sg:tags":[
        "builder"
    ],
    "wof:name":"Saltash Enterprises Ltd.",
    "wof:placetype":"venue"
},
  "geometry": {"coordinates":[-0.055863,51.48259],"type":"Point"}
}