{
  "type": "Feature",
  "properties": {
    "addr:full":"Banavie Fort William Highland PH33 7PD",
    "addr:postcode":"ph33 7pd",
    "addr:street":"Banavie Fort William",
    "iso:country":"GB",
    "sg:address":"Banavie",
    "sg:city":"Fort William",
    "sg:classifiers":[
        {
            "category":"Travel",
            "subcategory":"Hotels & Motels",
            "type":"Entertainment"
        }
    ],
    "sg:phone":"+44 1397 712700",
    "sg:postcode":"PH33 7PD",
    "sg:province":"Highland",
    "wof:name":"Glenloy Lodge Hotel",
    "wof:placetype":"venue"
},
  "geometry": {"coordinates":[-5.0979790688,56.8413619995],"type":"Point"}
}