{
  "type": "Feature",
  "properties": {
    "addr:full":"35-37 Barber Street, Eastwood Nottingham Derbyshire NG16 3EW",
    "addr:housenumber":"35-37",
    "addr:postcode":"ng16 3ew",
    "addr:street":"Barber Street",
    "iso:country":"GB",
    "sg:address":"35-37 Barber Street, Eastwood",
    "sg:city":"Nottingham",
    "sg:classifiers":[
        {
            "category":"Building & Trades",
            "subcategory":"Construction",
            "type":"Services"
        }
    ],
    "sg:phone":"+44 1773 760586",
    "sg:postcode":"NG16 3EW",
    "sg:province":"Derbyshire",
    "sg:tags":[
        "contractor"
    ],
    "wof:name":"D R Construction Ltd.",
    "wof:placetype":"venue"
},
  "geometry": {"coordinates":[-1.293653,53.015961],"type":"Point"}
}