{
  "type": "Feature",
  "properties": {
    "addr:full":"Banners Building Attercliffe, Road, Sheffield South Yorkshire S9 3QS",
    "addr:postcode":"s9 3qs",
    "addr:street":"Attercliffe Road",
    "iso:country":"GB",
    "sg:address":"Banners Building Attercliffe, Road,",
    "sg:city":"Sheffield",
    "sg:classifiers":[
        {
            "category":"Shopping",
            "subcategory":"Books",
            "type":"Retail Goods"
        }
    ],
    "sg:postcode":"S9 3QS",
    "sg:province":"South Yorkshire",
    "wof:name":"Cybertechnics Ltd",
    "wof:placetype":"venue"
},
  "geometry": {"coordinates":[-1.43297,53.393299],"type":"Point"}
}