{
  "type": "Feature",
  "properties": {
    "addr:full":"Market Muir Court Inverurie Aberdeenshire AB51 4ZP",
    "addr:postcode":"ab51 4zp",
    "addr:street":"Muir Court",
    "iso:country":"GB",
    "sg:address":"Market Muir Court",
    "sg:city":"Inverurie",
    "sg:classifiers":[
        {
            "category":"Social Services",
            "subcategory":"Adult Care",
            "type":"Services"
        },
        {
            "category":"Government",
            "subcategory":"Office",
            "type":"Public Place"
        }
    ],
    "sg:phone":"+44 1467 621228",
    "sg:postcode":"AB51 4ZP",
    "sg:province":"Aberdeenshire",
    "sg:tags":[
        "housing",
        "local",
        "sheltered"
    ],
    "wof:name":"Market Muir Court Sheltered Housing",
    "wof:placetype":"venue"
},
  "geometry": {"coordinates":[-2.389794,57.291119],"type":"Point"}
}