{
  "type": "Feature",
  "properties": {
    "addr:full":"Cva House, 2 Cooper Road Bristol Gloucestershire BS35 3UP",
    "addr:housenumber":"2",
    "addr:postcode":"bs35 3up",
    "addr:street":"Cooper Road",
    "iso:country":"GB",
    "sg:address":"Cva House, 2 Cooper Road",
    "sg:city":"Bristol",
    "sg:classifiers":[
        {
            "category":"Communications",
            "type":"Services"
        }
    ],
    "sg:phone":"+44 1454 281858",
    "sg:postcode":"BS35 3UP",
    "sg:province":"Gloucestershire",
    "sg:tags":[
        "audio-visual"
    ],
    "wof:name":"Cva Equipment Ltd.",
    "wof:placetype":"venue"
},
  "geometry": {"coordinates":[-2.524052,51.601639],"type":"Point"}
}