{
  "type": "Feature",
  "properties": {
    "addr:full":"Simpson Wreford & Partners, Suffolk House, George Street Croydon Surrey CR0 0YN",
    "addr:postcode":"cr0 0yn",
    "addr:street":"George Street",
    "iso:country":"GB",
    "sg:address":"Simpson Wreford & Partners, Suffolk House, George Street",
    "sg:city":"Croydon",
    "sg:classifiers":[
        {
            "category":"Real Estate",
            "subcategory":"Developer",
            "type":"Services"
        }
    ],
    "sg:postcode":"CR0 0YN",
    "sg:province":"Surrey",
    "sg:tags":[
        "property"
    ],
    "wof:name":"Victoria Soames Ltd",
    "wof:placetype":"venue"
},
  "geometry": {"coordinates":[-0.0107100001,51.3433418274],"type":"Point"}
}