{
  "type": "Feature",
  "properties": {
    "addr:full":"6 Grove Road, Up Holland Wigan Lancashire WN8 0LH",
    "addr:housenumber":"6",
    "addr:postcode":"wn8 0lh",
    "addr:street":"Grove Road",
    "iso:country":"GB",
    "sg:address":"6 Grove Road, Up Holland",
    "sg:city":"Wigan",
    "sg:classifiers":[
        {
            "category":"Professional",
            "subcategory":"Art Services",
            "type":"Services"
        }
    ],
    "sg:postcode":"WN8 0LH",
    "sg:province":"Lancashire",
    "sg:tags":[
        "graphic",
        "designer"
    ],
    "wof:name":"Orange Box Design",
    "wof:placetype":"venue"
},
  "geometry": {"coordinates":[-2.724658,53.545151],"type":"Point"}
}