{
  "type": "Feature",
  "properties": {
    "iso:country":"GB",
    "sg:address":"84 Cambridge Road, Walsworth",
    "sg:city":"Hitchin",
    "sg:classifiers":[
        {
            "category":"Bars & Pubs",
            "type":"Food & Drink"
        }
    ],
    "sg:phone":"+44 1462 432091",
    "sg:postcode":"SG4 0JH",
    "sg:province":"Hertfordshire",
    "sg:tags":[
        "pubs",
        "inn"
    ],
    "wof:name":"The Anchor",
    "wof:placetype":"venue"
},
  "geometry": {"coordinates":[-0.2574029863,51.955619812],"type":"Point"}
}