{
  "type": "Feature",
  "properties": {
    "addr:full":"11 Penywerlod Terrace, Markham Blackwood Caerphilly NP12 0RE",
    "addr:housenumber":"11",
    "addr:postcode":"np12 0re",
    "addr:street":"Penywerlod Terrace",
    "iso:country":"GB",
    "sg:address":"11 Penywerlod Terrace, Markham",
    "sg:city":"Blackwood",
    "sg:classifiers":[
        {
            "category":"Building & Trades",
            "subcategory":"Construction",
            "type":"Services"
        }
    ],
    "sg:phone":"+44 1495 220506",
    "sg:postcode":"NP12 0RE",
    "sg:province":"Caerphilly",
    "sg:tags":[
        "builder"
    ],
    "wof:name":"Williams Bros",
    "wof:placetype":"venue"
},
  "geometry": {"coordinates":[-3.2092239857,51.7069168091],"type":"Point"}
}