{
  "type": "Feature",
  "properties": {
    "addr:full":"31 Melbourne Road Leicester Leicestershire LE2 0GT",
    "addr:housenumber":"31",
    "addr:postcode":"le2 0gt",
    "addr:street":"Melbourne Road",
    "iso:country":"GB",
    "sg:address":"31 Melbourne Road",
    "sg:city":"Leicester",
    "sg:classifiers":[
        {
            "category":"Shopping",
            "subcategory":"Department Store",
            "type":"Retail Goods"
        }
    ],
    "sg:postcode":"LE2 0GT",
    "sg:province":"Leicestershire",
    "wof:name":"Apna Supermarket",
    "wof:placetype":"venue"
},
  "geometry": {"coordinates":[-1.1135439873,52.631187439],"type":"Point"}
}