{
  "type": "Feature",
  "properties": {
    "iso:country":"GB",
    "sg:address":"Amberley Farm, Cheltenham Rd",
    "sg:city":"Evesham",
    "sg:classifiers":[
        {
            "category":"Home & Garden",
            "subcategory":"Garden Supply",
            "type":"Retail Goods"
        }
    ],
    "sg:phone":"+44 1386 442055",
    "sg:postcode":"WR11 6LW",
    "sg:province":"Gloucestershire",
    "sg:tags":[
        "nursery",
        "centre"
    ],
    "wof:name":"S F Hoddinott",
    "wof:placetype":"venue"
},
  "geometry": {"coordinates":[-1.9439690113,52.1063919067],"type":"Point"}
}