{
  "type": "Feature",
  "properties": {
    "addr:full":"Station Road Crediton Devon EX17 6HU",
    "addr:postcode":"ex17 6hu",
    "addr:street":"Station Road",
    "iso:country":"GB",
    "sg:address":"Station Road",
    "sg:city":"Crediton",
    "sg:classifiers":[
        {
            "category":"Home & Garden",
            "subcategory":"Hardware",
            "type":"Retail Goods"
        }
    ],
    "sg:postcode":"EX17 6HU",
    "sg:province":"Devon",
    "sg:tags":[
        "lawnmowers",
        "machinery"
    ],
    "wof:name":"M S Leigh & Sons",
    "wof:placetype":"venue"
},
  "geometry": {"coordinates":[-3.820047,50.78561],"type":"Point"}
}