{
  "type": "Feature",
  "properties": {
    "addr:full":"Oriental City, 399 Edgware Road London Greater London NW9 0JJ",
    "addr:housenumber":"399",
    "addr:postcode":"nw9 0jj",
    "addr:street":"Edgware Road",
    "iso:country":"GB",
    "sg:address":"Oriental City, 399 Edgware Road",
    "sg:city":"London",
    "sg:classifiers":[
        {
            "category":"Personal",
            "type":"Services"
        }
    ],
    "sg:phone":"+44 20 8200 8700",
    "sg:postcode":"NW9 0JJ",
    "sg:province":"Greater London",
    "sg:tags":[
        "tailor"
    ],
    "wof:name":"Golden Fleece Made to Measure",
    "wof:placetype":"venue"
},
  "geometry": {"coordinates":[-0.25939,51.593731],"type":"Point"}
}