{
  "type": "Feature",
  "properties": {
    "addr:full":"164 Central Drive Blackpool Lancashire FY1 5EA",
    "addr:housenumber":"164",
    "addr:postcode":"fy1 5ea",
    "addr:street":"Central Drive",
    "iso:country":"GB",
    "sg:address":"164 Central Drive",
    "sg:city":"Blackpool",
    "sg:classifiers":[
        {
            "category":"Food & Beverages",
            "subcategory":"Candy",
            "type":"Retail Goods"
        },
        {
            "category":"Food & Beverages",
            "subcategory":"Bakery",
            "type":"Retail Goods"
        }
    ],
    "sg:phone":"+44 1253 622443",
    "sg:postcode":"FY1 5EA",
    "sg:province":"Lancashire",
    "sg:tags":[
        "confectioner",
        "baker"
    ],
    "wof:name":"Threfalls Confectioners",
    "wof:placetype":"venue"
},
  "geometry": {"coordinates":[-3.047623,53.810783],"type":"Point"}
}