{
  "type": "Feature",
  "properties": {
    "addr:full":"47 Birkett Street Wigan Lancashire WN1 3JA",
    "addr:housenumber":"47",
    "addr:postcode":"wn1 3ja",
    "addr:street":"Birkett Street",
    "iso:country":"GB",
    "sg:address":"47 Birkett Street",
    "sg:city":"Wigan",
    "sg:classifiers":[
        {
            "category":"Bars & Pubs",
            "type":"Food & Drink"
        }
    ],
    "sg:phone":"+44 1942 701637",
    "sg:postcode":"WN1 3JA",
    "sg:province":"Lancashire",
    "sg:tags":[
        "pubs",
        "inn"
    ],
    "wof:name":"Crispin Arms",
    "wof:placetype":"venue"
},
  "geometry": {"coordinates":[-2.615619,53.54641],"type":"Point"}
}