{
  "type": "Feature",
  "properties": {
    "iso:country":"GB",
    "sg:address":"10 Bellamy Lane",
    "sg:city":"Salisbury",
    "sg:classifiers":[
        {
            "category":"Social Services",
            "subcategory":"Retirement Home",
            "type":"Services"
        }
    ],
    "sg:phone":"+44 1722 331980",
    "sg:postcode":"SP1 2SP",
    "sg:province":"Wiltshire",
    "sg:tags":[
        "residential",
        "care"
    ],
    "wof:name":"Inwood House",
    "wof:placetype":"venue"
},
  "geometry": {"coordinates":[-1.786855,51.069195],"type":"Point"}
}