{
  "type": "Feature",
  "properties": {
    "addr:full":"Unit 2/4 Bath Somerset BA3 2BB",
    "addr:housenumber":"unit 2 / 4",
    "addr:postcode":"ba3 2bb",
    "iso:country":"GB",
    "sg:address":"Unit 2/4",
    "sg:city":"Bath",
    "sg:classifiers":[
        {
            "category":"Manufacturing",
            "subcategory":"Wood Products",
            "type":"Manufacturing & Wholesale Goods"
        },
        {
            "category":"Building & Trades",
            "subcategory":"Construction",
            "type":"Services"
        }
    ],
    "sg:phone":"+44 1761 415511",
    "sg:postcode":"BA3 2BB",
    "sg:province":"Somerset",
    "sg:tags":[
        "joinery",
        "manufacturer"
    ],
    "wof:name":"Somer Joinery Ltd.",
    "wof:placetype":"venue"
},
  "geometry": {"coordinates":[-2.481269,51.28783],"type":"Point"}
}