{
  "type": "Feature",
  "properties": {
    "addr:full":"96-98 Victoria St Grimsby Lincolnshire DN31 1BA",
    "addr:housenumber":"96-98",
    "addr:postcode":"dn31 1ba",
    "addr:street":"Victoria St",
    "iso:country":"GB",
    "sg:address":"96-98 Victoria St",
    "sg:city":"Grimsby",
    "sg:classifiers":[
        {
            "category":"Shopping",
            "subcategory":"Clothing, Apparel, & Fashions",
            "type":"Retail Goods"
        }
    ],
    "sg:phone":"+44 1472 361603",
    "sg:postcode":"DN31 1BA",
    "sg:province":"Lincolnshire",
    "sg:tags":[
        "shop"
    ],
    "wof:name":"Spinning Wheel Boutique",
    "wof:placetype":"venue"
},
  "geometry": {"coordinates":[-0.0811590031,53.5704231262],"type":"Point"}
}