{
  "type": "Feature",
  "properties": {
    "addr:full":"Unit 3a, Warren Wood Industrial Estate Hertford Hertfordshire SG14 3NU",
    "addr:housenumber":"unit 3a;estate",
    "addr:postcode":"sg14 3nu",
    "addr:street":"Warren Wood Industrial",
    "iso:country":"GB",
    "sg:address":"Unit 3a, Warren Wood Industrial Estate",
    "sg:city":"Hertford",
    "sg:classifiers":[
        {
            "category":"Retail",
            "subcategory":"Auto Repair",
            "type":"Services"
        }
    ],
    "sg:phone":"+44 7974 563779",
    "sg:postcode":"SG14 3NU",
    "sg:province":"Hertfordshire",
    "sg:tags":[
        "body",
        "car"
    ],
    "wof:name":"Watton Body Shop",
    "wof:placetype":"venue"
},
  "geometry": {"coordinates":[-0.101146,51.832447],"type":"Point"}
}