{
  "type": "Feature",
  "properties": {
    "iso:country":"GB",
    "sg:address":"100 Rosemount Place",
    "sg:city":"Aberdeen",
    "sg:classifiers":[
        {
            "category":"Shopping",
            "subcategory":"Clothing, Apparel, & Fashions",
            "type":"Retail Goods"
        }
    ],
    "sg:phone":"+44 1224 630967",
    "sg:postcode":"AB25 2XN",
    "sg:province":"Aberdeen City",
    "sg:tags":[
        "shop",
        "ladieswear"
    ],
    "wof:name":"Bentleys",
    "wof:placetype":"venue"
},
  "geometry": {"coordinates":[-2.114586,57.150223],"type":"Point"}
}