{
  "type": "Feature",
  "properties": {
    "addr:full":"Unit 40, The Galleria Hatfield Hertfordshire AL10 0XU",
    "addr:housenumber":"unit 40",
    "addr:postcode":"al10 0xu",
    "addr:street":"The Galleria Hatfield",
    "iso:country":"GB",
    "sg:address":"Unit 40, The Galleria",
    "sg:city":"Hatfield",
    "sg:classifiers":[
        {
            "category":"Shopping",
            "subcategory":"Music",
            "type":"Retail Goods"
        }
    ],
    "sg:phone":"+44 1707 251566",
    "sg:postcode":"AL10 0XU",
    "sg:province":"Hertfordshire",
    "sg:tags":[
        "record",
        "tape",
        "cd"
    ],
    "wof:name":"V Shop",
    "wof:placetype":"venue"
},
  "geometry": {"coordinates":[-0.2339649945,51.7610282898],"type":"Point"}
}