{
  "type": "Feature",
  "properties": {
    "addr:full":"Stanifield La Preston Lancashire PR5 2QA",
    "addr:postcode":"pr5 2qa",
    "addr:street":"La Preston",
    "iso:country":"GB",
    "sg:address":"Stanifield La",
    "sg:city":"Preston",
    "sg:classifiers":[
        {
            "category":"Place Of Worship",
            "type":"Public Place"
        }
    ],
    "sg:phone":"+44 1772 421174",
    "sg:postcode":"PR5 2QA",
    "sg:province":"Lancashire",
    "wof:name":"St Catherines R C Church",
    "wof:placetype":"venue"
},
  "geometry": {"coordinates":[-2.6830439568,53.7167434692],"type":"Point"}
}