{
  "type": "Feature",
  "properties": {
    "iso:country":"GB",
    "sg:address":"Cefn Wig Lane",
    "sg:city":"New Quay",
    "sg:classifiers":[
        {
            "category":"Shopping",
            "subcategory":"Gifts & Souvenirs",
            "type":"Retail Goods"
        }
    ],
    "sg:phone":"+44 1545 560778",
    "sg:postcode":"SA45 9NQ",
    "sg:province":"Ceredigion",
    "sg:tags":[
        "shop"
    ],
    "wof:name":"Pictoriana",
    "wof:placetype":"venue"
},
  "geometry": {"coordinates":[-4.36079,52.213673],"type":"Point"}
}