{
  "type": "Feature",
  "properties": {
    "addr:full":"Unit 1 George St Heckmondwike West Yorkshire WF16 9QP",
    "addr:housenumber":"unit 1",
    "addr:postcode":"wf16 9qp",
    "addr:street":"George St",
    "iso:country":"GB",
    "sg:address":"Unit 1 George St",
    "sg:city":"Heckmondwike",
    "sg:classifiers":[
        {
            "category":"Building & Trades",
            "subcategory":"Cleaning & Sanitation",
            "type":"Services"
        }
    ],
    "sg:phone":"+44 1924 400662",
    "sg:postcode":"WF16 9QP",
    "sg:province":"West Yorkshire",
    "sg:tags":[
        "cleaner",
        "window"
    ],
    "wof:name":"Joelee Window Cleaning Services",
    "wof:placetype":"venue"
},
  "geometry": {"coordinates":[-1.675374,53.708237],"type":"Point"}
}