{
  "type": "Feature",
  "properties": {
    "addr:full":"Kymba House, Drift Road, Whitehill Bordon Hampshire GU35 9DZ",
    "addr:postcode":"gu35 9dz",
    "addr:street":"Drift Road",
    "iso:country":"GB",
    "sg:address":"Kymba House, Drift Road, Whitehill",
    "sg:city":"Bordon",
    "sg:classifiers":[
        {
            "category":"Building & Trades",
            "subcategory":"Plumbing",
            "type":"Services"
        },
        {
            "category":"Home & Garden",
            "subcategory":"Building Materials",
            "type":"Retail Goods"
        }
    ],
    "sg:phone":"+44 1420 473401",
    "sg:postcode":"GU35 9DZ",
    "sg:province":"Hampshire",
    "sg:tags":[
        "ventilator",
        "plumber",
        "system",
        "ventilation"
    ],
    "wof:name":"AIRFLOW ENGINEERING SERVICES",
    "wof:placetype":"venue"
},
  "geometry": {"coordinates":[-0.8778560162,51.0991363525],"type":"Point"}
}