{
  "type": "Feature",
  "properties": {
    "addr:full":"140 Old Christchurch Road Bournemouth Dorset BH1 1NL",
    "addr:housenumber":"140",
    "addr:postcode":"bh1 1nl",
    "addr:street":"Old Christchurch Road",
    "iso:country":"GB",
    "sg:address":"140 Old Christchurch Road",
    "sg:city":"Bournemouth",
    "sg:classifiers":[
        {
            "category":"Food & Beverages",
            "subcategory":"Liquor & Beverages",
            "type":"Retail Goods"
        }
    ],
    "sg:phone":"+44 1202 555807",
    "sg:postcode":"BH1 1NL",
    "sg:province":"Dorset",
    "sg:tags":[
        "beer",
        "spirit",
        "wines"
    ],
    "wof:name":"The Liquor Store",
    "wof:placetype":"venue"
},
  "geometry": {"coordinates":[-1.8737059832,50.7223358154],"type":"Point"}
}