{
  "type": "Feature",
  "properties": {
    "addr:full":"56 High Rd Epping Essex CM16 6BY",
    "addr:housenumber":"56",
    "addr:postcode":"cm16 6by",
    "addr:street":"High Rd",
    "iso:country":"GB",
    "sg:address":"56 High Rd",
    "sg:city":"Epping",
    "sg:classifiers":[
        {
            "category":"Shopping",
            "subcategory":"Department Store",
            "type":"Retail Goods"
        }
    ],
    "sg:phone":"+44 1992 522257",
    "sg:postcode":"CM16 6BY",
    "sg:province":"Essex",
    "wof:name":"Londis",
    "wof:placetype":"venue"
},
  "geometry": {"coordinates":[0.167351,51.716179],"type":"Point"}
}