{
  "type": "Feature",
  "properties": {
    "iso:country":"GB",
    "sg:address":"30 King Street",
    "sg:city":"Leighton Buzzard",
    "sg:classifiers":[
        {
            "category":"Building & Trades",
            "subcategory":"Construction",
            "type":"Services"
        }
    ],
    "sg:postcode":"LU7 1BY",
    "sg:province":"Bedfordshire",
    "sg:tags":[
        "joiner",
        "carpenter"
    ],
    "wof:name":"K S M Carpentry Services",
    "wof:placetype":"venue"
},
  "geometry": {"coordinates":[-0.661346,51.922707],"type":"Point"}
}