{
  "type": "Feature",
  "properties": {
    "iso:country":"GB",
    "sg:address":"96 The Broadway, High St",
    "sg:city":"Chesham",
    "sg:classifiers":[
        {
            "category":"Bars & Pubs",
            "subcategory":"Nightclub",
            "type":"Food & Drink"
        }
    ],
    "sg:phone":"+44 1494 782792",
    "sg:postcode":"HP5 1EG",
    "sg:province":"Buckinghamshire",
    "sg:tags":[
        "karaoke"
    ],
    "wof:name":"Bg Karaoke",
    "wof:placetype":"venue"
},
  "geometry": {"coordinates":[-0.612114,51.706348],"type":"Point"}
}