{
  "type": "Feature",
  "properties": {
    "addr:full":"22 Hartville Rd Woolwich Greater London SE18 1DQ",
    "addr:housenumber":"22",
    "addr:postcode":"se18 1dq",
    "addr:street":"Hartville Rd",
    "iso:country":"GB",
    "sg:address":"22 Hartville Rd",
    "sg:city":"Woolwich",
    "sg:classifiers":[
        {
            "category":"Building & Trades",
            "subcategory":"Construction",
            "type":"Services"
        }
    ],
    "sg:phone":"+44 20 8855 7350",
    "sg:postcode":"SE18 1DQ",
    "sg:province":"Greater London",
    "sg:tags":[
        "builder"
    ],
    "wof:name":"Turner Building Services",
    "wof:placetype":"venue"
},
  "geometry": {"coordinates":[0.0924080014,51.4887161255],"type":"Point"}
}