{
  "type": "Feature",
  "properties": {
    "iso:country":"GB",
    "sg:address":"39 High Street",
    "sg:city":"Dunbar",
    "sg:classifiers":[
        {
            "category":"Professional",
            "subcategory":"Lawyer & Legal Services",
            "type":"Services"
        }
    ],
    "sg:phone":"+44 1368 862376",
    "sg:postcode":"EH42 1EW",
    "sg:province":"East Lothian",
    "sg:tags":[
        "solicitor"
    ],
    "wof:name":"Garden Stirling & Burnet",
    "wof:placetype":"venue"
},
  "geometry": {"coordinates":[-2.514574,56.000717],"type":"Point"}
}