{
  "type": "Feature",
  "properties": {
    "addr:full":"8 Tooting Bec Gardens London Greater London SW16 1RB",
    "addr:housenumber":"8",
    "addr:postcode":"sw16 1rb",
    "addr:street":"Tooting Bec Gardens",
    "iso:country":"GB",
    "sg:address":"8 Tooting Bec Gardens",
    "sg:city":"London",
    "sg:classifiers":[
        {
            "category":"Social Services",
            "subcategory":"Adult Care",
            "type":"Services"
        }
    ],
    "sg:postcode":"SW16 1RB",
    "sg:province":"Greater London",
    "sg:tags":[
        "day",
        "centre"
    ],
    "wof:name":"The Spires Centre",
    "wof:placetype":"venue"
},
  "geometry": {"coordinates":[-0.1316509992,51.4292297363],"type":"Point"}
}