{
  "type": "Feature",
  "properties": {
    "iso:country":"GB",
    "sg:address":"Off Wigan Lane",
    "sg:city":"Wigan",
    "sg:classifiers":[
        {
            "category":"Retail",
            "subcategory":"Auto Repair",
            "type":"Services"
        }
    ],
    "sg:phone":"+44 1942 244579",
    "sg:postcode":"WN1 1XR",
    "sg:province":"Lancashire",
    "sg:tags":[
        "modification",
        "garage"
    ],
    "wof:name":"Springfield Street Garage",
    "wof:placetype":"venue"
},
  "geometry": {"coordinates":[-2.633532,53.544155],"type":"Point"}
}