{
  "type": "Feature",
  "properties": {
    "addr:full":"49 Depot Road, Cwmavon Port Talbot Neath Port Talbot SA12 9BA",
    "addr:housenumber":"49",
    "addr:postcode":"sa12 9ba",
    "addr:street":"Depot Road",
    "iso:country":"GB",
    "sg:address":"49 Depot Road, Cwmavon",
    "sg:city":"Port Talbot",
    "sg:classifiers":[
        {
            "category":"Professional",
            "subcategory":"Engineering",
            "type":"Services"
        }
    ],
    "sg:phone":"+44 1639 896141",
    "sg:postcode":"SA12 9BA",
    "sg:province":"Neath Port Talbot",
    "sg:tags":[
        "precision",
        "engineer"
    ],
    "wof:name":"A & I Engineering Ltd.",
    "wof:placetype":"venue"
},
  "geometry": {"coordinates":[-3.7595789433,51.615436554],"type":"Point"}
}