{
  "type": "Feature",
  "properties": {
    "addr:full":"Main Street, Shieldhill Falkirk Falkirk FK1 2DT",
    "addr:postcode":"fk1 2dt",
    "addr:street":"Main Street Shieldhill",
    "iso:country":"GB",
    "sg:address":"Main Street, Shieldhill",
    "sg:city":"Falkirk",
    "sg:classifiers":[
        {
            "category":"Bars & Pubs",
            "type":"Food & Drink"
        }
    ],
    "sg:phone":"+44 1324 639763",
    "sg:postcode":"FK1 2DT",
    "sg:province":"Falkirk",
    "sg:tags":[
        "pubs",
        "inn"
    ],
    "wof:name":"The Norwood",
    "wof:placetype":"venue"
},
  "geometry": {"coordinates":[-3.7448289394,55.9341888428],"type":"Point"}
}