{
  "type": "Feature",
  "properties": {
    "iso:country":"GB",
    "sg:address":"Drayton House, 30 Gordon St",
    "sg:city":"Bloomsbury",
    "sg:classifiers":[
        {
            "category":"Organizations",
            "subcategory":"Non-profit Organization",
            "type":"Services"
        }
    ],
    "sg:phone":"+44 20 7387 2026",
    "sg:postcode":"WC1H 0AN",
    "sg:province":"Greater London",
    "sg:tags":[
        "organisation",
        "voluntary",
        "charity"
    ],
    "wof:name":"Umbrella",
    "wof:placetype":"venue"
},
  "geometry": {"coordinates":[-0.1332260072,51.5261726379],"type":"Point"}
}