{
  "type": "Feature",
  "properties": {
    "addr:full":"Town Street Dewsbury West Yorkshire WF12 8JA",
    "addr:postcode":"wf12 8ja",
    "addr:street":"Town Street",
    "iso:country":"GB",
    "sg:address":"Town Street",
    "sg:city":"Dewsbury",
    "sg:classifiers":[
        {
            "category":"Sports & Exercise",
            "subcategory":"Sports Center",
            "type":"Entertainment"
        }
    ],
    "sg:phone":"+44 1924 455551",
    "sg:postcode":"WF12 8JA",
    "sg:province":"West Yorkshire",
    "sg:tags":[
        "shop",
        "good"
    ],
    "wof:name":"Ravensport",
    "wof:placetype":"venue"
},
  "geometry": {"coordinates":[-1.610634,53.687256],"type":"Point"}
}