{
  "type": "Feature",
  "properties": {
    "iso:country":"GB",
    "sg:address":"Penrhos Avenue, Old Colwyn",
    "sg:city":"Colwyn Bay",
    "sg:classifiers":[
        {
            "category":"Education",
            "subcategory":"Special Training",
            "type":"Public Place"
        },
        {
            "category":"Government",
            "subcategory":"Office",
            "type":"Public Place"
        }
    ],
    "sg:phone":"+44 1492 516838",
    "sg:postcode":"LL29 9HW",
    "sg:province":"Conwy",
    "sg:tags":[
        "school",
        "local"
    ],
    "wof:name":"Ysgol Y Graig Special School",
    "wof:placetype":"venue"
},
  "geometry": {"coordinates":[-3.6824140549,53.2900733948],"type":"Point"}
}