{
  "type": "Feature",
  "properties": {
    "addr:full":"Unit 7 Scotshaw Brook Industrial Estate, Branch Rd Darwen Lancashire BB3 0PR",
    "addr:housenumber":"unit 7",
    "addr:postcode":"bb3 0pr",
    "addr:street":"Scotshaw Brook Industrial Estate Branch Rd",
    "iso:country":"GB",
    "sg:address":"Unit 7 Scotshaw Brook Industrial Estate, Branch Rd",
    "sg:city":"Darwen",
    "sg:classifiers":[
        {
            "category":"Building & Trades",
            "subcategory":"Construction",
            "type":"Services"
        }
    ],
    "sg:phone":"+44 1254 581765",
    "sg:postcode":"BB3 0PR",
    "sg:province":"Lancashire",
    "sg:tags":[
        "window",
        "sale"
    ],
    "wof:name":"Sapphire Windows",
    "wof:placetype":"venue"
},
  "geometry": {"coordinates":[-2.47119,53.722862],"type":"Point"}
}