{
  "type": "Feature",
  "properties": {
    "addr:full":"16 Piccadilly York North Yorkshire YO1 9NU",
    "addr:housenumber":"16",
    "addr:postcode":"yo1 9nu",
    "addr:street":"Piccadilly",
    "iso:country":"GB",
    "sg:address":"16 Piccadilly",
    "sg:city":"York",
    "sg:classifiers":[
        {
            "category":"Travel",
            "subcategory":"Travel Agent",
            "type":"Entertainment"
        }
    ],
    "sg:phone":"+44 1904 620622",
    "sg:postcode":"YO1 9NU",
    "sg:province":"North Yorkshire",
    "wof:name":"Going Places Leisure Travel",
    "wof:placetype":"venue"
},
  "geometry": {"coordinates":[-1.079115,53.957539],"type":"Point"}
}