{
  "type": "Feature",
  "properties": {
    "addr:full":"Warwick Road Coventry Warwickshire CV3 6AQ",
    "addr:postcode":"cv3 6aq",
    "addr:street":"Warwick Road",
    "iso:country":"GB",
    "sg:address":"Warwick Road",
    "sg:city":"Coventry",
    "sg:classifiers":[
        {
            "category":"Education",
            "subcategory":"School",
            "type":"Public Place"
        }
    ],
    "sg:phone":"+44 24 7667 3442",
    "sg:postcode":"CV3 6AQ",
    "sg:province":"Warwickshire",
    "sg:tags":[
        "independent",
        "preparatory"
    ],
    "wof:name":"King Henry Viii School",
    "wof:placetype":"venue"
},
  "geometry": {"coordinates":[-1.5165239573,52.3988189697],"type":"Point"}
}