{
  "type": "Feature",
  "properties": {
    "iso:country":"GB",
    "sg:address":"Gaza Trading Estate, Scabharbour Lane",
    "sg:city":"Tonbridge",
    "sg:classifiers":[
        {
            "category":"Autos & Motor Vehicles",
            "subcategory":"Auto Supplies",
            "type":"Retail Goods"
        }
    ],
    "sg:postcode":"TN11 8PL",
    "sg:province":"Kent",
    "sg:tags":[
        "gearbox"
    ],
    "wof:name":"Kent Automatic Transmissions",
    "wof:placetype":"venue"
},
  "geometry": {"coordinates":[0.19601,51.219761],"type":"Point"}
}