{
  "type": "Feature",
  "properties": {
    "addr:full":"6 West Street, Wilton Salisbury Wiltshire SP2 0DF",
    "addr:housenumber":"6",
    "addr:postcode":"sp2 0df",
    "addr:street":"West Street",
    "iso:country":"GB",
    "sg:address":"6 West Street, Wilton",
    "sg:city":"Salisbury",
    "sg:classifiers":[
        {
            "category":"Shopping",
            "subcategory":"Antiques",
            "type":"Retail Goods"
        }
    ],
    "sg:phone":"+44 1722 742573",
    "sg:postcode":"SP2 0DF",
    "sg:province":"Wiltshire",
    "wof:name":"Carol Musselwhite Antiques",
    "wof:placetype":"venue"
},
  "geometry": {"coordinates":[-1.8640350103,51.080291748],"type":"Point"}
}