{
  "type": "Feature",
  "properties": {
    "iso:country":"GB",
    "sg:address":"30 Clarence Road",
    "sg:city":"Benfleet",
    "sg:classifiers":[
        {
            "category":"Professional",
            "subcategory":"Art Services",
            "type":"Services"
        }
    ],
    "sg:phone":"+44 1268 566255",
    "sg:postcode":"SS7 1DD",
    "sg:province":"Essex",
    "sg:tags":[
        "photographer"
    ],
    "wof:name":"Dream 2 Photographics",
    "wof:placetype":"venue"
},
  "geometry": {"coordinates":[0.564859,51.556625],"type":"Point"}
}