{
  "type": "Feature",
  "properties": {
    "iso:country":"GB",
    "sg:address":"30 Blencathra Street",
    "sg:city":"Keswick",
    "sg:classifiers":[
        {
            "category":"Travel",
            "subcategory":"Hotels & Motels",
            "type":"Entertainment"
        }
    ],
    "sg:phone":"+44 17687 73184",
    "sg:postcode":"CA12 4HP",
    "sg:province":"Cumbria",
    "sg:tags":[
        "house",
        "guest"
    ],
    "wof:name":"Fellview Guest House",
    "wof:placetype":"venue"
},
  "geometry": {"coordinates":[-3.1318531036,54.6006584167],"type":"Point"}
}