{
  "type": "Feature",
  "properties": {
    "iso:country":"GB",
    "sg:address":"15-20 Hooks Hill Road",
    "sg:city":"Sheringham",
    "sg:classifiers":[
        {
            "category":"Organizations",
            "subcategory":"Non-profit Organization",
            "type":"Services"
        }
    ],
    "sg:postcode":"NR26 8NL",
    "sg:province":"Norfolk",
    "sg:tags":[
        "organisation",
        "voluntary",
        "charity"
    ],
    "wof:name":"Break",
    "wof:placetype":"venue"
},
  "geometry": {"coordinates":[1.2035720348,52.9394798279],"type":"Point"}
}