{
  "type": "Feature",
  "properties": {
    "iso:country":"GB",
    "sg:address":"43 Valley Mount",
    "sg:city":"Harrogate",
    "sg:classifiers":[
        {
            "category":"Shopping",
            "subcategory":"Gifts & Souvenirs",
            "type":"Retail Goods"
        },
        {
            "category":"Professional",
            "subcategory":"Printing & Photocopies",
            "type":"Services"
        }
    ],
    "sg:phone":"+44 1423 507319",
    "sg:postcode":"HG2 0JG",
    "sg:province":"North Yorkshire",
    "sg:tags":[
        "trophy",
        "supplier",
        "medal"
    ],
    "wof:name":"Trophies & Engraving",
    "wof:placetype":"venue"
},
  "geometry": {"coordinates":[-1.549463,53.989304],"type":"Point"}
}