{
  "type": "Feature",
  "properties": {
    "iso:country":"GB",
    "sg:address":"301 Eastwood Road North",
    "sg:city":"Leigh On Sea",
    "sg:classifiers":[
        {
            "category":"Real Estate",
            "subcategory":"Real Estate Agent",
            "type":"Services"
        }
    ],
    "sg:phone":"+44 1702 527775",
    "sg:postcode":"SS9 4LT",
    "sg:province":"Essex",
    "wof:name":"Capricorn Property Services",
    "wof:placetype":"venue"
},
  "geometry": {"coordinates":[0.6492099762,51.5592308044],"type":"Point"}
}