{
  "type": "Feature",
  "properties": {
    "iso:country":"GB",
    "sg:address":"Lower Manhay, Wendron",
    "sg:city":"Helston",
    "sg:classifiers":[
        {
            "category":"Farming",
            "subcategory":"Dairy Farm",
            "type":"Manufacturing & Wholesale Goods"
        }
    ],
    "sg:phone":"+44 1326 563530",
    "sg:postcode":"TR13 0NJ",
    "sg:province":"Cornwall",
    "wof:name":"M P & C A Thomas",
    "wof:placetype":"venue"
},
  "geometry": {"coordinates":[-5.2308,50.126564],"type":"Point"}
}