{
  "type": "Feature",
  "properties": {
    "iso:country":"GB",
    "sg:address":"93 Beaconsfield Road, Aston Clinton",
    "sg:city":"Aylesbury",
    "sg:classifiers":[
        {
            "category":"Professional",
            "subcategory":"Advertising",
            "type":"Services"
        },
        {
            "category":"Manufacturing",
            "subcategory":"Signs",
            "type":"Manufacturing & Wholesale Goods"
        }
    ],
    "sg:postcode":"HP22 5JX",
    "sg:province":"Buckinghamshire",
    "sg:tags":[
        "writer",
        "signwriters"
    ],
    "wof:name":"BRIAN ROBINSON",
    "wof:placetype":"venue"
},
  "geometry": {"coordinates":[-0.7191159725,51.7998046875],"type":"Point"}
}