{
  "type": "Feature",
  "properties": {
    "addr:full":"Tagon Quarff Shetland Islands ZE2 9PT",
    "addr:postcode":"ze2 9pt",
    "addr:street":"Shetland",
    "iso:country":"GB",
    "sg:address":"Tagon",
    "sg:city":"Quarff",
    "sg:classifiers":[
        {
            "category":"Bars & Pubs",
            "type":"Food & Drink"
        }
    ],
    "sg:phone":"+44 1806 588214",
    "sg:postcode":"ZE2 9PT",
    "sg:province":"Shetland Islands",
    "sg:tags":[
        "pubs",
        "inn"
    ],
    "wof:name":"Voe Tavern The",
    "wof:placetype":"venue"
},
  "geometry": {"coordinates":[-1.2359160185,60.3495178223],"type":"Point"}
}