{
  "type": "Feature",
  "properties": {
    "iso:country":"GB",
    "sg:address":"45 Daniel Place",
    "sg:city":"Penzance",
    "sg:classifiers":[
        {
            "category":"Retail",
            "subcategory":"Funeral Services",
            "type":"Services"
        }
    ],
    "sg:postcode":"TR18 4DU",
    "sg:province":"Cornwall",
    "wof:name":"William P Jewell",
    "wof:placetype":"venue"
},
  "geometry": {"coordinates":[-5.5365872383,50.1151847839],"type":"Point"}
}