{
  "type": "Feature",
  "properties": {
    "iso:country":"GB",
    "sg:address":"Switch House, Calder Road, Ravensthorpe",
    "sg:city":"Dewsbury",
    "sg:classifiers":[
        {
            "category":"Wholesale",
            "subcategory":"Chemicals & Plastics",
            "type":"Manufacturing & Wholesale Goods"
        }
    ],
    "sg:phone":"+44 1924 459745",
    "sg:postcode":"WF12 9EA",
    "sg:province":"West Yorkshire",
    "sg:tags":[
        "product",
        "allied"
    ],
    "wof:name":"Wilchap 157 Ltd.",
    "wof:placetype":"venue"
},
  "geometry": {"coordinates":[-1.655166,53.674503],"type":"Point"}
}