{
  "type": "Feature",
  "properties": {
    "addr:full":"121 Whiteacre Rd Ashton-under-lyne Greater Manchester OL6 9PJ",
    "addr:housenumber":"121",
    "addr:postcode":"ol6 9pj",
    "addr:street":"Whiteacre Rd",
    "iso:country":"GB",
    "sg:address":"121 Whiteacre Rd",
    "sg:city":"Ashton-under-lyne",
    "sg:classifiers":[
        {
            "category":"Shopping",
            "subcategory":"Books",
            "type":"Retail Goods"
        }
    ],
    "sg:postcode":"OL6 9PJ",
    "sg:province":"Greater Manchester",
    "sg:tags":[
        "bookseller"
    ],
    "wof:name":"Ayoub,Shaheen,",
    "wof:placetype":"venue"
},
  "geometry": {"coordinates":[-2.079149,53.496216],"type":"Point"}
}