{
  "type": "Feature",
  "properties": {
    "addr:full":"6 Pakefield Rd Lowestoft Suffolk NR33 0HS",
    "addr:housenumber":"6",
    "addr:postcode":"nr33 0hs",
    "addr:street":"Pakefield Rd",
    "iso:country":"GB",
    "sg:address":"6 Pakefield Rd",
    "sg:city":"Lowestoft",
    "sg:classifiers":[
        {
            "category":"Travel",
            "subcategory":"Hotels & Motels",
            "type":"Entertainment"
        }
    ],
    "sg:postcode":"NR33 0HS",
    "sg:province":"Suffolk",
    "wof:name":"Rockville House Hotel",
    "wof:placetype":"venue"
},
  "geometry": {"coordinates":[1.738312,52.460491],"type":"Point"}
}