{
  "type": "Feature",
  "properties": {
    "iso:country":"GB",
    "sg:address":"38 Garden Street",
    "sg:city":"Sheffield",
    "sg:classifiers":[
        {
            "category":"Organizations",
            "subcategory":"Non-profit Organization",
            "type":"Services"
        }
    ],
    "sg:phone":"+44 114 279 7971",
    "sg:postcode":"S1 4BJ",
    "sg:province":"South Yorkshire",
    "sg:tags":[
        "organisation",
        "voluntary",
        "charity"
    ],
    "wof:name":"Cot-Age Child Safety & Nursery Equipment",
    "wof:placetype":"venue"
},
  "geometry": {"coordinates":[-1.4757009745,53.3837127686],"type":"Point"}
}