{
  "type": "Feature",
  "properties": {
    "addr:full":"51 French Street Glasgow Glasgow City G40 4EH",
    "addr:housenumber":"51",
    "addr:postcode":"g40 4eh",
    "addr:street":"French Street",
    "iso:country":"GB",
    "sg:address":"51 French Street",
    "sg:city":"Glasgow",
    "sg:classifiers":[
        {
            "category":"Professional",
            "subcategory":"Art Services",
            "type":"Services"
        },
        {
            "category":"Professional",
            "subcategory":"Printing & Photocopies",
            "type":"Services"
        }
    ],
    "sg:phone":"+44 141 554 1410",
    "sg:postcode":"G40 4EH",
    "sg:province":"Glasgow City",
    "sg:tags":[
        "designer",
        "graphic",
        "printer"
    ],
    "wof:name":"Richmond Park",
    "wof:placetype":"venue"
},
  "geometry": {"coordinates":[-4.226622,55.841919],"type":"Point"}
}