{
  "type": "Feature",
  "properties": {
    "addr:full":"Gloucester Rd South Kensington Greater London SW7 4PP",
    "addr:postcode":"sw7 4pp",
    "addr:street":"Gloucester Rd",
    "iso:country":"GB",
    "sg:address":"Gloucester Rd",
    "sg:city":"South Kensington",
    "sg:classifiers":[
        {
            "category":"Building & Trades",
            "subcategory":"Plumbing",
            "type":"Services"
        }
    ],
    "sg:phone":"+44 20 7792 5757",
    "sg:postcode":"SW7 4PP",
    "sg:province":"Greater London",
    "sg:tags":[
        "heating"
    ],
    "wof:name":"Aden Plumbing Services",
    "wof:placetype":"venue"
},
  "geometry": {"coordinates":[-0.183689,51.498875],"type":"Point"}
}