{
  "type": "Feature",
  "properties": {
    "iso:country":"GB",
    "sg:address":"Market Street, Maud",
    "sg:city":"Peterhead",
    "sg:classifiers":[
        {
            "category":"Organizations",
            "subcategory":"Community Association",
            "type":"Services"
        },
        {
            "category":"Organizations",
            "subcategory":"Membership Organization",
            "type":"Services"
        }
    ],
    "sg:phone":"+44 1771 613259",
    "sg:postcode":"AB42 4NH",
    "sg:province":"Aberdeenshire",
    "sg:tags":[
        "club",
        "social"
    ],
    "wof:name":"Maud Football Social Club",
    "wof:placetype":"venue"
},
  "geometry": {"coordinates":[-2.128424,57.521633],"type":"Point"}
}