{
  "type": "Feature",
  "properties": {
    "addr:full":"35 Main St Turriff Aberdeenshire AB53 7AB",
    "addr:housenumber":"35",
    "addr:postcode":"ab53 7ab",
    "addr:street":"Main St",
    "iso:country":"GB",
    "sg:address":"35 Main St",
    "sg:city":"Turriff",
    "sg:classifiers":[
        {
            "category":"Fast Food",
            "type":"Food & Drink"
        }
    ],
    "sg:phone":"+44 1888 568520",
    "sg:postcode":"AB53 7AB",
    "sg:province":"Aberdeenshire",
    "sg:tags":[
        "away",
        "take"
    ],
    "wof:name":"Mr Chips",
    "wof:placetype":"venue"
},
  "geometry": {"coordinates":[-2.4552199841,57.5400085449],"type":"Point"}
}