{
  "type": "Feature",
  "properties": {
    "iso:country":"GB",
    "sg:address":"104 St Marys Road, Garston",
    "sg:city":"Liverpool",
    "sg:classifiers":[
        {
            "category":"Building & Trades",
            "subcategory":"Plumbing",
            "type":"Services"
        },
        {
            "category":"Home & Garden",
            "subcategory":"Hardware",
            "type":"Retail Goods"
        }
    ],
    "sg:phone":"+44 151 281 0590",
    "sg:postcode":"L19 2JG",
    "sg:province":"Merseyside",
    "sg:tags":[
        "merchant",
        "plumber",
        "plumbers'"
    ],
    "wof:name":"Garston Plumbing Supplies",
    "wof:placetype":"venue"
},
  "geometry": {"coordinates":[-2.901429,53.355167],"type":"Point"}
}