{
  "type": "Feature",
  "properties": {
    "addr:full":"7 Brook Lane, Warsash Southampton Hampshire SO31 9FH",
    "addr:housenumber":"7",
    "addr:postcode":"so31 9fh",
    "addr:street":"Brook Lane",
    "iso:country":"GB",
    "sg:address":"7 Brook Lane, Warsash",
    "sg:city":"Southampton",
    "sg:classifiers":[
        {
            "category":"Home & Garden",
            "subcategory":"Home Furnishings",
            "type":"Retail Goods"
        }
    ],
    "sg:phone":"+44 1489 885833",
    "sg:postcode":"SO31 9FH",
    "sg:province":"Hampshire",
    "sg:tags":[
        "blind",
        "curtain",
        "fitting"
    ],
    "wof:name":"Shepherd Interiors",
    "wof:placetype":"venue"
},
  "geometry": {"coordinates":[-1.300287,50.853645],"type":"Point"}
}