{
  "type": "Feature",
  "properties": {
    "addr:full":"Lower Broadway Didcot Oxfordshire OX11 8AG",
    "addr:postcode":"ox11 8ag",
    "addr:street":"Lower Broadway",
    "iso:country":"GB",
    "sg:address":"Lower Broadway",
    "sg:city":"Didcot",
    "sg:classifiers":[
        {
            "category":"Retail",
            "subcategory":"Auto Rental",
            "type":"Services"
        }
    ],
    "sg:phone":"+44 1235 819700",
    "sg:postcode":"OX11 8AG",
    "sg:province":"Oxfordshire",
    "sg:tags":[
        "car"
    ],
    "wof:name":"Hotsons Eurodrive",
    "wof:placetype":"venue"
},
  "geometry": {"coordinates":[-1.2321150303,51.6023826599],"type":"Point"}
}