{
  "type": "Feature",
  "properties": {
    "addr:full":"15 Alma Road Sidcup Kent DA14 4HN",
    "addr:housenumber":"15",
    "addr:postcode":"da14 4hn",
    "addr:street":"Alma Road",
    "iso:country":"GB",
    "sg:address":"15 Alma Road",
    "sg:city":"Sidcup",
    "sg:classifiers":[
        {
            "category":"Retail",
            "subcategory":"Auto Repair",
            "type":"Services"
        }
    ],
    "sg:postcode":"DA14 4HN",
    "sg:province":"Kent",
    "sg:tags":[
        "body",
        "car"
    ],
    "wof:name":"Kent Auto Centre",
    "wof:placetype":"venue"
},
  "geometry": {"coordinates":[0.103848,51.432064],"type":"Point"}
}