{
  "type": "Feature",
  "properties": {
    "iso:country":"GB",
    "sg:address":"25 Brandon Terrace",
    "sg:city":"Edinburgh",
    "sg:classifiers":[
        {
            "category":"Professional",
            "subcategory":"Testing Lab",
            "type":"Services"
        }
    ],
    "sg:postcode":"EH3 5DZ",
    "sg:province":"City of Edinburgh",
    "sg:tags":[
        "mot"
    ],
    "wof:name":"West Pier Motor Cycles",
    "wof:placetype":"venue"
},
  "geometry": {"coordinates":[-3.200564,55.961998],"type":"Point"}
}