{
  "type": "Feature",
  "properties": {
    "iso:country":"GB",
    "sg:address":"7 Grosvenor Road, Bircotes",
    "sg:city":"Doncaster",
    "sg:classifiers":[
        {
            "category":"Fast Food",
            "type":"Food & Drink"
        }
    ],
    "sg:phone":"+44 1302 744661",
    "sg:postcode":"DN11 8EY",
    "sg:province":"South Yorkshire",
    "sg:tags":[
        "away",
        "take"
    ],
    "wof:name":"Sizzlers Indian Take Away",
    "wof:placetype":"venue"
},
  "geometry": {"coordinates":[-1.0598499775,53.4172019958],"type":"Point"}
}