{
  "type": "Feature",
  "properties": {
    "addr:full":"6-8 Commercial Street, Aberbargoed Bargoed Caerphilly CF81 9BW",
    "addr:housenumber":"6-8",
    "addr:postcode":"cf81 9bw",
    "addr:street":"Commercial Street",
    "iso:country":"GB",
    "sg:address":"6-8 Commercial Street, Aberbargoed",
    "sg:city":"Bargoed",
    "sg:classifiers":[
        {
            "category":"Food & Beverages",
            "subcategory":"Supermarket",
            "type":"Retail Goods"
        }
    ],
    "sg:postcode":"CF81 9BW",
    "sg:province":"Caerphilly",
    "wof:name":"The Spar Shop",
    "wof:placetype":"venue"
},
  "geometry": {"coordinates":[-3.22525,51.694637],"type":"Point"}
}