{
  "type": "Feature",
  "properties": {
    "addr:full":"28 Clifford Road, Petersham Richmond Greater London TW10 7EA",
    "addr:housenumber":"28",
    "addr:postcode":"tw10 7ea",
    "addr:street":"Clifford Road",
    "iso:country":"GB",
    "sg:address":"28 Clifford Road, Petersham",
    "sg:city":"Richmond",
    "sg:classifiers":[
        {
            "category":"Building & Trades",
            "subcategory":"Cleaning & Sanitation",
            "type":"Services"
        }
    ],
    "sg:phone":"+44 20 8332 6373",
    "sg:postcode":"TW10 7EA",
    "sg:province":"Greater London",
    "sg:tags":[
        "commercial",
        "sweep",
        "chimney"
    ],
    "wof:name":"Vine Chimney Sweep",
    "wof:placetype":"venue"
},
  "geometry": {"coordinates":[-0.3047139943,51.4420051575],"type":"Point"}
}