{
  "type": "Feature",
  "properties": {
    "addr:full":"Vickers Place, Stanningley Pudsey West Yorkshire LS28 6LZ",
    "addr:postcode":"ls28 6lz",
    "addr:street":"Vickers Place;West",
    "iso:country":"GB",
    "sg:address":"Vickers Place, Stanningley",
    "sg:city":"Pudsey",
    "sg:classifiers":[
        {
            "category":"Organizations",
            "subcategory":"Labor Organization",
            "type":"Services"
        }
    ],
    "sg:phone":"+44 113 257 4736",
    "sg:postcode":"LS28 6LZ",
    "sg:province":"West Yorkshire",
    "sg:tags":[
        "woodworking",
        "machinery"
    ],
    "wof:name":"D B Keighley (Machinery) Ltd.",
    "wof:placetype":"venue"
},
  "geometry": {"coordinates":[-1.659892,53.807858],"type":"Point"}
}