{
  "type": "Feature",
  "properties": {
    "iso:country":"GB",
    "sg:address":"66 Hacton Drive",
    "sg:city":"Hornchurch",
    "sg:classifiers":[
        {
            "category":"Personal",
            "type":"Services"
        }
    ],
    "sg:phone":"+44 1708 455995",
    "sg:postcode":"RM12 6DP",
    "sg:province":"Essex",
    "sg:tags":[
        "kiss-o-grams"
    ],
    "wof:name":"First Call Entertainment",
    "wof:placetype":"venue"
},
  "geometry": {"coordinates":[0.221513,51.548481],"type":"Point"}
}