{
  "type": "Feature",
  "properties": {
    "addr:full":"Acre Road Leeds West Yorkshire LS10 4LF",
    "addr:postcode":"ls10 4lf",
    "addr:street":"Acre Road",
    "iso:country":"GB",
    "sg:address":"Acre Road",
    "sg:city":"Leeds",
    "sg:classifiers":[
        {
            "category":"Arena",
            "subcategory":"Sports Club",
            "type":"Entertainment"
        }
    ],
    "sg:phone":"+44 113 270 9916",
    "sg:postcode":"LS10 4LF",
    "sg:province":"West Yorkshire",
    "wof:name":"Middleton Marauders",
    "wof:placetype":"venue"
},
  "geometry": {"coordinates":[-1.538409,53.745998],"type":"Point"}
}