{
  "type": "Feature",
  "properties": {
    "iso:country":"GB",
    "sg:address":"114 Station Road, Ainsdale",
    "sg:city":"Southport",
    "sg:classifiers":[
        {
            "category":"Transit Center",
            "subcategory":"Freight",
            "type":"Transportation"
        }
    ],
    "sg:postcode":"PR8 3HL",
    "sg:province":"Lancashire",
    "sg:tags":[
        "shop",
        "craft",
        "centre"
    ],
    "wof:name":"Janet Foster",
    "wof:placetype":"venue"
},
  "geometry": {"coordinates":[-3.041445,53.602161],"type":"Point"}
}