{
  "type": "Feature",
  "properties": {
    "addr:full":"114 Station Road, Ainsdale Southport Lancashire PR8 3HL",
    "addr:housenumber":"114",
    "addr:postcode":"pr8 3hl",
    "addr:street":"Station Road",
    "iso:country":"GB",
    "sg:address":"114 Station Road, Ainsdale",
    "sg:city":"Southport",
    "sg:classifiers":[
        {
            "category":"Transit Center",
            "subcategory":"Freight",
            "type":"Transportation"
        }
    ],
    "sg:postcode":"PR8 3HL",
    "sg:province":"Lancashire",
    "sg:tags":[
        "shop",
        "craft",
        "centre"
    ],
    "wof:name":"Janet Foster",
    "wof:placetype":"venue"
},
  "geometry": {"coordinates":[-3.041445,53.602161],"type":"Point"}
}