{
  "type": "Feature",
  "properties": {
    "addr:full":"53 Gordon Square London Greater London WC1H 0PD",
    "addr:housenumber":"53",
    "addr:postcode":"wc1h 0pd",
    "addr:street":"Gordon Square",
    "iso:country":"GB",
    "sg:address":"53 Gordon Square",
    "sg:city":"London",
    "sg:classifiers":[
        {
            "category":"Museum",
            "subcategory":"Art Museum",
            "type":"Entertainment"
        }
    ],
    "sg:phone":"+44 20 7387 3909",
    "sg:postcode":"WC1H 0PD",
    "sg:province":"Greater London",
    "sg:tags":[
        "gallery"
    ],
    "wof:name":"Percival David Foundation of Chinese Art",
    "wof:placetype":"venue"
},
  "geometry": {"coordinates":[-0.129859,51.524242],"type":"Point"}
}