{
  "type": "Feature",
  "properties": {
    "iso:country":"GB",
    "sg:address":"24 Gillygate",
    "sg:city":"York",
    "sg:classifiers":[
        {
            "category":"Transit Center",
            "subcategory":"Freight",
            "type":"Transportation"
        },
        {
            "category":"Shopping",
            "subcategory":"Computers & Home Electronics",
            "type":"Retail Goods"
        }
    ],
    "sg:phone":"+44 1904 642463",
    "sg:postcode":"YO31 7EQ",
    "sg:province":"North Yorkshire",
    "sg:tags":[
        "hi-fi",
        "fi",
        "hi",
        "centre"
    ],
    "wof:name":"Vickers Hi Fi",
    "wof:placetype":"venue"
},
  "geometry": {"coordinates":[-1.0848579407,53.9632301331],"type":"Point"}
}