{
  "type": "Feature",
  "properties": {
    "iso:country":"GB",
    "sg:address":"Corwen Rd",
    "sg:city":"Ruthin",
    "sg:classifiers":[
        {
            "category":"Retail",
            "subcategory":"Event Space",
            "type":"Services"
        }
    ],
    "sg:phone":"+44 1824 703435",
    "sg:postcode":"LL15 2NU",
    "sg:province":"Denbighshire",
    "sg:tags":[
        "banqueting",
        "room"
    ],
    "wof:name":"Mediaeval Banquets Ruthin Castle Ltd",
    "wof:placetype":"venue"
},
  "geometry": {"coordinates":[-3.308846,53.109592],"type":"Point"}
}