{
  "type": "Feature",
  "properties": {
    "addr:full":"18 Rose Grn Road Bognor Regis West Sussex PO21 3ET",
    "addr:housenumber":"18",
    "addr:postcode":"po21 3et",
    "addr:street":"Rose Grn Road",
    "iso:country":"GB",
    "sg:address":"18 Rose Grn Road",
    "sg:city":"Bognor Regis",
    "sg:classifiers":[
        {
            "category":"Food & Beverages",
            "subcategory":"Liquor & Beverages",
            "type":"Retail Goods"
        }
    ],
    "sg:phone":"+44 1243 267044",
    "sg:postcode":"PO21 3ET",
    "sg:province":"West Sussex",
    "sg:tags":[
        "beer",
        "spirit",
        "wines"
    ],
    "wof:name":"Victoria Wine",
    "wof:placetype":"venue"
},
  "geometry": {"coordinates":[-0.7154459953,50.7863845825],"type":"Point"}
}