{
  "type": "Feature",
  "properties": {
    "iso:country":"GB",
    "sg:address":"1 Kew Road",
    "sg:city":"Southport",
    "sg:classifiers":[
        {
            "category":"Shopping",
            "subcategory":"Department Store",
            "type":"Retail Goods"
        }
    ],
    "sg:phone":"+44 1704 568384",
    "sg:postcode":"PR8 4HH",
    "sg:province":"Lancashire",
    "wof:name":"V Haynes",
    "wof:placetype":"venue"
},
  "geometry": {"coordinates":[-3.008275,53.630772],"type":"Point"}
}