{
  "type": "Feature",
  "properties": {
    "addr:full":"Stall 70 Blackburn Three Day Market, Ainsworth Street Blackburn Lancashire BB1 6AS",
    "addr:housenumber":"70",
    "addr:postcode":"bb1 6as",
    "addr:street":"Stall;Ainsworth Street",
    "iso:country":"GB",
    "sg:address":"Stall 70 Blackburn Three Day Market, Ainsworth Street",
    "sg:city":"Blackburn",
    "sg:classifiers":[
        {
            "category":"Food & Beverages",
            "subcategory":"Meat & Fish",
            "type":"Retail Goods"
        }
    ],
    "sg:phone":"+44 1254 262657",
    "sg:postcode":"BB1 6AS",
    "sg:province":"Lancashire",
    "sg:tags":[
        "butcher"
    ],
    "wof:name":"D Pinder Family Butcher",
    "wof:placetype":"venue"
},
  "geometry": {"coordinates":[-2.480399,53.748516],"type":"Point"}
}