{
  "type": "Feature",
  "properties": {
    "addr:full":"14 Wood Lane, Paradise Industrial Estate Hemel Hempstead Hertfordshire HP2 4TL",
    "addr:housenumber":"14",
    "addr:postcode":"hp2 4tl",
    "addr:street":"Wood Lane;Industrial;Hemel",
    "iso:country":"GB",
    "sg:address":"14 Wood Lane, Paradise Industrial Estate",
    "sg:city":"Hemel Hempstead",
    "sg:classifiers":[
        {
            "category":"Building & Trades",
            "subcategory":"Construction",
            "type":"Services"
        }
    ],
    "sg:postcode":"HP2 4TL",
    "sg:province":"Hertfordshire",
    "sg:tags":[
        "platform",
        "work",
        "scaffolding"
    ],
    "wof:name":"Independent Hire & Sales",
    "wof:placetype":"venue"
},
  "geometry": {"coordinates":[-0.467708,51.748253],"type":"Point"}
}