{
  "type": "Feature",
  "properties": {
    "iso:country":"GB",
    "sg:address":"Brantwood, Kirkhill",
    "sg:city":"Inverness",
    "sg:classifiers":[
        {
            "category":"Government",
            "subcategory":"Post Office",
            "type":"Public Place"
        }
    ],
    "sg:phone":"+44 1463 831779",
    "sg:postcode":"IV5 7NZ",
    "sg:province":"Highland",
    "wof:name":"Kirkhill Post Office",
    "wof:placetype":"venue"
},
  "geometry": {"coordinates":[-4.410119,57.476204],"type":"Point"}
}