{
  "type": "Feature",
  "properties": {
    "addr:full":"41 Pemberton Rd Llanelli Carmarthenshire SA14 9BG",
    "addr:housenumber":"41",
    "addr:postcode":"sa14 9bg",
    "addr:street":"Pemberton Rd",
    "iso:country":"GB",
    "sg:address":"41 Pemberton Rd",
    "sg:city":"Llanelli",
    "sg:classifiers":[
        {
            "category":"Shopping",
            "subcategory":"Antiques",
            "type":"Retail Goods"
        }
    ],
    "sg:phone":"+44 1554 755790",
    "sg:postcode":"SA14 9BG",
    "sg:province":"Carmarthenshire",
    "wof:name":"Radnadge Architectural Salvage",
    "wof:placetype":"venue"
},
  "geometry": {"coordinates":[-4.1278839111,51.6827774048],"type":"Point"}
}