{
  "type": "Feature",
  "properties": {
    "addr:full":"Unit 8, Sawpit Lane, Tibshelf Alfreton Derbyshire DE55 5NH",
    "addr:housenumber":"unit 8",
    "addr:postcode":"de55 5nh",
    "addr:street":"Sawpit Lane Tibshelf",
    "iso:country":"GB",
    "sg:address":"Unit 8, Sawpit Lane, Tibshelf",
    "sg:city":"Alfreton",
    "sg:classifiers":[
        {
            "category":"Building & Trades",
            "subcategory":"Equipment Rental",
            "type":"Services"
        }
    ],
    "sg:phone":"+44 1773 590012",
    "sg:postcode":"DE55 5NH",
    "sg:province":"Derbyshire",
    "sg:tags":[
        "plant",
        "machinery"
    ],
    "wof:name":"J S Pneumatics & Engineering Services",
    "wof:placetype":"venue"
},
  "geometry": {"coordinates":[-1.3310689926,53.1393623352],"type":"Point"}
}