{
  "type": "Feature",
  "properties": {
    "iso:country":"GB",
    "sg:address":"8 Lansdowne Terrace",
    "sg:city":"Newcastle-upon-tyne",
    "sg:classifiers":[
        {
            "category":"Health Services",
            "subcategory":"Clinic",
            "type":"Services"
        }
    ],
    "sg:phone":"+44 191 213 1388",
    "sg:postcode":"NE3 1HP",
    "sg:province":"Tyne and Wear",
    "sg:tags":[
        "aromatherapy"
    ],
    "wof:name":"Aromatherapy in Practice",
    "wof:placetype":"venue"
},
  "geometry": {"coordinates":[-1.6204990149,55.0101242065],"type":"Point"}
}