{
  "type": "Feature",
  "properties": {
    "addr:full":"Stadium Lincoln Lincolnshire LN5 8LD",
    "addr:postcode":"ln5 8ld",
    "iso:country":"GB",
    "sg:address":"Stadium",
    "sg:city":"Lincoln",
    "sg:classifiers":[
        {
            "category":"Arena",
            "subcategory":"Sports Club",
            "type":"Entertainment"
        }
    ],
    "sg:phone":"+44 1522 880011",
    "sg:postcode":"LN5 8LD",
    "sg:province":"Lincolnshire",
    "wof:name":"Lincoln City Football Club Co. Ltd.",
    "wof:placetype":"venue"
},
  "geometry": {"coordinates":[-0.5420380235,53.2260856628],"type":"Point"}
}