{
  "type": "Feature",
  "properties": {
    "iso:country":"GB",
    "sg:address":"Westpark 65-67 Albert Road",
    "sg:city":"Southport",
    "sg:classifiers":[
        {
            "category":"Health Services",
            "subcategory":"Nursing And Care Facility",
            "type":"Services"
        },
        {
            "category":"Social Services",
            "subcategory":"Adult Care",
            "type":"Services"
        },
        {
            "category":"Organizations",
            "subcategory":"Community Association",
            "type":"Services"
        }
    ],
    "sg:phone":"+44 1704 548426",
    "sg:postcode":"PR9 9LW",
    "sg:province":"Lancashire",
    "sg:tags":[
        "centre",
        "housing",
        "co-operatives",
        "society",
        "home",
        "trust",
        "day"
    ],
    "sg:website":"http://www.echg.org.uk",
    "wof:name":"English Churches Housing Group",
    "wof:placetype":"venue"
},
  "geometry": {"coordinates":[-2.98991,53.657581],"type":"Point"}
}