{
  "type": "Feature",
  "properties": {
    "addr:full":"Unit 5 27 Truro Road St Austell Cornwall PL25 5JE",
    "addr:housenumber":"unit;27",
    "addr:postcode":"pl25 5je",
    "addr:street":"Truro Road",
    "iso:country":"GB",
    "sg:address":"Unit 5 27 Truro Road",
    "sg:city":"St Austell",
    "sg:classifiers":[
        {
            "category":"Fast Food",
            "type":"Food & Drink"
        }
    ],
    "sg:phone":"+44 1726 69888",
    "sg:postcode":"PL25 5JE",
    "sg:province":"Cornwall",
    "sg:tags":[
        "away",
        "take"
    ],
    "wof:name":"Lee Gardens",
    "wof:placetype":"venue"
},
  "geometry": {"coordinates":[-4.7967581749,50.3384132385],"type":"Point"}
}