{
  "type": "Feature",
  "properties": {
    "addr:full":"6 Brandon Road London Greater London N7 9AA",
    "addr:housenumber":"6",
    "addr:postcode":"n7 9aa",
    "addr:street":"Brandon Road",
    "iso:country":"GB",
    "sg:address":"6 Brandon Road",
    "sg:city":"London",
    "sg:classifiers":[
        {
            "category":"Shopping",
            "subcategory":"Clothing, Apparel, & Fashions",
            "type":"Retail Goods"
        }
    ],
    "sg:phone":"+44 20 7609 3986",
    "sg:postcode":"N7 9AA",
    "sg:province":"Greater London",
    "sg:tags":[
        "t-shirt"
    ],
    "wof:name":"Morija Plc",
    "wof:placetype":"venue"
},
  "geometry": {"coordinates":[-0.1245429963,51.5434684753],"type":"Point"}
}