{
  "type": "Feature",
  "properties": {
    "addr:full":"Western Farm, Oakford Tiverton Devon EX16 9JE",
    "addr:postcode":"ex16 9je",
    "iso:country":"GB",
    "sg:address":"Western Farm, Oakford",
    "sg:city":"Tiverton",
    "sg:classifiers":[
        {
            "category":"Farming",
            "subcategory":"Dairy Farm",
            "type":"Manufacturing & Wholesale Goods"
        },
        {
            "category":"Farming",
            "subcategory":"Farm",
            "type":"Manufacturing & Wholesale Goods"
        }
    ],
    "sg:phone":"+44 1398 341667",
    "sg:postcode":"EX16 9JE",
    "sg:province":"Devon",
    "sg:tags":[
        "mixed"
    ],
    "wof:name":"T I & S Vigus",
    "wof:placetype":"venue"
},
  "geometry": {"coordinates":[-3.553774,50.981602],"type":"Point"}
}