{
  "type": "Feature",
  "properties": {
    "addr:full":"Wadham Park Farm, Church Rd Hockley Essex SS5 6AF",
    "addr:postcode":"ss5 6af",
    "addr:street":"Wadham;Church Rd",
    "iso:country":"GB",
    "sg:address":"Wadham Park Farm, Church Rd",
    "sg:city":"Hockley",
    "sg:classifiers":[
        {
            "category":"Farming",
            "subcategory":"Livestock Farm",
            "type":"Manufacturing & Wholesale Goods"
        }
    ],
    "sg:phone":"+44 1702 230269",
    "sg:postcode":"SS5 6AF",
    "sg:province":"Essex",
    "sg:tags":[
        "others"
    ],
    "wof:name":"W A Bird",
    "wof:placetype":"venue"
},
  "geometry": {"coordinates":[0.631435,51.615704],"type":"Point"}
}