{
  "type": "Feature",
  "properties": {
    "addr:full":"94 Wellington Street Luton Bedfordshire LU1 5AA",
    "addr:housenumber":"94",
    "addr:postcode":"lu1 5aa",
    "addr:street":"Wellington Street",
    "iso:country":"GB",
    "sg:address":"94 Wellington Street",
    "sg:city":"Luton",
    "sg:classifiers":[
        {
            "category":"Shopping",
            "subcategory":"News",
            "type":"Retail Goods"
        }
    ],
    "sg:postcode":"LU1 5AA",
    "sg:province":"Bedfordshire",
    "sg:tags":[
        "newsagent"
    ],
    "wof:name":"Steed,Martin,",
    "wof:placetype":"venue"
},
  "geometry": {"coordinates":[-0.4198949933,51.8776283264],"type":"Point"}
}