{
  "type": "Feature",
  "properties": {
    "addr:full":"Shaftesbury Ho, 5 Waterloo St Glasgow Glasgow City G2 6AY",
    "addr:housenumber":"5",
    "addr:postcode":"g2 6ay",
    "addr:street":"Waterloo St",
    "iso:country":"GB",
    "sg:address":"Shaftesbury Ho, 5 Waterloo St",
    "sg:city":"Glasgow",
    "sg:classifiers":[
        {
            "category":"Organizations",
            "subcategory":"Non-profit Organization",
            "type":"Services"
        }
    ],
    "sg:phone":"+44 141 221 1175",
    "sg:postcode":"G2 6AY",
    "sg:province":"Glasgow City",
    "sg:tags":[
        "organisation",
        "voluntary",
        "charity"
    ],
    "wof:name":"Scottish Drugs Forum",
    "wof:placetype":"venue"
},
  "geometry": {"coordinates":[-4.25945,55.86021],"type":"Point"}
}