{
  "type": "Feature",
  "properties": {
    "addr:full":"Unit 4, Moss Road Colchester Essex CO3 0LE",
    "addr:housenumber":"unit 4",
    "addr:postcode":"co3 0le",
    "addr:street":"Moss Road Colchester",
    "iso:country":"GB",
    "sg:address":"Unit 4, Moss Road",
    "sg:city":"Colchester",
    "sg:classifiers":[
        {
            "category":"Building & Trades",
            "subcategory":"Construction",
            "type":"Services"
        }
    ],
    "sg:phone":"+44 1206 212333",
    "sg:postcode":"CO3 0LE",
    "sg:province":"Essex",
    "sg:tags":[
        "glazier"
    ],
    "wof:name":"South East Glass Ltd.",
    "wof:placetype":"venue"
},
  "geometry": {"coordinates":[0.84928,51.876865],"type":"Point"}
}