{
  "type": "Feature",
  "properties": {
    "addr:full":"1 Church Crescent Ebbw Vale Blaenau Gwent NP23 5PE",
    "addr:housenumber":"1",
    "addr:postcode":"np23 5pe",
    "addr:street":"Church Crescent",
    "iso:country":"GB",
    "sg:address":"1 Church Crescent",
    "sg:city":"Ebbw Vale",
    "sg:classifiers":[
        {
            "category":"Shopping",
            "subcategory":"Department Store",
            "type":"Retail Goods"
        }
    ],
    "sg:phone":"+44 1495 303951",
    "sg:postcode":"NP23 5PE",
    "sg:province":"Blaenau Gwent",
    "wof:name":"The Corner Shop Garden Centre",
    "wof:placetype":"venue"
},
  "geometry": {"coordinates":[-3.2149848938,51.7970123291],"type":"Point"}
}