{
  "type": "Feature",
  "properties": {
    "addr:full":"47a Balham Rd Lower Edmonton Greater London N9 7AG",
    "addr:housenumber":"47a",
    "addr:postcode":"n9 7ag",
    "addr:street":"Balham Rd",
    "iso:country":"GB",
    "sg:address":"47a Balham Rd",
    "sg:city":"Lower Edmonton",
    "sg:classifiers":[
        {
            "category":"Education",
            "subcategory":"School",
            "type":"Public Place"
        }
    ],
    "sg:phone":"+44 20 8675 7747",
    "sg:postcode":"N9 7AG",
    "sg:province":"Greater London",
    "sg:tags":[
        "independent",
        "preparatory"
    ],
    "wof:name":"Balham & Tooting Prep School",
    "wof:placetype":"venue"
},
  "geometry": {"coordinates":[-0.0602939986,51.6277236938],"type":"Point"}
}