{
  "type": "Feature",
  "properties": {
    "addr:full":"Winchbottom Farm, Winchbottom Lane High Wycombe Buckinghamshire HP10 9QF",
    "addr:postcode":"hp10 9qf",
    "addr:street":"Winchbottom Lane",
    "iso:country":"GB",
    "sg:address":"Winchbottom Farm, Winchbottom Lane",
    "sg:city":"High Wycombe",
    "sg:classifiers":[
        {
            "category":"Farming",
            "subcategory":"Livestock Farm",
            "type":"Manufacturing & Wholesale Goods"
        },
        {
            "category":"Building & Trades",
            "subcategory":"Construction",
            "type":"Services"
        }
    ],
    "sg:postcode":"HP10 9QF",
    "sg:province":"Buckinghamshire",
    "sg:tags":[
        "builder",
        "others"
    ],
    "wof:name":"John Charles Hills",
    "wof:placetype":"venue"
},
  "geometry": {"coordinates":[-0.743912,51.608021],"type":"Point"}
}