{
  "type": "Feature",
  "properties": {
    "iso:country":"GB",
    "sg:address":"42 Downend Park Road, Downend",
    "sg:city":"Bristol",
    "sg:classifiers":[
        {
            "category":"Real Estate",
            "subcategory":"Real Estate Agent",
            "type":"Services"
        }
    ],
    "sg:postcode":"BS16 5SZ",
    "sg:province":"City of Bristol",
    "wof:name":"Dampkill Property Maintenance Ltd",
    "wof:placetype":"venue"
},
  "geometry": {"coordinates":[-2.508421,51.484642],"type":"Point"}
}