{
  "type": "Feature",
  "properties": {
    "iso:country":"GB",
    "sg:address":"15 Lealand Way",
    "sg:city":"Boston",
    "sg:classifiers":[
        {
            "category":"Recreation",
            "subcategory":"Amusement Park",
            "type":"Entertainment"
        }
    ],
    "sg:phone":"+44 1205 363633",
    "sg:postcode":"PE21 7SW",
    "sg:province":"Lincolnshire",
    "sg:tags":[
        "arcade"
    ],
    "wof:name":"Bell-Fruit Services Ltd.",
    "wof:placetype":"venue"
},
  "geometry": {"coordinates":[-0.012281,52.965656],"type":"Point"}
}