{
  "type": "Feature",
  "properties": {
    "addr:full":"2 London Road Southampton Hampshire SO15 2AF",
    "addr:housenumber":"2",
    "addr:postcode":"so15 2af",
    "addr:street":"London Road",
    "iso:country":"GB",
    "sg:address":"2 London Road",
    "sg:city":"Southampton",
    "sg:classifiers":[
        {
            "category":"Wholesale",
            "subcategory":"Medical Equipment & Supplies",
            "type":"Manufacturing & Wholesale Goods"
        }
    ],
    "sg:phone":"+44 23 8022 0300",
    "sg:postcode":"SO15 2AF",
    "sg:province":"Hampshire",
    "sg:tags":[
        "supplier",
        "aid",
        "hearing"
    ],
    "wof:name":"Sietech Hearing Ltd.",
    "wof:placetype":"venue"
},
  "geometry": {"coordinates":[-1.4047329426,50.9105529785],"type":"Point"}
}