{
  "type": "Feature",
  "properties": {
    "iso:country":"GB",
    "sg:address":"30 Oak Road",
    "sg:city":"Bromsgrove",
    "sg:classifiers":[
        {
            "category":"Building & Trades",
            "subcategory":"Construction",
            "type":"Services"
        }
    ],
    "sg:phone":"+44 1527 873581",
    "sg:postcode":"B61 0LT",
    "sg:province":"Worcestershire",
    "sg:tags":[
        "builder"
    ],
    "wof:name":"W G Waters",
    "wof:placetype":"venue"
},
  "geometry": {"coordinates":[-2.049842,52.363758],"type":"Point"}
}