{
  "type": "Feature",
  "properties": {
    "addr:full":"52 Warwick Road Carlisle Cumbria CA1 1DR",
    "addr:housenumber":"52",
    "addr:postcode":"ca1 1dr",
    "addr:street":"Warwick Road",
    "iso:country":"GB",
    "sg:address":"52 Warwick Road",
    "sg:city":"Carlisle",
    "sg:classifiers":[
        {
            "category":"Food & Beverages",
            "subcategory":"Bakery",
            "type":"Retail Goods"
        }
    ],
    "sg:phone":"+44 1228 527268",
    "sg:postcode":"CA1 1DR",
    "sg:province":"Cumbria",
    "sg:tags":[
        "shop",
        "baker"
    ],
    "wof:name":"Bells of Lazonby Ltd.",
    "wof:placetype":"venue"
},
  "geometry": {"coordinates":[-2.930654,54.893002],"type":"Point"}
}