{
  "type": "Feature",
  "properties": {
    "iso:country":"GB",
    "sg:address":"Camelot, Heather Way, Felbridge",
    "sg:city":"East Grinstead",
    "sg:classifiers":[
        {
            "category":"Building & Trades",
            "subcategory":"Construction",
            "type":"Services"
        }
    ],
    "sg:phone":"+44 1342 325333",
    "sg:postcode":"RH19 2RF",
    "sg:province":"East Sussex",
    "sg:tags":[
        "builder"
    ],
    "wof:name":"V J Friend",
    "wof:placetype":"venue"
},
  "geometry": {"coordinates":[-0.045123,51.140224],"type":"Point"}
}