{
  "type": "Feature",
  "properties": {
    "addr:full":"230 Market Street Hyde Cheshire SK14 1HB",
    "addr:housenumber":"230",
    "addr:postcode":"sk14 1hb",
    "addr:street":"Market Street",
    "iso:country":"GB",
    "sg:address":"230 Market Street",
    "sg:city":"Hyde",
    "sg:classifiers":[
        {
            "category":"Retail",
            "subcategory":"Funeral Services",
            "type":"Services"
        }
    ],
    "sg:postcode":"SK14 1HB",
    "sg:province":"Cheshire",
    "wof:name":"Robinsons & Jordans Fuenral Service",
    "wof:placetype":"venue"
},
  "geometry": {"coordinates":[-2.0753068924,53.4471626282],"type":"Point"}
}