{
  "type": "Feature",
  "properties": {
    "addr:full":"Eastgate Louth Lincolnshire LN11 9QE",
    "addr:postcode":"ln11 9qe",
    "addr:street":"Eastgate Louth",
    "iso:country":"GB",
    "sg:address":"Eastgate",
    "sg:city":"Louth",
    "sg:classifiers":[
        {
            "category":"Health Services",
            "subcategory":"Dentist",
            "type":"Services"
        }
    ],
    "sg:phone":"+44 1507 600099",
    "sg:postcode":"LN11 9QE",
    "sg:province":"Lincolnshire",
    "wof:name":"Frances A Miller",
    "wof:placetype":"venue"
},
  "geometry": {"coordinates":[0.00437,53.368351],"type":"Point"}
}