{
  "type": "Feature",
  "properties": {
    "iso:country":"GB",
    "sg:address":"9-15 The Street",
    "sg:city":"Fakenham",
    "sg:classifiers":[
        {
            "category":"Autos & Motor Vehicles",
            "subcategory":"Auto Supplies",
            "type":"Retail Goods"
        }
    ],
    "sg:phone":"+44 1328 863920",
    "sg:postcode":"NR21 9QD",
    "sg:province":"Norfolk",
    "sg:tags":[
        "part",
        "motorcycle",
        "accessory"
    ],
    "wof:name":"K & M Motor Cycles",
    "wof:placetype":"venue"
},
  "geometry": {"coordinates":[0.8161180019,52.8415184021],"type":"Point"}
}