{
  "type": "Feature",
  "properties": {
    "addr:full":"1 Sundridge Hill, Cuxton Rochester Kent ME2 1LH",
    "addr:housenumber":"1",
    "addr:postcode":"me2 1lh",
    "addr:street":"Sundridge Hill",
    "iso:country":"GB",
    "sg:address":"1 Sundridge Hill, Cuxton",
    "sg:city":"Rochester",
    "sg:classifiers":[
        {
            "category":"Retail",
            "subcategory":"Auto Repair",
            "type":"Services"
        }
    ],
    "sg:phone":"+44 1634 717987",
    "sg:postcode":"ME2 1LH",
    "sg:province":"Kent",
    "sg:tags":[
        "modification",
        "garage",
        "related"
    ],
    "wof:name":"Cuxton Auto Services",
    "wof:placetype":"venue"
},
  "geometry": {"coordinates":[0.457728,51.374168],"type":"Point"}
}