{
  "type": "Feature",
  "properties": {
    "addr:full":"Crouch End Hill Hornsey Greater London N8 8DH",
    "addr:postcode":"n8 8dh",
    "addr:street":"End Hill",
    "iso:country":"GB",
    "sg:address":"Crouch End Hill",
    "sg:city":"Hornsey",
    "sg:classifiers":[
        {
            "category":"Manufacturing",
            "subcategory":"Metals",
            "type":"Manufacturing & Wholesale Goods"
        }
    ],
    "sg:phone":"+44 20 8347 7003",
    "sg:postcode":"N8 8DH",
    "sg:province":"Greater London",
    "sg:tags":[
        "steel",
        "stockholder"
    ],
    "wof:name":"Central Steels",
    "wof:placetype":"venue"
},
  "geometry": {"coordinates":[-0.120637998,51.5818328857],"type":"Point"}
}