{
  "type": "Feature",
  "properties": {
    "addr:full":"31 Dalston La Hackney Greater London E8 3DF",
    "addr:housenumber":"31",
    "addr:postcode":"e8 3df",
    "addr:street":"Dalston La Hackney",
    "iso:country":"GB",
    "sg:address":"31 Dalston La",
    "sg:city":"Hackney",
    "sg:classifiers":[
        {
            "category":"Professional",
            "subcategory":"Lawyer & Legal Services",
            "type":"Services"
        }
    ],
    "sg:phone":"+44 20 7241 2299",
    "sg:postcode":"E8 3DF",
    "sg:province":"Greater London",
    "sg:tags":[
        "advice",
        "counselling"
    ],
    "wof:name":"Coldline",
    "wof:placetype":"venue"
},
  "geometry": {"coordinates":[-0.0723040029,51.5463829041],"type":"Point"}
}