{
  "type": "Feature",
  "properties": {
    "iso:country":"GB",
    "sg:address":"155 King St",
    "sg:city":"Dundee",
    "sg:classifiers":[
        {
            "category":"Bars & Pubs",
            "type":"Food & Drink"
        }
    ],
    "sg:phone":"+44 1382 779819",
    "sg:postcode":"DD5 2AX",
    "sg:province":"Angus",
    "sg:tags":[
        "pubs",
        "inn"
    ],
    "wof:name":"Eagle Inn The",
    "wof:placetype":"venue"
},
  "geometry": {"coordinates":[-2.876431,56.466221],"type":"Point"}
}