{
  "type": "Feature",
  "properties": {
    "addr:full":"415-417 Victoria Road, Crosshill Glasgow Glasgow City G42 8RW",
    "addr:housenumber":"415-417",
    "addr:postcode":"g42 8rw",
    "addr:street":"Victoria Road",
    "iso:country":"GB",
    "sg:address":"415-417 Victoria Road, Crosshill",
    "sg:city":"Glasgow",
    "sg:classifiers":[
        {
            "category":"Shopping",
            "subcategory":"Pharmacy",
            "type":"Retail Goods"
        }
    ],
    "sg:phone":"+44 141 423 1065",
    "sg:postcode":"G42 8RW",
    "sg:province":"Glasgow City",
    "sg:tags":[
        "pharmacist",
        "chemist"
    ],
    "wof:name":"Boots the Chemists",
    "wof:placetype":"venue"
},
  "geometry": {"coordinates":[-4.264729,55.8363],"type":"Point"}
}