{
  "type": "Feature",
  "properties": {
    "iso:country":"GB",
    "sg:address":"54a High Street, Hucknall",
    "sg:city":"Nottingham",
    "sg:classifiers":[
        {
            "category":"Shopping",
            "subcategory":"Shoes",
            "type":"Retail Goods"
        }
    ],
    "sg:postcode":"NG15 7AX",
    "sg:province":"Nottinghamshire",
    "wof:name":"Cobblers Locks & Keys",
    "wof:placetype":"venue"
},
  "geometry": {"coordinates":[-1.2029559612,53.0382423401],"type":"Point"}
}