{
  "type": "Feature",
  "properties": {
    "addr:full":"Manor Cottage, Main Street, Owston Oakham Leicestershire LE15 8DH",
    "addr:postcode":"le15 8dh",
    "addr:street":"Main Street",
    "iso:country":"GB",
    "sg:address":"Manor Cottage, Main Street, Owston",
    "sg:city":"Oakham",
    "sg:classifiers":[
        {
            "category":"Home & Garden",
            "subcategory":"Hardware",
            "type":"Retail Goods"
        }
    ],
    "sg:postcode":"LE15 8DH",
    "sg:province":"Leicestershire",
    "sg:tags":[
        "compressor",
        "air"
    ],
    "wof:name":"J & J Services",
    "wof:placetype":"venue"
},
  "geometry": {"coordinates":[-0.84999,52.66193],"type":"Point"}
}