{
  "type": "Feature",
  "properties": {
    "addr:full":"Lawman Gardens, Bonsall Lane Alfreton Derbyshire DE55 7PS",
    "addr:postcode":"de55 7ps",
    "addr:street":"Lawman Gardens Bonsall Lane",
    "iso:country":"GB",
    "sg:address":"Lawman Gardens, Bonsall Lane",
    "sg:city":"Alfreton",
    "sg:classifiers":[
        {
            "category":"Social Services",
            "subcategory":"Retirement Home",
            "type":"Services"
        },
        {
            "category":"Organizations",
            "subcategory":"Community Association",
            "type":"Services"
        }
    ],
    "sg:phone":"+44 1773 520167",
    "sg:postcode":"DE55 7PS",
    "sg:province":"Derbyshire",
    "sg:tags":[
        "society",
        "housing",
        "sheltered",
        "accommodation"
    ],
    "sg:website":"http://www.anchor.org.uk",
    "wof:name":"Anchor Trust",
    "wof:placetype":"venue"
},
  "geometry": {"coordinates":[-1.3850489855,53.097618103],"type":"Point"}
}