{
  "type": "Feature",
  "properties": {
    "addr:full":"Westerdale Road, Scawsby Doncaster South Yorkshire DN5 8RD",
    "addr:postcode":"dn5 8rd",
    "addr:street":"Westerdale Road",
    "iso:country":"GB",
    "sg:address":"Westerdale Road, Scawsby",
    "sg:city":"Doncaster",
    "sg:classifiers":[
        {
            "category":"Bars & Pubs",
            "type":"Food & Drink"
        }
    ],
    "sg:postcode":"DN5 8RD",
    "sg:province":"South Yorkshire",
    "sg:tags":[
        "pubs",
        "inn"
    ],
    "wof:name":"The Roman Ridge Hotel",
    "wof:placetype":"venue"
},
  "geometry": {"coordinates":[-1.1779379845,53.5392379761],"type":"Point"}
}