{
  "type": "Feature",
  "properties": {
    "iso:country":"GB",
    "sg:address":"P O Box 200",
    "sg:city":"Southampton",
    "sg:classifiers":[
        {
            "category":"Building & Trades",
            "subcategory":"Construction",
            "type":"Services"
        }
    ],
    "sg:phone":"+44 1489 787028",
    "sg:postcode":"SO30 4ZJ",
    "sg:province":"Hampshire",
    "sg:tags":[
        "roofing"
    ],
    "wof:name":"Roof-lok",
    "wof:placetype":"venue"
},
  "geometry": {"coordinates":[-1.3041390181,50.9147415161],"type":"Point"}
}