{
  "type": "Feature",
  "properties": {
    "addr:full":"240 Hawthorne Road Liverpool Merseyside L20 3AS",
    "addr:housenumber":"240",
    "addr:postcode":"l20 3as",
    "addr:street":"Hawthorne Road",
    "iso:country":"GB",
    "sg:address":"240 Hawthorne Road",
    "sg:city":"Liverpool",
    "sg:classifiers":[
        {
            "category":"Building & Trades",
            "subcategory":"Construction",
            "type":"Services"
        }
    ],
    "sg:phone":"+44 151 236 2490",
    "sg:postcode":"L20 3AS",
    "sg:province":"Merseyside",
    "sg:tags":[
        "platform",
        "work",
        "scaffolding"
    ],
    "wof:name":"M T D Scaffolding Ltd.",
    "wof:placetype":"venue"
},
  "geometry": {"coordinates":[-2.9972560406,53.4696121216],"type":"Point"}
}