{
  "type": "Feature",
  "properties": {
    "iso:country":"GB",
    "sg:address":"129a St Helens Street",
    "sg:city":"Ipswich",
    "sg:classifiers":[
        {
            "category":"Personal",
            "subcategory":"Beauty Salon",
            "type":"Services"
        }
    ],
    "sg:phone":"+44 1473 258176",
    "sg:postcode":"IP4 2LS",
    "sg:province":"Suffolk",
    "sg:tags":[
        "unisex",
        "hairdresser"
    ],
    "wof:name":"Roma Hairstylists",
    "wof:placetype":"venue"
},
  "geometry": {"coordinates":[1.165751,52.056713],"type":"Point"}
}