{
  "type": "Feature",
  "properties": {
    "addr:full":"201 High Street London Greater London SE20 7PF",
    "addr:housenumber":"201",
    "addr:postcode":"se20 7pf",
    "addr:street":"High Street",
    "iso:country":"GB",
    "sg:address":"201 High Street",
    "sg:city":"London",
    "sg:classifiers":[
        {
            "category":"Professional",
            "subcategory":"Accounting & Tax Preparation",
            "type":"Services"
        }
    ],
    "sg:phone":"+44 20 8659 1155",
    "sg:postcode":"SE20 7PF",
    "sg:province":"Greater London",
    "sg:tags":[
        "accountant"
    ],
    "wof:name":"Thauoos & Co",
    "wof:placetype":"venue"
},
  "geometry": {"coordinates":[-0.050996,51.413155],"type":"Point"}
}