{
  "type": "Feature",
  "properties": {
    "iso:country":"GB",
    "sg:address":"1 Dene Cottage, Wignall Street, Lawford",
    "sg:city":"Manningtree",
    "sg:classifiers":[
        {
            "category":"Building & Trades",
            "subcategory":"Construction",
            "type":"Services"
        }
    ],
    "sg:postcode":"CO11 2JL",
    "sg:province":"Essex",
    "sg:tags":[
        "glazier",
        "decorator",
        "painter"
    ],
    "wof:name":"P C Chittock",
    "wof:placetype":"venue"
},
  "geometry": {"coordinates":[1.042236,51.938225],"type":"Point"}
}