{
  "type": "Feature",
  "properties": {
    "iso:country":"GB",
    "sg:address":"598 Coventry Rd, Small Heath",
    "sg:city":"Birmingham",
    "sg:classifiers":[
        {
            "category":"Wholesale",
            "subcategory":"Scrap",
            "type":"Manufacturing & Wholesale Goods"
        }
    ],
    "sg:postcode":"B10 0US",
    "sg:province":"West Midlands",
    "sg:tags":[
        "breaker",
        "dismantlers"
    ],
    "wof:name":"Hussain,Amjud,",
    "wof:placetype":"venue"
},
  "geometry": {"coordinates":[-1.853292942,52.467880249],"type":"Point"}
}