{
  "type": "Feature",
  "properties": {
    "iso:country":"GB",
    "sg:address":"The City Business Centre, 2 London Wall Buildings",
    "sg:city":"London",
    "sg:classifiers":[
        {
            "category":"Professional",
            "subcategory":"Employment Agencies",
            "type":"Services"
        }
    ],
    "sg:phone":"+44 20 7448 5104",
    "sg:postcode":"EC2M 5UU",
    "sg:province":"Greater London",
    "sg:tags":[
        "consultant"
    ],
    "wof:name":"Barbara Houghton Temporaries Ltd.",
    "wof:placetype":"venue"
},
  "geometry": {"coordinates":[-0.08578,51.517101],"type":"Point"}
}