{
  "type": "Feature",
  "properties": {
    "addr:full":"56 Lake Street Ferndale Rhondda, Cynon, Taff CF43 4HL",
    "addr:housenumber":"56",
    "addr:postcode":"cf43 4hl",
    "addr:street":"Lake Street",
    "iso:country":"GB",
    "sg:address":"56 Lake Street",
    "sg:city":"Ferndale",
    "sg:classifiers":[
        {
            "category":"Organizations",
            "subcategory":"Community Association",
            "type":"Services"
        },
        {
            "category":"Organizations",
            "subcategory":"Membership Organization",
            "type":"Services"
        }
    ],
    "sg:phone":"+44 1443 730596",
    "sg:postcode":"CF43 4HL",
    "sg:province":"Rhondda, Cynon, Taff",
    "sg:tags":[
        "club",
        "social"
    ],
    "wof:name":"Ferndale Workmen's Conservative Club",
    "wof:placetype":"venue"
},
  "geometry": {"coordinates":[-3.44851,51.66114],"type":"Point"}
}