{
  "type": "Feature",
  "properties": {
    "iso:country":"GB",
    "sg:address":"Fore Street",
    "sg:city":"Sidmouth",
    "sg:classifiers":[
        {
            "category":"Manufacturing",
            "subcategory":"Textiles",
            "type":"Manufacturing & Wholesale Goods"
        }
    ],
    "sg:phone":"+44 1395 577789",
    "sg:postcode":"EX10 8AH",
    "sg:province":"Devon",
    "sg:tags":[
        "merchant",
        "knitwear",
        "agent"
    ],
    "wof:name":"Woollies",
    "wof:placetype":"venue"
},
  "geometry": {"coordinates":[-3.237419,50.67971],"type":"Point"}
}