{
  "type": "Feature",
  "properties": {
    "addr:full":"157 Mansfield Rd, Clipstone Mansfield Nottinghamshire NG21 9AA",
    "addr:housenumber":"157",
    "addr:postcode":"ng21 9aa",
    "addr:street":"Mansfield Rd",
    "iso:country":"GB",
    "sg:address":"157 Mansfield Rd, Clipstone",
    "sg:city":"Mansfield",
    "sg:classifiers":[
        {
            "category":"Personal",
            "subcategory":"Beauty Salon",
            "type":"Services"
        }
    ],
    "sg:postcode":"NG21 9AA",
    "sg:province":"Nottinghamshire",
    "sg:tags":[
        "unisex",
        "hairdresser"
    ],
    "wof:name":"Mellors,Mary,",
    "wof:placetype":"venue"
},
  "geometry": {"coordinates":[-1.1255379915,53.1598625183],"type":"Point"}
}