{
  "type": "Feature",
  "properties": {
    "iso:country":"GB",
    "sg:address":"207 Green Lane Road",
    "sg:city":"Leicester",
    "sg:classifiers":[
        {
            "category":"Government",
            "subcategory":"Post Office",
            "type":"Public Place"
        }
    ],
    "sg:phone":"+44 116 276 7300",
    "sg:postcode":"LE5 4PD",
    "sg:province":"Leicestershire",
    "wof:name":"Green Lane Post Office",
    "wof:placetype":"venue"
},
  "geometry": {"coordinates":[-1.096954,52.63652],"type":"Point"}
}