{
  "type": "Feature",
  "properties": {
    "addr:full":"Braefoot Kilmarnock East Ayrshire KA1 3AQ",
    "addr:postcode":"ka1 3aq",
    "addr:street":"East",
    "iso:country":"GB",
    "sg:address":"Braefoot",
    "sg:city":"Kilmarnock",
    "sg:classifiers":[
        {
            "category":"Professional",
            "type":"Services"
        }
    ],
    "sg:phone":"+44 1563 571747",
    "sg:postcode":"KA1 3AQ",
    "sg:province":"East Ayrshire",
    "sg:tags":[
        "caterer"
    ],
    "wof:name":"Burlington Outside Catering & Bars",
    "wof:placetype":"venue"
},
  "geometry": {"coordinates":[-4.5097298622,55.6088943481],"type":"Point"}
}