{
  "type": "Feature",
  "properties": {
    "addr:full":"399 Green Street London Greater London E13 9AU",
    "addr:housenumber":"399",
    "addr:postcode":"e13 9au",
    "addr:street":"Green Street",
    "iso:country":"GB",
    "sg:address":"399 Green Street",
    "sg:city":"London",
    "sg:classifiers":[
        {
            "category":"Personal",
            "subcategory":"Beauty Salon",
            "type":"Services"
        }
    ],
    "sg:phone":"+44 20 8472 3887",
    "sg:postcode":"E13 9AU",
    "sg:province":"Greater London",
    "sg:tags":[
        "unisex",
        "hairdresser"
    ],
    "wof:name":"Doulla Hair Fashions",
    "wof:placetype":"venue"
},
  "geometry": {"coordinates":[0.035985,51.534508],"type":"Point"}
}