{
  "type": "Feature",
  "properties": {
    "addr:full":"41 High Street Swanley Kent BR8 8BQ",
    "addr:housenumber":"41",
    "addr:postcode":"br8 8bq",
    "addr:street":"High Street",
    "iso:country":"GB",
    "sg:address":"41 High Street",
    "sg:city":"Swanley",
    "sg:classifiers":[
        {
            "category":"Real Estate",
            "subcategory":"Real Estate Agent",
            "type":"Services"
        }
    ],
    "sg:phone":"+44 1322 613949",
    "sg:postcode":"BR8 8BQ",
    "sg:province":"Kent",
    "wof:name":"Brookbanks",
    "wof:placetype":"venue"
},
  "geometry": {"coordinates":[0.1795009971,51.3944091797],"type":"Point"}
}