{
  "type": "Feature",
  "properties": {
    "iso:country":"GB",
    "sg:address":"79 Raleigh Rd",
    "sg:city":"Feltham",
    "sg:classifiers":[
        {
            "category":"Social Services",
            "type":"Services"
        }
    ],
    "sg:phone":"+44 20 8844 0546",
    "sg:postcode":"TW13 4LW",
    "sg:province":"Greater London",
    "sg:tags":[
        "disability"
    ],
    "wof:name":"Avondale Services",
    "wof:placetype":"venue"
},
  "geometry": {"coordinates":[-0.423054,51.443493],"type":"Point"}
}