{
  "type": "Feature",
  "properties": {
    "addr:full":"8 The Street, Limes Business Centre, Charlwood Horley Surrey RH6 0BY",
    "addr:housenumber":"8;business;charlwood",
    "addr:postcode":"rh6 0by",
    "addr:street":"The Street Limes",
    "iso:country":"GB",
    "sg:address":"8 The Street, Limes Business Centre, Charlwood",
    "sg:city":"Horley",
    "sg:classifiers":[
        {
            "category":"Professional",
            "subcategory":"Art Services",
            "type":"Services"
        }
    ],
    "sg:postcode":"RH6 0BY",
    "sg:province":"Surrey",
    "sg:tags":[
        "graphic",
        "designer"
    ],
    "wof:name":"Seal Design Print",
    "wof:placetype":"venue"
},
  "geometry": {"coordinates":[-0.2195329964,51.1545715332],"type":"Point"}
}