{
  "type": "Feature",
  "properties": {
    "addr:full":"Lower Yearsett, Linley Grn, Whitbourne Worcester Herefordshire WR6 5RQ",
    "addr:postcode":"wr6 5rq",
    "addr:street":"Linley Grn",
    "iso:country":"GB",
    "sg:address":"Lower Yearsett, Linley Grn, Whitbourne",
    "sg:city":"Worcester",
    "sg:classifiers":[
        {
            "category":"Farming",
            "subcategory":"Dairy Farm",
            "type":"Manufacturing & Wholesale Goods"
        }
    ],
    "sg:phone":"+44 1886 884275",
    "sg:postcode":"WR6 5RQ",
    "sg:province":"Herefordshire",
    "wof:name":"Bellingham & Son W R",
    "wof:placetype":"venue"
},
  "geometry": {"coordinates":[-2.4111390114,52.2081718445],"type":"Point"}
}