{
  "type": "Feature",
  "properties": {
    "addr:full":"Heron Flight Avenue Hornchurch Essex RM12 5LN",
    "addr:postcode":"rm12 5ln",
    "addr:street":"Flight Avenue",
    "iso:country":"GB",
    "sg:address":"Heron Flight Avenue",
    "sg:city":"Hornchurch",
    "sg:classifiers":[
        {
            "category":"Education",
            "subcategory":"School",
            "type":"Public Place"
        }
    ],
    "sg:phone":"+44 1708 555644",
    "sg:postcode":"RM12 5LN",
    "sg:province":"Essex",
    "sg:tags":[
        "local",
        "authority"
    ],
    "wof:name":"St Alban's Catholic Primary School",
    "wof:placetype":"venue"
},
  "geometry": {"coordinates":[0.1994200051,51.5392341614],"type":"Point"}
}