{
  "type": "Feature",
  "properties": {
    "iso:country":"GB",
    "sg:address":"Unit 19 The Boathouse",
    "sg:city":"Staines",
    "sg:classifiers":[
        {
            "category":"Home & Garden",
            "subcategory":"Home Furnishings",
            "type":"Retail Goods"
        }
    ],
    "sg:phone":"+44 1784 464643",
    "sg:postcode":"TW18 3JY",
    "sg:province":"Berkshire",
    "sg:tags":[
        "racking",
        "shelving",
        "diy"
    ],
    "wof:name":"Steel Shelving Systems",
    "wof:placetype":"venue"
},
  "geometry": {"coordinates":[-0.523614,51.433769],"type":"Point"}
}