{
  "type": "Feature",
  "properties": {
    "addr:full":"17 Hellesdon Road Norwich Norfolk NR6 5EB",
    "addr:housenumber":"17",
    "addr:postcode":"nr6 5eb",
    "addr:street":"Hellesdon Road Norwich Norfolk",
    "iso:country":"GB",
    "sg:address":"17 Hellesdon Road",
    "sg:city":"Norwich",
    "sg:classifiers":[
        {
            "category":"Health Services",
            "subcategory":"Health Practitioner",
            "type":"Services"
        }
    ],
    "sg:postcode":"NR6 5EB",
    "sg:province":"Norfolk",
    "sg:tags":[
        "hypnotherapists"
    ],
    "wof:name":"Maggie Perry",
    "wof:placetype":"venue"
},
  "geometry": {"coordinates":[1.2524729967,52.6385536194],"type":"Point"}
}