{
  "type": "Feature",
  "properties": {
    "addr:full":"7 Bradkirk Lane, Bamber Bridge Preston Lancashire PR5 6ZQ",
    "addr:housenumber":"7",
    "addr:postcode":"pr5 6zq",
    "addr:street":"Bradkirk Lane",
    "iso:country":"GB",
    "sg:address":"7 Bradkirk Lane, Bamber Bridge",
    "sg:city":"Preston",
    "sg:classifiers":[
        {
            "category":"Retail",
            "subcategory":"Repair Shop",
            "type":"Services"
        }
    ],
    "sg:phone":"+44 1772 314582",
    "sg:postcode":"PR5 6ZQ",
    "sg:province":"Lancashire",
    "sg:tags":[
        "radio",
        "television",
        "video"
    ],
    "wof:name":"Bob Wilson T V Repairs",
    "wof:placetype":"venue"
},
  "geometry": {"coordinates":[-2.6444189548,53.7270393372],"type":"Point"}
}