{
  "type": "Feature",
  "properties": {
    "addr:full":"Freeway House, 12 Waterway Garth Goole East Riding of Yorkshire DN14 0HQ",
    "addr:housenumber":"12",
    "addr:postcode":"dn14 0hq",
    "addr:street":"Waterway Garth",
    "iso:country":"GB",
    "sg:address":"Freeway House, 12 Waterway Garth",
    "sg:city":"Goole",
    "sg:classifiers":[
        {
            "category":"Banks & Credit Unions",
            "subcategory":"Bank",
            "type":"Services"
        }
    ],
    "sg:phone":"+44 1405 861354",
    "sg:postcode":"DN14 0HQ",
    "sg:province":"East Riding of Yorkshire",
    "sg:tags":[
        "stocktaking",
        "inventory"
    ],
    "wof:name":"Innstock Management Services",
    "wof:placetype":"venue"
},
  "geometry": {"coordinates":[-1.072839,53.668415],"type":"Point"}
}