{
  "type": "Feature",
  "properties": {
    "addr:full":"1-2 Warstone Mews Birmingham West Midlands B18 6JB",
    "addr:housenumber":"1-2",
    "addr:postcode":"b18 6jb",
    "addr:street":"Warstone Mews",
    "iso:country":"GB",
    "sg:address":"1-2 Warstone Mews",
    "sg:city":"Birmingham",
    "sg:classifiers":[
        {
            "category":"Manufacturing",
            "subcategory":"Tools & Machinery",
            "type":"Manufacturing & Wholesale Goods"
        },
        {
            "category":"Home & Garden",
            "subcategory":"Building Materials",
            "type":"Retail Goods"
        }
    ],
    "sg:phone":"+44 121 236 9346",
    "sg:postcode":"B18 6JB",
    "sg:province":"West Midlands",
    "sg:tags":[
        "supplier"
    ],
    "wof:name":"H S WALSH PROPERTIES LTD",
    "wof:placetype":"venue"
},
  "geometry": {"coordinates":[-1.909749,52.487427],"type":"Point"}
}