{
  "type": "Feature",
  "properties": {
    "addr:full":"33-34 Hall Gate Doncaster South Yorkshire DN1 3NL",
    "addr:housenumber":"33-34",
    "addr:postcode":"dn1 3nl",
    "addr:street":"Hall Gate",
    "iso:country":"GB",
    "sg:address":"33-34 Hall Gate",
    "sg:city":"Doncaster",
    "sg:classifiers":[
        {
            "category":"Bars & Pubs",
            "type":"Food & Drink"
        }
    ],
    "sg:phone":"+44 1302 323186",
    "sg:postcode":"DN1 3NL",
    "sg:province":"South Yorkshire",
    "sg:tags":[
        "pubs",
        "inn"
    ],
    "wof:name":"Dr Browns",
    "wof:placetype":"venue"
},
  "geometry": {"coordinates":[-1.1283659935,53.5221862793],"type":"Point"}
}