{
  "type": "Feature",
  "properties": {
    "iso:country":"GB",
    "sg:address":"33-34 Hall Gate",
    "sg:city":"Doncaster",
    "sg:classifiers":[
        {
            "category":"Bars & Pubs",
            "type":"Food & Drink"
        }
    ],
    "sg:phone":"+44 1302 323186",
    "sg:postcode":"DN1 3NL",
    "sg:province":"South Yorkshire",
    "sg:tags":[
        "pubs",
        "inn"
    ],
    "wof:name":"Dr Browns",
    "wof:placetype":"venue"
},
  "geometry": {"coordinates":[-1.1283659935,53.5221862793],"type":"Point"}
}