{
  "type": "Feature",
  "properties": {
    "iso:country":"GB",
    "sg:address":"The Old Village Hall, Bradenham",
    "sg:city":"High Wycombe",
    "sg:classifiers":[
        {
            "category":"Travel",
            "subcategory":"Hotels & Motels",
            "type":"Entertainment"
        },
        {
            "category":"Travel",
            "subcategory":"Hostel",
            "type":"Entertainment"
        }
    ],
    "sg:phone":"+44 1494 562929",
    "sg:postcode":"HP14 4HF",
    "sg:province":"Buckinghamshire",
    "sg:tags":[
        "youth"
    ],
    "wof:name":"Bradenham Youth Hostel",
    "wof:placetype":"venue"
},
  "geometry": {"coordinates":[-0.7965670228,51.6689147949],"type":"Point"}
}