{
  "type": "Feature",
  "properties": {
    "iso:country":"GB",
    "sg:address":"Cromwell House",
    "sg:city":"Hook",
    "sg:classifiers":[
        {
            "category":"Professional",
            "subcategory":"Computer Services",
            "type":"Services"
        }
    ],
    "sg:phone":"+44 1256 386900",
    "sg:postcode":"RG27 9XA",
    "sg:province":"Berkshire",
    "sg:tags":[
        "consultant",
        "system",
        "software"
    ],
    "wof:name":"I B S Consulting Services",
    "wof:placetype":"venue"
},
  "geometry": {"coordinates":[-0.965719,51.281361],"type":"Point"}
}