{
  "type": "Feature",
  "properties": {
    "addr:full":"25 Breck Road Poulton-le-fylde Lancashire FY6 7AA",
    "addr:housenumber":"25",
    "addr:postcode":"fy6 7aa",
    "addr:street":"Breck Road Poulton-Le-Fylde",
    "iso:country":"GB",
    "sg:address":"25 Breck Road",
    "sg:city":"Poulton-le-fylde",
    "sg:classifiers":[
        {
            "category":"Shopping",
            "subcategory":"Bicycles & Sporting Goods",
            "type":"Retail Goods"
        },
        {
            "category":"Wholesale",
            "subcategory":"Sporting Goods",
            "type":"Manufacturing & Wholesale Goods"
        }
    ],
    "sg:phone":"+44 1253 892445",
    "sg:postcode":"FY6 7AA",
    "sg:province":"Lancashire",
    "sg:tags":[
        "supplier",
        "equipment",
        "camping"
    ],
    "wof:name":"Out 'N' About",
    "wof:placetype":"venue"
},
  "geometry": {"coordinates":[-2.991462,53.848293],"type":"Point"}
}