{
  "type": "Feature",
  "properties": {
    "iso:country":"GB",
    "sg:address":"Marlowe Avenue",
    "sg:city":"Swindon",
    "sg:classifiers":[
        {
            "category":"Organizations",
            "subcategory":"Religious Organization",
            "type":"Services"
        }
    ],
    "sg:phone":"+44 1793 535708",
    "sg:postcode":"SN3 2PT",
    "sg:province":"Wiltshire",
    "sg:tags":[
        "organisation",
        "place",
        "worship"
    ],
    "wof:name":"Presentation Convent",
    "wof:placetype":"venue"
},
  "geometry": {"coordinates":[-1.748709,51.562679],"type":"Point"}
}