{
  "type": "Feature",
  "properties": {
    "addr:full":"35 Church La Cambridge Cambridgeshire CB1 6BQ",
    "addr:housenumber":"35",
    "addr:postcode":"cb1 6bq",
    "addr:street":"Church La",
    "iso:country":"GB",
    "sg:address":"35 Church La",
    "sg:city":"Cambridge",
    "sg:classifiers":[
        {
            "category":"Place Of Worship",
            "type":"Public Place"
        }
    ],
    "sg:phone":"+44 1223 891350",
    "sg:postcode":"CB1 6BQ",
    "sg:province":"Cambridgeshire",
    "wof:name":"Little Abington Parish Church",
    "wof:placetype":"venue"
},
  "geometry": {"coordinates":[0.2339739949,52.1203575134],"type":"Point"}
}