{
  "type": "Feature",
  "properties": {
    "addr:full":"39 Morgans Road Neath Neath Port Talbot SA11 2DG",
    "addr:housenumber":"39",
    "addr:postcode":"sa11 2dg",
    "addr:street":"Morgans Road",
    "iso:country":"GB",
    "sg:address":"39 Morgans Road",
    "sg:city":"Neath",
    "sg:classifiers":[
        {
            "category":"Bus Charters",
            "type":"Transportation"
        },
        {
            "category":"Bus Stop",
            "subcategory":"None",
            "type":"Transportation"
        }
    ],
    "sg:phone":"+44 1639 643084",
    "sg:postcode":"SA11 2DG",
    "sg:province":"Neath Port Talbot",
    "sg:tags":[
        "mini",
        "hire",
        "leasing",
        "min"
    ],
    "wof:name":"Briton Ferry Mini Bus Hire",
    "wof:placetype":"venue"
},
  "geometry": {"coordinates":[-3.8151240349,51.6500320435],"type":"Point"}
}