{
  "type": "Feature",
  "properties": {
    "iso:country":"GB",
    "sg:address":"Spreighton Road",
    "sg:city":"West Molesey",
    "sg:classifiers":[
        {
            "category":"Social Services",
            "subcategory":"Adult Care",
            "type":"Services"
        },
        {
            "category":"Organizations",
            "subcategory":"Community Association",
            "type":"Services"
        },
        {
            "category":"Government",
            "subcategory":"Office",
            "type":"Public Place"
        }
    ],
    "sg:phone":"+44 20 8941 3171",
    "sg:postcode":"KT8 2JF",
    "sg:province":"Greater London",
    "sg:tags":[
        "housing",
        "co-operatives",
        "society",
        "sheltered",
        "trust",
        "local"
    ],
    "wof:name":"The Limes",
    "wof:placetype":"venue"
},
  "geometry": {"coordinates":[-0.364906,51.401802],"type":"Point"}
}