{
  "type": "Feature",
  "properties": {
    "addr:full":"7 Althorp Road London Greater London SW17 7ED",
    "addr:housenumber":"7",
    "addr:postcode":"sw17 7ed",
    "addr:street":"Althorp Road",
    "iso:country":"GB",
    "sg:address":"7 Althorp Road",
    "sg:city":"London",
    "sg:classifiers":[
        {
            "category":"Shopping",
            "subcategory":"Computers & Home Electronics",
            "type":"Retail Goods"
        }
    ],
    "sg:phone":"+44 20 8672 6654",
    "sg:postcode":"SW17 7ED",
    "sg:province":"Greater London",
    "sg:tags":[
        "equipment",
        "audio-visual"
    ],
    "wof:name":"Nicholson Systems Ltd.",
    "wof:placetype":"venue"
},
  "geometry": {"coordinates":[-0.1663260013,51.4447860718],"type":"Point"}
}