{
  "type": "Feature",
  "properties": {
    "addr:full":"Greenwood Farm, The Village, Burton Neston Cheshire CH64 5TQ",
    "addr:postcode":"ch64 5tq",
    "addr:street":"The Village",
    "iso:country":"GB",
    "sg:address":"Greenwood Farm, The Village, Burton",
    "sg:city":"Neston",
    "sg:classifiers":[
        {
            "category":"Farming",
            "subcategory":"Livestock Farm",
            "type":"Manufacturing & Wholesale Goods"
        },
        {
            "category":"Farming",
            "subcategory":"Farm",
            "type":"Manufacturing & Wholesale Goods"
        }
    ],
    "sg:phone":"+44 151 336 4770",
    "sg:postcode":"CH64 5TQ",
    "sg:province":"Cheshire",
    "sg:tags":[
        "mixed",
        "crop"
    ],
    "wof:name":"J A Crossley",
    "wof:placetype":"venue"
},
  "geometry": {"coordinates":[-3.025129,53.261066],"type":"Point"}
}