{
  "type": "Feature",
  "properties": {
    "addr:full":"Wentworth Ind Est, Wentworth Way, Tankersley Barnsley South Yorkshire S75 3DH",
    "addr:postcode":"s75 3dh",
    "addr:street":"Wentworth Way;Yorkshire",
    "iso:country":"GB",
    "sg:address":"Wentworth Ind Est, Wentworth Way, Tankersley",
    "sg:city":"Barnsley",
    "sg:classifiers":[
        {
            "category":"Manufacturing",
            "subcategory":"Metals",
            "type":"Manufacturing & Wholesale Goods"
        }
    ],
    "sg:phone":"+44 1226 352903",
    "sg:postcode":"S75 3DH",
    "sg:province":"South Yorkshire",
    "sg:tags":[
        "steel",
        "stockholder"
    ],
    "wof:name":"The Stainless Steel Trade Centre",
    "wof:placetype":"venue"
},
  "geometry": {"coordinates":[-1.482897,53.495152],"type":"Point"}
}