{
  "type": "Feature",
  "properties": {
    "addr:full":"34 Appletree Gardens, Newcastle Newcastle Upon Tyne Tyne and Wear NE6 4PA",
    "addr:housenumber":"34",
    "addr:postcode":"ne6 4pa",
    "addr:street":"Appletree Gardens",
    "iso:country":"GB",
    "sg:address":"34 Appletree Gardens, Newcastle",
    "sg:city":"Newcastle Upon Tyne",
    "sg:classifiers":[
        {
            "category":"Professional",
            "type":"Services"
        }
    ],
    "sg:phone":"+44 191 263 0036",
    "sg:postcode":"NE6 4PA",
    "sg:province":"Tyne and Wear",
    "sg:tags":[
        "control",
        "system"
    ],
    "wof:name":"Akroma Technical Services Ltd",
    "wof:placetype":"venue"
},
  "geometry": {"coordinates":[-1.5547519922,54.9880027771],"type":"Point"}
}