{
  "type": "Feature",
  "properties": {
    "iso:country":"GB",
    "sg:address":"36 St Andrew Street",
    "sg:city":"Hertford",
    "sg:classifiers":[
        {
            "category":"Retail",
            "subcategory":"Laundry & Dry Cleaning",
            "type":"Services"
        }
    ],
    "sg:phone":"+44 1992 505048",
    "sg:postcode":"SG14 1JA",
    "sg:province":"Hertfordshire",
    "sg:tags":[
        "alteration"
    ],
    "wof:name":"Flamsteads Dry Cleaners",
    "wof:placetype":"venue"
},
  "geometry": {"coordinates":[-0.082473,51.79657],"type":"Point"}
}