{
  "type": "Feature",
  "properties": {
    "iso:country":"GB",
    "sg:address":"21 Water Street",
    "sg:city":"Rhyl",
    "sg:classifiers":[
        {
            "category":"Food & Beverages",
            "subcategory":"Meat & Fish",
            "type":"Retail Goods"
        }
    ],
    "sg:phone":"+44 1745 350988",
    "sg:postcode":"LL18 1SP",
    "sg:province":"Conwy",
    "sg:tags":[
        "chip"
    ],
    "wof:name":"The Fry Inn",
    "wof:placetype":"venue"
},
  "geometry": {"coordinates":[-3.494399,53.320995],"type":"Point"}
}