{
  "type": "Feature",
  "properties": {
    "addr:full":"51 Hardwick Rd Pontefract North Yorkshire WF8 3QY",
    "addr:housenumber":"51",
    "addr:postcode":"wf8 3qy",
    "addr:street":"Hardwick Rd",
    "iso:country":"GB",
    "sg:address":"51 Hardwick Rd",
    "sg:city":"Pontefract",
    "sg:classifiers":[
        {
            "category":"Home & Garden",
            "subcategory":"Carpets & Floor Coverings",
            "type":"Retail Goods"
        }
    ],
    "sg:phone":"+44 1977 703698",
    "sg:postcode":"WF8 3QY",
    "sg:province":"North Yorkshire",
    "sg:tags":[
        "cleaner",
        "upholstery"
    ],
    "wof:name":"Abbey Qik-Dri",
    "wof:placetype":"venue"
},
  "geometry": {"coordinates":[-1.3094609976,53.6754264832],"type":"Point"}
}