{
  "type": "Feature",
  "properties": {
    "addr:full":"Unit 5a8 Elstow Storage Depot, Ampthill Rd, Kempston Bedford Bedfordshire MK45 2NR",
    "addr:housenumber":"5a8",
    "addr:postcode":"mk45 2nr",
    "addr:street":"Ampthill Rd",
    "iso:country":"GB",
    "sg:address":"Unit 5a8 Elstow Storage Depot, Ampthill Rd, Kempston",
    "sg:city":"Bedford",
    "sg:classifiers":[
        {
            "category":"Manufacturing",
            "subcategory":"Metals",
            "type":"Manufacturing & Wholesale Goods"
        }
    ],
    "sg:postcode":"MK45 2NR",
    "sg:province":"Bedfordshire",
    "sg:tags":[
        "work",
        "sheet"
    ],
    "wof:name":"Altair Fabrications",
    "wof:placetype":"venue"
},
  "geometry": {"coordinates":[-0.4949940145,52.0279464722],"type":"Point"}
}