{
  "type": "Feature",
  "properties": {
    "iso:country":"GB",
    "sg:address":"Unit 3, The Arena",
    "sg:city":"Enfield",
    "sg:classifiers":[
        {
            "category":"Professional",
            "subcategory":"Research",
            "type":"Services"
        }
    ],
    "sg:postcode":"EN3 7NL",
    "sg:province":"Greater London",
    "sg:tags":[
        "market"
    ],
    "wof:name":"Radar Retail Research",
    "wof:placetype":"venue"
},
  "geometry": {"coordinates":[-0.025682,51.665245],"type":"Point"}
}