{
  "type": "Feature",
  "properties": {
    "iso:country":"GB",
    "sg:address":"Park Road",
    "sg:city":"Coleford",
    "sg:classifiers":[
        {
            "category":"Food & Beverages",
            "subcategory":"Supermarket",
            "type":"Retail Goods"
        }
    ],
    "sg:phone":"+44 1594 833756",
    "sg:postcode":"GL16 7AZ",
    "sg:province":"Gloucestershire",
    "wof:name":"M L Chanpniss",
    "wof:placetype":"venue"
},
  "geometry": {"coordinates":[-2.604089,51.791393],"type":"Point"}
}