{
  "type": "Feature",
  "properties": {
    "addr:full":"8 Tees Close, Valley Park, Chandlers Ford Southampton Hampshire SO53 4RU",
    "addr:housenumber":"8",
    "addr:postcode":"so53 4ru",
    "addr:street":"Tees Close",
    "iso:country":"GB",
    "sg:address":"8 Tees Close, Valley Park, Chandlers Ford",
    "sg:city":"Southampton",
    "sg:classifiers":[
        {
            "category":"Communications",
            "subcategory":"Film & Video Production",
            "type":"Services"
        }
    ],
    "sg:postcode":"SO53 4RU",
    "sg:province":"Hampshire",
    "sg:tags":[
        "illustrator",
        "artist"
    ],
    "wof:name":"N J Murphy Publicity Matters",
    "wof:placetype":"venue"
},
  "geometry": {"coordinates":[-1.401421,50.99168],"type":"Point"}
}