{
  "type": "Feature",
  "properties": {
    "iso:country":"GB",
    "sg:address":"Lewes Road",
    "sg:city":"Forest Row",
    "sg:classifiers":[
        {
            "category":"Shopping",
            "subcategory":"Bicycles & Sporting Goods",
            "type":"Retail Goods"
        }
    ],
    "sg:phone":"+44 1342 822847",
    "sg:postcode":"RH18 5HD",
    "sg:province":"East Sussex",
    "sg:tags":[
        "cycle",
        "accessory"
    ],
    "wof:name":"Futurecycles",
    "wof:placetype":"venue"
},
  "geometry": {"coordinates":[0.033455,51.097309],"type":"Point"}
}