{
  "type": "Feature",
  "properties": {
    "iso:country":"GB",
    "sg:address":"2 Rutland Street",
    "sg:city":"Matlock",
    "sg:classifiers":[
        {
            "category":"Professional",
            "subcategory":"Business Services",
            "type":"Services"
        }
    ],
    "sg:phone":"+44 1629 760695",
    "sg:postcode":"DE4 3GN",
    "sg:province":"Derbyshire",
    "sg:tags":[
        "tile",
        "stockist"
    ],
    "wof:name":"Peak Tiles",
    "wof:placetype":"venue"
},
  "geometry": {"coordinates":[-1.550213,53.14233],"type":"Point"}
}