{
  "type": "Feature",
  "properties": {
    "addr:full":"Lower Galdeford Ludlow Herefordshire SY8 1RT",
    "addr:postcode":"sy8 1rt",
    "addr:street":"Lower Galdeford",
    "iso:country":"GB",
    "sg:address":"Lower Galdeford",
    "sg:city":"Ludlow",
    "sg:classifiers":[
        {
            "category":"Retail",
            "subcategory":"Auto Repair",
            "type":"Services"
        }
    ],
    "sg:phone":"+44 1584 874711",
    "sg:postcode":"SY8 1RT",
    "sg:province":"Herefordshire",
    "sg:tags":[
        "body",
        "garage",
        "modification",
        "car"
    ],
    "wof:name":"Smithfield Motor's",
    "wof:placetype":"venue"
},
  "geometry": {"coordinates":[-2.713479,52.367981],"type":"Point"}
}