{
  "type": "Feature",
  "properties": {
    "addr:full":"Unit 5-6 109 Maybank Road London Greater London E18 1EJ",
    "addr:housenumber":"unit 5-6",
    "addr:postcode":"109;e18 1ej",
    "addr:street":"Maybank Road",
    "iso:country":"GB",
    "sg:address":"Unit 5-6 109 Maybank Road",
    "sg:city":"London",
    "sg:classifiers":[
        {
            "category":"Home & Garden",
            "subcategory":"Building Materials",
            "type":"Retail Goods"
        }
    ],
    "sg:phone":"+44 20 8477 1783",
    "sg:postcode":"E18 1EJ",
    "sg:province":"Greater London",
    "sg:tags":[
        "shutter",
        "door"
    ],
    "wof:name":"P V C Contact Strip Curtains",
    "wof:placetype":"venue"
},
  "geometry": {"coordinates":[0.03243,51.595459],"type":"Point"}
}