{
  "type": "Feature",
  "properties": {
    "addr:full":"2 Urmston Lane, Stretford Manchester Cheshire M32 9BP",
    "addr:housenumber":"2",
    "addr:postcode":"m32 9bp",
    "addr:street":"Urmston Lane",
    "iso:country":"GB",
    "sg:address":"2 Urmston Lane, Stretford",
    "sg:city":"Manchester",
    "sg:classifiers":[
        {
            "category":"Real Estate",
            "subcategory":"Surveying",
            "type":"Services"
        }
    ],
    "sg:phone":"+44 161 865 8456",
    "sg:postcode":"M32 9BP",
    "sg:province":"Cheshire",
    "sg:tags":[
        "surveyor",
        "land"
    ],
    "wof:name":"Countrywide Surveyors (1994)",
    "wof:placetype":"venue"
},
  "geometry": {"coordinates":[-2.313849,53.44569],"type":"Point"}
}