{
  "type": "Feature",
  "properties": {
    "addr:full":"220 Queenstown Road London Greater London SW8 4LP",
    "addr:housenumber":"220",
    "addr:postcode":"sw8 4lp",
    "addr:street":"Queenstown Road",
    "iso:country":"GB",
    "sg:address":"220 Queenstown Road",
    "sg:city":"London",
    "sg:classifiers":[
        {
            "category":"Food & Beverages",
            "subcategory":"Liquor & Beverages",
            "type":"Retail Goods"
        }
    ],
    "sg:phone":"+44 20 7821 2000",
    "sg:postcode":"SW8 4LP",
    "sg:province":"Greater London",
    "sg:tags":[
        "beer",
        "spirit",
        "wines"
    ],
    "wof:name":"Farr Vintners Ltd.",
    "wof:placetype":"venue"
},
  "geometry": {"coordinates":[-0.1478,51.475941],"type":"Point"}
}