{
  "type": "Feature",
  "properties": {
    "addr:full":"23 Bridge Road Wembley Greater London HA9 9AB",
    "addr:housenumber":"23",
    "addr:postcode":"ha9 9ab",
    "addr:street":"Bridge Road",
    "iso:country":"GB",
    "sg:address":"23 Bridge Road",
    "sg:city":"Wembley",
    "sg:classifiers":[
        {
            "category":"Fast Food",
            "type":"Food & Drink"
        }
    ],
    "sg:postcode":"HA9 9AB",
    "sg:province":"Greater London",
    "sg:tags":[
        "away",
        "take"
    ],
    "wof:name":"Tse,W,",
    "wof:placetype":"venue"
},
  "geometry": {"coordinates":[-0.277839,51.564568],"type":"Point"}
}