{
  "type": "Feature",
  "properties": {
    "addr:full":"Hempholme Bridge, Hempholme Driffield East Riding of Yorkshire YO25 8NA",
    "addr:postcode":"yo25 8na",
    "iso:country":"GB",
    "sg:address":"Hempholme Bridge, Hempholme",
    "sg:city":"Driffield",
    "sg:classifiers":[
        {
            "category":"Recreation",
            "subcategory":"Water Park",
            "type":"Entertainment"
        }
    ],
    "sg:phone":"+44 1964 543631",
    "sg:postcode":"YO25 8NA",
    "sg:province":"East Riding of Yorkshire",
    "sg:tags":[
        "sport"
    ],
    "wof:name":"Billabong Watersports & Caravan Park",
    "wof:placetype":"venue"
},
  "geometry": {"coordinates":[-0.3413040042,53.9370918274],"type":"Point"}
}