{
  "type": "Feature",
  "properties": {
    "iso:country":"GB",
    "sg:address":"Pipps Hill Country Club",
    "sg:city":"Basildon",
    "sg:classifiers":[
        {
            "category":"Recreation",
            "subcategory":"Water Park",
            "type":"Entertainment"
        }
    ],
    "sg:phone":"+44 1268 270044",
    "sg:postcode":"SS14 3DG",
    "sg:province":"Essex",
    "sg:tags":[
        "sport"
    ],
    "wof:name":"Basildon Jet Ski Centre",
    "wof:placetype":"venue"
},
  "geometry": {"coordinates":[0.47498,51.5854],"type":"Point"}
}