{
  "type": "Feature",
  "properties": {
    "addr:full":"Beaufort Lodge, 31 Park Road Hamilton South Lanarkshire ML3 6PD",
    "addr:housenumber":"31",
    "addr:postcode":"ml3 6pd",
    "addr:street":"Park Road",
    "iso:country":"GB",
    "sg:address":"Beaufort Lodge, 31 Park Road",
    "sg:city":"Hamilton",
    "sg:classifiers":[
        {
            "category":"Banks & Credit Unions",
            "subcategory":"Bank",
            "type":"Services"
        },
        {
            "category":"Professional",
            "subcategory":"Business Services",
            "type":"Services"
        }
    ],
    "sg:phone":"+44 1698 284481",
    "sg:postcode":"ML3 6PD",
    "sg:province":"South Lanarkshire",
    "sg:tags":[
        "stocktaking",
        "inventory"
    ],
    "wof:name":"Chemval Services",
    "wof:placetype":"venue"
},
  "geometry": {"coordinates":[-4.0528907776,55.7773208618],"type":"Point"}
}