{
  "type": "Feature",
  "properties": {
    "iso:country":"GB",
    "sg:address":"13 Buttermere",
    "sg:city":"Gateshead",
    "sg:classifiers":[
        {
            "category":"Food & Beverages",
            "subcategory":"Groceries & Convenience Stores",
            "type":"Retail Goods"
        }
    ],
    "sg:phone":"+44 191 438 1055",
    "sg:postcode":"NE10 0XE",
    "sg:province":"Tyne and Wear",
    "wof:name":"Grange Stores",
    "wof:placetype":"venue"
},
  "geometry": {"coordinates":[-1.5467059612,54.9499320984],"type":"Point"}
}