{
  "type": "Feature",
  "properties": {
    "iso:country":"GB",
    "sg:address":"1 Market Gates Shopping Ctr",
    "sg:city":"Great Yarmouth",
    "sg:classifiers":[
        {
            "category":"Shopping",
            "subcategory":"Florist",
            "type":"Retail Goods"
        }
    ],
    "sg:phone":"+44 1493 745505",
    "sg:postcode":"NR30 2AX",
    "sg:province":"Norfolk",
    "wof:name":"Market Gates Florist",
    "wof:placetype":"venue"
},
  "geometry": {"coordinates":[1.7277549505,52.6083984375],"type":"Point"}
}