{
  "type": "Feature",
  "properties": {
    "addr:full":"Long Lane, Aintree Liverpool Merseyside L9 0EB",
    "addr:postcode":"l9 0eb",
    "addr:street":"Long Lane",
    "iso:country":"GB",
    "sg:address":"Long Lane, Aintree",
    "sg:city":"Liverpool",
    "sg:classifiers":[
        {
            "category":"Home & Garden",
            "subcategory":"Furniture",
            "type":"Retail Goods"
        }
    ],
    "sg:phone":"+44 151 521 2223",
    "sg:postcode":"L9 0EB",
    "sg:province":"Merseyside",
    "sg:tags":[
        "bed",
        "mattress"
    ],
    "wof:name":"The Bed Factory",
    "wof:placetype":"venue"
},
  "geometry": {"coordinates":[-2.9544289112,53.4651641846],"type":"Point"}
}