{
  "type": "Feature",
  "properties": {
    "iso:country":"GB",
    "sg:address":"6 Paget Road",
    "sg:city":"Great Yarmouth",
    "sg:classifiers":[
        {
            "category":"Travel",
            "subcategory":"Hotels & Motels",
            "type":"Entertainment"
        }
    ],
    "sg:postcode":"NR30 2DN",
    "sg:province":"Norfolk",
    "sg:tags":[
        "house",
        "guest"
    ],
    "wof:name":"Strathclyde Guest House",
    "wof:placetype":"venue"
},
  "geometry": {"coordinates":[1.735617,52.609352],"type":"Point"}
}