{
  "type": "Feature",
  "properties": {
    "iso:country":"GB",
    "sg:address":"14 Upper St South, New Ash Grn",
    "sg:city":"Longfield",
    "sg:classifiers":[
        {
            "category":"Insurance",
            "subcategory":"Insurance Agent",
            "type":"Services"
        }
    ],
    "sg:phone":"+44 1474 874166",
    "sg:postcode":"DA3 8JJ",
    "sg:province":"Kent",
    "wof:name":"Aron Insurance",
    "wof:placetype":"venue"
},
  "geometry": {"coordinates":[0.30472,51.365898],"type":"Point"}
}