{
  "type": "Feature",
  "properties": {
    "iso:country":"GB",
    "sg:address":"191 Stoke Newington Church St",
    "sg:city":"Stoke Newington",
    "sg:classifiers":[
        {
            "category":"Cinema",
            "subcategory":"Movie Rental",
            "type":"Entertainment"
        }
    ],
    "sg:phone":"+44 20 7249 4344",
    "sg:postcode":"N16 0UL",
    "sg:province":"Greater London",
    "sg:tags":[
        "video",
        "library"
    ],
    "wof:name":"Sound Entertainment",
    "wof:placetype":"venue"
},
  "geometry": {"coordinates":[-0.083304,51.561069],"type":"Point"}
}