{
  "type": "Feature",
  "properties": {
    "iso:country":"GB",
    "sg:address":"193 Meanwood Road",
    "sg:city":"Leeds",
    "sg:classifiers":[
        {
            "category":"Transit Center",
            "subcategory":"Freight",
            "type":"Transportation"
        }
    ],
    "sg:postcode":"LS7 1NB",
    "sg:province":"West Yorkshire",
    "sg:tags":[
        "piano",
        "accessory"
    ],
    "wof:name":"Hughes Pianos",
    "wof:placetype":"venue"
},
  "geometry": {"coordinates":[-1.5429350138,53.8119468689],"type":"Point"}
}