{
  "type": "Feature",
  "properties": {
    "iso:country":"GB",
    "sg:address":"69 New Summer Street",
    "sg:city":"Birmingham",
    "sg:classifiers":[
        {
            "category":"Manufacturing",
            "subcategory":"Metals",
            "type":"Manufacturing & Wholesale Goods"
        },
        {
            "category":"Professional",
            "subcategory":"Art Services",
            "type":"Services"
        }
    ],
    "sg:phone":"+44 121 248 1500",
    "sg:postcode":"B19 3TE",
    "sg:province":"West Midlands",
    "sg:tags":[
        "polishing",
        "finishing"
    ],
    "wof:name":"S O S Metal Finishing Service",
    "wof:placetype":"venue"
},
  "geometry": {"coordinates":[-1.899189,52.489498],"type":"Point"}
}