{
  "type": "Feature",
  "properties": {
    "addr:full":"University Of Oxford, Wytham Oxford Oxfordshire OX2 8QJ",
    "addr:postcode":"ox2 8qj",
    "iso:country":"GB",
    "sg:address":"University Of Oxford, Wytham",
    "sg:city":"Oxford",
    "sg:classifiers":[
        {
            "category":"Farming",
            "subcategory":"Farm",
            "type":"Manufacturing & Wholesale Goods"
        }
    ],
    "sg:phone":"+44 1865 247359",
    "sg:postcode":"OX2 8QJ",
    "sg:province":"Oxfordshire",
    "sg:tags":[
        "mixed",
        "crop"
    ],
    "wof:name":"University Farm",
    "wof:placetype":"venue"
},
  "geometry": {"coordinates":[-1.311978,51.774895],"type":"Point"}
}