{
  "type": "Feature",
  "properties": {
    "iso:country":"GB",
    "sg:address":"Elmbank, Lairg Road, Bonar Bridge",
    "sg:city":"Ardgay",
    "sg:classifiers":[
        {
            "category":"Shopping",
            "subcategory":"Bicycles & Sporting Goods",
            "type":"Retail Goods"
        },
        {
            "category":"Personal",
            "subcategory":"Skin Care",
            "type":"Services"
        }
    ],
    "sg:phone":"+44 1863 766700",
    "sg:postcode":"IV24 3EA",
    "sg:province":"Highland",
    "sg:tags":[
        "merchant",
        "leather",
        "saddlery",
        "wear",
        "riding"
    ],
    "wof:name":"V D Mackenzie-Harris",
    "wof:placetype":"venue"
},
  "geometry": {"coordinates":[-4.363122,57.881462],"type":"Point"}
}