{
  "type": "Feature",
  "properties": {
    "addr:full":"Unit 7 The Gateway Est, West Midland Freeport Birmingham West Midlands B26 3QD",
    "addr:housenumber":"unit 7",
    "addr:postcode":"b26 3qd",
    "addr:street":"The Gateway Est West",
    "iso:country":"GB",
    "sg:address":"Unit 7 The Gateway Est, West Midland Freeport",
    "sg:city":"Birmingham",
    "sg:classifiers":[
        {
            "category":"Manufacturing",
            "subcategory":"Buildings",
            "type":"Manufacturing & Wholesale Goods"
        }
    ],
    "sg:phone":"+44 121 782 2533",
    "sg:postcode":"B26 3QD",
    "sg:province":"West Midlands",
    "sg:tags":[
        "system",
        "air conditioning"
    ],
    "wof:name":"Aquamajor",
    "wof:placetype":"venue"
},
  "geometry": {"coordinates":[-1.7544139624,52.4488449097],"type":"Point"}
}