{
  "type": "Feature",
  "properties": {
    "addr:full":"College Rd, Aston Clinton Aylesbury Somerset TA8 1ER",
    "addr:postcode":"ta8 1er",
    "addr:street":"College Rd",
    "iso:country":"GB",
    "sg:address":"College Rd, Aston Clinton",
    "sg:city":"Aylesbury",
    "sg:classifiers":[
        {
            "category":"Military Area",
            "subcategory":"Air Force Base",
            "type":"Public Place"
        }
    ],
    "sg:phone":"+44 1278 795499",
    "sg:postcode":"TA8 1ER",
    "sg:province":"Somerset",
    "sg:tags":[
        "water",
        "treatment"
    ],
    "wof:name":"Klargester Environmental En",
    "wof:placetype":"venue"
},
  "geometry": {"coordinates":[-2.99462,51.236752],"type":"Point"}
}