{
  "type": "Feature",
  "properties": {
    "addr:full":"15 Farndale Close Crewe Cheshire CW2 6SE",
    "addr:housenumber":"15",
    "addr:postcode":"cw2 6se",
    "addr:street":"Farndale Close",
    "iso:country":"GB",
    "sg:address":"15 Farndale Close",
    "sg:city":"Crewe",
    "sg:classifiers":[
        {
            "category":"Building & Trades",
            "subcategory":"Construction",
            "type":"Services"
        }
    ],
    "sg:phone":"+44 1270 650234",
    "sg:postcode":"CW2 6SE",
    "sg:province":"Cheshire",
    "sg:tags":[
        "builder"
    ],
    "wof:name":"C & S Builders",
    "wof:placetype":"venue"
},
  "geometry": {"coordinates":[-2.458386898,53.0729675293],"type":"Point"}
}