{
  "type": "Feature",
  "properties": {
    "addr:full":"76 Ravenor Park Road Greenford Greater London UB6 9QY",
    "addr:housenumber":"76",
    "addr:postcode":"ub6 9qy",
    "addr:street":"Ravenor Park Road",
    "iso:country":"GB",
    "sg:address":"76 Ravenor Park Road",
    "sg:city":"Greenford",
    "sg:classifiers":[
        {
            "category":"Arena",
            "subcategory":"Sports Club",
            "type":"Entertainment"
        }
    ],
    "sg:phone":"+44 20 8578 4678",
    "sg:postcode":"UB6 9QY",
    "sg:province":"Greater London",
    "wof:name":"Greenford Tennis Club",
    "wof:placetype":"venue"
},
  "geometry": {"coordinates":[-0.3590059876,51.5323867798],"type":"Point"}
}