{
  "type": "Feature",
  "properties": {
    "addr:full":"23 Chiswell Road Poole Dorset BH17 9FB",
    "addr:housenumber":"23",
    "addr:postcode":"bh17 9fb",
    "addr:street":"Chiswell Road",
    "iso:country":"GB",
    "sg:address":"23 Chiswell Road",
    "sg:city":"Poole",
    "sg:classifiers":[
        {
            "category":"Building & Trades",
            "subcategory":"Construction",
            "type":"Services"
        }
    ],
    "sg:phone":"+44 1202 246271",
    "sg:postcode":"BH17 9FB",
    "sg:province":"Dorset",
    "sg:tags":[
        "builder"
    ],
    "wof:name":"A Darby",
    "wof:placetype":"venue"
},
  "geometry": {"coordinates":[-1.976837039,50.7487297058],"type":"Point"}
}