{
  "type": "Feature",
  "properties": {
    "addr:full":"Unit 26 Lyon Rd Walton On Thames Surrey KT12 3PU",
    "addr:housenumber":"unit 26",
    "addr:postcode":"kt12 3pu",
    "addr:street":"Lyon Rd",
    "iso:country":"GB",
    "sg:address":"Unit 26 Lyon Rd",
    "sg:city":"Walton On Thames",
    "sg:classifiers":[
        {
            "category":"Government",
            "subcategory":"Post Office",
            "type":"Public Place"
        }
    ],
    "sg:phone":"+44 1932 267520",
    "sg:postcode":"KT12 3PU",
    "sg:province":"Surrey",
    "sg:tags":[
        "messenger",
        "courier"
    ],
    "wof:name":"P & L Couriers",
    "wof:placetype":"venue"
},
  "geometry": {"coordinates":[-0.386587,51.378899],"type":"Point"}
}