{
  "type": "Feature",
  "properties": {
    "addr:full":"3-5 Frenchay Road Weston-super-mare Somerset BS23 4JL",
    "addr:housenumber":"3-5",
    "addr:postcode":"bs23 4jl",
    "addr:street":"Frenchay Road",
    "iso:country":"GB",
    "sg:address":"3-5 Frenchay Road",
    "sg:city":"Weston-super-mare",
    "sg:classifiers":[
        {
            "category":"Health Services",
            "subcategory":"Nursing And Care Facility",
            "type":"Services"
        }
    ],
    "sg:postcode":"BS23 4JL",
    "sg:province":"Somerset",
    "sg:tags":[
        "home"
    ],
    "wof:name":"Churchill Nursing Home",
    "wof:placetype":"venue"
},
  "geometry": {"coordinates":[-2.974399,51.332195],"type":"Point"}
}