{
  "type": "Feature",
  "properties": {
    "addr:full":"70 Feiashill Road, Trysull Wolverhampton Shropshire WV5 7HT",
    "addr:housenumber":"70",
    "addr:postcode":"wv5 7ht",
    "addr:street":"Feiashill Road",
    "iso:country":"GB",
    "sg:address":"70 Feiashill Road, Trysull",
    "sg:city":"Wolverhampton",
    "sg:classifiers":[
        {
            "category":"Home & Garden",
            "subcategory":"Garden Supply",
            "type":"Retail Goods"
        },
        {
            "category":"Farming",
            "subcategory":"Farm",
            "type":"Manufacturing & Wholesale Goods"
        }
    ],
    "sg:postcode":"WV5 7HT",
    "sg:province":"Shropshire",
    "sg:tags":[
        "mixed",
        "bulb",
        "crop",
        "grower"
    ],
    "wof:name":"R M & C M Baker",
    "wof:placetype":"venue"
},
  "geometry": {"coordinates":[-2.223223,52.538269],"type":"Point"}
}