{
  "type": "Feature",
  "properties": {
    "addr:full":"5 The Beeches, Baildon Shipley West Yorkshire BD17 6JN",
    "addr:housenumber":"5",
    "addr:postcode":"bd17 6jn",
    "addr:street":"The Beeches Baildon",
    "iso:country":"GB",
    "sg:address":"5 The Beeches, Baildon",
    "sg:city":"Shipley",
    "sg:classifiers":[
        {
            "category":"Professional",
            "subcategory":"Management & Consulting",
            "type":"Services"
        }
    ],
    "sg:phone":"+44 1274 580008",
    "sg:postcode":"BD17 6JN",
    "sg:province":"West Yorkshire",
    "sg:tags":[
        "consultant",
        "business"
    ],
    "wof:name":"Maxfile Ltd.",
    "wof:placetype":"venue"
},
  "geometry": {"coordinates":[-1.766849,53.848671],"type":"Point"}
}