{
  "type": "Feature",
  "properties": {
    "iso:country":"GB",
    "sg:address":"2 Church Way",
    "sg:city":"Benfleet",
    "sg:classifiers":[
        {
            "category":"Arts & Performance",
            "subcategory":"Music",
            "type":"Entertainment"
        }
    ],
    "sg:postcode":"SS7 2EU",
    "sg:province":"Essex",
    "sg:tags":[
        "mobile",
        "disco"
    ],
    "wof:name":"South East Essex Disco Services",
    "wof:placetype":"venue"
},
  "geometry": {"coordinates":[0.62027,51.55093],"type":"Point"}
}