{
  "type": "Feature",
  "properties": {
    "iso:country":"GB",
    "sg:address":"The Lydiates",
    "sg:city":"Tenbury Wells",
    "sg:classifiers":[
        {
            "category":"Farming",
            "subcategory":"Farm",
            "type":"Manufacturing & Wholesale Goods"
        }
    ],
    "sg:postcode":"WR15 8RG",
    "sg:province":"Herefordshire",
    "sg:tags":[
        "mixed",
        "crop"
    ],
    "wof:name":"Staples Bros",
    "wof:placetype":"venue"
},
  "geometry": {"coordinates":[-2.594179,52.312584],"type":"Point"}
}