{
  "type": "Feature",
  "properties": {
    "iso:country":"GB",
    "sg:address":"Wern Farm, Colva",
    "sg:city":"Kington",
    "sg:classifiers":[
        {
            "category":"Home & Garden",
            "subcategory":"Garden Supply",
            "type":"Retail Goods"
        },
        {
            "category":"Farming",
            "subcategory":"Farm",
            "type":"Manufacturing & Wholesale Goods"
        }
    ],
    "sg:phone":"+44 1544 370245",
    "sg:postcode":"HR5 3QU",
    "sg:province":"Herefordshire",
    "sg:tags":[
        "mixed",
        "bulb",
        "crop",
        "grower"
    ],
    "wof:name":"S I Rogers",
    "wof:placetype":"venue"
},
  "geometry": {"coordinates":[-3.029478,52.203629],"type":"Point"}
}