{
  "type": "Feature",
  "properties": {
    "iso:country":"GB",
    "sg:address":"54 Spittal Road, Rutherglen",
    "sg:city":"Glasgow",
    "sg:classifiers":[
        {
            "category":"Health Services",
            "subcategory":"Dentist",
            "type":"Services"
        }
    ],
    "sg:phone":"+44 141 634 7102",
    "sg:postcode":"G73 4QE",
    "sg:province":"Glasgow City",
    "wof:name":"The Dental Surgery",
    "wof:placetype":"venue"
},
  "geometry": {"coordinates":[-4.221825,55.813251],"type":"Point"}
}