{
  "type": "Feature",
  "properties": {
    "addr:full":"10 Greenfield Crescent Birmingham West Midlands B15 3AU",
    "addr:housenumber":"10",
    "addr:postcode":"b15 3au",
    "addr:street":"Greenfield Crescent",
    "iso:country":"GB",
    "sg:address":"10 Greenfield Crescent",
    "sg:city":"Birmingham",
    "sg:classifiers":[
        {
            "category":"Professional",
            "subcategory":"Business Services",
            "type":"Services"
        }
    ],
    "sg:phone":"+44 121 456 6110",
    "sg:postcode":"B15 3AU",
    "sg:province":"West Midlands",
    "sg:tags":[
        "trade"
    ],
    "wof:name":"Metal Trustees (Services) Ltd.",
    "wof:placetype":"venue"
},
  "geometry": {"coordinates":[-1.9228570461,52.4703598022],"type":"Point"}
}