{
  "type": "Feature",
  "properties": {
    "iso:country":"GB",
    "sg:address":"57 Stoborough Meadow",
    "sg:city":"Wareham",
    "sg:classifiers":[
        {
            "category":"Real Estate",
            "subcategory":"Architect",
            "type":"Services"
        }
    ],
    "sg:phone":"+44 1929 550900",
    "sg:postcode":"BH20 5HP",
    "sg:province":"Dorset",
    "wof:name":"Michael J Clark Design Partnership",
    "wof:placetype":"venue"
},
  "geometry": {"coordinates":[-2.106353,50.672604],"type":"Point"}
}