{
  "type": "Feature",
  "properties": {
    "iso:country":"GB",
    "sg:address":"Dalton Barracks",
    "sg:city":"Abingdon",
    "sg:classifiers":[
        {
            "category":"Personal",
            "subcategory":"Beauty Salon",
            "type":"Services"
        }
    ],
    "sg:postcode":"OX13 6JB",
    "sg:province":"Oxfordshire",
    "sg:tags":[
        "lady",
        "hairdresser"
    ],
    "wof:name":"Bristow,Elizabeth Ann,",
    "wof:placetype":"venue"
},
  "geometry": {"coordinates":[-1.3190840483,51.6757621765],"type":"Point"}
}