{
  "type": "Feature",
  "properties": {
    "iso:country":"GB",
    "sg:address":"1 Metro Compound Pool Rd, Ind Est, Pool Rd",
    "sg:city":"Nuneaton",
    "sg:classifiers":[
        {
            "category":"Bus Charters",
            "type":"Transportation"
        }
    ],
    "sg:phone":"+44 24 7637 5965",
    "sg:postcode":"CV10 9AE",
    "sg:province":"Leicestershire",
    "sg:tags":[
        "hire",
        "coach"
    ],
    "wof:name":"Richies Minibuses",
    "wof:placetype":"venue"
},
  "geometry": {"coordinates":[-1.537259,52.524364],"type":"Point"}
}