{
  "type": "Feature",
  "properties": {
    "iso:country":"GB",
    "sg:address":"Whinbank Farm, Distington",
    "sg:city":"Workington",
    "sg:classifiers":[
        {
            "category":"Real Estate",
            "subcategory":"Real Estate Services",
            "type":"Services"
        },
        {
            "category":"Building & Trades",
            "subcategory":"Equipment Rental",
            "type":"Services"
        }
    ],
    "sg:phone":"+44 1946 830305",
    "sg:postcode":"CA14 4QH",
    "sg:province":"Cumbria",
    "sg:tags":[
        "hire",
        "leasing",
        "plant",
        "machinery"
    ],
    "wof:name":"G & A M Lawson Ltd",
    "wof:placetype":"venue"
},
  "geometry": {"coordinates":[-3.550002,54.638981],"type":"Point"}
}