{
  "type": "Feature",
  "properties": {
    "addr:full":"Malton Road, Kirby Misperton Malton North Yorkshire YO17 6UF",
    "addr:postcode":"yo17 6uf",
    "addr:street":"Malton Road",
    "iso:country":"GB",
    "sg:address":"Malton Road, Kirby Misperton",
    "sg:city":"Malton",
    "sg:classifiers":[
        {
            "category":"Home & Garden",
            "subcategory":"Building Materials",
            "type":"Retail Goods"
        }
    ],
    "sg:phone":"+44 1653 668437",
    "sg:postcode":"YO17 6UF",
    "sg:province":"North Yorkshire",
    "sg:tags":[
        "furnishers",
        "bathroom",
        "planner"
    ],
    "wof:name":"Bathroom Ceramics Ltd.",
    "wof:placetype":"venue"
},
  "geometry": {"coordinates":[-0.8065059781,54.2040061951],"type":"Point"}
}