{
  "type": "Feature",
  "properties": {
    "iso:country":"GB",
    "sg:address":"Unit 58 East Goscote Indust Est, Long Furrow",
    "sg:city":"Leicester",
    "sg:classifiers":[
        {
            "category":"Manufacturing",
            "subcategory":"Textiles",
            "type":"Manufacturing & Wholesale Goods"
        }
    ],
    "sg:phone":"+44 116 269 7989",
    "sg:postcode":"LE7 3XJ",
    "sg:province":"Leicestershire",
    "sg:tags":[
        "knitwear"
    ],
    "wof:name":"Irojetex Ltd",
    "wof:placetype":"venue"
},
  "geometry": {"coordinates":[-1.0593,52.71241],"type":"Point"}
}