{
  "type": "Feature",
  "properties": {
    "addr:full":"116 Turves Green, Northfield Birmingham West Midlands B31 4BL",
    "addr:housenumber":"116",
    "addr:postcode":"b31 4bl",
    "addr:street":"Turves",
    "iso:country":"GB",
    "sg:address":"116 Turves Green, Northfield",
    "sg:city":"Birmingham",
    "sg:classifiers":[
        {
            "category":"Food & Beverages",
            "subcategory":"Supermarket",
            "type":"Retail Goods"
        }
    ],
    "sg:phone":"+44 121 478 1892",
    "sg:postcode":"B31 4BL",
    "sg:province":"West Midlands",
    "wof:name":"Kwik Save Foodstores",
    "wof:placetype":"venue"
},
  "geometry": {"coordinates":[-1.968311,52.402077],"type":"Point"}
}