{
  "type": "Feature",
  "properties": {
    "addr:full":"87 Lee Gate, Harwood Bolton Lancashire BL2 4BQ",
    "addr:housenumber":"87",
    "addr:postcode":"bl2 4bq",
    "addr:street":"Lee Gate",
    "iso:country":"GB",
    "sg:address":"87 Lee Gate, Harwood",
    "sg:city":"Bolton",
    "sg:classifiers":[
        {
            "category":"Retail",
            "subcategory":"Laundry & Dry Cleaning",
            "type":"Services"
        }
    ],
    "sg:phone":"+44 1204 595934",
    "sg:postcode":"BL2 4BQ",
    "sg:province":"Lancashire",
    "sg:tags":[
        "alteration"
    ],
    "wof:name":"Halls Laundry & Dry Cleaning Co",
    "wof:placetype":"venue"
},
  "geometry": {"coordinates":[-2.3973329067,53.6068305969],"type":"Point"}
}