{
  "type": "Feature",
  "properties": {
    "addr:full":"125-127 Ralston Road Campbeltown Argyll and Bute PA28 6LG",
    "addr:housenumber":"125-127",
    "addr:postcode":"pa28 6lg",
    "addr:street":"Ralston Road",
    "iso:country":"GB",
    "sg:address":"125-127 Ralston Road",
    "sg:city":"Campbeltown",
    "sg:classifiers":[
        {
            "category":"Food & Beverages",
            "subcategory":"Groceries & Convenience Stores",
            "type":"Retail Goods"
        }
    ],
    "sg:phone":"+44 1586 553556",
    "sg:postcode":"PA28 6LG",
    "sg:province":"Argyll and Bute",
    "wof:name":"Archibald J Maclellan",
    "wof:placetype":"venue"
},
  "geometry": {"coordinates":[-5.612025,55.418175],"type":"Point"}
}