{
  "type": "Feature",
  "properties": {
    "iso:country":"GB",
    "sg:address":"Unit 7-9 Newstead Indstl Est, Hazelford Way, Newstead Village",
    "sg:city":"Nottingham",
    "sg:classifiers":[
        {
            "category":"Shopping",
            "subcategory":"Clothing, Apparel, & Fashions",
            "type":"Retail Goods"
        }
    ],
    "sg:phone":"+44 1623 757946",
    "sg:postcode":"NG15 0DQ",
    "sg:province":"Nottinghamshire",
    "sg:tags":[
        "clothing",
        "fabric"
    ],
    "wof:name":"Sterhall Ltd",
    "wof:placetype":"venue"
},
  "geometry": {"coordinates":[-1.22907,53.069012],"type":"Point"}
}