{
  "type": "Feature",
  "properties": {
    "addr:full":"Mill Hill Road Cowes Isle of Wight PO31 7EQ",
    "addr:postcode":"po31 7eq",
    "addr:street":"Mill Hill Road",
    "iso:country":"GB",
    "sg:address":"Mill Hill Road",
    "sg:city":"Cowes",
    "sg:classifiers":[
        {
            "category":"Organizations",
            "subcategory":"Non-profit Organization",
            "type":"Services"
        }
    ],
    "sg:phone":"+44 1983 299098",
    "sg:postcode":"PO31 7EQ",
    "sg:province":"Isle of Wight",
    "sg:tags":[
        "charitable",
        "organisation",
        "voluntary",
        "charity"
    ],
    "wof:name":"The National Childbirth Trust",
    "wof:placetype":"venue"
},
  "geometry": {"coordinates":[-1.2959640026,50.7594718933],"type":"Point"}
}