{
  "type": "Feature",
  "properties": {
    "iso:country":"GB",
    "sg:address":"55 Denmark Hill",
    "sg:city":"Camberwell",
    "sg:classifiers":[
        {
            "category":"Professional",
            "subcategory":"Business Services",
            "type":"Services"
        }
    ],
    "sg:phone":"+44 20 7708 5432",
    "sg:postcode":"SE5 8RS",
    "sg:province":"Greater London",
    "sg:tags":[
        "answering"
    ],
    "wof:name":"Camberwell Business Club",
    "wof:placetype":"venue"
},
  "geometry": {"coordinates":[-0.092804,51.471897],"type":"Point"}
}