{
  "type": "Feature",
  "properties": {
    "iso:country":"GB",
    "sg:address":"26 Poplar Street",
    "sg:city":"Southport",
    "sg:classifiers":[
        {
            "category":"Shopping",
            "subcategory":"Party Supplies",
            "type":"Retail Goods"
        },
        {
            "category":"Arts & Performance",
            "subcategory":"Music",
            "type":"Entertainment"
        }
    ],
    "sg:phone":"+44 1704 380761",
    "sg:postcode":"PR8 6DX",
    "sg:province":"Lancashire",
    "sg:tags":[
        "mobile",
        "operator",
        "disco"
    ],
    "wof:name":"Starlight Sounds Disco",
    "wof:placetype":"venue"
},
  "geometry": {"coordinates":[-2.97689,53.641773],"type":"Point"}
}