{
  "type": "Feature",
  "properties": {
    "addr:full":"41 Exmouth Market London Greater London EC1R 4QL",
    "addr:housenumber":"41",
    "addr:postcode":"ec1r 4ql",
    "addr:street":"Exmouth Market",
    "iso:country":"GB",
    "sg:address":"41 Exmouth Market",
    "sg:city":"London",
    "sg:classifiers":[
        {
            "category":"Food & Beverages",
            "subcategory":"Fruits & Vegetables",
            "type":"Retail Goods"
        }
    ],
    "sg:phone":"+44 20 7833 2354",
    "sg:postcode":"EC1R 4QL",
    "sg:province":"Greater London",
    "sg:tags":[
        "greengrocer"
    ],
    "wof:name":"Oriental Groceries",
    "wof:placetype":"venue"
},
  "geometry": {"coordinates":[-0.109106,51.526077],"type":"Point"}
}