{
  "type": "Feature",
  "properties": {
    "iso:country":"GB",
    "sg:address":"49 Fore Street",
    "sg:city":"Hayle",
    "sg:classifiers":[
        {
            "category":"Personal",
            "subcategory":"Beauty Salon",
            "type":"Services"
        }
    ],
    "sg:phone":"+44 1736 753440",
    "sg:postcode":"TR27 4DX",
    "sg:province":"Cornwall",
    "sg:tags":[
        "unisex",
        "hairdresser"
    ],
    "wof:name":"Hair Ways",
    "wof:placetype":"venue"
},
  "geometry": {"coordinates":[-5.411754,50.190868],"type":"Point"}
}