{
  "type": "Feature",
  "properties": {
    "addr:full":"Taeblair, Edderton Tain Highland IV19 1JY",
    "addr:postcode":"iv19 1jy",
    "iso:country":"GB",
    "sg:address":"Taeblair, Edderton",
    "sg:city":"Tain",
    "sg:classifiers":[
        {
            "category":"Retail",
            "subcategory":"Repair Shop",
            "type":"Services"
        }
    ],
    "sg:postcode":"IV19 1JY",
    "sg:province":"Highland",
    "sg:tags":[
        "upholsterer"
    ],
    "wof:name":"Highland Upholsterers",
    "wof:placetype":"venue"
},
  "geometry": {"coordinates":[-4.0532450676,57.8113594055],"type":"Point"}
}