{
  "type": "Feature",
  "properties": {
    "addr:full":"Oldbury Club, Windsor Road Oldbury West Midlands B68 8NY",
    "addr:postcode":"b68 8ny",
    "addr:street":"Windsor Road",
    "iso:country":"GB",
    "sg:address":"Oldbury Club, Windsor Road",
    "sg:city":"Oldbury",
    "sg:classifiers":[
        {
            "category":"Organizations",
            "subcategory":"Community Association",
            "type":"Services"
        },
        {
            "category":"Organizations",
            "subcategory":"Membership Organization",
            "type":"Services"
        }
    ],
    "sg:phone":"+44 121 552 1248",
    "sg:postcode":"B68 8NY",
    "sg:province":"West Midlands",
    "sg:tags":[
        "club",
        "social"
    ],
    "wof:name":"The Royal British Legion",
    "wof:placetype":"venue"
},
  "geometry": {"coordinates":[-2.01284,52.483501],"type":"Point"}
}