{
  "type": "Feature",
  "properties": {
    "iso:country":"GB",
    "sg:address":"7-8 Bridgtown Business Centre, Bridgetown",
    "sg:city":"Cannock",
    "sg:classifiers":[
        {
            "category":"Shopping",
            "subcategory":"Clothing, Apparel, & Fashions",
            "type":"Retail Goods"
        }
    ],
    "sg:phone":"+44 1543 571397",
    "sg:postcode":"WS11 3AZ",
    "sg:province":"Staffordshire",
    "sg:tags":[
        "dresswear"
    ],
    "wof:name":"The Five Star Dress Agency",
    "wof:placetype":"venue"
},
  "geometry": {"coordinates":[-2.029999,52.675743],"type":"Point"}
}