{
  "type": "Feature",
  "properties": {
    "iso:country":"GB",
    "sg:address":"43 Fore Street",
    "sg:city":"Kingsbridge",
    "sg:classifiers":[
        {
            "category":"Personal",
            "subcategory":"Beauty Salon",
            "type":"Services"
        }
    ],
    "sg:phone":"+44 1548 852128",
    "sg:postcode":"TQ7 1PG",
    "sg:province":"Devon",
    "sg:tags":[
        "unisex",
        "hairdresser"
    ],
    "wof:name":"The Salon",
    "wof:placetype":"venue"
},
  "geometry": {"coordinates":[-3.7774970531,50.2847824097],"type":"Point"}
}