{
  "type": "Feature",
  "properties": {
    "iso:country":"GB",
    "sg:address":"4 Ancliffe Lane, Bolton-le-sands",
    "sg:city":"Carnforth",
    "sg:classifiers":[
        {
            "category":"Professional",
            "type":"Services"
        },
        {
            "category":"Banks & Credit Unions",
            "subcategory":"Investment Brokerage",
            "type":"Services"
        }
    ],
    "sg:phone":"+44 1524 824302",
    "sg:postcode":"LA5 8DS",
    "sg:province":"Cumbria",
    "sg:tags":[
        "farm",
        "agricultural",
        "contractor"
    ],
    "wof:name":"M D Looker",
    "wof:placetype":"venue"
},
  "geometry": {"coordinates":[-2.785998106,54.0967750549],"type":"Point"}
}