{
  "type": "Feature",
  "properties": {
    "addr:full":"Unit 24 Park Farm Industrial Estate, Ermine Street Buntingford Hertfordshire SG9 9AZ",
    "addr:housenumber":"unit 24;estate",
    "addr:postcode":"sg9 9az",
    "addr:street":"Park Farm Industrial;Ermine Street",
    "iso:country":"GB",
    "sg:address":"Unit 24 Park Farm Industrial Estate, Ermine Street",
    "sg:city":"Buntingford",
    "sg:classifiers":[
        {
            "category":"Home & Garden",
            "subcategory":"Furniture",
            "type":"Retail Goods"
        }
    ],
    "sg:phone":"+44 1763 273326",
    "sg:postcode":"SG9 9AZ",
    "sg:province":"Hertfordshire",
    "wof:name":"A J Furniture",
    "wof:placetype":"venue"
},
  "geometry": {"coordinates":[-0.018635,51.946301],"type":"Point"}
}