{
  "type": "Feature",
  "properties": {
    "iso:country":"GB",
    "sg:address":"1 Coopers Heights, Wiveliscombe",
    "sg:city":"Taunton",
    "sg:classifiers":[
        {
            "category":"Building & Trades",
            "subcategory":"Construction",
            "type":"Services"
        }
    ],
    "sg:phone":"+44 1984 623830",
    "sg:postcode":"TA4 2YB",
    "sg:province":"Devon",
    "sg:tags":[
        "builder"
    ],
    "wof:name":"Aubrey Sandercock",
    "wof:placetype":"venue"
},
  "geometry": {"coordinates":[-3.3386819363,51.0336494446],"type":"Point"}
}