{
  "type": "Feature",
  "properties": {
    "iso:country":"GB",
    "sg:address":"293 Mossy Lea Rd",
    "sg:city":"Wigan",
    "sg:classifiers":[
        {
            "category":"Retail",
            "subcategory":"Driving School",
            "type":"Services"
        }
    ],
    "sg:phone":"+44 1257 422947",
    "sg:postcode":"WN6 9RN",
    "sg:province":"Lancashire",
    "wof:name":"Tony's School Of Motoring",
    "wof:placetype":"venue"
},
  "geometry": {"coordinates":[-2.702146,53.608833],"type":"Point"}
}