{
  "type": "Feature",
  "properties": {
    "iso:country":"GB",
    "sg:address":"24-28 Victoria Road",
    "sg:city":"Lytham St Annes",
    "sg:classifiers":[
        {
            "category":"Social Services",
            "subcategory":"Retirement Home",
            "type":"Services"
        }
    ],
    "sg:phone":"+44 1253 727114",
    "sg:postcode":"FY8 1LE",
    "sg:province":"Lancashire",
    "sg:tags":[
        "rest"
    ],
    "wof:name":"Westholme Home for the Elderly",
    "wof:placetype":"venue"
},
  "geometry": {"coordinates":[-3.021964,53.747871],"type":"Point"}
}