{
  "type": "Feature",
  "properties": {
    "iso:country":"GB",
    "sg:address":"Sanders Lodge Industrial Estate",
    "sg:city":"Rushden",
    "sg:classifiers":[
        {
            "category":"Shopping",
            "subcategory":"Stationery & Office Supplies",
            "type":"Retail Goods"
        }
    ],
    "sg:postcode":"NN10 6BQ",
    "sg:province":"Bedfordshire",
    "sg:tags":[
        "equipment"
    ],
    "wof:name":"E P S Office Furnishings",
    "wof:placetype":"venue"
},
  "geometry": {"coordinates":[-0.624204,52.296051],"type":"Point"}
}