{
  "type": "Feature",
  "properties": {
    "addr:full":"Conduit House, 5 Roberts Mews Orpington Kent BR6 0JP",
    "addr:housenumber":"5",
    "addr:postcode":"br6 0jp",
    "addr:street":"Roberts Mews",
    "iso:country":"GB",
    "sg:address":"Conduit House, 5 Roberts Mews",
    "sg:city":"Orpington",
    "sg:classifiers":[
        {
            "category":"Professional",
            "subcategory":"Engineering",
            "type":"Services"
        }
    ],
    "sg:phone":"+44 1689 877831",
    "sg:postcode":"BR6 0JP",
    "sg:province":"Kent",
    "sg:tags":[
        "consulting",
        "engineer"
    ],
    "wof:name":"Northerngate Holdings Ltd.",
    "wof:placetype":"venue"
},
  "geometry": {"coordinates":[0.099702,51.377167],"type":"Point"}
}