{
  "type": "Feature",
  "properties": {
    "iso:country":"GB",
    "sg:address":"55 St Johns Wood High Street",
    "sg:city":"London",
    "sg:classifiers":[
        {
            "category":"Food & Beverages",
            "subcategory":"Specialty",
            "type":"Retail Goods"
        }
    ],
    "sg:phone":"+44 20 7586 5494",
    "sg:postcode":"NW8 7NL",
    "sg:province":"Greater London",
    "sg:tags":[
        "product",
        "health"
    ],
    "wof:name":"Holland & Barrett",
    "wof:placetype":"venue"
},
  "geometry": {"coordinates":[-0.170886,51.533421],"type":"Point"}
}