{
  "type": "Feature",
  "properties": {
    "addr:full":"55 St Johns Wood High Street London Greater London NW8 7NL",
    "addr:housenumber":"55",
    "addr:postcode":"nw8 7nl",
    "addr:street":"St Johns Wood High Street",
    "iso:country":"GB",
    "sg:address":"55 St Johns Wood High Street",
    "sg:city":"London",
    "sg:classifiers":[
        {
            "category":"Food & Beverages",
            "subcategory":"Specialty",
            "type":"Retail Goods"
        }
    ],
    "sg:phone":"+44 20 7586 5494",
    "sg:postcode":"NW8 7NL",
    "sg:province":"Greater London",
    "sg:tags":[
        "product",
        "health"
    ],
    "wof:name":"Holland & Barrett",
    "wof:placetype":"venue"
},
  "geometry": {"coordinates":[-0.170886,51.533421],"type":"Point"}
}