{
  "type": "Feature",
  "properties": {
    "addr:full":"56 Church St Seaham Durham SR7 7HF",
    "addr:housenumber":"56",
    "addr:postcode":"sr7 7hf",
    "addr:street":"Church St",
    "iso:country":"GB",
    "sg:address":"56 Church St",
    "sg:city":"Seaham",
    "sg:classifiers":[
        {
            "category":"Manufacturing",
            "subcategory":"Tools & Machinery",
            "type":"Manufacturing & Wholesale Goods"
        }
    ],
    "sg:phone":"+44 191 581 3326",
    "sg:postcode":"SR7 7HF",
    "sg:province":"Durham",
    "sg:tags":[
        "society",
        "friendly"
    ],
    "wof:name":"Hays Insurance Services",
    "wof:placetype":"venue"
},
  "geometry": {"coordinates":[-1.331907,54.837219],"type":"Point"}
}