{
  "type": "Feature",
  "properties": {
    "iso:country":"GB",
    "sg:address":"50 Parsons Street",
    "sg:city":"Banbury",
    "sg:classifiers":[
        {
            "category":"Manufacturing",
            "subcategory":"Jewelry",
            "type":"Manufacturing & Wholesale Goods"
        }
    ],
    "sg:phone":"+44 1295 269210",
    "sg:postcode":"OX16 5NB",
    "sg:province":"Oxfordshire",
    "sg:tags":[
        "manufacture",
        "repair",
        "jewellery"
    ],
    "wof:name":"Watermans",
    "wof:placetype":"venue"
},
  "geometry": {"coordinates":[-1.3374209404,52.0623397827],"type":"Point"}
}