{
  "type": "Feature",
  "properties": {
    "addr:full":"104 Yorktown Rd Sandhurst Berkshire GU47 9BH",
    "addr:housenumber":"104",
    "addr:postcode":"gu47 9bh",
    "addr:street":"Yorktown Rd",
    "iso:country":"GB",
    "sg:address":"104 Yorktown Rd",
    "sg:city":"Sandhurst",
    "sg:classifiers":[
        {
            "category":"Professional",
            "type":"Services"
        }
    ],
    "sg:phone":"+44 1252 861999",
    "sg:postcode":"GU47 9BH",
    "sg:province":"Berkshire",
    "sg:tags":[
        "repair",
        "tech",
        "maintenance"
    ],
    "wof:name":"Computer Care Centre Ltd",
    "wof:placetype":"venue"
},
  "geometry": {"coordinates":[-0.7953950167,51.344871521],"type":"Point"}
}