{
  "type": "Feature",
  "properties": {
    "iso:country":"GB",
    "sg:address":"67 The Bridges",
    "sg:city":"Sunderland",
    "sg:classifiers":[
        {
            "category":"Communications",
            "type":"Services"
        }
    ],
    "sg:phone":"+44 191 514 7962",
    "sg:postcode":"SR1 3LE",
    "sg:province":"Tyne and Wear",
    "sg:tags":[
        "telecommunication"
    ],
    "wof:name":"The Link",
    "wof:placetype":"venue"
},
  "geometry": {"coordinates":[-1.444504,54.919304],"type":"Point"}
}