{
  "type": "Feature",
  "properties": {
    "addr:full":"Station Mill, Station Rd Keighley North Yorkshire BD20 6RY",
    "addr:postcode":"bd20 6ry",
    "addr:street":"Station Rd",
    "iso:country":"GB",
    "sg:address":"Station Mill, Station Rd",
    "sg:city":"Keighley",
    "sg:classifiers":[
        {
            "category":"Personal",
            "subcategory":"Skin Care",
            "type":"Services"
        }
    ],
    "sg:phone":"+44 1535 630006",
    "sg:postcode":"BD20 6RY",
    "sg:province":"North Yorkshire",
    "sg:tags":[
        "leather",
        "merchant"
    ],
    "wof:name":"J Wood",
    "wof:placetype":"venue"
},
  "geometry": {"coordinates":[-1.947549,53.896175],"type":"Point"}
}