{
  "type": "Feature",
  "properties": {
    "addr:full":"Glan Dwr, Waenfawr Caernarfon Gwynedd LL55 4SD",
    "addr:postcode":"ll55 4sd",
    "addr:street":"Glan;Waenfawr",
    "iso:country":"GB",
    "sg:address":"Glan Dwr, Waenfawr",
    "sg:city":"Caernarfon",
    "sg:classifiers":[
        {
            "category":"Professional",
            "subcategory":"Accounting & Tax Preparation",
            "type":"Services"
        }
    ],
    "sg:phone":"+44 1286 650334",
    "sg:postcode":"LL55 4SD",
    "sg:province":"Gwynedd",
    "sg:tags":[
        "accountant"
    ],
    "wof:name":"Alan George Pain",
    "wof:placetype":"venue"
},
  "geometry": {"coordinates":[-4.127646,53.119259],"type":"Point"}
}