{
  "type": "Feature",
  "properties": {
    "addr:full":"164 Brompton Rd Chelsea Greater London SW3 1HW",
    "addr:housenumber":"164",
    "addr:postcode":"sw3 1hw",
    "addr:street":"Brompton Rd",
    "iso:country":"GB",
    "sg:address":"164 Brompton Rd",
    "sg:city":"Chelsea",
    "sg:classifiers":[
        {
            "category":"Organizations",
            "subcategory":"Community Association",
            "type":"Services"
        }
    ],
    "sg:phone":"+44 20 7823 7555",
    "sg:postcode":"SW3 1HW",
    "sg:province":"Greater London",
    "sg:tags":[
        "relation",
        "public"
    ],
    "wof:name":"Sector Marketing",
    "wof:placetype":"venue"
},
  "geometry": {"coordinates":[-0.1605439931,51.5016937256],"type":"Point"}
}