{
  "type": "Feature",
  "properties": {
    "iso:country":"GB",
    "sg:address":"28 Ruby St",
    "sg:city":"Saltburn By The Sea",
    "sg:classifiers":[
        {
            "category":"Food & Beverages",
            "subcategory":"Meat & Fish",
            "type":"Retail Goods"
        }
    ],
    "sg:phone":"+44 1287 622333",
    "sg:postcode":"TS12 1EG",
    "sg:province":"North Yorkshire",
    "sg:tags":[
        "chip"
    ],
    "wof:name":"Odd Cod",
    "wof:placetype":"venue"
},
  "geometry": {"coordinates":[-0.976009,54.584873],"type":"Point"}
}