{
  "type": "Feature",
  "properties": {
    "addr:full":"Woodbury Quarries, Shelsley Beauchamp Worcester Herefordshire WR6 6RE",
    "addr:postcode":"wr6 6re",
    "iso:country":"GB",
    "sg:address":"Woodbury Quarries, Shelsley Beauchamp",
    "sg:city":"Worcester",
    "sg:classifiers":[
        {
            "category":"Home & Garden",
            "subcategory":"Garden Supply",
            "type":"Retail Goods"
        }
    ],
    "sg:phone":"+44 1886 812648",
    "sg:postcode":"WR6 6RE",
    "sg:province":"Herefordshire",
    "sg:tags":[
        "sand",
        "gravel"
    ],
    "wof:name":"Lafarge Aggregates Ltd.",
    "wof:placetype":"venue"
},
  "geometry": {"coordinates":[-2.4036140442,52.2730484009],"type":"Point"}
}