{
  "type": "Feature",
  "properties": {
    "iso:country":"GB",
    "sg:address":"142 Leeds Road",
    "sg:city":"Heckmondwike",
    "sg:classifiers":[
        {
            "category":"Autos & Motor Vehicles",
            "subcategory":"Auto Supplies",
            "type":"Retail Goods"
        }
    ],
    "sg:phone":"+44 1924 402615",
    "sg:postcode":"WF16 9DQ",
    "sg:province":"West Yorkshire",
    "sg:tags":[
        "tyre"
    ],
    "wof:name":"Tyre Market",
    "wof:placetype":"venue"
},
  "geometry": {"coordinates":[-1.6783289909,53.7161483765],"type":"Point"}
}