{
  "type": "Feature",
  "properties": {
    "iso:country":"GB",
    "sg:address":"3a Fore Street",
    "sg:city":"Chard",
    "sg:classifiers":[
        {
            "category":"Communications",
            "subcategory":"Newspaper",
            "type":"Services"
        }
    ],
    "sg:phone":"+44 1460 63442",
    "sg:postcode":"TA20 1PH",
    "sg:province":"Devon",
    "sg:tags":[
        "magazine"
    ],
    "wof:name":"Chard & Ilminster News",
    "wof:placetype":"venue"
},
  "geometry": {"coordinates":[-2.965632,50.872849],"type":"Point"}
}