{
  "type": "Feature",
  "properties": {
    "addr:full":"4 Stamford Street Ashton-under-lyne Greater Manchester OL5 0HR",
    "addr:housenumber":"4",
    "addr:postcode":"ol5 0hr",
    "addr:street":"Stamford Street",
    "iso:country":"GB",
    "sg:address":"4 Stamford Street",
    "sg:city":"Ashton-under-lyne",
    "sg:classifiers":[
        {
            "category":"Fast Food",
            "type":"Food & Drink"
        }
    ],
    "sg:phone":"+44 1457 832553",
    "sg:postcode":"OL5 0HR",
    "sg:province":"Greater Manchester",
    "sg:tags":[
        "away",
        "take"
    ],
    "wof:name":"Karens Cafe",
    "wof:placetype":"venue"
},
  "geometry": {"coordinates":[-2.046206,53.519215],"type":"Point"}
}