{
  "type": "Feature",
  "properties": {
    "iso:country":"GB",
    "sg:address":"294 Malling Rd",
    "sg:city":"Snodland",
    "sg:classifiers":[
        {
            "category":"Manufacturing",
            "subcategory":"Building Materials",
            "type":"Manufacturing & Wholesale Goods"
        }
    ],
    "sg:phone":"+44 1634 246103",
    "sg:postcode":"ME6 5JJ",
    "sg:province":"Kent",
    "sg:tags":[
        "merchant",
        "builder"
    ],
    "wof:name":"Britannia Building Centre",
    "wof:placetype":"venue"
},
  "geometry": {"coordinates":[0.436473,51.319714],"type":"Point"}
}