{
  "type": "Feature",
  "properties": {
    "iso:country":"GB",
    "sg:address":"36 Wellpark Clo",
    "sg:city":"Exeter",
    "sg:classifiers":[
        {
            "category":"Building & Trades",
            "subcategory":"Cleaning & Sanitation",
            "type":"Services"
        }
    ],
    "sg:phone":"+44 1392 413688",
    "sg:postcode":"EX4 1TS",
    "sg:province":"Devon",
    "sg:tags":[
        "commercial"
    ],
    "wof:name":"Prestige Cleaning Services",
    "wof:placetype":"venue"
},
  "geometry": {"coordinates":[-3.5514390469,50.7214927673],"type":"Point"}
}