{
  "type": "Feature",
  "properties": {
    "addr:full":"29 Ogilvie Street Dundee Dundee City DD4 6SE",
    "addr:housenumber":"29",
    "addr:postcode":"dd4 6se",
    "addr:street":"Ogilvie Street",
    "iso:country":"GB",
    "sg:address":"29 Ogilvie Street",
    "sg:city":"Dundee",
    "sg:classifiers":[
        {
            "category":"Food & Beverages",
            "subcategory":"Fruits & Vegetables",
            "type":"Retail Goods"
        },
        {
            "category":"Food & Beverages",
            "subcategory":"Groceries & Convenience Stores",
            "type":"Retail Goods"
        }
    ],
    "sg:phone":"+44 1382 459722",
    "sg:postcode":"DD4 6SE",
    "sg:province":"Dundee City",
    "sg:tags":[
        "greengrocer"
    ],
    "wof:name":"J Millan",
    "wof:placetype":"venue"
},
  "geometry": {"coordinates":[-2.962422,56.472111],"type":"Point"}
}