{
  "type": "Feature",
  "properties": {
    "addr:full":"Maes Y Llan Conwy Conwy LL32 8NB",
    "addr:postcode":"ll32 8nb",
    "addr:street":"Maes Y Llan",
    "iso:country":"GB",
    "sg:address":"Maes Y Llan",
    "sg:city":"Conwy",
    "sg:classifiers":[
        {
            "category":"Education",
            "subcategory":"School",
            "type":"Public Place"
        },
        {
            "category":"Government",
            "subcategory":"Office",
            "type":"Public Place"
        }
    ],
    "sg:postcode":"LL32 8NB",
    "sg:province":"Conwy",
    "sg:tags":[
        "local",
        "authority"
    ],
    "wof:name":"Babanod Gyffin Infant School",
    "wof:placetype":"venue"
},
  "geometry": {"coordinates":[-3.8329930305,53.2820358276],"type":"Point"}
}