{
  "type": "Feature",
  "properties": {
    "addr:full":"The Lane, Tebworth Leighton Buzzard Bedfordshire LU7 9QB",
    "addr:postcode":"lu7 9qb",
    "addr:street":"The Lane",
    "iso:country":"GB",
    "sg:address":"The Lane, Tebworth",
    "sg:city":"Leighton Buzzard",
    "sg:classifiers":[
        {
            "category":"Bars & Pubs",
            "type":"Food & Drink"
        }
    ],
    "sg:phone":"+44 1525 874101",
    "sg:postcode":"LU7 9QB",
    "sg:province":"Bedfordshire",
    "sg:tags":[
        "pubs",
        "inn"
    ],
    "wof:name":"The Queens Head",
    "wof:placetype":"venue"
},
  "geometry": {"coordinates":[-0.5684980154,51.9399337769],"type":"Point"}
}