{
  "type": "Feature",
  "properties": {
    "addr:full":"98 Pathfield Road London Greater London SW16 5NY",
    "addr:housenumber":"98",
    "addr:postcode":"sw16 5ny",
    "addr:street":"Pathfield Road",
    "iso:country":"GB",
    "sg:address":"98 Pathfield Road",
    "sg:city":"London",
    "sg:classifiers":[
        {
            "category":"Home & Garden",
            "subcategory":"Home Furnishings",
            "type":"Retail Goods"
        }
    ],
    "sg:phone":"+44 20 8664 6969",
    "sg:postcode":"SW16 5NY",
    "sg:province":"Greater London",
    "sg:tags":[
        "blind",
        "curtain",
        "fitting"
    ],
    "wof:name":"Folds Soft Furnishings",
    "wof:placetype":"venue"
},
  "geometry": {"coordinates":[-0.1330180019,51.4202079773],"type":"Point"}
}