{
  "type": "Feature",
  "properties": {
    "iso:country":"GB",
    "sg:address":"Woodend Farm, Owthorpe Road, Cotgrave",
    "sg:city":"Nottingham",
    "sg:classifiers":[
        {
            "category":"Building & Trades",
            "subcategory":"Construction",
            "type":"Services"
        }
    ],
    "sg:phone":"+44 115 989 9090",
    "sg:postcode":"NG12 3PU",
    "sg:province":"Nottinghamshire",
    "sg:tags":[
        "ceiling",
        "contractor"
    ],
    "wof:name":"Exclusive Partitions & Ceilings Ltd.",
    "wof:placetype":"venue"
},
  "geometry": {"coordinates":[-1.047477,52.909126],"type":"Point"}
}