{
  "type": "Feature",
  "properties": {
    "iso:country":"GB",
    "sg:address":"Teify Park Abattoir, Lampter Road",
    "sg:city":"Llanybydder",
    "sg:classifiers":[
        {
            "category":"Wholesale",
            "subcategory":"Meat",
            "type":"Manufacturing & Wholesale Goods"
        }
    ],
    "sg:phone":"+44 1570 480284",
    "sg:postcode":"SA40 9QE",
    "sg:province":"Carmarthenshire",
    "sg:tags":[
        "-"
    ],
    "wof:name":"Oriel Jones & Son Ltd.",
    "wof:placetype":"venue"
},
  "geometry": {"coordinates":[-4.1610860825,52.081993103],"type":"Point"}
}