{
  "type": "Feature",
  "properties": {
    "iso:country":"GB",
    "sg:address":"15 Ashford Avenue",
    "sg:city":"Ashford",
    "sg:classifiers":[
        {
            "category":"Building & Trades",
            "subcategory":"Construction",
            "type":"Services"
        }
    ],
    "sg:postcode":"TW15 2BB",
    "sg:province":"Greater London",
    "sg:tags":[
        "tiling",
        "contractor"
    ],
    "wof:name":"D Thomas",
    "wof:placetype":"venue"
},
  "geometry": {"coordinates":[-0.452991,51.426212],"type":"Point"}
}