{
  "type": "Feature",
  "properties": {
    "addr:full":"23 Court Street Newton Abbot Devon TQ13 8LG",
    "addr:housenumber":"23",
    "addr:postcode":"tq13 8lg",
    "addr:street":"Court Street",
    "iso:country":"GB",
    "sg:address":"23 Court Street",
    "sg:city":"Newton Abbot",
    "sg:classifiers":[
        {
            "category":"Home & Garden",
            "subcategory":"Building Materials",
            "type":"Retail Goods"
        }
    ],
    "sg:phone":"+44 1647 440891",
    "sg:postcode":"TQ13 8LG",
    "sg:province":"Devon",
    "sg:tags":[
        "fencing"
    ],
    "wof:name":"N B Lister",
    "wof:placetype":"venue"
},
  "geometry": {"coordinates":[-3.7675759792,50.6602554321],"type":"Point"}
}