{
  "type": "Feature",
  "properties": {
    "addr:full":"182 Northcote Road, Battersea London Greater London SW11 6RE",
    "addr:housenumber":"182",
    "addr:postcode":"sw11 6re",
    "addr:street":"Northcote Road",
    "iso:country":"GB",
    "sg:address":"182 Northcote Road, Battersea",
    "sg:city":"London",
    "sg:classifiers":[
        {
            "category":"Building & Trades",
            "subcategory":"Construction",
            "type":"Services"
        },
        {
            "category":"Home & Garden",
            "subcategory":"Kitchen Supply",
            "type":"Retail Goods"
        }
    ],
    "sg:phone":"+44 20 7228 4454",
    "sg:postcode":"SW11 6RE",
    "sg:province":"Greater London",
    "sg:tags":[
        "installers",
        "ware",
        "planner"
    ],
    "sg:website":"http://www.harveyjones.com",
    "wof:name":"Simple Kitchens Ltd",
    "wof:placetype":"venue"
},
  "geometry": {"coordinates":[-0.164031,51.453621],"type":"Point"}
}