{
  "type": "Feature",
  "properties": {
    "addr:full":"Wilditch Community Centre, Culvert Rd Battersea Greater London SW11 5BB",
    "addr:postcode":"sw11 5bb",
    "addr:street":"Culvert Rd",
    "iso:country":"GB",
    "sg:address":"Wilditch Community Centre, Culvert Rd",
    "sg:city":"Battersea",
    "sg:classifiers":[
        {
            "category":"Personal",
            "type":"Services"
        }
    ],
    "sg:phone":"+44 20 8265 9131",
    "sg:postcode":"SW11 5BB",
    "sg:province":"Greater London",
    "sg:tags":[
        "slimming",
        "product"
    ],
    "wof:name":"Slimming World",
    "wof:placetype":"venue"
},
  "geometry": {"coordinates":[-0.1628389955,51.467464447],"type":"Point"}
}