{
  "type": "Feature",
  "properties": {
    "addr:full":"114 Montgomery St Irvine North Ayrshire KA12 8PW",
    "addr:housenumber":"114",
    "addr:postcode":"ka12 8pw",
    "addr:street":"Montgomery St",
    "iso:country":"GB",
    "sg:address":"114 Montgomery St",
    "sg:city":"Irvine",
    "sg:classifiers":[
        {
            "category":"Taxi",
            "type":"Transportation"
        }
    ],
    "sg:phone":"+44 1294 278910",
    "sg:postcode":"KA12 8PW",
    "sg:province":"North Ayrshire",
    "sg:tags":[
        "mini",
        "cab"
    ],
    "wof:name":"Irvine Taxi Owners Association",
    "wof:placetype":"venue"
},
  "geometry": {"coordinates":[-4.677669,55.610477],"type":"Point"}
}