{
  "type": "Feature",
  "properties": {
    "addr:full":"Moorland Road St Austell Cornwall PL25 5BS",
    "addr:postcode":"pl25 5bs",
    "addr:street":"Moorland Road",
    "iso:country":"GB",
    "sg:address":"Moorland Road",
    "sg:city":"St Austell",
    "sg:classifiers":[
        {
            "category":"Food & Beverages",
            "subcategory":"Supermarket",
            "type":"Retail Goods"
        }
    ],
    "sg:phone":"+44 1726 65601",
    "sg:postcode":"PL25 5BS",
    "sg:province":"Cornwall",
    "wof:name":"Co-Operative Group (C W S) Ltd.",
    "wof:placetype":"venue"
},
  "geometry": {"coordinates":[-4.795835,50.336163],"type":"Point"}
}