{
  "type": "Feature",
  "properties": {
    "addr:full":"220 Park View Whitley Bay Northumberland NE26 3QR",
    "addr:housenumber":"220",
    "addr:postcode":"ne26 3qr",
    "addr:street":"Park View",
    "iso:country":"GB",
    "sg:address":"220 Park View",
    "sg:city":"Whitley Bay",
    "sg:classifiers":[
        {
            "category":"Organizations",
            "subcategory":"Membership Organization",
            "type":"Services"
        }
    ],
    "sg:postcode":"NE26 3QR",
    "sg:province":"Northumberland",
    "sg:tags":[
        "club"
    ],
    "wof:name":"Rodney Court (Whitley Bay) Management Co",
    "wof:placetype":"venue"
},
  "geometry": {"coordinates":[-1.451683,55.045055],"type":"Point"}
}