{
  "type": "Feature",
  "properties": {
    "iso:country":"GB",
    "sg:address":"8 Turner Street",
    "sg:city":"Ramsgate",
    "sg:classifiers":[
        {
            "category":"Retail",
            "subcategory":"Laundry & Dry Cleaning",
            "type":"Services"
        },
        {
            "category":"Retail",
            "subcategory":"Repair Shop",
            "type":"Services"
        }
    ],
    "sg:phone":"+44 1843 587730",
    "sg:postcode":"CT11 8NG",
    "sg:province":"Kent",
    "sg:tags":[
        "clothing",
        "alteration"
    ],
    "wof:name":"Jan'z Workshop",
    "wof:placetype":"venue"
},
  "geometry": {"coordinates":[1.4193840027,51.3342056274],"type":"Point"}
}