{
  "type": "Feature",
  "properties": {
    "addr:full":"410 Nuthall Road Nottingham Nottinghamshire NG8 5DS",
    "addr:housenumber":"410",
    "addr:postcode":"ng8 5ds",
    "addr:street":"Nuthall Road",
    "iso:country":"GB",
    "sg:address":"410 Nuthall Road",
    "sg:city":"Nottingham",
    "sg:classifiers":[
        {
            "category":"Banks & Credit Unions",
            "subcategory":"Financial Services",
            "type":"Services"
        }
    ],
    "sg:phone":"+44 115 970 4287",
    "sg:postcode":"NG8 5DS",
    "sg:province":"Nottinghamshire",
    "sg:tags":[
        "building",
        "society"
    ],
    "wof:name":"The Nottingham Building Society",
    "wof:placetype":"venue"
},
  "geometry": {"coordinates":[-1.190157,52.977356],"type":"Point"}
}