{
  "type": "Feature",
  "properties": {
    "addr:full":"10 Fenchurch Avenue Monument Greater London EC3M 5BN",
    "addr:housenumber":"10",
    "addr:postcode":"ec3m 5bn",
    "addr:street":"Fenchurch Avenue",
    "iso:country":"GB",
    "sg:address":"10 Fenchurch Avenue",
    "sg:city":"Monument",
    "sg:classifiers":[
        {
            "category":"Conference Center",
            "type":"Public Place"
        }
    ],
    "sg:phone":"+44 20 7663 5600",
    "sg:postcode":"EC3M 5BN",
    "sg:province":"Greater London",
    "sg:tags":[
        "business",
        "centre"
    ],
    "wof:name":"HQ Business Centres",
    "wof:placetype":"venue"
},
  "geometry": {"coordinates":[-0.081175,51.512482],"type":"Point"}
}