{
  "type": "Feature",
  "properties": {
    "iso:country":"GB",
    "sg:address":"School Road, Yardley Wood",
    "sg:city":"Birmingham",
    "sg:classifiers":[
        {
            "category":"Government",
            "subcategory":"Office",
            "type":"Public Place"
        }
    ],
    "sg:phone":"+44 121 474 2456",
    "sg:postcode":"B14 4ER",
    "sg:province":"West Midlands",
    "sg:tags":[
        "local"
    ],
    "wof:name":"Yardley Wood Junior & Infant School",
    "wof:placetype":"venue"
},
  "geometry": {"coordinates":[-1.868831,52.412399],"type":"Point"}
}