{
  "type": "Feature",
  "properties": {
    "iso:country":"GB",
    "sg:address":"65 Bloomfield Rd, Plumstead",
    "sg:city":"London",
    "sg:classifiers":[
        {
            "category":"Recreation",
            "subcategory":"Fishing",
            "type":"Entertainment"
        }
    ],
    "sg:postcode":"SE18 7JJ",
    "sg:province":"Greater London",
    "sg:tags":[
        "angling"
    ],
    "wof:name":"French,M J W,",
    "wof:placetype":"venue"
},
  "geometry": {"coordinates":[0.071172,51.484356],"type":"Point"}
}