{
  "type": "Feature",
  "properties": {
    "addr:full":"168 Wroxham Road, Sprowston Norwich Norfolk NR7 8DE",
    "addr:housenumber":"168",
    "addr:postcode":"nr7 8de",
    "addr:street":"Wroxham Road;Norwich Norfolk",
    "iso:country":"GB",
    "sg:address":"168 Wroxham Road, Sprowston",
    "sg:city":"Norwich",
    "sg:classifiers":[
        {
            "category":"Food & Beverages",
            "subcategory":"Liquor & Beverages",
            "type":"Retail Goods"
        }
    ],
    "sg:phone":"+44 1603 415115",
    "sg:postcode":"NR7 8DE",
    "sg:province":"Norfolk",
    "sg:tags":[
        "beer",
        "spirit",
        "wines"
    ],
    "wof:name":"Hall Batson & Co. Ltd.",
    "wof:placetype":"venue"
},
  "geometry": {"coordinates":[1.3263670206,52.6588630676],"type":"Point"}
}