{
  "type": "Feature",
  "properties": {
    "addr:full":"13-15 Renshaw St Liverpool Merseyside L1 2SA",
    "addr:housenumber":"13-15",
    "addr:postcode":"l1 2sa",
    "addr:street":"Renshaw St",
    "iso:country":"GB",
    "sg:address":"13-15 Renshaw St",
    "sg:city":"Liverpool",
    "sg:classifiers":[
        {
            "category":"Restaurant",
            "type":"Food & Drink"
        }
    ],
    "sg:phone":"+44 151 709 5059",
    "sg:postcode":"L1 2SA",
    "sg:province":"Merseyside",
    "sg:tags":[
        "american"
    ],
    "wof:name":"Uncle Sam's Bistro",
    "wof:placetype":"venue"
},
  "geometry": {"coordinates":[-2.977077961,53.4040031433],"type":"Point"}
}