{
  "type": "Feature",
  "properties": {
    "addr:full":"Mindale House, Hendre Road Prestatyn Denbighshire LL19 8PG",
    "addr:postcode":"ll19 8pg",
    "addr:street":"Hendre Road",
    "iso:country":"GB",
    "sg:address":"Mindale House, Hendre Road",
    "sg:city":"Prestatyn",
    "sg:classifiers":[
        {
            "category":"Professional",
            "subcategory":"Management & Consulting",
            "type":"Services"
        }
    ],
    "sg:phone":"+44 1745 851111",
    "sg:postcode":"LL19 8PG",
    "sg:province":"Denbighshire",
    "sg:tags":[
        "consultant",
        "business"
    ],
    "wof:name":"Warren Ward Associates",
    "wof:placetype":"venue"
},
  "geometry": {"coordinates":[-3.4005279541,53.3313751221],"type":"Point"}
}