{
  "type": "Feature",
  "properties": {
    "iso:country":"GB",
    "sg:address":"34 Kilpatrick View",
    "sg:city":"Dumbarton",
    "sg:classifiers":[
        {
            "category":"Freight",
            "type":"Transportation"
        }
    ],
    "sg:postcode":"G82 2ED",
    "sg:province":"Argyll and Bute",
    "sg:tags":[
        "haulage",
        "road"
    ],
    "wof:name":"Walker,David A,",
    "wof:placetype":"venue"
},
  "geometry": {"coordinates":[-4.5531759262,55.9505348206],"type":"Point"}
}