{
  "type": "Feature",
  "properties": {
    "addr:full":"189 Lavender Hill London Greater London SW11 5TB",
    "addr:housenumber":"189",
    "addr:postcode":"sw11 5tb",
    "addr:street":"Lavender Hill",
    "iso:country":"GB",
    "sg:address":"189 Lavender Hill",
    "sg:city":"London",
    "sg:classifiers":[
        {
            "category":"Professional",
            "subcategory":"Accounting & Tax Preparation",
            "type":"Services"
        }
    ],
    "sg:phone":"+44 20 7223 8221",
    "sg:postcode":"SW11 5TB",
    "sg:province":"Greater London",
    "sg:tags":[
        "accountant"
    ],
    "wof:name":"Shaheen Accountancy Services Ltd.",
    "wof:placetype":"venue"
},
  "geometry": {"coordinates":[-0.1602369994,51.464679718],"type":"Point"}
}