{
  "type": "Feature",
  "properties": {
    "addr:full":"1244 Melton Rd, Syston Leicester Leicestershire LE7 2HB",
    "addr:housenumber":"1244",
    "addr:postcode":"le7 2hb",
    "addr:street":"Melton Rd",
    "iso:country":"GB",
    "sg:address":"1244 Melton Rd, Syston",
    "sg:city":"Leicester",
    "sg:classifiers":[
        {
            "category":"Shopping",
            "subcategory":"News",
            "type":"Retail Goods"
        }
    ],
    "sg:postcode":"LE7 2HB",
    "sg:province":"Leicestershire",
    "sg:tags":[
        "newsagent"
    ],
    "wof:name":"Mercury News Shops",
    "wof:placetype":"venue"
},
  "geometry": {"coordinates":[-1.0753190517,52.6975479126],"type":"Point"}
}