{
  "type": "Feature",
  "properties": {
    "addr:full":"Gosford Street Coventry West Midlands CV1 5DL",
    "addr:postcode":"cv1 5dl",
    "addr:street":"Gosford Street",
    "iso:country":"GB",
    "sg:address":"Gosford Street",
    "sg:city":"Coventry",
    "sg:classifiers":[
        {
            "category":"Bars & Pubs",
            "type":"Food & Drink"
        }
    ],
    "sg:postcode":"CV1 5DL",
    "sg:province":"West Midlands",
    "sg:tags":[
        "pubs",
        "inn"
    ],
    "wof:name":"M Edwards",
    "wof:placetype":"venue"
},
  "geometry": {"coordinates":[-1.500868,52.406746],"type":"Point"}
}