{
  "type": "Feature",
  "properties": {
    "addr:full":"The Centre, Rawtenstall Rossendale Lancashire BB4 7QQ",
    "addr:postcode":"bb4 7qq",
    "addr:street":"Rawtenstall",
    "iso:country":"GB",
    "sg:address":"The Centre, Rawtenstall",
    "sg:city":"Rossendale",
    "sg:classifiers":[
        {
            "category":"Government",
            "subcategory":"City Hall",
            "type":"Public Place"
        }
    ],
    "sg:phone":"+44 1706 216965",
    "sg:postcode":"BB4 7QQ",
    "sg:province":"Lancashire",
    "wof:name":"New Astoria Ballroom",
    "wof:placetype":"venue"
},
  "geometry": {"coordinates":[-2.2798690796,53.7003707886],"type":"Point"}
}