{
  "type": "Feature",
  "properties": {
    "addr:full":"22 Churchill Road, Boscombe Bournemouth Dorset BH1 4ES",
    "addr:housenumber":"22",
    "addr:postcode":"bh1 4es",
    "addr:street":"Churchill Road",
    "iso:country":"GB",
    "sg:address":"22 Churchill Road, Boscombe",
    "sg:city":"Bournemouth",
    "sg:classifiers":[
        {
            "category":"Retail",
            "subcategory":"Storage",
            "type":"Services"
        }
    ],
    "sg:postcode":"BH1 4ES",
    "sg:province":"Dorset",
    "sg:tags":[
        "household",
        "removal"
    ],
    "wof:name":"Ralph Grundy Ltd.",
    "wof:placetype":"venue"
},
  "geometry": {"coordinates":[-1.8446329832,50.7298431396],"type":"Point"}
}