{
  "type": "Feature",
  "properties": {
    "iso:country":"GB",
    "sg:address":"40 High Street",
    "sg:city":"Malmesbury",
    "sg:classifiers":[
        {
            "category":"Retail",
            "subcategory":"Laundry & Dry Cleaning",
            "type":"Services"
        }
    ],
    "sg:phone":"+44 1666 825186",
    "sg:postcode":"SN16 9AA",
    "sg:province":"Wiltshire",
    "sg:tags":[
        "alteration"
    ],
    "wof:name":"West County Cleaners",
    "wof:placetype":"venue"
},
  "geometry": {"coordinates":[-2.097285,51.582397],"type":"Point"}
}