{
  "type": "Feature",
  "properties": {
    "addr:full":"26 Vivian Avenue London Greater London NW4 3XP",
    "addr:housenumber":"26",
    "addr:postcode":"nw4 3xp",
    "addr:street":"Vivian Avenue",
    "iso:country":"GB",
    "sg:address":"26 Vivian Avenue",
    "sg:city":"London",
    "sg:classifiers":[
        {
            "category":"Food & Beverages",
            "subcategory":"Meat & Fish",
            "type":"Retail Goods"
        }
    ],
    "sg:phone":"+44 20 8202 9580",
    "sg:postcode":"NW4 3XP",
    "sg:province":"Greater London",
    "sg:tags":[
        "butcher"
    ],
    "wof:name":"Hendon Halal Butchers",
    "wof:placetype":"venue"
},
  "geometry": {"coordinates":[-0.2290579975,51.5827064514],"type":"Point"}
}