{
  "type": "Feature",
  "properties": {
    "iso:country":"GB",
    "sg:address":"Unit 6 Ymca Buildings, North Road",
    "sg:city":"St Helens",
    "sg:classifiers":[
        {
            "category":"Health Services",
            "subcategory":"Podiatrist",
            "type":"Services"
        }
    ],
    "sg:phone":"+44 1744 23392",
    "sg:postcode":"WA10 2TZ",
    "sg:province":"Merseyside",
    "sg:tags":[
        "podiatrists",
        "chiropodist"
    ],
    "wof:name":"A & H Chiropody Surgery & Sports Clinic",
    "wof:placetype":"venue"
},
  "geometry": {"coordinates":[-2.738868,53.451687],"type":"Point"}
}