{
  "type": "Feature",
  "properties": {
    "addr:full":"Cleveland Terrace Dental Practice, 8 Cleveland Terrace Darlington Durham DL3 7HA",
    "addr:housenumber":"8",
    "addr:postcode":"dl3 7ha",
    "addr:street":"Cleveland;Cleveland Terrace",
    "iso:country":"GB",
    "sg:address":"Cleveland Terrace Dental Practice, 8 Cleveland Terrace",
    "sg:city":"Darlington",
    "sg:classifiers":[
        {
            "category":"Health Services",
            "subcategory":"Dentist",
            "type":"Services"
        }
    ],
    "sg:phone":"+44 1325 464169",
    "sg:postcode":"DL3 7HA",
    "sg:province":"Durham",
    "wof:name":"CLEVELAND TERRACE DENTAL PRACTICE",
    "wof:placetype":"venue"
},
  "geometry": {"coordinates":[-1.5642410517,54.5221061707],"type":"Point"}
}