{
  "type": "Feature",
  "properties": {
    "addr:full":"The Swineshead Medical Group, The Surgery, Church La Boston Lincolnshire PE20 3JA",
    "addr:postcode":"pe20 3ja",
    "addr:street":"La Boston",
    "iso:country":"GB",
    "sg:address":"The Swineshead Medical Group, The Surgery, Church La",
    "sg:city":"Boston",
    "sg:classifiers":[
        {
            "category":"Health Services",
            "subcategory":"Doctor",
            "type":"Services"
        }
    ],
    "sg:phone":"+44 1205 820204",
    "sg:postcode":"PE20 3JA",
    "sg:province":"Lincolnshire",
    "sg:tags":[
        "practitioners"
    ],
    "wof:name":"Mann, A L",
    "wof:placetype":"venue"
},
  "geometry": {"coordinates":[-0.1559219956,52.9412841797],"type":"Point"}
}