{
  "type": "Feature",
  "properties": {
    "iso:country":"GB",
    "sg:address":"13a Cobham Terr, Bean Rd",
    "sg:city":"Greenhithe",
    "sg:classifiers":[
        {
            "category":"Transit Center",
            "subcategory":"Passenger",
            "type":"Transportation"
        }
    ],
    "sg:phone":"+44 1322 386565",
    "sg:postcode":"DA9 9HZ",
    "sg:province":"Kent",
    "sg:tags":[
        "airport"
    ],
    "wof:name":"B & J Airport Cars & Mini Bus",
    "wof:placetype":"venue"
},
  "geometry": {"coordinates":[0.280226,51.4482],"type":"Point"}
}