{
  "type": "Feature",
  "properties": {
    "iso:country":"GB",
    "sg:address":"Longleat Square",
    "sg:city":"Warminster",
    "sg:classifiers":[
        {
            "category":"Home & Garden",
            "subcategory":"Garden Supply",
            "type":"Retail Goods"
        }
    ],
    "sg:phone":"+44 1985 844432",
    "sg:postcode":"BA12 7NW",
    "sg:province":"Somerset",
    "sg:tags":[
        "nursery",
        "centre"
    ],
    "wof:name":"The Garden Shop",
    "wof:placetype":"venue"
},
  "geometry": {"coordinates":[-2.278118,51.194511],"type":"Point"}
}