{
  "type": "Feature",
  "properties": {
    "addr:full":"New England House, Unit 4-7, Sandridge Park St Albans Hertfordshire AL3 6PH",
    "addr:housenumber":"unit 4-7",
    "addr:postcode":"al3 6ph",
    "addr:street":"Park",
    "iso:country":"GB",
    "sg:address":"New England House, Unit 4-7, Sandridge Park",
    "sg:city":"St Albans",
    "sg:classifiers":[
        {
            "category":"Wholesale",
            "subcategory":"Medical Equipment & Supplies",
            "type":"Manufacturing & Wholesale Goods"
        }
    ],
    "sg:phone":"+44 1727 831666",
    "sg:postcode":"AL3 6PH",
    "sg:province":"Hertfordshire",
    "sg:tags":[
        "hospital"
    ],
    "wof:name":"Boston Scientific Ltd.",
    "wof:placetype":"venue"
},
  "geometry": {"coordinates":[-0.323849,51.772919],"type":"Point"}
}