{
  "type": "Feature",
  "properties": {
    "addr:full":"65a Hill Road Clevedon Somerset BS21 7PD",
    "addr:housenumber":"65a",
    "addr:postcode":"bs21 7pd",
    "addr:street":"Hill Road",
    "iso:country":"GB",
    "sg:address":"65a Hill Road",
    "sg:city":"Clevedon",
    "sg:classifiers":[
        {
            "category":"Shopping",
            "subcategory":"Antiques",
            "type":"Retail Goods"
        }
    ],
    "sg:postcode":"BS21 7PD",
    "sg:province":"Somerset",
    "wof:name":"Nostalgia",
    "wof:placetype":"venue"
},
  "geometry": {"coordinates":[-2.8571910858,51.4430160522],"type":"Point"}
}