{
  "type": "Feature",
  "properties": {
    "addr:full":"3 Central Avenue, Syston Leicester Leicestershire LE7 2EF",
    "addr:housenumber":"3",
    "addr:postcode":"le7 2ef",
    "addr:street":"Central Avenue",
    "iso:country":"GB",
    "sg:address":"3 Central Avenue, Syston",
    "sg:city":"Leicester",
    "sg:classifiers":[
        {
            "category":"Parking",
            "type":"Transportation"
        }
    ],
    "sg:postcode":"LE7 2EF",
    "sg:province":"Leicestershire",
    "sg:tags":[
        "car",
        "valet"
    ],
    "wof:name":"Central Valeting Services",
    "wof:placetype":"venue"
},
  "geometry": {"coordinates":[-1.069767952,52.6998901367],"type":"Point"}
}