{
  "type": "Feature",
  "properties": {
    "addr:full":"St. Annes House, Lees Hall Rd Dewsbury West Yorkshire WF12 9HB",
    "addr:postcode":"wf12 9hb",
    "addr:street":"St.;Lees Hall Rd",
    "iso:country":"GB",
    "sg:address":"St. Annes House, Lees Hall Rd",
    "sg:city":"Dewsbury",
    "sg:classifiers":[
        {
            "category":"Building & Trades",
            "subcategory":"Construction",
            "type":"Services"
        }
    ],
    "sg:phone":"+44 1924 450008",
    "sg:postcode":"WF12 9HB",
    "sg:province":"West Yorkshire",
    "sg:tags":[
        "joinery"
    ],
    "wof:name":"Metalwork Steel Fencing",
    "wof:placetype":"venue"
},
  "geometry": {"coordinates":[-1.647873,53.6749],"type":"Point"}
}