{
  "type": "Feature",
  "properties": {
    "addr:full":", Kimpton Andover Andover Hampshire SP11 8NT",
    "addr:housenumber":"kimpton",
    "addr:postcode":"sp11 8nt",
    "addr:street":"Andover Andover Hampshire",
    "iso:country":"GB",
    "sg:address":", Kimpton Andover",
    "sg:city":"Andover",
    "sg:classifiers":[
        {
            "category":"Education",
            "subcategory":"School",
            "type":"Public Place"
        }
    ],
    "sg:phone":"+44 1264 772297",
    "sg:postcode":"SP11 8NT",
    "sg:province":"Hampshire",
    "sg:tags":[
        "local",
        "authority"
    ],
    "wof:name":"Kimpton Primary School",
    "wof:placetype":"venue"
},
  "geometry": {"coordinates":[-1.5975110531,51.2191238403],"type":"Point"}
}