{
  "type": "Feature",
  "properties": {
    "addr:full":"23 Wimborne Avenue Redhill Surrey RH1 5AQ",
    "addr:housenumber":"23",
    "addr:postcode":"rh1 5aq",
    "addr:street":"Wimborne Avenue",
    "iso:country":"GB",
    "sg:address":"23 Wimborne Avenue",
    "sg:city":"Redhill",
    "sg:classifiers":[
        {
            "category":"Building & Trades",
            "subcategory":"Cleaning & Sanitation",
            "type":"Services"
        }
    ],
    "sg:phone":"+44 1737 772603",
    "sg:postcode":"RH1 5AQ",
    "sg:province":"Surrey",
    "sg:tags":[
        "commercial"
    ],
    "wof:name":"Chris Sargent Cleaning Services",
    "wof:placetype":"venue"
},
  "geometry": {"coordinates":[-0.168234,51.215252],"type":"Point"}
}