{
  "type": "Feature",
  "properties": {
    "iso:country":"GB",
    "sg:address":"T A Centre, Sherwood Av",
    "sg:city":"Newark",
    "sg:classifiers":[
        {
            "category":"Community Center",
            "subcategory":"Youth",
            "type":"Public Place"
        }
    ],
    "sg:phone":"+44 1636 640974",
    "sg:postcode":"NG24 1QF",
    "sg:province":"Nottinghamshire",
    "sg:tags":[
        "organisation",
        "centre"
    ],
    "wof:name":"Sea Cadet Core Newark Unit The",
    "wof:placetype":"venue"
},
  "geometry": {"coordinates":[-0.809347,53.073895],"type":"Point"}
}