{
  "type": "Feature",
  "properties": {
    "iso:country":"GB",
    "sg:address":"Westfield Park, Scotstown Rd",
    "sg:city":"Aberdeen",
    "sg:classifiers":[
        {
            "category":"Community Center",
            "subcategory":"Youth",
            "type":"Public Place"
        }
    ],
    "sg:phone":"+44 1224 705508",
    "sg:postcode":"AB22 8HH",
    "sg:province":"Aberdeen City",
    "sg:tags":[
        "organisation",
        "centre"
    ],
    "wof:name":"46th Scout Group",
    "wof:placetype":"venue"
},
  "geometry": {"coordinates":[-2.0996,57.18092],"type":"Point"}
}