{
  "type": "Feature",
  "properties": {
    "addr:full":"137 Kirkdale, Sydenham London Greater London SE26 4QJ",
    "addr:housenumber":"137",
    "addr:postcode":"se26 4qj",
    "addr:street":"Kirkdale Sydenham",
    "iso:country":"GB",
    "sg:address":"137 Kirkdale, Sydenham",
    "sg:city":"London",
    "sg:classifiers":[
        {
            "category":"Shopping",
            "subcategory":"Computers & Home Electronics",
            "type":"Retail Goods"
        }
    ],
    "sg:phone":"+44 20 8699 8885",
    "sg:postcode":"SE26 4QJ",
    "sg:province":"Greater London",
    "sg:tags":[
        "equipment",
        "audio-visual"
    ],
    "wof:name":"Intimidation Ltd",
    "wof:placetype":"venue"
},
  "geometry": {"coordinates":[-0.0599719994,51.4314651489],"type":"Point"}
}