{
  "type": "Feature",
  "properties": {
    "addr:full":"Po Box 7 Cheadle Cheshire SK8 3BY",
    "addr:housenumber":"po;7 cheadle",
    "addr:postcode":"sk8 3by",
    "addr:street":"Box",
    "iso:country":"GB",
    "sg:address":"Po Box 7",
    "sg:city":"Cheadle",
    "sg:classifiers":[
        {
            "category":"Education",
            "subcategory":"Special Training",
            "type":"Public Place"
        }
    ],
    "sg:phone":"+44 161 437 4235",
    "sg:postcode":"SK8 3BY",
    "sg:province":"Cheshire",
    "sg:tags":[
        "product",
        "centre"
    ],
    "wof:name":"The College of Technical Authorship",
    "wof:placetype":"venue"
},
  "geometry": {"coordinates":[-2.216784,53.370865],"type":"Point"}
}