{
  "type": "Feature",
  "properties": {
    "iso:country":"GB",
    "sg:address":"Meikle Pinminnoch Farm, Portpatrick",
    "sg:city":"Stranraer",
    "sg:classifiers":[
        {
            "category":"Farming",
            "subcategory":"Dairy Farm",
            "type":"Manufacturing & Wholesale Goods"
        },
        {
            "category":"Food & Beverages",
            "subcategory":"Groceries & Convenience Stores",
            "type":"Retail Goods"
        }
    ],
    "sg:phone":"+44 1776 810264",
    "sg:postcode":"DG9 9AB",
    "sg:province":"Dumfries and Galloway",
    "wof:name":"Thomas Law",
    "wof:placetype":"venue"
},
  "geometry": {"coordinates":[-5.016444,54.905636],"type":"Point"}
}