{
  "type": "Feature",
  "properties": {
    "addr:full":"Fishers Green Lane, Holyfield Waltham Abbey Essex EN9 2ED",
    "addr:postcode":"en9 2ed",
    "addr:street":"Fishers Green Lane Holyfield;Abbey",
    "iso:country":"GB",
    "sg:address":"Fishers Green Lane, Holyfield",
    "sg:city":"Waltham Abbey",
    "sg:classifiers":[
        {
            "category":"Recreation",
            "subcategory":"Fishing",
            "type":"Entertainment"
        }
    ],
    "sg:phone":"+44 1992 768012",
    "sg:postcode":"EN9 2ED",
    "sg:province":"Essex",
    "sg:tags":[
        "angling"
    ],
    "wof:name":"Holyfield Fishery",
    "wof:placetype":"venue"
},
  "geometry": {"coordinates":[-0.0064559998,51.7055282593],"type":"Point"}
}