{
  "type": "Feature",
  "properties": {
    "addr:full":"Clarence Street Portsmouth Hampshire PO1 4BA",
    "addr:postcode":"hampshire po1 4ba",
    "addr:street":"Clarence Street",
    "iso:country":"GB",
    "sg:address":"Clarence Street",
    "sg:city":"Portsmouth",
    "sg:classifiers":[
        {
            "category":"Arena",
            "subcategory":"Sports Club",
            "type":"Entertainment"
        }
    ],
    "sg:phone":"+44 23 9282 4097",
    "sg:postcode":"PO1 4BA",
    "sg:province":"Hampshire",
    "wof:name":"Pitt Street Gymnastic Centre",
    "wof:placetype":"venue"
},
  "geometry": {"coordinates":[-1.089479,50.803684],"type":"Point"}
}