{
  "type": "Feature",
  "properties": {
    "iso:country":"GB",
    "sg:address":"3 Hampton Place",
    "sg:city":"Brighton",
    "sg:classifiers":[
        {
            "category":"Restaurant",
            "type":"Food & Drink"
        }
    ],
    "sg:phone":"+44 1273 777399",
    "sg:postcode":"BN1 3DA",
    "sg:province":"East Sussex",
    "sg:tags":[
        "french"
    ],
    "wof:name":"Le Gastronome",
    "wof:placetype":"venue"
},
  "geometry": {"coordinates":[-0.1508350074,50.8249282837],"type":"Point"}
}