{
  "type": "Feature",
  "properties": {
    "addr:full":"131 Stainbeck Lane Leeds West Yorkshire LS7 2EB",
    "addr:housenumber":"131",
    "addr:postcode":"yorkshire ls7 2eb",
    "addr:street":"Stainbeck Lane",
    "iso:country":"GB",
    "sg:address":"131 Stainbeck Lane",
    "sg:city":"Leeds",
    "sg:classifiers":[
        {
            "category":"Building & Trades",
            "subcategory":"Plumbing",
            "type":"Services"
        }
    ],
    "sg:phone":"+44 113 260 4304",
    "sg:postcode":"LS7 2EB",
    "sg:province":"West Yorkshire",
    "sg:tags":[
        "heating"
    ],
    "wof:name":"Meanwood Plumbing & Heating Services",
    "wof:placetype":"venue"
},
  "geometry": {"coordinates":[-1.548195,53.828678],"type":"Point"}
}