{
  "type": "Feature",
  "properties": {
    "addr:full":"Shenstone, Beechwood Gro Halifax West Yorkshire HX2 9BY",
    "addr:postcode":"hx2 9by",
    "addr:street":"Gro;West",
    "iso:country":"GB",
    "sg:address":"Shenstone, Beechwood Gro",
    "sg:city":"Halifax",
    "sg:classifiers":[
        {
            "category":"Building & Trades",
            "subcategory":"Construction",
            "type":"Services"
        }
    ],
    "sg:phone":"+44 1422 244251",
    "sg:postcode":"HX2 9BY",
    "sg:province":"West Yorkshire",
    "sg:tags":[
        "contractor",
        "paving",
        "driveway"
    ],
    "wof:name":"Expansion Driveways",
    "wof:placetype":"venue"
},
  "geometry": {"coordinates":[-1.88258,53.746849],"type":"Point"}
}