{
  "type": "Feature",
  "properties": {
    "iso:country":"GB",
    "sg:address":"2 Priory Road",
    "sg:city":"Milford Haven",
    "sg:classifiers":[
        {
            "category":"Home & Garden",
            "subcategory":"Household Appliances",
            "type":"Retail Goods"
        }
    ],
    "sg:postcode":"SA73 2DS",
    "sg:province":"Pembrokeshire",
    "sg:tags":[
        "electrical",
        "domestic"
    ],
    "wof:name":"Peter Jones",
    "wof:placetype":"venue"
},
  "geometry": {"coordinates":[-5.03566,51.713703],"type":"Point"}
}