{
  "type": "Feature",
  "properties": {
    "addr:full":"30 John Morris Rd Abingdon Oxfordshire OX14 5HW",
    "addr:housenumber":"30",
    "addr:postcode":"ox14 5hw",
    "addr:street":"John Morris Rd",
    "iso:country":"GB",
    "sg:address":"30 John Morris Rd",
    "sg:city":"Abingdon",
    "sg:classifiers":[
        {
            "category":"Health Services",
            "subcategory":"Clinic",
            "type":"Services"
        }
    ],
    "sg:phone":"+44 1235 538300",
    "sg:postcode":"OX14 5HW",
    "sg:province":"Oxfordshire",
    "sg:tags":[
        "aromatherapy"
    ],
    "wof:name":"Lila",
    "wof:placetype":"venue"
},
  "geometry": {"coordinates":[-1.285498023,51.6645011902],"type":"Point"}
}