{
  "type": "Feature",
  "properties": {
    "iso:country":"GB",
    "sg:address":"134 The Street",
    "sg:city":"Littlehampton",
    "sg:classifiers":[
        {
            "category":"Banks & Credit Unions",
            "subcategory":"Financial Services",
            "type":"Services"
        }
    ],
    "sg:phone":"+44 1903 772288",
    "sg:postcode":"BN16 3DA",
    "sg:province":"West Sussex",
    "sg:tags":[
        "adviser"
    ],
    "wof:name":"Taylor Churchill",
    "wof:placetype":"venue"
},
  "geometry": {"coordinates":[-0.505891,50.810436],"type":"Point"}
}