{
  "type": "Feature",
  "properties": {
    "addr:full":"57 Days Road Bristol City of Bristol BS2 0QS",
    "addr:housenumber":"57",
    "addr:postcode":"bs2 0qs",
    "addr:street":"Days Road",
    "iso:country":"GB",
    "sg:address":"57 Days Road",
    "sg:city":"Bristol",
    "sg:classifiers":[
        {
            "category":"Manufacturing",
            "subcategory":"Wood Products",
            "type":"Manufacturing & Wholesale Goods"
        }
    ],
    "sg:phone":"+44 117 941 4999",
    "sg:postcode":"BS2 0QS",
    "sg:province":"City of Bristol",
    "sg:tags":[
        "encapsulation",
        "lamination"
    ],
    "wof:name":"Bristol Laminates (S W) Ltd.",
    "wof:placetype":"venue"
},
  "geometry": {"coordinates":[-2.573418,51.45295],"type":"Point"}
}