{
  "type": "Feature",
  "properties": {
    "addr:full":"8 St Marys Place Newcastle-upon-tyne Tyne and Wear NE1 7PG",
    "addr:housenumber":"8",
    "addr:postcode":"ne1 7pg",
    "addr:street":"St Marys Place",
    "iso:country":"GB",
    "sg:address":"8 St Marys Place",
    "sg:city":"Newcastle-upon-tyne",
    "sg:classifiers":[
        {
            "category":"Shopping",
            "subcategory":"Crafts & Fabrics",
            "type":"Retail Goods"
        },
        {
            "category":"Professional",
            "subcategory":"Printing & Photocopies",
            "type":"Services"
        }
    ],
    "sg:phone":"+44 191 261 1101",
    "sg:postcode":"NE1 7PG",
    "sg:province":"Tyne and Wear",
    "sg:tags":[
        "textile",
        "printer",
        "duplicating",
        "copying"
    ],
    "wof:name":"Spectrum Imaging",
    "wof:placetype":"venue"
},
  "geometry": {"coordinates":[-1.6124099493,54.9777793884],"type":"Point"}
}