{
  "type": "Feature",
  "properties": {
    "addr:full":"Council Offices, Gernon Road Letchworth Hertfordshire SG6 3JF",
    "addr:postcode":"sg6 3jf",
    "addr:street":"Gernon Road",
    "iso:country":"GB",
    "sg:address":"Council Offices, Gernon Road",
    "sg:city":"Letchworth",
    "sg:classifiers":[
        {
            "category":"Retail",
            "subcategory":"Auto Repair",
            "type":"Services"
        },
        {
            "category":"Government",
            "subcategory":"Office",
            "type":"Public Place"
        }
    ],
    "sg:phone":"+44 1462 474000",
    "sg:postcode":"SG6 3JF",
    "sg:province":"Hertfordshire",
    "sg:tags":[
        "modification",
        "garage",
        "local"
    ],
    "wof:name":"North Hertfordshire District Council",
    "wof:placetype":"venue"
},
  "geometry": {"coordinates":[-0.222243,51.972549],"type":"Point"}
}