{
  "type": "Feature",
  "properties": {
    "addr:full":"Rectory Farm, Chellaston Lane, Aston-On-Trent Derby Derbyshire DE72 2AX",
    "addr:postcode":"de72 2ax",
    "addr:street":"Rectory;Chellaston Lane",
    "iso:country":"GB",
    "sg:address":"Rectory Farm, Chellaston Lane, Aston-On-Trent",
    "sg:city":"Derby",
    "sg:classifiers":[
        {
            "category":"Farming",
            "subcategory":"Livestock Farm",
            "type":"Manufacturing & Wholesale Goods"
        }
    ],
    "sg:phone":"+44 1332 792537",
    "sg:postcode":"DE72 2AX",
    "sg:province":"Derbyshire",
    "sg:tags":[
        "others"
    ],
    "wof:name":"J R Armett",
    "wof:placetype":"venue"
},
  "geometry": {"coordinates":[-1.405715,52.845333],"type":"Point"}
}