{
  "type": "Feature",
  "properties": {
    "iso:country":"GB",
    "sg:address":"Sedgegreen Road, Nazeing",
    "sg:city":"Waltham Abbey",
    "sg:classifiers":[
        {
            "category":"Autos & Motor Vehicles",
            "subcategory":"Automobile Sales",
            "type":"Retail Goods"
        }
    ],
    "sg:postcode":"EN9 2PA",
    "sg:province":"Essex",
    "sg:tags":[
        "car"
    ],
    "wof:name":"Belcher Motors",
    "wof:placetype":"venue"
},
  "geometry": {"coordinates":[0.048448,51.738914],"type":"Point"}
}