{
  "type": "Feature",
  "properties": {
    "addr:full":"30 Avon Rd, Hale Altrincham Cheshire CW9 6HS",
    "addr:housenumber":"30",
    "addr:postcode":"cw9 6hs",
    "addr:street":"Avon Rd;Altrincham",
    "iso:country":"GB",
    "sg:address":"30 Avon Rd, Hale",
    "sg:city":"Altrincham",
    "sg:classifiers":[
        {
            "category":"Building & Trades",
            "subcategory":"Construction",
            "type":"Services"
        }
    ],
    "sg:postcode":"CW9 6HS",
    "sg:province":"Cheshire",
    "sg:tags":[
        "builder"
    ],
    "wof:name":"Barnard,Nicolas James,",
    "wof:placetype":"venue"
},
  "geometry": {"coordinates":[-2.5289599895,53.2931289673],"type":"Point"}
}