{
  "type": "Feature",
  "properties": {
    "addr:full":"113 Lauriston Place Edinburgh City of Edinburgh EH3 9JG",
    "addr:housenumber":"113",
    "addr:postcode":"eh3 9jg",
    "addr:street":"Lauriston Place Edinburgh",
    "iso:country":"GB",
    "sg:address":"113 Lauriston Place",
    "sg:city":"Edinburgh",
    "sg:classifiers":[
        {
            "category":"Shopping",
            "subcategory":"Crafts & Fabrics",
            "type":"Retail Goods"
        }
    ],
    "sg:postcode":"EH3 9JG",
    "sg:province":"City of Edinburgh",
    "sg:tags":[
        "material",
        "art"
    ],
    "wof:name":"Edinburgh Creative Crafts",
    "wof:placetype":"venue"
},
  "geometry": {"coordinates":[-3.2020590305,55.9443016052],"type":"Point"}
}