{
  "type": "Feature",
  "properties": {
    "iso:country":"GB",
    "sg:address":"P O Box 100",
    "sg:city":"Malvern",
    "sg:classifiers":[
        {
            "category":"Professional",
            "subcategory":"Business Services",
            "type":"Services"
        }
    ],
    "sg:phone":"+44 1732 366606",
    "sg:postcode":"WR14 4YR",
    "sg:province":"Herefordshire",
    "sg:tags":[
        "assessment",
        "quality"
    ],
    "wof:name":"Oilsearch Plc",
    "wof:placetype":"venue"
},
  "geometry": {"coordinates":[-2.3390789032,52.0920906067],"type":"Point"}
}