{
  "type": "Feature",
  "properties": {
    "addr:full":"Barsham Lodge, 15 Chestnut Avenue Wokingham Berkshire RG41 3HW",
    "addr:housenumber":"15",
    "addr:postcode":"rg41 3hw",
    "addr:street":"Chestnut Avenue",
    "iso:country":"GB",
    "sg:address":"Barsham Lodge, 15 Chestnut Avenue",
    "sg:city":"Wokingham",
    "sg:classifiers":[
        {
            "category":"Retail",
            "subcategory":"Auto Rental",
            "type":"Services"
        }
    ],
    "sg:postcode":"RG41 3HW",
    "sg:province":"Berkshire",
    "sg:tags":[
        "car"
    ],
    "wof:name":"Martin Nowell",
    "wof:placetype":"venue"
},
  "geometry": {"coordinates":[-0.8595399857,51.4173583984],"type":"Point"}
}