{
  "type": "Feature",
  "properties": {
    "addr:full":"2 Church Street Tywyn Gwynedd LL36 9DA",
    "addr:housenumber":"2",
    "addr:postcode":"ll36 9da",
    "addr:street":"Church Street",
    "iso:country":"GB",
    "sg:address":"2 Church Street",
    "sg:city":"Tywyn",
    "sg:classifiers":[
        {
            "category":"Building & Trades",
            "subcategory":"Construction",
            "type":"Services"
        }
    ],
    "sg:phone":"+44 1654 710318",
    "sg:postcode":"LL36 9DA",
    "sg:province":"Gwynedd",
    "sg:tags":[
        "roofing",
        "contracting"
    ],
    "wof:name":"Membrane Water Proofing",
    "wof:placetype":"venue"
},
  "geometry": {"coordinates":[-4.085227,52.587368],"type":"Point"}
}