{
  "type": "Feature",
  "properties": {
    "iso:country":"GB",
    "sg:address":"Meadgate Cottage, Stevens Lane",
    "sg:city":"Weston-super-mare",
    "sg:classifiers":[
        {
            "category":"Professional",
            "subcategory":"Accounting & Tax Preparation",
            "type":"Services"
        }
    ],
    "sg:postcode":"BS24 0BX",
    "sg:province":"Somerset",
    "sg:tags":[
        "accountant"
    ],
    "wof:name":"R F Hicks",
    "wof:placetype":"venue"
},
  "geometry": {"coordinates":[-2.94599,51.288601],"type":"Point"}
}