{
  "type": "Feature",
  "properties": {
    "iso:country":"GB",
    "sg:address":"Lower Upton Farm, Upton",
    "sg:city":"Burford",
    "sg:classifiers":[
        {
            "category":"Farming",
            "subcategory":"Farm",
            "type":"Manufacturing & Wholesale Goods"
        }
    ],
    "sg:postcode":"OX18 4LX",
    "sg:province":"Gloucestershire",
    "sg:tags":[
        "mixed",
        "crop"
    ],
    "wof:name":"N G Mills",
    "wof:placetype":"venue"
},
  "geometry": {"coordinates":[-1.635023,51.802338],"type":"Point"}
}