{
  "type": "Feature",
  "properties": {
    "iso:country":"GB",
    "sg:address":"33 Stevenston Street",
    "sg:city":"Motherwell",
    "sg:classifiers":[
        {
            "category":"Fast Food",
            "type":"Food & Drink"
        }
    ],
    "sg:phone":"+44 1698 832505",
    "sg:postcode":"ML1 4LR",
    "sg:province":"North Lanarkshire",
    "sg:tags":[
        "away",
        "meal",
        "outlet",
        "take"
    ],
    "wof:name":"Lucky House",
    "wof:placetype":"venue"
},
  "geometry": {"coordinates":[-3.978026,55.813831],"type":"Point"}
}