{
  "type": "Feature",
  "properties": {
    "iso:country":"GB",
    "sg:address":", Horley",
    "sg:city":"Banbury",
    "sg:classifiers":[
        {
            "category":"Bars & Pubs",
            "type":"Food & Drink"
        }
    ],
    "sg:phone":"+44 1295 730427",
    "sg:postcode":"OX15 6BQ",
    "sg:province":"Oxfordshire",
    "sg:tags":[
        "pubs",
        "inn"
    ],
    "wof:name":"The Red Lion",
    "wof:placetype":"venue"
},
  "geometry": {"coordinates":[-1.3910030127,52.09167099],"type":"Point"}
}