{
  "type": "Feature",
  "properties": {
    "addr:full":"Unit 1 Alexander St Dundee Dundee City DD3 7DA",
    "addr:housenumber":"unit 1",
    "addr:postcode":"dd3 7da",
    "addr:street":"Alexander St",
    "iso:country":"GB",
    "sg:address":"Unit 1 Alexander St",
    "sg:city":"Dundee",
    "sg:classifiers":[
        {
            "category":"Manufacturing",
            "subcategory":"Signs",
            "type":"Manufacturing & Wholesale Goods"
        }
    ],
    "sg:phone":"+44 1382 226273",
    "sg:postcode":"DD3 7DA",
    "sg:province":"Dundee City",
    "sg:tags":[
        "nameplate"
    ],
    "wof:name":"Robert Parker",
    "wof:placetype":"venue"
},
  "geometry": {"coordinates":[-2.9666559696,56.4702415466],"type":"Point"}
}