{
  "type": "Feature",
  "properties": {
    "iso:country":"GB",
    "sg:address":"North Street",
    "sg:city":"Hailsham",
    "sg:classifiers":[
        {
            "category":"Commercial Area",
            "type":"Public Place"
        }
    ],
    "sg:phone":"+44 1323 847784",
    "sg:postcode":"BN27 1DP",
    "sg:province":"East Sussex",
    "sg:tags":[
        "shop",
        "centre"
    ],
    "wof:name":"The Quintins Centre",
    "wof:placetype":"venue"
},
  "geometry": {"coordinates":[0.257467,50.863338],"type":"Point"}
}