{
  "type": "Feature",
  "properties": {
    "iso:country":"GB",
    "sg:address":"1a Newarke Walk",
    "sg:city":"Leicester",
    "sg:classifiers":[
        {
            "category":"Professional",
            "subcategory":"Employment Agencies",
            "type":"Services"
        }
    ],
    "sg:phone":"+44 116 254 5678",
    "sg:postcode":"LE1 6TE",
    "sg:province":"Leicestershire",
    "sg:tags":[
        "consultant"
    ],
    "wof:name":"People First Recruitment Specialists",
    "wof:placetype":"venue"
},
  "geometry": {"coordinates":[-1.1342949867,52.6319961548],"type":"Point"}
}