{
  "type": "Feature",
  "properties": {
    "addr:full":"East Works, Norman Street Warrington Cheshire WA2 7HW",
    "addr:postcode":"wa2 7hw",
    "addr:street":"East;Norman Street",
    "iso:country":"GB",
    "sg:address":"East Works, Norman Street",
    "sg:city":"Warrington",
    "sg:classifiers":[
        {
            "category":"Retail",
            "subcategory":"Auto Repair",
            "type":"Services"
        }
    ],
    "sg:postcode":"WA2 7HW",
    "sg:province":"Cheshire",
    "sg:tags":[
        "modification",
        "garage"
    ],
    "wof:name":"A S G Garage",
    "wof:placetype":"venue"
},
  "geometry": {"coordinates":[-2.589254,53.393826],"type":"Point"}
}