{
  "type": "Feature",
  "properties": {
    "iso:country":"GB",
    "sg:address":"Abington House, 12 Abington Grove",
    "sg:city":"Northampton",
    "sg:classifiers":[
        {
            "category":"Professional",
            "subcategory":"Computer Services",
            "type":"Services"
        }
    ],
    "sg:postcode":"NN1 4QX",
    "sg:province":"Northamptonshire",
    "sg:tags":[
        "system",
        "software"
    ],
    "wof:name":"Daramind Ltd",
    "wof:placetype":"venue"
},
  "geometry": {"coordinates":[-0.877144,52.24897],"type":"Point"}
}