{
  "type": "Feature",
  "properties": {
    "iso:country":"GB",
    "sg:address":"2 Roberts Mews, High Street",
    "sg:city":"Orpington",
    "sg:classifiers":[
        {
            "category":"Manufacturing",
            "subcategory":"Textiles",
            "type":"Manufacturing & Wholesale Goods"
        }
    ],
    "sg:phone":"+44 1689 831822",
    "sg:postcode":"BR6 0JP",
    "sg:province":"Kent",
    "sg:tags":[
        "made-up"
    ],
    "wof:name":"Pretty Frills/Phone Fitter",
    "wof:placetype":"venue"
},
  "geometry": {"coordinates":[0.099702,51.377167],"type":"Point"}
}