{
  "type": "Feature",
  "properties": {
    "addr:full":"Rear Of Unit 2, Upper Conybere Street Birmingham West Midlands B12 0YP",
    "addr:housenumber":"rear of unit 2",
    "addr:postcode":"upper;b12 0yp",
    "addr:street":"Conybere Street",
    "iso:country":"GB",
    "sg:address":"Rear Of Unit 2, Upper Conybere Street",
    "sg:city":"Birmingham",
    "sg:classifiers":[
        {
            "category":"Manufacturing",
            "subcategory":"Tools & Machinery",
            "type":"Manufacturing & Wholesale Goods"
        }
    ],
    "sg:phone":"+44 121 440 6711",
    "sg:postcode":"B12 0YP",
    "sg:province":"West Midlands",
    "sg:tags":[
        "design",
        "maker"
    ],
    "wof:name":"Fred Powles",
    "wof:placetype":"venue"
},
  "geometry": {"coordinates":[-1.908604,52.478596],"type":"Point"}
}