{
  "type": "Feature",
  "properties": {
    "addr:full":"The Forge, Halnaker Chichester West Sussex PO18 0NQ",
    "addr:postcode":"po18 0nq",
    "addr:street":"Halnaker",
    "iso:country":"GB",
    "sg:address":"The Forge, Halnaker",
    "sg:city":"Chichester",
    "sg:classifiers":[
        {
            "category":"Home & Garden",
            "subcategory":"Building Materials",
            "type":"Retail Goods"
        }
    ],
    "sg:phone":"+44 1243 773431",
    "sg:postcode":"PO18 0NQ",
    "sg:province":"West Sussex",
    "sg:tags":[
        "ironwork",
        "diy",
        "wrought"
    ],
    "wof:name":"Blacksmith Shop",
    "wof:placetype":"venue"
},
  "geometry": {"coordinates":[-0.7109569907,50.8655319214],"type":"Point"}
}