{
  "type": "Feature",
  "properties": {
    "addr:full":"Unit 1 Westbourne Road Wednesbury West Midlands WS10 8BJ",
    "addr:housenumber":"unit 1",
    "addr:postcode":"ws10 8bj",
    "addr:street":"Westbourne Road",
    "iso:country":"GB",
    "sg:address":"Unit 1 Westbourne Road",
    "sg:city":"Wednesbury",
    "sg:classifiers":[
        {
            "category":"Retail",
            "subcategory":"Auto Repair",
            "type":"Services"
        }
    ],
    "sg:phone":"+44 121 526 2909",
    "sg:postcode":"WS10 8BJ",
    "sg:province":"West Midlands",
    "sg:tags":[
        "modification",
        "garage"
    ],
    "wof:name":"B & A Motors",
    "wof:placetype":"venue"
},
  "geometry": {"coordinates":[-2.0225930214,52.5712471008],"type":"Point"}
}