{
  "type": "Feature",
  "properties": {
    "iso:country":"GB",
    "sg:address":"Whittingham La, Gossnargh",
    "sg:city":"Preston",
    "sg:classifiers":[
        {
            "category":"Bars & Pubs",
            "type":"Food & Drink"
        }
    ],
    "sg:postcode":"PR3 2AU",
    "sg:province":"Lancashire",
    "sg:tags":[
        "pubs",
        "inn"
    ],
    "wof:name":"Willan,A & J,",
    "wof:placetype":"venue"
},
  "geometry": {"coordinates":[-2.6688790321,53.8222084045],"type":"Point"}
}