{
  "type": "Feature",
  "properties": {
    "addr:full":"139 Fortess Road London Greater London NW5 2HR",
    "addr:housenumber":"139",
    "addr:postcode":"nw5 2hr",
    "addr:street":"Fortess Road",
    "iso:country":"GB",
    "sg:address":"139 Fortess Road",
    "sg:city":"London",
    "sg:classifiers":[
        {
            "category":"Health Services",
            "subcategory":"Dentist",
            "type":"Services"
        }
    ],
    "sg:phone":"+44 20 7485 3833",
    "sg:postcode":"NW5 2HR",
    "sg:province":"Greater London",
    "wof:name":"Smileline Dental Practice",
    "wof:placetype":"venue"
},
  "geometry": {"coordinates":[-0.1395460069,51.555606842],"type":"Point"}
}