{
  "type": "Feature",
  "properties": {
    "iso:country":"GB",
    "sg:address":"Leominster Road",
    "sg:city":"Hereford",
    "sg:classifiers":[
        {
            "category":"Place Of Worship",
            "type":"Public Place"
        }
    ],
    "sg:phone":"+44 1432 273200",
    "sg:postcode":"HR4 9RG",
    "sg:province":"Herefordshire",
    "wof:name":"St Batholemews Church",
    "wof:placetype":"venue"
},
  "geometry": {"coordinates":[-2.7317609787,52.0592041016],"type":"Point"}
}