{
  "type": "Feature",
  "properties": {
    "iso:country":"GB",
    "sg:address":"29 Poolbrook Road",
    "sg:city":"Malvern",
    "sg:classifiers":[
        {
            "category":"Manufacturing",
            "subcategory":"Paper Products",
            "type":"Manufacturing & Wholesale Goods"
        }
    ],
    "sg:phone":"+44 1684 575346",
    "sg:postcode":"WR14 3NL",
    "sg:province":"Herefordshire",
    "sg:tags":[
        "cardboard"
    ],
    "wof:name":"Derek C Adams",
    "wof:placetype":"venue"
},
  "geometry": {"coordinates":[-2.305629,52.105621],"type":"Point"}
}