{
  "type": "Feature",
  "properties": {
    "iso:country":"GB",
    "sg:address":"66 Chamberlayne Rd",
    "sg:city":"Willesden",
    "sg:classifiers":[
        {
            "category":"Shopping",
            "subcategory":"Used Merchandise",
            "type":"Retail Goods"
        }
    ],
    "sg:phone":"+44 20 8969 1273",
    "sg:postcode":"NW10 3JJ",
    "sg:province":"Greater London",
    "sg:tags":[
        "shop",
        "second-hand"
    ],
    "wof:name":"Second Enterprises",
    "wof:placetype":"venue"
},
  "geometry": {"coordinates":[-0.2175890058,51.5321311951],"type":"Point"}
}