{
  "type": "Feature",
  "properties": {
    "iso:country":"GB",
    "sg:address":"29 Eglinton Street",
    "sg:city":"Irvine",
    "sg:classifiers":[
        {
            "category":"Retail",
            "subcategory":"Laundry & Dry Cleaning",
            "type":"Services"
        }
    ],
    "sg:phone":"+44 1294 311284",
    "sg:postcode":"KA12 8AX",
    "sg:province":"North Ayrshire",
    "sg:tags":[
        "alteration"
    ],
    "wof:name":"Ann Trousdale",
    "wof:placetype":"venue"
},
  "geometry": {"coordinates":[-4.6684341431,55.6035003662],"type":"Point"}
}