{
  "type": "Feature",
  "properties": {
    "addr:full":"25 New Rd, Harston Cambridge Cambridgeshire CB2 5QG",
    "addr:housenumber":"25",
    "addr:postcode":"cb2 5qg",
    "addr:street":"New Rd",
    "iso:country":"GB",
    "sg:address":"25 New Rd, Harston",
    "sg:city":"Cambridge",
    "sg:classifiers":[
        {
            "category":"Real Estate",
            "subcategory":"Architect",
            "type":"Services"
        }
    ],
    "sg:phone":"+44 7979 750201",
    "sg:postcode":"CB2 5QG",
    "sg:province":"Cambridgeshire",
    "wof:name":"Team: SLK.v2",
    "wof:placetype":"venue"
},
  "geometry": {"coordinates":[0.087652,52.142685],"type":"Point"}
}