{
  "type": "Feature",
  "properties": {
    "addr:full":"30 Clements Road East Ham Greater London E6 2DE",
    "addr:housenumber":"30",
    "addr:postcode":"e6 2de",
    "addr:street":"Clements Road",
    "iso:country":"GB",
    "sg:address":"30 Clements Road",
    "sg:city":"East Ham",
    "sg:classifiers":[
        {
            "category":"Manufacturing",
            "subcategory":"Textiles",
            "type":"Manufacturing & Wholesale Goods"
        }
    ],
    "sg:phone":"+44 20 8552 9091",
    "sg:postcode":"E6 2DE",
    "sg:province":"Greater London",
    "sg:tags":[
        "mnfr",
        "rug",
        "carpet"
    ],
    "wof:name":"Rebook Pressing & Ironing Services",
    "wof:placetype":"venue"
},
  "geometry": {"coordinates":[0.0531839989,51.5372390747],"type":"Point"}
}