{
  "type": "Feature",
  "properties": {
    "addr:full":"Warwick House, Allenbrook Road, Rosehill Estate Carlisle Cumbria CA1 2UT",
    "addr:postcode":"ca1 2ut",
    "addr:street":"Allenbrook Road",
    "iso:country":"GB",
    "sg:address":"Warwick House, Allenbrook Road, Rosehill Estate",
    "sg:city":"Carlisle",
    "sg:classifiers":[
        {
            "category":"Banks & Credit Unions",
            "subcategory":"Financial Services",
            "type":"Services"
        }
    ],
    "sg:phone":"+44 1228 595626",
    "sg:postcode":"CA1 2UT",
    "sg:province":"Cumbria",
    "sg:tags":[
        "consultant"
    ],
    "wof:name":"Dodd Financial Services Ltd.",
    "wof:placetype":"venue"
},
  "geometry": {"coordinates":[-2.8941400051,54.8922309875],"type":"Point"}
}