{
  "type": "Feature",
  "properties": {
    "iso:country":"GB",
    "sg:address":"6 Grosvenor Rd",
    "sg:city":"Aldershot",
    "sg:classifiers":[
        {
            "category":"Organizations",
            "subcategory":"Non-profit Organization",
            "type":"Services"
        }
    ],
    "sg:postcode":"GU11 1DP",
    "sg:province":"Hampshire",
    "sg:tags":[
        "organisation",
        "voluntary",
        "charity"
    ],
    "wof:name":"United Partners",
    "wof:placetype":"venue"
},
  "geometry": {"coordinates":[-0.767785,51.249352],"type":"Point"}
}