{
  "type": "Feature",
  "properties": {
    "iso:country":"GB",
    "sg:address":"54 Gresham Street",
    "sg:city":"London",
    "sg:classifiers":[
        {
            "category":"Banks & Credit Unions",
            "subcategory":"Financial Services",
            "type":"Services"
        }
    ],
    "sg:phone":"+44 20 7600 2570",
    "sg:postcode":"EC2V 7LL",
    "sg:province":"Greater London",
    "sg:tags":[
        "building",
        "society"
    ],
    "wof:name":"Chelsea Building Society",
    "wof:placetype":"venue"
},
  "geometry": {"coordinates":[-0.093359001,51.5154190063],"type":"Point"}
}