{
  "type": "Feature",
  "properties": {
    "addr:full":"Rookery Farm, Ludgershall Aylesbury Buckinghamshire HP18 9PA",
    "addr:housenumber":"ludgershall",
    "addr:postcode":"hp18 9pa",
    "addr:street":"Aylesbury",
    "iso:country":"GB",
    "sg:address":"Rookery Farm, Ludgershall",
    "sg:city":"Aylesbury",
    "sg:classifiers":[
        {
            "category":"Farming",
            "subcategory":"Livestock Farm",
            "type":"Manufacturing & Wholesale Goods"
        }
    ],
    "sg:postcode":"HP18 9PA",
    "sg:province":"Buckinghamshire",
    "sg:tags":[
        "others"
    ],
    "wof:name":"L & J W Burnell",
    "wof:placetype":"venue"
},
  "geometry": {"coordinates":[-1.038857,51.853779],"type":"Point"}
}