{
  "type": "Feature",
  "properties": {
    "addr:full":"Parkgate House,, 33a, Pratt Street, London Greater London NW1 0BG",
    "addr:housenumber":"33a",
    "addr:postcode":"nw1 0bg",
    "addr:street":"Parkgate;Pratt Street",
    "iso:country":"GB",
    "sg:address":"Parkgate House,, 33a, Pratt Street,",
    "sg:city":"London",
    "sg:classifiers":[
        {
            "category":"Communications",
            "type":"Services"
        }
    ],
    "sg:postcode":"NW1 0BG",
    "sg:province":"Greater London",
    "sg:tags":[
        "broadcasting"
    ],
    "wof:name":"Grove Television Limited",
    "wof:placetype":"venue"
},
  "geometry": {"coordinates":[-0.1392650008,51.5380134583],"type":"Point"}
}