{
  "type": "Feature",
  "properties": {
    "addr:full":"78 King St Maidstone Kent ME14 1BH",
    "addr:housenumber":"78",
    "addr:postcode":"me14 1bh",
    "addr:street":"King St",
    "iso:country":"GB",
    "sg:address":"78 King St",
    "sg:city":"Maidstone",
    "sg:classifiers":[
        {
            "category":"Professional",
            "subcategory":"Employment Agencies",
            "type":"Services"
        }
    ],
    "sg:phone":"+44 1622 200288",
    "sg:postcode":"ME14 1BH",
    "sg:province":"Kent",
    "sg:tags":[
        "consultant"
    ],
    "wof:name":"JBA Resourcing",
    "wof:placetype":"venue"
},
  "geometry": {"coordinates":[0.52838,51.273293],"type":"Point"}
}