{
  "type": "Feature",
  "properties": {
    "iso:country":"GB",
    "sg:address":"High Street, Boosbeck",
    "sg:city":"Saltburn-by-the-sea",
    "sg:classifiers":[
        {
            "category":"Sports & Exercise",
            "subcategory":"Tennis Court",
            "type":"Entertainment"
        }
    ],
    "sg:postcode":"TS12 3AG",
    "sg:province":"North Yorkshire",
    "sg:tags":[
        "breakdown",
        "recovery"
    ],
    "wof:name":"John Hislop Recovery",
    "wof:placetype":"venue"
},
  "geometry": {"coordinates":[-0.982484,54.543839],"type":"Point"}
}