{
  "type": "Feature",
  "properties": {
    "iso:country":"GB",
    "sg:address":"Unit 47 Court Road Industrial Estate",
    "sg:city":"Cwmbran",
    "sg:classifiers":[
        {
            "category":"Professional",
            "subcategory":"Engineering",
            "type":"Services"
        }
    ],
    "sg:phone":"+44 1633 871160",
    "sg:postcode":"NP44 3AS",
    "sg:province":"Monmouthshire",
    "sg:tags":[
        "contractor",
        "electrical",
        "engineer"
    ],
    "wof:name":"Technic Electrical Ltd.",
    "wof:placetype":"venue"
},
  "geometry": {"coordinates":[-3.0143990517,51.64453125],"type":"Point"}
}