{
  "type": "Feature",
  "properties": {
    "iso:country":"GB",
    "sg:address":"Corner House, Green Batt",
    "sg:city":"Alnwick",
    "sg:classifiers":[
        {
            "category":"Personal",
            "type":"Services"
        },
        {
            "category":"Professional",
            "subcategory":"Lawyer & Legal Services",
            "type":"Services"
        }
    ],
    "sg:phone":"+44 1665 605189",
    "sg:postcode":"NE66 1TS",
    "sg:province":"Northumberland",
    "sg:tags":[
        "advice",
        "counselling"
    ],
    "wof:name":"KENNETH GRAHAM MCDONALD",
    "wof:placetype":"venue"
},
  "geometry": {"coordinates":[-1.7071640491,55.411693573],"type":"Point"}
}