{
  "type": "Feature",
  "properties": {
    "addr:full":"62 Craven Avenue Plymouth Devon PL4 8SW",
    "addr:housenumber":"62",
    "addr:postcode":"pl4 8sw",
    "addr:street":"Craven Avenue",
    "iso:country":"GB",
    "sg:address":"62 Craven Avenue",
    "sg:city":"Plymouth",
    "sg:classifiers":[
        {
            "category":"Real Estate",
            "subcategory":"Real Estate Services",
            "type":"Services"
        },
        {
            "category":"Building & Trades",
            "subcategory":"Construction",
            "type":"Services"
        }
    ],
    "sg:postcode":"PL4 8SW",
    "sg:province":"Devon",
    "sg:tags":[
        "builder",
        "management"
    ],
    "wof:name":"DANIEL RUTH CLARK",
    "wof:placetype":"venue"
},
  "geometry": {"coordinates":[-4.1220860481,50.3765525818],"type":"Point"}
}