{
  "type": "Feature",
  "properties": {
    "iso:country":"GB",
    "sg:address":"38 Parsons Street",
    "sg:city":"Banbury",
    "sg:classifiers":[
        {
            "category":"Home & Garden",
            "subcategory":"Home Furnishings",
            "type":"Retail Goods"
        }
    ],
    "sg:phone":"+44 1295 253462",
    "sg:postcode":"OX16 5NA",
    "sg:province":"Oxfordshire",
    "sg:tags":[
        "blind",
        "curtain",
        "fitting"
    ],
    "wof:name":"Bernard Smith's Curtain Shop",
    "wof:placetype":"venue"
},
  "geometry": {"coordinates":[-1.3388940096,52.0622406006],"type":"Point"}
}