{
  "type": "Feature",
  "properties": {
    "iso:country":"GB",
    "sg:address":"95 Chestnut Gro",
    "sg:city":"Balham",
    "sg:classifiers":[
        {
            "category":"Professional",
            "subcategory":"Accounting & Tax Preparation",
            "type":"Services"
        }
    ],
    "sg:phone":"+44 20 8673 8869",
    "sg:postcode":"SW12 8JG",
    "sg:province":"Greater London",
    "sg:tags":[
        "accountant"
    ],
    "wof:name":"Teh Steve & Co",
    "wof:placetype":"venue"
},
  "geometry": {"coordinates":[-0.15591,51.446583],"type":"Point"}
}