{
  "type": "Feature",
  "properties": {
    "addr:full":"Innage Road Shifnal Shropshire TF11 8AD",
    "addr:postcode":"tf11 8ad",
    "addr:street":"Innage Road",
    "iso:country":"GB",
    "sg:address":"Innage Road",
    "sg:city":"Shifnal",
    "sg:classifiers":[
        {
            "category":"Organizations",
            "subcategory":"Membership Organization",
            "type":"Services"
        }
    ],
    "sg:phone":"+44 1952 270015",
    "sg:postcode":"TF11 8AD",
    "sg:province":"Shropshire",
    "sg:tags":[
        "club",
        "social"
    ],
    "wof:name":"The Shifnal War Memorial Club",
    "wof:placetype":"venue"
},
  "geometry": {"coordinates":[-2.377974,52.666935],"type":"Point"}
}