{
  "type": "Feature",
  "properties": {
    "iso:country":"GB",
    "sg:address":"2 Towning Close, Deeping St James",
    "sg:city":"Peterborough",
    "sg:classifiers":[
        {
            "category":"Retail",
            "subcategory":"Driving School",
            "type":"Services"
        }
    ],
    "sg:phone":"+44 1778 342415",
    "sg:postcode":"PE6 8HR",
    "sg:province":"Cambridgeshire",
    "wof:name":"Chips School of Motoring",
    "wof:placetype":"venue"
},
  "geometry": {"coordinates":[-0.3019399941,52.6793251038],"type":"Point"}
}