{
  "type": "Feature",
  "properties": {
    "addr:full":"82 Cormorant Dr St Austell Cornwall PL25 3BA",
    "addr:housenumber":"82",
    "addr:postcode":"pl25 3ba",
    "addr:street":"Cormorant Dr",
    "iso:country":"GB",
    "sg:address":"82 Cormorant Dr",
    "sg:city":"St Austell",
    "sg:classifiers":[
        {
            "category":"Retail",
            "subcategory":"Driving School",
            "type":"Services"
        }
    ],
    "sg:phone":"+44 1726 72410",
    "sg:postcode":"PL25 3BA",
    "sg:province":"Cornwall",
    "wof:name":"Trelawney Driving School",
    "wof:placetype":"venue"
},
  "geometry": {"coordinates":[-4.7663650513,50.3394241333],"type":"Point"}
}