{
  "type": "Feature",
  "properties": {
    "addr:full":"2 Solant Rd Havant Hampshire PO9 1JH",
    "addr:housenumber":"2",
    "addr:postcode":"po9 1jh",
    "addr:street":"Solant Rd",
    "iso:country":"GB",
    "sg:address":"2 Solant Rd",
    "sg:city":"Havant",
    "sg:classifiers":[
        {
            "category":"Community Center",
            "subcategory":"Social",
            "type":"Public Place"
        }
    ],
    "sg:phone":"+44 23 9247 0410",
    "sg:postcode":"PO9 1JH",
    "sg:province":"Hampshire",
    "sg:tags":[
        "case"
    ],
    "wof:name":"Cpg Tudorsale",
    "wof:placetype":"venue"
},
  "geometry": {"coordinates":[-0.9931650162,50.8497810364],"type":"Point"}
}