{
  "type": "Feature",
  "properties": {
    "addr:full":"7 Wyncham Av Sidcup Kent DA15 8EU",
    "addr:housenumber":"7",
    "addr:postcode":"da15 8eu",
    "addr:street":"Av Sidcup",
    "iso:country":"GB",
    "sg:address":"7 Wyncham Av",
    "sg:city":"Sidcup",
    "sg:classifiers":[
        {
            "category":"Professional",
            "subcategory":"Computer Services",
            "type":"Services"
        }
    ],
    "sg:phone":"+44 20 8300 3004",
    "sg:postcode":"DA15 8EU",
    "sg:province":"Kent",
    "sg:tags":[
        "system",
        "software"
    ],
    "wof:name":"Millennium Technology UK",
    "wof:placetype":"venue"
},
  "geometry": {"coordinates":[0.090426,51.43948],"type":"Point"}
}