{
  "type": "Feature",
  "properties": {
    "iso:country":"GB",
    "sg:address":"Woodside, Knill",
    "sg:city":"Presteigne",
    "sg:classifiers":[
        {
            "category":"Home & Garden",
            "subcategory":"Building Materials",
            "type":"Retail Goods"
        }
    ],
    "sg:phone":"+44 1544 267734",
    "sg:postcode":"LD8 2PR",
    "sg:province":"Herefordshire",
    "sg:tags":[
        "veneer"
    ],
    "wof:name":"Nicholls Fencing Products Ltd.",
    "wof:placetype":"venue"
},
  "geometry": {"coordinates":[-3.004454,52.270206],"type":"Point"}
}