{
  "type": "Feature",
  "properties": {
    "addr:full":"10 Cavendish Way, Mickleover Derby Derbyshire DE3 9BJ",
    "addr:housenumber":"10",
    "addr:postcode":"de3 9bj",
    "addr:street":"Cavendish Way",
    "iso:country":"GB",
    "sg:address":"10 Cavendish Way, Mickleover",
    "sg:city":"Derby",
    "sg:classifiers":[
        {
            "category":"Health Services",
            "subcategory":"Doctor",
            "type":"Services"
        }
    ],
    "sg:phone":"+44 1332 519160",
    "sg:postcode":"DE3 9BJ",
    "sg:province":"Derbyshire",
    "sg:tags":[
        "practitioners"
    ],
    "wof:name":"Mickleover Surgery",
    "wof:placetype":"venue"
},
  "geometry": {"coordinates":[-1.5363479853,52.9071006775],"type":"Point"}
}