{
  "type": "Feature",
  "properties": {
    "addr:full":"Lingfield House, Lowdells Lane East Grinstead East Sussex RH19 2EA",
    "addr:postcode":"rh19 2ea",
    "addr:street":"Lowdells Lane",
    "iso:country":"GB",
    "sg:address":"Lingfield House, Lowdells Lane",
    "sg:city":"East Grinstead",
    "sg:classifiers":[
        {
            "category":"Building & Trades",
            "subcategory":"Construction",
            "type":"Services"
        }
    ],
    "sg:phone":"+44 1342 321258",
    "sg:postcode":"RH19 2EA",
    "sg:province":"East Sussex",
    "sg:tags":[
        "builder"
    ],
    "wof:name":"B & A Home Improvements",
    "wof:placetype":"venue"
},
  "geometry": {"coordinates":[-0.02986,51.138268],"type":"Point"}
}