{
  "type": "Feature",
  "properties": {
    "addr:full":"25 Rose Street Glasgow Glasgow City G3 6RE",
    "addr:housenumber":"25",
    "addr:postcode":"g3 6re",
    "addr:street":"Rose Street",
    "iso:country":"GB",
    "sg:address":"25 Rose Street",
    "sg:city":"Glasgow",
    "sg:classifiers":[
        {
            "category":"Place Of Worship",
            "type":"Public Place"
        }
    ],
    "sg:phone":"+44 141 332 3039",
    "sg:postcode":"G3 6RE",
    "sg:province":"Glasgow City",
    "wof:name":"St.Aloysius Church",
    "wof:placetype":"venue"
},
  "geometry": {"coordinates":[-4.261219,55.866669],"type":"Point"}
}