{
  "type": "Feature",
  "properties": {
    "addr:full":"Lyndene, Sowerby Row Carlisle Cumbria CA4 0QH",
    "addr:postcode":"ca4 0qh",
    "addr:street":"Sowerby Row",
    "iso:country":"GB",
    "sg:address":"Lyndene, Sowerby Row",
    "sg:city":"Carlisle",
    "sg:classifiers":[
        {
            "category":"Building & Trades",
            "subcategory":"Construction",
            "type":"Services"
        }
    ],
    "sg:phone":"+44 16974 76384",
    "sg:postcode":"CA4 0QH",
    "sg:province":"Cumbria",
    "sg:tags":[
        "builder"
    ],
    "wof:name":"S & C Asbridge",
    "wof:placetype":"venue"
},
  "geometry": {"coordinates":[-2.9429600239,54.752368927],"type":"Point"}
}