{
  "type": "Feature",
  "properties": {
    "addr:full":"240 Fleet Lane St Helens Cheshire WA9 2RU",
    "addr:housenumber":"240",
    "addr:postcode":"wa9 2ru",
    "addr:street":"Fleet Lane",
    "iso:country":"GB",
    "sg:address":"240 Fleet Lane",
    "sg:city":"St Helens",
    "sg:classifiers":[
        {
            "category":"Education",
            "subcategory":"School",
            "type":"Public Place"
        }
    ],
    "sg:postcode":"WA9 2RU",
    "sg:province":"Cheshire",
    "sg:tags":[
        "private",
        "tuition"
    ],
    "wof:name":"David Stone Piano Teacher",
    "wof:placetype":"venue"
},
  "geometry": {"coordinates":[-2.7001979351,53.4475212097],"type":"Point"}
}