{
  "type": "Feature",
  "properties": {
    "iso:country":"GB",
    "sg:address":"Alexandra St, Devonside",
    "sg:city":"Tillicoultry",
    "sg:classifiers":[
        {
            "category":"Shopping",
            "subcategory":"Department Store",
            "type":"Retail Goods"
        }
    ],
    "sg:postcode":"FK13 6HR",
    "sg:province":"Clackmannanshire",
    "wof:name":"Snaddon,R,",
    "wof:placetype":"venue"
},
  "geometry": {"coordinates":[-3.74211,56.153267],"type":"Point"}
}