{
  "type": "Feature",
  "properties": {
    "iso:country":"GB",
    "sg:address":"Burleyhurst Lane, Mobberley",
    "sg:city":"Knutsford",
    "sg:classifiers":[
        {
            "category":"Sports & Exercise",
            "subcategory":"Golf",
            "type":"Entertainment"
        }
    ],
    "sg:phone":"+44 1565 880188",
    "sg:postcode":"WA16 7JZ",
    "sg:province":"Cheshire",
    "sg:tags":[
        "club",
        "course"
    ],
    "wof:name":"Mobberley Golf Club",
    "wof:placetype":"venue"
},
  "geometry": {"coordinates":[-2.2935419083,53.323802948],"type":"Point"}
}