{
  "type": "Feature",
  "properties": {
    "iso:country":"GB",
    "sg:address":"2 Sewardstone Road",
    "sg:city":"Waltham Abbey",
    "sg:classifiers":[
        {
            "category":"Professional",
            "subcategory":"Detective & Security Services",
            "type":"Services"
        }
    ],
    "sg:phone":"+44 1992 788777",
    "sg:postcode":"EN9 1NB",
    "sg:province":"Essex",
    "wof:name":"Safe Security Services",
    "wof:placetype":"venue"
},
  "geometry": {"coordinates":[0.00146,51.686687],"type":"Point"}
}