{
  "type": "Feature",
  "properties": {
    "addr:full":"Unit B Tinhay Mill Indust Est, Tinhay Lifton Devon PL16 0AH",
    "addr:housenumber":"lifton",
    "addr:postcode":"pl16 0ah",
    "addr:street":"Indust;Devon",
    "iso:country":"GB",
    "sg:address":"Unit B Tinhay Mill Indust Est, Tinhay",
    "sg:city":"Lifton",
    "sg:classifiers":[
        {
            "category":"Wholesale",
            "subcategory":"Electrical",
            "type":"Manufacturing & Wholesale Goods"
        }
    ],
    "sg:postcode":"PL16 0AH",
    "sg:province":"Devon",
    "sg:tags":[
        "equipment",
        "refrigeration"
    ],
    "wof:name":"Walpole,Gordon,",
    "wof:placetype":"venue"
},
  "geometry": {"coordinates":[-4.283153,50.643166],"type":"Point"}
}