{
  "type": "Feature",
  "properties": {
    "addr:full":"5 Denny Crescent London Greater London SE11 4UY",
    "addr:housenumber":"5",
    "addr:postcode":"se11 4uy",
    "addr:street":"Denny Crescent",
    "iso:country":"GB",
    "sg:address":"5 Denny Crescent",
    "sg:city":"London",
    "sg:classifiers":[
        {
            "category":"Building & Trades",
            "subcategory":"Construction",
            "type":"Services"
        }
    ],
    "sg:phone":"+44 20 7582 0120",
    "sg:postcode":"SE11 4UY",
    "sg:province":"Greater London",
    "sg:tags":[
        "partition",
        "installation",
        "refurbishment",
        "restoration"
    ],
    "wof:name":"Gianpaolo De Rocco Associates",
    "wof:placetype":"venue"
},
  "geometry": {"coordinates":[-0.1096500009,51.4901733398],"type":"Point"}
}