{
  "type": "Feature",
  "properties": {
    "addr:full":"Our Lady's Mill, Mill Street Aberystwyth Ceredigion SY23 1JB",
    "addr:postcode":"sy23 1jb",
    "addr:street":"Mill Street",
    "iso:country":"GB",
    "sg:address":"Our Lady's Mill, Mill Street",
    "sg:city":"Aberystwyth",
    "sg:classifiers":[
        {
            "category":"Personal",
            "subcategory":"Beauty Salon",
            "type":"Services"
        }
    ],
    "sg:postcode":"SY23 1JB",
    "sg:province":"Ceredigion",
    "wof:name":"Hayley Joy Salon Debeaute",
    "wof:placetype":"venue"
},
  "geometry": {"coordinates":[-4.0845298767,52.4121398926],"type":"Point"}
}