{
  "type": "Feature",
  "properties": {
    "addr:full":"23 Kingswear Gro Leeds West Yorkshire LS15 8PL",
    "addr:housenumber":"23",
    "addr:postcode":"ls15 8pl",
    "addr:street":"Kingswear Gro Leeds West",
    "iso:country":"GB",
    "sg:address":"23 Kingswear Gro",
    "sg:city":"Leeds",
    "sg:classifiers":[
        {
            "category":"Professional",
            "subcategory":"Detective & Security Services",
            "type":"Services"
        }
    ],
    "sg:phone":"+44 113 232 6662",
    "sg:postcode":"LS15 8PL",
    "sg:province":"West Yorkshire",
    "sg:tags":[
        "locksmith"
    ],
    "wof:name":"A1 Lockdoctors Mobile Locksmith",
    "wof:placetype":"venue"
},
  "geometry": {"coordinates":[-1.443453,53.802444],"type":"Point"}
}