{
  "type": "Feature",
  "properties": {
    "addr:full":"14 Crackenedge Lane Dewsbury West Yorkshire WF13 1PT",
    "addr:housenumber":"14",
    "addr:postcode":"wf13 1pt",
    "addr:street":"Crackenedge Lane",
    "iso:country":"GB",
    "sg:address":"14 Crackenedge Lane",
    "sg:city":"Dewsbury",
    "sg:classifiers":[
        {
            "category":"Shopping",
            "subcategory":"Thrift Store",
            "type":"Retail Goods"
        },
        {
            "category":"Organizations",
            "subcategory":"Non-profit Organization",
            "type":"Services"
        }
    ],
    "sg:phone":"+44 1924 469411",
    "sg:postcode":"WF13 1PT",
    "sg:province":"West Yorkshire",
    "sg:tags":[
        "shop",
        "charitable",
        "organisation",
        "charity"
    ],
    "sg:website":"http://www.nkmind.com",
    "wof:name":"Mind",
    "wof:placetype":"venue"
},
  "geometry": {"coordinates":[-1.6276589632,53.6917610168],"type":"Point"}
}