{
  "type": "Feature",
  "properties": {
    "iso:country":"GB",
    "sg:address":"Brick House Farm, Ipswich Road, Naughton",
    "sg:city":"Ipswich",
    "sg:classifiers":[
        {
            "category":"Farming",
            "subcategory":"Farm",
            "type":"Manufacturing & Wholesale Goods"
        }
    ],
    "sg:postcode":"IP7 7DA",
    "sg:province":"Suffolk",
    "sg:tags":[
        "mixed",
        "crop"
    ],
    "wof:name":"A J Pratt & Son",
    "wof:placetype":"venue"
},
  "geometry": {"coordinates":[0.9530199766,52.1023483276],"type":"Point"}
}