{
  "type": "Feature",
  "properties": {
    "addr:full":"111 Wellington Road South Stockport Cheshire SK1 3TL",
    "addr:housenumber":"111",
    "addr:postcode":"sk1 3tl",
    "addr:street":"Wellington Road South",
    "iso:country":"GB",
    "sg:address":"111 Wellington Road South",
    "sg:city":"Stockport",
    "sg:classifiers":[
        {
            "category":"Wholesale",
            "subcategory":"Construction Materials",
            "type":"Manufacturing & Wholesale Goods"
        }
    ],
    "sg:postcode":"SK1 3TL",
    "sg:province":"Cheshire",
    "sg:tags":[
        "whole",
        "asphalt",
        "macadam"
    ],
    "wof:name":"S Dodgeson",
    "wof:placetype":"venue"
},
  "geometry": {"coordinates":[-2.157807,53.404118],"type":"Point"}
}