{
  "type": "Feature",
  "properties": {
    "iso:country":"GB",
    "sg:address":"Oxford Road",
    "sg:city":"Runcorn",
    "sg:classifiers":[
        {
            "category":"Education",
            "subcategory":"School",
            "type":"Public Place"
        },
        {
            "category":"Government",
            "subcategory":"Office",
            "type":"Public Place"
        }
    ],
    "sg:phone":"+44 1928 572129",
    "sg:postcode":"WA7 4NX",
    "sg:province":"Cheshire",
    "sg:tags":[
        "local",
        "authority"
    ],
    "wof:name":"St Clement's R C (Aided) Primary School",
    "wof:placetype":"venue"
},
  "geometry": {"coordinates":[-2.7321989536,53.3321342468],"type":"Point"}
}