{
  "type": "Feature",
  "properties": {
    "addr:full":"Dumballs Road Cardiff Cardiff CF1 6UB",
    "addr:postcode":"cf1 6ub",
    "addr:street":"Dumballs Road",
    "iso:country":"GB",
    "sg:address":"Dumballs Road",
    "sg:city":"Cardiff",
    "sg:classifiers":[
        {
            "category":"Community Center",
            "subcategory":"Youth",
            "type":"Public Place"
        }
    ],
    "sg:phone":"+44 29 2048 8666",
    "sg:postcode":"CF1 6UB",
    "sg:province":"Cardiff",
    "sg:tags":[
        "organisation",
        "centre"
    ],
    "wof:name":"Butetown Youth Pavilion",
    "wof:placetype":"venue"
},
  "geometry": {"coordinates":[-3.176189,51.472481],"type":"Point"}
}