{
  "type": "Feature",
  "properties": {
    "addr:full":"79-81 Giles Street Edinburgh City of Edinburgh EH6 6BZ",
    "addr:housenumber":"79-81",
    "addr:postcode":"eh6 6bz",
    "addr:street":"Giles Street",
    "iso:country":"GB",
    "sg:address":"79-81 Giles Street",
    "sg:city":"Edinburgh",
    "sg:classifiers":[
        {
            "category":"Retail",
            "subcategory":"Auto Repair",
            "type":"Services"
        }
    ],
    "sg:phone":"+44 131 554 1233",
    "sg:postcode":"EH6 6BZ",
    "sg:province":"City of Edinburgh",
    "sg:tags":[
        "modification",
        "garage"
    ],
    "wof:name":"Tomson Motor Co",
    "wof:placetype":"venue"
},
  "geometry": {"coordinates":[-3.1728971004,55.9734535217],"type":"Point"}
}