{
  "type": "Feature",
  "properties": {
    "iso:country":"GB",
    "sg:address":"Red Wing, Lyon Street",
    "sg:city":"Dundee",
    "sg:classifiers":[
        {
            "category":"Health Services",
            "subcategory":"Doctor",
            "type":"Services"
        },
        {
            "category":"Health Services",
            "subcategory":"Clinic",
            "type":"Services"
        }
    ],
    "sg:phone":"+44 1382 456700",
    "sg:postcode":"DD4 6RB",
    "sg:province":"Dundee City",
    "sg:tags":[
        "nh",
        "practitioners"
    ],
    "wof:name":"Wallacetown Health Centre",
    "wof:placetype":"venue"
},
  "geometry": {"coordinates":[-2.9595999718,56.4682998657],"type":"Point"}
}