{
  "type": "Feature",
  "properties": {
    "iso:country":"GB",
    "sg:address":"21 Rigg Street, Stewarton",
    "sg:city":"Kilmarnock",
    "sg:classifiers":[
        {
            "category":"Sports & Exercise",
            "subcategory":"Gym",
            "type":"Entertainment"
        }
    ],
    "sg:phone":"+44 1560 485148",
    "sg:postcode":"KA3 5LE",
    "sg:province":"East Ayrshire",
    "sg:tags":[
        "fitness",
        "health",
        "centre"
    ],
    "wof:name":"Porky's Gymnasium",
    "wof:placetype":"venue"
},
  "geometry": {"coordinates":[-4.516829,55.681782],"type":"Point"}
}