{
  "type": "Feature",
  "properties": {
    "iso:country":"GB",
    "sg:address":"33 Holly Dene, Armthorpe",
    "sg:city":"Doncaster",
    "sg:classifiers":[
        {
            "category":"Building & Trades",
            "subcategory":"Construction",
            "type":"Services"
        }
    ],
    "sg:phone":"+44 1302 832337",
    "sg:postcode":"DN3 2HJ",
    "sg:province":"South Yorkshire",
    "sg:tags":[
        "builder"
    ],
    "wof:name":"John & Patricia Whittington",
    "wof:placetype":"venue"
},
  "geometry": {"coordinates":[-1.057311,53.544003],"type":"Point"}
}