{
  "type": "Feature",
  "properties": {
    "iso:country":"GB",
    "sg:address":"Carlton House, Grammar School",
    "sg:city":"Bradford",
    "sg:classifiers":[
        {
            "category":"Bars & Pubs",
            "type":"Food & Drink"
        }
    ],
    "sg:postcode":"BD1 4NS",
    "sg:province":"West Yorkshire",
    "sg:tags":[
        "pubs",
        "inn"
    ],
    "wof:name":"The Lancaster Hotels Ltd",
    "wof:placetype":"venue"
},
  "geometry": {"coordinates":[-1.7559939623,53.7980384827],"type":"Point"}
}