{
  "type": "Feature",
  "properties": {
    "addr:full":"5-19 Mount Wise Newquay Cornwall TR7 2BQ",
    "addr:housenumber":"5-19",
    "addr:postcode":"tr7 2bq",
    "addr:street":"Mount",
    "iso:country":"GB",
    "sg:address":"5-19 Mount Wise",
    "sg:city":"Newquay",
    "sg:classifiers":[
        {
            "category":"Travel",
            "subcategory":"Hotels & Motels",
            "type":"Entertainment"
        }
    ],
    "sg:phone":"+44 1637 851522",
    "sg:postcode":"TR7 2BQ",
    "sg:province":"Cornwall",
    "wof:name":"Ambassador Hotel",
    "wof:placetype":"venue"
},
  "geometry": {"coordinates":[-5.0799150467,50.412399292],"type":"Point"}
}