{
  "type": "Feature",
  "properties": {
    "addr:full":"Flat 2 Epirus Mansions, Epirus Road London Greater London SW6 7UJ",
    "addr:postcode":"sw6 7uj",
    "addr:street":"Epirus Road",
    "iso:country":"GB",
    "sg:address":"Flat 2 Epirus Mansions, Epirus Road",
    "sg:city":"London",
    "sg:classifiers":[
        {
            "category":"Taxi",
            "type":"Transportation"
        }
    ],
    "sg:phone":"+44 20 7381 4334",
    "sg:postcode":"SW6 7UJ",
    "sg:province":"Greater London",
    "sg:tags":[
        "mini",
        "cab"
    ],
    "wof:name":"Fulham & Chalsea Cars",
    "wof:placetype":"venue"
},
  "geometry": {"coordinates":[-0.2003999949,51.4818305969],"type":"Point"}
}