{
  "type": "Feature",
  "properties": {
    "addr:full":"6 Burnfarm Cotts, Killen Avoch Highland IV9 8RG",
    "addr:housenumber":"6",
    "addr:postcode":"iv9 8rg",
    "addr:street":"Burnfarm Cotts;Avoch",
    "iso:country":"GB",
    "sg:address":"6 Burnfarm Cotts, Killen",
    "sg:city":"Avoch",
    "sg:classifiers":[
        {
            "category":"Recreation",
            "subcategory":"Gun Range",
            "type":"Entertainment"
        }
    ],
    "sg:postcode":"IV9 8RG",
    "sg:province":"Highland",
    "sg:tags":[
        "operator",
        "tour"
    ],
    "wof:name":"Albannach",
    "wof:placetype":"venue"
},
  "geometry": {"coordinates":[-4.1764187813,57.5680084229],"type":"Point"}
}