{
  "type": "Feature",
  "properties": {
    "iso:country":"GB",
    "sg:address":"Parsons House, Parsons Road",
    "sg:city":"Washington",
    "sg:classifiers":[
        {
            "category":"Banks & Credit Unions",
            "subcategory":"Financial Services",
            "type":"Services"
        }
    ],
    "sg:phone":"+44 191 419 2221",
    "sg:postcode":"NE37 1EZ",
    "sg:province":"Tyne and Wear",
    "sg:tags":[
        "adviser",
        "independent"
    ],
    "sg:website":"http://www.ifas.co.uk",
    "wof:name":"Independent Financial Advisory Services",
    "wof:placetype":"venue"
},
  "geometry": {"coordinates":[-1.540859,54.910236],"type":"Point"}
}