{
  "type": "Feature",
  "properties": {
    "addr:full":"Four Lane Ends, Over Hulton Bolton Lancashire BL5 1EG",
    "addr:postcode":"bl5 1eg",
    "addr:street":"Four Lane Ends",
    "iso:country":"GB",
    "sg:address":"Four Lane Ends, Over Hulton",
    "sg:city":"Bolton",
    "sg:classifiers":[
        {
            "category":"Home & Garden",
            "subcategory":"Hardware",
            "type":"Retail Goods"
        }
    ],
    "sg:postcode":"BL5 1EG",
    "sg:province":"Lancashire",
    "sg:tags":[
        "device",
        "fixing",
        "fastener"
    ],
    "wof:name":"F Aspinall & Co. (Hulton) Ltd.",
    "wof:placetype":"venue"
},
  "geometry": {"coordinates":[-2.4706439972,53.5449180603],"type":"Point"}
}