{
  "type": "Feature",
  "properties": {
    "addr:full":"Phoenix House, 86 Fulham High Street London Greater London SW6 3LF",
    "addr:housenumber":"86",
    "addr:postcode":"sw6 3lf",
    "addr:street":"Fulham High Street",
    "iso:country":"GB",
    "sg:address":"Phoenix House, 86 Fulham High Street",
    "sg:city":"London",
    "sg:classifiers":[
        {
            "category":"Communications",
            "subcategory":"Newspaper",
            "type":"Services"
        }
    ],
    "sg:phone":"+44 20 7736 4424",
    "sg:postcode":"SW6 3LF",
    "sg:province":"Greater London",
    "sg:tags":[
        "magazine"
    ],
    "wof:name":"Eurostar Magazine",
    "wof:placetype":"venue"
},
  "geometry": {"coordinates":[-0.210521996,51.4698829651],"type":"Point"}
}