{
  "type": "Feature",
  "properties": {
    "iso:country":"GB",
    "sg:address":"Unit 9, 121 London Road, Bridge Yate",
    "sg:city":"Bristol",
    "sg:classifiers":[
        {
            "category":"Building & Trades",
            "subcategory":"Landscaping Services",
            "type":"Services"
        }
    ],
    "sg:phone":"+44 117 935 3588",
    "sg:postcode":"BS30 5NA",
    "sg:province":"Gloucestershire",
    "sg:tags":[
        "horticultural"
    ],
    "wof:name":"B S Mowers",
    "wof:placetype":"venue"
},
  "geometry": {"coordinates":[-2.45993,51.45739],"type":"Point"}
}