{
  "type": "Feature",
  "properties": {
    "addr:full":"Hill Gro, Bryn Port Talbot Neath Port Talbot SA13 2RR",
    "addr:postcode":"sa13 2rr",
    "addr:street":"Hill Gro Bryn Port Talbot",
    "iso:country":"GB",
    "sg:address":"Hill Gro, Bryn",
    "sg:city":"Port Talbot",
    "sg:classifiers":[
        {
            "category":"Arena",
            "subcategory":"Sports Club",
            "type":"Entertainment"
        }
    ],
    "sg:phone":"+44 1639 896278",
    "sg:postcode":"SA13 2RR",
    "sg:province":"Neath Port Talbot",
    "wof:name":"Bryn Wanderers Rugby Social Club Ltd.",
    "wof:placetype":"venue"
},
  "geometry": {"coordinates":[-3.7130270004,51.6172981262],"type":"Point"}
}