{
  "type": "Feature",
  "properties": {
    "addr:full":"16a Old Rd Manchester Lancashire M35 0AW",
    "addr:housenumber":"16a",
    "addr:postcode":"m35 0aw",
    "addr:street":"Old Rd",
    "iso:country":"GB",
    "sg:address":"16a Old Rd",
    "sg:city":"Manchester",
    "sg:classifiers":[
        {
            "category":"Building & Trades",
            "subcategory":"Plumbing",
            "type":"Services"
        }
    ],
    "sg:phone":"+44 161 682 4079",
    "sg:postcode":"M35 0AW",
    "sg:province":"Lancashire",
    "sg:tags":[
        "heating"
    ],
    "wof:name":"Morris Arnold Boiler Engineers",
    "wof:placetype":"venue"
},
  "geometry": {"coordinates":[-2.2187540531,53.5211906433],"type":"Point"}
}