{
  "type": "Feature",
  "properties": {
    "addr:full":"Whitby Court, Abbey Road, Huddersfield South Yorkshire HD8 8ER",
    "addr:postcode":"hd8 8er",
    "addr:street":"Whitby Court Abbey Road",
    "iso:country":"GB",
    "sg:address":"Whitby Court, Abbey Road,",
    "sg:city":"Huddersfield",
    "sg:classifiers":[
        {
            "category":"Professional",
            "subcategory":"Management & Consulting",
            "type":"Services"
        }
    ],
    "sg:postcode":"HD8 8ER",
    "sg:province":"South Yorkshire",
    "sg:tags":[
        "consultant",
        "investigation",
        "site"
    ],
    "wof:name":"Global Probing  &  Sampling Ltd",
    "wof:placetype":"venue"
},
  "geometry": {"coordinates":[-1.703639,53.585999],"type":"Point"}
}