{
  "type": "Feature",
  "properties": {
    "addr:full":"Reve Clinic, 2a Guildford Park Rd Guildford Surrey GU2 5ND",
    "addr:housenumber":"2a",
    "addr:postcode":"gu2 5nd",
    "addr:street":"Guildford Park Rd",
    "iso:country":"GB",
    "sg:address":"Reve Clinic, 2a Guildford Park Rd",
    "sg:city":"Guildford",
    "sg:classifiers":[
        {
            "category":"Health Services",
            "subcategory":"Health Practitioner",
            "type":"Services"
        }
    ],
    "sg:phone":"+44 1483 579500",
    "sg:postcode":"GU2 5ND",
    "sg:province":"Surrey",
    "sg:tags":[
        "psychotherapist"
    ],
    "wof:name":"Margaret Comport",
    "wof:placetype":"venue"
},
  "geometry": {"coordinates":[-0.5982199907,51.2472686768],"type":"Point"}
}