{
  "type": "Feature",
  "properties": {
    "addr:full":"Nibley Road Bristol City of Bristol BS11 9XW",
    "addr:postcode":"bs11 9xw",
    "addr:street":"Nibley Road",
    "iso:country":"GB",
    "sg:address":"Nibley Road",
    "sg:city":"Bristol",
    "sg:classifiers":[
        {
            "category":"Organizations",
            "subcategory":"Membership Organization",
            "type":"Services"
        }
    ],
    "sg:phone":"+44 117 982 3927",
    "sg:postcode":"BS11 9XW",
    "sg:province":"City of Bristol",
    "sg:tags":[
        "club"
    ],
    "wof:name":"The City & Port of Bristol Social & Sports Club",
    "wof:placetype":"venue"
},
  "geometry": {"coordinates":[-2.6695859432,51.4856147766],"type":"Point"}
}