{
  "type": "Feature",
  "properties": {
    "iso:country":"GB",
    "sg:address":"38 High Street, Sutton-on-sea",
    "sg:city":"Mablethorpe",
    "sg:classifiers":[
        {
            "category":"Retail",
            "subcategory":"Funeral Services",
            "type":"Services"
        }
    ],
    "sg:phone":"+44 1507 442300",
    "sg:postcode":"LN12 2DR",
    "sg:province":"Lincolnshire",
    "wof:name":"Arnold Funeral Services",
    "wof:placetype":"venue"
},
  "geometry": {"coordinates":[0.28094,53.31308],"type":"Point"}
}