{
  "type": "Feature",
  "properties": {
    "addr:full":"13 Barley Croft, Whittington Lichfield Staffordshire WS14 9LY",
    "addr:housenumber":"13",
    "addr:postcode":"ws14 9ly",
    "addr:street":"Barley Croft",
    "iso:country":"GB",
    "sg:address":"13 Barley Croft, Whittington",
    "sg:city":"Lichfield",
    "sg:classifiers":[
        {
            "category":"Professional",
            "subcategory":"Engineering",
            "type":"Services"
        },
        {
            "category":"Building & Trades",
            "subcategory":"Plumbing",
            "type":"Services"
        }
    ],
    "sg:postcode":"WS14 9LY",
    "sg:province":"Staffordshire",
    "sg:tags":[
        "gas",
        "heating",
        "engineer"
    ],
    "wof:name":"Robert J Talbot",
    "wof:placetype":"venue"
},
  "geometry": {"coordinates":[-1.7595059872,52.6739654541],"type":"Point"}
}