{
  "type": "Feature",
  "properties": {
    "addr:full":"15 Templars Firs, Wootton Bassett Swindon Wiltshire SN4 7ES",
    "addr:housenumber":"15",
    "addr:postcode":"sn4 7es",
    "addr:street":"Templars Firs Wootton",
    "iso:country":"GB",
    "sg:address":"15 Templars Firs, Wootton Bassett",
    "sg:city":"Swindon",
    "sg:classifiers":[
        {
            "category":"Building & Trades",
            "subcategory":"Construction",
            "type":"Services"
        }
    ],
    "sg:postcode":"SN4 7ES",
    "sg:province":"Wiltshire",
    "sg:tags":[
        "builder"
    ],
    "wof:name":"Apec Building & Roofing",
    "wof:placetype":"venue"
},
  "geometry": {"coordinates":[-1.8978749514,51.5331764221],"type":"Point"}
}