{
  "type": "Feature",
  "properties": {
    "addr:full":"Higher Ranscombe Road Brixham Devon TQ5 9HF",
    "addr:postcode":"tq5 9hf",
    "addr:street":"Ranscombe Road",
    "iso:country":"GB",
    "sg:address":"Higher Ranscombe Road",
    "sg:city":"Brixham",
    "sg:classifiers":[
        {
            "category":"Health Services",
            "subcategory":"Clinic",
            "type":"Services"
        },
        {
            "category":"Education",
            "subcategory":"School",
            "type":"Public Place"
        }
    ],
    "sg:phone":"+44 1803 858271",
    "sg:postcode":"TQ5 9HF",
    "sg:province":"Devon",
    "sg:tags":[
        "nh",
        "local",
        "authority"
    ],
    "wof:name":"Brixham Community College",
    "wof:placetype":"venue"
},
  "geometry": {"coordinates":[-3.505774,50.393486],"type":"Point"}
}