{
  "type": "Feature",
  "properties": {
    "addr:full":"7 St.james Rd Ferndown Dorset BH22 9NY",
    "addr:housenumber":"7",
    "addr:postcode":"bh22 9ny",
    "addr:street":"St.James Rd",
    "iso:country":"GB",
    "sg:address":"7 St.james Rd",
    "sg:city":"Ferndown",
    "sg:classifiers":[
        {
            "category":"Professional",
            "subcategory":"Detective & Security Services",
            "type":"Services"
        }
    ],
    "sg:phone":"+44 1202 893332",
    "sg:postcode":"BH22 9NY",
    "sg:province":"Dorset",
    "wof:name":"Quantumatic CCTV",
    "wof:placetype":"venue"
},
  "geometry": {"coordinates":[-1.894356966,50.8016853333],"type":"Point"}
}