{
  "type": "Feature",
  "properties": {
    "addr:full":"133-135 High St Blackwood Caerphilly NP2 1AA",
    "addr:housenumber":"133-135",
    "addr:postcode":"np2 1aa",
    "addr:street":"High St",
    "iso:country":"GB",
    "sg:address":"133-135 High St",
    "sg:city":"Blackwood",
    "sg:classifiers":[
        {
            "category":"Shopping",
            "subcategory":"Pharmacy",
            "type":"Retail Goods"
        }
    ],
    "sg:phone":"+44 1495 229909",
    "sg:postcode":"NP2 1AA",
    "sg:province":"Caerphilly",
    "sg:tags":[
        "store",
        "drug"
    ],
    "wof:name":"Lloyds Supersave Drugstore",
    "wof:placetype":"venue"
},
  "geometry": {"coordinates":[-3.195205,51.666767],"type":"Point"}
}