{
  "type": "Feature",
  "properties": {
    "addr:full":"Hockley Business Park, Hooley Lane Redhill Surrey RH1 6JS",
    "addr:postcode":"rh1 6js",
    "addr:street":"Hooley Lane",
    "iso:country":"GB",
    "sg:address":"Hockley Business Park, Hooley Lane",
    "sg:city":"Redhill",
    "sg:classifiers":[
        {
            "category":"Shopping",
            "type":"Retail Goods"
        }
    ],
    "sg:postcode":"RH1 6JS",
    "sg:province":"Surrey",
    "sg:tags":[
        "med",
        "scientific",
        "apparatus"
    ],
    "wof:name":"D C Scientific Glass Blowing",
    "wof:placetype":"venue"
},
  "geometry": {"coordinates":[-0.168879,51.238178],"type":"Point"}
}