{
  "type": "Feature",
  "properties": {
    "addr:full":"Westfield Road, Horbury Wakefield West Yorkshire WF4 6DW",
    "addr:postcode":"wf4 6dw",
    "addr:street":"Westfield Road;West",
    "iso:country":"GB",
    "sg:address":"Westfield Road, Horbury",
    "sg:city":"Wakefield",
    "sg:classifiers":[
        {
            "category":"Home & Garden",
            "subcategory":"Furniture",
            "type":"Retail Goods"
        }
    ],
    "sg:phone":"+44 1924 272458",
    "sg:postcode":"WF4 6DW",
    "sg:province":"West Yorkshire",
    "wof:name":"Dormant St01 Ltd.",
    "wof:placetype":"venue"
},
  "geometry": {"coordinates":[-1.5679490566,53.6642532349],"type":"Point"}
}