{
  "type": "Feature",
  "properties": {
    "addr:full":"Unit 1 Washdyke Lane, Hucknall Nottingham Nottinghamshire NG15 6NH",
    "addr:housenumber":"unit 1",
    "addr:postcode":"ng15 6nh",
    "addr:street":"Washdyke Lane",
    "iso:country":"GB",
    "sg:address":"Unit 1 Washdyke Lane, Hucknall",
    "sg:city":"Nottingham",
    "sg:classifiers":[
        {
            "category":"Shopping",
            "subcategory":"Discount & Variety Stores",
            "type":"Retail Goods"
        }
    ],
    "sg:phone":"+44 115 968 0759",
    "sg:postcode":"NG15 6NH",
    "sg:province":"Nottinghamshire",
    "sg:tags":[
        "cleaning",
        "supply"
    ],
    "wof:name":"Byron Textiles",
    "wof:placetype":"venue"
},
  "geometry": {"coordinates":[-1.2189,53.043404],"type":"Point"}
}