{
  "type": "Feature",
  "properties": {
    "addr:full":"6 Hartington Park Bristol City of Bristol BS6 7ES",
    "addr:housenumber":"6",
    "addr:postcode":"bs6 7es",
    "addr:street":"Hartington Park",
    "iso:country":"GB",
    "sg:address":"6 Hartington Park",
    "sg:city":"Bristol",
    "sg:classifiers":[
        {
            "category":"Professional",
            "subcategory":"Art Services",
            "type":"Services"
        }
    ],
    "sg:phone":"+44 117 985 3375",
    "sg:postcode":"BS6 7ES",
    "sg:province":"City of Bristol",
    "sg:tags":[
        "consultant",
        "design"
    ],
    "wof:name":"Meridian Design",
    "wof:placetype":"venue"
},
  "geometry": {"coordinates":[-2.604279,51.479149],"type":"Point"}
}