{
  "type": "Feature",
  "properties": {
    "iso:country":"GB",
    "sg:address":"295 Hertford Road",
    "sg:city":"Enfield",
    "sg:classifiers":[
        {
            "category":"Shopping",
            "subcategory":"News",
            "type":"Retail Goods"
        }
    ],
    "sg:phone":"+44 20 8804 5129",
    "sg:postcode":"EN3 5JN",
    "sg:province":"Greater London",
    "sg:tags":[
        "newsagent"
    ],
    "wof:name":"Newsflash",
    "wof:placetype":"venue"
},
  "geometry": {"coordinates":[-0.04586,51.661102],"type":"Point"}
}