{
  "type": "Feature",
  "properties": {
    "iso:country":"GB",
    "sg:address":"23-24 Neath Road, Hafod",
    "sg:city":"Swansea",
    "sg:classifiers":[
        {
            "category":"Banks & Credit Unions",
            "subcategory":"Bureau De Change",
            "type":"Services"
        },
        {
            "category":"Food & Beverages",
            "subcategory":"Liquor & Beverages",
            "type":"Retail Goods"
        }
    ],
    "sg:phone":"+44 1792 467779",
    "sg:postcode":"SA1 2ES",
    "sg:province":"Neath Port Talbot",
    "sg:tags":[
        "beer",
        "wine",
        "spirit",
        "wines"
    ],
    "wof:name":"Cocktails",
    "wof:placetype":"venue"
},
  "geometry": {"coordinates":[-3.9394919872,51.6319122314],"type":"Point"}
}