{
  "type": "Feature",
  "properties": {
    "addr:full":"62 Pembroke Road London Greater London W8 6NX",
    "addr:housenumber":"62",
    "addr:postcode":"w8 6nx",
    "addr:street":"Pembroke Road",
    "iso:country":"GB",
    "sg:address":"62 Pembroke Road",
    "sg:city":"London",
    "sg:classifiers":[
        {
            "category":"Professional",
            "type":"Services"
        }
    ],
    "sg:phone":"+44 20 7603 8662",
    "sg:postcode":"W8 6NX",
    "sg:province":"Greater London",
    "sg:tags":[
        "interior",
        "furnishers",
        "designer"
    ],
    "wof:name":"Richmond Torres Ltd.",
    "wof:placetype":"venue"
},
  "geometry": {"coordinates":[-0.1974419951,51.4954071045],"type":"Point"}
}