{
  "type": "Feature",
  "properties": {
    "addr:full":"4 Auchencrow Street Glasgow Glasgow City G34 0BW",
    "addr:housenumber":"4",
    "addr:postcode":"g34 0bw",
    "addr:street":"Auchencrow Street",
    "iso:country":"GB",
    "sg:address":"4 Auchencrow Street",
    "sg:city":"Glasgow",
    "sg:classifiers":[
        {
            "category":"Organizations",
            "subcategory":"Non-profit Organization",
            "type":"Services"
        }
    ],
    "sg:phone":"+44 141 771 4343",
    "sg:postcode":"G34 0BW",
    "sg:province":"Glasgow City",
    "sg:tags":[
        "charitable",
        "organisation",
        "voluntary",
        "charity"
    ],
    "wof:name":"THE SALVATION ARMY",
    "wof:placetype":"venue"
},
  "geometry": {"coordinates":[-4.1007790565,55.8659934998],"type":"Point"}
}