{
  "type": "Feature",
  "properties": {
    "addr:full":"35 Milkstone Road Rochdale Lancashire OL11 1EB",
    "addr:housenumber":"35",
    "addr:postcode":"ol11 1eb",
    "addr:street":"Milkstone Road",
    "iso:country":"GB",
    "sg:address":"35 Milkstone Road",
    "sg:city":"Rochdale",
    "sg:classifiers":[
        {
            "category":"Restaurant",
            "type":"Food & Drink"
        }
    ],
    "sg:postcode":"OL11 1EB",
    "sg:province":"Lancashire",
    "wof:name":"M R Choudry",
    "wof:placetype":"venue"
},
  "geometry": {"coordinates":[-2.1570680141,53.6108856201],"type":"Point"}
}