{
  "type": "Feature",
  "properties": {
    "addr:full":"The Yard, Island St Salcombe Devon TQ8 8DP",
    "addr:postcode":"tq8 8dp",
    "addr:street":"Island St",
    "iso:country":"GB",
    "sg:address":"The Yard, Island St",
    "sg:city":"Salcombe",
    "sg:classifiers":[
        {
            "category":"Building & Trades",
            "subcategory":"Construction",
            "type":"Services"
        }
    ],
    "sg:phone":"+44 1548 844337",
    "sg:postcode":"TQ8 8DP",
    "sg:province":"Devon",
    "sg:tags":[
        "worker",
        "metal"
    ],
    "wof:name":"Andrew Harris Ironworks",
    "wof:placetype":"venue"
},
  "geometry": {"coordinates":[-3.7747991085,50.237865448],"type":"Point"}
}