{
  "type": "Feature",
  "properties": {
    "addr:full":"Unit 3a Heapriding Mill, Ford Street Stockport Cheshire SK3 0BT",
    "addr:housenumber":"unit 3a",
    "addr:postcode":"sk3 0bt",
    "addr:street":"Heapriding Mill Ford Street",
    "iso:country":"GB",
    "sg:address":"Unit 3a Heapriding Mill, Ford Street",
    "sg:city":"Stockport",
    "sg:classifiers":[
        {
            "category":"Professional",
            "subcategory":"Printing & Photocopies",
            "type":"Services"
        }
    ],
    "sg:phone":"+44 7831 205749",
    "sg:postcode":"SK3 0BT",
    "sg:province":"Cheshire",
    "sg:tags":[
        "printer"
    ],
    "wof:name":"Screen Ink & Solvent Supplies Ltd.",
    "wof:placetype":"venue"
},
  "geometry": {"coordinates":[-2.161516,53.408409],"type":"Point"}
}