{
  "type": "Feature",
  "properties": {
    "addr:full":"6 West Port Arbroath Angus DD11 1RE",
    "addr:housenumber":"6",
    "addr:postcode":"dd11 1re",
    "addr:street":"West Port",
    "iso:country":"GB",
    "sg:address":"6 West Port",
    "sg:city":"Arbroath",
    "sg:classifiers":[
        {
            "category":"Fast Food",
            "type":"Food & Drink"
        }
    ],
    "sg:phone":"+44 1241 870967",
    "sg:postcode":"DD11 1RE",
    "sg:province":"Angus",
    "sg:tags":[
        "delivery"
    ],
    "wof:name":"Westport Pizza",
    "wof:placetype":"venue"
},
  "geometry": {"coordinates":[-2.587444067,56.5580825806],"type":"Point"}
}