{
  "type": "Feature",
  "properties": {
    "addr:full":"3 The Parade, High Street Watford Hertfordshire WD17 1LQ",
    "addr:housenumber":"3",
    "addr:postcode":"wd17 1lq",
    "addr:street":"The Parade High Street",
    "iso:country":"GB",
    "sg:address":"3 The Parade, High Street",
    "sg:city":"Watford",
    "sg:classifiers":[
        {
            "category":"Shopping",
            "subcategory":"Music",
            "type":"Retail Goods"
        }
    ],
    "sg:phone":"+44 1923 252300",
    "sg:postcode":"WD17 1LQ",
    "sg:province":"Hertfordshire",
    "sg:tags":[
        "shop"
    ],
    "wof:name":"C D Warehouse U K Ltd.",
    "wof:placetype":"venue"
},
  "geometry": {"coordinates":[-0.400219,51.658234],"type":"Point"}
}