{
  "type": "Feature",
  "properties": {
    "addr:full":"166 Burnham Lane Slough Berkshire SL1 6LE",
    "addr:housenumber":"166",
    "addr:postcode":"sl1 6le",
    "addr:street":"Burnham Lane",
    "iso:country":"GB",
    "sg:address":"166 Burnham Lane",
    "sg:city":"Slough",
    "sg:classifiers":[
        {
            "category":"Banks & Credit Unions",
            "subcategory":"Bureau De Change",
            "type":"Services"
        },
        {
            "category":"Retail",
            "subcategory":"Laundry & Dry Cleaning",
            "type":"Services"
        }
    ],
    "sg:phone":"+44 1628 660481",
    "sg:postcode":"SL1 6LE",
    "sg:province":"Berkshire",
    "sg:tags":[
        "alteration"
    ],
    "wof:name":"Laundro Coin",
    "wof:placetype":"venue"
},
  "geometry": {"coordinates":[-0.649345994,51.5275001526],"type":"Point"}
}