{
  "type": "Feature",
  "properties": {
    "addr:full":"31 Commerce Street Fraserburgh Aberdeenshire AB43 5AQ",
    "addr:housenumber":"31",
    "addr:postcode":"ab43 5aq",
    "addr:street":"Commerce Street",
    "iso:country":"GB",
    "sg:address":"31 Commerce Street",
    "sg:city":"Fraserburgh",
    "sg:classifiers":[
        {
            "category":"Food & Beverages",
            "subcategory":"Bakery",
            "type":"Retail Goods"
        }
    ],
    "sg:phone":"+44 1346 518236",
    "sg:postcode":"AB43 5AQ",
    "sg:province":"Aberdeenshire",
    "sg:tags":[
        "baker"
    ],
    "wof:name":"John Smith & Sons (New Pitsligo)",
    "wof:placetype":"venue"
},
  "geometry": {"coordinates":[-2.00638,57.69141],"type":"Point"}
}