{
  "type": "Feature",
  "properties": {
    "addr:full":"123 Stonecot Hill Sutton Surrey SM3 9HS",
    "addr:housenumber":"123",
    "addr:postcode":"sm3 9hs",
    "addr:street":"Stonecot Hill",
    "iso:country":"GB",
    "sg:address":"123 Stonecot Hill",
    "sg:city":"Sutton",
    "sg:classifiers":[
        {
            "category":"Building & Trades",
            "subcategory":"Construction",
            "type":"Services"
        }
    ],
    "sg:phone":"+44 20 8641 3674",
    "sg:postcode":"SM3 9HS",
    "sg:province":"Surrey",
    "sg:tags":[
        "builder"
    ],
    "wof:name":"Metro Building Contractors",
    "wof:placetype":"venue"
},
  "geometry": {"coordinates":[-0.2158579975,51.3819580078],"type":"Point"}
}