{
  "type": "Feature",
  "properties": {
    "addr:full":"164 Streatham Hill London Greater London SW2 4RU",
    "addr:housenumber":"164",
    "addr:postcode":"sw2 4ru",
    "addr:street":"Streatham Hill",
    "iso:country":"GB",
    "sg:address":"164 Streatham Hill",
    "sg:city":"London",
    "sg:classifiers":[
        {
            "category":"Travel",
            "subcategory":"Travel Agent",
            "type":"Entertainment"
        }
    ],
    "sg:phone":"+44 20 8671 9377",
    "sg:postcode":"SW2 4RU",
    "sg:province":"Greater London",
    "wof:name":"Clarkes Travel Ltd.",
    "wof:placetype":"venue"
},
  "geometry": {"coordinates":[-0.126695,51.438816],"type":"Point"}
}