{
  "type": "Feature",
  "properties": {
    "iso:country":"GB",
    "sg:address":"20 Bayton Road, Exhall",
    "sg:city":"Coventry",
    "sg:classifiers":[
        {
            "category":"Manufacturing",
            "subcategory":"Metals",
            "type":"Manufacturing & Wholesale Goods"
        }
    ],
    "sg:phone":"+44 24 7636 0822",
    "sg:postcode":"CV7 9EJ",
    "sg:province":"Warwickshire",
    "sg:tags":[
        "work",
        "sheet"
    ],
    "wof:name":"Apollo Sheet Metal Products",
    "wof:placetype":"venue"
},
  "geometry": {"coordinates":[-1.478223,52.463402],"type":"Point"}
}