{
  "type": "Feature",
  "properties": {
    "iso:country":"GB",
    "sg:address":"17-19 Church Lane, Hanford",
    "sg:city":"Stoke-on-trent",
    "sg:classifiers":[
        {
            "category":"Home & Garden",
            "subcategory":"Building Materials",
            "type":"Retail Goods"
        }
    ],
    "sg:phone":"+44 1782 644165",
    "sg:postcode":"ST4 4QB",
    "sg:province":"Staffordshire",
    "sg:tags":[
        "gate",
        "door",
        "barrier"
    ],
    "wof:name":"Trentham Fencing & Contractors Ltd.",
    "wof:placetype":"venue"
},
  "geometry": {"coordinates":[-2.19881,52.981316],"type":"Point"}
}