{
  "type": "Feature",
  "properties": {
    "addr:full":"18 Melrose Avenue Nuneaton Warwickshire CV12 0ES",
    "addr:housenumber":"18",
    "addr:postcode":"cv12 0es",
    "addr:street":"Melrose Avenue",
    "iso:country":"GB",
    "sg:address":"18 Melrose Avenue",
    "sg:city":"Nuneaton",
    "sg:classifiers":[
        {
            "category":"Personal",
            "type":"Services"
        }
    ],
    "sg:phone":"+44 24 7636 6238",
    "sg:postcode":"CV12 0ES",
    "sg:province":"Warwickshire",
    "sg:tags":[
        "wedding"
    ],
    "wof:name":"Julia Dee Bridal Wear",
    "wof:placetype":"venue"
},
  "geometry": {"coordinates":[-1.5010999441,52.4699211121],"type":"Point"}
}