{
  "type": "Feature",
  "properties": {
    "addr:full":", Kings Meaburn Penrith Cumbria CA10 3BU",
    "addr:postcode":"ca10 3bu",
    "addr:street":"Penrith",
    "iso:country":"GB",
    "sg:address":", Kings Meaburn",
    "sg:city":"Penrith",
    "sg:classifiers":[
        {
            "category":"Government",
            "subcategory":"Post Office",
            "type":"Public Place"
        }
    ],
    "sg:phone":"+44 1931 714256",
    "sg:postcode":"CA10 3BU",
    "sg:province":"Cumbria",
    "wof:name":"Kings Meaburn P.O",
    "wof:placetype":"venue"
},
  "geometry": {"coordinates":[-2.6038589478,54.5196990967],"type":"Point"}
}