{
  "type": "Feature",
  "properties": {
    "addr:full":"27 Hamilton Road Motherwell North Lanarkshire ML1 3BY",
    "addr:housenumber":"27",
    "addr:postcode":"ml1 3by",
    "addr:street":"Hamilton Road",
    "iso:country":"GB",
    "sg:address":"27 Hamilton Road",
    "sg:city":"Motherwell",
    "sg:classifiers":[
        {
            "category":"Fast Food",
            "type":"Food & Drink"
        }
    ],
    "sg:phone":"+44 1698 266982",
    "sg:postcode":"ML1 3BY",
    "sg:province":"North Lanarkshire",
    "sg:tags":[
        "away",
        "take"
    ],
    "wof:name":"Marcantonio",
    "wof:placetype":"venue"
},
  "geometry": {"coordinates":[-3.994192,55.789673],"type":"Point"}
}