{
  "type": "Feature",
  "properties": {
    "iso:country":"GB",
    "sg:address":"1 Park Rd, Stapleton",
    "sg:city":"Bristol",
    "sg:classifiers":[
        {
            "category":"Shopping",
            "subcategory":"Florist",
            "type":"Retail Goods"
        }
    ],
    "sg:postcode":"BS16 1AZ",
    "sg:province":"City of Bristol",
    "wof:name":"Palmer,Kathleen,",
    "wof:placetype":"venue"
},
  "geometry": {"coordinates":[-2.555543,51.481503],"type":"Point"}
}