{
  "type": "Feature",
  "properties": {
    "addr:full":"65 Mere Green Rd Sutton Coldfield Staffordshire B75 5BY",
    "addr:housenumber":"65",
    "addr:postcode":"b75 5by",
    "addr:street":"Mere Green Rd",
    "iso:country":"GB",
    "sg:address":"65 Mere Green Rd",
    "sg:city":"Sutton Coldfield",
    "sg:classifiers":[
        {
            "category":"Manufacturing",
            "subcategory":"Glass & Minerals",
            "type":"Manufacturing & Wholesale Goods"
        }
    ],
    "sg:phone":"+44 1827 316288",
    "sg:postcode":"B75 5BY",
    "sg:province":"Staffordshire",
    "sg:tags":[
        "mnfr",
        "glassware",
        "china"
    ],
    "wof:name":"Lindrick Pottery Ltd",
    "wof:placetype":"venue"
},
  "geometry": {"coordinates":[-1.8234169483,52.58776474],"type":"Point"}
}