{
  "type": "Feature",
  "properties": {
    "addr:full":"2 Coxwold Gro Bolton Lancashire BL3 3NG",
    "addr:housenumber":"2",
    "addr:postcode":"bl3 3ng",
    "addr:street":"Coxwold Gro",
    "iso:country":"GB",
    "sg:address":"2 Coxwold Gro",
    "sg:city":"Bolton",
    "sg:classifiers":[
        {
            "category":"Communications",
            "type":"Services"
        }
    ],
    "sg:phone":"+44 1204 654363",
    "sg:postcode":"BL3 3NG",
    "sg:province":"Lancashire",
    "sg:tags":[
        "tv",
        "video",
        "radio"
    ],
    "wof:name":"Satalink",
    "wof:placetype":"venue"
},
  "geometry": {"coordinates":[-2.447824955,53.5591125488],"type":"Point"}
}