{
  "type": "Feature",
  "properties": {
    "addr:full":"Salisbury Street, Mere Warminster Somerset BA12 6HE",
    "addr:postcode":"ba12 6he",
    "addr:street":"Salisbury Street",
    "iso:country":"GB",
    "sg:address":"Salisbury Street, Mere",
    "sg:city":"Warminster",
    "sg:classifiers":[
        {
            "category":"Personal",
            "subcategory":"Beauty Salon",
            "type":"Services"
        }
    ],
    "sg:phone":"+44 1747 860535",
    "sg:postcode":"BA12 6HE",
    "sg:province":"Somerset",
    "sg:tags":[
        "lady",
        "hairdresser"
    ],
    "wof:name":"Georgian House Hair Salon",
    "wof:placetype":"venue"
},
  "geometry": {"coordinates":[-2.270170927,51.090511322],"type":"Point"}
}