{
  "type": "Feature",
  "properties": {
    "iso:country":"GB",
    "sg:address":"The Spark Centre, 42-48 Dove Road, Blaen-y-maes",
    "sg:city":"Swansea",
    "sg:classifiers":[
        {
            "category":"Education",
            "subcategory":"Library",
            "type":"Public Place"
        }
    ],
    "sg:phone":"+44 1792 583866",
    "sg:postcode":"SA5 5QD",
    "sg:province":"Swansea",
    "sg:tags":[
        "book"
    ],
    "wof:name":"Blaen-y-Maes Library",
    "wof:placetype":"venue"
},
  "geometry": {"coordinates":[-3.97663,51.65662],"type":"Point"}
}