{
  "type": "Feature",
  "properties": {
    "addr:full":"Neighbourhood Centre, Ffordd Llanarth Deeside Flintshire CH5 4UP",
    "addr:postcode":"ch5 4up",
    "addr:street":"Ffordd Llanarth",
    "iso:country":"GB",
    "sg:address":"Neighbourhood Centre, Ffordd Llanarth",
    "sg:city":"Deeside",
    "sg:classifiers":[
        {
            "category":"Shopping",
            "subcategory":"News",
            "type":"Retail Goods"
        }
    ],
    "sg:phone":"+44 1244 811456",
    "sg:postcode":"CH5 4UP",
    "sg:province":"Flintshire",
    "sg:tags":[
        "newsagent"
    ],
    "wof:name":"Deeview News",
    "wof:placetype":"venue"
},
  "geometry": {"coordinates":[-3.073089,53.213848],"type":"Point"}
}