{
  "type": "Feature",
  "properties": {
    "addr:full":"46 Suffolk Drive, Whiteley Fareham Hampshire PO15 7DH",
    "addr:housenumber":"46",
    "addr:postcode":"po15 7dh",
    "addr:street":"Suffolk Drive",
    "iso:country":"GB",
    "sg:address":"46 Suffolk Drive, Whiteley",
    "sg:city":"Fareham",
    "sg:classifiers":[
        {
            "category":"Health Services",
            "subcategory":"Hospital",
            "type":"Services"
        }
    ],
    "sg:postcode":"PO15 7DH",
    "sg:province":"Hampshire",
    "wof:name":"Broad Hospital Consultancy Ltd.",
    "wof:placetype":"venue"
},
  "geometry": {"coordinates":[-1.26232,50.882275],"type":"Point"}
}