{
  "type": "Feature",
  "properties": {
    "addr:full":"55 Greyfriars Stafford Staffordshire ST16 2RG",
    "addr:housenumber":"55",
    "addr:postcode":"st16 2rg",
    "addr:street":"Greyfriars",
    "iso:country":"GB",
    "sg:address":"55 Greyfriars",
    "sg:city":"Stafford",
    "sg:classifiers":[
        {
            "category":"Shopping",
            "subcategory":"Stationery & Office Supplies",
            "type":"Retail Goods"
        }
    ],
    "sg:phone":"+44 1785 242265",
    "sg:postcode":"ST16 2RG",
    "sg:province":"Staffordshire",
    "sg:tags":[
        "equipment"
    ],
    "wof:name":"Phillips Office Services",
    "wof:placetype":"venue"
},
  "geometry": {"coordinates":[-2.1231100559,52.8150215149],"type":"Point"}
}