{
  "type": "Feature",
  "properties": {
    "iso:country":"GB",
    "sg:address":"Roadways House, Holyhead Road, Ketley",
    "sg:city":"Telford",
    "sg:classifiers":[
        {
            "category":"Autos & Motor Vehicles",
            "subcategory":"Automobile Sales",
            "type":"Retail Goods"
        }
    ],
    "sg:phone":"+44 1952 246500",
    "sg:postcode":"TF1 5BY",
    "sg:province":"Shropshire",
    "sg:tags":[
        "car"
    ],
    "wof:name":"Shropshire Motor Services",
    "wof:placetype":"venue"
},
  "geometry": {"coordinates":[-2.472589,52.695866],"type":"Point"}
}