{
  "type": "Feature",
  "properties": {
    "iso:country":"GB",
    "sg:address":"St Georges Pier",
    "sg:city":"Menai Bridge",
    "sg:classifiers":[
        {
            "category":"Travel",
            "subcategory":"Hotels & Motels",
            "type":"Entertainment"
        }
    ],
    "sg:phone":"+44 1248 712453",
    "sg:postcode":"LL59 5EY",
    "sg:province":"Isle of Anglesey",
    "wof:name":"Liverpool Arms Hotel",
    "wof:placetype":"venue"
},
  "geometry": {"coordinates":[-4.161559,53.227612],"type":"Point"}
}