{
  "type": "Feature",
  "properties": {
    "iso:country":"GB",
    "sg:address":"The Firs, Braybrooke",
    "sg:city":"Market Harborough",
    "sg:classifiers":[
        {
            "category":"Farming",
            "subcategory":"Livestock Farm",
            "type":"Manufacturing & Wholesale Goods"
        }
    ],
    "sg:postcode":"LE16 8LS",
    "sg:province":"Leicestershire",
    "sg:tags":[
        "others"
    ],
    "wof:name":"Department for Environment, Food & Rural",
    "wof:placetype":"venue"
},
  "geometry": {"coordinates":[-0.908234,52.47242],"type":"Point"}
}