{
  "type": "Feature",
  "properties": {
    "iso:country":"GB",
    "sg:address":"2 Odcroft Close",
    "sg:city":"Chippenham",
    "sg:classifiers":[
        {
            "category":"Organizations",
            "subcategory":"Non-profit Organization",
            "type":"Services"
        }
    ],
    "sg:phone":"+44 1249 444425",
    "sg:postcode":"SN15 3SD",
    "sg:province":"Wiltshire",
    "sg:tags":[
        "charitable",
        "organisation",
        "voluntary",
        "charity"
    ],
    "wof:name":"THE STROKE ASSOCIATION",
    "wof:placetype":"venue"
},
  "geometry": {"coordinates":[-2.102014,51.459389],"type":"Point"}
}