{
  "type": "Feature",
  "properties": {
    "addr:full":"Highfield House, 269 Highfield Rd Bradford West Yorkshire BD10 8QY",
    "addr:housenumber":"269",
    "addr:postcode":"bd10 8qy",
    "addr:street":"Highfield Rd",
    "iso:country":"GB",
    "sg:address":"Highfield House, 269 Highfield Rd",
    "sg:city":"Bradford",
    "sg:classifiers":[
        {
            "category":"Wholesale",
            "subcategory":"Electrical",
            "type":"Manufacturing & Wholesale Goods"
        }
    ],
    "sg:phone":"+44 1274 703377",
    "sg:postcode":"BD10 8QY",
    "sg:province":"West Yorkshire",
    "sg:tags":[
        "equipment",
        "refrigeration"
    ],
    "wof:name":"Linton Systems",
    "wof:placetype":"venue"
},
  "geometry": {"coordinates":[-1.735215,53.83276],"type":"Point"}
}