{
  "type": "Feature",
  "properties": {
    "iso:country":"GB",
    "sg:address":"Care Of Mackays Stores Ltd",
    "sg:city":"Ayr",
    "sg:classifiers":[
        {
            "category":"Shopping",
            "subcategory":"Clothing, Apparel, & Fashions",
            "type":"Retail Goods"
        },
        {
            "category":"Shopping",
            "subcategory":"Shoes",
            "type":"Retail Goods"
        }
    ],
    "sg:phone":"+44 1292 263447",
    "sg:postcode":"KA7 1SH",
    "sg:province":"South Ayrshire",
    "sg:tags":[
        "shop"
    ],
    "wof:name":"Stead & Simpson",
    "wof:placetype":"venue"
},
  "geometry": {"coordinates":[-4.6292819977,55.4428710938],"type":"Point"}
}