{
  "type": "Feature",
  "properties": {
    "addr:full":"Mr D Schreiber, Rabin Leacock Lipman, 7-10 Chandos St London Greater London W1M 0LL",
    "addr:housenumber":"7-10",
    "addr:postcode":"w1m 0ll",
    "addr:street":"Mr;Lipman;Chandos St",
    "iso:country":"GB",
    "sg:address":"Mr D Schreiber, Rabin Leacock Lipman, 7-10 Chandos St",
    "sg:city":"London",
    "sg:classifiers":[
        {
            "category":"Banks & Credit Unions",
            "subcategory":"Financial Services",
            "type":"Services"
        }
    ],
    "sg:postcode":"W1M 0LL",
    "sg:province":"Greater London",
    "sg:tags":[
        "consultant"
    ],
    "wof:name":"Barnett Property & Investment Co Ltd",
    "wof:placetype":"venue"
},
  "geometry": {"coordinates":[-0.12714,51.506321],"type":"Point"}
}