{
  "type": "Feature",
  "properties": {
    "iso:country":"GB",
    "sg:address":"5 Mill Lane, Horton Cum Studley",
    "sg:city":"Oxford",
    "sg:classifiers":[
        {
            "category":"Utilities",
            "type":"Services"
        }
    ],
    "sg:phone":"+44 1865 358815",
    "sg:postcode":"OX33 1DH",
    "sg:province":"Buckinghamshire",
    "sg:tags":[
        "internet"
    ],
    "wof:name":"Oxford Strategic Ltd.",
    "wof:placetype":"venue"
},
  "geometry": {"coordinates":[-1.140308,51.80822],"type":"Point"}
}