{
  "type": "Feature",
  "properties": {
    "iso:country":"GB",
    "sg:address":"254 Horn St",
    "sg:city":"Folkestone",
    "sg:classifiers":[
        {
            "category":"Shopping",
            "subcategory":"News",
            "type":"Retail Goods"
        }
    ],
    "sg:phone":"+44 1303 275582",
    "sg:postcode":"CT19 4JR",
    "sg:province":"Kent",
    "sg:tags":[
        "newsagent"
    ],
    "wof:name":"Horn Street P.O",
    "wof:placetype":"venue"
},
  "geometry": {"coordinates":[1.12869,51.089207],"type":"Point"}
}