{
  "type": "Feature",
  "properties": {
    "addr:full":"20 St Andrews Street Droitwich Worcestershire WR9 8DY",
    "addr:housenumber":"20",
    "addr:postcode":"wr9 8dy",
    "addr:street":"St Andrews Street",
    "iso:country":"GB",
    "sg:address":"20 St Andrews Street",
    "sg:city":"Droitwich",
    "sg:classifiers":[
        {
            "category":"Insurance",
            "subcategory":"Insurance Agent",
            "type":"Services"
        }
    ],
    "sg:phone":"+44 1905 795599",
    "sg:postcode":"WR9 8DY",
    "sg:province":"Worcestershire",
    "sg:tags":[
        "broker"
    ],
    "wof:name":"Clarke Roxburgh Insurance Brokers Ltd.",
    "wof:placetype":"venue"
},
  "geometry": {"coordinates":[-2.148907,52.267899],"type":"Point"}
}