{
  "type": "Feature",
  "properties": {
    "addr:full":"The Meads, Burnt Oak Edgware Greater London HA8 9HQ",
    "addr:postcode":"ha8 9hq",
    "addr:street":"The Meads Burnt Oak",
    "iso:country":"GB",
    "sg:address":"The Meads, Burnt Oak",
    "sg:city":"Edgware",
    "sg:classifiers":[
        {
            "category":"Education",
            "subcategory":"School",
            "type":"Public Place"
        },
        {
            "category":"Government",
            "subcategory":"Office",
            "type":"Public Place"
        }
    ],
    "sg:phone":"+44 20 8906 0723",
    "sg:postcode":"HA8 9HQ",
    "sg:province":"Greater London",
    "sg:tags":[
        "local",
        "authority"
    ],
    "wof:name":"The Annunciation Junior School",
    "wof:placetype":"venue"
},
  "geometry": {"coordinates":[-0.256634,51.611698],"type":"Point"}
}