{
  "type": "Feature",
  "properties": {
    "addr:full":"22 Linden Close, Moulsham Lodge Chelmsford Essex CM2 9JQ",
    "addr:housenumber":"22",
    "addr:postcode":"cm2 9jq",
    "addr:street":"Linden Close",
    "iso:country":"GB",
    "sg:address":"22 Linden Close, Moulsham Lodge",
    "sg:city":"Chelmsford",
    "sg:classifiers":[
        {
            "category":"Personal",
            "type":"Services"
        }
    ],
    "sg:postcode":"CM2 9JQ",
    "sg:province":"Essex",
    "sg:tags":[
        "wedding"
    ],
    "wof:name":"Anne Blanchard Design",
    "wof:placetype":"venue"
},
  "geometry": {"coordinates":[0.478610009,51.719329834],"type":"Point"}
}