{
  "type": "Feature",
  "properties": {
    "iso:country":"GB",
    "sg:address":"17 Lipscombe Rise",
    "sg:city":"Alton",
    "sg:classifiers":[
        {
            "category":"Food & Beverages",
            "subcategory":"Groceries & Convenience Stores",
            "type":"Retail Goods"
        }
    ],
    "sg:phone":"+44 1420 82857",
    "sg:postcode":"GU34 2HR",
    "sg:province":"Hampshire",
    "wof:name":"Hilltop Stores",
    "wof:placetype":"venue"
},
  "geometry": {"coordinates":[-0.971853,51.156757],"type":"Point"}
}