{
  "type": "Feature",
  "properties": {
    "addr:full":"Dillotford Avenue Coventry Warwickshire CV3 5EA",
    "addr:postcode":"cv3 5ea",
    "addr:street":"Dillotford Avenue",
    "iso:country":"GB",
    "sg:address":"Dillotford Avenue",
    "sg:city":"Coventry",
    "sg:classifiers":[
        {
            "category":"Manufacturing",
            "subcategory":"Tools & Machinery",
            "type":"Manufacturing & Wholesale Goods"
        }
    ],
    "sg:phone":"+44 24 7641 3755",
    "sg:postcode":"CV3 5EA",
    "sg:province":"Warwickshire",
    "sg:tags":[
        "design",
        "maker"
    ],
    "wof:name":"Garforth & Goodman Ltd.",
    "wof:placetype":"venue"
},
  "geometry": {"coordinates":[-1.513047,52.391933],"type":"Point"}
}