{
  "type": "Feature",
  "properties": {
    "addr:full":"Rochester Ho, 5a High St Corsham Wiltshire SN13 0ES",
    "addr:housenumber":"5a",
    "addr:postcode":"sn13 0es",
    "addr:street":"High St",
    "iso:country":"GB",
    "sg:address":"Rochester Ho, 5a High St",
    "sg:city":"Corsham",
    "sg:classifiers":[
        {
            "category":"Professional",
            "type":"Services"
        }
    ],
    "sg:phone":"+44 1249 712512",
    "sg:postcode":"SN13 0ES",
    "sg:province":"Wiltshire",
    "sg:tags":[
        "repair",
        "tech",
        "maintenance"
    ],
    "wof:name":"Disctech Ltd",
    "wof:placetype":"venue"
},
  "geometry": {"coordinates":[-2.1872389317,51.4314842224],"type":"Point"}
}