{
  "type": "Feature",
  "properties": {
    "iso:country":"GB",
    "sg:address":"Unit 3, Portors Way",
    "sg:city":"Birmingham",
    "sg:classifiers":[
        {
            "category":"Building & Trades",
            "subcategory":"Construction",
            "type":"Services"
        }
    ],
    "sg:phone":"+44 121 772 0747",
    "sg:postcode":"B9 5RR",
    "sg:province":"West Midlands",
    "sg:tags":[
        "monumental",
        "mason"
    ],
    "wof:name":"Waterhouse & Co",
    "wof:placetype":"venue"
},
  "geometry": {"coordinates":[-1.8487039804,52.4776191711],"type":"Point"}
}