{
  "type": "Feature",
  "properties": {
    "iso:country":"GB",
    "sg:address":"Wray House, Station Road",
    "sg:city":"Hull",
    "sg:classifiers":[
        {
            "category":"Farming",
            "subcategory":"Farm",
            "type":"Manufacturing & Wholesale Goods"
        }
    ],
    "sg:phone":"+44 1964 622365",
    "sg:postcode":"HU12 9SZ",
    "sg:province":"East Riding of Yorkshire",
    "sg:tags":[
        "mixed",
        "crop"
    ],
    "wof:name":"P Westmorland & Son",
    "wof:placetype":"venue"
},
  "geometry": {"coordinates":[-0.141027,53.730579],"type":"Point"}
}