{
  "type": "Feature",
  "properties": {
    "addr:full":"7 Long Sleets, Broadmeads Alfreton Derbyshire DE55 3AY",
    "addr:housenumber":"7",
    "addr:postcode":"de55 3ay",
    "addr:street":"Long Sleets Broadmeads",
    "iso:country":"GB",
    "sg:address":"7 Long Sleets, Broadmeads",
    "sg:city":"Alfreton",
    "sg:classifiers":[
        {
            "category":"Professional",
            "subcategory":"Engineering",
            "type":"Services"
        }
    ],
    "sg:phone":"+44 1773 861696",
    "sg:postcode":"DE55 3AY",
    "sg:province":"Derbyshire",
    "sg:tags":[
        "contractor",
        "electrical",
        "engineer"
    ],
    "wof:name":"M P S Electrical",
    "wof:placetype":"venue"
},
  "geometry": {"coordinates":[-1.329728961,53.0968093872],"type":"Point"}
}