{
  "type": "Feature",
  "properties": {
    "addr:full":"18 High St Northwood Greater London HA6 1BN",
    "addr:housenumber":"18",
    "addr:postcode":"ha6 1bn",
    "addr:street":"High St",
    "iso:country":"GB",
    "sg:address":"18 High St",
    "sg:city":"Northwood",
    "sg:classifiers":[
        {
            "category":"Personal",
            "subcategory":"Nail Salon",
            "type":"Services"
        }
    ],
    "sg:phone":"+44 1923 836471",
    "sg:postcode":"HA6 1BN",
    "sg:province":"Greater London",
    "sg:tags":[
        "technician"
    ],
    "wof:name":"Oceans Nail And Beauty Salon",
    "wof:placetype":"venue"
},
  "geometry": {"coordinates":[-0.4171809852,51.605381012],"type":"Point"}
}