{
  "type": "Feature",
  "properties": {
    "iso:country":"GB",
    "sg:address":"Ingol Lane, Hambleton",
    "sg:city":"Poulton-le-fylde",
    "sg:classifiers":[
        {
            "category":"Transit Center",
            "subcategory":"Passenger",
            "type":"Transportation"
        }
    ],
    "sg:phone":"+44 1253 700597",
    "sg:postcode":"FY6 9BJ",
    "sg:province":"Lancashire",
    "sg:tags":[
        "boarding",
        "kennel",
        "catteries"
    ],
    "wof:name":"Ingol Lodge Boarding Kennels & Cattery",
    "wof:placetype":"venue"
},
  "geometry": {"coordinates":[-2.957199,53.874603],"type":"Point"}
}