{
  "type": "Feature",
  "properties": {
    "iso:country":"GB",
    "sg:address":"112 Maxwell Avenue, Bearsden",
    "sg:city":"Glasgow",
    "sg:classifiers":[
        {
            "category":"Building & Trades",
            "subcategory":"Plumbing",
            "type":"Services"
        }
    ],
    "sg:phone":"+44 141 943 0017",
    "sg:postcode":"G61 1HU",
    "sg:province":"East Dunbartonshire",
    "sg:tags":[
        "central",
        "heating"
    ],
    "wof:name":"William Smith",
    "wof:placetype":"venue"
},
  "geometry": {"coordinates":[-4.335337,55.905148],"type":"Point"}
}