{
  "type": "Feature",
  "properties": {
    "iso:country":"GB",
    "sg:address":"6 Coniston Avenue, Little Hulton",
    "sg:city":"Manchester",
    "sg:classifiers":[
        {
            "category":"Shopping",
            "subcategory":"Pharmacy",
            "type":"Retail Goods"
        }
    ],
    "sg:phone":"+44 161 702 0135",
    "sg:postcode":"M38 9WX",
    "sg:province":"Greater Manchester",
    "sg:tags":[
        "pharmacist",
        "dispensing",
        "chemist"
    ],
    "wof:name":"Tims & Parker Ltd.",
    "wof:placetype":"venue"
},
  "geometry": {"coordinates":[-2.4208090305,53.5337753296],"type":"Point"}
}