{
  "type": "Feature",
  "properties": {
    "iso:country":"GB",
    "sg:address":"29a Main Street",
    "sg:city":"Oakham",
    "sg:classifiers":[
        {
            "category":"Farming",
            "subcategory":"Fish & Marine Products",
            "type":"Manufacturing & Wholesale Goods"
        }
    ],
    "sg:phone":"+44 1572 823110",
    "sg:postcode":"LE15 9LR",
    "sg:province":"Leicestershire",
    "sg:tags":[
        "fishmonger"
    ],
    "wof:name":"The Barn Store",
    "wof:placetype":"venue"
},
  "geometry": {"coordinates":[-0.710095,52.562969],"type":"Point"}
}