{
  "type": "Feature",
  "properties": {
    "addr:full":"288 High Street West Bromwich West Midlands B70 8AQ",
    "addr:housenumber":"288",
    "addr:postcode":"b70 8aq",
    "addr:street":"High Street",
    "iso:country":"GB",
    "sg:address":"288 High Street",
    "sg:city":"West Bromwich",
    "sg:classifiers":[
        {
            "category":"Real Estate",
            "subcategory":"Real Estate Agent",
            "type":"Services"
        }
    ],
    "sg:phone":"+44 121 525 1177",
    "sg:postcode":"B70 8AQ",
    "sg:province":"West Midlands",
    "wof:name":"CONNELL ESTATE AGENTS",
    "wof:placetype":"venue"
},
  "geometry": {"coordinates":[-1.995659,52.519421],"type":"Point"}
}