{
  "type": "Feature",
  "properties": {
    "iso:country":"GB",
    "sg:address":"Mashobra, Coach Road, Kilsyth",
    "sg:city":"Glasgow",
    "sg:classifiers":[
        {
            "category":"Travel",
            "subcategory":"Hotels & Motels",
            "type":"Entertainment"
        }
    ],
    "sg:postcode":"G65 0PR",
    "sg:province":"East Dunbartonshire",
    "sg:tags":[
        "house",
        "guest"
    ],
    "wof:name":"Molly Dunlop",
    "wof:placetype":"venue"
},
  "geometry": {"coordinates":[-4.058848,55.978645],"type":"Point"}
}