{
  "type": "Feature",
  "properties": {
    "addr:full":"4 Holborn Place, Colebrook Village Plymouth Devon PL7 4AD",
    "addr:housenumber":"4",
    "addr:postcode":"pl7 4ad",
    "addr:street":"Holborn Place Colebrook Village",
    "iso:country":"GB",
    "sg:address":"4 Holborn Place, Colebrook Village",
    "sg:city":"Plymouth",
    "sg:classifiers":[
        {
            "category":"Shopping",
            "subcategory":"Gifts & Souvenirs",
            "type":"Retail Goods"
        }
    ],
    "sg:postcode":"PL7 4AD",
    "sg:province":"Devon",
    "sg:tags":[
        "shop"
    ],
    "wof:name":"Ideas",
    "wof:placetype":"venue"
},
  "geometry": {"coordinates":[-4.054666,50.39238],"type":"Point"}
}