{
  "type": "Feature",
  "properties": {
    "addr:full":"3 Arthur Street, Clarkston Glasgow East Renfrewshire G76 8BQ",
    "addr:housenumber":"3",
    "addr:postcode":"g76 8bq",
    "addr:street":"Arthur Street",
    "iso:country":"GB",
    "sg:address":"3 Arthur Street, Clarkston",
    "sg:city":"Glasgow",
    "sg:classifiers":[
        {
            "category":"Real Estate",
            "subcategory":"Developer",
            "type":"Services"
        },
        {
            "category":"Building & Trades",
            "subcategory":"Construction",
            "type":"Services"
        }
    ],
    "sg:phone":"+44 141 644 2223",
    "sg:postcode":"G76 8BQ",
    "sg:province":"East Renfrewshire",
    "sg:tags":[
        "residential",
        "builder",
        "property"
    ],
    "wof:name":"Westpoint Homes Ltd",
    "wof:placetype":"venue"
},
  "geometry": {"coordinates":[-4.27322,55.785259],"type":"Point"}
}