{
  "type": "Feature",
  "properties": {
    "addr:full":"River House, Suggs Lane, Broadway Ilminster Somerset TA19 9RJ",
    "addr:postcode":"ta19 9rj",
    "addr:street":"Suggs Lane",
    "iso:country":"GB",
    "sg:address":"River House, Suggs Lane, Broadway",
    "sg:city":"Ilminster",
    "sg:classifiers":[
        {
            "category":"Building & Trades",
            "subcategory":"Construction",
            "type":"Services"
        }
    ],
    "sg:phone":"+44 1460 53884",
    "sg:postcode":"TA19 9RJ",
    "sg:province":"Somerset",
    "sg:tags":[
        "builder"
    ],
    "wof:name":"Hawgate Ltd",
    "wof:placetype":"venue"
},
  "geometry": {"coordinates":[-2.9594700336,50.9355278015],"type":"Point"}
}