{
  "type": "Feature",
  "properties": {
    "addr:full":"217-219 New London Road Chelmsford Essex CM2 0AJ",
    "addr:housenumber":"217-219",
    "addr:postcode":"cm2 0aj",
    "addr:street":"New London Road",
    "iso:country":"GB",
    "sg:address":"217-219 New London Road",
    "sg:city":"Chelmsford",
    "sg:classifiers":[
        {
            "category":"Travel",
            "subcategory":"Hotels & Motels",
            "type":"Entertainment"
        }
    ],
    "sg:phone":"+44 1245 354295",
    "sg:postcode":"CM2 0AJ",
    "sg:province":"Essex",
    "wof:name":"Tanunda Hotel",
    "wof:placetype":"venue"
},
  "geometry": {"coordinates":[0.46202,51.725342],"type":"Point"}
}