{
  "type": "Feature",
  "properties": {
    "addr:full":"100 Yardley Wood Rd Birmingham West Midlands B13 9JD",
    "addr:housenumber":"100",
    "addr:postcode":"b13 9jd",
    "addr:street":"Yardley Wood Rd",
    "iso:country":"GB",
    "sg:address":"100 Yardley Wood Rd",
    "sg:city":"Birmingham",
    "sg:classifiers":[
        {
            "category":"Social Services",
            "subcategory":"Retirement Home",
            "type":"Services"
        }
    ],
    "sg:phone":"+44 121 442 2273",
    "sg:postcode":"B13 9JD",
    "sg:province":"West Midlands",
    "sg:tags":[
        "residential",
        "care"
    ],
    "wof:name":"Lyndon House",
    "wof:placetype":"venue"
},
  "geometry": {"coordinates":[-1.8715569973,52.4470252991],"type":"Point"}
}