{
  "type": "Feature",
  "properties": {
    "addr:full":"Invincible Works, Woodend Avenue Liverpool Merseyside L24 9NB",
    "addr:postcode":"l24 9nb",
    "addr:street":"Woodend Avenue",
    "iso:country":"GB",
    "sg:address":"Invincible Works, Woodend Avenue",
    "sg:city":"Liverpool",
    "sg:classifiers":[
        {
            "category":"Shopping",
            "type":"Retail Goods"
        }
    ],
    "sg:phone":"+44 151 486 6362",
    "sg:postcode":"L24 9NB",
    "sg:province":"Merseyside",
    "sg:tags":[
        "merchant"
    ],
    "wof:name":"B Tickle & Sons Ltd.",
    "wof:placetype":"venue"
},
  "geometry": {"coordinates":[-2.8557100296,53.3576507568],"type":"Point"}
}