{
  "type": "Feature",
  "properties": {
    "addr:full":"30 Pine Grove, Brookmans Park Hatfield Hertfordshire AL9 7BS",
    "addr:housenumber":"30",
    "addr:postcode":"al9 7bs",
    "addr:street":"Pine Grove",
    "iso:country":"GB",
    "sg:address":"30 Pine Grove, Brookmans Park",
    "sg:city":"Hatfield",
    "sg:classifiers":[
        {
            "category":"Shopping",
            "subcategory":"Photographic Equipment",
            "type":"Retail Goods"
        }
    ],
    "sg:phone":"+44 1707 651539",
    "sg:postcode":"AL9 7BS",
    "sg:province":"Hertfordshire",
    "wof:name":"Point Blank Shooting",
    "wof:placetype":"venue"
},
  "geometry": {"coordinates":[-0.1792889982,51.7252693176],"type":"Point"}
}