{
  "type": "Feature",
  "properties": {
    "iso:country":"GB",
    "sg:address":"130 High St",
    "sg:city":"Tewkesbury",
    "sg:classifiers":[
        {
            "category":"Personal",
            "subcategory":"Beauty Salon",
            "type":"Services"
        }
    ],
    "sg:phone":"+44 1684 850852",
    "sg:postcode":"GL20 5JR",
    "sg:province":"Gloucestershire",
    "sg:tags":[
        "unisex",
        "hairdresser"
    ],
    "wof:name":"James Hairdressing",
    "wof:placetype":"venue"
},
  "geometry": {"coordinates":[-2.156968,51.993671],"type":"Point"}
}