{
  "type": "Feature",
  "properties": {
    "iso:country":"GB",
    "sg:address":"Janton House, Clifton Road, Bowers Gifford",
    "sg:city":"Basildon",
    "sg:classifiers":[
        {
            "category":"Building & Trades",
            "subcategory":"Construction",
            "type":"Services"
        }
    ],
    "sg:phone":"+44 1268 728128",
    "sg:postcode":"SS13 2LF",
    "sg:province":"Essex",
    "sg:tags":[
        "builder"
    ],
    "wof:name":"Janton Building & Double Glazing Ltd.",
    "wof:placetype":"venue"
},
  "geometry": {"coordinates":[0.5358300209,51.576789856],"type":"Point"}
}