{
  "type": "Feature",
  "properties": {
    "addr:full":"Fron Dorddu, Llanwrthwl Llandrindod Wells Powys LD1 6NY",
    "addr:postcode":"ld1 6ny",
    "addr:street":"Llandrindod Wells",
    "iso:country":"GB",
    "sg:address":"Fron Dorddu, Llanwrthwl",
    "sg:city":"Llandrindod Wells",
    "sg:classifiers":[
        {
            "category":"Farming",
            "subcategory":"Farm",
            "type":"Manufacturing & Wholesale Goods"
        }
    ],
    "sg:phone":"+44 1597 810083",
    "sg:postcode":"LD1 6NY",
    "sg:province":"Powys",
    "sg:tags":[
        "mixed",
        "crop"
    ],
    "wof:name":"I M Lewis & Sons",
    "wof:placetype":"venue"
},
  "geometry": {"coordinates":[-3.501713,52.263504],"type":"Point"}
}