{
  "type": "Feature",
  "properties": {
    "iso:country":"GB",
    "sg:address":"3 Bow Street",
    "sg:city":"Rugeley",
    "sg:classifiers":[
        {
            "category":"Home & Garden",
            "subcategory":"Home Furnishings",
            "type":"Retail Goods"
        }
    ],
    "sg:phone":"+44 1889 579044",
    "sg:postcode":"WS15 2BT",
    "sg:province":"Staffordshire",
    "sg:tags":[
        "blind",
        "curtain",
        "fitting"
    ],
    "wof:name":"Fairway Curtains",
    "wof:placetype":"venue"
},
  "geometry": {"coordinates":[-1.937101,52.760616],"type":"Point"}
}