{
  "type": "Feature",
  "properties": {
    "addr:full":"Ablington House, Ablington, Bibury Cirencester Gloucestershire GL7 5NU",
    "addr:postcode":"gl7 5nu",
    "addr:street":"Ablington",
    "iso:country":"GB",
    "sg:address":"Ablington House, Ablington, Bibury",
    "sg:city":"Cirencester",
    "sg:classifiers":[
        {
            "category":"Farming",
            "subcategory":"Farm",
            "type":"Manufacturing & Wholesale Goods"
        }
    ],
    "sg:postcode":"GL7 5NU",
    "sg:province":"Gloucestershire",
    "sg:tags":[
        "mixed",
        "crop"
    ],
    "wof:name":"A M  Mason",
    "wof:placetype":"venue"
},
  "geometry": {"coordinates":[-1.8480299711,51.7677001953],"type":"Point"}
}