{
  "type": "Feature",
  "properties": {
    "addr:full":"146 Queens Drive Liverpool Merseyside L13 0AL",
    "addr:housenumber":"146",
    "addr:postcode":"l13 0al",
    "addr:street":"Queens Drive",
    "iso:country":"GB",
    "sg:address":"146 Queens Drive",
    "sg:city":"Liverpool",
    "sg:classifiers":[
        {
            "category":"Professional",
            "subcategory":"Lawyer & Legal Services",
            "type":"Services"
        }
    ],
    "sg:postcode":"L13 0AL",
    "sg:province":"Merseyside",
    "sg:tags":[
        "solicitor"
    ],
    "wof:name":"Dooley & Co.",
    "wof:placetype":"venue"
},
  "geometry": {"coordinates":[-2.915249,53.424],"type":"Point"}
}