{
  "type": "Feature",
  "properties": {
    "addr:full":"Unit 4, Colndale Rd, Colnbrook Slough Berkshire SL3 0HQ",
    "addr:housenumber":"unit 4",
    "addr:postcode":"sl3 0hq",
    "addr:street":"Colndale Rd",
    "iso:country":"GB",
    "sg:address":"Unit 4, Colndale Rd, Colnbrook",
    "sg:city":"Slough",
    "sg:classifiers":[
        {
            "category":"Freight",
            "type":"Transportation"
        }
    ],
    "sg:phone":"+44 1753 689333",
    "sg:postcode":"SL3 0HQ",
    "sg:province":"Berkshire",
    "sg:tags":[
        "forwarders"
    ],
    "wof:name":"Woodland International Transport Co Ltd",
    "wof:placetype":"venue"
},
  "geometry": {"coordinates":[-0.5160400271,51.4761962891],"type":"Point"}
}