{
  "type": "Feature",
  "properties": {
    "addr:full":"Hawthorne House, Merrial St Newcastle Staffordshire ST5 2AW",
    "addr:postcode":"st5 2aw",
    "addr:street":"Merrial St",
    "iso:country":"GB",
    "sg:address":"Hawthorne House, Merrial St",
    "sg:city":"Newcastle",
    "sg:classifiers":[
        {
            "category":"Organizations",
            "subcategory":"Political Organization",
            "type":"Services"
        }
    ],
    "sg:phone":"+44 1782 619438",
    "sg:postcode":"ST5 2AW",
    "sg:province":"Staffordshire",
    "sg:tags":[
        "party"
    ],
    "wof:name":"Newcastle-under-lyme Conservative Association",
    "wof:placetype":"venue"
},
  "geometry": {"coordinates":[-2.2260789871,53.0129966736],"type":"Point"}
}