{
  "type": "Feature",
  "properties": {
    "iso:country":"GB",
    "sg:address":"Birmingham Road, Allesley",
    "sg:city":"Coventry",
    "sg:classifiers":[
        {
            "category":"Autos & Motor Vehicles",
            "subcategory":"Automobile Sales",
            "type":"Retail Goods"
        }
    ],
    "sg:phone":"+44 24 7640 7272",
    "sg:postcode":"CV5 9GY",
    "sg:province":"West Midlands",
    "sg:tags":[
        "commercial"
    ],
    "wof:name":"Shire Landrover",
    "wof:placetype":"venue"
},
  "geometry": {"coordinates":[-1.56447,52.424362],"type":"Point"}
}