{
  "type": "Feature",
  "properties": {
    "addr:full":"55 Spring Gardens Manchester Greater Manchester M2 2BY",
    "addr:housenumber":"55",
    "addr:postcode":"m2 2by",
    "addr:street":"Spring Gardens",
    "iso:country":"GB",
    "sg:address":"55 Spring Gardens",
    "sg:city":"Manchester",
    "sg:classifiers":[
        {
            "category":"Professional",
            "subcategory":"Employment Agencies",
            "type":"Services"
        }
    ],
    "sg:phone":"+44 161 228 6168",
    "sg:postcode":"M2 2BY",
    "sg:province":"Greater Manchester",
    "sg:tags":[
        "consultant",
        "recruitment"
    ],
    "wof:name":"Brook Street",
    "wof:placetype":"venue"
},
  "geometry": {"coordinates":[-2.241214,53.48016],"type":"Point"}
}