{
  "type": "Feature",
  "properties": {
    "iso:country":"GB",
    "sg:address":"Hill Farm, Earl Shilton Road, Thurlaston",
    "sg:city":"Leicester",
    "sg:classifiers":[
        {
            "category":"Farming",
            "subcategory":"Farm",
            "type":"Manufacturing & Wholesale Goods"
        }
    ],
    "sg:phone":"+44 1455 888374",
    "sg:postcode":"LE9 7TA",
    "sg:province":"Leicestershire",
    "sg:tags":[
        "mixed",
        "crop"
    ],
    "wof:name":"Mark Adrian Garner",
    "wof:placetype":"venue"
},
  "geometry": {"coordinates":[-1.259144,52.587101],"type":"Point"}
}