{
  "type": "Feature",
  "properties": {
    "iso:country":"GB",
    "sg:address":"16 Ringwood Rd",
    "sg:city":"Poole",
    "sg:classifiers":[
        {
            "category":"Manufacturing",
            "subcategory":"Petroleum Products",
            "type":"Manufacturing & Wholesale Goods"
        }
    ],
    "sg:postcode":"BH14 0RL",
    "sg:province":"Dorset",
    "sg:tags":[
        "double",
        "glazing"
    ],
    "wof:name":"Eurohome (U K) Ltd",
    "wof:placetype":"venue"
},
  "geometry": {"coordinates":[-1.9661890268,50.7258148193],"type":"Point"}
}