{
  "type": "Feature",
  "properties": {
    "iso:country":"GB",
    "sg:address":"Castleloch, Dundas",
    "sg:city":"South Queensferry",
    "sg:classifiers":[
        {
            "category":"Professional",
            "subcategory":"Management & Consulting",
            "type":"Services"
        }
    ],
    "sg:postcode":"EH30 9SP",
    "sg:province":"City of Edinburgh",
    "sg:tags":[
        "consultant",
        "business"
    ],
    "wof:name":"Consultancy Training Matters",
    "wof:placetype":"venue"
},
  "geometry": {"coordinates":[-3.396754,55.990383],"type":"Point"}
}