{
  "type": "Feature",
  "properties": {
    "iso:country":"GB",
    "sg:address":"Unit 2 Morgan Building",
    "sg:city":"Presteigne",
    "sg:classifiers":[
        {
            "category":"Autos & Motor Vehicles",
            "subcategory":"Auto Supplies",
            "type":"Retail Goods"
        }
    ],
    "sg:phone":"+44 1544 267240",
    "sg:postcode":"LD8 2UF",
    "sg:province":"Herefordshire",
    "sg:tags":[
        "tyre"
    ],
    "wof:name":"Presteigne Tyre Services",
    "wof:placetype":"venue"
},
  "geometry": {"coordinates":[-3.004454,52.270206],"type":"Point"}
}