{
  "type": "Feature",
  "properties": {
    "iso:country":"GB",
    "sg:address":"Golf Links Est, Fleming Rd",
    "sg:city":"Southall",
    "sg:classifiers":[
        {
            "category":"Government",
            "subcategory":"Office",
            "type":"Public Place"
        }
    ],
    "sg:phone":"+44 20 8571 1282",
    "sg:postcode":"UB1 3LP",
    "sg:province":"Greater London",
    "sg:tags":[
        "local"
    ],
    "wof:name":"Southall Area Housing",
    "wof:placetype":"venue"
},
  "geometry": {"coordinates":[-0.3783339858,51.5113792419],"type":"Point"}
}