{
  "type": "Feature",
  "properties": {
    "iso:country":"GB",
    "sg:address":"210 Victoria Avenue, Higher Blackley",
    "sg:city":"Manchester",
    "sg:classifiers":[
        {
            "category":"Retail",
            "subcategory":"Auto Repair",
            "type":"Services"
        }
    ],
    "sg:phone":"+44 161 795 7621",
    "sg:postcode":"M9 0RR",
    "sg:province":"Greater Manchester",
    "sg:tags":[
        "electrical",
        "centre"
    ],
    "wof:name":"John Young Auto Electrics",
    "wof:placetype":"venue"
},
  "geometry": {"coordinates":[-2.224795,53.53363],"type":"Point"}
}