{
  "type": "Feature",
  "properties": {
    "addr:full":"Purbeck Lodge, Lyonsgate Dorchester Dorset DT2 7AZ",
    "addr:postcode":"dt2 7az",
    "addr:street":"Lyonsgate",
    "iso:country":"GB",
    "sg:address":"Purbeck Lodge, Lyonsgate",
    "sg:city":"Dorchester",
    "sg:classifiers":[
        {
            "category":"Professional",
            "subcategory":"Management & Consulting",
            "type":"Services"
        }
    ],
    "sg:postcode":"DT2 7AZ",
    "sg:province":"Dorset",
    "sg:tags":[
        "consultant",
        "business"
    ],
    "wof:name":"Pearch Ltd.",
    "wof:placetype":"venue"
},
  "geometry": {"coordinates":[-2.4835000038,50.8514289856],"type":"Point"}
}