{
  "type": "Feature",
  "properties": {
    "addr:full":"Suite 1 Harrison Pk, 39 West Bryson Rd Edinburgh City of Edinburgh EH11 1BQ",
    "addr:housenumber":"suite 1",
    "addr:postcode":"eh11 1bq",
    "addr:street":"Harrison Pk 39 West Bryson Rd",
    "iso:country":"GB",
    "sg:address":"Suite 1 Harrison Pk, 39 West Bryson Rd",
    "sg:city":"Edinburgh",
    "sg:classifiers":[
        {
            "category":"Professional",
            "type":"Services"
        }
    ],
    "sg:postcode":"EH11 1BQ",
    "sg:province":"City of Edinburgh",
    "sg:tags":[
        "entertainer"
    ],
    "wof:name":"Sporting Connections",
    "wof:placetype":"venue"
},
  "geometry": {"coordinates":[-3.22442,55.93718],"type":"Point"}
}