{
  "type": "Feature",
  "properties": {
    "iso:country":"GB",
    "sg:address":"21 Joy Street",
    "sg:city":"Barnstaple",
    "sg:classifiers":[
        {
            "category":"Professional",
            "subcategory":"Accounting & Tax Preparation",
            "type":"Services"
        }
    ],
    "sg:phone":"+44 1271 342282",
    "sg:postcode":"EX31 1BS",
    "sg:province":"Devon",
    "sg:tags":[
        "accountant"
    ],
    "wof:name":"Simpkins Edwards",
    "wof:placetype":"venue"
},
  "geometry": {"coordinates":[-4.059421,51.081257],"type":"Point"}
}