{
  "type": "Feature",
  "properties": {
    "addr:full":"58 Balby Road Doncaster South Yorkshire DN4 0JL",
    "addr:housenumber":"58",
    "addr:postcode":"dn4 0jl",
    "addr:street":"Balby Road",
    "iso:country":"GB",
    "sg:address":"58 Balby Road",
    "sg:city":"Doncaster",
    "sg:classifiers":[
        {
            "category":"Insurance",
            "subcategory":"Insurance Agent",
            "type":"Services"
        }
    ],
    "sg:phone":"+44 1302 326340",
    "sg:postcode":"DN4 0JL",
    "sg:province":"South Yorkshire",
    "wof:name":"J M Fox Insurances",
    "wof:placetype":"venue"
},
  "geometry": {"coordinates":[-1.1407339573,53.5135879517],"type":"Point"}
}