{
  "type": "Feature",
  "properties": {
    "iso:country":"GB",
    "sg:address":"364 Brockley Road",
    "sg:city":"London",
    "sg:classifiers":[
        {
            "category":"Shopping",
            "subcategory":"Baby Store",
            "type":"Retail Goods"
        }
    ],
    "sg:phone":"+44 20 8692 3834",
    "sg:postcode":"SE4 2BY",
    "sg:province":"Greater London",
    "sg:tags":[
        "nursery",
        "accessory"
    ],
    "wof:name":"The Baby Centre",
    "wof:placetype":"venue"
},
  "geometry": {"coordinates":[-0.037477,51.454727],"type":"Point"}
}