{
  "type": "Feature",
  "properties": {
    "addr:full":"Ball Mill Bungalow, Main Road, Hallow Worcester Worcestershire WR2 6LS",
    "addr:postcode":"wr2 6ls",
    "addr:street":"Ball;Main Road",
    "iso:country":"GB",
    "sg:address":"Ball Mill Bungalow, Main Road, Hallow",
    "sg:city":"Worcester",
    "sg:classifiers":[
        {
            "category":"Building & Trades",
            "subcategory":"Landscaping Services",
            "type":"Services"
        }
    ],
    "sg:postcode":"WR2 6LS",
    "sg:province":"Worcestershire",
    "sg:tags":[
        "forestry",
        "tree"
    ],
    "wof:name":"E H Owen",
    "wof:placetype":"venue"
},
  "geometry": {"coordinates":[-2.2562389374,52.2265815735],"type":"Point"}
}