{
  "type": "Feature",
  "properties": {
    "iso:country":"GB",
    "sg:address":"Pasford House Chesterton Road, Pattingham",
    "sg:city":"Wolverhampton",
    "sg:classifiers":[
        {
            "category":"Military Area",
            "subcategory":"Air Force Base",
            "type":"Public Place"
        }
    ],
    "sg:phone":"+44 1902 700456",
    "sg:postcode":"WV6 7DZ",
    "sg:province":"Shropshire",
    "sg:tags":[
        "water",
        "treatment"
    ],
    "wof:name":"D A Baldwin",
    "wof:placetype":"venue"
},
  "geometry": {"coordinates":[-2.270574,52.586155],"type":"Point"}
}