{
  "type": "Feature",
  "properties": {
    "addr:full":"3 Marsh Lane Parade, Stafford Road Wolverhampton Staffordshire WV10 6RT",
    "addr:housenumber":"3",
    "addr:postcode":"wv10 6rt",
    "addr:street":"Marsh Lane Parade Stafford Road",
    "iso:country":"GB",
    "sg:address":"3 Marsh Lane Parade, Stafford Road",
    "sg:city":"Wolverhampton",
    "sg:classifiers":[
        {
            "category":"Food & Beverages",
            "subcategory":"Bakery",
            "type":"Retail Goods"
        }
    ],
    "sg:phone":"+44 1902 781005",
    "sg:postcode":"WV10 6RT",
    "sg:province":"Staffordshire",
    "sg:tags":[
        "baker"
    ],
    "wof:name":"Truffels Bakery",
    "wof:placetype":"venue"
},
  "geometry": {"coordinates":[-2.13076,52.621246],"type":"Point"}
}