{
  "type": "Feature",
  "properties": {
    "iso:country":"GB",
    "sg:address":"134 Main St",
    "sg:city":"Derby",
    "sg:classifiers":[
        {
            "category":"Shopping",
            "subcategory":"Stationery & Office Supplies",
            "type":"Retail Goods"
        }
    ],
    "sg:phone":"+44 1283 703259",
    "sg:postcode":"DE65 6FB",
    "sg:province":"Derbyshire",
    "sg:tags":[
        "equipment",
        "school"
    ],
    "wof:name":"Consolidata",
    "wof:placetype":"venue"
},
  "geometry": {"coordinates":[-1.5404,52.828426],"type":"Point"}
}