{
  "type": "Feature",
  "properties": {
    "addr:full":"3 Orchard Gro Kilmacolm Inverclyde PA13 4HQ",
    "addr:housenumber":"3",
    "addr:postcode":"pa13 4hq",
    "addr:street":"Orchard Gro",
    "iso:country":"GB",
    "sg:address":"3 Orchard Gro",
    "sg:city":"Kilmacolm",
    "sg:classifiers":[
        {
            "category":"Building & Trades",
            "subcategory":"Plumbing",
            "type":"Services"
        }
    ],
    "sg:phone":"+44 1505 874384",
    "sg:postcode":"PA13 4HQ",
    "sg:province":"Inverclyde",
    "sg:tags":[
        "central",
        "heating"
    ],
    "wof:name":"Gas Man Ltd",
    "wof:placetype":"venue"
},
  "geometry": {"coordinates":[-4.6333217621,55.8939704895],"type":"Point"}
}