{
  "type": "Feature",
  "properties": {
    "addr:full":"550 Streetsbrook Rd Birmingham West Midlands B91 1QT",
    "addr:housenumber":"550",
    "addr:postcode":"b91 1qt",
    "addr:street":"Streetsbrook Rd",
    "iso:country":"GB",
    "sg:address":"550 Streetsbrook Rd",
    "sg:city":"Birmingham",
    "sg:classifiers":[
        {
            "category":"Government",
            "subcategory":"Office",
            "type":"Public Place"
        }
    ],
    "sg:phone":"+44 121 711 2324",
    "sg:postcode":"B91 1QT",
    "sg:province":"West Midlands",
    "sg:tags":[
        "central"
    ],
    "wof:name":"Environment Agency",
    "wof:placetype":"venue"
},
  "geometry": {"coordinates":[-1.80143,52.416611],"type":"Point"}
}