{
  "type": "Feature",
  "properties": {
    "addr:full":"98 Flixton Road, Urmston Manchester Cheshire M41 5AL",
    "addr:housenumber":"98",
    "addr:postcode":"m41 5al",
    "addr:street":"Flixton Road",
    "iso:country":"GB",
    "sg:address":"98 Flixton Road, Urmston",
    "sg:city":"Manchester",
    "sg:classifiers":[
        {
            "category":"Retail",
            "subcategory":"Laundry & Dry Cleaning",
            "type":"Services"
        }
    ],
    "sg:phone":"+44 161 748 7130",
    "sg:postcode":"M41 5AL",
    "sg:province":"Cheshire",
    "sg:tags":[
        "alteration"
    ],
    "wof:name":"Max Clarke",
    "wof:placetype":"venue"
},
  "geometry": {"coordinates":[-2.359102,53.448341],"type":"Point"}
}