{
  "type": "Feature",
  "properties": {
    "iso:country":"GB",
    "sg:address":"113 High St North",
    "sg:city":"Dunstable",
    "sg:classifiers":[
        {
            "category":"Personal",
            "subcategory":"Beauty Salon",
            "type":"Services"
        },
        {
            "category":"Personal",
            "subcategory":"Barber",
            "type":"Services"
        }
    ],
    "sg:phone":"+44 1582 605535",
    "sg:postcode":"LU6 1JL",
    "sg:province":"Bedfordshire",
    "sg:tags":[
        "unisex",
        "hairdresser"
    ],
    "wof:name":"Hair Tek",
    "wof:placetype":"venue"
},
  "geometry": {"coordinates":[-0.5257859826,51.8894271851],"type":"Point"}
}