{
  "type": "Feature",
  "properties": {
    "addr:full":"Unit2 Pinewood Park Ruthin Denbighshire LL15 1NJ",
    "addr:postcode":"ll15 1nj",
    "addr:street":"Park",
    "iso:country":"GB",
    "sg:address":"Unit2 Pinewood Park",
    "sg:city":"Ruthin",
    "sg:classifiers":[
        {
            "category":"Home & Garden",
            "subcategory":"Furniture",
            "type":"Retail Goods"
        }
    ],
    "sg:phone":"+44 1824 704457",
    "sg:postcode":"LL15 1NJ",
    "sg:province":"Denbighshire",
    "wof:name":"Victoriana Fine Furniture",
    "wof:placetype":"venue"
},
  "geometry": {"coordinates":[-3.304522,53.114017],"type":"Point"}
}