{
  "type": "Feature",
  "properties": {
    "addr:full":"15 Club Mews Ely Cambridgeshire CB7 4NW",
    "addr:housenumber":"15",
    "addr:postcode":"cb7 4nw",
    "addr:street":"Club Mews",
    "iso:country":"GB",
    "sg:address":"15 Club Mews",
    "sg:city":"Ely",
    "sg:classifiers":[
        {
            "category":"Health Services",
            "subcategory":"Dentist",
            "type":"Services"
        }
    ],
    "sg:phone":"+44 1353 667200",
    "sg:postcode":"CB7 4NW",
    "sg:province":"Cambridgeshire",
    "wof:name":"D R Vincent",
    "wof:placetype":"venue"
},
  "geometry": {"coordinates":[0.2647520006,52.4011917114],"type":"Point"}
}