{
  "type": "Feature",
  "properties": {
    "addr:full":"39-51 Highgate Rd, Kentish Town Kentish Town Greater London NW5 1RT",
    "addr:housenumber":"39-51",
    "addr:postcode":"nw5 1rt",
    "addr:street":"Highgate Rd",
    "iso:country":"GB",
    "sg:address":"39-51 Highgate Rd, Kentish Town",
    "sg:city":"Kentish Town",
    "sg:classifiers":[
        {
            "category":"Communications",
            "type":"Services"
        }
    ],
    "sg:phone":"+44 20 7419 6611",
    "sg:postcode":"NW5 1RT",
    "sg:province":"Greater London",
    "sg:tags":[
        "data",
        "network"
    ],
    "wof:name":"Imaginality Media",
    "wof:placetype":"venue"
},
  "geometry": {"coordinates":[-0.1422580034,51.5531044006],"type":"Point"}
}