{
  "type": "Feature",
  "properties": {
    "iso:country":"GB",
    "sg:address":"1 Albert Road",
    "sg:city":"Horley",
    "sg:classifiers":[
        {
            "category":"Organizations",
            "subcategory":"Membership Organization",
            "type":"Services"
        }
    ],
    "sg:phone":"+44 1293 782045",
    "sg:postcode":"RH6 7HB",
    "sg:province":"Surrey",
    "sg:tags":[
        "club",
        "social"
    ],
    "wof:name":"The Horley & District Constitutional Club",
    "wof:placetype":"venue"
},
  "geometry": {"coordinates":[-0.163357,51.172291],"type":"Point"}
}