{
  "type": "Feature",
  "properties": {
    "addr:full":"74 Canute Road, Ore Village Hastings East Sussex TN35 5HT",
    "addr:housenumber":"74",
    "addr:postcode":"tn35 5ht",
    "addr:street":"Canute Road",
    "iso:country":"GB",
    "sg:address":"74 Canute Road, Ore Village",
    "sg:city":"Hastings",
    "sg:classifiers":[
        {
            "category":"Health Services",
            "subcategory":"Health Practitioner",
            "type":"Services"
        }
    ],
    "sg:postcode":"TN35 5HT",
    "sg:province":"East Sussex",
    "sg:tags":[
        "osteopath"
    ],
    "wof:name":"Nigel Bassett",
    "wof:placetype":"venue"
},
  "geometry": {"coordinates":[0.610559,50.872002],"type":"Point"}
}