{
  "type": "Feature",
  "properties": {
    "addr:full":"123 Ber St Norwich Norfolk NR1 3EY",
    "addr:housenumber":"123",
    "addr:postcode":"nr1 3ey",
    "addr:street":"Ber St",
    "iso:country":"GB",
    "sg:address":"123 Ber St",
    "sg:city":"Norwich",
    "sg:classifiers":[
        {
            "category":"Fast Food",
            "type":"Food & Drink"
        }
    ],
    "sg:postcode":"NR1 3EY",
    "sg:province":"Norfolk",
    "sg:tags":[
        "away",
        "take"
    ],
    "wof:name":"Jolly Friar Chip Shop",
    "wof:placetype":"venue"
},
  "geometry": {"coordinates":[1.2986279726,52.6228485107],"type":"Point"}
}