{
  "type": "Feature",
  "properties": {
    "iso:country":"GB",
    "sg:address":"81 Merkland Drive, Kirkintilloch",
    "sg:city":"Glasgow",
    "sg:classifiers":[
        {
            "category":"Government",
            "subcategory":"Post Office",
            "type":"Public Place"
        }
    ],
    "sg:phone":"+44 141 777 8606",
    "sg:postcode":"G66 3SJ",
    "sg:province":"East Dunbartonshire",
    "wof:name":"Merkland Sub Post Office",
    "wof:placetype":"venue"
},
  "geometry": {"coordinates":[-4.1307,55.942562],"type":"Point"}
}