{
  "type": "Feature",
  "properties": {
    "addr:full":"81 Merkland Drive, Kirkintilloch Glasgow East Dunbartonshire G66 3SJ",
    "addr:housenumber":"81",
    "addr:postcode":"g66 3sj",
    "addr:street":"Merkland Drive",
    "iso:country":"GB",
    "sg:address":"81 Merkland Drive, Kirkintilloch",
    "sg:city":"Glasgow",
    "sg:classifiers":[
        {
            "category":"Government",
            "subcategory":"Post Office",
            "type":"Public Place"
        }
    ],
    "sg:phone":"+44 141 777 8606",
    "sg:postcode":"G66 3SJ",
    "sg:province":"East Dunbartonshire",
    "wof:name":"Merkland Sub Post Office",
    "wof:placetype":"venue"
},
  "geometry": {"coordinates":[-4.1307,55.942562],"type":"Point"}
}