{
  "type": "Feature",
  "properties": {
    "iso:country":"GB",
    "sg:address":"24 Goddards Close",
    "sg:city":"Leicester",
    "sg:classifiers":[
        {
            "category":"Professional",
            "subcategory":"Engineering",
            "type":"Services"
        }
    ],
    "sg:phone":"+44 116 235 4957",
    "sg:postcode":"LE4 0QE",
    "sg:province":"Leicestershire",
    "sg:tags":[
        "engineer",
        "structural"
    ],
    "wof:name":"D Lad & Associates",
    "wof:placetype":"venue"
},
  "geometry": {"coordinates":[-1.162311,52.65683],"type":"Point"}
}