{
  "type": "Feature",
  "properties": {
    "iso:country":"GB",
    "sg:address":"150-156 Bath Road",
    "sg:city":"Cheltenham",
    "sg:classifiers":[
        {
            "category":"Building & Trades",
            "subcategory":"Equipment Rental",
            "type":"Services"
        }
    ],
    "sg:phone":"+44 1242 244255",
    "sg:postcode":"GL53 7NG",
    "sg:province":"Gloucestershire",
    "sg:tags":[
        "hire",
        "centre"
    ],
    "wof:name":"J P Hire Centres",
    "wof:placetype":"venue"
},
  "geometry": {"coordinates":[-2.068555,51.882629],"type":"Point"}
}