{
  "type": "Feature",
  "properties": {
    "iso:country":"GB",
    "sg:address":"14 Vine Street",
    "sg:city":"Grantham",
    "sg:classifiers":[
        {
            "category":"Fast Food",
            "type":"Food & Drink"
        }
    ],
    "sg:postcode":"NG31 6RQ",
    "sg:province":"Lincolnshire",
    "sg:tags":[
        "away",
        "take"
    ],
    "wof:name":"Mings Chinese Takeaway",
    "wof:placetype":"venue"
},
  "geometry": {"coordinates":[-0.642737,52.913712],"type":"Point"}
}