{
  "type": "Feature",
  "properties": {
    "iso:country":"GB",
    "sg:address":"Church Road, Bishops Cleeve",
    "sg:city":"Cheltenham",
    "sg:classifiers":[
        {
            "category":"Professional",
            "subcategory":"Art Services",
            "type":"Services"
        }
    ],
    "sg:postcode":"GL52 8LR",
    "sg:province":"Gloucestershire",
    "sg:tags":[
        "picture",
        "restoration",
        "framing",
        "cleaning"
    ],
    "wof:name":"Cleeve Picture Framing",
    "wof:placetype":"venue"
},
  "geometry": {"coordinates":[-2.0587229729,51.9470939636],"type":"Point"}
}