{
  "type": "Feature",
  "properties": {
    "addr:full":"18 Elm Terrace, Westfield Bath Somerset BA3 3XP",
    "addr:housenumber":"18",
    "addr:postcode":"ba3 3xp",
    "addr:street":"Elm Terrace",
    "iso:country":"GB",
    "sg:address":"18 Elm Terrace, Westfield",
    "sg:city":"Bath",
    "sg:classifiers":[
        {
            "category":"Shopping",
            "subcategory":"Department Store",
            "type":"Retail Goods"
        },
        {
            "category":"Government",
            "subcategory":"Post Office",
            "type":"Public Place"
        }
    ],
    "sg:postcode":"BA3 3XP",
    "sg:province":"Somerset",
    "wof:name":"Westfield Sub Post Office",
    "wof:placetype":"venue"
},
  "geometry": {"coordinates":[-2.46879,51.284039],"type":"Point"}
}