{
  "type": "Feature",
  "properties": {
    "addr:full":"C/o David W Pepper & Co, Springwood Ho, Low La, Horsforth Leeds West Yorkshire LS18 5NU",
    "addr:housenumber":"/ o",
    "addr:postcode":"ls18 5nu",
    "addr:street":"C;W;West",
    "iso:country":"GB",
    "sg:address":"C/o David W Pepper & Co, Springwood Ho, Low La, Horsforth",
    "sg:city":"Leeds",
    "sg:classifiers":[
        {
            "category":"Organizations",
            "subcategory":"Membership Organization",
            "type":"Services"
        }
    ],
    "sg:postcode":"LS18 5NU",
    "sg:province":"West Yorkshire",
    "sg:tags":[
        "club"
    ],
    "wof:name":"Breary Park View Management Ltd",
    "wof:placetype":"venue"
},
  "geometry": {"coordinates":[-1.6200699806,53.8387908936],"type":"Point"}
}