{
  "type": "Feature",
  "properties": {
    "addr:full":"Town Tenement, St Giles Torrington Devon EX38 7JQ",
    "addr:postcode":"ex38 7jq",
    "iso:country":"GB",
    "sg:address":"Town Tenement, St Giles",
    "sg:city":"Torrington",
    "sg:classifiers":[
        {
            "category":"Farming",
            "subcategory":"Livestock Farm",
            "type":"Manufacturing & Wholesale Goods"
        },
        {
            "category":"Farming",
            "subcategory":"Farm",
            "type":"Manufacturing & Wholesale Goods"
        }
    ],
    "sg:phone":"+44 1805 622296",
    "sg:postcode":"EX38 7JQ",
    "sg:province":"Devon",
    "sg:tags":[
        "mixed",
        "crop",
        "others"
    ],
    "wof:name":"J L & R J Hookway",
    "wof:placetype":"venue"
},
  "geometry": {"coordinates":[-4.142255,50.953152],"type":"Point"}
}