{
  "type": "Feature",
  "properties": {
    "addr:full":"Valentia Avenue Newcastle-upon-tyne Tyne and Wear NE6 4QR",
    "addr:postcode":"ne6 4qr",
    "addr:street":"Valentia Avenue",
    "iso:country":"GB",
    "sg:address":"Valentia Avenue",
    "sg:city":"Newcastle-upon-tyne",
    "sg:classifiers":[
        {
            "category":"Manufacturing",
            "subcategory":"Metals",
            "type":"Manufacturing & Wholesale Goods"
        }
    ],
    "sg:phone":"+44 191 224 4552",
    "sg:postcode":"NE6 4QR",
    "sg:province":"Tyne and Wear",
    "sg:tags":[
        "steel",
        "fabricator",
        "erectors"
    ],
    "wof:name":"W D Close & Sons Ltd.",
    "wof:placetype":"venue"
},
  "geometry": {"coordinates":[-1.5633039474,54.9825897217],"type":"Point"}
}