{
  "type": "Feature",
  "properties": {
    "iso:country":"GB",
    "sg:address":"9 Simonside, Hough Green",
    "sg:city":"Widnes",
    "sg:classifiers":[
        {
            "category":"Health Services",
            "subcategory":"Health Practitioner",
            "type":"Services"
        }
    ],
    "sg:postcode":"WA8 4YL",
    "sg:province":"Cheshire",
    "sg:tags":[
        "hypnotherapists"
    ],
    "wof:name":"The Hypnos Practice",
    "wof:placetype":"venue"
},
  "geometry": {"coordinates":[-2.764431,53.376961],"type":"Point"}
}