{
  "type": "Feature",
  "properties": {
    "addr:full":"14 Argoed Avenue, New Brighton Mold Denbighshire CH7 6QL",
    "addr:housenumber":"14",
    "addr:postcode":"ch7 6ql",
    "addr:street":"Argoed Avenue",
    "iso:country":"GB",
    "sg:address":"14 Argoed Avenue, New Brighton",
    "sg:city":"Mold",
    "sg:classifiers":[
        {
            "category":"Organizations",
            "subcategory":"Non-profit Organization",
            "type":"Services"
        }
    ],
    "sg:postcode":"CH7 6QL",
    "sg:province":"Denbighshire",
    "sg:tags":[
        "organisation",
        "voluntary",
        "charity"
    ],
    "wof:name":"National Childbirth Trust - East Clwyd Branch (The",
    "wof:placetype":"venue"
},
  "geometry": {"coordinates":[-3.115947,53.16827],"type":"Point"}
}