{
  "type": "Feature",
  "properties": {
    "iso:country":"GB",
    "sg:address":"174 Mid Street",
    "sg:city":"Keith",
    "sg:classifiers":[
        {
            "category":"Personal",
            "type":"Services"
        }
    ],
    "sg:phone":"+44 1542 882766",
    "sg:postcode":"AB55 3BL",
    "sg:province":"Moray",
    "sg:tags":[
        "tailor"
    ],
    "wof:name":"Grays of Keith",
    "wof:placetype":"venue"
},
  "geometry": {"coordinates":[-2.950414,57.539303],"type":"Point"}
}