{
  "type": "Feature",
  "properties": {
    "addr:full":"1 Thomas Dr Canvey Island Essex SS8 9RT",
    "addr:housenumber":"1",
    "addr:postcode":"ss8 9rt",
    "addr:street":"Thomas Dr",
    "iso:country":"GB",
    "sg:address":"1 Thomas Dr",
    "sg:city":"Canvey Island",
    "sg:classifiers":[
        {
            "category":"Retail",
            "subcategory":"Repair Shop",
            "type":"Services"
        }
    ],
    "sg:phone":"+44 1268 512043",
    "sg:postcode":"SS8 9RT",
    "sg:province":"Essex",
    "sg:tags":[
        "maintenance"
    ],
    "wof:name":"Double-R Builders & Decorators",
    "wof:placetype":"venue"
},
  "geometry": {"coordinates":[0.571082,51.528038],"type":"Point"}
}