{
  "type": "Feature",
  "properties": {
    "iso:country":"GB",
    "sg:address":"80 Southgate St",
    "sg:city":"Gloucester",
    "sg:classifiers":[
        {
            "category":"Manufacturing",
            "subcategory":"Petroleum Products",
            "type":"Manufacturing & Wholesale Goods"
        }
    ],
    "sg:phone":"+44 1452 308383",
    "sg:postcode":"GL1 2DX",
    "sg:province":"Gloucestershire",
    "sg:tags":[
        "double",
        "glazing"
    ],
    "wof:name":"Ariston",
    "wof:placetype":"venue"
},
  "geometry": {"coordinates":[-2.248383,51.863461],"type":"Point"}
}