{
  "type": "Feature",
  "properties": {
    "iso:country":"GB",
    "sg:address":"Broomhaugh Hotel, Broomhaugh",
    "sg:city":"Riding Mill",
    "sg:classifiers":[
        {
            "category":"Travel",
            "subcategory":"Hotels & Motels",
            "type":"Entertainment"
        }
    ],
    "sg:postcode":"NE44 6EG",
    "sg:province":"Northumberland",
    "wof:name":"Broomhaugh Hotel",
    "wof:placetype":"venue"
},
  "geometry": {"coordinates":[-1.974789,54.948711],"type":"Point"}
}