{
  "type": "Feature",
  "properties": {
    "addr:full":"Caxton St North Canning Town Greater London E16 1JL",
    "addr:postcode":"e16 1jl",
    "addr:street":"Caxton St",
    "iso:country":"GB",
    "sg:address":"Caxton St North",
    "sg:city":"Canning Town",
    "sg:classifiers":[
        {
            "category":"Home & Garden",
            "subcategory":"Kitchen Supply",
            "type":"Retail Goods"
        }
    ],
    "sg:phone":"+44 20 7474 4958",
    "sg:postcode":"E16 1JL",
    "sg:province":"Greater London",
    "sg:tags":[
        "equipment",
        "bakery"
    ],
    "wof:name":"K.G.S Engineering",
    "wof:placetype":"venue"
},
  "geometry": {"coordinates":[0.0114089996,51.5116157532],"type":"Point"}
}