{
  "type": "Feature",
  "properties": {
    "iso:country":"GB",
    "sg:address":"241 Globe Rd",
    "sg:city":"London",
    "sg:classifiers":[
        {
            "category":"Food & Beverages",
            "subcategory":"Specialty",
            "type":"Retail Goods"
        }
    ],
    "sg:postcode":"E2 0JD",
    "sg:province":"Greater London",
    "sg:tags":[
        "vegetarian"
    ],
    "wof:name":"The Cherry Orchard Vegetarian Restaurant",
    "wof:placetype":"venue"
},
  "geometry": {"coordinates":[-0.051029,51.527962],"type":"Point"}
}