{
  "type": "Feature",
  "properties": {
    "addr:full":"155 Allison Street Glasgow Glasgow City G42 8RY",
    "addr:housenumber":"155",
    "addr:postcode":"g42 8ry",
    "addr:street":"Allison Street",
    "iso:country":"GB",
    "sg:address":"155 Allison Street",
    "sg:city":"Glasgow",
    "sg:classifiers":[
        {
            "category":"Food & Beverages",
            "subcategory":"Liquor & Beverages",
            "type":"Retail Goods"
        }
    ],
    "sg:phone":"+44 141 433 2737",
    "sg:postcode":"G42 8RY",
    "sg:province":"Glasgow City",
    "sg:tags":[
        "beer",
        "spirit",
        "wines"
    ],
    "wof:name":"Thirsties",
    "wof:placetype":"venue"
},
  "geometry": {"coordinates":[-4.263879776,55.8366661072],"type":"Point"}
}