{
  "type": "Feature",
  "properties": {
    "addr:full":"66 Livesey Branch Road Blackburn Lancashire BB2 4LU",
    "addr:housenumber":"66",
    "addr:postcode":"bb2 4lu",
    "addr:street":"Livesey Branch Road",
    "iso:country":"GB",
    "sg:address":"66 Livesey Branch Road",
    "sg:city":"Blackburn",
    "sg:classifiers":[
        {
            "category":"Personal",
            "subcategory":"Beauty Salon",
            "type":"Services"
        }
    ],
    "sg:phone":"+44 1254 674242",
    "sg:postcode":"BB2 4LU",
    "sg:province":"Lancashire",
    "wof:name":"The Nail Room",
    "wof:placetype":"venue"
},
  "geometry": {"coordinates":[-2.495372,53.729797],"type":"Point"}
}