{
  "type": "Feature",
  "properties": {
    "addr:full":"5 East Cliff Preston Lancashire PR1 3JE",
    "addr:housenumber":"5",
    "addr:postcode":"pr1 3je",
    "addr:street":"East Cliff",
    "iso:country":"GB",
    "sg:address":"5 East Cliff",
    "sg:city":"Preston",
    "sg:classifiers":[
        {
            "category":"Professional",
            "subcategory":"Accounting & Tax Preparation",
            "type":"Services"
        }
    ],
    "sg:phone":"+44 1772 203515",
    "sg:postcode":"PR1 3JE",
    "sg:province":"Lancashire",
    "sg:tags":[
        "accountant"
    ],
    "wof:name":"Robinsons",
    "wof:placetype":"venue"
},
  "geometry": {"coordinates":[-2.704286,53.753574],"type":"Point"}
}