{
  "type": "Feature",
  "properties": {
    "addr:full":"103 Stanhope Road South Darlington Durham DL3 7SF",
    "addr:housenumber":"103",
    "addr:postcode":"dl3 7sf",
    "addr:street":"Stanhope Road South",
    "iso:country":"GB",
    "sg:address":"103 Stanhope Road South",
    "sg:city":"Darlington",
    "sg:classifiers":[
        {
            "category":"Professional",
            "subcategory":"Computer Services",
            "type":"Services"
        }
    ],
    "sg:phone":"+44 1325 381232",
    "sg:postcode":"DL3 7SF",
    "sg:province":"Durham",
    "sg:tags":[
        "system",
        "software"
    ],
    "wof:name":"J Bishop Ltd.",
    "wof:placetype":"venue"
},
  "geometry": {"coordinates":[-1.5624339581,54.5240440369],"type":"Point"}
}