{
  "type": "Feature",
  "properties": {
    "addr:full":"York Road Industrial Estate, York Road Wetherby North Yorkshire LS22 7SU",
    "addr:postcode":"ls22 7su",
    "addr:street":"York Road Industrial Estate York Road",
    "iso:country":"GB",
    "sg:address":"York Road Industrial Estate, York Road",
    "sg:city":"Wetherby",
    "sg:classifiers":[
        {
            "category":"Government",
            "subcategory":"City Hall",
            "type":"Public Place"
        },
        {
            "category":"Retail",
            "subcategory":"Event Space",
            "type":"Services"
        }
    ],
    "sg:phone":"+44 1937 581965",
    "sg:postcode":"LS22 7SU",
    "sg:province":"North Yorkshire",
    "sg:tags":[
        "function",
        "hire",
        "room"
    ],
    "wof:name":"Engine Shed",
    "wof:placetype":"venue"
},
  "geometry": {"coordinates":[-1.3868039846,53.9279899597],"type":"Point"}
}