{
  "type": "Feature",
  "properties": {
    "addr:full":"Ossington Chambers, 6 Castlegate Newark Nottinghamshire NG24 1AX",
    "addr:housenumber":"6",
    "addr:postcode":"ng24 1ax",
    "addr:street":"Castlegate",
    "iso:country":"GB",
    "sg:address":"Ossington Chambers, 6 Castlegate",
    "sg:city":"Newark",
    "sg:classifiers":[
        {
            "category":"Real Estate",
            "subcategory":"Real Estate Agent",
            "type":"Services"
        }
    ],
    "sg:postcode":"NG24 1AX",
    "sg:province":"Nottinghamshire",
    "wof:name":"Waterlakes Estates Ltd",
    "wof:placetype":"venue"
},
  "geometry": {"coordinates":[-0.805866003,53.0768432617],"type":"Point"}
}