{
  "type": "Feature",
  "properties": {
    "addr:full":"19 Magdalen Street Oxford Oxfordshire OX1 3AE",
    "addr:housenumber":"19",
    "addr:postcode":"ox1 3ae",
    "addr:street":"Magdalen Street",
    "iso:country":"GB",
    "sg:address":"19 Magdalen Street",
    "sg:city":"Oxford",
    "sg:classifiers":[
        {
            "category":"Personal",
            "subcategory":"Beauty Salon",
            "type":"Services"
        }
    ],
    "sg:phone":"+44 1865 244302",
    "sg:postcode":"OX1 3AE",
    "sg:province":"Oxfordshire",
    "sg:tags":[
        "lady",
        "hairdresser"
    ],
    "wof:name":"Roland of Switzerland",
    "wof:placetype":"venue"
},
  "geometry": {"coordinates":[-1.259395,51.75491],"type":"Point"}
}