{
  "type": "Feature",
  "properties": {
    "addr:full":"Dennett Court, Athlone Road Warrington Cheshire WA2 8JJ",
    "addr:postcode":"wa2 8jj",
    "addr:street":"Dennett Court Athlone Road",
    "iso:country":"GB",
    "sg:address":"Dennett Court, Athlone Road",
    "sg:city":"Warrington",
    "sg:classifiers":[
        {
            "category":"Recreation",
            "subcategory":"Amusement Park",
            "type":"Entertainment"
        }
    ],
    "sg:phone":"+44 1925 231767",
    "sg:postcode":"WA2 8JJ",
    "sg:province":"Cheshire",
    "sg:tags":[
        "arcade"
    ],
    "wof:name":"L & A Pool Services",
    "wof:placetype":"venue"
},
  "geometry": {"coordinates":[-2.597121,53.406879],"type":"Point"}
}