{
  "type": "Feature",
  "properties": {
    "iso:country":"GB",
    "sg:address":"Station Road",
    "sg:city":"Sunderland",
    "sg:classifiers":[
        {
            "category":"Organizations",
            "subcategory":"Membership Organization",
            "type":"Services"
        }
    ],
    "sg:phone":"+44 191 548 4314",
    "sg:postcode":"SR6 9AE",
    "sg:province":"Tyne and Wear",
    "sg:tags":[
        "club"
    ],
    "wof:name":"Mill View Social Club",
    "wof:placetype":"venue"
},
  "geometry": {"coordinates":[-1.383317,54.929489],"type":"Point"}
}