{
  "type": "Feature",
  "properties": {
    "addr:full":"97 Brickhill Drive Bedford Bedfordshire MK41 7QF",
    "addr:housenumber":"97",
    "addr:postcode":"mk41 7qf",
    "addr:street":"Brickhill Drive",
    "iso:country":"GB",
    "sg:address":"97 Brickhill Drive",
    "sg:city":"Bedford",
    "sg:classifiers":[
        {
            "category":"Shopping",
            "subcategory":"Florist",
            "type":"Retail Goods"
        }
    ],
    "sg:postcode":"MK41 7QF",
    "sg:province":"Bedfordshire",
    "wof:name":"Baccara Florists",
    "wof:placetype":"venue"
},
  "geometry": {"coordinates":[-0.464326,52.153919],"type":"Point"}
}