{
  "type": "Feature",
  "properties": {
    "iso:country":"GB",
    "sg:address":"303 Mount Road",
    "sg:city":"Manchester",
    "sg:classifiers":[
        {
            "category":"Retail",
            "subcategory":"Auto Repair",
            "type":"Services"
        }
    ],
    "sg:postcode":"M19 3ET",
    "sg:province":"Greater Manchester",
    "sg:tags":[
        "modification",
        "garage"
    ],
    "wof:name":"Mount Road Service Centre",
    "wof:placetype":"venue"
},
  "geometry": {"coordinates":[-2.179126,53.448837],"type":"Point"}
}