{
  "type": "Feature",
  "properties": {
    "addr:full":"59 Saville Street North Shields Tyne and Wear NE30 1AY",
    "addr:housenumber":"59",
    "addr:postcode":"ne30 1ay",
    "addr:street":"Saville Street",
    "iso:country":"GB",
    "sg:address":"59 Saville Street",
    "sg:city":"North Shields",
    "sg:classifiers":[
        {
            "category":"Deli",
            "type":"Food & Drink"
        }
    ],
    "sg:phone":"+44 191 296 4656",
    "sg:postcode":"NE30 1AY",
    "sg:province":"Tyne and Wear",
    "sg:tags":[
        "delicatessen"
    ],
    "wof:name":"The Wooden Deli",
    "wof:placetype":"venue"
},
  "geometry": {"coordinates":[-1.442777,55.009148],"type":"Point"}
}