{
  "type": "Feature",
  "properties": {
    "addr:full":"East Court, Whelford Fairford Gloucestershire GL7 4DY",
    "addr:postcode":"gl7 4dy",
    "addr:street":"East",
    "iso:country":"GB",
    "sg:address":"East Court, Whelford",
    "sg:city":"Fairford",
    "sg:classifiers":[
        {
            "category":"Building & Trades",
            "subcategory":"Construction",
            "type":"Services"
        }
    ],
    "sg:phone":"+44 1285 713103",
    "sg:postcode":"GL7 4DY",
    "sg:province":"Gloucestershire",
    "sg:tags":[
        "builder"
    ],
    "wof:name":"M Brown",
    "wof:placetype":"venue"
},
  "geometry": {"coordinates":[-1.773819,51.673401],"type":"Point"}
}