{
  "type": "Feature",
  "properties": {
    "iso:country":"GB",
    "sg:address":"3 Milner St",
    "sg:city":"Chelsea",
    "sg:classifiers":[
        {
            "category":"Restaurant",
            "type":"Food & Drink"
        }
    ],
    "sg:phone":"+44 20 7584 3002",
    "sg:postcode":"SW3 2QA",
    "sg:province":"Greater London",
    "wof:name":"English House The",
    "wof:placetype":"venue"
},
  "geometry": {"coordinates":[-0.164528,51.494175],"type":"Point"}
}