{
  "type": "Feature",
  "properties": {
    "addr:full":"16 Broadway Peterborough Cambridgeshire PE1 1RS",
    "addr:housenumber":"16",
    "addr:postcode":"pe1 1rs",
    "addr:street":"Broadway",
    "iso:country":"GB",
    "sg:address":"16 Broadway",
    "sg:city":"Peterborough",
    "sg:classifiers":[
        {
            "category":"Shopping",
            "subcategory":"Clothing, Apparel, & Fashions",
            "type":"Retail Goods"
        }
    ],
    "sg:postcode":"PE1 1RS",
    "sg:province":"Cambridgeshire",
    "sg:tags":[
        "ladieswear"
    ],
    "wof:name":"Naked on Broadway",
    "wof:placetype":"venue"
},
  "geometry": {"coordinates":[-0.241983,52.574558],"type":"Point"}
}