{
  "type": "Feature",
  "properties": {
    "iso:country":"GB",
    "sg:address":"15 Cuppin St",
    "sg:city":"Chester",
    "sg:classifiers":[
        {
            "category":"Organizations",
            "subcategory":"Religious Organization",
            "type":"Services"
        }
    ],
    "sg:phone":"+44 1244 351331",
    "sg:postcode":"CH1 2BN",
    "sg:province":"Cheshire",
    "sg:tags":[
        "organisation"
    ],
    "wof:name":"Franciscan Friary",
    "wof:placetype":"venue"
},
  "geometry": {"coordinates":[-2.893671,53.187878],"type":"Point"}
}