{
  "type": "Feature",
  "properties": {
    "addr:full":"C/o Jet Petrol Station, Birmingham Road Oldbury West Midlands B69 4EQ",
    "addr:postcode":"b69 4eq",
    "addr:street":"C;Birmingham Road",
    "iso:country":"GB",
    "sg:address":"C/o Jet Petrol Station, Birmingham Road",
    "sg:city":"Oldbury",
    "sg:classifiers":[
        {
            "category":"Retail",
            "subcategory":"Emissions Testing",
            "type":"Services"
        },
        {
            "category":"Retail",
            "subcategory":"Auto Repair",
            "type":"Services"
        }
    ],
    "sg:phone":"+44 121 544 2952",
    "sg:postcode":"B69 4EQ",
    "sg:province":"West Midlands",
    "sg:tags":[
        "modification",
        "garage",
        "mot"
    ],
    "wof:name":"Trinity Motor Services",
    "wof:placetype":"venue"
},
  "geometry": {"coordinates":[-2.015845,52.503777],"type":"Point"}
}