{
  "type": "Feature",
  "properties": {
    "iso:country":"GB",
    "sg:address":"19 St Catherines Close, Bathwick Hill",
    "sg:city":"Bath",
    "sg:classifiers":[
        {
            "category":"Professional",
            "subcategory":"Management & Consulting",
            "type":"Services"
        }
    ],
    "sg:postcode":"BA2 6BS",
    "sg:province":"Somerset",
    "sg:tags":[
        "consultant",
        "investigation",
        "site"
    ],
    "wof:name":"Mini Soil Surveys (West) Ltd.",
    "wof:placetype":"venue"
},
  "geometry": {"coordinates":[-2.345568,51.382858],"type":"Point"}
}