{
  "type": "Feature",
  "properties": {
    "addr:full":"226 Cromwell Road London Greater London SW5 0SR",
    "addr:housenumber":"226",
    "addr:postcode":"sw5 0sr",
    "addr:street":"Cromwell Road",
    "iso:country":"GB",
    "sg:address":"226 Cromwell Road",
    "sg:city":"London",
    "sg:classifiers":[
        {
            "category":"Education",
            "subcategory":"Music School",
            "type":"Public Place"
        },
        {
            "category":"Professional",
            "subcategory":"Management & Consulting",
            "type":"Services"
        }
    ],
    "sg:phone":"+44 20 8834 0500",
    "sg:postcode":"SW5 0SR",
    "sg:province":"Greater London",
    "sg:tags":[
        "consultant",
        "training"
    ],
    "wof:name":"L A M D A Ltd.",
    "wof:placetype":"venue"
},
  "geometry": {"coordinates":[-0.192159,51.494759],"type":"Point"}
}