{
  "type": "Feature",
  "properties": {
    "addr:full":"6 Park Avenue, Barford Norwich Norfolk NR9 4BA",
    "addr:housenumber":"6",
    "addr:postcode":"nr9 4ba",
    "addr:street":"Park Avenue",
    "iso:country":"GB",
    "sg:address":"6 Park Avenue, Barford",
    "sg:city":"Norwich",
    "sg:classifiers":[
        {
            "category":"Building & Trades",
            "subcategory":"Landscaping Services",
            "type":"Services"
        }
    ],
    "sg:postcode":"NR9 4BA",
    "sg:province":"Norfolk",
    "sg:tags":[
        "landscape",
        "contractor"
    ],
    "wof:name":"T E Dewsbury",
    "wof:placetype":"venue"
},
  "geometry": {"coordinates":[1.123924017,52.6250572205],"type":"Point"}
}