{
  "type": "Feature",
  "properties": {
    "addr:full":"Suite 3 Vogans Mill Wharf, 17 Mill Street London Greater London SE1 2BZ",
    "addr:housenumber":"suite 3;17",
    "addr:postcode":"se1 2bz",
    "addr:street":"Vogans Mill Wharf;Mill Street",
    "iso:country":"GB",
    "sg:address":"Suite 3 Vogans Mill Wharf, 17 Mill Street",
    "sg:city":"London",
    "sg:classifiers":[
        {
            "category":"Professional",
            "subcategory":"Computer Services",
            "type":"Services"
        }
    ],
    "sg:postcode":"SE1 2BZ",
    "sg:province":"Greater London",
    "sg:tags":[
        "information"
    ],
    "wof:name":"Global Newsbrokers",
    "wof:placetype":"venue"
},
  "geometry": {"coordinates":[-0.07156,51.501129],"type":"Point"}
}