{
  "type": "Feature",
  "properties": {
    "iso:country":"GB",
    "sg:address":"Wedgewood Farm, Hazeley Heath, Hook",
    "sg:city":"Basingstoke",
    "sg:classifiers":[
        {
            "category":"Transit Center",
            "subcategory":"Passenger",
            "type":"Transportation"
        }
    ],
    "sg:phone":"+44 1252 842453",
    "sg:postcode":"RG27 8LT",
    "sg:province":"Berkshire",
    "sg:tags":[
        "boarding",
        "kennel",
        "catteries"
    ],
    "wof:name":"Wedgewood Farm Kennels",
    "wof:placetype":"venue"
},
  "geometry": {"coordinates":[-0.915549,51.314274],"type":"Point"}
}