{
  "type": "Feature",
  "properties": {
    "iso:country":"GB",
    "sg:address":"Derwentside Works, Derwent Road, York Road Industrial Park",
    "sg:city":"Malton",
    "sg:classifiers":[
        {
            "category":"Professional",
            "subcategory":"Engineering",
            "type":"Services"
        }
    ],
    "sg:phone":"+44 1653 694713",
    "sg:postcode":"YO17 6NW",
    "sg:province":"North Yorkshire",
    "sg:tags":[
        "civil",
        "engineer"
    ],
    "wof:name":"Dobson Civil Engineering",
    "wof:placetype":"venue"
},
  "geometry": {"coordinates":[-0.788043,54.146866],"type":"Point"}
}