{
  "type": "Feature",
  "properties": {
    "addr:full":"17 Stockbridge Road Winchester Hampshire SO22 6RN",
    "addr:housenumber":"17",
    "addr:postcode":"so22 6rn",
    "addr:street":"Stockbridge Road",
    "iso:country":"GB",
    "sg:address":"17 Stockbridge Road",
    "sg:city":"Winchester",
    "sg:classifiers":[
        {
            "category":"Fast Food",
            "type":"Food & Drink"
        }
    ],
    "sg:phone":"+44 1962 877535",
    "sg:postcode":"SO22 6RN",
    "sg:province":"Hampshire",
    "sg:tags":[
        "away",
        "take"
    ],
    "wof:name":"N Islam",
    "wof:placetype":"venue"
},
  "geometry": {"coordinates":[-1.324558,51.067318],"type":"Point"}
}