{
  "type": "Feature",
  "properties": {
    "iso:country":"GB",
    "sg:address":"15 Dahl Drive, Townville",
    "sg:city":"Castleford",
    "sg:classifiers":[
        {
            "category":"Arts & Performance",
            "subcategory":"Music",
            "type":"Entertainment"
        }
    ],
    "sg:postcode":"WF10 3HB",
    "sg:province":"West Yorkshire",
    "sg:tags":[
        "mobile",
        "disco"
    ],
    "wof:name":"Wayne's World Disco's",
    "wof:placetype":"venue"
},
  "geometry": {"coordinates":[-1.3120670319,53.7127342224],"type":"Point"}
}