{
  "type": "Feature",
  "properties": {
    "iso:country":"GB",
    "sg:address":"40 Argyle Rd",
    "sg:city":"Ilford",
    "sg:classifiers":[
        {
            "category":"Professional",
            "subcategory":"Lawyer & Legal Services",
            "type":"Services"
        }
    ],
    "sg:phone":"+44 20 8518 0725",
    "sg:postcode":"IG1 3BG",
    "sg:province":"Essex",
    "sg:tags":[
        "advice",
        "counselling"
    ],
    "wof:name":"Asian Womens Association",
    "wof:placetype":"venue"
},
  "geometry": {"coordinates":[0.0659470037,51.5621109009],"type":"Point"}
}