{
  "type": "Feature",
  "properties": {
    "addr:full":"54-64 Heaton Moor Road Stockport Cheshire SK4 4NZ",
    "addr:housenumber":"54-64",
    "addr:postcode":"sk4 4nz",
    "addr:street":"Heaton Moor Road",
    "iso:country":"GB",
    "sg:address":"54-64 Heaton Moor Road",
    "sg:city":"Stockport",
    "sg:classifiers":[
        {
            "category":"Home & Garden",
            "subcategory":"Hardware",
            "type":"Retail Goods"
        }
    ],
    "sg:phone":"+44 161 432 2530",
    "sg:postcode":"SK4 4NZ",
    "sg:province":"Cheshire",
    "sg:tags":[
        "merchant",
        "ironmonger"
    ],
    "wof:name":"P Blagg Ltd.",
    "wof:placetype":"venue"
},
  "geometry": {"coordinates":[-2.182098,53.423901],"type":"Point"}
}