{
  "type": "Feature",
  "properties": {
    "iso:country":"GB",
    "sg:address":"15 Lindow Parade, Chapel Lane",
    "sg:city":"Wilmslow",
    "sg:classifiers":[
        {
            "category":"Health Services",
            "subcategory":"Chiropractor",
            "type":"Services"
        }
    ],
    "sg:phone":"+44 1625 531164",
    "sg:postcode":"SK9 5JL",
    "sg:province":"Cheshire",
    "wof:name":"Wilmslow Chiropractice Clinic",
    "wof:placetype":"venue"
},
  "geometry": {"coordinates":[-2.255037,53.325657],"type":"Point"}
}