{
  "type": "Feature",
  "properties": {
    "addr:full":"Ar-dachaidh, Lumphanan Banchory Aberdeen City AB31 4QL",
    "addr:postcode":"ab31 4ql",
    "iso:country":"GB",
    "sg:address":"Ar-dachaidh, Lumphanan",
    "sg:city":"Banchory",
    "sg:classifiers":[
        {
            "category":"Social Services",
            "subcategory":"Job Training",
            "type":"Services"
        }
    ],
    "sg:phone":"+44 1339 883436",
    "sg:postcode":"AB31 4QL",
    "sg:province":"Aberdeen City",
    "sg:tags":[
        "translator",
        "interpreter"
    ],
    "wof:name":"Russian Services",
    "wof:placetype":"venue"
},
  "geometry": {"coordinates":[-2.688454,57.128063],"type":"Point"}
}