{
  "type": "Feature",
  "properties": {
    "addr:full":"Kidnal House, Kidnal Malpas Cheshire SY14 7DJ",
    "addr:postcode":"sy14 7dj",
    "addr:street":"Kidnal",
    "iso:country":"GB",
    "sg:address":"Kidnal House, Kidnal",
    "sg:city":"Malpas",
    "sg:classifiers":[
        {
            "category":"Farming",
            "subcategory":"Dairy Farm",
            "type":"Manufacturing & Wholesale Goods"
        }
    ],
    "sg:phone":"+44 1948 860364",
    "sg:postcode":"SY14 7DJ",
    "sg:province":"Cheshire",
    "sg:tags":[
        "farmer"
    ],
    "wof:name":"A C Robinson & Son",
    "wof:placetype":"venue"
},
  "geometry": {"coordinates":[-2.7849099636,53.0395431519],"type":"Point"}
}