{
  "type": "Feature",
  "properties": {
    "addr:full":"596-598 High Road Woodford Green Essex IG8 0PS",
    "addr:housenumber":"596-598",
    "addr:postcode":"ig8 0ps",
    "addr:street":"High Road",
    "iso:country":"GB",
    "sg:address":"596-598 High Road",
    "sg:city":"Woodford Green",
    "sg:classifiers":[
        {
            "category":"Professional",
            "subcategory":"Employment Agencies",
            "type":"Services"
        }
    ],
    "sg:phone":"+44 20 8504 3921",
    "sg:postcode":"IG8 0PS",
    "sg:province":"Essex",
    "sg:tags":[
        "consultant",
        "recruitment"
    ],
    "wof:name":"DENTAL CONNECTIONS",
    "wof:placetype":"venue"
},
  "geometry": {"coordinates":[0.025808,51.616512],"type":"Point"}
}