{
  "type": "Feature",
  "properties": {
    "addr:full":"Pottery Road Newton Abbot Devon TQ12 3BN",
    "addr:postcode":"tq12 3bn",
    "addr:street":"Pottery Road",
    "iso:country":"GB",
    "sg:address":"Pottery Road",
    "sg:city":"Newton Abbot",
    "sg:classifiers":[
        {
            "category":"Retail",
            "subcategory":"Auto Repair",
            "type":"Services"
        }
    ],
    "sg:phone":"+44 1626 352545",
    "sg:postcode":"TQ12 3BN",
    "sg:province":"Devon",
    "sg:tags":[
        "modification",
        "garage"
    ],
    "wof:name":"Seymour Horwell Ltd.",
    "wof:placetype":"venue"
},
  "geometry": {"coordinates":[-3.598739,50.541519],"type":"Point"}
}