{
  "type": "Feature",
  "properties": {
    "addr:full":"20 High Terrace, Glaisdale Whitby North Yorkshire YO21 2PN",
    "addr:housenumber":"20",
    "addr:postcode":"yo21 2pn",
    "addr:street":"High Terrace",
    "iso:country":"GB",
    "sg:address":"20 High Terrace, Glaisdale",
    "sg:city":"Whitby",
    "sg:classifiers":[
        {
            "category":"Government",
            "subcategory":"Post Office",
            "type":"Public Place"
        }
    ],
    "sg:phone":"+44 1947 897244",
    "sg:postcode":"YO21 2PN",
    "sg:province":"North Yorkshire",
    "wof:name":"Glaisdale Post Office",
    "wof:placetype":"venue"
},
  "geometry": {"coordinates":[-0.9418029785,54.4636268616],"type":"Point"}
}