{
  "type": "Feature",
  "properties": {
    "addr:full":"230 Highbury Road, Bulwell Nottingham Nottinghamshire NG6 9FE",
    "addr:housenumber":"230",
    "addr:postcode":"ng6 9fe",
    "addr:street":"Highbury Road",
    "iso:country":"GB",
    "sg:address":"230 Highbury Road, Bulwell",
    "sg:city":"Nottingham",
    "sg:classifiers":[
        {
            "category":"Bus Charters",
            "type":"Transportation"
        }
    ],
    "sg:phone":"+44 115 976 4324",
    "sg:postcode":"NG6 9FE",
    "sg:province":"Nottinghamshire",
    "sg:tags":[
        "mini",
        "hire",
        "leasing"
    ],
    "wof:name":"Gary's Mini Buses",
    "wof:placetype":"venue"
},
  "geometry": {"coordinates":[-1.1923010349,52.9966506958],"type":"Point"}
}