{
  "type": "Feature",
  "properties": {
    "addr:full":"3 The Mount Fleet Hampshire GU51 4PX",
    "addr:housenumber":"3",
    "addr:postcode":"gu51 4px",
    "addr:street":"The Mount",
    "iso:country":"GB",
    "sg:address":"3 The Mount",
    "sg:city":"Fleet",
    "sg:classifiers":[
        {
            "category":"Professional",
            "subcategory":"Computer Services",
            "type":"Services"
        }
    ],
    "sg:phone":"+44 1252 316156",
    "sg:postcode":"GU51 4PX",
    "sg:province":"Hampshire",
    "sg:tags":[
        "system",
        "software"
    ],
    "wof:name":"Contec Enterprises Ltd.",
    "wof:placetype":"venue"
},
  "geometry": {"coordinates":[-0.8355910182,51.2882461548],"type":"Point"}
}