{
  "type": "Feature",
  "properties": {
    "iso:country":"GB",
    "sg:address":"Laurel Farm, Main Road, Kelsale",
    "sg:city":"Saxmundham",
    "sg:classifiers":[
        {
            "category":"Food & Beverages",
            "subcategory":"Farmers Market",
            "type":"Retail Goods"
        }
    ],
    "sg:postcode":"IP17 2RG",
    "sg:province":"Suffolk",
    "sg:tags":[
        "herb",
        "grower"
    ],
    "wof:name":"Laurel Farm Herbs",
    "wof:placetype":"venue"
},
  "geometry": {"coordinates":[1.4863300323,52.2346382141],"type":"Point"}
}