{
  "type": "Feature",
  "properties": {
    "addr:full":"41-43 Lancaster Rd Enfield Greater London EN2 0BU",
    "addr:housenumber":"41-43",
    "addr:postcode":"en2 0bu",
    "addr:street":"Lancaster Rd",
    "iso:country":"GB",
    "sg:address":"41-43 Lancaster Rd",
    "sg:city":"Enfield",
    "sg:classifiers":[
        {
            "category":"Autos & Motor Vehicles",
            "subcategory":"Automobile Sales",
            "type":"Retail Goods"
        }
    ],
    "sg:phone":"+44 20 8363 6728",
    "sg:postcode":"EN2 0BU",
    "sg:province":"Greater London",
    "sg:tags":[
        "commercial"
    ],
    "wof:name":"Lancaster Motor Co",
    "wof:placetype":"venue"
},
  "geometry": {"coordinates":[-0.079659,51.66375],"type":"Point"}
}