{
  "type": "Feature",
  "properties": {
    "iso:country":"GB",
    "sg:address":"10 Whins Rd",
    "sg:city":"Troon",
    "sg:classifiers":[
        {
            "category":"Retail",
            "subcategory":"Driving School",
            "type":"Services"
        }
    ],
    "sg:phone":"+44 1292 311737",
    "sg:postcode":"KA10 6UE",
    "sg:province":"South Ayrshire",
    "wof:name":"Isobel McKerrigan",
    "wof:placetype":"venue"
},
  "geometry": {"coordinates":[-4.6464400291,55.5636444092],"type":"Point"}
}