{
  "type": "Feature",
  "properties": {
    "iso:country":"GB",
    "sg:address":"6 Starkie Street",
    "sg:city":"Preston",
    "sg:classifiers":[
        {
            "category":"Professional",
            "subcategory":"Accounting & Tax Preparation",
            "type":"Services"
        }
    ],
    "sg:phone":"+44 1772 251385",
    "sg:postcode":"PR1 3LU",
    "sg:province":"Lancashire",
    "sg:tags":[
        "accountant"
    ],
    "wof:name":"Gleeson Bessent Ltd.",
    "wof:placetype":"venue"
},
  "geometry": {"coordinates":[-2.6998848915,53.7547683716],"type":"Point"}
}