{
  "type": "Feature",
  "properties": {
    "addr:full":"8 Dibles Road, Warsash Southampton Hampshire SO31 9HZ",
    "addr:housenumber":"8",
    "addr:postcode":"so31 9hz",
    "addr:street":"Dibles Road",
    "iso:country":"GB",
    "sg:address":"8 Dibles Road, Warsash",
    "sg:city":"Southampton",
    "sg:classifiers":[
        {
            "category":"Health Services",
            "subcategory":"Medical Lab",
            "type":"Services"
        }
    ],
    "sg:postcode":"SO31 9HZ",
    "sg:province":"Hampshire",
    "sg:tags":[
        "dental"
    ],
    "wof:name":"Stuart Avery Dental Technicians",
    "wof:placetype":"venue"
},
  "geometry": {"coordinates":[-1.29402,50.852592],"type":"Point"}
}