{
  "type": "Feature",
  "properties": {
    "addr:full":"42 High Street Honiton Devon EX14 1PJ",
    "addr:housenumber":"42",
    "addr:postcode":"ex14 1pj",
    "addr:street":"High Street",
    "iso:country":"GB",
    "sg:address":"42 High Street",
    "sg:city":"Honiton",
    "sg:classifiers":[
        {
            "category":"Bars & Pubs",
            "type":"Food & Drink"
        }
    ],
    "sg:phone":"+44 1404 42903",
    "sg:postcode":"EX14 1PJ",
    "sg:province":"Devon",
    "sg:tags":[
        "pubs",
        "inn"
    ],
    "wof:name":"The Carlton Inn",
    "wof:placetype":"venue"
},
  "geometry": {"coordinates":[-3.1859200001,50.8004455566],"type":"Point"}
}