{
  "type": "Feature",
  "properties": {
    "iso:country":"GB",
    "sg:address":"79 Allhallowgate",
    "sg:city":"Ripon",
    "sg:classifiers":[
        {
            "category":"Real Estate",
            "subcategory":"Real Estate Agent",
            "type":"Services"
        }
    ],
    "sg:phone":"+44 1765 692331",
    "sg:postcode":"HG4 1LE",
    "sg:province":"North Yorkshire",
    "wof:name":"Glyn Collard & Alison Sturgess",
    "wof:placetype":"venue"
},
  "geometry": {"coordinates":[-1.523248,54.13821],"type":"Point"}
}