{
  "type": "Feature",
  "properties": {
    "addr:full":"324 Streatham High Road London Greater London SW16 6HH",
    "addr:housenumber":"324",
    "addr:postcode":"sw16 6hh",
    "addr:street":"Streatham High Road",
    "iso:country":"GB",
    "sg:address":"324 Streatham High Road",
    "sg:city":"London",
    "sg:classifiers":[
        {
            "category":"Real Estate",
            "subcategory":"Surveying",
            "type":"Services"
        }
    ],
    "sg:phone":"+44 20 8677 7611",
    "sg:postcode":"SW16 6HH",
    "sg:province":"Greater London",
    "sg:tags":[
        "surveyor",
        "valuer"
    ],
    "wof:name":"Tyrrell Watson & Deanes",
    "wof:placetype":"venue"
},
  "geometry": {"coordinates":[-0.13136,51.427021],"type":"Point"}
}