{
  "type": "Feature",
  "properties": {
    "addr:full":"Radway Grn Venture Park, Radway Grn Crewe Cheshire CW2 5PR",
    "addr:postcode":"cw2 5pr",
    "addr:street":"Radway Grn Venture Park Radway Grn",
    "iso:country":"GB",
    "sg:address":"Radway Grn Venture Park, Radway Grn",
    "sg:city":"Crewe",
    "sg:classifiers":[
        {
            "category":"Professional",
            "subcategory":"Computer Services",
            "type":"Services"
        }
    ],
    "sg:phone":"+44 1270 874700",
    "sg:postcode":"CW2 5PR",
    "sg:province":"Cheshire",
    "sg:tags":[
        "system",
        "software"
    ],
    "wof:name":"M B S",
    "wof:placetype":"venue"
},
  "geometry": {"coordinates":[-2.3327999115,53.0845794678],"type":"Point"}
}