{
  "type": "Feature",
  "properties": {
    "addr:full":"14-20 Northwood Road Thornton Heath Surrey CR7 8HQ",
    "addr:housenumber":"14-20",
    "addr:postcode":"cr7 8hq",
    "addr:street":"Northwood Road",
    "iso:country":"GB",
    "sg:address":"14-20 Northwood Road",
    "sg:city":"Thornton Heath",
    "sg:classifiers":[
        {
            "category":"Manufacturing",
            "subcategory":"Metals",
            "type":"Manufacturing & Wholesale Goods"
        },
        {
            "category":"Professional",
            "subcategory":"Engineering",
            "type":"Services"
        }
    ],
    "sg:phone":"+44 20 8771 9541",
    "sg:postcode":"CR7 8HQ",
    "sg:province":"Surrey",
    "sg:tags":[
        "steel",
        "fabricator",
        "erectors"
    ],
    "wof:name":"K T B Engineering Ltd.",
    "wof:placetype":"venue"
},
  "geometry": {"coordinates":[-0.104137,51.407467],"type":"Point"}
}