{
  "type": "Feature",
  "properties": {
    "addr:full":"Folgate House Maidstone Kent ME16 0LL",
    "addr:postcode":"me16 0ll",
    "addr:street":"Folgate",
    "iso:country":"GB",
    "sg:address":"Folgate House",
    "sg:city":"Maidstone",
    "sg:classifiers":[
        {
            "category":"Insurance",
            "subcategory":"Insurance Agent",
            "type":"Services"
        }
    ],
    "sg:phone":"+44 1622 671747",
    "sg:postcode":"ME16 0LL",
    "sg:province":"Kent",
    "sg:tags":[
        "broker"
    ],
    "wof:name":"Folgate Risk Solutions (Maidstone) Ltd.",
    "wof:placetype":"venue"
},
  "geometry": {"coordinates":[0.50179,51.282959],"type":"Point"}
}