{
  "type": "Feature",
  "properties": {
    "iso:country":"GB",
    "sg:address":"4 Foundry Crescent, Arden Street",
    "sg:city":"Stratford-upon-avon",
    "sg:classifiers":[
        {
            "category":"Building & Trades",
            "subcategory":"Plumbing",
            "type":"Services"
        }
    ],
    "sg:phone":"+44 1789 766642",
    "sg:postcode":"CV37 9LP",
    "sg:province":"Warwickshire",
    "sg:tags":[
        "central",
        "heating"
    ],
    "wof:name":"C & G Gas Appliances",
    "wof:placetype":"venue"
},
  "geometry": {"coordinates":[-1.707269,52.194134],"type":"Point"}
}