{
  "type": "Feature",
  "properties": {
    "iso:country":"GB",
    "sg:address":"Island Crescent",
    "sg:city":"Newquay",
    "sg:classifiers":[
        {
            "category":"Travel",
            "subcategory":"Hotels & Motels",
            "type":"Entertainment"
        }
    ],
    "sg:phone":"+44 1637 874087",
    "sg:postcode":"TR7 1DZ",
    "sg:province":"Cornwall",
    "wof:name":"Edwardian Hotel",
    "wof:placetype":"venue"
},
  "geometry": {"coordinates":[-5.081606,50.415215],"type":"Point"}
}