{
  "type": "Feature",
  "properties": {
    "addr:full":"High Flatts Chester-le-street Durham DH2 1BL",
    "addr:postcode":"dh2 1bl",
    "addr:street":"High;Chester-Le-Street",
    "iso:country":"GB",
    "sg:address":"High Flatts",
    "sg:city":"Chester-le-street",
    "sg:classifiers":[
        {
            "category":"Bars & Pubs",
            "type":"Food & Drink"
        },
        {
            "category":"Community Center",
            "subcategory":"Social",
            "type":"Public Place"
        }
    ],
    "sg:phone":"+44 191 388 2068",
    "sg:postcode":"DH2 1BL",
    "sg:province":"Durham",
    "sg:tags":[
        "pubs",
        "house",
        "inn",
        "activity"
    ],
    "wof:name":"THE PLOUGH INN",
    "wof:placetype":"venue"
},
  "geometry": {"coordinates":[-1.5942900181,54.8679618835],"type":"Point"}
}