{
  "type": "Feature",
  "properties": {
    "addr:full":"66 Grange Rd Wellingborough Northamptonshire NN9 5YQ",
    "addr:housenumber":"66",
    "addr:postcode":"nn9 5yq",
    "addr:street":"Grange Rd",
    "iso:country":"GB",
    "sg:address":"66 Grange Rd",
    "sg:city":"Wellingborough",
    "sg:classifiers":[
        {
            "category":"Building & Trades",
            "subcategory":"Plumbing",
            "type":"Services"
        }
    ],
    "sg:phone":"+44 1933 677630",
    "sg:postcode":"NN9 5YQ",
    "sg:province":"Northamptonshire",
    "sg:tags":[
        "heating"
    ],
    "wof:name":"R P Line",
    "wof:placetype":"venue"
},
  "geometry": {"coordinates":[-0.7076889873,52.3234291077],"type":"Point"}
}