{
  "type": "Feature",
  "properties": {
    "addr:full":"Grepach, Rhosmeirch Llangefni Gwynedd LL77 7RZ",
    "addr:postcode":"ll77 7rz",
    "addr:street":"Llangefni",
    "iso:country":"GB",
    "sg:address":"Grepach, Rhosmeirch",
    "sg:city":"Llangefni",
    "sg:classifiers":[
        {
            "category":"Freight",
            "type":"Transportation"
        }
    ],
    "sg:phone":"+44 1248 723677",
    "sg:postcode":"LL77 7RZ",
    "sg:province":"Gwynedd",
    "sg:tags":[
        "haulage",
        "transport",
        "road"
    ],
    "wof:name":"R G & M J Parry",
    "wof:placetype":"venue"
},
  "geometry": {"coordinates":[-4.308464,53.255604],"type":"Point"}
}