{
  "type": "Feature",
  "properties": {
    "addr:full":"5 Dukes Avenue Dorchester Dorset DT1 1EN",
    "addr:housenumber":"5",
    "addr:postcode":"dt1 1en",
    "addr:street":"Dukes Avenue",
    "iso:country":"GB",
    "sg:address":"5 Dukes Avenue",
    "sg:city":"Dorchester",
    "sg:classifiers":[
        {
            "category":"Professional",
            "subcategory":"Art Services",
            "type":"Services"
        },
        {
            "category":"Building & Trades",
            "subcategory":"Construction",
            "type":"Services"
        }
    ],
    "sg:phone":"+44 1305 267721",
    "sg:postcode":"DT1 1EN",
    "sg:province":"Dorset",
    "sg:tags":[
        "decorator",
        "painter"
    ],
    "wof:name":"MICHAEL DESMOND LEGG",
    "wof:placetype":"venue"
},
  "geometry": {"coordinates":[-2.429439,50.712292],"type":"Point"}
}