{
  "type": "Feature",
  "properties": {
    "addr:full":"70 Nethergate Street Bungay Norfolk NR35 1HE",
    "addr:housenumber":"70",
    "addr:postcode":"nr35 1he",
    "addr:street":"Nethergate Street",
    "iso:country":"GB",
    "sg:address":"70 Nethergate Street",
    "sg:city":"Bungay",
    "sg:classifiers":[
        {
            "category":"Professional",
            "subcategory":"Engineering",
            "type":"Services"
        }
    ],
    "sg:phone":"+44 1986 892422",
    "sg:postcode":"NR35 1HE",
    "sg:province":"Norfolk",
    "wof:name":"Taylors Engineering",
    "wof:placetype":"venue"
},
  "geometry": {"coordinates":[1.4355640411,52.458732605],"type":"Point"}
}