{
  "type": "Feature",
  "properties": {
    "addr:full":"1/3 Sterling Court, Loddington Kettering Northamptonshire NN14 1RZ",
    "addr:housenumber":"1 / 3",
    "addr:postcode":"nn14 1rz",
    "addr:street":"Sterling Court",
    "iso:country":"GB",
    "sg:address":"1/3 Sterling Court, Loddington",
    "sg:city":"Kettering",
    "sg:classifiers":[
        {
            "category":"Taxi",
            "type":"Transportation"
        }
    ],
    "sg:postcode":"NN14 1RZ",
    "sg:province":"Northamptonshire",
    "sg:tags":[
        "mini",
        "cab"
    ],
    "wof:name":"Corby Black Cab Co  Ltd",
    "wof:placetype":"venue"
},
  "geometry": {"coordinates":[-0.8045979738,52.3978805542],"type":"Point"}
}