{
  "type": "Feature",
  "properties": {
    "iso:country":"GB",
    "sg:address":"18 Kings Parade",
    "sg:city":"Cambridge",
    "sg:classifiers":[
        {
            "category":"Shopping",
            "subcategory":"Gifts & Souvenirs",
            "type":"Retail Goods"
        }
    ],
    "sg:phone":"+44 1223 313443",
    "sg:postcode":"CB2 1SP",
    "sg:province":"Cambridgeshire",
    "sg:tags":[
        "shop"
    ],
    "wof:name":"Young's",
    "wof:placetype":"venue"
},
  "geometry": {"coordinates":[0.117914,52.204689],"type":"Point"}
}