{
  "type": "Feature",
  "properties": {
    "addr:full":"Unit 5h, Laytown Trading Estate, Lynwell Road Manchester Greater Manchester M30 9QG",
    "addr:housenumber":"5h",
    "addr:postcode":"m30 9qg",
    "addr:street":"Trading;Lynwell Road",
    "iso:country":"GB",
    "sg:address":"Unit 5h, Laytown Trading Estate, Lynwell Road",
    "sg:city":"Manchester",
    "sg:classifiers":[
        {
            "category":"Wholesale",
            "subcategory":"Machinery & Supplies",
            "type":"Manufacturing & Wholesale Goods"
        }
    ],
    "sg:postcode":"M30 9QG",
    "sg:province":"Greater Manchester",
    "sg:tags":[
        "pump"
    ],
    "wof:name":"Matthews Thomas (Pumps) Ltd.",
    "wof:placetype":"venue"
},
  "geometry": {"coordinates":[-2.341725,53.48539],"type":"Point"}
}