{
  "type": "Feature",
  "properties": {
    "iso:country":"GB",
    "sg:address":"63 High St",
    "sg:city":"Poole",
    "sg:classifiers":[
        {
            "category":"Restaurant",
            "type":"Food & Drink"
        }
    ],
    "sg:postcode":"BH15 1AF",
    "sg:province":"Dorset",
    "wof:name":"Bodrum Turkish Restaurant",
    "wof:placetype":"venue"
},
  "geometry": {"coordinates":[-1.986126,50.714031],"type":"Point"}
}