{
  "type": "Feature",
  "properties": {
    "iso:country":"GB",
    "sg:address":"East House Bridgnorth Road, Enville",
    "sg:city":"Stourbridge",
    "sg:classifiers":[
        {
            "category":"Manufacturing",
            "subcategory":"Metals",
            "type":"Manufacturing & Wholesale Goods"
        }
    ],
    "sg:phone":"+44 1384 872198",
    "sg:postcode":"DY7 5HA",
    "sg:province":"Shropshire",
    "sg:tags":[
        "fab",
        "industry",
        "foundry",
        "f-a"
    ],
    "wof:name":"Foundry Engineering Services Ltd.",
    "wof:placetype":"venue"
},
  "geometry": {"coordinates":[-2.2176868916,52.4629745483],"type":"Point"}
}