{
  "type": "Feature",
  "properties": {
    "addr:full":"Printing Unit, 140 Manningham La Bradford West Yorkshire BD1 3AH",
    "addr:housenumber":"unit 140",
    "addr:postcode":"bd1 3ah",
    "addr:street":"La Bradford West",
    "iso:country":"GB",
    "sg:address":"Printing Unit, 140 Manningham La",
    "sg:city":"Bradford",
    "sg:classifiers":[
        {
            "category":"Government",
            "subcategory":"Office",
            "type":"Public Place"
        }
    ],
    "sg:phone":"+44 1274 752300",
    "sg:postcode":"BD1 3AH",
    "sg:province":"West Yorkshire",
    "sg:tags":[
        "local"
    ],
    "wof:name":"Bradford Metropolitan District Council",
    "wof:placetype":"venue"
},
  "geometry": {"coordinates":[-1.758306,53.795738],"type":"Point"}
}