{
  "type": "Feature",
  "properties": {
    "addr:full":"Airport Ho, Purleyway Croydon Surrey CR0 0XZ",
    "addr:postcode":"cr0 0xz",
    "iso:country":"GB",
    "sg:address":"Airport Ho, Purleyway",
    "sg:city":"Croydon",
    "sg:classifiers":[
        {
            "category":"Professional",
            "subcategory":"Employment Agencies",
            "type":"Services"
        }
    ],
    "sg:postcode":"CR0 0XZ",
    "sg:province":"Surrey",
    "sg:tags":[
        "consultant"
    ],
    "wof:name":"Bailey Carroll Associates Ltd",
    "wof:placetype":"venue"
},
  "geometry": {"coordinates":[-0.01071,51.343342],"type":"Point"}
}