{
  "type": "Feature",
  "properties": {
    "addr:full":"28 Victoria Street Newton Stewart Dumfries and Galloway DG8 6BT",
    "addr:housenumber":"28",
    "addr:postcode":"dg8 6bt",
    "addr:street":"Victoria Street",
    "iso:country":"GB",
    "sg:address":"28 Victoria Street",
    "sg:city":"Newton Stewart",
    "sg:classifiers":[
        {
            "category":"Professional",
            "subcategory":"Lawyer & Legal Services",
            "type":"Services"
        }
    ],
    "sg:phone":"+44 1671 402104",
    "sg:postcode":"DG8 6BT",
    "sg:province":"Dumfries and Galloway",
    "sg:tags":[
        "solicitor"
    ],
    "wof:name":"N G McCormick & Co",
    "wof:placetype":"venue"
},
  "geometry": {"coordinates":[-4.482958,54.957806],"type":"Point"}
}