{
  "type": "Feature",
  "properties": {
    "addr:full":"25 Rodney Street Edinburgh City of Edinburgh EH7 4EL",
    "addr:housenumber":"25",
    "addr:postcode":"eh7 4el",
    "addr:street":"Rodney Street",
    "iso:country":"GB",
    "sg:address":"25 Rodney Street",
    "sg:city":"Edinburgh",
    "sg:classifiers":[
        {
            "category":"Professional",
            "subcategory":"Advertising",
            "type":"Services"
        }
    ],
    "sg:phone":"+44 131 625 6000",
    "sg:postcode":"EH7 4EL",
    "sg:province":"City of Edinburgh",
    "sg:tags":[
        "agency"
    ],
    "wof:name":"The Union Advertising Agency Ltd.",
    "wof:placetype":"venue"
},
  "geometry": {"coordinates":[-3.1958839893,55.9619140625],"type":"Point"}
}