{
  "type": "Feature",
  "properties": {
    "addr:full":"St. Martins House, Ockham Rd South, East Horsley Leatherhead Surrey KT24 6RX",
    "addr:postcode":"kt24 6rx",
    "addr:street":"Ockham Rd",
    "iso:country":"GB",
    "sg:address":"St. Martins House, Ockham Rd South, East Horsley",
    "sg:city":"Leatherhead",
    "sg:classifiers":[
        {
            "category":"Professional",
            "subcategory":"Engineering",
            "type":"Services"
        }
    ],
    "sg:phone":"+44 1483 285511",
    "sg:postcode":"KT24 6RX",
    "sg:province":"Surrey",
    "sg:tags":[
        "contractor",
        "electrical",
        "engineer"
    ],
    "wof:name":"Solo Electrical Services",
    "wof:placetype":"venue"
},
  "geometry": {"coordinates":[-0.435424,51.2776298523],"type":"Point"}
}