{
  "type": "Feature",
  "properties": {
    "addr:full":"A6 Falcon Centre, Victoria Street, Chadderton Oldham Lancashire OL9 0HB",
    "addr:housenumber":"a6",
    "addr:postcode":"ol9 0hb",
    "addr:street":"Falcon Centre Victoria Street",
    "iso:country":"GB",
    "sg:address":"A6 Falcon Centre, Victoria Street, Chadderton",
    "sg:city":"Oldham",
    "sg:classifiers":[
        {
            "category":"Communications",
            "subcategory":"Film & Video Production",
            "type":"Services"
        },
        {
            "category":"Home & Garden",
            "subcategory":"Home Furnishings",
            "type":"Retail Goods"
        }
    ],
    "sg:phone":"+44 161 345 8335",
    "sg:postcode":"OL9 0HB",
    "sg:province":"Lancashire",
    "sg:tags":[
        "wall",
        "wallpaper",
        "covering"
    ],
    "wof:name":"T I C Wallcoverings Ltd.",
    "wof:placetype":"venue"
},
  "geometry": {"coordinates":[-2.1355099678,53.5478210449],"type":"Point"}
}