{
  "type": "Feature",
  "properties": {
    "addr:full":"9 Redmead Road Hayes Greater London UB3 4AU",
    "addr:housenumber":"9",
    "addr:postcode":"ub3 4au",
    "addr:street":"Redmead Road",
    "iso:country":"GB",
    "sg:address":"9 Redmead Road",
    "sg:city":"Hayes",
    "sg:classifiers":[
        {
            "category":"Real Estate",
            "subcategory":"Real Estate Operator",
            "type":"Services"
        }
    ],
    "sg:postcode":"UB3 4AU",
    "sg:province":"Greater London",
    "sg:tags":[
        "letting",
        "agent"
    ],
    "wof:name":"Heritage Property Services",
    "wof:placetype":"venue"
},
  "geometry": {"coordinates":[-0.4280749857,51.4986457825],"type":"Point"}
}