{
  "type": "Feature",
  "properties": {
    "addr:full":"Unit 6 Alphingto Retaill Prk, Marsh Barton Road Exeter Devon EX2 8LH",
    "addr:housenumber":"unit 6;prk",
    "addr:postcode":"ex2 8lh",
    "addr:street":"Marsh Barton Road",
    "iso:country":"GB",
    "sg:address":"Unit 6 Alphingto Retaill Prk, Marsh Barton Road",
    "sg:city":"Exeter",
    "sg:classifiers":[
        {
            "category":"Home & Garden",
            "subcategory":"Household Appliances",
            "type":"Retail Goods"
        }
    ],
    "sg:phone":"+44 845 600 7002",
    "sg:postcode":"EX2 8LH",
    "sg:province":"Devon",
    "sg:tags":[
        "electrical",
        "domestic"
    ],
    "wof:name":"Comet Group Plc",
    "wof:placetype":"venue"
},
  "geometry": {"coordinates":[-3.5360100269,50.7095413208],"type":"Point"}
}