{
  "type": "Feature",
  "properties": {
    "addr:full":"835 Garratt Lane, Tooting London Greater London SW17 0PG",
    "addr:housenumber":"835",
    "addr:postcode":"sw17 0pg",
    "addr:street":"Garratt Lane",
    "iso:country":"GB",
    "sg:address":"835 Garratt Lane, Tooting",
    "sg:city":"London",
    "sg:classifiers":[
        {
            "category":"Place Of Worship",
            "subcategory":"Synagogue",
            "type":"Public Place"
        },
        {
            "category":"Shopping",
            "type":"Retail Goods"
        }
    ],
    "sg:phone":"+44 20 8946 0293",
    "sg:postcode":"SW17 0PG",
    "sg:province":"Greater London",
    "sg:tags":[
        "top",
        "sunroof",
        "vinyl",
        "part",
        "accessory"
    ],
    "wof:name":"Southern Fabrics Ltd.",
    "wof:placetype":"venue"
},
  "geometry": {"coordinates":[-0.1821040064,51.4331474304],"type":"Point"}
}