{
  "type": "Feature",
  "properties": {
    "addr:full":"67 Victoria Road Worthing West Sussex BN11 1UN",
    "addr:housenumber":"67",
    "addr:postcode":"bn11 1un",
    "addr:street":"Victoria Road",
    "iso:country":"GB",
    "sg:address":"67 Victoria Road",
    "sg:city":"Worthing",
    "sg:classifiers":[
        {
            "category":"Wholesale",
            "subcategory":"Machinery & Supplies",
            "type":"Manufacturing & Wholesale Goods"
        }
    ],
    "sg:phone":"+44 1903 203154",
    "sg:postcode":"BN11 1UN",
    "sg:province":"West Sussex",
    "sg:tags":[
        "hydraulic"
    ],
    "wof:name":"Hydraulic Equipment Supply Co. Ltd.",
    "wof:placetype":"venue"
},
  "geometry": {"coordinates":[-0.3773419857,50.8173332214],"type":"Point"}
}