{
  "type": "Feature",
  "properties": {
    "addr:full":"138-141 Castle Market Sheffield South Yorkshire S1 2AF",
    "addr:housenumber":"138-141",
    "addr:postcode":"s1 2af",
    "addr:street":"Castle Market",
    "iso:country":"GB",
    "sg:address":"138-141 Castle Market",
    "sg:city":"Sheffield",
    "sg:classifiers":[
        {
            "category":"Shopping",
            "subcategory":"Gifts & Souvenirs",
            "type":"Retail Goods"
        }
    ],
    "sg:phone":"+44 114 275 9842",
    "sg:postcode":"S1 2AF",
    "sg:province":"South Yorkshire",
    "sg:tags":[
        "shop",
        "poster",
        "card"
    ],
    "wof:name":"The Postbag",
    "wof:placetype":"venue"
},
  "geometry": {"coordinates":[-1.465499,53.383091],"type":"Point"}
}