{
  "type": "Feature",
  "properties": {
    "addr:full":"18 Green Gardens Rhayader Powys LD6 5EH",
    "addr:housenumber":"18",
    "addr:postcode":"ld6 5eh",
    "addr:street":"Green Gardens",
    "iso:country":"GB",
    "sg:address":"18 Green Gardens",
    "sg:city":"Rhayader",
    "sg:classifiers":[
        {
            "category":"Professional",
            "subcategory":"Employment Agencies",
            "type":"Services"
        }
    ],
    "sg:phone":"+44 1597 810363",
    "sg:postcode":"LD6 5EH",
    "sg:province":"Powys",
    "sg:tags":[
        "consultant"
    ],
    "wof:name":"Mcintyre Building Services",
    "wof:placetype":"venue"
},
  "geometry": {"coordinates":[-3.5103828907,52.3068466187],"type":"Point"}
}