{
  "type": "Feature",
  "properties": {
    "addr:full":"Kirkby Stephen Prim Sch Kitchen, Nateby Road Kirkby Stephen Cumbria CA17 4AE",
    "addr:postcode":"ca17 4ae",
    "addr:street":"Nateby Road",
    "iso:country":"GB",
    "sg:address":"Kirkby Stephen Prim Sch Kitchen, Nateby Road",
    "sg:city":"Kirkby Stephen",
    "sg:classifiers":[
        {
            "category":"Professional",
            "type":"Services"
        }
    ],
    "sg:postcode":"CA17 4AE",
    "sg:province":"Cumbria",
    "sg:tags":[
        "caterer"
    ],
    "wof:name":"Cumbria Catering Services",
    "wof:placetype":"venue"
},
  "geometry": {"coordinates":[-2.348623,54.472717],"type":"Point"}
}