{
  "type": "Feature",
  "properties": {
    "iso:country":"GB",
    "sg:address":"Kirkby Stephen Prim Sch Kitchen, Nateby Road",
    "sg:city":"Kirkby Stephen",
    "sg:classifiers":[
        {
            "category":"Professional",
            "type":"Services"
        }
    ],
    "sg:postcode":"CA17 4AE",
    "sg:province":"Cumbria",
    "sg:tags":[
        "caterer"
    ],
    "wof:name":"Cumbria Catering Services",
    "wof:placetype":"venue"
},
  "geometry": {"coordinates":[-2.348623,54.472717],"type":"Point"}
}