{
  "type": "Feature",
  "properties": {
    "iso:country":"GB",
    "sg:address":"72 South Street",
    "sg:city":"Reading",
    "sg:classifiers":[
        {
            "category":"Insurance",
            "subcategory":"Insurance Agent",
            "type":"Services"
        }
    ],
    "sg:phone":"+44 118 956 8800",
    "sg:postcode":"RG1 4RA",
    "sg:province":"Berkshire",
    "sg:tags":[
        "broker"
    ],
    "wof:name":"John Wason (Insurance Brokers) Ltd.",
    "wof:placetype":"venue"
},
  "geometry": {"coordinates":[-0.962972,51.45261],"type":"Point"}
}