{
  "type": "Feature",
  "properties": {
    "addr:full":"Regent House, Regent Street Wrexham Wrexham LL11 1PR",
    "addr:postcode":"ll11 1pr",
    "addr:street":"Regent Street",
    "iso:country":"GB",
    "sg:address":"Regent House, Regent Street",
    "sg:city":"Wrexham",
    "sg:classifiers":[
        {
            "category":"Organizations",
            "subcategory":"Non-profit Organization",
            "type":"Services"
        }
    ],
    "sg:phone":"+44 1978 310414",
    "sg:postcode":"LL11 1PR",
    "sg:province":"Wrexham",
    "sg:tags":[
        "organisation",
        "voluntary",
        "charity"
    ],
    "wof:name":"Clwyd Carers Project",
    "wof:placetype":"venue"
},
  "geometry": {"coordinates":[-2.998044,53.047466],"type":"Point"}
}