{
  "type": "Feature",
  "properties": {
    "addr:full":"The Barn, Woodrow Lane, Catshill Bromsgrove Worcestershire B61 0PL",
    "addr:postcode":"b61 0pl",
    "addr:street":"Woodrow Lane Catshill",
    "iso:country":"GB",
    "sg:address":"The Barn, Woodrow Lane, Catshill",
    "sg:city":"Bromsgrove",
    "sg:classifiers":[
        {
            "category":"Building & Trades",
            "subcategory":"Construction",
            "type":"Services"
        }
    ],
    "sg:phone":"+44 121 447 7151",
    "sg:postcode":"B61 0PL",
    "sg:province":"Worcestershire",
    "sg:tags":[
        "builder"
    ],
    "wof:name":"B Mogg Building Contractors",
    "wof:placetype":"venue"
},
  "geometry": {"coordinates":[-2.0486500263,52.3715515137],"type":"Point"}
}