{
  "type": "Feature",
  "properties": {
    "iso:country":"GB",
    "sg:address":"90-100 York St",
    "sg:city":"Hull",
    "sg:classifiers":[
        {
            "category":"Freight",
            "type":"Transportation"
        }
    ],
    "sg:phone":"+44 1482 325027",
    "sg:postcode":"HU2 0QD",
    "sg:province":"East Riding of Yorkshire",
    "sg:tags":[
        "haulage",
        "road"
    ],
    "wof:name":"Huon Haulage Ltd",
    "wof:placetype":"venue"
},
  "geometry": {"coordinates":[-0.330815,53.75449],"type":"Point"}
}