{
  "type": "Feature",
  "properties": {
    "addr:full":"7 Wadham Street Weston-super-mare Somerset BS23 1JY",
    "addr:housenumber":"7",
    "addr:postcode":"bs23 1jy",
    "addr:street":"Wadham Street",
    "iso:country":"GB",
    "sg:address":"7 Wadham Street",
    "sg:city":"Weston-super-mare",
    "sg:classifiers":[
        {
            "category":"Retail",
            "subcategory":"Auto Repair",
            "type":"Services"
        }
    ],
    "sg:postcode":"BS23 1JY",
    "sg:province":"Somerset",
    "sg:tags":[
        "modification",
        "garage"
    ],
    "wof:name":"Wadham Street Garage",
    "wof:placetype":"venue"
},
  "geometry": {"coordinates":[-2.9799718857,51.3507041931],"type":"Point"}
}