{
  "type": "Feature",
  "properties": {
    "iso:country":"GB",
    "sg:address":"Media Ho, Tipnor Wharf, Twyford Ave",
    "sg:city":"Portsmouth",
    "sg:classifiers":[
        {
            "category":"Communications",
            "type":"Services"
        }
    ],
    "sg:phone":"+44 23 9235 8853",
    "sg:postcode":"PO2 8PE",
    "sg:province":"Hampshire",
    "sg:tags":[
        "broadcasting"
    ],
    "wof:name":"Radio Victory Ltd",
    "wof:placetype":"venue"
},
  "geometry": {"coordinates":[-1.08468,50.82198],"type":"Point"}
}