{
  "type": "Feature",
  "properties": {
    "addr:full":"11 Old Town Street Plymouth Devon PL1 1DA",
    "addr:housenumber":"11",
    "addr:postcode":"pl1 1da",
    "addr:street":"Old Town Street",
    "iso:country":"GB",
    "sg:address":"11 Old Town Street",
    "sg:city":"Plymouth",
    "sg:classifiers":[
        {
            "category":"Cafe",
            "type":"Food & Drink"
        }
    ],
    "sg:postcode":"PL1 1DA",
    "sg:province":"Devon",
    "sg:tags":[
        "tea",
        "room"
    ],
    "wof:name":"Les Jardins De Bagatelle",
    "wof:placetype":"venue"
},
  "geometry": {"coordinates":[-4.139183,50.370911],"type":"Point"}
}