{
  "type": "Feature",
  "properties": {
    "iso:country":"GB",
    "sg:address":"Tyn Y Foel, Dwyran",
    "sg:city":"Llanfairpwllgwyngyll",
    "sg:classifiers":[
        {
            "category":"Sports & Exercise",
            "subcategory":"Stables",
            "type":"Entertainment"
        }
    ],
    "sg:phone":"+44 1248 430377",
    "sg:postcode":"LL61 6LQ",
    "sg:province":"Isle of Anglesey",
    "sg:tags":[
        "equestrian",
        "centre",
        "livery",
        "schools",
        "riding",
        "education"
    ],
    "wof:name":"Y Tal Foel Riding & Holiday Centre",
    "wof:placetype":"venue"
},
  "geometry": {"coordinates":[-4.324624,53.166794],"type":"Point"}
}