{
  "type": "Feature",
  "properties": {
    "iso:country":"GB",
    "sg:address":"Carn Iw Church Lane, Gaydon",
    "sg:city":"Warwick",
    "sg:classifiers":[
        {
            "category":"Professional",
            "subcategory":"Computer Services",
            "type":"Services"
        }
    ],
    "sg:phone":"+44 1926 641578",
    "sg:postcode":"CV35 0EY",
    "sg:province":"Warwickshire",
    "sg:tags":[
        "system",
        "software"
    ],
    "wof:name":"Q.E.D Software Development",
    "wof:placetype":"venue"
},
  "geometry": {"coordinates":[-1.4705460072,52.1832809448],"type":"Point"}
}