{
  "type": "Feature",
  "properties": {
    "addr:full":"Office 1 2a Wickham Avenue Bexhill-on-sea East Sussex TN39 3EW",
    "addr:housenumber":"1 2a",
    "addr:postcode":"tn39 3ew",
    "addr:street":"Wickham Avenue",
    "iso:country":"GB",
    "sg:address":"Office 1 2a Wickham Avenue",
    "sg:city":"Bexhill-on-sea",
    "sg:classifiers":[
        {
            "category":"Building & Trades",
            "subcategory":"Construction",
            "type":"Services"
        }
    ],
    "sg:phone":"+44 1424 221707",
    "sg:postcode":"TN39 3EW",
    "sg:province":"East Sussex",
    "sg:tags":[
        "builder"
    ],
    "wof:name":"S J Building Services Fuller",
    "wof:placetype":"venue"
},
  "geometry": {"coordinates":[0.469494,50.840023],"type":"Point"}
}