{
  "type": "Feature",
  "properties": {
    "addr:full":"161 Knightsbridge London Greater London SW1X 7PA",
    "addr:housenumber":"161",
    "addr:postcode":"sw1x 7pa",
    "addr:street":"Knightsbridge",
    "iso:country":"GB",
    "sg:address":"161 Knightsbridge",
    "sg:city":"London",
    "sg:classifiers":[
        {
            "category":"Home & Garden",
            "subcategory":"Carpets & Floor Coverings",
            "type":"Retail Goods"
        }
    ],
    "sg:phone":"+44 20 7584 6902",
    "sg:postcode":"SW1X 7PA",
    "sg:province":"Greater London",
    "sg:tags":[
        "carpets",
        "rug",
        "matting"
    ],
    "wof:name":"Ibraham Samad",
    "wof:placetype":"venue"
},
  "geometry": {"coordinates":[-0.162689,51.501671],"type":"Point"}
}