{
  "type": "Feature",
  "properties": {
    "addr:full":"3 Capital Quay Salford Greater Manchester M5 2WL",
    "addr:housenumber":"3",
    "addr:postcode":"m5 2wl",
    "addr:street":"Capital Quay",
    "iso:country":"GB",
    "sg:address":"3 Capital Quay",
    "sg:city":"Salford",
    "sg:classifiers":[
        {
            "category":"Restaurant",
            "type":"Food & Drink"
        }
    ],
    "sg:phone":"+44 161 877 1770",
    "sg:postcode":"M5 2WL",
    "sg:province":"Greater Manchester",
    "sg:tags":[
        "mexican"
    ],
    "wof:name":"City Centre Restaurants (U K) Ltd.",
    "wof:placetype":"venue"
},
  "geometry": {"coordinates":[-2.2836930752,53.4705085754],"type":"Point"}
}