{
  "type": "Feature",
  "properties": {
    "iso:country":"GB",
    "sg:address":"33 Cofton Hill, Cockwood, Starcross",
    "sg:city":"Exeter",
    "sg:classifiers":[
        {
            "category":"Shopping",
            "subcategory":"Department Store",
            "type":"Retail Goods"
        }
    ],
    "sg:postcode":"EX6 8RB",
    "sg:province":"Devon",
    "wof:name":"Topshop",
    "wof:placetype":"venue"
},
  "geometry": {"coordinates":[-3.45146,50.612686],"type":"Point"}
}