{
  "type": "Feature",
  "properties": {
    "iso:country":"GB",
    "sg:address":"24 Church Meadow",
    "sg:city":"Surbiton",
    "sg:classifiers":[
        {
            "category":"Professional",
            "subcategory":"Computer Services",
            "type":"Services"
        }
    ],
    "sg:phone":"+44 20 8398 8991",
    "sg:postcode":"KT6 5EW",
    "sg:province":"Surrey",
    "sg:tags":[
        "aided",
        "design"
    ],
    "wof:name":"Harry Skinner M Inst CES",
    "wof:placetype":"venue"
},
  "geometry": {"coordinates":[-0.313989,51.379002],"type":"Point"}
}