{
  "type": "Feature",
  "properties": {
    "iso:country":"GB",
    "sg:address":"430 Shirley Rd",
    "sg:city":"Birmingham",
    "sg:classifiers":[
        {
            "category":"Manufacturing",
            "subcategory":"Petroleum Products",
            "type":"Manufacturing & Wholesale Goods"
        }
    ],
    "sg:phone":"+44 121 777 2619",
    "sg:postcode":"B27 7NX",
    "sg:province":"West Midlands",
    "sg:tags":[
        "double",
        "glazing"
    ],
    "wof:name":"Hayes Double Glazing",
    "wof:placetype":"venue"
},
  "geometry": {"coordinates":[-1.832509,52.435825],"type":"Point"}
}