{
  "type": "Feature",
  "properties": {
    "iso:country":"GB",
    "sg:address":"14 Middleknowe",
    "sg:city":"Edinburgh",
    "sg:classifiers":[
        {
            "category":"Building & Trades",
            "subcategory":"Construction",
            "type":"Services"
        }
    ],
    "sg:phone":"+44 131 453 3850",
    "sg:postcode":"EH14 2TR",
    "sg:province":"City of Edinburgh",
    "sg:tags":[
        "glazier"
    ],
    "wof:name":"M Conington Painter & Decorator",
    "wof:placetype":"venue"
},
  "geometry": {"coordinates":[-3.296511,55.915829],"type":"Point"}
}