{
  "type": "Feature",
  "properties": {
    "iso:country":"GB",
    "sg:address":"Forge House, 66 High St",
    "sg:city":"Kingston Upon Thames",
    "sg:classifiers":[
        {
            "category":"Professional",
            "subcategory":"Computer Services",
            "type":"Services"
        }
    ],
    "sg:phone":"+44 20 8541 1999",
    "sg:postcode":"KT1 1HN",
    "sg:province":"Greater London",
    "sg:tags":[
        "system",
        "software"
    ],
    "wof:name":"LUSAS",
    "wof:placetype":"venue"
},
  "geometry": {"coordinates":[-0.308454,51.405579],"type":"Point"}
}