{
  "type": "Feature",
  "properties": {
    "iso:country":"GB",
    "sg:address":"78 Red Lion Lane",
    "sg:city":"London",
    "sg:classifiers":[
        {
            "category":"Bars & Pubs",
            "type":"Food & Drink"
        }
    ],
    "sg:phone":"+44 20 8856 4374",
    "sg:postcode":"SE18 4LE",
    "sg:province":"Greater London",
    "sg:tags":[
        "pubs",
        "inn"
    ],
    "wof:name":"The Eagle",
    "wof:placetype":"venue"
},
  "geometry": {"coordinates":[0.06064,51.471764],"type":"Point"}
}