{
  "type": "Feature",
  "properties": {
    "iso:country":"GB",
    "sg:address":"Withens La",
    "sg:city":"Wallasey",
    "sg:classifiers":[
        {
            "category":"Place Of Worship",
            "type":"Public Place"
        }
    ],
    "sg:phone":"+44 151 639 1553",
    "sg:postcode":"L45 7NQ",
    "sg:province":"Merseyside",
    "wof:name":"St Mary's C of E Church",
    "wof:placetype":"venue"
},
  "geometry": {"coordinates":[-3.038544,53.422779],"type":"Point"}
}