{
  "type": "Feature",
  "properties": {
    "iso:country":"GB",
    "sg:address":"1 Walton Rd",
    "sg:city":"East Molesey",
    "sg:classifiers":[
        {
            "category":"Government",
            "subcategory":"Police Station",
            "type":"Public Place"
        }
    ],
    "sg:phone":"+44 20 8941 3838",
    "sg:postcode":"KT8 0DE",
    "sg:province":"Greater London",
    "sg:tags":[
        "support"
    ],
    "wof:name":"Metropolitan Police Service",
    "wof:placetype":"venue"
},
  "geometry": {"coordinates":[-0.349281013,51.3987960815],"type":"Point"}
}