{
  "type": "Feature",
  "properties": {
    "addr:full":"38 Church Road Northolt Greater London UB5 5AB",
    "addr:housenumber":"38",
    "addr:postcode":"ub5 5ab",
    "addr:street":"Church Road",
    "iso:country":"GB",
    "sg:address":"38 Church Road",
    "sg:city":"Northolt",
    "sg:classifiers":[
        {
            "category":"Personal",
            "subcategory":"Beauty Salon",
            "type":"Services"
        }
    ],
    "sg:phone":"+44 20 8845 3062",
    "sg:postcode":"UB5 5AB",
    "sg:province":"Greater London",
    "sg:tags":[
        "lady",
        "hairdresser"
    ],
    "wof:name":"Fringe Benefits",
    "wof:placetype":"venue"
},
  "geometry": {"coordinates":[-0.372985,51.544769],"type":"Point"}
}