{
  "type": "Feature",
  "properties": {
    "iso:country":"GB",
    "sg:address":"20 Newcomen Road",
    "sg:city":"Dartmouth",
    "sg:classifiers":[
        {
            "category":"Place Of Worship",
            "type":"Public Place"
        }
    ],
    "sg:phone":"+44 1803 832860",
    "sg:postcode":"TQ6 9BN",
    "sg:province":"Devon",
    "wof:name":"St. John the baptist R C Church",
    "wof:placetype":"venue"
},
  "geometry": {"coordinates":[-3.578635931,50.3490638733],"type":"Point"}
}