{
  "type": "Feature",
  "properties": {
    "iso:country":"GB",
    "sg:address":"Unit 8 & 9 Long Lane Industrial Estate, Long Lane",
    "sg:city":"Craven Arms",
    "sg:classifiers":[
        {
            "category":"Manufacturing",
            "subcategory":"Electronics",
            "type":"Manufacturing & Wholesale Goods"
        }
    ],
    "sg:phone":"+44 1588 673411",
    "sg:postcode":"SY7 8DU",
    "sg:province":"Herefordshire",
    "sg:tags":[
        "mnfrs",
        "transformer"
    ],
    "wof:name":"Reo Ltd",
    "wof:placetype":"venue"
},
  "geometry": {"coordinates":[-2.84243,52.447731],"type":"Point"}
}