{
  "type": "Feature",
  "properties": {
    "addr:full":"East Garleton, Drem North Berwick East Lothian EH39 5BB",
    "addr:postcode":"eh39 5bb",
    "addr:street":"East;Drem;Berwick",
    "iso:country":"GB",
    "sg:address":"East Garleton, Drem",
    "sg:city":"North Berwick",
    "sg:classifiers":[
        {
            "category":"Farming",
            "subcategory":"Farm",
            "type":"Manufacturing & Wholesale Goods"
        }
    ],
    "sg:phone":"+44 1620 880511",
    "sg:postcode":"EH39 5BB",
    "sg:province":"East Lothian",
    "sg:tags":[
        "mixed",
        "crop"
    ],
    "wof:name":"John Shedden & Partners",
    "wof:placetype":"venue"
},
  "geometry": {"coordinates":[-2.786355,56.006172],"type":"Point"}
}