{
  "type": "Feature",
  "properties": {
    "iso:country":"GB",
    "sg:address":"20 Links Road",
    "sg:city":"Epsom",
    "sg:classifiers":[
        {
            "category":"Professional",
            "subcategory":"Engineering",
            "type":"Services"
        },
        {
            "category":"Building & Trades",
            "subcategory":"Electrical",
            "type":"Services"
        }
    ],
    "sg:phone":"+44 1372 743066",
    "sg:postcode":"KT17 3PS",
    "sg:province":"Surrey",
    "sg:tags":[
        "engineer",
        "electrician",
        "contractor"
    ],
    "wof:name":"T F Connolly",
    "wof:placetype":"venue"
},
  "geometry": {"coordinates":[-0.245708,51.329433],"type":"Point"}
}