{
  "type": "Feature",
  "properties": {
    "iso:country":"GB",
    "sg:address":"Geevor Ho, Trewellard Hill",
    "sg:city":"Penzance",
    "sg:classifiers":[
        {
            "category":"Building & Trades",
            "subcategory":"Cleaning & Sanitation",
            "type":"Services"
        }
    ],
    "sg:phone":"+44 1736 788302",
    "sg:postcode":"TR19 7TE",
    "sg:province":"Cornwall",
    "sg:tags":[
        "steam"
    ],
    "wof:name":"J & J Power Cleaning",
    "wof:placetype":"venue"
},
  "geometry": {"coordinates":[-5.6695590019,50.1444244385],"type":"Point"}
}