{
  "type": "Feature",
  "properties": {
    "iso:country":"GB",
    "sg:address":"Angel Hill",
    "sg:city":"Tiverton",
    "sg:classifiers":[
        {
            "category":"Education",
            "subcategory":"Library",
            "type":"Public Place"
        },
        {
            "category":"Government",
            "subcategory":"Office",
            "type":"Public Place"
        }
    ],
    "sg:phone":"+44 1884 252937",
    "sg:postcode":"EX16 6PE",
    "sg:province":"Devon",
    "sg:tags":[
        "book",
        "local"
    ],
    "wof:name":"Tiverton Library",
    "wof:placetype":"venue"
},
  "geometry": {"coordinates":[-3.489751,50.902798],"type":"Point"}
}