{
  "type": "Feature",
  "properties": {
    "addr:full":"Unit 1, Block A Billericay Essex CM11 1QE",
    "addr:housenumber":"unit 1 block a",
    "addr:postcode":"cm11 1qe",
    "iso:country":"GB",
    "sg:address":"Unit 1, Block A",
    "sg:city":"Billericay",
    "sg:classifiers":[
        {
            "category":"Professional",
            "subcategory":"Printing & Photocopies",
            "type":"Services"
        }
    ],
    "sg:postcode":"CM11 1QE",
    "sg:province":"Essex",
    "sg:tags":[
        "plate",
        "lithographic",
        "maker"
    ],
    "wof:name":"Windsor Reprographics",
    "wof:placetype":"venue"
},
  "geometry": {"coordinates":[0.48286,51.635109],"type":"Point"}
}