{
  "type": "Feature",
  "properties": {
    "addr:full":"Lethaby House Residential Home, 3 Moor Lane Budleigh Salterton Devon EX9 6PW",
    "addr:housenumber":"3",
    "addr:postcode":"ex9 6pw",
    "addr:street":"Moor Lane",
    "iso:country":"GB",
    "sg:address":"Lethaby House Residential Home, 3 Moor Lane",
    "sg:city":"Budleigh Salterton",
    "sg:classifiers":[
        {
            "category":"Organizations",
            "subcategory":"Community Association",
            "type":"Services"
        }
    ],
    "sg:phone":"+44 1395 442929",
    "sg:postcode":"EX9 6PW",
    "sg:province":"Devon",
    "sg:tags":[
        "co-operatives",
        "society",
        "housing",
        "trust"
    ],
    "wof:name":"Abbeyfield Budleigh Salterton Society Lt",
    "wof:placetype":"venue"
},
  "geometry": {"coordinates":[-3.3298230171,50.6340103149],"type":"Point"}
}