{
  "type": "Feature",
  "properties": {
    "addr:full":"159 Main Rd, Sutton At Hone Dartford Kent DA4 9HW",
    "addr:housenumber":"159",
    "addr:postcode":"da4 9hw",
    "addr:street":"Main Rd",
    "iso:country":"GB",
    "sg:address":"159 Main Rd, Sutton At Hone",
    "sg:city":"Dartford",
    "sg:classifiers":[
        {
            "category":"Building & Trades",
            "subcategory":"Construction",
            "type":"Services"
        }
    ],
    "sg:postcode":"DA4 9HW",
    "sg:province":"Kent",
    "sg:tags":[
        "roofing"
    ],
    "wof:name":"Bennett,Andrew J,",
    "wof:placetype":"venue"
},
  "geometry": {"coordinates":[0.237828,51.405907],"type":"Point"}
}