{
  "type": "Feature",
  "properties": {
    "addr:full":"4 Bogwood Ct, Mayfield Dalkeith City of Edinburgh EH22 5DG",
    "addr:housenumber":"4",
    "addr:postcode":"eh22 5dg",
    "addr:street":"Bogwood Ct",
    "iso:country":"GB",
    "sg:address":"4 Bogwood Ct, Mayfield",
    "sg:city":"Dalkeith",
    "sg:classifiers":[
        {
            "category":"Banks & Credit Unions",
            "subcategory":"Financial Services",
            "type":"Services"
        }
    ],
    "sg:postcode":"EH22 5DG",
    "sg:province":"City of Edinburgh",
    "sg:tags":[
        "consultant"
    ],
    "wof:name":"Shopacheck Financial Services Ltd",
    "wof:placetype":"venue"
},
  "geometry": {"coordinates":[-3.040945,55.874332],"type":"Point"}
}