{
  "type": "Feature",
  "properties": {
    "addr:full":"132 St Pancras Way London Greater London NW1 9NB",
    "addr:housenumber":"132",
    "addr:postcode":"nw1 9nb",
    "addr:street":"St Pancras Way",
    "iso:country":"GB",
    "sg:address":"132 St Pancras Way",
    "sg:city":"London",
    "sg:classifiers":[
        {
            "category":"Shopping",
            "subcategory":"Musical Instruments",
            "type":"Retail Goods"
        }
    ],
    "sg:phone":"+44 20 7482 5424",
    "sg:postcode":"NW1 9NB",
    "sg:province":"Greater London",
    "sg:tags":[
        "music",
        "sheet"
    ],
    "wof:name":"Dots-the Camden Music Shop",
    "wof:placetype":"venue"
},
  "geometry": {"coordinates":[-0.140065,51.543953],"type":"Point"}
}