{
  "type": "Feature",
  "properties": {
    "addr:full":"2-4 Astley Road, Irlam Manchester Greater Manchester M44 6AB",
    "addr:housenumber":"2-4",
    "addr:postcode":"m44 6ab",
    "addr:street":"Astley Road",
    "iso:country":"GB",
    "sg:address":"2-4 Astley Road, Irlam",
    "sg:city":"Manchester",
    "sg:classifiers":[
        {
            "category":"Organizations",
            "subcategory":"Membership Organization",
            "type":"Services"
        }
    ],
    "sg:postcode":"M44 6AB",
    "sg:province":"Greater Manchester",
    "sg:tags":[
        "club"
    ],
    "wof:name":"The Irlam Conservative Club Co. Ltd.",
    "wof:placetype":"venue"
},
  "geometry": {"coordinates":[-2.428678,53.438137],"type":"Point"}
}