{
  "type": "Feature",
  "properties": {
    "addr:full":"Unit 9b, Weltech Centre Welwyn Garden City Hertfordshire AL7 2AA",
    "addr:housenumber":"unit 9b",
    "addr:postcode":"al7 2aa",
    "addr:street":"Weltech Centre",
    "iso:country":"GB",
    "sg:address":"Unit 9b, Weltech Centre",
    "sg:city":"Welwyn Garden City",
    "sg:classifiers":[
        {
            "category":"Place Of Worship",
            "type":"Public Place"
        }
    ],
    "sg:phone":"+44 1707 324466",
    "sg:postcode":"AL7 2AA",
    "sg:province":"Hertfordshire",
    "wof:name":"Churchill  Minty & Friend Ltd.",
    "wof:placetype":"venue"
},
  "geometry": {"coordinates":[-0.1819799989,51.797618866],"type":"Point"}
}