{
  "type": "Feature",
  "properties": {
    "addr:full":"The Green, Caston Attleborough Norfolk NR17 1DB",
    "addr:postcode":"nr17 1db",
    "addr:street":"Green",
    "iso:country":"GB",
    "sg:address":"The Green, Caston",
    "sg:city":"Attleborough",
    "sg:classifiers":[
        {
            "category":"Bars & Pubs",
            "type":"Food & Drink"
        }
    ],
    "sg:phone":"+44 1953 483896",
    "sg:postcode":"NR17 1DB",
    "sg:province":"Norfolk",
    "sg:tags":[
        "pubs",
        "inn"
    ],
    "wof:name":"Red Lion Inn",
    "wof:placetype":"venue"
},
  "geometry": {"coordinates":[0.888042,52.541168],"type":"Point"}
}