{
  "type": "Feature",
  "properties": {
    "addr:full":"89 East Hill Colchester Essex CO1 2QN",
    "addr:housenumber":"89",
    "addr:postcode":"co1 2qn",
    "addr:street":"East Hill Colchester",
    "iso:country":"GB",
    "sg:address":"89 East Hill",
    "sg:city":"Colchester",
    "sg:classifiers":[
        {
            "category":"Communications",
            "subcategory":"Newspaper",
            "type":"Services"
        }
    ],
    "sg:phone":"+44 1206 505900",
    "sg:postcode":"CO1 2QN",
    "sg:province":"Essex",
    "sg:tags":[
        "magazine"
    ],
    "wof:name":"Aceville Magazines Ltd.",
    "wof:placetype":"venue"
},
  "geometry": {"coordinates":[0.9091899991,51.8900604248],"type":"Point"}
}