{
  "type": "Feature",
  "properties": {
    "addr:full":"6 Highfield Lane, Orgreave Sheffield South Yorkshire S13 9NA",
    "addr:housenumber":"6",
    "addr:postcode":"s13 9na",
    "addr:street":"Highfield Lane",
    "iso:country":"GB",
    "sg:address":"6 Highfield Lane, Orgreave",
    "sg:city":"Sheffield",
    "sg:classifiers":[
        {
            "category":"Manufacturing",
            "subcategory":"Buildings",
            "type":"Manufacturing & Wholesale Goods"
        }
    ],
    "sg:phone":"+44 114 254 0188",
    "sg:postcode":"S13 9NA",
    "sg:province":"South Yorkshire",
    "sg:tags":[
        "portable"
    ],
    "wof:name":"Pasuda Buildings Ltd.",
    "wof:placetype":"venue"
},
  "geometry": {"coordinates":[-1.3734869957,53.3754768372],"type":"Point"}
}