{
  "type": "Feature",
  "properties": {
    "addr:full":"20 Berachah Road Torquay Devon TQ1 3AX",
    "addr:housenumber":"20",
    "addr:postcode":"tq1 3ax",
    "addr:street":"Berachah Road",
    "iso:country":"GB",
    "sg:address":"20 Berachah Road",
    "sg:city":"Torquay",
    "sg:classifiers":[
        {
            "category":"Building & Trades",
            "subcategory":"Construction",
            "type":"Services"
        }
    ],
    "sg:phone":"+44 1803 200079",
    "sg:postcode":"TQ1 3AX",
    "sg:province":"Devon",
    "sg:tags":[
        "builder"
    ],
    "wof:name":"Rogers Construction",
    "wof:placetype":"venue"
},
  "geometry": {"coordinates":[-3.5289869308,50.4722137451],"type":"Point"}
}