{
  "type": "Feature",
  "properties": {
    "iso:country":"GB",
    "sg:address":"786 Oxford Road, Kennet House",
    "sg:city":"Reading",
    "sg:classifiers":[
        {
            "category":"Banks & Credit Unions",
            "subcategory":"Financial Services",
            "type":"Services"
        }
    ],
    "sg:phone":"+44 118 950 8973",
    "sg:postcode":"RG30 1EL",
    "sg:province":"Berkshire",
    "sg:tags":[
        "consultant"
    ],
    "wof:name":"Welcome Financial Services Ltd.",
    "wof:placetype":"venue"
},
  "geometry": {"coordinates":[-1.0105390549,51.4609184265],"type":"Point"}
}