{
  "type": "Feature",
  "properties": {
    "iso:country":"GB",
    "sg:address":"Mountain Hare",
    "sg:city":"Merthyr Tydfil",
    "sg:classifiers":[
        {
            "category":"Bars & Pubs",
            "type":"Food & Drink"
        }
    ],
    "sg:phone":"+44 1685 722131",
    "sg:postcode":"CF47 0LH",
    "sg:province":"Merthyr Tydfil",
    "sg:tags":[
        "pubs",
        "inn"
    ],
    "wof:name":"Williamsj",
    "wof:placetype":"venue"
},
  "geometry": {"coordinates":[-3.36193,51.74461],"type":"Point"}
}