{
  "type": "Feature",
  "properties": {
    "iso:country":"GB",
    "sg:address":"2 Whitehorse Street",
    "sg:city":"Baldock",
    "sg:classifiers":[
        {
            "category":"Shopping",
            "subcategory":"Mobile Phones",
            "type":"Retail Goods"
        }
    ],
    "sg:phone":"+44 1462 896800",
    "sg:postcode":"SG7 6QN",
    "sg:province":"Bedfordshire",
    "wof:name":"Half-Price Phone Co",
    "wof:placetype":"venue"
},
  "geometry": {"coordinates":[-0.18852,51.989716],"type":"Point"}
}