{
  "type": "Feature",
  "properties": {
    "addr:full":"216-218 Ocean Road South Shields Tyne and Wear NE33 2JQ",
    "addr:housenumber":"216-218",
    "addr:postcode":"ne33 2jq",
    "addr:street":"Ocean Road",
    "iso:country":"GB",
    "sg:address":"216-218 Ocean Road",
    "sg:city":"South Shields",
    "sg:classifiers":[
        {
            "category":"Restaurant",
            "type":"Food & Drink"
        }
    ],
    "sg:phone":"+44 191 427 1707",
    "sg:postcode":"NE33 2JQ",
    "sg:province":"Tyne and Wear",
    "sg:tags":[
        "indian",
        "-"
    ],
    "wof:name":"Royal Tandoori",
    "wof:placetype":"venue"
},
  "geometry": {"coordinates":[-1.4244459867,55.0003547668],"type":"Point"}
}