{
  "type": "Feature",
  "properties": {
    "iso:country":"GB",
    "sg:address":"9 St Johns Road",
    "sg:city":"Arlesey",
    "sg:classifiers":[
        {
            "category":"Home & Garden",
            "subcategory":"Carpets & Floor Coverings",
            "type":"Retail Goods"
        }
    ],
    "sg:postcode":"SG15 6ST",
    "sg:province":"Bedfordshire",
    "sg:tags":[
        "carpets",
        "rug",
        "matting"
    ],
    "wof:name":"Herts & Beds Carpet Fitting Services",
    "wof:placetype":"venue"
},
  "geometry": {"coordinates":[-0.2648960054,52.0091018677],"type":"Point"}
}