{
  "type": "Feature",
  "properties": {
    "addr:full":"27 Bifield Road, Stockworth Bristol City of Bristol BS14 8TJ",
    "addr:housenumber":"27",
    "addr:postcode":"bs14 8tj",
    "addr:street":"Bifield Road",
    "iso:country":"GB",
    "sg:address":"27 Bifield Road, Stockworth",
    "sg:city":"Bristol",
    "sg:classifiers":[
        {
            "category":"Building & Trades",
            "subcategory":"Construction",
            "type":"Services"
        }
    ],
    "sg:postcode":"BS14 8TJ",
    "sg:province":"City of Bristol",
    "sg:tags":[
        "roofing"
    ],
    "wof:name":"A J H Roofing Services",
    "wof:placetype":"venue"
},
  "geometry": {"coordinates":[-2.5399041176,51.4107398987],"type":"Point"}
}