{
  "type": "Feature",
  "properties": {
    "addr:full":"Unit 2, Thomas Street Congleton Cheshire CW12 1QU",
    "addr:housenumber":"unit 2",
    "addr:postcode":"cw12 1qu",
    "addr:street":"Thomas Street",
    "iso:country":"GB",
    "sg:address":"Unit 2, Thomas Street",
    "sg:city":"Congleton",
    "sg:classifiers":[
        {
            "category":"Wholesale",
            "subcategory":"Machinery & Supplies",
            "type":"Manufacturing & Wholesale Goods"
        }
    ],
    "sg:phone":"+44 1260 299438",
    "sg:postcode":"CW12 1QU",
    "sg:province":"Cheshire",
    "sg:tags":[
        "pump"
    ],
    "wof:name":"G M C (U K) Ltd.",
    "wof:placetype":"venue"
},
  "geometry": {"coordinates":[-2.2051889896,53.1648406982],"type":"Point"}
}