{
  "type": "Feature",
  "properties": {
    "iso:country":"GB",
    "sg:address":"17 Main Road, Weston Zoyland",
    "sg:city":"Bridgwater",
    "sg:classifiers":[
        {
            "category":"Government",
            "subcategory":"Post Office",
            "type":"Public Place"
        }
    ],
    "sg:phone":"+44 1278 691203",
    "sg:postcode":"TA7 0EB",
    "sg:province":"Somerset",
    "wof:name":"Weston Zoyland Sub Post Office",
    "wof:placetype":"venue"
},
  "geometry": {"coordinates":[-2.8966948986,51.0902671814],"type":"Point"}
}