{
  "type": "Feature",
  "properties": {
    "addr:full":"Sawmills, Corby Glend Grantham Leicestershire NG33 4LB",
    "addr:postcode":"ng33 4lb",
    "iso:country":"GB",
    "sg:address":"Sawmills, Corby Glend",
    "sg:city":"Grantham",
    "sg:classifiers":[
        {
            "category":"Manufacturing",
            "subcategory":"Lumber",
            "type":"Manufacturing & Wholesale Goods"
        }
    ],
    "sg:phone":"+44 1476 550231",
    "sg:postcode":"NG33 4LB",
    "sg:province":"Leicestershire",
    "sg:tags":[
        "merchant",
        "merchants",
        "importer",
        "agent",
        "timber"
    ],
    "wof:name":"Harry Adcock Ltd",
    "wof:placetype":"venue"
},
  "geometry": {"coordinates":[-0.5206040144,52.8121376038],"type":"Point"}
}