{
  "type": "Feature",
  "properties": {
    "iso:country":"GB",
    "sg:address":"181a Aylsham Rd",
    "sg:city":"Norwich",
    "sg:classifiers":[
        {
            "category":"Building & Trades",
            "subcategory":"Construction",
            "type":"Services"
        }
    ],
    "sg:phone":"+44 1603 488227",
    "sg:postcode":"NR3 2AD",
    "sg:province":"Norfolk",
    "sg:tags":[
        "dry",
        "lining",
        "plasterers",
        "screeders"
    ],
    "wof:name":"Edwards & Co Ltd",
    "wof:placetype":"venue"
},
  "geometry": {"coordinates":[1.283331,52.646679],"type":"Point"}
}