{
  "type": "Feature",
  "properties": {
    "iso:country":"GB",
    "sg:address":"31 Summertown Road",
    "sg:city":"Glasgow",
    "sg:classifiers":[
        {
            "category":"Arts & Performance",
            "subcategory":"Music",
            "type":"Entertainment"
        }
    ],
    "sg:postcode":"G51 2QA",
    "sg:province":"Glasgow City",
    "sg:tags":[
        "mobile",
        "disco"
    ],
    "wof:name":"Big Beat Promotions",
    "wof:placetype":"venue"
},
  "geometry": {"coordinates":[-4.3034329414,55.8571472168],"type":"Point"}
}