{
  "type": "Feature",
  "properties": {
    "iso:country":"GB",
    "sg:address":"Ecclesall Rd South",
    "sg:city":"Sheffield",
    "sg:classifiers":[
        {
            "category":"Community Center",
            "type":"Public Place"
        }
    ],
    "sg:phone":"+44 114 236 3173",
    "sg:postcode":"S11 9PZ",
    "sg:province":"Derbyshire",
    "sg:tags":[
        "conference",
        "room",
        "centre"
    ],
    "wof:name":"Whirlow Grange Conference Centre",
    "wof:placetype":"venue"
},
  "geometry": {"coordinates":[-1.511035,53.356434],"type":"Point"}
}