{
  "type": "Feature",
  "properties": {
    "iso:country":"GB",
    "sg:address":"70",
    "sg:city":"Chippenham",
    "sg:classifiers":[
        {
            "category":"Banks & Credit Unions",
            "subcategory":"Bank",
            "type":"Services"
        }
    ],
    "sg:postcode":"SN14 6JB",
    "sg:province":"Gloucestershire",
    "sg:tags":[
        "broker",
        "mortgage"
    ],
    "wof:name":"Monergy Ltd",
    "wof:placetype":"venue"
},
  "geometry": {"coordinates":[-2.1516489983,51.506401062],"type":"Point"}
}