{
  "type": "Feature",
  "properties": {
    "addr:full":"3c Mulberry Rd Canvey Island Essex SS8 0PR",
    "addr:housenumber":"3c",
    "addr:postcode":"ss8 0pr",
    "addr:street":"Mulberry Rd",
    "iso:country":"GB",
    "sg:address":"3c Mulberry Rd",
    "sg:city":"Canvey Island",
    "sg:classifiers":[
        {
            "category":"Building & Trades",
            "subcategory":"Construction",
            "type":"Services"
        }
    ],
    "sg:phone":"+44 1268 514417",
    "sg:postcode":"SS8 0PR",
    "sg:province":"Essex",
    "sg:tags":[
        "supplier",
        "installers",
        "cladding"
    ],
    "wof:name":"County Plastics",
    "wof:placetype":"venue"
},
  "geometry": {"coordinates":[0.5564699769,51.5219917297],"type":"Point"}
}