{
  "type": "Feature",
  "properties": {
    "addr:full":"13 Blair Road, Filham Moor Industrial Estate Ivybridge Devon PL21 0UR",
    "addr:housenumber":"13",
    "addr:postcode":"pl21 0ur",
    "addr:street":"Blair Road Filham Moor Industrial Estate",
    "iso:country":"GB",
    "sg:address":"13 Blair Road, Filham Moor Industrial Estate",
    "sg:city":"Ivybridge",
    "sg:classifiers":[
        {
            "category":"Professional",
            "subcategory":"Engineering",
            "type":"Services"
        }
    ],
    "sg:phone":"+44 1752 892507",
    "sg:postcode":"PL21 0UR",
    "sg:province":"Devon",
    "wof:name":"Welbro",
    "wof:placetype":"venue"
},
  "geometry": {"coordinates":[-3.918074,50.388248],"type":"Point"}
}