{
  "type": "Feature",
  "properties": {
    "iso:country":"GB",
    "sg:address":"Waterrow",
    "sg:city":"Taunton",
    "sg:classifiers":[
        {
            "category":"Travel",
            "subcategory":"Hotels & Motels",
            "type":"Entertainment"
        }
    ],
    "sg:phone":"+44 1984 623441",
    "sg:postcode":"TA4 2AT",
    "sg:province":"Devon",
    "sg:tags":[
        "self",
        "catering"
    ],
    "wof:name":"Hurstone Country House",
    "wof:placetype":"venue"
},
  "geometry": {"coordinates":[-3.3469,51.018082],"type":"Point"}
}