{
  "type": "Feature",
  "properties": {
    "iso:country":"GB",
    "sg:address":"Blenheim Farm",
    "sg:city":"Wallingford",
    "sg:classifiers":[
        {
            "category":"Manufacturing",
            "subcategory":"Pottery",
            "type":"Manufacturing & Wholesale Goods"
        }
    ],
    "sg:phone":"+44 1491 839707",
    "sg:postcode":"OX10 6PR",
    "sg:province":"Oxfordshire",
    "wof:name":"Blenheim Pots & Plaques",
    "wof:placetype":"venue"
},
  "geometry": {"coordinates":[-1.0729789734,51.6099700928],"type":"Point"}
}