{
  "type": "Feature",
  "properties": {
    "addr:full":"Wood Lane, Middlestown Wakefield West Yorkshire WF4 4XD",
    "addr:postcode":"wf4 4xd",
    "addr:street":"Wood Lane;West",
    "iso:country":"GB",
    "sg:address":"Wood Lane, Middlestown",
    "sg:city":"Wakefield",
    "sg:classifiers":[
        {
            "category":"Sports & Exercise",
            "subcategory":"Stables",
            "type":"Entertainment"
        }
    ],
    "sg:phone":"+44 1924 840614",
    "sg:postcode":"WF4 4XD",
    "sg:province":"West Yorkshire",
    "sg:tags":[
        "education",
        "equestrian"
    ],
    "wof:name":"Bank House Farm Riding & Livery Centre",
    "wof:placetype":"venue"
},
  "geometry": {"coordinates":[-1.6111609936,53.649066925],"type":"Point"}
}