{
  "type": "Feature",
  "properties": {
    "iso:country":"GB",
    "sg:address":"The Kestrels, Bucknalls Drive, Bricket Wood",
    "sg:city":"St Albans",
    "sg:classifiers":[
        {
            "category":"Social Services",
            "subcategory":"Retirement Home",
            "type":"Services"
        }
    ],
    "sg:phone":"+44 1923 681792",
    "sg:postcode":"AL2 3YB",
    "sg:province":"Hertfordshire",
    "sg:tags":[
        "residential",
        "care"
    ],
    "wof:name":"The Kestrels",
    "wof:placetype":"venue"
},
  "geometry": {"coordinates":[-0.367719,51.706676],"type":"Point"}
}