{
  "type": "Feature",
  "properties": {
    "iso:country":"GB",
    "sg:address":"2 St Cuthberts Street",
    "sg:city":"Wells",
    "sg:classifiers":[
        {
            "category":"Education",
            "subcategory":"Special Training",
            "type":"Public Place"
        }
    ],
    "sg:postcode":"BA5 2AW",
    "sg:province":"Somerset",
    "sg:tags":[
        "product",
        "centre"
    ],
    "wof:name":"Impetus Training & Development",
    "wof:placetype":"venue"
},
  "geometry": {"coordinates":[-2.649963,51.208172],"type":"Point"}
}