{
  "type": "Feature",
  "properties": {
    "addr:full":"Brynonen, Nanternis New Quay Ceredigion SA45 9RW",
    "addr:postcode":"sa45 9rw",
    "iso:country":"GB",
    "sg:address":"Brynonen, Nanternis",
    "sg:city":"New Quay",
    "sg:classifiers":[
        {
            "category":"Farming",
            "subcategory":"Livestock Farm",
            "type":"Manufacturing & Wholesale Goods"
        }
    ],
    "sg:phone":"+44 1545 560322",
    "sg:postcode":"SA45 9RW",
    "sg:province":"Ceredigion",
    "sg:tags":[
        "others"
    ],
    "wof:name":"T W & E A Davies",
    "wof:placetype":"venue"
},
  "geometry": {"coordinates":[-4.3607897758,52.2136726379],"type":"Point"}
}