{
  "type": "Feature",
  "properties": {
    "addr:full":"257 Upper Woodlands Road Bradford West Yorkshire BD8 9JQ",
    "addr:housenumber":"257",
    "addr:postcode":"bd8 9jq",
    "addr:street":"Upper Woodlands Road",
    "iso:country":"GB",
    "sg:address":"257 Upper Woodlands Road",
    "sg:city":"Bradford",
    "sg:classifiers":[
        {
            "category":"Health Services",
            "subcategory":"Health Practitioner",
            "type":"Services"
        }
    ],
    "sg:phone":"+44 1274 545095",
    "sg:postcode":"BD8 9JQ",
    "sg:province":"West Yorkshire",
    "sg:tags":[
        "osteopath"
    ],
    "wof:name":"Sajid Food Store",
    "wof:placetype":"venue"
},
  "geometry": {"coordinates":[-1.7864890099,53.8059043884],"type":"Point"}
}