{
  "type": "Feature",
  "properties": {
    "iso:country":"GB",
    "sg:address":"77 Castle Road",
    "sg:city":"Scarborough",
    "sg:classifiers":[
        {
            "category":"Bars & Pubs",
            "type":"Food & Drink"
        }
    ],
    "sg:phone":"+44 1723 355545",
    "sg:postcode":"YO11 1BH",
    "sg:province":"North Yorkshire",
    "sg:tags":[
        "pubs",
        "inn"
    ],
    "wof:name":"Sports Bar",
    "wof:placetype":"venue"
},
  "geometry": {"coordinates":[-0.4014370143,54.2852401733],"type":"Point"}
}