{
  "type": "Feature",
  "properties": {
    "iso:country":"GB",
    "sg:address":"43a Beechwood Road",
    "sg:city":"Caterham",
    "sg:classifiers":[
        {
            "category":"Building & Trades",
            "subcategory":"Construction",
            "type":"Services"
        }
    ],
    "sg:phone":"+44 1883 342408",
    "sg:postcode":"CR3 6NE",
    "sg:province":"Surrey",
    "sg:tags":[
        "builder"
    ],
    "wof:name":"K A Gates (Caterham) Ltd.",
    "wof:placetype":"venue"
},
  "geometry": {"coordinates":[-0.0755129978,51.2885437012],"type":"Point"}
}