{
  "type": "Feature",
  "properties": {
    "addr:full":"12 Clarence Rd Birkenhead Merseyside CH42 7JR",
    "addr:housenumber":"12",
    "addr:postcode":"ch42 7jr",
    "addr:street":"Clarence Rd",
    "iso:country":"GB",
    "sg:address":"12 Clarence Rd",
    "sg:city":"Birkenhead",
    "sg:classifiers":[
        {
            "category":"Building & Trades",
            "subcategory":"Construction",
            "type":"Services"
        }
    ],
    "sg:postcode":"CH42 7JR",
    "sg:province":"Merseyside",
    "sg:tags":[
        "builder"
    ],
    "wof:name":"Young,R J,",
    "wof:placetype":"venue"
},
  "geometry": {"coordinates":[-3.031771,53.377647],"type":"Point"}
}