{
  "type": "Feature",
  "properties": {
    "addr:full":"81 Main Rd Kilmarnock East Ayrshire KA3 6JU",
    "addr:housenumber":"81",
    "addr:postcode":"ka3 6ju",
    "addr:street":"Main Rd",
    "iso:country":"GB",
    "sg:address":"81 Main Rd",
    "sg:city":"Kilmarnock",
    "sg:classifiers":[
        {
            "category":"Health Services",
            "subcategory":"Dentist",
            "type":"Services"
        }
    ],
    "sg:phone":"+44 1563 573349",
    "sg:postcode":"KA3 6JU",
    "sg:province":"East Ayrshire",
    "sg:tags":[
        "technician",
        "dental"
    ],
    "wof:name":"Cummings Dental Ceramics",
    "wof:placetype":"venue"
},
  "geometry": {"coordinates":[-4.456187,55.64473],"type":"Point"}
}