{
  "type": "Feature",
  "properties": {
    "addr:full":"Po Box 5419 Helensburgh Argyll and Bute G84 8YD",
    "addr:housenumber":"po;5419",
    "addr:postcode":"g84 8yd",
    "addr:street":"Box",
    "iso:country":"GB",
    "sg:address":"Po Box 5419",
    "sg:city":"Helensburgh",
    "sg:classifiers":[
        {
            "category":"Professional",
            "subcategory":"Engineering",
            "type":"Services"
        }
    ],
    "sg:phone":"+44 1436 821445",
    "sg:postcode":"G84 8YD",
    "sg:province":"Argyll and Bute",
    "sg:tags":[
        "design",
        "engineer"
    ],
    "wof:name":"Sage Safety Ltd.",
    "wof:placetype":"venue"
},
  "geometry": {"coordinates":[-4.7595291138,56.0175704956],"type":"Point"}
}