{
  "type": "Feature",
  "properties": {
    "addr:full":"Haggerston Smithy Berwick-upon-tweed Northumberland TD15 2TL",
    "addr:postcode":"td15 2tl",
    "addr:street":"Northumberland",
    "iso:country":"GB",
    "sg:address":"Haggerston Smithy",
    "sg:city":"Berwick-upon-tweed",
    "sg:classifiers":[
        {
            "category":"Retail",
            "subcategory":"Auto Repair",
            "type":"Services"
        }
    ],
    "sg:phone":"+44 1289 381239",
    "sg:postcode":"TD15 2TL",
    "sg:province":"Northumberland",
    "sg:tags":[
        "modification",
        "car",
        "vehicle",
        "commercial",
        "garage"
    ],
    "wof:name":"Haggerston Motors",
    "wof:placetype":"venue"
},
  "geometry": {"coordinates":[-1.956,55.684559],"type":"Point"}
}