{
  "type": "Feature",
  "properties": {
    "addr:full":"Third Floor, Transport House, 1 Cathedral Road Cardiff Cardiff CF11 9SB",
    "addr:housenumber":"third;1",
    "addr:postcode":"cardiff cf11 9sb",
    "addr:street":"Cathedral Road",
    "iso:country":"GB",
    "sg:address":"Third Floor, Transport House, 1 Cathedral Road",
    "sg:city":"Cardiff",
    "sg:classifiers":[
        {
            "category":"Building & Trades",
            "subcategory":"Construction",
            "type":"Services"
        },
        {
            "category":"Organizations",
            "subcategory":"Professional Association",
            "type":"Services"
        }
    ],
    "sg:phone":"+44 29 2039 8333",
    "sg:postcode":"CF11 9SB",
    "sg:province":"Cardiff",
    "sg:tags":[
        "union",
        "activity"
    ],
    "wof:name":"Unison",
    "wof:placetype":"venue"
},
  "geometry": {"coordinates":[-3.189437,51.48172],"type":"Point"}
}