{
  "type": "Feature",
  "properties": {
    "addr:full":"14 Grangethorpe Rd, Urmston Manchester Cheshire M41 9HX",
    "addr:housenumber":"14",
    "addr:postcode":"m41 9hx",
    "addr:street":"Grangethorpe Rd",
    "iso:country":"GB",
    "sg:address":"14 Grangethorpe Rd, Urmston",
    "sg:city":"Manchester",
    "sg:classifiers":[
        {
            "category":"Insurance",
            "subcategory":"Insurance Agent",
            "type":"Services"
        }
    ],
    "sg:postcode":"M41 9HX",
    "sg:province":"Cheshire",
    "wof:name":"Entwistle,William,",
    "wof:placetype":"venue"
},
  "geometry": {"coordinates":[-2.3542749882,53.4442596436],"type":"Point"}
}