{
  "type": "Feature",
  "properties": {
    "addr:full":"Lee Road, Saunderton Lee Aylesbury Buckinghamshire HP17 9NX",
    "addr:postcode":"hp17 9nx",
    "addr:street":"Lee Road Saunderton Lee",
    "iso:country":"GB",
    "sg:address":"Lee Road, Saunderton Lee",
    "sg:city":"Aylesbury",
    "sg:classifiers":[
        {
            "category":"Sports & Exercise",
            "subcategory":"Golf",
            "type":"Entertainment"
        }
    ],
    "sg:phone":"+44 1844 274567",
    "sg:postcode":"HP17 9NX",
    "sg:province":"Buckinghamshire",
    "sg:tags":[
        "equipment"
    ],
    "wof:name":"Princes Risborough Pro Shop",
    "wof:placetype":"venue"
},
  "geometry": {"coordinates":[-0.84227,51.751801],"type":"Point"}
}