{
  "type": "Feature",
  "properties": {
    "addr:full":"1-4 Lower Green West Mitcham Greater London CR4 3AF",
    "addr:housenumber":"1-4",
    "addr:postcode":"cr4 3af",
    "addr:street":"Lower",
    "iso:country":"GB",
    "sg:address":"1-4 Lower Green West",
    "sg:city":"Mitcham",
    "sg:classifiers":[
        {
            "category":"Building & Trades",
            "subcategory":"Cleaning & Sanitation",
            "type":"Services"
        }
    ],
    "sg:phone":"+44 20 8646 5938",
    "sg:postcode":"CR4 3AF",
    "sg:province":"Greater London",
    "sg:tags":[
        "commercial"
    ],
    "wof:name":"KSH Mobile Xtra Kleen",
    "wof:placetype":"venue"
},
  "geometry": {"coordinates":[-0.164267,51.406219],"type":"Point"}
}