{
  "type": "Feature",
  "properties": {
    "addr:full":"Kensham Farm, Sandhurst Lane, Rolvenden Cranbrook Kent TN17 4PH",
    "addr:postcode":"tn17 4ph",
    "addr:street":"Sandhurst Lane",
    "iso:country":"GB",
    "sg:address":"Kensham Farm, Sandhurst Lane, Rolvenden",
    "sg:city":"Cranbrook",
    "sg:classifiers":[
        {
            "category":"Farming",
            "subcategory":"Livestock Farm",
            "type":"Manufacturing & Wholesale Goods"
        }
    ],
    "sg:postcode":"TN17 4PH",
    "sg:province":"Kent",
    "sg:tags":[
        "others"
    ],
    "wof:name":"Jenner Bros",
    "wof:placetype":"venue"
},
  "geometry": {"coordinates":[0.6299589872,51.0523147583],"type":"Point"}
}