{
  "type": "Feature",
  "properties": {
    "addr:full":"Great Western Road Gloucester Gloucestershire GL1 3NF",
    "addr:postcode":"gl1 3nf",
    "addr:street":"Great Western Road",
    "iso:country":"GB",
    "sg:address":"Great Western Road",
    "sg:city":"Gloucester",
    "sg:classifiers":[
        {
            "category":"Organizations",
            "subcategory":"Membership Organization",
            "type":"Services"
        }
    ],
    "sg:postcode":"GL1 3NF",
    "sg:province":"Gloucestershire",
    "sg:tags":[
        "club"
    ],
    "wof:name":"G W R Staff Association Club",
    "wof:placetype":"venue"
},
  "geometry": {"coordinates":[-2.232707,51.865005],"type":"Point"}
}