{
  "type": "Feature",
  "properties": {
    "addr:full":"76 High Street, Stony Stratford Milton Keynes Buckinghamshire MK11 1AH",
    "addr:housenumber":"76",
    "addr:postcode":"mk11 1ah",
    "addr:street":"High Street",
    "iso:country":"GB",
    "sg:address":"76 High Street, Stony Stratford",
    "sg:city":"Milton Keynes",
    "sg:classifiers":[
        {
            "category":"Real Estate",
            "subcategory":"Developer",
            "type":"Services"
        }
    ],
    "sg:postcode":"MK11 1AH",
    "sg:province":"Buckinghamshire",
    "sg:tags":[
        "property"
    ],
    "wof:name":"Augusta Developments Ltd.",
    "wof:placetype":"venue"
},
  "geometry": {"coordinates":[-0.8551669717,52.0582695007],"type":"Point"}
}