{
  "type": "Feature",
  "properties": {
    "addr:full":"Bonds Lane, Mid-holmwood Dorking Surrey RH5 4HF",
    "addr:postcode":"rh5 4hf",
    "addr:street":"Bonds Lane",
    "iso:country":"GB",
    "sg:address":"Bonds Lane, Mid-holmwood",
    "sg:city":"Dorking",
    "sg:classifiers":[
        {
            "category":"Building & Trades",
            "subcategory":"Construction",
            "type":"Services"
        }
    ],
    "sg:postcode":"RH5 4HF",
    "sg:province":"Surrey",
    "sg:tags":[
        "builder"
    ],
    "wof:name":"R T Overton & Sons Ltd.",
    "wof:placetype":"venue"
},
  "geometry": {"coordinates":[-0.3306330144,51.2038421631],"type":"Point"}
}