{
  "type": "Feature",
  "properties": {
    "iso:country":"GB",
    "sg:address":"14c The Avenue, High St",
    "sg:city":"Bridgwater",
    "sg:classifiers":[
        {
            "category":"Professional",
            "subcategory":"Engineering",
            "type":"Services"
        }
    ],
    "sg:phone":"+44 1278 429615",
    "sg:postcode":"TA6 3BW",
    "sg:province":"Somerset",
    "sg:tags":[
        "civil",
        "engineer"
    ],
    "wof:name":"Rs Cook",
    "wof:placetype":"venue"
},
  "geometry": {"coordinates":[-3.0138239861,51.1275558472],"type":"Point"}
}