{
  "type": "Feature",
  "properties": {
    "addr:full":"8 Camberwell Green Camberwell Greater London SE5 7AF",
    "addr:housenumber":"8",
    "addr:postcode":"se5 7af",
    "addr:street":"Camberwell Green",
    "iso:country":"GB",
    "sg:address":"8 Camberwell Green",
    "sg:city":"Camberwell",
    "sg:classifiers":[
        {
            "category":"Professional",
            "subcategory":"Lawyer & Legal Services",
            "type":"Services"
        }
    ],
    "sg:phone":"+44 20 7252 5505",
    "sg:postcode":"SE5 7AF",
    "sg:province":"Greater London",
    "sg:tags":[
        "solicitor"
    ],
    "wof:name":"Myria Pieri & Co",
    "wof:placetype":"venue"
},
  "geometry": {"coordinates":[-0.0933,51.474731],"type":"Point"}
}