{
  "type": "Feature",
  "properties": {
    "addr:full":"47 Morecambe Road Morecambe Lancashire LA3 3AA",
    "addr:housenumber":"47",
    "addr:postcode":"la3 3aa",
    "addr:street":"Morecambe Road",
    "iso:country":"GB",
    "sg:address":"47 Morecambe Road",
    "sg:city":"Morecambe",
    "sg:classifiers":[
        {
            "category":"Social Services",
            "subcategory":"Retirement Home",
            "type":"Services"
        }
    ],
    "sg:phone":"+44 1524 419919",
    "sg:postcode":"LA3 3AA",
    "sg:province":"Lancashire",
    "sg:tags":[
        "residential",
        "care"
    ],
    "wof:name":"Hall Bower",
    "wof:placetype":"venue"
},
  "geometry": {"coordinates":[-2.834137,54.064106],"type":"Point"}
}