{
  "type": "Feature",
  "properties": {
    "iso:country":"GB",
    "sg:address":"11 Little Normans, Longlevens",
    "sg:city":"Gloucester",
    "sg:classifiers":[
        {
            "category":"Organizations",
            "subcategory":"Non-profit Organization",
            "type":"Services"
        }
    ],
    "sg:postcode":"GL2 0EH",
    "sg:province":"Gloucestershire",
    "sg:tags":[
        "organisation",
        "voluntary",
        "charity"
    ],
    "wof:name":"Humphris,D A,",
    "wof:placetype":"venue"
},
  "geometry": {"coordinates":[-2.2147760391,51.8819465637],"type":"Point"}
}