{
  "type": "Feature",
  "properties": {
    "iso:country":"GB",
    "sg:address":"King St",
    "sg:city":"Sutton In Ashfield",
    "sg:classifiers":[
        {
            "category":"Shopping",
            "subcategory":"Clothing, Apparel, & Fashions",
            "type":"Retail Goods"
        }
    ],
    "sg:phone":"+44 1623 558674",
    "sg:postcode":"NG17 2PA",
    "sg:province":"Nottinghamshire",
    "sg:tags":[
        "sportswear"
    ],
    "wof:name":"Romart Sport",
    "wof:placetype":"venue"
},
  "geometry": {"coordinates":[-1.291514,53.12896],"type":"Point"}
}