{
  "type": "Feature",
  "properties": {
    "addr:full":"82 Claughton Street St Helens Merseyside WA10 1SN",
    "addr:housenumber":"82",
    "addr:postcode":"wa10 1sn",
    "addr:street":"Claughton Street",
    "iso:country":"GB",
    "sg:address":"82 Claughton Street",
    "sg:city":"St Helens",
    "sg:classifiers":[
        {
            "category":"Shopping",
            "subcategory":"Crafts & Fabrics",
            "type":"Retail Goods"
        }
    ],
    "sg:phone":"+44 1744 24234",
    "sg:postcode":"WA10 1SN",
    "sg:province":"Merseyside",
    "sg:tags":[
        "material",
        "art"
    ],
    "wof:name":"The Art Shop",
    "wof:placetype":"venue"
},
  "geometry": {"coordinates":[-2.738068,53.454742],"type":"Point"}
}