{
  "type": "Feature",
  "properties": {
    "iso:country":"GB",
    "sg:address":"186 North Hyde La",
    "sg:city":"Southall",
    "sg:classifiers":[
        {
            "category":"Shopping",
            "subcategory":"News",
            "type":"Retail Goods"
        }
    ],
    "sg:phone":"+44 20 8574 3311",
    "sg:postcode":"UB2 5SE",
    "sg:province":"Greater London",
    "sg:tags":[
        "newsagent"
    ],
    "wof:name":"Bains Newsagents",
    "wof:placetype":"venue"
},
  "geometry": {"coordinates":[-0.381731,51.491985],"type":"Point"}
}