{
  "type": "Feature",
  "properties": {
    "iso:country":"GB",
    "sg:address":"442 Lodge Avenue",
    "sg:city":"Dagenham",
    "sg:classifiers":[
        {
            "category":"Food & Beverages",
            "subcategory":"Liquor & Beverages",
            "type":"Retail Goods"
        }
    ],
    "sg:phone":"+44 20 8592 5986",
    "sg:postcode":"RM9 4QS",
    "sg:province":"Essex",
    "sg:tags":[
        "beer",
        "spirit",
        "wines"
    ],
    "wof:name":"Lodge Wines & Spirits",
    "wof:placetype":"venue"
},
  "geometry": {"coordinates":[0.110936,51.535297],"type":"Point"}
}