{
  "type": "Feature",
  "properties": {
    "iso:country":"GB",
    "sg:address":"6 Links Road",
    "sg:city":"Epsom",
    "sg:classifiers":[
        {
            "category":"Professional",
            "subcategory":"Engineering",
            "type":"Services"
        }
    ],
    "sg:phone":"+44 1372 723266",
    "sg:postcode":"KT17 3PS",
    "sg:province":"Surrey",
    "sg:tags":[
        "consulting",
        "engineer"
    ],
    "wof:name":"Alan W Shilston",
    "wof:placetype":"venue"
},
  "geometry": {"coordinates":[-0.246782,51.330399],"type":"Point"}
}