{
  "type": "Feature",
  "properties": {
    "addr:full":"27 Sydenham Rd London Greater London SE26 5EX",
    "addr:housenumber":"27",
    "addr:postcode":"se26 5ex",
    "addr:street":"Sydenham Rd",
    "iso:country":"GB",
    "sg:address":"27 Sydenham Rd",
    "sg:city":"London",
    "sg:classifiers":[
        {
            "category":"Shopping",
            "subcategory":"Comic Books",
            "type":"Retail Goods"
        }
    ],
    "sg:phone":"+44 20 8778 5361",
    "sg:postcode":"SE26 5EX",
    "sg:province":"Greater London",
    "sg:tags":[
        "jeweller"
    ],
    "wof:name":"Buik,G H,",
    "wof:placetype":"venue"
},
  "geometry": {"coordinates":[-0.053096,51.426468],"type":"Point"}
}