{
  "type": "Feature",
  "properties": {
    "iso:country":"GB",
    "sg:address":"Cliff Road",
    "sg:city":"Hornsea",
    "sg:classifiers":[
        {
            "category":"Farming",
            "subcategory":"Dairy Farm",
            "type":"Manufacturing & Wholesale Goods"
        }
    ],
    "sg:phone":"+44 1964 532652",
    "sg:postcode":"HU18 1JB",
    "sg:province":"East Riding of Yorkshire",
    "wof:name":"Dale Farm",
    "wof:placetype":"venue"
},
  "geometry": {"coordinates":[-0.1673289984,53.920375824],"type":"Point"}
}