{
  "type": "Feature",
  "properties": {
    "addr:full":"Mere Court, Burscough Ormskirk Lancashire L40 0TQ",
    "addr:postcode":"l40 0tq",
    "addr:street":"Mere Court",
    "iso:country":"GB",
    "sg:address":"Mere Court, Burscough",
    "sg:city":"Ormskirk",
    "sg:classifiers":[
        {
            "category":"Social Services",
            "subcategory":"Adult Care",
            "type":"Services"
        },
        {
            "category":"Social Services",
            "subcategory":"Retirement Home",
            "type":"Services"
        }
    ],
    "sg:phone":"+44 1704 893293",
    "sg:postcode":"L40 0TQ",
    "sg:province":"Lancashire",
    "sg:tags":[
        "housing",
        "sheltered",
        "accommodation"
    ],
    "wof:name":"Mere Court Sheltered Housing",
    "wof:placetype":"venue"
},
  "geometry": {"coordinates":[-2.8414740562,53.6062202454],"type":"Point"}
}