{
  "type": "Feature",
  "properties": {
    "addr:full":"Locko Rd Chesterfield Derbyshire S45 8DN",
    "addr:postcode":"s45 8dn",
    "addr:street":"Locko Rd",
    "iso:country":"GB",
    "sg:address":"Locko Rd",
    "sg:city":"Chesterfield",
    "sg:classifiers":[
        {
            "category":"Bars & Pubs",
            "type":"Food & Drink"
        }
    ],
    "sg:phone":"+44 1246 851011",
    "sg:postcode":"S45 8DN",
    "sg:province":"Derbyshire",
    "sg:tags":[
        "pubs",
        "inn"
    ],
    "wof:name":"Waterloo Inn The",
    "wof:placetype":"venue"
},
  "geometry": {"coordinates":[-1.378081,53.168167],"type":"Point"}
}