{
  "type": "Feature",
  "properties": {
    "addr:full":"52 Farringdon Street London Greater London EC4A 4BD",
    "addr:housenumber":"52",
    "addr:postcode":"ec4a 4bd",
    "addr:street":"Farringdon Street",
    "iso:country":"GB",
    "sg:address":"52 Farringdon Street",
    "sg:city":"London",
    "sg:classifiers":[
        {
            "category":"Shopping",
            "subcategory":"Tobacco",
            "type":"Retail Goods"
        },
        {
            "category":"Shopping",
            "subcategory":"News",
            "type":"Retail Goods"
        }
    ],
    "sg:phone":"+44 20 7283 0874",
    "sg:postcode":"EC4A 4BD",
    "sg:province":"Greater London",
    "sg:tags":[
        "tobacconist",
        "newsagent"
    ],
    "wof:name":"City Kiosk",
    "wof:placetype":"venue"
},
  "geometry": {"coordinates":[-0.1052979976,51.51720047],"type":"Point"}
}