{
  "type": "Feature",
  "properties": {
    "iso:country":"GB",
    "sg:address":"1 Eskdail Court",
    "sg:city":"Dalkeith",
    "sg:classifiers":[
        {
            "category":"Education",
            "subcategory":"Special Training",
            "type":"Public Place"
        }
    ],
    "sg:phone":"+44 131 663 6951",
    "sg:postcode":"EH22 2QB",
    "sg:province":"City of Edinburgh",
    "sg:tags":[
        "product",
        "centre"
    ],
    "wof:name":"MiTech (Midlothian IT Training Centre)",
    "wof:placetype":"venue"
},
  "geometry": {"coordinates":[-3.040489,55.889462],"type":"Point"}
}