{
  "type": "Feature",
  "properties": {
    "addr:full":"5 Freshfields, Wististon Crewe Cheshire CW2 6QD",
    "addr:housenumber":"5",
    "addr:postcode":"cw2 6qd",
    "addr:street":"Freshfields Wististon",
    "iso:country":"GB",
    "sg:address":"5 Freshfields, Wististon",
    "sg:city":"Crewe",
    "sg:classifiers":[
        {
            "category":"Military Area",
            "subcategory":"Air Force Base",
            "type":"Public Place"
        }
    ],
    "sg:phone":"+44 1270 666670",
    "sg:postcode":"CW2 6QD",
    "sg:province":"Cheshire",
    "sg:tags":[
        "taxi",
        "hire",
        "private"
    ],
    "wof:name":"Kershaw Taxis",
    "wof:placetype":"venue"
},
  "geometry": {"coordinates":[-2.4774401188,53.075340271],"type":"Point"}
}