{
  "type": "Feature",
  "properties": {
    "addr:full":"84 Churchfields Road Beckenham Kent BR3 4RQ",
    "addr:housenumber":"84",
    "addr:postcode":"br3 4rq",
    "addr:street":"Churchfields Road",
    "iso:country":"GB",
    "sg:address":"84 Churchfields Road",
    "sg:city":"Beckenham",
    "sg:classifiers":[
        {
            "category":"Health Services",
            "subcategory":"Dentist",
            "type":"Services"
        }
    ],
    "sg:phone":"+44 20 8650 0808",
    "sg:postcode":"BR3 4RQ",
    "sg:province":"Kent",
    "wof:name":"Churchfields Dental Practice",
    "wof:placetype":"venue"
},
  "geometry": {"coordinates":[-0.0458789989,51.4062767029],"type":"Point"}
}