{
  "type": "Feature",
  "properties": {
    "addr:full":"76 Fengate Peterborough Cambridgeshire PE1 5BB",
    "addr:housenumber":"76",
    "addr:postcode":"pe1 5bb",
    "addr:street":"Fengate Peterborough",
    "iso:country":"GB",
    "sg:address":"76 Fengate",
    "sg:city":"Peterborough",
    "sg:classifiers":[
        {
            "category":"Professional",
            "subcategory":"Detective & Security Services",
            "type":"Services"
        }
    ],
    "sg:phone":"+44 1733 558738",
    "sg:postcode":"PE1 5BB",
    "sg:province":"Cambridgeshire",
    "sg:tags":[
        "alarm",
        "burglar",
        "system"
    ],
    "wof:name":"Magnet Security & Fire Systems Ltd",
    "wof:placetype":"venue"
},
  "geometry": {"coordinates":[-0.2249120027,52.5708885193],"type":"Point"}
}