{
  "type": "Feature",
  "properties": {
    "addr:full":"464 Oxford Rd Reading Berkshire RG30 1EE",
    "addr:housenumber":"464",
    "addr:postcode":"rg30 1ee",
    "addr:street":"Oxford Rd",
    "iso:country":"GB",
    "sg:address":"464 Oxford Rd",
    "sg:city":"Reading",
    "sg:classifiers":[
        {
            "category":"Shopping",
            "subcategory":"Computers & Home Electronics",
            "type":"Retail Goods"
        }
    ],
    "sg:phone":"+44 118 958 4620",
    "sg:postcode":"RG30 1EE",
    "sg:province":"Berkshire",
    "sg:tags":[
        "electrical"
    ],
    "wof:name":"Sparkies Place",
    "wof:placetype":"venue"
},
  "geometry": {"coordinates":[-1.0005580187,51.4578742981],"type":"Point"}
}