{
  "type": "Feature",
  "properties": {
    "iso:country":"GB",
    "sg:address":"91 Victoria Road",
    "sg:city":"Swindon",
    "sg:classifiers":[
        {
            "category":"Retail",
            "subcategory":"Laundry & Dry Cleaning",
            "type":"Services"
        }
    ],
    "sg:phone":"+44 1793 616871",
    "sg:postcode":"SN1 3BD",
    "sg:province":"Wiltshire",
    "sg:tags":[
        "cleaner",
        "alteration"
    ],
    "wof:name":"Brooks Cleaning Services Ltd.",
    "wof:placetype":"venue"
},
  "geometry": {"coordinates":[-1.7770119905,51.5535011292],"type":"Point"}
}