{
  "type": "Feature",
  "properties": {
    "iso:country":"GB",
    "sg:address":"17 Old Market Place",
    "sg:city":"Grimsby",
    "sg:classifiers":[
        {
            "category":"Shopping",
            "subcategory":"Jewelry",
            "type":"Retail Goods"
        },
        {
            "category":"Shopping",
            "subcategory":"Comic Books",
            "type":"Retail Goods"
        }
    ],
    "sg:phone":"+44 1472 341742",
    "sg:postcode":"DN31 1EW",
    "sg:province":"Lincolnshire",
    "sg:tags":[
        "jeweller",
        "sale",
        "jewellery"
    ],
    "wof:name":"Nidd & Son Ltd",
    "wof:placetype":"venue"
},
  "geometry": {"coordinates":[-0.087994,53.564465],"type":"Point"}
}