{
  "type": "Feature",
  "properties": {
    "addr:full":"631 Rainham Road South Dagenham Essex RM10 8AH",
    "addr:housenumber":"631",
    "addr:postcode":"rm10 8ah",
    "addr:street":"Rainham Road South",
    "iso:country":"GB",
    "sg:address":"631 Rainham Road South",
    "sg:city":"Dagenham",
    "sg:classifiers":[
        {
            "category":"Shopping",
            "subcategory":"Mobile Phones",
            "type":"Retail Goods"
        }
    ],
    "sg:postcode":"RM10 8AH",
    "sg:province":"Essex",
    "wof:name":"London Mobile Communications",
    "wof:placetype":"venue"
},
  "geometry": {"coordinates":[0.165548,51.542843],"type":"Point"}
}