{
  "type": "Feature",
  "properties": {
    "addr:full":"Coventry Air Park, Rowley Road, Coventry Airport Coventry Warwickshire CV3 4FR",
    "addr:postcode":"cv3 4fr",
    "addr:street":"Rowley Road;Airport",
    "iso:country":"GB",
    "sg:address":"Coventry Air Park, Rowley Road, Coventry Airport",
    "sg:city":"Coventry",
    "sg:classifiers":[
        {
            "category":"Education",
            "subcategory":"Special Training",
            "type":"Public Place"
        },
        {
            "category":"Education",
            "subcategory":"School",
            "type":"Public Place"
        }
    ],
    "sg:phone":"+44 24 7630 4914",
    "sg:postcode":"CV3 4FR",
    "sg:province":"Warwickshire",
    "sg:tags":[
        "flying",
        "local",
        "authority"
    ],
    "wof:name":"Midland Air Training Ltd",
    "wof:placetype":"venue"
},
  "geometry": {"coordinates":[-1.47751,52.373772],"type":"Point"}
}