{
  "type": "Feature",
  "properties": {
    "addr:full":"Easton Lodge, Lodge Road, Easton Norwich Norfolk NR9 5EL",
    "addr:postcode":"nr9 5el",
    "addr:street":"Lodge Road;Norwich Norfolk",
    "iso:country":"GB",
    "sg:address":"Easton Lodge, Lodge Road, Easton",
    "sg:city":"Norwich",
    "sg:classifiers":[
        {
            "category":"Farming",
            "subcategory":"Farm",
            "type":"Manufacturing & Wholesale Goods"
        }
    ],
    "sg:phone":"+44 1603 742013",
    "sg:postcode":"NR9 5EL",
    "sg:province":"Norfolk",
    "sg:tags":[
        "mixed",
        "crop"
    ],
    "wof:name":"Easton Estates",
    "wof:placetype":"venue"
},
  "geometry": {"coordinates":[1.1480590105,52.6408538818],"type":"Point"}
}