{
  "type": "Feature",
  "properties": {
    "addr:full":"53 Cowgate, Kirkintilloch Glasgow East Dunbartonshire G66 1HW",
    "addr:housenumber":"53",
    "addr:postcode":"g66 1hw",
    "addr:street":"Cowgate Kirkintilloch",
    "iso:country":"GB",
    "sg:address":"53 Cowgate, Kirkintilloch",
    "sg:city":"Glasgow",
    "sg:classifiers":[
        {
            "category":"Shopping",
            "subcategory":"Shoes",
            "type":"Retail Goods"
        }
    ],
    "sg:phone":"+44 141 777 8614",
    "sg:postcode":"G66 1HW",
    "sg:province":"East Dunbartonshire",
    "sg:tags":[
        "shop"
    ],
    "wof:name":"Clarks Shoes",
    "wof:placetype":"venue"
},
  "geometry": {"coordinates":[-4.1579289436,55.940574646],"type":"Point"}
}