{
  "type": "Feature",
  "properties": {
    "iso:country":"GB",
    "sg:address":"4 High St",
    "sg:city":"East Grinstead",
    "sg:classifiers":[
        {
            "category":"Manufacturing",
            "subcategory":"Jewelry",
            "type":"Manufacturing & Wholesale Goods"
        }
    ],
    "sg:phone":"+44 1342 321659",
    "sg:postcode":"RH19 3AW",
    "sg:province":"East Sussex",
    "sg:tags":[
        "repair",
        "jewellery"
    ],
    "wof:name":"The Jewellery Workshop",
    "wof:placetype":"venue"
},
  "geometry": {"coordinates":[-0.008016,51.123913],"type":"Point"}
}