{
  "type": "Feature",
  "properties": {
    "iso:country":"GB",
    "sg:address":"Unit 6 39 Church Rd",
    "sg:city":"Bexleyheath",
    "sg:classifiers":[
        {
            "category":"Building & Trades",
            "subcategory":"Construction",
            "type":"Services"
        }
    ],
    "sg:phone":"+44 20 8301 5255",
    "sg:postcode":"DA7 4DD",
    "sg:province":"Kent",
    "sg:tags":[
        "flooring"
    ],
    "wof:name":"All Floors",
    "wof:placetype":"venue"
},
  "geometry": {"coordinates":[0.138354,51.458958],"type":"Point"}
}