{
  "type": "Feature",
  "properties": {
    "addr:full":"43 Cambridge Road Stamford Cambridgeshire PE9 1BY",
    "addr:housenumber":"43",
    "addr:postcode":"pe9 1by",
    "addr:street":"Cambridge Road",
    "iso:country":"GB",
    "sg:address":"43 Cambridge Road",
    "sg:city":"Stamford",
    "sg:classifiers":[
        {
            "category":"Fast Food",
            "type":"Food & Drink"
        }
    ],
    "sg:postcode":"PE9 1BY",
    "sg:province":"Cambridgeshire",
    "sg:tags":[
        "away",
        "take"
    ],
    "wof:name":"Guang Dong Cantonese Takeaway",
    "wof:placetype":"venue"
},
  "geometry": {"coordinates":[-0.4887230098,52.6608276367],"type":"Point"}
}