{
  "type": "Feature",
  "properties": {
    "iso:country":"GB",
    "sg:address":", Bowlish",
    "sg:city":"Shepton Mallet",
    "sg:classifiers":[
        {
            "category":"Education",
            "subcategory":"School",
            "type":"Public Place"
        }
    ],
    "sg:phone":"+44 1749 342514",
    "sg:postcode":"BA4 5JQ",
    "sg:province":"Somerset",
    "sg:tags":[
        "local",
        "authority"
    ],
    "wof:name":"Bowlish County Infant School",
    "wof:placetype":"venue"
},
  "geometry": {"coordinates":[-2.556554,51.193356],"type":"Point"}
}