{
  "type": "Feature",
  "properties": {
    "addr:full":"Caverstede Rd, Paston Peterborough Cambridgeshire PE4 6EX",
    "addr:postcode":"pe4 6ex",
    "addr:street":"Caverstede Rd;Peterborough",
    "iso:country":"GB",
    "sg:address":"Caverstede Rd, Paston",
    "sg:city":"Peterborough",
    "sg:classifiers":[
        {
            "category":"Farming",
            "subcategory":"Nursery",
            "type":"Manufacturing & Wholesale Goods"
        }
    ],
    "sg:phone":"+44 1733 571742",
    "sg:postcode":"PE4 6EX",
    "sg:province":"Cambridgeshire",
    "sg:tags":[
        "creche"
    ],
    "wof:name":"Caverstede Nursery School",
    "wof:placetype":"venue"
},
  "geometry": {"coordinates":[-0.260629,52.603954],"type":"Point"}
}