{
  "type": "Feature",
  "properties": {
    "addr:full":"2 Panmure Street Brechin Aberdeenshire DD9 6AP",
    "addr:housenumber":"2",
    "addr:postcode":"dd9 6ap",
    "addr:street":"Panmure Street",
    "iso:country":"GB",
    "sg:address":"2 Panmure Street",
    "sg:city":"Brechin",
    "sg:classifiers":[
        {
            "category":"Banks & Credit Unions",
            "subcategory":"Bank",
            "type":"Services"
        }
    ],
    "sg:phone":"+44 1356 623991",
    "sg:postcode":"DD9 6AP",
    "sg:province":"Aberdeenshire",
    "sg:tags":[
        "financial",
        "institution"
    ],
    "wof:name":"Clydesdale Bank Plc",
    "wof:placetype":"venue"
},
  "geometry": {"coordinates":[-2.658682,56.732574],"type":"Point"}
}