{
  "type": "Feature",
  "properties": {
    "iso:country":"GB",
    "sg:address":"71 High St",
    "sg:city":"Fordingbridge",
    "sg:classifiers":[
        {
            "category":"Home & Garden",
            "subcategory":"Carpets & Floor Coverings",
            "type":"Retail Goods"
        }
    ],
    "sg:phone":"+44 1425 655820",
    "sg:postcode":"SP6 1AS",
    "sg:province":"Dorset",
    "sg:tags":[
        "carpets",
        "rug",
        "matting"
    ],
    "wof:name":"Quay Flooring Centre",
    "wof:placetype":"venue"
},
  "geometry": {"coordinates":[-1.7922890186,50.9264793396],"type":"Point"}
}