{
  "type": "Feature",
  "properties": {
    "addr:full":"3 Trinity Avenue Westcliff-on-sea Essex SS0 7PU",
    "addr:housenumber":"3",
    "addr:postcode":"ss0 7pu",
    "addr:street":"Trinity Avenue",
    "iso:country":"GB",
    "sg:address":"3 Trinity Avenue",
    "sg:city":"Westcliff-on-sea",
    "sg:classifiers":[
        {
            "category":"Travel",
            "subcategory":"Hotels & Motels",
            "type":"Entertainment"
        }
    ],
    "sg:phone":"+44 1702 342282",
    "sg:postcode":"SS0 7PU",
    "sg:province":"Essex",
    "wof:name":"Chilton House",
    "wof:placetype":"venue"
},
  "geometry": {"coordinates":[0.699305,51.535912],"type":"Point"}
}