{
  "type": "Feature",
  "properties": {
    "iso:country":"GB",
    "sg:address":"Whitwick Road",
    "sg:city":"Coalville",
    "sg:classifiers":[
        {
            "category":"Travel",
            "subcategory":"Hotels & Motels",
            "type":"Entertainment"
        }
    ],
    "sg:phone":"+44 1530 814814",
    "sg:postcode":"LE67 3FA",
    "sg:province":"Leicestershire",
    "wof:name":"Three Queens Hotel Ltd.",
    "wof:placetype":"venue"
},
  "geometry": {"coordinates":[-1.367014,52.728111],"type":"Point"}
}