{
  "type": "Feature",
  "properties": {
    "addr:full":"The Granary, Potters Marston Hall, Potters Marston Leicester Leicestershire LE9 3JR",
    "addr:postcode":"le9 3jr",
    "addr:street":"Potters;Potters",
    "iso:country":"GB",
    "sg:address":"The Granary, Potters Marston Hall, Potters Marston",
    "sg:city":"Leicester",
    "sg:classifiers":[
        {
            "category":"Manufacturing",
            "subcategory":"Tools & Machinery",
            "type":"Manufacturing & Wholesale Goods"
        }
    ],
    "sg:phone":"+44 116 286 6897",
    "sg:postcode":"LE9 3JR",
    "sg:province":"Leicestershire",
    "sg:tags":[
        "monitoring",
        "temperature",
        "thermometer"
    ],
    "wof:name":"Arboret Ltd.",
    "wof:placetype":"venue"
},
  "geometry": {"coordinates":[-1.2594339848,52.5612564087],"type":"Point"}
}