{
  "type": "Feature",
  "properties": {
    "iso:country":"GB",
    "sg:address":"Linden Cottage, Chapel Rd",
    "sg:city":"Aylesbury",
    "sg:classifiers":[
        {
            "category":"Communications",
            "subcategory":"Film & Video Production",
            "type":"Services"
        }
    ],
    "sg:phone":"+44 1296 748647",
    "sg:postcode":"HP17 8XE",
    "sg:province":"Buckinghamshire",
    "sg:tags":[
        "tv",
        "studio"
    ],
    "wof:name":"P Richards",
    "wof:placetype":"venue"
},
  "geometry": {"coordinates":[-0.8751000166,51.7767601013],"type":"Point"}
}