{
  "type": "Feature",
  "properties": {
    "addr:full":"20 Avenue One, Station Lane Industrial Estate Witney Oxfordshire OX28 4XZ",
    "addr:housenumber":"20",
    "addr:postcode":"ox28 4xz",
    "addr:street":"Avenue One Station Lane Industrial Estate",
    "iso:country":"GB",
    "sg:address":"20 Avenue One, Station Lane Industrial Estate",
    "sg:city":"Witney",
    "sg:classifiers":[
        {
            "category":"Shopping",
            "subcategory":"Catalog Store",
            "type":"Retail Goods"
        }
    ],
    "sg:postcode":"OX28 4XZ",
    "sg:province":"Oxfordshire",
    "sg:tags":[
        "mail",
        "order"
    ],
    "wof:name":"Hawksbury Ltd.",
    "wof:placetype":"venue"
},
  "geometry": {"coordinates":[-1.489573,51.776833],"type":"Point"}
}