{
  "type": "Feature",
  "properties": {
    "addr:full":"Unit 1 Halesfield 18 Telford Shropshire TF7 4PP",
    "addr:housenumber":"unit 1;18",
    "addr:postcode":"tf7 4pp",
    "addr:street":"Halesfield",
    "iso:country":"GB",
    "sg:address":"Unit 1 Halesfield 18",
    "sg:city":"Telford",
    "sg:classifiers":[
        {
            "category":"Manufacturing",
            "subcategory":"Metals",
            "type":"Manufacturing & Wholesale Goods"
        }
    ],
    "sg:postcode":"TF7 4PP",
    "sg:province":"Shropshire",
    "sg:tags":[
        "fab",
        "foundry"
    ],
    "wof:name":"Victor Shell Castings Ltd.",
    "wof:placetype":"venue"
},
  "geometry": {"coordinates":[-2.428251,52.641312],"type":"Point"}
}