{
  "type": "Feature",
  "properties": {
    "addr:full":"Berkeley Grange Carlisle Cumbria CA2 7PW",
    "addr:postcode":"ca2 7pw",
    "iso:country":"GB",
    "sg:address":"Berkeley Grange",
    "sg:city":"Carlisle",
    "sg:classifiers":[
        {
            "category":"Health Services",
            "subcategory":"Nursing And Care Facility",
            "type":"Services"
        }
    ],
    "sg:phone":"+44 1228 595138",
    "sg:postcode":"CA2 7PW",
    "sg:province":"Cumbria",
    "sg:tags":[
        "home"
    ],
    "sg:website":"http://www.whc.co.uk",
    "wof:name":"Lannercost House",
    "wof:placetype":"venue"
},
  "geometry": {"coordinates":[-2.969139,54.8951],"type":"Point"}
}