{
  "type": "Feature",
  "properties": {
    "addr:full":"2 Leconfield Close Tonbridge Kent TN9 2QU",
    "addr:housenumber":"2",
    "addr:postcode":"tn9 2qu",
    "addr:street":"Leconfield Close",
    "iso:country":"GB",
    "sg:address":"2 Leconfield Close",
    "sg:city":"Tonbridge",
    "sg:classifiers":[
        {
            "category":"Shopping",
            "subcategory":"Stationery & Office Supplies",
            "type":"Retail Goods"
        }
    ],
    "sg:phone":"+44 1732 356101",
    "sg:postcode":"TN9 2QU",
    "sg:province":"Kent",
    "sg:tags":[
        "commercial"
    ],
    "wof:name":"Business to Business Services",
    "wof:placetype":"venue"
},
  "geometry": {"coordinates":[0.254735,51.185486],"type":"Point"}
}