{
  "type": "Feature",
  "properties": {
    "iso:country":"GB",
    "sg:address":"Key House, Woodville Close, Wincheap",
    "sg:city":"Canterbury",
    "sg:classifiers":[
        {
            "category":"Education",
            "subcategory":"Special Training",
            "type":"Public Place"
        }
    ],
    "sg:phone":"+44 1227 459788",
    "sg:postcode":"CT1 3TX",
    "sg:province":"Kent",
    "sg:tags":[
        "product",
        "centre"
    ],
    "wof:name":"Key Training Services",
    "wof:placetype":"venue"
},
  "geometry": {"coordinates":[1.070634,51.272449],"type":"Point"}
}