{
  "type": "Feature",
  "properties": {
    "iso:country":"GB",
    "sg:address":"32b Wellmeadow St",
    "sg:city":"Paisley",
    "sg:classifiers":[
        {
            "category":"Home & Garden",
            "subcategory":"Building Materials",
            "type":"Retail Goods"
        }
    ],
    "sg:phone":"+44 141 561 2269",
    "sg:postcode":"PA1 2EG",
    "sg:province":"Renfrewshire",
    "sg:tags":[
        "hinge"
    ],
    "wof:name":"True Value",
    "wof:placetype":"venue"
},
  "geometry": {"coordinates":[-4.436103,55.844692],"type":"Point"}
}