{
  "type": "Feature",
  "properties": {
    "iso:country":"GB",
    "sg:address":"7 Bellfield Avenue, Cheadle Hulme",
    "sg:city":"Cheadle",
    "sg:classifiers":[
        {
            "category":"Health Services",
            "subcategory":"Nursing And Care Facility",
            "type":"Services"
        }
    ],
    "sg:phone":"+44 161 426 0444",
    "sg:postcode":"SK8 7AG",
    "sg:province":"Cheshire",
    "sg:tags":[
        "agency"
    ],
    "wof:name":"All Care Services",
    "wof:placetype":"venue"
},
  "geometry": {"coordinates":[-2.186978,53.373878],"type":"Point"}
}