{
  "type": "Feature",
  "properties": {
    "addr:full":"The Arches, Park Road Hartlepool Durham TS26 9HU",
    "addr:postcode":"ts26 9hu",
    "addr:street":"Park Road",
    "iso:country":"GB",
    "sg:address":"The Arches, Park Road",
    "sg:city":"Hartlepool",
    "sg:classifiers":[
        {
            "category":"Shopping",
            "subcategory":"Clothing, Apparel, & Fashions",
            "type":"Retail Goods"
        }
    ],
    "sg:phone":"+44 1429 276976",
    "sg:postcode":"TS26 9HU",
    "sg:province":"Durham",
    "sg:tags":[
        "lady",
        "fashionwear",
        "ladieswear"
    ],
    "wof:name":"Joanne",
    "wof:placetype":"venue"
},
  "geometry": {"coordinates":[-1.2179700136,54.6827011108],"type":"Point"}
}