{
  "type": "Feature",
  "properties": {
    "addr:full":"73 Queens Road Buckhurst Hill Essex IG9 5BW",
    "addr:housenumber":"73",
    "addr:postcode":"ig9 5bw",
    "addr:street":"Queens Road",
    "iso:country":"GB",
    "sg:address":"73 Queens Road",
    "sg:city":"Buckhurst Hill",
    "sg:classifiers":[
        {
            "category":"Building & Trades",
            "subcategory":"Equipment Rental",
            "type":"Services"
        },
        {
            "category":"Shopping",
            "subcategory":"Comic Books",
            "type":"Retail Goods"
        }
    ],
    "sg:phone":"+44 20 8505 0500",
    "sg:postcode":"IG9 5BW",
    "sg:province":"Essex",
    "sg:tags":[
        "jeweller",
        "supply"
    ],
    "wof:name":"C J W Manufacturing Ltd.",
    "wof:placetype":"venue"
},
  "geometry": {"coordinates":[0.042213,51.625618],"type":"Point"}
}