{
  "type": "Feature",
  "properties": {
    "addr:full":"247 Great Western Road Glasgow Glasgow City G4 9EG",
    "addr:housenumber":"247",
    "addr:postcode":"g4 9eg",
    "addr:street":"Great Western Road",
    "iso:country":"GB",
    "sg:address":"247 Great Western Road",
    "sg:city":"Glasgow",
    "sg:classifiers":[
        {
            "category":"Retail",
            "subcategory":"Laundry & Dry Cleaning",
            "type":"Services"
        }
    ],
    "sg:phone":"+44 141 564 1018",
    "sg:postcode":"G4 9EG",
    "sg:province":"Glasgow City",
    "sg:tags":[
        "alteration"
    ],
    "wof:name":"V I P Dry Cleaning",
    "wof:placetype":"venue"
},
  "geometry": {"coordinates":[-4.2740850449,55.8727645874],"type":"Point"}
}