{
  "type": "Feature",
  "properties": {
    "iso:country":"GB",
    "sg:address":"6 Holloway Street",
    "sg:city":"Minehead",
    "sg:classifiers":[
        {
            "category":"Restaurant",
            "type":"Food & Drink"
        }
    ],
    "sg:phone":"+44 1643 702723",
    "sg:postcode":"TA24 5NP",
    "sg:province":"Somerset",
    "sg:tags":[
        "chinese"
    ],
    "wof:name":"The Golden House Resturant",
    "wof:placetype":"venue"
},
  "geometry": {"coordinates":[-3.4789559841,51.2060432434],"type":"Point"}
}