{
  "type": "Feature",
  "properties": {
    "iso:country":"GB",
    "sg:address":"83 Main Road, Sutton At Hone",
    "sg:city":"Dartford",
    "sg:classifiers":[
        {
            "category":"Retail",
            "subcategory":"Repair Shop",
            "type":"Services"
        },
        {
            "category":"Home & Garden",
            "subcategory":"Hardware",
            "type":"Retail Goods"
        }
    ],
    "sg:phone":"+44 1322 863285",
    "sg:postcode":"DA4 9HQ",
    "sg:province":"Kent",
    "sg:tags":[
        "lawnmowers",
        "agricultural",
        "sale",
        "machinery"
    ],
    "sg:website":"http://www.ernestdoe.com",
    "wof:name":"Ernest Doe & Sons Ltd",
    "wof:placetype":"venue"
},
  "geometry": {"coordinates":[0.2374339998,51.4086647034],"type":"Point"}
}