{
  "type": "Feature",
  "properties": {
    "iso:country":"GB",
    "sg:address":"31 High Street",
    "sg:city":"Belford",
    "sg:classifiers":[
        {
            "category":"Bars & Pubs",
            "type":"Food & Drink"
        },
        {
            "category":"Community Center",
            "subcategory":"Social",
            "type":"Public Place"
        }
    ],
    "sg:postcode":"NE70 7NG",
    "sg:province":"Northumberland",
    "sg:tags":[
        "pubs",
        "house",
        "inn",
        "activity"
    ],
    "wof:name":"KEITH HANSON",
    "wof:placetype":"venue"
},
  "geometry": {"coordinates":[-1.8282619715,55.5977020264],"type":"Point"}
}