{
  "type": "Feature",
  "properties": {
    "iso:country":"GB",
    "sg:address":"3 Town Hall St",
    "sg:city":"Mirfield",
    "sg:classifiers":[
        {
            "category":"Shopping",
            "subcategory":"Department Store",
            "type":"Retail Goods"
        }
    ],
    "sg:postcode":"WF14 8DH",
    "sg:province":"West Yorkshire",
    "wof:name":"Andrews,Richard,",
    "wof:placetype":"venue"
},
  "geometry": {"coordinates":[-1.691448,53.674389],"type":"Point"}
}