{
  "type": "Feature",
  "properties": {
    "iso:country":"GB",
    "sg:address":"Units 1, & 2 The Sidings, Station Rd, Stalbridge",
    "sg:city":"Sturminster Newton",
    "sg:classifiers":[
        {
            "category":"Professional",
            "subcategory":"Art Services",
            "type":"Services"
        }
    ],
    "sg:phone":"+44 1963 364080",
    "sg:postcode":"DT10 2SS",
    "sg:province":"Dorset",
    "sg:tags":[
        "photographer"
    ],
    "wof:name":"Underhill",
    "wof:placetype":"venue"
},
  "geometry": {"coordinates":[-2.37121,50.9613],"type":"Point"}
}