{
  "type": "Feature",
  "properties": {
    "iso:country":"GB",
    "sg:address":"111-113 The Mall",
    "sg:city":"Hyde",
    "sg:classifiers":[
        {
            "category":"Commercial Area",
            "type":"Public Place"
        }
    ],
    "sg:phone":"+44 161 367 9061",
    "sg:postcode":"SK14 2QT",
    "sg:province":"Cheshire",
    "sg:tags":[
        "shop",
        "centre"
    ],
    "wof:name":"Clarendon Square Shopping Centre",
    "wof:placetype":"venue"
},
  "geometry": {"coordinates":[-2.0740890503,53.452911377],"type":"Point"}
}