{
  "type": "Feature",
  "properties": {
    "iso:country":"GB",
    "sg:address":"61 George Street",
    "sg:city":"Walsall",
    "sg:classifiers":[
        {
            "category":"Professional",
            "subcategory":"Art Services",
            "type":"Services"
        }
    ],
    "sg:phone":"+44 1922 644667",
    "sg:postcode":"WS1 1RS",
    "sg:province":"West Midlands",
    "sg:tags":[
        "picture",
        "restoration"
    ],
    "wof:name":"George St.Gallery",
    "wof:placetype":"venue"
},
  "geometry": {"coordinates":[-1.98073,52.582474],"type":"Point"}
}