{
  "type": "Feature",
  "properties": {
    "addr:full":"Suite 8b Kirkgate Business Centre, Stennard Island, Chantry Bridge Wakefield West Yorkshire WF1 5DL",
    "addr:housenumber":"suite 8b",
    "addr:postcode":"wf1 5dl",
    "addr:street":"Kirkgate Business Centre Stennard Island;West",
    "iso:country":"GB",
    "sg:address":"Suite 8b Kirkgate Business Centre, Stennard Island, Chantry Bridge",
    "sg:city":"Wakefield",
    "sg:classifiers":[
        {
            "category":"Professional",
            "subcategory":"Business Services",
            "type":"Services"
        },
        {
            "category":"Professional",
            "subcategory":"Credit Reporting & Collection",
            "type":"Services"
        }
    ],
    "sg:phone":"+44 1924 315998",
    "sg:postcode":"WF1 5DL",
    "sg:province":"West Yorkshire",
    "sg:tags":[
        "merchant",
        "rag",
        "export",
        "agent",
        "import"
    ],
    "wof:name":"Benley Associates",
    "wof:placetype":"venue"
},
  "geometry": {"coordinates":[-1.4887700081,53.6766090393],"type":"Point"}
}