{
  "type": "Feature",
  "properties": {
    "addr:full":"15 Byrom Street Manchester Greater Manchester M3 4PF",
    "addr:housenumber":"15",
    "addr:postcode":"m3 4pf",
    "addr:street":"Byrom Street",
    "iso:country":"GB",
    "sg:address":"15 Byrom Street",
    "sg:city":"Manchester",
    "sg:classifiers":[
        {
            "category":"Professional",
            "subcategory":"Lawyer & Legal Services",
            "type":"Services"
        }
    ],
    "sg:phone":"+44 161 834 6066",
    "sg:postcode":"M3 4PF",
    "sg:province":"Greater Manchester",
    "sg:tags":[
        "solicitor"
    ],
    "wof:name":"Lambert Storey",
    "wof:placetype":"venue"
},
  "geometry": {"coordinates":[-2.2518959045,53.478187561],"type":"Point"}
}