{
  "type": "Feature",
  "properties": {
    "addr:full":"347 Fernhill Rd Farnborough Hampshire GU14 9EN",
    "addr:housenumber":"347",
    "addr:postcode":"gu14 9en",
    "addr:street":"Fernhill Rd",
    "iso:country":"GB",
    "sg:address":"347 Fernhill Rd",
    "sg:city":"Farnborough",
    "sg:classifiers":[
        {
            "category":"Utilities",
            "subcategory":"Natural Gas",
            "type":"Services"
        }
    ],
    "sg:phone":"+44 1276 34391",
    "sg:postcode":"GU14 9EN",
    "sg:province":"Hampshire",
    "sg:tags":[
        "control",
        "energy",
        "management",
        "system"
    ],
    "wof:name":"Webb Tony Gas Services",
    "wof:placetype":"venue"
},
  "geometry": {"coordinates":[-0.776704,51.315735],"type":"Point"}
}