{
  "type": "Feature",
  "properties": {
    "iso:country":"GB",
    "sg:address":"44 High Street",
    "sg:city":"Egham",
    "sg:classifiers":[
        {
            "category":"Retail",
            "subcategory":"Laundry & Dry Cleaning",
            "type":"Services"
        }
    ],
    "sg:phone":"+44 1784 477300",
    "sg:postcode":"TW20 9DP",
    "sg:province":"Surrey",
    "sg:tags":[
        "alteration"
    ],
    "wof:name":"Dry Cleaning by Panache",
    "wof:placetype":"venue"
},
  "geometry": {"coordinates":[-0.544734,51.43264],"type":"Point"}
}