{
  "type": "Feature",
  "properties": {
    "addr:full":"18 Newnham Parade, College Road, Cheshunt Waltham Cross Essex EN8 9NU",
    "addr:housenumber":"18",
    "addr:postcode":"en8 9nu",
    "addr:street":"Newnham Parade College Road",
    "iso:country":"GB",
    "sg:address":"18 Newnham Parade, College Road, Cheshunt",
    "sg:city":"Waltham Cross",
    "sg:classifiers":[
        {
            "category":"Shopping",
            "subcategory":"Shoes",
            "type":"Retail Goods"
        }
    ],
    "sg:phone":"+44 1992 636622",
    "sg:postcode":"EN8 9NU",
    "sg:province":"Essex",
    "wof:name":"Nicholas Shoe Repairs",
    "wof:placetype":"venue"
},
  "geometry": {"coordinates":[-0.0357040018,51.7022743225],"type":"Point"}
}