{
  "type": "Feature",
  "properties": {
    "iso:country":"GB",
    "sg:address":"Treluggan Quarry, Landrake",
    "sg:city":"Saltash",
    "sg:classifiers":[
        {
            "category":"Manufacturing",
            "subcategory":"Wood Products",
            "type":"Manufacturing & Wholesale Goods"
        }
    ],
    "sg:postcode":"PL12 5ES",
    "sg:province":"Cornwall",
    "sg:tags":[
        "maker",
        "cabinet"
    ],
    "wof:name":"K J Smale",
    "wof:placetype":"venue"
},
  "geometry": {"coordinates":[-4.290572,50.42329],"type":"Point"}
}