{
  "type": "Feature",
  "properties": {
    "addr:full":"Tremains Road Bridgend Bridgend CF31 1TZ",
    "addr:postcode":"cf31 1tz",
    "addr:street":"Tremains Road",
    "iso:country":"GB",
    "sg:address":"Tremains Road",
    "sg:city":"Bridgend",
    "sg:classifiers":[
        {
            "category":"Building & Trades",
            "subcategory":"Construction",
            "type":"Services"
        }
    ],
    "sg:phone":"+44 1656 663557",
    "sg:postcode":"CF31 1TZ",
    "sg:province":"Bridgend",
    "sg:tags":[
        "paint",
        "household",
        "spraying"
    ],
    "wof:name":"D B S Paint Factors",
    "wof:placetype":"venue"
},
  "geometry": {"coordinates":[-3.571944,51.505058],"type":"Point"}
}