{
  "type": "Feature",
  "properties": {
    "addr:full":"5 Bath Hill, Keynsham Bristol City of Bristol BS31 1EB",
    "addr:housenumber":"5",
    "addr:postcode":"bs31 1eb",
    "addr:street":"Bath Hill",
    "iso:country":"GB",
    "sg:address":"5 Bath Hill, Keynsham",
    "sg:city":"Bristol",
    "sg:classifiers":[
        {
            "category":"Professional",
            "subcategory":"Business Services",
            "type":"Services"
        }
    ],
    "sg:phone":"+44 117 986 2366",
    "sg:postcode":"BS31 1EB",
    "sg:province":"City of Bristol",
    "sg:tags":[
        "import",
        "export",
        "agent"
    ],
    "wof:name":"Keynsham Pet & Garden",
    "wof:placetype":"venue"
},
  "geometry": {"coordinates":[-2.49775,51.414738],"type":"Point"}
}