{
  "type": "Feature",
  "properties": {
    "addr:full":"42 Main Street, Longridge Bathgate North Lanarkshire EH47 8AD",
    "addr:housenumber":"42",
    "addr:postcode":"eh47 8ad",
    "addr:street":"Main Street;Bathgate",
    "iso:country":"GB",
    "sg:address":"42 Main Street, Longridge",
    "sg:city":"Bathgate",
    "sg:classifiers":[
        {
            "category":"Fast Food",
            "type":"Food & Drink"
        },
        {
            "category":"Food & Beverages",
            "subcategory":"Meat & Fish",
            "type":"Retail Goods"
        }
    ],
    "sg:phone":"+44 1501 772100",
    "sg:postcode":"EH47 8AD",
    "sg:province":"North Lanarkshire",
    "sg:tags":[
        "chip",
        "away",
        "take"
    ],
    "wof:name":"Aldo's Fish & Chicken Bar",
    "wof:placetype":"venue"
},
  "geometry": {"coordinates":[-3.6781671047,55.8429031372],"type":"Point"}
}