{
  "type": "Feature",
  "properties": {
    "iso:country":"GB",
    "sg:address":"Hills Jarrett, Gainsborough House",
    "sg:city":"Sawbridgeworth",
    "sg:classifiers":[
        {
            "category":"Real Estate",
            "subcategory":"Architect",
            "type":"Services"
        }
    ],
    "sg:postcode":"CM21 9RG",
    "sg:province":"Essex",
    "wof:name":"Engineering Support Ltd.",
    "wof:placetype":"venue"
},
  "geometry": {"coordinates":[0.1472229958,51.8125267029],"type":"Point"}
}