{
  "type": "Feature",
  "properties": {
    "addr:full":"12 Robin Hood Crescent, Edenthorpe Doncaster South Yorkshire DN3 2JJ",
    "addr:housenumber":"12",
    "addr:postcode":"dn3 2jj",
    "addr:street":"Robin Hood Crescent",
    "iso:country":"GB",
    "sg:address":"12 Robin Hood Crescent, Edenthorpe",
    "sg:city":"Doncaster",
    "sg:classifiers":[
        {
            "category":"Building & Trades",
            "subcategory":"Construction",
            "type":"Services"
        }
    ],
    "sg:postcode":"DN3 2JJ",
    "sg:province":"South Yorkshire",
    "sg:tags":[
        "decorator",
        "painter"
    ],
    "wof:name":"Design Decorators",
    "wof:placetype":"venue"
},
  "geometry": {"coordinates":[-1.0638999939,53.5503349304],"type":"Point"}
}