{
  "type": "Feature",
  "properties": {
    "addr:full":"259-261 Soho Road, Handsworth Birmingham West Midlands B21 9RY",
    "addr:housenumber":"259-261",
    "addr:postcode":"b21 9ry",
    "addr:street":"Soho Road",
    "iso:country":"GB",
    "sg:address":"259-261 Soho Road, Handsworth",
    "sg:city":"Birmingham",
    "sg:classifiers":[
        {
            "category":"Shopping",
            "subcategory":"Computers & Home Electronics",
            "type":"Retail Goods"
        },
        {
            "category":"Communications",
            "type":"Services"
        }
    ],
    "sg:phone":"+44 121 554 1878",
    "sg:postcode":"B21 9RY",
    "sg:province":"West Midlands",
    "sg:tags":[
        "tv",
        "radio",
        "television",
        "video",
        "sale"
    ],
    "wof:name":"Electro Centre Ltd",
    "wof:placetype":"venue"
},
  "geometry": {"coordinates":[-1.935543,52.50338],"type":"Point"}
}