{
  "type": "Feature",
  "properties": {
    "iso:country":"GB",
    "sg:address":"2 Rossal Place, Hodge Lea",
    "sg:city":"Milton Keynes",
    "sg:classifiers":[
        {
            "category":"Education",
            "subcategory":"Music School",
            "type":"Public Place"
        }
    ],
    "sg:postcode":"MK12 6JE",
    "sg:province":"Buckinghamshire",
    "sg:tags":[
        "teacher"
    ],
    "wof:name":"Winfields' Music Tuition",
    "wof:placetype":"venue"
},
  "geometry": {"coordinates":[-0.811481,52.051521],"type":"Point"}
}