{
  "type": "Feature",
  "properties": {
    "iso:country":"GB",
    "sg:address":"Westminster Road, North Hykeham",
    "sg:city":"Lincoln",
    "sg:classifiers":[
        {
            "category":"Building & Trades",
            "subcategory":"Equipment Rental",
            "type":"Services"
        }
    ],
    "sg:phone":"+44 1522 500488",
    "sg:postcode":"LN6 3QY",
    "sg:province":"Lincolnshire",
    "sg:tags":[
        "plant",
        "machinery"
    ],
    "wof:name":"P R S Hire Services Ltd.",
    "wof:placetype":"venue"
},
  "geometry": {"coordinates":[-0.597984,53.199333],"type":"Point"}
}