{
  "type": "Feature",
  "properties": {
    "iso:country":"GB",
    "sg:address":"30a Ashbourne Road",
    "sg:city":"Derby",
    "sg:classifiers":[
        {
            "category":"Communications",
            "type":"Services"
        }
    ],
    "sg:phone":"+44 1332 344430",
    "sg:postcode":"DE22 3AD",
    "sg:province":"Derbyshire",
    "sg:tags":[
        "telecommunication"
    ],
    "wof:name":"J I C  Electronics Ltd.",
    "wof:placetype":"venue"
},
  "geometry": {"coordinates":[-1.4926199913,52.9257850647],"type":"Point"}
}