{
  "type": "Feature",
  "properties": {
    "addr:full":"Spring Road Feltham Greater London TW13 7JB",
    "addr:postcode":"tw13 7jb",
    "addr:street":"Spring Road",
    "iso:country":"GB",
    "sg:address":"Spring Road",
    "sg:city":"Feltham",
    "sg:classifiers":[
        {
            "category":"Social Services",
            "subcategory":"Retirement Home",
            "type":"Services"
        }
    ],
    "sg:phone":"+44 20 8890 2167",
    "sg:postcode":"TW13 7JB",
    "sg:province":"Greater London",
    "sg:tags":[
        "residential",
        "care"
    ],
    "wof:name":"Shaw Homes",
    "wof:placetype":"venue"
},
  "geometry": {"coordinates":[-0.418924,51.437622],"type":"Point"}
}