{
  "type": "Feature",
  "properties": {
    "addr:full":"22 Church Street Rickmansworth Hertfordshire WD3 1DD",
    "addr:housenumber":"22",
    "addr:postcode":"wd3 1dd",
    "addr:street":"Church Street",
    "iso:country":"GB",
    "sg:address":"22 Church Street",
    "sg:city":"Rickmansworth",
    "sg:classifiers":[
        {
            "category":"Professional",
            "subcategory":"Printing & Photocopies",
            "type":"Services"
        }
    ],
    "sg:phone":"+44 1923 777575",
    "sg:postcode":"WD3 1DD",
    "sg:province":"Hertfordshire",
    "sg:tags":[
        "printer"
    ],
    "wof:name":"T P W Press Ltd.",
    "wof:placetype":"venue"
},
  "geometry": {"coordinates":[-0.4689539969,51.6377220154],"type":"Point"}
}