{
  "type": "Feature",
  "properties": {
    "addr:full":"108 Hawley La Farnborough Hampshire GU14 8HY",
    "addr:housenumber":"108",
    "addr:postcode":"gu14 8hy",
    "addr:street":"Hawley La Farnborough",
    "iso:country":"GB",
    "sg:address":"108 Hawley La",
    "sg:city":"Farnborough",
    "sg:classifiers":[
        {
            "category":"Organizations",
            "subcategory":"Professional Association",
            "type":"Services"
        }
    ],
    "sg:phone":"+44 1256 318900",
    "sg:postcode":"GU14 8HY",
    "sg:province":"Hampshire",
    "sg:tags":[
        "tech",
        "system",
        "automation"
    ],
    "wof:name":"Crouzet Ltd",
    "wof:placetype":"venue"
},
  "geometry": {"coordinates":[-0.754939,51.310299],"type":"Point"}
}