{
  "type": "Feature",
  "properties": {
    "addr:full":"33 Dudley Road Brierley Hill West Midlands DY5 1HA",
    "addr:housenumber":"33",
    "addr:postcode":"dy5 1ha",
    "addr:street":"Dudley Road",
    "iso:country":"GB",
    "sg:address":"33 Dudley Road",
    "sg:city":"Brierley Hill",
    "sg:classifiers":[
        {
            "category":"Bars & Pubs",
            "type":"Food & Drink"
        }
    ],
    "sg:phone":"+44 1384 75549",
    "sg:postcode":"DY5 1HA",
    "sg:province":"West Midlands",
    "sg:tags":[
        "pubs",
        "inn"
    ],
    "wof:name":"The Saracens Head",
    "wof:placetype":"venue"
},
  "geometry": {"coordinates":[-2.121333,52.484016],"type":"Point"}
}