{
  "type": "Feature",
  "properties": {
    "addr:full":"55 Dewley Cramlington Northumberland NE23 6DT",
    "addr:housenumber":"55",
    "addr:postcode":"ne23 6dt",
    "addr:street":"Dewley;Northumberland",
    "iso:country":"GB",
    "sg:address":"55 Dewley",
    "sg:city":"Cramlington",
    "sg:classifiers":[
        {
            "category":"Food & Beverages",
            "subcategory":"Bakery",
            "type":"Retail Goods"
        }
    ],
    "sg:postcode":"NE23 6DT",
    "sg:province":"Northumberland",
    "sg:tags":[
        "baker"
    ],
    "wof:name":"Fruit & Fancies",
    "wof:placetype":"venue"
},
  "geometry": {"coordinates":[-1.583269,55.081345],"type":"Point"}
}