{
  "type": "Feature",
  "properties": {
    "addr:full":"Old Stone Cottage Farm, Brighton Road Crawley West Sussex RH11 9BE",
    "addr:postcode":"rh11 9be",
    "addr:street":"Old;Brighton Road",
    "iso:country":"GB",
    "sg:address":"Old Stone Cottage Farm, Brighton Road",
    "sg:city":"Crawley",
    "sg:classifiers":[
        {
            "category":"Building & Trades",
            "subcategory":"Construction",
            "type":"Services"
        }
    ],
    "sg:phone":"+44 1293 520726",
    "sg:postcode":"RH11 9BE",
    "sg:province":"West Sussex",
    "sg:tags":[
        "builder"
    ],
    "wof:name":"J A Wyles",
    "wof:placetype":"venue"
},
  "geometry": {"coordinates":[-0.19553,51.092602],"type":"Point"}
}