{
  "type": "Feature",
  "properties": {
    "iso:country":"GB",
    "sg:address":"The Gateway, Parkgate",
    "sg:city":"Rotherham",
    "sg:classifiers":[
        {
            "category":"Manufacturing",
            "subcategory":"Wood Products",
            "type":"Manufacturing & Wholesale Goods"
        }
    ],
    "sg:phone":"+44 1709 521103",
    "sg:postcode":"S62 6JL",
    "sg:province":"South Yorkshire",
    "wof:name":"Z N D (U K) Ltd.",
    "wof:placetype":"venue"
},
  "geometry": {"coordinates":[-1.344284,53.456436],"type":"Point"}
}