{
  "type": "Feature",
  "properties": {
    "addr:full":"Unit 645 Portslade Road London Greater London SW8 3DH",
    "addr:housenumber":"645",
    "addr:postcode":"sw8 3dh",
    "addr:street":"Portslade Road",
    "iso:country":"GB",
    "sg:address":"Unit 645 Portslade Road",
    "sg:city":"London",
    "sg:classifiers":[
        {
            "category":"Parking",
            "type":"Transportation"
        },
        {
            "category":"Retail",
            "subcategory":"Auto Repair",
            "type":"Services"
        }
    ],
    "sg:phone":"+44 20 7627 8382",
    "sg:postcode":"SW8 3DH",
    "sg:province":"Greater London",
    "sg:tags":[
        "garage",
        "valet",
        "related",
        "car"
    ],
    "wof:name":"Magic Hand Car Wash & Valeting Centre",
    "wof:placetype":"venue"
},
  "geometry": {"coordinates":[-0.1411270052,51.4718208313],"type":"Point"}
}