{
  "type": "Feature",
  "properties": {
    "addr:full":"Oxstalls Farm, Warwick Road Stratford-upon-avon Warwickshire CV37 0NS",
    "addr:postcode":"cv37 0ns",
    "addr:street":"Warwick Road",
    "iso:country":"GB",
    "sg:address":"Oxstalls Farm, Warwick Road",
    "sg:city":"Stratford-upon-avon",
    "sg:classifiers":[
        {
            "category":"Farming",
            "subcategory":"Livestock Farm",
            "type":"Manufacturing & Wholesale Goods"
        },
        {
            "category":"Retail",
            "subcategory":"Animal Services",
            "type":"Services"
        }
    ],
    "sg:phone":"+44 1789 205277",
    "sg:postcode":"CV37 0NS",
    "sg:province":"Warwickshire",
    "sg:tags":[
        "breeder",
        "horse",
        "stud"
    ],
    "wof:name":"R R Evans",
    "wof:placetype":"venue"
},
  "geometry": {"coordinates":[-1.7072689533,52.1941337585],"type":"Point"}
}