{
  "type": "Feature",
  "properties": {
    "iso:country":"GB",
    "sg:address":"Compton Farm, Military Road, Brook",
    "sg:city":"Newport",
    "sg:classifiers":[
        {
            "category":"Recreation",
            "subcategory":"Campground",
            "type":"Entertainment"
        }
    ],
    "sg:postcode":"PO30 4HF",
    "sg:province":"Isle of Wight",
    "sg:tags":[
        "site",
        "camping"
    ],
    "wof:name":"Dennis T Phillips",
    "wof:placetype":"venue"
},
  "geometry": {"coordinates":[-1.4503409863,50.6520233154],"type":"Point"}
}