{
  "type": "Feature",
  "properties": {
    "addr:full":"23-27 Wellington Rd Orpington Kent BR5 4AG",
    "addr:housenumber":"23-27",
    "addr:postcode":"br5 4ag",
    "addr:street":"Wellington Rd",
    "iso:country":"GB",
    "sg:address":"23-27 Wellington Rd",
    "sg:city":"Orpington",
    "sg:classifiers":[
        {
            "category":"Professional",
            "subcategory":"Art Services",
            "type":"Services"
        },
        {
            "category":"Shopping",
            "subcategory":"Books",
            "type":"Retail Goods"
        }
    ],
    "sg:postcode":"BR5 4AG",
    "sg:province":"Kent",
    "sg:tags":[
        "graphic",
        "designer"
    ],
    "wof:name":"Jordan,Denis,",
    "wof:placetype":"venue"
},
  "geometry": {"coordinates":[0.1119889989,51.3854522705],"type":"Point"}
}