{
  "type": "Feature",
  "properties": {
    "iso:country":"GB",
    "sg:address":"30 Nottingham Road",
    "sg:city":"Loughborough",
    "sg:classifiers":[
        {
            "category":"Professional",
            "subcategory":"Testing Lab",
            "type":"Services"
        },
        {
            "category":"Autos & Motor Vehicles",
            "subcategory":"Motorcycle Sales",
            "type":"Retail Goods"
        }
    ],
    "sg:phone":"+44 1509 263967",
    "sg:postcode":"LE11 1EU",
    "sg:province":"Leicestershire",
    "sg:tags":[
        "mot"
    ],
    "wof:name":"David Wykes",
    "wof:placetype":"venue"
},
  "geometry": {"coordinates":[-1.200779,52.774914],"type":"Point"}
}