{
  "type": "Feature",
  "properties": {
    "addr:full":"Impulse House, St Johns Terrace, 19 Kingsway Bedford Bedfordshire MK42 9BJ",
    "addr:housenumber":"19",
    "addr:postcode":"mk42 9bj",
    "addr:street":"St Johns Terrace;Kingsway",
    "iso:country":"GB",
    "sg:address":"Impulse House, St Johns Terrace, 19 Kingsway",
    "sg:city":"Bedford",
    "sg:classifiers":[
        {
            "category":"Professional",
            "subcategory":"Management & Consulting",
            "type":"Services"
        }
    ],
    "sg:phone":"+44 1234 309444",
    "sg:postcode":"MK42 9BJ",
    "sg:province":"Bedfordshire",
    "sg:tags":[
        "consultant",
        "geophysical",
        "geological"
    ],
    "wof:name":"Impulse Geophysics",
    "wof:placetype":"venue"
},
  "geometry": {"coordinates":[-0.4659000039,52.1308403015],"type":"Point"}
}