{
  "type": "Feature",
  "properties": {
    "iso:country":"GB",
    "sg:address":"Unit 3, Pentland Retail Estate, Straiton Mains",
    "sg:city":"Loanhead",
    "sg:classifiers":[
        {
            "category":"Food & Beverages",
            "subcategory":"Supermarket",
            "type":"Retail Goods"
        }
    ],
    "sg:phone":"+44 131 448 2794",
    "sg:postcode":"EH20 9QH",
    "sg:province":"Midlothian",
    "wof:name":"Kwik Save Stores Ltd.",
    "wof:placetype":"venue"
},
  "geometry": {"coordinates":[-3.1492199898,55.877696991],"type":"Point"}
}