{
  "type": "Feature",
  "properties": {
    "addr:full":"1 Daniel Owen Precinct Mold Denbighshire CH7 1AP",
    "addr:housenumber":"1",
    "addr:postcode":"ch7 1ap",
    "addr:street":"Daniel Owen",
    "iso:country":"GB",
    "sg:address":"1 Daniel Owen Precinct",
    "sg:city":"Mold",
    "sg:classifiers":[
        {
            "category":"Personal",
            "subcategory":"Beauty Salon",
            "type":"Services"
        }
    ],
    "sg:phone":"+44 1352 756065",
    "sg:postcode":"CH7 1AP",
    "sg:province":"Denbighshire",
    "sg:tags":[
        "unisex",
        "hairdresser"
    ],
    "wof:name":"Streaks Ahead",
    "wof:placetype":"venue"
},
  "geometry": {"coordinates":[-3.142594099,53.1665267944],"type":"Point"}
}