{
  "type": "Feature",
  "properties": {
    "addr:full":"Liphook Road, Headley Bordon Hampshire GU35 8RF",
    "addr:postcode":"gu35 8rf",
    "addr:street":"Liphook Road",
    "iso:country":"GB",
    "sg:address":"Liphook Road, Headley",
    "sg:city":"Bordon",
    "sg:classifiers":[
        {
            "category":"Community Center",
            "type":"Public Place"
        }
    ],
    "sg:postcode":"GU35 8RF",
    "sg:province":"Hampshire",
    "sg:tags":[
        "nursery",
        "centre"
    ],
    "wof:name":"The Oaks Nursery",
    "wof:placetype":"venue"
},
  "geometry": {"coordinates":[-0.821696,51.120361],"type":"Point"}
}