{
  "type": "Feature",
  "properties": {
    "addr:full":"41 Castle Street Inverness Highland IV2 3DU",
    "addr:housenumber":"41",
    "addr:postcode":"iv2 3du",
    "addr:street":"Castle Street",
    "iso:country":"GB",
    "sg:address":"41 Castle Street",
    "sg:city":"Inverness",
    "sg:classifiers":[
        {
            "category":"Restaurant",
            "type":"Food & Drink"
        }
    ],
    "sg:phone":"+44 1463 230925",
    "sg:postcode":"IV2 3DU",
    "sg:province":"Highland",
    "wof:name":"Castle Restaurant",
    "wof:placetype":"venue"
},
  "geometry": {"coordinates":[-4.2241539955,57.4766044617],"type":"Point"}
}