{
  "type": "Feature",
  "properties": {
    "addr:full":"33a Rodney Street Liverpool Merseyside L1 9EH",
    "addr:housenumber":"33a",
    "addr:postcode":"l1 9eh",
    "addr:street":"Rodney Street",
    "iso:country":"GB",
    "sg:address":"33a Rodney Street",
    "sg:city":"Liverpool",
    "sg:classifiers":[
        {
            "category":"Health Services",
            "subcategory":"Optometrist",
            "type":"Services"
        }
    ],
    "sg:phone":"+44 151 709 0368",
    "sg:postcode":"L1 9EH",
    "sg:province":"Merseyside",
    "sg:tags":[
        "optician"
    ],
    "wof:name":"Conlon & Sons Ltd.",
    "wof:placetype":"venue"
},
  "geometry": {"coordinates":[-2.973247,53.40123],"type":"Point"}
}