{
  "type": "Feature",
  "properties": {
    "iso:country":"GB",
    "sg:address":"Charthouse, Chart Lane",
    "sg:city":"Dorking",
    "sg:classifiers":[
        {
            "category":"Professional",
            "subcategory":"Art Services",
            "type":"Services"
        }
    ],
    "sg:phone":"+44 1306 882040",
    "sg:postcode":"RH4 2BU",
    "sg:province":"Surrey",
    "sg:tags":[
        "graphic",
        "designer"
    ],
    "wof:name":"J.A Design",
    "wof:placetype":"venue"
},
  "geometry": {"coordinates":[-0.328814,51.233341],"type":"Point"}
}