{
  "type": "Feature",
  "properties": {
    "addr:full":"44 Little Common Spalding Cambridgeshire PE12 8BQ",
    "addr:housenumber":"44",
    "addr:postcode":"pe12 8bq",
    "addr:street":"Little Common",
    "iso:country":"GB",
    "sg:address":"44 Little Common",
    "sg:city":"Spalding",
    "sg:classifiers":[
        {
            "category":"Food & Beverages",
            "subcategory":"Farmers Market",
            "type":"Retail Goods"
        }
    ],
    "sg:postcode":"PE12 8BQ",
    "sg:province":"Cambridgeshire",
    "sg:tags":[
        "gardener"
    ],
    "wof:name":"Derek R Bridger",
    "wof:placetype":"venue"
},
  "geometry": {"coordinates":[0.000747,52.828186],"type":"Point"}
}