{
  "type": "Feature",
  "properties": {
    "addr:full":"93 Northbrook Street Newbury Berkshire RG14 1AA",
    "addr:housenumber":"93",
    "addr:postcode":"rg14 1aa",
    "addr:street":"Northbrook Street",
    "iso:country":"GB",
    "sg:address":"93 Northbrook Street",
    "sg:city":"Newbury",
    "sg:classifiers":[
        {
            "category":"Shopping",
            "subcategory":"Clothing, Apparel, & Fashions",
            "type":"Retail Goods"
        }
    ],
    "sg:phone":"+44 1635 36526",
    "sg:postcode":"RG14 1AA",
    "sg:province":"Berkshire",
    "sg:tags":[
        "shop"
    ],
    "wof:name":"Next Retail Ltd.",
    "wof:placetype":"venue"
},
  "geometry": {"coordinates":[-1.3246190548,51.4040718079],"type":"Point"}
}