{
  "type": "Feature",
  "properties": {
    "iso:country":"GB",
    "sg:address":"21 Watling Street",
    "sg:city":"Dartford",
    "sg:classifiers":[
        {
            "category":"Building & Trades",
            "subcategory":"Construction",
            "type":"Services"
        }
    ],
    "sg:phone":"+44 1322 274367",
    "sg:postcode":"DA1 1RP",
    "sg:province":"Kent",
    "sg:tags":[
        "ceiling",
        "contractor"
    ],
    "wof:name":"M J M Artexing",
    "wof:placetype":"venue"
},
  "geometry": {"coordinates":[0.236078,51.44117],"type":"Point"}
}