{
  "type": "Feature",
  "properties": {
    "addr:full":"60 Bounty Road Basingstoke Hampshire RG21 3BU",
    "addr:housenumber":"60",
    "addr:postcode":"rg21 3bu",
    "addr:street":"Bounty Road",
    "iso:country":"GB",
    "sg:address":"60 Bounty Road",
    "sg:city":"Basingstoke",
    "sg:classifiers":[
        {
            "category":"Health Services",
            "subcategory":"Health Practitioner",
            "type":"Services"
        }
    ],
    "sg:phone":"+44 1256 352719",
    "sg:postcode":"RG21 3BU",
    "sg:province":"Hampshire",
    "sg:tags":[
        "homoeopathic",
        "homeopathic"
    ],
    "wof:name":"Christopher Jacob",
    "wof:placetype":"venue"
},
  "geometry": {"coordinates":[-1.090641,51.260242],"type":"Point"}
}