{
  "type": "Feature",
  "properties": {
    "iso:country":"GB",
    "sg:address":"C/o The Janet Adegoke Leisure Ce, Ntre Bloemfontein Road",
    "sg:city":"London",
    "sg:classifiers":[
        {
            "category":"Sports & Exercise",
            "subcategory":"Gym",
            "type":"Entertainment"
        }
    ],
    "sg:phone":"+44 20 8743 3401",
    "sg:postcode":"W12 7DH",
    "sg:province":"Greater London",
    "sg:tags":[
        "fitness",
        "health",
        "centre"
    ],
    "wof:name":"Bodyworx",
    "wof:placetype":"venue"
},
  "geometry": {"coordinates":[-0.2348800004,51.510761261],"type":"Point"}
}