{
  "type": "Feature",
  "properties": {
    "addr:full":"Elm Tree Workshops, The Causeway Ipswich Suffolk IP7 7LJ",
    "addr:postcode":"ip7 7lj",
    "addr:street":"Elm;The Causeway",
    "iso:country":"GB",
    "sg:address":"Elm Tree Workshops, The Causeway",
    "sg:city":"Ipswich",
    "sg:classifiers":[
        {
            "category":"Shopping",
            "subcategory":"Hobbies, Toys, & Games",
            "type":"Retail Goods"
        }
    ],
    "sg:postcode":"IP7 7LJ",
    "sg:province":"Suffolk",
    "sg:tags":[
        "toy"
    ],
    "wof:name":"Hitcham Horses",
    "wof:placetype":"venue"
},
  "geometry": {"coordinates":[0.90409,52.134682],"type":"Point"}
}