{
  "type": "Feature",
  "properties": {
    "addr:full":"Erfstadt Ct Wokingham Berkshire RG40 2YF",
    "addr:postcode":"rg40 2yf",
    "addr:street":"Erfstadt Ct",
    "iso:country":"GB",
    "sg:address":"Erfstadt Ct",
    "sg:city":"Wokingham",
    "sg:classifiers":[
        {
            "category":"Bus Charters",
            "type":"Transportation"
        }
    ],
    "sg:phone":"+44 118 979 4875",
    "sg:postcode":"RG40 2YF",
    "sg:province":"Berkshire",
    "sg:tags":[
        "coach"
    ],
    "wof:name":"Q Drive Holdings Ltd",
    "wof:placetype":"venue"
},
  "geometry": {"coordinates":[-0.8348640203,51.4095954895],"type":"Point"}
}