{
  "type": "Feature",
  "properties": {
    "iso:country":"GB",
    "sg:address":"17 Uplands Avenue",
    "sg:city":"Deeside",
    "sg:classifiers":[
        {
            "category":"Building & Trades",
            "subcategory":"Construction",
            "type":"Services"
        }
    ],
    "sg:phone":"+44 1244 811835",
    "sg:postcode":"CH5 4LD",
    "sg:province":"Flintshire",
    "sg:tags":[
        "roofing"
    ],
    "wof:name":"Frederick Blundell",
    "wof:placetype":"venue"
},
  "geometry": {"coordinates":[-3.060679,53.210033],"type":"Point"}
}