{
  "type": "Feature",
  "properties": {
    "iso:country":"GB",
    "sg:address":"32 Halifax Road",
    "sg:city":"Halifax",
    "sg:classifiers":[
        {
            "category":"Retail",
            "subcategory":"Auto Repair",
            "type":"Services"
        }
    ],
    "sg:postcode":"HX3 8HQ",
    "sg:province":"West Yorkshire",
    "sg:tags":[
        "modification",
        "garage"
    ],
    "wof:name":"Roydfield Garage",
    "wof:placetype":"venue"
},
  "geometry": {"coordinates":[-1.817878,53.726109],"type":"Point"}
}