{
  "type": "Feature",
  "properties": {
    "addr:full":"85 High Street Pwllheli Gwynedd LL53 5RR",
    "addr:housenumber":"85",
    "addr:postcode":"ll53 5rr",
    "addr:street":"High Street",
    "iso:country":"GB",
    "sg:address":"85 High Street",
    "sg:city":"Pwllheli",
    "sg:classifiers":[
        {
            "category":"Shopping",
            "subcategory":"Gifts & Souvenirs",
            "type":"Retail Goods"
        }
    ],
    "sg:postcode":"LL53 5RR",
    "sg:province":"Gwynedd",
    "sg:tags":[
        "shop"
    ],
    "wof:name":"Mabinogi",
    "wof:placetype":"venue"
},
  "geometry": {"coordinates":[-4.416299,52.889931],"type":"Point"}
}