{
  "type": "Feature",
  "properties": {
    "iso:country":"GB",
    "sg:address":"Unit2, Central Retail Park, Grahams Road",
    "sg:city":"Falkirk",
    "sg:classifiers":[
        {
            "category":"Home & Garden",
            "subcategory":"Furniture",
            "type":"Retail Goods"
        }
    ],
    "sg:phone":"+44 1324 634027",
    "sg:postcode":"FK1 1LW",
    "sg:province":"Falkirk",
    "sg:tags":[
        "outlet"
    ],
    "sg:website":"http://www.harveys.co.uk",
    "wof:name":"Harveys Furnishing Ltd",
    "wof:placetype":"venue"
},
  "geometry": {"coordinates":[-3.782519,56.004154],"type":"Point"}
}