{
  "type": "Feature",
  "properties": {
    "iso:country":"GB",
    "sg:address":"8 Vine Street",
    "sg:city":"Grantham",
    "sg:classifiers":[
        {
            "category":"Personal",
            "subcategory":"Beauty Salon",
            "type":"Services"
        }
    ],
    "sg:phone":"+44 1476 561270",
    "sg:postcode":"NG31 6RQ",
    "sg:province":"Lincolnshire",
    "sg:tags":[
        "unisex",
        "hairdresser"
    ],
    "wof:name":"Margaret Newton Hair Stylists",
    "wof:placetype":"venue"
},
  "geometry": {"coordinates":[-0.642358,52.914127],"type":"Point"}
}