{
  "type": "Feature",
  "properties": {
    "iso:country":"GB",
    "sg:address":"Rufford, Colliery Lane, Rainworth",
    "sg:city":"Mansfield",
    "sg:classifiers":[
        {
            "category":"Wholesale",
            "subcategory":"Scrap",
            "type":"Manufacturing & Wholesale Goods"
        }
    ],
    "sg:phone":"+44 1623 795201",
    "sg:postcode":"NG21 0HR",
    "sg:province":"Nottinghamshire",
    "sg:tags":[
        "breaker",
        "dismantlers"
    ],
    "wof:name":"Robin Hood Coachworks",
    "wof:placetype":"venue"
},
  "geometry": {"coordinates":[-1.118713975,53.1182861328],"type":"Point"}
}