{
  "type": "Feature",
  "properties": {
    "iso:country":"GB",
    "sg:address":"3 Bondgate",
    "sg:city":"Otley",
    "sg:classifiers":[
        {
            "category":"Cafe",
            "type":"Food & Drink"
        }
    ],
    "sg:phone":"+44 1943 467874",
    "sg:postcode":"LS21 3AB",
    "sg:province":"North Yorkshire",
    "sg:tags":[
        "tea",
        "room"
    ],
    "wof:name":"Cobblestones Tea Rooms",
    "wof:placetype":"venue"
},
  "geometry": {"coordinates":[-1.6936440468,53.9039802551],"type":"Point"}
}