{
  "type": "Feature",
  "properties": {
    "addr:full":"29 Castle Street Dundee Dundee City DD1 3AD",
    "addr:housenumber":"29",
    "addr:postcode":"dd1 3ad",
    "addr:street":"Castle Street",
    "iso:country":"GB",
    "sg:address":"29 Castle Street",
    "sg:city":"Dundee",
    "sg:classifiers":[
        {
            "category":"Shopping",
            "subcategory":"Musical Instruments",
            "type":"Retail Goods"
        }
    ],
    "sg:phone":"+44 1382 225619",
    "sg:postcode":"DD1 3AD",
    "sg:province":"Dundee City",
    "sg:tags":[
        "music",
        "sheet"
    ],
    "wof:name":"Sound Control",
    "wof:placetype":"venue"
},
  "geometry": {"coordinates":[-2.968374,56.460506],"type":"Point"}
}