{
  "type": "Feature",
  "properties": {
    "iso:country":"GB",
    "sg:address":"Arbury House Farm, Withybrook Road, Bulkington",
    "sg:city":"Nuneaton",
    "sg:classifiers":[
        {
            "category":"Farming",
            "subcategory":"Farm",
            "type":"Manufacturing & Wholesale Goods"
        }
    ],
    "sg:phone":"+44 1455 220228",
    "sg:postcode":"CV12 9JW",
    "sg:province":"Warwickshire",
    "sg:tags":[
        "mixed",
        "crop"
    ],
    "wof:name":"C J Grindal & Son",
    "wof:placetype":"venue"
},
  "geometry": {"coordinates":[-1.422995,52.47628],"type":"Point"}
}