{
  "type": "Feature",
  "properties": {
    "addr:full":"Unit 21, Spartan Industrial Centre, Brickhouse Lane West Bromwich West Midlands B70 0DH",
    "addr:housenumber":"unit 21",
    "addr:postcode":"b70 0dh",
    "addr:street":"Spartan Industrial Centre Brickhouse Lane West",
    "iso:country":"GB",
    "sg:address":"Unit 21, Spartan Industrial Centre, Brickhouse Lane",
    "sg:city":"West Bromwich",
    "sg:classifiers":[
        {
            "category":"Freight",
            "type":"Transportation"
        }
    ],
    "sg:phone":"+44 121 557 4100",
    "sg:postcode":"B70 0DH",
    "sg:province":"West Midlands",
    "sg:tags":[
        "haulage",
        "road"
    ],
    "wof:name":"Transfreight (Midlands) Ltd.",
    "wof:placetype":"venue"
},
  "geometry": {"coordinates":[-1.990224,52.518623],"type":"Point"}
}