{
  "type": "Feature",
  "properties": {
    "iso:country":"GB",
    "sg:address":"37 Oldham Road",
    "sg:city":"Ashton-under-lyne",
    "sg:classifiers":[
        {
            "category":"Bars & Pubs",
            "type":"Food & Drink"
        },
        {
            "category":"Community Center",
            "subcategory":"Social",
            "type":"Public Place"
        }
    ],
    "sg:postcode":"OL6 7AP",
    "sg:province":"Greater Manchester",
    "sg:tags":[
        "pubs",
        "house",
        "inn",
        "activity"
    ],
    "wof:name":"Marston Thompson & Evershed Ltd.",
    "wof:placetype":"venue"
},
  "geometry": {"coordinates":[-2.098341,53.488319],"type":"Point"}
}