{
  "type": "Feature",
  "properties": {
    "iso:country":"GB",
    "sg:address":"Unit 16, Knightsridge Service Units",
    "sg:city":"Livingston",
    "sg:classifiers":[
        {
            "category":"Building & Trades",
            "subcategory":"Construction",
            "type":"Services"
        }
    ],
    "sg:phone":"+44 1506 442724",
    "sg:postcode":"EH54 8RA",
    "sg:province":"West Lothian",
    "sg:tags":[
        "dry",
        "lining",
        "plasterers",
        "screeders"
    ],
    "wof:name":"Cameron Drywall Contractors Ltd.",
    "wof:placetype":"venue"
},
  "geometry": {"coordinates":[-3.530962944,55.9141387939],"type":"Point"}
}