{
  "type": "Feature",
  "properties": {
    "iso:country":"GB",
    "sg:address":"Stirling House, 7 St Johns Road, Hedge End",
    "sg:city":"Southampton",
    "sg:classifiers":[
        {
            "category":"Building & Trades",
            "subcategory":"Construction",
            "type":"Services"
        }
    ],
    "sg:phone":"+44 23 8067 4644",
    "sg:postcode":"SO30 4AA",
    "sg:province":"Hampshire",
    "sg:tags":[
        "builder"
    ],
    "wof:name":"The Finnegan Building Co. Ltd.",
    "wof:placetype":"venue"
},
  "geometry": {"coordinates":[-1.3034479618,50.9132003784],"type":"Point"}
}