{
  "type": "Feature",
  "properties": {
    "addr:full":"42a Rossall Road Thornton-cleveleys Lancashire FY5 1EE",
    "addr:housenumber":"42a",
    "addr:postcode":"fy5 1ee",
    "addr:street":"Rossall Road",
    "iso:country":"GB",
    "sg:address":"42a Rossall Road",
    "sg:city":"Thornton-cleveleys",
    "sg:classifiers":[
        {
            "category":"Home & Garden",
            "subcategory":"Home Furnishings",
            "type":"Retail Goods"
        }
    ],
    "sg:postcode":"FY5 1EE",
    "sg:province":"Lancashire",
    "sg:tags":[
        "awning",
        "canopy",
        "blinds"
    ],
    "wof:name":"Rossall Blinds",
    "wof:placetype":"venue"
},
  "geometry": {"coordinates":[-3.0392930508,53.8818397522],"type":"Point"}
}