{
  "type": "Feature",
  "properties": {
    "addr:full":"Boyces Building Regent Street, Clifton Bristol City of Bristol BS8 4HU",
    "addr:postcode":"bs8 4hu",
    "addr:street":"Regent Street",
    "iso:country":"GB",
    "sg:address":"Boyces Building Regent Street, Clifton",
    "sg:city":"Bristol",
    "sg:classifiers":[
        {
            "category":"Professional",
            "type":"Services"
        }
    ],
    "sg:postcode":"BS8 4HU",
    "sg:province":"City of Bristol",
    "sg:tags":[
        "directory",
        "pub"
    ],
    "wof:name":"Dentons Directories (Franchise) Ltd",
    "wof:placetype":"venue"
},
  "geometry": {"coordinates":[-2.618284,51.455261],"type":"Point"}
}