{
  "type": "Feature",
  "properties": {
    "addr:full":"Premier House, 43-48 New St Birmingham West Midlands B2 4LJ",
    "addr:housenumber":"43-48",
    "addr:postcode":"b2 4lj",
    "addr:street":"New St",
    "iso:country":"GB",
    "sg:address":"Premier House, 43-48 New St",
    "sg:city":"Birmingham",
    "sg:classifiers":[
        {
            "category":"Organizations",
            "subcategory":"Non-profit Organization",
            "type":"Services"
        }
    ],
    "sg:phone":"+44 121 693 7652",
    "sg:postcode":"B2 4LJ",
    "sg:province":"West Midlands",
    "sg:tags":[
        "organisation",
        "voluntary",
        "charity"
    ],
    "wof:name":"The Child Aid Foundation",
    "wof:placetype":"venue"
},
  "geometry": {"coordinates":[-1.8993849754,52.4792518616],"type":"Point"}
}