{
  "type": "Feature",
  "properties": {
    "addr:full":"111 Bell St Reigate Surrey RH2 7LF",
    "addr:housenumber":"111",
    "addr:postcode":"rh2 7lf",
    "addr:street":"Bell St",
    "iso:country":"GB",
    "sg:address":"111 Bell St",
    "sg:city":"Reigate",
    "sg:classifiers":[
        {
            "category":"Professional",
            "subcategory":"Lawyer & Legal Services",
            "type":"Services"
        }
    ],
    "sg:phone":"+44 1737 244861",
    "sg:postcode":"RH2 7LF",
    "sg:province":"Surrey",
    "sg:tags":[
        "solicitor"
    ],
    "wof:name":"J Cooper",
    "wof:placetype":"venue"
},
  "geometry": {"coordinates":[-0.2033119947,51.2335548401],"type":"Point"}
}