{
  "type": "Feature",
  "properties": {
    "addr:full":"St Gilda's Chard Devon TA20 2AF",
    "addr:postcode":"ta20 2af",
    "addr:street":"St",
    "iso:country":"GB",
    "sg:address":"St Gilda's",
    "sg:city":"Chard",
    "sg:classifiers":[
        {
            "category":"Social Services",
            "subcategory":"Adult Care",
            "type":"Services"
        },
        {
            "category":"Government",
            "subcategory":"Office",
            "type":"Public Place"
        }
    ],
    "sg:phone":"+44 1460 67701",
    "sg:postcode":"TA20 2AF",
    "sg:province":"Devon",
    "sg:tags":[
        "housing",
        "local",
        "sheltered"
    ],
    "wof:name":"St Gilda's Sheltered Housing",
    "wof:placetype":"venue"
},
  "geometry": {"coordinates":[-2.9588999748,50.8726768494],"type":"Point"}
}