{
  "type": "Feature",
  "properties": {
    "iso:country":"GB",
    "sg:address":"Units 7 & 12 Eton Pk Indstl Est",
    "sg:city":"Burton-on-trent",
    "sg:classifiers":[
        {
            "category":"Shopping",
            "type":"Retail Goods"
        }
    ],
    "sg:postcode":"DE14 1RR",
    "sg:province":"Derbyshire",
    "sg:tags":[
        "part",
        "accessory"
    ],
    "wof:name":"Smith,Adrian D,",
    "wof:placetype":"venue"
},
  "geometry": {"coordinates":[-1.634353,52.819691],"type":"Point"}
}