{
  "type": "Feature",
  "properties": {
    "addr:full":"Units 7 & 12 Eton Pk Indstl Est Burton-on-trent Derbyshire DE14 1RR",
    "addr:housenumber":"units 7 & 12",
    "addr:postcode":"de14 1rr",
    "addr:street":"Eton Pk Indstl Est",
    "iso:country":"GB",
    "sg:address":"Units 7 & 12 Eton Pk Indstl Est",
    "sg:city":"Burton-on-trent",
    "sg:classifiers":[
        {
            "category":"Shopping",
            "type":"Retail Goods"
        }
    ],
    "sg:postcode":"DE14 1RR",
    "sg:province":"Derbyshire",
    "sg:tags":[
        "part",
        "accessory"
    ],
    "wof:name":"Smith,Adrian D,",
    "wof:placetype":"venue"
},
  "geometry": {"coordinates":[-1.634353,52.819691],"type":"Point"}
}