{
  "type": "Feature",
  "properties": {
    "addr:full":"20 Eastcheap London Greater London EC3M 1EB",
    "addr:housenumber":"20",
    "addr:postcode":"ec3m 1eb",
    "addr:street":"Eastcheap",
    "iso:country":"GB",
    "sg:address":"20 Eastcheap",
    "sg:city":"London",
    "sg:classifiers":[
        {
            "category":"Professional",
            "subcategory":"Management & Consulting",
            "type":"Services"
        }
    ],
    "sg:postcode":"EC3M 1EB",
    "sg:province":"Greater London",
    "sg:tags":[
        "consultant",
        "business"
    ],
    "wof:name":"Rimmer,John,",
    "wof:placetype":"venue"
},
  "geometry": {"coordinates":[-0.0838129967,51.5105552673],"type":"Point"}
}