{
  "type": "Feature",
  "properties": {
    "iso:country":"GB",
    "sg:address":"106 Moseley Av",
    "sg:city":"Coventry",
    "sg:classifiers":[
        {
            "category":"Professional",
            "subcategory":"Lawyer & Legal Services",
            "type":"Services"
        }
    ],
    "sg:phone":"+44 24 7660 1610",
    "sg:postcode":"CV6 1HQ",
    "sg:province":"Warwickshire",
    "sg:tags":[
        "writing"
    ],
    "wof:name":"Wills Direct",
    "wof:placetype":"venue"
},
  "geometry": {"coordinates":[-1.52555,52.418358],"type":"Point"}
}