{
  "type": "Feature",
  "properties": {
    "addr:full":"30 Heol Islwyn, Nelson Treharris Caerphilly CF46 6HG",
    "addr:housenumber":"30",
    "addr:postcode":"cf46 6hg",
    "addr:street":"Heol Islwyn",
    "iso:country":"GB",
    "sg:address":"30 Heol Islwyn, Nelson",
    "sg:city":"Treharris",
    "sg:classifiers":[
        {
            "category":"Social Services",
            "subcategory":"Adult Care",
            "type":"Services"
        },
        {
            "category":"Government",
            "subcategory":"Office",
            "type":"Public Place"
        }
    ],
    "sg:phone":"+44 1443 450066",
    "sg:postcode":"CF46 6HG",
    "sg:province":"Caerphilly",
    "sg:tags":[
        "housing",
        "central",
        "sheltered"
    ],
    "wof:name":"Heol Islwyn Complex",
    "wof:placetype":"venue"
},
  "geometry": {"coordinates":[-3.284114,51.652679],"type":"Point"}
}