{
  "type": "Feature",
  "properties": {
    "iso:country":"GB",
    "sg:address":"College Mill, Barkerend Road",
    "sg:city":"Bradford",
    "sg:classifiers":[
        {
            "category":"Shopping",
            "subcategory":"Crafts & Fabrics",
            "type":"Retail Goods"
        }
    ],
    "sg:phone":"+44 1274 722191",
    "sg:postcode":"BD1 4AU",
    "sg:province":"West Yorkshire",
    "sg:tags":[
        "yarn",
        "supply"
    ],
    "wof:name":"Texere Yarns",
    "wof:placetype":"venue"
},
  "geometry": {"coordinates":[-1.758306,53.795738],"type":"Point"}
}