{
  "type": "Feature",
  "properties": {
    "iso:country":"GB",
    "sg:address":"42 Stretford Rd, Urmston",
    "sg:city":"Manchester",
    "sg:classifiers":[
        {
            "category":"Autos & Motor Vehicles",
            "subcategory":"Fuel & Gas Station",
            "type":"Retail Goods"
        }
    ],
    "sg:phone":"+44 161 755 9840",
    "sg:postcode":"M41 9LS",
    "sg:province":"Cheshire",
    "sg:tags":[
        "petrol",
        "filling"
    ],
    "wof:name":"Total Convenience Stores",
    "wof:placetype":"venue"
},
  "geometry": {"coordinates":[-2.348702,53.445793],"type":"Point"}
}