{
  "type": "Feature",
  "properties": {
    "iso:country":"GB",
    "sg:address":"31 Fir Tree Avenue",
    "sg:city":"Chester",
    "sg:classifiers":[
        {
            "category":"Building & Trades",
            "subcategory":"Cleaning & Sanitation",
            "type":"Services"
        },
        {
            "category":"Retail",
            "subcategory":"Event Space",
            "type":"Services"
        }
    ],
    "sg:phone":"+44 1244 671672",
    "sg:postcode":"CH4 7QY",
    "sg:province":"Cheshire",
    "sg:tags":[
        "chemical",
        "wholesale",
        "polishing",
        "distribution",
        "floor"
    ],
    "wof:name":"Chemical Express",
    "wof:placetype":"venue"
},
  "geometry": {"coordinates":[-2.8994569778,53.1714401245],"type":"Point"}
}