{
  "type": "Feature",
  "properties": {
    "addr:full":"45 Lower Fitzwilliam Street Huddersfield West Yorkshire HD1 6AS",
    "addr:housenumber":"45",
    "addr:postcode":"hd1 6as",
    "addr:street":"Lower Fitzwilliam Street",
    "iso:country":"GB",
    "sg:address":"45 Lower Fitzwilliam Street",
    "sg:city":"Huddersfield",
    "sg:classifiers":[
        {
            "category":"Manufacturing",
            "subcategory":"Tools & Machinery",
            "type":"Manufacturing & Wholesale Goods"
        }
    ],
    "sg:postcode":"HD1 6AS",
    "sg:province":"West Yorkshire",
    "sg:tags":[
        "cleaning"
    ],
    "wof:name":"Ashley's Carpet Cleaners Supplies",
    "wof:placetype":"venue"
},
  "geometry": {"coordinates":[-1.78002,53.650936],"type":"Point"}
}