{
  "type": "Feature",
  "properties": {
    "iso:country":"GB",
    "sg:address":"Sintacel House, High Road",
    "sg:city":"Bushey",
    "sg:classifiers":[
        {
            "category":"Insurance",
            "subcategory":"Insurance Agent",
            "type":"Services"
        }
    ],
    "sg:phone":"+44 20 8950 0166",
    "sg:postcode":"WD23 1EE",
    "sg:province":"Hertfordshire",
    "sg:tags":[
        "broker"
    ],
    "wof:name":"Oakwood (Insurance)",
    "wof:placetype":"venue"
},
  "geometry": {"coordinates":[-0.3696619868,51.6454696655],"type":"Point"}
}