{
  "type": "Feature",
  "properties": {
    "iso:country":"GB",
    "sg:address":"46 Plymouth Court, Plymouth Close",
    "sg:city":"Redditch",
    "sg:classifiers":[
        {
            "category":"Social Services",
            "subcategory":"Adult Care",
            "type":"Services"
        },
        {
            "category":"Social Services",
            "subcategory":"Retirement Home",
            "type":"Services"
        }
    ],
    "sg:phone":"+44 1527 404446",
    "sg:postcode":"B97 4NR",
    "sg:province":"Warwickshire",
    "sg:tags":[
        "housing",
        "sheltered",
        "accommodation"
    ],
    "wof:name":"Plymouth Court Ltd",
    "wof:placetype":"venue"
},
  "geometry": {"coordinates":[-1.954884,52.297005],"type":"Point"}
}