{
  "type": "Feature",
  "properties": {
    "addr:full":"2 Kings Drive Midhurst West Sussex GU29 0BH",
    "addr:housenumber":"2",
    "addr:postcode":"gu29 0bh",
    "addr:street":"Kings Drive",
    "iso:country":"GB",
    "sg:address":"2 Kings Drive",
    "sg:city":"Midhurst",
    "sg:classifiers":[
        {
            "category":"Professional",
            "subcategory":"Management & Consulting",
            "type":"Services"
        }
    ],
    "sg:phone":"+44 1730 817123",
    "sg:postcode":"GU29 0BH",
    "sg:province":"West Sussex",
    "sg:tags":[
        "marketing",
        "consultant"
    ],
    "wof:name":"Ann Webster Associates",
    "wof:placetype":"venue"
},
  "geometry": {"coordinates":[-0.735611,51.017822],"type":"Point"}
}