{
  "type": "Feature",
  "properties": {
    "addr:full":"Galleymead Rd, Colnbrook Slough Berkshire SL3 0EH",
    "addr:postcode":"sl3 0eh",
    "addr:street":"Galleymead Rd",
    "iso:country":"GB",
    "sg:address":"Galleymead Rd, Colnbrook",
    "sg:city":"Slough",
    "sg:classifiers":[
        {
            "category":"Freight",
            "type":"Transportation"
        }
    ],
    "sg:postcode":"SL3 0EH",
    "sg:province":"Berkshire",
    "sg:tags":[
        "forwarders"
    ],
    "wof:name":"British Midland Airways Ltd",
    "wof:placetype":"venue"
},
  "geometry": {"coordinates":[-0.5064740181,51.4809799194],"type":"Point"}
}