{
  "type": "Feature",
  "properties": {
    "addr:full":"Campden Rd Stratford Upon Avon Warwickshire CV37 8LJ",
    "addr:postcode":"cv37 8lj",
    "addr:street":"Campden Rd",
    "iso:country":"GB",
    "sg:address":"Campden Rd",
    "sg:city":"Stratford Upon Avon",
    "sg:classifiers":[
        {
            "category":"Autos & Motor Vehicles",
            "subcategory":"Automobile Sales",
            "type":"Retail Goods"
        }
    ],
    "sg:phone":"+44 1789 721707",
    "sg:postcode":"CV37 8LJ",
    "sg:province":"Warwickshire",
    "sg:tags":[
        "car"
    ],
    "wof:name":"Cotswold Car Co",
    "wof:placetype":"venue"
},
  "geometry": {"coordinates":[-1.7167240381,52.1705741882],"type":"Point"}
}