{
  "type": "Feature",
  "properties": {
    "addr:full":"163 Dudley Rd Birmingham West Midlands B18 7QY",
    "addr:housenumber":"163",
    "addr:postcode":"b18 7qy",
    "addr:street":"Dudley Rd",
    "iso:country":"GB",
    "sg:address":"163 Dudley Rd",
    "sg:city":"Birmingham",
    "sg:classifiers":[
        {
            "category":"Home & Garden",
            "subcategory":"Home Furnishings",
            "type":"Retail Goods"
        }
    ],
    "sg:phone":"+44 121 454 0161",
    "sg:postcode":"B18 7QY",
    "sg:province":"West Midlands",
    "sg:tags":[
        "wall",
        "wallpaper",
        "covering"
    ],
    "wof:name":"Greens Wallpapers",
    "wof:placetype":"venue"
},
  "geometry": {"coordinates":[-1.9365849495,52.4867591858],"type":"Point"}
}