{
  "type": "Feature",
  "properties": {
    "iso:country":"GB",
    "sg:address":"191 Valley Rd",
    "sg:city":"Ipswich",
    "sg:classifiers":[
        {
            "category":"Shopping",
            "subcategory":"Pets & Pet Supplies",
            "type":"Retail Goods"
        }
    ],
    "sg:postcode":"IP4 3AH",
    "sg:province":"Suffolk",
    "sg:tags":[
        "food"
    ],
    "wof:name":"Kemp,John,",
    "wof:placetype":"venue"
},
  "geometry": {"coordinates":[1.1639289856,52.0714302063],"type":"Point"}
}