{
  "type": "Feature",
  "properties": {
    "addr:full":"Princess Street Folkestone Kent CT19 6QP",
    "addr:postcode":"ct19 6qp",
    "addr:street":"Princess Street",
    "iso:country":"GB",
    "sg:address":"Princess Street",
    "sg:city":"Folkestone",
    "sg:classifiers":[
        {
            "category":"Social Services",
            "subcategory":"Adult Care",
            "type":"Services"
        },
        {
            "category":"Government",
            "subcategory":"Office",
            "type":"Public Place"
        }
    ],
    "sg:phone":"+44 1303 256956",
    "sg:postcode":"CT19 6QP",
    "sg:province":"Kent",
    "sg:tags":[
        "housing",
        "local",
        "sheltered"
    ],
    "wof:name":"Walmsley House Sheltered Housing",
    "wof:placetype":"venue"
},
  "geometry": {"coordinates":[1.18624,51.087536],"type":"Point"}
}