{
  "type": "Feature",
  "properties": {
    "addr:full":"Heather Ho, Heather Gardens Golders Green Greater London NW11 9HS",
    "addr:postcode":"nw11 9hs",
    "addr:street":"Ho Heather Gardens",
    "iso:country":"GB",
    "sg:address":"Heather Ho, Heather Gardens",
    "sg:city":"Golders Green",
    "sg:classifiers":[
        {
            "category":"Professional",
            "subcategory":"Business Services",
            "type":"Services"
        }
    ],
    "sg:phone":"+44 20 8458 8522",
    "sg:postcode":"NW11 9HS",
    "sg:province":"Greater London",
    "sg:tags":[
        "import",
        "export",
        "agent"
    ],
    "wof:name":"Rubella International Ltd",
    "wof:placetype":"venue"
},
  "geometry": {"coordinates":[-0.2099650055,51.5795669556],"type":"Point"}
}