{
  "type": "Feature",
  "properties": {
    "iso:country":"GB",
    "sg:address":"82 Grainger Avenue, West Bridgford",
    "sg:city":"Nottingham",
    "sg:classifiers":[
        {
            "category":"Utilities",
            "subcategory":"Electric",
            "type":"Services"
        }
    ],
    "sg:phone":"+44 115 945 2244",
    "sg:postcode":"NG2 7AS",
    "sg:province":"Nottinghamshire",
    "sg:tags":[
        "electricity"
    ],
    "wof:name":"R.K.E Associates-energy Brokers",
    "wof:placetype":"venue"
},
  "geometry": {"coordinates":[-1.135502,52.912727],"type":"Point"}
}