{
  "type": "Feature",
  "properties": {
    "addr:full":"1 Greenfield Terrace, Newbridge Newport Blaenau Gwent NP11 4QX",
    "addr:housenumber":"1",
    "addr:postcode":"np11 4qx",
    "addr:street":"Greenfield Terrace",
    "iso:country":"GB",
    "sg:address":"1 Greenfield Terrace, Newbridge",
    "sg:city":"Newport",
    "sg:classifiers":[
        {
            "category":"Shopping",
            "subcategory":"Department Store",
            "type":"Retail Goods"
        }
    ],
    "sg:phone":"+44 1495 243205",
    "sg:postcode":"NP11 4QX",
    "sg:province":"Blaenau Gwent",
    "wof:name":"Charles",
    "wof:placetype":"venue"
},
  "geometry": {"coordinates":[-3.1440730095,51.6683044434],"type":"Point"}
}