{
  "type": "Feature",
  "properties": {
    "addr:full":"Chesterton Rd South Shields Tyne and Wear NE34 9HG",
    "addr:postcode":"ne34 9hg",
    "addr:street":"Chesterton Rd",
    "iso:country":"GB",
    "sg:address":"Chesterton Rd",
    "sg:city":"South Shields",
    "sg:classifiers":[
        {
            "category":"Military Area",
            "subcategory":"Air Force Base",
            "type":"Public Place"
        }
    ],
    "sg:postcode":"NE34 9HG",
    "sg:province":"Tyne and Wear",
    "sg:tags":[
        "taxi",
        "hire",
        "private"
    ],
    "wof:name":"Gessels,Ken,",
    "wof:placetype":"venue"
},
  "geometry": {"coordinates":[-1.44528,54.96513],"type":"Point"}
}