{
  "type": "Feature",
  "properties": {
    "iso:country":"GB",
    "sg:address":"47 Elbe Street",
    "sg:city":"Edinburgh",
    "sg:classifiers":[
        {
            "category":"Manufacturing",
            "subcategory":"Textiles",
            "type":"Manufacturing & Wholesale Goods"
        }
    ],
    "sg:postcode":"EH6 7HP",
    "sg:province":"City of Edinburgh",
    "sg:tags":[
        "printer"
    ],
    "wof:name":"Ralph Easton & Son",
    "wof:placetype":"venue"
},
  "geometry": {"coordinates":[-3.163656,55.97488],"type":"Point"}
}