{
  "type": "Feature",
  "properties": {
    "iso:country":"GB",
    "sg:address":"2 Market Hill",
    "sg:city":"Buckingham",
    "sg:classifiers":[
        {
            "category":"Banks & Credit Unions",
            "subcategory":"Bank",
            "type":"Services"
        }
    ],
    "sg:phone":"+44 1280 812118",
    "sg:postcode":"MK18 1JS",
    "sg:province":"Buckinghamshire",
    "sg:tags":[
        "financial",
        "institution"
    ],
    "wof:name":"NatWest",
    "wof:placetype":"venue"
},
  "geometry": {"coordinates":[-0.987317,52.000408],"type":"Point"}
}