{
  "type": "Feature",
  "properties": {
    "iso:country":"GB",
    "sg:address":"129 High Street",
    "sg:city":"Berkhamsted",
    "sg:classifiers":[
        {
            "category":"Professional",
            "subcategory":"Accounting & Tax Preparation",
            "type":"Services"
        }
    ],
    "sg:postcode":"HP4 2DJ",
    "sg:province":"Bedfordshire",
    "sg:tags":[
        "accountant"
    ],
    "wof:name":"F W P Lea & Co.",
    "wof:placetype":"venue"
},
  "geometry": {"coordinates":[-0.562196,51.759438],"type":"Point"}
}