{
  "type": "Feature",
  "properties": {
    "iso:country":"GB",
    "sg:address":"Hampton Loade",
    "sg:city":"Bridgnorth",
    "sg:classifiers":[
        {
            "category":"Recreation",
            "subcategory":"Water Park",
            "type":"Entertainment"
        }
    ],
    "sg:phone":"+44 1746 861560",
    "sg:postcode":"WV16 6BL",
    "sg:province":"Shropshire",
    "sg:tags":[
        "sport"
    ],
    "wof:name":"Chelmarsh Sailing Club",
    "wof:placetype":"venue"
},
  "geometry": {"coordinates":[-2.372609,52.476166],"type":"Point"}
}