{
  "type": "Feature",
  "properties": {
    "iso:country":"GB",
    "sg:address":"33 Laystall St",
    "sg:city":"Clerkenwell",
    "sg:classifiers":[
        {
            "category":"Cafe",
            "type":"Food & Drink"
        }
    ],
    "sg:phone":"+44 20 7833 2318",
    "sg:postcode":"EC1R 4PQ",
    "sg:province":"Greater London",
    "sg:tags":[
        "tea",
        "room"
    ],
    "wof:name":"Nice One",
    "wof:placetype":"venue"
},
  "geometry": {"coordinates":[-0.11231,51.52264],"type":"Point"}
}