{
  "type": "Feature",
  "properties": {
    "addr:full":"59 Southgate Rd Potters Bar Greater London EN6 5EQ",
    "addr:housenumber":"59",
    "addr:postcode":"en6 5eq",
    "addr:street":"Southgate Rd",
    "iso:country":"GB",
    "sg:address":"59 Southgate Rd",
    "sg:city":"Potters Bar",
    "sg:classifiers":[
        {
            "category":"Organizations",
            "subcategory":"Non-profit Organization",
            "type":"Services"
        }
    ],
    "sg:phone":"+44 1707 649355",
    "sg:postcode":"EN6 5EQ",
    "sg:province":"Greater London",
    "sg:tags":[
        "organisation",
        "voluntary",
        "charity"
    ],
    "wof:name":"Whitehouse Project",
    "wof:placetype":"venue"
},
  "geometry": {"coordinates":[-0.1758480072,51.6901702881],"type":"Point"}
}