{
  "type": "Feature",
  "properties": {
    "addr:full":"5 Station Parade Beaconsfield Buckinghamshire HP9 2PG",
    "addr:housenumber":"5",
    "addr:postcode":"hp9 2pg",
    "addr:street":"Station Parade",
    "iso:country":"GB",
    "sg:address":"5 Station Parade",
    "sg:city":"Beaconsfield",
    "sg:classifiers":[
        {
            "category":"Professional",
            "subcategory":"Lawyer & Legal Services",
            "type":"Services"
        }
    ],
    "sg:phone":"+44 1494 672661",
    "sg:postcode":"HP9 2PG",
    "sg:province":"Buckinghamshire",
    "sg:tags":[
        "solicitor"
    ],
    "wof:name":"Baily Gibson",
    "wof:placetype":"venue"
},
  "geometry": {"coordinates":[-0.6470230222,51.611869812],"type":"Point"}
}