{
  "type": "Feature",
  "properties": {
    "addr:full":"Lloyd House, 392 Third Avenue, Trafford Park Manchester Cheshire M17 1JE",
    "addr:housenumber":"392",
    "addr:postcode":"m17 1je",
    "addr:street":"Third Avenue Trafford",
    "iso:country":"GB",
    "sg:address":"Lloyd House, 392 Third Avenue, Trafford Park",
    "sg:city":"Manchester",
    "sg:classifiers":[
        {
            "category":"Professional",
            "subcategory":"Business Services",
            "type":"Services"
        }
    ],
    "sg:phone":"+44 161 877 5750",
    "sg:postcode":"M17 1JE",
    "sg:province":"Cheshire",
    "sg:tags":[
        "accomodation",
        "trade"
    ],
    "wof:name":"Trafford Park Business Forum",
    "wof:placetype":"venue"
},
  "geometry": {"coordinates":[-2.3103120327,53.4655838013],"type":"Point"}
}