{
  "type": "Feature",
  "properties": {
    "addr:full":"Castlehill Farm, Sanday Orkney Orkney Islands KW17 2BA",
    "addr:housenumber":"sanday orkney",
    "addr:postcode":"kw17 2ba",
    "addr:street":"Castlehill",
    "iso:country":"GB",
    "sg:address":"Castlehill Farm, Sanday",
    "sg:city":"Orkney",
    "sg:classifiers":[
        {
            "category":"Farming",
            "subcategory":"Livestock Farm",
            "type":"Manufacturing & Wholesale Goods"
        }
    ],
    "sg:postcode":"KW17 2BA",
    "sg:province":"Orkney Islands",
    "sg:tags":[
        "others"
    ],
    "wof:name":"Ernest M Groundwater",
    "wof:placetype":"venue"
},
  "geometry": {"coordinates":[-2.608138,59.249615],"type":"Point"}
}