{
  "type": "Feature",
  "properties": {
    "iso:country":"GB",
    "sg:address":"Representative Office, 177 Regent Street",
    "sg:city":"London",
    "sg:classifiers":[
        {
            "category":"Banks & Credit Unions",
            "subcategory":"Bank",
            "type":"Services"
        }
    ],
    "sg:postcode":"W1R 8DJ",
    "sg:province":"Greater London",
    "wof:name":"Banka Zagreb D D Privredna",
    "wof:placetype":"venue"
},
  "geometry": {"coordinates":[-0.1399600059,51.5122909546],"type":"Point"}
}