{
  "type": "Feature",
  "properties": {
    "iso:country":"GB",
    "sg:address":"47 Holly Court, St. Modwen Rd, Parkway Ind Est",
    "sg:city":"Plymouth",
    "sg:classifiers":[
        {
            "category":"Manufacturing",
            "subcategory":"Glass & Minerals",
            "type":"Manufacturing & Wholesale Goods"
        }
    ],
    "sg:phone":"+44 1752 663646",
    "sg:postcode":"PL6 8LG",
    "sg:province":"Devon",
    "sg:tags":[
        "fibre",
        "moulding"
    ],
    "wof:name":"Future Frames",
    "wof:placetype":"venue"
},
  "geometry": {"coordinates":[-4.092144,50.396206],"type":"Point"}
}