{
  "type": "Feature",
  "properties": {
    "addr:full":"101 Wellington Hill West Bristol City of Bristol BS9 4SH",
    "addr:housenumber":"101",
    "addr:postcode":"bs9 4sh",
    "addr:street":"Wellington Hill West",
    "iso:country":"GB",
    "sg:address":"101 Wellington Hill West",
    "sg:city":"Bristol",
    "sg:classifiers":[
        {
            "category":"Building & Trades",
            "subcategory":"Plumbing",
            "type":"Services"
        }
    ],
    "sg:postcode":"BS9 4SH",
    "sg:province":"City of Bristol",
    "sg:tags":[
        "heating"
    ],
    "wof:name":"Millais,Ian,",
    "wof:placetype":"venue"
},
  "geometry": {"coordinates":[-2.595995,51.491291],"type":"Point"}
}