{
  "type": "Feature",
  "properties": {
    "addr:full":"Elm Farm, Corse Lawn Gloucester Gloucestershire GL19 4LZ",
    "addr:postcode":"gl19 4lz",
    "iso:country":"GB",
    "sg:address":"Elm Farm, Corse Lawn",
    "sg:city":"Gloucester",
    "sg:classifiers":[
        {
            "category":"Farming",
            "subcategory":"Farm",
            "type":"Manufacturing & Wholesale Goods"
        }
    ],
    "sg:phone":"+44 1452 780245",
    "sg:postcode":"GL19 4LZ",
    "sg:province":"Gloucestershire",
    "sg:tags":[
        "mixed",
        "crop"
    ],
    "wof:name":"W G & S J CLEMENTS",
    "wof:placetype":"venue"
},
  "geometry": {"coordinates":[-2.2466390133,51.9746704102],"type":"Point"}
}