{
  "type": "Feature",
  "properties": {
    "addr:full":"66 Brockham Green, Brockham Betchworth Surrey RH3 7JR",
    "addr:housenumber":"66",
    "addr:postcode":"rh3 7jr",
    "addr:street":"Brockham Green;Betchworth",
    "iso:country":"GB",
    "sg:address":"66 Brockham Green, Brockham",
    "sg:city":"Betchworth",
    "sg:classifiers":[
        {
            "category":"Home & Garden",
            "subcategory":"Home Furnishings",
            "type":"Retail Goods"
        }
    ],
    "sg:postcode":"RH3 7JR",
    "sg:province":"Surrey",
    "sg:tags":[
        "blind",
        "curtain",
        "fitting"
    ],
    "wof:name":"Vivien Creswell",
    "wof:placetype":"venue"
},
  "geometry": {"coordinates":[-0.288969,51.236435],"type":"Point"}
}