{
  "type": "Feature",
  "properties": {
    "iso:country":"GB",
    "sg:address":"Meridian Road",
    "sg:city":"Bristol",
    "sg:classifiers":[
        {
            "category":"Retail",
            "subcategory":"Auto Repair",
            "type":"Services"
        }
    ],
    "sg:phone":"+44 117 942 4800",
    "sg:postcode":"BS6 6EG",
    "sg:province":"City of Bristol",
    "sg:tags":[
        "modification",
        "garage"
    ],
    "wof:name":"Redland Grove Garage",
    "wof:placetype":"venue"
},
  "geometry": {"coordinates":[-2.602079,51.467159],"type":"Point"}
}