{
  "type": "Feature",
  "properties": {
    "iso:country":"GB",
    "sg:address":"48-50 High Street, Rolvenden",
    "sg:city":"Cranbrook",
    "sg:classifiers":[
        {
            "category":"Government",
            "subcategory":"Post Office",
            "type":"Public Place"
        },
        {
            "category":"Food & Beverages",
            "subcategory":"Groceries & Convenience Stores",
            "type":"Retail Goods"
        }
    ],
    "sg:phone":"+44 1580 241245",
    "sg:postcode":"TN17 4LN",
    "sg:province":"Kent",
    "wof:name":"Rolvenden Post Office",
    "wof:placetype":"venue"
},
  "geometry": {"coordinates":[0.629692,51.052773],"type":"Point"}
}