{
  "type": "Feature",
  "properties": {
    "iso:country":"GB",
    "sg:address":"Southview, Lound Road, Toft",
    "sg:city":"Bourne",
    "sg:classifiers":[
        {
            "category":"Manufacturing",
            "subcategory":"Tools & Machinery",
            "type":"Manufacturing & Wholesale Goods"
        }
    ],
    "sg:postcode":"PE10 0JU",
    "sg:province":"Lincolnshire",
    "sg:tags":[
        "society",
        "friendly"
    ],
    "wof:name":"D R Baker & Co",
    "wof:placetype":"venue"
},
  "geometry": {"coordinates":[-0.4165799916,52.7507858276],"type":"Point"}
}