{
  "type": "Feature",
  "properties": {
    "addr:full":"82 Leafenden Avenue Burntwood Staffordshire WS7 8UU",
    "addr:housenumber":"82",
    "addr:postcode":"ws7 8uu",
    "addr:street":"Leafenden Avenue",
    "iso:country":"GB",
    "sg:address":"82 Leafenden Avenue",
    "sg:city":"Burntwood",
    "sg:classifiers":[
        {
            "category":"Building & Trades",
            "subcategory":"Cleaning & Sanitation",
            "type":"Services"
        }
    ],
    "sg:postcode":"WS7 8UU",
    "sg:province":"Staffordshire",
    "sg:tags":[
        "cleaner",
        "window"
    ],
    "wof:name":"Wellington Window Cleaners",
    "wof:placetype":"venue"
},
  "geometry": {"coordinates":[-1.921822,52.674],"type":"Point"}
}