{
  "type": "Feature",
  "properties": {
    "addr:full":"Livingston Ho, Watling Av, Burnt Oak Edgware Greater London HA8 0LD",
    "addr:postcode":"ha8 0ld",
    "addr:street":"Watling Av Burnt Oak",
    "iso:country":"GB",
    "sg:address":"Livingston Ho, Watling Av, Burnt Oak",
    "sg:city":"Edgware",
    "sg:classifiers":[
        {
            "category":"Professional",
            "subcategory":"Lawyer & Legal Services",
            "type":"Services"
        }
    ],
    "sg:phone":"+44 20 8906 8664",
    "sg:postcode":"HA8 0LD",
    "sg:province":"Greater London",
    "sg:tags":[
        "advice",
        "counselling"
    ],
    "wof:name":"Beulah Counselling Service",
    "wof:placetype":"venue"
},
  "geometry": {"coordinates":[-0.2648800015,51.6021614075],"type":"Point"}
}