{
  "type": "Feature",
  "properties": {
    "addr:full":"33 Coombe Lane Bristol City of Bristol BS9 2BL",
    "addr:housenumber":"33",
    "addr:postcode":"bs9 2bl",
    "addr:street":"Coombe Lane",
    "iso:country":"GB",
    "sg:address":"33 Coombe Lane",
    "sg:city":"Bristol",
    "sg:classifiers":[
        {
            "category":"Professional",
            "subcategory":"Business Services",
            "type":"Services"
        }
    ],
    "sg:phone":"+44 117 983 9085",
    "sg:postcode":"BS9 2BL",
    "sg:province":"City of Bristol",
    "sg:tags":[
        "import",
        "export",
        "agent"
    ],
    "wof:name":"Iskra Enterprises Ltd.",
    "wof:placetype":"venue"
},
  "geometry": {"coordinates":[-2.632124,51.48724],"type":"Point"}
}