{
  "type": "Feature",
  "properties": {
    "iso:country":"GB",
    "sg:address":"17 Hartley Way",
    "sg:city":"Purley",
    "sg:classifiers":[
        {
            "category":"Organizations",
            "subcategory":"Membership Organization",
            "type":"Services"
        }
    ],
    "sg:postcode":"CR8 4EJ",
    "sg:province":"Surrey",
    "sg:tags":[
        "club"
    ],
    "wof:name":"Reedham Park Sports Club Ltd.",
    "wof:placetype":"venue"
},
  "geometry": {"coordinates":[-0.1262450069,51.3225212097],"type":"Point"}
}