{
  "type": "Feature",
  "properties": {
    "addr:full":"118 Bankhead Road Aberdeen Aberdeen City AB21 9EA",
    "addr:housenumber":"118",
    "addr:postcode":"ab21 9ea",
    "addr:street":"Bankhead Road",
    "iso:country":"GB",
    "sg:address":"118 Bankhead Road",
    "sg:city":"Aberdeen",
    "sg:classifiers":[
        {
            "category":"Manufacturing",
            "subcategory":"Chemicals & Compounds",
            "type":"Manufacturing & Wholesale Goods"
        }
    ],
    "sg:phone":"+44 1224 712072",
    "sg:postcode":"AB21 9EA",
    "sg:province":"Aberdeen City",
    "wof:name":"Hamish F Buchanan",
    "wof:placetype":"venue"
},
  "geometry": {"coordinates":[-2.1859500408,57.1802902222],"type":"Point"}
}