{
  "type": "Feature",
  "properties": {
    "addr:full":"11-11a Finkin Street Grantham Lincolnshire NG31 6QZ",
    "addr:housenumber":"11-11a",
    "addr:postcode":"ng31 6qz",
    "addr:street":"Finkin Street",
    "iso:country":"GB",
    "sg:address":"11-11a Finkin Street",
    "sg:city":"Grantham",
    "sg:classifiers":[
        {
            "category":"Shopping",
            "subcategory":"Stationery & Office Supplies",
            "type":"Retail Goods"
        }
    ],
    "sg:phone":"+44 1476 590511",
    "sg:postcode":"NG31 6QZ",
    "sg:province":"Lincolnshire",
    "wof:name":"Stationery Management Services Ltd.",
    "wof:placetype":"venue"
},
  "geometry": {"coordinates":[-0.641252,52.912468],"type":"Point"}
}