{
  "type": "Feature",
  "properties": {
    "iso:country":"GB",
    "sg:address":"Elland Bridge",
    "sg:city":"Elland",
    "sg:classifiers":[
        {
            "category":"Professional",
            "type":"Services"
        }
    ],
    "sg:phone":"+44 1422 372295",
    "sg:postcode":"HX5 0SQ",
    "sg:province":"West Yorkshire",
    "sg:tags":[
        "shopfitters"
    ],
    "wof:name":"D & W Contracts Ltd",
    "wof:placetype":"venue"
},
  "geometry": {"coordinates":[-1.840578,53.688541],"type":"Point"}
}