{
  "type": "Feature",
  "properties": {
    "iso:country":"GB",
    "sg:address":"41 Ilges Lane, Cholsey",
    "sg:city":"Wallingford",
    "sg:classifiers":[
        {
            "category":"Professional",
            "subcategory":"Management & Consulting",
            "type":"Services"
        }
    ],
    "sg:phone":"+44 1491 652265",
    "sg:postcode":"OX10 9NX",
    "sg:province":"Oxfordshire",
    "sg:tags":[
        "consultant",
        "training"
    ],
    "wof:name":"Training & Development Associates",
    "wof:placetype":"venue"
},
  "geometry": {"coordinates":[-1.150503,51.575066],"type":"Point"}
}