{
  "type": "Feature",
  "properties": {
    "addr:full":"25 Merryweather Court, Tremlett Grove Archway Greater London N19 5LA",
    "addr:housenumber":"25",
    "addr:postcode":"n19 5la",
    "addr:street":"Merryweather Court Tremlett Grove",
    "iso:country":"GB",
    "sg:address":"25 Merryweather Court, Tremlett Grove",
    "sg:city":"Archway",
    "sg:classifiers":[
        {
            "category":"Professional",
            "subcategory":"Employment Agencies",
            "type":"Services"
        }
    ],
    "sg:phone":"+44 20 7263 1406",
    "sg:postcode":"N19 5LA",
    "sg:province":"Greater London",
    "sg:tags":[
        "asbestos",
        "mnfrs",
        "removal"
    ],
    "wof:name":"Asbestos Independent Advice",
    "wof:placetype":"venue"
},
  "geometry": {"coordinates":[-0.1381600052,51.5618515015],"type":"Point"}
}