{
  "type": "Feature",
  "properties": {
    "addr:full":"35 Coombe Street Lyme Regis Devon DT7 3PY",
    "addr:housenumber":"35",
    "addr:postcode":"dt7 3py",
    "addr:street":"Coombe Street",
    "iso:country":"GB",
    "sg:address":"35 Coombe Street",
    "sg:city":"Lyme Regis",
    "sg:classifiers":[
        {
            "category":"Food & Beverages",
            "subcategory":"Meat & Fish",
            "type":"Retail Goods"
        }
    ],
    "sg:phone":"+44 1297 443140",
    "sg:postcode":"DT7 3PY",
    "sg:province":"Devon",
    "sg:tags":[
        "butcher"
    ],
    "wof:name":"P & E A Pattimore",
    "wof:placetype":"venue"
},
  "geometry": {"coordinates":[-2.933134079,50.7257156372],"type":"Point"}
}