{
  "type": "Feature",
  "properties": {
    "addr:full":"Unit 4 Gatefield Wks, Whitelands Rd Ashton-under-lyne Greater Manchester OL6 6UG",
    "addr:housenumber":"unit 4",
    "addr:postcode":"ol6 6ug",
    "addr:street":"Gatefield Wks Whitelands Rd",
    "iso:country":"GB",
    "sg:address":"Unit 4 Gatefield Wks, Whitelands Rd",
    "sg:city":"Ashton-under-lyne",
    "sg:classifiers":[
        {
            "category":"Retail",
            "subcategory":"Auto Repair",
            "type":"Services"
        }
    ],
    "sg:postcode":"OL6 6UG",
    "sg:province":"Greater Manchester",
    "sg:tags":[
        "bodybuilder",
        "repairer"
    ],
    "wof:name":"Aim Vehicle Painters Limited",
    "wof:placetype":"venue"
},
  "geometry": {"coordinates":[-2.088242,53.489239],"type":"Point"}
}