{
  "type": "Feature",
  "properties": {
    "iso:country":"GB",
    "sg:address":"256-260 Morrison Street",
    "sg:city":"Edinburgh",
    "sg:classifiers":[
        {
            "category":"Bars & Pubs",
            "type":"Food & Drink"
        }
    ],
    "sg:phone":"+44 131 228 1949",
    "sg:postcode":"EH3 8DT",
    "sg:province":"City of Edinburgh",
    "sg:tags":[
        "pubs",
        "inn"
    ],
    "wof:name":"The Spiders Web",
    "wof:placetype":"venue"
},
  "geometry": {"coordinates":[-3.215099,55.946316],"type":"Point"}
}