{
  "type": "Feature",
  "properties": {
    "iso:country":"GB",
    "sg:address":"Unit 6, Protea Way, Pixmore Avenue",
    "sg:city":"Letchworth",
    "sg:classifiers":[
        {
            "category":"Home & Garden",
            "subcategory":"Hardware",
            "type":"Retail Goods"
        }
    ],
    "sg:phone":"+44 1462 481115",
    "sg:postcode":"SG6 1JT",
    "sg:province":"Hertfordshire",
    "sg:tags":[
        "equipment",
        "welding"
    ],
    "wof:name":"Premier Welding Range",
    "wof:placetype":"venue"
},
  "geometry": {"coordinates":[-0.215253,51.981079],"type":"Point"}
}