{
  "type": "Feature",
  "properties": {
    "addr:full":"70 Uppermoor Pudsey West Yorkshire LS28 7EX",
    "addr:housenumber":"70",
    "addr:postcode":"ls28 7ex",
    "addr:street":"Uppermoor Pudsey West",
    "iso:country":"GB",
    "sg:address":"70 Uppermoor",
    "sg:city":"Pudsey",
    "sg:classifiers":[
        {
            "category":"Bars & Pubs",
            "type":"Food & Drink"
        }
    ],
    "sg:phone":"+44 113 256 4018",
    "sg:postcode":"LS28 7EX",
    "sg:province":"West Yorkshire",
    "sg:tags":[
        "pubs",
        "house",
        "inn",
        "public",
        "activity"
    ],
    "wof:name":"Marsh Inn",
    "wof:placetype":"venue"
},
  "geometry": {"coordinates":[-1.6783030033,53.794719696],"type":"Point"}
}