{
  "type": "Feature",
  "properties": {
    "iso:country":"GB",
    "sg:address":"3 High Street",
    "sg:city":"Shefford",
    "sg:classifiers":[
        {
            "category":"Real Estate",
            "subcategory":"Real Estate Agent",
            "type":"Services"
        }
    ],
    "sg:phone":"+44 1462 629000",
    "sg:postcode":"SG17 5DD",
    "sg:province":"Bedfordshire",
    "wof:name":"Stephens",
    "wof:placetype":"venue"
},
  "geometry": {"coordinates":[-0.3340489864,52.0385093689],"type":"Point"}
}