{
  "type": "Feature",
  "properties": {
    "iso:country":"GB",
    "sg:address":"Helpline, 27 School Rd",
    "sg:city":"Bristol",
    "sg:classifiers":[
        {
            "category":"Organizations",
            "subcategory":"Non-profit Organization",
            "type":"Services"
        }
    ],
    "sg:phone":"+44 117 977 2225",
    "sg:postcode":"BS4 3BW",
    "sg:province":"City of Bristol",
    "sg:tags":[
        "organisation",
        "voluntary",
        "charity"
    ],
    "wof:name":"Supportive Parents For Special Children",
    "wof:placetype":"venue"
},
  "geometry": {"coordinates":[-2.57156,51.439911],"type":"Point"}
}