{
  "type": "Feature",
  "properties": {
    "addr:full":"Maybury Hill Woking Surrey GU22 8AB",
    "addr:postcode":"gu22 8ab",
    "addr:street":"Maybury Hill",
    "iso:country":"GB",
    "sg:address":"Maybury Hill",
    "sg:city":"Woking",
    "sg:classifiers":[
        {
            "category":"Bars & Pubs",
            "type":"Food & Drink"
        }
    ],
    "sg:phone":"+44 1483 760613",
    "sg:postcode":"GU22 8AB",
    "sg:province":"Surrey",
    "sg:tags":[
        "pubs",
        "inn"
    ],
    "wof:name":"Punch Retail Ltd",
    "wof:placetype":"venue"
},
  "geometry": {"coordinates":[-0.541734,51.324081],"type":"Point"}
}