{
  "type": "Feature",
  "properties": {
    "addr:full":"Southampton University, Highfield Southampton Hampshire SO17 1BJ",
    "addr:postcode":"so17 1bj",
    "iso:country":"GB",
    "sg:address":"Southampton University, Highfield",
    "sg:city":"Southampton",
    "sg:classifiers":[
        {
            "category":"Government",
            "subcategory":"Office",
            "type":"Public Place"
        }
    ],
    "sg:phone":"+44 23 8090 8870",
    "sg:postcode":"SO17 1BJ",
    "sg:province":"Hampshire",
    "sg:tags":[
        "education",
        "agency",
        "authority"
    ],
    "wof:name":"Southern Science Technology Forum",
    "wof:placetype":"venue"
},
  "geometry": {"coordinates":[-1.39601,50.934078],"type":"Point"}
}