{
  "type": "Feature",
  "properties": {
    "iso:country":"GB",
    "sg:address":"142a Brent Street",
    "sg:city":"London",
    "sg:classifiers":[
        {
            "category":"Fast Food",
            "type":"Food & Drink"
        }
    ],
    "sg:postcode":"NW4 2DR",
    "sg:province":"Greater London",
    "sg:tags":[
        "away",
        "take"
    ],
    "wof:name":"Babur Empire Ltd",
    "wof:placetype":"venue"
},
  "geometry": {"coordinates":[-0.220747,51.587498],"type":"Point"}
}