{
  "type": "Feature",
  "properties": {
    "addr:full":"Ashburnham House, 36 Ashburnham Rd Crawley Surrey RH10 6QZ",
    "addr:housenumber":"36",
    "addr:postcode":"rh10 6qz",
    "addr:street":"Ashburnham Rd",
    "iso:country":"GB",
    "sg:address":"Ashburnham House, 36 Ashburnham Rd",
    "sg:city":"Crawley",
    "sg:classifiers":[
        {
            "category":"Professional",
            "subcategory":"Computer Services",
            "type":"Services"
        }
    ],
    "sg:phone":"+44 1293 450070",
    "sg:postcode":"RH10 6QZ",
    "sg:province":"Surrey",
    "sg:tags":[
        "system",
        "software"
    ],
    "wof:name":"Black Box Computer Logistics",
    "wof:placetype":"venue"
},
  "geometry": {"coordinates":[-0.166279003,51.1067962646],"type":"Point"}
}