{
  "type": "Feature",
  "properties": {
    "iso:country":"GB",
    "sg:address":"19 Ashgrove Road",
    "sg:city":"Kilwinning",
    "sg:classifiers":[
        {
            "category":"Retail",
            "subcategory":"Auto Repair",
            "type":"Services"
        }
    ],
    "sg:phone":"+44 1294 550300",
    "sg:postcode":"KA13 6NX",
    "sg:province":"East Ayrshire",
    "sg:tags":[
        "modification",
        "garage"
    ],
    "wof:name":"Ian Porter",
    "wof:placetype":"venue"
},
  "geometry": {"coordinates":[-4.712249,55.656288],"type":"Point"}
}