{
  "type": "Feature",
  "properties": {
    "addr:full":"Watlington Industrial Estate, Cuxham Road Watlington Oxfordshire OX49 5NA",
    "addr:postcode":"ox49 5na",
    "addr:street":"Estate Cuxham Road",
    "iso:country":"GB",
    "sg:address":"Watlington Industrial Estate, Cuxham Road",
    "sg:city":"Watlington",
    "sg:classifiers":[
        {
            "category":"Freight",
            "type":"Transportation"
        }
    ],
    "sg:phone":"+44 1491 613175",
    "sg:postcode":"OX49 5NA",
    "sg:province":"Oxfordshire",
    "sg:tags":[
        "haulage",
        "road"
    ],
    "wof:name":"Verran Freight Ltd.",
    "wof:placetype":"venue"
},
  "geometry": {"coordinates":[-1.005681,51.644085],"type":"Point"}
}