{
  "type": "Feature",
  "properties": {
    "addr:full":"6 Cherry Hill St Albans Hertfordshire AL2 3BA",
    "addr:housenumber":"6",
    "addr:postcode":"al2 3ba",
    "addr:street":"Cherry Hill",
    "iso:country":"GB",
    "sg:address":"6 Cherry Hill",
    "sg:city":"St Albans",
    "sg:classifiers":[
        {
            "category":"Building & Trades",
            "subcategory":"Construction",
            "type":"Services"
        }
    ],
    "sg:postcode":"AL2 3BA",
    "sg:province":"Hertfordshire",
    "sg:tags":[
        "roofing"
    ],
    "wof:name":"Roofscan",
    "wof:placetype":"venue"
},
  "geometry": {"coordinates":[-0.362082988,51.7315368652],"type":"Point"}
}