{
  "type": "Feature",
  "properties": {
    "iso:country":"GB",
    "sg:address":"Lower East Street",
    "sg:city":"Middlesbrough",
    "sg:classifiers":[
        {
            "category":"Manufacturing",
            "subcategory":"Metals",
            "type":"Manufacturing & Wholesale Goods"
        }
    ],
    "sg:phone":"+44 1642 226304",
    "sg:postcode":"TS2 1PF",
    "sg:province":"Durham",
    "sg:tags":[
        "work",
        "sheet"
    ],
    "wof:name":"Granges Metalock (Casting Repairers)",
    "wof:placetype":"venue"
},
  "geometry": {"coordinates":[-1.2310739756,54.5810852051],"type":"Point"}
}