{
  "type": "Feature",
  "properties": {
    "iso:country":"GB",
    "sg:address":"High Street, New Galloway",
    "sg:city":"Castle Douglas",
    "sg:classifiers":[
        {
            "category":"Travel",
            "subcategory":"Hotels & Motels",
            "type":"Entertainment"
        }
    ],
    "sg:phone":"+44 1644 420327",
    "sg:postcode":"DG7 3RN",
    "sg:province":"Dumfries and Galloway",
    "wof:name":"Leamington Hotel",
    "wof:placetype":"venue"
},
  "geometry": {"coordinates":[-4.140919,55.072273],"type":"Point"}
}