{
  "type": "Feature",
  "properties": {
    "addr:full":"25 Canonbury Lane London Greater London N1 2AS",
    "addr:housenumber":"25",
    "addr:postcode":"n1 2as",
    "addr:street":"Canonbury Lane",
    "iso:country":"GB",
    "sg:address":"25 Canonbury Lane",
    "sg:city":"London",
    "sg:classifiers":[
        {
            "category":"Bars & Pubs",
            "type":"Food & Drink"
        }
    ],
    "sg:phone":"+44 20 7226 4095",
    "sg:postcode":"N1 2AS",
    "sg:province":"Greater London",
    "sg:tags":[
        "pubs",
        "inn"
    ],
    "wof:name":"The Four Sisters",
    "wof:placetype":"venue"
},
  "geometry": {"coordinates":[-0.1027700007,51.5431442261],"type":"Point"}
}