{
  "type": "Feature",
  "properties": {
    "addr:full":"St Andrews House, 62 Bridge Street Manchester Greater Manchester M3 3BW",
    "addr:housenumber":"62",
    "addr:postcode":"m3 3bw",
    "addr:street":"Bridge Street",
    "iso:country":"GB",
    "sg:address":"St Andrews House, 62 Bridge Street",
    "sg:city":"Manchester",
    "sg:classifiers":[
        {
            "category":"Real Estate",
            "subcategory":"Architect",
            "type":"Services"
        }
    ],
    "sg:phone":"+44 161 832 2393",
    "sg:postcode":"M3 3BW",
    "sg:province":"Greater Manchester",
    "wof:name":"The P D A Partnership Ltd.",
    "wof:placetype":"venue"
},
  "geometry": {"coordinates":[-2.250109,53.479568],"type":"Point"}
}