{
  "type": "Feature",
  "properties": {
    "addr:full":"3 Cross Street Willenhall West Midlands WV13 1PG",
    "addr:housenumber":"3",
    "addr:postcode":"wv13 1pg",
    "addr:street":"Cross Street",
    "iso:country":"GB",
    "sg:address":"3 Cross Street",
    "sg:city":"Willenhall",
    "sg:classifiers":[
        {
            "category":"Shopping",
            "subcategory":"Hobbies, Toys, & Games",
            "type":"Retail Goods"
        }
    ],
    "sg:phone":"+44 870 220 0505",
    "sg:postcode":"WV13 1PG",
    "sg:province":"West Midlands",
    "sg:tags":[
        "gunsmith"
    ],
    "wof:name":"W H B Supplies",
    "wof:placetype":"venue"
},
  "geometry": {"coordinates":[-2.054229,52.583771],"type":"Point"}
}