{
  "type": "Feature",
  "properties": {
    "addr:full":"Vicarage Hill Keswick Cumbria CA12 5QE",
    "addr:postcode":"ca12 5qe",
    "addr:street":"Vicarage Hill",
    "iso:country":"GB",
    "sg:address":"Vicarage Hill",
    "sg:city":"Keswick",
    "sg:classifiers":[
        {
            "category":"Education",
            "subcategory":"University",
            "type":"Public Place"
        },
        {
            "category":"Government",
            "subcategory":"Office",
            "type":"Public Place"
        }
    ],
    "sg:phone":"+44 17687 73565",
    "sg:postcode":"CA12 5QE",
    "sg:province":"Cumbria",
    "sg:tags":[
        "local",
        "adult"
    ],
    "wof:name":"Laithwaithe Adult Education Centre",
    "wof:placetype":"venue"
},
  "geometry": {"coordinates":[-3.1431939602,54.6087265015],"type":"Point"}
}