{
  "type": "Feature",
  "properties": {
    "iso:country":"GB",
    "sg:address":"Pool House, Horizon West, Hambridge Road",
    "sg:city":"Newbury",
    "sg:classifiers":[
        {
            "category":"Banks & Credit Unions",
            "subcategory":"Financial Services",
            "type":"Services"
        }
    ],
    "sg:phone":"+44 1565 654662",
    "sg:postcode":"RG14 5XF",
    "sg:province":"Berkshire",
    "sg:tags":[
        "consultant"
    ],
    "wof:name":"De La Rue Systems",
    "wof:placetype":"venue"
},
  "geometry": {"coordinates":[-1.325872,51.405872],"type":"Point"}
}