{
  "type": "Feature",
  "properties": {
    "iso:country":"GB",
    "sg:address":"Burnley Rd, Brierfield",
    "sg:city":"Nelson",
    "sg:classifiers":[
        {
            "category":"Autos & Motor Vehicles",
            "subcategory":"Fuel & Gas Station",
            "type":"Retail Goods"
        }
    ],
    "sg:phone":"+44 1282 602762",
    "sg:postcode":"BB9 5HY",
    "sg:province":"Lancashire",
    "sg:tags":[
        "petrol",
        "filling"
    ],
    "wof:name":"Briar Service Station",
    "wof:placetype":"venue"
},
  "geometry": {"coordinates":[-2.234284,53.823605],"type":"Point"}
}