{
  "type": "Feature",
  "properties": {
    "iso:country":"GB",
    "sg:address":"Courthouse, Wellington Square",
    "sg:city":"Ayr",
    "sg:classifiers":[
        {
            "category":"Government",
            "subcategory":"Court House",
            "type":"Public Place"
        }
    ],
    "sg:phone":"+44 1292 268474",
    "sg:postcode":"KA7 1DR",
    "sg:province":"South Ayrshire",
    "wof:name":"Sheriff Clerk",
    "wof:placetype":"venue"
},
  "geometry": {"coordinates":[-4.636369,55.460976],"type":"Point"}
}