{
  "type": "Feature",
  "properties": {
    "addr:full":"Awsland Farm, Peters Marland Torrington Devon EX38 8QW",
    "addr:housenumber":"peters",
    "addr:postcode":"ex38 8qw",
    "iso:country":"GB",
    "sg:address":"Awsland Farm, Peters Marland",
    "sg:city":"Torrington",
    "sg:classifiers":[
        {
            "category":"Farming",
            "subcategory":"Dairy Farm",
            "type":"Manufacturing & Wholesale Goods"
        }
    ],
    "sg:phone":"+44 1409 281246",
    "sg:postcode":"EX38 8QW",
    "sg:province":"Devon",
    "sg:tags":[
        "farmer"
    ],
    "wof:name":"M S Ashton & Sons",
    "wof:placetype":"venue"
},
  "geometry": {"coordinates":[-4.1422548294,50.9531517029],"type":"Point"}
}