{
  "type": "Feature",
  "properties": {
    "addr:full":"37 Wheelock Street Middlewich Cheshire CW10 9AB",
    "addr:housenumber":"37",
    "addr:postcode":"cw10 9ab",
    "addr:street":"Wheelock Street",
    "iso:country":"GB",
    "sg:address":"37 Wheelock Street",
    "sg:city":"Middlewich",
    "sg:classifiers":[
        {
            "category":"Food & Beverages",
            "subcategory":"Liquor & Beverages",
            "type":"Retail Goods"
        }
    ],
    "sg:phone":"+44 1606 832222",
    "sg:postcode":"CW10 9AB",
    "sg:province":"Cheshire",
    "sg:tags":[
        "beer",
        "spirit",
        "wines"
    ],
    "wof:name":"Bargain Booze Ltd.",
    "wof:placetype":"venue"
},
  "geometry": {"coordinates":[-2.44732,53.192974],"type":"Point"}
}