{
  "type": "Feature",
  "properties": {
    "iso:country":"GB",
    "sg:address":"Unit 3, Stakehill Ind Est, Middleton",
    "sg:city":"Manchester",
    "sg:classifiers":[
        {
            "category":"Home & Garden",
            "subcategory":"Household Appliances",
            "type":"Retail Goods"
        }
    ],
    "sg:phone":"+44 161 654 7713",
    "sg:postcode":"M24 2RW",
    "sg:province":"Greater Manchester",
    "sg:tags":[
        "refrigeration",
        "air conditioning"
    ],
    "wof:name":"Pullman Fleet Services",
    "wof:placetype":"venue"
},
  "geometry": {"coordinates":[-2.191324,53.5494],"type":"Point"}
}