{
  "type": "Feature",
  "properties": {
    "addr:full":"35 Oaktree Crescent, Bradley Stoke Bristol Gloucestershire BS32 9AB",
    "addr:housenumber":"35",
    "addr:postcode":"bs32 9ab",
    "addr:street":"Oaktree Crescent",
    "iso:country":"GB",
    "sg:address":"35 Oaktree Crescent, Bradley Stoke",
    "sg:city":"Bristol",
    "sg:classifiers":[
        {
            "category":"Building & Trades",
            "subcategory":"Construction",
            "type":"Services"
        }
    ],
    "sg:phone":"+44 1454 619545",
    "sg:postcode":"BS32 9AB",
    "sg:province":"Gloucestershire",
    "sg:tags":[
        "contractor"
    ],
    "wof:name":"Newgate Construction",
    "wof:placetype":"venue"
},
  "geometry": {"coordinates":[-2.56126,51.54248],"type":"Point"}
}