{
  "type": "Feature",
  "properties": {
    "addr:full":"White Horse Caravan Site, Bell Farm Lane, Minster On Sea Sheerness Kent ME12 4JA",
    "addr:postcode":"me12 4ja",
    "addr:street":"Farm Lane",
    "iso:country":"GB",
    "sg:address":"White Horse Caravan Site, Bell Farm Lane, Minster On Sea",
    "sg:city":"Sheerness",
    "sg:classifiers":[
        {
            "category":"Utilities",
            "subcategory":"Natural Gas",
            "type":"Services"
        }
    ],
    "sg:phone":"+44 1795 874433",
    "sg:postcode":"ME12 4JA",
    "sg:province":"Kent",
    "sg:tags":[
        "supplier"
    ],
    "wof:name":"A1 Industrial Gases",
    "wof:placetype":"venue"
},
  "geometry": {"coordinates":[0.7646650076,51.4388504028],"type":"Point"}
}