{
  "type": "Feature",
  "properties": {
    "addr:full":"Great Western Road, Martock Trading Estate Martock Somerset TA12 6HB",
    "addr:postcode":"ta12 6hb",
    "addr:street":"Great Western Road;Trading Estate",
    "iso:country":"GB",
    "sg:address":"Great Western Road, Martock Trading Estate",
    "sg:city":"Martock",
    "sg:classifiers":[
        {
            "category":"Autos & Motor Vehicles",
            "subcategory":"Automobile Sales",
            "type":"Retail Goods"
        }
    ],
    "sg:phone":"+44 1935 823556",
    "sg:postcode":"TA12 6HB",
    "sg:province":"Somerset",
    "sg:tags":[
        "commercial"
    ],
    "wof:name":"D T Commercial (Trucks) Ltd.",
    "wof:placetype":"venue"
},
  "geometry": {"coordinates":[-2.770669,50.967247],"type":"Point"}
}