{
  "type": "Feature",
  "properties": {
    "addr:full":"31 Church Street Godalming Surrey GU7 1EL",
    "addr:housenumber":"31",
    "addr:postcode":"gu7 1el",
    "addr:street":"Church Street",
    "iso:country":"GB",
    "sg:address":"31 Church Street",
    "sg:city":"Godalming",
    "sg:classifiers":[
        {
            "category":"Personal",
            "subcategory":"Beauty Salon",
            "type":"Services"
        },
        {
            "category":"Professional",
            "subcategory":"Management & Consulting",
            "type":"Services"
        }
    ],
    "sg:postcode":"GU7 1EL",
    "sg:province":"Surrey",
    "sg:tags":[
        "unisex",
        "consultant",
        "specialist",
        "hairdresser"
    ],
    "wof:name":"New Image Health & Beauty",
    "wof:placetype":"venue"
},
  "geometry": {"coordinates":[-0.616173,51.186657],"type":"Point"}
}