{
  "type": "Feature",
  "properties": {
    "iso:country":"GB",
    "sg:address":"Stanghow Rd",
    "sg:city":"Saltburn By The Sea",
    "sg:classifiers":[
        {
            "category":"Sports & Exercise",
            "subcategory":"Stables",
            "type":"Entertainment"
        }
    ],
    "sg:phone":"+44 1287 650303",
    "sg:postcode":"TS12 2AB",
    "sg:province":"North Yorkshire",
    "sg:tags":[
        "education",
        "equestrian"
    ],
    "wof:name":"Cleveland Riding Centre",
    "wof:placetype":"venue"
},
  "geometry": {"coordinates":[-0.972602,54.558903],"type":"Point"}
}