{
  "type": "Feature",
  "properties": {
    "iso:country":"GB",
    "sg:address":"4 Grovehurst Rd",
    "sg:city":"Sittingbourne",
    "sg:classifiers":[
        {
            "category":"Home & Garden",
            "subcategory":"Household Appliances",
            "type":"Retail Goods"
        }
    ],
    "sg:phone":"+44 1795 421538",
    "sg:postcode":"ME10 2RA",
    "sg:province":"Kent",
    "sg:tags":[
        "refrigeration",
        "air conditioning"
    ],
    "wof:name":"Carlson Cooling",
    "wof:placetype":"venue"
},
  "geometry": {"coordinates":[0.7386109829,51.3558769226],"type":"Point"}
}