{
  "type": "Feature",
  "properties": {
    "addr:full":"6 Station House, Manor House Lane, Datchet Slough Berkshire SL3 9EB",
    "addr:housenumber":"6",
    "addr:postcode":"sl3 9eb",
    "addr:street":"Manor House Lane",
    "iso:country":"GB",
    "sg:address":"6 Station House, Manor House Lane, Datchet",
    "sg:city":"Slough",
    "sg:classifiers":[
        {
            "category":"Building & Trades",
            "subcategory":"Construction",
            "type":"Services"
        }
    ],
    "sg:phone":"+44 1753 582564",
    "sg:postcode":"SL3 9EB",
    "sg:province":"Berkshire",
    "sg:tags":[
        "concrete"
    ],
    "wof:name":"Walker Brench Formwork Ltd.",
    "wof:placetype":"venue"
},
  "geometry": {"coordinates":[-0.5804880261,51.4840736389],"type":"Point"}
}