{
  "type": "Feature",
  "properties": {
    "addr:full":"124 Quarry Street Hamilton South Lanarkshire ML3 7AD",
    "addr:housenumber":"124",
    "addr:postcode":"ml3 7ad",
    "addr:street":"Quarry Street",
    "iso:country":"GB",
    "sg:address":"124 Quarry Street",
    "sg:city":"Hamilton",
    "sg:classifiers":[
        {
            "category":"Shopping",
            "subcategory":"Clothing, Apparel, & Fashions",
            "type":"Retail Goods"
        },
        {
            "category":"Shopping",
            "subcategory":"Baby Store",
            "type":"Retail Goods"
        }
    ],
    "sg:phone":"+44 1698 286175",
    "sg:postcode":"ML3 7AD",
    "sg:province":"South Lanarkshire",
    "sg:tags":[
        "child",
        "childrens",
        "babywear"
    ],
    "sg:website":"http://www.ecagb.co.uk",
    "wof:name":"Pauls Baby Shop",
    "wof:placetype":"venue"
},
  "geometry": {"coordinates":[-4.042759,55.771149],"type":"Point"}
}