{
  "type": "Feature",
  "properties": {
    "addr:full":"53 Liverpool Road South Liverpool Lancashire L31 7BN",
    "addr:housenumber":"53",
    "addr:postcode":"l31 7bn",
    "addr:street":"Liverpool Road South",
    "iso:country":"GB",
    "sg:address":"53 Liverpool Road South",
    "sg:city":"Liverpool",
    "sg:classifiers":[
        {
            "category":"Personal",
            "subcategory":"Tanning Parlor",
            "type":"Services"
        }
    ],
    "sg:phone":"+44 151 287 3049",
    "sg:postcode":"L31 7BN",
    "sg:province":"Lancashire",
    "sg:tags":[
        "sunbeds"
    ],
    "wof:name":"Sun Rays",
    "wof:placetype":"venue"
},
  "geometry": {"coordinates":[-2.9486970901,53.5035552979],"type":"Point"}
}