{
  "type": "Feature",
  "properties": {
    "addr:full":"The Arcade, 24 Wellington St Aldershot Hampshire GU11 1DZ",
    "addr:housenumber":"24",
    "addr:postcode":"gu11 1dz",
    "addr:street":"Wellington St",
    "iso:country":"GB",
    "sg:address":"The Arcade, 24 Wellington St",
    "sg:city":"Aldershot",
    "sg:classifiers":[
        {
            "category":"Personal",
            "type":"Services"
        }
    ],
    "sg:postcode":"GU11 1DZ",
    "sg:province":"Hampshire",
    "sg:tags":[
        "wedding"
    ],
    "wof:name":"Beer,Maureen,",
    "wof:placetype":"venue"
},
  "geometry": {"coordinates":[-0.759346,51.249603],"type":"Point"}
}