{
  "type": "Feature",
  "properties": {
    "iso:country":"GB",
    "sg:address":"116 High Street",
    "sg:city":"Ilford",
    "sg:classifiers":[
        {
            "category":"Home & Garden",
            "subcategory":"Furniture",
            "type":"Retail Goods"
        }
    ],
    "sg:postcode":"IG6 2DU",
    "sg:province":"Essex",
    "wof:name":"The Cushion Shop",
    "wof:placetype":"venue"
},
  "geometry": {"coordinates":[0.083504,51.59169],"type":"Point"}
}