{
  "type": "Feature",
  "properties": {
    "addr:full":"P O Box 85 Warrington Cheshire WA2 0NZ",
    "addr:housenumber":"box 85",
    "addr:postcode":"wa2 0nz",
    "addr:street":"P O",
    "iso:country":"GB",
    "sg:address":"P O Box 85",
    "sg:city":"Warrington",
    "sg:classifiers":[
        {
            "category":"Professional",
            "type":"Services"
        }
    ],
    "sg:phone":"+44 1925 811237",
    "sg:postcode":"WA2 0NZ",
    "sg:province":"Cheshire",
    "sg:tags":[
        "entertainer"
    ],
    "wof:name":"Reid Entertainments",
    "wof:placetype":"venue"
},
  "geometry": {"coordinates":[-2.5598390102,53.411491394],"type":"Point"}
}