{
  "type": "Feature",
  "properties": {
    "iso:country":"GB",
    "sg:address":"Broadway",
    "sg:city":"Shifnal",
    "sg:classifiers":[
        {
            "category":"Manufacturing",
            "subcategory":"Tools & Machinery",
            "type":"Manufacturing & Wholesale Goods"
        }
    ],
    "sg:phone":"+44 1952 460230",
    "sg:postcode":"TF11 8BD",
    "sg:province":"Shropshire",
    "sg:tags":[
        "design",
        "maker"
    ],
    "wof:name":"Shifnal Engineering Group Ltd.",
    "wof:placetype":"venue"
},
  "geometry": {"coordinates":[-2.334749,52.693661],"type":"Point"}
}