{
  "type": "Feature",
  "properties": {
    "addr:full":"Movements House, 9-15 West Netherton Street Kilmarnock East Ayrshire KA1 4BU",
    "addr:housenumber":"9-15",
    "addr:postcode":"ka1 4bu",
    "addr:street":"West Netherton Street",
    "iso:country":"GB",
    "sg:address":"Movements House, 9-15 West Netherton Street",
    "sg:city":"Kilmarnock",
    "sg:classifiers":[
        {
            "category":"Retail",
            "subcategory":"Storage",
            "type":"Services"
        }
    ],
    "sg:phone":"+44 1563 520001",
    "sg:postcode":"KA1 4BU",
    "sg:province":"East Ayrshire",
    "sg:tags":[
        "household",
        "removal"
    ],
    "wof:name":"Kilmarnock Removals International",
    "wof:placetype":"venue"
},
  "geometry": {"coordinates":[-4.495695,55.603012],"type":"Point"}
}