{
  "type": "Feature",
  "properties": {
    "iso:country":"GB",
    "sg:address":"865 High Road",
    "sg:city":"London",
    "sg:classifiers":[
        {
            "category":"Shopping",
            "subcategory":"News",
            "type":"Retail Goods"
        }
    ],
    "sg:phone":"+44 20 8445 2701",
    "sg:postcode":"N12 8PT",
    "sg:province":"Greater London",
    "sg:tags":[
        "newsagent"
    ],
    "wof:name":"Glover Newsagents",
    "wof:placetype":"venue"
},
  "geometry": {"coordinates":[-0.1769870073,51.6180534363],"type":"Point"}
}