{
  "type": "Feature",
  "properties": {
    "iso:country":"GB",
    "sg:address":"14 Wethersfield Road",
    "sg:city":"Colchester",
    "sg:classifiers":[
        {
            "category":"Fast Food",
            "type":"Food & Drink"
        }
    ],
    "sg:phone":"+44 1206 48492",
    "sg:postcode":"CO2 0BB",
    "sg:province":"Essex",
    "sg:tags":[
        "away",
        "take"
    ],
    "wof:name":"Monkwick Chinese the Kitchen",
    "wof:placetype":"venue"
},
  "geometry": {"coordinates":[0.905642,51.859894],"type":"Point"}
}