{
  "type": "Feature",
  "properties": {
    "addr:full":"Ivy Cottage, Groombridge Place, Groombridge Tunbridge Wells East Sussex TN3 9QG",
    "addr:postcode":"tn3 9qg",
    "addr:street":"Groombridge Place",
    "iso:country":"GB",
    "sg:address":"Ivy Cottage, Groombridge Place, Groombridge",
    "sg:city":"Tunbridge Wells",
    "sg:classifiers":[
        {
            "category":"Organizations",
            "subcategory":"Non-profit Organization",
            "type":"Services"
        }
    ],
    "sg:phone":"+44 1892 861175",
    "sg:postcode":"TN3 9QG",
    "sg:province":"East Sussex",
    "sg:tags":[
        "organisation",
        "animal",
        "welfare"
    ],
    "wof:name":"The Raptor Centre Birds of Prey",
    "wof:placetype":"venue"
},
  "geometry": {"coordinates":[0.178580001,51.1116256714],"type":"Point"}
}