{
  "type": "Feature",
  "properties": {
    "addr:full":"Bulldog House, 267-269 Reading Road,winnersh Wokingham Berkshire RG11 5AG",
    "addr:housenumber":"267-269",
    "addr:postcode":"rg11 5ag",
    "addr:street":"Reading Road",
    "iso:country":"GB",
    "sg:address":"Bulldog House, 267-269 Reading Road,winnersh",
    "sg:city":"Wokingham",
    "sg:classifiers":[
        {
            "category":"Building & Trades",
            "subcategory":"Plumbing",
            "type":"Services"
        }
    ],
    "sg:postcode":"RG11 5AG",
    "sg:province":"Berkshire",
    "sg:tags":[
        "drain",
        "clearance",
        "sewer"
    ],
    "wof:name":"Swift Clear Services",
    "wof:placetype":"venue"
},
  "geometry": {"coordinates":[-0.88064,51.430241],"type":"Point"}
}