{
  "type": "Feature",
  "properties": {
    "addr:full":"102 Cowley Rd Oxford Oxfordshire OX4 1JE",
    "addr:housenumber":"102",
    "addr:postcode":"ox4 1je",
    "addr:street":"Cowley Rd",
    "iso:country":"GB",
    "sg:address":"102 Cowley Rd",
    "sg:city":"Oxford",
    "sg:classifiers":[
        {
            "category":"Military Area",
            "subcategory":"Air Force Base",
            "type":"Public Place"
        }
    ],
    "sg:phone":"+44 1865 725444",
    "sg:postcode":"OX4 1JE",
    "sg:province":"Oxfordshire",
    "sg:tags":[
        "decorative",
        "glass",
        "mirror",
        "mnfr"
    ],
    "wof:name":"McLeans Mirrors",
    "wof:placetype":"venue"
},
  "geometry": {"coordinates":[-1.2393120527,51.7483787537],"type":"Point"}
}