{
  "type": "Feature",
  "properties": {
    "iso:country":"GB",
    "sg:address":"31 West Main Street, Armadale",
    "sg:city":"Bathgate",
    "sg:classifiers":[
        {
            "category":"Shopping",
            "subcategory":"Clothing, Apparel, & Fashions",
            "type":"Retail Goods"
        }
    ],
    "sg:phone":"+44 1501 733363",
    "sg:postcode":"EH48 3PZ",
    "sg:province":"West Lothian",
    "sg:tags":[
        "ladieswear"
    ],
    "wof:name":"Nans Drapers",
    "wof:placetype":"venue"
},
  "geometry": {"coordinates":[-3.701415,55.89851],"type":"Point"}
}