{
  "type": "Feature",
  "properties": {
    "iso:country":"GB",
    "sg:address":"59 Elmdene Road",
    "sg:city":"Kenilworth",
    "sg:classifiers":[
        {
            "category":"Professional",
            "subcategory":"Computer Services",
            "type":"Services"
        }
    ],
    "sg:phone":"+44 1926 779596",
    "sg:postcode":"CV8 2BW",
    "sg:province":"Warwickshire",
    "sg:tags":[
        "development",
        "system",
        "software"
    ],
    "wof:name":"Primordia Ltd.",
    "wof:placetype":"venue"
},
  "geometry": {"coordinates":[-1.567019,52.344364],"type":"Point"}
}