{
  "type": "Feature",
  "properties": {
    "iso:country":"GB",
    "sg:address":"23 Victoria Street",
    "sg:city":"Scarborough",
    "sg:classifiers":[
        {
            "category":"Professional",
            "subcategory":"Art Services",
            "type":"Services"
        },
        {
            "category":"Building & Trades",
            "subcategory":"Construction",
            "type":"Services"
        }
    ],
    "sg:phone":"+44 1723 363836",
    "sg:postcode":"YO12 7SS",
    "sg:province":"North Yorkshire",
    "sg:tags":[
        "glazier",
        "decorator",
        "painter"
    ],
    "wof:name":"TODD BROS",
    "wof:placetype":"venue"
},
  "geometry": {"coordinates":[-0.4072499871,54.2840385437],"type":"Point"}
}