{
  "type": "Feature",
  "properties": {
    "addr:full":"Unit 2 Ashfields Industrial Estate, Priors Court Road Thatcham Berkshire RG18 9XY",
    "addr:housenumber":"unit 2",
    "addr:postcode":"rg18 9xy",
    "addr:street":"Ashfields Industrial Estate Priors Court Road",
    "iso:country":"GB",
    "sg:address":"Unit 2 Ashfields Industrial Estate, Priors Court Road",
    "sg:city":"Thatcham",
    "sg:classifiers":[
        {
            "category":"Military Area",
            "subcategory":"Air Force Base",
            "type":"Public Place"
        }
    ],
    "sg:phone":"+44 1635 247800",
    "sg:postcode":"RG18 9XY",
    "sg:province":"Berkshire",
    "sg:tags":[
        "fibre",
        "optic"
    ],
    "wof:name":"Lumen Photonics Ltd.",
    "wof:placetype":"venue"
},
  "geometry": {"coordinates":[-1.247802,51.422985],"type":"Point"}
}