{
  "type": "Feature",
  "properties": {
    "addr:full":"Woodburn House, 54 Canaan Lane Edinburgh City of Edinburgh EH10 4SG",
    "addr:housenumber":"54",
    "addr:postcode":"eh10 4sg",
    "addr:street":"Canaan Lane",
    "iso:country":"GB",
    "sg:address":"Woodburn House, 54 Canaan Lane",
    "sg:city":"Edinburgh",
    "sg:classifiers":[
        {
            "category":"Government",
            "subcategory":"Office",
            "type":"Public Place"
        }
    ],
    "sg:phone":"+44 131 536 5500",
    "sg:postcode":"EH10 4SG",
    "sg:province":"City of Edinburgh",
    "sg:tags":[
        "central"
    ],
    "wof:name":"Health Education Board for Scotland",
    "wof:placetype":"venue"
},
  "geometry": {"coordinates":[-3.202229023,55.9283714294],"type":"Point"}
}