{
  "type": "Feature",
  "properties": {
    "addr:full":"1 St Georges Square Stamford Cambridgeshire PE9 2BN",
    "addr:housenumber":"1",
    "addr:postcode":"pe9 2bn",
    "addr:street":"St Georges Square",
    "iso:country":"GB",
    "sg:address":"1 St Georges Square",
    "sg:city":"Stamford",
    "sg:classifiers":[
        {
            "category":"Shopping",
            "subcategory":"Antiques",
            "type":"Retail Goods"
        }
    ],
    "sg:phone":"+44 1780 754117",
    "sg:postcode":"PE9 2BN",
    "sg:province":"Cambridgeshire",
    "wof:name":"St. Georges Antiques",
    "wof:placetype":"venue"
},
  "geometry": {"coordinates":[-0.4764640033,52.6517181396],"type":"Point"}
}