{
  "type": "Feature",
  "properties": {
    "addr:full":"Chapel Lane, Crich Matlock Derbyshire DE4 5BU",
    "addr:postcode":"de4 5bu",
    "addr:street":"Chapel Lane",
    "iso:country":"GB",
    "sg:address":"Chapel Lane, Crich",
    "sg:city":"Matlock",
    "sg:classifiers":[
        {
            "category":"Place Of Worship",
            "type":"Public Place"
        }
    ],
    "sg:phone":"+44 1773 743177",
    "sg:postcode":"DE4 5BU",
    "sg:province":"Derbyshire",
    "wof:name":"Crich Wesley Methodist Church",
    "wof:placetype":"venue"
},
  "geometry": {"coordinates":[-1.47795403,53.0793037415],"type":"Point"}
}