{
  "type": "Feature",
  "properties": {
    "iso:country":"GB",
    "sg:address":"14 Electric Avenue",
    "sg:city":"London",
    "sg:classifiers":[
        {
            "category":"Shopping",
            "subcategory":"Department Store",
            "type":"Retail Goods"
        },
        {
            "category":"Food & Beverages",
            "subcategory":"Specialty",
            "type":"Retail Goods"
        }
    ],
    "sg:phone":"+44 20 7924 0332",
    "sg:postcode":"SW9 8JX",
    "sg:province":"Greater London",
    "sg:tags":[
        "health",
        "retailer"
    ],
    "wof:name":"A1 Superstore",
    "wof:placetype":"venue"
},
  "geometry": {"coordinates":[-0.1143390015,51.4623565674],"type":"Point"}
}