{
  "type": "Feature",
  "properties": {
    "addr:full":"Moor Valley Way, Moor Valley, Mosborough Sheffield South Yorkshire S20 5BB",
    "addr:postcode":"s20 5bb",
    "addr:street":"Moor Valley Way Moor Valley Mosborough",
    "iso:country":"GB",
    "sg:address":"Moor Valley Way, Moor Valley, Mosborough",
    "sg:city":"Sheffield",
    "sg:classifiers":[
        {
            "category":"Retail",
            "subcategory":"Auto Repair",
            "type":"Services"
        }
    ],
    "sg:postcode":"S20 5BB",
    "sg:province":"South Yorkshire",
    "sg:tags":[
        "modification",
        "garage"
    ],
    "wof:name":"Miata Auto Services",
    "wof:placetype":"venue"
},
  "geometry": {"coordinates":[-1.383069,53.336143],"type":"Point"}
}