{
  "type": "Feature",
  "properties": {
    "addr:full":"10 Wells Road Ilkley North Yorkshire LS29 9JD",
    "addr:housenumber":"10",
    "addr:postcode":"ls29 9jd",
    "addr:street":"Wells Road",
    "iso:country":"GB",
    "sg:address":"10 Wells Road",
    "sg:city":"Ilkley",
    "sg:classifiers":[
        {
            "category":"Restaurant",
            "type":"Food & Drink"
        }
    ],
    "sg:phone":"+44 1943 602204",
    "sg:postcode":"LS29 9JD",
    "sg:province":"North Yorkshire",
    "sg:tags":[
        "-",
        "chinese"
    ],
    "wof:name":"Po Sang Chinese Restaurant",
    "wof:placetype":"venue"
},
  "geometry": {"coordinates":[-1.822964,53.92395],"type":"Point"}
}