{
  "type": "Feature",
  "properties": {
    "iso:country":"GB",
    "sg:address":"Business & Technology Centre, Bessemer Drive",
    "sg:city":"Stevenage",
    "sg:classifiers":[
        {
            "category":"Wholesale",
            "subcategory":"Meat",
            "type":"Manufacturing & Wholesale Goods"
        }
    ],
    "sg:phone":"+44 1438 353692",
    "sg:postcode":"SG1 2DX",
    "sg:province":"Hertfordshire",
    "sg:tags":[
        "-"
    ],
    "wof:name":"I G V Compaxo",
    "wof:placetype":"venue"
},
  "geometry": {"coordinates":[-0.2176299989,51.8997001648],"type":"Point"}
}