{
  "type": "Feature",
  "properties": {
    "addr:full":"26 Tarvin Road, Boughton Chester Cheshire CH3 5DH",
    "addr:housenumber":"26",
    "addr:postcode":"ch3 5dh",
    "addr:street":"Tarvin Road",
    "iso:country":"GB",
    "sg:address":"26 Tarvin Road, Boughton",
    "sg:city":"Chester",
    "sg:classifiers":[
        {
            "category":"Retail",
            "subcategory":"Veterinary Services",
            "type":"Services"
        }
    ],
    "sg:phone":"+44 1244 311106",
    "sg:postcode":"CH3 5DH",
    "sg:province":"Cheshire",
    "sg:tags":[
        "surgeon"
    ],
    "wof:name":"The Storrar Practice",
    "wof:placetype":"venue"
},
  "geometry": {"coordinates":[-2.8695280552,53.1918258667],"type":"Point"}
}