{
  "type": "Feature",
  "properties": {
    "iso:country":"GB",
    "sg:address":"4 High Street",
    "sg:city":"Ripley",
    "sg:classifiers":[
        {
            "category":"Personal",
            "subcategory":"Beauty Salon",
            "type":"Services"
        },
        {
            "category":"Personal",
            "subcategory":"Barber",
            "type":"Services"
        }
    ],
    "sg:phone":"+44 1773 570555",
    "sg:postcode":"DE5 3HH",
    "sg:province":"Derbyshire",
    "sg:tags":[
        "unisex",
        "hairdresser"
    ],
    "wof:name":"Jon-Jos Hairdressing",
    "wof:placetype":"venue"
},
  "geometry": {"coordinates":[-1.407152,53.049809],"type":"Point"}
}