{
  "type": "Feature",
  "properties": {
    "addr:full":"117-119 High Street Crawley Surrey RH10 1YN",
    "addr:housenumber":"117-119",
    "addr:postcode":"rh10 1yn",
    "addr:street":"High Street",
    "iso:country":"GB",
    "sg:address":"117-119 High Street",
    "sg:city":"Crawley",
    "sg:classifiers":[
        {
            "category":"Professional",
            "subcategory":"Lawyer & Legal Services",
            "type":"Services"
        }
    ],
    "sg:phone":"+44 1293 544071",
    "sg:postcode":"RH10 1YN",
    "sg:province":"Surrey",
    "sg:tags":[
        "solicitor"
    ],
    "wof:name":"Stevens Drake",
    "wof:placetype":"venue"
},
  "geometry": {"coordinates":[-0.1892510056,51.1176185608],"type":"Point"}
}