{
  "type": "Feature",
  "properties": {
    "addr:full":"17 Oxford Rd Kidlington Buckinghamshire OX5 2BP",
    "addr:housenumber":"17",
    "addr:postcode":"ox5 2bp",
    "addr:street":"Oxford Rd",
    "iso:country":"GB",
    "sg:address":"17 Oxford Rd",
    "sg:city":"Kidlington",
    "sg:classifiers":[
        {
            "category":"Banks & Credit Unions",
            "subcategory":"Bank",
            "type":"Services"
        }
    ],
    "sg:phone":"+44 1865 247411",
    "sg:postcode":"OX5 2BP",
    "sg:province":"Buckinghamshire",
    "wof:name":"NatWest",
    "wof:placetype":"venue"
},
  "geometry": {"coordinates":[-1.2886539698,51.8220901489],"type":"Point"}
}