{
  "type": "Feature",
  "properties": {
    "addr:full":"Unit 1b Southern Gate Park, Mayfield Trading Estate, Acre Road Reading Berkshire RG2 0RJ",
    "addr:housenumber":"unit 1b;estate",
    "addr:postcode":"rg2 0rj",
    "addr:street":"Southern Gate Park;Trading;Acre Road",
    "iso:country":"GB",
    "sg:address":"Unit 1b Southern Gate Park, Mayfield Trading Estate, Acre Road",
    "sg:city":"Reading",
    "sg:classifiers":[
        {
            "category":"Autos & Motor Vehicles",
            "subcategory":"Auto Supplies",
            "type":"Retail Goods"
        }
    ],
    "sg:phone":"+44 118 975 6630",
    "sg:postcode":"RG2 0RJ",
    "sg:province":"Berkshire",
    "sg:tags":[
        "windscreen"
    ],
    "wof:name":"Silver Shield Windscreens",
    "wof:placetype":"venue"
},
  "geometry": {"coordinates":[-0.97831,51.423168],"type":"Point"}
}