{
  "type": "Feature",
  "properties": {
    "addr:full":"Unit 23 Roxwell Trading Park, Argall Avenue London Greater London E10 7QY",
    "addr:housenumber":"unit 23 roxwell",
    "addr:postcode":"e10 7qy",
    "addr:street":"Park Argall Avenue",
    "iso:country":"GB",
    "sg:address":"Unit 23 Roxwell Trading Park, Argall Avenue",
    "sg:city":"London",
    "sg:classifiers":[
        {
            "category":"Retail",
            "subcategory":"Auto Repair",
            "type":"Services"
        }
    ],
    "sg:phone":"+44 20 8558 1366",
    "sg:postcode":"E10 7QY",
    "sg:province":"Greater London",
    "sg:tags":[
        "modification",
        "garage",
        "related"
    ],
    "wof:name":"S J Bedwell",
    "wof:placetype":"venue"
},
  "geometry": {"coordinates":[-0.0374599993,51.5708618164],"type":"Point"}
}