{
  "type": "Feature",
  "properties": {
    "addr:full":"Ashfield Works Otley North Yorkshire LS21 3AT",
    "addr:postcode":"ls21 3at",
    "iso:country":"GB",
    "sg:address":"Ashfield Works",
    "sg:city":"Otley",
    "sg:classifiers":[
        {
            "category":"Freight",
            "type":"Transportation"
        }
    ],
    "sg:phone":"+44 1943 461842",
    "sg:postcode":"LS21 3AT",
    "sg:province":"North Yorkshire",
    "sg:tags":[
        "haulage",
        "road"
    ],
    "wof:name":"Reg Jefferies & Son Ltd.",
    "wof:placetype":"venue"
},
  "geometry": {"coordinates":[-1.6949529648,53.9057197571],"type":"Point"}
}