{
  "type": "Feature",
  "properties": {
    "addr:full":"17 Taylor Avenue Chelmsford Essex CM1 2BT",
    "addr:housenumber":"17",
    "addr:postcode":"cm1 2bt",
    "addr:street":"Taylor Avenue",
    "iso:country":"GB",
    "sg:address":"17 Taylor Avenue",
    "sg:city":"Chelmsford",
    "sg:classifiers":[
        {
            "category":"Building & Trades",
            "subcategory":"Landscaping Services",
            "type":"Services"
        }
    ],
    "sg:phone":"+44 1245 609756",
    "sg:postcode":"CM1 2BT",
    "sg:province":"Essex",
    "sg:tags":[
        "designer",
        "architect",
        "landscape"
    ],
    "wof:name":"Open Spaces",
    "wof:placetype":"venue"
},
  "geometry": {"coordinates":[0.4527229965,51.7475776672],"type":"Point"}
}