{
  "type": "Feature",
  "properties": {
    "addr:full":"Cedarshade, All Saints Road Sidmouth Devon EX10 8EU",
    "addr:postcode":"ex10 8eu",
    "addr:street":"All Saints Road",
    "iso:country":"GB",
    "sg:address":"Cedarshade, All Saints Road",
    "sg:city":"Sidmouth",
    "sg:classifiers":[
        {
            "category":"Organizations",
            "subcategory":"Non-profit Organization",
            "type":"Services"
        }
    ],
    "sg:phone":"+44 1395 514033",
    "sg:postcode":"EX10 8EU",
    "sg:province":"Devon",
    "sg:tags":[
        "organisation",
        "voluntary",
        "charity"
    ],
    "wof:name":"W R V S",
    "wof:placetype":"venue"
},
  "geometry": {"coordinates":[-3.2388389111,50.6822013855],"type":"Point"}
}