{
  "type": "Feature",
  "properties": {
    "iso:country":"GB",
    "sg:address":"16 Cochran Close",
    "sg:city":"Milton Keynes",
    "sg:classifiers":[
        {
            "category":"Professional",
            "subcategory":"Engineering",
            "type":"Services"
        }
    ],
    "sg:phone":"+44 1908 261820",
    "sg:postcode":"MK8 0AJ",
    "sg:province":"Buckinghamshire",
    "sg:tags":[
        "contractor",
        "electrical",
        "engineer"
    ],
    "wof:name":"Farebrother Engineering Services Ltd.",
    "wof:placetype":"venue"
},
  "geometry": {"coordinates":[-0.800034,52.027679],"type":"Point"}
}