{
  "type": "Feature",
  "properties": {
    "addr:full":"71 Princess Road, Urmston Manchester Cheshire M41 5ST",
    "addr:housenumber":"71",
    "addr:postcode":"m41 5st",
    "addr:street":"Princess Road",
    "iso:country":"GB",
    "sg:address":"71 Princess Road, Urmston",
    "sg:city":"Manchester",
    "sg:classifiers":[
        {
            "category":"Home & Garden",
            "subcategory":"Kitchen Supply",
            "type":"Retail Goods"
        }
    ],
    "sg:phone":"+44 161 748 1520",
    "sg:postcode":"M41 5ST",
    "sg:province":"Cheshire",
    "sg:tags":[
        "equipment",
        "catering"
    ],
    "wof:name":"A Venning Ltd.",
    "wof:placetype":"venue"
},
  "geometry": {"coordinates":[-2.365023,53.45113],"type":"Point"}
}