{
  "type": "Feature",
  "properties": {
    "iso:country":"GB",
    "sg:address":"4 Manston Terrace",
    "sg:city":"Exeter",
    "sg:classifiers":[
        {
            "category":"Health Services",
            "subcategory":"Doctor",
            "type":"Services"
        }
    ],
    "sg:phone":"+44 1392 431833",
    "sg:postcode":"EX2 4NP",
    "sg:province":"Devon",
    "sg:tags":[
        "practitioners"
    ],
    "wof:name":"Martin, M R",
    "wof:placetype":"venue"
},
  "geometry": {"coordinates":[-3.5117259026,50.7211380005],"type":"Point"}
}