{
  "type": "Feature",
  "properties": {
    "iso:country":"GB",
    "sg:address":"94 Churchill Avenue",
    "sg:city":"Chatham",
    "sg:classifiers":[
        {
            "category":"Health Services",
            "subcategory":"Doctor",
            "type":"Services"
        }
    ],
    "sg:phone":"+44 1634 842397",
    "sg:postcode":"ME5 0DL",
    "sg:province":"Kent",
    "sg:tags":[
        "practitioners"
    ],
    "wof:name":"Churchill Clinic",
    "wof:placetype":"venue"
},
  "geometry": {"coordinates":[0.5324460268,51.358997345],"type":"Point"}
}