{
  "type": "Feature",
  "properties": {
    "iso:country":"GB",
    "sg:address":"144 Richmond Road",
    "sg:city":"Cardiff",
    "sg:classifiers":[
        {
            "category":"Retail",
            "subcategory":"Repair Shop",
            "type":"Services"
        }
    ],
    "sg:phone":"+44 29 2045 5505",
    "sg:postcode":"CF24 3BX",
    "sg:province":"Cardiff",
    "sg:tags":[
        "upholsterer"
    ],
    "wof:name":"Crosby's Upholstery",
    "wof:placetype":"venue"
},
  "geometry": {"coordinates":[-3.172191,51.491127],"type":"Point"}
}