{
  "type": "Feature",
  "properties": {
    "addr:full":"4 Miskin Road Mountain Ash Rhondda, Cynon, Taff CF45 3UB",
    "addr:housenumber":"4",
    "addr:postcode":"cf45 3ub",
    "addr:street":"Miskin Road;Cynon Taff",
    "iso:country":"GB",
    "sg:address":"4 Miskin Road",
    "sg:city":"Mountain Ash",
    "sg:classifiers":[
        {
            "category":"Cafe",
            "type":"Food & Drink"
        }
    ],
    "sg:phone":"+44 1443 473238",
    "sg:postcode":"CF45 3UB",
    "sg:province":"Rhondda, Cynon, Taff",
    "sg:tags":[
        "tea",
        "snack",
        "bar",
        "room"
    ],
    "wof:name":"Continental Cafe",
    "wof:placetype":"venue"
},
  "geometry": {"coordinates":[-3.37363,51.67828],"type":"Point"}
}