{
  "type": "Feature",
  "properties": {
    "addr:full":"Beech Avenue Stockport Cheshire SK3 8HB",
    "addr:postcode":"sk3 8hb",
    "addr:street":"Beech Avenue",
    "iso:country":"GB",
    "sg:address":"Beech Avenue",
    "sg:city":"Stockport",
    "sg:classifiers":[
        {
            "category":"Education",
            "subcategory":"School",
            "type":"Public Place"
        }
    ],
    "sg:phone":"+44 161 480 0329",
    "sg:postcode":"SK3 8HB",
    "sg:province":"Cheshire",
    "sg:tags":[
        "independent",
        "preparatory"
    ],
    "wof:name":"Hillcrest Grammar School",
    "wof:placetype":"venue"
},
  "geometry": {"coordinates":[-2.1569690704,53.3956756592],"type":"Point"}
}