{
  "type": "Feature",
  "properties": {
    "addr:full":"B & M House, 21a High Street Leighton Buzzard Bedfordshire LU7 1DN",
    "addr:housenumber":"21a",
    "addr:postcode":"lu7 1dn",
    "addr:street":"High Street",
    "iso:country":"GB",
    "sg:address":"B & M House, 21a High Street",
    "sg:city":"Leighton Buzzard",
    "sg:classifiers":[
        {
            "category":"Professional",
            "subcategory":"Management & Consulting",
            "type":"Services"
        }
    ],
    "sg:phone":"+44 1525 383106",
    "sg:postcode":"LU7 1DN",
    "sg:province":"Bedfordshire",
    "sg:tags":[
        "marketing",
        "consultant"
    ],
    "wof:name":"Inmarc Associates",
    "wof:placetype":"venue"
},
  "geometry": {"coordinates":[-0.663167,51.91626],"type":"Point"}
}