{
  "type": "Feature",
  "properties": {
    "addr:full":"176 Newbold Road Nuneaton Leicestershire CV13 0DT",
    "addr:housenumber":"176",
    "addr:postcode":"cv13 0dt",
    "addr:street":"Newbold Road",
    "iso:country":"GB",
    "sg:address":"176 Newbold Road",
    "sg:city":"Nuneaton",
    "sg:classifiers":[
        {
            "category":"Building & Trades",
            "subcategory":"Construction",
            "type":"Services"
        }
    ],
    "sg:postcode":"CV13 0DT",
    "sg:province":"Leicestershire",
    "sg:tags":[
        "builder"
    ],
    "wof:name":"Malcolm L Kent",
    "wof:placetype":"venue"
},
  "geometry": {"coordinates":[-1.354821,52.643421],"type":"Point"}
}