{
  "type": "Feature",
  "properties": {
    "iso:country":"GB",
    "sg:address":"1 Station Road",
    "sg:city":"Ammanford",
    "sg:classifiers":[
        {
            "category":"Shopping",
            "subcategory":"Department Store",
            "type":"Retail Goods"
        }
    ],
    "sg:phone":"+44 1269 592726",
    "sg:postcode":"SA18 2DB",
    "sg:province":"Carmarthenshire",
    "wof:name":"Park Stores",
    "wof:placetype":"venue"
},
  "geometry": {"coordinates":[-3.993629,51.797058],"type":"Point"}
}