{
  "type": "Feature",
  "properties": {
    "iso:country":"GB",
    "sg:address":"57 Gelli Road, Gelli",
    "sg:city":"Pentre",
    "sg:classifiers":[
        {
            "category":"Farming",
            "subcategory":"Dairy Farm",
            "type":"Manufacturing & Wholesale Goods"
        }
    ],
    "sg:postcode":"CF41 7NB",
    "sg:province":"Rhondda, Cynon, Taff",
    "wof:name":"Brinley Merrett",
    "wof:placetype":"venue"
},
  "geometry": {"coordinates":[-3.482947,51.644001],"type":"Point"}
}