{
  "type": "Feature",
  "properties": {
    "addr:full":"Renishaw Hall, Renishaw Park, Renishaw Sheffield Derbyshire S21 3WB",
    "addr:postcode":"s21 3wb",
    "iso:country":"GB",
    "sg:address":"Renishaw Hall, Renishaw Park, Renishaw",
    "sg:city":"Sheffield",
    "sg:classifiers":[
        {
            "category":"Home & Garden",
            "subcategory":"Building Materials",
            "type":"Retail Goods"
        }
    ],
    "sg:phone":"+44 1246 431115",
    "sg:postcode":"S21 3WB",
    "sg:province":"Derbyshire",
    "sg:tags":[
        "ironwork",
        "diy",
        "wrought"
    ],
    "wof:name":"P W A Enterprises",
    "wof:placetype":"venue"
},
  "geometry": {"coordinates":[-1.3303790092,53.2962265015],"type":"Point"}
}