{
  "type": "Feature",
  "properties": {
    "addr:full":"25-29 Samuel Street, Bloxwich Walsall Staffordshire WS3 2EU",
    "addr:housenumber":"25-29",
    "addr:postcode":"ws3 2eu",
    "addr:street":"Samuel Street",
    "iso:country":"GB",
    "sg:address":"25-29 Samuel Street, Bloxwich",
    "sg:city":"Walsall",
    "sg:classifiers":[
        {
            "category":"Retail",
            "subcategory":"Storage",
            "type":"Services"
        }
    ],
    "sg:phone":"+44 1922 497690",
    "sg:postcode":"WS3 2EU",
    "sg:province":"Staffordshire",
    "sg:tags":[
        "household",
        "removal"
    ],
    "wof:name":"Speedline Express Light Haulage & International Re",
    "wof:placetype":"venue"
},
  "geometry": {"coordinates":[-2.0052399635,52.6175994873],"type":"Point"}
}