{
  "type": "Feature",
  "properties": {
    "addr:full":"Denholme Gate Road, Hipperholme Halifax West Yorkshire HX3 8HX",
    "addr:postcode":"hx3 8hx",
    "addr:street":"Denholme Gate Road",
    "iso:country":"GB",
    "sg:address":"Denholme Gate Road, Hipperholme",
    "sg:city":"Halifax",
    "sg:classifiers":[
        {
            "category":"Food & Beverages",
            "subcategory":"Meat & Fish",
            "type":"Retail Goods"
        }
    ],
    "sg:phone":"+44 1422 202368",
    "sg:postcode":"HX3 8HX",
    "sg:province":"West Yorkshire",
    "sg:tags":[
        "butcher"
    ],
    "wof:name":"G Allen",
    "wof:placetype":"venue"
},
  "geometry": {"coordinates":[-1.808219,53.726341],"type":"Point"}
}