{
  "type": "Feature",
  "properties": {
    "addr:full":"The Old School, Burford Tenbury Wells Herefordshire WR15 8HF",
    "addr:postcode":"wr15 8hf",
    "iso:country":"GB",
    "sg:address":"The Old School, Burford",
    "sg:city":"Tenbury Wells",
    "sg:classifiers":[
        {
            "category":"Shopping",
            "subcategory":"Mobile Phones",
            "type":"Retail Goods"
        }
    ],
    "sg:phone":"+44 1584 810183",
    "sg:postcode":"WR15 8HF",
    "sg:province":"Herefordshire",
    "wof:name":"Well Communications Ltd.",
    "wof:placetype":"venue"
},
  "geometry": {"coordinates":[-2.594178915,52.3125839233],"type":"Point"}
}