{
  "type": "Feature",
  "properties": {
    "addr:full":"Main St Malton North Yorkshire YO17 0XL",
    "addr:postcode":"yo17 0xl",
    "addr:street":"Main St",
    "iso:country":"GB",
    "sg:address":"Main St",
    "sg:city":"Malton",
    "sg:classifiers":[
        {
            "category":"Government",
            "subcategory":"Post Office",
            "type":"Public Place"
        }
    ],
    "sg:phone":"+44 1653 668207",
    "sg:postcode":"YO17 0XL",
    "sg:province":"North Yorkshire",
    "wof:name":"Kirby Misperton Post Office",
    "wof:placetype":"venue"
},
  "geometry": {"coordinates":[-0.8537570238,54.1521568298],"type":"Point"}
}