{
  "type": "Feature",
  "properties": {
    "iso:country":"GB",
    "sg:address":"290 Promenade",
    "sg:city":"Blackpool",
    "sg:classifiers":[
        {
            "category":"Travel",
            "subcategory":"Hotels & Motels",
            "type":"Entertainment"
        }
    ],
    "sg:phone":"+44 1253 625724",
    "sg:postcode":"FY1 2EY",
    "sg:province":"Lancashire",
    "wof:name":"Lawnlea Hotel",
    "wof:placetype":"venue"
},
  "geometry": {"coordinates":[-3.055248,53.825951],"type":"Point"}
}