{
  "type": "Feature",
  "properties": {
    "iso:country":"GB",
    "sg:address":"Irlam Local Access Centre, Macdonald Road",
    "sg:city":"Manchester",
    "sg:classifiers":[
        {
            "category":"Education",
            "subcategory":"University",
            "type":"Public Place"
        }
    ],
    "sg:phone":"+44 161 777 6079",
    "sg:postcode":"M44 5LH",
    "sg:province":"Greater Manchester",
    "sg:tags":[
        "higher"
    ],
    "wof:name":"Salford College Students Union",
    "wof:placetype":"venue"
},
  "geometry": {"coordinates":[-2.4325,53.437832],"type":"Point"}
}