{
  "type": "Feature",
  "properties": {
    "iso:country":"GB",
    "sg:address":"1059 Pollokshaws Road",
    "sg:city":"Glasgow",
    "sg:classifiers":[
        {
            "category":"Fast Food",
            "type":"Food & Drink"
        }
    ],
    "sg:postcode":"G41 3YF",
    "sg:province":"Glasgow City",
    "sg:tags":[
        "away",
        "take"
    ],
    "wof:name":"Baba Tandoori",
    "wof:placetype":"venue"
},
  "geometry": {"coordinates":[-4.2793149948,55.8312530518],"type":"Point"}
}