{
  "type": "Feature",
  "properties": {
    "addr:full":"29 Gill Park Plymouth Devon PL3 6LX",
    "addr:housenumber":"29",
    "addr:postcode":"pl3 6lx",
    "addr:street":"Gill Park",
    "iso:country":"GB",
    "sg:address":"29 Gill Park",
    "sg:city":"Plymouth",
    "sg:classifiers":[
        {
            "category":"Professional",
            "subcategory":"Engineering",
            "type":"Services"
        }
    ],
    "sg:phone":"+44 1752 229230",
    "sg:postcode":"PL3 6LX",
    "sg:province":"Devon",
    "sg:tags":[
        "gas",
        "engineer"
    ],
    "wof:name":"A E Poole-Wheeler",
    "wof:placetype":"venue"
},
  "geometry": {"coordinates":[-4.1133317947,50.3864326477],"type":"Point"}
}