{
  "type": "Feature",
  "properties": {
    "iso:country":"GB",
    "sg:address":"131 Katherine Street",
    "sg:city":"Ashton-under-lyne",
    "sg:classifiers":[
        {
            "category":"Organizations",
            "subcategory":"Non-profit Organization",
            "type":"Services"
        }
    ],
    "sg:phone":"+44 161 308 5000",
    "sg:postcode":"OL6 7AW",
    "sg:province":"Greater Manchester",
    "sg:tags":[
        "organisation",
        "voluntary",
        "charity"
    ],
    "wof:name":"Age Concern Tameside Trading Ltd.",
    "wof:placetype":"venue"
},
  "geometry": {"coordinates":[-2.0974099636,53.4885063171],"type":"Point"}
}