{
  "type": "Feature",
  "properties": {
    "addr:full":"Bellfield Rd High Wycombe Buckinghamshire HP13 5HP",
    "addr:postcode":"hp13 5hp",
    "addr:street":"Bellfield Rd",
    "iso:country":"GB",
    "sg:address":"Bellfield Rd",
    "sg:city":"High Wycombe",
    "sg:classifiers":[
        {
            "category":"Home & Garden",
            "subcategory":"Hardware",
            "type":"Retail Goods"
        }
    ],
    "sg:phone":"+44 1494 600151",
    "sg:postcode":"HP13 5HP",
    "sg:province":"Buckinghamshire",
    "sg:tags":[
        "compressor",
        "air"
    ],
    "wof:name":"Compair Demag",
    "wof:placetype":"venue"
},
  "geometry": {"coordinates":[-0.753118,51.635159],"type":"Point"}
}