{
  "type": "Feature",
  "properties": {
    "addr:full":"Dyason Main Road, Boughton Newark Nottinghamshire NG22 9JF",
    "addr:postcode":"ng22 9jf",
    "addr:street":"Main Road",
    "iso:country":"GB",
    "sg:address":"Dyason Main Road, Boughton",
    "sg:city":"Newark",
    "sg:classifiers":[
        {
            "category":"Shopping",
            "subcategory":"Pets & Pet Supplies",
            "type":"Retail Goods"
        }
    ],
    "sg:postcode":"NG22 9JF",
    "sg:province":"Nottinghamshire",
    "sg:tags":[
        "food"
    ],
    "wof:name":"Easy Feeds",
    "wof:placetype":"venue"
},
  "geometry": {"coordinates":[-0.9933720231,53.2082672119],"type":"Point"}
}