{
  "type": "Feature",
  "properties": {
    "iso:country":"GB",
    "sg:address":"Falmouth Road",
    "sg:city":"Redruth",
    "sg:classifiers":[
        {
            "category":"Food & Beverages",
            "subcategory":"Supermarket",
            "type":"Retail Goods"
        }
    ],
    "sg:postcode":"TR15 2QJ",
    "sg:province":"Cornwall",
    "wof:name":"Spar",
    "wof:placetype":"venue"
},
  "geometry": {"coordinates":[-5.22836,50.231239],"type":"Point"}
}