{
  "type": "Feature",
  "properties": {
    "iso:country":"GB",
    "sg:address":"54 Wandsworth High Street",
    "sg:city":"London",
    "sg:classifiers":[
        {
            "category":"Personal",
            "subcategory":"Beauty Salon",
            "type":"Services"
        }
    ],
    "sg:postcode":"SW18 4LD",
    "sg:province":"Greater London",
    "sg:tags":[
        "unisex",
        "hairdresser"
    ],
    "wof:name":"Clipjoint",
    "wof:placetype":"venue"
},
  "geometry": {"coordinates":[-0.1926990002,51.4567909241],"type":"Point"}
}