{
  "type": "Feature",
  "properties": {
    "iso:country":"GB",
    "sg:address":"10 Bishops Rise",
    "sg:city":"Hatfield",
    "sg:classifiers":[
        {
            "category":"Retail",
            "subcategory":"Veterinary Services",
            "type":"Services"
        }
    ],
    "sg:postcode":"AL10 9HB",
    "sg:province":"Hertfordshire",
    "sg:tags":[
        "surgeon"
    ],
    "wof:name":"The Bishops Veterinary Surgery",
    "wof:placetype":"venue"
},
  "geometry": {"coordinates":[-0.237726,51.757133],"type":"Point"}
}