{
  "type": "Feature",
  "properties": {
    "iso:country":"GB",
    "sg:address":"2 Beatrice Place",
    "sg:city":"London",
    "sg:classifiers":[
        {
            "category":"Social Services",
            "type":"Services"
        },
        {
            "category":"Professional",
            "subcategory":"Employment Agencies",
            "type":"Services"
        }
    ],
    "sg:phone":"+44 20 7937 1611",
    "sg:postcode":"W8 5LP",
    "sg:province":"Greater London",
    "sg:tags":[
        "consultant",
        "disability"
    ],
    "sg:website":"http://www.rbkc.gov.uk",
    "wof:name":"Kensington Recruitment",
    "wof:placetype":"venue"
},
  "geometry": {"coordinates":[-0.1919039935,51.4964294434],"type":"Point"}
}