{
  "type": "Feature",
  "properties": {
    "iso:country":"GB",
    "sg:address":"39 Castle Arcade",
    "sg:city":"Cardiff",
    "sg:classifiers":[
        {
            "category":"Sports & Exercise",
            "subcategory":"Sports Center",
            "type":"Entertainment"
        }
    ],
    "sg:phone":"+44 29 2066 6400",
    "sg:postcode":"CF10 1BW",
    "sg:province":"Cardiff",
    "sg:tags":[
        "shop",
        "good"
    ],
    "wof:name":"Hustler",
    "wof:placetype":"venue"
},
  "geometry": {"coordinates":[-3.180717,51.481022],"type":"Point"}
}