{
  "type": "Feature",
  "properties": {
    "addr:full":"28 Standard Rd Bexleyheath Kent DA6 8DP",
    "addr:housenumber":"28",
    "addr:postcode":"da6 8dp",
    "addr:street":"Standard Rd",
    "iso:country":"GB",
    "sg:address":"28 Standard Rd",
    "sg:city":"Bexleyheath",
    "sg:classifiers":[
        {
            "category":"Freight",
            "type":"Transportation"
        }
    ],
    "sg:phone":"+44 20 8301 2141",
    "sg:postcode":"DA6 8DP",
    "sg:province":"Kent",
    "sg:tags":[
        "forwarders"
    ],
    "wof:name":"I S C Ltd",
    "wof:placetype":"venue"
},
  "geometry": {"coordinates":[0.134928003,51.456653595],"type":"Point"}
}