{
  "type": "Feature",
  "properties": {
    "iso:country":"GB",
    "sg:address":"1st Floor 5-9 Grey Street",
    "sg:city":"Newcastle-upon-tyne",
    "sg:classifiers":[
        {
            "category":"Shopping",
            "subcategory":"Books",
            "type":"Retail Goods"
        }
    ],
    "sg:postcode":"NE1 6AS",
    "sg:province":"Tyne and Wear",
    "wof:name":"Official Publications",
    "wof:placetype":"venue"
},
  "geometry": {"coordinates":[-1.610935,54.970963],"type":"Point"}
}