{
  "type": "Feature",
  "properties": {
    "addr:full":"Unit 7a, Beadle Trading Estate, Hithercroft Road Wallingford Oxfordshire OX10 9EZ",
    "addr:housenumber":"unit 7a beadle",
    "addr:postcode":"ox10 9ez",
    "addr:street":"Trading Estate Hithercroft Road",
    "iso:country":"GB",
    "sg:address":"Unit 7a, Beadle Trading Estate, Hithercroft Road",
    "sg:city":"Wallingford",
    "sg:classifiers":[
        {
            "category":"Autos & Motor Vehicles",
            "subcategory":"Boat Sales",
            "type":"Retail Goods"
        },
        {
            "category":"Retail",
            "subcategory":"Auto Repair",
            "type":"Services"
        }
    ],
    "sg:phone":"+44 1491 836222",
    "sg:postcode":"OX10 9EZ",
    "sg:province":"Oxfordshire",
    "sg:tags":[
        "engine",
        "car",
        "rebuilders",
        "specialist"
    ],
    "sg:website":"http://www.fondera.co.uk",
    "wof:name":"Fondera Ltd",
    "wof:placetype":"venue"
},
  "geometry": {"coordinates":[-1.1256229877,51.6009101868],"type":"Point"}
}