{
  "type": "Feature",
  "properties": {
    "iso:country":"GB",
    "sg:address":"Pakington St, Little Horton",
    "sg:city":"Bradford",
    "sg:classifiers":[
        {
            "category":"Place Of Worship",
            "type":"Public Place"
        }
    ],
    "sg:phone":"+44 1274 720299",
    "sg:postcode":"BD5 7LD",
    "sg:province":"West Yorkshire",
    "wof:name":"St. Josephs Church",
    "wof:placetype":"venue"
},
  "geometry": {"coordinates":[-1.759346,53.782494],"type":"Point"}
}