{
  "type": "Feature",
  "properties": {
    "addr:full":"New Century House Gateshead Tyne and Wear NE8 1HR",
    "addr:postcode":"ne8 1hr",
    "iso:country":"GB",
    "sg:address":"New Century House",
    "sg:city":"Gateshead",
    "sg:classifiers":[
        {
            "category":"Travel",
            "subcategory":"Travel Agent",
            "type":"Entertainment"
        }
    ],
    "sg:postcode":"NE8 1HR",
    "sg:province":"Tyne and Wear",
    "wof:name":"Travelcare",
    "wof:placetype":"venue"
},
  "geometry": {"coordinates":[-1.602046,54.96104],"type":"Point"}
}