{
  "type": "Feature",
  "properties": {
    "addr:full":"6 Clinton Road Redruth Cornwall TR15 2QE",
    "addr:housenumber":"6",
    "addr:postcode":"tr15 2qe",
    "addr:street":"Clinton Road",
    "iso:country":"GB",
    "sg:address":"6 Clinton Road",
    "sg:city":"Redruth",
    "sg:classifiers":[
        {
            "category":"Restaurant",
            "type":"Food & Drink"
        }
    ],
    "sg:phone":"+44 1209 210134",
    "sg:postcode":"TR15 2QE",
    "sg:province":"Cornwall",
    "wof:name":"Redruth Meadery",
    "wof:placetype":"venue"
},
  "geometry": {"coordinates":[-5.226041,50.231316],"type":"Point"}
}