{
  "type": "Feature",
  "properties": {
    "addr:full":"Dobella Lane, Rawcliffe Goole East Riding of Yorkshire DN14 8SQ",
    "addr:postcode":"dn14 8sq",
    "addr:street":"Dobella Lane",
    "iso:country":"GB",
    "sg:address":"Dobella Lane, Rawcliffe",
    "sg:city":"Goole",
    "sg:classifiers":[
        {
            "category":"Transit Center",
            "subcategory":"Passenger",
            "type":"Transportation"
        }
    ],
    "sg:phone":"+44 1405 839393",
    "sg:postcode":"DN14 8SQ",
    "sg:province":"East Riding of Yorkshire",
    "sg:tags":[
        "boarding",
        "kennel",
        "catteries"
    ],
    "wof:name":"West Pasture Boarding Kennels & Catteries",
    "wof:placetype":"venue"
},
  "geometry": {"coordinates":[-0.9627460241,53.6993980408],"type":"Point"}
}