{
  "type": "Feature",
  "properties": {
    "addr:full":"Rutland Chambers, 19 High Street Newmarket Cambridgeshire CB8 8LX",
    "addr:housenumber":"19",
    "addr:postcode":"cb8 8lx",
    "addr:street":"High Street",
    "iso:country":"GB",
    "sg:address":"Rutland Chambers, 19 High Street",
    "sg:city":"Newmarket",
    "sg:classifiers":[
        {
            "category":"Professional",
            "subcategory":"Employment Agencies",
            "type":"Services"
        }
    ],
    "sg:phone":"+44 1638 666495",
    "sg:postcode":"CB8 8LX",
    "sg:province":"Cambridgeshire",
    "sg:tags":[
        "consultant"
    ],
    "wof:name":"Bailey Fisher Recruitment Consultants Ltd.",
    "wof:placetype":"venue"
},
  "geometry": {"coordinates":[0.399165988,52.2498168945],"type":"Point"}
}