{
  "type": "Feature",
  "properties": {
    "iso:country":"GB",
    "sg:address":"91 Cousin La",
    "sg:city":"Halifax",
    "sg:classifiers":[
        {
            "category":"Social Services",
            "subcategory":"Child Care",
            "type":"Services"
        }
    ],
    "sg:phone":"+44 1422 244113",
    "sg:postcode":"HX2 8DQ",
    "sg:province":"West Yorkshire",
    "sg:tags":[
        "children's",
        "home"
    ],
    "wof:name":"Cousin Lane",
    "wof:placetype":"venue"
},
  "geometry": {"coordinates":[-1.890183,53.74202],"type":"Point"}
}