{
  "type": "Feature",
  "properties": {
    "iso:country":"GB",
    "sg:address":"5 Duke Street",
    "sg:city":"Chelmsford",
    "sg:classifiers":[
        {
            "category":"Shopping",
            "subcategory":"Jewelry",
            "type":"Retail Goods"
        },
        {
            "category":"Shopping",
            "subcategory":"Comic Books",
            "type":"Retail Goods"
        }
    ],
    "sg:phone":"+44 1245 352833",
    "sg:postcode":"CM1 1HL",
    "sg:province":"Essex",
    "sg:tags":[
        "jeweller",
        "sale",
        "jewellery"
    ],
    "wof:name":"Krafft Jewellers",
    "wof:placetype":"venue"
},
  "geometry": {"coordinates":[0.471383,51.735195],"type":"Point"}
}