{
  "type": "Feature",
  "properties": {
    "iso:country":"GB",
    "sg:address":"White House Farm, Valley Lane, Long Bennington",
    "sg:city":"Newark",
    "sg:classifiers":[
        {
            "category":"Farming",
            "subcategory":"Livestock Farm",
            "type":"Manufacturing & Wholesale Goods"
        },
        {
            "category":"Utilities",
            "subcategory":"Natural Gas",
            "type":"Services"
        }
    ],
    "sg:postcode":"NG23 5EE",
    "sg:province":"Lincolnshire",
    "sg:tags":[
        "supplier",
        "others"
    ],
    "wof:name":"Grantham & Newark Bottled Gas",
    "wof:placetype":"venue"
},
  "geometry": {"coordinates":[-0.758644,52.994484],"type":"Point"}
}