{
  "type": "Feature",
  "properties": {
    "iso:country":"GB",
    "sg:address":"Redcross Way",
    "sg:city":"London",
    "sg:classifiers":[
        {
            "category":"Education",
            "subcategory":"School",
            "type":"Public Place"
        }
    ],
    "sg:postcode":"SE1 1TD",
    "sg:province":"Greater London",
    "sg:tags":[
        "local",
        "authority"
    ],
    "wof:name":"Cathedral (Va) School of St.Saviour & St.Mary Overie",
    "wof:placetype":"venue"
},
  "geometry": {"coordinates":[-0.094869,51.502335],"type":"Point"}
}