{
  "type": "Feature",
  "properties": {
    "addr:full":"88 High Road, Byfleet West Byfleet Surrey KT14 7QW",
    "addr:housenumber":"88",
    "addr:postcode":"kt14 7qw",
    "addr:street":"High Road;West Byfleet",
    "iso:country":"GB",
    "sg:address":"88 High Road, Byfleet",
    "sg:city":"West Byfleet",
    "sg:classifiers":[
        {
            "category":"Building & Trades",
            "subcategory":"Cleaning & Sanitation",
            "type":"Services"
        }
    ],
    "sg:postcode":"KT14 7QW",
    "sg:province":"Surrey",
    "sg:tags":[
        "commercial"
    ],
    "wof:name":"Ace Cleaning",
    "wof:placetype":"venue"
},
  "geometry": {"coordinates":[-0.475904,51.339031],"type":"Point"}
}