{
  "type": "Feature",
  "properties": {
    "iso:country":"GB",
    "sg:address":"2 Ptarmigan Place, Attleborough Fields Industrial Estate",
    "sg:city":"Nuneaton",
    "sg:classifiers":[
        {
            "category":"Professional",
            "type":"Services"
        },
        {
            "category":"Professional",
            "subcategory":"Business Services",
            "type":"Services"
        },
        {
            "category":"Professional",
            "subcategory":"Testing Lab",
            "type":"Services"
        }
    ],
    "sg:phone":"+44 24 7632 6362",
    "sg:postcode":"CV11 6RX",
    "sg:province":"Leicestershire",
    "sg:tags":[
        "equipment",
        "inspection",
        "assessment",
        "quality",
        "calibration"
    ],
    "wof:name":"Harris Gauges",
    "wof:placetype":"venue"
},
  "geometry": {"coordinates":[-1.4478219748,52.5193595886],"type":"Point"}
}