{
  "type": "Feature",
  "properties": {
    "addr:full":"3a Cricket St Business Centre, Cricket Street Wigan Lancashire WN6 7TP",
    "addr:housenumber":"3a",
    "addr:postcode":"wn6 7tp",
    "addr:street":"Cricket St;Cricket Street",
    "iso:country":"GB",
    "sg:address":"3a Cricket St Business Centre, Cricket Street",
    "sg:city":"Wigan",
    "sg:classifiers":[
        {
            "category":"Building & Trades",
            "subcategory":"Construction",
            "type":"Services"
        }
    ],
    "sg:phone":"+44 1942 820131",
    "sg:postcode":"WN6 7TP",
    "sg:province":"Lancashire",
    "sg:tags":[
        "roofing"
    ],
    "wof:name":"Clydesdale Roofing Supplies (Leyland) Ltd.",
    "wof:placetype":"venue"
},
  "geometry": {"coordinates":[-2.642259,53.545719],"type":"Point"}
}