{
  "type": "Feature",
  "properties": {
    "iso:country":"GB",
    "sg:address":"5 Donview Road",
    "sg:city":"Aberdeen",
    "sg:classifiers":[
        {
            "category":"Banks & Credit Unions",
            "subcategory":"Financial Services",
            "type":"Services"
        }
    ],
    "sg:postcode":"AB24 2SH",
    "sg:province":"Aberdeen City",
    "sg:tags":[
        "adviser"
    ],
    "wof:name":"Grandholm Financial Services",
    "wof:placetype":"venue"
},
  "geometry": {"coordinates":[-2.12512,57.172302],"type":"Point"}
}