{
  "type": "Feature",
  "properties": {
    "iso:country":"GB",
    "sg:address":"84 Burncross Road",
    "sg:city":"Sheffield",
    "sg:classifiers":[
        {
            "category":"Fast Food",
            "type":"Food & Drink"
        }
    ],
    "sg:phone":"+44 114 246 9004",
    "sg:postcode":"S35 1SF",
    "sg:province":"South Yorkshire",
    "sg:tags":[
        "away",
        "take"
    ],
    "wof:name":"Greenhead House Restaurant",
    "wof:placetype":"venue"
},
  "geometry": {"coordinates":[-1.4710689783,53.462020874],"type":"Point"}
}