{
  "type": "Feature",
  "properties": {
    "addr:full":"Unit 6a Cardrew Indstl Est Redruth Cornwall TR15 1SS",
    "addr:housenumber":"unit 6a",
    "addr:postcode":"tr15 1ss",
    "addr:street":"Cardrew Indstl Est",
    "iso:country":"GB",
    "sg:address":"Unit 6a Cardrew Indstl Est",
    "sg:city":"Redruth",
    "sg:classifiers":[
        {
            "category":"Personal",
            "type":"Services"
        }
    ],
    "sg:phone":"+44 1209 313888",
    "sg:postcode":"TR15 1SS",
    "sg:province":"Cornwall",
    "sg:tags":[
        "delivery"
    ],
    "wof:name":"Johnson",
    "wof:placetype":"venue"
},
  "geometry": {"coordinates":[-5.2229938507,50.238609314],"type":"Point"}
}