{
  "type": "Feature",
  "properties": {
    "addr:full":"42 Yarmouth Rd Norwich Norfolk NR7 0EQ",
    "addr:housenumber":"42",
    "addr:postcode":"nr7 0eq",
    "addr:street":"Yarmouth Rd",
    "iso:country":"GB",
    "sg:address":"42 Yarmouth Rd",
    "sg:city":"Norwich",
    "sg:classifiers":[
        {
            "category":"Professional",
            "subcategory":"Lawyer & Legal Services",
            "type":"Services"
        }
    ],
    "sg:phone":"+44 1603 300425",
    "sg:postcode":"NR7 0EQ",
    "sg:province":"Norfolk",
    "sg:tags":[
        "solicitor"
    ],
    "wof:name":"B Mitchels",
    "wof:placetype":"venue"
},
  "geometry": {"coordinates":[1.338391,52.626083],"type":"Point"}
}