{
  "type": "Feature",
  "properties": {
    "addr:full":"265 Burlington Rd New Malden Surrey KT3 4NE",
    "addr:housenumber":"265",
    "addr:postcode":"kt3 4ne",
    "addr:street":"Burlington Rd",
    "iso:country":"GB",
    "sg:address":"265 Burlington Rd",
    "sg:city":"New Malden",
    "sg:classifiers":[
        {
            "category":"Communications",
            "type":"Services"
        }
    ],
    "sg:phone":"+44 20 8286 5170",
    "sg:postcode":"KT3 4NE",
    "sg:province":"Surrey",
    "sg:tags":[
        "audio-visual"
    ],
    "wof:name":"Kinexus Ltd",
    "wof:placetype":"venue"
},
  "geometry": {"coordinates":[-0.238484,51.400532],"type":"Point"}
}