{
  "type": "Feature",
  "properties": {
    "iso:country":"GB",
    "sg:address":"Po Box 765",
    "sg:city":"Chelmsford",
    "sg:classifiers":[
        {
            "category":"Communications",
            "type":"Services"
        }
    ],
    "sg:phone":"+44 1245 616000",
    "sg:postcode":"CM2 9XB",
    "sg:province":"Essex",
    "sg:tags":[
        "broadcasting"
    ],
    "wof:name":"Essex",
    "wof:placetype":"venue"
},
  "geometry": {"coordinates":[0.475699991,51.7225112915],"type":"Point"}
}