{
  "type": "Feature",
  "properties": {
    "iso:country":"GB",
    "sg:address":"95 Maple Road",
    "sg:city":"Dartford",
    "sg:classifiers":[
        {
            "category":"Building & Trades",
            "subcategory":"Pest Control",
            "type":"Services"
        }
    ],
    "sg:phone":"+44 1322 408901",
    "sg:postcode":"DA1 2QY",
    "sg:province":"Kent",
    "sg:tags":[
        "vermin"
    ],
    "wof:name":"A 1 Pest Control",
    "wof:placetype":"venue"
},
  "geometry": {"coordinates":[0.207369,51.436794],"type":"Point"}
}