{
  "type": "Feature",
  "properties": {
    "addr:full":"1 Sparrows Green Road, Sparrows Grn Wadhurst East Sussex TN5 6ST",
    "addr:housenumber":"1",
    "addr:postcode":"tn5 6st",
    "addr:street":"Sparrows Green Road Sparrows Grn",
    "iso:country":"GB",
    "sg:address":"1 Sparrows Green Road, Sparrows Grn",
    "sg:city":"Wadhurst",
    "sg:classifiers":[
        {
            "category":"Retail",
            "subcategory":"Auto Repair",
            "type":"Services"
        }
    ],
    "sg:postcode":"TN5 6ST",
    "sg:province":"East Sussex",
    "sg:tags":[
        "modification",
        "garage"
    ],
    "wof:name":"Ben Greig Motors Ltd.",
    "wof:placetype":"venue"
},
  "geometry": {"coordinates":[0.3331130147,51.0658454895],"type":"Point"}
}