{
  "type": "Feature",
  "properties": {
    "iso:country":"GB",
    "sg:address":"Deansbrook, Brookfield Lane West, Cheshunt",
    "sg:city":"Waltham Cross",
    "sg:classifiers":[
        {
            "category":"Professional",
            "subcategory":"Accounting & Tax Preparation",
            "type":"Services"
        }
    ],
    "sg:phone":"+44 1992 635113",
    "sg:postcode":"EN8 0QY",
    "sg:province":"Essex",
    "sg:tags":[
        "accountant"
    ],
    "wof:name":"John H Viner & Co",
    "wof:placetype":"venue"
},
  "geometry": {"coordinates":[-0.039877,51.714806],"type":"Point"}
}