{
  "type": "Feature",
  "properties": {
    "addr:full":"Ymca, 50-52 Talbot Road Port Talbot Neath Port Talbot SA13 1HU",
    "addr:housenumber":"50-52",
    "addr:postcode":"sa13 1hu",
    "addr:street":"Talbot Road",
    "iso:country":"GB",
    "sg:address":"Ymca, 50-52 Talbot Road",
    "sg:city":"Port Talbot",
    "sg:classifiers":[
        {
            "category":"Professional",
            "subcategory":"Management & Consulting",
            "type":"Services"
        }
    ],
    "sg:phone":"+44 1639 894420",
    "sg:postcode":"SA13 1HU",
    "sg:province":"Neath Port Talbot",
    "sg:tags":[
        "consultant",
        "training"
    ],
    "wof:name":"Accents Training Systems Ltd.",
    "wof:placetype":"venue"
},
  "geometry": {"coordinates":[-3.777780056,51.5902900696],"type":"Point"}
}