{
  "type": "Feature",
  "properties": {
    "addr:full":"34 Outend Isle Of Scalpay Eilean Siar HS4 3YG",
    "addr:housenumber":"34",
    "addr:postcode":"hs4 3yg",
    "addr:street":"Outend Isle",
    "iso:country":"GB",
    "sg:address":"34 Outend",
    "sg:city":"Isle Of Scalpay",
    "sg:classifiers":[
        {
            "category":"Recreation",
            "subcategory":"Water Park",
            "type":"Entertainment"
        }
    ],
    "sg:phone":"+44 1859 540328",
    "sg:postcode":"HS4 3YG",
    "sg:province":"Eilean Siar",
    "sg:tags":[
        "sport"
    ],
    "wof:name":"Scalpay Diving Services",
    "wof:placetype":"venue"
},
  "geometry": {"coordinates":[-6.6960120201,57.8696670532],"type":"Point"}
}