{
  "type": "Feature",
  "properties": {
    "addr:full":"Unit 4, Diamond Court Airport Ind Est Newcastle Upon Tyne Tyne and Wear NE3 2EN",
    "addr:housenumber":"unit 4",
    "addr:postcode":"ne3 2en",
    "addr:street":"Diamond Court",
    "iso:country":"GB",
    "sg:address":"Unit 4, Diamond Court Airport Ind Est",
    "sg:city":"Newcastle Upon Tyne",
    "sg:classifiers":[
        {
            "category":"Professional",
            "subcategory":"Detective & Security Services",
            "type":"Services"
        }
    ],
    "sg:phone":"+44 191 286 3097",
    "sg:postcode":"NE3 2EN",
    "sg:province":"Tyne and Wear",
    "wof:name":"Swift Response",
    "wof:placetype":"venue"
},
  "geometry": {"coordinates":[-1.662001,55.012703],"type":"Point"}
}