{
  "type": "Feature",
  "properties": {
    "iso:country":"GB",
    "sg:address":"360 York Road",
    "sg:city":"Leeds",
    "sg:classifiers":[
        {
            "category":"Bars & Pubs",
            "type":"Food & Drink"
        }
    ],
    "sg:phone":"+44 113 216 4111",
    "sg:postcode":"LS9 9DN",
    "sg:province":"West Yorkshire",
    "sg:tags":[
        "pubs",
        "house",
        "inn",
        "public",
        "activity"
    ],
    "wof:name":"White Horse Pub",
    "wof:placetype":"venue"
},
  "geometry": {"coordinates":[-1.507904,53.798916],"type":"Point"}
}