{
  "type": "Feature",
  "properties": {
    "iso:country":"GB",
    "sg:address":"21 Augusta Street, Hockley",
    "sg:city":"Birmingham",
    "sg:classifiers":[
        {
            "category":"Professional",
            "subcategory":"Computer Services",
            "type":"Services"
        }
    ],
    "sg:postcode":"B18 6JA",
    "sg:province":"West Midlands",
    "sg:tags":[
        "system",
        "software"
    ],
    "wof:name":"Micronet Ltd.",
    "wof:placetype":"venue"
},
  "geometry": {"coordinates":[-1.909934,52.487682],"type":"Point"}
}