{
  "type": "Feature",
  "properties": {
    "addr:full":"35 Post Street, Godmanchester Huntingdon Cambridgeshire PE29 2AQ",
    "addr:housenumber":"35",
    "addr:postcode":"pe29 2aq",
    "addr:street":"Post Street",
    "iso:country":"GB",
    "sg:address":"35 Post Street, Godmanchester",
    "sg:city":"Huntingdon",
    "sg:classifiers":[
        {
            "category":"Building & Trades",
            "subcategory":"Construction",
            "type":"Services"
        }
    ],
    "sg:postcode":"PE29 2AQ",
    "sg:province":"Cambridgeshire",
    "sg:tags":[
        "builder"
    ],
    "wof:name":"C & S Builders",
    "wof:placetype":"venue"
},
  "geometry": {"coordinates":[-0.1758369952,52.3219261169],"type":"Point"}
}