{
  "type": "Feature",
  "properties": {
    "iso:country":"GB",
    "sg:address":"Disos Business Centre, 50 Springfield Rd",
    "sg:city":"Cheadle",
    "sg:classifiers":[
        {
            "category":"Education",
            "subcategory":"School",
            "type":"Public Place"
        }
    ],
    "sg:phone":"+44 161 428 7666",
    "sg:postcode":"SK8 4PF",
    "sg:province":"Cheshire",
    "sg:tags":[
        "private",
        "tuition"
    ],
    "wof:name":"Business Studies Economics",
    "wof:placetype":"venue"
},
  "geometry": {"coordinates":[-2.212272,53.395248],"type":"Point"}
}