{
  "type": "Feature",
  "properties": {
    "addr:full":"89 Boutport St Barnstaple Devon EX31 1SX",
    "addr:housenumber":"89",
    "addr:postcode":"ex31 1sx",
    "addr:street":"Boutport St",
    "iso:country":"GB",
    "sg:address":"89 Boutport St",
    "sg:city":"Barnstaple",
    "sg:classifiers":[
        {
            "category":"Food & Beverages",
            "subcategory":"Meat & Fish",
            "type":"Retail Goods"
        }
    ],
    "sg:postcode":"EX31 1SX",
    "sg:province":"Devon",
    "sg:tags":[
        "butcher"
    ],
    "wof:name":"Gratton,D A,",
    "wof:placetype":"venue"
},
  "geometry": {"coordinates":[-4.05829,51.079967],"type":"Point"}
}