{
  "type": "Feature",
  "properties": {
    "addr:full":"283 Camberwell New Rd Camberwell Greater London SE5 0TF",
    "addr:housenumber":"283",
    "addr:postcode":"se5 0tf",
    "addr:street":"Camberwell New Rd",
    "iso:country":"GB",
    "sg:address":"283 Camberwell New Rd",
    "sg:city":"Camberwell",
    "sg:classifiers":[
        {
            "category":"Bars & Pubs",
            "type":"Food & Drink"
        }
    ],
    "sg:phone":"+44 20 7703 0260",
    "sg:postcode":"SE5 0TF",
    "sg:province":"Greater London",
    "sg:tags":[
        "pubs",
        "inn"
    ],
    "wof:name":"King William IV",
    "wof:placetype":"venue"
},
  "geometry": {"coordinates":[-0.098135,51.476158],"type":"Point"}
}