{
  "type": "Feature",
  "properties": {
    "iso:country":"GB",
    "sg:address":"Lakeside Farm, Three Mile Lane, Whitmore",
    "sg:city":"Newcastle",
    "sg:classifiers":[
        {
            "category":"Manufacturing",
            "subcategory":"Wood Products",
            "type":"Manufacturing & Wholesale Goods"
        }
    ],
    "sg:phone":"+44 1782 680508",
    "sg:postcode":"ST5 5HW",
    "sg:province":"Staffordshire",
    "sg:tags":[
        "maker",
        "cabinet"
    ],
    "wof:name":"Redmond Kemp",
    "wof:placetype":"venue"
},
  "geometry": {"coordinates":[-2.290187,52.983021],"type":"Point"}
}