{
  "type": "Feature",
  "properties": {
    "addr:full":"Carsegate Ho, Glendoe Terr Inverness Highland IV3 6ED",
    "addr:postcode":"iv3 6ed",
    "addr:street":"Carsegate;Glendoe Terr",
    "iso:country":"GB",
    "sg:address":"Carsegate Ho, Glendoe Terr",
    "sg:city":"Inverness",
    "sg:classifiers":[
        {
            "category":"Government",
            "subcategory":"Office",
            "type":"Public Place"
        }
    ],
    "sg:phone":"+44 1463 724040",
    "sg:postcode":"IV3 6ED",
    "sg:province":"Highland",
    "sg:tags":[
        "local"
    ],
    "wof:name":"Criminal Justice Service",
    "wof:placetype":"venue"
},
  "geometry": {"coordinates":[-4.235612,57.479015],"type":"Point"}
}