{
  "type": "Feature",
  "properties": {
    "iso:country":"GB",
    "sg:address":"Guisborough Hall",
    "sg:city":"Guisborough",
    "sg:classifiers":[
        {
            "category":"Travel",
            "subcategory":"Hotels & Motels",
            "type":"Entertainment"
        }
    ],
    "sg:phone":"+44 1287 634533",
    "sg:postcode":"TS14 6PT",
    "sg:province":"North Yorkshire",
    "wof:name":"Guisborough Hotels Ltd.",
    "wof:placetype":"venue"
},
  "geometry": {"coordinates":[-1.0522840023,54.5356369019],"type":"Point"}
}