{
  "type": "Feature",
  "properties": {
    "iso:country":"GB",
    "sg:address":"The Jays, Light Oaks Lane, Glazebury",
    "sg:city":"Warrington",
    "sg:classifiers":[
        {
            "category":"Bus Charters",
            "type":"Transportation"
        }
    ],
    "sg:phone":"+44 1925 766465",
    "sg:postcode":"WA3 5LH",
    "sg:province":"Cheshire",
    "sg:tags":[
        "coach"
    ],
    "wof:name":"Jim Stones Coaches",
    "wof:placetype":"venue"
},
  "geometry": {"coordinates":[-2.4950480461,53.4717559814],"type":"Point"}
}