{
  "type": "Feature",
  "properties": {
    "iso:country":"GB",
    "sg:address":"115 Craven Park Road",
    "sg:city":"London",
    "sg:classifiers":[
        {
            "category":"Real Estate",
            "subcategory":"Real Estate Agent",
            "type":"Services"
        }
    ],
    "sg:postcode":"N15 6BL",
    "sg:province":"Greater London",
    "wof:name":"Empire Estates Ltd",
    "wof:placetype":"venue"
},
  "geometry": {"coordinates":[-0.0657510012,51.5770072937],"type":"Point"}
}