{
  "type": "Feature",
  "properties": {
    "iso:country":"GB",
    "sg:address":"56-58 St Marys St",
    "sg:city":"Edinburgh",
    "sg:classifiers":[
        {
            "category":"Restaurant",
            "type":"Food & Drink"
        }
    ],
    "sg:phone":"+44 131 556 5888",
    "sg:postcode":"EH1 1SX",
    "sg:province":"City of Edinburgh",
    "wof:name":"Bonars At L'Auberge",
    "wof:placetype":"venue"
},
  "geometry": {"coordinates":[-3.188509,55.949169],"type":"Point"}
}