{
  "type": "Feature",
  "properties": {
    "addr:full":"50 Knapton Lane, Haycombe York North Yorkshire YO26 5PU",
    "addr:housenumber":"50",
    "addr:postcode":"yo26 5pu",
    "addr:street":"Knapton Lane",
    "iso:country":"GB",
    "sg:address":"50 Knapton Lane, Haycombe",
    "sg:city":"York",
    "sg:classifiers":[
        {
            "category":"Utilities",
            "subcategory":"Refuse",
            "type":"Services"
        }
    ],
    "sg:phone":"+44 1904 782811",
    "sg:postcode":"YO26 5PU",
    "sg:province":"North Yorkshire",
    "sg:tags":[
        "skip",
        "hire"
    ],
    "wof:name":"Dial A Skip",
    "wof:placetype":"venue"
},
  "geometry": {"coordinates":[-1.138351,53.958366],"type":"Point"}
}