{
  "type": "Feature",
  "properties": {
    "iso:country":"GB",
    "sg:address":"Freeholme, White Shack Lane, Chandlers Cross",
    "sg:city":"Rickmansworth",
    "sg:classifiers":[
        {
            "category":"Building & Trades",
            "subcategory":"Construction",
            "type":"Services"
        }
    ],
    "sg:phone":"+44 1923 263100",
    "sg:postcode":"WD3 4ND",
    "sg:province":"Hertfordshire",
    "sg:tags":[
        "builder"
    ],
    "wof:name":"Northovers Ltd.",
    "wof:placetype":"venue"
},
  "geometry": {"coordinates":[-0.459422,51.672665],"type":"Point"}
}