{
  "type": "Feature",
  "properties": {
    "addr:full":"90 Carmoor Road Manchester Greater Manchester M13 0FB",
    "addr:housenumber":"90",
    "addr:postcode":"m13 0fb",
    "addr:street":"Carmoor Road",
    "iso:country":"GB",
    "sg:address":"90 Carmoor Road",
    "sg:city":"Manchester",
    "sg:classifiers":[
        {
            "category":"Retail",
            "subcategory":"Emissions Testing",
            "type":"Services"
        },
        {
            "category":"Professional",
            "subcategory":"Testing Lab",
            "type":"Services"
        }
    ],
    "sg:phone":"+44 161 224 0648",
    "sg:postcode":"M13 0FB",
    "sg:province":"Greater Manchester",
    "sg:tags":[
        "mot"
    ],
    "wof:name":"Pat Rafter Garages",
    "wof:placetype":"venue"
},
  "geometry": {"coordinates":[-2.221009016,53.461643219],"type":"Point"}
}