{
  "type": "Feature",
  "properties": {
    "addr:full":"38 Coxley Crescent, Netherton Wakefield West Yorkshire WF4 4LR",
    "addr:housenumber":"38",
    "addr:postcode":"wf4 4lr",
    "addr:street":"Coxley Crescent;West",
    "iso:country":"GB",
    "sg:address":"38 Coxley Crescent, Netherton",
    "sg:city":"Wakefield",
    "sg:classifiers":[
        {
            "category":"Health Services",
            "subcategory":"Health Practitioner",
            "type":"Services"
        }
    ],
    "sg:phone":"+44 1924 277081",
    "sg:postcode":"WF4 4LR",
    "sg:province":"West Yorkshire",
    "sg:tags":[
        "hypnotherapists"
    ],
    "wof:name":"Barrington Bennet John",
    "wof:placetype":"venue"
},
  "geometry": {"coordinates":[-1.58218,53.650906],"type":"Point"}
}