{
  "type": "Feature",
  "properties": {
    "addr:full":"21 Great Bank Road Rotherham South Yorkshire S65 3BT",
    "addr:housenumber":"21",
    "addr:postcode":"s65 3bt",
    "addr:street":"Great Bank Road",
    "iso:country":"GB",
    "sg:address":"21 Great Bank Road",
    "sg:city":"Rotherham",
    "sg:classifiers":[
        {
            "category":"Home & Garden",
            "subcategory":"Home Furnishings",
            "type":"Retail Goods"
        }
    ],
    "sg:phone":"+44 1709 837352",
    "sg:postcode":"S65 3BT",
    "sg:province":"South Yorkshire",
    "sg:tags":[
        "awning",
        "canopy",
        "blinds"
    ],
    "wof:name":"Derek Stacey",
    "wof:placetype":"venue"
},
  "geometry": {"coordinates":[-1.318647,53.419914],"type":"Point"}
}