{
  "type": "Feature",
  "properties": {
    "addr:full":"Pentney Road, Narborough King's Lynn Norfolk PE32 1TE",
    "addr:postcode":"pe32 1te",
    "addr:street":"Pentney Road;Lynn",
    "iso:country":"GB",
    "sg:address":"Pentney Road, Narborough",
    "sg:city":"King's Lynn",
    "sg:classifiers":[
        {
            "category":"Building & Trades",
            "subcategory":"Construction",
            "type":"Services"
        }
    ],
    "sg:phone":"+44 1760 337424",
    "sg:postcode":"PE32 1TE",
    "sg:province":"Norfolk",
    "sg:tags":[
        "builder"
    ],
    "wof:name":"Veltshaw Builders Ltd",
    "wof:placetype":"venue"
},
  "geometry": {"coordinates":[0.5838800073,52.6873283386],"type":"Point"}
}