{
  "type": "Feature",
  "properties": {
    "addr:full":"339 Cannock Road Wolverhampton Staffordshire WV10 0BG",
    "addr:housenumber":"339",
    "addr:postcode":"wv10 0bg",
    "addr:street":"Cannock Road",
    "iso:country":"GB",
    "sg:address":"339 Cannock Road",
    "sg:city":"Wolverhampton",
    "sg:classifiers":[
        {
            "category":"Cinema",
            "subcategory":"Movie Rental",
            "type":"Entertainment"
        }
    ],
    "sg:phone":"+44 1902 450722",
    "sg:postcode":"WV10 0BG",
    "sg:province":"Staffordshire",
    "sg:tags":[
        "video",
        "library"
    ],
    "wof:name":"Stars Video & Recording Studio",
    "wof:placetype":"venue"
},
  "geometry": {"coordinates":[-2.1127870083,52.5971908569],"type":"Point"}
}