{
  "type": "Feature",
  "properties": {
    "addr:full":"13 York Place, London Rd Brighton East Sussex BN1 4GU",
    "addr:housenumber":"13",
    "addr:postcode":"bn1 4gu",
    "addr:street":"York Place London Rd",
    "iso:country":"GB",
    "sg:address":"13 York Place, London Rd",
    "sg:city":"Brighton",
    "sg:classifiers":[
        {
            "category":"Fast Food",
            "type":"Food & Drink"
        }
    ],
    "sg:phone":"+44 1273 700733",
    "sg:postcode":"BN1 4GU",
    "sg:province":"East Sussex",
    "sg:tags":[
        "away",
        "take"
    ],
    "wof:name":"Uncle Sams Hamburger Express",
    "wof:placetype":"venue"
},
  "geometry": {"coordinates":[-0.1357180029,50.8284034729],"type":"Point"}
}