{
  "type": "Feature",
  "properties": {
    "iso:country":"GB",
    "sg:address":"Dyffryn Marlais, Llanboidy",
    "sg:city":"Whitland",
    "sg:classifiers":[
        {
            "category":"Professional",
            "subcategory":"Management & Consulting",
            "type":"Services"
        }
    ],
    "sg:phone":"+44 1994 448644",
    "sg:postcode":"SA34 0ER",
    "sg:province":"Carmarthenshire",
    "sg:tags":[
        "sport"
    ],
    "wof:name":"R S E Sports Management",
    "wof:placetype":"venue"
},
  "geometry": {"coordinates":[-4.612054,51.819256],"type":"Point"}
}