{
  "type": "Feature",
  "properties": {
    "addr:full":"Glasgow Rd, Kilsyth Glasgow East Dunbartonshire G65 9BL",
    "addr:postcode":"g65 9bl",
    "addr:street":"Glasgow Rd",
    "iso:country":"GB",
    "sg:address":"Glasgow Rd, Kilsyth",
    "sg:city":"Glasgow",
    "sg:classifiers":[
        {
            "category":"Mining & Drilling",
            "type":"Manufacturing & Wholesale Goods"
        }
    ],
    "sg:phone":"+44 1236 822666",
    "sg:postcode":"G65 9BL",
    "sg:province":"East Dunbartonshire",
    "sg:tags":[
        "contractor"
    ],
    "wof:name":"Nuttall,Edmund,Ltd",
    "wof:placetype":"venue"
},
  "geometry": {"coordinates":[-4.0818681717,55.9750099182],"type":"Point"}
}