{
  "type": "Feature",
  "properties": {
    "iso:country":"GB",
    "sg:address":"1 Quay Ct, Bull La",
    "sg:city":"St Ives",
    "sg:classifiers":[
        {
            "category":"Shopping",
            "subcategory":"Clothing, Apparel, & Fashions",
            "type":"Retail Goods"
        }
    ],
    "sg:postcode":"PE27 5AU",
    "sg:province":"Cambridgeshire",
    "sg:tags":[
        "ladieswear"
    ],
    "wof:name":"Clarke,J,",
    "wof:placetype":"venue"
},
  "geometry": {"coordinates":[-0.074364,52.323093],"type":"Point"}
}