{
  "type": "Feature",
  "properties": {
    "addr:full":"Twycross, Norton Juxta Twycross Atherstone Leicestershire CV9 3QF",
    "addr:housenumber":"twycross",
    "addr:postcode":"cv9 3qf",
    "addr:street":"Norton;Leicestershire",
    "iso:country":"GB",
    "sg:address":"Twycross, Norton Juxta Twycross",
    "sg:city":"Atherstone",
    "sg:classifiers":[
        {
            "category":"Farming",
            "subcategory":"Livestock Farm",
            "type":"Manufacturing & Wholesale Goods"
        }
    ],
    "sg:phone":"+44 1827 880373",
    "sg:postcode":"CV9 3QF",
    "sg:province":"Leicestershire",
    "sg:tags":[
        "others"
    ],
    "wof:name":"P S & M Greenfield",
    "wof:placetype":"venue"
},
  "geometry": {"coordinates":[-1.5055530071,52.6425247192],"type":"Point"}
}