{
  "type": "Feature",
  "properties": {
    "iso:country":"GB",
    "sg:address":"Mill Farm, Charlton Road",
    "sg:city":"Hitchin",
    "sg:classifiers":[
        {
            "category":"Farming",
            "subcategory":"Livestock Farm",
            "type":"Manufacturing & Wholesale Goods"
        }
    ],
    "sg:postcode":"SG5 2AB",
    "sg:province":"Bedfordshire",
    "sg:tags":[
        "others"
    ],
    "wof:name":"L Gray",
    "wof:placetype":"venue"
},
  "geometry": {"coordinates":[-0.284408,51.952435],"type":"Point"}
}