{
  "type": "Feature",
  "properties": {
    "addr:full":"379 Cowley Rd Oxford Oxfordshire OX4 2BS",
    "addr:housenumber":"379",
    "addr:postcode":"ox4 2bs",
    "addr:street":"Cowley Rd",
    "iso:country":"GB",
    "sg:address":"379 Cowley Rd",
    "sg:city":"Oxford",
    "sg:classifiers":[
        {
            "category":"Home & Garden",
            "subcategory":"Hardware",
            "type":"Retail Goods"
        }
    ],
    "sg:phone":"+44 1865 773333",
    "sg:postcode":"OX4 2BS",
    "sg:province":"Oxfordshire",
    "sg:tags":[
        "part",
        "accessory"
    ],
    "wof:name":"George White Superbike Centre",
    "wof:placetype":"venue"
},
  "geometry": {"coordinates":[-1.225131,51.741619],"type":"Point"}
}