{
  "type": "Feature",
  "properties": {
    "iso:country":"GB",
    "sg:address":"56 Market Street",
    "sg:city":"Wigan",
    "sg:classifiers":[
        {
            "category":"Home & Garden",
            "subcategory":"Carpets & Floor Coverings",
            "type":"Retail Goods"
        }
    ],
    "sg:phone":"+44 1942 45625",
    "sg:postcode":"WN1 1HY",
    "sg:province":"Lancashire",
    "sg:tags":[
        "carpets",
        "rug",
        "matting"
    ],
    "wof:name":"G & G Carpets (Wigan) Ltd.",
    "wof:placetype":"venue"
},
  "geometry": {"coordinates":[-2.633534,53.547649],"type":"Point"}
}