{
  "type": "Feature",
  "properties": {
    "addr:full":"Anerley Site, William Booth Rd London Greater London SE20 8BW",
    "addr:postcode":"se20 8bw",
    "addr:street":"William Booth Rd",
    "iso:country":"GB",
    "sg:address":"Anerley Site, William Booth Rd",
    "sg:city":"London",
    "sg:classifiers":[
        {
            "category":"Government",
            "subcategory":"Office",
            "type":"Public Place"
        }
    ],
    "sg:postcode":"SE20 8BW",
    "sg:province":"Greater London",
    "sg:tags":[
        "education",
        "agency",
        "authority"
    ],
    "wof:name":"London Borough of Bromley Council",
    "wof:placetype":"venue"
},
  "geometry": {"coordinates":[-0.069514,51.412544],"type":"Point"}
}