{
  "type": "Feature",
  "properties": {
    "addr:full":"100 Raeburn Place Edinburgh City of Edinburgh EH4 1HH",
    "addr:housenumber":"100",
    "addr:postcode":"eh4 1hh",
    "addr:street":"Raeburn Place Edinburgh",
    "iso:country":"GB",
    "sg:address":"100 Raeburn Place",
    "sg:city":"Edinburgh",
    "sg:classifiers":[
        {
            "category":"Building & Trades",
            "subcategory":"Equipment Rental",
            "type":"Services"
        }
    ],
    "sg:phone":"+44 131 315 3020",
    "sg:postcode":"EH4 1HH",
    "sg:province":"City of Edinburgh",
    "sg:tags":[
        "supply"
    ],
    "wof:name":"Beadnik",
    "wof:placetype":"venue"
},
  "geometry": {"coordinates":[-3.212444067,55.9590682983],"type":"Point"}
}