{
  "type": "Feature",
  "properties": {
    "addr:full":"Ty Gwyn, Nantmawr Oswestry Shropshire SY10 9EG",
    "addr:postcode":"sy10 9eg",
    "iso:country":"GB",
    "sg:address":"Ty Gwyn, Nantmawr",
    "sg:city":"Oswestry",
    "sg:classifiers":[
        {
            "category":"Farming",
            "subcategory":"Farm",
            "type":"Manufacturing & Wholesale Goods"
        }
    ],
    "sg:phone":"+44 1691 828367",
    "sg:postcode":"SY10 9EG",
    "sg:province":"Shropshire",
    "sg:tags":[
        "mixed",
        "crop"
    ],
    "wof:name":"A R Evison",
    "wof:placetype":"venue"
},
  "geometry": {"coordinates":[-3.115618,52.812225],"type":"Point"}
}