{
  "type": "Feature",
  "properties": {
    "addr:full":"The Lilla Huset, 191 Talgarth Road London Greater London W6 8BJ",
    "addr:housenumber":"191",
    "addr:postcode":"w6 8bj",
    "addr:street":"Talgarth Road",
    "iso:country":"GB",
    "sg:address":"The Lilla Huset, 191 Talgarth Road",
    "sg:city":"London",
    "sg:classifiers":[
        {
            "category":"Education",
            "subcategory":"Special Training",
            "type":"Public Place"
        }
    ],
    "sg:phone":"+44 20 8748 3352",
    "sg:postcode":"W6 8BJ",
    "sg:province":"Greater London",
    "sg:tags":[
        "product",
        "centre"
    ],
    "wof:name":"Hammersmith & Fulham Business Resources Ltd.",
    "wof:placetype":"venue"
},
  "geometry": {"coordinates":[-0.2220660001,51.4911842346],"type":"Point"}
}