{
  "type": "Feature",
  "properties": {
    "iso:country":"GB",
    "sg:address":"Romney Lodge, Alton Grn, Lower Holbrook",
    "sg:city":"Ipswich",
    "sg:classifiers":[
        {
            "category":"Taxi",
            "type":"Transportation"
        },
        {
            "category":"Military Area",
            "subcategory":"Air Force Base",
            "type":"Public Place"
        }
    ],
    "sg:postcode":"IP9 2RN",
    "sg:province":"Suffolk",
    "sg:tags":[
        "mini",
        "hire",
        "private",
        "cab"
    ],
    "wof:name":"Alton Green Cars",
    "wof:placetype":"venue"
},
  "geometry": {"coordinates":[1.159085,51.984627],"type":"Point"}
}