{
  "type": "Feature",
  "properties": {
    "addr:full":"79 George Street Croydon Surrey CR0 1LD",
    "addr:housenumber":"79",
    "addr:postcode":"cr0 1ld",
    "addr:street":"George Street",
    "iso:country":"GB",
    "sg:address":"79 George Street",
    "sg:city":"Croydon",
    "sg:classifiers":[
        {
            "category":"Travel",
            "subcategory":"Travel Agent",
            "type":"Entertainment"
        }
    ],
    "sg:phone":"+44 20 8760 0879",
    "sg:postcode":"CR0 1LD",
    "sg:province":"Surrey",
    "wof:name":"Pure Crete",
    "wof:placetype":"venue"
},
  "geometry": {"coordinates":[-0.094675,51.374294],"type":"Point"}
}