{
  "type": "Feature",
  "properties": {
    "iso:country":"GB",
    "sg:address":"19, Ruby Street",
    "sg:city":"Bristol",
    "sg:classifiers":[
        {
            "category":"Professional",
            "subcategory":"Management & Consulting",
            "type":"Services"
        }
    ],
    "sg:postcode":"BS3 3DX",
    "sg:province":"City of Bristol",
    "sg:tags":[
        "consultant",
        "business"
    ],
    "wof:name":"Nickel Consulting Ltd",
    "wof:placetype":"venue"
},
  "geometry": {"coordinates":[-2.607165,51.438469],"type":"Point"}
}