{
  "type": "Feature",
  "properties": {
    "iso:country":"GB",
    "sg:address":"Colas Tonne, Collaton, Malborough",
    "sg:city":"Kingsbridge",
    "sg:classifiers":[
        {
            "category":"Health Services",
            "subcategory":"Health Practitioner",
            "type":"Services"
        }
    ],
    "sg:phone":"+44 1548 561553",
    "sg:postcode":"TQ7 3DJ",
    "sg:province":"Devon",
    "sg:tags":[
        "physiotherapist"
    ],
    "wof:name":"Jean Graham",
    "wof:placetype":"venue"
},
  "geometry": {"coordinates":[-3.8121159077,50.244178772],"type":"Point"}
}