{
  "type": "Feature",
  "properties": {
    "addr:full":"187 Queen Street Withernsea East Riding of Yorkshire HU19 2JR",
    "addr:housenumber":"187",
    "addr:postcode":"hu19 2jr",
    "addr:street":"Queen Street",
    "iso:country":"GB",
    "sg:address":"187 Queen Street",
    "sg:city":"Withernsea",
    "sg:classifiers":[
        {
            "category":"Professional",
            "subcategory":"Lawyer & Legal Services",
            "type":"Services"
        }
    ],
    "sg:phone":"+44 1964 612318",
    "sg:postcode":"HU19 2JR",
    "sg:province":"East Riding of Yorkshire",
    "sg:tags":[
        "solicitor"
    ],
    "wof:name":"David Macnamara",
    "wof:placetype":"venue"
},
  "geometry": {"coordinates":[0.029424,53.735073],"type":"Point"}
}