{
  "type": "Feature",
  "properties": {
    "addr:full":"43 Station St, Kirkby In Ashfield Nottingham Nottinghamshire NG17 7AN",
    "addr:housenumber":"43",
    "addr:postcode":"ng17 7an",
    "addr:street":"Station St;In Ashfield",
    "iso:country":"GB",
    "sg:address":"43 Station St, Kirkby In Ashfield",
    "sg:city":"Nottingham",
    "sg:classifiers":[
        {
            "category":"Shopping",
            "subcategory":"Comic Books",
            "type":"Retail Goods"
        }
    ],
    "sg:phone":"+44 1623 455025",
    "sg:postcode":"NG17 7AN",
    "sg:province":"Nottinghamshire",
    "sg:tags":[
        "jeweller"
    ],
    "wof:name":"M & A  JEWELLERS",
    "wof:placetype":"venue"
},
  "geometry": {"coordinates":[-1.2455869913,53.0991096497],"type":"Point"}
}