{
  "type": "Feature",
  "properties": {
    "addr:full":"West Moors Garage, Ringwood Rd Ferndown Dorset BH22 0AB",
    "addr:postcode":"bh22 0ab",
    "addr:street":"West;Ringwood Rd",
    "iso:country":"GB",
    "sg:address":"West Moors Garage, Ringwood Rd",
    "sg:city":"Ferndown",
    "sg:classifiers":[
        {
            "category":"Retail",
            "subcategory":"Auto Rental",
            "type":"Services"
        }
    ],
    "sg:phone":"+44 1202 897953",
    "sg:postcode":"BH22 0AB",
    "sg:province":"Dorset",
    "sg:tags":[
        "car",
        "hire",
        "truck"
    ],
    "wof:name":"R C Contracts",
    "wof:placetype":"venue"
},
  "geometry": {"coordinates":[-1.889695,50.835835],"type":"Point"}
}