{
  "type": "Feature",
  "properties": {
    "addr:full":"1 Alpine Cotts, Severn Street Newnham Gloucestershire GL14 1AZ",
    "addr:housenumber":"1",
    "addr:postcode":"gl14 1az",
    "addr:street":"Alpine Cotts Severn Street",
    "iso:country":"GB",
    "sg:address":"1 Alpine Cotts, Severn Street",
    "sg:city":"Newnham",
    "sg:classifiers":[
        {
            "category":"Building & Trades",
            "subcategory":"Construction",
            "type":"Services"
        }
    ],
    "sg:postcode":"GL14 1AZ",
    "sg:province":"Gloucestershire",
    "sg:tags":[
        "builder"
    ],
    "wof:name":"Annis & Jaynes",
    "wof:placetype":"venue"
},
  "geometry": {"coordinates":[-2.449804,51.803883],"type":"Point"}
}