{
  "type": "Feature",
  "properties": {
    "iso:country":"GB",
    "sg:address":"1 Alpine Cotts, Severn Street",
    "sg:city":"Newnham",
    "sg:classifiers":[
        {
            "category":"Building & Trades",
            "subcategory":"Construction",
            "type":"Services"
        }
    ],
    "sg:postcode":"GL14 1AZ",
    "sg:province":"Gloucestershire",
    "sg:tags":[
        "builder"
    ],
    "wof:name":"Annis & Jaynes",
    "wof:placetype":"venue"
},
  "geometry": {"coordinates":[-2.449804,51.803883],"type":"Point"}
}