{
  "type": "Feature",
  "properties": {
    "iso:country":"GB",
    "sg:address":"130 Swan Street, Sible Hedingham",
    "sg:city":"Halstead",
    "sg:classifiers":[
        {
            "category":"Government",
            "subcategory":"Post Office",
            "type":"Public Place"
        }
    ],
    "sg:phone":"+44 1787 460557",
    "sg:postcode":"CO9 3PR",
    "sg:province":"Essex",
    "wof:name":"Sible Hedingham Post Office",
    "wof:placetype":"venue"
},
  "geometry": {"coordinates":[0.593078,51.9772],"type":"Point"}
}