{
  "type": "Feature",
  "properties": {
    "addr:full":"82 High St Redhill Surrey RH1 1SG",
    "addr:housenumber":"82",
    "addr:postcode":"rh1 1sg",
    "addr:street":"High St",
    "iso:country":"GB",
    "sg:address":"82 High St",
    "sg:city":"Redhill",
    "sg:classifiers":[
        {
            "category":"Organizations",
            "subcategory":"Non-profit Organization",
            "type":"Services"
        }
    ],
    "sg:phone":"+44 1737 765615",
    "sg:postcode":"RH1 1SG",
    "sg:province":"Surrey",
    "sg:tags":[
        "organisation",
        "voluntary",
        "charity"
    ],
    "wof:name":"Redhill Christian Fellowship Trust",
    "wof:placetype":"venue"
},
  "geometry": {"coordinates":[-0.1685349941,51.2387542725],"type":"Point"}
}