{
  "type": "Feature",
  "properties": {
    "addr:full":"3 Upton Street, Off Crossbank Road Batley West Yorkshire WF17 8PH",
    "addr:housenumber":"3",
    "addr:postcode":"wf17 8ph",
    "addr:street":"Upton Street Off Crossbank Road",
    "iso:country":"GB",
    "sg:address":"3 Upton Street, Off Crossbank Road",
    "sg:city":"Batley",
    "sg:classifiers":[
        {
            "category":"Place Of Worship",
            "type":"Public Place"
        },
        {
            "category":"Organizations",
            "subcategory":"Religious Organization",
            "type":"Services"
        }
    ],
    "sg:phone":"+44 1924 420990",
    "sg:postcode":"WF17 8PH",
    "sg:province":"West Yorkshire",
    "sg:tags":[
        "organisation"
    ],
    "wof:name":"Franciscan Missionaries of the Divine Motherhood",
    "wof:placetype":"venue"
},
  "geometry": {"coordinates":[-1.6421999931,53.7169723511],"type":"Point"}
}