{
  "type": "Feature",
  "properties": {
    "addr:full":"Orpin House, Hilders Lane Edenbridge East Sussex TN8 6JX",
    "addr:postcode":"tn8 6jx",
    "addr:street":"Hilders Lane",
    "iso:country":"GB",
    "sg:address":"Orpin House, Hilders Lane",
    "sg:city":"Edenbridge",
    "sg:classifiers":[
        {
            "category":"Manufacturing",
            "subcategory":"Metals",
            "type":"Manufacturing & Wholesale Goods"
        }
    ],
    "sg:phone":"+44 1732 862237",
    "sg:postcode":"TN8 6JX",
    "sg:province":"East Sussex",
    "sg:tags":[
        "industry",
        "f-a"
    ],
    "wof:name":"Edenbridge Metals Ltd.",
    "wof:placetype":"venue"
},
  "geometry": {"coordinates":[0.0559450015,51.2104988098],"type":"Point"}
}