{
  "type": "Feature",
  "properties": {
    "iso:country":"GB",
    "sg:address":"Addiewell Work Yards, Station Rd",
    "sg:city":"West Calder",
    "sg:classifiers":[
        {
            "category":"Bus Charters",
            "type":"Transportation"
        }
    ],
    "sg:phone":"+44 1501 762500",
    "sg:postcode":"EH55 8QA",
    "sg:province":"South Lanarkshire",
    "sg:tags":[
        "coach"
    ],
    "wof:name":"Bulldog Travel",
    "wof:placetype":"venue"
},
  "geometry": {"coordinates":[-3.572372,55.851124],"type":"Point"}
}