{
  "type": "Feature",
  "properties": {
    "addr:full":"98 Nathans Rd Wembley Greater London HA0 3RX",
    "addr:housenumber":"98",
    "addr:postcode":"ha0 3rx",
    "addr:street":"Nathans Rd",
    "iso:country":"GB",
    "sg:address":"98 Nathans Rd",
    "sg:city":"Wembley",
    "sg:classifiers":[
        {
            "category":"Professional",
            "subcategory":"Engineering",
            "type":"Services"
        }
    ],
    "sg:phone":"+44 20 8904 9702",
    "sg:postcode":"HA0 3RX",
    "sg:province":"Greater London",
    "sg:tags":[
        "contractor",
        "electrical",
        "engineer"
    ],
    "wof:name":"Home Style Electrics",
    "wof:placetype":"venue"
},
  "geometry": {"coordinates":[-0.309511,51.570789],"type":"Point"}
}