{
  "type": "Feature",
  "properties": {
    "iso:country":"GB",
    "sg:address":"75 Verity Crescent",
    "sg:city":"Poole",
    "sg:classifiers":[
        {
            "category":"Building & Trades",
            "subcategory":"Cleaning & Sanitation",
            "type":"Services"
        }
    ],
    "sg:phone":"+44 1202 676952",
    "sg:postcode":"BH17 8TT",
    "sg:province":"Dorset",
    "sg:tags":[
        "contracting",
        "commercial"
    ],
    "wof:name":"Canford Cares",
    "wof:placetype":"venue"
},
  "geometry": {"coordinates":[-1.9616240263,50.7468910217],"type":"Point"}
}