{
  "type": "Feature",
  "properties": {
    "addr:full":"Isle Close Scunthorpe Lincolnshire DN17 4NR",
    "addr:postcode":"dn17 4nr",
    "addr:street":"Isle Close",
    "iso:country":"GB",
    "sg:address":"Isle Close",
    "sg:city":"Scunthorpe",
    "sg:classifiers":[
        {
            "category":"Building & Trades",
            "subcategory":"Construction",
            "type":"Services"
        }
    ],
    "sg:phone":"+44 1724 710335",
    "sg:postcode":"DN17 4NR",
    "sg:province":"Lincolnshire",
    "sg:tags":[
        "builder"
    ],
    "wof:name":"Askew Homes",
    "wof:placetype":"venue"
},
  "geometry": {"coordinates":[-0.8314189911,53.6135940552],"type":"Point"}
}