{
  "type": "Feature",
  "properties": {
    "iso:country":"GB",
    "sg:address":"65 Dulverton Drive, Furzton",
    "sg:city":"Milton Keynes",
    "sg:classifiers":[
        {
            "category":"Shopping",
            "subcategory":"Pharmacy",
            "type":"Retail Goods"
        }
    ],
    "sg:phone":"+44 1908 505659",
    "sg:postcode":"MK4 1EW",
    "sg:province":"Buckinghamshire",
    "sg:tags":[
        "pharmacist",
        "dispensing",
        "chemist"
    ],
    "wof:name":"Jardines Pharmacy",
    "wof:placetype":"venue"
},
  "geometry": {"coordinates":[-0.773294,52.00906],"type":"Point"}
}