{
  "type": "Feature",
  "properties": {
    "addr:full":"37 Loughton Road Milton Keynes Buckinghamshire MK13 9AF",
    "addr:housenumber":"37",
    "addr:postcode":"mk13 9af",
    "addr:street":"Loughton Road",
    "iso:country":"GB",
    "sg:address":"37 Loughton Road",
    "sg:city":"Milton Keynes",
    "sg:classifiers":[
        {
            "category":"Professional",
            "subcategory":"Engineering",
            "type":"Services"
        }
    ],
    "sg:phone":"+44 1908 312232",
    "sg:postcode":"MK13 9AF",
    "sg:province":"Buckinghamshire",
    "sg:tags":[
        "ge",
        "engineer",
        "mechanical"
    ],
    "wof:name":"T Daniels",
    "wof:placetype":"venue"
},
  "geometry": {"coordinates":[-0.786996007,52.0478019714],"type":"Point"}
}