{
  "type": "Feature",
  "properties": {
    "addr:full":"4 Moorside Rd, Drighlington Bradford West Yorkshire BD11 1EP",
    "addr:housenumber":"4",
    "addr:postcode":"bd11 1ep",
    "addr:street":"Moorside Rd",
    "iso:country":"GB",
    "sg:address":"4 Moorside Rd, Drighlington",
    "sg:city":"Bradford",
    "sg:classifiers":[
        {
            "category":"Fast Food",
            "type":"Food & Drink"
        }
    ],
    "sg:phone":"+44 113 285 2814",
    "sg:postcode":"BD11 1EP",
    "sg:province":"West Yorkshire",
    "sg:tags":[
        "away",
        "take"
    ],
    "wof:name":"Angie's Moorstores",
    "wof:placetype":"venue"
},
  "geometry": {"coordinates":[-1.656335,53.75386],"type":"Point"}
}