{
  "type": "Feature",
  "properties": {
    "iso:country":"GB",
    "sg:address":"1 Silver Street, Thorne",
    "sg:city":"Doncaster",
    "sg:classifiers":[
        {
            "category":"Personal",
            "subcategory":"Beauty Salon",
            "type":"Services"
        }
    ],
    "sg:postcode":"DN8 5DR",
    "sg:province":"East Riding of Yorkshire",
    "wof:name":"Angelique's Beauty Salon",
    "wof:placetype":"venue"
},
  "geometry": {"coordinates":[-0.960414,53.610344],"type":"Point"}
}