{
  "type": "Feature",
  "properties": {
    "addr:full":"George Davies & Co Fountain, Court, Manchester Greater Manchester M2 2FB",
    "addr:postcode":"m2 2fb",
    "addr:street":"Fountain Court",
    "iso:country":"GB",
    "sg:address":"George Davies & Co Fountain, Court,",
    "sg:city":"Manchester",
    "sg:classifiers":[
        {
            "category":"Professional",
            "type":"Services"
        }
    ],
    "sg:postcode":"M2 2FB",
    "sg:province":"Greater Manchester",
    "sg:tags":[
        "repair",
        "tech",
        "maintenance"
    ],
    "wof:name":"Complete Office Solutions Ltd",
    "wof:placetype":"venue"
},
  "geometry": {"coordinates":[-2.2423698902,53.479801178],"type":"Point"}
}