{
  "type": "Feature",
  "properties": {
    "iso:country":"GB",
    "sg:address":"Kenwick Lodge Farm, Cockshutt",
    "sg:city":"Ellesmere",
    "sg:classifiers":[
        {
            "category":"Farming",
            "subcategory":"Dairy Farm",
            "type":"Manufacturing & Wholesale Goods"
        }
    ],
    "sg:phone":"+44 1939 270442",
    "sg:postcode":"SY12 0JQ",
    "sg:province":"Shropshire",
    "wof:name":"A Wrench",
    "wof:placetype":"venue"
},
  "geometry": {"coordinates":[-2.8967549801,52.9076843262],"type":"Point"}
}