{
  "type": "Feature",
  "properties": {
    "addr:full":"7 Kensington Court London Greater London W8 5DL",
    "addr:housenumber":"7",
    "addr:postcode":"w8 5dl",
    "addr:street":"Kensington Court",
    "iso:country":"GB",
    "sg:address":"7 Kensington Court",
    "sg:city":"London",
    "sg:classifiers":[
        {
            "category":"Government",
            "subcategory":"Embassy",
            "type":"Public Place"
        }
    ],
    "sg:phone":"+44 20 7937 0150",
    "sg:postcode":"W8 5DL",
    "sg:province":"Greater London",
    "sg:tags":[
        "consulate"
    ],
    "wof:name":"Embassy of Mongolia",
    "wof:placetype":"venue"
},
  "geometry": {"coordinates":[-0.1870049983,51.5014381409],"type":"Point"}
}