{
  "type": "Feature",
  "properties": {
    "addr:full":"Stoke Road, Tredington Tewkesbury Gloucestershire GL20 7BZ",
    "addr:postcode":"gl20 7bz",
    "addr:street":"Stoke Road",
    "iso:country":"GB",
    "sg:address":"Stoke Road, Tredington",
    "sg:city":"Tewkesbury",
    "sg:classifiers":[
        {
            "category":"Shopping",
            "type":"Retail Goods"
        }
    ],
    "sg:phone":"+44 1684 293368",
    "sg:postcode":"GL20 7BZ",
    "sg:province":"Gloucestershire",
    "sg:tags":[
        "merchant"
    ],
    "wof:name":"W M S",
    "wof:placetype":"venue"
},
  "geometry": {"coordinates":[-2.144484,51.965504],"type":"Point"}
}