{
  "type": "Feature",
  "properties": {
    "iso:country":"GB",
    "sg:address":"Chasewater Heaths Business Park, Attwood Road, Burntwood",
    "sg:city":"Burntwood",
    "sg:classifiers":[
        {
            "category":"Professional",
            "subcategory":"Engineering",
            "type":"Services"
        },
        {
            "category":"Home & Garden",
            "subcategory":"Hardware",
            "type":"Retail Goods"
        }
    ],
    "sg:phone":"+44 1543 273900",
    "sg:postcode":"WS7 8GJ",
    "sg:province":"Staffordshire",
    "sg:tags":[
        "device",
        "fixing",
        "fastener"
    ],
    "wof:name":"I T W Highland (U K)",
    "wof:placetype":"venue"
},
  "geometry": {"coordinates":[-1.95003,52.6819],"type":"Point"}
}