{
  "type": "Feature",
  "properties": {
    "iso:country":"GB",
    "sg:address":"1030 Harrow Road",
    "sg:city":"London",
    "sg:classifiers":[
        {
            "category":"Restaurant",
            "type":"Food & Drink"
        },
        {
            "category":"Cafe",
            "type":"Food & Drink"
        }
    ],
    "sg:phone":"+44 20 8960 8268",
    "sg:postcode":"NW10 5NN",
    "sg:province":"Greater London",
    "sg:tags":[
        "tea",
        "thai",
        "-",
        "room"
    ],
    "wof:name":"May'S Cafe",
    "wof:placetype":"venue"
},
  "geometry": {"coordinates":[-0.230376,51.531143],"type":"Point"}
}