{
  "type": "Feature",
  "properties": {
    "addr:full":"7 The Village, Haxby York North Yorkshire YO32 3HS",
    "addr:housenumber":"7",
    "addr:postcode":"yo32 3hs",
    "addr:street":"The Village",
    "iso:country":"GB",
    "sg:address":"7 The Village, Haxby",
    "sg:city":"York",
    "sg:classifiers":[
        {
            "category":"Real Estate",
            "subcategory":"Real Estate Agent",
            "type":"Services"
        }
    ],
    "sg:phone":"+44 1904 750555",
    "sg:postcode":"YO32 3HS",
    "sg:province":"North Yorkshire",
    "wof:name":"Hunters the Estate Agents",
    "wof:placetype":"venue"
},
  "geometry": {"coordinates":[-1.0740089417,54.0157546997],"type":"Point"}
}