{
  "type": "Feature",
  "properties": {
    "addr:full":"67 Victoria Road Worthing West Sussex BN11 1UN",
    "addr:housenumber":"67",
    "addr:postcode":"bn11 1un",
    "addr:street":"Victoria Road",
    "iso:country":"GB",
    "sg:address":"67 Victoria Road",
    "sg:city":"Worthing",
    "sg:classifiers":[
        {
            "category":"Education",
            "subcategory":"Music School",
            "type":"Public Place"
        },
        {
            "category":"Retail",
            "subcategory":"Auto Repair",
            "type":"Services"
        }
    ],
    "sg:postcode":"BN11 1UN",
    "sg:province":"West Sussex",
    "sg:tags":[
        "body",
        "conservatory",
        "car"
    ],
    "wof:name":"C M C",
    "wof:placetype":"venue"
},
  "geometry": {"coordinates":[-0.3773419857,50.8173332214],"type":"Point"}
}