{
  "type": "Feature",
  "properties": {
    "iso:country":"GB",
    "sg:address":"The Cherries 28 Sitwell Grove",
    "sg:city":"York",
    "sg:classifiers":[
        {
            "category":"Professional",
            "subcategory":"Accounting & Tax Preparation",
            "type":"Services"
        }
    ],
    "sg:phone":"+44 1904 780036",
    "sg:postcode":"YO26 5JG",
    "sg:province":"North Yorkshire",
    "sg:tags":[
        "accountant"
    ],
    "wof:name":"H K Consulting",
    "wof:placetype":"venue"
},
  "geometry": {"coordinates":[-1.12643,53.964802],"type":"Point"}
}