{
  "type": "Feature",
  "properties": {
    "iso:country":"GB",
    "sg:address":"Unit 1 Cliffhill Wks, Balne La",
    "sg:city":"Wakefield",
    "sg:classifiers":[
        {
            "category":"Recreation",
            "subcategory":"Arcade",
            "type":"Entertainment"
        }
    ],
    "sg:phone":"+44 1924 381591",
    "sg:postcode":"WF2 0DF",
    "sg:province":"West Yorkshire",
    "sg:tags":[
        "machine",
        "amusement"
    ],
    "wof:name":"J A T Leisure U K Ltd",
    "wof:placetype":"venue"
},
  "geometry": {"coordinates":[-1.5102740526,53.6799697876],"type":"Point"}
}