{
  "type": "Feature",
  "properties": {
    "iso:country":"GB",
    "sg:address":"Watling Street",
    "sg:city":"Llanrwst",
    "sg:classifiers":[
        {
            "category":"Shopping",
            "subcategory":"Clothing, Apparel, & Fashions",
            "type":"Retail Goods"
        }
    ],
    "sg:phone":"+44 1492 642090",
    "sg:postcode":"LL26 0LS",
    "sg:province":"Conwy",
    "sg:tags":[
        "lady",
        "fashionwear",
        "ladieswear"
    ],
    "wof:name":"Steil",
    "wof:placetype":"venue"
},
  "geometry": {"coordinates":[-3.796904,53.138657],"type":"Point"}
}