{
  "type": "Feature",
  "properties": {
    "iso:country":"GB",
    "sg:address":"115 High Street",
    "sg:city":"Heckmondwike",
    "sg:classifiers":[
        {
            "category":"Social Services",
            "subcategory":"Child Care",
            "type":"Services"
        },
        {
            "category":"Retail",
            "subcategory":"Repair Shop",
            "type":"Services"
        }
    ],
    "sg:phone":"+44 1924 401669",
    "sg:postcode":"WF16 0AL",
    "sg:province":"West Yorkshire",
    "sg:tags":[
        "television",
        "good",
        "video",
        "servicing",
        "maintenance",
        "radio"
    ],
    "wof:name":"M A Electronics",
    "wof:placetype":"venue"
},
  "geometry": {"coordinates":[-1.669589,53.708317],"type":"Point"}
}