{
  "type": "Feature",
  "properties": {
    "iso:country":"GB",
    "sg:address":"Thistlefield, Primrose Hill",
    "sg:city":"Cowbridge",
    "sg:classifiers":[
        {
            "category":"Building & Trades",
            "subcategory":"Construction",
            "type":"Services"
        }
    ],
    "sg:phone":"+44 1446 773631",
    "sg:postcode":"CF71 7DU",
    "sg:province":"The Vale of Glamorgan",
    "sg:tags":[
        "builder"
    ],
    "wof:name":"Neil Smith & Co. (Cardiff) Ltd.",
    "wof:placetype":"venue"
},
  "geometry": {"coordinates":[-3.450425,51.462391],"type":"Point"}
}