{
  "type": "Feature",
  "properties": {
    "iso:country":"GB",
    "sg:address":"Swinnow Lane",
    "sg:city":"Leeds",
    "sg:classifiers":[
        {
            "category":"Home & Garden",
            "subcategory":"Home Furnishings",
            "type":"Retail Goods"
        }
    ],
    "sg:phone":"+44 113 257 1385",
    "sg:postcode":"LS13 4QT",
    "sg:province":"West Yorkshire",
    "sg:tags":[
        "beds",
        "bedding",
        "blanket"
    ],
    "wof:name":"Beds for Everyone",
    "wof:placetype":"venue"
},
  "geometry": {"coordinates":[-1.6461540461,53.8035469055],"type":"Point"}
}