{
  "type": "Feature",
  "properties": {
    "iso:country":"GB",
    "sg:address":"2 South Place, The Quay",
    "sg:city":"Kingsbridge",
    "sg:classifiers":[
        {
            "category":"Personal",
            "subcategory":"Beauty Salon",
            "type":"Services"
        }
    ],
    "sg:phone":"+44 1548 853073",
    "sg:postcode":"TQ7 1JE",
    "sg:province":"Devon",
    "sg:tags":[
        "lady",
        "hairdresser"
    ],
    "wof:name":"The Hair Advice Centre",
    "wof:placetype":"venue"
},
  "geometry": {"coordinates":[-3.777619,50.283104],"type":"Point"}
}