{
  "type": "Feature",
  "properties": {
    "iso:country":"GB",
    "sg:address":"Pigeon House La",
    "sg:city":"Swindon",
    "sg:classifiers":[
        {
            "category":"Retail",
            "subcategory":"Storage",
            "type":"Services"
        }
    ],
    "sg:phone":"+44 117 929 2100",
    "sg:postcode":"SN3 3LE",
    "sg:province":"Wiltshire",
    "sg:tags":[
        "household",
        "removal"
    ],
    "wof:name":"Doree Bonner International",
    "wof:placetype":"venue"
},
  "geometry": {"coordinates":[-1.752072,51.565338],"type":"Point"}
}