{
  "type": "Feature",
  "properties": {
    "addr:full":"170b Long Road Canvey Island Essex SS8 0JP",
    "addr:housenumber":"170b",
    "addr:postcode":"ss8 0jp",
    "addr:street":"Long Road",
    "iso:country":"GB",
    "sg:address":"170b Long Road",
    "sg:city":"Canvey Island",
    "sg:classifiers":[
        {
            "category":"Personal",
            "subcategory":"Beauty Salon",
            "type":"Services"
        }
    ],
    "sg:postcode":"SS8 0JP",
    "sg:province":"Essex",
    "sg:tags":[
        "lady",
        "hairdresser"
    ],
    "wof:name":"Hobbits",
    "wof:placetype":"venue"
},
  "geometry": {"coordinates":[0.5806999803,51.5202522278],"type":"Point"}
}