{
  "type": "Feature",
  "properties": {
    "addr:full":"Batten House, Lea Road, Sonning Common Reading Berkshire RG4 9LH",
    "addr:postcode":"rg4 9lh",
    "addr:street":"Lea Road",
    "iso:country":"GB",
    "sg:address":"Batten House, Lea Road, Sonning Common",
    "sg:city":"Reading",
    "sg:classifiers":[
        {
            "category":"Organizations",
            "subcategory":"Non-profit Organization",
            "type":"Services"
        }
    ],
    "sg:postcode":"RG4 9LH",
    "sg:province":"Berkshire",
    "sg:tags":[
        "organisation",
        "voluntary",
        "charity"
    ],
    "wof:name":"Btcv Green Gym Project",
    "wof:placetype":"venue"
},
  "geometry": {"coordinates":[-0.980494976,51.5150985718],"type":"Point"}
}