{
  "type": "Feature",
  "properties": {
    "iso:country":"GB",
    "sg:address":"23 Swyre",
    "sg:city":"Dorchester",
    "sg:classifiers":[
        {
            "category":"Farming",
            "subcategory":"Livestock Farm",
            "type":"Manufacturing & Wholesale Goods"
        }
    ],
    "sg:phone":"+44 1308 897235",
    "sg:postcode":"DT2 9DN",
    "sg:province":"Dorset",
    "sg:tags":[
        "others"
    ],
    "wof:name":"W E Yeates & Son",
    "wof:placetype":"venue"
},
  "geometry": {"coordinates":[-2.66843009,50.693939209],"type":"Point"}
}