{
  "type": "Feature",
  "properties": {
    "iso:country":"GB",
    "sg:address":"Unit 2 41-43 Gosport Street",
    "sg:city":"Lymington",
    "sg:classifiers":[
        {
            "category":"Food & Beverages",
            "subcategory":"Meat & Fish",
            "type":"Retail Goods"
        }
    ],
    "sg:phone":"+44 1590 670452",
    "sg:postcode":"SO41 9BB",
    "sg:province":"Hampshire",
    "sg:tags":[
        "merchant"
    ],
    "wof:name":"A & M Seafoods",
    "wof:placetype":"venue"
},
  "geometry": {"coordinates":[-1.539203,50.760921],"type":"Point"}
}