{
  "type": "Feature",
  "properties": {
    "iso:country":"GB",
    "sg:address":"Blackriding Works",
    "sg:city":"Oldham",
    "sg:classifiers":[
        {
            "category":"Autos & Motor Vehicles",
            "subcategory":"Auto Supplies",
            "type":"Retail Goods"
        }
    ],
    "sg:postcode":"OL9 7SU",
    "sg:province":"Lancashire",
    "sg:tags":[
        "electric"
    ],
    "wof:name":"Taylor & Goodman Ltd.",
    "wof:placetype":"venue"
},
  "geometry": {"coordinates":[-2.13397,53.537762],"type":"Point"}
}