{
  "type": "Feature",
  "properties": {
    "iso:country":"GB",
    "sg:address":"Unit 17 Olympic Business Centre, Paycocke Road",
    "sg:city":"Basildon",
    "sg:classifiers":[
        {
            "category":"Home & Garden",
            "subcategory":"Household Appliances",
            "type":"Retail Goods"
        }
    ],
    "sg:phone":"+44 1268 532414",
    "sg:postcode":"SS14 3EX",
    "sg:province":"Essex",
    "sg:tags":[
        "refrigeration",
        "air conditioning"
    ],
    "wof:name":"J L Harrison & Son (Air Conditioning) Ltd.",
    "wof:placetype":"venue"
},
  "geometry": {"coordinates":[0.493705,51.58881],"type":"Point"}
}