{
  "type": "Feature",
  "properties": {
    "iso:country":"GB",
    "sg:address":"7 Church Street, Golborne",
    "sg:city":"Warrington",
    "sg:classifiers":[
        {
            "category":"Shopping",
            "subcategory":"Pharmacy",
            "type":"Retail Goods"
        }
    ],
    "sg:phone":"+44 1928 733236",
    "sg:postcode":"WA3 3TL",
    "sg:province":"Cheshire",
    "sg:tags":[
        "pharmacist",
        "chemist"
    ],
    "wof:name":"Earlams Ltd.",
    "wof:placetype":"venue"
},
  "geometry": {"coordinates":[-2.5938539505,53.4794769287],"type":"Point"}
}