{
  "type": "Feature",
  "properties": {
    "iso:country":"GB",
    "sg:address":"24a Lealand Rd",
    "sg:city":"Portsmouth",
    "sg:classifiers":[
        {
            "category":"Manufacturing",
            "subcategory":"Chemicals & Compounds",
            "type":"Manufacturing & Wholesale Goods"
        }
    ],
    "sg:phone":"+44 23 9232 4479",
    "sg:postcode":"PO6 1LY",
    "sg:province":"Hampshire",
    "sg:tags":[
        "mnfrs",
        "explosive",
        "engineer"
    ],
    "wof:name":"Kidman Diving & Explosives Consultant",
    "wof:placetype":"venue"
},
  "geometry": {"coordinates":[-1.041379,50.844296],"type":"Point"}
}