{
  "type": "Feature",
  "properties": {
    "addr:full":"Unit 4 Charles St Wrexham Wrexham LL13 8BT",
    "addr:housenumber":"unit 4",
    "addr:postcode":"ll13 8bt",
    "addr:street":"Charles St",
    "iso:country":"GB",
    "sg:address":"Unit 4 Charles St",
    "sg:city":"Wrexham",
    "sg:classifiers":[
        {
            "category":"Communications",
            "type":"Services"
        }
    ],
    "sg:postcode":"LL13 8BT",
    "sg:province":"Wrexham",
    "sg:tags":[
        "tv",
        "video",
        "radio"
    ],
    "wof:name":"Domestic Direct",
    "wof:placetype":"venue"
},
  "geometry": {"coordinates":[-2.9904329777,53.0455131531],"type":"Point"}
}