{
  "type": "Feature",
  "properties": {
    "addr:full":"16 Stepstairs Lane Cirencester Gloucestershire GL7 1LA",
    "addr:housenumber":"16",
    "addr:postcode":"gl7 1la",
    "addr:street":"Stepstairs Lane",
    "iso:country":"GB",
    "sg:address":"16 Stepstairs Lane",
    "sg:city":"Cirencester",
    "sg:classifiers":[
        {
            "category":"Building & Trades",
            "subcategory":"Construction",
            "type":"Services"
        },
        {
            "category":"Manufacturing",
            "subcategory":"Building Materials",
            "type":"Manufacturing & Wholesale Goods"
        }
    ],
    "sg:phone":"+44 1285 652109",
    "sg:postcode":"GL7 1LA",
    "sg:province":"Gloucestershire",
    "sg:tags":[
        "stonemason",
        "builder"
    ],
    "wof:name":"I F A Terrett",
    "wof:placetype":"venue"
},
  "geometry": {"coordinates":[-1.962298,51.710037],"type":"Point"}
}