{
  "type": "Feature",
  "properties": {
    "addr:full":"Unit L Marshgate Trading Estate, Taplow Maidenhead Berkshire SL6 0ND",
    "addr:postcode":"sl6 0nd",
    "iso:country":"GB",
    "sg:address":"Unit L Marshgate Trading Estate, Taplow",
    "sg:city":"Maidenhead",
    "sg:classifiers":[
        {
            "category":"Manufacturing",
            "subcategory":"Metals",
            "type":"Manufacturing & Wholesale Goods"
        }
    ],
    "sg:postcode":"SL6 0ND",
    "sg:province":"Berkshire",
    "wof:name":"Metal Finishers J B",
    "wof:placetype":"venue"
},
  "geometry": {"coordinates":[-0.687149,51.532169],"type":"Point"}
}