{
  "type": "Feature",
  "properties": {
    "addr:full":"130 School Green Road Freshwater Isle of Wight PO40 9BA",
    "addr:housenumber":"130",
    "addr:postcode":"po40 9ba",
    "addr:street":"School Green Road",
    "iso:country":"GB",
    "sg:address":"130 School Green Road",
    "sg:city":"Freshwater",
    "sg:classifiers":[
        {
            "category":"Professional",
            "subcategory":"Engineering",
            "type":"Services"
        }
    ],
    "sg:phone":"+44 1983 754293",
    "sg:postcode":"PO40 9BA",
    "sg:province":"Isle of Wight",
    "sg:tags":[
        "gas",
        "engineer"
    ],
    "wof:name":"S J Installation",
    "wof:placetype":"venue"
},
  "geometry": {"coordinates":[-1.5177930593,50.6822776794],"type":"Point"}
}