{
  "type": "Feature",
  "properties": {
    "iso:country":"GB",
    "sg:address":"Briercliffe Road",
    "sg:city":"Burnley",
    "sg:classifiers":[
        {
            "category":"Social Services",
            "subcategory":"Retirement Home",
            "type":"Services"
        },
        {
            "category":"Government",
            "subcategory":"Office",
            "type":"Public Place"
        }
    ],
    "sg:phone":"+44 1282 421016",
    "sg:postcode":"BB10 2EZ",
    "sg:province":"Lancashire",
    "sg:tags":[
        "residential",
        "local",
        "care"
    ],
    "wof:name":"Lane Head House",
    "wof:placetype":"venue"
},
  "geometry": {"coordinates":[-2.2080609798,53.811290741],"type":"Point"}
}