{
  "type": "Feature",
  "properties": {
    "addr:full":"45 Lower Brook Street Ipswich Suffolk IP4 1AQ",
    "addr:housenumber":"45",
    "addr:postcode":"ip4 1aq",
    "addr:street":"Lower Brook Street",
    "iso:country":"GB",
    "sg:address":"45 Lower Brook Street",
    "sg:city":"Ipswich",
    "sg:classifiers":[
        {
            "category":"Real Estate",
            "subcategory":"Real Estate Agent",
            "type":"Services"
        }
    ],
    "sg:phone":"+44 1473 289600",
    "sg:postcode":"IP4 1AQ",
    "sg:province":"Suffolk",
    "wof:name":"Reader Commercial Ltd.",
    "wof:placetype":"venue"
},
  "geometry": {"coordinates":[1.1560640335,52.0536804199],"type":"Point"}
}