{
  "type": "Feature",
  "properties": {
    "addr:full":"30 South Road, Waterloo Liverpool Merseyside L22 5PQ",
    "addr:housenumber":"30",
    "addr:postcode":"l22 5pq",
    "addr:street":"South Road",
    "iso:country":"GB",
    "sg:address":"30 South Road, Waterloo",
    "sg:city":"Liverpool",
    "sg:classifiers":[
        {
            "category":"Restaurant",
            "type":"Food & Drink"
        }
    ],
    "sg:phone":"+44 151 928 2862",
    "sg:postcode":"L22 5PQ",
    "sg:province":"Merseyside",
    "sg:tags":[
        "italian"
    ],
    "wof:name":"Nicolas Restaurant",
    "wof:placetype":"venue"
},
  "geometry": {"coordinates":[-3.0277159214,53.4739761353],"type":"Point"}
}