{
  "type": "Feature",
  "properties": {
    "addr:full":"4 Southwick Square, Southwick Steyning West Sussex BN42 4FJ",
    "addr:housenumber":"4",
    "addr:postcode":"bn42 4fj",
    "addr:street":"Southwick Square",
    "iso:country":"GB",
    "sg:address":"4 Southwick Square, Southwick",
    "sg:city":"Steyning",
    "sg:classifiers":[
        {
            "category":"Home & Garden",
            "subcategory":"Household Appliances",
            "type":"Retail Goods"
        }
    ],
    "sg:postcode":"BN42 4FJ",
    "sg:province":"West Sussex",
    "sg:tags":[
        "electrical"
    ],
    "wof:name":"Carters Appliance Repairs",
    "wof:placetype":"venue"
},
  "geometry": {"coordinates":[-0.235524,50.834358],"type":"Point"}
}