{
  "type": "Feature",
  "properties": {
    "addr:full":"20 Fonnereau Rd Ipswich Suffolk IP1 3JP",
    "addr:housenumber":"20",
    "addr:postcode":"ip1 3jp",
    "addr:street":"Fonnereau Rd",
    "iso:country":"GB",
    "sg:address":"20 Fonnereau Rd",
    "sg:city":"Ipswich",
    "sg:classifiers":[
        {
            "category":"Building & Trades",
            "subcategory":"Cleaning & Sanitation",
            "type":"Services"
        }
    ],
    "sg:phone":"+44 1473 402509",
    "sg:postcode":"IP1 3JP",
    "sg:province":"Suffolk",
    "sg:tags":[
        "steam"
    ],
    "wof:name":"PD Chemicals",
    "wof:placetype":"venue"
},
  "geometry": {"coordinates":[1.1534539461,52.0614242554],"type":"Point"}
}