{
  "type": "Feature",
  "properties": {
    "addr:full":"5 Lilford St Leigh Lancashire WN7 4JN",
    "addr:housenumber":"5",
    "addr:postcode":"wn7 4jn",
    "addr:street":"Lilford St",
    "iso:country":"GB",
    "sg:address":"5 Lilford St",
    "sg:city":"Leigh",
    "sg:classifiers":[
        {
            "category":"Retail",
            "subcategory":"Auto Repair",
            "type":"Services"
        }
    ],
    "sg:phone":"+44 1942 269819",
    "sg:postcode":"WN7 4JN",
    "sg:province":"Lancashire",
    "sg:tags":[
        "modification",
        "garage"
    ],
    "wof:name":"A 1 Computer Tune",
    "wof:placetype":"venue"
},
  "geometry": {"coordinates":[-2.525658,53.493896],"type":"Point"}
}