{
  "type": "Feature",
  "properties": {
    "iso:country":"GB",
    "sg:address":"Parsonage Street, Oldbury",
    "sg:city":"Smethwick",
    "sg:classifiers":[
        {
            "category":"Professional",
            "subcategory":"Engineering",
            "type":"Services"
        }
    ],
    "sg:phone":"+44 121 552 6065",
    "sg:postcode":"B69 4PH",
    "sg:province":"West Midlands",
    "sg:tags":[
        "precision",
        "engineer"
    ],
    "wof:name":"Whiton Tools Ltd.",
    "wof:placetype":"venue"
},
  "geometry": {"coordinates":[-2.015845,52.503777],"type":"Point"}
}