{
  "type": "Feature",
  "properties": {
    "addr:full":"3 Summerskill Grn Chesterfield Derbyshire S43 3SR",
    "addr:housenumber":"3",
    "addr:postcode":"s43 3sr",
    "addr:street":"Summerskill Grn",
    "iso:country":"GB",
    "sg:address":"3 Summerskill Grn",
    "sg:city":"Chesterfield",
    "sg:classifiers":[
        {
            "category":"Food & Beverages",
            "subcategory":"Fruits & Vegetables",
            "type":"Retail Goods"
        }
    ],
    "sg:phone":"+44 1246 472895",
    "sg:postcode":"S43 3SR",
    "sg:province":"Derbyshire",
    "sg:tags":[
        "greengrocer"
    ],
    "wof:name":"The Fruit Bowl",
    "wof:placetype":"venue"
},
  "geometry": {"coordinates":[-1.370463,53.255672],"type":"Point"}
}