{
  "type": "Feature",
  "properties": {
    "iso:country":"GB",
    "sg:address":"Savoy Works, Pershore Road, Kings Norton",
    "sg:city":"Birmingham",
    "sg:classifiers":[
        {
            "category":"Building & Trades",
            "subcategory":"Plumbing",
            "type":"Services"
        }
    ],
    "sg:phone":"+44 121 433 3099",
    "sg:postcode":"B30 3DR",
    "sg:province":"West Midlands",
    "sg:tags":[
        "merchant",
        "plumbers'"
    ],
    "wof:name":"A B Plumbing Supplies Ltd.",
    "wof:placetype":"venue"
},
  "geometry": {"coordinates":[-1.92164,52.420559],"type":"Point"}
}