{
  "type": "Feature",
  "properties": {
    "iso:country":"GB",
    "sg:address":"Glasslyn Nurseries, 199 Common Edge Rd",
    "sg:city":"Blackpool",
    "sg:classifiers":[
        {
            "category":"Food & Beverages",
            "subcategory":"Farmers Market",
            "type":"Retail Goods"
        }
    ],
    "sg:phone":"+44 1253 764052",
    "sg:postcode":"FY4 5DJ",
    "sg:province":"Lancashire",
    "sg:tags":[
        "gardener"
    ],
    "wof:name":"W.J & D Picken",
    "wof:placetype":"venue"
},
  "geometry": {"coordinates":[-3.01861,53.780331],"type":"Point"}
}