{
  "type": "Feature",
  "properties": {
    "addr:full":"Crow Lane Works, Crow Lane, Ramsbottom Bury Lancashire BL0 9BR",
    "addr:postcode":"bl0 9br",
    "addr:street":"Crow Lane;Crow Lane",
    "iso:country":"GB",
    "sg:address":"Crow Lane Works, Crow Lane, Ramsbottom",
    "sg:city":"Bury",
    "sg:classifiers":[
        {
            "category":"Manufacturing",
            "subcategory":"Petroleum Products",
            "type":"Manufacturing & Wholesale Goods"
        }
    ],
    "sg:postcode":"BL0 9BR",
    "sg:province":"Lancashire",
    "sg:tags":[
        "double",
        "glazing"
    ],
    "wof:name":"Ramsbottom Glass & Glazing Ltd.",
    "wof:placetype":"venue"
},
  "geometry": {"coordinates":[-2.3163459301,53.6497802734],"type":"Point"}
}