{
  "type": "Feature",
  "properties": {
    "addr:full":"Rear Of 275-281 King Street, Beavor Lane London Greater London W6 9LZ",
    "addr:housenumber":"275-281",
    "addr:postcode":"w6 9lz",
    "addr:street":"King Street Beavor Lane",
    "iso:country":"GB",
    "sg:address":"Rear Of 275-281 King Street, Beavor Lane",
    "sg:city":"London",
    "sg:classifiers":[
        {
            "category":"Professional",
            "subcategory":"Art Services",
            "type":"Services"
        }
    ],
    "sg:phone":"+44 20 8748 6110",
    "sg:postcode":"W6 9LZ",
    "sg:province":"Greater London",
    "sg:tags":[
        "model",
        "maker"
    ],
    "wof:name":"Architectural Models International",
    "wof:placetype":"venue"
},
  "geometry": {"coordinates":[-0.2389100045,51.4931297302],"type":"Point"}
}