{
  "type": "Feature",
  "properties": {
    "addr:full":"25 Brindley Road, Exhall Coventry Warwickshire CV7 9EP",
    "addr:housenumber":"25",
    "addr:postcode":"cv7 9ep",
    "addr:street":"Brindley Road",
    "iso:country":"GB",
    "sg:address":"25 Brindley Road, Exhall",
    "sg:city":"Coventry",
    "sg:classifiers":[
        {
            "category":"Manufacturing",
            "subcategory":"Tools & Machinery",
            "type":"Manufacturing & Wholesale Goods"
        }
    ],
    "sg:phone":"+44 24 7664 4663",
    "sg:postcode":"CV7 9EP",
    "sg:province":"Warwickshire",
    "wof:name":"Saturn Industries Ltd.",
    "wof:placetype":"venue"
},
  "geometry": {"coordinates":[-1.474118,52.466576],"type":"Point"}
}