{
  "type": "Feature",
  "properties": {
    "addr:full":"Headington Road Oxford Oxfordshire OX3 7TD",
    "addr:postcode":"ox3 7td",
    "addr:street":"Headington Road",
    "iso:country":"GB",
    "sg:address":"Headington Road",
    "sg:city":"Oxford",
    "sg:classifiers":[
        {
            "category":"Education",
            "subcategory":"School",
            "type":"Public Place"
        }
    ],
    "sg:phone":"+44 1865 759100",
    "sg:postcode":"OX3 7TD",
    "sg:province":"Oxfordshire",
    "sg:tags":[
        "independent",
        "preparatory"
    ],
    "wof:name":"Headington School Oxford Ltd.",
    "wof:placetype":"venue"
},
  "geometry": {"coordinates":[-1.2250510454,51.7558708191],"type":"Point"}
}