{
  "type": "Feature",
  "properties": {
    "iso:country":"GB",
    "sg:address":"70 Heather Road",
    "sg:city":"Newport",
    "sg:classifiers":[
        {
            "category":"Food & Beverages",
            "subcategory":"Groceries & Convenience Stores",
            "type":"Retail Goods"
        }
    ],
    "sg:postcode":"NP19 7QX",
    "sg:province":"Newport",
    "wof:name":"Four Seasons",
    "wof:placetype":"venue"
},
  "geometry": {"coordinates":[-2.9704639912,51.597820282],"type":"Point"}
}