{
  "type": "Feature",
  "properties": {
    "iso:country":"GB",
    "sg:address":"234a Stroud Road, Tuffley",
    "sg:city":"Gloucester",
    "sg:classifiers":[
        {
            "category":"Parking",
            "type":"Transportation"
        }
    ],
    "sg:phone":"+44 1452 414319",
    "sg:postcode":"GL4 0AU",
    "sg:province":"Gloucestershire",
    "sg:tags":[
        "car",
        "valet"
    ],
    "wof:name":"Unit 11 Cars",
    "wof:placetype":"venue"
},
  "geometry": {"coordinates":[-2.244173,51.83485],"type":"Point"}
}