{
  "type": "Feature",
  "properties": {
    "addr:full":"10 Moorlands Road, West Moors Ferndown Dorset BH22 0JW",
    "addr:housenumber":"10",
    "addr:postcode":"bh22 0jw",
    "addr:street":"Moorlands Road West",
    "iso:country":"GB",
    "sg:address":"10 Moorlands Road, West Moors",
    "sg:city":"Ferndown",
    "sg:classifiers":[
        {
            "category":"Shopping",
            "subcategory":"Computers & Home Electronics",
            "type":"Retail Goods"
        }
    ],
    "sg:phone":"+44 1202 876873",
    "sg:postcode":"BH22 0JW",
    "sg:province":"Dorset",
    "sg:tags":[
        "aerial",
        "television",
        "radio"
    ],
    "wof:name":"Ferndown Aerial Co",
    "wof:placetype":"venue"
},
  "geometry": {"coordinates":[-1.8879400492,50.8253822327],"type":"Point"}
}