{
  "type": "Feature",
  "properties": {
    "iso:country":"GB",
    "sg:address":"61 Kempock Street",
    "sg:city":"Gourock",
    "sg:classifiers":[
        {
            "category":"Arts & Performance",
            "subcategory":"Art Gallery",
            "type":"Entertainment"
        }
    ],
    "sg:phone":"+44 1475 650555",
    "sg:postcode":"PA19 1NF",
    "sg:province":"Inverclyde",
    "wof:name":"Original Artists",
    "wof:placetype":"venue"
},
  "geometry": {"coordinates":[-4.820364,55.961578],"type":"Point"}
}