{
  "type": "Feature",
  "properties": {
    "iso:country":"GB",
    "sg:address":"119a Evington Road",
    "sg:city":"Leicester",
    "sg:classifiers":[
        {
            "category":"Shopping",
            "subcategory":"Musical Instruments",
            "type":"Retail Goods"
        }
    ],
    "sg:phone":"+44 116 255 5519",
    "sg:postcode":"LE2 1QH",
    "sg:province":"Leicestershire",
    "sg:tags":[
        "music",
        "sheet"
    ],
    "wof:name":"Goodies",
    "wof:placetype":"venue"
},
  "geometry": {"coordinates":[-1.111913,52.626228],"type":"Point"}
}