{
  "type": "Feature",
  "properties": {
    "iso:country":"GB",
    "sg:address":"56 Cornfield Road",
    "sg:city":"Reigate",
    "sg:classifiers":[
        {
            "category":"Professional",
            "subcategory":"Printing & Photocopies",
            "type":"Services"
        }
    ],
    "sg:postcode":"RH2 7HE",
    "sg:province":"Surrey",
    "sg:tags":[
        "printer"
    ],
    "wof:name":"Glintprint",
    "wof:placetype":"venue"
},
  "geometry": {"coordinates":[-0.1945839971,51.2300643921],"type":"Point"}
}