{
  "type": "Feature",
  "properties": {
    "addr:full":"134-136 Commercial Road London Greater London E1 1NL",
    "addr:housenumber":"134-136",
    "addr:postcode":"e1 1nl",
    "addr:street":"Commercial Road",
    "iso:country":"GB",
    "sg:address":"134-136 Commercial Road",
    "sg:city":"London",
    "sg:classifiers":[
        {
            "category":"Shopping",
            "subcategory":"Clothing, Apparel, & Fashions",
            "type":"Retail Goods"
        },
        {
            "category":"Wholesale",
            "subcategory":"Apparel",
            "type":"Manufacturing & Wholesale Goods"
        }
    ],
    "sg:phone":"+44 20 7480 6101",
    "sg:postcode":"E1 1NL",
    "sg:province":"Greater London",
    "sg:tags":[
        "supplier",
        "clothing"
    ],
    "wof:name":"Dineshco Textiles Ltd",
    "wof:placetype":"venue"
},
  "geometry": {"coordinates":[-0.0632399991,51.5146484375],"type":"Point"}
}