{
  "type": "Feature",
  "properties": {
    "iso:country":"GB",
    "sg:address":"Lyons Court, 1664a High Street",
    "sg:city":"Solihull",
    "sg:classifiers":[
        {
            "category":"Professional",
            "subcategory":"Printing & Photocopies",
            "type":"Services"
        }
    ],
    "sg:phone":"+44 1564 772898",
    "sg:postcode":"B93 0LY",
    "sg:province":"Warwickshire",
    "sg:tags":[
        "printer"
    ],
    "wof:name":"C B F Business Forms",
    "wof:placetype":"venue"
},
  "geometry": {"coordinates":[-1.7338160276,52.3874206543],"type":"Point"}
}