{
  "type": "Feature",
  "properties": {
    "addr:full":"Edgefield Avenue Newcastle-upon-tyne Tyne and Wear NE3 3TT",
    "addr:postcode":"ne3 3tt",
    "addr:street":"Edgefield Avenue",
    "iso:country":"GB",
    "sg:address":"Edgefield Avenue",
    "sg:city":"Newcastle-upon-tyne",
    "sg:classifiers":[
        {
            "category":"Wholesale",
            "subcategory":"Chemicals & Plastics",
            "type":"Manufacturing & Wholesale Goods"
        }
    ],
    "sg:phone":"+44 191 285 3931",
    "sg:postcode":"NE3 3TT",
    "sg:province":"Tyne and Wear",
    "sg:tags":[
        "product",
        "allied"
    ],
    "wof:name":"Sanofi Winthrop Production Division",
    "wof:placetype":"venue"
},
  "geometry": {"coordinates":[-1.644349,55.013157],"type":"Point"}
}