{
  "type": "Feature",
  "properties": {
    "iso:country":"GB",
    "sg:address":"45a Fore Street",
    "sg:city":"Redruth",
    "sg:classifiers":[
        {
            "category":"Shopping",
            "subcategory":"News",
            "type":"Retail Goods"
        }
    ],
    "sg:phone":"+44 1209 216229",
    "sg:postcode":"TR15 2AE",
    "sg:province":"Cornwall",
    "sg:tags":[
        "newsagent"
    ],
    "wof:name":"Pearce Newsagents",
    "wof:placetype":"venue"
},
  "geometry": {"coordinates":[-5.226302,50.234097],"type":"Point"}
}