{
  "type": "Feature",
  "properties": {
    "addr:full":"9 Town Street, Marple Bridge Stockport Cheshire SK6 5AA",
    "addr:housenumber":"9",
    "addr:postcode":"sk6 5aa",
    "addr:street":"Town Street",
    "iso:country":"GB",
    "sg:address":"9 Town Street, Marple Bridge",
    "sg:city":"Stockport",
    "sg:classifiers":[
        {
            "category":"Fast Food",
            "type":"Food & Drink"
        }
    ],
    "sg:phone":"+44 161 449 7290",
    "sg:postcode":"SK6 5AA",
    "sg:province":"Cheshire",
    "sg:tags":[
        "away",
        "take"
    ],
    "wof:name":"The Great Wall",
    "wof:placetype":"venue"
},
  "geometry": {"coordinates":[-2.053817,53.401024],"type":"Point"}
}