{
  "type": "Feature",
  "properties": {
    "iso:country":"GB",
    "sg:address":"Po Box 5675",
    "sg:city":"Solihull",
    "sg:classifiers":[
        {
            "category":"Shopping",
            "subcategory":"Photographic Equipment",
            "type":"Retail Goods"
        }
    ],
    "sg:postcode":"B92 8TF",
    "sg:province":"West Midlands",
    "sg:tags":[
        "supply"
    ],
    "wof:name":"S W Brown Ampro Designs",
    "wof:placetype":"venue"
},
  "geometry": {"coordinates":[-1.7888799906,52.4417991638],"type":"Point"}
}