{
  "type": "Feature",
  "properties": {
    "iso:country":"GB",
    "sg:address":"2 Lower Ascott, Wing",
    "sg:city":"Leighton Buzzard",
    "sg:classifiers":[
        {
            "category":"Professional",
            "subcategory":"Engineering",
            "type":"Services"
        }
    ],
    "sg:postcode":"LU7 0PU",
    "sg:province":"Bedfordshire",
    "sg:tags":[
        "contractor",
        "electrical",
        "engineer"
    ],
    "wof:name":"J D  Electrical Services",
    "wof:placetype":"venue"
},
  "geometry": {"coordinates":[-0.7149990201,51.8978347778],"type":"Point"}
}