{
  "type": "Feature",
  "properties": {
    "addr:full":"178 Burgess Road Southampton Hampshire SO16 3HH",
    "addr:housenumber":"178",
    "addr:postcode":"so16 3hh",
    "addr:street":"Burgess Road",
    "iso:country":"GB",
    "sg:address":"178 Burgess Road",
    "sg:city":"Southampton",
    "sg:classifiers":[
        {
            "category":"Shopping",
            "subcategory":"Thrift Store",
            "type":"Retail Goods"
        }
    ],
    "sg:phone":"+44 23 8067 9095",
    "sg:postcode":"SO16 3HH",
    "sg:province":"Hampshire",
    "sg:tags":[
        "shop",
        "charity"
    ],
    "wof:name":"Winged Fellowship Trust",
    "wof:placetype":"venue"
},
  "geometry": {"coordinates":[-1.3925449848,50.9382133484],"type":"Point"}
}