{
  "type": "Feature",
  "properties": {
    "addr:full":"106 Atherstone Rd Loughborough Leicestershire LE11 2SL",
    "addr:housenumber":"106",
    "addr:postcode":"le11 2sl",
    "addr:street":"Atherstone Rd",
    "iso:country":"GB",
    "sg:address":"106 Atherstone Rd",
    "sg:city":"Loughborough",
    "sg:classifiers":[
        {
            "category":"Manufacturing",
            "subcategory":"Petroleum Products",
            "type":"Manufacturing & Wholesale Goods"
        }
    ],
    "sg:postcode":"LE11 2SL",
    "sg:province":"Leicestershire",
    "sg:tags":[
        "double",
        "glazing"
    ],
    "wof:name":"Frostick & Marchant",
    "wof:placetype":"venue"
},
  "geometry": {"coordinates":[-1.2165139914,52.7509651184],"type":"Point"}
}