{
  "type": "Feature",
  "properties": {
    "addr:full":"Coombe Farm Tenterden Kent TN30 6XA",
    "addr:postcode":"tn30 6xa",
    "iso:country":"GB",
    "sg:address":"Coombe Farm",
    "sg:city":"Tenterden",
    "sg:classifiers":[
        {
            "category":"Recreation",
            "subcategory":"Fishing",
            "type":"Entertainment"
        }
    ],
    "sg:phone":"+44 1580 763201",
    "sg:postcode":"TN30 6XA",
    "sg:province":"Kent",
    "sg:tags":[
        "angling"
    ],
    "wof:name":"Tenterden Trout Waters",
    "wof:placetype":"venue"
},
  "geometry": {"coordinates":[0.6940600276,51.0754051208],"type":"Point"}
}