{
  "type": "Feature",
  "properties": {
    "addr:full":"234a Upper Richmond Road, Putney London Greater London SW15 6SP",
    "addr:housenumber":"234a",
    "addr:postcode":"sw15 6sp",
    "addr:street":"Upper Richmond Road",
    "iso:country":"GB",
    "sg:address":"234a Upper Richmond Road, Putney",
    "sg:city":"London",
    "sg:classifiers":[
        {
            "category":"Taxi",
            "type":"Transportation"
        },
        {
            "category":"Military Area",
            "subcategory":"Air Force Base",
            "type":"Public Place"
        }
    ],
    "sg:phone":"+44 20 8780 2699",
    "sg:postcode":"SW15 6SP",
    "sg:province":"Greater London",
    "sg:tags":[
        "mini",
        "hire",
        "private",
        "cab"
    ],
    "wof:name":"Pavilion Car Service",
    "wof:placetype":"venue"
},
  "geometry": {"coordinates":[-0.218912,51.461411],"type":"Point"}
}