{
  "type": "Feature",
  "properties": {
    "addr:full":"Unit 30 Hillgrove Business Park, Nazeing Road, Nazeing Waltham Abbey Essex EN9 2HB",
    "addr:housenumber":"unit 30",
    "addr:postcode":"en9 2hb",
    "addr:street":"Business Park Nazeing Road;Abbey",
    "iso:country":"GB",
    "sg:address":"Unit 30 Hillgrove Business Park, Nazeing Road, Nazeing",
    "sg:city":"Waltham Abbey",
    "sg:classifiers":[
        {
            "category":"Wholesale",
            "subcategory":"Vending Machines",
            "type":"Manufacturing & Wholesale Goods"
        }
    ],
    "sg:phone":"+44 1992 892993",
    "sg:postcode":"EN9 2HB",
    "sg:province":"Essex",
    "sg:tags":[
        "sale"
    ],
    "wof:name":"Sharp's Vending & Wholesalers",
    "wof:placetype":"venue"
},
  "geometry": {"coordinates":[0.048448,51.738914],"type":"Point"}
}