{
  "type": "Feature",
  "properties": {
    "iso:country":"GB",
    "sg:address":"Unit 5 Keppenburn Workshop, Main Rd",
    "sg:city":"Largs",
    "sg:classifiers":[
        {
            "category":"Home & Garden",
            "subcategory":"Home Furnishings",
            "type":"Retail Goods"
        }
    ],
    "sg:phone":"+44 1475 568862",
    "sg:postcode":"KA29 0AS",
    "sg:province":"North Ayrshire",
    "sg:tags":[
        "blind",
        "curtain",
        "fitting"
    ],
    "wof:name":"Inside Story Design Partnership",
    "wof:placetype":"venue"
},
  "geometry": {"coordinates":[-4.853062,55.765118],"type":"Point"}
}