{
  "type": "Feature",
  "properties": {
    "addr:full":"Tarholm Nursery Ayr East Ayrshire KA6 5HX",
    "addr:postcode":"ka6 5hx",
    "addr:street":"East",
    "iso:country":"GB",
    "sg:address":"Tarholm Nursery",
    "sg:city":"Ayr",
    "sg:classifiers":[
        {
            "category":"Home & Garden",
            "subcategory":"Garden Supply",
            "type":"Retail Goods"
        }
    ],
    "sg:postcode":"KA6 5HX",
    "sg:province":"East Ayrshire",
    "sg:tags":[
        "nursery",
        "centre"
    ],
    "wof:name":"J McCallum",
    "wof:placetype":"venue"
},
  "geometry": {"coordinates":[-4.5428299904,55.4668006897],"type":"Point"}
}