{
  "type": "Feature",
  "properties": {
    "iso:country":"GB",
    "sg:address":"19 Hick Lane",
    "sg:city":"Batley",
    "sg:classifiers":[
        {
            "category":"Sports & Exercise",
            "subcategory":"Gym",
            "type":"Entertainment"
        }
    ],
    "sg:phone":"+44 1924 476476",
    "sg:postcode":"WF17 5TD",
    "sg:province":"West Yorkshire",
    "sg:tags":[
        "fitness",
        "health",
        "centre"
    ],
    "wof:name":"Jordanelle Coffee House & Sandwich Bar",
    "wof:placetype":"venue"
},
  "geometry": {"coordinates":[-1.628829,53.71257],"type":"Point"}
}