{
  "type": "Feature",
  "properties": {
    "addr:full":"Unit C3, Lympne Industrial Estate, Lympne Hythe Kent CT21 4LR",
    "addr:postcode":"ct21 4lr",
    "addr:street":"Industrial Estate",
    "iso:country":"GB",
    "sg:address":"Unit C3, Lympne Industrial Estate, Lympne",
    "sg:city":"Hythe",
    "sg:classifiers":[
        {
            "category":"Freight",
            "type":"Transportation"
        }
    ],
    "sg:phone":"+44 1303 260477",
    "sg:postcode":"CT21 4LR",
    "sg:province":"Kent",
    "sg:tags":[
        "haulage",
        "road"
    ],
    "wof:name":"Roland & Kenny Barton",
    "wof:placetype":"venue"
},
  "geometry": {"coordinates":[1.0121819973,51.0818405151],"type":"Point"}
}