{
  "type": "Feature",
  "properties": {
    "addr:full":"Unit 7-8 Springmill Industrial Estat Stroud Gloucestershire GL6 0BS",
    "addr:housenumber":"unit 7-8",
    "addr:postcode":"gl6 0bs",
    "addr:street":"Springmill Industrial Estat",
    "iso:country":"GB",
    "sg:address":"Unit 7-8 Springmill Industrial Estat",
    "sg:city":"Stroud",
    "sg:classifiers":[
        {
            "category":"Ice Cream",
            "type":"Food & Drink"
        }
    ],
    "sg:postcode":"GL6 0BS",
    "sg:province":"Gloucestershire",
    "sg:tags":[
        "mnfr"
    ],
    "wof:name":"Midlands Ice Cream Supplies Ltd.",
    "wof:placetype":"venue"
},
  "geometry": {"coordinates":[-2.2141,51.694561],"type":"Point"}
}