{
  "type": "Feature",
  "properties": {
    "addr:full":"26 Castle Street Hinckley Leicestershire LE10 1DB",
    "addr:housenumber":"26",
    "addr:postcode":"le10 1db",
    "addr:street":"Castle Street",
    "iso:country":"GB",
    "sg:address":"26 Castle Street",
    "sg:city":"Hinckley",
    "sg:classifiers":[
        {
            "category":"Shopping",
            "subcategory":"Gifts & Souvenirs",
            "type":"Retail Goods"
        }
    ],
    "sg:phone":"+44 1455 890779",
    "sg:postcode":"LE10 1DB",
    "sg:province":"Leicestershire",
    "sg:tags":[
        "poster",
        "card"
    ],
    "wof:name":"Strand Cards & Gifts",
    "wof:placetype":"venue"
},
  "geometry": {"coordinates":[-1.371812,52.541588],"type":"Point"}
}