{
  "type": "Feature",
  "properties": {
    "addr:full":"Tyn Y Mynydd, Mynytho Pwllheli Gwynedd LL53 7PS",
    "addr:postcode":"ll53 7ps",
    "addr:street":"Tyn Y Mynydd Mynytho Pwllheli",
    "iso:country":"GB",
    "sg:address":"Tyn Y Mynydd, Mynytho",
    "sg:city":"Pwllheli",
    "sg:classifiers":[
        {
            "category":"Farming",
            "subcategory":"Livestock Farm",
            "type":"Manufacturing & Wholesale Goods"
        }
    ],
    "sg:phone":"+44 1758 740439",
    "sg:postcode":"LL53 7PS",
    "sg:province":"Gwynedd",
    "sg:tags":[
        "others"
    ],
    "wof:name":"A Jones",
    "wof:placetype":"venue"
},
  "geometry": {"coordinates":[-4.5166039467,52.8515510559],"type":"Point"}
}