{
  "type": "Feature",
  "properties": {
    "iso:country":"GB",
    "sg:address":"4 The Crossway",
    "sg:city":"London",
    "sg:classifiers":[
        {
            "category":"Professional",
            "subcategory":"Accounting & Tax Preparation",
            "type":"Services"
        }
    ],
    "sg:phone":"+44 20 8402 1596",
    "sg:postcode":"SE9 4JJ",
    "sg:province":"Greater London",
    "sg:tags":[
        "accountant",
        "activity"
    ],
    "wof:name":"J C Beames & Co",
    "wof:placetype":"venue"
},
  "geometry": {"coordinates":[0.03985,51.435581],"type":"Point"}
}