{
  "type": "Feature",
  "properties": {
    "addr:full":"4a Dukes Avenue, Chiswick Chiswick Greater London W4 2AE",
    "addr:housenumber":"4a",
    "addr:postcode":"w4 2ae",
    "addr:street":"Dukes Avenue",
    "iso:country":"GB",
    "sg:address":"4a Dukes Avenue, Chiswick",
    "sg:city":"Chiswick",
    "sg:classifiers":[
        {
            "category":"Autos & Motor Vehicles",
            "subcategory":"Motorcycle Sales",
            "type":"Retail Goods"
        }
    ],
    "sg:phone":"+44 20 8987 8661",
    "sg:postcode":"W4 2AE",
    "sg:province":"Greater London",
    "sg:tags":[
        "chauffeur",
        "driven",
        "car"
    ],
    "wof:name":"L & A Chauffeurs",
    "wof:placetype":"venue"
},
  "geometry": {"coordinates":[-0.2605729997,51.4919395447],"type":"Point"}
}