{
  "type": "Feature",
  "properties": {
    "iso:country":"GB",
    "sg:address":"48 Broadway, Pelsall",
    "sg:city":"Walsall",
    "sg:classifiers":[
        {
            "category":"Building & Trades",
            "subcategory":"Construction",
            "type":"Services"
        }
    ],
    "sg:phone":"+44 1922 683427",
    "sg:postcode":"WS4 1AN",
    "sg:province":"West Midlands",
    "sg:tags":[
        "decorator",
        "painter"
    ],
    "wof:name":"Trendorway Ltd.",
    "wof:placetype":"venue"
},
  "geometry": {"coordinates":[-1.955749,52.616409],"type":"Point"}
}