{
  "type": "Feature",
  "properties": {
    "iso:country":"GB",
    "sg:address":"4 Craignair St",
    "sg:city":"Dalbeattie",
    "sg:classifiers":[
        {
            "category":"Building & Trades",
            "subcategory":"Construction",
            "type":"Services"
        }
    ],
    "sg:phone":"+44 1556 612447",
    "sg:postcode":"DG5 4AX",
    "sg:province":"Dumfries and Galloway",
    "sg:tags":[
        "builder"
    ],
    "wof:name":"W.J. McDougall",
    "wof:placetype":"venue"
},
  "geometry": {"coordinates":[-3.8256309032,54.9323654175],"type":"Point"}
}