{
  "type": "Feature",
  "properties": {
    "addr:full":"The Old Park, Ingleby Lincoln Lincolnshire LN1 2PQ",
    "addr:postcode":"ln1 2pq",
    "iso:country":"GB",
    "sg:address":"The Old Park, Ingleby",
    "sg:city":"Lincoln",
    "sg:classifiers":[
        {
            "category":"Autos & Motor Vehicles",
            "subcategory":"Boat Sales",
            "type":"Retail Goods"
        }
    ],
    "sg:phone":"+44 1427 787987",
    "sg:postcode":"LN1 2PQ",
    "sg:province":"Lincolnshire",
    "sg:tags":[
        "repair",
        "builder"
    ],
    "wof:name":"Marine & Industrial Covers",
    "wof:placetype":"venue"
},
  "geometry": {"coordinates":[-0.66238,53.283463],"type":"Point"}
}