{
  "type": "Feature",
  "properties": {
    "iso:country":"GB",
    "sg:address":"2 Churchill Close",
    "sg:city":"Hereford",
    "sg:classifiers":[
        {
            "category":"Building & Trades",
            "subcategory":"Plumbing",
            "type":"Services"
        }
    ],
    "sg:phone":"+44 1432 270016",
    "sg:postcode":"HR1 1DH",
    "sg:province":"Herefordshire",
    "sg:tags":[
        "central",
        "heating"
    ],
    "wof:name":"Alex Quinn",
    "wof:placetype":"venue"
},
  "geometry": {"coordinates":[-2.701833,52.064651],"type":"Point"}
}