{
  "type": "Feature",
  "properties": {
    "iso:country":"GB",
    "sg:address":"Green Moor Bank, Old Hutton",
    "sg:city":"Kendal",
    "sg:classifiers":[
        {
            "category":"Travel",
            "subcategory":"Hotels & Motels",
            "type":"Entertainment"
        }
    ],
    "sg:postcode":"LA8 0NT",
    "sg:province":"Cumbria",
    "sg:tags":[
        "self",
        "catering"
    ],
    "wof:name":"Robertson Holidays",
    "wof:placetype":"venue"
},
  "geometry": {"coordinates":[-2.6803359985,54.2918586731],"type":"Point"}
}