{
  "type": "Feature",
  "properties": {
    "iso:country":"GB",
    "sg:address":"94 Poole Road",
    "sg:city":"Bournemouth",
    "sg:classifiers":[
        {
            "category":"Shopping",
            "subcategory":"Shoes",
            "type":"Retail Goods"
        }
    ],
    "sg:phone":"+44 1202 768019",
    "sg:postcode":"BH4 9EF",
    "sg:province":"Dorset",
    "wof:name":"Gullivers",
    "wof:placetype":"venue"
},
  "geometry": {"coordinates":[-1.903596,50.723312],"type":"Point"}
}