{
  "type": "Feature",
  "properties": {
    "addr:full":"17 St Georges Road Worthing West Sussex BN11 2DS",
    "addr:housenumber":"17",
    "addr:postcode":"bn11 2ds",
    "addr:street":"St Georges Road",
    "iso:country":"GB",
    "sg:address":"17 St Georges Road",
    "sg:city":"Worthing",
    "sg:classifiers":[
        {
            "category":"Travel",
            "subcategory":"Hotels & Motels",
            "type":"Entertainment"
        }
    ],
    "sg:postcode":"BN11 2DS",
    "sg:province":"West Sussex",
    "sg:tags":[
        "house",
        "guest"
    ],
    "wof:name":"Marcroft",
    "wof:placetype":"venue"
},
  "geometry": {"coordinates":[-0.3576849997,50.8136367798],"type":"Point"}
}