{
  "type": "Feature",
  "properties": {
    "addr:full":"Beckery Garage, Beckery Rd Glastonbury Somerset BA6 9NX",
    "addr:postcode":"ba6 9nx",
    "addr:street":"Beckery Rd",
    "iso:country":"GB",
    "sg:address":"Beckery Garage, Beckery Rd",
    "sg:city":"Glastonbury",
    "sg:classifiers":[
        {
            "category":"Military Area",
            "subcategory":"Air Force Base",
            "type":"Public Place"
        }
    ],
    "sg:phone":"+44 1458 832278",
    "sg:postcode":"BA6 9NX",
    "sg:province":"Somerset",
    "sg:tags":[
        "taxi",
        "hire",
        "private"
    ],
    "wof:name":"Chisletts Taxis",
    "wof:placetype":"venue"
},
  "geometry": {"coordinates":[-2.7170090675,51.1475906372],"type":"Point"}
}