{
  "type": "Feature",
  "properties": {
    "iso:country":"GB",
    "sg:address":"Sandown Works, Chairborough Road",
    "sg:city":"High Wycombe",
    "sg:classifiers":[
        {
            "category":"Shopping",
            "subcategory":"Musical Instruments",
            "type":"Retail Goods"
        }
    ],
    "sg:phone":"+44 1494 442925",
    "sg:postcode":"HP12 3HH",
    "sg:province":"Buckinghamshire",
    "wof:name":"Electric Wood",
    "wof:placetype":"venue"
},
  "geometry": {"coordinates":[-0.7740380168,51.629989624],"type":"Point"}
}