{
  "type": "Feature",
  "properties": {
    "iso:country":"GB",
    "sg:address":"20-26 Murraygate",
    "sg:city":"Dundee",
    "sg:classifiers":[
        {
            "category":"Shopping",
            "subcategory":"Shoes",
            "type":"Retail Goods"
        }
    ],
    "sg:phone":"+44 1382 201043",
    "sg:postcode":"DD1 2AZ",
    "sg:province":"Dundee City",
    "sg:tags":[
        "shop"
    ],
    "wof:name":"Dolcis",
    "wof:placetype":"venue"
},
  "geometry": {"coordinates":[-2.969039,56.462364],"type":"Point"}
}