{
  "type": "Feature",
  "properties": {
    "addr:full":"5th Flr,victoria Ho Queens Rd Norwich Norfolk NR1 3QQ",
    "addr:housenumber":"5th flr",
    "addr:postcode":"nr1 3qq",
    "addr:street":"Rd",
    "iso:country":"GB",
    "sg:address":"5th Flr,victoria Ho Queens Rd",
    "sg:city":"Norwich",
    "sg:classifiers":[
        {
            "category":"Insurance",
            "subcategory":"Insurance Agent",
            "type":"Services"
        }
    ],
    "sg:phone":"+44 1603 660202",
    "sg:postcode":"NR1 3QQ",
    "sg:province":"Norfolk",
    "sg:tags":[
        "broker"
    ],
    "wof:name":"Sedgwick Ltd",
    "wof:placetype":"venue"
},
  "geometry": {"coordinates":[1.2949,52.622494],"type":"Point"}
}