{
  "type": "Feature",
  "properties": {
    "iso:country":"GB",
    "sg:address":"46 Stamford Rd, Mossley",
    "sg:city":"Ashton-under-lyne",
    "sg:classifiers":[
        {
            "category":"Organizations",
            "subcategory":"Political Organization",
            "type":"Services"
        }
    ],
    "sg:postcode":"OL5 0BE",
    "sg:province":"Greater Manchester",
    "sg:tags":[
        "party"
    ],
    "wof:name":"Ford,Glyn,",
    "wof:placetype":"venue"
},
  "geometry": {"coordinates":[-2.0417420864,53.5164375305],"type":"Point"}
}