{
  "type": "Feature",
  "properties": {
    "iso:country":"GB",
    "sg:address":"63 North Street",
    "sg:city":"Sudbury",
    "sg:classifiers":[
        {
            "category":"Real Estate",
            "subcategory":"Surveying",
            "type":"Services"
        }
    ],
    "sg:postcode":"CO10 1RE",
    "sg:province":"Essex",
    "sg:tags":[
        "surveyor",
        "valuer"
    ],
    "wof:name":"Birchall Steel",
    "wof:placetype":"venue"
},
  "geometry": {"coordinates":[0.730071,52.041069],"type":"Point"}
}