{
  "type": "Feature",
  "properties": {
    "addr:full":"43 Reddish La, Gorton Manchester Greater Manchester M18 7JH",
    "addr:housenumber":"43",
    "addr:postcode":"m18 7jh",
    "addr:street":"Reddish La Gorton",
    "iso:country":"GB",
    "sg:address":"43 Reddish La, Gorton",
    "sg:city":"Manchester",
    "sg:classifiers":[
        {
            "category":"Shopping",
            "subcategory":"Department Store",
            "type":"Retail Goods"
        }
    ],
    "sg:postcode":"M18 7JH",
    "sg:province":"Greater Manchester",
    "wof:name":"Wool Baa (The)",
    "wof:placetype":"venue"
},
  "geometry": {"coordinates":[-2.159807,53.456726],"type":"Point"}
}