{
  "type": "Feature",
  "properties": {
    "addr:full":"Deborah Drive, Chaddesden Derby Derbyshire DE21 4RJ",
    "addr:postcode":"de21 4rj",
    "addr:street":"Deborah Drive",
    "iso:country":"GB",
    "sg:address":"Deborah Drive, Chaddesden",
    "sg:city":"Derby",
    "sg:classifiers":[
        {
            "category":"Education",
            "subcategory":"School",
            "type":"Public Place"
        }
    ],
    "sg:phone":"+44 1332 672338",
    "sg:postcode":"DE21 4RJ",
    "sg:province":"Derbyshire",
    "sg:tags":[
        "local",
        "authority"
    ],
    "wof:name":"Cavendish Close Junior School",
    "wof:placetype":"venue"
},
  "geometry": {"coordinates":[-1.429616,52.932823],"type":"Point"}
}