{
  "type": "Feature",
  "properties": {
    "addr:full":"171a Chepstow Road Newport Newport NP19 8GH",
    "addr:housenumber":"171a",
    "addr:postcode":"np19 8gh",
    "addr:street":"Chepstow Road",
    "iso:country":"GB",
    "sg:address":"171a Chepstow Road",
    "sg:city":"Newport",
    "sg:classifiers":[
        {
            "category":"Retail",
            "subcategory":"Auto Repair",
            "type":"Services"
        }
    ],
    "sg:postcode":"NP19 8GH",
    "sg:province":"Newport",
    "sg:tags":[
        "body",
        "car"
    ],
    "wof:name":"Gwent Resprays Ltd",
    "wof:placetype":"venue"
},
  "geometry": {"coordinates":[-2.9768230915,51.5897445679],"type":"Point"}
}