{
  "type": "Feature",
  "properties": {
    "addr:full":"79 Braunstone Gate Leicester Leicestershire LE3 5LH",
    "addr:housenumber":"79",
    "addr:postcode":"le3 5lh",
    "addr:street":"Braunstone Gate",
    "iso:country":"GB",
    "sg:address":"79 Braunstone Gate",
    "sg:city":"Leicester",
    "sg:classifiers":[
        {
            "category":"Fast Food",
            "type":"Food & Drink"
        }
    ],
    "sg:phone":"+44 116 275 5768",
    "sg:postcode":"LE3 5LH",
    "sg:province":"Leicestershire",
    "sg:tags":[
        "away",
        "take"
    ],
    "wof:name":"Le Pantry",
    "wof:placetype":"venue"
},
  "geometry": {"coordinates":[-1.1468700171,52.630821228],"type":"Point"}
}