{
  "type": "Feature",
  "properties": {
    "addr:full":"The Limes, 7 Brackley Road Towcester Buckinghamshire NN12 6DH",
    "addr:housenumber":"7",
    "addr:postcode":"nn12 6dh",
    "addr:street":"The Limes;Brackley Road",
    "iso:country":"GB",
    "sg:address":"The Limes, 7 Brackley Road",
    "sg:city":"Towcester",
    "sg:classifiers":[
        {
            "category":"Real Estate",
            "subcategory":"Real Estate Agent",
            "type":"Services"
        }
    ],
    "sg:postcode":"NN12 6DH",
    "sg:province":"Buckinghamshire",
    "wof:name":"John Newman Properties (71 Watling Stree",
    "wof:placetype":"venue"
},
  "geometry": {"coordinates":[-0.9870089889,52.1305084229],"type":"Point"}
}