{
  "type": "Feature",
  "properties": {
    "addr:full":"40 The Promenade Withernsea East Riding of Yorkshire HU19 2DW",
    "addr:housenumber":"40",
    "addr:postcode":"hu19 2dw",
    "addr:street":"The Promenade",
    "iso:country":"GB",
    "sg:address":"40 The Promenade",
    "sg:city":"Withernsea",
    "sg:classifiers":[
        {
            "category":"Travel",
            "subcategory":"Hotels & Motels",
            "type":"Entertainment"
        }
    ],
    "sg:phone":"+44 1964 612483",
    "sg:postcode":"HU19 2DW",
    "sg:province":"East Riding of Yorkshire",
    "sg:tags":[
        "house",
        "guest"
    ],
    "wof:name":"St Hilda Guest House",
    "wof:placetype":"venue"
},
  "geometry": {"coordinates":[0.0330349989,53.7302818298],"type":"Point"}
}