{
  "type": "Feature",
  "properties": {
    "addr:full":"40-42 High Street North East Ham Greater London E6 2HJ",
    "addr:housenumber":"40-42",
    "addr:postcode":"e6 2hj",
    "addr:street":"High Street North",
    "iso:country":"GB",
    "sg:address":"40-42 High Street North",
    "sg:city":"East Ham",
    "sg:classifiers":[
        {
            "category":"Real Estate",
            "subcategory":"Real Estate Agent",
            "type":"Services"
        }
    ],
    "sg:phone":"+44 20 8471 2313",
    "sg:postcode":"E6 2HJ",
    "sg:province":"Greater London",
    "wof:name":"J H Friend",
    "wof:placetype":"venue"
},
  "geometry": {"coordinates":[0.0536140017,51.5343093872],"type":"Point"}
}