{
  "type": "Feature",
  "properties": {
    "iso:country":"GB",
    "sg:address":"Invergordon Boat Yard, 37 Shore Road",
    "sg:city":"Invergordon",
    "sg:classifiers":[
        {
            "category":"Farming",
            "subcategory":"Farm",
            "type":"Manufacturing & Wholesale Goods"
        }
    ],
    "sg:phone":"+44 1349 852611",
    "sg:postcode":"IV18 0EH",
    "sg:province":"Highland",
    "sg:tags":[
        "hatchery"
    ],
    "wof:name":"J P Knight (Caledonian) Ltd.",
    "wof:placetype":"venue"
},
  "geometry": {"coordinates":[-4.166444,57.687851],"type":"Point"}
}