{
  "type": "Feature",
  "properties": {
    "addr:full":"Ebberston Road West, Rhos On Sea Colwyn Bay Conwy LL28 4AP",
    "addr:postcode":"ll28 4ap",
    "addr:street":"Ebberston Road West Rhos On",
    "iso:country":"GB",
    "sg:address":"Ebberston Road West, Rhos On Sea",
    "sg:city":"Colwyn Bay",
    "sg:classifiers":[
        {
            "category":"Health Services",
            "subcategory":"Nursing And Care Facility",
            "type":"Services"
        },
        {
            "category":"Social Services",
            "subcategory":"Retirement Home",
            "type":"Services"
        }
    ],
    "sg:phone":"+44 1492 544231",
    "sg:postcode":"LL28 4AP",
    "sg:province":"Conwy",
    "sg:tags":[
        "residential"
    ],
    "wof:name":"ABBEYDENE PRIVATE HOME FOR THE ELDERLY",
    "wof:placetype":"venue"
},
  "geometry": {"coordinates":[-3.745125,53.302219],"type":"Point"}
}