{
  "type": "Feature",
  "properties": {
    "iso:country":"GB",
    "sg:address":"28 Cricklade Street",
    "sg:city":"Cirencester",
    "sg:classifiers":[
        {
            "category":"Food & Beverages",
            "subcategory":"Candy",
            "type":"Retail Goods"
        }
    ],
    "sg:phone":"+44 1285 656929",
    "sg:postcode":"GL7 1JH",
    "sg:province":"Gloucestershire",
    "sg:tags":[
        "confectioner"
    ],
    "wof:name":"Thorntons plc",
    "wof:placetype":"venue"
},
  "geometry": {"coordinates":[-1.967859,51.715946],"type":"Point"}
}