{
  "type": "Feature",
  "properties": {
    "addr:full":"1st Floor, 20a The Borough Hinckley Leicestershire LE10 1NL",
    "addr:housenumber":"20a",
    "addr:postcode":"le10 1nl",
    "addr:street":"Floor",
    "iso:country":"GB",
    "sg:address":"1st Floor, 20a The Borough",
    "sg:city":"Hinckley",
    "sg:classifiers":[
        {
            "category":"Professional",
            "subcategory":"Detective & Security Services",
            "type":"Services"
        }
    ],
    "sg:postcode":"LE10 1NL",
    "sg:province":"Leicestershire",
    "wof:name":"Fortress Security Services Ltd",
    "wof:placetype":"venue"
},
  "geometry": {"coordinates":[-1.373575,52.542137],"type":"Point"}
}