{
  "type": "Feature",
  "properties": {
    "addr:full":"Ballance Road London Greater London E9 5SR",
    "addr:postcode":"e9 5sr",
    "addr:street":"Ballance Road",
    "iso:country":"GB",
    "sg:address":"Ballance Road",
    "sg:city":"London",
    "sg:classifiers":[
        {
            "category":"Education",
            "subcategory":"School",
            "type":"Public Place"
        }
    ],
    "sg:phone":"+44 20 8985 6438",
    "sg:postcode":"E9 5SR",
    "sg:province":"Greater London",
    "sg:tags":[
        "local",
        "authority"
    ],
    "wof:name":"ST DOMINIC'S R C JUNIOR SCHOOL",
    "wof:placetype":"venue"
},
  "geometry": {"coordinates":[-0.040164,51.545761],"type":"Point"}
}