{
  "type": "Feature",
  "properties": {
    "addr:full":"2 Upperton Gardens Eastbourne East Sussex BN21 2AH",
    "addr:housenumber":"2",
    "addr:postcode":"bn21 2ah",
    "addr:street":"Upperton Gardens",
    "iso:country":"GB",
    "sg:address":"2 Upperton Gardens",
    "sg:city":"Eastbourne",
    "sg:classifiers":[
        {
            "category":"Retail",
            "subcategory":"Storage",
            "type":"Services"
        }
    ],
    "sg:postcode":"BN21 2AH",
    "sg:province":"East Sussex",
    "sg:tags":[
        "household",
        "removal"
    ],
    "wof:name":"Plant Handling Services Ltd.",
    "wof:placetype":"venue"
},
  "geometry": {"coordinates":[0.279742,50.771328],"type":"Point"}
}