{
  "type": "Feature",
  "properties": {
    "addr:full":"15a Dean Road London Greater London NW2 5AB",
    "addr:housenumber":"15a",
    "addr:postcode":"nw2 5ab",
    "addr:street":"Dean Road",
    "iso:country":"GB",
    "sg:address":"15a Dean Road",
    "sg:city":"London",
    "sg:classifiers":[
        {
            "category":"Communications",
            "subcategory":"Film & Video Production",
            "type":"Services"
        },
        {
            "category":"Communications",
            "type":"Services"
        }
    ],
    "sg:phone":"+44 20 8830 3727",
    "sg:postcode":"NW2 5AB",
    "sg:province":"Greater London",
    "sg:tags":[
        "tv",
        "studio",
        "audio-visual"
    ],
    "wof:name":"Pipedream Pictures Ltd.",
    "wof:placetype":"venue"
},
  "geometry": {"coordinates":[-0.2237749994,51.5484542847],"type":"Point"}
}