{
  "type": "Feature",
  "properties": {
    "addr:full":"86 Hereford Road, Holland On Sea Clacton-on-sea Essex CO15 5SU",
    "addr:housenumber":"86",
    "addr:postcode":"co15 5su",
    "addr:street":"Hereford Road",
    "iso:country":"GB",
    "sg:address":"86 Hereford Road, Holland On Sea",
    "sg:city":"Clacton-on-sea",
    "sg:classifiers":[
        {
            "category":"Retail",
            "subcategory":"Driving School",
            "type":"Services"
        }
    ],
    "sg:phone":"+44 1255 813957",
    "sg:postcode":"CO15 5SU",
    "sg:province":"Essex",
    "wof:name":"A E W School of Motoring",
    "wof:placetype":"venue"
},
  "geometry": {"coordinates":[1.197543,51.803967],"type":"Point"}
}