{
  "type": "Feature",
  "properties": {
    "iso:country":"GB",
    "sg:address":"Flower Shop, London Hilton Hotel, 2 Park Lane",
    "sg:city":"West End",
    "sg:classifiers":[
        {
            "category":"Shopping",
            "subcategory":"Florist",
            "type":"Retail Goods"
        }
    ],
    "sg:phone":"+44 20 7629 3355",
    "sg:postcode":"W1Y 4BE",
    "sg:province":"Hampshire",
    "wof:name":"Angela Saunders",
    "wof:placetype":"venue"
},
  "geometry": {"coordinates":[-0.152263999,51.5068626404],"type":"Point"}
}