{
  "type": "Feature",
  "properties": {
    "addr:full":"Farnham Road Guildford Surrey GU2 4LU",
    "addr:postcode":"gu2 4lu",
    "addr:street":"Farnham Road",
    "iso:country":"GB",
    "sg:address":"Farnham Road",
    "sg:city":"Guildford",
    "sg:classifiers":[
        {
            "category":"Education",
            "subcategory":"School",
            "type":"Public Place"
        }
    ],
    "sg:phone":"+44 1483 504089",
    "sg:postcode":"GU2 4LU",
    "sg:province":"Surrey",
    "sg:tags":[
        "college"
    ],
    "wof:name":"Guildford County School",
    "wof:placetype":"venue"
},
  "geometry": {"coordinates":[-0.5833989978,51.2351417542],"type":"Point"}
}