{
  "type": "Feature",
  "properties": {
    "addr:full":"Bramble Lodge, The Shrubbery, Elford Tamworth Staffordshire B79 9BX",
    "addr:postcode":"b79 9bx",
    "addr:street":"The;Elford",
    "iso:country":"GB",
    "sg:address":"Bramble Lodge, The Shrubbery, Elford",
    "sg:city":"Tamworth",
    "sg:classifiers":[
        {
            "category":"Professional",
            "subcategory":"Art Services",
            "type":"Services"
        }
    ],
    "sg:postcode":"B79 9BX",
    "sg:province":"Staffordshire",
    "sg:tags":[
        "graphic",
        "designer"
    ],
    "wof:name":"D W Design",
    "wof:placetype":"venue"
},
  "geometry": {"coordinates":[-1.7159340382,52.6912994385],"type":"Point"}
}