{
  "type": "Feature",
  "properties": {
    "addr:full":"117 Church Street, Walmer Deal Kent CT14 7RP",
    "addr:housenumber":"117",
    "addr:postcode":"ct14 7rp",
    "addr:street":"Church Street",
    "iso:country":"GB",
    "sg:address":"117 Church Street, Walmer",
    "sg:city":"Deal",
    "sg:classifiers":[
        {
            "category":"Professional",
            "subcategory":"Engineering",
            "type":"Services"
        },
        {
            "category":"Building & Trades",
            "subcategory":"Electrical",
            "type":"Services"
        }
    ],
    "sg:phone":"+44 1304 372946",
    "sg:postcode":"CT14 7RP",
    "sg:province":"Kent",
    "sg:tags":[
        "engineer",
        "electrician",
        "contractor"
    ],
    "wof:name":"Peter Ladd Electrical Contractor",
    "wof:placetype":"venue"
},
  "geometry": {"coordinates":[1.385699,51.204678],"type":"Point"}
}