{
  "type": "Feature",
  "properties": {
    "iso:country":"GB",
    "sg:address":"Sandy Road, Scone",
    "sg:city":"Perth",
    "sg:classifiers":[
        {
            "category":"Education",
            "subcategory":"Library",
            "type":"Public Place"
        }
    ],
    "sg:postcode":"PH2 6JL",
    "sg:province":"Perth and Kinross",
    "sg:tags":[
        "book"
    ],
    "wof:name":"Scone Library",
    "wof:placetype":"venue"
},
  "geometry": {"coordinates":[-3.406808,56.422775],"type":"Point"}
}