{
  "type": "Feature",
  "properties": {
    "iso:country":"GB",
    "sg:address":"Dale Road",
    "sg:city":"Matlock",
    "sg:classifiers":[
        {
            "category":"Bars & Pubs",
            "subcategory":"Wine Bar",
            "type":"Food & Drink"
        }
    ],
    "sg:phone":"+44 1629 584452",
    "sg:postcode":"DE4 3LT",
    "sg:province":"Derbyshire",
    "wof:name":"Shakespeares Wine Bar",
    "wof:placetype":"venue"
},
  "geometry": {"coordinates":[-1.555604,53.136284],"type":"Point"}
}