{
  "type": "Feature",
  "properties": {
    "iso:country":"GB",
    "sg:address":"7 Artillery Passage",
    "sg:city":"London",
    "sg:classifiers":[
        {
            "category":"Manufacturing",
            "subcategory":"Textiles",
            "type":"Manufacturing & Wholesale Goods"
        }
    ],
    "sg:phone":"+44 20 7833 0933",
    "sg:postcode":"E1 7LJ",
    "sg:province":"Greater London",
    "sg:tags":[
        "knitwear"
    ],
    "wof:name":"D P Marwaha & Bros Ltd.",
    "wof:placetype":"venue"
},
  "geometry": {"coordinates":[-0.0791340023,51.5185432434],"type":"Point"}
}