{
  "type": "Feature",
  "properties": {
    "iso:country":"GB",
    "sg:address":"15 Mill Grn, Warboys",
    "sg:city":"Huntingdon",
    "sg:classifiers":[
        {
            "category":"Building & Trades",
            "subcategory":"Electrical",
            "type":"Services"
        }
    ],
    "sg:postcode":"PE28 2SA",
    "sg:province":"Bedfordshire",
    "sg:tags":[
        "lighting"
    ],
    "wof:name":"A J Bernasconi",
    "wof:placetype":"venue"
},
  "geometry": {"coordinates":[-0.074474,52.403793],"type":"Point"}
}