{
  "type": "Feature",
  "properties": {
    "addr:full":"Hangar C2 Site C, Kemble Enterprise Park, Kemble Cirencester Gloucestershire GL7 6FD",
    "addr:postcode":"gl7 6fd",
    "iso:country":"GB",
    "sg:address":"Hangar C2 Site C, Kemble Enterprise Park, Kemble",
    "sg:city":"Cirencester",
    "sg:classifiers":[
        {
            "category":"Military Area",
            "subcategory":"Air Force Base",
            "type":"Public Place"
        }
    ],
    "sg:phone":"+44 1285 770095",
    "sg:postcode":"GL7 6FD",
    "sg:province":"Gloucestershire",
    "sg:tags":[
        "engine",
        "aircraft"
    ],
    "wof:name":"Devonair Aviation Services Ltd.",
    "wof:placetype":"venue"
},
  "geometry": {"coordinates":[-2.0183339119,51.6752090454],"type":"Point"}
}