{
  "type": "Feature",
  "properties": {
    "addr:full":"1 Barton Road Tiverton Devon EX16 6BB",
    "addr:housenumber":"1",
    "addr:postcode":"ex16 6bb",
    "addr:street":"Barton Road",
    "iso:country":"GB",
    "sg:address":"1 Barton Road",
    "sg:city":"Tiverton",
    "sg:classifiers":[
        {
            "category":"Professional",
            "subcategory":"Engineering",
            "type":"Services"
        },
        {
            "category":"Building & Trades",
            "subcategory":"Electrical",
            "type":"Services"
        }
    ],
    "sg:phone":"+44 1884 258009",
    "sg:postcode":"EX16 6BB",
    "sg:province":"Devon",
    "sg:tags":[
        "engineer",
        "electrician",
        "contractor"
    ],
    "wof:name":"GARRY S PRATT",
    "wof:placetype":"venue"
},
  "geometry": {"coordinates":[-3.4854938984,50.9132575989],"type":"Point"}
}