{
  "type": "Feature",
  "properties": {
    "addr:full":"Play For Children Play Centre, Mansfield Road Nottingham Nottinghamshire NG5 3FN",
    "addr:postcode":"ng5 3fn",
    "addr:street":"Mansfield Road",
    "iso:country":"GB",
    "sg:address":"Play For Children Play Centre, Mansfield Road",
    "sg:city":"Nottingham",
    "sg:classifiers":[
        {
            "category":"Organizations",
            "subcategory":"Non-profit Organization",
            "type":"Services"
        }
    ],
    "sg:phone":"+44 115 969 3432",
    "sg:postcode":"NG5 3FN",
    "sg:province":"Nottinghamshire",
    "sg:tags":[
        "organisation",
        "voluntary",
        "charity"
    ],
    "wof:name":"The Play Centre for Disabled Children & Young People  & Thei",
    "wof:placetype":"venue"
},
  "geometry": {"coordinates":[-1.14343,52.986229],"type":"Point"}
}