{
  "type": "Feature",
  "properties": {
    "addr:full":"14 Brecknock Road London Greater London N7 0DD",
    "addr:housenumber":"14",
    "addr:postcode":"n7 0dd",
    "addr:street":"Brecknock Road",
    "iso:country":"GB",
    "sg:address":"14 Brecknock Road",
    "sg:city":"London",
    "sg:classifiers":[
        {
            "category":"Cafe",
            "type":"Food & Drink"
        }
    ],
    "sg:phone":"+44 20 7607 1169",
    "sg:postcode":"N7 0DD",
    "sg:province":"Greater London",
    "sg:tags":[
        "tea",
        "room"
    ],
    "wof:name":"Sunrise Cafeteria Ltd.",
    "wof:placetype":"venue"
},
  "geometry": {"coordinates":[-0.129356,51.549183],"type":"Point"}
}