{
  "type": "Feature",
  "properties": {
    "addr:full":"19 Cookridge Street Leeds West Yorkshire LS2 3AG",
    "addr:housenumber":"19",
    "addr:postcode":"ls2 3ag",
    "addr:street":"Cookridge Street",
    "iso:country":"GB",
    "sg:address":"19 Cookridge Street",
    "sg:city":"Leeds",
    "sg:classifiers":[
        {
            "category":"Banks & Credit Unions",
            "subcategory":"Investment Brokerage",
            "type":"Services"
        }
    ],
    "sg:postcode":"LS2 3AG",
    "sg:province":"West Yorkshire",
    "sg:tags":[
        "fund",
        "raising"
    ],
    "wof:name":"V.I. Projects Ltd",
    "wof:placetype":"venue"
},
  "geometry": {"coordinates":[-1.5474150181,53.8000984192],"type":"Point"}
}