{
  "type": "Feature",
  "properties": {
    "iso:country":"GB",
    "sg:address":"94 Talbot Road",
    "sg:city":"Port Talbot",
    "sg:classifiers":[
        {
            "category":"Restaurant",
            "type":"Food & Drink"
        }
    ],
    "sg:phone":"+44 1639 769499",
    "sg:postcode":"SA13 1LB",
    "sg:province":"Neath Port Talbot",
    "sg:tags":[
        "indian",
        "-"
    ],
    "wof:name":"Imran Khan",
    "wof:placetype":"venue"
},
  "geometry": {"coordinates":[-3.775869,51.588619],"type":"Point"}
}