{
  "type": "Feature",
  "properties": {
    "addr:full":"Kings Road Dereham Norfolk NR19 2AG",
    "addr:postcode":"nr19 2ag",
    "addr:street":"Kings Road",
    "iso:country":"GB",
    "sg:address":"Kings Road",
    "sg:city":"Dereham",
    "sg:classifiers":[
        {
            "category":"Education",
            "subcategory":"School",
            "type":"Public Place"
        }
    ],
    "sg:phone":"+44 1362 694077",
    "sg:postcode":"NR19 2AG",
    "sg:province":"Norfolk",
    "sg:tags":[
        "local",
        "authority"
    ],
    "wof:name":"NORFOLK COUNTY COUNCIL",
    "wof:placetype":"venue"
},
  "geometry": {"coordinates":[0.9444169998,52.6844062805],"type":"Point"}
}