{
  "type": "Feature",
  "properties": {
    "addr:full":"223 Euston Gro Morecambe Lancashire LA4 5LH",
    "addr:housenumber":"223",
    "addr:postcode":"la4 5lh",
    "addr:street":"Euston Gro Morecambe",
    "iso:country":"GB",
    "sg:address":"223 Euston Gro",
    "sg:city":"Morecambe",
    "sg:classifiers":[
        {
            "category":"Food & Beverages",
            "subcategory":"Bakery",
            "type":"Retail Goods"
        }
    ],
    "sg:postcode":"LA4 5LH",
    "sg:province":"Lancashire",
    "sg:tags":[
        "baker"
    ],
    "wof:name":"Hadwins Bakers",
    "wof:placetype":"venue"
},
  "geometry": {"coordinates":[-2.852588892,54.0696601868],"type":"Point"}
}