{
  "type": "Feature",
  "properties": {
    "addr:full":"Unit 8, Wadsworth Close, Perrivale Greenford Greater London UB6 7JD",
    "addr:housenumber":"unit 8",
    "addr:postcode":"ub6 7jd",
    "addr:street":"Wadsworth Close",
    "iso:country":"GB",
    "sg:address":"Unit 8, Wadsworth Close, Perrivale",
    "sg:city":"Greenford",
    "sg:classifiers":[
        {
            "category":"Retail",
            "subcategory":"Auto Repair",
            "type":"Services"
        }
    ],
    "sg:phone":"+44 20 8998 0062",
    "sg:postcode":"UB6 7JD",
    "sg:province":"Greater London",
    "sg:tags":[
        "modification",
        "garage"
    ],
    "wof:name":"Autotech",
    "wof:placetype":"venue"
},
  "geometry": {"coordinates":[-0.3129589856,51.5353240967],"type":"Point"}
}