{
  "type": "Feature",
  "properties": {
    "addr:full":"Nfc House Vickers Industrial Estate, Mellishaw Lane Morecambe Lancashire LA3 3DY",
    "addr:postcode":"la3 3dy",
    "addr:street":"Vickers Industrial;Mellishaw Lane",
    "iso:country":"GB",
    "sg:address":"Nfc House Vickers Industrial Estate, Mellishaw Lane",
    "sg:city":"Morecambe",
    "sg:classifiers":[
        {
            "category":"Building & Trades",
            "subcategory":"Plumbing",
            "type":"Services"
        },
        {
            "category":"Bus Stop",
            "subcategory":"None",
            "type":"Transportation"
        }
    ],
    "sg:phone":"+44 1524 388696",
    "sg:postcode":"LA3 3DY",
    "sg:province":"Lancashire",
    "sg:tags":[
        "filter",
        "filtration",
        "system"
    ],
    "wof:name":"Air Safety Ltd.",
    "wof:placetype":"venue"
},
  "geometry": {"coordinates":[-2.850855,54.056004],"type":"Point"}
}