{
  "type": "Feature",
  "properties": {
    "addr:full":"Churchend Banbury Northamptonshire OX17 1DZ",
    "addr:postcode":"ox17 1dz",
    "iso:country":"GB",
    "sg:address":"Churchend",
    "sg:city":"Banbury",
    "sg:classifiers":[
        {
            "category":"Professional",
            "subcategory":"Engineering",
            "type":"Services"
        }
    ],
    "sg:phone":"+44 1295 690600",
    "sg:postcode":"OX17 1DZ",
    "sg:province":"Northamptonshire",
    "sg:tags":[
        "engineer"
    ],
    "wof:name":"Steve Prentice Design Ltd.",
    "wof:placetype":"venue"
},
  "geometry": {"coordinates":[-1.3686599731,52.1432495117],"type":"Point"}
}