{
  "type": "Feature",
  "properties": {
    "iso:country":"GB",
    "sg:address":"What-a-joy, Durnford Drove",
    "sg:city":"Swanage",
    "sg:classifiers":[
        {
            "category":"Building & Trades",
            "subcategory":"Plumbing",
            "type":"Services"
        }
    ],
    "sg:phone":"+44 1929 425390",
    "sg:postcode":"BH19 3HG",
    "sg:province":"Dorset",
    "sg:tags":[
        "plumber",
        "heating"
    ],
    "wof:name":"A P T Plumbing",
    "wof:placetype":"venue"
},
  "geometry": {"coordinates":[-1.9640660286,50.6119842529],"type":"Point"}
}