{
  "type": "Feature",
  "properties": {
    "addr:full":"Old Wheel Ho, Church St Reigate Surrey RH2 0AD",
    "addr:postcode":"rh2 0ad",
    "addr:street":"Old;St",
    "iso:country":"GB",
    "sg:address":"Old Wheel Ho, Church St",
    "sg:city":"Reigate",
    "sg:classifiers":[
        {
            "category":"Professional",
            "subcategory":"Lawyer & Legal Services",
            "type":"Services"
        }
    ],
    "sg:postcode":"RH2 0AD",
    "sg:province":"Surrey",
    "sg:tags":[
        "solicitor"
    ],
    "wof:name":"Beeney,G E,",
    "wof:placetype":"venue"
},
  "geometry": {"coordinates":[-0.2047789991,51.2357444763],"type":"Point"}
}