{
  "type": "Feature",
  "properties": {
    "iso:country":"GB",
    "sg:address":"113 High Street, Skelton",
    "sg:city":"Saltburn-by-the-sea",
    "sg:classifiers":[
        {
            "category":"Real Estate",
            "subcategory":"Real Estate Agent",
            "type":"Services"
        }
    ],
    "sg:phone":"+44 1287 650994",
    "sg:postcode":"TS12 2DY",
    "sg:province":"North Yorkshire",
    "wof:name":"Skelton & Brotton General Insurance Brokers",
    "wof:placetype":"venue"
},
  "geometry": {"coordinates":[-0.930175,54.56929],"type":"Point"}
}