{
  "type": "Feature",
  "properties": {
    "addr:full":"5 Old Nichol St Bethnal Green Greater London E2 7HR",
    "addr:housenumber":"5",
    "addr:postcode":"e2 7hr",
    "addr:street":"Old Nichol St Bethnal Green",
    "iso:country":"GB",
    "sg:address":"5 Old Nichol St",
    "sg:city":"Bethnal Green",
    "sg:classifiers":[
        {
            "category":"Professional",
            "subcategory":"Art Services",
            "type":"Services"
        }
    ],
    "sg:phone":"+44 7710 035999",
    "sg:postcode":"E2 7HR",
    "sg:province":"Greater London",
    "sg:tags":[
        "photographer"
    ],
    "wof:name":"Musgrave T",
    "wof:placetype":"venue"
},
  "geometry": {"coordinates":[-0.074094,51.524769],"type":"Point"}
}