{
  "type": "Feature",
  "properties": {
    "addr:full":"Harewood Court, Wilbury Road Hove East Sussex BN3 3GL",
    "addr:postcode":"bn3 3gl",
    "addr:street":"Harewood Court Wilbury Road",
    "iso:country":"GB",
    "sg:address":"Harewood Court, Wilbury Road",
    "sg:city":"Hove",
    "sg:classifiers":[
        {
            "category":"Social Services",
            "subcategory":"Adult Care",
            "type":"Services"
        }
    ],
    "sg:phone":"+44 1273 739515",
    "sg:postcode":"BN3 3GL",
    "sg:province":"East Sussex",
    "sg:tags":[
        "housing",
        "sheltered"
    ],
    "wof:name":"Royal Masonic Benevolent Institution",
    "wof:placetype":"venue"
},
  "geometry": {"coordinates":[-0.166128993,50.8293190002],"type":"Point"}
}