{
  "type": "Feature",
  "properties": {
    "iso:country":"GB",
    "sg:address":"47 Manor Rd",
    "sg:city":"Romney Marsh",
    "sg:classifiers":[
        {
            "category":"Building & Trades",
            "subcategory":"Landscaping Services",
            "type":"Services"
        }
    ],
    "sg:phone":"+44 1797 320633",
    "sg:postcode":"TN29 9HR",
    "sg:province":"Kent",
    "sg:tags":[
        "contractor",
        "drainage"
    ],
    "wof:name":"David Wild",
    "wof:placetype":"venue"
},
  "geometry": {"coordinates":[0.910018,50.949615],"type":"Point"}
}