{
  "type": "Feature",
  "properties": {
    "iso:country":"GB",
    "sg:address":"24 Silver Street",
    "sg:city":"Bury",
    "sg:classifiers":[
        {
            "category":"Bars & Pubs",
            "type":"Food & Drink"
        }
    ],
    "sg:phone":"+44 161 764 4321",
    "sg:postcode":"BL9 0DH",
    "sg:province":"Lancashire",
    "sg:tags":[
        "pubs",
        "inn"
    ],
    "wof:name":"The Royal Hotel",
    "wof:placetype":"venue"
},
  "geometry": {"coordinates":[-2.2989358902,53.5926704407],"type":"Point"}
}