{
  "type": "Feature",
  "properties": {
    "addr:full":"22 Grove Road, Barton New Milton Hampshire BH25 7JD",
    "addr:housenumber":"22",
    "addr:postcode":"bh25 7jd",
    "addr:street":"Grove Road",
    "iso:country":"GB",
    "sg:address":"22 Grove Road, Barton",
    "sg:city":"New Milton",
    "sg:classifiers":[
        {
            "category":"Building & Trades",
            "subcategory":"Construction",
            "type":"Services"
        }
    ],
    "sg:phone":"+44 1425 612483",
    "sg:postcode":"BH25 7JD",
    "sg:province":"Hampshire",
    "sg:tags":[
        "joiner",
        "carpenter"
    ],
    "wof:name":"K J Kilford Loft Conversion Specialist",
    "wof:placetype":"venue"
},
  "geometry": {"coordinates":[-1.6593420506,50.736743927],"type":"Point"}
}