{
  "type": "Feature",
  "properties": {
    "addr:full":"101 Longmore Avenue, New Barnet Barnet Hertfordshire EN5 1JZ",
    "addr:housenumber":"101",
    "addr:postcode":"en5 1jz",
    "addr:street":"Longmore Avenue",
    "iso:country":"GB",
    "sg:address":"101 Longmore Avenue, New Barnet",
    "sg:city":"Barnet",
    "sg:classifiers":[
        {
            "category":"Health Services",
            "subcategory":"Health Practitioner",
            "type":"Services"
        }
    ],
    "sg:phone":"+44 20 8441 8726",
    "sg:postcode":"EN5 1JZ",
    "sg:province":"Hertfordshire",
    "sg:tags":[
        "osteopath"
    ],
    "wof:name":"Paul Field",
    "wof:placetype":"venue"
},
  "geometry": {"coordinates":[-0.1755460054,51.6434020996],"type":"Point"}
}