{
  "type": "Feature",
  "properties": {
    "addr:full":"39-51 Highgate Rd Kentish Town Greater London NW5 1RS",
    "addr:housenumber":"39-51",
    "addr:postcode":"nw5 1rs",
    "addr:street":"Highgate Rd",
    "iso:country":"GB",
    "sg:address":"39-51 Highgate Rd",
    "sg:city":"Kentish Town",
    "sg:classifiers":[
        {
            "category":"Real Estate",
            "subcategory":"Architect",
            "type":"Services"
        }
    ],
    "sg:phone":"+44 20 7428 9500",
    "sg:postcode":"NW5 1RS",
    "sg:province":"Greater London",
    "wof:name":"Woolf Jonathan",
    "wof:placetype":"venue"
},
  "geometry": {"coordinates":[-0.1422580034,51.5531044006],"type":"Point"}
}