{
  "type": "Feature",
  "properties": {
    "iso:country":"GB",
    "sg:address":"Wood Green",
    "sg:city":"Norwich",
    "sg:classifiers":[
        {
            "category":"Farming",
            "subcategory":"Farm",
            "type":"Manufacturing & Wholesale Goods"
        }
    ],
    "sg:phone":"+44 1508 530352",
    "sg:postcode":"NR15 2RR",
    "sg:province":"Norfolk",
    "sg:tags":[
        "mixed",
        "crop"
    ],
    "wof:name":"J F Wilson & Son",
    "wof:placetype":"venue"
},
  "geometry": {"coordinates":[1.254,52.474236],"type":"Point"}
}