{
  "type": "Feature",
  "properties": {
    "addr:full":"Wellingfen Business Park, Main Road, Newport Brough East Riding of Yorkshire HU15 2RH",
    "addr:postcode":"hu15 2rh",
    "addr:street":"Main Road",
    "iso:country":"GB",
    "sg:address":"Wellingfen Business Park, Main Road, Newport",
    "sg:city":"Brough",
    "sg:classifiers":[
        {
            "category":"Train Station",
            "subcategory":"Rail",
            "type":"Transportation"
        }
    ],
    "sg:phone":"+44 1430 449479",
    "sg:postcode":"HU15 2RH",
    "sg:province":"East Riding of Yorkshire",
    "sg:tags":[
        "caravan"
    ],
    "wof:name":"Classique Holiday Homes Ltd.",
    "wof:placetype":"venue"
},
  "geometry": {"coordinates":[-0.695354,53.764118],"type":"Point"}
}