{
  "type": "Feature",
  "properties": {
    "addr:full":"15-17 Church St Twickenham Greater London TW1 3NJ",
    "addr:housenumber":"15-17",
    "addr:postcode":"tw1 3nj",
    "addr:street":"Church St",
    "iso:country":"GB",
    "sg:address":"15-17 Church St",
    "sg:city":"Twickenham",
    "sg:classifiers":[
        {
            "category":"Professional",
            "subcategory":"Engineering",
            "type":"Services"
        }
    ],
    "sg:postcode":"TW1 3NJ",
    "sg:province":"Greater London",
    "sg:tags":[
        "consulting",
        "engineer"
    ],
    "wof:name":"Dames & Moore",
    "wof:placetype":"venue"
},
  "geometry": {"coordinates":[-0.3268119991,51.4469985962],"type":"Point"}
}