{
  "type": "Feature",
  "properties": {
    "addr:full":"77 Sussex Avenue Isleworth Greater London TW7 6LD",
    "addr:housenumber":"77",
    "addr:postcode":"tw7 6ld",
    "addr:street":"Sussex Avenue",
    "iso:country":"GB",
    "sg:address":"77 Sussex Avenue",
    "sg:city":"Isleworth",
    "sg:classifiers":[
        {
            "category":"Real Estate",
            "subcategory":"Architect",
            "type":"Services"
        }
    ],
    "sg:postcode":"TW7 6LD",
    "sg:province":"Greater London",
    "wof:name":"Hadworth Engineering Ltd",
    "wof:placetype":"venue"
},
  "geometry": {"coordinates":[-0.342706,51.467976],"type":"Point"}
}