{
  "type": "Feature",
  "properties": {
    "iso:country":"GB",
    "sg:address":"77 Sussex Avenue",
    "sg:city":"Isleworth",
    "sg:classifiers":[
        {
            "category":"Real Estate",
            "subcategory":"Architect",
            "type":"Services"
        }
    ],
    "sg:postcode":"TW7 6LD",
    "sg:province":"Greater London",
    "wof:name":"Hadworth Engineering Ltd",
    "wof:placetype":"venue"
},
  "geometry": {"coordinates":[-0.342706,51.467976],"type":"Point"}
}