{
  "type": "Feature",
  "properties": {
    "iso:country":"GB",
    "sg:address":"150 Barrowford Road",
    "sg:city":"Colne",
    "sg:classifiers":[
        {
            "category":"Building & Trades",
            "subcategory":"Plumbing",
            "type":"Services"
        }
    ],
    "sg:phone":"+44 1282 862435",
    "sg:postcode":"BB8 9QR",
    "sg:province":"Lancashire",
    "sg:tags":[
        "plumber",
        "heating"
    ],
    "wof:name":"Leonard Green & Son",
    "wof:placetype":"venue"
},
  "geometry": {"coordinates":[-2.190376,53.856724],"type":"Point"}
}