{
  "type": "Feature",
  "properties": {
    "iso:country":"GB",
    "sg:address":"6 Challenge Way",
    "sg:city":"Colchester",
    "sg:classifiers":[
        {
            "category":"Freight",
            "type":"Transportation"
        }
    ],
    "sg:phone":"+44 1206 798111",
    "sg:postcode":"CO1 2LY",
    "sg:province":"Essex",
    "sg:tags":[
        "forwarders"
    ],
    "wof:name":"Hemisphere Freight Services Ltd.",
    "wof:placetype":"venue"
},
  "geometry": {"coordinates":[0.918702,51.885284],"type":"Point"}
}