{
  "type": "Feature",
  "properties": {
    "iso:country":"GB",
    "sg:address":"7 Wentworth Street",
    "sg:city":"Peterborough",
    "sg:classifiers":[
        {
            "category":"Wholesale",
            "subcategory":"Photographic Equipment",
            "type":"Manufacturing & Wholesale Goods"
        },
        {
            "category":"Shopping",
            "subcategory":"Photographic Equipment",
            "type":"Retail Goods"
        }
    ],
    "sg:phone":"+44 1733 311291",
    "sg:postcode":"PE1 1DH",
    "sg:province":"Cambridgeshire",
    "sg:tags":[
        "supply"
    ],
    "wof:name":"Youngs Cameras",
    "wof:placetype":"venue"
},
  "geometry": {"coordinates":[-0.243125,52.5714],"type":"Point"}
}