{
  "type": "Feature",
  "properties": {
    "addr:full":"14-18 Queens Promenade Blackpool Lancashire FY2 9SQ",
    "addr:housenumber":"14-18",
    "addr:postcode":"fy2 9sq",
    "addr:street":"Queens Promenade",
    "iso:country":"GB",
    "sg:address":"14-18 Queens Promenade",
    "sg:city":"Blackpool",
    "sg:classifiers":[
        {
            "category":"Travel",
            "subcategory":"Hotels & Motels",
            "type":"Entertainment"
        }
    ],
    "sg:phone":"+44 1253 351465",
    "sg:postcode":"FY2 9SQ",
    "sg:province":"Lancashire",
    "wof:name":"Hacketts York House Hotel Ltd.",
    "wof:placetype":"venue"
},
  "geometry": {"coordinates":[-3.054599,53.834991],"type":"Point"}
}