{
  "type": "Feature",
  "properties": {
    "iso:country":"GB",
    "sg:address":"14 Albany Road, Granby Industrial Estate",
    "sg:city":"Weymouth",
    "sg:classifiers":[
        {
            "category":"Professional",
            "subcategory":"Engineering",
            "type":"Services"
        }
    ],
    "sg:phone":"+44 1305 770440",
    "sg:postcode":"DT4 9TH",
    "sg:province":"Dorset",
    "sg:tags":[
        "electronic",
        "engineer"
    ],
    "wof:name":"Martech Systems (Weymouth) Ltd.",
    "wof:placetype":"venue"
},
  "geometry": {"coordinates":[-2.489255,50.614471],"type":"Point"}
}