{
  "type": "Feature",
  "properties": {
    "addr:full":"53 Gun Street London Greater London E1 6AH",
    "addr:housenumber":"53",
    "addr:postcode":"e1 6ah",
    "addr:street":"Gun Street",
    "iso:country":"GB",
    "sg:address":"53 Gun Street",
    "sg:city":"London",
    "sg:classifiers":[
        {
            "category":"Professional",
            "subcategory":"Computer Services",
            "type":"Services"
        }
    ],
    "sg:postcode":"E1 6AH",
    "sg:province":"Greater London",
    "sg:tags":[
        "aided",
        "design"
    ],
    "wof:name":"I T Cad Designs Associates",
    "wof:placetype":"venue"
},
  "geometry": {"coordinates":[-0.077039,51.51902],"type":"Point"}
}