{
  "type": "Feature",
  "properties": {
    "iso:country":"GB",
    "sg:address":"3 Longlands Rd, East Wittering",
    "sg:city":"Chichester",
    "sg:classifiers":[
        {
            "category":"Professional",
            "subcategory":"Business Services",
            "type":"Services"
        }
    ],
    "sg:phone":"+44 1243 671999",
    "sg:postcode":"PO20 8DE",
    "sg:province":"West Sussex",
    "sg:tags":[
        "fashion",
        "agent"
    ],
    "wof:name":"COUNT DESIGN",
    "wof:placetype":"venue"
},
  "geometry": {"coordinates":[-0.8747249842,50.7665023804],"type":"Point"}
}