{
  "type": "Feature",
  "properties": {
    "iso:country":"GB",
    "sg:address":"4 Masons Parade, Newgatestreet Road, Goffs Oak",
    "sg:city":"Waltham Cross",
    "sg:classifiers":[
        {
            "category":"Food & Beverages",
            "subcategory":"Meat & Fish",
            "type":"Retail Goods"
        }
    ],
    "sg:phone":"+44 1707 872906",
    "sg:postcode":"EN7 5RJ",
    "sg:province":"Greater London",
    "sg:tags":[
        "chip"
    ],
    "wof:name":"Popeye's Fish Bar",
    "wof:placetype":"venue"
},
  "geometry": {"coordinates":[-0.0885189995,51.7114105225],"type":"Point"}
}