{
  "type": "Feature",
  "properties": {
    "addr:full":"Filmer Road London Greater London SW6 6AS",
    "addr:postcode":"sw6 6as",
    "addr:street":"Filmer Road",
    "iso:country":"GB",
    "sg:address":"Filmer Road",
    "sg:city":"London",
    "sg:classifiers":[
        {
            "category":"Education",
            "subcategory":"University",
            "type":"Public Place"
        },
        {
            "category":"Government",
            "subcategory":"Office",
            "type":"Public Place"
        }
    ],
    "sg:phone":"+44 20 7736 0864",
    "sg:postcode":"SW6 6AS",
    "sg:province":"Greater London",
    "sg:tags":[
        "local",
        "adult"
    ],
    "wof:name":"Community Learning & Leisure Centre",
    "wof:placetype":"venue"
},
  "geometry": {"coordinates":[-0.208851,51.476997],"type":"Point"}
}