{
  "type": "Feature",
  "properties": {
    "iso:country":"GB",
    "sg:address":"41 Crawford Street",
    "sg:city":"London",
    "sg:classifiers":[
        {
            "category":"Travel",
            "subcategory":"Travel Agent",
            "type":"Entertainment"
        }
    ],
    "sg:phone":"+44 20 7258 0304",
    "sg:postcode":"W1H 1HA",
    "sg:province":"Greater London",
    "wof:name":"Multitours",
    "wof:placetype":"venue"
},
  "geometry": {"coordinates":[-0.162272,51.519428],"type":"Point"}
}