{
  "type": "Feature",
  "properties": {
    "iso:country":"GB",
    "sg:address":"Rent Office, Refuge Ho, 50 North St",
    "sg:city":"Brighton",
    "sg:classifiers":[
        {
            "category":"Government",
            "subcategory":"Office",
            "type":"Public Place"
        }
    ],
    "sg:phone":"+44 1273 329061",
    "sg:postcode":"BN1 1RH",
    "sg:province":"East Sussex",
    "sg:tags":[
        "local"
    ],
    "wof:name":"East Sussex County Council",
    "wof:placetype":"venue"
},
  "geometry": {"coordinates":[-0.14243,50.823101],"type":"Point"}
}