{
  "type": "Feature",
  "properties": {
    "addr:full":"2 Swan Gro, Exning Newmarket Cambridgeshire CB8 7HX",
    "addr:housenumber":"2",
    "addr:postcode":"cb8 7hx",
    "addr:street":"Swan Gro",
    "iso:country":"GB",
    "sg:address":"2 Swan Gro, Exning",
    "sg:city":"Newmarket",
    "sg:classifiers":[
        {
            "category":"Professional",
            "subcategory":"Accounting & Tax Preparation",
            "type":"Services"
        },
        {
            "category":"Sports & Exercise",
            "subcategory":"Race Track",
            "type":"Entertainment"
        }
    ],
    "sg:phone":"+44 1638 577416",
    "sg:postcode":"CB8 7HX",
    "sg:province":"Cambridgeshire",
    "sg:tags":[
        "motor"
    ],
    "wof:name":"Zealia Engineering",
    "wof:placetype":"venue"
},
  "geometry": {"coordinates":[0.3726179898,52.2659492493],"type":"Point"}
}