{
  "type": "Feature",
  "properties": {
    "addr:full":"46 St. Marks Av Gravesend Kent DA11 9LW",
    "addr:housenumber":"46",
    "addr:postcode":"da11 9lw",
    "addr:street":"St. Marks Av",
    "iso:country":"GB",
    "sg:address":"46 St. Marks Av",
    "sg:city":"Gravesend",
    "sg:classifiers":[
        {
            "category":"Retail",
            "subcategory":"Driving School",
            "type":"Services"
        }
    ],
    "sg:phone":"+44 1474 567503",
    "sg:postcode":"DA11 9LW",
    "sg:province":"Kent",
    "wof:name":"Elite School Of Motoring",
    "wof:placetype":"venue"
},
  "geometry": {"coordinates":[0.35255301,51.441078186],"type":"Point"}
}