{
  "type": "Feature",
  "properties": {
    "addr:full":"Avonex Business Park, Quedgeley Enterprice Centre Stonehouse Gloucestershire GL2 4SN",
    "addr:postcode":"gl2 4sn",
    "addr:street":"Business Park",
    "iso:country":"GB",
    "sg:address":"Avonex Business Park, Quedgeley Enterprice Centre",
    "sg:city":"Stonehouse",
    "sg:classifiers":[
        {
            "category":"Professional",
            "subcategory":"Computer Services",
            "type":"Services"
        }
    ],
    "sg:phone":"+44 1452 724488",
    "sg:postcode":"GL2 4SN",
    "sg:province":"Gloucestershire",
    "sg:tags":[
        "system",
        "software"
    ],
    "wof:name":"Computec Systems Ltd.",
    "wof:placetype":"venue"
},
  "geometry": {"coordinates":[-2.279169,51.818604],"type":"Point"}
}