{
  "type": "Feature",
  "properties": {
    "iso:country":"GB",
    "sg:address":"1 Kings Road",
    "sg:city":"Llandovery",
    "sg:classifiers":[
        {
            "category":"Real Estate",
            "subcategory":"Real Estate Operator",
            "type":"Services"
        }
    ],
    "sg:phone":"+44 1550 720270",
    "sg:postcode":"SA20 0AW",
    "sg:province":"Carmarthenshire",
    "sg:tags":[
        "letting",
        "agent"
    ],
    "wof:name":"Town & Country Property Services",
    "wof:placetype":"venue"
},
  "geometry": {"coordinates":[-3.795885,51.993824],"type":"Point"}
}