{
  "type": "Feature",
  "properties": {
    "addr:full":"63a Spitalfields Norwich Norfolk NR1 4EY",
    "addr:housenumber":"63a",
    "addr:postcode":"nr1 4ey",
    "addr:street":"Spitalfields Norwich Norfolk",
    "iso:country":"GB",
    "sg:address":"63a Spitalfields",
    "sg:city":"Norwich",
    "sg:classifiers":[
        {
            "category":"Retail",
            "subcategory":"Repair Shop",
            "type":"Services"
        }
    ],
    "sg:phone":"+44 1603 621785",
    "sg:postcode":"NR1 4EY",
    "sg:province":"Norfolk",
    "sg:tags":[
        "upholsterer"
    ],
    "wof:name":"Bourne & James Upholsterers",
    "wof:placetype":"venue"
},
  "geometry": {"coordinates":[1.3120260239,52.6342849731],"type":"Point"}
}