{
  "type": "Feature",
  "properties": {
    "iso:country":"GB",
    "sg:address":"Baystone, Colliers Clo, Wembury",
    "sg:city":"Plymouth",
    "sg:classifiers":[
        {
            "category":"Banks & Credit Unions",
            "subcategory":"Bank",
            "type":"Services"
        }
    ],
    "sg:postcode":"PL9 0JN",
    "sg:province":"Devon",
    "sg:tags":[
        "broker",
        "mortgage"
    ],
    "wof:name":"Heslop,Bruce,",
    "wof:placetype":"venue"
},
  "geometry": {"coordinates":[-4.070407,50.324333],"type":"Point"}
}