{
  "type": "Feature",
  "properties": {
    "iso:country":"GB",
    "sg:address":"50 Kingsland High Street",
    "sg:city":"London",
    "sg:classifiers":[
        {
            "category":"Shopping",
            "subcategory":"Clothing, Apparel, & Fashions",
            "type":"Retail Goods"
        }
    ],
    "sg:phone":"+44 20 7254 9469",
    "sg:postcode":"E8 2JP",
    "sg:province":"Greater London",
    "sg:tags":[
        "menswear"
    ],
    "wof:name":"Manhattan Menswear Ltd.",
    "wof:placetype":"venue"
},
  "geometry": {"coordinates":[-0.075357,51.547501],"type":"Point"}
}