{
  "type": "Feature",
  "properties": {
    "addr:full":"Roseville Street Dartmouth Devon TQ6 9QH",
    "addr:postcode":"tq6 9qh",
    "addr:street":"Roseville Street",
    "iso:country":"GB",
    "sg:address":"Roseville Street",
    "sg:city":"Dartmouth",
    "sg:classifiers":[
        {
            "category":"Retail",
            "subcategory":"Veterinary Services",
            "type":"Services"
        }
    ],
    "sg:postcode":"TQ6 9QH",
    "sg:province":"Devon",
    "sg:tags":[
        "surgeon"
    ],
    "wof:name":"The Dart Vale Vetinary Group",
    "wof:placetype":"venue"
},
  "geometry": {"coordinates":[-3.581972,50.351593],"type":"Point"}
}