{
  "type": "Feature",
  "properties": {
    "addr:full":"The Olympia Shopping Centre, East Kilbride Glasgow South Lanarkshire G74 1PG",
    "addr:postcode":"g74 1pg",
    "iso:country":"GB",
    "sg:address":"The Olympia Shopping Centre, East Kilbride",
    "sg:city":"Glasgow",
    "sg:classifiers":[
        {
            "category":"Commercial Area",
            "type":"Public Place"
        }
    ],
    "sg:phone":"+44 1355 264348",
    "sg:postcode":"G74 1PG",
    "sg:province":"South Lanarkshire",
    "sg:tags":[
        "shop",
        "centre"
    ],
    "wof:name":"Land Securities",
    "wof:placetype":"venue"
},
  "geometry": {"coordinates":[-4.185876,55.767391],"type":"Point"}
}