{
  "type": "Feature",
  "properties": {
    "iso:country":"GB",
    "sg:address":"44 Lochside Rd",
    "sg:city":"Dumfries",
    "sg:classifiers":[
        {
            "category":"Retail",
            "subcategory":"Driving School",
            "type":"Services"
        }
    ],
    "sg:phone":"+44 1387 257474",
    "sg:postcode":"DG2 0LW",
    "sg:province":"Dumfries and Galloway",
    "wof:name":"Cherry School Of Motoring",
    "wof:placetype":"venue"
},
  "geometry": {"coordinates":[-3.6308629513,55.0803794861],"type":"Point"}
}