{
  "type": "Feature",
  "properties": {
    "iso:country":"GB",
    "sg:address":"8 Village Farm Road, Village Farm Industrial Estate, Pyle",
    "sg:city":"Bridgend",
    "sg:classifiers":[
        {
            "category":"Real Estate",
            "subcategory":"Real Estate Services",
            "type":"Services"
        },
        {
            "category":"Building & Trades",
            "subcategory":"Equipment Rental",
            "type":"Services"
        }
    ],
    "sg:phone":"+44 1656 746999",
    "sg:postcode":"CF33 6BL",
    "sg:province":"Bridgend",
    "sg:tags":[
        "hire",
        "leasing",
        "plant",
        "machinery"
    ],
    "wof:name":"P S C Plant Ltd.",
    "wof:placetype":"venue"
},
  "geometry": {"coordinates":[-3.6747839451,51.5245094299],"type":"Point"}
}