{
  "type": "Feature",
  "properties": {
    "iso:country":"GB",
    "sg:address":"80 The Pentagon",
    "sg:city":"Chatham",
    "sg:classifiers":[
        {
            "category":"Food & Beverages",
            "subcategory":"Bakery",
            "type":"Retail Goods"
        }
    ],
    "sg:phone":"+44 1634 406677",
    "sg:postcode":"ME4 4HP",
    "sg:province":"Kent",
    "sg:tags":[
        "baker"
    ],
    "wof:name":"The Bakers Oven",
    "wof:placetype":"venue"
},
  "geometry": {"coordinates":[0.5224400163,51.3818893433],"type":"Point"}
}