{
  "type": "Feature",
  "properties": {
    "iso:country":"GB",
    "sg:address":"Kirkby Rd",
    "sg:city":"Sutton In Ashfield",
    "sg:classifiers":[
        {
            "category":"Shopping",
            "subcategory":"Clothing, Apparel, & Fashions",
            "type":"Retail Goods"
        }
    ],
    "sg:phone":"+44 1623 441122",
    "sg:postcode":"NG17 1HA",
    "sg:province":"Nottinghamshire",
    "sg:tags":[
        "clothing",
        "fabric"
    ],
    "wof:name":"Albert Martins",
    "wof:placetype":"venue"
},
  "geometry": {"coordinates":[-1.2653820515,53.1223754883],"type":"Point"}
}