{
  "type": "Feature",
  "properties": {
    "addr:full":"170-172 Montrose Street Brechin Aberdeenshire DD9 7DZ",
    "addr:housenumber":"170-172",
    "addr:postcode":"dd9 7dz",
    "addr:street":"Montrose Street",
    "iso:country":"GB",
    "sg:address":"170-172 Montrose Street",
    "sg:city":"Brechin",
    "sg:classifiers":[
        {
            "category":"Shopping",
            "subcategory":"Used Merchandise",
            "type":"Retail Goods"
        }
    ],
    "sg:postcode":"DD9 7DZ",
    "sg:province":"Aberdeenshire",
    "sg:tags":[
        "shop",
        "second-hand"
    ],
    "wof:name":"N & W Thomson",
    "wof:placetype":"venue"
},
  "geometry": {"coordinates":[-2.645659,56.727348],"type":"Point"}
}