{
  "type": "Feature",
  "properties": {
    "iso:country":"GB",
    "sg:address":"11 Fore St",
    "sg:city":"St. Austell",
    "sg:classifiers":[
        {
            "category":"Building & Trades",
            "subcategory":"Construction",
            "type":"Services"
        }
    ],
    "sg:phone":"+44 1726 64876",
    "sg:postcode":"PL25 5PX",
    "sg:province":"Cornwall",
    "sg:tags":[
        "concrete"
    ],
    "wof:name":"Mun-decay",
    "wof:placetype":"venue"
},
  "geometry": {"coordinates":[-4.793154,50.338249],"type":"Point"}
}