{
  "type": "Feature",
  "properties": {
    "addr:full":"106 Collier Row Road Romford Essex RM5 2BA",
    "addr:housenumber":"106",
    "addr:postcode":"rm5 2ba",
    "addr:street":"Collier Row Road",
    "iso:country":"GB",
    "sg:address":"106 Collier Row Road",
    "sg:city":"Romford",
    "sg:classifiers":[
        {
            "category":"Shopping",
            "subcategory":"News",
            "type":"Retail Goods"
        }
    ],
    "sg:phone":"+44 1708 742929",
    "sg:postcode":"RM5 2BA",
    "sg:province":"Essex",
    "sg:tags":[
        "newsagent"
    ],
    "wof:name":"Roller Row Newsagents",
    "wof:placetype":"venue"
},
  "geometry": {"coordinates":[0.166581,51.590988],"type":"Point"}
}