{
  "type": "Feature",
  "properties": {
    "addr:full":"252a London Road Waterlooville Hampshire PO7 7HG",
    "addr:housenumber":"252a",
    "addr:postcode":"po7 7hg",
    "addr:street":"London Road",
    "iso:country":"GB",
    "sg:address":"252a London Road",
    "sg:city":"Waterlooville",
    "sg:classifiers":[
        {
            "category":"Professional",
            "subcategory":"Employment Agencies",
            "type":"Services"
        }
    ],
    "sg:phone":"+44 23 9225 4111",
    "sg:postcode":"PO7 7HG",
    "sg:province":"Hampshire",
    "sg:tags":[
        "consultant"
    ],
    "wof:name":"Drivemaster Personnel Ltd.",
    "wof:placetype":"venue"
},
  "geometry": {"coordinates":[-1.033037,50.878426],"type":"Point"}
}