{
  "type": "Feature",
  "properties": {
    "addr:full":"119a Pitshanger Lane London Greater London W5 1RH",
    "addr:housenumber":"119a",
    "addr:postcode":"w5 1rh",
    "addr:street":"Pitshanger Lane",
    "iso:country":"GB",
    "sg:address":"119a Pitshanger Lane",
    "sg:city":"London",
    "sg:classifiers":[
        {
            "category":"Shopping",
            "subcategory":"Shoes",
            "type":"Retail Goods"
        }
    ],
    "sg:phone":"+44 20 8997 2779",
    "sg:postcode":"W5 1RH",
    "sg:province":"Greater London",
    "wof:name":"Kamps",
    "wof:placetype":"venue"
},
  "geometry": {"coordinates":[-0.314917,51.525696],"type":"Point"}
}