{
  "type": "Feature",
  "properties": {
    "addr:full":"14 Herriotts Lane Wellingborough Northamptonshire NN8 4PU",
    "addr:housenumber":"14",
    "addr:postcode":"nn8 4pu",
    "addr:street":"Herriotts Lane",
    "iso:country":"GB",
    "sg:address":"14 Herriotts Lane",
    "sg:city":"Wellingborough",
    "sg:classifiers":[
        {
            "category":"Food & Beverages",
            "subcategory":"Meat & Fish",
            "type":"Retail Goods"
        }
    ],
    "sg:phone":"+44 1933 272878",
    "sg:postcode":"NN8 4PU",
    "sg:province":"Northamptonshire",
    "sg:tags":[
        "chip"
    ],
    "wof:name":"Good Catch Fish & Chips",
    "wof:placetype":"venue"
},
  "geometry": {"coordinates":[-0.6941589713,52.3040313721],"type":"Point"}
}