{
  "type": "Feature",
  "properties": {
    "iso:country":"GB",
    "sg:address":"3 Westfield Drive",
    "sg:city":"Ossett",
    "sg:classifiers":[
        {
            "category":"Building & Trades",
            "subcategory":"Landscaping Services",
            "type":"Services"
        }
    ],
    "sg:phone":"+44 1924 271379",
    "sg:postcode":"WF5 8HJ",
    "sg:province":"West Yorkshire",
    "sg:tags":[
        "gardening"
    ],
    "wof:name":"Handy Gardener",
    "wof:placetype":"venue"
},
  "geometry": {"coordinates":[-1.588544,53.680367],"type":"Point"}
}