{
  "type": "Feature",
  "properties": {
    "addr:full":"8 Ferry Brae Dunoon Argyll and Bute PA23 7DJ",
    "addr:housenumber":"8",
    "addr:postcode":"pa23 7dj",
    "addr:street":"Ferry Brae Dunoon",
    "iso:country":"GB",
    "sg:address":"8 Ferry Brae",
    "sg:city":"Dunoon",
    "sg:classifiers":[
        {
            "category":"Personal",
            "subcategory":"Barber",
            "type":"Services"
        }
    ],
    "sg:postcode":"PA23 7DJ",
    "sg:province":"Argyll and Bute",
    "sg:tags":[
        "men's",
        "hairdresser"
    ],
    "wof:name":"Charlie's Barber Shop",
    "wof:placetype":"venue"
},
  "geometry": {"coordinates":[-4.925645,55.948494],"type":"Point"}
}