{
  "type": "Feature",
  "properties": {
    "addr:full":"Lake District Business, Park Kendal Cumbria LA9 6NH",
    "addr:postcode":"la9 6nh",
    "addr:street":"Business Park Kendal",
    "iso:country":"GB",
    "sg:address":"Lake District Business, Park",
    "sg:city":"Kendal",
    "sg:classifiers":[
        {
            "category":"Education",
            "subcategory":"Special Training",
            "type":"Public Place"
        }
    ],
    "sg:postcode":"LA9 6NH",
    "sg:province":"Cumbria",
    "sg:tags":[
        "product",
        "centre"
    ],
    "wof:name":"The National Access & Rescue Centre (Uk) Ltd.",
    "wof:placetype":"venue"
},
  "geometry": {"coordinates":[-2.748084,54.324001],"type":"Point"}
}