{
  "type": "Feature",
  "properties": {
    "addr:full":"67 High Street Corsham Wiltshire SN13 0EZ",
    "addr:housenumber":"67",
    "addr:postcode":"sn13 0ez",
    "addr:street":"High Street",
    "iso:country":"GB",
    "sg:address":"67 High Street",
    "sg:city":"Corsham",
    "sg:classifiers":[
        {
            "category":"Fast Food",
            "type":"Food & Drink"
        }
    ],
    "sg:phone":"+44 1249 701881",
    "sg:postcode":"SN13 0EZ",
    "sg:province":"Wiltshire",
    "sg:tags":[
        "away",
        "meal",
        "outlet",
        "take"
    ],
    "wof:name":"Delicious House Chinese Takeaway",
    "wof:placetype":"venue"
},
  "geometry": {"coordinates":[-2.184595,51.434143],"type":"Point"}
}