{
  "type": "Feature",
  "properties": {
    "addr:full":"Unit 19 Chadkirk Industrial Estate Stockport Cheshire SK6 3LE",
    "addr:housenumber":"unit 19",
    "addr:postcode":"sk6 3le",
    "addr:street":"Chadkirk Industrial Estate",
    "iso:country":"GB",
    "sg:address":"Unit 19 Chadkirk Industrial Estate",
    "sg:city":"Stockport",
    "sg:classifiers":[
        {
            "category":"Retail",
            "subcategory":"Auto Repair",
            "type":"Services"
        }
    ],
    "sg:postcode":"SK6 3LE",
    "sg:province":"Cheshire",
    "sg:tags":[
        "modification",
        "garage"
    ],
    "wof:name":"Chadkirk Motor Centre",
    "wof:placetype":"venue"
},
  "geometry": {"coordinates":[-2.0953490734,53.4034843445],"type":"Point"}
}