{
  "type": "Feature",
  "properties": {
    "addr:full":"Augustus Street London Greater London NW1 3TJ",
    "addr:postcode":"nw1 3tj",
    "addr:street":"Augustus Street",
    "iso:country":"GB",
    "sg:address":"Augustus Street",
    "sg:city":"London",
    "sg:classifiers":[
        {
            "category":"Farming",
            "subcategory":"Nursery",
            "type":"Manufacturing & Wholesale Goods"
        }
    ],
    "sg:phone":"+44 20 7387 2382",
    "sg:postcode":"NW1 3TJ",
    "sg:province":"Greater London",
    "sg:tags":[
        "creche"
    ],
    "wof:name":"Regents Park Childrens Centre",
    "wof:placetype":"venue"
},
  "geometry": {"coordinates":[-0.142039001,51.5314903259],"type":"Point"}
}