{
  "type": "Feature",
  "properties": {
    "iso:country":"GB",
    "sg:address":"55 Price Street",
    "sg:city":"Birmingham",
    "sg:classifiers":[
        {
            "category":"Shopping",
            "subcategory":"Hobbies, Toys, & Games",
            "type":"Retail Goods"
        }
    ],
    "sg:phone":"+44 121 359 6806",
    "sg:postcode":"B4 6JZ",
    "sg:province":"West Midlands",
    "sg:tags":[
        "gunsmith"
    ],
    "wof:name":"G M Cruxton",
    "wof:placetype":"venue"
},
  "geometry": {"coordinates":[-1.8949650526,52.4865684509],"type":"Point"}
}