{
  "type": "Feature",
  "properties": {
    "addr:full":"Chantry Bridge Wakefield West Yorkshire WF1 5PQ",
    "addr:postcode":"wf1 5pq",
    "addr:street":"Chantry Bridge",
    "iso:country":"GB",
    "sg:address":"Chantry Bridge",
    "sg:city":"Wakefield",
    "sg:classifiers":[
        {
            "category":"Home & Garden",
            "subcategory":"Hardware",
            "type":"Retail Goods"
        }
    ],
    "sg:phone":"+44 1924 369660",
    "sg:postcode":"WF1 5PQ",
    "sg:province":"West Yorkshire",
    "sg:tags":[
        "retailer",
        "diy"
    ],
    "wof:name":"No Frills Diy",
    "wof:placetype":"venue"
},
  "geometry": {"coordinates":[-1.487942,53.675148],"type":"Point"}
}