{
  "type": "Feature",
  "properties": {
    "addr:full":"443 North Woolwich Road London Greater London E16 2DA",
    "addr:housenumber":"443",
    "addr:postcode":"e16 2da",
    "addr:street":"North Woolwich Road",
    "iso:country":"GB",
    "sg:address":"443 North Woolwich Road",
    "sg:city":"London",
    "sg:classifiers":[
        {
            "category":"Professional",
            "type":"Services"
        },
        {
            "category":"Arts & Performance",
            "subcategory":"Theater",
            "type":"Entertainment"
        }
    ],
    "sg:phone":"+44 20 7511 6655",
    "sg:postcode":"E16 2DA",
    "sg:province":"Greater London",
    "sg:tags":[
        "designer",
        "concert",
        "theatre",
        "furnishers",
        "interior",
        "hall"
    ],
    "wof:name":"Brick Lane Music Hall Ltd.",
    "wof:placetype":"venue"
},
  "geometry": {"coordinates":[0.0425099991,51.5027503967],"type":"Point"}
}