{
  "type": "Feature",
  "properties": {
    "iso:country":"GB",
    "sg:address":"130 Nottingham Rd",
    "sg:city":"Nottingham",
    "sg:classifiers":[
        {
            "category":"Health Services",
            "subcategory":"Dentist",
            "type":"Services"
        }
    ],
    "sg:phone":"+44 1773 713771",
    "sg:postcode":"NG16 3GD",
    "sg:province":"Derbyshire",
    "wof:name":"F X D'Sa",
    "wof:placetype":"venue"
},
  "geometry": {"coordinates":[-1.302241,53.017147],"type":"Point"}
}