{
  "type": "Feature",
  "properties": {
    "addr:full":"86 Westow Hill, Crystal Palace London Greater London SE19 1SB",
    "addr:housenumber":"86",
    "addr:postcode":"se19 1sb",
    "addr:street":"Westow Hill",
    "iso:country":"GB",
    "sg:address":"86 Westow Hill, Crystal Palace",
    "sg:city":"London",
    "sg:classifiers":[
        {
            "category":"Fast Food",
            "type":"Food & Drink"
        }
    ],
    "sg:phone":"+44 20 8766 7887",
    "sg:postcode":"SE19 1SB",
    "sg:province":"Greater London",
    "sg:tags":[
        "away",
        "take"
    ],
    "wof:name":"Palace Kebab",
    "wof:placetype":"venue"
},
  "geometry": {"coordinates":[-0.078625001,51.4197235107],"type":"Point"}
}