{
  "type": "Feature",
  "properties": {
    "iso:country":"GB",
    "sg:address":"33 Station Rd",
    "sg:city":"Bexhill On Sea",
    "sg:classifiers":[
        {
            "category":"Professional",
            "subcategory":"Employment Agencies",
            "type":"Services"
        }
    ],
    "sg:phone":"+44 1424 224520",
    "sg:postcode":"TN40 1RG",
    "sg:province":"East Sussex",
    "sg:tags":[
        "consultant"
    ],
    "wof:name":"Nine To Five Bexhill Employment Agency",
    "wof:placetype":"venue"
},
  "geometry": {"coordinates":[0.473267,50.840805],"type":"Point"}
}