{
  "type": "Feature",
  "properties": {
    "addr:full":"Lion House, Bethel Square Brecon Powys LD3 7JP",
    "addr:postcode":"ld3 7jp",
    "addr:street":"Bethel Square",
    "iso:country":"GB",
    "sg:address":"Lion House, Bethel Square",
    "sg:city":"Brecon",
    "sg:classifiers":[
        {
            "category":"Professional",
            "subcategory":"Management & Consulting",
            "type":"Services"
        },
        {
            "category":"Banks & Credit Unions",
            "subcategory":"Financial Services",
            "type":"Services"
        },
        {
            "category":"Organizations",
            "subcategory":"Community Association",
            "type":"Services"
        }
    ],
    "sg:phone":"+44 1874 625708",
    "sg:postcode":"LD3 7JP",
    "sg:province":"Powys",
    "sg:tags":[
        "club",
        "consultant",
        "conservation",
        "social"
    ],
    "wof:name":"BRECKNOCK WILDLIFE TRUST LTD",
    "wof:placetype":"venue"
},
  "geometry": {"coordinates":[-3.3911418915,51.9497413635],"type":"Point"}
}