{
  "type": "Feature",
  "properties": {
    "addr:full":"42 Croft Lane Letchworth Hertfordshire SG6 1AP",
    "addr:housenumber":"42",
    "addr:postcode":"sg6 1ap",
    "addr:street":"Croft Lane",
    "iso:country":"GB",
    "sg:address":"42 Croft Lane",
    "sg:city":"Letchworth",
    "sg:classifiers":[
        {
            "category":"Building & Trades",
            "subcategory":"Construction",
            "type":"Services"
        }
    ],
    "sg:phone":"+44 1462 484022",
    "sg:postcode":"SG6 1AP",
    "sg:province":"Hertfordshire",
    "sg:tags":[
        "flooring"
    ],
    "wof:name":"Allen Mezzanines",
    "wof:placetype":"venue"
},
  "geometry": {"coordinates":[-0.2132149935,51.992313385],"type":"Point"}
}