{
  "type": "Feature",
  "properties": {
    "iso:country":"GB",
    "sg:address":"118 Wandsworth High Street",
    "sg:city":"London",
    "sg:classifiers":[
        {
            "category":"Fast Food",
            "type":"Food & Drink"
        }
    ],
    "sg:postcode":"SW18 4JP",
    "sg:province":"Greater London",
    "sg:tags":[
        "away",
        "take"
    ],
    "wof:name":"Hippo Pizza Ltd.",
    "wof:placetype":"venue"
},
  "geometry": {"coordinates":[-0.196706,51.457363],"type":"Point"}
}