{
  "type": "Feature",
  "properties": {
    "iso:country":"GB",
    "sg:address":"222 High Road",
    "sg:city":"Loughton",
    "sg:classifiers":[
        {
            "category":"Home & Garden",
            "subcategory":"Home Furnishings",
            "type":"Retail Goods"
        }
    ],
    "sg:phone":"+44 20 8502 5811",
    "sg:postcode":"IG10 1ET",
    "sg:province":"Essex",
    "sg:tags":[
        "blind",
        "curtain",
        "fitting"
    ],
    "wof:name":"Dolly's Curtain Design",
    "wof:placetype":"venue"
},
  "geometry": {"coordinates":[0.055682,51.64801],"type":"Point"}
}