{
  "type": "Feature",
  "properties": {
    "iso:country":"GB",
    "sg:address":"14 Sevenoaks Drive, Spencers Wood",
    "sg:city":"Reading",
    "sg:classifiers":[
        {
            "category":"Organizations",
            "subcategory":"Membership Organization",
            "type":"Services"
        }
    ],
    "sg:phone":"+44 118 988 3852",
    "sg:postcode":"RG7 1AZ",
    "sg:province":"Berkshire",
    "sg:tags":[
        "club"
    ],
    "wof:name":"Claremont Park (Spencers Wood) Residents Association Ltd.",
    "wof:placetype":"venue"
},
  "geometry": {"coordinates":[-0.97335,51.400684],"type":"Point"}
}