{
  "type": "Feature",
  "properties": {
    "addr:full":"Rathmell Road Leeds West Yorkshire LS15 0NZ",
    "addr:postcode":"ls15 0nz",
    "addr:street":"Rathmell Road",
    "iso:country":"GB",
    "sg:address":"Rathmell Road",
    "sg:city":"Leeds",
    "sg:classifiers":[
        {
            "category":"Bars & Pubs",
            "type":"Food & Drink"
        }
    ],
    "sg:phone":"+44 113 264 6256",
    "sg:postcode":"LS15 0NZ",
    "sg:province":"West Yorkshire",
    "sg:tags":[
        "pubs",
        "house",
        "inn",
        "public",
        "activity"
    ],
    "wof:name":"The Halton Moor",
    "wof:placetype":"venue"
},
  "geometry": {"coordinates":[-1.4778939486,53.7944450378],"type":"Point"}
}