{
  "type": "Feature",
  "properties": {
    "iso:country":"GB",
    "sg:address":"226 Mill Rd",
    "sg:city":"Cambridge",
    "sg:classifiers":[
        {
            "category":"Wholesale",
            "subcategory":"Groceries",
            "type":"Manufacturing & Wholesale Goods"
        }
    ],
    "sg:phone":"+44 1223 861467",
    "sg:postcode":"CB1 3NF",
    "sg:province":"Cambridgeshire",
    "sg:tags":[
        "food",
        "supplier",
        "drink"
    ],
    "wof:name":"The Real Samosa Co",
    "wof:placetype":"venue"
},
  "geometry": {"coordinates":[0.14517,52.197411],"type":"Point"}
}