{
  "type": "Feature",
  "properties": {
    "addr:full":"157 High Street, Southgate London Greater London N14 6BP",
    "addr:housenumber":"157",
    "addr:postcode":"london n14 6bp",
    "addr:street":"High Street",
    "iso:country":"GB",
    "sg:address":"157 High Street, Southgate",
    "sg:city":"London",
    "sg:classifiers":[
        {
            "category":"Real Estate",
            "subcategory":"Real Estate Agent",
            "type":"Services"
        }
    ],
    "sg:phone":"+44 20 8882 0111",
    "sg:postcode":"N14 6BP",
    "sg:province":"Greater London",
    "wof:name":"Gilmartin Ley Ltd.",
    "wof:placetype":"venue"
},
  "geometry": {"coordinates":[-0.128036,51.630653],"type":"Point"}
}