{
  "type": "Feature",
  "properties": {
    "addr:full":"New Hockley Hall Farm, Lower Road Hockley Essex SS5 5NW",
    "addr:postcode":"ss5 5nw",
    "addr:street":"Lower Road Hockley",
    "iso:country":"GB",
    "sg:address":"New Hockley Hall Farm, Lower Road",
    "sg:city":"Hockley",
    "sg:classifiers":[
        {
            "category":"Farming",
            "subcategory":"Livestock Farm",
            "type":"Manufacturing & Wholesale Goods"
        }
    ],
    "sg:phone":"+44 1702 202930",
    "sg:postcode":"SS5 5NW",
    "sg:province":"Essex",
    "sg:tags":[
        "others"
    ],
    "wof:name":"A H Gemmill",
    "wof:placetype":"venue"
},
  "geometry": {"coordinates":[0.666821,51.606663],"type":"Point"}
}