{
  "type": "Feature",
  "properties": {
    "iso:country":"GB",
    "sg:address":"59 High St",
    "sg:city":"Shanklin",
    "sg:classifiers":[
        {
            "category":"Restaurant",
            "type":"Food & Drink"
        }
    ],
    "sg:phone":"+44 1983 862814",
    "sg:postcode":"PO37 6JJ",
    "sg:province":"Isle of Wight",
    "sg:tags":[
        "italian"
    ],
    "wof:name":"Sorrento Italian Restaurant",
    "wof:placetype":"venue"
},
  "geometry": {"coordinates":[-1.1798559427,50.6279449463],"type":"Point"}
}