{
  "type": "Feature",
  "properties": {
    "addr:full":"110 Agbrigg Road Wakefield West Yorkshire WF1 5BL",
    "addr:housenumber":"110",
    "addr:postcode":"wf1 5bl",
    "addr:street":"Agbrigg Road",
    "iso:country":"GB",
    "sg:address":"110 Agbrigg Road",
    "sg:city":"Wakefield",
    "sg:classifiers":[
        {
            "category":"Shopping",
            "type":"Retail Goods"
        }
    ],
    "sg:phone":"+44 1924 259050",
    "sg:postcode":"WF1 5BL",
    "sg:province":"West Yorkshire",
    "sg:tags":[
        "part",
        "accessory"
    ],
    "wof:name":"Maurice's Car & Home Supplies",
    "wof:placetype":"venue"
},
  "geometry": {"coordinates":[-1.477859,53.667194],"type":"Point"}
}