{
  "type": "Feature",
  "properties": {
    "addr:full":"14 Cherberry Close, Ancells Farm Fleet Hampshire GU51 2TD",
    "addr:housenumber":"14;fleet",
    "addr:postcode":"gu51 2td",
    "addr:street":"Cherberry Close;Hampshire",
    "iso:country":"GB",
    "sg:address":"14 Cherberry Close, Ancells Farm",
    "sg:city":"Fleet",
    "sg:classifiers":[
        {
            "category":"Building & Trades",
            "subcategory":"Plumbing",
            "type":"Services"
        }
    ],
    "sg:phone":"+44 1252 623054",
    "sg:postcode":"GU51 2TD",
    "sg:province":"Hampshire",
    "sg:tags":[
        "central",
        "heating"
    ],
    "wof:name":"Waterford Heating",
    "wof:placetype":"venue"
},
  "geometry": {"coordinates":[-0.826565,51.29446],"type":"Point"}
}