{
  "type": "Feature",
  "properties": {
    "addr:full":"214d Lwr Blandford Rd Broadstone Dorset BH18 8DX",
    "addr:housenumber":"214d",
    "addr:postcode":"bh18 8dx",
    "addr:street":"Lwr Blandford Rd",
    "iso:country":"GB",
    "sg:address":"214d Lwr Blandford Rd",
    "sg:city":"Broadstone",
    "sg:classifiers":[
        {
            "category":"Shopping",
            "subcategory":"Florist",
            "type":"Retail Goods"
        }
    ],
    "sg:postcode":"BH18 8DX",
    "sg:province":"Dorset",
    "wof:name":"Burden,Caroline,",
    "wof:placetype":"venue"
},
  "geometry": {"coordinates":[-1.9954940081,50.7612686157],"type":"Point"}
}