{
  "type": "Feature",
  "properties": {
    "iso:country":"GB",
    "sg:address":"Rosario House, Berkley Rd, Crosby",
    "sg:city":"Liverpool",
    "sg:classifiers":[
        {
            "category":"Professional",
            "subcategory":"Business Services",
            "type":"Services"
        }
    ],
    "sg:phone":"+44 151 931 3002",
    "sg:postcode":"L23 7UD",
    "sg:province":"Merseyside",
    "sg:tags":[
        "import",
        "export",
        "agent"
    ],
    "wof:name":"ROSARIO EXPORTS",
    "wof:placetype":"venue"
},
  "geometry": {"coordinates":[-3.035964,53.494137],"type":"Point"}
}