{
  "type": "Feature",
  "properties": {
    "addr:full":"121 Palatine Road Manchester Greater Manchester M20 3YA",
    "addr:housenumber":"121",
    "addr:postcode":"m20 3ya",
    "addr:street":"Palatine Road",
    "iso:country":"GB",
    "sg:address":"121 Palatine Road",
    "sg:city":"Manchester",
    "sg:classifiers":[
        {
            "category":"Professional",
            "subcategory":"Art Services",
            "type":"Services"
        },
        {
            "category":"Professional",
            "subcategory":"Computer Services",
            "type":"Services"
        }
    ],
    "sg:phone":"+44 161 448 2424",
    "sg:postcode":"M20 3YA",
    "sg:province":"Greater Manchester",
    "sg:tags":[
        "graphic",
        "system",
        "designer",
        "software"
    ],
    "wof:name":"Clear Presentations Ltd",
    "wof:placetype":"venue"
},
  "geometry": {"coordinates":[-2.227869,53.434608],"type":"Point"}
}