{
  "type": "Feature",
  "properties": {
    "iso:country":"GB",
    "sg:address":"40 Chester Terrace",
    "sg:city":"London",
    "sg:classifiers":[
        {
            "category":"Banks & Credit Unions",
            "subcategory":"Bank",
            "type":"Services"
        },
        {
            "category":"Banks & Credit Unions",
            "subcategory":"Financial Services",
            "type":"Services"
        }
    ],
    "sg:phone":"+44 7785 237768",
    "sg:postcode":"NW1 4ND",
    "sg:province":"Greater London",
    "sg:tags":[
        "consultant",
        "institution"
    ],
    "wof:name":"Kalran Investments Ltd.",
    "wof:placetype":"venue"
},
  "geometry": {"coordinates":[-0.145248,51.530216],"type":"Point"}
}