{
  "type": "Feature",
  "properties": {
    "addr:full":"10 Leap Cross Small Business Cen Hailsham East Sussex BN27 3PD",
    "addr:housenumber":"10",
    "addr:postcode":"bn27 3pd",
    "addr:street":"Leap Cross",
    "iso:country":"GB",
    "sg:address":"10 Leap Cross Small Business Cen",
    "sg:city":"Hailsham",
    "sg:classifiers":[
        {
            "category":"Food & Beverages",
            "subcategory":"Bakery",
            "type":"Retail Goods"
        }
    ],
    "sg:postcode":"BN27 3PD",
    "sg:province":"East Sussex",
    "sg:tags":[
        "baker"
    ],
    "wof:name":"Let Them Eat",
    "wof:placetype":"venue"
},
  "geometry": {"coordinates":[0.2565200031,50.8653831482],"type":"Point"}
}