{
  "type": "Feature",
  "properties": {
    "iso:country":"GB",
    "sg:address":"120 Long Acre",
    "sg:city":"London",
    "sg:classifiers":[
        {
            "category":"Professional",
            "subcategory":"Art Services",
            "type":"Services"
        }
    ],
    "sg:postcode":"WC2E 9PA",
    "sg:province":"Greater London",
    "sg:tags":[
        "photographer"
    ],
    "wof:name":"Format (W1) Ltd",
    "wof:placetype":"venue"
},
  "geometry": {"coordinates":[-0.125236,51.512794],"type":"Point"}
}