{
  "type": "Feature",
  "properties": {
    "addr:full":"1 Mount Street Aberdeen Aberdeen City AB25 2RA",
    "addr:housenumber":"1",
    "addr:postcode":"ab25 2ra",
    "addr:street":"Mount Street",
    "iso:country":"GB",
    "sg:address":"1 Mount Street",
    "sg:city":"Aberdeen",
    "sg:classifiers":[
        {
            "category":"Shopping",
            "subcategory":"Pharmacy",
            "type":"Retail Goods"
        }
    ],
    "sg:phone":"+44 1224 630101",
    "sg:postcode":"AB25 2RA",
    "sg:province":"Aberdeen City",
    "sg:tags":[
        "dispensing",
        "store",
        "pharmacist",
        "chemist",
        "drug"
    ],
    "wof:name":"Michael Wood Pharmacies",
    "wof:placetype":"venue"
},
  "geometry": {"coordinates":[-2.112416,57.150677],"type":"Point"}
}