{
  "type": "Feature",
  "properties": {
    "addr:full":"50-52 Halesowen Road Dudley West Midlands DY2 9QB",
    "addr:housenumber":"50-52",
    "addr:postcode":"dy2 9qb",
    "addr:street":"Halesowen Road",
    "iso:country":"GB",
    "sg:address":"50-52 Halesowen Road",
    "sg:city":"Dudley",
    "sg:classifiers":[
        {
            "category":"Professional",
            "subcategory":"Lawyer & Legal Services",
            "type":"Services"
        }
    ],
    "sg:phone":"+44 1384 236101",
    "sg:postcode":"DY2 9QB",
    "sg:province":"West Midlands",
    "sg:tags":[
        "solicitor"
    ],
    "wof:name":"Silk Solicitors",
    "wof:placetype":"venue"
},
  "geometry": {"coordinates":[-2.0708448887,52.4817352295],"type":"Point"}
}