{
  "type": "Feature",
  "properties": {
    "iso:country":"GB",
    "sg:address":"606 Blackburn Road, Astley Bridge",
    "sg:city":"Bolton",
    "sg:classifiers":[
        {
            "category":"Shopping",
            "subcategory":"Clothing, Apparel, & Fashions",
            "type":"Retail Goods"
        }
    ],
    "sg:phone":"+44 1204 596084",
    "sg:postcode":"BL1 7AL",
    "sg:province":"Lancashire",
    "sg:tags":[
        "dresswear"
    ],
    "wof:name":"Swanks",
    "wof:placetype":"venue"
},
  "geometry": {"coordinates":[-2.4324729443,53.6021118164],"type":"Point"}
}