{
  "type": "Feature",
  "properties": {
    "addr:full":"606 Blackburn Road, Astley Bridge Bolton Lancashire BL1 7AL",
    "addr:housenumber":"606",
    "addr:postcode":"bl1 7al",
    "addr:street":"Blackburn Road",
    "iso:country":"GB",
    "sg:address":"606 Blackburn Road, Astley Bridge",
    "sg:city":"Bolton",
    "sg:classifiers":[
        {
            "category":"Shopping",
            "subcategory":"Clothing, Apparel, & Fashions",
            "type":"Retail Goods"
        }
    ],
    "sg:phone":"+44 1204 596084",
    "sg:postcode":"BL1 7AL",
    "sg:province":"Lancashire",
    "sg:tags":[
        "dresswear"
    ],
    "wof:name":"Swanks",
    "wof:placetype":"venue"
},
  "geometry": {"coordinates":[-2.4324729443,53.6021118164],"type":"Point"}
}