{
  "type": "Feature",
  "properties": {
    "iso:country":"GB",
    "sg:address":"463 Lordship Lane, Wood Green",
    "sg:city":"London",
    "sg:classifiers":[
        {
            "category":"Fast Food",
            "type":"Food & Drink"
        }
    ],
    "sg:phone":"+44 20 8888 9809",
    "sg:postcode":"N22 5DJ",
    "sg:province":"Greater London",
    "sg:tags":[
        "away",
        "take"
    ],
    "wof:name":"Marina Kebab & Burger House",
    "wof:placetype":"venue"
},
  "geometry": {"coordinates":[-0.094723,51.598045],"type":"Point"}
}