{
  "type": "Feature",
  "properties": {
    "iso:country":"GB",
    "sg:address":"65 Craigleith Hill Crescent",
    "sg:city":"Edinburgh",
    "sg:classifiers":[
        {
            "category":"Building & Trades",
            "subcategory":"Construction",
            "type":"Services"
        }
    ],
    "sg:phone":"+44 131 332 7373",
    "sg:postcode":"EH4 2JS",
    "sg:province":"City of Edinburgh",
    "sg:tags":[
        "flooring"
    ],
    "wof:name":"Alba Floor Sanding",
    "wof:placetype":"venue"
},
  "geometry": {"coordinates":[-3.2350900173,55.9602394104],"type":"Point"}
}