{
  "type": "Feature",
  "properties": {
    "addr:full":"7 Guildford Avenue Chorley Lancashire PR6 8TG",
    "addr:housenumber":"7",
    "addr:postcode":"pr6 8tg",
    "addr:street":"Guildford Avenue",
    "iso:country":"GB",
    "sg:address":"7 Guildford Avenue",
    "sg:city":"Chorley",
    "sg:classifiers":[
        {
            "category":"Building & Trades",
            "subcategory":"Construction",
            "type":"Services"
        }
    ],
    "sg:phone":"+44 1257 273315",
    "sg:postcode":"PR6 8TG",
    "sg:province":"Lancashire",
    "sg:tags":[
        "tiling",
        "contractor"
    ],
    "wof:name":"Paul Taberner",
    "wof:placetype":"venue"
},
  "geometry": {"coordinates":[-2.615242,53.672825],"type":"Point"}
}