{
  "type": "Feature",
  "properties": {
    "iso:country":"GB",
    "sg:address":"Unit 1, Patriot Drive, Rooksley Retail Park",
    "sg:city":"Milton Keynes",
    "sg:classifiers":[
        {
            "category":"Shopping",
            "subcategory":"Computers & Home Electronics",
            "type":"Retail Goods"
        }
    ],
    "sg:phone":"+44 1908 240258",
    "sg:postcode":"MK13 8PH",
    "sg:province":"Buckinghamshire",
    "wof:name":"Pc World",
    "wof:placetype":"venue"
},
  "geometry": {"coordinates":[-0.7771170139,52.0423126221],"type":"Point"}
}