{
  "type": "Feature",
  "properties": {
    "addr:full":"2-4 Westbourne Gro Bayswater Greater London W2 5RA",
    "addr:housenumber":"2-4",
    "addr:postcode":"w2 5ra",
    "addr:street":"Westbourne Gro",
    "iso:country":"GB",
    "sg:address":"2-4 Westbourne Gro",
    "sg:city":"Bayswater",
    "sg:classifiers":[
        {
            "category":"Shopping",
            "subcategory":"Mobile Phones",
            "type":"Retail Goods"
        }
    ],
    "sg:phone":"+44 20 7221 3456",
    "sg:postcode":"W2 5RA",
    "sg:province":"Greater London",
    "wof:name":"Euro Fone House",
    "wof:placetype":"venue"
},
  "geometry": {"coordinates":[-0.190103,51.515743],"type":"Point"}
}