{
  "type": "Feature",
  "properties": {
    "addr:full":"Lugg View Indust Estate, Moreton On Lugg Hereford Herefordshire HR4 8DP",
    "addr:housenumber":"lugg",
    "addr:postcode":"hr4 8dp",
    "iso:country":"GB",
    "sg:address":"Lugg View Indust Estate, Moreton On Lugg",
    "sg:city":"Hereford",
    "sg:classifiers":[
        {
            "category":"Manufacturing",
            "subcategory":"Jewelry",
            "type":"Manufacturing & Wholesale Goods"
        }
    ],
    "sg:phone":"+44 1432 761641",
    "sg:postcode":"HR4 8DP",
    "sg:province":"Herefordshire",
    "sg:tags":[
        "repair",
        "jewellery"
    ],
    "wof:name":"Traditional Joinery & Furniture Co",
    "wof:placetype":"venue"
},
  "geometry": {"coordinates":[-2.7296640873,52.1082077026],"type":"Point"}
}