{
  "type": "Feature",
  "properties": {
    "addr:full":"The Manse, Tabernacle Walk Stroud Gloucestershire GL5 3UJ",
    "addr:postcode":"gl5 3uj",
    "addr:street":"Walk",
    "iso:country":"GB",
    "sg:address":"The Manse, Tabernacle Walk",
    "sg:city":"Stroud",
    "sg:classifiers":[
        {
            "category":"Place Of Worship",
            "type":"Public Place"
        }
    ],
    "sg:phone":"+44 1453 758179",
    "sg:postcode":"GL5 3UJ",
    "sg:province":"Gloucestershire",
    "wof:name":"Rodborough Tabernacle United Reformed Church",
    "wof:placetype":"venue"
},
  "geometry": {"coordinates":[-2.2228589058,51.7354698181],"type":"Point"}
}