{
  "type": "Feature",
  "properties": {
    "iso:country":"GB",
    "sg:address":"Unit 2 Swallowfield Centre, Swallowfield Way",
    "sg:city":"Hayes",
    "sg:classifiers":[
        {
            "category":"Home & Garden",
            "subcategory":"Household Appliances",
            "type":"Retail Goods"
        }
    ],
    "sg:phone":"+44 870 567 8910",
    "sg:postcode":"UB3 1AW",
    "sg:province":"Greater London",
    "sg:tags":[
        "electrical"
    ],
    "wof:name":"B S H Appliance Care",
    "wof:placetype":"venue"
},
  "geometry": {"coordinates":[-0.435947001,51.5059928894],"type":"Point"}
}