{
  "type": "Feature",
  "properties": {
    "iso:country":"GB",
    "sg:address":"7-9 The Triangle, Tilehurst",
    "sg:city":"Reading",
    "sg:classifiers":[
        {
            "category":"Food & Beverages",
            "subcategory":"Meat & Fish",
            "type":"Retail Goods"
        }
    ],
    "sg:postcode":"RG30 4RN",
    "sg:province":"Berkshire",
    "sg:tags":[
        "butcher"
    ],
    "wof:name":"Village Butchers",
    "wof:placetype":"venue"
},
  "geometry": {"coordinates":[-1.041076,51.45742],"type":"Point"}
}