{
  "type": "Feature",
  "properties": {
    "addr:full":"7-9 The Triangle, Tilehurst Reading Berkshire RG30 4RN",
    "addr:housenumber":"7-9",
    "addr:postcode":"rg30 4rn",
    "addr:street":"The Triangle",
    "iso:country":"GB",
    "sg:address":"7-9 The Triangle, Tilehurst",
    "sg:city":"Reading",
    "sg:classifiers":[
        {
            "category":"Food & Beverages",
            "subcategory":"Meat & Fish",
            "type":"Retail Goods"
        }
    ],
    "sg:postcode":"RG30 4RN",
    "sg:province":"Berkshire",
    "sg:tags":[
        "butcher"
    ],
    "wof:name":"Village Butchers",
    "wof:placetype":"venue"
},
  "geometry": {"coordinates":[-1.041076,51.45742],"type":"Point"}
}