{
  "type": "Feature",
  "properties": {
    "addr:full":"300 Burnley Road Colne Lancashire BB8 8JN",
    "addr:housenumber":"300",
    "addr:postcode":"bb8 8jn",
    "addr:street":"Burnley Road",
    "iso:country":"GB",
    "sg:address":"300 Burnley Road",
    "sg:city":"Colne",
    "sg:classifiers":[
        {
            "category":"Retail",
            "subcategory":"Auto Rental",
            "type":"Services"
        }
    ],
    "sg:phone":"+44 1282 864481",
    "sg:postcode":"BB8 8JN",
    "sg:province":"Lancashire",
    "sg:tags":[
        "car"
    ],
    "wof:name":"Union Car Hire",
    "wof:placetype":"venue"
},
  "geometry": {"coordinates":[-2.1933720112,53.8481330872],"type":"Point"}
}