{
  "type": "Feature",
  "properties": {
    "iso:country":"GB",
    "sg:address":"43 Brunswick Street",
    "sg:city":"Cardiff",
    "sg:classifiers":[
        {
            "category":"Professional",
            "subcategory":"Lawyer & Legal Services",
            "type":"Services"
        }
    ],
    "sg:phone":"+44 29 2037 3582",
    "sg:postcode":"CF5 1LJ",
    "sg:province":"Cardiff",
    "sg:tags":[
        "conveyancing"
    ],
    "wof:name":"Beverly Davies Guthrie",
    "wof:placetype":"venue"
},
  "geometry": {"coordinates":[-3.206925,51.48103],"type":"Point"}
}