{
  "type": "Feature",
  "properties": {
    "addr:full":"Spring Bank West Hull East Riding of Yorkshire HU3 1LD",
    "addr:postcode":"hu3 1ld",
    "addr:street":"Spring Bank West",
    "iso:country":"GB",
    "sg:address":"Spring Bank West",
    "sg:city":"Hull",
    "sg:classifiers":[
        {
            "category":"Shopping",
            "subcategory":"Party Supplies",
            "type":"Retail Goods"
        }
    ],
    "sg:phone":"+44 1482 470366",
    "sg:postcode":"HU3 1LD",
    "sg:province":"East Riding of Yorkshire",
    "sg:tags":[
        "inflatables",
        "bouncy",
        "castle"
    ],
    "wof:name":"Castles in the Air",
    "wof:placetype":"venue"
},
  "geometry": {"coordinates":[-0.365059,53.75132],"type":"Point"}
}