{
  "type": "Feature",
  "properties": {
    "iso:country":"GB",
    "sg:address":"35a Ormskirk Road, Rainford",
    "sg:city":"St Helens",
    "sg:classifiers":[
        {
            "category":"Retail",
            "subcategory":"Veterinary Services",
            "type":"Services"
        }
    ],
    "sg:phone":"+44 1744 886284",
    "sg:postcode":"WA11 8DQ",
    "sg:province":"Lancashire",
    "sg:tags":[
        "surgeon"
    ],
    "wof:name":"Balmoral Veterinary Surgery",
    "wof:placetype":"venue"
},
  "geometry": {"coordinates":[-2.7905449867,53.5036773682],"type":"Point"}
}