{
  "type": "Feature",
  "properties": {
    "addr:full":"41 High Street Knaresborough North Yorkshire HG5 0HB",
    "addr:housenumber":"41",
    "addr:postcode":"hg5 0hb",
    "addr:street":"High Street",
    "iso:country":"GB",
    "sg:address":"41 High Street",
    "sg:city":"Knaresborough",
    "sg:classifiers":[
        {
            "category":"Home & Garden",
            "subcategory":"Kitchen Supply",
            "type":"Retail Goods"
        }
    ],
    "sg:postcode":"HG5 0HB",
    "sg:province":"North Yorkshire",
    "sg:tags":[
        "glassware",
        "china"
    ],
    "wof:name":"Practical Homes",
    "wof:placetype":"venue"
},
  "geometry": {"coordinates":[-1.467205,54.00864],"type":"Point"}
}