{
  "type": "Feature",
  "properties": {
    "addr:full":"9 Hillsborough Close, Eyres Monsell Leicester Leicestershire LE2 9QQ",
    "addr:housenumber":"9",
    "addr:postcode":"eyres;le2 9qq",
    "addr:street":"Hillsborough Close",
    "iso:country":"GB",
    "sg:address":"9 Hillsborough Close, Eyres Monsell",
    "sg:city":"Leicester",
    "sg:classifiers":[
        {
            "category":"Government",
            "subcategory":"Post Office",
            "type":"Public Place"
        }
    ],
    "sg:phone":"+44 116 278 3809",
    "sg:postcode":"LE2 9QQ",
    "sg:province":"Leicestershire",
    "sg:tags":[
        "messenger",
        "courier"
    ],
    "wof:name":"Leicester Despatch Riders",
    "wof:placetype":"venue"
},
  "geometry": {"coordinates":[-1.15389,52.585663],"type":"Point"}
}