{
  "type": "Feature",
  "properties": {
    "addr:full":"47 Minerva Way Wellingborough Northamptonshire NN8 3TP",
    "addr:housenumber":"47",
    "addr:postcode":"nn8 3tp",
    "addr:street":"Minerva Way",
    "iso:country":"GB",
    "sg:address":"47 Minerva Way",
    "sg:city":"Wellingborough",
    "sg:classifiers":[
        {
            "category":"Building & Trades",
            "subcategory":"Construction",
            "type":"Services"
        }
    ],
    "sg:postcode":"NN8 3TP",
    "sg:province":"Northamptonshire",
    "sg:tags":[
        "builder"
    ],
    "wof:name":"Interbuild Developments Ltd",
    "wof:placetype":"venue"
},
  "geometry": {"coordinates":[-0.7131119967,52.3066825867],"type":"Point"}
}