{
  "type": "Feature",
  "properties": {
    "iso:country":"GB",
    "sg:address":"New Road Surgery, 46 New Road",
    "sg:city":"Bromsgrove",
    "sg:classifiers":[
        {
            "category":"Health Services",
            "subcategory":"Clinic",
            "type":"Services"
        }
    ],
    "sg:phone":"+44 1527 871097",
    "sg:postcode":"B60 2JS",
    "sg:province":"Worcestershire",
    "sg:tags":[
        "nh"
    ],
    "wof:name":"Worcester & District Health Authority",
    "wof:placetype":"venue"
},
  "geometry": {"coordinates":[-2.05587,52.331089],"type":"Point"}
}