{
  "type": "Feature",
  "properties": {
    "iso:country":"GB",
    "sg:address":"30 Vauxhall Street",
    "sg:city":"London",
    "sg:classifiers":[
        {
            "category":"Food & Beverages",
            "subcategory":"Candy",
            "type":"Retail Goods"
        }
    ],
    "sg:phone":"+44 20 7793 0343",
    "sg:postcode":"SE11 5LG",
    "sg:province":"Greater London",
    "sg:tags":[
        "confectioner"
    ],
    "wof:name":"Kunal Confectioners",
    "wof:placetype":"venue"
},
  "geometry": {"coordinates":[-0.117617,51.488804],"type":"Point"}
}