{
  "type": "Feature",
  "properties": {
    "iso:country":"GB",
    "sg:address":"The Bungalow, Walcot Rd",
    "sg:city":"Shrewsbury",
    "sg:classifiers":[
        {
            "category":"Building & Trades",
            "subcategory":"Construction",
            "type":"Services"
        }
    ],
    "sg:phone":"+44 1952 770379",
    "sg:postcode":"SY4 4QQ",
    "sg:province":"Shropshire",
    "sg:tags":[
        "builder"
    ],
    "wof:name":"M Palmer",
    "wof:placetype":"venue"
},
  "geometry": {"coordinates":[-2.61897,52.722179],"type":"Point"}
}