{
  "type": "Feature",
  "properties": {
    "addr:full":"Units 13-16 Wirral Business Centre, Dock Rd Birkenhead Merseyside L41 1JW",
    "addr:housenumber":"units 13-16",
    "addr:postcode":"l41 1jw",
    "addr:street":"Wirral Business Centre Dock Rd",
    "iso:country":"GB",
    "sg:address":"Units 13-16 Wirral Business Centre, Dock Rd",
    "sg:city":"Birkenhead",
    "sg:classifiers":[
        {
            "category":"Professional",
            "subcategory":"Printing & Photocopies",
            "type":"Services"
        }
    ],
    "sg:phone":"+44 151 638 3771",
    "sg:postcode":"L41 1JW",
    "sg:province":"Merseyside",
    "sg:tags":[
        "print",
        "finisher"
    ],
    "wof:name":"Deeside Print Finishing Ltd",
    "wof:placetype":"venue"
},
  "geometry": {"coordinates":[-3.0254900455,53.3925590515],"type":"Point"}
}