{
  "type": "Feature",
  "properties": {
    "iso:country":"GB",
    "sg:address":"10 London Rd",
    "sg:city":"Grays",
    "sg:classifiers":[
        {
            "category":"Shopping",
            "subcategory":"Antiques",
            "type":"Retail Goods"
        }
    ],
    "sg:phone":"+44 1375 371200",
    "sg:postcode":"RM17 5XY",
    "sg:province":"Essex",
    "wof:name":"Kendon's Antiques",
    "wof:placetype":"venue"
},
  "geometry": {"coordinates":[0.3223800063,51.4784202576],"type":"Point"}
}