{
  "type": "Feature",
  "properties": {
    "addr:full":"138-140 Epsom Road Croydon Surrey CR0 4PY",
    "addr:housenumber":"138-140",
    "addr:postcode":"cr0 4py",
    "addr:street":"Epsom Road",
    "iso:country":"GB",
    "sg:address":"138-140 Epsom Road",
    "sg:city":"Croydon",
    "sg:classifiers":[
        {
            "category":"Professional",
            "subcategory":"Computer Services",
            "type":"Services"
        }
    ],
    "sg:phone":"+44 20 8667 9555",
    "sg:postcode":"CR0 4PY",
    "sg:province":"Surrey",
    "sg:tags":[
        "system",
        "software"
    ],
    "wof:name":"Off-Shore Four Hundred Ltd.",
    "wof:placetype":"venue"
},
  "geometry": {"coordinates":[-0.117089,51.367325],"type":"Point"}
}