{
  "type": "Feature",
  "properties": {
    "addr:full":"Horselake Farm, Cheriton Bishop Exeter Devon EX6 6HD",
    "addr:postcode":"ex6 6hd",
    "iso:country":"GB",
    "sg:address":"Horselake Farm, Cheriton Bishop",
    "sg:city":"Exeter",
    "sg:classifiers":[
        {
            "category":"Farming",
            "subcategory":"Livestock Farm",
            "type":"Manufacturing & Wholesale Goods"
        }
    ],
    "sg:phone":"+44 1647 24220",
    "sg:postcode":"EX6 6HD",
    "sg:province":"Devon",
    "sg:tags":[
        "others"
    ],
    "wof:name":"Philip J Stephens",
    "wof:placetype":"venue"
},
  "geometry": {"coordinates":[-3.7384989262,50.7236213684],"type":"Point"}
}