{
  "type": "Feature",
  "properties": {
    "iso:country":"GB",
    "sg:address":"41 Ingleton",
    "sg:city":"Bracknell",
    "sg:classifiers":[
        {
            "category":"Social Services",
            "subcategory":"Child Care",
            "type":"Services"
        }
    ],
    "sg:phone":"+44 1344 481409",
    "sg:postcode":"RG12 7RN",
    "sg:province":"Berkshire",
    "sg:tags":[
        "agency",
        "nanny"
    ],
    "wof:name":"Jigsaw Nanny Agency",
    "wof:placetype":"venue"
},
  "geometry": {"coordinates":[-0.76048702,51.4108810425],"type":"Point"}
}