{
  "type": "Feature",
  "properties": {
    "addr:full":"26 Broadmead Rd Leicester Leicestershire LE8 4AB",
    "addr:housenumber":"26",
    "addr:postcode":"le8 4ab",
    "addr:street":"Broadmead Rd",
    "iso:country":"GB",
    "sg:address":"26 Broadmead Rd",
    "sg:city":"Leicester",
    "sg:classifiers":[
        {
            "category":"Communications",
            "subcategory":"Film & Video Production",
            "type":"Services"
        }
    ],
    "sg:phone":"+44 116 277 3284",
    "sg:postcode":"LE8 4AB",
    "sg:province":"Leicestershire",
    "sg:tags":[
        "illustrator",
        "artist"
    ],
    "wof:name":"Krystyna Lange",
    "wof:placetype":"venue"
},
  "geometry": {"coordinates":[-1.169568,52.567173],"type":"Point"}
}