{
  "type": "Feature",
  "properties": {
    "iso:country":"GB",
    "sg:address":"First Floor, 57 High Road",
    "sg:city":"Bushey",
    "sg:classifiers":[
        {
            "category":"Professional",
            "subcategory":"Accounting & Tax Preparation",
            "type":"Services"
        }
    ],
    "sg:phone":"+44 20 8950 6177",
    "sg:postcode":"WD23 1EE",
    "sg:province":"Hertfordshire",
    "sg:tags":[
        "accountant"
    ],
    "wof:name":"George F Gibbs",
    "wof:placetype":"venue"
},
  "geometry": {"coordinates":[-0.3421150148,51.6343421936],"type":"Point"}
}