{
  "type": "Feature",
  "properties": {
    "addr:full":"3 Firecrest Drive, Leegomery Telford Shropshire TF1 6FZ",
    "addr:housenumber":"3",
    "addr:postcode":"tf1 6fz",
    "addr:street":"Firecrest Drive",
    "iso:country":"GB",
    "sg:address":"3 Firecrest Drive, Leegomery",
    "sg:city":"Telford",
    "sg:classifiers":[
        {
            "category":"Professional",
            "subcategory":"Accounting & Tax Preparation",
            "type":"Services"
        }
    ],
    "sg:phone":"+44 1952 243268",
    "sg:postcode":"TF1 6FZ",
    "sg:province":"Shropshire",
    "sg:tags":[
        "accountant",
        "bookkeeping",
        "primarily",
        "activity"
    ],
    "wof:name":"Tab Services",
    "wof:placetype":"venue"
},
  "geometry": {"coordinates":[-2.5083858967,52.7089195251],"type":"Point"}
}