{
  "type": "Feature",
  "properties": {
    "iso:country":"GB",
    "sg:address":"Kelvin Gro",
    "sg:city":"North Shields",
    "sg:classifiers":[
        {
            "category":"Health Services",
            "subcategory":"Health Practitioner",
            "type":"Services"
        }
    ],
    "sg:postcode":"NE29 9LE",
    "sg:province":"Tyne and Wear",
    "sg:tags":[
        "physiotherapist"
    ],
    "wof:name":"Sports Massage Centre",
    "wof:placetype":"venue"
},
  "geometry": {"coordinates":[-1.452263,55.021507],"type":"Point"}
}