{
  "type": "Feature",
  "properties": {
    "iso:country":"GB",
    "sg:address":"23 Beck Lane, Horsham St Faith",
    "sg:city":"Norwich",
    "sg:classifiers":[
        {
            "category":"Building & Trades",
            "subcategory":"Construction",
            "type":"Services"
        }
    ],
    "sg:postcode":"NR10 3LD",
    "sg:province":"Norfolk",
    "sg:tags":[
        "heating",
        "contractor"
    ],
    "wof:name":"Bernard & Craig Dennis",
    "wof:placetype":"venue"
},
  "geometry": {"coordinates":[1.283205986,52.6928939819],"type":"Point"}
}