{
  "type": "Feature",
  "properties": {
    "iso:country":"GB",
    "sg:address":"34 Charterhouse Rd, Idle",
    "sg:city":"Bradford",
    "sg:classifiers":[
        {
            "category":"Retail",
            "subcategory":"Storage",
            "type":"Services"
        }
    ],
    "sg:postcode":"BD10 8LZ",
    "sg:province":"West Yorkshire",
    "sg:tags":[
        "household",
        "removal"
    ],
    "wof:name":"Sykes,M,",
    "wof:placetype":"venue"
},
  "geometry": {"coordinates":[-1.734262,53.840054],"type":"Point"}
}