{
  "type": "Feature",
  "properties": {
    "iso:country":"GB",
    "sg:address":"101 Atherton Road",
    "sg:city":"Wigan",
    "sg:classifiers":[
        {
            "category":"Food & Beverages",
            "subcategory":"Meat & Fish",
            "type":"Retail Goods"
        }
    ],
    "sg:phone":"+44 1942 256246",
    "sg:postcode":"WN2 3EE",
    "sg:province":"Lancashire",
    "sg:tags":[
        "butcher"
    ],
    "wof:name":"E J Rogers",
    "wof:placetype":"venue"
},
  "geometry": {"coordinates":[-2.57712,53.532108],"type":"Point"}
}