{
  "type": "Feature",
  "properties": {
    "addr:full":"Fairoaks Airport, Chobham Woking Surrey GU24 8HU",
    "addr:postcode":"gu24 8hu",
    "iso:country":"GB",
    "sg:address":"Fairoaks Airport, Chobham",
    "sg:city":"Woking",
    "sg:classifiers":[
        {
            "category":"Professional",
            "subcategory":"Management & Consulting",
            "type":"Services"
        }
    ],
    "sg:postcode":"GU24 8HU",
    "sg:province":"Surrey",
    "sg:tags":[
        "consultant",
        "safety",
        "business"
    ],
    "wof:name":"Barker,John,",
    "wof:placetype":"venue"
},
  "geometry": {"coordinates":[-0.56338,51.350052],"type":"Point"}
}