{
  "type": "Feature",
  "properties": {
    "addr:full":"Mill Farm, Metheringham Fen Lincoln Lincolnshire LN4 3AH",
    "addr:housenumber":"metheringham",
    "addr:postcode":"ln4 3ah",
    "addr:street":"Fen Lincoln",
    "iso:country":"GB",
    "sg:address":"Mill Farm, Metheringham Fen",
    "sg:city":"Lincoln",
    "sg:classifiers":[
        {
            "category":"Farming",
            "subcategory":"Livestock Farm",
            "type":"Manufacturing & Wholesale Goods"
        }
    ],
    "sg:postcode":"LN4 3AH",
    "sg:province":"Lincolnshire",
    "sg:tags":[
        "others"
    ],
    "wof:name":"A J Pearson",
    "wof:placetype":"venue"
},
  "geometry": {"coordinates":[-0.40507,53.141895],"type":"Point"}
}