{
  "type": "Feature",
  "properties": {
    "addr:full":"163 Northfield Road Ringwood Dorset BH24 1SS",
    "addr:housenumber":"163",
    "addr:postcode":"bh24 1ss",
    "addr:street":"Northfield Road",
    "iso:country":"GB",
    "sg:address":"163 Northfield Road",
    "sg:city":"Ringwood",
    "sg:classifiers":[
        {
            "category":"Health Services",
            "subcategory":"Dentist",
            "type":"Services"
        }
    ],
    "sg:phone":"+44 1425 480032",
    "sg:postcode":"BH24 1SS",
    "sg:province":"Dorset",
    "wof:name":"D M Smit",
    "wof:placetype":"venue"
},
  "geometry": {"coordinates":[-1.769938,50.856033],"type":"Point"}
}