{
  "type": "Feature",
  "properties": {
    "addr:full":"12 Bank Street Penicuik Midlothian EH26 9BG",
    "addr:housenumber":"12",
    "addr:postcode":"eh26 9bg",
    "addr:street":"Bank Street",
    "iso:country":"GB",
    "sg:address":"12 Bank Street",
    "sg:city":"Penicuik",
    "sg:classifiers":[
        {
            "category":"Personal",
            "subcategory":"Beauty Salon",
            "type":"Services"
        }
    ],
    "sg:postcode":"EH26 9BG",
    "sg:province":"Midlothian",
    "wof:name":"Beauty Basics",
    "wof:placetype":"venue"
},
  "geometry": {"coordinates":[-3.222481966,55.8267555237],"type":"Point"}
}