{
  "type": "Feature",
  "properties": {
    "addr:full":"8 Lower Road, Bedhampton Havant Hampshire PO9 3LH",
    "addr:housenumber":"8",
    "addr:postcode":"po9 3lh",
    "addr:street":"Lower Road",
    "iso:country":"GB",
    "sg:address":"8 Lower Road, Bedhampton",
    "sg:city":"Havant",
    "sg:classifiers":[
        {
            "category":"Health Services",
            "subcategory":"Nursing And Care Facility",
            "type":"Services"
        },
        {
            "category":"Social Services",
            "subcategory":"Retirement Home",
            "type":"Services"
        }
    ],
    "sg:phone":"+44 23 9245 2644",
    "sg:postcode":"PO9 3LH",
    "sg:province":"Hampshire",
    "sg:tags":[
        "rest"
    ],
    "wof:name":"The Lodge",
    "wof:placetype":"venue"
},
  "geometry": {"coordinates":[-1.005781,50.852039],"type":"Point"}
}