{
  "type": "Feature",
  "properties": {
    "iso:country":"GB",
    "sg:address":"59 Fleet Street",
    "sg:city":"Swindon",
    "sg:classifiers":[
        {
            "category":"Bars & Pubs",
            "type":"Food & Drink"
        }
    ],
    "sg:phone":"+44 1793 534116",
    "sg:postcode":"SN1 1RA",
    "sg:province":"Wiltshire",
    "sg:tags":[
        "pubs",
        "inn"
    ],
    "wof:name":"The Mail Coach",
    "wof:placetype":"venue"
},
  "geometry": {"coordinates":[-1.786769,51.562447],"type":"Point"}
}