{
  "type": "Feature",
  "properties": {
    "iso:country":"GB",
    "sg:address":"30 St Peters Rd",
    "sg:city":"Huntingdon",
    "sg:classifiers":[
        {
            "category":"Building & Trades",
            "subcategory":"Construction",
            "type":"Services"
        }
    ],
    "sg:phone":"+44 1480 414191",
    "sg:postcode":"PE18 7DG",
    "sg:province":"Cambridgeshire",
    "sg:tags":[
        "builder"
    ],
    "wof:name":"Haymills Ltd",
    "wof:placetype":"venue"
},
  "geometry": {"coordinates":[-0.298309,52.331532],"type":"Point"}
}