{
  "type": "Feature",
  "properties": {
    "addr:full":"Robsheugh Farm Cottage, Millbourne Newcastle-upon-tyne Northumberland NE20 0JQ",
    "addr:postcode":"ne20 0jq",
    "addr:street":"Millbourne",
    "iso:country":"GB",
    "sg:address":"Robsheugh Farm Cottage, Millbourne",
    "sg:city":"Newcastle-upon-tyne",
    "sg:classifiers":[
        {
            "category":"Farming",
            "subcategory":"Poultry Farm",
            "type":"Manufacturing & Wholesale Goods"
        },
        {
            "category":"Shopping",
            "type":"Retail Goods"
        }
    ],
    "sg:phone":"+44 1661 855900",
    "sg:postcode":"NE20 0JQ",
    "sg:province":"Northumberland",
    "sg:tags":[
        "merchant",
        "related"
    ],
    "wof:name":"United Agri Products Ltd.",
    "wof:placetype":"venue"
},
  "geometry": {"coordinates":[-1.8473299742,55.0623283386],"type":"Point"}
}