{
  "type": "Feature",
  "properties": {
    "addr:full":"Rothewrwick House, 3 Thomas Moore London Greater London E1W 1YX",
    "addr:housenumber":"3",
    "addr:postcode":"e1w 1yx",
    "addr:street":"Thomas Moore",
    "iso:country":"GB",
    "sg:address":"Rothewrwick House, 3 Thomas Moore",
    "sg:city":"London",
    "sg:classifiers":[
        {
            "category":"Professional",
            "subcategory":"Accounting & Tax Preparation",
            "type":"Services"
        }
    ],
    "sg:phone":"+44 20 7628 4321",
    "sg:postcode":"E1W 1YX",
    "sg:province":"Greater London",
    "sg:tags":[
        "accountant"
    ],
    "wof:name":"Dixon Wilson",
    "wof:placetype":"venue"
},
  "geometry": {"coordinates":[-0.0682900026,51.5062599182],"type":"Point"}
}