{
  "type": "Feature",
  "properties": {
    "addr:full":"Hems Court, 84-86 Longbrook Street Exeter Devon EX4 6AP",
    "addr:housenumber":"84-86",
    "addr:postcode":"ex4 6ap",
    "addr:street":"Hems;Longbrook Street",
    "iso:country":"GB",
    "sg:address":"Hems Court, 84-86 Longbrook Street",
    "sg:city":"Exeter",
    "sg:classifiers":[
        {
            "category":"Manufacturing",
            "subcategory":"Buildings",
            "type":"Manufacturing & Wholesale Goods"
        }
    ],
    "sg:phone":"+44 1392 421200",
    "sg:postcode":"EX4 6AP",
    "sg:province":"Devon",
    "sg:tags":[
        "framed",
        "timber"
    ],
    "wof:name":"Westructure Ltd.",
    "wof:placetype":"venue"
},
  "geometry": {"coordinates":[-3.5263700485,50.7281570435],"type":"Point"}
}