{
  "type": "Feature",
  "properties": {
    "addr:full":"Floyds Row, St.aldgates Oxford Oxfordshire OX1 1SS",
    "addr:postcode":"ox1 1ss",
    "addr:street":"Floyds Row St.Aldgates",
    "iso:country":"GB",
    "sg:address":"Floyds Row, St.aldgates",
    "sg:city":"Oxford",
    "sg:classifiers":[
        {
            "category":"Social Services",
            "type":"Services"
        }
    ],
    "sg:phone":"+44 1865 442600",
    "sg:postcode":"OX1 1SS",
    "sg:province":"Oxfordshire",
    "sg:tags":[
        "benefit",
        "agency"
    ],
    "wof:name":"Benefits Agency",
    "wof:placetype":"venue"
},
  "geometry": {"coordinates":[-1.2560540438,51.7484397888],"type":"Point"}
}