{
  "type": "Feature",
  "properties": {
    "addr:full":"153 Court Rd Orpington Kent BR6 0PX",
    "addr:housenumber":"153",
    "addr:postcode":"br6 0px",
    "addr:street":"Court Rd",
    "iso:country":"GB",
    "sg:address":"153 Court Rd",
    "sg:city":"Orpington",
    "sg:classifiers":[
        {
            "category":"Professional",
            "subcategory":"Lawyer & Legal Services",
            "type":"Services"
        }
    ],
    "sg:phone":"+44 1689 603217",
    "sg:postcode":"BR6 0PX",
    "sg:province":"Kent",
    "wof:name":"Chambers Legal Costs Consultancy",
    "wof:placetype":"venue"
},
  "geometry": {"coordinates":[0.10108,51.37804],"type":"Point"}
}