{
  "type": "Feature",
  "properties": {
    "iso:country":"GB",
    "sg:address":"Valley View, Church Lane, Waltham",
    "sg:city":"Canterbury",
    "sg:classifiers":[
        {
            "category":"Professional",
            "subcategory":"Printing & Photocopies",
            "type":"Services"
        }
    ],
    "sg:phone":"+44 1227 700473",
    "sg:postcode":"CT4 5SS",
    "sg:province":"Kent",
    "sg:tags":[
        "duplicating",
        "copying"
    ],
    "wof:name":"Kent Business Equipment",
    "wof:placetype":"venue"
},
  "geometry": {"coordinates":[1.016816,51.198357],"type":"Point"}
}