{
  "type": "Feature",
  "properties": {
    "iso:country":"GB",
    "sg:address":"Bristol Street",
    "sg:city":"Birmingham",
    "sg:classifiers":[
        {
            "category":"Professional",
            "subcategory":"Business Services",
            "type":"Services"
        }
    ],
    "sg:phone":"+44 121 622 2528",
    "sg:postcode":"B5 7AS",
    "sg:province":"West Midlands",
    "sg:tags":[
        "accomodation"
    ],
    "wof:name":"Monaco House",
    "wof:placetype":"venue"
},
  "geometry": {"coordinates":[-1.9004889727,52.4687767029],"type":"Point"}
}