{
  "type": "Feature",
  "properties": {
    "iso:country":"GB",
    "sg:address":"Village Farm, Shilbottle",
    "sg:city":"Alnwick",
    "sg:classifiers":[
        {
            "category":"Sports & Exercise",
            "subcategory":"Gym",
            "type":"Entertainment"
        }
    ],
    "sg:phone":"+44 1665 575187",
    "sg:postcode":"NE66 2XR",
    "sg:province":"Northumberland",
    "sg:tags":[
        "fitness",
        "health",
        "centre"
    ],
    "wof:name":"Village Farm Fitness Club",
    "wof:placetype":"venue"
},
  "geometry": {"coordinates":[-1.685958,55.370876],"type":"Point"}
}