{
  "type": "Feature",
  "properties": {
    "iso:country":"GB",
    "sg:address":"13 Grand Hotel Buildings, Compton Street",
    "sg:city":"Eastbourne",
    "sg:classifiers":[
        {
            "category":"Deli",
            "type":"Food & Drink"
        }
    ],
    "sg:phone":"+44 1323 724546",
    "sg:postcode":"BN21 4EJ",
    "sg:province":"East Sussex",
    "sg:tags":[
        "delicatessen"
    ],
    "wof:name":"Hudsons",
    "wof:placetype":"venue"
},
  "geometry": {"coordinates":[0.2853499949,50.766910553],"type":"Point"}
}