{
  "type": "Feature",
  "properties": {
    "addr:full":"Unit 4, Windroos Nursery Littlehampton West Sussex BN17 6LY",
    "addr:housenumber":"unit 4 windroos",
    "addr:postcode":"bn17 6ly",
    "iso:country":"GB",
    "sg:address":"Unit 4, Windroos Nursery",
    "sg:city":"Littlehampton",
    "sg:classifiers":[
        {
            "category":"Manufacturing",
            "subcategory":"Wood Products",
            "type":"Manufacturing & Wholesale Goods"
        }
    ],
    "sg:postcode":"BN17 6LY",
    "sg:province":"West Sussex",
    "sg:tags":[
        "packaging",
        "crate",
        "pallets"
    ],
    "wof:name":"D A P Foods",
    "wof:placetype":"venue"
},
  "geometry": {"coordinates":[-0.5389590263,50.8210296631],"type":"Point"}
}