{
  "type": "Feature",
  "properties": {
    "addr:full":"24 Oxford Street Southampton Hampshire SO14 3DJ",
    "addr:housenumber":"24",
    "addr:postcode":"so14 3dj",
    "addr:street":"Oxford Street",
    "iso:country":"GB",
    "sg:address":"24 Oxford Street",
    "sg:city":"Southampton",
    "sg:classifiers":[
        {
            "category":"Personal",
            "subcategory":"Beauty Salon",
            "type":"Services"
        }
    ],
    "sg:postcode":"SO14 3DJ",
    "sg:province":"Hampshire",
    "sg:tags":[
        "unisex",
        "hairdresser"
    ],
    "wof:name":"Frank David",
    "wof:placetype":"venue"
},
  "geometry": {"coordinates":[-1.3987770081,50.8983612061],"type":"Point"}
}