{
  "type": "Feature",
  "properties": {
    "addr:full":"31 Westgate Grantham Lincolnshire NG31 6LX",
    "addr:housenumber":"31",
    "addr:postcode":"ng31 6lx",
    "addr:street":"Westgate Grantham",
    "iso:country":"GB",
    "sg:address":"31 Westgate",
    "sg:city":"Grantham",
    "sg:classifiers":[
        {
            "category":"Professional",
            "subcategory":"Accounting & Tax Preparation",
            "type":"Services"
        }
    ],
    "sg:postcode":"NG31 6LX",
    "sg:province":"Lincolnshire",
    "sg:tags":[
        "consultant",
        "accountant"
    ],
    "wof:name":"East Midlands Tax Services",
    "wof:placetype":"venue"
},
  "geometry": {"coordinates":[-0.6448330283,52.9104042053],"type":"Point"}
}