{
  "type": "Feature",
  "properties": {
    "addr:full":"All Hallows Street Retford Nottinghamshire DN22 7TP",
    "addr:postcode":"dn22 7tp",
    "addr:street":"Hallows Street",
    "iso:country":"GB",
    "sg:address":"All Hallows Street",
    "sg:city":"Retford",
    "sg:classifiers":[
        {
            "category":"Bars & Pubs",
            "type":"Food & Drink"
        }
    ],
    "sg:phone":"+44 1777 702014",
    "sg:postcode":"DN22 7TP",
    "sg:province":"Nottinghamshire",
    "sg:tags":[
        "pubs",
        "inn"
    ],
    "wof:name":"The Gate Inn",
    "wof:placetype":"venue"
},
  "geometry": {"coordinates":[-0.9429870248,53.3095474243],"type":"Point"}
}