{
  "type": "Feature",
  "properties": {
    "iso:country":"GB",
    "sg:address":"Summit House, Summit Road, Crambourne Industrial Estate",
    "sg:city":"Potters Bar",
    "sg:classifiers":[
        {
            "category":"Professional",
            "subcategory":"Business Services",
            "type":"Services"
        },
        {
            "category":"Shopping",
            "subcategory":"Used Merchandise",
            "type":"Retail Goods"
        }
    ],
    "sg:phone":"+44 1707 662287",
    "sg:postcode":"EN6 3ER",
    "sg:province":"Greater London",
    "sg:tags":[
        "shop",
        "import",
        "export",
        "second-hand",
        "agent"
    ],
    "wof:name":"The Essential Housewares Co. Ltd.",
    "wof:placetype":"venue"
},
  "geometry": {"coordinates":[-0.2002830058,51.7044754028],"type":"Point"}
}