{
  "type": "Feature",
  "properties": {
    "addr:full":"38 Fisher St Workington Cumbria CA14 2ER",
    "addr:housenumber":"38",
    "addr:postcode":"ca14 2er",
    "addr:street":"Fisher St",
    "iso:country":"GB",
    "sg:address":"38 Fisher St",
    "sg:city":"Workington",
    "sg:classifiers":[
        {
            "category":"Health Services",
            "subcategory":"Podiatrist",
            "type":"Services"
        }
    ],
    "sg:phone":"+44 1900 823615",
    "sg:postcode":"CA14 2ER",
    "sg:province":"Cumbria",
    "sg:tags":[
        "podiatrists",
        "chiropodist"
    ],
    "wof:name":"Janet White",
    "wof:placetype":"venue"
},
  "geometry": {"coordinates":[-3.552583,54.645115],"type":"Point"}
}