{
  "type": "Feature",
  "properties": {
    "iso:country":"GB",
    "sg:address":"379 Clarkston Road",
    "sg:city":"Glasgow",
    "sg:classifiers":[
        {
            "category":"Bakery",
            "type":"Food & Drink"
        }
    ],
    "sg:phone":"+44 141 633 0392",
    "sg:postcode":"G44 3JG",
    "sg:province":"East Renfrewshire",
    "sg:tags":[
        "cake",
        "maker"
    ],
    "wof:name":"Creative Cakes",
    "wof:placetype":"venue"
},
  "geometry": {"coordinates":[-4.2697610855,55.8115348816],"type":"Point"}
}