{
  "type": "Feature",
  "properties": {
    "addr:full":"9 Priory Street Monmouth Gloucestershire NP25 3BR",
    "addr:housenumber":"9",
    "addr:postcode":"np25 3br",
    "addr:street":"Priory Street",
    "iso:country":"GB",
    "sg:address":"9 Priory Street",
    "sg:city":"Monmouth",
    "sg:classifiers":[
        {
            "category":"Restaurant",
            "type":"Food & Drink"
        }
    ],
    "sg:phone":"+44 1600 714940",
    "sg:postcode":"NP25 3BR",
    "sg:province":"Gloucestershire",
    "sg:tags":[
        "indian"
    ],
    "wof:name":"Mishbah Tandoori Restaurant",
    "wof:placetype":"venue"
},
  "geometry": {"coordinates":[-2.7146449089,51.8133468628],"type":"Point"}
}