{
  "type": "Feature",
  "properties": {
    "addr:full":"117 High Road, Needham Harleston Norfolk IP20 9LG",
    "addr:housenumber":"117",
    "addr:postcode":"ip20 9lg",
    "addr:street":"High Road;Harleston",
    "iso:country":"GB",
    "sg:address":"117 High Road, Needham",
    "sg:city":"Harleston",
    "sg:classifiers":[
        {
            "category":"Bars & Pubs",
            "type":"Food & Drink"
        }
    ],
    "sg:phone":"+44 1379 853930",
    "sg:postcode":"IP20 9LG",
    "sg:province":"Norfolk",
    "sg:tags":[
        "pubs",
        "inn"
    ],
    "wof:name":"The Red Lion",
    "wof:placetype":"venue"
},
  "geometry": {"coordinates":[1.2676969767,52.3817405701],"type":"Point"}
}