{
  "type": "Feature",
  "properties": {
    "addr:full":"Unit 13b Brindley Court, Dalewood Road Newcastle Staffordshire ST5 9QA",
    "addr:housenumber":"unit 13b",
    "addr:postcode":"st5 9qa",
    "addr:street":"Brindley Court Dalewood Road",
    "iso:country":"GB",
    "sg:address":"Unit 13b Brindley Court, Dalewood Road",
    "sg:city":"Newcastle",
    "sg:classifiers":[
        {
            "category":"Professional",
            "subcategory":"Computer Services",
            "type":"Services"
        }
    ],
    "sg:phone":"+44 1782 562522",
    "sg:postcode":"ST5 9QA",
    "sg:province":"Staffordshire",
    "sg:tags":[
        "system",
        "software"
    ],
    "wof:name":"Mayne Computer Technology Ltd.",
    "wof:placetype":"venue"
},
  "geometry": {"coordinates":[-2.2482559681,53.030456543],"type":"Point"}
}