{
  "type": "Feature",
  "properties": {
    "iso:country":"GB",
    "sg:address":"West St, Moulton",
    "sg:city":"Northampton",
    "sg:classifiers":[
        {
            "category":"Autos & Motor Vehicles",
            "subcategory":"Automobile Sales",
            "type":"Retail Goods"
        }
    ],
    "sg:phone":"+44 1604 644034",
    "sg:postcode":"NN3 7SB",
    "sg:province":"Northamptonshire",
    "sg:tags":[
        "car"
    ],
    "wof:name":"Clifford Hill Car Sales",
    "wof:placetype":"venue"
},
  "geometry": {"coordinates":[-0.8524479866,52.2885894775],"type":"Point"}
}