{
  "type": "Feature",
  "properties": {
    "addr:full":"59 Creek Road London Greater London SE8 3BU",
    "addr:housenumber":"59",
    "addr:postcode":"se8 3bu",
    "addr:street":"Creek Road",
    "iso:country":"GB",
    "sg:address":"59 Creek Road",
    "sg:city":"London",
    "sg:classifiers":[
        {
            "category":"Taxi",
            "type":"Transportation"
        }
    ],
    "sg:phone":"+44 20 8691 5821",
    "sg:postcode":"SE8 3BU",
    "sg:province":"Greater London",
    "sg:tags":[
        "mini",
        "hire",
        "cab",
        "private",
        "vehicle"
    ],
    "wof:name":"Salis Car Hire",
    "wof:placetype":"venue"
},
  "geometry": {"coordinates":[-0.0231849998,51.4809837341],"type":"Point"}
}