{
  "type": "Feature",
  "properties": {
    "iso:country":"GB",
    "sg:address":"8 Scrub Rise",
    "sg:city":"Billericay",
    "sg:classifiers":[
        {
            "category":"Transit Center",
            "subcategory":"Passenger",
            "type":"Transportation"
        }
    ],
    "sg:phone":"+44 1277 655772",
    "sg:postcode":"CM12 9PG",
    "sg:province":"Essex",
    "sg:tags":[
        "boarding",
        "kennel",
        "catteries"
    ],
    "wof:name":"Animal Magic",
    "wof:placetype":"venue"
},
  "geometry": {"coordinates":[0.405855,51.616798],"type":"Point"}
}