{
  "type": "Feature",
  "properties": {
    "addr:full":"27 Jock's Lodge Edinburgh City of Edinburgh EH8 7AA",
    "addr:housenumber":"27",
    "addr:postcode":"eh8 7aa",
    "addr:street":"Jock'S Lodge Edinburgh",
    "iso:country":"GB",
    "sg:address":"27 Jock's Lodge",
    "sg:city":"Edinburgh",
    "sg:classifiers":[
        {
            "category":"Restaurant",
            "type":"Food & Drink"
        }
    ],
    "sg:phone":"+44 131 661 0202",
    "sg:postcode":"EH8 7AA",
    "sg:province":"City of Edinburgh",
    "wof:name":"Seven Spices",
    "wof:placetype":"venue"
},
  "geometry": {"coordinates":[-3.1500599384,55.9552116394],"type":"Point"}
}