{
  "type": "Feature",
  "properties": {
    "addr:full":"28 Princess Road, Fairgrove Rochdale Lancashire OL16 4AY",
    "addr:housenumber":"28",
    "addr:postcode":"ol16 4ay",
    "addr:street":"Princess Road",
    "iso:country":"GB",
    "sg:address":"28 Princess Road, Fairgrove",
    "sg:city":"Rochdale",
    "sg:classifiers":[
        {
            "category":"Building & Trades",
            "subcategory":"Construction",
            "type":"Services"
        }
    ],
    "sg:phone":"+44 1706 642225",
    "sg:postcode":"OL16 4AY",
    "sg:province":"Lancashire",
    "sg:tags":[
        "decorator",
        "painter"
    ],
    "wof:name":"E J Chrimes",
    "wof:placetype":"venue"
},
  "geometry": {"coordinates":[-2.1222651005,53.6139526367],"type":"Point"}
}