{
  "type": "Feature",
  "properties": {
    "iso:country":"GB",
    "sg:address":"River Road",
    "sg:city":"Thornton Cleveleys",
    "sg:classifiers":[
        {
            "category":"Recreation",
            "subcategory":"Campground",
            "type":"Entertainment"
        }
    ],
    "sg:phone":"+44 1253 826129",
    "sg:postcode":"FY5 5LR",
    "sg:province":"Lancashire",
    "sg:tags":[
        "caravan",
        "park"
    ],
    "wof:name":"D Edwards",
    "wof:placetype":"venue"
},
  "geometry": {"coordinates":[-2.983435,53.879761],"type":"Point"}
}