{
  "type": "Feature",
  "properties": {
    "iso:country":"GB",
    "sg:address":"70 Shirburn Rd",
    "sg:city":"Torquay",
    "sg:classifiers":[
        {
            "category":"Home & Garden",
            "subcategory":"Carpets & Floor Coverings",
            "type":"Retail Goods"
        }
    ],
    "sg:postcode":"TQ1 4HR",
    "sg:province":"Devon",
    "sg:tags":[
        "carpets",
        "rug",
        "matting"
    ],
    "wof:name":"Hogg,David,",
    "wof:placetype":"venue"
},
  "geometry": {"coordinates":[-3.534259,50.477219],"type":"Point"}
}