{
  "type": "Feature",
  "properties": {
    "addr:full":"Shripney Rd Bognor Regis West Sussex PO22 9LN",
    "addr:postcode":"po22 9ln",
    "addr:street":"Shripney Rd",
    "iso:country":"GB",
    "sg:address":"Shripney Rd",
    "sg:city":"Bognor Regis",
    "sg:classifiers":[
        {
            "category":"Bars & Pubs",
            "type":"Food & Drink"
        }
    ],
    "sg:phone":"+44 1604 668866",
    "sg:postcode":"PO22 9LN",
    "sg:province":"West Sussex",
    "sg:tags":[
        "pubs",
        "inn"
    ],
    "wof:name":"Carlsberg-Tetley Plc",
    "wof:placetype":"venue"
},
  "geometry": {"coordinates":[-0.6694880128,50.7952384949],"type":"Point"}
}