{
  "type": "Feature",
  "properties": {
    "addr:full":"64-66 Buchanan Street Glasgow Glasgow City G1 3JE",
    "addr:housenumber":"64-66",
    "addr:postcode":"g1 3je",
    "addr:street":"Buchanan Street",
    "iso:country":"GB",
    "sg:address":"64-66 Buchanan Street",
    "sg:city":"Glasgow",
    "sg:classifiers":[
        {
            "category":"Shopping",
            "subcategory":"Clothing, Apparel, & Fashions",
            "type":"Retail Goods"
        }
    ],
    "sg:phone":"+44 141 248 2780",
    "sg:postcode":"G1 3JE",
    "sg:province":"Glasgow City",
    "sg:tags":[
        "shop"
    ],
    "wof:name":"Next Retail",
    "wof:placetype":"venue"
},
  "geometry": {"coordinates":[-4.254407,55.859589],"type":"Point"}
}