{
  "type": "Feature",
  "properties": {
    "addr:full":"14 Tennyson Drive Newport Pagnell Buckinghamshire MK16 8PH",
    "addr:housenumber":"14",
    "addr:postcode":"mk16 8ph",
    "addr:street":"Tennyson Drive",
    "iso:country":"GB",
    "sg:address":"14 Tennyson Drive",
    "sg:city":"Newport Pagnell",
    "sg:classifiers":[
        {
            "category":"Manufacturing",
            "subcategory":"Petroleum Products",
            "type":"Manufacturing & Wholesale Goods"
        }
    ],
    "sg:postcode":"MK16 8PH",
    "sg:province":"Buckinghamshire",
    "sg:tags":[
        "double",
        "glazing"
    ],
    "wof:name":"Anglo Windows",
    "wof:placetype":"venue"
},
  "geometry": {"coordinates":[-0.7413920164,52.0851478577],"type":"Point"}
}