{
  "type": "Feature",
  "properties": {
    "addr:full":"Western Ho, 43 Smallbrook Queensway Birmingham West Midlands B5 4HQ",
    "addr:housenumber":"43",
    "addr:postcode":"b5 4hq",
    "addr:street":"Smallbrook Queensway",
    "iso:country":"GB",
    "sg:address":"Western Ho, 43 Smallbrook Queensway",
    "sg:city":"Birmingham",
    "sg:classifiers":[
        {
            "category":"Manufacturing",
            "subcategory":"Tools & Machinery",
            "type":"Manufacturing & Wholesale Goods"
        }
    ],
    "sg:phone":"+44 121 631 4686",
    "sg:postcode":"B5 4HQ",
    "sg:province":"West Midlands",
    "sg:tags":[
        "society",
        "friendly"
    ],
    "wof:name":"Hambro Assistance",
    "wof:placetype":"venue"
},
  "geometry": {"coordinates":[-1.89897,52.47533],"type":"Point"}
}