{
  "type": "Feature",
  "properties": {
    "iso:country":"GB",
    "sg:address":"36 Thornton Way, Girton",
    "sg:city":"Cambridge",
    "sg:classifiers":[
        {
            "category":"Professional",
            "subcategory":"Engineering",
            "type":"Services"
        }
    ],
    "sg:postcode":"CB3 0NJ",
    "sg:province":"Cambridgeshire",
    "sg:tags":[
        "consulting",
        "engineer"
    ],
    "wof:name":"Land & Water Partnership",
    "wof:placetype":"venue"
},
  "geometry": {"coordinates":[0.0949909985,52.2281341553],"type":"Point"}
}