{
  "type": "Feature",
  "properties": {
    "addr:full":"2 Colliers Cottages, Main Road Farnham Hampshire GU10 4LR",
    "addr:housenumber":"2",
    "addr:postcode":"gu10 4lr",
    "addr:street":"Colliers;Main Road",
    "iso:country":"GB",
    "sg:address":"2 Colliers Cottages, Main Road",
    "sg:city":"Farnham",
    "sg:classifiers":[
        {
            "category":"Home & Garden",
            "subcategory":"Building Materials",
            "type":"Retail Goods"
        }
    ],
    "sg:phone":"+44 1428 727575",
    "sg:postcode":"GU10 4LR",
    "sg:province":"Hampshire",
    "sg:tags":[
        "fencing"
    ],
    "wof:name":"Baldwin Contractors",
    "wof:placetype":"venue"
},
  "geometry": {"coordinates":[-0.8474500179,51.1692390442],"type":"Point"}
}