{
  "type": "Feature",
  "properties": {
    "addr:full":"Court Farm, Trelleck Monmouth Gloucestershire NP25 4PE",
    "addr:postcode":"np25 4pe",
    "addr:street":"Trelleck",
    "iso:country":"GB",
    "sg:address":"Court Farm, Trelleck",
    "sg:city":"Monmouth",
    "sg:classifiers":[
        {
            "category":"Farming",
            "subcategory":"Dairy Farm",
            "type":"Manufacturing & Wholesale Goods"
        }
    ],
    "sg:postcode":"NP25 4PE",
    "sg:province":"Gloucestershire",
    "wof:name":"H Evans & Sons",
    "wof:placetype":"venue"
},
  "geometry": {"coordinates":[-2.719426,51.76656],"type":"Point"}
}