{
  "type": "Feature",
  "properties": {
    "addr:full":"162 High Street, Eston Middlesbrough North Yorkshire TS6 9JA",
    "addr:housenumber":"162",
    "addr:postcode":"ts6 9ja",
    "addr:street":"High Street",
    "iso:country":"GB",
    "sg:address":"162 High Street, Eston",
    "sg:city":"Middlesbrough",
    "sg:classifiers":[
        {
            "category":"Banks & Credit Unions",
            "subcategory":"Financial Services",
            "type":"Services"
        },
        {
            "category":"Shopping",
            "subcategory":"Pawn Shop",
            "type":"Retail Goods"
        },
        {
            "category":"Professional",
            "subcategory":"Business Services",
            "type":"Services"
        }
    ],
    "sg:phone":"+44 1642 465049",
    "sg:postcode":"TS6 9JA",
    "sg:province":"North Yorkshire",
    "sg:tags":[
        "cashing",
        "agent",
        "pawnbroker",
        "export",
        "cheque",
        "import",
        "operation"
    ],
    "wof:name":"John Ramsden",
    "wof:placetype":"venue"
},
  "geometry": {"coordinates":[-1.142891,54.559311],"type":"Point"}
}