{
  "type": "Feature",
  "properties": {
    "iso:country":"GB",
    "sg:address":"26 Pinions Road",
    "sg:city":"High Wycombe",
    "sg:classifiers":[
        {
            "category":"Professional",
            "subcategory":"Art Services",
            "type":"Services"
        }
    ],
    "sg:phone":"+44 1494 526503",
    "sg:postcode":"HP13 7AS",
    "sg:province":"Buckinghamshire",
    "sg:tags":[
        "photographer"
    ],
    "wof:name":"Studio Mcalpin",
    "wof:placetype":"venue"
},
  "geometry": {"coordinates":[-0.727265,51.623158],"type":"Point"}
}