{
  "type": "Feature",
  "properties": {
    "addr:full":"4 Friar St Worcester Worcestershire WR1 2LZ",
    "addr:housenumber":"4",
    "addr:postcode":"wr1 2lz",
    "addr:street":"Friar St",
    "iso:country":"GB",
    "sg:address":"4 Friar St",
    "sg:city":"Worcester",
    "sg:classifiers":[
        {
            "category":"Shopping",
            "subcategory":"Clothing, Apparel, & Fashions",
            "type":"Retail Goods"
        }
    ],
    "sg:phone":"+44 1905 21414",
    "sg:postcode":"WR1 2LZ",
    "sg:province":"Worcestershire",
    "sg:tags":[
        "dresswear"
    ],
    "wof:name":"Designer Agency The",
    "wof:placetype":"venue"
},
  "geometry": {"coordinates":[-2.2190690041,52.190788269],"type":"Point"}
}