{
  "type": "Feature",
  "properties": {
    "addr:full":"Heywood Lane Tenby Pembrokeshire SA70 8BZ",
    "addr:postcode":"sa70 8bz",
    "addr:street":"Heywood Lane",
    "iso:country":"GB",
    "sg:address":"Heywood Lane",
    "sg:city":"Tenby",
    "sg:classifiers":[
        {
            "category":"Education",
            "subcategory":"School",
            "type":"Public Place"
        }
    ],
    "sg:phone":"+44 1834 843248",
    "sg:postcode":"SA70 8BZ",
    "sg:province":"Pembrokeshire",
    "sg:tags":[
        "local",
        "authority"
    ],
    "wof:name":"Tenby County Primary Junior School",
    "wof:placetype":"venue"
},
  "geometry": {"coordinates":[-4.7094497681,51.675365448],"type":"Point"}
}