{
  "type": "Feature",
  "properties": {
    "addr:full":"11 Market Sq Amersham Buckinghamshire HP7 0DF",
    "addr:housenumber":"11",
    "addr:postcode":"hp7 0df",
    "addr:street":"Market Sq",
    "iso:country":"GB",
    "sg:address":"11 Market Sq",
    "sg:city":"Amersham",
    "sg:classifiers":[
        {
            "category":"Restaurant",
            "type":"Food & Drink"
        }
    ],
    "sg:postcode":"HP7 0DF",
    "sg:province":"Buckinghamshire",
    "wof:name":"Number Eleven Bistro",
    "wof:placetype":"venue"
},
  "geometry": {"coordinates":[-0.616338,51.666527],"type":"Point"}
}