{
  "type": "Feature",
  "properties": {
    "addr:full":"13 Anchor Reach, South Woodham Ferrers Chelmsford Essex CM3 5GS",
    "addr:housenumber":"13",
    "addr:postcode":"cm3 5gs",
    "addr:street":"Anchor Reach;Woodham Ferrers Chelmsford",
    "iso:country":"GB",
    "sg:address":"13 Anchor Reach, South Woodham Ferrers",
    "sg:city":"Chelmsford",
    "sg:classifiers":[
        {
            "category":"Bars & Pubs",
            "subcategory":"Sports Bar",
            "type":"Food & Drink"
        },
        {
            "category":"Professional",
            "type":"Services"
        }
    ],
    "sg:postcode":"CM3 5GS",
    "sg:province":"Essex",
    "sg:tags":[
        "reflexology",
        "therapist",
        "reflexologists"
    ],
    "wof:name":"DOREEN RIVETT",
    "wof:placetype":"venue"
},
  "geometry": {"coordinates":[0.618635,51.637211],"type":"Point"}
}