{
  "type": "Feature",
  "properties": {
    "addr:full":"60 Druid Street London Greater London SE1 2EZ",
    "addr:housenumber":"60",
    "addr:postcode":"se1 2ez",
    "addr:street":"Druid Street",
    "iso:country":"GB",
    "sg:address":"60 Druid Street",
    "sg:city":"London",
    "sg:classifiers":[
        {
            "category":"Building & Trades",
            "subcategory":"Construction",
            "type":"Services"
        }
    ],
    "sg:phone":"+44 20 7357 0911",
    "sg:postcode":"SE1 2EZ",
    "sg:province":"Greater London",
    "sg:tags":[
        "joiner",
        "carpenter"
    ],
    "wof:name":"Tower Bridge Joinery",
    "wof:placetype":"venue"
},
  "geometry": {"coordinates":[-0.076359,51.500526],"type":"Point"}
}