{
  "type": "Feature",
  "properties": {
    "iso:country":"GB",
    "sg:address":"Hainault Works, Hainault Road",
    "sg:city":"Romford",
    "sg:classifiers":[
        {
            "category":"Autos & Motor Vehicles",
            "subcategory":"Auto Supplies",
            "type":"Retail Goods"
        }
    ],
    "sg:phone":"+44 20 8599 9928",
    "sg:postcode":"RM6 4XA",
    "sg:province":"Essex",
    "sg:tags":[
        "windscreen"
    ],
    "wof:name":"A P S Windscreens & Sunroofs Ltd.",
    "wof:placetype":"venue"
},
  "geometry": {"coordinates":[0.12167,51.575199],"type":"Point"}
}