{
  "type": "Feature",
  "properties": {
    "addr:full":"Unit 4f, Severnside Trading Estate, St Andrews Road Bristol City of Bristol BS11 9YQ",
    "addr:housenumber":"unit 4f severnside trading estate",
    "addr:postcode":"road;bs11 9yq",
    "addr:street":"St Andrews",
    "iso:country":"GB",
    "sg:address":"Unit 4f, Severnside Trading Estate, St Andrews Road",
    "sg:city":"Bristol",
    "sg:classifiers":[
        {
            "category":"Retail",
            "subcategory":"Auto Repair",
            "type":"Services"
        }
    ],
    "sg:phone":"+44 117 982 0626",
    "sg:postcode":"BS11 9YQ",
    "sg:province":"City of Bristol",
    "sg:tags":[
        "modification",
        "garage"
    ],
    "wof:name":"Severn Servicing Garages",
    "wof:placetype":"venue"
},
  "geometry": {"coordinates":[-2.591429,51.453667],"type":"Point"}
}