{
  "type": "Feature",
  "properties": {
    "addr:full":"121 Plymouth Rd Buckfastleigh Devon TQ11 0DA",
    "addr:housenumber":"121",
    "addr:postcode":"tq11 0da",
    "addr:street":"Plymouth Rd",
    "iso:country":"GB",
    "sg:address":"121 Plymouth Rd",
    "sg:city":"Buckfastleigh",
    "sg:classifiers":[
        {
            "category":"Building & Trades",
            "subcategory":"Cleaning & Sanitation",
            "type":"Services"
        }
    ],
    "sg:phone":"+44 1364 643020",
    "sg:postcode":"TQ11 0DA",
    "sg:province":"Devon",
    "sg:tags":[
        "sweep",
        "chimney"
    ],
    "wof:name":"Malcolm Wood",
    "wof:placetype":"venue"
},
  "geometry": {"coordinates":[-3.7785410881,50.4811325073],"type":"Point"}
}