{
  "type": "Feature",
  "properties": {
    "addr:full":"37 Canal Street Stockport Cheshire SK1 3BZ",
    "addr:housenumber":"37",
    "addr:postcode":"sk1 3bz",
    "addr:street":"Canal Street",
    "iso:country":"GB",
    "sg:address":"37 Canal Street",
    "sg:city":"Stockport",
    "sg:classifiers":[
        {
            "category":"Building & Trades",
            "subcategory":"Construction",
            "type":"Services"
        }
    ],
    "sg:phone":"+44 161 477 7034",
    "sg:postcode":"SK1 3BZ",
    "sg:province":"Cheshire",
    "sg:tags":[
        "glazier"
    ],
    "wof:name":"Nationwide Glass Co.",
    "wof:placetype":"venue"
},
  "geometry": {"coordinates":[-2.1521420479,53.4055747986],"type":"Point"}
}