{
  "type": "Feature",
  "properties": {
    "iso:country":"GB",
    "sg:address":"61-63 Church Street, Caversham",
    "sg:city":"Reading",
    "sg:classifiers":[
        {
            "category":"Building & Trades",
            "subcategory":"Construction",
            "type":"Services"
        }
    ],
    "sg:phone":"+44 118 946 4100",
    "sg:postcode":"RG4 8AX",
    "sg:province":"Berkshire",
    "sg:tags":[
        "specialised",
        "builder",
        "contractor"
    ],
    "wof:name":"MAINPROJECTS LTD",
    "wof:placetype":"venue"
},
  "geometry": {"coordinates":[-0.973444,51.467369],"type":"Point"}
}