{
  "type": "Feature",
  "properties": {
    "iso:country":"GB",
    "sg:address":"44 Grove End Rd",
    "sg:city":"London",
    "sg:classifiers":[
        {
            "category":"Real Estate",
            "subcategory":"Developer",
            "type":"Services"
        }
    ],
    "sg:postcode":"NW8 9NE",
    "sg:province":"Greater London",
    "sg:tags":[
        "property"
    ],
    "wof:name":"Bleier Property Co Ltd",
    "wof:placetype":"venue"
},
  "geometry": {"coordinates":[-0.175771,51.533829],"type":"Point"}
}