{
  "type": "Feature",
  "properties": {
    "addr:full":"Aikshaw House, Aikshaw, Silloth Wigton Cumbria CA7 4NF",
    "addr:postcode":"ca7 4nf",
    "iso:country":"GB",
    "sg:address":"Aikshaw House, Aikshaw, Silloth",
    "sg:city":"Wigton",
    "sg:classifiers":[
        {
            "category":"Home & Garden",
            "subcategory":"Garden Supply",
            "type":"Retail Goods"
        },
        {
            "category":"Farming",
            "subcategory":"Livestock Farm",
            "type":"Manufacturing & Wholesale Goods"
        }
    ],
    "sg:postcode":"CA7 4NF",
    "sg:province":"Cumbria",
    "sg:tags":[
        "bulb",
        "grower",
        "others"
    ],
    "wof:name":"P Brown",
    "wof:placetype":"venue"
},
  "geometry": {"coordinates":[-3.3869590759,54.8679962158],"type":"Point"}
}