{
  "type": "Feature",
  "properties": {
    "addr:full":"Unit 5 Meltex House, Kepler Tamworth Staffordshire B79 7XE",
    "addr:housenumber":"unit 5 meltex house kepler",
    "addr:postcode":"b79 7xe",
    "iso:country":"GB",
    "sg:address":"Unit 5 Meltex House, Kepler",
    "sg:city":"Tamworth",
    "sg:classifiers":[
        {
            "category":"Professional",
            "subcategory":"Engineering",
            "type":"Services"
        }
    ],
    "sg:phone":"+44 1827 311000",
    "sg:postcode":"B79 7XE",
    "sg:province":"Staffordshire",
    "sg:tags":[
        "engineer",
        "mechanical"
    ],
    "wof:name":"Mitie Engineering Services (Midlands) Ltd.",
    "wof:placetype":"venue"
},
  "geometry": {"coordinates":[-1.717633,52.644882],"type":"Point"}
}