{
  "type": "Feature",
  "properties": {
    "addr:full":"43 Green Lane Ilford Essex IG1 1XG",
    "addr:housenumber":"43",
    "addr:postcode":"ig1 1xg",
    "addr:street":"Green Lane",
    "iso:country":"GB",
    "sg:address":"43 Green Lane",
    "sg:city":"Ilford",
    "sg:classifiers":[
        {
            "category":"Home & Garden",
            "subcategory":"Household Appliances",
            "type":"Retail Goods"
        }
    ],
    "sg:phone":"+44 20 8553 0954",
    "sg:postcode":"IG1 1XG",
    "sg:province":"Essex",
    "sg:tags":[
        "electrical",
        "domestic"
    ],
    "wof:name":"D H Wings Electronics",
    "wof:placetype":"venue"
},
  "geometry": {"coordinates":[0.084824,51.558861],"type":"Point"}
}