{
  "type": "Feature",
  "properties": {
    "iso:country":"GB",
    "sg:address":"334-336 South Coast Rd",
    "sg:city":"Peacehaven",
    "sg:classifiers":[
        {
            "category":"Autos & Motor Vehicles",
            "subcategory":"Fuel & Gas Station",
            "type":"Retail Goods"
        }
    ],
    "sg:phone":"+44 1273 579900",
    "sg:postcode":"BN10 7EN",
    "sg:province":"East Sussex",
    "sg:tags":[
        "petrol",
        "filling"
    ],
    "wof:name":"Total Convenience Stores",
    "wof:placetype":"venue"
},
  "geometry": {"coordinates":[-0.012549,50.793652],"type":"Point"}
}