{
  "type": "Feature",
  "properties": {
    "addr:full":"The Aucklands, Broad Lane, Sykehouse Goole East Riding of Yorkshire DN14 9AX",
    "addr:postcode":"dn14 9ax",
    "addr:street":"Lane",
    "iso:country":"GB",
    "sg:address":"The Aucklands, Broad Lane, Sykehouse",
    "sg:city":"Goole",
    "sg:classifiers":[
        {
            "category":"Freight",
            "type":"Transportation"
        }
    ],
    "sg:phone":"+44 1405 785639",
    "sg:postcode":"DN14 9AX",
    "sg:province":"East Riding of Yorkshire",
    "sg:tags":[
        "haulage",
        "road"
    ],
    "wof:name":"Roy Gilson Haulage Ltd.",
    "wof:placetype":"venue"
},
  "geometry": {"coordinates":[-1.0473680496,53.6459197998],"type":"Point"}
}