{
  "type": "Feature",
  "properties": {
    "iso:country":"GB",
    "sg:address":"The Square, Cartmel",
    "sg:city":"Grange-over-sands",
    "sg:classifiers":[
        {
            "category":"Shopping",
            "subcategory":"Gifts & Souvenirs",
            "type":"Retail Goods"
        }
    ],
    "sg:phone":"+44 15395 36553",
    "sg:postcode":"LA11 6QB",
    "sg:province":"Cumbria",
    "sg:tags":[
        "shop"
    ],
    "wof:name":"Tarragon Giftware Ltd.",
    "wof:placetype":"venue"
},
  "geometry": {"coordinates":[-2.9538021088,54.2009429932],"type":"Point"}
}