{
  "type": "Feature",
  "properties": {
    "addr:full":"140 Cromwell Road London Greater London SW7 4HA",
    "addr:housenumber":"140",
    "addr:postcode":"sw7 4ha",
    "addr:street":"Cromwell Road",
    "iso:country":"GB",
    "sg:address":"140 Cromwell Road",
    "sg:city":"London",
    "sg:classifiers":[
        {
            "category":"Building & Trades",
            "subcategory":"Construction",
            "type":"Services"
        }
    ],
    "sg:phone":"+44 20 7835 0021",
    "sg:postcode":"SW7 4HA",
    "sg:province":"Greater London",
    "sg:tags":[
        "builder"
    ],
    "wof:name":"D M G Ltd.",
    "wof:placetype":"venue"
},
  "geometry": {"coordinates":[-0.187594,51.494797],"type":"Point"}
}