{
  "type": "Feature",
  "properties": {
    "addr:full":"112 Myddleton Road London Greater London N22 8NQ",
    "addr:housenumber":"112",
    "addr:postcode":"n22 8nq",
    "addr:street":"Myddleton Road",
    "iso:country":"GB",
    "sg:address":"112 Myddleton Road",
    "sg:city":"London",
    "sg:classifiers":[
        {
            "category":"Retail",
            "subcategory":"Repair Shop",
            "type":"Services"
        }
    ],
    "sg:phone":"+44 20 8889 6699",
    "sg:postcode":"N22 8NQ",
    "sg:province":"Greater London",
    "sg:tags":[
        "television",
        "good",
        "video",
        "servicing",
        "maintenance",
        "radio"
    ],
    "wof:name":"S & K Mistry",
    "wof:placetype":"venue"
},
  "geometry": {"coordinates":[-0.1185780019,51.6065979004],"type":"Point"}
}