{
  "type": "Feature",
  "properties": {
    "addr:full":"Appleyards Ho, 72 Brighton Rd Horsham West Sussex RH13 5BU",
    "addr:housenumber":"72",
    "addr:postcode":"rh13 5bu",
    "addr:street":"Brighton Rd",
    "iso:country":"GB",
    "sg:address":"Appleyards Ho, 72 Brighton Rd",
    "sg:city":"Horsham",
    "sg:classifiers":[
        {
            "category":"Real Estate",
            "subcategory":"Surveying",
            "type":"Services"
        }
    ],
    "sg:phone":"+44 870 527 5201",
    "sg:postcode":"RH13 5BU",
    "sg:province":"West Sussex",
    "sg:tags":[
        "surveyor",
        "valuer"
    ],
    "wof:name":"Appleyards",
    "wof:placetype":"venue"
},
  "geometry": {"coordinates":[-0.3165200055,51.0587997437],"type":"Point"}
}