{
  "type": "Feature",
  "properties": {
    "iso:country":"GB",
    "sg:address":"Beckney Lodge, Lower Road",
    "sg:city":"Hockley",
    "sg:classifiers":[
        {
            "category":"Autos & Motor Vehicles",
            "subcategory":"Motorcycle Sales",
            "type":"Retail Goods"
        }
    ],
    "sg:phone":"+44 1702 200664",
    "sg:postcode":"SS5 5LD",
    "sg:province":"Essex",
    "sg:tags":[
        "chauffeur",
        "driven",
        "car"
    ],
    "wof:name":"Elegance Limousines",
    "wof:placetype":"venue"
},
  "geometry": {"coordinates":[0.666821003,51.6066627502],"type":"Point"}
}