{
  "type": "Feature",
  "properties": {
    "addr:full":"5 The  Cent Crescent Taunton Somerset TA1 4EA",
    "addr:housenumber":"5",
    "addr:postcode":"ta1 4ea",
    "addr:street":"The Cent Crescent",
    "iso:country":"GB",
    "sg:address":"5 The  Cent Crescent",
    "sg:city":"Taunton",
    "sg:classifiers":[
        {
            "category":"Building & Trades",
            "subcategory":"Construction",
            "type":"Services"
        }
    ],
    "sg:phone":"+44 1823 327785",
    "sg:postcode":"TA1 4EA",
    "sg:province":"Somerset",
    "sg:tags":[
        "decorator",
        "painter"
    ],
    "wof:name":"Dil Roworth",
    "wof:placetype":"venue"
},
  "geometry": {"coordinates":[-3.105737,51.013386],"type":"Point"}
}