{
  "type": "Feature",
  "properties": {
    "iso:country":"GB",
    "sg:address":"14 St Bartholomew Close",
    "sg:city":"Colchester",
    "sg:classifiers":[
        {
            "category":"Professional",
            "subcategory":"Art Services",
            "type":"Services"
        },
        {
            "category":"Building & Trades",
            "subcategory":"Construction",
            "type":"Services"
        },
        {
            "category":"Manufacturing",
            "subcategory":"Paper Products",
            "type":"Manufacturing & Wholesale Goods"
        }
    ],
    "sg:phone":"+44 1206 842199",
    "sg:postcode":"CO4 0LT",
    "sg:province":"Essex",
    "sg:tags":[
        "cardboard",
        "decorator",
        "painter"
    ],
    "wof:name":"B C F Dunt",
    "wof:placetype":"venue"
},
  "geometry": {"coordinates":[0.926775,51.906013],"type":"Point"}
}