{
  "type": "Feature",
  "properties": {
    "addr:full":"637 Tower Bridge Business Complex, 100 Clements Road London Greater London SE16 4DG",
    "addr:housenumber":"637;100",
    "addr:postcode":"se16 4dg",
    "addr:street":"Tower Bridge;Clements Road",
    "iso:country":"GB",
    "sg:address":"637 Tower Bridge Business Complex, 100 Clements Road",
    "sg:city":"London",
    "sg:classifiers":[
        {
            "category":"Shopping",
            "subcategory":"Computers & Home Electronics",
            "type":"Retail Goods"
        }
    ],
    "sg:phone":"+44 20 7231 9482",
    "sg:postcode":"SE16 4DG",
    "sg:province":"Greater London",
    "sg:tags":[
        "sound",
        "equipment",
        "system"
    ],
    "wof:name":"The Mainline Sound Co.",
    "wof:placetype":"venue"
},
  "geometry": {"coordinates":[-0.0634400025,51.495098114],"type":"Point"}
}