{
  "type": "Feature",
  "properties": {
    "addr:full":"5 Post Office Walk, Fore Street Hertford Hertfordshire SG14 1DL",
    "addr:housenumber":"5",
    "addr:postcode":"sg14 1dl",
    "addr:street":"Post Office Walk Fore Street",
    "iso:country":"GB",
    "sg:address":"5 Post Office Walk, Fore Street",
    "sg:city":"Hertford",
    "sg:classifiers":[
        {
            "category":"Shopping",
            "subcategory":"Musical Instruments",
            "type":"Retail Goods"
        }
    ],
    "sg:phone":"+44 1992 500976",
    "sg:postcode":"SG14 1DL",
    "sg:province":"Hertfordshire",
    "sg:tags":[
        "music",
        "sheet"
    ],
    "wof:name":"Hertford Music Guitar Centre",
    "wof:placetype":"venue"
},
  "geometry": {"coordinates":[-0.0826990008,51.7963409424],"type":"Point"}
}