{
  "type": "Feature",
  "properties": {
    "addr:full":"2 Gifford Road, Lighthorne Heath Leamington Spa Warwickshire CV33 9TT",
    "addr:housenumber":"2",
    "addr:postcode":"cv33 9tt",
    "addr:street":"Gifford Road",
    "iso:country":"GB",
    "sg:address":"2 Gifford Road, Lighthorne Heath",
    "sg:city":"Leamington Spa",
    "sg:classifiers":[
        {
            "category":"Arts & Performance",
            "subcategory":"Music",
            "type":"Entertainment"
        }
    ],
    "sg:postcode":"CV33 9TT",
    "sg:province":"Warwickshire",
    "sg:tags":[
        "mobile",
        "disco"
    ],
    "wof:name":"Flexitec Ltd.",
    "wof:placetype":"venue"
},
  "geometry": {"coordinates":[-1.486742,52.201099],"type":"Point"}
}