{
  "type": "Feature",
  "properties": {
    "iso:country":"GB",
    "sg:address":"21 Hawkshead Avenue",
    "sg:city":"Liverpool",
    "sg:classifiers":[
        {
            "category":"Building & Trades",
            "subcategory":"Construction",
            "type":"Services"
        }
    ],
    "sg:postcode":"L12 0HS",
    "sg:province":"Merseyside",
    "sg:tags":[
        "decorator",
        "painter"
    ],
    "wof:name":"A Tunstall",
    "wof:placetype":"venue"
},
  "geometry": {"coordinates":[-2.900666,53.442799],"type":"Point"}
}