{
  "type": "Feature",
  "properties": {
    "addr:full":"Estate Office, Bonar Bridge Ardgay Highland IV24 3EA",
    "addr:postcode":"iv24 3ea",
    "addr:street":"Ardgay",
    "iso:country":"GB",
    "sg:address":"Estate Office, Bonar Bridge",
    "sg:city":"Ardgay",
    "sg:classifiers":[
        {
            "category":"Real Estate",
            "subcategory":"Surveying",
            "type":"Services"
        }
    ],
    "sg:phone":"+44 1863 766683",
    "sg:postcode":"IV24 3EA",
    "sg:province":"Highland",
    "sg:tags":[
        "surveyor",
        "valuer"
    ],
    "wof:name":"Bell-Ingram",
    "wof:placetype":"venue"
},
  "geometry": {"coordinates":[-4.363122,57.881462],"type":"Point"}
}