{
  "type": "Feature",
  "properties": {
    "addr:full":"28 Commercial St Whitechapel Greater London E1 6LS",
    "addr:housenumber":"28",
    "addr:postcode":"e1 6ls",
    "addr:street":"Commercial St",
    "iso:country":"GB",
    "sg:address":"28 Commercial St",
    "sg:city":"Whitechapel",
    "sg:classifiers":[
        {
            "category":"Organizations",
            "subcategory":"Non-profit Organization",
            "type":"Services"
        }
    ],
    "sg:phone":"+44 20 7247 3146",
    "sg:postcode":"E1 6LS",
    "sg:province":"Greater London",
    "sg:tags":[
        "organisation",
        "voluntary",
        "charity"
    ],
    "wof:name":"Student Assembly Against Racism",
    "wof:placetype":"venue"
},
  "geometry": {"coordinates":[-0.0725890025,51.516456604],"type":"Point"}
}