{
  "type": "Feature",
  "properties": {
    "iso:country":"GB",
    "sg:address":"84 High Street",
    "sg:city":"Sutton",
    "sg:classifiers":[
        {
            "category":"Health Services",
            "subcategory":"Health Practitioner",
            "type":"Services"
        }
    ],
    "sg:postcode":"SM1 1EX",
    "sg:province":"Surrey",
    "sg:tags":[
        "hypnotherapists"
    ],
    "wof:name":"Hypnotherapy Centre Sutton",
    "wof:placetype":"venue"
},
  "geometry": {"coordinates":[-0.192355,51.362106],"type":"Point"}
}