{
  "type": "Feature",
  "properties": {
    "iso:country":"GB",
    "sg:address":"6 Durham Road, Birtley",
    "sg:city":"Chester-le-street",
    "sg:classifiers":[
        {
            "category":"Banks & Credit Unions",
            "subcategory":"Financial Services",
            "type":"Services"
        }
    ],
    "sg:phone":"+44 191 416 3777",
    "sg:postcode":"DH3 2QG",
    "sg:province":"Durham",
    "sg:tags":[
        "consultant"
    ],
    "wof:name":"Ken Jobling Financial Services",
    "wof:placetype":"venue"
},
  "geometry": {"coordinates":[-1.573183,54.880329],"type":"Point"}
}