{
  "type": "Feature",
  "properties": {
    "addr:full":"43 Hamilton Street Birkenhead Merseyside L41 5AA",
    "addr:housenumber":"43",
    "addr:postcode":"l41 5aa",
    "addr:street":"Hamilton Street",
    "iso:country":"GB",
    "sg:address":"43 Hamilton Street",
    "sg:city":"Birkenhead",
    "sg:classifiers":[
        {
            "category":"Government",
            "subcategory":"Office",
            "type":"Public Place"
        }
    ],
    "sg:phone":"+44 151 666 5023",
    "sg:postcode":"L41 5AA",
    "sg:province":"Merseyside",
    "sg:tags":[
        "local"
    ],
    "wof:name":"Hamilton Quarter",
    "wof:placetype":"venue"
},
  "geometry": {"coordinates":[-3.016375,53.392887],"type":"Point"}
}