{
  "type": "Feature",
  "properties": {
    "addr:full":"Cumberland Road Middlesbrough North Yorkshire TS5 6JB",
    "addr:postcode":"ts5 6jb",
    "addr:street":"Cumberland Road",
    "iso:country":"GB",
    "sg:address":"Cumberland Road",
    "sg:city":"Middlesbrough",
    "sg:classifiers":[
        {
            "category":"Organizations",
            "subcategory":"Community Association",
            "type":"Services"
        },
        {
            "category":"Organizations",
            "subcategory":"Membership Organization",
            "type":"Services"
        }
    ],
    "sg:phone":"+44 1642 817301",
    "sg:postcode":"TS5 6JB",
    "sg:province":"North Yorkshire",
    "sg:tags":[
        "club",
        "social"
    ],
    "wof:name":"Erimus Quoit & Rifle Club",
    "wof:placetype":"venue"
},
  "geometry": {"coordinates":[-1.23113,54.562286],"type":"Point"}
}