{
  "type": "Feature",
  "properties": {
    "addr:full":"41 Lafone Street London Greater London SE1 2LX",
    "addr:housenumber":"41",
    "addr:postcode":"se1 2lx",
    "addr:street":"Lafone Street",
    "iso:country":"GB",
    "sg:address":"41 Lafone Street",
    "sg:city":"London",
    "sg:classifiers":[
        {
            "category":"Food & Beverages",
            "subcategory":"Bakery",
            "type":"Retail Goods"
        },
        {
            "category":"Professional",
            "subcategory":"Business Services",
            "type":"Services"
        }
    ],
    "sg:phone":"+44 20 7378 7373",
    "sg:postcode":"SE1 2LX",
    "sg:province":"Greater London",
    "sg:tags":[
        "import",
        "export",
        "agent",
        "pizza"
    ],
    "wof:name":"Chain Investments (U K) Ltd.",
    "wof:placetype":"venue"
},
  "geometry": {"coordinates":[-0.0759759992,51.5020332336],"type":"Point"}
}