{
  "type": "Feature",
  "properties": {
    "addr:full":"York Road Totland Bay Isle of Wight PO39 0HB",
    "addr:postcode":"po39 0hb",
    "addr:street":"York Road",
    "iso:country":"GB",
    "sg:address":"York Road",
    "sg:city":"Totland Bay",
    "sg:classifiers":[
        {
            "category":"Retail",
            "subcategory":"Repair Shop",
            "type":"Services"
        },
        {
            "category":"Building & Trades",
            "subcategory":"Construction",
            "type":"Services"
        }
    ],
    "sg:phone":"+44 1983 752187",
    "sg:postcode":"PO39 0HB",
    "sg:province":"Isle of Wight",
    "sg:tags":[
        "builder",
        "maintenance"
    ],
    "wof:name":"William Downer & Sons Iw Ltd",
    "wof:placetype":"venue"
},
  "geometry": {"coordinates":[-1.5465209484,50.6787872314],"type":"Point"}
}