{
  "type": "Feature",
  "properties": {
    "addr:full":"160 Julian Road Nottingham Nottinghamshire NG2 5AN",
    "addr:housenumber":"160",
    "addr:postcode":"ng2 5an",
    "addr:street":"Julian Road",
    "iso:country":"GB",
    "sg:address":"160 Julian Road",
    "sg:city":"Nottingham",
    "sg:classifiers":[
        {
            "category":"Building & Trades",
            "subcategory":"Plumbing",
            "type":"Services"
        }
    ],
    "sg:phone":"+44 115 982 2445",
    "sg:postcode":"NG2 5AN",
    "sg:province":"Nottinghamshire",
    "sg:tags":[
        "heating"
    ],
    "wof:name":"T W Roe",
    "wof:placetype":"venue"
},
  "geometry": {"coordinates":[-1.115944,52.934387],"type":"Point"}
}