{
  "type": "Feature",
  "properties": {
    "addr:full":"Cokeland Place Cradley Heath West Midlands B64 6AN",
    "addr:postcode":"b64 6an",
    "addr:street":"Cokeland Place",
    "iso:country":"GB",
    "sg:address":"Cokeland Place",
    "sg:city":"Cradley Heath",
    "sg:classifiers":[
        {
            "category":"Professional",
            "subcategory":"Printing & Photocopies",
            "type":"Services"
        }
    ],
    "sg:phone":"+44 1384 569934",
    "sg:postcode":"B64 6AN",
    "sg:province":"West Midlands",
    "sg:tags":[
        "printer"
    ],
    "sg:website":"http://www.service1.co.uk",
    "wof:name":"Service Business Forms Ltd.",
    "wof:placetype":"venue"
},
  "geometry": {"coordinates":[-2.0794389248,52.4707107544],"type":"Point"}
}