{
  "type": "Feature",
  "properties": {
    "addr:full":"Unit 8 Forbes Building, 311-321 Linthorpe Road Middlesbrough North Yorkshire TS1 4AW",
    "addr:housenumber":"unit 8;311-321",
    "addr:postcode":"ts1 4aw",
    "addr:street":"Linthorpe Road",
    "iso:country":"GB",
    "sg:address":"Unit 8 Forbes Building, 311-321 Linthorpe Road",
    "sg:city":"Middlesbrough",
    "sg:classifiers":[
        {
            "category":"Shopping",
            "subcategory":"Hobbies, Toys, & Games",
            "type":"Retail Goods"
        }
    ],
    "sg:phone":"+44 1642 213313",
    "sg:postcode":"TS1 4AW",
    "sg:province":"North Yorkshire",
    "sg:tags":[
        "computer"
    ],
    "wof:name":"Games World",
    "wof:placetype":"venue"
},
  "geometry": {"coordinates":[-1.236569,54.572971],"type":"Point"}
}