{
  "type": "Feature",
  "properties": {
    "addr:full":"Smithfield Street, Amesbury Salisbury Hampshire SP4 7AL",
    "addr:postcode":"sp4 7al",
    "addr:street":"Smithfield Street",
    "iso:country":"GB",
    "sg:address":"Smithfield Street, Amesbury",
    "sg:city":"Salisbury",
    "sg:classifiers":[
        {
            "category":"Health Services",
            "subcategory":"Podiatrist",
            "type":"Services"
        }
    ],
    "sg:phone":"+44 1980 625313",
    "sg:postcode":"SP4 7AL",
    "sg:province":"Hampshire",
    "sg:tags":[
        "podiatrists",
        "chiropodist"
    ],
    "wof:name":"Amesbury Family Planning Clinic",
    "wof:placetype":"venue"
},
  "geometry": {"coordinates":[-1.778529,51.171726],"type":"Point"}
}