{
  "type": "Feature",
  "properties": {
    "addr:full":"Wentwood Rark, London Road Colchester Essex CO6 4BS",
    "addr:postcode":"co6 4bs",
    "addr:street":"London Road Colchester",
    "iso:country":"GB",
    "sg:address":"Wentwood Rark, London Road",
    "sg:city":"Colchester",
    "sg:classifiers":[
        {
            "category":"Shopping",
            "subcategory":"Computers & Home Electronics",
            "type":"Retail Goods"
        }
    ],
    "sg:phone":"+44 1206 274020",
    "sg:postcode":"CO6 4BS",
    "sg:province":"Essex",
    "sg:tags":[
        "equipment",
        "video",
        "cctv"
    ],
    "wof:name":"Image Surveillance Systems",
    "wof:placetype":"venue"
},
  "geometry": {"coordinates":[0.8559299707,51.9347496033],"type":"Point"}
}