{
  "type": "Feature",
  "properties": {
    "addr:full":"18 Hill St Saffron Walden Cambridgeshire CB10 1JD",
    "addr:housenumber":"18",
    "addr:postcode":"cb10 1jd",
    "addr:street":"Hill St",
    "iso:country":"GB",
    "sg:address":"18 Hill St",
    "sg:city":"Saffron Walden",
    "sg:classifiers":[
        {
            "category":"Shopping",
            "type":"Retail Goods"
        }
    ],
    "sg:phone":"+44 1799 524913",
    "sg:postcode":"CB10 1JD",
    "sg:province":"Cambridgeshire",
    "sg:tags":[
        "med",
        "scientific",
        "apparatus"
    ],
    "wof:name":"Topometrix Corporation",
    "wof:placetype":"venue"
},
  "geometry": {"coordinates":[0.2424779981,52.0233535767],"type":"Point"}
}