{
  "type": "Feature",
  "properties": {
    "iso:country":"GB",
    "sg:address":"29 St Johns Road",
    "sg:city":"Isleworth",
    "sg:classifiers":[
        {
            "category":"Bars & Pubs",
            "type":"Food & Drink"
        },
        {
            "category":"Community Center",
            "subcategory":"Social",
            "type":"Public Place"
        }
    ],
    "sg:phone":"+44 20 8560 1468",
    "sg:postcode":"TW7 6NY",
    "sg:province":"Greater London",
    "sg:tags":[
        "pubs",
        "house",
        "inn",
        "activity"
    ],
    "wof:name":"The Woodlands Tavern",
    "wof:placetype":"venue"
},
  "geometry": {"coordinates":[-0.3375990093,51.4731407166],"type":"Point"}
}