{
  "type": "Feature",
  "properties": {
    "addr:full":"Lower Berrow Farm, Trickses Lane, Ham Grn Redditch Warwickshire B97 5TT",
    "addr:postcode":"b97 5tt",
    "addr:street":"Lower Berrow;Trickses Lane Ham Grn",
    "iso:country":"GB",
    "sg:address":"Lower Berrow Farm, Trickses Lane, Ham Grn",
    "sg:city":"Redditch",
    "sg:classifiers":[
        {
            "category":"Farming",
            "subcategory":"Livestock Farm",
            "type":"Manufacturing & Wholesale Goods"
        }
    ],
    "sg:postcode":"B97 5TT",
    "sg:province":"Warwickshire",
    "sg:tags":[
        "others"
    ],
    "wof:name":"G A Lewis & Co",
    "wof:placetype":"venue"
},
  "geometry": {"coordinates":[-1.9412670135,52.30727005],"type":"Point"}
}