{
  "type": "Feature",
  "properties": {
    "iso:country":"GB",
    "sg:address":"6 Devonia Close",
    "sg:city":"Plymouth",
    "sg:classifiers":[
        {
            "category":"Social Services",
            "subcategory":"Job Training",
            "type":"Services"
        }
    ],
    "sg:postcode":"PL7 4DS",
    "sg:province":"Devon",
    "sg:tags":[
        "draughtsman",
        "drawing"
    ],
    "wof:name":"3D Design",
    "wof:placetype":"venue"
},
  "geometry": {"coordinates":[-4.053755,50.398575],"type":"Point"}
}