{
  "type": "Feature",
  "properties": {
    "iso:country":"GB",
    "sg:address":"Nunsthorpe & Bradley Park Resour, Ce Centr Second A",
    "sg:city":"Grimsby",
    "sg:classifiers":[
        {
            "category":"Professional",
            "subcategory":"Lawyer & Legal Services",
            "type":"Services"
        }
    ],
    "sg:phone":"+44 1472 322111",
    "sg:postcode":"DN33 1NU",
    "sg:province":"Lincolnshire",
    "sg:tags":[
        "advice",
        "counselling"
    ],
    "wof:name":"Scunthorpe & Grimsby Rape Crisis",
    "wof:placetype":"venue"
},
  "geometry": {"coordinates":[-0.0984,53.547119],"type":"Point"}
}