{
  "type": "Feature",
  "properties": {
    "addr:full":"72 Shoreditch High St London Greater London E1 6JJ",
    "addr:housenumber":"72",
    "addr:postcode":"e1 6jj",
    "addr:street":"Shoreditch High St",
    "iso:country":"GB",
    "sg:address":"72 Shoreditch High St",
    "sg:city":"London",
    "sg:classifiers":[
        {
            "category":"Bars & Pubs",
            "type":"Food & Drink"
        }
    ],
    "sg:postcode":"E1 6JJ",
    "sg:province":"Greater London",
    "sg:tags":[
        "pubs",
        "inn"
    ],
    "wof:name":"Thomas,Mervyn,",
    "wof:placetype":"venue"
},
  "geometry": {"coordinates":[-0.077045,51.524799],"type":"Point"}
}