{
  "type": "Feature",
  "properties": {
    "iso:country":"GB",
    "sg:address":"10 Varcoe Rd",
    "sg:city":"London",
    "sg:classifiers":[
        {
            "category":"Home & Garden",
            "subcategory":"Building Materials",
            "type":"Retail Goods"
        }
    ],
    "sg:postcode":"SE16 3DG",
    "sg:province":"Greater London",
    "sg:tags":[
        "furnishers",
        "bathroom",
        "planner"
    ],
    "wof:name":"Silver Crest Plastics Ltd",
    "wof:placetype":"venue"
},
  "geometry": {"coordinates":[-0.057491,51.485195],"type":"Point"}
}