{
  "type": "Feature",
  "properties": {
    "addr:full":"19a Collingwood Road Witham Essex CM8 2DY",
    "addr:housenumber":"19a",
    "addr:postcode":"cm8 2dy",
    "addr:street":"Collingwood Road",
    "iso:country":"GB",
    "sg:address":"19a Collingwood Road",
    "sg:city":"Witham",
    "sg:classifiers":[
        {
            "category":"Shopping",
            "subcategory":"Pharmacy",
            "type":"Retail Goods"
        }
    ],
    "sg:phone":"+44 1376 502762",
    "sg:postcode":"CM8 2DY",
    "sg:province":"Essex",
    "sg:tags":[
        "medicine",
        "therapy"
    ],
    "wof:name":"Association of Natural Medicines Ltd.",
    "wof:placetype":"venue"
},
  "geometry": {"coordinates":[0.6386290193,51.8015289307],"type":"Point"}
}