{
  "type": "Feature",
  "properties": {
    "addr:full":"121 Causewayend Aberdeen Aberdeen City AB25 3TP",
    "addr:housenumber":"121",
    "addr:postcode":"ab25 3tp",
    "addr:street":"Causewayend Aberdeen",
    "iso:country":"GB",
    "sg:address":"121 Causewayend",
    "sg:city":"Aberdeen",
    "sg:classifiers":[
        {
            "category":"Retail",
            "subcategory":"Auto Rental",
            "type":"Services"
        }
    ],
    "sg:phone":"+44 1224 631199",
    "sg:postcode":"AB25 3TP",
    "sg:province":"Aberdeen City",
    "sg:tags":[
        "car"
    ],
    "wof:name":"Europcar Interrent",
    "wof:placetype":"venue"
},
  "geometry": {"coordinates":[-2.103839,57.155407],"type":"Point"}
}