{
  "type": "Feature",
  "properties": {
    "addr:full":"6 Moor Oaks Road Sheffield South Yorkshire S10 1BX",
    "addr:housenumber":"6",
    "addr:postcode":"s10 1bx",
    "addr:street":"Moor Oaks Road",
    "iso:country":"GB",
    "sg:address":"6 Moor Oaks Road",
    "sg:city":"Sheffield",
    "sg:classifiers":[
        {
            "category":"Professional",
            "subcategory":"Accounting & Tax Preparation",
            "type":"Services"
        }
    ],
    "sg:phone":"+44 114 268 0357",
    "sg:postcode":"S10 1BX",
    "sg:province":"South Yorkshire",
    "sg:tags":[
        "accountant"
    ],
    "wof:name":"Robert M Grierson & Co",
    "wof:placetype":"venue"
},
  "geometry": {"coordinates":[-1.498081,53.379452],"type":"Point"}
}