{
  "type": "Feature",
  "properties": {
    "iso:country":"GB",
    "sg:address":"834 Ecclesall Road",
    "sg:city":"Sheffield",
    "sg:classifiers":[
        {
            "category":"Fast Food",
            "type":"Food & Drink"
        }
    ],
    "sg:postcode":"S11 8TD",
    "sg:province":"Derbyshire",
    "sg:tags":[
        "away",
        "take"
    ],
    "wof:name":"K Kong",
    "wof:placetype":"venue"
},
  "geometry": {"coordinates":[-1.5076980591,53.3647766113],"type":"Point"}
}