{
  "type": "Feature",
  "properties": {
    "addr:full":"Malvern House, 41 Mapperley Road, Mapperley Nottingham Nottinghamshire NG3 5AQ",
    "addr:housenumber":"41",
    "addr:postcode":"ng3 5aq",
    "addr:street":"Mapperley Road",
    "iso:country":"GB",
    "sg:address":"Malvern House, 41 Mapperley Road, Mapperley",
    "sg:city":"Nottingham",
    "sg:classifiers":[
        {
            "category":"Health Services",
            "subcategory":"Doctor",
            "type":"Services"
        }
    ],
    "sg:phone":"+44 115 962 3559",
    "sg:postcode":"NG3 5AQ",
    "sg:province":"Nottinghamshire",
    "sg:tags":[
        "practitioners"
    ],
    "wof:name":"Mapperley Pk Medical Centre",
    "wof:placetype":"venue"
},
  "geometry": {"coordinates":[-1.1471389532,52.9680137634],"type":"Point"}
}