{
  "type": "Feature",
  "properties": {
    "addr:full":"Unit 4 Colebrook Indstl Est, Longfield Rd Tunbridge Wells East Sussex TN2 3DG",
    "addr:housenumber":"unit 4",
    "addr:postcode":"tn2 3dg",
    "addr:street":"Colebrook Indstl Est Longfield Rd",
    "iso:country":"GB",
    "sg:address":"Unit 4 Colebrook Indstl Est, Longfield Rd",
    "sg:city":"Tunbridge Wells",
    "sg:classifiers":[
        {
            "category":"Home & Garden",
            "subcategory":"Kitchen Supply",
            "type":"Retail Goods"
        }
    ],
    "sg:phone":"+44 1892 510202",
    "sg:postcode":"TN2 3DG",
    "sg:province":"East Sussex",
    "sg:tags":[
        "measuring",
        "scale"
    ],
    "wof:name":"Salter Weightronix Ltd",
    "wof:placetype":"venue"
},
  "geometry": {"coordinates":[0.291687,51.155922],"type":"Point"}
}