{
  "type": "Feature",
  "properties": {
    "addr:full":"Unit 10, Moor Lane Birmingham West Midlands B6 7AQ",
    "addr:housenumber":"unit 10",
    "addr:postcode":"b6 7aq",
    "addr:street":"Moor Lane",
    "iso:country":"GB",
    "sg:address":"Unit 10, Moor Lane",
    "sg:city":"Birmingham",
    "sg:classifiers":[
        {
            "category":"Government",
            "subcategory":"Department Of Motor Vehicles",
            "type":"Public Place"
        }
    ],
    "sg:phone":"+44 121 359 4214",
    "sg:postcode":"B6 7AQ",
    "sg:province":"West Midlands",
    "sg:tags":[
        "engine",
        "component"
    ],
    "wof:name":"Auto Service Radiators",
    "wof:placetype":"venue"
},
  "geometry": {"coordinates":[-1.884173,52.530067],"type":"Point"}
}