{
  "type": "Feature",
  "properties": {
    "iso:country":"GB",
    "sg:address":"Old Army Camp, Mardy Road, Rumney",
    "sg:city":"Cardiff",
    "sg:classifiers":[
        {
            "category":"Manufacturing",
            "subcategory":"Metals",
            "type":"Manufacturing & Wholesale Goods"
        },
        {
            "category":"Wholesale",
            "subcategory":"Scrap",
            "type":"Manufacturing & Wholesale Goods"
        },
        {
            "category":"Wholesale",
            "subcategory":"Auto Parts",
            "type":"Manufacturing & Wholesale Goods"
        }
    ],
    "sg:phone":"+44 29 2079 1383",
    "sg:postcode":"CF3 2EH",
    "sg:province":"Caerphilly",
    "sg:tags":[
        "car",
        "breaker",
        "dismantlers"
    ],
    "wof:name":"G N H VEHICLE DISMANTLERS",
    "wof:placetype":"venue"
},
  "geometry": {"coordinates":[-3.1240599155,51.5094718933],"type":"Point"}
}