{
  "type": "Feature",
  "properties": {
    "addr:full":"Redridge House, 9 Bailey Lane Sheffield South Yorkshire S1 4EG",
    "addr:housenumber":"9",
    "addr:postcode":"s1 4eg",
    "addr:street":"Bailey Lane",
    "iso:country":"GB",
    "sg:address":"Redridge House, 9 Bailey Lane",
    "sg:city":"Sheffield",
    "sg:classifiers":[
        {
            "category":"Professional",
            "subcategory":"Employment Agencies",
            "type":"Services"
        }
    ],
    "sg:phone":"+44 114 278 0011",
    "sg:postcode":"S1 4EG",
    "sg:province":"South Yorkshire",
    "sg:tags":[
        "consultant"
    ],
    "wof:name":"Abraham Beasley Price Morgan",
    "wof:placetype":"venue"
},
  "geometry": {"coordinates":[-1.475911,53.382267],"type":"Point"}
}