{
  "type": "Feature",
  "properties": {
    "addr:full":"34 Ladbroke Gro London Greater London W11 3BQ",
    "addr:housenumber":"34",
    "addr:postcode":"w11 3bq",
    "addr:street":"Ladbroke Gro",
    "iso:country":"GB",
    "sg:address":"34 Ladbroke Gro",
    "sg:city":"London",
    "sg:classifiers":[
        {
            "category":"Farming",
            "subcategory":"Nursery",
            "type":"Manufacturing & Wholesale Goods"
        },
        {
            "category":"Government",
            "subcategory":"Office",
            "type":"Public Place"
        }
    ],
    "sg:phone":"+44 20 7727 4807",
    "sg:postcode":"W11 3BQ",
    "sg:province":"Greater London",
    "sg:tags":[
        "local",
        "creche"
    ],
    "wof:name":"Ladbroke Day Nursery",
    "wof:placetype":"venue"
},
  "geometry": {"coordinates":[-0.2041150033,51.5095672607],"type":"Point"}
}