{
  "type": "Feature",
  "properties": {
    "iso:country":"GB",
    "sg:address":"Rowan Tree Farm, Fryup Road, Ainthorpe",
    "sg:city":"Whitby",
    "sg:classifiers":[
        {
            "category":"Farming",
            "subcategory":"Livestock Farm",
            "type":"Manufacturing & Wholesale Goods"
        }
    ],
    "sg:phone":"+44 1287 660396",
    "sg:postcode":"YO21 2LE",
    "sg:province":"North Yorkshire",
    "sg:tags":[
        "others"
    ],
    "wof:name":"Rowan Tree Farm",
    "wof:placetype":"venue"
},
  "geometry": {"coordinates":[-0.915615,54.46294],"type":"Point"}
}