{
  "type": "Feature",
  "properties": {
    "iso:country":"GB",
    "sg:address":"Lower Penllan, Forden",
    "sg:city":"Welshpool",
    "sg:classifiers":[
        {
            "category":"Building & Trades",
            "subcategory":"Equipment Rental",
            "type":"Services"
        }
    ],
    "sg:phone":"+44 1938 580463",
    "sg:postcode":"SY21 8RY",
    "sg:province":"Shropshire",
    "sg:tags":[
        "plant",
        "machinery"
    ],
    "wof:name":"John M Williams",
    "wof:placetype":"venue"
},
  "geometry": {"coordinates":[-3.138589,52.597088],"type":"Point"}
}