{
  "type": "Feature",
  "properties": {
    "addr:full":"Unit 7 Bedwas Business Centre, Bedwas Caerphilly Caerphilly CF83 8DU",
    "addr:housenumber":"unit 7",
    "addr:postcode":"cf83 8du",
    "iso:country":"GB",
    "sg:address":"Unit 7 Bedwas Business Centre, Bedwas",
    "sg:city":"Caerphilly",
    "sg:classifiers":[
        {
            "category":"Professional",
            "subcategory":"Printing & Photocopies",
            "type":"Services"
        }
    ],
    "sg:phone":"+44 29 2086 6555",
    "sg:postcode":"CF83 8DU",
    "sg:province":"Caerphilly",
    "sg:tags":[
        "printer"
    ],
    "wof:name":"Treforest Printing Ltd.",
    "wof:placetype":"venue"
},
  "geometry": {"coordinates":[-3.199564,51.589359],"type":"Point"}
}