{
  "type": "Feature",
  "properties": {
    "iso:country":"GB",
    "sg:address":"4 Prospect Terrace, Plawsworth",
    "sg:city":"Chester-le-street",
    "sg:classifiers":[
        {
            "category":"Sports & Exercise",
            "subcategory":"Tennis Court",
            "type":"Entertainment"
        }
    ],
    "sg:phone":"+44 191 371 0102",
    "sg:postcode":"DH2 3LF",
    "sg:province":"Durham",
    "sg:tags":[
        "breakdown",
        "recovery"
    ],
    "wof:name":"Quick Shift Transport",
    "wof:placetype":"venue"
},
  "geometry": {"coordinates":[-1.591167,54.822201],"type":"Point"}
}