{
  "type": "Feature",
  "properties": {
    "addr:full":"2 Stranraer Close, Mansfield Woodhouse Mansfield Derbyshire NG19 8PP",
    "addr:housenumber":"2",
    "addr:postcode":"ng19 8pp",
    "addr:street":"Stranraer Close",
    "iso:country":"GB",
    "sg:address":"2 Stranraer Close, Mansfield Woodhouse",
    "sg:city":"Mansfield",
    "sg:classifiers":[
        {
            "category":"Professional",
            "subcategory":"Engineering",
            "type":"Services"
        }
    ],
    "sg:postcode":"NG19 8PP",
    "sg:province":"Derbyshire",
    "sg:tags":[
        "contractor",
        "electrical",
        "engineer"
    ],
    "wof:name":"Steven Holmes Electrical Services",
    "wof:placetype":"venue"
},
  "geometry": {"coordinates":[-1.193217,53.17659],"type":"Point"}
}