{
  "type": "Feature",
  "properties": {
    "addr:full":"1a Dolau Rd Llanelli Carmarthenshire SA15 2HL",
    "addr:housenumber":"1a",
    "addr:postcode":"sa15 2hl",
    "addr:street":"Dolau Rd",
    "iso:country":"GB",
    "sg:address":"1a Dolau Rd",
    "sg:city":"Llanelli",
    "sg:classifiers":[
        {
            "category":"Building & Trades",
            "subcategory":"Construction",
            "type":"Services"
        }
    ],
    "sg:phone":"+44 1554 773605",
    "sg:postcode":"SA15 2HL",
    "sg:province":"Carmarthenshire",
    "sg:tags":[
        "builder"
    ],
    "wof:name":"Colarusso Construction",
    "wof:placetype":"venue"
},
  "geometry": {"coordinates":[-4.156928,51.670696],"type":"Point"}
}