{
  "type": "Feature",
  "properties": {
    "addr:full":"Unit 38 Walton Business Centre, 44 Terrace Road Walton-on-thames Surrey KT12 2SD",
    "addr:housenumber":"unit 38;business;44",
    "addr:postcode":"kt12 2sd",
    "addr:street":"Walton;Terrace Road",
    "iso:country":"GB",
    "sg:address":"Unit 38 Walton Business Centre, 44 Terrace Road",
    "sg:city":"Walton-on-thames",
    "sg:classifiers":[
        {
            "category":"Building & Trades",
            "subcategory":"Construction",
            "type":"Services"
        }
    ],
    "sg:phone":"+44 1932 269021",
    "sg:postcode":"KT12 2SD",
    "sg:province":"Surrey",
    "sg:tags":[
        "builder"
    ],
    "wof:name":"Pegasus Building Co.",
    "wof:placetype":"venue"
},
  "geometry": {"coordinates":[-0.4207040071,51.3843460083],"type":"Point"}
}