{
  "type": "Feature",
  "properties": {
    "addr:full":"1 London Rd Slough Berkshire SL3 7RL",
    "addr:housenumber":"1",
    "addr:postcode":"sl3 7rl",
    "addr:street":"London Rd",
    "iso:country":"GB",
    "sg:address":"1 London Rd",
    "sg:city":"Slough",
    "sg:classifiers":[
        {
            "category":"Professional",
            "subcategory":"Computer Services",
            "type":"Services"
        }
    ],
    "sg:phone":"+44 1753 779900",
    "sg:postcode":"SL3 7RL",
    "sg:province":"Berkshire",
    "sg:tags":[
        "system",
        "software"
    ],
    "wof:name":"D T M Europe Ltd",
    "wof:placetype":"venue"
},
  "geometry": {"coordinates":[-0.571927,51.504391],"type":"Point"}
}