{
  "type": "Feature",
  "properties": {
    "iso:country":"GB",
    "sg:address":"134 Main Street, Stenhousemuir",
    "sg:city":"Larbert",
    "sg:classifiers":[
        {
            "category":"Personal",
            "subcategory":"Beauty Salon",
            "type":"Services"
        },
        {
            "category":"Personal",
            "subcategory":"Barber",
            "type":"Services"
        }
    ],
    "sg:phone":"+44 1324 562444",
    "sg:postcode":"FK5 3JF",
    "sg:province":"Falkirk",
    "sg:tags":[
        "unisex",
        "hairdresser"
    ],
    "wof:name":"Streaks Ahead",
    "wof:placetype":"venue"
},
  "geometry": {"coordinates":[-3.825989,56.02354],"type":"Point"}
}