{
  "type": "Feature",
  "properties": {
    "addr:full":"2a Fir Tree Lane, Groby Leicester Leicestershire LE6 0FH",
    "addr:housenumber":"2a",
    "addr:postcode":"le6 0fh",
    "addr:street":"Fir Tree Lane",
    "iso:country":"GB",
    "sg:address":"2a Fir Tree Lane, Groby",
    "sg:city":"Leicester",
    "sg:classifiers":[
        {
            "category":"Home & Garden",
            "subcategory":"Home Furnishings",
            "type":"Retail Goods"
        },
        {
            "category":"Home & Garden",
            "subcategory":"Building Materials",
            "type":"Retail Goods"
        }
    ],
    "sg:phone":"+44 116 232 2731",
    "sg:postcode":"LE6 0FH",
    "sg:province":"Leicestershire",
    "sg:tags":[
        "installers",
        "planner",
        "kitchen",
        "furnishers"
    ],
    "wof:name":"Groby Kitchens",
    "wof:placetype":"venue"
},
  "geometry": {"coordinates":[-1.227807045,52.6622657776],"type":"Point"}
}