{
  "type": "Feature",
  "properties": {
    "addr:full":"Perch Buildings, 20 West Bute Street Cardiff Cardiff CF10 5EP",
    "addr:housenumber":"20",
    "addr:postcode":"cf10 5ep",
    "addr:street":"West Bute Street",
    "iso:country":"GB",
    "sg:address":"Perch Buildings, 20 West Bute Street",
    "sg:city":"Cardiff",
    "sg:classifiers":[
        {
            "category":"Professional",
            "subcategory":"Accounting & Tax Preparation",
            "type":"Services"
        }
    ],
    "sg:postcode":"CF10 5EP",
    "sg:province":"Cardiff",
    "sg:tags":[
        "accountant"
    ],
    "wof:name":"Keane & Co",
    "wof:placetype":"venue"
},
  "geometry": {"coordinates":[-3.1806690693,51.4812583923],"type":"Point"}
}