{
  "type": "Feature",
  "properties": {
    "iso:country":"GB",
    "sg:address":"Abbey Ho, 30 Angel Hill",
    "sg:city":"Bury St Edmunds",
    "sg:classifiers":[
        {
            "category":"Communications",
            "type":"Services"
        }
    ],
    "sg:phone":"+44 1284 769700",
    "sg:postcode":"IP33 1LS",
    "sg:province":"Suffolk",
    "sg:tags":[
        "broadcasting"
    ],
    "wof:name":"BBC Radio Suffolk",
    "wof:placetype":"venue"
},
  "geometry": {"coordinates":[0.7093200088,52.2499046326],"type":"Point"}
}