{
  "type": "Feature",
  "properties": {
    "addr:full":"69 Cornwallis Avenue, Aylesham Canterbury Kent CT3 3HG",
    "addr:housenumber":"69",
    "addr:postcode":"ct3 3hg",
    "addr:street":"Cornwallis Avenue",
    "iso:country":"GB",
    "sg:address":"69 Cornwallis Avenue, Aylesham",
    "sg:city":"Canterbury",
    "sg:classifiers":[
        {
            "category":"Food & Beverages",
            "subcategory":"Meat & Fish",
            "type":"Retail Goods"
        },
        {
            "category":"Food & Beverages",
            "subcategory":"Groceries & Convenience Stores",
            "type":"Retail Goods"
        }
    ],
    "sg:phone":"+44 1304 840374",
    "sg:postcode":"CT3 3HG",
    "sg:province":"Kent",
    "sg:tags":[
        "shop",
        "chip"
    ],
    "wof:name":"Cornwallis Fish Bar",
    "wof:placetype":"venue"
},
  "geometry": {"coordinates":[1.203714,51.228954],"type":"Point"}
}