{
  "type": "Feature",
  "properties": {
    "iso:country":"GB",
    "sg:address":"43 East Croft, Ratho",
    "sg:city":"Newbridge",
    "sg:classifiers":[
        {
            "category":"Communications",
            "subcategory":"Film & Video Production",
            "type":"Services"
        }
    ],
    "sg:postcode":"EH28 8PD",
    "sg:province":"City of Edinburgh",
    "sg:tags":[
        "illustrator",
        "artist"
    ],
    "wof:name":"David Bell Fine Arts",
    "wof:placetype":"venue"
},
  "geometry": {"coordinates":[-3.372734,55.923553],"type":"Point"}
}