{
  "type": "Feature",
  "properties": {
    "addr:full":"8 Sawrey St, Octagon Plymouth Devon PL1 3LA",
    "addr:housenumber":"8",
    "addr:postcode":"pl1 3la",
    "addr:street":"Sawrey St",
    "iso:country":"GB",
    "sg:address":"8 Sawrey St, Octagon",
    "sg:city":"Plymouth",
    "sg:classifiers":[
        {
            "category":"Utilities",
            "subcategory":"Mobile Phone",
            "type":"Services"
        }
    ],
    "sg:phone":"+44 1752 227228",
    "sg:postcode":"PL1 3LA",
    "sg:province":"Devon",
    "sg:tags":[
        "battery",
        "supplier"
    ],
    "wof:name":"Car Electrical (Plymouth) Ltd",
    "wof:placetype":"venue"
},
  "geometry": {"coordinates":[-4.152895,50.368828],"type":"Point"}
}