{
  "type": "Feature",
  "properties": {
    "addr:full":"150 Lynedoch St Greenock Inverclyde PA15 4BE",
    "addr:housenumber":"150",
    "addr:postcode":"pa15 4be",
    "addr:street":"Lynedoch St Greenock",
    "iso:country":"GB",
    "sg:address":"150 Lynedoch St",
    "sg:city":"Greenock",
    "sg:classifiers":[
        {
            "category":"Food & Beverages",
            "subcategory":"Supermarket",
            "type":"Retail Goods"
        }
    ],
    "sg:phone":"+44 1475 721241",
    "sg:postcode":"PA15 4BE",
    "sg:province":"Inverclyde",
    "sg:tags":[
        "frozen"
    ],
    "wof:name":"Tate & Lyle Sugars",
    "wof:placetype":"venue"
},
  "geometry": {"coordinates":[-4.75769,55.941933],"type":"Point"}
}