{
  "type": "Feature",
  "properties": {
    "iso:country":"GB",
    "sg:address":"Irvine Road",
    "sg:city":"Kilmarnock",
    "sg:classifiers":[
        {
            "category":"Government",
            "subcategory":"Office",
            "type":"Public Place"
        },
        {
            "category":"Sports & Exercise",
            "subcategory":"Golf",
            "type":"Entertainment"
        }
    ],
    "sg:phone":"+44 1563 521512",
    "sg:postcode":"KA1 2RT",
    "sg:province":"East Ayrshire",
    "sg:tags":[
        "club",
        "course",
        "local"
    ],
    "wof:name":"Annanhill Golf Course",
    "wof:placetype":"venue"
},
  "geometry": {"coordinates":[-4.521459,55.611435],"type":"Point"}
}