{
  "type": "Feature",
  "properties": {
    "addr:full":"34 St Andrews Road, Montpelier Bristol City of Bristol BS6 5EH",
    "addr:housenumber":"34",
    "addr:postcode":"bs6 5eh",
    "addr:street":"St Andrews Road",
    "iso:country":"GB",
    "sg:address":"34 St Andrews Road, Montpelier",
    "sg:city":"Bristol",
    "sg:classifiers":[
        {
            "category":"Bars & Pubs",
            "type":"Food & Drink"
        }
    ],
    "sg:phone":"+44 117 909 6667",
    "sg:postcode":"BS6 5EH",
    "sg:province":"City of Bristol",
    "sg:tags":[
        "pubs",
        "inn"
    ],
    "wof:name":"Dcs Inns",
    "wof:placetype":"venue"
},
  "geometry": {"coordinates":[-2.5873470306,51.4674873352],"type":"Point"}
}