{
  "type": "Feature",
  "properties": {
    "iso:country":"GB",
    "sg:address":"The Laurels, Firmins Court, West Bergholt",
    "sg:city":"Colchester",
    "sg:classifiers":[
        {
            "category":"Banks & Credit Unions",
            "subcategory":"Financial Services",
            "type":"Services"
        }
    ],
    "sg:postcode":"CO6 3BQ",
    "sg:province":"Essex",
    "sg:tags":[
        "consultant"
    ],
    "wof:name":"Allan Hunns Financial Services",
    "wof:placetype":"venue"
},
  "geometry": {"coordinates":[0.84595,51.915291],"type":"Point"}
}