{
  "type": "Feature",
  "properties": {
    "iso:country":"GB",
    "sg:address":"Town St, The Green, Horsforth",
    "sg:city":"Leeds",
    "sg:classifiers":[
        {
            "category":"Bars & Pubs",
            "type":"Food & Drink"
        }
    ],
    "sg:postcode":"LS18 5JB",
    "sg:province":"West Yorkshire",
    "sg:tags":[
        "pubs",
        "inn"
    ],
    "wof:name":"Punch Inns (U K) Ltd",
    "wof:placetype":"venue"
},
  "geometry": {"coordinates":[-1.6392639875,53.8392448425],"type":"Point"}
}