{
  "type": "Feature",
  "properties": {
    "addr:full":"31 Turnpike Road Hayle Cornwall TR27 5DT",
    "addr:housenumber":"31",
    "addr:postcode":"tr27 5dt",
    "addr:street":"Turnpike Road",
    "iso:country":"GB",
    "sg:address":"31 Turnpike Road",
    "sg:city":"Hayle",
    "sg:classifiers":[
        {
            "category":"Autos & Motor Vehicles",
            "subcategory":"Fuel & Gas Station",
            "type":"Retail Goods"
        }
    ],
    "sg:postcode":"TR27 5DT",
    "sg:province":"Cornwall",
    "sg:tags":[
        "petrol",
        "filling"
    ],
    "wof:name":"Dover Service Station",
    "wof:placetype":"venue"
},
  "geometry": {"coordinates":[-5.372361,50.204109],"type":"Point"}
}