{
  "type": "Feature",
  "properties": {
    "addr:full":"4 Knowsley Park Lane Prescot Merseyside L34 3NB",
    "addr:housenumber":"4",
    "addr:postcode":"l34 3nb",
    "addr:street":"Knowsley Park Lane",
    "iso:country":"GB",
    "sg:address":"4 Knowsley Park Lane",
    "sg:city":"Prescot",
    "sg:classifiers":[
        {
            "category":"Organizations",
            "subcategory":"Non-profit Organization",
            "type":"Services"
        }
    ],
    "sg:phone":"+44 151 426 6063",
    "sg:postcode":"L34 3NB",
    "sg:province":"Merseyside",
    "sg:tags":[
        "organisation",
        "voluntary",
        "charity"
    ],
    "wof:name":"The Bungalow",
    "wof:placetype":"venue"
},
  "geometry": {"coordinates":[-2.811211,53.429783],"type":"Point"}
}