{
  "type": "Feature",
  "properties": {
    "addr:full":"Pym St Tavistock Devon PL19 0AW",
    "addr:postcode":"pl19 0aw",
    "addr:street":"Pym St",
    "iso:country":"GB",
    "sg:address":"Pym St",
    "sg:city":"Tavistock",
    "sg:classifiers":[
        {
            "category":"Home & Garden",
            "subcategory":"Hardware",
            "type":"Retail Goods"
        }
    ],
    "sg:postcode":"PL19 0AW",
    "sg:province":"Devon",
    "sg:tags":[
        "retailer",
        "lighting"
    ],
    "wof:name":"Harmony Lighting & Electrical",
    "wof:placetype":"venue"
},
  "geometry": {"coordinates":[-4.145989,50.550419],"type":"Point"}
}