{
  "type": "Feature",
  "properties": {
    "addr:full":"191 Preston New Road Blackpool Lancashire FY3 9TN",
    "addr:housenumber":"191",
    "addr:postcode":"fy3 9tn",
    "addr:street":"Preston New Road",
    "iso:country":"GB",
    "sg:address":"191 Preston New Road",
    "sg:city":"Blackpool",
    "sg:classifiers":[
        {
            "category":"Health Services",
            "subcategory":"Optometrist",
            "type":"Services"
        }
    ],
    "sg:postcode":"FY3 9TN",
    "sg:province":"Lancashire",
    "sg:tags":[
        "optician"
    ],
    "wof:name":"D & V Pellowe",
    "wof:placetype":"venue"
},
  "geometry": {"coordinates":[-3.015916,53.805218],"type":"Point"}
}