{
  "type": "Feature",
  "properties": {
    "iso:country":"GB",
    "sg:address":"Limerstone Road, Brighstone",
    "sg:city":"Newport",
    "sg:classifiers":[
        {
            "category":"Bars & Pubs",
            "type":"Food & Drink"
        }
    ],
    "sg:phone":"+44 1983 740616",
    "sg:postcode":"PO30 4AE",
    "sg:province":"Isle of Wight",
    "sg:tags":[
        "pubs",
        "house",
        "inn",
        "public",
        "activity"
    ],
    "wof:name":"The Countryman",
    "wof:placetype":"venue"
},
  "geometry": {"coordinates":[-1.394329,50.64246],"type":"Point"}
}