{
  "type": "Feature",
  "properties": {
    "addr:full":"47 Seaton Road Felixstowe Suffolk IP11 9BS",
    "addr:housenumber":"47",
    "addr:postcode":"ip11 9bs",
    "addr:street":"Seaton Road",
    "iso:country":"GB",
    "sg:address":"47 Seaton Road",
    "sg:city":"Felixstowe",
    "sg:classifiers":[
        {
            "category":"Home & Garden",
            "subcategory":"Carpets & Floor Coverings",
            "type":"Retail Goods"
        }
    ],
    "sg:phone":"+44 1394 282941",
    "sg:postcode":"IP11 9BS",
    "sg:province":"Suffolk",
    "sg:tags":[
        "carpets",
        "retailer",
        "rug",
        "matting"
    ],
    "wof:name":"Eric Scott Carpets",
    "wof:placetype":"venue"
},
  "geometry": {"coordinates":[1.3400679827,51.9691429138],"type":"Point"}
}