{
  "type": "Feature",
  "properties": {
    "iso:country":"GB",
    "sg:address":"6 Stinsford Road",
    "sg:city":"Poole",
    "sg:classifiers":[
        {
            "category":"Manufacturing",
            "subcategory":"Textiles",
            "type":"Manufacturing & Wholesale Goods"
        }
    ],
    "sg:postcode":"BH17 0SW",
    "sg:province":"Dorset",
    "sg:tags":[
        "merchant",
        "agent"
    ],
    "wof:name":"Gp & J Baker Ltd.",
    "wof:placetype":"venue"
},
  "geometry": {"coordinates":[-1.978031,50.745239],"type":"Point"}
}