{
  "type": "Feature",
  "properties": {
    "iso:country":"GB",
    "sg:address":"51 Wolborough Street",
    "sg:city":"Newton Abbot",
    "sg:classifiers":[
        {
            "category":"Communications",
            "type":"Services"
        }
    ],
    "sg:postcode":"TQ12 1JQ",
    "sg:province":"Devon",
    "sg:tags":[
        "telecommunication"
    ],
    "wof:name":"Auto Sounds & Alarms",
    "wof:placetype":"venue"
},
  "geometry": {"coordinates":[-3.615144,50.528496],"type":"Point"}
}