{
  "type": "Feature",
  "properties": {
    "iso:country":"GB",
    "sg:address":"70 Fazeley Street",
    "sg:city":"Birmingham",
    "sg:classifiers":[
        {
            "category":"Retail",
            "subcategory":"Car Wash",
            "type":"Services"
        },
        {
            "category":"Retail",
            "subcategory":"Auto Repair",
            "type":"Services"
        }
    ],
    "sg:phone":"+44 121 643 0852",
    "sg:postcode":"B5 5RD",
    "sg:province":"West Midlands",
    "sg:tags":[
        "upholsterer",
        "trimmer"
    ],
    "wof:name":"William Marston Ltd.",
    "wof:placetype":"venue"
},
  "geometry": {"coordinates":[-1.8868499994,52.4799842834],"type":"Point"}
}