{
  "type": "Feature",
  "properties": {
    "addr:full":"78 Bayford Close Hemel Hempstead Hertfordshire HP2 7NA",
    "addr:housenumber":"78",
    "addr:postcode":"hp2 7na",
    "addr:street":"Bayford Close",
    "iso:country":"GB",
    "sg:address":"78 Bayford Close",
    "sg:city":"Hemel Hempstead",
    "sg:classifiers":[
        {
            "category":"Home & Garden",
            "subcategory":"Carpets & Floor Coverings",
            "type":"Retail Goods"
        }
    ],
    "sg:postcode":"HP2 7NA",
    "sg:province":"Hertfordshire",
    "sg:tags":[
        "cleaner",
        "upholstery"
    ],
    "wof:name":"P & C Carpet Clean",
    "wof:placetype":"venue"
},
  "geometry": {"coordinates":[-0.4331929982,51.7767448425],"type":"Point"}
}