{
  "type": "Feature",
  "properties": {
    "addr:full":"Damerel Ho, Damerel Clo Plymouth Devon PL1 4JZ",
    "addr:postcode":"pl1 4jz",
    "addr:street":"Clo",
    "iso:country":"GB",
    "sg:address":"Damerel Ho, Damerel Clo",
    "sg:city":"Plymouth",
    "sg:classifiers":[
        {
            "category":"Health Services",
            "subcategory":"Clinic",
            "type":"Services"
        }
    ],
    "sg:phone":"+44 1752 566660",
    "sg:postcode":"PL1 4JZ",
    "sg:province":"Devon",
    "sg:tags":[
        "abuse",
        "drug"
    ],
    "wof:name":"Community Drugs Service",
    "wof:placetype":"venue"
},
  "geometry": {"coordinates":[-4.1702928543,50.3702735901],"type":"Point"}
}