{
  "type": "Feature",
  "properties": {
    "addr:full":"12 Ashbury Drive, Tilehurst Reading Berkshire RG31 5LJ",
    "addr:housenumber":"12",
    "addr:postcode":"rg31 5lj",
    "addr:street":"Ashbury Drive",
    "iso:country":"GB",
    "sg:address":"12 Ashbury Drive, Tilehurst",
    "sg:city":"Reading",
    "sg:classifiers":[
        {
            "category":"Building & Trades",
            "subcategory":"Construction",
            "type":"Services"
        }
    ],
    "sg:phone":"+44 118 942 8781",
    "sg:postcode":"RG31 5LJ",
    "sg:province":"Berkshire",
    "sg:tags":[
        "decorator",
        "painter"
    ],
    "wof:name":"Sumner & Lee",
    "wof:placetype":"venue"
},
  "geometry": {"coordinates":[-1.050141,51.455952],"type":"Point"}
}