{
  "type": "Feature",
  "properties": {
    "addr:full":"366 Woodside Road, Wyke Bradford West Yorkshire BD12 8HT",
    "addr:housenumber":"366",
    "addr:postcode":"bd12 8ht",
    "addr:street":"Woodside Road",
    "iso:country":"GB",
    "sg:address":"366 Woodside Road, Wyke",
    "sg:city":"Bradford",
    "sg:classifiers":[
        {
            "category":"Autos & Motor Vehicles",
            "subcategory":"Motorcycle Sales",
            "type":"Retail Goods"
        },
        {
            "category":"Personal",
            "subcategory":"Skin Care",
            "type":"Services"
        }
    ],
    "sg:phone":"+44 1274 604672",
    "sg:postcode":"BD12 8HT",
    "sg:province":"West Yorkshire",
    "sg:tags":[
        "part",
        "component",
        "manufacturer",
        "accessory"
    ],
    "wof:name":"Motorcycle Seatworks",
    "wof:placetype":"venue"
},
  "geometry": {"coordinates":[-1.769805,53.742203],"type":"Point"}
}