{
  "type": "Feature",
  "properties": {
    "iso:country":"GB",
    "sg:address":"Rushmoor Farm, Johnston",
    "sg:city":"Haverfordwest",
    "sg:classifiers":[
        {
            "category":"Farming",
            "subcategory":"Livestock Farm",
            "type":"Manufacturing & Wholesale Goods"
        }
    ],
    "sg:postcode":"SA62 3HG",
    "sg:province":"Pembrokeshire",
    "sg:tags":[
        "others"
    ],
    "wof:name":"Edward R Henderson",
    "wof:placetype":"venue"
},
  "geometry": {"coordinates":[-4.9971308708,51.7550849915],"type":"Point"}
}