{
  "type": "Feature",
  "properties": {
    "addr:full":"Stubbs Mill, Upper Kirby Street Manchester Greater Manchester M4 6FA",
    "addr:postcode":"m4 6fa",
    "addr:street":"Stubbs Mill Upper Kirby Street",
    "iso:country":"GB",
    "sg:address":"Stubbs Mill, Upper Kirby Street",
    "sg:city":"Manchester",
    "sg:classifiers":[
        {
            "category":"Autos & Motor Vehicles",
            "subcategory":"Motorcycle Sales",
            "type":"Retail Goods"
        }
    ],
    "sg:postcode":"M4 6FA",
    "sg:province":"Greater Manchester",
    "sg:tags":[
        "component"
    ],
    "wof:name":"A J Varrechai",
    "wof:placetype":"venue"
},
  "geometry": {"coordinates":[-2.2231600285,53.4843597412],"type":"Point"}
}