{
  "type": "Feature",
  "properties": {
    "iso:country":"GB",
    "sg:address":"59a Leabrook Road",
    "sg:city":"Wednesbury",
    "sg:classifiers":[
        {
            "category":"Retail",
            "subcategory":"Auto Rental",
            "type":"Services"
        }
    ],
    "sg:phone":"+44 121 556 0081",
    "sg:postcode":"WS10 7NW",
    "sg:province":"West Midlands",
    "sg:tags":[
        "car"
    ],
    "wof:name":"Albany Vehicle Rentals",
    "wof:placetype":"venue"
},
  "geometry": {"coordinates":[-2.0356550217,52.5460472107],"type":"Point"}
}