{
  "type": "Feature",
  "properties": {
    "addr:full":"Loddon Vale, Practice Hurricane Way, Woodley Reading Reading Berkshire RG5 4UX",
    "addr:postcode":"rg5 4ux",
    "addr:street":"Loddon;Hurricane Way",
    "iso:country":"GB",
    "sg:address":"Loddon Vale, Practice Hurricane Way, Woodley Reading",
    "sg:city":"Reading",
    "sg:classifiers":[
        {
            "category":"Health Services",
            "subcategory":"Clinic",
            "type":"Services"
        }
    ],
    "sg:phone":"+44 11890327",
    "sg:postcode":"RG5 4UX",
    "sg:province":"Berkshire",
    "sg:tags":[
        "private"
    ],
    "wof:name":"Marie Stopes Vasectomy Centre",
    "wof:placetype":"venue"
},
  "geometry": {"coordinates":[-0.897734,51.453156],"type":"Point"}
}