{
  "type": "Feature",
  "properties": {
    "addr:full":"360 Wells Road Bristol City of Bristol BS4 2QL",
    "addr:housenumber":"360",
    "addr:postcode":"bs4 2ql",
    "addr:street":"Wells Road",
    "iso:country":"GB",
    "sg:address":"360 Wells Road",
    "sg:city":"Bristol",
    "sg:classifiers":[
        {
            "category":"Health Services",
            "subcategory":"Health Practitioner",
            "type":"Services"
        }
    ],
    "sg:phone":"+44 117 977 4159",
    "sg:postcode":"BS4 2QL",
    "sg:province":"City of Bristol",
    "sg:tags":[
        "physiotherapist"
    ],
    "wof:name":"The Bardsley Physiotherpy Clinic",
    "wof:placetype":"venue"
},
  "geometry": {"coordinates":[-2.56496,51.432426],"type":"Point"}
}