{
  "type": "Feature",
  "properties": {
    "iso:country":"GB",
    "sg:address":"Stenners Yard, Hartcliffe Way",
    "sg:city":"Bristol",
    "sg:classifiers":[
        {
            "category":"Retail",
            "subcategory":"Auto Repair",
            "type":"Services"
        }
    ],
    "sg:phone":"+44 117 963 4723",
    "sg:postcode":"BS3 5RJ",
    "sg:province":"City of Bristol",
    "sg:tags":[
        "modification",
        "garage"
    ],
    "wof:name":"Luckwell Road Garage",
    "wof:placetype":"venue"
},
  "geometry": {"coordinates":[-2.6062500477,51.4294891357],"type":"Point"}
}