{
  "type": "Feature",
  "properties": {
    "iso:country":"GB",
    "sg:address":"259 Rednal Road, Kings Norton",
    "sg:city":"Birmingham",
    "sg:classifiers":[
        {
            "category":"Building & Trades",
            "subcategory":"Plumbing",
            "type":"Services"
        }
    ],
    "sg:phone":"+44 121 458 3230",
    "sg:postcode":"B38 8EB",
    "sg:province":"West Midlands",
    "sg:tags":[
        "merchant",
        "plumbers'"
    ],
    "wof:name":"Ashbrook Engineering Co",
    "wof:placetype":"venue"
},
  "geometry": {"coordinates":[-1.94202,52.401581],"type":"Point"}
}