{
  "type": "Feature",
  "properties": {
    "iso:country":"GB",
    "sg:address":"Key Ho, Howden Indstl Est",
    "sg:city":"Tiverton",
    "sg:classifiers":[
        {
            "category":"Military Area",
            "subcategory":"Air Force Base",
            "type":"Public Place"
        }
    ],
    "sg:postcode":"EX16 5HW",
    "sg:province":"Devon",
    "sg:tags":[
        "taxi",
        "hire",
        "private"
    ],
    "wof:name":"Edwards,Philip,",
    "wof:placetype":"venue"
},
  "geometry": {"coordinates":[-3.493149,50.905025],"type":"Point"}
}