{
  "type": "Feature",
  "properties": {
    "iso:country":"GB",
    "sg:address":"58 Woodgate",
    "sg:city":"Leicester",
    "sg:classifiers":[
        {
            "category":"Personal",
            "subcategory":"Beauty Salon",
            "type":"Services"
        },
        {
            "category":"Personal",
            "subcategory":"Barber",
            "type":"Services"
        }
    ],
    "sg:phone":"+44 116 262 5282",
    "sg:postcode":"LE3 5GF",
    "sg:province":"Leicestershire",
    "sg:tags":[
        "unisex",
        "hairdresser"
    ],
    "wof:name":"Frezzante Hair Academy",
    "wof:placetype":"venue"
},
  "geometry": {"coordinates":[-1.147561,52.643772],"type":"Point"}
}