{
  "type": "Feature",
  "properties": {
    "iso:country":"GB",
    "sg:address":"Unit 9 Tilia Rd",
    "sg:city":"Clapton",
    "sg:classifiers":[
        {
            "category":"Manufacturing",
            "subcategory":"Wood Products",
            "type":"Manufacturing & Wholesale Goods"
        }
    ],
    "sg:phone":"+44 20 8985 6616",
    "sg:postcode":"E5 8JB",
    "sg:province":"Greater London",
    "sg:tags":[
        "maker",
        "cabinet"
    ],
    "wof:name":"Patfort Cabinet Making & Joinery",
    "wof:placetype":"venue"
},
  "geometry": {"coordinates":[-0.055644,51.552731],"type":"Point"}
}