{
  "type": "Feature",
  "properties": {
    "addr:full":"Meadow Thatch Grimsby Lincolnshire DN36 5UW",
    "addr:postcode":"dn36 5uw",
    "iso:country":"GB",
    "sg:address":"Meadow Thatch",
    "sg:city":"Grimsby",
    "sg:classifiers":[
        {
            "category":"Building & Trades",
            "subcategory":"Construction",
            "type":"Services"
        }
    ],
    "sg:postcode":"DN36 5UW",
    "sg:province":"Lincolnshire",
    "sg:tags":[
        "builder"
    ],
    "wof:name":"M J Hall",
    "wof:placetype":"venue"
},
  "geometry": {"coordinates":[-0.076044,53.47596],"type":"Point"}
}