{
  "type": "Feature",
  "properties": {
    "addr:full":"Lodge Lane, Morfe Road Bridgnorth Shropshire WV15 5EQ",
    "addr:postcode":"wv15 5eq",
    "addr:street":"Lodge Lane Morfe Road",
    "iso:country":"GB",
    "sg:address":"Lodge Lane, Morfe Road",
    "sg:city":"Bridgnorth",
    "sg:classifiers":[
        {
            "category":"Education",
            "subcategory":"School",
            "type":"Public Place"
        }
    ],
    "sg:phone":"+44 1746 763455",
    "sg:postcode":"WV15 5EQ",
    "sg:province":"Shropshire",
    "sg:tags":[
        "local",
        "authority"
    ],
    "wof:name":"St Mary's Bluecoat C of E Primary School",
    "wof:placetype":"venue"
},
  "geometry": {"coordinates":[-2.405384,52.535889],"type":"Point"}
}