{
  "type": "Feature",
  "properties": {
    "addr:full":"4 Randolph Cres Edinburgh City of Edinburgh EH3 7TH",
    "addr:housenumber":"4",
    "addr:postcode":"eh3 7th",
    "addr:street":"Randolph Cres",
    "iso:country":"GB",
    "sg:address":"4 Randolph Cres",
    "sg:city":"Edinburgh",
    "sg:classifiers":[
        {
            "category":"Banks & Credit Unions",
            "subcategory":"Investment Brokerage",
            "type":"Services"
        }
    ],
    "sg:postcode":"EH3 7TH",
    "sg:province":"City of Edinburgh",
    "sg:tags":[
        "overseas",
        "property",
        "agent"
    ],
    "wof:name":"Holiday Properties Ltd",
    "wof:placetype":"venue"
},
  "geometry": {"coordinates":[-3.210801,55.95182],"type":"Point"}
}