{
  "type": "Feature",
  "properties": {
    "iso:country":"GB",
    "sg:address":"42-44 Chertsey Rd, Byfleet",
    "sg:city":"West Byfleet",
    "sg:classifiers":[
        {
            "category":"Social Services",
            "subcategory":"Retirement Home",
            "type":"Services"
        }
    ],
    "sg:phone":"+44 1932 336200",
    "sg:postcode":"KT14 7AN",
    "sg:province":"Surrey",
    "sg:tags":[
        "residential",
        "care"
    ],
    "wof:name":"Brambletye Care Ltd",
    "wof:placetype":"venue"
},
  "geometry": {"coordinates":[-0.480973,51.343269],"type":"Point"}
}