{
  "type": "Feature",
  "properties": {
    "addr:full":"Plastan Dinas, Dinas Dingle Caernarfon Gwynedd LL54 5TW",
    "addr:postcode":"ll54 5tw",
    "iso:country":"GB",
    "sg:address":"Plastan Dinas, Dinas Dingle",
    "sg:city":"Caernarfon",
    "sg:classifiers":[
        {
            "category":"Bars & Pubs",
            "type":"Food & Drink"
        }
    ],
    "sg:postcode":"LL54 5TW",
    "sg:province":"Gwynedd",
    "sg:tags":[
        "pubs",
        "inn"
    ],
    "wof:name":"Plastan Dinas & Dingles",
    "wof:placetype":"venue"
},
  "geometry": {"coordinates":[-4.2782378197,53.1030006409],"type":"Point"}
}