{
  "type": "Feature",
  "properties": {
    "addr:full":"31 Davies Street London Greater London W1K 4LP",
    "addr:housenumber":"31",
    "addr:postcode":"w1k 4lp",
    "addr:street":"Davies Street",
    "iso:country":"GB",
    "sg:address":"31 Davies Street",
    "sg:city":"London",
    "sg:classifiers":[
        {
            "category":"Real Estate",
            "subcategory":"Surveying",
            "type":"Services"
        }
    ],
    "sg:phone":"+44 20 7495 3232",
    "sg:postcode":"W1K 4LP",
    "sg:province":"Greater London",
    "sg:tags":[
        "surveyor",
        "valuer"
    ],
    "wof:name":"Hanrahan Deane Ltd.",
    "wof:placetype":"venue"
},
  "geometry": {"coordinates":[-0.1481229961,51.5117759705],"type":"Point"}
}