{
  "type": "Feature",
  "properties": {
    "addr:full":"Ashwood Way, Winklebury Basingstoke Hampshire RG23 8AA",
    "addr:postcode":"rg23 8aa",
    "addr:street":"Ashwood Way Winklebury",
    "iso:country":"GB",
    "sg:address":"Ashwood Way, Winklebury",
    "sg:city":"Basingstoke",
    "sg:classifiers":[
        {
            "category":"Social Services",
            "subcategory":"Adult Care",
            "type":"Services"
        }
    ],
    "sg:phone":"+44 1256 465725",
    "sg:postcode":"RG23 8AA",
    "sg:province":"Hampshire",
    "sg:tags":[
        "day",
        "centre"
    ],
    "wof:name":"Basingstoke Day Services",
    "wof:placetype":"venue"
},
  "geometry": {"coordinates":[-1.1309390068,51.2673110962],"type":"Point"}
}