{
  "type": "Feature",
  "properties": {
    "addr:full":"Beckhithe Norwich Norfolk NR9 3NP",
    "addr:postcode":"nr9 3np",
    "addr:street":"Norwich Norfolk",
    "iso:country":"GB",
    "sg:address":"Beckhithe",
    "sg:city":"Norwich",
    "sg:classifiers":[
        {
            "category":"Manufacturing",
            "subcategory":"Building Materials",
            "type":"Manufacturing & Wholesale Goods"
        }
    ],
    "sg:phone":"+44 1603 810394",
    "sg:postcode":"NR9 3NP",
    "sg:province":"Norfolk",
    "sg:tags":[
        "concrete",
        "product"
    ],
    "wof:name":"Cement Craft",
    "wof:placetype":"venue"
},
  "geometry": {"coordinates":[1.1802799702,52.6119613647],"type":"Point"}
}