{
  "type": "Feature",
  "properties": {
    "iso:country":"GB",
    "sg:address":"Horbour Street",
    "sg:city":"Tarbert",
    "sg:classifiers":[
        {
            "category":"Manufacturing",
            "subcategory":"Watercraft",
            "type":"Manufacturing & Wholesale Goods"
        }
    ],
    "sg:phone":"+44 1880 820180",
    "sg:postcode":"PA29 6UD",
    "sg:province":"Argyll and Bute",
    "sg:tags":[
        "repair",
        "ship",
        "builder"
    ],
    "wof:name":"J S B (Tarbert) Ltd.",
    "wof:placetype":"venue"
},
  "geometry": {"coordinates":[-5.41655,55.863384],"type":"Point"}
}