{
  "type": "Feature",
  "properties": {
    "addr:full":"132 Hither Green Lane, Lewisham London Greater London SE13 6QA",
    "addr:housenumber":"132",
    "addr:postcode":"se13 6qa",
    "addr:street":"Hither Green Lane",
    "iso:country":"GB",
    "sg:address":"132 Hither Green Lane, Lewisham",
    "sg:city":"London",
    "sg:classifiers":[
        {
            "category":"Sports & Exercise",
            "subcategory":"Tennis Court",
            "type":"Entertainment"
        }
    ],
    "sg:phone":"+44 20 8852 8919",
    "sg:postcode":"SE13 6QA",
    "sg:province":"Greater London",
    "sg:tags":[
        "breakdown",
        "recovery"
    ],
    "wof:name":"P A C Motors & Recovery",
    "wof:placetype":"venue"
},
  "geometry": {"coordinates":[-0.008089,51.45319],"type":"Point"}
}