{
  "type": "Feature",
  "properties": {
    "addr:full":"298 Kilburn High Road London Greater London NW6 2DB",
    "addr:housenumber":"298",
    "addr:postcode":"nw6 2db",
    "addr:street":"Kilburn High Road",
    "iso:country":"GB",
    "sg:address":"298 Kilburn High Road",
    "sg:city":"London",
    "sg:classifiers":[
        {
            "category":"Shopping",
            "subcategory":"Department Store",
            "type":"Retail Goods"
        }
    ],
    "sg:phone":"+44 20 7624 4175",
    "sg:postcode":"NW6 2DB",
    "sg:province":"Greater London",
    "wof:name":"Mayfair Jewellers Ltd.",
    "wof:placetype":"venue"
},
  "geometry": {"coordinates":[-0.19997,51.543747],"type":"Point"}
}