{
  "type": "Feature",
  "properties": {
    "addr:full":"Salisbury Road, Abbotts Ann Andover Hampshire SP11 7NX",
    "addr:postcode":"sp11 7nx",
    "addr:street":"Salisbury Road",
    "iso:country":"GB",
    "sg:address":"Salisbury Road, Abbotts Ann",
    "sg:city":"Andover",
    "sg:classifiers":[
        {
            "category":"Professional",
            "subcategory":"Engineering",
            "type":"Services"
        }
    ],
    "sg:phone":"+44 1264 710367",
    "sg:postcode":"SP11 7NX",
    "sg:province":"Hampshire",
    "wof:name":"Dell Engineering Ltd.",
    "wof:placetype":"venue"
},
  "geometry": {"coordinates":[-1.5311080217,51.1912574768],"type":"Point"}
}