{
  "type": "Feature",
  "properties": {
    "addr:full":"Chichest College, Avenue De Chartres, Avenue De Chartres Chichester West Sussex PO19 1SB",
    "addr:postcode":"po19 1sb",
    "addr:street":"College Avenue De Chartres Avenue De Chartres",
    "iso:country":"GB",
    "sg:address":"Chichest College, Avenue De Chartres, Avenue De Chartres",
    "sg:city":"Chichester",
    "sg:classifiers":[
        {
            "category":"Travel",
            "subcategory":"Travel Agent",
            "type":"Entertainment"
        }
    ],
    "sg:postcode":"PO19 1SB",
    "sg:province":"West Sussex",
    "wof:name":"College Travel",
    "wof:placetype":"venue"
},
  "geometry": {"coordinates":[-0.775429,50.836166],"type":"Point"}
}