{
  "type": "Feature",
  "properties": {
    "addr:full":"36 Front Street, Portesham Weymouth Dorset DT3 4ET",
    "addr:housenumber":"36",
    "addr:postcode":"dt3 4et",
    "addr:street":"Front Street",
    "iso:country":"GB",
    "sg:address":"36 Front Street, Portesham",
    "sg:city":"Weymouth",
    "sg:classifiers":[
        {
            "category":"Government",
            "subcategory":"Post Office",
            "type":"Public Place"
        }
    ],
    "sg:phone":"+44 1305 871278",
    "sg:postcode":"DT3 4ET",
    "sg:province":"Dorset",
    "wof:name":"Portesham Post Office Stores",
    "wof:placetype":"venue"
},
  "geometry": {"coordinates":[-2.5634980202,50.6712646484],"type":"Point"}
}