{
  "type": "Feature",
  "properties": {
    "addr:full":"33 Alma Street Taunton Somerset TA1 3AJ",
    "addr:housenumber":"33",
    "addr:postcode":"ta1 3aj",
    "addr:street":"Alma Street",
    "iso:country":"GB",
    "sg:address":"33 Alma Street",
    "sg:city":"Taunton",
    "sg:classifiers":[
        {
            "category":"Professional",
            "subcategory":"Lawyer & Legal Services",
            "type":"Services"
        },
        {
            "category":"Real Estate",
            "subcategory":"Real Estate Agent",
            "type":"Services"
        }
    ],
    "sg:phone":"+44 1823 274568",
    "sg:postcode":"TA1 3AJ",
    "sg:province":"Somerset",
    "sg:tags":[
        "writing"
    ],
    "wof:name":"Will Power",
    "wof:placetype":"venue"
},
  "geometry": {"coordinates":[-3.094796896,51.0140228271],"type":"Point"}
}