{
  "type": "Feature",
  "properties": {
    "addr:full":"Unit 2 Shaw House, Shawclough Trading Estate Rochdale Lancashire OL12 6ND",
    "addr:housenumber":"unit 2",
    "addr:postcode":"ol12 6nd",
    "addr:street":"Shaw;Rochdale",
    "iso:country":"GB",
    "sg:address":"Unit 2 Shaw House, Shawclough Trading Estate",
    "sg:city":"Rochdale",
    "sg:classifiers":[
        {
            "category":"Home & Garden",
            "subcategory":"Home Furnishings",
            "type":"Retail Goods"
        }
    ],
    "sg:postcode":"OL12 6ND",
    "sg:province":"Lancashire",
    "sg:tags":[
        "mantelpiece",
        "fireplace"
    ],
    "wof:name":"Elegant Fireplaces",
    "wof:placetype":"venue"
},
  "geometry": {"coordinates":[-2.1627659798,53.6190071106],"type":"Point"}
}