{
  "type": "Feature",
  "properties": {
    "iso:country":"GB",
    "sg:address":"1 Owler Ings Road",
    "sg:city":"Brighouse",
    "sg:classifiers":[
        {
            "category":"Home & Garden",
            "subcategory":"Carpets & Floor Coverings",
            "type":"Retail Goods"
        }
    ],
    "sg:phone":"+44 1484 400820",
    "sg:postcode":"HD6 1EJ",
    "sg:province":"West Yorkshire",
    "sg:tags":[
        "carpets",
        "rug",
        "matting"
    ],
    "wof:name":"The Carpet Emporium",
    "wof:placetype":"venue"
},
  "geometry": {"coordinates":[-1.784694,53.701317],"type":"Point"}
}