{
  "type": "Feature",
  "properties": {
    "iso:country":"GB",
    "sg:address":"Lichfield Rd",
    "sg:city":"Cannock",
    "sg:classifiers":[
        {
            "category":"Restaurant",
            "type":"Food & Drink"
        }
    ],
    "sg:phone":"+44 1543 466770",
    "sg:postcode":"WS11 3EE",
    "sg:province":"Staffordshire",
    "wof:name":"Mill Farm Toby Carvery",
    "wof:placetype":"venue"
},
  "geometry": {"coordinates":[-2.0177400112,52.686668396],"type":"Point"}
}