{
  "type": "Feature",
  "properties": {
    "addr:full":"Graphic House, 152/154 High Street Rayleigh Essex SS9 5BS",
    "addr:housenumber":"152 / 154",
    "addr:postcode":"ss9 5bs",
    "addr:street":"High Street Rayleigh",
    "iso:country":"GB",
    "sg:address":"Graphic House, 152/154 High Street",
    "sg:city":"Rayleigh",
    "sg:classifiers":[
        {
            "category":"Professional",
            "subcategory":"Business Services",
            "type":"Services"
        }
    ],
    "sg:phone":"+44 1268 741124",
    "sg:postcode":"SS9 5BS",
    "sg:province":"Essex",
    "sg:tags":[
        "tile",
        "stockist"
    ],
    "wof:name":"Essex Tile Design Ltd.",
    "wof:placetype":"venue"
},
  "geometry": {"coordinates":[0.602666,51.584507],"type":"Point"}
}