{
  "type": "Feature",
  "properties": {
    "iso:country":"GB",
    "sg:address":"112 Victoria Dock Road",
    "sg:city":"London",
    "sg:classifiers":[
        {
            "category":"Shopping",
            "subcategory":"Clothing, Apparel, & Fashions",
            "type":"Retail Goods"
        },
        {
            "category":"Manufacturing",
            "subcategory":"Paper Products",
            "type":"Manufacturing & Wholesale Goods"
        }
    ],
    "sg:phone":"+44 20 7511 5775",
    "sg:postcode":"E16 1DA",
    "sg:province":"Greater London",
    "sg:tags":[
        "t-shirt",
        "shirt",
        "manufacturer"
    ],
    "wof:name":"T C B Inc Merchandise",
    "wof:placetype":"venue"
},
  "geometry": {"coordinates":[0.011814,51.510117],"type":"Point"}
}