{
  "type": "Feature",
  "properties": {
    "iso:country":"GB",
    "sg:address":"36 Union Street",
    "sg:city":"Ryde",
    "sg:classifiers":[
        {
            "category":"Professional",
            "subcategory":"Business Services",
            "type":"Services"
        }
    ],
    "sg:phone":"+44 1983 613913",
    "sg:postcode":"PO33 2LE",
    "sg:province":"Isle of Wight",
    "sg:tags":[
        "bookmaker"
    ],
    "wof:name":"Jennings Racing Ltd.",
    "wof:placetype":"venue"
},
  "geometry": {"coordinates":[-1.162298,50.730419],"type":"Point"}
}