{
  "type": "Feature",
  "properties": {
    "addr:full":"9 Forge Corner, Blaby Leicester Leicestershire LE8 4FZ",
    "addr:housenumber":"9",
    "addr:postcode":"le8 4fz",
    "addr:street":"Forge Corner",
    "iso:country":"GB",
    "sg:address":"9 Forge Corner, Blaby",
    "sg:city":"Leicester",
    "sg:classifiers":[
        {
            "category":"Real Estate",
            "subcategory":"Real Estate Agent",
            "type":"Services"
        }
    ],
    "sg:phone":"+44 116 277 7159",
    "sg:postcode":"LE8 4FZ",
    "sg:province":"Leicestershire",
    "wof:name":"Halifax Property Services",
    "wof:placetype":"venue"
},
  "geometry": {"coordinates":[-1.1638629436,52.5757522583],"type":"Point"}
}