{
  "type": "Feature",
  "properties": {
    "iso:country":"GB",
    "sg:address":"Po Box 3020",
    "sg:city":"Barnet",
    "sg:classifiers":[
        {
            "category":"Professional",
            "subcategory":"Detective & Security Services",
            "type":"Services"
        },
        {
            "category":"Building & Trades",
            "subcategory":"Locksmith",
            "type":"Services"
        }
    ],
    "sg:phone":"+44 20 8275 5360",
    "sg:postcode":"EN4 8ZP",
    "sg:province":"Hertfordshire",
    "wof:name":"Ammerhurst Ltd.",
    "wof:placetype":"venue"
},
  "geometry": {"coordinates":[-0.156919,51.641361],"type":"Point"}
}