{
  "type": "Feature",
  "properties": {
    "addr:full":"Grieves Building Houghton-le-spring Durham DH4 7AU",
    "addr:postcode":"dh4 7au",
    "iso:country":"GB",
    "sg:address":"Grieves Building",
    "sg:city":"Houghton-le-spring",
    "sg:classifiers":[
        {
            "category":"Government",
            "subcategory":"Post Office",
            "type":"Public Place"
        }
    ],
    "sg:phone":"+44 191 584 2132",
    "sg:postcode":"DH4 7AU",
    "sg:province":"Durham",
    "wof:name":"New Herrington Post Office",
    "wof:placetype":"venue"
},
  "geometry": {"coordinates":[-1.4798699617,54.868850708],"type":"Point"}
}