{
  "type": "Feature",
  "properties": {
    "addr:full":"42 Alie Street London Greater London E1 8DA",
    "addr:housenumber":"42",
    "addr:postcode":"e1 8da",
    "addr:street":"Alie Street",
    "iso:country":"GB",
    "sg:address":"42 Alie Street",
    "sg:city":"London",
    "sg:classifiers":[
        {
            "category":"Real Estate",
            "subcategory":"Developer",
            "type":"Services"
        }
    ],
    "sg:postcode":"E1 8DA",
    "sg:province":"Greater London",
    "sg:tags":[
        "property"
    ],
    "wof:name":"Maxiacre Limited",
    "wof:placetype":"venue"
},
  "geometry": {"coordinates":[-0.0708979964,51.5136947632],"type":"Point"}
}