{
  "type": "Feature",
  "properties": {
    "iso:country":"GB",
    "sg:address":"47 Goodge St",
    "sg:city":"West End",
    "sg:classifiers":[
        {
            "category":"Fast Food",
            "type":"Food & Drink"
        }
    ],
    "sg:phone":"+44 20 7323 3381",
    "sg:postcode":"W1P 1FB",
    "sg:province":"Hampshire",
    "sg:tags":[
        "away",
        "take"
    ],
    "wof:name":"Crazy Salads",
    "wof:placetype":"venue"
},
  "geometry": {"coordinates":[-0.1358249933,51.5191802979],"type":"Point"}
}