{
  "type": "Feature",
  "properties": {
    "addr:full":"Whitmore Road Blaydon-on-tyne Tyne and Wear NE21 4AN",
    "addr:postcode":"ne21 4an",
    "addr:street":"Whitmore Road",
    "iso:country":"GB",
    "sg:address":"Whitmore Road",
    "sg:city":"Blaydon-on-tyne",
    "sg:classifiers":[
        {
            "category":"Health Services",
            "subcategory":"Nursing And Care Facility",
            "type":"Services"
        }
    ],
    "sg:phone":"+44 191 414 8374",
    "sg:postcode":"NE21 4AN",
    "sg:province":"Tyne and Wear",
    "sg:tags":[
        "home"
    ],
    "wof:name":"MENTAL HEALTH CONCERN",
    "wof:placetype":"venue"
},
  "geometry": {"coordinates":[-1.71622,54.964588],"type":"Point"}
}