{
  "type": "Feature",
  "properties": {
    "addr:full":"64 High Street Eyemouth Scottish Borders TD14 5EU",
    "addr:housenumber":"64",
    "addr:postcode":"td14 5eu",
    "addr:street":"High Street",
    "iso:country":"GB",
    "sg:address":"64 High Street",
    "sg:city":"Eyemouth",
    "sg:classifiers":[
        {
            "category":"Farming",
            "subcategory":"Fish & Marine Products",
            "type":"Manufacturing & Wholesale Goods"
        },
        {
            "category":"Wholesale",
            "subcategory":"Seafood",
            "type":"Manufacturing & Wholesale Goods"
        }
    ],
    "sg:phone":"+44 1890 752538",
    "sg:postcode":"TD14 5EU",
    "sg:province":"Scottish Borders",
    "sg:tags":[
        "merchant",
        "fishmonger"
    ],
    "wof:name":"David Dougal & Son",
    "wof:placetype":"venue"
},
  "geometry": {"coordinates":[-2.0926039219,55.8733711243],"type":"Point"}
}