{
  "type": "Feature",
  "properties": {
    "addr:full":"Edge Lane Street, Royton Oldham Lancashire OL2 6DX",
    "addr:postcode":"ol2 6dx",
    "addr:street":"Edge Lane Street",
    "iso:country":"GB",
    "sg:address":"Edge Lane Street, Royton",
    "sg:city":"Oldham",
    "sg:classifiers":[
        {
            "category":"Manufacturing",
            "subcategory":"Buildings",
            "type":"Manufacturing & Wholesale Goods"
        }
    ],
    "sg:phone":"+44 161 627 5111",
    "sg:postcode":"OL2 6DX",
    "sg:province":"Lancashire",
    "sg:tags":[
        "portable"
    ],
    "sg:website":"http://www.portakabin.com",
    "wof:name":"Portakabin Ltd",
    "wof:placetype":"venue"
},
  "geometry": {"coordinates":[-2.1155939102,53.5646934509],"type":"Point"}
}