{
  "type": "Feature",
  "properties": {
    "addr:full":"74 Leicester Road, Glen Parva Leicester Leicestershire LE2 9HE",
    "addr:housenumber":"74",
    "addr:postcode":"le2 9he",
    "addr:street":"Leicester Road",
    "iso:country":"GB",
    "sg:address":"74 Leicester Road, Glen Parva",
    "sg:city":"Leicester",
    "sg:classifiers":[
        {
            "category":"Building & Trades",
            "subcategory":"Construction",
            "type":"Services"
        }
    ],
    "sg:phone":"+44 116 277 2736",
    "sg:postcode":"LE2 9HE",
    "sg:province":"Leicestershire",
    "sg:tags":[
        "tiling",
        "contractor"
    ],
    "wof:name":"George Smith",
    "wof:placetype":"venue"
},
  "geometry": {"coordinates":[-1.162977,52.583069],"type":"Point"}
}