{
  "type": "Feature",
  "properties": {
    "iso:country":"GB",
    "sg:address":"15-17 Cardiff Rd",
    "sg:city":"Luton",
    "sg:classifiers":[
        {
            "category":"Health Services",
            "subcategory":"Clinic",
            "type":"Services"
        }
    ],
    "sg:phone":"+44 1582 414480",
    "sg:postcode":"LU1 1PP",
    "sg:province":"Bedfordshire",
    "sg:tags":[
        "abuse",
        "drug"
    ],
    "wof:name":"SOBEDAS (South Bedfordshire Drug & Alcohol Service)",
    "wof:placetype":"venue"
},
  "geometry": {"coordinates":[-0.4221689999,51.8793640137],"type":"Point"}
}