{
  "type": "Feature",
  "properties": {
    "iso:country":"GB",
    "sg:address":"14a Martins Yard, Spencer Bridge Road",
    "sg:city":"Northampton",
    "sg:classifiers":[
        {
            "category":"Wholesale",
            "subcategory":"Scrap",
            "type":"Manufacturing & Wholesale Goods"
        }
    ],
    "sg:phone":"+44 1604 631001",
    "sg:postcode":"NN5 7DU",
    "sg:province":"Northamptonshire",
    "sg:tags":[
        "breaker",
        "dismantlers"
    ],
    "wof:name":"Northampton Vehicle Dismantlers",
    "wof:placetype":"venue"
},
  "geometry": {"coordinates":[-0.915824,52.241425],"type":"Point"}
}