{
  "type": "Feature",
  "properties": {
    "addr:full":"11 Richmond Road Pembroke Dock Pembrokeshire SA72 6TZ",
    "addr:housenumber":"11",
    "addr:postcode":"sa72 6tz",
    "addr:street":"Richmond Road",
    "iso:country":"GB",
    "sg:address":"11 Richmond Road",
    "sg:city":"Pembroke Dock",
    "sg:classifiers":[
        {
            "category":"Retail",
            "subcategory":"Auto Repair",
            "type":"Services"
        }
    ],
    "sg:postcode":"SA72 6TZ",
    "sg:province":"Pembrokeshire",
    "sg:tags":[
        "modification",
        "garage"
    ],
    "wof:name":"Giles Beck Sports Cars",
    "wof:placetype":"venue"
},
  "geometry": {"coordinates":[-4.9389309883,51.6991081238],"type":"Point"}
}