{
  "type": "Feature",
  "properties": {
    "iso:country":"GB",
    "sg:address":"63 Hampton Court Way",
    "sg:city":"Thames Ditton",
    "sg:classifiers":[
        {
            "category":"Government",
            "subcategory":"Office",
            "type":"Public Place"
        }
    ],
    "sg:phone":"+44 20 8398 4066",
    "sg:postcode":"KT7 0LT",
    "sg:province":"Surrey",
    "sg:tags":[
        "chamber",
        "commerce"
    ],
    "wof:name":"Health Food Manufacturers Association",
    "wof:placetype":"venue"
},
  "geometry": {"coordinates":[-0.346989,51.386204],"type":"Point"}
}