{
  "type": "Feature",
  "properties": {
    "iso:country":"GB",
    "sg:address":"50 Malden Rd",
    "sg:city":"Kentish Town",
    "sg:classifiers":[
        {
            "category":"Health Services",
            "subcategory":"Dentist",
            "type":"Services"
        }
    ],
    "sg:phone":"+44 20 7284 2523",
    "sg:postcode":"NW5 3HG",
    "sg:province":"Greater London",
    "wof:name":"I Brett",
    "wof:placetype":"venue"
},
  "geometry": {"coordinates":[-0.152039,51.547821],"type":"Point"}
}