{
  "type": "Feature",
  "properties": {
    "addr:full":"21 George Street Hove East Sussex BN3 3YA",
    "addr:housenumber":"21",
    "addr:postcode":"bn3 3ya",
    "addr:street":"George Street",
    "iso:country":"GB",
    "sg:address":"21 George Street",
    "sg:city":"Hove",
    "sg:classifiers":[
        {
            "category":"Food & Beverages",
            "subcategory":"Bakery",
            "type":"Retail Goods"
        }
    ],
    "sg:phone":"+44 1273 739366",
    "sg:postcode":"BN3 3YA",
    "sg:province":"East Sussex",
    "sg:tags":[
        "baker"
    ],
    "wof:name":"Regency Bakery Ltd.",
    "wof:placetype":"venue"
},
  "geometry": {"coordinates":[-0.1734540015,50.8292121887],"type":"Point"}
}