{
  "type": "Feature",
  "properties": {
    "iso:country":"GB",
    "sg:address":"1 St Johns Close, Hall Road",
    "sg:city":"Norwich",
    "sg:classifiers":[
        {
            "category":"Shopping",
            "subcategory":"Beauty & Cosmetics",
            "type":"Retail Goods"
        }
    ],
    "sg:postcode":"NR1 2AD",
    "sg:province":"Norfolk",
    "sg:tags":[
        "wig",
        "hairpiece"
    ],
    "wof:name":"Dorsert Wig Co.",
    "wof:placetype":"venue"
},
  "geometry": {"coordinates":[1.294397,52.614117],"type":"Point"}
}