{
  "type": "Feature",
  "properties": {
    "iso:country":"GB",
    "sg:address":"White Gate House, 52 Fishergate",
    "sg:city":"Norwich",
    "sg:classifiers":[
        {
            "category":"Professional",
            "type":"Services"
        }
    ],
    "sg:phone":"+44 1603 616426",
    "sg:postcode":"NR3 1SE",
    "sg:province":"Norfolk",
    "sg:tags":[
        "auctioneer"
    ],
    "wof:name":"Phillips Auctioneers",
    "wof:placetype":"venue"
},
  "geometry": {"coordinates":[1.299449,52.634296],"type":"Point"}
}