{
  "type": "Feature",
  "properties": {
    "addr:full":"The Old Forge, High Street, Haversham Milton Keynes Buckinghamshire MK19 7DT",
    "addr:postcode":"mk19 7dt",
    "addr:street":"High Street",
    "iso:country":"GB",
    "sg:address":"The Old Forge, High Street, Haversham",
    "sg:city":"Milton Keynes",
    "sg:classifiers":[
        {
            "category":"Professional",
            "subcategory":"Management & Consulting",
            "type":"Services"
        },
        {
            "category":"Professional",
            "subcategory":"Research",
            "type":"Services"
        }
    ],
    "sg:phone":"+44 1908 225165",
    "sg:postcode":"MK19 7DT",
    "sg:province":"Buckinghamshire",
    "sg:tags":[
        "consultant",
        "market",
        "business"
    ],
    "wof:name":"QUALITY AUDIT SERVICES LTD",
    "wof:placetype":"venue"
},
  "geometry": {"coordinates":[-0.8057140112,52.0764579773],"type":"Point"}
}