{
  "type": "Feature",
  "properties": {
    "addr:full":"Stable Ct, Huddersfield Rd Huddersfield West Yorkshire HD7 1AZ",
    "addr:postcode":"hd7 1az",
    "addr:street":"Stable Ct Huddersfield Rd",
    "iso:country":"GB",
    "sg:address":"Stable Ct, Huddersfield Rd",
    "sg:city":"Huddersfield",
    "sg:classifiers":[
        {
            "category":"Health Services",
            "subcategory":"Dentist",
            "type":"Services"
        }
    ],
    "sg:phone":"+44 1484 688770",
    "sg:postcode":"HD7 1AZ",
    "sg:province":"West Yorkshire",
    "wof:name":"Mrs G Owen",
    "wof:placetype":"venue"
},
  "geometry": {"coordinates":[-1.78268,53.64695],"type":"Point"}
}