{
  "type": "Feature",
  "properties": {
    "addr:full":"Brechin Post Office, 22 Clerk Street Brechin Aberdeenshire DD9 6AA",
    "addr:housenumber":"22",
    "addr:postcode":"dd9 6aa",
    "addr:street":"Clerk Street",
    "iso:country":"GB",
    "sg:address":"Brechin Post Office, 22 Clerk Street",
    "sg:city":"Brechin",
    "sg:classifiers":[
        {
            "category":"Personal",
            "type":"Services"
        }
    ],
    "sg:phone":"+44 1356 625465",
    "sg:postcode":"DD9 6AA",
    "sg:province":"Aberdeenshire",
    "sg:tags":[
        "delivery"
    ],
    "wof:name":"The Post Office",
    "wof:placetype":"venue"
},
  "geometry": {"coordinates":[-2.6815040112,56.7536048889],"type":"Point"}
}