{
  "type": "Feature",
  "properties": {
    "iso:country":"GB",
    "sg:address":"470 Thornton Rd",
    "sg:city":"Bradford",
    "sg:classifiers":[
        {
            "category":"Building & Trades",
            "subcategory":"Cleaning & Sanitation",
            "type":"Services"
        }
    ],
    "sg:phone":"+44 1274 780444",
    "sg:postcode":"BD8 9BS",
    "sg:province":"West Yorkshire",
    "sg:tags":[
        "hygiene",
        "cleansing"
    ],
    "wof:name":"Local Hygiene",
    "wof:placetype":"venue"
},
  "geometry": {"coordinates":[-1.783574,53.79921],"type":"Point"}
}