{
  "type": "Feature",
  "properties": {
    "addr:full":"Philipots Quarry,, West Hoathley East Grinstead East Sussex RH19 4PS",
    "addr:postcode":"rh19 4ps",
    "addr:street":"Philipots Quarry West Hoathley",
    "iso:country":"GB",
    "sg:address":"Philipots Quarry,, West Hoathley",
    "sg:city":"East Grinstead",
    "sg:classifiers":[
        {
            "category":"Manufacturing",
            "subcategory":"Wood Products",
            "type":"Manufacturing & Wholesale Goods"
        }
    ],
    "sg:postcode":"RH19 4PS",
    "sg:province":"East Sussex",
    "sg:tags":[
        "stone"
    ],
    "wof:name":"Philpots Quarry Ltd",
    "wof:placetype":"venue"
},
  "geometry": {"coordinates":[-0.0638099983,51.0746688843],"type":"Point"}
}