{
  "type": "Feature",
  "properties": {
    "iso:country":"GB",
    "sg:address":"Po Box 9",
    "sg:city":"Teignmouth",
    "sg:classifiers":[
        {
            "category":"Professional",
            "subcategory":"Computer Services",
            "type":"Services"
        }
    ],
    "sg:phone":"+44 1626 775599",
    "sg:postcode":"TQ14 8YA",
    "sg:province":"Devon",
    "sg:tags":[
        "consultant"
    ],
    "wof:name":"Derrick Boey & Associates",
    "wof:placetype":"venue"
},
  "geometry": {"coordinates":[-3.500104,50.548344],"type":"Point"}
}