{
  "type": "Feature",
  "properties": {
    "addr:full":"Sheaf Plate Works, Arundel Street Sheffield South Yorkshire S1 1DJ",
    "addr:postcode":"s1 1dj",
    "addr:street":"Arundel Street",
    "iso:country":"GB",
    "sg:address":"Sheaf Plate Works, Arundel Street",
    "sg:city":"Sheffield",
    "sg:classifiers":[
        {
            "category":"Professional",
            "subcategory":"Printing & Photocopies",
            "type":"Services"
        }
    ],
    "sg:phone":"+44 114 273 7715",
    "sg:postcode":"S1 1DJ",
    "sg:province":"South Yorkshire",
    "sg:tags":[
        "plate",
        "lithographic",
        "maker"
    ],
    "wof:name":"M T Marsden",
    "wof:placetype":"venue"
},
  "geometry": {"coordinates":[-1.4645440578,53.3831100464],"type":"Point"}
}