{
  "type": "Feature",
  "properties": {
    "addr:full":"195 Galmington Road Taunton Somerset TA1 4SS",
    "addr:housenumber":"195",
    "addr:postcode":"ta1 4ss",
    "addr:street":"Galmington Road",
    "iso:country":"GB",
    "sg:address":"195 Galmington Road",
    "sg:city":"Taunton",
    "sg:classifiers":[
        {
            "category":"Retail",
            "subcategory":"Laundry & Dry Cleaning",
            "type":"Services"
        }
    ],
    "sg:phone":"+44 1823 331122",
    "sg:postcode":"TA1 4SS",
    "sg:province":"Somerset",
    "sg:tags":[
        "alteration"
    ],
    "wof:name":"Galmington Dry Cleaners",
    "wof:placetype":"venue"
},
  "geometry": {"coordinates":[-3.1175680161,51.0078315735],"type":"Point"}
}