{
  "type": "Feature",
  "properties": {
    "addr:full":"102 Mount Pleasant Redditch Warwickshire B97 4JH",
    "addr:housenumber":"102",
    "addr:postcode":"b97 4jh",
    "addr:street":"Mount Pleasant",
    "iso:country":"GB",
    "sg:address":"102 Mount Pleasant",
    "sg:city":"Redditch",
    "sg:classifiers":[
        {
            "category":"Bars & Pubs",
            "type":"Food & Drink"
        },
        {
            "category":"Shopping",
            "subcategory":"Gifts & Souvenirs",
            "type":"Retail Goods"
        },
        {
            "category":"Community Center",
            "subcategory":"Social",
            "type":"Public Place"
        }
    ],
    "sg:phone":"+44 1527 402299",
    "sg:postcode":"B97 4JH",
    "sg:province":"Warwickshire",
    "sg:tags":[
        "pubs",
        "giftware",
        "inn",
        "activity",
        "house"
    ],
    "wof:name":"The Woodland Cottage",
    "wof:placetype":"venue"
},
  "geometry": {"coordinates":[-1.9438,52.300545],"type":"Point"}
}