{
  "type": "Feature",
  "properties": {
    "iso:country":"GB",
    "sg:address":"Village Square, Willaston, Neston",
    "sg:city":"Wirral",
    "sg:classifiers":[
        {
            "category":"Travel",
            "subcategory":"Hotels & Motels",
            "type":"Entertainment"
        }
    ],
    "sg:postcode":"CH64 2TU",
    "sg:province":"Cheshire",
    "wof:name":"Pollards Hotel & Restaurant",
    "wof:placetype":"venue"
},
  "geometry": {"coordinates":[-3.007074,53.29232],"type":"Point"}
}