{
  "type": "Feature",
  "properties": {
    "addr:full":"12 Summit Littleborough Lancashire OL15 9QW",
    "addr:housenumber":"12",
    "addr:postcode":"ol15 9qw",
    "addr:street":"Summit Littleborough",
    "iso:country":"GB",
    "sg:address":"12 Summit",
    "sg:city":"Littleborough",
    "sg:classifiers":[
        {
            "category":"Bars & Pubs",
            "type":"Food & Drink"
        }
    ],
    "sg:phone":"+44 1706 377741",
    "sg:postcode":"OL15 9QW",
    "sg:province":"Lancashire",
    "sg:tags":[
        "pubs",
        "inn"
    ],
    "wof:name":"The Sportsman's Rest",
    "wof:placetype":"venue"
},
  "geometry": {"coordinates":[-2.0828809738,53.6609725952],"type":"Point"}
}