{
  "type": "Feature",
  "properties": {
    "addr:full":"292 Victoria Road East Leicester Leicestershire LE5 0LF",
    "addr:housenumber":"292",
    "addr:postcode":"le5 0lf",
    "addr:street":"Victoria Road",
    "iso:country":"GB",
    "sg:address":"292 Victoria Road East",
    "sg:city":"Leicester",
    "sg:classifiers":[
        {
            "category":"Building & Trades",
            "subcategory":"Landscaping Services",
            "type":"Services"
        },
        {
            "category":"Autos & Motor Vehicles",
            "subcategory":"Auto Supplies",
            "type":"Retail Goods"
        }
    ],
    "sg:phone":"+44 116 274 0557",
    "sg:postcode":"LE5 0LF",
    "sg:province":"Leicestershire",
    "sg:tags":[
        "gardening",
        "component"
    ],
    "wof:name":"Victoria Garden Services Ltd.",
    "wof:placetype":"venue"
},
  "geometry": {"coordinates":[-1.0954420567,52.6483612061],"type":"Point"}
}