{
  "type": "Feature",
  "properties": {
    "addr:full":"1 Springhouse Shops, High Street Hythe Kent CT21 5LL",
    "addr:housenumber":"1",
    "addr:postcode":"ct21 5ll",
    "addr:street":"High Street",
    "iso:country":"GB",
    "sg:address":"1 Springhouse Shops, High Street",
    "sg:city":"Hythe",
    "sg:classifiers":[
        {
            "category":"Shopping",
            "subcategory":"Clothing, Apparel, & Fashions",
            "type":"Retail Goods"
        }
    ],
    "sg:phone":"+44 1303 269191",
    "sg:postcode":"CT21 5LL",
    "sg:province":"Kent",
    "sg:tags":[
        "shop"
    ],
    "wof:name":"Jinti",
    "wof:placetype":"venue"
},
  "geometry": {"coordinates":[1.080481,51.070827],"type":"Point"}
}