{
  "type": "Feature",
  "properties": {
    "addr:full":"Summers Road, Farncombe Godalming Surrey GU7 3BF",
    "addr:postcode":"gu7 3bf",
    "addr:street":"Summers Road",
    "iso:country":"GB",
    "sg:address":"Summers Road, Farncombe",
    "sg:city":"Godalming",
    "sg:classifiers":[
        {
            "category":"Social Services",
            "subcategory":"Retirement Home",
            "type":"Services"
        },
        {
            "category":"Government",
            "subcategory":"Office",
            "type":"Public Place"
        }
    ],
    "sg:phone":"+44 1483 414186",
    "sg:postcode":"GU7 3BF",
    "sg:province":"Surrey",
    "sg:tags":[
        "residential",
        "local",
        "care"
    ],
    "wof:name":"Broadwater Home for the Elderly",
    "wof:placetype":"venue"
},
  "geometry": {"coordinates":[-0.5945240259,51.2019042969],"type":"Point"}
}