{
  "type": "Feature",
  "properties": {
    "addr:full":"143 Camping Hill, Stiffkey Wells-next-the-sea Norfolk NR23 1QL",
    "addr:housenumber":"143",
    "addr:postcode":"nr23 1ql",
    "addr:street":"Camping Hill",
    "iso:country":"GB",
    "sg:address":"143 Camping Hill, Stiffkey",
    "sg:city":"Wells-next-the-sea",
    "sg:classifiers":[
        {
            "category":"Building & Trades",
            "subcategory":"Construction",
            "type":"Services"
        }
    ],
    "sg:postcode":"NR23 1QL",
    "sg:province":"Norfolk",
    "sg:tags":[
        "builder"
    ],
    "wof:name":"J T C Design Services",
    "wof:placetype":"venue"
},
  "geometry": {"coordinates":[0.85581,52.952644],"type":"Point"}
}