{
  "type": "Feature",
  "properties": {
    "addr:full":"22 Bridge Street Wick Highland KW1 4NG",
    "addr:housenumber":"22",
    "addr:postcode":"kw1 4ng",
    "addr:street":"Bridge Street",
    "iso:country":"GB",
    "sg:address":"22 Bridge Street",
    "sg:city":"Wick",
    "sg:classifiers":[
        {
            "category":"Professional",
            "subcategory":"Lawyer & Legal Services",
            "type":"Services"
        }
    ],
    "sg:phone":"+44 1955 606060",
    "sg:postcode":"KW1 4NG",
    "sg:province":"Highland",
    "sg:tags":[
        "solicitor"
    ],
    "wof:name":"D W Georgeson & Son",
    "wof:placetype":"venue"
},
  "geometry": {"coordinates":[-3.0928618908,58.4423675537],"type":"Point"}
}