{
  "type": "Feature",
  "properties": {
    "addr:full":"37-45 Mere Lane Rochdale Lancashire OL11 3TD",
    "addr:housenumber":"37-45",
    "addr:postcode":"ol11 3td",
    "addr:street":"Mere Lane",
    "iso:country":"GB",
    "sg:address":"37-45 Mere Lane",
    "sg:city":"Rochdale",
    "sg:classifiers":[
        {
            "category":"Shopping",
            "subcategory":"Clothing, Apparel, & Fashions",
            "type":"Retail Goods"
        }
    ],
    "sg:postcode":"OL11 3TD",
    "sg:province":"Lancashire",
    "sg:tags":[
        "clothing",
        "fabric"
    ],
    "wof:name":"N R S Fashions Ltd.",
    "wof:placetype":"venue"
},
  "geometry": {"coordinates":[-2.158451,53.608387],"type":"Point"}
}