{
  "type": "Feature",
  "properties": {
    "iso:country":"GB",
    "sg:address":"780 Holloway Rd",
    "sg:city":"London",
    "sg:classifiers":[
        {
            "category":"Professional",
            "subcategory":"Art Services",
            "type":"Services"
        }
    ],
    "sg:postcode":"N19 3JH",
    "sg:province":"Greater London",
    "sg:tags":[
        "photographer"
    ],
    "wof:name":"Ramanah,Kres,",
    "wof:placetype":"venue"
},
  "geometry": {"coordinates":[-0.132704,51.565018],"type":"Point"}
}