{
  "type": "Feature",
  "properties": {
    "addr:full":"5 High Street, Castleton Whitby North Yorkshire YO21 2EE",
    "addr:housenumber":"5",
    "addr:postcode":"yo21 2ee",
    "addr:street":"High Street",
    "iso:country":"GB",
    "sg:address":"5 High Street, Castleton",
    "sg:city":"Whitby",
    "sg:classifiers":[
        {
            "category":"Government",
            "subcategory":"Post Office",
            "type":"Public Place"
        }
    ],
    "sg:phone":"+44 1287 660201",
    "sg:postcode":"YO21 2EE",
    "sg:province":"North Yorkshire",
    "wof:name":"Castleton Post Office",
    "wof:placetype":"venue"
},
  "geometry": {"coordinates":[-0.9406710267,54.4633750916],"type":"Point"}
}