{
  "type": "Feature",
  "properties": {
    "iso:country":"GB",
    "sg:address":"227 Greengate, Middleton",
    "sg:city":"Manchester",
    "sg:classifiers":[
        {
            "category":"Cafe",
            "type":"Food & Drink"
        }
    ],
    "sg:phone":"+44 161 655 3297",
    "sg:postcode":"M24 1RU",
    "sg:province":"Greater Manchester",
    "sg:tags":[
        "tea",
        "snack",
        "bar",
        "room"
    ],
    "wof:name":"The Nook Cafe",
    "wof:placetype":"venue"
},
  "geometry": {"coordinates":[-2.174758,53.533035],"type":"Point"}
}