{
  "type": "Feature",
  "properties": {
    "addr:full":"1 Lime Hill Rd Tunbridge Wells Kent TN1 1LJ",
    "addr:housenumber":"1",
    "addr:postcode":"tn1 1lj",
    "addr:street":"Lime Hill Rd",
    "iso:country":"GB",
    "sg:address":"1 Lime Hill Rd",
    "sg:city":"Tunbridge Wells",
    "sg:classifiers":[
        {
            "category":"Personal",
            "subcategory":"Beauty Salon",
            "type":"Services"
        }
    ],
    "sg:phone":"+44 1892 530436",
    "sg:postcode":"TN1 1LJ",
    "sg:province":"Kent",
    "sg:tags":[
        "lady",
        "hairdresser"
    ],
    "wof:name":"Shaws Ladies Hairdressing Salon",
    "wof:placetype":"venue"
},
  "geometry": {"coordinates":[0.2633700073,51.1343688965],"type":"Point"}
}