{
  "type": "Feature",
  "properties": {
    "addr:full":"171 Gloucester Road, Bishopston Bristol City of Bristol BS7 8BE",
    "addr:housenumber":"171",
    "addr:postcode":"bs7 8be",
    "addr:street":"Gloucester Road",
    "iso:country":"GB",
    "sg:address":"171 Gloucester Road, Bishopston",
    "sg:city":"Bristol",
    "sg:classifiers":[
        {
            "category":"Home & Garden",
            "subcategory":"Household Appliances",
            "type":"Retail Goods"
        }
    ],
    "sg:phone":"+44 117 949 1849",
    "sg:postcode":"BS7 8BE",
    "sg:province":"City of Bristol",
    "sg:tags":[
        "electrical"
    ],
    "wof:name":"Nailsea Electrical Ltd.",
    "wof:placetype":"venue"
},
  "geometry": {"coordinates":[-2.5938549042,51.4699668884],"type":"Point"}
}