{
  "type": "Feature",
  "properties": {
    "iso:country":"GB",
    "sg:address":"Cana Berry Lane",
    "sg:city":"Littlehampton",
    "sg:classifiers":[
        {
            "category":"Shopping",
            "type":"Retail Goods"
        }
    ],
    "sg:phone":"+44 1903 721973",
    "sg:postcode":"BN17 5HD",
    "sg:province":"West Sussex",
    "sg:tags":[
        "med",
        "scientific",
        "apparatus"
    ],
    "wof:name":"Peter Sharp",
    "wof:placetype":"venue"
},
  "geometry": {"coordinates":[-0.530446,50.807674],"type":"Point"}
}