{
  "type": "Feature",
  "properties": {
    "addr:full":"Unit 10 Redstone Indust Est, Redstone Rd Boston Lincolnshire PE21 8EA",
    "addr:housenumber":"unit 10",
    "addr:postcode":"pe21 8ea",
    "addr:street":"Indust Est Redstone Rd",
    "iso:country":"GB",
    "sg:address":"Unit 10 Redstone Indust Est, Redstone Rd",
    "sg:city":"Boston",
    "sg:classifiers":[
        {
            "category":"Shopping",
            "subcategory":"Computers & Home Electronics",
            "type":"Retail Goods"
        }
    ],
    "sg:postcode":"PE21 8EA",
    "sg:province":"Lincolnshire",
    "sg:tags":[
        "sound",
        "equipment"
    ],
    "wof:name":"Gross,David,",
    "wof:placetype":"venue"
},
  "geometry": {"coordinates":[-0.0297219995,52.9679336548],"type":"Point"}
}