{
  "type": "Feature",
  "properties": {
    "addr:full":"59 Sutherland Av Welling Kent DA16 2NN",
    "addr:housenumber":"59",
    "addr:postcode":"da16 2nn",
    "addr:street":"Sutherland Av Welling",
    "iso:country":"GB",
    "sg:address":"59 Sutherland Av",
    "sg:city":"Welling",
    "sg:classifiers":[
        {
            "category":"Building & Trades",
            "subcategory":"Construction",
            "type":"Services"
        }
    ],
    "sg:phone":"+44 20 8301 4517",
    "sg:postcode":"DA16 2NN",
    "sg:province":"Kent",
    "sg:tags":[
        "builder"
    ],
    "wof:name":"A J M & Co",
    "wof:placetype":"venue"
},
  "geometry": {"coordinates":[0.1001060009,51.4537696838],"type":"Point"}
}