{
  "type": "Feature",
  "properties": {
    "iso:country":"GB",
    "sg:address":"23 Clay Lane",
    "sg:city":"Oldbury",
    "sg:classifiers":[
        {
            "category":"Government",
            "subcategory":"Office",
            "type":"Public Place"
        }
    ],
    "sg:phone":"+44 121 552 9930",
    "sg:postcode":"B69 4TH",
    "sg:province":"West Midlands",
    "sg:tags":[
        "central"
    ],
    "wof:name":"Sycamore Lodge Bail Hostel",
    "wof:placetype":"venue"
},
  "geometry": {"coordinates":[-2.013845,52.489151],"type":"Point"}
}