{
  "type": "Feature",
  "properties": {
    "addr:full":"93 Oswald Road, Chorlton Cum Hardy Manchester Cheshire M21 9GE",
    "addr:housenumber":"93",
    "addr:postcode":"m21 9ge",
    "addr:street":"Oswald Road",
    "iso:country":"GB",
    "sg:address":"93 Oswald Road, Chorlton Cum Hardy",
    "sg:city":"Manchester",
    "sg:classifiers":[
        {
            "category":"Government",
            "subcategory":"Post Office",
            "type":"Public Place"
        }
    ],
    "sg:phone":"+44 161 860 7137",
    "sg:postcode":"M21 9GE",
    "sg:province":"Cheshire",
    "sg:tags":[
        "messenger",
        "courier"
    ],
    "wof:name":"A S A P Couriers",
    "wof:placetype":"venue"
},
  "geometry": {"coordinates":[-2.2801780701,53.4467811584],"type":"Point"}
}