{
  "type": "Feature",
  "properties": {
    "iso:country":"GB",
    "sg:address":"16 Strine Close, Wellington",
    "sg:city":"Telford",
    "sg:classifiers":[
        {
            "category":"Building & Trades",
            "subcategory":"Construction",
            "type":"Services"
        }
    ],
    "sg:phone":"+44 1952 247857",
    "sg:postcode":"TF1 3LR",
    "sg:province":"Shropshire",
    "sg:tags":[
        "glazier",
        "decorator",
        "painter"
    ],
    "wof:name":"David John Beamond",
    "wof:placetype":"venue"
},
  "geometry": {"coordinates":[-2.524595,52.708828],"type":"Point"}
}