{
  "type": "Feature",
  "properties": {
    "iso:country":"GB",
    "sg:address":"5 Well Street",
    "sg:city":"Moffat",
    "sg:classifiers":[
        {
            "category":"Food & Beverages",
            "subcategory":"Fruits & Vegetables",
            "type":"Retail Goods"
        },
        {
            "category":"Shopping",
            "subcategory":"Shoes",
            "type":"Retail Goods"
        },
        {
            "category":"Food & Beverages",
            "subcategory":"Groceries & Convenience Stores",
            "type":"Retail Goods"
        }
    ],
    "sg:phone":"+44 1683 220059",
    "sg:postcode":"DG10 9DP",
    "sg:province":"Dumfries and Galloway",
    "sg:tags":[
        "shop",
        "greengrocer"
    ],
    "wof:name":"D & J HUTCHISON",
    "wof:placetype":"venue"
},
  "geometry": {"coordinates":[-3.44363,55.332821],"type":"Point"}
}