{
  "type": "Feature",
  "properties": {
    "iso:country":"GB",
    "sg:address":"Burbush House, Pound Lane, Burley",
    "sg:city":"Ringwood",
    "sg:classifiers":[
        {
            "category":"Professional",
            "subcategory":"Advertising",
            "type":"Services"
        }
    ],
    "sg:postcode":"BH24 4EF",
    "sg:province":"Dorset",
    "sg:tags":[
        "agency"
    ],
    "wof:name":"Generator (Creative Energy) Ltd.",
    "wof:placetype":"venue"
},
  "geometry": {"coordinates":[-1.704309,50.824051],"type":"Point"}
}