{
  "type": "Feature",
  "properties": {
    "addr:full":"14-16 Great Portland Street London Greater London W1W 8QW",
    "addr:housenumber":"14-16",
    "addr:postcode":"w1w 8qw",
    "addr:street":"Great Portland Street",
    "iso:country":"GB",
    "sg:address":"14-16 Great Portland Street",
    "sg:city":"London",
    "sg:classifiers":[
        {
            "category":"Professional",
            "subcategory":"Lawyer & Legal Services",
            "type":"Services"
        }
    ],
    "sg:phone":"+44 20 7323 0100",
    "sg:postcode":"W1W 8QW",
    "sg:province":"Greater London",
    "sg:tags":[
        "solicitor"
    ],
    "wof:name":"Lawrence Stephens",
    "wof:placetype":"venue"
},
  "geometry": {"coordinates":[-0.1408499926,51.5163917542],"type":"Point"}
}