{
  "type": "Feature",
  "properties": {
    "addr:full":"121 Shipston Rd Stratford-upon-avon Warwickshire CV37 7LW",
    "addr:housenumber":"121",
    "addr:postcode":"cv37 7lw",
    "addr:street":"Shipston Rd",
    "iso:country":"GB",
    "sg:address":"121 Shipston Rd",
    "sg:city":"Stratford-upon-avon",
    "sg:classifiers":[
        {
            "category":"Restaurant",
            "type":"Food & Drink"
        }
    ],
    "sg:postcode":"CV37 7LW",
    "sg:province":"Warwickshire",
    "wof:name":"James,Michael,",
    "wof:placetype":"venue"
},
  "geometry": {"coordinates":[-1.700687,52.184433],"type":"Point"}
}