{
  "type": "Feature",
  "properties": {
    "addr:full":"42 Weston Cres Bristol City of Bristol BS7 8UT",
    "addr:housenumber":"42",
    "addr:postcode":"bs7 8ut",
    "addr:street":"Weston Cres",
    "iso:country":"GB",
    "sg:address":"42 Weston Cres",
    "sg:city":"Bristol",
    "sg:classifiers":[
        {
            "category":"Building & Trades",
            "subcategory":"Construction",
            "type":"Services"
        }
    ],
    "sg:phone":"+44 117 951 4290",
    "sg:postcode":"BS7 8UT",
    "sg:province":"City of Bristol",
    "sg:tags":[
        "decorator",
        "painter"
    ],
    "wof:name":"W A E Mizen & Son",
    "wof:placetype":"venue"
},
  "geometry": {"coordinates":[-2.5883591175,51.4881019592],"type":"Point"}
}