{
  "type": "Feature",
  "properties": {
    "iso:country":"GB",
    "sg:address":"Brightowgate Coach Station",
    "sg:city":"Grimsby",
    "sg:classifiers":[
        {
            "category":"Bus Charters",
            "type":"Transportation"
        }
    ],
    "sg:phone":"+44 1472 241133",
    "sg:postcode":"DN32 0QE",
    "sg:province":"Lincolnshire",
    "sg:tags":[
        "hire",
        "coach"
    ],
    "wof:name":"Amvale Coaches",
    "wof:placetype":"venue"
},
  "geometry": {"coordinates":[-0.0886380002,53.562789917],"type":"Point"}
}