{
  "type": "Feature",
  "properties": {
    "iso:country":"GB",
    "sg:address":"126 Dukes Rd",
    "sg:city":"Glasgow",
    "sg:classifiers":[
        {
            "category":"Cinema",
            "subcategory":"Movie Rental",
            "type":"Entertainment"
        }
    ],
    "sg:phone":"+44 141 579 5026",
    "sg:postcode":"G73 5AF",
    "sg:province":"Glasgow City",
    "sg:tags":[
        "video",
        "library"
    ],
    "wof:name":"Universal Home Entertainment",
    "wof:placetype":"venue"
},
  "geometry": {"coordinates":[-4.1913819313,55.818572998],"type":"Point"}
}