{
  "type": "Feature",
  "properties": {
    "addr:full":"821 Osmaston Road Derby Derbyshire DE24 9BQ",
    "addr:housenumber":"821",
    "addr:postcode":"de24 9bq",
    "addr:street":"Osmaston Road",
    "iso:country":"GB",
    "sg:address":"821 Osmaston Road",
    "sg:city":"Derby",
    "sg:classifiers":[
        {
            "category":"Shopping",
            "subcategory":"Florist",
            "type":"Retail Goods"
        }
    ],
    "sg:phone":"+44 1332 340610",
    "sg:postcode":"DE24 9BQ",
    "sg:province":"Derbyshire",
    "wof:name":"SPONDON FLORISTS",
    "wof:placetype":"venue"
},
  "geometry": {"coordinates":[-1.451996,52.890923],"type":"Point"}
}