{
  "type": "Feature",
  "properties": {
    "addr:full":"Unit G Bakers Boatyard, Brickyard Lane Exeter Devon EX6 8SA",
    "addr:housenumber":"unit g",
    "addr:postcode":"ex6 8sa",
    "addr:street":"Brickyard Lane",
    "iso:country":"GB",
    "sg:address":"Unit G Bakers Boatyard, Brickyard Lane",
    "sg:city":"Exeter",
    "sg:classifiers":[
        {
            "category":"Manufacturing",
            "subcategory":"Glass & Minerals",
            "type":"Manufacturing & Wholesale Goods"
        }
    ],
    "sg:phone":"+44 1626 891383",
    "sg:postcode":"EX6 8SA",
    "sg:province":"Devon",
    "sg:tags":[
        "stained"
    ],
    "wof:name":"Peter Baker Art Glass Co",
    "wof:placetype":"venue"
},
  "geometry": {"coordinates":[-3.450979948,50.625869751],"type":"Point"}
}