{
  "type": "Feature",
  "properties": {
    "addr:full":"Old Brickyard Road, Sandleheath Industrial Estate Fordingbridge Dorset SP6 1PA",
    "addr:postcode":"sp6 1pa",
    "addr:street":"Old Brickyard Road;Industrial Estate",
    "iso:country":"GB",
    "sg:address":"Old Brickyard Road, Sandleheath Industrial Estate",
    "sg:city":"Fordingbridge",
    "sg:classifiers":[
        {
            "category":"Professional",
            "subcategory":"Engineering",
            "type":"Services"
        }
    ],
    "sg:phone":"+44 1425 652409",
    "sg:postcode":"SP6 1PA",
    "sg:province":"Dorset",
    "sg:tags":[
        "civil",
        "engineer"
    ],
    "wof:name":"Rockbourne Civil Engineering Ltd.",
    "wof:placetype":"venue"
},
  "geometry": {"coordinates":[-1.820629,50.934029],"type":"Point"}
}