{
  "type": "Feature",
  "properties": {
    "iso:country":"GB",
    "sg:address":"Squire Gate, Nash Grove Lane, Finchampstead",
    "sg:city":"Wokingham",
    "sg:classifiers":[
        {
            "category":"Real Estate",
            "subcategory":"Developer",
            "type":"Services"
        }
    ],
    "sg:phone":"+44 118 973 5833",
    "sg:postcode":"RG40 4HE",
    "sg:province":"Berkshire",
    "sg:tags":[
        "property"
    ],
    "wof:name":"Redrow Homes (Southern) Ltd.",
    "wof:placetype":"venue"
},
  "geometry": {"coordinates":[-0.858299017,51.3851203918],"type":"Point"}
}