{
  "type": "Feature",
  "properties": {
    "addr:full":"8th Floor, Hill House, Highgate Hill London Greater London N19 5NA",
    "addr:housenumber":"8th",
    "addr:postcode":"n19 5na",
    "addr:street":"Floor Hill House Highgate Hill",
    "iso:country":"GB",
    "sg:address":"8th Floor, Hill House, Highgate Hill",
    "sg:city":"London",
    "sg:classifiers":[
        {
            "category":"Professional",
            "subcategory":"Research",
            "type":"Services"
        }
    ],
    "sg:phone":"+44 20 7272 7779",
    "sg:postcode":"N19 5NA",
    "sg:province":"Greater London",
    "sg:tags":[
        "market"
    ],
    "wof:name":"F D S International Ltd.",
    "wof:placetype":"venue"
},
  "geometry": {"coordinates":[-0.1349299997,51.5656700134],"type":"Point"}
}