{
  "type": "Feature",
  "properties": {
    "iso:country":"GB",
    "sg:address":"14a Blackmore Park Indust Estate, Hanley Swan",
    "sg:city":"Worcester",
    "sg:classifiers":[
        {
            "category":"Professional",
            "type":"Services"
        }
    ],
    "sg:phone":"+44 1684 891664",
    "sg:postcode":"WR8 0EF",
    "sg:province":"Gloucestershire",
    "sg:tags":[
        "directory",
        "pub"
    ],
    "wof:name":"R Beard",
    "wof:placetype":"venue"
},
  "geometry": {"coordinates":[-2.2735788822,52.0839118958],"type":"Point"}
}