{
  "type": "Feature",
  "properties": {
    "addr:full":"Shaw Farm, Gratwich Uttoxeter Derbyshire ST14 8SF",
    "addr:postcode":"st14 8sf",
    "addr:street":"Uttoxeter",
    "iso:country":"GB",
    "sg:address":"Shaw Farm, Gratwich",
    "sg:city":"Uttoxeter",
    "sg:classifiers":[
        {
            "category":"Farming",
            "subcategory":"Livestock Farm",
            "type":"Manufacturing & Wholesale Goods"
        }
    ],
    "sg:postcode":"ST14 8SF",
    "sg:province":"Derbyshire",
    "sg:tags":[
        "others"
    ],
    "wof:name":"J W Cotton",
    "wof:placetype":"venue"
},
  "geometry": {"coordinates":[-1.95381,52.881416],"type":"Point"}
}