{
  "type": "Feature",
  "properties": {
    "addr:full":"93 Western Rd Tring Buckinghamshire HP23 4BN",
    "addr:housenumber":"93",
    "addr:postcode":"hp23 4bn",
    "addr:street":"Western Rd",
    "iso:country":"GB",
    "sg:address":"93 Western Rd",
    "sg:city":"Tring",
    "sg:classifiers":[
        {
            "category":"Wholesale",
            "subcategory":"Books, Periodicals, & Newspapers",
            "type":"Manufacturing & Wholesale Goods"
        }
    ],
    "sg:phone":"+44 1442 827499",
    "sg:postcode":"HP23 4BN",
    "sg:province":"Buckinghamshire",
    "sg:tags":[
        "publishing"
    ],
    "wof:name":"Swift Media Services",
    "wof:placetype":"venue"
},
  "geometry": {"coordinates":[-0.6697499752,51.7905769348],"type":"Point"}
}