{
  "type": "Feature",
  "properties": {
    "addr:full":"Torridon Lane,off Grampian Road, Rosyth Dunfermline Fife KY11 2EU",
    "addr:postcode":"ky11 2eu",
    "addr:street":"Torridon Lane Off Grampian Road",
    "iso:country":"GB",
    "sg:address":"Torridon Lane,off Grampian Road, Rosyth",
    "sg:city":"Dunfermline",
    "sg:classifiers":[
        {
            "category":"Real Estate",
            "subcategory":"Architect",
            "type":"Services"
        }
    ],
    "sg:postcode":"KY11 2EU",
    "sg:province":"Fife",
    "wof:name":"Muir Engineering Services Ltd",
    "wof:placetype":"venue"
},
  "geometry": {"coordinates":[-3.426664,56.028687],"type":"Point"}
}