{
  "type": "Feature",
  "properties": {
    "iso:country":"GB",
    "sg:address":"39 Willow Road, Charlton Kings",
    "sg:city":"Cheltenham",
    "sg:classifiers":[
        {
            "category":"Bus Charters",
            "type":"Transportation"
        }
    ],
    "sg:phone":"+44 1242 582747",
    "sg:postcode":"GL53 8PH",
    "sg:province":"Gloucestershire",
    "sg:tags":[
        "mini",
        "hire",
        "leasing"
    ],
    "wof:name":"Acme Roadrunner",
    "wof:placetype":"venue"
},
  "geometry": {"coordinates":[-2.044766,51.879734],"type":"Point"}
}