{
  "type": "Feature",
  "properties": {
    "addr:full":"Park Road, Woodsetton Dudley West Midlands DY1 4JH",
    "addr:postcode":"dy1 4jh",
    "addr:street":"Park Road",
    "iso:country":"GB",
    "sg:address":"Park Road, Woodsetton",
    "sg:city":"Dudley",
    "sg:classifiers":[
        {
            "category":"Bars & Pubs",
            "type":"Food & Drink"
        }
    ],
    "sg:phone":"+44 1902 665105",
    "sg:postcode":"DY1 4JH",
    "sg:province":"West Midlands",
    "sg:tags":[
        "pubs",
        "inn"
    ],
    "wof:name":"The Bramford Arms",
    "wof:placetype":"venue"
},
  "geometry": {"coordinates":[-2.095589,52.535954],"type":"Point"}
}