{
  "type": "Feature",
  "properties": {
    "addr:full":"St James Road, St James Industrial Estate Corby Northamptonshire NN18 8AL",
    "addr:postcode":"nn18 8al",
    "addr:street":"St James Road St;Estate",
    "iso:country":"GB",
    "sg:address":"St James Road, St James Industrial Estate",
    "sg:city":"Corby",
    "sg:classifiers":[
        {
            "category":"Retail",
            "subcategory":"Auto Repair",
            "type":"Services"
        }
    ],
    "sg:phone":"+44 1536 401198",
    "sg:postcode":"NN18 8AL",
    "sg:province":"Northamptonshire",
    "sg:tags":[
        "modification",
        "garage"
    ],
    "wof:name":"Townsmore Cars",
    "wof:placetype":"venue"
},
  "geometry": {"coordinates":[-0.6830400229,52.4870986938],"type":"Point"}
}