{
  "type": "Feature",
  "properties": {
    "addr:full":"Unit 20 Hollygate Industrial Park, Hollygate Lane, Cotgrave Nottingham Nottinghamshire NG12 3JW",
    "addr:housenumber":"unit 20",
    "addr:postcode":"ng12 3jw",
    "addr:street":"Hollygate Industrial Park Hollygate Lane",
    "iso:country":"GB",
    "sg:address":"Unit 20 Hollygate Industrial Park, Hollygate Lane, Cotgrave",
    "sg:city":"Nottingham",
    "sg:classifiers":[
        {
            "category":"Professional",
            "type":"Services"
        }
    ],
    "sg:phone":"+44 115 989 3322",
    "sg:postcode":"NG12 3JW",
    "sg:province":"Nottinghamshire",
    "sg:tags":[
        "services",
        "belt",
        "conveyor"
    ],
    "wof:name":"P S P Conveyers",
    "wof:placetype":"venue"
},
  "geometry": {"coordinates":[-1.0474770069,52.9091262817],"type":"Point"}
}