{
  "type": "Feature",
  "properties": {
    "addr:full":"15 Lyndale Cramlington Northumberland NE23 3XU",
    "addr:housenumber":"15",
    "addr:postcode":"ne23 3xu",
    "addr:street":"Lyndale;Northumberland",
    "iso:country":"GB",
    "sg:address":"15 Lyndale",
    "sg:city":"Cramlington",
    "sg:classifiers":[
        {
            "category":"Building & Trades",
            "subcategory":"Construction",
            "type":"Services"
        }
    ],
    "sg:phone":"+44 1670 713331",
    "sg:postcode":"NE23 3XU",
    "sg:province":"Northumberland",
    "sg:tags":[
        "decorator",
        "painter"
    ],
    "wof:name":"English Decorating Contracts",
    "wof:placetype":"venue"
},
  "geometry": {"coordinates":[-1.576363,55.099705],"type":"Point"}
}