{
  "type": "Feature",
  "properties": {
    "iso:country":"GB",
    "sg:address":"62 Batley Road",
    "sg:city":"Heckmondwike",
    "sg:classifiers":[
        {
            "category":"Fast Food",
            "type":"Food & Drink"
        }
    ],
    "sg:phone":"+44 1924 412700",
    "sg:postcode":"WF16 9NA",
    "sg:province":"West Yorkshire",
    "sg:tags":[
        "away",
        "meal",
        "outlet",
        "take"
    ],
    "wof:name":"Kashmir Takeaway",
    "wof:placetype":"venue"
},
  "geometry": {"coordinates":[-1.6612930298,53.7094268799],"type":"Point"}
}