{
  "type": "Feature",
  "properties": {
    "addr:full":"47-49 Hartington Street Barrow-in-furness Cumbria LA14 5SL",
    "addr:housenumber":"47-49",
    "addr:postcode":"la14 5sl",
    "addr:street":"Hartington Street",
    "iso:country":"GB",
    "sg:address":"47-49 Hartington Street",
    "sg:city":"Barrow-in-furness",
    "sg:classifiers":[
        {
            "category":"Education",
            "subcategory":"Special Training",
            "type":"Public Place"
        }
    ],
    "sg:phone":"+44 1229 837122",
    "sg:postcode":"LA14 5SL",
    "sg:province":"Cumbria",
    "sg:tags":[
        "product",
        "centre"
    ],
    "wof:name":"Protocol Skills Ltd.",
    "wof:placetype":"venue"
},
  "geometry": {"coordinates":[-3.2298989296,54.1172027588],"type":"Point"}
}