{
  "type": "Feature",
  "properties": {
    "iso:country":"GB",
    "sg:address":"205 St Georges Road",
    "sg:city":"Bolton",
    "sg:classifiers":[
        {
            "category":"Organizations",
            "subcategory":"Non-profit Organization",
            "type":"Services"
        }
    ],
    "sg:phone":"+44 1204 521160",
    "sg:postcode":"BL1 2PG",
    "sg:province":"Lancashire",
    "sg:tags":[
        "organisation",
        "animal",
        "welfare"
    ],
    "wof:name":"Rspca Animal Welfare Centre",
    "wof:placetype":"venue"
},
  "geometry": {"coordinates":[-2.4380099773,53.5817756653],"type":"Point"}
}