{
  "type": "Feature",
  "properties": {
    "addr:full":"Ashlawn Drive Boston Lincolnshire PE21 9PX",
    "addr:postcode":"pe21 9px",
    "addr:street":"Ashlawn Drive",
    "iso:country":"GB",
    "sg:address":"Ashlawn Drive",
    "sg:city":"Boston",
    "sg:classifiers":[
        {
            "category":"Education",
            "subcategory":"School",
            "type":"Public Place"
        }
    ],
    "sg:phone":"+44 1205 365922",
    "sg:postcode":"PE21 9PX",
    "sg:province":"Lincolnshire",
    "sg:tags":[
        "college",
        "local",
        "authority"
    ],
    "wof:name":"Tower Road Primary School",
    "wof:placetype":"venue"
},
  "geometry": {"coordinates":[-0.005934,52.9836578369],"type":"Point"}
}