{
  "type": "Feature",
  "properties": {
    "addr:full":"12 Shakespeare Road Stowmarket Suffolk IP14 1TJ",
    "addr:housenumber":"12",
    "addr:postcode":"ip14 1tj",
    "addr:street":"Shakespeare Road",
    "iso:country":"GB",
    "sg:address":"12 Shakespeare Road",
    "sg:city":"Stowmarket",
    "sg:classifiers":[
        {
            "category":"Manufacturing",
            "subcategory":"Lumber",
            "type":"Manufacturing & Wholesale Goods"
        }
    ],
    "sg:postcode":"IP14 1TJ",
    "sg:province":"Suffolk",
    "sg:tags":[
        "importer",
        "merchants",
        "agent",
        "timber"
    ],
    "wof:name":"T M Jones Timber Brokers",
    "wof:placetype":"venue"
},
  "geometry": {"coordinates":[0.9822329879,52.198474884],"type":"Point"}
}