{
  "type": "Feature",
  "properties": {
    "addr:full":"Hall Road, Stainforth Doncaster South Yorkshire DN7 5JD",
    "addr:postcode":"dn7 5jd",
    "addr:street":"Hall Road",
    "iso:country":"GB",
    "sg:address":"Hall Road, Stainforth",
    "sg:city":"Doncaster",
    "sg:classifiers":[
        {
            "category":"Organizations",
            "subcategory":"Community Association",
            "type":"Services"
        },
        {
            "category":"Organizations",
            "subcategory":"Membership Organization",
            "type":"Services"
        }
    ],
    "sg:phone":"+44 1302 350691",
    "sg:postcode":"DN7 5JD",
    "sg:province":"South Yorkshire",
    "sg:tags":[
        "club",
        "social"
    ],
    "wof:name":"The Old Club",
    "wof:placetype":"venue"
},
  "geometry": {"coordinates":[-1.0303989649,53.5950737],"type":"Point"}
}