{
  "type": "Feature",
  "properties": {
    "iso:country":"GB",
    "sg:address":"8 Carlton Place",
    "sg:city":"Southampton",
    "sg:classifiers":[
        {
            "category":"Professional",
            "subcategory":"Detective & Security Services",
            "type":"Services"
        }
    ],
    "sg:postcode":"SO15 2EA",
    "sg:province":"Hampshire",
    "wof:name":"South Coast Security Ltd",
    "wof:placetype":"venue"
},
  "geometry": {"coordinates":[-1.4043339491,50.9127616882],"type":"Point"}
}