{
  "type": "Feature",
  "properties": {
    "addr:full":"Watergate House, 85 Watergate Street Chester Cheshire CH1 2LF",
    "addr:housenumber":"85",
    "addr:postcode":"ch1 2lf",
    "addr:street":"Watergate Street",
    "iso:country":"GB",
    "sg:address":"Watergate House, 85 Watergate Street",
    "sg:city":"Chester",
    "sg:classifiers":[
        {
            "category":"Communications",
            "subcategory":"Newspaper",
            "type":"Services"
        }
    ],
    "sg:phone":"+44 1244 342055",
    "sg:postcode":"CH1 2LF",
    "sg:province":"Cheshire",
    "sg:tags":[
        "magazine"
    ],
    "wof:name":"Daily Post & Liverpool Echo",
    "wof:placetype":"venue"
},
  "geometry": {"coordinates":[-2.8949270248,53.1898651123],"type":"Point"}
}