{
  "type": "Feature",
  "properties": {
    "addr:full":"25 Park Royal Road London Greater London NW10 7LQ",
    "addr:housenumber":"25",
    "addr:postcode":"nw10 7lq",
    "addr:street":"Park Royal Road",
    "iso:country":"GB",
    "sg:address":"25 Park Royal Road",
    "sg:city":"London",
    "sg:classifiers":[
        {
            "category":"Retail",
            "subcategory":"Auto Repair",
            "type":"Services"
        }
    ],
    "sg:phone":"+44 20 8961 0616",
    "sg:postcode":"NW10 7LQ",
    "sg:province":"Greater London",
    "sg:tags":[
        "modification",
        "garage"
    ],
    "wof:name":"McArdle Coachbuilders Ltd.",
    "wof:placetype":"venue"
},
  "geometry": {"coordinates":[-0.266864,51.526459],"type":"Point"}
}