{
  "type": "Feature",
  "properties": {
    "iso:country":"GB",
    "sg:address":"The Old Chapel, Church St, Coggeshall",
    "sg:city":"Colchester",
    "sg:classifiers":[
        {
            "category":"Professional",
            "subcategory":"Business Services",
            "type":"Services"
        }
    ],
    "sg:phone":"+44 1376 562563",
    "sg:postcode":"CO6 1TU",
    "sg:province":"Essex",
    "sg:tags":[
        "hospitality",
        "corporate"
    ],
    "wof:name":"Podium",
    "wof:placetype":"venue"
},
  "geometry": {"coordinates":[0.6910380125,51.8712997437],"type":"Point"}
}