{
  "type": "Feature",
  "properties": {
    "addr:full":"56-57 Argyll Arcade Glasgow Glasgow City G2 8BG",
    "addr:housenumber":"56-57",
    "addr:postcode":"g2 8bg",
    "addr:street":"Argyll Arcade",
    "iso:country":"GB",
    "sg:address":"56-57 Argyll Arcade",
    "sg:city":"Glasgow",
    "sg:classifiers":[
        {
            "category":"Shopping",
            "subcategory":"Jewelry",
            "type":"Retail Goods"
        },
        {
            "category":"Shopping",
            "subcategory":"Comic Books",
            "type":"Retail Goods"
        }
    ],
    "sg:phone":"+44 141 221 3781",
    "sg:postcode":"G2 8BG",
    "sg:province":"Glasgow City",
    "sg:tags":[
        "jeweller",
        "sale",
        "jewellery"
    ],
    "wof:name":"SAUL BERCOTT LTD",
    "wof:placetype":"venue"
},
  "geometry": {"coordinates":[-4.260089,55.85865],"type":"Point"}
}