{
  "type": "Feature",
  "properties": {
    "addr:full":"The Old Barn Willow House, Ratling Road Canterbury Kent CT3 3HL",
    "addr:housenumber":"willow",
    "addr:postcode":"ct3 3hl",
    "addr:street":"Ratling Road",
    "iso:country":"GB",
    "sg:address":"The Old Barn Willow House, Ratling Road",
    "sg:city":"Canterbury",
    "sg:classifiers":[
        {
            "category":"Building & Trades",
            "subcategory":"Landscaping Services",
            "type":"Services"
        },
        {
            "category":"Building & Trades",
            "subcategory":"Construction",
            "type":"Services"
        }
    ],
    "sg:phone":"+44 1304 840033",
    "sg:postcode":"CT3 3HL",
    "sg:province":"Kent",
    "sg:tags":[
        "roofing",
        "landscape",
        "contractor"
    ],
    "wof:name":"Fineview Landscapes Ltd.",
    "wof:placetype":"venue"
},
  "geometry": {"coordinates":[1.20692,51.234337],"type":"Point"}
}