{
  "type": "Feature",
  "properties": {
    "addr:full":"97 High Street Maidenhead Berkshire SL6 1JX",
    "addr:housenumber":"97",
    "addr:postcode":"sl6 1jx",
    "addr:street":"High Street",
    "iso:country":"GB",
    "sg:address":"97 High Street",
    "sg:city":"Maidenhead",
    "sg:classifiers":[
        {
            "category":"Shopping",
            "subcategory":"Pharmacy",
            "type":"Retail Goods"
        },
        {
            "category":"Health Services",
            "subcategory":"Chiropractor",
            "type":"Services"
        }
    ],
    "sg:phone":"+44 1628 788420",
    "sg:postcode":"SL6 1JX",
    "sg:province":"Berkshire",
    "sg:tags":[
        "medicine",
        "therapy"
    ],
    "wof:name":"Healtheries",
    "wof:placetype":"venue"
},
  "geometry": {"coordinates":[-0.7233420014,51.5223693848],"type":"Point"}
}