{
  "type": "Feature",
  "properties": {
    "iso:country":"GB",
    "sg:address":"Crown Lane",
    "sg:city":"Denbigh",
    "sg:classifiers":[
        {
            "category":"Retail",
            "subcategory":"Auto Repair",
            "type":"Services"
        }
    ],
    "sg:phone":"+44 1745 815225",
    "sg:postcode":"LL16 3SY",
    "sg:province":"Conwy",
    "sg:tags":[
        "modification",
        "garage"
    ],
    "wof:name":"Crown Garage",
    "wof:placetype":"venue"
},
  "geometry": {"coordinates":[-3.4197928905,53.1843833923],"type":"Point"}
}