{
  "type": "Feature",
  "properties": {
    "addr:full":"Lower Bolton Hill, Old Hakin Rd Haverfordwest Pembrokeshire SA62 3EW",
    "addr:postcode":"sa62 3ew",
    "addr:street":"Lower;Hakin Rd",
    "iso:country":"GB",
    "sg:address":"Lower Bolton Hill, Old Hakin Rd",
    "sg:city":"Haverfordwest",
    "sg:classifiers":[
        {
            "category":"Farming",
            "subcategory":"Livestock Farm",
            "type":"Manufacturing & Wholesale Goods"
        }
    ],
    "sg:phone":"+44 1437 891537",
    "sg:postcode":"SA62 3EW",
    "sg:province":"Pembrokeshire",
    "sg:tags":[
        "others"
    ],
    "wof:name":"A Thomas",
    "wof:placetype":"venue"
},
  "geometry": {"coordinates":[-5.01507,51.770641],"type":"Point"}
}