{
  "type": "Feature",
  "properties": {
    "addr:full":"91 East St, Braintree Essex CM7 3JJ",
    "addr:housenumber":"91",
    "addr:postcode":"cm7 3jj",
    "addr:street":"East St",
    "iso:country":"GB",
    "sg:address":"91 East St,",
    "sg:city":"Braintree",
    "sg:classifiers":[
        {
            "category":"Wholesale",
            "subcategory":"Fruits & Vegetables",
            "type":"Manufacturing & Wholesale Goods"
        }
    ],
    "sg:postcode":"CM7 3JJ",
    "sg:province":"Essex",
    "wof:name":"Reading,Frank E,",
    "wof:placetype":"venue"
},
  "geometry": {"coordinates":[0.5628769994,51.8792686462],"type":"Point"}
}