{
  "type": "Feature",
  "properties": {
    "iso:country":"GB",
    "sg:address":"35 Regent Street",
    "sg:city":"Great Yarmouth",
    "sg:classifiers":[
        {
            "category":"Health Services",
            "subcategory":"Optometrist",
            "type":"Services"
        },
        {
            "category":"Shopping",
            "subcategory":"Optician",
            "type":"Retail Goods"
        }
    ],
    "sg:phone":"+44 1493 843937",
    "sg:postcode":"NR30 1RR",
    "sg:province":"Norfolk",
    "sg:tags":[
        "ophthalmic"
    ],
    "wof:name":"Paxon & Thomas",
    "wof:placetype":"venue"
},
  "geometry": {"coordinates":[1.726637,52.606743],"type":"Point"}
}