{
  "type": "Feature",
  "properties": {
    "iso:country":"GB",
    "sg:address":"8 Albion Street, Buttershaw",
    "sg:city":"Bradford",
    "sg:classifiers":[
        {
            "category":"Health Services",
            "subcategory":"Health Practitioner",
            "type":"Services"
        }
    ],
    "sg:phone":"+44 1274 607002",
    "sg:postcode":"BD6 2ES",
    "sg:province":"West Yorkshire",
    "sg:tags":[
        "hypnotherapists"
    ],
    "wof:name":"Albion Hypnotherapy Centre",
    "wof:placetype":"venue"
},
  "geometry": {"coordinates":[-1.79678,53.759064],"type":"Point"}
}