{
  "type": "Feature",
  "properties": {
    "iso:country":"GB",
    "sg:address":"Mundesley Maritime Museum, Beach Road, Mundesley",
    "sg:city":"Norwich",
    "sg:classifiers":[
        {
            "category":"Organizations",
            "subcategory":"Non-profit Organization",
            "type":"Services"
        }
    ],
    "sg:phone":"+44 1263 722399",
    "sg:postcode":"NR11 8BG",
    "sg:province":"Norfolk",
    "sg:tags":[
        "organisation",
        "voluntary",
        "charity"
    ],
    "wof:name":"National Coast Watch Institution",
    "wof:placetype":"venue"
},
  "geometry": {"coordinates":[1.431019,52.880333],"type":"Point"}
}