{
  "type": "Feature",
  "properties": {
    "addr:full":"Fosse Farm, Wolston Coventry Warwickshire CV8 3DG",
    "addr:postcode":"cv8 3dg",
    "addr:street":"Fosse",
    "iso:country":"GB",
    "sg:address":"Fosse Farm, Wolston",
    "sg:city":"Coventry",
    "sg:classifiers":[
        {
            "category":"Farming",
            "subcategory":"Dairy Farm",
            "type":"Manufacturing & Wholesale Goods"
        }
    ],
    "sg:postcode":"CV8 3DG",
    "sg:province":"Warwickshire",
    "wof:name":"Fosshill Dairies",
    "wof:placetype":"venue"
},
  "geometry": {"coordinates":[-1.395956,52.377865],"type":"Point"}
}