{
  "type": "Feature",
  "properties": {
    "addr:full":"104a East Street Southampton Hampshire SO14 3HH",
    "addr:housenumber":"104a",
    "addr:postcode":"so14 3hh",
    "addr:street":"East Street",
    "iso:country":"GB",
    "sg:address":"104a East Street",
    "sg:city":"Southampton",
    "sg:classifiers":[
        {
            "category":"Professional",
            "subcategory":"Printing & Photocopies",
            "type":"Services"
        }
    ],
    "sg:phone":"+44 23 8033 3200",
    "sg:postcode":"SO14 3HH",
    "sg:province":"Hampshire",
    "sg:tags":[
        "engraving"
    ],
    "wof:name":"The Glass Lady",
    "wof:placetype":"venue"
},
  "geometry": {"coordinates":[-1.4016009569,50.9016265869],"type":"Point"}
}