{
  "type": "Feature",
  "properties": {
    "iso:country":"GB",
    "sg:address":"178 Stoney Stanton Road",
    "sg:city":"Coventry",
    "sg:classifiers":[
        {
            "category":"Home & Garden",
            "subcategory":"Carpets & Floor Coverings",
            "type":"Retail Goods"
        }
    ],
    "sg:phone":"+44 24 7625 1414",
    "sg:postcode":"CV1 4FN",
    "sg:province":"West Midlands",
    "sg:tags":[
        "carpets",
        "retailer",
        "rug",
        "matting"
    ],
    "wof:name":"Silver Carpets",
    "wof:placetype":"venue"
},
  "geometry": {"coordinates":[-1.500265,52.418056],"type":"Point"}
}