{
  "type": "Feature",
  "properties": {
    "addr:full":"4 Marlborough Road Dartford Kent DA1 3EL",
    "addr:housenumber":"4",
    "addr:postcode":"da1 3el",
    "addr:street":"Marlborough Road",
    "iso:country":"GB",
    "sg:address":"4 Marlborough Road",
    "sg:city":"Dartford",
    "sg:classifiers":[
        {
            "category":"Home & Garden",
            "subcategory":"Carpets & Floor Coverings",
            "type":"Retail Goods"
        }
    ],
    "sg:phone":"+44 1322 277370",
    "sg:postcode":"DA1 3EL",
    "sg:province":"Kent",
    "sg:tags":[
        "cleaner",
        "upholstery"
    ],
    "wof:name":"Deluxe Cleaning Services",
    "wof:placetype":"venue"
},
  "geometry": {"coordinates":[0.2016710043,51.4466362],"type":"Point"}
}