{
  "type": "Feature",
  "properties": {
    "iso:country":"GB",
    "sg:address":"1 Lower Parade",
    "sg:city":"Sutton Coldfield",
    "sg:classifiers":[
        {
            "category":"Fast Food",
            "type":"Food & Drink"
        },
        {
            "category":"Restaurant",
            "type":"Food & Drink"
        }
    ],
    "sg:phone":"+44 121 354 3152",
    "sg:postcode":"B72 1XX",
    "sg:province":"West Midlands",
    "sg:tags":[
        "american",
        "-",
        "away",
        "take"
    ],
    "wof:name":"McDonald's Restaurants Ltd",
    "wof:placetype":"venue"
},
  "geometry": {"coordinates":[-1.823018,52.563225],"type":"Point"}
}