{
  "type": "Feature",
  "properties": {
    "addr:full":"Laleham Road Staines Berkshire TW18 2DX",
    "addr:postcode":"tw18 2dx",
    "addr:street":"Laleham Road",
    "iso:country":"GB",
    "sg:address":"Laleham Road",
    "sg:city":"Staines",
    "sg:classifiers":[
        {
            "category":"Place Of Worship",
            "type":"Public Place"
        }
    ],
    "sg:phone":"+44 1784 469155",
    "sg:postcode":"TW18 2DX",
    "sg:province":"Berkshire",
    "wof:name":"ST PETERS PARISH OFFICE",
    "wof:placetype":"venue"
},
  "geometry": {"coordinates":[-0.5100089908,51.4301757812],"type":"Point"}
}