{
  "type": "Feature",
  "properties": {
    "addr:full":"4 Herbert Road Bournemouth Dorset BH4 8HD",
    "addr:housenumber":"4",
    "addr:postcode":"bh4 8hd",
    "addr:street":"Herbert Road",
    "iso:country":"GB",
    "sg:address":"4 Herbert Road",
    "sg:city":"Bournemouth",
    "sg:classifiers":[
        {
            "category":"Travel",
            "subcategory":"Hotels & Motels",
            "type":"Entertainment"
        }
    ],
    "sg:postcode":"BH4 8HD",
    "sg:province":"Dorset",
    "wof:name":"Chase Lodge",
    "wof:placetype":"venue"
},
  "geometry": {"coordinates":[-1.905147,50.716297],"type":"Point"}
}