{
  "type": "Feature",
  "properties": {
    "addr:full":"18 King Edward Avenue Worthing West Sussex BN14 8DD",
    "addr:housenumber":"18",
    "addr:postcode":"bn14 8dd",
    "addr:street":"King Edward Avenue",
    "iso:country":"GB",
    "sg:address":"18 King Edward Avenue",
    "sg:city":"Worthing",
    "sg:classifiers":[
        {
            "category":"Education",
            "subcategory":"Dance Studio",
            "type":"Public Place"
        }
    ],
    "sg:postcode":"BN14 8DD",
    "sg:province":"West Sussex",
    "sg:tags":[
        "school",
        "dancing"
    ],
    "wof:name":"Performing Arts School",
    "wof:placetype":"venue"
},
  "geometry": {"coordinates":[-0.3715200126,50.8198623657],"type":"Point"}
}