{
  "type": "Feature",
  "properties": {
    "iso:country":"GB",
    "sg:address":"23 Darnley Road",
    "sg:city":"Rochester",
    "sg:classifiers":[
        {
            "category":"Shopping",
            "subcategory":"News",
            "type":"Retail Goods"
        }
    ],
    "sg:phone":"+44 1634 718413",
    "sg:postcode":"ME2 2EU",
    "sg:province":"Kent",
    "sg:tags":[
        "newsagent"
    ],
    "wof:name":"Dyllons",
    "wof:placetype":"venue"
},
  "geometry": {"coordinates":[0.4849520028,51.3930702209],"type":"Point"}
}