{
  "type": "Feature",
  "properties": {
    "addr:full":"213 Brompton Road London Greater London SW3 2EJ",
    "addr:housenumber":"213",
    "addr:postcode":"sw3 2ej",
    "addr:street":"Brompton Road",
    "iso:country":"GB",
    "sg:address":"213 Brompton Road",
    "sg:city":"London",
    "sg:classifiers":[
        {
            "category":"Banks & Credit Unions",
            "subcategory":"Bureau De Change",
            "type":"Services"
        }
    ],
    "sg:postcode":"SW3 2EJ",
    "sg:province":"Greater London",
    "wof:name":"Global Exchange Ltd.",
    "wof:placetype":"venue"
},
  "geometry": {"coordinates":[-0.1682190001,51.4971389771],"type":"Point"}
}