{
  "type": "Feature",
  "properties": {
    "addr:full":"Lancaster Parker Road Rochester Kent ME1 3QU",
    "addr:postcode":"me1 3qu",
    "addr:street":"Parker Road Rochester",
    "iso:country":"GB",
    "sg:address":"Lancaster Parker Road",
    "sg:city":"Rochester",
    "sg:classifiers":[
        {
            "category":"Utilities",
            "subcategory":"Telephone",
            "type":"Services"
        },
        {
            "category":"Shopping",
            "subcategory":"Computers & Home Electronics",
            "type":"Retail Goods"
        }
    ],
    "sg:phone":"+44 1634 687133",
    "sg:postcode":"ME1 3QU",
    "sg:province":"Kent",
    "sg:tags":[
        "telecom",
        "equipment",
        "system",
        "telecommunication"
    ],
    "wof:name":"Telspec plc",
    "wof:placetype":"venue"
},
  "geometry": {"coordinates":[0.499205,51.354549],"type":"Point"}
}