{
  "type": "Feature",
  "properties": {
    "iso:country":"GB",
    "sg:address":"27 Dimple Road",
    "sg:city":"Matlock",
    "sg:classifiers":[
        {
            "category":"Social Services",
            "subcategory":"Retirement Home",
            "type":"Services"
        }
    ],
    "sg:postcode":"DE4 3JX",
    "sg:province":"Derbyshire",
    "sg:tags":[
        "residential",
        "care"
    ],
    "wof:name":"Lazy Days Residential Home",
    "wof:placetype":"venue"
},
  "geometry": {"coordinates":[-1.560218,53.141228],"type":"Point"}
}