{
  "type": "Feature",
  "properties": {
    "iso:country":"GB",
    "sg:address":"4 Rabone Lane",
    "sg:city":"Smethwick",
    "sg:classifiers":[
        {
            "category":"Shopping",
            "subcategory":"Clothing, Apparel, & Fashions",
            "type":"Retail Goods"
        },
        {
            "category":"Manufacturing",
            "subcategory":"Paper Products",
            "type":"Manufacturing & Wholesale Goods"
        }
    ],
    "sg:phone":"+44 121 558 0949",
    "sg:postcode":"B66 3JH",
    "sg:province":"West Midlands",
    "sg:tags":[
        "manufacturer",
        "clothing",
        "fabric",
        "leisure",
        "wear"
    ],
    "wof:name":"Suthi Enterprises",
    "wof:placetype":"venue"
},
  "geometry": {"coordinates":[-1.9611150026,52.49634552],"type":"Point"}
}