{
  "type": "Feature",
  "properties": {
    "iso:country":"GB",
    "sg:address":", Ffestiniog",
    "sg:city":"Blaenau Ffestiniog",
    "sg:classifiers":[
        {
            "category":"Education",
            "subcategory":"School",
            "type":"Public Place"
        }
    ],
    "sg:phone":"+44 1766 762668",
    "sg:postcode":"LL41 4NF",
    "sg:province":"Gwynedd",
    "sg:tags":[
        "local",
        "authority"
    ],
    "wof:name":"Ysgol Bro Cynfal",
    "wof:placetype":"venue"
},
  "geometry": {"coordinates":[-3.9315590858,52.9613494873],"type":"Point"}
}