{
  "type": "Feature",
  "properties": {
    "iso:country":"GB",
    "sg:address":"93-95 Basingstoke Road",
    "sg:city":"Reading",
    "sg:classifiers":[
        {
            "category":"Travel",
            "subcategory":"Hotels & Motels",
            "type":"Entertainment"
        }
    ],
    "sg:phone":"+44 118 987 2076",
    "sg:postcode":"RG2 0HA",
    "sg:province":"Berkshire",
    "wof:name":"The Reading Hotel",
    "wof:placetype":"venue"
},
  "geometry": {"coordinates":[-0.967595,51.438831],"type":"Point"}
}