{
  "type": "Feature",
  "properties": {
    "iso:country":"GB",
    "sg:address":"1 Church Road",
    "sg:city":"Droitwich",
    "sg:classifiers":[
        {
            "category":"Building & Trades",
            "subcategory":"Construction",
            "type":"Services"
        }
    ],
    "sg:postcode":"WR9 8LN",
    "sg:province":"Worcestershire",
    "sg:tags":[
        "builder"
    ],
    "wof:name":"L T Jordan",
    "wof:placetype":"venue"
},
  "geometry": {"coordinates":[-2.1431679726,52.2712249756],"type":"Point"}
}