{
  "type": "Feature",
  "properties": {
    "addr:full":"19 High Street Woking Surrey GU21 6BW",
    "addr:housenumber":"19",
    "addr:postcode":"gu21 6bw",
    "addr:street":"High Street",
    "iso:country":"GB",
    "sg:address":"19 High Street",
    "sg:city":"Woking",
    "sg:classifiers":[
        {
            "category":"Cafe",
            "type":"Food & Drink"
        },
        {
            "category":"Government",
            "subcategory":"Office",
            "type":"Public Place"
        }
    ],
    "sg:phone":"+44 1483 762891",
    "sg:postcode":"GU21 6BW",
    "sg:province":"Surrey",
    "sg:tags":[
        "tea",
        "local",
        "room"
    ],
    "wof:name":"The Marjorie Richardson Centre",
    "wof:placetype":"venue"
},
  "geometry": {"coordinates":[-0.5589129925,51.318195343],"type":"Point"}
}