{
  "type": "Feature",
  "properties": {
    "addr:full":"10 Braiers Close Chelmsford Essex CM2 8GY",
    "addr:housenumber":"10",
    "addr:postcode":"cm2 8gy",
    "addr:street":"Braiers Close",
    "iso:country":"GB",
    "sg:address":"10 Braiers Close",
    "sg:city":"Chelmsford",
    "sg:classifiers":[
        {
            "category":"Professional",
            "subcategory":"Engineering",
            "type":"Services"
        }
    ],
    "sg:postcode":"CM2 8GY",
    "sg:province":"Essex",
    "sg:tags":[
        "contractor",
        "electrical",
        "engineer"
    ],
    "wof:name":"Maldon Electrical Services Ltd.",
    "wof:placetype":"venue"
},
  "geometry": {"coordinates":[0.477891,51.731918],"type":"Point"}
}