{
  "type": "Feature",
  "properties": {
    "addr:full":"Sicilian House, Sicilian Avenue Bloomsbury Greater London WC1A 2QH",
    "addr:postcode":"wc1a 2qh",
    "addr:street":"Sicilian Avenue",
    "iso:country":"GB",
    "sg:address":"Sicilian House, Sicilian Avenue",
    "sg:city":"Bloomsbury",
    "sg:classifiers":[
        {
            "category":"Professional",
            "subcategory":"Employment Agencies",
            "type":"Services"
        }
    ],
    "sg:phone":"+44 20 7242 9962",
    "sg:postcode":"WC1A 2QH",
    "sg:province":"Greater London",
    "sg:tags":[
        "consultant"
    ],
    "wof:name":"Target Appointments",
    "wof:placetype":"venue"
},
  "geometry": {"coordinates":[-0.121304,51.518463],"type":"Point"}
}