{
  "type": "Feature",
  "properties": {
    "addr:full":"42-44 Cutlers Road, Saltcoats Industrial Estate, South Woodham Ferrers Chelmsford Essex CM3 5XJ",
    "addr:housenumber":"42-44",
    "addr:postcode":"cm3 5xj",
    "addr:street":"Cutlers Road Saltcoats Industrial Estate;Woodham Ferrers",
    "iso:country":"GB",
    "sg:address":"42-44 Cutlers Road, Saltcoats Industrial Estate, South Woodham Ferrers",
    "sg:city":"Chelmsford",
    "sg:classifiers":[
        {
            "category":"Retail",
            "subcategory":"Repair Shop",
            "type":"Services"
        },
        {
            "category":"Wholesale",
            "subcategory":"Machinery & Supplies",
            "type":"Manufacturing & Wholesale Goods"
        }
    ],
    "sg:phone":"+44 1245 322733",
    "sg:postcode":"CM3 5XJ",
    "sg:province":"Essex",
    "sg:tags":[
        "agricultural",
        "sale"
    ],
    "wof:name":"R W Crawford Agricultural Machinery Ltd",
    "wof:placetype":"venue"
},
  "geometry": {"coordinates":[0.619968,51.648876],"type":"Point"}
}