{
  "type": "Feature",
  "properties": {
    "addr:full":"123 Maes-y-coed Road Cardiff Cardiff CF14 4HE",
    "addr:housenumber":"123",
    "addr:postcode":"cf14 4he",
    "addr:street":"Maes-Y-Coed Road",
    "iso:country":"GB",
    "sg:address":"123 Maes-y-coed Road",
    "sg:city":"Cardiff",
    "sg:classifiers":[
        {
            "category":"Personal",
            "subcategory":"Beauty Salon",
            "type":"Services"
        }
    ],
    "sg:postcode":"CF14 4HE",
    "sg:province":"Cardiff",
    "sg:tags":[
        "lady",
        "hairdresser"
    ],
    "wof:name":"Heatwave Hair Fashions",
    "wof:placetype":"venue"
},
  "geometry": {"coordinates":[-3.1954240799,51.5195655823],"type":"Point"}
}