{
  "type": "Feature",
  "properties": {
    "addr:full":"18 Old Town, Clapham London Greater London SW4 0LB",
    "addr:housenumber":"18",
    "addr:postcode":"sw4 0lb",
    "addr:street":"Old Town",
    "iso:country":"GB",
    "sg:address":"18 Old Town, Clapham",
    "sg:city":"London",
    "sg:classifiers":[
        {
            "category":"Education",
            "subcategory":"Special Training",
            "type":"Public Place"
        }
    ],
    "sg:phone":"+44 20 7622 7254",
    "sg:postcode":"SW4 0LB",
    "sg:province":"Greater London",
    "sg:tags":[
        "school",
        "language"
    ],
    "wof:name":"English Language Training",
    "wof:placetype":"venue"
},
  "geometry": {"coordinates":[-0.1414130032,51.4644622803],"type":"Point"}
}