{
  "type": "Feature",
  "properties": {
    "addr:full":"31 St Johns Rd Feltham Greater London TW13 6NW",
    "addr:housenumber":"31",
    "addr:postcode":"tw13 6nw",
    "addr:street":"St Johns Rd",
    "iso:country":"GB",
    "sg:address":"31 St Johns Rd",
    "sg:city":"Feltham",
    "sg:classifiers":[
        {
            "category":"Retail",
            "subcategory":"Auto Repair",
            "type":"Services"
        }
    ],
    "sg:phone":"+44 20 8560 5561",
    "sg:postcode":"TW13 6NW",
    "sg:province":"Greater London",
    "sg:tags":[
        "body",
        "car"
    ],
    "wof:name":"Davis H A & Co",
    "wof:placetype":"venue"
},
  "geometry": {"coordinates":[-0.382652,51.434086],"type":"Point"}
}