{
  "type": "Feature",
  "properties": {
    "iso:country":"GB",
    "sg:address":"9 High Street, Hoyland",
    "sg:city":"Barnsley",
    "sg:classifiers":[
        {
            "category":"Bars & Pubs",
            "type":"Food & Drink"
        }
    ],
    "sg:phone":"+44 1226 742358",
    "sg:postcode":"S74 9AB",
    "sg:province":"South Yorkshire",
    "sg:tags":[
        "pubs",
        "inn"
    ],
    "wof:name":"Gardeners Arms",
    "wof:placetype":"venue"
},
  "geometry": {"coordinates":[-1.438505,53.500477],"type":"Point"}
}