{
  "type": "Feature",
  "properties": {
    "addr:full":"1-3 Herbert Road Nottingham Nottinghamshire NG5 1BS",
    "addr:housenumber":"1-3",
    "addr:postcode":"ng5 1bs",
    "addr:street":"Herbert Road",
    "iso:country":"GB",
    "sg:address":"1-3 Herbert Road",
    "sg:city":"Nottingham",
    "sg:classifiers":[
        {
            "category":"Social Services",
            "subcategory":"Retirement Home",
            "type":"Services"
        }
    ],
    "sg:phone":"+44 115 962 6316",
    "sg:postcode":"NG5 1BS",
    "sg:province":"Nottinghamshire",
    "sg:tags":[
        "rest"
    ],
    "wof:name":"Yolanta House",
    "wof:placetype":"venue"
},
  "geometry": {"coordinates":[-1.160955,52.973755],"type":"Point"}
}