{
  "type": "Feature",
  "properties": {
    "addr:full":"Bromborough Dock, Dock Road South Wirral Cheshire CH62 4SR",
    "addr:postcode":"ch62 4sr",
    "addr:street":"Dock Road South",
    "iso:country":"GB",
    "sg:address":"Bromborough Dock, Dock Road South",
    "sg:city":"Wirral",
    "sg:classifiers":[
        {
            "category":"Professional",
            "subcategory":"Engineering",
            "type":"Services"
        },
        {
            "category":"Professional",
            "type":"Services"
        }
    ],
    "sg:phone":"+44 151 643 8787",
    "sg:postcode":"CH62 4SR",
    "sg:province":"Cheshire",
    "sg:tags":[
        "civil",
        "marine",
        "engineer"
    ],
    "wof:name":"PORT DREDGING LTD",
    "wof:placetype":"venue"
},
  "geometry": {"coordinates":[-2.9818840027,53.3473701477],"type":"Point"}
}