{
  "type": "Feature",
  "properties": {
    "iso:country":"GB",
    "sg:address":"56 Long Brook St",
    "sg:city":"Exeter",
    "sg:classifiers":[
        {
            "category":"Real Estate",
            "subcategory":"Real Estate Agent",
            "type":"Services"
        }
    ],
    "sg:postcode":"EX4 6AH",
    "sg:province":"Devon",
    "wof:name":"Shire Property Management",
    "wof:placetype":"venue"
},
  "geometry": {"coordinates":[-3.527009964,50.7269210815],"type":"Point"}
}