{
  "type": "Feature",
  "properties": {
    "addr:full":"98 Wentworth Way South Croydon Surrey CR2 9EW",
    "addr:housenumber":"98",
    "addr:postcode":"cr2 9ew",
    "addr:street":"Wentworth Way",
    "iso:country":"GB",
    "sg:address":"98 Wentworth Way",
    "sg:city":"South Croydon",
    "sg:classifiers":[
        {
            "category":"Retail",
            "subcategory":"Auto Repair",
            "type":"Services"
        }
    ],
    "sg:postcode":"CR2 9EW",
    "sg:province":"Surrey",
    "sg:tags":[
        "modification",
        "garage"
    ],
    "wof:name":"Ellis Autos",
    "wof:placetype":"venue"
},
  "geometry": {"coordinates":[-0.071389,51.322453],"type":"Point"}
}