{
  "type": "Feature",
  "properties": {
    "addr:full":"Unit 6, Dinnington Business Centre, Outgang Lane Sheffield South Yorkshire S25 3QX",
    "addr:housenumber":"unit 6",
    "addr:postcode":"s25 3qx",
    "addr:street":"Dinnington Business;Outgang Lane",
    "iso:country":"GB",
    "sg:address":"Unit 6, Dinnington Business Centre, Outgang Lane",
    "sg:city":"Sheffield",
    "sg:classifiers":[
        {
            "category":"Professional",
            "subcategory":"Computer Services",
            "type":"Services"
        }
    ],
    "sg:phone":"+44 1709 821433",
    "sg:postcode":"S25 3QX",
    "sg:province":"South Yorkshire",
    "sg:tags":[
        "system",
        "software"
    ],
    "wof:name":"Future Media Uk Ltd.",
    "wof:placetype":"venue"
},
  "geometry": {"coordinates":[-1.21722,53.375389],"type":"Point"}
}