{
  "type": "Feature",
  "properties": {
    "addr:full":"Sunnyside Road, Beeston Nottingham Nottinghamshire NG9 4FR",
    "addr:postcode":"ng9 4fr",
    "addr:street":"Sunnyside Road",
    "iso:country":"GB",
    "sg:address":"Sunnyside Road, Beeston",
    "sg:city":"Nottingham",
    "sg:classifiers":[
        {
            "category":"Social Services",
            "subcategory":"Adult Care",
            "type":"Services"
        },
        {
            "category":"Government",
            "subcategory":"Office",
            "type":"Public Place"
        }
    ],
    "sg:phone":"+44 115 925 0172",
    "sg:postcode":"NG9 4FR",
    "sg:province":"Nottinghamshire",
    "sg:tags":[
        "local",
        "day",
        "centre"
    ],
    "wof:name":"The Barncroft Centre",
    "wof:placetype":"venue"
},
  "geometry": {"coordinates":[-1.2403359413,52.9252738953],"type":"Point"}
}