{
  "type": "Feature",
  "properties": {
    "addr:full":"Hornsbury Hill Farm, Hornsbury Hill Chard Devon TA20 3DB",
    "addr:postcode":"ta20 3db",
    "addr:street":"Hornsbury Hill;Hornsbury Hill",
    "iso:country":"GB",
    "sg:address":"Hornsbury Hill Farm, Hornsbury Hill",
    "sg:city":"Chard",
    "sg:classifiers":[
        {
            "category":"Travel",
            "subcategory":"Hotels & Motels",
            "type":"Entertainment"
        },
        {
            "category":"Farming",
            "subcategory":"Farm",
            "type":"Manufacturing & Wholesale Goods"
        }
    ],
    "sg:phone":"+44 1460 65516",
    "sg:postcode":"TA20 3DB",
    "sg:province":"Devon",
    "sg:tags":[
        "mixed",
        "self",
        "crop",
        "catering"
    ],
    "wof:name":"Hornsbury Hill Farm",
    "wof:placetype":"venue"
},
  "geometry": {"coordinates":[-2.9484050274,50.8907814026],"type":"Point"}
}