{
  "type": "Feature",
  "properties": {
    "addr:full":"162 Woodhouse Lane Leeds West Yorkshire LS2 9HB",
    "addr:housenumber":"162",
    "addr:postcode":"ls2 9hb",
    "addr:street":"Woodhouse Lane",
    "iso:country":"GB",
    "sg:address":"162 Woodhouse Lane",
    "sg:city":"Leeds",
    "sg:classifiers":[
        {
            "category":"Personal",
            "subcategory":"Beauty Salon",
            "type":"Services"
        },
        {
            "category":"Personal",
            "subcategory":"Barber",
            "type":"Services"
        }
    ],
    "sg:phone":"+44 113 242 3861",
    "sg:postcode":"LS2 9HB",
    "sg:province":"West Yorkshire",
    "sg:tags":[
        "unisex",
        "hairdresser"
    ],
    "wof:name":"Mega City One",
    "wof:placetype":"venue"
},
  "geometry": {"coordinates":[-1.5521889925,53.8082122803],"type":"Point"}
}