{
  "type": "Feature",
  "properties": {
    "addr:full":"81 Lower St Pulborough West Sussex RH20 2BP",
    "addr:housenumber":"81",
    "addr:postcode":"rh20 2bp",
    "addr:street":"Lower St",
    "iso:country":"GB",
    "sg:address":"81 Lower St",
    "sg:city":"Pulborough",
    "sg:classifiers":[
        {
            "category":"Farming",
            "subcategory":"Fish & Marine Products",
            "type":"Manufacturing & Wholesale Goods"
        }
    ],
    "sg:postcode":"RH20 2BP",
    "sg:province":"West Sussex",
    "sg:tags":[
        "fishmonger"
    ],
    "wof:name":"Coughtrey,Anthony C,",
    "wof:placetype":"venue"
},
  "geometry": {"coordinates":[-0.502386,50.957317],"type":"Point"}
}