{
  "type": "Feature",
  "properties": {
    "iso:country":"GB",
    "sg:address":"Riversdale House, Greenside",
    "sg:city":"Ryton",
    "sg:classifiers":[
        {
            "category":"Food & Beverages",
            "subcategory":"Meat & Fish",
            "type":"Retail Goods"
        }
    ],
    "sg:phone":"+44 191 413 2139",
    "sg:postcode":"NE40 4SU",
    "sg:province":"Tyne and Wear",
    "sg:tags":[
        "butcher"
    ],
    "wof:name":"F & L Holliday",
    "wof:placetype":"venue"
},
  "geometry": {"coordinates":[-1.791247,54.966221],"type":"Point"}
}