{
  "type": "Feature",
  "properties": {
    "addr:full":"2 Ochre Hill, Wellington Heath Ledbury Gloucestershire HR8 1LZ",
    "addr:housenumber":"2",
    "addr:postcode":"hr8 1lz",
    "addr:street":"Ochre Hill",
    "iso:country":"GB",
    "sg:address":"2 Ochre Hill, Wellington Heath",
    "sg:city":"Ledbury",
    "sg:classifiers":[
        {
            "category":"Professional",
            "subcategory":"Computer Services",
            "type":"Services"
        }
    ],
    "sg:phone":"+44 7977 553438",
    "sg:postcode":"HR8 1LZ",
    "sg:province":"Gloucestershire",
    "sg:tags":[
        "system",
        "software"
    ],
    "wof:name":"Breakunique Ltd.",
    "wof:placetype":"venue"
},
  "geometry": {"coordinates":[-2.418649,52.062935],"type":"Point"}
}