{
  "type": "Feature",
  "properties": {
    "addr:full":"Castle Street Cardigan Ceredigion SA43 3AA",
    "addr:postcode":"sa43 3aa",
    "addr:street":"Castle Street",
    "iso:country":"GB",
    "sg:address":"Castle Street",
    "sg:city":"Cardigan",
    "sg:classifiers":[
        {
            "category":"Landmark",
            "subcategory":"Tourist Attraction",
            "type":"Public Place"
        }
    ],
    "sg:phone":"+44 1239 614404",
    "sg:postcode":"SA43 3AA",
    "sg:province":"Ceredigion",
    "sg:tags":[
        "interest"
    ],
    "wof:name":"Cardigan Heritage Centre",
    "wof:placetype":"venue"
},
  "geometry": {"coordinates":[-4.660577774,52.0801277161],"type":"Point"}
}