{
  "type": "Feature",
  "properties": {
    "addr:full":"13 Westland Place Islington Greater London N1 7LP",
    "addr:housenumber":"13",
    "addr:postcode":"n1 7lp",
    "addr:street":"Westland Place",
    "iso:country":"GB",
    "sg:address":"13 Westland Place",
    "sg:city":"Islington",
    "sg:classifiers":[
        {
            "category":"Museum",
            "subcategory":"Art Museum",
            "type":"Entertainment"
        }
    ],
    "sg:phone":"+44 20 7251 6456",
    "sg:postcode":"N1 7LP",
    "sg:province":"Greater London",
    "sg:tags":[
        "gallery"
    ],
    "wof:name":"Gallery Westland Place",
    "wof:placetype":"venue"
},
  "geometry": {"coordinates":[-0.090279,51.528603],"type":"Point"}
}