{
  "type": "Feature",
  "properties": {
    "addr:full":"Unit 27 Phoenix Industrial Estate, Duke Street Manchester Lancashire M35 9DT",
    "addr:housenumber":"unit 27;estate",
    "addr:postcode":"m35 9dt",
    "addr:street":"Phoenix Industrial;Duke Street",
    "iso:country":"GB",
    "sg:address":"Unit 27 Phoenix Industrial Estate, Duke Street",
    "sg:city":"Manchester",
    "sg:classifiers":[
        {
            "category":"Retail",
            "subcategory":"Auto Repair",
            "type":"Services"
        }
    ],
    "sg:phone":"+44 161 684 7696",
    "sg:postcode":"M35 9DT",
    "sg:province":"Lancashire",
    "sg:tags":[
        "modification",
        "garage"
    ],
    "wof:name":"Prestige Car Services",
    "wof:placetype":"venue"
},
  "geometry": {"coordinates":[-2.1494500637,53.5145683289],"type":"Point"}
}