{
  "type": "Feature",
  "properties": {
    "iso:country":"GB",
    "sg:address":"193 Loughborough Road",
    "sg:city":"Leicester",
    "sg:classifiers":[
        {
            "category":"Shopping",
            "subcategory":"Used Merchandise",
            "type":"Retail Goods"
        }
    ],
    "sg:postcode":"LE4 5PL",
    "sg:province":"Leicestershire",
    "sg:tags":[
        "shop",
        "second-hand"
    ],
    "wof:name":"Edward Puszka",
    "wof:placetype":"venue"
},
  "geometry": {"coordinates":[-1.122837,52.659081],"type":"Point"}
}