{
  "type": "Feature",
  "properties": {
    "addr:full":"8 Hayes Garden Bromley Kent BR2 7DG",
    "addr:housenumber":"8",
    "addr:postcode":"br2 7dg",
    "addr:street":"Hayes Garden",
    "iso:country":"GB",
    "sg:address":"8 Hayes Garden",
    "sg:city":"Bromley",
    "sg:classifiers":[
        {
            "category":"Professional",
            "type":"Services"
        }
    ],
    "sg:postcode":"BR2 7DG",
    "sg:province":"Kent",
    "sg:tags":[
        "caterer"
    ],
    "wof:name":"Williams Colin Professional Catering Services",
    "wof:placetype":"venue"
},
  "geometry": {"coordinates":[0.0130009996,51.3771972656],"type":"Point"}
}