{
  "type": "Feature",
  "properties": {
    "iso:country":"GB",
    "sg:address":"Estates Office, Glamis",
    "sg:city":"Forfar",
    "sg:classifiers":[
        {
            "category":"Landmark",
            "subcategory":"Tourist Attraction",
            "type":"Public Place"
        }
    ],
    "sg:phone":"+44 1307 840393",
    "sg:postcode":"DD8 1RJ",
    "sg:province":"Angus",
    "sg:tags":[
        "interest"
    ],
    "wof:name":"Glamis Castle",
    "wof:placetype":"venue"
},
  "geometry": {"coordinates":[-3.0058920383,56.6074295044],"type":"Point"}
}