{
  "type": "Feature",
  "properties": {
    "addr:full":"28 St. Marks Clo Evesham Gloucestershire WR11 6EU",
    "addr:housenumber":"28",
    "addr:postcode":"wr11 6eu",
    "addr:street":"St.;Evesham",
    "iso:country":"GB",
    "sg:address":"28 St. Marks Clo",
    "sg:city":"Evesham",
    "sg:classifiers":[
        {
            "category":"Professional",
            "subcategory":"Computer Services",
            "type":"Services"
        }
    ],
    "sg:phone":"+44 1386 49513",
    "sg:postcode":"WR11 6EU",
    "sg:province":"Gloucestershire",
    "sg:tags":[
        "aided",
        "design"
    ],
    "wof:name":"Firefly Computers",
    "wof:placetype":"venue"
},
  "geometry": {"coordinates":[-1.944664,52.076954],"type":"Point"}
}