{
  "type": "Feature",
  "properties": {
    "iso:country":"GB",
    "sg:address":"237 Blackfen Rd",
    "sg:city":"Sidcup",
    "sg:classifiers":[
        {
            "category":"Banks & Credit Unions",
            "subcategory":"Financial Services",
            "type":"Services"
        }
    ],
    "sg:phone":"+44 20 8850 1330",
    "sg:postcode":"DA15 8PR",
    "sg:province":"Kent",
    "sg:tags":[
        "adviser"
    ],
    "wof:name":"Parkwood Financial Services",
    "wof:placetype":"venue"
},
  "geometry": {"coordinates":[0.100955,51.45105],"type":"Point"}
}