{
  "type": "Feature",
  "properties": {
    "iso:country":"GB",
    "sg:address":"The Parade, 4 Coppice Road, Woodley",
    "sg:city":"Reading",
    "sg:classifiers":[
        {
            "category":"Fast Food",
            "type":"Food & Drink"
        }
    ],
    "sg:phone":"+44 118 969 0019",
    "sg:postcode":"RG5 3RB",
    "sg:province":"Berkshire",
    "sg:tags":[
        "away",
        "meal",
        "outlet",
        "take"
    ],
    "wof:name":"Woodley Chef",
    "wof:placetype":"venue"
},
  "geometry": {"coordinates":[-0.913439,51.451962],"type":"Point"}
}