{
  "type": "Feature",
  "properties": {
    "addr:full":"212 Big Barn Lane Mansfield Nottinghamshire NG18 3LA",
    "addr:housenumber":"212",
    "addr:postcode":"ng18 3la",
    "addr:street":"Big Barn Lane",
    "iso:country":"GB",
    "sg:address":"212 Big Barn Lane",
    "sg:city":"Mansfield",
    "sg:classifiers":[
        {
            "category":"Shopping",
            "subcategory":"News",
            "type":"Retail Goods"
        }
    ],
    "sg:phone":"+44 1623 453912",
    "sg:postcode":"NG18 3LA",
    "sg:province":"Nottinghamshire",
    "sg:tags":[
        "newsagent"
    ],
    "wof:name":"Big Barn News",
    "wof:placetype":"venue"
},
  "geometry": {"coordinates":[-1.167041,53.135937],"type":"Point"}
}