{
  "type": "Feature",
  "properties": {
    "addr:full":"6 Tudor Court, South Elmsall Pontefract West Yorkshire WF9 2UZ",
    "addr:housenumber":"6",
    "addr:postcode":"wf9 2uz",
    "addr:street":"Tudor Court South;Pontefract West",
    "iso:country":"GB",
    "sg:address":"6 Tudor Court, South Elmsall",
    "sg:city":"Pontefract",
    "sg:classifiers":[
        {
            "category":"Building & Trades",
            "subcategory":"Construction",
            "type":"Services"
        },
        {
            "category":"Manufacturing",
            "subcategory":"Paper Products",
            "type":"Manufacturing & Wholesale Goods"
        }
    ],
    "sg:phone":"+44 1977 643264",
    "sg:postcode":"WF9 2UZ",
    "sg:province":"West Yorkshire",
    "sg:tags":[
        "cardboard",
        "decorator",
        "painter"
    ],
    "wof:name":"David Webb",
    "wof:placetype":"venue"
},
  "geometry": {"coordinates":[-1.292922,53.595894],"type":"Point"}
}