{
  "type": "Feature",
  "properties": {
    "addr:full":"43a Watnall Road, Hucknall Nottingham Nottinghamshire NG15 7JQ",
    "addr:housenumber":"43a",
    "addr:postcode":"ng15 7jq",
    "addr:street":"Watnall Road",
    "iso:country":"GB",
    "sg:address":"43a Watnall Road, Hucknall",
    "sg:city":"Nottingham",
    "sg:classifiers":[
        {
            "category":"Health Services",
            "subcategory":"Podiatrist",
            "type":"Services"
        }
    ],
    "sg:phone":"+44 115 968 0391",
    "sg:postcode":"NG15 7JQ",
    "sg:province":"Nottinghamshire",
    "sg:tags":[
        "podiatrists",
        "chiropodist"
    ],
    "wof:name":"Julia Greenwood Chiropodist",
    "wof:placetype":"venue"
},
  "geometry": {"coordinates":[-1.2038340569,53.0358314514],"type":"Point"}
}