{
  "type": "Feature",
  "properties": {
    "addr:full":"30a Fitzroy Street Cambridge Cambridgeshire CB1 1EW",
    "addr:housenumber":"30a",
    "addr:postcode":"cb1 1ew",
    "addr:street":"Fitzroy Street",
    "iso:country":"GB",
    "sg:address":"30a Fitzroy Street",
    "sg:city":"Cambridge",
    "sg:classifiers":[
        {
            "category":"Banks & Credit Unions",
            "subcategory":"Bank",
            "type":"Services"
        }
    ],
    "sg:phone":"+44 845 603 3610",
    "sg:postcode":"CB1 1EW",
    "sg:province":"Cambridgeshire",
    "wof:name":"Halifax Plc",
    "wof:placetype":"venue"
},
  "geometry": {"coordinates":[0.130989,52.206596],"type":"Point"}
}