{
  "type": "Feature",
  "properties": {
    "iso:country":"GB",
    "sg:address":"7 The Hopyard",
    "sg:city":"Tewkesbury",
    "sg:classifiers":[
        {
            "category":"Retail",
            "subcategory":"Driving School",
            "type":"Services"
        }
    ],
    "sg:phone":"+44 1684 299963",
    "sg:postcode":"GL20 8RR",
    "sg:province":"Gloucestershire",
    "wof:name":"Arrow School Of Motoring",
    "wof:placetype":"venue"
},
  "geometry": {"coordinates":[-2.119078,52.005539],"type":"Point"}
}