{
  "type": "Feature",
  "properties": {
    "addr:full":"11 Brighton Road Horley Surrey RH6 7HH",
    "addr:housenumber":"11",
    "addr:postcode":"rh6 7hh",
    "addr:street":"Brighton Road",
    "iso:country":"GB",
    "sg:address":"11 Brighton Road",
    "sg:city":"Horley",
    "sg:classifiers":[
        {
            "category":"Travel",
            "subcategory":"Hotels & Motels",
            "type":"Entertainment"
        }
    ],
    "sg:postcode":"RH6 7HH",
    "sg:province":"Surrey",
    "sg:tags":[
        "house",
        "guest"
    ],
    "wof:name":"Furze Down Guest House",
    "wof:placetype":"venue"
},
  "geometry": {"coordinates":[-0.174527,51.169483],"type":"Point"}
}