{
  "type": "Feature",
  "properties": {
    "addr:full":"Bridge Street, Swinton Mexborough South Yorkshire S64 8AP",
    "addr:postcode":"s64 8ap",
    "addr:street":"Bridge Street",
    "iso:country":"GB",
    "sg:address":"Bridge Street, Swinton",
    "sg:city":"Mexborough",
    "sg:classifiers":[
        {
            "category":"Bars & Pubs",
            "type":"Food & Drink"
        }
    ],
    "sg:phone":"+44 1709 583242",
    "sg:postcode":"S64 8AP",
    "sg:province":"South Yorkshire",
    "sg:tags":[
        "pubs",
        "inn"
    ],
    "wof:name":"Joan Sherwood",
    "wof:placetype":"venue"
},
  "geometry": {"coordinates":[-1.317868948,53.4877662659],"type":"Point"}
}