{
  "type": "Feature",
  "properties": {
    "addr:full":"199 Handley Road, New Whittington Chesterfield Derbyshire S43 2ES",
    "addr:housenumber":"199",
    "addr:postcode":"s43 2es",
    "addr:street":"Handley Road New",
    "iso:country":"GB",
    "sg:address":"199 Handley Road, New Whittington",
    "sg:city":"Chesterfield",
    "sg:classifiers":[
        {
            "category":"Utilities",
            "subcategory":"Fuel Oil & Lpg",
            "type":"Services"
        }
    ],
    "sg:postcode":"S43 2ES",
    "sg:province":"Derbyshire",
    "sg:tags":[
        "coal",
        "smokeless"
    ],
    "wof:name":"P Parker & Son",
    "wof:placetype":"venue"
},
  "geometry": {"coordinates":[-1.4049090147,53.28332901],"type":"Point"}
}