{
  "type": "Feature",
  "properties": {
    "addr:full":"294 Clipsley Lane, Haydock St Helens Lancashire WA11 0JQ",
    "addr:housenumber":"294",
    "addr:postcode":"wa11 0jq",
    "addr:street":"Clipsley Lane Haydock",
    "iso:country":"GB",
    "sg:address":"294 Clipsley Lane, Haydock",
    "sg:city":"St Helens",
    "sg:classifiers":[
        {
            "category":"Food & Beverages",
            "subcategory":"Meat & Fish",
            "type":"Retail Goods"
        }
    ],
    "sg:phone":"+44 1744 612894",
    "sg:postcode":"WA11 0JQ",
    "sg:province":"Lancashire",
    "sg:tags":[
        "chip"
    ],
    "wof:name":"The Little Chippy",
    "wof:placetype":"venue"
},
  "geometry": {"coordinates":[-2.6775329113,53.4667472839],"type":"Point"}
}