{
  "type": "Feature",
  "properties": {
    "addr:full":"224 Malden Road, Cheam Sutton Surrey SM3 8EJ",
    "addr:housenumber":"224",
    "addr:postcode":"sm3 8ej",
    "addr:street":"Malden Road",
    "iso:country":"GB",
    "sg:address":"224 Malden Road, Cheam",
    "sg:city":"Sutton",
    "sg:classifiers":[
        {
            "category":"Personal",
            "subcategory":"Beauty Salon",
            "type":"Services"
        },
        {
            "category":"Personal",
            "subcategory":"Barber",
            "type":"Services"
        }
    ],
    "sg:phone":"+44 20 8644 9647",
    "sg:postcode":"SM3 8EJ",
    "sg:province":"Surrey",
    "sg:tags":[
        "unisex",
        "hairdresser"
    ],
    "wof:name":"Hair N Scissors",
    "wof:placetype":"venue"
},
  "geometry": {"coordinates":[-0.223016,51.365688],"type":"Point"}
}