{
  "type": "Feature",
  "properties": {
    "iso:country":"GB",
    "sg:address":"26 St Cuthbert Street",
    "sg:city":"Kirkcudbright",
    "sg:classifiers":[
        {
            "category":"Shopping",
            "subcategory":"Clothing, Apparel, & Fashions",
            "type":"Retail Goods"
        }
    ],
    "sg:phone":"+44 1557 330611",
    "sg:postcode":"DG6 4HZ",
    "sg:province":"Dumfries and Galloway",
    "sg:tags":[
        "shop"
    ],
    "wof:name":"Gowans",
    "wof:placetype":"venue"
},
  "geometry": {"coordinates":[-4.051474,54.83699],"type":"Point"}
}