{
  "type": "Feature",
  "properties": {
    "iso:country":"GB",
    "sg:address":"98 Guiserby Way, Durham Lane Industrial Estate",
    "sg:city":"Stockton-on-tees",
    "sg:classifiers":[
        {
            "category":"Shopping",
            "subcategory":"Computers & Home Electronics",
            "type":"Retail Goods"
        }
    ],
    "sg:postcode":"TS16 0PN",
    "sg:province":"Durham",
    "sg:tags":[
        "sound",
        "equipment"
    ],
    "wof:name":"Servemain",
    "wof:placetype":"venue"
},
  "geometry": {"coordinates":[-1.357229948,54.5293998718],"type":"Point"}
}