{
  "type": "Feature",
  "properties": {
    "iso:country":"GB",
    "sg:address":"Penhow, Llanvaches",
    "sg:city":"Caldicot",
    "sg:classifiers":[
        {
            "category":"Transit Center",
            "subcategory":"Passenger",
            "type":"Transportation"
        }
    ],
    "sg:phone":"+44 1633 400308",
    "sg:postcode":"NP26 3BA",
    "sg:province":"Monmouthshire",
    "sg:tags":[
        "boarding",
        "kennel",
        "catteries"
    ],
    "wof:name":"Huntshill Boarding Kennels & Cattery",
    "wof:placetype":"venue"
},
  "geometry": {"coordinates":[-2.748045,51.585957],"type":"Point"}
}