{
  "type": "Feature",
  "properties": {
    "iso:country":"GB",
    "sg:address":"Hollyhedge Rd",
    "sg:city":"West Bromwich",
    "sg:classifiers":[
        {
            "category":"Bars & Pubs",
            "type":"Food & Drink"
        },
        {
            "category":"Community Center",
            "subcategory":"Social",
            "type":"Public Place"
        }
    ],
    "sg:phone":"+44 121 567 0921",
    "sg:postcode":"B71 3BS",
    "sg:province":"West Midlands",
    "sg:tags":[
        "pubs",
        "house",
        "inn",
        "activity"
    ],
    "wof:name":"Crown & Anchor The",
    "wof:placetype":"venue"
},
  "geometry": {"coordinates":[-1.9811940193,52.5420265198],"type":"Point"}
}