{
  "type": "Feature",
  "properties": {
    "iso:country":"GB",
    "sg:address":"White House Business Centre, Imperial Business Park",
    "sg:city":"Gravesend",
    "sg:classifiers":[
        {
            "category":"Manufacturing",
            "subcategory":"Metals",
            "type":"Manufacturing & Wholesale Goods"
        }
    ],
    "sg:phone":"+44 1474 333360",
    "sg:postcode":"DA11 0AE",
    "sg:province":"Kent",
    "sg:tags":[
        "steel",
        "fabricator",
        "erectors"
    ],
    "wof:name":"Ray Engineering",
    "wof:placetype":"venue"
},
  "geometry": {"coordinates":[0.364606,51.432827],"type":"Point"}
}