{
  "type": "Feature",
  "properties": {
    "addr:full":"Altrincham Road Manchester Greater Manchester M22 4BJ",
    "addr:postcode":"m22 4bj",
    "addr:street":"Altrincham Road",
    "iso:country":"GB",
    "sg:address":"Altrincham Road",
    "sg:city":"Manchester",
    "sg:classifiers":[
        {
            "category":"Travel",
            "subcategory":"Hotels & Motels",
            "type":"Entertainment"
        }
    ],
    "sg:postcode":"M22 4BJ",
    "sg:province":"Greater Manchester",
    "wof:name":"Royals Hotel",
    "wof:placetype":"venue"
},
  "geometry": {"coordinates":[-2.264381,53.398674],"type":"Point"}
}