{
  "type": "Feature",
  "properties": {
    "addr:full":"Abacus Ho, Dudley St Luton Bedfordshire LU2 0NS",
    "addr:postcode":"lu2 0ns",
    "addr:street":"Dudley St",
    "iso:country":"GB",
    "sg:address":"Abacus Ho, Dudley St",
    "sg:city":"Luton",
    "sg:classifiers":[
        {
            "category":"Real Estate",
            "subcategory":"Surveying",
            "type":"Services"
        }
    ],
    "sg:phone":"+44 1582 702707",
    "sg:postcode":"LU2 0NS",
    "sg:province":"Bedfordshire",
    "sg:tags":[
        "surveyor",
        "valuer"
    ],
    "wof:name":"Estimating Services Ltd",
    "wof:placetype":"venue"
},
  "geometry": {"coordinates":[-0.4153999984,51.8839683533],"type":"Point"}
}