{
  "type": "Feature",
  "properties": {
    "addr:full":"23 Gibb Street Birmingham West Midlands B9 4AA",
    "addr:housenumber":"23",
    "addr:postcode":"b9 4aa",
    "addr:street":"Gibb Street",
    "iso:country":"GB",
    "sg:address":"23 Gibb Street",
    "sg:city":"Birmingham",
    "sg:classifiers":[
        {
            "category":"Professional",
            "subcategory":"Art Services",
            "type":"Services"
        }
    ],
    "sg:postcode":"B9 4AA",
    "sg:province":"West Midlands",
    "sg:tags":[
        "photographer"
    ],
    "wof:name":"Stephen Vernon-Clarke",
    "wof:placetype":"venue"
},
  "geometry": {"coordinates":[-1.884138,52.475216],"type":"Point"}
}