{
  "type": "Feature",
  "properties": {
    "iso:country":"GB",
    "sg:address":"96 Fisherton Street",
    "sg:city":"Salisbury",
    "sg:classifiers":[
        {
            "category":"Shopping",
            "subcategory":"Books",
            "type":"Retail Goods"
        }
    ],
    "sg:postcode":"SP2 7QY",
    "sg:province":"Wiltshire",
    "wof:name":"High Heel Productions",
    "wof:placetype":"venue"
},
  "geometry": {"coordinates":[-1.801468,51.070271],"type":"Point"}
}