{
  "type": "Feature",
  "properties": {
    "iso:country":"GB",
    "sg:address":"22 Church Street",
    "sg:city":"Godalming",
    "sg:classifiers":[
        {
            "category":"Manufacturing",
            "subcategory":"Tools & Machinery",
            "type":"Manufacturing & Wholesale Goods"
        }
    ],
    "sg:phone":"+44 1483 426966",
    "sg:postcode":"GU7 1EW",
    "sg:province":"Surrey",
    "sg:tags":[
        "society",
        "friendly"
    ],
    "wof:name":"Stoneways Insurance",
    "wof:placetype":"venue"
},
  "geometry": {"coordinates":[-0.615466,51.186291],"type":"Point"}
}