{
  "type": "Feature",
  "properties": {
    "addr:full":"193 Cole Lane, Borrowash Derby Derbyshire DE72 3GN",
    "addr:housenumber":"193",
    "addr:postcode":"de72 3gn",
    "addr:street":"Cole Lane",
    "iso:country":"GB",
    "sg:address":"193 Cole Lane, Borrowash",
    "sg:city":"Derby",
    "sg:classifiers":[
        {
            "category":"Bus Charters",
            "type":"Transportation"
        }
    ],
    "sg:phone":"+44 1332 663322",
    "sg:postcode":"DE72 3GN",
    "sg:province":"Derbyshire",
    "sg:tags":[
        "mini",
        "hire",
        "leasing"
    ],
    "wof:name":"K L Mini Hire & Services",
    "wof:placetype":"venue"
},
  "geometry": {"coordinates":[-1.3662400246,52.9071044922],"type":"Point"}
}