{
  "type": "Feature",
  "properties": {
    "iso:country":"GB",
    "sg:address":"71 St Albans Road, Sandridge",
    "sg:city":"St Albans",
    "sg:classifiers":[
        {
            "category":"Education",
            "subcategory":"Dance Studio",
            "type":"Public Place"
        }
    ],
    "sg:phone":"+44 1727 766430",
    "sg:postcode":"AL4 9LH",
    "sg:province":"Hertfordshire",
    "sg:tags":[
        "school",
        "dancing"
    ],
    "wof:name":"The Marguerita Hoare School of Dancing",
    "wof:placetype":"venue"
},
  "geometry": {"coordinates":[-0.313228,51.774132],"type":"Point"}
}