{
  "type": "Feature",
  "properties": {
    "addr:full":"66 Limmer Lane Bognor Regis West Sussex PO22 7HD",
    "addr:housenumber":"66",
    "addr:postcode":"po22 7hd",
    "addr:street":"Limmer Lane",
    "iso:country":"GB",
    "sg:address":"66 Limmer Lane",
    "sg:city":"Bognor Regis",
    "sg:classifiers":[
        {
            "category":"Building & Trades",
            "subcategory":"Construction",
            "type":"Services"
        }
    ],
    "sg:postcode":"PO22 7HD",
    "sg:province":"West Sussex",
    "sg:tags":[
        "builder"
    ],
    "wof:name":"Rowe Building",
    "wof:placetype":"venue"
},
  "geometry": {"coordinates":[-0.6461089849,50.789604187],"type":"Point"}
}