{
  "type": "Feature",
  "properties": {
    "iso:country":"GB",
    "sg:address":"Tirril",
    "sg:city":"Penrith",
    "sg:classifiers":[
        {
            "category":"Bars & Pubs",
            "type":"Food & Drink"
        },
        {
            "category":"Community Center",
            "subcategory":"Social",
            "type":"Public Place"
        }
    ],
    "sg:phone":"+44 1768 863219",
    "sg:postcode":"CA10 2JF",
    "sg:province":"Cumbria",
    "sg:tags":[
        "pubs",
        "house",
        "inn",
        "activity"
    ],
    "wof:name":"The Queens Head Inn",
    "wof:placetype":"venue"
},
  "geometry": {"coordinates":[-2.77207,54.632839],"type":"Point"}
}