{
  "type": "Feature",
  "properties": {
    "addr:full":"Framlingham Road, Kettleburgh Woodbridge Suffolk IP13 7LL",
    "addr:postcode":"ip13 7ll",
    "addr:street":"Framlingham Road",
    "iso:country":"GB",
    "sg:address":"Framlingham Road, Kettleburgh",
    "sg:city":"Woodbridge",
    "sg:classifiers":[
        {
            "category":"Professional",
            "subcategory":"Engineering",
            "type":"Services"
        },
        {
            "category":"Building & Trades",
            "subcategory":"Electrical",
            "type":"Services"
        }
    ],
    "sg:phone":"+44 1728 723289",
    "sg:postcode":"IP13 7LL",
    "sg:province":"Suffolk",
    "sg:tags":[
        "engineer",
        "electrician",
        "contractor"
    ],
    "wof:name":"CORSTON ELECTRICAL DESIGN & TESTING LTD",
    "wof:placetype":"venue"
},
  "geometry": {"coordinates":[1.311451,52.193314],"type":"Point"}
}