{
  "type": "Feature",
  "properties": {
    "addr:full":"Crooklands Farm, Crooklands Milnthorpe Cumbria LA7 7NW",
    "addr:postcode":"la7 7nw",
    "addr:street":"Crooklands;Crooklands",
    "iso:country":"GB",
    "sg:address":"Crooklands Farm, Crooklands",
    "sg:city":"Milnthorpe",
    "sg:classifiers":[
        {
            "category":"Farming",
            "subcategory":"Livestock Farm",
            "type":"Manufacturing & Wholesale Goods"
        },
        {
            "category":"Farming",
            "subcategory":"Farm",
            "type":"Manufacturing & Wholesale Goods"
        }
    ],
    "sg:phone":"+44 15395 67375",
    "sg:postcode":"LA7 7NW",
    "sg:province":"Cumbria",
    "sg:tags":[
        "mixed",
        "crop",
        "others"
    ],
    "wof:name":"Thomas Edward Dalbraith",
    "wof:placetype":"venue"
},
  "geometry": {"coordinates":[-2.772592,54.226864],"type":"Point"}
}