{
  "type": "Feature",
  "properties": {
    "iso:country":"GB",
    "sg:address":"6-17 Pundersons Gardens",
    "sg:city":"London",
    "sg:classifiers":[
        {
            "category":"Professional",
            "subcategory":"Management & Consulting",
            "type":"Services"
        }
    ],
    "sg:phone":"+44 20 7739 3062",
    "sg:postcode":"E2 9RU",
    "sg:province":"Greater London",
    "sg:tags":[
        "marketing",
        "consultant"
    ],
    "wof:name":"The John Grant",
    "wof:placetype":"venue"
},
  "geometry": {"coordinates":[-0.058189,51.528625],"type":"Point"}
}