{
  "type": "Feature",
  "properties": {
    "addr:full":"Trevenson Campus, Pool Redruth Cornwall TR15 3RD",
    "addr:postcode":"tr15 3rd",
    "iso:country":"GB",
    "sg:address":"Trevenson Campus, Pool",
    "sg:city":"Redruth",
    "sg:classifiers":[
        {
            "category":"Personal",
            "subcategory":"Beauty Salon",
            "type":"Services"
        },
        {
            "category":"Education",
            "subcategory":"University",
            "type":"Public Place"
        }
    ],
    "sg:postcode":"TR15 3RD",
    "sg:province":"Cornwall",
    "sg:tags":[
        "unisex",
        "higher",
        "hairdresser"
    ],
    "wof:name":"Cornwall College",
    "wof:placetype":"venue"
},
  "geometry": {"coordinates":[-5.266689,50.228035],"type":"Point"}
}