{
  "type": "Feature",
  "properties": {
    "addr:full":"Radio Ho, Whittle Ave Fareham Hampshire PO15 5SH",
    "addr:postcode":"po15 5sh",
    "addr:street":"Whittle Ave",
    "iso:country":"GB",
    "sg:address":"Radio Ho, Whittle Ave",
    "sg:city":"Fareham",
    "sg:classifiers":[
        {
            "category":"Communications",
            "type":"Services"
        },
        {
            "category":"Government",
            "subcategory":"Post Office",
            "type":"Public Place"
        }
    ],
    "sg:phone":"+44 1489 589911",
    "sg:postcode":"PO15 5SH",
    "sg:province":"Hampshire",
    "sg:tags":[
        "broadcasting"
    ],
    "wof:name":"Power Fm Ltd",
    "wof:placetype":"venue"
},
  "geometry": {"coordinates":[-1.2590399981,50.8702583313],"type":"Point"}
}