{
  "type": "Feature",
  "properties": {
    "iso:country":"GB",
    "sg:address":"50 St Martins Rd",
    "sg:city":"Dartford",
    "sg:classifiers":[
        {
            "category":"Real Estate",
            "subcategory":"Architect",
            "type":"Services"
        }
    ],
    "sg:postcode":"DA1 1UJ",
    "sg:province":"Kent",
    "sg:tags":[
        "architectural"
    ],
    "wof:name":"Atkin,Chris,",
    "wof:placetype":"venue"
},
  "geometry": {"coordinates":[0.225794,51.445724],"type":"Point"}
}