{
  "type": "Feature",
  "properties": {
    "addr:full":"62 Fore St Bodmin Cornwall PL31 2HR",
    "addr:housenumber":"62",
    "addr:postcode":"pl31 2hr",
    "addr:street":"Fore St",
    "iso:country":"GB",
    "sg:address":"62 Fore St",
    "sg:city":"Bodmin",
    "sg:classifiers":[
        {
            "category":"Health Services",
            "subcategory":"Clinic",
            "type":"Services"
        }
    ],
    "sg:phone":"+44 1208 73234",
    "sg:postcode":"PL31 2HR",
    "sg:province":"Cornwall",
    "sg:tags":[
        "private"
    ],
    "wof:name":"Bodmin Fertility Clinic",
    "wof:placetype":"venue"
},
  "geometry": {"coordinates":[-4.7219729424,50.4711227417],"type":"Point"}
}