{
  "type": "Feature",
  "properties": {
    "addr:full":"Exchange Shopping Centre, Bennett Precinct, Market Street Stoke-on-trent Staffordshire ST3 1BX",
    "addr:postcode":"st3 1bx",
    "addr:street":"Market Street",
    "iso:country":"GB",
    "sg:address":"Exchange Shopping Centre, Bennett Precinct, Market Street",
    "sg:city":"Stoke-on-trent",
    "sg:classifiers":[
        {
            "category":"Shopping",
            "subcategory":"Clothing, Apparel, & Fashions",
            "type":"Retail Goods"
        }
    ],
    "sg:phone":"+44 1782 595606",
    "sg:postcode":"ST3 1BX",
    "sg:province":"Staffordshire",
    "sg:tags":[
        "ladieswear"
    ],
    "wof:name":"Select",
    "wof:placetype":"venue"
},
  "geometry": {"coordinates":[-2.1350500584,52.9890594482],"type":"Point"}
}