{
  "type": "Feature",
  "properties": {
    "iso:country":"GB",
    "sg:address":"Unit 44a, Smarts Heath Lane",
    "sg:city":"Woking",
    "sg:classifiers":[
        {
            "category":"Building & Trades",
            "subcategory":"Construction",
            "type":"Services"
        }
    ],
    "sg:phone":"+44 1483 237899",
    "sg:postcode":"GU22 0RQ",
    "sg:province":"Surrey",
    "sg:tags":[
        "platform",
        "builder",
        "work",
        "scaffolding"
    ],
    "wof:name":"Miles Scaffolding",
    "wof:placetype":"venue"
},
  "geometry": {"coordinates":[-0.5908430219,51.2918968201],"type":"Point"}
}