{
  "type": "Feature",
  "properties": {
    "iso:country":"GB",
    "sg:address":"The Moss, Moss Lane",
    "sg:city":"Nantwich",
    "sg:classifiers":[
        {
            "category":"Farming",
            "subcategory":"Dairy Farm",
            "type":"Manufacturing & Wholesale Goods"
        }
    ],
    "sg:phone":"+44 1270 841480",
    "sg:postcode":"CW5 7HB",
    "sg:province":"Cheshire",
    "wof:name":"F E O Shone & Son",
    "wof:placetype":"venue"
},
  "geometry": {"coordinates":[-2.516502,53.065891],"type":"Point"}
}