{
  "type": "Feature",
  "properties": {
    "iso:country":"GB",
    "sg:address":"42 Back Rd, Lynton",
    "sg:city":"Cambridge",
    "sg:classifiers":[
        {
            "category":"Professional",
            "subcategory":"Engineering",
            "type":"Services"
        }
    ],
    "sg:postcode":"CB1 6JF",
    "sg:province":"Cambridgeshire",
    "sg:tags":[
        "contractor",
        "electrical",
        "engineer"
    ],
    "wof:name":"Security Advisory Service (The)",
    "wof:placetype":"venue"
},
  "geometry": {"coordinates":[0.27637,52.102036],"type":"Point"}
}