{
  "type": "Feature",
  "properties": {
    "addr:full":"New Bungalow, Bungalow Gaunt Farm, Gaunt Fen Chatteris Cambridgeshire PE16 6TF",
    "addr:postcode":"pe16 6tf",
    "addr:street":"Gaunt;Gaunt Fen",
    "iso:country":"GB",
    "sg:address":"New Bungalow, Bungalow Gaunt Farm, Gaunt Fen",
    "sg:city":"Chatteris",
    "sg:classifiers":[
        {
            "category":"Farming",
            "subcategory":"Livestock Farm",
            "type":"Manufacturing & Wholesale Goods"
        }
    ],
    "sg:phone":"+44 1354 692674",
    "sg:postcode":"PE16 6TF",
    "sg:province":"Cambridgeshire",
    "sg:tags":[
        "others"
    ],
    "wof:name":"Douglas J Howard",
    "wof:placetype":"venue"
},
  "geometry": {"coordinates":[0.048666,52.453632],"type":"Point"}
}