{
  "type": "Feature",
  "properties": {
    "addr:full":"Crawley Ridge Camberley Berkshire GU15 2AJ",
    "addr:postcode":"gu15 2aj",
    "addr:street":"Crawley Ridge",
    "iso:country":"GB",
    "sg:address":"Crawley Ridge",
    "sg:city":"Camberley",
    "sg:classifiers":[
        {
            "category":"Farming",
            "subcategory":"Nursery",
            "type":"Manufacturing & Wholesale Goods"
        },
        {
            "category":"Education",
            "subcategory":"School",
            "type":"Public Place"
        }
    ],
    "sg:phone":"+44 1276 27546",
    "sg:postcode":"GU15 2AJ",
    "sg:province":"Berkshire",
    "sg:tags":[
        "local",
        "creche",
        "authority"
    ],
    "wof:name":"Crawley Ridge Infant School",
    "wof:placetype":"venue"
},
  "geometry": {"coordinates":[-0.718609,51.343994],"type":"Point"}
}