{
  "type": "Feature",
  "properties": {
    "addr:full":"Warren Road Scunthorpe Lincolnshire DN15 6XH",
    "addr:postcode":"dn15 6xh",
    "addr:street":"Warren Road",
    "iso:country":"GB",
    "sg:address":"Warren Road",
    "sg:city":"Scunthorpe",
    "sg:classifiers":[
        {
            "category":"Autos & Motor Vehicles",
            "subcategory":"Auto Supplies",
            "type":"Retail Goods"
        },
        {
            "category":"Shopping",
            "type":"Retail Goods"
        }
    ],
    "sg:phone":"+44 1724 844835",
    "sg:postcode":"DN15 6XH",
    "sg:province":"Lincolnshire",
    "sg:tags":[
        "part",
        "component",
        "accessory"
    ],
    "wof:name":"Carter Factors",
    "wof:placetype":"venue"
},
  "geometry": {"coordinates":[-0.644849,53.598801],"type":"Point"}
}