{
  "type": "Feature",
  "properties": {
    "addr:full":"11 Holligrave Road Bromley Kent BR1 3PJ",
    "addr:housenumber":"11",
    "addr:postcode":"br1 3pj",
    "addr:street":"Holligrave Road",
    "iso:country":"GB",
    "sg:address":"11 Holligrave Road",
    "sg:city":"Bromley",
    "sg:classifiers":[
        {
            "category":"Health Services",
            "subcategory":"Health Practitioner",
            "type":"Services"
        }
    ],
    "sg:postcode":"BR1 3PJ",
    "sg:province":"Kent",
    "sg:tags":[
        "osteopath"
    ],
    "wof:name":"B Judge",
    "wof:placetype":"venue"
},
  "geometry": {"coordinates":[0.0170210004,51.4113121033],"type":"Point"}
}