{
  "type": "Feature",
  "properties": {
    "iso:country":"GB",
    "sg:address":"1 Charles Street",
    "sg:city":"Worcester",
    "sg:classifiers":[
        {
            "category":"Personal",
            "subcategory":"Beauty Salon",
            "type":"Services"
        }
    ],
    "sg:phone":"+44 1905 613704",
    "sg:postcode":"WR1 2AQ",
    "sg:province":"Worcestershire",
    "sg:tags":[
        "unisex",
        "hairdresser"
    ],
    "wof:name":"The Chop Shop",
    "wof:placetype":"venue"
},
  "geometry": {"coordinates":[-2.218354,52.190708],"type":"Point"}
}