{
  "type": "Feature",
  "properties": {
    "iso:country":"GB",
    "sg:address":"37 Gloucester Road",
    "sg:city":"Coleford",
    "sg:classifiers":[
        {
            "category":"Organizations",
            "subcategory":"Community Association",
            "type":"Services"
        },
        {
            "category":"Organizations",
            "subcategory":"Non-profit Organization",
            "type":"Services"
        }
    ],
    "sg:phone":"+44 1594 833381",
    "sg:postcode":"GL16 8BH",
    "sg:province":"Gloucestershire",
    "sg:tags":[
        "voluntary",
        "organisation",
        "animal",
        "welfare",
        "charity",
        "care"
    ],
    "wof:name":"Cats Protection League",
    "wof:placetype":"venue"
},
  "geometry": {"coordinates":[-2.6144959927,51.7948150635],"type":"Point"}
}