{
  "type": "Feature",
  "properties": {
    "addr:full":"The Enterprise Centre Middlesbrough Durham TS2 1LZ",
    "addr:postcode":"ts2 1lz",
    "addr:street":"Middlesbrough",
    "iso:country":"GB",
    "sg:address":"The Enterprise Centre",
    "sg:city":"Middlesbrough",
    "sg:classifiers":[
        {
            "category":"Professional",
            "subcategory":"Engineering",
            "type":"Services"
        },
        {
            "category":"Building & Trades",
            "subcategory":"Construction",
            "type":"Services"
        }
    ],
    "sg:phone":"+44 1642 232146",
    "sg:postcode":"TS2 1LZ",
    "sg:province":"Durham",
    "sg:tags":[
        "contractor",
        "gas",
        "heating",
        "engineer"
    ],
    "wof:name":"Maclean & Nuttall Ltd.",
    "wof:placetype":"venue"
},
  "geometry": {"coordinates":[-1.2365599871,54.5830612183],"type":"Point"}
}