{
  "type": "Feature",
  "properties": {
    "addr:full":"Manor Farm, Blackwell Shipston-on-stour Warwickshire CV36 4PE",
    "addr:postcode":"cv36 4pe",
    "addr:street":"Manor",
    "iso:country":"GB",
    "sg:address":"Manor Farm, Blackwell",
    "sg:city":"Shipston-on-stour",
    "sg:classifiers":[
        {
            "category":"Home & Garden",
            "subcategory":"Garden Supply",
            "type":"Retail Goods"
        }
    ],
    "sg:phone":"+44 1608 682248",
    "sg:postcode":"CV36 4PE",
    "sg:province":"Warwickshire",
    "sg:tags":[
        "bulb",
        "grower"
    ],
    "wof:name":"David Kerby & Son",
    "wof:placetype":"venue"
},
  "geometry": {"coordinates":[-1.627134,52.062271],"type":"Point"}
}