{
  "type": "Feature",
  "properties": {
    "addr:full":"Hawthorn Cottage Cockburnspath East Lothian TD13 5YF",
    "addr:postcode":"td13 5yf",
    "addr:street":"Cockburnspath",
    "iso:country":"GB",
    "sg:address":"Hawthorn Cottage",
    "sg:city":"Cockburnspath",
    "sg:classifiers":[
        {
            "category":"Wholesale",
            "subcategory":"Sporting Goods",
            "type":"Manufacturing & Wholesale Goods"
        }
    ],
    "sg:phone":"+44 1368 830240",
    "sg:postcode":"TD13 5YF",
    "sg:province":"East Lothian",
    "sg:tags":[
        "mnfr",
        "sport",
        "equipment"
    ],
    "wof:name":"Ride Snowboards Inc",
    "wof:placetype":"venue"
},
  "geometry": {"coordinates":[-2.36145,55.932983],"type":"Point"}
}