{
  "type": "Feature",
  "properties": {
    "addr:full":"52 St Albans Avenue, Hartshead Ashton-under-lyne Greater Manchester OL6 8DG",
    "addr:housenumber":"52",
    "addr:postcode":"ol6 8dg",
    "addr:street":"St Albans Avenue Hartshead",
    "iso:country":"GB",
    "sg:address":"52 St Albans Avenue, Hartshead",
    "sg:city":"Ashton-under-lyne",
    "sg:classifiers":[
        {
            "category":"Retail",
            "subcategory":"Laundry & Dry Cleaning",
            "type":"Services"
        }
    ],
    "sg:phone":"+44 161 339 0938",
    "sg:postcode":"OL6 8DG",
    "sg:province":"Greater Manchester",
    "sg:tags":[
        "alteration"
    ],
    "wof:name":"Shirley's Valet Service",
    "wof:placetype":"venue"
},
  "geometry": {"coordinates":[-2.0821630955,53.5084075928],"type":"Point"}
}