{
  "type": "Feature",
  "properties": {
    "addr:full":"Unit 2, Rear Of 28 Broomfield Rd, Urdington Birmingham West Midlands B23 7QA",
    "addr:housenumber":"unit 2 rear of 28",
    "addr:postcode":"b23 7qa",
    "addr:street":"Broomfield Rd",
    "iso:country":"GB",
    "sg:address":"Unit 2, Rear Of 28 Broomfield Rd, Urdington",
    "sg:city":"Birmingham",
    "sg:classifiers":[
        {
            "category":"Retail",
            "subcategory":"Auto Repair",
            "type":"Services"
        }
    ],
    "sg:phone":"+44 121 327 7031",
    "sg:postcode":"B23 7QA",
    "sg:province":"West Midlands",
    "sg:tags":[
        "modification",
        "garage"
    ],
    "wof:name":"Knotts Services",
    "wof:placetype":"venue"
},
  "geometry": {"coordinates":[-1.8593100309,52.5141410828],"type":"Point"}
}