{
  "type": "Feature",
  "properties": {
    "addr:full":"4 High Street Thames Ditton Surrey KT7 0RY",
    "addr:housenumber":"4",
    "addr:postcode":"kt7 0ry",
    "addr:street":"High Street",
    "iso:country":"GB",
    "sg:address":"4 High Street",
    "sg:city":"Thames Ditton",
    "sg:classifiers":[
        {
            "category":"Organizations",
            "subcategory":"Membership Organization",
            "type":"Services"
        }
    ],
    "sg:postcode":"KT7 0RY",
    "sg:province":"Surrey",
    "sg:tags":[
        "club"
    ],
    "wof:name":"Porton Court Residents Co Ltd",
    "wof:placetype":"venue"
},
  "geometry": {"coordinates":[-0.3333550096,51.3897323608],"type":"Point"}
}