{
  "type": "Feature",
  "properties": {
    "addr:full":"182a Durham Road Bradford West Yorkshire BD8 9HU",
    "addr:housenumber":"182a",
    "addr:postcode":"bd8 9hu",
    "addr:street":"Durham Road",
    "iso:country":"GB",
    "sg:address":"182a Durham Road",
    "sg:city":"Bradford",
    "sg:classifiers":[
        {
            "category":"Organizations",
            "subcategory":"Non-profit Organization",
            "type":"Services"
        }
    ],
    "sg:phone":"+44 1274 544358",
    "sg:postcode":"BD8 9HU",
    "sg:province":"West Yorkshire",
    "sg:tags":[
        "charitable",
        "organisation",
        "voluntary",
        "charity"
    ],
    "wof:name":"Girlington Muslim Welfare Association",
    "wof:placetype":"venue"
},
  "geometry": {"coordinates":[-1.7857370377,53.8024673462],"type":"Point"}
}