{
  "type": "Feature",
  "properties": {
    "addr:full":"30a Fore Street Callington Cornwall PL17 7AD",
    "addr:housenumber":"30a",
    "addr:postcode":"pl17 7ad",
    "addr:street":"Fore Street",
    "iso:country":"GB",
    "sg:address":"30a Fore Street",
    "sg:city":"Callington",
    "sg:classifiers":[
        {
            "category":"Food & Beverages",
            "subcategory":"Meat & Fish",
            "type":"Retail Goods"
        }
    ],
    "sg:phone":"+44 1579 384999",
    "sg:postcode":"PL17 7AD",
    "sg:province":"Cornwall",
    "sg:tags":[
        "chip"
    ],
    "wof:name":"Kelly's of Callington",
    "wof:placetype":"venue"
},
  "geometry": {"coordinates":[-4.3166890144,50.5033912659],"type":"Point"}
}