{
  "type": "Feature",
  "properties": {
    "iso:country":"GB",
    "sg:address":"30a Fore Street",
    "sg:city":"Callington",
    "sg:classifiers":[
        {
            "category":"Food & Beverages",
            "subcategory":"Meat & Fish",
            "type":"Retail Goods"
        }
    ],
    "sg:phone":"+44 1579 384999",
    "sg:postcode":"PL17 7AD",
    "sg:province":"Cornwall",
    "sg:tags":[
        "chip"
    ],
    "wof:name":"Kelly's of Callington",
    "wof:placetype":"venue"
},
  "geometry": {"coordinates":[-4.3166890144,50.5033912659],"type":"Point"}
}