{
  "type": "Feature",
  "properties": {
    "iso:country":"GB",
    "sg:address":"Hazel Dene, Woodhouse Lane",
    "sg:city":"Brighouse",
    "sg:classifiers":[
        {
            "category":"Personal",
            "subcategory":"Tanning Parlor",
            "type":"Services"
        }
    ],
    "sg:phone":"+44 1484 401040",
    "sg:postcode":"HD6 3TH",
    "sg:province":"West Yorkshire",
    "sg:tags":[
        "sunbeds"
    ],
    "wof:name":"Mr Tan the Sunbed Man",
    "wof:placetype":"venue"
},
  "geometry": {"coordinates":[-1.7737369537,53.7021942139],"type":"Point"}
}