{
  "type": "Feature",
  "properties": {
    "addr:full":"Station Garage, Oldmeldrum Inverurie Aberdeenshire AB51 0EZ",
    "addr:postcode":"ab51 0ez",
    "iso:country":"GB",
    "sg:address":"Station Garage, Oldmeldrum",
    "sg:city":"Inverurie",
    "sg:classifiers":[
        {
            "category":"Bus Charters",
            "type":"Transportation"
        }
    ],
    "sg:postcode":"AB51 0EZ",
    "sg:province":"Aberdeenshire",
    "sg:tags":[
        "coach"
    ],
    "wof:name":"Baines Coaches",
    "wof:placetype":"venue"
},
  "geometry": {"coordinates":[-2.3240189552,57.3347167969],"type":"Point"}
}