{
  "type": "Feature",
  "properties": {
    "iso:country":"GB",
    "sg:address":"24 Westmead Dr, Salfords",
    "sg:city":"Redhill",
    "sg:classifiers":[
        {
            "category":"Professional",
            "type":"Services"
        }
    ],
    "sg:postcode":"RH1 5DB",
    "sg:province":"Surrey",
    "sg:tags":[
        "repair",
        "tech",
        "maintenance"
    ],
    "wof:name":"Saunders,Michael,",
    "wof:placetype":"venue"
},
  "geometry": {"coordinates":[-0.163891,51.202202],"type":"Point"}
}