{
  "type": "Feature",
  "properties": {
    "addr:full":"3 Blind Lane, Breadhurst Gillingham Kent ME7 3JR",
    "addr:housenumber":"3",
    "addr:postcode":"me7 3jr",
    "addr:street":"Blind Lane Breadhurst",
    "iso:country":"GB",
    "sg:address":"3 Blind Lane, Breadhurst",
    "sg:city":"Gillingham",
    "sg:classifiers":[
        {
            "category":"Retail",
            "subcategory":"Auto Repair",
            "type":"Services"
        }
    ],
    "sg:phone":"+44 1634 375193",
    "sg:postcode":"ME7 3JR",
    "sg:province":"Kent",
    "sg:tags":[
        "modification",
        "garage"
    ],
    "wof:name":"Alan Cyril Croucher",
    "wof:placetype":"venue"
},
  "geometry": {"coordinates":[0.5706980228,51.3297386169],"type":"Point"}
}