{
  "type": "Feature",
  "properties": {
    "iso:country":"GB",
    "sg:address":"Unit D",
    "sg:city":"Camelford",
    "sg:classifiers":[
        {
            "category":"Wholesale",
            "subcategory":"Sporting Goods",
            "type":"Manufacturing & Wholesale Goods"
        },
        {
            "category":"Professional",
            "subcategory":"Business Services",
            "type":"Services"
        }
    ],
    "sg:phone":"+44 1840 212955",
    "sg:postcode":"PL32 9RA",
    "sg:province":"Cornwall",
    "sg:tags":[
        "mnfr",
        "sport",
        "manufacturer",
        "equipment"
    ],
    "sg:website":"http://www.stix.co.uk",
    "wof:name":"Jay Jay Sports Ltd.",
    "wof:placetype":"venue"
},
  "geometry": {"coordinates":[-4.678636,50.623116],"type":"Point"}
}