{
  "type": "Feature",
  "properties": {
    "addr:full":"37 King St Luton Bedfordshire LU1 2DW",
    "addr:housenumber":"37",
    "addr:postcode":"lu1 2dw",
    "addr:street":"King St",
    "iso:country":"GB",
    "sg:address":"37 King St",
    "sg:city":"Luton",
    "sg:classifiers":[
        {
            "category":"Professional",
            "subcategory":"Lawyer & Legal Services",
            "type":"Services"
        }
    ],
    "sg:phone":"+44 1582 454777",
    "sg:postcode":"LU1 2DW",
    "sg:province":"Bedfordshire",
    "sg:tags":[
        "solicitor"
    ],
    "wof:name":"Howe Roache & Waller",
    "wof:placetype":"venue"
},
  "geometry": {"coordinates":[-0.417666,51.878014],"type":"Point"}
}