{
  "type": "Feature",
  "properties": {
    "iso:country":"GB",
    "sg:address":"8a Buckingham Avenue",
    "sg:city":"Slough",
    "sg:classifiers":[
        {
            "category":"Manufacturing",
            "subcategory":"Metals",
            "type":"Manufacturing & Wholesale Goods"
        }
    ],
    "sg:postcode":"SL1 4SD",
    "sg:province":"Berkshire",
    "sg:tags":[
        "steel",
        "stockholder"
    ],
    "wof:name":"Corus U K Ltd.",
    "wof:placetype":"venue"
},
  "geometry": {"coordinates":[-0.6339619756,51.5235557556],"type":"Point"}
}