{
  "type": "Feature",
  "properties": {
    "iso:country":"GB",
    "sg:address":"15 The Sycamores, Hersden",
    "sg:city":"Canterbury",
    "sg:classifiers":[
        {
            "category":"Building & Trades",
            "subcategory":"Construction",
            "type":"Services"
        }
    ],
    "sg:postcode":"CT3 4JA",
    "sg:province":"Kent",
    "sg:tags":[
        "joinery",
        "joiner",
        "carpenter",
        "carpentry"
    ],
    "wof:name":"MAURICE E EDWARDS",
    "wof:placetype":"venue"
},
  "geometry": {"coordinates":[1.158362,51.314281],"type":"Point"}
}