{
  "type": "Feature",
  "properties": {
    "addr:full":"17 Broomfield Road Chelmsford Essex CM1 1SY",
    "addr:housenumber":"17",
    "addr:postcode":"cm1 1sy",
    "addr:street":"Broomfield Road",
    "iso:country":"GB",
    "sg:address":"17 Broomfield Road",
    "sg:city":"Chelmsford",
    "sg:classifiers":[
        {
            "category":"Restaurant",
            "type":"Food & Drink"
        }
    ],
    "sg:phone":"+44 1245 491088",
    "sg:postcode":"CM1 1SY",
    "sg:province":"Essex",
    "sg:tags":[
        "-",
        "chinese"
    ],
    "wof:name":"Lantern House Restaurant",
    "wof:placetype":"venue"
},
  "geometry": {"coordinates":[0.465795,51.738079],"type":"Point"}
}