{
  "type": "Feature",
  "properties": {
    "iso:country":"GB",
    "sg:address":"33 High Street",
    "sg:city":"Glastonbury",
    "sg:classifiers":[
        {
            "category":"Deli",
            "type":"Food & Drink"
        },
        {
            "category":"Food & Beverages",
            "subcategory":"Bakery",
            "type":"Retail Goods"
        }
    ],
    "sg:phone":"+44 1458 832116",
    "sg:postcode":"BA6 9HT",
    "sg:province":"Somerset",
    "sg:tags":[
        "baker",
        "delicatessen"
    ],
    "wof:name":"The Truckle of Cheese",
    "wof:placetype":"venue"
},
  "geometry": {"coordinates":[-2.715011,51.147957],"type":"Point"}
}