{
  "type": "Feature",
  "properties": {
    "addr:full":"8 Queen Anne Street London Greater London W1G 9LG",
    "addr:housenumber":"8",
    "addr:postcode":"w1g 9lg",
    "addr:street":"Queen Anne Street",
    "iso:country":"GB",
    "sg:address":"8 Queen Anne Street",
    "sg:city":"London",
    "sg:classifiers":[
        {
            "category":"Real Estate",
            "subcategory":"Real Estate Agent",
            "type":"Services"
        }
    ],
    "sg:phone":"+44 20 7436 2339",
    "sg:postcode":"W1G 9LG",
    "sg:province":"Greater London",
    "wof:name":"Eskmuir Properties Ltd.",
    "wof:placetype":"venue"
},
  "geometry": {"coordinates":[-0.1463119984,51.5183181763],"type":"Point"}
}