{
  "type": "Feature",
  "properties": {
    "addr:full":"Manor Farm, Upper Wick Dursley Gloucestershire GL11 6DE",
    "addr:postcode":"gl11 6de",
    "addr:street":"Manor;Upper",
    "iso:country":"GB",
    "sg:address":"Manor Farm, Upper Wick",
    "sg:city":"Dursley",
    "sg:classifiers":[
        {
            "category":"Farming",
            "subcategory":"Crops",
            "type":"Manufacturing & Wholesale Goods"
        },
        {
            "category":"Farming",
            "subcategory":"Dairy Farm",
            "type":"Manufacturing & Wholesale Goods"
        },
        {
            "category":"Farming",
            "subcategory":"Livestock Farm",
            "type":"Manufacturing & Wholesale Goods"
        }
    ],
    "sg:postcode":"GL11 6DE",
    "sg:province":"Gloucestershire",
    "sg:tags":[
        "arable",
        "others"
    ],
    "wof:name":"COLIN G REA",
    "wof:placetype":"venue"
},
  "geometry": {"coordinates":[-2.4060559273,51.6703681946],"type":"Point"}
}