{
  "type": "Feature",
  "properties": {
    "addr:full":"Prescot Rd Liverpool Lancashire L31 1AR",
    "addr:postcode":"l31 1ar",
    "addr:street":"Prescot Rd",
    "iso:country":"GB",
    "sg:address":"Prescot Rd",
    "sg:city":"Liverpool",
    "sg:classifiers":[
        {
            "category":"Food & Beverages",
            "subcategory":"Farmers Market",
            "type":"Retail Goods"
        }
    ],
    "sg:phone":"+44 151 546 0422",
    "sg:postcode":"L31 1AR",
    "sg:province":"Lancashire",
    "sg:tags":[
        "farm",
        "shop",
        "pyo"
    ],
    "wof:name":"Bells Farm",
    "wof:placetype":"venue"
},
  "geometry": {"coordinates":[-2.9002029896,53.5217323303],"type":"Point"}
}