{
  "type": "Feature",
  "properties": {
    "addr:full":"163 Wardour Street, West End London Greater London W1F 8WL",
    "addr:housenumber":"163",
    "addr:postcode":"w1f 8wl",
    "addr:street":"Wardour Street",
    "iso:country":"GB",
    "sg:address":"163 Wardour Street, West End",
    "sg:city":"London",
    "sg:classifiers":[
        {
            "category":"Personal",
            "type":"Services"
        }
    ],
    "sg:phone":"+44 20 7437 0393",
    "sg:postcode":"W1F 8WL",
    "sg:province":"Greater London",
    "sg:tags":[
        "tailor"
    ],
    "wof:name":"Dave Rose",
    "wof:placetype":"venue"
},
  "geometry": {"coordinates":[-0.135027,51.514565],"type":"Point"}
}