{
  "type": "Feature",
  "properties": {
    "addr:full":"Norlivean, Staplecrosss Robertsbridge East Sussex TN32 5QB",
    "addr:postcode":"tn32 5qb",
    "iso:country":"GB",
    "sg:address":"Norlivean, Staplecrosss",
    "sg:city":"Robertsbridge",
    "sg:classifiers":[
        {
            "category":"Professional",
            "subcategory":"Business Services",
            "type":"Services"
        }
    ],
    "sg:phone":"+44 1580 830356",
    "sg:postcode":"TN32 5QB",
    "sg:province":"East Sussex",
    "sg:tags":[
        "food",
        "import",
        "export",
        "agent"
    ],
    "wof:name":"Keith Matthews",
    "wof:placetype":"venue"
},
  "geometry": {"coordinates":[0.4744699895,50.9856491089],"type":"Point"}
}