{
  "type": "Feature",
  "properties": {
    "addr:full":"6 Dane Drive Wilmslow Cheshire SK9 2AH",
    "addr:housenumber":"6",
    "addr:postcode":"sk9 2ah",
    "addr:street":"Dane Drive",
    "iso:country":"GB",
    "sg:address":"6 Dane Drive",
    "sg:city":"Wilmslow",
    "sg:classifiers":[
        {
            "category":"Professional",
            "subcategory":"Management & Consulting",
            "type":"Services"
        }
    ],
    "sg:postcode":"SK9 2AH",
    "sg:province":"Cheshire",
    "sg:tags":[
        "marketing",
        "consultant"
    ],
    "wof:name":"Consulting Anderson",
    "wof:placetype":"venue"
},
  "geometry": {"coordinates":[-2.214488,53.324745],"type":"Point"}
}