{
  "type": "Feature",
  "properties": {
    "iso:country":"GB",
    "sg:address":"Nottingham Road",
    "sg:city":"Melton Mowbray",
    "sg:classifiers":[
        {
            "category":"Autos & Motor Vehicles",
            "subcategory":"Fuel & Gas Station",
            "type":"Retail Goods"
        }
    ],
    "sg:phone":"+44 1664 562527",
    "sg:postcode":"LE13 0NR",
    "sg:province":"Leicestershire",
    "sg:tags":[
        "hr",
        "petrol"
    ],
    "wof:name":"Brookside Service Station",
    "wof:placetype":"venue"
},
  "geometry": {"coordinates":[-0.899399,52.780403],"type":"Point"}
}