{
  "type": "Feature",
  "properties": {
    "addr:full":"38 Carrington Lane, Milford On Sea Lymington Hampshire SO41 0RB",
    "addr:housenumber":"38",
    "addr:postcode":"so41 0rb",
    "addr:street":"Carrington Lane",
    "iso:country":"GB",
    "sg:address":"38 Carrington Lane, Milford On Sea",
    "sg:city":"Lymington",
    "sg:classifiers":[
        {
            "category":"Social Services",
            "subcategory":"Job Training",
            "type":"Services"
        }
    ],
    "sg:postcode":"SO41 0RB",
    "sg:province":"Hampshire",
    "sg:tags":[
        "draughtsman",
        "drawing"
    ],
    "wof:name":"Milford Draughting & Tracing Services",
    "wof:placetype":"venue"
},
  "geometry": {"coordinates":[-1.5844860077,50.7272033691],"type":"Point"}
}