{
  "type": "Feature",
  "properties": {
    "iso:country":"GB",
    "sg:address":"4 Princes Street",
    "sg:city":"Norwich",
    "sg:classifiers":[
        {
            "category":"Professional",
            "subcategory":"Computer Services",
            "type":"Services"
        }
    ],
    "sg:phone":"+44 1603 610900",
    "sg:postcode":"NR3 1AZ",
    "sg:province":"Norfolk",
    "sg:tags":[
        "information"
    ],
    "wof:name":"Exin",
    "wof:placetype":"venue"
},
  "geometry": {"coordinates":[1.295991,52.630863],"type":"Point"}
}