{
  "type": "Feature",
  "properties": {
    "addr:full":"126 Whiteladies Rd Bristol City of Bristol BS8 2RP",
    "addr:housenumber":"126",
    "addr:postcode":"bs8 2rp",
    "addr:street":"Whiteladies Rd",
    "iso:country":"GB",
    "sg:address":"126 Whiteladies Rd",
    "sg:city":"Bristol",
    "sg:classifiers":[
        {
            "category":"Shopping",
            "subcategory":"Pharmacy",
            "type":"Retail Goods"
        }
    ],
    "sg:phone":"+44 117 946 6035",
    "sg:postcode":"BS8 2RP",
    "sg:province":"City of Bristol",
    "sg:tags":[
        "medicine",
        "therapy"
    ],
    "wof:name":"Natural Therapy Centre The",
    "wof:placetype":"venue"
},
  "geometry": {"coordinates":[-2.6139640808,51.4687385559],"type":"Point"}
}