{
  "type": "Feature",
  "properties": {
    "addr:full":"Planter Gap Main Road, Lower Somersham Ipswich Suffolk IP8 4QD",
    "addr:postcode":"ip8 4qd",
    "addr:street":"Planter Gap Main Road Lower",
    "iso:country":"GB",
    "sg:address":"Planter Gap Main Road, Lower Somersham",
    "sg:city":"Ipswich",
    "sg:classifiers":[
        {
            "category":"Organizations",
            "subcategory":"Labor Organization",
            "type":"Services"
        },
        {
            "category":"Building & Trades",
            "subcategory":"Electrical",
            "type":"Services"
        }
    ],
    "sg:phone":"+44 1473 831661",
    "sg:postcode":"IP8 4QD",
    "sg:province":"Suffolk",
    "sg:tags":[
        "equipment",
        "purification",
        "system",
        "air"
    ],
    "wof:name":"Sable Design Ltd",
    "wof:placetype":"venue"
},
  "geometry": {"coordinates":[1.047845006,52.0961990356],"type":"Point"}
}