{
  "type": "Feature",
  "properties": {
    "addr:full":"91 High Street Deal Kent CT14 6ED",
    "addr:housenumber":"91",
    "addr:postcode":"ct14 6ed",
    "addr:street":"High Street Deal",
    "iso:country":"GB",
    "sg:address":"91 High Street",
    "sg:city":"Deal",
    "sg:classifiers":[
        {
            "category":"Bars & Pubs",
            "type":"Food & Drink"
        }
    ],
    "sg:phone":"+44 1304 375626",
    "sg:postcode":"CT14 6ED",
    "sg:province":"Kent",
    "sg:tags":[
        "pubs",
        "inn"
    ],
    "wof:name":"The Rose Hotel",
    "wof:placetype":"venue"
},
  "geometry": {"coordinates":[1.402469039,51.2255020142],"type":"Point"}
}