{
  "type": "Feature",
  "properties": {
    "addr:full":"5 Bilston Central Industrial Estate, Brook Terrace Bilston West Midlands WV14 0SX",
    "addr:housenumber":"5",
    "addr:postcode":"wv14 0sx",
    "addr:street":"Bilston Central Industrial Estate Brook Terrace",
    "iso:country":"GB",
    "sg:address":"5 Bilston Central Industrial Estate, Brook Terrace",
    "sg:city":"Bilston",
    "sg:classifiers":[
        {
            "category":"Wholesale",
            "subcategory":"Scrap",
            "type":"Manufacturing & Wholesale Goods"
        }
    ],
    "sg:postcode":"WV14 0SX",
    "sg:province":"West Midlands",
    "sg:tags":[
        "breaker",
        "dismantlers"
    ],
    "wof:name":"Fairdeal Car Spares",
    "wof:placetype":"venue"
},
  "geometry": {"coordinates":[-2.07449,52.566635],"type":"Point"}
}