{
  "type": "Feature",
  "properties": {
    "iso:country":"GB",
    "sg:address":"Old Odeon Cinema, Allendale Road",
    "sg:city":"Greenford",
    "sg:classifiers":[
        {
            "category":"Farming",
            "subcategory":"Nursery",
            "type":"Manufacturing & Wholesale Goods"
        }
    ],
    "sg:phone":"+44 20 8902 4999",
    "sg:postcode":"UB6 0RS",
    "sg:province":"Greater London",
    "sg:tags":[
        "creche"
    ],
    "wof:name":"Sudbury Town Nursery School Ltd.",
    "wof:placetype":"venue"
},
  "geometry": {"coordinates":[-0.3399,51.549271],"type":"Point"}
}