{
  "type": "Feature",
  "properties": {
    "addr:full":"154 Lancaster Road Barnet Hertfordshire EN4 8AL",
    "addr:housenumber":"154",
    "addr:postcode":"en4 8al",
    "addr:street":"Lancaster Road",
    "iso:country":"GB",
    "sg:address":"154 Lancaster Road",
    "sg:city":"Barnet",
    "sg:classifiers":[
        {
            "category":"Real Estate",
            "subcategory":"Architect",
            "type":"Services"
        }
    ],
    "sg:phone":"+44 20 8449 5864",
    "sg:postcode":"EN4 8AL",
    "sg:province":"Hertfordshire",
    "sg:tags":[
        "technologist",
        "architectural"
    ],
    "wof:name":"Stuart A Greenburg",
    "wof:placetype":"venue"
},
  "geometry": {"coordinates":[-0.1694509983,51.6435661316],"type":"Point"}
}