{
  "type": "Feature",
  "properties": {
    "addr:full":"1 Burlington Parade, Burlington Gardens, Portslade Brighton East Sussex BN41 2DJ",
    "addr:housenumber":"1",
    "addr:postcode":"bn41 2dj",
    "addr:street":"Burlington Parade;Gardens",
    "iso:country":"GB",
    "sg:address":"1 Burlington Parade, Burlington Gardens, Portslade",
    "sg:city":"Brighton",
    "sg:classifiers":[
        {
            "category":"Food & Beverages",
            "subcategory":"Meat & Fish",
            "type":"Retail Goods"
        }
    ],
    "sg:phone":"+44 1273 411953",
    "sg:postcode":"BN41 2DJ",
    "sg:province":"East Sussex",
    "sg:tags":[
        "butcher"
    ],
    "wof:name":"Mill Butchers",
    "wof:placetype":"venue"
},
  "geometry": {"coordinates":[-0.2107950002,50.8437194824],"type":"Point"}
}