{
  "type": "Feature",
  "properties": {
    "iso:country":"GB",
    "sg:address":"52 Ivar Gardens, Chineham South",
    "sg:city":"Basingstoke",
    "sg:classifiers":[
        {
            "category":"Health Services",
            "subcategory":"Health Practitioner",
            "type":"Services"
        },
        {
            "category":"Shopping",
            "subcategory":"Pharmacy",
            "type":"Retail Goods"
        }
    ],
    "sg:postcode":"RG24 8YD",
    "sg:province":"Hampshire",
    "sg:tags":[
        "medicine",
        "physiotherapist",
        "therapy"
    ],
    "wof:name":"Linda A Tagg",
    "wof:placetype":"venue"
},
  "geometry": {"coordinates":[-1.0545730591,51.2814102173],"type":"Point"}
}