{
  "type": "Feature",
  "properties": {
    "iso:country":"GB",
    "sg:address":"18 Bluebell Close",
    "sg:city":"Biggleswade",
    "sg:classifiers":[
        {
            "category":"Home & Garden",
            "subcategory":"Carpets & Floor Coverings",
            "type":"Retail Goods"
        }
    ],
    "sg:phone":"+44 1767 601113",
    "sg:postcode":"SG18 8SL",
    "sg:province":"Bedfordshire",
    "sg:tags":[
        "carpets",
        "rug",
        "matting"
    ],
    "wof:name":"Bluebell Carpets",
    "wof:placetype":"venue"
},
  "geometry": {"coordinates":[-0.2434130013,52.0784263611],"type":"Point"}
}