{
  "type": "Feature",
  "properties": {
    "iso:country":"GB",
    "sg:address":"5 Miltons Cottages, Petworth Road, Witley",
    "sg:city":"Godalming",
    "sg:classifiers":[
        {
            "category":"Manufacturing",
            "subcategory":"Wood Products",
            "type":"Manufacturing & Wholesale Goods"
        }
    ],
    "sg:phone":"+44 1428 685124",
    "sg:postcode":"GU8 5LT",
    "sg:province":"Surrey",
    "sg:tags":[
        "woodturning"
    ],
    "wof:name":"Yewcraft Ltd.",
    "wof:placetype":"venue"
},
  "geometry": {"coordinates":[-0.647235,51.151123],"type":"Point"}
}