{
  "type": "Feature",
  "properties": {
    "addr:full":"19 New Street Woodbridge Suffolk IP12 1DY",
    "addr:housenumber":"19",
    "addr:postcode":"ip12 1dy",
    "addr:street":"New Street",
    "iso:country":"GB",
    "sg:address":"19 New Street",
    "sg:city":"Woodbridge",
    "sg:classifiers":[
        {
            "category":"Community Center",
            "subcategory":"Youth",
            "type":"Public Place"
        }
    ],
    "sg:phone":"+44 1394 388538",
    "sg:postcode":"IP12 1DY",
    "sg:province":"Suffolk",
    "sg:tags":[
        "organisation",
        "centre"
    ],
    "wof:name":"The Rochford Trust",
    "wof:placetype":"venue"
},
  "geometry": {"coordinates":[1.318083,52.093933],"type":"Point"}
}