{
  "type": "Feature",
  "properties": {
    "iso:country":"GB",
    "sg:address":"3 Bridge Street",
    "sg:city":"Leatherhead",
    "sg:classifiers":[
        {
            "category":"Professional",
            "subcategory":"Employment Agencies",
            "type":"Services"
        }
    ],
    "sg:phone":"+44 1372 362200",
    "sg:postcode":"KT22 8BL",
    "sg:province":"Surrey",
    "sg:tags":[
        "consultant"
    ],
    "wof:name":"Selective Recruitment Ltd.",
    "wof:placetype":"venue"
},
  "geometry": {"coordinates":[-0.330173,51.294872],"type":"Point"}
}