{
  "type": "Feature",
  "properties": {
    "addr:full":"Bittern Road, Sowton Industrial Estate Exeter Devon EX2 7LW",
    "addr:postcode":"ex2 7lw",
    "addr:street":"Bittern Road;Industrial Estate",
    "iso:country":"GB",
    "sg:address":"Bittern Road, Sowton Industrial Estate",
    "sg:city":"Exeter",
    "sg:classifiers":[
        {
            "category":"Building & Trades",
            "subcategory":"Equipment Rental",
            "type":"Services"
        }
    ],
    "sg:phone":"+44 1392 272375",
    "sg:postcode":"EX2 7LW",
    "sg:province":"Devon",
    "sg:tags":[
        "plant",
        "machinery"
    ],
    "wof:name":"Selwood Hire",
    "wof:placetype":"venue"
},
  "geometry": {"coordinates":[-3.469539,50.722321],"type":"Point"}
}