{
  "type": "Feature",
  "properties": {
    "addr:full":"Trinity House Thames Street Weybridge Surrey KT13 8JG",
    "addr:postcode":"kt13 8jg",
    "addr:street":"Thames Street",
    "iso:country":"GB",
    "sg:address":"Trinity House Thames Street",
    "sg:city":"Weybridge",
    "sg:classifiers":[
        {
            "category":"Professional",
            "subcategory":"Computer Services",
            "type":"Services"
        }
    ],
    "sg:phone":"+44 1932 827227",
    "sg:postcode":"KT13 8JG",
    "sg:province":"Surrey",
    "sg:tags":[
        "system",
        "software"
    ],
    "wof:name":"Tridex Systems Ltd.",
    "wof:placetype":"venue"
},
  "geometry": {"coordinates":[-0.455269,51.378746],"type":"Point"}
}