{
  "type": "Feature",
  "properties": {
    "addr:full":"Harcourt Street, Walkden Manchester Greater Manchester M28 3GN",
    "addr:postcode":"m28 3gn",
    "addr:street":"Harcourt Street",
    "iso:country":"GB",
    "sg:address":"Harcourt Street, Walkden",
    "sg:city":"Manchester",
    "sg:classifiers":[
        {
            "category":"Autos & Motor Vehicles",
            "subcategory":"Automobile Sales",
            "type":"Retail Goods"
        }
    ],
    "sg:phone":"+44 1204 794545",
    "sg:postcode":"M28 3GN",
    "sg:province":"Greater Manchester",
    "sg:tags":[
        "car",
        "specialist",
        "sales",
        "classic"
    ],
    "wof:name":"Classicarco",
    "wof:placetype":"venue"
},
  "geometry": {"coordinates":[-2.399294,53.535721],"type":"Point"}
}