{
  "type": "Feature",
  "properties": {
    "iso:country":"GB",
    "sg:address":"10 Treewall Gardens",
    "sg:city":"Bromley",
    "sg:classifiers":[
        {
            "category":"Home & Garden",
            "subcategory":"Carpets & Floor Coverings",
            "type":"Retail Goods"
        }
    ],
    "sg:postcode":"BR1 5BT",
    "sg:province":"Kent",
    "sg:tags":[
        "carpets",
        "rug",
        "matting"
    ],
    "wof:name":"Alpha Flooring",
    "wof:placetype":"venue"
},
  "geometry": {"coordinates":[0.022312,51.425968],"type":"Point"}
}