{
  "type": "Feature",
  "properties": {
    "iso:country":"GB",
    "sg:address":"Rockingham Road",
    "sg:city":"Market Harborough",
    "sg:classifiers":[
        {
            "category":"Retail",
            "subcategory":"Auto Repair",
            "type":"Services"
        }
    ],
    "sg:phone":"+44 1858 464123",
    "sg:postcode":"LE16 7QE",
    "sg:province":"Leicestershire",
    "sg:tags":[
        "modification",
        "garage"
    ],
    "wof:name":"Aveling Motors",
    "wof:placetype":"venue"
},
  "geometry": {"coordinates":[-0.895203,52.486969],"type":"Point"}
}