{
  "type": "Feature",
  "properties": {
    "addr:full":"46 Sycamore Rd, Northway Tewkesbury Gloucestershire GL20 8PY",
    "addr:housenumber":"46",
    "addr:postcode":"gl20 8py",
    "addr:street":"Sycamore Rd Northway",
    "iso:country":"GB",
    "sg:address":"46 Sycamore Rd, Northway",
    "sg:city":"Tewkesbury",
    "sg:classifiers":[
        {
            "category":"Building & Trades",
            "subcategory":"Construction",
            "type":"Services"
        }
    ],
    "sg:postcode":"GL20 8PY",
    "sg:province":"Gloucestershire",
    "sg:tags":[
        "roofing"
    ],
    "wof:name":"Short,Michael,",
    "wof:placetype":"venue"
},
  "geometry": {"coordinates":[-2.114386,52.003372],"type":"Point"}
}