{
  "type": "Feature",
  "properties": {
    "addr:full":"Dte House, Hollins Mount Bury Lancashire BL9 8AT",
    "addr:postcode":"bl9 8at",
    "addr:street":"Mount",
    "iso:country":"GB",
    "sg:address":"Dte House, Hollins Mount",
    "sg:city":"Bury",
    "sg:classifiers":[
        {
            "category":"Sports & Exercise",
            "subcategory":"Gym",
            "type":"Entertainment"
        }
    ],
    "sg:postcode":"BL9 8AT",
    "sg:province":"Lancashire",
    "sg:tags":[
        "fitness",
        "health",
        "centre"
    ],
    "wof:name":"Unicorn Aerobic Fitness Centres (Ashton)",
    "wof:placetype":"venue"
},
  "geometry": {"coordinates":[-2.2766389847,53.5679397583],"type":"Point"}
}