{
  "type": "Feature",
  "properties": {
    "addr:full":", Preston Le Skerne Newton Aycliffe Durham DL5 6JH",
    "addr:postcode":"dl5 6jh",
    "addr:street":"Preston;Aycliffe",
    "iso:country":"GB",
    "sg:address":", Preston Le Skerne",
    "sg:city":"Newton Aycliffe",
    "sg:classifiers":[
        {
            "category":"Bars & Pubs",
            "type":"Food & Drink"
        }
    ],
    "sg:phone":"+44 1325 314873",
    "sg:postcode":"DL5 6JH",
    "sg:province":"Durham",
    "sg:tags":[
        "pubs",
        "inn"
    ],
    "wof:name":"The Blacksmiths Arms",
    "wof:placetype":"venue"
},
  "geometry": {"coordinates":[-1.563024044,54.5962715149],"type":"Point"}
}