{
  "type": "Feature",
  "properties": {
    "iso:country":"GB",
    "sg:address":"Unit4, Crumps Corner, Headcorn Road, Grafty Green",
    "sg:city":"Maidstone",
    "sg:classifiers":[
        {
            "category":"Home & Garden",
            "subcategory":"Garden Supply",
            "type":"Retail Goods"
        },
        {
            "category":"Shopping",
            "subcategory":"Florist",
            "type":"Retail Goods"
        }
    ],
    "sg:phone":"+44 1622 858800",
    "sg:postcode":"ME17 2AT",
    "sg:province":"Kent",
    "sg:tags":[
        "nursery",
        "centre"
    ],
    "wof:name":"Grafty Garden Centre",
    "wof:placetype":"venue"
},
  "geometry": {"coordinates":[0.6694899797,51.19947052],"type":"Point"}
}