{
  "type": "Feature",
  "properties": {
    "iso:country":"GB",
    "sg:address":"28 Bank Street, Cheadle",
    "sg:city":"Stoke-on-trent",
    "sg:classifiers":[
        {
            "category":"Shopping",
            "subcategory":"Used Merchandise",
            "type":"Retail Goods"
        }
    ],
    "sg:postcode":"ST10 1NT",
    "sg:province":"Staffordshire",
    "sg:tags":[
        "shop",
        "second-hand"
    ],
    "wof:name":"Scoops Houseware Wholesalers",
    "wof:placetype":"venue"
},
  "geometry": {"coordinates":[-1.991213,52.985744],"type":"Point"}
}