{
  "type": "Feature",
  "properties": {
    "iso:country":"GB",
    "sg:address":"Quickbury Farm, Hatfield Heath Road",
    "sg:city":"Sawbridgeworth",
    "sg:classifiers":[
        {
            "category":"Freight",
            "type":"Transportation"
        }
    ],
    "sg:phone":"+44 1279 600637",
    "sg:postcode":"CM21 9HY",
    "sg:province":"Essex",
    "sg:tags":[
        "haulage",
        "road"
    ],
    "wof:name":"Chapmans Transport",
    "wof:placetype":"venue"
},
  "geometry": {"coordinates":[0.147223,51.812527],"type":"Point"}
}