{
  "type": "Feature",
  "properties": {
    "iso:country":"GB",
    "sg:address":"New Piggery, Sutterby Road, Aswardby",
    "sg:city":"Spilsby",
    "sg:classifiers":[
        {
            "category":"Farming",
            "subcategory":"Livestock Farm",
            "type":"Manufacturing & Wholesale Goods"
        }
    ],
    "sg:phone":"+44 1790 752556",
    "sg:postcode":"PE23 4JN",
    "sg:province":"Lincolnshire",
    "sg:tags":[
        "others"
    ],
    "wof:name":"Hawkes Ltd.",
    "wof:placetype":"venue"
},
  "geometry": {"coordinates":[0.061649,53.212589],"type":"Point"}
}