{
  "type": "Feature",
  "properties": {
    "addr:full":"21 Nithsdale Street Glasgow Glasgow City G41 2PZ",
    "addr:housenumber":"21",
    "addr:postcode":"g41 2pz",
    "addr:street":"Nithsdale Street",
    "iso:country":"GB",
    "sg:address":"21 Nithsdale Street",
    "sg:city":"Glasgow",
    "sg:classifiers":[
        {
            "category":"Retail",
            "subcategory":"Funeral Services",
            "type":"Services"
        }
    ],
    "sg:postcode":"G41 2PZ",
    "sg:province":"Glasgow City",
    "wof:name":"The Glossop Carriage Co. Ltd.",
    "wof:placetype":"venue"
},
  "geometry": {"coordinates":[-4.271519,55.83672],"type":"Point"}
}