{
  "type": "Feature",
  "properties": {
    "iso:country":"GB",
    "sg:address":"Rhosllan",
    "sg:city":"Brynteg",
    "sg:classifiers":[
        {
            "category":"Building & Trades",
            "subcategory":"Equipment Rental",
            "type":"Services"
        }
    ],
    "sg:phone":"+44 1248 853599",
    "sg:postcode":"LL78 8JS",
    "sg:province":"Isle of Anglesey",
    "sg:tags":[
        "plant",
        "machinery"
    ],
    "wof:name":"Alan Hughes",
    "wof:placetype":"venue"
},
  "geometry": {"coordinates":[-4.2594590187,53.319606781],"type":"Point"}
}