{
  "type": "Feature",
  "properties": {
    "addr:full":"Ye Olde Farmhouse, Chinham Farm Faringdon Oxfordshire SN7 8EZ",
    "addr:postcode":"sn7 8ez",
    "addr:street":"Chinham;Faringdon",
    "iso:country":"GB",
    "sg:address":"Ye Olde Farmhouse, Chinham Farm",
    "sg:city":"Faringdon",
    "sg:classifiers":[
        {
            "category":"Banks & Credit Unions",
            "subcategory":"Investment Brokerage",
            "type":"Services"
        }
    ],
    "sg:postcode":"SN7 8EZ",
    "sg:province":"Oxfordshire",
    "sg:tags":[
        "contractor"
    ],
    "wof:name":"K J B Agricrop Services",
    "wof:placetype":"venue"
},
  "geometry": {"coordinates":[-1.5866539478,51.6561698914],"type":"Point"}
}