{
  "type": "Feature",
  "properties": {
    "addr:full":"White House Farm, Higher Lane, Rainford St Helens Lancashire WA11 8NL",
    "addr:postcode":"wa11 8nl",
    "addr:street":"Higher Lane",
    "iso:country":"GB",
    "sg:address":"White House Farm, Higher Lane, Rainford",
    "sg:city":"St Helens",
    "sg:classifiers":[
        {
            "category":"Farming",
            "subcategory":"Farm",
            "type":"Manufacturing & Wholesale Goods"
        }
    ],
    "sg:postcode":"WA11 8NL",
    "sg:province":"Lancashire",
    "sg:tags":[
        "mixed",
        "crop"
    ],
    "wof:name":"J R Rosbotham & Son",
    "wof:placetype":"venue"
},
  "geometry": {"coordinates":[-2.7889239788,53.5027694702],"type":"Point"}
}