{
  "type": "Feature",
  "properties": {
    "addr:full":"Unit 1 Lawrence Road, Off Pound Lane Basildon Essex SS13 2NA",
    "addr:housenumber":"unit 1",
    "addr:postcode":"ss13 2na",
    "addr:street":"Lawrence Road Off Pound Lane",
    "iso:country":"GB",
    "sg:address":"Unit 1 Lawrence Road, Off Pound Lane",
    "sg:city":"Basildon",
    "sg:classifiers":[
        {
            "category":"Retail",
            "subcategory":"Auto Repair",
            "type":"Services"
        }
    ],
    "sg:phone":"+44 1268 724633",
    "sg:postcode":"SS13 2NA",
    "sg:province":"Essex",
    "sg:tags":[
        "modification",
        "garage"
    ],
    "wof:name":"Geds Vehicle Repairs",
    "wof:placetype":"venue"
},
  "geometry": {"coordinates":[0.534225,51.579456],"type":"Point"}
}