{
  "type": "Feature",
  "properties": {
    "iso:country":"GB",
    "sg:address":"The Bdwy, Fulwood",
    "sg:city":"Preston",
    "sg:classifiers":[
        {
            "category":"Organizations",
            "subcategory":"Membership Organization",
            "type":"Services"
        }
    ],
    "sg:phone":"+44 1772 716040",
    "sg:postcode":"PR2 9TH",
    "sg:province":"Lancashire",
    "sg:tags":[
        "club",
        "social"
    ],
    "wof:name":"St John Baptist Church Club",
    "wof:placetype":"venue"
},
  "geometry": {"coordinates":[-2.713179,53.790054],"type":"Point"}
}