{
  "type": "Feature",
  "properties": {
    "iso:country":"GB",
    "sg:address":"31 Tarrant Drive",
    "sg:city":"Harpenden",
    "sg:classifiers":[
        {
            "category":"Professional",
            "subcategory":"Art Services",
            "type":"Services"
        }
    ],
    "sg:phone":"+44 1582 766350",
    "sg:postcode":"AL5 1RP",
    "sg:province":"Hertfordshire",
    "sg:tags":[
        "photographer"
    ],
    "wof:name":"Photo Scene",
    "wof:placetype":"venue"
},
  "geometry": {"coordinates":[-0.340202,51.804585],"type":"Point"}
}