{
  "type": "Feature",
  "properties": {
    "addr:full":"Box Office, Portugal Street London Greater London WC2A 2HT",
    "addr:postcode":"wc2a 2ht",
    "addr:street":"Portugal Street",
    "iso:country":"GB",
    "sg:address":"Box Office, Portugal Street",
    "sg:city":"London",
    "sg:classifiers":[
        {
            "category":"Arts & Performance",
            "subcategory":"Theater",
            "type":"Entertainment"
        }
    ],
    "sg:phone":"+44 20 7863 8222",
    "sg:postcode":"WC2A 2HT",
    "sg:province":"Greater London",
    "sg:tags":[
        "hall",
        "theatre",
        "concert"
    ],
    "wof:name":"Peacock Theatre",
    "wof:placetype":"venue"
},
  "geometry": {"coordinates":[-0.118,51.514568],"type":"Point"}
}