{
  "type": "Feature",
  "properties": {
    "iso:country":"GB",
    "sg:address":"Innox Lane, Upper Swainswick",
    "sg:city":"Bath",
    "sg:classifiers":[
        {
            "category":"Education",
            "subcategory":"School",
            "type":"Public Place"
        }
    ],
    "sg:phone":"+44 1225 859279",
    "sg:postcode":"BA1 8DB",
    "sg:province":"Bath and North East Somerset",
    "sg:tags":[
        "local",
        "authority"
    ],
    "wof:name":"Swainswick C Of E Primary School",
    "wof:placetype":"venue"
},
  "geometry": {"coordinates":[-2.3476779461,51.4112167358],"type":"Point"}
}