{
  "type": "Feature",
  "properties": {
    "addr:full":"Old Road, Ashton In Makerfield Wigan Lancashire WN4 9TP",
    "addr:postcode":"wn4 9tp",
    "addr:street":"Old Road",
    "iso:country":"GB",
    "sg:address":"Old Road, Ashton In Makerfield",
    "sg:city":"Wigan",
    "sg:classifiers":[
        {
            "category":"Education",
            "subcategory":"School",
            "type":"Public Place"
        }
    ],
    "sg:phone":"+44 1942 720711",
    "sg:postcode":"WN4 9TP",
    "sg:province":"Lancashire",
    "sg:tags":[
        "local",
        "authority"
    ],
    "wof:name":"Cansfield High School",
    "wof:placetype":"venue"
},
  "geometry": {"coordinates":[-2.646641,53.493626],"type":"Point"}
}