{
  "type": "Feature",
  "properties": {
    "addr:full":"29 Cross Road Croydon Surrey CR0 6TE",
    "addr:housenumber":"29",
    "addr:postcode":"cr0 6te",
    "addr:street":"Cross Road",
    "iso:country":"GB",
    "sg:address":"29 Cross Road",
    "sg:city":"Croydon",
    "sg:classifiers":[
        {
            "category":"Wholesale",
            "subcategory":"Scrap",
            "type":"Manufacturing & Wholesale Goods"
        },
        {
            "category":"Health Services",
            "subcategory":"Nursing And Care Facility",
            "type":"Services"
        }
    ],
    "sg:phone":"+44 20 8760 9992",
    "sg:postcode":"CR0 6TE",
    "sg:province":"Surrey",
    "sg:tags":[
        "aid",
        "waste",
        "metal",
        "first",
        "supply"
    ],
    "wof:name":"A V Surgery Supplies",
    "wof:placetype":"venue"
},
  "geometry": {"coordinates":[-0.090645,51.379208],"type":"Point"}
}