{
  "type": "Feature",
  "properties": {
    "addr:full":"98 High Street Eastleigh Hampshire SO50 5LR",
    "addr:housenumber":"98",
    "addr:postcode":"so50 5lr",
    "addr:street":"High Street",
    "iso:country":"GB",
    "sg:address":"98 High Street",
    "sg:city":"Eastleigh",
    "sg:classifiers":[
        {
            "category":"Home & Garden",
            "subcategory":"Household Appliances",
            "type":"Retail Goods"
        }
    ],
    "sg:phone":"+44 23 8061 5848",
    "sg:postcode":"SO50 5LR",
    "sg:province":"Hampshire",
    "sg:tags":[
        "gas"
    ],
    "wof:name":"G & S Domestic Gas Services",
    "wof:placetype":"venue"
},
  "geometry": {"coordinates":[-1.353825,50.965733],"type":"Point"}
}