{
  "type": "Feature",
  "properties": {
    "addr:full":"Unit 3 Leeds West Yorkshire LS9 6HH",
    "addr:housenumber":"unit 3",
    "addr:postcode":"ls9 6hh",
    "addr:street":"Leeds West",
    "iso:country":"GB",
    "sg:address":"Unit 3",
    "sg:city":"Leeds",
    "sg:classifiers":[
        {
            "category":"Manufacturing",
            "subcategory":"Building Materials",
            "type":"Manufacturing & Wholesale Goods"
        }
    ],
    "sg:phone":"+44 113 249 5906",
    "sg:postcode":"LS9 6HH",
    "sg:province":"West Yorkshire",
    "sg:tags":[
        "shutter",
        "supp",
        "door"
    ],
    "wof:name":"Grange Security Products",
    "wof:placetype":"venue"
},
  "geometry": {"coordinates":[-1.5064300299,53.8051109314],"type":"Point"}
}